{
  "type": "Feature",
  "properties": {
    "addr:full":"200 Garrison Rd Fort Erie ON L2A 5S6",
    "addr:housenumber":"200",
    "addr:postcode":"l2a 5s6",
    "addr:street":"Garrison Rd",
    "iso:country":"CA",
    "sg:address":"200 Garrison Rd",
    "sg:city":"Fort Erie",
    "sg:classifiers":[
        {
            "category":"Banks & Credit Unions",
            "subcategory":"Bank",
            "type":"Services"
        }
    ],
    "sg:phone":"+1 905 871 5824",
    "sg:postcode":"L2A 5S6",
    "sg:province":"ON",
    "wof:name":"Scotiabank",
    "wof:placetype":"venue"
},
  "geometry": {"coordinates":[-78.92087554930001,42.9055023193],"type":"Point"}
}