{
  "type": "Feature",
  "properties": {
    "addr:full":"501 Rue Du Sud Cowansville QC J2K 2X9",
    "addr:housenumber":"501",
    "addr:postcode":"j2k 2x9",
    "addr:street":"Rue Du Sud",
    "iso:country":"CA",
    "sg:address":"501 Rue Du Sud",
    "sg:city":"Cowansville",
    "sg:classifiers":[
        {
            "category":"Health Services",
            "subcategory":"Optometrist",
            "type":"Services"
        }
    ],
    "sg:phone":"+1 450 263 3341",
    "sg:postcode":"J2K 2X9",
    "sg:province":"QC",
    "wof:name":"Iris Clinique D'Optometrie",
    "wof:placetype":"venue"
},
  "geometry": {"coordinates":[-72.74678,45.203701],"type":"Point"}
}