{
  "type": "Feature",
  "properties": {
    "addr:full":"98 Newcombe Cres Winnipeg MB R2J 3T6",
    "addr:housenumber":"98",
    "addr:postcode":"r2j 3t6",
    "addr:street":"Newcombe Cres",
    "iso:country":"CA",
    "sg:address":"98 Newcombe Cres",
    "sg:city":"Winnipeg",
    "sg:classifiers":[
        {
            "category":"Professional",
            "subcategory":"Engineering",
            "type":"Services"
        }
    ],
    "sg:phone":"+1 204 255 3932",
    "sg:postcode":"R2J 3T6",
    "sg:province":"MB",
    "sg:tags":[
        "environmental",
        "ecological",
        "engineer"
    ],
    "wof:name":"Mid Canada Environmental Svc",
    "wof:placetype":"venue"
},
  "geometry": {"coordinates":[-97.05835,49.848278],"type":"Point"}
}