{
  "type": "Feature",
  "properties": {
    "addr:full":"500 Rue Des Erables Cap-DE-LA-Madeleine QC G8T 9S4",
    "addr:housenumber":"500",
    "addr:postcode":"g8t 9s4",
    "addr:street":"Rue Des Erables",
    "iso:country":"CA",
    "sg:address":"500 Rue Des Erables",
    "sg:city":"Cap-DE-LA-Madeleine",
    "sg:classifiers":[
        {
            "category":"Government",
            "subcategory":"Office",
            "type":"Public Place"
        }
    ],
    "sg:phone":"+1 819 371 6031",
    "sg:postcode":"G8T 9S4",
    "sg:province":"QC",
    "wof:name":"Quebec Centre Local D'Emploi",
    "wof:placetype":"venue"
},
  "geometry": {"coordinates":[-72.5227050781,46.3788642883],"type":"Point"}
}