{
  "type": "Feature",
  "properties": {
    "addr:full":"91 West Ave N Hamilton ON L8L 5C1",
    "addr:housenumber":"91",
    "addr:postcode":"l8l 5c1",
    "addr:street":"West Ave N",
    "iso:country":"CA",
    "sg:address":"91 West Ave N",
    "sg:city":"Hamilton",
    "sg:classifiers":[
        {
            "category":"Professional",
            "subcategory":"Management & Consulting",
            "type":"Services"
        }
    ],
    "sg:phone":"+1 905 546 1700",
    "sg:postcode":"L8L 5C1",
    "sg:province":"ON",
    "sg:tags":[
        "machine",
        "folding"
    ],
    "wof:name":"Hartro Copy Systems",
    "wof:placetype":"venue"
},
  "geometry": {"coordinates":[-79.85715500000001,43.255924],"type":"Point"}
}