{
  "type": "Feature",
  "properties": {
    "addr:full":"6715 97 St NW Edmonton AB T6E 3J9",
    "addr:housenumber":"6715",
    "addr:postcode":"t6e 3j9",
    "addr:street":"97 St Nw",
    "iso:country":"CA",
    "sg:address":"6715 97 St NW",
    "sg:city":"Edmonton",
    "sg:classifiers":[
        {
            "category":"Education",
            "subcategory":"School",
            "type":"Public Place"
        }
    ],
    "sg:phone":"+1 780 433 7583",
    "sg:postcode":"T6E 3J9",
    "sg:province":"AB",
    "wof:name":"Hazeldean Elementary School",
    "wof:placetype":"venue"
},
  "geometry": {"coordinates":[-113.479248,53.50412],"type":"Point"}
}