{
  "type": "Feature",
  "properties": {
    "addr:full":"8870 Rue Verville Montreal QC H2N 1X9",
    "addr:housenumber":"8870",
    "addr:postcode":"h2n 1x9",
    "addr:street":"Rue Verville",
    "iso:country":"CA",
    "sg:address":"8870 Rue Verville",
    "sg:city":"Montreal",
    "sg:classifiers":[
        {
            "category":"Manufacturing",
            "subcategory":"Food",
            "type":"Manufacturing & Wholesale Goods"
        }
    ],
    "sg:phone":"+1 514 381 7181",
    "sg:postcode":"H2N 1X9",
    "sg:province":"QC",
    "sg:tags":[
        "grocer",
        "cookie",
        "bakery"
    ],
    "wof:name":"Boulangerie Du Vieux Pays",
    "wof:placetype":"venue"
},
  "geometry": {"coordinates":[-73.6475524902,45.5368118286],"type":"Point"}
}