{
  "type": "Feature",
  "properties": {
    "addr:full":"4322 40 St Delta BC V4K 3N2",
    "addr:housenumber":"4322",
    "addr:postcode":"v4k 3n2",
    "addr:street":"40 St",
    "iso:country":"CA",
    "sg:address":"4322 40 St",
    "sg:city":"Delta",
    "sg:classifiers":[
        {
            "category":"Shopping",
            "subcategory":"Bicycles & Sporting Goods",
            "type":"Retail Goods"
        }
    ],
    "sg:phone":"+1 604 946 7886",
    "sg:postcode":"V4K 3N2",
    "sg:province":"BC",
    "sg:tags":[
        "netting"
    ],
    "wof:name":"Netex Canada Netting",
    "wof:placetype":"venue"
},
  "geometry": {"coordinates":[-123.112983704,49.0813713074],"type":"Point"}
}