{
  "type": "Feature",
  "properties": {
    "addr:full":"The Pas MB R9A 1S5",
    "addr:postcode":"r9a 1s5",
    "iso:country":"CA",
    "sg:city":"The Pas",
    "sg:classifiers":[
        {
            "category":"Real Estate",
            "subcategory":"Real Estate Agent",
            "type":"Services"
        }
    ],
    "sg:phone":"+1 204 623 6100",
    "sg:postcode":"R9A 1S5",
    "sg:province":"MB",
    "wof:name":"Pineview Realty Ltd",
    "wof:placetype":"venue"
},
  "geometry": {"coordinates":[-101.25035099999999,53.813435],"type":"Point"}
}