{
  "type": "Feature",
  "properties": {
    "addr:full":"5469 Ch Queen-Mary Montreal QC H3X 1V4",
    "addr:housenumber":"5469",
    "addr:postcode":"h3x 1v4",
    "addr:street":"Ch Queen-Mary",
    "iso:country":"CA",
    "sg:address":"5469 Ch Queen-Mary",
    "sg:city":"Montreal",
    "sg:classifiers":[
        {
            "category":"Banks & Credit Unions",
            "subcategory":"Bank",
            "type":"Services"
        }
    ],
    "sg:phone":"+1 514 394 5555",
    "sg:postcode":"H3X 1V4",
    "sg:province":"QC",
    "wof:name":"Banque National Du Canada",
    "wof:placetype":"venue"
},
  "geometry": {"coordinates":[-73.63102722169999,45.4818344116],"type":"Point"}
}