{
  "type": "Feature",
  "properties": {
    "addr:full":"6901 20A St SE Calgary AB T2C 0R5",
    "addr:housenumber":"6901",
    "addr:postcode":"t2c 0r5",
    "addr:street":"20A St Se",
    "iso:country":"CA",
    "sg:address":"6901 20A St SE",
    "sg:city":"Calgary",
    "sg:classifiers":[
        {
            "category":"Organizations",
            "subcategory":"Professional Association",
            "type":"Services"
        }
    ],
    "sg:phone":"+1 403 720 6761",
    "sg:postcode":"T2C 0R5",
    "sg:province":"AB",
    "wof:name":"Moca-Linck Family Resource Ctr",
    "wof:placetype":"venue"
},
  "geometry": {"coordinates":[-114.010155,50.991882],"type":"Point"}
}