{
  "type": "Feature",
  "properties": {
    "addr:full":"106 Foster Cres Brampton ON L6V 3M8",
    "addr:housenumber":"106",
    "addr:postcode":"l6v 3m8",
    "addr:street":"Foster Cres",
    "iso:country":"CA",
    "sg:address":"106 Foster Cres",
    "sg:city":"Brampton",
    "sg:classifiers":[
        {
            "category":"Professional",
            "subcategory":"Business Services",
            "type":"Services"
        }
    ],
    "sg:phone":"+1 905 454 8112",
    "sg:postcode":"L6V 3M8",
    "sg:province":"ON",
    "sg:tags":[
        "drafting"
    ],
    "wof:name":"Aerostar Drafting Svc",
    "wof:placetype":"venue"
},
  "geometry": {"coordinates":[-79.77505499999999,43.70993],"type":"Point"}
}