{
  "type": "Feature",
  "properties": {
    "addr:full":"10805 120 St Surrey BC V3V 4G5",
    "addr:housenumber":"10805",
    "addr:postcode":"v3v 4g5",
    "addr:street":"120 St",
    "iso:country":"CA",
    "sg:address":"10805 120 St",
    "sg:city":"Surrey",
    "sg:classifiers":[
        {
            "category":"Retail",
            "subcategory":"Auto Repair",
            "type":"Services"
        }
    ],
    "sg:phone":"+1 604 580 2876",
    "sg:postcode":"V3V 4G5",
    "sg:province":"BC",
    "sg:tags":[
        "truck"
    ],
    "wof:name":"Scott Spring Ltd",
    "wof:placetype":"venue"
},
  "geometry": {"coordinates":[-122.888756,49.193909],"type":"Point"}
}