{
  "type": "Feature",
  "properties": {
    "addr:full":"Rte 101 E South Porcupine ON P0N 1H0",
    "addr:housenumber":"e",
    "addr:postcode":"p0n 1h0",
    "addr:street":"Rte 101;South Porcupine",
    "iso:country":"CA",
    "sg:address":"Rte 101 E",
    "sg:city":"South Porcupine",
    "sg:classifiers":[
        {
            "category":"Government",
            "subcategory":"Office",
            "type":"Public Place"
        }
    ],
    "sg:phone":"+1 705 235 1615",
    "sg:postcode":"P0N 1H0",
    "sg:province":"ON",
    "wof:name":"Ontario Geologue Resident",
    "wof:placetype":"venue"
},
  "geometry": {"coordinates":[-81.20946502690001,48.4851455688],"type":"Point"}
}