{
  "type": "Feature",
  "properties": {
    "addr:full":"RR 1 STN Galt Cambridge ON N1R 5S2",
    "addr:postcode":"n1r 5s2",
    "addr:street":"Rr 1 Stn Galt",
    "iso:country":"CA",
    "sg:address":"RR 1 STN Galt",
    "sg:city":"Cambridge",
    "sg:classifiers":[
        {
            "category":"Manufacturing",
            "subcategory":"Tools & Machinery",
            "type":"Manufacturing & Wholesale Goods"
        }
    ],
    "sg:phone":"+1 519 623 1440",
    "sg:postcode":"N1R 5S2",
    "sg:province":"ON",
    "sg:tags":[
        "conditioning",
        "air",
        "system",
        "contractor"
    ],
    "wof:name":"R M Beer Heating & Air Cond",
    "wof:placetype":"venue"
},
  "geometry": {"coordinates":[-80.3153305054,43.3614082336],"type":"Point"}
}