{
  "type": "Feature",
  "properties": {
    "addr:full":"378 Bulyea Rd NW Edmonton AB T6R 2B3",
    "addr:housenumber":"378",
    "addr:postcode":"t6r 2b3",
    "addr:street":"Bulyea Rd Nw",
    "iso:country":"CA",
    "sg:address":"378 Bulyea Rd NW",
    "sg:city":"Edmonton",
    "sg:classifiers":[
        {
            "category":"Restaurant",
            "type":"Food & Drink"
        }
    ],
    "sg:phone":"+1 780 431 8431",
    "sg:postcode":"T6R 2B3",
    "sg:province":"AB",
    "wof:name":"Boston Pizza",
    "wof:placetype":"venue"
},
  "geometry": {"coordinates":[-113.57311199999999,53.475643],"type":"Point"}
}