{
  "type": "Feature",
  "properties": {
    "addr:full":"32503 Route 11 Glencoe NB E3N 5A6",
    "addr:housenumber":"32503",
    "addr:postcode":"e3n 5a6",
    "addr:street":"Route 11",
    "iso:country":"CA",
    "sg:address":"32503 Route 11",
    "sg:city":"Glencoe",
    "sg:classifiers":[
        {
            "category":"Retail",
            "subcategory":"Animal Services",
            "type":"Services"
        }
    ],
    "sg:phone":"+1 506 759 9393",
    "sg:postcode":"E3N 5A6",
    "sg:province":"NB",
    "sg:tags":[
        "pet",
        "grooming",
        "washing"
    ],
    "wof:name":"Sue's K-9 Kastle & Brdg Knls",
    "wof:placetype":"venue"
},
  "geometry": {"coordinates":[-66.8041763306,47.9525756836],"type":"Point"}
}