{
  "type": "Feature",
  "properties": {
    "addr:full":"100 Elora St N Clifford ON N0G 1M0",
    "addr:housenumber":"100",
    "addr:postcode":"n0g 1m0",
    "addr:street":"Elora St N",
    "iso:country":"CA",
    "sg:address":"100 Elora St N",
    "sg:city":"Clifford",
    "sg:classifiers":[
        {
            "category":"Professional",
            "subcategory":"Business Services",
            "type":"Services"
        }
    ],
    "sg:phone":"+1 519 327 9333",
    "sg:postcode":"N0G 1M0",
    "sg:province":"ON",
    "sg:tags":[
        "information",
        "referral"
    ],
    "wof:name":"Minto Chamber of Commerce",
    "wof:placetype":"venue"
},
  "geometry": {"coordinates":[-80.9845657349,43.9725341797],"type":"Point"}
}