{
  "type": "Feature",
  "properties": {
    "iso:country":"CA",
    "sg:address":"263 Waverley Rd",
    "sg:city":"Dartmouth",
    "sg:classifiers":[
        {
            "category":"Organizations",
            "subcategory":"Religious Organization",
            "type":"Services"
        }
    ],
    "sg:phone":"+1 902 435 3644",
    "sg:postcode":"B2X 2C8",
    "sg:province":"NS",
    "sg:tags":[
        "church"
    ],
    "wof:name":"Port Wallis United Church",
    "wof:placetype":"venue"
},
  "geometry": {"coordinates":[-63.5479202271,44.699886322],"type":"Point"}
}