{
  "type": "Feature",
  "properties": {
    "addr:full":"Montreal QC H2J 2K9",
    "addr:postcode":"h2j 2k9",
    "iso:country":"CA",
    "sg:city":"Montreal",
    "sg:classifiers":[
        {
            "category":"Restaurant",
            "type":"Food & Drink"
        }
    ],
    "sg:phone":"+1 514 848 1119",
    "sg:postcode":"H2J 2K9",
    "sg:province":"QC",
    "sg:tags":[
        "shop",
        "coffee"
    ],
    "wof:name":"Ceramic Cafe-Studio Inc",
    "wof:placetype":"venue"
},
  "geometry": {"coordinates":[-73.57815600000001,45.521999],"type":"Point"}
}