{
  "type": "Feature",
  "properties": {
    "iso:country":"CA",
    "sg:address":"903 Sherwood Ave",
    "sg:city":"Coquitlam",
    "sg:classifiers":[
        {
            "category":"Manufacturing",
            "subcategory":"Tools & Machinery",
            "type":"Manufacturing & Wholesale Goods"
        }
    ],
    "sg:phone":"+1 604 522 7828",
    "sg:postcode":"V3K 1A7",
    "sg:province":"BC",
    "sg:tags":[
        "machine",
        "shop"
    ],
    "wof:name":"Alltool Grinding & Machining",
    "wof:placetype":"venue"
},
  "geometry": {"coordinates":[-122.87260437,49.2359161377],"type":"Point"}
}