{
  "type": "Feature",
  "properties": {
    "addr:full":"965 Rue Commerciale Saint-Jean-Chrysostome QC G6Z 3G7",
    "addr:housenumber":"965",
    "addr:postcode":"g6z 3g7",
    "addr:street":"Rue Commerciale Saint-Jean-Chrysostome",
    "iso:country":"CA",
    "sg:address":"965 Rue Commerciale",
    "sg:city":"Saint-Jean-Chrysostome",
    "sg:classifiers":[
        {
            "category":"Shopping",
            "subcategory":"Crafts & Fabrics",
            "type":"Retail Goods"
        }
    ],
    "sg:phone":"+1 418 839 9621",
    "sg:postcode":"G6Z 3G7",
    "sg:province":"QC",
    "sg:tags":[
        "shop"
    ],
    "wof:name":"Tissus Drb Inc",
    "wof:placetype":"venue"
},
  "geometry": {"coordinates":[-71.19882200000001,46.720985],"type":"Point"}
}