{
  "type": "Feature",
  "properties": {
    "addr:full":"9721 118 Ave NW Edmonton AB T5G 0P4",
    "addr:housenumber":"9721",
    "addr:postcode":"t5g 0p4",
    "addr:street":"118 Ave Nw",
    "iso:country":"CA",
    "sg:address":"9721 118 Ave NW",
    "sg:city":"Edmonton",
    "sg:classifiers":[
        {
            "category":"Retail",
            "subcategory":"Laundry & Dry Cleaning",
            "type":"Services"
        }
    ],
    "sg:phone":"+1 780 477 9714",
    "sg:postcode":"T5G 0P4",
    "sg:province":"AB",
    "sg:tags":[
        "cleaners"
    ],
    "wof:name":"K & W Coin Laundry",
    "wof:placetype":"venue"
},
  "geometry": {"coordinates":[-113.492515564,53.5701217651],"type":"Point"}
}