{
  "type": "Feature",
  "properties": {
    "addr:full":"712 Wilson Rd S # 9A Oshawa ON L1H 8R3",
    "addr:housenumber":"712",
    "addr:postcode":"l1h 8r3",
    "addr:street":"Wilson Rd S # 9A",
    "iso:country":"CA",
    "sg:address":"712 Wilson Rd S # 9A",
    "sg:city":"Oshawa",
    "sg:classifiers":[
        {
            "category":"Building & Trades",
            "subcategory":"Electrical",
            "type":"Services"
        }
    ],
    "sg:phone":"+1 905 725 9594",
    "sg:postcode":"L1H 8R3",
    "sg:province":"ON",
    "sg:tags":[
        "equipment",
        "telephone",
        "supply"
    ],
    "wof:name":"Telecomp Systems Inc",
    "wof:placetype":"venue"
},
  "geometry": {"coordinates":[-78.83543396,43.8826408386],"type":"Point"}
}