{
  "type": "Feature",
  "properties": {
    "addr:full":"206 Concession St Kingston ON K7K 2B5",
    "addr:housenumber":"206",
    "addr:postcode":"k7k 2b5",
    "addr:street":"Concession St",
    "iso:country":"CA",
    "sg:address":"206 Concession St",
    "sg:city":"Kingston",
    "sg:classifiers":[
        {
            "category":"Manufacturing",
            "subcategory":"Printing",
            "type":"Manufacturing & Wholesale Goods"
        }
    ],
    "sg:phone":"+1 613 548 4546",
    "sg:postcode":"K7K 2B5",
    "sg:province":"ON",
    "sg:tags":[
        "printer"
    ],
    "wof:name":"Digigraphics Inc",
    "wof:placetype":"venue"
},
  "geometry": {"coordinates":[-76.504677,44.241165],"type":"Point"}
}