{
  "type": "Feature",
  "properties": {
    "iso:country":"CA",
    "sg:city":"Cambridge",
    "sg:classifiers":[
        {
            "category":"Social Services",
            "type":"Services"
        }
    ],
    "sg:phone":"+1 519 740 8565",
    "sg:postcode":"N1R 2X6",
    "sg:province":"ON",
    "sg:tags":[
        "organization",
        "welfare"
    ],
    "wof:name":"Champlain Community Ctr",
    "wof:placetype":"venue"
},
  "geometry": {"coordinates":[-80.30187225340001,43.3457946777],"type":"Point"}
}