{
  "type": "Feature",
  "properties": {
    "addr:full":"RR 1 STN Main Truro NS B2N 5A9",
    "addr:postcode":"b2n 5a9",
    "addr:street":"Rr 1 Stn Main",
    "iso:country":"CA",
    "sg:address":"RR 1 STN Main",
    "sg:city":"Truro",
    "sg:classifiers":[
        {
            "category":"Organizations",
            "subcategory":"Religious Organization",
            "type":"Services"
        }
    ],
    "sg:phone":"+1 902 895 2914",
    "sg:postcode":"B2N 5A9",
    "sg:province":"NS",
    "sg:tags":[
        "church"
    ],
    "wof:name":"Clifton Pastoral Charge",
    "wof:placetype":"venue"
},
  "geometry": {"coordinates":[-63.2890396118,45.3660202026],"type":"Point"}
}