{
  "type": "Feature",
  "properties": {
    "iso:country":"CA",
    "sg:address":"4 Clinic Dr",
    "sg:city":"Deer Lake",
    "sg:classifiers":[
        {
            "category":"Health Services",
            "subcategory":"Doctor",
            "type":"Services"
        }
    ],
    "sg:phone":"+1 709 635 2925",
    "sg:postcode":"A8A 1E2",
    "sg:province":"NL",
    "sg:tags":[
        "physician",
        "surgeon"
    ],
    "wof:name":"Deer Lake Medical Clinic",
    "wof:placetype":"venue"
},
  "geometry": {"coordinates":[-57.423664093,49.1753387451],"type":"Point"}
}