{
  "type": "Feature",
  "properties": {
    "iso:country":"CA",
    "sg:address":"1002 Bateau Pl",
    "sg:city":"Orleans",
    "sg:classifiers":[
        {
            "category":"Professional",
            "subcategory":"Computer Services",
            "type":"Services"
        }
    ],
    "sg:phone":"+1 613 795 2323",
    "sg:postcode":"K1C 2N2",
    "sg:province":"ON",
    "sg:tags":[
        "website",
        "design"
    ],
    "wof:name":"Canroc.com",
    "wof:placetype":"venue"
},
  "geometry": {"coordinates":[-75.556694,45.473274],"type":"Point"}
}