{
  "type": "Feature",
  "properties": {
    "iso:country":"CA",
    "sg:city":"Calgary",
    "sg:classifiers":[
        {
            "category":"Building & Trades",
            "subcategory":"Construction",
            "type":"Services"
        }
    ],
    "sg:phone":"+1 403 692 0820",
    "sg:postcode":"T2H 2L2",
    "sg:province":"AB",
    "sg:tags":[
        "repairing",
        "solarium",
        "remodeling",
        "contractor"
    ],
    "wof:name":"Sunrooms Direct",
    "wof:placetype":"venue"
},
  "geometry": {"coordinates":[-114.057106018,50.996509552],"type":"Point"}
}