{
  "type": "Feature",
  "properties": {
    "addr:full":"Ottawa ON K1P 6B9",
    "addr:postcode":"k1p 6b9",
    "iso:country":"CA",
    "sg:city":"Ottawa",
    "sg:classifiers":[
        {
            "category":"Government",
            "subcategory":"Office",
            "type":"Public Place"
        }
    ],
    "sg:phone":"+1 613 563 9010",
    "sg:postcode":"K1P 6B9",
    "sg:province":"ON",
    "sg:tags":[
        "federal",
        "affairs"
    ],
    "wof:name":"Saudi Arabian Educational",
    "wof:placetype":"venue"
},
  "geometry": {"coordinates":[-75.700294,45.42009],"type":"Point"}
}