{
  "type": "Feature",
  "properties": {
    "addr:full":"Elk Point AB T0A 1A0",
    "addr:postcode":"t0a 1a0",
    "iso:country":"CA",
    "sg:city":"Elk Point",
    "sg:classifiers":[
        {
            "category":"Home & Garden",
            "subcategory":"Building Materials",
            "type":"Retail Goods"
        }
    ],
    "sg:phone":"+1 780 724 2760",
    "sg:postcode":"T0A 1A0",
    "sg:province":"AB",
    "wof:name":"Vincent's Building Supplies",
    "wof:placetype":"venue"
},
  "geometry": {"coordinates":[-110.89960479699999,53.8952865601],"type":"Point"}
}