{
  "type": "Feature",
  "properties": {
    "addr:full":"228 Second Ave N Yorkton SK S3N 1G7",
    "addr:housenumber":"228",
    "addr:postcode":"s3n 1g7",
    "addr:street":"Second Ave N",
    "iso:country":"CA",
    "sg:address":"228 Second Ave N",
    "sg:city":"Yorkton",
    "sg:classifiers":[
        {
            "category":"Education",
            "subcategory":"Special Training",
            "type":"Public Place"
        }
    ],
    "sg:phone":"+1 306 782 2077",
    "sg:postcode":"S3N 1G7",
    "sg:province":"SK",
    "sg:tags":[
        "instruction",
        "driving"
    ],
    "wof:name":"4 Seasons Driving School",
    "wof:placetype":"venue"
},
  "geometry": {"coordinates":[-102.461586,51.218319],"type":"Point"}
}