{
  "type": "Feature",
  "properties": {
    "iso:country":"CA",
    "sg:city":"Maple",
    "sg:classifiers":[
        {
            "category":"Manufacturing",
            "subcategory":"Tools & Machinery",
            "type":"Manufacturing & Wholesale Goods"
        }
    ],
    "sg:phone":"+1 905 832 0493",
    "sg:postcode":"L6A 1R4",
    "sg:province":"ON",
    "sg:tags":[
        "built",
        "designed"
    ],
    "wof:name":"Fiedler Technology Ltd",
    "wof:placetype":"venue"
},
  "geometry": {"coordinates":[-79.512146,43.872414],"type":"Point"}
}