{
  "type": "Feature",
  "properties": {
    "addr:full":"5790 Rue Pare Mont-Royal QC H4P 2M2",
    "addr:housenumber":"5790",
    "addr:postcode":"h4p 2m2",
    "addr:street":"Rue Pare",
    "iso:country":"CA",
    "sg:address":"5790 Rue Pare",
    "sg:city":"Mont-Royal",
    "sg:classifiers":[
        {
            "category":"Wholesale",
            "subcategory":"Sporting Goods",
            "type":"Manufacturing & Wholesale Goods"
        }
    ],
    "sg:phone":"+1 514 344 4838",
    "sg:postcode":"H4P 2M2",
    "sg:province":"QC",
    "sg:tags":[
        "equipment",
        "golf",
        "supply"
    ],
    "wof:name":"Agence DE Vente John Tate",
    "wof:placetype":"venue"
},
  "geometry": {"coordinates":[-73.66667200000001,45.487141],"type":"Point"}
}