{
  "type": "Feature",
  "properties": {
    "addr:full":"2048 Carnarvon St Victoria BC V8R 2V3",
    "addr:housenumber":"2048",
    "addr:postcode":"v8r 2v3",
    "addr:street":"Carnarvon St",
    "iso:country":"CA",
    "sg:address":"2048 Carnarvon St",
    "sg:city":"Victoria",
    "sg:classifiers":[
        {
            "category":"Wholesale",
            "subcategory":"Motor Vehicles",
            "type":"Manufacturing & Wholesale Goods"
        }
    ],
    "sg:phone":"+1 250 598 1898",
    "sg:postcode":"V8R 2V3",
    "sg:province":"BC",
    "sg:tags":[
        "automobile",
        "truck",
        "broker"
    ],
    "wof:name":"Auto Finders Svc Inc",
    "wof:placetype":"venue"
},
  "geometry": {"coordinates":[-123.36451700000001,48.428314],"type":"Point"}
}