{
  "type": "Feature",
  "properties": {
    "addr:full":"71 Gough Ave Toronto ON M4K 3N9",
    "addr:housenumber":"71",
    "addr:postcode":"m4k 3n9",
    "addr:street":"Gough Ave",
    "iso:country":"CA",
    "sg:address":"71 Gough Ave",
    "sg:city":"Toronto",
    "sg:classifiers":[
        {
            "category":"Social Services",
            "type":"Services"
        }
    ],
    "sg:phone":"+1 416 469 0842",
    "sg:postcode":"M4K 3N9",
    "sg:province":"ON",
    "sg:tags":[
        "organization",
        "welfare"
    ],
    "wof:name":"Society of St Vincent DE Paul",
    "wof:placetype":"venue"
},
  "geometry": {"coordinates":[-79.34618377690001,43.6794700623],"type":"Point"}
}