{
  "type": "Feature",
  "properties": {
    "addr:full":"Calgary AB T2J 5N8",
    "addr:postcode":"t2j 5n8",
    "iso:country":"CA",
    "sg:city":"Calgary",
    "sg:classifiers":[
        {
            "category":"Shopping",
            "subcategory":"Jewelry",
            "type":"Retail Goods"
        }
    ],
    "sg:phone":"+1 403 278 0477",
    "sg:postcode":"T2J 5N8",
    "sg:province":"AB",
    "sg:tags":[
        "clocks"
    ],
    "wof:name":"Clock Gallery Ltd",
    "wof:placetype":"venue"
},
  "geometry": {"coordinates":[-114.071281,50.956909],"type":"Point"}
}