{
  "type": "Feature",
  "properties": {
    "addr:full":"701 Robert St E Swift Current SK S9H 5G1",
    "addr:housenumber":"701",
    "addr:postcode":"s9h 5g1",
    "addr:street":"Robert St E",
    "iso:country":"CA",
    "sg:address":"701 Robert St E",
    "sg:city":"Swift Current",
    "sg:classifiers":[
        {
            "category":"Restaurant",
            "type":"Food & Drink"
        }
    ],
    "sg:phone":"+1 306 773 7221",
    "sg:postcode":"S9H 5G1",
    "sg:province":"SK",
    "wof:name":"Joey's Only Seafood Restaurant",
    "wof:placetype":"venue"
},
  "geometry": {"coordinates":[-107.79193100000001,50.298176],"type":"Point"}
}