{
  "type": "Feature",
  "properties": {
    "addr:full":"15 Granville Gate Markham ON L3R 4J2",
    "addr:housenumber":"15",
    "addr:postcode":"l3r 4j2",
    "addr:street":"Granville Gate",
    "iso:country":"CA",
    "sg:address":"15 Granville Gate",
    "sg:city":"Markham",
    "sg:classifiers":[
        {
            "category":"Building & Trades",
            "subcategory":"Landscaping Services",
            "type":"Services"
        }
    ],
    "sg:phone":"+1 905 479 2033",
    "sg:postcode":"L3R 4J2",
    "sg:province":"ON",
    "sg:tags":[
        "lawn",
        "maintenance",
        "grounds"
    ],
    "wof:name":"Grasshopper Lawn Care",
    "wof:placetype":"venue"
},
  "geometry": {"coordinates":[-79.351524353,43.8584823608],"type":"Point"}
}