{
  "type": "Feature",
  "properties": {
    "addr:full":"North York ON M4N 2N1",
    "addr:postcode":"m4n 2n1",
    "iso:country":"CA",
    "sg:city":"North York",
    "sg:classifiers":[
        {
            "category":"Building & Trades",
            "subcategory":"Construction",
            "type":"Services"
        }
    ],
    "sg:phone":"+1 416 486 3121",
    "sg:postcode":"M4N 2N1",
    "sg:province":"ON",
    "sg:tags":[
        "home",
        "general",
        "improvement",
        "contractor"
    ],
    "wof:name":"J C Kneider & Assoc Ltd",
    "wof:placetype":"venue"
},
  "geometry": {"coordinates":[-79.404099,43.733131],"type":"Point"}
}