{
  "type": "Feature",
  "properties": {
    "iso:country":"CA",
    "sg:address":"4195 Rue DE L'Amazone",
    "sg:city":"Jonquiere",
    "sg:classifiers":[
        {
            "category":"Professional",
            "subcategory":"Accounting & Tax Preparation",
            "type":"Services"
        }
    ],
    "sg:phone":"+1 418 695 3023",
    "sg:postcode":"G8A 2H9",
    "sg:province":"QC",
    "sg:tags":[
        "accountant"
    ],
    "wof:name":"Gravel, Sylvain",
    "wof:placetype":"venue"
},
  "geometry": {"coordinates":[-71.273125,48.421886],"type":"Point"}
}