{
  "type": "Feature",
  "properties": {
    "addr:full":"7240 Boul Maurice-Duplessis Montreal QC H1E 4A7",
    "addr:housenumber":"7240",
    "addr:postcode":"h1e 4a7",
    "addr:street":"Boul Maurice-Duplessis",
    "iso:country":"CA",
    "sg:address":"7240 Boul Maurice-Duplessis",
    "sg:city":"Montreal",
    "sg:classifiers":[
        {
            "category":"Professional",
            "subcategory":"Accounting & Tax Preparation",
            "type":"Services"
        }
    ],
    "sg:phone":"+1 514 648 1190",
    "sg:postcode":"H1E 4A7",
    "sg:province":"QC",
    "sg:tags":[
        "accountant"
    ],
    "wof:name":"Caticchio, Michael CA",
    "wof:placetype":"venue"
},
  "geometry": {"coordinates":[-73.60218,45.623589],"type":"Point"}
}