{
  "type": "Feature",
  "properties": {
    "iso:country":"CA",
    "sg:address":"750 Av Du Phare O # 22",
    "sg:city":"Matane",
    "sg:classifiers":[
        {
            "category":"Restaurant",
            "type":"Food & Drink"
        }
    ],
    "sg:phone":"+1 418 566 2833",
    "sg:postcode":"G4W 3W8",
    "sg:province":"QC",
    "sg:tags":[
        "chicken",
        "dinner"
    ],
    "wof:name":"Poulet Frit Chester-L'Escale",
    "wof:placetype":"venue"
},
  "geometry": {"coordinates":[-67.5010757446,48.8525123596],"type":"Point"}
}