{
  "type": "Feature",
  "properties": {
    "addr:full":"4960 Rue Dubois Drummondville QC J2B 6V4",
    "addr:housenumber":"4960",
    "addr:postcode":"j2b 6v4",
    "addr:street":"Rue Dubois",
    "iso:country":"CA",
    "sg:address":"4960 Rue Dubois",
    "sg:city":"Drummondville",
    "sg:classifiers":[
        {
            "category":"Manufacturing",
            "subcategory":"Tools & Machinery",
            "type":"Manufacturing & Wholesale Goods"
        }
    ],
    "sg:phone":"+1 819 475 6702",
    "sg:postcode":"J2B 6V4",
    "sg:province":"QC",
    "sg:tags":[
        "equipment",
        "supply",
        "therapy",
        "massage",
        "physical"
    ],
    "wof:name":"Equipements Masso-Kit Can",
    "wof:placetype":"venue"
},
  "geometry": {"coordinates":[-72.529526,45.902756],"type":"Point"}
}