{
  "type": "Feature",
  "properties": {
    "addr:full":"507 Rue Principale Sainte-Apolline-DE-Patton QC G0R 2P0",
    "addr:housenumber":"507",
    "addr:postcode":"g0r 2p0",
    "addr:street":"Rue Principale",
    "iso:country":"CA",
    "sg:address":"507 Rue Principale",
    "sg:city":"Sainte-Apolline-DE-Patton",
    "sg:classifiers":[
        {
            "category":"Organizations",
            "subcategory":"Religious Organization",
            "type":"Services"
        }
    ],
    "sg:phone":"+1 418 469 2166",
    "sg:postcode":"G0R 2P0",
    "sg:province":"QC",
    "sg:tags":[
        "church"
    ],
    "wof:name":"Presbytere Ste-Apolline-DE-Pat",
    "wof:placetype":"venue"
},
  "geometry": {"coordinates":[-70.19589999999999,46.806965],"type":"Point"}
}