{
  "type": "Feature",
  "properties": {
    "addr:full":"5114 48 Ave Ponoka AB T4J 1J2",
    "addr:housenumber":"5114",
    "addr:postcode":"t4j 1j2",
    "addr:street":"48 Ave",
    "iso:country":"CA",
    "sg:address":"5114 48 Ave",
    "sg:city":"Ponoka",
    "sg:classifiers":[
        {
            "category":"Shopping",
            "subcategory":"Gifts & Souvenirs",
            "type":"Retail Goods"
        }
    ],
    "sg:phone":"+1 403 783 5355",
    "sg:postcode":"T4J 1J2",
    "sg:province":"AB",
    "sg:tags":[
        "shop"
    ],
    "wof:name":"Walrus & the Carpenter",
    "wof:placetype":"venue"
},
  "geometry": {"coordinates":[-113.57997899999999,52.675224],"type":"Point"}
}