{
  "type": "Feature",
  "properties": {
    "addr:full":"439 2nd St E Cornwall ON K6H 1Z2",
    "addr:housenumber":"439",
    "addr:postcode":"k6h 1z2",
    "addr:street":"2Nd St E",
    "iso:country":"CA",
    "sg:address":"439 2nd St E",
    "sg:city":"Cornwall",
    "sg:classifiers":[
        {
            "category":"Health Services",
            "subcategory":"Nursing And Care Facility",
            "type":"Services"
        }
    ],
    "sg:phone":"+1 613 933 2592",
    "sg:postcode":"K6H 1Z2",
    "sg:province":"ON",
    "sg:tags":[
        "home",
        "convalescent"
    ],
    "wof:name":"Parisien Manor",
    "wof:placetype":"venue"
},
  "geometry": {"coordinates":[-74.7196350098,45.020980835],"type":"Point"}
}