{
  "type": "Feature",
  "properties": {
    "addr:full":"5253 46 Ave Vegreville AB T9C 1P9",
    "addr:housenumber":"5253",
    "addr:postcode":"t9c 1p9",
    "addr:street":"46 Ave",
    "iso:country":"CA",
    "sg:address":"5253 46 Ave",
    "sg:city":"Vegreville",
    "sg:classifiers":[
        {
            "category":"Professional",
            "type":"Services"
        }
    ],
    "sg:phone":"+1 780 632 2229",
    "sg:postcode":"T9C 1P9",
    "sg:province":"AB",
    "sg:tags":[
        "senior",
        "establishment",
        "housing",
        "citizen"
    ],
    "wof:name":"Homestead Senior Citizen's Ldg",
    "wof:placetype":"venue"
},
  "geometry": {"coordinates":[-112.063568115,53.49376297],"type":"Point"}
}