{
  "type": "Feature",
  "properties": {
    "iso:country":"CA",
    "sg:city":"Burlington",
    "sg:classifiers":[
        {
            "category":"Shopping",
            "type":"Retail Goods"
        }
    ],
    "sg:phone":"+1 905 681 2300",
    "sg:postcode":"L7L 1V1",
    "sg:province":"ON",
    "sg:tags":[
        "gourmet",
        "shop",
        "wedding",
        "supply"
    ],
    "wof:name":"Castlefield Fine Wine & Jellie",
    "wof:placetype":"venue"
},
  "geometry": {"coordinates":[-79.7529296875,43.3675613403],"type":"Point"}
}