{
  "type": "Feature",
  "properties": {
    "addr:full":"95 Rue Saint-Vallier O Quebec QC G1K 1J7",
    "addr:housenumber":"95",
    "addr:postcode":"g1k 1j7",
    "addr:street":"Rue Saint-Vallier O",
    "iso:country":"CA",
    "sg:address":"95 Rue Saint-Vallier O",
    "sg:city":"Quebec",
    "sg:classifiers":[
        {
            "category":"Recreation",
            "type":"Entertainment"
        }
    ],
    "sg:phone":"+1 418 523 6638",
    "sg:postcode":"G1K 1J7",
    "sg:province":"QC",
    "sg:tags":[
        "martial",
        "arts",
        "instruction"
    ],
    "wof:name":"Studios Unis D'Auto Defense",
    "wof:placetype":"venue"
},
  "geometry": {"coordinates":[-71.22914900000001,46.811188],"type":"Point"}
}