{
  "type": "Feature",
  "properties": {
    "addr:full":"6540 4 St NE Calgary AB T2K 6H2",
    "addr:housenumber":"6540 4",
    "addr:postcode":"t2k 6h2",
    "addr:street":"St Ne",
    "iso:country":"CA",
    "sg:address":"6540 4 St NE",
    "sg:city":"Calgary",
    "sg:classifiers":[
        {
            "category":"Travel",
            "subcategory":"Travel Agent",
            "type":"Entertainment"
        }
    ],
    "sg:phone":"+1 403 275 4116",
    "sg:postcode":"T2K 6H2",
    "sg:province":"AB",
    "sg:tags":[
        "agency",
        "bureau"
    ],
    "wof:name":"Affordable Travel",
    "wof:placetype":"venue"
},
  "geometry": {"coordinates":[-114.056518555,51.1111984253],"type":"Point"}
}