{
  "type": "Feature",
  "properties": {
    "iso:country":"CA",
    "sg:address":"9385 Boul Saint-Michel",
    "sg:city":"Montreal",
    "sg:classifiers":[
        {
            "category":"Social Services",
            "subcategory":"Child Care",
            "type":"Services"
        }
    ],
    "sg:phone":"+1 514 321 9662",
    "sg:postcode":"H1Z 4G9",
    "sg:province":"QC",
    "wof:name":"Garderie Piccolo Mondo Inc",
    "wof:placetype":"venue"
},
  "geometry": {"coordinates":[-73.633522,45.574612],"type":"Point"}
}