{
  "type": "Feature",
  "properties": {
    "addr:full":"10159 108 St NW Edmonton AB T5J 1L1",
    "addr:housenumber":"10159",
    "addr:postcode":"t5j 1l1",
    "addr:street":"108 St Nw",
    "iso:country":"CA",
    "sg:address":"10159 108 St NW",
    "sg:city":"Edmonton",
    "sg:classifiers":[
        {
            "category":"Communications",
            "subcategory":"Film & Video Production",
            "type":"Services"
        }
    ],
    "sg:phone":"+1 780 448 0277",
    "sg:postcode":"T5J 1L1",
    "sg:province":"AB",
    "sg:tags":[
        "advertising",
        "taping"
    ],
    "wof:name":"Chronos Video Productions Inc",
    "wof:placetype":"venue"
},
  "geometry": {"coordinates":[-113.50633999999999,53.54211],"type":"Point"}
}