{
  "type": "Feature",
  "properties": {
    "addr:full":"2080 Van Dyke Pl Richmond BC V6V 1X9",
    "addr:housenumber":"2080",
    "addr:postcode":"v6v 1x9",
    "addr:street":"Van Dyke Pl",
    "iso:country":"CA",
    "sg:address":"2080 Van Dyke Pl",
    "sg:city":"Richmond",
    "sg:classifiers":[
        {
            "category":"Wholesale",
            "subcategory":"Auto Parts",
            "type":"Manufacturing & Wholesale Goods"
        }
    ],
    "sg:phone":"+1 604 278 2045",
    "sg:postcode":"V6V 1X9",
    "sg:province":"BC",
    "sg:tags":[
        "equipment",
        "truck"
    ],
    "wof:name":"Aries Offroad Canada",
    "wof:placetype":"venue"
},
  "geometry": {"coordinates":[-123.063377,49.197636],"type":"Point"}
}