{
  "type": "Feature",
  "properties": {
    "iso:country":"CA",
    "sg:city":"Laval",
    "sg:classifiers":[
        {
            "category":"Professional",
            "subcategory":"Accounting & Tax Preparation",
            "type":"Services"
        }
    ],
    "sg:phone":"+1 450 687 8855",
    "sg:postcode":"H7V 3Y7",
    "sg:province":"QC",
    "sg:tags":[
        "payroll"
    ],
    "wof:name":"Service DE Paie Infobec",
    "wof:placetype":"venue"
},
  "geometry": {"coordinates":[-73.7467575073,45.5524635315],"type":"Point"}
}