{
  "type": "Feature",
  "properties": {
    "addr:full":"6444 12 St SE Calgary AB T2H 2X2",
    "addr:housenumber":"6444",
    "addr:postcode":"t2h 2x2",
    "addr:street":"12 St Se",
    "iso:country":"CA",
    "sg:address":"6444 12 St SE",
    "sg:city":"Calgary",
    "sg:classifiers":[
        {
            "category":"Professional",
            "subcategory":"Business Services",
            "type":"Services"
        }
    ],
    "sg:phone":"+1 403 255 4225",
    "sg:postcode":"T2H 2X2",
    "sg:province":"AB",
    "wof:name":"European Cutters Intl Ltd",
    "wof:placetype":"venue"
},
  "geometry": {"coordinates":[-114.03655999999999,50.995331],"type":"Point"}
}