{
  "type": "Feature",
  "properties": {
    "addr:full":"501 Ellice Ave Winnipeg MB R3B 1Y8",
    "addr:housenumber":"501",
    "addr:postcode":"r3b 1y8",
    "addr:street":"Ellice Ave",
    "iso:country":"CA",
    "sg:address":"501 Ellice Ave",
    "sg:city":"Winnipeg",
    "sg:classifiers":[
        {
            "category":"Food & Beverages",
            "subcategory":"Groceries & Convenience Stores",
            "type":"Retail Goods"
        }
    ],
    "sg:phone":"+1 204 774 0058",
    "sg:postcode":"R3B 1Y8",
    "sg:province":"MB",
    "sg:tags":[
        "grocer"
    ],
    "wof:name":"Y-Not Foods",
    "wof:placetype":"venue"
},
  "geometry": {"coordinates":[-97.152603,49.893127],"type":"Point"}
}