{
  "type": "Feature",
  "properties": {
    "addr:full":"12240 Boul Laurentien Montreal QC H4K 1M9",
    "addr:housenumber":"12240",
    "addr:postcode":"h4k 1m9",
    "addr:street":"Boul Laurentien",
    "iso:country":"CA",
    "sg:address":"12240 Boul Laurentien",
    "sg:city":"Montreal",
    "sg:classifiers":[
        {
            "category":"Health Services",
            "subcategory":"Doctor",
            "type":"Services"
        }
    ],
    "sg:phone":"+1 514 331 0880",
    "sg:postcode":"H4K 1M9",
    "sg:province":"QC",
    "sg:tags":[
        "dentist"
    ],
    "wof:name":"Hamamji, Paul DDS",
    "wof:placetype":"venue"
},
  "geometry": {"coordinates":[-73.7211685181,45.5282363892],"type":"Point"}
}