{
  "type": "Feature",
  "properties": {
    "addr:full":"780 Boul Des Recollets Trois-Rivieres QC G8Z 3W2",
    "addr:housenumber":"780",
    "addr:postcode":"g8z 3w2",
    "addr:street":"Boul Des Recollets Trois-Rivieres",
    "iso:country":"CA",
    "sg:address":"780 Boul Des Recollets",
    "sg:city":"Trois-Rivieres",
    "sg:classifiers":[
        {
            "category":"Shopping",
            "subcategory":"Books",
            "type":"Retail Goods"
        }
    ],
    "sg:phone":"+1 819 379 1344",
    "sg:postcode":"G8Z 3W2",
    "sg:province":"QC",
    "sg:tags":[
        "dealer"
    ],
    "wof:name":"Librairie Le Lecteur Enr",
    "wof:placetype":"venue"
},
  "geometry": {"coordinates":[-72.569717,46.360725],"type":"Point"}
}