{
  "type": "Feature",
  "properties": {
    "addr:full":"3522 Main St West St Paul MB R4A 5A2",
    "addr:housenumber":"3522",
    "addr:postcode":"r4a 5a2",
    "addr:street":"Main St",
    "iso:country":"CA",
    "sg:address":"3522 Main St",
    "sg:city":"West St Paul",
    "sg:classifiers":[
        {
            "category":"Manufacturing",
            "subcategory":"Apparel",
            "type":"Manufacturing & Wholesale Goods"
        }
    ],
    "sg:phone":"+1 204 338 2420",
    "sg:postcode":"R4A 5A2",
    "sg:province":"MB",
    "wof:name":"Northern Sail Works Ltd",
    "wof:placetype":"venue"
},
  "geometry": {"coordinates":[-97.0679397583,49.9791030884],"type":"Point"}
}