{
  "type": "Feature",
  "properties": {
    "addr:full":"26390 Fraser Hwy Aldergrove BC V4W 2V1",
    "addr:housenumber":"26390",
    "addr:postcode":"v4w 2v1",
    "addr:street":"Fraser Hwy",
    "iso:country":"CA",
    "sg:address":"26390 Fraser Hwy",
    "sg:city":"Aldergrove",
    "sg:classifiers":[
        {
            "category":"Autos & Motor Vehicles",
            "subcategory":"Fuel & Gas Station",
            "type":"Retail Goods"
        }
    ],
    "sg:phone":"+1 604 856 2282",
    "sg:postcode":"V4W 2V1",
    "sg:province":"BC",
    "sg:tags":[
        "oil"
    ],
    "wof:name":"Aldergrove Town Pantry",
    "wof:placetype":"venue"
},
  "geometry": {"coordinates":[-122.492722,49.059551],"type":"Point"}
}