{
  "type": "Feature",
  "properties": {
    "addr:full":"5011 Bella Vista Rd Vernon BC V1H 1A1",
    "addr:housenumber":"5011",
    "addr:postcode":"v1h 1a1",
    "addr:street":"Bella Vista Rd",
    "iso:country":"CA",
    "sg:address":"5011 Bella Vista Rd",
    "sg:city":"Vernon",
    "sg:classifiers":[
        {
            "category":"Food & Beverages",
            "subcategory":"Fruits & Vegetables",
            "type":"Retail Goods"
        }
    ],
    "sg:phone":"+1 250 545 0105",
    "sg:postcode":"V1H 1A1",
    "sg:province":"BC",
    "sg:tags":[
        "produce"
    ],
    "wof:name":"Bella Vista Farm Market",
    "wof:placetype":"venue"
},
  "geometry": {"coordinates":[-119.306785584,50.2628631592],"type":"Point"}
}