{
  "type": "Feature",
  "properties": {
    "addr:full":"Pond Inlet NU X0A 0S0",
    "addr:postcode":"x0a 0s0",
    "iso:country":"CA",
    "sg:city":"Pond Inlet",
    "sg:classifiers":[
        {
            "category":"Government",
            "subcategory":"Office",
            "type":"Public Place"
        }
    ],
    "sg:phone":"+1 867 899 8720",
    "sg:postcode":"X0A 0S0",
    "sg:province":"NU",
    "sg:tags":[
        "village"
    ],
    "wof:name":"Pond Inlet Arena",
    "wof:placetype":"venue"
},
  "geometry": {"coordinates":[-77.95394134519999,72.6981430054],"type":"Point"}
}