{
  "type": "Feature",
  "properties": {
    "addr:full":"12240 Vickers Way Richmond BC V6V 1H9",
    "addr:housenumber":"12240",
    "addr:postcode":"v6v 1h9",
    "addr:street":"Vickers Way",
    "iso:country":"CA",
    "sg:address":"12240 Vickers Way",
    "sg:city":"Richmond",
    "sg:classifiers":[
        {
            "category":"Professional",
            "subcategory":"Business Services",
            "type":"Services"
        }
    ],
    "sg:phone":"+1 604 276 9265",
    "sg:postcode":"V6V 1H9",
    "sg:province":"BC",
    "sg:tags":[
        "water",
        "treatment"
    ],
    "wof:name":"International Hydro System Inc",
    "wof:placetype":"venue"
},
  "geometry": {"coordinates":[-123.087563,49.191128],"type":"Point"}
}