{
  "type": "Feature",
  "properties": {
    "iso:country":"CA",
    "sg:address":"15 2nd Ave N",
    "sg:city":"Sauble Beach",
    "sg:classifiers":[
        {
            "category":"Professional",
            "subcategory":"Lawyer & Legal Services",
            "type":"Services"
        }
    ],
    "sg:phone":"+1 519 422 2122",
    "sg:postcode":"N0H 2G0",
    "sg:province":"ON",
    "sg:tags":[
        "attorney"
    ],
    "wof:name":"Jensen, Nicoletta",
    "wof:placetype":"venue"
},
  "geometry": {"coordinates":[-81.2692184448,44.6296958923],"type":"Point"}
}