{
  "type": "Feature",
  "properties": {
    "addr:full":"3 Bleams Rd E New Hamburg ON N3A 1G5",
    "addr:housenumber":"3",
    "addr:postcode":"n3a 1g5",
    "addr:street":"Bleams Rd E",
    "iso:country":"CA",
    "sg:address":"3 Bleams Rd E",
    "sg:city":"New Hamburg",
    "sg:classifiers":[
        {
            "category":"Retail",
            "subcategory":"Portrait Studio",
            "type":"Services"
        }
    ],
    "sg:phone":"+1 519 662 3063",
    "sg:postcode":"N3A 1G5",
    "sg:province":"ON",
    "sg:tags":[
        "photographer"
    ],
    "wof:name":"Images Photography",
    "wof:placetype":"venue"
},
  "geometry": {"coordinates":[-80.70463599999999,43.373886],"type":"Point"}
}