{
  "type": "Feature",
  "properties": {
    "iso:country":"CA",
    "sg:address":"RR 3 Lcd Collingwood",
    "sg:city":"Collingwood",
    "sg:classifiers":[
        {
            "category":"Recreation",
            "type":"Entertainment"
        }
    ],
    "sg:phone":"+1 705 445 0201",
    "sg:postcode":"L9Y 3Z2",
    "sg:province":"ON",
    "sg:tags":[
        "provincial",
        "parks"
    ],
    "wof:name":"Sheffield Park",
    "wof:placetype":"venue"
},
  "geometry": {"coordinates":[-80.2168273926,44.4998893738],"type":"Point"}
}