{
  "type": "Feature",
  "properties": {
    "addr:full":"750 Elizabeth St London ON N5Y 4T7",
    "addr:housenumber":"750",
    "addr:postcode":"n5y 4t7",
    "addr:street":"Elizabeth St",
    "iso:country":"CA",
    "sg:address":"750 Elizabeth St",
    "sg:city":"London",
    "sg:classifiers":[
        {
            "category":"Professional",
            "subcategory":"Detective & Security Services",
            "type":"Services"
        }
    ],
    "sg:phone":"+1 519 433 6763",
    "sg:postcode":"N5Y 4T7",
    "sg:province":"ON",
    "sg:tags":[
        "guard",
        "patrol"
    ],
    "wof:name":"Commissionaires Western Region",
    "wof:placetype":"venue"
},
  "geometry": {"coordinates":[-81.2339553833,42.999912262],"type":"Point"}
}