{
  "type": "Feature",
  "properties": {
    "addr:full":"117 Main St St Walburg SK S0M 2T0",
    "addr:housenumber":"117",
    "addr:postcode":"s0m 2t0",
    "addr:street":"Main St St",
    "iso:country":"CA",
    "sg:address":"117 Main St",
    "sg:city":"St Walburg",
    "sg:classifiers":[
        {
            "category":"Organizations",
            "subcategory":"Religious Organization",
            "type":"Services"
        }
    ],
    "sg:phone":"+1 306 248 3337",
    "sg:postcode":"S0M 2T0",
    "sg:province":"SK",
    "sg:tags":[
        "church"
    ],
    "wof:name":"St Paul's United Church",
    "wof:placetype":"venue"
},
  "geometry": {"coordinates":[-109.200081,53.634724],"type":"Point"}
}