{
  "type": "Feature",
  "properties": {
    "addr:full":"Lloydminster AB T9V 2E8",
    "addr:postcode":"t9v 2e8",
    "iso:country":"CA",
    "sg:city":"Lloydminster",
    "sg:classifiers":[
        {
            "category":"Wholesale",
            "subcategory":"Machinery & Supplies",
            "type":"Manufacturing & Wholesale Goods"
        }
    ],
    "sg:phone":"+1 780 875 5167",
    "sg:postcode":"T9V 2E8",
    "sg:province":"AB",
    "sg:tags":[
        "repairing"
    ],
    "wof:name":"Garfield Diesel Repair Ltd",
    "wof:placetype":"venue"
},
  "geometry": {"coordinates":[-110.015152,53.303406],"type":"Point"}
}