{
  "type": "Feature",
  "properties": {
    "addr:full":"12817 73 St NW Edmonton AB T5C 0T2",
    "addr:housenumber":"12817",
    "addr:postcode":"t5c 0t2",
    "addr:street":"73 St Nw",
    "iso:country":"CA",
    "sg:address":"12817 73 St NW",
    "sg:city":"Edmonton",
    "sg:classifiers":[
        {
            "category":"Social Services",
            "subcategory":"Adult Care",
            "type":"Services"
        }
    ],
    "sg:phone":"+1 780 422 0871",
    "sg:postcode":"T5C 0T2",
    "sg:province":"AB",
    "sg:tags":[
        "home"
    ],
    "wof:name":"Balwin Group Home",
    "wof:placetype":"venue"
},
  "geometry": {"coordinates":[-113.45380400000001,53.586418],"type":"Point"}
}