{
  "type": "Feature",
  "properties": {
    "iso:country":"CA",
    "sg:address":"266 Speers Rd",
    "sg:city":"Oakville",
    "sg:classifiers":[
        {
            "category":"Home & Garden",
            "subcategory":"Carpets & Floor Coverings",
            "type":"Retail Goods"
        }
    ],
    "sg:phone":"+1 905 845 8562",
    "sg:postcode":"L6K 2E9",
    "sg:province":"ON",
    "sg:tags":[
        "paint",
        "material"
    ],
    "wof:name":"Speers Paint & Flooring Ltd",
    "wof:placetype":"venue"
},
  "geometry": {"coordinates":[-79.691048,43.442562],"type":"Point"}
}