{
  "type": "Feature",
  "properties": {
    "addr:full":"95 Cascade St Hamilton ON L8E 3B7",
    "addr:housenumber":"95",
    "addr:postcode":"l8e 3b7",
    "addr:street":"Cascade St",
    "iso:country":"CA",
    "sg:address":"95 Cascade St",
    "sg:city":"Hamilton",
    "sg:classifiers":[
        {
            "category":"Wholesale",
            "subcategory":"Metals & Minerals",
            "type":"Manufacturing & Wholesale Goods"
        }
    ],
    "sg:phone":"+1 905 560 2360",
    "sg:postcode":"L8E 3B7",
    "sg:province":"ON",
    "sg:tags":[
        "steel",
        "warehouse"
    ],
    "wof:name":"Abacus Metal Supply",
    "wof:placetype":"venue"
},
  "geometry": {"coordinates":[-79.754272,43.239555],"type":"Point"}
}