{
  "type": "Feature",
  "properties": {
    "addr:full":"415 Rue Vachon Cap-DE-LA-Madeleine QC G8T 8P6",
    "addr:housenumber":"415",
    "addr:postcode":"g8t 8p6",
    "addr:street":"Rue Vachon",
    "iso:country":"CA",
    "sg:address":"415 Rue Vachon",
    "sg:city":"Cap-DE-LA-Madeleine",
    "sg:classifiers":[
        {
            "category":"Sports & Exercise",
            "subcategory":"Bowling",
            "type":"Entertainment"
        }
    ],
    "sg:phone":"+1 819 374 8383",
    "sg:postcode":"G8T 8P6",
    "sg:province":"QC",
    "sg:tags":[
        "center"
    ],
    "wof:name":"Salon DE Quilles-Francheville",
    "wof:placetype":"venue"
},
  "geometry": {"coordinates":[-72.55358886720001,46.3725357056],"type":"Point"}
}