{
  "type": "Feature",
  "properties": {
    "addr:full":"226 Cromwell Ave Oshawa ON L1J 4T8",
    "addr:housenumber":"226",
    "addr:postcode":"l1j 4t8",
    "addr:street":"Cromwell Ave",
    "iso:country":"CA",
    "sg:address":"226 Cromwell Ave",
    "sg:city":"Oshawa",
    "sg:classifiers":[
        {
            "category":"Recreation",
            "type":"Entertainment"
        }
    ],
    "sg:phone":"+1 905 725 9179",
    "sg:postcode":"L1J 4T8",
    "sg:province":"ON",
    "sg:tags":[
        "astrologer"
    ],
    "wof:name":"Astrological Consultations",
    "wof:placetype":"venue"
},
  "geometry": {"coordinates":[-78.8734588623,43.8896141052],"type":"Point"}
}