{
  "type": "Feature",
  "properties": {
    "addr:full":"357 J W Pickersgill Blvd Wareham-Centreville NL A0G 4P0",
    "addr:housenumber":"357",
    "addr:postcode":"a0g 4p0",
    "addr:street":"J W Pickersgill Blvd",
    "iso:country":"CA",
    "sg:address":"357 J W Pickersgill Blvd",
    "sg:city":"Wareham-Centreville",
    "sg:classifiers":[
        {
            "category":"Food & Beverages",
            "subcategory":"Groceries & Convenience Stores",
            "type":"Retail Goods"
        }
    ],
    "sg:phone":"+1 709 678 2844",
    "sg:postcode":"A0G 4P0",
    "sg:province":"NL",
    "sg:tags":[
        "grocer"
    ],
    "wof:name":"Indian Bay Frozen Foods",
    "wof:placetype":"venue"
},
  "geometry": {"coordinates":[-53.888969,49.012432],"type":"Point"}
}