{
  "type": "Feature",
  "properties": {
    "addr:full":"Baie-Comeau QC G5C 1M5",
    "addr:postcode":"g5c 1m5",
    "iso:country":"CA",
    "sg:city":"Baie-Comeau",
    "sg:classifiers":[
        {
            "category":"Manufacturing",
            "subcategory":"Signs",
            "type":"Manufacturing & Wholesale Goods"
        }
    ],
    "sg:phone":"+1 418 589 8703",
    "sg:postcode":"G5C 1M5",
    "sg:province":"QC",
    "wof:name":"Fillion Enseignes Enr",
    "wof:placetype":"venue"
},
  "geometry": {"coordinates":[-68.24709320069999,49.1932258606],"type":"Point"}
}