{
  "type": "Feature",
  "properties": {
    "addr:full":"LA Pocatiere QC G0R 1Z0",
    "addr:postcode":"g0r 1z0",
    "iso:country":"CA",
    "sg:city":"LA Pocatiere",
    "sg:classifiers":[
        {
            "category":"Restaurant",
            "type":"Food & Drink"
        }
    ],
    "sg:phone":"+1 418 856 3426",
    "sg:postcode":"G0R 1Z0",
    "sg:province":"QC",
    "wof:name":"Casse-Croute Chez Line",
    "wof:placetype":"venue"
},
  "geometry": {"coordinates":[-70.047958374,47.3597564697],"type":"Point"}
}