{
  "type": "Feature",
  "properties": {
    "addr:full":"10 Northland Way NE Medicine Hat AB T1C 1Z2",
    "addr:housenumber":"10",
    "addr:postcode":"t1c 1z2",
    "addr:street":"Northland Way Ne",
    "iso:country":"CA",
    "sg:address":"10 Northland Way NE",
    "sg:city":"Medicine Hat",
    "sg:classifiers":[
        {
            "category":"Food & Beverages",
            "subcategory":"Groceries & Convenience Stores",
            "type":"Retail Goods"
        }
    ],
    "sg:phone":"+1 403 528 6607",
    "sg:postcode":"T1C 1Z2",
    "sg:province":"AB",
    "sg:tags":[
        "grocer",
        "pharmacy"
    ],
    "wof:name":"Medicine Hat CO-OP Ltd",
    "wof:placetype":"venue"
},
  "geometry": {"coordinates":[-110.678093,50.041069],"type":"Point"}
}