{
  "type": "Feature",
  "properties": {
    "addr:full":"2941 Lake Shore Blvd W Etobicoke ON M8V 1J5",
    "addr:housenumber":"2941",
    "addr:postcode":"m8v 1j5",
    "addr:street":"Lake Shore Blvd W",
    "iso:country":"CA",
    "sg:address":"2941 Lake Shore Blvd W",
    "sg:city":"Etobicoke",
    "sg:classifiers":[
        {
            "category":"Shopping",
            "subcategory":"Discount & Variety Stores",
            "type":"Retail Goods"
        }
    ],
    "sg:phone":"+1 416 255 8657",
    "sg:postcode":"M8V 1J5",
    "sg:province":"ON",
    "wof:name":"Village Convenience",
    "wof:placetype":"venue"
},
  "geometry": {"coordinates":[-79.505486,43.600613],"type":"Point"}
}