{
  "type": "Feature",
  "properties": {
    "iso:country":"CA",
    "sg:city":"Lethbridge",
    "sg:classifiers":[
        {
            "category":"Recreation",
            "type":"Entertainment"
        }
    ],
    "sg:phone":"+1 403 320 3009",
    "sg:postcode":"T1J 0P6",
    "sg:province":"AB",
    "sg:tags":[
        "skating",
        "rink",
        "government"
    ],
    "wof:name":"Adams Ice Ctr",
    "wof:placetype":"venue"
},
  "geometry": {"coordinates":[-112.833519,49.694458],"type":"Point"}
}