{
  "type": "Feature",
  "properties": {
    "iso:country":"CA",
    "sg:address":"969 Upper James St",
    "sg:city":"Hamilton",
    "sg:classifiers":[
        {
            "category":"Home & Garden",
            "subcategory":"Home Furnishings",
            "type":"Retail Goods"
        }
    ],
    "sg:phone":"+1 905 383 3581",
    "sg:postcode":"L9C 3A6",
    "sg:province":"ON",
    "sg:tags":[
        "shop",
        "made",
        "fabric",
        "drapery"
    ],
    "wof:name":"Fabricland Distributors",
    "wof:placetype":"venue"
},
  "geometry": {"coordinates":[-79.8836364746,43.2236671448],"type":"Point"}
}