{
  "type": "Feature",
  "properties": {
    "addr:full":"Gaudet St St Isidore DE Bellevue SK S0K 3Y0",
    "addr:postcode":"s0k 3y0",
    "addr:street":"Gaudet St St;De Bellevue",
    "iso:country":"CA",
    "sg:address":"Gaudet St",
    "sg:city":"St Isidore DE Bellevue",
    "sg:classifiers":[
        {
            "category":"Insurance",
            "subcategory":"Insurance Agent",
            "type":"Services"
        }
    ],
    "sg:phone":"+1 306 423 5500",
    "sg:postcode":"S0K 3Y0",
    "sg:province":"SK",
    "wof:name":"P Gaudet Agencies",
    "wof:placetype":"venue"
},
  "geometry": {"coordinates":[-105.920692444,52.7837562561],"type":"Point"}
}