{
  "type": "Feature",
  "properties": {
    "addr:full":"70 Centre Ave Blumenort MB R0A 0C0",
    "addr:housenumber":"70",
    "addr:postcode":"r0a 0c0",
    "addr:street":"Centre Ave",
    "iso:country":"CA",
    "sg:address":"70 Centre Ave",
    "sg:city":"Blumenort",
    "sg:classifiers":[
        {
            "category":"Building & Trades",
            "subcategory":"Construction",
            "type":"Services"
        }
    ],
    "sg:phone":"+1 204 326 9973",
    "sg:postcode":"R0A 0C0",
    "sg:province":"MB",
    "sg:tags":[
        "road",
        "contractor"
    ],
    "wof:name":"Fast Brothers Ltd",
    "wof:placetype":"venue"
},
  "geometry": {"coordinates":[-96.69016999999999,49.604256],"type":"Point"}
}