{
  "type": "Feature",
  "properties": {
    "addr:full":"Sherwood Park AB T8H 2H3",
    "addr:postcode":"t8h 2h3",
    "iso:country":"CA",
    "sg:city":"Sherwood Park",
    "sg:classifiers":[
        {
            "category":"Professional",
            "subcategory":"Research",
            "type":"Services"
        }
    ],
    "sg:phone":"+1 780 416 5590",
    "sg:postcode":"T8H 2H3",
    "sg:province":"AB",
    "sg:tags":[
        "environmental",
        "ecological"
    ],
    "wof:name":"Genoil",
    "wof:placetype":"venue"
},
  "geometry": {"coordinates":[-113.319633,53.563927],"type":"Point"}
}