{
  "type": "Feature",
  "properties": {
    "iso:country":"CA",
    "sg:city":"Fort Mcmurray",
    "sg:classifiers":[
        {
            "category":"Restaurant",
            "type":"Food & Drink"
        }
    ],
    "sg:phone":"+1 780 790 1697",
    "sg:postcode":"T9H 3K8",
    "sg:province":"AB",
    "wof:name":"Taste of the Orient",
    "wof:placetype":"venue"
},
  "geometry": {"coordinates":[-111.36486053500001,56.721446991],"type":"Point"}
}