{
  "type": "Feature",
  "properties": {
    "addr:full":"147 Riverside Close SE Calgary AB T2C 3N4",
    "addr:housenumber":"147",
    "addr:postcode":"t2c 3n4",
    "addr:street":"Riverside Close Se",
    "iso:country":"CA",
    "sg:address":"147 Riverside Close SE",
    "sg:city":"Calgary",
    "sg:classifiers":[
        {
            "category":"Professional",
            "subcategory":"Advertising",
            "type":"Services"
        }
    ],
    "sg:phone":"+1 403 279 4539",
    "sg:postcode":"T2C 3N4",
    "sg:province":"AB",
    "sg:tags":[
        "counselor"
    ],
    "wof:name":"Dave Whamond Illustrations",
    "wof:placetype":"venue"
},
  "geometry": {"coordinates":[-114.028144836,50.9759368896],"type":"Point"}
}