{
  "type": "Feature",
  "properties": {
    "addr:full":"7764 83 Ave NW Edmonton AB T6C 1A4",
    "addr:housenumber":"7764",
    "addr:postcode":"t6c 1a4",
    "addr:street":"83 Ave Nw",
    "iso:country":"CA",
    "sg:address":"7764 83 Ave NW",
    "sg:city":"Edmonton",
    "sg:classifiers":[
        {
            "category":"Real Estate",
            "subcategory":"Real Estate Operator",
            "type":"Services"
        }
    ],
    "sg:phone":"+1 780 469 1591",
    "sg:postcode":"T6C 1A4",
    "sg:province":"AB",
    "sg:tags":[
        "apartment"
    ],
    "wof:name":"Landus Agencies Ltd",
    "wof:placetype":"venue"
},
  "geometry": {"coordinates":[-113.447761536,53.5192565918],"type":"Point"}
}