{
  "type": "Feature",
  "properties": {
    "addr:full":"3275 6th Ave E Vancouver BC V5M 1S6",
    "addr:housenumber":"3275",
    "addr:postcode":"v5m 1s6",
    "addr:street":"6Th Ave E",
    "iso:country":"CA",
    "sg:address":"3275 6th Ave E",
    "sg:city":"Vancouver",
    "sg:classifiers":[
        {
            "category":"Professional",
            "subcategory":"Business Services",
            "type":"Services"
        }
    ],
    "sg:phone":"+1 604 254 3721",
    "sg:postcode":"V5M 1S6",
    "sg:province":"BC",
    "wof:name":"A & A Trading CO",
    "wof:placetype":"venue"
},
  "geometry": {"coordinates":[-123.034531,49.264904],"type":"Point"}
}