{
  "type": "Feature",
  "properties": {
    "addr:full":"120 Enterprise Dr Yellowknife NT X1A 2P2",
    "addr:housenumber":"120",
    "addr:postcode":"x1a 2p2",
    "addr:street":"Enterprise Dr",
    "iso:country":"CA",
    "sg:address":"120 Enterprise Dr",
    "sg:city":"Yellowknife",
    "sg:classifiers":[
        {
            "category":"Freight",
            "type":"Transportation"
        }
    ],
    "sg:phone":"+1 867 873 2681",
    "sg:postcode":"X1A 2P2",
    "sg:province":"NT",
    "sg:tags":[
        "mover"
    ],
    "wof:name":"Western Moving & Storage Ltd",
    "wof:placetype":"venue"
},
  "geometry": {"coordinates":[-114.427261,62.428574],"type":"Point"}
}