{
  "type": "Feature",
  "properties": {
    "addr:full":"1735 Balaclava St Vancouver BC V6K 4B6",
    "addr:housenumber":"1735",
    "addr:postcode":"v6k 4b6",
    "addr:street":"Balaclava St",
    "iso:country":"CA",
    "sg:address":"1735 Balaclava St",
    "sg:city":"Vancouver",
    "sg:classifiers":[
        {
            "category":"Real Estate",
            "subcategory":"Architect",
            "type":"Services"
        }
    ],
    "sg:phone":"+1 604 734 4003",
    "sg:postcode":"V6K 4B6",
    "sg:province":"BC",
    "wof:name":"Cumberbirch, Neill F",
    "wof:placetype":"venue"
},
  "geometry": {"coordinates":[-123.173858643,49.2707977295],"type":"Point"}
}