{
  "type": "Feature",
  "properties": {
    "addr:full":"11368 Lakeshore Rd W Port Colborne ON L3K 5V4",
    "addr:housenumber":"11368",
    "addr:postcode":"l3k 5v4",
    "addr:street":"Lakeshore Rd W",
    "iso:country":"CA",
    "sg:address":"11368 Lakeshore Rd W",
    "sg:city":"Port Colborne",
    "sg:classifiers":[
        {
            "category":"Shopping",
            "type":"Retail Goods"
        }
    ],
    "sg:phone":"+1 905 835 0332",
    "sg:postcode":"L3K 5V4",
    "sg:province":"ON",
    "sg:tags":[
        "equipment",
        "telephone",
        "supply"
    ],
    "wof:name":"Mac Telephone Svc",
    "wof:placetype":"venue"
},
  "geometry": {"coordinates":[-79.2802658081,42.8738594055],"type":"Point"}
}