{
  "type": "Feature",
  "properties": {
    "addr:full":"571 Rte 138 Les Escoumins QC G0T 1K0",
    "addr:housenumber":"571",
    "addr:postcode":"g0t 1k0",
    "addr:street":"Rte 138",
    "iso:country":"CA",
    "sg:address":"571 Rte 138",
    "sg:city":"Les Escoumins",
    "sg:classifiers":[
        {
            "category":"Health Services",
            "subcategory":"Nursing And Care Facility",
            "type":"Services"
        }
    ],
    "sg:phone":"+1 418 233 2144",
    "sg:postcode":"G0T 1K0",
    "sg:province":"QC",
    "sg:tags":[
        "home",
        "retirement",
        "community"
    ],
    "wof:name":"Hotel Motel Carmen",
    "wof:placetype":"venue"
},
  "geometry": {"coordinates":[-69.35923,48.38195],"type":"Point"}
}