{
  "type": "Feature",
  "properties": {
    "addr:full":"68 Portugal Cove Rd St. John's NL A1B 2L9",
    "addr:housenumber":"68",
    "addr:postcode":"a1b 2l9",
    "addr:street":"Portugal Cove Rd",
    "iso:country":"CA",
    "sg:address":"68 Portugal Cove Rd",
    "sg:city":"St. John's",
    "sg:classifiers":[
        {
            "category":"Insurance",
            "subcategory":"Insurance Agent",
            "type":"Services"
        }
    ],
    "sg:phone":"+1 709 737 1680",
    "sg:postcode":"A1B 2L9",
    "sg:province":"NL",
    "sg:tags":[
        "adjuster"
    ],
    "wof:name":"Unifund Adjusting Inc",
    "wof:placetype":"venue"
},
  "geometry": {"coordinates":[-52.7121772766,47.5810012817],"type":"Point"}
}