{
  "type": "Feature",
  "properties": {
    "addr:full":"PO Box 185 Ceylon SK S0C 0T0",
    "addr:housenumber":"po;185",
    "addr:postcode":"s0c 0t0",
    "addr:street":"Box",
    "iso:country":"CA",
    "sg:address":"PO Box 185",
    "sg:city":"Ceylon",
    "sg:classifiers":[
        {
            "category":"Organizations",
            "subcategory":"Religious Organization",
            "type":"Services"
        }
    ],
    "sg:phone":"+1 306 454 2460",
    "sg:postcode":"S0C 0T0",
    "sg:province":"SK",
    "sg:tags":[
        "church"
    ],
    "wof:name":"Ceylon United Church",
    "wof:placetype":"venue"
},
  "geometry": {"coordinates":[-104.605812073,49.456829071],"type":"Point"}
}