{
  "type": "Feature",
  "properties": {
    "iso:country":"CA",
    "sg:address":"170 Great Lakes Dr",
    "sg:city":"Brampton",
    "sg:classifiers":[
        {
            "category":"Restaurant",
            "type":"Food & Drink"
        }
    ],
    "sg:phone":"+1 905 789 6488",
    "sg:postcode":"L6R 2K7",
    "sg:province":"ON",
    "wof:name":"Montana's Cookhouse Saloon",
    "wof:placetype":"venue"
},
  "geometry": {"coordinates":[-79.764038,43.73254],"type":"Point"}
}