{
  "type": "Feature",
  "properties": {
    "addr:full":"2909 Saskatchewan Dr Regina SK S4T 1H4",
    "addr:housenumber":"2909",
    "addr:postcode":"s4t 1h4",
    "addr:street":"Saskatchewan Dr",
    "iso:country":"CA",
    "sg:address":"2909 Saskatchewan Dr",
    "sg:city":"Regina",
    "sg:classifiers":[
        {
            "category":"Building & Trades",
            "subcategory":"Construction",
            "type":"Services"
        }
    ],
    "sg:phone":"+1 306 352 2434",
    "sg:postcode":"S4T 1H4",
    "sg:province":"SK",
    "sg:tags":[
        "general",
        "contractor"
    ],
    "wof:name":"Westridge Construction Ltd",
    "wof:placetype":"venue"
},
  "geometry": {"coordinates":[-104.622680664,50.4501152039],"type":"Point"}
}