{
  "type": "Feature",
  "properties": {
    "iso:country":"CA",
    "sg:address":"1 James",
    "sg:city":"Iron Bridge",
    "sg:classifiers":[
        {
            "category":"Museum",
            "type":"Entertainment"
        }
    ],
    "sg:phone":"+1 705 843 2336",
    "sg:postcode":"P0R 1H0",
    "sg:province":"ON",
    "sg:tags":[
        "government"
    ],
    "wof:name":"Museum Information",
    "wof:placetype":"venue"
},
  "geometry": {"coordinates":[-83.2174453735,46.2785682678],"type":"Point"}
}