{
  "type": "Feature",
  "properties": {
    "addr:full":"62 Victoria Rd Middleton NS B0S 1P0",
    "addr:housenumber":"62",
    "addr:postcode":"b0s 1p0",
    "addr:street":"Victoria Rd",
    "iso:country":"CA",
    "sg:address":"62 Victoria Rd",
    "sg:city":"Middleton",
    "sg:classifiers":[
        {
            "category":"Retail",
            "subcategory":"Auto Repair",
            "type":"Services"
        }
    ],
    "sg:phone":"+1 902 825 6461",
    "sg:postcode":"B0S 1P0",
    "sg:province":"NS",
    "sg:tags":[
        "automobile",
        "painting",
        "truck"
    ],
    "wof:name":"Day-Nite Auto Body",
    "wof:placetype":"venue"
},
  "geometry": {"coordinates":[-65.07733899999999,44.943966],"type":"Point"}
}