{
  "type": "Feature",
  "properties": {
    "addr:full":"Fox Creek AB T0H 1P0",
    "addr:postcode":"t0h 1p0",
    "iso:country":"CA",
    "sg:city":"Fox Creek",
    "sg:classifiers":[
        {
            "category":"Freight",
            "type":"Transportation"
        }
    ],
    "sg:phone":"+1 780 622 3006",
    "sg:postcode":"T0H 1P0",
    "sg:province":"AB",
    "sg:tags":[
        "field",
        "oil",
        "trucking"
    ],
    "wof:name":"Trottier Trucking Ltd",
    "wof:placetype":"venue"
},
  "geometry": {"coordinates":[-116.795845032,54.3921775818],"type":"Point"}
}