{
  "type": "Feature",
  "properties": {
    "addr:full":"Ottawa ON K1Z 8N8",
    "addr:postcode":"k1z 8n8",
    "iso:country":"CA",
    "sg:city":"Ottawa",
    "sg:classifiers":[
        {
            "category":"Professional",
            "subcategory":"Lawyer & Legal Services",
            "type":"Services"
        }
    ],
    "sg:phone":"+1 613 725 3723",
    "sg:postcode":"K1Z 8N8",
    "sg:province":"ON",
    "sg:tags":[
        "attorney"
    ],
    "wof:name":"Scott & Mc Guire",
    "wof:placetype":"venue"
},
  "geometry": {"coordinates":[-75.73483299999999,45.386009],"type":"Point"}
}