{
  "type": "Feature",
  "properties": {
    "addr:full":"1427 Hunter St North Vancouver BC V7J 1H3",
    "addr:housenumber":"1427",
    "addr:postcode":"v7j 1h3",
    "addr:street":"Hunter St",
    "iso:country":"CA",
    "sg:address":"1427 Hunter St",
    "sg:city":"North Vancouver",
    "sg:classifiers":[
        {
            "category":"Wholesale",
            "subcategory":"Groceries",
            "type":"Manufacturing & Wholesale Goods"
        }
    ],
    "sg:phone":"+1 604 984 0188",
    "sg:postcode":"V7J 1H3",
    "sg:province":"BC",
    "sg:tags":[
        "grocer"
    ],
    "wof:name":"Gourmet Savories & Sweets Inc",
    "wof:placetype":"venue"
},
  "geometry": {"coordinates":[-123.03404998800001,49.3104438782],"type":"Point"}
}