{
  "type": "Feature",
  "properties": {
    "iso:country":"CA",
    "sg:address":"140 Kelsey Blvd",
    "sg:city":"Churchill",
    "sg:classifiers":[
        {
            "category":"Insurance",
            "subcategory":"Insurance Agent",
            "type":"Services"
        }
    ],
    "sg:phone":"+1 204 675 8829",
    "sg:postcode":"R0B 0E0",
    "sg:province":"MB",
    "wof:name":"Hyska's Insurance",
    "wof:placetype":"venue"
},
  "geometry": {"coordinates":[-94.1679534912,58.7691192627],"type":"Point"}
}