{
  "type": "Feature",
  "properties": {
    "addr:full":"24497 Mcmurchy Line West Lorne ON N0L 2P0",
    "addr:housenumber":"24497",
    "addr:postcode":"n0l 2p0",
    "addr:street":"Mcmurchy Line",
    "iso:country":"CA",
    "sg:address":"24497 Mcmurchy Line",
    "sg:city":"West Lorne",
    "sg:classifiers":[
        {
            "category":"Building & Trades",
            "subcategory":"Construction",
            "type":"Services"
        }
    ],
    "sg:phone":"+1 519 768 0813",
    "sg:postcode":"N0L 2P0",
    "sg:province":"ON",
    "sg:tags":[
        "carpenter"
    ],
    "wof:name":"Maple Leaf Custom Carpentry",
    "wof:placetype":"venue"
},
  "geometry": {"coordinates":[-81.6080093384,42.6047134399],"type":"Point"}
}