{
  "type": "Feature",
  "properties": {
    "addr:full":"20 High Point Rd North York ON M3B 2A4",
    "addr:housenumber":"20",
    "addr:postcode":"m3b 2a4",
    "addr:street":"High Point Rd",
    "iso:country":"CA",
    "sg:address":"20 High Point Rd",
    "sg:city":"North York",
    "sg:classifiers":[
        {
            "category":"Building & Trades",
            "subcategory":"Cleaning & Sanitation",
            "type":"Services"
        }
    ],
    "sg:phone":"+1 416 444 8320",
    "sg:postcode":"M3B 2A4",
    "sg:province":"ON",
    "sg:tags":[
        "management",
        "maintenance",
        "real estate",
        "property"
    ],
    "wof:name":"Kwan & Kwan Ltd",
    "wof:placetype":"venue"
},
  "geometry": {"coordinates":[-79.369637,43.733238],"type":"Point"}
}