{
  "type": "Feature",
  "properties": {
    "iso:country":"CA",
    "sg:address":"7639 Rue Centrale",
    "sg:city":"Lasalle",
    "sg:classifiers":[
        {
            "category":"Personal",
            "subcategory":"Beauty Salon",
            "type":"Services"
        }
    ],
    "sg:phone":"+1 514 363 6274",
    "sg:postcode":"H8P 1L2",
    "sg:province":"QC",
    "wof:name":"Coiffure Essima",
    "wof:placetype":"venue"
},
  "geometry": {"coordinates":[-73.59796142579999,45.4313926697],"type":"Point"}
}