{
  "type": "Feature",
  "properties": {
    "iso:country":"CA",
    "sg:address":"5629 Rue Ferrier",
    "sg:city":"Mont-Royal",
    "sg:classifiers":[
        {
            "category":"Wholesale",
            "subcategory":"Stationery",
            "type":"Manufacturing & Wholesale Goods"
        }
    ],
    "sg:phone":"+1 514 735 1317",
    "sg:postcode":"H4P 1N1",
    "sg:province":"QC",
    "sg:tags":[
        "business",
        "form",
        "system"
    ],
    "wof:name":"Formules Bch Ltee",
    "wof:placetype":"venue"
},
  "geometry": {"coordinates":[-73.66551971440001,45.4916152954],"type":"Point"}
}