{
  "type": "Feature",
  "properties": {
    "addr:full":"970 Rue Saint-Antoine Joliette QC J6E 3S9",
    "addr:housenumber":"970",
    "addr:postcode":"j6e 3s9",
    "addr:street":"Rue Saint-Antoine",
    "iso:country":"CA",
    "sg:address":"970 Rue Saint-Antoine",
    "sg:city":"Joliette",
    "sg:classifiers":[
        {
            "category":"Real Estate",
            "subcategory":"Architect",
            "type":"Services"
        }
    ],
    "sg:phone":"+1 450 759 3093",
    "sg:postcode":"J6E 3S9",
    "sg:province":"QC",
    "wof:name":"Michel Tellier Inc",
    "wof:placetype":"venue"
},
  "geometry": {"coordinates":[-73.44473266599999,46.016456604],"type":"Point"}
}