{
  "type": "Feature",
  "properties": {
    "addr:full":"Repentigny QC J6A 2P8",
    "addr:postcode":"j6a 2p8",
    "iso:country":"CA",
    "sg:city":"Repentigny",
    "sg:classifiers":[
        {
            "category":"Health Services",
            "subcategory":"Optometrist",
            "type":"Services"
        }
    ],
    "sg:phone":"+1 450 581 8700",
    "sg:postcode":"J6A 2P8",
    "sg:province":"QC",
    "wof:name":"Lapierre, Sebastien OD",
    "wof:placetype":"venue"
},
  "geometry": {"coordinates":[-73.46854399999999,45.718182],"type":"Point"}
}