{
  "type": "Feature",
  "properties": {
    "iso:country":"CA",
    "sg:address":"1588 Bayview Ave",
    "sg:city":"Toronto",
    "sg:classifiers":[
        {
            "category":"Shopping",
            "subcategory":"Used Merchandise",
            "type":"Retail Goods"
        }
    ],
    "sg:phone":"+1 416 322 9744",
    "sg:postcode":"M4G 3B7",
    "sg:province":"ON",
    "sg:tags":[
        "antique"
    ],
    "wof:name":"Elegant Garage Sale",
    "wof:placetype":"venue"
},
  "geometry": {"coordinates":[-79.375381,43.705837],"type":"Point"}
}