{
  "type": "Feature",
  "properties": {
    "addr:full":"7620 Yonge St Thornhill ON L4J 1V9",
    "addr:housenumber":"7620",
    "addr:postcode":"l4j 1v9",
    "addr:street":"Yonge St",
    "iso:country":"CA",
    "sg:address":"7620 Yonge St",
    "sg:city":"Thornhill",
    "sg:classifiers":[
        {
            "category":"Banks & Credit Unions",
            "subcategory":"Investment Brokerage",
            "type":"Services"
        }
    ],
    "sg:phone":"+1 905 731 9800",
    "sg:postcode":"L4J 1V9",
    "sg:province":"ON",
    "sg:tags":[
        "consultant",
        "planning",
        "financial"
    ],
    "wof:name":"DE Thomas Financial Corp",
    "wof:placetype":"venue"
},
  "geometry": {"coordinates":[-79.42394299999999,43.813076],"type":"Point"}
}