{
  "type": "Feature",
  "properties": {
    "addr:full":"3334 30 Ave # 105 Vernon BC V1T 2C8",
    "addr:housenumber":"3334",
    "addr:postcode":"v1t 2c8",
    "addr:street":"30 Ave # 105",
    "iso:country":"CA",
    "sg:address":"3334 30 Ave # 105",
    "sg:city":"Vernon",
    "sg:classifiers":[
        {
            "category":"Manufacturing",
            "subcategory":"Food",
            "type":"Manufacturing & Wholesale Goods"
        }
    ],
    "sg:phone":"+1 250 503 2535",
    "sg:postcode":"V1T 2C8",
    "sg:province":"BC",
    "sg:tags":[
        "cocoa",
        "chocolate"
    ],
    "wof:name":"Cottons Chocolates",
    "wof:placetype":"venue"
},
  "geometry": {"coordinates":[-119.27583300000001,50.26355],"type":"Point"}
}