{
  "type": "Feature",
  "properties": {
    "addr:full":"London ON N6M 1A1",
    "addr:postcode":"n6m 1a1",
    "iso:country":"CA",
    "sg:city":"London",
    "sg:classifiers":[
        {
            "category":"Home & Garden",
            "subcategory":"Building Materials",
            "type":"Retail Goods"
        }
    ],
    "sg:phone":"+1 519 659 0438",
    "sg:postcode":"N6M 1A1",
    "sg:province":"ON",
    "sg:tags":[
        "door"
    ],
    "wof:name":"London Door Svc",
    "wof:placetype":"venue"
},
  "geometry": {"coordinates":[-81.1379165649,42.9909934998],"type":"Point"}
}