{
  "type": "Feature",
  "properties": {
    "addr:full":"8237 Swenson Way Delta BC V4G 1J5",
    "addr:housenumber":"8237",
    "addr:postcode":"v4g 1j5",
    "addr:street":"Swenson Way",
    "iso:country":"CA",
    "sg:address":"8237 Swenson Way",
    "sg:city":"Delta",
    "sg:classifiers":[
        {
            "category":"Wholesale",
            "subcategory":"Groceries",
            "type":"Manufacturing & Wholesale Goods"
        }
    ],
    "sg:phone":"+1 604 584 5417",
    "sg:postcode":"V4G 1J5",
    "sg:province":"BC",
    "sg:tags":[
        "tea",
        "coffee"
    ],
    "wof:name":"Gold Cup Coffee CO Ltd",
    "wof:placetype":"venue"
},
  "geometry": {"coordinates":[-122.94092559800001,49.1500511169],"type":"Point"}
}