{
  "type": "Feature",
  "properties": {
    "addr:full":"178 Butler Rd Surrey BC V4N 4R1",
    "addr:housenumber":"178",
    "addr:postcode":"v4n 4r1",
    "addr:street":"Butler Rd",
    "iso:country":"CA",
    "sg:address":"178 Butler Rd",
    "sg:city":"Surrey",
    "sg:classifiers":[
        {
            "category":"Wholesale",
            "subcategory":"Fruits & Vegetables",
            "type":"Manufacturing & Wholesale Goods"
        }
    ],
    "sg:phone":"+1 604 581 4374",
    "sg:postcode":"V4N 4R1",
    "sg:province":"BC",
    "sg:tags":[
        "shipper"
    ],
    "wof:name":"Opus Cranberries",
    "wof:placetype":"venue"
},
  "geometry": {"coordinates":[-122.830215,49.105179],"type":"Point"}
}