{
  "type": "Feature",
  "properties": {
    "addr:full":"1114 Queen St Smithers BC V0J 2N0",
    "addr:housenumber":"1114",
    "addr:postcode":"v0j 2n0",
    "addr:street":"Queen St",
    "iso:country":"CA",
    "sg:address":"1114 Queen St",
    "sg:city":"Smithers",
    "sg:classifiers":[
        {
            "category":"Food & Beverages",
            "subcategory":"Liquor & Beverages",
            "type":"Retail Goods"
        }
    ],
    "sg:phone":"+1 250 847 7408",
    "sg:postcode":"V0J 2N0",
    "sg:province":"BC",
    "sg:tags":[
        "store"
    ],
    "wof:name":"Smithers Liquor Store",
    "wof:placetype":"venue"
},
  "geometry": {"coordinates":[-127.17439299999999,54.780666],"type":"Point"}
}