{
  "type": "Feature",
  "properties": {
    "addr:full":"709 St Mary's Rd Winnipeg MB R2M 3M8",
    "addr:housenumber":"709",
    "addr:postcode":"r2m 3m8",
    "addr:street":"St Mary'S Rd",
    "iso:country":"CA",
    "sg:address":"709 St Mary's Rd",
    "sg:city":"Winnipeg",
    "sg:classifiers":[
        {
            "category":"Organizations",
            "subcategory":"Religious Organization",
            "type":"Services"
        }
    ],
    "sg:phone":"+1 204 256 2413",
    "sg:postcode":"R2M 3M8",
    "sg:province":"MB",
    "sg:tags":[
        "church"
    ],
    "wof:name":"St Andrew's Presbyterian Chr",
    "wof:placetype":"venue"
},
  "geometry": {"coordinates":[-97.111946106,49.8565101624],"type":"Point"}
}