{
  "type": "Feature",
  "properties": {
    "addr:full":"6063 Boul Henri-Bourassa E Montreal-Nord QC H1G 2V2",
    "addr:housenumber":"6063",
    "addr:postcode":"h1g 2v2",
    "addr:street":"Boul Henri-Bourassa E",
    "iso:country":"CA",
    "sg:address":"6063 Boul Henri-Bourassa E",
    "sg:city":"Montreal-Nord",
    "sg:classifiers":[
        {
            "category":"Professional",
            "subcategory":"Accounting & Tax Preparation",
            "type":"Services"
        }
    ],
    "sg:phone":"+1 514 328 7979",
    "sg:postcode":"H1G 2V2",
    "sg:province":"QC",
    "sg:tags":[
        "return",
        "filing"
    ],
    "wof:name":"H & R Block Canada Inc",
    "wof:placetype":"venue"
},
  "geometry": {"coordinates":[-73.61608099999999,45.608215],"type":"Point"}
}