{
  "type": "Feature",
  "properties": {
    "addr:full":"Oliver BC V0H 1T0",
    "addr:postcode":"bc v0h 1t0",
    "iso:country":"CA",
    "sg:city":"Oliver",
    "sg:classifiers":[
        {
            "category":"Education",
            "subcategory":"School",
            "type":"Public Place"
        }
    ],
    "sg:phone":"+1 250 498 2019",
    "sg:postcode":"V0H 1T0",
    "sg:province":"BC",
    "wof:name":"Sen'Pok'Chin School",
    "wof:placetype":"venue"
},
  "geometry": {"coordinates":[-119.536942,49.18449],"type":"Point"}
}