{
  "type": "Feature",
  "properties": {
    "addr:full":"Rawdon QC J0K 1S0",
    "addr:postcode":"j0k 1s0",
    "iso:country":"CA",
    "sg:city":"Rawdon",
    "sg:classifiers":[
        {
            "category":"Shopping",
            "type":"Retail Goods"
        }
    ],
    "sg:phone":"+1 450 834 8455",
    "sg:postcode":"J0K 1S0",
    "sg:province":"QC",
    "sg:tags":[
        "pet",
        "shop"
    ],
    "wof:name":"Animaleire Rawdon",
    "wof:placetype":"venue"
},
  "geometry": {"coordinates":[-73.6941986084,46.041229248],"type":"Point"}
}