{
  "type": "Feature",
  "properties": {
    "addr:full":"Fredericton NB E3B 1B6",
    "addr:postcode":"e3b 1b6",
    "iso:country":"CA",
    "sg:city":"Fredericton",
    "sg:classifiers":[
        {
            "category":"Professional",
            "subcategory":"Lawyer & Legal Services",
            "type":"Services"
        }
    ],
    "sg:phone":"+1 506 460 5248",
    "sg:postcode":"E3B 1B6",
    "sg:province":"NB",
    "sg:tags":[
        "attorney"
    ],
    "wof:name":"Richmond, George",
    "wof:placetype":"venue"
},
  "geometry": {"coordinates":[-66.6413803101,45.9621124268],"type":"Point"}
}