{
  "type": "Feature",
  "properties": {
    "addr:full":"370 Dixon Rd # 511 Etobicoke ON M9R 1T2",
    "addr:housenumber":"370",
    "addr:postcode":"m9r 1t2",
    "addr:street":"Dixon Rd # 511",
    "iso:country":"CA",
    "sg:address":"370 Dixon Rd # 511",
    "sg:city":"Etobicoke",
    "sg:classifiers":[
        {
            "category":"Health Services",
            "subcategory":"Nursing And Care Facility",
            "type":"Services"
        }
    ],
    "sg:phone":"+1 416 245 3133",
    "sg:postcode":"M9R 1T2",
    "sg:province":"ON",
    "sg:tags":[
        "home",
        "retirement",
        "community"
    ],
    "wof:name":"New Haven Rest Home Inc",
    "wof:placetype":"venue"
},
  "geometry": {"coordinates":[-79.556358,43.694977],"type":"Point"}
}