{
  "type": "Feature",
  "properties": {
    "addr:full":"1 Mount Bernard Ave Corner Brook NL A2H 6Y5",
    "addr:housenumber":"1",
    "addr:postcode":"a2h 6y5",
    "addr:street":"Mount Bernard Ave",
    "iso:country":"CA",
    "sg:address":"1 Mount Bernard Ave",
    "sg:city":"Corner Brook",
    "sg:classifiers":[
        {
            "category":"Professional",
            "subcategory":"Accounting & Tax Preparation",
            "type":"Services"
        }
    ],
    "sg:phone":"+1 709 634 0209",
    "sg:postcode":"A2H 6Y5",
    "sg:province":"NL",
    "sg:tags":[
        "return",
        "filing"
    ],
    "wof:name":"Liberty Tax Svc",
    "wof:placetype":"venue"
},
  "geometry": {"coordinates":[-57.9499664307,48.9511604309],"type":"Point"}
}