{
  "type": "Feature",
  "properties": {
    "addr:full":"2209 20th St Delburne AB T0M 0V0",
    "addr:housenumber":"2209",
    "addr:postcode":"t0m 0v0",
    "addr:street":"20Th St",
    "iso:country":"CA",
    "sg:address":"2209 20th St",
    "sg:city":"Delburne",
    "sg:classifiers":[
        {
            "category":"Banks & Credit Unions",
            "subcategory":"Bank",
            "type":"Services"
        }
    ],
    "sg:phone":"+1 403 749 3937",
    "sg:postcode":"T0M 0V0",
    "sg:province":"AB",
    "wof:name":"Community Savings",
    "wof:placetype":"venue"
},
  "geometry": {"coordinates":[-113.230789,52.198959],"type":"Point"}
}