{
  "type": "Feature",
  "properties": {
    "addr:full":"Tweed ON K0K 3J0",
    "addr:postcode":"k0k 3j0",
    "iso:country":"CA",
    "sg:city":"Tweed",
    "sg:classifiers":[
        {
            "category":"Food & Beverages",
            "subcategory":"Specialty",
            "type":"Retail Goods"
        }
    ],
    "sg:phone":"+1 613 478 2828",
    "sg:postcode":"K0K 3J0",
    "sg:province":"ON",
    "sg:tags":[
        "eggs"
    ],
    "wof:name":"Drain Poultry Farm",
    "wof:placetype":"venue"
},
  "geometry": {"coordinates":[-77.344925,44.378323],"type":"Point"}
}