{
  "type": "Feature",
  "properties": {
    "addr:full":"Richmond BC V6V 1Y6",
    "addr:postcode":"v6v 1y6",
    "iso:country":"CA",
    "sg:city":"Richmond",
    "sg:classifiers":[
        {
            "category":"Wholesale",
            "subcategory":"Machinery & Supplies",
            "type":"Manufacturing & Wholesale Goods"
        }
    ],
    "sg:phone":"+1 604 270 1691",
    "sg:postcode":"V6V 1Y6",
    "sg:province":"BC",
    "sg:tags":[
        "rope"
    ],
    "wof:name":"Canada Cordage Inc",
    "wof:placetype":"venue"
},
  "geometry": {"coordinates":[-123.08010899999999,49.186531],"type":"Point"}
}