{
  "type": "Feature",
  "properties": {
    "addr:full":"2 Jellicoe Dr St Catharines ON L2N 6J2",
    "addr:housenumber":"2",
    "addr:postcode":"l2n 6j2",
    "addr:street":"Jellicoe Dr",
    "iso:country":"CA",
    "sg:address":"2 Jellicoe Dr",
    "sg:city":"St Catharines",
    "sg:classifiers":[
        {
            "category":"Manufacturing",
            "subcategory":"Printing",
            "type":"Manufacturing & Wholesale Goods"
        }
    ],
    "sg:phone":"+1 905 935 8807",
    "sg:postcode":"L2N 6J2",
    "sg:province":"ON",
    "sg:tags":[
        "printer"
    ],
    "wof:name":"Mem Quality Printing",
    "wof:placetype":"venue"
},
  "geometry": {"coordinates":[-79.24993896479999,43.2044410706],"type":"Point"}
}