{
  "type": "Feature",
  "properties": {
    "addr:full":"766 Hemsworth Rd Qualicum Beach BC V9K 1R1",
    "addr:housenumber":"766",
    "addr:postcode":"v9k 1r1",
    "addr:street":"Hemsworth Rd",
    "iso:country":"CA",
    "sg:address":"766 Hemsworth Rd",
    "sg:city":"Qualicum Beach",
    "sg:classifiers":[
        {
            "category":"Building & Trades",
            "subcategory":"Construction",
            "type":"Services"
        }
    ],
    "sg:phone":"+1 250 752 6420",
    "sg:postcode":"V9K 1R1",
    "sg:province":"BC",
    "sg:tags":[
        "general",
        "contractor"
    ],
    "wof:name":"Willow Lane Construction Ltd",
    "wof:placetype":"venue"
},
  "geometry": {"coordinates":[-124.42804700000001,49.345325],"type":"Point"}
}