{
  "type": "Feature",
  "properties": {
    "addr:full":"Picton ON K0K 2T0",
    "addr:postcode":"k0k 2t0",
    "iso:country":"CA",
    "sg:city":"Picton",
    "sg:classifiers":[
        {
            "category":"Manufacturing",
            "subcategory":"Signs",
            "type":"Manufacturing & Wholesale Goods"
        }
    ],
    "sg:phone":"+1 613 476 9888",
    "sg:postcode":"K0K 2T0",
    "sg:province":"ON",
    "wof:name":"Island Signs",
    "wof:placetype":"venue"
},
  "geometry": {"coordinates":[-77.1395568848,44.0163917542],"type":"Point"}
}