{
  "type": "Feature",
  "properties": {
    "iso:country":"CA",
    "sg:address":"400 Hayimiisaxaa Way",
    "sg:city":"Hartley Bay",
    "sg:classifiers":[
        {
            "category":"Government",
            "subcategory":"Fire Station",
            "type":"Public Place"
        }
    ],
    "sg:phone":"+1 ",
    "sg:postcode":"V0V 1A0",
    "sg:province":"BC",
    "sg:tags":[
        "department"
    ],
    "wof:name":"Hartley Bay Fire Department",
    "wof:placetype":"venue"
},
  "geometry": {"coordinates":[-129.253509522,53.4239196777],"type":"Point"}
}