{
  "type": "Feature",
  "properties": {
    "iso:country":"CA",
    "sg:city":"Markham",
    "sg:classifiers":[
        {
            "category":"Retail",
            "subcategory":"Laundry & Dry Cleaning",
            "type":"Services"
        }
    ],
    "sg:phone":"+1 905 513 6555",
    "sg:postcode":"L3R 2R7",
    "sg:province":"ON",
    "sg:tags":[
        "cleaners",
        "rug",
        "carpet"
    ],
    "wof:name":"Mft Specialty Cleaning Inc",
    "wof:placetype":"venue"
},
  "geometry": {"coordinates":[-79.3398361206,43.8275680542],"type":"Point"}
}