{
  "type": "Feature",
  "properties": {
    "addr:full":"109 George St Hamilton ON L8P 1E3",
    "addr:housenumber":"109",
    "addr:postcode":"l8p 1e3",
    "addr:street":"George St",
    "iso:country":"CA",
    "sg:address":"109 George St",
    "sg:city":"Hamilton",
    "sg:classifiers":[
        {
            "category":"Restaurant",
            "type":"Food & Drink"
        }
    ],
    "sg:phone":"+1 905 529 6199",
    "sg:postcode":"L8P 1E3",
    "sg:province":"ON",
    "wof:name":"Smooth Herman's Bar & Grill",
    "wof:placetype":"venue"
},
  "geometry": {"coordinates":[-79.8786621094,43.2581863403],"type":"Point"}
}