{
  "type": "Feature",
  "properties": {
    "addr:full":"2300 Rue Nicolet Montreal QC H1W 3L4",
    "addr:housenumber":"2300",
    "addr:postcode":"h1w 3l4",
    "addr:street":"Rue Nicolet",
    "iso:country":"CA",
    "sg:address":"2300 Rue Nicolet",
    "sg:city":"Montreal",
    "sg:classifiers":[
        {
            "category":"Health Services",
            "subcategory":"Nursing And Care Facility",
            "type":"Services"
        }
    ],
    "sg:phone":"+1 514 527 2161",
    "sg:postcode":"H1W 3L4",
    "sg:province":"QC",
    "sg:tags":[
        "home",
        "rest"
    ],
    "wof:name":"Chsld Lucille Teasdale",
    "wof:placetype":"venue"
},
  "geometry": {"coordinates":[-73.5478210449,45.5474662781],"type":"Point"}
}