{
  "type": "Feature",
  "properties": {
    "addr:full":"1075 Denman St Vancouver BC V6G 2M7",
    "addr:housenumber":"1075",
    "addr:postcode":"v6g 2m7",
    "addr:street":"Denman St",
    "iso:country":"CA",
    "sg:address":"1075 Denman St",
    "sg:city":"Vancouver",
    "sg:classifiers":[
        {
            "category":"Retail",
            "subcategory":"Laundry & Dry Cleaning",
            "type":"Services"
        }
    ],
    "sg:phone":"+1 604 683 8914",
    "sg:postcode":"V6G 2M7",
    "sg:province":"BC",
    "sg:tags":[
        "cleaners"
    ],
    "wof:name":"Denman Cleantec",
    "wof:placetype":"venue"
},
  "geometry": {"coordinates":[-123.14020538299999,49.2885322571],"type":"Point"}
}