{
  "type": "Feature",
  "properties": {
    "addr:full":"114 Main St S Mount Forest ON N0G 2L0",
    "addr:housenumber":"114",
    "addr:postcode":"n0g 2l0",
    "addr:street":"Main St S Mount",
    "iso:country":"CA",
    "sg:address":"114 Main St S",
    "sg:city":"Mount Forest",
    "sg:classifiers":[
        {
            "category":"Insurance",
            "subcategory":"Insurance Agent",
            "type":"Services"
        }
    ],
    "sg:phone":"+1 519 323 2841",
    "sg:postcode":"N0G 2L0",
    "sg:province":"ON",
    "wof:name":"Cockburn Insurance Brokers Ltd",
    "wof:placetype":"venue"
},
  "geometry": {"coordinates":[-80.7350387573,43.981590271],"type":"Point"}
}