{
  "type": "Feature",
  "properties": {
    "addr:full":"105 Judge Rd Etobicoke ON M8Z 5B5",
    "addr:housenumber":"105",
    "addr:postcode":"m8z 5b5",
    "addr:street":"Judge Rd",
    "iso:country":"CA",
    "sg:address":"105 Judge Rd",
    "sg:city":"Etobicoke",
    "sg:classifiers":[
        {
            "category":"Shopping",
            "type":"Retail Goods"
        }
    ],
    "sg:phone":"+1 416 252 6888",
    "sg:postcode":"M8Z 5B5",
    "sg:province":"ON",
    "sg:tags":[
        "orthopedic",
        "appliance"
    ],
    "wof:name":"Total Applied Biomechanic",
    "wof:placetype":"venue"
},
  "geometry": {"coordinates":[-79.530373,43.636936],"type":"Point"}
}