{
  "type": "Feature",
  "properties": {
    "addr:full":"7760 Rue Sherbrooke E Montreal QC H1L 1A5",
    "addr:housenumber":"7760",
    "addr:postcode":"h1l 1a5",
    "addr:street":"Rue Sherbrooke E",
    "iso:country":"CA",
    "sg:address":"7760 Rue Sherbrooke E",
    "sg:city":"Montreal",
    "sg:classifiers":[
        {
            "category":"Cinema",
            "subcategory":"Movie Rental",
            "type":"Entertainment"
        }
    ],
    "sg:phone":"+1 514 353 1222",
    "sg:postcode":"H1L 1A5",
    "sg:province":"QC",
    "sg:tags":[
        "leasing",
        "video",
        "disc",
        "tape"
    ],
    "wof:name":"Blockbuster Video",
    "wof:placetype":"venue"
},
  "geometry": {"coordinates":[-73.535904,45.594517],"type":"Point"}
}