{
  "type": "Feature",
  "properties": {
    "addr:full":"329 Welland Ave St Catharines ON L2R 2R2",
    "addr:housenumber":"329",
    "addr:postcode":"l2r 2r2",
    "addr:street":"Welland Ave",
    "iso:country":"CA",
    "sg:address":"329 Welland Ave",
    "sg:city":"St Catharines",
    "sg:classifiers":[
        {
            "category":"Recreation",
            "type":"Entertainment"
        }
    ],
    "sg:phone":"+1 905 984 2160",
    "sg:postcode":"L2R 2R2",
    "sg:province":"ON",
    "sg:tags":[
        "diving",
        "instruction"
    ],
    "wof:name":"Dan's Dive Shop Inc",
    "wof:placetype":"venue"
},
  "geometry": {"coordinates":[-79.227097,43.170525],"type":"Point"}
}