{
  "type": "Feature",
  "properties": {
    "iso:country":"CA",
    "sg:city":"Vancouver",
    "sg:classifiers":[
        {
            "category":"Real Estate",
            "subcategory":"Real Estate Agent",
            "type":"Services"
        }
    ],
    "sg:phone":"+1 604 430 4522",
    "sg:postcode":"V5R 5K2",
    "sg:province":"BC",
    "wof:name":"Realtrust Real Estate Corp",
    "wof:placetype":"venue"
},
  "geometry": {"coordinates":[-123.038604736,49.2354507446],"type":"Point"}
}