{
  "type": "Feature",
  "properties": {
    "addr:full":"365 River Oak Pl Waterloo ON N2K 3N8",
    "addr:housenumber":"365",
    "addr:postcode":"n2k 3n8",
    "addr:street":"River Oak Pl",
    "iso:country":"CA",
    "sg:address":"365 River Oak Pl",
    "sg:city":"Waterloo",
    "sg:classifiers":[
        {
            "category":"Wholesale",
            "subcategory":"Plants",
            "type":"Manufacturing & Wholesale Goods"
        }
    ],
    "sg:phone":"+1 519 744 2626",
    "sg:postcode":"N2K 3N8",
    "sg:province":"ON",
    "sg:tags":[
        "florist"
    ],
    "wof:name":"S C Imports",
    "wof:placetype":"venue"
},
  "geometry": {"coordinates":[-80.481262,43.502277],"type":"Point"}
}