{
  "type": "Feature",
  "properties": {
    "iso:country":"CA",
    "sg:city":"Coquitlam",
    "sg:classifiers":[
        {
            "category":"Insurance",
            "subcategory":"Insurance Agent",
            "type":"Services"
        }
    ],
    "sg:phone":"+1 604 942 3555",
    "sg:postcode":"V3E 1J7",
    "sg:province":"BC",
    "wof:name":"Eagleridge Insurance",
    "wof:placetype":"venue"
},
  "geometry": {"coordinates":[-122.809623718,49.2839317322],"type":"Point"}
}