{
  "type": "Feature",
  "properties": {
    "addr:full":"Orillia ON L3V 6H7",
    "addr:postcode":"l3v 6h7",
    "iso:country":"CA",
    "sg:city":"Orillia",
    "sg:classifiers":[
        {
            "category":"Recreation",
            "subcategory":"Marina",
            "type":"Entertainment"
        }
    ],
    "sg:phone":"+1 705 325 3051",
    "sg:postcode":"L3V 6H7",
    "sg:province":"ON",
    "wof:name":"Marina Del Rey",
    "wof:placetype":"venue"
},
  "geometry": {"coordinates":[-79.3902511597,44.6028594971],"type":"Point"}
}