{
  "type": "Feature",
  "properties": {
    "addr:full":"191 Caldari Rd #1A Concord ON L4K 4A1",
    "addr:housenumber":"191",
    "addr:postcode":"l4k 4a1",
    "addr:street":"Caldari Rd # 1A",
    "iso:country":"CA",
    "sg:address":"191 Caldari Rd #1A",
    "sg:city":"Concord",
    "sg:classifiers":[
        {
            "category":"Retail",
            "subcategory":"Auto Repair",
            "type":"Services"
        }
    ],
    "sg:phone":"+1 905 738 5984",
    "sg:postcode":"L4K 4A1",
    "sg:province":"ON",
    "sg:tags":[
        "automobile",
        "top",
        "upholstery"
    ],
    "wof:name":"Ravencraft Limited",
    "wof:placetype":"venue"
},
  "geometry": {"coordinates":[-79.52887,43.82222],"type":"Point"}
}