{
  "type": "Feature",
  "properties": {
    "addr:full":"315 Oxbow Cres Mississauga ON L4Z 2S4",
    "addr:housenumber":"315",
    "addr:postcode":"l4z 2s4",
    "addr:street":"Oxbow Cres",
    "iso:country":"CA",
    "sg:address":"315 Oxbow Cres",
    "sg:city":"Mississauga",
    "sg:classifiers":[
        {
            "category":"Insurance",
            "subcategory":"Insurance Agent",
            "type":"Services"
        }
    ],
    "sg:phone":"+1 905 890 0998",
    "sg:postcode":"L4Z 2S4",
    "sg:province":"ON",
    "wof:name":"Gene Meyer Insurance Ltd",
    "wof:placetype":"venue"
},
  "geometry": {"coordinates":[-79.6402130127,43.6094245911],"type":"Point"}
}