{
  "type": "Feature",
  "properties": {
    "addr:full":"22 Rue Saint-Laurent Riviere-Du-Loup QC G5R 4W5",
    "addr:housenumber":"22",
    "addr:postcode":"g5r 4w5",
    "addr:street":"Rue Saint-Laurent",
    "iso:country":"CA",
    "sg:address":"22 Rue Saint-Laurent",
    "sg:city":"Riviere-Du-Loup",
    "sg:classifiers":[
        {
            "category":"Health Services",
            "subcategory":"Clinic",
            "type":"Services"
        }
    ],
    "sg:phone":"+1 418 867 2642",
    "sg:postcode":"G5R 4W5",
    "sg:province":"QC",
    "sg:tags":[
        "social",
        "home",
        "welfare",
        "organization"
    ],
    "wof:name":"Clsc Rivieres & Marees",
    "wof:placetype":"venue"
},
  "geometry": {"coordinates":[-69.5366439819,47.8299636841],"type":"Point"}
}