{
  "type": "Feature",
  "properties": {
    "addr:full":"1390 Fielding Rd Nanaimo BC V9X 1K8",
    "addr:housenumber":"1390",
    "addr:postcode":"v9x 1k8",
    "addr:street":"Fielding Rd",
    "iso:country":"CA",
    "sg:address":"1390 Fielding Rd",
    "sg:city":"Nanaimo",
    "sg:classifiers":[
        {
            "category":"Building & Trades",
            "subcategory":"Construction",
            "type":"Services"
        }
    ],
    "sg:phone":"+1 250 722 3879",
    "sg:postcode":"V9X 1K8",
    "sg:province":"BC",
    "sg:tags":[
        "contractor"
    ],
    "wof:name":"Bill's Carpentry & Woodwork",
    "wof:placetype":"venue"
},
  "geometry": {"coordinates":[-123.909882,49.1301],"type":"Point"}
}