{
  "type": "Feature",
  "properties": {
    "addr:full":"626 Boul Rene-Levesque O Quebec QC G1S 1S8",
    "addr:housenumber":"626",
    "addr:postcode":"g1s 1s8",
    "addr:street":"Boul Rene-Levesque O",
    "iso:country":"CA",
    "sg:address":"626 Boul Rene-Levesque O",
    "sg:city":"Quebec",
    "sg:classifiers":[
        {
            "category":"Health Services",
            "subcategory":"Health Practitioner",
            "type":"Services"
        }
    ],
    "sg:phone":"+1 418 686 3083",
    "sg:postcode":"G1S 1S8",
    "sg:province":"QC",
    "sg:tags":[
        "psychologist"
    ],
    "wof:name":"Fournier, Michele",
    "wof:placetype":"venue"
},
  "geometry": {"coordinates":[-71.218025,46.809078],"type":"Point"}
}