{
  "type": "Feature",
  "properties": {
    "addr:full":"1141 5th St E Saskatoon SK S7H 1H4",
    "addr:housenumber":"1141",
    "addr:postcode":"s7h 1h4",
    "addr:street":"5Th St E",
    "iso:country":"CA",
    "sg:address":"1141 5th St E",
    "sg:city":"Saskatoon",
    "sg:classifiers":[
        {
            "category":"Organizations",
            "subcategory":"Religious Organization",
            "type":"Services"
        }
    ],
    "sg:phone":"+1 306 343 6085",
    "sg:postcode":"S7H 1H4",
    "sg:province":"SK",
    "sg:tags":[
        "church"
    ],
    "wof:name":"Bethel United Church",
    "wof:placetype":"venue"
},
  "geometry": {"coordinates":[-106.64278400000001,52.112129],"type":"Point"}
}