{
  "type": "Feature",
  "properties": {
    "addr:full":"2801 Highway 2 Berwick NS B0P 1E0",
    "addr:housenumber":"2801",
    "addr:postcode":"b0p 1e0",
    "addr:street":"Highway 2",
    "iso:country":"CA",
    "sg:address":"2801 Highway 2",
    "sg:city":"Berwick",
    "sg:classifiers":[
        {
            "category":"Building & Trades",
            "subcategory":"Construction",
            "type":"Services"
        }
    ],
    "sg:phone":"+1 902 758 3750",
    "sg:postcode":"B0P 1E0",
    "sg:province":"NS",
    "sg:tags":[
        "drainage",
        "contractor"
    ],
    "wof:name":"Atlantic Land Drainage",
    "wof:placetype":"venue"
},
  "geometry": {"coordinates":[-64.7377243042,45.0498161316],"type":"Point"}
}