{
  "type": "Feature",
  "properties": {
    "addr:full":"1st Ave W Consul SK S0N 0P0",
    "addr:postcode":"s0n 0p0",
    "addr:street":"1St Ave W Consul",
    "iso:country":"CA",
    "sg:address":"1st Ave W",
    "sg:city":"Consul",
    "sg:classifiers":[
        {
            "category":"Mining & Drilling",
            "type":"Manufacturing & Wholesale Goods"
        }
    ],
    "sg:phone":"+1 306 299 4849",
    "sg:postcode":"S0N 0P0",
    "sg:province":"SK",
    "sg:tags":[
        "oil",
        "well"
    ],
    "wof:name":"Chris-Nick Oilfield Svc Ltd",
    "wof:placetype":"venue"
},
  "geometry": {"coordinates":[-109.520584,49.294289],"type":"Point"}
}