{
  "type": "Feature",
  "properties": {
    "addr:full":"16618 109 Ave NW Edmonton AB T5P 1C2",
    "addr:housenumber":"16618",
    "addr:postcode":"t5p 1c2",
    "addr:street":"109 Ave Nw",
    "iso:country":"CA",
    "sg:address":"16618 109 Ave NW",
    "sg:city":"Edmonton",
    "sg:classifiers":[
        {
            "category":"Food & Beverages",
            "subcategory":"Liquor & Beverages",
            "type":"Retail Goods"
        }
    ],
    "sg:phone":"+1 780 444 1011",
    "sg:postcode":"T5P 1C2",
    "sg:province":"AB",
    "sg:tags":[
        "store"
    ],
    "wof:name":"Mayfield Vendors Liquor Store",
    "wof:placetype":"venue"
},
  "geometry": {"coordinates":[-113.60647582999999,53.5560874939],"type":"Point"}
}