{
  "type": "Feature",
  "properties": {
    "iso:country":"CA",
    "sg:address":"21 Swiftdale Pl",
    "sg:city":"North York",
    "sg:classifiers":[
        {
            "category":"Real Estate",
            "subcategory":"Real Estate Agent",
            "type":"Services"
        }
    ],
    "sg:phone":"+1 416 493 3232",
    "sg:postcode":"M3B 1M3",
    "sg:province":"ON",
    "wof:name":"Rainbow Realty Ltd",
    "wof:placetype":"venue"
},
  "geometry": {"coordinates":[-79.3431015015,43.7464103699],"type":"Point"}
}