{
  "type": "Feature",
  "properties": {
    "addr:full":"100 Rue Onulphe-Peltier L'Epiphanie QC J5X 3W8",
    "addr:housenumber":"100",
    "addr:postcode":"j5x 3w8",
    "addr:street":"Rue Onulphe-Peltier L'Epiphanie",
    "iso:country":"CA",
    "sg:address":"100 Rue Onulphe-Peltier",
    "sg:city":"L'Epiphanie",
    "sg:classifiers":[
        {
            "category":"Personal",
            "subcategory":"Beauty Salon",
            "type":"Services"
        }
    ],
    "sg:phone":"+1 450 588 4220",
    "sg:postcode":"J5X 3W8",
    "sg:province":"QC",
    "wof:name":"Salon DE Coiffure Capri",
    "wof:placetype":"venue"
},
  "geometry": {"coordinates":[-73.47878300000001,45.84462],"type":"Point"}
}