{
  "type": "Feature",
  "properties": {
    "addr:full":"1040 Hargrieve Rd London ON N6E 1P5",
    "addr:housenumber":"1040",
    "addr:postcode":"n6e 1p5",
    "addr:street":"Hargrieve Rd",
    "iso:country":"CA",
    "sg:address":"1040 Hargrieve Rd",
    "sg:city":"London",
    "sg:classifiers":[
        {
            "category":"Wholesale",
            "subcategory":"Chemicals & Plastics",
            "type":"Manufacturing & Wholesale Goods"
        }
    ],
    "sg:phone":"+1 519 685 3040",
    "sg:postcode":"N6E 1P5",
    "sg:province":"ON",
    "sg:tags":[
        "compound",
        "waste",
        "cleaning",
        "liquid",
        "removal"
    ],
    "wof:name":"Safety Kleen Canada Ltd",
    "wof:placetype":"venue"
},
  "geometry": {"coordinates":[-81.215141,42.930012],"type":"Point"}
}