{
  "type": "Feature",
  "properties": {
    "iso:country":"CA",
    "sg:address":"7685 Boul Maurice-Duplessis",
    "sg:city":"Montreal",
    "sg:classifiers":[
        {
            "category":"Restaurant",
            "type":"Food & Drink"
        }
    ],
    "sg:phone":"+1 514 643 2892",
    "sg:postcode":"H1E 5M9",
    "sg:province":"QC",
    "wof:name":"Mc Donald's",
    "wof:placetype":"venue"
},
  "geometry": {"coordinates":[-73.595009,45.627697],"type":"Point"}
}