{
  "type": "Feature",
  "properties": {
    "addr:full":"1519 Crois Nelligan Mascouche QC J7K 3N8",
    "addr:housenumber":"1519",
    "addr:postcode":"j7k 3n8",
    "addr:street":"Crois Nelligan",
    "iso:country":"CA",
    "sg:address":"1519 Crois Nelligan",
    "sg:city":"Mascouche",
    "sg:classifiers":[
        {
            "category":"Shopping",
            "subcategory":"Computers & Home Electronics",
            "type":"Retail Goods"
        }
    ],
    "sg:phone":"+1 450 474 0358",
    "sg:postcode":"J7K 3N8",
    "sg:province":"QC",
    "sg:tags":[
        "equipment",
        "dealer"
    ],
    "wof:name":"Service Informatique Jb",
    "wof:placetype":"venue"
},
  "geometry": {"coordinates":[-73.59214799999999,45.757828],"type":"Point"}
}