{
  "type": "Feature",
  "properties": {
    "addr:full":"759 Principale St Casselman ON K0A 1M0",
    "addr:housenumber":"759",
    "addr:postcode":"k0a 1m0",
    "addr:street":"Principale St",
    "iso:country":"CA",
    "sg:address":"759 Principale St",
    "sg:city":"Casselman",
    "sg:classifiers":[
        {
            "category":"Shopping",
            "subcategory":"Computers & Home Electronics",
            "type":"Retail Goods"
        }
    ],
    "sg:phone":"+1 613 764 0633",
    "sg:postcode":"K0A 1M0",
    "sg:province":"ON",
    "sg:tags":[
        "television",
        "radio"
    ],
    "wof:name":"Baker Audiotronic",
    "wof:placetype":"venue"
},
  "geometry": {"coordinates":[-75.0884857178,45.3144111633],"type":"Point"}
}