{
  "type": "Feature",
  "properties": {
    "addr:full":"39 Riverside Dr Kapuskasing ON P5N 1A7",
    "addr:housenumber":"39",
    "addr:postcode":"p5n 1a7",
    "addr:street":"Riverside Dr",
    "iso:country":"CA",
    "sg:address":"39 Riverside Dr",
    "sg:city":"Kapuskasing",
    "sg:classifiers":[
        {
            "category":"Retail",
            "subcategory":"Laundry & Dry Cleaning",
            "type":"Services"
        }
    ],
    "sg:phone":"+1 705 335 2208",
    "sg:postcode":"P5N 1A7",
    "sg:province":"ON",
    "sg:tags":[
        "cleaners"
    ],
    "wof:name":"North Star Linen Uniform Svc",
    "wof:placetype":"venue"
},
  "geometry": {"coordinates":[-82.423309,49.415428],"type":"Point"}
}