{
  "type": "Feature",
  "properties": {
    "addr:full":"2105 7 St Nisku AB T9E 7Y3",
    "addr:housenumber":"2105 7",
    "addr:postcode":"t9e 7y3",
    "addr:street":"St",
    "iso:country":"CA",
    "sg:address":"2105 7 St",
    "sg:city":"Nisku",
    "sg:classifiers":[
        {
            "category":"Manufacturing",
            "subcategory":"Metals",
            "type":"Manufacturing & Wholesale Goods"
        }
    ],
    "sg:phone":"+1 780 955 3881",
    "sg:postcode":"T9E 7Y3",
    "sg:province":"AB",
    "wof:name":"Canadian Industrial Mtlzng",
    "wof:placetype":"venue"
},
  "geometry": {"coordinates":[-113.521111,53.339672],"type":"Point"}
}