{
  "type": "Feature",
  "properties": {
    "addr:full":"420 105 Rte N Maniwaki QC J9E 3A9",
    "addr:housenumber":"105",
    "addr:postcode":"j9e 3a9",
    "addr:street":"Rte N",
    "iso:country":"CA",
    "sg:address":"420 105 Rte N",
    "sg:city":"Maniwaki",
    "sg:classifiers":[
        {
            "category":"Manufacturing",
            "subcategory":"Tools & Machinery",
            "type":"Manufacturing & Wholesale Goods"
        }
    ],
    "sg:phone":"+1 819 449 7293",
    "sg:postcode":"J9E 3A9",
    "sg:province":"QC",
    "sg:tags":[
        "machine",
        "shop",
        "welding"
    ],
    "wof:name":"Atelier D'Usinage Jdg Inc",
    "wof:placetype":"venue"
},
  "geometry": {"coordinates":[-75.98159800000001,46.37468],"type":"Point"}
}