{
  "type": "Feature",
  "properties": {
    "iso:country":"CA",
    "sg:address":"7035 Wallace Dr",
    "sg:city":"Brentwood Bay",
    "sg:classifiers":[
        {
            "category":"Shopping",
            "subcategory":"Used Merchandise",
            "type":"Retail Goods"
        }
    ],
    "sg:phone":"+1 250 652 1758",
    "sg:postcode":"V8M 1E9",
    "sg:province":"BC",
    "sg:tags":[
        "antique"
    ],
    "wof:name":"Dan Gentile Antique Rstrtn",
    "wof:placetype":"venue"
},
  "geometry": {"coordinates":[-123.449485779,48.5735931396],"type":"Point"}
}