{
  "type": "Feature",
  "properties": {
    "addr:full":"Venise-En-Quebec QC J0J 2K0",
    "addr:postcode":"j0j 2k0",
    "iso:country":"CA",
    "sg:city":"Venise-En-Quebec",
    "sg:classifiers":[
        {
            "category":"Restaurant",
            "type":"Food & Drink"
        }
    ],
    "sg:phone":"+1 450 244 5722",
    "sg:postcode":"J0J 2K0",
    "sg:province":"QC",
    "wof:name":"Resto Le pa-Pion",
    "wof:placetype":"venue"
},
  "geometry": {"coordinates":[-73.13381200000001,45.083748],"type":"Point"}
}