{
  "type": "Feature",
  "properties": {
    "addr:full":"7200 Av Jean-Bourdon Montreal QC H4K 1G8",
    "addr:housenumber":"7200",
    "addr:postcode":"h4k 1g8",
    "addr:street":"Av Jean-Bourdon",
    "iso:country":"CA",
    "sg:address":"7200 Av Jean-Bourdon",
    "sg:city":"Montreal",
    "sg:classifiers":[
        {
            "category":"Real Estate",
            "subcategory":"Real Estate Agent",
            "type":"Services"
        }
    ],
    "sg:phone":"+1 514 748 5828",
    "sg:postcode":"H4K 1G8",
    "sg:province":"QC",
    "wof:name":"Germain Gagnon & Assoc Inc",
    "wof:placetype":"venue"
},
  "geometry": {"coordinates":[-73.73034667970001,45.5248336792],"type":"Point"}
}