{
  "type": "Feature",
  "properties": {
    "addr:full":"10260 107 St Westlock AB T7P 1X4",
    "addr:housenumber":"10260",
    "addr:postcode":"t7p 1x4",
    "addr:street":"107 St",
    "iso:country":"CA",
    "sg:address":"10260 107 St",
    "sg:city":"Westlock",
    "sg:classifiers":[
        {
            "category":"Professional",
            "subcategory":"Accounting & Tax Preparation",
            "type":"Services"
        }
    ],
    "sg:phone":"+1 780 349 4408",
    "sg:postcode":"T7P 1X4",
    "sg:province":"AB",
    "sg:tags":[
        "consultant",
        "return",
        "filing"
    ],
    "wof:name":"H & R Block Canada Inc",
    "wof:placetype":"venue"
},
  "geometry": {"coordinates":[-113.85401899999999,54.159081],"type":"Point"}
}