{
  "type": "Feature",
  "properties": {
    "iso:country":"CA",
    "sg:address":"17 Rue Principale O",
    "sg:city":"Adstock",
    "sg:classifiers":[
        {
            "category":"Restaurant",
            "type":"Food & Drink"
        }
    ],
    "sg:phone":"+1 418 422 5786",
    "sg:postcode":"G0N 1S0",
    "sg:province":"QC",
    "wof:name":"Cantine Couture",
    "wof:placetype":"venue"
},
  "geometry": {"coordinates":[-71.0755844116,46.0462684631],"type":"Point"}
}