{
  "type": "Feature",
  "properties": {
    "iso:country":"CA",
    "sg:address":"757 Kember Ave",
    "sg:city":"Sarnia",
    "sg:classifiers":[
        {
            "category":"Education",
            "subcategory":"School",
            "type":"Public Place"
        }
    ],
    "sg:phone":"+1 519 332 0474",
    "sg:postcode":"N7S 2T3",
    "sg:province":"ON",
    "wof:name":"High Park School",
    "wof:placetype":"venue"
},
  "geometry": {"coordinates":[-82.3715133667,42.9820861816],"type":"Point"}
}