{
  "type": "Feature",
  "properties": {
    "iso:country":"CA",
    "sg:city":"Calgary",
    "sg:classifiers":[
        {
            "category":"Building & Trades",
            "subcategory":"Construction",
            "type":"Services"
        }
    ],
    "sg:phone":"+1 403 258 8660",
    "sg:postcode":"T2W 4X9",
    "sg:province":"AB",
    "sg:tags":[
        "contractor",
        "petrochemical",
        "general"
    ],
    "wof:name":"Cord Projects Ltd",
    "wof:placetype":"venue"
},
  "geometry": {"coordinates":[-114.073509,50.964279],"type":"Point"}
}