{
  "type": "Feature",
  "properties": {
    "addr:full":"4524 Westchester Bourne Belmont ON N0L 1B0",
    "addr:housenumber":"4524",
    "addr:postcode":"n0l 1b0",
    "addr:street":"Westchester Bourne",
    "iso:country":"CA",
    "sg:address":"4524 Westchester Bourne",
    "sg:city":"Belmont",
    "sg:classifiers":[
        {
            "category":"Autos & Motor Vehicles",
            "subcategory":"Automobile Sales",
            "type":"Retail Goods"
        }
    ],
    "sg:phone":"+1 519 644 0101",
    "sg:postcode":"N0L 1B0",
    "sg:province":"ON",
    "sg:tags":[
        "car",
        "dealer"
    ],
    "wof:name":"Kennedy Auto Marine Inc",
    "wof:placetype":"venue"
},
  "geometry": {"coordinates":[-81.087349,42.880638],"type":"Point"}
}