{
  "type": "Feature",
  "properties": {
    "iso:country":"CA",
    "sg:address":"12267 Rue DE Saint-Real",
    "sg:city":"Montreal",
    "sg:classifiers":[
        {
            "category":"Professional",
            "subcategory":"Business Services",
            "type":"Services"
        }
    ],
    "sg:phone":"+1 514 334 0022",
    "sg:postcode":"H3M 2Z4",
    "sg:province":"QC",
    "sg:tags":[
        "fund",
        "promotion",
        "raising"
    ],
    "wof:name":"Pro Musi Com",
    "wof:placetype":"venue"
},
  "geometry": {"coordinates":[-73.699173,45.54501],"type":"Point"}
}