{
  "type": "Feature",
  "properties": {
    "addr:full":"222 Boul Poliquin Sorel-Tracy QC J3P 7Y9",
    "addr:housenumber":"222",
    "addr:postcode":"j3p 7y9",
    "addr:street":"Boul Poliquin",
    "iso:country":"CA",
    "sg:address":"222 Boul Poliquin",
    "sg:city":"Sorel-Tracy",
    "sg:classifiers":[
        {
            "category":"Recreation",
            "type":"Entertainment"
        }
    ],
    "sg:phone":"+1 450 743 9704",
    "sg:postcode":"J3P 7Y9",
    "sg:province":"QC",
    "sg:tags":[
        "hall",
        "auditorium"
    ],
    "wof:name":"Salle Martin Guy",
    "wof:placetype":"venue"
},
  "geometry": {"coordinates":[-73.0978317261,46.0282020569],"type":"Point"}
}