{
  "type": "Feature",
  "properties": {
    "addr:full":"895 Rue Georges Buckingham QC J8L 2E4",
    "addr:housenumber":"895",
    "addr:postcode":"j8l 2e4",
    "addr:street":"Rue Georges",
    "iso:country":"CA",
    "sg:address":"895 Rue Georges",
    "sg:city":"Buckingham",
    "sg:classifiers":[
        {
            "category":"Building & Trades",
            "subcategory":"Cleaning & Sanitation",
            "type":"Services"
        }
    ],
    "sg:phone":"+1 819 986 8817",
    "sg:postcode":"J8L 2E4",
    "sg:province":"QC",
    "sg:tags":[
        "window",
        "maintenance"
    ],
    "wof:name":"Laveur DE Vitre Goldstar",
    "wof:placetype":"venue"
},
  "geometry": {"coordinates":[-75.42523199999999,45.570358],"type":"Point"}
}