{
  "type": "Feature",
  "properties": {
    "addr:full":"1160 Boul Saint-Joseph E # 205 Montreal QC H2J 1L4",
    "addr:housenumber":"1160",
    "addr:postcode":"h2j 1l4",
    "addr:street":"Boul Saint-Joseph E # 205",
    "iso:country":"CA",
    "sg:address":"1160 Boul Saint-Joseph E # 205",
    "sg:city":"Montreal",
    "sg:classifiers":[
        {
            "category":"Professional",
            "subcategory":"Accounting & Tax Preparation",
            "type":"Services"
        }
    ],
    "sg:phone":"+1 514 529 7448",
    "sg:postcode":"H2J 1L4",
    "sg:province":"QC",
    "sg:tags":[
        "accountant"
    ],
    "wof:name":"Derome, Jean-Franc CA",
    "wof:placetype":"venue"
},
  "geometry": {"coordinates":[-73.5835266113,45.5306129456],"type":"Point"}
}