{
  "type": "Feature",
  "properties": {
    "addr:full":"4161 95 St NW Edmonton AB T6E 5R6",
    "addr:housenumber":"4161",
    "addr:postcode":"t6e 5r6",
    "addr:street":"95 St Nw",
    "iso:country":"CA",
    "sg:address":"4161 95 St NW",
    "sg:city":"Edmonton",
    "sg:classifiers":[
        {
            "category":"Building & Trades",
            "subcategory":"Plumbing",
            "type":"Services"
        }
    ],
    "sg:phone":"+1 780 436 2550",
    "sg:postcode":"T6E 5R6",
    "sg:province":"AB",
    "sg:tags":[
        "sheet",
        "electric",
        "work",
        "metal",
        "contractor",
        "equipment"
    ],
    "wof:name":"Ruttan Manufacturing Ltd",
    "wof:placetype":"venue"
},
  "geometry": {"coordinates":[-113.475082398,53.4780921936],"type":"Point"}
}