{
  "type": "Feature",
  "properties": {
    "addr:full":"555 Rue Chabanel O Montreal QC H2N 2L1",
    "addr:housenumber":"555",
    "addr:postcode":"h2n 2l1",
    "addr:street":"Rue Chabanel O",
    "iso:country":"CA",
    "sg:address":"555 Rue Chabanel O",
    "sg:city":"Montreal",
    "sg:classifiers":[
        {
            "category":"Wholesale",
            "subcategory":"Durable Goods & Equipment",
            "type":"Manufacturing & Wholesale Goods"
        }
    ],
    "sg:phone":"+1 514 389 0214",
    "sg:postcode":"H2N 2L1",
    "sg:province":"QC",
    "sg:tags":[
        "importer"
    ],
    "wof:name":"Diffusion Amor-Lux Inc",
    "wof:placetype":"venue"
},
  "geometry": {"coordinates":[-73.648155,45.549534],"type":"Point"}
}