{
  "type": "Feature",
  "properties": {
    "addr:full":"1251 Boul Sainte-Rose Laval QC H7R 1S2",
    "addr:housenumber":"1251",
    "addr:postcode":"h7r 1s2",
    "addr:street":"Boul Sainte-Rose",
    "iso:country":"CA",
    "sg:address":"1251 Boul Sainte-Rose",
    "sg:city":"Laval",
    "sg:classifiers":[
        {
            "category":"Building & Trades",
            "subcategory":"Plumbing",
            "type":"Services"
        }
    ],
    "sg:phone":"+1 450 962 9999",
    "sg:postcode":"H7R 1S2",
    "sg:province":"QC",
    "sg:tags":[
        "contractor"
    ],
    "wof:name":"Plomberie Gilles Boulay Inc",
    "wof:placetype":"venue"
},
  "geometry": {"coordinates":[-73.74463653559999,45.5515670776],"type":"Point"}
}