{
  "type": "Feature",
  "properties": {
    "addr:full":"301 St Joseph St Tweed ON K0K 3J0",
    "addr:housenumber":"301",
    "addr:postcode":"k0k 3j0",
    "addr:street":"St Joseph St",
    "iso:country":"CA",
    "sg:address":"301 St Joseph St",
    "sg:city":"Tweed",
    "sg:classifiers":[
        {
            "category":"Recreation",
            "type":"Entertainment"
        }
    ],
    "sg:phone":"+1 613 478 2311",
    "sg:postcode":"K0K 3J0",
    "sg:province":"ON",
    "sg:tags":[
        "club",
        "curling",
        "hall",
        "auditorium"
    ],
    "wof:name":"Land O'Lakes Curling Club Inc",
    "wof:placetype":"venue"
},
  "geometry": {"coordinates":[-77.31025699999999,44.480972],"type":"Point"}
}