{
  "type": "Feature",
  "properties": {
    "addr:full":"5295 Ch DE Chambly Saint-Hubert QC J3Y 3N5",
    "addr:postcode":"5295;j3y 3n5",
    "addr:street":"Ch De Chambly",
    "iso:country":"CA",
    "sg:address":"5295 Ch DE Chambly",
    "sg:city":"Saint-Hubert",
    "sg:classifiers":[
        {
            "category":"Education",
            "subcategory":"School",
            "type":"Public Place"
        }
    ],
    "sg:phone":"+1 450 678 0792",
    "sg:postcode":"J3Y 3N5",
    "sg:province":"QC",
    "wof:name":"Ecole Paul Chagnon",
    "wof:placetype":"venue"
},
  "geometry": {"coordinates":[-73.4220581055,45.5040893555],"type":"Point"}
}