{
  "type": "Feature",
  "properties": {
    "addr:full":"1150 Edward Ave Windsor ON N8S 3A1",
    "addr:housenumber":"1150",
    "addr:postcode":"n8s 3a1",
    "addr:street":"Edward Ave",
    "iso:country":"CA",
    "sg:address":"1150 Edward Ave",
    "sg:city":"Windsor",
    "sg:classifiers":[
        {
            "category":"Recreation",
            "type":"Entertainment"
        }
    ],
    "sg:phone":"+1 519 945 7426",
    "sg:postcode":"N8S 3A1",
    "sg:province":"ON",
    "sg:tags":[
        "center",
        "government"
    ],
    "wof:name":"Windsor Edward Street Comm Ctr",
    "wof:placetype":"venue"
},
  "geometry": {"coordinates":[-82.948105,42.324268],"type":"Point"}
}