{
  "type": "Feature",
  "properties": {
    "addr:full":"Calgary AB T2P 3R7",
    "addr:postcode":"t2p 3r7",
    "iso:country":"CA",
    "sg:city":"Calgary",
    "sg:classifiers":[
        {
            "category":"Wholesale",
            "subcategory":"Machinery & Supplies",
            "type":"Manufacturing & Wholesale Goods"
        }
    ],
    "sg:phone":"+1 403 264 4146",
    "sg:postcode":"T2P 3R7",
    "sg:province":"AB",
    "sg:tags":[
        "equipment",
        "oil",
        "well"
    ],
    "wof:name":"Abb Vetco Gray Canada Inc",
    "wof:placetype":"venue"
},
  "geometry": {"coordinates":[-114.072021484,51.0487518311],"type":"Point"}
}