{
  "type": "Feature",
  "properties": {
    "addr:full":"Kamloops BC V2C 1Y6",
    "addr:postcode":"bc v2c 1y6",
    "iso:country":"CA",
    "sg:city":"Kamloops",
    "sg:classifiers":[
        {
            "category":"Health Services",
            "subcategory":"Doctor",
            "type":"Services"
        }
    ],
    "sg:phone":"+1 250 314 1234",
    "sg:postcode":"V2C 1Y6",
    "sg:province":"BC",
    "sg:tags":[
        "dentist"
    ],
    "wof:name":"Murphy, Tracey DDS",
    "wof:placetype":"venue"
},
  "geometry": {"coordinates":[-120.325561523,50.6764793396],"type":"Point"}
}