{
  "type": "Feature",
  "properties": {
    "addr:full":"5901 Ottawa St E Richmond ON K0A 2Z0",
    "addr:housenumber":"5901",
    "addr:postcode":"k0a 2z0",
    "addr:street":"Ottawa St",
    "iso:country":"CA",
    "sg:address":"5901 Ottawa St E",
    "sg:city":"Richmond",
    "sg:classifiers":[
        {
            "category":"Home & Garden",
            "subcategory":"Garden Supply",
            "type":"Retail Goods"
        }
    ],
    "sg:phone":"+1 613 838 5959",
    "sg:postcode":"K0A 2Z0",
    "sg:province":"ON",
    "sg:tags":[
        "center"
    ],
    "wof:name":"Lalonde's Richmond Gardens",
    "wof:placetype":"venue"
},
  "geometry": {"coordinates":[-75.8190994263,45.1905632019],"type":"Point"}
}