{
  "type": "Feature",
  "properties": {
    "addr:full":"6265 Rose Ville Garden Dr Windsor ON N8T 3B9",
    "addr:housenumber":"6265",
    "addr:postcode":"n8t 3b9",
    "addr:street":"Rose Ville Garden Dr",
    "iso:country":"CA",
    "sg:address":"6265 Rose Ville Garden Dr",
    "sg:city":"Windsor",
    "sg:classifiers":[
        {
            "category":"Education",
            "subcategory":"School",
            "type":"Public Place"
        }
    ],
    "sg:phone":"+1 519 944 3611",
    "sg:postcode":"N8T 3B9",
    "sg:province":"ON",
    "wof:name":"Roseville Public Elementary",
    "wof:placetype":"venue"
},
  "geometry": {"coordinates":[-82.946968,42.307262],"type":"Point"}
}