{
  "type": "Feature",
  "properties": {
    "addr:full":"12 Morningside Dr Smiths Falls ON K7A 4S5",
    "addr:housenumber":"12",
    "addr:postcode":"k7a 4s5",
    "addr:street":"Morningside Dr",
    "iso:country":"CA",
    "sg:address":"12 Morningside Dr",
    "sg:city":"Smiths Falls",
    "sg:classifiers":[
        {
            "category":"Social Services",
            "type":"Services"
        }
    ],
    "sg:phone":"+1 613 284 0634",
    "sg:postcode":"K7A 4S5",
    "sg:province":"ON",
    "sg:tags":[
        "youth",
        "organization",
        "center"
    ],
    "wof:name":"Dalhousie Home For Youth",
    "wof:placetype":"venue"
},
  "geometry": {"coordinates":[-76.02151499999999,44.902584],"type":"Point"}
}