{
  "type": "Feature",
  "properties": {
    "addr:full":"3095 Boul Sainte-Anne Beauport QC G1E 3K1",
    "addr:housenumber":"3095",
    "addr:postcode":"qc g1e 3k1",
    "addr:street":"Boul Sainte-Anne",
    "iso:country":"CA",
    "sg:address":"3095 Boul Sainte-Anne",
    "sg:city":"Beauport",
    "sg:classifiers":[
        {
            "category":"Retail",
            "subcategory":"Auto Repair",
            "type":"Services"
        }
    ],
    "sg:phone":"+1 418 661 4450",
    "sg:postcode":"G1E 3K1",
    "sg:province":"QC",
    "sg:tags":[
        "repairing",
        "automobile"
    ],
    "wof:name":"Station DE Svc Louis Dostie",
    "wof:placetype":"venue"
},
  "geometry": {"coordinates":[-71.209389,46.847958],"type":"Point"}
}