{
  "type": "Feature",
  "properties": {
    "addr:full":"10429 Hwy 3 Hubbards NS B0J 1T0",
    "addr:housenumber":"10429",
    "addr:postcode":"b0j 1t0",
    "addr:street":"Hwy 3",
    "iso:country":"CA",
    "sg:address":"10429 Hwy 3",
    "sg:city":"Hubbards",
    "sg:classifiers":[
        {
            "category":"Retail",
            "subcategory":"Funeral Services",
            "type":"Services"
        }
    ],
    "sg:phone":"+1 902 857 9594",
    "sg:postcode":"B0J 1T0",
    "sg:province":"NS",
    "sg:tags":[
        "director"
    ],
    "wof:name":"Ronald A Walker Funeral Home",
    "wof:placetype":"venue"
},
  "geometry": {"coordinates":[-64.052055,44.643314],"type":"Point"}
}