{
  "type": "Feature",
  "properties": {
    "addr:full":"703 Jackson St Dauphin MB R7N 2N2",
    "addr:housenumber":"703",
    "addr:postcode":"r7n 2n2",
    "addr:street":"Jackson St",
    "iso:country":"CA",
    "sg:address":"703 Jackson St",
    "sg:city":"Dauphin",
    "sg:classifiers":[
        {
            "category":"Health Services",
            "subcategory":"Nursing And Care Facility",
            "type":"Services"
        }
    ],
    "sg:phone":"+1 204 638 3129",
    "sg:postcode":"R7N 2N2",
    "sg:province":"MB",
    "sg:tags":[
        "personal",
        "home"
    ],
    "wof:name":"St Paul's Home",
    "wof:placetype":"venue"
},
  "geometry": {"coordinates":[-100.063339,51.142727],"type":"Point"}
}