{
  "type": "Feature",
  "properties": {
    "iso:country":"CA",
    "sg:address":"339 Avenue C S",
    "sg:city":"Saskatoon",
    "sg:classifiers":[
        {
            "category":"Organizations",
            "subcategory":"Religious Organization",
            "type":"Services"
        }
    ],
    "sg:phone":"+1 306 242 6833",
    "sg:postcode":"S7M 1N5",
    "sg:province":"SK",
    "sg:tags":[
        "church"
    ],
    "wof:name":"Salvation Army Family Svc",
    "wof:placetype":"venue"
},
  "geometry": {"coordinates":[-106.673751831,52.1254997253],"type":"Point"}
}