{
  "type": "Feature",
  "properties": {
    "addr:full":"1200 Sheppard Ave E North York ON M2K 2S5",
    "addr:housenumber":"1200",
    "addr:postcode":"m2k 2s5",
    "addr:street":"Sheppard Ave E",
    "iso:country":"CA",
    "sg:address":"1200 Sheppard Ave E",
    "sg:city":"North York",
    "sg:classifiers":[
        {
            "category":"Professional",
            "subcategory":"Computer Services",
            "type":"Services"
        }
    ],
    "sg:phone":"+1 416 492 0321",
    "sg:postcode":"M2K 2S5",
    "sg:province":"ON",
    "sg:tags":[
        "website",
        "design"
    ],
    "wof:name":"Creative People Online",
    "wof:placetype":"venue"
},
  "geometry": {"coordinates":[-79.366005,43.771584],"type":"Point"}
}