{
  "type": "Feature",
  "properties": {
    "iso:country":"CA",
    "sg:address":"3585 Rue Principale",
    "sg:city":"Tracadie-Sheila",
    "sg:classifiers":[
        {
            "category":"Organizations",
            "subcategory":"Religious Organization",
            "type":"Services"
        }
    ],
    "sg:phone":"+1 506 395 2230",
    "sg:postcode":"E1X 1C9",
    "sg:province":"NB",
    "sg:tags":[
        "church"
    ],
    "wof:name":"Paroisse St-Jean-Baptiste",
    "wof:placetype":"venue"
},
  "geometry": {"coordinates":[-64.9176864624,47.4913406372],"type":"Point"}
}