{
  "type": "Feature",
  "properties": {
    "addr:full":"Courtenay BC V9N 2L8",
    "addr:postcode":"v9n 2l8",
    "iso:country":"CA",
    "sg:city":"Courtenay",
    "sg:classifiers":[
        {
            "category":"Retail",
            "subcategory":"Repair Shop",
            "type":"Services"
        }
    ],
    "sg:phone":"+1 250 338 5244",
    "sg:postcode":"V9N 2L8",
    "sg:province":"BC",
    "sg:tags":[
        "lock",
        "locksmith"
    ],
    "wof:name":"Prices Security Locksmiths",
    "wof:placetype":"venue"
},
  "geometry": {"coordinates":[-124.98075900000001,49.672577],"type":"Point"}
}