{
  "type": "Feature",
  "properties": {
    "addr:full":"2122 Government St Victoria BC V8T 5G5",
    "addr:housenumber":"2122",
    "addr:postcode":"v8t 5g5",
    "addr:street":"Government St",
    "iso:country":"CA",
    "sg:address":"2122 Government St",
    "sg:city":"Victoria",
    "sg:classifiers":[
        {
            "category":"Home & Garden",
            "subcategory":"Building Materials",
            "type":"Retail Goods"
        }
    ],
    "sg:phone":"+1 250 381 3132",
    "sg:postcode":"V8T 5G5",
    "sg:province":"BC",
    "sg:tags":[
        "glass",
        "window",
        "plate"
    ],
    "wof:name":"Standard Auto Glass",
    "wof:placetype":"venue"
},
  "geometry": {"coordinates":[-123.367454529,48.4329605103],"type":"Point"}
}