{
  "type": "Feature",
  "properties": {
    "iso:country":"CA",
    "sg:address":"65 Ellen St",
    "sg:city":"Barrie",
    "sg:classifiers":[
        {
            "category":"Real Estate",
            "subcategory":"Real Estate Operator",
            "type":"Services"
        }
    ],
    "sg:phone":"+1 705 721 9944",
    "sg:postcode":"L4N 3A5",
    "sg:province":"ON",
    "sg:tags":[
        "condominium"
    ],
    "wof:name":"Marina Bay Condominiums",
    "wof:placetype":"venue"
},
  "geometry": {"coordinates":[-79.69194793699999,44.380191803],"type":"Point"}
}