{
  "type": "Feature",
  "properties": {
    "iso:country":"CA",
    "sg:address":"10 Struan St",
    "sg:city":"Bradwell",
    "sg:classifiers":[
        {
            "category":"Food & Beverages",
            "subcategory":"Groceries & Convenience Stores",
            "type":"Retail Goods"
        }
    ],
    "sg:phone":"+1 306 257 3363",
    "sg:postcode":"S0K 0P0",
    "sg:province":"SK",
    "sg:tags":[
        "grocer"
    ],
    "wof:name":"Bradwell Store",
    "wof:placetype":"venue"
},
  "geometry": {"coordinates":[-106.233093262,51.9472732544],"type":"Point"}
}