{
  "type": "Feature",
  "properties": {
    "addr:full":"10 Days Rd Wickham NB E5T 3Z2",
    "addr:housenumber":"10",
    "addr:postcode":"e5t 3z2",
    "addr:street":"Days Rd",
    "iso:country":"CA",
    "sg:address":"10 Days Rd",
    "sg:city":"Wickham",
    "sg:classifiers":[
        {
            "category":"Organizations",
            "subcategory":"Religious Organization",
            "type":"Services"
        }
    ],
    "sg:phone":"+1 506 485 0088",
    "sg:postcode":"E5T 3Z2",
    "sg:province":"NB",
    "sg:tags":[
        "church"
    ],
    "wof:name":"Maranatha Christian Assembly",
    "wof:placetype":"venue"
},
  "geometry": {"coordinates":[-66.07337200000001,45.63525],"type":"Point"}
}