{
  "type": "Feature",
  "properties": {
    "addr:full":"137 Rue DE Martigny O Saint-Jerome QC J7Y 2G2",
    "addr:housenumber":"137",
    "addr:postcode":"j7y 2g2",
    "addr:street":"Rue De Martigny O Saint-Jerome",
    "iso:country":"CA",
    "sg:address":"137 Rue DE Martigny O",
    "sg:city":"Saint-Jerome",
    "sg:classifiers":[
        {
            "category":"Health Services",
            "subcategory":"Doctor",
            "type":"Services"
        }
    ],
    "sg:phone":"+1 450 438 4299",
    "sg:postcode":"J7Y 2G2",
    "sg:province":"QC",
    "sg:tags":[
        "dentist"
    ],
    "wof:name":"Clinique Dentaire Masson Mcfad",
    "wof:placetype":"venue"
},
  "geometry": {"coordinates":[-74.0113983154,45.7797431946],"type":"Point"}
}