{
  "type": "Feature",
  "properties": {
    "addr:full":"371 Rue Notre-Dame E Victoriaville QC G6P 4A8",
    "addr:housenumber":"371",
    "addr:postcode":"g6p 4a8",
    "addr:street":"Rue Notre-Dame E",
    "iso:country":"CA",
    "sg:address":"371 Rue Notre-Dame E",
    "sg:city":"Victoriaville",
    "sg:classifiers":[
        {
            "category":"Health Services",
            "subcategory":"Health Practitioner",
            "type":"Services"
        }
    ],
    "sg:phone":"+1 819 758 3540",
    "sg:postcode":"G6P 4A8",
    "sg:province":"QC",
    "sg:tags":[
        "psychologist"
    ],
    "wof:name":"Centre DE Svc Psychologiques",
    "wof:placetype":"venue"
},
  "geometry": {"coordinates":[-71.947701,46.059021],"type":"Point"}
}