{
  "type": "Feature",
  "properties": {
    "addr:full":"4923 Ravine Dr Swan Hills AB T0G 2C0",
    "addr:housenumber":"4923",
    "addr:postcode":"t0g 2c0",
    "addr:street":"Ravine Dr",
    "iso:country":"CA",
    "sg:address":"4923 Ravine Dr",
    "sg:city":"Swan Hills",
    "sg:classifiers":[
        {
            "category":"Food & Beverages",
            "subcategory":"Groceries & Convenience Stores",
            "type":"Retail Goods"
        }
    ],
    "sg:phone":"+1 780 333 2600",
    "sg:postcode":"T0G 2C0",
    "sg:province":"AB",
    "sg:tags":[
        "grocer"
    ],
    "wof:name":"Swan Hills Super A",
    "wof:placetype":"venue"
},
  "geometry": {"coordinates":[-115.401268,54.716518],"type":"Point"}
}