{
  "type": "Feature",
  "properties": {
    "iso:country":"CA",
    "sg:address":"3695 Rue DE L'Hetriere",
    "sg:city":"Saint-Augustin-DE-Desmaures",
    "sg:classifiers":[
        {
            "category":"Health Services",
            "subcategory":"Doctor",
            "type":"Services"
        }
    ],
    "sg:phone":"+1 418 877 8770",
    "sg:postcode":"G3A 1X1",
    "sg:province":"QC",
    "sg:tags":[
        "dentist"
    ],
    "wof:name":"Beaulieu & Dorval Orthodontist",
    "wof:placetype":"venue"
},
  "geometry": {"coordinates":[-71.3835144043,46.7499847412],"type":"Point"}
}