{
  "type": "Feature",
  "properties": {
    "addr:full":"5040 48 Ave Delta BC V4K 1V8",
    "addr:housenumber":"5040",
    "addr:postcode":"v4k 1v8",
    "addr:street":"48 Ave",
    "iso:country":"CA",
    "sg:address":"5040 48 Ave",
    "sg:city":"Delta",
    "sg:classifiers":[
        {
            "category":"Shopping",
            "subcategory":"Used Merchandise",
            "type":"Retail Goods"
        }
    ],
    "sg:phone":"+1 604 940 4490",
    "sg:postcode":"V4K 1V8",
    "sg:province":"BC",
    "sg:tags":[
        "shop",
        "infant",
        "consignment",
        "wear"
    ],
    "wof:name":"Little Layla's",
    "wof:placetype":"venue"
},
  "geometry": {"coordinates":[-123.083893,49.090069],"type":"Point"}
}