{
  "type": "Feature",
  "properties": {
    "addr:full":"9390 Rue Berri Montreal QC H2M 1R2",
    "addr:housenumber":"9390",
    "addr:postcode":"h2m 1r2",
    "addr:street":"Rue Berri",
    "iso:country":"CA",
    "sg:address":"9390 Rue Berri",
    "sg:city":"Montreal",
    "sg:classifiers":[
        {
            "category":"Building & Trades",
            "subcategory":"Construction",
            "type":"Services"
        }
    ],
    "sg:phone":"+1 514 384 4480",
    "sg:postcode":"H2M 1R2",
    "sg:province":"QC",
    "sg:tags":[
        "excavating",
        "contractor",
        "snow",
        "removal"
    ],
    "wof:name":"Dleta Excavation",
    "wof:placetype":"venue"
},
  "geometry": {"coordinates":[-73.64995574949999,45.5490188599],"type":"Point"}
}