{
  "type": "Feature",
  "properties": {
    "iso:country":"CA",
    "sg:address":"3690 Westmount Rd",
    "sg:city":"West Vancouver",
    "sg:classifiers":[
        {
            "category":"Autos & Motor Vehicles",
            "subcategory":"Fuel & Gas Station",
            "type":"Retail Goods"
        }
    ],
    "sg:phone":"+1 604 922 6211",
    "sg:postcode":"V7V 3G9",
    "sg:province":"BC",
    "sg:tags":[
        "oil"
    ],
    "wof:name":"Westmount Chevron Svc",
    "wof:placetype":"venue"
},
  "geometry": {"coordinates":[-123.21804046600001,49.3456916809],"type":"Point"}
}