{
  "type": "Feature",
  "properties": {
    "iso:country":"CA",
    "sg:address":"702 Douglas St",
    "sg:city":"Victoria",
    "sg:classifiers":[
        {
            "category":"Shopping",
            "subcategory":"Clothing, Apparel, & Fashions",
            "type":"Retail Goods"
        }
    ],
    "sg:phone":"+1 250 383 8186",
    "sg:postcode":"V8W 3M6",
    "sg:province":"BC",
    "sg:tags":[
        "t"
    ],
    "wof:name":"Maple Leaf Gifts",
    "wof:placetype":"venue"
},
  "geometry": {"coordinates":[-123.366592407,48.4204521179],"type":"Point"}
}