{
  "type": "Feature",
  "properties": {
    "addr:full":"PO Box 270 Resolute NU X0A 0V0",
    "addr:housenumber":"po",
    "addr:postcode":"x0a 0v0",
    "addr:street":"Box 270",
    "iso:country":"CA",
    "sg:address":"PO Box 270",
    "sg:city":"Resolute",
    "sg:classifiers":[
        {
            "category":"Food & Beverages",
            "subcategory":"Groceries & Convenience Stores",
            "type":"Retail Goods"
        }
    ],
    "sg:phone":"+1 867 252 3854",
    "sg:postcode":"X0A 0V0",
    "sg:province":"NU",
    "sg:tags":[
        "grocer"
    ],
    "wof:name":"Tudjaat CO-OP",
    "wof:placetype":"venue"
},
  "geometry": {"coordinates":[-94.8399353027,74.6945266724],"type":"Point"}
}