{
  "type": "Feature",
  "properties": {
    "addr:full":"7694 Islington Ave Woodbridge ON L4L 1W3",
    "addr:housenumber":"7694",
    "addr:postcode":"l4l 1w3",
    "addr:street":"Islington Ave",
    "iso:country":"CA",
    "sg:address":"7694 Islington Ave",
    "sg:city":"Woodbridge",
    "sg:classifiers":[
        {
            "category":"Personal",
            "subcategory":"Beauty Salon",
            "type":"Services"
        }
    ],
    "sg:phone":"+1 905 264 1515",
    "sg:postcode":"L4L 1W3",
    "sg:province":"ON",
    "wof:name":"Salon Classique",
    "wof:placetype":"venue"
},
  "geometry": {"coordinates":[-79.587929,43.779629],"type":"Point"}
}