{
  "type": "Feature",
  "properties": {
    "iso:country":"CA",
    "sg:address":"126 Spring Town Rd",
    "sg:city":"Woodbridge",
    "sg:classifiers":[
        {
            "category":"Professional",
            "subcategory":"Computer Services",
            "type":"Services"
        }
    ],
    "sg:phone":"+1 905 856 2190",
    "sg:postcode":"L4L 8E6",
    "sg:province":"ON",
    "sg:tags":[
        "website",
        "design",
        "internet"
    ],
    "wof:name":"Web Scroll Svc Inc",
    "wof:placetype":"venue"
},
  "geometry": {"coordinates":[-79.565582,43.789032],"type":"Point"}
}