{
  "type": "Feature",
  "properties": {
    "addr:full":"Calgary AB T2E 6X8",
    "addr:postcode":"t2e 6x8",
    "iso:country":"CA",
    "sg:city":"Calgary",
    "sg:classifiers":[
        {
            "category":"Wholesale",
            "subcategory":"Electrical",
            "type":"Manufacturing & Wholesale Goods"
        }
    ],
    "sg:phone":"+1 403 265 2355",
    "sg:postcode":"T2E 6X8",
    "sg:province":"AB",
    "sg:tags":[
        "communication",
        "radio",
        "system"
    ],
    "wof:name":"Westcan Wireless",
    "wof:placetype":"venue"
},
  "geometry": {"coordinates":[-114.01200103799999,51.0884208679],"type":"Point"}
}