{
  "type": "Feature",
  "properties": {
    "addr:full":"660 Speedvale Ave W Guelph ON N1K 1E5",
    "addr:housenumber":"660",
    "addr:postcode":"n1k 1e5",
    "addr:street":"Speedvale Ave W",
    "iso:country":"CA",
    "sg:address":"660 Speedvale Ave W",
    "sg:city":"Guelph",
    "sg:classifiers":[
        {
            "category":"Professional",
            "subcategory":"Testing Lab",
            "type":"Services"
        }
    ],
    "sg:phone":"+1 519 824 2320",
    "sg:postcode":"N1K 1E5",
    "sg:province":"ON",
    "sg:tags":[
        "laboratory"
    ],
    "wof:name":"Ontario Dairy Herd Improvement",
    "wof:placetype":"venue"
},
  "geometry": {"coordinates":[-80.300797,43.534573],"type":"Point"}
}