{
  "type": "Feature",
  "properties": {
    "addr:full":"1355 Rue Antoine-Deat Montreal QC H2M 2R2",
    "addr:housenumber":"1355",
    "addr:postcode":"h2m 2r2",
    "addr:street":"Rue Antoine-Deat",
    "iso:country":"CA",
    "sg:address":"1355 Rue Antoine-Deat",
    "sg:city":"Montreal",
    "sg:classifiers":[
        {
            "category":"Professional",
            "subcategory":"Employment Agencies",
            "type":"Services"
        }
    ],
    "sg:phone":"+1 514 387 8276",
    "sg:postcode":"H2M 2R2",
    "sg:province":"QC",
    "sg:tags":[
        "consultant",
        "search",
        "executive",
        "opportunity"
    ],
    "wof:name":"Gisele Brunette & Assoc",
    "wof:placetype":"venue"
},
  "geometry": {"coordinates":[-73.6447525024,45.5633468628],"type":"Point"}
}