{
  "type": "Feature",
  "properties": {
    "addr:full":"2069 Danforth Ave Toronto ON M4C 1J8",
    "addr:housenumber":"2069",
    "addr:postcode":"m4c 1j8",
    "addr:street":"Danforth Ave",
    "iso:country":"CA",
    "sg:address":"2069 Danforth Ave",
    "sg:city":"Toronto",
    "sg:classifiers":[
        {
            "category":"Education",
            "subcategory":"Special Training",
            "type":"Public Place"
        }
    ],
    "sg:phone":"+1 416 691 6855",
    "sg:postcode":"M4C 1J8",
    "sg:province":"ON",
    "sg:tags":[
        "instruction",
        "driving"
    ],
    "wof:name":"Beach Driving Academy",
    "wof:placetype":"venue"
},
  "geometry": {"coordinates":[-79.31303405760001,43.6854743958],"type":"Point"}
}