{
  "type": "Feature",
  "properties": {
    "iso:country":"CA",
    "sg:address":"730 Rue William-G.-Ross",
    "sg:city":"Saint-Nicolas",
    "sg:classifiers":[
        {
            "category":"Home & Garden",
            "subcategory":"Furniture",
            "type":"Retail Goods"
        }
    ],
    "sg:phone":"+1 418 831 5978",
    "sg:postcode":"G7A 2N2",
    "sg:province":"QC",
    "sg:tags":[
        "bathroom",
        "kitchen",
        "remodeling",
        "cabinet"
    ],
    "wof:name":"Armoires G Baron Inc",
    "wof:placetype":"venue"
},
  "geometry": {"coordinates":[-71.30261230470001,46.6985054016],"type":"Point"}
}