{
  "type": "Feature",
  "properties": {
    "addr:full":"RR 2 STN Main Grande Prairie AB T8V 2Z9",
    "addr:postcode":"t8v 2z9",
    "addr:street":"Rr 2 Stn Main",
    "iso:country":"CA",
    "sg:address":"RR 2 STN Main",
    "sg:city":"Grande Prairie",
    "sg:classifiers":[
        {
            "category":"Professional",
            "subcategory":"Business Services",
            "type":"Services"
        }
    ],
    "sg:phone":"+1 780 539 7720",
    "sg:postcode":"T8V 2Z9",
    "sg:province":"AB",
    "sg:tags":[
        "drafting"
    ],
    "wof:name":"Nor-Tech Design Svc",
    "wof:placetype":"venue"
},
  "geometry": {"coordinates":[-118.79489100000001,55.171162],"type":"Point"}
}