{
  "type": "Feature",
  "properties": {
    "iso:country":"CA",
    "sg:address":"2221 Bowen Rd",
    "sg:city":"Nanaimo",
    "sg:classifiers":[
        {
            "category":"Social Services",
            "type":"Services"
        }
    ],
    "sg:phone":"+1 250 751 7888",
    "sg:postcode":"V9S 5J3",
    "sg:province":"BC",
    "sg:tags":[
        "community"
    ],
    "wof:name":"Rainbows Ministries Society",
    "wof:placetype":"venue"
},
  "geometry": {"coordinates":[-123.992821,49.193108],"type":"Point"}
}