{
  "type": "Feature",
  "properties": {
    "addr:full":"Owen Sound ON N4K 2K8",
    "addr:postcode":"n4k 2k8",
    "iso:country":"CA",
    "sg:city":"Owen Sound",
    "sg:classifiers":[
        {
            "category":"Health Services",
            "subcategory":"Doctor",
            "type":"Services"
        }
    ],
    "sg:phone":"+1 519 371 3432",
    "sg:postcode":"N4K 2K8",
    "sg:province":"ON",
    "sg:tags":[
        "dentist"
    ],
    "wof:name":"Grigg, Paul DDS",
    "wof:placetype":"venue"
},
  "geometry": {"coordinates":[-80.94100952150001,44.5669326782],"type":"Point"}
}