{
  "type": "Feature",
  "properties": {
    "iso:country":"CA",
    "sg:address":"2775 Avonhurst Dr",
    "sg:city":"Regina",
    "sg:classifiers":[
        {
            "category":"Shopping",
            "subcategory":"Books",
            "type":"Retail Goods"
        }
    ],
    "sg:phone":"+1 306 347 1007",
    "sg:postcode":"S4R 3J3",
    "sg:province":"SK",
    "sg:tags":[
        "dealer"
    ],
    "wof:name":"Blessings",
    "wof:placetype":"venue"
},
  "geometry": {"coordinates":[-104.62140655499999,50.4706459045],"type":"Point"}
}