{
  "type": "Feature",
  "properties": {
    "iso:country":"CA",
    "sg:address":"1340 Elmwood Dr",
    "sg:city":"Moncton",
    "sg:classifiers":[
        {
            "category":"Shopping",
            "subcategory":"Computers & Home Electronics",
            "type":"Retail Goods"
        }
    ],
    "sg:phone":"+1 506 855 7400",
    "sg:postcode":"E1H 2H3",
    "sg:province":"NB",
    "sg:tags":[
        "equipment",
        "satellite",
        "system"
    ],
    "wof:name":"Satellite Services-Programming",
    "wof:placetype":"venue"
},
  "geometry": {"coordinates":[-64.7755889893,46.1474189758],"type":"Point"}
}