{
  "type": "Feature",
  "properties": {
    "addr:full":"531 Davis Dr # 301 Newmarket ON L3Y 6P5",
    "addr:housenumber":"531;301",
    "addr:postcode":"l3y 6p5",
    "addr:street":"Davis Dr #",
    "iso:country":"CA",
    "sg:address":"531 Davis Dr # 301",
    "sg:city":"Newmarket",
    "sg:classifiers":[
        {
            "category":"Health Services",
            "subcategory":"Doctor",
            "type":"Services"
        }
    ],
    "sg:phone":"+1 905 895 4161",
    "sg:postcode":"L3Y 6P5",
    "sg:province":"ON",
    "sg:tags":[
        "physician",
        "surgeon"
    ],
    "wof:name":"Mark, Larry K MD",
    "wof:placetype":"venue"
},
  "geometry": {"coordinates":[-79.45597100000001,44.060417],"type":"Point"}
}