{
  "type": "Feature",
  "properties": {
    "addr:full":"Surrey BC V3R 4E4",
    "addr:postcode":"v3r 4e4",
    "iso:country":"CA",
    "sg:city":"Surrey",
    "sg:classifiers":[
        {
            "category":"Shopping",
            "subcategory":"Books",
            "type":"Retail Goods"
        }
    ],
    "sg:phone":"+1 604 582 2877",
    "sg:postcode":"V3R 4E4",
    "sg:province":"BC",
    "sg:tags":[
        "comic"
    ],
    "wof:name":"Comics Scene",
    "wof:placetype":"venue"
},
  "geometry": {"coordinates":[-122.801254273,49.1648292542],"type":"Point"}
}