{
  "type": "Feature",
  "properties": {
    "addr:full":"Ottawa ON K1B 4W5",
    "addr:postcode":"k1b 4w5",
    "iso:country":"CA",
    "sg:city":"Ottawa",
    "sg:classifiers":[
        {
            "category":"Organizations",
            "subcategory":"Professional Association",
            "type":"Services"
        }
    ],
    "sg:phone":"+1 613 739 3845",
    "sg:postcode":"K1B 4W5",
    "sg:province":"ON",
    "wof:name":"Hemophilia Ontario",
    "wof:placetype":"venue"
},
  "geometry": {"coordinates":[-75.609886,45.395115],"type":"Point"}
}