{
  "type": "Feature",
  "properties": {
    "iso:country":"CA",
    "sg:address":"520 Third St",
    "sg:city":"Collingwood",
    "sg:classifiers":[
        {
            "category":"Building & Trades",
            "subcategory":"Electrical",
            "type":"Services"
        }
    ],
    "sg:phone":"+1 705 445 1364",
    "sg:postcode":"L9Y 4X6",
    "sg:province":"ON",
    "sg:tags":[
        "electric",
        "contractor"
    ],
    "wof:name":"Wayne Spears Electric Ltd",
    "wof:placetype":"venue"
},
  "geometry": {"coordinates":[-80.233902,44.496937],"type":"Point"}
}