{
  "type": "Feature",
  "properties": {
    "addr:full":"12755 King George Hwy Surrey BC V3V 3K7",
    "addr:housenumber":"12755",
    "addr:postcode":"v3v 3k7",
    "addr:street":"King George Hwy",
    "iso:country":"CA",
    "sg:address":"12755 King George Hwy",
    "sg:city":"Surrey",
    "sg:classifiers":[
        {
            "category":"Autos & Motor Vehicles",
            "subcategory":"Automobile Sales",
            "type":"Retail Goods"
        }
    ],
    "sg:phone":"+1 604 580 3444",
    "sg:postcode":"V3V 3K7",
    "sg:province":"BC",
    "sg:tags":[
        "car",
        "dealer"
    ],
    "wof:name":"Quest Auto Group",
    "wof:placetype":"venue"
},
  "geometry": {"coordinates":[-122.868652,49.206509],"type":"Point"}
}