{
  "type": "Feature",
  "properties": {
    "addr:full":"Peace River AB T8S 1J7",
    "addr:postcode":"t8s 1j7",
    "iso:country":"CA",
    "sg:city":"Peace River",
    "sg:classifiers":[
        {
            "category":"Personal",
            "subcategory":"Beauty Salon",
            "type":"Services"
        }
    ],
    "sg:phone":"+1 780 624 2881",
    "sg:postcode":"T8S 1J7",
    "sg:province":"AB",
    "sg:tags":[
        "barber"
    ],
    "wof:name":"Gentlemen's Creative Choice",
    "wof:placetype":"venue"
},
  "geometry": {"coordinates":[-117.290046692,56.237197876],"type":"Point"}
}