{
  "type": "Feature",
  "properties": {
    "addr:full":"72 Ridge Rd Shannonville ON K0K 3A0",
    "addr:housenumber":"72",
    "addr:postcode":"k0k 3a0",
    "addr:street":"Ridge Rd",
    "iso:country":"CA",
    "sg:address":"72 Ridge Rd",
    "sg:city":"Shannonville",
    "sg:classifiers":[
        {
            "category":"Retail",
            "subcategory":"Auto Repair",
            "type":"Services"
        }
    ],
    "sg:phone":"+1 613 969 5503",
    "sg:postcode":"K0K 3A0",
    "sg:province":"ON",
    "sg:tags":[
        "body",
        "automobile",
        "painting"
    ],
    "wof:name":"Brant's Auto Body",
    "wof:placetype":"venue"
},
  "geometry": {"coordinates":[-77.230011,44.197327],"type":"Point"}
}