{
  "type": "Feature",
  "properties": {
    "addr:full":"1421 4E Ave LA Pocatiere QC G0R 1Z0",
    "addr:housenumber":"1421",
    "addr:postcode":"g0r 1z0",
    "addr:street":"4E Ave",
    "iso:country":"CA",
    "sg:address":"1421 4E Ave",
    "sg:city":"LA Pocatiere",
    "sg:classifiers":[
        {
            "category":"Food & Beverages",
            "subcategory":"Groceries & Convenience Stores",
            "type":"Retail Goods"
        }
    ],
    "sg:phone":"+1 418 856 1151",
    "sg:postcode":"G0R 1Z0",
    "sg:province":"QC",
    "wof:name":"Depanneur Le Pionnier",
    "wof:placetype":"venue"
},
  "geometry": {"coordinates":[-70.03224945069999,47.36901474],"type":"Point"}
}