{
  "type": "Feature",
  "properties": {
    "addr:full":"Kamloops BC V2H 1A7",
    "addr:postcode":"kamloops bc v2h 1a7",
    "iso:country":"CA",
    "sg:city":"Kamloops",
    "sg:classifiers":[
        {
            "category":"Building & Trades",
            "subcategory":"Construction",
            "type":"Services"
        }
    ],
    "sg:phone":"+1 250 372 3333",
    "sg:postcode":"V2H 1A7",
    "sg:province":"BC",
    "sg:tags":[
        "front",
        "glass",
        "store"
    ],
    "wof:name":"Kamloops Glass Ltd",
    "wof:placetype":"venue"
},
  "geometry": {"coordinates":[-120.32274627699999,50.6854095459],"type":"Point"}
}