{
  "type": "Feature",
  "properties": {
    "addr:full":"103 Moilliet St Parksville BC V9P 1K6",
    "addr:housenumber":"103",
    "addr:postcode":"v9p 1k6",
    "addr:street":"Moilliet St",
    "iso:country":"CA",
    "sg:address":"103 Moilliet St",
    "sg:city":"Parksville",
    "sg:classifiers":[
        {
            "category":"Building & Trades",
            "subcategory":"Construction",
            "type":"Services"
        }
    ],
    "sg:phone":"+1 250 248 2060",
    "sg:postcode":"V9P 1K6",
    "sg:province":"BC",
    "sg:tags":[
        "dry wall",
        "contractor"
    ],
    "wof:name":"Larry Biggs Drywall",
    "wof:placetype":"venue"
},
  "geometry": {"coordinates":[-124.323959,49.320496],"type":"Point"}
}