{
  "type": "Feature",
  "properties": {
    "iso:country":"CA",
    "sg:address":"1072 Bathurst St",
    "sg:city":"Toronto",
    "sg:classifiers":[
        {
            "category":"Shopping",
            "subcategory":"Discount & Variety Stores",
            "type":"Retail Goods"
        }
    ],
    "sg:phone":"+1 416 588 9350",
    "sg:postcode":"M5R 3G9",
    "sg:province":"ON",
    "wof:name":"Hollywood Grocery & Variety",
    "wof:placetype":"venue"
},
  "geometry": {"coordinates":[-79.4142150879,43.6722640991],"type":"Point"}
}