{
  "type": "Feature",
  "properties": {
    "iso:country":"CA",
    "sg:address":"1464 Broadway Ave",
    "sg:city":"Regina",
    "sg:classifiers":[
        {
            "category":"Recreation",
            "type":"Entertainment"
        }
    ],
    "sg:phone":"+1 306 522 1649",
    "sg:postcode":"S4P 1E2",
    "sg:province":"SK",
    "sg:tags":[
        "club",
        "curling"
    ],
    "wof:name":"Tartan Curling Club",
    "wof:placetype":"venue"
},
  "geometry": {"coordinates":[-104.600639343,50.4378356934],"type":"Point"}
}