{
  "type": "Feature",
  "properties": {
    "addr:full":"Mississauga ON L4W 1J1",
    "addr:postcode":"l4w 1j1",
    "iso:country":"CA",
    "sg:city":"Mississauga",
    "sg:classifiers":[
        {
            "category":"Restaurant",
            "type":"Food & Drink"
        }
    ],
    "sg:phone":"+1 905 624 8478",
    "sg:postcode":"L4W 1J1",
    "sg:province":"ON",
    "sg:tags":[
        "caterer"
    ],
    "wof:name":"Sandwich Shop",
    "wof:placetype":"venue"
},
  "geometry": {"coordinates":[-79.626823,43.642254],"type":"Point"}
}