{
  "type": "Feature",
  "properties": {
    "addr:full":"1680 Rue Principale Saint-Norbert QC J0K 3C0",
    "addr:housenumber":"1680",
    "addr:postcode":"j0k 3c0",
    "addr:street":"Rue Principale",
    "iso:country":"CA",
    "sg:address":"1680 Rue Principale",
    "sg:city":"Saint-Norbert",
    "sg:classifiers":[
        {
            "category":"Home & Garden",
            "subcategory":"Carpets & Floor Coverings",
            "type":"Retail Goods"
        }
    ],
    "sg:phone":"+1 450 836 4405",
    "sg:postcode":"J0K 3C0",
    "sg:province":"QC",
    "sg:tags":[
        "material"
    ],
    "wof:name":"Dubeau Parquets Ltee",
    "wof:placetype":"venue"
},
  "geometry": {"coordinates":[-73.304069519,46.1607704163],"type":"Point"}
}