{
  "type": "Feature",
  "properties": {
    "addr:full":"3065 Rue Rolland Sainte-Adele QC J8B 1C9",
    "addr:housenumber":"3065",
    "addr:postcode":"j8b 1c9",
    "addr:street":"Rue Rolland",
    "iso:country":"CA",
    "sg:address":"3065 Rue Rolland",
    "sg:city":"Sainte-Adele",
    "sg:classifiers":[
        {
            "category":"Travel",
            "subcategory":"Hotels & Motels",
            "type":"Entertainment"
        }
    ],
    "sg:phone":"+1 450 229 2225",
    "sg:postcode":"J8B 1C9",
    "sg:province":"QC",
    "wof:name":"Auberge Du P'Tit Train Du Nord",
    "wof:placetype":"venue"
},
  "geometry": {"coordinates":[-74.119957,45.940052],"type":"Point"}
}