{
  "type": "Feature",
  "properties": {
    "addr:full":"Gads Hill Station ON N0K 1J0",
    "addr:postcode":"n0k 1j0",
    "iso:country":"CA",
    "sg:city":"Gads Hill Station",
    "sg:classifiers":[
        {
            "category":"Shopping",
            "subcategory":"Discount & Variety Stores",
            "type":"Retail Goods"
        }
    ],
    "sg:phone":"+1 519 271 2493",
    "sg:postcode":"N0K 1J0",
    "sg:province":"ON",
    "wof:name":"Gadshill Gas & Variety Postal",
    "wof:placetype":"venue"
},
  "geometry": {"coordinates":[-80.922493,43.445126],"type":"Point"}
}