{
  "type": "Feature",
  "properties": {
    "addr:full":"77 Yorkville Ave Toronto ON M5R 1C1",
    "addr:housenumber":"77",
    "addr:postcode":"m5r 1c1",
    "addr:street":"Yorkville Ave",
    "iso:country":"CA",
    "sg:address":"77 Yorkville Ave",
    "sg:city":"Toronto",
    "sg:classifiers":[
        {
            "category":"Shopping",
            "subcategory":"Used Merchandise",
            "type":"Retail Goods"
        }
    ],
    "sg:phone":"+1 416 923 0962",
    "sg:postcode":"M5R 1C1",
    "sg:province":"ON",
    "sg:tags":[
        "antique"
    ],
    "wof:name":"Paisley Garden Ltd",
    "wof:placetype":"venue"
},
  "geometry": {"coordinates":[-79.391426,43.670959],"type":"Point"}
}