{
  "type": "Feature",
  "properties": {
    "iso:country":"CA",
    "sg:city":"Surrey",
    "sg:classifiers":[
        {
            "category":"Shopping",
            "subcategory":"Florist",
            "type":"Retail Goods"
        }
    ],
    "sg:phone":"+1 604 584 4343",
    "sg:postcode":"V3T 2X3",
    "sg:province":"BC",
    "wof:name":"Dean's Flowers-Dell Ctr",
    "wof:placetype":"venue"
},
  "geometry": {"coordinates":[-122.84529113799999,49.1916389465],"type":"Point"}
}