{
  "type": "Feature",
  "properties": {
    "iso:country":"CA",
    "sg:city":"Edmonton",
    "sg:classifiers":[
        {
            "category":"Professional",
            "subcategory":"Business Services",
            "type":"Services"
        }
    ],
    "sg:phone":"+1 780 917 5454",
    "sg:postcode":"T5J 2Z1",
    "sg:province":"AB",
    "sg:tags":[
        "paging",
        "answering"
    ],
    "wof:name":"Select Call Ctr Inc",
    "wof:placetype":"venue"
},
  "geometry": {"coordinates":[-113.49344635,53.5432891846],"type":"Point"}
}