{
  "type": "Feature",
  "properties": {
    "addr:full":"Courtenay BC V9N 9H4",
    "addr:postcode":"v9n 9h4",
    "iso:country":"CA",
    "sg:city":"Courtenay",
    "sg:classifiers":[
        {
            "category":"Travel",
            "subcategory":"Campground",
            "type":"Entertainment"
        }
    ],
    "sg:phone":"+1 250 338 9386",
    "sg:postcode":"V9N 9H4",
    "sg:province":"BC",
    "wof:name":"Maple Pool Campsite",
    "wof:placetype":"venue"
},
  "geometry": {"coordinates":[-124.99375915500001,49.7025718689],"type":"Point"}
}