{
  "type": "Feature",
  "properties": {
    "iso:country":"CA",
    "sg:address":"170 3rd St W",
    "sg:city":"North Vancouver",
    "sg:classifiers":[
        {
            "category":"Recreation",
            "type":"Entertainment"
        }
    ],
    "sg:phone":"+1 604 987 8815",
    "sg:postcode":"V7M 1E8",
    "sg:province":"BC",
    "sg:tags":[
        "organization",
        "hall",
        "fraternal",
        "auditorium"
    ],
    "wof:name":"Foe",
    "wof:placetype":"venue"
},
  "geometry": {"coordinates":[-123.07897186300001,49.3144760132],"type":"Point"}
}