{
  "type": "Feature",
  "properties": {
    "addr:full":"206 Main St N Morris MB R0G 1K0",
    "addr:housenumber":"206",
    "addr:postcode":"r0g 1k0",
    "addr:street":"Main St N",
    "iso:country":"CA",
    "sg:address":"206 Main St N",
    "sg:city":"Morris",
    "sg:classifiers":[
        {
            "category":"Professional",
            "subcategory":"Computer Services",
            "type":"Services"
        }
    ],
    "sg:phone":"+1 204 746 2561",
    "sg:postcode":"R0G 1K0",
    "sg:province":"MB",
    "sg:tags":[
        "internet"
    ],
    "wof:name":"Morris Shoe Store",
    "wof:placetype":"venue"
},
  "geometry": {"coordinates":[-97.364197,49.356499],"type":"Point"}
}