{
  "type": "Feature",
  "properties": {
    "addr:full":"5735 3 St SE Calgary AB T2H 1K1",
    "addr:housenumber":"5735 3",
    "addr:postcode":"t2h 1k1",
    "addr:street":"St Se",
    "iso:country":"CA",
    "sg:address":"5735 3 St SE",
    "sg:city":"Calgary",
    "sg:classifiers":[
        {
            "category":"Wholesale",
            "subcategory":"Meat",
            "type":"Manufacturing & Wholesale Goods"
        }
    ],
    "sg:phone":"+1 403 252 9000",
    "sg:postcode":"T2H 1K1",
    "sg:province":"AB",
    "sg:tags":[
        "sausage",
        "maker"
    ],
    "wof:name":"Weigles Sausage & Meat Ltd",
    "wof:placetype":"venue"
},
  "geometry": {"coordinates":[-114.057304,51.003029],"type":"Point"}
}