{
  "type": "Feature",
  "properties": {
    "addr:full":"230 Cowie Hill Rd Halifax NS B3P 2M3",
    "addr:housenumber":"230",
    "addr:postcode":"b3p 2m3",
    "addr:street":"Cowie Hill Rd",
    "iso:country":"CA",
    "sg:address":"230 Cowie Hill Rd",
    "sg:city":"Halifax",
    "sg:classifiers":[
        {
            "category":"Education",
            "subcategory":"School",
            "type":"Public Place"
        }
    ],
    "sg:phone":"+1 902 479 4298",
    "sg:postcode":"B3P 2M3",
    "sg:province":"NS",
    "wof:name":"Chebucto Heights School",
    "wof:placetype":"venue"
},
  "geometry": {"coordinates":[-63.6235084534,44.6298561096],"type":"Point"}
}