{
  "type": "Feature",
  "properties": {
    "addr:full":"722 Twelfth St New Westminster BC V3M 4J9",
    "addr:housenumber":"722",
    "addr:postcode":"v3m 4j9",
    "addr:street":"Twelfth St",
    "iso:country":"CA",
    "sg:address":"722 Twelfth St",
    "sg:city":"New Westminster",
    "sg:classifiers":[
        {
            "category":"Organizations",
            "subcategory":"Labor Organization",
            "type":"Services"
        }
    ],
    "sg:phone":"+1 604 524 1908",
    "sg:postcode":"V3M 4J9",
    "sg:province":"BC",
    "wof:name":"Cupe",
    "wof:placetype":"venue"
},
  "geometry": {"coordinates":[-122.93349499999999,49.209763],"type":"Point"}
}