{
  "type": "Feature",
  "properties": {
    "addr:full":"1172 15th St W North Vancouver BC V7P 1M9",
    "addr:housenumber":"1172",
    "addr:postcode":"v7p 1m9",
    "addr:street":"15Th St W",
    "iso:country":"CA",
    "sg:address":"1172 15th St W",
    "sg:city":"North Vancouver",
    "sg:classifiers":[
        {
            "category":"Building & Trades",
            "subcategory":"Construction",
            "type":"Services"
        }
    ],
    "sg:phone":"+1 604 986 1191",
    "sg:postcode":"V7P 1M9",
    "sg:province":"BC",
    "sg:tags":[
        "excavating",
        "contractor"
    ],
    "wof:name":"Atlas Leasing Ltd",
    "wof:placetype":"venue"
},
  "geometry": {"coordinates":[-123.097015,49.322041],"type":"Point"}
}