{
  "type": "Feature",
  "properties": {
    "addr:full":"205 Boul Iberville Repentigny QC J6A 1Z3",
    "addr:housenumber":"205",
    "addr:postcode":"j6a 1z3",
    "addr:street":"Boul Iberville",
    "iso:country":"CA",
    "sg:address":"205 Boul Iberville",
    "sg:city":"Repentigny",
    "sg:classifiers":[
        {
            "category":"Building & Trades",
            "subcategory":"Plumbing",
            "type":"Services"
        }
    ],
    "sg:phone":"+1 514 838 6665",
    "sg:postcode":"J6A 1Z3",
    "sg:province":"QC",
    "sg:tags":[
        "heating",
        "contractor"
    ],
    "wof:name":"Rmj Electricite Inc",
    "wof:placetype":"venue"
},
  "geometry": {"coordinates":[-73.467957,45.723026],"type":"Point"}
}