{
  "type": "Feature",
  "properties": {
    "addr:full":"3425 Duggan Ave New Waterford NS B1H 1P4",
    "addr:housenumber":"3425",
    "addr:postcode":"b1h 1p4",
    "addr:street":"Duggan Ave",
    "iso:country":"CA",
    "sg:address":"3425 Duggan Ave",
    "sg:city":"New Waterford",
    "sg:classifiers":[
        {
            "category":"Professional",
            "subcategory":"Business Services",
            "type":"Services"
        }
    ],
    "sg:phone":"+1 902 565 2413",
    "sg:postcode":"B1H 1P4",
    "sg:province":"NS",
    "sg:tags":[
        "diver"
    ],
    "wof:name":"Ross' Diving",
    "wof:placetype":"venue"
},
  "geometry": {"coordinates":[-60.089397,46.244835],"type":"Point"}
}