{
  "type": "Feature",
  "properties": {
    "addr:full":"Vernon BC V1T 8G4",
    "addr:postcode":"v1t 8g4",
    "iso:country":"CA",
    "sg:city":"Vernon",
    "sg:classifiers":[
        {
            "category":"Autos & Motor Vehicles",
            "subcategory":"Auto Supplies",
            "type":"Retail Goods"
        }
    ],
    "sg:phone":"+1 250 549 2862",
    "sg:postcode":"V1T 8G4",
    "sg:province":"BC",
    "sg:tags":[
        "automobile",
        "stereo",
        "radio"
    ],
    "wof:name":"Vernon Auto Sound Plus",
    "wof:placetype":"venue"
},
  "geometry": {"coordinates":[-119.266319275,50.28383255],"type":"Point"}
}