{
  "type": "Feature",
  "properties": {
    "addr:full":"123 Boul Jutras E Victoriaville QC G6P 4L7",
    "addr:housenumber":"123",
    "addr:postcode":"g6p 4l7",
    "addr:street":"Boul Jutras E",
    "iso:country":"CA",
    "sg:address":"123 Boul Jutras E",
    "sg:city":"Victoriaville",
    "sg:classifiers":[
        {
            "category":"Retail",
            "subcategory":"Auto Repair",
            "type":"Services"
        }
    ],
    "sg:phone":"+1 819 751 6060",
    "sg:postcode":"G6P 4L7",
    "sg:province":"QC",
    "sg:tags":[
        "repairing",
        "automobile",
        "muffler",
        "system",
        "exhaust"
    ],
    "wof:name":"Silencieux Pronovost Inc",
    "wof:placetype":"venue"
},
  "geometry": {"coordinates":[-71.94664,46.054466],"type":"Point"}
}