{
  "type": "Feature",
  "properties": {
    "addr:full":"Calgary AB T2E 2R8",
    "addr:postcode":"t2e 2r8",
    "iso:country":"CA",
    "sg:city":"Calgary",
    "sg:classifiers":[
        {
            "category":"Retail",
            "subcategory":"Photofinishing",
            "type":"Services"
        }
    ],
    "sg:phone":"+1 403 230 8018",
    "sg:postcode":"T2E 2R8",
    "sg:province":"AB",
    "sg:tags":[
        "photo",
        "finishing"
    ],
    "wof:name":"Tim's Multi Svc Ltd",
    "wof:placetype":"venue"
},
  "geometry": {"coordinates":[-114.06398,51.064651],"type":"Point"}
}