{
  "type": "Feature",
  "properties": {
    "addr:full":"2932 Ch Sainte-Marie Mascouche QC J7K 1N7",
    "addr:housenumber":"2932",
    "addr:postcode":"j7k 1n7",
    "addr:street":"Ch Sainte-Marie",
    "iso:country":"CA",
    "sg:address":"2932 Ch Sainte-Marie",
    "sg:city":"Mascouche",
    "sg:classifiers":[
        {
            "category":"Shopping",
            "subcategory":"Jewelry",
            "type":"Retail Goods"
        }
    ],
    "sg:phone":"+1 450 474 0534",
    "sg:postcode":"J7K 1N7",
    "sg:province":"QC",
    "sg:tags":[
        "jeweler"
    ],
    "wof:name":"Specialistes DE LA Reparation",
    "wof:placetype":"venue"
},
  "geometry": {"coordinates":[-73.6035995483,45.7483634949],"type":"Point"}
}