{
  "type": "Feature",
  "properties": {
    "iso:country":"CA",
    "sg:address":"7 Woodmount Ave",
    "sg:city":"Toronto",
    "sg:classifiers":[
        {
            "category":"Manufacturing",
            "subcategory":"Printing",
            "type":"Manufacturing & Wholesale Goods"
        }
    ],
    "sg:phone":"+1 416 421 8655",
    "sg:postcode":"M4C 3X4",
    "sg:province":"ON",
    "sg:tags":[
        "printer"
    ],
    "wof:name":"World Printing CO",
    "wof:placetype":"venue"
},
  "geometry": {"coordinates":[-79.3152084351,43.685508728],"type":"Point"}
}