{
  "type": "Feature",
  "properties": {
    "iso:country":"CA",
    "sg:address":"2939 Gulfstream Way",
    "sg:city":"Mississauga",
    "sg:classifiers":[
        {
            "category":"Wholesale",
            "subcategory":"Construction Materials",
            "type":"Manufacturing & Wholesale Goods"
        }
    ],
    "sg:phone":"+1 905 824 0477",
    "sg:postcode":"L5N 6J9",
    "sg:province":"ON",
    "sg:tags":[
        "frame",
        "industrial",
        "door"
    ],
    "wof:name":"Mel's Door Svc",
    "wof:placetype":"venue"
},
  "geometry": {"coordinates":[-79.7784194946,43.5970077515],"type":"Point"}
}