{
  "type": "Feature",
  "properties": {
    "addr:full":"Humboldt SK S0K 2A0",
    "addr:postcode":"s0k 2a0",
    "addr:street":"Humboldt",
    "iso:country":"CA",
    "sg:city":"Humboldt",
    "sg:classifiers":[
        {
            "category":"Building & Trades",
            "subcategory":"Electrical",
            "type":"Services"
        }
    ],
    "sg:phone":"+1 306 682 5617",
    "sg:postcode":"S0K 2A0",
    "sg:province":"SK",
    "sg:tags":[
        "electric",
        "contractor"
    ],
    "wof:name":"T J Electric Ltd",
    "wof:placetype":"venue"
},
  "geometry": {"coordinates":[-105.12146758999999,52.2019004822],"type":"Point"}
}