{
  "type": "Feature",
  "properties": {
    "addr:full":"Saint-Laurent QC H4T 1V6",
    "addr:postcode":"h4t 1v6",
    "iso:country":"CA",
    "sg:city":"Saint-Laurent",
    "sg:classifiers":[
        {
            "category":"Professional",
            "subcategory":"Management & Consulting",
            "type":"Services"
        }
    ],
    "sg:phone":"+1 514 331 8826",
    "sg:postcode":"H4T 1V6",
    "sg:province":"QC",
    "sg:tags":[
        "consultant",
        "elevator"
    ],
    "wof:name":"Jean Marc Caron & Assoc Inc",
    "wof:placetype":"venue"
},
  "geometry": {"coordinates":[-73.71087646479999,45.4893417358],"type":"Point"}
}