{
  "type": "Feature",
  "properties": {
    "addr:full":"650 Boul Cremazie O Montreal QC H3N 2W9",
    "addr:housenumber":"650",
    "addr:postcode":"h3n 2w9",
    "addr:street":"Boul Cremazie O",
    "iso:country":"CA",
    "sg:address":"650 Boul Cremazie O",
    "sg:city":"Montreal",
    "sg:classifiers":[
        {
            "category":"Farming",
            "subcategory":"Farm",
            "type":"Manufacturing & Wholesale Goods"
        }
    ],
    "sg:phone":"+1 514 276 0161",
    "sg:postcode":"H3N 2W9",
    "sg:province":"QC",
    "sg:tags":[
        "poultry"
    ],
    "wof:name":"Sunchef Farms Inc",
    "wof:placetype":"venue"
},
  "geometry": {"coordinates":[-73.636307,45.547638],"type":"Point"}
}