{
  "type": "Feature",
  "properties": {
    "iso:country":"CA",
    "sg:address":"399 Breithaupt St",
    "sg:city":"Kitchener",
    "sg:classifiers":[
        {
            "category":"Building & Trades",
            "subcategory":"Construction",
            "type":"Services"
        }
    ],
    "sg:phone":"+1 519 745 8686",
    "sg:postcode":"N2H 5H8",
    "sg:province":"ON",
    "sg:tags":[
        "concrete",
        "pumping"
    ],
    "wof:name":"Postma Construction",
    "wof:placetype":"venue"
},
  "geometry": {"coordinates":[-80.482468,43.460407],"type":"Point"}
}