{
  "type": "Feature",
  "properties": {
    "addr:full":"455 Dundas St Woodstock ON N4S 1C2",
    "addr:housenumber":"455",
    "addr:postcode":"n4s 1c2",
    "addr:street":"Dundas St",
    "iso:country":"CA",
    "sg:address":"455 Dundas St",
    "sg:city":"Woodstock",
    "sg:classifiers":[
        {
            "category":"Restaurant",
            "type":"Food & Drink"
        }
    ],
    "sg:phone":"+1 519 539 4224",
    "sg:postcode":"N4S 1C2",
    "sg:province":"ON",
    "wof:name":"Piccadilly Restaurant",
    "wof:placetype":"venue"
},
  "geometry": {"coordinates":[-80.75786600000001,43.130013],"type":"Point"}
}