{
  "type": "Feature",
  "properties": {
    "iso:country":"CA",
    "sg:address":"2817 Keele St",
    "sg:city":"North York",
    "sg:classifiers":[
        {
            "category":"Real Estate",
            "subcategory":"Real Estate Agent",
            "type":"Services"
        }
    ],
    "sg:phone":"+1 416 630 6661",
    "sg:postcode":"M3M 2G6",
    "sg:province":"ON",
    "wof:name":"Joseph Leonardis Real Estate",
    "wof:placetype":"venue"
},
  "geometry": {"coordinates":[-79.48258199999999,43.72982],"type":"Point"}
}