{
  "type": "Feature",
  "properties": {
    "addr:full":"6979 Yonge St North York ON M2M 3X9",
    "addr:housenumber":"6979",
    "addr:postcode":"m2m 3x9",
    "addr:street":"Yonge St",
    "iso:country":"CA",
    "sg:address":"6979 Yonge St",
    "sg:city":"North York",
    "sg:classifiers":[
        {
            "category":"Travel",
            "subcategory":"Travel Agent",
            "type":"Entertainment"
        }
    ],
    "sg:phone":"+1 416 225 8500",
    "sg:postcode":"M2M 3X9",
    "sg:province":"ON",
    "sg:tags":[
        "agency",
        "bureau"
    ],
    "wof:name":"Star Travel & Cruise Ltd",
    "wof:placetype":"venue"
},
  "geometry": {"coordinates":[-79.41997499999999,43.798],"type":"Point"}
}