{
  "type": "Feature",
  "properties": {
    "iso:country":"CA",
    "sg:address":"6979 Yonge St",
    "sg:city":"North York",
    "sg:classifiers":[
        {
            "category":"Travel",
            "subcategory":"Travel Agent",
            "type":"Entertainment"
        }
    ],
    "sg:phone":"+1 416 225 8500",
    "sg:postcode":"M2M 3X9",
    "sg:province":"ON",
    "sg:tags":[
        "agency",
        "bureau"
    ],
    "wof:name":"Star Travel & Cruise Ltd",
    "wof:placetype":"venue"
},
  "geometry": {"coordinates":[-79.419975,43.798],"type":"Point"}
}