{
  "type": "Feature",
  "properties": {
    "addr:full":"48 Boul Industriel Saint-Eustache QC J7R 5C1",
    "addr:housenumber":"48",
    "addr:postcode":"j7r 5c1",
    "addr:street":"Boul Industriel",
    "iso:country":"CA",
    "sg:address":"48 Boul Industriel",
    "sg:city":"Saint-Eustache",
    "sg:classifiers":[
        {
            "category":"Home & Garden",
            "subcategory":"Building Materials",
            "type":"Retail Goods"
        }
    ],
    "sg:phone":"+1 450 472 1810",
    "sg:postcode":"J7R 5C1",
    "sg:province":"QC",
    "wof:name":"Boiseries Mille Iles Inc",
    "wof:placetype":"venue"
},
  "geometry": {"coordinates":[-73.9195556641,45.5704498291],"type":"Point"}
}