{
  "type": "Feature",
  "properties": {
    "addr:full":"55 Folger St Kingston ON K7K 4Y7",
    "addr:housenumber":"55",
    "addr:postcode":"k7k 4y7",
    "addr:street":"Folger St",
    "iso:country":"CA",
    "sg:address":"55 Folger St",
    "sg:city":"Kingston",
    "sg:classifiers":[
        {
            "category":"Building & Trades",
            "subcategory":"Cleaning & Sanitation",
            "type":"Services"
        }
    ],
    "sg:phone":"+1 613 548 7149",
    "sg:postcode":"K7K 4Y7",
    "sg:province":"ON",
    "sg:tags":[
        "venetian",
        "blind"
    ],
    "wof:name":"Roxannes Ultrasonic Cleaning",
    "wof:placetype":"venue"
},
  "geometry": {"coordinates":[-76.48011779789999,44.2667808533],"type":"Point"}
}