{
  "type": "Feature",
  "properties": {
    "addr:full":"RR 1 Perth Road ON K0H 2L0",
    "addr:postcode":"k0h 2l0",
    "addr:street":"Rr 1 Perth Road",
    "iso:country":"CA",
    "sg:address":"RR 1",
    "sg:city":"Perth Road",
    "sg:classifiers":[
        {
            "category":"Manufacturing",
            "subcategory":"Printing",
            "type":"Manufacturing & Wholesale Goods"
        }
    ],
    "sg:phone":"+1 613 273 4752",
    "sg:postcode":"K0H 2L0",
    "sg:province":"ON",
    "sg:tags":[
        "printer"
    ],
    "wof:name":"Asap Cheques Forms & Suppli",
    "wof:placetype":"venue"
},
  "geometry": {"coordinates":[-76.491455,44.465244],"type":"Point"}
}