{
  "type": "Feature",
  "properties": {
    "addr:full":"4935 Hubalta Rd SE Calgary AB T2B 1T5",
    "addr:housenumber":"4935",
    "addr:postcode":"t2b 1t5",
    "addr:street":"Hubalta Rd Se",
    "iso:country":"CA",
    "sg:address":"4935 Hubalta Rd SE",
    "sg:city":"Calgary",
    "sg:classifiers":[
        {
            "category":"Building & Trades",
            "subcategory":"Landscaping Services",
            "type":"Services"
        }
    ],
    "sg:phone":"+1 403 248 4475",
    "sg:postcode":"T2B 1T5",
    "sg:province":"AB",
    "sg:tags":[
        "landscape",
        "contractor"
    ],
    "wof:name":"Green Country Maintenance Ltd",
    "wof:placetype":"venue"
},
  "geometry": {"coordinates":[-113.963066,51.030872],"type":"Point"}
}