{
  "type": "Feature",
  "properties": {
    "addr:full":"1905 Main St Moncton NB E1E 1H9",
    "addr:housenumber":"1905",
    "addr:postcode":"e1e 1h9",
    "addr:street":"Main St",
    "iso:country":"CA",
    "sg:address":"1905 Main St",
    "sg:city":"Moncton",
    "sg:classifiers":[
        {
            "category":"Travel",
            "subcategory":"Hotels & Motels",
            "type":"Entertainment"
        }
    ],
    "sg:phone":"+1 506 382 2587",
    "sg:postcode":"E1E 1H9",
    "sg:province":"NB",
    "wof:name":"Econo Lodge",
    "wof:placetype":"venue"
},
  "geometry": {"coordinates":[-64.8042144775,46.0757331848],"type":"Point"}
}