{
  "type": "Feature",
  "properties": {
    "addr:full":"360 Great Northern Rd Sault Ste Marie ON P6B 4Z7",
    "addr:housenumber":"360",
    "addr:postcode":"p6b 4z7",
    "addr:street":"Great Northern Rd",
    "iso:country":"CA",
    "sg:address":"360 Great Northern Rd",
    "sg:city":"Sault Ste Marie",
    "sg:classifiers":[
        {
            "category":"Travel",
            "subcategory":"Hotels & Motels",
            "type":"Entertainment"
        }
    ],
    "sg:phone":"+1 705 949 8111",
    "sg:postcode":"P6B 4Z7",
    "sg:province":"ON",
    "wof:name":"Algoma's Water Tower Inn",
    "wof:placetype":"venue"
},
  "geometry": {"coordinates":[-84.318726,46.536518],"type":"Point"}
}