{
  "type": "Feature",
  "properties": {
    "iso:country":"CA",
    "sg:address":"720 Avonwick Ave",
    "sg:city":"Mississauga",
    "sg:classifiers":[
        {
            "category":"Professional",
            "subcategory":"Management & Consulting",
            "type":"Services"
        }
    ],
    "sg:phone":"+1 905 755 9843",
    "sg:postcode":"L5R 4C6",
    "sg:province":"ON",
    "sg:tags":[
        "promotion",
        "sales"
    ],
    "wof:name":"Webber Patterson Inc",
    "wof:placetype":"venue"
},
  "geometry": {"coordinates":[-79.6863708496,43.6066818237],"type":"Point"}
}