{
  "type": "Feature",
  "properties": {
    "addr:full":"1352 110th St North Battleford SK S9A 2J1",
    "addr:housenumber":"1352",
    "addr:postcode":"s9a 2j1",
    "addr:street":"110Th St",
    "iso:country":"CA",
    "sg:address":"1352 110th St",
    "sg:city":"North Battleford",
    "sg:classifiers":[
        {
            "category":"Education",
            "subcategory":"School",
            "type":"Public Place"
        }
    ],
    "sg:phone":"+1 306 445 5152",
    "sg:postcode":"S9A 2J1",
    "sg:province":"SK",
    "wof:name":"St Mary School",
    "wof:placetype":"venue"
},
  "geometry": {"coordinates":[-108.28404998800001,52.7773170471],"type":"Point"}
}