{
  "type": "Feature",
  "properties": {
    "addr:full":"4821 51st Ave Tofield AB T0B 4J0",
    "addr:housenumber":"4821",
    "addr:postcode":"t0b 4j0",
    "addr:street":"51St Ave",
    "iso:country":"CA",
    "sg:address":"4821 51st Ave",
    "sg:city":"Tofield",
    "sg:classifiers":[
        {
            "category":"Wholesale",
            "subcategory":"Electrical",
            "type":"Manufacturing & Wholesale Goods"
        }
    ],
    "sg:phone":"+1 780 662 4443",
    "sg:postcode":"T0B 4J0",
    "sg:province":"AB",
    "sg:tags":[
        "control",
        "security",
        "system"
    ],
    "wof:name":"Video Guard Inc",
    "wof:placetype":"venue"
},
  "geometry": {"coordinates":[-112.663918,53.367146],"type":"Point"}
}