{
  "type": "Feature",
  "properties": {
    "iso:country":"CA",
    "sg:city":"Bognor",
    "sg:classifiers":[
        {
            "category":"Recreation",
            "type":"Entertainment"
        }
    ],
    "sg:phone":"+1 519 372 9771",
    "sg:postcode":"N0H 1E0",
    "sg:province":"ON",
    "sg:tags":[
        "government",
        "hall",
        "auditorium"
    ],
    "wof:name":"Bognor Community Ctr",
    "wof:placetype":"venue"
},
  "geometry": {"coordinates":[-80.74398040769999,44.5237083435],"type":"Point"}
}