{
  "type": "Feature",
  "properties": {
    "addr:full":"195 Rue Georges Saint-Augustin-DE-Desmaures QC G3A 1W7",
    "addr:housenumber":"195",
    "addr:postcode":"g3a 1w7",
    "addr:street":"Rue Georges",
    "iso:country":"CA",
    "sg:address":"195 Rue Georges",
    "sg:city":"Saint-Augustin-DE-Desmaures",
    "sg:classifiers":[
        {
            "category":"Building & Trades",
            "subcategory":"Cleaning & Sanitation",
            "type":"Services"
        }
    ],
    "sg:phone":"+1 418 871 3999",
    "sg:postcode":"G3A 1W7",
    "sg:province":"QC",
    "sg:tags":[
        "janitor"
    ],
    "wof:name":"Nettoyeur Pelican Enr",
    "wof:placetype":"venue"
},
  "geometry": {"coordinates":[-71.4060287476,46.742389679],"type":"Point"}
}