{
  "type": "Feature",
  "properties": {
    "addr:full":"330 Kingston Rd Toronto ON M4L 1T7",
    "addr:housenumber":"330",
    "addr:postcode":"m4l 1t7",
    "addr:street":"Kingston Rd",
    "iso:country":"CA",
    "sg:address":"330 Kingston Rd",
    "sg:city":"Toronto",
    "sg:classifiers":[
        {
            "category":"Health Services",
            "subcategory":"Doctor",
            "type":"Services"
        }
    ],
    "sg:phone":"+1 416 694 8144",
    "sg:postcode":"M4L 1T7",
    "sg:province":"ON",
    "sg:tags":[
        "dentist"
    ],
    "wof:name":"Shields, Kathryn DDS",
    "wof:placetype":"venue"
},
  "geometry": {"coordinates":[-79.307045,43.674896],"type":"Point"}
}