{
  "type": "Feature",
  "properties": {
    "addr:full":"28 Water E Little Current ON P0P 1K0",
    "addr:housenumber":"28",
    "addr:postcode":"p0p 1k0",
    "addr:street":"Water E",
    "iso:country":"CA",
    "sg:address":"28 Water E",
    "sg:city":"Little Current",
    "sg:classifiers":[
        {
            "category":"Government",
            "subcategory":"Office",
            "type":"Public Place"
        }
    ],
    "sg:phone":"+1 705 368 0238",
    "sg:postcode":"P0P 1K0",
    "sg:province":"ON",
    "sg:tags":[
        "village"
    ],
    "wof:name":"Northeastern Manitoulin Social",
    "wof:placetype":"venue"
},
  "geometry": {"coordinates":[-81.9225311279,45.9804992676],"type":"Point"}
}