{
  "type": "Feature",
  "properties": {
    "addr:full":"912 Tecumseh Rd E Windsor ON N8X 2S6",
    "addr:housenumber":"912",
    "addr:postcode":"n8x 2s6",
    "addr:street":"Tecumseh Rd E",
    "iso:country":"CA",
    "sg:address":"912 Tecumseh Rd E",
    "sg:city":"Windsor",
    "sg:classifiers":[
        {
            "category":"Manufacturing",
            "subcategory":"Food",
            "type":"Manufacturing & Wholesale Goods"
        }
    ],
    "sg:phone":"+1 519 256 6575",
    "sg:postcode":"N8X 2S6",
    "sg:province":"ON",
    "sg:tags":[
        "baker",
        "cookie",
        "bakery"
    ],
    "wof:name":"Adriatic Bakery",
    "wof:placetype":"venue"
},
  "geometry": {"coordinates":[-83.010963,42.299305],"type":"Point"}
}