{
  "type": "Feature",
  "properties": {
    "addr:full":"13516 80 Ave Surrey BC V3W 3C1",
    "addr:housenumber":"13516",
    "addr:postcode":"v3w 3c1",
    "addr:street":"80 Ave",
    "iso:country":"CA",
    "sg:address":"13516 80 Ave",
    "sg:city":"Surrey",
    "sg:classifiers":[
        {
            "category":"Retail",
            "subcategory":"Repair Shop",
            "type":"Services"
        }
    ],
    "sg:phone":"+1 604 596 5825",
    "sg:postcode":"V3W 3C1",
    "sg:province":"BC",
    "sg:tags":[
        "television",
        "radio"
    ],
    "wof:name":"Trans Canada Tv",
    "wof:placetype":"venue"
},
  "geometry": {"coordinates":[-122.847939,49.147953],"type":"Point"}
}