{
  "type": "Feature",
  "properties": {
    "addr:full":"96 Rue Principale Saint-Esprit QC J0K 2L0",
    "addr:housenumber":"96",
    "addr:postcode":"j0k 2l0",
    "addr:street":"Rue Principale",
    "iso:country":"CA",
    "sg:address":"96 Rue Principale",
    "sg:city":"Saint-Esprit",
    "sg:classifiers":[
        {
            "category":"Health Services",
            "subcategory":"Chiropractor",
            "type":"Services"
        }
    ],
    "sg:phone":"+1 450 839 3725",
    "sg:postcode":"J0K 2L0",
    "sg:province":"QC",
    "wof:name":"Clinique Chiro Saint-Esprit",
    "wof:placetype":"venue"
},
  "geometry": {"coordinates":[-73.6653594971,45.9026565552],"type":"Point"}
}