{
  "type": "Feature",
  "properties": {
    "addr:full":"15 Rue Marziali Bedford QC J0J 1A0",
    "addr:housenumber":"15",
    "addr:postcode":"j0j 1a0",
    "addr:street":"Rue Marziali",
    "iso:country":"CA",
    "sg:address":"15 Rue Marziali",
    "sg:city":"Bedford",
    "sg:classifiers":[
        {
            "category":"Arena",
            "subcategory":"Sports Club",
            "type":"Entertainment"
        }
    ],
    "sg:phone":"+1 450 248 3224",
    "sg:postcode":"J0J 1A0",
    "sg:province":"QC",
    "sg:tags":[
        "athletic",
        "fields",
        "stadium",
        "government"
    ],
    "wof:name":"Bedford Arena",
    "wof:placetype":"venue"
},
  "geometry": {"coordinates":[-72.99597199999999,45.1199],"type":"Point"}
}