{
  "type": "Feature",
  "properties": {
    "iso:country":"CA",
    "sg:address":"461 Parliament St",
    "sg:city":"Toronto",
    "sg:classifiers":[
        {
            "category":"Retail",
            "subcategory":"Portrait Studio",
            "type":"Services"
        }
    ],
    "sg:phone":"+1 416 922 7399",
    "sg:postcode":"M5A 3A3",
    "sg:province":"ON",
    "sg:tags":[
        "photographer"
    ],
    "wof:name":"Sooter's",
    "wof:placetype":"venue"
},
  "geometry": {"coordinates":[-79.3675231934,43.6636657715],"type":"Point"}
}