{
  "type": "Feature",
  "properties": {
    "addr:full":"2325 Preston Ave # 55 Saskatoon SK S7J 2G2",
    "addr:housenumber":"2325",
    "addr:postcode":"s7j 2g2",
    "addr:street":"Preston Ave # 55",
    "iso:country":"CA",
    "sg:address":"2325 Preston Ave # 55",
    "sg:city":"Saskatoon",
    "sg:classifiers":[
        {
            "category":"Food & Beverages",
            "subcategory":"Liquor & Beverages",
            "type":"Retail Goods"
        }
    ],
    "sg:phone":"+1 306 933 5346",
    "sg:postcode":"S7J 2G2",
    "sg:province":"SK",
    "sg:tags":[
        "store"
    ],
    "wof:name":"Liquor Board Stores",
    "wof:placetype":"venue"
},
  "geometry": {"coordinates":[-106.62247467,52.1013145447],"type":"Point"}
}