{
  "type": "Feature",
  "properties": {
    "addr:full":"3420 South Millway # 4 Mississauga ON L5L 3V4",
    "addr:housenumber":"3420",
    "addr:postcode":"l5l 3v4",
    "addr:street":"South Millway # 4",
    "iso:country":"CA",
    "sg:address":"3420 South Millway # 4",
    "sg:city":"Mississauga",
    "sg:classifiers":[
        {
            "category":"Health Services",
            "subcategory":"Health Practitioner",
            "type":"Services"
        }
    ],
    "sg:phone":"+1 905 607 7263",
    "sg:postcode":"L5L 3V4",
    "sg:province":"ON",
    "sg:tags":[
        "nurse",
        "registry"
    ],
    "wof:name":"Peridata",
    "wof:placetype":"venue"
},
  "geometry": {"coordinates":[-79.67743682859999,43.5445098877],"type":"Point"}
}