{
  "type": "Feature",
  "properties": {
    "addr:full":"4755 Av Van Horne Montreal QC H3W 1H8",
    "addr:postcode":"h3w 1h8",
    "addr:street":"Av Van Horne",
    "iso:country":"CA",
    "sg:address":"4755 Av Van Horne",
    "sg:city":"Montreal",
    "sg:classifiers":[
        {
            "category":"Shopping",
            "subcategory":"Clothing, Apparel, & Fashions",
            "type":"Retail Goods"
        }
    ],
    "sg:phone":"+1 514 340 9688",
    "sg:postcode":"H3W 1H8",
    "sg:province":"QC",
    "sg:tags":[
        "dressmaker"
    ],
    "wof:name":"Wadek Couture",
    "wof:placetype":"venue"
},
  "geometry": {"coordinates":[-73.6372833252,45.4949951172],"type":"Point"}
}