{
  "type": "Feature",
  "properties": {
    "addr:full":"100 Mallochs Point Rd Wilsons Beach NB E5E 1R9",
    "addr:housenumber":"100",
    "addr:postcode":"e5e 1r9",
    "addr:street":"Mallochs Point Rd",
    "iso:country":"CA",
    "sg:address":"100 Mallochs Point Rd",
    "sg:city":"Wilsons Beach",
    "sg:classifiers":[
        {
            "category":"Wholesale",
            "subcategory":"Seafood",
            "type":"Manufacturing & Wholesale Goods"
        }
    ],
    "sg:phone":"+1 506 752 2255",
    "sg:postcode":"E5E 1R9",
    "sg:province":"NB",
    "sg:tags":[
        "product",
        "fish",
        "prepared"
    ],
    "wof:name":"Harbour DE Loutre Products Ltd",
    "wof:placetype":"venue"
},
  "geometry": {"coordinates":[-66.93231201170001,44.9255981445],"type":"Point"}
}