{
  "type": "Feature",
  "properties": {
    "addr:full":"Banff AB T1L 1H1",
    "addr:postcode":"t1l 1h1",
    "iso:country":"CA",
    "sg:city":"Banff",
    "sg:classifiers":[
        {
            "category":"Shopping",
            "subcategory":"Clothing, Apparel, & Fashions",
            "type":"Retail Goods"
        }
    ],
    "sg:phone":"+1 403 760 7625",
    "sg:postcode":"T1L 1H1",
    "sg:province":"AB",
    "sg:tags":[
        "lingerie"
    ],
    "wof:name":"LA Senza Lingerie",
    "wof:placetype":"venue"
},
  "geometry": {"coordinates":[-115.57068633999999,51.1790275574],"type":"Point"}
}