{
  "type": "Feature",
  "properties": {
    "addr:full":"416 Main St Grandview MB R0L 0Y0",
    "addr:housenumber":"416",
    "addr:postcode":"r0l 0y0",
    "addr:street":"Main St",
    "iso:country":"CA",
    "sg:address":"416 Main St",
    "sg:city":"Grandview",
    "sg:classifiers":[
        {
            "category":"Manufacturing",
            "subcategory":"Printing",
            "type":"Manufacturing & Wholesale Goods"
        }
    ],
    "sg:phone":"+1 204 546 2555",
    "sg:postcode":"R0L 0Y0",
    "sg:province":"MB",
    "sg:tags":[
        "newspaper"
    ],
    "wof:name":"Exponent Office",
    "wof:placetype":"venue"
},
  "geometry": {"coordinates":[-100.6996,51.168411],"type":"Point"}
}