{
  "type": "Feature",
  "properties": {
    "addr:full":"16 South St St George NB E5C 3P4",
    "addr:housenumber":"16",
    "addr:postcode":"e5c 3p4",
    "addr:street":"South St",
    "iso:country":"CA",
    "sg:address":"16 South St",
    "sg:city":"St George",
    "sg:classifiers":[
        {
            "category":"Travel",
            "subcategory":"Hotels & Motels",
            "type":"Entertainment"
        }
    ],
    "sg:phone":"+1 506 755 3216",
    "sg:postcode":"E5C 3P4",
    "sg:province":"NB",
    "sg:tags":[
        "breakfast",
        "inn",
        "bed",
        "accommodation"
    ],
    "wof:name":"Hibbard House Inn",
    "wof:placetype":"venue"
},
  "geometry": {"coordinates":[-66.8196182251,45.130531311],"type":"Point"}
}