{
  "type": "Feature",
  "properties": {
    "iso:country":"CA",
    "sg:address":"3000 Boul Des Laurentides",
    "sg:city":"Vimont",
    "sg:classifiers":[
        {
            "category":"Home & Garden",
            "subcategory":"Furniture",
            "type":"Retail Goods"
        }
    ],
    "sg:phone":"+1 450 667 5557",
    "sg:postcode":"H7K 3G5",
    "sg:province":"QC",
    "sg:tags":[
        "equipment",
        "kitchen",
        "cabinet"
    ],
    "wof:name":"Gestions Dupuis & Senecal Ltee",
    "wof:placetype":"venue"
},
  "geometry": {"coordinates":[-73.739449,45.614655],"type":"Point"}
}