{
  "type": "Feature",
  "properties": {
    "addr:full":"15110 Boul Lacroix Saint-Georges QC G5Y 1R7",
    "addr:housenumber":"15110",
    "addr:postcode":"g5y 1r7",
    "addr:street":"Boul Lacroix",
    "iso:country":"CA",
    "sg:address":"15110 Boul Lacroix",
    "sg:city":"Saint-Georges",
    "sg:classifiers":[
        {
            "category":"Retail",
            "subcategory":"Laundry & Dry Cleaning",
            "type":"Services"
        }
    ],
    "sg:phone":"+1 418 227 5050",
    "sg:postcode":"G5Y 1R7",
    "sg:province":"QC",
    "sg:tags":[
        "cleaners",
        "rug",
        "carpet"
    ],
    "wof:name":"Steamatic",
    "wof:placetype":"venue"
},
  "geometry": {"coordinates":[-70.6553573608,46.1070671082],"type":"Point"}
}