{
  "type": "Feature",
  "properties": {
    "addr:full":"3897 Bathurst St North York ON M3H 5V1",
    "addr:housenumber":"3897",
    "addr:postcode":"m3h 5v1",
    "addr:street":"Bathurst St",
    "iso:country":"CA",
    "sg:address":"3897 Bathurst St",
    "sg:city":"North York",
    "sg:classifiers":[
        {
            "category":"Personal",
            "subcategory":"Beauty Salon",
            "type":"Services"
        }
    ],
    "sg:phone":"+1 416 638 3992",
    "sg:postcode":"M3H 5V1",
    "sg:province":"ON",
    "wof:name":"Hair Designers",
    "wof:placetype":"venue"
},
  "geometry": {"coordinates":[-79.435043335,43.7424163818],"type":"Point"}
}