{
  "type": "Feature",
  "properties": {
    "iso:country":"CA",
    "sg:address":"1914 Hamilton St # 700",
    "sg:city":"Regina",
    "sg:classifiers":[
        {
            "category":"Professional",
            "subcategory":"Lawyer & Legal Services",
            "type":"Services"
        }
    ],
    "sg:phone":"+1 306 522 3030",
    "sg:postcode":"S4P 3N6",
    "sg:province":"SK",
    "sg:tags":[
        "attorney"
    ],
    "wof:name":"Williams, John M",
    "wof:placetype":"venue"
},
  "geometry": {"coordinates":[-104.609604,50.448498],"type":"Point"}
}