{
  "type": "Feature",
  "properties": {
    "addr:full":"178 Glen Ave Sault Ste Marie ON P6A 5E2",
    "addr:housenumber":"178",
    "addr:postcode":"p6a 5e2",
    "addr:street":"Glen Ave",
    "iso:country":"CA",
    "sg:address":"178 Glen Ave",
    "sg:city":"Sault Ste Marie",
    "sg:classifiers":[
        {
            "category":"Education",
            "subcategory":"School",
            "type":"Public Place"
        }
    ],
    "sg:phone":"+1 705 945 5538",
    "sg:postcode":"P6A 5E2",
    "sg:province":"ON",
    "wof:name":"Sister Mary Clare Elementary",
    "wof:placetype":"venue"
},
  "geometry": {"coordinates":[-84.2681503296,46.5081710815],"type":"Point"}
}