{
  "type": "Feature",
  "properties": {
    "addr:full":"801 Lake Shore Blvd E Toronto ON M4M 1A9",
    "addr:housenumber":"801",
    "addr:postcode":"m4m 1a9",
    "addr:street":"Lake Shore Blvd E",
    "iso:country":"CA",
    "sg:address":"801 Lake Shore Blvd E",
    "sg:city":"Toronto",
    "sg:classifiers":[
        {
            "category":"Personal",
            "type":"Services"
        }
    ],
    "sg:phone":"+1 416 466 3777",
    "sg:postcode":"M4M 1A9",
    "sg:province":"ON",
    "sg:tags":[
        "program",
        "physical",
        "exercise",
        "fitness"
    ],
    "wof:name":"Mayfair Lakeshore Racquet Club",
    "wof:placetype":"venue"
},
  "geometry": {"coordinates":[-79.33950042719999,43.654045105],"type":"Point"}
}