{
  "type": "Feature",
  "properties": {
    "addr:full":"Edmonton AB T5S 1J8",
    "addr:postcode":"t5s 1j8",
    "iso:country":"CA",
    "sg:city":"Edmonton",
    "sg:classifiers":[
        {
            "category":"Insurance",
            "subcategory":"Insurance Agent",
            "type":"Services"
        }
    ],
    "sg:phone":"+1 780 484 0364",
    "sg:postcode":"T5S 1J8",
    "sg:province":"AB",
    "sg:tags":[
        "adjuster"
    ],
    "wof:name":"Shumka Craig & Moore Adjstrs",
    "wof:placetype":"venue"
},
  "geometry": {"coordinates":[-113.62097168,53.5431747437],"type":"Point"}
}