{
  "type": "Feature",
  "properties": {
    "addr:full":"848 Rte Du President-Kennedy Pintendre QC G6C 1A4",
    "addr:housenumber":"848",
    "addr:postcode":"g6c 1a4",
    "addr:street":"Rte Du President-Kennedy Pintendre",
    "iso:country":"CA",
    "sg:address":"848 Rte Du President-Kennedy",
    "sg:city":"Pintendre",
    "sg:classifiers":[
        {
            "category":"Shopping",
            "subcategory":"Clothing, Apparel, & Fashions",
            "type":"Retail Goods"
        }
    ],
    "sg:phone":"+1 418 837 4295",
    "sg:postcode":"G6C 1A4",
    "sg:province":"QC",
    "sg:tags":[
        "fur",
        "business"
    ],
    "wof:name":"Robert Boivin Inc",
    "wof:placetype":"venue"
},
  "geometry": {"coordinates":[-71.119141,46.749966],"type":"Point"}
}