{
  "type": "Feature",
  "properties": {
    "addr:full":"10 West Dr Brampton ON L6T 4Y4",
    "addr:housenumber":"10",
    "addr:postcode":"l6t 4y4",
    "addr:street":"West Dr",
    "iso:country":"CA",
    "sg:address":"10 West Dr",
    "sg:city":"Brampton",
    "sg:classifiers":[
        {
            "category":"Manufacturing",
            "subcategory":"Chemicals & Compounds",
            "type":"Manufacturing & Wholesale Goods"
        }
    ],
    "sg:phone":"+1 905 796 2222",
    "sg:postcode":"L6T 4Y4",
    "sg:province":"ON",
    "sg:tags":[
        "lithographing",
        "ink"
    ],
    "wof:name":"Sun Chemical",
    "wof:placetype":"venue"
},
  "geometry": {"coordinates":[-79.71226501460001,43.6943511963],"type":"Point"}
}