{
  "type": "Feature",
  "properties": {
    "addr:full":"818 12th St Invermere BC V0A 1K0",
    "addr:housenumber":"818",
    "addr:postcode":"v0a 1k0",
    "addr:street":"12Th St",
    "iso:country":"CA",
    "sg:address":"818 12th St",
    "sg:city":"Invermere",
    "sg:classifiers":[
        {
            "category":"Restaurant",
            "type":"Food & Drink"
        }
    ],
    "sg:phone":"+1 250 342 6344",
    "sg:postcode":"V0A 1K0",
    "sg:province":"BC",
    "wof:name":"Strand's Old House Restaurant",
    "wof:placetype":"venue"
},
  "geometry": {"coordinates":[-116.029136658,50.5043640137],"type":"Point"}
}