{
  "type": "Feature",
  "properties": {
    "addr:full":"859 Rue Saint-Georges Saint-Jerome QC J7Z 5E4",
    "addr:housenumber":"859",
    "addr:postcode":"j7z 5e4",
    "addr:street":"Rue Saint-Georges Saint-Jerome",
    "iso:country":"CA",
    "sg:address":"859 Rue Saint-Georges",
    "sg:city":"Saint-Jerome",
    "sg:classifiers":[
        {
            "category":"Professional",
            "subcategory":"Accounting & Tax Preparation",
            "type":"Services"
        }
    ],
    "sg:phone":"+1 450 431 4524",
    "sg:postcode":"J7Z 5E4",
    "sg:province":"QC",
    "sg:tags":[
        "accountant"
    ],
    "wof:name":"Lavigne, Michel",
    "wof:placetype":"venue"
},
  "geometry": {"coordinates":[-74.005028,45.791206],"type":"Point"}
}