{
  "type": "Feature",
  "properties": {
    "addr:full":"Richmond BC V6X 2T4",
    "addr:postcode":"v6x 2t4",
    "iso:country":"CA",
    "sg:city":"Richmond",
    "sg:classifiers":[
        {
            "category":"Manufacturing",
            "subcategory":"Aerospace",
            "type":"Manufacturing & Wholesale Goods"
        }
    ],
    "sg:phone":"+1 604 244 1668",
    "sg:postcode":"V6X 2T4",
    "sg:province":"BC",
    "sg:tags":[
        "engine",
        "aircraft"
    ],
    "wof:name":"Airborne Engines",
    "wof:placetype":"venue"
},
  "geometry": {"coordinates":[-123.09175109900001,49.1912727356],"type":"Point"}
}