{
  "type": "Feature",
  "properties": {
    "addr:full":"905 Baker St Cranbrook BC V1C 1A4",
    "addr:housenumber":"905",
    "addr:postcode":"bc v1c 1a4",
    "addr:street":"Baker St",
    "iso:country":"CA",
    "sg:address":"905 Baker St",
    "sg:city":"Cranbrook",
    "sg:classifiers":[
        {
            "category":"Travel",
            "subcategory":"Travel Agent",
            "type":"Entertainment"
        }
    ],
    "sg:phone":"+1 250 426 8975",
    "sg:postcode":"V1C 1A4",
    "sg:province":"BC",
    "sg:tags":[
        "agency",
        "bureau"
    ],
    "wof:name":"Uniglobe Baker St Travel Ltd",
    "wof:placetype":"venue"
},
  "geometry": {"coordinates":[-115.76831817599999,49.5120773315],"type":"Point"}
}