{
  "type": "Feature",
  "properties": {
    "addr:full":"9919 113 Ave Grande Prairie AB T8V 1W6",
    "addr:housenumber":"9919",
    "addr:postcode":"t8v 1w6",
    "addr:street":"113 Ave",
    "iso:country":"CA",
    "sg:address":"9919 113 Ave",
    "sg:city":"Grande Prairie",
    "sg:classifiers":[
        {
            "category":"Sports & Exercise",
            "subcategory":"Gym",
            "type":"Entertainment"
        }
    ],
    "sg:phone":"+1 780 538 1188",
    "sg:postcode":"T8V 1W6",
    "sg:province":"AB",
    "sg:tags":[
        "club",
        "health",
        "studio",
        "gymnasium"
    ],
    "wof:name":"Maximum Fitness",
    "wof:placetype":"venue"
},
  "geometry": {"coordinates":[-118.79227400000001,55.182274],"type":"Point"}
}