{
  "type": "Feature",
  "properties": {
    "addr:full":"1855 Brunet Dr Windsor ON N9C 3S2",
    "addr:housenumber":"1855",
    "addr:postcode":"n9c 3s2",
    "addr:street":"Brunet Dr",
    "iso:country":"CA",
    "sg:address":"1855 Brunet Dr",
    "sg:city":"Windsor",
    "sg:classifiers":[
        {
            "category":"Freight",
            "type":"Transportation"
        }
    ],
    "sg:phone":"+1 519 250 3916",
    "sg:postcode":"N9C 3S2",
    "sg:province":"ON",
    "sg:tags":[
        "broker",
        "customs"
    ],
    "wof:name":"K N Customs Brokers",
    "wof:placetype":"venue"
},
  "geometry": {"coordinates":[-83.0339126587,42.3178215027],"type":"Point"}
}