{
  "type": "Feature",
  "properties": {
    "addr:full":"633222 Hwy 10 N Orangeville ON L9W 2Z1",
    "addr:postcode":"633222;l9w 2z1",
    "addr:street":"Hwy 10 N",
    "iso:country":"CA",
    "sg:address":"633222 Hwy 10 N",
    "sg:city":"Orangeville",
    "sg:classifiers":[
        {
            "category":"Autos & Motor Vehicles",
            "subcategory":"Automobile Sales",
            "type":"Retail Goods"
        }
    ],
    "sg:phone":"+1 519 940 0222",
    "sg:postcode":"L9W 2Z1",
    "sg:province":"ON",
    "sg:tags":[
        "car",
        "dealer"
    ],
    "wof:name":"Orangeville Nissan",
    "wof:placetype":"venue"
},
  "geometry": {"coordinates":[-80.0727844238,43.9168701172],"type":"Point"}
}