{
  "type": "Feature",
  "properties": {
    "addr:full":"7557 Minster Dr W Delta BC V4C 4L8",
    "addr:housenumber":"7557",
    "addr:postcode":"v4c 4l8",
    "addr:street":"Minster Dr W",
    "iso:country":"CA",
    "sg:address":"7557 Minster Dr W",
    "sg:city":"Delta",
    "sg:classifiers":[
        {
            "category":"Freight",
            "type":"Transportation"
        }
    ],
    "sg:phone":"+1 604 596 0562",
    "sg:postcode":"V4C 4L8",
    "sg:province":"BC",
    "sg:tags":[
        "trucking"
    ],
    "wof:name":"Trans Delta Express Ltd",
    "wof:placetype":"venue"
},
  "geometry": {"coordinates":[-122.916442871,49.1397666931],"type":"Point"}
}