{
  "type": "Feature",
  "properties": {
    "addr:full":"426 Carveth's Marina Rd Lakefield ON K0L 2H0",
    "addr:housenumber":"426",
    "addr:postcode":"k0l 2h0",
    "addr:street":"Carveth'S Marina Rd",
    "iso:country":"CA",
    "sg:address":"426 Carveth's Marina Rd",
    "sg:city":"Lakefield",
    "sg:classifiers":[
        {
            "category":"Recreation",
            "subcategory":"Marina",
            "type":"Entertainment"
        }
    ],
    "sg:phone":"+1 705 652 6226",
    "sg:postcode":"K0L 2H0",
    "sg:province":"ON",
    "sg:tags":[
        "repairing",
        "boat"
    ],
    "wof:name":"Carveth's Marina Ltd",
    "wof:placetype":"venue"
},
  "geometry": {"coordinates":[-78.2727813721,44.4225082397],"type":"Point"}
}