{
  "type": "Feature",
  "properties": {
    "addr:full":"Sainte-Foy QC G2G 2R1",
    "addr:postcode":"g2g 2r1",
    "iso:country":"CA",
    "sg:city":"Sainte-Foy",
    "sg:classifiers":[
        {
            "category":"Health Services",
            "subcategory":"Doctor",
            "type":"Services"
        }
    ],
    "sg:phone":"+1 418 877 2288",
    "sg:postcode":"G2G 2R1",
    "sg:province":"QC",
    "sg:tags":[
        "clinic"
    ],
    "wof:name":"Clinique Dentaire Nicole",
    "wof:placetype":"venue"
},
  "geometry": {"coordinates":[-71.35759,46.777172],"type":"Point"}
}