{
  "type": "Feature",
  "properties": {
    "iso:country":"CA",
    "sg:address":"1115 Cardiff Blvd",
    "sg:city":"Mississauga",
    "sg:classifiers":[
        {
            "category":"Freight",
            "type":"Transportation"
        }
    ],
    "sg:phone":"+1 905 564 2115",
    "sg:postcode":"L5S 1L8",
    "sg:province":"ON",
    "sg:tags":[
        "cartage"
    ],
    "wof:name":"Canada Cartage System Ltd",
    "wof:placetype":"venue"
},
  "geometry": {"coordinates":[-79.6887969971,43.6685600281],"type":"Point"}
}