{
  "type": "Feature",
  "properties": {
    "addr:full":"66 Whites Ave Tara ON N0H 2N0",
    "addr:housenumber":"66",
    "addr:postcode":"n0h 2n0",
    "addr:street":"Whites Ave",
    "iso:country":"CA",
    "sg:address":"66 Whites Ave",
    "sg:city":"Tara",
    "sg:classifiers":[
        {
            "category":"Building & Trades",
            "subcategory":"Pest Control",
            "type":"Services"
        }
    ],
    "sg:phone":"+1 519 934 3257",
    "sg:postcode":"N0H 2N0",
    "sg:province":"ON",
    "wof:name":"Aamcott Pest Control",
    "wof:placetype":"venue"
},
  "geometry": {"coordinates":[-81.1479721069,44.4787635803],"type":"Point"}
}