{
  "type": "Feature",
  "properties": {
    "addr:full":"PO Box 4 Hussar AB T0J 1S0",
    "addr:housenumber":"po;4",
    "addr:postcode":"t0j 1s0",
    "addr:street":"Box",
    "iso:country":"CA",
    "sg:address":"PO Box 4",
    "sg:city":"Hussar",
    "sg:classifiers":[
        {
            "category":"Personal",
            "subcategory":"Beauty Salon",
            "type":"Services"
        }
    ],
    "sg:phone":"+1 403 787 3745",
    "sg:postcode":"T0J 1S0",
    "sg:province":"AB",
    "wof:name":"Hussar Hairstyling",
    "wof:placetype":"venue"
},
  "geometry": {"coordinates":[-112.676331,51.037907],"type":"Point"}
}