{
  "type": "Feature",
  "properties": {
    "addr:full":"Ash St N Porcupine Plain SK S0E 1H0",
    "addr:postcode":"s0e 1h0",
    "addr:street":"Ash St N Porcupine Plain",
    "iso:country":"CA",
    "sg:address":"Ash St N",
    "sg:city":"Porcupine Plain",
    "sg:classifiers":[
        {
            "category":"Recreation",
            "type":"Entertainment"
        }
    ],
    "sg:phone":"+1 306 278 2144",
    "sg:postcode":"S0E 1H0",
    "sg:province":"SK",
    "sg:tags":[
        "club",
        "curling"
    ],
    "wof:name":"Porcupine Plain Curling Club",
    "wof:placetype":"venue"
},
  "geometry": {"coordinates":[-103.254333,52.598064],"type":"Point"}
}