{
  "type": "Feature",
  "properties": {
    "addr:full":"Whitecourt AB T7S 1P3",
    "addr:postcode":"t7s 1p3",
    "iso:country":"CA",
    "sg:city":"Whitecourt",
    "sg:classifiers":[
        {
            "category":"Building & Trades",
            "subcategory":"Electrical",
            "type":"Services"
        }
    ],
    "sg:phone":"+1 780 778 5373",
    "sg:postcode":"T7S 1P3",
    "sg:province":"AB",
    "sg:tags":[
        "field",
        "oil",
        "electric",
        "contractor"
    ],
    "wof:name":"Select Controls Ltd",
    "wof:placetype":"venue"
},
  "geometry": {"coordinates":[-115.70787811300001,54.1394348145],"type":"Point"}
}