{
  "type": "Feature",
  "properties": {
    "addr:full":"545 Eglinton Ave E Toronto ON M4P 1N7",
    "addr:housenumber":"545",
    "addr:postcode":"m4p 1n7",
    "addr:street":"Eglinton Ave E",
    "iso:country":"CA",
    "sg:address":"545 Eglinton Ave E",
    "sg:city":"Toronto",
    "sg:classifiers":[
        {
            "category":"Health Services",
            "subcategory":"Doctor",
            "type":"Services"
        }
    ],
    "sg:phone":"+1 416 482 9533",
    "sg:postcode":"M4P 1N7",
    "sg:province":"ON",
    "sg:tags":[
        "physician",
        "surgeon"
    ],
    "wof:name":"Leitenberg, S MD",
    "wof:placetype":"venue"
},
  "geometry": {"coordinates":[-79.37916564939999,43.7105064392],"type":"Point"}
}