{
  "type": "Feature",
  "properties": {
    "iso:country":"CA",
    "sg:address":"1065 Ch DE LA Carriere",
    "sg:city":"Bedford",
    "sg:classifiers":[
        {
            "category":"Freight",
            "type":"Transportation"
        }
    ],
    "sg:phone":"+1 450 248 4422",
    "sg:postcode":"J0J 1A0",
    "sg:province":"QC",
    "sg:tags":[
        "trucking"
    ],
    "wof:name":"Transports Chalut Inc",
    "wof:placetype":"venue"
},
  "geometry": {"coordinates":[-72.98598480219999,45.1198005676],"type":"Point"}
}