{
  "type": "Feature",
  "properties": {
    "iso:country":"CA",
    "sg:address":"3365 Harvester Rd",
    "sg:city":"Burlington",
    "sg:classifiers":[
        {
            "category":"Professional",
            "subcategory":"Lawyer & Legal Services",
            "type":"Services"
        }
    ],
    "sg:phone":"+1 905 681 2476",
    "sg:postcode":"L7N 3N2",
    "sg:province":"ON",
    "sg:tags":[
        "attorney"
    ],
    "wof:name":"Brechin & Huffman",
    "wof:placetype":"venue"
},
  "geometry": {"coordinates":[-79.790543,43.358898],"type":"Point"}
}