{
  "type": "Feature",
  "properties": {
    "addr:full":"Winnipeg MB R3C 3X1",
    "addr:postcode":"r3c 3x1",
    "iso:country":"CA",
    "sg:city":"Winnipeg",
    "sg:classifiers":[
        {
            "category":"Government",
            "subcategory":"Office",
            "type":"Public Place"
        }
    ],
    "sg:phone":"+1 204 945 2510",
    "sg:postcode":"R3C 3X1",
    "sg:province":"MB",
    "wof:name":"Manitoba Treaty Entitlement",
    "wof:placetype":"venue"
},
  "geometry": {"coordinates":[-97.15228271479999,49.890209198],"type":"Point"}
}