{
  "type": "Feature",
  "properties": {
    "addr:full":"2330 2nd Ave Regina SK S4R 1A6",
    "addr:housenumber":"2330",
    "addr:postcode":"s4r 1a6",
    "addr:street":"2Nd Ave",
    "iso:country":"CA",
    "sg:address":"2330 2nd Ave",
    "sg:city":"Regina",
    "sg:classifiers":[
        {
            "category":"Organizations",
            "subcategory":"Labor Organization",
            "type":"Services"
        }
    ],
    "sg:phone":"+1 306 525 1666",
    "sg:postcode":"S4R 1A6",
    "sg:province":"SK",
    "wof:name":"Sask Union of Nurses",
    "wof:placetype":"venue"
},
  "geometry": {"coordinates":[-104.61389200000001,50.466305],"type":"Point"}
}