{
  "type": "Feature",
  "properties": {
    "addr:full":"160 Peace St Cannington ON L0E 1E0",
    "addr:housenumber":"160",
    "addr:postcode":"l0e 1e0",
    "addr:street":"Peace St",
    "iso:country":"CA",
    "sg:address":"160 Peace St",
    "sg:city":"Cannington",
    "sg:classifiers":[
        {
            "category":"Manufacturing",
            "subcategory":"Tools & Machinery",
            "type":"Manufacturing & Wholesale Goods"
        }
    ],
    "sg:phone":"+1 705 432 2535",
    "sg:postcode":"L0E 1E0",
    "sg:province":"ON",
    "sg:tags":[
        "equipment",
        "conveyor",
        "material",
        "handling",
        "conveying"
    ],
    "wof:name":"Strongco Engineered Systs Inc",
    "wof:placetype":"venue"
},
  "geometry": {"coordinates":[-79.0335235596,44.3459701538],"type":"Point"}
}