{
  "type": "Feature",
  "properties": {
    "addr:full":"284 Rue Principale Sud L'Annonciation QC J0T 1T0",
    "addr:housenumber":"284",
    "addr:postcode":"j0t 1t0",
    "addr:street":"Rue Principale Sud",
    "iso:country":"CA",
    "sg:address":"284 Rue Principale Sud",
    "sg:city":"L'Annonciation",
    "sg:classifiers":[
        {
            "category":"Organizations",
            "subcategory":"Professional Association",
            "type":"Services"
        }
    ],
    "sg:phone":"+1 819 275 1241",
    "sg:postcode":"J0T 1T0",
    "sg:province":"QC",
    "wof:name":"Action Benevole DE LA Rouge",
    "wof:placetype":"venue"
},
  "geometry": {"coordinates":[-74.8690109253,46.4084358215],"type":"Point"}
}