{
  "type": "Feature",
  "properties": {
    "iso:country":"CA",
    "sg:address":"19 River St",
    "sg:city":"Toronto",
    "sg:classifiers":[
        {
            "category":"Real Estate",
            "subcategory":"Real Estate Agent",
            "type":"Services"
        }
    ],
    "sg:phone":"+1 416 363 1888",
    "sg:postcode":"M5A 3P1",
    "sg:province":"ON",
    "wof:name":"Alfco Alliance Ltd",
    "wof:placetype":"venue"
},
  "geometry": {"coordinates":[-79.3565750122,43.6579399109],"type":"Point"}
}