{
  "type": "Feature",
  "properties": {
    "addr:full":"16244 13 Ave Surrey BC V4A 8E6",
    "addr:housenumber":"16244",
    "addr:postcode":"v4a 8e6",
    "addr:street":"13 Ave",
    "iso:country":"CA",
    "sg:address":"16244 13 Ave",
    "sg:city":"Surrey",
    "sg:classifiers":[
        {
            "category":"Education",
            "subcategory":"School",
            "type":"Public Place"
        }
    ],
    "sg:phone":"+1 604 538 7114",
    "sg:postcode":"V4A 8E6",
    "sg:province":"BC",
    "wof:name":"South Meridian Elementary Schl",
    "wof:placetype":"venue"
},
  "geometry": {"coordinates":[-122.7724,49.02599],"type":"Point"}
}