{
  "type": "Feature",
  "properties": {
    "addr:full":"111 Main St Biggar SK S0K 0M0",
    "addr:housenumber":"111",
    "addr:postcode":"s0k 0m0",
    "addr:street":"Main St",
    "iso:country":"CA",
    "sg:address":"111 Main St",
    "sg:city":"Biggar",
    "sg:classifiers":[
        {
            "category":"Restaurant",
            "type":"Food & Drink"
        }
    ],
    "sg:phone":"+1 306 948 2861",
    "sg:postcode":"S0K 0M0",
    "sg:province":"SK",
    "wof:name":"Snow White Family Restaurant",
    "wof:placetype":"venue"
},
  "geometry": {"coordinates":[-107.98658,52.054173],"type":"Point"}
}