{
  "type": "Feature",
  "properties": {
    "iso:country":"CA",
    "sg:address":"575 Harrop Dr",
    "sg:city":"Milton",
    "sg:classifiers":[
        {
            "category":"Home & Garden",
            "subcategory":"Building Materials",
            "type":"Retail Goods"
        }
    ],
    "sg:phone":"+1 905 876 4728",
    "sg:postcode":"L9T 3H3",
    "sg:province":"ON",
    "sg:tags":[
        "mixed",
        "concrete"
    ],
    "wof:name":"Lafarge Construction Materials",
    "wof:placetype":"venue"
},
  "geometry": {"coordinates":[-79.891563,43.533951],"type":"Point"}
}