{
  "type": "Feature",
  "properties": {
    "iso:country":"CA",
    "sg:address":"6133 Av Du Bocage",
    "sg:city":"Anjou",
    "sg:classifiers":[
        {
            "category":"Building & Trades",
            "subcategory":"Plumbing",
            "type":"Services"
        }
    ],
    "sg:phone":"+1 514 351 1130",
    "sg:postcode":"H1M 1X5",
    "sg:province":"QC",
    "sg:tags":[
        "ventilating",
        "refrigerating",
        "contractor"
    ],
    "wof:name":"Refrigeration Lacaille Inc",
    "wof:placetype":"venue"
},
  "geometry": {"coordinates":[-73.55201721189999,45.5931549072],"type":"Point"}
}