{
  "type": "Feature",
  "properties": {
    "addr:full":"28 Wilson St W Perth ON K7H 2M9",
    "addr:housenumber":"28",
    "addr:postcode":"k7h 2m9",
    "addr:street":"Wilson St W",
    "iso:country":"CA",
    "sg:address":"28 Wilson St W",
    "sg:city":"Perth",
    "sg:classifiers":[
        {
            "category":"Food & Beverages",
            "subcategory":"Groceries & Convenience Stores",
            "type":"Retail Goods"
        }
    ],
    "sg:phone":"+1 613 267 6024",
    "sg:postcode":"K7H 2M9",
    "sg:province":"ON",
    "sg:tags":[
        "grocer"
    ],
    "wof:name":"Mac's Convenience Stores Ltd",
    "wof:placetype":"venue"
},
  "geometry": {"coordinates":[-76.254166,44.901543],"type":"Point"}
}