{
  "type": "Feature",
  "properties": {
    "addr:full":"135 Fifth St Collingwood ON L9Y 1X3",
    "addr:housenumber":"135",
    "addr:postcode":"l9y 1x3",
    "addr:street":"Fifth St",
    "iso:country":"CA",
    "sg:address":"135 Fifth St",
    "sg:city":"Collingwood",
    "sg:classifiers":[
        {
            "category":"Freight",
            "type":"Transportation"
        }
    ],
    "sg:phone":"+1 705 444 9310",
    "sg:postcode":"L9Y 1X3",
    "sg:province":"ON",
    "sg:tags":[
        "delivery"
    ],
    "wof:name":"Quicksilver Deliveries",
    "wof:placetype":"venue"
},
  "geometry": {"coordinates":[-80.219619751,44.494682312],"type":"Point"}
}