{
  "type": "Feature",
  "properties": {
    "addr:full":"3854 Chesswood Dr North York ON M3J 2W6",
    "addr:housenumber":"3854",
    "addr:postcode":"m3j 2w6",
    "addr:street":"Chesswood Dr",
    "iso:country":"CA",
    "sg:address":"3854 Chesswood Dr",
    "sg:city":"North York",
    "sg:classifiers":[
        {
            "category":"Shopping",
            "type":"Retail Goods"
        }
    ],
    "sg:phone":"+1 416 631 6998",
    "sg:postcode":"M3J 2W6",
    "sg:province":"ON",
    "sg:tags":[
        "church",
        "religious",
        "supply"
    ],
    "wof:name":"Nazarene Spiritual Baptist",
    "wof:placetype":"venue"
},
  "geometry": {"coordinates":[-79.4746627808,43.7564125061],"type":"Point"}
}