{
  "type": "Feature",
  "properties": {
    "addr:full":"3015 Boul Sainte-Anne Beauport QC G1E 3J6",
    "addr:housenumber":"3015",
    "addr:postcode":"qc g1e 3j6",
    "addr:street":"Boul Sainte-Anne",
    "iso:country":"CA",
    "sg:address":"3015 Boul Sainte-Anne",
    "sg:city":"Beauport",
    "sg:classifiers":[
        {
            "category":"Home & Garden",
            "subcategory":"Household Appliances",
            "type":"Retail Goods"
        }
    ],
    "sg:phone":"+1 418 666 7792",
    "sg:postcode":"G1E 3J6",
    "sg:province":"QC",
    "sg:tags":[
        "cleaners",
        "vacuum"
    ],
    "wof:name":"Aspirateur Central & Domest",
    "wof:placetype":"venue"
},
  "geometry": {"coordinates":[-71.2106170654,46.8472137451],"type":"Point"}
}