{
  "type": "Feature",
  "properties": {
    "addr:full":"Saint-Laurent QC H4R 2M3",
    "addr:postcode":"h4r 2m3",
    "iso:country":"CA",
    "sg:city":"Saint-Laurent",
    "sg:classifiers":[
        {
            "category":"Banks & Credit Unions",
            "subcategory":"Investment Brokerage",
            "type":"Services"
        }
    ],
    "sg:phone":"+1 514 331 5838",
    "sg:postcode":"H4R 2M3",
    "sg:province":"QC",
    "sg:tags":[
        "consultant",
        "planning",
        "financial"
    ],
    "wof:name":"London Life Insurance CO",
    "wof:placetype":"venue"
},
  "geometry": {"coordinates":[-73.710067749,45.4928321838],"type":"Point"}
}