{
  "type": "Feature",
  "properties": {
    "addr:full":"Calgary AB T2E 1L6",
    "addr:postcode":"t2e 1l6",
    "iso:country":"CA",
    "sg:city":"Calgary",
    "sg:classifiers":[
        {
            "category":"Professional",
            "subcategory":"Lawyer & Legal Services",
            "type":"Services"
        }
    ],
    "sg:phone":"+1 403 520 2011",
    "sg:postcode":"T2E 1L6",
    "sg:province":"AB",
    "sg:tags":[
        "attorney"
    ],
    "wof:name":"Fares, Abraham",
    "wof:placetype":"venue"
},
  "geometry": {"coordinates":[-114.061485,51.067997],"type":"Point"}
}