{
  "type": "Feature",
  "properties": {
    "addr:full":"1794 Dunrobin Rd Kanata ON K2K 1X7",
    "addr:housenumber":"1794",
    "addr:postcode":"k2k 1x7",
    "addr:street":"Dunrobin Rd",
    "iso:country":"CA",
    "sg:address":"1794 Dunrobin Rd",
    "sg:city":"Kanata",
    "sg:classifiers":[
        {
            "category":"Autos & Motor Vehicles",
            "subcategory":"Fuel & Gas Station",
            "type":"Retail Goods"
        }
    ],
    "sg:phone":"+1 613 839 1804",
    "sg:postcode":"K2K 1X7",
    "sg:province":"ON",
    "sg:tags":[
        "oil"
    ],
    "wof:name":"Mac Ewen Petroleum Inc",
    "wof:placetype":"venue"
},
  "geometry": {"coordinates":[-75.9692153931,45.3828315735],"type":"Point"}
}