{
  "type": "Feature",
  "properties": {
    "addr:full":"Woodlands MB R0C 3H0",
    "addr:postcode":"r0c 3h0",
    "iso:country":"CA",
    "sg:city":"Woodlands",
    "sg:classifiers":[
        {
            "category":"Farming",
            "subcategory":"Fish & Marine Products",
            "type":"Manufacturing & Wholesale Goods"
        }
    ],
    "sg:phone":"+1 204 383 5628",
    "sg:postcode":"R0C 3H0",
    "sg:province":"MB",
    "sg:tags":[
        "wildlife"
    ],
    "wof:name":"Ace Wilderness Guiding",
    "wof:placetype":"venue"
},
  "geometry": {"coordinates":[-97.5571517944,50.1389427185],"type":"Point"}
}