{
  "type": "Feature",
  "properties": {
    "addr:full":"509 Glendale Ave Niagara on the Lake ON L0S 1J0",
    "addr:housenumber":"509",
    "addr:postcode":"l0s 1j0",
    "addr:street":"Glendale Ave;On",
    "iso:country":"CA",
    "sg:address":"509 Glendale Ave",
    "sg:city":"Niagara on the Lake",
    "sg:classifiers":[
        {
            "category":"Professional",
            "subcategory":"Management & Consulting",
            "type":"Services"
        }
    ],
    "sg:phone":"+1 905 687 8813",
    "sg:postcode":"L0S 1J0",
    "sg:province":"ON",
    "sg:tags":[
        "consultant",
        "business"
    ],
    "wof:name":"Niagara Enterprise Agency",
    "wof:placetype":"venue"
},
  "geometry": {"coordinates":[-79.1906280518,43.145565033],"type":"Point"}
}