{
  "type": "Feature",
  "properties": {
    "iso:country":"CA",
    "sg:address":"SW 7 9 6W",
    "sg:city":"St Claude",
    "sg:classifiers":[
        {
            "category":"Manufacturing",
            "subcategory":"Apparel",
            "type":"Manufacturing & Wholesale Goods"
        }
    ],
    "sg:phone":"+1 204 379 2693",
    "sg:postcode":"R0G 1Z0",
    "sg:province":"MB",
    "sg:tags":[
        "flag",
        "banner"
    ],
    "wof:name":"Ethel's Flag Svc",
    "wof:placetype":"venue"
},
  "geometry": {"coordinates":[-98.342873,49.657928],"type":"Point"}
}