{
  "type": "Feature",
  "properties": {
    "addr:full":"424 John St Burlington ON L7R 2K5",
    "addr:housenumber":"424",
    "addr:postcode":"l7r 2k5",
    "addr:street":"John St",
    "iso:country":"CA",
    "sg:address":"424 John St",
    "sg:city":"Burlington",
    "sg:classifiers":[
        {
            "category":"Local Transit",
            "type":"Transportation"
        }
    ],
    "sg:phone":"+1 905 639 0550",
    "sg:postcode":"L7R 2K5",
    "sg:province":"ON",
    "sg:tags":[
        "bus",
        "line"
    ],
    "wof:name":"Burlington Transit Terminal",
    "wof:placetype":"venue"
},
  "geometry": {"coordinates":[-79.796761,43.325565],"type":"Point"}
}