{
  "type": "Feature",
  "properties": {
    "addr:full":"110 Second Ave Coniston ON P0M 1M0",
    "addr:housenumber":"110",
    "addr:postcode":"p0m 1m0",
    "addr:street":"Second Ave",
    "iso:country":"CA",
    "sg:address":"110 Second Ave",
    "sg:city":"Coniston",
    "sg:classifiers":[
        {
            "category":"Banks & Credit Unions",
            "subcategory":"Bank",
            "type":"Services"
        }
    ],
    "sg:phone":"+1 705 694 4741",
    "sg:postcode":"P0M 1M0",
    "sg:province":"ON",
    "sg:tags":[
        "loan"
    ],
    "wof:name":"Northern Credit Union Ltd",
    "wof:placetype":"venue"
},
  "geometry": {"coordinates":[-80.8473739624,46.4931716919],"type":"Point"}
}