{
  "type": "Feature",
  "properties": {
    "addr:full":"305 6th Ave E Vancouver BC V5T 1J9",
    "addr:housenumber":"305",
    "addr:postcode":"v5t 1j9",
    "addr:street":"6Th Ave E",
    "iso:country":"CA",
    "sg:address":"305 6th Ave E",
    "sg:city":"Vancouver",
    "sg:classifiers":[
        {
            "category":"Building & Trades",
            "subcategory":"Plumbing",
            "type":"Services"
        }
    ],
    "sg:phone":"+1 604 873 1841",
    "sg:postcode":"V5T 1J9",
    "sg:province":"BC",
    "sg:tags":[
        "contractor"
    ],
    "wof:name":"C B Hodgson Plumbing & Mech",
    "wof:placetype":"venue"
},
  "geometry": {"coordinates":[-123.09852600000001,49.265625],"type":"Point"}
}