{
  "type": "Feature",
  "properties": {
    "addr:full":"5600 Rue Saint-Georges Levis QC G6V 4M5",
    "addr:housenumber":"5600",
    "addr:postcode":"g6v 4m5",
    "addr:street":"Rue Saint-Georges",
    "iso:country":"CA",
    "sg:address":"5600 Rue Saint-Georges",
    "sg:city":"Levis",
    "sg:classifiers":[
        {
            "category":"Health Services",
            "subcategory":"Chiropractor",
            "type":"Services"
        }
    ],
    "sg:phone":"+1 418 837 9745",
    "sg:postcode":"G6V 4M5",
    "sg:province":"QC",
    "wof:name":"Clinique Chiropratique Levis",
    "wof:placetype":"venue"
},
  "geometry": {"coordinates":[-71.181816,46.799416],"type":"Point"}
}