{
  "type": "Feature",
  "properties": {
    "addr:full":"615 Stamps Landing Vancouver BC V5Z 3Z1",
    "addr:housenumber":"615",
    "addr:postcode":"v5z 3z1",
    "addr:street":"Stamps Landing",
    "iso:country":"CA",
    "sg:address":"615 Stamps Landing",
    "sg:city":"Vancouver",
    "sg:classifiers":[
        {
            "category":"Building & Trades",
            "subcategory":"Landscaping Services",
            "type":"Services"
        }
    ],
    "sg:phone":"+1 604 874 9967",
    "sg:postcode":"V5Z 3Z1",
    "sg:province":"BC",
    "sg:tags":[
        "designer",
        "landscape"
    ],
    "wof:name":"Maruyama & Assoc",
    "wof:placetype":"venue"
},
  "geometry": {"coordinates":[-123.118347,49.268734],"type":"Point"}
}