{
  "type": "Feature",
  "properties": {
    "iso:country":"CA",
    "sg:address":"46 Murray St",
    "sg:city":"Ottawa",
    "sg:classifiers":[
        {
            "category":"Shopping",
            "subcategory":"Clothing, Apparel, & Fashions",
            "type":"Retail Goods"
        }
    ],
    "sg:phone":"+1 613 241 5827",
    "sg:postcode":"K1N 5M4",
    "sg:province":"ON",
    "sg:tags":[
        "hat"
    ],
    "wof:name":"Maxine's Hats & Accessories",
    "wof:placetype":"venue"
},
  "geometry": {"coordinates":[-75.69482421879999,45.429019928],"type":"Point"}
}