{
  "type": "Feature",
  "properties": {
    "addr:full":"Edwards ON K0A 1V0",
    "addr:postcode":"k0a 1v0",
    "iso:country":"CA",
    "sg:city":"Edwards",
    "sg:classifiers":[
        {
            "category":"Recreation",
            "type":"Entertainment"
        }
    ],
    "sg:phone":"+1 613 821 3737",
    "sg:postcode":"K0A 1V0",
    "sg:province":"ON",
    "sg:tags":[
        "range",
        "baseball",
        "batting"
    ],
    "wof:name":"417 Strike Zone",
    "wof:placetype":"venue"
},
  "geometry": {"coordinates":[-75.4582901001,45.3085479736],"type":"Point"}
}