{
  "type": "Feature",
  "properties": {
    "addr:full":"PO Box 2 Water Valley AB T0M 2E0",
    "addr:housenumber":"po;2",
    "addr:postcode":"t0m 2e0",
    "addr:street":"Box;Water Valley",
    "iso:country":"CA",
    "sg:address":"PO Box 2",
    "sg:city":"Water Valley",
    "sg:classifiers":[
        {
            "category":"Travel",
            "subcategory":"Campground",
            "type":"Entertainment"
        }
    ],
    "sg:phone":"+1 403 637 2117",
    "sg:postcode":"T0M 2E0",
    "sg:province":"AB",
    "wof:name":"Water Valley Rv Park",
    "wof:placetype":"venue"
},
  "geometry": {"coordinates":[-114.60555267300001,51.5038909912],"type":"Point"}
}