{
  "type": "Feature",
  "properties": {
    "addr:full":"80 Driscoll Cres Moncton NB E1E 3R8",
    "addr:housenumber":"80",
    "addr:postcode":"e1e 3r8",
    "addr:street":"Driscoll Cres",
    "iso:country":"CA",
    "sg:address":"80 Driscoll Cres",
    "sg:city":"Moncton",
    "sg:classifiers":[
        {
            "category":"Professional",
            "subcategory":"Engineering",
            "type":"Services"
        }
    ],
    "sg:phone":"+1 506 856 9671",
    "sg:postcode":"E1E 3R8",
    "sg:province":"NB",
    "sg:tags":[
        "engineer"
    ],
    "wof:name":"Comtrac Limited",
    "wof:placetype":"venue"
},
  "geometry": {"coordinates":[-64.835739,46.084805],"type":"Point"}
}