{
  "type": "Feature",
  "properties": {
    "addr:full":"4231 23 Ave NW Edmonton AB T6L 5Z8",
    "addr:housenumber":"4231",
    "addr:postcode":"t6l 5z8",
    "addr:street":"23 Ave Nw",
    "iso:country":"CA",
    "sg:address":"4231 23 Ave NW",
    "sg:city":"Edmonton",
    "sg:classifiers":[
        {
            "category":"Social Services",
            "subcategory":"Child Care",
            "type":"Services"
        }
    ],
    "sg:phone":"+1 780 461 2761",
    "sg:postcode":"T6L 5Z8",
    "sg:province":"AB",
    "wof:name":"Daly Grove Day Care",
    "wof:placetype":"venue"
},
  "geometry": {"coordinates":[-113.40529600000001,53.454758],"type":"Point"}
}