{
  "type": "Feature",
  "properties": {
    "addr:full":"16685 Edgewood Dr Surrey BC V3S 9X9",
    "addr:housenumber":"16685",
    "addr:postcode":"v3s 9x9",
    "addr:street":"Edgewood Dr",
    "iso:country":"CA",
    "sg:address":"16685 Edgewood Dr",
    "sg:city":"Surrey",
    "sg:classifiers":[
        {
            "category":"Professional",
            "subcategory":"Management & Consulting",
            "type":"Services"
        }
    ],
    "sg:phone":"+1 604 535 4227",
    "sg:postcode":"V3S 9X9",
    "sg:province":"BC",
    "sg:tags":[
        "consultant",
        "business"
    ],
    "wof:name":"Manwescana Consulting Inc",
    "wof:placetype":"venue"
},
  "geometry": {"coordinates":[-122.760246,49.042023],"type":"Point"}
}