{
  "type": "Feature",
  "properties": {
    "addr:full":"2272 Kingston Rd Scarborough ON M1N 1T9",
    "addr:housenumber":"2272",
    "addr:postcode":"m1n 1t9",
    "addr:street":"Kingston Rd",
    "iso:country":"CA",
    "sg:address":"2272 Kingston Rd",
    "sg:city":"Scarborough",
    "sg:classifiers":[
        {
            "category":"Retail",
            "subcategory":"Auto Repair",
            "type":"Services"
        }
    ],
    "sg:phone":"+1 416 266 7277",
    "sg:postcode":"M1N 1T9",
    "sg:province":"ON",
    "sg:tags":[
        "repairing",
        "automobile"
    ],
    "wof:name":"Ab's Auto Repair",
    "wof:placetype":"venue"
},
  "geometry": {"coordinates":[-79.252274,43.70517],"type":"Point"}
}