{
  "type": "Feature",
  "properties": {
    "addr:full":"Edmonton AB T5N 3W1",
    "addr:postcode":"t5n 3w1",
    "iso:country":"CA",
    "sg:city":"Edmonton",
    "sg:classifiers":[
        {
            "category":"Organizations",
            "subcategory":"Professional Association",
            "type":"Services"
        }
    ],
    "sg:phone":"+1 780 488 9088",
    "sg:postcode":"T5N 3W1",
    "sg:province":"AB",
    "wof:name":"Alberta Committee-Citizens-Dis",
    "wof:placetype":"venue"
},
  "geometry": {"coordinates":[-113.535675,53.545265],"type":"Point"}
}