{
  "type": "Feature",
  "properties": {
    "addr:full":"1548 Woodward Ave Ottawa ON K1Z 7W7",
    "addr:housenumber":"1548",
    "addr:postcode":"k1z 7w7",
    "addr:street":"Woodward Ave",
    "iso:country":"CA",
    "sg:address":"1548 Woodward Ave",
    "sg:city":"Ottawa",
    "sg:classifiers":[
        {
            "category":"Retail",
            "subcategory":"Auto Repair",
            "type":"Services"
        }
    ],
    "sg:phone":"+1 613 798 8163",
    "sg:postcode":"K1Z 7W7",
    "sg:province":"ON",
    "sg:tags":[
        "repairing",
        "automobile"
    ],
    "wof:name":"Robson Auto Ctr",
    "wof:placetype":"venue"
},
  "geometry": {"coordinates":[-75.74310302729999,45.3765792847],"type":"Point"}
}