{
  "type": "Feature",
  "properties": {
    "addr:full":"Mississauga ON L4W 4Y5",
    "addr:postcode":"l4w 4y5",
    "iso:country":"CA",
    "sg:city":"Mississauga",
    "sg:classifiers":[
        {
            "category":"Shopping",
            "subcategory":"Computers & Home Electronics",
            "type":"Retail Goods"
        }
    ],
    "sg:phone":"+1 905 602 5300",
    "sg:postcode":"L4W 4Y5",
    "sg:province":"ON",
    "sg:tags":[
        "equipment",
        "dealer",
        "consultant"
    ],
    "wof:name":"Softek Computer Svc Inc",
    "wof:placetype":"venue"
},
  "geometry": {"coordinates":[-79.5988693237,43.6562805176],"type":"Point"}
}