{
  "type": "Feature",
  "properties": {
    "addr:full":"10354 Boul Saint-Laurent Montreal QC H3L 2P3",
    "addr:housenumber":"10354",
    "addr:postcode":"h3l 2p3",
    "addr:street":"Boul Saint-Laurent",
    "iso:country":"CA",
    "sg:address":"10354 Boul Saint-Laurent",
    "sg:city":"Montreal",
    "sg:classifiers":[
        {
            "category":"Home & Garden",
            "subcategory":"Home Furnishings",
            "type":"Retail Goods"
        }
    ],
    "sg:phone":"+1 514 387 7002",
    "sg:postcode":"H3L 2P3",
    "sg:province":"QC",
    "sg:tags":[
        "lamp",
        "lighting",
        "frame",
        "shade",
        "supply"
    ],
    "wof:name":"Dello Sbarba Inc",
    "wof:placetype":"venue"
},
  "geometry": {"coordinates":[-73.665947,45.548676],"type":"Point"}
}