{
  "type": "Feature",
  "properties": {
    "addr:full":"731 1 St SE Medicine Hat AB T1A 0B3",
    "addr:housenumber":"731 1",
    "addr:postcode":"t1a 0b3",
    "addr:street":"St Se",
    "iso:country":"CA",
    "sg:address":"731 1 St SE",
    "sg:city":"Medicine Hat",
    "sg:classifiers":[
        {
            "category":"Retail",
            "subcategory":"Auto Rental",
            "type":"Services"
        }
    ],
    "sg:phone":"+1 403 528 2500",
    "sg:postcode":"T1A 0B3",
    "sg:province":"AB",
    "sg:tags":[
        "renting",
        "truck",
        "leasing"
    ],
    "wof:name":"U-Haul CO Ltd",
    "wof:placetype":"venue"
},
  "geometry": {"coordinates":[-110.67269899999999,50.042767],"type":"Point"}
}