{
  "type": "Feature",
  "properties": {
    "iso:country":"CA",
    "sg:address":"947 Boul Monseigneur-DE Laval",
    "sg:city":"Baie-Saint-Paul",
    "sg:classifiers":[
        {
            "category":"Sports & Exercise",
            "subcategory":"Bowling",
            "type":"Entertainment"
        }
    ],
    "sg:phone":"+1 418 435 6155",
    "sg:postcode":"G3Z 2W1",
    "sg:province":"QC",
    "sg:tags":[
        "center"
    ],
    "wof:name":"Salon DE Quilles-LA Baie Inc",
    "wof:placetype":"venue"
},
  "geometry": {"coordinates":[-70.5157699585,47.4438514709],"type":"Point"}
}