{
  "type": "Feature",
  "properties": {
    "addr:full":"7419 40 St NE Calgary AB T3J 4H2",
    "addr:housenumber":"7419",
    "addr:postcode":"t3j 4h2",
    "addr:street":"40 St Ne",
    "iso:country":"CA",
    "sg:address":"7419 40 St NE",
    "sg:city":"Calgary",
    "sg:classifiers":[
        {
            "category":"Wholesale",
            "subcategory":"Machinery & Supplies",
            "type":"Manufacturing & Wholesale Goods"
        }
    ],
    "sg:phone":"+1 403 571 5515",
    "sg:postcode":"T3J 4H2",
    "sg:province":"AB",
    "sg:tags":[
        "contractor"
    ],
    "wof:name":"NU Century Equipment Sales Inc",
    "wof:placetype":"venue"
},
  "geometry": {"coordinates":[-113.97654,51.119392],"type":"Point"}
}