{
  "type": "Feature",
  "properties": {
    "addr:full":"14 Atlantic Ave Placentia NL A0B 2Y0",
    "addr:housenumber":"14",
    "addr:postcode":"a0b 2y0",
    "addr:street":"Atlantic Ave",
    "iso:country":"CA",
    "sg:address":"14 Atlantic Ave",
    "sg:city":"Placentia",
    "sg:classifiers":[
        {
            "category":"Education",
            "subcategory":"Library",
            "type":"Public Place"
        }
    ],
    "sg:phone":"+1 709 227 3621",
    "sg:postcode":"A0B 2Y0",
    "sg:province":"NL",
    "wof:name":"Placentia Public Library",
    "wof:placetype":"venue"
},
  "geometry": {"coordinates":[-53.9622192383,47.2540740967],"type":"Point"}
}