{
  "type": "Feature",
  "properties": {
    "iso:country":"CA",
    "sg:address":"60 Copper Rd",
    "sg:city":"Thompson",
    "sg:classifiers":[
        {
            "category":"Social Services",
            "subcategory":"Child Care",
            "type":"Services"
        }
    ],
    "sg:phone":"+1 204 677 9007",
    "sg:postcode":"R8N 0V6",
    "sg:province":"MB",
    "wof:name":"Riverside Daycare",
    "wof:placetype":"venue"
},
  "geometry": {"coordinates":[-97.85302734379999,55.7483901978],"type":"Point"}
}