{
  "type": "Feature",
  "properties": {
    "addr:full":"300 153 Rte E Grand-Mere QC G9T 3B8",
    "addr:housenumber":"153",
    "addr:postcode":"g9t 3b8",
    "addr:street":"Rte E Grand-Mere",
    "iso:country":"CA",
    "sg:address":"300 153 Rte E",
    "sg:city":"Grand-Mere",
    "sg:classifiers":[
        {
            "category":"Food & Beverages",
            "subcategory":"Groceries & Convenience Stores",
            "type":"Retail Goods"
        }
    ],
    "sg:phone":"+1 819 538 0397",
    "sg:postcode":"G9T 3B8",
    "sg:province":"QC",
    "wof:name":"Depanneur Couche-Tard",
    "wof:placetype":"venue"
},
  "geometry": {"coordinates":[-72.69319915769999,46.6209564209],"type":"Point"}
}