{
  "type": "Feature",
  "properties": {
    "addr:full":"3105 Rue Principale Saint-Jean-Baptiste QC J0L 2B0",
    "addr:housenumber":"3105",
    "addr:postcode":"j0l 2b0",
    "addr:street":"Rue Principale",
    "iso:country":"CA",
    "sg:address":"3105 Rue Principale",
    "sg:city":"Saint-Jean-Baptiste",
    "sg:classifiers":[
        {
            "category":"Government",
            "subcategory":"Office",
            "type":"Public Place"
        }
    ],
    "sg:phone":"+1 450 467 3705",
    "sg:postcode":"J0L 2B0",
    "sg:province":"QC",
    "sg:tags":[
        "village"
    ],
    "wof:name":"St Jean Baptiste Travaux Pblcs",
    "wof:placetype":"venue"
},
  "geometry": {"coordinates":[-73.1251373291,45.5195388794],"type":"Point"}
}