{
  "type": "Feature",
  "properties": {
    "addr:full":"North Battleford SK S9A 0Z9",
    "addr:postcode":"s9a 0z9",
    "iso:country":"CA",
    "sg:city":"North Battleford",
    "sg:classifiers":[
        {
            "category":"Professional",
            "subcategory":"Lawyer & Legal Services",
            "type":"Services"
        }
    ],
    "sg:phone":"+1 306 445 3613",
    "sg:postcode":"S9A 0Z9",
    "sg:province":"SK",
    "sg:tags":[
        "attorney"
    ],
    "wof:name":"David Conroy Law Offices",
    "wof:placetype":"venue"
},
  "geometry": {"coordinates":[-108.297768,52.777298],"type":"Point"}
}