{
  "type": "Feature",
  "properties": {
    "addr:full":"102 Rue Child Coaticook QC J1A 2B3",
    "addr:housenumber":"102",
    "addr:postcode":"j1a 2b3",
    "addr:street":"Rue Child",
    "iso:country":"CA",
    "sg:address":"102 Rue Child",
    "sg:city":"Coaticook",
    "sg:classifiers":[
        {
            "category":"Insurance",
            "subcategory":"Insurance Agent",
            "type":"Services"
        }
    ],
    "sg:phone":"+1 819 849 9891",
    "sg:postcode":"J1A 2B3",
    "sg:province":"QC",
    "wof:name":"Promutuel Coaticook-Sherbrooke",
    "wof:placetype":"venue"
},
  "geometry": {"coordinates":[-71.80491600000001,45.13401],"type":"Point"}
}