{
  "type": "Feature",
  "properties": {
    "addr:full":"Pigeon Lake MA-ME-O Beach AB T0C 1X0",
    "addr:postcode":"t0c 1x0",
    "addr:street":"Pigeon",
    "iso:country":"CA",
    "sg:address":"Pigeon Lake",
    "sg:city":"MA-ME-O Beach",
    "sg:classifiers":[
        {
            "category":"Shopping",
            "subcategory":"Pharmacy",
            "type":"Retail Goods"
        }
    ],
    "sg:phone":"+1 780 586 0798",
    "sg:postcode":"T0C 1X0",
    "sg:province":"AB",
    "wof:name":"Leibel's Pharmacy Inc",
    "wof:placetype":"venue"
},
  "geometry": {"coordinates":[-113.96126599999999,52.973751],"type":"Point"}
}