{
  "type": "Feature",
  "properties": {
    "addr:full":"415 Caunaught Dr Jasper AB T0E 1E0",
    "addr:housenumber":"415",
    "addr:postcode":"t0e 1e0",
    "addr:street":"Caunaught Dr",
    "iso:country":"CA",
    "sg:address":"415 Caunaught Dr",
    "sg:city":"Jasper",
    "sg:classifiers":[
        {
            "category":"Shopping",
            "subcategory":"Books",
            "type":"Retail Goods"
        }
    ],
    "sg:phone":"+1 780 852 4767",
    "sg:postcode":"T0E 1E0",
    "sg:province":"AB",
    "sg:tags":[
        "charitable",
        "institution"
    ],
    "wof:name":"Friends of Jasper National Prk",
    "wof:placetype":"venue"
},
  "geometry": {"coordinates":[-118.078994751,52.878704071],"type":"Point"}
}