{
  "type": "Feature",
  "properties": {
    "addr:full":"Mississauga ON L4W 2W6",
    "addr:postcode":"l4w 2w6",
    "iso:country":"CA",
    "sg:city":"Mississauga",
    "sg:classifiers":[
        {
            "category":"Professional",
            "subcategory":"Accounting & Tax Preparation",
            "type":"Services"
        }
    ],
    "sg:phone":"+1 905 238 5111",
    "sg:postcode":"L4W 2W6",
    "sg:province":"ON",
    "sg:tags":[
        "accountant"
    ],
    "wof:name":"Campbell Odometers Inc",
    "wof:placetype":"venue"
},
  "geometry": {"coordinates":[-79.6384506226,43.6304397583],"type":"Point"}
}