{
  "type": "Feature",
  "properties": {
    "addr:full":"85 Queen St N Mississauga ON L5N 1A4",
    "addr:housenumber":"85",
    "addr:postcode":"l5n 1a4",
    "addr:street":"Queen St N",
    "iso:country":"CA",
    "sg:address":"85 Queen St N",
    "sg:city":"Mississauga",
    "sg:classifiers":[
        {
            "category":"Home & Garden",
            "subcategory":"Building Materials",
            "type":"Retail Goods"
        }
    ],
    "sg:phone":"+1 905 826 1117",
    "sg:postcode":"L5N 1A4",
    "sg:province":"ON",
    "wof:name":"Forest Products & Builders",
    "wof:placetype":"venue"
},
  "geometry": {"coordinates":[-79.593636,43.548782],"type":"Point"}
}