{
  "type": "Feature",
  "properties": {
    "addr:full":"1717 Osler St Regina SK S4P 3W3",
    "addr:housenumber":"1717",
    "addr:postcode":"s4p 3w3",
    "addr:street":"Osler St",
    "iso:country":"CA",
    "sg:address":"1717 Osler St",
    "sg:city":"Regina",
    "sg:classifiers":[
        {
            "category":"Government",
            "subcategory":"Police Station",
            "type":"Public Place"
        }
    ],
    "sg:phone":"+1 306 777 6500",
    "sg:postcode":"S4P 3W3",
    "sg:province":"SK",
    "sg:tags":[
        "department"
    ],
    "wof:name":"Regina Police",
    "wof:placetype":"venue"
},
  "geometry": {"coordinates":[-104.604766846,50.4515686035],"type":"Point"}
}