{
  "type": "Feature",
  "properties": {
    "iso:country":"CA",
    "sg:address":"120 Lancing Dr",
    "sg:city":"Hamilton",
    "sg:classifiers":[
        {
            "category":"Building & Trades",
            "subcategory":"Construction",
            "type":"Services"
        }
    ],
    "sg:phone":"+1 905 388 8881",
    "sg:postcode":"L8W 3A1",
    "sg:province":"ON",
    "sg:tags":[
        "painter"
    ],
    "wof:name":"Northern Painters",
    "wof:placetype":"venue"
},
  "geometry": {"coordinates":[-79.8409576416,43.1917800903],"type":"Point"}
}