{
  "type": "Feature",
  "properties": {
    "addr:full":"Mississauga ON L4X 2Z5",
    "addr:postcode":"l4x 2z5",
    "iso:country":"CA",
    "sg:city":"Mississauga",
    "sg:classifiers":[
        {
            "category":"Wholesale",
            "subcategory":"Electrical",
            "type":"Manufacturing & Wholesale Goods"
        }
    ],
    "sg:phone":"+1 905 615 8585",
    "sg:postcode":"L4X 2Z5",
    "sg:province":"ON",
    "sg:tags":[
        "sound",
        "equipment",
        "system"
    ],
    "wof:name":"Mac Millan Group Sound & Lghtg",
    "wof:placetype":"venue"
},
  "geometry": {"coordinates":[-79.5670623779,43.6098518372],"type":"Point"}
}