{
  "type": "Feature",
  "properties": {
    "addr:full":"4625 Boul Saint-Joseph Saint-Nicephore QC J2A 1C2",
    "addr:housenumber":"4625",
    "addr:postcode":"j2a 1c2",
    "addr:street":"Boul Saint-Joseph Saint-Nicephore",
    "iso:country":"CA",
    "sg:address":"4625 Boul Saint-Joseph",
    "sg:city":"Saint-Nicephore",
    "sg:classifiers":[
        {
            "category":"Building & Trades",
            "subcategory":"Construction",
            "type":"Services"
        }
    ],
    "sg:phone":"+1 819 477 1123",
    "sg:postcode":"J2A 1C2",
    "sg:province":"QC",
    "sg:tags":[
        "builder",
        "system",
        "air",
        "conditioning",
        "contractor",
        "repairer",
        "chimney"
    ],
    "wof:name":"Cheminee Drummond",
    "wof:placetype":"venue"
},
  "geometry": {"coordinates":[-72.426864624,45.8352050781],"type":"Point"}
}