{
  "type": "Feature",
  "properties": {
    "addr:full":"383 Rang Notre-Dame Saint-Chrysostome QC J0S 1R0",
    "addr:housenumber":"383",
    "addr:postcode":"j0s 1r0",
    "addr:street":"Rang Notre-Dame",
    "iso:country":"CA",
    "sg:address":"383 Rang Notre-Dame",
    "sg:city":"Saint-Chrysostome",
    "sg:classifiers":[
        {
            "category":"Manufacturing",
            "subcategory":"Apparel",
            "type":"Manufacturing & Wholesale Goods"
        }
    ],
    "sg:phone":"+1 450 826 4691",
    "sg:postcode":"J0S 1R0",
    "sg:province":"QC",
    "sg:tags":[
        "sewing",
        "contractor"
    ],
    "wof:name":"Chandely Sportwear Inc",
    "wof:placetype":"venue"
},
  "geometry": {"coordinates":[-73.7642440796,45.0896987915],"type":"Point"}
}