{
  "type": "Feature",
  "properties": {
    "addr:full":"28 Oxford St W London ON N6H 1R3",
    "addr:housenumber":"28",
    "addr:postcode":"n6h 1r3",
    "addr:street":"Oxford St W",
    "iso:country":"CA",
    "sg:address":"28 Oxford St W",
    "sg:city":"London",
    "sg:classifiers":[
        {
            "category":"Personal",
            "subcategory":"Shoe Repair & Shine",
            "type":"Services"
        }
    ],
    "sg:phone":"+1 519 433 0751",
    "sg:postcode":"N6H 1R3",
    "sg:province":"ON",
    "sg:tags":[
        "repairing",
        "boot"
    ],
    "wof:name":"Joseph's Shoe Store & Repair",
    "wof:placetype":"venue"
},
  "geometry": {"coordinates":[-81.2631988525,42.9923973083],"type":"Point"}
}