{
  "type": "Feature",
  "properties": {
    "addr:full":"8490 Av Pierre-Martin Montreal QC H1E 1E8",
    "addr:housenumber":"8490",
    "addr:postcode":"h1e 1e8",
    "addr:street":"Av Pierre-Martin",
    "iso:country":"CA",
    "sg:address":"8490 Av Pierre-Martin",
    "sg:city":"Montreal",
    "sg:classifiers":[
        {
            "category":"Building & Trades",
            "subcategory":"Construction",
            "type":"Services"
        }
    ],
    "sg:phone":"+1 514 881 9692",
    "sg:postcode":"H1E 1E8",
    "sg:province":"QC",
    "sg:tags":[
        "sewer",
        "contractor"
    ],
    "wof:name":"Action R-Vac Inc",
    "wof:placetype":"venue"
},
  "geometry": {"coordinates":[-73.591194,45.647038],"type":"Point"}
}