{
  "type": "Feature",
  "properties": {
    "addr:full":"10471 Whistler Pl Richmond BC V7E 4C6",
    "addr:housenumber":"10471",
    "addr:postcode":"v7e 4c6",
    "addr:street":"Whistler Pl",
    "iso:country":"CA",
    "sg:address":"10471 Whistler Pl",
    "sg:city":"Richmond",
    "sg:classifiers":[
        {
            "category":"Real Estate",
            "subcategory":"Real Estate Agent",
            "type":"Services"
        }
    ],
    "sg:phone":"+1 604 271 0220",
    "sg:postcode":"V7E 4C6",
    "sg:province":"BC",
    "sg:tags":[
        "management"
    ],
    "wof:name":"Bower Property Management Inc",
    "wof:placetype":"venue"
},
  "geometry": {"coordinates":[-123.149422,49.13644],"type":"Point"}
}