{
  "type": "Feature",
  "properties": {
    "addr:full":"7931 13th Ave Burnaby BC V3N 2E8",
    "addr:housenumber":"7931",
    "addr:postcode":"v3n 2e8",
    "addr:street":"13Th Ave",
    "iso:country":"CA",
    "sg:address":"7931 13th Ave",
    "sg:city":"Burnaby",
    "sg:classifiers":[
        {
            "category":"Wholesale",
            "subcategory":"Hardware",
            "type":"Manufacturing & Wholesale Goods"
        }
    ],
    "sg:phone":"+1 604 532 7575",
    "sg:postcode":"V3N 2E8",
    "sg:province":"BC",
    "sg:tags":[
        "refrigerating"
    ],
    "wof:name":"Crystal Refrigeration & Ac",
    "wof:placetype":"venue"
},
  "geometry": {"coordinates":[-122.929565,49.221878],"type":"Point"}
}