{
  "type": "Feature",
  "properties": {
    "iso:country":"CA",
    "sg:address":"7931 13th Ave",
    "sg:city":"Burnaby",
    "sg:classifiers":[
        {
            "category":"Wholesale",
            "subcategory":"Hardware",
            "type":"Manufacturing & Wholesale Goods"
        }
    ],
    "sg:phone":"+1 604 532 7575",
    "sg:postcode":"V3N 2E8",
    "sg:province":"BC",
    "sg:tags":[
        "refrigerating"
    ],
    "wof:name":"Crystal Refrigeration & Ac",
    "wof:placetype":"venue"
},
  "geometry": {"coordinates":[-122.929565,49.221878],"type":"Point"}
}