{
  "type": "Feature",
  "properties": {
    "addr:full":"Winnipeg MB R3J 0K8",
    "addr:postcode":"r3j 0k8",
    "iso:country":"CA",
    "sg:city":"Winnipeg",
    "sg:classifiers":[
        {
            "category":"Professional",
            "subcategory":"Business Services",
            "type":"Services"
        }
    ],
    "sg:phone":"+1 204 885 9323",
    "sg:postcode":"R3J 0K8",
    "sg:province":"MB",
    "sg:tags":[
        "interior",
        "consultant",
        "design",
        "architect",
        "decorator"
    ],
    "wof:name":"Friesen Tokar Architects",
    "wof:placetype":"venue"
},
  "geometry": {"coordinates":[-97.22994199999999,49.877697],"type":"Point"}
}