{
  "type": "Feature",
  "properties": {
    "addr:full":"1176 Nicholson Rd Estevan SK S4A 0H3",
    "addr:housenumber":"1176",
    "addr:postcode":"s4a 0h3",
    "addr:street":"Nicholson Rd",
    "iso:country":"CA",
    "sg:address":"1176 Nicholson Rd",
    "sg:city":"Estevan",
    "sg:classifiers":[
        {
            "category":"Health Services",
            "subcategory":"Hospital",
            "type":"Services"
        }
    ],
    "sg:phone":"+1 306 634 0400",
    "sg:postcode":"S4A 0H3",
    "sg:province":"SK",
    "wof:name":"St Joseph's Hospital",
    "wof:placetype":"venue"
},
  "geometry": {"coordinates":[-103.011391,49.151367],"type":"Point"}
}