{
  "type": "Feature",
  "properties": {
    "iso:country":"CA",
    "sg:address":"785 Ch DE Chambly",
    "sg:city":"Longueuil",
    "sg:classifiers":[
        {
            "category":"Real Estate",
            "subcategory":"Developer",
            "type":"Services"
        }
    ],
    "sg:phone":"+1 450 463 2224",
    "sg:postcode":"J4H 3M2",
    "sg:province":"QC",
    "sg:tags":[
        "company",
        "land"
    ],
    "wof:name":"Groupe Cooke Bombardier Lesage",
    "wof:placetype":"venue"
},
  "geometry": {"coordinates":[-73.497887,45.536411],"type":"Point"}
}