{
  "type": "Feature",
  "properties": {
    "addr:full":"23 Steeles Ave E North York ON M2M 3Y2",
    "addr:housenumber":"23",
    "addr:postcode":"m2m 3y2",
    "addr:street":"Steeles Ave E",
    "iso:country":"CA",
    "sg:address":"23 Steeles Ave E",
    "sg:city":"North York",
    "sg:classifiers":[
        {
            "category":"Recreation",
            "type":"Entertainment"
        }
    ],
    "sg:phone":"+1 416 225 5818",
    "sg:postcode":"M2M 3Y2",
    "sg:province":"ON",
    "sg:tags":[
        "astrologer"
    ],
    "wof:name":"Psychic Astrology & Taro Card",
    "wof:placetype":"venue"
},
  "geometry": {"coordinates":[-79.41817500000001,43.79829],"type":"Point"}
}