{
  "type": "Feature",
  "properties": {
    "addr:full":"5690 Wyandotte St E Windsor ON N8S 1M3",
    "addr:housenumber":"5690",
    "addr:postcode":"n8s 1m3",
    "addr:street":"Wyandotte St E",
    "iso:country":"CA",
    "sg:address":"5690 Wyandotte St E",
    "sg:city":"Windsor",
    "sg:classifiers":[
        {
            "category":"Banks & Credit Unions",
            "subcategory":"Bank",
            "type":"Services"
        }
    ],
    "sg:phone":"+1 519 944 7300",
    "sg:postcode":"N8S 1M3",
    "sg:province":"ON",
    "wof:name":"Cibc",
    "wof:placetype":"venue"
},
  "geometry": {"coordinates":[-82.968628,42.328671],"type":"Point"}
}