{
  "type": "Feature",
  "properties": {
    "addr:full":"44 Ch Des Ursulines Stanstead QC J0B 3E0",
    "addr:housenumber":"44",
    "addr:postcode":"j0b 3e0",
    "addr:street":"Ch Des Ursulines",
    "iso:country":"CA",
    "sg:address":"44 Ch Des Ursulines",
    "sg:city":"Stanstead",
    "sg:phone":"+1 819 876 2211",
    "sg:postcode":"J0B 3E0",
    "sg:province":"QC",
    "sg:tags":[
        "lubricant"
    ],
    "wof:name":"Asalco Inc",
    "wof:placetype":"venue"
},
  "geometry": {"coordinates":[-72.0847167969,45.0204734802],"type":"Point"}
}