{
  "type": "Feature",
  "properties": {
    "iso:country":"CA",
    "sg:address":"103 Humber Cres",
    "sg:city":"King City",
    "sg:classifiers":[
        {
            "category":"Building & Trades",
            "subcategory":"Construction",
            "type":"Services"
        }
    ],
    "sg:phone":"+1 905 833 0390",
    "sg:postcode":"L7B 1J3",
    "sg:province":"ON",
    "sg:tags":[
        "painter"
    ],
    "wof:name":"Chris S Pedersen Painting",
    "wof:placetype":"venue"
},
  "geometry": {"coordinates":[-79.5320739746,43.9306182861],"type":"Point"}
}