{
  "type": "Feature",
  "properties": {
    "addr:full":"8820 Beckwith Rd Richmond BC V6X 1V5",
    "addr:housenumber":"8820",
    "addr:postcode":"v6x 1v5",
    "addr:street":"Beckwith Rd",
    "iso:country":"CA",
    "sg:address":"8820 Beckwith Rd",
    "sg:city":"Richmond",
    "sg:classifiers":[
        {
            "category":"Retail",
            "subcategory":"Auto Repair",
            "type":"Services"
        }
    ],
    "sg:phone":"+1 604 273 6933",
    "sg:postcode":"V6X 1V5",
    "sg:province":"BC",
    "sg:tags":[
        "truck"
    ],
    "wof:name":"Ted's Truck Trailer & Auto",
    "wof:placetype":"venue"
},
  "geometry": {"coordinates":[-123.12688446,49.1936912537],"type":"Point"}
}