{
  "type": "Feature",
  "properties": {
    "addr:full":"16 Packham Rd Stratford ON N5A 6T6",
    "addr:housenumber":"16",
    "addr:postcode":"n5a 6t6",
    "addr:street":"Packham Rd",
    "iso:country":"CA",
    "sg:address":"16 Packham Rd",
    "sg:city":"Stratford",
    "sg:classifiers":[
        {
            "category":"Manufacturing",
            "subcategory":"Printing",
            "type":"Manufacturing & Wholesale Goods"
        }
    ],
    "sg:phone":"+1 519 271 2220",
    "sg:postcode":"N5A 6T6",
    "sg:province":"ON",
    "sg:tags":[
        "newspaper"
    ],
    "wof:name":"Beacon Herald",
    "wof:placetype":"venue"
},
  "geometry": {"coordinates":[-81.003418,43.348454],"type":"Point"}
}