{
  "type": "Feature",
  "properties": {
    "addr:full":"Vancouver BC V6P 4Z4",
    "addr:postcode":"v6p 4z4",
    "iso:country":"CA",
    "sg:city":"Vancouver",
    "sg:classifiers":[
        {
            "category":"Restaurant",
            "type":"Food & Drink"
        }
    ],
    "sg:phone":"+1 604 261 2238",
    "sg:postcode":"V6P 4Z4",
    "sg:province":"BC",
    "wof:name":"Granville Chinese Seafood",
    "wof:placetype":"venue"
},
  "geometry": {"coordinates":[-123.14024353000001,49.2115211487],"type":"Point"}
}