{
  "type": "Feature",
  "properties": {
    "addr:full":"Montreal QC H3A 1M8",
    "addr:postcode":"h3a 1m8",
    "iso:country":"CA",
    "sg:city":"Montreal",
    "sg:classifiers":[
        {
            "category":"Food & Beverages",
            "subcategory":"Bakery",
            "type":"Retail Goods"
        }
    ],
    "sg:phone":"+1 514 282 0953",
    "sg:postcode":"H3A 1M8",
    "sg:province":"QC",
    "wof:name":"Mmmuffins",
    "wof:placetype":"venue"
},
  "geometry": {"coordinates":[-73.55805969239999,45.5184402466],"type":"Point"}
}