{
  "type": "Feature",
  "properties": {
    "addr:full":"1250 Stittsville Main St Stittsville ON K2S 1S9",
    "addr:housenumber":"1250",
    "addr:postcode":"k2s 1s9",
    "addr:street":"Stittsville Main St",
    "iso:country":"CA",
    "sg:address":"1250 Stittsville Main St",
    "sg:city":"Stittsville",
    "sg:classifiers":[
        {
            "category":"Retail",
            "subcategory":"Laundry & Dry Cleaning",
            "type":"Services"
        }
    ],
    "sg:phone":"+1 613 831 4730",
    "sg:postcode":"K2S 1S9",
    "sg:province":"ON",
    "sg:tags":[
        "cleaners"
    ],
    "wof:name":"Hillary's",
    "wof:placetype":"venue"
},
  "geometry": {"coordinates":[-75.93045806879999,45.2689743042],"type":"Point"}
}