{
  "type": "Feature",
  "properties": {
    "addr:full":"Calgary AB T3E 6V9",
    "addr:postcode":"t3e 6v9",
    "iso:country":"CA",
    "sg:city":"Calgary",
    "sg:classifiers":[
        {
            "category":"Real Estate",
            "subcategory":"Real Estate Agent",
            "type":"Services"
        }
    ],
    "sg:phone":"+1 403 246 2746",
    "sg:postcode":"T3E 6V9",
    "sg:province":"AB",
    "sg:tags":[
        "housing",
        "cooperative"
    ],
    "wof:name":"Sarcee Meadows Hsng CO-OP Ltd",
    "wof:placetype":"venue"
},
  "geometry": {"coordinates":[-114.13567352299999,51.0170402527],"type":"Point"}
}