{
  "type": "Feature",
  "properties": {
    "addr:full":"Whistler BC V0N 1B2",
    "addr:postcode":"v0n 1b2",
    "iso:country":"CA",
    "sg:city":"Whistler",
    "sg:classifiers":[
        {
            "category":"Health Services",
            "subcategory":"Doctor",
            "type":"Services"
        }
    ],
    "sg:phone":"+1 604 938 1550",
    "sg:postcode":"V0N 1B2",
    "sg:province":"BC",
    "sg:tags":[
        "dentist"
    ],
    "wof:name":"Rivera, Michael DDS",
    "wof:placetype":"venue"
},
  "geometry": {"coordinates":[-122.992492676,50.0942382812],"type":"Point"}
}