{
  "type": "Feature",
  "properties": {
    "addr:full":"368 Mill St Dundas ON L9H 2M1",
    "addr:housenumber":"368",
    "addr:postcode":"l9h 2m1",
    "addr:street":"Mill St",
    "iso:country":"CA",
    "sg:address":"368 Mill St",
    "sg:city":"Dundas",
    "sg:classifiers":[
        {
            "category":"Home & Garden",
            "subcategory":"Garden Supply",
            "type":"Retail Goods"
        }
    ],
    "sg:phone":"+1 905 628 3055",
    "sg:postcode":"L9H 2M1",
    "sg:province":"ON",
    "sg:tags":[
        "lawn",
        "mower"
    ],
    "wof:name":"Windmill Power Equipment Ltd",
    "wof:placetype":"venue"
},
  "geometry": {"coordinates":[-79.9732666016,43.2676620483],"type":"Point"}
}