{
  "type": "Feature",
  "properties": {
    "addr:full":"159 Hastings St N Bancroft ON K0L 1C0",
    "addr:housenumber":"159",
    "addr:postcode":"k0l 1c0",
    "addr:street":"Hastings St N",
    "iso:country":"CA",
    "sg:address":"159 Hastings St N",
    "sg:city":"Bancroft",
    "sg:classifiers":[
        {
            "category":"Insurance",
            "subcategory":"Insurance Agent",
            "type":"Services"
        }
    ],
    "sg:phone":"+1 613 332 3455",
    "sg:postcode":"K0L 1C0",
    "sg:province":"ON",
    "wof:name":"Clarke Gaebel Rl Est & Ins Ltd",
    "wof:placetype":"venue"
},
  "geometry": {"coordinates":[-77.8588180542,45.0648880005],"type":"Point"}
}