{
  "type": "Feature",
  "properties": {
    "addr:full":"54 Atomic Ave Etobicoke ON M8Z 5L1",
    "addr:housenumber":"54",
    "addr:postcode":"m8z 5l1",
    "addr:street":"Atomic Ave",
    "iso:country":"CA",
    "sg:address":"54 Atomic Ave",
    "sg:city":"Etobicoke",
    "sg:classifiers":[
        {
            "category":"Wholesale",
            "subcategory":"Stationery",
            "type":"Manufacturing & Wholesale Goods"
        }
    ],
    "sg:phone":"+1 416 253 7441",
    "sg:postcode":"M8Z 5L1",
    "sg:province":"ON",
    "sg:tags":[
        "packaging",
        "fiber",
        "machinery"
    ],
    "wof:name":"Coleman Containers Ltd",
    "wof:placetype":"venue"
},
  "geometry": {"coordinates":[-79.54205322270001,43.619972229],"type":"Point"}
}