{
  "type": "Feature",
  "properties": {
    "addr:full":"60 Rue DE L'Eglise Verdun QC H4G 2L9",
    "addr:housenumber":"60",
    "addr:postcode":"h4g 2l9",
    "addr:street":"Rue De L'Eglise",
    "iso:country":"CA",
    "sg:address":"60 Rue DE L'Eglise",
    "sg:city":"Verdun",
    "sg:classifiers":[
        {
            "category":"Health Services",
            "subcategory":"Nursing And Care Facility",
            "type":"Services"
        }
    ],
    "sg:phone":"+1 514 762 5429",
    "sg:postcode":"H4G 2L9",
    "sg:province":"QC",
    "sg:tags":[
        "home",
        "rest",
        "site",
        "reception",
        "wedding"
    ],
    "wof:name":"Maison Simon",
    "wof:placetype":"venue"
},
  "geometry": {"coordinates":[-73.5642776489,45.4628410339],"type":"Point"}
}