{
  "type": "Feature",
  "properties": {
    "addr:full":"6291 Yonge St North York ON M2M 3X6",
    "addr:housenumber":"6291",
    "addr:postcode":"m2m 3x6",
    "addr:street":"Yonge St",
    "iso:country":"CA",
    "sg:address":"6291 Yonge St",
    "sg:city":"North York",
    "sg:classifiers":[
        {
            "category":"Building & Trades",
            "subcategory":"Construction",
            "type":"Services"
        }
    ],
    "sg:phone":"+1 416 516 0113",
    "sg:postcode":"M2M 3X6",
    "sg:province":"ON",
    "sg:tags":[
        "masonry",
        "contractor"
    ],
    "wof:name":"Image Enhanced Inc",
    "wof:placetype":"venue"
},
  "geometry": {"coordinates":[-79.41915899999999,43.795219],"type":"Point"}
}