{
  "type": "Feature",
  "properties": {
    "iso:country":"CA",
    "sg:address":"343 Rue Des Forges",
    "sg:city":"Trois-Rivieres",
    "sg:classifiers":[
        {
            "category":"Shopping",
            "subcategory":"Clothing, Apparel, & Fashions",
            "type":"Retail Goods"
        }
    ],
    "sg:phone":"+1 819 379 8690",
    "sg:postcode":"G9A 2G9",
    "sg:province":"QC",
    "sg:tags":[
        "boutique"
    ],
    "wof:name":"Boutique Cou D'Oeil",
    "wof:placetype":"venue"
},
  "geometry": {"coordinates":[-72.5428848267,46.3420257568],"type":"Point"}
}