{
  "type": "Feature",
  "properties": {
    "addr:full":"6604 62B St Delta BC V4K 5A8",
    "addr:housenumber":"6604",
    "addr:postcode":"v4k 5a8",
    "addr:street":"62B St",
    "iso:country":"CA",
    "sg:address":"6604 62B St",
    "sg:city":"Delta",
    "sg:classifiers":[
        {
            "category":"Building & Trades",
            "subcategory":"Landscaping Services",
            "type":"Services"
        }
    ],
    "sg:phone":"+1 604 946 6122",
    "sg:postcode":"V4K 5A8",
    "sg:province":"BC",
    "sg:tags":[
        "topsoil"
    ],
    "wof:name":"Westwood Topsoil Ltd",
    "wof:placetype":"venue"
},
  "geometry": {"coordinates":[-123.059616089,49.0848007202],"type":"Point"}
}