{
  "type": "Feature",
  "properties": {
    "addr:full":"24 Hawthorne Ave Charlottetown PE C1A 5Y1",
    "addr:housenumber":"24",
    "addr:postcode":"c1a 5y1",
    "addr:street":"Hawthorne Ave",
    "iso:country":"CA",
    "sg:address":"24 Hawthorne Ave",
    "sg:city":"Charlottetown",
    "sg:classifiers":[
        {
            "category":"Manufacturing",
            "subcategory":"Printing",
            "type":"Manufacturing & Wholesale Goods"
        }
    ],
    "sg:phone":"+1 902 368 2517",
    "sg:postcode":"C1A 5Y1",
    "sg:province":"PE",
    "sg:tags":[
        "printer",
        "business",
        "form",
        "system"
    ],
    "wof:name":"Best Forms Inc",
    "wof:placetype":"venue"
},
  "geometry": {"coordinates":[-63.121307,46.246902],"type":"Point"}
}