{
  "type": "Feature",
  "properties": {
    "addr:full":"1375 Rue Biron Drummondville QC J2C 6H3",
    "addr:housenumber":"1375",
    "addr:postcode":"j2c 6h3",
    "addr:street":"Rue Biron",
    "iso:country":"CA",
    "sg:address":"1375 Rue Biron",
    "sg:city":"Drummondville",
    "sg:classifiers":[
        {
            "category":"Restaurant",
            "type":"Food & Drink"
        }
    ],
    "sg:phone":"+1 819 478 2295",
    "sg:postcode":"J2C 6H3",
    "sg:province":"QC",
    "sg:tags":[
        "bars"
    ],
    "wof:name":"Taverne Philippe",
    "wof:placetype":"venue"
},
  "geometry": {"coordinates":[-72.5125045776,45.8760528564],"type":"Point"}
}