{
  "type": "Feature",
  "properties": {
    "addr:full":"130 Bridge St # 23 Princeton BC V0X 1W0",
    "addr:housenumber":"130;23",
    "addr:postcode":"v0x 1w0",
    "addr:street":"Bridge St #",
    "iso:country":"CA",
    "sg:address":"130 Bridge St # 23",
    "sg:city":"Princeton",
    "sg:classifiers":[
        {
            "category":"Travel",
            "subcategory":"Hotels & Motels",
            "type":"Entertainment"
        }
    ],
    "sg:phone":"+1 250 295 6941",
    "sg:postcode":"V0X 1W0",
    "sg:province":"BC",
    "wof:name":"Ponderosa Motel",
    "wof:placetype":"venue"
},
  "geometry": {"coordinates":[-120.506683,49.459053],"type":"Point"}
}