{
  "type": "Feature",
  "properties": {
    "iso:country":"CA",
    "sg:city":"Abbotsford",
    "sg:classifiers":[
        {
            "category":"Professional",
            "subcategory":"Lawyer & Legal Services",
            "type":"Services"
        }
    ],
    "sg:phone":"+1 604 850 1675",
    "sg:postcode":"V2T 5T4",
    "sg:province":"BC",
    "sg:tags":[
        "attorney"
    ],
    "wof:name":"Mac Adams Law Firm",
    "wof:placetype":"venue"
},
  "geometry": {"coordinates":[-122.315513611,49.0559272766],"type":"Point"}
}