{
  "type": "Feature",
  "properties": {
    "addr:full":"1034 Weston Rd York ON M6N 3S2",
    "addr:housenumber":"1034",
    "addr:postcode":"m6n 3s2",
    "addr:street":"Weston Rd",
    "iso:country":"CA",
    "sg:address":"1034 Weston Rd",
    "sg:city":"York",
    "sg:classifiers":[
        {
            "category":"Personal",
            "subcategory":"Beauty Salon",
            "type":"Services"
        }
    ],
    "sg:phone":"+1 416 245 2198",
    "sg:postcode":"M6N 3S2",
    "sg:province":"ON",
    "wof:name":"Ontario Nurses Agency",
    "wof:placetype":"venue"
},
  "geometry": {"coordinates":[-79.48597717289999,43.6850662231],"type":"Point"}
}