{
  "type": "Feature",
  "properties": {
    "addr:full":"1670 O'Connor Dr North York ON M4A 1W4",
    "addr:housenumber":"1670",
    "addr:postcode":"m4a 1w4",
    "addr:street":"O'Connor Dr",
    "iso:country":"CA",
    "sg:address":"1670 O'Connor Dr",
    "sg:city":"North York",
    "sg:classifiers":[
        {
            "category":"Manufacturing",
            "subcategory":"Motor Vehicles & Parts",
            "type":"Manufacturing & Wholesale Goods"
        }
    ],
    "sg:phone":"+1 416 757 0123",
    "sg:postcode":"M4A 1W4",
    "sg:province":"ON",
    "sg:tags":[
        "automobile",
        "supply"
    ],
    "wof:name":"Mister Starter Auto Electric",
    "wof:placetype":"venue"
},
  "geometry": {"coordinates":[-79.353553772,43.6924667358],"type":"Point"}
}