{
  "type": "Feature",
  "properties": {
    "addr:full":"1235 S Maquinna Dr Tahsis BC V0P 1X0",
    "addr:housenumber":"1235",
    "addr:postcode":"v0p 1x0",
    "addr:street":"S Maquinna Dr",
    "iso:country":"CA",
    "sg:address":"1235 S Maquinna Dr",
    "sg:city":"Tahsis",
    "sg:classifiers":[
        {
            "category":"Travel",
            "subcategory":"Campground",
            "type":"Entertainment"
        }
    ],
    "sg:phone":"+1 250 934 6689",
    "sg:postcode":"V0P 1X0",
    "sg:province":"BC",
    "wof:name":"Seaside Rv Campground",
    "wof:placetype":"venue"
},
  "geometry": {"coordinates":[-126.663246,49.911293],"type":"Point"}
}