{
  "type": "Feature",
  "properties": {
    "addr:full":"700 East River Rd New Glasgow NS B2H 3S1",
    "addr:housenumber":"700",
    "addr:postcode":"b2h 3s1",
    "addr:street":"East River Rd",
    "iso:country":"CA",
    "sg:address":"700 East River Rd",
    "sg:city":"New Glasgow",
    "sg:classifiers":[
        {
            "category":"Restaurant",
            "type":"Food & Drink"
        }
    ],
    "sg:phone":"+1 902 755 4742",
    "sg:postcode":"B2H 3S1",
    "sg:province":"NS",
    "wof:name":"Mc Donald's",
    "wof:placetype":"venue"
},
  "geometry": {"coordinates":[-62.641922,45.575943],"type":"Point"}
}