{
  "type": "Feature",
  "properties": {
    "addr:full":"Sharbot Lake ON K0H 2P0",
    "addr:postcode":"k0h 2p0",
    "iso:country":"CA",
    "sg:city":"Sharbot Lake",
    "sg:classifiers":[
        {
            "category":"Building & Trades",
            "subcategory":"Plumbing",
            "type":"Services"
        }
    ],
    "sg:phone":"+1 613 375 8176",
    "sg:postcode":"K0H 2P0",
    "sg:province":"ON",
    "sg:tags":[
        "tank",
        "septic"
    ],
    "wof:name":"E Quinn Contracting & Excvtng",
    "wof:placetype":"venue"
},
  "geometry": {"coordinates":[-76.6874008179,44.7715492249],"type":"Point"}
}