{
  "type": "Feature",
  "properties": {
    "addr:full":"196 Sherbrooke St Peterborough ON K9J 2N3",
    "addr:housenumber":"196",
    "addr:postcode":"k9j 2n3",
    "addr:street":"Sherbrooke St",
    "iso:country":"CA",
    "sg:address":"196 Sherbrooke St",
    "sg:city":"Peterborough",
    "sg:classifiers":[
        {
            "category":"Food & Beverages",
            "subcategory":"Liquor & Beverages",
            "type":"Retail Goods"
        }
    ],
    "sg:phone":"+1 705 745 1333",
    "sg:postcode":"K9J 2N3",
    "sg:province":"ON",
    "sg:tags":[
        "store"
    ],
    "wof:name":"Liquor Control Board of Ont",
    "wof:placetype":"venue"
},
  "geometry": {"coordinates":[-78.3211364746,44.3008728027],"type":"Point"}
}