{
  "type": "Feature",
  "properties": {
    "addr:full":"6108 50 Ave Stettler AB T0C 2L2",
    "addr:housenumber":"6108",
    "addr:postcode":"t0c 2l2",
    "addr:street":"50 Ave",
    "iso:country":"CA",
    "sg:address":"6108 50 Ave",
    "sg:city":"Stettler",
    "sg:classifiers":[
        {
            "category":"Restaurant",
            "type":"Food & Drink"
        }
    ],
    "sg:phone":"+1 403 742 1999",
    "sg:postcode":"T0C 2L2",
    "sg:province":"AB",
    "wof:name":"Hong Kong Restaurant",
    "wof:placetype":"venue"
},
  "geometry": {"coordinates":[-112.72922515899999,52.3253288269],"type":"Point"}
}