{
  "type": "Feature",
  "properties": {
    "iso:country":"CA",
    "sg:city":"Harrison Hot Springs",
    "sg:classifiers":[
        {
            "category":"Food & Beverages",
            "subcategory":"Groceries & Convenience Stores",
            "type":"Retail Goods"
        }
    ],
    "sg:phone":"+1 604 796 2180",
    "sg:postcode":"V0M 1K0",
    "sg:province":"BC",
    "sg:tags":[
        "grocer"
    ],
    "wof:name":"Harrison Lake Market",
    "wof:placetype":"venue"
},
  "geometry": {"coordinates":[-121.786125183,49.3033218384],"type":"Point"}
}