{
  "type": "Feature",
  "properties": {
    "addr:full":"3723 Hershey St Ridgeway ON L0S 1N0",
    "addr:housenumber":"3723",
    "addr:postcode":"l0s 1n0",
    "addr:street":"Hershey St",
    "iso:country":"CA",
    "sg:address":"3723 Hershey St",
    "sg:city":"Ridgeway",
    "sg:classifiers":[
        {
            "category":"Building & Trades",
            "subcategory":"Plumbing",
            "type":"Services"
        }
    ],
    "sg:phone":"+1 905 894 0545",
    "sg:postcode":"L0S 1N0",
    "sg:province":"ON",
    "sg:tags":[
        "contractor"
    ],
    "wof:name":"Joe Thebeud Plumbing",
    "wof:placetype":"venue"
},
  "geometry": {"coordinates":[-79.053032,42.88361],"type":"Point"}
}