{
  "type": "Feature",
  "properties": {
    "iso:country":"CA",
    "sg:address":"1276 4th Ave",
    "sg:city":"Prince George",
    "sg:classifiers":[
        {
            "category":"Shopping",
            "subcategory":"Gifts & Souvenirs",
            "type":"Retail Goods"
        }
    ],
    "sg:phone":"+1 250 562 4747",
    "sg:postcode":"V2L 3J4",
    "sg:province":"BC",
    "sg:tags":[
        "shop"
    ],
    "wof:name":"J J Springer & CO",
    "wof:placetype":"venue"
},
  "geometry": {"coordinates":[-122.746238709,53.916267395],"type":"Point"}
}