{
  "type": "Feature",
  "properties": {
    "addr:full":"1420 Rue Belanger Montreal QC H2G 1A4",
    "addr:housenumber":"1420",
    "addr:postcode":"h2g 1a4",
    "addr:street":"Rue Belanger",
    "iso:country":"CA",
    "sg:address":"1420 Rue Belanger",
    "sg:city":"Montreal",
    "sg:classifiers":[
        {
            "category":"Organizations",
            "subcategory":"Religious Organization",
            "type":"Services"
        }
    ],
    "sg:phone":"+1 514 948 4389",
    "sg:postcode":"H2G 1A4",
    "sg:province":"QC",
    "wof:name":"Communaute Catholique Vietnam",
    "wof:placetype":"venue"
},
  "geometry": {"coordinates":[-73.6053771973,45.5440711975],"type":"Point"}
}