{
  "type": "Feature",
  "properties": {
    "iso:country":"CA",
    "sg:address":"371 Rue Racine E",
    "sg:city":"Chicoutimi",
    "sg:classifiers":[
        {
            "category":"Organizations",
            "subcategory":"Professional Association",
            "type":"Services"
        }
    ],
    "sg:phone":"+1 418 543 7088",
    "sg:postcode":"G7H 1S8",
    "sg:province":"QC",
    "wof:name":"Societe DE L'Autisme-LA Region",
    "wof:placetype":"venue"
},
  "geometry": {"coordinates":[-71.056976,48.427856],"type":"Point"}
}