{
  "type": "Feature",
  "properties": {
    "iso:country":"CA",
    "sg:address":"13 Beech Cres",
    "sg:city":"Olds",
    "sg:classifiers":[
        {
            "category":"Building & Trades",
            "subcategory":"Construction",
            "type":"Services"
        }
    ],
    "sg:phone":"+1 403 556 6666",
    "sg:postcode":"T4H 1M1",
    "sg:province":"AB",
    "sg:tags":[
        "excavating",
        "contractor"
    ],
    "wof:name":"Van Tighem's Backhoe Svc",
    "wof:placetype":"venue"
},
  "geometry": {"coordinates":[-114.129302978,51.7917938232],"type":"Point"}
}