{
  "type": "Feature",
  "properties": {
    "addr:full":"4053 York Corners Rd Metcalfe ON K0A 2P0",
    "addr:housenumber":"4053",
    "addr:postcode":"k0a 2p0",
    "addr:street":"York Corners Rd",
    "iso:country":"CA",
    "sg:address":"4053 York Corners Rd",
    "sg:city":"Metcalfe",
    "sg:classifiers":[
        {
            "category":"Farming",
            "subcategory":"Farm",
            "type":"Manufacturing & Wholesale Goods"
        }
    ],
    "sg:phone":"+1 613 821 2997",
    "sg:postcode":"K0A 2P0",
    "sg:province":"ON",
    "wof:name":"Donevelyn Farms Ltd",
    "wof:placetype":"venue"
},
  "geometry": {"coordinates":[-75.472191,45.236084],"type":"Point"}
}