{
  "type": "Feature",
  "properties": {
    "addr:full":"190 Bronson Ave Ottawa ON K1R 6H4",
    "addr:housenumber":"190",
    "addr:postcode":"k1r 6h4",
    "addr:street":"Bronson Ave",
    "iso:country":"CA",
    "sg:address":"190 Bronson Ave",
    "sg:city":"Ottawa",
    "sg:classifiers":[
        {
            "category":"Professional",
            "subcategory":"Accounting & Tax Preparation",
            "type":"Services"
        }
    ],
    "sg:phone":"+1 613 230 9459",
    "sg:postcode":"K1R 6H4",
    "sg:province":"ON",
    "sg:tags":[
        "accountant"
    ],
    "wof:name":"Miller, Norman C CA",
    "wof:placetype":"venue"
},
  "geometry": {"coordinates":[-75.70737457280001,45.4139137268],"type":"Point"}
}