{
  "type": "Feature",
  "properties": {
    "addr:full":"Elk Point AB T0A 1A0",
    "addr:postcode":"t0a 1a0",
    "iso:country":"CA",
    "sg:city":"Elk Point",
    "sg:classifiers":[
        {
            "category":"Education",
            "subcategory":"School",
            "type":"Public Place"
        }
    ],
    "sg:phone":"+1 780 724 3966",
    "sg:postcode":"T0A 1A0",
    "sg:province":"AB",
    "wof:name":"F G Miller High School",
    "wof:placetype":"venue"
},
  "geometry": {"coordinates":[-110.902381897,53.8997459412],"type":"Point"}
}