{
  "type": "Feature",
  "properties": {
    "addr:full":"6118 6th Ave Whitehorse YT Y1A 1M9",
    "addr:housenumber":"6118",
    "addr:postcode":"y1a 1m9",
    "addr:street":"6Th Ave",
    "iso:country":"CA",
    "sg:address":"6118 6th Ave",
    "sg:city":"Whitehorse",
    "sg:classifiers":[
        {
            "category":"Government",
            "subcategory":"Office",
            "type":"Public Place"
        }
    ],
    "sg:phone":"+1 867 667 8473",
    "sg:postcode":"Y1A 1M9",
    "sg:province":"YT",
    "wof:name":"Yukon Detoxification Ctr",
    "wof:placetype":"venue"
},
  "geometry": {"coordinates":[-135.06092799999999,60.718822],"type":"Point"}
}