{
  "type": "Feature",
  "properties": {
    "addr:full":"75 Ch Des Falaises LA Malbaie QC G5A 3C9",
    "addr:housenumber":"75",
    "addr:postcode":"g5a 3c9",
    "addr:street":"Ch Des Falaises",
    "iso:country":"CA",
    "sg:address":"75 Ch Des Falaises",
    "sg:city":"LA Malbaie",
    "sg:classifiers":[
        {
            "category":"Professional",
            "subcategory":"Advertising",
            "type":"Services"
        }
    ],
    "sg:phone":"+1 418 665 6220",
    "sg:postcode":"G5A 3C9",
    "sg:province":"QC",
    "sg:tags":[
        "publicity"
    ],
    "wof:name":"Communication Morency Inc",
    "wof:placetype":"venue"
},
  "geometry": {"coordinates":[-70.159721,47.642529],"type":"Point"}
}