{
  "type": "Feature",
  "properties": {
    "addr:full":"37 Mcphillips St Winnipeg MB R3E 2J5",
    "addr:housenumber":"37",
    "addr:postcode":"r3e 2j5",
    "addr:street":"Mcphillips St",
    "iso:country":"CA",
    "sg:address":"37 Mcphillips St",
    "sg:city":"Winnipeg",
    "sg:classifiers":[
        {
            "category":"Retail",
            "subcategory":"Auto Repair",
            "type":"Services"
        }
    ],
    "sg:phone":"+1 204 783 7141",
    "sg:postcode":"R3E 2J5",
    "sg:province":"MB",
    "sg:tags":[
        "repairing",
        "automobile",
        "radiator"
    ],
    "wof:name":"Garry Radiators Ltd",
    "wof:placetype":"venue"
},
  "geometry": {"coordinates":[-97.1710357666,49.9067573547],"type":"Point"}
}