{
  "type": "Feature",
  "properties": {
    "addr:full":"5235 Av Du Parc # A Montreal QC H2V 4G9",
    "addr:housenumber":"5235",
    "addr:postcode":"h2v 4g9",
    "addr:street":"Av Du Parc # A",
    "iso:country":"CA",
    "sg:address":"5235 Av Du Parc # A",
    "sg:city":"Montreal",
    "sg:classifiers":[
        {
            "category":"Restaurant",
            "type":"Food & Drink"
        }
    ],
    "sg:phone":"+1 514 948 2219",
    "sg:postcode":"H2V 4G9",
    "sg:province":"QC",
    "wof:name":"Frite Alors",
    "wof:placetype":"venue"
},
  "geometry": {"coordinates":[-73.59854900000001,45.520821],"type":"Point"}
}