{
  "type": "Feature",
  "properties": {
    "iso:country":"CA",
    "sg:address":"5235 Av Du Parc # A",
    "sg:city":"Montreal",
    "sg:classifiers":[
        {
            "category":"Restaurant",
            "type":"Food & Drink"
        }
    ],
    "sg:phone":"+1 514 948 2219",
    "sg:postcode":"H2V 4G9",
    "sg:province":"QC",
    "wof:name":"Frite Alors",
    "wof:placetype":"venue"
},
  "geometry": {"coordinates":[-73.598549,45.520821],"type":"Point"}
}