{
  "type": "Feature",
  "properties": {
    "addr:full":"Hebertville-Station QC G0W 1T0",
    "addr:postcode":"g0w 1t0",
    "iso:country":"CA",
    "sg:city":"Hebertville-Station",
    "sg:classifiers":[
        {
            "category":"Government",
            "subcategory":"Office",
            "type":"Public Place"
        }
    ],
    "sg:phone":"+1 418 343 3844",
    "sg:postcode":"G0W 1T0",
    "sg:province":"QC",
    "sg:tags":[
        "village"
    ],
    "wof:name":"Hebertville-Station Garage",
    "wof:placetype":"venue"
},
  "geometry": {"coordinates":[-71.66391,48.448425],"type":"Point"}
}