{
  "type": "Feature",
  "properties": {
    "addr:full":"136 West Main St Welland ON L3C 5A2",
    "addr:housenumber":"136",
    "addr:postcode":"l3c 5a2",
    "addr:street":"West Main St",
    "iso:country":"CA",
    "sg:address":"136 West Main St",
    "sg:city":"Welland",
    "sg:classifiers":[
        {
            "category":"Professional",
            "subcategory":"Computer Services",
            "type":"Services"
        }
    ],
    "sg:phone":"+1 905 788 3577",
    "sg:postcode":"L3C 5A2",
    "sg:province":"ON",
    "sg:tags":[
        "website",
        "design"
    ],
    "wof:name":"International Trading CO",
    "wof:placetype":"venue"
},
  "geometry": {"coordinates":[-79.25547,42.991241],"type":"Point"}
}