{
  "type": "Feature",
  "properties": {
    "addr:full":"1 Birch St Fort St James BC V0J 1P0",
    "addr:housenumber":"1",
    "addr:postcode":"v0j 1p0",
    "addr:street":"Birch St Fort St",
    "iso:country":"CA",
    "sg:address":"1 Birch St",
    "sg:city":"Fort St James",
    "sg:classifiers":[
        {
            "category":"Education",
            "subcategory":"School",
            "type":"Public Place"
        }
    ],
    "sg:phone":"+1 250 996 8237",
    "sg:postcode":"V0J 1P0",
    "sg:province":"BC",
    "wof:name":"David Hoy Elementary School",
    "wof:placetype":"venue"
},
  "geometry": {"coordinates":[-124.254554748,54.4474182129],"type":"Point"}
}