{
  "type": "Feature",
  "properties": {
    "addr:full":"320 Terry Fox Dr Kanata ON K2K 3L1",
    "addr:housenumber":"320",
    "addr:postcode":"k2k 3l1",
    "addr:street":"Terry Fox Dr",
    "iso:country":"CA",
    "sg:address":"320 Terry Fox Dr",
    "sg:city":"Kanata",
    "sg:classifiers":[
        {
            "category":"Recreation",
            "type":"Entertainment"
        }
    ],
    "sg:phone":"+1 613 271 3377",
    "sg:postcode":"K2K 3L1",
    "sg:province":"ON",
    "sg:tags":[
        "course",
        "golf"
    ],
    "wof:name":"Marshes Golf Club",
    "wof:placetype":"venue"
},
  "geometry": {"coordinates":[-75.91155999999999,45.351936],"type":"Point"}
}