{
  "type": "Feature",
  "properties": {
    "addr:full":"Sudbury ON P3E 5P5",
    "addr:postcode":"p3e 5p5",
    "iso:country":"CA",
    "sg:city":"Sudbury",
    "sg:classifiers":[
        {
            "category":"Professional",
            "subcategory":"Research",
            "type":"Services"
        }
    ],
    "sg:phone":"+1 705 523 6680",
    "sg:postcode":"P3E 5P5",
    "sg:province":"ON",
    "sg:tags":[
        "environmental",
        "ecological",
        "engineer"
    ],
    "wof:name":"Dst Consulting Engineers",
    "wof:placetype":"venue"
},
  "geometry": {"coordinates":[-81.030258,46.464901],"type":"Point"}
}