{
  "type": "Feature",
  "properties": {
    "addr:full":"Delmas SK S0M 0P0",
    "addr:postcode":"s0m 0p0",
    "iso:country":"CA",
    "sg:city":"Delmas",
    "sg:classifiers":[
        {
            "category":"Wholesale",
            "subcategory":"Farm Supplies",
            "type":"Manufacturing & Wholesale Goods"
        }
    ],
    "sg:phone":"+1 306 895 4831",
    "sg:postcode":"S0M 0P0",
    "sg:province":"SK",
    "sg:tags":[
        "fertilizer"
    ],
    "wof:name":"Multi Crop Svc Ltd",
    "wof:placetype":"venue"
},
  "geometry": {"coordinates":[-108.59848,52.932762],"type":"Point"}
}