{
  "type": "Feature",
  "properties": {
    "addr:full":"Calgary AB T2E 4P9",
    "addr:postcode":"t2e 4p9",
    "iso:country":"CA",
    "sg:city":"Calgary",
    "sg:classifiers":[
        {
            "category":"Building & Trades",
            "subcategory":"Construction",
            "type":"Services"
        }
    ],
    "sg:phone":"+1 403 291 3093",
    "sg:postcode":"T2E 4P9",
    "sg:province":"AB",
    "sg:tags":[
        "downspouts",
        "gutter"
    ],
    "wof:name":"Big 5 Exteriors Ltd",
    "wof:placetype":"venue"
},
  "geometry": {"coordinates":[-114.03222700000001,51.088997],"type":"Point"}
}