{
  "type": "Feature",
  "properties": {
    "addr:full":"Hamilton ON L8V 1B6",
    "addr:postcode":"l8v 1b6",
    "iso:country":"CA",
    "sg:city":"Hamilton",
    "sg:classifiers":[
        {
            "category":"Real Estate",
            "subcategory":"Real Estate Operator",
            "type":"Services"
        }
    ],
    "sg:phone":"+1 905 383 2934",
    "sg:postcode":"L8V 1B6",
    "sg:province":"ON",
    "sg:tags":[
        "apartment"
    ],
    "wof:name":"Colliseum Apartments",
    "wof:placetype":"venue"
},
  "geometry": {"coordinates":[-79.8490524292,43.2401885986],"type":"Point"}
}