{
  "type": "Feature",
  "properties": {
    "iso:country":"CA",
    "sg:city":"Edmonton",
    "sg:classifiers":[
        {
            "category":"Communications",
            "subcategory":"Radio Station",
            "type":"Services"
        }
    ],
    "sg:phone":"+1 780 486 2800",
    "sg:postcode":"T5S 2E2",
    "sg:province":"AB",
    "sg:tags":[
        "company",
        "broadcasting"
    ],
    "wof:name":"Cfrn",
    "wof:placetype":"venue"
},
  "geometry": {"coordinates":[-113.642715454,53.5414505005],"type":"Point"}
}