{
  "type": "Feature",
  "properties": {
    "iso:country":"CA",
    "sg:address":"2 Utah Dr",
    "sg:city":"Stephenville",
    "sg:classifiers":[
        {
            "category":"Wholesale",
            "subcategory":"Groceries",
            "type":"Manufacturing & Wholesale Goods"
        }
    ],
    "sg:phone":"+1 709 643 3240",
    "sg:postcode":"A2N 2Z5",
    "sg:province":"NL",
    "sg:tags":[
        "beverage"
    ],
    "wof:name":"Canmor Distributing Ltd",
    "wof:placetype":"venue"
},
  "geometry": {"coordinates":[-58.551071167,48.5537452698],"type":"Point"}
}