{
  "type": "Feature",
  "properties": {
    "addr:full":"605 Middlefield Rd # 6 Scarborough ON M1V 5B9",
    "addr:housenumber":"605",
    "addr:postcode":"m1v 5b9",
    "addr:street":"Middlefield Rd # 6",
    "iso:country":"CA",
    "sg:address":"605 Middlefield Rd # 6",
    "sg:city":"Scarborough",
    "sg:classifiers":[
        {
            "category":"Manufacturing",
            "subcategory":"Tools & Machinery",
            "type":"Manufacturing & Wholesale Goods"
        }
    ],
    "sg:phone":"+1 416 609 0376",
    "sg:postcode":"M1V 5B9",
    "sg:province":"ON",
    "sg:tags":[
        "machine",
        "shop"
    ],
    "wof:name":"Bga Technologies Inc",
    "wof:placetype":"venue"
},
  "geometry": {"coordinates":[-79.258865,43.813057],"type":"Point"}
}