{
  "type": "Feature",
  "properties": {
    "iso:country":"CA",
    "sg:address":"4167 Rue Saint-Denis",
    "sg:city":"Montreal",
    "sg:classifiers":[
        {
            "category":"Professional",
            "subcategory":"Business Services",
            "type":"Services"
        }
    ],
    "sg:phone":"+1 514 985 2982",
    "sg:postcode":"H2W 2M7",
    "sg:province":"QC",
    "sg:tags":[
        "fund",
        "promotion",
        "raising"
    ],
    "wof:name":"Zof CA",
    "wof:placetype":"venue"
},
  "geometry": {"coordinates":[-73.5774,45.521618],"type":"Point"}
}