{
  "type": "Feature",
  "properties": {
    "addr:full":"Sarnia ON N7T 1G4",
    "addr:postcode":"n7t 1g4",
    "iso:country":"CA",
    "sg:city":"Sarnia",
    "sg:classifiers":[
        {
            "category":"Social Services",
            "type":"Services"
        }
    ],
    "sg:phone":"+1 519 337 8110",
    "sg:postcode":"N7T 1G4",
    "sg:province":"ON",
    "sg:tags":[
        "organization",
        "psychologist",
        "welfare"
    ],
    "wof:name":"Lambton Family Initiative",
    "wof:placetype":"venue"
},
  "geometry": {"coordinates":[-82.40744018549999,42.9692993164],"type":"Point"}
}