{
  "type": "Feature",
  "properties": {
    "addr:full":"1560 Lasalle Blvd Sudbury ON P3A 1Z7",
    "addr:housenumber":"1560",
    "addr:postcode":"p3a 1z7",
    "addr:street":"Lasalle Blvd",
    "iso:country":"CA",
    "sg:address":"1560 Lasalle Blvd",
    "sg:city":"Sudbury",
    "sg:classifiers":[
        {
            "category":"Shopping",
            "subcategory":"Used Merchandise",
            "type":"Retail Goods"
        }
    ],
    "sg:phone":"+1 705 560 2274",
    "sg:postcode":"P3A 1Z7",
    "sg:province":"ON",
    "sg:tags":[
        "second",
        "store",
        "hand"
    ],
    "wof:name":"Hock Shop Canada",
    "wof:placetype":"venue"
},
  "geometry": {"coordinates":[-80.94006299999999,46.522179],"type":"Point"}
}