{
  "type": "Feature",
  "properties": {
    "addr:full":"1201 9th St E Saskatoon SK S7H 0N7",
    "addr:housenumber":"1201",
    "addr:postcode":"s7h 0n7",
    "addr:street":"9Th St E",
    "iso:country":"CA",
    "sg:address":"1201 9th St E",
    "sg:city":"Saskatoon",
    "sg:classifiers":[
        {
            "category":"Organizations",
            "subcategory":"Religious Organization",
            "type":"Services"
        }
    ],
    "sg:phone":"+1 306 343 7115",
    "sg:postcode":"S7H 0N7",
    "sg:province":"SK",
    "sg:tags":[
        "church"
    ],
    "wof:name":"Courts of Praise Foursquare",
    "wof:placetype":"venue"
},
  "geometry": {"coordinates":[-106.641189575,52.1159172058],"type":"Point"}
}