{
  "type": "Feature",
  "properties": {
    "iso:country":"CA",
    "sg:city":"Scarborough",
    "sg:classifiers":[
        {
            "category":"Health Services",
            "subcategory":"Doctor",
            "type":"Services"
        }
    ],
    "sg:phone":"+1 416 282 7421",
    "sg:postcode":"M1C 1E9",
    "sg:province":"ON",
    "sg:tags":[
        "dentist"
    ],
    "wof:name":"Katzman, Sydney DDS",
    "wof:placetype":"venue"
},
  "geometry": {"coordinates":[-79.1705703735,43.7836227417],"type":"Point"}
}