{
  "type": "Feature",
  "properties": {
    "iso:country":"CA",
    "sg:address":"130 Simcoe St",
    "sg:city":"Peterborough",
    "sg:classifiers":[
        {
            "category":"Banks & Credit Unions",
            "subcategory":"Bank",
            "type":"Services"
        }
    ],
    "sg:phone":"+1 705 745 3201",
    "sg:postcode":"K9H 2H5",
    "sg:province":"ON",
    "wof:name":"Bmo Bank of Montreal",
    "wof:placetype":"venue"
},
  "geometry": {"coordinates":[-78.3190002441,44.3048286438],"type":"Point"}
}