{
  "type": "Feature",
  "properties": {
    "addr:full":"221 Main St N Mount Forest ON N0G 2L1",
    "addr:housenumber":"221",
    "addr:postcode":"n0g 2l1",
    "addr:street":"Main St N",
    "iso:country":"CA",
    "sg:address":"221 Main St N",
    "sg:city":"Mount Forest",
    "sg:classifiers":[
        {
            "category":"Building & Trades",
            "subcategory":"Cleaning & Sanitation",
            "type":"Services"
        }
    ],
    "sg:phone":"+1 519 323 2142",
    "sg:postcode":"N0G 2L1",
    "sg:province":"ON",
    "sg:tags":[
        "janitor"
    ],
    "wof:name":"Superclean Janitorial Svc",
    "wof:placetype":"venue"
},
  "geometry": {"coordinates":[-80.73786200000001,43.983189],"type":"Point"}
}