{
  "type": "Feature",
  "properties": {
    "addr:full":"Rocky Mountain House AB T4T 1A1",
    "addr:postcode":"t4t 1a1",
    "iso:country":"CA",
    "sg:city":"Rocky Mountain House",
    "sg:classifiers":[
        {
            "category":"Mining & Drilling",
            "type":"Manufacturing & Wholesale Goods"
        }
    ],
    "sg:phone":"+1 403 844 3000",
    "sg:postcode":"T4T 1A1",
    "sg:province":"AB",
    "sg:tags":[
        "field",
        "oil"
    ],
    "wof:name":"Competition Wireline Svc Ltd",
    "wof:placetype":"venue"
},
  "geometry": {"coordinates":[-114.903976,52.369701],"type":"Point"}
}