{
  "type": "Feature",
  "properties": {
    "addr:full":"20702 Eastleigh Cres Langley BC V3A 4C4",
    "addr:postcode":"20702;v3a 4c4",
    "iso:country":"CA",
    "sg:address":"20702 Eastleigh Cres",
    "sg:city":"Langley",
    "sg:classifiers":[
        {
            "category":"Organizations",
            "subcategory":"Community Association",
            "type":"Services"
        }
    ],
    "sg:phone":"+1 604 534 3615",
    "sg:postcode":"V3A 4C4",
    "sg:province":"BC",
    "sg:tags":[
        "fraternal"
    ],
    "wof:name":"Royal Canadian Legion",
    "wof:placetype":"venue"
},
  "geometry": {"coordinates":[-122.649787903,49.1059112549],"type":"Point"}
}