{
  "type": "Feature",
  "properties": {
    "addr:full":"Calgary AB T3H 3C8",
    "addr:postcode":"t3h 3c8",
    "iso:country":"CA",
    "sg:city":"Calgary",
    "sg:classifiers":[
        {
            "category":"Professional",
            "subcategory":"Research",
            "type":"Services"
        }
    ],
    "sg:phone":"+1 403 233 0035",
    "sg:postcode":"T3H 3C8",
    "sg:province":"AB",
    "sg:tags":[
        "environmental",
        "ecological"
    ],
    "wof:name":"Enviroconsult Inc",
    "wof:placetype":"venue"
},
  "geometry": {"coordinates":[-114.169113,51.015247],"type":"Point"}
}