{
  "type": "Feature",
  "properties": {
    "addr:full":"2421 St Clair Ave W Toronto ON M6N 1K9",
    "addr:housenumber":"2421",
    "addr:postcode":"m6n 1k9",
    "addr:street":"St Clair Ave W",
    "iso:country":"CA",
    "sg:address":"2421 St Clair Ave W",
    "sg:city":"Toronto",
    "sg:classifiers":[
        {
            "category":"Food & Beverages",
            "subcategory":"Fruits & Vegetables",
            "type":"Retail Goods"
        }
    ],
    "sg:phone":"+1 416 769 7316",
    "sg:postcode":"M6N 1K9",
    "sg:province":"ON",
    "sg:tags":[
        "produce"
    ],
    "wof:name":"Santokhi Dhandari",
    "wof:placetype":"venue"
},
  "geometry": {"coordinates":[-79.48247499999999,43.669075],"type":"Point"}
}