{
  "type": "Feature",
  "properties": {
    "addr:full":"3136 Hwy 2 Economy NS B0M 1J0",
    "addr:housenumber":"3136",
    "addr:postcode":"b0m 1j0",
    "addr:street":"Hwy 2",
    "iso:country":"CA",
    "sg:address":"3136 Hwy 2",
    "sg:city":"Economy",
    "sg:classifiers":[
        {
            "category":"Organizations",
            "subcategory":"Religious Organization",
            "type":"Services"
        }
    ],
    "sg:phone":"+1 902 647 2502",
    "sg:postcode":"B0M 1J0",
    "sg:province":"NS",
    "sg:tags":[
        "church"
    ],
    "wof:name":"United Church Manse",
    "wof:placetype":"venue"
},
  "geometry": {"coordinates":[-63.9113960266,45.3849143982],"type":"Point"}
}