{
  "type": "Feature",
  "properties": {
    "addr:full":"Westmount QC H3Z 2A7",
    "addr:postcode":"h3z 2a7",
    "iso:country":"CA",
    "sg:city":"Westmount",
    "sg:classifiers":[
        {
            "category":"Professional",
            "subcategory":"Research",
            "type":"Services"
        }
    ],
    "sg:phone":"+1 514 939 2296",
    "sg:postcode":"H3Z 2A7",
    "sg:province":"QC",
    "sg:tags":[
        "economic",
        "analysis"
    ],
    "wof:name":"Etude Economique Conseil",
    "wof:placetype":"venue"
},
  "geometry": {"coordinates":[-73.589714,45.487137],"type":"Point"}
}