{
  "type": "Feature",
  "properties": {
    "iso:country":"CA",
    "sg:address":"7415 Hunterhaven Pl NW",
    "sg:city":"Calgary",
    "sg:classifiers":[
        {
            "category":"Wholesale",
            "subcategory":"Non-durable Goods",
            "type":"Manufacturing & Wholesale Goods"
        }
    ],
    "sg:phone":"+1 403 275 8621",
    "sg:postcode":"T2K 4K7",
    "sg:province":"AB",
    "sg:tags":[
        "advertising"
    ],
    "wof:name":"Kmc Sales",
    "wof:placetype":"venue"
},
  "geometry": {"coordinates":[-114.077179,51.118343],"type":"Point"}
}