{
  "type": "Feature",
  "properties": {
    "addr:full":"113 Principale St St Albert ON K0A 3C0",
    "addr:housenumber":"113",
    "addr:postcode":"k0a 3c0",
    "addr:street":"Principale St",
    "iso:country":"CA",
    "sg:address":"113 Principale St",
    "sg:city":"St Albert",
    "sg:classifiers":[
        {
            "category":"Wholesale",
            "subcategory":"Meat",
            "type":"Manufacturing & Wholesale Goods"
        }
    ],
    "sg:phone":"+1 613 987 2070",
    "sg:postcode":"K0A 3C0",
    "sg:province":"ON",
    "sg:tags":[
        "packer"
    ],
    "wof:name":"Savage Jose Abattoir",
    "wof:placetype":"venue"
},
  "geometry": {"coordinates":[-75.124306,45.254524],"type":"Point"}
}