{
  "type": "Feature",
  "properties": {
    "addr:full":"2 Billingham Rd #203 Etobicoke ON M9B 6E1",
    "addr:housenumber":"2",
    "addr:postcode":"m9b 6e1",
    "addr:street":"Billingham Rd # 203",
    "iso:country":"CA",
    "sg:address":"2 Billingham Rd #203",
    "sg:city":"Etobicoke",
    "sg:classifiers":[
        {
            "category":"Professional",
            "subcategory":"Computer Services",
            "type":"Services"
        }
    ],
    "sg:phone":"+1 416 232 9717",
    "sg:postcode":"M9B 6E1",
    "sg:province":"ON",
    "sg:tags":[
        "consultant"
    ],
    "wof:name":"Core Solutions",
    "wof:placetype":"venue"
},
  "geometry": {"coordinates":[-79.54941599999999,43.630684],"type":"Point"}
}