{
  "type": "Feature",
  "properties": {
    "addr:full":"253 Maplewood Ave Winnipeg MB R3L 2L4",
    "addr:housenumber":"253",
    "addr:postcode":"r3l 2l4",
    "addr:street":"Maplewood Ave",
    "iso:country":"CA",
    "sg:address":"253 Maplewood Ave",
    "sg:city":"Winnipeg",
    "sg:classifiers":[
        {
            "category":"Education",
            "subcategory":"School",
            "type":"Public Place"
        }
    ],
    "sg:phone":"+1 204 284 5983",
    "sg:postcode":"R3L 2L4",
    "sg:province":"MB",
    "wof:name":"Riverview School",
    "wof:placetype":"venue"
},
  "geometry": {"coordinates":[-97.127304,49.86562],"type":"Point"}
}