{
  "type": "Feature",
  "properties": {
    "addr:full":"254 Reid St Quesnel BC V2J 2M2",
    "addr:housenumber":"254",
    "addr:postcode":"v2j 2m2",
    "addr:street":"Reid St",
    "iso:country":"CA",
    "sg:address":"254 Reid St",
    "sg:city":"Quesnel",
    "sg:classifiers":[
        {
            "category":"Banks & Credit Unions",
            "subcategory":"Bank",
            "type":"Services"
        }
    ],
    "sg:phone":"+1 250 992 7295",
    "sg:postcode":"V2J 2M2",
    "sg:province":"BC",
    "sg:tags":[
        "loan",
        "real estate"
    ],
    "wof:name":"Northland Mortgages Quesnel",
    "wof:placetype":"venue"
},
  "geometry": {"coordinates":[-122.496330261,52.9766311646],"type":"Point"}
}