{
  "type": "Feature",
  "properties": {
    "iso:country":"CA",
    "sg:address":"11401 99 St",
    "sg:city":"Grande Prairie",
    "sg:classifiers":[
        {
            "category":"Insurance",
            "subcategory":"Insurance Agent",
            "type":"Services"
        }
    ],
    "sg:phone":"+1 780 532 4421",
    "sg:postcode":"T8V 2H6",
    "sg:province":"AB",
    "sg:tags":[
        "travel",
        "agency",
        "bureau"
    ],
    "wof:name":"Alberta Motor Assn",
    "wof:placetype":"venue"
},
  "geometry": {"coordinates":[-118.791511536,55.1833534241],"type":"Point"}
}