{
  "type": "Feature",
  "properties": {
    "addr:full":"261 Portage Rd Grand Falls NB E3Z 3E8",
    "addr:housenumber":"261",
    "addr:postcode":"e3z 3e8",
    "addr:street":"Portage Rd",
    "iso:country":"CA",
    "sg:address":"261 Portage Rd",
    "sg:city":"Grand Falls",
    "sg:classifiers":[
        {
            "category":"Autos & Motor Vehicles",
            "subcategory":"Automobile Sales",
            "type":"Retail Goods"
        }
    ],
    "sg:phone":"+1 506 473 2727",
    "sg:postcode":"E3Z 3E8",
    "sg:province":"NB",
    "sg:tags":[
        "car",
        "dealer"
    ],
    "wof:name":"Toner Pontiac Buick Gmc Ltd",
    "wof:placetype":"venue"
},
  "geometry": {"coordinates":[-67.74530799999999,47.037697],"type":"Point"}
}