{
  "type": "Feature",
  "properties": {
    "addr:full":"5790 Av Royalmount Mont-Royal QC H4P 1K5",
    "addr:housenumber":"5790",
    "addr:postcode":"h4p 1k5",
    "addr:street":"Av Royalmount",
    "iso:country":"CA",
    "sg:address":"5790 Av Royalmount",
    "sg:city":"Mont-Royal",
    "sg:classifiers":[
        {
            "category":"Manufacturing",
            "subcategory":"Paper Products",
            "type":"Manufacturing & Wholesale Goods"
        }
    ],
    "sg:phone":"+1 514 735 5777",
    "sg:postcode":"H4P 1K5",
    "sg:province":"QC",
    "sg:tags":[
        "packaging",
        "material"
    ],
    "wof:name":"Bsr Industries Inc",
    "wof:placetype":"venue"
},
  "geometry": {"coordinates":[-73.6708526611,45.4906463623],"type":"Point"}
}