{
  "type": "Feature",
  "properties": {
    "addr:full":"Sechelt BC V0N 3A0",
    "addr:postcode":"v0n 3a0",
    "iso:country":"CA",
    "sg:city":"Sechelt",
    "sg:classifiers":[
        {
            "category":"Professional",
            "subcategory":"Accounting & Tax Preparation",
            "type":"Services"
        }
    ],
    "sg:phone":"+1 604 885 2254",
    "sg:postcode":"V0N 3A0",
    "sg:province":"BC",
    "sg:tags":[
        "accountant"
    ],
    "wof:name":"Beecham Wilson",
    "wof:placetype":"venue"
},
  "geometry": {"coordinates":[-123.758545,49.471264],"type":"Point"}
}