{
  "type": "Feature",
  "properties": {
    "addr:full":"200 64E Rue O Charlesbourg QC G1H 4Y6",
    "addr:housenumber":"200",
    "addr:postcode":"g1h 4y6",
    "addr:street":"64E Rue O",
    "iso:country":"CA",
    "sg:address":"200 64E Rue O",
    "sg:city":"Charlesbourg",
    "sg:classifiers":[
        {
            "category":"Building & Trades",
            "subcategory":"Construction",
            "type":"Services"
        }
    ],
    "sg:phone":"+1 418 623 2505",
    "sg:postcode":"G1H 4Y6",
    "sg:province":"QC",
    "sg:tags":[
        "masonry",
        "contractor"
    ],
    "wof:name":"Bellemare & Bellemare Inc",
    "wof:placetype":"venue"
},
  "geometry": {"coordinates":[-71.251289,46.845665],"type":"Point"}
}