{
  "type": "Feature",
  "properties": {
    "addr:full":"1250 Main St Winnipeg MB R2W 3S9",
    "addr:housenumber":"1250",
    "addr:postcode":"r2w 3s9",
    "addr:street":"Main St",
    "iso:country":"CA",
    "sg:address":"1250 Main St",
    "sg:city":"Winnipeg",
    "sg:classifiers":[
        {
            "category":"Autos & Motor Vehicles",
            "subcategory":"Automobile Sales",
            "type":"Retail Goods"
        }
    ],
    "sg:phone":"+1 204 586 8334",
    "sg:postcode":"R2W 3S9",
    "sg:province":"MB",
    "sg:tags":[
        "car",
        "dealer"
    ],
    "wof:name":"Northstar Motors",
    "wof:placetype":"venue"
},
  "geometry": {"coordinates":[-97.128578,49.920811],"type":"Point"}
}