{
  "type": "Feature",
  "properties": {
    "addr:full":"402 Saskatchewan Ave E Portage LA Prairie MB R1N 0K7",
    "addr:housenumber":"402",
    "addr:postcode":"r1n 0k7",
    "addr:street":"Saskatchewan Ave E",
    "iso:country":"CA",
    "sg:address":"402 Saskatchewan Ave E",
    "sg:city":"Portage LA Prairie",
    "sg:classifiers":[
        {
            "category":"Food & Beverages",
            "subcategory":"Groceries & Convenience Stores",
            "type":"Retail Goods"
        }
    ],
    "sg:phone":"+1 204 239 1666",
    "sg:postcode":"R1N 0K7",
    "sg:province":"MB",
    "sg:tags":[
        "grocer"
    ],
    "wof:name":"Portage Supermarket Ltd",
    "wof:placetype":"venue"
},
  "geometry": {"coordinates":[-98.28398900000001,49.972847],"type":"Point"}
}