{
  "type": "Feature",
  "properties": {
    "addr:full":"180 Rue Montcalm Hull QC J8Y 3B5",
    "addr:housenumber":"180",
    "addr:postcode":"j8y 3b5",
    "addr:street":"Rue Montcalm",
    "iso:country":"CA",
    "sg:address":"180 Rue Montcalm",
    "sg:city":"Hull",
    "sg:classifiers":[
        {
            "category":"Manufacturing",
            "subcategory":"Retail Goods",
            "type":"Manufacturing & Wholesale Goods"
        }
    ],
    "sg:phone":"+1 819 771 6211",
    "sg:postcode":"J8Y 3B5",
    "sg:province":"QC",
    "sg:tags":[
        "pin"
    ],
    "wof:name":"Nemo Mfr Inc",
    "wof:placetype":"venue"
},
  "geometry": {"coordinates":[-75.72757,45.429901],"type":"Point"}
}