{
  "type": "Feature",
  "properties": {
    "addr:full":"135 Lexington Rd Waterloo ON N2J 4G8",
    "addr:housenumber":"135",
    "addr:postcode":"n2j 4g8",
    "addr:street":"Lexington Rd",
    "iso:country":"CA",
    "sg:address":"135 Lexington Rd",
    "sg:city":"Waterloo",
    "sg:classifiers":[
        {
            "category":"Retail",
            "subcategory":"Veterinary Services",
            "type":"Services"
        }
    ],
    "sg:phone":"+1 519 746 4440",
    "sg:postcode":"N2J 4G8",
    "sg:province":"ON",
    "sg:tags":[
        "veterinarian"
    ],
    "wof:name":"Hardy, Marie DVM",
    "wof:placetype":"venue"
},
  "geometry": {"coordinates":[-80.51815000000001,43.488514],"type":"Point"}
}