{
  "type": "Feature",
  "properties": {
    "iso:country":"CA",
    "sg:city":"London",
    "sg:classifiers":[
        {
            "category":"Professional",
            "subcategory":"Management & Consulting",
            "type":"Services"
        }
    ],
    "sg:phone":"+1 519 432 3030",
    "sg:postcode":"N6B 2V2",
    "sg:province":"ON",
    "sg:tags":[
        "consultant",
        "business"
    ],
    "wof:name":"Passmore Management Inc",
    "wof:placetype":"venue"
},
  "geometry": {"coordinates":[-81.24276733400001,42.9928627014],"type":"Point"}
}