{
  "type": "Feature",
  "properties": {
    "iso:country":"CA",
    "sg:address":"1 Columbo Dr",
    "sg:city":"Dartmouth",
    "sg:classifiers":[
        {
            "category":"Wholesale",
            "subcategory":"Durable Goods & Equipment",
            "type":"Manufacturing & Wholesale Goods"
        }
    ],
    "sg:phone":"+1 902 434 7740",
    "sg:postcode":"B2X 3M1",
    "sg:province":"NS",
    "sg:tags":[
        "representative",
        "manufacturer"
    ],
    "wof:name":"Prestige Sales Ltd",
    "wof:placetype":"venue"
},
  "geometry": {"coordinates":[-63.54274,44.703072],"type":"Point"}
}