{
  "type": "Feature",
  "properties": {
    "iso:country":"CA",
    "sg:address":"50 Featherstone Ave",
    "sg:city":"Markham",
    "sg:classifiers":[
        {
            "category":"Social Services",
            "subcategory":"Child Care",
            "type":"Services"
        }
    ],
    "sg:phone":"+1 905 472 3712",
    "sg:postcode":"L3S 2H4",
    "sg:province":"ON",
    "wof:name":"Rainbow Connection",
    "wof:placetype":"venue"
},
  "geometry": {"coordinates":[-79.26898956300001,43.8400230408],"type":"Point"}
}