{
  "type": "Feature",
  "properties": {
    "addr:full":"725 Rue Des Volontaires Trois-Rivieres QC G9A 2G2",
    "addr:housenumber":"725",
    "addr:postcode":"g9a 2g2",
    "addr:street":"Rue Des Volontaires Trois-Rivieres",
    "iso:country":"CA",
    "sg:address":"725 Rue Des Volontaires",
    "sg:city":"Trois-Rivieres",
    "sg:classifiers":[
        {
            "category":"Insurance",
            "subcategory":"Insurance Agent",
            "type":"Services"
        }
    ],
    "sg:phone":"+1 819 379 8212",
    "sg:postcode":"G9A 2G2",
    "sg:province":"QC",
    "sg:tags":[
        "adjuster"
    ],
    "wof:name":"Agents DE Reclaimations DE",
    "wof:placetype":"venue"
},
  "geometry": {"coordinates":[-72.5479354858,46.3434257507],"type":"Point"}
}