{
  "type": "Feature",
  "properties": {
    "iso:country":"CA",
    "sg:address":"431 Konihowski Rd",
    "sg:city":"Saskatoon",
    "sg:classifiers":[
        {
            "category":"Shopping",
            "subcategory":"Computers & Home Electronics",
            "type":"Retail Goods"
        }
    ],
    "sg:phone":"+1 306 249 1919",
    "sg:postcode":"S7S 1C6",
    "sg:province":"SK",
    "sg:tags":[
        "equipment",
        "dealer",
        "consultant"
    ],
    "wof:name":"3 P Computer Svc Inc",
    "wof:placetype":"venue"
},
  "geometry": {"coordinates":[-106.590873718,52.1562271118],"type":"Point"}
}