{
  "type": "Feature",
  "properties": {
    "addr:full":"Sarnia ON N7S 3Y6",
    "addr:postcode":"n7s 3y6",
    "iso:country":"CA",
    "sg:city":"Sarnia",
    "sg:classifiers":[
        {
            "category":"Professional",
            "subcategory":"Engineering",
            "type":"Services"
        }
    ],
    "sg:phone":"+1 519 337 6580",
    "sg:postcode":"N7S 3Y6",
    "sg:province":"ON",
    "sg:tags":[
        "engineer"
    ],
    "wof:name":"Elecsar Engineering Ltd",
    "wof:placetype":"venue"
},
  "geometry": {"coordinates":[-82.37390899659999,42.9589920044],"type":"Point"}
}