{
  "type": "Feature",
  "properties": {
    "addr:full":"3262 Tottenham Rd Beeton ON L0G 1A0",
    "addr:housenumber":"3262",
    "addr:postcode":"l0g 1a0",
    "addr:street":"Tottenham Rd",
    "iso:country":"CA",
    "sg:address":"3262 Tottenham Rd",
    "sg:city":"Beeton",
    "sg:classifiers":[
        {
            "category":"Retail",
            "subcategory":"Auto Rental",
            "type":"Services"
        }
    ],
    "sg:phone":"+1 905 729 0032",
    "sg:postcode":"L0G 1A0",
    "sg:province":"ON",
    "sg:tags":[
        "renting",
        "truck",
        "leasing"
    ],
    "wof:name":"Ryder Canada",
    "wof:placetype":"venue"
},
  "geometry": {"coordinates":[-79.822075,44.085564],"type":"Point"}
}