{
  "type": "Feature",
  "properties": {
    "addr:full":"144 Newcastle Blvd Miramichi NB E1V 2L7",
    "addr:housenumber":"144",
    "addr:postcode":"e1v 2l7",
    "addr:street":"Newcastle Blvd",
    "iso:country":"CA",
    "sg:address":"144 Newcastle Blvd",
    "sg:city":"Miramichi",
    "sg:classifiers":[
        {
            "category":"Shopping",
            "subcategory":"Books",
            "type":"Retail Goods"
        }
    ],
    "sg:phone":"+1 506 622 1185",
    "sg:postcode":"E1V 2L7",
    "sg:province":"NB",
    "sg:tags":[
        "dealer"
    ],
    "wof:name":"Books Inn Book Store",
    "wof:placetype":"venue"
},
  "geometry": {"coordinates":[-65.564774,47.001572],"type":"Point"}
}