{
  "type": "Feature",
  "properties": {
    "iso:country":"CA",
    "sg:city":"Barrie",
    "sg:classifiers":[
        {
            "category":"Professional",
            "subcategory":"Lawyer & Legal Services",
            "type":"Services"
        }
    ],
    "sg:phone":"+1 705 726 9021",
    "sg:postcode":"L4M 6C1",
    "sg:province":"ON",
    "sg:tags":[
        "attorney"
    ],
    "wof:name":"Cameron, Brian",
    "wof:placetype":"venue"
},
  "geometry": {"coordinates":[-79.690453,44.408161],"type":"Point"}
}