{
  "type": "Feature",
  "properties": {
    "addr:full":"6030 50 St NW Edmonton AB T6B 3C4",
    "addr:housenumber":"6030",
    "addr:postcode":"t6b 3c4",
    "addr:street":"50 St Nw",
    "iso:country":"CA",
    "sg:address":"6030 50 St NW",
    "sg:city":"Edmonton",
    "sg:classifiers":[
        {
            "category":"Building & Trades",
            "subcategory":"Construction",
            "type":"Services"
        }
    ],
    "sg:phone":"+1 780 465 4239",
    "sg:postcode":"T6B 3C4",
    "sg:province":"AB",
    "sg:tags":[
        "dry wall",
        "contractor"
    ],
    "wof:name":"Alberta Drywall & Stucco Supl",
    "wof:placetype":"venue"
},
  "geometry": {"coordinates":[-113.418488,53.498089],"type":"Point"}
}