{
  "type": "Feature",
  "properties": {
    "addr:full":"15 Saturn Cres Hanwell NB E3C 1M9",
    "addr:housenumber":"15",
    "addr:postcode":"e3c 1m9",
    "addr:street":"Saturn Cres",
    "iso:country":"CA",
    "sg:address":"15 Saturn Cres",
    "sg:city":"Hanwell",
    "sg:classifiers":[
        {
            "category":"Building & Trades",
            "subcategory":"Construction",
            "type":"Services"
        }
    ],
    "sg:phone":"+1 506 459 8600",
    "sg:postcode":"E3C 1M9",
    "sg:province":"NB",
    "sg:tags":[
        "contractor",
        "general"
    ],
    "wof:name":"Star-Lite Homes Ltd",
    "wof:placetype":"venue"
},
  "geometry": {"coordinates":[-66.795441,45.868484],"type":"Point"}
}