{
  "type": "Feature",
  "properties": {
    "addr:full":"800 Rue King E Sherbrooke QC J1G 1C7",
    "addr:housenumber":"800",
    "addr:postcode":"j1g 1c7",
    "addr:street":"Rue King E",
    "iso:country":"CA",
    "sg:address":"800 Rue King E",
    "sg:city":"Sherbrooke",
    "sg:classifiers":[
        {
            "category":"Cinema",
            "subcategory":"Movie Rental",
            "type":"Entertainment"
        }
    ],
    "sg:phone":"+1 819 562 0878",
    "sg:postcode":"J1G 1C7",
    "sg:province":"QC",
    "sg:tags":[
        "leasing",
        "video",
        "disc",
        "tape"
    ],
    "wof:name":"Blockbuster Video",
    "wof:placetype":"venue"
},
  "geometry": {"coordinates":[-71.8714828491,45.4079971313],"type":"Point"}
}