{
  "type": "Feature",
  "properties": {
    "addr:full":"Ralston AB T0J 2N0",
    "addr:postcode":"t0j 2n0",
    "iso:country":"CA",
    "sg:city":"Ralston",
    "sg:classifiers":[
        {
            "category":"Restaurant",
            "type":"Food & Drink"
        }
    ],
    "sg:phone":"+1 403 544 3550",
    "sg:postcode":"T0J 2N0",
    "sg:province":"AB",
    "sg:tags":[
        "pizza"
    ],
    "wof:name":"Cactus Pizza & Submarine",
    "wof:placetype":"venue"
},
  "geometry": {"coordinates":[-111.173096,50.254745],"type":"Point"}
}