{
  "type": "Feature",
  "properties": {
    "addr:full":"109 Young St Kitchener ON N2H 4Z2",
    "addr:housenumber":"109",
    "addr:postcode":"n2h 4z2",
    "addr:street":"Young St",
    "iso:country":"CA",
    "sg:address":"109 Young St",
    "sg:city":"Kitchener",
    "sg:classifiers":[
        {
            "category":"Social Services",
            "type":"Services"
        }
    ],
    "sg:phone":"+1 519 571 0722",
    "sg:postcode":"N2H 4Z2",
    "sg:province":"ON",
    "sg:tags":[
        "organization",
        "welfare"
    ],
    "wof:name":"Marillac Place",
    "wof:placetype":"venue"
},
  "geometry": {"coordinates":[-80.4908370972,43.4526672363],"type":"Point"}
}