{
  "type": "Feature",
  "properties": {
    "iso:country":"CA",
    "sg:address":"1786 Main Rd",
    "sg:city":"Church Point",
    "sg:classifiers":[
        {
            "category":"Insurance",
            "subcategory":"Insurance Agent",
            "type":"Services"
        }
    ],
    "sg:phone":"+1 902 769 3000",
    "sg:postcode":"B0W 1M0",
    "sg:province":"NS",
    "wof:name":"Vaughne Assurance Ltd",
    "wof:placetype":"venue"
},
  "geometry": {"coordinates":[-66.11591339109999,44.3361778259],"type":"Point"}
}