{
  "type": "Feature",
  "properties": {
    "addr:full":"RR 1 STN Main Trenton ON K8V 5P4",
    "addr:postcode":"k8v 5p4",
    "addr:street":"Rr 1 Stn Main",
    "iso:country":"CA",
    "sg:address":"RR 1 STN Main",
    "sg:city":"Trenton",
    "sg:classifiers":[
        {
            "category":"Home & Garden",
            "subcategory":"Building Materials",
            "type":"Retail Goods"
        }
    ],
    "sg:phone":"+1 613 392 2038",
    "sg:postcode":"K8V 5P4",
    "sg:province":"ON",
    "sg:tags":[
        "mixed",
        "concrete"
    ],
    "wof:name":"Quinte Mobile Concrete Svc",
    "wof:placetype":"venue"
},
  "geometry": {"coordinates":[-77.57630899999999,44.101139],"type":"Point"}
}