{
  "type": "Feature",
  "properties": {
    "iso:country":"CA",
    "sg:address":"350 St Anne's Rd",
    "sg:city":"Winnipeg",
    "sg:classifiers":[
        {
            "category":"Autos & Motor Vehicles",
            "subcategory":"Fuel & Gas Station",
            "type":"Retail Goods"
        }
    ],
    "sg:phone":"+1 204 256 9114",
    "sg:postcode":"R2M 3B5",
    "sg:province":"MB",
    "sg:tags":[
        "oil"
    ],
    "wof:name":"Shell Canada Products Ltd",
    "wof:placetype":"venue"
},
  "geometry": {"coordinates":[-97.0997619629,49.8495368958],"type":"Point"}
}