{
  "type": "Feature",
  "properties": {
    "addr:full":"PO Box 1284 STN Main Grande Prairie AB T8V 4Z1",
    "addr:housenumber":"po",
    "addr:postcode":"t8v 4z1",
    "addr:street":"Box 1284 Stn Main",
    "iso:country":"CA",
    "sg:address":"PO Box 1284 STN Main",
    "sg:city":"Grande Prairie",
    "sg:classifiers":[
        {
            "category":"Wholesale",
            "subcategory":"Metals & Minerals",
            "type":"Manufacturing & Wholesale Goods"
        }
    ],
    "sg:phone":"+1 780 766 3758",
    "sg:postcode":"T8V 4Z1",
    "sg:province":"AB",
    "sg:tags":[
        "piling"
    ],
    "wof:name":"Peace Land Piling Ltd",
    "wof:placetype":"venue"
},
  "geometry": {"coordinates":[-118.79489100000001,55.171162],"type":"Point"}
}