{
  "type": "Feature",
  "properties": {
    "iso:country":"CA",
    "sg:address":"36 Riedel St",
    "sg:city":"Fort Mcmurray",
    "sg:classifiers":[
        {
            "category":"Real Estate",
            "subcategory":"Real Estate Operator",
            "type":"Services"
        }
    ],
    "sg:phone":"+1 780 791 1500",
    "sg:postcode":"T9H 3E1",
    "sg:province":"AB",
    "sg:tags":[
        "mall",
        "shopping",
        "center"
    ],
    "wof:name":"River Pointe Shops",
    "wof:placetype":"venue"
},
  "geometry": {"coordinates":[-111.36273956300001,56.7238540649],"type":"Point"}
}