{
  "type": "Feature",
  "properties": {
    "addr:full":"209 County Court Blvd Brampton ON L6W 4P5",
    "addr:housenumber":"209",
    "addr:postcode":"l6w 4p5",
    "addr:street":"County Court Blvd",
    "iso:country":"CA",
    "sg:address":"209 County Court Blvd",
    "sg:city":"Brampton",
    "sg:classifiers":[
        {
            "category":"Banks & Credit Unions",
            "subcategory":"Bank",
            "type":"Services"
        }
    ],
    "sg:phone":"+1 905 796 6200",
    "sg:postcode":"L6W 4P5",
    "sg:province":"ON",
    "wof:name":"Royal Bank Financial Group",
    "wof:placetype":"venue"
},
  "geometry": {"coordinates":[-79.722054,43.660088],"type":"Point"}
}