{
  "type": "Feature",
  "properties": {
    "addr:full":"7655 Boul Decarie Montreal QC H4P 2H2",
    "addr:housenumber":"7655",
    "addr:postcode":"h4p 2h2",
    "addr:street":"Boul Decarie",
    "iso:country":"CA",
    "sg:address":"7655 Boul Decarie",
    "sg:city":"Montreal",
    "sg:classifiers":[
        {
            "category":"Shopping",
            "subcategory":"Jewelry",
            "type":"Retail Goods"
        }
    ],
    "sg:phone":"+1 514 737 5621",
    "sg:postcode":"H4P 2H2",
    "sg:province":"QC",
    "sg:tags":[
        "jeweler"
    ],
    "wof:name":"Lynn Lober Jewellery Inc",
    "wof:placetype":"venue"
},
  "geometry": {"coordinates":[-73.655418,45.496277],"type":"Point"}
}