{
  "type": "Feature",
  "properties": {
    "addr:full":"2479 Bellevue Ave West Vancouver BC V7V 1E1",
    "addr:housenumber":"2479",
    "addr:postcode":"v7v 1e1",
    "addr:street":"Bellevue Ave",
    "iso:country":"CA",
    "sg:address":"2479 Bellevue Ave",
    "sg:city":"West Vancouver",
    "sg:classifiers":[
        {
            "category":"Real Estate",
            "subcategory":"Real Estate Agent",
            "type":"Services"
        }
    ],
    "sg:phone":"+1 604 922 9213",
    "sg:postcode":"V7V 1E1",
    "sg:province":"BC",
    "wof:name":"Fred E Russell Ltd",
    "wof:placetype":"venue"
},
  "geometry": {"coordinates":[-123.181510925,49.3339424133],"type":"Point"}
}