{
  "type": "Feature",
  "properties": {
    "addr:full":"374 Hamilton River Rd Happy Valley-Goose Bay NL A0P 1E0",
    "addr:housenumber":"374",
    "addr:postcode":"a0p 1e0",
    "addr:street":"Hamilton River Rd",
    "iso:country":"CA",
    "sg:address":"374 Hamilton River Rd",
    "sg:city":"Happy Valley-Goose Bay",
    "sg:classifiers":[
        {
            "category":"Autos & Motor Vehicles",
            "subcategory":"Fuel & Gas Station",
            "type":"Retail Goods"
        }
    ],
    "sg:phone":"+1 709 896 8959",
    "sg:postcode":"A0P 1E0",
    "sg:province":"NL",
    "sg:tags":[
        "oil"
    ],
    "wof:name":"Goose Bay Ultramar",
    "wof:placetype":"venue"
},
  "geometry": {"coordinates":[-60.376831,53.309422],"type":"Point"}
}