{
  "type": "Feature",
  "properties": {
    "addr:full":"1037 2nd St Estevan SK S4A 0L6",
    "addr:housenumber":"1037",
    "addr:postcode":"s4a 0l6",
    "addr:street":"2Nd St",
    "iso:country":"CA",
    "sg:address":"1037 2nd St",
    "sg:city":"Estevan",
    "sg:classifiers":[
        {
            "category":"Education",
            "subcategory":"Dance Studio",
            "type":"Public Place"
        }
    ],
    "sg:phone":"+1 306 634 6973",
    "sg:postcode":"S4A 0L6",
    "sg:province":"SK",
    "sg:tags":[
        "instruction",
        "dancing"
    ],
    "wof:name":"Drewitz School of Dance",
    "wof:placetype":"venue"
},
  "geometry": {"coordinates":[-102.992943,49.137672],"type":"Point"}
}