{
  "type": "Feature",
  "properties": {
    "addr:full":"8330 Mcintyre Rd NW Edmonton AB T6E 6R6",
    "addr:housenumber":"8330",
    "addr:postcode":"t6e 6r6",
    "addr:street":"Mcintyre Rd Nw",
    "iso:country":"CA",
    "sg:address":"8330 Mcintyre Rd NW",
    "sg:city":"Edmonton",
    "sg:classifiers":[
        {
            "category":"Wholesale",
            "subcategory":"Electrical",
            "type":"Manufacturing & Wholesale Goods"
        }
    ],
    "sg:phone":"+1 780 469 0475",
    "sg:postcode":"T6E 6R6",
    "sg:province":"AB",
    "sg:tags":[
        "equipment",
        "electric",
        "supply"
    ],
    "wof:name":"Westburne Electric Supply",
    "wof:placetype":"venue"
},
  "geometry": {"coordinates":[-113.449363709,53.4934043884],"type":"Point"}
}