{
  "type": "Feature",
  "properties": {
    "addr:full":"185 Northmount Rd North Bay ON P1B 8G2",
    "addr:housenumber":"185",
    "addr:postcode":"p1b 8g2",
    "addr:street":"Northmount Rd",
    "iso:country":"CA",
    "sg:address":"185 Northmount Rd",
    "sg:city":"North Bay",
    "sg:classifiers":[
        {
            "category":"Building & Trades",
            "subcategory":"Landscaping Services",
            "type":"Services"
        }
    ],
    "sg:phone":"+1 705 472 6657",
    "sg:postcode":"P1B 8G2",
    "sg:province":"ON",
    "sg:tags":[
        "landscape",
        "contractor"
    ],
    "wof:name":"Robert Guy Landscaping Ltd",
    "wof:placetype":"venue"
},
  "geometry": {"coordinates":[-79.386124,46.36153],"type":"Point"}
}