{
  "type": "Feature",
  "properties": {
    "addr:full":"Hawkesbury ON K6A 2R2",
    "addr:postcode":"k6a 2r2",
    "iso:country":"CA",
    "sg:city":"Hawkesbury",
    "sg:classifiers":[
        {
            "category":"Recreation",
            "type":"Entertainment"
        }
    ],
    "sg:phone":"+1 613 632 4320",
    "sg:postcode":"K6A 2R2",
    "sg:province":"ON",
    "sg:tags":[
        "course",
        "golf"
    ],
    "wof:name":"Hawkesbury Golf & Curling Club",
    "wof:placetype":"venue"
},
  "geometry": {"coordinates":[-74.61414337159999,45.6078948975],"type":"Point"}
}