{
  "type": "Feature",
  "properties": {
    "addr:full":"262 Dupont St Toronto ON M5R 1V7",
    "addr:housenumber":"262",
    "addr:postcode":"m5r 1v7",
    "addr:street":"Dupont St",
    "iso:country":"CA",
    "sg:address":"262 Dupont St",
    "sg:city":"Toronto",
    "sg:classifiers":[
        {
            "category":"Restaurant",
            "type":"Food & Drink"
        }
    ],
    "sg:phone":"+1 416 928 2021",
    "sg:postcode":"M5R 1V7",
    "sg:province":"ON",
    "wof:name":"Annex Bar & Grill",
    "wof:placetype":"venue"
},
  "geometry": {"coordinates":[-79.40659332280001,43.675113678],"type":"Point"}
}