{
  "type": "Feature",
  "properties": {
    "addr:full":"323 Sumner St Esterhazy SK S0A 0X0",
    "addr:housenumber":"323",
    "addr:postcode":"s0a 0x0",
    "addr:street":"Sumner St",
    "iso:country":"CA",
    "sg:address":"323 Sumner St",
    "sg:city":"Esterhazy",
    "sg:classifiers":[
        {
            "category":"Autos & Motor Vehicles",
            "subcategory":"Auto Supplies",
            "type":"Retail Goods"
        }
    ],
    "sg:phone":"+1 306 745 2212",
    "sg:postcode":"S0A 0X0",
    "sg:province":"SK",
    "sg:tags":[
        "tire"
    ],
    "wof:name":"Esterhazy Tire",
    "wof:placetype":"venue"
},
  "geometry": {"coordinates":[-102.075698852,50.6538963318],"type":"Point"}
}