{
  "type": "Feature",
  "properties": {
    "addr:full":"Coteau-Du-Lac QC J0P 1B0",
    "addr:postcode":"j0p 1b0",
    "iso:country":"CA",
    "sg:city":"Coteau-Du-Lac",
    "sg:classifiers":[
        {
            "category":"Manufacturing",
            "subcategory":"Metals",
            "type":"Manufacturing & Wholesale Goods"
        }
    ],
    "sg:phone":"+1 450 763 1071",
    "sg:postcode":"J0P 1B0",
    "sg:province":"QC",
    "sg:tags":[
        "heat",
        "air",
        "system",
        "conditioning",
        "contractor"
    ],
    "wof:name":"Yvan Allison Refrigeration",
    "wof:placetype":"venue"
},
  "geometry": {"coordinates":[-74.183708,45.280827],"type":"Point"}
}