{
  "type": "Feature",
  "properties": {
    "addr:full":"48 Geneva Cres St Albert AB T8N 0Z4",
    "addr:housenumber":"48",
    "addr:postcode":"t8n 0z4",
    "addr:street":"Geneva Cres",
    "iso:country":"CA",
    "sg:address":"48 Geneva Cres",
    "sg:city":"St Albert",
    "sg:classifiers":[
        {
            "category":"Real Estate",
            "subcategory":"Real Estate Agent",
            "type":"Services"
        }
    ],
    "sg:phone":"+1 780 459 1400",
    "sg:postcode":"T8N 0Z4",
    "sg:province":"AB",
    "wof:name":"Craft Realty Inc",
    "wof:placetype":"venue"
},
  "geometry": {"coordinates":[-113.629814,53.621536],"type":"Point"}
}