{
  "type": "Feature",
  "properties": {
    "addr:full":"9943 Jasper Ave NW Edmonton AB T5J 2X4",
    "addr:housenumber":"9943",
    "addr:postcode":"t5j 2x4",
    "addr:street":"Jasper Ave Nw",
    "iso:country":"CA",
    "sg:address":"9943 Jasper Ave NW",
    "sg:city":"Edmonton",
    "sg:classifiers":[
        {
            "category":"Retail",
            "subcategory":"Auto Rental",
            "type":"Services"
        }
    ],
    "sg:phone":"+1 780 408 8890",
    "sg:postcode":"T5J 2X4",
    "sg:province":"AB",
    "sg:tags":[
        "renting",
        "automobile"
    ],
    "wof:name":"Alamo Rent A Car",
    "wof:placetype":"venue"
},
  "geometry": {"coordinates":[-113.489074707,53.5411567688],"type":"Point"}
}