{
  "type": "Feature",
  "properties": {
    "addr:full":"123 Thames St S Ingersoll ON N5C 2T3",
    "addr:housenumber":"123",
    "addr:postcode":"n5c 2t3",
    "addr:street":"Thames St S",
    "iso:country":"CA",
    "sg:address":"123 Thames St S",
    "sg:city":"Ingersoll",
    "sg:classifiers":[
        {
            "category":"Shopping",
            "subcategory":"Hobbies, Toys, & Games",
            "type":"Retail Goods"
        }
    ],
    "sg:phone":"+1 519 485 2525",
    "sg:postcode":"N5C 2T3",
    "sg:province":"ON",
    "sg:tags":[
        "craft",
        "supply"
    ],
    "wof:name":"Kraft Korner",
    "wof:placetype":"venue"
},
  "geometry": {"coordinates":[-80.88293457029999,43.0387496948],"type":"Point"}
}