{
  "type": "Feature",
  "properties": {
    "iso:country":"CA",
    "sg:address":"62 Hartleywood Dr",
    "sg:city":"Scarborough",
    "sg:classifiers":[
        {
            "category":"Retail",
            "subcategory":"Repair Shop",
            "type":"Services"
        }
    ],
    "sg:phone":"+1 416 918 6016",
    "sg:postcode":"M1S 3N2",
    "sg:province":"ON",
    "sg:tags":[
        "appliance"
    ],
    "wof:name":"I & R Appliance",
    "wof:placetype":"venue"
},
  "geometry": {"coordinates":[-79.27075958250001,43.8053474426],"type":"Point"}
}