{
  "type": "Feature",
  "properties": {
    "addr:full":"1874 Highway 20 E Fenwick ON L0S 1C0",
    "addr:housenumber":"1874",
    "addr:postcode":"l0s 1c0",
    "addr:street":"Highway 20 E",
    "iso:country":"CA",
    "sg:address":"1874 Highway 20 E",
    "sg:city":"Fenwick",
    "sg:classifiers":[
        {
            "category":"Professional",
            "subcategory":"Business Services",
            "type":"Services"
        }
    ],
    "sg:phone":"+1 905 892 0319",
    "sg:postcode":"L0S 1C0",
    "sg:province":"ON",
    "sg:tags":[
        "recording",
        "studio"
    ],
    "wof:name":"Sonic Theatre Recording Studio",
    "wof:placetype":"venue"
},
  "geometry": {"coordinates":[-79.35745199999999,43.026161],"type":"Point"}
}