{
  "type": "Feature",
  "properties": {
    "addr:full":"London ON N5Y 4V6",
    "addr:postcode":"n5y 4v6",
    "iso:country":"CA",
    "sg:city":"London",
    "sg:classifiers":[
        {
            "category":"Real Estate",
            "subcategory":"Real Estate Operator",
            "type":"Services"
        }
    ],
    "sg:phone":"+1 519 453 7410",
    "sg:postcode":"N5Y 4V6",
    "sg:province":"ON",
    "sg:tags":[
        "apartment"
    ],
    "wof:name":"Gemini Towers",
    "wof:placetype":"venue"
},
  "geometry": {"coordinates":[-81.22663116459999,43.0164985657],"type":"Point"}
}