{
  "type": "Feature",
  "properties": {
    "iso:country":"CA",
    "sg:address":"621 Justus Dr",
    "sg:city":"Kingston",
    "sg:classifiers":[
        {
            "category":"Home & Garden",
            "subcategory":"Furniture",
            "type":"Retail Goods"
        }
    ],
    "sg:phone":"+1 613 384 2633",
    "sg:postcode":"K7M 4H5",
    "sg:province":"ON",
    "sg:tags":[
        "equipment",
        "kitchen",
        "cabinet"
    ],
    "wof:name":"Hawthorne Kitchens",
    "wof:placetype":"venue"
},
  "geometry": {"coordinates":[-76.572479,44.244633],"type":"Point"}
}