{
  "type": "Feature",
  "properties": {
    "addr:full":"6021 Nelson Rd Nanaimo BC V9T 5N7",
    "addr:housenumber":"6021",
    "addr:postcode":"v9t 5n7",
    "addr:street":"Nelson Rd",
    "iso:country":"CA",
    "sg:address":"6021 Nelson Rd",
    "sg:city":"Nanaimo",
    "sg:classifiers":[
        {
            "category":"Education",
            "subcategory":"School",
            "type":"Public Place"
        }
    ],
    "sg:phone":"+1 250 758 5076",
    "sg:postcode":"V9T 5N7",
    "sg:province":"BC",
    "wof:name":"Randerson Ridge School",
    "wof:placetype":"venue"
},
  "geometry": {"coordinates":[-124.02697000000001,49.226856],"type":"Point"}
}