{
  "type": "Feature",
  "properties": {
    "iso:country":"CA",
    "sg:address":"225 Crystal Cres",
    "sg:city":"New Liskeard",
    "sg:classifiers":[
        {
            "category":"Building & Trades",
            "subcategory":"Construction",
            "type":"Services"
        }
    ],
    "sg:phone":"+1 705 647 9200",
    "sg:postcode":"P0J 1P0",
    "sg:province":"ON",
    "sg:tags":[
        "carpenter"
    ],
    "wof:name":"Jacques & Son Genl Carpentry",
    "wof:placetype":"venue"
},
  "geometry": {"coordinates":[-79.67366790769999,47.5085792542],"type":"Point"}
}