{
  "type": "Feature",
  "properties": {
    "addr:full":"10328 82 Ave NW Edmonton AB T6E 1Z8",
    "addr:housenumber":"10328",
    "addr:postcode":"t6e 1z8",
    "addr:street":"82 Ave Nw",
    "iso:country":"CA",
    "sg:address":"10328 82 Ave NW",
    "sg:city":"Edmonton",
    "sg:classifiers":[
        {
            "category":"Shopping",
            "subcategory":"Clothing, Apparel, & Fashions",
            "type":"Retail Goods"
        }
    ],
    "sg:phone":"+1 780 434 0467",
    "sg:postcode":"T6E 1Z8",
    "sg:province":"AB",
    "wof:name":"Mars & Venus",
    "wof:placetype":"venue"
},
  "geometry": {"coordinates":[-113.495743,53.518368],"type":"Point"}
}