{
  "type": "Feature",
  "properties": {
    "addr:full":"1288 Military Trail Scarborough ON M1C 1A5",
    "addr:housenumber":"1288",
    "addr:postcode":"m1c 1a5",
    "addr:street":"Military Trail",
    "iso:country":"CA",
    "sg:address":"1288 Military Trail",
    "sg:city":"Scarborough",
    "sg:classifiers":[
        {
            "category":"Manufacturing",
            "subcategory":"Printing",
            "type":"Manufacturing & Wholesale Goods"
        }
    ],
    "sg:phone":"+1 416 287 1788",
    "sg:postcode":"M1C 1A5",
    "sg:province":"ON",
    "sg:tags":[
        "printer"
    ],
    "wof:name":"Ibs Printing",
    "wof:placetype":"venue"
},
  "geometry": {"coordinates":[-79.184792,43.784981],"type":"Point"}
}