{
  "type": "Feature",
  "properties": {
    "addr:full":"Dubuisson QC J9P 4N7",
    "addr:postcode":"j9p 4n7",
    "addr:street":"Dubuisson",
    "iso:country":"CA",
    "sg:city":"Dubuisson",
    "sg:classifiers":[
        {
            "category":"Education",
            "subcategory":"School",
            "type":"Public Place"
        }
    ],
    "sg:phone":"+1 819 738 4038",
    "sg:postcode":"J9P 4N7",
    "sg:province":"QC",
    "wof:name":"Ecole St-Philippe",
    "wof:placetype":"venue"
},
  "geometry": {"coordinates":[-77.946297,48.112976],"type":"Point"}
}