{
  "type": "Feature",
  "properties": {
    "addr:full":"115 Saunders Rd Mcadam NB E6J 1L7",
    "addr:housenumber":"115",
    "addr:postcode":"e6j 1l7",
    "addr:street":"Saunders Rd",
    "iso:country":"CA",
    "sg:address":"115 Saunders Rd",
    "sg:city":"Mcadam",
    "sg:classifiers":[
        {
            "category":"Insurance",
            "subcategory":"Insurance Agent",
            "type":"Services"
        }
    ],
    "sg:phone":"+1 506 784 2222",
    "sg:postcode":"E6J 1L7",
    "sg:province":"NB",
    "wof:name":"Mc Adam Insurance Svc Ltd",
    "wof:placetype":"venue"
},
  "geometry": {"coordinates":[-67.32822400000001,45.592209],"type":"Point"}
}