{
  "type": "Feature",
  "properties": {
    "addr:full":"744 Baker Cres Kingston ON K7M 6P6",
    "addr:housenumber":"744",
    "addr:postcode":"k7m 6p6",
    "addr:street":"Baker Cres",
    "iso:country":"CA",
    "sg:address":"744 Baker Cres",
    "sg:city":"Kingston",
    "sg:classifiers":[
        {
            "category":"Building & Trades",
            "subcategory":"Electrical",
            "type":"Services"
        }
    ],
    "sg:phone":"+1 613 384 1100",
    "sg:postcode":"K7M 6P6",
    "sg:province":"ON",
    "sg:tags":[
        "electric",
        "contractor"
    ],
    "wof:name":"Ontario Electrical Constr CO",
    "wof:placetype":"venue"
},
  "geometry": {"coordinates":[-76.575447,44.244911],"type":"Point"}
}