{
  "type": "Feature",
  "properties": {
    "addr:full":"7700 Boul Henri-Bourassa Charlesbourg QC G1H 3G2",
    "addr:housenumber":"7700",
    "addr:postcode":"g1h 3g2",
    "addr:street":"Boul Henri-Bourassa",
    "iso:country":"CA",
    "sg:address":"7700 Boul Henri-Bourassa",
    "sg:city":"Charlesbourg",
    "sg:classifiers":[
        {
            "category":"Personal",
            "subcategory":"Beauty Salon",
            "type":"Services"
        }
    ],
    "sg:phone":"+1 418 627 4309",
    "sg:postcode":"G1H 3G2",
    "sg:province":"QC",
    "wof:name":"Escompte-Coiffe",
    "wof:placetype":"venue"
},
  "geometry": {"coordinates":[-71.265694,46.860756],"type":"Point"}
}