{
  "type": "Feature",
  "properties": {
    "addr:full":"609 Winnipeg St Regina SK S4R 8P2",
    "addr:housenumber":"609",
    "addr:postcode":"s4r 8p2",
    "addr:street":"Winnipeg St",
    "iso:country":"CA",
    "sg:address":"609 Winnipeg St",
    "sg:city":"Regina",
    "sg:classifiers":[
        {
            "category":"Autos & Motor Vehicles",
            "subcategory":"Automobile Sales",
            "type":"Retail Goods"
        }
    ],
    "sg:phone":"+1 306 525 6700",
    "sg:postcode":"S4R 8P2",
    "sg:province":"SK",
    "sg:tags":[
        "car",
        "dealer"
    ],
    "wof:name":"Auto Gallery/Suzuki/Subaru",
    "wof:placetype":"venue"
},
  "geometry": {"coordinates":[-104.594978,50.4692],"type":"Point"}
}