{
  "type": "Feature",
  "properties": {
    "iso:country":"CA",
    "sg:address":"2306 Rue Des Parulines",
    "sg:city":"Laval",
    "sg:classifiers":[
        {
            "category":"Professional",
            "subcategory":"Lawyer & Legal Services",
            "type":"Services"
        }
    ],
    "sg:phone":"+1 450 963 9936",
    "sg:postcode":"H7L 4Y7",
    "sg:province":"QC",
    "sg:tags":[
        "attorney"
    ],
    "wof:name":"Bougie, Elysabeth",
    "wof:placetype":"venue"
},
  "geometry": {"coordinates":[-73.7705001831,45.5936355591],"type":"Point"}
}