{
  "type": "Feature",
  "properties": {
    "addr:full":"9737 54 Ave NW Edmonton AB T6E 5J4",
    "addr:housenumber":"9737",
    "addr:postcode":"t6e 5j4",
    "addr:street":"54 Ave Nw",
    "iso:country":"CA",
    "sg:address":"9737 54 Ave NW",
    "sg:city":"Edmonton",
    "sg:classifiers":[
        {
            "category":"Manufacturing",
            "subcategory":"Metals",
            "type":"Manufacturing & Wholesale Goods"
        }
    ],
    "sg:phone":"+1 780 430 3622",
    "sg:postcode":"T6E 5J4",
    "sg:province":"AB",
    "sg:tags":[
        "fabricator",
        "sheet"
    ],
    "wof:name":"Fabco Metal Products Ltd",
    "wof:placetype":"venue"
},
  "geometry": {"coordinates":[-113.48146800000001,53.489689],"type":"Point"}
}