{
  "type": "Feature",
  "properties": {
    "addr:full":"609 Centrale St Memramcook NB E4K 3W4",
    "addr:housenumber":"609",
    "addr:postcode":"e4k 3w4",
    "addr:street":"Centrale St",
    "iso:country":"CA",
    "sg:address":"609 Centrale St",
    "sg:city":"Memramcook",
    "sg:classifiers":[
        {
            "category":"Building & Trades",
            "subcategory":"Plumbing",
            "type":"Services"
        }
    ],
    "sg:phone":"+1 506 758 8806",
    "sg:postcode":"E4K 3W4",
    "sg:province":"NB",
    "sg:tags":[
        "ventilating",
        "conditioning",
        "contractor",
        "system",
        "air"
    ],
    "wof:name":"Conair Ventilation",
    "wof:placetype":"venue"
},
  "geometry": {"coordinates":[-64.565574646,45.9737968445],"type":"Point"}
}