{
  "type": "Feature",
  "properties": {
    "addr:full":"11029 Groat Rd NW Edmonton AB T5M 3J9",
    "addr:housenumber":"11029",
    "addr:postcode":"t5m 3j9",
    "addr:street":"Groat Rd Nw",
    "iso:country":"CA",
    "sg:address":"11029 Groat Rd NW",
    "sg:city":"Edmonton",
    "sg:classifiers":[
        {
            "category":"Health Services",
            "subcategory":"Doctor",
            "type":"Services"
        }
    ],
    "sg:phone":"+1 780 452 7090",
    "sg:postcode":"T5M 3J9",
    "sg:province":"AB",
    "sg:tags":[
        "dentist"
    ],
    "wof:name":"Kreutz, Randall W DDS",
    "wof:placetype":"venue"
},
  "geometry": {"coordinates":[-113.55057499999999,53.557308],"type":"Point"}
}