{
  "type": "Feature",
  "properties": {
    "addr:full":"60 Mill St W Elora ON N0B 1S0",
    "addr:housenumber":"60",
    "addr:postcode":"n0b 1s0",
    "addr:street":"Mill St W",
    "iso:country":"CA",
    "sg:address":"60 Mill St W",
    "sg:city":"Elora",
    "sg:classifiers":[
        {
            "category":"Shopping",
            "subcategory":"Gifts & Souvenirs",
            "type":"Retail Goods"
        }
    ],
    "sg:phone":"+1 519 846 0260",
    "sg:postcode":"N0B 1S0",
    "sg:province":"ON",
    "sg:tags":[
        "shop"
    ],
    "wof:name":"Naomi's",
    "wof:placetype":"venue"
},
  "geometry": {"coordinates":[-80.4307556152,43.6808433533],"type":"Point"}
}