{
  "type": "Feature",
  "properties": {
    "addr:full":"16 Boul DE LA Seigneurie E Blainville QC J7C 3V5",
    "addr:housenumber":"16",
    "addr:postcode":"j7c 3v5",
    "addr:street":"Boul De La Seigneurie E",
    "iso:country":"CA",
    "sg:address":"16 Boul DE LA Seigneurie E",
    "sg:city":"Blainville",
    "sg:classifiers":[
        {
            "category":"Wholesale",
            "subcategory":"Construction Materials",
            "type":"Manufacturing & Wholesale Goods"
        }
    ],
    "sg:phone":"+1 450 435 6591",
    "sg:postcode":"J7C 3V5",
    "sg:province":"QC",
    "sg:tags":[
        "lumber"
    ],
    "wof:name":"Simon Lussier Ltee",
    "wof:placetype":"venue"
},
  "geometry": {"coordinates":[-73.8679199219,45.6690330505],"type":"Point"}
}