{
  "type": "Feature",
  "properties": {
    "iso:country":"CA",
    "sg:address":"740 Carmi Ave",
    "sg:city":"Penticton",
    "sg:classifiers":[
        {
            "category":"Government",
            "subcategory":"Office",
            "type":"Public Place"
        }
    ],
    "sg:phone":"+1 250 770 3477",
    "sg:postcode":"V2A 8P9",
    "sg:province":"BC",
    "wof:name":"B C Long Term Care",
    "wof:placetype":"venue"
},
  "geometry": {"coordinates":[-119.575035095,49.4824905396],"type":"Point"}
}