{
  "type": "Feature",
  "properties": {
    "addr:full":"1226 Lockhart Rd Burlington ON L7S 1H1",
    "addr:housenumber":"1226",
    "addr:postcode":"l7s 1h1",
    "addr:street":"Lockhart Rd",
    "iso:country":"CA",
    "sg:address":"1226 Lockhart Rd",
    "sg:city":"Burlington",
    "sg:classifiers":[
        {
            "category":"Education",
            "subcategory":"School",
            "type":"Public Place"
        }
    ],
    "sg:phone":"+1 905 637 3852",
    "sg:postcode":"L7S 1H1",
    "sg:province":"ON",
    "wof:name":"Ecole Rennaissance",
    "wof:placetype":"venue"
},
  "geometry": {"coordinates":[-79.808464,43.320686],"type":"Point"}
}