{
  "type": "Feature",
  "properties": {
    "addr:full":"103 Mitton St S Sarnia ON N7T 3C5",
    "addr:housenumber":"103",
    "addr:postcode":"n7t 3c5",
    "addr:street":"Mitton St S",
    "iso:country":"CA",
    "sg:address":"103 Mitton St S",
    "sg:city":"Sarnia",
    "sg:classifiers":[
        {
            "category":"Insurance",
            "subcategory":"Insurance Agent",
            "type":"Services"
        }
    ],
    "sg:phone":"+1 519 332 2193",
    "sg:postcode":"N7T 3C5",
    "sg:province":"ON",
    "wof:name":"Kett Financial Group",
    "wof:placetype":"venue"
},
  "geometry": {"coordinates":[-82.39855957029999,42.9704208374],"type":"Point"}
}