{
  "type": "Feature",
  "properties": {
    "iso:country":"CA",
    "sg:address":"800 Rue Bombardier",
    "sg:city":"Mascouche",
    "sg:classifiers":[
        {
            "category":"Retail",
            "subcategory":"Auto Repair",
            "type":"Services"
        }
    ],
    "sg:phone":"+1 450 474 2738",
    "sg:postcode":"J7K 1X9",
    "sg:province":"QC",
    "sg:tags":[
        "body",
        "automobile",
        "painting"
    ],
    "wof:name":"Carrosserie Micart Ltee",
    "wof:placetype":"venue"
},
  "geometry": {"coordinates":[-73.5937957764,45.7392578125],"type":"Point"}
}