{
  "type": "Feature",
  "properties": {
    "addr:full":"410 Falconbridge Rd Sudbury ON P3A 4S4",
    "addr:housenumber":"410",
    "addr:postcode":"p3a 4s4",
    "addr:street":"Falconbridge Rd",
    "iso:country":"CA",
    "sg:address":"410 Falconbridge Rd",
    "sg:city":"Sudbury",
    "sg:classifiers":[
        {
            "category":"Shopping",
            "type":"Retail Goods"
        }
    ],
    "sg:phone":"+1 705 524 1396",
    "sg:postcode":"P3A 4S4",
    "sg:province":"ON",
    "sg:tags":[
        "splicing",
        "installation",
        "cable",
        "supply",
        "telephone",
        "detection",
        "equipment"
    ],
    "wof:name":"Desjardins Communications Ltd",
    "wof:placetype":"venue"
},
  "geometry": {"coordinates":[-80.935318,46.507851],"type":"Point"}
}