{
  "type": "Feature",
  "properties": {
    "iso:country":"CA",
    "sg:city":"Woodstock",
    "sg:classifiers":[
        {
            "category":"Professional",
            "subcategory":"Employment Agencies",
            "type":"Services"
        }
    ],
    "sg:phone":"+1 519 539 0448",
    "sg:postcode":"N4S 1B9",
    "sg:province":"ON",
    "sg:tags":[
        "opportunity"
    ],
    "wof:name":"Kelly Svc",
    "wof:placetype":"venue"
},
  "geometry": {"coordinates":[-80.759803772,43.1295166016],"type":"Point"}
}