{
  "type": "Feature",
  "properties": {
    "addr:full":"92 Rue DE L'Hotel-DE-Ville Hull QC J8X 2E6",
    "addr:housenumber":"92",
    "addr:postcode":"j8x 2e6",
    "addr:street":"Rue De L'Hotel-De-Ville",
    "iso:country":"CA",
    "sg:address":"92 Rue DE L'Hotel-DE-Ville",
    "sg:city":"Hull",
    "sg:classifiers":[
        {
            "category":"Real Estate",
            "subcategory":"Real Estate Operator",
            "type":"Services"
        }
    ],
    "sg:phone":"+1 819 771 0000",
    "sg:postcode":"J8X 2E6",
    "sg:province":"QC",
    "sg:tags":[
        "boarding",
        "house"
    ],
    "wof:name":"Duvernay Motel",
    "wof:placetype":"venue"
},
  "geometry": {"coordinates":[-75.71887207029999,45.4278526306],"type":"Point"}
}