{
  "type": "Feature",
  "properties": {
    "addr:full":"Toronto ON M6H 1Z1",
    "addr:postcode":"m6h 1z1",
    "iso:country":"CA",
    "sg:city":"Toronto",
    "sg:classifiers":[
        {
            "category":"Manufacturing",
            "subcategory":"Signs",
            "type":"Manufacturing & Wholesale Goods"
        }
    ],
    "sg:phone":"+1 416 536 6667",
    "sg:postcode":"M6H 1Z1",
    "sg:province":"ON",
    "wof:name":"Chok Sign Studio",
    "wof:placetype":"venue"
},
  "geometry": {"coordinates":[-79.42941999999999,43.670055],"type":"Point"}
}