{
  "type": "Feature",
  "properties": {
    "addr:full":"1333 Rue University Montreal QC H3A 2A4",
    "addr:housenumber":"1333",
    "addr:postcode":"h3a 2a4",
    "addr:street":"Rue University",
    "iso:country":"CA",
    "sg:address":"1333 Rue University",
    "sg:city":"Montreal",
    "sg:classifiers":[
        {
            "category":"Restaurant",
            "type":"Food & Drink"
        }
    ],
    "sg:phone":"+1 514 844 1619",
    "sg:postcode":"H3A 2A4",
    "sg:province":"QC",
    "wof:name":"Restaurant Le Parchemin Ltd",
    "wof:placetype":"venue"
},
  "geometry": {"coordinates":[-73.569839,45.503357],"type":"Point"}
}