{
  "type": "Feature",
  "properties": {
    "addr:full":"77 Crescent Dr New Minas NS B4N 3G7",
    "addr:housenumber":"77",
    "addr:postcode":"b4n 3g7",
    "addr:street":"Crescent Dr",
    "iso:country":"CA",
    "sg:address":"77 Crescent Dr",
    "sg:city":"New Minas",
    "sg:classifiers":[
        {
            "category":"Shopping",
            "subcategory":"Used Merchandise",
            "type":"Retail Goods"
        }
    ],
    "sg:phone":"+1 902 681 6075",
    "sg:postcode":"B4N 3G7",
    "sg:province":"NS",
    "sg:tags":[
        "shop",
        "consignment"
    ],
    "wof:name":"Consignors's Place",
    "wof:placetype":"venue"
},
  "geometry": {"coordinates":[-64.4621505737,45.0695762634],"type":"Point"}
}