{
  "type": "Feature",
  "properties": {
    "addr:full":"107 Erie St Stratford ON N5A 2M5",
    "addr:housenumber":"107",
    "addr:postcode":"n5a 2m5",
    "addr:street":"Erie St",
    "iso:country":"CA",
    "sg:address":"107 Erie St",
    "sg:city":"Stratford",
    "sg:classifiers":[
        {
            "category":"Travel",
            "subcategory":"Hotels & Motels",
            "type":"Entertainment"
        }
    ],
    "sg:phone":"+1 519 273 3666",
    "sg:postcode":"N5A 2M5",
    "sg:province":"ON",
    "wof:name":"Stratford Hotel",
    "wof:placetype":"venue"
},
  "geometry": {"coordinates":[-80.984093,43.369644],"type":"Point"}
}