{
  "type": "Feature",
  "properties": {
    "addr:full":"1109 Av Du Mont-Royal E Montreal QC H2J 1X9",
    "addr:housenumber":"1109",
    "addr:postcode":"h2j 1x9",
    "addr:street":"Av Du Mont-Royal E",
    "iso:country":"CA",
    "sg:address":"1109 Av Du Mont-Royal E",
    "sg:city":"Montreal",
    "sg:classifiers":[
        {
            "category":"Shopping",
            "subcategory":"Clothing, Apparel, & Fashions",
            "type":"Retail Goods"
        }
    ],
    "sg:phone":"+1 514 521 2873",
    "sg:postcode":"H2J 1X9",
    "sg:province":"QC",
    "wof:name":"Fet'Art",
    "wof:placetype":"venue"
},
  "geometry": {"coordinates":[-73.579208374,45.5282096863],"type":"Point"}
}