{
  "type": "Feature",
  "properties": {
    "iso:country":"CA",
    "sg:address":"2051 Rue Saint-Denis",
    "sg:city":"Montreal",
    "sg:classifiers":[
        {
            "category":"Restaurant",
            "type":"Food & Drink"
        }
    ],
    "sg:phone":"+1 514 845 8867",
    "sg:postcode":"H2X 3K8",
    "sg:province":"QC",
    "wof:name":"Restaurant Shezan",
    "wof:placetype":"venue"
},
  "geometry": {"coordinates":[-73.565964,45.516415],"type":"Point"}
}