{
  "type": "Feature",
  "properties": {
    "addr:full":"8 Elm St Toronto ON M5G 1G7",
    "addr:housenumber":"8",
    "addr:postcode":"m5g 1g7",
    "addr:street":"Elm St",
    "iso:country":"CA",
    "sg:address":"8 Elm St",
    "sg:city":"Toronto",
    "sg:classifiers":[
        {
            "category":"Arts & Performance",
            "subcategory":"Theater",
            "type":"Entertainment"
        }
    ],
    "sg:phone":"+1 416 964 8522",
    "sg:postcode":"M5G 1G7",
    "sg:province":"ON",
    "sg:tags":[
        "talent",
        "agency",
        "casting"
    ],
    "wof:name":"Characters Talent Agency",
    "wof:placetype":"venue"
},
  "geometry": {"coordinates":[-79.382233,43.65789],"type":"Point"}
}