{
  "type": "Feature",
  "properties": {
    "addr:full":"120 King St Spruce Grove AB T7X 3B1",
    "addr:housenumber":"120",
    "addr:postcode":"t7x 3b1",
    "addr:street":"King St",
    "iso:country":"CA",
    "sg:address":"120 King St",
    "sg:city":"Spruce Grove",
    "sg:classifiers":[
        {
            "category":"Personal",
            "type":"Services"
        }
    ],
    "sg:phone":"+1 780 960 3020",
    "sg:postcode":"T7X 3B1",
    "sg:province":"AB",
    "sg:tags":[
        "therapist",
        "massage"
    ],
    "wof:name":"Parkland Massage Therapy",
    "wof:placetype":"venue"
},
  "geometry": {"coordinates":[-113.899811,53.542007],"type":"Point"}
}