{
  "type": "Feature",
  "properties": {
    "iso:country":"CA",
    "sg:address":"3016 Cedar Ridge Dr SW",
    "sg:city":"Calgary",
    "sg:classifiers":[
        {
            "category":"Retail",
            "subcategory":"Repair Shop",
            "type":"Services"
        }
    ],
    "sg:phone":"+1 403 282 3711",
    "sg:postcode":"T2W 1X6",
    "sg:province":"AB",
    "sg:tags":[
        "appliance"
    ],
    "wof:name":"Aarons Appliance Svc",
    "wof:placetype":"venue"
},
  "geometry": {"coordinates":[-114.131088257,50.9595947266],"type":"Point"}
}