{
  "type": "Feature",
  "properties": {
    "addr:full":"3483 Steller Pl Roberts Creek BC V0N 2W1",
    "addr:postcode":"3483;v0n 2w1",
    "addr:street":"Steller Pl",
    "iso:country":"CA",
    "sg:address":"3483 Steller Pl",
    "sg:city":"Roberts Creek",
    "sg:classifiers":[
        {
            "category":"Building & Trades",
            "subcategory":"Landscaping Services",
            "type":"Services"
        }
    ],
    "sg:phone":"+1 604 885 9502",
    "sg:postcode":"V0N 2W1",
    "sg:province":"BC",
    "sg:tags":[
        "landscape",
        "contractor"
    ],
    "wof:name":"Guyscapes Landscaping",
    "wof:placetype":"venue"
},
  "geometry": {"coordinates":[-123.606461,49.413261],"type":"Point"}
}