{
  "type": "Feature",
  "properties": {
    "iso:country":"CA",
    "sg:address":"2 Director Crt",
    "sg:city":"Woodbridge",
    "sg:classifiers":[
        {
            "category":"Freight",
            "type":"Transportation"
        }
    ],
    "sg:phone":"+1 905 265 1221",
    "sg:postcode":"L4L 3Z5",
    "sg:province":"ON",
    "sg:tags":[
        "trucking"
    ],
    "wof:name":"Loft Transportation Inc",
    "wof:placetype":"venue"
},
  "geometry": {"coordinates":[-79.5410003662,43.7718505859],"type":"Point"}
}