{
  "type": "Feature",
  "properties": {
    "iso:country":"CA",
    "sg:address":"1469 Sunset Dr",
    "sg:city":"Fort Erie",
    "sg:classifiers":[
        {
            "category":"Building & Trades",
            "subcategory":"Construction",
            "type":"Services"
        }
    ],
    "sg:phone":"+1 905 871 9349",
    "sg:postcode":"L2A 5M4",
    "sg:province":"ON",
    "sg:tags":[
        "maker",
        "cabinet"
    ],
    "wof:name":"Epb Cabinetry & Renovations",
    "wof:placetype":"venue"
},
  "geometry": {"coordinates":[-78.9783401489,42.9156570435],"type":"Point"}
}