{
  "type": "Feature",
  "properties": {
    "addr:full":"385 Greenfield Rd Greenfield NB E7L 3C7",
    "addr:housenumber":"385",
    "addr:postcode":"e7l 3c7",
    "addr:street":"Greenfield Rd",
    "iso:country":"CA",
    "sg:address":"385 Greenfield Rd",
    "sg:city":"Greenfield",
    "sg:classifiers":[
        {
            "category":"Retail",
            "subcategory":"Auto Repair",
            "type":"Services"
        }
    ],
    "sg:phone":"+1 506 392 6975",
    "sg:postcode":"E7L 3C7",
    "sg:province":"NB",
    "sg:tags":[
        "truck"
    ],
    "wof:name":"H Mc Quade & Sons Truck Repair",
    "wof:placetype":"venue"
},
  "geometry": {"coordinates":[-67.659943,46.462879],"type":"Point"}
}