{
  "type": "Feature",
  "properties": {
    "addr:full":"Hearst ON P0L 1N0",
    "addr:postcode":"p0l 1n0",
    "iso:country":"CA",
    "sg:city":"Hearst",
    "sg:classifiers":[
        {
            "category":"Autos & Motor Vehicles",
            "subcategory":"Fuel & Gas Station",
            "type":"Retail Goods"
        }
    ],
    "sg:phone":"+1 705 362 4868",
    "sg:postcode":"P0L 1N0",
    "sg:province":"ON",
    "sg:tags":[
        "propane",
        "oil"
    ],
    "wof:name":"Husky Plus",
    "wof:placetype":"venue"
},
  "geometry": {"coordinates":[-83.664948,49.689316],"type":"Point"}
}