{
  "type": "Feature",
  "properties": {
    "addr:full":"Quesnel BC V2J 2Y1",
    "addr:postcode":"v2j 2y1",
    "iso:country":"CA",
    "sg:city":"Quesnel",
    "sg:classifiers":[
        {
            "category":"Autos & Motor Vehicles",
            "subcategory":"Fuel & Gas Station",
            "type":"Retail Goods"
        }
    ],
    "sg:phone":"+1 250 992 9450",
    "sg:postcode":"V2J 2Y1",
    "sg:province":"BC",
    "sg:tags":[
        "oil"
    ],
    "wof:name":"Super Save Gas",
    "wof:placetype":"venue"
},
  "geometry": {"coordinates":[-122.501693726,52.9879646301],"type":"Point"}
}