{
  "type": "Feature",
  "properties": {
    "addr:full":"29 Manitoba St # 1 Bracebridge ON P1L 1S4",
    "addr:housenumber":"29",
    "addr:postcode":"p1l 1s4",
    "addr:street":"Manitoba St # 1",
    "iso:country":"CA",
    "sg:address":"29 Manitoba St # 1",
    "sg:city":"Bracebridge",
    "sg:classifiers":[
        {
            "category":"Organizations",
            "subcategory":"Professional Association",
            "type":"Services"
        }
    ],
    "sg:phone":"+1 705 645 9827",
    "sg:postcode":"P1L 1S4",
    "sg:province":"ON",
    "wof:name":"Community Ywca of Muskoka",
    "wof:placetype":"venue"
},
  "geometry": {"coordinates":[-79.309479,45.040882],"type":"Point"}
}