{
  "type": "Feature",
  "properties": {
    "addr:full":"493 Concession St Hamilton ON L9A 1C1",
    "addr:housenumber":"493",
    "addr:postcode":"l9a 1c1",
    "addr:street":"Concession St",
    "iso:country":"CA",
    "sg:address":"493 Concession St",
    "sg:city":"Hamilton",
    "sg:classifiers":[
        {
            "category":"Personal",
            "type":"Services"
        }
    ],
    "sg:phone":"+1 905 387 3092",
    "sg:postcode":"L9A 1C1",
    "sg:province":"ON",
    "sg:tags":[
        "therapist",
        "massage"
    ],
    "wof:name":"Family Massage Therapy Clinic",
    "wof:placetype":"venue"
},
  "geometry": {"coordinates":[-79.854523,43.241722],"type":"Point"}
}