{
  "type": "Feature",
  "properties": {
    "iso:country":"CA",
    "sg:address":"50 Hadrian Dr",
    "sg:city":"Etobicoke",
    "sg:classifiers":[
        {
            "category":"Education",
            "subcategory":"School",
            "type":"Public Place"
        }
    ],
    "sg:phone":"+1 416 394 7913",
    "sg:postcode":"M9W 1V4",
    "sg:province":"ON",
    "wof:name":"Elmlea Junior School",
    "wof:placetype":"venue"
},
  "geometry": {"coordinates":[-79.55023956300001,43.7156105042],"type":"Point"}
}