{
  "type": "Feature",
  "properties": {
    "addr:full":"75 Rue Gamelin Hull QC J8Y 1V5",
    "addr:housenumber":"75",
    "addr:postcode":"j8y 1v5",
    "addr:street":"Rue Gamelin",
    "iso:country":"CA",
    "sg:address":"75 Rue Gamelin",
    "sg:city":"Hull",
    "sg:classifiers":[
        {
            "category":"Personal",
            "subcategory":"Beauty Salon",
            "type":"Services"
        }
    ],
    "sg:phone":"+1 819 777 5617",
    "sg:postcode":"J8Y 1V5",
    "sg:province":"QC",
    "sg:tags":[
        "electrolysis"
    ],
    "wof:name":"Esthetique & Electrolyse",
    "wof:placetype":"venue"
},
  "geometry": {"coordinates":[-75.736664,45.443512],"type":"Point"}
}