{
  "type": "Feature",
  "properties": {
    "addr:full":"65 Glasgow St Kitchener ON N2G 2G8",
    "addr:housenumber":"65",
    "addr:postcode":"n2g 2g8",
    "addr:street":"Glasgow St",
    "iso:country":"CA",
    "sg:address":"65 Glasgow St",
    "sg:city":"Kitchener",
    "sg:classifiers":[
        {
            "category":"Health Services",
            "subcategory":"Doctor",
            "type":"Services"
        }
    ],
    "sg:phone":"+1 519 749 9713",
    "sg:postcode":"N2G 2G8",
    "sg:province":"ON",
    "sg:tags":[
        "dentist"
    ],
    "wof:name":"Pather, Kumie DDS",
    "wof:placetype":"venue"
},
  "geometry": {"coordinates":[-80.5112457275,43.453742981],"type":"Point"}
}