{
  "type": "Feature",
  "properties": {
    "addr:full":"182 East St S Bobcaygeon ON K0M 1A0",
    "addr:housenumber":"182",
    "addr:postcode":"k0m 1a0",
    "addr:street":"East St S Bobcaygeon",
    "iso:country":"CA",
    "sg:address":"182 East St S",
    "sg:city":"Bobcaygeon",
    "sg:classifiers":[
        {
            "category":"Health Services",
            "subcategory":"Chiropractor",
            "type":"Services"
        }
    ],
    "sg:phone":"+1 705 738 3573",
    "sg:postcode":"K0M 1A0",
    "sg:province":"ON",
    "wof:name":"Bobcaygeon Chiropractic Ctr",
    "wof:placetype":"venue"
},
  "geometry": {"coordinates":[-78.536598,44.534515],"type":"Point"}
}