{
  "type": "Feature",
  "properties": {
    "addr:full":"18 Av Coolbreeze Pointe-Claire QC H9S 5G4",
    "addr:postcode":"h9s 5g4",
    "addr:street":"18 Av Coolbreeze",
    "iso:country":"CA",
    "sg:address":"18 Av Coolbreeze",
    "sg:city":"Pointe-Claire",
    "sg:classifiers":[
        {
            "category":"Professional",
            "subcategory":"Art Services",
            "type":"Services"
        }
    ],
    "sg:phone":"+1 514 426 4221",
    "sg:postcode":"H9S 5G4",
    "sg:province":"QC",
    "sg:tags":[
        "graphic",
        "designer"
    ],
    "wof:name":"Javelot Design",
    "wof:placetype":"venue"
},
  "geometry": {"coordinates":[-73.80085,45.44508],"type":"Point"}
}