{
  "type": "Feature",
  "properties": {
    "addr:full":"546 Bath Rd Kingston ON K7M 2Y3",
    "addr:housenumber":"546",
    "addr:postcode":"k7m 2y3",
    "addr:street":"Bath Rd",
    "iso:country":"CA",
    "sg:address":"546 Bath Rd",
    "sg:city":"Kingston",
    "sg:classifiers":[
        {
            "category":"Personal",
            "subcategory":"Beauty Salon",
            "type":"Services"
        }
    ],
    "sg:phone":"+1 613 548 7553",
    "sg:postcode":"K7M 2Y3",
    "sg:province":"ON",
    "wof:name":"Marianna's Hair Salon",
    "wof:placetype":"venue"
},
  "geometry": {"coordinates":[-76.539833,44.238247],"type":"Point"}
}