{
  "type": "Feature",
  "properties": {
    "addr:full":"7533 Main St W Radium Hot Springs BC V0A 1M0",
    "addr:housenumber":"7533",
    "addr:postcode":"v0a 1m0",
    "addr:street":"Main St W",
    "iso:country":"CA",
    "sg:address":"7533 Main St W",
    "sg:city":"Radium Hot Springs",
    "sg:classifiers":[
        {
            "category":"Cinema",
            "subcategory":"Movie Rental",
            "type":"Entertainment"
        }
    ],
    "sg:phone":"+1 250 347 9765",
    "sg:postcode":"V0A 1M0",
    "sg:province":"BC",
    "sg:tags":[
        "leasing",
        "video",
        "tape",
        "equipment"
    ],
    "wof:name":"Radium Video",
    "wof:placetype":"venue"
},
  "geometry": {"coordinates":[-116.071198,50.620262],"type":"Point"}
}