{
  "type": "Feature",
  "properties": {
    "addr:full":"20 James St E Cobourg ON K9A 1G9",
    "addr:housenumber":"20",
    "addr:postcode":"k9a 1g9",
    "addr:street":"James St E",
    "iso:country":"CA",
    "sg:address":"20 James St E",
    "sg:city":"Cobourg",
    "sg:classifiers":[
        {
            "category":"Organizations",
            "subcategory":"Professional Association",
            "type":"Services"
        }
    ],
    "sg:phone":"+1 905 372 4020",
    "sg:postcode":"K9A 1G9",
    "sg:province":"ON",
    "wof:name":"Cobourg Masonic Temple",
    "wof:placetype":"venue"
},
  "geometry": {"coordinates":[-78.166138,43.962982],"type":"Point"}
}