{
  "type": "Feature",
  "properties": {
    "iso:country":"CA",
    "sg:address":"12511 82 Ave",
    "sg:city":"Surrey",
    "sg:classifiers":[
        {
            "category":"Manufacturing",
            "subcategory":"Metals",
            "type":"Manufacturing & Wholesale Goods"
        }
    ],
    "sg:phone":"+1 604 591 8274",
    "sg:postcode":"V3W 3E8",
    "sg:province":"BC",
    "sg:tags":[
        "pipe",
        "fitting"
    ],
    "wof:name":"Le-Ron Plastics Inc",
    "wof:placetype":"venue"
},
  "geometry": {"coordinates":[-122.87511444099999,49.1521835327],"type":"Point"}
}