{
  "type": "Feature",
  "properties": {
    "addr:full":"3599 Boul Saint-Jean Dollard-Des-Ormeaux QC H9G 1W9",
    "addr:housenumber":"3599",
    "addr:postcode":"h9g 1w9",
    "addr:street":"Boul Saint-Jean",
    "iso:country":"CA",
    "sg:address":"3599 Boul Saint-Jean",
    "sg:city":"Dollard-Des-Ormeaux",
    "sg:classifiers":[
        {
            "category":"Retail",
            "subcategory":"Auto Repair",
            "type":"Services"
        }
    ],
    "sg:phone":"+1 514 626 9831",
    "sg:postcode":"H9G 1W9",
    "sg:province":"QC",
    "sg:tags":[
        "repairing",
        "automobile",
        "muffler",
        "system",
        "exhaust"
    ],
    "wof:name":"Service Auto Speedy",
    "wof:placetype":"venue"
},
  "geometry": {"coordinates":[-73.83232099999999,45.470905],"type":"Point"}
}