{
  "type": "Feature",
  "properties": {
    "addr:full":"Flesherton ON N0C 1E0",
    "addr:postcode":"n0c 1e0",
    "iso:country":"CA",
    "sg:city":"Flesherton",
    "sg:classifiers":[
        {
            "category":"Organizations",
            "subcategory":"Religious Organization",
            "type":"Services"
        }
    ],
    "sg:phone":"+1 519 922 1126",
    "sg:postcode":"N0C 1E0",
    "sg:province":"ON",
    "sg:tags":[
        "house",
        "school",
        "retreat"
    ],
    "wof:name":"Silver Springs Culinary",
    "wof:placetype":"venue"
},
  "geometry": {"coordinates":[-80.453926,44.331833],"type":"Point"}
}