{
  "type": "Feature",
  "properties": {
    "iso:country":"CA",
    "sg:address":"2040 Algonquin Rd",
    "sg:city":"Sudbury",
    "sg:classifiers":[
        {
            "category":"Autos & Motor Vehicles",
            "subcategory":"Auto Supplies",
            "type":"Retail Goods"
        }
    ],
    "sg:phone":"+1 705 522 2198",
    "sg:postcode":"P3E 4Z6",
    "sg:province":"ON",
    "sg:tags":[
        "automobile",
        "parts"
    ],
    "wof:name":"Canadian Tire Gas & Stop",
    "wof:placetype":"venue"
},
  "geometry": {"coordinates":[-80.9950332642,46.4480743408],"type":"Point"}
}