{
  "type": "Feature",
  "properties": {
    "iso:country":"CA",
    "sg:address":"306 Alexander St",
    "sg:city":"Whitehorse",
    "sg:classifiers":[
        {
            "category":"Social Services",
            "type":"Services"
        }
    ],
    "sg:phone":"+1 867 667 2810",
    "sg:postcode":"Y1A 2L6",
    "sg:province":"YT",
    "sg:tags":[
        "organization",
        "association",
        "welfare"
    ],
    "wof:name":"Royal Canadian Legion Ladies",
    "wof:placetype":"venue"
},
  "geometry": {"coordinates":[-135.05758667000001,60.7231674194],"type":"Point"}
}