{
  "type": "Feature",
  "properties": {
    "iso:country":"CA",
    "sg:address":"61 Bimbrok Rd",
    "sg:city":"Scarborough",
    "sg:classifiers":[
        {
            "category":"Shopping",
            "type":"Retail Goods"
        }
    ],
    "sg:phone":"+1 416 269 9738",
    "sg:postcode":"M1K 4T8",
    "sg:province":"ON",
    "sg:tags":[
        "monument"
    ],
    "wof:name":"William Tunstead Monument CO",
    "wof:placetype":"venue"
},
  "geometry": {"coordinates":[-79.2531738281,43.7390670776],"type":"Point"}
}