{
  "type": "Feature",
  "properties": {
    "addr:full":"5651 Boul Cavendish Cote Saint-Luc QC H4W 3K5",
    "addr:housenumber":"5651",
    "addr:postcode":"h4w 3k5",
    "addr:street":"Boul Cavendish Cote",
    "iso:country":"CA",
    "sg:address":"5651 Boul Cavendish",
    "sg:city":"Cote Saint-Luc",
    "sg:classifiers":[
        {
            "category":"Wholesale",
            "subcategory":"Apparel",
            "type":"Manufacturing & Wholesale Goods"
        }
    ],
    "sg:phone":"+1 514 488 7404",
    "sg:postcode":"H4W 3K5",
    "sg:province":"QC",
    "sg:tags":[
        "woolen",
        "worsted",
        "fabric"
    ],
    "wof:name":"Domeuil",
    "wof:placetype":"venue"
},
  "geometry": {"coordinates":[-73.657196,45.475254],"type":"Point"}
}