{
  "type": "Feature",
  "properties": {
    "addr:full":"2032 Robie St Halifax NS B3K 4M3",
    "addr:housenumber":"2032",
    "addr:postcode":"b3k 4m3",
    "addr:street":"Robie St",
    "iso:country":"CA",
    "sg:address":"2032 Robie St",
    "sg:city":"Halifax",
    "sg:classifiers":[
        {
            "category":"Retail",
            "subcategory":"Funeral Services",
            "type":"Services"
        }
    ],
    "sg:phone":"+1 902 423 7295",
    "sg:postcode":"B3K 4M3",
    "sg:province":"NS",
    "sg:tags":[
        "director"
    ],
    "wof:name":"Cruikshank's Halifax Funeral",
    "wof:placetype":"venue"
},
  "geometry": {"coordinates":[-63.591042,44.647846],"type":"Point"}
}