{
  "type": "Feature",
  "properties": {
    "addr:full":"20 Robinson Rd Lawrencetown NS B2Z 1L9",
    "addr:housenumber":"20",
    "addr:postcode":"b2z 1l9",
    "addr:street":"Robinson Rd",
    "iso:country":"CA",
    "sg:address":"20 Robinson Rd",
    "sg:city":"Lawrencetown",
    "sg:classifiers":[
        {
            "category":"Freight",
            "type":"Transportation"
        }
    ],
    "sg:phone":"+1 902 433 0814",
    "sg:postcode":"B2Z 1L9",
    "sg:province":"NS",
    "sg:tags":[
        "trucking"
    ],
    "wof:name":"H & C Trucking",
    "wof:placetype":"venue"
},
  "geometry": {"coordinates":[-63.338531,44.645439],"type":"Point"}
}