{
  "type": "Feature",
  "properties": {
    "addr:full":"Caledonia ON N3W 1B6",
    "addr:postcode":"n3w 1b6",
    "iso:country":"CA",
    "sg:city":"Caledonia",
    "sg:classifiers":[
        {
            "category":"Professional",
            "subcategory":"Computer Services",
            "type":"Services"
        }
    ],
    "sg:phone":"+1 905 765 2882",
    "sg:postcode":"N3W 1B6",
    "sg:province":"ON",
    "sg:tags":[
        "website",
        "design"
    ],
    "wof:name":"Osim",
    "wof:placetype":"venue"
},
  "geometry": {"coordinates":[-79.952187,43.073479],"type":"Point"}
}