{
  "type": "Feature",
  "properties": {
    "iso:country":"CA",
    "sg:address":"2138 Brant St",
    "sg:city":"Burlington",
    "sg:classifiers":[
        {
            "category":"Organizations",
            "subcategory":"Religious Organization",
            "type":"Services"
        }
    ],
    "sg:phone":"+1 905 335 2640",
    "sg:postcode":"L7P 3W5",
    "sg:province":"ON",
    "sg:tags":[
        "church"
    ],
    "wof:name":"Brant Hills Presbyterian Chr",
    "wof:placetype":"venue"
},
  "geometry": {"coordinates":[-79.839508,43.353783],"type":"Point"}
}