{
  "type": "Feature",
  "properties": {
    "iso:country":"CA",
    "sg:address":"Airport Hangar 2",
    "sg:city":"Yorkton",
    "sg:classifiers":[
        {
            "category":"Building & Trades",
            "subcategory":"Equipment Rental",
            "type":"Services"
        }
    ],
    "sg:phone":"+1 306 783 5438",
    "sg:postcode":"S3N 3X3",
    "sg:province":"SK",
    "sg:tags":[
        "helicopter",
        "aircraft",
        "leasing",
        "charter"
    ],
    "wof:name":"Heli-Lift Intl Inc",
    "wof:placetype":"venue"
},
  "geometry": {"coordinates":[-102.449874878,51.2040557861],"type":"Point"}
}