{
  "type": "Feature",
  "properties": {
    "addr:full":"27 Bernard Pl NW Calgary AB T3K 2B8",
    "addr:housenumber":"27",
    "addr:postcode":"t3k 2b8",
    "addr:street":"Bernard Pl Nw",
    "iso:country":"CA",
    "sg:address":"27 Bernard Pl NW",
    "sg:city":"Calgary",
    "sg:classifiers":[
        {
            "category":"Recreation",
            "type":"Entertainment"
        }
    ],
    "sg:phone":"+1 403 295 0886",
    "sg:postcode":"T3K 2B8",
    "sg:province":"AB",
    "sg:tags":[
        "instruction",
        "swimming"
    ],
    "wof:name":"Kalos Swim Team",
    "wof:placetype":"venue"
},
  "geometry": {"coordinates":[-114.077682495,51.1337127686],"type":"Point"}
}