{
  "type": "Feature",
  "properties": {
    "addr:full":"105 Main St W Listowel ON N4W 1A2",
    "addr:housenumber":"105",
    "addr:postcode":"n4w 1a2",
    "addr:street":"Main St W",
    "iso:country":"CA",
    "sg:address":"105 Main St W",
    "sg:city":"Listowel",
    "sg:classifiers":[
        {
            "category":"Banks & Credit Unions",
            "subcategory":"Bank",
            "type":"Services"
        }
    ],
    "sg:phone":"+1 519 291 1920",
    "sg:postcode":"N4W 1A2",
    "sg:province":"ON",
    "wof:name":"Cibc",
    "wof:placetype":"venue"
},
  "geometry": {"coordinates":[-80.9532699585,43.7317390442],"type":"Point"}
}