{
  "type": "Feature",
  "properties": {
    "iso:country":"CA",
    "sg:city":"Edmonton",
    "sg:classifiers":[
        {
            "category":"Shopping",
            "subcategory":"Photographic Equipment",
            "type":"Retail Goods"
        }
    ],
    "sg:phone":"+1 780 434 0873",
    "sg:postcode":"T6H 4M6",
    "sg:province":"AB",
    "sg:tags":[
        "photo",
        "finishing"
    ],
    "wof:name":"Mc Bain Camera Ltd",
    "wof:placetype":"venue"
},
  "geometry": {"coordinates":[-113.490371704,53.5462188721],"type":"Point"}
}