{
  "type": "Feature",
  "properties": {
    "addr:full":"332 Crestview Rd Ottawa ON K1H 5G6",
    "addr:housenumber":"332",
    "addr:postcode":"k1h 5g6",
    "addr:street":"Crestview Rd",
    "iso:country":"CA",
    "sg:address":"332 Crestview Rd",
    "sg:city":"Ottawa",
    "sg:classifiers":[
        {
            "category":"Professional",
            "subcategory":"Research",
            "type":"Services"
        }
    ],
    "sg:phone":"+1 613 737 2026",
    "sg:postcode":"K1H 5G6",
    "sg:province":"ON",
    "sg:tags":[
        "development",
        "electronic"
    ],
    "wof:name":"Asr Technologies Inc",
    "wof:placetype":"venue"
},
  "geometry": {"coordinates":[-75.6583480835,45.3960838318],"type":"Point"}
}