{
  "type": "Feature",
  "properties": {
    "iso:country":"CA",
    "sg:address":"211 Wharncliffe Rd S",
    "sg:city":"London",
    "sg:classifiers":[
        {
            "category":"Retail",
            "subcategory":"Auto Repair",
            "type":"Services"
        }
    ],
    "sg:phone":"+1 519 433 0186",
    "sg:postcode":"N6J 2K8",
    "sg:province":"ON",
    "sg:tags":[
        "transmission",
        "automobile",
        "repairing"
    ],
    "wof:name":"Mister Transmission",
    "wof:placetype":"venue"
},
  "geometry": {"coordinates":[-81.261917,42.969429],"type":"Point"}
}