{
  "type": "Feature",
  "properties": {
    "addr:full":"Digby NS B0V 1A0",
    "addr:postcode":"b0v 1a0",
    "iso:country":"CA",
    "sg:city":"Digby",
    "sg:classifiers":[
        {
            "category":"Professional",
            "type":"Services"
        }
    ],
    "sg:phone":"+1 902 245 2437",
    "sg:postcode":"B0V 1A0",
    "sg:province":"NS",
    "sg:tags":[
        "establishment",
        "utility"
    ],
    "wof:name":"Maritime Harbour Society",
    "wof:placetype":"venue"
},
  "geometry": {"coordinates":[-65.7565,44.624645],"type":"Point"}
}