{
  "type": "Feature",
  "properties": {
    "addr:full":"3371 No. 6 Rd Richmond BC V6V 1P6",
    "addr:postcode":"3371;v6v 1p6",
    "addr:street":"6 Rd",
    "iso:country":"CA",
    "sg:address":"3371 No. 6 Rd",
    "sg:city":"Richmond",
    "sg:classifiers":[
        {
            "category":"Wholesale",
            "subcategory":"Meat",
            "type":"Manufacturing & Wholesale Goods"
        }
    ],
    "sg:phone":"+1 604 278 4517",
    "sg:postcode":"V6V 1P6",
    "sg:province":"BC",
    "sg:tags":[
        "product"
    ],
    "wof:name":"New Zealand Lamb CO Ltd",
    "wof:placetype":"venue"
},
  "geometry": {"coordinates":[-123.06943511999999,49.189125061],"type":"Point"}
}