{
  "type": "Feature",
  "properties": {
    "addr:full":"224 Rue Dupont L'Ile-Bizard QC H9C 1M4",
    "addr:housenumber":"224",
    "addr:postcode":"h9c 1m4",
    "addr:street":"Rue Dupont",
    "iso:country":"CA",
    "sg:address":"224 Rue Dupont",
    "sg:city":"L'Ile-Bizard",
    "sg:classifiers":[
        {
            "category":"Retail",
            "subcategory":"Auto Repair",
            "type":"Services"
        }
    ],
    "sg:phone":"+1 514 624 4840",
    "sg:postcode":"H9C 1M4",
    "sg:province":"QC",
    "sg:tags":[
        "repairing",
        "automobile"
    ],
    "wof:name":"Kal Auto Svc",
    "wof:placetype":"venue"
},
  "geometry": {"coordinates":[-73.87190200000001,45.487396],"type":"Point"}
}