{
  "type": "Feature",
  "properties": {
    "addr:full":"3886 Rue Jean-Talon E Montreal QC H2A 1Y7",
    "addr:housenumber":"3886",
    "addr:postcode":"h2a 1y7",
    "addr:street":"Rue Jean-Talon E",
    "iso:country":"CA",
    "sg:address":"3886 Rue Jean-Talon E",
    "sg:city":"Montreal",
    "sg:classifiers":[
        {
            "category":"Health Services",
            "subcategory":"Medical Lab",
            "type":"Services"
        }
    ],
    "sg:phone":"+1 514 729 5015",
    "sg:postcode":"H2A 1Y7",
    "sg:province":"QC",
    "wof:name":"Sanchez, Jose",
    "wof:placetype":"venue"
},
  "geometry": {"coordinates":[-73.592484,45.565086],"type":"Point"}
}