{
  "type": "Feature",
  "properties": {
    "addr:full":"2695 Rue Diab Saint-Laurent QC H4S 1E7",
    "addr:housenumber":"2695",
    "addr:postcode":"h4s 1e7",
    "addr:street":"Rue Diab",
    "iso:country":"CA",
    "sg:address":"2695 Rue Diab",
    "sg:city":"Saint-Laurent",
    "sg:classifiers":[
        {
            "category":"Wholesale",
            "subcategory":"Machinery & Supplies",
            "type":"Manufacturing & Wholesale Goods"
        }
    ],
    "sg:phone":"+1 514 333 1555",
    "sg:postcode":"H4S 1E7",
    "sg:province":"QC",
    "sg:tags":[
        "spring",
        "flat"
    ],
    "wof:name":"Mark Tech Inc",
    "wof:placetype":"venue"
},
  "geometry": {"coordinates":[-73.747192,45.494579],"type":"Point"}
}