{
  "type": "Feature",
  "properties": {
    "iso:country":"CA",
    "sg:address":"851 Rue Saint-Georges",
    "sg:city":"Saint-Jerome",
    "sg:classifiers":[
        {
            "category":"Retail",
            "subcategory":"Auto Repair",
            "type":"Services"
        }
    ],
    "sg:phone":"+1 450 436 1060",
    "sg:postcode":"J7Z 5E2",
    "sg:province":"QC",
    "sg:tags":[
        "repairing",
        "automobile",
        "tire"
    ],
    "wof:name":"Pneus Mathieu Freins Ltee",
    "wof:placetype":"venue"
},
  "geometry": {"coordinates":[-74.0049362183,45.7907371521],"type":"Point"}
}