{
  "type": "Feature",
  "properties": {
    "iso:country":"CA",
    "sg:city":"Scarborough",
    "sg:classifiers":[
        {
            "category":"Manufacturing",
            "subcategory":"Metals",
            "type":"Manufacturing & Wholesale Goods"
        }
    ],
    "sg:phone":"+1 416 757 7381",
    "sg:postcode":"M1P 4V5",
    "sg:province":"ON",
    "sg:tags":[
        "plating"
    ],
    "wof:name":"B & H Plating CO Ltd",
    "wof:placetype":"venue"
},
  "geometry": {"coordinates":[-79.276306,43.761681],"type":"Point"}
}