{
  "type": "Feature",
  "properties": {
    "addr:full":"132 Boul Jean-Paul-Vincent Longueuil QC J4G 1T2",
    "addr:housenumber":"132",
    "addr:postcode":"j4g 1t2",
    "addr:street":"Boul Jean-Paul-Vincent",
    "iso:country":"CA",
    "sg:address":"132 Boul Jean-Paul-Vincent",
    "sg:city":"Longueuil",
    "sg:classifiers":[
        {
            "category":"Wholesale",
            "subcategory":"Electrical",
            "type":"Manufacturing & Wholesale Goods"
        }
    ],
    "sg:phone":"+1 450 442 4402",
    "sg:postcode":"J4G 1T2",
    "sg:province":"QC",
    "sg:tags":[
        "timing",
        "devices"
    ],
    "wof:name":"Sports Technologies Inc",
    "wof:placetype":"venue"
},
  "geometry": {"coordinates":[-73.48383331300001,45.5678405762],"type":"Point"}
}