{
  "type": "Feature",
  "properties": {
    "addr:full":"Ear Falls ON P0V 1T0",
    "addr:postcode":"p0v 1t0",
    "iso:country":"CA",
    "sg:city":"Ear Falls",
    "sg:classifiers":[
        {
            "category":"Autos & Motor Vehicles",
            "subcategory":"Boat Sales",
            "type":"Retail Goods"
        }
    ],
    "sg:phone":"+1 807 222 3479",
    "sg:postcode":"P0V 1T0",
    "sg:province":"ON",
    "sg:tags":[
        "equipment",
        "marine",
        "supply"
    ],
    "wof:name":"Rob's Earfalls Marine Svc",
    "wof:placetype":"venue"
},
  "geometry": {"coordinates":[-93.234421,50.638622],"type":"Point"}
}