{
  "type": "Feature",
  "properties": {
    "addr:full":"Kitchener ON N2G 4S4",
    "addr:postcode":"n2g 4s4",
    "iso:country":"CA",
    "sg:city":"Kitchener",
    "sg:classifiers":[
        {
            "category":"Health Services",
            "subcategory":"Doctor",
            "type":"Services"
        }
    ],
    "sg:phone":"+1 519 578 7484",
    "sg:postcode":"N2G 4S4",
    "sg:province":"ON",
    "sg:tags":[
        "physician",
        "surgeon"
    ],
    "wof:name":"Judges, David P MD",
    "wof:placetype":"venue"
},
  "geometry": {"coordinates":[-80.49555969239999,43.4433403015],"type":"Point"}
}