{
  "type": "Feature",
  "properties": {
    "addr:full":"North York ON M3J 3M1",
    "addr:postcode":"m3j 3m1",
    "iso:country":"CA",
    "sg:city":"North York",
    "sg:classifiers":[
        {
            "category":"Food & Beverages",
            "subcategory":"Bakery",
            "type":"Retail Goods"
        }
    ],
    "sg:phone":"+1 416 633 3135",
    "sg:postcode":"M3J 3M1",
    "sg:province":"ON",
    "sg:tags":[
        "doughnut"
    ],
    "wof:name":"Coffee Time Donuts",
    "wof:placetype":"venue"
},
  "geometry": {"coordinates":[-79.488388,43.752258],"type":"Point"}
}