{
  "type": "Feature",
  "properties": {
    "addr:full":"10 Washburn Way Scarborough ON M1B 1H3",
    "addr:housenumber":"10",
    "addr:postcode":"m1b 1h3",
    "addr:street":"Washburn Way",
    "iso:country":"CA",
    "sg:address":"10 Washburn Way",
    "sg:city":"Scarborough",
    "sg:classifiers":[
        {
            "category":"Professional",
            "subcategory":"Research",
            "type":"Services"
        }
    ],
    "sg:phone":"+1 416 297 9870",
    "sg:postcode":"M1B 1H3",
    "sg:province":"ON",
    "sg:tags":[
        "foundation",
        "philanthropic"
    ],
    "wof:name":"St Barnabas Conference Society",
    "wof:placetype":"venue"
},
  "geometry": {"coordinates":[-79.227859,43.796482],"type":"Point"}
}