{
  "type": "Feature",
  "properties": {
    "addr:full":"209 10th St Hanover ON N4N 1N8",
    "addr:housenumber":"209",
    "addr:postcode":"n4n 1n8",
    "addr:street":"10Th St",
    "iso:country":"CA",
    "sg:address":"209 10th St",
    "sg:city":"Hanover",
    "sg:classifiers":[
        {
            "category":"Food & Beverages",
            "subcategory":"Groceries & Convenience Stores",
            "type":"Retail Goods"
        }
    ],
    "sg:phone":"+1 519 364 2670",
    "sg:postcode":"N4N 1N8",
    "sg:province":"ON",
    "sg:tags":[
        "grocer"
    ],
    "wof:name":"Freshir Foods Inc",
    "wof:placetype":"venue"
},
  "geometry": {"coordinates":[-81.031509,44.15134],"type":"Point"}
}