{
  "type": "Feature",
  "properties": {
    "addr:full":"22 Maple Cres Paris ON N3L 3R4",
    "addr:housenumber":"22",
    "addr:postcode":"n3l 3r4",
    "addr:street":"Maple Cres",
    "iso:country":"CA",
    "sg:address":"22 Maple Cres",
    "sg:city":"Paris",
    "sg:classifiers":[
        {
            "category":"Building & Trades",
            "subcategory":"Construction",
            "type":"Services"
        }
    ],
    "sg:phone":"+1 519 442 4935",
    "sg:postcode":"N3L 3R4",
    "sg:province":"ON",
    "sg:tags":[
        "home",
        "improvement"
    ],
    "wof:name":"Paul Boilard Construction",
    "wof:placetype":"venue"
},
  "geometry": {"coordinates":[-80.392967,43.208466],"type":"Point"}
}