{
  "type": "Feature",
  "properties": {
    "addr:full":"Corkums Island Lunenburg NS B0J 2C0",
    "addr:postcode":"b0j 2c0",
    "iso:country":"CA",
    "sg:address":"Corkums Island",
    "sg:city":"Lunenburg",
    "sg:classifiers":[
        {
            "category":"Farming",
            "subcategory":"Aquatic Farm",
            "type":"Manufacturing & Wholesale Goods"
        }
    ],
    "sg:phone":"+1 902 634 3868",
    "sg:postcode":"B0J 2C0",
    "sg:province":"NS",
    "sg:tags":[
        "hatchery",
        "fish"
    ],
    "wof:name":"Lunenburg Shellfish",
    "wof:placetype":"venue"
},
  "geometry": {"coordinates":[-64.318443,44.377213],"type":"Point"}
}