{
  "type": "Feature",
  "properties": {
    "addr:full":"12 Blackfoot Rd # 28 Sherwood Park AB T8A 4P4",
    "addr:housenumber":"12;28",
    "addr:postcode":"t8a 4p4",
    "addr:street":"Blackfoot Rd #;Park",
    "iso:country":"CA",
    "sg:address":"12 Blackfoot Rd # 28",
    "sg:city":"Sherwood Park",
    "sg:classifiers":[
        {
            "category":"Personal",
            "type":"Services"
        }
    ],
    "sg:phone":"+1 780 449 2420",
    "sg:postcode":"T8A 4P4",
    "sg:province":"AB",
    "sg:tags":[
        "therapist",
        "massage"
    ],
    "wof:name":"Lifestyles-Therapeutic Massage",
    "wof:placetype":"venue"
},
  "geometry": {"coordinates":[-113.32317399999999,53.538391],"type":"Point"}
}