{
  "type": "Feature",
  "properties": {
    "iso:country":"CA",
    "sg:address":"2000 Airport Rd NE",
    "sg:city":"Calgary",
    "sg:classifiers":[
        {
            "category":"Shopping",
            "subcategory":"Clothing, Apparel, & Fashions",
            "type":"Retail Goods"
        }
    ],
    "sg:phone":"+1 403 571 9755",
    "sg:postcode":"T2E 6W5",
    "sg:province":"AB",
    "sg:tags":[
        "sporting"
    ],
    "wof:name":"Flames Fan Attic",
    "wof:placetype":"venue"
},
  "geometry": {"coordinates":[-114.010803,51.134357],"type":"Point"}
}