{
  "type": "Feature",
  "properties": {
    "addr:full":"273 Boul Saint-Rene O Gatineau QC J8P 2V7",
    "addr:housenumber":"273",
    "addr:postcode":"j8p 2v7",
    "addr:street":"Boul Saint-Rene O",
    "iso:country":"CA",
    "sg:address":"273 Boul Saint-Rene O",
    "sg:city":"Gatineau",
    "sg:classifiers":[
        {
            "category":"Restaurant",
            "type":"Food & Drink"
        }
    ],
    "sg:phone":"+1 819 663 7719",
    "sg:postcode":"J8P 2V7",
    "sg:province":"QC",
    "wof:name":"China Moon Restaurant",
    "wof:placetype":"venue"
},
  "geometry": {"coordinates":[-75.6447753906,45.4929008484],"type":"Point"}
}