{
  "type": "Feature",
  "properties": {
    "addr:full":"4896 Boul Taschereau Greenfield Park QC J4V 2J2",
    "addr:housenumber":"4896",
    "addr:postcode":"j4v 2j2",
    "addr:street":"Boul Taschereau",
    "iso:country":"CA",
    "sg:address":"4896 Boul Taschereau",
    "sg:city":"Greenfield Park",
    "sg:classifiers":[
        {
            "category":"Professional",
            "subcategory":"Accounting & Tax Preparation",
            "type":"Services"
        }
    ],
    "sg:phone":"+1 450 466 4043",
    "sg:postcode":"J4V 2J2",
    "sg:province":"QC",
    "sg:tags":[
        "accountant"
    ],
    "wof:name":"Raymond Hughuette",
    "wof:placetype":"venue"
},
  "geometry": {"coordinates":[-73.465599,45.483494],"type":"Point"}
}