{
  "type": "Feature",
  "properties": {
    "addr:full":"253 King St N # 202 Waterloo ON N2J 2Y8",
    "addr:housenumber":"253;202",
    "addr:postcode":"n2j 2y8",
    "addr:street":"King St N #",
    "iso:country":"CA",
    "sg:address":"253 King St N # 202",
    "sg:city":"Waterloo",
    "sg:classifiers":[
        {
            "category":"Professional",
            "subcategory":"Computer Services",
            "type":"Services"
        }
    ],
    "sg:phone":"+1 519 725 1593",
    "sg:postcode":"N2J 2Y8",
    "sg:province":"ON",
    "sg:tags":[
        "internet"
    ],
    "wof:name":"Montana Publishing",
    "wof:placetype":"venue"
},
  "geometry": {"coordinates":[-80.5252609253,43.4765968323],"type":"Point"}
}