{
  "type": "Feature",
  "properties": {
    "addr:full":"Kelowna BC V1Y 9S4",
    "addr:postcode":"v1y 9s4",
    "iso:country":"CA",
    "sg:city":"Kelowna",
    "sg:classifiers":[
        {
            "category":"Utilities",
            "subcategory":"Electric",
            "type":"Services"
        }
    ],
    "sg:phone":"+1 250 717 3707",
    "sg:postcode":"V1Y 9S4",
    "sg:province":"BC",
    "sg:tags":[
        "company"
    ],
    "wof:name":"Altek Power Corp",
    "wof:placetype":"venue"
},
  "geometry": {"coordinates":[-119.460556,49.879398],"type":"Point"}
}