{
  "type": "Feature",
  "properties": {
    "addr:full":"1066 Hudson Dr Kingston ON K7M 5K8",
    "addr:housenumber":"1066",
    "addr:postcode":"k7m 5k8",
    "addr:street":"Hudson Dr",
    "iso:country":"CA",
    "sg:address":"1066 Hudson Dr",
    "sg:city":"Kingston",
    "sg:classifiers":[
        {
            "category":"Education",
            "subcategory":"School",
            "type":"Public Place"
        }
    ],
    "sg:phone":"+1 613 389 6900",
    "sg:postcode":"K7M 5K8",
    "sg:province":"ON",
    "wof:name":"Bayridge Public School",
    "wof:placetype":"venue"
},
  "geometry": {"coordinates":[-76.59465026860001,44.2485923767],"type":"Point"}
}