{
  "type": "Feature",
  "properties": {
    "addr:full":"4493 Main St Vancouver BC V5V 3R2",
    "addr:housenumber":"4493",
    "addr:postcode":"v5v 3r2",
    "addr:street":"Main St",
    "iso:country":"CA",
    "sg:address":"4493 Main St",
    "sg:city":"Vancouver",
    "sg:classifiers":[
        {
            "category":"Banks & Credit Unions",
            "subcategory":"Bank",
            "type":"Services"
        }
    ],
    "sg:phone":"+1 ",
    "sg:postcode":"V5V 3R2",
    "sg:province":"BC",
    "wof:name":"Cibc",
    "wof:placetype":"venue"
},
  "geometry": {"coordinates":[-123.1014328,49.244682312],"type":"Point"}
}