{
  "type": "Feature",
  "properties": {
    "iso:country":"CA",
    "sg:address":"345 James St N",
    "sg:city":"Lumsden",
    "sg:classifiers":[
        {
            "category":"Health Services",
            "subcategory":"Doctor",
            "type":"Services"
        }
    ],
    "sg:phone":"+1 306 731 3129",
    "sg:postcode":"S0G 3C0",
    "sg:province":"SK",
    "sg:tags":[
        "physician",
        "surgeon"
    ],
    "wof:name":"Lumsden Medical Clinic",
    "wof:placetype":"venue"
},
  "geometry": {"coordinates":[-104.866493225,50.6468544006],"type":"Point"}
}