{
  "type": "Feature",
  "properties": {
    "addr:full":"297 Rue Principale O Magog QC J1X 2A8",
    "addr:housenumber":"297",
    "addr:postcode":"j1x 2a8",
    "addr:street":"Rue Principale O",
    "iso:country":"CA",
    "sg:address":"297 Rue Principale O",
    "sg:city":"Magog",
    "sg:classifiers":[
        {
            "category":"Shopping",
            "subcategory":"Clothing, Apparel, & Fashions",
            "type":"Retail Goods"
        }
    ],
    "sg:phone":"+1 819 847 3056",
    "sg:postcode":"J1X 2A8",
    "sg:province":"QC",
    "sg:tags":[
        "item",
        "boutique"
    ],
    "wof:name":"Chantournelle Inc",
    "wof:placetype":"venue"
},
  "geometry": {"coordinates":[-72.13904599999999,45.262779],"type":"Point"}
}