{
  "type": "Feature",
  "properties": {
    "addr:full":"940 Sherbrook St Winnipeg MB R3A 1N4",
    "addr:housenumber":"940",
    "addr:postcode":"r3a 1n4",
    "addr:street":"Sherbrook St",
    "iso:country":"CA",
    "sg:address":"940 Sherbrook St",
    "sg:city":"Winnipeg",
    "sg:classifiers":[
        {
            "category":"Organizations",
            "subcategory":"Community Association",
            "type":"Services"
        }
    ],
    "sg:phone":"+1 204 774 5147",
    "sg:postcode":"R3A 1N4",
    "sg:province":"MB",
    "sg:tags":[
        "club"
    ],
    "wof:name":"Casa Benfica",
    "wof:placetype":"venue"
},
  "geometry": {"coordinates":[-97.154015,49.906685],"type":"Point"}
}