{
  "type": "Feature",
  "properties": {
    "addr:full":"138 Principale E Ru # A Saint-Elzear-DE-Bonaventure QC G0C 2W0",
    "addr:housenumber":"138",
    "addr:postcode":"g0c 2w0",
    "addr:street":"Principale E Ru # A Saint-Elzear-De-Bonaventure",
    "iso:country":"CA",
    "sg:address":"138 Principale E Ru # A",
    "sg:city":"Saint-Elzear-DE-Bonaventure",
    "sg:classifiers":[
        {
            "category":"Organizations",
            "subcategory":"Religious Organization",
            "type":"Services"
        }
    ],
    "sg:phone":"+1 418 534 2737",
    "sg:postcode":"G0C 2W0",
    "sg:province":"QC",
    "sg:tags":[
        "church"
    ],
    "wof:name":"St-Elzear Eglises",
    "wof:placetype":"venue"
},
  "geometry": {"coordinates":[-65.494446,48.045422],"type":"Point"}
}