{
  "type": "Feature",
  "properties": {
    "addr:full":"Flesherton ON N0C 1E0",
    "addr:postcode":"n0c 1e0",
    "iso:country":"CA",
    "sg:city":"Flesherton",
    "sg:classifiers":[
        {
            "category":"Personal",
            "type":"Services"
        }
    ],
    "sg:phone":"+1 519 924 0698",
    "sg:postcode":"N0C 1E0",
    "sg:province":"ON",
    "sg:tags":[
        "therapist",
        "massage"
    ],
    "wof:name":"Delphi",
    "wof:placetype":"venue"
},
  "geometry": {"coordinates":[-80.54986599999999,44.261234],"type":"Point"}
}