{
  "type": "Feature",
  "properties": {
    "addr:full":"117 10th St Brandon MB R7A 4E7",
    "addr:housenumber":"117",
    "addr:postcode":"r7a 4e7",
    "addr:street":"10Th St",
    "iso:country":"CA",
    "sg:address":"117 10th St",
    "sg:city":"Brandon",
    "sg:classifiers":[
        {
            "category":"Professional",
            "subcategory":"Accounting & Tax Preparation",
            "type":"Services"
        }
    ],
    "sg:phone":"+1 204 727 0671",
    "sg:postcode":"R7A 4E7",
    "sg:province":"MB",
    "sg:tags":[
        "accountant"
    ],
    "wof:name":"Bdo Dunwoody Ltd",
    "wof:placetype":"venue"
},
  "geometry": {"coordinates":[-99.951294,49.848103],"type":"Point"}
}