{
  "type": "Feature",
  "properties": {
    "addr:full":"111 Vermillion Ave Princeton BC V0X 1W0",
    "addr:housenumber":"111",
    "addr:postcode":"v0x 1w0",
    "addr:street":"Vermillion Ave",
    "iso:country":"CA",
    "sg:address":"111 Vermillion Ave",
    "sg:city":"Princeton",
    "sg:classifiers":[
        {
            "category":"Shopping",
            "subcategory":"Used Merchandise",
            "type":"Retail Goods"
        }
    ],
    "sg:phone":"+1 250 295 6881",
    "sg:postcode":"V0X 1W0",
    "sg:province":"BC",
    "sg:tags":[
        "shop",
        "thrift"
    ],
    "wof:name":"Princeton Crisis Assistance",
    "wof:placetype":"venue"
},
  "geometry": {"coordinates":[-120.508347,49.460247],"type":"Point"}
}