{
  "type": "Feature",
  "properties": {
    "iso:country":"CA",
    "sg:city":"Richmond Hill",
    "sg:classifiers":[
        {
            "category":"Professional",
            "subcategory":"Engineering",
            "type":"Services"
        }
    ],
    "sg:phone":"+1 905 882 4100",
    "sg:postcode":"L4B 1J8",
    "sg:province":"ON",
    "sg:tags":[
        "engineer"
    ],
    "wof:name":"Itrans Consulting Inc",
    "wof:placetype":"venue"
},
  "geometry": {"coordinates":[-79.378105,43.847752],"type":"Point"}
}