{
  "type": "Feature",
  "properties": {
    "addr:full":"40 Morrow Rd Barrie ON L4N 3V8",
    "addr:housenumber":"40",
    "addr:postcode":"l4n 3v8",
    "addr:street":"Morrow Rd",
    "iso:country":"CA",
    "sg:address":"40 Morrow Rd",
    "sg:city":"Barrie",
    "sg:classifiers":[
        {
            "category":"Autos & Motor Vehicles",
            "subcategory":"Auto Supplies",
            "type":"Retail Goods"
        }
    ],
    "sg:phone":"+1 705 726 5510",
    "sg:postcode":"L4N 3V8",
    "sg:province":"ON",
    "sg:tags":[
        "tire"
    ],
    "wof:name":"Al's Tire Wholesale",
    "wof:placetype":"venue"
},
  "geometry": {"coordinates":[-79.701981,44.360771],"type":"Point"}
}