{
  "type": "Feature",
  "properties": {
    "addr:full":"Winnipeg MB R3B 3B1",
    "addr:postcode":"r3b 3b1",
    "iso:country":"CA",
    "sg:city":"Winnipeg",
    "sg:classifiers":[
        {
            "category":"Manufacturing",
            "subcategory":"Printing",
            "type":"Manufacturing & Wholesale Goods"
        }
    ],
    "sg:phone":"+1 204 943 9587",
    "sg:postcode":"R3B 3B1",
    "sg:province":"MB",
    "sg:tags":[
        "printer"
    ],
    "wof:name":"Derksen Printers Ltd",
    "wof:placetype":"venue"
},
  "geometry": {"coordinates":[-97.134148,49.895649],"type":"Point"}
}