{
  "type": "Feature",
  "properties": {
    "addr:full":"PO Box 750 Provost AB T0B 3S0",
    "addr:housenumber":"po;750;ab",
    "addr:postcode":"t0b 3s0",
    "addr:street":"Box;Provost",
    "iso:country":"CA",
    "sg:address":"PO Box 750",
    "sg:city":"Provost",
    "sg:classifiers":[
        {
            "category":"Organizations",
            "subcategory":"Religious Organization",
            "type":"Services"
        }
    ],
    "sg:phone":"+1 403 753 2081",
    "sg:postcode":"T0B 3S0",
    "sg:province":"AB",
    "sg:tags":[
        "church"
    ],
    "wof:name":"Macklin United Church",
    "wof:placetype":"venue"
},
  "geometry": {"coordinates":[-110.268295288,52.3611373901],"type":"Point"}
}