{
  "type": "Feature",
  "properties": {
    "addr:full":"338 Hamilton Manitou MB R0G 1G0",
    "addr:housenumber":"338",
    "addr:postcode":"r0g 1g0",
    "addr:street":"Hamilton",
    "iso:country":"CA",
    "sg:address":"338 Hamilton",
    "sg:city":"Manitou",
    "sg:classifiers":[
        {
            "category":"Organizations",
            "subcategory":"Religious Organization",
            "type":"Services"
        }
    ],
    "sg:phone":"+1 204 242 2448",
    "sg:postcode":"R0G 1G0",
    "sg:province":"MB",
    "sg:tags":[
        "church"
    ],
    "wof:name":"United Church of Manitou",
    "wof:placetype":"venue"
},
  "geometry": {"coordinates":[-98.53465300000001,49.236721],"type":"Point"}
}