{
  "type": "Feature",
  "properties": {
    "addr:full":"1010 Pape Ave East York ON M4K 3V9",
    "addr:housenumber":"1010",
    "addr:postcode":"m4k 3v9",
    "addr:street":"Pape Ave",
    "iso:country":"CA",
    "sg:address":"1010 Pape Ave",
    "sg:city":"East York",
    "sg:classifiers":[
        {
            "category":"Shopping",
            "subcategory":"Gifts & Souvenirs",
            "type":"Retail Goods"
        }
    ],
    "sg:phone":"+1 416 421 2255",
    "sg:postcode":"M4K 3V9",
    "sg:province":"ON",
    "sg:tags":[
        "shop"
    ],
    "wof:name":"B A & M Trading Ltd",
    "wof:placetype":"venue"
},
  "geometry": {"coordinates":[-79.348755,43.688763],"type":"Point"}
}