{
  "type": "Feature",
  "properties": {
    "addr:full":"53 King St E Hamilton ON L8N 1A5",
    "addr:housenumber":"53",
    "addr:postcode":"l8n 1a5",
    "addr:street":"King St E",
    "iso:country":"CA",
    "sg:address":"53 King St E",
    "sg:city":"Hamilton",
    "sg:classifiers":[
        {
            "category":"Food & Beverages",
            "subcategory":"Groceries & Convenience Stores",
            "type":"Retail Goods"
        }
    ],
    "sg:phone":"+1 905 528 8116",
    "sg:postcode":"L8N 1A5",
    "sg:province":"ON",
    "sg:tags":[
        "grocer"
    ],
    "wof:name":"My Convenience Store",
    "wof:placetype":"venue"
},
  "geometry": {"coordinates":[-79.86735534669999,43.2562522888],"type":"Point"}
}