{
  "type": "Feature",
  "properties": {
    "addr:full":"Etobicoke ON M8Z 1N1",
    "addr:postcode":"m8z 1n1",
    "iso:country":"CA",
    "sg:city":"Etobicoke",
    "sg:classifiers":[
        {
            "category":"Manufacturing",
            "subcategory":"Food",
            "type":"Manufacturing & Wholesale Goods"
        }
    ],
    "sg:phone":"+1 416 255 1001",
    "sg:postcode":"M8Z 1N1",
    "sg:province":"ON",
    "sg:tags":[
        "beer",
        "ale",
        "brewer"
    ],
    "wof:name":"Brew Factory",
    "wof:placetype":"venue"
},
  "geometry": {"coordinates":[-79.505135,43.625637],"type":"Point"}
}