{
  "type": "Feature",
  "properties": {
    "addr:full":"155 Wyse Rd Dartmouth NS B3A 1M5",
    "addr:housenumber":"155",
    "addr:postcode":"b3a 1m5",
    "addr:street":"Wyse Rd",
    "iso:country":"CA",
    "sg:address":"155 Wyse Rd",
    "sg:city":"Dartmouth",
    "sg:classifiers":[
        {
            "category":"Health Services",
            "subcategory":"Doctor",
            "type":"Services"
        }
    ],
    "sg:phone":"+1 902 469 4999",
    "sg:postcode":"B3A 1M5",
    "sg:province":"NS",
    "sg:tags":[
        "physician",
        "surgeon"
    ],
    "wof:name":"Metro Medical Clinic",
    "wof:placetype":"venue"
},
  "geometry": {"coordinates":[-63.5793495178,44.670917511],"type":"Point"}
}