{
  "type": "Feature",
  "properties": {
    "addr:full":"130 Russell St S Sarnia ON N7T 3L1",
    "addr:housenumber":"130",
    "addr:postcode":"n7t 3l1",
    "addr:street":"Russell St S",
    "iso:country":"CA",
    "sg:address":"130 Russell St S",
    "sg:city":"Sarnia",
    "sg:classifiers":[
        {
            "category":"Personal",
            "subcategory":"Beauty Salon",
            "type":"Services"
        }
    ],
    "sg:phone":"+1 519 337 5893",
    "sg:postcode":"N7T 3L1",
    "sg:province":"ON",
    "wof:name":"90 Degrees",
    "wof:placetype":"venue"
},
  "geometry": {"coordinates":[-82.391457,42.969013],"type":"Point"}
}