{
  "type": "Feature",
  "properties": {
    "iso:country":"CA",
    "sg:address":"261 Regent St",
    "sg:city":"Sudbury",
    "sg:classifiers":[
        {
            "category":"Wholesale",
            "subcategory":"Hardware",
            "type":"Manufacturing & Wholesale Goods"
        }
    ],
    "sg:phone":"+1 705 673 1449",
    "sg:postcode":"P3C 4C6",
    "sg:province":"ON",
    "sg:tags":[
        "fastener"
    ],
    "wof:name":"Northfast Limited",
    "wof:placetype":"venue"
},
  "geometry": {"coordinates":[-81.0072402954,46.4869499207],"type":"Point"}
}