{
  "type": "Feature",
  "properties": {
    "iso:country":"CA",
    "sg:address":"332 Sheppard Ave E",
    "sg:city":"North York",
    "sg:classifiers":[
        {
            "category":"Banks & Credit Unions",
            "subcategory":"Investment Brokerage",
            "type":"Services"
        }
    ],
    "sg:phone":"+1 416 226 1505",
    "sg:postcode":"M2N 3B4",
    "sg:province":"ON",
    "sg:tags":[
        "loan",
        "real estate"
    ],
    "wof:name":"Northview Financial Svc Inc",
    "wof:placetype":"venue"
},
  "geometry": {"coordinates":[-79.39571380620001,43.7650032043],"type":"Point"}
}