{
  "type": "Feature",
  "properties": {
    "addr:full":"Red Deer AB T4N 1R3",
    "addr:postcode":"t4n 1r3",
    "iso:country":"CA",
    "sg:city":"Red Deer",
    "sg:classifiers":[
        {
            "category":"Professional",
            "subcategory":"Lawyer & Legal Services",
            "type":"Services"
        }
    ],
    "sg:phone":"+1 403 342 7715",
    "sg:postcode":"T4N 1R3",
    "sg:province":"AB",
    "sg:tags":[
        "attorney"
    ],
    "wof:name":"Flanagan Sully",
    "wof:placetype":"venue"
},
  "geometry": {"coordinates":[-113.80978399999999,52.265949],"type":"Point"}
}