{
  "type": "Feature",
  "properties": {
    "addr:full":"5720 Saint-Francois Ch Saint-Laurent QC H4S 1B4",
    "addr:housenumber":"5720",
    "addr:postcode":"h4s 1b4",
    "addr:street":"Saint-Francois Ch Saint-Laurent",
    "iso:country":"CA",
    "sg:address":"5720 Saint-Francois Ch",
    "sg:city":"Saint-Laurent",
    "sg:classifiers":[
        {
            "category":"Manufacturing",
            "subcategory":"Tools & Machinery",
            "type":"Manufacturing & Wholesale Goods"
        }
    ],
    "sg:phone":"+1 514 335 9126",
    "sg:postcode":"H4S 1B4",
    "sg:province":"QC",
    "sg:tags":[
        "machine",
        "screw",
        "product",
        "equipment"
    ],
    "wof:name":"Protomatik",
    "wof:placetype":"venue"
},
  "geometry": {"coordinates":[-73.73773956300001,45.4872589111],"type":"Point"}
}