{
  "type": "Feature",
  "properties": {
    "addr:full":"124 Main St E Shelburne ON L0N 1S0",
    "addr:housenumber":"124",
    "addr:postcode":"l0n 1s0",
    "addr:street":"Main St E",
    "iso:country":"CA",
    "sg:address":"124 Main St E",
    "sg:city":"Shelburne",
    "sg:classifiers":[
        {
            "category":"Travel",
            "subcategory":"Travel Agent",
            "type":"Entertainment"
        }
    ],
    "sg:phone":"+1 519 925 3080",
    "sg:postcode":"L0N 1S0",
    "sg:province":"ON",
    "sg:tags":[
        "agency",
        "bureau"
    ],
    "wof:name":"Carlson Wagonlit Travel",
    "wof:placetype":"venue"
},
  "geometry": {"coordinates":[-80.2034988403,44.0785484314],"type":"Point"}
}