{
  "type": "Feature",
  "properties": {
    "addr:full":"80 Rue Collard O Alma QC G8B 1M6",
    "addr:housenumber":"80",
    "addr:postcode":"g8b 1m6",
    "addr:street":"Rue Collard O",
    "iso:country":"CA",
    "sg:address":"80 Rue Collard O",
    "sg:city":"Alma",
    "sg:classifiers":[
        {
            "category":"Organizations",
            "subcategory":"Professional Association",
            "type":"Services"
        }
    ],
    "sg:phone":"+1 418 662 5040",
    "sg:postcode":"G8B 1M6",
    "sg:province":"QC",
    "wof:name":"Almacueil",
    "wof:placetype":"venue"
},
  "geometry": {"coordinates":[-71.64464599999999,48.545376],"type":"Point"}
}