{
  "type": "Feature",
  "properties": {
    "addr:full":"99 Main St N Alexandria ON K0C 1A0",
    "addr:housenumber":"99",
    "addr:postcode":"k0c 1a0",
    "addr:street":"Main St N",
    "iso:country":"CA",
    "sg:address":"99 Main St N",
    "sg:city":"Alexandria",
    "sg:classifiers":[
        {
            "category":"Food & Beverages",
            "subcategory":"Groceries & Convenience Stores",
            "type":"Retail Goods"
        }
    ],
    "sg:phone":"+1 613 525 1252",
    "sg:postcode":"K0C 1A0",
    "sg:province":"ON",
    "sg:tags":[
        "grocer"
    ],
    "wof:name":"Genuine Convenience Store",
    "wof:placetype":"venue"
},
  "geometry": {"coordinates":[-74.637833,45.312885],"type":"Point"}
}