{
  "type": "Feature",
  "properties": {
    "addr:full":"4726 Montrose Rd Niagara Falls ON L2H 1K3",
    "addr:housenumber":"4726",
    "addr:postcode":"l2h 1k3",
    "addr:street":"Montrose Rd",
    "iso:country":"CA",
    "sg:address":"4726 Montrose Rd",
    "sg:city":"Niagara Falls",
    "sg:classifiers":[
        {
            "category":"Recreation",
            "type":"Entertainment"
        }
    ],
    "sg:phone":"+1 905 374 3131",
    "sg:postcode":"L2H 1K3",
    "sg:province":"ON",
    "sg:tags":[
        "instruction",
        "gymnastic"
    ],
    "wof:name":"Quantum Niagara Gymnastics",
    "wof:placetype":"venue"
},
  "geometry": {"coordinates":[-79.12396200000001,43.104843],"type":"Point"}
}