{
  "type": "Feature",
  "properties": {
    "addr:full":"251 Sorauren Ave Toronto ON M6R 2G3",
    "addr:housenumber":"251",
    "addr:postcode":"m6r 2g3",
    "addr:street":"Sorauren Ave",
    "iso:country":"CA",
    "sg:address":"251 Sorauren Ave",
    "sg:city":"Toronto",
    "sg:classifiers":[
        {
            "category":"Manufacturing",
            "subcategory":"Tools & Machinery",
            "type":"Manufacturing & Wholesale Goods"
        }
    ],
    "sg:phone":"+1 416 516 3821",
    "sg:postcode":"M6R 2G3",
    "sg:province":"ON",
    "sg:tags":[
        "model",
        "maker"
    ],
    "wof:name":"Studio C",
    "wof:placetype":"venue"
},
  "geometry": {"coordinates":[-79.44358099999999,43.647106],"type":"Point"}
}