{
  "type": "Feature",
  "properties": {
    "addr:full":"132 58E Rue E Charlesbourg QC G1H 2E8",
    "addr:housenumber":"132",
    "addr:postcode":"g1h 2e8",
    "addr:street":"58E Rue E",
    "iso:country":"CA",
    "sg:address":"132 58E Rue E",
    "sg:city":"Charlesbourg",
    "sg:classifiers":[
        {
            "category":"Building & Trades",
            "subcategory":"Construction",
            "type":"Services"
        }
    ],
    "sg:phone":"+1 418 626 1340",
    "sg:postcode":"G1H 2E8",
    "sg:province":"QC",
    "sg:tags":[
        "excavating",
        "contractor"
    ],
    "wof:name":"Hamel Machineries Inc",
    "wof:placetype":"venue"
},
  "geometry": {"coordinates":[-71.251335144,46.8456459045],"type":"Point"}
}