{
  "type": "Feature",
  "properties": {
    "addr:full":"Langley BC V3A 8M8",
    "addr:postcode":"v3a 8m8",
    "iso:country":"CA",
    "sg:city":"Langley",
    "sg:classifiers":[
        {
            "category":"Government",
            "subcategory":"Office",
            "type":"Public Place"
        }
    ],
    "sg:phone":"+1 604 532 3693",
    "sg:postcode":"V3A 8M8",
    "sg:province":"BC",
    "sg:tags":[
        "village"
    ],
    "wof:name":"B C Members of the Legislative",
    "wof:placetype":"venue"
},
  "geometry": {"coordinates":[-122.651657,49.10767],"type":"Point"}
}