{
  "type": "Feature",
  "properties": {
    "addr:full":"2436 2 Ave NW Calgary AB T2N 0H4",
    "addr:housenumber":"2436",
    "addr:postcode":"t2n 0h4",
    "addr:street":"2 Ave Nw",
    "iso:country":"CA",
    "sg:address":"2436 2 Ave NW",
    "sg:city":"Calgary",
    "sg:classifiers":[
        {
            "category":"Restaurant",
            "type":"Food & Drink"
        }
    ],
    "sg:phone":"+1 403 270 8334",
    "sg:postcode":"T2N 0H4",
    "sg:province":"AB",
    "sg:tags":[
        "delicatessen"
    ],
    "wof:name":"Jans Meat & Delicatessen",
    "wof:placetype":"venue"
},
  "geometry": {"coordinates":[-114.116264343,51.0545921326],"type":"Point"}
}