{
  "type": "Feature",
  "properties": {
    "iso:country":"CA",
    "sg:city":"Greenfield Park",
    "sg:classifiers":[
        {
            "category":"Health Services",
            "subcategory":"Health Practitioner",
            "type":"Services"
        }
    ],
    "sg:phone":"+1 450 671 2686",
    "sg:postcode":"J4V 2N2",
    "sg:province":"QC",
    "sg:tags":[
        "acupuncture"
    ],
    "wof:name":"Acupuncture Celine Hamelin",
    "wof:placetype":"venue"
},
  "geometry": {"coordinates":[-73.483276,45.494598],"type":"Point"}
}