{
  "type": "Feature",
  "properties": {
    "addr:full":"46 Herriott St Perth ON K7H 1T2",
    "addr:housenumber":"46",
    "addr:postcode":"k7h 1t2",
    "addr:street":"Herriott St",
    "iso:country":"CA",
    "sg:address":"46 Herriott St",
    "sg:city":"Perth",
    "sg:classifiers":[
        {
            "category":"Personal",
            "subcategory":"Beauty Salon",
            "type":"Services"
        }
    ],
    "sg:phone":"+1 613 267 4728",
    "sg:postcode":"K7H 1T2",
    "sg:province":"ON",
    "wof:name":"Joanne's Hairstyling",
    "wof:placetype":"venue"
},
  "geometry": {"coordinates":[-76.25005299999999,44.899948],"type":"Point"}
}