{
  "type": "Feature",
  "properties": {
    "iso:country":"CA",
    "sg:address":"2600 Boul Laurier #2460",
    "sg:city":"Sainte-Foy",
    "sg:classifiers":[
        {
            "category":"Banks & Credit Unions",
            "subcategory":"Investment Brokerage",
            "type":"Services"
        }
    ],
    "sg:phone":"+1 418 657 6601",
    "sg:postcode":"G1V 4M6",
    "sg:province":"QC",
    "sg:tags":[
        "consultant",
        "planning",
        "financial"
    ],
    "wof:name":"Compagnie DE Gestion MD Ltee",
    "wof:placetype":"venue"
},
  "geometry": {"coordinates":[-71.281059,46.771248],"type":"Point"}
}