{
  "type": "Feature",
  "properties": {
    "iso:country":"CA",
    "sg:address":"3781 Rue Villeray",
    "sg:city":"Montreal",
    "sg:classifiers":[
        {
            "category":"Social Services",
            "subcategory":"Child Care",
            "type":"Services"
        }
    ],
    "sg:phone":"+1 514 593 5944",
    "sg:postcode":"H2A 1G5",
    "sg:province":"QC",
    "wof:name":"Garderie Royaume D'Aladin",
    "wof:placetype":"venue"
},
  "geometry": {"coordinates":[-73.59958648680001,45.5661201477],"type":"Point"}
}