{
  "type": "Feature",
  "properties": {
    "addr:full":"47 Queen's Park Cres E Toronto ON M5S 2C3",
    "addr:housenumber":"47",
    "addr:postcode":"m5s 2c3",
    "addr:street":"Queen'S Park Cres E",
    "iso:country":"CA",
    "sg:address":"47 Queen's Park Cres E",
    "sg:city":"Toronto",
    "sg:classifiers":[
        {
            "category":"Professional",
            "subcategory":"Management & Consulting",
            "type":"Services"
        }
    ],
    "sg:phone":"+1 416 928 2394",
    "sg:postcode":"M5S 2C3",
    "sg:province":"ON",
    "sg:tags":[
        "consultant",
        "business"
    ],
    "wof:name":"Nlp Canada Training Inc",
    "wof:placetype":"venue"
},
  "geometry": {"coordinates":[-79.38433074949999,43.6728820801],"type":"Point"}
}