{
  "type": "Feature",
  "properties": {
    "addr:full":"4041 Macleod Trail SW Calgary AB T2G 2R6",
    "addr:housenumber":"4041",
    "addr:postcode":"t2g 2r6",
    "addr:street":"Macleod Trail Sw",
    "iso:country":"CA",
    "sg:address":"4041 Macleod Trail SW",
    "sg:city":"Calgary",
    "sg:classifiers":[
        {
            "category":"Shopping",
            "subcategory":"Florist",
            "type":"Retail Goods"
        }
    ],
    "sg:phone":"+1 403 243 3388",
    "sg:postcode":"T2G 2R6",
    "sg:province":"AB",
    "wof:name":"Grower Direct",
    "wof:placetype":"venue"
},
  "geometry": {"coordinates":[-114.063393,51.018135],"type":"Point"}
}