{
  "type": "Feature",
  "properties": {
    "addr:full":"Abbotsford QC J0E 1A0",
    "addr:postcode":"j0e 1a0",
    "iso:country":"CA",
    "sg:city":"Abbotsford",
    "sg:classifiers":[
        {
            "category":"Manufacturing",
            "subcategory":"Furniture",
            "type":"Manufacturing & Wholesale Goods"
        }
    ],
    "sg:phone":"+1 450 379 2088",
    "sg:postcode":"J0E 1A0",
    "sg:province":"QC",
    "wof:name":"Concept Can-Bec Immobilier",
    "wof:placetype":"venue"
},
  "geometry": {"coordinates":[-72.864730835,45.4340705872],"type":"Point"}
}