{
  "type": "Feature",
  "properties": {
    "iso:country":"CA",
    "sg:address":"9815 Rue Lajeunesse",
    "sg:city":"Montreal",
    "sg:classifiers":[
        {
            "category":"Autos & Motor Vehicles",
            "subcategory":"Fuel & Gas Station",
            "type":"Retail Goods"
        }
    ],
    "sg:phone":"+1 514 382 7319",
    "sg:postcode":"H3L 2C9",
    "sg:province":"QC",
    "sg:tags":[
        "oil"
    ],
    "wof:name":"Ultramar",
    "wof:placetype":"venue"
},
  "geometry": {"coordinates":[-73.653427124,45.5509300232],"type":"Point"}
}