{
  "type": "Feature",
  "properties": {
    "addr:full":"14 Skyview Cres North York ON M2J 1B8",
    "addr:housenumber":"14",
    "addr:postcode":"m2j 1b8",
    "addr:street":"Skyview Cres",
    "iso:country":"CA",
    "sg:address":"14 Skyview Cres",
    "sg:city":"North York",
    "sg:classifiers":[
        {
            "category":"Manufacturing",
            "subcategory":"Printing",
            "type":"Manufacturing & Wholesale Goods"
        }
    ],
    "sg:phone":"+1 416 491 4349",
    "sg:postcode":"M2J 1B8",
    "sg:province":"ON",
    "sg:tags":[
        "publisher"
    ],
    "wof:name":"Mountain Rendezvous Publishing",
    "wof:placetype":"venue"
},
  "geometry": {"coordinates":[-79.34955600000001,43.768757],"type":"Point"}
}