{
  "type": "Feature",
  "properties": {
    "addr:full":"263 Second Ave Ottawa ON K1S 2H8",
    "addr:housenumber":"263",
    "addr:postcode":"k1s 2h8",
    "addr:street":"Second Ave",
    "iso:country":"CA",
    "sg:address":"263 Second Ave",
    "sg:city":"Ottawa",
    "sg:classifiers":[
        {
            "category":"Professional",
            "subcategory":"Management & Consulting",
            "type":"Services"
        }
    ],
    "sg:phone":"+1 613 238 3639",
    "sg:postcode":"K1S 2H8",
    "sg:province":"ON",
    "sg:tags":[
        "consultant",
        "educational"
    ],
    "wof:name":"Androcom Interactive Media",
    "wof:placetype":"venue"
},
  "geometry": {"coordinates":[-75.6936035156,45.4019012451],"type":"Point"}
}