{
  "type": "Feature",
  "properties": {
    "addr:full":"901 108th Ave W Tisdale SK S0E 1T0",
    "addr:housenumber":"901",
    "addr:postcode":"s0e 1t0",
    "addr:street":"108Th Ave W Tisdale",
    "iso:country":"CA",
    "sg:address":"901 108th Ave W",
    "sg:city":"Tisdale",
    "sg:classifiers":[
        {
            "category":"Health Services",
            "subcategory":"Clinic",
            "type":"Services"
        }
    ],
    "sg:phone":"+1 306 873 3100",
    "sg:postcode":"S0E 1T0",
    "sg:province":"SK",
    "wof:name":"Kelsey Trail Health Region",
    "wof:placetype":"venue"
},
  "geometry": {"coordinates":[-104.04426599999999,52.854744],"type":"Point"}
}