{
  "type": "Feature",
  "properties": {
    "addr:full":"264 Dundurn St S Hamilton ON L8P 4K9",
    "addr:housenumber":"264",
    "addr:postcode":"l8p 4k9",
    "addr:street":"Dundurn St S",
    "iso:country":"CA",
    "sg:address":"264 Dundurn St S",
    "sg:city":"Hamilton",
    "sg:classifiers":[
        {
            "category":"Food & Beverages",
            "subcategory":"Groceries & Convenience Stores",
            "type":"Retail Goods"
        }
    ],
    "sg:phone":"+1 905 525 6664",
    "sg:postcode":"L8P 4K9",
    "sg:province":"ON",
    "sg:tags":[
        "delicatessen"
    ],
    "wof:name":"Zarky's Fine Food on Dundurn",
    "wof:placetype":"venue"
},
  "geometry": {"coordinates":[-79.8916854858,43.2539176941],"type":"Point"}
}