{
  "type": "Feature",
  "properties": {
    "addr:full":"Sundre AB T0M 1X0",
    "addr:postcode":"t0m 1x0",
    "iso:country":"CA",
    "sg:city":"Sundre",
    "sg:classifiers":[
        {
            "category":"Health Services",
            "subcategory":"Doctor",
            "type":"Services"
        }
    ],
    "sg:phone":"+1 403 638 2424",
    "sg:postcode":"T0M 1X0",
    "sg:province":"AB",
    "sg:tags":[
        "physician",
        "surgeon"
    ],
    "wof:name":"Foolen, Carla MD",
    "wof:placetype":"venue"
},
  "geometry": {"coordinates":[-114.63723754900001,51.8075714111],"type":"Point"}
}