{
  "type": "Feature",
  "properties": {
    "iso:country":"CA",
    "sg:address":"5680 Boul Saint-Joseph",
    "sg:city":"Saint-Nicephore",
    "sg:classifiers":[
        {
            "category":"Retail",
            "subcategory":"Auto Repair",
            "type":"Services"
        }
    ],
    "sg:phone":"+1 819 472 1392",
    "sg:postcode":"J2A 3V9",
    "sg:province":"QC",
    "sg:tags":[
        "repairing",
        "automobile",
        "wrecker"
    ],
    "wof:name":"Mecanique Mobile Enrg",
    "wof:placetype":"venue"
},
  "geometry": {"coordinates":[-72.3930892944,45.8166999817],"type":"Point"}
}