{
  "type": "Feature",
  "properties": {
    "addr:full":"2400 Ch Sainte-Marie Mascouche QC J7K 1M5",
    "addr:postcode":"2400;j7k 1m5",
    "addr:street":"Ch Sainte-Marie",
    "iso:country":"CA",
    "sg:address":"2400 Ch Sainte-Marie",
    "sg:city":"Mascouche",
    "sg:classifiers":[
        {
            "category":"Home & Garden",
            "subcategory":"Household Appliances",
            "type":"Retail Goods"
        }
    ],
    "sg:phone":"+1 450 474 0312",
    "sg:postcode":"J7K 1M5",
    "sg:province":"QC",
    "wof:name":"Electro 2400 Enr",
    "wof:placetype":"venue"
},
  "geometry": {"coordinates":[-73.62204742430001,45.7539291382],"type":"Point"}
}