{
  "type": "Feature",
  "properties": {
    "iso:country":"CA",
    "sg:city":"York",
    "sg:classifiers":[
        {
            "category":"Professional",
            "subcategory":"Detective & Security Services",
            "type":"Services"
        }
    ],
    "sg:phone":"+1 416 787 1448",
    "sg:postcode":"M6E 2J7",
    "sg:province":"ON",
    "sg:tags":[
        "guard",
        "patrol"
    ],
    "wof:name":"Northwest Protection Svc",
    "wof:placetype":"venue"
},
  "geometry": {"coordinates":[-79.45337677000001,43.6949462891],"type":"Point"}
}