{
  "type": "Feature",
  "properties": {
    "addr:full":"462 13th St E Regina Beach SK S0G 4C0",
    "addr:housenumber":"462",
    "addr:postcode":"s0g 4c0",
    "addr:street":"13Th St E Regina Beach",
    "iso:country":"CA",
    "sg:address":"462 13th St E",
    "sg:city":"Regina Beach",
    "sg:classifiers":[
        {
            "category":"Building & Trades",
            "subcategory":"Construction",
            "type":"Services"
        }
    ],
    "sg:phone":"+1 306 729 2765",
    "sg:postcode":"S0G 4C0",
    "sg:province":"SK",
    "sg:tags":[
        "contractor",
        "general"
    ],
    "wof:name":"Bartlett Construction",
    "wof:placetype":"venue"
},
  "geometry": {"coordinates":[-104.97402954099999,50.7871360779],"type":"Point"}
}