{
  "type": "Feature",
  "properties": {
    "addr:full":"201 Rue Joseph-Carrier Vaudreuil-Dorion QC J7V 5V5",
    "addr:housenumber":"201",
    "addr:postcode":"j7v 5v5",
    "addr:street":"Rue Joseph-Carrier",
    "iso:country":"CA",
    "sg:address":"201 Rue Joseph-Carrier",
    "sg:city":"Vaudreuil-Dorion",
    "sg:classifiers":[
        {
            "category":"Wholesale",
            "subcategory":"Machinery & Supplies",
            "type":"Manufacturing & Wholesale Goods"
        }
    ],
    "sg:phone":"+1 450 424 5632",
    "sg:postcode":"J7V 5V5",
    "sg:province":"QC",
    "sg:tags":[
        "equipment",
        "material",
        "truck",
        "handling"
    ],
    "wof:name":"Kebec Expert Ltee",
    "wof:placetype":"venue"
},
  "geometry": {"coordinates":[-74.04568481450001,45.4083786011],"type":"Point"}
}