{
  "type": "Feature",
  "properties": {
    "addr:full":"6086 Rue Sherbrooke E Montreal QC H1N 1C1",
    "addr:housenumber":"6086",
    "addr:postcode":"h1n 1c1",
    "addr:street":"Rue Sherbrooke E",
    "iso:country":"CA",
    "sg:address":"6086 Rue Sherbrooke E",
    "sg:city":"Montreal",
    "sg:classifiers":[
        {
            "category":"Recreation",
            "type":"Entertainment"
        }
    ],
    "sg:phone":"+1 514 255 2922",
    "sg:postcode":"H1N 1C1",
    "sg:province":"QC",
    "sg:tags":[
        "auditorium",
        "rooms",
        "banquet",
        "hall"
    ],
    "wof:name":"Antique Salle DE Reception",
    "wof:placetype":"venue"
},
  "geometry": {"coordinates":[-73.5455093384,45.578250885],"type":"Point"}
}