{
  "type": "Feature",
  "properties": {
    "addr:full":"779 Rue DE Brouage Boucherville QC J4B 2E9",
    "addr:housenumber":"779",
    "addr:postcode":"j4b 2e9",
    "addr:street":"Rue De Brouage",
    "iso:country":"CA",
    "sg:address":"779 Rue DE Brouage",
    "sg:city":"Boucherville",
    "sg:classifiers":[
        {
            "category":"Building & Trades",
            "subcategory":"Construction",
            "type":"Services"
        }
    ],
    "sg:phone":"+1 450 449 2855",
    "sg:postcode":"J4B 2E9",
    "sg:province":"QC",
    "sg:tags":[
        "repairing",
        "remodeling",
        "contractor"
    ],
    "wof:name":"Renovation Jean Enr",
    "wof:placetype":"venue"
},
  "geometry": {"coordinates":[-73.450768,45.597332],"type":"Point"}
}