{
  "type": "Feature",
  "properties": {
    "addr:full":"Caledonia ON N3W 1M6",
    "addr:postcode":"n3w 1m6",
    "iso:country":"CA",
    "sg:city":"Caledonia",
    "sg:classifiers":[
        {
            "category":"Home & Garden",
            "subcategory":"Furniture",
            "type":"Retail Goods"
        }
    ],
    "sg:phone":"+1 905 765 4094",
    "sg:postcode":"N3W 1M6",
    "sg:province":"ON",
    "wof:name":"Applegate & James Country Furn",
    "wof:placetype":"venue"
},
  "geometry": {"coordinates":[-79.950729,43.073563],"type":"Point"}
}