{
  "type": "Feature",
  "properties": {
    "addr:full":"86 Wintemute St Fort Erie ON L2A 2P1",
    "addr:housenumber":"86",
    "addr:postcode":"l2a 2p1",
    "addr:street":"Wintemute St",
    "iso:country":"CA",
    "sg:address":"86 Wintemute St",
    "sg:city":"Fort Erie",
    "sg:classifiers":[
        {
            "category":"Manufacturing",
            "subcategory":"Retail Goods",
            "type":"Manufacturing & Wholesale Goods"
        }
    ],
    "sg:phone":"+1 905 871 3433",
    "sg:postcode":"L2A 2P1",
    "sg:province":"ON",
    "sg:tags":[
        "designer",
        "assembly",
        "fabricating"
    ],
    "wof:name":"Flextek Design",
    "wof:placetype":"venue"
},
  "geometry": {"coordinates":[-78.921722,42.925423],"type":"Point"}
}