{
  "type": "Feature",
  "properties": {
    "addr:full":"515 Snyder's Rd E Baden ON N3A 3L1",
    "addr:housenumber":"515",
    "addr:postcode":"n3a 3l1",
    "addr:street":"Snyder'S Rd E",
    "iso:country":"CA",
    "sg:address":"515 Snyder's Rd E",
    "sg:city":"Baden",
    "sg:classifiers":[
        {
            "category":"Building & Trades",
            "subcategory":"Landscaping Services",
            "type":"Services"
        }
    ],
    "sg:phone":"+1 519 634 5559",
    "sg:postcode":"N3A 3L1",
    "sg:province":"ON",
    "sg:tags":[
        "lawn",
        "maintenance",
        "grounds"
    ],
    "wof:name":"Greensleeve Maintenance Ltd",
    "wof:placetype":"venue"
},
  "geometry": {"coordinates":[-80.66796875,43.4029083252],"type":"Point"}
}