{
  "type": "Feature",
  "properties": {
    "iso:country":"CA",
    "sg:address":"1005 Tudor Glen",
    "sg:city":"St Albert",
    "sg:classifiers":[
        {
            "category":"Retail",
            "subcategory":"Veterinary Services",
            "type":"Services"
        }
    ],
    "sg:phone":"+1 780 458 6051",
    "sg:postcode":"T8N 3V4",
    "sg:province":"AB",
    "sg:tags":[
        "veterinarian"
    ],
    "wof:name":"Tudor Glen Veterinary Hospital",
    "wof:placetype":"venue"
},
  "geometry": {"coordinates":[-113.627349853,53.633518219],"type":"Point"}
}