{
  "type": "Feature",
  "properties": {
    "addr:full":"104 Chatham St S Blenheim ON N0P 1A0",
    "addr:housenumber":"104",
    "addr:postcode":"n0p 1a0",
    "addr:street":"Chatham St S",
    "iso:country":"CA",
    "sg:address":"104 Chatham St S",
    "sg:city":"Blenheim",
    "sg:classifiers":[
        {
            "category":"Shopping",
            "subcategory":"Discount & Variety Stores",
            "type":"Retail Goods"
        }
    ],
    "sg:phone":"+1 519 676 4772",
    "sg:postcode":"N0P 1A0",
    "sg:province":"ON",
    "wof:name":"Han's Mini Mart",
    "wof:placetype":"venue"
},
  "geometry": {"coordinates":[-81.993942,42.333794],"type":"Point"}
}