{
  "type": "Feature",
  "properties": {
    "addr:full":"5214 50 St Cold Lake AB T9M 1C9",
    "addr:housenumber":"5214",
    "addr:postcode":"t9m 1c9",
    "addr:street":"50 St",
    "iso:country":"CA",
    "sg:address":"5214 50 St",
    "sg:city":"Cold Lake",
    "sg:classifiers":[
        {
            "category":"Home & Garden",
            "subcategory":"Home Furnishings",
            "type":"Retail Goods"
        }
    ],
    "sg:phone":"+1 780 594 5200",
    "sg:postcode":"T9M 1C9",
    "sg:province":"AB",
    "sg:tags":[
        "quilting"
    ],
    "wof:name":"Quilted Gems & Treasures",
    "wof:placetype":"venue"
},
  "geometry": {"coordinates":[-110.205887,54.416412],"type":"Point"}
}