{
  "type": "Feature",
  "properties": {
    "addr:full":"650 Spadina Ave Toronto ON M5S 2H7",
    "addr:housenumber":"650",
    "addr:postcode":"m5s 2h7",
    "addr:street":"Spadina Ave",
    "iso:country":"CA",
    "sg:address":"650 Spadina Ave",
    "sg:city":"Toronto",
    "sg:classifiers":[
        {
            "category":"Restaurant",
            "type":"Food & Drink"
        }
    ],
    "sg:phone":"+1 416 323 3663",
    "sg:postcode":"M5S 2H7",
    "sg:province":"ON",
    "wof:name":"B B Ques",
    "wof:placetype":"venue"
},
  "geometry": {"coordinates":[-79.4024810791,43.6632270813],"type":"Point"}
}