{
  "type": "Feature",
  "properties": {
    "addr:full":"834 Fielden Ave Port Colborne ON L3K 6B7",
    "addr:housenumber":"834",
    "addr:postcode":"l3k 6b7",
    "addr:street":"Fielden Ave",
    "iso:country":"CA",
    "sg:address":"834 Fielden Ave",
    "sg:city":"Port Colborne",
    "sg:classifiers":[
        {
            "category":"Wholesale",
            "subcategory":"Electrical",
            "type":"Manufacturing & Wholesale Goods"
        }
    ],
    "sg:phone":"+1 905 834 0931",
    "sg:postcode":"L3K 6B7",
    "sg:province":"ON",
    "sg:tags":[
        "alarm",
        "burglar",
        "system"
    ],
    "wof:name":"Pace Security Group Ltd",
    "wof:placetype":"venue"
},
  "geometry": {"coordinates":[-79.25711099999999,42.904705],"type":"Point"}
}