{
  "type": "Feature",
  "properties": {
    "addr:full":"123 Commerce Valley Dr E Thornhill ON L3T 7W8",
    "addr:housenumber":"123",
    "addr:postcode":"l3t 7w8",
    "addr:street":"Commerce Valley Dr E",
    "iso:country":"CA",
    "sg:address":"123 Commerce Valley Dr E",
    "sg:city":"Thornhill",
    "sg:classifiers":[
        {
            "category":"Insurance",
            "subcategory":"Insurance Agent",
            "type":"Services"
        }
    ],
    "sg:phone":"+1 905 882 1088",
    "sg:postcode":"L3T 7W8",
    "sg:province":"ON",
    "wof:name":"Allen Wong Assoc Insurance",
    "wof:placetype":"venue"
},
  "geometry": {"coordinates":[-79.37507600000001,43.841637],"type":"Point"}
}