{
  "type": "Feature",
  "properties": {
    "addr:full":"1054 Centre St Thornhill ON L4J 8E5",
    "addr:housenumber":"1054",
    "addr:postcode":"l4j 8e5",
    "addr:street":"Centre St",
    "iso:country":"CA",
    "sg:address":"1054 Centre St",
    "sg:city":"Thornhill",
    "sg:classifiers":[
        {
            "category":"Cinema",
            "subcategory":"Movie Rental",
            "type":"Entertainment"
        }
    ],
    "sg:phone":"+1 905 731 6076",
    "sg:postcode":"L4J 8E5",
    "sg:province":"ON",
    "sg:tags":[
        "leasing",
        "video",
        "disc",
        "tape"
    ],
    "wof:name":"Rogers Video",
    "wof:placetype":"venue"
},
  "geometry": {"coordinates":[-79.45965576170001,43.8090133667],"type":"Point"}
}