{
  "type": "Feature",
  "properties": {
    "addr:full":"10003 110 Ave # 350 Fort St John BC V1J 6M7",
    "addr:housenumber":"10003",
    "addr:postcode":"v1j 6m7",
    "addr:street":"110 Ave # 350",
    "iso:country":"CA",
    "sg:address":"10003 110 Ave # 350",
    "sg:city":"Fort St John",
    "sg:classifiers":[
        {
            "category":"Government",
            "subcategory":"Office",
            "type":"Public Place"
        }
    ],
    "sg:phone":"+1 250 787 3240",
    "sg:postcode":"V1J 6M7",
    "sg:province":"BC",
    "wof:name":"BC Agriculture",
    "wof:placetype":"venue"
},
  "geometry": {"coordinates":[-120.847862244,56.255115509],"type":"Point"}
}