{
  "type": "Feature",
  "properties": {
    "iso:country":"CA",
    "sg:address":"1151 Rue Du Dominion",
    "sg:city":"Sherbrooke",
    "sg:classifiers":[
        {
            "category":"Personal",
            "subcategory":"Beauty Salon",
            "type":"Services"
        }
    ],
    "sg:phone":"+1 819 564 1555",
    "sg:postcode":"J1H 1C9",
    "sg:province":"QC",
    "wof:name":"Coiff'Allures",
    "wof:placetype":"venue"
},
  "geometry": {"coordinates":[-71.9061050415,45.4067726135],"type":"Point"}
}