{
  "type": "Feature",
  "properties": {
    "addr:full":"1881 Rue Principale Saint-Norbert QC J0K 3C0",
    "addr:housenumber":"1881",
    "addr:postcode":"j0k 3c0",
    "addr:street":"Rue Principale",
    "iso:country":"CA",
    "sg:address":"1881 Rue Principale",
    "sg:city":"Saint-Norbert",
    "sg:classifiers":[
        {
            "category":"Autos & Motor Vehicles",
            "subcategory":"Automobile Sales",
            "type":"Retail Goods"
        }
    ],
    "sg:phone":"+1 450 836 3783",
    "sg:postcode":"J0K 3C0",
    "sg:province":"QC",
    "sg:tags":[
        "car",
        "dealer"
    ],
    "wof:name":"Rejean Laporte & Fils Autos",
    "wof:placetype":"venue"
},
  "geometry": {"coordinates":[-73.3136291504,46.1679763794],"type":"Point"}
}