{
  "type": "Feature",
  "properties": {
    "addr:full":"201 Rue Des Sources Saint-Felix-DE-Valois QC J0K 2M0",
    "addr:housenumber":"201",
    "addr:postcode":"j0k 2m0",
    "addr:street":"Rue Des Sources",
    "iso:country":"CA",
    "sg:address":"201 Rue Des Sources",
    "sg:city":"Saint-Felix-DE-Valois",
    "sg:classifiers":[
        {
            "category":"Travel",
            "subcategory":"Campground",
            "type":"Entertainment"
        }
    ],
    "sg:phone":"+1 450 889 4638",
    "sg:postcode":"J0K 2M0",
    "sg:province":"QC",
    "wof:name":"Camping Le Petit Bonheur Inc",
    "wof:placetype":"venue"
},
  "geometry": {"coordinates":[-73.430206,46.128708],"type":"Point"}
}