{
  "type": "Feature",
  "properties": {
    "addr:full":"94 Glenholme Ave Toronto ON M6H 3B1",
    "addr:housenumber":"94",
    "addr:postcode":"m6h 3b1",
    "addr:street":"Glenholme Ave",
    "iso:country":"CA",
    "sg:address":"94 Glenholme Ave",
    "sg:city":"Toronto",
    "sg:classifiers":[
        {
            "category":"Building & Trades",
            "subcategory":"Construction",
            "type":"Services"
        }
    ],
    "sg:phone":"+1 416 658 5660",
    "sg:postcode":"M6H 3B1",
    "sg:province":"ON",
    "sg:tags":[
        "general",
        "contractor"
    ],
    "wof:name":"Comm Interior Alternations",
    "wof:placetype":"venue"
},
  "geometry": {"coordinates":[-79.43877410890001,43.6784858704],"type":"Point"}
}