{
  "type": "Feature",
  "properties": {
    "addr:full":"444 Broad St Regina SK S4R 1X3",
    "addr:housenumber":"444",
    "addr:postcode":"s4r 1x3",
    "addr:street":"Broad St",
    "iso:country":"CA",
    "sg:address":"444 Broad St",
    "sg:city":"Regina",
    "sg:classifiers":[
        {
            "category":"Recreation",
            "type":"Entertainment"
        }
    ],
    "sg:phone":"+1 306 777 7384",
    "sg:postcode":"S4R 1X3",
    "sg:province":"SK",
    "sg:tags":[
        "skating",
        "rink"
    ],
    "wof:name":"Jack W Staples Arena",
    "wof:placetype":"venue"
},
  "geometry": {"coordinates":[-104.60675000000001,50.471813],"type":"Point"}
}