{
  "type": "Feature",
  "properties": {
    "addr:full":"148 Main St Yarmouth NS B5A 1B8",
    "addr:housenumber":"148",
    "addr:postcode":"b5a 1b8",
    "addr:street":"Main St",
    "iso:country":"CA",
    "sg:address":"148 Main St",
    "sg:city":"Yarmouth",
    "sg:classifiers":[
        {
            "category":"Wholesale",
            "subcategory":"Meat",
            "type":"Manufacturing & Wholesale Goods"
        }
    ],
    "sg:phone":"+1 902 742 2685",
    "sg:postcode":"B5A 1B8",
    "sg:province":"NS",
    "sg:tags":[
        "butchering"
    ],
    "wof:name":"Emin's Meat Market",
    "wof:placetype":"venue"
},
  "geometry": {"coordinates":[-66.1222076416,43.8262367249],"type":"Point"}
}