{
  "type": "Feature",
  "properties": {
    "addr:full":"Auto Rd Kaministiquia ON P0T 1X0",
    "addr:postcode":"p0t 1x0",
    "addr:street":"Auto Rd",
    "iso:country":"CA",
    "sg:address":"Auto Rd",
    "sg:city":"Kaministiquia",
    "sg:classifiers":[
        {
            "category":"Wholesale",
            "subcategory":"Machinery & Supplies",
            "type":"Manufacturing & Wholesale Goods"
        }
    ],
    "sg:phone":"+1 807 933 4097",
    "sg:postcode":"P0T 1X0",
    "sg:province":"ON",
    "sg:tags":[
        "contractor"
    ],
    "wof:name":"Dan's Equipment Svc",
    "wof:placetype":"venue"
},
  "geometry": {"coordinates":[-89.6157,48.532066],"type":"Point"}
}