{
  "type": "Feature",
  "properties": {
    "addr:full":"661 Mountain Rd Moncton NB E1C 2P4",
    "addr:housenumber":"661",
    "addr:postcode":"e1c 2p4",
    "addr:street":"Mountain Rd",
    "iso:country":"CA",
    "sg:address":"661 Mountain Rd",
    "sg:city":"Moncton",
    "sg:classifiers":[
        {
            "category":"Professional",
            "subcategory":"Accounting & Tax Preparation",
            "type":"Services"
        }
    ],
    "sg:phone":"+1 506 857 2290",
    "sg:postcode":"E1C 2P4",
    "sg:province":"NB",
    "sg:tags":[
        "accountant"
    ],
    "wof:name":"Paul L Bourque & Assoc",
    "wof:placetype":"venue"
},
  "geometry": {"coordinates":[-64.802094,46.098942],"type":"Point"}
}