{
  "type": "Feature",
  "properties": {
    "addr:full":"1442 County Home Rd Waterville NS B0P 1V0",
    "addr:housenumber":"1442",
    "addr:postcode":"b0p 1v0",
    "addr:street":"County Home Rd",
    "iso:country":"CA",
    "sg:address":"1442 County Home Rd",
    "sg:city":"Waterville",
    "sg:classifiers":[
        {
            "category":"Professional",
            "subcategory":"Management & Consulting",
            "type":"Services"
        }
    ],
    "sg:phone":"+1 902 538 8071",
    "sg:postcode":"B0P 1V0",
    "sg:province":"NS",
    "sg:tags":[
        "correctional",
        "government"
    ],
    "wof:name":"Nova Scotia Youth Ctr",
    "wof:placetype":"venue"
},
  "geometry": {"coordinates":[-64.67743682859999,45.0482063293],"type":"Point"}
}