{
  "type": "Feature",
  "properties": {
    "addr:full":"Gloucester ON K1J 9J2",
    "addr:postcode":"k1j 9j2",
    "iso:country":"CA",
    "sg:city":"Gloucester",
    "sg:classifiers":[
        {
            "category":"Health Services",
            "subcategory":"Clinic",
            "type":"Services"
        }
    ],
    "sg:phone":"+1 613 744 7909",
    "sg:postcode":"K1J 9J2",
    "sg:province":"ON",
    "sg:tags":[
        "aid",
        "first",
        "supply"
    ],
    "wof:name":"Sos Emergency Response Tech",
    "wof:placetype":"venue"
},
  "geometry": {"coordinates":[-75.58419000000001,45.456493],"type":"Point"}
}