{
  "type": "Feature",
  "properties": {
    "addr:full":"10950 119 St NW Edmonton AB T5H 3P5",
    "addr:housenumber":"10950",
    "addr:postcode":"t5h 3p5",
    "addr:street":"119 St Nw",
    "iso:country":"CA",
    "sg:address":"10950 119 St NW",
    "sg:city":"Edmonton",
    "sg:classifiers":[
        {
            "category":"Professional",
            "subcategory":"Engineering",
            "type":"Services"
        }
    ],
    "sg:phone":"+1 780 452 1800",
    "sg:postcode":"T5H 3P5",
    "sg:province":"AB",
    "sg:tags":[
        "engineer"
    ],
    "wof:name":"Hemisphere Engineering Inc",
    "wof:placetype":"venue"
},
  "geometry": {"coordinates":[-113.52722199999999,53.556416],"type":"Point"}
}