{
  "type": "Feature",
  "properties": {
    "addr:full":"Plympton NS B0W 2R0",
    "addr:postcode":"b0w 2r0",
    "iso:country":"CA",
    "sg:city":"Plympton",
    "sg:classifiers":[
        {
            "category":"Food & Beverages",
            "subcategory":"Groceries & Convenience Stores",
            "type":"Retail Goods"
        }
    ],
    "sg:phone":"+1 902 837 7132",
    "sg:postcode":"B0W 2R0",
    "sg:province":"NS",
    "sg:tags":[
        "grocer"
    ],
    "wof:name":"V&J Kwik-Way",
    "wof:placetype":"venue"
},
  "geometry": {"coordinates":[-65.9168014526,44.5046386719],"type":"Point"}
}