{
  "type": "Feature",
  "properties": {
    "iso:country":"CA",
    "sg:city":"Surrey",
    "sg:classifiers":[
        {
            "category":"Real Estate",
            "subcategory":"Real Estate Agent",
            "type":"Services"
        }
    ],
    "sg:phone":"+1 604 583 2000",
    "sg:postcode":"V3R 0N9",
    "sg:province":"BC",
    "wof:name":"Re-Max 2000",
    "wof:placetype":"venue"
},
  "geometry": {"coordinates":[-122.803009033,49.1844177246],"type":"Point"}
}