{
  "type": "Feature",
  "properties": {
    "addr:full":"42 Rue Saint-Antoine Loretteville QC G2B 1L7",
    "addr:housenumber":"42",
    "addr:postcode":"g2b 1l7",
    "addr:street":"Rue Saint-Antoine",
    "iso:country":"CA",
    "sg:address":"42 Rue Saint-Antoine",
    "sg:city":"Loretteville",
    "sg:classifiers":[
        {
            "category":"Communications",
            "subcategory":"Film & Video Production",
            "type":"Services"
        }
    ],
    "sg:phone":"+1 418 847 4488",
    "sg:postcode":"G2B 1L7",
    "sg:province":"QC",
    "sg:tags":[
        "motion",
        "picture"
    ],
    "wof:name":"Distributors Netima Ltee",
    "wof:placetype":"venue"
},
  "geometry": {"coordinates":[-71.346321106,46.8551139832],"type":"Point"}
}