{
  "type": "Feature",
  "properties": {
    "addr:full":"9950 Av DE London Montreal-Nord QC H1H 4H1",
    "addr:housenumber":"9950",
    "addr:postcode":"h1h 4h1",
    "addr:street":"Av De London",
    "iso:country":"CA",
    "sg:address":"9950 Av DE London",
    "sg:city":"Montreal-Nord",
    "sg:classifiers":[
        {
            "category":"Manufacturing",
            "subcategory":"Apparel",
            "type":"Manufacturing & Wholesale Goods"
        }
    ],
    "sg:phone":"+1 514 277 8184",
    "sg:postcode":"H1H 4H1",
    "sg:province":"QC",
    "sg:tags":[
        "sewing",
        "contractor"
    ],
    "wof:name":"Mode Jfk Inc",
    "wof:placetype":"venue"
},
  "geometry": {"coordinates":[-73.63243900000001,45.581932],"type":"Point"}
}