{
  "type": "Feature",
  "properties": {
    "iso:country":"CA",
    "sg:address":"14 Dalhousie St",
    "sg:city":"Brantford",
    "sg:classifiers":[
        {
            "category":"Shopping",
            "subcategory":"Gifts & Souvenirs",
            "type":"Retail Goods"
        }
    ],
    "sg:phone":"+1 519 751 4333",
    "sg:postcode":"N3T 2H7",
    "sg:province":"ON",
    "sg:tags":[
        "antique",
        "shop"
    ],
    "wof:name":"Grieve's Mercantile",
    "wof:placetype":"venue"
},
  "geometry": {"coordinates":[-80.268005,43.13924],"type":"Point"}
}