{
  "type": "Feature",
  "properties": {
    "addr:full":"1526 19E Rue Saint-Come-Liniere QC G0M 1J0",
    "addr:housenumber":"1526",
    "addr:postcode":"g0m 1j0",
    "addr:street":"19E Rue Saint-Come-Liniere",
    "iso:country":"CA",
    "sg:address":"1526 19E Rue",
    "sg:city":"Saint-Come-Liniere",
    "sg:classifiers":[
        {
            "category":"Education",
            "subcategory":"School",
            "type":"Public Place"
        }
    ],
    "sg:phone":"+1 418 685 3181",
    "sg:postcode":"G0M 1J0",
    "sg:province":"QC",
    "wof:name":"Centre Mole",
    "wof:placetype":"venue"
},
  "geometry": {"coordinates":[-70.52057600000001,46.0611],"type":"Point"}
}