{
  "type": "Feature",
  "properties": {
    "addr:full":"Trois-Pistoles QC G0L 4K0",
    "addr:postcode":"g0l 4k0",
    "iso:country":"CA",
    "sg:city":"Trois-Pistoles",
    "sg:classifiers":[
        {
            "category":"Education",
            "subcategory":"School",
            "type":"Public Place"
        }
    ],
    "sg:phone":"+1 418 851 3341",
    "sg:postcode":"G0L 4K0",
    "sg:province":"QC",
    "wof:name":"Commission Scolaire-Basques",
    "wof:placetype":"venue"
},
  "geometry": {"coordinates":[-69.17487335209999,48.1250190735],"type":"Point"}
}