{
  "type": "Feature",
  "properties": {
    "iso:country":"CA",
    "sg:city":"North Vancouver",
    "sg:classifiers":[
        {
            "category":"Restaurant",
            "type":"Food & Drink"
        }
    ],
    "sg:phone":"+1 604 998 6500",
    "sg:postcode":"V7P 1B7",
    "sg:province":"BC",
    "wof:name":"Milestone's Restaurants",
    "wof:placetype":"venue"
},
  "geometry": {"coordinates":[-123.11965942400001,49.3175315857],"type":"Point"}
}