{
  "type": "Feature",
  "properties": {
    "addr:full":"13 Confederation Dr Niagara on the Lake ON L0S 1J0",
    "addr:housenumber":"13",
    "addr:postcode":"l0s 1j0",
    "addr:street":"Confederation Dr;On",
    "iso:country":"CA",
    "sg:address":"13 Confederation Dr",
    "sg:city":"Niagara on the Lake",
    "sg:classifiers":[
        {
            "category":"Shopping",
            "subcategory":"Computers & Home Electronics",
            "type":"Retail Goods"
        }
    ],
    "sg:phone":"+1 905 468 1719",
    "sg:postcode":"L0S 1J0",
    "sg:province":"ON",
    "sg:tags":[
        "software"
    ],
    "wof:name":"Mac Sween & Assoc",
    "wof:placetype":"venue"
},
  "geometry": {"coordinates":[-79.093987,43.248024],"type":"Point"}
}