{
  "type": "Feature",
  "properties": {
    "iso:country":"CA",
    "sg:address":"Hwy 3",
    "sg:city":"Keremeos",
    "sg:classifiers":[
        {
            "category":"Wholesale",
            "subcategory":"Auto Parts",
            "type":"Manufacturing & Wholesale Goods"
        }
    ],
    "sg:phone":"+1 250 499 2226",
    "sg:postcode":"V0X 1N0",
    "sg:province":"BC",
    "sg:tags":[
        "equipment",
        "truck"
    ],
    "wof:name":"Mantle Truck & Equipment",
    "wof:placetype":"venue"
},
  "geometry": {"coordinates":[-119.830505371,49.2051963806],"type":"Point"}
}