{
  "type": "Feature",
  "properties": {
    "addr:full":"Hull QC J8Y 1J5",
    "addr:postcode":"j8y 1j5",
    "iso:country":"CA",
    "sg:city":"Hull",
    "sg:classifiers":[
        {
            "category":"Organizations",
            "subcategory":"Professional Association",
            "type":"Services"
        }
    ],
    "sg:phone":"+1 819 776 5506",
    "sg:postcode":"J8Y 1J5",
    "sg:province":"QC",
    "wof:name":"Syndicat DE L'Enseignement",
    "wof:placetype":"venue"
},
  "geometry": {"coordinates":[-75.7104797363,45.4278488159],"type":"Point"}
}