{
  "type": "Feature",
  "properties": {
    "addr:full":"21 Quarry Rd #202 Waubaushene ON L0K 2C0",
    "addr:housenumber":"21",
    "addr:postcode":"l0k 2c0",
    "addr:street":"Quarry Rd # 202",
    "iso:country":"CA",
    "sg:address":"21 Quarry Rd #202",
    "sg:city":"Waubaushene",
    "sg:classifiers":[
        {
            "category":"Autos & Motor Vehicles",
            "subcategory":"Fuel & Gas Station",
            "type":"Retail Goods"
        }
    ],
    "sg:phone":"+1 705 538 2900",
    "sg:postcode":"L0K 2C0",
    "sg:province":"ON",
    "sg:tags":[
        "oil",
        "truck",
        "stops",
        "plaza"
    ],
    "wof:name":"Waubashene Auto & Truck Stop",
    "wof:placetype":"venue"
},
  "geometry": {"coordinates":[-79.71072387700001,44.754119873],"type":"Point"}
}