{
  "type": "Feature",
  "properties": {
    "addr:full":"129 2nd Ave Dodsland SK S0L 0V0",
    "addr:housenumber":"129",
    "addr:postcode":"s0l 0v0",
    "addr:street":"2Nd Ave",
    "iso:country":"CA",
    "sg:address":"129 2nd Ave",
    "sg:city":"Dodsland",
    "sg:classifiers":[
        {
            "category":"Education",
            "subcategory":"Library",
            "type":"Public Place"
        }
    ],
    "sg:phone":"+1 306 356 2180",
    "sg:postcode":"S0L 0V0",
    "sg:province":"SK",
    "wof:name":"Library-Dodsland",
    "wof:placetype":"venue"
},
  "geometry": {"coordinates":[-108.839256287,51.7998313904],"type":"Point"}
}