{
  "type": "Feature",
  "properties": {
    "addr:full":"Etobicoke ON M9W 6H9",
    "addr:postcode":"m9w 6h9",
    "iso:country":"CA",
    "sg:city":"Etobicoke",
    "sg:classifiers":[
        {
            "category":"Wholesale",
            "subcategory":"Machinery & Supplies",
            "type":"Manufacturing & Wholesale Goods"
        }
    ],
    "sg:phone":"+1 416 675 2442",
    "sg:postcode":"M9W 6H9",
    "sg:province":"ON",
    "sg:tags":[
        "concrete"
    ],
    "wof:name":"Concrete Depot Inc",
    "wof:placetype":"venue"
},
  "geometry": {"coordinates":[-79.619659,43.754066],"type":"Point"}
}