{
  "type": "Feature",
  "properties": {
    "addr:full":"370 Frederick St Kitchener ON N2H 2P3",
    "addr:housenumber":"370",
    "addr:postcode":"n2h 2p3",
    "addr:street":"Frederick St",
    "iso:country":"CA",
    "sg:address":"370 Frederick St",
    "sg:city":"Kitchener",
    "sg:classifiers":[
        {
            "category":"Real Estate",
            "subcategory":"Developer",
            "type":"Services"
        }
    ],
    "sg:phone":"+1 519 578 1112",
    "sg:postcode":"N2H 2P3",
    "sg:province":"ON",
    "sg:tags":[
        "company",
        "land"
    ],
    "wof:name":"Clair Hills Developments Inc",
    "wof:placetype":"venue"
},
  "geometry": {"coordinates":[-80.47486114500001,43.4574394226],"type":"Point"}
}