{
  "type": "Feature",
  "properties": {
    "addr:full":"17771 98A Ave NW Edmonton AB T5T 5W8",
    "addr:housenumber":"17771",
    "addr:postcode":"t5t 5w8",
    "addr:street":"98A Ave Nw",
    "iso:country":"CA",
    "sg:address":"17771 98A Ave NW",
    "sg:city":"Edmonton",
    "sg:classifiers":[
        {
            "category":"Retail",
            "subcategory":"Auto Repair",
            "type":"Services"
        }
    ],
    "sg:phone":"+1 780 483 2281",
    "sg:postcode":"T5T 5W8",
    "sg:province":"AB",
    "sg:tags":[
        "automobile",
        "lubrication"
    ],
    "wof:name":"Lubex Service Ctr",
    "wof:placetype":"venue"
},
  "geometry": {"coordinates":[-113.627845764,53.5342521667],"type":"Point"}
}