{
  "type": "Feature",
  "properties": {
    "addr:full":"393 York Rd Niagara on the Lake ON L0S 1J0",
    "addr:housenumber":"393",
    "addr:postcode":"l0s 1j0",
    "addr:street":"York Rd;On",
    "iso:country":"CA",
    "sg:address":"393 York Rd",
    "sg:city":"Niagara on the Lake",
    "sg:classifiers":[
        {
            "category":"Shopping",
            "type":"Retail Goods"
        }
    ],
    "sg:phone":"+1 905 685 6666",
    "sg:postcode":"L0S 1J0",
    "sg:province":"ON",
    "sg:tags":[
        "cosmetic",
        "perfume"
    ],
    "wof:name":"French Perfume Factory",
    "wof:placetype":"venue"
},
  "geometry": {"coordinates":[-79.168251,43.159992],"type":"Point"}
}