{
  "type": "Feature",
  "properties": {
    "addr:full":"798 4E Rue E LA Guadeloupe QC G0M 1G0",
    "addr:housenumber":"798",
    "addr:postcode":"g0m 1g0",
    "addr:street":"4E Rue E",
    "iso:country":"CA",
    "sg:address":"798 4E Rue E",
    "sg:city":"LA Guadeloupe",
    "sg:classifiers":[
        {
            "category":"Building & Trades",
            "subcategory":"Construction",
            "type":"Services"
        }
    ],
    "sg:phone":"+1 418 459 6302",
    "sg:postcode":"G0M 1G0",
    "sg:province":"QC",
    "sg:tags":[
        "contractor"
    ],
    "wof:name":"Renovation Jb Drouin Inc",
    "wof:placetype":"venue"
},
  "geometry": {"coordinates":[-70.92384300000001,45.964378],"type":"Point"}
}