{
  "type": "Feature",
  "properties": {
    "addr:full":"Campbell River BC V9W 2R1",
    "addr:postcode":"v9w 2r1",
    "iso:country":"CA",
    "sg:city":"Campbell River",
    "sg:classifiers":[
        {
            "category":"Organizations",
            "subcategory":"Professional Association",
            "type":"Services"
        }
    ],
    "sg:phone":"+1 250 287 3785",
    "sg:postcode":"V9W 2R1",
    "sg:province":"BC",
    "wof:name":"Discovery Coast Greenways Land",
    "wof:placetype":"venue"
},
  "geometry": {"coordinates":[-125.244445801,50.0254135132],"type":"Point"}
}