{
  "type": "Feature",
  "properties": {
    "addr:full":"Pointe-Claire QC H9R 1E9",
    "addr:postcode":"h9r 1e9",
    "iso:country":"CA",
    "sg:city":"Pointe-Claire",
    "sg:classifiers":[
        {
            "category":"Social Services",
            "subcategory":"Job Training",
            "type":"Services"
        }
    ],
    "sg:phone":"+1 514 426 9508",
    "sg:postcode":"H9R 1E9",
    "sg:province":"QC",
    "sg:tags":[
        "employment"
    ],
    "wof:name":"Trait D'Union",
    "wof:placetype":"venue"
},
  "geometry": {"coordinates":[-73.818466,45.461102],"type":"Point"}
}