{
  "type": "Feature",
  "properties": {
    "addr:full":"Sillery QC G1S 1G8",
    "addr:postcode":"g1s 1g8",
    "iso:country":"CA",
    "sg:city":"Sillery",
    "sg:classifiers":[
        {
            "category":"Freight",
            "type":"Transportation"
        }
    ],
    "sg:phone":"+1 418 681 5928",
    "sg:postcode":"G1S 1G8",
    "sg:province":"QC",
    "sg:tags":[
        "shop",
        "storage",
        "gift",
        "wine"
    ],
    "wof:name":"Maison DE Josee",
    "wof:placetype":"venue"
},
  "geometry": {"coordinates":[-71.24625399999999,46.78384],"type":"Point"}
}