{
  "type": "Feature",
  "properties": {
    "addr:full":"18 Mill St E Milverton ON N0K 1M0",
    "addr:housenumber":"18",
    "addr:postcode":"n0k 1m0",
    "addr:street":"Mill St;Milverton",
    "iso:country":"CA",
    "sg:address":"18 Mill St E",
    "sg:city":"Milverton",
    "sg:classifiers":[
        {
            "category":"Professional",
            "subcategory":"Lawyer & Legal Services",
            "type":"Services"
        }
    ],
    "sg:phone":"+1 519 595 8277",
    "sg:postcode":"N0K 1M0",
    "sg:province":"ON",
    "sg:tags":[
        "attorney"
    ],
    "wof:name":"Tar Bush, R Mark",
    "wof:placetype":"venue"
},
  "geometry": {"coordinates":[-80.920525,43.5653],"type":"Point"}
}