{
  "type": "Feature",
  "properties": {
    "addr:full":"3128 13th Ave Regina SK S4T 1P2",
    "addr:housenumber":"3128",
    "addr:postcode":"s4t 1p2",
    "addr:street":"13Th Ave",
    "iso:country":"CA",
    "sg:address":"3128 13th Ave",
    "sg:city":"Regina",
    "sg:classifiers":[
        {
            "category":"Shopping",
            "subcategory":"Used Merchandise",
            "type":"Retail Goods"
        }
    ],
    "sg:phone":"+1 306 525 1552",
    "sg:postcode":"S4T 1P2",
    "sg:province":"SK",
    "sg:tags":[
        "antique"
    ],
    "wof:name":"Cat & the Fiddle Antiques",
    "wof:placetype":"venue"
},
  "geometry": {"coordinates":[-104.62588501,50.4457321167],"type":"Point"}
}