{
  "type": "Feature",
  "properties": {
    "addr:full":"3706 53 St Athabasca AB T9S 1B2",
    "addr:housenumber":"3706",
    "addr:postcode":"t9s 1b2",
    "addr:street":"53 St",
    "iso:country":"CA",
    "sg:address":"3706 53 St",
    "sg:city":"Athabasca",
    "sg:classifiers":[
        {
            "category":"Mining & Drilling",
            "type":"Manufacturing & Wholesale Goods"
        }
    ],
    "sg:phone":"+1 780 675 9234",
    "sg:postcode":"T9S 1B2",
    "sg:province":"AB",
    "sg:tags":[
        "field",
        "oil",
        "electric",
        "contractor"
    ],
    "wof:name":"Pyramid Corp",
    "wof:placetype":"venue"
},
  "geometry": {"coordinates":[-113.296997,54.702236],"type":"Point"}
}