{
  "type": "Feature",
  "properties": {
    "addr:full":"480 Lambert Ave Nanaimo BC V9R 3N5",
    "addr:housenumber":"480",
    "addr:postcode":"v9r 3n5",
    "addr:street":"Lambert Ave",
    "iso:country":"CA",
    "sg:address":"480 Lambert Ave",
    "sg:city":"Nanaimo",
    "sg:classifiers":[
        {
            "category":"Building & Trades",
            "subcategory":"Construction",
            "type":"Services"
        }
    ],
    "sg:phone":"+1 250 754 6980",
    "sg:postcode":"V9R 3N5",
    "sg:province":"BC",
    "sg:tags":[
        "painter"
    ],
    "wof:name":"Semple Nairn Decorating",
    "wof:placetype":"venue"
},
  "geometry": {"coordinates":[-123.958045959,49.1558609009],"type":"Point"}
}