{
  "type": "Feature",
  "properties": {
    "addr:full":"2411 Westside Pl Kelowna BC V1Z 3T5",
    "addr:housenumber":"2411",
    "addr:postcode":"v1z 3t5",
    "addr:street":"Westside Pl",
    "iso:country":"CA",
    "sg:address":"2411 Westside Pl",
    "sg:city":"Kelowna",
    "sg:classifiers":[
        {
            "category":"Travel",
            "subcategory":"Campground",
            "type":"Entertainment"
        }
    ],
    "sg:phone":"+1 250 769 3676",
    "sg:postcode":"V1Z 3T5",
    "sg:province":"BC",
    "sg:tags":[
        "camp"
    ],
    "wof:name":"Owaissi Anglican Camp Assn",
    "wof:placetype":"venue"
},
  "geometry": {"coordinates":[-119.49313354500001,49.9993057251],"type":"Point"}
}