{
  "type": "Feature",
  "properties": {
    "addr:full":"10030 34 St NW Edmonton AB T6B 2Y5",
    "addr:housenumber":"10030",
    "addr:postcode":"t6b 2y5",
    "addr:street":"34 St Nw",
    "iso:country":"CA",
    "sg:address":"10030 34 St NW",
    "sg:city":"Edmonton",
    "sg:classifiers":[
        {
            "category":"Manufacturing",
            "subcategory":"Metals",
            "type":"Manufacturing & Wholesale Goods"
        }
    ],
    "sg:phone":"+1 780 469 1258",
    "sg:postcode":"T6B 2Y5",
    "sg:province":"AB",
    "sg:tags":[
        "steel"
    ],
    "wof:name":"Waiward Steel Fabricators Ltd",
    "wof:placetype":"venue"
},
  "geometry": {"coordinates":[-113.394104,53.538773],"type":"Point"}
}