{
  "type": "Feature",
  "properties": {
    "iso:country":"CA",
    "sg:address":"3455 Rue Isabelle",
    "sg:city":"Brossard",
    "sg:classifiers":[
        {
            "category":"Professional",
            "subcategory":"Business Services",
            "type":"Services"
        }
    ],
    "sg:phone":"+1 450 444 1213",
    "sg:postcode":"J4Y 2R2",
    "sg:province":"QC",
    "wof:name":"Monserco Ltee",
    "wof:placetype":"venue"
},
  "geometry": {"coordinates":[-73.467453,45.429394],"type":"Point"}
}