{
  "type": "Feature",
  "properties": {
    "addr:full":"3455 Rue Isabelle Brossard QC J4Y 2R2",
    "addr:housenumber":"3455",
    "addr:postcode":"j4y 2r2",
    "addr:street":"Rue Isabelle",
    "iso:country":"CA",
    "sg:address":"3455 Rue Isabelle",
    "sg:city":"Brossard",
    "sg:classifiers":[
        {
            "category":"Professional",
            "subcategory":"Business Services",
            "type":"Services"
        }
    ],
    "sg:phone":"+1 450 444 1213",
    "sg:postcode":"J4Y 2R2",
    "sg:province":"QC",
    "wof:name":"Monserco Ltee",
    "wof:placetype":"venue"
},
  "geometry": {"coordinates":[-73.46745300000001,45.429394],"type":"Point"}
}