{
  "type": "Feature",
  "properties": {
    "addr:full":"3825 10E Ave Saint-Georges QC G5Y 8G5",
    "addr:housenumber":"3825",
    "addr:postcode":"g5y 8g5",
    "addr:street":"10E Ave",
    "iso:country":"CA",
    "sg:address":"3825 10E Ave",
    "sg:city":"Saint-Georges",
    "sg:classifiers":[
        {
            "category":"Food & Beverages",
            "subcategory":"Bakery",
            "type":"Retail Goods"
        }
    ],
    "sg:phone":"+1 418 228 2168",
    "sg:postcode":"G5Y 8G5",
    "sg:province":"QC",
    "sg:tags":[
        "baker"
    ],
    "wof:name":"Multi-Marques Inc",
    "wof:placetype":"venue"
},
  "geometry": {"coordinates":[-70.67115020750001,46.1233482361],"type":"Point"}
}