{
  "type": "Feature",
  "properties": {
    "addr:full":"PO Box 21 Deadwood AB T0H 1A0",
    "addr:housenumber":"po box 21",
    "addr:postcode":"t0h 1a0",
    "iso:country":"CA",
    "sg:address":"PO Box 21",
    "sg:city":"Deadwood",
    "sg:classifiers":[
        {
            "category":"Building & Trades",
            "subcategory":"Construction",
            "type":"Services"
        }
    ],
    "sg:phone":"+1 780 836 2473",
    "sg:postcode":"T0H 1A0",
    "sg:province":"AB",
    "sg:tags":[
        "general",
        "contractor"
    ],
    "wof:name":"Burroughs Contractors",
    "wof:placetype":"venue"
},
  "geometry": {"coordinates":[-117.47154235799999,56.7410011292],"type":"Point"}
}