{
  "type": "Feature",
  "properties": {
    "addr:full":"212 Centre Ave W Black Diamond AB T0L 0H0",
    "addr:housenumber":"212",
    "addr:postcode":"t0l 0h0",
    "addr:street":"Centre Ave W",
    "iso:country":"CA",
    "sg:address":"212 Centre Ave W",
    "sg:city":"Black Diamond",
    "sg:classifiers":[
        {
            "category":"Organizations",
            "subcategory":"Religious Organization",
            "type":"Services"
        }
    ],
    "sg:phone":"+1 403 933 4957",
    "sg:postcode":"T0L 0H0",
    "sg:province":"AB",
    "sg:tags":[
        "church"
    ],
    "wof:name":"Black Diamond Gospel Chapel",
    "wof:placetype":"venue"
},
  "geometry": {"coordinates":[-114.234917,50.688541],"type":"Point"}
}