{
  "type": "Feature",
  "properties": {
    "addr:full":"2300 Ryan Rd Courtenay BC V9N 8N6",
    "addr:housenumber":"2300",
    "addr:postcode":"v9n 8n6",
    "addr:street":"Ryan Rd",
    "iso:country":"CA",
    "sg:address":"2300 Ryan Rd",
    "sg:city":"Courtenay",
    "sg:classifiers":[
        {
            "category":"Social Services",
            "subcategory":"Child Care",
            "type":"Services"
        }
    ],
    "sg:phone":"+1 250 897 1233",
    "sg:postcode":"V9N 8N6",
    "sg:province":"BC",
    "wof:name":"Beaufort Childrens Ctr",
    "wof:placetype":"venue"
},
  "geometry": {"coordinates":[-124.97141999999999,49.707485],"type":"Point"}
}