{
  "type": "Feature",
  "properties": {
    "addr:full":"Saskatoon SK S7K 2A6",
    "addr:postcode":"s7k 2a6",
    "iso:country":"CA",
    "sg:city":"Saskatoon",
    "sg:classifiers":[
        {
            "category":"Retail",
            "subcategory":"Auto Repair",
            "type":"Services"
        }
    ],
    "sg:phone":"+1 306 242 1229",
    "sg:postcode":"S7K 2A6",
    "sg:province":"SK",
    "sg:tags":[
        "body",
        "automobile",
        "painting"
    ],
    "wof:name":"Inline Paint & Body",
    "wof:placetype":"venue"
},
  "geometry": {"coordinates":[-106.660828,52.162048],"type":"Point"}
}