{
  "type": "Feature",
  "properties": {
    "addr:full":"105 Howard Ave Riverview NB E1B 1L8",
    "addr:housenumber":"105",
    "addr:postcode":"e1b 1l8",
    "addr:street":"Howard Ave",
    "iso:country":"CA",
    "sg:address":"105 Howard Ave",
    "sg:city":"Riverview",
    "sg:classifiers":[
        {
            "category":"Organizations",
            "subcategory":"Religious Organization",
            "type":"Services"
        }
    ],
    "sg:phone":"+1 506 386 7722",
    "sg:postcode":"E1B 1L8",
    "sg:province":"NB",
    "sg:tags":[
        "church"
    ],
    "wof:name":"Providence Reformed Baptist",
    "wof:placetype":"venue"
},
  "geometry": {"coordinates":[-64.7789306641,46.073928833],"type":"Point"}
}