{
  "type": "Feature",
  "properties": {
    "iso:country":"CA",
    "sg:address":"11 Bowridge Dr NW",
    "sg:city":"Calgary",
    "sg:classifiers":[
        {
            "category":"Shopping",
            "subcategory":"Bicycles & Sporting Goods",
            "type":"Retail Goods"
        }
    ],
    "sg:phone":"+1 403 247 3320",
    "sg:postcode":"T3B 3R6",
    "sg:province":"AB",
    "wof:name":"Ski Cellar Snowboard",
    "wof:placetype":"venue"
},
  "geometry": {"coordinates":[-114.204185486,51.0830688477],"type":"Point"}
}