{
  "type": "Feature",
  "properties": {
    "iso:country":"CA",
    "sg:address":"14642 119 Ave NW",
    "sg:city":"Edmonton",
    "sg:classifiers":[
        {
            "category":"Shopping",
            "subcategory":"Computers & Home Electronics",
            "type":"Retail Goods"
        }
    ],
    "sg:phone":"+1 780 453 1870",
    "sg:postcode":"T5L 2P2",
    "sg:province":"AB",
    "sg:tags":[
        "equipment",
        "satellite",
        "system"
    ],
    "wof:name":"Tramstar Audio Visual Ltd",
    "wof:placetype":"venue"
},
  "geometry": {"coordinates":[-113.573791504,53.5717964172],"type":"Point"}
}