{
  "type": "Feature",
  "properties": {
    "iso:country":"CA",
    "sg:address":"2380 Av Dalton",
    "sg:city":"Sainte-Foy",
    "sg:classifiers":[
        {
            "category":"Retail",
            "subcategory":"Auto Repair",
            "type":"Services"
        }
    ],
    "sg:phone":"+1 418 657 2425",
    "sg:postcode":"G1P 3X1",
    "sg:province":"QC",
    "sg:tags":[
        "truck"
    ],
    "wof:name":"Camions Freightliner Quebec",
    "wof:placetype":"venue"
},
  "geometry": {"coordinates":[-71.294388,46.792717],"type":"Point"}
}