{
  "type": "Feature",
  "properties": {
    "iso:country":"CA",
    "sg:address":"163 Rue Montevista",
    "sg:city":"Dollard-Des-Ormeaux",
    "sg:classifiers":[
        {
            "category":"Real Estate",
            "subcategory":"Real Estate Agent",
            "type":"Services"
        }
    ],
    "sg:phone":"+1 514 683 6666",
    "sg:postcode":"H9B 3A4",
    "sg:province":"QC",
    "wof:name":"Immeubles Gloria Inc",
    "wof:placetype":"venue"
},
  "geometry": {"coordinates":[-73.81233215330001,45.4849243164],"type":"Point"}
}