{
  "type": "Feature",
  "properties": {
    "iso:country":"CA",
    "sg:address":"2225 Avenue C N",
    "sg:city":"Saskatoon",
    "sg:classifiers":[
        {
            "category":"Manufacturing",
            "subcategory":"Metals",
            "type":"Manufacturing & Wholesale Goods"
        }
    ],
    "sg:phone":"+1 306 664 3611",
    "sg:postcode":"S7L 5Z2",
    "sg:province":"SK",
    "sg:tags":[
        "brass",
        "bronze",
        "aluminum"
    ],
    "wof:name":"Kaycan Limited",
    "wof:placetype":"venue"
},
  "geometry": {"coordinates":[-106.673660278,52.1605377197],"type":"Point"}
}