{
  "type": "Feature",
  "properties": {
    "iso:country":"CA",
    "sg:address":"10321 Gething St",
    "sg:city":"Hudson's Hope",
    "sg:classifiers":[
        {
            "category":"Home & Garden",
            "subcategory":"Garden Supply",
            "type":"Retail Goods"
        }
    ],
    "sg:phone":"+1 250 783 5507",
    "sg:postcode":"V0C 1V0",
    "sg:province":"BC",
    "sg:tags":[
        "hardware",
        "lawn"
    ],
    "wof:name":"Pro Hardware & Building Supply",
    "wof:placetype":"venue"
},
  "geometry": {"coordinates":[-121.913109,56.026451],"type":"Point"}
}