{
  "type": "Feature",
  "properties": {
    "addr:full":"1751 10 Ave SW Salmon Arm BC V1E 1T4",
    "addr:housenumber":"1751",
    "addr:postcode":"v1e 1t4",
    "addr:street":"10 Ave Sw",
    "iso:country":"CA",
    "sg:address":"1751 10 Ave SW",
    "sg:city":"Salmon Arm",
    "sg:classifiers":[
        {
            "category":"Government",
            "subcategory":"Office",
            "type":"Public Place"
        }
    ],
    "sg:phone":"+1 250 804 7000",
    "sg:postcode":"V1E 1T4",
    "sg:province":"BC",
    "wof:name":"Fisheries & Oceans Canada",
    "wof:placetype":"venue"
},
  "geometry": {"coordinates":[-119.308532715,50.6927185059],"type":"Point"}
}