{
  "type": "Feature",
  "properties": {
    "addr:full":"3880 Boul Harvey Jonquiere QC G7X 8R6",
    "addr:housenumber":"3880",
    "addr:postcode":"g7x 8r6",
    "addr:street":"Boul Harvey",
    "iso:country":"CA",
    "sg:address":"3880 Boul Harvey",
    "sg:city":"Jonquiere",
    "sg:classifiers":[
        {
            "category":"Organizations",
            "subcategory":"Religious Organization",
            "type":"Services"
        }
    ],
    "sg:phone":"+1 418 542 2991",
    "sg:postcode":"G7X 8R6",
    "sg:province":"QC",
    "sg:tags":[
        "church"
    ],
    "wof:name":"Presbytere St Albert Le Grand",
    "wof:placetype":"venue"
},
  "geometry": {"coordinates":[-71.2518692017,48.4132461548],"type":"Point"}
}