{
  "type": "Feature",
  "properties": {
    "addr:full":"10530 132 Ave NW Edmonton AB T5E 0Z4",
    "addr:housenumber":"10530",
    "addr:postcode":"t5e 0z4",
    "addr:street":"132 Ave Nw",
    "iso:country":"CA",
    "sg:address":"10530 132 Ave NW",
    "sg:city":"Edmonton",
    "sg:classifiers":[
        {
            "category":"Communications",
            "subcategory":"Film & Video Production",
            "type":"Services"
        }
    ],
    "sg:phone":"+1 780 478 4202",
    "sg:postcode":"T5E 0Z4",
    "sg:province":"AB",
    "sg:tags":[
        "motion",
        "picture",
        "studio",
        "producer"
    ],
    "wof:name":"Pro Cinema Corp",
    "wof:placetype":"venue"
},
  "geometry": {"coordinates":[-113.50145000000001,53.592213],"type":"Point"}
}