{
  "type": "Feature",
  "properties": {
    "iso:country":"CA",
    "sg:address":"2206 Boul Du Jardin",
    "sg:city":"Saint-Felicien",
    "sg:classifiers":[
        {
            "category":"Travel",
            "subcategory":"Campground",
            "type":"Entertainment"
        }
    ],
    "sg:phone":"+1 418 679 1719",
    "sg:postcode":"G8K 2P8",
    "sg:province":"QC",
    "wof:name":"Camping St-Felicien",
    "wof:placetype":"venue"
},
  "geometry": {"coordinates":[-72.497756958,48.686340332],"type":"Point"}
}