{
  "type": "Feature",
  "properties": {
    "addr:full":"2206 Boul Du Jardin Saint-Felicien QC G8K 2P8",
    "addr:housenumber":"2206",
    "addr:postcode":"g8k 2p8",
    "addr:street":"Boul Du Jardin Saint-Felicien",
    "iso:country":"CA",
    "sg:address":"2206 Boul Du Jardin",
    "sg:city":"Saint-Felicien",
    "sg:classifiers":[
        {
            "category":"Travel",
            "subcategory":"Campground",
            "type":"Entertainment"
        }
    ],
    "sg:phone":"+1 418 679 1719",
    "sg:postcode":"G8K 2P8",
    "sg:province":"QC",
    "wof:name":"Camping St-Felicien",
    "wof:placetype":"venue"
},
  "geometry": {"coordinates":[-72.497756958,48.686340332],"type":"Point"}
}