{
  "type": "Feature",
  "properties": {
    "addr:full":"1973 Lawrence Ave E Scarborough ON M1R 2Z2",
    "addr:housenumber":"1973",
    "addr:postcode":"m1r 2z2",
    "addr:street":"Lawrence Ave E",
    "iso:country":"CA",
    "sg:address":"1973 Lawrence Ave E",
    "sg:city":"Scarborough",
    "sg:classifiers":[
        {
            "category":"Shopping",
            "type":"Retail Goods"
        }
    ],
    "sg:phone":"+1 416 285 9225",
    "sg:postcode":"M1R 2Z2",
    "sg:province":"ON",
    "sg:tags":[
        "cosmetic",
        "perfume"
    ],
    "wof:name":"Amore Canada Inc",
    "wof:placetype":"venue"
},
  "geometry": {"coordinates":[-79.2965621948,43.744846344],"type":"Point"}
}