{
  "type": "Feature",
  "properties": {
    "addr:full":"Conception Bay South NL A1W 3A6",
    "addr:postcode":"a1w 3a6",
    "iso:country":"CA",
    "sg:city":"Conception Bay South",
    "sg:classifiers":[
        {
            "category":"Home & Garden",
            "subcategory":"Hardware",
            "type":"Retail Goods"
        }
    ],
    "sg:phone":"+1 709 834 8621",
    "sg:postcode":"A1W 3A6",
    "sg:province":"NL",
    "wof:name":"Home Hardware Handyman",
    "wof:placetype":"venue"
},
  "geometry": {"coordinates":[-52.9574203491,47.5182952881],"type":"Point"}
}