{
  "type": "Feature",
  "properties": {
    "addr:full":"1325 Bodley Rd Mississauga ON L5J 3X1",
    "addr:housenumber":"1325",
    "addr:postcode":"l5j 3x1",
    "addr:street":"Bodley Rd",
    "iso:country":"CA",
    "sg:address":"1325 Bodley Rd",
    "sg:city":"Mississauga",
    "sg:classifiers":[
        {
            "category":"Education",
            "subcategory":"School",
            "type":"Public Place"
        }
    ],
    "sg:phone":"+1 905 822 4564",
    "sg:postcode":"L5J 3X1",
    "sg:province":"ON",
    "wof:name":"St Helen School",
    "wof:placetype":"venue"
},
  "geometry": {"coordinates":[-79.65149700000001,43.505367],"type":"Point"}
}