{
  "type": "Feature",
  "properties": {
    "iso:country":"CA",
    "sg:address":"176 Bullock Dr",
    "sg:city":"Markham",
    "sg:classifiers":[
        {
            "category":"Retail",
            "subcategory":"Auto Repair",
            "type":"Services"
        }
    ],
    "sg:phone":"+1 905 472 3494",
    "sg:postcode":"L3P 7N1",
    "sg:province":"ON",
    "sg:tags":[
        "repairing",
        "automobile"
    ],
    "wof:name":"Blakeney Auto Svc",
    "wof:placetype":"venue"
},
  "geometry": {"coordinates":[-79.2790145874,43.8749542236],"type":"Point"}
}