{
  "type": "Feature",
  "properties": {
    "addr:full":"2527 Nagle Rd Baltimore ON K0K 1C0",
    "addr:housenumber":"2527",
    "addr:postcode":"k0k 1c0",
    "addr:street":"Nagle Rd",
    "iso:country":"CA",
    "sg:address":"2527 Nagle Rd",
    "sg:city":"Baltimore",
    "sg:classifiers":[
        {
            "category":"Building & Trades",
            "subcategory":"Construction",
            "type":"Services"
        }
    ],
    "sg:phone":"+1 905 372 6691",
    "sg:postcode":"K0K 1C0",
    "sg:province":"ON",
    "sg:tags":[
        "bridge",
        "builder"
    ],
    "wof:name":"Baltimore Development & Svc",
    "wof:placetype":"venue"
},
  "geometry": {"coordinates":[-78.148438,44.022724],"type":"Point"}
}