{
  "type": "Feature",
  "properties": {
    "addr:full":"1388 Hwy 138 Godmanchester QC J0S 1L0",
    "addr:housenumber":"1388",
    "addr:postcode":"j0s 1l0",
    "addr:street":"Hwy 138",
    "iso:country":"CA",
    "sg:address":"1388 Hwy 138",
    "sg:city":"Godmanchester",
    "sg:classifiers":[
        {
            "category":"Farming",
            "subcategory":"Farm",
            "type":"Manufacturing & Wholesale Goods"
        }
    ],
    "sg:phone":"+1 450 264 4592",
    "sg:postcode":"J0S 1L0",
    "sg:province":"QC",
    "wof:name":"Fermes Ajiro Inc",
    "wof:placetype":"venue"
},
  "geometry": {"coordinates":[-74.313255,45.008976],"type":"Point"}
}