{
  "type": "Feature",
  "properties": {
    "addr:full":"897 321 Rte N Saint-Andre-Avellin QC J0V 1W0",
    "addr:housenumber":"321",
    "addr:postcode":"j0v 1w0",
    "addr:street":"Rte N",
    "iso:country":"CA",
    "sg:address":"897 321 Rte N",
    "sg:city":"Saint-Andre-Avellin",
    "sg:classifiers":[
        {
            "category":"Professional",
            "subcategory":"Computer Services",
            "type":"Services"
        }
    ],
    "sg:phone":"+1 819 983 2012",
    "sg:postcode":"J0V 1W0",
    "sg:province":"QC",
    "sg:tags":[
        "information",
        "system",
        "consultant"
    ],
    "wof:name":"Pilon, Marcel",
    "wof:placetype":"venue"
},
  "geometry": {"coordinates":[-75.054253,45.724167],"type":"Point"}
}