{
  "type": "Feature",
  "properties": {
    "addr:full":"Montreal QC H2L 4C7",
    "addr:postcode":"h2l 4c7",
    "iso:country":"CA",
    "sg:city":"Montreal",
    "sg:classifiers":[
        {
            "category":"Organizations",
            "subcategory":"Professional Association",
            "type":"Services"
        }
    ],
    "sg:phone":"+1 514 848 9977",
    "sg:postcode":"H2L 4C7",
    "sg:province":"QC",
    "wof:name":"Federation Autonome-Collegial",
    "wof:placetype":"venue"
},
  "geometry": {"coordinates":[-73.55838,45.514233],"type":"Point"}
}