{
  "type": "Feature",
  "properties": {
    "iso:country":"CA",
    "sg:address":"320 Mary St W",
    "sg:city":"Lindsay",
    "sg:classifiers":[
        {
            "category":"Social Services",
            "subcategory":"Child Care",
            "type":"Services"
        }
    ],
    "sg:phone":"+1 705 324 8691",
    "sg:postcode":"K9V 5X5",
    "sg:province":"ON",
    "wof:name":"Kawartha Child Cares Svc",
    "wof:placetype":"venue"
},
  "geometry": {"coordinates":[-78.75607299799999,44.3398361206],"type":"Point"}
}