{
  "type": "Feature",
  "properties": {
    "addr:full":"38 Centre St Bowmanville ON L1C 2Y3",
    "addr:housenumber":"38",
    "addr:postcode":"l1c 2y3",
    "addr:street":"Centre St",
    "iso:country":"CA",
    "sg:address":"38 Centre St",
    "sg:city":"Bowmanville",
    "sg:classifiers":[
        {
            "category":"Retail",
            "subcategory":"Animal Services",
            "type":"Services"
        }
    ],
    "sg:phone":"+1 905 697 8857",
    "sg:postcode":"L1C 2Y3",
    "sg:province":"ON",
    "sg:tags":[
        "pet",
        "boarding",
        "sitting"
    ],
    "wof:name":"Home Alone",
    "wof:placetype":"venue"
},
  "geometry": {"coordinates":[-78.68579864500001,43.9160881042],"type":"Point"}
}