{
  "type": "Feature",
  "properties": {
    "addr:full":"1222 5th Ave Valemount BC V0E 2Z0",
    "addr:housenumber":"1222",
    "addr:postcode":"v0e 2z0",
    "addr:street":"5Th Ave",
    "iso:country":"CA",
    "sg:address":"1222 5th Ave",
    "sg:city":"Valemount",
    "sg:classifiers":[
        {
            "category":"Professional",
            "subcategory":"Accounting & Tax Preparation",
            "type":"Services"
        }
    ],
    "sg:phone":"+1 250 566 4854",
    "sg:postcode":"V0E 2Z0",
    "sg:province":"BC",
    "sg:tags":[
        "accountant"
    ],
    "wof:name":"Ladd Patton & CO",
    "wof:placetype":"venue"
},
  "geometry": {"coordinates":[-119.25743866000001,52.8321075439],"type":"Point"}
}