{
  "type": "Feature",
  "properties": {
    "iso:country":"CA",
    "sg:address":"850 Route 430",
    "sg:city":"Big River",
    "sg:classifiers":[
        {
            "category":"Retail",
            "subcategory":"Animal Services",
            "type":"Services"
        }
    ],
    "sg:phone":"+1 506 548 8288",
    "sg:postcode":"E2A 6P8",
    "sg:province":"NB",
    "sg:tags":[
        "pet",
        "grooming",
        "washing"
    ],
    "wof:name":"Lynda's Pet Parlour",
    "wof:placetype":"venue"
},
  "geometry": {"coordinates":[-65.6640701294,47.5800018311],"type":"Point"}
}