{
  "type": "Feature",
  "properties": {
    "addr:full":"2180 Hammonds Plains Rd Hammonds Plains NS B4B 1M5",
    "addr:housenumber":"2180",
    "addr:postcode":"b4b 1m5",
    "addr:street":"Hammonds Plains Rd",
    "iso:country":"CA",
    "sg:address":"2180 Hammonds Plains Rd",
    "sg:city":"Hammonds Plains",
    "sg:classifiers":[
        {
            "category":"Education",
            "subcategory":"School",
            "type":"Public Place"
        }
    ],
    "sg:phone":"+1 902 832 8412",
    "sg:postcode":"B4B 1M5",
    "sg:province":"NS",
    "wof:name":"Hammonds Plains Consolidated",
    "wof:placetype":"venue"
},
  "geometry": {"coordinates":[-63.7898788452,44.7341880798],"type":"Point"}
}