{
  "type": "Feature",
  "properties": {
    "addr:full":"1206 Rue Des Epinettes Prevost QC J0R 1T0",
    "addr:housenumber":"1206",
    "addr:postcode":"j0r 1t0",
    "addr:street":"Rue Des Epinettes Prevost",
    "iso:country":"CA",
    "sg:address":"1206 Rue Des Epinettes",
    "sg:city":"Prevost",
    "sg:classifiers":[
        {
            "category":"Wholesale",
            "subcategory":"Stationery",
            "type":"Manufacturing & Wholesale Goods"
        }
    ],
    "sg:phone":"+1 450 436 7892",
    "sg:postcode":"J0R 1T0",
    "sg:province":"QC",
    "sg:tags":[
        "sanitary",
        "product",
        "supply"
    ],
    "wof:name":"Distributions Car-Den Enr",
    "wof:placetype":"venue"
},
  "geometry": {"coordinates":[-74.0503234863,45.8278923035],"type":"Point"}
}