{
  "type": "Feature",
  "properties": {
    "iso:country":"CA",
    "sg:address":"1040 North Talbot Rd",
    "sg:city":"Windsor",
    "sg:classifiers":[
        {
            "category":"Building & Trades",
            "subcategory":"Electrical",
            "type":"Services"
        }
    ],
    "sg:phone":"+1 519 256 3561",
    "sg:postcode":"N9G 2S3",
    "sg:province":"ON",
    "sg:tags":[
        "electric",
        "contractor"
    ],
    "wof:name":"A C Electric",
    "wof:placetype":"venue"
},
  "geometry": {"coordinates":[-82.982216,42.243427],"type":"Point"}
}