{
  "type": "Feature",
  "properties": {
    "addr:full":"Richmond BC V6Y 2C4",
    "addr:postcode":"v6y 2c4",
    "iso:country":"CA",
    "sg:city":"Richmond",
    "sg:classifiers":[
        {
            "category":"Professional",
            "subcategory":"Art Services",
            "type":"Services"
        }
    ],
    "sg:phone":"+1 604 270 3942",
    "sg:postcode":"V6Y 2C4",
    "sg:province":"BC",
    "sg:tags":[
        "photographer"
    ],
    "wof:name":"Ted Deeley Photography",
    "wof:placetype":"venue"
},
  "geometry": {"coordinates":[-123.13640599999999,49.163658],"type":"Point"}
}