{
  "type": "Feature",
  "properties": {
    "iso:country":"CA",
    "sg:address":"3680 Boul Saint-Laurent",
    "sg:city":"Montreal",
    "sg:classifiers":[
        {
            "category":"Shopping",
            "subcategory":"Used Merchandise",
            "type":"Retail Goods"
        }
    ],
    "sg:phone":"+1 514 288 3804",
    "sg:postcode":"H2X 2V4",
    "sg:province":"QC",
    "sg:tags":[
        "antique"
    ],
    "wof:name":"Antiques Hubert",
    "wof:placetype":"venue"
},
  "geometry": {"coordinates":[-73.573898,45.514366],"type":"Point"}
}