{
  "type": "Feature",
  "properties": {
    "addr:full":"1000 Bishop St N Cambridge ON N3H 4V7",
    "addr:housenumber":"1000",
    "addr:postcode":"n3h 4v7",
    "addr:street":"Bishop St N",
    "iso:country":"CA",
    "sg:address":"1000 Bishop St N",
    "sg:city":"Cambridge",
    "sg:classifiers":[
        {
            "category":"Manufacturing",
            "subcategory":"Rubber & Plastics",
            "type":"Manufacturing & Wholesale Goods"
        }
    ],
    "sg:phone":"+1 519 653 6116",
    "sg:postcode":"N3H 4V7",
    "sg:province":"ON",
    "sg:tags":[
        "equipment",
        "laminating",
        "supply"
    ],
    "wof:name":"Canlam Distributing",
    "wof:placetype":"venue"
},
  "geometry": {"coordinates":[-80.332443,43.393581],"type":"Point"}
}