{
  "type": "Feature",
  "properties": {
    "addr:full":"2840 Kew Dr Windsor ON N8T 3C6",
    "addr:housenumber":"2840",
    "addr:postcode":"n8t 3c6",
    "addr:street":"Kew Dr",
    "iso:country":"CA",
    "sg:address":"2840 Kew Dr",
    "sg:city":"Windsor",
    "sg:classifiers":[
        {
            "category":"Recreation",
            "type":"Entertainment"
        }
    ],
    "sg:phone":"+1 519 945 8173",
    "sg:postcode":"N8T 3C6",
    "sg:province":"ON",
    "sg:tags":[
        "cutting",
        "laser",
        "amusement"
    ],
    "wof:name":"Canadian Laser Cutting Inc",
    "wof:placetype":"venue"
},
  "geometry": {"coordinates":[-82.9377288818,42.3043632507],"type":"Point"}
}