{
  "type": "Feature",
  "properties": {
    "addr:full":"Bridgetown NS B0S 1C0",
    "addr:postcode":"b0s 1c0",
    "iso:country":"CA",
    "sg:city":"Bridgetown",
    "sg:classifiers":[
        {
            "category":"Organizations",
            "subcategory":"Religious Organization",
            "type":"Services"
        }
    ],
    "sg:phone":"+1 902 665 4734",
    "sg:postcode":"B0S 1C0",
    "sg:province":"NS",
    "sg:tags":[
        "church"
    ],
    "wof:name":"St James Anglican Church",
    "wof:placetype":"venue"
},
  "geometry": {"coordinates":[-65.2864990234,44.841468811],"type":"Point"}
}