{
  "type": "Feature",
  "properties": {
    "iso:country":"CA",
    "sg:city":"Woodbridge",
    "sg:classifiers":[
        {
            "category":"Recreation",
            "subcategory":"Amusement Park",
            "type":"Entertainment"
        }
    ],
    "sg:phone":"+1 905 850 7529",
    "sg:postcode":"L4L 5Y6",
    "sg:province":"ON",
    "wof:name":"Bounce 'N Play Inc",
    "wof:placetype":"venue"
},
  "geometry": {"coordinates":[-79.564804,43.781006],"type":"Point"}
}