{
  "type": "Feature",
  "properties": {
    "iso:country":"CA",
    "sg:address":"777 Bay St # 400",
    "sg:city":"Toronto",
    "sg:classifiers":[
        {
            "category":"Restaurant",
            "type":"Food & Drink"
        }
    ],
    "sg:phone":"+1 416 598 9501",
    "sg:postcode":"M5G 2C8",
    "sg:province":"ON",
    "wof:name":"Cultures Fresh Food Restaurant",
    "wof:placetype":"venue"
},
  "geometry": {"coordinates":[-79.385399,43.660233],"type":"Point"}
}