{
  "type": "Feature",
  "properties": {
    "addr:full":"57 Atomic Ave Etobicoke ON M8Z 5K8",
    "addr:housenumber":"57",
    "addr:postcode":"m8z 5k8",
    "addr:street":"Atomic Ave",
    "iso:country":"CA",
    "sg:address":"57 Atomic Ave",
    "sg:city":"Etobicoke",
    "sg:classifiers":[
        {
            "category":"Manufacturing",
            "subcategory":"Metals",
            "type":"Manufacturing & Wholesale Goods"
        }
    ],
    "sg:phone":"+1 416 255 7878",
    "sg:postcode":"M8Z 5K8",
    "sg:province":"ON",
    "sg:tags":[
        "valve"
    ],
    "wof:name":"Mcrae Engineering Equipment",
    "wof:placetype":"venue"
},
  "geometry": {"coordinates":[-79.541748,43.620159],"type":"Point"}
}