{
  "type": "Feature",
  "properties": {
    "iso:country":"CA",
    "sg:address":"715 1st Ave",
    "sg:city":"Regina",
    "sg:classifiers":[
        {
            "category":"Freight",
            "type":"Transportation"
        }
    ],
    "sg:phone":"+1 306 924 1044",
    "sg:postcode":"S4N 4M4",
    "sg:province":"SK",
    "sg:tags":[
        "trucking"
    ],
    "wof:name":"Plains Ventures Ltd",
    "wof:placetype":"venue"
},
  "geometry": {"coordinates":[-104.592025757,50.4673805237],"type":"Point"}
}