{
  "type": "Feature",
  "properties": {
    "addr:full":"Port Coquitlam BC V3C 6N2",
    "addr:postcode":"v3c 6n2",
    "iso:country":"CA",
    "sg:city":"Port Coquitlam",
    "sg:classifiers":[
        {
            "category":"Arts & Performance",
            "subcategory":"Theater",
            "type":"Entertainment"
        }
    ],
    "sg:phone":"+1 604 468 2911",
    "sg:postcode":"V3C 6N2",
    "sg:province":"BC",
    "sg:tags":[
        "bureau"
    ],
    "wof:name":"Noteable Entertainment",
    "wof:placetype":"venue"
},
  "geometry": {"coordinates":[-122.77320899999999,49.257538],"type":"Point"}
}