{
  "type": "Feature",
  "properties": {
    "addr:full":"Surrey BC V3W 4Z9",
    "addr:postcode":"v3w 4z9",
    "iso:country":"CA",
    "sg:city":"Surrey",
    "sg:classifiers":[
        {
            "category":"Professional",
            "subcategory":"Business Services",
            "type":"Services"
        }
    ],
    "sg:phone":"+1 604 572 4060",
    "sg:postcode":"V3W 4Z9",
    "sg:province":"BC",
    "sg:tags":[
        "translator",
        "interpreter"
    ],
    "wof:name":"Options Services To Comms",
    "wof:placetype":"venue"
},
  "geometry": {"coordinates":[-122.845589,49.126202],"type":"Point"}
}