{
  "type": "Feature",
  "properties": {
    "addr:full":"1306 Algonquin Ave North Bay ON P1B 4Y2",
    "addr:housenumber":"1306",
    "addr:postcode":"p1b 4y2",
    "addr:street":"Algonquin Ave",
    "iso:country":"CA",
    "sg:address":"1306 Algonquin Ave",
    "sg:city":"North Bay",
    "sg:classifiers":[
        {
            "category":"Personal",
            "subcategory":"Beauty Salon",
            "type":"Services"
        }
    ],
    "sg:phone":"+1 705 472 3950",
    "sg:postcode":"P1B 4Y2",
    "sg:province":"ON",
    "wof:name":"Anne's Hairstyling",
    "wof:placetype":"venue"
},
  "geometry": {"coordinates":[-79.4661026001,46.32762146],"type":"Point"}
}