{
  "type": "Feature",
  "properties": {
    "addr:full":"201 Waterloo St Veteran AB T0C 2S0",
    "addr:housenumber":"201",
    "addr:postcode":"t0c 2s0",
    "addr:street":"Waterloo St",
    "iso:country":"CA",
    "sg:address":"201 Waterloo St",
    "sg:city":"Veteran",
    "sg:classifiers":[
        {
            "category":"Mining & Drilling",
            "type":"Manufacturing & Wholesale Goods"
        }
    ],
    "sg:phone":"+1 403 575 2184",
    "sg:postcode":"T0C 2S0",
    "sg:province":"AB",
    "sg:tags":[
        "field",
        "oil"
    ],
    "wof:name":"Kitter's Bit Supply",
    "wof:placetype":"venue"
},
  "geometry": {"coordinates":[-111.12022399999999,52.002079],"type":"Point"}
}