{
  "type": "Feature",
  "properties": {
    "addr:full":"2670 Victoria Dr Vancouver BC V5N 4L2",
    "addr:housenumber":"2670",
    "addr:postcode":"v5n 4l2",
    "addr:street":"Victoria Dr",
    "iso:country":"CA",
    "sg:address":"2670 Victoria Dr",
    "sg:city":"Vancouver",
    "sg:classifiers":[
        {
            "category":"Organizations",
            "subcategory":"Religious Organization",
            "type":"Services"
        }
    ],
    "sg:phone":"+1 604 872 7915",
    "sg:postcode":"V5N 4L2",
    "sg:province":"BC",
    "sg:tags":[
        "church"
    ],
    "wof:name":"Christian Reformed Churches",
    "wof:placetype":"venue"
},
  "geometry": {"coordinates":[-123.065673828,49.2607727051],"type":"Point"}
}