{
  "type": "Feature",
  "properties": {
    "iso:country":"CA",
    "sg:city":"Coquitlam",
    "sg:classifiers":[
        {
            "category":"Wholesale",
            "subcategory":"Groceries",
            "type":"Manufacturing & Wholesale Goods"
        }
    ],
    "sg:phone":"+1 604 515 8986",
    "sg:postcode":"V3K 4X8",
    "sg:province":"BC",
    "sg:tags":[
        "food",
        "product"
    ],
    "wof:name":"J C Foods Ltd",
    "wof:placetype":"venue"
},
  "geometry": {"coordinates":[-122.852287,49.234455],"type":"Point"}
}