{
  "type": "Feature",
  "properties": {
    "iso:country":"CA",
    "sg:address":"1000 Dryden Blvd",
    "sg:city":"Whitby",
    "sg:classifiers":[
        {
            "category":"Social Services",
            "subcategory":"Child Care",
            "type":"Services"
        }
    ],
    "sg:phone":"+1 905 430 8598",
    "sg:postcode":"L1R 2A2",
    "sg:province":"ON",
    "wof:name":"Pryde Learning Ctr",
    "wof:placetype":"venue"
},
  "geometry": {"coordinates":[-78.9386978149,43.9097518921],"type":"Point"}
}