{
  "type": "Feature",
  "properties": {
    "addr:full":"388 Boul St-Pierre O Caraquet NB E1W 1A3",
    "addr:housenumber":"388",
    "addr:postcode":"e1w 1a3",
    "addr:street":"Boul St-Pierre O",
    "iso:country":"CA",
    "sg:address":"388 Boul St-Pierre O",
    "sg:city":"Caraquet",
    "sg:classifiers":[
        {
            "category":"Food & Beverages",
            "subcategory":"Specialty",
            "type":"Retail Goods"
        }
    ],
    "sg:phone":"+1 506 727 5411",
    "sg:postcode":"E1W 1A3",
    "sg:province":"NB",
    "sg:tags":[
        "water",
        "bulk",
        "company"
    ],
    "wof:name":"Ward Eau Inc",
    "wof:placetype":"venue"
},
  "geometry": {"coordinates":[-64.8791809082,47.7991409302],"type":"Point"}
}