{
  "type": "Feature",
  "properties": {
    "addr:full":"Mississauga ON L5R 3V2",
    "addr:postcode":"l5r 3v2",
    "iso:country":"CA",
    "sg:city":"Mississauga",
    "sg:classifiers":[
        {
            "category":"Restaurant",
            "type":"Food & Drink"
        }
    ],
    "sg:phone":"+1 905 712 3131",
    "sg:postcode":"L5R 3V2",
    "sg:province":"ON",
    "sg:tags":[
        "parlor",
        "ice",
        "cream"
    ],
    "wof:name":"Baskin Robbins Ice Cream",
    "wof:placetype":"venue"
},
  "geometry": {"coordinates":[-79.66802978520001,43.5931243896],"type":"Point"}
}