{
  "type": "Feature",
  "properties": {
    "addr:full":"6936 Mitch Owens Rd Greely ON K4P 1C5",
    "addr:housenumber":"6936",
    "addr:postcode":"k4p 1c5",
    "addr:street":"Mitch Owens Rd",
    "iso:country":"CA",
    "sg:address":"6936 Mitch Owens Rd",
    "sg:city":"Greely",
    "sg:classifiers":[
        {
            "category":"Building & Trades",
            "subcategory":"Electrical",
            "type":"Services"
        }
    ],
    "sg:phone":"+1 613 822 9888",
    "sg:postcode":"K4P 1C5",
    "sg:province":"ON",
    "sg:tags":[
        "electric",
        "contractor"
    ],
    "wof:name":"Bruce Moodie Electric",
    "wof:placetype":"venue"
},
  "geometry": {"coordinates":[-75.580513,45.275246],"type":"Point"}
}