{
  "type": "Feature",
  "properties": {
    "iso:country":"CA",
    "sg:address":"8822 Boul Langelier",
    "sg:city":"Saint-Leonard",
    "sg:classifiers":[
        {
            "category":"Retail",
            "subcategory":"Portrait Studio",
            "type":"Services"
        }
    ],
    "sg:phone":"+1 514 327 9551",
    "sg:postcode":"H1P 3H2",
    "sg:province":"QC",
    "sg:tags":[
        "photographer"
    ],
    "wof:name":"Glamor Photography & Video Enr",
    "wof:placetype":"venue"
},
  "geometry": {"coordinates":[-73.595261,45.600433],"type":"Point"}
}