{
  "type": "Feature",
  "properties": {
    "addr:full":"8822 Boul Langelier Saint-Leonard QC H1P 3H2",
    "addr:housenumber":"8822",
    "addr:postcode":"h1p 3h2",
    "addr:street":"Boul Langelier",
    "iso:country":"CA",
    "sg:address":"8822 Boul Langelier",
    "sg:city":"Saint-Leonard",
    "sg:classifiers":[
        {
            "category":"Retail",
            "subcategory":"Portrait Studio",
            "type":"Services"
        }
    ],
    "sg:phone":"+1 514 327 9551",
    "sg:postcode":"H1P 3H2",
    "sg:province":"QC",
    "sg:tags":[
        "photographer"
    ],
    "wof:name":"Glamor Photography & Video Enr",
    "wof:placetype":"venue"
},
  "geometry": {"coordinates":[-73.59526099999999,45.600433],"type":"Point"}
}