{
  "type": "Feature",
  "properties": {
    "addr:full":"4603 Bank St Gloucester ON K1T 3W6",
    "addr:housenumber":"4603",
    "addr:postcode":"k1t 3w6",
    "addr:street":"Bank St",
    "iso:country":"CA",
    "sg:address":"4603 Bank St",
    "sg:city":"Gloucester",
    "sg:classifiers":[
        {
            "category":"Building & Trades",
            "subcategory":"Construction",
            "type":"Services"
        }
    ],
    "sg:phone":"+1 613 822 2984",
    "sg:postcode":"K1T 3W6",
    "sg:province":"ON",
    "sg:tags":[
        "pavement",
        "sealing"
    ],
    "wof:name":"Hodgins Asphalt Sealers",
    "wof:placetype":"venue"
},
  "geometry": {"coordinates":[-75.5984039307,45.3288345337],"type":"Point"}
}