{
  "type": "Feature",
  "properties": {
    "addr:full":"75 Portsmouth Dr Scarborough ON M1C 5C8",
    "addr:housenumber":"75",
    "addr:postcode":"m1c 5c8",
    "addr:street":"Portsmouth Dr",
    "iso:country":"CA",
    "sg:address":"75 Portsmouth Dr",
    "sg:city":"Scarborough",
    "sg:classifiers":[
        {
            "category":"Home & Garden",
            "subcategory":"Household Appliances",
            "type":"Retail Goods"
        }
    ],
    "sg:phone":"+1 416 284 4410",
    "sg:postcode":"M1C 5C8",
    "sg:province":"ON",
    "wof:name":"General Appliance Svc",
    "wof:placetype":"venue"
},
  "geometry": {"coordinates":[-79.14328,43.777039],"type":"Point"}
}