{
  "type": "Feature",
  "properties": {
    "addr:full":"381 Pine St Sudbury ON P3C 1Y1",
    "addr:housenumber":"381",
    "addr:postcode":"p3c 1y1",
    "addr:street":"Pine St",
    "iso:country":"CA",
    "sg:address":"381 Pine St",
    "sg:city":"Sudbury",
    "sg:classifiers":[
        {
            "category":"Arts & Performance",
            "subcategory":"Theater",
            "type":"Entertainment"
        }
    ],
    "sg:phone":"+1 705 688 8452",
    "sg:postcode":"P3C 1Y1",
    "sg:province":"ON",
    "sg:tags":[
        "theatrical",
        "manager",
        "producer"
    ],
    "wof:name":"R & I Design",
    "wof:placetype":"venue"
},
  "geometry": {"coordinates":[-81.0088882446,46.4937095642],"type":"Point"}
}