{
  "type": "Feature",
  "properties": {
    "addr:full":"Pointe-Calumet QC J0N 1G2",
    "addr:postcode":"j0n 1g2",
    "iso:country":"CA",
    "sg:city":"Pointe-Calumet",
    "sg:classifiers":[
        {
            "category":"Organizations",
            "subcategory":"Professional Association",
            "type":"Services"
        }
    ],
    "sg:phone":"+1 450 491 6638",
    "sg:postcode":"J0N 1G2",
    "sg:province":"QC",
    "wof:name":"Chevaliers DE Colomb Conseil",
    "wof:placetype":"venue"
},
  "geometry": {"coordinates":[-73.970337,45.499016],"type":"Point"}
}