{
  "type": "Feature",
  "properties": {
    "addr:full":"1685 Windsor Ave Windsor ON N8X 3M5",
    "addr:housenumber":"1685",
    "addr:postcode":"n8x 3m5",
    "addr:street":"Windsor Ave",
    "iso:country":"CA",
    "sg:address":"1685 Windsor Ave",
    "sg:city":"Windsor",
    "sg:classifiers":[
        {
            "category":"Manufacturing",
            "subcategory":"Printing",
            "type":"Manufacturing & Wholesale Goods"
        }
    ],
    "sg:phone":"+1 519 254 5237",
    "sg:postcode":"N8X 3M5",
    "sg:province":"ON",
    "sg:tags":[
        "printer"
    ],
    "wof:name":"Wheeler's Printing & Copying",
    "wof:placetype":"venue"
},
  "geometry": {"coordinates":[-83.02262115480001,42.2973861694],"type":"Point"}
}