{
  "type": "Feature",
  "properties": {
    "addr:full":"144 Av Principale Rouyn-Noranda QC J9X 4P5",
    "addr:postcode":"j9x 4p5",
    "addr:street":"144 Av Principale",
    "iso:country":"CA",
    "sg:address":"144 Av Principale",
    "sg:city":"Rouyn-Noranda",
    "sg:classifiers":[
        {
            "category":"Personal",
            "subcategory":"Beauty Salon",
            "type":"Services"
        }
    ],
    "sg:phone":"+1 819 762 3933",
    "sg:postcode":"J9X 4P5",
    "sg:province":"QC",
    "wof:name":"Salon Bel-Air",
    "wof:placetype":"venue"
},
  "geometry": {"coordinates":[-79.020203,48.239361],"type":"Point"}
}