{
  "type": "Feature",
  "properties": {
    "iso:country":"CA",
    "sg:address":"822 Main St",
    "sg:city":"Woodstock",
    "sg:classifiers":[
        {
            "category":"Government",
            "subcategory":"Police Station",
            "type":"Public Place"
        }
    ],
    "sg:phone":"+1 506 325 4601",
    "sg:postcode":"E7M 2E8",
    "sg:province":"NB",
    "sg:tags":[
        "department"
    ],
    "wof:name":"Woodstock Police Dept",
    "wof:placetype":"venue"
},
  "geometry": {"coordinates":[-67.57437896730001,46.1630020142],"type":"Point"}
}