{
  "type": "Feature",
  "properties": {
    "iso:country":"CA",
    "sg:city":"Georgetown",
    "sg:classifiers":[
        {
            "category":"Personal",
            "subcategory":"Beauty Salon",
            "type":"Services"
        }
    ],
    "sg:phone":"+1 905 877 7222",
    "sg:postcode":"L7G 3H3",
    "sg:province":"ON",
    "wof:name":"Riviera Hair Stylists",
    "wof:placetype":"venue"
},
  "geometry": {"coordinates":[-79.93361663819999,43.6548728943],"type":"Point"}
}