{
  "type": "Feature",
  "properties": {
    "iso:country":"CA",
    "sg:address":"11624 120 St NW",
    "sg:city":"Edmonton",
    "sg:classifiers":[
        {
            "category":"Retail",
            "subcategory":"Repair Shop",
            "type":"Services"
        }
    ],
    "sg:phone":"+1 780 413 6600",
    "sg:postcode":"T5G 2Y2",
    "sg:province":"AB",
    "sg:tags":[
        "refinishing",
        "furniture"
    ],
    "wof:name":"Rgo Office Products Ltd",
    "wof:placetype":"venue"
},
  "geometry": {"coordinates":[-113.529533,53.568161],"type":"Point"}
}