{
  "type": "Feature",
  "properties": {
    "addr:full":"5613 Hwy 9 St Andrews MB R1A 2Y9",
    "addr:housenumber":"5613",
    "addr:postcode":"r1a 2y9",
    "addr:street":"Hwy 9",
    "iso:country":"CA",
    "sg:address":"5613 Hwy 9",
    "sg:city":"St Andrews",
    "sg:classifiers":[
        {
            "category":"Shopping",
            "subcategory":"Florist",
            "type":"Retail Goods"
        }
    ],
    "sg:phone":"+1 204 334 4919",
    "sg:postcode":"R1A 2Y9",
    "sg:province":"MB",
    "wof:name":"Elizabeth's Florist & Gifts",
    "wof:placetype":"venue"
},
  "geometry": {"coordinates":[-96.940567,50.136848],"type":"Point"}
}