{
  "type": "Feature",
  "properties": {
    "iso:country":"CA",
    "sg:address":"4310 Rue Belanger",
    "sg:city":"Montreal",
    "sg:classifiers":[
        {
            "category":"Restaurant",
            "type":"Food & Drink"
        }
    ],
    "sg:phone":"+1 514 729 5111",
    "sg:postcode":"H1T 1A7",
    "sg:province":"QC",
    "wof:name":"Restobar Chez Toutou",
    "wof:placetype":"venue"
},
  "geometry": {"coordinates":[-73.5855102539,45.5668334961],"type":"Point"}
}