{
  "type": "Feature",
  "properties": {
    "addr:full":"2652 Nicola Ave Merritt BC V1K 1B8",
    "addr:housenumber":"2652",
    "addr:postcode":"v1k 1b8",
    "addr:street":"Nicola Ave",
    "iso:country":"CA",
    "sg:address":"2652 Nicola Ave",
    "sg:city":"Merritt",
    "sg:classifiers":[
        {
            "category":"Travel",
            "subcategory":"Hotels & Motels",
            "type":"Entertainment"
        }
    ],
    "sg:phone":"+1 250 378 2352",
    "sg:postcode":"V1K 1B8",
    "sg:province":"BC",
    "wof:name":"All Seasons Motel",
    "wof:placetype":"venue"
},
  "geometry": {"coordinates":[-120.773933411,50.1079063416],"type":"Point"}
}