{
  "type": "Feature",
  "properties": {
    "addr:full":"6551 No. 3 Rd Richmond BC V6Y 2B6",
    "addr:postcode":"6551;v6y 2b6",
    "addr:street":"3 Rd",
    "iso:country":"CA",
    "sg:address":"6551 No. 3 Rd",
    "sg:city":"Richmond",
    "sg:classifiers":[
        {
            "category":"Professional",
            "subcategory":"Computer Services",
            "type":"Services"
        }
    ],
    "sg:phone":"+1 604 232 9790",
    "sg:postcode":"V6Y 2B6",
    "sg:province":"BC",
    "sg:tags":[
        "internet"
    ],
    "wof:name":"Surftime Internet Marketing",
    "wof:placetype":"venue"
},
  "geometry": {"coordinates":[-123.136657715,49.1663742065],"type":"Point"}
}