{
  "type": "Feature",
  "properties": {
    "addr:full":"69 4th Ave NE Swift Current SK S9H 2J1",
    "addr:housenumber":"69",
    "addr:postcode":"s9h 2j1",
    "addr:street":"4Th Ave Ne",
    "iso:country":"CA",
    "sg:address":"69 4th Ave NE",
    "sg:city":"Swift Current",
    "sg:classifiers":[
        {
            "category":"Retail",
            "subcategory":"Funeral Services",
            "type":"Services"
        }
    ],
    "sg:phone":"+1 306 773 2931",
    "sg:postcode":"S9H 2J1",
    "sg:province":"SK",
    "sg:tags":[
        "director"
    ],
    "wof:name":"Parkside Memorial Funeral Home",
    "wof:placetype":"venue"
},
  "geometry": {"coordinates":[-107.79428900000001,50.283043],"type":"Point"}
}