{
  "type": "Feature",
  "properties": {
    "addr:full":"3239 395 Rte N Amos QC J9T 3A1",
    "addr:housenumber":"3239",
    "addr:postcode":"j9t 3a1",
    "addr:street":"395 Rte N Amos",
    "iso:country":"CA",
    "sg:address":"3239 395 Rte N",
    "sg:city":"Amos",
    "sg:classifiers":[
        {
            "category":"Utilities",
            "subcategory":"Refuse",
            "type":"Services"
        }
    ],
    "sg:phone":"+1 819 732 8833",
    "sg:postcode":"J9T 3A1",
    "sg:province":"QC",
    "sg:tags":[
        "garbage",
        "collection"
    ],
    "wof:name":"Sanimos Inc",
    "wof:placetype":"venue"
},
  "geometry": {"coordinates":[-78.028549,48.603336],"type":"Point"}
}