{
  "type": "Feature",
  "properties": {
    "addr:full":"244 Bain Ave Toronto ON M4K 1G3",
    "addr:housenumber":"244",
    "addr:postcode":"m4k 1g3",
    "addr:street":"Bain Ave",
    "iso:country":"CA",
    "sg:address":"244 Bain Ave",
    "sg:city":"Toronto",
    "sg:classifiers":[
        {
            "category":"Organizations",
            "subcategory":"Non-profit Organization",
            "type":"Services"
        }
    ],
    "sg:phone":"+1 416 461 4872",
    "sg:postcode":"M4K 1G3",
    "sg:province":"ON",
    "sg:tags":[
        "corporate",
        "program",
        "health"
    ],
    "wof:name":"Barb Gormley Fitness Cnsltng",
    "wof:placetype":"venue"
},
  "geometry": {"coordinates":[-79.34404754640001,43.6727180481],"type":"Point"}
}