{
  "type": "Feature",
  "properties": {
    "addr:full":"216 Main St N Exeter ON N0M 1S3",
    "addr:housenumber":"216",
    "addr:postcode":"n0m 1s3",
    "addr:street":"Main St N",
    "iso:country":"CA",
    "sg:address":"216 Main St N",
    "sg:city":"Exeter",
    "sg:classifiers":[
        {
            "category":"Government",
            "subcategory":"Fire Station",
            "type":"Public Place"
        }
    ],
    "sg:phone":"+1 ",
    "sg:postcode":"N0M 1S3",
    "sg:province":"ON",
    "sg:tags":[
        "department"
    ],
    "wof:name":"Exeter Fire Dept",
    "wof:placetype":"venue"
},
  "geometry": {"coordinates":[-81.483795,43.362198],"type":"Point"}
}