{
  "type": "Feature",
  "properties": {
    "addr:full":"1000 Miramichi Ave Bathurst NB E2A 1X8",
    "addr:housenumber":"1000",
    "addr:postcode":"e2a 1x8",
    "addr:street":"Miramichi Ave",
    "iso:country":"CA",
    "sg:address":"1000 Miramichi Ave",
    "sg:city":"Bathurst",
    "sg:classifiers":[
        {
            "category":"Building & Trades",
            "subcategory":"Construction",
            "type":"Services"
        }
    ],
    "sg:phone":"+1 506 548 3747",
    "sg:postcode":"E2A 1X8",
    "sg:province":"NB",
    "sg:tags":[
        "home",
        "improvement"
    ],
    "wof:name":"Bayshore Renovators",
    "wof:placetype":"venue"
},
  "geometry": {"coordinates":[-65.63455999999999,47.612648],"type":"Point"}
}