{
  "type": "Feature",
  "properties": {
    "addr:full":"1107 Kramer Blvd Regina SK S4S 5W4",
    "addr:housenumber":"1107",
    "addr:postcode":"s4s 5w4",
    "addr:street":"Kramer Blvd",
    "iso:country":"CA",
    "sg:address":"1107 Kramer Blvd",
    "sg:city":"Regina",
    "sg:classifiers":[
        {
            "category":"Autos & Motor Vehicles",
            "subcategory":"Fuel & Gas Station",
            "type":"Retail Goods"
        }
    ],
    "sg:phone":"+1 306 586 4675",
    "sg:postcode":"S4S 5W4",
    "sg:province":"SK",
    "sg:tags":[
        "oil"
    ],
    "wof:name":"Kramer Mowhawk",
    "wof:placetype":"venue"
},
  "geometry": {"coordinates":[-104.59571099999999,50.415424],"type":"Point"}
}