{
  "type": "Feature",
  "properties": {
    "addr:full":"2402 Gottselig Rd N Regina SK S4R 8R7",
    "addr:housenumber":"2402",
    "addr:postcode":"s4r 8r7",
    "addr:street":"Gottselig Rd N",
    "iso:country":"CA",
    "sg:address":"2402 Gottselig Rd N",
    "sg:city":"Regina",
    "sg:classifiers":[
        {
            "category":"Building & Trades",
            "subcategory":"Construction",
            "type":"Services"
        }
    ],
    "sg:phone":"+1 306 543 7700",
    "sg:postcode":"S4R 8R7",
    "sg:province":"SK",
    "sg:tags":[
        "pipe",
        "lining",
        "coating",
        "sandblasting"
    ],
    "wof:name":"General Sandblasting & Paint",
    "wof:placetype":"venue"
},
  "geometry": {"coordinates":[-104.59517700000001,50.448013],"type":"Point"}
}