{
  "type": "Feature",
  "properties": {
    "addr:full":"2438 Edgar Cres Vancouver BC V6L 2G4",
    "addr:housenumber":"2438",
    "addr:postcode":"v6l 2g4",
    "addr:street":"Edgar Cres",
    "iso:country":"CA",
    "sg:address":"2438 Edgar Cres",
    "sg:city":"Vancouver",
    "sg:classifiers":[
        {
            "category":"Wholesale",
            "subcategory":"Durable Goods & Equipment",
            "type":"Manufacturing & Wholesale Goods"
        }
    ],
    "sg:phone":"+1 604 730 9400",
    "sg:postcode":"V6L 2G4",
    "sg:province":"BC",
    "sg:tags":[
        "representative",
        "manufacturer"
    ],
    "wof:name":"Bruce P Innes Ltd",
    "wof:placetype":"venue"
},
  "geometry": {"coordinates":[-123.161934,49.245869],"type":"Point"}
}