{
  "type": "Feature",
  "properties": {
    "addr:full":"600 Squier St Thunder Bay ON P7B 4A8",
    "addr:housenumber":"600",
    "addr:postcode":"p7b 4a8",
    "addr:street":"Squier St",
    "iso:country":"CA",
    "sg:address":"600 Squier St",
    "sg:city":"Thunder Bay",
    "sg:classifiers":[
        {
            "category":"Professional",
            "subcategory":"Printing & Photocopies",
            "type":"Services"
        }
    ],
    "sg:phone":"+1 807 344 9202",
    "sg:postcode":"P7B 4A8",
    "sg:province":"ON",
    "sg:tags":[
        "printer",
        "duplicating",
        "copying"
    ],
    "wof:name":"Citi Centre Print & Storage",
    "wof:placetype":"venue"
},
  "geometry": {"coordinates":[-89.2467498779,48.4163780212],"type":"Point"}
}