{
  "type": "Feature",
  "properties": {
    "addr:full":"510 Richardson Ave Ottawa ON K2B 5H1",
    "addr:housenumber":"510",
    "addr:postcode":"k2b 5h1",
    "addr:street":"Richardson Ave",
    "iso:country":"CA",
    "sg:address":"510 Richardson Ave",
    "sg:city":"Ottawa",
    "sg:classifiers":[
        {
            "category":"Shopping",
            "subcategory":"Used Merchandise",
            "type":"Retail Goods"
        }
    ],
    "sg:phone":"+1 613 828 6198",
    "sg:postcode":"K2B 5H1",
    "sg:province":"ON",
    "sg:tags":[
        "shop",
        "consignment"
    ],
    "wof:name":"Clothes Cupboard",
    "wof:placetype":"venue"
},
  "geometry": {"coordinates":[-75.77722900000001,45.368259],"type":"Point"}
}