{
  "type": "Feature",
  "properties": {
    "addr:full":"Newmarket ON L3Y 8E1",
    "addr:postcode":"l3y 8e1",
    "iso:country":"CA",
    "sg:city":"Newmarket",
    "sg:classifiers":[
        {
            "category":"Retail",
            "subcategory":"Car Wash",
            "type":"Services"
        }
    ],
    "sg:phone":"+1 905 830 1793",
    "sg:postcode":"L3Y 8E1",
    "sg:province":"ON",
    "sg:tags":[
        "polishing",
        "washing"
    ],
    "wof:name":"Carwash CO",
    "wof:placetype":"venue"
},
  "geometry": {"coordinates":[-79.42965700000001,44.05772],"type":"Point"}
}