{
  "type": "Feature",
  "properties": {
    "addr:full":"24 Seeley Dr North York ON M3M 2V6",
    "addr:housenumber":"24",
    "addr:postcode":"m3m 2v6",
    "addr:street":"Seeley Dr",
    "iso:country":"CA",
    "sg:address":"24 Seeley Dr",
    "sg:city":"North York",
    "sg:classifiers":[
        {
            "category":"Building & Trades",
            "subcategory":"Construction",
            "type":"Services"
        }
    ],
    "sg:phone":"+1 416 315 0301",
    "sg:postcode":"M3M 2V6",
    "sg:province":"ON",
    "sg:tags":[
        "painter"
    ],
    "wof:name":"Image Painting & Wallcoverings",
    "wof:placetype":"venue"
},
  "geometry": {"coordinates":[-79.492752,43.740997],"type":"Point"}
}