{
  "type": "Feature",
  "properties": {
    "addr:full":"250 Cardinal Cres Saskatoon SK S7L 6H8",
    "addr:housenumber":"250",
    "addr:postcode":"s7l 6h8",
    "addr:street":"Cardinal Cres",
    "iso:country":"CA",
    "sg:address":"250 Cardinal Cres",
    "sg:city":"Saskatoon",
    "sg:classifiers":[
        {
            "category":"Organizations",
            "subcategory":"Labor Organization",
            "type":"Services"
        }
    ],
    "sg:phone":"+1 306 382 8262",
    "sg:postcode":"S7L 6H8",
    "sg:province":"SK",
    "wof:name":"Canadian Union Public Emplys",
    "wof:placetype":"venue"
},
  "geometry": {"coordinates":[-106.687462,52.154198],"type":"Point"}
}