{
  "type": "Feature",
  "properties": {
    "addr:full":"Toronto ON M5J 2G4",
    "addr:postcode":"m5j 2g4",
    "iso:country":"CA",
    "sg:city":"Toronto",
    "sg:classifiers":[
        {
            "category":"Cinema",
            "subcategory":"Movie Rental",
            "type":"Entertainment"
        }
    ],
    "sg:phone":"+1 416 363 6363",
    "sg:postcode":"M5J 2G4",
    "sg:province":"ON",
    "sg:tags":[
        "leasing",
        "video",
        "disc",
        "tape"
    ],
    "wof:name":"Video Store",
    "wof:placetype":"venue"
},
  "geometry": {"coordinates":[-79.3773803711,43.6407356262],"type":"Point"}
}