{
  "type": "Feature",
  "properties": {
    "addr:full":"Calgary AB T2H 0J9",
    "addr:postcode":"t2h 0j9",
    "iso:country":"CA",
    "sg:city":"Calgary",
    "sg:classifiers":[
        {
            "category":"Real Estate",
            "subcategory":"Real Estate Agent",
            "type":"Services"
        }
    ],
    "sg:phone":"+1 403 253 3016",
    "sg:postcode":"T2H 0J9",
    "sg:province":"AB",
    "sg:tags":[
        "management"
    ],
    "wof:name":"Hart Property Management Ltd",
    "wof:placetype":"venue"
},
  "geometry": {"coordinates":[-114.07192999999999,51.002327],"type":"Point"}
}