{
  "type": "Feature",
  "properties": {
    "addr:full":"PO Box 77 Lumsden NL A0G 3E0",
    "addr:housenumber":"po box 77",
    "addr:postcode":"a0g 3e0",
    "iso:country":"CA",
    "sg:address":"PO Box 77",
    "sg:city":"Lumsden",
    "sg:classifiers":[
        {
            "category":"Building & Trades",
            "subcategory":"Construction",
            "type":"Services"
        }
    ],
    "sg:phone":"+1 709 530 2232",
    "sg:postcode":"A0G 3E0",
    "sg:province":"NL",
    "sg:tags":[
        "general",
        "contractor"
    ],
    "wof:name":"Goodyear Trucking Ltd",
    "wof:placetype":"venue"
},
  "geometry": {"coordinates":[-53.603638,49.296249],"type":"Point"}
}