{
  "type": "Feature",
  "properties": {
    "addr:full":"7 Anne St S # 6 Barrie ON L4N 2C4",
    "addr:housenumber":"7",
    "addr:postcode":"l4n 2c4",
    "addr:street":"Anne St S # 6",
    "iso:country":"CA",
    "sg:address":"7 Anne St S # 6",
    "sg:city":"Barrie",
    "sg:classifiers":[
        {
            "category":"Personal",
            "type":"Services"
        }
    ],
    "sg:phone":"+1 705 734 1516",
    "sg:postcode":"L4N 2C4",
    "sg:province":"ON",
    "sg:tags":[
        "therapist",
        "massage"
    ],
    "wof:name":"Oriental Spa",
    "wof:placetype":"venue"
},
  "geometry": {"coordinates":[-79.7046966553,44.382106781],"type":"Point"}
}