{
  "type": "Feature",
  "properties": {
    "addr:full":"12860 125 Rte Entrelacs QC J0T 2E0",
    "addr:housenumber":"12860",
    "addr:postcode":"j0t 2e0",
    "addr:street":"125 Rte",
    "iso:country":"CA",
    "sg:address":"12860 125 Rte",
    "sg:city":"Entrelacs",
    "sg:phone":"+1 450 228 2347",
    "sg:postcode":"J0T 2E0",
    "sg:province":"QC",
    "sg:tags":[
        "food",
        "equipment",
        "processing"
    ],
    "wof:name":"Expert Erable",
    "wof:placetype":"venue"
},
  "geometry": {"coordinates":[-74.0026855469,46.1097297668],"type":"Point"}
}