{
  "type": "Feature",
  "properties": {
    "addr:full":"Toronto ON M4W 3C8",
    "addr:postcode":"m4w 3c8",
    "iso:country":"CA",
    "sg:city":"Toronto",
    "sg:classifiers":[
        {
            "category":"Professional",
            "subcategory":"Art Services",
            "type":"Services"
        }
    ],
    "sg:phone":"+1 416 926 0888",
    "sg:postcode":"M4W 3C8",
    "sg:province":"ON",
    "sg:tags":[
        "artist"
    ],
    "wof:name":"Paul Berta Assoc Ltd",
    "wof:placetype":"venue"
},
  "geometry": {"coordinates":[-79.388435,43.673801],"type":"Point"}
}