{
  "type": "Feature",
  "properties": {
    "addr:full":"Port Coquitlam BC V3C 2A9",
    "addr:postcode":"v3c 2a9",
    "iso:country":"CA",
    "sg:city":"Port Coquitlam",
    "sg:classifiers":[
        {
            "category":"Health Services",
            "subcategory":"Doctor",
            "type":"Services"
        }
    ],
    "sg:phone":"+1 604 941 0111",
    "sg:postcode":"V3C 2A9",
    "sg:province":"BC",
    "sg:tags":[
        "dentist"
    ],
    "wof:name":"Bianco, T A DDS",
    "wof:placetype":"venue"
},
  "geometry": {"coordinates":[-122.778885,49.26202],"type":"Point"}
}