{
  "type": "Feature",
  "properties": {
    "addr:full":"800 Rue Des Carrieres Saint-Jean-Sur-Richelieu QC J3B 2P2",
    "addr:housenumber":"800",
    "addr:postcode":"j3b 2p2",
    "addr:street":"Rue Des Carrieres",
    "iso:country":"CA",
    "sg:address":"800 Rue Des Carrieres",
    "sg:city":"Saint-Jean-Sur-Richelieu",
    "sg:classifiers":[
        {
            "category":"Building & Trades",
            "subcategory":"Construction",
            "type":"Services"
        }
    ],
    "sg:phone":"+1 450 866 8333",
    "sg:postcode":"J3B 2P2",
    "sg:province":"QC",
    "sg:tags":[
        "general",
        "contractor"
    ],
    "wof:name":"P Baillargeon Ltee",
    "wof:placetype":"venue"
},
  "geometry": {"coordinates":[-73.29443359379999,45.303440094],"type":"Point"}
}