{
  "type": "Feature",
  "properties": {
    "addr:full":"3571 Rue Michel-Ange Montreal QC H2A 1J3",
    "addr:housenumber":"3571",
    "addr:postcode":"h2a 1j3",
    "addr:street":"Rue Michel-Ange",
    "iso:country":"CA",
    "sg:address":"3571 Rue Michel-Ange",
    "sg:city":"Montreal",
    "sg:classifiers":[
        {
            "category":"Building & Trades",
            "subcategory":"Electrical",
            "type":"Services"
        }
    ],
    "sg:phone":"+1 514 376 2224",
    "sg:postcode":"H2A 1J3",
    "sg:province":"QC",
    "sg:tags":[
        "electric",
        "contractor"
    ],
    "wof:name":"Valcourt Electrique Inc",
    "wof:placetype":"venue"
},
  "geometry": {"coordinates":[-73.5975036621,45.5631370544],"type":"Point"}
}