{
  "type": "Feature",
  "properties": {
    "addr:full":"880 Rue Du Pere-Champagnat Chicoutimi QC G7H 3P6",
    "addr:housenumber":"880",
    "addr:postcode":"g7h 3p6",
    "addr:street":"Rue Du Pere-Champagnat",
    "iso:country":"CA",
    "sg:address":"880 Rue Du Pere-Champagnat",
    "sg:city":"Chicoutimi",
    "sg:classifiers":[
        {
            "category":"Professional",
            "subcategory":"Business Services",
            "type":"Services"
        }
    ],
    "sg:phone":"+1 418 696 0262",
    "sg:postcode":"G7H 3P6",
    "sg:province":"QC",
    "sg:tags":[
        "adjuster",
        "insurance",
        "appraiser"
    ],
    "wof:name":"Dany Gagny Estimation Enr",
    "wof:placetype":"venue"
},
  "geometry": {"coordinates":[-71.0402755737,48.414730072],"type":"Point"}
}