{
  "type": "Feature",
  "properties": {
    "addr:full":"Toronto ON M5V 3A8",
    "addr:postcode":"m5v 3a8",
    "iso:country":"CA",
    "sg:city":"Toronto",
    "sg:classifiers":[
        {
            "category":"Professional",
            "subcategory":"Business Services",
            "type":"Services"
        }
    ],
    "sg:phone":"+1 416 586 0089",
    "sg:postcode":"M5V 3A8",
    "sg:province":"ON",
    "sg:tags":[
        "translator",
        "interpreter"
    ],
    "wof:name":"Dominion Translation",
    "wof:placetype":"venue"
},
  "geometry": {"coordinates":[-79.395088,43.64785],"type":"Point"}
}