{
  "type": "Feature",
  "properties": {
    "iso:country":"CA",
    "sg:address":"29623 Downes Rd",
    "sg:city":"Abbotsford",
    "sg:classifiers":[
        {
            "category":"Organizations",
            "subcategory":"Religious Organization",
            "type":"Services"
        }
    ],
    "sg:phone":"+1 604 856 6302",
    "sg:postcode":"V4X 1Z8",
    "sg:province":"BC",
    "sg:tags":[
        "church"
    ],
    "wof:name":"Church of God in Christ",
    "wof:placetype":"venue"
},
  "geometry": {"coordinates":[-122.400978,49.075142],"type":"Point"}
}