{
  "type": "Feature",
  "properties": {
    "addr:full":"29623 Downes Rd Abbotsford BC V4X 1Z8",
    "addr:housenumber":"29623",
    "addr:postcode":"v4x 1z8",
    "addr:street":"Downes Rd",
    "iso:country":"CA",
    "sg:address":"29623 Downes Rd",
    "sg:city":"Abbotsford",
    "sg:classifiers":[
        {
            "category":"Organizations",
            "subcategory":"Religious Organization",
            "type":"Services"
        }
    ],
    "sg:phone":"+1 604 856 6302",
    "sg:postcode":"V4X 1Z8",
    "sg:province":"BC",
    "sg:tags":[
        "church"
    ],
    "wof:name":"Church of God in Christ",
    "wof:placetype":"venue"
},
  "geometry": {"coordinates":[-122.40097799999999,49.075142],"type":"Point"}
}