{
  "type": "Feature",
  "properties": {
    "iso:country":"CA",
    "sg:address":"99 Second Ave N",
    "sg:city":"Williams Lake",
    "sg:classifiers":[
        {
            "category":"Home & Garden",
            "subcategory":"Furniture",
            "type":"Retail Goods"
        }
    ],
    "sg:phone":"+1 250 392 6933",
    "sg:postcode":"V2G 1Z3",
    "sg:province":"BC",
    "wof:name":"Laketown Furnishings Ltd",
    "wof:placetype":"venue"
},
  "geometry": {"coordinates":[-122.14405059800001,52.129737854],"type":"Point"}
}