{
  "type": "Feature",
  "properties": {
    "iso:country":"CA",
    "sg:address":"1000 Gorham St",
    "sg:city":"Newmarket",
    "sg:classifiers":[
        {
            "category":"Organizations",
            "subcategory":"Religious Organization",
            "type":"Services"
        }
    ],
    "sg:phone":"+1 905 895 8893",
    "sg:postcode":"L3Y 1L8",
    "sg:province":"ON",
    "sg:tags":[
        "church"
    ],
    "wof:name":"Cedarview Community Church",
    "wof:placetype":"venue"
},
  "geometry": {"coordinates":[-79.43315124510001,44.0559082031],"type":"Point"}
}