{
  "type": "Feature",
  "properties": {
    "addr:full":"Sussex NB E4E 2J1",
    "addr:postcode":"e4e 2j1",
    "iso:country":"CA",
    "sg:city":"Sussex",
    "sg:classifiers":[
        {
            "category":"Restaurant",
            "type":"Food & Drink"
        }
    ],
    "sg:phone":"+1 506 433 4898",
    "sg:postcode":"E4E 2J1",
    "sg:province":"NB",
    "wof:name":"Dandy's Family Restaurant",
    "wof:placetype":"venue"
},
  "geometry": {"coordinates":[-65.507744,45.722473],"type":"Point"}
}