{
  "type": "Feature",
  "properties": {
    "addr:full":"Lorraine QC J6Z 2Y7",
    "addr:postcode":"j6z 2y7",
    "iso:country":"CA",
    "sg:city":"Lorraine",
    "sg:classifiers":[
        {
            "category":"Manufacturing",
            "subcategory":"Metals",
            "type":"Manufacturing & Wholesale Goods"
        }
    ],
    "sg:phone":"+1 450 621 3555",
    "sg:postcode":"J6Z 2Y7",
    "sg:province":"QC",
    "sg:tags":[
        "coating"
    ],
    "wof:name":"Orange Metal Technologie",
    "wof:placetype":"venue"
},
  "geometry": {"coordinates":[-73.78266143800001,45.669719696],"type":"Point"}
}