{
  "type": "Feature",
  "properties": {
    "addr:full":"940 Ch Du Sault Saint-Romuald QC G6W 5M6",
    "addr:housenumber":"940",
    "addr:postcode":"g6w 5m6",
    "addr:street":"Ch Du Sault",
    "iso:country":"CA",
    "sg:address":"940 Ch Du Sault",
    "sg:city":"Saint-Romuald",
    "sg:classifiers":[
        {
            "category":"Travel",
            "subcategory":"Travel Agent",
            "type":"Entertainment"
        }
    ],
    "sg:phone":"+1 418 839 8433",
    "sg:postcode":"G6W 5M6",
    "sg:province":"QC",
    "sg:tags":[
        "agency",
        "bureau"
    ],
    "wof:name":"Voyages Funtastique",
    "wof:placetype":"venue"
},
  "geometry": {"coordinates":[-71.2692184448,46.7303543091],"type":"Point"}
}