{
  "type": "Feature",
  "properties": {
    "addr:full":"2813 Victoria Park Ave Scarborough ON M1W 1A1",
    "addr:housenumber":"2813",
    "addr:postcode":"m1w 1a1",
    "addr:street":"Victoria Park Ave",
    "iso:country":"CA",
    "sg:address":"2813 Victoria Park Ave",
    "sg:city":"Scarborough",
    "sg:classifiers":[
        {
            "category":"Health Services",
            "subcategory":"Doctor",
            "type":"Services"
        }
    ],
    "sg:phone":"+1 416 492 6598",
    "sg:postcode":"M1W 1A1",
    "sg:province":"ON",
    "sg:tags":[
        "clinic"
    ],
    "wof:name":"Health Reform",
    "wof:placetype":"venue"
},
  "geometry": {"coordinates":[-79.327095,43.784176],"type":"Point"}
}