{
  "type": "Feature",
  "properties": {
    "iso:country":"CA",
    "sg:address":"36 Elgin St",
    "sg:city":"Sudbury",
    "sg:classifiers":[
        {
            "category":"Government",
            "subcategory":"Office",
            "type":"Public Place"
        }
    ],
    "sg:phone":"+1 705 673 7107",
    "sg:postcode":"P3C 5B4",
    "sg:province":"ON",
    "wof:name":"Diane Marleau Deputee",
    "wof:placetype":"venue"
},
  "geometry": {"coordinates":[-80.9962844849,46.4936408997],"type":"Point"}
}