{
  "type": "Feature",
  "properties": {
    "addr:full":"Dollard-Des-Ormeaux QC H9B 2M9",
    "addr:postcode":"h9b 2m9",
    "iso:country":"CA",
    "sg:city":"Dollard-Des-Ormeaux",
    "sg:classifiers":[
        {
            "category":"Manufacturing",
            "subcategory":"Printing",
            "type":"Manufacturing & Wholesale Goods"
        }
    ],
    "sg:phone":"+1 514 684 7278",
    "sg:postcode":"H9B 2M9",
    "sg:province":"QC",
    "sg:tags":[
        "publisher",
        "art"
    ],
    "wof:name":"Alexandrium Fine Art",
    "wof:placetype":"venue"
},
  "geometry": {"coordinates":[-73.7880783081,45.4850578308],"type":"Point"}
}