{
  "type": "Feature",
  "properties": {
    "addr:full":"110 36 St NE Calgary AB T2A 7E6",
    "addr:housenumber":"36",
    "addr:postcode":"t2a 7e6",
    "addr:street":"110;St Ne",
    "iso:country":"CA",
    "sg:address":"110 36 St NE",
    "sg:city":"Calgary",
    "sg:classifiers":[
        {
            "category":"Autos & Motor Vehicles",
            "subcategory":"Fuel & Gas Station",
            "type":"Retail Goods"
        }
    ],
    "sg:phone":"+1 403 272 4038",
    "sg:postcode":"T2A 7E6",
    "sg:province":"AB",
    "sg:tags":[
        "oil"
    ],
    "wof:name":"Marlborough Esso Svc Plus Wash",
    "wof:placetype":"venue"
},
  "geometry": {"coordinates":[-113.981262,51.053051],"type":"Point"}
}