{
  "type": "Feature",
  "properties": {
    "addr:full":"10024 Biggs Ave Fort Mcmurray AB T9H 1S3",
    "addr:housenumber":"10024",
    "addr:postcode":"t9h 1s3",
    "addr:street":"Biggs Ave",
    "iso:country":"CA",
    "sg:address":"10024 Biggs Ave",
    "sg:city":"Fort Mcmurray",
    "sg:classifiers":[
        {
            "category":"Travel",
            "subcategory":"Hotels & Motels",
            "type":"Entertainment"
        }
    ],
    "sg:phone":"+1 780 743 3391",
    "sg:postcode":"T9H 1S3",
    "sg:province":"AB",
    "wof:name":"Twin Pine Motor Inn",
    "wof:placetype":"venue"
},
  "geometry": {"coordinates":[-111.38435363799999,56.7266082764],"type":"Point"}
}