{
  "type": "Feature",
  "properties": {
    "addr:full":"121 Queen St E Sault Ste Marie ON P6A 1Y6",
    "addr:housenumber":"121",
    "addr:postcode":"p6a 1y6",
    "addr:street":"Queen St E",
    "iso:country":"CA",
    "sg:address":"121 Queen St E",
    "sg:city":"Sault Ste Marie",
    "sg:classifiers":[
        {
            "category":"Retail",
            "subcategory":"Laundry & Dry Cleaning",
            "type":"Services"
        }
    ],
    "sg:phone":"+1 705 495 3344",
    "sg:postcode":"P6A 1Y6",
    "sg:province":"ON",
    "sg:tags":[
        "uniform",
        "rental",
        "mat",
        "matting"
    ],
    "wof:name":"G & K Svc",
    "wof:placetype":"venue"
},
  "geometry": {"coordinates":[-84.3392486572,46.5161399841],"type":"Point"}
}