{
  "type": "Feature",
  "properties": {
    "addr:full":"482 Russett Dr Arnprior ON K7S 3G8",
    "addr:housenumber":"482",
    "addr:postcode":"k7s 3g8",
    "addr:street":"Russett Dr",
    "iso:country":"CA",
    "sg:address":"482 Russett Dr",
    "sg:city":"Arnprior",
    "sg:classifiers":[
        {
            "category":"Building & Trades",
            "subcategory":"Landscaping Services",
            "type":"Services"
        }
    ],
    "sg:phone":"+1 613 623 5277",
    "sg:postcode":"K7S 3G8",
    "sg:province":"ON",
    "sg:tags":[
        "landscape",
        "contractor"
    ],
    "wof:name":"Mr Dirt Landscape Supplies",
    "wof:placetype":"venue"
},
  "geometry": {"coordinates":[-76.378677,45.422291],"type":"Point"}
}