{
  "type": "Feature",
  "properties": {
    "addr:full":"401 Hastings St W Vancouver BC V6B 1L5",
    "addr:housenumber":"401",
    "addr:postcode":"v6b 1l5",
    "addr:street":"Hastings St W",
    "iso:country":"CA",
    "sg:address":"401 Hastings St W",
    "sg:city":"Vancouver",
    "sg:classifiers":[
        {
            "category":"Organizations",
            "subcategory":"Religious Organization",
            "type":"Services"
        }
    ],
    "sg:phone":"+1 604 681 9121",
    "sg:postcode":"V6B 1L5",
    "sg:province":"BC",
    "sg:tags":[
        "church"
    ],
    "wof:name":"Church of Scientology of BC",
    "wof:placetype":"venue"
},
  "geometry": {"coordinates":[-123.110877991,49.283493042],"type":"Point"}
}