{
  "type": "Feature",
  "properties": {
    "addr:full":"10304 Alaska Rd Fort St John BC V1J 1A8",
    "addr:housenumber":"10304",
    "addr:postcode":"v1j 1a8",
    "addr:street":"Alaska Rd",
    "iso:country":"CA",
    "sg:address":"10304 Alaska Rd",
    "sg:city":"Fort St John",
    "sg:classifiers":[
        {
            "category":"Utilities",
            "subcategory":"Fuel Oil & Lpg",
            "type":"Services"
        }
    ],
    "sg:phone":"+1 250 785 5000",
    "sg:postcode":"V1J 1A8",
    "sg:province":"BC",
    "sg:tags":[
        "propane",
        "gas"
    ],
    "wof:name":"Joy Propane Ltd",
    "wof:placetype":"venue"
},
  "geometry": {"coordinates":[-120.852096558,56.2389526367],"type":"Point"}
}