{
  "type": "Feature",
  "properties": {
    "addr:full":"267 Main St Liverpool NS B0T 1K0",
    "addr:housenumber":"267",
    "addr:postcode":"b0t 1k0",
    "addr:street":"Main St",
    "iso:country":"CA",
    "sg:address":"267 Main St",
    "sg:city":"Liverpool",
    "sg:classifiers":[
        {
            "category":"Government",
            "subcategory":"Office",
            "type":"Public Place"
        }
    ],
    "sg:phone":"+1 902 354 2933",
    "sg:postcode":"B0T 1K0",
    "sg:province":"NS",
    "wof:name":"Queens Regional Housing Auth",
    "wof:placetype":"venue"
},
  "geometry": {"coordinates":[-64.716171,44.038532],"type":"Point"}
}