{
  "type": "Feature",
  "properties": {
    "addr:full":"Sillery QC G1S 1T8",
    "addr:postcode":"g1s 1t8",
    "iso:country":"CA",
    "sg:city":"Sillery",
    "sg:classifiers":[
        {
            "category":"Health Services",
            "subcategory":"Health Practitioner",
            "type":"Services"
        }
    ],
    "sg:phone":"+1 418 527 2507",
    "sg:postcode":"G1S 1T8",
    "sg:province":"QC",
    "sg:tags":[
        "nurse",
        "registry"
    ],
    "wof:name":"Ordre Regionale Des Infirieres",
    "wof:placetype":"venue"
},
  "geometry": {"coordinates":[-71.239440918,46.796787262],"type":"Point"}
}