{
  "type": "Feature",
  "properties": {
    "addr:full":"1610 1st St N Brandon MB R7C 1A4",
    "addr:housenumber":"1610",
    "addr:postcode":"r7c 1a4",
    "addr:street":"1St St N",
    "iso:country":"CA",
    "sg:address":"1610 1st St N",
    "sg:city":"Brandon",
    "sg:classifiers":[
        {
            "category":"Autos & Motor Vehicles",
            "subcategory":"Automobile Sales",
            "type":"Retail Goods"
        }
    ],
    "sg:phone":"+1 204 727 4043",
    "sg:postcode":"R7C 1A4",
    "sg:province":"MB",
    "sg:tags":[
        "car",
        "dealer"
    ],
    "wof:name":"A B Auto Sales",
    "wof:placetype":"venue"
},
  "geometry": {"coordinates":[-99.9392547607,49.87758255],"type":"Point"}
}