{
  "type": "Feature",
  "properties": {
    "addr:full":"Etobicoke ON M9W 4Y6",
    "addr:postcode":"m9w 4y6",
    "iso:country":"CA",
    "sg:city":"Etobicoke",
    "sg:classifiers":[
        {
            "category":"Professional",
            "subcategory":"Computer Services",
            "type":"Services"
        }
    ],
    "sg:phone":"+1 416 674 0225",
    "sg:postcode":"M9W 4Y6",
    "sg:province":"ON",
    "sg:tags":[
        "internet"
    ],
    "wof:name":"Solucom Inc",
    "wof:placetype":"venue"
},
  "geometry": {"coordinates":[-79.585762,43.679497],"type":"Point"}
}