{
  "type": "Feature",
  "properties": {
    "iso:country":"CA",
    "sg:city":"Rankin Inlet",
    "sg:classifiers":[
        {
            "category":"Airline",
            "type":"Transportation"
        }
    ],
    "sg:phone":"+1 867 645 2746",
    "sg:postcode":"X0C 0G0",
    "sg:province":"NU",
    "sg:tags":[
        "company"
    ],
    "wof:name":"Canadian North",
    "wof:placetype":"venue"
},
  "geometry": {"coordinates":[-92.08335113530001,62.8071403503],"type":"Point"}
}