{
  "type": "Feature",
  "properties": {
    "addr:full":"3613 55 St NE Calgary AB T1Y 4B4",
    "addr:housenumber":"3613",
    "addr:postcode":"t1y 4b4",
    "addr:street":"55 St Ne",
    "iso:country":"CA",
    "sg:address":"3613 55 St NE",
    "sg:city":"Calgary",
    "sg:classifiers":[
        {
            "category":"Building & Trades",
            "subcategory":"Construction",
            "type":"Services"
        }
    ],
    "sg:phone":"+1 403 280 6352",
    "sg:postcode":"T1Y 4B4",
    "sg:province":"AB",
    "sg:tags":[
        "painter"
    ],
    "wof:name":"John Mazury Painting & Decor",
    "wof:placetype":"venue"
},
  "geometry": {"coordinates":[-113.95443,51.086464],"type":"Point"}
}