{
  "type": "Feature",
  "properties": {
    "addr:full":"3470 Boul Des Entreprises Terrebonne QC J6X 4J8",
    "addr:housenumber":"3470",
    "addr:postcode":"j6x 4j8",
    "addr:street":"Boul Des Entreprises",
    "iso:country":"CA",
    "sg:address":"3470 Boul Des Entreprises",
    "sg:city":"Terrebonne",
    "sg:classifiers":[
        {
            "category":"Manufacturing",
            "subcategory":"Tools & Machinery",
            "type":"Manufacturing & Wholesale Goods"
        }
    ],
    "sg:phone":"+1 450 968 8896",
    "sg:postcode":"J6X 4J8",
    "sg:province":"QC",
    "sg:tags":[
        "equipment",
        "welding",
        "supply"
    ],
    "wof:name":"Techno-Controle Cybernmetique",
    "wof:placetype":"venue"
},
  "geometry": {"coordinates":[-73.6815032959,45.7284698486],"type":"Point"}
}