{
  "type": "Feature",
  "properties": {
    "addr:full":"930 Rossland Ave Trail BC V1R 3N6",
    "addr:housenumber":"930",
    "addr:postcode":"bc v1r 3n6",
    "addr:street":"Rossland Ave Trail",
    "iso:country":"CA",
    "sg:address":"930 Rossland Ave",
    "sg:city":"Trail",
    "sg:classifiers":[
        {
            "category":"Shopping",
            "subcategory":"Bicycles & Sporting Goods",
            "type":"Retail Goods"
        }
    ],
    "sg:phone":"+1 250 364 1661",
    "sg:postcode":"V1R 3N6",
    "sg:province":"BC",
    "wof:name":"Gerick Cycle & Sports",
    "wof:placetype":"venue"
},
  "geometry": {"coordinates":[-117.71523999999999,49.096474],"type":"Point"}
}