{
  "type": "Feature",
  "properties": {
    "addr:full":"Gaspe QC G4X 5E7",
    "addr:postcode":"g4x 5e7",
    "iso:country":"CA",
    "sg:city":"Gaspe",
    "sg:classifiers":[
        {
            "category":"Home & Garden",
            "subcategory":"Household Appliances",
            "type":"Retail Goods"
        }
    ],
    "sg:phone":"+1 418 269 7377",
    "sg:postcode":"G4X 5E7",
    "sg:province":"QC",
    "sg:tags":[
        "cleaners",
        "vacuum"
    ],
    "wof:name":"Aspirateur Plus Enr",
    "wof:placetype":"venue"
},
  "geometry": {"coordinates":[-64.480667,48.831451],"type":"Point"}
}