{
  "type": "Feature",
  "properties": {
    "iso:country":"CA",
    "sg:city":"Richmond",
    "sg:classifiers":[
        {
            "category":"Retail",
            "subcategory":"Auto Repair",
            "type":"Services"
        }
    ],
    "sg:phone":"+1 604 276 9688",
    "sg:postcode":"V6X 1V5",
    "sg:province":"BC",
    "sg:tags":[
        "repairing",
        "automobile"
    ],
    "wof:name":"Rich-Tek Industries Ltd",
    "wof:placetype":"venue"
},
  "geometry": {"coordinates":[-123.126594544,49.1936912537],"type":"Point"}
}