{
  "type": "Feature",
  "properties": {
    "addr:full":"Brantford ON N3S 7W3",
    "addr:postcode":"n3s 7w3",
    "iso:country":"CA",
    "sg:city":"Brantford",
    "sg:classifiers":[
        {
            "category":"Manufacturing",
            "subcategory":"Metals",
            "type":"Manufacturing & Wholesale Goods"
        }
    ],
    "sg:phone":"+1 519 753 2226",
    "sg:postcode":"N3S 7W3",
    "sg:province":"ON",
    "sg:tags":[
        "concrete",
        "reinforcement"
    ],
    "wof:name":"Vulkan Harex Steelfiber Inc",
    "wof:placetype":"venue"
},
  "geometry": {"coordinates":[-80.217491,43.157444],"type":"Point"}
}