{
  "type": "Feature",
  "properties": {
    "iso:country":"CA",
    "sg:address":"2077 Pitt St",
    "sg:city":"Cornwall",
    "sg:classifiers":[
        {
            "category":"Organizations",
            "subcategory":"Religious Organization",
            "type":"Services"
        }
    ],
    "sg:phone":"+1 613 937 4022",
    "sg:postcode":"K6J 5G2",
    "sg:province":"ON",
    "sg:tags":[
        "church"
    ],
    "wof:name":"Kingdon Hall of Jehovah Wtnss",
    "wof:placetype":"venue"
},
  "geometry": {"coordinates":[-74.7532119751,45.0494232178],"type":"Point"}
}