{
  "type": "Feature",
  "properties": {
    "iso:country":"CA",
    "sg:address":"93 Av Lindsay",
    "sg:city":"Dorval",
    "sg:phone":"+1 514 633 8228",
    "sg:postcode":"H9P 2S6",
    "sg:province":"QC",
    "sg:tags":[
        "oil"
    ],
    "wof:name":"Safety Kleen",
    "wof:placetype":"venue"
},
  "geometry": {"coordinates":[-73.7250823975,45.4555511475],"type":"Point"}
}