{
  "type": "Feature",
  "properties": {
    "addr:full":"1964 Loch Lomond Rd Saint John NB E2J 2A3",
    "addr:housenumber":"1964",
    "addr:postcode":"e2j 2a3",
    "addr:street":"Loch Lomond Rd",
    "iso:country":"CA",
    "sg:address":"1964 Loch Lomond Rd",
    "sg:city":"Saint John",
    "sg:classifiers":[
        {
            "category":"Retail",
            "subcategory":"Veterinary Services",
            "type":"Services"
        }
    ],
    "sg:phone":"+1 506 696 2550",
    "sg:postcode":"E2J 2A3",
    "sg:province":"NB",
    "sg:tags":[
        "veterinarian"
    ],
    "wof:name":"Loch Lomond Veterinary Hosp",
    "wof:placetype":"venue"
},
  "geometry": {"coordinates":[-65.966469,45.31292],"type":"Point"}
}