{
  "type": "Feature",
  "properties": {
    "addr:full":"550 Kay Rd Mckees Mills NB E4V 2S4",
    "addr:housenumber":"550",
    "addr:postcode":"e4v 2s4",
    "addr:street":"Kay Rd",
    "iso:country":"CA",
    "sg:address":"550 Kay Rd",
    "sg:city":"Mckees Mills",
    "sg:classifiers":[
        {
            "category":"Professional",
            "subcategory":"Art Services",
            "type":"Services"
        }
    ],
    "sg:phone":"+1 506 525 2874",
    "sg:postcode":"E4V 2S4",
    "sg:province":"NB",
    "sg:tags":[
        "graphic",
        "printer",
        "designer"
    ],
    "wof:name":"True Imaging & Design",
    "wof:placetype":"venue"
},
  "geometry": {"coordinates":[-64.71347,46.427784],"type":"Point"}
}