{
  "type": "Feature",
  "properties": {
    "addr:full":"3646 Solina Rd Bowmanville ON L1C 3K4",
    "addr:housenumber":"3646",
    "addr:postcode":"l1c 3k4",
    "addr:street":"Solina Rd",
    "iso:country":"CA",
    "sg:address":"3646 Solina Rd",
    "sg:city":"Bowmanville",
    "sg:classifiers":[
        {
            "category":"Building & Trades",
            "subcategory":"Landscaping Services",
            "type":"Services"
        }
    ],
    "sg:phone":"+1 905 434 2711",
    "sg:postcode":"L1C 3K4",
    "sg:province":"ON",
    "sg:tags":[
        "landscape",
        "contractor"
    ],
    "wof:name":"Wiggans Landscaping",
    "wof:placetype":"venue"
},
  "geometry": {"coordinates":[-78.68847700000001,43.913834],"type":"Point"}
}