{
  "type": "Feature",
  "properties": {
    "iso:country":"CA",
    "sg:city":"Langley",
    "sg:classifiers":[
        {
            "category":"Shopping",
            "subcategory":"Jewelry",
            "type":"Retail Goods"
        }
    ],
    "sg:phone":"+1 604 534 1661",
    "sg:postcode":"V3A 4G4",
    "sg:province":"BC",
    "sg:tags":[
        "jeweler"
    ],
    "wof:name":"Heritage Jewellers Ltd",
    "wof:placetype":"venue"
},
  "geometry": {"coordinates":[-122.650551,49.103565],"type":"Point"}
}