{
  "type": "Feature",
  "properties": {
    "iso:country":"CA",
    "sg:city":"Sudbury",
    "sg:classifiers":[
        {
            "category":"Manufacturing",
            "subcategory":"Food",
            "type":"Manufacturing & Wholesale Goods"
        }
    ],
    "sg:phone":"+1 705 525 2700",
    "sg:postcode":"P3A 5K6",
    "sg:province":"ON",
    "sg:tags":[
        "tea",
        "coffee",
        "product"
    ],
    "wof:name":"Coffee Mill",
    "wof:placetype":"venue"
},
  "geometry": {"coordinates":[-80.929901,46.512367],"type":"Point"}
}