{
  "type": "Feature",
  "properties": {
    "addr:full":"3475 Boul DE LA Cote-Vertu Saint-Laurent QC H4R 1R2",
    "addr:housenumber":"3475",
    "addr:postcode":"h4r 1r2",
    "addr:street":"Boul De La Cote-Vertu",
    "iso:country":"CA",
    "sg:address":"3475 Boul DE LA Cote-Vertu",
    "sg:city":"Saint-Laurent",
    "sg:classifiers":[
        {
            "category":"Home & Garden",
            "subcategory":"Home Furnishings",
            "type":"Retail Goods"
        }
    ],
    "sg:phone":"+1 514 334 4440",
    "sg:postcode":"H4R 1R2",
    "sg:province":"QC",
    "sg:tags":[
        "item",
        "boutique",
        "made",
        "drapery"
    ],
    "wof:name":"Jostar Decor",
    "wof:placetype":"venue"
},
  "geometry": {"coordinates":[-73.7074508667,45.4948997498],"type":"Point"}
}