{
  "type": "Feature",
  "properties": {
    "addr:full":"835 Stone Church Rd E Hamilton ON L8W 1R8",
    "addr:housenumber":"835",
    "addr:postcode":"l8w 1r8",
    "addr:street":"Stone Church Rd E",
    "iso:country":"CA",
    "sg:address":"835 Stone Church Rd E",
    "sg:city":"Hamilton",
    "sg:classifiers":[
        {
            "category":"Organizations",
            "subcategory":"Religious Organization",
            "type":"Services"
        }
    ],
    "sg:phone":"+1 905 389 3618",
    "sg:postcode":"L8W 1R8",
    "sg:province":"ON",
    "sg:tags":[
        "church"
    ],
    "wof:name":"Salvation Army",
    "wof:placetype":"venue"
},
  "geometry": {"coordinates":[-79.852417,43.202076],"type":"Point"}
}