{
  "type": "Feature",
  "properties": {
    "addr:full":"43 Andrew St Campbellton NB E3N 2B6",
    "addr:housenumber":"43",
    "addr:postcode":"e3n 2b6",
    "addr:street":"Andrew St",
    "iso:country":"CA",
    "sg:address":"43 Andrew St",
    "sg:city":"Campbellton",
    "sg:classifiers":[
        {
            "category":"Organizations",
            "subcategory":"Religious Organization",
            "type":"Services"
        }
    ],
    "sg:phone":"+1 506 789 1881",
    "sg:postcode":"E3N 2B6",
    "sg:province":"NB",
    "sg:tags":[
        "church"
    ],
    "wof:name":"St Thomas Aquinas Catholic Ch",
    "wof:placetype":"venue"
},
  "geometry": {"coordinates":[-66.6711807251,48.0024032593],"type":"Point"}
}