{
  "type": "Feature",
  "properties": {
    "addr:full":"Kentville NS B4N 3V8",
    "addr:postcode":"b4n 3v8",
    "iso:country":"CA",
    "sg:city":"Kentville",
    "sg:classifiers":[
        {
            "category":"Food & Beverages",
            "subcategory":"Groceries & Convenience Stores",
            "type":"Retail Goods"
        }
    ],
    "sg:phone":"+1 902 678 9362",
    "sg:postcode":"B4N 3V8",
    "sg:province":"NS",
    "wof:name":"D & A Convenience",
    "wof:placetype":"venue"
},
  "geometry": {"coordinates":[-64.492577,45.072224],"type":"Point"}
}