{
  "type": "Feature",
  "properties": {
    "addr:full":"41 West Ave N Hamilton ON L8L 5C1",
    "addr:housenumber":"41",
    "addr:postcode":"l8l 5c1",
    "addr:street":"West Ave N",
    "iso:country":"CA",
    "sg:address":"41 West Ave N",
    "sg:city":"Hamilton",
    "sg:classifiers":[
        {
            "category":"Professional",
            "subcategory":"Printing & Photocopies",
            "type":"Services"
        }
    ],
    "sg:phone":"+1 905 527 2753",
    "sg:postcode":"L8L 5C1",
    "sg:province":"ON",
    "sg:tags":[
        "duplicating",
        "copying"
    ],
    "wof:name":"Printing House Ltd",
    "wof:placetype":"venue"
},
  "geometry": {"coordinates":[-79.857674,43.254749],"type":"Point"}
}