{
  "type": "Feature",
  "properties": {
    "addr:full":"450 City Centre Kitimat BC V8C 1T6",
    "addr:housenumber":"450",
    "addr:postcode":"bc v8c 1t6",
    "addr:street":"City",
    "iso:country":"CA",
    "sg:address":"450 City Centre",
    "sg:city":"Kitimat",
    "sg:classifiers":[
        {
            "category":"Government",
            "subcategory":"Office",
            "type":"Public Place"
        }
    ],
    "sg:phone":"+1 250 632 7611",
    "sg:postcode":"V8C 1T6",
    "sg:province":"BC",
    "wof:name":"Canada Customs Dept",
    "wof:placetype":"venue"
},
  "geometry": {"coordinates":[-128.65541076700001,54.0533256531],"type":"Point"}
}