{
  "type": "Feature",
  "properties": {
    "addr:full":"209 Christina St N Sarnia ON N7T 5V1",
    "addr:housenumber":"209",
    "addr:postcode":"n7t 5v1",
    "addr:street":"Christina St N",
    "iso:country":"CA",
    "sg:address":"209 Christina St N",
    "sg:city":"Sarnia",
    "sg:classifiers":[
        {
            "category":"Shopping",
            "subcategory":"Florist",
            "type":"Retail Goods"
        }
    ],
    "sg:phone":"+1 519 344 2437",
    "sg:postcode":"N7T 5V1",
    "sg:province":"ON",
    "wof:name":"Mac Kellar's Flowers Ltd",
    "wof:placetype":"venue"
},
  "geometry": {"coordinates":[-82.407059,42.973732],"type":"Point"}
}