{
  "type": "Feature",
  "properties": {
    "addr:full":"220 Boul Harwood Vaudreuil-Dorion QC J7V 1Y4",
    "addr:housenumber":"220",
    "addr:postcode":"j7v 1y4",
    "addr:street":"Boul Harwood",
    "iso:country":"CA",
    "sg:address":"220 Boul Harwood",
    "sg:city":"Vaudreuil-Dorion",
    "sg:classifiers":[
        {
            "category":"Autos & Motor Vehicles",
            "subcategory":"Automobile Sales",
            "type":"Retail Goods"
        }
    ],
    "sg:phone":"+1 450 424 8070",
    "sg:postcode":"J7V 1Y4",
    "sg:province":"QC",
    "sg:tags":[
        "car",
        "dealer"
    ],
    "wof:name":"Automobiles S Lefrancois",
    "wof:placetype":"venue"
},
  "geometry": {"coordinates":[-74.013306,45.382095],"type":"Point"}
}