{
  "type": "Feature",
  "properties": {
    "addr:full":"4427 58 St NE Calgary AB T1Y 4G3",
    "addr:housenumber":"4427",
    "addr:postcode":"t1y 4g3",
    "addr:street":"58 St Ne",
    "iso:country":"CA",
    "sg:address":"4427 58 St NE",
    "sg:city":"Calgary",
    "sg:classifiers":[
        {
            "category":"Social Services",
            "subcategory":"Child Care",
            "type":"Services"
        }
    ],
    "sg:phone":"+1 403 285 2467",
    "sg:postcode":"T1Y 4G3",
    "sg:province":"AB",
    "wof:name":"Coral Springs Childcare Soc",
    "wof:placetype":"venue"
},
  "geometry": {"coordinates":[-113.94893646200001,51.0918083191],"type":"Point"}
}