{
  "type": "Feature",
  "properties": {
    "addr:full":"39 Cote Del'Eglise Notre-Dame-Des-Bois QC J0B 2E0",
    "addr:housenumber":"39",
    "addr:postcode":"j0b 2e0",
    "addr:street":"Cote Del'Eglise",
    "iso:country":"CA",
    "sg:address":"39 Cote Del'Eglise",
    "sg:city":"Notre-Dame-Des-Bois",
    "sg:classifiers":[
        {
            "category":"Government",
            "subcategory":"Office",
            "type":"Public Place"
        }
    ],
    "sg:phone":"+1 819 888 2502",
    "sg:postcode":"J0B 2E0",
    "sg:province":"QC",
    "sg:tags":[
        "village"
    ],
    "wof:name":"Notre-Dame Des Bois Garage",
    "wof:placetype":"venue"
},
  "geometry": {"coordinates":[-71.058716,45.387165],"type":"Point"}
}