{
  "type": "Feature",
  "properties": {
    "addr:full":"1105 Wellington Rd # 93 London ON N6E 1V4",
    "addr:housenumber":"1105",
    "addr:postcode":"n6e 1v4",
    "addr:street":"Wellington Rd # 93",
    "iso:country":"CA",
    "sg:address":"1105 Wellington Rd # 93",
    "sg:city":"London",
    "sg:classifiers":[
        {
            "category":"Shopping",
            "subcategory":"Bicycles & Sporting Goods",
            "type":"Retail Goods"
        }
    ],
    "sg:phone":"+1 519 649 6736",
    "sg:postcode":"N6E 1V4",
    "sg:province":"ON",
    "wof:name":"Sport Chek",
    "wof:placetype":"venue"
},
  "geometry": {"coordinates":[-81.221642,42.931622],"type":"Point"}
}