{
  "type": "Feature",
  "properties": {
    "addr:full":"4040 Rue DE Longueval Cap-Rouge QC G1Y 1M9",
    "addr:housenumber":"4040",
    "addr:postcode":"g1y 1m9",
    "addr:street":"Rue De Longueval",
    "iso:country":"CA",
    "sg:address":"4040 Rue DE Longueval",
    "sg:city":"Cap-Rouge",
    "sg:classifiers":[
        {
            "category":"Health Services",
            "subcategory":"Chiropractor",
            "type":"Services"
        }
    ],
    "sg:phone":"+1 418 653 4668",
    "sg:postcode":"G1Y 1M9",
    "sg:province":"QC",
    "wof:name":"Larochelle, Jacques DC",
    "wof:placetype":"venue"
},
  "geometry": {"coordinates":[-71.342613,46.757557],"type":"Point"}
}