{
  "type": "Feature",
  "properties": {
    "addr:full":"Markham ON L3R 1H8",
    "addr:postcode":"l3r 1h8",
    "iso:country":"CA",
    "sg:city":"Markham",
    "sg:classifiers":[
        {
            "category":"Travel",
            "subcategory":"Travel Agent",
            "type":"Entertainment"
        }
    ],
    "sg:phone":"+1 905 946 0626",
    "sg:postcode":"L3R 1H8",
    "sg:province":"ON",
    "sg:tags":[
        "agency",
        "bureau"
    ],
    "wof:name":"Sjs Travel Svc",
    "wof:placetype":"venue"
},
  "geometry": {"coordinates":[-79.3356246948,43.820526123],"type":"Point"}
}