{
  "type": "Feature",
  "properties": {
    "addr:full":"610 St Andrew St W Fergus ON N1M 1P6",
    "addr:housenumber":"610",
    "addr:postcode":"n1m 1p6",
    "addr:street":"St Andrew St W",
    "iso:country":"CA",
    "sg:address":"610 St Andrew St W",
    "sg:city":"Fergus",
    "sg:classifiers":[
        {
            "category":"Shopping",
            "subcategory":"Bicycles & Sporting Goods",
            "type":"Retail Goods"
        }
    ],
    "sg:phone":"+1 519 787 7873",
    "sg:postcode":"N1M 1P6",
    "sg:province":"ON",
    "wof:name":"Chipps Distributing",
    "wof:placetype":"venue"
},
  "geometry": {"coordinates":[-80.3834075928,43.6982307434],"type":"Point"}
}