{
  "type": "Feature",
  "properties": {
    "addr:full":"5758 Landmark Way Surrey BC V3S 7H1",
    "addr:housenumber":"5758",
    "addr:postcode":"v3s 7h1",
    "addr:street":"Landmark Way",
    "iso:country":"CA",
    "sg:address":"5758 Landmark Way",
    "sg:city":"Surrey",
    "sg:classifiers":[
        {
            "category":"Freight",
            "type":"Transportation"
        }
    ],
    "sg:phone":"+1 604 533 1030",
    "sg:postcode":"V3S 7H1",
    "sg:province":"BC",
    "sg:tags":[
        "commercial",
        "storage"
    ],
    "wof:name":"Maple Leaf Self Storage",
    "wof:placetype":"venue"
},
  "geometry": {"coordinates":[-122.6823349,49.1074562073],"type":"Point"}
}