{
  "type": "Feature",
  "properties": {
    "addr:full":"12 Rue Saint-Henri Cap-DE-LA-Madeleine QC G8T 7S4",
    "addr:housenumber":"12",
    "addr:postcode":"g8t 7s4",
    "addr:street":"Rue Saint-Henri",
    "iso:country":"CA",
    "sg:address":"12 Rue Saint-Henri",
    "sg:city":"Cap-DE-LA-Madeleine",
    "sg:classifiers":[
        {
            "category":"Professional",
            "subcategory":"Business Services",
            "type":"Services"
        }
    ],
    "sg:phone":"+1 819 371 2393",
    "sg:postcode":"G8T 7S4",
    "sg:province":"QC",
    "sg:tags":[
        "dressmaker",
        "embroidery"
    ],
    "wof:name":"Couture Plus Enr",
    "wof:placetype":"venue"
},
  "geometry": {"coordinates":[-72.52751159669999,46.3637924194],"type":"Point"}
}