{
  "type": "Feature",
  "properties": {
    "addr:full":"804 Ch Pintendre Pintendre QC G6C 1C5",
    "addr:housenumber":"804",
    "addr:postcode":"g6c 1c5",
    "addr:street":"Ch Pintendre Pintendre",
    "iso:country":"CA",
    "sg:address":"804 Ch Pintendre",
    "sg:city":"Pintendre",
    "sg:classifiers":[
        {
            "category":"Wholesale",
            "subcategory":"Non-durable Goods",
            "type":"Manufacturing & Wholesale Goods"
        }
    ],
    "sg:phone":"+1 418 838 9395",
    "sg:postcode":"G6C 1C5",
    "sg:province":"QC",
    "wof:name":"Ateliers Du Vieux Grenier",
    "wof:placetype":"venue"
},
  "geometry": {"coordinates":[-71.1251296997,46.7535858154],"type":"Point"}
}