{
  "type": "Feature",
  "properties": {
    "addr:full":"Mississauga ON L4W 2Z2",
    "addr:postcode":"l4w 2z2",
    "iso:country":"CA",
    "sg:city":"Mississauga",
    "sg:classifiers":[
        {
            "category":"Restaurant",
            "type":"Food & Drink"
        }
    ],
    "sg:phone":"+1 416 621 6971",
    "sg:postcode":"L4W 2Z2",
    "sg:province":"ON",
    "sg:tags":[
        "baker"
    ],
    "wof:name":"Lasem",
    "wof:placetype":"venue"
},
  "geometry": {"coordinates":[-79.623062,43.633801],"type":"Point"}
}