{
  "type": "Feature",
  "properties": {
    "addr:full":"167 Lake Nosbonsing Rd Callander ON P0H 1H0",
    "addr:housenumber":"167",
    "addr:postcode":"p0h 1h0",
    "addr:street":"Lake Nosbonsing Rd",
    "iso:country":"CA",
    "sg:address":"167 Lake Nosbonsing Rd",
    "sg:city":"Callander",
    "sg:classifiers":[
        {
            "category":"Building & Trades",
            "subcategory":"Plumbing",
            "type":"Services"
        }
    ],
    "sg:phone":"+1 705 752 4523",
    "sg:postcode":"P0H 1H0",
    "sg:province":"ON",
    "sg:tags":[
        "excavating",
        "tank",
        "septic",
        "contractor"
    ],
    "wof:name":"Neil Jones Construction",
    "wof:placetype":"venue"
},
  "geometry": {"coordinates":[-79.351494,46.193737],"type":"Point"}
}