{
  "type": "Feature",
  "properties": {
    "addr:full":"Laval QC H7N 1A2",
    "addr:postcode":"h7n 1a2",
    "iso:country":"CA",
    "sg:city":"Laval",
    "sg:classifiers":[
        {
            "category":"Education",
            "subcategory":"College",
            "type":"Public Place"
        }
    ],
    "sg:phone":"+1 450 662 9090",
    "sg:postcode":"H7N 1A2",
    "sg:province":"QC",
    "sg:tags":[
        "academic",
        "school"
    ],
    "wof:name":"College Cdi DE Technologies",
    "wof:placetype":"venue"
},
  "geometry": {"coordinates":[-73.70513200000001,45.581181],"type":"Point"}
}