{
  "type": "Feature",
  "properties": {
    "addr:full":"1680 Rue Villeray Montreal QC H2E 1H4",
    "addr:housenumber":"1680",
    "addr:postcode":"h2e 1h4",
    "addr:street":"Rue Villeray",
    "iso:country":"CA",
    "sg:address":"1680 Rue Villeray",
    "sg:city":"Montreal",
    "sg:classifiers":[
        {
            "category":"Personal",
            "subcategory":"Beauty Salon",
            "type":"Services"
        }
    ],
    "sg:phone":"+1 514 593 0606",
    "sg:postcode":"H2E 1H4",
    "sg:province":"QC",
    "wof:name":"Black Touch Salon DE Coiffure",
    "wof:placetype":"venue"
},
  "geometry": {"coordinates":[-73.6148223877,45.5507545471],"type":"Point"}
}