{
  "type": "Feature",
  "properties": {
    "addr:full":"7001 Mumford Rd Halifax NS B3L 2H8",
    "addr:housenumber":"7001",
    "addr:postcode":"b3l 2h8",
    "addr:street":"Mumford Rd",
    "iso:country":"CA",
    "sg:address":"7001 Mumford Rd",
    "sg:city":"Halifax",
    "sg:classifiers":[
        {
            "category":"Shopping",
            "subcategory":"Shoes",
            "type":"Retail Goods"
        }
    ],
    "sg:phone":"+1 902 454 2233",
    "sg:postcode":"B3L 2H8",
    "sg:province":"NS",
    "wof:name":"Aldo Shoes Inc",
    "wof:placetype":"venue"
},
  "geometry": {"coordinates":[-63.619663,44.647785],"type":"Point"}
}