{
  "type": "Feature",
  "properties": {
    "addr:full":"Kelowna BC V1X 7T5",
    "addr:postcode":"v1x 7t5",
    "iso:country":"CA",
    "sg:city":"Kelowna",
    "sg:classifiers":[
        {
            "category":"Food & Beverages",
            "subcategory":"Bakery",
            "type":"Retail Goods"
        }
    ],
    "sg:phone":"+1 250 765 9434",
    "sg:postcode":"V1X 7T5",
    "sg:province":"BC",
    "sg:tags":[
        "doughnut"
    ],
    "wof:name":"Tim Hortons",
    "wof:placetype":"venue"
},
  "geometry": {"coordinates":[-119.388435364,49.918006897],"type":"Point"}
}