{
  "type": "Feature",
  "properties": {
    "addr:full":"1212 Av Seymour Montreal QC H3H 2A5",
    "addr:housenumber":"1212",
    "addr:postcode":"h3h 2a5",
    "addr:street":"Av Seymour",
    "iso:country":"CA",
    "sg:address":"1212 Av Seymour",
    "sg:city":"Montreal",
    "sg:classifiers":[
        {
            "category":"Health Services",
            "subcategory":"Doctor",
            "type":"Services"
        }
    ],
    "sg:phone":"+1 514 932 3308",
    "sg:postcode":"H3H 2A5",
    "sg:province":"QC",
    "sg:tags":[
        "dentist"
    ],
    "wof:name":"Aubry, Chantal DDS",
    "wof:placetype":"venue"
},
  "geometry": {"coordinates":[-73.58058200000001,45.490185],"type":"Point"}
}