{
  "type": "Feature",
  "properties": {
    "iso:country":"CA",
    "sg:address":"65 Des Pins",
    "sg:city":"Lebel-Sur-Quevillon",
    "sg:classifiers":[
        {
            "category":"Building & Trades",
            "subcategory":"Electrical",
            "type":"Services"
        }
    ],
    "sg:phone":"+1 819 755 4210",
    "sg:postcode":"J0Y 1X0",
    "sg:province":"QC",
    "sg:tags":[
        "electric",
        "contractor"
    ],
    "wof:name":"Energie Electrique Du Nord Inc",
    "wof:placetype":"venue"
},
  "geometry": {"coordinates":[-76.9740142822,49.049949646],"type":"Point"}
}