{
  "type": "Feature",
  "properties": {
    "addr:full":"Kamloops BC V1S 1L8",
    "addr:postcode":"bc v1s 1l8",
    "iso:country":"CA",
    "sg:city":"Kamloops",
    "sg:classifiers":[
        {
            "category":"Manufacturing",
            "subcategory":"Food",
            "type":"Manufacturing & Wholesale Goods"
        }
    ],
    "sg:phone":"+1 250 377 7555",
    "sg:postcode":"V1S 1L8",
    "sg:province":"BC",
    "sg:tags":[
        "grocer",
        "product",
        "manufacturer"
    ],
    "wof:name":"Fresh Is Best Salsa CO",
    "wof:placetype":"venue"
},
  "geometry": {"coordinates":[-120.376892,50.651749],"type":"Point"}
}