{
  "type": "Feature",
  "properties": {
    "addr:full":"30 13th St E Cornwall ON K6H 6V9",
    "addr:housenumber":"30",
    "addr:postcode":"k6h 6v9",
    "addr:street":"13Th St E",
    "iso:country":"CA",
    "sg:address":"30 13th St E",
    "sg:city":"Cornwall",
    "sg:classifiers":[
        {
            "category":"Shopping",
            "subcategory":"Pharmacy",
            "type":"Retail Goods"
        }
    ],
    "sg:phone":"+1 613 933 0670",
    "sg:postcode":"K6H 6V9",
    "sg:province":"ON",
    "wof:name":"Medical Arts Pharmacy",
    "wof:placetype":"venue"
},
  "geometry": {"coordinates":[-74.73969268800001,45.0344009399],"type":"Point"}
}