{
  "type": "Feature",
  "properties": {
    "iso:country":"CA",
    "sg:city":"Surrey",
    "sg:classifiers":[
        {
            "category":"Home & Garden",
            "subcategory":"Home Furnishings",
            "type":"Retail Goods"
        }
    ],
    "sg:phone":"+1 604 597 7222",
    "sg:postcode":"V3W 0K6",
    "sg:province":"BC",
    "sg:tags":[
        "venetian",
        "blind",
        "made",
        "drapery"
    ],
    "wof:name":"Surrey Drapery & Blinds Ltd",
    "wof:placetype":"venue"
},
  "geometry": {"coordinates":[-122.862693787,49.1552658081],"type":"Point"}
}