{
  "type": "Feature",
  "properties": {
    "addr:full":"105 Rue Saint-Germain O Rimouski QC G5L 4B6",
    "addr:housenumber":"105",
    "addr:postcode":"g5l 4b6",
    "addr:street":"Rue Saint-Germain O",
    "iso:country":"CA",
    "sg:address":"105 Rue Saint-Germain O",
    "sg:city":"Rimouski",
    "sg:classifiers":[
        {
            "category":"Restaurant",
            "type":"Food & Drink"
        }
    ],
    "sg:phone":"+1 418 723 3666",
    "sg:postcode":"G5L 4B6",
    "sg:province":"QC",
    "sg:tags":[
        "delicatessen",
        "sausage"
    ],
    "wof:name":"Maitre Saucissier",
    "wof:placetype":"venue"
},
  "geometry": {"coordinates":[-68.522713,48.453175],"type":"Point"}
}