{
  "type": "Feature",
  "properties": {
    "iso:country":"CA",
    "sg:address":"945 Gardiners Rd #60",
    "sg:city":"Kingston",
    "sg:classifiers":[
        {
            "category":"Shopping",
            "subcategory":"Clothing, Apparel, & Fashions",
            "type":"Retail Goods"
        }
    ],
    "sg:phone":"+1 613 634 7218",
    "sg:postcode":"K7M 7H4",
    "sg:province":"ON",
    "wof:name":"Reitmans",
    "wof:placetype":"venue"
},
  "geometry": {"coordinates":[-76.5689163208,44.2562675476],"type":"Point"}
}