{
  "type": "Feature",
  "properties": {
    "addr:full":"Inwood MB R0C 1P0",
    "addr:postcode":"r0c 1p0",
    "iso:country":"CA",
    "sg:city":"Inwood",
    "sg:classifiers":[
        {
            "category":"Building & Trades",
            "subcategory":"Construction",
            "type":"Services"
        }
    ],
    "sg:phone":"+1 204 278 3328",
    "sg:postcode":"R0C 1P0",
    "sg:province":"MB",
    "sg:tags":[
        "water",
        "well",
        "drilling"
    ],
    "wof:name":"Interlake Water Supply CO Ltd",
    "wof:placetype":"venue"
},
  "geometry": {"coordinates":[-97.4974441528,50.5078392029],"type":"Point"}
}