{
  "type": "Feature",
  "properties": {
    "addr:full":"77 Yonge St S Elmvale ON L0L 1P0",
    "addr:housenumber":"77",
    "addr:postcode":"l0l 1p0",
    "addr:street":"Yonge St S",
    "iso:country":"CA",
    "sg:address":"77 Yonge St S",
    "sg:city":"Elmvale",
    "sg:classifiers":[
        {
            "category":"Real Estate",
            "subcategory":"Real Estate Agent",
            "type":"Services"
        }
    ],
    "sg:phone":"+1 705 322 5000",
    "sg:postcode":"L0L 1P0",
    "sg:province":"ON",
    "wof:name":"Georgian Bay Realty Ltd",
    "wof:placetype":"venue"
},
  "geometry": {"coordinates":[-79.8609619141,44.5781059265],"type":"Point"}
}