{
  "type": "Feature",
  "properties": {
    "addr:full":"1180 Houghton Rd Kelowna BC V1X 2C9",
    "addr:housenumber":"1180",
    "addr:postcode":"v1x 2c9",
    "addr:street":"Houghton Rd",
    "iso:country":"CA",
    "sg:address":"1180 Houghton Rd",
    "sg:city":"Kelowna",
    "sg:classifiers":[
        {
            "category":"Education",
            "subcategory":"School",
            "type":"Public Place"
        }
    ],
    "sg:phone":"+1 250 868 8816",
    "sg:postcode":"V1X 2C9",
    "sg:province":"BC",
    "wof:name":"Vedanta Academy",
    "wof:placetype":"venue"
},
  "geometry": {"coordinates":[-119.409668,49.892387],"type":"Point"}
}