{
  "type": "Feature",
  "properties": {
    "addr:full":"300 Glad Park Ave Stouffville ON L4A 1E5",
    "addr:housenumber":"300",
    "addr:postcode":"l4a 1e5",
    "addr:street":"Glad Park Ave",
    "iso:country":"CA",
    "sg:address":"300 Glad Park Ave",
    "sg:city":"Stouffville",
    "sg:classifiers":[
        {
            "category":"Education",
            "subcategory":"School",
            "type":"Public Place"
        }
    ],
    "sg:phone":"+1 905 642 0224",
    "sg:postcode":"L4A 1E5",
    "sg:province":"ON",
    "wof:name":"Glad Park Public School",
    "wof:placetype":"venue"
},
  "geometry": {"coordinates":[-79.259293,43.974125],"type":"Point"}
}