{
  "type": "Feature",
  "properties": {
    "addr:full":"87 Rue Prince # 120 Montreal QC H3C 2M7",
    "addr:housenumber":"87",
    "addr:postcode":"h3c 2m7",
    "addr:street":"Rue Prince # 120",
    "iso:country":"CA",
    "sg:address":"87 Rue Prince # 120",
    "sg:city":"Montreal",
    "sg:classifiers":[
        {
            "category":"Restaurant",
            "type":"Food & Drink"
        }
    ],
    "sg:phone":"+1 514 871 2233",
    "sg:postcode":"H3C 2M7",
    "sg:province":"QC",
    "sg:tags":[
        "cafe"
    ],
    "wof:name":"Cafe DE LA Cite",
    "wof:placetype":"venue"
},
  "geometry": {"coordinates":[-73.55506099999999,45.49688],"type":"Point"}
}