{
  "type": "Feature",
  "properties": {
    "iso:country":"CA",
    "sg:address":"87 Rue Prince # 120",
    "sg:city":"Montreal",
    "sg:classifiers":[
        {
            "category":"Restaurant",
            "type":"Food & Drink"
        }
    ],
    "sg:phone":"+1 514 871 2233",
    "sg:postcode":"H3C 2M7",
    "sg:province":"QC",
    "sg:tags":[
        "cafe"
    ],
    "wof:name":"Cafe DE LA Cite",
    "wof:placetype":"venue"
},
  "geometry": {"coordinates":[-73.555061,45.49688],"type":"Point"}
}