{
  "type": "Feature",
  "properties": {
    "addr:full":"4243 17A St SE Calgary AB T2G 3X1",
    "addr:housenumber":"4243",
    "addr:postcode":"t2g 3x1",
    "addr:street":"17A St Se",
    "iso:country":"CA",
    "sg:address":"4243 17A St SE",
    "sg:city":"Calgary",
    "sg:classifiers":[
        {
            "category":"Manufacturing",
            "subcategory":"Metals",
            "type":"Manufacturing & Wholesale Goods"
        }
    ],
    "sg:phone":"+1 403 233 8345",
    "sg:postcode":"T2G 3X1",
    "sg:province":"AB",
    "sg:tags":[
        "steel"
    ],
    "wof:name":"Rambler Fabrication Inc",
    "wof:placetype":"venue"
},
  "geometry": {"coordinates":[-114.017906,51.016659],"type":"Point"}
}