{
  "type": "Feature",
  "properties": {
    "addr:full":"Toronto ON M4K 1N2",
    "addr:postcode":"m4k 1n2",
    "iso:country":"CA",
    "sg:city":"Toronto",
    "sg:classifiers":[
        {
            "category":"Health Services",
            "subcategory":"Doctor",
            "type":"Services"
        }
    ],
    "sg:phone":"+1 416 466 1311",
    "sg:postcode":"M4K 1N2",
    "sg:province":"ON",
    "sg:tags":[
        "physician",
        "surgeon"
    ],
    "wof:name":"Perlmuter, Marty MD",
    "wof:placetype":"venue"
},
  "geometry": {"coordinates":[-79.355316,43.676731],"type":"Point"}
}