{
  "type": "Feature",
  "properties": {
    "addr:full":"Calgary AB T2R 1L9",
    "addr:postcode":"t2r 1l9",
    "iso:country":"CA",
    "sg:city":"Calgary",
    "sg:classifiers":[
        {
            "category":"Professional",
            "subcategory":"Computer Services",
            "type":"Services"
        }
    ],
    "sg:phone":"+1 403 234 7067",
    "sg:postcode":"T2R 1L9",
    "sg:province":"AB",
    "sg:tags":[
        "repair",
        "dealer",
        "equipment"
    ],
    "wof:name":"Metafore Corp",
    "wof:placetype":"venue"
},
  "geometry": {"coordinates":[-114.06892395,51.0424003601],"type":"Point"}
}