{
  "type": "Feature",
  "properties": {
    "addr:full":"1310 9th Ave Valemount BC V0E 2Z0",
    "addr:housenumber":"1310",
    "addr:postcode":"v0e 2z0",
    "addr:street":"9Th Ave",
    "iso:country":"CA",
    "sg:address":"1310 9th Ave",
    "sg:city":"Valemount",
    "sg:classifiers":[
        {
            "category":"Retail",
            "subcategory":"Laundry & Dry Cleaning",
            "type":"Services"
        }
    ],
    "sg:phone":"+1 250 566 4578",
    "sg:postcode":"V0E 2Z0",
    "sg:province":"BC",
    "sg:tags":[
        "cleaners",
        "rug",
        "carpet"
    ],
    "wof:name":"Choice Carpet Care",
    "wof:placetype":"venue"
},
  "geometry": {"coordinates":[-119.265815735,52.8329658508],"type":"Point"}
}