{
  "type": "Feature",
  "properties": {
    "addr:full":"101 Union St Saint John NB E2L 1A4",
    "addr:housenumber":"101",
    "addr:postcode":"nb e2l 1a4",
    "addr:street":"Union St",
    "iso:country":"CA",
    "sg:address":"101 Union St",
    "sg:city":"Saint John",
    "sg:classifiers":[
        {
            "category":"Retail",
            "subcategory":"Auto Repair",
            "type":"Services"
        }
    ],
    "sg:phone":"+1 506 657 7566",
    "sg:postcode":"E2L 1A4",
    "sg:province":"NB",
    "sg:tags":[
        "repairing",
        "automobile"
    ],
    "wof:name":"Bob Pearson's Svc Ctr",
    "wof:placetype":"venue"
},
  "geometry": {"coordinates":[-66.06187438960001,45.2746963501],"type":"Point"}
}