{
  "type": "Feature",
  "properties": {
    "addr:full":"61 Sixth St New Westminster BC V3L 2Z6",
    "addr:housenumber":"61",
    "addr:postcode":"v3l 2z6",
    "addr:street":"Sixth St",
    "iso:country":"CA",
    "sg:address":"61 Sixth St",
    "sg:city":"New Westminster",
    "sg:classifiers":[
        {
            "category":"Food & Beverages",
            "subcategory":"Groceries & Convenience Stores",
            "type":"Retail Goods"
        }
    ],
    "sg:phone":"+1 604 525 6163",
    "sg:postcode":"V3L 2Z6",
    "sg:province":"BC",
    "sg:tags":[
        "grocer"
    ],
    "wof:name":"Victoria Food Market",
    "wof:placetype":"venue"
},
  "geometry": {"coordinates":[-122.909378,49.204521],"type":"Point"}
}