{
  "type": "Feature",
  "properties": {
    "addr:full":"Calgary AB T2P 0W5",
    "addr:postcode":"t2p 0w5",
    "iso:country":"CA",
    "sg:city":"Calgary",
    "sg:classifiers":[
        {
            "category":"Real Estate",
            "subcategory":"Architect",
            "type":"Services"
        }
    ],
    "sg:phone":"+1 403 261 8881",
    "sg:postcode":"T2P 0W5",
    "sg:province":"AB",
    "wof:name":"Jason Poon Architect Inc",
    "wof:placetype":"venue"
},
  "geometry": {"coordinates":[-114.063782,51.046394],"type":"Point"}
}