{
  "type": "Feature",
  "properties": {
    "addr:full":"7493 Main St W Radium Hot Springs BC V0A 1M0",
    "addr:housenumber":"7493",
    "addr:postcode":"v0a 1m0",
    "addr:street":"Main St W",
    "iso:country":"CA",
    "sg:address":"7493 Main St W",
    "sg:city":"Radium Hot Springs",
    "sg:classifiers":[
        {
            "category":"Restaurant",
            "type":"Food & Drink"
        }
    ],
    "sg:phone":"+1 250 347 2340",
    "sg:postcode":"V0A 1M0",
    "sg:province":"BC",
    "wof:name":"Cabina Ristorante & Carrington",
    "wof:placetype":"venue"
},
  "geometry": {"coordinates":[-116.071769714,50.6214408875],"type":"Point"}
}