{
  "type": "Feature",
  "properties": {
    "addr:full":"3232 Rue Belanger # 20 Montreal QC H1Y 3H5",
    "addr:housenumber":"3232",
    "addr:postcode":"h1y 3h5",
    "addr:street":"Rue Belanger # 20",
    "iso:country":"CA",
    "sg:address":"3232 Rue Belanger # 20",
    "sg:city":"Montreal",
    "sg:classifiers":[
        {
            "category":"Building & Trades",
            "subcategory":"Construction",
            "type":"Services"
        }
    ],
    "sg:phone":"+1 514 728 2420",
    "sg:postcode":"H1Y 3H5",
    "sg:province":"QC",
    "sg:tags":[
        "contractor"
    ],
    "wof:name":"Construction Jean Drouin",
    "wof:placetype":"venue"
},
  "geometry": {"coordinates":[-73.59400939939999,45.5570068359],"type":"Point"}
}