{
  "type": "Feature",
  "properties": {
    "iso:country":"CA",
    "sg:address":"4 Central Ave",
    "sg:city":"Wolfville",
    "sg:classifiers":[
        {
            "category":"Health Services",
            "subcategory":"Optometrist",
            "type":"Services"
        }
    ],
    "sg:phone":"+1 902 542 3435",
    "sg:postcode":"B4P 2A6",
    "sg:province":"NS",
    "wof:name":"Pothier, S J OD",
    "wof:placetype":"venue"
},
  "geometry": {"coordinates":[-64.36186218260001,45.0918540955],"type":"Point"}
}