{
  "type": "Feature",
  "properties": {
    "iso:country":"CA",
    "sg:address":"RR 1",
    "sg:city":"Milverton",
    "sg:classifiers":[
        {
            "category":"Freight",
            "type":"Transportation"
        }
    ],
    "sg:phone":"+1 519 595 8022",
    "sg:postcode":"N0K 1M0",
    "sg:province":"ON",
    "sg:tags":[
        "trucking"
    ],
    "wof:name":"Dwight Satchell Livestock",
    "wof:placetype":"venue"
},
  "geometry": {"coordinates":[-80.9208679199,43.5675125122],"type":"Point"}
}