{
  "type": "Feature",
  "properties": {
    "addr:full":"722 College St #303 Toronto ON M6G 1C4",
    "addr:housenumber":"722",
    "addr:postcode":"m6g 1c4",
    "addr:street":"College St # 303",
    "iso:country":"CA",
    "sg:address":"722 College St #303",
    "sg:city":"Toronto",
    "sg:classifiers":[
        {
            "category":"Professional",
            "subcategory":"Lawyer & Legal Services",
            "type":"Services"
        }
    ],
    "sg:phone":"+1 416 533 6002",
    "sg:postcode":"M6G 1C4",
    "sg:province":"ON",
    "sg:tags":[
        "attorney"
    ],
    "wof:name":"Libanio, Susan M C",
    "wof:placetype":"venue"
},
  "geometry": {"coordinates":[-79.419189,43.655212],"type":"Point"}
}