{
  "type": "Feature",
  "properties": {
    "addr:full":"1070 Mcdougall Rd NE Calgary AB T2E 7Z2",
    "addr:housenumber":"1070",
    "addr:postcode":"t2e 7z2",
    "addr:street":"Mcdougall Rd Ne",
    "iso:country":"CA",
    "sg:address":"1070 Mcdougall Rd NE",
    "sg:city":"Calgary",
    "sg:classifiers":[
        {
            "category":"Health Services",
            "subcategory":"Nursing And Care Facility",
            "type":"Services"
        }
    ],
    "sg:phone":"+1 403 267 2900",
    "sg:postcode":"T2E 7Z2",
    "sg:province":"AB",
    "sg:tags":[
        "home",
        "convalescent"
    ],
    "wof:name":"Carewest",
    "wof:placetype":"venue"
},
  "geometry": {"coordinates":[-114.03808600000001,51.051003],"type":"Point"}
}