{
  "type": "Feature",
  "properties": {
    "iso:country":"CA",
    "sg:address":"4161 Morris Dr",
    "sg:city":"Burlington",
    "sg:classifiers":[
        {
            "category":"Wholesale",
            "subcategory":"Machinery & Supplies",
            "type":"Manufacturing & Wholesale Goods"
        }
    ],
    "sg:phone":"+1 905 333 5670",
    "sg:postcode":"L7L 5L5",
    "sg:province":"ON",
    "sg:tags":[
        "contractor"
    ],
    "wof:name":"Martek Construction Products",
    "wof:placetype":"venue"
},
  "geometry": {"coordinates":[-79.7807769775,43.3679962158],"type":"Point"}
}