{
  "type": "Feature",
  "properties": {
    "addr:full":"513 Rue DE L'Eglise Saint-Romuald QC G6W 3J2",
    "addr:housenumber":"513",
    "addr:postcode":"g6w 3j2",
    "addr:street":"Rue De L'Eglise",
    "iso:country":"CA",
    "sg:address":"513 Rue DE L'Eglise",
    "sg:city":"Saint-Romuald",
    "sg:classifiers":[
        {
            "category":"Building & Trades",
            "subcategory":"Construction",
            "type":"Services"
        }
    ],
    "sg:phone":"+1 418 839 0700",
    "sg:postcode":"G6W 3J2",
    "sg:province":"QC",
    "sg:tags":[
        "excavating",
        "contractor"
    ],
    "wof:name":"Gerard Ruel Excavation Inc",
    "wof:placetype":"venue"
},
  "geometry": {"coordinates":[-71.2391586304,46.7580490112],"type":"Point"}
}