{
  "type": "Feature",
  "properties": {
    "addr:full":"70 Place Du 21-Mars Nicolet QC J3T 1E9",
    "addr:housenumber":"70",
    "addr:postcode":"j3t 1e9",
    "addr:street":"Place Du 21-Mars",
    "iso:country":"CA",
    "sg:address":"70 Place Du 21-Mars",
    "sg:city":"Nicolet",
    "sg:classifiers":[
        {
            "category":"Shopping",
            "subcategory":"Clothing, Apparel, & Fashions",
            "type":"Retail Goods"
        }
    ],
    "sg:phone":"+1 819 293 5642",
    "sg:postcode":"J3T 1E9",
    "sg:province":"QC",
    "sg:tags":[
        "item",
        "boutique"
    ],
    "wof:name":"Boutique Denijean",
    "wof:placetype":"venue"
},
  "geometry": {"coordinates":[-72.617912,46.225876],"type":"Point"}
}