{
  "type": "Feature",
  "properties": {
    "addr:full":"2100 Sherobee Rd Mississauga ON L5A 4C5",
    "addr:housenumber":"2100",
    "addr:postcode":"l5a 4c5",
    "addr:street":"Sherobee Rd",
    "iso:country":"CA",
    "sg:address":"2100 Sherobee Rd",
    "sg:city":"Mississauga",
    "sg:classifiers":[
        {
            "category":"Real Estate",
            "subcategory":"Real Estate Operator",
            "type":"Services"
        }
    ],
    "sg:phone":"+1 905 848 6838",
    "sg:postcode":"L5A 4C5",
    "sg:province":"ON",
    "sg:tags":[
        "condominium"
    ],
    "wof:name":"Somerset Place",
    "wof:placetype":"venue"
},
  "geometry": {"coordinates":[-79.602097,43.57267],"type":"Point"}
}