{
  "type": "Feature",
  "properties": {
    "addr:full":"821 Lake Dr E Sutton West ON L0E 1R0",
    "addr:housenumber":"821",
    "addr:postcode":"l0e 1r0",
    "addr:street":"Lake Dr E",
    "iso:country":"CA",
    "sg:address":"821 Lake Dr E",
    "sg:city":"Sutton West",
    "sg:classifiers":[
        {
            "category":"Travel",
            "subcategory":"Hotels & Motels",
            "type":"Entertainment"
        }
    ],
    "sg:phone":"+1 905 722 0003",
    "sg:postcode":"L0E 1R0",
    "sg:province":"ON",
    "sg:tags":[
        "cottage",
        "cabin"
    ],
    "wof:name":"Jackson's Point Cottages",
    "wof:placetype":"venue"
},
  "geometry": {"coordinates":[-79.3612365723,44.3048667908],"type":"Point"}
}