{
  "type": "Feature",
  "properties": {
    "addr:full":"Mackenzie BC V0J 2C0",
    "addr:postcode":"v0j 2c0",
    "iso:country":"CA",
    "sg:city":"Mackenzie",
    "sg:classifiers":[
        {
            "category":"Professional",
            "subcategory":"Accounting & Tax Preparation",
            "type":"Services"
        }
    ],
    "sg:phone":"+1 250 997 9003",
    "sg:postcode":"V0J 2C0",
    "sg:province":"BC",
    "sg:tags":[
        "consultant",
        "return",
        "filing"
    ],
    "wof:name":"H & R Block Canada Inc",
    "wof:placetype":"venue"
},
  "geometry": {"coordinates":[-123.094696,55.336571],"type":"Point"}
}