{
  "type": "Feature",
  "properties": {
    "iso:country":"CA",
    "sg:address":"48 Boul Des Bois-Francs S",
    "sg:city":"Victoriaville",
    "sg:classifiers":[
        {
            "category":"Personal",
            "subcategory":"Beauty Salon",
            "type":"Services"
        }
    ],
    "sg:phone":"+1 819 751 2079",
    "sg:postcode":"G6P 4S1",
    "sg:province":"QC",
    "wof:name":"Salon Multi-Look Coiffure Enr",
    "wof:placetype":"venue"
},
  "geometry": {"coordinates":[-71.949501,46.058147],"type":"Point"}
}