{
  "type": "Feature",
  "properties": {
    "iso:country":"CA",
    "sg:city":"Kamloops",
    "sg:classifiers":[
        {
            "category":"Retail",
            "subcategory":"Funeral Services",
            "type":"Services"
        }
    ],
    "sg:phone":"+1 250 554 2324",
    "sg:postcode":"V2B 3E8",
    "sg:province":"BC",
    "sg:tags":[
        "director"
    ],
    "wof:name":"Personal Alternative Funeral",
    "wof:placetype":"venue"
},
  "geometry": {"coordinates":[-120.355629,50.685303],"type":"Point"}
}