{
  "type": "Feature",
  "properties": {
    "addr:full":"335 Neptune Cres London ON N6M 1A9",
    "addr:housenumber":"335",
    "addr:postcode":"n6m 1a9",
    "addr:street":"Neptune Cres",
    "iso:country":"CA",
    "sg:address":"335 Neptune Cres",
    "sg:city":"London",
    "sg:classifiers":[
        {
            "category":"Building & Trades",
            "subcategory":"Construction",
            "type":"Services"
        }
    ],
    "sg:phone":"+1 519 455 0704",
    "sg:postcode":"N6M 1A9",
    "sg:province":"ON",
    "sg:tags":[
        "builder",
        "stair"
    ],
    "wof:name":"London Stair & Railing CO",
    "wof:placetype":"venue"
},
  "geometry": {"coordinates":[-81.139038,42.992409],"type":"Point"}
}