{
  "type": "Feature",
  "properties": {
    "addr:full":"2323 Stevenage Dr Ottawa ON K1G 3W1",
    "addr:housenumber":"2323",
    "addr:postcode":"k1g 3w1",
    "addr:street":"Stevenage Dr",
    "iso:country":"CA",
    "sg:address":"2323 Stevenage Dr",
    "sg:city":"Ottawa",
    "sg:classifiers":[
        {
            "category":"Retail",
            "subcategory":"Auto Rental",
            "type":"Services"
        }
    ],
    "sg:phone":"+1 613 738 7117",
    "sg:postcode":"K1G 3W1",
    "sg:province":"ON",
    "sg:tags":[
        "renting",
        "truck",
        "leasing"
    ],
    "wof:name":"Penske Truck Rental & Leasing",
    "wof:placetype":"venue"
},
  "geometry": {"coordinates":[-75.6097412109,45.3800735474],"type":"Point"}
}