{
  "type": "Feature",
  "properties": {
    "iso:country":"CA",
    "sg:address":"476 Av Lafleur",
    "sg:city":"Lasalle",
    "sg:classifiers":[
        {
            "category":"Wholesale",
            "subcategory":"Meat",
            "type":"Manufacturing & Wholesale Goods"
        }
    ],
    "sg:phone":"+1 514 365 4313",
    "sg:postcode":"H8R 3H9",
    "sg:province":"QC",
    "sg:tags":[
        "product"
    ],
    "wof:name":"Marche DE L'Abattoir",
    "wof:placetype":"venue"
},
  "geometry": {"coordinates":[-73.645980835,45.4337081909],"type":"Point"}
}