{
  "type": "Feature",
  "properties": {
    "addr:full":"319 First Ave W North Bay ON P1B 3C3",
    "addr:housenumber":"319",
    "addr:postcode":"p1b 3c3",
    "addr:street":"First Ave W",
    "iso:country":"CA",
    "sg:address":"319 First Ave W",
    "sg:city":"North Bay",
    "sg:classifiers":[
        {
            "category":"Social Services",
            "type":"Services"
        }
    ],
    "sg:phone":"+1 705 474 2254",
    "sg:postcode":"P1B 3C3",
    "sg:province":"ON",
    "sg:tags":[
        "organization",
        "welfare"
    ],
    "wof:name":"Manu Residence",
    "wof:placetype":"venue"
},
  "geometry": {"coordinates":[-79.46386699999999,46.315075],"type":"Point"}
}