{
  "type": "Feature",
  "properties": {
    "addr:full":"Abbotsford BC V2T 4V6",
    "addr:postcode":"v2t 4v6",
    "iso:country":"CA",
    "sg:city":"Abbotsford",
    "sg:classifiers":[
        {
            "category":"Wholesale",
            "subcategory":"Dairy",
            "type":"Manufacturing & Wholesale Goods"
        }
    ],
    "sg:phone":"+1 604 855 4444",
    "sg:postcode":"V2T 4V6",
    "sg:province":"BC",
    "sg:tags":[
        "food",
        "frozen",
        "product",
        "ice",
        "cream"
    ],
    "wof:name":"Yogurt Island",
    "wof:placetype":"venue"
},
  "geometry": {"coordinates":[-122.316597,49.056412],"type":"Point"}
}