{
  "type": "Feature",
  "properties": {
    "iso:country":"CA",
    "sg:city":"Edmonton",
    "sg:classifiers":[
        {
            "category":"Health Services",
            "subcategory":"Medical Lab",
            "type":"Services"
        }
    ],
    "sg:phone":"+1 780 422 3235",
    "sg:postcode":"T5N 3W6",
    "sg:province":"AB",
    "wof:name":"Burton Denture Clinic",
    "wof:placetype":"venue"
},
  "geometry": {"coordinates":[-113.536140442,53.5436935425],"type":"Point"}
}