{
  "type": "Feature",
  "properties": {
    "addr:full":"Smith AB T0G 2B0",
    "addr:postcode":"t0g 2b0",
    "iso:country":"CA",
    "sg:city":"Smith",
    "sg:classifiers":[
        {
            "category":"Utilities",
            "subcategory":"Refuse",
            "type":"Services"
        }
    ],
    "sg:phone":"+1 780 829 2788",
    "sg:postcode":"T0G 2B0",
    "sg:province":"AB",
    "sg:tags":[
        "disposal",
        "waste"
    ],
    "wof:name":"Athabasca Regional Waste Fclty",
    "wof:placetype":"venue"
},
  "geometry": {"coordinates":[-114.020309,55.150787],"type":"Point"}
}