{
  "type": "Feature",
  "properties": {
    "addr:full":"950 Cole Harbour Rd Dartmouth NS B2V 1E6",
    "addr:housenumber":"950",
    "addr:postcode":"b2v 1e6",
    "addr:street":"Cole Harbour Rd",
    "iso:country":"CA",
    "sg:address":"950 Cole Harbour Rd",
    "sg:city":"Dartmouth",
    "sg:classifiers":[
        {
            "category":"Shopping",
            "subcategory":"Pharmacy",
            "type":"Retail Goods"
        }
    ],
    "sg:phone":"+1 902 462 7416",
    "sg:postcode":"B2V 1E6",
    "sg:province":"NS",
    "wof:name":"Lawton's Drugs",
    "wof:placetype":"venue"
},
  "geometry": {"coordinates":[-63.4963,44.671135],"type":"Point"}
}