{
  "type": "Feature",
  "properties": {
    "addr:full":"Stratford ON N5A 6S2",
    "addr:postcode":"n5a 6s2",
    "iso:country":"CA",
    "sg:city":"Stratford",
    "sg:classifiers":[
        {
            "category":"Education",
            "subcategory":"Special Training",
            "type":"Public Place"
        }
    ],
    "sg:phone":"+1 519 271 4881",
    "sg:postcode":"N5A 6S2",
    "sg:province":"ON",
    "sg:tags":[
        "aircraft",
        "school"
    ],
    "wof:name":"Stratford Air Svc Ltd",
    "wof:placetype":"venue"
},
  "geometry": {"coordinates":[-80.98192596440001,43.370136261],"type":"Point"}
}