{
  "type": "Feature",
  "properties": {
    "addr:full":"268 King St Winnipeg MB R3B 1J5",
    "addr:housenumber":"268",
    "addr:postcode":"r3b 1j5",
    "addr:street":"King St",
    "iso:country":"CA",
    "sg:address":"268 King St",
    "sg:city":"Winnipeg",
    "sg:classifiers":[
        {
            "category":"Food & Beverages",
            "subcategory":"Groceries & Convenience Stores",
            "type":"Retail Goods"
        }
    ],
    "sg:phone":"+1 204 943 4103",
    "sg:postcode":"R3B 1J5",
    "sg:province":"MB",
    "sg:tags":[
        "grocer"
    ],
    "wof:name":"Oriental Market & CO Ltd",
    "wof:placetype":"venue"
},
  "geometry": {"coordinates":[-97.137581,49.90295],"type":"Point"}
}