{
  "type": "Feature",
  "properties": {
    "iso:country":"CA",
    "sg:address":"2575 Blackwell St #102",
    "sg:city":"Ottawa",
    "sg:classifiers":[
        {
            "category":"Wholesale",
            "subcategory":"Machinery & Supplies",
            "type":"Manufacturing & Wholesale Goods"
        }
    ],
    "sg:phone":"+1 613 748 0453",
    "sg:postcode":"K1B 4E4",
    "sg:province":"ON",
    "sg:tags":[
        "compressor",
        "gas"
    ],
    "wof:name":"Regional Compressor",
    "wof:placetype":"venue"
},
  "geometry": {"coordinates":[-75.6091003418,45.4044075012],"type":"Point"}
}