{
  "type": "Feature",
  "properties": {
    "iso:country":"CA",
    "sg:address":"816 Boul Saint-Joseph",
    "sg:city":"Roberval",
    "sg:classifiers":[
        {
            "category":"Retail",
            "subcategory":"Funeral Services",
            "type":"Services"
        }
    ],
    "sg:phone":"+1 418 275 3331",
    "sg:postcode":"G8H 2L5",
    "sg:province":"QC",
    "sg:tags":[
        "director"
    ],
    "wof:name":"Salon Funeratium",
    "wof:placetype":"venue"
},
  "geometry": {"coordinates":[-72.2211303711,48.5172576904],"type":"Point"}
}