{
  "type": "Feature",
  "properties": {
    "addr:full":"855 Westney Rd S Ajax ON L1S 3M4",
    "addr:housenumber":"855",
    "addr:postcode":"l1s 3m4",
    "addr:street":"Westney Rd",
    "iso:country":"CA",
    "sg:address":"855 Westney Rd S",
    "sg:city":"Ajax",
    "sg:classifiers":[
        {
            "category":"Restaurant",
            "type":"Food & Drink"
        }
    ],
    "sg:phone":"+1 905 683 4946",
    "sg:postcode":"L1S 3M4",
    "sg:province":"ON",
    "wof:name":"Pizza Pino",
    "wof:placetype":"venue"
},
  "geometry": {"coordinates":[-79.02085113530001,43.8300628662],"type":"Point"}
}