{
  "type": "Feature",
  "properties": {
    "addr:full":"1785 Alta Vista Dr Ottawa ON K1G 3Y6",
    "addr:housenumber":"1785",
    "addr:postcode":"k1g 3y6",
    "addr:street":"Alta Vista Dr",
    "iso:country":"CA",
    "sg:address":"1785 Alta Vista Dr",
    "sg:city":"Ottawa",
    "sg:classifiers":[
        {
            "category":"Wholesale",
            "subcategory":"Drugs",
            "type":"Manufacturing & Wholesale Goods"
        }
    ],
    "sg:phone":"+1 613 738 8607",
    "sg:postcode":"K1G 3Y6",
    "sg:province":"ON",
    "sg:tags":[
        "pharmaceutical",
        "product"
    ],
    "wof:name":"Arthropharm Pharmaceuticals",
    "wof:placetype":"venue"
},
  "geometry": {"coordinates":[-75.66213999999999,45.401806],"type":"Point"}
}