{
  "type": "Feature",
  "properties": {
    "addr:full":"218 Main St Rosenfeld MB R0G 1X0",
    "addr:housenumber":"218",
    "addr:postcode":"r0g 1x0",
    "addr:street":"Main St",
    "iso:country":"CA",
    "sg:address":"218 Main St",
    "sg:city":"Rosenfeld",
    "sg:classifiers":[
        {
            "category":"Retail",
            "subcategory":"Auto Repair",
            "type":"Services"
        }
    ],
    "sg:phone":"+1 204 324 6254",
    "sg:postcode":"R0G 1X0",
    "sg:province":"MB",
    "sg:tags":[
        "repairing",
        "automobile"
    ],
    "wof:name":"Martel's Garage",
    "wof:placetype":"venue"
},
  "geometry": {"coordinates":[-97.54969024659999,49.198841095],"type":"Point"}
}