{
  "type": "Feature",
  "properties": {
    "addr:full":"Mississauga ON L4W 4V9",
    "addr:postcode":"l4w 4v9",
    "iso:country":"CA",
    "sg:city":"Mississauga",
    "sg:classifiers":[
        {
            "category":"Retail",
            "subcategory":"Laundry & Dry Cleaning",
            "type":"Services"
        }
    ],
    "sg:phone":"+1 905 602 6914",
    "sg:postcode":"L4W 4V9",
    "sg:province":"ON",
    "sg:tags":[
        "cleaners"
    ],
    "wof:name":"Exton Custom Dry Cleaners",
    "wof:placetype":"venue"
},
  "geometry": {"coordinates":[-79.59974699999999,43.661713],"type":"Point"}
}