{
  "type": "Feature",
  "properties": {
    "addr:full":"1323 Lougar Ave Sarnia ON N7S 5N5",
    "addr:housenumber":"1323",
    "addr:postcode":"n7s 5n5",
    "addr:street":"Lougar Ave",
    "iso:country":"CA",
    "sg:address":"1323 Lougar Ave",
    "sg:city":"Sarnia",
    "sg:classifiers":[
        {
            "category":"Building & Trades",
            "subcategory":"Construction",
            "type":"Services"
        }
    ],
    "sg:phone":"+1 519 337 4192",
    "sg:postcode":"N7S 5N5",
    "sg:province":"ON",
    "sg:tags":[
        "fire",
        "cleaners",
        "rug",
        "damage",
        "restoration",
        "carpet"
    ],
    "wof:name":"Shamrock Services",
    "wof:placetype":"venue"
},
  "geometry": {"coordinates":[-82.358124,42.957794],"type":"Point"}
}