{
  "type": "Feature",
  "properties": {
    "addr:full":"91 Rue Acadie Grande-Anse NB E8N 1A1",
    "addr:housenumber":"91",
    "addr:postcode":"e8n 1a1",
    "addr:street":"Rue Acadie",
    "iso:country":"CA",
    "sg:address":"91 Rue Acadie",
    "sg:city":"Grande-Anse",
    "sg:classifiers":[
        {
            "category":"Professional",
            "subcategory":"Business Services",
            "type":"Services"
        }
    ],
    "sg:phone":"+1 506 732 2068",
    "sg:postcode":"E8N 1A1",
    "sg:province":"NB",
    "sg:tags":[
        "translator",
        "interpreter"
    ],
    "wof:name":"Trans-Lingua",
    "wof:placetype":"venue"
},
  "geometry": {"coordinates":[-65.206963,47.803047],"type":"Point"}
}