{
  "type": "Feature",
  "properties": {
    "addr:full":"154 Main St Parkhill ON N0M 2K0",
    "addr:housenumber":"154",
    "addr:postcode":"n0m 2k0",
    "addr:street":"Main St",
    "iso:country":"CA",
    "sg:address":"154 Main St",
    "sg:city":"Parkhill",
    "sg:classifiers":[
        {
            "category":"Personal",
            "type":"Services"
        }
    ],
    "sg:phone":"+1 519 294 0893",
    "sg:postcode":"N0M 2K0",
    "sg:province":"ON",
    "sg:tags":[
        "genealogist"
    ],
    "wof:name":"Kinfolk Finders",
    "wof:placetype":"venue"
},
  "geometry": {"coordinates":[-81.68500518800001,43.1588630676],"type":"Point"}
}