{
  "type": "Feature",
  "properties": {
    "addr:full":"714 Robson St Vancouver BC V6Z 1A1",
    "addr:housenumber":"714",
    "addr:postcode":"v6z 1a1",
    "addr:street":"Robson St",
    "iso:country":"CA",
    "sg:address":"714 Robson St",
    "sg:city":"Vancouver",
    "sg:classifiers":[
        {
            "category":"Shopping",
            "subcategory":"Jewelry",
            "type":"Retail Goods"
        }
    ],
    "sg:phone":"+1 604 688 0857",
    "sg:postcode":"V6Z 1A1",
    "sg:province":"BC",
    "sg:tags":[
        "jeweler"
    ],
    "wof:name":"Lynn's Jewellery Ltd",
    "wof:placetype":"venue"
},
  "geometry": {"coordinates":[-123.12014770499999,49.2814102173],"type":"Point"}
}