{
  "type": "Feature",
  "properties": {
    "addr:full":"530 Henderson Dr Regina SK S4N 5X2",
    "addr:housenumber":"530",
    "addr:postcode":"s4n 5x2",
    "addr:street":"Henderson Dr",
    "iso:country":"CA",
    "sg:address":"530 Henderson Dr",
    "sg:city":"Regina",
    "sg:classifiers":[
        {
            "category":"Home & Garden",
            "subcategory":"Household Appliances",
            "type":"Retail Goods"
        }
    ],
    "sg:phone":"+1 306 352 6668",
    "sg:postcode":"S4N 5X2",
    "sg:province":"SK",
    "sg:tags":[
        "cleaners",
        "vacuum"
    ],
    "wof:name":"Vacu-Maid",
    "wof:placetype":"venue"
},
  "geometry": {"coordinates":[-104.568253,50.470448],"type":"Point"}
}