{
  "type": "Feature",
  "properties": {
    "addr:full":"3420 Lawrence Ave E Scarborough ON M1H 1A9",
    "addr:housenumber":"3420",
    "addr:postcode":"m1h 1a9",
    "addr:street":"Lawrence Ave E",
    "iso:country":"CA",
    "sg:address":"3420 Lawrence Ave E",
    "sg:city":"Scarborough",
    "sg:classifiers":[
        {
            "category":"Shopping",
            "subcategory":"Optical Goods",
            "type":"Retail Goods"
        }
    ],
    "sg:phone":"+1 416 439 1577",
    "sg:postcode":"M1H 1A9",
    "sg:province":"ON",
    "sg:tags":[
        "optician"
    ],
    "wof:name":"Civic Optical",
    "wof:placetype":"venue"
},
  "geometry": {"coordinates":[-79.231567,43.758625],"type":"Point"}
}