{
  "type": "Feature",
  "properties": {
    "addr:full":"212 Brooksbank Ave North Vancouver BC V7J 2C1",
    "addr:housenumber":"212",
    "addr:postcode":"v7j 2c1",
    "addr:street":"Brooksbank Ave",
    "iso:country":"CA",
    "sg:address":"212 Brooksbank Ave",
    "sg:city":"North Vancouver",
    "sg:classifiers":[
        {
            "category":"Professional",
            "subcategory":"Testing Lab",
            "type":"Services"
        }
    ],
    "sg:phone":"+1 604 984 0221",
    "sg:postcode":"V7J 2C1",
    "sg:province":"BC",
    "sg:tags":[
        "laboratory",
        "assayer",
        "assaying"
    ],
    "wof:name":"Als Chemex",
    "wof:placetype":"venue"
},
  "geometry": {"coordinates":[-123.04029800000001,49.307472],"type":"Point"}
}