{
  "type": "Feature",
  "properties": {
    "iso:country":"CA",
    "sg:address":"810 Boul Baril O",
    "sg:city":"Princeville",
    "sg:classifiers":[
        {
            "category":"Building & Trades",
            "subcategory":"Construction",
            "type":"Services"
        }
    ],
    "sg:phone":"+1 819 364 7671",
    "sg:postcode":"G6L 3W6",
    "sg:province":"QC",
    "sg:tags":[
        "asbestos",
        "ventilating",
        "system",
        "removal"
    ],
    "wof:name":"Air Action",
    "wof:placetype":"venue"
},
  "geometry": {"coordinates":[-71.88767242430001,46.1496582031],"type":"Point"}
}