{
  "type": "Feature",
  "properties": {
    "addr:full":"Sainte-Croix QC G0S 2H0",
    "addr:postcode":"g0s 2h0",
    "iso:country":"CA",
    "sg:city":"Sainte-Croix",
    "sg:classifiers":[
        {
            "category":"Education",
            "subcategory":"School",
            "type":"Public Place"
        }
    ],
    "sg:phone":"+1 418 926 3221",
    "sg:postcode":"G0S 2H0",
    "sg:province":"QC",
    "wof:name":"Ecole LA Mennais",
    "wof:placetype":"venue"
},
  "geometry": {"coordinates":[-71.7397155762,46.6237030029],"type":"Point"}
}