{
  "type": "Feature",
  "properties": {
    "addr:full":"9008 100 St Westlock AB T7P 2L4",
    "addr:housenumber":"9008",
    "addr:postcode":"t7p 2l4",
    "addr:street":"100 St",
    "iso:country":"CA",
    "sg:address":"9008 100 St",
    "sg:city":"Westlock",
    "sg:classifiers":[
        {
            "category":"Wholesale",
            "subcategory":"Machinery & Supplies",
            "type":"Manufacturing & Wholesale Goods"
        }
    ],
    "sg:phone":"+1 780 349 2588",
    "sg:postcode":"T7P 2L4",
    "sg:province":"AB",
    "sg:tags":[
        "farm",
        "equipment"
    ],
    "wof:name":"K & M Farm Equipment Ltd",
    "wof:placetype":"venue"
},
  "geometry": {"coordinates":[-113.887580872,54.1526412964],"type":"Point"}
}