{
  "type": "Feature",
  "properties": {
    "addr:full":"19511 92 Ave Surrey BC V4N 4G6",
    "addr:housenumber":"19511",
    "addr:postcode":"v4n 4g6",
    "addr:street":"92 Ave",
    "iso:country":"CA",
    "sg:address":"19511 92 Ave",
    "sg:city":"Surrey",
    "sg:classifiers":[
        {
            "category":"Manufacturing",
            "subcategory":"Metals",
            "type":"Manufacturing & Wholesale Goods"
        }
    ],
    "sg:phone":"+1 604 888 0911",
    "sg:postcode":"V4N 4G6",
    "sg:province":"BC",
    "sg:tags":[
        "grating"
    ],
    "wof:name":"Fisher & Ludlow Inc",
    "wof:placetype":"venue"
},
  "geometry": {"coordinates":[-122.68190800000001,49.170406],"type":"Point"}
}