{
  "type": "Feature",
  "properties": {
    "addr:full":"7490 Rue Rollinat Laval QC H7R 5L6",
    "addr:housenumber":"7490",
    "addr:postcode":"h7r 5l6",
    "addr:street":"Rue Rollinat",
    "iso:country":"CA",
    "sg:address":"7490 Rue Rollinat",
    "sg:city":"Laval",
    "sg:classifiers":[
        {
            "category":"Shopping",
            "type":"Retail Goods"
        }
    ],
    "sg:phone":"+1 450 962 0694",
    "sg:postcode":"H7R 5L6",
    "sg:province":"QC",
    "sg:tags":[
        "equipment",
        "telephone",
        "supply"
    ],
    "wof:name":"Servitel",
    "wof:placetype":"venue"
},
  "geometry": {"coordinates":[-73.86004638670001,45.545879364],"type":"Point"}
}