{
  "type": "Feature",
  "properties": {
    "addr:full":"3028 53 St Delta BC V4L 2N5",
    "addr:housenumber":"3028",
    "addr:postcode":"v4l 2n5",
    "addr:street":"53 St",
    "iso:country":"CA",
    "sg:address":"3028 53 St",
    "sg:city":"Delta",
    "sg:classifiers":[
        {
            "category":"Building & Trades",
            "subcategory":"Plumbing",
            "type":"Services"
        }
    ],
    "sg:phone":"+1 604 946 9824",
    "sg:postcode":"V4L 2N5",
    "sg:province":"BC",
    "sg:tags":[
        "contractor"
    ],
    "wof:name":"Delta Plumbing Repairs",
    "wof:placetype":"venue"
},
  "geometry": {"coordinates":[-123.076843,49.058037],"type":"Point"}
}