{
  "type": "Feature",
  "properties": {
    "addr:full":"221 9th Ave S Cranbrook BC V1C 2M4",
    "addr:housenumber":"221",
    "addr:postcode":"bc v1c 2m4",
    "addr:street":"9Th Ave S",
    "iso:country":"CA",
    "sg:address":"221 9th Ave S",
    "sg:city":"Cranbrook",
    "sg:classifiers":[
        {
            "category":"Health Services",
            "subcategory":"Chiropractor",
            "type":"Services"
        }
    ],
    "sg:phone":"+1 250 426 8398",
    "sg:postcode":"V1C 2M4",
    "sg:province":"BC",
    "wof:name":"Mile, Edward Z DC",
    "wof:placetype":"venue"
},
  "geometry": {"coordinates":[-115.769188,49.508015],"type":"Point"}
}