{
  "type": "Feature",
  "properties": {
    "addr:full":"792 Gerrard St E Toronto ON M4M 1Y6",
    "addr:housenumber":"792",
    "addr:postcode":"m4m 1y6",
    "addr:street":"Gerrard St E",
    "iso:country":"CA",
    "sg:address":"792 Gerrard St E",
    "sg:city":"Toronto",
    "sg:classifiers":[
        {
            "category":"Food & Beverages",
            "subcategory":"Groceries & Convenience Stores",
            "type":"Retail Goods"
        }
    ],
    "sg:phone":"+1 416 465 3706",
    "sg:postcode":"M4M 1Y6",
    "sg:province":"ON",
    "sg:tags":[
        "grocer"
    ],
    "wof:name":"City Food Mart",
    "wof:placetype":"venue"
},
  "geometry": {"coordinates":[-79.345451,43.667156],"type":"Point"}
}