{
  "type": "Feature",
  "properties": {
    "addr:full":"9833 Tecumseh Rd E Windsor ON N8R 1A5",
    "addr:housenumber":"9833",
    "addr:postcode":"n8r 1a5",
    "addr:street":"Tecumseh Rd E",
    "iso:country":"CA",
    "sg:address":"9833 Tecumseh Rd E",
    "sg:city":"Windsor",
    "sg:classifiers":[
        {
            "category":"Health Services",
            "subcategory":"Doctor",
            "type":"Services"
        }
    ],
    "sg:phone":"+1 519 979 6141",
    "sg:postcode":"N8R 1A5",
    "sg:province":"ON",
    "sg:tags":[
        "physician",
        "surgeon"
    ],
    "wof:name":"Cygnus Cellulite & Skin",
    "wof:placetype":"venue"
},
  "geometry": {"coordinates":[-82.9190292358,42.3139953613],"type":"Point"}
}