{
  "type": "Feature",
  "properties": {
    "addr:full":"2079 Davenport Rd Toronto ON M6N 1C9",
    "addr:housenumber":"2079",
    "addr:postcode":"m6n 1c9",
    "addr:street":"Davenport Rd",
    "iso:country":"CA",
    "sg:address":"2079 Davenport Rd",
    "sg:city":"Toronto",
    "sg:classifiers":[
        {
            "category":"Manufacturing",
            "subcategory":"Jewelry",
            "type":"Manufacturing & Wholesale Goods"
        }
    ],
    "sg:phone":"+1 416 651 9934",
    "sg:postcode":"M6N 1C9",
    "sg:province":"ON",
    "wof:name":"S S Intl Jewellers",
    "wof:placetype":"venue"
},
  "geometry": {"coordinates":[-79.46106,43.670628],"type":"Point"}
}