{
  "type": "Feature",
  "properties": {
    "addr:full":"Highway 217 Tiverton NS B0V 1G0",
    "addr:postcode":"b0v 1g0",
    "addr:street":"Highway 217",
    "iso:country":"CA",
    "sg:address":"Highway 217",
    "sg:city":"Tiverton",
    "sg:classifiers":[
        {
            "category":"Retail",
            "subcategory":"Auto Repair",
            "type":"Services"
        }
    ],
    "sg:phone":"+1 902 839 2990",
    "sg:postcode":"B0V 1G0",
    "sg:province":"NS",
    "sg:tags":[
        "repairing",
        "automobile"
    ],
    "wof:name":"Rodlyn Auto Repair",
    "wof:placetype":"venue"
},
  "geometry": {"coordinates":[-66.21753699999999,44.384087],"type":"Point"}
}