{
  "type": "Feature",
  "properties": {
    "addr:full":"Sainte-Foy QC G1P 3X2",
    "addr:postcode":"g1p 3x2",
    "iso:country":"CA",
    "sg:city":"Sainte-Foy",
    "sg:classifiers":[
        {
            "category":"Wholesale",
            "subcategory":"Fruits & Vegetables",
            "type":"Manufacturing & Wholesale Goods"
        }
    ],
    "sg:phone":"+1 418 651 0980",
    "sg:postcode":"G1P 3X2",
    "sg:province":"QC",
    "wof:name":"Mar-Gi Fruit Inc",
    "wof:placetype":"venue"
},
  "geometry": {"coordinates":[-71.296768,46.790119],"type":"Point"}
}