{
  "type": "Feature",
  "properties": {
    "addr:full":"748 Guelph Line Burlington ON L7R 3N5",
    "addr:housenumber":"748",
    "addr:postcode":"l7r 3n5",
    "addr:street":"Guelph Line",
    "iso:country":"CA",
    "sg:address":"748 Guelph Line",
    "sg:city":"Burlington",
    "sg:classifiers":[
        {
            "category":"Banks & Credit Unions",
            "subcategory":"Bank",
            "type":"Services"
        }
    ],
    "sg:phone":"+1 905 631 1222",
    "sg:postcode":"L7R 3N5",
    "sg:province":"ON",
    "sg:tags":[
        "cashing",
        "loan",
        "check"
    ],
    "wof:name":"Cash Money Cheque Cashing",
    "wof:placetype":"venue"
},
  "geometry": {"coordinates":[-79.7955245972,43.3456954956],"type":"Point"}
}