{
  "type": "Feature",
  "properties": {
    "iso:country":"CA",
    "sg:address":"4430 13th Ave W",
    "sg:city":"Vancouver",
    "sg:classifiers":[
        {
            "category":"Real Estate",
            "subcategory":"Architect",
            "type":"Services"
        }
    ],
    "sg:phone":"+1 604 224 8820",
    "sg:postcode":"V6R 2V3",
    "sg:province":"BC",
    "wof:name":"Wiltshire, Walter Ian",
    "wof:placetype":"venue"
},
  "geometry": {"coordinates":[-123.207199097,49.2609443665],"type":"Point"}
}