{
  "type": "Feature",
  "properties": {
    "addr:full":"2965 Gordon Rd Regina SK S4S 6H7",
    "addr:housenumber":"2965",
    "addr:postcode":"s4s 6h7",
    "addr:street":"Gordon Rd",
    "iso:country":"CA",
    "sg:address":"2965 Gordon Rd",
    "sg:city":"Regina",
    "sg:classifiers":[
        {
            "category":"Shopping",
            "subcategory":"Shoes",
            "type":"Retail Goods"
        }
    ],
    "sg:phone":"+1 306 586 8722",
    "sg:postcode":"S4S 6H7",
    "sg:province":"SK",
    "wof:name":"Aldo Shoes",
    "wof:placetype":"venue"
},
  "geometry": {"coordinates":[-104.62309265099999,50.4046173096],"type":"Point"}
}