{
  "type": "Feature",
  "properties": {
    "addr:full":"Wakefield QC J0X 3G0",
    "addr:postcode":"j0x 3g0",
    "iso:country":"CA",
    "sg:city":"Wakefield",
    "sg:classifiers":[
        {
            "category":"Recreation",
            "type":"Entertainment"
        }
    ],
    "sg:phone":"+1 819 671 0014",
    "sg:postcode":"J0X 3G0",
    "sg:province":"QC",
    "sg:tags":[
        "provincial",
        "parks",
        "government"
    ],
    "wof:name":"Val Des Monts Ecole L'Equipage",
    "wof:placetype":"venue"
},
  "geometry": {"coordinates":[-75.92881,45.634491],"type":"Point"}
}