{
  "type": "Feature",
  "properties": {
    "addr:full":"440 10 St SW Salmon Arm BC V1E 1T1",
    "addr:postcode":"440 10;v1e 1t1",
    "addr:street":"St Sw",
    "iso:country":"CA",
    "sg:address":"440 10 St SW",
    "sg:city":"Salmon Arm",
    "sg:classifiers":[
        {
            "category":"Retail",
            "subcategory":"Funeral Services",
            "type":"Services"
        }
    ],
    "sg:phone":"+1 250 832 2223",
    "sg:postcode":"V1E 1T1",
    "sg:province":"BC",
    "sg:tags":[
        "director"
    ],
    "wof:name":"Bowers Funeral Svc Ltd",
    "wof:placetype":"venue"
},
  "geometry": {"coordinates":[-119.29650100000001,50.69548],"type":"Point"}
}