{
  "type": "Feature",
  "properties": {
    "addr:full":"735 Boul Taschereau Longueuil QC J4K 2W8",
    "addr:housenumber":"735",
    "addr:postcode":"j4k 2w8",
    "addr:street":"Boul Taschereau",
    "iso:country":"CA",
    "sg:address":"735 Boul Taschereau",
    "sg:city":"Longueuil",
    "sg:classifiers":[
        {
            "category":"Retail",
            "subcategory":"Auto Repair",
            "type":"Services"
        }
    ],
    "sg:phone":"+1 450 670 9241",
    "sg:postcode":"J4K 2W8",
    "sg:province":"QC",
    "sg:tags":[
        "body",
        "automobile",
        "painting"
    ],
    "wof:name":"Carrosserie Metro",
    "wof:placetype":"venue"
},
  "geometry": {"coordinates":[-73.51288599999999,45.517906],"type":"Point"}
}