{
  "type": "Feature",
  "properties": {
    "iso:country":"CA",
    "sg:address":"735 Boul Taschereau",
    "sg:city":"Longueuil",
    "sg:classifiers":[
        {
            "category":"Retail",
            "subcategory":"Auto Repair",
            "type":"Services"
        }
    ],
    "sg:phone":"+1 450 670 9241",
    "sg:postcode":"J4K 2W8",
    "sg:province":"QC",
    "sg:tags":[
        "body",
        "automobile",
        "painting"
    ],
    "wof:name":"Carrosserie Metro",
    "wof:placetype":"venue"
},
  "geometry": {"coordinates":[-73.512886,45.517906],"type":"Point"}
}