{
  "type": "Feature",
  "properties": {
    "addr:full":"611 Keele St Toronto ON M6N 3E5",
    "addr:housenumber":"611",
    "addr:postcode":"m6n 3e5",
    "addr:street":"Keele St",
    "iso:country":"CA",
    "sg:address":"611 Keele St",
    "sg:city":"Toronto",
    "sg:classifiers":[
        {
            "category":"Retail",
            "subcategory":"Car Wash",
            "type":"Services"
        }
    ],
    "sg:phone":"+1 416 766 7510",
    "sg:postcode":"M6N 3E5",
    "sg:province":"ON",
    "sg:tags":[
        "polishing",
        "washing"
    ],
    "wof:name":"Jet Kleen Coin Car Wash",
    "wof:placetype":"venue"
},
  "geometry": {"coordinates":[-79.467056,43.671684],"type":"Point"}
}