{
  "type": "Feature",
  "properties": {
    "addr:full":"76 Nail Pond Rd Tignish PE C0B 2B0",
    "addr:housenumber":"76",
    "addr:postcode":"c0b 2b0",
    "addr:street":"Nail Pond Rd",
    "iso:country":"CA",
    "sg:address":"76 Nail Pond Rd",
    "sg:city":"Tignish",
    "sg:classifiers":[
        {
            "category":"Personal",
            "subcategory":"Beauty Salon",
            "type":"Services"
        }
    ],
    "sg:phone":"+1 902 882 3574",
    "sg:postcode":"C0B 2B0",
    "sg:province":"PE",
    "wof:name":"Emily's Hair Salon",
    "wof:placetype":"venue"
},
  "geometry": {"coordinates":[-64.0333862305,46.9513168335],"type":"Point"}
}