{
  "type": "Feature",
  "properties": {
    "addr:full":"5 Chester St Winnipeg MB R2L 1W5",
    "addr:housenumber":"5",
    "addr:postcode":"r2l 1w5",
    "addr:street":"Chester St",
    "iso:country":"CA",
    "sg:address":"5 Chester St",
    "sg:city":"Winnipeg",
    "sg:classifiers":[
        {
            "category":"Wholesale",
            "subcategory":"Motor Vehicles",
            "type":"Manufacturing & Wholesale Goods"
        }
    ],
    "sg:phone":"+1 204 667 1553",
    "sg:postcode":"R2L 1W5",
    "sg:province":"MB",
    "sg:tags":[
        "body",
        "equipment",
        "truck"
    ],
    "wof:name":"Nord-Sen Metal Industries Ltd",
    "wof:placetype":"venue"
},
  "geometry": {"coordinates":[-97.0888748169,49.9007034302],"type":"Point"}
}