{
  "type": "Feature",
  "properties": {
    "iso:country":"CA",
    "sg:address":"9790 Second St # 106",
    "sg:city":"Sidney",
    "sg:classifiers":[
        {
            "category":"Shopping",
            "subcategory":"Clothing, Apparel, & Fashions",
            "type":"Retail Goods"
        }
    ],
    "sg:phone":"+1 250 655 6535",
    "sg:postcode":"V8L 3Y8",
    "sg:province":"BC",
    "sg:tags":[
        "theatrical",
        "costume"
    ],
    "wof:name":"Stansfield, Jane",
    "wof:placetype":"venue"
},
  "geometry": {"coordinates":[-123.396751404,48.648601532],"type":"Point"}
}