{
  "type": "Feature",
  "properties": {
    "addr:full":"1277 Main St Smithers BC V0J 2N0",
    "addr:housenumber":"1277",
    "addr:postcode":"v0j 2n0",
    "addr:street":"Main St",
    "iso:country":"CA",
    "sg:address":"1277 Main St",
    "sg:city":"Smithers",
    "sg:classifiers":[
        {
            "category":"Health Services",
            "subcategory":"Clinic",
            "type":"Services"
        }
    ],
    "sg:phone":"+1 250 847 8871",
    "sg:postcode":"V0J 2N0",
    "sg:province":"BC",
    "sg:tags":[
        "food",
        "herbalist",
        "organic"
    ],
    "wof:name":"Narnia Farms",
    "wof:placetype":"venue"
},
  "geometry": {"coordinates":[-127.16915899999999,54.781025],"type":"Point"}
}