{
  "type": "Feature",
  "properties": {
    "iso:country":"CA",
    "sg:address":"2124 18E Rue",
    "sg:city":"Quebec",
    "sg:classifiers":[
        {
            "category":"Insurance",
            "subcategory":"Insurance Agent",
            "type":"Services"
        }
    ],
    "sg:phone":"+1 418 667 0510",
    "sg:postcode":"G1J 2A6",
    "sg:province":"QC",
    "sg:tags":[
        "technical",
        "adjuster",
        "expertise",
        "analysis"
    ],
    "wof:name":"Michaud & Freres Inc",
    "wof:placetype":"venue"
},
  "geometry": {"coordinates":[-71.21918487550001,46.8401679993],"type":"Point"}
}