{
  "type": "Feature",
  "properties": {
    "addr:full":"561 Victoria Ave W Winnipeg MB R2C 1T3",
    "addr:housenumber":"561",
    "addr:postcode":"r2c 1t3",
    "addr:street":"Victoria Ave W",
    "iso:country":"CA",
    "sg:address":"561 Victoria Ave W",
    "sg:city":"Winnipeg",
    "sg:classifiers":[
        {
            "category":"Manufacturing",
            "subcategory":"Building Materials",
            "type":"Manufacturing & Wholesale Goods"
        }
    ],
    "sg:phone":"+1 204 224 4099",
    "sg:postcode":"R2C 1T3",
    "sg:province":"MB",
    "wof:name":"Grade A Millwork",
    "wof:placetype":"venue"
},
  "geometry": {"coordinates":[-97.018196,49.896168],"type":"Point"}
}