{
  "type": "Feature",
  "properties": {
    "iso:country":"CA",
    "sg:address":"7 High St",
    "sg:city":"Grand Falls-Windsor",
    "sg:classifiers":[
        {
            "category":"Health Services",
            "subcategory":"Health Practitioner",
            "type":"Services"
        }
    ],
    "sg:phone":"+1 709 489 7730",
    "sg:postcode":"A2A 1C3",
    "sg:province":"NL",
    "sg:tags":[
        "psychologist"
    ],
    "wof:name":"Pathways Consulting Inc",
    "wof:placetype":"venue"
},
  "geometry": {"coordinates":[-55.6589431763,48.9276428223],"type":"Point"}
}