{
  "type": "Feature",
  "properties": {
    "addr:full":"Calgary AB T2P 0S2",
    "addr:postcode":"t2p 0s2",
    "iso:country":"CA",
    "sg:city":"Calgary",
    "sg:classifiers":[
        {
            "category":"Mining & Drilling",
            "type":"Manufacturing & Wholesale Goods"
        }
    ],
    "sg:phone":"+1 403 262 9226",
    "sg:postcode":"T2P 0S2",
    "sg:province":"AB",
    "sg:tags":[
        "company",
        "oil"
    ],
    "wof:name":"C 2 Energy Inc",
    "wof:placetype":"venue"
},
  "geometry": {"coordinates":[-114.072601318,51.0478248596],"type":"Point"}
}