{
  "type": "Feature",
  "properties": {
    "iso:country":"CA",
    "sg:address":"1262 Don Mills Rd",
    "sg:city":"North York",
    "sg:classifiers":[
        {
            "category":"Building & Trades",
            "subcategory":"Cleaning & Sanitation",
            "type":"Services"
        }
    ],
    "sg:phone":"+1 416 445 3094",
    "sg:postcode":"M3B 2W7",
    "sg:province":"ON",
    "sg:tags":[
        "janitor"
    ],
    "wof:name":"J & B Building Maintenance Ltd",
    "wof:placetype":"venue"
},
  "geometry": {"coordinates":[-79.34548950200001,43.7437553406],"type":"Point"}
}