{
  "type": "Feature",
  "properties": {
    "addr:full":"Calgary AB T2N 1V7",
    "addr:postcode":"t2n 1v7",
    "iso:country":"CA",
    "sg:city":"Calgary",
    "sg:classifiers":[
        {
            "category":"Shopping",
            "subcategory":"Shoes",
            "type":"Retail Goods"
        }
    ],
    "sg:phone":"+1 403 270 7317",
    "sg:postcode":"T2N 1V7",
    "sg:province":"AB",
    "sg:tags":[
        "sporting"
    ],
    "wof:name":"Running Room Ltd",
    "wof:placetype":"venue"
},
  "geometry": {"coordinates":[-114.08609,51.054455],"type":"Point"}
}