{
  "type": "Feature",
  "properties": {
    "addr:full":"172 Main St E Hamilton ON L8N 1G9",
    "addr:housenumber":"172",
    "addr:postcode":"l8n 1g9",
    "addr:street":"Main St E",
    "iso:country":"CA",
    "sg:address":"172 Main St E",
    "sg:city":"Hamilton",
    "sg:classifiers":[
        {
            "category":"Professional",
            "subcategory":"Lawyer & Legal Services",
            "type":"Services"
        }
    ],
    "sg:phone":"+1 905 572 6611",
    "sg:postcode":"L8N 1G9",
    "sg:province":"ON",
    "sg:tags":[
        "attorney"
    ],
    "wof:name":"Vandenberg, Jennifer M",
    "wof:placetype":"venue"
},
  "geometry": {"coordinates":[-79.86264,43.253567],"type":"Point"}
}