{
  "type": "Feature",
  "properties": {
    "iso:country":"CA",
    "sg:address":"450 2nd St",
    "sg:city":"Sointula",
    "sg:classifiers":[
        {
            "category":"Manufacturing",
            "subcategory":"Food",
            "type":"Manufacturing & Wholesale Goods"
        }
    ],
    "sg:phone":"+1 250 973 6459",
    "sg:postcode":"V0N 3E0",
    "sg:province":"BC",
    "sg:tags":[
        "smoking",
        "fish",
        "curing"
    ],
    "wof:name":"Coast Select Smokehouse",
    "wof:placetype":"venue"
},
  "geometry": {"coordinates":[-127.016685486,50.6290359497],"type":"Point"}
}