{
  "type": "Feature",
  "properties": {
    "iso:country":"CA",
    "sg:address":"302 Sandy Beach Rd",
    "sg:city":"Dryden",
    "sg:classifiers":[
        {
            "category":"Building & Trades",
            "subcategory":"Construction",
            "type":"Services"
        }
    ],
    "sg:phone":"+1 807 223 8898",
    "sg:postcode":"P8N 2Y4",
    "sg:province":"ON",
    "sg:tags":[
        "elevator"
    ],
    "wof:name":"Otis Canada Inc",
    "wof:placetype":"venue"
},
  "geometry": {"coordinates":[-92.81829833979999,49.771156311],"type":"Point"}
}