{
  "type": "Feature",
  "properties": {
    "addr:full":"Squatec QC G0L 4H0",
    "addr:postcode":"g0l 4h0",
    "iso:country":"CA",
    "sg:city":"Squatec",
    "sg:classifiers":[
        {
            "category":"Manufacturing",
            "subcategory":"Building Materials",
            "type":"Manufacturing & Wholesale Goods"
        }
    ],
    "sg:phone":"+1 418 855 2033",
    "sg:postcode":"G0L 4H0",
    "sg:province":"QC",
    "sg:tags":[
        "lumber"
    ],
    "wof:name":"Richard Pelletier & Fils Inc",
    "wof:placetype":"venue"
},
  "geometry": {"coordinates":[-68.7172470093,47.8821983337],"type":"Point"}
}