{
  "type": "Feature",
  "properties": {
    "addr:full":"2 Rankin Crt Dundas ON L9H 6S3",
    "addr:housenumber":"2",
    "addr:postcode":"l9h 6s3",
    "addr:street":"Rankin Crt",
    "iso:country":"CA",
    "sg:address":"2 Rankin Crt",
    "sg:city":"Dundas",
    "sg:classifiers":[
        {
            "category":"Wholesale",
            "subcategory":"Electrical",
            "type":"Manufacturing & Wholesale Goods"
        }
    ],
    "sg:phone":"+1 905 628 0704",
    "sg:postcode":"L9H 6S3",
    "sg:province":"ON",
    "sg:tags":[
        "game",
        "video"
    ],
    "wof:name":"Ultimate Video Game Accessorie",
    "wof:placetype":"venue"
},
  "geometry": {"coordinates":[-79.98328399659999,43.2558479309],"type":"Point"}
}