{
  "type": "Feature",
  "properties": {
    "addr:full":"Belleville ON K8N 4Z7",
    "addr:postcode":"k8n 4z7",
    "iso:country":"CA",
    "sg:city":"Belleville",
    "sg:classifiers":[
        {
            "category":"Manufacturing",
            "subcategory":"Tools & Machinery",
            "type":"Manufacturing & Wholesale Goods"
        }
    ],
    "sg:phone":"+1 613 966 1134",
    "sg:postcode":"K8N 4Z7",
    "sg:province":"ON",
    "sg:tags":[
        "refrigeration",
        "refrigerating"
    ],
    "wof:name":"Bentley Heating & Air Cond",
    "wof:placetype":"venue"
},
  "geometry": {"coordinates":[-77.38189697270001,44.1610450745],"type":"Point"}
}