{
  "type": "Feature",
  "properties": {
    "iso:country":"CA",
    "sg:address":"277 Lakeshore Rd E",
    "sg:city":"Oakville",
    "sg:classifiers":[
        {
            "category":"Professional",
            "subcategory":"Lawyer & Legal Services",
            "type":"Services"
        }
    ],
    "sg:phone":"+1 905 845 7591",
    "sg:postcode":"L6J 6J3",
    "sg:province":"ON",
    "sg:tags":[
        "attorney"
    ],
    "wof:name":"Legal Aid Ontario",
    "wof:placetype":"venue"
},
  "geometry": {"coordinates":[-79.66677856450001,43.4473114014],"type":"Point"}
}