{
  "type": "Feature",
  "properties": {
    "addr:full":"6739 Norwest Bay Rd Sechelt BC V0N 3A8",
    "addr:housenumber":"6739",
    "addr:postcode":"v0n 3a8",
    "addr:street":"Norwest Bay Rd",
    "iso:country":"CA",
    "sg:address":"6739 Norwest Bay Rd",
    "sg:city":"Sechelt",
    "sg:classifiers":[
        {
            "category":"Home & Garden",
            "subcategory":"Garden Supply",
            "type":"Retail Goods"
        }
    ],
    "sg:phone":"+1 604 885 3989",
    "sg:postcode":"V0N 3A8",
    "sg:province":"BC",
    "sg:tags":[
        "nurseryman"
    ],
    "wof:name":"Willow Farm Nursery",
    "wof:placetype":"venue"
},
  "geometry": {"coordinates":[-123.814308,49.478573],"type":"Point"}
}