{
  "type": "Feature",
  "properties": {
    "iso:country":"CA",
    "sg:address":"172 Bullock Dr # 26",
    "sg:city":"Markham",
    "sg:classifiers":[
        {
            "category":"Building & Trades",
            "subcategory":"Construction",
            "type":"Services"
        }
    ],
    "sg:phone":"+1 905 294 7927",
    "sg:postcode":"L3P 7M9",
    "sg:province":"ON",
    "sg:tags":[
        "masonry",
        "contractor"
    ],
    "wof:name":"Emco Masonry Ltd",
    "wof:placetype":"venue"
},
  "geometry": {"coordinates":[-79.278297,43.875137],"type":"Point"}
}