{
  "type": "Feature",
  "properties": {
    "addr:full":"Brampton ON L7A 1B4",
    "addr:postcode":"l7a 1b4",
    "iso:country":"CA",
    "sg:city":"Brampton",
    "sg:classifiers":[
        {
            "category":"Building & Trades",
            "subcategory":"Construction",
            "type":"Services"
        }
    ],
    "sg:phone":"+1 905 840 5577",
    "sg:postcode":"L7A 1B4",
    "sg:province":"ON",
    "sg:tags":[
        "plumbing",
        "contractor",
        "drainage"
    ],
    "wof:name":"Bossco Plumbing & Heating Ltd",
    "wof:placetype":"venue"
},
  "geometry": {"coordinates":[-79.805770874,43.7042350769],"type":"Point"}
}