{
  "type": "Feature",
  "properties": {
    "addr:full":"4455 Rue Sherbrooke O Westmount QC H3Z 1E7",
    "addr:housenumber":"4455",
    "addr:postcode":"h3z 1e7",
    "addr:street":"Rue Sherbrooke O",
    "iso:country":"CA",
    "sg:address":"4455 Rue Sherbrooke O",
    "sg:city":"Westmount",
    "sg:classifiers":[
        {
            "category":"Real Estate",
            "subcategory":"Architect",
            "type":"Services"
        }
    ],
    "sg:phone":"+1 514 931 5871",
    "sg:postcode":"H3Z 1E7",
    "sg:province":"QC",
    "wof:name":"Bobrow Architects",
    "wof:placetype":"venue"
},
  "geometry": {"coordinates":[-73.5979,45.484028],"type":"Point"}
}