{
  "type": "Feature",
  "properties": {
    "addr:full":"169 South Service Rd Grimsby ON L3M 4H6",
    "addr:housenumber":"169",
    "addr:postcode":"l3m 4h6",
    "addr:street":"South Service Rd",
    "iso:country":"CA",
    "sg:address":"169 South Service Rd",
    "sg:city":"Grimsby",
    "sg:classifiers":[
        {
            "category":"Building & Trades",
            "subcategory":"Plumbing",
            "type":"Services"
        }
    ],
    "sg:phone":"+1 905 945 5992",
    "sg:postcode":"L3M 4H6",
    "sg:province":"ON",
    "sg:tags":[
        "sheet",
        "work",
        "metal",
        "contractor"
    ],
    "wof:name":"Empire Manufacturing",
    "wof:placetype":"venue"
},
  "geometry": {"coordinates":[-79.51649500000001,43.189075],"type":"Point"}
}