{
  "type": "Feature",
  "properties": {
    "addr:full":"London ON N6H 4S4",
    "addr:postcode":"n6h 4s4",
    "iso:country":"CA",
    "sg:city":"London",
    "sg:classifiers":[
        {
            "category":"Health Services",
            "subcategory":"Health Practitioner",
            "type":"Services"
        }
    ],
    "sg:phone":"+1 519 432 2251",
    "sg:postcode":"N6H 4S4",
    "sg:province":"ON",
    "sg:tags":[
        "physician",
        "surgeon",
        "audiologists"
    ],
    "wof:name":"London Ear Clinic",
    "wof:placetype":"venue"
},
  "geometry": {"coordinates":[-81.27629852290001,42.9887580872],"type":"Point"}
}