{
  "type": "Feature",
  "properties": {
    "addr:full":"71 Stafford St Crossfield AB T0M 0S0",
    "addr:housenumber":"71",
    "addr:postcode":"t0m 0s0",
    "addr:street":"Stafford St",
    "iso:country":"CA",
    "sg:address":"71 Stafford St",
    "sg:city":"Crossfield",
    "sg:classifiers":[
        {
            "category":"Retail",
            "subcategory":"Laundry & Dry Cleaning",
            "type":"Services"
        }
    ],
    "sg:phone":"+1 403 946 0050",
    "sg:postcode":"T0M 0S0",
    "sg:province":"AB",
    "sg:tags":[
        "cleaners",
        "rug",
        "carpet"
    ],
    "wof:name":"Rockyview Carpet Cleaning",
    "wof:placetype":"venue"
},
  "geometry": {"coordinates":[-114.03420300000001,51.432503],"type":"Point"}
}