{
  "type": "Feature",
  "properties": {
    "addr:full":"Yorkton SK S3N 3Z3",
    "addr:postcode":"s3n 3z3",
    "iso:country":"CA",
    "sg:city":"Yorkton",
    "sg:classifiers":[
        {
            "category":"Health Services",
            "subcategory":"Medical Lab",
            "type":"Services"
        }
    ],
    "sg:phone":"+1 306 783 6776",
    "sg:postcode":"S3N 3Z3",
    "sg:province":"SK",
    "wof:name":"Parkland Denture Clinic",
    "wof:placetype":"venue"
},
  "geometry": {"coordinates":[-102.437973,51.210423],"type":"Point"}
}