{
  "type": "Feature",
  "properties": {
    "addr:full":"11053 Boul Louis-H.-Lafontaine Anjou QC H1J 3A3",
    "addr:housenumber":"11053",
    "addr:postcode":"h1j 3a3",
    "addr:street":"Boul Louis-H.-Lafontaine",
    "iso:country":"CA",
    "sg:address":"11053 Boul Louis-H.-Lafontaine",
    "sg:city":"Anjou",
    "sg:classifiers":[
        {
            "category":"Restaurant",
            "type":"Food & Drink"
        }
    ],
    "sg:phone":"+1 514 383 0556",
    "sg:postcode":"H1J 3A3",
    "sg:province":"QC",
    "sg:tags":[
        "delicatessen"
    ],
    "wof:name":"Aliments Prince Sec",
    "wof:placetype":"venue"
},
  "geometry": {"coordinates":[-73.5900344849,45.6144332886],"type":"Point"}
}