{
  "type": "Feature",
  "properties": {
    "iso:country":"CA",
    "sg:address":"1380 Rue Joliot-Curie",
    "sg:city":"Boucherville",
    "sg:classifiers":[
        {
            "category":"Wholesale",
            "subcategory":"Machinery & Supplies",
            "type":"Manufacturing & Wholesale Goods"
        }
    ],
    "sg:phone":"+1 450 655 6676",
    "sg:postcode":"J4B 7L9",
    "sg:province":"QC",
    "sg:tags":[
        "roofing",
        "equipment"
    ],
    "wof:name":"Soprema Inc",
    "wof:placetype":"venue"
},
  "geometry": {"coordinates":[-73.43528747560001,45.5581016541],"type":"Point"}
}