{
  "type": "Feature",
  "properties": {
    "addr:full":"160 Cooledge Ch Mansonville QC J0E 1X0",
    "addr:housenumber":"160",
    "addr:postcode":"j0e 1x0",
    "addr:street":"Cooledge Ch Mansonville",
    "iso:country":"CA",
    "sg:address":"160 Cooledge Ch",
    "sg:city":"Mansonville",
    "sg:classifiers":[
        {
            "category":"Travel",
            "subcategory":"Hotels & Motels",
            "type":"Entertainment"
        }
    ],
    "sg:phone":"+1 450 292 3246",
    "sg:postcode":"J0E 1X0",
    "sg:province":"QC",
    "sg:tags":[
        "inn"
    ],
    "wof:name":"L'Aubergine",
    "wof:placetype":"venue"
},
  "geometry": {"coordinates":[-72.392197,45.04887],"type":"Point"}
}