{
  "type": "Feature",
  "properties": {
    "addr:full":"3300 Ch Royal Beauport QC G1E 1V6",
    "addr:postcode":"3300;qc g1e 1v6",
    "addr:street":"Ch Royal",
    "iso:country":"CA",
    "sg:address":"3300 Ch Royal",
    "sg:city":"Beauport",
    "sg:classifiers":[
        {
            "category":"Recreation",
            "type":"Entertainment"
        }
    ],
    "sg:phone":"+1 418 666 2172",
    "sg:postcode":"G1E 1V6",
    "sg:province":"QC",
    "sg:tags":[
        "government",
        "hall",
        "auditorium"
    ],
    "wof:name":"Beauport Chalet St-Ignace",
    "wof:placetype":"venue"
},
  "geometry": {"coordinates":[-71.208466,46.852036],"type":"Point"}
}