{
  "type": "Feature",
  "properties": {
    "addr:full":"41 Main St Ashern MB R0C 0E0",
    "addr:housenumber":"41",
    "addr:postcode":"r0c 0e0",
    "addr:street":"Main St",
    "iso:country":"CA",
    "sg:address":"41 Main St",
    "sg:city":"Ashern",
    "sg:classifiers":[
        {
            "category":"Restaurant",
            "type":"Food & Drink"
        }
    ],
    "sg:phone":"+1 204 768 3500",
    "sg:postcode":"R0C 0E0",
    "sg:province":"MB",
    "wof:name":"Chicken Chef",
    "wof:placetype":"venue"
},
  "geometry": {"coordinates":[-98.3502655029,51.1808052063],"type":"Point"}
}