{
  "type": "Feature",
  "properties": {
    "iso:country":"CA",
    "sg:city":"Sainte-Foy",
    "sg:classifiers":[
        {
            "category":"Food & Beverages",
            "subcategory":"Dairy",
            "type":"Retail Goods"
        }
    ],
    "sg:phone":"+1 418 651 5220",
    "sg:postcode":"G1X 4X7",
    "sg:province":"QC",
    "sg:tags":[
        "cheese"
    ],
    "wof:name":"Saputo Fromages Ltee",
    "wof:placetype":"venue"
},
  "geometry": {"coordinates":[-71.3303451538,46.7822151184],"type":"Point"}
}