{
  "type": "Feature",
  "properties": {
    "addr:full":"1498 Rue Ontario E Montreal QC H2L 1S3",
    "addr:housenumber":"1498",
    "addr:postcode":"h2l 1s3",
    "addr:street":"Rue Ontario E",
    "iso:country":"CA",
    "sg:address":"1498 Rue Ontario E",
    "sg:city":"Montreal",
    "sg:classifiers":[
        {
            "category":"Personal",
            "subcategory":"Beauty Salon",
            "type":"Services"
        }
    ],
    "sg:phone":"+1 514 524 0484",
    "sg:postcode":"H2L 1S3",
    "sg:province":"QC",
    "wof:name":"Salon Hair",
    "wof:placetype":"venue"
},
  "geometry": {"coordinates":[-73.560379,45.524227],"type":"Point"}
}