{
  "type": "Feature",
  "properties": {
    "addr:full":"3 Hillyard St Hamilton ON L8L 6A9",
    "addr:housenumber":"3",
    "addr:postcode":"l8l 6a9",
    "addr:street":"Hillyard St",
    "iso:country":"CA",
    "sg:address":"3 Hillyard St",
    "sg:city":"Hamilton",
    "sg:classifiers":[
        {
            "category":"Wholesale",
            "subcategory":"Scrap",
            "type":"Manufacturing & Wholesale Goods"
        }
    ],
    "sg:phone":"+1 905 577 9333",
    "sg:postcode":"L8L 6A9",
    "sg:province":"ON",
    "sg:tags":[
        "recycling",
        "center"
    ],
    "wof:name":"Plaza Integrated Environments",
    "wof:placetype":"venue"
},
  "geometry": {"coordinates":[-79.840965,43.263229],"type":"Point"}
}