{
  "type": "Feature",
  "properties": {
    "iso:country":"CA",
    "sg:address":"844 Niagara St",
    "sg:city":"Welland",
    "sg:classifiers":[
        {
            "category":"Health Services",
            "subcategory":"Doctor",
            "type":"Services"
        }
    ],
    "sg:phone":"+1 905 732 6104",
    "sg:postcode":"L3C 1M3",
    "sg:province":"ON",
    "sg:tags":[
        "dentist"
    ],
    "wof:name":"Lew, George W DDS",
    "wof:placetype":"venue"
},
  "geometry": {"coordinates":[-79.2496337891,43.0187263489],"type":"Point"}
}