{
  "type": "Feature",
  "properties": {
    "addr:full":"Kelowna BC V1Y 2E4",
    "addr:postcode":"v1y 2e4",
    "iso:country":"CA",
    "sg:city":"Kelowna",
    "sg:classifiers":[
        {
            "category":"Professional",
            "subcategory":"Accounting & Tax Preparation",
            "type":"Services"
        }
    ],
    "sg:phone":"+1 250 763 8919",
    "sg:postcode":"V1Y 2E4",
    "sg:province":"BC",
    "sg:tags":[
        "accountant"
    ],
    "wof:name":"Allwright, Roberta",
    "wof:placetype":"venue"
},
  "geometry": {"coordinates":[-119.49168396,49.8874092102],"type":"Point"}
}