{
  "type": "Feature",
  "properties": {
    "iso:country":"CA",
    "sg:address":"527 Mackenzie Ave S # C",
    "sg:city":"Williams Lake",
    "sg:classifiers":[
        {
            "category":"Shopping",
            "subcategory":"Clothing, Apparel, & Fashions",
            "type":"Retail Goods"
        }
    ],
    "sg:phone":"+1 250 392 5362",
    "sg:postcode":"V2G 1C8",
    "sg:province":"BC",
    "sg:tags":[
        "tackle",
        "salvage",
        "fishing",
        "merchandise",
        "surplus"
    ],
    "wof:name":"Surplus Herby's",
    "wof:placetype":"venue"
},
  "geometry": {"coordinates":[-122.139549,52.122852],"type":"Point"}
}