{
  "type": "Feature",
  "properties": {
    "addr:full":"Shawinigan QC G9N 1E9",
    "addr:postcode":"g9n 1e9",
    "iso:country":"CA",
    "sg:city":"Shawinigan",
    "sg:classifiers":[
        {
            "category":"Manufacturing",
            "subcategory":"Printing",
            "type":"Manufacturing & Wholesale Goods"
        }
    ],
    "sg:phone":"+1 819 536 3085",
    "sg:postcode":"G9N 1E9",
    "sg:province":"QC",
    "sg:tags":[
        "building",
        "parks"
    ],
    "wof:name":"Edifice Place Cascade Inc",
    "wof:placetype":"venue"
},
  "geometry": {"coordinates":[-72.751724,46.540504],"type":"Point"}
}