{
  "type": "Feature",
  "properties": {
    "addr:full":"Moncton NB E1C 2T3",
    "addr:postcode":"e1c 2t3",
    "iso:country":"CA",
    "sg:city":"Moncton",
    "sg:classifiers":[
        {
            "category":"Health Services",
            "subcategory":"Doctor",
            "type":"Services"
        }
    ],
    "sg:phone":"+1 506 857 0015",
    "sg:postcode":"E1C 2T3",
    "sg:province":"NB",
    "sg:tags":[
        "physician",
        "surgeon"
    ],
    "wof:name":"Richard, Ceri Dwen MD",
    "wof:placetype":"venue"
},
  "geometry": {"coordinates":[-64.8220367432,46.1056785583],"type":"Point"}
}