{
  "type": "Feature",
  "properties": {
    "addr:full":"19267 Lougheed Hwy Pitt Meadows BC V3Y 2J5",
    "addr:housenumber":"19267",
    "addr:postcode":"v3y 2j5",
    "addr:street":"Lougheed Hwy",
    "iso:country":"CA",
    "sg:address":"19267 Lougheed Hwy",
    "sg:city":"Pitt Meadows",
    "sg:classifiers":[
        {
            "category":"Bars & Pubs",
            "type":"Food & Drink"
        }
    ],
    "sg:phone":"+1 604 460 1507",
    "sg:postcode":"V3Y 2J5",
    "sg:province":"BC",
    "wof:name":"Jersey Joe's Sports Bar & Grll",
    "wof:placetype":"venue"
},
  "geometry": {"coordinates":[-122.687843,49.23061],"type":"Point"}
}