{
  "type": "Feature",
  "properties": {
    "iso:country":"CA",
    "sg:address":"66 Boul Industriel",
    "sg:city":"Saint-Eustache",
    "sg:classifiers":[
        {
            "category":"Recreation",
            "type":"Entertainment"
        }
    ],
    "sg:phone":"+1 450 472 6032",
    "sg:postcode":"J7R 5C2",
    "sg:province":"QC",
    "sg:tags":[
        "hall",
        "auditorium"
    ],
    "wof:name":"Salle DE Reception LA Rigole",
    "wof:placetype":"venue"
},
  "geometry": {"coordinates":[-73.92063903810001,45.5699234009],"type":"Point"}
}