{
  "type": "Feature",
  "properties": {
    "addr:full":"998 East Ave Pincher Creek AB T0K 1W0",
    "addr:housenumber":"998",
    "addr:postcode":"t0k 1w0",
    "addr:street":"East Ave",
    "iso:country":"CA",
    "sg:address":"998 East Ave",
    "sg:city":"Pincher Creek",
    "sg:classifiers":[
        {
            "category":"Shopping",
            "type":"Retail Goods"
        }
    ],
    "sg:phone":"+1 403 627 4012",
    "sg:postcode":"T0K 1W0",
    "sg:province":"AB",
    "sg:tags":[
        "stamp",
        "collector",
        "for"
    ],
    "wof:name":"Canada Post Corp",
    "wof:placetype":"venue"
},
  "geometry": {"coordinates":[-113.94812,49.485516],"type":"Point"}
}