{
  "type": "Feature",
  "properties": {
    "addr:full":"Lindsay ON K9V 6A5",
    "addr:postcode":"k9v 6a5",
    "iso:country":"CA",
    "sg:city":"Lindsay",
    "sg:classifiers":[
        {
            "category":"Shopping",
            "type":"Retail Goods"
        }
    ],
    "sg:phone":"+1 705 324 9628",
    "sg:postcode":"K9V 6A5",
    "sg:province":"ON",
    "sg:tags":[
        "supply",
        "equipment",
        "audiologists",
        "hearing",
        "impaired"
    ],
    "wof:name":"Helix Hearing Care Ctr",
    "wof:placetype":"venue"
},
  "geometry": {"coordinates":[-78.74109649659999,44.3527908325],"type":"Point"}
}