{
  "type": "Feature",
  "properties": {
    "addr:full":"91 Marion Ave Oxbow SK S0C 2B0",
    "addr:housenumber":"91",
    "addr:postcode":"s0c 2b0",
    "addr:street":"Marion Ave",
    "iso:country":"CA",
    "sg:address":"91 Marion Ave",
    "sg:city":"Oxbow",
    "sg:classifiers":[
        {
            "category":"Autos & Motor Vehicles",
            "subcategory":"Auto Supplies",
            "type":"Retail Goods"
        }
    ],
    "sg:phone":"+1 306 483 2379",
    "sg:postcode":"S0C 2B0",
    "sg:province":"SK",
    "sg:tags":[
        "automobile",
        "parts"
    ],
    "wof:name":"C Line",
    "wof:placetype":"venue"
},
  "geometry": {"coordinates":[-102.172516,49.228073],"type":"Point"}
}