{
  "type": "Feature",
  "properties": {
    "iso:country":"CA",
    "sg:address":"1310 Boul Taschereau",
    "sg:city":"Lemoyne",
    "sg:classifiers":[
        {
            "category":"Autos & Motor Vehicles",
            "subcategory":"Automobile Sales",
            "type":"Retail Goods"
        }
    ],
    "sg:phone":"+1 450 466 4477",
    "sg:postcode":"J4P 3M4",
    "sg:province":"QC",
    "sg:tags":[
        "car",
        "dealer"
    ],
    "wof:name":"Instant Auto Credit",
    "wof:placetype":"venue"
},
  "geometry": {"coordinates":[-73.50113677980001,45.5127258301],"type":"Point"}
}