{
  "type": "Feature",
  "properties": {
    "addr:full":"1904 4 St SW Calgary AB T2S 1W3",
    "addr:housenumber":"1904 4",
    "addr:postcode":"t2s 1w3",
    "addr:street":"St Sw",
    "iso:country":"CA",
    "sg:address":"1904 4 St SW",
    "sg:city":"Calgary",
    "sg:classifiers":[
        {
            "category":"Restaurant",
            "type":"Food & Drink"
        }
    ],
    "sg:phone":"+1 403 228 1205",
    "sg:postcode":"T2S 1W3",
    "sg:province":"AB",
    "wof:name":"Peking Dragon Restaurant",
    "wof:placetype":"venue"
},
  "geometry": {"coordinates":[-114.07137299999999,51.035931],"type":"Point"}
}