{
  "type": "Feature",
  "properties": {
    "addr:full":"60 Martindale Close NE Calgary AB T3J 2V1",
    "addr:housenumber":"60",
    "addr:postcode":"t3j 2v1",
    "addr:street":"Martindale Close Ne",
    "iso:country":"CA",
    "sg:address":"60 Martindale Close NE",
    "sg:city":"Calgary",
    "sg:classifiers":[
        {
            "category":"Organizations",
            "subcategory":"Professional Association",
            "type":"Services"
        }
    ],
    "sg:phone":"+1 403 280 6006",
    "sg:postcode":"T3J 2V1",
    "sg:province":"AB",
    "wof:name":"Alberta Floor Covering Assn",
    "wof:placetype":"venue"
},
  "geometry": {"coordinates":[-113.95380400000001,51.11071],"type":"Point"}
}