{
  "type": "Feature",
  "properties": {
    "iso:country":"CA",
    "sg:city":"Montreal",
    "sg:classifiers":[
        {
            "category":"Health Services",
            "subcategory":"Hospital",
            "type":"Services"
        }
    ],
    "sg:phone":"+1 514 271 4407",
    "sg:postcode":"H2R 1J1",
    "sg:province":"QC",
    "sg:tags":[
        "psycho",
        "mental"
    ],
    "wof:name":"Maison Multi Ethnique Myosotis",
    "wof:placetype":"venue"
},
  "geometry": {"coordinates":[-73.621727,45.543144],"type":"Point"}
}