{
  "type": "Feature",
  "properties": {
    "addr:full":"105 Hall St Ayr ON N0B 1E0",
    "addr:housenumber":"105",
    "addr:postcode":"n0b 1e0",
    "addr:street":"Hall St",
    "iso:country":"CA",
    "sg:address":"105 Hall St",
    "sg:city":"Ayr",
    "sg:classifiers":[
        {
            "category":"Education",
            "subcategory":"School",
            "type":"Public Place"
        }
    ],
    "sg:phone":"+1 519 632 7424",
    "sg:postcode":"N0B 1E0",
    "sg:province":"ON",
    "wof:name":"Ayr Public School",
    "wof:placetype":"venue"
},
  "geometry": {"coordinates":[-80.4499511719,43.2898101807],"type":"Point"}
}