{
  "type": "Feature",
  "properties": {
    "addr:full":"665 28th St E Prince Albert SK S6V 6E9",
    "addr:housenumber":"665",
    "addr:postcode":"s6v 6e9",
    "addr:street":"28Th St",
    "iso:country":"CA",
    "sg:address":"665 28th St E",
    "sg:city":"Prince Albert",
    "sg:classifiers":[
        {
            "category":"Education",
            "subcategory":"School",
            "type":"Public Place"
        }
    ],
    "sg:phone":"+1 306 922 3115",
    "sg:postcode":"S6V 6E9",
    "sg:province":"SK",
    "wof:name":"Carlton Comprehensive High",
    "wof:placetype":"venue"
},
  "geometry": {"coordinates":[-105.734711,53.187607],"type":"Point"}
}