{
  "type": "Feature",
  "properties": {
    "iso:country":"CA",
    "sg:address":"270 Weber St N",
    "sg:city":"Waterloo",
    "sg:classifiers":[
        {
            "category":"Shopping",
            "subcategory":"Stationery & Office Supplies",
            "type":"Retail Goods"
        }
    ],
    "sg:phone":"+1 519 884 9966",
    "sg:postcode":"N2J 3H6",
    "sg:province":"ON",
    "sg:tags":[
        "equipment",
        "computer",
        "dealer"
    ],
    "wof:name":"Office Depot",
    "wof:placetype":"venue"
},
  "geometry": {"coordinates":[-80.521156311,43.479724884],"type":"Point"}
}