{
  "type": "Feature",
  "properties": {
    "iso:country":"CA",
    "sg:address":"PO Box 1556 STN Main",
    "sg:city":"Uxbridge",
    "sg:classifiers":[
        {
            "category":"Recreation",
            "type":"Entertainment"
        }
    ],
    "sg:phone":"+1 905 852 9611",
    "sg:postcode":"L9P 1N7",
    "sg:province":"ON",
    "sg:tags":[
        "club",
        "hockey"
    ],
    "wof:name":"Uxbridge Youth Hockey",
    "wof:placetype":"venue"
},
  "geometry": {"coordinates":[-79.123863,44.106167],"type":"Point"}
}