{
  "type": "Feature",
  "properties": {
    "addr:full":"Montreal QC H1X 3M7",
    "addr:postcode":"h1x 3m7",
    "iso:country":"CA",
    "sg:city":"Montreal",
    "sg:classifiers":[
        {
            "category":"Health Services",
            "subcategory":"Medical Lab",
            "type":"Services"
        }
    ],
    "sg:phone":"+1 514 593 1423",
    "sg:postcode":"H1X 3M7",
    "sg:province":"QC",
    "wof:name":"Therrien, Gaston",
    "wof:placetype":"venue"
},
  "geometry": {"coordinates":[-73.5891799927,45.5629386902],"type":"Point"}
}