{
  "type": "Feature",
  "properties": {
    "addr:full":"12227 107 Ave NW # 3 Edmonton AB T5M 1Y9",
    "addr:housenumber":"12227",
    "addr:postcode":"t5m 1y9",
    "addr:street":"107 Ave Nw # 3",
    "iso:country":"CA",
    "sg:address":"12227 107 Ave NW # 3",
    "sg:city":"Edmonton",
    "sg:classifiers":[
        {
            "category":"Building & Trades",
            "subcategory":"Construction",
            "type":"Services"
        }
    ],
    "sg:phone":"+1 780 428 0244",
    "sg:postcode":"T5M 1Y9",
    "sg:province":"AB",
    "sg:tags":[
        "repairing",
        "remodeling",
        "contractor"
    ],
    "wof:name":"First Choice Siding",
    "wof:placetype":"venue"
},
  "geometry": {"coordinates":[-113.532974,53.550743],"type":"Point"}
}