{
  "type": "Feature",
  "properties": {
    "addr:full":"6 Rue Tasse Sainte-Therese QC J7E 1V3",
    "addr:housenumber":"6",
    "addr:postcode":"j7e 1v3",
    "addr:street":"Rue Tasse Sainte-Therese",
    "iso:country":"CA",
    "sg:address":"6 Rue Tasse",
    "sg:city":"Sainte-Therese",
    "sg:classifiers":[
        {
            "category":"Organizations",
            "subcategory":"Labor Organization",
            "type":"Services"
        }
    ],
    "sg:phone":"+1 450 430 1167",
    "sg:postcode":"J7E 1V3",
    "sg:province":"QC",
    "wof:name":"Scfp 4296",
    "wof:placetype":"venue"
},
  "geometry": {"coordinates":[-73.83772277830001,45.6408004761],"type":"Point"}
}