{
  "type": "Feature",
  "properties": {
    "addr:full":"1 Du Quai Marsoui LA Martre QC G0E 2H0",
    "addr:housenumber":"1",
    "addr:postcode":"g0e 2h0",
    "addr:street":"Du Quai",
    "iso:country":"CA",
    "sg:address":"1 Du Quai Marsoui",
    "sg:city":"LA Martre",
    "sg:classifiers":[
        {
            "category":"Social Services",
            "type":"Services"
        }
    ],
    "sg:phone":"+1 418 288 5511",
    "sg:postcode":"G0E 2H0",
    "sg:province":"QC",
    "sg:tags":[
        "organization",
        "welfare"
    ],
    "wof:name":"Clsc Des Berges",
    "wof:placetype":"venue"
},
  "geometry": {"coordinates":[-66.16455078120001,49.2057418823],"type":"Point"}
}