{
  "type": "Feature",
  "properties": {
    "addr:full":"New Westminster BC V3M 1X4",
    "addr:postcode":"v3m 1x4",
    "iso:country":"CA",
    "sg:city":"New Westminster",
    "sg:classifiers":[
        {
            "category":"Health Services",
            "subcategory":"Doctor",
            "type":"Services"
        }
    ],
    "sg:phone":"+1 604 521 7211",
    "sg:postcode":"V3M 1X4",
    "sg:province":"BC",
    "sg:tags":[
        "physician",
        "surgeon"
    ],
    "wof:name":"Hepburn, A MD",
    "wof:placetype":"venue"
},
  "geometry": {"coordinates":[-122.91911315900001,49.2115707397],"type":"Point"}
}