{
  "type": "Feature",
  "properties": {
    "addr:full":"220 Carlton St Winnipeg MB R3C 1P5",
    "addr:housenumber":"220",
    "addr:postcode":"r3c 1p5",
    "addr:street":"Carlton St",
    "iso:country":"CA",
    "sg:address":"220 Carlton St",
    "sg:city":"Winnipeg",
    "sg:classifiers":[
        {
            "category":"Travel",
            "subcategory":"Hotels & Motels",
            "type":"Entertainment"
        }
    ],
    "sg:phone":"+1 204 942 0881",
    "sg:postcode":"R3C 1P5",
    "sg:province":"MB",
    "wof:name":"Carlton Inn",
    "wof:placetype":"venue"
},
  "geometry": {"coordinates":[-97.14506530760001,49.8907966614],"type":"Point"}
}