{
  "type": "Feature",
  "properties": {
    "addr:full":"127 Fairmount Rd Brome QC J0E 1K0",
    "addr:housenumber":"127",
    "addr:postcode":"j0e 1k0",
    "addr:street":"Fairmount Rd",
    "iso:country":"CA",
    "sg:address":"127 Fairmount Rd",
    "sg:city":"Brome",
    "sg:classifiers":[
        {
            "category":"Travel",
            "subcategory":"Campground",
            "type":"Entertainment"
        }
    ],
    "sg:phone":"+1 450 266 0928",
    "sg:postcode":"J0E 1K0",
    "sg:province":"QC",
    "wof:name":"Camping Fairmount",
    "wof:placetype":"venue"
},
  "geometry": {"coordinates":[-72.60535400000001,45.242085],"type":"Point"}
}