{
  "type": "Feature",
  "properties": {
    "addr:full":"205 Ironwood Dr Amherstburg ON N9V 3V4",
    "addr:housenumber":"205",
    "addr:postcode":"n9v 3v4",
    "addr:street":"Ironwood Dr",
    "iso:country":"CA",
    "sg:address":"205 Ironwood Dr",
    "sg:city":"Amherstburg",
    "sg:classifiers":[
        {
            "category":"Professional",
            "subcategory":"Management & Consulting",
            "type":"Services"
        }
    ],
    "sg:phone":"+1 519 736 1796",
    "sg:postcode":"N9V 3V4",
    "sg:province":"ON",
    "sg:tags":[
        "consultant",
        "business"
    ],
    "wof:name":"Biafore Associates Inc",
    "wof:placetype":"venue"
},
  "geometry": {"coordinates":[-83.097763,42.140873],"type":"Point"}
}