{
  "type": "Feature",
  "properties": {
    "addr:full":"397 1Re Av Asbestos QC J1T 1Z1",
    "addr:housenumber":"397",
    "addr:postcode":"j1t 1z1",
    "addr:street":"1Re Av",
    "iso:country":"CA",
    "sg:address":"397 1Re Av",
    "sg:city":"Asbestos",
    "sg:classifiers":[
        {
            "category":"Food & Beverages",
            "subcategory":"Bakery",
            "type":"Retail Goods"
        }
    ],
    "sg:phone":"+1 819 879 5858",
    "sg:postcode":"J1T 1Z1",
    "sg:province":"QC",
    "sg:tags":[
        "doughnut"
    ],
    "wof:name":"Ben Bon Beignes",
    "wof:placetype":"venue"
},
  "geometry": {"coordinates":[-71.932365,45.772392],"type":"Point"}
}