{
  "type": "Feature",
  "properties": {
    "addr:full":"1935 Lawrence Ave E Scarborough ON M1R 2Y8",
    "addr:housenumber":"1935",
    "addr:postcode":"m1r 2y8",
    "addr:street":"Lawrence Ave E",
    "iso:country":"CA",
    "sg:address":"1935 Lawrence Ave E",
    "sg:city":"Scarborough",
    "sg:classifiers":[
        {
            "category":"Retail",
            "subcategory":"Auto Repair",
            "type":"Services"
        }
    ],
    "sg:phone":"+1 416 752 3662",
    "sg:postcode":"M1R 2Y8",
    "sg:province":"ON",
    "sg:tags":[
        "repairing",
        "automobile"
    ],
    "wof:name":"Speedy Auto Svc",
    "wof:placetype":"venue"
},
  "geometry": {"coordinates":[-79.2987976074,43.7443580627],"type":"Point"}
}