{
  "type": "Feature",
  "properties": {
    "addr:full":"95 Winnipeg St Schreiber ON P0T 2S0",
    "addr:housenumber":"95",
    "addr:postcode":"p0t 2s0",
    "addr:street":"Winnipeg St",
    "iso:country":"CA",
    "sg:address":"95 Winnipeg St",
    "sg:city":"Schreiber",
    "sg:classifiers":[
        {
            "category":"Government",
            "subcategory":"Office",
            "type":"Public Place"
        }
    ],
    "sg:phone":"+1 807 824 2459",
    "sg:postcode":"P0T 2S0",
    "sg:province":"ON",
    "sg:tags":[
        "village"
    ],
    "wof:name":"Schreiber Sewer Treatment Plnt",
    "wof:placetype":"venue"
},
  "geometry": {"coordinates":[-87.2686004639,48.8051567078],"type":"Point"}
}