{
  "type": "Feature",
  "properties": {
    "addr:full":"2093 Calais Rd Duncan BC V9L 5V8",
    "addr:housenumber":"2093",
    "addr:postcode":"v9l 5v8",
    "addr:street":"Calais Rd",
    "iso:country":"CA",
    "sg:address":"2093 Calais Rd",
    "sg:city":"Duncan",
    "sg:classifiers":[
        {
            "category":"Freight",
            "type":"Transportation"
        }
    ],
    "sg:phone":"+1 250 748 3626",
    "sg:postcode":"V9L 5V8",
    "sg:province":"BC",
    "sg:tags":[
        "mover"
    ],
    "wof:name":"Every Detail",
    "wof:placetype":"venue"
},
  "geometry": {"coordinates":[-123.707382,48.779095],"type":"Point"}
}