{
  "type": "Feature",
  "properties": {
    "addr:full":"127 Simcoe St Tillsonburg ON N4G 2J2",
    "addr:housenumber":"127",
    "addr:postcode":"n4g 2j2",
    "addr:street":"Simcoe St",
    "iso:country":"CA",
    "sg:address":"127 Simcoe St",
    "sg:city":"Tillsonburg",
    "sg:classifiers":[
        {
            "category":"Retail",
            "subcategory":"Auto Repair",
            "type":"Services"
        }
    ],
    "sg:phone":"+1 519 842 5230",
    "sg:postcode":"N4G 2J2",
    "sg:province":"ON",
    "sg:tags":[
        "repairing",
        "automobile",
        "lubrication"
    ],
    "wof:name":"Lubricare",
    "wof:placetype":"venue"
},
  "geometry": {"coordinates":[-80.70974731450001,42.8583641052],"type":"Point"}
}