{
  "type": "Feature",
  "properties": {
    "addr:full":"4257 Stewart Rd Chilliwack BC V2R 5G2",
    "addr:housenumber":"4257",
    "addr:postcode":"v2r 5g2",
    "addr:street":"Stewart Rd",
    "iso:country":"CA",
    "sg:address":"4257 Stewart Rd",
    "sg:city":"Chilliwack",
    "sg:classifiers":[
        {
            "category":"Building & Trades",
            "subcategory":"Plumbing",
            "type":"Services"
        }
    ],
    "sg:phone":"+1 604 823 4964",
    "sg:postcode":"V2R 5G2",
    "sg:province":"BC",
    "sg:tags":[
        "air",
        "conditioning",
        "contractor",
        "system",
        "heating"
    ],
    "wof:name":"Valley Air Conditioning & Heat",
    "wof:placetype":"venue"
},
  "geometry": {"coordinates":[-122.067863464,49.0787124634],"type":"Point"}
}