{
  "type": "Feature",
  "properties": {
    "addr:full":"38 Ch Labrie Saint-Quentin NB E8A 2E1",
    "addr:housenumber":"38",
    "addr:postcode":"e8a 2e1",
    "addr:street":"Ch Labrie",
    "iso:country":"CA",
    "sg:address":"38 Ch Labrie",
    "sg:city":"Saint-Quentin",
    "sg:classifiers":[
        {
            "category":"Manufacturing",
            "subcategory":"Lumber",
            "type":"Manufacturing & Wholesale Goods"
        }
    ],
    "sg:phone":"+1 506 235 1888",
    "sg:postcode":"E8A 2E1",
    "sg:province":"NB",
    "sg:tags":[
        "hardware"
    ],
    "wof:name":"Materiaux Parent-Rona",
    "wof:placetype":"venue"
},
  "geometry": {"coordinates":[-67.39671300000001,47.504463],"type":"Point"}
}