{
  "type": "Feature",
  "properties": {
    "addr:full":"Calgary AB T2J 3G8",
    "addr:postcode":"t2j 3g8",
    "iso:country":"CA",
    "sg:city":"Calgary",
    "sg:classifiers":[
        {
            "category":"Personal",
            "subcategory":"Barber",
            "type":"Services"
        }
    ],
    "sg:phone":"+1 403 259 5334",
    "sg:postcode":"T2J 3G8",
    "sg:province":"AB",
    "wof:name":"Tomek Men's Hair Design Ltd",
    "wof:placetype":"venue"
},
  "geometry": {"coordinates":[-114.069496155,50.9688034058],"type":"Point"}
}