{
  "type": "Feature",
  "properties": {
    "iso:country":"CA",
    "sg:city":"New Germany",
    "sg:classifiers":[
        {
            "category":"Health Services",
            "subcategory":"Nursing And Care Facility",
            "type":"Services"
        }
    ],
    "sg:phone":"+1 902 644 2008",
    "sg:postcode":"B0R 1E0",
    "sg:province":"NS",
    "sg:tags":[
        "home",
        "convalescent"
    ],
    "wof:name":"Rosedale Home For Special Care",
    "wof:placetype":"venue"
},
  "geometry": {"coordinates":[-64.7164611816,44.5417671204],"type":"Point"}
}