{
  "type": "Feature",
  "properties": {
    "iso:country":"CA",
    "sg:address":"1 Wekusko Dr",
    "sg:city":"Snow Lake",
    "sg:classifiers":[
        {
            "category":"Retail",
            "subcategory":"Auto Repair",
            "type":"Services"
        }
    ],
    "sg:phone":"+1 204 358 2325",
    "sg:postcode":"R0B 1M0",
    "sg:province":"MB",
    "sg:tags":[
        "wrecker"
    ],
    "wof:name":"Petro-Canada",
    "wof:placetype":"venue"
},
  "geometry": {"coordinates":[-100.015022278,54.8745231628],"type":"Point"}
}