{
  "type": "Feature",
  "properties": {
    "addr:full":"468 Bowlen St Fredericton NB E3A 2T4",
    "addr:housenumber":"468",
    "addr:postcode":"e3a 2t4",
    "addr:street":"Bowlen St",
    "iso:country":"CA",
    "sg:address":"468 Bowlen St",
    "sg:city":"Fredericton",
    "sg:classifiers":[
        {
            "category":"Insurance",
            "subcategory":"Insurance Agent",
            "type":"Services"
        }
    ],
    "sg:phone":"+1 506 452 1909",
    "sg:postcode":"E3A 2T4",
    "sg:province":"NB",
    "sg:tags":[
        "adjuster"
    ],
    "wof:name":"Crawford Adjusters Canada",
    "wof:placetype":"venue"
},
  "geometry": {"coordinates":[-66.635063,45.969574],"type":"Point"}
}