{
  "type": "Feature",
  "properties": {
    "addr:full":"PO Box 25 Rivercourse AB T0B 3X0",
    "addr:housenumber":"po box 25",
    "addr:postcode":"t0b 3x0",
    "iso:country":"CA",
    "sg:address":"PO Box 25",
    "sg:city":"Rivercourse",
    "sg:classifiers":[
        {
            "category":"Farming",
            "subcategory":"Nursery",
            "type":"Manufacturing & Wholesale Goods"
        }
    ],
    "sg:phone":"+1 780 745 2578",
    "sg:postcode":"T0B 3X0",
    "sg:province":"AB",
    "sg:tags":[
        "greenhouse"
    ],
    "wof:name":"Di-Al Seed Farm",
    "wof:placetype":"venue"
},
  "geometry": {"coordinates":[-110.06572,53.016499],"type":"Point"}
}