{
  "type": "Feature",
  "properties": {
    "addr:full":"1106 Broadway W Vancouver BC V6H 1G5",
    "addr:housenumber":"1106",
    "addr:postcode":"v6h 1g5",
    "addr:street":"Broadway W",
    "iso:country":"CA",
    "sg:address":"1106 Broadway W",
    "sg:city":"Vancouver",
    "sg:classifiers":[
        {
            "category":"Manufacturing",
            "subcategory":"Retail Goods",
            "type":"Manufacturing & Wholesale Goods"
        }
    ],
    "sg:phone":"+1 604 669 9444",
    "sg:postcode":"V6H 1G5",
    "sg:province":"BC",
    "sg:tags":[
        "umbrella"
    ],
    "wof:name":"Umbrella Shop",
    "wof:placetype":"venue"
},
  "geometry": {"coordinates":[-123.129371643,49.2633285522],"type":"Point"}
}