{
  "type": "Feature",
  "properties": {
    "addr:full":"Guelph ON N1H 7M7",
    "addr:postcode":"n1h 7m7",
    "iso:country":"CA",
    "sg:city":"Guelph",
    "sg:classifiers":[
        {
            "category":"Wholesale",
            "subcategory":"Farm Supplies",
            "type":"Manufacturing & Wholesale Goods"
        }
    ],
    "sg:phone":"+1 519 821 1020",
    "sg:postcode":"N1H 7M7",
    "sg:province":"ON",
    "sg:tags":[
        "livestock"
    ],
    "wof:name":"Jersey Canada",
    "wof:placetype":"venue"
},
  "geometry": {"coordinates":[-80.29040500000001,43.542088],"type":"Point"}
}