{
  "type": "Feature",
  "properties": {
    "addr:full":"Campbellford ON K0L 1L0",
    "addr:postcode":"k0l 1l0",
    "iso:country":"CA",
    "sg:city":"Campbellford",
    "sg:classifiers":[
        {
            "category":"Real Estate",
            "subcategory":"Real Estate Agent",
            "type":"Services"
        }
    ],
    "sg:phone":"+1 705 653 0585",
    "sg:postcode":"K0L 1L0",
    "sg:province":"ON",
    "wof:name":"Burleigh, Ed",
    "wof:placetype":"venue"
},
  "geometry": {"coordinates":[-77.7979812622,44.3084869385],"type":"Point"}
}