{
  "type": "Feature",
  "properties": {
    "iso:country":"CA",
    "sg:address":"712 1E Rue E",
    "sg:city":"Amos",
    "sg:classifiers":[
        {
            "category":"Education",
            "subcategory":"School",
            "type":"Public Place"
        }
    ],
    "sg:phone":"+1 819 732 5582",
    "sg:postcode":"J9T 2H8",
    "sg:province":"QC",
    "wof:name":"Ecole Du Sacre-Coeur",
    "wof:placetype":"venue"
},
  "geometry": {"coordinates":[-78.11126708979999,48.5624160767],"type":"Point"}
}