{
  "type": "Feature",
  "properties": {
    "iso:country":"CA",
    "sg:address":"70 2nd St",
    "sg:city":"Lac Du Bonnet",
    "sg:classifiers":[
        {
            "category":"Shopping",
            "subcategory":"Discount & Variety Stores",
            "type":"Retail Goods"
        }
    ],
    "sg:phone":"+1 204 345 0033",
    "sg:postcode":"R0E 1A0",
    "sg:province":"MB",
    "sg:tags":[
        "novelty",
        "general"
    ],
    "wof:name":"Deals For Dollars",
    "wof:placetype":"venue"
},
  "geometry": {"coordinates":[-96.06196594239999,50.2516365051],"type":"Point"}
}