{
  "type": "Feature",
  "properties": {
    "addr:full":"6253 Boul Des Laurentides Laval QC H7H 2V3",
    "addr:housenumber":"6253",
    "addr:postcode":"h7h 2v3",
    "addr:street":"Boul Des Laurentides",
    "iso:country":"CA",
    "sg:address":"6253 Boul Des Laurentides",
    "sg:city":"Laval",
    "sg:classifiers":[
        {
            "category":"Cinema",
            "subcategory":"Movie Rental",
            "type":"Entertainment"
        }
    ],
    "sg:phone":"+1 450 628 8899",
    "sg:postcode":"H7H 2V3",
    "sg:province":"QC",
    "sg:tags":[
        "leasing",
        "video",
        "disc",
        "tape"
    ],
    "wof:name":"Video Zone Auteuil",
    "wof:placetype":"venue"
},
  "geometry": {"coordinates":[-73.754242,45.637016],"type":"Point"}
}