{
  "type": "Feature",
  "properties": {
    "addr:full":"1 King St W Millbrook ON L0A 1G0",
    "addr:housenumber":"1",
    "addr:postcode":"l0a 1g0",
    "addr:street":"King St W",
    "iso:country":"CA",
    "sg:address":"1 King St W",
    "sg:city":"Millbrook",
    "sg:classifiers":[
        {
            "category":"Professional",
            "subcategory":"Lawyer & Legal Services",
            "type":"Services"
        }
    ],
    "sg:phone":"+1 705 932 1811",
    "sg:postcode":"L0A 1G0",
    "sg:province":"ON",
    "sg:tags":[
        "attorney"
    ],
    "wof:name":"Kirkpatrick, Julie",
    "wof:placetype":"venue"
},
  "geometry": {"coordinates":[-78.4494400024,44.1501998901],"type":"Point"}
}