{
  "type": "Feature",
  "properties": {
    "iso:country":"CA",
    "sg:city":"Gretna",
    "sg:classifiers":[
        {
            "category":"Organizations",
            "subcategory":"Religious Organization",
            "type":"Services"
        }
    ],
    "sg:phone":"+1 204 327 5208",
    "sg:postcode":"R0G 0V0",
    "sg:province":"MB",
    "sg:tags":[
        "church"
    ],
    "wof:name":"Blumenort Mennonite Church",
    "wof:placetype":"venue"
},
  "geometry": {"coordinates":[-97.5609970093,49.0079307556],"type":"Point"}
}