{
  "type": "Feature",
  "properties": {
    "addr:full":"Burnaby BC V5H 1Z8",
    "addr:postcode":"v5h 1z8",
    "iso:country":"CA",
    "sg:city":"Burnaby",
    "sg:classifiers":[
        {
            "category":"Restaurant",
            "type":"Food & Drink"
        }
    ],
    "sg:phone":"+1 604 434 0308",
    "sg:postcode":"V5H 1Z8",
    "sg:province":"BC",
    "sg:tags":[
        "shop",
        "coffee"
    ],
    "wof:name":"Esquires Coffee House",
    "wof:placetype":"venue"
},
  "geometry": {"coordinates":[-123.008583069,49.2312736511],"type":"Point"}
}