{
  "type": "Feature",
  "properties": {
    "iso:country":"CA",
    "sg:address":"1151 London Rd",
    "sg:city":"Sarnia",
    "sg:classifiers":[
        {
            "category":"Retail",
            "subcategory":"Auto Repair",
            "type":"Services"
        }
    ],
    "sg:phone":"+1 519 383 0606",
    "sg:postcode":"N7S 1P3",
    "sg:province":"ON",
    "sg:tags":[
        "repairing",
        "automobile"
    ],
    "wof:name":"Goodyear Certified Auto Svc",
    "wof:placetype":"venue"
},
  "geometry": {"coordinates":[-82.3658294678,42.978969574],"type":"Point"}
}