{
  "type": "Feature",
  "properties": {
    "addr:full":"395 Broadway St Wyoming ON N0N 1T0",
    "addr:housenumber":"395",
    "addr:postcode":"n0n 1t0",
    "addr:street":"Broadway St",
    "iso:country":"CA",
    "sg:address":"395 Broadway St",
    "sg:city":"Wyoming",
    "sg:classifiers":[
        {
            "category":"Manufacturing",
            "subcategory":"Printing",
            "type":"Manufacturing & Wholesale Goods"
        }
    ],
    "sg:phone":"+1 519 845 0821",
    "sg:postcode":"N0N 1T0",
    "sg:province":"ON",
    "sg:tags":[
        "printer"
    ],
    "wof:name":"Huron Web Offset Printing Inc",
    "wof:placetype":"venue"
},
  "geometry": {"coordinates":[-82.118965,42.936134],"type":"Point"}
}