{
  "type": "Feature",
  "properties": {
    "iso:country":"CA",
    "sg:address":"418 Ch Des Frenes",
    "sg:city":"L'Acadie",
    "sg:classifiers":[
        {
            "category":"Manufacturing",
            "subcategory":"Tools & Machinery",
            "type":"Manufacturing & Wholesale Goods"
        }
    ],
    "sg:phone":"+1 450 346 8710",
    "sg:postcode":"J2Y 1J1",
    "sg:province":"QC",
    "sg:tags":[
        "tachograph"
    ],
    "wof:name":"Controle Pc Enr",
    "wof:placetype":"venue"
},
  "geometry": {"coordinates":[-73.388763,45.324657],"type":"Point"}
}