{
  "type": "Feature",
  "properties": {
    "addr:full":"5 Con Henwood Earlton ON P0J 1E0",
    "addr:housenumber":"5",
    "addr:postcode":"p0j 1e0",
    "addr:street":"Con Henwood",
    "iso:country":"CA",
    "sg:address":"5 Con Henwood",
    "sg:city":"Earlton",
    "sg:classifiers":[
        {
            "category":"Recreation",
            "type":"Entertainment"
        }
    ],
    "sg:phone":"+1 705 563 2404",
    "sg:postcode":"P0J 1E0",
    "sg:province":"ON",
    "sg:tags":[
        "hall",
        "auditorium"
    ],
    "wof:name":"Kenabeek Community Society",
    "wof:placetype":"venue"
},
  "geometry": {"coordinates":[-79.824326,47.711414],"type":"Point"}
}