{
  "type": "Feature",
  "properties": {
    "iso:country":"CA",
    "sg:address":"110 Goldcrest Rd",
    "sg:city":"Brampton",
    "sg:classifiers":[
        {
            "category":"Real Estate",
            "subcategory":"Surveying",
            "type":"Services"
        }
    ],
    "sg:phone":"+1 905 792 6641",
    "sg:postcode":"L6S 1H4",
    "sg:province":"ON",
    "sg:tags":[
        "surveyor"
    ],
    "wof:name":"Van Lankveld, Ted",
    "wof:placetype":"venue"
},
  "geometry": {"coordinates":[-79.7163848877,43.7299957275],"type":"Point"}
}