{
  "type": "Feature",
  "properties": {
    "addr:full":"High River AB T1V 1M7",
    "addr:postcode":"t1v 1m7",
    "iso:country":"CA",
    "sg:city":"High River",
    "sg:classifiers":[
        {
            "category":"Health Services",
            "subcategory":"Doctor",
            "type":"Services"
        }
    ],
    "sg:phone":"+1 403 652 7993",
    "sg:postcode":"T1V 1M7",
    "sg:province":"AB",
    "sg:tags":[
        "physician",
        "surgeon"
    ],
    "wof:name":"Jensen, Brian MD",
    "wof:placetype":"venue"
},
  "geometry": {"coordinates":[-113.872787476,50.5792694092],"type":"Point"}
}