{
  "type": "Feature",
  "properties": {
    "addr:full":"262 Cree Rd Sherwood Park AB T8A 4G2",
    "addr:housenumber":"262",
    "addr:postcode":"t8a 4g2",
    "addr:street":"Cree Rd",
    "iso:country":"CA",
    "sg:address":"262 Cree Rd",
    "sg:city":"Sherwood Park",
    "sg:classifiers":[
        {
            "category":"Retail",
            "subcategory":"Auto Repair",
            "type":"Services"
        }
    ],
    "sg:phone":"+1 780 467 0783",
    "sg:postcode":"T8A 4G2",
    "sg:province":"AB",
    "sg:tags":[
        "repairing",
        "automobile"
    ],
    "wof:name":"George's Auto Repair",
    "wof:placetype":"venue"
},
  "geometry": {"coordinates":[-113.329414,53.539135],"type":"Point"}
}