{
  "type": "Feature",
  "properties": {
    "addr:full":"4620 Nahanni Dr Fort Nelson BC V0C 1R0",
    "addr:postcode":"4620;bc v0c 1r0",
    "addr:street":"Nahanni Dr",
    "iso:country":"CA",
    "sg:address":"4620 Nahanni Dr",
    "sg:city":"Fort Nelson",
    "sg:classifiers":[
        {
            "category":"Freight",
            "type":"Transportation"
        }
    ],
    "sg:phone":"+1 250 774 2234",
    "sg:postcode":"V0C 1R0",
    "sg:province":"BC",
    "sg:tags":[
        "trucking"
    ],
    "wof:name":"Canadian Freightways Ltd",
    "wof:placetype":"venue"
},
  "geometry": {"coordinates":[-122.681976318,58.7988319397],"type":"Point"}
}