{
  "type": "Feature",
  "properties": {
    "iso:country":"CA",
    "sg:address":"6861 Hastings St",
    "sg:city":"Burnaby",
    "sg:classifiers":[
        {
            "category":"Retail",
            "subcategory":"Auto Repair",
            "type":"Services"
        }
    ],
    "sg:phone":"+1 604 298 0202",
    "sg:postcode":"V5B 1S9",
    "sg:province":"BC",
    "sg:tags":[
        "body",
        "automobile",
        "painting"
    ],
    "wof:name":"Jordan Auto Body",
    "wof:placetype":"venue"
},
  "geometry": {"coordinates":[-122.962112,49.280361],"type":"Point"}
}