{
  "type": "Feature",
  "properties": {
    "addr:full":"35 Campbell Ave St. John's NL A1E 2Z3",
    "addr:housenumber":"35",
    "addr:postcode":"a1e 2z3",
    "addr:street":"Campbell Ave",
    "iso:country":"CA",
    "sg:address":"35 Campbell Ave",
    "sg:city":"St. John's",
    "sg:classifiers":[
        {
            "category":"Health Services",
            "subcategory":"Doctor",
            "type":"Services"
        }
    ],
    "sg:phone":"+1 709 753 5075",
    "sg:postcode":"A1E 2Z3",
    "sg:province":"NL",
    "sg:tags":[
        "physician",
        "surgeon"
    ],
    "wof:name":"Nurse, M C MD",
    "wof:placetype":"venue"
},
  "geometry": {"coordinates":[-52.7254753113,47.5544128418],"type":"Point"}
}