{
  "type": "Feature",
  "properties": {
    "addr:full":"595 Av Principale Authier QC J0Z 1C0",
    "addr:postcode":"j0z 1c0",
    "addr:street":"595 Av Principale",
    "iso:country":"CA",
    "sg:address":"595 Av Principale",
    "sg:city":"Authier",
    "sg:classifiers":[
        {
            "category":"Building & Trades",
            "subcategory":"Construction",
            "type":"Services"
        }
    ],
    "sg:phone":"+1 819 782 3097",
    "sg:postcode":"J0Z 1C0",
    "sg:province":"QC",
    "sg:tags":[
        "contractor"
    ],
    "wof:name":"Construction DE LA Source Inc",
    "wof:placetype":"venue"
},
  "geometry": {"coordinates":[-78.857742,48.729107],"type":"Point"}
}