{
  "type": "Feature",
  "properties": {
    "iso:country":"CA",
    "sg:address":"176 Woolwich St",
    "sg:city":"Guelph",
    "sg:classifiers":[
        {
            "category":"Professional",
            "subcategory":"Lawyer & Legal Services",
            "type":"Services"
        }
    ],
    "sg:phone":"+1 519 826 6952",
    "sg:postcode":"N1H 3V5",
    "sg:province":"ON",
    "sg:tags":[
        "attorney"
    ],
    "wof:name":"Philp, M Wesley",
    "wof:placetype":"venue"
},
  "geometry": {"coordinates":[-80.252617,43.548126],"type":"Point"}
}