{
  "type": "Feature",
  "properties": {
    "iso:country":"CA",
    "sg:address":"90 Hamilton St",
    "sg:city":"Elora",
    "sg:classifiers":[
        {
            "category":"Wholesale",
            "subcategory":"Electrical",
            "type":"Manufacturing & Wholesale Goods"
        }
    ],
    "sg:phone":"+1 519 846 0878",
    "sg:postcode":"N0B 1S0",
    "sg:province":"ON",
    "sg:tags":[
        "fire",
        "alarm",
        "system"
    ],
    "wof:name":"National & Marine Fire Svc",
    "wof:placetype":"venue"
},
  "geometry": {"coordinates":[-80.42598724370001,43.675327301],"type":"Point"}
}