{
  "type": "Feature",
  "properties": {
    "addr:full":"49 Ch Labrie Saint-Quentin NB E8A 2C9",
    "addr:housenumber":"49",
    "addr:postcode":"e8a 2c9",
    "addr:street":"Ch Labrie",
    "iso:country":"CA",
    "sg:address":"49 Ch Labrie",
    "sg:city":"Saint-Quentin",
    "sg:classifiers":[
        {
            "category":"Manufacturing",
            "subcategory":"Tools & Machinery",
            "type":"Manufacturing & Wholesale Goods"
        }
    ],
    "sg:phone":"+1 506 235 2705",
    "sg:postcode":"E8A 2C9",
    "sg:province":"NB",
    "sg:tags":[
        "machine",
        "equipment",
        "honing"
    ],
    "wof:name":"Affutage Central Ltee",
    "wof:placetype":"venue"
},
  "geometry": {"coordinates":[-67.3966674805,47.504108429],"type":"Point"}
}