{
  "type": "Feature",
  "properties": {
    "addr:full":"2 Wolf Cres Redwood Meadows AB T3Z 1A3",
    "addr:housenumber":"2",
    "addr:postcode":"t3z 1a3",
    "addr:street":"Wolf Cres",
    "iso:country":"CA",
    "sg:address":"2 Wolf Cres",
    "sg:city":"Redwood Meadows",
    "sg:classifiers":[
        {
            "category":"Professional",
            "subcategory":"Lawyer & Legal Services",
            "type":"Services"
        }
    ],
    "sg:phone":"+1 403 949 2930",
    "sg:postcode":"T3Z 1A3",
    "sg:province":"AB",
    "sg:tags":[
        "attorney"
    ],
    "wof:name":"Brian Calliou Law Office",
    "wof:placetype":"venue"
},
  "geometry": {"coordinates":[-114.511116028,50.9851303101],"type":"Point"}
}