{
  "type": "Feature",
  "properties": {
    "addr:full":"Richmond BC V6X 1T4",
    "addr:postcode":"v6x 1t4",
    "iso:country":"CA",
    "sg:city":"Richmond",
    "sg:classifiers":[
        {
            "category":"Manufacturing",
            "subcategory":"Printing",
            "type":"Manufacturing & Wholesale Goods"
        }
    ],
    "sg:phone":"+1 604 231 9090",
    "sg:postcode":"V6X 1T4",
    "sg:province":"BC",
    "sg:tags":[
        "printer"
    ],
    "wof:name":"Cmyk Digital Printing",
    "wof:placetype":"venue"
},
  "geometry": {"coordinates":[-123.096626282,49.1921272278],"type":"Point"}
}