{
  "type": "Feature",
  "properties": {
    "addr:full":"750 Rue Des Pins O Alma QC G8B 7R3",
    "addr:housenumber":"750",
    "addr:postcode":"g8b 7r3",
    "addr:street":"Rue Des Pins O",
    "iso:country":"CA",
    "sg:address":"750 Rue Des Pins O",
    "sg:city":"Alma",
    "sg:classifiers":[
        {
            "category":"Building & Trades",
            "subcategory":"Cleaning & Sanitation",
            "type":"Services"
        }
    ],
    "sg:phone":"+1 418 668 4758",
    "sg:postcode":"G8B 7R3",
    "sg:province":"QC",
    "sg:tags":[
        "janitor"
    ],
    "wof:name":"Chaine DE Travail Adapte Cta",
    "wof:placetype":"venue"
},
  "geometry": {"coordinates":[-71.6497421265,48.5717201233],"type":"Point"}
}