{
  "type": "Feature",
  "properties": {
    "addr:full":"101 3rd Ave W Neilburg SK S0M 2C0",
    "addr:housenumber":"101",
    "addr:postcode":"s0m 2c0",
    "addr:street":"3Rd Ave W Neilburg",
    "iso:country":"CA",
    "sg:address":"101 3rd Ave W",
    "sg:city":"Neilburg",
    "sg:classifiers":[
        {
            "category":"Wholesale",
            "subcategory":"Machinery & Supplies",
            "type":"Manufacturing & Wholesale Goods"
        }
    ],
    "sg:phone":"+1 306 823 4561",
    "sg:postcode":"S0M 2C0",
    "sg:province":"SK",
    "sg:tags":[
        "equipment",
        "oil",
        "well"
    ],
    "wof:name":"Chad Equipment",
    "wof:placetype":"venue"
},
  "geometry": {"coordinates":[-109.623062,52.842045],"type":"Point"}
}