{
  "type": "Feature",
  "properties": {
    "addr:full":"83 Bridlewood Dr Dundas ON L9H 6L5",
    "addr:housenumber":"83",
    "addr:postcode":"l9h 6l5",
    "addr:street":"Bridlewood Dr",
    "iso:country":"CA",
    "sg:address":"83 Bridlewood Dr",
    "sg:city":"Dundas",
    "sg:classifiers":[
        {
            "category":"Building & Trades",
            "subcategory":"Construction",
            "type":"Services"
        }
    ],
    "sg:phone":"+1 905 628 6692",
    "sg:postcode":"L9H 6L5",
    "sg:province":"ON",
    "sg:tags":[
        "contractor"
    ],
    "wof:name":"Fieldcrest Homes Ltd",
    "wof:placetype":"venue"
},
  "geometry": {"coordinates":[-79.9748840332,43.2551116943],"type":"Point"}
}