{
  "type": "Feature",
  "properties": {
    "iso:country":"CA",
    "sg:address":"4645 Rue Jarry E",
    "sg:city":"Saint-Leonard",
    "sg:classifiers":[
        {
            "category":"Retail",
            "subcategory":"Portrait Studio",
            "type":"Services"
        }
    ],
    "sg:phone":"+1 514 725 8213",
    "sg:postcode":"H1R 1X6",
    "sg:province":"QC",
    "sg:tags":[
        "photographer"
    ],
    "wof:name":"Photo Porcelaine Dominic Inc",
    "wof:placetype":"venue"
},
  "geometry": {"coordinates":[-73.598022,45.577045],"type":"Point"}
}