{
  "type": "Feature",
  "properties": {
    "addr:full":"Mississauga ON L4T 2T9",
    "addr:postcode":"l4t 2t9",
    "iso:country":"CA",
    "sg:city":"Mississauga",
    "sg:classifiers":[
        {
            "category":"Food & Beverages",
            "subcategory":"Groceries & Convenience Stores",
            "type":"Retail Goods"
        }
    ],
    "sg:phone":"+1 905 677 1608",
    "sg:postcode":"L4T 2T9",
    "sg:province":"ON",
    "sg:tags":[
        "grocer"
    ],
    "wof:name":"Food Fiesta",
    "wof:placetype":"venue"
},
  "geometry": {"coordinates":[-79.637016,43.71769],"type":"Point"}
}