{
  "type": "Feature",
  "properties": {
    "iso:country":"CA",
    "sg:address":"850 Av Murray",
    "sg:city":"Quebec",
    "sg:classifiers":[
        {
            "category":"Health Services",
            "subcategory":"Health Practitioner",
            "type":"Services"
        }
    ],
    "sg:phone":"+1 418 527 1293",
    "sg:postcode":"G1S 3B3",
    "sg:province":"QC",
    "sg:tags":[
        "psychologist"
    ],
    "wof:name":"Guimont, Marie-Jose",
    "wof:placetype":"venue"
},
  "geometry": {"coordinates":[-71.23816680909999,46.8005256653],"type":"Point"}
}