{
  "type": "Feature",
  "properties": {
    "iso:country":"CA",
    "sg:address":"22 Spragge St",
    "sg:city":"Manitowaning",
    "sg:classifiers":[
        {
            "category":"Retail",
            "subcategory":"Auto Repair",
            "type":"Services"
        }
    ],
    "sg:phone":"+1 705 859 3431",
    "sg:postcode":"P0P 1N0",
    "sg:province":"ON",
    "sg:tags":[
        "repairing",
        "automobile"
    ],
    "wof:name":"Allen's Automotive Group",
    "wof:placetype":"venue"
},
  "geometry": {"coordinates":[-81.82930755620001,45.7488365173],"type":"Point"}
}