{
  "type": "Feature",
  "properties": {
    "iso:country":"CA",
    "sg:address":"1201 Division St # 14",
    "sg:city":"Kingston",
    "sg:classifiers":[
        {
            "category":"Restaurant",
            "type":"Food & Drink"
        }
    ],
    "sg:phone":"+1 613 531 0741",
    "sg:postcode":"K7K 6X4",
    "sg:province":"ON",
    "wof:name":"Mr Sub",
    "wof:placetype":"venue"
},
  "geometry": {"coordinates":[-76.498383,44.26548],"type":"Point"}
}