{
  "type": "Feature",
  "properties": {
    "addr:full":"209 Main Hwy Bay Roberts NL A0A 1G0",
    "addr:housenumber":"209",
    "addr:postcode":"a0a 1g0",
    "addr:street":"Main Hwy Bay",
    "iso:country":"CA",
    "sg:address":"209 Main Hwy",
    "sg:city":"Bay Roberts",
    "sg:classifiers":[
        {
            "category":"Insurance",
            "subcategory":"Insurance Agent",
            "type":"Services"
        }
    ],
    "sg:phone":"+1 709 786 1580",
    "sg:postcode":"A0A 1G0",
    "sg:province":"NL",
    "wof:name":"CO-Operators General Insurance",
    "wof:placetype":"venue"
},
  "geometry": {"coordinates":[-53.3283424377,47.5735855103],"type":"Point"}
}