{
  "type": "Feature",
  "properties": {
    "addr:full":"Gatineau QC J8T 7Y3",
    "addr:postcode":"j8t 7y3",
    "iso:country":"CA",
    "sg:city":"Gatineau",
    "sg:classifiers":[
        {
            "category":"Real Estate",
            "subcategory":"Real Estate Agent",
            "type":"Services"
        }
    ],
    "sg:phone":"+1 819 243 3111",
    "sg:postcode":"J8T 7Y3",
    "sg:province":"QC",
    "wof:name":"Re/Max Vision Inc",
    "wof:placetype":"venue"
},
  "geometry": {"coordinates":[-75.7067947388,45.4759864807],"type":"Point"}
}