{
  "type": "Feature",
  "properties": {
    "addr:full":"66 Anderson Rd Kinkora PE C0B 1N0",
    "addr:housenumber":"66",
    "addr:postcode":"c0b 1n0",
    "addr:street":"Anderson Rd",
    "iso:country":"CA",
    "sg:address":"66 Anderson Rd",
    "sg:city":"Kinkora",
    "sg:classifiers":[
        {
            "category":"Food & Beverages",
            "subcategory":"Groceries & Convenience Stores",
            "type":"Retail Goods"
        }
    ],
    "sg:phone":"+1 902 887 2284",
    "sg:postcode":"C0B 1N0",
    "sg:province":"PE",
    "sg:tags":[
        "grocer"
    ],
    "wof:name":"Kinkora Esso Convenience & Dnr",
    "wof:placetype":"venue"
},
  "geometry": {"coordinates":[-63.599026,46.322521],"type":"Point"}
}