{
  "type": "Feature",
  "properties": {
    "addr:full":"Mississauga ON L5C 1V8",
    "addr:postcode":"l5c 1v8",
    "iso:country":"CA",
    "sg:city":"Mississauga",
    "sg:classifiers":[
        {
            "category":"Wholesale",
            "subcategory":"Durable Goods & Equipment",
            "type":"Manufacturing & Wholesale Goods"
        }
    ],
    "sg:phone":"+1 905 949 0266",
    "sg:postcode":"L5C 1V8",
    "sg:province":"ON",
    "sg:tags":[
        "exporter"
    ],
    "wof:name":"Lemargo Inc",
    "wof:placetype":"venue"
},
  "geometry": {"coordinates":[-79.64222717289999,43.5675773621],"type":"Point"}
}