{
  "type": "Feature",
  "properties": {
    "addr:full":"Joliette QC J6E 5E7",
    "addr:postcode":"j6e 5e7",
    "iso:country":"CA",
    "sg:city":"Joliette",
    "sg:classifiers":[
        {
            "category":"Professional",
            "subcategory":"Lawyer & Legal Services",
            "type":"Services"
        }
    ],
    "sg:phone":"+1 450 752 5551",
    "sg:postcode":"J6E 5E7",
    "sg:province":"QC",
    "sg:tags":[
        "attorney"
    ],
    "wof:name":"Tremblay, Janie",
    "wof:placetype":"venue"
},
  "geometry": {"coordinates":[-73.4400253296,46.0247306824],"type":"Point"}
}