{
  "type": "Feature",
  "properties": {
    "addr:full":"1110 Heritage Rd Burlington ON L7L 4X9",
    "addr:housenumber":"1110",
    "addr:postcode":"l7l 4x9",
    "addr:street":"Heritage Rd",
    "iso:country":"CA",
    "sg:address":"1110 Heritage Rd",
    "sg:city":"Burlington",
    "sg:classifiers":[
        {
            "category":"Wholesale",
            "subcategory":"Durable Goods & Equipment",
            "type":"Manufacturing & Wholesale Goods"
        }
    ],
    "sg:phone":"+1 905 331 3386",
    "sg:postcode":"L7L 4X9",
    "sg:province":"ON",
    "sg:tags":[
        "instrument",
        "scientific",
        "apparatus"
    ],
    "wof:name":"Canalytical Instrumentation",
    "wof:placetype":"venue"
},
  "geometry": {"coordinates":[-79.784729,43.375374],"type":"Point"}
}