{
  "type": "Feature",
  "properties": {
    "addr:full":"3182 Ch Sainte-Foy Sainte-Foy QC G1X 1R4",
    "addr:postcode":"3182;g1x 1r4",
    "addr:street":"Ch Sainte-Foy",
    "iso:country":"CA",
    "sg:address":"3182 Ch Sainte-Foy",
    "sg:city":"Sainte-Foy",
    "sg:classifiers":[
        {
            "category":"Manufacturing",
            "subcategory":"Tools & Machinery",
            "type":"Manufacturing & Wholesale Goods"
        }
    ],
    "sg:phone":"+1 418 653 5655",
    "sg:postcode":"G1X 1R4",
    "sg:province":"QC",
    "sg:tags":[
        "optical",
        "optician"
    ],
    "wof:name":"Lunetterie F Farhat",
    "wof:placetype":"venue"
},
  "geometry": {"coordinates":[-71.291763,46.769211],"type":"Point"}
}