{
  "type": "Feature",
  "properties": {
    "addr:full":"29 Maywood Ave St Catharines ON L2R 1C5",
    "addr:housenumber":"29",
    "addr:postcode":"l2r 1c5",
    "addr:street":"Maywood Ave",
    "iso:country":"CA",
    "sg:address":"29 Maywood Ave",
    "sg:city":"St Catharines",
    "sg:classifiers":[
        {
            "category":"Building & Trades",
            "subcategory":"Equipment Rental",
            "type":"Services"
        }
    ],
    "sg:phone":"+1 905 682 9974",
    "sg:postcode":"L2R 1C5",
    "sg:province":"ON",
    "sg:tags":[
        "party",
        "supply"
    ],
    "wof:name":"Special Occasions Party Rental",
    "wof:placetype":"venue"
},
  "geometry": {"coordinates":[-79.26234436039999,43.178817749],"type":"Point"}
}