{
  "type": "Feature",
  "properties": {
    "addr:full":"25 Albert St W Alliston ON L9R 1H2",
    "addr:housenumber":"25",
    "addr:postcode":"l9r 1h2",
    "addr:street":"Albert St W Alliston",
    "iso:country":"CA",
    "sg:address":"25 Albert St W",
    "sg:city":"Alliston",
    "sg:classifiers":[
        {
            "category":"Education",
            "subcategory":"School",
            "type":"Public Place"
        }
    ],
    "sg:phone":"+1 705 435 7391",
    "sg:postcode":"L9R 1H2",
    "sg:province":"ON",
    "wof:name":"Alliston Union School",
    "wof:placetype":"venue"
},
  "geometry": {"coordinates":[-79.869095,44.150398],"type":"Point"}
}