{
  "type": "Feature",
  "properties": {
    "addr:full":"6311 Prince Albert St Vancouver BC V5W 3E7",
    "addr:housenumber":"6311",
    "addr:postcode":"v5w 3e7",
    "addr:street":"Prince Albert St",
    "iso:country":"CA",
    "sg:address":"6311 Prince Albert St",
    "sg:city":"Vancouver",
    "sg:classifiers":[
        {
            "category":"Organizations",
            "subcategory":"Religious Organization",
            "type":"Services"
        }
    ],
    "sg:phone":"+1 604 321 8077",
    "sg:postcode":"V5W 3E7",
    "sg:province":"BC",
    "sg:tags":[
        "church"
    ],
    "wof:name":"Canaan Church",
    "wof:placetype":"venue"
},
  "geometry": {"coordinates":[-123.08815800000001,49.227119],"type":"Point"}
}