{
  "type": "Feature",
  "properties": {
    "addr:full":"Fort Mcmurray AB T9H 3K8",
    "addr:postcode":"t9h 3k8",
    "iso:country":"CA",
    "sg:city":"Fort Mcmurray",
    "sg:classifiers":[
        {
            "category":"Health Services",
            "subcategory":"Chiropractor",
            "type":"Services"
        }
    ],
    "sg:phone":"+1 780 743 1971",
    "sg:postcode":"T9H 3K8",
    "sg:province":"AB",
    "wof:name":"Mc Bean, James R DC",
    "wof:placetype":"venue"
},
  "geometry": {"coordinates":[-111.364861,56.721447],"type":"Point"}
}