{
  "type": "Feature",
  "properties": {
    "addr:full":"116 Idylwyld Dr N Saskatoon SK S7L 0Y7",
    "addr:housenumber":"116",
    "addr:postcode":"s7l 0y7",
    "addr:street":"Idylwyld Dr N",
    "iso:country":"CA",
    "sg:address":"116 Idylwyld Dr N",
    "sg:city":"Saskatoon",
    "sg:classifiers":[
        {
            "category":"Shopping",
            "subcategory":"Optical Goods",
            "type":"Retail Goods"
        }
    ],
    "sg:phone":"+1 306 934 4545",
    "sg:postcode":"S7L 0Y7",
    "sg:province":"SK",
    "sg:tags":[
        "sun",
        "goggles",
        "sunglasses",
        "optician"
    ],
    "wof:name":"Eyes International Inc",
    "wof:placetype":"venue"
},
  "geometry": {"coordinates":[-106.669921875,52.1299819946],"type":"Point"}
}