{
  "type": "Feature",
  "properties": {
    "addr:full":"162086 A Line Owen Sound ON N4K 5N7",
    "addr:housenumber":"162086",
    "addr:postcode":"n4k 5n7",
    "addr:street":"A Line",
    "iso:country":"CA",
    "sg:address":"162086 A Line",
    "sg:city":"Owen Sound",
    "sg:classifiers":[
        {
            "category":"Food & Beverages",
            "subcategory":"Specialty",
            "type":"Retail Goods"
        }
    ],
    "sg:phone":"+1 519 371 0456",
    "sg:postcode":"N4K 5N7",
    "sg:province":"ON",
    "sg:tags":[
        "game",
        "venison",
        "bird"
    ],
    "wof:name":"S C Distributors",
    "wof:placetype":"venue"
},
  "geometry": {"coordinates":[-80.9426040649,44.5648765564],"type":"Point"}
}