{
  "type": "Feature",
  "properties": {
    "addr:full":"1430 Rue Montarville Saint-Bruno QC J3V 3T5",
    "addr:housenumber":"1430",
    "addr:postcode":"j3v 3t5",
    "addr:street":"Rue Montarville",
    "iso:country":"CA",
    "sg:address":"1430 Rue Montarville",
    "sg:city":"Saint-Bruno",
    "sg:classifiers":[
        {
            "category":"Education",
            "subcategory":"School",
            "type":"Public Place"
        }
    ],
    "sg:phone":"+1 450 653 3672",
    "sg:postcode":"J3V 3T5",
    "sg:province":"QC",
    "wof:name":"Centre Des Svc Alternatifs",
    "wof:placetype":"venue"
},
  "geometry": {"coordinates":[-71.675522,48.471771],"type":"Point"}
}