{
  "type": "Feature",
  "properties": {
    "addr:full":"575 Rue Du Boisselier Saint-Charles-DE-Drummond QC J2C 7S3",
    "addr:housenumber":"575",
    "addr:postcode":"j2c 7s3",
    "addr:street":"Rue Du Boisselier",
    "iso:country":"CA",
    "sg:address":"575 Rue Du Boisselier",
    "sg:city":"Saint-Charles-DE-Drummond",
    "sg:classifiers":[
        {
            "category":"Building & Trades",
            "subcategory":"Construction",
            "type":"Services"
        }
    ],
    "sg:phone":"+1 819 474 2817",
    "sg:postcode":"J2C 7S3",
    "sg:province":"QC",
    "sg:tags":[
        "general",
        "door",
        "contractor"
    ],
    "wof:name":"Installation Pro Plus",
    "wof:placetype":"venue"
},
  "geometry": {"coordinates":[-72.48279599999999,45.899162],"type":"Point"}
}