{
  "type": "Feature",
  "properties": {
    "addr:full":"Arthur ON N0G 1A0",
    "addr:postcode":"n0g 1a0",
    "iso:country":"CA",
    "sg:city":"Arthur",
    "sg:classifiers":[
        {
            "category":"Wholesale",
            "subcategory":"Meat",
            "type":"Manufacturing & Wholesale Goods"
        }
    ],
    "sg:phone":"+1 519 848 5882",
    "sg:postcode":"N0G 1A0",
    "sg:province":"ON",
    "sg:tags":[
        "packer"
    ],
    "wof:name":"Domingos Meat Packers",
    "wof:placetype":"venue"
},
  "geometry": {"coordinates":[-80.536644,43.83165],"type":"Point"}
}