{
  "type": "Feature",
  "properties": {
    "iso:country":"CA",
    "sg:city":"Ilderton",
    "sg:classifiers":[
        {
            "category":"Professional",
            "subcategory":"Lawyer & Legal Services",
            "type":"Services"
        }
    ],
    "sg:phone":"+1 519 666 0831",
    "sg:postcode":"N0M 2A0",
    "sg:province":"ON",
    "sg:tags":[
        "attorney"
    ],
    "wof:name":"Sinker, George E",
    "wof:placetype":"venue"
},
  "geometry": {"coordinates":[-81.3820800781,43.0791282654],"type":"Point"}
}