{
  "type": "Feature",
  "properties": {
    "addr:full":"1115 Niagara St N Welland ON L3B 5N5",
    "addr:housenumber":"1115",
    "addr:postcode":"l3b 5n5",
    "addr:street":"Niagara St N",
    "iso:country":"CA",
    "sg:address":"1115 Niagara St N",
    "sg:city":"Welland",
    "sg:classifiers":[
        {
            "category":"Autos & Motor Vehicles",
            "subcategory":"Recreational Vehicle Sales",
            "type":"Retail Goods"
        }
    ],
    "sg:phone":"+1 905 735 8033",
    "sg:postcode":"L3B 5N5",
    "sg:province":"ON",
    "wof:name":"Seaway Trailer Sales",
    "wof:placetype":"venue"
},
  "geometry": {"coordinates":[-79.2529373169,43.0037307739],"type":"Point"}
}