{
  "type": "Feature",
  "properties": {
    "iso:country":"CA",
    "sg:address":"10274 110 Ave",
    "sg:city":"Grande Prairie",
    "sg:classifiers":[
        {
            "category":"Building & Trades",
            "subcategory":"Construction",
            "type":"Services"
        }
    ],
    "sg:phone":"+1 780 539 0716",
    "sg:postcode":"T8V 1S7",
    "sg:province":"AB",
    "sg:tags":[
        "designer",
        "landscape"
    ],
    "wof:name":"Land Design",
    "wof:placetype":"venue"
},
  "geometry": {"coordinates":[-118.80381011999999,55.1799278259],"type":"Point"}
}