{
  "type": "Feature",
  "properties": {
    "addr:full":"Barrhead AB T7N 1A2",
    "addr:postcode":"t7n 1a2",
    "iso:country":"CA",
    "sg:city":"Barrhead",
    "sg:classifiers":[
        {
            "category":"Health Services",
            "subcategory":"Doctor",
            "type":"Services"
        }
    ],
    "sg:phone":"+1 780 674 6016",
    "sg:postcode":"T7N 1A2",
    "sg:province":"AB",
    "sg:tags":[
        "dentist"
    ],
    "wof:name":"North Country Dental Ctr",
    "wof:placetype":"venue"
},
  "geometry": {"coordinates":[-114.40419,54.118519],"type":"Point"}
}