{
  "type": "Feature",
  "properties": {
    "addr:full":"5170 County Rd 27 Cookstown ON L0L 1L0",
    "addr:housenumber":"5170;27",
    "addr:postcode":"l0l 1l0",
    "addr:street":"County Rd",
    "iso:country":"CA",
    "sg:address":"5170 County Rd 27",
    "sg:city":"Cookstown",
    "sg:classifiers":[
        {
            "category":"Building & Trades",
            "subcategory":"Construction",
            "type":"Services"
        }
    ],
    "sg:phone":"+1 705 458 1522",
    "sg:postcode":"L0L 1L0",
    "sg:province":"ON",
    "sg:tags":[
        "excavating",
        "contractor"
    ],
    "wof:name":"Robinson Enterprises Excvtng",
    "wof:placetype":"venue"
},
  "geometry": {"coordinates":[-79.702796936,44.1896362305],"type":"Point"}
}