{
  "type": "Feature",
  "properties": {
    "iso:country":"CA",
    "sg:address":"233 Boul Provencher",
    "sg:city":"Winnipeg",
    "sg:classifiers":[
        {
            "category":"Government",
            "subcategory":"Office",
            "type":"Public Place"
        }
    ],
    "sg:phone":"+1 204 945 0911",
    "sg:postcode":"R2H 0G4",
    "sg:province":"MB",
    "wof:name":"Manitoba Environment",
    "wof:placetype":"venue"
},
  "geometry": {"coordinates":[-97.119873,49.892937],"type":"Point"}
}