{
  "type": "Feature",
  "properties": {
    "iso:country":"CA",
    "sg:address":"14 Mill St",
    "sg:city":"Russell",
    "sg:classifiers":[
        {
            "category":"Education",
            "subcategory":"School",
            "type":"Public Place"
        }
    ],
    "sg:phone":"+1 613 445 2190",
    "sg:postcode":"K4R 1E1",
    "sg:province":"ON",
    "wof:name":"Russell Public School",
    "wof:placetype":"venue"
},
  "geometry": {"coordinates":[-75.363518,45.25679],"type":"Point"}
}