{
  "type": "Feature",
  "properties": {
    "addr:full":"2647 Ch Du Village Saint-Adolphe-D'Howard QC J0T 2B0",
    "addr:postcode":"2647;j0t 2b0",
    "addr:street":"Ch Du Village",
    "iso:country":"CA",
    "sg:address":"2647 Ch Du Village",
    "sg:city":"Saint-Adolphe-D'Howard",
    "sg:classifiers":[
        {
            "category":"Travel",
            "subcategory":"Hotels & Motels",
            "type":"Entertainment"
        }
    ],
    "sg:phone":"+1 819 327 2103",
    "sg:postcode":"J0T 2B0",
    "sg:province":"QC",
    "sg:tags":[
        "cottage",
        "cabin",
        "real estate"
    ],
    "wof:name":"Chalets St-Adolphe Inc",
    "wof:placetype":"venue"
},
  "geometry": {"coordinates":[-74.60230300000001,46.207088],"type":"Point"}
}