{
  "type": "Feature",
  "properties": {
    "iso:country":"CA",
    "sg:city":"Saint-Laurent",
    "sg:classifiers":[
        {
            "category":"Shopping",
            "subcategory":"Used Merchandise",
            "type":"Retail Goods"
        }
    ],
    "sg:phone":"+1 514 856 2484",
    "sg:postcode":"H4N 1C8",
    "sg:province":"QC",
    "sg:tags":[
        "second",
        "hand",
        "store",
        "variety"
    ],
    "wof:name":"Varietes DE Dollars",
    "wof:placetype":"venue"
},
  "geometry": {"coordinates":[-73.66951,45.528343],"type":"Point"}
}