{
  "type": "Feature",
  "properties": {
    "iso:country":"CA",
    "sg:city":"North York",
    "sg:classifiers":[
        {
            "category":"Real Estate",
            "subcategory":"Developer",
            "type":"Services"
        }
    ],
    "sg:phone":"+1 416 630 6767",
    "sg:postcode":"M3H 1T2",
    "sg:province":"ON",
    "sg:tags":[
        "management"
    ],
    "wof:name":"Famcorp Developments Ltd",
    "wof:placetype":"venue"
},
  "geometry": {"coordinates":[-79.4360580444,43.736831665],"type":"Point"}
}