{
  "type": "Feature",
  "properties": {
    "addr:full":"11260 184 St NW Edmonton AB T5S 2S6",
    "addr:housenumber":"11260",
    "addr:postcode":"t5s 2s6",
    "addr:street":"184 St Nw",
    "iso:country":"CA",
    "sg:address":"11260 184 St NW",
    "sg:city":"Edmonton",
    "sg:classifiers":[
        {
            "category":"Shopping",
            "subcategory":"Stationery & Office Supplies",
            "type":"Retail Goods"
        }
    ],
    "sg:phone":"+1 780 465 0006",
    "sg:postcode":"T5S 2S6",
    "sg:province":"AB",
    "sg:tags":[
        "envelope"
    ],
    "wof:name":"Premier Envelope Ltd",
    "wof:placetype":"venue"
},
  "geometry": {"coordinates":[-113.639832,53.561512],"type":"Point"}
}