{
  "type": "Feature",
  "properties": {
    "iso:country":"CA",
    "sg:address":"401 Cannon St E",
    "sg:city":"Hamilton",
    "sg:classifiers":[
        {
            "category":"Building & Trades",
            "subcategory":"Plumbing",
            "type":"Services"
        }
    ],
    "sg:phone":"+1 905 528 0769",
    "sg:postcode":"L8L 2C5",
    "sg:province":"ON",
    "sg:tags":[
        "sheet",
        "work",
        "metal",
        "contractor"
    ],
    "wof:name":"Alco Sheet Metal",
    "wof:placetype":"venue"
},
  "geometry": {"coordinates":[-79.849754,43.256596],"type":"Point"}
}