{
  "type": "Feature",
  "properties": {
    "addr:full":"756 Boul Saint-Joseph Roberval QC G8H 2L5",
    "addr:housenumber":"756",
    "addr:postcode":"g8h 2l5",
    "addr:street":"Boul Saint-Joseph",
    "iso:country":"CA",
    "sg:address":"756 Boul Saint-Joseph",
    "sg:city":"Roberval",
    "sg:classifiers":[
        {
            "category":"Government",
            "subcategory":"Office",
            "type":"Public Place"
        }
    ],
    "sg:phone":"+1 418 275 0207",
    "sg:postcode":"G8H 2L5",
    "sg:province":"QC",
    "wof:name":"Quebec Detention",
    "wof:placetype":"venue"
},
  "geometry": {"coordinates":[-72.220871,48.516197],"type":"Point"}
}