{
  "type": "Feature",
  "properties": {
    "addr:full":"1767 Wyandotte St E Windsor ON N8Y 1C9",
    "addr:housenumber":"1767",
    "addr:postcode":"n8y 1c9",
    "addr:street":"Wyandotte St E",
    "iso:country":"CA",
    "sg:address":"1767 Wyandotte St E",
    "sg:city":"Windsor",
    "sg:classifiers":[
        {
            "category":"Shopping",
            "subcategory":"Discount & Variety Stores",
            "type":"Retail Goods"
        }
    ],
    "sg:phone":"+1 519 252 2241",
    "sg:postcode":"N8Y 1C9",
    "sg:province":"ON",
    "wof:name":"Frank's Corner Store",
    "wof:placetype":"venue"
},
  "geometry": {"coordinates":[-83.01435089109999,42.3221054077],"type":"Point"}
}