{
  "type": "Feature",
  "properties": {
    "addr:full":"240 Elm St Aylmer ON N5H 2M8",
    "addr:housenumber":"240",
    "addr:postcode":"n5h 2m8",
    "addr:street":"Elm St",
    "iso:country":"CA",
    "sg:address":"240 Elm St",
    "sg:city":"Aylmer",
    "sg:classifiers":[
        {
            "category":"Autos & Motor Vehicles",
            "subcategory":"Automobile Sales",
            "type":"Retail Goods"
        }
    ],
    "sg:phone":"+1 519 773 8324",
    "sg:postcode":"N5H 2M8",
    "sg:province":"ON",
    "sg:tags":[
        "cart"
    ],
    "wof:name":"Kreative Karts Inc",
    "wof:placetype":"venue"
},
  "geometry": {"coordinates":[-80.989532,42.783169],"type":"Point"}
}