{
  "type": "Feature",
  "properties": {
    "addr:full":"18 Gard Rd Alberton PE C0B 1B0",
    "addr:housenumber":"18",
    "addr:postcode":"c0b 1b0",
    "addr:street":"Gard Rd",
    "iso:country":"CA",
    "sg:address":"18 Gard Rd",
    "sg:city":"Alberton",
    "sg:classifiers":[
        {
            "category":"Professional",
            "subcategory":"Accounting & Tax Preparation",
            "type":"Services"
        }
    ],
    "sg:phone":"+1 902 853 3470",
    "sg:postcode":"C0B 1B0",
    "sg:province":"PE",
    "sg:tags":[
        "bookkeeping",
        "return",
        "filing",
        "general"
    ],
    "wof:name":"West Prince Bookkeeping",
    "wof:placetype":"venue"
},
  "geometry": {"coordinates":[-64.06532300000001,46.813465],"type":"Point"}
}