{
  "type": "Feature",
  "properties": {
    "addr:full":"9601 Rue Colbert Anjou QC H1J 1Z9",
    "addr:housenumber":"9601",
    "addr:postcode":"h1j 1z9",
    "addr:street":"Rue Colbert",
    "iso:country":"CA",
    "sg:address":"9601 Rue Colbert",
    "sg:city":"Anjou",
    "sg:classifiers":[
        {
            "category":"Manufacturing",
            "subcategory":"Tools & Machinery",
            "type":"Manufacturing & Wholesale Goods"
        }
    ],
    "sg:phone":"+1 514 354 9432",
    "sg:postcode":"H1J 1Z9",
    "sg:province":"QC",
    "sg:tags":[
        "die",
        "maker"
    ],
    "wof:name":"Gaube Too & Die Ltd",
    "wof:placetype":"venue"
},
  "geometry": {"coordinates":[-73.5763549805,45.6116447449],"type":"Point"}
}