{
  "type": "Feature",
  "properties": {
    "addr:full":"6004 46 Ave Taber AB T1G 2B1",
    "addr:housenumber":"6004",
    "addr:postcode":"t1g 2b1",
    "addr:street":"46 Ave",
    "iso:country":"CA",
    "sg:address":"6004 46 Ave",
    "sg:city":"Taber",
    "sg:classifiers":[
        {
            "category":"Autos & Motor Vehicles",
            "subcategory":"Auto Supplies",
            "type":"Retail Goods"
        }
    ],
    "sg:phone":"+1 403 223 2555",
    "sg:postcode":"T1G 2B1",
    "sg:province":"AB",
    "sg:tags":[
        "tire"
    ],
    "wof:name":"Baker & Fitch Tire Ltd",
    "wof:placetype":"venue"
},
  "geometry": {"coordinates":[-112.13458300000001,49.784176],"type":"Point"}
}