{
  "type": "Feature",
  "properties": {
    "iso:country":"CA",
    "sg:address":"113 2nd St E",
    "sg:city":"Cornwall",
    "sg:classifiers":[
        {
            "category":"Professional",
            "subcategory":"Accounting & Tax Preparation",
            "type":"Services"
        }
    ],
    "sg:phone":"+1 613 932 8691",
    "sg:postcode":"K6H 1Y5",
    "sg:province":"ON",
    "sg:tags":[
        "accountant"
    ],
    "wof:name":"Bdo Dunwoody Ltd",
    "wof:placetype":"venue"
},
  "geometry": {"coordinates":[-74.726471,45.019051],"type":"Point"}
}