{
  "type": "Feature",
  "properties": {
    "addr:full":"112 Rue Marcellin Saint-Alphonse-DE-Caplan QC G0C 2V0",
    "addr:housenumber":"112",
    "addr:postcode":"g0c 2v0",
    "addr:street":"Rue Marcellin Saint-Alphonse-De-Caplan",
    "iso:country":"CA",
    "sg:address":"112 Rue Marcellin",
    "sg:city":"Saint-Alphonse-DE-Caplan",
    "sg:classifiers":[
        {
            "category":"Freight",
            "type":"Transportation"
        }
    ],
    "sg:phone":"+1 418 388 2177",
    "sg:postcode":"G0C 2V0",
    "sg:province":"QC",
    "sg:tags":[
        "trucking"
    ],
    "wof:name":"Transport Poirier & Freres Inc",
    "wof:placetype":"venue"
},
  "geometry": {"coordinates":[-65.67924499510001,48.1011810303],"type":"Point"}
}