{
  "type": "Feature",
  "properties": {
    "iso:country":"CA",
    "sg:address":"1880 Eglinton Ave E",
    "sg:city":"Scarborough",
    "sg:classifiers":[
        {
            "category":"Food & Beverages",
            "subcategory":"Bakery",
            "type":"Retail Goods"
        }
    ],
    "sg:phone":"+1 416 757 3970",
    "sg:postcode":"M1L 2L1",
    "sg:province":"ON",
    "sg:tags":[
        "doughnut"
    ],
    "wof:name":"Coffee Time Donuts",
    "wof:placetype":"venue"
},
  "geometry": {"coordinates":[-79.30052185060001,43.7252197266],"type":"Point"}
}