{
  "type": "Feature",
  "properties": {
    "addr:full":"1200 Aimco Blvd Mississauga ON L4W 1B2",
    "addr:housenumber":"1200",
    "addr:postcode":"l4w 1b2",
    "addr:street":"Aimco Blvd",
    "iso:country":"CA",
    "sg:address":"1200 Aimco Blvd",
    "sg:city":"Mississauga",
    "sg:classifiers":[
        {
            "category":"Retail",
            "subcategory":"Repair Shop",
            "type":"Services"
        }
    ],
    "sg:phone":"+1 905 238 4871",
    "sg:postcode":"L4W 1B2",
    "sg:province":"ON",
    "sg:tags":[
        "welding"
    ],
    "wof:name":"Kbc Metal Mfg Ltd",
    "wof:placetype":"venue"
},
  "geometry": {"coordinates":[-79.630424,43.632904],"type":"Point"}
}