{
  "type": "Feature",
  "properties": {
    "addr:full":"900 Grand Ave Indian Head SK S0G 2K0",
    "addr:housenumber":"900",
    "addr:postcode":"s0g 2k0",
    "addr:street":"Grand Ave",
    "iso:country":"CA",
    "sg:address":"900 Grand Ave",
    "sg:city":"Indian Head",
    "sg:classifiers":[
        {
            "category":"Recreation",
            "type":"Entertainment"
        }
    ],
    "sg:phone":"+1 306 695 3627",
    "sg:postcode":"S0G 2K0",
    "sg:province":"SK",
    "sg:tags":[
        "pool",
        "swimming"
    ],
    "wof:name":"Indian Head Swimming Pool",
    "wof:placetype":"venue"
},
  "geometry": {"coordinates":[-103.668861389,50.5325698853],"type":"Point"}
}