{
  "type": "Feature",
  "properties": {
    "addr:full":"390 Elizabeth Ave St. John's NL A1B 1V2",
    "addr:housenumber":"390",
    "addr:postcode":"a1b 1v2",
    "addr:street":"Elizabeth Ave",
    "iso:country":"CA",
    "sg:address":"390 Elizabeth Ave",
    "sg:city":"St. John's",
    "sg:classifiers":[
        {
            "category":"Professional",
            "subcategory":"Art Services",
            "type":"Services"
        }
    ],
    "sg:phone":"+1 709 722 5812",
    "sg:postcode":"A1B 1V2",
    "sg:province":"NL",
    "sg:tags":[
        "photographer"
    ],
    "wof:name":"Randy Dawe Photography-Framing",
    "wof:placetype":"venue"
},
  "geometry": {"coordinates":[-52.7382202148,47.5652084351],"type":"Point"}
}