{
  "type": "Feature",
  "properties": {
    "addr:full":"802 Highway Ave NE Redcliff AB T0J 2P0",
    "addr:housenumber":"802",
    "addr:postcode":"t0j 2p0",
    "addr:street":"Highway Ave Ne",
    "iso:country":"CA",
    "sg:address":"802 Highway Ave NE",
    "sg:city":"Redcliff",
    "sg:classifiers":[
        {
            "category":"Autos & Motor Vehicles",
            "subcategory":"Automobile Sales",
            "type":"Retail Goods"
        }
    ],
    "sg:phone":"+1 403 548 6820",
    "sg:postcode":"T0J 2P0",
    "sg:province":"AB",
    "sg:tags":[
        "car",
        "dealer"
    ],
    "wof:name":"Jack's Auto Sales",
    "wof:placetype":"venue"
},
  "geometry": {"coordinates":[-110.77788543699999,50.0812606812],"type":"Point"}
}