{
  "type": "Feature",
  "properties": {
    "iso:country":"CA",
    "sg:address":"4202 66 St NW",
    "sg:city":"Edmonton",
    "sg:classifiers":[
        {
            "category":"Restaurant",
            "type":"Food & Drink"
        }
    ],
    "sg:phone":"+1 780 414 8369",
    "sg:postcode":"T6K 4A2",
    "sg:province":"AB",
    "wof:name":"Mc Donald's",
    "wof:placetype":"venue"
},
  "geometry": {"coordinates":[-113.44303893999999,53.4800338745],"type":"Point"}
}