{
  "type": "Feature",
  "properties": {
    "addr:full":"Hwy 40 S Grande Prairie AB T8V 2Z9",
    "addr:postcode":"t8v 2z9",
    "addr:street":"Hwy 40 S",
    "iso:country":"CA",
    "sg:address":"Hwy 40 S",
    "sg:city":"Grande Prairie",
    "sg:classifiers":[
        {
            "category":"Freight",
            "type":"Transportation"
        }
    ],
    "sg:phone":"+1 780 532 0598",
    "sg:postcode":"T8V 2Z9",
    "sg:province":"AB",
    "sg:tags":[
        "trucking"
    ],
    "wof:name":"Trimac Transportation Svc Inc",
    "wof:placetype":"venue"
},
  "geometry": {"coordinates":[-118.820595,55.167339],"type":"Point"}
}