{
  "type": "Feature",
  "properties": {
    "addr:full":"607 Princess Ave London ON N6B 2C1",
    "addr:housenumber":"607",
    "addr:postcode":"n6b 2c1",
    "addr:street":"Princess Ave",
    "iso:country":"CA",
    "sg:address":"607 Princess Ave",
    "sg:city":"London",
    "sg:classifiers":[
        {
            "category":"Professional",
            "subcategory":"Lawyer & Legal Services",
            "type":"Services"
        }
    ],
    "sg:phone":"+1 519 432 4644",
    "sg:postcode":"N6B 2C1",
    "sg:province":"ON",
    "sg:tags":[
        "attorney"
    ],
    "wof:name":"Underhill Joles",
    "wof:placetype":"venue"
},
  "geometry": {"coordinates":[-81.2337265015,42.9925308228],"type":"Point"}
}