{
  "type": "Feature",
  "properties": {
    "addr:full":"69 William St York ON M9N 2G6",
    "addr:housenumber":"69",
    "addr:postcode":"m9n 2g6",
    "addr:street":"William St",
    "iso:country":"CA",
    "sg:address":"69 William St",
    "sg:city":"York",
    "sg:classifiers":[
        {
            "category":"Social Services",
            "subcategory":"Child Care",
            "type":"Services"
        }
    ],
    "sg:phone":"+1 416 245 3585",
    "sg:postcode":"M9N 2G6",
    "sg:province":"ON",
    "wof:name":"Weston Village Child Care",
    "wof:placetype":"venue"
},
  "geometry": {"coordinates":[-79.51350402830001,43.7036247253],"type":"Point"}
}