{
  "type": "Feature",
  "properties": {
    "addr:full":"8787 Greenall Ave Burnaby BC V5J 3M9",
    "addr:housenumber":"8787",
    "addr:postcode":"v5j 3m9",
    "addr:street":"Greenall Ave",
    "iso:country":"CA",
    "sg:address":"8787 Greenall Ave",
    "sg:city":"Burnaby",
    "sg:classifiers":[
        {
            "category":"Autos & Motor Vehicles",
            "subcategory":"Auto Supplies",
            "type":"Retail Goods"
        }
    ],
    "sg:phone":"+1 604 434 3316",
    "sg:postcode":"V5J 3M9",
    "sg:province":"BC",
    "sg:tags":[
        "filter",
        "gas"
    ],
    "wof:name":"Renu Filters Ltd",
    "wof:placetype":"venue"
},
  "geometry": {"coordinates":[-123.01812,49.20446],"type":"Point"}
}