{
  "type": "Feature",
  "properties": {
    "iso:country":"CA",
    "sg:city":"Merritt",
    "sg:classifiers":[
        {
            "category":"Retail",
            "subcategory":"Auto Rental",
            "type":"Services"
        }
    ],
    "sg:phone":"+1 250 378 5976",
    "sg:postcode":"V1K 1B9",
    "sg:province":"BC",
    "sg:tags":[
        "renting",
        "truck",
        "leasing"
    ],
    "wof:name":"U-Haul CO Ltd",
    "wof:placetype":"venue"
},
  "geometry": {"coordinates":[-120.772132873,50.096496582],"type":"Point"}
}