{
  "type": "Feature",
  "properties": {
    "iso:country":"CA",
    "sg:address":"47 Aubin Dr",
    "sg:city":"Winnipeg",
    "sg:classifiers":[
        {
            "category":"Shopping",
            "subcategory":"Bicycles & Sporting Goods",
            "type":"Retail Goods"
        }
    ],
    "sg:phone":"+1 204 781 3188",
    "sg:postcode":"R3X 1J8",
    "sg:province":"MB",
    "sg:tags":[
        "equipment",
        "diver",
        "supply"
    ],
    "wof:name":"Sure-Fit Mfg Ltd",
    "wof:placetype":"venue"
},
  "geometry": {"coordinates":[-97.084007,49.838379],"type":"Point"}
}