{
  "type": "Feature",
  "properties": {
    "addr:full":"305 Av Du Mont-Royal E Montreal QC H2T 1P8",
    "addr:postcode":"h2t 1p8",
    "addr:street":"305 Av Du Mont-Royal E",
    "iso:country":"CA",
    "sg:address":"305 Av Du Mont-Royal E",
    "sg:city":"Montreal",
    "sg:classifiers":[
        {
            "category":"Arts & Performance",
            "subcategory":"Theater",
            "type":"Entertainment"
        }
    ],
    "sg:phone":"+1 514 845 4108",
    "sg:postcode":"H2T 1P8",
    "sg:province":"QC",
    "sg:tags":[
        "music"
    ],
    "wof:name":"Jeunesses Musicales Du Canada",
    "wof:placetype":"venue"
},
  "geometry": {"coordinates":[-73.58386230470001,45.5230102539],"type":"Point"}
}