{
  "type": "Feature",
  "properties": {
    "addr:full":"Norwood ON K0L 2V0",
    "addr:postcode":"k0l 2v0",
    "iso:country":"CA",
    "sg:city":"Norwood",
    "sg:classifiers":[
        {
            "category":"Personal",
            "type":"Services"
        }
    ],
    "sg:phone":"+1 705 639 2786",
    "sg:postcode":"K0L 2V0",
    "sg:province":"ON",
    "sg:tags":[
        "therapist",
        "massage"
    ],
    "wof:name":"Massage Therapy Clinic",
    "wof:placetype":"venue"
},
  "geometry": {"coordinates":[-77.979133606,44.3830299377],"type":"Point"}
}