{
  "type": "Feature",
  "properties": {
    "addr:full":"310 Argyle St S Renfrew ON K7V 1T9",
    "addr:housenumber":"310",
    "addr:postcode":"k7v 1t9",
    "addr:street":"Argyle St S",
    "iso:country":"CA",
    "sg:address":"310 Argyle St S",
    "sg:city":"Renfrew",
    "sg:classifiers":[
        {
            "category":"Retail",
            "subcategory":"Funeral Services",
            "type":"Services"
        }
    ],
    "sg:phone":"+1 613 432 2849",
    "sg:postcode":"K7V 1T9",
    "sg:province":"ON",
    "sg:tags":[
        "director"
    ],
    "wof:name":"Goulet Funeral Home",
    "wof:placetype":"venue"
},
  "geometry": {"coordinates":[-76.683029,45.469772],"type":"Point"}
}