{
  "type": "Feature",
  "properties": {
    "addr:full":"252 Laird Dr East York ON M4G 4C7",
    "addr:housenumber":"252",
    "addr:postcode":"m4g 4c7",
    "addr:street":"Laird Dr",
    "iso:country":"CA",
    "sg:address":"252 Laird Dr",
    "sg:city":"East York",
    "sg:classifiers":[
        {
            "category":"Restaurant",
            "type":"Food & Drink"
        }
    ],
    "sg:phone":"+1 416 429 1371",
    "sg:postcode":"M4G 4C7",
    "sg:province":"ON",
    "wof:name":"Mr Submarine",
    "wof:placetype":"venue"
},
  "geometry": {"coordinates":[-79.364799,43.713196],"type":"Point"}
}