{
  "type": "Feature",
  "properties": {
    "addr:full":"5400 Lawrence Ave E Scarborough ON M1C 2C6",
    "addr:housenumber":"5400",
    "addr:postcode":"m1c 2c6",
    "addr:street":"Lawrence Ave E",
    "iso:country":"CA",
    "sg:address":"5400 Lawrence Ave E",
    "sg:city":"Scarborough",
    "sg:classifiers":[
        {
            "category":"Education",
            "subcategory":"School",
            "type":"Public Place"
        }
    ],
    "sg:phone":"+1 416 396 6802",
    "sg:postcode":"M1C 2C6",
    "sg:province":"ON",
    "wof:name":"Sir Oliver Mowat Collegiate",
    "wof:placetype":"venue"
},
  "geometry": {"coordinates":[-79.14215900000001,43.778469],"type":"Point"}
}