{
  "type": "Feature",
  "properties": {
    "addr:full":"5581 Rue Pare # A Mont-Royal QC H4P 1P7",
    "addr:housenumber":"5581",
    "addr:postcode":"h4p 1p7",
    "addr:street":"Rue Pare # A Mont-Royal",
    "iso:country":"CA",
    "sg:address":"5581 Rue Pare # A",
    "sg:city":"Mont-Royal",
    "sg:classifiers":[
        {
            "category":"Restaurant",
            "type":"Food & Drink"
        }
    ],
    "sg:phone":"+1 514 739 9161",
    "sg:postcode":"H4P 1P7",
    "sg:province":"QC",
    "wof:name":"Pare Restaurant",
    "wof:placetype":"venue"
},
  "geometry": {"coordinates":[-73.6614990234,45.4915504456],"type":"Point"}
}