{
  "type": "Feature",
  "properties": {
    "iso:country":"CA",
    "sg:address":"1563 Regan Ave",
    "sg:city":"Coquitlam",
    "sg:classifiers":[
        {
            "category":"Education",
            "subcategory":"School",
            "type":"Public Place"
        }
    ],
    "sg:phone":"+1 604 939 1151",
    "sg:postcode":"V3J 3B7",
    "sg:province":"BC",
    "wof:name":"Parkland Elementary School",
    "wof:placetype":"venue"
},
  "geometry": {"coordinates":[-122.84992981000001,49.2617034912],"type":"Point"}
}