{
  "type": "Feature",
  "properties": {
    "addr:full":"Calumet QC J0V 1B0",
    "addr:postcode":"j0v 1b0",
    "iso:country":"CA",
    "sg:city":"Calumet",
    "sg:classifiers":[
        {
            "category":"Restaurant",
            "type":"Food & Drink"
        }
    ],
    "sg:phone":"+1 819 242 2912",
    "sg:postcode":"J0V 1B0",
    "sg:province":"QC",
    "wof:name":"Calumet Restaurant",
    "wof:placetype":"venue"
},
  "geometry": {"coordinates":[-74.64702606199999,45.6487998962],"type":"Point"}
}