{
  "type": "Feature",
  "properties": {
    "iso:country":"CA",
    "sg:address":"73 Industrial Pky N",
    "sg:city":"Aurora",
    "sg:classifiers":[
        {
            "category":"Freight",
            "type":"Transportation"
        }
    ],
    "sg:phone":"+1 905 751 0999",
    "sg:postcode":"L4G 4C4",
    "sg:province":"ON",
    "sg:tags":[
        "commercial",
        "storage"
    ],
    "wof:name":"Apple Self Storage Ltd",
    "wof:placetype":"venue"
},
  "geometry": {"coordinates":[-79.458168,44.005226],"type":"Point"}
}