{
  "type": "Feature",
  "properties": {
    "addr:full":"Fredericton NB E3B 1A8",
    "addr:postcode":"e3b 1a8",
    "iso:country":"CA",
    "sg:city":"Fredericton",
    "sg:classifiers":[
        {
            "category":"Social Services",
            "type":"Services"
        }
    ],
    "sg:phone":"+1 506 459 3992",
    "sg:postcode":"E3B 1A8",
    "sg:province":"NB",
    "sg:tags":[
        "counselor",
        "marriage",
        "family"
    ],
    "wof:name":"Fredericton Counselling Ctr",
    "wof:placetype":"venue"
},
  "geometry": {"coordinates":[-66.647277832,45.9645576477],"type":"Point"}
}