{
  "type": "Feature",
  "properties": {
    "addr:full":"112 Kensington Rd Charlottetown PE C1A 5J5",
    "addr:housenumber":"112",
    "addr:postcode":"c1a 5j5",
    "addr:street":"Kensington Rd",
    "iso:country":"CA",
    "sg:address":"112 Kensington Rd",
    "sg:city":"Charlottetown",
    "sg:classifiers":[
        {
            "category":"Shopping",
            "type":"Retail Goods"
        }
    ],
    "sg:phone":"+1 902 892 3777",
    "sg:postcode":"C1A 5J5",
    "sg:province":"PE",
    "sg:tags":[
        "monument"
    ],
    "wof:name":"Heritage Memorials",
    "wof:placetype":"venue"
},
  "geometry": {"coordinates":[-63.1150245667,46.2541999817],"type":"Point"}
}