{
  "type": "Feature",
  "properties": {
    "addr:full":"2337 Emily Cres Cornwall ON K6H 7H5",
    "addr:housenumber":"2337",
    "addr:postcode":"k6h 7h5",
    "addr:street":"Emily Cres",
    "iso:country":"CA",
    "sg:address":"2337 Emily Cres",
    "sg:city":"Cornwall",
    "sg:classifiers":[
        {
            "category":"Building & Trades",
            "subcategory":"Cleaning & Sanitation",
            "type":"Services"
        }
    ],
    "sg:phone":"+1 613 936 8307",
    "sg:postcode":"K6H 7H5",
    "sg:province":"ON",
    "sg:tags":[
        "snow",
        "removal"
    ],
    "wof:name":"Srls",
    "wof:placetype":"venue"
},
  "geometry": {"coordinates":[-74.67672,45.037582],"type":"Point"}
}