{
  "type": "Feature",
  "properties": {
    "addr:full":"1621 Road 3 Ruthven ON N0P 2G0",
    "addr:housenumber":"1621",
    "addr:postcode":"n0p 2g0",
    "addr:street":"Road 3 Ruthven",
    "iso:country":"CA",
    "sg:address":"1621 Road 3",
    "sg:city":"Ruthven",
    "sg:classifiers":[
        {
            "category":"Wholesale",
            "subcategory":"Fruits & Vegetables",
            "type":"Manufacturing & Wholesale Goods"
        }
    ],
    "sg:phone":"+1 519 326 9041",
    "sg:postcode":"N0P 2G0",
    "sg:province":"ON",
    "wof:name":"Red Zoo Marketing",
    "wof:placetype":"venue"
},
  "geometry": {"coordinates":[-82.67202,42.051914],"type":"Point"}
}