{
  "type": "Feature",
  "properties": {
    "addr:full":"615 Granville St Port Hawkesbury NS B9A 2N1",
    "addr:housenumber":"615",
    "addr:postcode":"b9a 2n1",
    "addr:street":"Granville St",
    "iso:country":"CA",
    "sg:address":"615 Granville St",
    "sg:city":"Port Hawkesbury",
    "sg:classifiers":[
        {
            "category":"Health Services",
            "subcategory":"Doctor",
            "type":"Services"
        }
    ],
    "sg:phone":"+1 902 625 1666",
    "sg:postcode":"B9A 2N1",
    "sg:province":"NS",
    "sg:tags":[
        "dentist"
    ],
    "wof:name":"Greencorn, Patty DDS",
    "wof:placetype":"venue"
},
  "geometry": {"coordinates":[-61.36277,45.613972],"type":"Point"}
}