{
  "type": "Feature",
  "properties": {
    "addr:full":"Etobicoke ON M9W 1B3",
    "addr:postcode":"m9w 1b3",
    "iso:country":"CA",
    "sg:city":"Etobicoke",
    "sg:classifiers":[
        {
            "category":"Professional",
            "subcategory":"Engineering",
            "type":"Services"
        }
    ],
    "sg:phone":"+1 416 249 3361",
    "sg:postcode":"M9W 1B3",
    "sg:province":"ON",
    "sg:tags":[
        "acoustical",
        "consultant"
    ],
    "wof:name":"Aercoustics Engineering Ltd",
    "wof:placetype":"venue"
},
  "geometry": {"coordinates":[-79.56459,43.698425],"type":"Point"}
}