{
  "type": "Feature",
  "properties": {
    "iso:country":"CA",
    "sg:address":"15 Rue Saint-Joseph",
    "sg:city":"Saint-Constant",
    "sg:classifiers":[
        {
            "category":"Autos & Motor Vehicles",
            "subcategory":"Auto Supplies",
            "type":"Retail Goods"
        }
    ],
    "sg:phone":"+1 450 632 1706",
    "sg:postcode":"J5A 2A3",
    "sg:province":"QC",
    "sg:tags":[
        "equipment",
        "racing",
        "car",
        "automobile"
    ],
    "wof:name":"Entreprises DE Course Jocelyn",
    "wof:placetype":"venue"
},
  "geometry": {"coordinates":[-73.568039,45.364452],"type":"Point"}
}