{
  "type": "Feature",
  "properties": {
    "addr:full":"412 27th St W Battleford SK S0M 0E0",
    "addr:housenumber":"412",
    "addr:postcode":"s0m 0e0",
    "addr:street":"27Th St W",
    "iso:country":"CA",
    "sg:address":"412 27th St W",
    "sg:city":"Battleford",
    "sg:classifiers":[
        {
            "category":"Recreation",
            "type":"Entertainment"
        }
    ],
    "sg:phone":"+1 306 937 2431",
    "sg:postcode":"S0M 0E0",
    "sg:province":"SK",
    "sg:tags":[
        "club",
        "curling"
    ],
    "wof:name":"Battleford Curling Club",
    "wof:placetype":"venue"
},
  "geometry": {"coordinates":[-108.31314086899999,52.7362365723],"type":"Point"}
}