{
  "type": "Feature",
  "properties": {
    "addr:full":"London Rd Carbonear NL A1Y 1B3",
    "addr:postcode":"a1y 1b3",
    "addr:street":"London Rd",
    "iso:country":"CA",
    "sg:address":"London Rd",
    "sg:city":"Carbonear",
    "sg:classifiers":[
        {
            "category":"Shopping",
            "subcategory":"Clothing, Apparel, & Fashions",
            "type":"Retail Goods"
        }
    ],
    "sg:phone":"+1 709 596 0544",
    "sg:postcode":"A1Y 1B3",
    "sg:province":"NL",
    "sg:tags":[
        "jean"
    ],
    "wof:name":"Jeans Experts",
    "wof:placetype":"venue"
},
  "geometry": {"coordinates":[-53.246262,47.729042],"type":"Point"}
}