{
  "type": "Feature",
  "properties": {
    "addr:full":"465 South Industrial Dr Prince Albert SK S6V 7L9",
    "addr:housenumber":"465",
    "addr:postcode":"s6v 7l9",
    "addr:street":"South Industrial Dr",
    "iso:country":"CA",
    "sg:address":"465 South Industrial Dr",
    "sg:city":"Prince Albert",
    "sg:classifiers":[
        {
            "category":"Home & Garden",
            "subcategory":"Building Materials",
            "type":"Retail Goods"
        }
    ],
    "sg:phone":"+1 306 764 9505",
    "sg:postcode":"S6V 7L9",
    "sg:province":"SK",
    "sg:tags":[
        "lumber"
    ],
    "wof:name":"Windsor Plywood",
    "wof:placetype":"venue"
},
  "geometry": {"coordinates":[-105.740852356,53.1810951233],"type":"Point"}
}