{
  "type": "Feature",
  "properties": {
    "addr:full":"18 Ivybridge Dr Brampton ON L6V 2X2",
    "addr:housenumber":"18",
    "addr:postcode":"l6v 2x2",
    "addr:street":"Ivybridge Dr",
    "iso:country":"CA",
    "sg:address":"18 Ivybridge Dr",
    "sg:city":"Brampton",
    "sg:classifiers":[
        {
            "category":"Real Estate",
            "subcategory":"Surveying",
            "type":"Services"
        }
    ],
    "sg:phone":"+1 905 457 5061",
    "sg:postcode":"L6V 2X2",
    "sg:province":"ON",
    "sg:tags":[
        "surveyor"
    ],
    "wof:name":"Bmc Construction Layout Svc",
    "wof:placetype":"venue"
},
  "geometry": {"coordinates":[-79.75885772709999,43.7097434998],"type":"Point"}
}