{
  "type": "Feature",
  "properties": {
    "iso:country":"CA",
    "sg:address":"1335 Trunk Rd",
    "sg:city":"Sault Ste Marie",
    "sg:classifiers":[
        {
            "category":"Freight",
            "type":"Transportation"
        }
    ],
    "sg:phone":"+1 705 946 5353",
    "sg:postcode":"P6A 6X8",
    "sg:province":"ON",
    "sg:tags":[
        "contractor",
        "sewer",
        "trucking"
    ],
    "wof:name":"Wellwood & Sons",
    "wof:placetype":"venue"
},
  "geometry": {"coordinates":[-84.2492523193,46.5324668884],"type":"Point"}
}