{
  "type": "Feature",
  "properties": {
    "addr:full":"717 1/2 Queen St E Toronto ON M4M 1H1",
    "addr:housenumber":"717 1 / 2",
    "addr:postcode":"m4m 1h1",
    "addr:street":"Queen St E",
    "iso:country":"CA",
    "sg:address":"717 1/2 Queen St E",
    "sg:city":"Toronto",
    "sg:classifiers":[
        {
            "category":"Professional",
            "type":"Services"
        }
    ],
    "sg:phone":"+1 416 778 5596",
    "sg:postcode":"M4M 1H1",
    "sg:province":"ON",
    "sg:tags":[
        "arts",
        "artist"
    ],
    "wof:name":"Kolisnyk, Peter",
    "wof:placetype":"venue"
},
  "geometry": {"coordinates":[-79.34936500000001,43.658833],"type":"Point"}
}