{
  "type": "Feature",
  "properties": {
    "addr:full":"7110 Rte 366 Northport NS B0L 1E0",
    "addr:housenumber":"7110",
    "addr:postcode":"b0l 1e0",
    "addr:street":"Rte 366",
    "iso:country":"CA",
    "sg:address":"7110 Rte 366",
    "sg:city":"Northport",
    "sg:classifiers":[
        {
            "category":"Education",
            "subcategory":"School",
            "type":"Public Place"
        }
    ],
    "sg:phone":"+1 902 661 2490",
    "sg:postcode":"B0L 1E0",
    "sg:province":"NS",
    "wof:name":"Northport Consolidated Elem",
    "wof:placetype":"venue"
},
  "geometry": {"coordinates":[-63.8619880676,45.9305839539],"type":"Point"}
}