{
  "type": "Feature",
  "properties": {
    "addr:full":"1213 Caledonia Rd North York ON M6A 2X3",
    "addr:housenumber":"1213",
    "addr:postcode":"m6a 2x3",
    "addr:street":"Caledonia Rd",
    "iso:country":"CA",
    "sg:address":"1213 Caledonia Rd",
    "sg:city":"North York",
    "sg:classifiers":[
        {
            "category":"Autos & Motor Vehicles",
            "subcategory":"Auto Supplies",
            "type":"Retail Goods"
        }
    ],
    "sg:phone":"+1 416 781 6816",
    "sg:postcode":"M6A 2X3",
    "sg:province":"ON",
    "sg:tags":[
        "automobile",
        "parts"
    ],
    "wof:name":"Auto Spot Parts Depot",
    "wof:placetype":"venue"
},
  "geometry": {"coordinates":[-79.468193,43.718666],"type":"Point"}
}