{
  "type": "Feature",
  "properties": {
    "addr:full":"15844 Central Ave Inverness NS B0E 1N0",
    "addr:housenumber":"15844",
    "addr:postcode":"b0e 1n0",
    "addr:street":"Central Ave",
    "iso:country":"CA",
    "sg:address":"15844 Central Ave",
    "sg:city":"Inverness",
    "sg:classifiers":[
        {
            "category":"Shopping",
            "subcategory":"Clothing, Apparel, & Fashions",
            "type":"Retail Goods"
        }
    ],
    "sg:phone":"+1 902 258 2186",
    "sg:postcode":"B0E 1N0",
    "sg:province":"NS",
    "wof:name":"Grant's Family Clothing",
    "wof:placetype":"venue"
},
  "geometry": {"coordinates":[-61.30621,46.230019],"type":"Point"}
}