{
  "type": "Feature",
  "properties": {
    "addr:full":"479 Sherritt Ave Lynn Lake MB R0B 0W0",
    "addr:housenumber":"479",
    "addr:postcode":"r0b 0w0",
    "addr:street":"Sherritt Ave Lynn",
    "iso:country":"CA",
    "sg:address":"479 Sherritt Ave",
    "sg:city":"Lynn Lake",
    "sg:classifiers":[
        {
            "category":"Shopping",
            "subcategory":"Jewelry",
            "type":"Retail Goods"
        }
    ],
    "sg:phone":"+1 204 356 2961",
    "sg:postcode":"R0B 0W0",
    "sg:province":"MB",
    "sg:tags":[
        "jeweler"
    ],
    "wof:name":"Connie's Jewellery",
    "wof:placetype":"venue"
},
  "geometry": {"coordinates":[-101.048934937,56.8514709473],"type":"Point"}
}