{
  "type": "Feature",
  "properties": {
    "addr:full":"20745 36 Ave Langley BC V3A 4Y4",
    "addr:housenumber":"20745",
    "addr:postcode":"v3a 4y4",
    "addr:street":"36 Ave",
    "iso:country":"CA",
    "sg:address":"20745 36 Ave",
    "sg:city":"Langley",
    "sg:classifiers":[
        {
            "category":"Wholesale",
            "subcategory":"Meat",
            "type":"Manufacturing & Wholesale Goods"
        }
    ],
    "sg:phone":"+1 604 534 3675",
    "sg:postcode":"V3A 4Y4",
    "sg:province":"BC",
    "wof:name":"Valley Meat Snack Inc",
    "wof:placetype":"venue"
},
  "geometry": {"coordinates":[-122.649635315,49.0676651001],"type":"Point"}
}