{
  "type": "Feature",
  "properties": {
    "addr:full":"536 Rue Des Rossignols Gatineau QC J8R 1B2",
    "addr:housenumber":"536",
    "addr:postcode":"j8r 1b2",
    "addr:street":"Rue Des Rossignols",
    "iso:country":"CA",
    "sg:address":"536 Rue Des Rossignols",
    "sg:city":"Gatineau",
    "sg:classifiers":[
        {
            "category":"Arts & Performance",
            "subcategory":"Theater",
            "type":"Entertainment"
        }
    ],
    "sg:phone":"+1 819 669 9866",
    "sg:postcode":"J8R 1B2",
    "sg:province":"QC",
    "sg:tags":[
        "magician",
        "clown"
    ],
    "wof:name":"Clownatec",
    "wof:placetype":"venue"
},
  "geometry": {"coordinates":[-75.5801315308,45.501789093],"type":"Point"}
}