{
  "type": "Feature",
  "properties": {
    "addr:full":"4925 50 St Camrose AB T4V 1P9",
    "addr:housenumber":"4925",
    "addr:postcode":"t4v 1p9",
    "addr:street":"50 St",
    "iso:country":"CA",
    "sg:address":"4925 50 St",
    "sg:city":"Camrose",
    "sg:classifiers":[
        {
            "category":"Shopping",
            "subcategory":"Jewelry",
            "type":"Retail Goods"
        }
    ],
    "sg:phone":"+1 780 672 4000",
    "sg:postcode":"T4V 1P9",
    "sg:province":"AB",
    "sg:tags":[
        "jeweler"
    ],
    "wof:name":"Lascala Jewellers",
    "wof:placetype":"venue"
},
  "geometry": {"coordinates":[-112.824905395,53.0211410522],"type":"Point"}
}