{
  "type": "Feature",
  "properties": {
    "addr:full":"Woodstock ON N4S 7V9",
    "addr:postcode":"n4s 7v9",
    "iso:country":"CA",
    "sg:city":"Woodstock",
    "sg:classifiers":[
        {
            "category":"Retail",
            "subcategory":"Animal Services",
            "type":"Services"
        }
    ],
    "sg:phone":"+1 519 421 9869",
    "sg:postcode":"N4S 7V9",
    "sg:province":"ON",
    "sg:tags":[
        "pet",
        "grooming",
        "washing"
    ],
    "wof:name":"Rover's Return",
    "wof:placetype":"venue"
},
  "geometry": {"coordinates":[-80.7644271851,43.1417350769],"type":"Point"}
}