{
  "type": "Feature",
  "properties": {
    "addr:full":"Inverary ON K0H 1X0",
    "addr:postcode":"k0h 1x0",
    "iso:country":"CA",
    "sg:city":"Inverary",
    "sg:classifiers":[
        {
            "category":"Government",
            "subcategory":"Fire Station",
            "type":"Public Place"
        }
    ],
    "sg:phone":"+1 613 353 2255",
    "sg:postcode":"K0H 1X0",
    "sg:province":"ON",
    "sg:tags":[
        "department"
    ],
    "wof:name":"Storrington District Fire Dept",
    "wof:placetype":"venue"
},
  "geometry": {"coordinates":[-76.47435760499999,44.3861961365],"type":"Point"}
}