{
  "type": "Feature",
  "properties": {
    "addr:full":"585 28th St W Prince Albert SK S6V 4T1",
    "addr:housenumber":"585",
    "addr:postcode":"s6v 4t1",
    "addr:street":"28Th St",
    "iso:country":"CA",
    "sg:address":"585 28th St W",
    "sg:city":"Prince Albert",
    "sg:classifiers":[
        {
            "category":"Health Services",
            "subcategory":"Chiropractor",
            "type":"Services"
        }
    ],
    "sg:phone":"+1 306 764 6115",
    "sg:postcode":"S6V 4T1",
    "sg:province":"SK",
    "wof:name":"Braun, Janelle DC",
    "wof:placetype":"venue"
},
  "geometry": {"coordinates":[-105.769096,53.187576],"type":"Point"}
}