{
  "type": "Feature",
  "properties": {
    "iso:country":"CA",
    "sg:city":"Big Trout Lake",
    "sg:classifiers":[
        {
            "category":"Government",
            "subcategory":"Office",
            "type":"Public Place"
        }
    ],
    "sg:phone":"+1 807 537 2262",
    "sg:postcode":"P0V 1G0",
    "sg:province":"ON",
    "wof:name":"Canada Nursing Station",
    "wof:placetype":"venue"
},
  "geometry": {"coordinates":[-89.8350906372,53.8187599182],"type":"Point"}
}