{
  "type": "Feature",
  "properties": {
    "addr:full":"1264 Ch Trois Milles Saint-Jacques NB E7B 2J1",
    "addr:housenumber":"1264",
    "addr:postcode":"e7b 2j1",
    "addr:street":"Ch Trois Milles",
    "iso:country":"CA",
    "sg:address":"1264 Ch Trois Milles",
    "sg:city":"Saint-Jacques",
    "sg:classifiers":[
        {
            "category":"Building & Trades",
            "subcategory":"Construction",
            "type":"Services"
        }
    ],
    "sg:phone":"+1 506 735 1644",
    "sg:postcode":"E7B 2J1",
    "sg:province":"NB",
    "sg:tags":[
        "plastering",
        "contractor"
    ],
    "wof:name":"Pelletier Platrage",
    "wof:placetype":"venue"
},
  "geometry": {"coordinates":[-68.457069,47.409294],"type":"Point"}
}