{
  "type": "Feature",
  "properties": {
    "addr:full":"5797 Rue Hochelaga Montreal QC H1N 1W6",
    "addr:housenumber":"5797",
    "addr:postcode":"h1n 1w6",
    "addr:street":"Rue Hochelaga",
    "iso:country":"CA",
    "sg:address":"5797 Rue Hochelaga",
    "sg:city":"Montreal",
    "sg:classifiers":[
        {
            "category":"Social Services",
            "type":"Services"
        }
    ],
    "sg:phone":"+1 514 255 1054",
    "sg:postcode":"H1N 1W6",
    "sg:province":"QC",
    "sg:tags":[
        "organization",
        "welfare"
    ],
    "wof:name":"Parrainage Civique DE L'Est",
    "wof:placetype":"venue"
},
  "geometry": {"coordinates":[-73.5373840332,45.5710754395],"type":"Point"}
}