{
  "type": "Feature",
  "properties": {
    "addr:full":"376 Boul Saint-Joseph E Montreal QC H2T 1J6",
    "addr:housenumber":"376",
    "addr:postcode":"h2t 1j6",
    "addr:street":"Boul Saint-Joseph E",
    "iso:country":"CA",
    "sg:address":"376 Boul Saint-Joseph E",
    "sg:city":"Montreal",
    "sg:classifiers":[
        {
            "category":"Professional",
            "subcategory":"Business Services",
            "type":"Services"
        }
    ],
    "sg:phone":"+1 514 287 9796",
    "sg:postcode":"H2T 1J6",
    "sg:province":"QC",
    "sg:tags":[
        "notary"
    ],
    "wof:name":"Blouin, Sarto",
    "wof:placetype":"venue"
},
  "geometry": {"coordinates":[-73.587982,45.525883],"type":"Point"}
}