{
  "type": "Feature",
  "properties": {
    "iso:country":"CA",
    "sg:address":"Cp 11 Succ Mont-Royal",
    "sg:city":"Montreal",
    "sg:classifiers":[
        {
            "category":"Retail",
            "subcategory":"Repair Shop",
            "type":"Services"
        }
    ],
    "sg:phone":"+1 514 747 1623",
    "sg:postcode":"H3P 3B8",
    "sg:province":"QC",
    "sg:tags":[
        "lock",
        "locksmith"
    ],
    "wof:name":"Atelier Marc Gravel Serrurier",
    "wof:placetype":"venue"
},
  "geometry": {"coordinates":[-73.55438995359999,45.5122871399],"type":"Point"}
}