{
  "type": "Feature",
  "properties": {
    "addr:full":"1162 Av Des Ecoles Normandin QC G8M 3Z6",
    "addr:housenumber":"1162",
    "addr:postcode":"g8m 3z6",
    "addr:street":"Av Des Ecoles",
    "iso:country":"CA",
    "sg:address":"1162 Av Des Ecoles",
    "sg:city":"Normandin",
    "sg:classifiers":[
        {
            "category":"Health Services",
            "subcategory":"Nursing And Care Facility",
            "type":"Services"
        }
    ],
    "sg:phone":"+1 418 274 2993",
    "sg:postcode":"G8M 3Z6",
    "sg:province":"QC",
    "sg:tags":[
        "retirement",
        "site",
        "community",
        "reception",
        "wedding",
        "home"
    ],
    "wof:name":"Pavillon Normandin",
    "wof:placetype":"venue"
},
  "geometry": {"coordinates":[-72.5277557373,48.8364181519],"type":"Point"}
}