{
  "type": "Feature",
  "properties": {
    "addr:full":"113 Rue DE Fontenelle Blainville QC J7B 1M9",
    "addr:housenumber":"113",
    "addr:postcode":"j7b 1m9",
    "addr:street":"Rue De Fontenelle",
    "iso:country":"CA",
    "sg:address":"113 Rue DE Fontenelle",
    "sg:city":"Blainville",
    "sg:classifiers":[
        {
            "category":"Insurance",
            "subcategory":"Insurance Agent",
            "type":"Services"
        }
    ],
    "sg:phone":"+1 450 435 8880",
    "sg:postcode":"J7B 1M9",
    "sg:province":"QC",
    "wof:name":"Cadieux Beausejour Dupras Inc",
    "wof:placetype":"venue"
},
  "geometry": {"coordinates":[-73.83070373539999,45.6561012268],"type":"Point"}
}