{
  "type": "Feature",
  "properties": {
    "iso:country":"CA",
    "sg:city":"Montreal",
    "sg:classifiers":[
        {
            "category":"Wholesale",
            "subcategory":"Apparel",
            "type":"Manufacturing & Wholesale Goods"
        }
    ],
    "sg:phone":"+1 514 383 4546",
    "sg:postcode":"H2N 1C3",
    "sg:province":"QC",
    "sg:tags":[
        "infant",
        "wear"
    ],
    "wof:name":"Johnson Creations Inc",
    "wof:placetype":"venue"
},
  "geometry": {"coordinates":[-73.650742,45.545265],"type":"Point"}
}