{
  "type": "Feature",
  "properties": {
    "addr:full":"10121 Yonge St Richmond Hill ON L4C 1T7",
    "addr:housenumber":"10121",
    "addr:postcode":"l4c 1t7",
    "addr:street":"Yonge St",
    "iso:country":"CA",
    "sg:address":"10121 Yonge St",
    "sg:city":"Richmond Hill",
    "sg:classifiers":[
        {
            "category":"Social Services",
            "type":"Services"
        }
    ],
    "sg:phone":"+1 905 780 0491",
    "sg:postcode":"L4C 1T7",
    "sg:province":"ON",
    "sg:tags":[
        "organization",
        "welfare"
    ],
    "wof:name":"Krasman Centre",
    "wof:placetype":"venue"
},
  "geometry": {"coordinates":[-79.437592,43.873886],"type":"Point"}
}