{
  "type": "Feature",
  "properties": {
    "addr:full":"2 Eva Rd #200 Etobicoke ON M9C 2A8",
    "addr:housenumber":"2",
    "addr:postcode":"m9c 2a8",
    "addr:street":"Eva Rd # 200",
    "iso:country":"CA",
    "sg:address":"2 Eva Rd #200",
    "sg:city":"Etobicoke",
    "sg:classifiers":[
        {
            "category":"Professional",
            "type":"Services"
        }
    ],
    "sg:phone":"+1 416 622 0660",
    "sg:postcode":"M9C 2A8",
    "sg:province":"ON",
    "sg:tags":[
        "establishment",
        "investment"
    ],
    "wof:name":"Goran Capital Inc",
    "wof:placetype":"venue"
},
  "geometry": {"coordinates":[-79.563362,43.639729],"type":"Point"}
}