{
  "type": "Feature",
  "properties": {
    "addr:full":"9612 Yonge St Richmond Hill ON L4C 1V6",
    "addr:housenumber":"9612",
    "addr:postcode":"l4c 1v6",
    "addr:street":"Yonge St",
    "iso:country":"CA",
    "sg:address":"9612 Yonge St",
    "sg:city":"Richmond Hill",
    "sg:classifiers":[
        {
            "category":"Autos & Motor Vehicles",
            "subcategory":"Automobile Sales",
            "type":"Retail Goods"
        }
    ],
    "sg:phone":"+1 905 884 4481",
    "sg:postcode":"L4C 1V6",
    "sg:province":"ON",
    "sg:tags":[
        "car",
        "dealer"
    ],
    "wof:name":"Tomlinson Pontiac Buick Gmc",
    "wof:placetype":"venue"
},
  "geometry": {"coordinates":[-79.4352264404,43.8616218567],"type":"Point"}
}