{
  "type": "Feature",
  "properties": {
    "iso:country":"CA",
    "sg:address":"62 King St E",
    "sg:city":"Hamilton",
    "sg:classifiers":[
        {
            "category":"Restaurant",
            "type":"Food & Drink"
        }
    ],
    "sg:phone":"+1 905 577 7722",
    "sg:postcode":"L8N 1A6",
    "sg:province":"ON",
    "wof:name":"Finger's Bar & Grill",
    "wof:placetype":"venue"
},
  "geometry": {"coordinates":[-79.867378,43.255692],"type":"Point"}
}