{
  "type": "Feature",
  "properties": {
    "addr:full":"Red Deer AB T4R 2T4",
    "addr:postcode":"t4r 2t4",
    "iso:country":"CA",
    "sg:city":"Red Deer",
    "sg:classifiers":[
        {
            "category":"Insurance",
            "subcategory":"Insurance Agent",
            "type":"Services"
        }
    ],
    "sg:phone":"+1 403 342 7770",
    "sg:postcode":"T4R 2T4",
    "sg:province":"AB",
    "wof:name":"Allstate Insurance CO-Canada",
    "wof:placetype":"venue"
},
  "geometry": {"coordinates":[-113.818534851,52.2390174866],"type":"Point"}
}