{
  "type": "Feature",
  "properties": {
    "iso:country":"CA",
    "sg:city":"Burnaby",
    "sg:classifiers":[
        {
            "category":"Manufacturing",
            "subcategory":"Tools & Machinery",
            "type":"Manufacturing & Wholesale Goods"
        }
    ],
    "sg:phone":"+1 604 436 2739",
    "sg:postcode":"V5J 5H7",
    "sg:province":"BC",
    "sg:tags":[
        "machine",
        "shop"
    ],
    "wof:name":"Apex Technology Ltd",
    "wof:placetype":"venue"
},
  "geometry": {"coordinates":[-123.018066406,49.2005691528],"type":"Point"}
}