{
  "type": "Feature",
  "properties": {
    "iso:country":"CA",
    "sg:address":"2025 Corydon Ave",
    "sg:city":"Winnipeg",
    "sg:classifiers":[
        {
            "category":"Wholesale",
            "subcategory":"Groceries",
            "type":"Manufacturing & Wholesale Goods"
        }
    ],
    "sg:phone":"+1 204 488 6107",
    "sg:postcode":"R3P 0N5",
    "sg:province":"MB",
    "sg:tags":[
        "basket",
        "cocoa",
        "parcel",
        "gift",
        "chocolate"
    ],
    "wof:name":"Laura Secord/Hallmark",
    "wof:placetype":"venue"
},
  "geometry": {"coordinates":[-97.211639,49.866642],"type":"Point"}
}