{
  "type": "Feature",
  "properties": {
    "addr:full":"548 Riverbend Sq NW Edmonton AB T6R 2E3",
    "addr:housenumber":"548",
    "addr:postcode":"t6r 2e3",
    "addr:street":"Riverbend Sq Nw",
    "iso:country":"CA",
    "sg:address":"548 Riverbend Sq NW",
    "sg:city":"Edmonton",
    "sg:classifiers":[
        {
            "category":"Food & Beverages",
            "subcategory":"Specialty",
            "type":"Retail Goods"
        }
    ],
    "sg:phone":"+1 780 413 6488",
    "sg:postcode":"T6R 2E3",
    "sg:province":"AB",
    "sg:tags":[
        "health",
        "diet"
    ],
    "wof:name":"Natural Health Ctr Ltd",
    "wof:placetype":"venue"
},
  "geometry": {"coordinates":[-113.58782959,53.4697608948],"type":"Point"}
}