{
  "type": "Feature",
  "properties": {
    "addr:full":"581 Boul Saint-Rene E Gatineau QC J8P 8A6",
    "addr:housenumber":"581",
    "addr:postcode":"j8p 8a6",
    "addr:street":"Boul Saint-Rene E",
    "iso:country":"CA",
    "sg:address":"581 Boul Saint-Rene E",
    "sg:city":"Gatineau",
    "sg:classifiers":[
        {
            "category":"Utilities",
            "subcategory":"Fuel Oil & Lpg",
            "type":"Services"
        }
    ],
    "sg:phone":"+1 819 663 5868",
    "sg:postcode":"J8P 8A6",
    "sg:province":"QC",
    "sg:tags":[
        "conditioning",
        "air",
        "system",
        "contractor"
    ],
    "wof:name":"Raymond Huile A Chauffage",
    "wof:placetype":"venue"
},
  "geometry": {"coordinates":[-75.630821228,45.4954071045],"type":"Point"}
}