{
  "type": "Feature",
  "properties": {
    "addr:full":"4471 207A St Langley BC V3A 5V8",
    "addr:housenumber":"4471",
    "addr:postcode":"v3a 5v8",
    "addr:street":"207A St",
    "iso:country":"CA",
    "sg:address":"4471 207A St",
    "sg:city":"Langley",
    "sg:classifiers":[
        {
            "category":"Education",
            "subcategory":"School",
            "type":"Public Place"
        }
    ],
    "sg:phone":"+1 604 533 1285",
    "sg:postcode":"V3A 5V8",
    "sg:province":"BC",
    "wof:name":"Uplands Elementary School",
    "wof:placetype":"venue"
},
  "geometry": {"coordinates":[-122.65657,49.104122],"type":"Point"}
}