{
  "type": "Feature",
  "properties": {
    "addr:full":"3040 Rue DE Bourbon Sorel-Tracy QC J3R 4T3",
    "addr:housenumber":"3040",
    "addr:postcode":"j3r 4t3",
    "addr:street":"Rue De Bourbon",
    "iso:country":"CA",
    "sg:address":"3040 Rue DE Bourbon",
    "sg:city":"Sorel-Tracy",
    "sg:classifiers":[
        {
            "category":"Personal",
            "subcategory":"Barber",
            "type":"Services"
        }
    ],
    "sg:phone":"+1 450 743 6757",
    "sg:postcode":"J3R 4T3",
    "sg:province":"QC",
    "wof:name":"Salon Des Boises",
    "wof:placetype":"venue"
},
  "geometry": {"coordinates":[-73.151802,46.010464],"type":"Point"}
}