{
  "type": "Feature",
  "properties": {
    "iso:country":"CA",
    "sg:city":"Gores Landing",
    "sg:classifiers":[
        {
            "category":"Recreation",
            "subcategory":"Marina",
            "type":"Entertainment"
        }
    ],
    "sg:phone":"+1 905 342 2153",
    "sg:postcode":"K0K 2E0",
    "sg:province":"ON",
    "sg:tags":[
        "dealer",
        "boat",
        "sales"
    ],
    "wof:name":"Harris Boat Works Ltd",
    "wof:placetype":"venue"
},
  "geometry": {"coordinates":[-78.23249053959999,44.1192054749],"type":"Point"}
}