{
  "type": "Feature",
  "properties": {
    "addr:full":"497 Woolwich St Guelph ON N1H 3X9",
    "addr:housenumber":"497",
    "addr:postcode":"n1h 3x9",
    "addr:street":"Woolwich St",
    "iso:country":"CA",
    "sg:address":"497 Woolwich St",
    "sg:city":"Guelph",
    "sg:classifiers":[
        {
            "category":"Insurance",
            "subcategory":"Insurance Agent",
            "type":"Services"
        }
    ],
    "sg:phone":"+1 519 822 7110",
    "sg:postcode":"N1H 3X9",
    "sg:province":"ON",
    "sg:tags":[
        "adjuster"
    ],
    "wof:name":"Cunningham Lindsey Canada Ltd",
    "wof:placetype":"venue"
},
  "geometry": {"coordinates":[-80.2634429932,43.5550384521],"type":"Point"}
}