{
  "type": "Feature",
  "properties": {
    "addr:full":"1625 Ch Sainte-Angelique Saint-Lazare QC J7T 2X5",
    "addr:housenumber":"1625",
    "addr:postcode":"j7t 2x5",
    "addr:street":"Ch Sainte-Angelique",
    "iso:country":"CA",
    "sg:address":"1625 Ch Sainte-Angelique",
    "sg:city":"Saint-Lazare",
    "sg:classifiers":[
        {
            "category":"Restaurant",
            "type":"Food & Drink"
        }
    ],
    "sg:phone":"+1 450 455 4438",
    "sg:postcode":"J7T 2X5",
    "sg:province":"QC",
    "wof:name":"Planete St-Lazare",
    "wof:placetype":"venue"
},
  "geometry": {"coordinates":[-74.13023376460001,45.3990631104],"type":"Point"}
}