{
  "type": "Feature",
  "properties": {
    "addr:full":"6267 Av Aumont Brossard QC J4Z 1E9",
    "addr:housenumber":"6267",
    "addr:postcode":"j4z 1e9",
    "addr:street":"Av Aumont",
    "iso:country":"CA",
    "sg:address":"6267 Av Aumont",
    "sg:city":"Brossard",
    "sg:classifiers":[
        {
            "category":"Wholesale",
            "subcategory":"Office Equipment",
            "type":"Manufacturing & Wholesale Goods"
        }
    ],
    "sg:phone":"+1 450 926 3410",
    "sg:postcode":"J4Z 1E9",
    "sg:province":"QC",
    "sg:tags":[
        "accounting",
        "bookkeeping",
        "system"
    ],
    "wof:name":"Informer Inc",
    "wof:placetype":"venue"
},
  "geometry": {"coordinates":[-73.463058,45.476643],"type":"Point"}
}