{
  "type": "Feature",
  "properties": {
    "addr:full":"2 Merrymeeting Rd St. John's NL A1C 2V5",
    "addr:housenumber":"2",
    "addr:postcode":"a1c 2v5",
    "addr:street":"Merrymeeting Rd",
    "iso:country":"CA",
    "sg:address":"2 Merrymeeting Rd",
    "sg:city":"St. John's",
    "sg:classifiers":[
        {
            "category":"Retail",
            "subcategory":"Auto Repair",
            "type":"Services"
        }
    ],
    "sg:phone":"+1 709 753 8888",
    "sg:postcode":"A1C 2V5",
    "sg:province":"NL",
    "sg:tags":[
        "repairing",
        "automobile"
    ],
    "wof:name":"Janes Ultramar",
    "wof:placetype":"venue"
},
  "geometry": {"coordinates":[-52.71352005,47.5671272278],"type":"Point"}
}