{
  "type": "Feature",
  "properties": {
    "iso:country":"CA",
    "sg:address":"33285 Farrant Cres",
    "sg:city":"Abbotsford",
    "sg:classifiers":[
        {
            "category":"Building & Trades",
            "subcategory":"Landscaping Services",
            "type":"Services"
        }
    ],
    "sg:phone":"+1 604 850 7141",
    "sg:postcode":"V2S 1V4",
    "sg:province":"BC",
    "sg:tags":[
        "lawn",
        "maintenance",
        "grounds"
    ],
    "wof:name":"Vogt Home & Garden Svc",
    "wof:placetype":"venue"
},
  "geometry": {"coordinates":[-122.302139282,49.0448417664],"type":"Point"}
}