{
  "type": "Feature",
  "properties": {
    "iso:country":"CA",
    "sg:address":"770 1E Av",
    "sg:city":"Quebec",
    "sg:classifiers":[
        {
            "category":"Health Services",
            "subcategory":"Doctor",
            "type":"Services"
        }
    ],
    "sg:phone":"+1 418 529 0042",
    "sg:postcode":"G1L 3K2",
    "sg:province":"QC",
    "sg:tags":[
        "physician",
        "clinic",
        "surgeon"
    ],
    "wof:name":"Clinique Madico-Dentaire",
    "wof:placetype":"venue"
},
  "geometry": {"coordinates":[-71.231506,46.823669],"type":"Point"}
}