{
  "type": "Feature",
  "properties": {
    "addr:full":"470 Parliament St Toronto ON M5A 3A2",
    "addr:housenumber":"470",
    "addr:postcode":"m5a 3a2",
    "addr:street":"Parliament St",
    "iso:country":"CA",
    "sg:address":"470 Parliament St",
    "sg:city":"Toronto",
    "sg:classifiers":[
        {
            "category":"Health Services",
            "subcategory":"Doctor",
            "type":"Services"
        }
    ],
    "sg:phone":"+1 416 923 7492",
    "sg:postcode":"M5A 3A2",
    "sg:province":"ON",
    "sg:tags":[
        "dentist"
    ],
    "wof:name":"P Shillingford & Assoc",
    "wof:placetype":"venue"
},
  "geometry": {"coordinates":[-79.3680648804,43.6640892029],"type":"Point"}
}