{
  "type": "Feature",
  "properties": {
    "addr:full":"120 Av Duluth E Montreal QC H2W 1H1",
    "addr:postcode":"h2w 1h1",
    "addr:street":"120 Av Duluth E",
    "iso:country":"CA",
    "sg:address":"120 Av Duluth E",
    "sg:city":"Montreal",
    "sg:classifiers":[
        {
            "category":"Organizations",
            "subcategory":"Membership Organization",
            "type":"Services"
        }
    ],
    "sg:phone":"+1 514 282 0661",
    "sg:postcode":"H2W 1H1",
    "sg:province":"QC",
    "wof:name":"Rivo",
    "wof:placetype":"venue"
},
  "geometry": {"coordinates":[-73.578194,45.518032],"type":"Point"}
}