{
  "type": "Feature",
  "properties": {
    "iso:country":"CA",
    "sg:address":"5633 Teskey Way",
    "sg:city":"Chilliwack",
    "sg:classifiers":[
        {
            "category":"Real Estate",
            "subcategory":"Architect",
            "type":"Services"
        }
    ],
    "sg:phone":"+1 604 858 2691",
    "sg:postcode":"V2R 4V8",
    "sg:province":"BC",
    "wof:name":"Plantech Design & Drafting",
    "wof:placetype":"venue"
},
  "geometry": {"coordinates":[-121.93201446499999,49.1039619446],"type":"Point"}
}