{
  "type": "Feature",
  "properties": {
    "addr:full":"110 Woodbend Way Okotoks AB T1S 1L6",
    "addr:housenumber":"110",
    "addr:postcode":"t1s 1l6",
    "addr:street":"Woodbend Way;Ab",
    "iso:country":"CA",
    "sg:address":"110 Woodbend Way",
    "sg:city":"Okotoks",
    "sg:classifiers":[
        {
            "category":"Professional",
            "subcategory":"Business Services",
            "type":"Services"
        }
    ],
    "sg:phone":"+1 403 938 2137",
    "sg:postcode":"T1S 1L6",
    "sg:province":"AB",
    "sg:tags":[
        "field",
        "oil"
    ],
    "wof:name":"Homestead Vac Svc",
    "wof:placetype":"venue"
},
  "geometry": {"coordinates":[-113.97455600000001,50.71843],"type":"Point"}
}