{
  "type": "Feature",
  "properties": {
    "iso:country":"CA",
    "sg:address":"18 Love Cres",
    "sg:city":"Ajax",
    "sg:classifiers":[
        {
            "category":"Building & Trades",
            "subcategory":"Plumbing",
            "type":"Services"
        }
    ],
    "sg:phone":"+1 905 427 8734",
    "sg:postcode":"L1S 4T1",
    "sg:province":"ON",
    "sg:tags":[
        "heating",
        "contractor"
    ],
    "wof:name":"Blue Line Plumbing & Heating",
    "wof:placetype":"venue"
},
  "geometry": {"coordinates":[-79.0218582153,43.8198432922],"type":"Point"}
}