{
  "type": "Feature",
  "properties": {
    "iso:country":"CA",
    "sg:city":"Delta",
    "sg:classifiers":[
        {
            "category":"Manufacturing",
            "subcategory":"Tools & Machinery",
            "type":"Manufacturing & Wholesale Goods"
        }
    ],
    "sg:phone":"+1 604 525 0081",
    "sg:postcode":"V3M 6M4",
    "sg:province":"BC",
    "sg:tags":[
        "equipment",
        "hydraulic"
    ],
    "wof:name":"Hypower Systems Inc",
    "wof:placetype":"venue"
},
  "geometry": {"coordinates":[-122.96273803699999,49.1622657776],"type":"Point"}
}