{
  "type": "Feature",
  "properties": {
    "iso:country":"CA",
    "sg:city":"Winnipeg",
    "sg:classifiers":[
        {
            "category":"Professional",
            "subcategory":"Management & Consulting",
            "type":"Services"
        }
    ],
    "sg:phone":"+1 204 783 0283",
    "sg:postcode":"R3G 0R4",
    "sg:province":"MB",
    "sg:tags":[
        "consultant",
        "educational"
    ],
    "wof:name":"Foundations Learning Ctr",
    "wof:placetype":"venue"
},
  "geometry": {"coordinates":[-97.173828125,49.8846321106],"type":"Point"}
}