{
  "type": "Feature",
  "properties": {
    "iso:country":"CA",
    "sg:address":"4 Newton Ave",
    "sg:city":"Hamilton",
    "sg:classifiers":[
        {
            "category":"Retail",
            "subcategory":"Self-service Laundry",
            "type":"Services"
        }
    ],
    "sg:phone":"+1 905 524 1313",
    "sg:postcode":"L8S 1V7",
    "sg:province":"ON",
    "sg:tags":[
        "cleaners"
    ],
    "wof:name":"Westdale Laundromat",
    "wof:placetype":"venue"
},
  "geometry": {"coordinates":[-79.90731,43.261082],"type":"Point"}
}