{
  "type": "Feature",
  "properties": {
    "iso:country":"CA",
    "sg:address":"6790 Kitimat Rd #18",
    "sg:city":"Mississauga",
    "sg:classifiers":[
        {
            "category":"Manufacturing",
            "subcategory":"Glass & Minerals",
            "type":"Manufacturing & Wholesale Goods"
        }
    ],
    "sg:phone":"+1 905 821 3991",
    "sg:postcode":"L5N 5L9",
    "sg:province":"ON",
    "sg:tags":[
        "reflector"
    ],
    "wof:name":"Reflexite Canada Inc",
    "wof:placetype":"venue"
},
  "geometry": {"coordinates":[-79.736831665,43.6061897278],"type":"Point"}
}