{
  "type": "Feature",
  "properties": {
    "addr:full":"4060 Rue Sere Saint-Laurent QC H4T 1A6",
    "addr:housenumber":"4060",
    "addr:postcode":"h4t 1a6",
    "addr:street":"Rue Sere",
    "iso:country":"CA",
    "sg:address":"4060 Rue Sere",
    "sg:city":"Saint-Laurent",
    "sg:classifiers":[
        {
            "category":"Government",
            "subcategory":"Police Station",
            "type":"Public Place"
        }
    ],
    "sg:phone":"+1 514 341 4411",
    "sg:postcode":"H4T 1A6",
    "sg:province":"QC",
    "sg:tags":[
        "department"
    ],
    "wof:name":"Quebec Surete Du Quebec Ctr",
    "wof:placetype":"venue"
},
  "geometry": {"coordinates":[-73.706192,45.485538],"type":"Point"}
}