{
  "type": "Feature",
  "properties": {
    "addr:full":"2607 Portage Ave Winnipeg MB R3J 0P6",
    "addr:housenumber":"2607",
    "addr:postcode":"r3j 0p6",
    "addr:street":"Portage Ave",
    "iso:country":"CA",
    "sg:address":"2607 Portage Ave",
    "sg:city":"Winnipeg",
    "sg:classifiers":[
        {
            "category":"Autos & Motor Vehicles",
            "subcategory":"Fuel & Gas Station",
            "type":"Retail Goods"
        }
    ],
    "sg:phone":"+1 204 831 0020",
    "sg:postcode":"R3J 0P6",
    "sg:province":"MB",
    "sg:tags":[
        "oil"
    ],
    "wof:name":"Petro-Canada",
    "wof:placetype":"venue"
},
  "geometry": {"coordinates":[-97.2657623291,49.8763008118],"type":"Point"}
}