{
  "type": "Feature",
  "properties": {
    "addr:full":"1400 Vienna Rd Tillsonburg ON N4G 4G9",
    "addr:postcode":"1400;n4g 4g9",
    "addr:street":"Vienna Rd",
    "iso:country":"CA",
    "sg:address":"1400 Vienna Rd",
    "sg:city":"Tillsonburg",
    "sg:classifiers":[
        {
            "category":"Farming",
            "subcategory":"Farm & Veterinary Services",
            "type":"Manufacturing & Wholesale Goods"
        }
    ],
    "sg:phone":"+1 519 688 3362",
    "sg:postcode":"N4G 4G9",
    "sg:province":"ON",
    "wof:name":"Van Meer Farms Inc",
    "wof:placetype":"venue"
},
  "geometry": {"coordinates":[-80.72345,42.846142],"type":"Point"}
}