{
  "type": "Feature",
  "properties": {
    "addr:full":"5202 144 Ave NW Edmonton AB T5A 4E8",
    "addr:housenumber":"5202",
    "addr:postcode":"t5a 4e8",
    "addr:street":"144 Ave Nw",
    "iso:country":"CA",
    "sg:address":"5202 144 Ave NW",
    "sg:city":"Edmonton",
    "sg:classifiers":[
        {
            "category":"Real Estate",
            "subcategory":"Real Estate Agent",
            "type":"Services"
        }
    ],
    "sg:phone":"+1 780 476 0494",
    "sg:postcode":"T5A 4E8",
    "sg:province":"AB",
    "sg:tags":[
        "agency",
        "rental"
    ],
    "wof:name":"Homestead Housing CO-OP Ltd",
    "wof:placetype":"venue"
},
  "geometry": {"coordinates":[-113.421386719,53.6070785522],"type":"Point"}
}