{
  "type": "Feature",
  "properties": {
    "addr:full":"Montreal QC H2W 1Z3",
    "addr:postcode":"h2w 1z3",
    "iso:country":"CA",
    "sg:city":"Montreal",
    "sg:classifiers":[
        {
            "category":"Shopping",
            "subcategory":"Computers & Home Electronics",
            "type":"Retail Goods"
        }
    ],
    "sg:phone":"+1 514 495 8280",
    "sg:postcode":"H2W 1Z3",
    "sg:province":"QC",
    "sg:tags":[
        "software"
    ],
    "wof:name":"Inzigo Research",
    "wof:placetype":"venue"
},
  "geometry": {"coordinates":[-73.58308410639999,45.5185012817],"type":"Point"}
}