{
  "type": "Feature",
  "properties": {
    "addr:full":"803 Rue Principale Rougemont QC J0L 1M0",
    "addr:housenumber":"803",
    "addr:postcode":"j0l 1m0",
    "addr:street":"Rue Principale",
    "iso:country":"CA",
    "sg:address":"803 Rue Principale",
    "sg:city":"Rougemont",
    "sg:classifiers":[
        {
            "category":"Health Services",
            "subcategory":"Medical Lab",
            "type":"Services"
        }
    ],
    "sg:phone":"+1 450 469 2322",
    "sg:postcode":"J0L 1M0",
    "sg:province":"QC",
    "wof:name":"Bienvenue, Gilles",
    "wof:placetype":"venue"
},
  "geometry": {"coordinates":[-73.05748,45.438805],"type":"Point"}
}