{
  "type": "Feature",
  "properties": {
    "addr:full":"Vancouver BC V6Z 1L3",
    "addr:postcode":"v6z 1l3",
    "iso:country":"CA",
    "sg:city":"Vancouver",
    "sg:classifiers":[
        {
            "category":"Education",
            "subcategory":"Dance Studio",
            "type":"Public Place"
        }
    ],
    "sg:phone":"+1 604 258 0274",
    "sg:postcode":"V6Z 1L3",
    "sg:province":"BC",
    "sg:tags":[
        "instruction",
        "dancing"
    ],
    "wof:name":"Main Dance",
    "wof:placetype":"venue"
},
  "geometry": {"coordinates":[-123.122093201,49.2800827026],"type":"Point"}
}