{
  "type": "Feature",
  "properties": {
    "addr:full":"4608 50 Ave Bonnyville AB T9N 1A4",
    "addr:housenumber":"4608",
    "addr:postcode":"t9n 1a4",
    "addr:street":"50 Ave",
    "iso:country":"CA",
    "sg:address":"4608 50 Ave",
    "sg:city":"Bonnyville",
    "sg:classifiers":[
        {
            "category":"Shopping",
            "subcategory":"Clothing, Apparel, & Fashions",
            "type":"Retail Goods"
        }
    ],
    "sg:phone":"+1 780 826 3999",
    "sg:postcode":"T9N 1A4",
    "sg:province":"AB",
    "wof:name":"Fields Stores",
    "wof:placetype":"venue"
},
  "geometry": {"coordinates":[-110.730506897,54.2677383423],"type":"Point"}
}