{
  "type": "Feature",
  "properties": {
    "addr:full":"4811 Ch DE LA Savane Saint-Hubert QC J3Y 9G1",
    "addr:housenumber":"4811",
    "addr:postcode":"j3y 9g1",
    "addr:street":"Ch De La Savane",
    "iso:country":"CA",
    "sg:address":"4811 Ch DE LA Savane",
    "sg:city":"Saint-Hubert",
    "sg:classifiers":[
        {
            "category":"Wholesale",
            "subcategory":"Electrical",
            "type":"Manufacturing & Wholesale Goods"
        }
    ],
    "sg:phone":"+1 450 926 1778",
    "sg:postcode":"J3Y 9G1",
    "sg:province":"QC",
    "sg:tags":[
        "equipment",
        "electronic",
        "supply"
    ],
    "wof:name":"Varitron Technologies Inc",
    "wof:placetype":"venue"
},
  "geometry": {"coordinates":[-73.4268951416,45.521270752],"type":"Point"}
}