{
  "type": "Feature",
  "properties": {
    "iso:country":"CA",
    "sg:address":"391 Willowdale Ave",
    "sg:city":"North York",
    "sg:classifiers":[
        {
            "category":"Professional",
            "subcategory":"Lawyer & Legal Services",
            "type":"Services"
        }
    ],
    "sg:phone":"+1 416 590 0311",
    "sg:postcode":"M2N 5A8",
    "sg:province":"ON",
    "sg:tags":[
        "attorney"
    ],
    "wof:name":"Hartmann, Klaus A",
    "wof:placetype":"venue"
},
  "geometry": {"coordinates":[-79.404335022,43.7754859924],"type":"Point"}
}