{
  "type": "Feature",
  "properties": {
    "addr:full":"8110 Boul Decarie Montreal QC H4P 2S8",
    "addr:housenumber":"8110",
    "addr:postcode":"h4p 2s8",
    "addr:street":"Boul Decarie",
    "iso:country":"CA",
    "sg:address":"8110 Boul Decarie",
    "sg:city":"Montreal",
    "sg:classifiers":[
        {
            "category":"Shopping",
            "type":"Retail Goods"
        }
    ],
    "sg:phone":"+1 514 733 3939",
    "sg:postcode":"H4P 2S8",
    "sg:province":"QC",
    "sg:tags":[
        "art",
        "gallery",
        "dealer"
    ],
    "wof:name":"Dimension Plus",
    "wof:placetype":"venue"
},
  "geometry": {"coordinates":[-73.65967559809999,45.4979743958],"type":"Point"}
}