{
  "type": "Feature",
  "properties": {
    "iso:country":"CA",
    "sg:address":"736 Clarke Rd",
    "sg:city":"Coquitlam",
    "sg:classifiers":[
        {
            "category":"Real Estate",
            "subcategory":"Real Estate Agent",
            "type":"Services"
        }
    ],
    "sg:phone":"+1 604 931 1288",
    "sg:postcode":"V3J 3Y1",
    "sg:province":"BC",
    "sg:tags":[
        "cooperative"
    ],
    "wof:name":"Anskar Court Housing CO-OP",
    "wof:placetype":"venue"
},
  "geometry": {"coordinates":[-122.882041931,49.2677154541],"type":"Point"}
}