{
  "type": "Feature",
  "properties": {
    "addr:full":"Etobicoke ON M9V 4A8",
    "addr:postcode":"m9v 4a8",
    "iso:country":"CA",
    "sg:city":"Etobicoke",
    "sg:classifiers":[
        {
            "category":"Building & Trades",
            "subcategory":"Plumbing",
            "type":"Services"
        }
    ],
    "sg:phone":"+1 416 749 2200",
    "sg:postcode":"M9V 4A8",
    "sg:province":"ON",
    "sg:tags":[
        "heating",
        "contractor"
    ],
    "wof:name":"Cynergy Mechanical Ltd",
    "wof:placetype":"venue"
},
  "geometry": {"coordinates":[-79.60591125489999,43.7458763123],"type":"Point"}
}