{
  "type": "Feature",
  "properties": {
    "addr:full":"505 Rue St-Joseph St-Barnabe-Nord QC G0X 2K0",
    "addr:housenumber":"505",
    "addr:postcode":"g0x 2k0",
    "addr:street":"Rue St-Joseph St-Barnabe-Nord",
    "iso:country":"CA",
    "sg:address":"505 Rue St-Joseph",
    "sg:city":"St-Barnabe-Nord",
    "sg:classifiers":[
        {
            "category":"Retail",
            "subcategory":"Auto Repair",
            "type":"Services"
        }
    ],
    "sg:phone":"+1 819 264 2064",
    "sg:postcode":"G0X 2K0",
    "sg:province":"QC",
    "sg:tags":[
        "repairing",
        "automobile"
    ],
    "wof:name":"Centre Mecano Sylvain Lavergne",
    "wof:placetype":"venue"
},
  "geometry": {"coordinates":[-72.8800201416,46.393901825],"type":"Point"}
}