{
  "type": "Feature",
  "properties": {
    "addr:full":"2015 Lajoie St Lefaivre ON K0B 1J0",
    "addr:housenumber":"2015",
    "addr:postcode":"k0b 1j0",
    "addr:street":"Lajoie St",
    "iso:country":"CA",
    "sg:address":"2015 Lajoie St",
    "sg:city":"Lefaivre",
    "sg:classifiers":[
        {
            "category":"Government",
            "subcategory":"Office",
            "type":"Public Place"
        }
    ],
    "sg:phone":"+1 613 679 4631",
    "sg:postcode":"K0B 1J0",
    "sg:province":"ON",
    "wof:name":"Ontario Usines DE Traitement",
    "wof:placetype":"venue"
},
  "geometry": {"coordinates":[-74.8978881836,45.639175415],"type":"Point"}
}