{
  "type": "Feature",
  "properties": {
    "iso:country":"CA",
    "sg:city":"Thornbury",
    "sg:classifiers":[
        {
            "category":"Personal",
            "subcategory":"Beauty Salon",
            "type":"Services"
        }
    ],
    "sg:phone":"+1 519 599 3195",
    "sg:postcode":"N0H 2P0",
    "sg:province":"ON",
    "wof:name":"Curling Iron Beauty Salon",
    "wof:placetype":"venue"
},
  "geometry": {"coordinates":[-80.44882202150001,44.5611495972],"type":"Point"}
}