{
  "type": "Feature",
  "properties": {
    "addr:full":"165 Av Sunnyside Pointe-Claire QC H9R 3V2",
    "addr:housenumber":"165",
    "addr:postcode":"h9r 3v2",
    "addr:street":"Av Sunnyside",
    "iso:country":"CA",
    "sg:address":"165 Av Sunnyside",
    "sg:city":"Pointe-Claire",
    "sg:classifiers":[
        {
            "category":"Arts & Performance",
            "subcategory":"Theater",
            "type":"Entertainment"
        }
    ],
    "sg:phone":"+1 514 694 6892",
    "sg:postcode":"H9R 3V2",
    "sg:province":"QC",
    "sg:tags":[
        "band",
        "orchestra"
    ],
    "wof:name":"Peter Freeman Orchestra",
    "wof:placetype":"venue"
},
  "geometry": {"coordinates":[-73.8032,45.455128],"type":"Point"}
}