{
  "type": "Feature",
  "properties": {
    "addr:full":"11 Main St Cambridge ON N1R 1V5",
    "addr:housenumber":"11",
    "addr:postcode":"n1r 1v5",
    "addr:street":"Main St",
    "iso:country":"CA",
    "sg:address":"11 Main St",
    "sg:city":"Cambridge",
    "sg:classifiers":[
        {
            "category":"Banks & Credit Unions",
            "subcategory":"Bank",
            "type":"Services"
        }
    ],
    "sg:phone":"+1 519 621 5030",
    "sg:postcode":"N1R 1V5",
    "sg:province":"ON",
    "wof:name":"Cibc",
    "wof:placetype":"venue"
},
  "geometry": {"coordinates":[-80.31613900000001,43.358803],"type":"Point"}
}