{
  "type": "Feature",
  "properties": {
    "addr:full":"1846 Danforth Ave Toronto ON M4C 1H8",
    "addr:housenumber":"1846",
    "addr:postcode":"m4c 1h8",
    "addr:street":"Danforth Ave",
    "iso:country":"CA",
    "sg:address":"1846 Danforth Ave",
    "sg:city":"Toronto",
    "sg:classifiers":[
        {
            "category":"Food & Beverages",
            "subcategory":"Fruits & Vegetables",
            "type":"Retail Goods"
        }
    ],
    "sg:phone":"+1 416 461 6944",
    "sg:postcode":"M4C 1H8",
    "sg:province":"ON",
    "sg:tags":[
        "produce"
    ],
    "wof:name":"Prince of Wales Fruit Market",
    "wof:placetype":"venue"
},
  "geometry": {"coordinates":[-79.31778,43.684662],"type":"Point"}
}