{
  "type": "Feature",
  "properties": {
    "addr:full":"Mont-Tremblant QC J8E 1H5",
    "addr:postcode":"j8e 1h5",
    "iso:country":"CA",
    "sg:city":"Mont-Tremblant",
    "sg:classifiers":[
        {
            "category":"Manufacturing",
            "subcategory":"Printing",
            "type":"Manufacturing & Wholesale Goods"
        }
    ],
    "sg:phone":"+1 819 425 5551",
    "sg:postcode":"J8E 1H5",
    "sg:province":"QC",
    "sg:tags":[
        "publisher"
    ],
    "wof:name":"Sommets Du Mont-Tremblant",
    "wof:placetype":"venue"
},
  "geometry": {"coordinates":[-74.61539500000001,46.199162],"type":"Point"}
}