{
  "type": "Feature",
  "properties": {
    "iso:country":"CA",
    "sg:city":"Woodbridge",
    "sg:classifiers":[
        {
            "category":"Home & Garden",
            "subcategory":"Home Furnishings",
            "type":"Retail Goods"
        }
    ],
    "sg:phone":"+1 905 850 3273",
    "sg:postcode":"L4L 5W3",
    "sg:province":"ON",
    "sg:tags":[
        "mirror"
    ],
    "wof:name":"Je Rose Mirror & Glass Ltd",
    "wof:placetype":"venue"
},
  "geometry": {"coordinates":[-79.571686,43.7803],"type":"Point"}
}