{
  "type": "Feature",
  "properties": {
    "iso:country":"CA",
    "sg:address":"2374 Hoover Rd",
    "sg:city":"Campbell River",
    "sg:classifiers":[
        {
            "category":"Building & Trades",
            "subcategory":"Construction",
            "type":"Services"
        }
    ],
    "sg:phone":"+1 250 923 3200",
    "sg:postcode":"V9H 1C5",
    "sg:province":"BC",
    "sg:tags":[
        "excavating",
        "contractor"
    ],
    "wof:name":"Lana Construction Ltd",
    "wof:placetype":"venue"
},
  "geometry": {"coordinates":[-125.248168945,50.0246086121],"type":"Point"}
}