{
  "type": "Feature",
  "properties": {
    "addr:full":"Kamloops BC V2C 6M1",
    "addr:postcode":"bc v2c 6m1",
    "iso:country":"CA",
    "sg:city":"Kamloops",
    "sg:classifiers":[
        {
            "category":"Building & Trades",
            "subcategory":"Cleaning & Sanitation",
            "type":"Services"
        }
    ],
    "sg:phone":"+1 250 851 2935",
    "sg:postcode":"V2C 6M1",
    "sg:province":"BC",
    "sg:tags":[
        "janitor"
    ],
    "wof:name":"Jani-King",
    "wof:placetype":"venue"
},
  "geometry": {"coordinates":[-120.353584,50.666786],"type":"Point"}
}