{
  "type": "Feature",
  "properties": {
    "addr:full":"171 Rue DE LA Montagne Montreal QC H3C 2A6",
    "addr:housenumber":"171",
    "addr:postcode":"h3c 2a6",
    "addr:street":"Rue De La Montagne",
    "iso:country":"CA",
    "sg:address":"171 Rue DE LA Montagne",
    "sg:city":"Montreal",
    "sg:classifiers":[
        {
            "category":"Food & Beverages",
            "subcategory":"Groceries & Convenience Stores",
            "type":"Retail Goods"
        }
    ],
    "sg:phone":"+1 514 935 6925",
    "sg:postcode":"H3C 2A6",
    "sg:province":"QC",
    "sg:tags":[
        "grocer"
    ],
    "wof:name":"Depanneur DE LA Montagne",
    "wof:placetype":"venue"
},
  "geometry": {"coordinates":[-73.5595626831,45.4920349121],"type":"Point"}
}