{
  "type": "Feature",
  "properties": {
    "addr:full":"2809 44 Ave Vernon BC V1T 7P4",
    "addr:housenumber":"2809",
    "addr:postcode":"v1t 7p4",
    "addr:street":"44 Ave",
    "iso:country":"CA",
    "sg:address":"2809 44 Ave",
    "sg:city":"Vernon",
    "sg:classifiers":[
        {
            "category":"Organizations",
            "subcategory":"Professional Association",
            "type":"Services"
        }
    ],
    "sg:phone":"+1 250 545 3111",
    "sg:postcode":"V1T 7P4",
    "sg:province":"BC",
    "wof:name":"Red Cross Canadian Society",
    "wof:placetype":"venue"
},
  "geometry": {"coordinates":[-119.26872299999999,50.276402],"type":"Point"}
}