{
  "type": "Feature",
  "properties": {
    "addr:full":"Estevan SK S4A 2J4",
    "addr:postcode":"s4a 2j4",
    "iso:country":"CA",
    "sg:city":"Estevan",
    "sg:classifiers":[
        {
            "category":"Insurance",
            "subcategory":"Insurance Agent",
            "type":"Services"
        }
    ],
    "sg:phone":"+1 306 634 2671",
    "sg:postcode":"S4A 2J4",
    "sg:province":"SK",
    "wof:name":"Cathedral Insurance Brokers",
    "wof:placetype":"venue"
},
  "geometry": {"coordinates":[-102.993637085,49.1454772949],"type":"Point"}
}