{
  "type": "Feature",
  "properties": {
    "addr:full":"1173 Boul Charest O Quebec QC G1N 2C9",
    "addr:housenumber":"1173",
    "addr:postcode":"g1n 2c9",
    "addr:street":"Boul Charest O",
    "iso:country":"CA",
    "sg:address":"1173 Boul Charest O",
    "sg:city":"Quebec",
    "sg:classifiers":[
        {
            "category":"Professional",
            "subcategory":"Computer Services",
            "type":"Services"
        }
    ],
    "sg:phone":"+1 418 683 1080",
    "sg:postcode":"G1N 2C9",
    "sg:province":"QC",
    "sg:tags":[
        "graphics"
    ],
    "wof:name":"Solid Xperts",
    "wof:placetype":"venue"
},
  "geometry": {"coordinates":[-71.25361599999999,46.799908],"type":"Point"}
}