{
  "type": "Feature",
  "properties": {
    "addr:full":"Saint-Anaclet QC G0K 1H0",
    "addr:postcode":"g0k 1h0",
    "iso:country":"CA",
    "sg:city":"Saint-Anaclet",
    "sg:classifiers":[
        {
            "category":"Manufacturing",
            "subcategory":"Tools & Machinery",
            "type":"Manufacturing & Wholesale Goods"
        }
    ],
    "sg:phone":"+1 418 724 7222",
    "sg:postcode":"G0K 1H0",
    "sg:province":"QC",
    "sg:tags":[
        "farm",
        "equipment"
    ],
    "wof:name":"Equipements Lb",
    "wof:placetype":"venue"
},
  "geometry": {"coordinates":[-68.4098815918,48.4665107727],"type":"Point"}
}