{
  "type": "Feature",
  "properties": {
    "addr:full":"182 Dalhousie St New Glasgow NS B2H 4M3",
    "addr:housenumber":"182",
    "addr:postcode":"b2h 4m3",
    "addr:street":"Dalhousie St",
    "iso:country":"CA",
    "sg:address":"182 Dalhousie St",
    "sg:city":"New Glasgow",
    "sg:classifiers":[
        {
            "category":"Personal",
            "type":"Services"
        }
    ],
    "sg:phone":"+1 902 752 9543",
    "sg:postcode":"B2H 4M3",
    "sg:province":"NS",
    "sg:tags":[
        "genealogist"
    ],
    "wof:name":"Pictou County Roots Society",
    "wof:placetype":"venue"
},
  "geometry": {"coordinates":[-62.643989563,45.5879478455],"type":"Point"}
}