{
  "type": "Feature",
  "properties": {
    "iso:country":"CA",
    "sg:address":"16 Billa St # 203",
    "sg:city":"Bancroft",
    "sg:classifiers":[
        {
            "category":"Health Services",
            "subcategory":"Podiatrist",
            "type":"Services"
        }
    ],
    "sg:phone":"+1 613 332 1565",
    "sg:postcode":"K0L 1C0",
    "sg:province":"ON",
    "wof:name":"Ferguson, Peter J DPM",
    "wof:placetype":"venue"
},
  "geometry": {"coordinates":[-77.8497467041,45.0567398071],"type":"Point"}
}