{
  "type": "Feature",
  "properties": {
    "addr:full":"5329 48 Ave Taber AB T1G 1S7",
    "addr:housenumber":"5329",
    "addr:postcode":"t1g 1s7",
    "addr:street":"48 Ave Taber",
    "iso:country":"CA",
    "sg:address":"5329 48 Ave",
    "sg:city":"Taber",
    "sg:classifiers":[
        {
            "category":"Professional",
            "subcategory":"Accounting & Tax Preparation",
            "type":"Services"
        }
    ],
    "sg:phone":"+1 403 223 3798",
    "sg:postcode":"T1G 1S7",
    "sg:province":"AB",
    "sg:tags":[
        "accountant"
    ],
    "wof:name":"Valgardson, Kevin G CA",
    "wof:placetype":"venue"
},
  "geometry": {"coordinates":[-112.144256592,49.7848968506],"type":"Point"}
}