{
  "type": "Feature",
  "properties": {
    "addr:full":"295 Jamieson Pky Cambridge ON N3C 3X1",
    "addr:housenumber":"295",
    "addr:postcode":"n3c 3x1",
    "addr:street":"Jamieson Pky",
    "iso:country":"CA",
    "sg:address":"295 Jamieson Pky",
    "sg:city":"Cambridge",
    "sg:classifiers":[
        {
            "category":"Health Services",
            "subcategory":"Optometrist",
            "type":"Services"
        }
    ],
    "sg:phone":"+1 519 651 2872",
    "sg:postcode":"N3C 3X1",
    "sg:province":"ON",
    "wof:name":"Hespeler Family Eye Care Ctr",
    "wof:placetype":"venue"
},
  "geometry": {"coordinates":[-80.30341300000001,43.417564],"type":"Point"}
}