{
  "type": "Feature",
  "properties": {
    "iso:country":"CA",
    "sg:address":"69 Spencer St",
    "sg:city":"Ottawa",
    "sg:classifiers":[
        {
            "category":"Health Services",
            "subcategory":"Health Practitioner",
            "type":"Services"
        }
    ],
    "sg:phone":"+1 613 798 0595",
    "sg:postcode":"K1Y 4W8",
    "sg:province":"ON",
    "sg:tags":[
        "acupuncture"
    ],
    "wof:name":"Capital Acupuncture Healing",
    "wof:placetype":"venue"
},
  "geometry": {"coordinates":[-75.73263549799999,45.4020462036],"type":"Point"}
}