{
  "type": "Feature",
  "properties": {
    "addr:full":"4117 5 St E Claresholm AB T0L 0T0",
    "addr:housenumber":"4117 5",
    "addr:postcode":"t0l 0t0",
    "addr:street":"St E Claresholm",
    "iso:country":"CA",
    "sg:address":"4117 5 St E",
    "sg:city":"Claresholm",
    "sg:classifiers":[
        {
            "category":"Retail",
            "subcategory":"Auto Repair",
            "type":"Services"
        }
    ],
    "sg:phone":"+1 403 625 3000",
    "sg:postcode":"T0L 0T0",
    "sg:province":"AB",
    "sg:tags":[
        "repairing",
        "automobile"
    ],
    "wof:name":"Southgate Rv & Auto Svc",
    "wof:placetype":"venue"
},
  "geometry": {"coordinates":[-113.572891,50.027592],"type":"Point"}
}