{
  "type": "Feature",
  "properties": {
    "addr:full":"1454 Dundas St E Mississauga ON L4X 1L4",
    "addr:housenumber":"1454",
    "addr:postcode":"l4x 1l4",
    "addr:street":"Dundas St E",
    "iso:country":"CA",
    "sg:address":"1454 Dundas St E",
    "sg:city":"Mississauga",
    "sg:classifiers":[
        {
            "category":"Building & Trades",
            "subcategory":"Construction",
            "type":"Services"
        }
    ],
    "sg:phone":"+1 905 566 8064",
    "sg:postcode":"L4X 1L4",
    "sg:province":"ON",
    "sg:tags":[
        "contractor"
    ],
    "wof:name":"Mador Homes",
    "wof:placetype":"venue"
},
  "geometry": {"coordinates":[-79.5820846558,43.6106491089],"type":"Point"}
}