{
  "type": "Feature",
  "properties": {
    "addr:full":"414 Av Lafleur Lasalle QC H8R 3H6",
    "addr:postcode":"h8r 3h6",
    "addr:street":"414 Av Lafleur",
    "iso:country":"CA",
    "sg:address":"414 Av Lafleur",
    "sg:city":"Lasalle",
    "sg:classifiers":[
        {
            "category":"Education",
            "subcategory":"College",
            "type":"Public Place"
        }
    ],
    "sg:phone":"+1 514 363 8363",
    "sg:postcode":"H8R 3H6",
    "sg:province":"QC",
    "sg:tags":[
        "academic",
        "school"
    ],
    "wof:name":"College National DE Securite",
    "wof:placetype":"venue"
},
  "geometry": {"coordinates":[-73.6468048096,45.4319953918],"type":"Point"}
}