{
  "type": "Feature",
  "properties": {
    "addr:full":"86 Rue Du Seigneur-Cote L'Isle-Verte QC G0L 1K0",
    "addr:housenumber":"86",
    "addr:postcode":"g0l 1k0",
    "addr:street":"Rue Du Seigneur-Cote",
    "iso:country":"CA",
    "sg:address":"86 Rue Du Seigneur-Cote",
    "sg:city":"L'Isle-Verte",
    "sg:classifiers":[
        {
            "category":"Food & Beverages",
            "subcategory":"Meat & Fish",
            "type":"Retail Goods"
        }
    ],
    "sg:phone":"+1 418 898 3057",
    "sg:postcode":"G0L 1K0",
    "sg:province":"QC",
    "sg:tags":[
        "seafood"
    ],
    "wof:name":"Poissonnerie Georgette Enr",
    "wof:placetype":"venue"
},
  "geometry": {"coordinates":[-69.335205,48.018375],"type":"Point"}
}