{
  "type": "Feature",
  "properties": {
    "addr:full":"430 Balmoral St Thunder Bay ON P7C 5G8",
    "addr:housenumber":"430",
    "addr:postcode":"p7c 5g8",
    "addr:street":"Balmoral St",
    "iso:country":"CA",
    "sg:address":"430 Balmoral St",
    "sg:city":"Thunder Bay",
    "sg:classifiers":[
        {
            "category":"Building & Trades",
            "subcategory":"Pest Control",
            "type":"Services"
        }
    ],
    "sg:phone":"+1 807 577 2499",
    "sg:postcode":"P7C 5G8",
    "sg:province":"ON",
    "wof:name":"Nor West Pest Control",
    "wof:placetype":"venue"
},
  "geometry": {"coordinates":[-89.25797300000001,48.391285],"type":"Point"}
}