{
  "type": "Feature",
  "properties": {
    "addr:full":"3105 Benbow Rd West Vancouver BC V7V 3E1",
    "addr:housenumber":"3105",
    "addr:postcode":"v7v 3e1",
    "addr:street":"Benbow Rd",
    "iso:country":"CA",
    "sg:address":"3105 Benbow Rd",
    "sg:city":"West Vancouver",
    "sg:classifiers":[
        {
            "category":"Manufacturing",
            "subcategory":"Printing",
            "type":"Manufacturing & Wholesale Goods"
        }
    ],
    "sg:phone":"+1 604 922 5516",
    "sg:postcode":"V7V 3E1",
    "sg:province":"BC",
    "sg:tags":[
        "publication"
    ],
    "wof:name":"Electrical Line",
    "wof:placetype":"venue"
},
  "geometry": {"coordinates":[-123.202133179,49.3458099365],"type":"Point"}
}