{
  "type": "Feature",
  "properties": {
    "addr:full":"3rd Ave & 12th St Fort Macleod AB T0L 0Z0",
    "addr:postcode":"t0l 0z0",
    "addr:street":"3Rd Ave & 12Th St",
    "iso:country":"CA",
    "sg:address":"3rd Ave & 12th St",
    "sg:city":"Fort Macleod",
    "sg:classifiers":[
        {
            "category":"Home & Garden",
            "subcategory":"Hardware",
            "type":"Retail Goods"
        }
    ],
    "sg:phone":"+1 403 553 4642",
    "sg:postcode":"T0L 0Z0",
    "sg:province":"AB",
    "wof:name":"Alberta Hardware & Variety Ltd",
    "wof:placetype":"venue"
},
  "geometry": {"coordinates":[-113.40593,49.716282],"type":"Point"}
}