{
  "type": "Feature",
  "properties": {
    "iso:country":"CA",
    "sg:city":"Prince Albert",
    "sg:classifiers":[
        {
            "category":"Health Services",
            "subcategory":"Doctor",
            "type":"Services"
        }
    ],
    "sg:phone":"+1 306 764 1513",
    "sg:postcode":"S6V 3K8",
    "sg:province":"SK",
    "sg:tags":[
        "physician",
        "surgeon"
    ],
    "wof:name":"Associate Medical Clinic",
    "wof:placetype":"venue"
},
  "geometry": {"coordinates":[-105.760040283,53.2003593445],"type":"Point"}
}