{
  "type": "Feature",
  "properties": {
    "addr:full":"901 Rue Duhamel Saint-Lazare QC J7T 2B6",
    "addr:housenumber":"901",
    "addr:postcode":"j7t 2b6",
    "addr:street":"Rue Duhamel",
    "iso:country":"CA",
    "sg:address":"901 Rue Duhamel",
    "sg:city":"Saint-Lazare",
    "sg:classifiers":[
        {
            "category":"Retail",
            "subcategory":"Auto Repair",
            "type":"Services"
        }
    ],
    "sg:phone":"+1 450 455 9591",
    "sg:postcode":"J7T 2B6",
    "sg:province":"QC",
    "sg:tags":[
        "body",
        "automobile",
        "painting"
    ],
    "wof:name":"Rodrigue Auto Debosselage",
    "wof:placetype":"venue"
},
  "geometry": {"coordinates":[-74.10919199999999,45.376148],"type":"Point"}
}