{
  "type": "Feature",
  "properties": {
    "iso:country":"CA",
    "sg:city":"Mississauga",
    "sg:classifiers":[
        {
            "category":"Food & Beverages",
            "subcategory":"Bakery",
            "type":"Retail Goods"
        }
    ],
    "sg:phone":"+1 905 566 4401",
    "sg:postcode":"L4Y 1Y6",
    "sg:province":"ON",
    "sg:tags":[
        "baker"
    ],
    "wof:name":"Petit Paris Cake & Coffee Shop",
    "wof:placetype":"venue"
},
  "geometry": {"coordinates":[-79.5908203125,43.5931243896],"type":"Point"}
}