{
  "type": "Feature",
  "properties": {
    "iso:country":"CA",
    "sg:address":"89 Main St",
    "sg:city":"Cambridge",
    "sg:classifiers":[
        {
            "category":"Government",
            "subcategory":"Office",
            "type":"Public Place"
        }
    ],
    "sg:phone":"+1 519 623 0170",
    "sg:postcode":"N1R 1W1",
    "sg:province":"ON",
    "wof:name":"Ontario Attorney General",
    "wof:placetype":"venue"
},
  "geometry": {"coordinates":[-80.3126831055,43.3587493896],"type":"Point"}
}