{
  "type": "Feature",
  "properties": {
    "iso:country":"CA",
    "sg:address":"57 Northview Blvd # 4",
    "sg:city":"Woodbridge",
    "sg:classifiers":[
        {
            "category":"Shopping",
            "subcategory":"Gifts & Souvenirs",
            "type":"Retail Goods"
        }
    ],
    "sg:phone":"+1 905 264 3533",
    "sg:postcode":"L4L 8X9",
    "sg:province":"ON",
    "sg:tags":[
        "shop",
        "glassware",
        "chinaware"
    ],
    "wof:name":"Rob Mc Intosh China & Crystal",
    "wof:placetype":"venue"
},
  "geometry": {"coordinates":[-79.545662,43.791397],"type":"Point"}
}