{
  "type": "Feature",
  "properties": {
    "iso:country":"CA",
    "sg:city":"Marathon",
    "sg:classifiers":[
        {
            "category":"Government",
            "subcategory":"Police Station",
            "type":"Public Place"
        }
    ],
    "sg:phone":"+1 807 229 2242",
    "sg:postcode":"P0T 2E0",
    "sg:province":"ON",
    "sg:tags":[
        "department"
    ],
    "wof:name":"Ojibways Police Svc",
    "wof:placetype":"venue"
},
  "geometry": {"coordinates":[-86.3756942749,48.7199363708],"type":"Point"}
}