{
  "type": "Feature",
  "properties": {
    "addr:full":"Mont-Royal QC H4P 1B3",
    "addr:postcode":"h4p 1b3",
    "iso:country":"CA",
    "sg:city":"Mont-Royal",
    "sg:classifiers":[
        {
            "category":"Professional",
            "subcategory":"Management & Consulting",
            "type":"Services"
        }
    ],
    "sg:phone":"+1 514 341 9900",
    "sg:postcode":"H4P 1B3",
    "sg:province":"QC",
    "sg:tags":[
        "consultant",
        "telecommunication"
    ],
    "wof:name":"Lde Telecommunications Inc",
    "wof:placetype":"venue"
},
  "geometry": {"coordinates":[-73.660698,45.506222],"type":"Point"}
}