{
  "type": "Feature",
  "properties": {
    "addr:full":"219 Rang Saint-Luc Dolbeau-Mistassini QC G8L 6A2",
    "addr:housenumber":"219",
    "addr:postcode":"g8l 6a2",
    "addr:street":"Rang Saint-Luc",
    "iso:country":"CA",
    "sg:address":"219 Rang Saint-Luc",
    "sg:city":"Dolbeau-Mistassini",
    "sg:classifiers":[
        {
            "category":"Travel",
            "subcategory":"Campground",
            "type":"Entertainment"
        }
    ],
    "sg:phone":"+1 418 276 5544",
    "sg:postcode":"G8L 6A2",
    "sg:province":"QC",
    "sg:tags":[
        "camp"
    ],
    "wof:name":"Camp Service Jeunesse",
    "wof:placetype":"venue"
},
  "geometry": {"coordinates":[-72.233261,48.889881],"type":"Point"}
}