{
  "type": "Feature",
  "properties": {
    "iso:country":"CA",
    "sg:address":"67 Queen St W",
    "sg:city":"Elmvale",
    "sg:classifiers":[
        {
            "category":"Restaurant",
            "type":"Food & Drink"
        }
    ],
    "sg:phone":"+1 705 322 0641",
    "sg:postcode":"L0L 1P0",
    "sg:province":"ON",
    "wof:name":"Doctor's in",
    "wof:placetype":"venue"
},
  "geometry": {"coordinates":[-79.8694152832,44.5820121765],"type":"Point"}
}