{
  "type": "Feature",
  "properties": {
    "addr:full":"1316 Benjamin Cres Regina SK S4X 4K1",
    "addr:housenumber":"1316",
    "addr:postcode":"s4x 4k1",
    "addr:street":"Benjamin Cres",
    "iso:country":"CA",
    "sg:address":"1316 Benjamin Cres",
    "sg:city":"Regina",
    "sg:classifiers":[
        {
            "category":"Building & Trades",
            "subcategory":"Construction",
            "type":"Services"
        }
    ],
    "sg:phone":"+1 306 775 2661",
    "sg:postcode":"S4X 4K1",
    "sg:province":"SK",
    "sg:tags":[
        "plumbing",
        "contractor",
        "general"
    ],
    "wof:name":"Aabco Plumbing & Heating Ltd",
    "wof:placetype":"venue"
},
  "geometry": {"coordinates":[-104.663055,50.499287],"type":"Point"}
}