{
  "type": "Feature",
  "properties": {
    "addr:full":"100 Kemp St Bedford QC J0J 1A0",
    "addr:housenumber":"100",
    "addr:postcode":"j0j 1a0",
    "addr:street":"Kemp St",
    "iso:country":"CA",
    "sg:address":"100 Kemp St",
    "sg:city":"Bedford",
    "sg:classifiers":[
        {
            "category":"Manufacturing",
            "subcategory":"Tools & Machinery",
            "type":"Manufacturing & Wholesale Goods"
        }
    ],
    "sg:phone":"+1 450 248 2887",
    "sg:postcode":"J0J 1A0",
    "sg:province":"QC",
    "sg:tags":[
        "machine",
        "shop"
    ],
    "wof:name":"Atelier D'Usinage Choiniere",
    "wof:placetype":"venue"
},
  "geometry": {"coordinates":[-72.99271400000001,45.124943],"type":"Point"}
}