{
  "type": "Feature",
  "properties": {
    "addr:full":"57 Boul Hymus Pointe-Claire QC H9R 4T2",
    "addr:housenumber":"57",
    "addr:postcode":"h9r 4t2",
    "addr:street":"Boul Hymus",
    "iso:country":"CA",
    "sg:address":"57 Boul Hymus",
    "sg:city":"Pointe-Claire",
    "sg:classifiers":[
        {
            "category":"Manufacturing",
            "subcategory":"Paper Products",
            "type":"Manufacturing & Wholesale Goods"
        }
    ],
    "sg:phone":"+1 514 426 7192",
    "sg:postcode":"H9R 4T2",
    "sg:province":"QC",
    "sg:tags":[
        "packaging",
        "material"
    ],
    "wof:name":"Storopack Canada Inc",
    "wof:placetype":"venue"
},
  "geometry": {"coordinates":[-73.7965393066,45.4733085632],"type":"Point"}
}