{
  "type": "Feature",
  "properties": {
    "addr:full":"572 Main St Woodstock ON N4S 1V6",
    "addr:housenumber":"572",
    "addr:postcode":"n4s 1v6",
    "addr:street":"Main St",
    "iso:country":"CA",
    "sg:address":"572 Main St",
    "sg:city":"Woodstock",
    "sg:classifiers":[
        {
            "category":"Manufacturing",
            "subcategory":"Tools & Machinery",
            "type":"Manufacturing & Wholesale Goods"
        }
    ],
    "sg:phone":"+1 519 539 1287",
    "sg:postcode":"N4S 1V6",
    "sg:province":"ON",
    "sg:tags":[
        "machine",
        "shop"
    ],
    "wof:name":"Whitelaw Machinery CO Ltd",
    "wof:placetype":"venue"
},
  "geometry": {"coordinates":[-80.752747,43.12709],"type":"Point"}
}