{
  "type": "Feature",
  "properties": {
    "addr:full":"5206 58 St Lacombe AB T4L 1G9",
    "addr:housenumber":"5206",
    "addr:postcode":"t4l 1g9",
    "addr:street":"58 St",
    "iso:country":"CA",
    "sg:address":"5206 58 St",
    "sg:city":"Lacombe",
    "sg:classifiers":[
        {
            "category":"Education",
            "subcategory":"School",
            "type":"Public Place"
        }
    ],
    "sg:phone":"+1 403 782 6531",
    "sg:postcode":"T4L 1G9",
    "sg:province":"AB",
    "wof:name":"Lacombe Christian School",
    "wof:placetype":"venue"
},
  "geometry": {"coordinates":[-113.74751999999999,52.467422],"type":"Point"}
}