{
  "type": "Feature",
  "properties": {
    "addr:full":"331 Rue Saint-Francois LA Tuque QC G9X 1S2",
    "addr:housenumber":"331",
    "addr:postcode":"g9x 1s2",
    "addr:street":"Rue Saint-Francois",
    "iso:country":"CA",
    "sg:address":"331 Rue Saint-Francois",
    "sg:city":"LA Tuque",
    "sg:classifiers":[
        {
            "category":"Shopping",
            "subcategory":"Tobacco",
            "type":"Retail Goods"
        }
    ],
    "sg:phone":"+1 819 523 9222",
    "sg:postcode":"G9X 1S2",
    "sg:province":"QC",
    "sg:tags":[
        "cigarette",
        "cigar",
        "dealer"
    ],
    "wof:name":"Tabagie Tremblay Enr",
    "wof:placetype":"venue"
},
  "geometry": {"coordinates":[-72.7836074829,47.4375724792],"type":"Point"}
}