{
  "type": "Feature",
  "properties": {
    "iso:country":"CA",
    "sg:address":"7151 Ch DE LA Cote-Saint-Luc",
    "sg:city":"Cote Saint-Luc",
    "sg:classifiers":[
        {
            "category":"Food & Beverages",
            "subcategory":"Groceries & Convenience Stores",
            "type":"Retail Goods"
        }
    ],
    "sg:phone":"+1 514 486 3254",
    "sg:postcode":"H4V 1J2",
    "sg:province":"QC",
    "sg:tags":[
        "grocer"
    ],
    "wof:name":"Supermarche Pagano Shnaidman",
    "wof:placetype":"venue"
},
  "geometry": {"coordinates":[-73.6543426514,45.4649047852],"type":"Point"}
}