{
  "type": "Feature",
  "properties": {
    "addr:full":"4720 Ch Saint-Paul Laterriere QC G7N 1C7",
    "addr:postcode":"4720;g7n 1c7",
    "addr:street":"Ch Saint-Paul Laterriere",
    "iso:country":"CA",
    "sg:address":"4720 Ch Saint-Paul",
    "sg:city":"Laterriere",
    "sg:classifiers":[
        {
            "category":"Freight",
            "type":"Transportation"
        }
    ],
    "sg:phone":"+1 418 543 8075",
    "sg:postcode":"G7N 1C7",
    "sg:province":"QC",
    "sg:tags":[
        "trucking"
    ],
    "wof:name":"Transport Michel Murray",
    "wof:placetype":"venue"
},
  "geometry": {"coordinates":[-71.125671,48.338879],"type":"Point"}
}