{
  "type": "Feature",
  "properties": {
    "addr:full":"Farm Preeceville SK S0A 3B0",
    "addr:postcode":"s0a 3b0",
    "iso:country":"CA",
    "sg:address":"Farm",
    "sg:city":"Preeceville",
    "sg:classifiers":[
        {
            "category":"Wholesale",
            "subcategory":"Farm Supplies",
            "type":"Manufacturing & Wholesale Goods"
        }
    ],
    "sg:phone":"+1 306 548 4213",
    "sg:postcode":"S0A 3B0",
    "sg:province":"SK",
    "sg:tags":[
        "livestock"
    ],
    "wof:name":"Sturgis Livestock Ltd",
    "wof:placetype":"venue"
},
  "geometry": {"coordinates":[-102.668121,51.95631],"type":"Point"}
}