{
  "type": "Feature",
  "properties": {
    "iso:country":"CA",
    "sg:address":"3646 Reynolds Rd",
    "sg:city":"Nanaimo",
    "sg:classifiers":[
        {
            "category":"Building & Trades",
            "subcategory":"Construction",
            "type":"Services"
        }
    ],
    "sg:phone":"+1 250 714 0344",
    "sg:postcode":"V9T 2P4",
    "sg:province":"BC",
    "sg:tags":[
        "painter"
    ],
    "wof:name":"Fancy Walls",
    "wof:placetype":"venue"
},
  "geometry": {"coordinates":[-123.9896698,49.2112388611],"type":"Point"}
}