{
  "type": "Feature",
  "properties": {
    "addr:full":"1400 Boul Saint-Jude S Alma QC G8B 3L4",
    "addr:housenumber":"1400",
    "addr:postcode":"g8b 3l4",
    "addr:street":"Boul Saint-Jude S",
    "iso:country":"CA",
    "sg:address":"1400 Boul Saint-Jude S",
    "sg:city":"Alma",
    "sg:classifiers":[
        {
            "category":"Food & Beverages",
            "subcategory":"Fruits & Vegetables",
            "type":"Retail Goods"
        }
    ],
    "sg:phone":"+1 418 662 6647",
    "sg:postcode":"G8B 3L4",
    "sg:province":"QC",
    "wof:name":"Fruits Du Royaume Quebec 87",
    "wof:placetype":"venue"
},
  "geometry": {"coordinates":[-71.667389,48.531998],"type":"Point"}
}