{
  "type": "Feature",
  "properties": {
    "addr:full":"Surrey BC V3T 5R3",
    "addr:postcode":"v3t 5r3",
    "iso:country":"CA",
    "sg:city":"Surrey",
    "sg:classifiers":[
        {
            "category":"Banks & Credit Unions",
            "subcategory":"Bank",
            "type":"Services"
        }
    ],
    "sg:phone":"+1 604 581 2161",
    "sg:postcode":"V3T 5R3",
    "sg:province":"BC",
    "sg:tags":[
        "loan",
        "real estate"
    ],
    "wof:name":"Alpine Credits Ltd",
    "wof:placetype":"venue"
},
  "geometry": {"coordinates":[-122.830215454,49.105178833],"type":"Point"}
}