{
  "type": "Feature",
  "properties": {
    "iso:country":"CA",
    "sg:city":"Shelburne",
    "sg:classifiers":[
        {
            "category":"Wholesale",
            "subcategory":"Farm Supplies",
            "type":"Manufacturing & Wholesale Goods"
        }
    ],
    "sg:phone":"+1 519 925 2091",
    "sg:postcode":"L0N 1S0",
    "sg:province":"ON",
    "sg:tags":[
        "auctioneer"
    ],
    "wof:name":"Bob Severn Auctioneering",
    "wof:placetype":"venue"
},
  "geometry": {"coordinates":[-80.20208740229999,44.0787849426],"type":"Point"}
}