{
  "type": "Feature",
  "properties": {
    "iso:country":"CA",
    "sg:city":"Oakville",
    "sg:classifiers":[
        {
            "category":"Shopping",
            "subcategory":"Clothing, Apparel, & Fashions",
            "type":"Retail Goods"
        }
    ],
    "sg:phone":"+1 905 847 1512",
    "sg:postcode":"L6L 6L5",
    "sg:province":"ON",
    "sg:tags":[
        "lingerie"
    ],
    "wof:name":"Goodnight Goodmorning",
    "wof:placetype":"venue"
},
  "geometry": {"coordinates":[-79.711823,43.393944],"type":"Point"}
}