{
  "type": "Feature",
  "properties": {
    "addr:full":"160 Grant St Morden MB R6M 1Y4",
    "addr:housenumber":"160",
    "addr:postcode":"r6m 1y4",
    "addr:street":"Grant St",
    "iso:country":"CA",
    "sg:address":"160 Grant St",
    "sg:city":"Morden",
    "sg:classifiers":[
        {
            "category":"Utilities",
            "subcategory":"Refuse",
            "type":"Services"
        }
    ],
    "sg:phone":"+1 204 822 6859",
    "sg:postcode":"R6M 1Y4",
    "sg:province":"MB",
    "sg:tags":[
        "garbage",
        "collection"
    ],
    "wof:name":"Pembina Valley Containers",
    "wof:placetype":"venue"
},
  "geometry": {"coordinates":[-98.103531,49.18388],"type":"Point"}
}