{
  "type": "Feature",
  "properties": {
    "iso:country":"CA",
    "sg:address":"2118 King Rd",
    "sg:city":"King City",
    "sg:classifiers":[
        {
            "category":"Food & Beverages",
            "subcategory":"Bakery",
            "type":"Retail Goods"
        }
    ],
    "sg:phone":"+1 905 833 4759",
    "sg:postcode":"L7B 1L1",
    "sg:province":"ON",
    "sg:tags":[
        "doughnut"
    ],
    "wof:name":"Country Style Donuts",
    "wof:placetype":"venue"
},
  "geometry": {"coordinates":[-79.522682,43.930065],"type":"Point"}
}