{
  "type": "Feature",
  "properties": {
    "addr:full":"Calgary AB T2H 2H9",
    "addr:postcode":"t2h 2h9",
    "iso:country":"CA",
    "sg:city":"Calgary",
    "sg:classifiers":[
        {
            "category":"Wholesale",
            "subcategory":"Machinery & Supplies",
            "type":"Manufacturing & Wholesale Goods"
        }
    ],
    "sg:phone":"+1 403 253 2737",
    "sg:postcode":"T2H 2H9",
    "sg:province":"AB",
    "sg:tags":[
        "pump"
    ],
    "wof:name":"Hayward Gordon Ltd",
    "wof:placetype":"venue"
},
  "geometry": {"coordinates":[-114.054039,50.99786],"type":"Point"}
}