{
  "type": "Feature",
  "properties": {
    "addr:full":"155 Turbine Dr North York ON M9L 2S7",
    "addr:housenumber":"155",
    "addr:postcode":"m9l 2s7",
    "addr:street":"Turbine Dr",
    "iso:country":"CA",
    "sg:address":"155 Turbine Dr",
    "sg:city":"North York",
    "sg:classifiers":[
        {
            "category":"Manufacturing",
            "subcategory":"Tools & Machinery",
            "type":"Manufacturing & Wholesale Goods"
        }
    ],
    "sg:phone":"+1 416 749 3980",
    "sg:postcode":"M9L 2S7",
    "sg:province":"ON",
    "sg:tags":[
        "die",
        "stamping",
        "metal",
        "maker"
    ],
    "wof:name":"F & K Mfg CO Ltd",
    "wof:placetype":"venue"
},
  "geometry": {"coordinates":[-79.55732,43.7673],"type":"Point"}
}