{
  "type": "Feature",
  "properties": {
    "iso:country":"CA",
    "sg:city":"Kingston",
    "sg:classifiers":[
        {
            "category":"Professional",
            "subcategory":"Employment Agencies",
            "type":"Services"
        }
    ],
    "sg:phone":"+1 613 541 1100",
    "sg:postcode":"K7L 1H1",
    "sg:province":"ON",
    "sg:tags":[
        "opportunity"
    ],
    "wof:name":"Adecco Employment Svc Ltd",
    "wof:placetype":"venue"
},
  "geometry": {"coordinates":[-76.5105133057,44.2405662537],"type":"Point"}
}