{
  "type": "Feature",
  "properties": {
    "addr:full":"1190 Dixie Rd Mississauga ON L5E 2P4",
    "addr:housenumber":"1190",
    "addr:postcode":"l5e 2p4",
    "addr:street":"Dixie Rd",
    "iso:country":"CA",
    "sg:address":"1190 Dixie Rd",
    "sg:city":"Mississauga",
    "sg:classifiers":[
        {
            "category":"Sports & Exercise",
            "subcategory":"Golf",
            "type":"Entertainment"
        }
    ],
    "sg:phone":"+1 905 615 4653",
    "sg:postcode":"L5E 2P4",
    "sg:province":"ON",
    "sg:tags":[
        "course"
    ],
    "wof:name":"Lakeview Golf Course",
    "wof:placetype":"venue"
},
  "geometry": {"coordinates":[-79.555480957,43.5873947144],"type":"Point"}
}