{
  "type": "Feature",
  "properties": {
    "addr:full":"3180 Flint St Port Coquitlam BC V3B 4J1",
    "addr:housenumber":"3180",
    "addr:postcode":"v3b 4j1",
    "addr:street":"Flint St",
    "iso:country":"CA",
    "sg:address":"3180 Flint St",
    "sg:city":"Port Coquitlam",
    "sg:classifiers":[
        {
            "category":"Organizations",
            "subcategory":"Religious Organization",
            "type":"Services"
        }
    ],
    "sg:phone":"+1 604 941 3687",
    "sg:postcode":"V3B 4J1",
    "sg:province":"BC",
    "sg:tags":[
        "church"
    ],
    "wof:name":"Coquitlam Chinese Evangelical",
    "wof:placetype":"venue"
},
  "geometry": {"coordinates":[-122.77076,49.270672],"type":"Point"}
}