{
  "type": "Feature",
  "properties": {
    "iso:country":"CA",
    "sg:address":"6376 Village Rd",
    "sg:city":"Avola",
    "sg:classifiers":[
        {
            "category":"Bars & Pubs",
            "type":"Food & Drink"
        }
    ],
    "sg:phone":"+1 250 678 2337",
    "sg:postcode":"V0E 1C0",
    "sg:province":"BC",
    "wof:name":"Log Inn Pub",
    "wof:placetype":"venue"
},
  "geometry": {"coordinates":[-119.324188232,51.7827949524],"type":"Point"}
}