{
  "type": "Feature",
  "properties": {
    "addr:full":"1278 Av Du Bourg-Royal Charlesbourg QC G2L 1X9",
    "addr:housenumber":"1278",
    "addr:postcode":"g2l 1x9",
    "addr:street":"Av Du Bourg-Royal",
    "iso:country":"CA",
    "sg:address":"1278 Av Du Bourg-Royal",
    "sg:city":"Charlesbourg",
    "sg:classifiers":[
        {
            "category":"Building & Trades",
            "subcategory":"Landscaping Services",
            "type":"Services"
        }
    ],
    "sg:phone":"+1 418 624 0750",
    "sg:postcode":"G2L 1X9",
    "sg:province":"QC",
    "sg:tags":[
        "horticultural",
        "consultant"
    ],
    "wof:name":"Entreprises Pousse-Partout",
    "wof:placetype":"venue"
},
  "geometry": {"coordinates":[-71.25532531739999,46.8895683289],"type":"Point"}
}