{
  "type": "Feature",
  "properties": {
    "addr:full":"411 Main St N Russell MB R0J 1W0",
    "addr:housenumber":"411",
    "addr:postcode":"r0j 1w0",
    "addr:street":"Main St N",
    "iso:country":"CA",
    "sg:address":"411 Main St N",
    "sg:city":"Russell",
    "sg:classifiers":[
        {
            "category":"Autos & Motor Vehicles",
            "subcategory":"Auto Supplies",
            "type":"Retail Goods"
        }
    ],
    "sg:phone":"+1 204 773 3391",
    "sg:postcode":"R0J 1W0",
    "sg:province":"MB",
    "sg:tags":[
        "automobile",
        "parts"
    ],
    "wof:name":"Russell Farm & Auto",
    "wof:placetype":"venue"
},
  "geometry": {"coordinates":[-101.288009644,50.7827758789],"type":"Point"}
}