{
  "type": "Feature",
  "properties": {
    "iso:country":"CA",
    "sg:address":"1032 17 Ave SW",
    "sg:city":"Calgary",
    "sg:classifiers":[
        {
            "category":"Personal",
            "subcategory":"Beauty Salon",
            "type":"Services"
        }
    ],
    "sg:phone":"+1 403 209 1855",
    "sg:postcode":"T2T 0A5",
    "sg:province":"AB",
    "wof:name":"Hair By Sean & CO",
    "wof:placetype":"venue"
},
  "geometry": {"coordinates":[-114.085914612,51.0378990173],"type":"Point"}
}