{
  "type": "Feature",
  "properties": {
    "addr:full":"1391 Gerrard St E Toronto ON M4L 1Z3",
    "addr:housenumber":"1391",
    "addr:postcode":"m4l 1z3",
    "addr:street":"Gerrard St E",
    "iso:country":"CA",
    "sg:address":"1391 Gerrard St E",
    "sg:city":"Toronto",
    "sg:classifiers":[
        {
            "category":"Health Services",
            "subcategory":"Health Practitioner",
            "type":"Services"
        }
    ],
    "sg:phone":"+1 416 778 7334",
    "sg:postcode":"M4L 1Z3",
    "sg:province":"ON",
    "sg:tags":[
        "homeopath"
    ],
    "wof:name":"Chopra Homeopathy Ctr",
    "wof:placetype":"venue"
},
  "geometry": {"coordinates":[-79.32415771479999,43.6716423035],"type":"Point"}
}