{
  "type": "Feature",
  "properties": {
    "addr:full":"St Leonard NB E7E 1Y6",
    "addr:postcode":"e7e 1y6",
    "addr:street":"St",
    "iso:country":"CA",
    "sg:city":"St Leonard",
    "sg:classifiers":[
        {
            "category":"Organizations",
            "subcategory":"Professional Association",
            "type":"Services"
        }
    ],
    "sg:phone":"+1 506 423 7216",
    "sg:postcode":"E7E 1Y6",
    "sg:province":"NB",
    "wof:name":"Centre DE Formation & Soutien",
    "wof:placetype":"venue"
},
  "geometry": {"coordinates":[-67.91980700000001,47.166531],"type":"Point"}
}