{
  "type": "Feature",
  "properties": {
    "addr:full":"1492 Victoria Park Ave North York ON M4A 2M6",
    "addr:housenumber":"1492",
    "addr:postcode":"m4a 2m6",
    "addr:street":"Victoria Park Ave",
    "iso:country":"CA",
    "sg:address":"1492 Victoria Park Ave",
    "sg:city":"North York",
    "sg:classifiers":[
        {
            "category":"Social Services",
            "subcategory":"Child Care",
            "type":"Services"
        }
    ],
    "sg:phone":"+1 416 755 0305",
    "sg:postcode":"M4A 2M6",
    "sg:province":"ON",
    "wof:name":"My Little School",
    "wof:placetype":"venue"
},
  "geometry": {"coordinates":[-79.30246,43.723831],"type":"Point"}
}