{
  "type": "Feature",
  "properties": {
    "addr:full":"202 1st Ave S Vulcan AB T0L 2B0",
    "addr:housenumber":"202",
    "addr:postcode":"t0l 2b0",
    "addr:street":"1St Ave S Vulcan",
    "iso:country":"CA",
    "sg:address":"202 1st Ave S",
    "sg:city":"Vulcan",
    "sg:classifiers":[
        {
            "category":"Autos & Motor Vehicles",
            "subcategory":"Fuel & Gas Station",
            "type":"Retail Goods"
        }
    ],
    "sg:phone":"+1 403 485 6300",
    "sg:postcode":"T0L 2B0",
    "sg:province":"AB",
    "sg:tags":[
        "oil"
    ],
    "wof:name":"Mohawk",
    "wof:placetype":"venue"
},
  "geometry": {"coordinates":[-113.25955200200001,50.4042739868],"type":"Point"}
}