{
  "type": "Feature",
  "properties": {
    "addr:full":"227 1/2 Second St S Kenora ON P9N 1G1",
    "addr:housenumber":"227 1 / 2",
    "addr:postcode":"p9n 1g1",
    "addr:street":"Second St S",
    "iso:country":"CA",
    "sg:address":"227 1/2 Second St S",
    "sg:city":"Kenora",
    "sg:classifiers":[
        {
            "category":"Professional",
            "subcategory":"Management & Consulting",
            "type":"Services"
        }
    ],
    "sg:phone":"+1 807 467 4640",
    "sg:postcode":"P9N 1G1",
    "sg:province":"ON",
    "sg:tags":[
        "consultant",
        "business"
    ],
    "wof:name":"Lake of the Woods Business",
    "wof:placetype":"venue"
},
  "geometry": {"coordinates":[-94.4902191162,49.7660598755],"type":"Point"}
}