{
  "type": "Feature",
  "properties": {
    "addr:full":"252 6th St S Winkler MB R6W 2P3",
    "addr:housenumber":"252",
    "addr:postcode":"r6w 2p3",
    "addr:street":"6Th St S",
    "iso:country":"CA",
    "sg:address":"252 6th St S",
    "sg:city":"Winkler",
    "sg:classifiers":[
        {
            "category":"Organizations",
            "subcategory":"Religious Organization",
            "type":"Services"
        }
    ],
    "sg:phone":"+1 204 325 9563",
    "sg:postcode":"R6W 2P3",
    "sg:province":"MB",
    "sg:tags":[
        "church"
    ],
    "wof:name":"Winkler Bergthaler Mennonite",
    "wof:placetype":"venue"
},
  "geometry": {"coordinates":[-97.9408950806,49.1717185974],"type":"Point"}
}