{
  "type": "Feature",
  "properties": {
    "addr:full":"18 Brockley Dr Hamilton ON L8E 3P1",
    "addr:housenumber":"18",
    "addr:postcode":"l8e 3p1",
    "addr:street":"Brockley Dr",
    "iso:country":"CA",
    "sg:address":"18 Brockley Dr",
    "sg:city":"Hamilton",
    "sg:classifiers":[
        {
            "category":"Wholesale",
            "subcategory":"Hardware",
            "type":"Manufacturing & Wholesale Goods"
        }
    ],
    "sg:phone":"+1 905 561 4461",
    "sg:postcode":"L8E 3P1",
    "sg:province":"ON",
    "sg:tags":[
        "parts",
        "refrigerating"
    ],
    "wof:name":"Carrier Canada",
    "wof:placetype":"venue"
},
  "geometry": {"coordinates":[-79.745819,43.234608],"type":"Point"}
}