{
  "type": "Feature",
  "properties": {
    "addr:full":"10010 171 St NW Edmonton AB T5S 1S3",
    "addr:housenumber":"10010",
    "addr:postcode":"t5s 1s3",
    "addr:street":"171 St Nw",
    "iso:country":"CA",
    "sg:address":"10010 171 St NW",
    "sg:city":"Edmonton",
    "sg:classifiers":[
        {
            "category":"Restaurant",
            "type":"Food & Drink"
        }
    ],
    "sg:phone":"+1 780 484 6735",
    "sg:postcode":"T5S 1S3",
    "sg:province":"AB",
    "wof:name":"Red Robin Restaurant",
    "wof:placetype":"venue"
},
  "geometry": {"coordinates":[-113.617126,53.539642],"type":"Point"}
}