{
  "type": "Feature",
  "properties": {
    "addr:full":"11228 33 Ave NW Edmonton AB T6J 3X3",
    "addr:housenumber":"11228",
    "addr:postcode":"t6j 3x3",
    "addr:street":"33 Ave Nw",
    "iso:country":"CA",
    "sg:address":"11228 33 Ave NW",
    "sg:city":"Edmonton",
    "sg:classifiers":[
        {
            "category":"Building & Trades",
            "subcategory":"Construction",
            "type":"Services"
        }
    ],
    "sg:phone":"+1 780 437 2460",
    "sg:postcode":"T6J 3X3",
    "sg:province":"AB",
    "sg:tags":[
        "wallpaper",
        "painter"
    ],
    "wof:name":"Shen Enterprises Painting",
    "wof:placetype":"venue"
},
  "geometry": {"coordinates":[-113.521233,53.465588],"type":"Point"}
}