{
  "type": "Feature",
  "properties": {
    "addr:full":"130 King St London ON N6A 1C5",
    "addr:housenumber":"130",
    "addr:postcode":"n6a 1c5",
    "addr:street":"King St",
    "iso:country":"CA",
    "sg:address":"130 King St",
    "sg:city":"London",
    "sg:classifiers":[
        {
            "category":"Shopping",
            "type":"Retail Goods"
        }
    ],
    "sg:phone":"+1 519 642 0202",
    "sg:postcode":"N6A 1C5",
    "sg:province":"ON",
    "sg:tags":[
        "candle"
    ],
    "wof:name":"Candle Tree",
    "wof:placetype":"venue"
},
  "geometry": {"coordinates":[-81.25058,42.982243],"type":"Point"}
}