{
  "type": "Feature",
  "properties": {
    "addr:full":"9095 25E Av Saint-Georges QC G6A 1A1",
    "addr:housenumber":"9095",
    "addr:postcode":"g6a 1a1",
    "addr:street":"25E Av",
    "iso:country":"CA",
    "sg:address":"9095 25E Av",
    "sg:city":"Saint-Georges",
    "sg:classifiers":[
        {
            "category":"Manufacturing",
            "subcategory":"Motor Vehicles & Parts",
            "type":"Manufacturing & Wholesale Goods"
        }
    ],
    "sg:phone":"+1 418 228 8934",
    "sg:postcode":"G6A 1A1",
    "sg:province":"QC",
    "sg:tags":[
        "fabricator",
        "bicycle"
    ],
    "wof:name":"Procycle Inc",
    "wof:placetype":"venue"
},
  "geometry": {"coordinates":[-70.67455291749999,46.1438179016],"type":"Point"}
}