{
  "type": "Feature",
  "properties": {
    "addr:full":"946 Main St Dartmouth NS B2W 3V3",
    "addr:housenumber":"946",
    "addr:postcode":"b2w 3v3",
    "addr:street":"Main St",
    "iso:country":"CA",
    "sg:address":"946 Main St",
    "sg:city":"Dartmouth",
    "sg:classifiers":[
        {
            "category":"Organizations",
            "subcategory":"Religious Organization",
            "type":"Services"
        }
    ],
    "sg:phone":"+1 902 462 6099",
    "sg:postcode":"B2W 3V3",
    "sg:province":"NS",
    "sg:tags":[
        "church"
    ],
    "wof:name":"City Heights Church",
    "wof:placetype":"venue"
},
  "geometry": {"coordinates":[-63.482521,44.700317],"type":"Point"}
}