{
  "type": "Feature",
  "properties": {
    "addr:full":"273 Londonderry Mall NW Edmonton AB T5C 3C8",
    "addr:housenumber":"273",
    "addr:postcode":"t5c 3c8",
    "addr:street":"Londonderry Mall Nw",
    "iso:country":"CA",
    "sg:address":"273 Londonderry Mall NW",
    "sg:city":"Edmonton",
    "sg:classifiers":[
        {
            "category":"Restaurant",
            "type":"Food & Drink"
        }
    ],
    "sg:phone":"+1 780 473 6013",
    "sg:postcode":"T5C 3C8",
    "sg:province":"AB",
    "wof:name":"Louie's Submarine",
    "wof:placetype":"venue"
},
  "geometry": {"coordinates":[-113.490371704,53.5462188721],"type":"Point"}
}