{
  "type": "Feature",
  "properties": {
    "addr:full":"819 Boul Maloney E Gatineau QC J8P 1G5",
    "addr:housenumber":"819",
    "addr:postcode":"j8p 1g5",
    "addr:street":"Boul Maloney E",
    "iso:country":"CA",
    "sg:address":"819 Boul Maloney E",
    "sg:city":"Gatineau",
    "sg:classifiers":[
        {
            "category":"Recreation",
            "subcategory":"Marina",
            "type":"Entertainment"
        }
    ],
    "sg:phone":"+1 819 643 9104",
    "sg:postcode":"J8P 1G5",
    "sg:province":"QC",
    "sg:tags":[
        "repairing",
        "boat"
    ],
    "wof:name":"Marc Marine",
    "wof:placetype":"venue"
},
  "geometry": {"coordinates":[-75.610596,45.484043],"type":"Point"}
}