{
  "type": "Feature",
  "properties": {
    "addr:full":"260 3E Rue Notre-Dame-Du-Mont-Carmel QC G0X 3J0",
    "addr:housenumber":"260",
    "addr:postcode":"g0x 3j0",
    "addr:street":"3E Rue",
    "iso:country":"CA",
    "sg:address":"260 3E Rue",
    "sg:city":"Notre-Dame-Du-Mont-Carmel",
    "sg:classifiers":[
        {
            "category":"Health Services",
            "subcategory":"Nursing And Care Facility",
            "type":"Services"
        }
    ],
    "sg:phone":"+1 819 375 8744",
    "sg:postcode":"G0X 3J0",
    "sg:province":"QC",
    "sg:tags":[
        "home",
        "retirement",
        "community"
    ],
    "wof:name":"Pavillon Valmont Enr",
    "wof:placetype":"venue"
},
  "geometry": {"coordinates":[-69.86582900000001,47.437191],"type":"Point"}
}