{
  "type": "Feature",
  "properties": {
    "addr:full":"1278 Wharf St Pickering ON L1W 1A3",
    "addr:housenumber":"1278",
    "addr:postcode":"l1w 1a3",
    "addr:street":"Wharf St",
    "iso:country":"CA",
    "sg:address":"1278 Wharf St",
    "sg:city":"Pickering",
    "sg:classifiers":[
        {
            "category":"Recreation",
            "subcategory":"Marina",
            "type":"Entertainment"
        }
    ],
    "sg:phone":"+1 905 420 8869",
    "sg:postcode":"L1W 1A3",
    "sg:province":"ON",
    "sg:tags":[
        "repairing",
        "boat"
    ],
    "wof:name":"Northern Yacht Ltd",
    "wof:placetype":"venue"
},
  "geometry": {"coordinates":[-79.0823669434,43.8159675598],"type":"Point"}
}