{
  "type": "Feature",
  "properties": {
    "addr:full":"1104 Pembina Hwy Winnipeg MB R3T 1Z9",
    "addr:housenumber":"1104",
    "addr:postcode":"r3t 1z9",
    "addr:street":"Pembina Hwy",
    "iso:country":"CA",
    "sg:address":"1104 Pembina Hwy",
    "sg:city":"Winnipeg",
    "sg:classifiers":[
        {
            "category":"Building & Trades",
            "subcategory":"Landscaping Services",
            "type":"Services"
        }
    ],
    "sg:phone":"+1 204 475 6362",
    "sg:postcode":"R3T 1Z9",
    "sg:province":"MB",
    "sg:tags":[
        "excavating",
        "landscape",
        "contractor"
    ],
    "wof:name":"Chico's Bobcat Svc",
    "wof:placetype":"venue"
},
  "geometry": {"coordinates":[-97.15252700000001,49.848351],"type":"Point"}
}