{
  "type": "Feature",
  "properties": {
    "iso:country":"CA",
    "sg:city":"Ottawa",
    "sg:classifiers":[
        {
            "category":"Professional",
            "subcategory":"Lawyer & Legal Services",
            "type":"Services"
        }
    ],
    "sg:phone":"+1 613 232 3574",
    "sg:postcode":"K2P 0G3",
    "sg:province":"ON",
    "sg:tags":[
        "attorney"
    ],
    "wof:name":"J Asselin & Assoc",
    "wof:placetype":"venue"
},
  "geometry": {"coordinates":[-75.692284,45.418137],"type":"Point"}
}