{
  "type": "Feature",
  "properties": {
    "addr:full":"218 Rang Charlotte Saint-Liboire QC J0H 1R0",
    "addr:housenumber":"218",
    "addr:postcode":"j0h 1r0",
    "addr:street":"Rang Charlotte",
    "iso:country":"CA",
    "sg:address":"218 Rang Charlotte",
    "sg:city":"Saint-Liboire",
    "sg:classifiers":[
        {
            "category":"Farming",
            "subcategory":"Livestock Farm",
            "type":"Manufacturing & Wholesale Goods"
        }
    ],
    "sg:phone":"+1 450 793 2827",
    "sg:postcode":"J0H 1R0",
    "sg:province":"QC",
    "sg:tags":[
        "circus",
        "broker",
        "animal",
        "dealer"
    ],
    "wof:name":"Trudeau International",
    "wof:placetype":"venue"
},
  "geometry": {"coordinates":[-72.730476,45.666832],"type":"Point"}
}