{
  "type": "Feature",
  "properties": {
    "addr:full":"6509 Sooke Rd Sooke BC V0S 1N0",
    "addr:housenumber":"6509",
    "addr:postcode":"v0s 1n0",
    "addr:street":"Sooke Rd",
    "iso:country":"CA",
    "sg:address":"6509 Sooke Rd",
    "sg:city":"Sooke",
    "sg:classifiers":[
        {
            "category":"Retail",
            "subcategory":"Repair Shop",
            "type":"Services"
        }
    ],
    "sg:phone":"+1 250 642 5512",
    "sg:postcode":"V0S 1N0",
    "sg:province":"BC",
    "sg:tags":[
        "welding"
    ],
    "wof:name":"Razu Welding",
    "wof:placetype":"venue"
},
  "geometry": {"coordinates":[-123.712898,48.380539],"type":"Point"}
}