{
  "type": "Feature",
  "properties": {
    "addr:full":"1523 Birchmount Rd Scarborough ON M1P 2H2",
    "addr:housenumber":"1523",
    "addr:postcode":"m1p 2h2",
    "addr:street":"Birchmount Rd",
    "iso:country":"CA",
    "sg:address":"1523 Birchmount Rd",
    "sg:city":"Scarborough",
    "sg:classifiers":[
        {
            "category":"Restaurant",
            "type":"Food & Drink"
        }
    ],
    "sg:phone":"+1 416 751 1079",
    "sg:postcode":"M1P 2H2",
    "sg:province":"ON",
    "wof:name":"Mr Zee's Bar & Eatery",
    "wof:placetype":"venue"
},
  "geometry": {"coordinates":[-79.289513,43.75909],"type":"Point"}
}