{
  "type": "Feature",
  "properties": {
    "addr:full":"North York ON M2R 3T5",
    "addr:postcode":"m2r 3t5",
    "iso:country":"CA",
    "sg:city":"North York",
    "sg:classifiers":[
        {
            "category":"Health Services",
            "subcategory":"Doctor",
            "type":"Services"
        }
    ],
    "sg:phone":"+1 416 225 0095",
    "sg:postcode":"M2R 3T5",
    "sg:province":"ON",
    "sg:tags":[
        "physician",
        "surgeon"
    ],
    "wof:name":"Gyenes, T MD",
    "wof:placetype":"venue"
},
  "geometry": {"coordinates":[-79.4448394775,43.7818756104],"type":"Point"}
}