{
  "type": "Feature",
  "properties": {
    "addr:full":"7140 Russell Ave Burnaby BC V5J 4R9",
    "addr:housenumber":"7140",
    "addr:postcode":"v5j 4r9",
    "addr:street":"Russell Ave",
    "iso:country":"CA",
    "sg:address":"7140 Russell Ave",
    "sg:city":"Burnaby",
    "sg:classifiers":[
        {
            "category":"Retail",
            "subcategory":"Auto Repair",
            "type":"Services"
        }
    ],
    "sg:phone":"+1 604 433 4717",
    "sg:postcode":"V5J 4R9",
    "sg:province":"BC",
    "sg:tags":[
        "automobile",
        "differential",
        "parts",
        "supply"
    ],
    "wof:name":"Iwe Rear Ends Only Ltd",
    "wof:placetype":"venue"
},
  "geometry": {"coordinates":[-122.978721619,49.2190933228],"type":"Point"}
}