{
  "type": "Feature",
  "properties": {
    "addr:full":"15 Stavebank Rd S Mississauga ON L5G 2T2",
    "addr:housenumber":"15",
    "addr:postcode":"l5g 2t2",
    "addr:street":"Stavebank Rd S",
    "iso:country":"CA",
    "sg:address":"15 Stavebank Rd S",
    "sg:city":"Mississauga",
    "sg:classifiers":[
        {
            "category":"Restaurant",
            "type":"Food & Drink"
        }
    ],
    "sg:phone":"+1 905 891 6225",
    "sg:postcode":"L5G 2T2",
    "sg:province":"ON",
    "wof:name":"Breakwater Fine Dining",
    "wof:placetype":"venue"
},
  "geometry": {"coordinates":[-79.5840682983,43.5512008667],"type":"Point"}
}