{
  "type": "Feature",
  "properties": {
    "addr:full":"110 Rue DE LA Montagne Charlesbourg QC G2M 1C8",
    "addr:housenumber":"110",
    "addr:postcode":"g2m 1c8",
    "addr:street":"Rue De La Montagne",
    "iso:country":"CA",
    "sg:address":"110 Rue DE LA Montagne",
    "sg:city":"Charlesbourg",
    "sg:classifiers":[
        {
            "category":"Professional",
            "subcategory":"Business Services",
            "type":"Services"
        }
    ],
    "sg:phone":"+1 418 849 3146",
    "sg:postcode":"G2M 1C8",
    "sg:province":"QC",
    "wof:name":"Conseil Jac",
    "wof:placetype":"venue"
},
  "geometry": {"coordinates":[-71.269699,46.861462],"type":"Point"}
}