{
  "type": "Feature",
  "properties": {
    "iso:country":"CA",
    "sg:address":"85 Howard Pl",
    "sg:city":"Kitchener",
    "sg:classifiers":[
        {
            "category":"Building & Trades",
            "subcategory":"Construction",
            "type":"Services"
        }
    ],
    "sg:phone":"+1 519 576 5526",
    "sg:postcode":"N2K 2Z4",
    "sg:province":"ON",
    "sg:tags":[
        "retaining",
        "wall",
        "stone"
    ],
    "wof:name":"Envirobond Products Corp",
    "wof:placetype":"venue"
},
  "geometry": {"coordinates":[-80.464478,43.478924],"type":"Point"}
}