{
  "type": "Feature",
  "properties": {
    "addr:full":"1193 St Clair Ave W Toronto ON M6E 1B5",
    "addr:housenumber":"1193",
    "addr:postcode":"m6e 1b5",
    "addr:street":"St Clair Ave W",
    "iso:country":"CA",
    "sg:address":"1193 St Clair Ave W",
    "sg:city":"Toronto",
    "sg:classifiers":[
        {
            "category":"Restaurant",
            "type":"Food & Drink"
        }
    ],
    "sg:phone":"+1 416 656 2928",
    "sg:postcode":"M6E 1B5",
    "sg:province":"ON",
    "sg:tags":[
        "caterer"
    ],
    "wof:name":"Very Good Food",
    "wof:placetype":"venue"
},
  "geometry": {"coordinates":[-79.4439086914,43.6776123047],"type":"Point"}
}