{
  "type": "Feature",
  "properties": {
    "addr:full":"1253 Wyandotte St E Windsor ON N9A 3K6",
    "addr:housenumber":"1253",
    "addr:postcode":"n9a 3k6",
    "addr:street":"Wyandotte St E",
    "iso:country":"CA",
    "sg:address":"1253 Wyandotte St E",
    "sg:city":"Windsor",
    "sg:classifiers":[
        {
            "category":"Organizations",
            "subcategory":"Professional Association",
            "type":"Services"
        }
    ],
    "sg:phone":"+1 519 973 0087",
    "sg:postcode":"N9A 3K6",
    "sg:province":"ON",
    "sg:tags":[
        "club"
    ],
    "wof:name":"French Canadian Club",
    "wof:placetype":"venue"
},
  "geometry": {"coordinates":[-83.019463,42.32016],"type":"Point"}
}