{
  "type": "Feature",
  "properties": {
    "addr:full":"Rama ON L0K 1T0",
    "addr:postcode":"l0k 1t0",
    "iso:country":"CA",
    "sg:city":"Rama",
    "sg:classifiers":[
        {
            "category":"Recreation",
            "subcategory":"Marina",
            "type":"Entertainment"
        }
    ],
    "sg:phone":"+1 705 326 5855",
    "sg:postcode":"L0K 1T0",
    "sg:province":"ON",
    "wof:name":"Ojibway Bay Marina",
    "wof:placetype":"venue"
},
  "geometry": {"coordinates":[-79.3498764038,44.6895599365],"type":"Point"}
}