{
  "type": "Feature",
  "properties": {
    "addr:full":"9396 Av Royale Sainte-Anne-DE-Beaupre QC G0A 3C0",
    "addr:housenumber":"9396",
    "addr:postcode":"g0a 3c0",
    "addr:street":"Av Royale",
    "iso:country":"CA",
    "sg:address":"9396 Av Royale",
    "sg:city":"Sainte-Anne-DE-Beaupre",
    "sg:classifiers":[
        {
            "category":"Retail",
            "subcategory":"Auto Repair",
            "type":"Services"
        }
    ],
    "sg:phone":"+1 418 827 3697",
    "sg:postcode":"G0A 3C0",
    "sg:province":"QC",
    "sg:tags":[
        "body",
        "automobile",
        "painting"
    ],
    "wof:name":"Fix Auto Ste-Anne DE Beaupre",
    "wof:placetype":"venue"
},
  "geometry": {"coordinates":[-70.9447174072,47.0169143677],"type":"Point"}
}