{
  "type": "Feature",
  "properties": {
    "addr:full":"141 Frecker Dr St. John's NL A1E 4W1",
    "addr:housenumber":"141",
    "addr:postcode":"a1e 4w1",
    "addr:street":"Frecker Dr",
    "iso:country":"CA",
    "sg:address":"141 Frecker Dr",
    "sg:city":"St. John's",
    "sg:classifiers":[
        {
            "category":"Organizations",
            "subcategory":"Religious Organization",
            "type":"Services"
        }
    ],
    "sg:phone":"+1 709 745 2871",
    "sg:postcode":"A1E 4W1",
    "sg:province":"NL",
    "sg:tags":[
        "church"
    ],
    "wof:name":"Cowan Hgts United Church",
    "wof:placetype":"venue"
},
  "geometry": {"coordinates":[-52.7663345337,47.5317573547],"type":"Point"}
}