{
  "type": "Feature",
  "properties": {
    "addr:full":"Port Alberni BC V9Y 1T7",
    "addr:postcode":"v9y 1t7",
    "iso:country":"CA",
    "sg:city":"Port Alberni",
    "sg:classifiers":[
        {
            "category":"Shopping",
            "type":"Retail Goods"
        }
    ],
    "sg:phone":"+1 250 724 5999",
    "sg:postcode":"V9Y 1T7",
    "sg:province":"BC",
    "sg:tags":[
        "picture",
        "frame"
    ],
    "wof:name":"Clock Tower Gallery Ltd",
    "wof:placetype":"venue"
},
  "geometry": {"coordinates":[-124.813889,49.234463],"type":"Point"}
}