{
  "type": "Feature",
  "properties": {
    "iso:country":"CA",
    "sg:address":"763 Rue Jean-Talon O",
    "sg:city":"Montreal",
    "sg:classifiers":[
        {
            "category":"Personal",
            "type":"Services"
        }
    ],
    "sg:phone":"+1 514 272 8469",
    "sg:postcode":"H3N 1S3",
    "sg:province":"QC",
    "sg:tags":[
        "electrolysis"
    ],
    "wof:name":"Hryssi Anyssia Aesthetics Elec",
    "wof:placetype":"venue"
},
  "geometry": {"coordinates":[-73.613441,45.540501],"type":"Point"}
}