{
  "type": "Feature",
  "properties": {
    "addr:full":"763 Rue Jean-Talon O Montreal QC H3N 1S3",
    "addr:housenumber":"763",
    "addr:postcode":"h3n 1s3",
    "addr:street":"Rue Jean-Talon O",
    "iso:country":"CA",
    "sg:address":"763 Rue Jean-Talon O",
    "sg:city":"Montreal",
    "sg:classifiers":[
        {
            "category":"Personal",
            "type":"Services"
        }
    ],
    "sg:phone":"+1 514 272 8469",
    "sg:postcode":"H3N 1S3",
    "sg:province":"QC",
    "sg:tags":[
        "electrolysis"
    ],
    "wof:name":"Hryssi Anyssia Aesthetics Elec",
    "wof:placetype":"venue"
},
  "geometry": {"coordinates":[-73.61344099999999,45.540501],"type":"Point"}
}