{
  "type": "Feature",
  "properties": {
    "addr:full":"3281 Yonge St Toronto ON M4N 2L8",
    "addr:housenumber":"3281",
    "addr:postcode":"m4n 2l8",
    "addr:street":"Yonge St",
    "iso:country":"CA",
    "sg:address":"3281 Yonge St",
    "sg:city":"Toronto",
    "sg:classifiers":[
        {
            "category":"Personal",
            "subcategory":"Beauty Salon",
            "type":"Services"
        }
    ],
    "sg:phone":"+1 416 932 2445",
    "sg:postcode":"M4N 2L8",
    "sg:province":"ON",
    "sg:tags":[
        "school",
        "day"
    ],
    "wof:name":"Beauty Exchange Inc",
    "wof:placetype":"venue"
},
  "geometry": {"coordinates":[-79.40323600000001,43.72974],"type":"Point"}
}