{
  "type": "Feature",
  "properties": {
    "addr:full":"4235 Sheppard Ave E Scarborough ON M1S 1T7",
    "addr:housenumber":"4235",
    "addr:postcode":"m1s 1t7",
    "addr:street":"Sheppard Ave E",
    "iso:country":"CA",
    "sg:address":"4235 Sheppard Ave E",
    "sg:city":"Scarborough",
    "sg:classifiers":[
        {
            "category":"Building & Trades",
            "subcategory":"Plumbing",
            "type":"Services"
        }
    ],
    "sg:phone":"+1 416 298 6478",
    "sg:postcode":"M1S 1T7",
    "sg:province":"ON",
    "sg:tags":[
        "contractor"
    ],
    "wof:name":"Henry Vankrieken Contracting",
    "wof:placetype":"venue"
},
  "geometry": {"coordinates":[-79.277626,43.785408],"type":"Point"}
}