{
  "type": "Feature",
  "properties": {
    "addr:full":"1279 Marie-Anne St E, Montreal, QC H2J 2C1, Canada",
    "iso:country":"CA",
    "name:eng_x_preferred":[
        "Le Loup Blue"
    ],
    "wof:name":"Le Loup Blue",
    "wof:placetype":"venue"
},
  "geometry": {"coordinates":[-73.57535900000001,45.528746],"type":"Point"}
}