{
  "type": "Feature",
  "properties": {
    "addr:full":"3369 Bloor St W Etobicoke ON M8X 1G2",
    "addr:housenumber":"3369",
    "addr:postcode":"m8x 1g2",
    "addr:street":"Bloor St W",
    "iso:country":"CA",
    "sg:address":"3369 Bloor St W",
    "sg:city":"Etobicoke",
    "sg:classifiers":[
        {
            "category":"Restaurant",
            "type":"Food & Drink"
        }
    ],
    "sg:phone":"+1 416 236 7832",
    "sg:postcode":"M8X 1G2",
    "sg:province":"ON",
    "wof:name":"Slip Mahoney's Bar & Grill",
    "wof:placetype":"venue"
},
  "geometry": {"coordinates":[-79.52269,43.644672],"type":"Point"}
}