{
  "type": "Feature",
  "properties": {
    "addr:full":"RR 1 Sebringville ON N0K 1X0",
    "addr:postcode":"n0k 1x0",
    "addr:street":"Rr 1",
    "iso:country":"CA",
    "sg:address":"RR 1",
    "sg:city":"Sebringville",
    "sg:classifiers":[
        {
            "category":"Building & Trades",
            "subcategory":"Construction",
            "type":"Services"
        }
    ],
    "sg:phone":"+1 519 273 1900",
    "sg:postcode":"N0K 1X0",
    "sg:province":"ON",
    "sg:tags":[
        "general",
        "contractor"
    ],
    "wof:name":"Culliton Construction",
    "wof:placetype":"venue"
},
  "geometry": {"coordinates":[-81.0568161011,43.4051551819],"type":"Point"}
}