{
  "type": "Feature",
  "properties": {
    "addr:full":"829 Ch Du Lac-Meech Chelsea QC J9B 1H9",
    "addr:housenumber":"829",
    "addr:postcode":"qc j9b 1h9",
    "addr:street":"Ch Du Lac-Meech",
    "iso:country":"CA",
    "sg:address":"829 Ch Du Lac-Meech",
    "sg:city":"Chelsea",
    "sg:classifiers":[
        {
            "category":"Professional",
            "subcategory":"Art Services",
            "type":"Services"
        }
    ],
    "sg:phone":"+1 819 827 1009",
    "sg:postcode":"J9B 1H9",
    "sg:province":"QC",
    "sg:tags":[
        "photographer"
    ],
    "wof:name":"William P Mc Elligott Photo",
    "wof:placetype":"venue"
},
  "geometry": {"coordinates":[-75.89027400000001,45.533241],"type":"Point"}
}