{
  "type": "Feature",
  "properties": {
    "iso:country":"CA",
    "sg:city":"Gracefield",
    "sg:classifiers":[
        {
            "category":"Shopping",
            "subcategory":"Pharmacy",
            "type":"Retail Goods"
        }
    ],
    "sg:phone":"+1 819 463 2552",
    "sg:postcode":"J0X 1W0",
    "sg:province":"QC",
    "wof:name":"Pharmacie Brossard Delombaerde",
    "wof:placetype":"venue"
},
  "geometry": {"coordinates":[-76.0441360474,46.09765625],"type":"Point"}
}