{
  "type": "Feature",
  "properties": {
    "addr:full":"489 College St Toronto ON M6G 1A5",
    "addr:housenumber":"489",
    "addr:postcode":"m6g 1a5",
    "addr:street":"College St",
    "iso:country":"CA",
    "sg:address":"489 College St",
    "sg:city":"Toronto",
    "sg:classifiers":[
        {
            "category":"Bars & Pubs",
            "type":"Food & Drink"
        }
    ],
    "sg:phone":"+1 416 927 7774",
    "sg:postcode":"M6G 1A5",
    "sg:province":"ON",
    "sg:tags":[
        "lounge",
        "cocktail"
    ],
    "wof:name":"Ciao Edie",
    "wof:placetype":"venue"
},
  "geometry": {"coordinates":[-79.4093551636,43.656036377],"type":"Point"}
}