{
  "type": "Feature",
  "properties": {
    "addr:full":"528 Boul L'Assomption Repentigny QC J6A 6S3",
    "addr:housenumber":"528",
    "addr:postcode":"j6a 6s3",
    "addr:street":"Boul L'Assomption",
    "iso:country":"CA",
    "sg:address":"528 Boul L'Assomption",
    "sg:city":"Repentigny",
    "sg:classifiers":[
        {
            "category":"Education",
            "subcategory":"Special Training",
            "type":"Public Place"
        }
    ],
    "sg:phone":"+1 450 581 8979",
    "sg:postcode":"J6A 6S3",
    "sg:province":"QC",
    "sg:tags":[
        "instruction",
        "music"
    ],
    "wof:name":"Studio DE Musique Dm Drouin",
    "wof:placetype":"venue"
},
  "geometry": {"coordinates":[-73.444061,45.75544],"type":"Point"}
}