{
  "type": "Feature",
  "properties": {
    "addr:full":"1375 Southdown Rd Mississauga ON L5J 2Z1",
    "addr:housenumber":"1375",
    "addr:postcode":"l5j 2z1",
    "addr:street":"Southdown Rd",
    "iso:country":"CA",
    "sg:address":"1375 Southdown Rd",
    "sg:city":"Mississauga",
    "sg:classifiers":[
        {
            "category":"Shopping",
            "subcategory":"Pharmacy",
            "type":"Retail Goods"
        }
    ],
    "sg:phone":"+1 905 822 1631",
    "sg:postcode":"L5J 2Z1",
    "sg:province":"ON",
    "wof:name":"Pharma Plus Drugmart",
    "wof:placetype":"venue"
},
  "geometry": {"coordinates":[-79.63930499999999,43.518196],"type":"Point"}
}