{
  "type": "Feature",
  "properties": {
    "addr:full":"521 Seventh St New Westminster BC V3M 3L6",
    "addr:housenumber":"521",
    "addr:postcode":"v3m 3l6",
    "addr:street":"Seventh St",
    "iso:country":"CA",
    "sg:address":"521 Seventh St",
    "sg:city":"New Westminster",
    "sg:classifiers":[
        {
            "category":"Food & Beverages",
            "subcategory":"Liquor & Beverages",
            "type":"Retail Goods"
        }
    ],
    "sg:phone":"+1 604 526 9463",
    "sg:postcode":"V3M 3L6",
    "sg:province":"BC",
    "sg:tags":[
        "beer",
        "ale"
    ],
    "wof:name":"Moonrakers Cold Beer & Wine",
    "wof:placetype":"venue"
},
  "geometry": {"coordinates":[-122.920891,49.211838],"type":"Point"}
}