{
  "type": "Feature",
  "properties": {
    "iso:country":"CA",
    "sg:address":"289 Montreal Rd",
    "sg:city":"Vanier",
    "sg:classifiers":[
        {
            "category":"Retail",
            "subcategory":"Laundry & Dry Cleaning",
            "type":"Services"
        }
    ],
    "sg:phone":"+1 613 742 1375",
    "sg:postcode":"K1L 6B8",
    "sg:province":"ON",
    "sg:tags":[
        "cleaners"
    ],
    "wof:name":"Fantastic Tailor & Cleaner",
    "wof:placetype":"venue"
},
  "geometry": {"coordinates":[-75.6593322754,45.4370574951],"type":"Point"}
}