{
  "type": "Feature",
  "properties": {
    "addr:full":"321 St. Paul St W St Catharines ON L2S 2E8",
    "addr:housenumber":"321",
    "addr:postcode":"l2s 2e8",
    "addr:street":"St. Paul St W",
    "iso:country":"CA",
    "sg:address":"321 St. Paul St W",
    "sg:city":"St Catharines",
    "sg:classifiers":[
        {
            "category":"Shopping",
            "subcategory":"Discount & Variety Stores",
            "type":"Retail Goods"
        }
    ],
    "sg:phone":"+1 905 685 8838",
    "sg:postcode":"L2S 2E8",
    "sg:province":"ON",
    "wof:name":"Pony Mini Mart",
    "wof:placetype":"venue"
},
  "geometry": {"coordinates":[-79.26895141599999,43.1431884766],"type":"Point"}
}