{
  "type": "Feature",
  "properties": {
    "iso:country":"CA",
    "sg:address":"7515 Forest Glade Dr",
    "sg:city":"Windsor",
    "sg:classifiers":[
        {
            "category":"Professional",
            "subcategory":"Advertising",
            "type":"Services"
        }
    ],
    "sg:phone":"+1 519 948 4139",
    "sg:postcode":"N8T 3P5",
    "sg:province":"ON",
    "sg:tags":[
        "newspaper"
    ],
    "wof:name":"Rempart",
    "wof:placetype":"venue"
},
  "geometry": {"coordinates":[-82.9228057861,42.2997207642],"type":"Point"}
}