{
  "type": "Feature",
  "properties": {
    "addr:full":"838 Rg Du Moulin Sainte-Helene-DE-Kamouraska QC G0L 3J0",
    "addr:housenumber":"838",
    "addr:postcode":"g0l 3j0",
    "addr:street":"Rg Du Moulin Sainte-Helene-De-Kamouraska",
    "iso:country":"CA",
    "sg:address":"838 Rg Du Moulin",
    "sg:city":"Sainte-Helene-DE-Kamouraska",
    "sg:classifiers":[
        {
            "category":"Building & Trades",
            "subcategory":"Electrical",
            "type":"Services"
        }
    ],
    "sg:phone":"+1 418 492 7930",
    "sg:postcode":"G0L 3J0",
    "sg:province":"QC",
    "sg:tags":[
        "electric",
        "contractor"
    ],
    "wof:name":"Denis Ouellet Electrique Ltee",
    "wof:placetype":"venue"
},
  "geometry": {"coordinates":[-69.86264799999999,47.563976],"type":"Point"}
}