{
  "type": "Feature",
  "properties": {
    "addr:full":"6915 Rue Saint-Denis Montreal QC H2S 2S3",
    "addr:housenumber":"6915",
    "addr:postcode":"h2s 2s3",
    "addr:street":"Rue Saint-Denis",
    "iso:country":"CA",
    "sg:address":"6915 Rue Saint-Denis",
    "sg:city":"Montreal",
    "sg:classifiers":[
        {
            "category":"Health Services",
            "subcategory":"Doctor",
            "type":"Services"
        }
    ],
    "sg:phone":"+1 514 277 4107",
    "sg:postcode":"H2S 2S3",
    "sg:province":"QC",
    "sg:tags":[
        "physician",
        "surgeon"
    ],
    "wof:name":"Paquette, Jacques Y MD",
    "wof:placetype":"venue"
},
  "geometry": {"coordinates":[-73.61106872560001,45.5369186401],"type":"Point"}
}