{
  "type": "Feature",
  "properties": {
    "addr:full":"RR 4 Lcd 1 Red Deer AB T4N 5E4",
    "addr:housenumber":"1",
    "addr:postcode":"t4n 5e4",
    "addr:street":"Rr 4 Lcd",
    "iso:country":"CA",
    "sg:address":"RR 4 Lcd 1",
    "sg:city":"Red Deer",
    "sg:classifiers":[
        {
            "category":"Travel",
            "subcategory":"Hotels & Motels",
            "type":"Entertainment"
        }
    ],
    "sg:phone":"+1 403 340 0031",
    "sg:postcode":"T4N 5E4",
    "sg:province":"AB",
    "sg:tags":[
        "breakfast",
        "accommodation",
        "bed"
    ],
    "wof:name":"LA Solitude Bed & Breakfast",
    "wof:placetype":"venue"
},
  "geometry": {"coordinates":[-113.817436,52.262302],"type":"Point"}
}