{
  "type": "Feature",
  "properties": {
    "iso:country":"CA",
    "sg:address":"3255 Ch D'Oka",
    "sg:city":"Sainte-Marthe-Sur-Le-Lac",
    "sg:classifiers":[
        {
            "category":"Retail",
            "subcategory":"Auto Rental",
            "type":"Services"
        }
    ],
    "sg:phone":"+1 450 472 2222",
    "sg:postcode":"J0N 1P0",
    "sg:province":"QC",
    "sg:tags":[
        "renting",
        "automobile",
        "leasing"
    ],
    "wof:name":"Location Poliseno Inc",
    "wof:placetype":"venue"
},
  "geometry": {"coordinates":[-73.99458312989999,45.5016860962],"type":"Point"}
}