{
  "type": "Feature",
  "properties": {
    "addr:full":"386 Rue Principale St-Mathieu QC G0L 3T0",
    "addr:housenumber":"386",
    "addr:postcode":"g0l 3t0",
    "addr:street":"Rue Principale",
    "iso:country":"CA",
    "sg:address":"386 Rue Principale",
    "sg:city":"St-Mathieu",
    "sg:classifiers":[
        {
            "category":"Food & Beverages",
            "subcategory":"Groceries & Convenience Stores",
            "type":"Retail Goods"
        }
    ],
    "sg:phone":"+1 418 738 2033",
    "sg:postcode":"G0L 3T0",
    "sg:province":"QC",
    "sg:tags":[
        "grocer"
    ],
    "wof:name":"Marche DE Chez-Nous",
    "wof:placetype":"venue"
},
  "geometry": {"coordinates":[-68.985206604,48.1843719482],"type":"Point"}
}