{
  "type": "Feature",
  "properties": {
    "addr:full":"Abbotsford BC V2T 6K8",
    "addr:postcode":"v2t 6k8",
    "iso:country":"CA",
    "sg:city":"Abbotsford",
    "sg:classifiers":[
        {
            "category":"Shopping",
            "subcategory":"Computers & Home Electronics",
            "type":"Retail Goods"
        }
    ],
    "sg:phone":"+1 604 854 8718",
    "sg:postcode":"V2T 6K8",
    "sg:province":"BC",
    "sg:tags":[
        "equipment",
        "dealer"
    ],
    "wof:name":"First Choice Computers",
    "wof:placetype":"venue"
},
  "geometry": {"coordinates":[-122.356239,49.045761],"type":"Point"}
}