{
  "type": "Feature",
  "properties": {
    "addr:full":"Farm Burstall SK S0N 0H0",
    "addr:postcode":"s0n 0h0",
    "iso:country":"CA",
    "sg:address":"Farm",
    "sg:city":"Burstall",
    "sg:classifiers":[
        {
            "category":"Mining & Drilling",
            "type":"Manufacturing & Wholesale Goods"
        }
    ],
    "sg:phone":"+1 306 679 2049",
    "sg:postcode":"S0N 0H0",
    "sg:province":"SK",
    "sg:tags":[
        "company",
        "oil"
    ],
    "wof:name":"Eog Resources",
    "wof:placetype":"venue"
},
  "geometry": {"coordinates":[-109.90460967999999,50.659614563],"type":"Point"}
}