{
  "type": "Feature",
  "properties": {
    "addr:full":"554 Waterloo St London ON N6B 2P9",
    "addr:housenumber":"554",
    "addr:postcode":"n6b 2p9",
    "addr:street":"Waterloo St",
    "iso:country":"CA",
    "sg:address":"554 Waterloo St",
    "sg:city":"London",
    "sg:classifiers":[
        {
            "category":"Professional",
            "subcategory":"Management & Consulting",
            "type":"Services"
        }
    ],
    "sg:phone":"+1 519 432 1634",
    "sg:postcode":"N6B 2P9",
    "sg:province":"ON",
    "sg:tags":[
        "marketing",
        "advertising",
        "consultant"
    ],
    "wof:name":"Link Advertising Inc",
    "wof:placetype":"venue"
},
  "geometry": {"coordinates":[-81.2447280884,42.990524292],"type":"Point"}
}