{
  "type": "Feature",
  "properties": {
    "iso:country":"CA",
    "sg:address":"205 Boul Cure-Labelle",
    "sg:city":"Sainte-Rose",
    "sg:classifiers":[
        {
            "category":"Professional",
            "subcategory":"Engineering",
            "type":"Services"
        }
    ],
    "sg:phone":"+1 450 628 0555",
    "sg:postcode":"H7L 2Z9",
    "sg:province":"QC",
    "sg:tags":[
        "engineer"
    ],
    "wof:name":"Blondin Fortin Inc",
    "wof:placetype":"venue"
},
  "geometry": {"coordinates":[-73.7903671265,45.6036376953],"type":"Point"}
}