{
  "type": "Feature",
  "properties": {
    "addr:full":"Fort Erie ON L2A 1R9",
    "addr:postcode":"l2a 1r9",
    "iso:country":"CA",
    "sg:city":"Fort Erie",
    "sg:classifiers":[
        {
            "category":"Professional",
            "subcategory":"Accounting & Tax Preparation",
            "type":"Services"
        }
    ],
    "sg:phone":"+1 905 871 8530",
    "sg:postcode":"L2A 1R9",
    "sg:province":"ON",
    "sg:tags":[
        "return",
        "filing"
    ],
    "wof:name":"Garrison Tax Svc",
    "wof:placetype":"venue"
},
  "geometry": {"coordinates":[-78.929092,42.907852],"type":"Point"}
}