{
  "type": "Feature",
  "properties": {
    "addr:full":"3 Bannock St Stony Rapids SK S0J 2R0",
    "addr:housenumber":"3",
    "addr:postcode":"s0j 2r0",
    "addr:street":"Bannock St",
    "iso:country":"CA",
    "sg:address":"3 Bannock St",
    "sg:city":"Stony Rapids",
    "sg:classifiers":[
        {
            "category":"Retail",
            "subcategory":"Auto Repair",
            "type":"Services"
        }
    ],
    "sg:phone":"+1 306 439 2056",
    "sg:postcode":"S0J 2R0",
    "sg:province":"SK",
    "sg:tags":[
        "repairing",
        "automobile",
        "fur"
    ],
    "wof:name":"Stony Rapids Snowmobile Ctr",
    "wof:placetype":"venue"
},
  "geometry": {"coordinates":[-105.835953,59.25782],"type":"Point"}
}