{
  "type": "Feature",
  "properties": {
    "addr:full":"108 1st Ave W Frontier SK S0N 0W0",
    "addr:housenumber":"108",
    "addr:postcode":"s0n 0w0",
    "addr:street":"1St Ave W Frontier",
    "iso:country":"CA",
    "sg:address":"108 1st Ave W",
    "sg:city":"Frontier",
    "sg:classifiers":[
        {
            "category":"Government",
            "subcategory":"Office",
            "type":"Public Place"
        }
    ],
    "sg:phone":"+1 306 296 2030",
    "sg:postcode":"S0N 0W0",
    "sg:province":"SK",
    "sg:tags":[
        "municipality"
    ],
    "wof:name":"R M of Frontier",
    "wof:placetype":"venue"
},
  "geometry": {"coordinates":[-108.561851502,49.2041664124],"type":"Point"}
}