{
  "type": "Feature",
  "properties": {
    "addr:full":"St Paul AB T0A 3A3",
    "addr:postcode":"t0a 3a3",
    "iso:country":"CA",
    "sg:city":"St Paul",
    "sg:classifiers":[
        {
            "category":"Social Services",
            "subcategory":"Adult Care",
            "type":"Services"
        }
    ],
    "sg:phone":"+1 780 645 5366",
    "sg:postcode":"T0A 3A3",
    "sg:province":"AB",
    "sg:tags":[
        "senior",
        "housing",
        "citizen"
    ],
    "wof:name":"Heritage Homes",
    "wof:placetype":"venue"
},
  "geometry": {"coordinates":[-111.288918,53.986614],"type":"Point"}
}