{
  "type": "Feature",
  "properties": {
    "iso:country":"CA",
    "sg:address":"2374 Carling Ave",
    "sg:city":"Ottawa",
    "sg:classifiers":[
        {
            "category":"Health Services",
            "subcategory":"Nursing And Care Facility",
            "type":"Services"
        }
    ],
    "sg:phone":"+1 613 820 7333",
    "sg:postcode":"K2B 7G5",
    "sg:province":"ON",
    "sg:tags":[
        "home",
        "retirement",
        "community"
    ],
    "wof:name":"Central Park Lodges",
    "wof:placetype":"venue"
},
  "geometry": {"coordinates":[-75.7784118652,45.3665733337],"type":"Point"}
}