{
  "type": "Feature",
  "properties": {
    "addr:full":"9 1st St Wabush NL A0R 1B0",
    "addr:housenumber":"9",
    "addr:postcode":"a0r 1b0",
    "addr:street":"1St St",
    "iso:country":"CA",
    "sg:address":"9 1st St",
    "sg:city":"Wabush",
    "sg:classifiers":[
        {
            "category":"Building & Trades",
            "subcategory":"Plumbing",
            "type":"Services"
        }
    ],
    "sg:phone":"+1 709 282 5088",
    "sg:postcode":"A0R 1B0",
    "sg:province":"NL",
    "sg:tags":[
        "conditioning",
        "air",
        "refrigeration",
        "system",
        "contractor"
    ],
    "wof:name":"Perma Refrigeration Ltd",
    "wof:placetype":"venue"
},
  "geometry": {"coordinates":[-66.868637085,52.8973655701],"type":"Point"}
}