{
  "type": "Feature",
  "properties": {
    "addr:full":"21 Dundurn Cres York ON M6C 1H4",
    "addr:housenumber":"21",
    "addr:postcode":"m6c 1h4",
    "addr:street":"Dundurn Cres",
    "iso:country":"CA",
    "sg:address":"21 Dundurn Cres",
    "sg:city":"York",
    "sg:classifiers":[
        {
            "category":"Professional",
            "subcategory":"Computer Services",
            "type":"Services"
        }
    ],
    "sg:phone":"+1 416 657 1662",
    "sg:postcode":"M6C 1H4",
    "sg:province":"ON",
    "sg:tags":[
        "consultant"
    ],
    "wof:name":"Dundurn Marketing Inc",
    "wof:placetype":"venue"
},
  "geometry": {"coordinates":[-79.4328460693,43.6832237244],"type":"Point"}
}