{
  "type": "Feature",
  "properties": {
    "addr:full":"81 Ranleigh Ave Toronto ON M4N 1X2",
    "addr:housenumber":"81",
    "addr:postcode":"m4n 1x2",
    "addr:street":"Ranleigh Ave",
    "iso:country":"CA",
    "sg:address":"81 Ranleigh Ave",
    "sg:city":"Toronto",
    "sg:classifiers":[
        {
            "category":"Social Services",
            "subcategory":"Child Care",
            "type":"Services"
        }
    ],
    "sg:phone":"+1 416 487 2373",
    "sg:postcode":"M4N 1X2",
    "sg:province":"ON",
    "wof:name":"Ranleigh Rascals Daycare",
    "wof:placetype":"venue"
},
  "geometry": {"coordinates":[-79.400284,43.727966],"type":"Point"}
}