{
  "type": "Feature",
  "properties": {
    "addr:full":"Burnaby BC V5H 4K7",
    "addr:postcode":"v5h 4k7",
    "iso:country":"CA",
    "sg:city":"Burnaby",
    "sg:classifiers":[
        {
            "category":"Health Services",
            "subcategory":"Doctor",
            "type":"Services"
        }
    ],
    "sg:phone":"+1 604 436 4414",
    "sg:postcode":"V5H 4K7",
    "sg:province":"BC",
    "sg:tags":[
        "dentist"
    ],
    "wof:name":"Lear, Clement S C DDS",
    "wof:placetype":"venue"
},
  "geometry": {"coordinates":[-122.992835998,49.2261428833],"type":"Point"}
}