{
  "type": "Feature",
  "properties": {
    "addr:full":"1644 3rd Ave W Vancouver BC V6J 1K2",
    "addr:housenumber":"1644",
    "addr:postcode":"v6j 1k2",
    "addr:street":"3Rd Ave W",
    "iso:country":"CA",
    "sg:address":"1644 3rd Ave W",
    "sg:city":"Vancouver",
    "sg:classifiers":[
        {
            "category":"Communications",
            "subcategory":"Film & Video Production",
            "type":"Services"
        }
    ],
    "sg:phone":"+1 604 731 2490",
    "sg:postcode":"V6J 1K2",
    "sg:province":"BC",
    "sg:tags":[
        "multimedia"
    ],
    "wof:name":"Second Stage Management Svc",
    "wof:placetype":"venue"
},
  "geometry": {"coordinates":[-123.141937,49.268715],"type":"Point"}
}