{
  "type": "Feature",
  "properties": {
    "addr:full":"Belleville ON K8N 5K6",
    "addr:postcode":"k8n 5k6",
    "iso:country":"CA",
    "sg:city":"Belleville",
    "sg:classifiers":[
        {
            "category":"Professional",
            "subcategory":"Lawyer & Legal Services",
            "type":"Services"
        }
    ],
    "sg:phone":"+1 613 966 2620",
    "sg:postcode":"K8N 5K6",
    "sg:province":"ON",
    "sg:tags":[
        "attorney"
    ],
    "wof:name":"Sullivan, Ian B",
    "wof:placetype":"venue"
},
  "geometry": {"coordinates":[-77.370071,44.162598],"type":"Point"}
}