{
  "type": "Feature",
  "properties": {
    "addr:full":"1647 Rue Sainte-Catherine O Montreal QC H3H 1L9",
    "addr:housenumber":"1647",
    "addr:postcode":"h3h 1l9",
    "addr:street":"Rue Sainte-Catherine O",
    "iso:country":"CA",
    "sg:address":"1647 Rue Sainte-Catherine O",
    "sg:city":"Montreal",
    "sg:classifiers":[
        {
            "category":"Professional",
            "subcategory":"Lawyer & Legal Services",
            "type":"Services"
        }
    ],
    "sg:phone":"+1 514 938 9240",
    "sg:postcode":"H3H 1L9",
    "sg:province":"QC",
    "sg:tags":[
        "attorney"
    ],
    "wof:name":"Baer, Warren",
    "wof:placetype":"venue"
},
  "geometry": {"coordinates":[-73.55300099999999,45.522156],"type":"Point"}
}