{
  "type": "Feature",
  "properties": {
    "addr:full":"2095 Tecumseh Rd W Windsor ON N9B 1V8",
    "addr:housenumber":"2095",
    "addr:postcode":"n9b 1v8",
    "addr:street":"Tecumseh Rd W",
    "iso:country":"CA",
    "sg:address":"2095 Tecumseh Rd W",
    "sg:city":"Windsor",
    "sg:classifiers":[
        {
            "category":"Retail",
            "subcategory":"Auto Repair",
            "type":"Services"
        }
    ],
    "sg:phone":"+1 519 258 5711",
    "sg:postcode":"N9B 1V8",
    "sg:province":"ON",
    "sg:tags":[
        "automobile",
        "lubrication"
    ],
    "wof:name":"Mr Lube",
    "wof:placetype":"venue"
},
  "geometry": {"coordinates":[-83.052223,42.29314],"type":"Point"}
}