{
  "type": "Feature",
  "properties": {
    "addr:full":"Lac LA Biche AB T0A 2C0",
    "addr:postcode":"t0a 2c0",
    "iso:country":"CA",
    "sg:city":"Lac LA Biche",
    "sg:classifiers":[
        {
            "category":"Freight",
            "type":"Transportation"
        }
    ],
    "sg:phone":"+1 780 623 2193",
    "sg:postcode":"T0A 2C0",
    "sg:province":"AB",
    "sg:tags":[
        "field",
        "oil",
        "trucking"
    ],
    "wof:name":"Cadieux Brothers Transport",
    "wof:placetype":"venue"
},
  "geometry": {"coordinates":[-111.974457,54.771107],"type":"Point"}
}