{
  "type": "Feature",
  "properties": {
    "addr:full":"200 Edgeley Blvd # 30 Concord ON L4K 3Y8",
    "addr:housenumber":"200",
    "addr:postcode":"l4k 3y8",
    "addr:street":"Edgeley Blvd # 30",
    "iso:country":"CA",
    "sg:address":"200 Edgeley Blvd # 30",
    "sg:city":"Concord",
    "sg:classifiers":[
        {
            "category":"Building & Trades",
            "subcategory":"Construction",
            "type":"Services"
        }
    ],
    "sg:phone":"+1 905 761 0378",
    "sg:postcode":"L4K 3Y8",
    "sg:province":"ON",
    "sg:tags":[
        "dry wall",
        "contractor"
    ],
    "wof:name":"Dixon Drywall",
    "wof:placetype":"venue"
},
  "geometry": {"coordinates":[-79.5332336426,43.7975502014],"type":"Point"}
}