{
  "type": "Feature",
  "properties": {
    "addr:full":"1875 Grant Ave Winnipeg MB R3N 1Z2",
    "addr:housenumber":"1875",
    "addr:postcode":"r3n 1z2",
    "addr:street":"Grant Ave",
    "iso:country":"CA",
    "sg:address":"1875 Grant Ave",
    "sg:city":"Winnipeg",
    "sg:classifiers":[
        {
            "category":"Shopping",
            "subcategory":"Shoes",
            "type":"Retail Goods"
        }
    ],
    "sg:phone":"+1 204 487 7582",
    "sg:postcode":"R3N 1Z2",
    "sg:province":"MB",
    "sg:tags":[
        "sporting"
    ],
    "wof:name":"Running Room Canada Inc",
    "wof:placetype":"venue"
},
  "geometry": {"coordinates":[-97.20444500000001,49.857338],"type":"Point"}
}