{
  "type": "Feature",
  "properties": {
    "iso:country":"CA",
    "sg:address":"1017 Hammond Ave # B",
    "sg:city":"Crossfield",
    "sg:classifiers":[
        {
            "category":"Personal",
            "subcategory":"Beauty Salon",
            "type":"Services"
        }
    ],
    "sg:phone":"+1 403 946 4442",
    "sg:postcode":"T0M 0S0",
    "sg:province":"AB",
    "wof:name":"Hair N More",
    "wof:placetype":"venue"
},
  "geometry": {"coordinates":[-114.028374,51.428257],"type":"Point"}
}