{
  "type": "Feature",
  "properties": {
    "iso:country":"CA",
    "sg:address":"4560 Boul Lasalle",
    "sg:city":"Verdun",
    "sg:classifiers":[
        {
            "category":"Building & Trades",
            "subcategory":"Construction",
            "type":"Services"
        }
    ],
    "sg:phone":"+1 514 766 4706",
    "sg:postcode":"H4G 2B1",
    "sg:province":"QC",
    "sg:tags":[
        "maker",
        "cabinet"
    ],
    "wof:name":"Ebenisterie Serge",
    "wof:placetype":"venue"
},
  "geometry": {"coordinates":[-73.56313323969999,45.4585075378],"type":"Point"}
}