{
  "type": "Feature",
  "properties": {
    "addr:full":"28 Tsse Dufferin Laval QC H7L 2J2",
    "addr:housenumber":"28",
    "addr:postcode":"h7l 2j2",
    "addr:street":"Tsse Dufferin",
    "iso:country":"CA",
    "sg:address":"28 Tsse Dufferin",
    "sg:city":"Laval",
    "sg:classifiers":[
        {
            "category":"Building & Trades",
            "subcategory":"Electrical",
            "type":"Services"
        }
    ],
    "sg:phone":"+1 450 622 3956",
    "sg:postcode":"H7L 2J2",
    "sg:province":"QC",
    "sg:tags":[
        "electric",
        "contractor"
    ],
    "wof:name":"Installations Electriques Jf",
    "wof:placetype":"venue"
},
  "geometry": {"coordinates":[-73.782043,45.626396],"type":"Point"}
}