{
  "type": "Feature",
  "properties": {
    "addr:full":"Gatineau QC J8R 1H2",
    "addr:postcode":"j8r 1h2",
    "iso:country":"CA",
    "sg:city":"Gatineau",
    "sg:classifiers":[
        {
            "category":"Professional",
            "type":"Services"
        }
    ],
    "sg:phone":"+1 819 246 5844",
    "sg:postcode":"J8R 1H2",
    "sg:province":"QC",
    "sg:tags":[
        "mapping",
        "geographer"
    ],
    "wof:name":"Geotech",
    "wof:placetype":"venue"
},
  "geometry": {"coordinates":[-75.71666,45.444679],"type":"Point"}
}