{
  "type": "Feature",
  "properties": {
    "iso:country":"CA",
    "sg:address":"4290 Boul Samson",
    "sg:city":"Laval",
    "sg:classifiers":[
        {
            "category":"Personal",
            "type":"Services"
        }
    ],
    "sg:phone":"+1 450 681 9096",
    "sg:postcode":"H7W 2G9",
    "sg:province":"QC",
    "sg:tags":[
        "genealogist"
    ],
    "wof:name":"Societe D'Histoire Et Geneolog",
    "wof:placetype":"venue"
},
  "geometry": {"coordinates":[-73.751198,45.532726],"type":"Point"}
}