{
  "type": "Feature",
  "properties": {
    "addr:full":"5001 45 Ave Drayton Valley AB T7A 1L1",
    "addr:housenumber":"5001",
    "addr:postcode":"t7a 1l1",
    "addr:street":"45 Ave",
    "iso:country":"CA",
    "sg:address":"5001 45 Ave",
    "sg:city":"Drayton Valley",
    "sg:classifiers":[
        {
            "category":"Retail",
            "subcategory":"Funeral Services",
            "type":"Services"
        }
    ],
    "sg:phone":"+1 780 542 5511",
    "sg:postcode":"T7A 1L1",
    "sg:province":"AB",
    "sg:tags":[
        "director"
    ],
    "wof:name":"Drayton Valley Funeral Chapel",
    "wof:placetype":"venue"
},
  "geometry": {"coordinates":[-114.97686,53.216354],"type":"Point"}
}