{
  "type": "Feature",
  "properties": {
    "addr:full":"1096 10th Ave W Vancouver BC V6H 1H8",
    "addr:housenumber":"1096",
    "addr:postcode":"v6h 1h8",
    "addr:street":"10Th Ave W",
    "iso:country":"CA",
    "sg:address":"1096 10th Ave W",
    "sg:city":"Vancouver",
    "sg:classifiers":[
        {
            "category":"Professional",
            "subcategory":"Engineering",
            "type":"Services"
        }
    ],
    "sg:phone":"+1 604 734 7900",
    "sg:postcode":"V6H 1H8",
    "sg:province":"BC",
    "sg:tags":[
        "engineer"
    ],
    "wof:name":"Rar Consultants Ltd",
    "wof:placetype":"venue"
},
  "geometry": {"coordinates":[-123.128754,49.262341],"type":"Point"}
}