{
  "type": "Feature",
  "properties": {
    "addr:full":"79 Riverside Dr Fredericton NB E3A 3X9",
    "addr:housenumber":"79",
    "addr:postcode":"e3a 3x9",
    "addr:street":"Riverside Dr",
    "iso:country":"CA",
    "sg:address":"79 Riverside Dr",
    "sg:city":"Fredericton",
    "sg:classifiers":[
        {
            "category":"Retail",
            "subcategory":"Laundry & Dry Cleaning",
            "type":"Services"
        }
    ],
    "sg:phone":"+1 506 472 4429",
    "sg:postcode":"E3A 3X9",
    "sg:province":"NB",
    "wof:name":"Riverside Quik Mart & Lndrmt",
    "wof:placetype":"venue"
},
  "geometry": {"coordinates":[-66.622765,45.950081],"type":"Point"}
}