{
  "type": "Feature",
  "properties": {
    "addr:full":"Inverness NS B0E 1N0",
    "addr:postcode":"b0e 1n0",
    "iso:country":"CA",
    "sg:city":"Inverness",
    "sg:classifiers":[
        {
            "category":"Organizations",
            "subcategory":"Religious Organization",
            "type":"Services"
        }
    ],
    "sg:phone":"+1 902 258 2361",
    "sg:postcode":"B0E 1N0",
    "sg:province":"NS",
    "sg:tags":[
        "church"
    ],
    "wof:name":"St Margarets Parish",
    "wof:placetype":"venue"
},
  "geometry": {"coordinates":[-61.529888,46.006577],"type":"Point"}
}