{
  "type": "Feature",
  "properties": {
    "addr:full":"6112 Quinpool Rd Halifax NS B3L 1A3",
    "addr:housenumber":"6112",
    "addr:postcode":"b3l 1a3",
    "addr:street":"Quinpool Rd",
    "iso:country":"CA",
    "sg:address":"6112 Quinpool Rd",
    "sg:city":"Halifax",
    "sg:classifiers":[
        {
            "category":"Restaurant",
            "type":"Food & Drink"
        }
    ],
    "sg:phone":"+1 902 420 9999",
    "sg:postcode":"B3L 1A3",
    "sg:province":"NS",
    "sg:tags":[
        "pizza"
    ],
    "wof:name":"Domino's Pizza",
    "wof:placetype":"venue"
},
  "geometry": {"coordinates":[-63.5936317444,44.6462173462],"type":"Point"}
}