{
  "type": "Feature",
  "properties": {
    "addr:full":"Toronto ON M5S 3A5",
    "addr:postcode":"m5s 3a5",
    "iso:country":"CA",
    "sg:city":"Toronto",
    "sg:classifiers":[
        {
            "category":"Professional",
            "subcategory":"Management & Consulting",
            "type":"Services"
        }
    ],
    "sg:phone":"+1 416 964 6479",
    "sg:postcode":"M5S 3A5",
    "sg:province":"ON",
    "sg:tags":[
        "consultant",
        "business"
    ],
    "wof:name":"Bay Consulting Group",
    "wof:placetype":"venue"
},
  "geometry": {"coordinates":[-79.387703,43.666058],"type":"Point"}
}