{
  "type": "Feature",
  "properties": {
    "addr:full":"Wrentham AB T0K 2P0",
    "addr:postcode":"t0k 2p0",
    "iso:country":"CA",
    "sg:city":"Wrentham",
    "sg:classifiers":[
        {
            "category":"Freight",
            "type":"Transportation"
        }
    ],
    "sg:phone":"+1 403 222 2134",
    "sg:postcode":"T0K 2P0",
    "sg:province":"AB",
    "sg:tags":[
        "field",
        "oil",
        "trucking"
    ],
    "wof:name":"Owen Oil Svc Ltd",
    "wof:placetype":"venue"
},
  "geometry": {"coordinates":[-112.180419922,49.5190162659],"type":"Point"}
}