{
  "type": "Feature",
  "properties": {
    "addr:full":"401 2nd Ave Langham SK S0K 2L0",
    "addr:housenumber":"401",
    "addr:postcode":"s0k 2l0",
    "addr:street":"2Nd Ave",
    "iso:country":"CA",
    "sg:address":"401 2nd Ave",
    "sg:city":"Langham",
    "sg:classifiers":[
        {
            "category":"Farming",
            "subcategory":"Nursery",
            "type":"Manufacturing & Wholesale Goods"
        }
    ],
    "sg:phone":"+1 306 283 4376",
    "sg:postcode":"S0K 2L0",
    "sg:province":"SK",
    "sg:tags":[
        "greenhouse"
    ],
    "wof:name":"Dieter Martin Greenhouse Ltd",
    "wof:placetype":"venue"
},
  "geometry": {"coordinates":[-106.958190918,52.3611793518],"type":"Point"}
}