{
  "type": "Feature",
  "properties": {
    "addr:full":"3459 Highway 35 115 Newcastle ON L1B 1L9",
    "addr:housenumber":"3459;115",
    "addr:postcode":"l1b 1l9",
    "addr:street":"Highway 35",
    "iso:country":"CA",
    "sg:address":"3459 Highway 35 115",
    "sg:city":"Newcastle",
    "sg:classifiers":[
        {
            "category":"Restaurant",
            "type":"Food & Drink"
        }
    ],
    "sg:phone":"+1 905 987 1200",
    "sg:postcode":"L1B 1L9",
    "sg:province":"ON",
    "wof:name":"Harvey's",
    "wof:placetype":"venue"
},
  "geometry": {"coordinates":[-78.60302734379999,43.9428977966],"type":"Point"}
}