{
  "type": "Feature",
  "properties": {
    "addr:full":"102 Saskatchewan Ave E Outlook SK S0L 2N0",
    "addr:housenumber":"102",
    "addr:postcode":"s0l 2n0",
    "addr:street":"Saskatchewan Ave E Outlook",
    "iso:country":"CA",
    "sg:address":"102 Saskatchewan Ave E",
    "sg:city":"Outlook",
    "sg:classifiers":[
        {
            "category":"Food & Beverages",
            "subcategory":"Liquor & Beverages",
            "type":"Retail Goods"
        }
    ],
    "sg:phone":"+1 306 867 5566",
    "sg:postcode":"S0L 2N0",
    "sg:province":"SK",
    "sg:tags":[
        "store"
    ],
    "wof:name":"Liquor Stores",
    "wof:placetype":"venue"
},
  "geometry": {"coordinates":[-107.056961,51.488049],"type":"Point"}
}