{
  "type": "Feature",
  "properties": {
    "iso:country":"CA",
    "sg:address":"89 Lorne Ave E",
    "sg:city":"Stratford",
    "sg:classifiers":[
        {
            "category":"Building & Trades",
            "subcategory":"Construction",
            "type":"Services"
        }
    ],
    "sg:phone":"+1 519 271 1771",
    "sg:postcode":"N5A 6S4",
    "sg:province":"ON",
    "sg:tags":[
        "general",
        "contractor"
    ],
    "wof:name":"Hyde Construction Ltd",
    "wof:placetype":"venue"
},
  "geometry": {"coordinates":[-80.9931335449,43.3543815613],"type":"Point"}
}