{
  "type": "Feature",
  "properties": {
    "addr:full":"341 Marsland Dr Waterloo ON N2J 3Z2",
    "addr:housenumber":"341",
    "addr:postcode":"n2j 3z2",
    "addr:street":"Marsland Dr",
    "iso:country":"CA",
    "sg:address":"341 Marsland Dr",
    "sg:city":"Waterloo",
    "sg:classifiers":[
        {
            "category":"Restaurant",
            "type":"Food & Drink"
        }
    ],
    "sg:phone":"+1 519 886 7777",
    "sg:postcode":"N2J 3Z2",
    "sg:province":"ON",
    "wof:name":"Flying Dog",
    "wof:placetype":"venue"
},
  "geometry": {"coordinates":[-80.518463,43.483234],"type":"Point"}
}