{
  "type": "Feature",
  "properties": {
    "addr:full":"Mont-Brun QC J0Z 2Y0",
    "addr:postcode":"j0z 2y0",
    "iso:country":"CA",
    "sg:city":"Mont-Brun",
    "sg:classifiers":[
        {
            "category":"Home & Garden",
            "subcategory":"Building Materials",
            "type":"Retail Goods"
        }
    ],
    "sg:phone":"+1 819 637 2483",
    "sg:postcode":"J0Z 2Y0",
    "sg:province":"QC",
    "sg:tags":[
        "consultant",
        "instructional"
    ],
    "wof:name":"Boutique DE L'Artisan Decapeur",
    "wof:placetype":"venue"
},
  "geometry": {"coordinates":[-78.714439,48.366615],"type":"Point"}
}