{
  "type": "Feature",
  "properties": {
    "addr:full":"30 Mary St Thamesville ON N0P 2K0",
    "addr:housenumber":"30",
    "addr:postcode":"n0p 2k0",
    "addr:street":"Mary St",
    "iso:country":"CA",
    "sg:address":"30 Mary St",
    "sg:city":"Thamesville",
    "sg:classifiers":[
        {
            "category":"Education",
            "subcategory":"School",
            "type":"Public Place"
        }
    ],
    "sg:phone":"+1 519 692 3908",
    "sg:postcode":"N0P 2K0",
    "sg:province":"ON",
    "wof:name":"Thamesville Area Public School",
    "wof:placetype":"venue"
},
  "geometry": {"coordinates":[-81.9760437012,42.5553855896],"type":"Point"}
}