{
  "type": "Feature",
  "properties": {
    "addr:full":"10009 Superior St Port Franks ON N0M 2L0",
    "addr:housenumber":"10009",
    "addr:postcode":"n0m 2l0",
    "addr:street":"Superior St",
    "iso:country":"CA",
    "sg:address":"10009 Superior St",
    "sg:city":"Port Franks",
    "sg:classifiers":[
        {
            "category":"Recreation",
            "subcategory":"Marina",
            "type":"Entertainment"
        }
    ],
    "sg:phone":"+1 519 243 3900",
    "sg:postcode":"N0M 2L0",
    "sg:province":"ON",
    "wof:name":"Huron Shores Marine Ltd",
    "wof:placetype":"venue"
},
  "geometry": {"coordinates":[-81.89218139650001,43.2309188843],"type":"Point"}
}