{
  "type": "Feature",
  "properties": {
    "addr:full":"1920 30 Ave SW Calgary AB T2T 1P9",
    "addr:housenumber":"1920",
    "addr:postcode":"t2t 1p9",
    "addr:street":"30 Ave Sw",
    "iso:country":"CA",
    "sg:address":"1920 30 Ave SW",
    "sg:city":"Calgary",
    "sg:classifiers":[
        {
            "category":"Building & Trades",
            "subcategory":"Construction",
            "type":"Services"
        }
    ],
    "sg:phone":"+1 403 230 0078",
    "sg:postcode":"T2T 1P9",
    "sg:province":"AB",
    "sg:tags":[
        "dry wall",
        "contractor"
    ],
    "wof:name":"Classic Contractors Ltd",
    "wof:placetype":"venue"
},
  "geometry": {"coordinates":[-114.10515599999999,51.026863],"type":"Point"}
}