{
  "type": "Feature",
  "properties": {
    "addr:full":"1155 Pacific St Vancouver BC V6E 3X8",
    "addr:housenumber":"1155",
    "addr:postcode":"v6e 3x8",
    "addr:street":"Pacific St",
    "iso:country":"CA",
    "sg:address":"1155 Pacific St",
    "sg:city":"Vancouver",
    "sg:classifiers":[
        {
            "category":"Food & Beverages",
            "subcategory":"Fruits & Vegetables",
            "type":"Retail Goods"
        }
    ],
    "sg:phone":"+1 604 605 1155",
    "sg:postcode":"V6E 3X8",
    "sg:province":"BC",
    "sg:tags":[
        "produce"
    ],
    "wof:name":"Hyrise Produce",
    "wof:placetype":"venue"
},
  "geometry": {"coordinates":[-123.135429,49.279148],"type":"Point"}
}