{
  "type": "Feature",
  "properties": {
    "addr:full":"11598 224 St Maple Ridge BC V2X 5Z7",
    "addr:housenumber":"11598",
    "addr:postcode":"v2x 5z7",
    "addr:street":"224 St",
    "iso:country":"CA",
    "sg:address":"11598 224 St",
    "sg:city":"Maple Ridge",
    "sg:classifiers":[
        {
            "category":"Restaurant",
            "type":"Food & Drink"
        }
    ],
    "sg:phone":"+1 604 463 6838",
    "sg:postcode":"V2X 5Z7",
    "sg:province":"BC",
    "wof:name":"Gourmet's Steak Out",
    "wof:placetype":"venue"
},
  "geometry": {"coordinates":[-122.602218628,49.2132072449],"type":"Point"}
}