{
  "type": "Feature",
  "properties": {
    "addr:full":"Brockville ON K6V 1A7",
    "addr:postcode":"k6v 1a7",
    "iso:country":"CA",
    "sg:city":"Brockville",
    "sg:classifiers":[
        {
            "category":"Professional",
            "subcategory":"Accounting & Tax Preparation",
            "type":"Services"
        }
    ],
    "sg:phone":"+1 613 498 4111",
    "sg:postcode":"K6V 1A7",
    "sg:province":"ON",
    "sg:tags":[
        "accountant"
    ],
    "wof:name":"Van Mierlo, Brian CA",
    "wof:placetype":"venue"
},
  "geometry": {"coordinates":[-75.681786,44.591064],"type":"Point"}
}