{
  "type": "Feature",
  "properties": {
    "addr:full":"242 Buckingham Ave Riverview NB E1B 2N8",
    "addr:housenumber":"242",
    "addr:postcode":"e1b 2n8",
    "addr:street":"Buckingham Ave",
    "iso:country":"CA",
    "sg:address":"242 Buckingham Ave",
    "sg:city":"Riverview",
    "sg:classifiers":[
        {
            "category":"Personal",
            "subcategory":"Beauty Salon",
            "type":"Services"
        }
    ],
    "sg:phone":"+1 506 386 6232",
    "sg:postcode":"E1B 2N8",
    "sg:province":"NB",
    "wof:name":"A Touch Above Hairstyling",
    "wof:placetype":"venue"
},
  "geometry": {"coordinates":[-64.80522155760001,46.0581512451],"type":"Point"}
}