{
  "type": "Feature",
  "properties": {
    "addr:full":"Calgary AB T2A 5H5",
    "addr:postcode":"t2a 5h5",
    "iso:country":"CA",
    "sg:city":"Calgary",
    "sg:classifiers":[
        {
            "category":"Health Services",
            "subcategory":"Doctor",
            "type":"Services"
        }
    ],
    "sg:phone":"+1 403 248 2772",
    "sg:postcode":"T2A 5H5",
    "sg:province":"AB",
    "sg:tags":[
        "dentist"
    ],
    "wof:name":"Bindman, Michael D DDS",
    "wof:placetype":"venue"
},
  "geometry": {"coordinates":[-113.977135,51.055443],"type":"Point"}
}