{
  "type": "Feature",
  "properties": {
    "addr:full":"Nampa AB T0H 2R0",
    "addr:postcode":"t0h 2r0",
    "iso:country":"CA",
    "sg:city":"Nampa",
    "sg:classifiers":[
        {
            "category":"Organizations",
            "subcategory":"Professional Association",
            "type":"Services"
        }
    ],
    "sg:phone":"+1 780 322 2346",
    "sg:postcode":"T0H 2R0",
    "sg:province":"AB",
    "wof:name":"Harmon Valley Community Hall",
    "wof:placetype":"venue"
},
  "geometry": {"coordinates":[-117.134315,56.038799],"type":"Point"}
}