{
  "type": "Feature",
  "properties": {
    "addr:full":"18 Keefer Rd St Catharines ON L2M 7N9",
    "addr:housenumber":"18",
    "addr:postcode":"l2m 7n9",
    "addr:street":"Keefer Rd",
    "iso:country":"CA",
    "sg:address":"18 Keefer Rd",
    "sg:city":"St Catharines",
    "sg:classifiers":[
        {
            "category":"Recreation",
            "subcategory":"Marina",
            "type":"Entertainment"
        }
    ],
    "sg:phone":"+1 905 646 0116",
    "sg:postcode":"L2M 7N9",
    "sg:province":"ON",
    "sg:tags":[
        "repairing",
        "boat"
    ],
    "wof:name":"Tremont Wood Specialties Inc",
    "wof:placetype":"venue"
},
  "geometry": {"coordinates":[-79.205383,43.222637],"type":"Point"}
}