{
  "type": "Feature",
  "properties": {
    "addr:full":"1568 Meadowfield Pl Orleans ON K1C 5V7",
    "addr:housenumber":"1568",
    "addr:postcode":"k1c 5v7",
    "addr:street":"Meadowfield Pl",
    "iso:country":"CA",
    "sg:address":"1568 Meadowfield Pl",
    "sg:city":"Orleans",
    "sg:classifiers":[
        {
            "category":"Professional",
            "type":"Services"
        }
    ],
    "sg:phone":"+1 613 834 6121",
    "sg:postcode":"K1C 5V7",
    "sg:province":"ON",
    "sg:tags":[
        "writer"
    ],
    "wof:name":"Innova Solutions Inc",
    "wof:placetype":"venue"
},
  "geometry": {"coordinates":[-75.54071807859999,45.4498443604],"type":"Point"}
}