{
  "type": "Feature",
  "properties": {
    "iso:country":"CA",
    "sg:address":"6529 Rama Rd",
    "sg:city":"Longford Mills",
    "sg:classifiers":[
        {
            "category":"Wholesale",
            "subcategory":"Meat",
            "type":"Manufacturing & Wholesale Goods"
        }
    ],
    "sg:phone":"+1 705 326 5130",
    "sg:postcode":"L0K 1L0",
    "sg:province":"ON",
    "sg:tags":[
        "butchering"
    ],
    "wof:name":"Longford Mills Meats Ltd",
    "wof:placetype":"venue"
},
  "geometry": {"coordinates":[-79.3494110107,44.674156189],"type":"Point"}
}