{
  "type": "Feature",
  "properties": {
    "addr:full":"741 Taunton Rd E Oshawa ON L1H 7K5",
    "addr:housenumber":"741",
    "addr:postcode":"l1h 7k5",
    "addr:street":"Taunton Rd E",
    "iso:country":"CA",
    "sg:address":"741 Taunton Rd E",
    "sg:city":"Oshawa",
    "sg:classifiers":[
        {
            "category":"Manufacturing",
            "subcategory":"Tools & Machinery",
            "type":"Manufacturing & Wholesale Goods"
        }
    ],
    "sg:phone":"+1 905 721 1778",
    "sg:postcode":"L1H 7K5",
    "sg:province":"ON",
    "sg:tags":[
        "machine",
        "shop"
    ],
    "wof:name":"Danco Welding Inc",
    "wof:placetype":"venue"
},
  "geometry": {"coordinates":[-78.852379,43.938751],"type":"Point"}
}