{
  "type": "Feature",
  "properties": {
    "addr:full":"222 Main St Sackville NB E4L 4C1",
    "addr:housenumber":"222",
    "addr:postcode":"e4l 4c1",
    "addr:street":"Main St",
    "iso:country":"CA",
    "sg:address":"222 Main St",
    "sg:city":"Sackville",
    "sg:classifiers":[
        {
            "category":"Restaurant",
            "type":"Food & Drink"
        }
    ],
    "sg:phone":"+1 506 364 1997",
    "sg:postcode":"E4L 4C1",
    "sg:province":"NB",
    "wof:name":"Mc Donald's",
    "wof:placetype":"venue"
},
  "geometry": {"coordinates":[-64.37333700000001,45.907642],"type":"Point"}
}