{
  "type": "Feature",
  "properties": {
    "addr:full":"Burlington ON L7N 3G7",
    "addr:postcode":"l7n 3g7",
    "iso:country":"CA",
    "sg:city":"Burlington",
    "sg:classifiers":[
        {
            "category":"Insurance",
            "subcategory":"Insurance Agent",
            "type":"Services"
        }
    ],
    "sg:phone":"+1 905 681 1311",
    "sg:postcode":"L7N 3G7",
    "sg:province":"ON",
    "sg:tags":[
        "consultant",
        "planning",
        "financial"
    ],
    "wof:name":"Tru Financial Group",
    "wof:placetype":"venue"
},
  "geometry": {"coordinates":[-79.8003921509,43.3512802124],"type":"Point"}
}