{
  "type": "Feature",
  "properties": {
    "addr:full":"144 Daniel St S Arnprior ON K7S 2L7",
    "addr:housenumber":"144",
    "addr:postcode":"k7s 2l7",
    "addr:street":"Daniel St S",
    "iso:country":"CA",
    "sg:address":"144 Daniel St S",
    "sg:city":"Arnprior",
    "sg:classifiers":[
        {
            "category":"Retail",
            "subcategory":"Auto Repair",
            "type":"Services"
        }
    ],
    "sg:phone":"+1 613 623 4734",
    "sg:postcode":"K7S 2L7",
    "sg:province":"ON",
    "sg:tags":[
        "repairing",
        "automobile"
    ],
    "wof:name":"Arnprior Mister Muffler",
    "wof:placetype":"venue"
},
  "geometry": {"coordinates":[-76.360916,45.427357],"type":"Point"}
}