{
  "type": "Feature",
  "properties": {
    "addr:full":"Dartmouth NS B3B 2B4",
    "addr:postcode":"b3b 2b4",
    "iso:country":"CA",
    "sg:city":"Dartmouth",
    "sg:classifiers":[
        {
            "category":"Insurance",
            "subcategory":"Insurance Agent",
            "type":"Services"
        }
    ],
    "sg:phone":"+1 902 421 1519",
    "sg:postcode":"B3B 2B4",
    "sg:province":"NS",
    "sg:tags":[
        "adjuster"
    ],
    "wof:name":"Cunninham Lindsey Canada Ltd",
    "wof:placetype":"venue"
},
  "geometry": {"coordinates":[-63.579315,44.695885],"type":"Point"}
}