{
  "type": "Feature",
  "properties": {
    "iso:country":"CA",
    "sg:city":"North Vancouver",
    "sg:classifiers":[
        {
            "category":"Health Services",
            "subcategory":"Doctor",
            "type":"Services"
        }
    ],
    "sg:phone":"+1 604 985 2870",
    "sg:postcode":"V7M 3G4",
    "sg:province":"BC",
    "sg:tags":[
        "dentist"
    ],
    "wof:name":"John W Wilson Inc",
    "wof:placetype":"venue"
},
  "geometry": {"coordinates":[-123.07369995099999,49.3240242004],"type":"Point"}
}