{
  "type": "Feature",
  "properties": {
    "addr:full":"417 Bethune St Peterborough ON K9H 3Z1",
    "addr:housenumber":"417",
    "addr:postcode":"k9h 3z1",
    "addr:street":"Bethune St",
    "iso:country":"CA",
    "sg:address":"417 Bethune St",
    "sg:city":"Peterborough",
    "sg:classifiers":[
        {
            "category":"Professional",
            "subcategory":"Art Services",
            "type":"Services"
        }
    ],
    "sg:phone":"+1 705 745 8063",
    "sg:postcode":"K9H 3Z1",
    "sg:province":"ON",
    "sg:tags":[
        "photographer"
    ],
    "wof:name":"Trent Photographics",
    "wof:placetype":"venue"
},
  "geometry": {"coordinates":[-78.324692,44.305965],"type":"Point"}
}