{
  "type": "Feature",
  "properties": {
    "addr:full":"6120 90 Ave NW Edmonton AB T6B 0P2",
    "addr:housenumber":"6120",
    "addr:postcode":"t6b 0p2",
    "addr:street":"90 Ave Nw",
    "iso:country":"CA",
    "sg:address":"6120 90 Ave NW",
    "sg:city":"Edmonton",
    "sg:classifiers":[
        {
            "category":"Retail",
            "subcategory":"Veterinary Services",
            "type":"Services"
        }
    ],
    "sg:phone":"+1 780 466 1826",
    "sg:postcode":"T6B 0P2",
    "sg:province":"AB",
    "sg:tags":[
        "veterinarian"
    ],
    "wof:name":"Ottewell Animal Clinic",
    "wof:placetype":"venue"
},
  "geometry": {"coordinates":[-113.426811218,53.5245285034],"type":"Point"}
}