{
  "type": "Feature",
  "properties": {
    "addr:full":"12 Weldon St Moncton NB E1C 5V8",
    "addr:housenumber":"12",
    "addr:postcode":"e1c 5v8",
    "addr:street":"Weldon St",
    "iso:country":"CA",
    "sg:address":"12 Weldon St",
    "sg:city":"Moncton",
    "sg:classifiers":[
        {
            "category":"Organizations",
            "subcategory":"Community Association",
            "type":"Services"
        }
    ],
    "sg:phone":"+1 506 856 8300",
    "sg:postcode":"E1C 5V8",
    "sg:province":"NB",
    "sg:tags":[
        "club"
    ],
    "wof:name":"Elks Club",
    "wof:placetype":"venue"
},
  "geometry": {"coordinates":[-64.786575,46.08633],"type":"Point"}
}