{
  "type": "Feature",
  "properties": {
    "addr:full":"33 Centre St Gimli MB R0C 1B0",
    "addr:housenumber":"33",
    "addr:postcode":"r0c 1b0",
    "addr:street":"Centre St",
    "iso:country":"CA",
    "sg:address":"33 Centre St",
    "sg:city":"Gimli",
    "sg:classifiers":[
        {
            "category":"Shopping",
            "subcategory":"Used Merchandise",
            "type":"Retail Goods"
        }
    ],
    "sg:phone":"+1 204 642 9509",
    "sg:postcode":"R0C 1B0",
    "sg:province":"MB",
    "sg:tags":[
        "book",
        "rare",
        "dealer"
    ],
    "wof:name":"Page's Book Exchange & Craft",
    "wof:placetype":"venue"
},
  "geometry": {"coordinates":[-96.9855270386,50.6319847107],"type":"Point"}
}