{
  "type": "Feature",
  "properties": {
    "addr:full":"68 Renfrew St Pembroke ON K8A 5R6",
    "addr:housenumber":"68",
    "addr:postcode":"k8a 5r6",
    "addr:street":"Renfrew St",
    "iso:country":"CA",
    "sg:address":"68 Renfrew St",
    "sg:city":"Pembroke",
    "sg:classifiers":[
        {
            "category":"Organizations",
            "subcategory":"Religious Organization",
            "type":"Services"
        }
    ],
    "sg:phone":"+1 613 732 4658",
    "sg:postcode":"K8A 5R6",
    "sg:province":"ON",
    "sg:tags":[
        "church"
    ],
    "wof:name":"Holy Trinity Church",
    "wof:placetype":"venue"
},
  "geometry": {"coordinates":[-77.11380800000001,45.824951],"type":"Point"}
}