{
  "type": "Feature",
  "properties": {
    "addr:full":"Delta BC V4K 5B3",
    "addr:postcode":"v4k 5b3",
    "iso:country":"CA",
    "sg:city":"Delta",
    "sg:classifiers":[
        {
            "category":"Communications",
            "subcategory":"Radio Station",
            "type":"Services"
        }
    ],
    "sg:phone":"+1 604 940 8787",
    "sg:postcode":"V4K 5B3",
    "sg:province":"BC",
    "sg:tags":[
        "company",
        "broadcasting"
    ],
    "wof:name":"Sky Words Traffic Network Inc",
    "wof:placetype":"venue"
},
  "geometry": {"coordinates":[-123.024047852,49.0827674866],"type":"Point"}
}