{
  "type": "Feature",
  "properties": {
    "addr:full":"1955 Boul Saint-Elzear O Laval QC H7L 3N7",
    "addr:housenumber":"1955",
    "addr:postcode":"h7l 3n7",
    "addr:street":"Boul Saint-Elzear O",
    "iso:country":"CA",
    "sg:address":"1955 Boul Saint-Elzear O",
    "sg:city":"Laval",
    "sg:classifiers":[
        {
            "category":"Building & Trades",
            "subcategory":"Plumbing",
            "type":"Services"
        }
    ],
    "sg:phone":"+1 514 745 0230",
    "sg:postcode":"H7L 3N7",
    "sg:province":"QC",
    "sg:tags":[
        "conditioning",
        "air",
        "system",
        "contractor"
    ],
    "wof:name":"Ventilabec Inc",
    "wof:placetype":"venue"
},
  "geometry": {"coordinates":[-73.75086212159999,45.583366394],"type":"Point"}
}