{
  "type": "Feature",
  "properties": {
    "iso:country":"CA",
    "sg:address":"102 Lafayette Blvd W",
    "sg:city":"Lethbridge",
    "sg:classifiers":[
        {
            "category":"Shopping",
            "type":"Retail Goods"
        }
    ],
    "sg:phone":"+1 403 381 7111",
    "sg:postcode":"T1K 3Y7",
    "sg:province":"AB",
    "sg:tags":[
        "cosmetic",
        "perfume"
    ],
    "wof:name":"Concept Now Cosmetics Ltd",
    "wof:placetype":"venue"
},
  "geometry": {"coordinates":[-112.876754761,49.6790275574],"type":"Point"}
}