{
  "type": "Feature",
  "properties": {
    "addr:full":"1450 Pandosy St Kelowna BC V1Y 1P3",
    "addr:housenumber":"1450",
    "addr:postcode":"v1y 1p3",
    "addr:street":"Pandosy St",
    "iso:country":"CA",
    "sg:address":"1450 Pandosy St",
    "sg:city":"Kelowna",
    "sg:classifiers":[
        {
            "category":"Real Estate",
            "subcategory":"Architect",
            "type":"Services"
        }
    ],
    "sg:phone":"+1 250 860 8185",
    "sg:postcode":"V1Y 1P3",
    "sg:province":"BC",
    "wof:name":"New Town Architectural Svc",
    "wof:placetype":"venue"
},
  "geometry": {"coordinates":[-119.4953,49.886803],"type":"Point"}
}