{
  "type": "Feature",
  "properties": {
    "addr:full":"Burns Lake BC V0J 1E0",
    "addr:postcode":"bc v0j 1e0",
    "addr:street":"Burns Lake",
    "iso:country":"CA",
    "sg:city":"Burns Lake",
    "sg:classifiers":[
        {
            "category":"Manufacturing",
            "subcategory":"Lumber",
            "type":"Manufacturing & Wholesale Goods"
        }
    ],
    "sg:phone":"+1 250 692 9119",
    "sg:postcode":"V0J 1E0",
    "sg:province":"BC",
    "sg:tags":[
        "forester"
    ],
    "wof:name":"Earth Keeper Contracting Ltd",
    "wof:placetype":"venue"
},
  "geometry": {"coordinates":[-125.758537292,54.2266998291],"type":"Point"}
}