{
  "type": "Feature",
  "properties": {
    "addr:full":"1549 Fairburn St Sudbury ON P3A 1N6",
    "addr:housenumber":"1549",
    "addr:postcode":"p3a 1n6",
    "addr:street":"Fairburn St",
    "iso:country":"CA",
    "sg:address":"1549 Fairburn St",
    "sg:city":"Sudbury",
    "sg:classifiers":[
        {
            "category":"Shopping",
            "subcategory":"Computers & Home Electronics",
            "type":"Retail Goods"
        }
    ],
    "sg:phone":"+1 705 560 2423",
    "sg:postcode":"P3A 1N6",
    "sg:province":"ON",
    "sg:tags":[
        "communication",
        "radio",
        "system",
        "antenna"
    ],
    "wof:name":"Fair Radio Svc Ctr",
    "wof:placetype":"venue"
},
  "geometry": {"coordinates":[-80.941093,46.517448],"type":"Point"}
}