{
  "type": "Feature",
  "properties": {
    "addr:full":"389 Route 105 Nackawic NB E6G 1T9",
    "addr:housenumber":"389",
    "addr:postcode":"e6g 1t9",
    "addr:street":"Route 105",
    "iso:country":"CA",
    "sg:address":"389 Route 105",
    "sg:city":"Nackawic",
    "sg:classifiers":[
        {
            "category":"Autos & Motor Vehicles",
            "subcategory":"Motorcycle Sales",
            "type":"Retail Goods"
        }
    ],
    "sg:phone":"+1 506 575 2990",
    "sg:postcode":"E6G 1T9",
    "sg:province":"NB",
    "sg:tags":[
        "scooter"
    ],
    "wof:name":"Mac Wing of Canada",
    "wof:placetype":"venue"
},
  "geometry": {"coordinates":[-67.24457550050001,45.9901733398],"type":"Point"}
}