{
  "type": "Feature",
  "properties": {
    "iso:country":"CA",
    "sg:address":"1431 Rue Pompadour",
    "sg:city":"Charlesbourg",
    "sg:classifiers":[
        {
            "category":"Personal",
            "subcategory":"Beauty Salon",
            "type":"Services"
        }
    ],
    "sg:phone":"+1 418 622 5354",
    "sg:postcode":"G2L 2A8",
    "sg:province":"QC",
    "wof:name":"Centre DE Beaute C Giguere Enr",
    "wof:placetype":"venue"
},
  "geometry": {"coordinates":[-71.267426,46.888378],"type":"Point"}
}