{
  "type": "Feature",
  "properties": {
    "addr:full":"319 City Centre Kitimat BC V8C 1T6",
    "addr:housenumber":"319",
    "addr:postcode":"bc v8c 1t6",
    "addr:street":"City",
    "iso:country":"CA",
    "sg:address":"319 City Centre",
    "sg:city":"Kitimat",
    "sg:classifiers":[
        {
            "category":"Retail",
            "subcategory":"Laundry & Dry Cleaning",
            "type":"Services"
        }
    ],
    "sg:phone":"+1 250 632 7878",
    "sg:postcode":"V8C 1T6",
    "sg:province":"BC",
    "sg:tags":[
        "cleaners"
    ],
    "wof:name":"Towne Cleaners Ltd",
    "wof:placetype":"venue"
},
  "geometry": {"coordinates":[-128.65548699999999,54.053123],"type":"Point"}
}