{
  "type": "Feature",
  "properties": {
    "addr:full":"4085 Rue Clark Montreal QC H2W 1X1",
    "addr:housenumber":"4085",
    "addr:postcode":"h2w 1x1",
    "addr:street":"Rue Clark",
    "iso:country":"CA",
    "sg:address":"4085 Rue Clark",
    "sg:city":"Montreal",
    "sg:classifiers":[
        {
            "category":"Professional",
            "subcategory":"Business Services",
            "type":"Services"
        }
    ],
    "sg:phone":"+1 514 845 1370",
    "sg:postcode":"H2W 1X1",
    "sg:province":"QC",
    "sg:tags":[
        "interior",
        "consultant",
        "design",
        "decorator"
    ],
    "wof:name":"M & M Design Intl",
    "wof:placetype":"venue"
},
  "geometry": {"coordinates":[-73.58042144780001,45.5168685913],"type":"Point"}
}