{
  "type": "Feature",
  "properties": {
    "iso:country":"CA",
    "sg:address":"1410 Parkway Blvd",
    "sg:city":"Coquitlam",
    "sg:classifiers":[
        {
            "category":"Food & Beverages",
            "subcategory":"Groceries & Convenience Stores",
            "type":"Retail Goods"
        }
    ],
    "sg:phone":"+1 604 444 6211",
    "sg:postcode":"V3E 3J7",
    "sg:province":"BC",
    "sg:tags":[
        "grocer"
    ],
    "wof:name":"Iga Stores",
    "wof:placetype":"venue"
},
  "geometry": {"coordinates":[-122.803344727,49.2968864441],"type":"Point"}
}