{
  "type": "Feature",
  "properties": {
    "addr:full":"3201 30 Ave Vernon BC V1T 2C6",
    "addr:housenumber":"3201",
    "addr:postcode":"v1t 2c6",
    "addr:street":"30 Ave",
    "iso:country":"CA",
    "sg:address":"3201 30 Ave",
    "sg:city":"Vernon",
    "sg:classifiers":[
        {
            "category":"Professional",
            "subcategory":"Accounting & Tax Preparation",
            "type":"Services"
        }
    ],
    "sg:phone":"+1 250 542 0333",
    "sg:postcode":"V1T 2C6",
    "sg:province":"BC",
    "sg:tags":[
        "accountant"
    ],
    "wof:name":"Beardsell & CO",
    "wof:placetype":"venue"
},
  "geometry": {"coordinates":[-119.27394866900001,50.2638244629],"type":"Point"}
}