{
  "type": "Feature",
  "properties": {
    "addr:full":"125 Oshawa Blvd S Oshawa ON L1H 5R4",
    "addr:housenumber":"125",
    "addr:postcode":"l1h 5r4",
    "addr:street":"Oshawa Blvd S",
    "iso:country":"CA",
    "sg:address":"125 Oshawa Blvd S",
    "sg:city":"Oshawa",
    "sg:classifiers":[
        {
            "category":"Professional",
            "subcategory":"Accounting & Tax Preparation",
            "type":"Services"
        }
    ],
    "sg:phone":"+1 905 576 7520",
    "sg:postcode":"L1H 5R4",
    "sg:province":"ON",
    "sg:tags":[
        "accountant"
    ],
    "wof:name":"Jackson, Keith A",
    "wof:placetype":"venue"
},
  "geometry": {"coordinates":[-78.8499450684,43.8968849182],"type":"Point"}
}