{
  "type": "Feature",
  "properties": {
    "addr:full":"78 Shade St Cambridge ON N1R 4J8",
    "addr:housenumber":"78",
    "addr:postcode":"n1r 4j8",
    "addr:street":"Shade St",
    "iso:country":"CA",
    "sg:address":"78 Shade St",
    "sg:city":"Cambridge",
    "sg:classifiers":[
        {
            "category":"Autos & Motor Vehicles",
            "subcategory":"Automobile Sales",
            "type":"Retail Goods"
        }
    ],
    "sg:phone":"+1 519 621 7711",
    "sg:postcode":"N1R 4J8",
    "sg:province":"ON",
    "sg:tags":[
        "repairing",
        "car"
    ],
    "wof:name":"Werner's Auto Svc",
    "wof:placetype":"venue"
},
  "geometry": {"coordinates":[-80.3072967529,43.3616294861],"type":"Point"}
}