{
  "type": "Feature",
  "properties": {
    "iso:country":"CA",
    "sg:address":"Evening Path",
    "sg:city":"Torbay",
    "sg:classifiers":[
        {
            "category":"Freight",
            "type":"Transportation"
        }
    ],
    "sg:phone":"+1 709 437 6951",
    "sg:postcode":"A1K 1E4",
    "sg:province":"NL",
    "sg:tags":[
        "trucking"
    ],
    "wof:name":"White's Excavating & Trucking",
    "wof:placetype":"venue"
},
  "geometry": {"coordinates":[-52.7433357239,47.6566886902],"type":"Point"}
}