{
  "type": "Feature",
  "properties": {
    "addr:full":"2500 11th Ave Regina SK S4P 0K5",
    "addr:housenumber":"2500",
    "addr:postcode":"s4p 0k5",
    "addr:street":"11Th Ave",
    "iso:country":"CA",
    "sg:address":"2500 11th Ave",
    "sg:city":"Regina",
    "sg:classifiers":[
        {
            "category":"Health Services",
            "subcategory":"Chiropractor",
            "type":"Services"
        }
    ],
    "sg:phone":"+1 306 525 6151",
    "sg:postcode":"S4P 0K5",
    "sg:province":"SK",
    "wof:name":"Flash, J E DC",
    "wof:placetype":"venue"
},
  "geometry": {"coordinates":[-104.616722107,50.4504737854],"type":"Point"}
}