{
  "type": "Feature",
  "properties": {
    "iso:country":"CA",
    "sg:address":"359 Grand Ave E",
    "sg:city":"Chatham",
    "sg:classifiers":[
        {
            "category":"Building & Trades",
            "subcategory":"Pest Control",
            "type":"Services"
        }
    ],
    "sg:phone":"+1 519 351 4342",
    "sg:postcode":"N7L 1W9",
    "sg:province":"ON",
    "wof:name":"On Guard Pest Control",
    "wof:placetype":"venue"
},
  "geometry": {"coordinates":[-82.178696,42.416325],"type":"Point"}
}