{
  "type": "Feature",
  "properties": {
    "addr:full":"Vancouver BC V6A 3X4",
    "addr:postcode":"v6a 3x4",
    "iso:country":"CA",
    "sg:city":"Vancouver",
    "sg:classifiers":[
        {
            "category":"Real Estate",
            "subcategory":"Real Estate Agent",
            "type":"Services"
        }
    ],
    "sg:phone":"+1 604 255 4778",
    "sg:postcode":"V6A 3X4",
    "sg:province":"BC",
    "sg:tags":[
        "cooperative"
    ],
    "wof:name":"Dan Mau Gardens Housing CO-OP",
    "wof:placetype":"venue"
},
  "geometry": {"coordinates":[-123.096260071,49.280128479],"type":"Point"}
}