{
  "type": "Feature",
  "properties": {
    "addr:full":"1403 39 Ave Vernon BC V1T 3A6",
    "addr:housenumber":"1403",
    "addr:postcode":"v1t 3a6",
    "addr:street":"39 Ave",
    "iso:country":"CA",
    "sg:address":"1403 39 Ave",
    "sg:city":"Vernon",
    "sg:classifiers":[
        {
            "category":"Retail",
            "subcategory":"Portrait Studio",
            "type":"Services"
        }
    ],
    "sg:phone":"+1 250 558 1983",
    "sg:postcode":"V1T 3A6",
    "sg:province":"BC",
    "sg:tags":[
        "photographer"
    ],
    "wof:name":"Ian Bull Photography",
    "wof:placetype":"venue"
},
  "geometry": {"coordinates":[-119.250427,50.270363],"type":"Point"}
}