{
  "type": "Feature",
  "properties": {
    "iso:country":"CA",
    "sg:address":"387 Phillip St",
    "sg:city":"Waterloo",
    "sg:classifiers":[
        {
            "category":"Wholesale",
            "subcategory":"Hardware",
            "type":"Manufacturing & Wholesale Goods"
        }
    ],
    "sg:phone":"+1 519 884 0600",
    "sg:postcode":"N2L 5R8",
    "sg:province":"ON",
    "sg:tags":[
        "used",
        "boiler"
    ],
    "wof:name":"Waterloo Manufacturing CO Ltd",
    "wof:placetype":"venue"
},
  "geometry": {"coordinates":[-80.5418624878,43.4796524048],"type":"Point"}
}