{
  "type": "Feature",
  "properties": {
    "addr:full":"2500 Airport Rd Windsor ON N8W 5E7",
    "addr:housenumber":"2500",
    "addr:postcode":"n8w 5e7",
    "addr:street":"Airport Rd",
    "iso:country":"CA",
    "sg:address":"2500 Airport Rd",
    "sg:city":"Windsor",
    "sg:classifiers":[
        {
            "category":"Retail",
            "subcategory":"Auto Rental",
            "type":"Services"
        }
    ],
    "sg:phone":"+1 519 966 3791",
    "sg:postcode":"N8W 5E7",
    "sg:province":"ON",
    "sg:tags":[
        "renting",
        "truck",
        "leasing"
    ],
    "wof:name":"M G John & Sons Ltd",
    "wof:placetype":"venue"
},
  "geometry": {"coordinates":[-82.968765,42.268089],"type":"Point"}
}