{
  "type": "Feature",
  "properties": {
    "iso:country":"CA",
    "sg:address":"470 Rue Victoria",
    "sg:city":"Sherbrooke",
    "sg:classifiers":[
        {
            "category":"Social Services",
            "type":"Services"
        }
    ],
    "sg:phone":"+1 819 563 1622",
    "sg:postcode":"J1H 3J2",
    "sg:province":"QC",
    "sg:tags":[
        "organization",
        "welfare"
    ],
    "wof:name":"Villa Marie-Claire Inc",
    "wof:placetype":"venue"
},
  "geometry": {"coordinates":[-71.9057312012,45.405292511],"type":"Point"}
}