{
  "type": "Feature",
  "properties": {
    "addr:full":"1505 Macleod Trail SE Calgary AB T2G 2N6",
    "addr:housenumber":"1505",
    "addr:postcode":"t2g 2n6",
    "addr:street":"Macleod Trail Se",
    "iso:country":"CA",
    "sg:address":"1505 Macleod Trail SE",
    "sg:city":"Calgary",
    "sg:classifiers":[
        {
            "category":"Insurance",
            "subcategory":"Insurance Agent",
            "type":"Services"
        }
    ],
    "sg:phone":"+1 403 705 5067",
    "sg:postcode":"T2G 2N6",
    "sg:province":"AB",
    "wof:name":"Mc Pherson Financial Group Inc",
    "wof:placetype":"venue"
},
  "geometry": {"coordinates":[-114.05883,51.038719],"type":"Point"}
}