{
  "type": "Feature",
  "properties": {
    "addr:full":"Brockville ON K6V 6E5",
    "addr:postcode":"k6v 6e5",
    "iso:country":"CA",
    "sg:city":"Brockville",
    "sg:classifiers":[
        {
            "category":"Health Services",
            "subcategory":"Doctor",
            "type":"Services"
        }
    ],
    "sg:phone":"+1 613 345 0918",
    "sg:postcode":"K6V 6E5",
    "sg:province":"ON",
    "sg:tags":[
        "physician",
        "surgeon"
    ],
    "wof:name":"Steacie, Adam MD",
    "wof:placetype":"venue"
},
  "geometry": {"coordinates":[-75.689796,44.601189],"type":"Point"}
}