{
  "type": "Feature",
  "properties": {
    "addr:full":"34 Rue Rachel O Montreal QC H2W 1G1",
    "addr:housenumber":"34",
    "addr:postcode":"h2w 1g1",
    "addr:street":"Rue Rachel O",
    "iso:country":"CA",
    "sg:address":"34 Rue Rachel O",
    "sg:city":"Montreal",
    "sg:classifiers":[
        {
            "category":"Restaurant",
            "type":"Food & Drink"
        }
    ],
    "sg:phone":"+1 514 282 1519",
    "sg:postcode":"H2W 1G1",
    "sg:province":"QC",
    "wof:name":"Rotisserie Portugalia",
    "wof:placetype":"venue"
},
  "geometry": {"coordinates":[-73.58122253419999,45.5182723999],"type":"Point"}
}