{
  "type": "Feature",
  "properties": {
    "iso:country":"CA",
    "sg:city":"Saint-Eustache",
    "sg:classifiers":[
        {
            "category":"Personal",
            "subcategory":"Beauty Salon",
            "type":"Services"
        }
    ],
    "sg:phone":"+1 450 623 7773",
    "sg:postcode":"J7P 1V2",
    "sg:province":"QC",
    "wof:name":"Action Coiffure Plus",
    "wof:placetype":"venue"
},
  "geometry": {"coordinates":[-73.90045166020001,45.5636634827],"type":"Point"}
}