{
  "type": "Feature",
  "properties": {
    "addr:full":"50 Boul Maurice-Bastien Wendake QC G0A 4V0",
    "addr:housenumber":"50",
    "addr:postcode":"g0a 4v0",
    "addr:street":"Boul Maurice-Bastien",
    "iso:country":"CA",
    "sg:address":"50 Boul Maurice-Bastien",
    "sg:city":"Wendake",
    "sg:classifiers":[
        {
            "category":"Shopping",
            "subcategory":"Computers & Home Electronics",
            "type":"Retail Goods"
        }
    ],
    "sg:phone":"+1 418 843 2503",
    "sg:postcode":"G0A 4V0",
    "sg:province":"QC",
    "sg:tags":[
        "equipment",
        "video"
    ],
    "wof:name":"Top Video Wendake",
    "wof:placetype":"venue"
},
  "geometry": {"coordinates":[-74.008682251,45.8044967651],"type":"Point"}
}