{
  "type": "Feature",
  "properties": {
    "addr:full":"1328 Mcgill Rd Kamloops BC V2C 6N6",
    "addr:housenumber":"1328",
    "addr:postcode":"bc v2c 6n6",
    "addr:street":"Mcgill Rd",
    "iso:country":"CA",
    "sg:address":"1328 Mcgill Rd",
    "sg:city":"Kamloops",
    "sg:classifiers":[
        {
            "category":"Building & Trades",
            "subcategory":"Construction",
            "type":"Services"
        }
    ],
    "sg:phone":"+1 250 372 8448",
    "sg:postcode":"V2C 6N6",
    "sg:province":"BC",
    "sg:tags":[
        "general",
        "contractor"
    ],
    "wof:name":"Dalgleish Construction Mgmt",
    "wof:placetype":"venue"
},
  "geometry": {"coordinates":[-120.374351502,50.6722488403],"type":"Point"}
}