{
  "type": "Feature",
  "properties": {
    "iso:country":"CA",
    "sg:city":"Red Deer",
    "sg:classifiers":[
        {
            "category":"Organizations",
            "subcategory":"Professional Association",
            "type":"Services"
        }
    ],
    "sg:phone":"+1 403 346 5321",
    "sg:postcode":"T4P 2B4",
    "sg:province":"AB",
    "wof:name":"Central Alberta Home Builders",
    "wof:placetype":"venue"
},
  "geometry": {"coordinates":[-113.813828,52.288502],"type":"Point"}
}