{
  "type": "Feature",
  "properties": {
    "addr:full":"Blind Bay BC V0E 1H1",
    "addr:postcode":"v0e 1h1",
    "iso:country":"CA",
    "sg:city":"Blind Bay",
    "sg:classifiers":[
        {
            "category":"Shopping",
            "type":"Retail Goods"
        }
    ],
    "sg:phone":"+1 250 675 3701",
    "sg:postcode":"V0E 1H1",
    "sg:province":"BC",
    "sg:tags":[
        "picture",
        "frame",
        "material",
        "artist",
        "supply"
    ],
    "wof:name":"Little River Framing Studio",
    "wof:placetype":"venue"
},
  "geometry": {"coordinates":[-119.222389221,50.9327468872],"type":"Point"}
}