{
  "type": "Feature",
  "properties": {
    "addr:full":"2205 Boul Cournoyer Sorel-Tracy QC J3R 2N1",
    "addr:housenumber":"2205",
    "addr:postcode":"j3r 2n1",
    "addr:street":"Boul Cournoyer",
    "iso:country":"CA",
    "sg:address":"2205 Boul Cournoyer",
    "sg:city":"Sorel-Tracy",
    "sg:classifiers":[
        {
            "category":"Shopping",
            "type":"Retail Goods"
        }
    ],
    "sg:phone":"+1 450 730 2856",
    "sg:postcode":"J3R 2N1",
    "sg:province":"QC",
    "sg:tags":[
        "equipment",
        "supply",
        "system",
        "telephone"
    ],
    "wof:name":"Techni-Express Svc Tel",
    "wof:placetype":"venue"
},
  "geometry": {"coordinates":[-73.141548,46.026424],"type":"Point"}
}