{
  "type": "Feature",
  "properties": {
    "addr:full":"Saint-Camille-DE-Bellechasse QC G0R 2S0",
    "addr:postcode":"g0r 2s0",
    "iso:country":"CA",
    "sg:city":"Saint-Camille-DE-Bellechasse",
    "sg:classifiers":[
        {
            "category":"Recreation",
            "type":"Entertainment"
        }
    ],
    "sg:phone":"+1 418 595 2148",
    "sg:postcode":"G0R 2S0",
    "sg:province":"QC",
    "sg:tags":[
        "center"
    ],
    "wof:name":"Chalet Des Loisirs",
    "wof:placetype":"venue"
},
  "geometry": {"coordinates":[-70.21115112299999,46.4935035706],"type":"Point"}
}