{
  "type": "Feature",
  "properties": {
    "addr:full":"563 Notre Dame Ave Winnipeg MB R3B 1S5",
    "addr:housenumber":"563",
    "addr:postcode":"r3b 1s5",
    "addr:street":"Notre Dame Ave",
    "iso:country":"CA",
    "sg:address":"563 Notre Dame Ave",
    "sg:city":"Winnipeg",
    "sg:classifiers":[
        {
            "category":"Manufacturing",
            "subcategory":"Apparel",
            "type":"Manufacturing & Wholesale Goods"
        }
    ],
    "sg:phone":"+1 204 786 1503",
    "sg:postcode":"R3B 1S5",
    "sg:province":"MB",
    "sg:tags":[
        "clothing"
    ],
    "wof:name":"Kelsey Sportswear Ltd",
    "wof:placetype":"venue"
},
  "geometry": {"coordinates":[-97.154678,49.900211],"type":"Point"}
}