{
  "type": "Feature",
  "properties": {
    "iso:country":"CA",
    "sg:city":"Ottawa",
    "sg:classifiers":[
        {
            "category":"Organizations",
            "subcategory":"Professional Association",
            "type":"Services"
        }
    ],
    "sg:phone":"+1 613 789 3328",
    "sg:postcode":"K1N 7B7",
    "sg:province":"ON",
    "wof:name":"Canadem",
    "wof:placetype":"venue"
},
  "geometry": {"coordinates":[-75.6905288696,45.4266891479],"type":"Point"}
}