{
  "type": "Feature",
  "properties": {
    "addr:full":"100 Bayshore Dr # 100 Nepean ON K2B 8C1",
    "addr:housenumber":"100;100",
    "addr:postcode":"k2b 8c1",
    "addr:street":"Bayshore Dr #",
    "iso:country":"CA",
    "sg:address":"100 Bayshore Dr # 100",
    "sg:city":"Nepean",
    "sg:classifiers":[
        {
            "category":"Restaurant",
            "type":"Food & Drink"
        }
    ],
    "sg:phone":"+1 613 829 2520",
    "sg:postcode":"K2B 8C1",
    "sg:province":"ON",
    "sg:tags":[
        "shop",
        "coffee"
    ],
    "wof:name":"Second Cup",
    "wof:placetype":"venue"
},
  "geometry": {"coordinates":[-75.8050918579,45.3490791321],"type":"Point"}
}