{
  "type": "Feature",
  "properties": {
    "addr:full":"388 Parliament St Toronto ON M5A 2Z7",
    "addr:housenumber":"388",
    "addr:postcode":"m5a 2z7",
    "addr:street":"Parliament St",
    "iso:country":"CA",
    "sg:address":"388 Parliament St",
    "sg:city":"Toronto",
    "sg:classifiers":[
        {
            "category":"Manufacturing",
            "subcategory":"Printing",
            "type":"Manufacturing & Wholesale Goods"
        }
    ],
    "sg:phone":"+1 416 923 3374",
    "sg:postcode":"M5A 2Z7",
    "sg:province":"ON",
    "sg:tags":[
        "printer"
    ],
    "wof:name":"Re Print Copy & Printing Ltd",
    "wof:placetype":"venue"
},
  "geometry": {"coordinates":[-79.366989,43.661396],"type":"Point"}
}