{
  "type": "Feature",
  "properties": {
    "addr:full":"130 Fried St Dashwood ON N0M 1N0",
    "addr:housenumber":"130",
    "addr:postcode":"n0m 1n0",
    "addr:street":"Fried St",
    "iso:country":"CA",
    "sg:address":"130 Fried St",
    "sg:city":"Dashwood",
    "sg:classifiers":[
        {
            "category":"Manufacturing",
            "subcategory":"Wood Products",
            "type":"Manufacturing & Wholesale Goods"
        }
    ],
    "sg:phone":"+1 519 237 3127",
    "sg:postcode":"N0M 1N0",
    "sg:province":"ON",
    "sg:tags":[
        "pallet",
        "skid"
    ],
    "wof:name":"Dashwood Wood Products",
    "wof:placetype":"venue"
},
  "geometry": {"coordinates":[-81.6337356567,43.346622467],"type":"Point"}
}