{
  "type": "Feature",
  "properties": {
    "addr:full":"243 Cundles Rd E Barrie ON L4M 6L1",
    "addr:housenumber":"243",
    "addr:postcode":"l4m 6l1",
    "addr:street":"Cundles Rd E",
    "iso:country":"CA",
    "sg:address":"243 Cundles Rd E",
    "sg:city":"Barrie",
    "sg:classifiers":[
        {
            "category":"Education",
            "subcategory":"School",
            "type":"Public Place"
        }
    ],
    "sg:phone":"+1 705 728 3120",
    "sg:postcode":"L4M 6L1",
    "sg:province":"ON",
    "wof:name":"St Joseph's High School",
    "wof:placetype":"venue"
},
  "geometry": {"coordinates":[-79.6847457886,44.413269043],"type":"Point"}
}