{
  "type": "Feature",
  "properties": {
    "addr:full":"553 Adelaide St N London ON N6B 3J6",
    "addr:housenumber":"553",
    "addr:postcode":"n6b 3j6",
    "addr:street":"Adelaide St N",
    "iso:country":"CA",
    "sg:address":"553 Adelaide St N",
    "sg:city":"London",
    "sg:classifiers":[
        {
            "category":"Shopping",
            "subcategory":"Computers & Home Electronics",
            "type":"Retail Goods"
        }
    ],
    "sg:phone":"+1 519 433 0279",
    "sg:postcode":"N6B 3J6",
    "sg:province":"ON",
    "sg:tags":[
        "equipment",
        "dealer"
    ],
    "wof:name":"Advanced Computer Ideas",
    "wof:placetype":"venue"
},
  "geometry": {"coordinates":[-81.2339096069,42.9932098389],"type":"Point"}
}