{
  "type": "Feature",
  "properties": {
    "addr:full":"80 Rue Saint-Joseph Terrebonne QC J6W 2Y3",
    "addr:housenumber":"80",
    "addr:postcode":"j6w 2y3",
    "addr:street":"Rue Saint-Joseph",
    "iso:country":"CA",
    "sg:address":"80 Rue Saint-Joseph",
    "sg:city":"Terrebonne",
    "sg:classifiers":[
        {
            "category":"Health Services",
            "subcategory":"Nursing And Care Facility",
            "type":"Services"
        }
    ],
    "sg:phone":"+1 450 492 2144",
    "sg:postcode":"J6W 2Y3",
    "sg:province":"QC",
    "sg:tags":[
        "home",
        "retirement",
        "community"
    ],
    "wof:name":"Manoir DE LA Rive",
    "wof:placetype":"venue"
},
  "geometry": {"coordinates":[-73.6326217651,45.6914482117],"type":"Point"}
}