{
  "type": "Feature",
  "properties": {
    "addr:full":"1543 Kokanee Rd Castlegar BC V1N 4S2",
    "addr:housenumber":"1543",
    "addr:postcode":"v1n 4s2",
    "addr:street":"Kokanee Rd",
    "iso:country":"CA",
    "sg:address":"1543 Kokanee Rd",
    "sg:city":"Castlegar",
    "sg:classifiers":[
        {
            "category":"Building & Trades",
            "subcategory":"Construction",
            "type":"Services"
        }
    ],
    "sg:phone":"+1 250 365 3155",
    "sg:postcode":"V1N 4S2",
    "sg:province":"BC",
    "sg:tags":[
        "excavating",
        "contractor",
        "general"
    ],
    "wof:name":"Sorensen Excavating",
    "wof:placetype":"venue"
},
  "geometry": {"coordinates":[-117.65418200000001,49.296253],"type":"Point"}
}