{
  "type": "Feature",
  "properties": {
    "addr:full":"6161 Rue Principale Saint-Felix-DE-Kingsey QC J0B 2T0",
    "addr:housenumber":"6161",
    "addr:postcode":"j0b 2t0",
    "addr:street":"Rue Principale",
    "iso:country":"CA",
    "sg:address":"6161 Rue Principale",
    "sg:city":"Saint-Felix-DE-Kingsey",
    "sg:classifiers":[
        {
            "category":"Home & Garden",
            "subcategory":"Building Materials",
            "type":"Retail Goods"
        }
    ],
    "sg:phone":"+1 819 848 2332",
    "sg:postcode":"J0B 2T0",
    "sg:province":"QC",
    "wof:name":"Materiaux Pyl Inc",
    "wof:placetype":"venue"
},
  "geometry": {"coordinates":[-72.1881103516,45.7932510376],"type":"Point"}
}