{
  "type": "Feature",
  "properties": {
    "addr:full":"4714 53 St Taber AB T1G 1W5",
    "addr:housenumber":"4714",
    "addr:postcode":"t1g 1w5",
    "addr:street":"53 St",
    "iso:country":"CA",
    "sg:address":"4714 53 St",
    "sg:city":"Taber",
    "sg:classifiers":[
        {
            "category":"Shopping",
            "subcategory":"Catalog Store",
            "type":"Retail Goods"
        }
    ],
    "sg:phone":"+1 403 223 4441",
    "sg:postcode":"T1G 1W5",
    "sg:province":"AB",
    "sg:tags":[
        "mail",
        "order",
        "internet"
    ],
    "wof:name":"Sears Canada Inc",
    "wof:placetype":"venue"
},
  "geometry": {"coordinates":[-112.144836,49.783886],"type":"Point"}
}