{
  "type": "Feature",
  "properties": {
    "iso:country":"CA",
    "sg:address":"2724 Ch Sullivan",
    "sg:city":"Sullivan",
    "sg:classifiers":[
        {
            "category":"Home & Garden",
            "subcategory":"Furniture",
            "type":"Retail Goods"
        }
    ],
    "sg:phone":"+1 819 874 1422",
    "sg:postcode":"J0Y 2N0",
    "sg:province":"QC",
    "sg:tags":[
        "equipment",
        "kitchen",
        "cabinet"
    ],
    "wof:name":"Mathero",
    "wof:placetype":"venue"
},
  "geometry": {"coordinates":[-77.82591247560001,48.1175613403],"type":"Point"}
}