{
  "type": "Feature",
  "properties": {
    "addr:full":"451 Queen St E Sault Ste Marie ON P6A 1Z5",
    "addr:housenumber":"451",
    "addr:postcode":"p6a 1z5",
    "addr:street":"Queen St E",
    "iso:country":"CA",
    "sg:address":"451 Queen St E",
    "sg:city":"Sault Ste Marie",
    "sg:classifiers":[
        {
            "category":"Health Services",
            "subcategory":"Health Practitioner",
            "type":"Services"
        }
    ],
    "sg:phone":"+1 705 942 8577",
    "sg:postcode":"P6A 1Z5",
    "sg:province":"ON",
    "sg:tags":[
        "physiotherapist"
    ],
    "wof:name":"Hinding Hales & Assoc Clinic",
    "wof:placetype":"venue"
},
  "geometry": {"coordinates":[-84.33272599999999,46.511215],"type":"Point"}
}