{
  "type": "Feature",
  "properties": {
    "addr:full":"417 Wellington St St Thomas ON N5R 5J5",
    "addr:housenumber":"417",
    "addr:postcode":"n5r 5j5",
    "addr:street":"Wellington St",
    "iso:country":"CA",
    "sg:address":"417 Wellington St",
    "sg:city":"St Thomas",
    "sg:classifiers":[
        {
            "category":"Shopping",
            "subcategory":"Department Store",
            "type":"Retail Goods"
        }
    ],
    "sg:phone":"+1 519 633 4645",
    "sg:postcode":"N5R 5J5",
    "sg:province":"ON",
    "wof:name":"Zellers",
    "wof:placetype":"venue"
},
  "geometry": {"coordinates":[-81.162384,42.774792],"type":"Point"}
}