{
  "type": "Feature",
  "properties": {
    "addr:full":"3803 27 St Vernon BC V1T 4X6",
    "addr:housenumber":"3803",
    "addr:postcode":"v1t 4x6",
    "addr:street":"27 St",
    "iso:country":"CA",
    "sg:address":"3803 27 St",
    "sg:city":"Vernon",
    "sg:classifiers":[
        {
            "category":"Shopping",
            "subcategory":"Florist",
            "type":"Retail Goods"
        }
    ],
    "sg:phone":"+1 250 503 2262",
    "sg:postcode":"V1T 4X6",
    "sg:province":"BC",
    "wof:name":"27th Street Florist & Gift",
    "wof:placetype":"venue"
},
  "geometry": {"coordinates":[-119.266678,50.269615],"type":"Point"}
}