{
  "type": "Feature",
  "properties": {
    "iso:country":"CA",
    "sg:address":"30 Soudan Ave",
    "sg:city":"Toronto",
    "sg:classifiers":[
        {
            "category":"Real Estate",
            "subcategory":"Real Estate Agent",
            "type":"Services"
        }
    ],
    "sg:phone":"+1 416 481 4811",
    "sg:postcode":"M4S 1V6",
    "sg:province":"ON",
    "sg:tags":[
        "management"
    ],
    "wof:name":"Red Cliff Realty Management",
    "wof:placetype":"venue"
},
  "geometry": {"coordinates":[-79.39683532710001,43.7046852112],"type":"Point"}
}