{
  "type": "Feature",
  "properties": {
    "addr:full":"12552 Rue Sherbrooke E Pointe-Aux-Trembles QC H1B 1C9",
    "addr:housenumber":"12552",
    "addr:postcode":"h1b 1c9",
    "addr:street":"Rue Sherbrooke E Pointe-Aux-Trembles",
    "iso:country":"CA",
    "sg:address":"12552 Rue Sherbrooke E",
    "sg:city":"Pointe-Aux-Trembles",
    "sg:classifiers":[
        {
            "category":"Banks & Credit Unions",
            "subcategory":"Bank",
            "type":"Services"
        }
    ],
    "sg:phone":"+1 514 645 4435",
    "sg:postcode":"H1B 1C9",
    "sg:province":"QC",
    "sg:tags":[
        "loan",
        "real estate"
    ],
    "wof:name":"Citifinanciere Canada Inc",
    "wof:placetype":"venue"
},
  "geometry": {"coordinates":[-73.511284,45.650436],"type":"Point"}
}