{
  "type": "Feature",
  "properties": {
    "addr:full":"1101 9th Ave W #1 Kindersley SK S0L 1S0",
    "addr:housenumber":"1101",
    "addr:postcode":"s0l 1s0",
    "addr:street":"9Th Ave W # 1 Kindersley",
    "iso:country":"CA",
    "sg:address":"1101 9th Ave W #1",
    "sg:city":"Kindersley",
    "sg:classifiers":[
        {
            "category":"Building & Trades",
            "subcategory":"Electrical",
            "type":"Services"
        }
    ],
    "sg:phone":"+1 306 463 6262",
    "sg:postcode":"S0L 1S0",
    "sg:province":"SK",
    "sg:tags":[
        "oil",
        "well",
        "electric",
        "contractor"
    ],
    "wof:name":"Pronghorn Controls Ltd",
    "wof:placetype":"venue"
},
  "geometry": {"coordinates":[-109.170113,51.472843],"type":"Point"}
}