{
  "type": "Feature",
  "properties": {
    "addr:full":"432 River Ave E Dauphin MB R7N 0H8",
    "addr:housenumber":"432",
    "addr:postcode":"r7n 0h8",
    "addr:street":"River Ave E Dauphin",
    "iso:country":"CA",
    "sg:address":"432 River Ave E",
    "sg:city":"Dauphin",
    "sg:classifiers":[
        {
            "category":"Wholesale",
            "subcategory":"Electrical",
            "type":"Manufacturing & Wholesale Goods"
        }
    ],
    "sg:phone":"+1 204 638 8736",
    "sg:postcode":"R7N 0H8",
    "sg:province":"MB",
    "sg:tags":[
        "appliance"
    ],
    "wof:name":"Farmer's Appliance Svc",
    "wof:placetype":"venue"
},
  "geometry": {"coordinates":[-100.03162399999999,51.155224],"type":"Point"}
}