{
  "type": "Feature",
  "properties": {
    "addr:full":"PO Box 37 Hillgrade NL A0G 2S0",
    "addr:housenumber":"po box 37",
    "addr:postcode":"a0g 2s0",
    "iso:country":"CA",
    "sg:address":"PO Box 37",
    "sg:city":"Hillgrade",
    "sg:classifiers":[
        {
            "category":"Organizations",
            "subcategory":"Religious Organization",
            "type":"Services"
        }
    ],
    "sg:phone":"+1 709 628 5245",
    "sg:postcode":"A0G 2S0",
    "sg:province":"NL",
    "sg:tags":[
        "church"
    ],
    "wof:name":"Nwie Central United Church",
    "wof:placetype":"venue"
},
  "geometry": {"coordinates":[-54.688522,49.573715],"type":"Point"}
}