{
  "type": "Feature",
  "properties": {
    "addr:full":"7604 112 St NW Edmonton AB T6G 1J7",
    "addr:housenumber":"7604",
    "addr:postcode":"t6g 1j7",
    "addr:street":"112 St Nw",
    "iso:country":"CA",
    "sg:address":"7604 112 St NW",
    "sg:city":"Edmonton",
    "sg:classifiers":[
        {
            "category":"Personal",
            "subcategory":"Barber",
            "type":"Services"
        }
    ],
    "sg:phone":"+1 780 436 0175",
    "sg:postcode":"T6G 1J7",
    "sg:province":"AB",
    "wof:name":"X L Barber Shop",
    "wof:placetype":"venue"
},
  "geometry": {"coordinates":[-113.52011899999999,53.512394],"type":"Point"}
}