{
  "type": "Feature",
  "properties": {
    "iso:country":"CA",
    "sg:address":"1341 Lapchuk Cres",
    "sg:city":"Regina",
    "sg:classifiers":[
        {
            "category":"Building & Trades",
            "subcategory":"Construction",
            "type":"Services"
        }
    ],
    "sg:phone":"+1 306 546 5353",
    "sg:postcode":"S4X 4K6",
    "sg:province":"SK",
    "sg:tags":[
        "general",
        "contractor"
    ],
    "wof:name":"Yakobovich Homes",
    "wof:placetype":"venue"
},
  "geometry": {"coordinates":[-104.658210754,50.5001907349],"type":"Point"}
}