{
  "type": "Feature",
  "properties": {
    "addr:full":"2867 White Lake Rd Tappen BC V0E 2X0",
    "addr:housenumber":"2867",
    "addr:postcode":"v0e 2x0",
    "addr:street":"White Lake Rd",
    "iso:country":"CA",
    "sg:address":"2867 White Lake Rd",
    "sg:city":"Tappen",
    "sg:classifiers":[
        {
            "category":"Travel",
            "subcategory":"Campground",
            "type":"Entertainment"
        }
    ],
    "sg:phone":"+1 250 835 8686",
    "sg:postcode":"V0E 2X0",
    "sg:province":"BC",
    "wof:name":"Sunny Shore Resort",
    "wof:placetype":"venue"
},
  "geometry": {"coordinates":[-119.349212647,50.7808265686],"type":"Point"}
}