{
  "type": "Feature",
  "properties": {
    "addr:full":"731 Railway Ave Canmore AB T1W 1P2",
    "addr:housenumber":"731",
    "addr:postcode":"t1w 1p2",
    "addr:street":"Railway Ave",
    "iso:country":"CA",
    "sg:address":"731 Railway Ave",
    "sg:city":"Canmore",
    "sg:classifiers":[
        {
            "category":"Home & Garden",
            "subcategory":"Building Materials",
            "type":"Retail Goods"
        }
    ],
    "sg:phone":"+1 403 678 4588",
    "sg:postcode":"T1W 1P2",
    "sg:province":"AB",
    "sg:tags":[
        "glass",
        "window",
        "plate"
    ],
    "wof:name":"Canmore Glass & Screen Ltd",
    "wof:placetype":"venue"
},
  "geometry": {"coordinates":[-115.351005554,51.0881690979],"type":"Point"}
}