{
  "type": "Feature",
  "properties": {
    "iso:country":"CA",
    "sg:address":"500 Boul Des Laurentides",
    "sg:city":"Piedmont",
    "sg:classifiers":[
        {
            "category":"Retail",
            "subcategory":"Car Wash",
            "type":"Services"
        }
    ],
    "sg:phone":"+1 450 227 6473",
    "sg:postcode":"J0R 1K0",
    "sg:province":"QC",
    "sg:tags":[
        "polishing",
        "washing"
    ],
    "wof:name":"Lave Auto Bo-Car",
    "wof:placetype":"venue"
},
  "geometry": {"coordinates":[-74.118522644,45.8930053711],"type":"Point"}
}