{
  "type": "Feature",
  "properties": {
    "addr:full":"5042 Still Creek Ave Burnaby BC V5C 4E4",
    "addr:housenumber":"5042",
    "addr:postcode":"v5c 4e4",
    "addr:street":"Still Creek Ave",
    "iso:country":"CA",
    "sg:address":"5042 Still Creek Ave",
    "sg:city":"Burnaby",
    "sg:classifiers":[
        {
            "category":"Manufacturing",
            "subcategory":"Metals",
            "type":"Manufacturing & Wholesale Goods"
        }
    ],
    "sg:phone":"+1 604 299 8191",
    "sg:postcode":"V5C 4E4",
    "sg:province":"BC",
    "sg:tags":[
        "steel"
    ],
    "wof:name":"W M Fabricating Ltd",
    "wof:placetype":"venue"
},
  "geometry": {"coordinates":[-122.990646,49.260719],"type":"Point"}
}