{
  "type": "Feature",
  "properties": {
    "iso:country":"CA",
    "sg:address":"570 Bloor St W",
    "sg:city":"Toronto",
    "sg:classifiers":[
        {
            "category":"Real Estate",
            "subcategory":"Real Estate Agent",
            "type":"Services"
        }
    ],
    "sg:phone":"+1 416 588 6777",
    "sg:postcode":"M6G 1K1",
    "sg:province":"ON",
    "wof:name":"Remax West Realty Inc",
    "wof:placetype":"venue"
},
  "geometry": {"coordinates":[-79.412003,43.665089],"type":"Point"}
}