{
  "type": "Feature",
  "properties": {
    "addr:full":"5915 Todd Rd Kamloops BC V2C 6P2",
    "addr:housenumber":"5915",
    "addr:postcode":"bc v2c 6p2",
    "addr:street":"Todd Rd",
    "iso:country":"CA",
    "sg:address":"5915 Todd Rd",
    "sg:city":"Kamloops",
    "sg:classifiers":[
        {
            "category":"Building & Trades",
            "subcategory":"Landscaping Services",
            "type":"Services"
        }
    ],
    "sg:phone":"+1 250 573 4114",
    "sg:postcode":"V2C 6P2",
    "sg:province":"BC",
    "sg:tags":[
        "landscape",
        "contractor"
    ],
    "wof:name":"Marshall Landscapes Ltd",
    "wof:placetype":"venue"
},
  "geometry": {"coordinates":[-120.166252,50.648087],"type":"Point"}
}