{
  "type": "Feature",
  "properties": {
    "iso:country":"CA",
    "sg:city":"Coquitlam",
    "sg:classifiers":[
        {
            "category":"Real Estate",
            "subcategory":"Developer",
            "type":"Services"
        }
    ],
    "sg:phone":"+1 604 552 1980",
    "sg:postcode":"V3B 6B4",
    "sg:province":"BC",
    "sg:tags":[
        "company",
        "land"
    ],
    "wof:name":"Kempe-West Enterprises Ltd",
    "wof:placetype":"venue"
},
  "geometry": {"coordinates":[-122.792167664,49.2789916992],"type":"Point"}
}