{
  "type": "Feature",
  "properties": {
    "iso:country":"CA",
    "sg:city":"Barrhead",
    "sg:classifiers":[
        {
            "category":"Banks & Credit Unions",
            "subcategory":"Bank",
            "type":"Services"
        }
    ],
    "sg:phone":"+1 780 674 3345",
    "sg:postcode":"T7N 1A4",
    "sg:province":"AB",
    "wof:name":"Common Wealth Credit Union Ltd",
    "wof:placetype":"venue"
},
  "geometry": {"coordinates":[-114.40418243400001,54.1184997559],"type":"Point"}
}