{
  "type": "Feature",
  "properties": {
    "iso:country":"CA",
    "sg:address":"258 Ch DE LA Grande-Cote",
    "sg:city":"Saint-Eustache",
    "sg:classifiers":[
        {
            "category":"Shopping",
            "type":"Retail Goods"
        }
    ],
    "sg:phone":"+1 450 472 3737",
    "sg:postcode":"J7P 1B9",
    "sg:province":"QC",
    "sg:tags":[
        "trophy",
        "medal",
        "award"
    ],
    "wof:name":"Trophee Promo-Plus",
    "wof:placetype":"venue"
},
  "geometry": {"coordinates":[-73.868812561,45.5708580017],"type":"Point"}
}