{
  "type": "Feature",
  "properties": {
    "addr:full":"140 Rue Saint-Aime Louiseville QC J5V 2B1",
    "addr:housenumber":"140",
    "addr:postcode":"j5v 2b1",
    "addr:street":"Rue Saint-Aime",
    "iso:country":"CA",
    "sg:address":"140 Rue Saint-Aime",
    "sg:city":"Louiseville",
    "sg:classifiers":[
        {
            "category":"Retail",
            "subcategory":"Funeral Services",
            "type":"Services"
        }
    ],
    "sg:phone":"+1 819 228 4822",
    "sg:postcode":"J5V 2B1",
    "sg:province":"QC",
    "sg:tags":[
        "director",
        "monument"
    ],
    "wof:name":"Louis Richard & Fils Ltee",
    "wof:placetype":"venue"
},
  "geometry": {"coordinates":[-72.94323,46.257862],"type":"Point"}
}