{
  "type": "Feature",
  "properties": {
    "addr:full":"5020 72 Ave NW Edmonton AB T6B 3H4",
    "addr:housenumber":"5020",
    "addr:postcode":"t6b 3h4",
    "addr:street":"72 Ave Nw",
    "iso:country":"CA",
    "sg:address":"5020 72 Ave NW",
    "sg:city":"Edmonton",
    "sg:classifiers":[
        {
            "category":"Home & Garden",
            "subcategory":"Household Appliances",
            "type":"Retail Goods"
        }
    ],
    "sg:phone":"+1 780 469 5336",
    "sg:postcode":"T6B 3H4",
    "sg:province":"AB",
    "sg:tags":[
        "air",
        "room",
        "conditioning"
    ],
    "wof:name":"J & L Appliance Sales Svc Prts",
    "wof:placetype":"venue"
},
  "geometry": {"coordinates":[-113.41870880099999,53.5082931519],"type":"Point"}
}