{
  "type": "Feature",
  "properties": {
    "addr:full":"Drayton Valley AB T7A 1S4",
    "addr:postcode":"t7a 1s4",
    "addr:street":"Drayton",
    "iso:country":"CA",
    "sg:city":"Drayton Valley",
    "sg:classifiers":[
        {
            "category":"Professional",
            "subcategory":"Management & Consulting",
            "type":"Services"
        }
    ],
    "sg:phone":"+1 780 542 9191",
    "sg:postcode":"T7A 1S4",
    "sg:province":"AB",
    "sg:tags":[
        "consultant",
        "safety"
    ],
    "wof:name":"Summit Safety Inc",
    "wof:placetype":"venue"
},
  "geometry": {"coordinates":[-114.98494700000001,53.22686],"type":"Point"}
}