{
  "type": "Feature",
  "properties": {
    "addr:full":"167 Rue Champlain Saint-Jean-Sur-Richelieu QC J3B 6V5",
    "addr:housenumber":"167",
    "addr:postcode":"j3b 6v5",
    "addr:street":"Rue Champlain",
    "iso:country":"CA",
    "sg:address":"167 Rue Champlain",
    "sg:city":"Saint-Jean-Sur-Richelieu",
    "sg:classifiers":[
        {
            "category":"Health Services",
            "subcategory":"Doctor",
            "type":"Services"
        }
    ],
    "sg:phone":"+1 450 347 3733",
    "sg:postcode":"J3B 6V5",
    "sg:province":"QC",
    "sg:tags":[
        "clinic"
    ],
    "wof:name":"Clinique Medicale Centre Ville",
    "wof:placetype":"venue"
},
  "geometry": {"coordinates":[-73.251976,45.305412],"type":"Point"}
}