{
  "type": "Feature",
  "properties": {
    "iso:country":"CA",
    "sg:address":"100 Rue Principale",
    "sg:city":"Clarenceville",
    "sg:classifiers":[
        {
            "category":"Organizations",
            "subcategory":"Professional Association",
            "type":"Services"
        }
    ],
    "sg:phone":"+1 450 294 2646",
    "sg:postcode":"J0J 1B0",
    "sg:province":"QC",
    "wof:name":"Centre D'Action Benevole",
    "wof:placetype":"venue"
},
  "geometry": {"coordinates":[-73.172996521,45.0470199585],"type":"Point"}
}