{
  "type": "Feature",
  "properties": {
    "addr:full":"1728 Rue Principale Saint-Philemon QC G0R 4A0",
    "addr:housenumber":"1728",
    "addr:postcode":"g0r 4a0",
    "addr:street":"Rue Principale",
    "iso:country":"CA",
    "sg:address":"1728 Rue Principale",
    "sg:city":"Saint-Philemon",
    "sg:classifiers":[
        {
            "category":"Retail",
            "subcategory":"Auto Repair",
            "type":"Services"
        }
    ],
    "sg:phone":"+1 418 469 3136",
    "sg:postcode":"G0R 4A0",
    "sg:province":"QC",
    "sg:tags":[
        "repairing",
        "automobile"
    ],
    "wof:name":"Garage Daniel Bouffard",
    "wof:placetype":"venue"
},
  "geometry": {"coordinates":[-70.443832,46.674908],"type":"Point"}
}