{
  "type": "Feature",
  "properties": {
    "addr:full":"510 Rue Boyd Lachute QC J8H 1E7",
    "addr:housenumber":"510",
    "addr:postcode":"j8h 1e7",
    "addr:street":"Rue Boyd",
    "iso:country":"CA",
    "sg:address":"510 Rue Boyd",
    "sg:city":"Lachute",
    "sg:classifiers":[
        {
            "category":"Manufacturing",
            "subcategory":"Glass & Minerals",
            "type":"Manufacturing & Wholesale Goods"
        }
    ],
    "sg:phone":"+1 450 562 1477",
    "sg:postcode":"J8H 1E7",
    "sg:province":"QC",
    "sg:tags":[
        "fabricator",
        "fiber"
    ],
    "wof:name":"Fibres DE Verres & Psp Inc",
    "wof:placetype":"venue"
},
  "geometry": {"coordinates":[-74.329926,45.651005],"type":"Point"}
}