{
  "type": "Feature",
  "properties": {
    "addr:full":"23 Green Acres Cres Grand Bend ON N0M 1T0",
    "addr:housenumber":"23",
    "addr:postcode":"n0m 1t0",
    "addr:street":"Green Acres Cres",
    "iso:country":"CA",
    "sg:address":"23 Green Acres Cres",
    "sg:city":"Grand Bend",
    "sg:classifiers":[
        {
            "category":"Building & Trades",
            "subcategory":"Construction",
            "type":"Services"
        }
    ],
    "sg:phone":"+1 519 238 5600",
    "sg:postcode":"N0M 1T0",
    "sg:province":"ON",
    "sg:tags":[
        "contractor",
        "general"
    ],
    "wof:name":"Pineridge Construction",
    "wof:placetype":"venue"
},
  "geometry": {"coordinates":[-81.75804100000001,43.307716],"type":"Point"}
}