{
  "type": "Feature",
  "properties": {
    "addr:full":"Winnipeg MB R3E 2V7",
    "addr:postcode":"r3e 2v7",
    "iso:country":"CA",
    "sg:city":"Winnipeg",
    "sg:classifiers":[
        {
            "category":"Wholesale",
            "subcategory":"Chemicals & Plastics",
            "type":"Manufacturing & Wholesale Goods"
        }
    ],
    "sg:phone":"+1 204 989 4790",
    "sg:postcode":"R3E 2V7",
    "sg:province":"MB",
    "wof:name":"Gardex Chemicals Ltd",
    "wof:placetype":"venue"
},
  "geometry": {"coordinates":[-97.186493,49.905376],"type":"Point"}
}