{
  "type": "Feature",
  "properties": {
    "addr:full":"Toronto ON M5V 2J1",
    "addr:postcode":"m5v 2j1",
    "iso:country":"CA",
    "sg:city":"Toronto",
    "sg:classifiers":[
        {
            "category":"Professional",
            "subcategory":"Advertising",
            "type":"Services"
        }
    ],
    "sg:phone":"+1 416 591 2444",
    "sg:postcode":"M5V 2J1",
    "sg:province":"ON",
    "sg:tags":[
        "counselor"
    ],
    "wof:name":"What's the Big Idea",
    "wof:placetype":"venue"
},
  "geometry": {"coordinates":[-79.393967,43.643761],"type":"Point"}
}