{
  "type": "Feature",
  "properties": {
    "addr:full":"Scarborough ON M1V 4T5",
    "addr:postcode":"m1v 4t5",
    "iso:country":"CA",
    "sg:city":"Scarborough",
    "sg:classifiers":[
        {
            "category":"Manufacturing",
            "subcategory":"Printing",
            "type":"Manufacturing & Wholesale Goods"
        }
    ],
    "sg:phone":"+1 416 291 8457",
    "sg:postcode":"M1V 4T5",
    "sg:province":"ON",
    "sg:tags":[
        "printer"
    ],
    "wof:name":"Royal Crest Printing",
    "wof:placetype":"venue"
},
  "geometry": {"coordinates":[-79.3030471802,43.8186759949],"type":"Point"}
}