{
  "type": "Feature",
  "properties": {
    "addr:full":"5950 Boul Cousineau Saint-Hubert QC J3Y 7R9",
    "addr:housenumber":"5950",
    "addr:postcode":"j3y 7r9",
    "addr:street":"Boul Cousineau",
    "iso:country":"CA",
    "sg:address":"5950 Boul Cousineau",
    "sg:city":"Saint-Hubert",
    "sg:classifiers":[
        {
            "category":"Retail",
            "subcategory":"Laundry & Dry Cleaning",
            "type":"Services"
        }
    ],
    "sg:phone":"+1 450 656 7980",
    "sg:postcode":"J3Y 7R9",
    "sg:province":"QC",
    "sg:tags":[
        "cleaners"
    ],
    "wof:name":"Nettoyeur Champlain",
    "wof:placetype":"venue"
},
  "geometry": {"coordinates":[-73.4097290039,45.4957084656],"type":"Point"}
}