{
  "type": "Feature",
  "properties": {
    "addr:full":"132 Algoma St S Thunder Bay ON P7B 3B8",
    "addr:housenumber":"132",
    "addr:postcode":"p7b 3b8",
    "addr:street":"Algoma St S",
    "iso:country":"CA",
    "sg:address":"132 Algoma St S",
    "sg:city":"Thunder Bay",
    "sg:classifiers":[
        {
            "category":"Recreation",
            "type":"Entertainment"
        }
    ],
    "sg:phone":"+1 807 345 5511",
    "sg:postcode":"P7B 3B8",
    "sg:province":"ON",
    "sg:tags":[
        "caterer",
        "hall",
        "auditorium"
    ],
    "wof:name":"Italian Cultural Ctr",
    "wof:placetype":"venue"
},
  "geometry": {"coordinates":[-89.22863,48.432796],"type":"Point"}
}