{
  "type": "Feature",
  "properties": {
    "addr:full":"224 Rue Des Laurentides Chicoutimi QC G7H 7X8",
    "addr:housenumber":"224",
    "addr:postcode":"g7h 7x8",
    "addr:street":"Rue Des Laurentides",
    "iso:country":"CA",
    "sg:address":"224 Rue Des Laurentides",
    "sg:city":"Chicoutimi",
    "sg:classifiers":[
        {
            "category":"Sports & Exercise",
            "subcategory":"Bowling",
            "type":"Entertainment"
        }
    ],
    "sg:phone":"+1 418 690 0300",
    "sg:postcode":"G7H 7X8",
    "sg:province":"QC",
    "sg:tags":[
        "center"
    ],
    "wof:name":"Royaume Du Quilleur Chicoutimi",
    "wof:placetype":"venue"
},
  "geometry": {"coordinates":[-71.06426999999999,48.399105],"type":"Point"}
}