{
  "type": "Feature",
  "properties": {
    "addr:full":"2600 John St # 108 Markham ON L3R 3W3",
    "addr:housenumber":"2600",
    "addr:postcode":"l3r 3w3",
    "addr:street":"John St # 108",
    "iso:country":"CA",
    "sg:address":"2600 John St # 108",
    "sg:city":"Markham",
    "sg:classifiers":[
        {
            "category":"Building & Trades",
            "subcategory":"Construction",
            "type":"Services"
        }
    ],
    "sg:phone":"+1 905 479 4516",
    "sg:postcode":"L3R 3W3",
    "sg:province":"ON",
    "sg:tags":[
        "general",
        "contractor"
    ],
    "wof:name":"Land Construction CO Ltd",
    "wof:placetype":"venue"
},
  "geometry": {"coordinates":[-79.3617935181,43.8243408203],"type":"Point"}
}