{
  "type": "Feature",
  "properties": {
    "addr:full":"1245 Boul Saint-Jean-Baptiste Pointe-Aux-Trembles QC H1B 4A2",
    "addr:housenumber":"1245",
    "addr:postcode":"h1b 4a2",
    "addr:street":"Boul Saint-Jean-Baptiste",
    "iso:country":"CA",
    "sg:address":"1245 Boul Saint-Jean-Baptiste",
    "sg:city":"Pointe-Aux-Trembles",
    "sg:classifiers":[
        {
            "category":"Personal",
            "subcategory":"Beauty Salon",
            "type":"Services"
        }
    ],
    "sg:phone":"+1 514 645 2097",
    "sg:postcode":"H1B 4A2",
    "sg:province":"QC",
    "wof:name":"Salon D'Esthetique Roseline",
    "wof:placetype":"venue"
},
  "geometry": {"coordinates":[-73.50132751460001,45.641910553],"type":"Point"}
}