{
  "type": "Feature",
  "properties": {
    "addr:full":"1 Pembroke St E Pembroke ON K8A 6X3",
    "addr:housenumber":"1",
    "addr:postcode":"k8a 6x3",
    "addr:street":"Pembroke St E",
    "iso:country":"CA",
    "sg:address":"1 Pembroke St E",
    "sg:city":"Pembroke",
    "sg:classifiers":[
        {
            "category":"Government",
            "subcategory":"Office",
            "type":"Public Place"
        }
    ],
    "sg:phone":"+1 613 735 6821",
    "sg:postcode":"K8A 6X3",
    "sg:province":"ON",
    "sg:tags":[
        "village"
    ],
    "wof:name":"Pembroke Municipal Offices",
    "wof:placetype":"venue"
},
  "geometry": {"coordinates":[-77.110733,45.826756],"type":"Point"}
}