{
  "type": "Feature",
  "properties": {
    "addr:full":"120 Hunter St E Peterborough ON K9H 1G6",
    "addr:housenumber":"120",
    "addr:postcode":"k9h 1g6",
    "addr:street":"Hunter St E",
    "iso:country":"CA",
    "sg:address":"120 Hunter St E",
    "sg:city":"Peterborough",
    "sg:classifiers":[
        {
            "category":"Shopping",
            "subcategory":"Hobbies, Toys, & Games",
            "type":"Retail Goods"
        }
    ],
    "sg:phone":"+1 705 742 6083",
    "sg:postcode":"K9H 1G6",
    "sg:province":"ON",
    "sg:tags":[
        "craft",
        "supply"
    ],
    "wof:name":"Ashburnham Crafting Supplies",
    "wof:placetype":"venue"
},
  "geometry": {"coordinates":[-78.308556,44.306831],"type":"Point"}
}