{
  "type": "Feature",
  "properties": {
    "iso:country":"CA",
    "sg:address":"434 Rue Champoux",
    "sg:city":"Disraeli",
    "sg:classifiers":[
        {
            "category":"Building & Trades",
            "subcategory":"Cleaning & Sanitation",
            "type":"Services"
        }
    ],
    "sg:phone":"+1 418 449 2812",
    "sg:postcode":"G0N 1E0",
    "sg:province":"QC",
    "sg:tags":[
        "snow",
        "removal"
    ],
    "wof:name":"Real St-Laurent Construction",
    "wof:placetype":"venue"
},
  "geometry": {"coordinates":[-71.3519515991,45.9047584534],"type":"Point"}
}