{
  "type": "Feature",
  "properties": {
    "addr:full":"738 St Joseph St Winnipeg MB R2H 3A3",
    "addr:housenumber":"738",
    "addr:postcode":"r2h 3a3",
    "addr:street":"St Joseph St",
    "iso:country":"CA",
    "sg:address":"738 St Joseph St",
    "sg:city":"Winnipeg",
    "sg:classifiers":[
        {
            "category":"Manufacturing",
            "subcategory":"Food",
            "type":"Manufacturing & Wholesale Goods"
        }
    ],
    "sg:phone":"+1 204 233 1441",
    "sg:postcode":"R2H 3A3",
    "sg:province":"MB",
    "sg:tags":[
        "product",
        "manufacturer"
    ],
    "wof:name":"Parmalat Canada",
    "wof:placetype":"venue"
},
  "geometry": {"coordinates":[-97.1236343384,49.8944396973],"type":"Point"}
}