{
  "type": "Feature",
  "properties": {
    "addr:full":"12823 58 Ave Surrey BC V3X 2P7",
    "addr:housenumber":"12823",
    "addr:postcode":"v3x 2p7",
    "addr:street":"58 Ave",
    "iso:country":"CA",
    "sg:address":"12823 58 Ave",
    "sg:city":"Surrey",
    "sg:classifiers":[
        {
            "category":"Autos & Motor Vehicles",
            "subcategory":"Fuel & Gas Station",
            "type":"Retail Goods"
        }
    ],
    "sg:phone":"+1 604 543 8505",
    "sg:postcode":"V3X 2P7",
    "sg:province":"BC",
    "sg:tags":[
        "oil"
    ],
    "wof:name":"Panorama Chevron",
    "wof:placetype":"venue"
},
  "geometry": {"coordinates":[-122.866219,49.108318],"type":"Point"}
}