{
  "type": "Feature",
  "properties": {
    "addr:full":"80 Rte 132 E Bonaventure QC G0C 1E0",
    "addr:housenumber":"80",
    "addr:postcode":"g0c 1e0",
    "addr:street":"Rte 132 E",
    "iso:country":"CA",
    "sg:address":"80 Rte 132 E",
    "sg:city":"Bonaventure",
    "sg:classifiers":[
        {
            "category":"Restaurant",
            "type":"Food & Drink"
        }
    ],
    "sg:phone":"+1 418 534 2233",
    "sg:postcode":"G0C 1E0",
    "sg:province":"QC",
    "wof:name":"Dixie Lee",
    "wof:placetype":"venue"
},
  "geometry": {"coordinates":[-65.4762420654,48.0406532288],"type":"Point"}
}