{
  "type": "Feature",
  "properties": {
    "addr:full":"232 Wellington St W Virden MB R0M 2C0",
    "addr:housenumber":"232",
    "addr:postcode":"r0m 2c0",
    "addr:street":"Wellington St W Virden",
    "iso:country":"CA",
    "sg:address":"232 Wellington St W",
    "sg:city":"Virden",
    "sg:classifiers":[
        {
            "category":"Government",
            "subcategory":"Office",
            "type":"Public Place"
        }
    ],
    "sg:phone":"+1 204 748 4288",
    "sg:postcode":"R0M 2C0",
    "sg:province":"MB",
    "wof:name":"Manitoba Justice",
    "wof:placetype":"venue"
},
  "geometry": {"coordinates":[-100.91971599999999,49.856026],"type":"Point"}
}