{
  "type": "Feature",
  "properties": {
    "addr:full":"117 Rue Front Aylmer QC J9H 5S9",
    "addr:housenumber":"117",
    "addr:postcode":"j9h 5s9",
    "addr:street":"Rue Front",
    "iso:country":"CA",
    "sg:address":"117 Rue Front",
    "sg:city":"Aylmer",
    "sg:classifiers":[
        {
            "category":"Professional",
            "subcategory":"Business Services",
            "type":"Services"
        }
    ],
    "sg:phone":"+1 819 684 8299",
    "sg:postcode":"J9H 5S9",
    "sg:province":"QC",
    "sg:tags":[
        "notary"
    ],
    "wof:name":"Monnet, Bernard",
    "wof:placetype":"venue"
},
  "geometry": {"coordinates":[-75.85494199999999,45.404068],"type":"Point"}
}