{
  "type": "Feature",
  "properties": {
    "addr:full":"10519 101 Ave Fort St John BC V1J 2B7",
    "addr:housenumber":"10519",
    "addr:postcode":"v1j 2b7",
    "addr:street":"101 Ave",
    "iso:country":"CA",
    "sg:address":"10519 101 Ave",
    "sg:city":"Fort St John",
    "sg:classifiers":[
        {
            "category":"Shopping",
            "subcategory":"Computers & Home Electronics",
            "type":"Retail Goods"
        }
    ],
    "sg:phone":"+1 250 785 0383",
    "sg:postcode":"V1J 2B7",
    "sg:province":"BC",
    "sg:tags":[
        "equipment",
        "dealer"
    ],
    "wof:name":"Nortech Data Svc Ltd",
    "wof:placetype":"venue"
},
  "geometry": {"coordinates":[-120.856163,56.247208],"type":"Point"}
}