{
  "type": "Feature",
  "properties": {
    "addr:full":"15 Erin Woods Blvd SE Calgary AB T2B 2X2",
    "addr:housenumber":"15",
    "addr:postcode":"t2b 2x2",
    "addr:street":"Erin Woods Blvd Se",
    "iso:country":"CA",
    "sg:address":"15 Erin Woods Blvd SE",
    "sg:city":"Calgary",
    "sg:classifiers":[
        {
            "category":"Autos & Motor Vehicles",
            "subcategory":"Fuel & Gas Station",
            "type":"Retail Goods"
        }
    ],
    "sg:phone":"+1 403 272 4220",
    "sg:postcode":"T2B 2X2",
    "sg:province":"AB",
    "sg:tags":[
        "oil"
    ],
    "wof:name":"Erin Woods Petro-Canada",
    "wof:placetype":"venue"
},
  "geometry": {"coordinates":[-113.978706,51.017948],"type":"Point"}
}