{
  "type": "Feature",
  "properties": {
    "addr:full":"3445 Boul Henri-Bourassa E Montreal-Nord QC H1H 5T4",
    "addr:housenumber":"3445",
    "addr:postcode":"h1h 5t4",
    "addr:street":"Boul Henri-Bourassa E",
    "iso:country":"CA",
    "sg:address":"3445 Boul Henri-Bourassa E",
    "sg:city":"Montreal-Nord",
    "sg:classifiers":[
        {
            "category":"Personal",
            "subcategory":"Beauty Salon",
            "type":"Services"
        }
    ],
    "sg:phone":"+1 514 329 1634",
    "sg:postcode":"H1H 5T4",
    "sg:province":"QC",
    "wof:name":"Passeport Beaute",
    "wof:placetype":"venue"
},
  "geometry": {"coordinates":[-73.648788,45.588154],"type":"Point"}
}