{
  "type": "Feature",
  "properties": {
    "iso:country":"CA",
    "sg:address":"5305 Rue Jean-Talon E",
    "sg:city":"Saint-Leonard",
    "sg:classifiers":[
        {
            "category":"Food & Beverages",
            "subcategory":"Groceries & Convenience Stores",
            "type":"Retail Goods"
        }
    ],
    "sg:phone":"+1 514 725 9212",
    "sg:postcode":"H1S 1L4",
    "sg:province":"QC",
    "sg:tags":[
        "grocer"
    ],
    "wof:name":"Intermarche",
    "wof:placetype":"venue"
},
  "geometry": {"coordinates":[-73.5822753906,45.5789604187],"type":"Point"}
}