{
  "type": "Feature",
  "properties": {
    "addr:full":"Vulcan AB T0L 2B0",
    "addr:postcode":"t0l 2b0",
    "iso:country":"CA",
    "sg:city":"Vulcan",
    "sg:classifiers":[
        {
            "category":"Education",
            "subcategory":"School",
            "type":"Public Place"
        }
    ],
    "sg:phone":"+1 403 485 6180",
    "sg:postcode":"T0L 2B0",
    "sg:province":"AB",
    "wof:name":"Vulcan Outreach School",
    "wof:placetype":"venue"
},
  "geometry": {"coordinates":[-112.63977800000001,50.349792],"type":"Point"}
}