{
  "type": "Feature",
  "properties": {
    "addr:full":"Hartney MB R0M 0X0",
    "addr:postcode":"r0m 0x0",
    "iso:country":"CA",
    "sg:city":"Hartney",
    "sg:classifiers":[
        {
            "category":"Government",
            "subcategory":"Office",
            "type":"Public Place"
        }
    ],
    "sg:phone":"+1 204 858 2590",
    "sg:postcode":"R0M 0X0",
    "sg:province":"MB",
    "sg:tags":[
        "village"
    ],
    "wof:name":"Cameron Rural Municipality",
    "wof:placetype":"venue"
},
  "geometry": {"coordinates":[-100.528015,49.477478],"type":"Point"}
}