{
  "type": "Feature",
  "properties": {
    "addr:full":"129 Ch Morgan Coaticook QC J1A 1V6",
    "addr:housenumber":"129",
    "addr:postcode":"j1a 1v6",
    "addr:street":"Ch Morgan",
    "iso:country":"CA",
    "sg:address":"129 Ch Morgan",
    "sg:city":"Coaticook",
    "sg:classifiers":[
        {
            "category":"Farming",
            "subcategory":"Farm",
            "type":"Manufacturing & Wholesale Goods"
        }
    ],
    "sg:phone":"+1 819 849 9293",
    "sg:postcode":"J1A 1V6",
    "sg:province":"QC",
    "wof:name":"Centre D'Initiative En Agrcltr",
    "wof:placetype":"venue"
},
  "geometry": {"coordinates":[-71.8201217651,45.140838623],"type":"Point"}
}