{
  "type": "Feature",
  "properties": {
    "iso:country":"CA",
    "sg:address":"182 University Park Dr",
    "sg:city":"Regina",
    "sg:classifiers":[
        {
            "category":"Health Services",
            "subcategory":"Doctor",
            "type":"Services"
        }
    ],
    "sg:phone":"+1 306 789 5800",
    "sg:postcode":"S4V 1A3",
    "sg:province":"SK",
    "sg:tags":[
        "physician",
        "surgeon"
    ],
    "wof:name":"University Park Medical Clinic",
    "wof:placetype":"venue"
},
  "geometry": {"coordinates":[-104.558197022,50.4319343567],"type":"Point"}
}