{
  "type": "Feature",
  "properties": {
    "addr:full":"Saint-Damase-Des-Aulnaies QC G0R 2X0",
    "addr:postcode":"g0r 2x0",
    "iso:country":"CA",
    "sg:city":"Saint-Damase-Des-Aulnaies",
    "sg:classifiers":[
        {
            "category":"Building & Trades",
            "subcategory":"Construction",
            "type":"Services"
        }
    ],
    "sg:phone":"+1 418 598 6500",
    "sg:postcode":"G0R 2X0",
    "sg:province":"QC",
    "sg:tags":[
        "excavating",
        "contractor"
    ],
    "wof:name":"Fortrac Inc",
    "wof:placetype":"venue"
},
  "geometry": {"coordinates":[-70.1276016235,47.1936149597],"type":"Point"}
}