{
  "type": "Feature",
  "properties": {
    "addr:full":"196 Boul Laurier Laurier-Station QC G0S 1N0",
    "addr:housenumber":"196",
    "addr:postcode":"g0s 1n0",
    "addr:street":"Boul Laurier",
    "iso:country":"CA",
    "sg:address":"196 Boul Laurier",
    "sg:city":"Laurier-Station",
    "sg:classifiers":[
        {
            "category":"Government",
            "subcategory":"Police Station",
            "type":"Public Place"
        }
    ],
    "sg:phone":"+1 ",
    "sg:postcode":"G0S 1N0",
    "sg:province":"QC",
    "sg:tags":[
        "department"
    ],
    "wof:name":"Quebec Surete",
    "wof:placetype":"venue"
},
  "geometry": {"coordinates":[-71.6237945557,46.5436820984],"type":"Point"}
}