{
  "type": "Feature",
  "properties": {
    "addr:full":"1173 North Service Rd E Oakville ON L6H 1A7",
    "addr:housenumber":"1173",
    "addr:postcode":"l6h 1a7",
    "addr:street":"North Service Rd E",
    "iso:country":"CA",
    "sg:address":"1173 North Service Rd E",
    "sg:city":"Oakville",
    "sg:classifiers":[
        {
            "category":"Food & Beverages",
            "subcategory":"Bakery",
            "type":"Retail Goods"
        }
    ],
    "sg:phone":"+1 905 842 8770",
    "sg:postcode":"L6H 1A7",
    "sg:province":"ON",
    "sg:tags":[
        "baker"
    ],
    "wof:name":"Bun King Bakery",
    "wof:placetype":"venue"
},
  "geometry": {"coordinates":[-79.67346999999999,43.474277],"type":"Point"}
}