{
  "type": "Feature",
  "properties": {
    "addr:full":"Deer Lake NL A8A 1A3",
    "addr:postcode":"a8a 1a3",
    "iso:country":"CA",
    "sg:city":"Deer Lake",
    "sg:classifiers":[
        {
            "category":"Restaurant",
            "type":"Food & Drink"
        }
    ],
    "sg:phone":"+1 709 635 3031",
    "sg:postcode":"A8A 1A3",
    "sg:province":"NL",
    "wof:name":"Westons Concessions Ltd",
    "wof:placetype":"venue"
},
  "geometry": {"coordinates":[-57.423664,49.175339],"type":"Point"}
}