{
  "type": "Feature",
  "properties": {
    "iso:country":"CA",
    "sg:address":"1202 2nd St",
    "sg:city":"Estevan",
    "sg:classifiers":[
        {
            "category":"Organizations",
            "subcategory":"Religious Organization",
            "type":"Services"
        }
    ],
    "sg:phone":"+1 306 634 3761",
    "sg:postcode":"S4A 0M2",
    "sg:province":"SK",
    "sg:tags":[
        "church"
    ],
    "wof:name":"Estevan Gospel Chapel",
    "wof:placetype":"venue"
},
  "geometry": {"coordinates":[-102.996711731,49.1387825012],"type":"Point"}
}