{
  "type": "Feature",
  "properties": {
    "addr:full":"900 Boul DE Sainte-Adele Sainte-Adele QC J8B 2N2",
    "addr:housenumber":"900",
    "addr:postcode":"j8b 2n2",
    "addr:street":"Boul De Sainte-Adele Sainte-Adele",
    "iso:country":"CA",
    "sg:address":"900 Boul DE Sainte-Adele",
    "sg:city":"Sainte-Adele",
    "sg:classifiers":[
        {
            "category":"Real Estate",
            "subcategory":"Surveying",
            "type":"Services"
        }
    ],
    "sg:phone":"+1 450 229 4244",
    "sg:postcode":"J8B 2N2",
    "sg:province":"QC",
    "sg:tags":[
        "surveyor"
    ],
    "wof:name":"Beaudry & Jarry",
    "wof:placetype":"venue"
},
  "geometry": {"coordinates":[-74.1159362793,45.9605903625],"type":"Point"}
}