{
  "type": "Feature",
  "properties": {
    "addr:full":"705 Rue Sainte-Catherine O # 2 Montreal QC H3B 4G5",
    "addr:housenumber":"705",
    "addr:postcode":"h3b 4g5",
    "addr:street":"Rue Sainte-Catherine O # 2",
    "iso:country":"CA",
    "sg:address":"705 Rue Sainte-Catherine O # 2",
    "sg:city":"Montreal",
    "sg:classifiers":[
        {
            "category":"Shopping",
            "subcategory":"Clothing, Apparel, & Fashions",
            "type":"Retail Goods"
        }
    ],
    "sg:phone":"+1 514 849 1256",
    "sg:postcode":"H3B 4G5",
    "sg:province":"QC",
    "sg:tags":[
        "item",
        "boutique"
    ],
    "wof:name":"Bikini Village Inc",
    "wof:placetype":"venue"
},
  "geometry": {"coordinates":[-73.5591964722,45.5153617859],"type":"Point"}
}