{
  "type": "Feature",
  "properties": {
    "addr:full":"Trois-Rivieres QC G9A 4L9",
    "addr:postcode":"g9a 4l9",
    "iso:country":"CA",
    "sg:city":"Trois-Rivieres",
    "sg:classifiers":[
        {
            "category":"Social Services",
            "subcategory":"Child Care",
            "type":"Services"
        }
    ],
    "sg:phone":"+1 819 379 6778",
    "sg:postcode":"G9A 4L9",
    "sg:province":"QC",
    "wof:name":"Cpe Mamuse Et Meduque",
    "wof:placetype":"venue"
},
  "geometry": {"coordinates":[-72.552246,46.332897],"type":"Point"}
}