{
  "type": "Feature",
  "properties": {
    "addr:full":"Winnipeg MB R3C 4J9",
    "addr:postcode":"r3c 4j9",
    "iso:country":"CA",
    "sg:city":"Winnipeg",
    "sg:classifiers":[
        {
            "category":"Organizations",
            "subcategory":"Professional Association",
            "type":"Services"
        }
    ],
    "sg:phone":"+1 204 982 6060",
    "sg:postcode":"R3C 4J9",
    "sg:province":"MB",
    "wof:name":"Opticians Association-Canada",
    "wof:placetype":"venue"
},
  "geometry": {"coordinates":[-97.1415863037,49.8956413269],"type":"Point"}
}