{
  "type": "Feature",
  "properties": {
    "addr:full":"430 King St Niagara on the Lake ON L0S 1J0",
    "addr:housenumber":"430",
    "addr:postcode":"l0s 1j0",
    "addr:street":"King St;On",
    "iso:country":"CA",
    "sg:address":"430 King St",
    "sg:city":"Niagara on the Lake",
    "sg:classifiers":[
        {
            "category":"Social Services",
            "subcategory":"Child Care",
            "type":"Services"
        }
    ],
    "sg:phone":"+1 905 468 5357",
    "sg:postcode":"L0S 1J0",
    "sg:province":"ON",
    "sg:tags":[
        "kindergarten",
        "academic",
        "school"
    ],
    "wof:name":"Niagara Nursery School",
    "wof:placetype":"venue"
},
  "geometry": {"coordinates":[-79.07550000000001,43.249638],"type":"Point"}
}