{
  "type": "Feature",
  "properties": {
    "iso:country":"CA",
    "sg:address":"188 Carlton St",
    "sg:city":"Toronto",
    "sg:classifiers":[
        {
            "category":"Social Services",
            "type":"Services"
        }
    ],
    "sg:phone":"+1 416 929 7572",
    "sg:postcode":"M5A 2K8",
    "sg:province":"ON",
    "sg:tags":[
        "organization",
        "welfare"
    ],
    "wof:name":"St Peters Food Bank",
    "wof:placetype":"venue"
},
  "geometry": {"coordinates":[-79.3720321655,43.6634979248],"type":"Point"}
}