{
  "type": "Feature",
  "properties": {
    "addr:full":"2009 Park Royal S West Vancouver BC V7T 2W4",
    "addr:housenumber":"2009",
    "addr:postcode":"v7t 2w4",
    "addr:street":"Park Royal S West",
    "iso:country":"CA",
    "sg:address":"2009 Park Royal S",
    "sg:city":"West Vancouver",
    "sg:classifiers":[
        {
            "category":"Banks & Credit Unions",
            "subcategory":"Bank",
            "type":"Services"
        }
    ],
    "sg:phone":"+1 604 913 0034",
    "sg:postcode":"V7T 2W4",
    "sg:province":"BC",
    "sg:tags":[
        "broker",
        "foreign",
        "dealer",
        "exchange"
    ],
    "wof:name":"Thomas Cook Foreign Exchange",
    "wof:placetype":"venue"
},
  "geometry": {"coordinates":[-123.140098572,49.3244857788],"type":"Point"}
}