{
  "type": "Feature",
  "properties": {
    "iso:country":"CA",
    "sg:address":"55 George St W",
    "sg:city":"Lindsay",
    "sg:classifiers":[
        {
            "category":"Utilities",
            "subcategory":"Cable",
            "type":"Services"
        }
    ],
    "sg:phone":"+1 705 878 9000",
    "sg:postcode":"K9V 4V6",
    "sg:province":"ON",
    "sg:tags":[
        "television"
    ],
    "wof:name":"Lindsay Comcable",
    "wof:placetype":"venue"
},
  "geometry": {"coordinates":[-78.73593139650001,44.3476486206],"type":"Point"}
}