{
  "type": "Feature",
  "properties": {
    "addr:full":"1399 Boul DE LA Grande-Allee Boisbriand QC J7G 2T5",
    "addr:housenumber":"1399",
    "addr:postcode":"j7g 2t5",
    "addr:street":"Boul De La Grande-Allee",
    "iso:country":"CA",
    "sg:address":"1399 Boul DE LA Grande-Allee",
    "sg:city":"Boisbriand",
    "sg:classifiers":[
        {
            "category":"Health Services",
            "subcategory":"Medical Lab",
            "type":"Services"
        }
    ],
    "sg:phone":"+1 450 435 4350",
    "sg:postcode":"J7G 2T5",
    "sg:province":"QC",
    "wof:name":"Laplante, Denis",
    "wof:placetype":"venue"
},
  "geometry": {"coordinates":[-73.8422088623,45.6173553467],"type":"Point"}
}