{
  "type": "Feature",
  "properties": {
    "addr:full":"Riviere-Bleue QC G0L 2B0",
    "addr:postcode":"g0l 2b0",
    "iso:country":"CA",
    "sg:city":"Riviere-Bleue",
    "sg:classifiers":[
        {
            "category":"Bars & Pubs",
            "type":"Food & Drink"
        }
    ],
    "sg:phone":"+1 418 893 2811",
    "sg:postcode":"G0L 2B0",
    "sg:province":"QC",
    "sg:tags":[
        "lounge",
        "cocktail"
    ],
    "wof:name":"Bar Belle Rive",
    "wof:placetype":"venue"
},
  "geometry": {"coordinates":[-69.04409800000001,47.438938],"type":"Point"}
}