{
  "type": "Feature",
  "properties": {
    "addr:full":"141 Main St S Morris MB R0G 1K0",
    "addr:housenumber":"141",
    "addr:postcode":"r0g 1k0",
    "addr:street":"Main St S Morris",
    "iso:country":"CA",
    "sg:address":"141 Main St S",
    "sg:city":"Morris",
    "sg:classifiers":[
        {
            "category":"Organizations",
            "subcategory":"Professional Association",
            "type":"Services"
        }
    ],
    "sg:phone":"+1 204 746 6275",
    "sg:postcode":"R0G 1K0",
    "sg:province":"MB",
    "wof:name":"Morris & Districh Chamber-Cmmr",
    "wof:placetype":"venue"
},
  "geometry": {"coordinates":[-97.364784,49.353542],"type":"Point"}
}