{
  "type": "Feature",
  "properties": {
    "iso:country":"CA",
    "sg:city":"Kilworthy",
    "sg:classifiers":[
        {
            "category":"Professional",
            "subcategory":"Accounting & Tax Preparation",
            "type":"Services"
        }
    ],
    "sg:phone":"+1 705 687 7812",
    "sg:postcode":"P0E 1G0",
    "sg:province":"ON",
    "sg:tags":[
        "bookkeeping",
        "general"
    ],
    "wof:name":"Buck's Business Svc",
    "wof:placetype":"venue"
},
  "geometry": {"coordinates":[-79.3479309082,44.8502349854],"type":"Point"}
}