{
  "type": "Feature",
  "properties": {
    "addr:full":"Uxbridge ON L9P 1R4",
    "addr:postcode":"l9p 1r4",
    "iso:country":"CA",
    "sg:city":"Uxbridge",
    "sg:classifiers":[
        {
            "category":"Retail",
            "subcategory":"Auto Repair",
            "type":"Services"
        }
    ],
    "sg:phone":"+1 905 649 3873",
    "sg:postcode":"L9P 1R4",
    "sg:province":"ON",
    "sg:tags":[
        "repairing",
        "automobile"
    ],
    "wof:name":"Gary Coppins Svc",
    "wof:placetype":"venue"
},
  "geometry": {"coordinates":[-79.12386322019999,44.1061668396],"type":"Point"}
}