{
  "type": "Feature",
  "properties": {
    "addr:full":"Toronto ON M6P 1Y3",
    "addr:postcode":"m6p 1y3",
    "iso:country":"CA",
    "sg:city":"Toronto",
    "sg:classifiers":[
        {
            "category":"Health Services",
            "subcategory":"Doctor",
            "type":"Services"
        }
    ],
    "sg:phone":"+1 416 767 9591",
    "sg:postcode":"M6P 1Y3",
    "sg:province":"ON",
    "sg:tags":[
        "dentist"
    ],
    "wof:name":"Chen, Yule DDS",
    "wof:placetype":"venue"
},
  "geometry": {"coordinates":[-79.46133399999999,43.665394],"type":"Point"}
}