{
  "type": "Feature",
  "properties": {
    "iso:country":"CA",
    "sg:city":"Winnipeg",
    "sg:classifiers":[
        {
            "category":"Retail",
            "subcategory":"Veterinary Services",
            "type":"Services"
        }
    ],
    "sg:phone":"+1 204 589 8381",
    "sg:postcode":"R2V 3M5",
    "sg:province":"MB",
    "sg:tags":[
        "veterinarian"
    ],
    "wof:name":"Stockburger, R DVM",
    "wof:placetype":"venue"
},
  "geometry": {"coordinates":[-97.149612,49.950703],"type":"Point"}
}