{
  "type": "Feature",
  "properties": {
    "iso:country":"CA",
    "sg:address":"20538 Fraser Hwy",
    "sg:city":"Langley",
    "sg:classifiers":[
        {
            "category":"Organizations",
            "subcategory":"Professional Association",
            "type":"Services"
        }
    ],
    "sg:phone":"+1 604 534 2737",
    "sg:postcode":"V3A 4G2",
    "sg:province":"BC",
    "wof:name":"Sexual Abuse Support Svc",
    "wof:placetype":"venue"
},
  "geometry": {"coordinates":[-122.653640747,49.1039543152],"type":"Point"}
}