{
  "type": "Feature",
  "properties": {
    "addr:full":"167 Rue Saint-Jean-Baptiste Granby QC J2G 7W1",
    "addr:housenumber":"167",
    "addr:postcode":"j2g 7w1",
    "addr:street":"Rue Saint-Jean-Baptiste",
    "iso:country":"CA",
    "sg:address":"167 Rue Saint-Jean-Baptiste",
    "sg:city":"Granby",
    "sg:classifiers":[
        {
            "category":"Arts & Performance",
            "subcategory":"Theater",
            "type":"Entertainment"
        }
    ],
    "sg:phone":"+1 450 777 1977",
    "sg:postcode":"J2G 7W1",
    "sg:province":"QC",
    "sg:tags":[
        "mobile",
        "discotheque"
    ],
    "wof:name":"Musitech K-Danse Enr",
    "wof:placetype":"venue"
},
  "geometry": {"coordinates":[-72.74850499999999,45.401093],"type":"Point"}
}