{
  "type": "Feature",
  "properties": {
    "addr:full":"35 Trottier Bay Winnipeg MB R3T 3R3",
    "addr:housenumber":"35",
    "addr:postcode":"r3t 3r3",
    "addr:street":"Trottier Bay",
    "iso:country":"CA",
    "sg:address":"35 Trottier Bay",
    "sg:city":"Winnipeg",
    "sg:classifiers":[
        {
            "category":"Manufacturing",
            "subcategory":"Tools & Machinery",
            "type":"Manufacturing & Wholesale Goods"
        }
    ],
    "sg:phone":"+1 204 453 2477",
    "sg:postcode":"R3T 3R3",
    "sg:province":"MB",
    "sg:tags":[
        "farm",
        "equipment",
        "cutting",
        "gear"
    ],
    "wof:name":"Omega Drives Inc",
    "wof:placetype":"venue"
},
  "geometry": {"coordinates":[-97.16245269780001,49.8271179199],"type":"Point"}
}