{
  "type": "Feature",
  "properties": {
    "iso:country":"CA",
    "sg:address":"3739 Shoecove Rd",
    "sg:city":"LA Scie",
    "sg:classifiers":[
        {
            "category":"Shopping",
            "subcategory":"Bicycles & Sporting Goods",
            "type":"Retail Goods"
        }
    ],
    "sg:phone":"+1 709 675 2060",
    "sg:postcode":"A0K 3M0",
    "sg:province":"NL",
    "sg:tags":[
        "tackle",
        "fishing"
    ],
    "wof:name":"Cape John Industries Ltd",
    "wof:placetype":"venue"
},
  "geometry": {"coordinates":[-55.5948295593,49.9541816711],"type":"Point"}
}