{
  "type": "Feature",
  "properties": {
    "addr:full":"70 Dickinson Dr Ingleside ON K0C 1M0",
    "addr:housenumber":"70",
    "addr:postcode":"k0c 1m0",
    "addr:street":"Dickinson Dr",
    "iso:country":"CA",
    "sg:address":"70 Dickinson Dr",
    "sg:city":"Ingleside",
    "sg:classifiers":[
        {
            "category":"Manufacturing",
            "subcategory":"Food",
            "type":"Manufacturing & Wholesale Goods"
        }
    ],
    "sg:phone":"+1 613 537 2226",
    "sg:postcode":"K0C 1M0",
    "sg:province":"ON",
    "sg:tags":[
        "grocer",
        "product",
        "manufacturer"
    ],
    "wof:name":"Kraft Canada Inc",
    "wof:placetype":"venue"
},
  "geometry": {"coordinates":[-74.9922714233,45.003780365],"type":"Point"}
}