{
  "type": "Feature",
  "properties": {
    "iso:country":"CA",
    "sg:address":"1170 Ch DE Chambly",
    "sg:city":"Longueuil",
    "sg:classifiers":[
        {
            "category":"Restaurant",
            "type":"Food & Drink"
        }
    ],
    "sg:phone":"+1 450 677 2801",
    "sg:postcode":"J4J 3W6",
    "sg:province":"QC",
    "wof:name":"Restaurant Supreme Pizzeria",
    "wof:placetype":"venue"
},
  "geometry": {"coordinates":[-73.4907073975,45.5330848694],"type":"Point"}
}