{
  "type": "Feature",
  "properties": {
    "addr:full":"Emsdale ON P0A 1J0",
    "addr:postcode":"p0a 1j0",
    "iso:country":"CA",
    "sg:city":"Emsdale",
    "sg:classifiers":[
        {
            "category":"Education",
            "subcategory":"Library",
            "type":"Public Place"
        }
    ],
    "sg:phone":"+1 705 636 5454",
    "sg:postcode":"P0A 1J0",
    "sg:province":"ON",
    "wof:name":"Perry Twp Public Library",
    "wof:placetype":"venue"
},
  "geometry": {"coordinates":[-79.31875599999999,45.528534],"type":"Point"}
}