{
  "type": "Feature",
  "properties": {
    "iso:country":"CA",
    "sg:city":"Matheson",
    "sg:classifiers":[
        {
            "category":"Restaurant",
            "type":"Food & Drink"
        }
    ],
    "sg:phone":"+1 705 273 2944",
    "sg:postcode":"P0K 1N0",
    "sg:province":"ON",
    "sg:tags":[
        "auditorium",
        "rooms",
        "banquet",
        "hall"
    ],
    "wof:name":"Shillington Community Ctr",
    "wof:placetype":"venue"
},
  "geometry": {"coordinates":[-80.4639968872,48.5354232788],"type":"Point"}
}