{
  "type": "Feature",
  "properties": {
    "addr:full":"Cobourg ON K9A 5H7",
    "addr:postcode":"k9a 5h7",
    "iso:country":"CA",
    "sg:city":"Cobourg",
    "sg:classifiers":[
        {
            "category":"Shopping",
            "subcategory":"Tobacco",
            "type":"Retail Goods"
        }
    ],
    "sg:phone":"+1 905 373 4895",
    "sg:postcode":"K9A 5H7",
    "sg:province":"ON",
    "sg:tags":[
        "cigarette",
        "cigar",
        "dealer"
    ],
    "wof:name":"Cigar Store",
    "wof:placetype":"venue"
},
  "geometry": {"coordinates":[-78.202286,43.970566],"type":"Point"}
}