{
  "type": "Feature",
  "properties": {
    "addr:full":"340 Rte 108 Cookshire QC J0B 1M0",
    "addr:housenumber":"340",
    "addr:postcode":"j0b 1m0",
    "addr:street":"Rte 108 Cookshire",
    "iso:country":"CA",
    "sg:address":"340 Rte 108",
    "sg:city":"Cookshire",
    "sg:classifiers":[
        {
            "category":"Retail",
            "subcategory":"Repair Shop",
            "type":"Services"
        }
    ],
    "sg:phone":"+1 819 875 3684",
    "sg:postcode":"J0B 1M0",
    "sg:province":"QC",
    "sg:tags":[
        "appliance"
    ],
    "wof:name":"Boulet Service",
    "wof:placetype":"venue"
},
  "geometry": {"coordinates":[-71.6888656616,45.3726615906],"type":"Point"}
}