{
  "type": "Feature",
  "properties": {
    "addr:full":"30 Prince Edward St Saint John NB E2L 4M5",
    "addr:housenumber":"30",
    "addr:postcode":"nb e2l 4m5",
    "addr:street":"Prince Edward St",
    "iso:country":"CA",
    "sg:address":"30 Prince Edward St",
    "sg:city":"Saint John",
    "sg:classifiers":[
        {
            "category":"Health Services",
            "subcategory":"Doctor",
            "type":"Services"
        }
    ],
    "sg:phone":"+1 506 633 0189",
    "sg:postcode":"E2L 4M5",
    "sg:province":"NB",
    "sg:tags":[
        "physiotherapist",
        "clinic"
    ],
    "wof:name":"Bay City Physiotherapy Clinic",
    "wof:placetype":"venue"
},
  "geometry": {"coordinates":[-66.0556488037,45.2759780884],"type":"Point"}
}