{
  "type": "Feature",
  "properties": {
    "addr:full":"15152 North Bluff Rd White Rock BC V4B 3E5",
    "addr:housenumber":"15152",
    "addr:postcode":"v4b 3e5",
    "addr:street":"North Bluff Rd",
    "iso:country":"CA",
    "sg:address":"15152 North Bluff Rd",
    "sg:city":"White Rock",
    "sg:classifiers":[
        {
            "category":"Personal",
            "subcategory":"Beauty Salon",
            "type":"Services"
        }
    ],
    "sg:phone":"+1 604 536 5154",
    "sg:postcode":"V4B 3E5",
    "sg:province":"BC",
    "sg:tags":[
        "barber"
    ],
    "wof:name":"Central Plaza Barbers",
    "wof:placetype":"venue"
},
  "geometry": {"coordinates":[-122.80239899999999,49.030987],"type":"Point"}
}