{
  "type": "Feature",
  "properties": {
    "iso:country":"CA",
    "sg:address":"2405 Rue DE LA Metallurgie",
    "sg:city":"Jonquiere",
    "sg:classifiers":[
        {
            "category":"Manufacturing",
            "subcategory":"Chemicals & Compounds",
            "type":"Manufacturing & Wholesale Goods"
        }
    ],
    "sg:phone":"+1 418 542 6863",
    "sg:postcode":"G7X 9V8",
    "sg:province":"QC",
    "sg:tags":[
        "control",
        "pest",
        "supply"
    ],
    "wof:name":"Extermination Tremblay-Lemieux",
    "wof:placetype":"venue"
},
  "geometry": {"coordinates":[-71.230217,48.405697],"type":"Point"}
}