{
  "type": "Feature",
  "properties": {
    "addr:full":"Scarborough ON M1R 5A8",
    "addr:postcode":"m1r 5a8",
    "iso:country":"CA",
    "sg:city":"Scarborough",
    "sg:classifiers":[
        {
            "category":"Retail",
            "subcategory":"Animal Services",
            "type":"Services"
        }
    ],
    "sg:phone":"+1 416 285 9830",
    "sg:postcode":"M1R 5A8",
    "sg:province":"ON",
    "sg:tags":[
        "pet",
        "shop",
        "grooming",
        "washing"
    ],
    "wof:name":"Adopt A Friend",
    "wof:placetype":"venue"
},
  "geometry": {"coordinates":[-79.29827899999999,43.754635],"type":"Point"}
}