{
  "type": "Feature",
  "properties": {
    "iso:country":"CA",
    "sg:address":"411 Ridge Rd N",
    "sg:city":"Ridgeway",
    "sg:classifiers":[
        {
            "category":"Shopping",
            "subcategory":"Gifts & Souvenirs",
            "type":"Retail Goods"
        }
    ],
    "sg:phone":"+1 905 894 1864",
    "sg:postcode":"L0S 1N0",
    "sg:province":"ON",
    "sg:tags":[
        "shop"
    ],
    "wof:name":"Country Bunny Gifts",
    "wof:placetype":"venue"
},
  "geometry": {"coordinates":[-79.05220031739999,42.8858795166],"type":"Point"}
}