{
  "type": "Feature",
  "properties": {
    "addr:full":"187 Main St Parrsboro NS B0M 1S0",
    "addr:housenumber":"187",
    "addr:postcode":"b0m 1s0",
    "addr:street":"Main St",
    "iso:country":"CA",
    "sg:address":"187 Main St",
    "sg:city":"Parrsboro",
    "sg:classifiers":[
        {
            "category":"Shopping",
            "subcategory":"Pharmacy",
            "type":"Retail Goods"
        }
    ],
    "sg:phone":"+1 902 254 2342",
    "sg:postcode":"B0M 1S0",
    "sg:province":"NS",
    "wof:name":"Wright's Pharmasave Inc",
    "wof:placetype":"venue"
},
  "geometry": {"coordinates":[-64.3268127441,45.4037437439],"type":"Point"}
}