{
  "type": "Feature",
  "properties": {
    "addr:full":"944 Rue Charlevoix Montreal QC H3K 2Y8",
    "addr:housenumber":"944",
    "addr:postcode":"h3k 2y8",
    "addr:street":"Rue Charlevoix",
    "iso:country":"CA",
    "sg:address":"944 Rue Charlevoix",
    "sg:city":"Montreal",
    "sg:classifiers":[
        {
            "category":"Retail",
            "subcategory":"Auto Repair",
            "type":"Services"
        }
    ],
    "sg:phone":"+1 514 932 2651",
    "sg:postcode":"H3K 2Y8",
    "sg:province":"QC",
    "sg:tags":[
        "repairing",
        "automobile"
    ],
    "wof:name":"Garage Lacroix Inc",
    "wof:placetype":"venue"
},
  "geometry": {"coordinates":[-73.565704,45.476254],"type":"Point"}
}