{
  "type": "Feature",
  "properties": {
    "addr:full":"1310 41 St N Lethbridge AB T1H 5V3",
    "addr:housenumber":"1310",
    "addr:postcode":"t1h 5v3",
    "addr:street":"41 St N",
    "iso:country":"CA",
    "sg:address":"1310 41 St N",
    "sg:city":"Lethbridge",
    "sg:classifiers":[
        {
            "category":"Wholesale",
            "subcategory":"Farm Supplies",
            "type":"Manufacturing & Wholesale Goods"
        }
    ],
    "sg:phone":"+1 403 320 2659",
    "sg:postcode":"T1H 5V3",
    "sg:province":"AB",
    "sg:tags":[
        "product",
        "health",
        "animal"
    ],
    "wof:name":"Adm Animal Health & Nutrition",
    "wof:placetype":"venue"
},
  "geometry": {"coordinates":[-112.78125799999999,49.718342],"type":"Point"}
}