{
  "type": "Feature",
  "properties": {
    "addr:full":"92 Macdowall Cres Prince Albert SK S6V 6N3",
    "addr:housenumber":"92",
    "addr:postcode":"s6v 6n3",
    "addr:street":"Macdowall Cres",
    "iso:country":"CA",
    "sg:address":"92 Macdowall Cres",
    "sg:city":"Prince Albert",
    "sg:classifiers":[
        {
            "category":"Building & Trades",
            "subcategory":"Electrical",
            "type":"Services"
        }
    ],
    "sg:phone":"+1 306 764 3980",
    "sg:postcode":"S6V 6N3",
    "sg:province":"SK",
    "sg:tags":[
        "electric",
        "contractor"
    ],
    "wof:name":"Double G Installations Ltd",
    "wof:placetype":"venue"
},
  "geometry": {"coordinates":[-105.697738648,53.2059326172],"type":"Point"}
}