{
  "type": "Feature",
  "properties": {
    "addr:full":"Toronto ON M4E 1E2",
    "addr:postcode":"m4e 1e2",
    "iso:country":"CA",
    "sg:city":"Toronto",
    "sg:classifiers":[
        {
            "category":"Banks & Credit Unions",
            "subcategory":"Investment Brokerage",
            "type":"Services"
        }
    ],
    "sg:phone":"+1 416 699 3795",
    "sg:postcode":"M4E 1E2",
    "sg:province":"ON",
    "sg:tags":[
        "consultant",
        "accountant",
        "planning",
        "financial"
    ],
    "wof:name":"Ryder, Margie",
    "wof:placetype":"venue"
},
  "geometry": {"coordinates":[-79.294685,43.671299],"type":"Point"}
}