{
  "type": "Feature",
  "properties": {
    "addr:full":"5457 Trafalgar St Vancouver BC V6N 1C1",
    "addr:housenumber":"5457",
    "addr:postcode":"v6n 1c1",
    "addr:street":"Trafalgar St",
    "iso:country":"CA",
    "sg:address":"5457 Trafalgar St",
    "sg:city":"Vancouver",
    "sg:classifiers":[
        {
            "category":"Organizations",
            "subcategory":"Religious Organization",
            "type":"Services"
        }
    ],
    "sg:phone":"+1 604 266 8800",
    "sg:postcode":"V6N 1C1",
    "sg:province":"BC",
    "sg:tags":[
        "church"
    ],
    "wof:name":"St John the Apostle Parish",
    "wof:placetype":"venue"
},
  "geometry": {"coordinates":[-123.16598500000001,49.237106],"type":"Point"}
}