{
  "type": "Feature",
  "properties": {
    "iso:country":"CA",
    "sg:city":"Guelph",
    "sg:classifiers":[
        {
            "category":"Restaurant",
            "type":"Food & Drink"
        }
    ],
    "sg:phone":"+1 519 837 2939",
    "sg:postcode":"N1E 6R2",
    "sg:province":"ON",
    "wof:name":"Mary Brown's Famous Chicken",
    "wof:placetype":"venue"
},
  "geometry": {"coordinates":[-80.2489852905,43.5612373352],"type":"Point"}
}