{
  "type": "Feature",
  "properties": {
    "addr:full":"1862 Lakeshore Rd W Mississauga ON L5J 1J7",
    "addr:housenumber":"1862",
    "addr:postcode":"l5j 1j7",
    "addr:street":"Lakeshore Rd W",
    "iso:country":"CA",
    "sg:address":"1862 Lakeshore Rd W",
    "sg:city":"Mississauga",
    "sg:classifiers":[
        {
            "category":"Personal",
            "subcategory":"Beauty Salon",
            "type":"Services"
        }
    ],
    "sg:phone":"+1 905 822 4305",
    "sg:postcode":"L5J 1J7",
    "sg:province":"ON",
    "wof:name":"Crystal Nails",
    "wof:placetype":"venue"
},
  "geometry": {"coordinates":[-79.6256484985,43.5147399902],"type":"Point"}
}