{
  "type": "Feature",
  "properties": {
    "addr:full":"Concord ON L4K 2A8",
    "addr:postcode":"l4k 2a8",
    "iso:country":"CA",
    "sg:city":"Concord",
    "sg:classifiers":[
        {
            "category":"Manufacturing",
            "subcategory":"Furniture",
            "type":"Manufacturing & Wholesale Goods"
        }
    ],
    "sg:phone":"+1 905 761 0213",
    "sg:postcode":"L4K 2A8",
    "sg:province":"ON",
    "sg:tags":[
        "fixture",
        "store"
    ],
    "wof:name":"Flair Woodworking Ltd",
    "wof:placetype":"venue"
},
  "geometry": {"coordinates":[-79.513741,43.794472],"type":"Point"}
}