{
  "type": "Feature",
  "properties": {
    "addr:full":"37 Ch Petit-Cayamant Lac-Cayamant QC J0X 1Y0",
    "addr:housenumber":"37",
    "addr:postcode":"j0x 1y0",
    "addr:street":"Ch Petit-Cayamant",
    "iso:country":"CA",
    "sg:address":"37 Ch Petit-Cayamant",
    "sg:city":"Lac-Cayamant",
    "sg:classifiers":[
        {
            "category":"Restaurant",
            "type":"Food & Drink"
        }
    ],
    "sg:phone":"+1 819 463 4392",
    "sg:postcode":"J0X 1Y0",
    "sg:province":"QC",
    "wof:name":"Resto-Bar & Camping 4 Seasons",
    "wof:placetype":"venue"
},
  "geometry": {"coordinates":[-76.25501300000001,46.140659],"type":"Point"}
}