{
  "type": "Feature",
  "properties": {
    "addr:full":"4299 Boul Saint-Jean Dollard-Des-Ormeaux QC H9G 2R4",
    "addr:housenumber":"4299",
    "addr:postcode":"h9g 2r4",
    "addr:street":"Boul Saint-Jean",
    "iso:country":"CA",
    "sg:address":"4299 Boul Saint-Jean",
    "sg:city":"Dollard-Des-Ormeaux",
    "sg:classifiers":[
        {
            "category":"Retail",
            "subcategory":"Auto Repair",
            "type":"Services"
        }
    ],
    "sg:phone":"+1 514 624 0267",
    "sg:postcode":"H9G 2R4",
    "sg:province":"QC",
    "sg:tags":[
        "automobile",
        "lubrication"
    ],
    "wof:name":"Pennzoil 10 Minutes Ddo",
    "wof:placetype":"venue"
},
  "geometry": {"coordinates":[-73.841309,45.479931],"type":"Point"}
}