{
  "type": "Feature",
  "properties": {
    "addr:full":"North Vancouver BC V7M 3G4",
    "addr:postcode":"v7m 3g4",
    "iso:country":"CA",
    "sg:city":"North Vancouver",
    "sg:classifiers":[
        {
            "category":"Professional",
            "subcategory":"Lawyer & Legal Services",
            "type":"Services"
        }
    ],
    "sg:phone":"+1 604 984 9521",
    "sg:postcode":"V7M 3G4",
    "sg:province":"BC",
    "sg:tags":[
        "attorney"
    ],
    "wof:name":"Perrick, Ronald W",
    "wof:placetype":"venue"
},
  "geometry": {"coordinates":[-123.0737,49.324024],"type":"Point"}
}