{
  "type": "Feature",
  "properties": {
    "iso:country":"CA",
    "sg:address":"12141 Harris Rd",
    "sg:city":"Pitt Meadows",
    "sg:classifiers":[
        {
            "category":"Travel",
            "subcategory":"Travel Agent",
            "type":"Entertainment"
        }
    ],
    "sg:phone":"+1 604 465 8944",
    "sg:postcode":"V3Y 2E9",
    "sg:province":"BC",
    "sg:tags":[
        "agency",
        "bureau"
    ],
    "wof:name":"Pitt Meadows Travel",
    "wof:placetype":"venue"
},
  "geometry": {"coordinates":[-122.689827,49.223358],"type":"Point"}
}