{
  "type": "Feature",
  "properties": {
    "addr:full":"12141 Harris Rd Pitt Meadows BC V3Y 2E9",
    "addr:housenumber":"12141",
    "addr:postcode":"v3y 2e9",
    "addr:street":"Harris Rd",
    "iso:country":"CA",
    "sg:address":"12141 Harris Rd",
    "sg:city":"Pitt Meadows",
    "sg:classifiers":[
        {
            "category":"Travel",
            "subcategory":"Travel Agent",
            "type":"Entertainment"
        }
    ],
    "sg:phone":"+1 604 465 8944",
    "sg:postcode":"V3Y 2E9",
    "sg:province":"BC",
    "sg:tags":[
        "agency",
        "bureau"
    ],
    "wof:name":"Pitt Meadows Travel",
    "wof:placetype":"venue"
},
  "geometry": {"coordinates":[-122.68982699999999,49.223358],"type":"Point"}
}