{
  "type": "Feature",
  "properties": {
    "addr:full":"1800 Hamilton St Regina SK S4P 4K7",
    "addr:housenumber":"1800",
    "addr:postcode":"s4p 4k7",
    "addr:street":"Hamilton St",
    "iso:country":"CA",
    "sg:address":"1800 Hamilton St",
    "sg:city":"Regina",
    "sg:classifiers":[
        {
            "category":"Banks & Credit Unions",
            "subcategory":"Bank",
            "type":"Services"
        }
    ],
    "sg:phone":"+1 306 780 8100",
    "sg:postcode":"S4P 4K7",
    "sg:province":"SK",
    "sg:tags":[
        "government"
    ],
    "wof:name":"Farm Credit Corp",
    "wof:placetype":"venue"
},
  "geometry": {"coordinates":[-104.609528,50.450249],"type":"Point"}
}