{
  "type": "Feature",
  "properties": {
    "iso:country":"CA",
    "sg:address":"412 Rue King E",
    "sg:city":"Sherbrooke",
    "sg:classifiers":[
        {
            "category":"Personal",
            "subcategory":"Barber",
            "type":"Services"
        }
    ],
    "sg:phone":"+1 819 346 4013",
    "sg:postcode":"J1G 1B5",
    "sg:province":"QC",
    "wof:name":"Salon Murray Enr",
    "wof:placetype":"venue"
},
  "geometry": {"coordinates":[-71.8797,45.407921],"type":"Point"}
}