{
  "type": "Feature",
  "properties": {
    "addr:full":"1198 Montreal Rd Cornwall ON K6H 1E2",
    "addr:housenumber":"1198",
    "addr:postcode":"k6h 1e2",
    "addr:street":"Montreal Rd",
    "iso:country":"CA",
    "sg:address":"1198 Montreal Rd",
    "sg:city":"Cornwall",
    "sg:classifiers":[
        {
            "category":"Health Services",
            "subcategory":"Nursing And Care Facility",
            "type":"Services"
        }
    ],
    "sg:phone":"+1 613 938 7455",
    "sg:postcode":"K6H 1E2",
    "sg:province":"ON",
    "sg:tags":[
        "home",
        "rest"
    ],
    "wof:name":"Riverview Manor Ltd",
    "wof:placetype":"venue"
},
  "geometry": {"coordinates":[-74.6945571899,45.020565033],"type":"Point"}
}