{
  "type": "Feature",
  "properties": {
    "addr:full":"4330 Pollock Rd Duncan BC V9L 6H1",
    "addr:housenumber":"4330",
    "addr:postcode":"v9l 6h1",
    "addr:street":"Pollock Rd",
    "iso:country":"CA",
    "sg:address":"4330 Pollock Rd",
    "sg:city":"Duncan",
    "sg:classifiers":[
        {
            "category":"Building & Trades",
            "subcategory":"Construction",
            "type":"Services"
        }
    ],
    "sg:phone":"+1 250 746 4332",
    "sg:postcode":"V9L 6H1",
    "sg:province":"BC",
    "sg:tags":[
        "roofing",
        "contractor"
    ],
    "wof:name":"T C Roofing",
    "wof:placetype":"venue"
},
  "geometry": {"coordinates":[-123.707382,48.779095],"type":"Point"}
}