{
  "type": "Feature",
  "properties": {
    "addr:full":"PO Box 327 Hague SK S0K 1X0",
    "addr:housenumber":"po",
    "addr:postcode":"s0k 1x0",
    "addr:street":"Box 327",
    "iso:country":"CA",
    "sg:address":"PO Box 327",
    "sg:city":"Hague",
    "sg:classifiers":[
        {
            "category":"Freight",
            "type":"Transportation"
        }
    ],
    "sg:phone":"+1 306 225 4360",
    "sg:postcode":"S0K 1X0",
    "sg:province":"SK",
    "sg:tags":[
        "building",
        "house",
        "mover"
    ],
    "wof:name":"B & M Building Movers Ltd",
    "wof:placetype":"venue"
},
  "geometry": {"coordinates":[-106.411896,52.51218],"type":"Point"}
}