{
  "type": "Feature",
  "properties": {
    "addr:full":"398 Ferrier St # 8 Markham ON L3R 2Z5",
    "addr:housenumber":"398",
    "addr:postcode":"l3r 2z5",
    "addr:street":"Ferrier St # 8",
    "iso:country":"CA",
    "sg:address":"398 Ferrier St # 8",
    "sg:city":"Markham",
    "sg:classifiers":[
        {
            "category":"Shopping",
            "subcategory":"Florist",
            "type":"Retail Goods"
        }
    ],
    "sg:phone":"+1 905 946 1750",
    "sg:postcode":"L3R 2Z5",
    "sg:province":"ON",
    "wof:name":"You & Me Flowers & Gifts",
    "wof:placetype":"venue"
},
  "geometry": {"coordinates":[-79.3310852051,43.8204421997],"type":"Point"}
}