{
  "type": "Feature",
  "properties": {
    "addr:full":"469 Merton St Toronto ON M4S 1B4",
    "addr:housenumber":"469",
    "addr:postcode":"m4s 1b4",
    "addr:street":"Merton St",
    "iso:country":"CA",
    "sg:address":"469 Merton St",
    "sg:city":"Toronto",
    "sg:classifiers":[
        {
            "category":"Education",
            "subcategory":"School",
            "type":"Public Place"
        }
    ],
    "sg:phone":"+1 416 487 5308",
    "sg:postcode":"M4S 1B4",
    "sg:province":"ON",
    "wof:name":"Sunnybrook School",
    "wof:placetype":"venue"
},
  "geometry": {"coordinates":[-79.380959,43.699196],"type":"Point"}
}