{
  "type": "Feature",
  "properties": {
    "addr:full":"813 Brant St Burlington ON L7R 2J4",
    "addr:housenumber":"813",
    "addr:postcode":"l7r 2j4",
    "addr:street":"Brant St",
    "iso:country":"CA",
    "sg:address":"813 Brant St",
    "sg:city":"Burlington",
    "sg:classifiers":[
        {
            "category":"Shopping",
            "subcategory":"Bicycles & Sporting Goods",
            "type":"Retail Goods"
        }
    ],
    "sg:phone":"+1 905 634 2566",
    "sg:postcode":"L7R 2J4",
    "sg:province":"ON",
    "wof:name":"Action Bikes",
    "wof:placetype":"venue"
},
  "geometry": {"coordinates":[-79.810349,43.334469],"type":"Point"}
}