{
  "type": "Feature",
  "properties": {
    "iso:country":"CA",
    "sg:address":"7381 Kennedy Rd # 106",
    "sg:city":"Markham",
    "sg:classifiers":[
        {
            "category":"Health Services",
            "subcategory":"Doctor",
            "type":"Services"
        }
    ],
    "sg:phone":"+1 905 947 8827",
    "sg:postcode":"L3R 5B5",
    "sg:province":"ON",
    "sg:tags":[
        "dentist"
    ],
    "wof:name":"Lau, Clarence Y DDS",
    "wof:placetype":"venue"
},
  "geometry": {"coordinates":[-79.3040008545,43.8348121643],"type":"Point"}
}