{
  "type": "Feature",
  "properties": {
    "addr:full":"44 St. Charles Blvd Beaconsfield QC H9W 5Z6",
    "addr:housenumber":"44",
    "addr:postcode":"h9w 5z6",
    "addr:street":"St. Charles Blvd",
    "iso:country":"CA",
    "sg:address":"44 St. Charles Blvd",
    "sg:city":"Beaconsfield",
    "sg:classifiers":[
        {
            "category":"Restaurant",
            "type":"Food & Drink"
        }
    ],
    "sg:phone":"+1 514 694 3427",
    "sg:postcode":"H9W 5Z6",
    "sg:province":"QC",
    "wof:name":"Mc Donald's",
    "wof:placetype":"venue"
},
  "geometry": {"coordinates":[-73.846649,45.432156],"type":"Point"}
}