{
  "type": "Feature",
  "properties": {
    "iso:country":"CA",
    "sg:address":"402 Bisson Ch",
    "sg:city":"Rouyn-Noranda",
    "sg:classifiers":[
        {
            "category":"Building & Trades",
            "subcategory":"Plumbing",
            "type":"Services"
        }
    ],
    "sg:phone":"+1 819 797 1176",
    "sg:postcode":"J9Y 1E8",
    "sg:province":"QC",
    "sg:tags":[
        "refrigeration",
        "appliance",
        "contractor"
    ],
    "wof:name":"Atelier-Reparation R Bergeron",
    "wof:placetype":"venue"
},
  "geometry": {"coordinates":[-78.97761535639999,48.1555480957],"type":"Point"}
}