{
  "type": "Feature",
  "properties": {
    "addr:full":"Chilliwack BC V2P 4H3",
    "addr:postcode":"v2p 4h3",
    "iso:country":"CA",
    "sg:city":"Chilliwack",
    "sg:classifiers":[
        {
            "category":"Health Services",
            "subcategory":"Doctor",
            "type":"Services"
        }
    ],
    "sg:phone":"+1 604 792 0616",
    "sg:postcode":"V2P 4H3",
    "sg:province":"BC",
    "sg:tags":[
        "dentist"
    ],
    "wof:name":"Chilliwack Dental Ctr",
    "wof:placetype":"venue"
},
  "geometry": {"coordinates":[-121.95807647700001,49.1714134216],"type":"Point"}
}