{
  "type": "Feature",
  "properties": {
    "addr:full":"5000 Boul Cousineau Saint-Hubert QC J3Y 7G5",
    "addr:housenumber":"5000",
    "addr:postcode":"j3y 7g5",
    "addr:street":"Boul Cousineau",
    "iso:country":"CA",
    "sg:address":"5000 Boul Cousineau",
    "sg:city":"Saint-Hubert",
    "sg:classifiers":[
        {
            "category":"Restaurant",
            "type":"Food & Drink"
        }
    ],
    "sg:phone":"+1 450 445 1715",
    "sg:postcode":"J3Y 7G5",
    "sg:province":"QC",
    "wof:name":"Teddy's Deli & Bar",
    "wof:placetype":"venue"
},
  "geometry": {"coordinates":[-73.42982499999999,45.506214],"type":"Point"}
}