{
  "type": "Feature",
  "properties": {
    "addr:full":"402 Boul L'Assomption Repentigny QC J6A 1C2",
    "addr:housenumber":"402",
    "addr:postcode":"j6a 1c2",
    "addr:street":"Boul L'Assomption",
    "iso:country":"CA",
    "sg:address":"402 Boul L'Assomption",
    "sg:city":"Repentigny",
    "sg:classifiers":[
        {
            "category":"Building & Trades",
            "subcategory":"Landscaping Services",
            "type":"Services"
        }
    ],
    "sg:phone":"+1 450 585 7347",
    "sg:postcode":"J6A 1C2",
    "sg:province":"QC",
    "sg:tags":[
        "landscape",
        "contractor"
    ],
    "wof:name":"Amenagement Paysager Perreault",
    "wof:placetype":"venue"
},
  "geometry": {"coordinates":[-73.4440612793,45.7554397583],"type":"Point"}
}