{
  "type": "Feature",
  "properties": {
    "iso:country":"CA",
    "sg:address":"66 Centre St",
    "sg:city":"Thornhill",
    "sg:classifiers":[
        {
            "category":"Professional",
            "subcategory":"Computer Services",
            "type":"Services"
        }
    ],
    "sg:phone":"+1 905 731 4184",
    "sg:postcode":"L4J 1E9",
    "sg:province":"ON",
    "sg:tags":[
        "consultant"
    ],
    "wof:name":"World Connect Inc",
    "wof:placetype":"venue"
},
  "geometry": {"coordinates":[-79.426949,43.815937],"type":"Point"}
}