{
  "type": "Feature",
  "properties": {
    "addr:full":"Winnipeg MB R3Y 1V8",
    "addr:postcode":"r3y 1v8",
    "iso:country":"CA",
    "sg:city":"Winnipeg",
    "sg:classifiers":[
        {
            "category":"Health Services",
            "subcategory":"Chiropractor",
            "type":"Services"
        }
    ],
    "sg:phone":"+1 204 489 1600",
    "sg:postcode":"R3Y 1V8",
    "sg:province":"MB",
    "wof:name":"Linden Ridge Chiropractic",
    "wof:placetype":"venue"
},
  "geometry": {"coordinates":[-97.1981430054,49.8180122375],"type":"Point"}
}