{
  "type": "Feature",
  "properties": {
    "addr:full":"436 Charlotte St Sydney NS B1P 1E4",
    "addr:housenumber":"436",
    "addr:postcode":"b1p 1e4",
    "addr:street":"Charlotte St",
    "iso:country":"CA",
    "sg:address":"436 Charlotte St",
    "sg:city":"Sydney",
    "sg:classifiers":[
        {
            "category":"Shopping",
            "subcategory":"Used Merchandise",
            "type":"Retail Goods"
        }
    ],
    "sg:phone":"+1 902 564 6123",
    "sg:postcode":"B1P 1E4",
    "sg:province":"NS",
    "sg:tags":[
        "furniture"
    ],
    "wof:name":"Sid's Used Furniture Store",
    "wof:placetype":"venue"
},
  "geometry": {"coordinates":[-60.1940803528,46.135509491],"type":"Point"}
}