{
  "type": "Feature",
  "properties": {
    "addr:full":"2600 Skymark Ave #201 Mississauga ON L4W 5B2",
    "addr:housenumber":"2600",
    "addr:postcode":"l4w 5b2",
    "addr:street":"Skymark Ave # 201",
    "iso:country":"CA",
    "sg:address":"2600 Skymark Ave #201",
    "sg:city":"Mississauga",
    "sg:classifiers":[
        {
            "category":"Professional",
            "subcategory":"Computer Services",
            "type":"Services"
        }
    ],
    "sg:phone":"+1 905 206 1311",
    "sg:postcode":"L4W 5B2",
    "sg:province":"ON",
    "sg:tags":[
        "consultant"
    ],
    "wof:name":"Re Act Technologies",
    "wof:placetype":"venue"
},
  "geometry": {"coordinates":[-79.59807600000001,43.658791],"type":"Point"}
}