{
  "type": "Feature",
  "properties": {
    "addr:full":"397 Place DE Louvain Montreal QC H2N 1A1",
    "addr:housenumber":"397",
    "addr:postcode":"h2n 1a1",
    "addr:street":"Place De Louvain",
    "iso:country":"CA",
    "sg:address":"397 Place DE Louvain",
    "sg:city":"Montreal",
    "sg:classifiers":[
        {
            "category":"Wholesale",
            "subcategory":"Home Furnishings",
            "type":"Manufacturing & Wholesale Goods"
        }
    ],
    "sg:phone":"+1 514 383 2227",
    "sg:postcode":"H2N 1A1",
    "sg:province":"QC",
    "sg:tags":[
        "rug",
        "carpet"
    ],
    "wof:name":"Agences Sdr Agencies Inc",
    "wof:placetype":"venue"
},
  "geometry": {"coordinates":[-73.65844,45.539585],"type":"Point"}
}