{
  "type": "Feature",
  "properties": {
    "addr:full":"5875 Carnarvon St Vancouver BC V6N 1J5",
    "addr:housenumber":"5875",
    "addr:postcode":"v6n 1j5",
    "addr:street":"Carnarvon St",
    "iso:country":"CA",
    "sg:address":"5875 Carnarvon St",
    "sg:city":"Vancouver",
    "sg:classifiers":[
        {
            "category":"Building & Trades",
            "subcategory":"Plumbing",
            "type":"Services"
        }
    ],
    "sg:phone":"+1 604 263 4599",
    "sg:postcode":"V6N 1J5",
    "sg:province":"BC",
    "sg:tags":[
        "tank",
        "installation"
    ],
    "wof:name":"Paulsen Industries Ltd",
    "wof:placetype":"venue"
},
  "geometry": {"coordinates":[-123.173210144,49.2331008911],"type":"Point"}
}