{
  "type": "Feature",
  "properties": {
    "iso:country":"CA",
    "sg:address":"RR 4",
    "sg:city":"Lansdowne",
    "sg:classifiers":[
        {
            "category":"Organizations",
            "subcategory":"Religious Organization",
            "type":"Services"
        }
    ],
    "sg:phone":"+1 613 659 2412",
    "sg:postcode":"K0E 1L0",
    "sg:province":"ON",
    "sg:tags":[
        "church"
    ],
    "wof:name":"St Patrick Catholic Church",
    "wof:placetype":"venue"
},
  "geometry": {"coordinates":[-76.0189361572,44.4057388306],"type":"Point"}
}