{
  "type": "Feature",
  "properties": {
    "addr:full":"5220 Yonge St North York ON M2N 5P6",
    "addr:housenumber":"5220",
    "addr:postcode":"m2n 5p6",
    "addr:street":"Yonge St",
    "iso:country":"CA",
    "sg:address":"5220 Yonge St",
    "sg:city":"North York",
    "sg:classifiers":[
        {
            "category":"Retail",
            "subcategory":"Auto Repair",
            "type":"Services"
        }
    ],
    "sg:phone":"+1 416 225 7796",
    "sg:postcode":"M2N 5P6",
    "sg:province":"ON",
    "sg:tags":[
        "repairing",
        "automobile"
    ],
    "wof:name":"Speedy Auto Svc",
    "wof:placetype":"venue"
},
  "geometry": {"coordinates":[-79.4134597778,43.7708244324],"type":"Point"}
}