{
  "type": "Feature",
  "properties": {
    "iso:country":"CA",
    "sg:city":"Saint-Eugene-DE-Grantham",
    "sg:classifiers":[
        {
            "category":"Recreation",
            "type":"Entertainment"
        }
    ],
    "sg:phone":"+1 819 396 5187",
    "sg:postcode":"J0C 1J0",
    "sg:province":"QC",
    "sg:tags":[
        "hall",
        "auditorium"
    ],
    "wof:name":"Salle Municipale",
    "wof:placetype":"venue"
},
  "geometry": {"coordinates":[-72.6982040405,45.8049697876],"type":"Point"}
}