{
  "type": "Feature",
  "properties": {
    "addr:full":"Saint-Felix-DE-Valois QC J0K 2M0",
    "addr:postcode":"j0k 2m0",
    "iso:country":"CA",
    "sg:city":"Saint-Felix-DE-Valois",
    "sg:classifiers":[
        {
            "category":"Shopping",
            "type":"Retail Goods"
        }
    ],
    "sg:phone":"+1 450 889 4255",
    "sg:postcode":"J0K 2M0",
    "sg:province":"QC",
    "sg:tags":[
        "awning",
        "canopy"
    ],
    "wof:name":"Toiles St-Felix Enr",
    "wof:placetype":"venue"
},
  "geometry": {"coordinates":[-73.42952728269999,46.1503067017],"type":"Point"}
}