{
  "type": "Feature",
  "properties": {
    "addr:full":"624 Boul Sir-Wilfrid-Laurier Beloeil QC J3G 4J2",
    "addr:housenumber":"624",
    "addr:postcode":"j3g 4j2",
    "addr:street":"Boul Sir-Wilfrid-Laurier",
    "iso:country":"CA",
    "sg:address":"624 Boul Sir-Wilfrid-Laurier",
    "sg:city":"Beloeil",
    "sg:classifiers":[
        {
            "category":"Retail",
            "subcategory":"Auto Repair",
            "type":"Services"
        }
    ],
    "sg:phone":"+1 450 467 9351",
    "sg:postcode":"J3G 4J2",
    "sg:province":"QC",
    "sg:tags":[
        "repairing",
        "automobile"
    ],
    "wof:name":"Garage Hubert Normand Inc",
    "wof:placetype":"venue"
},
  "geometry": {"coordinates":[-73.20648199999999,45.563076],"type":"Point"}
}