{
  "type": "Feature",
  "properties": {
    "iso:country":"CA",
    "sg:city":"Vancouver",
    "sg:classifiers":[
        {
            "category":"Banks & Credit Unions",
            "subcategory":"Investment Brokerage",
            "type":"Services"
        }
    ],
    "sg:phone":"+1 604 327 1411",
    "sg:postcode":"V5Z 2X8",
    "sg:province":"BC",
    "sg:tags":[
        "consultant",
        "planning",
        "financial"
    ],
    "wof:name":"Heritage Scholarship Trust Pln",
    "wof:placetype":"venue"
},
  "geometry": {"coordinates":[-123.115203857,49.2492713928],"type":"Point"}
}