{
  "type": "Feature",
  "properties": {
    "addr:full":"Hwy 43 Kemptville ON K0G 1J0",
    "addr:postcode":"k0g 1j0",
    "addr:street":"Hwy 43",
    "iso:country":"CA",
    "sg:address":"Hwy 43",
    "sg:city":"Kemptville",
    "sg:classifiers":[
        {
            "category":"Shopping",
            "subcategory":"Stationery & Office Supplies",
            "type":"Retail Goods"
        }
    ],
    "sg:phone":"+1 613 258 2910",
    "sg:postcode":"K0G 1J0",
    "sg:province":"ON",
    "wof:name":"Business Strategies",
    "wof:placetype":"venue"
},
  "geometry": {"coordinates":[-75.674751,45.010056],"type":"Point"}
}