{
  "type": "Feature",
  "properties": {
    "addr:full":"Orillia ON L3V 5B8",
    "addr:postcode":"l3v 5b8",
    "iso:country":"CA",
    "sg:city":"Orillia",
    "sg:classifiers":[
        {
            "category":"Professional",
            "subcategory":"Lawyer & Legal Services",
            "type":"Services"
        }
    ],
    "sg:phone":"+1 705 327 6671",
    "sg:postcode":"L3V 5B8",
    "sg:province":"ON",
    "sg:tags":[
        "attorney"
    ],
    "wof:name":"French, Allan",
    "wof:placetype":"venue"
},
  "geometry": {"coordinates":[-79.41961669920001,44.6085014343],"type":"Point"}
}