{
  "type": "Feature",
  "properties": {
    "iso:country":"CA",
    "sg:address":"11 Athabasca Ave #A",
    "sg:city":"Devon",
    "sg:classifiers":[
        {
            "category":"Insurance",
            "subcategory":"Insurance Agent",
            "type":"Services"
        }
    ],
    "sg:phone":"+1 780 987 3344",
    "sg:postcode":"T9G 1G5",
    "sg:province":"AB",
    "sg:tags":[
        "license"
    ],
    "wof:name":"Devon Registries & Insurance",
    "wof:placetype":"venue"
},
  "geometry": {"coordinates":[-113.73088799999999,53.365616],"type":"Point"}
}