{
  "type": "Feature",
  "properties": {
    "iso:country":"CA",
    "sg:address":"1050 Eldorado St",
    "sg:city":"Trail",
    "sg:classifiers":[
        {
            "category":"Government",
            "subcategory":"Office",
            "type":"Public Place"
        }
    ],
    "sg:phone":"+1 250 364 0591",
    "sg:postcode":"V1R 3V7",
    "sg:province":"BC",
    "wof:name":"BC Govt Agents",
    "wof:placetype":"venue"
},
  "geometry": {"coordinates":[-117.70803832999999,49.0963249207],"type":"Point"}
}