{
  "type": "Feature",
  "properties": {
    "iso:country":"CA",
    "sg:address":"9 Yerxa Lane",
    "sg:city":"Keswick",
    "sg:classifiers":[
        {
            "category":"Food & Beverages",
            "subcategory":"Bakery",
            "type":"Retail Goods"
        }
    ],
    "sg:phone":"+1 506 363 4618",
    "sg:postcode":"E6L 1N7",
    "sg:province":"NB",
    "sg:tags":[
        "baker"
    ],
    "wof:name":"Keswick Kitchen",
    "wof:placetype":"venue"
},
  "geometry": {"coordinates":[-66.8293457031,45.9975471497],"type":"Point"}
}