{
  "type": "Feature",
  "properties": {
    "addr:full":"895 Rue Arthur-Buies # 120 Saint-Jerome QC J7Y 4X3",
    "addr:housenumber":"895",
    "addr:postcode":"j7y 4x3",
    "addr:street":"Rue Arthur-Buies # 120 Saint-Jerome",
    "iso:country":"CA",
    "sg:address":"895 Rue Arthur-Buies # 120",
    "sg:city":"Saint-Jerome",
    "sg:classifiers":[
        {
            "category":"Building & Trades",
            "subcategory":"Construction",
            "type":"Services"
        }
    ],
    "sg:phone":"+1 450 431 1403",
    "sg:postcode":"J7Y 4X3",
    "sg:province":"QC",
    "sg:tags":[
        "repairing",
        "retirement",
        "community",
        "contractor",
        "home",
        "remodeling"
    ],
    "wof:name":"Manoir Philippe Alexandre",
    "wof:placetype":"venue"
},
  "geometry": {"coordinates":[-74.014175415,45.7948303223],"type":"Point"}
}