{
  "type": "Feature",
  "properties": {
    "iso:country":"CA",
    "sg:address":"5438 47 St",
    "sg:city":"Red Deer",
    "sg:classifiers":[
        {
            "category":"Government",
            "subcategory":"Office",
            "type":"Public Place"
        }
    ],
    "sg:phone":"+1 403 342 8225",
    "sg:postcode":"T4N 6Z4",
    "sg:province":"AB",
    "sg:tags":[
        "village"
    ],
    "wof:name":"Red Deer Transit Dept",
    "wof:placetype":"venue"
},
  "geometry": {"coordinates":[-113.822387695,52.2673912048],"type":"Point"}
}