{
  "type": "Feature",
  "properties": {
    "addr:full":"63 Ch Des Lilas Sainte-Anne-Des-Lacs QC J0R 1B0",
    "addr:housenumber":"63",
    "addr:postcode":"j0r 1b0",
    "addr:street":"Ch Des Lilas",
    "iso:country":"CA",
    "sg:address":"63 Ch Des Lilas",
    "sg:city":"Sainte-Anne-Des-Lacs",
    "sg:classifiers":[
        {
            "category":"Building & Trades",
            "subcategory":"Plumbing",
            "type":"Services"
        }
    ],
    "sg:phone":"+1 450 224 2216",
    "sg:postcode":"J0R 1B0",
    "sg:province":"QC",
    "sg:tags":[
        "contractor"
    ],
    "wof:name":"Plomberie James Descoeurs Inc",
    "wof:placetype":"venue"
},
  "geometry": {"coordinates":[-74.1188583374,45.8600730896],"type":"Point"}
}