{
  "type": "Feature",
  "properties": {
    "iso:country":"CA",
    "sg:address":"2496 Boul Prudentiel",
    "sg:city":"Laval",
    "sg:classifiers":[
        {
            "category":"Professional",
            "subcategory":"Business Services",
            "type":"Services"
        }
    ],
    "sg:phone":"+1 450 668 4863",
    "sg:postcode":"H7K 2R9",
    "sg:province":"QC",
    "sg:tags":[
        "notary"
    ],
    "wof:name":"Beaudoin, Marie-Chris",
    "wof:placetype":"venue"
},
  "geometry": {"coordinates":[-73.7324371338,45.6235656738],"type":"Point"}
}