{
  "type": "Feature",
  "properties": {
    "iso:country":"CA",
    "sg:address":"292 Church St S",
    "sg:city":"Alliston",
    "sg:classifiers":[
        {
            "category":"Freight",
            "type":"Transportation"
        }
    ],
    "sg:phone":"+1 705 434 3136",
    "sg:postcode":"L9R 1T9",
    "sg:province":"ON",
    "sg:tags":[
        "warehousing"
    ],
    "wof:name":"Nissin Transport Canada Inc",
    "wof:placetype":"venue"
},
  "geometry": {"coordinates":[-79.864281,44.141785],"type":"Point"}
}