{
  "type": "Feature",
  "properties": {
    "iso:country":"CA",
    "sg:address":"189 Bullock Dr # B",
    "sg:city":"Markham",
    "sg:classifiers":[
        {
            "category":"Wholesale",
            "subcategory":"Electrical",
            "type":"Manufacturing & Wholesale Goods"
        }
    ],
    "sg:phone":"+1 905 294 9570",
    "sg:postcode":"L3P 1W4",
    "sg:province":"ON",
    "sg:tags":[
        "lighting",
        "fixture"
    ],
    "wof:name":"Thomas Lighting",
    "wof:placetype":"venue"
},
  "geometry": {"coordinates":[-79.282379,43.873398],"type":"Point"}
}