{
  "type": "Feature",
  "properties": {
    "iso:country":"CA",
    "sg:address":"1390 Av Du Mont-Royal E",
    "sg:city":"Montreal",
    "sg:classifiers":[
        {
            "category":"Shopping",
            "subcategory":"Hobbies, Toys, & Games",
            "type":"Retail Goods"
        }
    ],
    "sg:phone":"+1 514 528 8889",
    "sg:postcode":"H2J 1Y7",
    "sg:province":"QC",
    "wof:name":"Au Diabolo Jeux & Jouets",
    "wof:placetype":"venue"
},
  "geometry": {"coordinates":[-73.576462,45.530651],"type":"Point"}
}