{
  "type": "Feature",
  "properties": {
    "addr:full":"1390 Av Du Mont-Royal E Montreal QC H2J 1Y7",
    "addr:housenumber":"1390",
    "addr:postcode":"h2j 1y7",
    "addr:street":"Av Du Mont-Royal E",
    "iso:country":"CA",
    "sg:address":"1390 Av Du Mont-Royal E",
    "sg:city":"Montreal",
    "sg:classifiers":[
        {
            "category":"Shopping",
            "subcategory":"Hobbies, Toys, & Games",
            "type":"Retail Goods"
        }
    ],
    "sg:phone":"+1 514 528 8889",
    "sg:postcode":"H2J 1Y7",
    "sg:province":"QC",
    "wof:name":"Au Diabolo Jeux & Jouets",
    "wof:placetype":"venue"
},
  "geometry": {"coordinates":[-73.57646200000001,45.530651],"type":"Point"}
}