{
  "type": "Feature",
  "properties": {
    "iso:country":"CA",
    "sg:city":"Shediac",
    "sg:classifiers":[
        {
            "category":"Government",
            "subcategory":"Office",
            "type":"Public Place"
        }
    ],
    "sg:phone":"+1 506 533 5018",
    "sg:postcode":"E4P 2E7",
    "sg:province":"NB",
    "wof:name":"Canada Etudiants",
    "wof:placetype":"venue"
},
  "geometry": {"coordinates":[-64.543732,46.219555],"type":"Point"}
}