{
  "type": "Feature",
  "properties": {
    "addr:full":"4100 Montee Gagnon Terrebonne QC J6Y 1K8",
    "addr:postcode":"4100;j6y 1k8",
    "addr:street":"Montee Gagnon",
    "iso:country":"CA",
    "sg:address":"4100 Montee Gagnon",
    "sg:city":"Terrebonne",
    "sg:classifiers":[
        {
            "category":"Retail",
            "subcategory":"Auto Repair",
            "type":"Services"
        }
    ],
    "sg:phone":"+1 450 430 9939",
    "sg:postcode":"J6Y 1K8",
    "sg:province":"QC",
    "sg:tags":[
        "repairing",
        "automobile"
    ],
    "wof:name":"Garage Gilles Michaud",
    "wof:placetype":"venue"
},
  "geometry": {"coordinates":[-73.817024,45.704807],"type":"Point"}
}