{
  "type": "Feature",
  "properties": {
    "addr:full":"2700 Boul Poirier Saint-Laurent QC H4R 2P6",
    "addr:housenumber":"2700",
    "addr:postcode":"h4r 2p6",
    "addr:street":"Boul Poirier",
    "iso:country":"CA",
    "sg:address":"2700 Boul Poirier",
    "sg:city":"Saint-Laurent",
    "sg:classifiers":[
        {
            "category":"Social Services",
            "subcategory":"Child Care",
            "type":"Services"
        }
    ],
    "sg:phone":"+1 514 332 6161",
    "sg:postcode":"H4R 2P6",
    "sg:province":"QC",
    "wof:name":"Garderie LA Joconde Inc",
    "wof:placetype":"venue"
},
  "geometry": {"coordinates":[-73.70787,45.51022],"type":"Point"}
}