{
  "type": "Feature",
  "properties": {
    "addr:full":"1337 Danforth Ave Toronto ON M4J 1N1",
    "addr:housenumber":"1337",
    "addr:postcode":"m4j 1n1",
    "addr:street":"Danforth Ave",
    "iso:country":"CA",
    "sg:address":"1337 Danforth Ave",
    "sg:city":"Toronto",
    "sg:classifiers":[
        {
            "category":"Professional",
            "subcategory":"Accounting & Tax Preparation",
            "type":"Services"
        }
    ],
    "sg:phone":"+1 416 461 3665",
    "sg:postcode":"M4J 1N1",
    "sg:province":"ON",
    "sg:tags":[
        "bookkeeping",
        "general"
    ],
    "wof:name":"Superior Bookkeeping Svc Ltd",
    "wof:placetype":"venue"
},
  "geometry": {"coordinates":[-79.329063,43.682049],"type":"Point"}
}