{
  "type": "Feature",
  "properties": {
    "addr:full":"7072 Ch DE LA Cote-Des-Neiges Montreal QC H3R 2L9",
    "addr:postcode":"7072;h3r 2l9",
    "addr:street":"Ch De La Cote-Des-Neiges",
    "iso:country":"CA",
    "sg:address":"7072 Ch DE LA Cote-Des-Neiges",
    "sg:city":"Montreal",
    "sg:classifiers":[
        {
            "category":"Building & Trades",
            "subcategory":"Landscaping Services",
            "type":"Services"
        }
    ],
    "sg:phone":"+1 514 344 3474",
    "sg:postcode":"H3R 2L9",
    "sg:province":"QC",
    "sg:tags":[
        "landscape",
        "contractor"
    ],
    "wof:name":"Aqua Sculpture",
    "wof:placetype":"venue"
},
  "geometry": {"coordinates":[-73.640968,45.504421],"type":"Point"}
}