{
  "type": "Feature",
  "properties": {
    "addr:full":"11 Boul D'Anjou Chateauguay QC J6J 2P6",
    "addr:housenumber":"11",
    "addr:postcode":"j6j 2p6",
    "addr:street":"Boul D'Anjou",
    "iso:country":"CA",
    "sg:address":"11 Boul D'Anjou",
    "sg:city":"Chateauguay",
    "sg:classifiers":[
        {
            "category":"Health Services",
            "subcategory":"Nursing And Care Facility",
            "type":"Services"
        }
    ],
    "sg:phone":"+1 450 692 6285",
    "sg:postcode":"J6J 2P6",
    "sg:province":"QC",
    "sg:tags":[
        "home",
        "retirement",
        "community"
    ],
    "wof:name":"Manoir Parent Inc",
    "wof:placetype":"venue"
},
  "geometry": {"coordinates":[-73.740112,45.361485],"type":"Point"}
}