{
  "type": "Feature",
  "properties": {
    "addr:full":"Edmonton AB T5H 2N5",
    "addr:postcode":"t5h 2n5",
    "iso:country":"CA",
    "sg:city":"Edmonton",
    "sg:classifiers":[
        {
            "category":"Personal",
            "subcategory":"Beauty Salon",
            "type":"Services"
        }
    ],
    "sg:phone":"+1 780 421 7898",
    "sg:postcode":"T5H 2N5",
    "sg:province":"AB",
    "wof:name":"Mina's Hair & Beauty Salon",
    "wof:placetype":"venue"
},
  "geometry": {"coordinates":[-113.489570618,53.5495300293],"type":"Point"}
}