{
  "type": "Feature",
  "properties": {
    "addr:full":"Fredericton NB E3B 6Z3",
    "addr:postcode":"e3b 6z3",
    "iso:country":"CA",
    "sg:city":"Fredericton",
    "sg:classifiers":[
        {
            "category":"Real Estate",
            "subcategory":"Real Estate Operator",
            "type":"Services"
        }
    ],
    "sg:phone":"+1 506 459 7799",
    "sg:postcode":"E3B 6Z3",
    "sg:province":"NB",
    "sg:tags":[
        "building",
        "parks"
    ],
    "wof:name":"Cardinal Investments Ltd",
    "wof:placetype":"venue"
},
  "geometry": {"coordinates":[-66.646553,45.962307],"type":"Point"}
}