{
  "type": "Feature",
  "properties": {
    "addr:full":"400 Anderson St Whitby ON L1N 3V6",
    "addr:housenumber":"400",
    "addr:postcode":"l1n 3v6",
    "addr:street":"Anderson St",
    "iso:country":"CA",
    "sg:address":"400 Anderson St",
    "sg:city":"Whitby",
    "sg:classifiers":[
        {
            "category":"Education",
            "subcategory":"School",
            "type":"Public Place"
        }
    ],
    "sg:phone":"+1 905 668 5809",
    "sg:postcode":"L1N 3V6",
    "sg:province":"ON",
    "wof:name":"Cvi Anderson",
    "wof:placetype":"venue"
},
  "geometry": {"coordinates":[-78.9240951538,43.8877677917],"type":"Point"}
}