{
  "type": "Feature",
  "properties": {
    "iso:country":"CA",
    "sg:address":"252 Dundas St",
    "sg:city":"London",
    "sg:classifiers":[
        {
            "category":"Restaurant",
            "type":"Food & Drink"
        }
    ],
    "sg:phone":"+1 519 660 3658",
    "sg:postcode":"N6A 1H3",
    "sg:province":"ON",
    "wof:name":"Arby's",
    "wof:placetype":"venue"
},
  "geometry": {"coordinates":[-81.24621582029999,42.9848175049],"type":"Point"}
}