{
  "type": "Feature",
  "properties": {
    "addr:full":"1950 Boul Du Cure-Labelle Saint-Jerome QC J7Y 1S1",
    "addr:housenumber":"1950",
    "addr:postcode":"j7y 1s1",
    "addr:street":"Boul Du Cure-Labelle Saint-Jerome",
    "iso:country":"CA",
    "sg:address":"1950 Boul Du Cure-Labelle",
    "sg:city":"Saint-Jerome",
    "sg:classifiers":[
        {
            "category":"Shopping",
            "subcategory":"Pharmacy",
            "type":"Retail Goods"
        }
    ],
    "sg:phone":"+1 450 432 9771",
    "sg:postcode":"J7Y 1S1",
    "sg:province":"QC",
    "wof:name":"Brunet Pharmacie Affiliee",
    "wof:placetype":"venue"
},
  "geometry": {"coordinates":[-74.00891900000001,45.794289],"type":"Point"}
}