{
  "type": "Feature",
  "properties": {
    "addr:full":"PO Box 145 STN Main Port Hope ON L1A 3W3",
    "addr:housenumber":"po",
    "addr:postcode":"l1a 3w3",
    "addr:street":"Box 145 Stn Main",
    "iso:country":"CA",
    "sg:address":"PO Box 145 STN Main",
    "sg:city":"Port Hope",
    "sg:classifiers":[
        {
            "category":"Building & Trades",
            "subcategory":"Landscaping Services",
            "type":"Services"
        }
    ],
    "sg:phone":"+1 905 885 2965",
    "sg:postcode":"L1A 3W3",
    "sg:province":"ON",
    "sg:tags":[
        "landscape",
        "contractor"
    ],
    "wof:name":"Weed Man",
    "wof:placetype":"venue"
},
  "geometry": {"coordinates":[-79.91278076170001,43.1599464417],"type":"Point"}
}