{
  "type": "Feature",
  "properties": {
    "addr:full":"159 Cardevco Rd Carp ON K0A 1L0",
    "addr:housenumber":"159",
    "addr:postcode":"k0a 1l0",
    "addr:street":"Cardevco Rd",
    "iso:country":"CA",
    "sg:address":"159 Cardevco Rd",
    "sg:city":"Carp",
    "sg:classifiers":[
        {
            "category":"Home & Garden",
            "subcategory":"Building Materials",
            "type":"Retail Goods"
        }
    ],
    "sg:phone":"+1 613 831 2169",
    "sg:postcode":"K0A 1L0",
    "sg:province":"ON",
    "sg:tags":[
        "door",
        "molding"
    ],
    "wof:name":"Trimcor",
    "wof:placetype":"venue"
},
  "geometry": {"coordinates":[-75.978737,45.293171],"type":"Point"}
}