{
  "type": "Feature",
  "properties": {
    "addr:full":"69 Young St Sudbury ON P3E 3G5",
    "addr:housenumber":"69",
    "addr:postcode":"p3e 3g5",
    "addr:street":"Young St",
    "iso:country":"CA",
    "sg:address":"69 Young St",
    "sg:city":"Sudbury",
    "sg:classifiers":[
        {
            "category":"Education",
            "subcategory":"School",
            "type":"Public Place"
        }
    ],
    "sg:phone":"+1 705 674 3171",
    "sg:postcode":"P3E 3G5",
    "sg:province":"ON",
    "wof:name":"Rainbow District School Board",
    "wof:placetype":"venue"
},
  "geometry": {"coordinates":[-80.99076843260001,46.4919586182],"type":"Point"}
}