{
  "type": "Feature",
  "properties": {
    "addr:full":"8295 Rue Pascal-Gagnon Saint-Leonard QC H1P 1Y5",
    "addr:housenumber":"8295",
    "addr:postcode":"h1p 1y5",
    "addr:street":"Rue Pascal-Gagnon",
    "iso:country":"CA",
    "sg:address":"8295 Rue Pascal-Gagnon",
    "sg:city":"Saint-Leonard",
    "sg:classifiers":[
        {
            "category":"Retail",
            "subcategory":"Auto Repair",
            "type":"Services"
        }
    ],
    "sg:phone":"+1 514 327 9323",
    "sg:postcode":"H1P 1Y5",
    "sg:province":"QC",
    "sg:tags":[
        "body",
        "automobile",
        "painting"
    ],
    "wof:name":"Carrosserie Lucien Breard Enr",
    "wof:placetype":"venue"
},
  "geometry": {"coordinates":[-73.582481,45.600128],"type":"Point"}
}