{
  "type": "Feature",
  "properties": {
    "addr:full":"Kelowna BC V1V 1P8",
    "addr:postcode":"v1v 1p8",
    "iso:country":"CA",
    "sg:city":"Kelowna",
    "sg:classifiers":[
        {
            "category":"Organizations",
            "subcategory":"Community Association",
            "type":"Services"
        }
    ],
    "sg:phone":"+1 250 762 2396",
    "sg:postcode":"V1V 1P8",
    "sg:province":"BC",
    "sg:tags":[
        "club"
    ],
    "wof:name":"Sandpointe Club House",
    "wof:placetype":"venue"
},
  "geometry": {"coordinates":[-119.446884,49.908524],"type":"Point"}
}