{
  "type": "Feature",
  "properties": {
    "addr:full":"51 Keefer Crt Hamilton ON L8E 4W8",
    "addr:housenumber":"51",
    "addr:postcode":"l8e 4w8",
    "addr:street":"Keefer Crt",
    "iso:country":"CA",
    "sg:address":"51 Keefer Crt",
    "sg:city":"Hamilton",
    "sg:classifiers":[
        {
            "category":"Travel",
            "subcategory":"Hotels & Motels",
            "type":"Entertainment"
        }
    ],
    "sg:phone":"+1 905 578 1212",
    "sg:postcode":"L8E 4W8",
    "sg:province":"ON",
    "wof:name":"Holiday Inn Express",
    "wof:placetype":"venue"
},
  "geometry": {"coordinates":[-79.760651,43.245735],"type":"Point"}
}