{
  "type": "Feature",
  "properties": {
    "addr:full":"36 Niagara St Welland ON L3C 1H9",
    "addr:housenumber":"36",
    "addr:postcode":"l3c 1h9",
    "addr:street":"Niagara St",
    "iso:country":"CA",
    "sg:address":"36 Niagara St",
    "sg:city":"Welland",
    "sg:classifiers":[
        {
            "category":"Home & Garden",
            "subcategory":"Furniture",
            "type":"Retail Goods"
        }
    ],
    "sg:phone":"+1 905 384 0292",
    "sg:postcode":"L3C 1H9",
    "sg:province":"ON",
    "sg:tags":[
        "mattress"
    ],
    "wof:name":"Sleep Factory",
    "wof:placetype":"venue"
},
  "geometry": {"coordinates":[-79.25249481199999,42.9923095703],"type":"Point"}
}