{
  "type": "Feature",
  "properties": {
    "addr:full":"2530 Alberni Hwy Coombs BC V0R 1M0",
    "addr:housenumber":"2530",
    "addr:postcode":"v0r 1m0",
    "addr:street":"Alberni Hwy",
    "iso:country":"CA",
    "sg:address":"2530 Alberni Hwy",
    "sg:city":"Coombs",
    "sg:classifiers":[
        {
            "category":"Wholesale",
            "subcategory":"Auto Parts",
            "type":"Manufacturing & Wholesale Goods"
        }
    ],
    "sg:phone":"+1 250 248 7191",
    "sg:postcode":"V0R 1M0",
    "sg:province":"BC",
    "sg:tags":[
        "automobile",
        "wrecking"
    ],
    "wof:name":"Mid-Island Used Auto Parts Ltd",
    "wof:placetype":"venue"
},
  "geometry": {"coordinates":[-124.417739868,49.305431366],"type":"Point"}
}