{
  "type": "Feature",
  "properties": {
    "addr:full":"1015 Bank St Ottawa ON K1S 3W7",
    "addr:housenumber":"1015",
    "addr:postcode":"k1s 3w7",
    "addr:street":"Bank St",
    "iso:country":"CA",
    "sg:address":"1015 Bank St",
    "sg:city":"Ottawa",
    "sg:classifiers":[
        {
            "category":"Recreation",
            "type":"Entertainment"
        }
    ],
    "sg:phone":"+1 613 232 6767",
    "sg:postcode":"K1S 3W7",
    "sg:province":"ON",
    "sg:tags":[
        "club",
        "hockey"
    ],
    "wof:name":"Ottawa 67's Hockey Club",
    "wof:placetype":"venue"
},
  "geometry": {"coordinates":[-75.68498200000001,45.39743],"type":"Point"}
}