{
  "type": "Feature",
  "properties": {
    "addr:full":"5115 50 Ave Drayton Valley AB T7A 1J7",
    "addr:housenumber":"5115",
    "addr:postcode":"t7a 1j7",
    "addr:street":"50 Ave",
    "iso:country":"CA",
    "sg:address":"5115 50 Ave",
    "sg:city":"Drayton Valley",
    "sg:classifiers":[
        {
            "category":"Real Estate",
            "subcategory":"Real Estate Agent",
            "type":"Services"
        }
    ],
    "sg:phone":"+1 780 542 4800",
    "sg:postcode":"T7A 1J7",
    "sg:province":"AB",
    "wof:name":"Venture Realty Inc",
    "wof:placetype":"venue"
},
  "geometry": {"coordinates":[-114.97633399999999,53.221378],"type":"Point"}
}