{
  "type": "Feature",
  "properties": {
    "addr:full":"500 Simpson St Thunder Bay ON P7C 3J4",
    "addr:housenumber":"500",
    "addr:postcode":"p7c 3j4",
    "addr:street":"Simpson St",
    "iso:country":"CA",
    "sg:address":"500 Simpson St",
    "sg:city":"Thunder Bay",
    "sg:classifiers":[
        {
            "category":"Freight",
            "type":"Transportation"
        }
    ],
    "sg:phone":"+1 807 623 7433",
    "sg:postcode":"P7C 3J4",
    "sg:province":"ON",
    "sg:tags":[
        "commercial",
        "storage"
    ],
    "wof:name":"Warehouse 500",
    "wof:placetype":"venue"
},
  "geometry": {"coordinates":[-89.237663269,48.3903198242],"type":"Point"}
}