{
  "type": "Feature",
  "properties": {
    "addr:full":"125 Mill St Stouffville ON L4A 1J2",
    "addr:housenumber":"125",
    "addr:postcode":"l4a 1j2",
    "addr:street":"Mill St",
    "iso:country":"CA",
    "sg:address":"125 Mill St",
    "sg:city":"Stouffville",
    "sg:classifiers":[
        {
            "category":"Banks & Credit Unions",
            "subcategory":"Investment Brokerage",
            "type":"Services"
        }
    ],
    "sg:phone":"+1 905 640 9034",
    "sg:postcode":"L4A 1J2",
    "sg:province":"ON",
    "sg:tags":[
        "consultant",
        "planning",
        "financial"
    ],
    "wof:name":"Hugh Dodd Investments & Ins",
    "wof:placetype":"venue"
},
  "geometry": {"coordinates":[-79.24839,43.97451],"type":"Point"}
}