{
  "type": "Feature",
  "properties": {
    "iso:country":"CA",
    "sg:address":"766 Colborne St",
    "sg:city":"Brantford",
    "sg:classifiers":[
        {
            "category":"Real Estate",
            "subcategory":"Real Estate Agent",
            "type":"Services"
        }
    ],
    "sg:phone":"+1 519 753 7311",
    "sg:postcode":"N3S 3S1",
    "sg:province":"ON",
    "wof:name":"Royal Le Page Action Realty",
    "wof:placetype":"venue"
},
  "geometry": {"coordinates":[-80.2285461426,43.143535614],"type":"Point"}
}