{
  "type": "Feature",
  "properties": {
    "addr:full":"1040 Kelly Lake Rd Sudbury ON P3E 5P4",
    "addr:housenumber":"1040",
    "addr:postcode":"p3e 5p4",
    "addr:street":"Kelly Lake Rd",
    "iso:country":"CA",
    "sg:address":"1040 Kelly Lake Rd",
    "sg:city":"Sudbury",
    "sg:classifiers":[
        {
            "category":"Retail",
            "subcategory":"Repair Shop",
            "type":"Services"
        }
    ],
    "sg:phone":"+1 705 675 3000",
    "sg:postcode":"P3E 5P4",
    "sg:province":"ON",
    "sg:tags":[
        "sharpening",
        "rental"
    ],
    "wof:name":"Toojacks Rentals & Sales Ltd",
    "wof:placetype":"venue"
},
  "geometry": {"coordinates":[-81.037453,46.469921],"type":"Point"}
}