{
  "type": "Feature",
  "properties": {
    "iso:country":"CA",
    "sg:city":"Calgary",
    "sg:classifiers":[
        {
            "category":"Shopping",
            "subcategory":"Computers & Home Electronics",
            "type":"Retail Goods"
        }
    ],
    "sg:phone":"+1 403 220 9066",
    "sg:postcode":"T2K 1A3",
    "sg:province":"AB",
    "sg:tags":[
        "game",
        "video"
    ],
    "wof:name":"Movies To Go",
    "wof:placetype":"venue"
},
  "geometry": {"coordinates":[-114.071747,51.087742],"type":"Point"}
}