{
  "type": "Feature",
  "properties": {
    "addr:full":"20454 Trans Canada Hwy Crapaud PE C0A 1J0",
    "addr:housenumber":"20454",
    "addr:postcode":"c0a 1j0",
    "addr:street":"Trans Canada Hwy",
    "iso:country":"CA",
    "sg:address":"20454 Trans Canada Hwy",
    "sg:city":"Crapaud",
    "sg:classifiers":[
        {
            "category":"Shopping",
            "subcategory":"Florist",
            "type":"Retail Goods"
        }
    ],
    "sg:phone":"+1 902 658 2971",
    "sg:postcode":"C0A 1J0",
    "sg:province":"PE",
    "wof:name":"In Full Bloom Florist & Gifts",
    "wof:placetype":"venue"
},
  "geometry": {"coordinates":[-63.499512,46.237694],"type":"Point"}
}