{
  "type": "Feature",
  "properties": {
    "addr:full":"Burlington ON L7R 4X6",
    "addr:postcode":"l7r 4x6",
    "iso:country":"CA",
    "sg:city":"Burlington",
    "sg:classifiers":[
        {
            "category":"Health Services",
            "subcategory":"Chiropractor",
            "type":"Services"
        }
    ],
    "sg:phone":"+1 905 634 8598",
    "sg:postcode":"L7R 4X6",
    "sg:province":"ON",
    "sg:tags":[
        "clinic"
    ],
    "wof:name":"Burlington Family Chiropractic",
    "wof:placetype":"venue"
},
  "geometry": {"coordinates":[-79.818321,43.33913],"type":"Point"}
}