{
  "type": "Feature",
  "properties": {
    "iso:country":"CA",
    "sg:address":"20 Maud St",
    "sg:city":"Toronto",
    "sg:classifiers":[
        {
            "category":"Professional",
            "subcategory":"Art Services",
            "type":"Services"
        }
    ],
    "sg:phone":"+1 416 504 7600",
    "sg:postcode":"M5V 2M5",
    "sg:province":"ON",
    "sg:tags":[
        "illustrator"
    ],
    "wof:name":"I2I Art Inc",
    "wof:placetype":"venue"
},
  "geometry": {"coordinates":[-79.399544,43.646275],"type":"Point"}
}