{
  "type": "Feature",
  "properties": {
    "iso:country":"CA",
    "sg:address":"2132 Buckingham Crt",
    "sg:city":"Burlington",
    "sg:classifiers":[
        {
            "category":"Real Estate",
            "subcategory":"Real Estate Agent",
            "type":"Services"
        }
    ],
    "sg:phone":"+1 905 332 3651",
    "sg:postcode":"L7P 1P5",
    "sg:province":"ON",
    "wof:name":"Buzza Realty Inc",
    "wof:placetype":"venue"
},
  "geometry": {"coordinates":[-79.8523025513,43.3465576172],"type":"Point"}
}