{
  "type": "Feature",
  "properties": {
    "addr:full":"6180 Scott Rd Vernon BC V1H 1N4",
    "addr:housenumber":"6180",
    "addr:postcode":"v1h 1n4",
    "addr:street":"Scott Rd",
    "iso:country":"CA",
    "sg:address":"6180 Scott Rd",
    "sg:city":"Vernon",
    "sg:classifiers":[
        {
            "category":"Building & Trades",
            "subcategory":"Construction",
            "type":"Services"
        }
    ],
    "sg:phone":"+1 250 542 6240",
    "sg:postcode":"V1H 1N4",
    "sg:province":"BC",
    "sg:tags":[
        "general",
        "contractor"
    ],
    "wof:name":"L Steiner Construction Ltd",
    "wof:placetype":"venue"
},
  "geometry": {"coordinates":[-119.322891,50.252094],"type":"Point"}
}