{
  "type": "Feature",
  "properties": {
    "addr:full":"304 Walton Pl Victoria BC V9E 2A4",
    "addr:housenumber":"304",
    "addr:postcode":"v9e 2a4",
    "addr:street":"Walton Pl",
    "iso:country":"CA",
    "sg:address":"304 Walton Pl",
    "sg:city":"Victoria",
    "sg:classifiers":[
        {
            "category":"Home & Garden",
            "subcategory":"Garden Supply",
            "type":"Retail Goods"
        }
    ],
    "sg:phone":"+1 250 658 5888",
    "sg:postcode":"V9E 2A4",
    "sg:province":"BC",
    "sg:tags":[
        "nurseryman",
        "center"
    ],
    "wof:name":"Coteau Farms",
    "wof:placetype":"venue"
},
  "geometry": {"coordinates":[-123.364517212,48.428314209],"type":"Point"}
}