{
  "type": "Feature",
  "properties": {
    "addr:full":"243 Rue Victoria Salaberry-DE-Valleyfield QC J6T 1A9",
    "addr:housenumber":"243",
    "addr:postcode":"j6t 1a9",
    "addr:street":"Rue Victoria",
    "iso:country":"CA",
    "sg:address":"243 Rue Victoria",
    "sg:city":"Salaberry-DE-Valleyfield",
    "sg:classifiers":[
        {
            "category":"Shopping",
            "subcategory":"Clothing, Apparel, & Fashions",
            "type":"Retail Goods"
        }
    ],
    "sg:phone":"+1 450 371 9045",
    "sg:postcode":"J6T 1A9",
    "sg:province":"QC",
    "sg:tags":[
        "lingerie"
    ],
    "wof:name":"Lingerie Frou-Frou Ltee",
    "wof:placetype":"venue"
},
  "geometry": {"coordinates":[-74.131523,45.256306],"type":"Point"}
}