{
  "type": "Feature",
  "properties": {
    "addr:full":"370 Rang Saint-Olivier Saint-Anselme QC G0R 2N0",
    "addr:housenumber":"370",
    "addr:postcode":"g0r 2n0",
    "addr:street":"Rang Saint-Olivier",
    "iso:country":"CA",
    "sg:address":"370 Rang Saint-Olivier",
    "sg:city":"Saint-Anselme",
    "sg:classifiers":[
        {
            "category":"Professional",
            "type":"Services"
        }
    ],
    "sg:phone":"+1 418 885 4211",
    "sg:postcode":"G0R 2N0",
    "sg:province":"QC",
    "sg:tags":[
        "breeder",
        "establishment",
        "livestock"
    ],
    "wof:name":"Alfred Couture Ltee",
    "wof:placetype":"venue"
},
  "geometry": {"coordinates":[-70.97727999999999,46.608978],"type":"Point"}
}