{
  "type": "Feature",
  "properties": {
    "addr:full":"955 10th St W Owen Sound ON N4K 5S2",
    "addr:housenumber":"955",
    "addr:postcode":"n4k 5s2",
    "addr:street":"10Th St W",
    "iso:country":"CA",
    "sg:address":"955 10th St W",
    "sg:city":"Owen Sound",
    "sg:classifiers":[
        {
            "category":"Shopping",
            "subcategory":"Department Store",
            "type":"Retail Goods"
        }
    ],
    "sg:phone":"+1 519 376 9148",
    "sg:postcode":"N4K 5S2",
    "sg:province":"ON",
    "sg:tags":[
        "shop"
    ],
    "wof:name":"Deals",
    "wof:placetype":"venue"
},
  "geometry": {"coordinates":[-80.962158,44.565979],"type":"Point"}
}