{
  "type": "Feature",
  "properties": {
    "addr:full":"6150 Lougheed Hwy Burnaby BC V5B 2Z9",
    "addr:housenumber":"6150",
    "addr:postcode":"v5b 2z9",
    "addr:street":"Lougheed Hwy",
    "iso:country":"CA",
    "sg:address":"6150 Lougheed Hwy",
    "sg:city":"Burnaby",
    "sg:classifiers":[
        {
            "category":"Wholesale",
            "subcategory":"Construction Materials",
            "type":"Manufacturing & Wholesale Goods"
        }
    ],
    "sg:phone":"+1 604 294 6666",
    "sg:postcode":"V5B 2Z9",
    "sg:province":"BC",
    "sg:tags":[
        "resurfacing",
        "molding",
        "laying",
        "refinishing",
        "floor"
    ],
    "wof:name":"Finishing Touch Doors Mldng",
    "wof:placetype":"venue"
},
  "geometry": {"coordinates":[-122.97509002699999,49.2629318237],"type":"Point"}
}