{
  "type": "Feature",
  "properties": {
    "addr:full":"220 Principale St S Waterville QC J0B 3H0",
    "addr:housenumber":"220",
    "addr:postcode":"j0b 3h0",
    "addr:street":"Principale St S",
    "iso:country":"CA",
    "sg:address":"220 Principale St S",
    "sg:city":"Waterville",
    "sg:classifiers":[
        {
            "category":"Food & Beverages",
            "subcategory":"Groceries & Convenience Stores",
            "type":"Retail Goods"
        }
    ],
    "sg:phone":"+1 819 837 2351",
    "sg:postcode":"J0B 3H0",
    "sg:province":"QC",
    "sg:tags":[
        "grocer"
    ],
    "wof:name":"Marche Garneau",
    "wof:placetype":"venue"
},
  "geometry": {"coordinates":[-71.8907699585,45.2774085999],"type":"Point"}
}