{
  "type": "Feature",
  "properties": {
    "addr:full":"3 Ateah Rd Victoria Beach MB R0E 2C0",
    "addr:housenumber":"3",
    "addr:postcode":"r0e 2c0",
    "addr:street":"Ateah Rd",
    "iso:country":"CA",
    "sg:address":"3 Ateah Rd",
    "sg:city":"Victoria Beach",
    "sg:classifiers":[
        {
            "category":"Social Services",
            "type":"Services"
        }
    ],
    "sg:phone":"+1 204 756 6471",
    "sg:postcode":"R0E 2C0",
    "sg:province":"MB",
    "sg:tags":[
        "senior",
        "citizen"
    ],
    "wof:name":"Help Ctr",
    "wof:placetype":"venue"
},
  "geometry": {"coordinates":[-96.530128,50.698463],"type":"Point"}
}