{
  "type": "Feature",
  "properties": {
    "addr:full":"5014 47 Ave Taber AB T1G 1P9",
    "addr:housenumber":"5014",
    "addr:postcode":"t1g 1p9",
    "addr:street":"47 Ave",
    "iso:country":"CA",
    "sg:address":"5014 47 Ave",
    "sg:city":"Taber",
    "sg:classifiers":[
        {
            "category":"Autos & Motor Vehicles",
            "subcategory":"Fuel & Gas Station",
            "type":"Retail Goods"
        }
    ],
    "sg:phone":"+1 403 223 9307",
    "sg:postcode":"T1G 1P9",
    "sg:province":"AB",
    "sg:tags":[
        "oil"
    ],
    "wof:name":"Short Stop Food Store",
    "wof:placetype":"venue"
},
  "geometry": {"coordinates":[-112.148399353,49.7828445435],"type":"Point"}
}