{
  "type": "Feature",
  "properties": {
    "addr:full":"470 Rue Gilford Montreal QC H2J 1N3",
    "addr:housenumber":"470",
    "addr:postcode":"h2j 1n3",
    "addr:street":"Rue Gilford",
    "iso:country":"CA",
    "sg:address":"470 Rue Gilford",
    "sg:city":"Montreal",
    "sg:classifiers":[
        {
            "category":"Organizations",
            "subcategory":"Religious Organization",
            "type":"Services"
        }
    ],
    "sg:phone":"+1 514 849 8999",
    "sg:postcode":"H2J 1N3",
    "sg:province":"QC",
    "sg:tags":[
        "church"
    ],
    "wof:name":"Eglise DE Jesus Christ-Saints",
    "wof:placetype":"venue"
},
  "geometry": {"coordinates":[-73.5861816406,45.5264396667],"type":"Point"}
}