{
  "type": "Feature",
  "properties": {
    "addr:full":"15156 Boul Gouin O Sainte-Genevieve QC H9H 1B5",
    "addr:housenumber":"15156",
    "addr:postcode":"h9h 1b5",
    "addr:street":"Boul Gouin O Sainte-Genevieve",
    "iso:country":"CA",
    "sg:address":"15156 Boul Gouin O",
    "sg:city":"Sainte-Genevieve",
    "sg:classifiers":[
        {
            "category":"Health Services",
            "subcategory":"Doctor",
            "type":"Services"
        }
    ],
    "sg:phone":"+1 514 620 1838",
    "sg:postcode":"H9H 1B5",
    "sg:province":"QC",
    "sg:tags":[
        "dentist"
    ],
    "wof:name":"Bonin, Michel DDS",
    "wof:placetype":"venue"
},
  "geometry": {"coordinates":[-73.86238899999999,45.486469],"type":"Point"}
}