{
  "type": "Feature",
  "properties": {
    "addr:full":"22 Carnforth Rd North York ON M4A 2K7",
    "addr:housenumber":"22",
    "addr:postcode":"m4a 2k7",
    "addr:street":"Carnforth Rd",
    "iso:country":"CA",
    "sg:address":"22 Carnforth Rd",
    "sg:city":"North York",
    "sg:classifiers":[
        {
            "category":"Organizations",
            "subcategory":"Religious Organization",
            "type":"Services"
        }
    ],
    "sg:phone":"+1 416 615 2204",
    "sg:postcode":"M4A 2K7",
    "sg:province":"ON",
    "sg:tags":[
        "church"
    ],
    "wof:name":"East Toronto Chinese Baptist",
    "wof:placetype":"venue"
},
  "geometry": {"coordinates":[-79.315322876,43.740070343],"type":"Point"}
}