{
  "type": "Feature",
  "properties": {
    "addr:full":"16 Stanley St Ayr ON N0B 1E0",
    "addr:housenumber":"16",
    "addr:postcode":"n0b 1e0",
    "addr:street":"Stanley St",
    "iso:country":"CA",
    "sg:address":"16 Stanley St",
    "sg:city":"Ayr",
    "sg:classifiers":[
        {
            "category":"Insurance",
            "subcategory":"Insurance Agent",
            "type":"Services"
        }
    ],
    "sg:phone":"+1 519 632 7494",
    "sg:postcode":"N0B 1E0",
    "sg:province":"ON",
    "wof:name":"Dalrymple Insurance Brkrs Ltd",
    "wof:placetype":"venue"
},
  "geometry": {"coordinates":[-80.4507522583,43.2855262756],"type":"Point"}
}