{
  "type": "Feature",
  "properties": {
    "addr:full":"1764 Boul Wilfrid-Hamel Quebec QC G1N 3Y8",
    "addr:housenumber":"1764",
    "addr:postcode":"g1n 3y8",
    "addr:street":"Boul Wilfrid-Hamel",
    "iso:country":"CA",
    "sg:address":"1764 Boul Wilfrid-Hamel",
    "sg:city":"Quebec",
    "sg:classifiers":[
        {
            "category":"Wholesale",
            "subcategory":"Hardware",
            "type":"Manufacturing & Wholesale Goods"
        }
    ],
    "sg:phone":"+1 418 681 0808",
    "sg:postcode":"G1N 3Y8",
    "sg:province":"QC",
    "sg:tags":[
        "refrigerating"
    ],
    "wof:name":"T R Refrigeration Inc",
    "wof:placetype":"venue"
},
  "geometry": {"coordinates":[-71.28095245359999,46.8059043884],"type":"Point"}
}