{
  "type": "Feature",
  "properties": {
    "addr:full":"558 Park Royal N West Vancouver BC V7T 1H9",
    "addr:housenumber":"558",
    "addr:postcode":"v7t 1h9",
    "addr:street":"Park Royal N",
    "iso:country":"CA",
    "sg:address":"558 Park Royal N",
    "sg:city":"West Vancouver",
    "sg:classifiers":[
        {
            "category":"Health Services",
            "subcategory":"Optometrist",
            "type":"Services"
        }
    ],
    "sg:phone":"+1 604 925 8968",
    "sg:postcode":"V7T 1H9",
    "sg:province":"BC",
    "wof:name":"Wong, Gordon OD",
    "wof:placetype":"venue"
},
  "geometry": {"coordinates":[-123.134887695,49.3275909424],"type":"Point"}
}