{
  "type": "Feature",
  "properties": {
    "addr:full":"11535 1E Av Saint-Georges QC G5Y 7H5",
    "addr:housenumber":"11535",
    "addr:postcode":"g5y 7h5",
    "addr:street":"1E Av",
    "iso:country":"CA",
    "sg:address":"11535 1E Av",
    "sg:city":"Saint-Georges",
    "sg:classifiers":[
        {
            "category":"Restaurant",
            "type":"Food & Drink"
        }
    ],
    "sg:phone":"+1 418 226 0255",
    "sg:postcode":"G5Y 7H5",
    "sg:province":"QC",
    "wof:name":"Mc Donald's",
    "wof:placetype":"venue"
},
  "geometry": {"coordinates":[-70.67115,46.123348],"type":"Point"}
}