{
  "type": "Feature",
  "properties": {
    "iso:country":"CA",
    "sg:address":"144 Armstrong Ave",
    "sg:city":"Georgetown",
    "sg:classifiers":[
        {
            "category":"Manufacturing",
            "subcategory":"Furniture",
            "type":"Manufacturing & Wholesale Goods"
        }
    ],
    "sg:phone":"+1 905 702 1336",
    "sg:postcode":"L7G 4S3",
    "sg:province":"ON",
    "sg:tags":[
        "woodworker"
    ],
    "wof:name":"Woodworking Solutions Inc",
    "wof:placetype":"venue"
},
  "geometry": {"coordinates":[-79.889877,43.655853],"type":"Point"}
}