{
  "type": "Feature",
  "properties": {
    "addr:full":"40 Elmartin Dr Scarborough ON M1W 3C5",
    "addr:housenumber":"40",
    "addr:postcode":"m1w 3c5",
    "addr:street":"Elmartin Dr",
    "iso:country":"CA",
    "sg:address":"40 Elmartin Dr",
    "sg:city":"Scarborough",
    "sg:classifiers":[
        {
            "category":"Local Transit",
            "type":"Transportation"
        }
    ],
    "sg:phone":"+1 416 502 2522",
    "sg:postcode":"M1W 3C5",
    "sg:province":"ON",
    "sg:tags":[
        "limousine"
    ],
    "wof:name":"Canadian National Limousine",
    "wof:placetype":"venue"
},
  "geometry": {"coordinates":[-79.31690999999999,43.81279],"type":"Point"}
}