{
  "type": "Feature",
  "properties": {
    "addr:full":"1687 Sunrise Rd Kelowna BC V1P 1G3",
    "addr:housenumber":"1687",
    "addr:postcode":"v1p 1g3",
    "addr:street":"Sunrise Rd",
    "iso:country":"CA",
    "sg:address":"1687 Sunrise Rd",
    "sg:city":"Kelowna",
    "sg:classifiers":[
        {
            "category":"Building & Trades",
            "subcategory":"Cleaning & Sanitation",
            "type":"Services"
        }
    ],
    "sg:phone":"+1 250 491 9311",
    "sg:postcode":"V1P 1G3",
    "sg:province":"BC",
    "sg:tags":[
        "janitor"
    ],
    "wof:name":"Ned's Cleaning Svc",
    "wof:placetype":"venue"
},
  "geometry": {"coordinates":[-119.355262756,49.8631286621],"type":"Point"}
}