{
  "type": "Feature",
  "properties": {
    "addr:full":"2096 Commercial Dr Vancouver BC V5N 4B2",
    "addr:housenumber":"2096",
    "addr:postcode":"v5n 4b2",
    "addr:street":"Commercial Dr",
    "iso:country":"CA",
    "sg:address":"2096 Commercial Dr",
    "sg:city":"Vancouver",
    "sg:classifiers":[
        {
            "category":"Restaurant",
            "type":"Food & Drink"
        }
    ],
    "sg:phone":"+1 604 254 1195",
    "sg:postcode":"V5N 4B2",
    "sg:province":"BC",
    "wof:name":"Cafe Deux Soleil",
    "wof:placetype":"venue"
},
  "geometry": {"coordinates":[-123.069672,49.2659],"type":"Point"}
}