{
  "type": "Feature",
  "properties": {
    "iso:country":"CA",
    "sg:address":"2655 Rue Sicard",
    "sg:city":"Montreal",
    "sg:classifiers":[
        {
            "category":"Professional",
            "subcategory":"Detective & Security Services",
            "type":"Services"
        }
    ],
    "sg:phone":"+1 514 256 9557",
    "sg:postcode":"H1V 2Y8",
    "sg:province":"QC",
    "sg:tags":[
        "burglary",
        "protective",
        "robbery"
    ],
    "wof:name":"Gti Securite Inc",
    "wof:placetype":"venue"
},
  "geometry": {"coordinates":[-73.5466,45.55957],"type":"Point"}
}