{
  "type": "Feature",
  "properties": {
    "addr:full":"8040 Manson St Mission BC V2V 6P6",
    "addr:housenumber":"8040",
    "addr:postcode":"v2v 6p6",
    "addr:street":"Manson St",
    "iso:country":"CA",
    "sg:address":"8040 Manson St",
    "sg:city":"Mission",
    "sg:classifiers":[
        {
            "category":"Building & Trades",
            "subcategory":"Construction",
            "type":"Services"
        }
    ],
    "sg:phone":"+1 604 820 0760",
    "sg:postcode":"V2V 6P6",
    "sg:province":"BC",
    "sg:tags":[
        "steel"
    ],
    "wof:name":"Don Harris Drafting Svc Ltd",
    "wof:placetype":"venue"
},
  "geometry": {"coordinates":[-122.26754,49.147644],"type":"Point"}
}