{
  "type": "Feature",
  "properties": {
    "addr:full":"398 Pearl St Burlington ON L7R 2M9",
    "addr:housenumber":"398",
    "addr:postcode":"l7r 2m9",
    "addr:street":"Pearl St",
    "iso:country":"CA",
    "sg:address":"398 Pearl St",
    "sg:city":"Burlington",
    "sg:classifiers":[
        {
            "category":"Personal",
            "subcategory":"Beauty Salon",
            "type":"Services"
        }
    ],
    "sg:phone":"+1 905 634 4085",
    "sg:postcode":"L7R 2M9",
    "sg:province":"ON",
    "wof:name":"Dagmar's Nails & Esthetics",
    "wof:placetype":"venue"
},
  "geometry": {"coordinates":[-79.794533,43.326321],"type":"Point"}
}