{
  "type": "Feature",
  "properties": {
    "addr:full":"219 Centre St Meadow Lake SK S9X 1L5",
    "addr:housenumber":"219",
    "addr:postcode":"s9x 1l5",
    "addr:street":"Centre St",
    "iso:country":"CA",
    "sg:address":"219 Centre St",
    "sg:city":"Meadow Lake",
    "sg:classifiers":[
        {
            "category":"Education",
            "subcategory":"School",
            "type":"Public Place"
        }
    ],
    "sg:phone":"+1 306 236 5991",
    "sg:postcode":"S9X 1L5",
    "sg:province":"SK",
    "sg:tags":[
        "training",
        "computer"
    ],
    "wof:name":"Academy of Learning Computer",
    "wof:placetype":"venue"
},
  "geometry": {"coordinates":[-108.432198,54.119946],"type":"Point"}
}