{
  "type": "Feature",
  "properties": {
    "addr:full":"1593 Ch Du Fer-A-Cheval Sainte-Julie QC J3E 1G5",
    "addr:postcode":"1593;j3e 1g5",
    "addr:street":"Ch Du Fer-A-Cheval",
    "iso:country":"CA",
    "sg:address":"1593 Ch Du Fer-A-Cheval",
    "sg:city":"Sainte-Julie",
    "sg:classifiers":[
        {
            "category":"Health Services",
            "subcategory":"Chiropractor",
            "type":"Services"
        }
    ],
    "sg:phone":"+1 450 649 1411",
    "sg:postcode":"J3E 1G5",
    "sg:province":"QC",
    "wof:name":"Clinique Chiro Ste-Julie",
    "wof:placetype":"venue"
},
  "geometry": {"coordinates":[-73.32708,45.587597],"type":"Point"}
}