{
  "type": "Feature",
  "properties": {
    "addr:full":"356 Queens Ave London ON N6B 1X6",
    "addr:housenumber":"356",
    "addr:postcode":"n6b 1x6",
    "addr:street":"Queens Ave",
    "iso:country":"CA",
    "sg:address":"356 Queens Ave",
    "sg:city":"London",
    "sg:classifiers":[
        {
            "category":"Social Services",
            "type":"Services"
        }
    ],
    "sg:phone":"+1 519 660 1430",
    "sg:postcode":"N6B 1X6",
    "sg:province":"ON",
    "sg:tags":[
        "senior",
        "citizen"
    ],
    "wof:name":"Meals on Wheels London",
    "wof:placetype":"venue"
},
  "geometry": {"coordinates":[-81.2426147461,42.9872627258],"type":"Point"}
}