{
  "type": "Feature",
  "properties": {
    "addr:full":"63 Milltown Blvd St Stephen NB E3L 1G4",
    "addr:housenumber":"63",
    "addr:postcode":"e3l 1g4",
    "addr:street":"Milltown Blvd",
    "iso:country":"CA",
    "sg:address":"63 Milltown Blvd",
    "sg:city":"St Stephen",
    "sg:classifiers":[
        {
            "category":"Restaurant",
            "type":"Food & Drink"
        }
    ],
    "sg:phone":"+1 506 466 3030",
    "sg:postcode":"E3L 1G4",
    "sg:province":"NB",
    "sg:tags":[
        "pizza"
    ],
    "wof:name":"Greco Pizza Donair",
    "wof:placetype":"venue"
},
  "geometry": {"coordinates":[-67.27788543699999,45.1927223206],"type":"Point"}
}