{
  "type": "Feature",
  "properties": {
    "addr:full":"32707 Mcrae Ave Mission BC V2V 2L8",
    "addr:postcode":"32707;v2v 2l8",
    "addr:street":"Mcrae Ave",
    "iso:country":"CA",
    "sg:address":"32707 Mcrae Ave",
    "sg:city":"Mission",
    "sg:classifiers":[
        {
            "category":"Building & Trades",
            "subcategory":"Plumbing",
            "type":"Services"
        }
    ],
    "sg:phone":"+1 604 826 2641",
    "sg:postcode":"V2V 2L8",
    "sg:province":"BC",
    "sg:tags":[
        "heating",
        "contractor"
    ],
    "wof:name":"Veltex Heating Ltd",
    "wof:placetype":"venue"
},
  "geometry": {"coordinates":[-122.31856500000001,49.143864],"type":"Point"}
}