{
  "type": "Feature",
  "properties": {
    "addr:full":"630 Scottsdale Dr Guelph ON N1G 3M2",
    "addr:housenumber":"630",
    "addr:postcode":"n1g 3m2",
    "addr:street":"Scottsdale Dr",
    "iso:country":"CA",
    "sg:address":"630 Scottsdale Dr",
    "sg:city":"Guelph",
    "sg:classifiers":[
        {
            "category":"Health Services",
            "subcategory":"Doctor",
            "type":"Services"
        }
    ],
    "sg:phone":"+1 519 836 5110",
    "sg:postcode":"N1G 3M2",
    "sg:province":"ON",
    "sg:tags":[
        "dentist"
    ],
    "wof:name":"Bacher, D B DDS",
    "wof:placetype":"venue"
},
  "geometry": {"coordinates":[-80.23833500000001,43.514889],"type":"Point"}
}