{
  "type": "Feature",
  "properties": {
    "iso:country":"CA",
    "sg:address":"58 Rossland Cres SE",
    "sg:city":"Medicine Hat",
    "sg:classifiers":[
        {
            "category":"Professional",
            "subcategory":"Engineering",
            "type":"Services"
        }
    ],
    "sg:phone":"+1 403 529 5863",
    "sg:postcode":"T1B 2B6",
    "sg:province":"AB",
    "sg:tags":[
        "engineer"
    ],
    "wof:name":"Diverse Engineering",
    "wof:placetype":"venue"
},
  "geometry": {"coordinates":[-110.62600707999999,50.004322052],"type":"Point"}
}