{
  "type": "Feature",
  "properties": {
    "iso:country":"CA",
    "sg:city":"Comox",
    "sg:classifiers":[
        {
            "category":"Health Services",
            "subcategory":"Doctor",
            "type":"Services"
        }
    ],
    "sg:phone":"+1 250 339 4525",
    "sg:postcode":"V9M 3M7",
    "sg:province":"BC",
    "sg:tags":[
        "dentist"
    ],
    "wof:name":"J A Hershmiller Inc",
    "wof:placetype":"venue"
},
  "geometry": {"coordinates":[-124.928749084,49.6743469238],"type":"Point"}
}