{
  "type": "Feature",
  "properties": {
    "iso:country":"CA",
    "sg:address":"1514 Broughton Boul",
    "sg:city":"Port Mcneill",
    "sg:classifiers":[
        {
            "category":"Recreation",
            "type":"Entertainment"
        }
    ],
    "sg:phone":"+1 250 956 9865",
    "sg:postcode":"V0N 2R0",
    "sg:province":"BC",
    "sg:tags":[
        "whale",
        "charter",
        "watching"
    ],
    "wof:name":"Mac Kay Whale Watching Ltd",
    "wof:placetype":"venue"
},
  "geometry": {"coordinates":[-127.08678436300001,50.5895767212],"type":"Point"}
}