{
  "type": "Feature",
  "properties": {
    "iso:country":"CA",
    "sg:address":"10960 104 St NW",
    "sg:city":"Edmonton",
    "sg:classifiers":[
        {
            "category":"Restaurant",
            "type":"Food & Drink"
        }
    ],
    "sg:phone":"+1 780 944 8086",
    "sg:postcode":"T5H 2W6",
    "sg:province":"AB",
    "wof:name":"Poilish Club Syrena",
    "wof:placetype":"venue"
},
  "geometry": {"coordinates":[-113.499465942,53.5558700562],"type":"Point"}
}