{
  "type": "Feature",
  "properties": {
    "addr:full":"1101 Wabasha St Winnipeg MB R2C 1G6",
    "addr:housenumber":"1101",
    "addr:postcode":"r2c 1g6",
    "addr:street":"Wabasha St",
    "iso:country":"CA",
    "sg:address":"1101 Wabasha St",
    "sg:city":"Winnipeg",
    "sg:classifiers":[
        {
            "category":"Recreation",
            "type":"Entertainment"
        }
    ],
    "sg:phone":"+1 204 986 6660",
    "sg:postcode":"R2C 1G6",
    "sg:province":"MB",
    "sg:tags":[
        "pool",
        "swimming"
    ],
    "wof:name":"Transcona Centennial Pool",
    "wof:placetype":"venue"
},
  "geometry": {"coordinates":[-96.998299,49.901779],"type":"Point"}
}