{
  "type": "Feature",
  "properties": {
    "addr:full":"Garden St Ignace ON P0T 1T0",
    "addr:postcode":"p0t 1t0",
    "addr:street":"Garden St",
    "iso:country":"CA",
    "sg:address":"Garden St",
    "sg:city":"Ignace",
    "sg:classifiers":[
        {
            "category":"Organizations",
            "subcategory":"Religious Organization",
            "type":"Services"
        }
    ],
    "sg:phone":"+1 807 934 2773",
    "sg:postcode":"P0T 1T0",
    "sg:province":"ON",
    "sg:tags":[
        "church"
    ],
    "wof:name":"Anglican Church",
    "wof:placetype":"venue"
},
  "geometry": {"coordinates":[-91.66005699999999,49.417416],"type":"Point"}
}