{
  "type": "Feature",
  "properties": {
    "addr:full":"28064 112 Ave Maple Ridge BC V2W 1M9",
    "addr:housenumber":"28064",
    "addr:postcode":"v2w 1m9",
    "addr:street":"112 Ave",
    "iso:country":"CA",
    "sg:address":"28064 112 Ave",
    "sg:city":"Maple Ridge",
    "sg:classifiers":[
        {
            "category":"Freight",
            "type":"Transportation"
        }
    ],
    "sg:phone":"+1 604 462 9726",
    "sg:postcode":"V2W 1M9",
    "sg:province":"BC",
    "sg:tags":[
        "trucking"
    ],
    "wof:name":"Rod Marquet Ltd",
    "wof:placetype":"venue"
},
  "geometry": {"coordinates":[-122.444076538,49.2054595947],"type":"Point"}
}