{
  "type": "Feature",
  "properties": {
    "iso:country":"CA",
    "sg:address":"2205 Shakespeare St",
    "sg:city":"Victoria",
    "sg:classifiers":[
        {
            "category":"Health Services",
            "subcategory":"Clinic",
            "type":"Services"
        }
    ],
    "sg:phone":"+1 250 595 2123",
    "sg:postcode":"V8R 4G2",
    "sg:province":"BC",
    "wof:name":"First Open Heart Socity of BC",
    "wof:placetype":"venue"
},
  "geometry": {"coordinates":[-123.335380554,48.4316978455],"type":"Point"}
}