{
  "type": "Feature",
  "properties": {
    "addr:full":"8 Rue Moise-Plante Salaberry-DE-Valleyfield QC J6T 5A8",
    "addr:housenumber":"8",
    "addr:postcode":"j6t 5a8",
    "addr:street":"Rue Moise-Plante",
    "iso:country":"CA",
    "sg:address":"8 Rue Moise-Plante",
    "sg:city":"Salaberry-DE-Valleyfield",
    "sg:classifiers":[
        {
            "category":"Home & Garden",
            "subcategory":"Building Materials",
            "type":"Retail Goods"
        }
    ],
    "sg:phone":"+1 450 377 2454",
    "sg:postcode":"J6T 5A8",
    "sg:province":"QC",
    "sg:tags":[
        "shower",
        "glass",
        "door",
        "enclosure"
    ],
    "wof:name":"Vitrerie Du Suroit",
    "wof:placetype":"venue"
},
  "geometry": {"coordinates":[-74.1224899292,45.2569465637],"type":"Point"}
}