{
  "type": "Feature",
  "properties": {
    "addr:full":"Toronto ON M5E 1B3",
    "addr:postcode":"m5e 1b3",
    "iso:country":"CA",
    "sg:city":"Toronto",
    "sg:classifiers":[
        {
            "category":"Professional",
            "subcategory":"Advertising",
            "type":"Services"
        }
    ],
    "sg:phone":"+1 416 363 6591",
    "sg:postcode":"M5E 1B3",
    "sg:province":"ON",
    "sg:tags":[
        "counselor"
    ],
    "wof:name":"Howe Brand Communications Inc",
    "wof:placetype":"venue"
},
  "geometry": {"coordinates":[-79.37447400000001,43.64793],"type":"Point"}
}