{
  "type": "Feature",
  "properties": {
    "addr:full":"5 Herriott St Perth ON K7H 3E5",
    "addr:housenumber":"5",
    "addr:postcode":"k7h 3e5",
    "addr:street":"Herriott St",
    "iso:country":"CA",
    "sg:address":"5 Herriott St",
    "sg:city":"Perth",
    "sg:classifiers":[
        {
            "category":"Wholesale",
            "subcategory":"Drugs",
            "type":"Manufacturing & Wholesale Goods"
        }
    ],
    "sg:phone":"+1 613 267 1881",
    "sg:postcode":"K7H 3E5",
    "sg:province":"ON",
    "sg:tags":[
        "cosmetic"
    ],
    "wof:name":"Perth Soap Inc",
    "wof:placetype":"venue"
},
  "geometry": {"coordinates":[-76.246048,44.902763],"type":"Point"}
}