{
  "type": "Feature",
  "properties": {
    "iso:country":"CA",
    "sg:city":"North York",
    "sg:classifiers":[
        {
            "category":"Shopping",
            "subcategory":"Tobacco",
            "type":"Retail Goods"
        }
    ],
    "sg:phone":"+1 416 250 1441",
    "sg:postcode":"M2N 6Z4",
    "sg:province":"ON",
    "sg:tags":[
        "cigarette",
        "cigar",
        "dealer"
    ],
    "wof:name":"Shefield & Sons Tobacconists",
    "wof:placetype":"venue"
},
  "geometry": {"coordinates":[-79.41236114500001,43.7679748535],"type":"Point"}
}