{
  "type": "Feature",
  "properties": {
    "iso:country":"CA",
    "sg:address":"2394 Rue Du Cantonnier",
    "sg:city":"Charny",
    "sg:classifiers":[
        {
            "category":"Retail",
            "subcategory":"Repair Shop",
            "type":"Services"
        }
    ],
    "sg:phone":"+1 418 832 2708",
    "sg:postcode":"G6X 2N5",
    "sg:province":"QC",
    "sg:tags":[
        "sharpening",
        "lawn",
        "mower"
    ],
    "wof:name":"Charny Equipement Enrg",
    "wof:placetype":"venue"
},
  "geometry": {"coordinates":[-71.27160644529999,46.7097129822],"type":"Point"}
}