{
  "type": "Feature",
  "properties": {
    "addr:full":"2394 Rue Du Cantonnier Charny QC G6X 2N5",
    "addr:housenumber":"2394",
    "addr:postcode":"g6x 2n5",
    "addr:street":"Rue Du Cantonnier",
    "iso:country":"CA",
    "sg:address":"2394 Rue Du Cantonnier",
    "sg:city":"Charny",
    "sg:classifiers":[
        {
            "category":"Retail",
            "subcategory":"Repair Shop",
            "type":"Services"
        }
    ],
    "sg:phone":"+1 418 832 2708",
    "sg:postcode":"G6X 2N5",
    "sg:province":"QC",
    "sg:tags":[
        "sharpening",
        "lawn",
        "mower"
    ],
    "wof:name":"Charny Equipement Enrg",
    "wof:placetype":"venue"
},
  "geometry": {"coordinates":[-71.27160644529999,46.7097129822],"type":"Point"}
}