{
  "type": "Feature",
  "properties": {
    "addr:full":"255 Davie Rd Kelowna BC V1X 3Y6",
    "addr:housenumber":"255",
    "addr:postcode":"v1x 3y6",
    "addr:street":"Davie Rd",
    "iso:country":"CA",
    "sg:address":"255 Davie Rd",
    "sg:city":"Kelowna",
    "sg:classifiers":[
        {
            "category":"Building & Trades",
            "subcategory":"Landscaping Services",
            "type":"Services"
        }
    ],
    "sg:phone":"+1 250 862 3665",
    "sg:postcode":"V1X 3Y6",
    "sg:province":"BC",
    "sg:tags":[
        "lawn",
        "contractor",
        "landscape",
        "maintenance",
        "grounds"
    ],
    "wof:name":"AAA Lawn & Yard Maintenance",
    "wof:placetype":"venue"
},
  "geometry": {"coordinates":[-119.40561676,49.8869247437],"type":"Point"}
}