{
  "type": "Feature",
  "properties": {
    "addr:full":"Charlottetown PE C1A 7J7",
    "addr:postcode":"c1a 7j7",
    "iso:country":"CA",
    "sg:city":"Charlottetown",
    "sg:classifiers":[
        {
            "category":"Manufacturing",
            "subcategory":"Metals",
            "type":"Manufacturing & Wholesale Goods"
        }
    ],
    "sg:phone":"+1 902 628 9333",
    "sg:postcode":"C1A 7J7",
    "sg:province":"PE",
    "sg:tags":[
        "heat",
        "exchanger"
    ],
    "wof:name":"Control Air Systems Inc",
    "wof:placetype":"venue"
},
  "geometry": {"coordinates":[-63.124367,46.26395],"type":"Point"}
}