{
  "type": "Feature",
  "properties": {
    "iso:country":"CA",
    "sg:address":"114 Rte Du President-Kennedy",
    "sg:city":"Levis",
    "sg:classifiers":[
        {
            "category":"Shopping",
            "subcategory":"Clothing, Apparel, & Fashions",
            "type":"Retail Goods"
        }
    ],
    "sg:phone":"+1 418 837 0455",
    "sg:postcode":"G6V 6C9",
    "sg:province":"QC",
    "wof:name":"Mode Le Grenier Inc",
    "wof:placetype":"venue"
},
  "geometry": {"coordinates":[-71.167519,46.788918],"type":"Point"}
}