{
  "type": "Feature",
  "properties": {
    "addr:full":"2320 Boul Henri-Bourassa E Montreal QC H2B 1T6",
    "addr:housenumber":"2320",
    "addr:postcode":"h2b 1t6",
    "addr:street":"Boul Henri-Bourassa E",
    "iso:country":"CA",
    "sg:address":"2320 Boul Henri-Bourassa E",
    "sg:city":"Montreal",
    "sg:classifiers":[
        {
            "category":"Restaurant",
            "type":"Food & Drink"
        }
    ],
    "sg:phone":"+1 514 381 1550",
    "sg:postcode":"H2B 1T6",
    "sg:province":"QC",
    "sg:tags":[
        "cafe"
    ],
    "wof:name":"Toca",
    "wof:placetype":"venue"
},
  "geometry": {"coordinates":[-73.654586792,45.5761413574],"type":"Point"}
}