{
  "type": "Feature",
  "properties": {
    "addr:full":"2012 Boul Rene-Laennec Laval QC H7M 4J8",
    "addr:housenumber":"2012",
    "addr:postcode":"h7m 4j8",
    "addr:street":"Boul Rene-Laennec",
    "iso:country":"CA",
    "sg:address":"2012 Boul Rene-Laennec",
    "sg:city":"Laval",
    "sg:classifiers":[
        {
            "category":"Shopping",
            "subcategory":"Computers & Home Electronics",
            "type":"Retail Goods"
        }
    ],
    "sg:phone":"+1 450 975 9000",
    "sg:postcode":"H7M 4J8",
    "sg:province":"QC",
    "sg:tags":[
        "software"
    ],
    "wof:name":"Informatel Inc",
    "wof:placetype":"venue"
},
  "geometry": {"coordinates":[-73.7196807861,45.60887146],"type":"Point"}
}