{
  "type": "Feature",
  "properties": {
    "addr:full":"105 Towerline Pl London ON N6E 2T3",
    "addr:housenumber":"105",
    "addr:postcode":"n6e 2t3",
    "addr:street":"Towerline Pl",
    "iso:country":"CA",
    "sg:address":"105 Towerline Pl",
    "sg:city":"London",
    "sg:classifiers":[
        {
            "category":"Manufacturing",
            "subcategory":"Tools & Machinery",
            "type":"Manufacturing & Wholesale Goods"
        }
    ],
    "sg:phone":"+1 519 686 2643",
    "sg:postcode":"N6E 2T3",
    "sg:province":"ON",
    "sg:tags":[
        "mold"
    ],
    "wof:name":"Lamko Tool & Mould Inc",
    "wof:placetype":"venue"
},
  "geometry": {"coordinates":[-81.1987533569,42.9330177307],"type":"Point"}
}