{
  "type": "Feature",
  "properties": {
    "iso:country":"CA",
    "sg:address":"610 Keewatin St",
    "sg:city":"Winnipeg",
    "sg:classifiers":[
        {
            "category":"Retail",
            "subcategory":"Auto Repair",
            "type":"Services"
        }
    ],
    "sg:phone":"+1 204 633 2700",
    "sg:postcode":"R2X 2R9",
    "sg:province":"MB",
    "sg:tags":[
        "truck"
    ],
    "wof:name":"Keewatin Truck Svc",
    "wof:placetype":"venue"
},
  "geometry": {"coordinates":[-97.19542694090001,49.9305686951],"type":"Point"}
}