{
  "type": "Feature",
  "properties": {
    "addr:full":"Saint-Georges QC G5Y 2H3",
    "addr:postcode":"g5y 2h3",
    "iso:country":"CA",
    "sg:city":"Saint-Georges",
    "sg:classifiers":[
        {
            "category":"Retail",
            "subcategory":"Funeral Services",
            "type":"Services"
        }
    ],
    "sg:phone":"+1 418 228 1214",
    "sg:postcode":"G5Y 2H3",
    "sg:province":"QC",
    "sg:tags":[
        "director"
    ],
    "wof:name":"Maison Funeraire Quebecoise",
    "wof:placetype":"venue"
},
  "geometry": {"coordinates":[-70.67115,46.123348],"type":"Point"}
}