{
  "type": "Feature",
  "properties": {
    "iso:country":"CA",
    "sg:address":"960 Scurfield Blvd",
    "sg:city":"Winnipeg",
    "sg:classifiers":[
        {
            "category":"Education",
            "subcategory":"School",
            "type":"Public Place"
        }
    ],
    "sg:phone":"+1 204 489 1239",
    "sg:postcode":"R3Y 1N6",
    "sg:province":"MB",
    "wof:name":"Henry G Izatt Middle School",
    "wof:placetype":"venue"
},
  "geometry": {"coordinates":[-97.215401,49.807327],"type":"Point"}
}