{
  "type": "Feature",
  "properties": {
    "addr:full":"528 Rue Saint-Viateur Joliette QC J6E 3B3",
    "addr:housenumber":"528",
    "addr:postcode":"j6e 3b3",
    "addr:street":"Rue Saint-Viateur",
    "iso:country":"CA",
    "sg:address":"528 Rue Saint-Viateur",
    "sg:city":"Joliette",
    "sg:classifiers":[
        {
            "category":"Shopping",
            "type":"Retail Goods"
        }
    ],
    "sg:phone":"+1 450 755 4338",
    "sg:postcode":"J6E 3B3",
    "sg:province":"QC",
    "sg:tags":[
        "lace"
    ],
    "wof:name":"Dentelles Du Dirois",
    "wof:placetype":"venue"
},
  "geometry": {"coordinates":[-73.4422073364,46.0249557495],"type":"Point"}
}