{
  "type": "Feature",
  "properties": {
    "iso:country":"CA",
    "sg:city":"Ottawa",
    "sg:classifiers":[
        {
            "category":"Professional",
            "subcategory":"Art Services",
            "type":"Services"
        }
    ],
    "sg:phone":"+1 613 235 1085",
    "sg:postcode":"K1P 6E2",
    "sg:province":"ON",
    "sg:tags":[
        "graphic",
        "designer"
    ],
    "wof:name":"Carisse Graphic Design Ltd",
    "wof:placetype":"venue"
},
  "geometry": {"coordinates":[-75.6967544556,45.4205055237],"type":"Point"}
}