{
  "type": "Feature",
  "properties": {
    "iso:country":"CA",
    "sg:address":"580 the Queensway",
    "sg:city":"Peterborough",
    "sg:classifiers":[
        {
            "category":"Manufacturing",
            "subcategory":"Printing",
            "type":"Manufacturing & Wholesale Goods"
        }
    ],
    "sg:phone":"+1 705 745 2221",
    "sg:postcode":"K9J 7H2",
    "sg:province":"ON",
    "sg:tags":[
        "printer"
    ],
    "wof:name":"401 Publications",
    "wof:placetype":"venue"
},
  "geometry": {"coordinates":[-78.3385772705,44.2760009766],"type":"Point"}
}