{
  "type": "Feature",
  "properties": {
    "addr:full":"72 Notre-Dame E Cap-Chat QC G0J 1E0",
    "addr:housenumber":"72",
    "addr:postcode":"g0j 1e0",
    "addr:street":"Notre-Dame E Cap-Chat",
    "iso:country":"CA",
    "sg:address":"72 Notre-Dame E",
    "sg:city":"Cap-Chat",
    "sg:classifiers":[
        {
            "category":"Sports & Exercise",
            "subcategory":"Bowling",
            "type":"Entertainment"
        }
    ],
    "sg:phone":"+1 418 786 2420",
    "sg:postcode":"G0J 1E0",
    "sg:province":"QC",
    "sg:tags":[
        "center"
    ],
    "wof:name":"Salon DE Quilles DE L'Anse Inc",
    "wof:placetype":"venue"
},
  "geometry": {"coordinates":[-66.6859664917,49.097530365],"type":"Point"}
}