{
  "type": "Feature",
  "properties": {
    "addr:full":"524 Firby Crt Coquitlam BC V3J 5S9",
    "addr:housenumber":"524",
    "addr:postcode":"v3j 5s9",
    "addr:street":"Firby Crt",
    "iso:country":"CA",
    "sg:address":"524 Firby Crt",
    "sg:city":"Coquitlam",
    "sg:classifiers":[
        {
            "category":"Building & Trades",
            "subcategory":"Construction",
            "type":"Services"
        }
    ],
    "sg:phone":"+1 604 939 0080",
    "sg:postcode":"V3J 5S9",
    "sg:province":"BC",
    "sg:tags":[
        "fireproofing"
    ],
    "wof:name":"Columbia Seal Firestop Ltd",
    "wof:placetype":"venue"
},
  "geometry": {"coordinates":[-122.851112,49.250275],"type":"Point"}
}