{
  "type": "Feature",
  "properties": {
    "addr:full":"491 Somerset St W Ottawa ON K1R 5J7",
    "addr:housenumber":"491",
    "addr:postcode":"k1r 5j7",
    "addr:street":"Somerset St W",
    "iso:country":"CA",
    "sg:address":"491 Somerset St W",
    "sg:city":"Ottawa",
    "sg:classifiers":[
        {
            "category":"Restaurant",
            "type":"Food & Drink"
        }
    ],
    "sg:phone":"+1 613 233 2320",
    "sg:postcode":"K1R 5J7",
    "sg:province":"ON",
    "sg:tags":[
        "pizza"
    ],
    "wof:name":"Pavarazzi's Gourmet Pizza",
    "wof:placetype":"venue"
},
  "geometry": {"coordinates":[-75.7003860474,45.4138717651],"type":"Point"}
}