{
  "type": "Feature",
  "properties": {
    "addr:full":"576 Wagg Rd Uxbridge ON L9P 1R4",
    "addr:housenumber":"576",
    "addr:postcode":"l9p 1r4",
    "addr:street":"Wagg Rd",
    "iso:country":"CA",
    "sg:address":"576 Wagg Rd",
    "sg:city":"Uxbridge",
    "sg:classifiers":[
        {
            "category":"Building & Trades",
            "subcategory":"Construction",
            "type":"Services"
        }
    ],
    "sg:phone":"+1 905 852 4291",
    "sg:postcode":"L9P 1R4",
    "sg:province":"ON",
    "sg:tags":[
        "downspouts",
        "gutter"
    ],
    "wof:name":"Sutherland's Aluminum Instltns",
    "wof:placetype":"venue"
},
  "geometry": {"coordinates":[-79.13683319090001,44.0675430298],"type":"Point"}
}