{
  "type": "Feature",
  "properties": {
    "addr:full":"887 Webber Ave Peterborough ON K9J 5X9",
    "addr:housenumber":"887",
    "addr:postcode":"k9j 5x9",
    "addr:street":"Webber Ave",
    "iso:country":"CA",
    "sg:address":"887 Webber Ave",
    "sg:city":"Peterborough",
    "sg:classifiers":[
        {
            "category":"Retail",
            "subcategory":"Auto Repair",
            "type":"Services"
        }
    ],
    "sg:phone":"+1 705 745 8699",
    "sg:postcode":"K9J 5X9",
    "sg:province":"ON",
    "sg:tags":[
        "automobile",
        "inspection",
        "dealer"
    ],
    "wof:name":"Class A Automotive",
    "wof:placetype":"venue"
},
  "geometry": {"coordinates":[-78.34884643549999,44.2822418213],"type":"Point"}
}