{
  "type": "Feature",
  "properties": {
    "iso:country":"CA",
    "sg:address":"124 Dowling Ave",
    "sg:city":"Toronto",
    "sg:classifiers":[
        {
            "category":"Health Services",
            "subcategory":"Nursing And Care Facility",
            "type":"Services"
        }
    ],
    "sg:phone":"+1 416 534 5274",
    "sg:postcode":"M6K 3A6",
    "sg:province":"ON",
    "sg:tags":[
        "home",
        "retirement",
        "community"
    ],
    "wof:name":"Dowling Rest Home",
    "wof:placetype":"venue"
},
  "geometry": {"coordinates":[-79.43887329099999,43.6369247437],"type":"Point"}
}