{
  "type": "Feature",
  "properties": {
    "addr:full":"Surrey BC V3R 1M7",
    "addr:postcode":"v3r 1m7",
    "iso:country":"CA",
    "sg:city":"Surrey",
    "sg:classifiers":[
        {
            "category":"Professional",
            "subcategory":"Accounting & Tax Preparation",
            "type":"Services"
        }
    ],
    "sg:phone":"+1 604 589 8590",
    "sg:postcode":"V3R 1M7",
    "sg:province":"BC",
    "sg:tags":[
        "accountant"
    ],
    "wof:name":"Wong, Kermit",
    "wof:placetype":"venue"
},
  "geometry": {"coordinates":[-122.80872345,49.1913604736],"type":"Point"}
}