{
  "type": "Feature",
  "properties": {
    "addr:full":"675 Rue Saint-Joseph Marieville QC J3M 1H1",
    "addr:housenumber":"675",
    "addr:postcode":"j3m 1h1",
    "addr:street":"Rue Saint-Joseph",
    "iso:country":"CA",
    "sg:address":"675 Rue Saint-Joseph",
    "sg:city":"Marieville",
    "sg:classifiers":[
        {
            "category":"Government",
            "subcategory":"Fire Station",
            "type":"Public Place"
        }
    ],
    "sg:phone":"+1 ",
    "sg:postcode":"J3M 1H1",
    "sg:province":"QC",
    "sg:tags":[
        "department"
    ],
    "wof:name":"Marieville Feu",
    "wof:placetype":"venue"
},
  "geometry": {"coordinates":[-73.164513,45.430779],"type":"Point"}
}