{
  "type": "Feature",
  "properties": {
    "addr:full":"139 Victoria St E Amherst NS B4H 1X9",
    "addr:housenumber":"139",
    "addr:postcode":"b4h 1x9",
    "addr:street":"Victoria St E",
    "iso:country":"CA",
    "sg:address":"139 Victoria St E",
    "sg:city":"Amherst",
    "sg:classifiers":[
        {
            "category":"Retail",
            "subcategory":"Auto Repair",
            "type":"Services"
        }
    ],
    "sg:phone":"+1 902 667 9231",
    "sg:postcode":"B4H 1X9",
    "sg:province":"NS",
    "sg:tags":[
        "repairing",
        "automobile"
    ],
    "wof:name":"Duffy's Esso Svc",
    "wof:placetype":"venue"
},
  "geometry": {"coordinates":[-64.2112197876,45.8357162476],"type":"Point"}
}