{
  "type": "Feature",
  "properties": {
    "addr:full":"52 Av Parent Port-Cartier QC G5B 2G5",
    "addr:postcode":"g5b 2g5",
    "addr:street":"52 Av Parent",
    "iso:country":"CA",
    "sg:address":"52 Av Parent",
    "sg:city":"Port-Cartier",
    "sg:classifiers":[
        {
            "category":"Retail",
            "subcategory":"Laundry & Dry Cleaning",
            "type":"Services"
        }
    ],
    "sg:phone":"+1 418 766 5522",
    "sg:postcode":"G5B 2G5",
    "sg:province":"QC",
    "sg:tags":[
        "cleaners"
    ],
    "wof:name":"Nettoyeur Port-Cartois Ltee",
    "wof:placetype":"venue"
},
  "geometry": {"coordinates":[-66.875389,50.019299],"type":"Point"}
}