{
  "type": "Feature",
  "properties": {
    "iso:country":"CA",
    "sg:address":"177 Maple Ave",
    "sg:city":"Georgetown",
    "sg:classifiers":[
        {
            "category":"Organizations",
            "subcategory":"Religious Organization",
            "type":"Services"
        }
    ],
    "sg:phone":"+1 905 873 9211",
    "sg:postcode":"L7G 1X6",
    "sg:province":"ON",
    "sg:tags":[
        "church"
    ],
    "wof:name":"Maple Avenue Baptist Church",
    "wof:placetype":"venue"
},
  "geometry": {"coordinates":[-79.91668701170001,43.6497421265],"type":"Point"}
}