{
  "type": "Feature",
  "properties": {
    "addr:full":"629 Sneddon St Regina SK S4T 6H1",
    "addr:housenumber":"629",
    "addr:postcode":"s4t 6h1",
    "addr:street":"Sneddon St",
    "iso:country":"CA",
    "sg:address":"629 Sneddon St",
    "sg:city":"Regina",
    "sg:classifiers":[
        {
            "category":"Professional",
            "subcategory":"Detective & Security Services",
            "type":"Services"
        }
    ],
    "sg:phone":"+1 306 543 7172",
    "sg:postcode":"S4T 6H1",
    "sg:province":"SK",
    "sg:tags":[
        "guard",
        "patrol"
    ],
    "wof:name":"National Guard & Patrol Ltd",
    "wof:placetype":"venue"
},
  "geometry": {"coordinates":[-104.67682600000001,50.468304],"type":"Point"}
}