{
  "type": "Feature",
  "properties": {
    "addr:full":"Milton ON L9T 5A7",
    "addr:postcode":"l9t 5a7",
    "iso:country":"CA",
    "sg:city":"Milton",
    "sg:classifiers":[
        {
            "category":"Professional",
            "subcategory":"Computer Services",
            "type":"Services"
        }
    ],
    "sg:phone":"+1 905 876 4026",
    "sg:postcode":"L9T 5A7",
    "sg:province":"ON",
    "wof:name":"Acp Computer Technologies",
    "wof:placetype":"venue"
},
  "geometry": {"coordinates":[-79.86934661870001,43.5261154175],"type":"Point"}
}