{
  "type": "Feature",
  "properties": {
    "addr:full":"1399 Mcphillips St # 1160 Winnipeg MB R2V 3C4",
    "addr:housenumber":"1399",
    "addr:postcode":"r2v 3c4",
    "addr:street":"Mcphillips St # 1160",
    "iso:country":"CA",
    "sg:address":"1399 Mcphillips St # 1160",
    "sg:city":"Winnipeg",
    "sg:classifiers":[
        {
            "category":"Shopping",
            "subcategory":"Pharmacy",
            "type":"Retail Goods"
        }
    ],
    "sg:phone":"+1 204 338 3060",
    "sg:postcode":"R2V 3C4",
    "sg:province":"MB",
    "wof:name":"Northgate Clinic Pharmacy Inc",
    "wof:placetype":"venue"
},
  "geometry": {"coordinates":[-97.15757000000001,49.941643],"type":"Point"}
}