{
  "type": "Feature",
  "properties": {
    "addr:full":"Sudbury ON P3A 1Z2",
    "addr:postcode":"p3a 1z2",
    "iso:country":"CA",
    "sg:city":"Sudbury",
    "sg:classifiers":[
        {
            "category":"Shopping",
            "subcategory":"Gifts & Souvenirs",
            "type":"Retail Goods"
        }
    ],
    "sg:phone":"+1 705 560 4473",
    "sg:postcode":"P3A 1Z2",
    "sg:province":"ON",
    "sg:tags":[
        "basket",
        "parcel"
    ],
    "wof:name":"Body Shop",
    "wof:placetype":"venue"
},
  "geometry": {"coordinates":[-80.94998931879999,46.5219802856],"type":"Point"}
}