{
  "type": "Feature",
  "properties": {
    "addr:full":"270 Salter St Winnipeg MB R2W 4K9",
    "addr:housenumber":"270",
    "addr:postcode":"r2w 4k9",
    "addr:street":"Salter St",
    "iso:country":"CA",
    "sg:address":"270 Salter St",
    "sg:city":"Winnipeg",
    "sg:classifiers":[
        {
            "category":"Food & Beverages",
            "subcategory":"Groceries & Convenience Stores",
            "type":"Retail Goods"
        }
    ],
    "sg:phone":"+1 204 589 8489",
    "sg:postcode":"R2W 4K9",
    "sg:province":"MB",
    "sg:tags":[
        "grocer"
    ],
    "wof:name":"Salter Garden Market",
    "wof:placetype":"venue"
},
  "geometry": {"coordinates":[-97.138329,49.918758],"type":"Point"}
}