{
  "type": "Feature",
  "properties": {
    "addr:full":"1995 Rue Girouard O Saint-Hyacinthe QC J2S 3A5",
    "addr:housenumber":"1995",
    "addr:postcode":"j2s 3a5",
    "addr:street":"Rue Girouard O",
    "iso:country":"CA",
    "sg:address":"1995 Rue Girouard O",
    "sg:city":"Saint-Hyacinthe",
    "sg:classifiers":[
        {
            "category":"Real Estate",
            "subcategory":"Surveying",
            "type":"Services"
        }
    ],
    "sg:phone":"+1 450 773 3489",
    "sg:postcode":"J2S 3A5",
    "sg:province":"QC",
    "sg:tags":[
        "surveyor"
    ],
    "wof:name":"Malo, Francois",
    "wof:placetype":"venue"
},
  "geometry": {"coordinates":[-72.949066,45.623547],"type":"Point"}
}