{
  "type": "Feature",
  "properties": {
    "addr:full":"8006 Edgar Industrial Dr Red Deer AB T4P 3R2",
    "addr:housenumber":"8006",
    "addr:postcode":"t4p 3r2",
    "addr:street":"Edgar Industrial Dr",
    "iso:country":"CA",
    "sg:address":"8006 Edgar Industrial Dr",
    "sg:city":"Red Deer",
    "sg:classifiers":[
        {
            "category":"Mining & Drilling",
            "type":"Manufacturing & Wholesale Goods"
        }
    ],
    "sg:phone":"+1 403 341 4337",
    "sg:postcode":"T4P 3R2",
    "sg:province":"AB",
    "sg:tags":[
        "field",
        "oil"
    ],
    "wof:name":"Proflo Productions Separators",
    "wof:placetype":"venue"
},
  "geometry": {"coordinates":[-113.847534,52.314499],"type":"Point"}
}