{
  "type": "Feature",
  "properties": {
    "addr:full":"137 Pitt St Cornwall ON K6J 3P5",
    "addr:housenumber":"137",
    "addr:postcode":"k6j 3p5",
    "addr:street":"Pitt St",
    "iso:country":"CA",
    "sg:address":"137 Pitt St",
    "sg:city":"Cornwall",
    "sg:classifiers":[
        {
            "category":"Home & Garden",
            "subcategory":"Hardware",
            "type":"Retail Goods"
        }
    ],
    "sg:phone":"+1 613 932 3662",
    "sg:postcode":"K6J 3P5",
    "sg:province":"ON",
    "wof:name":"Snetsinger's Pro Hardware",
    "wof:placetype":"venue"
},
  "geometry": {"coordinates":[-74.72803497309999,45.0174560547],"type":"Point"}
}