{
  "type": "Feature",
  "properties": {
    "addr:full":"363 Wilson Rd S Oshawa ON L1H 6C6",
    "addr:housenumber":"363",
    "addr:postcode":"l1h 6c6",
    "addr:street":"Wilson Rd",
    "iso:country":"CA",
    "sg:address":"363 Wilson Rd S",
    "sg:city":"Oshawa",
    "sg:classifiers":[
        {
            "category":"Restaurant",
            "type":"Food & Drink"
        }
    ],
    "sg:phone":"+1 905 434 8841",
    "sg:postcode":"L1H 6C6",
    "sg:province":"ON",
    "sg:tags":[
        "doughnut"
    ],
    "wof:name":"Forever Fresh Coffee & Donuts",
    "wof:placetype":"venue"
},
  "geometry": {"coordinates":[-78.839409,43.892609],"type":"Point"}
}