{
  "type": "Feature",
  "properties": {
    "addr:full":"5997 Bathurst St North York ON M2R 1Z3",
    "addr:housenumber":"5997",
    "addr:postcode":"m2r 1z3",
    "addr:street":"Bathurst St",
    "iso:country":"CA",
    "sg:address":"5997 Bathurst St",
    "sg:city":"North York",
    "sg:classifiers":[
        {
            "category":"Personal",
            "subcategory":"Beauty Salon",
            "type":"Services"
        }
    ],
    "sg:phone":"+1 416 226 3205",
    "sg:postcode":"M2R 1Z3",
    "sg:province":"ON",
    "wof:name":"Ruffles Hair Design",
    "wof:placetype":"venue"
},
  "geometry": {"coordinates":[-79.445908,43.786121],"type":"Point"}
}