{
  "type": "Feature",
  "properties": {
    "addr:full":"Tory Hill ON K0L 2Y0",
    "addr:postcode":"k0l 2y0",
    "addr:street":"Hill",
    "iso:country":"CA",
    "sg:city":"Tory Hill",
    "sg:classifiers":[
        {
            "category":"Building & Trades",
            "subcategory":"Plumbing",
            "type":"Services"
        }
    ],
    "sg:phone":"+1 705 448 3148",
    "sg:postcode":"K0L 2Y0",
    "sg:province":"ON",
    "sg:tags":[
        "contractor"
    ],
    "wof:name":"Clarkson Plumbing",
    "wof:placetype":"venue"
},
  "geometry": {"coordinates":[-78.2757797241,44.9734535217],"type":"Point"}
}