{
  "type": "Feature",
  "properties": {
    "addr:full":"Calgary AB T2R 1K9",
    "addr:postcode":"t2r 1k9",
    "iso:country":"CA",
    "sg:city":"Calgary",
    "sg:classifiers":[
        {
            "category":"Government",
            "subcategory":"Office",
            "type":"Public Place"
        }
    ],
    "sg:phone":"+1 403 244 7737",
    "sg:postcode":"T2R 1K9",
    "sg:province":"AB",
    "wof:name":"Calgary Buffalo Constituency",
    "wof:placetype":"venue"
},
  "geometry": {"coordinates":[-114.08814239500001,51.0429344177],"type":"Point"}
}