{
  "type": "Feature",
  "properties": {
    "addr:full":"567 Millidge Ave Saint John NB E2K 2N5",
    "addr:housenumber":"567",
    "addr:postcode":"e2k 2n5",
    "addr:street":"Millidge Ave",
    "iso:country":"CA",
    "sg:address":"567 Millidge Ave",
    "sg:city":"Saint John",
    "sg:classifiers":[
        {
            "category":"Social Services",
            "subcategory":"Child Care",
            "type":"Services"
        }
    ],
    "sg:phone":"+1 506 634 0088",
    "sg:postcode":"E2K 2N5",
    "sg:province":"NB",
    "wof:name":"Kids Choice Childcare",
    "wof:placetype":"venue"
},
  "geometry": {"coordinates":[-66.095467,45.291584],"type":"Point"}
}