{
  "type": "Feature",
  "properties": {
    "addr:full":"4230 Montee Gagnon Terrebonne QC J6Y 1K9",
    "addr:postcode":"4230;j6y 1k9",
    "addr:street":"Montee Gagnon",
    "iso:country":"CA",
    "sg:address":"4230 Montee Gagnon",
    "sg:city":"Terrebonne",
    "sg:classifiers":[
        {
            "category":"Bus Charters",
            "type":"Transportation"
        }
    ],
    "sg:phone":"+1 450 433 2666",
    "sg:postcode":"J6Y 1K9",
    "sg:province":"QC",
    "sg:tags":[
        "rental"
    ],
    "wof:name":"Autobus Rm Inc",
    "wof:placetype":"venue"
},
  "geometry": {"coordinates":[-73.817482,45.706257],"type":"Point"}
}