{
  "type": "Feature",
  "properties": {
    "addr:full":"128 Boul Bellerose E Laval QC H7K 1S7",
    "addr:housenumber":"128",
    "addr:postcode":"qc h7k 1s7",
    "addr:street":"Boul Bellerose E",
    "iso:country":"CA",
    "sg:address":"128 Boul Bellerose E",
    "sg:city":"Laval",
    "sg:classifiers":[
        {
            "category":"Personal",
            "subcategory":"Barber",
            "type":"Services"
        }
    ],
    "sg:phone":"+1 450 669 0731",
    "sg:postcode":"H7K 1S7",
    "sg:province":"QC",
    "wof:name":"Salon Presto",
    "wof:placetype":"venue"
},
  "geometry": {"coordinates":[-73.7297363281,45.6145095825],"type":"Point"}
}