{
  "type": "Feature",
  "properties": {
    "addr:full":"Dorion ON P0T 1K0",
    "addr:postcode":"p0t 1k0",
    "iso:country":"CA",
    "sg:city":"Dorion",
    "sg:classifiers":[
        {
            "category":"Government",
            "subcategory":"Fire Station",
            "type":"Public Place"
        }
    ],
    "sg:phone":"+1 807 857 1037",
    "sg:postcode":"P0T 1K0",
    "sg:province":"ON",
    "sg:tags":[
        "department"
    ],
    "wof:name":"Dorion Fire Hall",
    "wof:placetype":"venue"
},
  "geometry": {"coordinates":[-88.54020690919999,48.7883911133],"type":"Point"}
}