{
  "type": "Feature",
  "properties": {
    "addr:full":"4 Locksley Pl Brampton ON L6S 2P6",
    "addr:housenumber":"4",
    "addr:postcode":"l6s 2p6",
    "addr:street":"Locksley Pl",
    "iso:country":"CA",
    "sg:address":"4 Locksley Pl",
    "sg:city":"Brampton",
    "sg:classifiers":[
        {
            "category":"Retail",
            "subcategory":"Portrait Studio",
            "type":"Services"
        }
    ],
    "sg:phone":"+1 905 459 0909",
    "sg:postcode":"L6S 2P6",
    "sg:province":"ON",
    "sg:tags":[
        "photographer"
    ],
    "wof:name":"Studio Nine Photography",
    "wof:placetype":"venue"
},
  "geometry": {"coordinates":[-79.731323,43.7155],"type":"Point"}
}