{
  "type": "Feature",
  "properties": {
    "addr:full":"Molloy's Rd Trepassey NL A0A 4B0",
    "addr:postcode":"a0a 4b0",
    "addr:street":"Molloy'S Rd",
    "iso:country":"CA",
    "sg:address":"Molloy's Rd",
    "sg:city":"Trepassey",
    "sg:classifiers":[
        {
            "category":"Education",
            "subcategory":"Library",
            "type":"Public Place"
        }
    ],
    "sg:phone":"+1 709 438 2224",
    "sg:postcode":"A0A 4B0",
    "sg:province":"NL",
    "wof:name":"Trepassey Public Library",
    "wof:placetype":"venue"
},
  "geometry": {"coordinates":[-53.364891,46.73745],"type":"Point"}
}