{
  "type": "Feature",
  "properties": {
    "addr:full":"33 Rue Evangeline Granby QC J2G 6N4",
    "addr:housenumber":"33",
    "addr:postcode":"j2g 6n4",
    "addr:street":"Rue Evangeline",
    "iso:country":"CA",
    "sg:address":"33 Rue Evangeline",
    "sg:city":"Granby",
    "sg:classifiers":[
        {
            "category":"Wholesale",
            "subcategory":"Groceries",
            "type":"Manufacturing & Wholesale Goods"
        }
    ],
    "sg:phone":"+1 450 777 7785",
    "sg:postcode":"J2G 6N4",
    "sg:province":"QC",
    "sg:tags":[
        "cocoa",
        "shop",
        "bridal",
        "chocolate"
    ],
    "wof:name":"Choco-Gateau",
    "wof:placetype":"venue"
},
  "geometry": {"coordinates":[-72.7483291626,45.4131965637],"type":"Point"}
}