{
  "type": "Feature",
  "properties": {
    "addr:full":"704 Coxwell Ave Toronto ON M4C 3B9",
    "addr:housenumber":"704",
    "addr:postcode":"m4c 3b9",
    "addr:street":"Coxwell Ave",
    "iso:country":"CA",
    "sg:address":"704 Coxwell Ave",
    "sg:city":"Toronto",
    "sg:classifiers":[
        {
            "category":"Health Services",
            "subcategory":"Doctor",
            "type":"Services"
        }
    ],
    "sg:phone":"+1 416 465 9343",
    "sg:postcode":"M4C 3B9",
    "sg:province":"ON",
    "sg:tags":[
        "dentist"
    ],
    "wof:name":"Dennis Marangos & Assoc",
    "wof:placetype":"venue"
},
  "geometry": {"coordinates":[-79.32401275629999,43.6838874817],"type":"Point"}
}