{
  "type": "Feature",
  "properties": {
    "addr:full":"4975 Rue Dudemaine Montreal QC H4J 1N4",
    "addr:housenumber":"4975",
    "addr:postcode":"h4j 1n4",
    "addr:street":"Rue Dudemaine",
    "iso:country":"CA",
    "sg:address":"4975 Rue Dudemaine",
    "sg:city":"Montreal",
    "sg:classifiers":[
        {
            "category":"Food & Beverages",
            "subcategory":"Groceries & Convenience Stores",
            "type":"Retail Goods"
        }
    ],
    "sg:phone":"+1 514 332 0678",
    "sg:postcode":"H4J 1N4",
    "sg:province":"QC",
    "wof:name":"Couche-Tard",
    "wof:placetype":"venue"
},
  "geometry": {"coordinates":[-73.7007598877,45.5286827087],"type":"Point"}
}