{
  "type": "Feature",
  "properties": {
    "addr:full":"39 Lennox Dr Barrie ON L4N 9V7",
    "addr:housenumber":"39",
    "addr:postcode":"l4n 9v7",
    "addr:street":"Lennox Dr",
    "iso:country":"CA",
    "sg:address":"39 Lennox Dr",
    "sg:city":"Barrie",
    "sg:classifiers":[
        {
            "category":"Building & Trades",
            "subcategory":"Electrical",
            "type":"Services"
        }
    ],
    "sg:phone":"+1 705 726 5666",
    "sg:postcode":"L4N 9V7",
    "sg:province":"ON",
    "sg:tags":[
        "electric",
        "contractor"
    ],
    "wof:name":"Morrow Electric Inc",
    "wof:placetype":"venue"
},
  "geometry": {"coordinates":[-79.7197418213,44.3779411316],"type":"Point"}
}