{
  "type": "Feature",
  "properties": {
    "addr:full":"30 Wolseley Crt Cambridge ON N1R 6X3",
    "addr:housenumber":"30",
    "addr:postcode":"n1r 6x3",
    "addr:street":"Wolseley Crt",
    "iso:country":"CA",
    "sg:address":"30 Wolseley Crt",
    "sg:city":"Cambridge",
    "sg:classifiers":[
        {
            "category":"Manufacturing",
            "subcategory":"Rubber & Plastics",
            "type":"Manufacturing & Wholesale Goods"
        }
    ],
    "sg:phone":"+1 519 623 3180",
    "sg:postcode":"N1R 6X3",
    "sg:province":"ON",
    "sg:tags":[
        "mold",
        "maker"
    ],
    "wof:name":"Shirlon Plastic CO Ltd",
    "wof:placetype":"venue"
},
  "geometry": {"coordinates":[-80.312477,43.403973],"type":"Point"}
}