{
  "type": "Feature",
  "properties": {
    "iso:country":"CA",
    "sg:address":"4720 Joyce Ave",
    "sg:city":"Powell River",
    "sg:classifiers":[
        {
            "category":"Autos & Motor Vehicles",
            "subcategory":"Auto Supplies",
            "type":"Retail Goods"
        }
    ],
    "sg:phone":"+1 604 485 4649",
    "sg:postcode":"V8A 3B6",
    "sg:province":"BC",
    "sg:tags":[
        "repairing",
        "automobile",
        "parts"
    ],
    "wof:name":"Canadian Tire",
    "wof:placetype":"venue"
},
  "geometry": {"coordinates":[-124.520484924,49.843624115],"type":"Point"}
}