{
  "type": "Feature",
  "properties": {
    "addr:full":"9505 100th St Fort Simpson NT X0E 0N0",
    "addr:housenumber":"9505",
    "addr:postcode":"x0e 0n0",
    "addr:street":"100Th St",
    "iso:country":"CA",
    "sg:address":"9505 100th St",
    "sg:city":"Fort Simpson",
    "sg:classifiers":[
        {
            "category":"Building & Trades",
            "subcategory":"Construction",
            "type":"Services"
        }
    ],
    "sg:phone":"+1 867 695 3533",
    "sg:postcode":"X0E 0N0",
    "sg:province":"NT",
    "sg:tags":[
        "general",
        "contractor"
    ],
    "wof:name":"Nogha Enterprises Ltd",
    "wof:placetype":"venue"
},
  "geometry": {"coordinates":[-121.24024963399999,61.7775421143],"type":"Point"}
}