{
  "type": "Feature",
  "properties": {
    "addr:full":"919 Ch Canada Edmundston NB E3V 3X2",
    "addr:housenumber":"919",
    "addr:postcode":"e3v 3x2",
    "addr:street":"Ch",
    "iso:country":"CA",
    "sg:address":"919 Ch Canada",
    "sg:city":"Edmundston",
    "sg:classifiers":[
        {
            "category":"Restaurant",
            "type":"Food & Drink"
        }
    ],
    "sg:phone":"+1 506 735 6434",
    "sg:postcode":"E3V 3X2",
    "sg:province":"NB",
    "wof:name":"P Js Bar & Grille",
    "wof:placetype":"venue"
},
  "geometry": {"coordinates":[-68.353561,47.39397],"type":"Point"}
}