{
  "type": "Feature",
  "properties": {
    "addr:full":"1025 Rue Dupre Beloeil QC J3G 4B1",
    "addr:housenumber":"1025",
    "addr:postcode":"j3g 4b1",
    "addr:street":"Rue Dupre",
    "iso:country":"CA",
    "sg:address":"1025 Rue Dupre",
    "sg:city":"Beloeil",
    "sg:classifiers":[
        {
            "category":"Personal",
            "subcategory":"Barber",
            "type":"Services"
        }
    ],
    "sg:phone":"+1 450 464 2471",
    "sg:postcode":"J3G 4B1",
    "sg:province":"QC",
    "wof:name":"Salon Chez Ti-Pere",
    "wof:placetype":"venue"
},
  "geometry": {"coordinates":[-73.200119,45.574081],"type":"Point"}
}