{
  "type": "Feature",
  "properties": {
    "addr:full":"Petit DE Grat NS B0E 2L0",
    "addr:postcode":"ns b0e 2l0",
    "addr:street":"Petit De Grat",
    "iso:country":"CA",
    "sg:city":"Petit DE Grat",
    "sg:classifiers":[
        {
            "category":"Government",
            "subcategory":"Office",
            "type":"Public Place"
        }
    ],
    "sg:phone":"+1 902 226 2787",
    "sg:postcode":"B0E 2L0",
    "sg:province":"NS",
    "wof:name":"Nova Scotia Fisheries",
    "wof:placetype":"venue"
},
  "geometry": {"coordinates":[-60.957039,45.505089],"type":"Point"}
}