{
  "type": "Feature",
  "properties": {
    "addr:full":"69 Lindsay Lane White Lake ON K0A 3L0",
    "addr:housenumber":"69",
    "addr:postcode":"k0a 3l0",
    "addr:street":"Lindsay Lane",
    "iso:country":"CA",
    "sg:address":"69 Lindsay Lane",
    "sg:city":"White Lake",
    "sg:classifiers":[
        {
            "category":"Recreation",
            "subcategory":"Marina",
            "type":"Entertainment"
        }
    ],
    "sg:phone":"+1 613 623 2568",
    "sg:postcode":"K0A 3L0",
    "sg:province":"ON",
    "wof:name":"White Lake Marina",
    "wof:placetype":"venue"
},
  "geometry": {"coordinates":[-76.506348,45.363804],"type":"Point"}
}