{
  "type": "Feature",
  "properties": {
    "addr:full":"RR 1 Niton Junction AB T0E 1S0",
    "addr:postcode":"t0e 1s0",
    "addr:street":"Rr 1 Niton Junction",
    "iso:country":"CA",
    "sg:address":"RR 1",
    "sg:city":"Niton Junction",
    "sg:classifiers":[
        {
            "category":"Wholesale",
            "subcategory":"Construction Materials",
            "type":"Manufacturing & Wholesale Goods"
        }
    ],
    "sg:phone":"+1 780 795 2462",
    "sg:postcode":"T0E 1S0",
    "sg:province":"AB",
    "sg:tags":[
        "sand",
        "gravel"
    ],
    "wof:name":"Kim Brown Trucking Ltd",
    "wof:placetype":"venue"
},
  "geometry": {"coordinates":[-115.770782471,53.6356887817],"type":"Point"}
}