{
  "type": "Feature",
  "properties": {
    "addr:full":"2940 Rue Goyer Montreal QC H3S 1H6",
    "addr:housenumber":"2940",
    "addr:postcode":"h3s 1h6",
    "addr:street":"Rue Goyer",
    "iso:country":"CA",
    "sg:address":"2940 Rue Goyer",
    "sg:city":"Montreal",
    "sg:classifiers":[
        {
            "category":"Arts & Performance",
            "subcategory":"Theater",
            "type":"Entertainment"
        }
    ],
    "sg:phone":"+1 514 733 1683",
    "sg:postcode":"H3S 1H6",
    "sg:province":"QC",
    "sg:tags":[
        "music"
    ],
    "wof:name":"Clown Jouvence",
    "wof:placetype":"venue"
},
  "geometry": {"coordinates":[-73.630897522,45.5091705322],"type":"Point"}
}