{
  "type": "Feature",
  "properties": {
    "addr:full":"516 Yonge St Midland ON L4R 2C5",
    "addr:housenumber":"516",
    "addr:postcode":"l4r 2c5",
    "addr:street":"Yonge St",
    "iso:country":"CA",
    "sg:address":"516 Yonge St",
    "sg:city":"Midland",
    "sg:classifiers":[
        {
            "category":"Retail",
            "subcategory":"Laundry & Dry Cleaning",
            "type":"Services"
        }
    ],
    "sg:phone":"+1 705 526 5436",
    "sg:postcode":"L4R 2C5",
    "sg:province":"ON",
    "sg:tags":[
        "cleaners"
    ],
    "wof:name":"Dion's Laundry & Dry Cleaning",
    "wof:placetype":"venue"
},
  "geometry": {"coordinates":[-79.88362100000001,44.746883],"type":"Point"}
}