{
  "type": "Feature",
  "properties": {
    "addr:full":"Belleville ON K8N 4Z5",
    "addr:postcode":"k8n 4z5",
    "iso:country":"CA",
    "sg:city":"Belleville",
    "sg:classifiers":[
        {
            "category":"Restaurant",
            "type":"Food & Drink"
        }
    ],
    "sg:phone":"+1 613 962 0222",
    "sg:postcode":"K8N 4Z5",
    "sg:province":"ON",
    "wof:name":"Roxanne's Bar & Grill",
    "wof:placetype":"venue"
},
  "geometry": {"coordinates":[-77.381897,44.161041],"type":"Point"}
}