{
  "type": "Feature",
  "properties": {
    "addr:full":"600 Wellington St E Sault Ste Marie ON P6A 2M5",
    "addr:housenumber":"600",
    "addr:postcode":"p6a 2m5",
    "addr:street":"Wellington St E",
    "iso:country":"CA",
    "sg:address":"600 Wellington St E",
    "sg:city":"Sault Ste Marie",
    "sg:classifiers":[
        {
            "category":"Health Services",
            "subcategory":"Chiropractor",
            "type":"Services"
        }
    ],
    "sg:phone":"+1 705 759 3944",
    "sg:postcode":"P6A 2M5",
    "sg:province":"ON",
    "wof:name":"Chiropractor Hlth & Wellness",
    "wof:placetype":"venue"
},
  "geometry": {"coordinates":[-84.32621,46.510456],"type":"Point"}
}