{
  "type": "Feature",
  "properties": {
    "iso:country":"CA",
    "sg:address":"10226 147 St NW",
    "sg:city":"Edmonton",
    "sg:classifiers":[
        {
            "category":"Personal",
            "subcategory":"Beauty Salon",
            "type":"Services"
        }
    ],
    "sg:phone":"+1 780 488 8874",
    "sg:postcode":"T5N 3B9",
    "sg:province":"AB",
    "wof:name":"Salon Indigo",
    "wof:placetype":"venue"
},
  "geometry": {"coordinates":[-113.57450103799999,53.5427017212],"type":"Point"}
}