{
  "type": "Feature",
  "properties": {
    "addr:full":"Railway Ave & 1st St Smeaton SK S0J 2J0",
    "addr:postcode":"s0j 2j0",
    "addr:street":"Railway Ave & 1St St",
    "iso:country":"CA",
    "sg:address":"Railway Ave & 1st St",
    "sg:city":"Smeaton",
    "sg:classifiers":[
        {
            "category":"Travel",
            "subcategory":"Hotels & Motels",
            "type":"Entertainment"
        }
    ],
    "sg:phone":"+1 306 426 2050",
    "sg:postcode":"S0J 2J0",
    "sg:province":"SK",
    "wof:name":"Smeaton Hotel",
    "wof:placetype":"venue"
},
  "geometry": {"coordinates":[-104.806282,53.491909],"type":"Point"}
}