{
  "type": "Feature",
  "properties": {
    "addr:full":"260 Boul LA Salle Baie-Comeau QC G4Z 1S8",
    "addr:housenumber":"260",
    "addr:postcode":"g4z 1s8",
    "addr:street":"Boul La",
    "iso:country":"CA",
    "sg:address":"260 Boul LA Salle",
    "sg:city":"Baie-Comeau",
    "sg:classifiers":[
        {
            "category":"Autos & Motor Vehicles",
            "subcategory":"Fuel & Gas Station",
            "type":"Retail Goods"
        }
    ],
    "sg:phone":"+1 418 296 9201",
    "sg:postcode":"G4Z 1S8",
    "sg:province":"QC",
    "sg:tags":[
        "oil"
    ],
    "wof:name":"Gas Bar Andre Gagnon",
    "wof:placetype":"venue"
},
  "geometry": {"coordinates":[-68.177826,49.213287],"type":"Point"}
}