{
  "type": "Feature",
  "properties": {
    "iso:country":"CA",
    "sg:address":"120 Philip Ave",
    "sg:city":"North Vancouver",
    "sg:classifiers":[
        {
            "category":"Wholesale",
            "subcategory":"Groceries",
            "type":"Manufacturing & Wholesale Goods"
        }
    ],
    "sg:phone":"+1 604 984 2525",
    "sg:postcode":"V7P 2V6",
    "sg:province":"BC",
    "sg:tags":[
        "grocer"
    ],
    "wof:name":"Bean Baking CO Ltd",
    "wof:placetype":"venue"
},
  "geometry": {"coordinates":[-123.113426209,49.3168678284],"type":"Point"}
}