{
  "type": "Feature",
  "properties": {
    "iso:country":"CA",
    "sg:city":"New Richmond",
    "sg:classifiers":[
        {
            "category":"Professional",
            "subcategory":"Lawyer & Legal Services",
            "type":"Services"
        }
    ],
    "sg:phone":"+1 418 392 5068",
    "sg:postcode":"G0C 2B0",
    "sg:province":"QC",
    "sg:tags":[
        "attorney"
    ],
    "wof:name":"Rioux, Andree",
    "wof:placetype":"venue"
},
  "geometry": {"coordinates":[-65.847946167,48.1553688049],"type":"Point"}
}