{
  "type": "Feature",
  "properties": {
    "iso:country":"CA",
    "sg:address":"231 Boul LA Salle",
    "sg:city":"Baie-Comeau",
    "sg:classifiers":[
        {
            "category":"Professional",
            "subcategory":"Accounting & Tax Preparation",
            "type":"Services"
        }
    ],
    "sg:phone":"+1 418 296 9651",
    "sg:postcode":"G4Z 1S7",
    "sg:province":"QC",
    "sg:tags":[
        "accountant"
    ],
    "wof:name":"Mallette Senc",
    "wof:placetype":"venue"
},
  "geometry": {"coordinates":[-68.1737365723,49.2150688171],"type":"Point"}
}