{
  "type": "Feature",
  "properties": {
    "addr:full":"741 Ch Du Pont-Tache N Alma QC G8B 5B7",
    "addr:housenumber":"741",
    "addr:postcode":"g8b 5b7",
    "addr:street":"Ch Du Pont-Tache N",
    "iso:country":"CA",
    "sg:address":"741 Ch Du Pont-Tache N",
    "sg:city":"Alma",
    "sg:classifiers":[
        {
            "category":"Retail",
            "subcategory":"Veterinary Services",
            "type":"Services"
        }
    ],
    "sg:phone":"+1 418 662 6573",
    "sg:postcode":"G8B 5B7",
    "sg:province":"QC",
    "sg:tags":[
        "veterinarian"
    ],
    "wof:name":"Bouchard, Gilles DVM",
    "wof:placetype":"venue"
},
  "geometry": {"coordinates":[-71.6370544434,48.5602264404],"type":"Point"}
}