{
  "type": "Feature",
  "properties": {
    "addr:full":"1133 Leslie St North York ON M3C 2J6",
    "addr:housenumber":"1133",
    "addr:postcode":"m3c 2j6",
    "addr:street":"Leslie St",
    "iso:country":"CA",
    "sg:address":"1133 Leslie St",
    "sg:city":"North York",
    "sg:classifiers":[
        {
            "category":"Organizations",
            "subcategory":"Professional Association",
            "type":"Services"
        }
    ],
    "sg:phone":"+1 416 383 0777",
    "sg:postcode":"M3C 2J6",
    "sg:province":"ON",
    "wof:name":"Korean Canadian Assn of Metro",
    "wof:placetype":"venue"
},
  "geometry": {"coordinates":[-79.34936500000001,43.721107],"type":"Point"}
}