{
  "type": "Feature",
  "properties": {
    "addr:full":"4944 Little Harbour Rd New Glasgow NS B2H 5C4",
    "addr:housenumber":"4944",
    "addr:postcode":"b2h 5c4",
    "addr:street":"Little Harbour Rd",
    "iso:country":"CA",
    "sg:address":"4944 Little Harbour Rd",
    "sg:city":"New Glasgow",
    "sg:classifiers":[
        {
            "category":"Freight",
            "type":"Transportation"
        }
    ],
    "sg:phone":"+1 902 396 8473",
    "sg:postcode":"B2H 5C4",
    "sg:province":"NS",
    "sg:tags":[
        "commercial",
        "storage"
    ],
    "wof:name":"Harbour-Way Storage & Rentals",
    "wof:placetype":"venue"
},
  "geometry": {"coordinates":[-62.627888,45.600189],"type":"Point"}
}