{
  "type": "Feature",
  "properties": {
    "addr:full":"461 South St London ON N6B 1C1",
    "addr:housenumber":"461",
    "addr:postcode":"n6b 1c1",
    "addr:street":"South St",
    "iso:country":"CA",
    "sg:address":"461 South St",
    "sg:city":"London",
    "sg:classifiers":[
        {
            "category":"Professional",
            "subcategory":"Art Services",
            "type":"Services"
        }
    ],
    "sg:phone":"+1 519 672 8318",
    "sg:postcode":"N6B 1C1",
    "sg:province":"ON",
    "sg:tags":[
        "photographer"
    ],
    "wof:name":"Brian Hillier Photography",
    "wof:placetype":"venue"
},
  "geometry": {"coordinates":[-81.23255899999999,42.977444],"type":"Point"}
}