{
  "type": "Feature",
  "properties": {
    "iso:country":"CA",
    "sg:address":"461 South St",
    "sg:city":"London",
    "sg:classifiers":[
        {
            "category":"Professional",
            "subcategory":"Art Services",
            "type":"Services"
        }
    ],
    "sg:phone":"+1 519 672 8318",
    "sg:postcode":"N6B 1C1",
    "sg:province":"ON",
    "sg:tags":[
        "photographer"
    ],
    "wof:name":"Brian Hillier Photography",
    "wof:placetype":"venue"
},
  "geometry": {"coordinates":[-81.232559,42.977444],"type":"Point"}
}