{
  "type": "Feature",
  "properties": {
    "addr:full":"Ottawa ON K1Z 8L8",
    "addr:postcode":"k1z 8l8",
    "iso:country":"CA",
    "sg:city":"Ottawa",
    "sg:classifiers":[
        {
            "category":"Professional",
            "subcategory":"Art Services",
            "type":"Services"
        }
    ],
    "sg:phone":"+1 613 722 1584",
    "sg:postcode":"K1Z 8L8",
    "sg:province":"ON",
    "sg:tags":[
        "graphic",
        "designer"
    ],
    "wof:name":"Earthlore Communications Inc",
    "wof:placetype":"venue"
},
  "geometry": {"coordinates":[-75.75050354,45.3967704773],"type":"Point"}
}