{
  "type": "Feature",
  "properties": {
    "addr:full":"525 Main St Moncton NB E1C 1C4",
    "addr:housenumber":"525",
    "addr:postcode":"e1c 1c4",
    "addr:street":"Main St",
    "iso:country":"CA",
    "sg:address":"525 Main St",
    "sg:city":"Moncton",
    "sg:classifiers":[
        {
            "category":"Insurance",
            "subcategory":"Insurance Agent",
            "type":"Services"
        }
    ],
    "sg:phone":"+1 506 857 8025",
    "sg:postcode":"E1C 1C4",
    "sg:province":"NB",
    "wof:name":"Rbc Insurance",
    "wof:placetype":"venue"
},
  "geometry": {"coordinates":[-64.7724761963,46.0901756287],"type":"Point"}
}