{
  "type": "Feature",
  "properties": {
    "addr:full":"421 Cartier Blvd Hawkesbury ON K6A 1V9",
    "addr:housenumber":"421",
    "addr:postcode":"k6a 1v9",
    "addr:street":"Cartier Blvd",
    "iso:country":"CA",
    "sg:address":"421 Cartier Blvd",
    "sg:city":"Hawkesbury",
    "sg:classifiers":[
        {
            "category":"Organizations",
            "subcategory":"Professional Association",
            "type":"Services"
        }
    ],
    "sg:phone":"+1 613 632 8294",
    "sg:postcode":"K6A 1V9",
    "sg:province":"ON",
    "sg:tags":[
        "club"
    ],
    "wof:name":"Club Age D'Or 50",
    "wof:placetype":"venue"
},
  "geometry": {"coordinates":[-74.604874,45.607082],"type":"Point"}
}