{
  "type": "Feature",
  "properties": {
    "addr:full":"50 Rue Girouard Victoriaville QC G6P 5S8",
    "addr:housenumber":"50",
    "addr:postcode":"g6p 5s8",
    "addr:street":"Rue Girouard",
    "iso:country":"CA",
    "sg:address":"50 Rue Girouard",
    "sg:city":"Victoriaville",
    "sg:classifiers":[
        {
            "category":"Retail",
            "subcategory":"Veterinary Services",
            "type":"Services"
        }
    ],
    "sg:phone":"+1 819 357 8281",
    "sg:postcode":"G6P 5S8",
    "sg:province":"QC",
    "sg:tags":[
        "veterinarian"
    ],
    "wof:name":"Beauregard, Mario DVM",
    "wof:placetype":"venue"
},
  "geometry": {"coordinates":[-71.93296100000001,46.050385],"type":"Point"}
}