{
  "type": "Feature",
  "properties": {
    "addr:full":"Victoria Rd Madawaska ON K0J 2C0",
    "addr:postcode":"k0j 2c0",
    "addr:street":"Victoria Rd",
    "iso:country":"CA",
    "sg:address":"Victoria Rd",
    "sg:city":"Madawaska",
    "sg:classifiers":[
        {
            "category":"Education",
            "subcategory":"Library",
            "type":"Public Place"
        }
    ],
    "sg:phone":"+1 613 637 1099",
    "sg:postcode":"K0J 2C0",
    "sg:province":"ON",
    "wof:name":"Madawaska Public Library",
    "wof:placetype":"venue"
},
  "geometry": {"coordinates":[-77.99046300000001,45.501709],"type":"Point"}
}