{
  "type": "Feature",
  "properties": {
    "addr:full":"40 Fielding Dr SE Calgary AB T2H 1H1",
    "addr:housenumber":"40",
    "addr:postcode":"t2h 1h1",
    "addr:street":"Fielding Dr Se",
    "iso:country":"CA",
    "sg:address":"40 Fielding Dr SE",
    "sg:city":"Calgary",
    "sg:classifiers":[
        {
            "category":"Professional",
            "subcategory":"Engineering",
            "type":"Services"
        }
    ],
    "sg:phone":"+1 403 253 8161",
    "sg:postcode":"T2H 1H1",
    "sg:province":"AB",
    "sg:tags":[
        "engineer"
    ],
    "wof:name":"R A Enns Technical Ltd",
    "wof:placetype":"venue"
},
  "geometry": {"coordinates":[-114.068443,50.982944],"type":"Point"}
}