{
  "type": "Feature",
  "properties": {
    "addr:full":"1496 Carsonby Rd E Kars ON K0A 2E0",
    "addr:housenumber":"1496",
    "addr:postcode":"k0a 2e0",
    "addr:street":"Carsonby Rd E",
    "iso:country":"CA",
    "sg:address":"1496 Carsonby Rd E",
    "sg:city":"Kars",
    "sg:classifiers":[
        {
            "category":"Shopping",
            "subcategory":"Hobbies, Toys, & Games",
            "type":"Retail Goods"
        }
    ],
    "sg:phone":"+1 613 692 2428",
    "sg:postcode":"K0A 2E0",
    "sg:province":"ON",
    "sg:tags":[
        "model",
        "supply"
    ],
    "wof:name":"Hobbywood Products",
    "wof:placetype":"venue"
},
  "geometry": {"coordinates":[-75.64814,45.152485],"type":"Point"}
}