{
  "type": "Feature",
  "properties": {
    "addr:full":"11119 100 St Grande Prairie AB T8V 2N2",
    "addr:housenumber":"11119",
    "addr:postcode":"t8v 2n2",
    "addr:street":"100 St",
    "iso:country":"CA",
    "sg:address":"11119 100 St",
    "sg:city":"Grande Prairie",
    "sg:classifiers":[
        {
            "category":"Retail",
            "subcategory":"Repair Shop",
            "type":"Services"
        }
    ],
    "sg:phone":"+1 780 532 0122",
    "sg:postcode":"T8V 2N2",
    "sg:province":"AB",
    "sg:tags":[
        "lock",
        "locksmith"
    ],
    "wof:name":"Lang Locks & Safes",
    "wof:placetype":"venue"
},
  "geometry": {"coordinates":[-118.794555664,55.1809082031],"type":"Point"}
}