{
  "type": "Feature",
  "properties": {
    "addr:full":"704 Rue Notre-Dame O Montreal QC H3C 1J2",
    "addr:housenumber":"704",
    "addr:postcode":"h3c 1j2",
    "addr:street":"Rue Notre-Dame O",
    "iso:country":"CA",
    "sg:address":"704 Rue Notre-Dame O",
    "sg:city":"Montreal",
    "sg:classifiers":[
        {
            "category":"Retail",
            "subcategory":"Repair Shop",
            "type":"Services"
        }
    ],
    "sg:phone":"+1 514 397 2621",
    "sg:postcode":"H3C 1J2",
    "sg:province":"QC",
    "sg:tags":[
        "lock",
        "locksmith"
    ],
    "wof:name":"Serrupro",
    "wof:placetype":"venue"
},
  "geometry": {"coordinates":[-73.55088000000001,45.512554],"type":"Point"}
}