{
  "type": "Feature",
  "properties": {
    "addr:full":"33825 Harmony Parkhill ON N0M 2K0",
    "addr:housenumber":"33825",
    "addr:postcode":"n0m 2k0",
    "addr:street":"Harmony",
    "iso:country":"CA",
    "sg:address":"33825 Harmony",
    "sg:city":"Parkhill",
    "sg:classifiers":[
        {
            "category":"Organizations",
            "subcategory":"Professional Association",
            "type":"Services"
        }
    ],
    "sg:phone":"+1 519 294 6464",
    "sg:postcode":"N0M 2K0",
    "sg:province":"ON",
    "sg:tags":[
        "club"
    ],
    "wof:name":"Harmony Woods Recreation Club",
    "wof:placetype":"venue"
},
  "geometry": {"coordinates":[-81.696747,43.207874],"type":"Point"}
}