{
  "type": "Feature",
  "properties": {
    "addr:full":"6864 Dow Ave Burnaby BC V5J 3W9",
    "addr:housenumber":"6864",
    "addr:postcode":"v5j 3w9",
    "addr:street":"Dow Ave",
    "iso:country":"CA",
    "sg:address":"6864 Dow Ave",
    "sg:city":"Burnaby",
    "sg:classifiers":[
        {
            "category":"Building & Trades",
            "subcategory":"Cleaning & Sanitation",
            "type":"Services"
        }
    ],
    "sg:phone":"+1 604 786 7735",
    "sg:postcode":"V5J 3W9",
    "sg:province":"BC",
    "sg:tags":[
        "janitor"
    ],
    "wof:name":"Azorean Building Maintenance",
    "wof:placetype":"venue"
},
  "geometry": {"coordinates":[-123.002937,49.221371],"type":"Point"}
}