{
  "type": "Feature",
  "properties": {
    "addr:full":"3805 Nashua Dr Mississauga ON L4V 1R3",
    "addr:housenumber":"3805",
    "addr:postcode":"l4v 1r3",
    "addr:street":"Nashua Dr",
    "iso:country":"CA",
    "sg:address":"3805 Nashua Dr",
    "sg:city":"Mississauga",
    "sg:classifiers":[
        {
            "category":"Freight",
            "type":"Transportation"
        }
    ],
    "sg:phone":"+1 905 677 8108",
    "sg:postcode":"L4V 1R3",
    "sg:province":"ON",
    "sg:tags":[
        "box",
        "commercial"
    ],
    "wof:name":"Public Storage",
    "wof:placetype":"venue"
},
  "geometry": {"coordinates":[-79.620895,43.71542],"type":"Point"}
}