{
  "type": "Feature",
  "properties": {
    "addr:full":"12 Centre St Neilburg SK S0M 2C0",
    "addr:housenumber":"12",
    "addr:postcode":"s0m 2c0",
    "addr:street":"Centre St",
    "iso:country":"CA",
    "sg:address":"12 Centre St",
    "sg:city":"Neilburg",
    "sg:classifiers":[
        {
            "category":"Organizations",
            "subcategory":"Community Association",
            "type":"Services"
        }
    ],
    "sg:phone":"+1 306 823 4311",
    "sg:postcode":"S0M 2C0",
    "sg:province":"SK",
    "sg:tags":[
        "club"
    ],
    "wof:name":"Neilburg Seniors Ctr",
    "wof:placetype":"venue"
},
  "geometry": {"coordinates":[-109.63024900000001,52.836155],"type":"Point"}
}