{
  "type": "Feature",
  "properties": {
    "addr:full":"88 Rue St Joseph Squatec QC G0L 4H0",
    "addr:housenumber":"88",
    "addr:postcode":"g0l 4h0",
    "addr:street":"Rue St Joseph Squatec",
    "iso:country":"CA",
    "sg:address":"88 Rue St Joseph",
    "sg:city":"Squatec",
    "sg:classifiers":[
        {
            "category":"Restaurant",
            "type":"Food & Drink"
        }
    ],
    "sg:phone":"+1 418 855 2459",
    "sg:postcode":"G0L 4H0",
    "sg:province":"QC",
    "wof:name":"Restaurant LA Bonne Bouffe",
    "wof:placetype":"venue"
},
  "geometry": {"coordinates":[-68.72566223139999,47.881313324],"type":"Point"}
}