{
  "type": "Feature",
  "properties": {
    "iso:country":"CA",
    "sg:city":"Toronto",
    "sg:classifiers":[
        {
            "category":"Recreation",
            "type":"Entertainment"
        }
    ],
    "sg:phone":"+1 416 975 8904",
    "sg:postcode":"M4Y 2P2",
    "sg:province":"ON",
    "sg:tags":[
        "astrologer"
    ],
    "wof:name":"Aneta's Tea Room",
    "wof:placetype":"venue"
},
  "geometry": {"coordinates":[-79.3856964111,43.669380188],"type":"Point"}
}