{
  "type": "Feature",
  "properties": {
    "addr:full":"Manning AB T0H 2M0",
    "addr:postcode":"t0h 2m0",
    "iso:country":"CA",
    "sg:city":"Manning",
    "sg:classifiers":[
        {
            "category":"Health Services",
            "subcategory":"Doctor",
            "type":"Services"
        }
    ],
    "sg:phone":"+1 780 836 2811",
    "sg:postcode":"T0H 2M0",
    "sg:province":"AB",
    "sg:tags":[
        "clinic"
    ],
    "wof:name":"Associated Medical Clinic",
    "wof:placetype":"venue"
},
  "geometry": {"coordinates":[-117.63079071,56.9237670898],"type":"Point"}
}