{
  "type": "Feature",
  "properties": {
    "addr:full":"617 Cedar St Iroquois Falls A ON P0K 1G0",
    "addr:housenumber":"617",
    "addr:postcode":"p0k 1g0",
    "addr:street":"Cedar St",
    "iso:country":"CA",
    "sg:address":"617 Cedar St",
    "sg:city":"Iroquois Falls A",
    "sg:classifiers":[
        {
            "category":"Retail",
            "subcategory":"Laundry & Dry Cleaning",
            "type":"Services"
        }
    ],
    "sg:phone":"+1 705 232 4555",
    "sg:postcode":"P0K 1G0",
    "sg:province":"ON",
    "sg:tags":[
        "cleaners"
    ],
    "wof:name":"Nutech Laundry & Dry Cleaning",
    "wof:placetype":"venue"
},
  "geometry": {"coordinates":[-80.6848068237,48.7584991455],"type":"Point"}
}