{
  "type": "Feature",
  "properties": {
    "addr:full":"121 Union St Toronto ON M6N 3N4",
    "addr:housenumber":"121",
    "addr:postcode":"m6n 3n4",
    "addr:street":"Union St",
    "iso:country":"CA",
    "sg:address":"121 Union St",
    "sg:city":"Toronto",
    "sg:classifiers":[
        {
            "category":"Autos & Motor Vehicles",
            "subcategory":"Automobile Sales",
            "type":"Retail Goods"
        }
    ],
    "sg:phone":"+1 416 654 7222",
    "sg:postcode":"M6N 3N4",
    "sg:province":"ON",
    "sg:tags":[
        "car",
        "dealer"
    ],
    "wof:name":"Stark Auto Sales",
    "wof:placetype":"venue"
},
  "geometry": {"coordinates":[-79.46742248539999,43.6779937744],"type":"Point"}
}