{
  "type": "Feature",
  "properties": {
    "addr:full":"18 Algoma St W Thessalon ON P0R 1L0",
    "addr:housenumber":"18",
    "addr:postcode":"p0r 1l0",
    "addr:street":"Algoma St W",
    "iso:country":"CA",
    "sg:address":"18 Algoma St W",
    "sg:city":"Thessalon",
    "sg:classifiers":[
        {
            "category":"Organizations",
            "subcategory":"Professional Association",
            "type":"Services"
        }
    ],
    "sg:phone":"+1 705 842 2418",
    "sg:postcode":"P0R 1L0",
    "sg:province":"ON",
    "wof:name":"Royal Canadian Legion",
    "wof:placetype":"venue"
},
  "geometry": {"coordinates":[-83.5575256348,46.2557067871],"type":"Point"}
}