{
  "type": "Feature",
  "properties": {
    "addr:full":"9056 152 St Surrey BC V3R 4E7",
    "addr:housenumber":"9056",
    "addr:postcode":"v3r 4e7",
    "addr:street":"152 St",
    "iso:country":"CA",
    "sg:address":"9056 152 St",
    "sg:city":"Surrey",
    "sg:classifiers":[
        {
            "category":"Restaurant",
            "type":"Food & Drink"
        }
    ],
    "sg:phone":"+1 604 583 7775",
    "sg:postcode":"V3R 4E7",
    "sg:province":"BC",
    "wof:name":"Kfc",
    "wof:placetype":"venue"
},
  "geometry": {"coordinates":[-122.80116271999999,49.1673355103],"type":"Point"}
}