{
  "type": "Feature",
  "properties": {
    "addr:full":"72 Wilson Ave Kitchener ON N2C 1G5",
    "addr:housenumber":"72",
    "addr:postcode":"n2c 1g5",
    "addr:street":"Wilson Ave",
    "iso:country":"CA",
    "sg:address":"72 Wilson Ave",
    "sg:city":"Kitchener",
    "sg:classifiers":[
        {
            "category":"Arena",
            "subcategory":"Sports Club",
            "type":"Entertainment"
        }
    ],
    "sg:phone":"+1 519 741 2900",
    "sg:postcode":"N2C 1G5",
    "sg:province":"ON",
    "sg:tags":[
        "athletic",
        "fields",
        "stadium",
        "government"
    ],
    "wof:name":"Patrick J Doherty Arena",
    "wof:placetype":"venue"
},
  "geometry": {"coordinates":[-80.457115,43.428795],"type":"Point"}
}