{
  "type": "Feature",
  "properties": {
    "addr:full":"801 23E Av Dolbeau-Mistassini QC G8L 2V2",
    "addr:housenumber":"801",
    "addr:postcode":"g8l 2v2",
    "addr:street":"23E Av Dolbeau-Mistassini",
    "iso:country":"CA",
    "sg:address":"801 23E Av",
    "sg:city":"Dolbeau-Mistassini",
    "sg:classifiers":[
        {
            "category":"Travel",
            "subcategory":"Hotels & Motels",
            "type":"Entertainment"
        }
    ],
    "sg:phone":"+1 418 276 8926",
    "sg:postcode":"G8L 2V2",
    "sg:province":"QC",
    "sg:tags":[
        "outing",
        "therapist",
        "massage",
        "facility"
    ],
    "wof:name":"Magie Du Sous-Bois",
    "wof:placetype":"venue"
},
  "geometry": {"coordinates":[-72.2566986084,48.8666305542],"type":"Point"}
}