{
  "type": "Feature",
  "properties": {
    "addr:full":"487 Queensway W Simcoe ON N3Y 4R5",
    "addr:housenumber":"487",
    "addr:postcode":"n3y 4r5",
    "addr:street":"Queensway W",
    "iso:country":"CA",
    "sg:address":"487 Queensway W",
    "sg:city":"Simcoe",
    "sg:classifiers":[
        {
            "category":"Autos & Motor Vehicles",
            "subcategory":"Boat Sales",
            "type":"Retail Goods"
        }
    ],
    "sg:phone":"+1 519 426 0653",
    "sg:postcode":"N3Y 4R5",
    "sg:province":"ON",
    "sg:tags":[
        "dealer"
    ],
    "wof:name":"Proctor Marine Ltd",
    "wof:placetype":"venue"
},
  "geometry": {"coordinates":[-80.328018,42.84137],"type":"Point"}
}