{
  "type": "Feature",
  "properties": {
    "addr:full":"1479 Bancroft Dr Mississauga ON L5V 1M3",
    "addr:housenumber":"1479",
    "addr:postcode":"l5v 1m3",
    "addr:street":"Bancroft Dr",
    "iso:country":"CA",
    "sg:address":"1479 Bancroft Dr",
    "sg:city":"Mississauga",
    "sg:classifiers":[
        {
            "category":"Building & Trades",
            "subcategory":"Landscaping Services",
            "type":"Services"
        }
    ],
    "sg:phone":"+1 905 816 1597",
    "sg:postcode":"L5V 1M3",
    "sg:province":"ON",
    "sg:tags":[
        "landscape",
        "contractor"
    ],
    "wof:name":"Landscape View",
    "wof:placetype":"venue"
},
  "geometry": {"coordinates":[-79.7144775391,43.6005096436],"type":"Point"}
}