{
  "type": "Feature",
  "properties": {
    "addr:full":"RR 1 Ilderton ON N0M 2A0",
    "addr:postcode":"n0m 2a0",
    "addr:street":"Rr 1",
    "iso:country":"CA",
    "sg:address":"RR 1",
    "sg:city":"Ilderton",
    "sg:classifiers":[
        {
            "category":"Organizations",
            "subcategory":"Religious Organization",
            "type":"Services"
        }
    ],
    "sg:phone":"+1 519 666 0019",
    "sg:postcode":"N0M 2A0",
    "sg:province":"ON",
    "sg:tags":[
        "church"
    ],
    "wof:name":"Melville United Church",
    "wof:placetype":"venue"
},
  "geometry": {"coordinates":[-81.38208,43.079128],"type":"Point"}
}