{
  "type": "Feature",
  "properties": {
    "iso:country":"CA",
    "sg:city":"Gatineau",
    "sg:classifiers":[
        {
            "category":"Building & Trades",
            "subcategory":"Construction",
            "type":"Services"
        }
    ],
    "sg:phone":"+1 819 243 6364",
    "sg:postcode":"J8T 4H2",
    "sg:province":"QC",
    "sg:tags":[
        "contractor"
    ],
    "wof:name":"Cdm Construction Enr",
    "wof:placetype":"venue"
},
  "geometry": {"coordinates":[-75.710487,45.427853],"type":"Point"}
}