{
  "type": "Feature",
  "properties": {
    "addr:full":"3523 Virginia Park Ave Windsor ON N9E 2C6",
    "addr:housenumber":"3523",
    "addr:postcode":"n9e 2c6",
    "addr:street":"Virginia Park Ave",
    "iso:country":"CA",
    "sg:address":"3523 Virginia Park Ave",
    "sg:city":"Windsor",
    "sg:classifiers":[
        {
            "category":"Wholesale",
            "subcategory":"Metals & Minerals",
            "type":"Manufacturing & Wholesale Goods"
        }
    ],
    "sg:phone":"+1 519 966 9276",
    "sg:postcode":"N9E 2C6",
    "sg:province":"ON",
    "sg:tags":[
        "steel",
        "warehouse"
    ],
    "wof:name":"Taylor Steel Inc",
    "wof:placetype":"venue"
},
  "geometry": {"coordinates":[-83.01453399659999,42.2602615356],"type":"Point"}
}