{
  "type": "Feature",
  "properties": {
    "iso:country":"CA",
    "sg:city":"Laval",
    "sg:classifiers":[
        {
            "category":"Health Services",
            "subcategory":"Optometrist",
            "type":"Services"
        }
    ],
    "sg:phone":"+1 450 689 4747",
    "sg:postcode":"H7X 3S5",
    "sg:province":"QC",
    "wof:name":"Iris Clinique D'Optometrie",
    "wof:placetype":"venue"
},
  "geometry": {"coordinates":[-73.7870101929,45.5222053528],"type":"Point"}
}