{
  "type": "Feature",
  "properties": {
    "addr:full":"1120 Loch Lomond Rd Saint John NB E2J 1Z6",
    "addr:housenumber":"1120",
    "addr:postcode":"e2j 1z6",
    "addr:street":"Loch Lomond Rd",
    "iso:country":"CA",
    "sg:address":"1120 Loch Lomond Rd",
    "sg:city":"Saint John",
    "sg:classifiers":[
        {
            "category":"Home & Garden",
            "subcategory":"Hardware",
            "type":"Retail Goods"
        }
    ],
    "sg:phone":"+1 506 658 4663",
    "sg:postcode":"E2J 1Z6",
    "sg:province":"NB",
    "wof:name":"Home Hardware Building Ctr",
    "wof:placetype":"venue"
},
  "geometry": {"coordinates":[-65.996414,45.302322],"type":"Point"}
}