{
  "type": "Feature",
  "properties": {
    "addr:full":"10537 82 Ave NW Edmonton AB T6E 2A3",
    "addr:housenumber":"10537",
    "addr:postcode":"t6e 2a3",
    "addr:street":"82 Ave Nw",
    "iso:country":"CA",
    "sg:address":"10537 82 Ave NW",
    "sg:city":"Edmonton",
    "sg:classifiers":[
        {
            "category":"Banks & Credit Unions",
            "subcategory":"Bank",
            "type":"Services"
        }
    ],
    "sg:phone":"+1 780 448 7800",
    "sg:postcode":"T6E 2A3",
    "sg:province":"AB",
    "wof:name":"Scotiabank",
    "wof:placetype":"venue"
},
  "geometry": {"coordinates":[-113.501656,53.517853],"type":"Point"}
}