{
  "type": "Feature",
  "properties": {
    "addr:full":"5300 No. 3 Rd #619 Richmond BC V6X 2X9",
    "addr:housenumber":"619",
    "addr:postcode":"5300;v6x 2x9",
    "addr:street":"3 Rd #",
    "iso:country":"CA",
    "sg:address":"5300 No. 3 Rd #619",
    "sg:city":"Richmond",
    "sg:classifiers":[
        {
            "category":"Insurance",
            "subcategory":"Insurance Agent",
            "type":"Services"
        }
    ],
    "sg:phone":"+1 604 278 3001",
    "sg:postcode":"V6X 2X9",
    "sg:province":"BC",
    "wof:name":"Lansdowne Insurance Ltd",
    "wof:placetype":"venue"
},
  "geometry": {"coordinates":[-123.136291504,49.1751708984],"type":"Point"}
}