{
  "type": "Feature",
  "properties": {
    "addr:full":"Milton ON L9T 5B6",
    "addr:postcode":"l9t 5b6",
    "iso:country":"CA",
    "sg:city":"Milton",
    "sg:classifiers":[
        {
            "category":"Building & Trades",
            "subcategory":"Construction",
            "type":"Services"
        }
    ],
    "sg:phone":"+1 905 875 1337",
    "sg:postcode":"L9T 5B6",
    "sg:province":"ON",
    "sg:tags":[
        "maker",
        "cabinet"
    ],
    "wof:name":"Pemberton Custom Woodwork",
    "wof:placetype":"venue"
},
  "geometry": {"coordinates":[-79.878601,43.501247],"type":"Point"}
}