{
  "type": "Feature",
  "properties": {
    "addr:full":"550 Old Petersen Rd Campbell River BC V9W 3M9",
    "addr:housenumber":"550",
    "addr:postcode":"v9w 3m9",
    "addr:street":"Old Petersen Rd",
    "iso:country":"CA",
    "sg:address":"550 Old Petersen Rd",
    "sg:city":"Campbell River",
    "sg:classifiers":[
        {
            "category":"Wholesale",
            "subcategory":"Scrap",
            "type":"Manufacturing & Wholesale Goods"
        }
    ],
    "sg:phone":"+1 250 287 3958",
    "sg:postcode":"V9W 3M9",
    "sg:province":"BC",
    "sg:tags":[
        "recycling",
        "center"
    ],
    "wof:name":"Camvest Disposals",
    "wof:placetype":"venue"
},
  "geometry": {"coordinates":[-125.264343,50.016716],"type":"Point"}
}