{
  "type": "Feature",
  "properties": {
    "iso:country":"CA",
    "sg:address":"4021 Yonge St",
    "sg:city":"North York",
    "sg:classifiers":[
        {
            "category":"Autos & Motor Vehicles",
            "subcategory":"Fuel & Gas Station",
            "type":"Retail Goods"
        }
    ],
    "sg:phone":"+1 416 223 0837",
    "sg:postcode":"M2P 1N6",
    "sg:province":"ON",
    "sg:tags":[
        "oil"
    ],
    "wof:name":"Shell Station",
    "wof:placetype":"venue"
},
  "geometry": {"coordinates":[-79.4064941406,43.7439537048],"type":"Point"}
}