{
  "type": "Feature",
  "properties": {
    "addr:full":"RR 1 Elora ON N0B 1S0",
    "addr:postcode":"n0b 1s0",
    "addr:street":"Rr 1",
    "iso:country":"CA",
    "sg:address":"RR 1",
    "sg:city":"Elora",
    "sg:classifiers":[
        {
            "category":"Building & Trades",
            "subcategory":"Electrical",
            "type":"Services"
        }
    ],
    "sg:phone":"+1 519 846 0814",
    "sg:postcode":"N0B 1S0",
    "sg:province":"ON",
    "sg:tags":[
        "electric",
        "contractor"
    ],
    "wof:name":"F M Electric Ltd",
    "wof:placetype":"venue"
},
  "geometry": {"coordinates":[-80.42974853520001,43.6815795898],"type":"Point"}
}