{
  "type": "Feature",
  "properties": {
    "iso:country":"CA",
    "sg:address":"2255 54E Ave",
    "sg:city":"Lachine",
    "sg:classifiers":[
        {
            "category":"Restaurant",
            "type":"Food & Drink"
        }
    ],
    "sg:phone":"+1 514 631 9327",
    "sg:postcode":"H8T 3A8",
    "sg:province":"QC",
    "wof:name":"Jumbo Restaurant",
    "wof:placetype":"venue"
},
  "geometry": {"coordinates":[-73.7234344482,45.4593696594],"type":"Point"}
}