{
  "type": "Feature",
  "properties": {
    "addr:full":"880 Logan Ave Winnipeg MB R3E 1N8",
    "addr:housenumber":"880",
    "addr:postcode":"r3e 1n8",
    "addr:street":"Logan Ave",
    "iso:country":"CA",
    "sg:address":"880 Logan Ave",
    "sg:city":"Winnipeg",
    "sg:classifiers":[
        {
            "category":"Taxi",
            "type":"Transportation"
        }
    ],
    "sg:phone":"+1 204 774 8294",
    "sg:postcode":"R3E 1N8",
    "sg:province":"MB",
    "sg:tags":[
        "taxicab"
    ],
    "wof:name":"Spring Taxi",
    "wof:placetype":"venue"
},
  "geometry": {"coordinates":[-97.161537,49.910675],"type":"Point"}
}