{
  "type": "Feature",
  "properties": {
    "addr:full":"Earlton ON P0J 1E0",
    "addr:postcode":"p0j 1e0",
    "iso:country":"CA",
    "sg:city":"Earlton",
    "sg:classifiers":[
        {
            "category":"Banks & Credit Unions",
            "subcategory":"Bank",
            "type":"Services"
        }
    ],
    "sg:phone":"+1 705 563 2662",
    "sg:postcode":"P0J 1E0",
    "sg:province":"ON",
    "wof:name":"Scotiabank",
    "wof:placetype":"venue"
},
  "geometry": {"coordinates":[-79.823204,47.711105],"type":"Point"}
}