{
  "type": "Feature",
  "properties": {
    "addr:full":"335 Rue Julie Drummondville QC J2E 1S1",
    "addr:housenumber":"335",
    "addr:postcode":"j2e 1s1",
    "addr:street":"Rue Julie",
    "iso:country":"CA",
    "sg:address":"335 Rue Julie",
    "sg:city":"Drummondville",
    "sg:classifiers":[
        {
            "category":"Personal",
            "subcategory":"Beauty Salon",
            "type":"Services"
        }
    ],
    "sg:phone":"+1 819 477 7677",
    "sg:postcode":"J2E 1S1",
    "sg:province":"QC",
    "wof:name":"Salon Signature France",
    "wof:placetype":"venue"
},
  "geometry": {"coordinates":[-72.5291213989,45.9055290222],"type":"Point"}
}