{
  "type": "Feature",
  "properties": {
    "addr:full":"PO Box 870 LA Ronge SK S0J 1L0",
    "addr:housenumber":"po",
    "addr:postcode":"s0j 1l0",
    "addr:street":"Box 870",
    "iso:country":"CA",
    "sg:address":"PO Box 870",
    "sg:city":"LA Ronge",
    "sg:classifiers":[
        {
            "category":"Education",
            "subcategory":"School",
            "type":"Public Place"
        }
    ],
    "sg:phone":"+1 306 425 5041",
    "sg:postcode":"S0J 1L0",
    "sg:province":"SK",
    "wof:name":"Sally Ross School-Hall Lake",
    "wof:placetype":"venue"
},
  "geometry": {"coordinates":[-105.295326,55.112495],"type":"Point"}
}