{
  "type": "Feature",
  "properties": {
    "addr:full":"Provost AB T0B 3S0",
    "addr:postcode":"t0b 3s0",
    "iso:country":"CA",
    "sg:city":"Provost",
    "sg:classifiers":[
        {
            "category":"Mining & Drilling",
            "type":"Manufacturing & Wholesale Goods"
        }
    ],
    "sg:phone":"+1 780 753 3076",
    "sg:postcode":"T0B 3S0",
    "sg:province":"AB",
    "sg:tags":[
        "field",
        "oil"
    ],
    "wof:name":"C J Welding & Oilfield",
    "wof:placetype":"venue"
},
  "geometry": {"coordinates":[-110.245002747,52.3577156067],"type":"Point"}
}