{
  "type": "Feature",
  "properties": {
    "addr:full":"Campbell River BC V9W 2R1",
    "addr:postcode":"v9w 2r1",
    "iso:country":"CA",
    "sg:city":"Campbell River",
    "sg:classifiers":[
        {
            "category":"Personal",
            "type":"Services"
        }
    ],
    "sg:phone":"+1 250 287 3134",
    "sg:postcode":"V9W 2R1",
    "sg:province":"BC",
    "sg:tags":[
        "therapist",
        "massage"
    ],
    "wof:name":"Campbell River Massage Clinic",
    "wof:placetype":"venue"
},
  "geometry": {"coordinates":[-125.244445801,50.0254135132],"type":"Point"}
}