{
  "type": "Feature",
  "properties": {
    "addr:full":"228 Wilkinson Rd Brampton ON L6T 4N7",
    "addr:housenumber":"228",
    "addr:postcode":"l6t 4n7",
    "addr:street":"Wilkinson Rd",
    "iso:country":"CA",
    "sg:address":"228 Wilkinson Rd",
    "sg:city":"Brampton",
    "sg:classifiers":[
        {
            "category":"Home & Garden",
            "subcategory":"Building Materials",
            "type":"Retail Goods"
        }
    ],
    "sg:phone":"+1 905 455 1800",
    "sg:postcode":"L6T 4N7",
    "sg:province":"ON",
    "wof:name":"Procon Building Supplies Ltd",
    "wof:placetype":"venue"
},
  "geometry": {"coordinates":[-79.69593,43.685951],"type":"Point"}
}