{
  "type": "Feature",
  "properties": {
    "addr:full":"275 Second Line W Sault Ste Marie ON P6C 2J4",
    "addr:housenumber":"275",
    "addr:postcode":"p6c 2j4",
    "addr:street":"Second Line W",
    "iso:country":"CA",
    "sg:address":"275 Second Line W",
    "sg:city":"Sault Ste Marie",
    "sg:classifiers":[
        {
            "category":"Cinema",
            "subcategory":"Movie Rental",
            "type":"Entertainment"
        }
    ],
    "sg:phone":"+1 705 945 7782",
    "sg:postcode":"P6C 2J4",
    "sg:province":"ON",
    "sg:tags":[
        "leasing",
        "video",
        "disc",
        "tape"
    ],
    "wof:name":"Great Canadian Video Network",
    "wof:placetype":"venue"
},
  "geometry": {"coordinates":[-84.36586761469999,46.5371932983],"type":"Point"}
}