{
  "type": "Feature",
  "properties": {
    "iso:country":"CA",
    "sg:city":"Le Gardeur",
    "sg:classifiers":[
        {
            "category":"Health Services",
            "subcategory":"Doctor",
            "type":"Services"
        }
    ],
    "sg:phone":"+1 450 582 7000",
    "sg:postcode":"J5Z 1P5",
    "sg:province":"QC",
    "sg:tags":[
        "clinic"
    ],
    "wof:name":"Centre Dentaire Familial",
    "wof:placetype":"venue"
},
  "geometry": {"coordinates":[-73.466019,45.755135],"type":"Point"}
}