{
  "type": "Feature",
  "properties": {
    "addr:full":"98 Water St Summerside PE C1N 4N6",
    "addr:housenumber":"98",
    "addr:postcode":"c1n 4n6",
    "addr:street":"Water St",
    "iso:country":"CA",
    "sg:address":"98 Water St",
    "sg:city":"Summerside",
    "sg:classifiers":[
        {
            "category":"Shopping",
            "subcategory":"Tobacco",
            "type":"Retail Goods"
        }
    ],
    "sg:phone":"+1 902 436 5963",
    "sg:postcode":"C1N 4N6",
    "sg:province":"PE",
    "sg:tags":[
        "cigarette",
        "cigar",
        "dealer"
    ],
    "wof:name":"Mac's News & Novelties",
    "wof:placetype":"venue"
},
  "geometry": {"coordinates":[-63.7822799683,46.3902778625],"type":"Point"}
}