{
  "type": "Feature",
  "properties": {
    "addr:full":"3851 18th Ave Prince George BC V2N 1B1",
    "addr:housenumber":"3851",
    "addr:postcode":"v2n 1b1",
    "addr:street":"18Th Ave",
    "iso:country":"CA",
    "sg:address":"3851 18th Ave",
    "sg:city":"Prince George",
    "sg:classifiers":[
        {
            "category":"Organizations",
            "subcategory":"Professional Association",
            "type":"Services"
        }
    ],
    "sg:phone":"+1 250 563 1744",
    "sg:postcode":"V2N 1B1",
    "sg:province":"BC",
    "wof:name":"Northern BC Construction Assn",
    "wof:placetype":"venue"
},
  "geometry": {"coordinates":[-122.790519714,53.9070701599],"type":"Point"}
}