{
  "type": "Feature",
  "properties": {
    "addr:full":"68 Titan Rd Etobicoke ON M8Z 2J8",
    "addr:housenumber":"68",
    "addr:postcode":"m8z 2j8",
    "addr:street":"Titan Rd",
    "iso:country":"CA",
    "sg:address":"68 Titan Rd",
    "sg:city":"Etobicoke",
    "sg:classifiers":[
        {
            "category":"Manufacturing",
            "subcategory":"Petroleum Products",
            "type":"Manufacturing & Wholesale Goods"
        }
    ],
    "sg:phone":"+1 416 239 1548",
    "sg:postcode":"M8Z 2J8",
    "sg:province":"ON",
    "sg:tags":[
        "lubricant"
    ],
    "wof:name":"Battenfeld Grease Ltd",
    "wof:placetype":"venue"
},
  "geometry": {"coordinates":[-79.52285000000001,43.629932],"type":"Point"}
}