{
  "type": "Feature",
  "properties": {
    "addr:full":"Burlington ON L7L 6C1",
    "addr:postcode":"l7l 6c1",
    "iso:country":"CA",
    "sg:city":"Burlington",
    "sg:classifiers":[
        {
            "category":"Wholesale",
            "subcategory":"Machinery & Supplies",
            "type":"Manufacturing & Wholesale Goods"
        }
    ],
    "sg:phone":"+1 905 335 4877",
    "sg:postcode":"L7L 6C1",
    "sg:province":"ON",
    "sg:tags":[
        "equipment",
        "welding"
    ],
    "wof:name":"Air Liquide Canada Inc",
    "wof:placetype":"venue"
},
  "geometry": {"coordinates":[-79.76248168950001,43.3904533386],"type":"Point"}
}