{
  "type": "Feature",
  "properties": {
    "addr:full":"Scarborough ON M1R 3C7",
    "addr:postcode":"m1r 3c7",
    "iso:country":"CA",
    "sg:city":"Scarborough",
    "sg:classifiers":[
        {
            "category":"Wholesale",
            "subcategory":"Stationery",
            "type":"Manufacturing & Wholesale Goods"
        }
    ],
    "sg:phone":"+1 416 751 8866",
    "sg:postcode":"M1R 3C7",
    "sg:province":"ON",
    "sg:tags":[
        "product",
        "paper"
    ],
    "wof:name":"Paper Plus",
    "wof:placetype":"venue"
},
  "geometry": {"coordinates":[-79.2889785767,43.7497596741],"type":"Point"}
}