{
  "type": "Feature",
  "properties": {
    "addr:full":"Quathiaski Cove BC V0P 1N0",
    "addr:postcode":"v0p 1n0",
    "iso:country":"CA",
    "sg:city":"Quathiaski Cove",
    "sg:classifiers":[
        {
            "category":"Insurance",
            "subcategory":"Insurance Agent",
            "type":"Services"
        }
    ],
    "sg:phone":"+1 250 285 2333",
    "sg:postcode":"V0P 1N0",
    "sg:province":"BC",
    "wof:name":"B C Land & Insurance Brokers",
    "wof:placetype":"venue"
},
  "geometry": {"coordinates":[-125.211769104,50.0434455872],"type":"Point"}
}