{
  "type": "Feature",
  "properties": {
    "iso:country":"CA",
    "sg:address":"36 Bowes St",
    "sg:city":"Parry Sound",
    "sg:classifiers":[
        {
            "category":"Shopping",
            "subcategory":"Florist",
            "type":"Retail Goods"
        }
    ],
    "sg:phone":"+1 705 746 5311",
    "sg:postcode":"P2A 2K9",
    "sg:province":"ON",
    "sg:tags":[
        "garden",
        "center"
    ],
    "wof:name":"Little Garden Greenhouse",
    "wof:placetype":"venue"
},
  "geometry": {"coordinates":[-80.0244445801,45.3441162109],"type":"Point"}
}