{
  "type": "Feature",
  "properties": {
    "addr:full":"3353 the Credit Woodlands Mississauga ON L5C 2K1",
    "addr:housenumber":"3353",
    "addr:postcode":"l5c 2k1",
    "addr:street":"The Credit Woodlands",
    "iso:country":"CA",
    "sg:address":"3353 the Credit Woodlands",
    "sg:city":"Mississauga",
    "sg:classifiers":[
        {
            "category":"Health Services",
            "subcategory":"Doctor",
            "type":"Services"
        }
    ],
    "sg:phone":"+1 905 270 5666",
    "sg:postcode":"L5C 2K1",
    "sg:province":"ON",
    "sg:tags":[
        "dentist"
    ],
    "wof:name":"Bleiman, S L DDS",
    "wof:placetype":"venue"
},
  "geometry": {"coordinates":[-79.65818023680001,43.5589370728],"type":"Point"}
}