{
  "type": "Feature",
  "properties": {
    "addr:full":"22 Compton Crt Bath ON K0H 1G0",
    "addr:housenumber":"22",
    "addr:postcode":"k0h 1g0",
    "addr:street":"Compton Crt",
    "iso:country":"CA",
    "sg:address":"22 Compton Crt",
    "sg:city":"Bath",
    "sg:classifiers":[
        {
            "category":"Shopping",
            "subcategory":"Gifts & Souvenirs",
            "type":"Retail Goods"
        }
    ],
    "sg:phone":"+1 613 389 1333",
    "sg:postcode":"K0H 1G0",
    "sg:province":"ON",
    "sg:tags":[
        "basket",
        "parcel"
    ],
    "wof:name":"Bursta Baskets By Brenda",
    "wof:placetype":"venue"
},
  "geometry": {"coordinates":[-76.775261,44.183041],"type":"Point"}
}