{
  "type": "Feature",
  "properties": {
    "addr:full":"2472 Pirart Rd Nanaimo BC V9R 6V5",
    "addr:housenumber":"2472",
    "addr:postcode":"v9r 6v5",
    "addr:street":"Pirart Rd",
    "iso:country":"CA",
    "sg:address":"2472 Pirart Rd",
    "sg:city":"Nanaimo",
    "sg:classifiers":[
        {
            "category":"Building & Trades",
            "subcategory":"Construction",
            "type":"Services"
        }
    ],
    "sg:phone":"+1 250 754 7390",
    "sg:postcode":"V9R 6V5",
    "sg:province":"BC",
    "sg:tags":[
        "excavating",
        "contractor"
    ],
    "wof:name":"Fournier Excavating Ltd",
    "wof:placetype":"venue"
},
  "geometry": {"coordinates":[-123.93615699999999,49.164268],"type":"Point"}
}