{
  "type": "Feature",
  "properties": {
    "addr:full":"90 Cumberland Loop RR 7 Amherst NS B4H 3Y5",
    "addr:housenumber":"90;7",
    "addr:postcode":"b4h 3y5",
    "addr:street":"Cumberland Loop Rr",
    "iso:country":"CA",
    "sg:address":"90 Cumberland Loop RR 7",
    "sg:city":"Amherst",
    "sg:classifiers":[
        {
            "category":"Travel",
            "subcategory":"Travel Agent",
            "type":"Entertainment"
        }
    ],
    "sg:phone":"+1 902 667 0696",
    "sg:postcode":"B4H 3Y5",
    "sg:province":"NS",
    "sg:tags":[
        "information",
        "tourist"
    ],
    "wof:name":"Amherst Tourist Bureau",
    "wof:placetype":"venue"
},
  "geometry": {"coordinates":[-64.2099304199,45.8320388794],"type":"Point"}
}