{
  "type": "Feature",
  "properties": {
    "addr:full":"Yellowknife NT X1A 3S7",
    "addr:postcode":"x1a 3s7",
    "iso:country":"CA",
    "sg:city":"Yellowknife",
    "sg:classifiers":[
        {
            "category":"Professional",
            "subcategory":"Engineering",
            "type":"Services"
        }
    ],
    "sg:phone":"+1 867 920 4055",
    "sg:postcode":"X1A 3S7",
    "sg:province":"NT",
    "sg:tags":[
        "association",
        "engineer"
    ],
    "wof:name":"Napegg",
    "wof:placetype":"venue"
},
  "geometry": {"coordinates":[-114.374107,62.456326],"type":"Point"}
}