{
  "type": "Feature",
  "properties": {
    "addr:full":"PO Box 248 Wabasca AB T0G 2K0",
    "addr:housenumber":"po",
    "addr:postcode":"t0g 2k0",
    "addr:street":"Box 248",
    "iso:country":"CA",
    "sg:address":"PO Box 248",
    "sg:city":"Wabasca",
    "sg:classifiers":[
        {
            "category":"Mining & Drilling",
            "type":"Manufacturing & Wholesale Goods"
        }
    ],
    "sg:phone":"+1 780 891 3700",
    "sg:postcode":"T0G 2K0",
    "sg:province":"AB",
    "sg:tags":[
        "field",
        "oil"
    ],
    "wof:name":"E-Can Oilfield Svc Ltd",
    "wof:placetype":"venue"
},
  "geometry": {"coordinates":[-113.823402,55.948551],"type":"Point"}
}