{
  "type": "Feature",
  "properties": {
    "iso:country":"CA",
    "sg:address":"20 Procee Cir",
    "sg:city":"Barrie",
    "sg:classifiers":[
        {
            "category":"Health Services",
            "subcategory":"Clinic",
            "type":"Services"
        }
    ],
    "sg:phone":"+1 705 722 4220",
    "sg:postcode":"L4M 4Y8",
    "sg:province":"ON",
    "sg:tags":[
        "information",
        "medical"
    ],
    "wof:name":"Tourette Syndrome Assn of Ont",
    "wof:placetype":"venue"
},
  "geometry": {"coordinates":[-79.6863250732,44.3893013],"type":"Point"}
}