{
  "type": "Feature",
  "properties": {
    "addr:full":"250 Rue Bouchard L'Assomption QC J5W 1J4",
    "addr:housenumber":"250",
    "addr:postcode":"j5w 1j4",
    "addr:street":"Rue Bouchard",
    "iso:country":"CA",
    "sg:address":"250 Rue Bouchard",
    "sg:city":"L'Assomption",
    "sg:classifiers":[
        {
            "category":"Building & Trades",
            "subcategory":"Construction",
            "type":"Services"
        }
    ],
    "sg:phone":"+1 450 589 3292",
    "sg:postcode":"J5W 1J4",
    "sg:province":"QC",
    "sg:tags":[
        "excavating",
        "contractor"
    ],
    "wof:name":"Excavation Rive-Nord Inc",
    "wof:placetype":"venue"
},
  "geometry": {"coordinates":[-73.44038399999999,45.82481],"type":"Point"}
}