{
  "type": "Feature",
  "properties": {
    "addr:full":"1620 Rue DE Louvain O Montreal QC H4N 1G7",
    "addr:housenumber":"1620",
    "addr:postcode":"h4n 1g7",
    "addr:street":"Rue De Louvain O",
    "iso:country":"CA",
    "sg:address":"1620 Rue DE Louvain O",
    "sg:city":"Montreal",
    "sg:classifiers":[
        {
            "category":"Wholesale",
            "subcategory":"Meat",
            "type":"Manufacturing & Wholesale Goods"
        }
    ],
    "sg:phone":"+1 514 383 1900",
    "sg:postcode":"H4N 1G7",
    "sg:province":"QC",
    "sg:tags":[
        "delicatessen",
        "product"
    ],
    "wof:name":"J Macher Inc",
    "wof:placetype":"venue"
},
  "geometry": {"coordinates":[-73.6622161865,45.5315437317],"type":"Point"}
}