{
  "type": "Feature",
  "properties": {
    "addr:full":"1B Knightsbridge Rd Brampton ON L6T 3Y6",
    "addr:housenumber":"1b",
    "addr:postcode":"l6t 3y6",
    "addr:street":"Knightsbridge Rd",
    "iso:country":"CA",
    "sg:address":"1B Knightsbridge Rd",
    "sg:city":"Brampton",
    "sg:classifiers":[
        {
            "category":"Social Services",
            "subcategory":"Child Care",
            "type":"Services"
        }
    ],
    "sg:phone":"+1 905 793 2211",
    "sg:postcode":"L6T 3Y6",
    "sg:province":"ON",
    "sg:tags":[
        "government"
    ],
    "wof:name":"Peel Child Development Ctr",
    "wof:placetype":"venue"
},
  "geometry": {"coordinates":[-79.717857,43.717255],"type":"Point"}
}