{
  "type": "Feature",
  "properties": {
    "addr:full":"5677 Riverbend Rd NW Edmonton AB T6H 5K4",
    "addr:housenumber":"5677",
    "addr:postcode":"t6h 5k4",
    "addr:street":"Riverbend Rd Nw",
    "iso:country":"CA",
    "sg:address":"5677 Riverbend Rd NW",
    "sg:city":"Edmonton",
    "sg:classifiers":[
        {
            "category":"Personal",
            "subcategory":"Beauty Salon",
            "type":"Services"
        }
    ],
    "sg:phone":"+1 780 435 4067",
    "sg:postcode":"T6H 5K4",
    "sg:province":"AB",
    "wof:name":"Riverbend Hairstyling",
    "wof:placetype":"venue"
},
  "geometry": {"coordinates":[-113.57811700000001,53.494339],"type":"Point"}
}