{
  "type": "Feature",
  "properties": {
    "addr:full":"890 Pender St W Vancouver BC V6C 1J9",
    "addr:housenumber":"890",
    "addr:postcode":"v6c 1j9",
    "addr:street":"Pender St W",
    "iso:country":"CA",
    "sg:address":"890 Pender St W",
    "sg:city":"Vancouver",
    "sg:classifiers":[
        {
            "category":"Building & Trades",
            "subcategory":"Construction",
            "type":"Services"
        }
    ],
    "sg:phone":"+1 604 689 5235",
    "sg:postcode":"V6C 1J9",
    "sg:province":"BC",
    "sg:tags":[
        "painter"
    ],
    "wof:name":"City Painting Contractors Ltd",
    "wof:placetype":"venue"
},
  "geometry": {"coordinates":[-123.116653,49.285728],"type":"Point"}
}