{
  "type": "Feature",
  "properties": {
    "addr:full":"RR 22 STN Preston Cambridge ON N3C 2V4",
    "addr:housenumber":"22",
    "addr:postcode":"n3c 2v4",
    "addr:street":"Rr",
    "iso:country":"CA",
    "sg:address":"RR 22 STN Preston",
    "sg:city":"Cambridge",
    "sg:classifiers":[
        {
            "category":"Building & Trades",
            "subcategory":"Construction",
            "type":"Services"
        }
    ],
    "sg:phone":"+1 519 654 0371",
    "sg:postcode":"N3C 2V4",
    "sg:province":"ON",
    "sg:tags":[
        "home",
        "general",
        "improvement",
        "contractor"
    ],
    "wof:name":"Wilson Enterprises",
    "wof:placetype":"venue"
},
  "geometry": {"coordinates":[-80.3153305054,43.3614082336],"type":"Point"}
}