{
  "type": "Feature",
  "properties": {
    "addr:full":"21 Lakeshore Dr W Penticton BC V2A 7M5",
    "addr:housenumber":"21",
    "addr:postcode":"v2a 7m5",
    "addr:street":"Lakeshore Dr W",
    "iso:country":"CA",
    "sg:address":"21 Lakeshore Dr W",
    "sg:city":"Penticton",
    "sg:classifiers":[
        {
            "category":"Sports & Exercise",
            "subcategory":"Gym",
            "type":"Entertainment"
        }
    ],
    "sg:phone":"+1 250 493 7600",
    "sg:postcode":"V2A 7M5",
    "sg:province":"BC",
    "sg:tags":[
        "club",
        "health",
        "studio",
        "gymnasium"
    ],
    "wof:name":"Lakeside Fitness Club",
    "wof:placetype":"venue"
},
  "geometry": {"coordinates":[-119.594802856,49.5026435852],"type":"Point"}
}