{
  "type": "Feature",
  "properties": {
    "addr:full":"1560 Boul Laird Mont-Royal QC H3P 2T5",
    "addr:housenumber":"1560",
    "addr:postcode":"h3p 2t5",
    "addr:street":"Boul Laird",
    "iso:country":"CA",
    "sg:address":"1560 Boul Laird",
    "sg:city":"Mont-Royal",
    "sg:classifiers":[
        {
            "category":"Education",
            "subcategory":"School",
            "type":"Public Place"
        }
    ],
    "sg:phone":"+1 514 739 5322",
    "sg:postcode":"H3P 2T5",
    "sg:province":"QC",
    "wof:name":"Saint-Clement Ecole",
    "wof:placetype":"venue"
},
  "geometry": {"coordinates":[-73.6447677612,45.5194358826],"type":"Point"}
}