{
  "type": "Feature",
  "properties": {
    "addr:full":"150 Berry Rd # 32 Etobicoke ON M8Y 1W3",
    "addr:housenumber":"150",
    "addr:postcode":"m8y 1w3",
    "addr:street":"Berry Rd # 32",
    "iso:country":"CA",
    "sg:address":"150 Berry Rd # 32",
    "sg:city":"Etobicoke",
    "sg:classifiers":[
        {
            "category":"Restaurant",
            "type":"Food & Drink"
        }
    ],
    "sg:phone":"+1 416 233 1173",
    "sg:postcode":"M8Y 1W3",
    "sg:province":"ON",
    "wof:name":"Grace Deli",
    "wof:placetype":"venue"
},
  "geometry": {"coordinates":[-79.4881057739,43.6374473572],"type":"Point"}
}