{
  "type": "Feature",
  "properties": {
    "addr:full":"4237 Rue Sainte-Catherine E Montreal QC H1V 1X4",
    "addr:housenumber":"4237",
    "addr:postcode":"h1v 1x4",
    "addr:street":"Rue Sainte-Catherine E",
    "iso:country":"CA",
    "sg:address":"4237 Rue Sainte-Catherine E",
    "sg:city":"Montreal",
    "sg:classifiers":[
        {
            "category":"Building & Trades",
            "subcategory":"Plumbing",
            "type":"Services"
        }
    ],
    "sg:phone":"+1 514 254 9161",
    "sg:postcode":"H1V 1X4",
    "sg:province":"QC",
    "sg:tags":[
        "refrigeration",
        "contractor"
    ],
    "wof:name":"Frimabec Inc",
    "wof:placetype":"venue"
},
  "geometry": {"coordinates":[-73.53485870359999,45.5498733521],"type":"Point"}
}