{
  "type": "Feature",
  "properties": {
    "addr:full":"2137 Plecas Rd Nanaimo BC V9X 1R9",
    "addr:housenumber":"2137",
    "addr:postcode":"v9x 1r9",
    "addr:street":"Plecas Rd",
    "iso:country":"CA",
    "sg:address":"2137 Plecas Rd",
    "sg:city":"Nanaimo",
    "sg:classifiers":[
        {
            "category":"Building & Trades",
            "subcategory":"Construction",
            "type":"Services"
        }
    ],
    "sg:phone":"+1 250 754 9378",
    "sg:postcode":"V9X 1R9",
    "sg:province":"BC",
    "sg:tags":[
        "excavating",
        "contractor"
    ],
    "wof:name":"Cascade Excavating Ltd",
    "wof:placetype":"venue"
},
  "geometry": {"coordinates":[-123.951187,49.139961],"type":"Point"}
}