{
  "type": "Feature",
  "properties": {
    "addr:full":"3130 16 St SW Calgary AB T2T 4G7",
    "addr:housenumber":"3130",
    "addr:postcode":"t2t 4g7",
    "addr:street":"16 St Sw",
    "iso:country":"CA",
    "sg:address":"3130 16 St SW",
    "sg:city":"Calgary",
    "sg:classifiers":[
        {
            "category":"Recreation",
            "type":"Entertainment"
        }
    ],
    "sg:phone":"+1 403 268 2300",
    "sg:postcode":"T2T 4G7",
    "sg:province":"AB",
    "sg:tags":[
        "pool",
        "swimming"
    ],
    "wof:name":"South Calgary Outdoor Pool",
    "wof:placetype":"venue"
},
  "geometry": {"coordinates":[-114.099349976,51.0264320374],"type":"Point"}
}