{
  "type": "Feature",
  "properties": {
    "addr:full":"8650 Av DE L'Esplanade Montreal QC H2P 2S2",
    "addr:housenumber":"8650",
    "addr:postcode":"h2p 2s2",
    "addr:street":"Av De L'Esplanade",
    "iso:country":"CA",
    "sg:address":"8650 Av DE L'Esplanade",
    "sg:city":"Montreal",
    "sg:classifiers":[
        {
            "category":"Wholesale",
            "subcategory":"Construction Materials",
            "type":"Manufacturing & Wholesale Goods"
        }
    ],
    "sg:phone":"+1 514 326 9590",
    "sg:postcode":"H2P 2S2",
    "sg:province":"QC",
    "sg:tags":[
        "building"
    ],
    "wof:name":"Placages DE Bois",
    "wof:placetype":"venue"
},
  "geometry": {"coordinates":[-73.554359436,45.5123100281],"type":"Point"}
}