{
  "type": "Feature",
  "properties": {
    "addr:full":"61 Centre Ave E Altona MB R0G 0B0",
    "addr:housenumber":"61",
    "addr:postcode":"r0g 0b0",
    "addr:street":"Centre Ave E",
    "iso:country":"CA",
    "sg:address":"61 Centre Ave E",
    "sg:city":"Altona",
    "sg:classifiers":[
        {
            "category":"Travel",
            "subcategory":"Hotels & Motels",
            "type":"Entertainment"
        }
    ],
    "sg:phone":"+1 204 324 5241",
    "sg:postcode":"R0G 0B0",
    "sg:province":"MB",
    "wof:name":"Altona Motor Hotel",
    "wof:placetype":"venue"
},
  "geometry": {"coordinates":[-97.5569763184,49.1036453247],"type":"Point"}
}