{
  "type": "Feature",
  "properties": {
    "iso:country":"CA",
    "sg:address":"6420 Lady Hammond Rd",
    "sg:city":"Halifax",
    "sg:classifiers":[
        {
            "category":"Home & Garden",
            "subcategory":"Furniture",
            "type":"Retail Goods"
        }
    ],
    "sg:phone":"+1 902 455 3445",
    "sg:postcode":"B3K 2S3",
    "sg:province":"NS",
    "sg:tags":[
        "equipment",
        "kitchen",
        "cabinet"
    ],
    "wof:name":"Patti's Kitchen & Bath Design",
    "wof:placetype":"venue"
},
  "geometry": {"coordinates":[-63.619629,44.663952],"type":"Point"}
}