{
  "type": "Feature",
  "properties": {
    "addr:full":"5 Louvain St York ON M6N 4W7",
    "addr:housenumber":"5",
    "addr:postcode":"m6n 4w7",
    "addr:street":"Louvain St",
    "iso:country":"CA",
    "sg:address":"5 Louvain St",
    "sg:city":"York",
    "sg:classifiers":[
        {
            "category":"Organizations",
            "subcategory":"Religious Organization",
            "type":"Services"
        }
    ],
    "sg:phone":"+1 416 766 0414",
    "sg:postcode":"M6N 4W7",
    "sg:province":"ON",
    "sg:tags":[
        "church"
    ],
    "wof:name":"Humber Blvd Baptist Church",
    "wof:placetype":"venue"
},
  "geometry": {"coordinates":[-79.482193,43.680748],"type":"Point"}
}