{
  "type": "Feature",
  "properties": {
    "addr:full":"945 Lougheed Hwy Coquitlam BC V3K 3T4",
    "addr:housenumber":"945",
    "addr:postcode":"v3k 3t4",
    "addr:street":"Lougheed Hwy",
    "iso:country":"CA",
    "sg:address":"945 Lougheed Hwy",
    "sg:city":"Coquitlam",
    "sg:classifiers":[
        {
            "category":"Shopping",
            "subcategory":"Bicycles & Sporting Goods",
            "type":"Retail Goods"
        }
    ],
    "sg:phone":"+1 604 469 8742",
    "sg:postcode":"V3K 3T4",
    "sg:province":"BC",
    "wof:name":"Tri-Cation Sports Ltd",
    "wof:placetype":"venue"
},
  "geometry": {"coordinates":[-122.87108600000001,49.236675],"type":"Point"}
}