{
  "type": "Feature",
  "properties": {
    "addr:full":"385 Calderstone Cres Scarborough ON M1C 3A3",
    "addr:housenumber":"385",
    "addr:postcode":"m1c 3a3",
    "addr:street":"Calderstone Cres",
    "iso:country":"CA",
    "sg:address":"385 Calderstone Cres",
    "sg:city":"Scarborough",
    "sg:classifiers":[
        {
            "category":"Building & Trades",
            "subcategory":"Plumbing",
            "type":"Services"
        }
    ],
    "sg:phone":"+1 416 282 9902",
    "sg:postcode":"M1C 3A3",
    "sg:province":"ON",
    "sg:tags":[
        "cleaning",
        "boiler"
    ],
    "wof:name":"Jordan Boiler Repair Inc",
    "wof:placetype":"venue"
},
  "geometry": {"coordinates":[-79.1408233643,43.7927207947],"type":"Point"}
}