{
  "type": "Feature",
  "properties": {
    "iso:country":"CA",
    "sg:address":"215 Grand River Ave",
    "sg:city":"Brantford",
    "sg:classifiers":[
        {
            "category":"Shopping",
            "subcategory":"Discount & Variety Stores",
            "type":"Retail Goods"
        }
    ],
    "sg:phone":"+1 519 752 4740",
    "sg:postcode":"N3T 4Y3",
    "sg:province":"ON",
    "wof:name":"Vic's Variety",
    "wof:placetype":"venue"
},
  "geometry": {"coordinates":[-80.2877731323,43.141166687],"type":"Point"}
}