{
  "type": "Feature",
  "properties": {
    "addr:full":"1418 Ontario St Burlington ON L7S 1G4",
    "addr:housenumber":"1418",
    "addr:postcode":"l7s 1g4",
    "addr:street":"Ontario St",
    "iso:country":"CA",
    "sg:address":"1418 Ontario St",
    "sg:city":"Burlington",
    "sg:classifiers":[
        {
            "category":"Health Services",
            "subcategory":"Doctor",
            "type":"Services"
        }
    ],
    "sg:phone":"+1 905 639 4214",
    "sg:postcode":"L7S 1G4",
    "sg:province":"ON",
    "sg:tags":[
        "physician",
        "surgeon"
    ],
    "wof:name":"Burlington Medical",
    "wof:placetype":"venue"
},
  "geometry": {"coordinates":[-79.8006896973,43.3247375488],"type":"Point"}
}