{
  "type": "Feature",
  "properties": {
    "addr:full":"3127 Sheppard Ave E Scarborough ON M1T 3J7",
    "addr:housenumber":"3127",
    "addr:postcode":"m1t 3j7",
    "addr:street":"Sheppard Ave E",
    "iso:country":"CA",
    "sg:address":"3127 Sheppard Ave E",
    "sg:city":"Scarborough",
    "sg:classifiers":[
        {
            "category":"Health Services",
            "subcategory":"Doctor",
            "type":"Services"
        }
    ],
    "sg:phone":"+1 416 491 8621",
    "sg:postcode":"M1T 3J7",
    "sg:province":"ON",
    "sg:tags":[
        "dentist"
    ],
    "wof:name":"Gharai, Sepideh DDS",
    "wof:placetype":"venue"
},
  "geometry": {"coordinates":[-79.3167266846,43.7765922546],"type":"Point"}
}