{
  "type": "Feature",
  "properties": {
    "iso:country":"CA",
    "sg:address":"200 Ch Du Tour-DE-L'Isle",
    "sg:city":"Montreal",
    "sg:classifiers":[
        {
            "category":"Restaurant",
            "type":"Food & Drink"
        }
    ],
    "sg:phone":"+1 514 395 2424",
    "sg:postcode":"H3C 4G8",
    "sg:province":"QC",
    "wof:name":"Restaurant Helne DE Champlain",
    "wof:placetype":"venue"
},
  "geometry": {"coordinates":[-73.532463,45.508362],"type":"Point"}
}