{
  "type": "Feature",
  "properties": {
    "iso:country":"CA",
    "sg:city":"Calgary",
    "sg:classifiers":[
        {
            "category":"Home & Garden",
            "subcategory":"Carpets & Floor Coverings",
            "type":"Retail Goods"
        }
    ],
    "sg:phone":"+1 403 259 3995",
    "sg:postcode":"T2H 2J5",
    "sg:province":"AB",
    "sg:tags":[
        "dealer",
        "rug"
    ],
    "wof:name":"Berry Flooring Ltd",
    "wof:placetype":"venue"
},
  "geometry": {"coordinates":[-114.05638885499999,50.9988021851],"type":"Point"}
}