{
  "type": "Feature",
  "properties": {
    "iso:country":"CA",
    "sg:address":"10402 Hoppe Ave",
    "sg:city":"Grande Cache",
    "sg:classifiers":[
        {
            "category":"Education",
            "subcategory":"School",
            "type":"Public Place"
        }
    ],
    "sg:phone":"+1 780 827 3820",
    "sg:postcode":"T0E 0Y0",
    "sg:province":"AB",
    "wof:name":"Summitview School",
    "wof:placetype":"venue"
},
  "geometry": {"coordinates":[-119.126884,53.885872],"type":"Point"}
}