{
  "type": "Feature",
  "properties": {
    "addr:full":"3300 Boul Tracy Laval QC H7E 1L9",
    "addr:housenumber":"3300",
    "addr:postcode":"h7e 1l9",
    "addr:street":"Boul Tracy",
    "iso:country":"CA",
    "sg:address":"3300 Boul Tracy",
    "sg:city":"Laval",
    "sg:classifiers":[
        {
            "category":"Professional",
            "subcategory":"Management & Consulting",
            "type":"Services"
        }
    ],
    "sg:phone":"+1 450 661 6850",
    "sg:postcode":"H7E 1L9",
    "sg:province":"QC",
    "sg:tags":[
        "consultant",
        "educational"
    ],
    "wof:name":"Rivest & Assoc",
    "wof:placetype":"venue"
},
  "geometry": {"coordinates":[-73.67009,45.59885],"type":"Point"}
}