{
  "type": "Feature",
  "properties": {
    "addr:full":"767 Hamilton Rd London ON N5Z 1V1",
    "addr:housenumber":"767",
    "addr:postcode":"n5z 1v1",
    "addr:street":"Hamilton Rd",
    "iso:country":"CA",
    "sg:address":"767 Hamilton Rd",
    "sg:city":"London",
    "sg:classifiers":[
        {
            "category":"Food & Beverages",
            "subcategory":"Groceries & Convenience Stores",
            "type":"Retail Goods"
        }
    ],
    "sg:phone":"+1 519 659 0518",
    "sg:postcode":"N5Z 1V1",
    "sg:province":"ON",
    "sg:tags":[
        "grocer"
    ],
    "wof:name":"Hasty Market",
    "wof:placetype":"venue"
},
  "geometry": {"coordinates":[-81.204041,42.978924],"type":"Point"}
}