{
  "type": "Feature",
  "properties": {
    "addr:full":"Kamloops BC V2C 1T3",
    "addr:postcode":"bc v2c 1t3",
    "iso:country":"CA",
    "sg:city":"Kamloops",
    "sg:classifiers":[
        {
            "category":"Real Estate",
            "subcategory":"Real Estate Operator",
            "type":"Services"
        }
    ],
    "sg:phone":"+1 250 828 1711",
    "sg:postcode":"V2C 1T3",
    "sg:province":"BC",
    "sg:tags":[
        "apartment"
    ],
    "wof:name":"Sands Apartments",
    "wof:placetype":"venue"
},
  "geometry": {"coordinates":[-120.348328,50.67268],"type":"Point"}
}