{
  "type": "Feature",
  "properties": {
    "addr:full":"640 Rue Heriot Drummondville QC J2B 1C3",
    "addr:housenumber":"640",
    "addr:postcode":"j2b 1c3",
    "addr:street":"Rue Heriot",
    "iso:country":"CA",
    "sg:address":"640 Rue Heriot",
    "sg:city":"Drummondville",
    "sg:classifiers":[
        {
            "category":"Manufacturing",
            "subcategory":"Apparel",
            "type":"Manufacturing & Wholesale Goods"
        }
    ],
    "sg:phone":"+1 819 479 0830",
    "sg:postcode":"J2B 1C3",
    "sg:province":"QC",
    "sg:tags":[
        "canvas",
        "product",
        "related"
    ],
    "wof:name":"Multi-Canevas Inc",
    "wof:placetype":"venue"
},
  "geometry": {"coordinates":[-72.4787445068,45.8797721863],"type":"Point"}
}