{
  "type": "Feature",
  "properties": {
    "addr:full":"1668 Kingsway Vancouver BC V5N 2S1",
    "addr:housenumber":"1668",
    "addr:postcode":"v5n 2s1",
    "addr:street":"Kingsway",
    "iso:country":"CA",
    "sg:address":"1668 Kingsway",
    "sg:city":"Vancouver",
    "sg:classifiers":[
        {
            "category":"Manufacturing",
            "subcategory":"Food",
            "type":"Manufacturing & Wholesale Goods"
        }
    ],
    "sg:phone":"+1 604 876 2288",
    "sg:postcode":"V5N 2S1",
    "sg:province":"BC",
    "sg:tags":[
        "frozen",
        "product",
        "manufacturer"
    ],
    "wof:name":"Loon Shung Frozen Chinese Food",
    "wof:placetype":"venue"
},
  "geometry": {"coordinates":[-123.0704422,49.2474365234],"type":"Point"}
}