{
  "type": "Feature",
  "properties": {
    "addr:full":"70 Mountjoy St N Timmins ON P4N 4V7",
    "addr:housenumber":"70",
    "addr:postcode":"p4n 4v7",
    "addr:street":"Mountjoy St N",
    "iso:country":"CA",
    "sg:address":"70 Mountjoy St N",
    "sg:city":"Timmins",
    "sg:classifiers":[
        {
            "category":"Banks & Credit Unions",
            "subcategory":"Bank",
            "type":"Services"
        }
    ],
    "sg:phone":"+1 705 267 6846",
    "sg:postcode":"P4N 4V7",
    "sg:province":"ON",
    "wof:name":"Northern Credit Union Ltd",
    "wof:placetype":"venue"
},
  "geometry": {"coordinates":[-81.3355331421,48.4768257141],"type":"Point"}
}