{
  "type": "Feature",
  "properties": {
    "addr:full":"6731 Lachine Crt SW Calgary AB T3E 6E7",
    "addr:housenumber":"6731",
    "addr:postcode":"t3e 6e7",
    "addr:street":"Lachine Crt Sw",
    "iso:country":"CA",
    "sg:address":"6731 Lachine Crt SW",
    "sg:city":"Calgary",
    "sg:classifiers":[
        {
            "category":"Professional",
            "subcategory":"Engineering",
            "type":"Services"
        }
    ],
    "sg:phone":"+1 403 246 9320",
    "sg:postcode":"T3E 6E7",
    "sg:province":"AB",
    "sg:tags":[
        "engineer"
    ],
    "wof:name":"John Scott Engineering",
    "wof:placetype":"venue"
},
  "geometry": {"coordinates":[-114.12059000000001,50.993244],"type":"Point"}
}