{
  "type": "Feature",
  "properties": {
    "iso:country":"CA",
    "sg:address":"55 Josephine St",
    "sg:city":"Wingham",
    "sg:classifiers":[
        {
            "category":"Banks & Credit Unions",
            "subcategory":"Bank",
            "type":"Services"
        }
    ],
    "sg:phone":"+1 519 357 1750",
    "sg:postcode":"N0G 2W0",
    "sg:province":"ON",
    "wof:name":"Bank of Montreal",
    "wof:placetype":"venue"
},
  "geometry": {"coordinates":[-81.31646728520001,43.8815994263],"type":"Point"}
}