{
  "type": "Feature",
  "properties": {
    "iso:country":"CA",
    "sg:address":"26035 31B Ave",
    "sg:city":"Aldergrove",
    "sg:classifiers":[
        {
            "category":"Home & Garden",
            "subcategory":"Building Materials",
            "type":"Retail Goods"
        }
    ],
    "sg:phone":"+1 604 856 7779",
    "sg:postcode":"V4W 2Z6",
    "sg:province":"BC",
    "sg:tags":[
        "wood",
        "preserving"
    ],
    "wof:name":"Western Wood Preservers Ltd",
    "wof:placetype":"venue"
},
  "geometry": {"coordinates":[-122.462455749,49.0586090088],"type":"Point"}
}