{
  "type": "Feature",
  "properties": {
    "addr:full":"Richmond BC V7C 5K1",
    "addr:postcode":"v7c 5k1",
    "iso:country":"CA",
    "sg:city":"Richmond",
    "sg:classifiers":[
        {
            "category":"Food & Beverages",
            "subcategory":"Bakery",
            "type":"Retail Goods"
        }
    ],
    "sg:phone":"+1 604 274 6916",
    "sg:postcode":"V7C 5K1",
    "sg:province":"BC",
    "sg:tags":[
        "baker"
    ],
    "wof:name":"Blundell Bakery Ltd",
    "wof:placetype":"venue"
},
  "geometry": {"coordinates":[-123.15877500000001,49.154381],"type":"Point"}
}