{
  "type": "Feature",
  "properties": {
    "iso:country":"CA",
    "sg:city":"Leduc",
    "sg:classifiers":[
        {
            "category":"Professional",
            "subcategory":"Accounting & Tax Preparation",
            "type":"Services"
        }
    ],
    "sg:phone":"+1 780 980 2574",
    "sg:postcode":"T9E 6Z6",
    "sg:province":"AB",
    "sg:tags":[
        "accountant"
    ],
    "wof:name":"Harmon, Thomas",
    "wof:placetype":"venue"
},
  "geometry": {"coordinates":[-113.552696,53.267311],"type":"Point"}
}