{
  "type": "Feature",
  "properties": {
    "addr:full":"4711 10 Ave Edson AB T7E 1E4",
    "addr:housenumber":"4711",
    "addr:postcode":"t7e 1e4",
    "addr:street":"10 Ave",
    "iso:country":"CA",
    "sg:address":"4711 10 Ave",
    "sg:city":"Edson",
    "sg:classifiers":[
        {
            "category":"Building & Trades",
            "subcategory":"Plumbing",
            "type":"Services"
        }
    ],
    "sg:phone":"+1 780 723 5638",
    "sg:postcode":"T7E 1E4",
    "sg:province":"AB",
    "sg:tags":[
        "contractor"
    ],
    "wof:name":"Lyndale Plumbing & Gasfitting",
    "wof:placetype":"venue"
},
  "geometry": {"coordinates":[-116.430358887,53.5905952454],"type":"Point"}
}