{
  "type": "Feature",
  "properties": {
    "iso:country":"CA",
    "sg:address":"329 Main St",
    "sg:city":"Foam Lake",
    "sg:classifiers":[
        {
            "category":"Home & Garden",
            "subcategory":"Hardware",
            "type":"Retail Goods"
        }
    ],
    "sg:phone":"+1 306 272 3314",
    "sg:postcode":"S0A 1A0",
    "sg:province":"SK",
    "wof:name":"Foam Lake CO-Operative Assoc",
    "wof:placetype":"venue"
},
  "geometry": {"coordinates":[-103.53357696499999,51.6415634155],"type":"Point"}
}