{
  "type": "Feature",
  "properties": {
    "iso:country":"CA",
    "sg:address":"21 Midland Cres #20",
    "sg:city":"Nepean",
    "sg:classifiers":[
        {
            "category":"Education",
            "subcategory":"Special Training",
            "type":"Public Place"
        }
    ],
    "sg:phone":"+1 613 828 4560",
    "sg:postcode":"K2H 8P6",
    "sg:province":"ON",
    "sg:tags":[
        "management"
    ],
    "wof:name":"Montgomery Group",
    "wof:placetype":"venue"
},
  "geometry": {"coordinates":[-75.780281,45.322308],"type":"Point"}
}