{
  "type": "Feature",
  "properties": {
    "addr:full":"1912 Spall Rd #101 Kelowna BC V1Y 4R1",
    "addr:housenumber":"1912",
    "addr:postcode":"v1y 4r1",
    "addr:street":"Spall Rd # 101",
    "iso:country":"CA",
    "sg:address":"1912 Spall Rd #101",
    "sg:city":"Kelowna",
    "sg:classifiers":[
        {
            "category":"Retail",
            "subcategory":"Repair Shop",
            "type":"Services"
        }
    ],
    "sg:phone":"+1 250 862 3577",
    "sg:postcode":"V1Y 4R1",
    "sg:province":"BC",
    "sg:tags":[
        "furnace",
        "conditioning",
        "air"
    ],
    "wof:name":"Air-Ease Distributors",
    "wof:placetype":"venue"
},
  "geometry": {"coordinates":[-119.454666,49.879208],"type":"Point"}
}