{
  "type": "Feature",
  "properties": {
    "addr:full":"London ON N6A 4G5",
    "addr:postcode":"n6a 4g5",
    "iso:country":"CA",
    "sg:city":"London",
    "sg:classifiers":[
        {
            "category":"Health Services",
            "subcategory":"Doctor",
            "type":"Services"
        }
    ],
    "sg:phone":"+1 519 685 8349",
    "sg:postcode":"N6A 4G5",
    "sg:province":"ON",
    "sg:tags":[
        "physician",
        "surgeon"
    ],
    "wof:name":"Lindsay, R M MD",
    "wof:placetype":"venue"
},
  "geometry": {"coordinates":[-81.23584700000001,42.97654],"type":"Point"}
}