{
  "type": "Feature",
  "properties": {
    "addr:full":"Montreal QC H3H 1J9",
    "addr:postcode":"h3h 1j9",
    "iso:country":"CA",
    "sg:city":"Montreal",
    "sg:classifiers":[
        {
            "category":"Health Services",
            "subcategory":"Doctor",
            "type":"Services"
        }
    ],
    "sg:phone":"+1 514 933 3641",
    "sg:postcode":"H3H 1J9",
    "sg:province":"QC",
    "sg:tags":[
        "dentist"
    ],
    "wof:name":"Clinique Dentaire Cohen",
    "wof:placetype":"venue"
},
  "geometry": {"coordinates":[-73.553787,45.523373],"type":"Point"}
}