{
  "type": "Feature",
  "properties": {
    "addr:full":"42 Lansdowne Ave Carleton Place ON K7C 2T8",
    "addr:housenumber":"42",
    "addr:postcode":"k7c 2t8",
    "addr:street":"Lansdowne Ave",
    "iso:country":"CA",
    "sg:address":"42 Lansdowne Ave",
    "sg:city":"Carleton Place",
    "sg:classifiers":[
        {
            "category":"Health Services",
            "subcategory":"Doctor",
            "type":"Services"
        }
    ],
    "sg:phone":"+1 613 257 1717",
    "sg:postcode":"K7C 2T8",
    "sg:province":"ON",
    "sg:tags":[
        "dentist"
    ],
    "wof:name":"Nguyen, K DDS",
    "wof:placetype":"venue"
},
  "geometry": {"coordinates":[-76.1407546997,45.1355514526],"type":"Point"}
}