{
  "type": "Feature",
  "properties": {
    "iso:country":"CA",
    "sg:city":"Powell River",
    "sg:classifiers":[
        {
            "category":"Restaurant",
            "type":"Food & Drink"
        }
    ],
    "sg:phone":"+1 604 485 0122",
    "sg:postcode":"V8A 1W6",
    "sg:province":"BC",
    "sg:tags":[
        "shop",
        "coffee"
    ],
    "wof:name":"Aroma's Gourmet Coffee & Lunch",
    "wof:placetype":"venue"
},
  "geometry": {"coordinates":[-124.50587463399999,49.8371086121],"type":"Point"}
}