{
  "type": "Feature",
  "properties": {
    "addr:full":"205 Lonsdale Ave North Vancouver BC V7M 2E9",
    "addr:housenumber":"205",
    "addr:postcode":"v7m 2e9",
    "addr:street":"Lonsdale Ave",
    "iso:country":"CA",
    "sg:address":"205 Lonsdale Ave",
    "sg:city":"North Vancouver",
    "sg:classifiers":[
        {
            "category":"Wholesale",
            "subcategory":"Groceries",
            "type":"Manufacturing & Wholesale Goods"
        }
    ],
    "sg:phone":"+1 604 990 0833",
    "sg:postcode":"V7M 2E9",
    "sg:province":"BC",
    "sg:tags":[
        "aromatherapy"
    ],
    "wof:name":"Nature's Creations",
    "wof:placetype":"venue"
},
  "geometry": {"coordinates":[-123.077819824,49.3128395081],"type":"Point"}
}