{
  "type": "Feature",
  "properties": {
    "addr:full":"Red Deer AB T4R 1C5",
    "addr:postcode":"t4r 1c5",
    "iso:country":"CA",
    "sg:city":"Red Deer",
    "sg:classifiers":[
        {
            "category":"Arts & Performance",
            "subcategory":"Theater",
            "type":"Entertainment"
        }
    ],
    "sg:phone":"+1 403 342 5505",
    "sg:postcode":"T4R 1C5",
    "sg:province":"AB",
    "sg:tags":[
        "player",
        "recorder",
        "video"
    ],
    "wof:name":"Adult Video Super Store",
    "wof:placetype":"venue"
},
  "geometry": {"coordinates":[-113.81459,52.24329],"type":"Point"}
}