{
  "type": "Feature",
  "properties": {
    "addr:full":"Trois-Rivieres QC G8Y 5M6",
    "addr:postcode":"g8y 5m6",
    "iso:country":"CA",
    "sg:city":"Trois-Rivieres",
    "sg:classifiers":[
        {
            "category":"Insurance",
            "subcategory":"Insurance Agent",
            "type":"Services"
        }
    ],
    "sg:phone":"+1 819 373 4949",
    "sg:postcode":"G8Y 5M6",
    "sg:province":"QC",
    "wof:name":"Services Financiers Rg Inc",
    "wof:placetype":"venue"
},
  "geometry": {"coordinates":[-72.5769729614,46.3550415039],"type":"Point"}
}