{
  "type": "Feature",
  "properties": {
    "addr:full":"1063 Av Des Noyers Sainte-Julienne QC J0K 2T0",
    "addr:housenumber":"1063",
    "addr:postcode":"j0k 2t0",
    "addr:street":"Av Des Noyers",
    "iso:country":"CA",
    "sg:address":"1063 Av Des Noyers",
    "sg:city":"Sainte-Julienne",
    "sg:classifiers":[
        {
            "category":"Building & Trades",
            "subcategory":"Electrical",
            "type":"Services"
        }
    ],
    "sg:phone":"+1 450 831 3289",
    "sg:postcode":"J0K 2T0",
    "sg:province":"QC",
    "sg:tags":[
        "electric",
        "contractor"
    ],
    "wof:name":"Electrilarme",
    "wof:placetype":"venue"
},
  "geometry": {"coordinates":[-73.76556396479999,45.9492263794],"type":"Point"}
}