{
  "type": "Feature",
  "properties": {
    "iso:country":"CA",
    "sg:city":"Surrey",
    "sg:classifiers":[
        {
            "category":"Autos & Motor Vehicles",
            "subcategory":"Boat Sales",
            "type":"Retail Goods"
        }
    ],
    "sg:phone":"+1 604 596 7311",
    "sg:postcode":"V3W 2V8",
    "sg:province":"BC",
    "sg:tags":[
        "propeller"
    ],
    "wof:name":"Precision Propeller Ltd",
    "wof:placetype":"venue"
},
  "geometry": {"coordinates":[-122.86792755099999,49.1410598755],"type":"Point"}
}