{
  "type": "Feature",
  "properties": {
    "addr:full":"Bloomfield ON K0K 1G0",
    "addr:postcode":"k0k 1g0",
    "iso:country":"CA",
    "sg:city":"Bloomfield",
    "sg:classifiers":[
        {
            "category":"Building & Trades",
            "subcategory":"Plumbing",
            "type":"Services"
        }
    ],
    "sg:phone":"+1 613 393 2262",
    "sg:postcode":"K0K 1G0",
    "sg:province":"ON",
    "sg:tags":[
        "contractor"
    ],
    "wof:name":"Veenstra's Plumbing & Heating",
    "wof:placetype":"venue"
},
  "geometry": {"coordinates":[-77.212318,43.988529],"type":"Point"}
}