{
  "type": "Feature",
  "properties": {
    "addr:full":"71 Elizabeth Ave St. John's NL A1A 1W8",
    "addr:housenumber":"71",
    "addr:postcode":"a1a 1w8",
    "addr:street":"Elizabeth Ave",
    "iso:country":"CA",
    "sg:address":"71 Elizabeth Ave",
    "sg:city":"St. John's",
    "sg:classifiers":[
        {
            "category":"Autos & Motor Vehicles",
            "subcategory":"Fuel & Gas Station",
            "type":"Retail Goods"
        }
    ],
    "sg:phone":"+1 709 753 7200",
    "sg:postcode":"A1A 1W8",
    "sg:province":"NL",
    "sg:tags":[
        "oil"
    ],
    "wof:name":"Elizabeth Ave Irving",
    "wof:placetype":"venue"
},
  "geometry": {"coordinates":[-58.5768661499,48.5545005798],"type":"Point"}
}