{
  "type": "Feature",
  "properties": {
    "addr:full":"10624 59 St NW Edmonton AB T6A 2K7",
    "addr:housenumber":"10624",
    "addr:postcode":"t6a 2k7",
    "addr:street":"59 St Nw",
    "iso:country":"CA",
    "sg:address":"10624 59 St NW",
    "sg:city":"Edmonton",
    "sg:classifiers":[
        {
            "category":"Social Services",
            "subcategory":"Adult Care",
            "type":"Services"
        }
    ],
    "sg:phone":"+1 780 422 1443",
    "sg:postcode":"T6A 2K7",
    "sg:province":"AB",
    "sg:tags":[
        "home"
    ],
    "wof:name":"Hardisty Group Home",
    "wof:placetype":"venue"
},
  "geometry": {"coordinates":[-113.426872,53.551182],"type":"Point"}
}