{
  "type": "Feature",
  "properties": {
    "addr:full":"111 Commerce Rd Orillia ON L3V 6H3",
    "addr:housenumber":"111",
    "addr:postcode":"l3v 6h3",
    "addr:street":"Commerce Rd",
    "iso:country":"CA",
    "sg:address":"111 Commerce Rd",
    "sg:city":"Orillia",
    "sg:classifiers":[
        {
            "category":"Autos & Motor Vehicles",
            "subcategory":"Automobile Sales",
            "type":"Retail Goods"
        }
    ],
    "sg:phone":"+1 705 325 6311",
    "sg:postcode":"L3V 6H3",
    "sg:province":"ON",
    "sg:tags":[
        "scooter",
        "motorcycle",
        "snowmobile"
    ],
    "wof:name":"Orillia Motor Sport Ltd",
    "wof:placetype":"venue"
},
  "geometry": {"coordinates":[-79.4261856079,44.6375198364],"type":"Point"}
}