{
  "type": "Feature",
  "properties": {
    "addr:full":"General Delivery Kegaska QC G0G 1S0",
    "addr:postcode":"g0g 1s0",
    "addr:street":"Kegaska",
    "iso:country":"CA",
    "sg:address":"General Delivery",
    "sg:city":"Kegaska",
    "sg:classifiers":[
        {
            "category":"Travel",
            "subcategory":"Travel Agent",
            "type":"Entertainment"
        }
    ],
    "sg:phone":"+1 418 726 3527",
    "sg:postcode":"G0G 1S0",
    "sg:province":"QC",
    "sg:tags":[
        "agency",
        "steamship"
    ],
    "wof:name":"Relais Nordik Kegaska",
    "wof:placetype":"venue"
},
  "geometry": {"coordinates":[-61.272289,50.188374],"type":"Point"}
}