{
  "type": "Feature",
  "properties": {
    "iso:country":"CA",
    "sg:address":"115 Ram Forest Rd",
    "sg:city":"Gormley",
    "sg:classifiers":[
        {
            "category":"Home & Garden",
            "subcategory":"Mobile Homes",
            "type":"Retail Goods"
        }
    ],
    "sg:phone":"+1 905 841 1433",
    "sg:postcode":"L0H 1G0",
    "sg:province":"ON",
    "sg:tags":[
        "renting",
        "commercial",
        "leasing",
        "unit",
        "trailer"
    ],
    "wof:name":"Mobilease Rentals Inc",
    "wof:placetype":"venue"
},
  "geometry": {"coordinates":[-79.3790054321,43.9433898926],"type":"Point"}
}