{
  "type": "Feature",
  "properties": {
    "addr:full":"1190 Marine Dr North Vancouver BC V7P 1S8",
    "addr:housenumber":"1190",
    "addr:postcode":"v7p 1s8",
    "addr:street":"Marine Dr",
    "iso:country":"CA",
    "sg:address":"1190 Marine Dr",
    "sg:city":"North Vancouver",
    "sg:classifiers":[
        {
            "category":"Home & Garden",
            "subcategory":"Garden Supply",
            "type":"Retail Goods"
        }
    ],
    "sg:phone":"+1 604 988 2121",
    "sg:postcode":"V7P 1S8",
    "sg:province":"BC",
    "sg:tags":[
        "house",
        "bird",
        "feeder"
    ],
    "wof:name":"Wild Birds Unlimited",
    "wof:placetype":"venue"
},
  "geometry": {"coordinates":[-123.107231,49.32394],"type":"Point"}
}