{
  "type": "Feature",
  "properties": {
    "addr:full":"Medicine Hat AB T1A 8L9",
    "addr:postcode":"t1a 8l9",
    "iso:country":"CA",
    "sg:city":"Medicine Hat",
    "sg:classifiers":[
        {
            "category":"Food & Beverages",
            "subcategory":"Specialty",
            "type":"Retail Goods"
        }
    ],
    "sg:phone":"+1 403 504 4525",
    "sg:postcode":"T1A 8L9",
    "sg:province":"AB",
    "sg:tags":[
        "health",
        "diet"
    ],
    "wof:name":"Vitamin Centre",
    "wof:placetype":"venue"
},
  "geometry": {"coordinates":[-110.656662,50.00972],"type":"Point"}
}