{
  "type": "Feature",
  "properties": {
    "addr:full":"88 Rue Taschereau O Rouyn-Noranda QC J9X 2V4",
    "addr:housenumber":"88",
    "addr:postcode":"j9x 2v4",
    "addr:street":"Rue Taschereau O",
    "iso:country":"CA",
    "sg:address":"88 Rue Taschereau O",
    "sg:city":"Rouyn-Noranda",
    "sg:classifiers":[
        {
            "category":"Retail",
            "subcategory":"Repair Shop",
            "type":"Services"
        }
    ],
    "sg:phone":"+1 819 764 6611",
    "sg:postcode":"J9X 2V4",
    "sg:province":"QC",
    "sg:tags":[
        "sharpening"
    ],
    "wof:name":"Affuteurs Du Nord-Ouest Inc",
    "wof:placetype":"venue"
},
  "geometry": {"coordinates":[-79.017937,48.237259],"type":"Point"}
}