{
  "type": "Feature",
  "properties": {
    "addr:full":"634 Colborne St Brantford ON N3S 3P8",
    "addr:housenumber":"634",
    "addr:postcode":"n3s 3p8",
    "addr:street":"Colborne St",
    "iso:country":"CA",
    "sg:address":"634 Colborne St",
    "sg:city":"Brantford",
    "sg:classifiers":[
        {
            "category":"Recreation",
            "type":"Entertainment"
        }
    ],
    "sg:phone":"+1 519 756 8813",
    "sg:postcode":"N3S 3P8",
    "sg:province":"ON",
    "sg:tags":[
        "parlor",
        "billiard"
    ],
    "wof:name":"Colby's",
    "wof:placetype":"venue"
},
  "geometry": {"coordinates":[-80.2400894165,43.140712738],"type":"Point"}
}