{
  "type": "Feature",
  "properties": {
    "addr:full":"621 Boul Charest E Quebec QC G1K 3J5",
    "addr:housenumber":"621",
    "addr:postcode":"g1k 3j5",
    "addr:street":"Boul Charest E",
    "iso:country":"CA",
    "sg:address":"621 Boul Charest E",
    "sg:city":"Quebec",
    "sg:classifiers":[
        {
            "category":"Banks & Credit Unions",
            "subcategory":"Financial Services",
            "type":"Services"
        }
    ],
    "sg:phone":"+1 418 525 4641",
    "sg:postcode":"G1K 3J5",
    "sg:province":"QC",
    "sg:tags":[
        "bankruptcy",
        "trustee"
    ],
    "wof:name":"Leblond & Assoc Inc",
    "wof:placetype":"venue"
},
  "geometry": {"coordinates":[-71.221046,46.814434],"type":"Point"}
}