{
  "type": "Feature",
  "properties": {
    "addr:full":"5054 Rue DE Castille Montreal-Nord QC H1G 3C2",
    "addr:housenumber":"5054",
    "addr:postcode":"h1g 3c2",
    "addr:street":"Rue De Castille",
    "iso:country":"CA",
    "sg:address":"5054 Rue DE Castille",
    "sg:city":"Montreal-Nord",
    "sg:classifiers":[
        {
            "category":"Restaurant",
            "type":"Food & Drink"
        }
    ],
    "sg:phone":"+1 514 852 9391",
    "sg:postcode":"H1G 3C2",
    "sg:province":"QC",
    "wof:name":"Restaurant Chez LA Mere",
    "wof:placetype":"venue"
},
  "geometry": {"coordinates":[-73.62487,45.597401],"type":"Point"}
}