{
  "type": "Feature",
  "properties": {
    "addr:full":"Parksville BC V9P 2G3",
    "addr:postcode":"v9p 2g3",
    "iso:country":"CA",
    "sg:city":"Parksville",
    "sg:classifiers":[
        {
            "category":"Shopping",
            "type":"Retail Goods"
        }
    ],
    "sg:phone":"+1 250 248 8144",
    "sg:postcode":"V9P 2G3",
    "sg:province":"BC",
    "sg:tags":[
        "hearing",
        "equipment",
        "supply",
        "impaired"
    ],
    "wof:name":"Island Hearing Svc",
    "wof:placetype":"venue"
},
  "geometry": {"coordinates":[-124.306892,49.319546],"type":"Point"}
}