{
  "type": "Feature",
  "properties": {
    "addr:full":"118 Rue Saint-Thomas Montmagny QC G5V 1M2",
    "addr:housenumber":"118",
    "addr:postcode":"g5v 1m2",
    "addr:street":"Rue Saint-Thomas",
    "iso:country":"CA",
    "sg:address":"118 Rue Saint-Thomas",
    "sg:city":"Montmagny",
    "sg:classifiers":[
        {
            "category":"Organizations",
            "subcategory":"Professional Association",
            "type":"Services"
        }
    ],
    "sg:phone":"+1 418 248 7141",
    "sg:postcode":"G5V 1M2",
    "sg:province":"QC",
    "wof:name":"Logements Cote Du Sud Inc",
    "wof:placetype":"venue"
},
  "geometry": {"coordinates":[-70.5577468872,46.9803543091],"type":"Point"}
}