{
  "type": "Feature",
  "properties": {
    "addr:full":"Uxbridge ON L9P 1S9",
    "addr:postcode":"l9p 1s9",
    "iso:country":"CA",
    "sg:city":"Uxbridge",
    "sg:classifiers":[
        {
            "category":"Restaurant",
            "type":"Food & Drink"
        }
    ],
    "sg:phone":"+1 905 852 5639",
    "sg:postcode":"L9P 1S9",
    "sg:province":"ON",
    "wof:name":"B & L Country Kitchen",
    "wof:placetype":"venue"
},
  "geometry": {"coordinates":[-79.131714,44.092262],"type":"Point"}
}