{
  "type": "Feature",
  "properties": {
    "iso:country":"CA",
    "sg:address":"253 King St E",
    "sg:city":"Oshawa",
    "sg:classifiers":[
        {
            "category":"Shopping",
            "subcategory":"Optical Goods",
            "type":"Retail Goods"
        }
    ],
    "sg:phone":"+1 905 432 6033",
    "sg:postcode":"L1H 1C5",
    "sg:province":"ON",
    "sg:tags":[
        "optician"
    ],
    "wof:name":"New Vision Optical Inc",
    "wof:placetype":"venue"
},
  "geometry": {"coordinates":[-78.85443115229999,43.8995742798],"type":"Point"}
}