{
  "type": "Feature",
  "properties": {
    "addr:full":"1350 Boul Cremazie E Montreal QC H2E 1A1",
    "addr:housenumber":"1350",
    "addr:postcode":"h2e 1a1",
    "addr:street":"Boul Cremazie E",
    "iso:country":"CA",
    "sg:address":"1350 Boul Cremazie E",
    "sg:city":"Montreal",
    "sg:classifiers":[
        {
            "category":"Education",
            "subcategory":"School",
            "type":"Public Place"
        }
    ],
    "sg:phone":"+1 514 596 4300",
    "sg:postcode":"H2E 1A1",
    "sg:province":"QC",
    "wof:name":"Victor-Dore Ecole",
    "wof:placetype":"venue"
},
  "geometry": {"coordinates":[-73.625542,45.552135],"type":"Point"}
}