{
  "type": "Feature",
  "properties": {
    "addr:full":"400 St Laurent Blvd Ottawa ON K1K 2Z6",
    "addr:housenumber":"400",
    "addr:postcode":"k1k 2z6",
    "addr:street":"St Laurent Blvd",
    "iso:country":"CA",
    "sg:address":"400 St Laurent Blvd",
    "sg:city":"Ottawa",
    "sg:classifiers":[
        {
            "category":"Organizations",
            "subcategory":"Religious Organization",
            "type":"Services"
        }
    ],
    "sg:phone":"+1 613 748 6040",
    "sg:postcode":"K1K 2Z6",
    "sg:province":"ON",
    "sg:tags":[
        "church"
    ],
    "wof:name":"Our Lady of Mount Carmel Chr",
    "wof:placetype":"venue"
},
  "geometry": {"coordinates":[-75.6507797241,45.4477386475],"type":"Point"}
}