{
  "type": "Feature",
  "properties": {
    "addr:full":"Melbourne ON N0L 1T0",
    "addr:postcode":"n0l 1t0",
    "iso:country":"CA",
    "sg:city":"Melbourne",
    "sg:classifiers":[
        {
            "category":"Personal",
            "subcategory":"Beauty Salon",
            "type":"Services"
        }
    ],
    "sg:phone":"+1 519 289 0930",
    "sg:postcode":"N0L 1T0",
    "sg:province":"ON",
    "wof:name":"Hair Works",
    "wof:placetype":"venue"
},
  "geometry": {"coordinates":[-81.550186,42.81522],"type":"Point"}
}