{
  "type": "Feature",
  "properties": {
    "addr:full":"7646 Colborne St E Elora ON N0B 1S0",
    "addr:housenumber":"7646",
    "addr:postcode":"n0b 1s0",
    "addr:street":"Colborne St E",
    "iso:country":"CA",
    "sg:address":"7646 Colborne St E",
    "sg:city":"Elora",
    "sg:classifiers":[
        {
            "category":"Home & Garden",
            "subcategory":"Garden Supply",
            "type":"Retail Goods"
        }
    ],
    "sg:phone":"+1 519 846 9639",
    "sg:postcode":"N0B 1S0",
    "sg:province":"ON",
    "sg:tags":[
        "center"
    ],
    "wof:name":"Gerrie's Garden Ctr & Farm",
    "wof:placetype":"venue"
},
  "geometry": {"coordinates":[-80.410561,43.698338],"type":"Point"}
}