{
  "type": "Feature",
  "properties": {
    "addr:full":"4575 Fourth St Windsor ON N9E 4M9",
    "addr:housenumber":"4575",
    "addr:postcode":"n9e 4m9",
    "addr:street":"Fourth St",
    "iso:country":"CA",
    "sg:address":"4575 Fourth St",
    "sg:city":"Windsor",
    "sg:classifiers":[
        {
            "category":"Bus Charters",
            "type":"Transportation"
        }
    ],
    "sg:phone":"+1 519 969 0184",
    "sg:postcode":"N9E 4M9",
    "sg:province":"ON",
    "sg:tags":[
        "rental"
    ],
    "wof:name":"Laidlaw Transit Ltd",
    "wof:placetype":"venue"
},
  "geometry": {"coordinates":[-83.0339126587,42.3178215027],"type":"Point"}
}