{
  "type": "Feature",
  "properties": {
    "addr:full":"2774 Rue DE Salaberry Montreal QC H3M 1L3",
    "addr:housenumber":"2774",
    "addr:postcode":"h3m 1l3",
    "addr:street":"Rue De Salaberry",
    "iso:country":"CA",
    "sg:address":"2774 Rue DE Salaberry",
    "sg:city":"Montreal",
    "sg:classifiers":[
        {
            "category":"Personal",
            "subcategory":"Beauty Salon",
            "type":"Services"
        }
    ],
    "sg:phone":"+1 514 334 8813",
    "sg:postcode":"H3M 1L3",
    "sg:province":"QC",
    "sg:tags":[
        "manicuring"
    ],
    "wof:name":"Lina Ongle",
    "wof:placetype":"venue"
},
  "geometry": {"coordinates":[-73.700012207,45.537322998],"type":"Point"}
}