{
  "type": "Feature",
  "properties": {
    "addr:full":"10705 109 St NW Edmonton AB T5H 3B7",
    "addr:housenumber":"10705",
    "addr:postcode":"t5h 3b7",
    "addr:street":"109 St Nw",
    "iso:country":"CA",
    "sg:address":"10705 109 St NW",
    "sg:city":"Edmonton",
    "sg:classifiers":[
        {
            "category":"Personal",
            "subcategory":"Barber",
            "type":"Services"
        }
    ],
    "sg:phone":"+1 780 414 6026",
    "sg:postcode":"T5H 3B7",
    "sg:province":"AB",
    "wof:name":"Seventh & Ninth Barber & Bty",
    "wof:placetype":"venue"
},
  "geometry": {"coordinates":[-113.50822448700001,53.5515594482],"type":"Point"}
}