{
  "type": "Feature",
  "properties": {
    "addr:full":"2 Mcleod St Minden ON K0M 2K0",
    "addr:housenumber":"2",
    "addr:postcode":"k0m 2k0",
    "addr:street":"Mcleod St",
    "iso:country":"CA",
    "sg:address":"2 Mcleod St",
    "sg:city":"Minden",
    "sg:classifiers":[
        {
            "category":"Building & Trades",
            "subcategory":"Plumbing",
            "type":"Services"
        }
    ],
    "sg:phone":"+1 705 286 3616",
    "sg:postcode":"K0M 2K0",
    "sg:province":"ON",
    "sg:tags":[
        "contractor"
    ],
    "wof:name":"Howard Scott Plumbing",
    "wof:placetype":"venue"
},
  "geometry": {"coordinates":[-78.7293167114,44.9276847839],"type":"Point"}
}