{
  "type": "Feature",
  "properties": {
    "addr:full":"Newmarket ON L3Y 7C1",
    "addr:postcode":"l3y 7c1",
    "iso:country":"CA",
    "sg:city":"Newmarket",
    "sg:classifiers":[
        {
            "category":"Food & Beverages",
            "subcategory":"Groceries & Convenience Stores",
            "type":"Retail Goods"
        }
    ],
    "sg:phone":"+1 905 895 9700",
    "sg:postcode":"L3Y 7C1",
    "sg:province":"ON",
    "sg:tags":[
        "grocer"
    ],
    "wof:name":"Dominion Plus",
    "wof:placetype":"venue"
},
  "geometry": {"coordinates":[-79.48138400000001,44.059731],"type":"Point"}
}