{
  "type": "Feature",
  "properties": {
    "iso:country":"CA",
    "sg:address":"36 Cashel St",
    "sg:city":"Brampton",
    "sg:classifiers":[
        {
            "category":"Retail",
            "subcategory":"Laundry & Dry Cleaning",
            "type":"Services"
        }
    ],
    "sg:phone":"+1 905 840 9811",
    "sg:postcode":"L6Z 2Y7",
    "sg:province":"ON",
    "sg:tags":[
        "rental",
        "uniform"
    ],
    "wof:name":"Uniform Rental & Svc",
    "wof:placetype":"venue"
},
  "geometry": {"coordinates":[-79.7871017456,43.709690094],"type":"Point"}
}