{
  "type": "Feature",
  "properties": {
    "iso:country":"CA",
    "sg:address":"76 Rue Industrielle",
    "sg:city":"Saint-Jacques",
    "sg:classifiers":[
        {
            "category":"Retail",
            "subcategory":"Repair Shop",
            "type":"Services"
        }
    ],
    "sg:phone":"+1 506 735 7019",
    "sg:postcode":"E7B 1T1",
    "sg:province":"NB",
    "sg:tags":[
        "welding"
    ],
    "wof:name":"Desjardins Welding Enr",
    "wof:placetype":"venue"
},
  "geometry": {"coordinates":[-68.4672241211,47.4772491455],"type":"Point"}
}