{
  "type": "Feature",
  "properties": {
    "addr:full":"3415 3 Ave NW Calgary AB T2N 0M4",
    "addr:housenumber":"3415",
    "addr:postcode":"t2n 0m4",
    "addr:street":"3 Ave Nw",
    "iso:country":"CA",
    "sg:address":"3415 3 Ave NW",
    "sg:city":"Calgary",
    "sg:classifiers":[
        {
            "category":"Professional",
            "subcategory":"Engineering",
            "type":"Services"
        }
    ],
    "sg:phone":"+1 403 283 0791",
    "sg:postcode":"T2N 0M4",
    "sg:province":"AB",
    "sg:tags":[
        "engineer"
    ],
    "wof:name":"Carswell Consulting Engineers",
    "wof:placetype":"venue"
},
  "geometry": {"coordinates":[-114.13670349100001,51.0577087402],"type":"Point"}
}