{
  "type": "Feature",
  "properties": {
    "addr:full":"156 Princess St Kingston ON K7L 1B1",
    "addr:housenumber":"156",
    "addr:postcode":"k7l 1b1",
    "addr:street":"Princess St",
    "iso:country":"CA",
    "sg:address":"156 Princess St",
    "sg:city":"Kingston",
    "sg:classifiers":[
        {
            "category":"Shopping",
            "subcategory":"Books",
            "type":"Retail Goods"
        }
    ],
    "sg:phone":"+1 613 546 9799",
    "sg:postcode":"K7L 1B1",
    "sg:province":"ON",
    "sg:tags":[
        "dealer"
    ],
    "wof:name":"Novel Idea",
    "wof:placetype":"venue"
},
  "geometry": {"coordinates":[-76.4845657349,44.2317237854],"type":"Point"}
}