{
  "type": "Feature",
  "properties": {
    "iso:country":"CA",
    "sg:address":"80 Rue Saint-Thomas",
    "sg:city":"Salaberry-DE-Valleyfield",
    "sg:classifiers":[
        {
            "category":"Education",
            "subcategory":"Library",
            "type":"Public Place"
        }
    ],
    "sg:phone":"+1 450 370 4860",
    "sg:postcode":"J6T 4J7",
    "sg:province":"QC",
    "wof:name":"Bibliotheque Armand Frappier",
    "wof:placetype":"venue"
},
  "geometry": {"coordinates":[-74.13241577150001,45.253578186],"type":"Point"}
}