{
  "type": "Feature",
  "properties": {
    "iso:country":"CA",
    "sg:address":"3 Ch Versant S",
    "sg:city":"Chelsea",
    "sg:classifiers":[
        {
            "category":"Professional",
            "subcategory":"Art Services",
            "type":"Services"
        }
    ],
    "sg:phone":"+1 819 827 8227",
    "sg:postcode":"J9B 1S1",
    "sg:province":"QC",
    "sg:tags":[
        "graphic",
        "designer"
    ],
    "wof:name":"Methane Design",
    "wof:placetype":"venue"
},
  "geometry": {"coordinates":[-75.8112564087,45.5091705322],"type":"Point"}
}