{
  "type": "Feature",
  "properties": {
    "addr:full":"36853 99th St Oliver BC V0H 1T0",
    "addr:housenumber":"36853",
    "addr:postcode":"bc v0h 1t0",
    "addr:street":"99Th St",
    "iso:country":"CA",
    "sg:address":"36853 99th St",
    "sg:city":"Oliver",
    "sg:classifiers":[
        {
            "category":"Organizations",
            "subcategory":"Religious Organization",
            "type":"Services"
        }
    ],
    "sg:phone":"+1 250 498 4253",
    "sg:postcode":"V0H 1T0",
    "sg:province":"BC",
    "sg:tags":[
        "church"
    ],
    "wof:name":"Alliance Church",
    "wof:placetype":"venue"
},
  "geometry": {"coordinates":[-119.550781,49.187569],"type":"Point"}
}