{
  "type": "Feature",
  "properties": {
    "addr:full":"2653 Walpole Cres North Vancouver BC V7H 1K7",
    "addr:postcode":"2653;v7h 1k7",
    "iso:country":"CA",
    "sg:address":"2653 Walpole Cres",
    "sg:city":"North Vancouver",
    "sg:classifiers":[
        {
            "category":"Building & Trades",
            "subcategory":"Construction",
            "type":"Services"
        }
    ],
    "sg:phone":"+1 604 929 7080",
    "sg:postcode":"V7H 1K7",
    "sg:province":"BC",
    "sg:tags":[
        "contractor"
    ],
    "wof:name":"Dima Construction Ltd",
    "wof:placetype":"venue"
},
  "geometry": {"coordinates":[-122.999816895,49.3216896057],"type":"Point"}
}