{
  "type": "Feature",
  "properties": {
    "addr:full":"74 Hamilton St N Waterdown ON L0R 2H4",
    "addr:housenumber":"74",
    "addr:postcode":"l0r 2h4",
    "addr:street":"Hamilton St N",
    "iso:country":"CA",
    "sg:address":"74 Hamilton St N",
    "sg:city":"Waterdown",
    "sg:classifiers":[
        {
            "category":"Shopping",
            "subcategory":"Used Merchandise",
            "type":"Retail Goods"
        }
    ],
    "sg:phone":"+1 905 689 0561",
    "sg:postcode":"L0R 2H4",
    "sg:province":"ON",
    "sg:tags":[
        "clothing"
    ],
    "wof:name":"Amity Goodwill",
    "wof:placetype":"venue"
},
  "geometry": {"coordinates":[-79.89794921879999,43.3328590393],"type":"Point"}
}