{
  "type": "Feature",
  "properties": {
    "addr:full":"130 Centrale Ave Ste Anne MB R5H 1J3",
    "addr:housenumber":"130",
    "addr:postcode":"r5h 1j3",
    "addr:street":"Centrale Ave",
    "iso:country":"CA",
    "sg:address":"130 Centrale Ave",
    "sg:city":"Ste Anne",
    "sg:classifiers":[
        {
            "category":"Banks & Credit Unions",
            "subcategory":"Bank",
            "type":"Services"
        }
    ],
    "sg:phone":"+1 204 422 8896",
    "sg:postcode":"R5H 1J3",
    "sg:province":"MB",
    "wof:name":"Caisse Populaire DE Ste Anne",
    "wof:placetype":"venue"
},
  "geometry": {"coordinates":[-96.652428,49.6712],"type":"Point"}
}