{
  "type": "Feature",
  "properties": {
    "addr:full":"7250 22E Av Montreal QC H2A 2H4",
    "addr:housenumber":"7250",
    "addr:postcode":"h2a 2h4",
    "addr:street":"22E Av",
    "iso:country":"CA",
    "sg:address":"7250 22E Av",
    "sg:city":"Montreal",
    "sg:classifiers":[
        {
            "category":"Health Services",
            "subcategory":"Medical Lab",
            "type":"Services"
        }
    ],
    "sg:phone":"+1 514 729 3114",
    "sg:postcode":"H2A 2H4",
    "sg:province":"QC",
    "wof:name":"Robida, Yvan",
    "wof:placetype":"venue"
},
  "geometry": {"coordinates":[-73.59292600000001,45.566257],"type":"Point"}
}