{
  "type": "Feature",
  "properties": {
    "addr:full":"1278 Val Doucet Rd Tracadie-Sheila NB E1X 1G4",
    "addr:housenumber":"1278",
    "addr:postcode":"e1x 1g4",
    "addr:street":"Val Doucet Rd",
    "iso:country":"CA",
    "sg:address":"1278 Val Doucet Rd",
    "sg:city":"Tracadie-Sheila",
    "sg:classifiers":[
        {
            "category":"Shopping",
            "type":"Retail Goods"
        }
    ],
    "sg:phone":"+1 506 764 3488",
    "sg:postcode":"E1X 1G4",
    "sg:province":"NB",
    "sg:tags":[
        "decoration",
        "light",
        "exporter",
        "christmas"
    ],
    "wof:name":"Savoie Export Ltee",
    "wof:placetype":"venue"
},
  "geometry": {"coordinates":[-64.910599,47.521317],"type":"Point"}
}