{
  "type": "Feature",
  "properties": {
    "addr:full":"Ste Anne MB R5H 1C3",
    "addr:postcode":"r5h 1c3",
    "iso:country":"CA",
    "sg:city":"Ste Anne",
    "sg:classifiers":[
        {
            "category":"Shopping",
            "subcategory":"Pharmacy",
            "type":"Retail Goods"
        }
    ],
    "sg:phone":"+1 204 422 8226",
    "sg:postcode":"R5H 1C3",
    "sg:province":"MB",
    "wof:name":"Seine Pharmacy Ltd",
    "wof:placetype":"venue"
},
  "geometry": {"coordinates":[-96.652428,49.6712],"type":"Point"}
}