{
  "type": "Feature",
  "properties": {
    "addr:full":"Saint-Laurent QC H4N 1C8",
    "addr:postcode":"h4n 1c8",
    "iso:country":"CA",
    "sg:city":"Saint-Laurent",
    "sg:classifiers":[
        {
            "category":"Health Services",
            "subcategory":"Doctor",
            "type":"Services"
        }
    ],
    "sg:phone":"+1 514 337 0585",
    "sg:postcode":"H4N 1C8",
    "sg:province":"QC",
    "sg:tags":[
        "dentist"
    ],
    "wof:name":"Simard, Jacques DDS",
    "wof:placetype":"venue"
},
  "geometry": {"coordinates":[-73.6695098877,45.5283432007],"type":"Point"}
}