{
  "type": "Feature",
  "properties": {
    "iso:country":"CA",
    "sg:address":"739 Av Godin",
    "sg:city":"Vanier",
    "sg:classifiers":[
        {
            "category":"Wholesale",
            "subcategory":"Electrical",
            "type":"Manufacturing & Wholesale Goods"
        }
    ],
    "sg:phone":"+1 418 681 6045",
    "sg:postcode":"G1M 2W8",
    "sg:province":"QC",
    "sg:tags":[
        "control",
        "security",
        "system"
    ],
    "wof:name":"Chubb Systemes DE Securite",
    "wof:placetype":"venue"
},
  "geometry": {"coordinates":[-71.2776260376,46.8205871582],"type":"Point"}
}