{
  "type": "Feature",
  "properties": {
    "iso:country":"CA",
    "sg:address":"60 Columbia Way",
    "sg:city":"Markham",
    "sg:classifiers":[
        {
            "category":"Professional",
            "subcategory":"Computer Services",
            "type":"Services"
        }
    ],
    "sg:phone":"+1 905 415 0384",
    "sg:postcode":"L3R 0C9",
    "sg:province":"ON",
    "wof:name":"Ods Networks",
    "wof:placetype":"venue"
},
  "geometry": {"coordinates":[-79.369408,43.852329],"type":"Point"}
}