{
  "type": "Feature",
  "properties": {
    "iso:country":"CA",
    "sg:address":"2735 Iris St",
    "sg:city":"Ottawa",
    "sg:classifiers":[
        {
            "category":"Shopping",
            "subcategory":"Books",
            "type":"Retail Goods"
        }
    ],
    "sg:phone":"+1 613 596 3003",
    "sg:postcode":"K2C 3Z7",
    "sg:province":"ON",
    "sg:tags":[
        "dealer"
    ],
    "wof:name":"Chapters",
    "wof:placetype":"venue"
},
  "geometry": {"coordinates":[-75.786346,45.348339],"type":"Point"}
}