{
  "type": "Feature",
  "properties": {
    "addr:full":"2735 Iris St Ottawa ON K2C 3Z7",
    "addr:housenumber":"2735",
    "addr:postcode":"k2c 3z7",
    "addr:street":"Iris St",
    "iso:country":"CA",
    "sg:address":"2735 Iris St",
    "sg:city":"Ottawa",
    "sg:classifiers":[
        {
            "category":"Shopping",
            "subcategory":"Books",
            "type":"Retail Goods"
        }
    ],
    "sg:phone":"+1 613 596 3003",
    "sg:postcode":"K2C 3Z7",
    "sg:province":"ON",
    "sg:tags":[
        "dealer"
    ],
    "wof:name":"Chapters",
    "wof:placetype":"venue"
},
  "geometry": {"coordinates":[-75.78634599999999,45.348339],"type":"Point"}
}