{
  "type": "Feature",
  "properties": {
    "iso:country":"CA",
    "sg:address":"1 Dufferin St",
    "sg:city":"Cookstown",
    "sg:classifiers":[
        {
            "category":"Home & Garden",
            "subcategory":"Home Furnishings",
            "type":"Retail Goods"
        }
    ],
    "sg:phone":"+1 705 458 4546",
    "sg:postcode":"L0L 1L0",
    "sg:province":"ON",
    "sg:tags":[
        "quilting"
    ],
    "wof:name":"Country Concessions",
    "wof:placetype":"venue"
},
  "geometry": {"coordinates":[-79.70501708979999,44.1889266968],"type":"Point"}
}