{
  "type": "Feature",
  "properties": {
    "addr:full":"306 17 St SE Calgary AB T2E 8V7",
    "addr:housenumber":"17",
    "addr:postcode":"t2e 8v7",
    "addr:street":"306;St Se",
    "iso:country":"CA",
    "sg:address":"306 17 St SE",
    "sg:city":"Calgary",
    "sg:classifiers":[
        {
            "category":"Freight",
            "type":"Transportation"
        }
    ],
    "sg:phone":"+1 403 203 2511",
    "sg:postcode":"T2E 8V7",
    "sg:province":"AB",
    "sg:tags":[
        "commercial",
        "storage"
    ],
    "wof:name":"Storage To Go",
    "wof:placetype":"venue"
},
  "geometry": {"coordinates":[-114.01316070599999,51.0508918762],"type":"Point"}
}