{
  "type": "Feature",
  "properties": {
    "iso:country":"CA",
    "sg:address":"2541 Empire St",
    "sg:city":"Victoria",
    "sg:classifiers":[
        {
            "category":"Social Services",
            "type":"Services"
        }
    ],
    "sg:phone":"+1 250 380 1955",
    "sg:postcode":"V8T 3M3",
    "sg:province":"BC",
    "sg:tags":[
        "counselor",
        "marriage",
        "family"
    ],
    "wof:name":"Family Violence Project",
    "wof:placetype":"venue"
},
  "geometry": {"coordinates":[-123.350502014,48.4362068176],"type":"Point"}
}