{
  "type": "Feature",
  "properties": {
    "addr:full":"Winnipeg MB R3C 3J1",
    "addr:postcode":"r3c 3j1",
    "iso:country":"CA",
    "sg:city":"Winnipeg",
    "sg:classifiers":[
        {
            "category":"Travel",
            "subcategory":"Hotels & Motels",
            "type":"Entertainment"
        }
    ],
    "sg:phone":"+1 204 956 4000",
    "sg:postcode":"R3C 3J1",
    "sg:province":"MB",
    "wof:name":"Country Inn & Suites",
    "wof:placetype":"venue"
},
  "geometry": {"coordinates":[-97.14399,49.889622],"type":"Point"}
}