{
  "type": "Feature",
  "properties": {
    "addr:full":"2150 Burnhamthorpe Rd W Mississauga ON L5L 3A2",
    "addr:housenumber":"2150",
    "addr:postcode":"l5l 3a2",
    "addr:street":"Burnhamthorpe Rd W",
    "iso:country":"CA",
    "sg:address":"2150 Burnhamthorpe Rd W",
    "sg:city":"Mississauga",
    "sg:classifiers":[
        {
            "category":"Shopping",
            "subcategory":"Clothing, Apparel, & Fashions",
            "type":"Retail Goods"
        }
    ],
    "sg:phone":"+1 905 820 8652",
    "sg:postcode":"L5L 3A2",
    "sg:province":"ON",
    "wof:name":"Fashion Max",
    "wof:placetype":"venue"
},
  "geometry": {"coordinates":[-79.6842803955,43.545425415],"type":"Point"}
}