{
  "type": "Feature",
  "properties": {
    "addr:full":"4 Robb Blvd Orangeville ON L9W 3L2",
    "addr:housenumber":"4",
    "addr:postcode":"l9w 3l2",
    "addr:street":"Robb Blvd",
    "iso:country":"CA",
    "sg:address":"4 Robb Blvd",
    "sg:city":"Orangeville",
    "sg:classifiers":[
        {
            "category":"Manufacturing",
            "subcategory":"Metals",
            "type":"Manufacturing & Wholesale Goods"
        }
    ],
    "sg:phone":"+1 519 941 7000",
    "sg:postcode":"L9W 3L2",
    "sg:province":"ON",
    "sg:tags":[
        "steel",
        "erectors",
        "forging"
    ],
    "wof:name":"Shannon Steel Ltd",
    "wof:placetype":"venue"
},
  "geometry": {"coordinates":[-80.11174800000001,43.906746],"type":"Point"}
}