{
  "type": "Feature",
  "properties": {
    "addr:full":"1887 Ch Du Tremblay Longueuil QC J4N 1A4",
    "addr:housenumber":"1887",
    "addr:postcode":"j4n 1a4",
    "addr:street":"Ch Du Tremblay",
    "iso:country":"CA",
    "sg:address":"1887 Ch Du Tremblay",
    "sg:city":"Longueuil",
    "sg:classifiers":[
        {
            "category":"Shopping",
            "subcategory":"Florist",
            "type":"Retail Goods"
        }
    ],
    "sg:phone":"+1 450 468 0950",
    "sg:postcode":"J4N 1A4",
    "sg:province":"QC",
    "wof:name":"Fleuriste Scardera Ltee",
    "wof:placetype":"venue"
},
  "geometry": {"coordinates":[-73.4524688721,45.5447731018],"type":"Point"}
}