{
  "type": "Feature",
  "properties": {
    "iso:country":"CA",
    "sg:city":"Saint-Augustin-DE-Desmaures",
    "sg:classifiers":[
        {
            "category":"Health Services",
            "subcategory":"Doctor",
            "type":"Services"
        }
    ],
    "sg:phone":"+1 418 878 5250",
    "sg:postcode":"G3A 2S7",
    "sg:province":"QC",
    "sg:tags":[
        "physiotherapist",
        "clinic"
    ],
    "wof:name":"Clinique DE Physiotherapy St",
    "wof:placetype":"venue"
},
  "geometry": {"coordinates":[-71.3847198486,46.749168396],"type":"Point"}
}