{
  "type": "Feature",
  "properties": {
    "iso:country":"CA",
    "sg:address":"RR 1",
    "sg:city":"Bentley",
    "sg:classifiers":[
        {
            "category":"Building & Trades",
            "subcategory":"Plumbing",
            "type":"Services"
        }
    ],
    "sg:phone":"+1 403 748 2628",
    "sg:postcode":"T0C 0J0",
    "sg:province":"AB",
    "sg:tags":[
        "septic"
    ],
    "wof:name":"Jim's Septic Tank Svc",
    "wof:placetype":"venue"
},
  "geometry": {"coordinates":[-114.04576873800001,52.4650497437],"type":"Point"}
}