{
  "type": "Feature",
  "properties": {
    "addr:full":"Calgary AB T2E 6Z4",
    "addr:postcode":"t2e 6z4",
    "iso:country":"CA",
    "sg:city":"Calgary",
    "sg:classifiers":[
        {
            "category":"Retail",
            "subcategory":"Auto Repair",
            "type":"Services"
        }
    ],
    "sg:phone":"+1 403 250 2257",
    "sg:postcode":"T2E 6Z4",
    "sg:province":"AB",
    "sg:tags":[
        "repairing",
        "automobile"
    ],
    "wof:name":"Canadian Motors CO Ltd",
    "wof:placetype":"venue"
},
  "geometry": {"coordinates":[-114.012306213,51.0751190186],"type":"Point"}
}