{
  "type": "Feature",
  "properties": {
    "addr:full":"Woodstock ON N4V 1C8",
    "addr:postcode":"n4v 1c8",
    "iso:country":"CA",
    "sg:city":"Woodstock",
    "sg:classifiers":[
        {
            "category":"Retail",
            "subcategory":"Repair Shop",
            "type":"Services"
        }
    ],
    "sg:phone":"+1 519 539 0532",
    "sg:postcode":"N4V 1C8",
    "sg:province":"ON",
    "sg:tags":[
        "welding"
    ],
    "wof:name":"Terry's Welding",
    "wof:placetype":"venue"
},
  "geometry": {"coordinates":[-80.726967,43.109459],"type":"Point"}
}