{
  "type": "Feature",
  "properties": {
    "iso:country":"CA",
    "sg:address":"1415 Whyte Ave",
    "sg:city":"Winnipeg",
    "sg:classifiers":[
        {
            "category":"Manufacturing",
            "subcategory":"Chemicals & Compounds",
            "type":"Manufacturing & Wholesale Goods"
        }
    ],
    "sg:phone":"+1 204 786 5736",
    "sg:postcode":"R3E 1V7",
    "sg:province":"MB",
    "sg:tags":[
        "fertilizer"
    ],
    "wof:name":"Power Rich Corp",
    "wof:placetype":"venue"
},
  "geometry": {"coordinates":[-97.1823883057,49.9189605713],"type":"Point"}
}