{
  "type": "Feature",
  "properties": {
    "iso:country":"CA",
    "sg:address":"125 Ferndale Dr S",
    "sg:city":"Barrie",
    "sg:classifiers":[
        {
            "category":"Building & Trades",
            "subcategory":"Construction",
            "type":"Services"
        }
    ],
    "sg:phone":"+1 705 726 9441",
    "sg:postcode":"L4N 6Y6",
    "sg:province":"ON",
    "sg:tags":[
        "general",
        "contractor"
    ],
    "wof:name":"Dawson Contracting Ltd",
    "wof:placetype":"venue"
},
  "geometry": {"coordinates":[-79.71521,44.361481],"type":"Point"}
}