{
  "type": "Feature",
  "properties": {
    "addr:full":"2 St Clair Ave E Toronto ON M4T 2T5",
    "addr:housenumber":"2",
    "addr:postcode":"m4t 2t5",
    "addr:street":"St Clair Ave E",
    "iso:country":"CA",
    "sg:address":"2 St Clair Ave E",
    "sg:city":"Toronto",
    "sg:classifiers":[
        {
            "category":"Shopping",
            "subcategory":"Optical Goods",
            "type":"Retail Goods"
        }
    ],
    "sg:phone":"+1 416 966 2489",
    "sg:postcode":"M4T 2T5",
    "sg:province":"ON",
    "sg:tags":[
        "optician"
    ],
    "wof:name":"City Optical",
    "wof:placetype":"venue"
},
  "geometry": {"coordinates":[-79.393974,43.688213],"type":"Point"}
}