{
  "type": "Feature",
  "properties": {
    "addr:full":"85 Hartzell Rd St Catharines ON L2P 1N2",
    "addr:housenumber":"85",
    "addr:postcode":"l2p 1n2",
    "addr:street":"Hartzell Rd",
    "iso:country":"CA",
    "sg:address":"85 Hartzell Rd",
    "sg:city":"St Catharines",
    "sg:classifiers":[
        {
            "category":"Restaurant",
            "type":"Food & Drink"
        }
    ],
    "sg:phone":"+1 905 682 3295",
    "sg:postcode":"L2P 1N2",
    "sg:province":"ON",
    "wof:name":"Lancer Restaurants",
    "wof:placetype":"venue"
},
  "geometry": {"coordinates":[-79.21449279789999,43.1530456543],"type":"Point"}
}