{
  "type": "Feature",
  "properties": {
    "addr:full":"104 Rue Eddy Hull QC J8X 2W5",
    "addr:housenumber":"104",
    "addr:postcode":"j8x 2w5",
    "addr:street":"Rue Eddy",
    "iso:country":"CA",
    "sg:address":"104 Rue Eddy",
    "sg:city":"Hull",
    "sg:classifiers":[
        {
            "category":"Bars & Pubs",
            "type":"Food & Drink"
        }
    ],
    "sg:phone":"+1 819 772 1806",
    "sg:postcode":"J8X 2W5",
    "sg:province":"QC",
    "wof:name":"Bistro Bar L'Original",
    "wof:placetype":"venue"
},
  "geometry": {"coordinates":[-75.719955,45.42836],"type":"Point"}
}