{
  "type": "Feature",
  "properties": {
    "addr:full":"32 Gordon Mackay Rd North York ON M9N 2V6",
    "addr:housenumber":"32",
    "addr:postcode":"m9n 2v6",
    "addr:street":"Gordon Mackay Rd",
    "iso:country":"CA",
    "sg:address":"32 Gordon Mackay Rd",
    "sg:city":"North York",
    "sg:classifiers":[
        {
            "category":"Building & Trades",
            "subcategory":"Plumbing",
            "type":"Services"
        }
    ],
    "sg:phone":"+1 416 743 1038",
    "sg:postcode":"M9N 2V6",
    "sg:province":"ON",
    "sg:tags":[
        "contractor"
    ],
    "wof:name":"J J Mechanical Contractors",
    "wof:placetype":"venue"
},
  "geometry": {"coordinates":[-79.50975,43.715023],"type":"Point"}
}