{
  "type": "Feature",
  "properties": {
    "addr:full":"325 Sandhill Rd Kanata ON K2K 1X7",
    "addr:housenumber":"325",
    "addr:postcode":"k2k 1x7",
    "addr:street":"Sandhill Rd",
    "iso:country":"CA",
    "sg:address":"325 Sandhill Rd",
    "sg:city":"Kanata",
    "sg:classifiers":[
        {
            "category":"Organizations",
            "subcategory":"Religious Organization",
            "type":"Services"
        }
    ],
    "sg:phone":"+1 613 592 4747",
    "sg:postcode":"K2K 1X7",
    "sg:province":"ON",
    "sg:tags":[
        "church"
    ],
    "wof:name":"St John's Anglican South March",
    "wof:placetype":"venue"
},
  "geometry": {"coordinates":[-75.9270324707,45.3555984497],"type":"Point"}
}