{
  "type": "Feature",
  "properties": {
    "addr:full":"Richmond Hill ON L4B 1C5",
    "addr:postcode":"l4b 1c5",
    "iso:country":"CA",
    "sg:city":"Richmond Hill",
    "sg:classifiers":[
        {
            "category":"Retail",
            "subcategory":"Repair Shop",
            "type":"Services"
        }
    ],
    "sg:phone":"+1 905 771 6111",
    "sg:postcode":"L4B 1C5",
    "sg:province":"ON",
    "sg:tags":[
        "tool",
        "parts"
    ],
    "wof:name":"Dubiner Industries",
    "wof:placetype":"venue"
},
  "geometry": {"coordinates":[-79.385559082,43.8481941223],"type":"Point"}
}