{
  "type": "Feature",
  "properties": {
    "addr:full":"4913 Main St Vancouver BC V5W 2R2",
    "addr:housenumber":"4913",
    "addr:postcode":"v5w 2r2",
    "addr:street":"Main St",
    "iso:country":"CA",
    "sg:address":"4913 Main St",
    "sg:city":"Vancouver",
    "sg:classifiers":[
        {
            "category":"Retail",
            "subcategory":"Laundry & Dry Cleaning",
            "type":"Services"
        }
    ],
    "sg:phone":"+1 604 322 3216",
    "sg:postcode":"V5W 2R2",
    "sg:province":"BC",
    "sg:tags":[
        "cleaners"
    ],
    "wof:name":"Abc Dry Cleaners",
    "wof:placetype":"venue"
},
  "geometry": {"coordinates":[-123.101608,49.240276],"type":"Point"}
}