{
  "type": "Feature",
  "properties": {
    "addr:full":"83 Water St Pictou NS B0K 1H0",
    "addr:housenumber":"83",
    "addr:postcode":"b0k 1h0",
    "addr:street":"Water St",
    "iso:country":"CA",
    "sg:address":"83 Water St",
    "sg:city":"Pictou",
    "sg:classifiers":[
        {
            "category":"Organizations",
            "subcategory":"Non-profit Organization",
            "type":"Services"
        }
    ],
    "sg:phone":"+1 902 485 4491",
    "sg:postcode":"B0K 1H0",
    "sg:province":"NS",
    "sg:tags":[
        "charitable",
        "institution"
    ],
    "wof:name":"Eastern Star Lodge",
    "wof:placetype":"venue"
},
  "geometry": {"coordinates":[-62.711399,45.676189],"type":"Point"}
}