{
  "type": "Feature",
  "properties": {
    "iso:country":"CA",
    "sg:city":"Edmonton",
    "sg:classifiers":[
        {
            "category":"Professional",
            "subcategory":"Engineering",
            "type":"Services"
        }
    ],
    "sg:phone":"+1 780 450 6436",
    "sg:postcode":"T6E 5E8",
    "sg:province":"AB",
    "sg:tags":[
        "engineer"
    ],
    "wof:name":"Bouthillier, Ed PE",
    "wof:placetype":"venue"
},
  "geometry": {"coordinates":[-113.45790863000001,53.4882774353],"type":"Point"}
}