{
  "type": "Feature",
  "properties": {
    "iso:country":"CA",
    "sg:address":"3791 No. 3 Rd",
    "sg:city":"Richmond",
    "sg:classifiers":[
        {
            "category":"Retail",
            "subcategory":"Auto Rental",
            "type":"Services"
        }
    ],
    "sg:phone":"+1 604 276 1840",
    "sg:postcode":"V6X 2B8",
    "sg:province":"BC",
    "sg:tags":[
        "renting",
        "automobile"
    ],
    "wof:name":"Thrifty Car Rental",
    "wof:placetype":"venue"
},
  "geometry": {"coordinates":[-123.135529,49.186108],"type":"Point"}
}