{
  "type": "Feature",
  "properties": {
    "iso:country":"CA",
    "sg:address":"87 Irondale Dr",
    "sg:city":"North York",
    "sg:classifiers":[
        {
            "category":"Professional",
            "subcategory":"Engineering",
            "type":"Services"
        }
    ],
    "sg:phone":"+1 416 745 0833",
    "sg:postcode":"M9L 2S6",
    "sg:province":"ON",
    "sg:tags":[
        "engineer"
    ],
    "wof:name":"Condeland Engineering",
    "wof:placetype":"venue"
},
  "geometry": {"coordinates":[-79.54921,43.769157],"type":"Point"}
}