{
  "type": "Feature",
  "properties": {
    "addr:full":"537 2nd Ave Prince George BC V2L 2Z8",
    "addr:housenumber":"537",
    "addr:postcode":"v2l 2z8",
    "addr:street":"2Nd Ave",
    "iso:country":"CA",
    "sg:address":"537 2nd Ave",
    "sg:city":"Prince George",
    "sg:classifiers":[
        {
            "category":"Wholesale",
            "subcategory":"Non-durable Goods",
            "type":"Manufacturing & Wholesale Goods"
        }
    ],
    "sg:phone":"+1 250 561 1530",
    "sg:postcode":"V2L 2Z8",
    "sg:province":"BC",
    "sg:tags":[
        "t"
    ],
    "wof:name":"Custom Stitch",
    "wof:placetype":"venue"
},
  "geometry": {"coordinates":[-122.73339843799999,53.9142494202],"type":"Point"}
}