{
  "type": "Feature",
  "properties": {
    "addr:full":"1401 Ontario St Burlington ON L7S 1G3",
    "addr:housenumber":"1401",
    "addr:postcode":"l7s 1g3",
    "addr:street":"Ontario St",
    "iso:country":"CA",
    "sg:address":"1401 Ontario St",
    "sg:city":"Burlington",
    "sg:classifiers":[
        {
            "category":"Social Services",
            "type":"Services"
        }
    ],
    "sg:phone":"+1 905 681 2682",
    "sg:postcode":"L7S 1G3",
    "sg:province":"ON",
    "sg:tags":[
        "organization",
        "welfare"
    ],
    "wof:name":"Carey House",
    "wof:placetype":"venue"
},
  "geometry": {"coordinates":[-79.801468,43.324348],"type":"Point"}
}