{
  "type": "Feature",
  "properties": {
    "addr:full":"3198 Logan Farm Dr Osgoode ON K0A 2W0",
    "addr:housenumber":"3198",
    "addr:postcode":"k0a 2w0",
    "addr:street":"Logan Farm Dr",
    "iso:country":"CA",
    "sg:address":"3198 Logan Farm Dr",
    "sg:city":"Osgoode",
    "sg:classifiers":[
        {
            "category":"Health Services",
            "subcategory":"Health Practitioner",
            "type":"Services"
        }
    ],
    "sg:phone":"+1 613 826 1662",
    "sg:postcode":"K0A 2W0",
    "sg:province":"ON",
    "sg:tags":[
        "physiotherapist"
    ],
    "wof:name":"Cooper Physiotherapy Clinic",
    "wof:placetype":"venue"
},
  "geometry": {"coordinates":[-75.60237121580001,45.1483650208],"type":"Point"}
}