{
  "type": "Feature",
  "properties": {
    "addr:full":"North York ON M3J 2Z1",
    "addr:postcode":"m3j 2z1",
    "iso:country":"CA",
    "sg:city":"North York",
    "sg:classifiers":[
        {
            "category":"Restaurant",
            "type":"Food & Drink"
        }
    ],
    "sg:phone":"+1 416 665 1052",
    "sg:postcode":"M3J 2Z1",
    "sg:province":"ON",
    "wof:name":"A Bis Gourmet",
    "wof:placetype":"venue"
},
  "geometry": {"coordinates":[-79.48421500000001,43.760975],"type":"Point"}
}