{
  "type": "Feature",
  "properties": {
    "addr:full":"323 Nelson Ave Nelson BC V1L 2M7",
    "addr:housenumber":"323",
    "addr:postcode":"bc v1l 2m7",
    "addr:street":"Nelson Ave",
    "iso:country":"CA",
    "sg:address":"323 Nelson Ave",
    "sg:city":"Nelson",
    "sg:classifiers":[
        {
            "category":"Retail",
            "subcategory":"Self-service Laundry",
            "type":"Services"
        }
    ],
    "sg:phone":"+1 250 352 1233",
    "sg:postcode":"V1L 2M7",
    "sg:province":"BC",
    "wof:name":"Daily Grind",
    "wof:placetype":"venue"
},
  "geometry": {"coordinates":[-117.279640198,49.5002861023],"type":"Point"}
}