{
  "type": "Feature",
  "properties": {
    "addr:full":"3015 New St Burlington ON L7R 1K3",
    "addr:housenumber":"3015",
    "addr:postcode":"l7r 1k3",
    "addr:street":"New St",
    "iso:country":"CA",
    "sg:address":"3015 New St",
    "sg:city":"Burlington",
    "sg:classifiers":[
        {
            "category":"Food & Beverages",
            "subcategory":"Groceries & Convenience Stores",
            "type":"Retail Goods"
        }
    ],
    "sg:phone":"+1 905 633 8034",
    "sg:postcode":"L7R 1K3",
    "sg:province":"ON",
    "sg:tags":[
        "grocer"
    ],
    "wof:name":"Hasty Market",
    "wof:placetype":"venue"
},
  "geometry": {"coordinates":[-79.7847747803,43.3390083313],"type":"Point"}
}