{
  "type": "Feature",
  "properties": {
    "addr:full":"Saint-Jacques QC J0K 2R0",
    "addr:postcode":"j0k 2r0",
    "iso:country":"CA",
    "sg:city":"Saint-Jacques",
    "sg:classifiers":[
        {
            "category":"Real Estate",
            "subcategory":"Real Estate Agent",
            "type":"Services"
        }
    ],
    "sg:phone":"+1 450 839 3642",
    "sg:postcode":"J0K 2R0",
    "sg:province":"QC",
    "sg:tags":[
        "hardware",
        "cooperative"
    ],
    "wof:name":"Cooperative Agricole Profid'Or",
    "wof:placetype":"venue"
},
  "geometry": {"coordinates":[-73.578766,45.941944],"type":"Point"}
}