{
  "type": "Feature",
  "properties": {
    "iso:country":"CA",
    "sg:address":"1 Oland Cres",
    "sg:city":"Halifax",
    "sg:classifiers":[
        {
            "category":"Retail",
            "subcategory":"Repair Shop",
            "type":"Services"
        }
    ],
    "sg:phone":"+1 902 450 5175",
    "sg:postcode":"B3S 1C6",
    "sg:province":"NS",
    "sg:tags":[
        "lock",
        "locksmith"
    ],
    "wof:name":"Accurate Security Svc",
    "wof:placetype":"venue"
},
  "geometry": {"coordinates":[-63.675018,44.647774],"type":"Point"}
}