{
  "type": "Feature",
  "properties": {
    "addr:full":"570 Boul Des Laurentides Laval QC H7G 2V5",
    "addr:housenumber":"570",
    "addr:postcode":"qc h7g 2v5",
    "addr:street":"Boul Des Laurentides",
    "iso:country":"CA",
    "sg:address":"570 Boul Des Laurentides",
    "sg:city":"Laval",
    "sg:classifiers":[
        {
            "category":"Shopping",
            "subcategory":"Bicycles & Sporting Goods",
            "type":"Retail Goods"
        }
    ],
    "sg:phone":"+1 450 663 8640",
    "sg:postcode":"H7G 2V5",
    "sg:province":"QC",
    "wof:name":"Giguere Sports Quincaillerie",
    "wof:placetype":"venue"
},
  "geometry": {"coordinates":[-73.6938858032,45.5720024109],"type":"Point"}
}