{
  "type": "Feature",
  "properties": {
    "addr:full":"95 Akerley Blvd Dartmouth NS B3B 1R7",
    "addr:housenumber":"95",
    "addr:postcode":"b3b 1r7",
    "addr:street":"Akerley Blvd",
    "iso:country":"CA",
    "sg:address":"95 Akerley Blvd",
    "sg:city":"Dartmouth",
    "sg:classifiers":[
        {
            "category":"Manufacturing",
            "subcategory":"Pottery",
            "type":"Manufacturing & Wholesale Goods"
        }
    ],
    "sg:phone":"+1 902 468 4100",
    "sg:postcode":"B3B 1R7",
    "sg:province":"NS",
    "wof:name":"Atlantic Stained Glass Studio",
    "wof:placetype":"venue"
},
  "geometry": {"coordinates":[-63.5945510864,44.7136039734],"type":"Point"}
}