{
  "type": "Feature",
  "properties": {
    "addr:full":"861 Rue Saint-Arsene Rimouski QC G5L 3X6",
    "addr:housenumber":"861",
    "addr:postcode":"g5l 3x6",
    "addr:street":"Rue Saint-Arsene",
    "iso:country":"CA",
    "sg:address":"861 Rue Saint-Arsene",
    "sg:city":"Rimouski",
    "sg:classifiers":[
        {
            "category":"Personal",
            "subcategory":"Beauty Salon",
            "type":"Services"
        }
    ],
    "sg:phone":"+1 418 722 8578",
    "sg:postcode":"G5L 3X6",
    "sg:province":"QC",
    "wof:name":"Salon Carole Coiffure",
    "wof:placetype":"venue"
},
  "geometry": {"coordinates":[-68.590332,48.426235],"type":"Point"}
}