{
  "type": "Feature",
  "properties": {
    "addr:full":"5 John St W Oshawa ON L1H 1W8",
    "addr:housenumber":"5",
    "addr:postcode":"l1h 1w8",
    "addr:street":"John St W",
    "iso:country":"CA",
    "sg:address":"5 John St W",
    "sg:city":"Oshawa",
    "sg:classifiers":[
        {
            "category":"Personal",
            "subcategory":"Beauty Salon",
            "type":"Services"
        }
    ],
    "sg:phone":"+1 905 725 0662",
    "sg:postcode":"L1H 1W8",
    "sg:province":"ON",
    "wof:name":"Nick Hair Salon",
    "wof:placetype":"venue"
},
  "geometry": {"coordinates":[-78.86232800000001,43.893936],"type":"Point"}
}