{
  "type": "Feature",
  "properties": {
    "addr:full":"144 Bennett Dr Gander NL A1V 2E4",
    "addr:housenumber":"144",
    "addr:postcode":"a1v 2e4",
    "addr:street":"Bennett Dr",
    "iso:country":"CA",
    "sg:address":"144 Bennett Dr",
    "sg:city":"Gander",
    "sg:classifiers":[
        {
            "category":"Personal",
            "subcategory":"Beauty Salon",
            "type":"Services"
        }
    ],
    "sg:phone":"+1 709 256 4448",
    "sg:postcode":"A1V 2E4",
    "sg:province":"NL",
    "wof:name":"A Cut Above",
    "wof:placetype":"venue"
},
  "geometry": {"coordinates":[-54.604748,48.952496],"type":"Point"}
}