{
  "type": "Feature",
  "properties": {
    "addr:full":"12705 82 St NW Edmonton AB T5E 2S9",
    "addr:housenumber":"12705",
    "addr:postcode":"t5e 2s9",
    "addr:street":"82 St Nw",
    "iso:country":"CA",
    "sg:address":"12705 82 St NW",
    "sg:city":"Edmonton",
    "sg:classifiers":[
        {
            "category":"Autos & Motor Vehicles",
            "subcategory":"Fuel & Gas Station",
            "type":"Retail Goods"
        }
    ],
    "sg:phone":"+1 780 476 1442",
    "sg:postcode":"T5E 2S9",
    "sg:province":"AB",
    "sg:tags":[
        "oil"
    ],
    "wof:name":"Delton CO-OP Gas Bar",
    "wof:placetype":"venue"
},
  "geometry": {"coordinates":[-113.46704864500001,53.5852546692],"type":"Point"}
}