{
  "type": "Feature",
  "properties": {
    "addr:full":"702 1E Av Beauceville QC G5X 1L8",
    "addr:housenumber":"702",
    "addr:postcode":"g5x 1l8",
    "addr:street":"1E Av",
    "iso:country":"CA",
    "sg:address":"702 1E Av",
    "sg:city":"Beauceville",
    "sg:classifiers":[
        {
            "category":"Health Services",
            "subcategory":"Nursing And Care Facility",
            "type":"Services"
        }
    ],
    "sg:phone":"+1 418 774 3857",
    "sg:postcode":"G5X 1L8",
    "sg:province":"QC",
    "sg:tags":[
        "home",
        "retirement",
        "community"
    ],
    "wof:name":"Residence Renault Enr",
    "wof:placetype":"venue"
},
  "geometry": {"coordinates":[-70.774597,46.211102],"type":"Point"}
}