{
  "type": "Feature",
  "properties": {
    "addr:full":"6342 Route 8 Boiestown NB E6A 1Z5",
    "addr:housenumber":"6342",
    "addr:postcode":"e6a 1z5",
    "addr:street":"Route 8",
    "iso:country":"CA",
    "sg:address":"6342 Route 8",
    "sg:city":"Boiestown",
    "sg:classifiers":[
        {
            "category":"Museum",
            "type":"Entertainment"
        }
    ],
    "sg:phone":"+1 506 369 7214",
    "sg:postcode":"E6A 1Z5",
    "sg:province":"NB",
    "wof:name":"Central NB Woodmen's Inc",
    "wof:placetype":"venue"
},
  "geometry": {"coordinates":[-66.41635100000001,46.456909],"type":"Point"}
}