{
  "type": "Feature",
  "properties": {
    "addr:full":"Eganville ON K0J 1T0",
    "addr:postcode":"k0j 1t0",
    "iso:country":"CA",
    "sg:city":"Eganville",
    "sg:classifiers":[
        {
            "category":"Organizations",
            "subcategory":"Religious Organization",
            "type":"Services"
        }
    ],
    "sg:phone":"+1 613 754 2011",
    "sg:postcode":"K0J 1T0",
    "sg:province":"ON",
    "sg:tags":[
        "church"
    ],
    "wof:name":"Lyndock Baptist Church",
    "wof:placetype":"venue"
},
  "geometry": {"coordinates":[-77.1009063721,45.5400772095],"type":"Point"}
}