{
  "type": "Feature",
  "properties": {
    "iso:country":"CA",
    "sg:address":"1153 Greenwood St",
    "sg:city":"Campbell River",
    "sg:classifiers":[
        {
            "category":"Organizations",
            "subcategory":"Professional Association",
            "type":"Services"
        }
    ],
    "sg:phone":"+1 250 286 0391",
    "sg:postcode":"V9W 3C5",
    "sg:province":"BC",
    "wof:name":"Campbell River & District Assn",
    "wof:placetype":"venue"
},
  "geometry": {"coordinates":[-125.252059937,50.026348114],"type":"Point"}
}