{
  "type": "Feature",
  "properties": {
    "addr:full":"1153 Greenwood St Campbell River BC V9W 3C5",
    "addr:housenumber":"1153",
    "addr:postcode":"v9w 3c5",
    "addr:street":"Greenwood St",
    "iso:country":"CA",
    "sg:address":"1153 Greenwood St",
    "sg:city":"Campbell River",
    "sg:classifiers":[
        {
            "category":"Organizations",
            "subcategory":"Professional Association",
            "type":"Services"
        }
    ],
    "sg:phone":"+1 250 286 0391",
    "sg:postcode":"V9W 3C5",
    "sg:province":"BC",
    "wof:name":"Campbell River & District Assn",
    "wof:placetype":"venue"
},
  "geometry": {"coordinates":[-125.252059937,50.026348114],"type":"Point"}
}