{
  "type": "Feature",
  "properties": {
    "addr:full":"8750 Rue Hochelaga Montreal QC H1L 2M7",
    "addr:housenumber":"8750",
    "addr:postcode":"h1l 2m7",
    "addr:street":"Rue Hochelaga",
    "iso:country":"CA",
    "sg:address":"8750 Rue Hochelaga",
    "sg:city":"Montreal",
    "sg:classifiers":[
        {
            "category":"Shopping",
            "subcategory":"Department Store",
            "type":"Retail Goods"
        }
    ],
    "sg:phone":"+1 514 351 3725",
    "sg:postcode":"H1L 2M7",
    "sg:province":"QC",
    "wof:name":"Mini-Prix Ltee",
    "wof:placetype":"venue"
},
  "geometry": {"coordinates":[-73.51937103269999,45.6019172668],"type":"Point"}
}