{
  "type": "Feature",
  "properties": {
    "addr:full":"96 Loyalist Dr Welland ON L3C 2Y1",
    "addr:housenumber":"96",
    "addr:postcode":"l3c 2y1",
    "addr:street":"Loyalist Dr",
    "iso:country":"CA",
    "sg:address":"96 Loyalist Dr",
    "sg:city":"Welland",
    "sg:classifiers":[
        {
            "category":"Real Estate",
            "subcategory":"Real Estate Agent",
            "type":"Services"
        }
    ],
    "sg:phone":"+1 905 732 6292",
    "sg:postcode":"L3C 2Y1",
    "sg:province":"ON",
    "wof:name":"Percy Sharpe Realty Ltd",
    "wof:placetype":"venue"
},
  "geometry": {"coordinates":[-79.275284,42.999577],"type":"Point"}
}