{
  "type": "Feature",
  "properties": {
    "addr:full":"314 Ch Cote-Sainte-Catherine Outremont QC H2V 2B4",
    "addr:housenumber":"314",
    "addr:postcode":"h2v 2b4",
    "addr:street":"Ch Cote-Sainte-Catherine",
    "iso:country":"CA",
    "sg:address":"314 Ch Cote-Sainte-Catherine",
    "sg:city":"Outremont",
    "sg:classifiers":[
        {
            "category":"Organizations",
            "subcategory":"Religious Organization",
            "type":"Services"
        }
    ],
    "sg:phone":"+1 514 495 1551",
    "sg:postcode":"H2V 2B4",
    "sg:province":"QC",
    "wof:name":"Soeurs Missionaires Immcl Ccpt",
    "wof:placetype":"venue"
},
  "geometry": {"coordinates":[-73.6013336182,45.5157241821],"type":"Point"}
}