{
  "type": "Feature",
  "properties": {
    "iso:country":"CA",
    "sg:address":"2796 Constable Rd",
    "sg:city":"Mississauga",
    "sg:classifiers":[
        {
            "category":"Social Services",
            "subcategory":"Child Care",
            "type":"Services"
        }
    ],
    "sg:phone":"+1 905 855 5273",
    "sg:postcode":"L5J 1W4",
    "sg:province":"ON",
    "wof:name":"Kiddie Kare Day Care Svc",
    "wof:placetype":"venue"
},
  "geometry": {"coordinates":[-79.6522521973,43.5041656494],"type":"Point"}
}