{
  "type": "Feature",
  "properties": {
    "addr:full":"707 Folsom St Coquitlam BC V3J 7H4",
    "addr:housenumber":"707",
    "addr:postcode":"v3j 7h4",
    "addr:street":"Folsom St",
    "iso:country":"CA",
    "sg:address":"707 Folsom St",
    "sg:city":"Coquitlam",
    "sg:classifiers":[
        {
            "category":"Wholesale",
            "subcategory":"Groceries",
            "type":"Manufacturing & Wholesale Goods"
        }
    ],
    "sg:phone":"+1 604 939 4433",
    "sg:postcode":"V3J 7H4",
    "sg:province":"BC",
    "sg:tags":[
        "food",
        "broker"
    ],
    "wof:name":"Robin Marketing Corp",
    "wof:placetype":"venue"
},
  "geometry": {"coordinates":[-122.864562988,49.2598762512],"type":"Point"}
}