{
  "type": "Feature",
  "properties": {
    "iso:country":"CA",
    "sg:city":"Asbestos",
    "sg:classifiers":[
        {
            "category":"Manufacturing",
            "subcategory":"Furniture",
            "type":"Manufacturing & Wholesale Goods"
        }
    ],
    "sg:phone":"+1 819 879 5044",
    "sg:postcode":"J1T 3P6",
    "sg:province":"QC",
    "sg:tags":[
        "stationer"
    ],
    "wof:name":"Megaburo Inc",
    "wof:placetype":"venue"
},
  "geometry": {"coordinates":[-71.9008102417,45.7986717224],"type":"Point"}
}