{
  "type": "Feature",
  "properties": {
    "iso:country":"CA",
    "sg:address":"1595 Av Sainte-Croix",
    "sg:city":"Saint-Laurent",
    "sg:classifiers":[
        {
            "category":"Real Estate",
            "subcategory":"Real Estate Agent",
            "type":"Services"
        }
    ],
    "sg:phone":"+1 514 747 6148",
    "sg:postcode":"H4L 3Z5",
    "sg:province":"QC",
    "sg:tags":[
        "management"
    ],
    "wof:name":"Gestion Db Laurentides Inc",
    "wof:placetype":"venue"
},
  "geometry": {"coordinates":[-73.6876068115,45.5212745667],"type":"Point"}
}