{
  "type": "Feature",
  "properties": {
    "addr:full":"688 Richmond St W Toronto ON M6J 1C5",
    "addr:housenumber":"688",
    "addr:postcode":"m6j 1c5",
    "addr:street":"Richmond St W",
    "iso:country":"CA",
    "sg:address":"688 Richmond St W",
    "sg:city":"Toronto",
    "sg:classifiers":[
        {
            "category":"Professional",
            "subcategory":"Computer Services",
            "type":"Services"
        }
    ],
    "sg:phone":"+1 416 599 7669",
    "sg:postcode":"M6J 1C5",
    "sg:province":"ON",
    "sg:tags":[
        "website",
        "design",
        "internet"
    ],
    "wof:name":"One Trick Pony",
    "wof:placetype":"venue"
},
  "geometry": {"coordinates":[-79.4066619873,43.6459960938],"type":"Point"}
}