{
  "type": "Feature",
  "properties": {
    "addr:full":"5716 198 St Langley BC V3A 7C7",
    "addr:housenumber":"5716",
    "addr:postcode":"v3a 7c7",
    "addr:street":"198 St",
    "iso:country":"CA",
    "sg:address":"5716 198 St",
    "sg:city":"Langley",
    "sg:classifiers":[
        {
            "category":"Retail",
            "subcategory":"Auto Repair",
            "type":"Services"
        }
    ],
    "sg:phone":"+1 604 534 7611",
    "sg:postcode":"V3A 7C7",
    "sg:province":"BC",
    "sg:tags":[
        "repairing",
        "automobile",
        "wheel",
        "alignment"
    ],
    "wof:name":"B & G Alignment Ltd",
    "wof:placetype":"venue"
},
  "geometry": {"coordinates":[-122.67314910899999,49.106628418],"type":"Point"}
}