{
  "type": "Feature",
  "properties": {
    "addr:full":"172 Holdway St Mcbride BC V0J 2E0",
    "addr:housenumber":"172",
    "addr:postcode":"v0j 2e0",
    "addr:street":"Holdway St",
    "iso:country":"CA",
    "sg:address":"172 Holdway St",
    "sg:city":"Mcbride",
    "sg:classifiers":[
        {
            "category":"Organizations",
            "subcategory":"Community Association",
            "type":"Services"
        }
    ],
    "sg:phone":"+1 250 569 2205",
    "sg:postcode":"V0J 2E0",
    "sg:province":"BC",
    "sg:tags":[
        "fraternal"
    ],
    "wof:name":"Elks Club",
    "wof:placetype":"venue"
},
  "geometry": {"coordinates":[-120.168670654,53.3004798889],"type":"Point"}
}