{
  "type": "Feature",
  "properties": {
    "addr:full":"Mississauga ON L5S 1A6",
    "addr:postcode":"l5s 1a6",
    "iso:country":"CA",
    "sg:city":"Mississauga",
    "sg:classifiers":[
        {
            "category":"Freight",
            "type":"Transportation"
        }
    ],
    "sg:phone":"+1 905 612 8996",
    "sg:postcode":"L5S 1A6",
    "sg:province":"ON",
    "sg:tags":[
        "trucking"
    ],
    "wof:name":"D S Intl Transport",
    "wof:placetype":"venue"
},
  "geometry": {"coordinates":[-79.6634902954,43.6955490112],"type":"Point"}
}