{
  "type": "Feature",
  "properties": {
    "addr:full":"220 Royal Crest Crt Markham ON L3R 9Y2",
    "addr:housenumber":"220",
    "addr:postcode":"l3r 9y2",
    "addr:street":"Royal Crest Crt",
    "iso:country":"CA",
    "sg:address":"220 Royal Crest Crt",
    "sg:city":"Markham",
    "sg:classifiers":[
        {
            "category":"Building & Trades",
            "subcategory":"Plumbing",
            "type":"Services"
        }
    ],
    "sg:phone":"+1 905 513 0345",
    "sg:postcode":"L3R 9Y2",
    "sg:province":"ON",
    "sg:tags":[
        "conditioning",
        "air",
        "system",
        "contractor"
    ],
    "wof:name":"High Life Heating Air Cond",
    "wof:placetype":"venue"
},
  "geometry": {"coordinates":[-79.32353999999999,43.841938],"type":"Point"}
}