{
  "type": "Feature",
  "properties": {
    "iso:country":"CA",
    "sg:address":"2 Goldridge Dr #2D",
    "sg:city":"Kanata",
    "sg:classifiers":[
        {
            "category":"Restaurant",
            "type":"Food & Drink"
        }
    ],
    "sg:phone":"+1 613 271 0608",
    "sg:postcode":"K2T 1C7",
    "sg:province":"ON",
    "sg:tags":[
        "delicatessen"
    ],
    "wof:name":"Little Euro Deli",
    "wof:placetype":"venue"
},
  "geometry": {"coordinates":[-75.9201583862,45.3160705566],"type":"Point"}
}