{
  "type": "Feature",
  "properties": {
    "addr:full":"11141 89 Ave Fort Saskatchewan AB T8L 2S6",
    "addr:housenumber":"11141",
    "addr:postcode":"t8l 2s6",
    "addr:street":"89 Ave",
    "iso:country":"CA",
    "sg:address":"11141 89 Ave",
    "sg:city":"Fort Saskatchewan",
    "sg:classifiers":[
        {
            "category":"Retail",
            "subcategory":"Auto Repair",
            "type":"Services"
        }
    ],
    "sg:phone":"+1 780 992 1298",
    "sg:postcode":"T8L 2S6",
    "sg:province":"AB",
    "sg:tags":[
        "repairing",
        "automobile"
    ],
    "wof:name":"Fort Saskatchewan Auto Svc",
    "wof:placetype":"venue"
},
  "geometry": {"coordinates":[-113.196365356,53.7077941895],"type":"Point"}
}