{
  "type": "Feature",
  "properties": {
    "addr:full":"5 Catherine St Smiths Falls ON K7A 3Z9",
    "addr:housenumber":"5",
    "addr:postcode":"k7a 3z9",
    "addr:street":"Catherine St",
    "iso:country":"CA",
    "sg:address":"5 Catherine St",
    "sg:city":"Smiths Falls",
    "sg:classifiers":[
        {
            "category":"Education",
            "subcategory":"School",
            "type":"Public Place"
        }
    ],
    "sg:phone":"+1 613 283 1848",
    "sg:postcode":"K7A 3Z9",
    "sg:province":"ON",
    "wof:name":"St James the Greater School",
    "wof:placetype":"venue"
},
  "geometry": {"coordinates":[-76.01902,44.893246],"type":"Point"}
}