{
  "type": "Feature",
  "properties": {
    "addr:full":"1325 Summit Ave Prince Rupert BC V8J 4C1",
    "addr:housenumber":"1325",
    "addr:postcode":"v8j 4c1",
    "addr:street":"Summit Ave",
    "iso:country":"CA",
    "sg:address":"1325 Summit Ave",
    "sg:city":"Prince Rupert",
    "sg:classifiers":[
        {
            "category":"Government",
            "subcategory":"Office",
            "type":"Public Place"
        }
    ],
    "sg:phone":"+1 250 627 8497",
    "sg:postcode":"V8J 4C1",
    "sg:province":"BC",
    "wof:name":"Acropolis Manor",
    "wof:placetype":"venue"
},
  "geometry": {"coordinates":[-130.33012400000001,54.306999],"type":"Point"}
}