{
  "type": "Feature",
  "properties": {
    "addr:full":"1970 Maddocks Rd Revelstoke BC V0E 2S0",
    "addr:postcode":"1970;v0e 2s0",
    "addr:street":"Maddocks Rd",
    "iso:country":"CA",
    "sg:address":"1970 Maddocks Rd",
    "sg:city":"Revelstoke",
    "sg:classifiers":[
        {
            "category":"Building & Trades",
            "subcategory":"Landscaping Services",
            "type":"Services"
        }
    ],
    "sg:phone":"+1 250 837 3851",
    "sg:postcode":"V0E 2S0",
    "sg:province":"BC",
    "sg:tags":[
        "lawn",
        "contractor",
        "landscape",
        "maintenance",
        "grounds"
    ],
    "wof:name":"Thors Lawn & Yard Maintenance",
    "wof:placetype":"venue"
},
  "geometry": {"coordinates":[-118.22228200000001,51.011425],"type":"Point"}
}