{
  "type": "Feature",
  "properties": {
    "addr:full":"1945 Rue DE Varennes Sherbrooke QC J1J 1P3",
    "addr:housenumber":"1945",
    "addr:postcode":"j1j 1p3",
    "addr:street":"Rue De Varennes",
    "iso:country":"CA",
    "sg:address":"1945 Rue DE Varennes",
    "sg:city":"Sherbrooke",
    "sg:classifiers":[
        {
            "category":"Health Services",
            "subcategory":"Health Practitioner",
            "type":"Services"
        }
    ],
    "sg:phone":"+1 819 829 2008",
    "sg:postcode":"J1J 1P3",
    "sg:province":"QC",
    "sg:tags":[
        "psychologist"
    ],
    "wof:name":"Lambert, Jacinthe",
    "wof:placetype":"venue"
},
  "geometry": {"coordinates":[-71.963058,45.382801],"type":"Point"}
}