{
  "type": "Feature",
  "properties": {
    "iso:country":"CA",
    "sg:address":"3849 Rue Mackay",
    "sg:city":"Saint-Hubert",
    "sg:classifiers":[
        {
            "category":"Building & Trades",
            "subcategory":"Construction",
            "type":"Services"
        }
    ],
    "sg:phone":"+1 450 445 2274",
    "sg:postcode":"J4T 2P6",
    "sg:province":"QC",
    "sg:tags":[
        "roofing",
        "contractor"
    ],
    "wof:name":"Toitures Bondu Inc",
    "wof:placetype":"venue"
},
  "geometry": {"coordinates":[-73.4671783447,45.4899406433],"type":"Point"}
}