{
  "type": "Feature",
  "properties": {
    "addr:full":"3464 Gardner Crt Burnaby BC V5G 3K4",
    "addr:housenumber":"3464",
    "addr:postcode":"v5g 3k4",
    "addr:street":"Gardner Crt",
    "iso:country":"CA",
    "sg:address":"3464 Gardner Crt",
    "sg:city":"Burnaby",
    "sg:classifiers":[
        {
            "category":"Wholesale",
            "subcategory":"Hardware",
            "type":"Manufacturing & Wholesale Goods"
        }
    ],
    "sg:phone":"+1 604 437 8053",
    "sg:postcode":"V5G 3K4",
    "sg:province":"BC",
    "sg:tags":[
        "compressor"
    ],
    "wof:name":"Prime Fasteners of BC Ltd",
    "wof:placetype":"venue"
},
  "geometry": {"coordinates":[-122.996284,49.253002],"type":"Point"}
}