{
  "type": "Feature",
  "properties": {
    "addr:full":"52 Vaughan Rd Toronto ON M6G 2N4",
    "addr:housenumber":"52",
    "addr:postcode":"m6g 2n4",
    "addr:street":"Vaughan Rd",
    "iso:country":"CA",
    "sg:address":"52 Vaughan Rd",
    "sg:city":"Toronto",
    "sg:classifiers":[
        {
            "category":"Organizations",
            "subcategory":"Professional Association",
            "type":"Services"
        }
    ],
    "sg:phone":"+1 416 653 6697",
    "sg:postcode":"M6G 2N4",
    "sg:province":"ON",
    "sg:tags":[
        "consultant",
        "educational"
    ],
    "wof:name":"Disabled Workers Reps",
    "wof:placetype":"venue"
},
  "geometry": {"coordinates":[-79.41962432859999,43.6823196411],"type":"Point"}
}