{
  "type": "Feature",
  "properties": {
    "iso:country":"CA",
    "sg:address":"467 Kitley Line 3",
    "sg:city":"Toledo",
    "sg:classifiers":[
        {
            "category":"Retail",
            "subcategory":"Animal Services",
            "type":"Services"
        }
    ],
    "sg:phone":"+1 613 275 1292",
    "sg:postcode":"K0E 1Y0",
    "sg:province":"ON",
    "sg:tags":[
        "pet",
        "grooming",
        "washing"
    ],
    "wof:name":"Susie's Kanine Klips",
    "wof:placetype":"venue"
},
  "geometry": {"coordinates":[-76.0012893677,44.746295929],"type":"Point"}
}