{
  "type": "Feature",
  "properties": {
    "iso:country":"CA",
    "sg:address":"1034 Av Cartier",
    "sg:city":"Quebec",
    "sg:classifiers":[
        {
            "category":"Restaurant",
            "type":"Food & Drink"
        }
    ],
    "sg:phone":"+1 418 648 8821",
    "sg:postcode":"G1R 2S4",
    "sg:province":"QC",
    "wof:name":"Sushi Bar Kimono",
    "wof:placetype":"venue"
},
  "geometry": {"coordinates":[-71.22626495359999,46.8037986755],"type":"Point"}
}