{
  "type": "Feature",
  "properties": {
    "addr:full":"Woodstock NB E7M 2C3",
    "addr:postcode":"e7m 2c3",
    "iso:country":"CA",
    "sg:city":"Woodstock",
    "sg:classifiers":[
        {
            "category":"Restaurant",
            "type":"Food & Drink"
        }
    ],
    "sg:phone":"+1 506 325 2337",
    "sg:postcode":"E7M 2C3",
    "sg:province":"NB",
    "sg:tags":[
        "pub"
    ],
    "wof:name":"Riverside Pub",
    "wof:placetype":"venue"
},
  "geometry": {"coordinates":[-67.5747451782,46.1481170654],"type":"Point"}
}