{
  "type": "Feature",
  "properties": {
    "addr:full":"Riviere-Saint-Jean QC G0G 2N0",
    "addr:postcode":"g0g 2n0",
    "iso:country":"CA",
    "sg:city":"Riviere-Saint-Jean",
    "sg:classifiers":[
        {
            "category":"Communications",
            "subcategory":"Television Station",
            "type":"Services"
        }
    ],
    "sg:phone":"+1 418 949 2340",
    "sg:postcode":"G0G 2N0",
    "sg:province":"QC",
    "sg:tags":[
        "broadcasting",
        "co"
    ],
    "wof:name":"Television Communautaire",
    "wof:placetype":"venue"
},
  "geometry": {"coordinates":[-64.326988,50.292667],"type":"Point"}
}