{
  "type": "Feature",
  "properties": {
    "addr:full":"Con Bay Hwy Bay Roberts NL A0A 1G0",
    "addr:postcode":"a0a 1g0",
    "addr:street":"Hwy Bay",
    "iso:country":"CA",
    "sg:address":"Con Bay Hwy",
    "sg:city":"Bay Roberts",
    "sg:classifiers":[
        {
            "category":"Recreation",
            "type":"Entertainment"
        }
    ],
    "sg:phone":"+1 709 786 3638",
    "sg:postcode":"A0A 1G0",
    "sg:province":"NL",
    "sg:tags":[
        "skating",
        "rink"
    ],
    "wof:name":"Bay Arena Assn Ltd",
    "wof:placetype":"venue"
},
  "geometry": {"coordinates":[-53.281509,47.583984],"type":"Point"}
}