{
  "type": "Feature",
  "properties": {
    "addr:full":"Lloydminster AB T9V 0B6",
    "addr:postcode":"t9v 0b6",
    "iso:country":"CA",
    "sg:city":"Lloydminster",
    "sg:classifiers":[
        {
            "category":"Education",
            "subcategory":"Dance Studio",
            "type":"Public Place"
        }
    ],
    "sg:phone":"+1 780 875 1404",
    "sg:postcode":"T9V 0B6",
    "sg:province":"AB",
    "sg:tags":[
        "instruction",
        "dancing"
    ],
    "wof:name":"Alison Lamont School of Dance",
    "wof:placetype":"venue"
},
  "geometry": {"coordinates":[-110.02554321300001,53.2781448364],"type":"Point"}
}