{
  "type": "Feature",
  "properties": {
    "addr:full":"70 Sherbrook St Winnipeg MB R3C 2B3",
    "addr:housenumber":"70",
    "addr:postcode":"r3c 2b3",
    "addr:street":"Sherbrook St",
    "iso:country":"CA",
    "sg:address":"70 Sherbrook St",
    "sg:city":"Winnipeg",
    "sg:classifiers":[
        {
            "category":"Retail",
            "subcategory":"Repair Shop",
            "type":"Services"
        }
    ],
    "sg:phone":"+1 204 783 4649",
    "sg:postcode":"R3C 2B3",
    "sg:province":"MB",
    "sg:tags":[
        "equipment",
        "photographic"
    ],
    "wof:name":"Precision Camera Repair",
    "wof:placetype":"venue"
},
  "geometry": {"coordinates":[-97.159828186,49.8807678223],"type":"Point"}
}