{
  "type": "Feature",
  "properties": {
    "addr:full":"155 Cushman Rd St Catharines ON L2M 6T4",
    "addr:housenumber":"155",
    "addr:postcode":"l2m 6t4",
    "addr:street":"Cushman Rd",
    "iso:country":"CA",
    "sg:address":"155 Cushman Rd",
    "sg:city":"St Catharines",
    "sg:classifiers":[
        {
            "category":"Building & Trades",
            "subcategory":"Electrical",
            "type":"Services"
        }
    ],
    "sg:phone":"+1 905 685 9293",
    "sg:postcode":"L2M 6T4",
    "sg:province":"ON",
    "sg:tags":[
        "electric",
        "contractor"
    ],
    "wof:name":"Canal Marine",
    "wof:placetype":"venue"
},
  "geometry": {"coordinates":[-79.20001999999999,43.177887],"type":"Point"}
}