{
  "type": "Feature",
  "properties": {
    "addr:full":"207 Main St E Grimsby ON L3M 1P5",
    "addr:housenumber":"207",
    "addr:postcode":"l3m 1p5",
    "addr:street":"Main St E",
    "iso:country":"CA",
    "sg:address":"207 Main St E",
    "sg:city":"Grimsby",
    "sg:classifiers":[
        {
            "category":"Arts & Performance",
            "subcategory":"Theater",
            "type":"Entertainment"
        }
    ],
    "sg:phone":"+1 905 309 6358",
    "sg:postcode":"L3M 1P5",
    "sg:province":"ON",
    "wof:name":"Peninsula Players Community",
    "wof:placetype":"venue"
},
  "geometry": {"coordinates":[-79.5363998413,43.1862869263],"type":"Point"}
}