{
  "type": "Feature",
  "properties": {
    "addr:full":"1475 Rue Janelle Drummondville QC J2C 5S5",
    "addr:housenumber":"1475",
    "addr:postcode":"j2c 5s5",
    "addr:street":"Rue Janelle",
    "iso:country":"CA",
    "sg:address":"1475 Rue Janelle",
    "sg:city":"Drummondville",
    "sg:classifiers":[
        {
            "category":"Home & Garden",
            "subcategory":"Building Materials",
            "type":"Retail Goods"
        }
    ],
    "sg:phone":"+1 819 477 0054",
    "sg:postcode":"J2C 5S5",
    "sg:province":"QC",
    "sg:tags":[
        "glass",
        "window",
        "plate"
    ],
    "wof:name":"Vitrerie Smith Inc",
    "wof:placetype":"venue"
},
  "geometry": {"coordinates":[-72.52061500000001,45.884869],"type":"Point"}
}