{
  "type": "Feature",
  "properties": {
    "iso:country":"CA",
    "sg:address":"3055 Highland Blvd",
    "sg:city":"North Vancouver",
    "sg:classifiers":[
        {
            "category":"Restaurant",
            "type":"Food & Drink"
        }
    ],
    "sg:phone":"+1 604 990 9162",
    "sg:postcode":"V7R 2X4",
    "sg:province":"BC",
    "sg:tags":[
        "delicatessen"
    ],
    "wof:name":"LA Galleria Delicatessen",
    "wof:placetype":"venue"
},
  "geometry": {"coordinates":[-123.102424622,49.3373641968],"type":"Point"}
}