{
  "type": "Feature",
  "properties": {
    "addr:full":"4642 Rue Forest Montreal-Nord QC H1H 2P3",
    "addr:housenumber":"4642",
    "addr:postcode":"h1h 2p3",
    "addr:street":"Rue Forest",
    "iso:country":"CA",
    "sg:address":"4642 Rue Forest",
    "sg:city":"Montreal-Nord",
    "sg:classifiers":[
        {
            "category":"Social Services",
            "type":"Services"
        }
    ],
    "sg:phone":"+1 514 328 1114",
    "sg:postcode":"H1H 2P3",
    "sg:province":"QC",
    "sg:tags":[
        "organization",
        "welfare"
    ],
    "wof:name":"Centre D'Action Benevole",
    "wof:placetype":"venue"
},
  "geometry": {"coordinates":[-73.62779999999999,45.590508],"type":"Point"}
}