{
  "type": "Feature",
  "properties": {
    "addr:full":"285 Coldwater Rd W Orillia ON L3V 3M1",
    "addr:housenumber":"285",
    "addr:postcode":"l3v 3m1",
    "addr:street":"Coldwater Rd W",
    "iso:country":"CA",
    "sg:address":"285 Coldwater Rd W",
    "sg:city":"Orillia",
    "sg:classifiers":[
        {
            "category":"Banks & Credit Unions",
            "subcategory":"Bank",
            "type":"Services"
        }
    ],
    "sg:phone":"+1 705 325 1378",
    "sg:postcode":"L3V 3M1",
    "sg:province":"ON",
    "wof:name":"Bank of Montreal",
    "wof:placetype":"venue"
},
  "geometry": {"coordinates":[-79.4376373291,44.6095504761],"type":"Point"}
}