{
  "type": "Feature",
  "properties": {
    "addr:full":"335 Maxwell Cres Regina SK S4N 5X9",
    "addr:housenumber":"335",
    "addr:postcode":"s4n 5x9",
    "addr:street":"Maxwell Cres",
    "iso:country":"CA",
    "sg:address":"335 Maxwell Cres",
    "sg:city":"Regina",
    "sg:classifiers":[
        {
            "category":"Professional",
            "subcategory":"Research",
            "type":"Services"
        }
    ],
    "sg:phone":"+1 306 721 0646",
    "sg:postcode":"S4N 5X9",
    "sg:province":"SK",
    "sg:tags":[
        "market",
        "analysis"
    ],
    "wof:name":"Arcas Group Inc",
    "wof:placetype":"venue"
},
  "geometry": {"coordinates":[-104.569191,50.473446],"type":"Point"}
}