{
  "type": "Feature",
  "properties": {
    "addr:full":"85 202 Rte Lacolle QC J0J 1J0",
    "addr:housenumber":"202",
    "addr:postcode":"j0j 1j0",
    "addr:street":"85;Rte Lacolle",
    "iso:country":"CA",
    "sg:address":"85 202 Rte",
    "sg:city":"Lacolle",
    "sg:classifiers":[
        {
            "category":"Building & Trades",
            "subcategory":"Construction",
            "type":"Services"
        }
    ],
    "sg:phone":"+1 450 246 2180",
    "sg:postcode":"J0J 1J0",
    "sg:province":"QC",
    "sg:tags":[
        "excavating",
        "contractor"
    ],
    "wof:name":"G Bielen & Fils Inc",
    "wof:placetype":"venue"
},
  "geometry": {"coordinates":[-73.3729019165,45.0824737549],"type":"Point"}
}