{
  "type": "Feature",
  "properties": {
    "addr:full":"201 Av Authier Amos QC J9T 1W1",
    "addr:housenumber":"201",
    "addr:postcode":"j9t 1w1",
    "addr:street":"Av Authier",
    "iso:country":"CA",
    "sg:address":"201 Av Authier",
    "sg:city":"Amos",
    "sg:classifiers":[
        {
            "category":"Travel",
            "subcategory":"Hotels & Motels",
            "type":"Entertainment"
        }
    ],
    "sg:phone":"+1 819 732 5386",
    "sg:postcode":"J9T 1W1",
    "sg:province":"QC",
    "wof:name":"Hotel Des Eskers",
    "wof:placetype":"venue"
},
  "geometry": {"coordinates":[-78.1204528809,48.5712585449],"type":"Point"}
}