{
  "type": "Feature",
  "properties": {
    "addr:full":"1005 Memorial Ave Thunder Bay ON P7B 4A1",
    "addr:housenumber":"1005",
    "addr:postcode":"p7b 4a1",
    "addr:street":"Memorial Ave",
    "iso:country":"CA",
    "sg:address":"1005 Memorial Ave",
    "sg:city":"Thunder Bay",
    "sg:classifiers":[
        {
            "category":"Retail",
            "subcategory":"Auto Repair",
            "type":"Services"
        }
    ],
    "sg:phone":"+1 807 345 2105",
    "sg:postcode":"P7B 4A1",
    "sg:province":"ON",
    "sg:tags":[
        "transmission"
    ],
    "wof:name":"Mister Transmission",
    "wof:placetype":"venue"
},
  "geometry": {"coordinates":[-89.24533099999999,48.406361],"type":"Point"}
}