{
  "type": "Feature",
  "properties": {
    "addr:full":"1287 Boundary Rd Oshawa ON L1J 6Z7",
    "addr:housenumber":"1287",
    "addr:postcode":"l1j 6z7",
    "addr:street":"Boundary Rd",
    "iso:country":"CA",
    "sg:address":"1287 Boundary Rd",
    "sg:city":"Oshawa",
    "sg:classifiers":[
        {
            "category":"Manufacturing",
            "subcategory":"Metals",
            "type":"Manufacturing & Wholesale Goods"
        }
    ],
    "sg:phone":"+1 905 432 3200",
    "sg:postcode":"L1J 6Z7",
    "sg:province":"ON",
    "sg:tags":[
        "railing"
    ],
    "wof:name":"Escalator Handrail CO",
    "wof:placetype":"venue"
},
  "geometry": {"coordinates":[-78.883934,43.858059],"type":"Point"}
}