{
  "type": "Feature",
  "properties": {
    "addr:full":"400 Burnhamthorpe Rd Etobicoke ON M9B 2A8",
    "addr:housenumber":"400",
    "addr:postcode":"m9b 2a8",
    "addr:street":"Burnhamthorpe Rd",
    "iso:country":"CA",
    "sg:address":"400 Burnhamthorpe Rd",
    "sg:city":"Etobicoke",
    "sg:classifiers":[
        {
            "category":"Organizations",
            "subcategory":"Religious Organization",
            "type":"Services"
        }
    ],
    "sg:phone":"+1 416 622 4113",
    "sg:postcode":"M9B 2A8",
    "sg:province":"ON",
    "sg:tags":[
        "church"
    ],
    "wof:name":"St James United Church",
    "wof:placetype":"venue"
},
  "geometry": {"coordinates":[-79.5570602417,43.6467933655],"type":"Point"}
}