{
  "type": "Feature",
  "properties": {
    "addr:full":"1205 6 St Nisku AB T9E 7P1",
    "addr:housenumber":"1205 6",
    "addr:postcode":"t9e 7p1",
    "addr:street":"St",
    "iso:country":"CA",
    "sg:address":"1205 6 St",
    "sg:city":"Nisku",
    "sg:classifiers":[
        {
            "category":"Manufacturing",
            "subcategory":"Glass & Minerals",
            "type":"Manufacturing & Wholesale Goods"
        }
    ],
    "sg:phone":"+1 780 955 7107",
    "sg:postcode":"T9E 7P1",
    "sg:province":"AB",
    "sg:tags":[
        "concrete",
        "brick",
        "prod",
        "block"
    ],
    "wof:name":"Specialty Precast Western Ltd",
    "wof:placetype":"venue"
},
  "geometry": {"coordinates":[-113.52503967299999,53.3114509583],"type":"Point"}
}