{
  "type": "Feature",
  "properties": {
    "addr:full":"137 Main St Abernethy SK S0A 0A0",
    "addr:housenumber":"137",
    "addr:postcode":"s0a 0a0",
    "addr:street":"Main St",
    "iso:country":"CA",
    "sg:address":"137 Main St",
    "sg:city":"Abernethy",
    "sg:classifiers":[
        {
            "category":"Organizations",
            "subcategory":"Professional Association",
            "type":"Services"
        }
    ],
    "sg:phone":"+1 306 333 2232",
    "sg:postcode":"S0A 0A0",
    "sg:province":"SK",
    "wof:name":"Abernethy Senior Citizen",
    "wof:placetype":"venue"
},
  "geometry": {"coordinates":[-103.423934937,50.7459182739],"type":"Point"}
}