{
  "type": "Feature",
  "properties": {
    "addr:full":"Varennes QC J3X 1P5",
    "addr:postcode":"j3x 1p5",
    "iso:country":"CA",
    "sg:city":"Varennes",
    "sg:classifiers":[
        {
            "category":"Professional",
            "subcategory":"Lawyer & Legal Services",
            "type":"Services"
        }
    ],
    "sg:phone":"+1 450 929 4688",
    "sg:postcode":"J3X 1P5",
    "sg:province":"QC",
    "sg:tags":[
        "attorney"
    ],
    "wof:name":"Desjardins, Ginette",
    "wof:placetype":"venue"
},
  "geometry": {"coordinates":[-73.4324264526,45.6748657227],"type":"Point"}
}