{
  "type": "Feature",
  "properties": {
    "addr:full":"10733 Sixth Line Georgetown ON L7G 4S6",
    "addr:housenumber":"10733",
    "addr:postcode":"l7g 4s6",
    "addr:street":"Sixth Line",
    "iso:country":"CA",
    "sg:address":"10733 Sixth Line",
    "sg:city":"Georgetown",
    "sg:classifiers":[
        {
            "category":"Building & Trades",
            "subcategory":"Construction",
            "type":"Services"
        }
    ],
    "sg:phone":"+1 905 702 9915",
    "sg:postcode":"L7G 4S6",
    "sg:province":"ON",
    "sg:tags":[
        "excavating",
        "contractor"
    ],
    "wof:name":"D & R Contractors",
    "wof:placetype":"venue"
},
  "geometry": {"coordinates":[-79.923546,43.612103],"type":"Point"}
}