{
  "type": "Feature",
  "properties": {
    "iso:country":"CA",
    "sg:city":"Hilton Beach",
    "sg:classifiers":[
        {
            "category":"Retail",
            "subcategory":"Auto Repair",
            "type":"Services"
        }
    ],
    "sg:phone":"+1 705 246 2231",
    "sg:postcode":"P0R 1G0",
    "sg:province":"ON",
    "sg:tags":[
        "repairing",
        "automobile"
    ],
    "wof:name":"Nick's Automotive",
    "wof:placetype":"venue"
},
  "geometry": {"coordinates":[-83.8900604248,46.2578353882],"type":"Point"}
}