{
  "type": "Feature",
  "properties": {
    "iso:country":"CA",
    "sg:address":"2560 Rue Belanger",
    "sg:city":"Montreal",
    "sg:classifiers":[
        {
            "category":"Retail",
            "subcategory":"Auto Repair",
            "type":"Services"
        }
    ],
    "sg:phone":"+1 514 721 4510",
    "sg:postcode":"H1Y 1A4",
    "sg:province":"QC",
    "sg:tags":[
        "repairing",
        "automobile"
    ],
    "wof:name":"P G Mecanique",
    "wof:placetype":"venue"
},
  "geometry": {"coordinates":[-73.5984573364,45.5521888733],"type":"Point"}
}