{
  "type": "Feature",
  "properties": {
    "addr:full":"117 Rundle St Stellarton NS B0K 1S0",
    "addr:housenumber":"117",
    "addr:postcode":"b0k 1s0",
    "addr:street":"Rundle St",
    "iso:country":"CA",
    "sg:address":"117 Rundle St",
    "sg:city":"Stellarton",
    "sg:classifiers":[
        {
            "category":"Manufacturing",
            "subcategory":"Furniture",
            "type":"Manufacturing & Wholesale Goods"
        }
    ],
    "sg:phone":"+1 902 752 4484",
    "sg:postcode":"B0K 1S0",
    "sg:province":"NS",
    "sg:tags":[
        "equipment",
        "supply"
    ],
    "wof:name":"Mack Restaurant & Equipment",
    "wof:placetype":"venue"
},
  "geometry": {"coordinates":[-62.6607589722,45.5617713928],"type":"Point"}
}