{
  "type": "Feature",
  "properties": {
    "iso:country":"CA",
    "sg:address":"10704 181 St NW",
    "sg:city":"Edmonton",
    "sg:classifiers":[
        {
            "category":"Professional",
            "subcategory":"Research",
            "type":"Services"
        }
    ],
    "sg:phone":"+1 780 483 7240",
    "sg:postcode":"T5S 1K8",
    "sg:province":"AB",
    "sg:tags":[
        "environmental",
        "ecological"
    ],
    "wof:name":"Hydrogeological Consultants",
    "wof:placetype":"venue"
},
  "geometry": {"coordinates":[-113.633460998,53.5535888672],"type":"Point"}
}