{
  "type": "Feature",
  "properties": {
    "addr:full":"Woodbridge ON L4L 5W5",
    "addr:postcode":"l4l 5w5",
    "iso:country":"CA",
    "sg:city":"Woodbridge",
    "sg:classifiers":[
        {
            "category":"Manufacturing",
            "subcategory":"Food",
            "type":"Manufacturing & Wholesale Goods"
        }
    ],
    "sg:phone":"+1 905 856 5333",
    "sg:postcode":"L4L 5W5",
    "sg:province":"ON",
    "sg:tags":[
        "tea",
        "coffee"
    ],
    "wof:name":"Fiesta Coffee",
    "wof:placetype":"venue"
},
  "geometry": {"coordinates":[-79.571152,43.782124],"type":"Point"}
}