{
  "type": "Feature",
  "properties": {
    "addr:full":"421 George St N Peterborough ON K9H 3R4",
    "addr:housenumber":"421",
    "addr:postcode":"k9h 3r4",
    "addr:street":"George St N",
    "iso:country":"CA",
    "sg:address":"421 George St N",
    "sg:city":"Peterborough",
    "sg:classifiers":[
        {
            "category":"Banks & Credit Unions",
            "subcategory":"Bank",
            "type":"Services"
        }
    ],
    "sg:phone":"+1 705 743 5558",
    "sg:postcode":"K9H 3R4",
    "sg:province":"ON",
    "wof:name":"National Bank of Canada",
    "wof:placetype":"venue"
},
  "geometry": {"coordinates":[-78.320305,44.306538],"type":"Point"}
}