{
  "type": "Feature",
  "properties": {
    "addr:full":"3200 Portage Ave # 101 Winnipeg MB R3K 0Y7",
    "addr:housenumber":"3200",
    "addr:postcode":"r3k 0y7",
    "addr:street":"Portage Ave # 101",
    "iso:country":"CA",
    "sg:address":"3200 Portage Ave # 101",
    "sg:city":"Winnipeg",
    "sg:classifiers":[
        {
            "category":"Real Estate",
            "subcategory":"Real Estate Operator",
            "type":"Services"
        }
    ],
    "sg:phone":"+1 204 885 1095",
    "sg:postcode":"R3K 0Y7",
    "sg:province":"MB",
    "sg:tags":[
        "condominium"
    ],
    "wof:name":"Westwood House",
    "wof:placetype":"venue"
},
  "geometry": {"coordinates":[-97.288658,49.880852],"type":"Point"}
}