{
  "type": "Feature",
  "properties": {
    "addr:full":"400 Rue Notre-Dame Gatineau QC J8P 1L5",
    "addr:housenumber":"400",
    "addr:postcode":"j8p 1l5",
    "addr:street":"Rue Notre-Dame",
    "iso:country":"CA",
    "sg:address":"400 Rue Notre-Dame",
    "sg:city":"Gatineau",
    "sg:classifiers":[
        {
            "category":"Shopping",
            "subcategory":"Clothing, Apparel, & Fashions",
            "type":"Retail Goods"
        }
    ],
    "sg:phone":"+1 819 663 5000",
    "sg:postcode":"J8P 1L5",
    "sg:province":"QC",
    "sg:tags":[
        "furnishing"
    ],
    "wof:name":"Willie Assad Inc Men's Wear",
    "wof:placetype":"venue"
},
  "geometry": {"coordinates":[-75.64019012449999,45.4811897278],"type":"Point"}
}