{
  "type": "Feature",
  "properties": {
    "addr:full":"4823 Rue Sherbrooke O #270 Westmount QC H3Z 1G7",
    "addr:housenumber":"4823",
    "addr:postcode":"h3z 1g7",
    "addr:street":"Rue Sherbrooke O # 270",
    "iso:country":"CA",
    "sg:address":"4823 Rue Sherbrooke O #270",
    "sg:city":"Westmount",
    "sg:classifiers":[
        {
            "category":"Professional",
            "subcategory":"Management & Consulting",
            "type":"Services"
        }
    ],
    "sg:phone":"+1 514 935 4207",
    "sg:postcode":"H3Z 1G7",
    "sg:province":"QC",
    "sg:tags":[
        "consultant",
        "instructional"
    ],
    "wof:name":"Cirem",
    "wof:placetype":"venue"
},
  "geometry": {"coordinates":[-73.6031951904,45.4794120789],"type":"Point"}
}