{
  "type": "Feature",
  "properties": {
    "iso:country":"CA",
    "sg:address":"4570 Rue Jean-Talon E #201",
    "sg:city":"Saint-Leonard",
    "sg:classifiers":[
        {
            "category":"Health Services",
            "subcategory":"Doctor",
            "type":"Services"
        }
    ],
    "sg:phone":"+1 514 376 4187",
    "sg:postcode":"H1S 1K2",
    "sg:province":"QC",
    "sg:tags":[
        "dentist"
    ],
    "wof:name":"DE Minico, B DDS",
    "wof:placetype":"venue"
},
  "geometry": {"coordinates":[-73.586891,45.571552],"type":"Point"}
}