{
  "type": "Feature",
  "properties": {
    "addr:full":"1479 133 Rte Henryville QC J0J 1E0",
    "addr:housenumber":"1479",
    "addr:postcode":"j0j 1e0",
    "addr:street":"133 Rte",
    "iso:country":"CA",
    "sg:address":"1479 133 Rte",
    "sg:city":"Henryville",
    "sg:classifiers":[
        {
            "category":"Retail",
            "subcategory":"Auto Repair",
            "type":"Services"
        }
    ],
    "sg:phone":"+1 450 244 5860",
    "sg:postcode":"J0J 1E0",
    "sg:province":"QC",
    "sg:tags":[
        "repairing",
        "automobile"
    ],
    "wof:name":"Garage Stephane Belhumeur",
    "wof:placetype":"venue"
},
  "geometry": {"coordinates":[-73.18058000000001,45.138004],"type":"Point"}
}