{
  "type": "Feature",
  "properties": {
    "addr:full":"7690 Av Papineau Montreal QC H2E 2H2",
    "addr:postcode":"7690;h2e 2h2",
    "addr:street":"Av Papineau",
    "iso:country":"CA",
    "sg:address":"7690 Av Papineau",
    "sg:city":"Montreal",
    "sg:classifiers":[
        {
            "category":"Restaurant",
            "type":"Food & Drink"
        }
    ],
    "sg:phone":"+1 514 721 1500",
    "sg:postcode":"H2E 2H2",
    "sg:province":"QC",
    "wof:name":"Restaurant Deli-Plus",
    "wof:placetype":"venue"
},
  "geometry": {"coordinates":[-73.614441,45.551064],"type":"Point"}
}