{
  "type": "Feature",
  "properties": {
    "addr:full":"1288 Rue Soucy Saint-Hubert QC J4T 1A3",
    "addr:housenumber":"1288",
    "addr:postcode":"j4t 1a3",
    "addr:street":"Rue Soucy",
    "iso:country":"CA",
    "sg:address":"1288 Rue Soucy",
    "sg:city":"Saint-Hubert",
    "sg:classifiers":[
        {
            "category":"Wholesale",
            "subcategory":"Auto Parts",
            "type":"Manufacturing & Wholesale Goods"
        }
    ],
    "sg:phone":"+1 450 443 0406",
    "sg:postcode":"J4T 1A3",
    "sg:province":"QC",
    "sg:tags":[
        "alternator",
        "automobile",
        "rebuilt",
        "generator"
    ],
    "wof:name":"Demarreurs Rive-Sud Inc",
    "wof:placetype":"venue"
},
  "geometry": {"coordinates":[-73.446556,45.497559],"type":"Point"}
}