{
  "type": "Feature",
  "properties": {
    "addr:full":"Post St Whitney ON K0J 2M0",
    "addr:postcode":"k0j 2m0",
    "iso:country":"CA",
    "sg:address":"Post St",
    "sg:city":"Whitney",
    "sg:classifiers":[
        {
            "category":"Shopping",
            "subcategory":"Gifts & Souvenirs",
            "type":"Retail Goods"
        }
    ],
    "sg:phone":"+1 613 637 2805",
    "sg:postcode":"K0J 2M0",
    "sg:province":"ON",
    "sg:tags":[
        "shop"
    ],
    "wof:name":"Men Wah Tay",
    "wof:placetype":"venue"
},
  "geometry": {"coordinates":[-78.24499511720001,45.4991912842],"type":"Point"}
}