{
  "type": "Feature",
  "properties": {
    "addr:full":"172 Wellington St Bowmanville ON L1C 1W3",
    "addr:housenumber":"172",
    "addr:postcode":"l1c 1w3",
    "addr:street":"Wellington St",
    "iso:country":"CA",
    "sg:address":"172 Wellington St",
    "sg:city":"Bowmanville",
    "sg:classifiers":[
        {
            "category":"Manufacturing",
            "subcategory":"Metals",
            "type":"Manufacturing & Wholesale Goods"
        }
    ],
    "sg:phone":"+1 905 623 3313",
    "sg:postcode":"L1C 1W3",
    "sg:province":"ON",
    "sg:tags":[
        "foundry"
    ],
    "wof:name":"Bowmanville Foundry CO Ltd",
    "wof:placetype":"venue"
},
  "geometry": {"coordinates":[-78.693398,43.915882],"type":"Point"}
}