{
  "type": "Feature",
  "properties": {
    "addr:full":"1328 Unity Rd Glenburnie ON K0H 1S0",
    "addr:housenumber":"1328",
    "addr:postcode":"k0h 1s0",
    "addr:street":"Unity Rd",
    "iso:country":"CA",
    "sg:address":"1328 Unity Rd",
    "sg:city":"Glenburnie",
    "sg:classifiers":[
        {
            "category":"Shopping",
            "type":"Retail Goods"
        }
    ],
    "sg:phone":"+1 613 544 0210",
    "sg:postcode":"K0H 1S0",
    "sg:province":"ON",
    "sg:tags":[
        "cosmetic",
        "perfume"
    ],
    "wof:name":"Aloette Cosmetics Kingston",
    "wof:placetype":"venue"
},
  "geometry": {"coordinates":[-76.4616317749,44.3213882446],"type":"Point"}
}