{
  "type": "Feature",
  "properties": {
    "addr:full":"1230 Rue Des Erables Saint-Lambert-DE-Lauzon QC G0S 2W0",
    "addr:housenumber":"1230",
    "addr:postcode":"g0s 2w0",
    "addr:street":"Rue Des Erables",
    "iso:country":"CA",
    "sg:address":"1230 Rue Des Erables",
    "sg:city":"Saint-Lambert-DE-Lauzon",
    "sg:classifiers":[
        {
            "category":"Manufacturing",
            "subcategory":"Metals",
            "type":"Manufacturing & Wholesale Goods"
        }
    ],
    "sg:phone":"+1 418 889 9761",
    "sg:postcode":"G0S 2W0",
    "sg:province":"QC",
    "sg:tags":[
        "brass",
        "material",
        "siding",
        "bronze"
    ],
    "wof:name":"Revetements Alnordica Inc",
    "wof:placetype":"venue"
},
  "geometry": {"coordinates":[-71.2120056152,46.588180542],"type":"Point"}
}