{
  "type": "Feature",
  "properties": {
    "addr:full":"837 Millwood Rd East York ON M4G 1W5",
    "addr:housenumber":"837",
    "addr:postcode":"m4g 1w5",
    "addr:street":"Millwood Rd",
    "iso:country":"CA",
    "sg:address":"837 Millwood Rd",
    "sg:city":"East York",
    "sg:classifiers":[
        {
            "category":"Professional",
            "subcategory":"Management & Consulting",
            "type":"Services"
        }
    ],
    "sg:phone":"+1 416 467 0011",
    "sg:postcode":"M4G 1W5",
    "sg:province":"ON",
    "sg:tags":[
        "consultant",
        "business"
    ],
    "wof:name":"S B Smith Consulting Group Inc",
    "wof:placetype":"venue"
},
  "geometry": {"coordinates":[-79.3676376343,43.7045707703],"type":"Point"}
}