{
  "type": "Feature",
  "properties": {
    "addr:full":"8365 Boul Viau Saint-Leonard QC H1R 2T6",
    "addr:housenumber":"8365",
    "addr:postcode":"h1r 2t6",
    "addr:street":"Boul Viau",
    "iso:country":"CA",
    "sg:address":"8365 Boul Viau",
    "sg:city":"Saint-Leonard",
    "sg:classifiers":[
        {
            "category":"Shopping",
            "subcategory":"Clothing, Apparel, & Fashions",
            "type":"Retail Goods"
        }
    ],
    "sg:phone":"+1 514 323 0427",
    "sg:postcode":"H1R 2T6",
    "sg:province":"QC",
    "sg:tags":[
        "lingerie"
    ],
    "wof:name":"Lingerie Pina & Carmelo Sacco",
    "wof:placetype":"venue"
},
  "geometry": {"coordinates":[-73.60186767579999,45.5801391602],"type":"Point"}
}