{
  "type": "Feature",
  "properties": {
    "addr:full":"2707 1E Av Quebec QC G1L 3N7",
    "addr:housenumber":"2707",
    "addr:postcode":"g1l 3n7",
    "addr:street":"1E Av",
    "iso:country":"CA",
    "sg:address":"2707 1E Av",
    "sg:city":"Quebec",
    "sg:classifiers":[
        {
            "category":"Insurance",
            "subcategory":"Insurance Agent",
            "type":"Services"
        }
    ],
    "sg:phone":"+1 418 627 4444",
    "sg:postcode":"G1L 3N7",
    "sg:province":"QC",
    "wof:name":"Andre Fradet & Assoc Inc",
    "wof:placetype":"venue"
},
  "geometry": {"coordinates":[-71.24389600000001,46.836514],"type":"Point"}
}