{
  "type": "Feature",
  "properties": {
    "addr:full":"1142 Rue Du Pont Saint-Lambert-DE-Lauzon QC G0S 2W0",
    "addr:housenumber":"1142",
    "addr:postcode":"g0s 2w0",
    "addr:street":"Rue Du Pont",
    "iso:country":"CA",
    "sg:address":"1142 Rue Du Pont",
    "sg:city":"Saint-Lambert-DE-Lauzon",
    "sg:classifiers":[
        {
            "category":"Food & Beverages",
            "subcategory":"Groceries & Convenience Stores",
            "type":"Retail Goods"
        }
    ],
    "sg:phone":"+1 418 889 8686",
    "sg:postcode":"G0S 2W0",
    "sg:province":"QC",
    "wof:name":"Depanneur Du Pont St Lambert",
    "wof:placetype":"venue"
},
  "geometry": {"coordinates":[-71.21152499999999,46.587654],"type":"Point"}
}