{
  "type": "Feature",
  "properties": {
    "addr:full":"Havre Boucher NS B0H 1P0",
    "addr:postcode":"b0h 1p0",
    "iso:country":"CA",
    "sg:city":"Havre Boucher",
    "sg:classifiers":[
        {
            "category":"Recreation",
            "type":"Entertainment"
        }
    ],
    "sg:phone":"+1 902 747 2429",
    "sg:postcode":"B0H 1P0",
    "sg:province":"NS",
    "sg:tags":[
        "diving",
        "instruction",
        "marine",
        "designer",
        "contractor"
    ],
    "wof:name":"Causeway Diver Supply",
    "wof:placetype":"venue"
},
  "geometry": {"coordinates":[-61.5395240784,45.6796035767],"type":"Point"}
}