{
  "type": "Feature",
  "properties": {
    "addr:full":"2210 Park Ave Brandon MB R7B 0S1",
    "addr:housenumber":"2210",
    "addr:postcode":"r7b 0s1",
    "addr:street":"Park Ave",
    "iso:country":"CA",
    "sg:address":"2210 Park Ave",
    "sg:city":"Brandon",
    "sg:classifiers":[
        {
            "category":"Building & Trades",
            "subcategory":"Construction",
            "type":"Services"
        }
    ],
    "sg:phone":"+1 204 728 2699",
    "sg:postcode":"R7B 0S1",
    "sg:province":"MB",
    "sg:tags":[
        "excavating",
        "contractor"
    ],
    "wof:name":"C & C Construction Ltd",
    "wof:placetype":"venue"
},
  "geometry": {"coordinates":[-99.967758,49.835861],"type":"Point"}
}