{
  "type": "Feature",
  "properties": {
    "addr:full":"10 Cundall Dr Estevan SK S4A 1T1",
    "addr:housenumber":"10",
    "addr:postcode":"s4a 1t1",
    "addr:street":"Cundall Dr",
    "iso:country":"CA",
    "sg:address":"10 Cundall Dr",
    "sg:city":"Estevan",
    "sg:classifiers":[
        {
            "category":"Health Services",
            "subcategory":"Medical Lab",
            "type":"Services"
        }
    ],
    "sg:phone":"+1 306 634 2030",
    "sg:postcode":"S4A 1T1",
    "sg:province":"SK",
    "wof:name":"B G Denture Clinic",
    "wof:placetype":"venue"
},
  "geometry": {"coordinates":[-102.993858,49.14724],"type":"Point"}
}