{
  "type": "Feature",
  "properties": {
    "addr:full":"1814 Theatre Rd Cranbrook BC V1C 7G1",
    "addr:housenumber":"1814",
    "addr:postcode":"bc v1c 7g1",
    "addr:street":"Theatre Rd",
    "iso:country":"CA",
    "sg:address":"1814 Theatre Rd",
    "sg:city":"Cranbrook",
    "sg:classifiers":[
        {
            "category":"Manufacturing",
            "subcategory":"Petroleum Products",
            "type":"Manufacturing & Wholesale Goods"
        }
    ],
    "sg:phone":"+1 250 426 6669",
    "sg:postcode":"V1C 7G1",
    "sg:province":"BC",
    "sg:tags":[
        "oil"
    ],
    "wof:name":"Jepson Petroleum Ltd",
    "wof:placetype":"venue"
},
  "geometry": {"coordinates":[-115.75398300000001,49.53091],"type":"Point"}
}