{
  "type": "Feature",
  "properties": {
    "iso:country":"CA",
    "sg:address":"7533 12th Ave",
    "sg:city":"Burnaby",
    "sg:classifiers":[
        {
            "category":"Freight",
            "type":"Transportation"
        }
    ],
    "sg:phone":"+1 604 522 9412",
    "sg:postcode":"V3N 2K3",
    "sg:province":"BC",
    "sg:tags":[
        "mover"
    ],
    "wof:name":"K C's Moving CO Ltd",
    "wof:placetype":"venue"
},
  "geometry": {"coordinates":[-122.936950684,49.2165336609],"type":"Point"}
}