{
  "type": "Feature",
  "properties": {
    "addr:full":"3823 Lake Shore Blvd W Etobicoke ON M8W 1R2",
    "addr:housenumber":"3823",
    "addr:postcode":"m8w 1r2",
    "addr:street":"Lake Shore Blvd W",
    "iso:country":"CA",
    "sg:address":"3823 Lake Shore Blvd W",
    "sg:city":"Etobicoke",
    "sg:classifiers":[
        {
            "category":"Food & Beverages",
            "subcategory":"Groceries & Convenience Stores",
            "type":"Retail Goods"
        }
    ],
    "sg:phone":"+1 416 255 4189",
    "sg:postcode":"M8W 1R2",
    "sg:province":"ON",
    "sg:tags":[
        "grocer"
    ],
    "wof:name":"H Y Food Town",
    "wof:placetype":"venue"
},
  "geometry": {"coordinates":[-79.543358,43.591904],"type":"Point"}
}