{
  "type": "Feature",
  "properties": {
    "addr:full":"Toronto ON M5A 1P4",
    "addr:postcode":"m5a 1p4",
    "iso:country":"CA",
    "sg:city":"Toronto",
    "sg:classifiers":[
        {
            "category":"Retail",
            "subcategory":"Photofinishing",
            "type":"Services"
        }
    ],
    "sg:phone":"+1 416 368 9777",
    "sg:postcode":"M5A 1P4",
    "sg:province":"ON",
    "sg:tags":[
        "photo",
        "finishing"
    ],
    "wof:name":"Madison Photo Murals Ltd",
    "wof:placetype":"venue"
},
  "geometry": {"coordinates":[-79.370125,43.653259],"type":"Point"}
}