{
  "type": "Feature",
  "properties": {
    "addr:full":"10014 102 St Grande Prairie AB T8V 2V6",
    "addr:housenumber":"10014",
    "addr:postcode":"t8v 2v6",
    "addr:street":"102 St",
    "iso:country":"CA",
    "sg:address":"10014 102 St",
    "sg:city":"Grande Prairie",
    "sg:classifiers":[
        {
            "category":"Restaurant",
            "type":"Food & Drink"
        }
    ],
    "sg:phone":"+1 780 532 4222",
    "sg:postcode":"T8V 2V6",
    "sg:province":"AB",
    "sg:tags":[
        "beverage"
    ],
    "wof:name":"Coca-Cola/Canada Dry",
    "wof:placetype":"venue"
},
  "geometry": {"coordinates":[-118.80154400000001,55.170895],"type":"Point"}
}