{
  "type": "Feature",
  "properties": {
    "addr:full":"198 Victoria St W Kamloops BC V2C 1A4",
    "addr:housenumber":"198",
    "addr:postcode":"bc v2c 1a4",
    "addr:street":"Victoria St W",
    "iso:country":"CA",
    "sg:address":"198 Victoria St W",
    "sg:city":"Kamloops",
    "sg:classifiers":[
        {
            "category":"Shopping",
            "subcategory":"Computers & Home Electronics",
            "type":"Retail Goods"
        }
    ],
    "sg:phone":"+1 250 374 3848",
    "sg:postcode":"V2C 1A4",
    "sg:province":"BC",
    "sg:tags":[
        "high",
        "equipment",
        "fidelity",
        "stereophonic",
        "satellite"
    ],
    "wof:name":"Stereo Warehouse",
    "wof:placetype":"venue"
},
  "geometry": {"coordinates":[-120.342590332,50.6771278381],"type":"Point"}
}