{
  "type": "Feature",
  "properties": {
    "iso:country":"CA",
    "sg:address":"250 Martindale Rd",
    "sg:city":"St Catharines",
    "sg:classifiers":[
        {
            "category":"Professional",
            "subcategory":"Research",
            "type":"Services"
        }
    ],
    "sg:phone":"+1 905 641 0941",
    "sg:postcode":"L2R 6P9",
    "sg:province":"ON",
    "sg:tags":[
        "environmental",
        "ecological",
        "engineer"
    ],
    "wof:name":"Asi Group Ltd",
    "wof:placetype":"venue"
},
  "geometry": {"coordinates":[-79.274757,43.175335],"type":"Point"}
}