{
  "type": "Feature",
  "properties": {
    "addr:full":"2107 1/2 Yonge St Toronto ON M4S 2A4",
    "addr:housenumber":"2107 1 / 2",
    "addr:postcode":"m4s 2a4",
    "addr:street":"Yonge St",
    "iso:country":"CA",
    "sg:address":"2107 1/2 Yonge St",
    "sg:city":"Toronto",
    "sg:classifiers":[
        {
            "category":"Shopping",
            "subcategory":"Computers & Home Electronics",
            "type":"Retail Goods"
        }
    ],
    "sg:phone":"+1 416 488 9293",
    "sg:postcode":"M4S 2A4",
    "sg:province":"ON",
    "sg:tags":[
        "equipment",
        "dealer"
    ],
    "wof:name":"Union Computer & Electronic",
    "wof:placetype":"venue"
},
  "geometry": {"coordinates":[-79.3974151611,43.7031135559],"type":"Point"}
}