{
  "type": "Feature",
  "properties": {
    "addr:full":"Shearstown Rd Shearstown NL A0A 3V0",
    "addr:postcode":"a0a 3v0",
    "addr:street":"Shearstown Rd",
    "iso:country":"CA",
    "sg:address":"Shearstown Rd",
    "sg:city":"Shearstown",
    "sg:classifiers":[
        {
            "category":"Restaurant",
            "type":"Food & Drink"
        }
    ],
    "sg:phone":"+1 709 786 2438",
    "sg:postcode":"A0A 3V0",
    "sg:province":"NL",
    "wof:name":"Mountain View Grocery & Take",
    "wof:placetype":"venue"
},
  "geometry": {"coordinates":[-53.300694,47.58691],"type":"Point"}
}