{
  "type": "Feature",
  "properties": {
    "addr:full":"455 Ch Ozias-Leduc # A Otterburn Park QC J3H 4A7",
    "addr:housenumber":"455",
    "addr:postcode":"j3h 4a7",
    "addr:street":"Ch Ozias-Leduc # A Otterburn Park",
    "iso:country":"CA",
    "sg:address":"455 Ch Ozias-Leduc # A",
    "sg:city":"Otterburn Park",
    "sg:classifiers":[
        {
            "category":"Shopping",
            "subcategory":"Bicycles & Sporting Goods",
            "type":"Retail Goods"
        }
    ],
    "sg:phone":"+1 450 464 8808",
    "sg:postcode":"J3H 4A7",
    "sg:province":"QC",
    "wof:name":"D & M Cyclo Sport",
    "wof:placetype":"venue"
},
  "geometry": {"coordinates":[-73.1869049072,45.54322052],"type":"Point"}
}