{
  "type": "Feature",
  "properties": {
    "addr:full":"6710 Ogden Dale Rd SE Calgary AB T2C 3A9",
    "addr:housenumber":"6710",
    "addr:postcode":"t2c 3a9",
    "addr:street":"Ogden Dale Rd Se",
    "iso:country":"CA",
    "sg:address":"6710 Ogden Dale Rd SE",
    "sg:city":"Calgary",
    "sg:classifiers":[
        {
            "category":"Retail",
            "subcategory":"Auto Repair",
            "type":"Services"
        }
    ],
    "sg:phone":"+1 403 236 2550",
    "sg:postcode":"T2C 3A9",
    "sg:province":"AB",
    "sg:tags":[
        "automobile",
        "mover",
        "co",
        "transporter"
    ],
    "wof:name":"Allied Systems CO",
    "wof:placetype":"venue"
},
  "geometry": {"coordinates":[-113.990325928,50.9926185608],"type":"Point"}
}