{
  "type": "Feature",
  "properties": {
    "addr:full":"4352 Kingston Rd Scarborough ON M1E 2M8",
    "addr:housenumber":"4352",
    "addr:postcode":"m1e 2m8",
    "addr:street":"Kingston Rd",
    "iso:country":"CA",
    "sg:address":"4352 Kingston Rd",
    "sg:city":"Scarborough",
    "sg:classifiers":[
        {
            "category":"Banks & Credit Unions",
            "subcategory":"Bank",
            "type":"Services"
        }
    ],
    "sg:phone":"+1 416 286 3712",
    "sg:postcode":"M1E 2M8",
    "sg:province":"ON",
    "sg:tags":[
        "cashing",
        "money",
        "check",
        "order"
    ],
    "wof:name":"Money Mart Cheque Cashing Ctrs",
    "wof:placetype":"venue"
},
  "geometry": {"coordinates":[-79.191734314,43.7656593323],"type":"Point"}
}