{
  "type": "Feature",
  "properties": {
    "iso:country":"CA",
    "sg:city":"Cambridge Bay",
    "sg:classifiers":[
        {
            "category":"Real Estate",
            "subcategory":"Real Estate Agent",
            "type":"Services"
        }
    ],
    "sg:phone":"+1 867 857 8700",
    "sg:postcode":"X0B 0C0",
    "sg:province":"NU",
    "sg:tags":[
        "authorities",
        "housing",
        "assistance"
    ],
    "wof:name":"Nunavut Housing Corp",
    "wof:placetype":"venue"
},
  "geometry": {"coordinates":[-105.057556152,69.11428070069999],"type":"Point"}
}