{
  "type": "Feature",
  "properties": {
    "addr:full":"Dawson Creek BC V1G 2G4",
    "addr:postcode":"v1g 2g4",
    "iso:country":"CA",
    "sg:city":"Dawson Creek",
    "sg:classifiers":[
        {
            "category":"Shopping",
            "subcategory":"Used Merchandise",
            "type":"Retail Goods"
        }
    ],
    "sg:phone":"+1 250 782 8811",
    "sg:postcode":"V1G 2G4",
    "sg:province":"BC",
    "wof:name":"Under the Willow",
    "wof:placetype":"venue"
},
  "geometry": {"coordinates":[-120.227279663,55.7569465637],"type":"Point"}
}