{
  "type": "Feature",
  "properties": {
    "iso:country":"CA",
    "sg:address":"2064 19 St N",
    "sg:city":"Lethbridge",
    "sg:classifiers":[
        {
            "category":"Farming",
            "subcategory":"Nursery",
            "type":"Manufacturing & Wholesale Goods"
        }
    ],
    "sg:phone":"+1 403 327 0684",
    "sg:postcode":"T1H 4B2",
    "sg:province":"AB",
    "sg:tags":[
        "greenhouse"
    ],
    "wof:name":"South West Seeds",
    "wof:placetype":"venue"
},
  "geometry": {"coordinates":[-112.815078735,49.7224464417],"type":"Point"}
}