{
  "type": "Feature",
  "properties": {
    "addr:full":"806 Freeman St Prince George BC V2M 2R5",
    "addr:housenumber":"806",
    "addr:postcode":"v2m 2r5",
    "addr:street":"Freeman St",
    "iso:country":"CA",
    "sg:address":"806 Freeman St",
    "sg:city":"Prince George",
    "sg:classifiers":[
        {
            "category":"Building & Trades",
            "subcategory":"Construction",
            "type":"Services"
        }
    ],
    "sg:phone":"+1 250 561 0307",
    "sg:postcode":"V2M 2R5",
    "sg:province":"BC",
    "sg:tags":[
        "repairing",
        "contractor",
        "remodeling",
        "general"
    ],
    "wof:name":"Tps Enterprises",
    "wof:placetype":"venue"
},
  "geometry": {"coordinates":[-122.773613,53.917351],"type":"Point"}
}