{
  "type": "Feature",
  "properties": {
    "addr:full":"2080 55E Av Dorval QC H9P 1H1",
    "addr:housenumber":"2080",
    "addr:postcode":"h9p 1h1",
    "addr:street":"55E Av",
    "iso:country":"CA",
    "sg:address":"2080 55E Av",
    "sg:city":"Dorval",
    "sg:classifiers":[
        {
            "category":"Manufacturing",
            "subcategory":"Rubber & Plastics",
            "type":"Manufacturing & Wholesale Goods"
        }
    ],
    "sg:phone":"+1 514 631 2231",
    "sg:postcode":"H9P 1H1",
    "sg:province":"QC",
    "wof:name":"Sismo Extrusions Inc",
    "wof:placetype":"venue"
},
  "geometry": {"coordinates":[-73.7274398804,45.4631385803],"type":"Point"}
}