{
  "type": "Feature",
  "properties": {
    "addr:full":"5950 No. 6 Rd Richmond BC V6V 1Z1",
    "addr:postcode":"5950;v6v 1z1",
    "addr:street":"6 Rd",
    "iso:country":"CA",
    "sg:address":"5950 No. 6 Rd",
    "sg:city":"Richmond",
    "sg:classifiers":[
        {
            "category":"Retail",
            "subcategory":"Auto Repair",
            "type":"Services"
        }
    ],
    "sg:phone":"+1 604 278 0087",
    "sg:postcode":"V6V 1Z1",
    "sg:province":"BC",
    "sg:tags":[
        "body",
        "automobile",
        "painting"
    ],
    "wof:name":"Sharp Collision Repair Ltd",
    "wof:placetype":"venue"
},
  "geometry": {"coordinates":[-123.068977,49.171051],"type":"Point"}
}