{
  "type": "Feature",
  "properties": {
    "addr:full":"480 Hartney St Arnprior ON K7S 3H4",
    "addr:housenumber":"480",
    "addr:postcode":"k7s 3h4",
    "addr:street":"Hartney St",
    "iso:country":"CA",
    "sg:address":"480 Hartney St",
    "sg:city":"Arnprior",
    "sg:classifiers":[
        {
            "category":"Retail",
            "subcategory":"Auto Repair",
            "type":"Services"
        }
    ],
    "sg:phone":"+1 613 623 6508",
    "sg:postcode":"K7S 3H4",
    "sg:province":"ON",
    "sg:tags":[
        "truck"
    ],
    "wof:name":"R & M Truck & Trailer Repair",
    "wof:placetype":"venue"
},
  "geometry": {"coordinates":[-76.342918396,45.423034668],"type":"Point"}
}