{
  "type": "Feature",
  "properties": {
    "addr:full":"426 Wilson Ave North York ON M3H 1S9",
    "addr:housenumber":"426",
    "addr:postcode":"m3h 1s9",
    "addr:street":"Wilson Ave",
    "iso:country":"CA",
    "sg:address":"426 Wilson Ave",
    "sg:city":"North York",
    "sg:classifiers":[
        {
            "category":"Retail",
            "subcategory":"Laundry & Dry Cleaning",
            "type":"Services"
        }
    ],
    "sg:phone":"+1 416 635 6361",
    "sg:postcode":"M3H 1S9",
    "sg:province":"ON",
    "sg:tags":[
        "cleaners"
    ],
    "wof:name":"North Park Dry Cleaners",
    "wof:placetype":"venue"
},
  "geometry": {"coordinates":[-79.4424667358,43.735748291],"type":"Point"}
}