{
  "type": "Feature",
  "properties": {
    "addr:full":"Concord ON L4K 1J3",
    "addr:postcode":"l4k 1j3",
    "iso:country":"CA",
    "sg:city":"Concord",
    "sg:classifiers":[
        {
            "category":"Manufacturing",
            "subcategory":"Tools & Machinery",
            "type":"Manufacturing & Wholesale Goods"
        }
    ],
    "sg:phone":"+1 905 731 8104",
    "sg:postcode":"L4K 1J3",
    "sg:province":"ON",
    "sg:tags":[
        "oil",
        "grease",
        "absorbent"
    ],
    "wof:name":"M J Intl & Assoc Inc",
    "wof:placetype":"venue"
},
  "geometry": {"coordinates":[-79.49361399999999,43.811684],"type":"Point"}
}