{
  "type": "Feature",
  "properties": {
    "iso:country":"CA",
    "sg:address":"5204 50 Ave",
    "sg:city":"Camrose",
    "sg:classifiers":[
        {
            "category":"Government",
            "subcategory":"Office",
            "type":"Public Place"
        }
    ],
    "sg:phone":"+1 780 672 4426",
    "sg:postcode":"T4V 0S8",
    "sg:province":"AB",
    "sg:tags":[
        "arena",
        "athletic",
        "village",
        "stadium",
        "fields"
    ],
    "wof:name":"Camrose City Office",
    "wof:placetype":"venue"
},
  "geometry": {"coordinates":[-112.82949829099999,53.0227851868],"type":"Point"}
}