{
  "type": "Feature",
  "properties": {
    "addr:full":"Montreal QC H1N 1C7",
    "addr:postcode":"h1n 1c7",
    "iso:country":"CA",
    "sg:city":"Montreal",
    "sg:classifiers":[
        {
            "category":"Professional",
            "subcategory":"Lawyer & Legal Services",
            "type":"Services"
        }
    ],
    "sg:phone":"+1 514 253 0876",
    "sg:postcode":"H1N 1C7",
    "sg:province":"QC",
    "sg:tags":[
        "attorney"
    ],
    "wof:name":"Bastien, Michel",
    "wof:placetype":"venue"
},
  "geometry": {"coordinates":[-73.5431594849,45.583026886],"type":"Point"}
}