{
  "type": "Feature",
  "properties": {
    "addr:full":"999 Rue Dollard Buckingham QC J8L 3E6",
    "addr:housenumber":"999",
    "addr:postcode":"j8l 3e6",
    "addr:street":"Rue Dollard",
    "iso:country":"CA",
    "sg:address":"999 Rue Dollard",
    "sg:city":"Buckingham",
    "sg:classifiers":[
        {
            "category":"Shopping",
            "subcategory":"Shoes",
            "type":"Retail Goods"
        }
    ],
    "sg:phone":"+1 819 281 1966",
    "sg:postcode":"J8L 3E6",
    "sg:province":"QC",
    "wof:name":"Magasins Libre Svc Pitt Ltee",
    "wof:placetype":"venue"
},
  "geometry": {"coordinates":[-75.407066,45.576565],"type":"Point"}
}