{
  "type": "Feature",
  "properties": {
    "iso:country":"CA",
    "sg:address":"570 Shakespeare Ave",
    "sg:city":"Oshawa",
    "sg:classifiers":[
        {
            "category":"Education",
            "subcategory":"School",
            "type":"Public Place"
        }
    ],
    "sg:phone":"+1 905 725 8271",
    "sg:postcode":"L1H 3H6",
    "sg:province":"ON",
    "wof:name":"Gertrude Colpus Public School",
    "wof:placetype":"venue"
},
  "geometry": {"coordinates":[-78.8370666504,43.8899650574],"type":"Point"}
}