{
  "type": "Feature",
  "properties": {
    "addr:full":"6964 Boul Sainte-Anne L'Ange Gardien QC G0A 2K0",
    "addr:housenumber":"6964",
    "addr:postcode":"g0a 2k0",
    "addr:street":"Boul Sainte-Anne",
    "iso:country":"CA",
    "sg:address":"6964 Boul Sainte-Anne",
    "sg:city":"L'Ange Gardien",
    "sg:classifiers":[
        {
            "category":"Autos & Motor Vehicles",
            "subcategory":"Automobile Sales",
            "type":"Retail Goods"
        }
    ],
    "sg:phone":"+1 418 822 1475",
    "sg:postcode":"G0A 2K0",
    "sg:province":"QC",
    "sg:tags":[
        "car",
        "dealer"
    ],
    "wof:name":"Automobiles Prime Roberge Inc",
    "wof:placetype":"venue"
},
  "geometry": {"coordinates":[-72.9380264282,45.357460022],"type":"Point"}
}