{
  "type": "Feature",
  "properties": {
    "iso:country":"CA",
    "sg:address":"2620 2 Ave N",
    "sg:city":"Lethbridge",
    "sg:classifiers":[
        {
            "category":"Home & Garden",
            "subcategory":"Garden Supply",
            "type":"Retail Goods"
        }
    ],
    "sg:phone":"+1 403 327 8080",
    "sg:postcode":"T1H 0C2",
    "sg:province":"AB",
    "sg:tags":[
        "lawn",
        "mower"
    ],
    "wof:name":"Ddk Lawn & Garden Equipment",
    "wof:placetype":"venue"
},
  "geometry": {"coordinates":[-112.803276,49.699993],"type":"Point"}
}