{
  "type": "Feature",
  "properties": {
    "addr:full":"139 Holland Ave Ottawa ON K1Y 0Y2",
    "addr:housenumber":"139",
    "addr:postcode":"k1y 0y2",
    "addr:street":"Holland Ave",
    "iso:country":"CA",
    "sg:address":"139 Holland Ave",
    "sg:city":"Ottawa",
    "sg:classifiers":[
        {
            "category":"Shopping",
            "subcategory":"Optical Goods",
            "type":"Retail Goods"
        }
    ],
    "sg:phone":"+1 613 798 0219",
    "sg:postcode":"K1Y 0Y2",
    "sg:province":"ON",
    "sg:tags":[
        "contact",
        "lense",
        "optician"
    ],
    "wof:name":"Kimberley Optical",
    "wof:placetype":"venue"
},
  "geometry": {"coordinates":[-75.73146800000001,45.399181],"type":"Point"}
}