{
  "type": "Feature",
  "properties": {
    "addr:full":"959 Midland Ave Scarborough ON M1K 4G4",
    "addr:housenumber":"959",
    "addr:postcode":"m1k 4g4",
    "addr:street":"Midland Ave",
    "iso:country":"CA",
    "sg:address":"959 Midland Ave",
    "sg:city":"Scarborough",
    "sg:classifiers":[
        {
            "category":"Education",
            "subcategory":"School",
            "type":"Public Place"
        }
    ],
    "sg:phone":"+1 416 393 5554",
    "sg:postcode":"M1K 4G4",
    "sg:province":"ON",
    "wof:name":"Jean Vanier School",
    "wof:placetype":"venue"
},
  "geometry": {"coordinates":[-79.2593612671,43.7379417419],"type":"Point"}
}