{
  "type": "Feature",
  "properties": {
    "addr:full":"19 Alexandra Wood Richmond Hill ON L4B 2L1",
    "addr:housenumber":"19",
    "addr:postcode":"l4b 2l1",
    "addr:street":"Alexandra Wood",
    "iso:country":"CA",
    "sg:address":"19 Alexandra Wood",
    "sg:city":"Richmond Hill",
    "sg:classifiers":[
        {
            "category":"Real Estate",
            "subcategory":"Architect",
            "type":"Services"
        }
    ],
    "sg:phone":"+1 905 737 5477",
    "sg:postcode":"L4B 2L1",
    "sg:province":"ON",
    "wof:name":"Tjan, David S",
    "wof:placetype":"venue"
},
  "geometry": {"coordinates":[-79.40933200000001,43.864388],"type":"Point"}
}