{
  "type": "Feature",
  "properties": {
    "addr:full":"Marten River ON P0H 1T0",
    "addr:postcode":"p0h 1t0",
    "addr:street":"Marten River",
    "iso:country":"CA",
    "sg:city":"Marten River",
    "sg:classifiers":[
        {
            "category":"Travel",
            "subcategory":"Hotels & Motels",
            "type":"Entertainment"
        }
    ],
    "sg:phone":"+1 705 892 2211",
    "sg:postcode":"P0H 1T0",
    "sg:province":"ON",
    "wof:name":"Rock Pine Motel & Restaurant",
    "wof:placetype":"venue"
},
  "geometry": {"coordinates":[-79.8195343018,46.743888855],"type":"Point"}
}