{
  "type": "Feature",
  "properties": {
    "iso:country":"CA",
    "sg:address":"872 Dutton Rd",
    "sg:city":"Peterborough",
    "sg:classifiers":[
        {
            "category":"Social Services",
            "type":"Services"
        }
    ],
    "sg:phone":"+1 705 748 2221",
    "sg:postcode":"K9H 7G1",
    "sg:province":"ON",
    "sg:tags":[
        "organization",
        "welfare"
    ],
    "wof:name":"Five Counties Children's Ctr",
    "wof:placetype":"venue"
},
  "geometry": {"coordinates":[-78.317345,44.324837],"type":"Point"}
}