{
  "type": "Feature",
  "properties": {
    "iso:country":"CA",
    "sg:city":"Ottawa",
    "sg:classifiers":[
        {
            "category":"Shopping",
            "type":"Retail Goods"
        }
    ],
    "sg:phone":"+1 613 520 2120",
    "sg:postcode":"K1S 5B6",
    "sg:province":"ON",
    "sg:tags":[
        "museum",
        "art",
        "gallery",
        "dealer"
    ],
    "wof:name":"Carleton University Art Gllry",
    "wof:placetype":"venue"
},
  "geometry": {"coordinates":[-75.697906,45.392605],"type":"Point"}
}