{
  "type": "Feature",
  "properties": {
    "addr:full":"Toronto ON M5V 1S8",
    "addr:postcode":"m5v 1s8",
    "iso:country":"CA",
    "sg:city":"Toronto",
    "sg:classifiers":[
        {
            "category":"Real Estate",
            "subcategory":"Architect",
            "type":"Services"
        }
    ],
    "sg:phone":"+1 416 929 6556",
    "sg:postcode":"M5V 1S8",
    "sg:province":"ON",
    "wof:name":"Goldsmith Borgal & CO Ltd",
    "wof:placetype":"venue"
},
  "geometry": {"coordinates":[-79.39664500000001,43.646667],"type":"Point"}
}