{
  "type": "Feature",
  "properties": {
    "addr:full":"735 Wall St Winnipeg MB R3G 2T6",
    "addr:housenumber":"735",
    "addr:postcode":"r3g 2t6",
    "addr:street":"Wall St",
    "iso:country":"CA",
    "sg:address":"735 Wall St",
    "sg:city":"Winnipeg",
    "sg:classifiers":[
        {
            "category":"Retail",
            "subcategory":"Repair Shop",
            "type":"Services"
        }
    ],
    "sg:phone":"+1 204 783 1693",
    "sg:postcode":"R3G 2T6",
    "sg:province":"MB",
    "sg:tags":[
        "upholsterer"
    ],
    "wof:name":"Harvick's Auto Uphlstrg & Tops",
    "wof:placetype":"venue"
},
  "geometry": {"coordinates":[-97.18232,49.889221],"type":"Point"}
}