{
  "type": "Feature",
  "properties": {
    "addr:full":"522 Main St W Grimsby ON L3M 1T5",
    "addr:housenumber":"522",
    "addr:postcode":"l3m 1t5",
    "addr:street":"Main St W",
    "iso:country":"CA",
    "sg:address":"522 Main St W",
    "sg:city":"Grimsby",
    "sg:classifiers":[
        {
            "category":"Personal",
            "subcategory":"Beauty Salon",
            "type":"Services"
        }
    ],
    "sg:phone":"+1 905 945 1986",
    "sg:postcode":"L3M 1T5",
    "sg:province":"ON",
    "wof:name":"Hair Fashions",
    "wof:placetype":"venue"
},
  "geometry": {"coordinates":[-79.6185531616,43.2048530579],"type":"Point"}
}