{
  "type": "Feature",
  "properties": {
    "addr:full":"16030 118 Ave NW Edmonton AB T5V 1C6",
    "addr:housenumber":"16030",
    "addr:postcode":"t5v 1c6",
    "addr:street":"118 Ave Nw",
    "iso:country":"CA",
    "sg:address":"16030 118 Ave NW",
    "sg:city":"Edmonton",
    "sg:classifiers":[
        {
            "category":"Home & Garden",
            "subcategory":"Garden Supply",
            "type":"Retail Goods"
        }
    ],
    "sg:phone":"+1 780 453 5950",
    "sg:postcode":"T5V 1C6",
    "sg:province":"AB",
    "sg:tags":[
        "sprinkler"
    ],
    "wof:name":"Alberta Irrigation Supply Ltd",
    "wof:placetype":"venue"
},
  "geometry": {"coordinates":[-113.598007,53.570744],"type":"Point"}
}