{
  "type": "Feature",
  "properties": {
    "addr:full":"Toronto ON M5K 1A1",
    "addr:postcode":"m5k 1a1",
    "iso:country":"CA",
    "sg:city":"Toronto",
    "sg:classifiers":[
        {
            "category":"Shopping",
            "subcategory":"Gifts & Souvenirs",
            "type":"Retail Goods"
        }
    ],
    "sg:phone":"+1 416 368 6704",
    "sg:postcode":"M5K 1A1",
    "sg:province":"ON",
    "sg:tags":[
        "cards",
        "greeting"
    ],
    "wof:name":"Carleton Cards",
    "wof:placetype":"venue"
},
  "geometry": {"coordinates":[-79.3814086914,43.6470947266],"type":"Point"}
}