{
  "type": "Feature",
  "properties": {
    "iso:country":"CA",
    "sg:city":"Winnipeg",
    "sg:classifiers":[
        {
            "category":"Wholesale",
            "subcategory":"Electrical",
            "type":"Manufacturing & Wholesale Goods"
        }
    ],
    "sg:phone":"+1 204 633 7008",
    "sg:postcode":"R2R 0N1",
    "sg:province":"MB",
    "sg:tags":[
        "bearing",
        "electric"
    ],
    "wof:name":"B C Bearing Engineers Ltd",
    "wof:placetype":"venue"
},
  "geometry": {"coordinates":[-97.20697021479999,49.9245758057],"type":"Point"}
}