{
  "type": "Feature",
  "properties": {
    "addr:full":"505 Dupont St Toronto ON M6G 1Y6",
    "addr:housenumber":"505",
    "addr:postcode":"m6g 1y6",
    "addr:street":"Dupont St",
    "iso:country":"CA",
    "sg:address":"505 Dupont St",
    "sg:city":"Toronto",
    "sg:classifiers":[
        {
            "category":"Shopping",
            "subcategory":"Gifts & Souvenirs",
            "type":"Retail Goods"
        }
    ],
    "sg:phone":"+1 416 532 1162",
    "sg:postcode":"M6G 1Y6",
    "sg:province":"ON",
    "sg:tags":[
        "party",
        "supply"
    ],
    "wof:name":"Alligator Party Rentals",
    "wof:placetype":"venue"
},
  "geometry": {"coordinates":[-79.4159164429,43.6726951599],"type":"Point"}
}