{
  "type": "Feature",
  "properties": {
    "addr:full":"29 Cavan St Millbrook ON L0A 1G0",
    "addr:housenumber":"29",
    "addr:postcode":"l0a 1g0",
    "addr:street":"Cavan St",
    "iso:country":"CA",
    "sg:address":"29 Cavan St",
    "sg:city":"Millbrook",
    "sg:classifiers":[
        {
            "category":"Professional",
            "subcategory":"Art Services",
            "type":"Services"
        }
    ],
    "sg:phone":"+1 705 932 2211",
    "sg:postcode":"L0A 1G0",
    "sg:province":"ON",
    "sg:tags":[
        "artist"
    ],
    "wof:name":"Joe Weissmann Illustrator",
    "wof:placetype":"venue"
},
  "geometry": {"coordinates":[-78.454048,44.148247],"type":"Point"}
}