{
  "type": "Feature",
  "properties": {
    "addr:full":"Calgary AB T2C 2J4",
    "addr:postcode":"t2c 2j4",
    "iso:country":"CA",
    "sg:city":"Calgary",
    "sg:classifiers":[
        {
            "category":"Professional",
            "subcategory":"Management & Consulting",
            "type":"Services"
        }
    ],
    "sg:phone":"+1 403 720 0001",
    "sg:postcode":"T2C 2J4",
    "sg:province":"AB",
    "sg:tags":[
        "consultant",
        "instruction",
        "safety",
        "driving"
    ],
    "wof:name":"W T Safety Truck Driving Schl",
    "wof:placetype":"venue"
},
  "geometry": {"coordinates":[-113.981071472,50.9807128906],"type":"Point"}
}