{
  "type": "Feature",
  "properties": {
    "iso:country":"CA",
    "sg:city":"Hull",
    "sg:classifiers":[
        {
            "category":"Building & Trades",
            "subcategory":"Construction",
            "type":"Services"
        }
    ],
    "sg:phone":"+1 819 770 3141",
    "sg:postcode":"J8Y 6K9",
    "sg:province":"QC",
    "sg:tags":[
        "roofing",
        "contractor"
    ],
    "wof:name":"Reparation DE Toitures",
    "wof:placetype":"venue"
},
  "geometry": {"coordinates":[-75.710487,45.427853],"type":"Point"}
}