{
  "type": "Feature",
  "properties": {
    "addr:full":"1400 Ninth St N Kenora ON P9N 2T7",
    "addr:housenumber":"1400",
    "addr:postcode":"p9n 2t7",
    "addr:street":"Ninth St N",
    "iso:country":"CA",
    "sg:address":"1400 Ninth St N",
    "sg:city":"Kenora",
    "sg:classifiers":[
        {
            "category":"Education",
            "subcategory":"School",
            "type":"Public Place"
        }
    ],
    "sg:phone":"+1 807 468 6401",
    "sg:postcode":"P9N 2T7",
    "sg:province":"ON",
    "wof:name":"Beaver Brae Secondary School",
    "wof:placetype":"venue"
},
  "geometry": {"coordinates":[-94.46315,49.775887],"type":"Point"}
}