{
  "type": "Feature",
  "properties": {
    "iso:country":"CA",
    "sg:address":"228 University Park Dr",
    "sg:city":"Regina",
    "sg:classifiers":[
        {
            "category":"Health Services",
            "subcategory":"Doctor",
            "type":"Services"
        }
    ],
    "sg:phone":"+1 306 789 0827",
    "sg:postcode":"S4V 1A3",
    "sg:province":"SK",
    "sg:tags":[
        "dentist"
    ],
    "wof:name":"University Park Dental Office",
    "wof:placetype":"venue"
},
  "geometry": {"coordinates":[-104.556976318,50.4329338074],"type":"Point"}
}