{
  "type": "Feature",
  "properties": {
    "iso:country":"CA",
    "sg:address":"910 Columbia St W",
    "sg:city":"Kamloops",
    "sg:classifiers":[
        {
            "category":"Insurance",
            "subcategory":"Insurance Agent",
            "type":"Services"
        }
    ],
    "sg:phone":"+1 250 377 3093",
    "sg:postcode":"V2C 1L2",
    "sg:province":"BC",
    "wof:name":"Sussex Insurance",
    "wof:placetype":"venue"
},
  "geometry": {"coordinates":[-120.354576111,50.6682624817],"type":"Point"}
}