{
  "type": "Feature",
  "properties": {
    "addr:full":"11361 95 St NW Edmonton AB T5G 1L2",
    "addr:housenumber":"11361",
    "addr:postcode":"t5g 1l2",
    "addr:street":"95 St Nw",
    "iso:country":"CA",
    "sg:address":"11361 95 St NW",
    "sg:city":"Edmonton",
    "sg:classifiers":[
        {
            "category":"Food & Beverages",
            "subcategory":"Groceries & Convenience Stores",
            "type":"Retail Goods"
        }
    ],
    "sg:phone":"+1 780 477 3201",
    "sg:postcode":"T5G 1L2",
    "sg:province":"AB",
    "sg:tags":[
        "grocer"
    ],
    "wof:name":"Arden's Variety Food Mart",
    "wof:placetype":"venue"
},
  "geometry": {"coordinates":[-113.486930847,53.563621521],"type":"Point"}
}