{
  "type": "Feature",
  "properties": {
    "addr:full":"6495 Malden Rd Windsor ON N9H 1T4",
    "addr:housenumber":"6495",
    "addr:postcode":"n9h 1t4",
    "addr:street":"Malden Rd",
    "iso:country":"CA",
    "sg:address":"6495 Malden Rd",
    "sg:city":"Windsor",
    "sg:classifiers":[
        {
            "category":"Retail",
            "subcategory":"Auto Repair",
            "type":"Services"
        }
    ],
    "sg:phone":"+1 519 978 1221",
    "sg:postcode":"N9H 1T4",
    "sg:province":"ON",
    "sg:tags":[
        "repairing",
        "automobile",
        "dealer"
    ],
    "wof:name":"LA Salle Auto Sales & Svc",
    "wof:placetype":"venue"
},
  "geometry": {"coordinates":[-83.060593,42.251629],"type":"Point"}
}