{
  "type": "Feature",
  "properties": {
    "addr:full":"Vernon BC V1T 8B5",
    "addr:postcode":"v1t 8b5",
    "iso:country":"CA",
    "sg:city":"Vernon",
    "sg:classifiers":[
        {
            "category":"Health Services",
            "subcategory":"Medical Lab",
            "type":"Services"
        }
    ],
    "sg:phone":"+1 250 549 4745",
    "sg:postcode":"V1T 8B5",
    "sg:province":"BC",
    "wof:name":"Braun Denture Clinic",
    "wof:placetype":"venue"
},
  "geometry": {"coordinates":[-119.27729797400001,50.2631111145],"type":"Point"}
}