{
  "type": "Feature",
  "properties": {
    "addr:full":"834 Sheppard Ave W North York ON M3H 2T1",
    "addr:housenumber":"834",
    "addr:postcode":"m3h 2t1",
    "addr:street":"Sheppard Ave W",
    "iso:country":"CA",
    "sg:address":"834 Sheppard Ave W",
    "sg:city":"North York",
    "sg:classifiers":[
        {
            "category":"Personal",
            "type":"Services"
        }
    ],
    "sg:phone":"+1 416 631 0217",
    "sg:postcode":"M3H 2T1",
    "sg:province":"ON",
    "sg:tags":[
        "program",
        "physical",
        "exercise",
        "fitness"
    ],
    "wof:name":"Studio 21 Personal Trainer",
    "wof:placetype":"venue"
},
  "geometry": {"coordinates":[-79.45133209230001,43.7529449463],"type":"Point"}
}