{
  "type": "Feature",
  "properties": {
    "addr:full":"Armstrong BC V0E 1B1",
    "addr:postcode":"v0e 1b1",
    "iso:country":"CA",
    "sg:city":"Armstrong",
    "sg:classifiers":[
        {
            "category":"Sports & Exercise",
            "subcategory":"Gym",
            "type":"Entertainment"
        }
    ],
    "sg:phone":"+1 250 546 3230",
    "sg:postcode":"V0E 1B1",
    "sg:province":"BC",
    "sg:tags":[
        "club",
        "health",
        "studio",
        "gymnasium"
    ],
    "wof:name":"Curves For Women",
    "wof:placetype":"venue"
},
  "geometry": {"coordinates":[-119.184326,50.44215],"type":"Point"}
}