{
  "type": "Feature",
  "properties": {
    "iso:country":"CA",
    "sg:city":"Montreal",
    "sg:classifiers":[
        {
            "category":"Restaurant",
            "type":"Food & Drink"
        }
    ],
    "sg:phone":"+1 514 274 0919",
    "sg:postcode":"H2T 2M8",
    "sg:province":"QC",
    "sg:tags":[
        "shop",
        "coffee"
    ],
    "wof:name":"Cafe Arts",
    "wof:placetype":"venue"
},
  "geometry": {"coordinates":[-73.596802,45.521503],"type":"Point"}
}