{
  "type": "Feature",
  "properties": {
    "addr:full":"6120 Midfield Rd Mississauga ON L5P 1B1",
    "addr:housenumber":"6120",
    "addr:postcode":"l5p 1b1",
    "addr:street":"Midfield Rd",
    "iso:country":"CA",
    "sg:address":"6120 Midfield Rd",
    "sg:city":"Mississauga",
    "sg:classifiers":[
        {
            "category":"Building & Trades",
            "subcategory":"Equipment Rental",
            "type":"Services"
        }
    ],
    "sg:phone":"+1 905 677 3300",
    "sg:postcode":"L5P 1B1",
    "sg:province":"ON",
    "sg:tags":[
        "aircraft",
        "leasing",
        "charter"
    ],
    "wof:name":"Skyservice",
    "wof:placetype":"venue"
},
  "geometry": {"coordinates":[-79.64372299999999,43.588284],"type":"Point"}
}