{
  "type": "Feature",
  "properties": {
    "addr:full":"25 Linden St Toronto ON M4Y 1V5",
    "addr:housenumber":"25",
    "addr:postcode":"m4y 1v5",
    "addr:street":"Linden St",
    "iso:country":"CA",
    "sg:address":"25 Linden St",
    "sg:city":"Toronto",
    "sg:classifiers":[
        {
            "category":"Social Services",
            "subcategory":"Child Care",
            "type":"Services"
        }
    ],
    "sg:phone":"+1 416 960 9929",
    "sg:postcode":"M4Y 1V5",
    "sg:province":"ON",
    "wof:name":"Bouts D'Choux",
    "wof:placetype":"venue"
},
  "geometry": {"coordinates":[-79.377808,43.670265],"type":"Point"}
}