{
  "type": "Feature",
  "properties": {
    "addr:full":"23 Bayfield St Charlottetown PE C1A 2G3",
    "addr:housenumber":"23",
    "addr:postcode":"c1a 2g3",
    "addr:street":"Bayfield St",
    "iso:country":"CA",
    "sg:address":"23 Bayfield St",
    "sg:city":"Charlottetown",
    "sg:classifiers":[
        {
            "category":"Retail",
            "subcategory":"Auto Repair",
            "type":"Services"
        }
    ],
    "sg:phone":"+1 902 892 6652",
    "sg:postcode":"C1A 2G3",
    "sg:province":"PE",
    "sg:tags":[
        "repairing",
        "automobile"
    ],
    "wof:name":"Mac Leans Garage",
    "wof:placetype":"venue"
},
  "geometry": {"coordinates":[-63.1339111328,46.2384529114],"type":"Point"}
}