{
  "type": "Feature",
  "properties": {
    "addr:full":"938 Queens Ave Brandon MB R7A 1L7",
    "addr:housenumber":"938",
    "addr:postcode":"r7a 1l7",
    "addr:street":"Queens Ave",
    "iso:country":"CA",
    "sg:address":"938 Queens Ave",
    "sg:city":"Brandon",
    "sg:classifiers":[
        {
            "category":"Autos & Motor Vehicles",
            "subcategory":"Automobile Sales",
            "type":"Retail Goods"
        }
    ],
    "sg:phone":"+1 204 728 6915",
    "sg:postcode":"R7A 1L7",
    "sg:province":"MB",
    "sg:tags":[
        "car",
        "dealer"
    ],
    "wof:name":"European Auto Ltd",
    "wof:placetype":"venue"
},
  "geometry": {"coordinates":[-99.9501876831,49.8300971985],"type":"Point"}
}