{
  "type": "Feature",
  "properties": {
    "addr:full":"PO Box 201 STN Main Guelph ON N1H 6J9",
    "addr:housenumber":"po",
    "addr:postcode":"n1h 6j9",
    "addr:street":"Box 201 Stn",
    "iso:country":"CA",
    "sg:address":"PO Box 201 STN Main",
    "sg:city":"Guelph",
    "sg:classifiers":[
        {
            "category":"Professional",
            "subcategory":"Computer Services",
            "type":"Services"
        }
    ],
    "sg:phone":"+1 519 763 4244",
    "sg:postcode":"N1H 6J9",
    "sg:province":"ON",
    "sg:tags":[
        "leasing"
    ],
    "wof:name":"Vanguard Computers",
    "wof:placetype":"venue"
},
  "geometry": {"coordinates":[-80.2478713989,43.5445632935],"type":"Point"}
}