{
  "type": "Feature",
  "properties": {
    "addr:full":"120 Bayview Pky Newmarket ON L3Y 3W3",
    "addr:housenumber":"120",
    "addr:postcode":"l3y 3w3",
    "addr:street":"Bayview Pky",
    "iso:country":"CA",
    "sg:address":"120 Bayview Pky",
    "sg:city":"Newmarket",
    "sg:classifiers":[
        {
            "category":"Government",
            "subcategory":"Office",
            "type":"Public Place"
        }
    ],
    "sg:phone":"+1 905 895 1281",
    "sg:postcode":"L3Y 3W3",
    "sg:province":"ON",
    "sg:tags":[
        "village"
    ],
    "wof:name":"Lake Simcoe Region Cnsrvtn",
    "wof:placetype":"venue"
},
  "geometry": {"coordinates":[-79.456749,44.063251],"type":"Point"}
}