{
  "type": "Feature",
  "properties": {
    "addr:full":"Saskatoon SK S7N 4R3",
    "addr:postcode":"s7n 4r3",
    "iso:country":"CA",
    "sg:city":"Saskatoon",
    "sg:classifiers":[
        {
            "category":"Freight",
            "type":"Transportation"
        }
    ],
    "sg:phone":"+1 306 931 3455",
    "sg:postcode":"S7N 4R3",
    "sg:province":"SK",
    "sg:tags":[
        "trucking"
    ],
    "wof:name":"Ferster Truckin' Inc",
    "wof:placetype":"venue"
},
  "geometry": {"coordinates":[-106.579956055,52.1439971924],"type":"Point"}
}