{
  "type": "Feature",
  "properties": {
    "addr:full":"440 Pim St Sault Ste Marie ON P6B 2V1",
    "addr:housenumber":"440",
    "addr:postcode":"p6b 2v1",
    "addr:street":"Pim St",
    "iso:country":"CA",
    "sg:address":"440 Pim St",
    "sg:city":"Sault Ste Marie",
    "sg:classifiers":[
        {
            "category":"Bars & Pubs",
            "type":"Food & Drink"
        }
    ],
    "sg:phone":"+1 705 256 1551",
    "sg:postcode":"P6B 2V1",
    "sg:province":"ON",
    "wof:name":"Smack Daddy's Bar & Grill",
    "wof:placetype":"venue"
},
  "geometry": {"coordinates":[-84.319283,46.518978],"type":"Point"}
}