{
  "type": "Feature",
  "properties": {
    "iso:country":"CA",
    "sg:address":"3175 Thompson Pl",
    "sg:city":"West Vancouver",
    "sg:classifiers":[
        {
            "category":"Education",
            "subcategory":"School",
            "type":"Public Place"
        }
    ],
    "sg:phone":"+1 604 981 1260",
    "sg:postcode":"V7V 3E3",
    "sg:province":"BC",
    "wof:name":"West Bay Elementary School",
    "wof:placetype":"venue"
},
  "geometry": {"coordinates":[-123.20532989500001,49.3440322876],"type":"Point"}
}