{
  "type": "Feature",
  "properties": {
    "iso:country":"CA",
    "sg:address":"1325 Rue Jacques-Cartier S",
    "sg:city":"Farnham",
    "sg:classifiers":[
        {
            "category":"Wholesale",
            "subcategory":"Meat",
            "type":"Manufacturing & Wholesale Goods"
        }
    ],
    "sg:phone":"+1 450 293 3310",
    "sg:postcode":"J2N 1Y7",
    "sg:province":"QC",
    "sg:tags":[
        "butchering"
    ],
    "wof:name":"Boucherie Andre",
    "wof:placetype":"venue"
},
  "geometry": {"coordinates":[-72.9849700928,45.26537323],"type":"Point"}
}