{
  "type": "Feature",
  "properties": {
    "addr:full":"365 Norman St Timmins ON P4N 4B6",
    "addr:housenumber":"365",
    "addr:postcode":"p4n 4b6",
    "addr:street":"Norman St",
    "iso:country":"CA",
    "sg:address":"365 Norman St",
    "sg:city":"Timmins",
    "sg:classifiers":[
        {
            "category":"Organizations",
            "subcategory":"Religious Organization",
            "type":"Services"
        }
    ],
    "sg:phone":"+1 705 264 5838",
    "sg:postcode":"P4N 4B6",
    "sg:province":"ON",
    "sg:tags":[
        "church"
    ],
    "wof:name":"Paroisse St Dominique",
    "wof:placetype":"venue"
},
  "geometry": {"coordinates":[-81.3570175171,48.4799385071],"type":"Point"}
}