{
  "type": "Feature",
  "properties": {
    "addr:full":"11 Willow St Truro NS B2N 4Z5",
    "addr:housenumber":"11",
    "addr:postcode":"b2n 4z5",
    "addr:street":"Willow St",
    "iso:country":"CA",
    "sg:address":"11 Willow St",
    "sg:city":"Truro",
    "sg:classifiers":[
        {
            "category":"Home & Garden",
            "subcategory":"Building Materials",
            "type":"Retail Goods"
        }
    ],
    "sg:phone":"+1 902 895 5381",
    "sg:postcode":"B2N 4Z5",
    "sg:province":"NS",
    "sg:tags":[
        "glass",
        "window",
        "plate"
    ],
    "wof:name":"Standard Auto Glass",
    "wof:placetype":"venue"
},
  "geometry": {"coordinates":[-63.2868,45.365311],"type":"Point"}
}