{
  "type": "Feature",
  "properties": {
    "addr:full":"36 Ontario Rd Mitchell ON N0K 1N0",
    "addr:housenumber":"36",
    "addr:postcode":"n0k 1n0",
    "addr:street":"Ontario Rd",
    "iso:country":"CA",
    "sg:address":"36 Ontario Rd",
    "sg:city":"Mitchell",
    "sg:classifiers":[
        {
            "category":"Restaurant",
            "type":"Food & Drink"
        }
    ],
    "sg:phone":"+1 519 348 9533",
    "sg:postcode":"N0K 1N0",
    "sg:province":"ON",
    "wof:name":"Rose & Crown",
    "wof:placetype":"venue"
},
  "geometry": {"coordinates":[-81.19724273680001,43.4676094055],"type":"Point"}
}