{
  "type": "Feature",
  "properties": {
    "addr:full":"64 Rue Monseigneur-Tessier O Rouyn-Noranda QC J9X 2S4",
    "addr:housenumber":"64",
    "addr:postcode":"j9x 2s4",
    "addr:street":"Rue Monseigneur-Tessier O",
    "iso:country":"CA",
    "sg:address":"64 Rue Monseigneur-Tessier O",
    "sg:city":"Rouyn-Noranda",
    "sg:classifiers":[
        {
            "category":"Shopping",
            "subcategory":"Clothing, Apparel, & Fashions",
            "type":"Retail Goods"
        }
    ],
    "sg:phone":"+1 819 762 6670",
    "sg:postcode":"J9X 2S4",
    "sg:province":"QC",
    "sg:tags":[
        "fur",
        "business"
    ],
    "wof:name":"Fourrures Clement Boivin",
    "wof:placetype":"venue"
},
  "geometry": {"coordinates":[-79.014511,48.237076],"type":"Point"}
}