{
  "type": "Feature",
  "properties": {
    "iso:country":"CA",
    "sg:address":"458 Boul Salaberry N",
    "sg:city":"Chateauguay",
    "sg:classifiers":[
        {
            "category":"Building & Trades",
            "subcategory":"Construction",
            "type":"Services"
        }
    ],
    "sg:phone":"+1 450 699 9712",
    "sg:postcode":"J6J 4M3",
    "sg:province":"QC",
    "sg:tags":[
        "contractor"
    ],
    "wof:name":"Wedo Construction",
    "wof:placetype":"venue"
},
  "geometry": {"coordinates":[-73.7494812012,45.3960227966],"type":"Point"}
}