{
  "type": "Feature",
  "properties": {
    "addr:full":"24 Guided Crt Etobicoke ON M9V 4K6",
    "addr:housenumber":"24",
    "addr:postcode":"m9v 4k6",
    "addr:street":"Guided Crt",
    "iso:country":"CA",
    "sg:address":"24 Guided Crt",
    "sg:city":"Etobicoke",
    "sg:classifiers":[
        {
            "category":"Manufacturing",
            "subcategory":"Printing",
            "type":"Manufacturing & Wholesale Goods"
        }
    ],
    "sg:phone":"+1 416 748 5866",
    "sg:postcode":"M9V 4K6",
    "sg:province":"ON",
    "sg:tags":[
        "printer"
    ],
    "wof:name":"Ink & Foil Printing",
    "wof:placetype":"venue"
},
  "geometry": {"coordinates":[-79.60828399659999,43.7542076111],"type":"Point"}
}