{
  "type": "Feature",
  "properties": {
    "iso:country":"CA",
    "sg:address":"1927 Kemptown St",
    "sg:city":"Truro",
    "sg:classifiers":[
        {
            "category":"Manufacturing",
            "subcategory":"Lumber",
            "type":"Manufacturing & Wholesale Goods"
        }
    ],
    "sg:phone":"+1 902 657 3711",
    "sg:postcode":"B2N 5B1",
    "sg:province":"NS",
    "sg:tags":[
        "syrup",
        "maple",
        "sugar"
    ],
    "wof:name":"Kirmac Maple Products",
    "wof:placetype":"venue"
},
  "geometry": {"coordinates":[-63.2890396118,45.3660202026],"type":"Point"}
}