{
  "type": "Feature",
  "properties": {
    "addr:full":"1302 Shoppers Park Mall Grande Cache AB T0E 0Y0",
    "addr:housenumber":"1302",
    "addr:postcode":"t0e 0y0",
    "addr:street":"Shoppers Park Mall Grande",
    "iso:country":"CA",
    "sg:address":"1302 Shoppers Park Mall",
    "sg:city":"Grande Cache",
    "sg:classifiers":[
        {
            "category":"Food & Beverages",
            "subcategory":"Groceries & Convenience Stores",
            "type":"Retail Goods"
        }
    ],
    "sg:phone":"+1 780 827 3825",
    "sg:postcode":"T0E 0Y0",
    "sg:province":"AB",
    "wof:name":"Chalet Food Stores Ltd",
    "wof:placetype":"venue"
},
  "geometry": {"coordinates":[-119.115242004,53.8899154663],"type":"Point"}
}