{
  "type": "Feature",
  "properties": {
    "addr:full":"Cambridge ON N3C 2A7",
    "addr:postcode":"n3c 2a7",
    "iso:country":"CA",
    "sg:city":"Cambridge",
    "sg:classifiers":[
        {
            "category":"Restaurant",
            "type":"Food & Drink"
        }
    ],
    "sg:phone":"+1 519 658 9242",
    "sg:postcode":"N3C 2A7",
    "sg:province":"ON",
    "wof:name":"Papou's Place",
    "wof:placetype":"venue"
},
  "geometry": {"coordinates":[-80.310776,43.431442],"type":"Point"}
}