{
  "type": "Feature",
  "properties": {
    "addr:full":"20 King St E Hamilton ON L8N 1A3",
    "addr:housenumber":"20",
    "addr:postcode":"l8n 1a3",
    "addr:street":"King St E",
    "iso:country":"CA",
    "sg:address":"20 King St E",
    "sg:city":"Hamilton",
    "sg:classifiers":[
        {
            "category":"Shopping",
            "subcategory":"Discount & Variety Stores",
            "type":"Retail Goods"
        }
    ],
    "sg:phone":"+1 905 308 9933",
    "sg:postcode":"L8N 1A3",
    "sg:province":"ON",
    "wof:name":"Town Convenience",
    "wof:placetype":"venue"
},
  "geometry": {"coordinates":[-79.868759,43.25602],"type":"Point"}
}