{
  "type": "Feature",
  "properties": {
    "addr:full":"Calgary AB T2R 1M6",
    "addr:postcode":"t2r 1m6",
    "iso:country":"CA",
    "sg:city":"Calgary",
    "sg:classifiers":[
        {
            "category":"Manufacturing",
            "subcategory":"Tools & Machinery",
            "type":"Manufacturing & Wholesale Goods"
        }
    ],
    "sg:phone":"+1 403 244 3901",
    "sg:postcode":"T2R 1M6",
    "sg:province":"AB",
    "sg:tags":[
        "battery",
        "equipment",
        "charging"
    ],
    "wof:name":"Bmi Technologies Inc",
    "wof:placetype":"venue"
},
  "geometry": {"coordinates":[-114.081833,51.040615],"type":"Point"}
}