{
  "type": "Feature",
  "properties": {
    "addr:full":"320 Arena Ave Trochu AB T0M 2C0",
    "addr:housenumber":"320",
    "addr:postcode":"t0m 2c0",
    "addr:street":"Arena Ave",
    "iso:country":"CA",
    "sg:address":"320 Arena Ave",
    "sg:city":"Trochu",
    "sg:classifiers":[
        {
            "category":"Insurance",
            "subcategory":"Insurance Agent",
            "type":"Services"
        }
    ],
    "sg:phone":"+1 403 442 3747",
    "sg:postcode":"T0M 2C0",
    "sg:province":"AB",
    "wof:name":"Simpson Insurance Ltd",
    "wof:placetype":"venue"
},
  "geometry": {"coordinates":[-113.227760315,51.8263549805],"type":"Point"}
}