{
  "type": "Feature",
  "properties": {
    "addr:full":"1591 9E Av Grand-Mere QC G9T 1X5",
    "addr:housenumber":"1591",
    "addr:postcode":"g9t 1x5",
    "addr:street":"9E Av Grand-Mere",
    "iso:country":"CA",
    "sg:address":"1591 9E Av",
    "sg:city":"Grand-Mere",
    "sg:classifiers":[
        {
            "category":"Shopping",
            "subcategory":"Bicycles & Sporting Goods",
            "type":"Retail Goods"
        }
    ],
    "sg:phone":"+1 819 538 8205",
    "sg:postcode":"G9T 1X5",
    "sg:province":"QC",
    "sg:tags":[
        "tackle",
        "fishing"
    ],
    "wof:name":"Villemure Chasse & Peche Inc",
    "wof:placetype":"venue"
},
  "geometry": {"coordinates":[-72.7070770264,46.6078338623],"type":"Point"}
}