{
  "type": "Feature",
  "properties": {
    "addr:full":"5 Coupar Terr Truro NS B2N 4Z3",
    "addr:housenumber":"5",
    "addr:postcode":"b2n 4z3",
    "addr:street":"Coupar Terr",
    "iso:country":"CA",
    "sg:address":"5 Coupar Terr",
    "sg:city":"Truro",
    "sg:classifiers":[
        {
            "category":"Organizations",
            "subcategory":"Religious Organization",
            "type":"Services"
        }
    ],
    "sg:phone":"+1 902 897 0015",
    "sg:postcode":"B2N 4Z3",
    "sg:province":"NS",
    "sg:tags":[
        "church"
    ],
    "wof:name":"St George's Anglican Church",
    "wof:placetype":"venue"
},
  "geometry": {"coordinates":[-63.28904,45.36602],"type":"Point"}
}