{
  "type": "Feature",
  "properties": {
    "addr:full":"16896 Rue Des Prairies Mirabel QC J7J 2A3",
    "addr:housenumber":"16896",
    "addr:postcode":"j7j 2a3",
    "addr:street":"Rue Des Prairies",
    "iso:country":"CA",
    "sg:address":"16896 Rue Des Prairies",
    "sg:city":"Mirabel",
    "sg:classifiers":[
        {
            "category":"Autos & Motor Vehicles",
            "subcategory":"Motorcycle Sales",
            "type":"Retail Goods"
        }
    ],
    "sg:phone":"+1 450 475 8107",
    "sg:postcode":"J7J 2A3",
    "sg:province":"QC",
    "sg:tags":[
        "snowmobile"
    ],
    "wof:name":"Mecanique Plus Enr",
    "wof:placetype":"venue"
},
  "geometry": {"coordinates":[-73.94705200200001,45.6500854492],"type":"Point"}
}