{
  "type": "Feature",
  "properties": {
    "iso:country":"CA",
    "sg:address":"4707 Fountain Dr",
    "sg:city":"Red Deer",
    "sg:classifiers":[
        {
            "category":"Organizations",
            "subcategory":"Professional Association",
            "type":"Services"
        }
    ],
    "sg:phone":"+1 403 346 0055",
    "sg:postcode":"T4N 6Z8",
    "sg:province":"AB",
    "sg:tags":[
        "government"
    ],
    "wof:name":"Cronquist House",
    "wof:placetype":"venue"
},
  "geometry": {"coordinates":[-113.837562561,52.2678146362],"type":"Point"}
}