{
  "type": "Feature",
  "properties": {
    "addr:full":"1923 Eglinton Ave W York ON M6E 2J7",
    "addr:housenumber":"1923",
    "addr:postcode":"m6e 2j7",
    "addr:street":"Eglinton Ave W",
    "iso:country":"CA",
    "sg:address":"1923 Eglinton Ave W",
    "sg:city":"York",
    "sg:classifiers":[
        {
            "category":"Food & Beverages",
            "subcategory":"Specialty",
            "type":"Retail Goods"
        }
    ],
    "sg:phone":"+1 416 783 3093",
    "sg:postcode":"M6E 2J7",
    "sg:province":"ON",
    "sg:tags":[
        "health",
        "diet"
    ],
    "wof:name":"Life Essential Health Food",
    "wof:placetype":"venue"
},
  "geometry": {"coordinates":[-79.4524765015,43.6950645447],"type":"Point"}
}