{
  "type": "Feature",
  "properties": {
    "iso:country":"CA",
    "sg:address":"10247 178 St NW",
    "sg:city":"Edmonton",
    "sg:classifiers":[
        {
            "category":"Insurance",
            "subcategory":"Insurance Agent",
            "type":"Services"
        }
    ],
    "sg:phone":"+1 780 483 8785",
    "sg:postcode":"T5S 1M3",
    "sg:province":"AB",
    "wof:name":"Weinstein Insurance",
    "wof:placetype":"venue"
},
  "geometry": {"coordinates":[-113.627159,53.544247],"type":"Point"}
}