{
  "type": "Feature",
  "properties": {
    "addr:full":"10247 178 St NW Edmonton AB T5S 1M3",
    "addr:housenumber":"10247",
    "addr:postcode":"t5s 1m3",
    "addr:street":"178 St Nw",
    "iso:country":"CA",
    "sg:address":"10247 178 St NW",
    "sg:city":"Edmonton",
    "sg:classifiers":[
        {
            "category":"Insurance",
            "subcategory":"Insurance Agent",
            "type":"Services"
        }
    ],
    "sg:phone":"+1 780 483 8785",
    "sg:postcode":"T5S 1M3",
    "sg:province":"AB",
    "wof:name":"Weinstein Insurance",
    "wof:placetype":"venue"
},
  "geometry": {"coordinates":[-113.62715900000001,53.544247],"type":"Point"}
}