{
  "type": "Feature",
  "properties": {
    "iso:country":"CA",
    "sg:address":"215 Ontario St S",
    "sg:city":"Milton",
    "sg:classifiers":[
        {
            "category":"Education",
            "subcategory":"School",
            "type":"Public Place"
        }
    ],
    "sg:phone":"+1 905 878 0575",
    "sg:postcode":"L9T 4N5",
    "sg:province":"ON",
    "wof:name":"E C Drury High School",
    "wof:placetype":"venue"
},
  "geometry": {"coordinates":[-79.87162780760001,43.5141601562],"type":"Point"}
}