{
  "type": "Feature",
  "properties": {
    "addr:full":"Richmond BC V6X 3A6",
    "addr:postcode":"v6x 3a6",
    "iso:country":"CA",
    "sg:city":"Richmond",
    "sg:classifiers":[
        {
            "category":"Personal",
            "subcategory":"Hair Removal",
            "type":"Services"
        }
    ],
    "sg:phone":"+1 604 303 7003",
    "sg:postcode":"V6X 3A6",
    "sg:province":"BC",
    "sg:tags":[
        "removing",
        "laser",
        "treatment"
    ],
    "wof:name":"Dermalite Laser Ctr Ltd",
    "wof:placetype":"venue"
},
  "geometry": {"coordinates":[-123.13621500000001,49.179062],"type":"Point"}
}