{
  "type": "Feature",
  "properties": {
    "addr:full":"10640 Av Vianney Montreal QC H2B 2X9",
    "addr:housenumber":"10640",
    "addr:postcode":"h2b 2x9",
    "addr:street":"Av Vianney",
    "iso:country":"CA",
    "sg:address":"10640 Av Vianney",
    "sg:city":"Montreal",
    "sg:classifiers":[
        {
            "category":"Health Services",
            "subcategory":"Health Practitioner",
            "type":"Services"
        }
    ],
    "sg:phone":"+1 514 384 2228",
    "sg:postcode":"H2B 2X9",
    "sg:province":"QC",
    "sg:tags":[
        "psychologist"
    ],
    "wof:name":"Lemieux, Michel",
    "wof:placetype":"venue"
},
  "geometry": {"coordinates":[-73.65089399999999,45.579533],"type":"Point"}
}