{
  "type": "Feature",
  "properties": {
    "addr:full":"58 Bedford Hwy Halifax NS B3M 2J2",
    "addr:housenumber":"58",
    "addr:postcode":"b3m 2j2",
    "addr:street":"Bedford Hwy",
    "iso:country":"CA",
    "sg:address":"58 Bedford Hwy",
    "sg:city":"Halifax",
    "sg:classifiers":[
        {
            "category":"Professional",
            "subcategory":"Accounting & Tax Preparation",
            "type":"Services"
        }
    ],
    "sg:phone":"+1 902 445 4446",
    "sg:postcode":"B3M 2J2",
    "sg:province":"NS",
    "sg:tags":[
        "accountant"
    ],
    "wof:name":"Mac Lean, Stuart CA",
    "wof:placetype":"venue"
},
  "geometry": {"coordinates":[-63.635719,44.665249],"type":"Point"}
}