{
  "type": "Feature",
  "properties": {
    "iso:country":"CA",
    "sg:address":"1050 Boul Saint-Joseph",
    "sg:city":"Hull",
    "sg:classifiers":[
        {
            "category":"Autos & Motor Vehicles",
            "subcategory":"Fuel & Gas Station",
            "type":"Retail Goods"
        }
    ],
    "sg:phone":"+1 819 772 4194",
    "sg:postcode":"J8Z 1T3",
    "sg:province":"QC",
    "sg:tags":[
        "oil"
    ],
    "wof:name":"Libre Service Shell",
    "wof:placetype":"venue"
},
  "geometry": {"coordinates":[-75.7384338379,45.4710426331],"type":"Point"}
}