{
  "type": "Feature",
  "properties": {
    "iso:country":"CA",
    "sg:address":"36005 97th St",
    "sg:city":"Oliver",
    "sg:classifiers":[
        {
            "category":"Health Services",
            "subcategory":"Doctor",
            "type":"Services"
        }
    ],
    "sg:phone":"+1 250 498 3411",
    "sg:postcode":"V0H 1T0",
    "sg:province":"BC",
    "sg:tags":[
        "physician",
        "surgeon"
    ],
    "wof:name":"Main Street Medical Ctr",
    "wof:placetype":"venue"
},
  "geometry": {"coordinates":[-119.55023956300001,49.1843299866],"type":"Point"}
}