{
  "type": "Feature",
  "properties": {
    "addr:full":"2 May St #A Parry Sound ON P2A 1S2",
    "addr:housenumber":"2",
    "addr:postcode":"p2a 1s2",
    "addr:street":"May St # A",
    "iso:country":"CA",
    "sg:address":"2 May St #A",
    "sg:city":"Parry Sound",
    "sg:classifiers":[
        {
            "category":"Health Services",
            "subcategory":"Hospital",
            "type":"Services"
        }
    ],
    "sg:phone":"+1 705 746 4293",
    "sg:postcode":"P2A 1S2",
    "sg:province":"ON",
    "sg:tags":[
        "organization",
        "social",
        "mental",
        "welfare"
    ],
    "wof:name":"Algonquin Child & Family Svc",
    "wof:placetype":"venue"
},
  "geometry": {"coordinates":[-80.0384063721,45.3564186096],"type":"Point"}
}