{
  "type": "Feature",
  "properties": {
    "addr:full":"Winnipeg MB R3C 4L8",
    "addr:postcode":"r3c 4l8",
    "iso:country":"CA",
    "sg:city":"Winnipeg",
    "sg:classifiers":[
        {
            "category":"Restaurant",
            "type":"Food & Drink"
        }
    ],
    "sg:phone":"+1 204 947 5485",
    "sg:postcode":"R3C 4L8",
    "sg:province":"MB",
    "sg:tags":[
        "parlor",
        "ice",
        "cream"
    ],
    "wof:name":"Neon Cone",
    "wof:placetype":"venue"
},
  "geometry": {"coordinates":[-97.1312484741,49.8879585266],"type":"Point"}
}