{
  "type": "Feature",
  "properties": {
    "addr:full":"Peterborough ON K9J 6X7",
    "addr:postcode":"k9j 6x7",
    "iso:country":"CA",
    "sg:city":"Peterborough",
    "sg:classifiers":[
        {
            "category":"Wholesale",
            "subcategory":"Machinery & Supplies",
            "type":"Manufacturing & Wholesale Goods"
        }
    ],
    "sg:phone":"+1 705 741 6447",
    "sg:postcode":"K9J 6X7",
    "sg:province":"ON",
    "sg:tags":[
        "abrasive"
    ],
    "wof:name":"Pearl Abrasives CO",
    "wof:placetype":"venue"
},
  "geometry": {"coordinates":[-78.29323599999999,44.276146],"type":"Point"}
}