{
  "type": "Feature",
  "properties": {
    "addr:full":"Calgary AB T2E 7P6",
    "addr:postcode":"t2e 7p6",
    "iso:country":"CA",
    "sg:city":"Calgary",
    "sg:classifiers":[
        {
            "category":"Utilities",
            "subcategory":"Mobile Phone",
            "type":"Services"
        }
    ],
    "sg:phone":"+1 403 274 7937",
    "sg:postcode":"T2E 7P6",
    "sg:province":"AB",
    "sg:tags":[
        "telephone",
        "cellular"
    ],
    "wof:name":"Cellular Wholesaling CO Inc",
    "wof:placetype":"venue"
},
  "geometry": {"coordinates":[-114.017021,51.079536],"type":"Point"}
}