{
  "type": "Feature",
  "properties": {
    "addr:full":"370 N Service Rd Moose Jaw SK S6H 4N9",
    "addr:housenumber":"370",
    "addr:postcode":"s6h 4n9",
    "addr:street":"N Service Rd",
    "iso:country":"CA",
    "sg:address":"370 N Service Rd",
    "sg:city":"Moose Jaw",
    "sg:classifiers":[
        {
            "category":"Autos & Motor Vehicles",
            "subcategory":"Fuel & Gas Station",
            "type":"Retail Goods"
        }
    ],
    "sg:phone":"+1 306 693 5858",
    "sg:postcode":"S6H 4N9",
    "sg:province":"SK",
    "sg:tags":[
        "oil"
    ],
    "wof:name":"Shell Canada Products Ltd",
    "wof:placetype":"venue"
},
  "geometry": {"coordinates":[-105.545372,50.426498],"type":"Point"}
}