{
  "type": "Feature",
  "properties": {
    "addr:full":"1795 St Laurent Blvd Ottawa ON K1G 3V4",
    "addr:housenumber":"1795",
    "addr:postcode":"k1g 3v4",
    "addr:street":"St Laurent Blvd",
    "iso:country":"CA",
    "sg:address":"1795 St Laurent Blvd",
    "sg:city":"Ottawa",
    "sg:classifiers":[
        {
            "category":"Building & Trades",
            "subcategory":"Construction",
            "type":"Services"
        }
    ],
    "sg:phone":"+1 613 731 0552",
    "sg:postcode":"K1G 3V4",
    "sg:province":"ON",
    "sg:tags":[
        "general",
        "contractor"
    ],
    "wof:name":"Bulwark Construction Ltd",
    "wof:placetype":"venue"
},
  "geometry": {"coordinates":[-75.62580871580001,45.4042167664],"type":"Point"}
}