{
  "type": "Feature",
  "properties": {
    "addr:full":"Red Deer AB T4N 1X9",
    "addr:postcode":"t4n 1x9",
    "iso:country":"CA",
    "sg:city":"Red Deer",
    "sg:classifiers":[
        {
            "category":"Shopping",
            "type":"Retail Goods"
        }
    ],
    "sg:phone":"+1 403 340 8320",
    "sg:postcode":"T4N 1X9",
    "sg:province":"AB",
    "sg:tags":[
        "coin",
        "dealer",
        "supply"
    ],
    "wof:name":"Red Deer Stamps & Coins",
    "wof:placetype":"venue"
},
  "geometry": {"coordinates":[-113.812828064,52.2688903809],"type":"Point"}
}