{
  "type": "Feature",
  "properties": {
    "addr:full":"3215 Main St Salisbury NB E4J 2K7",
    "addr:housenumber":"3215",
    "addr:postcode":"e4j 2k7",
    "addr:street":"Main St",
    "iso:country":"CA",
    "sg:address":"3215 Main St",
    "sg:city":"Salisbury",
    "sg:classifiers":[
        {
            "category":"Education",
            "subcategory":"Library",
            "type":"Public Place"
        }
    ],
    "sg:phone":"+1 506 372 3240",
    "sg:postcode":"E4J 2K7",
    "sg:province":"NB",
    "wof:name":"Salisbury Library",
    "wof:placetype":"venue"
},
  "geometry": {"coordinates":[-65.049599,46.025219],"type":"Point"}
}