{
  "type": "Feature",
  "properties": {
    "addr:full":"196 Brooke Ave North York ON M5M 2K6",
    "addr:housenumber":"196",
    "addr:postcode":"m5m 2k6",
    "addr:street":"Brooke Ave",
    "iso:country":"CA",
    "sg:address":"196 Brooke Ave",
    "sg:city":"North York",
    "sg:classifiers":[
        {
            "category":"Organizations",
            "subcategory":"Professional Association",
            "type":"Services"
        }
    ],
    "sg:phone":"+1 416 787 9802",
    "sg:postcode":"M5M 2K6",
    "sg:province":"ON",
    "sg:tags":[
        "foundation"
    ],
    "wof:name":"Thomas J Johnston Foundation",
    "wof:placetype":"venue"
},
  "geometry": {"coordinates":[-79.41757200000001,43.733776],"type":"Point"}
}