{
  "type": "Feature",
  "properties": {
    "iso:country":"CA",
    "sg:address":"87 Ormond St N",
    "sg:city":"Thorold",
    "sg:classifiers":[
        {
            "category":"Retail",
            "subcategory":"Auto Repair",
            "type":"Services"
        }
    ],
    "sg:phone":"+1 905 227 5772",
    "sg:postcode":"L2V 1Z3",
    "sg:province":"ON",
    "sg:tags":[
        "body",
        "automobile",
        "painting"
    ],
    "wof:name":"Red's Auto Body",
    "wof:placetype":"venue"
},
  "geometry": {"coordinates":[-79.1994934082,43.1311607361],"type":"Point"}
}