{
  "type": "Feature",
  "properties": {
    "addr:full":"North York ON M6A 2A4",
    "addr:postcode":"m6a 2a4",
    "iso:country":"CA",
    "sg:city":"North York",
    "sg:classifiers":[
        {
            "category":"Real Estate",
            "subcategory":"Real Estate Operator",
            "type":"Services"
        }
    ],
    "sg:phone":"+1 416 781 3783",
    "sg:postcode":"M6A 2A4",
    "sg:province":"ON",
    "sg:tags":[
        "management",
        "apartment"
    ],
    "wof:name":"Village Gardens",
    "wof:placetype":"venue"
},
  "geometry": {"coordinates":[-79.4298171997,43.7203903198],"type":"Point"}
}