{
  "type": "Feature",
  "properties": {
    "iso:country":"CA",
    "sg:address":"30 Kerrison Dr W",
    "sg:city":"Ajax",
    "sg:classifiers":[
        {
            "category":"Education",
            "subcategory":"School",
            "type":"Public Place"
        }
    ],
    "sg:phone":"+1 905 686 2135",
    "sg:postcode":"L1Z 1K1",
    "sg:province":"ON",
    "wof:name":"Terry Fox Public School",
    "wof:placetype":"venue"
},
  "geometry": {"coordinates":[-79.02694702150001,43.870174408],"type":"Point"}
}