{
  "type": "Feature",
  "properties": {
    "addr:full":"1508 Columbia Ave Port Coquitlam BC V3C 1C3",
    "addr:housenumber":"1508",
    "addr:postcode":"v3c 1c3",
    "addr:street":"Columbia Ave",
    "iso:country":"CA",
    "sg:address":"1508 Columbia Ave",
    "sg:city":"Port Coquitlam",
    "sg:classifiers":[
        {
            "category":"Cinema",
            "subcategory":"Movie Rental",
            "type":"Entertainment"
        }
    ],
    "sg:phone":"+1 604 945 5734",
    "sg:postcode":"V3C 1C3",
    "sg:province":"BC",
    "sg:tags":[
        "leasing",
        "video",
        "disc",
        "tape"
    ],
    "wof:name":"Columbia Video",
    "wof:placetype":"venue"
},
  "geometry": {"coordinates":[-122.775390625,49.2419776917],"type":"Point"}
}