{
  "type": "Feature",
  "properties": {
    "addr:full":"65 Dewdney Ave Winnipeg MB R3B 0E1",
    "addr:housenumber":"65",
    "addr:postcode":"r3b 0e1",
    "addr:street":"Dewdney Ave",
    "iso:country":"CA",
    "sg:address":"65 Dewdney Ave",
    "sg:city":"Winnipeg",
    "sg:classifiers":[
        {
            "category":"Professional",
            "subcategory":"Management & Consulting",
            "type":"Services"
        }
    ],
    "sg:phone":"+1 204 949 5150",
    "sg:postcode":"R3B 0E1",
    "sg:province":"MB",
    "sg:tags":[
        "consultant",
        "business"
    ],
    "wof:name":"P M Assoc Ltd",
    "wof:placetype":"venue"
},
  "geometry": {"coordinates":[-97.116364,49.901302],"type":"Point"}
}