{
  "type": "Feature",
  "properties": {
    "addr:full":"7942 51 St SE Calgary AB T2C 4R2",
    "addr:housenumber":"7942",
    "addr:postcode":"t2c 4r2",
    "addr:street":"51 St Se",
    "iso:country":"CA",
    "sg:address":"7942 51 St SE",
    "sg:city":"Calgary",
    "sg:classifiers":[
        {
            "category":"Wholesale",
            "subcategory":"Hardware",
            "type":"Manufacturing & Wholesale Goods"
        }
    ],
    "sg:phone":"+1 403 219 0600",
    "sg:postcode":"T2C 4R2",
    "sg:province":"AB",
    "sg:tags":[
        "fastener"
    ],
    "wof:name":"Mattic Industries Ltd",
    "wof:placetype":"venue"
},
  "geometry": {"coordinates":[-113.959915,50.981983],"type":"Point"}
}