{
  "type": "Feature",
  "properties": {
    "addr:full":"Drayton Valley AB T7A 1R7",
    "addr:postcode":"t7a 1r7",
    "addr:street":"Drayton",
    "iso:country":"CA",
    "sg:city":"Drayton Valley",
    "sg:classifiers":[
        {
            "category":"Retail",
            "subcategory":"Auto Repair",
            "type":"Services"
        }
    ],
    "sg:phone":"+1 780 542 3455",
    "sg:postcode":"T7A 1R7",
    "sg:province":"AB",
    "sg:tags":[
        "repairing",
        "automobile"
    ],
    "wof:name":"Mar-Lin Holdings Ltd",
    "wof:placetype":"venue"
},
  "geometry": {"coordinates":[-114.98249800000001,53.228699],"type":"Point"}
}