{
  "type": "Feature",
  "properties": {
    "addr:full":"307 Main W Atikokan ON P0T 1C0",
    "addr:housenumber":"307",
    "addr:postcode":"p0t 1c0",
    "addr:street":"Main W Atikokan",
    "iso:country":"CA",
    "sg:address":"307 Main W",
    "sg:city":"Atikokan",
    "sg:classifiers":[
        {
            "category":"Organizations",
            "subcategory":"Professional Association",
            "type":"Services"
        }
    ],
    "sg:phone":"+1 807 597 1213",
    "sg:postcode":"P0T 1C0",
    "sg:province":"ON",
    "sg:tags":[
        "social",
        "welfare"
    ],
    "wof:name":"Atikokan Native Friendship Ctr",
    "wof:placetype":"venue"
},
  "geometry": {"coordinates":[-91.62492370610001,48.7573814392],"type":"Point"}
}