{
  "type": "Feature",
  "properties": {
    "addr:full":"Vancouver BC V6B 6E3",
    "addr:postcode":"v6b 6e3",
    "iso:country":"CA",
    "sg:city":"Vancouver",
    "sg:classifiers":[
        {
            "category":"Organizations",
            "subcategory":"Community Association",
            "type":"Services"
        }
    ],
    "sg:phone":"+1 604 684 3926",
    "sg:postcode":"V6B 6E3",
    "sg:province":"BC",
    "sg:tags":[
        "club"
    ],
    "wof:name":"Bryan Adams Fan Club",
    "wof:placetype":"venue"
},
  "geometry": {"coordinates":[-123.104614258,49.2811965942],"type":"Point"}
}