{
  "type": "Feature",
  "properties": {
    "iso:country":"CA",
    "sg:address":"923 Ch Des Anglais",
    "sg:city":"Mascouche",
    "sg:classifiers":[
        {
            "category":"Home & Garden",
            "subcategory":"Household Appliances",
            "type":"Retail Goods"
        }
    ],
    "sg:phone":"+1 450 968 1155",
    "sg:postcode":"J7L 3R8",
    "sg:province":"QC",
    "sg:tags":[
        "machine",
        "sewing",
        "attachment"
    ],
    "wof:name":"Claude Duval Enr",
    "wof:placetype":"venue"
},
  "geometry": {"coordinates":[-73.645493,45.744431],"type":"Point"}
}