{
  "type": "Feature",
  "properties": {
    "addr:full":"222 Ridley Blvd Toronto ON M5M 3M6",
    "addr:housenumber":"222",
    "addr:postcode":"m5m 3m6",
    "addr:street":"Ridley Blvd",
    "iso:country":"CA",
    "sg:address":"222 Ridley Blvd",
    "sg:city":"Toronto",
    "sg:classifiers":[
        {
            "category":"Organizations",
            "subcategory":"Religious Organization",
            "type":"Services"
        }
    ],
    "sg:phone":"+1 416 485 7781",
    "sg:postcode":"M5M 3M6",
    "sg:province":"ON",
    "sg:tags":[
        "church"
    ],
    "wof:name":"St Margaret",
    "wof:placetype":"venue"
},
  "geometry": {"coordinates":[-79.421875,43.738537],"type":"Point"}
}