{
  "type": "Feature",
  "properties": {
    "iso:country":"CA",
    "sg:address":"5322 Yonge St",
    "sg:city":"North York",
    "sg:classifiers":[
        {
            "category":"Shopping",
            "type":"Retail Goods"
        }
    ],
    "sg:phone":"+1 416 223 7383",
    "sg:postcode":"M2N 5P9",
    "sg:province":"ON",
    "sg:tags":[
        "art",
        "gallery",
        "dealer"
    ],
    "wof:name":"Gallery Sunami",
    "wof:placetype":"venue"
},
  "geometry": {"coordinates":[-79.4140777588,43.7732620239],"type":"Point"}
}