{
  "type": "Feature",
  "properties": {
    "iso:country":"CA",
    "sg:address":"2229 Boul Barrette",
    "sg:city":"Lourdes-DE-Joliette",
    "sg:classifiers":[
        {
            "category":"Retail",
            "subcategory":"Funeral Services",
            "type":"Services"
        }
    ],
    "sg:phone":"+1 450 755 5494",
    "sg:postcode":"J0K 1K0",
    "sg:province":"QC",
    "sg:tags":[
        "director"
    ],
    "wof:name":"Residence Funeraire Coop",
    "wof:placetype":"venue"
},
  "geometry": {"coordinates":[-73.4419555664,46.0235710144],"type":"Point"}
}