{
  "type": "Feature",
  "properties": {
    "addr:full":"3100 Boul Ford Chateauguay QC J6J 4Z2",
    "addr:housenumber":"3100",
    "addr:postcode":"j6j 4z2",
    "addr:street":"Boul Ford",
    "iso:country":"CA",
    "sg:address":"3100 Boul Ford",
    "sg:city":"Chateauguay",
    "sg:classifiers":[
        {
            "category":"Autos & Motor Vehicles",
            "subcategory":"Auto Supplies",
            "type":"Retail Goods"
        }
    ],
    "sg:phone":"+1 450 691 0002",
    "sg:postcode":"J6J 4Z2",
    "sg:province":"QC",
    "sg:tags":[
        "filter",
        "gas"
    ],
    "wof:name":"Bon Air Fabrication Inc",
    "wof:placetype":"venue"
},
  "geometry": {"coordinates":[-73.676903,45.343159],"type":"Point"}
}