{
  "type": "Feature",
  "properties": {
    "addr:full":"243 41 Ave NE Calgary AB T2E 2N4",
    "addr:postcode":"t2e 2n4",
    "addr:street":"243 41 Ave Ne",
    "iso:country":"CA",
    "sg:address":"243 41 Ave NE",
    "sg:city":"Calgary",
    "sg:classifiers":[
        {
            "category":"Wholesale",
            "subcategory":"Auto Parts",
            "type":"Manufacturing & Wholesale Goods"
        }
    ],
    "sg:phone":"+1 403 276 9187",
    "sg:postcode":"T2E 2N4",
    "sg:province":"AB",
    "sg:tags":[
        "automobile",
        "rebuilt"
    ],
    "wof:name":"A-1 Mc Knight Auto & Truck",
    "wof:placetype":"venue"
},
  "geometry": {"coordinates":[-114.060455322,51.0891456604],"type":"Point"}
}