{
  "type": "Feature",
  "properties": {
    "addr:full":"174 Bridgeland Ave North York ON M6A 1Z4",
    "addr:housenumber":"174",
    "addr:postcode":"m6a 1z4",
    "addr:street":"Bridgeland Ave",
    "iso:country":"CA",
    "sg:address":"174 Bridgeland Ave",
    "sg:city":"North York",
    "sg:classifiers":[
        {
            "category":"Retail",
            "subcategory":"Auto Repair",
            "type":"Services"
        }
    ],
    "sg:phone":"+1 416 781 1179",
    "sg:postcode":"M6A 1Z4",
    "sg:province":"ON",
    "sg:tags":[
        "repairing",
        "automobile"
    ],
    "wof:name":"Japanese Automotive",
    "wof:placetype":"venue"
},
  "geometry": {"coordinates":[-79.465332,43.725292],"type":"Point"}
}