{
  "type": "Feature",
  "properties": {
    "addr:full":"43 Base Line Rd W London ON N6J 1V5",
    "addr:housenumber":"43",
    "addr:postcode":"n6j 1v5",
    "addr:street":"Base Line Rd W",
    "iso:country":"CA",
    "sg:address":"43 Base Line Rd W",
    "sg:city":"London",
    "sg:classifiers":[
        {
            "category":"Manufacturing",
            "subcategory":"Food",
            "type":"Manufacturing & Wholesale Goods"
        }
    ],
    "sg:phone":"+1 519 645 6045",
    "sg:postcode":"N6J 1V5",
    "sg:province":"ON",
    "sg:tags":[
        "frozen",
        "dessert",
        "ice",
        "cream"
    ],
    "wof:name":"London Ice Cream CO",
    "wof:placetype":"venue"
},
  "geometry": {"coordinates":[-81.2638244629,42.958896637],"type":"Point"}
}