{
  "type": "Feature",
  "properties": {
    "addr:full":"6440 Boul Gouin O Montreal QC H4K 1B1",
    "addr:housenumber":"6440",
    "addr:postcode":"h4k 1b1",
    "addr:street":"Boul Gouin O",
    "iso:country":"CA",
    "sg:address":"6440 Boul Gouin O",
    "sg:city":"Montreal",
    "sg:classifiers":[
        {
            "category":"Personal",
            "subcategory":"Beauty Salon",
            "type":"Services"
        }
    ],
    "sg:phone":"+1 514 336 8000",
    "sg:postcode":"H4K 1B1",
    "sg:province":"QC",
    "wof:name":"Gretta Haute Coiffure",
    "wof:placetype":"venue"
},
  "geometry": {"coordinates":[-73.724464,45.528927],"type":"Point"}
}