{
  "type": "Feature",
  "properties": {
    "addr:full":"140 Grande Allee E # 140 Quebec QC G1R 5M8",
    "addr:housenumber":"140",
    "addr:postcode":"g1r 5m8",
    "addr:street":"Grande Allee E # 140",
    "iso:country":"CA",
    "sg:address":"140 Grande Allee E # 140",
    "sg:city":"Quebec",
    "sg:classifiers":[
        {
            "category":"Professional",
            "subcategory":"Management & Consulting",
            "type":"Services"
        }
    ],
    "sg:phone":"+1 418 647 0889",
    "sg:postcode":"G1R 5M8",
    "sg:province":"QC",
    "sg:tags":[
        "consultant",
        "traffic",
        "parking"
    ],
    "wof:name":"Quebec Auto-Parc",
    "wof:placetype":"venue"
},
  "geometry": {"coordinates":[-71.22189331049999,46.8034324646],"type":"Point"}
}