{
  "type": "Feature",
  "properties": {
    "addr:full":"2190 Harvey Ave Kelowna BC V1Y 6G8",
    "addr:housenumber":"2190",
    "addr:postcode":"v1y 6g8",
    "addr:street":"Harvey Ave",
    "iso:country":"CA",
    "sg:address":"2190 Harvey Ave",
    "sg:city":"Kelowna",
    "sg:classifiers":[
        {
            "category":"Restaurant",
            "type":"Food & Drink"
        }
    ],
    "sg:phone":"+1 250 763 1660",
    "sg:postcode":"V1Y 6G8",
    "sg:province":"BC",
    "wof:name":"White Spot Ltd",
    "wof:placetype":"venue"
},
  "geometry": {"coordinates":[-119.439339,49.882027],"type":"Point"}
}