{
  "type": "Feature",
  "properties": {
    "addr:full":"249 Trowers Rd Woodbridge ON L4L 5Z8",
    "addr:housenumber":"249",
    "addr:postcode":"l4l 5z8",
    "addr:street":"Trowers Rd",
    "iso:country":"CA",
    "sg:address":"249 Trowers Rd",
    "sg:city":"Woodbridge",
    "sg:classifiers":[
        {
            "category":"Wholesale",
            "subcategory":"Hardware",
            "type":"Manufacturing & Wholesale Goods"
        }
    ],
    "sg:phone":"+1 905 850 6299",
    "sg:postcode":"L4L 5Z8",
    "sg:province":"ON",
    "sg:tags":[
        "equipment",
        "heating",
        "system"
    ],
    "wof:name":"Sterling Sheet Metal Mfg Inc",
    "wof:placetype":"venue"
},
  "geometry": {"coordinates":[-79.56102752690001,43.7853126526],"type":"Point"}
}