{
  "type": "Feature",
  "properties": {
    "addr:full":"130 Hunter St W Peterborough ON K9H 2K8",
    "addr:housenumber":"130",
    "addr:postcode":"k9h 2k8",
    "addr:street":"Hunter St W",
    "iso:country":"CA",
    "sg:address":"130 Hunter St W",
    "sg:city":"Peterborough",
    "sg:classifiers":[
        {
            "category":"Organizations",
            "subcategory":"Non-profit Organization",
            "type":"Services"
        }
    ],
    "sg:phone":"+1 705 876 1292",
    "sg:postcode":"K9H 2K8",
    "sg:province":"ON",
    "sg:tags":[
        "addiction",
        "treatment",
        "center"
    ],
    "wof:name":"Four Cast Addiction Svc",
    "wof:placetype":"venue"
},
  "geometry": {"coordinates":[-78.31912994379999,44.3060417175],"type":"Point"}
}