{
  "type": "Feature",
  "properties": {
    "addr:full":"4929 50 Ave Barrhead AB T7N 1A1",
    "addr:housenumber":"4929",
    "addr:postcode":"t7n 1a1",
    "addr:street":"50 Ave",
    "iso:country":"CA",
    "sg:address":"4929 50 Ave",
    "sg:city":"Barrhead",
    "sg:classifiers":[
        {
            "category":"Shopping",
            "type":"Retail Goods"
        }
    ],
    "sg:phone":"+1 780 674 6662",
    "sg:postcode":"T7N 1A1",
    "sg:province":"AB",
    "sg:tags":[
        "satellite",
        "system",
        "equipment",
        "hot",
        "spa",
        "tub"
    ],
    "wof:name":"Tubs 'N Toys",
    "wof:placetype":"venue"
},
  "geometry": {"coordinates":[-114.40418200000001,54.1185],"type":"Point"}
}