{
  "type": "Feature",
  "properties": {
    "addr:full":"15749 Rue Gaucher Pierrefonds QC H9H 4V5",
    "addr:housenumber":"15749",
    "addr:postcode":"h9h 4v5",
    "addr:street":"Rue Gaucher",
    "iso:country":"CA",
    "sg:address":"15749 Rue Gaucher",
    "sg:city":"Pierrefonds",
    "sg:classifiers":[
        {
            "category":"Personal",
            "type":"Services"
        }
    ],
    "sg:phone":"+1 514 696 5865",
    "sg:postcode":"H9H 4V5",
    "sg:province":"QC",
    "sg:tags":[
        "child",
        "bureau",
        "care"
    ],
    "wof:name":"Garderie Funtastique",
    "wof:placetype":"venue"
},
  "geometry": {"coordinates":[-73.864807,45.463375],"type":"Point"}
}