{
  "type": "Feature",
  "properties": {
    "addr:full":"Burnaby BC V5H 4J2",
    "addr:postcode":"v5h 4j2",
    "iso:country":"CA",
    "sg:city":"Burnaby",
    "sg:classifiers":[
        {
            "category":"Shopping",
            "subcategory":"Shoes",
            "type":"Retail Goods"
        }
    ],
    "sg:phone":"+1 604 439 1585",
    "sg:postcode":"V5H 4J2",
    "sg:province":"BC",
    "wof:name":"Naturalizer",
    "wof:placetype":"venue"
},
  "geometry": {"coordinates":[-122.996178,49.227299],"type":"Point"}
}