{
  "type": "Feature",
  "properties": {
    "iso:country":"CA",
    "sg:address":"88 Main St W",
    "sg:city":"Stewiacke",
    "sg:classifiers":[
        {
            "category":"Autos & Motor Vehicles",
            "subcategory":"Fuel & Gas Station",
            "type":"Retail Goods"
        }
    ],
    "sg:phone":"+1 902 639 9299",
    "sg:postcode":"B0N 2J0",
    "sg:province":"NS",
    "sg:tags":[
        "oil"
    ],
    "wof:name":"Gas N Go Esso",
    "wof:placetype":"venue"
},
  "geometry": {"coordinates":[-63.3668479919,45.1402130127],"type":"Point"}
}