{
  "type": "Feature",
  "properties": {
    "addr:full":"225 Lakeshore Dr North Bay ON P1A 2B7",
    "addr:housenumber":"225",
    "addr:postcode":"p1a 2b7",
    "addr:street":"Lakeshore Dr",
    "iso:country":"CA",
    "sg:address":"225 Lakeshore Dr",
    "sg:city":"North Bay",
    "sg:classifiers":[
        {
            "category":"Restaurant",
            "type":"Food & Drink"
        }
    ],
    "sg:phone":"+1 705 474 8530",
    "sg:postcode":"P1A 2B7",
    "sg:province":"ON",
    "wof:name":"Rialto Family Restaurant",
    "wof:placetype":"venue"
},
  "geometry": {"coordinates":[-79.45067596440001,46.2864570618],"type":"Point"}
}