{
  "type": "Feature",
  "properties": {
    "addr:full":"3597 Rue Asselin Longueuil QC J4M 2W7",
    "addr:housenumber":"3597",
    "addr:postcode":"j4m 2w7",
    "addr:street":"Rue Asselin",
    "iso:country":"CA",
    "sg:address":"3597 Rue Asselin",
    "sg:city":"Longueuil",
    "sg:classifiers":[
        {
            "category":"Health Services",
            "subcategory":"Health Practitioner",
            "type":"Services"
        }
    ],
    "sg:phone":"+1 450 448 8803",
    "sg:postcode":"J4M 2W7",
    "sg:province":"QC",
    "sg:tags":[
        "food",
        "dietitian",
        "facility"
    ],
    "wof:name":"Isa-Conseil En Gestion Info",
    "wof:placetype":"venue"
},
  "geometry": {"coordinates":[-73.4403762817,45.5378608704],"type":"Point"}
}