{
  "type": "Feature",
  "properties": {
    "addr:full":"1109 Derry Rd E Mississauga ON L5T 1P3",
    "addr:housenumber":"1109",
    "addr:postcode":"l5t 1p3",
    "addr:street":"Derry Rd E",
    "iso:country":"CA",
    "sg:address":"1109 Derry Rd E",
    "sg:city":"Mississauga",
    "sg:classifiers":[
        {
            "category":"Home & Garden",
            "subcategory":"Building Materials",
            "type":"Retail Goods"
        }
    ],
    "sg:phone":"+1 905 795 1234",
    "sg:postcode":"L5T 1P3",
    "sg:province":"ON",
    "sg:tags":[
        "glass",
        "window",
        "plate"
    ],
    "wof:name":"Auto Glass Magic",
    "wof:placetype":"venue"
},
  "geometry": {"coordinates":[-79.68255615229999,43.6678009033],"type":"Point"}
}