{
  "type": "Feature",
  "properties": {
    "iso:country":"CA",
    "sg:address":"1020 Rue Saint-Denis",
    "sg:city":"Montreal",
    "sg:classifiers":[
        {
            "category":"Utilities",
            "subcategory":"Mobile Phone",
            "type":"Services"
        }
    ],
    "sg:phone":"+1 514 843 0355",
    "sg:postcode":"H2X 3J2",
    "sg:province":"QC",
    "sg:tags":[
        "telephone",
        "cellular"
    ],
    "wof:name":"Proxi Telecom",
    "wof:placetype":"venue"
},
  "geometry": {"coordinates":[-73.55638885499999,45.5117073059],"type":"Point"}
}