{
  "type": "Feature",
  "properties": {
    "addr:full":"Mississauga ON L5B 1M2",
    "addr:postcode":"l5b 1m2",
    "iso:country":"CA",
    "sg:city":"Mississauga",
    "sg:classifiers":[
        {
            "category":"Wholesale",
            "subcategory":"Chemicals & Plastics",
            "type":"Manufacturing & Wholesale Goods"
        }
    ],
    "sg:phone":"+1 905 273 5959",
    "sg:postcode":"L5B 1M2",
    "sg:province":"ON",
    "wof:name":"Akzo Nobel Chemicals Ltd",
    "wof:placetype":"venue"
},
  "geometry": {"coordinates":[-79.6399230957,43.5947990417],"type":"Point"}
}