{
  "type": "Feature",
  "properties": {
    "iso:country":"CA",
    "sg:address":"1159 16th St W",
    "sg:city":"North Vancouver",
    "sg:classifiers":[
        {
            "category":"Wholesale",
            "subcategory":"Hardware",
            "type":"Manufacturing & Wholesale Goods"
        }
    ],
    "sg:phone":"+1 604 988 4141",
    "sg:postcode":"V7P 1R4",
    "sg:province":"BC",
    "sg:tags":[
        "plumbing",
        "fixture",
        "supply"
    ],
    "wof:name":"Bartle & Gibson CO Ltd",
    "wof:placetype":"venue"
},
  "geometry": {"coordinates":[-123.09976196300001,49.3232917786],"type":"Point"}
}