{
  "type": "Feature",
  "properties": {
    "addr:full":"504 2nd Ave N Maple Creek SK S0N 1N0",
    "addr:housenumber":"504",
    "addr:postcode":"s0n 1n0",
    "addr:street":"2Nd Ave N",
    "iso:country":"CA",
    "sg:address":"504 2nd Ave N",
    "sg:city":"Maple Creek",
    "sg:classifiers":[
        {
            "category":"Retail",
            "subcategory":"Auto Repair",
            "type":"Services"
        }
    ],
    "sg:phone":"+1 306 662 3728",
    "sg:postcode":"S0N 1N0",
    "sg:province":"SK",
    "sg:tags":[
        "body",
        "automobile",
        "painting"
    ],
    "wof:name":"C & G Collision",
    "wof:placetype":"venue"
},
  "geometry": {"coordinates":[-109.480407715,49.9065856934],"type":"Point"}
}