{
  "type": "Feature",
  "properties": {
    "addr:full":"Quebec QC G1N 3P9",
    "addr:postcode":"g1n 3p9",
    "iso:country":"CA",
    "sg:city":"Quebec",
    "sg:classifiers":[
        {
            "category":"Building & Trades",
            "subcategory":"Equipment Rental",
            "type":"Services"
        }
    ],
    "sg:phone":"+1 418 686 0960",
    "sg:postcode":"G1N 3P9",
    "sg:province":"QC",
    "sg:tags":[
        "crane"
    ],
    "wof:name":"Service Technique Vml Inc",
    "wof:placetype":"venue"
},
  "geometry": {"coordinates":[-71.25196099999999,46.807697],"type":"Point"}
}