{
  "type": "Feature",
  "properties": {
    "addr:full":"28 Macewan Dr NW Calgary AB T3K 2P2",
    "addr:housenumber":"28",
    "addr:postcode":"t3k 2p2",
    "addr:street":"Macewan Dr Nw",
    "iso:country":"CA",
    "sg:address":"28 Macewan Dr NW",
    "sg:city":"Calgary",
    "sg:classifiers":[
        {
            "category":"Social Services",
            "subcategory":"Child Care",
            "type":"Services"
        }
    ],
    "sg:phone":"+1 403 275 3829",
    "sg:postcode":"T3K 2P2",
    "sg:province":"AB",
    "wof:name":"Kidsland Daycare Ctr",
    "wof:placetype":"venue"
},
  "geometry": {"coordinates":[-114.10896301299999,51.1348190308],"type":"Point"}
}