{
  "type": "Feature",
  "properties": {
    "addr:full":"240 5th Ave NW Moose Jaw SK S6H 7X2",
    "addr:housenumber":"240",
    "addr:postcode":"s6h 7x2",
    "addr:street":"5Th Ave Nw",
    "iso:country":"CA",
    "sg:address":"240 5th Ave NW",
    "sg:city":"Moose Jaw",
    "sg:classifiers":[
        {
            "category":"Home & Garden",
            "subcategory":"Building Materials",
            "type":"Retail Goods"
        }
    ],
    "sg:phone":"+1 306 694 4000",
    "sg:postcode":"S6H 7X2",
    "sg:province":"SK",
    "sg:tags":[
        "lumber"
    ],
    "wof:name":"Home Building Ctr",
    "wof:placetype":"venue"
},
  "geometry": {"coordinates":[-105.547279358,50.3920402527],"type":"Point"}
}