{
  "type": "Feature",
  "properties": {
    "addr:full":"3670 Hoskins Rd Westbank BC V4T 1P7",
    "addr:housenumber":"3670",
    "addr:postcode":"v4t 1p7",
    "addr:street":"Hoskins Rd",
    "iso:country":"CA",
    "sg:address":"3670 Hoskins Rd",
    "sg:city":"Westbank",
    "sg:classifiers":[
        {
            "category":"Professional",
            "subcategory":"Accounting & Tax Preparation",
            "type":"Services"
        }
    ],
    "sg:phone":"+1 250 768 0644",
    "sg:postcode":"V4T 1P7",
    "sg:province":"BC",
    "sg:tags":[
        "accountant"
    ],
    "wof:name":"Joe Maciel Inc",
    "wof:placetype":"venue"
},
  "geometry": {"coordinates":[-119.627044678,49.830242157],"type":"Point"}
}