{
  "type": "Feature",
  "properties": {
    "addr:full":"20 Deanna Dr Munns Rd Souris PE C0A 2B0",
    "addr:housenumber":"20",
    "addr:postcode":"c0a 2b0",
    "addr:street":"Deanna Dr Munns Rd",
    "iso:country":"CA",
    "sg:address":"20 Deanna Dr Munns Rd",
    "sg:city":"Souris",
    "sg:phone":"+1 902 357 2732",
    "sg:postcode":"C0A 2B0",
    "sg:province":"PE",
    "sg:tags":[
        "grower",
        "potato"
    ],
    "wof:name":"Marvyn Robertson Warehouse",
    "wof:placetype":"venue"
},
  "geometry": {"coordinates":[-62.2530326843,46.3544883728],"type":"Point"}
}