{
  "type": "Feature",
  "properties": {
    "addr:full":"Pointe-Claire QC H9R 1G6",
    "addr:postcode":"h9r 1g6",
    "iso:country":"CA",
    "sg:city":"Pointe-Claire",
    "sg:classifiers":[
        {
            "category":"Wholesale",
            "subcategory":"Durable Goods & Equipment",
            "type":"Manufacturing & Wholesale Goods"
        }
    ],
    "sg:phone":"+1 514 694 6378",
    "sg:postcode":"H9R 1G6",
    "sg:province":"QC",
    "sg:tags":[
        "representative",
        "manufacturer"
    ],
    "wof:name":"A R Gray & Assoc",
    "wof:placetype":"venue"
},
  "geometry": {"coordinates":[-73.83065000000001,45.45602],"type":"Point"}
}