{
  "type": "Feature",
  "properties": {
    "addr:full":"Guelph ON N1H 3R3",
    "addr:postcode":"n1h 3r3",
    "iso:country":"CA",
    "sg:city":"Guelph",
    "sg:classifiers":[
        {
            "category":"Professional",
            "subcategory":"Research",
            "type":"Services"
        }
    ],
    "sg:phone":"+1 519 837 4858",
    "sg:postcode":"N1H 3R3",
    "sg:province":"ON",
    "sg:tags":[
        "foundation",
        "philanthropic"
    ],
    "wof:name":"Heart & Stroke Foundation",
    "wof:placetype":"venue"
},
  "geometry": {"coordinates":[-80.2462005615,43.540397644],"type":"Point"}
}