{
  "type": "Feature",
  "properties": {
    "addr:full":"PO Box 129 Seven Persons AB T0K 1Z0",
    "addr:housenumber":"po;129",
    "addr:postcode":"t0k 1z0",
    "addr:street":"Box;Seven",
    "iso:country":"CA",
    "sg:address":"PO Box 129",
    "sg:city":"Seven Persons",
    "sg:classifiers":[
        {
            "category":"Organizations",
            "subcategory":"Religious Organization",
            "type":"Services"
        }
    ],
    "sg:phone":"+1 403 832 2051",
    "sg:postcode":"T0K 1Z0",
    "sg:province":"AB",
    "sg:tags":[
        "church"
    ],
    "wof:name":"Seven Persons Community Church",
    "wof:placetype":"venue"
},
  "geometry": {"coordinates":[-110.91289500000001,49.876205],"type":"Point"}
}