{
  "type": "Feature",
  "properties": {
    "addr:full":"895 Keewatin St Winnipeg MB R2X 2X4",
    "addr:housenumber":"895",
    "addr:postcode":"r2x 2x4",
    "addr:street":"Keewatin St",
    "iso:country":"CA",
    "sg:address":"895 Keewatin St",
    "sg:city":"Winnipeg",
    "sg:classifiers":[
        {
            "category":"Wholesale",
            "subcategory":"Construction Materials",
            "type":"Manufacturing & Wholesale Goods"
        }
    ],
    "sg:phone":"+1 204 633 6150",
    "sg:postcode":"R2X 2X4",
    "sg:province":"MB",
    "sg:tags":[
        "lumber"
    ],
    "wof:name":"Hardwoods",
    "wof:placetype":"venue"
},
  "geometry": {"coordinates":[-97.19489299999999,49.941349],"type":"Point"}
}