{
  "type": "Feature",
  "properties": {
    "addr:full":"1020 26 St NE Calgary AB T2A 2M4",
    "addr:housenumber":"1020",
    "addr:postcode":"t2a 2m4",
    "addr:street":"26 St Ne",
    "iso:country":"CA",
    "sg:address":"1020 26 St NE",
    "sg:city":"Calgary",
    "sg:classifiers":[
        {
            "category":"Wholesale",
            "subcategory":"Farm Supplies",
            "type":"Manufacturing & Wholesale Goods"
        }
    ],
    "sg:phone":"+1 403 531 6656",
    "sg:postcode":"T2A 2M4",
    "sg:province":"AB",
    "sg:tags":[
        "feed",
        "poultry",
        "bedding"
    ],
    "wof:name":"Federated CO-Operatives Ltd",
    "wof:placetype":"venue"
},
  "geometry": {"coordinates":[-113.995811,51.060688],"type":"Point"}
}