{
  "type": "Feature",
  "properties": {
    "addr:full":"2485 Boul Sainte-Anne Quebec QC G1J 1Y4",
    "addr:housenumber":"2485",
    "addr:postcode":"g1j 1y4",
    "addr:street":"Boul Sainte-Anne",
    "iso:country":"CA",
    "sg:address":"2485 Boul Sainte-Anne",
    "sg:city":"Quebec",
    "sg:classifiers":[
        {
            "category":"Shopping",
            "subcategory":"Luggage & Leather Goods",
            "type":"Retail Goods"
        }
    ],
    "sg:phone":"+1 418 661 5227",
    "sg:postcode":"G1J 1Y4",
    "sg:province":"QC",
    "wof:name":"Bentley Leathers Inc",
    "wof:placetype":"venue"
},
  "geometry": {"coordinates":[-71.215675,46.843941],"type":"Point"}
}