{
  "type": "Feature",
  "properties": {
    "addr:full":"2696 Broadway W Vancouver BC V6K 2G3",
    "addr:housenumber":"2696",
    "addr:postcode":"v6k 2g3",
    "addr:street":"Broadway W",
    "iso:country":"CA",
    "sg:address":"2696 Broadway W",
    "sg:city":"Vancouver",
    "sg:classifiers":[
        {
            "category":"Food & Beverages",
            "subcategory":"Specialty",
            "type":"Retail Goods"
        }
    ],
    "sg:phone":"+1 604 738 0326",
    "sg:postcode":"V6K 2G3",
    "sg:province":"BC",
    "sg:tags":[
        "health",
        "diet"
    ],
    "wof:name":"On Broadway Specialty Food Ltd",
    "wof:placetype":"venue"
},
  "geometry": {"coordinates":[-123.166122437,49.2639198303],"type":"Point"}
}