{
  "type": "Feature",
  "properties": {
    "addr:full":"5848 Av Du Pont N Alma QC G8E 1X3",
    "addr:housenumber":"5848",
    "addr:postcode":"g8e 1x3",
    "addr:street":"Av Du Pont N",
    "iso:country":"CA",
    "sg:address":"5848 Av Du Pont N",
    "sg:city":"Alma",
    "sg:classifiers":[
        {
            "category":"Personal",
            "subcategory":"Beauty Salon",
            "type":"Services"
        }
    ],
    "sg:phone":"+1 418 347 4652",
    "sg:postcode":"G8E 1X3",
    "sg:province":"QC",
    "wof:name":"Salon D'Esthetique & D'Elect",
    "wof:placetype":"venue"
},
  "geometry": {"coordinates":[-71.701103,48.632542],"type":"Point"}
}