{
  "type": "Feature",
  "properties": {
    "addr:full":"2412 Ronald Rd Minesing ON L0L 1Y0",
    "addr:housenumber":"2412",
    "addr:postcode":"l0l 1y0",
    "addr:street":"Ronald Rd",
    "iso:country":"CA",
    "sg:address":"2412 Ronald Rd",
    "sg:city":"Minesing",
    "sg:classifiers":[
        {
            "category":"Organizations",
            "subcategory":"Religious Organization",
            "type":"Services"
        }
    ],
    "sg:phone":"+1 705 720 2020",
    "sg:postcode":"L0L 1Y0",
    "sg:province":"ON",
    "sg:tags":[
        "church"
    ],
    "wof:name":"St Peters Anglican Church",
    "wof:placetype":"venue"
},
  "geometry": {"coordinates":[-79.843155,44.442734],"type":"Point"}
}