{
  "type": "Feature",
  "properties": {
    "iso:country":"CA",
    "sg:address":"57 Calderbridge Cres",
    "sg:city":"Markham",
    "sg:classifiers":[
        {
            "category":"Professional",
            "subcategory":"Computer Services",
            "type":"Services"
        }
    ],
    "sg:phone":"+1 905 415 8655",
    "sg:postcode":"L3R 9M6",
    "sg:province":"ON",
    "wof:name":"Datacom",
    "wof:placetype":"venue"
},
  "geometry": {"coordinates":[-79.3380279541,43.866733551],"type":"Point"}
}