{
  "type": "Feature",
  "properties": {
    "addr:full":"171 North St E Tillsonburg ON N4G 1B8",
    "addr:housenumber":"171",
    "addr:postcode":"n4g 1b8",
    "addr:street":"North St",
    "iso:country":"CA",
    "sg:address":"171 North St E",
    "sg:city":"Tillsonburg",
    "sg:classifiers":[
        {
            "category":"Health Services",
            "subcategory":"Health Practitioner",
            "type":"Services"
        }
    ],
    "sg:phone":"+1 519 842 5162",
    "sg:postcode":"N4G 1B8",
    "sg:province":"ON",
    "sg:tags":[
        "physiotherapist"
    ],
    "wof:name":"Tillsonburg Physiotherapy Clnc",
    "wof:placetype":"venue"
},
  "geometry": {"coordinates":[-80.72560882569999,42.8812522888],"type":"Point"}
}