{
  "type": "Feature",
  "properties": {
    "iso:country":"CA",
    "sg:address":"886 Winston Churchill Blvd",
    "sg:city":"Oakville",
    "sg:classifiers":[
        {
            "category":"Organizations",
            "subcategory":"Professional Association",
            "type":"Services"
        }
    ],
    "sg:phone":"+1 905 842 1790",
    "sg:postcode":"L6J 7X5",
    "sg:province":"ON",
    "wof:name":"Associated Earth Movers",
    "wof:placetype":"venue"
},
  "geometry": {"coordinates":[-79.643417,43.494625],"type":"Point"}
}