{
  "type": "Feature",
  "properties": {
    "addr:full":"99 Rue Saint-Germain O Rimouski QC G5L 4B6",
    "addr:housenumber":"99",
    "addr:postcode":"g5l 4b6",
    "addr:street":"Rue Saint-Germain O",
    "iso:country":"CA",
    "sg:address":"99 Rue Saint-Germain O",
    "sg:city":"Rimouski",
    "sg:classifiers":[
        {
            "category":"Food & Beverages",
            "subcategory":"Groceries & Convenience Stores",
            "type":"Retail Goods"
        }
    ],
    "sg:phone":"+1 418 723 0355",
    "sg:postcode":"G5L 4B6",
    "sg:province":"QC",
    "wof:name":"Coop Alina",
    "wof:placetype":"venue"
},
  "geometry": {"coordinates":[-68.523186,48.452946],"type":"Point"}
}