{
  "type": "Feature",
  "properties": {
    "addr:full":"330 317th Ave Marysville BC V1A 3G9",
    "addr:housenumber":"330",
    "addr:postcode":"v1a 3g9",
    "addr:street":"317Th Ave",
    "iso:country":"CA",
    "sg:address":"330 317th Ave",
    "sg:city":"Marysville",
    "sg:classifiers":[
        {
            "category":"Wholesale",
            "subcategory":"Scrap",
            "type":"Manufacturing & Wholesale Goods"
        }
    ],
    "sg:phone":"+1 250 427 2994",
    "sg:postcode":"V1A 3G9",
    "sg:province":"BC",
    "sg:tags":[
        "recycling",
        "metal",
        "center",
        "iron"
    ],
    "wof:name":"Columbia Recycle Ltd",
    "wof:placetype":"venue"
},
  "geometry": {"coordinates":[-115.882133,49.606174],"type":"Point"}
}