{
  "type": "Feature",
  "properties": {
    "addr:full":"337 Pine St Waubaushene ON L0K 2C0",
    "addr:housenumber":"337",
    "addr:postcode":"l0k 2c0",
    "addr:street":"Pine St",
    "iso:country":"CA",
    "sg:address":"337 Pine St",
    "sg:city":"Waubaushene",
    "sg:classifiers":[
        {
            "category":"Shopping",
            "subcategory":"Used Merchandise",
            "type":"Retail Goods"
        }
    ],
    "sg:phone":"+1 705 538 1857",
    "sg:postcode":"L0K 2C0",
    "sg:province":"ON",
    "sg:tags":[
        "antique"
    ],
    "wof:name":"Waubaushene Heritage",
    "wof:placetype":"venue"
},
  "geometry": {"coordinates":[-79.7085952759,44.751953125],"type":"Point"}
}