{
  "type": "Feature",
  "properties": {
    "iso:country":"CA",
    "sg:address":"19 Christine St",
    "sg:city":"Southampton",
    "sg:classifiers":[
        {
            "category":"Social Services",
            "subcategory":"Child Care",
            "type":"Services"
        }
    ],
    "sg:phone":"+1 519 797 2419",
    "sg:postcode":"N0H 2L0",
    "sg:province":"ON",
    "wof:name":"G'Shawdagawin Day Care Ctr",
    "wof:placetype":"venue"
},
  "geometry": {"coordinates":[-81.3698501587,44.4977455139],"type":"Point"}
}