{
  "type": "Feature",
  "properties": {
    "addr:full":"14 Great George St Charlottetown PE C1A 4J6",
    "addr:housenumber":"14",
    "addr:postcode":"c1a 4j6",
    "addr:street":"Great George St",
    "iso:country":"CA",
    "sg:address":"14 Great George St",
    "sg:city":"Charlottetown",
    "sg:classifiers":[
        {
            "category":"Professional",
            "subcategory":"Lawyer & Legal Services",
            "type":"Services"
        }
    ],
    "sg:phone":"+1 902 368 3221",
    "sg:postcode":"C1A 4J6",
    "sg:province":"PE",
    "sg:tags":[
        "attorney"
    ],
    "wof:name":"Mullin, Paul J D QC",
    "wof:placetype":"venue"
},
  "geometry": {"coordinates":[-63.123009,46.232849],"type":"Point"}
}