{
  "type": "Feature",
  "properties": {
    "addr:full":"10 Lovett Lake Crt Halifax NS B3S 1B8",
    "addr:housenumber":"10",
    "addr:postcode":"b3s 1b8",
    "addr:street":"Lovett Lake Crt",
    "iso:country":"CA",
    "sg:address":"10 Lovett Lake Crt",
    "sg:city":"Halifax",
    "sg:classifiers":[
        {
            "category":"Real Estate",
            "subcategory":"Real Estate Agent",
            "type":"Services"
        }
    ],
    "sg:phone":"+1 902 468 5459",
    "sg:postcode":"B3S 1B8",
    "sg:province":"NS",
    "sg:tags":[
        "management"
    ],
    "wof:name":"Atlantic Premises Management",
    "wof:placetype":"venue"
},
  "geometry": {"coordinates":[-63.6646118164,44.6446380615],"type":"Point"}
}