{
  "type": "Feature",
  "properties": {
    "addr:full":"148 Wallace Ave N Listowel ON N4W 1K7",
    "addr:housenumber":"148",
    "addr:postcode":"n4w 1k7",
    "addr:street":"Wallace Ave N",
    "iso:country":"CA",
    "sg:address":"148 Wallace Ave N",
    "sg:city":"Listowel",
    "sg:classifiers":[
        {
            "category":"Building & Trades",
            "subcategory":"Construction",
            "type":"Services"
        }
    ],
    "sg:phone":"+1 519 291 5715",
    "sg:postcode":"N4W 1K7",
    "sg:province":"ON",
    "sg:tags":[
        "paint",
        "painter"
    ],
    "wof:name":"Town & Country Decorating",
    "wof:placetype":"venue"
},
  "geometry": {"coordinates":[-80.95264434809999,43.7319717407],"type":"Point"}
}