{
  "type": "Feature",
  "properties": {
    "addr:full":"121 16E Rue Shippagan NB E8S 1E9",
    "addr:housenumber":"121",
    "addr:postcode":"e8s 1e9",
    "addr:street":"16E Rue Shippagan",
    "iso:country":"CA",
    "sg:address":"121 16E Rue",
    "sg:city":"Shippagan",
    "sg:classifiers":[
        {
            "category":"Restaurant",
            "type":"Food & Drink"
        }
    ],
    "sg:phone":"+1 506 336 0004",
    "sg:postcode":"E8S 1E9",
    "sg:province":"NB",
    "wof:name":"Bistro Au Pirate Maboule",
    "wof:placetype":"venue"
},
  "geometry": {"coordinates":[-64.708763,47.743847],"type":"Point"}
}