{
  "type": "Feature",
  "properties": {
    "addr:full":"1851 Lawrence Ave E Scarborough ON M1R 2Y3",
    "addr:housenumber":"1851",
    "addr:postcode":"m1r 2y3",
    "addr:street":"Lawrence Ave E",
    "iso:country":"CA",
    "sg:address":"1851 Lawrence Ave E",
    "sg:city":"Scarborough",
    "sg:classifiers":[
        {
            "category":"Shopping",
            "subcategory":"Discount & Variety Stores",
            "type":"Retail Goods"
        }
    ],
    "sg:phone":"+1 416 288 9671",
    "sg:postcode":"M1R 2Y3",
    "sg:province":"ON",
    "wof:name":"Millenium Mart",
    "wof:placetype":"venue"
},
  "geometry": {"coordinates":[-79.302994,43.743439],"type":"Point"}
}