{
  "type": "Feature",
  "properties": {
    "addr:full":"4075 Bath Rd Kingston ON K7M 4Y6",
    "addr:housenumber":"4075",
    "addr:postcode":"k7m 4y6",
    "addr:street":"Bath Rd",
    "iso:country":"CA",
    "sg:address":"4075 Bath Rd",
    "sg:city":"Kingston",
    "sg:classifiers":[
        {
            "category":"Education",
            "subcategory":"School",
            "type":"Public Place"
        }
    ],
    "sg:phone":"+1 613 389 0500",
    "sg:postcode":"K7M 4Y6",
    "sg:province":"ON",
    "wof:name":"Collins Bay Public School",
    "wof:placetype":"venue"
},
  "geometry": {"coordinates":[-76.610649,44.241276],"type":"Point"}
}