{
  "type": "Feature",
  "properties": {
    "iso:country":"CA",
    "sg:address":"600 Rue Louis-Pasteur",
    "sg:city":"Boucherville",
    "sg:classifiers":[
        {
            "category":"Freight",
            "type":"Transportation"
        }
    ],
    "sg:phone":"+1 450 641 0082",
    "sg:postcode":"J4B 7Z1",
    "sg:province":"QC",
    "sg:tags":[
        "trucking"
    ],
    "wof:name":"Groupe VA Inc",
    "wof:placetype":"venue"
},
  "geometry": {"coordinates":[-73.400169,45.566357],"type":"Point"}
}