{
  "type": "Feature",
  "properties": {
    "addr:full":"2324 Butler Ave Houston BC V0J 1Z0",
    "addr:housenumber":"2324",
    "addr:postcode":"v0j 1z0",
    "addr:street":"Butler Ave",
    "iso:country":"CA",
    "sg:address":"2324 Butler Ave",
    "sg:city":"Houston",
    "sg:classifiers":[
        {
            "category":"Organizations",
            "subcategory":"Religious Organization",
            "type":"Services"
        }
    ],
    "sg:phone":"+1 250 845 3188",
    "sg:postcode":"V0J 1Z0",
    "sg:province":"BC",
    "sg:tags":[
        "church"
    ],
    "wof:name":"Anglican Church of St Clements",
    "wof:placetype":"venue"
},
  "geometry": {"coordinates":[-126.643836975,54.4002113342],"type":"Point"}
}