{
  "type": "Feature",
  "properties": {
    "addr:full":"1182 Hastings St E Vancouver BC V6A 1S2",
    "addr:housenumber":"1182",
    "addr:postcode":"v6a 1s2",
    "addr:street":"Hastings St E",
    "iso:country":"CA",
    "sg:address":"1182 Hastings St E",
    "sg:city":"Vancouver",
    "sg:classifiers":[
        {
            "category":"Manufacturing",
            "subcategory":"Printing",
            "type":"Manufacturing & Wholesale Goods"
        }
    ],
    "sg:phone":"+1 604 251 2474",
    "sg:postcode":"V6A 1S2",
    "sg:province":"BC",
    "sg:tags":[
        "printer"
    ],
    "wof:name":"Sandhill Press",
    "wof:placetype":"venue"
},
  "geometry": {"coordinates":[-123.079620361,49.2808761597],"type":"Point"}
}