{
  "type": "Feature",
  "properties": {
    "iso:country":"CA",
    "sg:city":"Calgary",
    "sg:classifiers":[
        {
            "category":"Shopping",
            "subcategory":"Clothing, Apparel, & Fashions",
            "type":"Retail Goods"
        }
    ],
    "sg:phone":"+1 403 271 4633",
    "sg:postcode":"T2J 3V1",
    "sg:province":"AB",
    "wof:name":"American Eagle",
    "wof:placetype":"venue"
},
  "geometry": {"coordinates":[-114.06149292000001,50.9497756958],"type":"Point"}
}