{
  "type": "Feature",
  "properties": {
    "iso:country":"CA",
    "sg:address":"660 Boul L'Assomption",
    "sg:city":"Repentigny",
    "sg:classifiers":[
        {
            "category":"Professional",
            "subcategory":"Business Services",
            "type":"Services"
        }
    ],
    "sg:phone":"+1 450 654 1400",
    "sg:postcode":"J6A 7P2",
    "sg:province":"QC",
    "sg:tags":[
        "notary"
    ],
    "wof:name":"Lewis, Danielle",
    "wof:placetype":"venue"
},
  "geometry": {"coordinates":[-73.4440612793,45.7554397583],"type":"Point"}
}