{
  "type": "Feature",
  "properties": {
    "addr:full":"650 Rue DE LA Visitation Saint-Charles-Borromee QC J6E 7S2",
    "addr:housenumber":"650",
    "addr:postcode":"j6e 7s2",
    "addr:street":"Rue De La Visitation Saint-Charles-Borromee",
    "iso:country":"CA",
    "sg:address":"650 Rue DE LA Visitation",
    "sg:city":"Saint-Charles-Borromee",
    "sg:classifiers":[
        {
            "category":"Food & Beverages",
            "subcategory":"Groceries & Convenience Stores",
            "type":"Retail Goods"
        }
    ],
    "sg:phone":"+1 450 759 5363",
    "sg:postcode":"J6E 7S2",
    "sg:province":"QC",
    "wof:name":"Depanneur Rapido",
    "wof:placetype":"venue"
},
  "geometry": {"coordinates":[-73.468193,46.051411],"type":"Point"}
}