{
  "type": "Feature",
  "properties": {
    "addr:full":"19868 Langley Bypass Langley BC V3A 4Y1",
    "addr:housenumber":"19868",
    "addr:postcode":"v3a 4y1",
    "addr:street":"Langley Bypass",
    "iso:country":"CA",
    "sg:address":"19868 Langley Bypass",
    "sg:city":"Langley",
    "sg:classifiers":[
        {
            "category":"Shopping",
            "subcategory":"Used Merchandise",
            "type":"Retail Goods"
        }
    ],
    "sg:phone":"+1 604 530 1321",
    "sg:postcode":"V3A 4Y1",
    "sg:province":"BC",
    "sg:tags":[
        "shop",
        "thrift"
    ],
    "wof:name":"Salvation Army",
    "wof:placetype":"venue"
},
  "geometry": {"coordinates":[-122.67319500000001,49.11272],"type":"Point"}
}