{
  "type": "Feature",
  "properties": {
    "iso:country":"CA",
    "sg:address":"19868 Langley Bypass",
    "sg:city":"Langley",
    "sg:classifiers":[
        {
            "category":"Shopping",
            "subcategory":"Used Merchandise",
            "type":"Retail Goods"
        }
    ],
    "sg:phone":"+1 604 530 1321",
    "sg:postcode":"V3A 4Y1",
    "sg:province":"BC",
    "sg:tags":[
        "shop",
        "thrift"
    ],
    "wof:name":"Salvation Army",
    "wof:placetype":"venue"
},
  "geometry": {"coordinates":[-122.673195,49.11272],"type":"Point"}
}