{
  "type": "Feature",
  "properties": {
    "addr:full":"6490 Hwy 3 Western Shore NS B0J 3M0",
    "addr:housenumber":"6490",
    "addr:postcode":"b0j 3m0",
    "addr:street":"Hwy 3",
    "iso:country":"CA",
    "sg:address":"6490 Hwy 3",
    "sg:city":"Western Shore",
    "sg:classifiers":[
        {
            "category":"Restaurant",
            "type":"Food & Drink"
        }
    ],
    "sg:phone":"+1 902 627 2880",
    "sg:postcode":"B0J 3M0",
    "sg:province":"NS",
    "wof:name":"Big Red's Family Restaurant",
    "wof:placetype":"venue"
},
  "geometry": {"coordinates":[-64.31012699999999,44.523281],"type":"Point"}
}