{
  "type": "Feature",
  "properties": {
    "addr:full":"7633 Rockhill Rd Mississauga ON L4T 2Z9",
    "addr:housenumber":"7633",
    "addr:postcode":"l4t 2z9",
    "addr:street":"Rockhill Rd",
    "iso:country":"CA",
    "sg:address":"7633 Rockhill Rd",
    "sg:city":"Mississauga",
    "sg:classifiers":[
        {
            "category":"Food & Beverages",
            "subcategory":"Groceries & Convenience Stores",
            "type":"Retail Goods"
        }
    ],
    "sg:phone":"+1 905 678 9890",
    "sg:postcode":"L4T 2Z9",
    "sg:province":"ON",
    "sg:tags":[
        "grocer"
    ],
    "wof:name":"Midi Mart Convenience Store",
    "wof:placetype":"venue"
},
  "geometry": {"coordinates":[-79.64170799999999,43.731571],"type":"Point"}
}