{
  "type": "Feature",
  "properties": {
    "addr:full":"41 Budd Ave St Stephen NB E3L 1E8",
    "addr:housenumber":"41",
    "addr:postcode":"e3l 1e8",
    "addr:street":"Budd Ave",
    "iso:country":"CA",
    "sg:address":"41 Budd Ave",
    "sg:city":"St Stephen",
    "sg:classifiers":[
        {
            "category":"Health Services",
            "subcategory":"Clinic",
            "type":"Services"
        }
    ],
    "sg:phone":"+1 506 466 1759",
    "sg:postcode":"E3L 1E8",
    "sg:province":"NB",
    "sg:tags":[
        "home",
        "homemaker"
    ],
    "wof:name":"Home Support Svc Meals",
    "wof:placetype":"venue"
},
  "geometry": {"coordinates":[-67.271378,45.192173],"type":"Point"}
}