{
  "type": "Feature",
  "properties": {
    "addr:full":"Parisville QC G0S 1X0",
    "addr:postcode":"g0s 1x0",
    "iso:country":"CA",
    "sg:city":"Parisville",
    "sg:classifiers":[
        {
            "category":"Retail",
            "subcategory":"Auto Repair",
            "type":"Services"
        }
    ],
    "sg:phone":"+1 819 292 2933",
    "sg:postcode":"G0S 1X0",
    "sg:province":"QC",
    "sg:tags":[
        "body",
        "automobile",
        "painting"
    ],
    "wof:name":"Garage R Paris Inc",
    "wof:placetype":"venue"
},
  "geometry": {"coordinates":[-72.057693,46.514668],"type":"Point"}
}