{
  "type": "Feature",
  "properties": {
    "addr:full":"Montreal QC H3M 3E2",
    "addr:postcode":"h3m 3e2",
    "iso:country":"CA",
    "sg:city":"Montreal",
    "sg:classifiers":[
        {
            "category":"Professional",
            "subcategory":"Lawyer & Legal Services",
            "type":"Services"
        }
    ],
    "sg:phone":"+1 514 333 0860",
    "sg:postcode":"H3M 3E2",
    "sg:province":"QC",
    "sg:tags":[
        "attorney"
    ],
    "wof:name":"Desormeau Ouellet",
    "wof:placetype":"venue"
},
  "geometry": {"coordinates":[-73.6787185669,45.5368003845],"type":"Point"}
}