{
  "type": "Feature",
  "properties": {
    "iso:country":"CA",
    "sg:address":"39 Boul Saint-Joseph",
    "sg:city":"Hull",
    "sg:classifiers":[
        {
            "category":"Food & Beverages",
            "subcategory":"Bakery",
            "type":"Retail Goods"
        }
    ],
    "sg:phone":"+1 819 771 1770",
    "sg:postcode":"J8Y 3V9",
    "sg:province":"QC",
    "sg:tags":[
        "baker"
    ],
    "wof:name":"Patisserie Francaise-St-Honore",
    "wof:placetype":"venue"
},
  "geometry": {"coordinates":[-75.73360443120001,45.4260520935],"type":"Point"}
}