{
  "type": "Feature",
  "properties": {
    "iso:country":"CA",
    "sg:address":"10155 Boul Saint-Laurent",
    "sg:city":"Montreal",
    "sg:classifiers":[
        {
            "category":"Personal",
            "type":"Services"
        }
    ],
    "sg:phone":"+1 514 383 6363",
    "sg:postcode":"H3L 2N5",
    "sg:province":"QC",
    "sg:tags":[
        "therapist",
        "massage"
    ],
    "wof:name":"L'Asolu",
    "wof:placetype":"venue"
},
  "geometry": {"coordinates":[-73.662979,45.548073],"type":"Point"}
}