{
  "type": "Feature",
  "properties": {
    "addr:full":"251 John St Sudbury ON P3E 1P9",
    "addr:housenumber":"251",
    "addr:postcode":"p3e 1p9",
    "addr:street":"John St",
    "iso:country":"CA",
    "sg:address":"251 John St",
    "sg:city":"Sudbury",
    "sg:classifiers":[
        {
            "category":"Shopping",
            "type":"Retail Goods"
        }
    ],
    "sg:phone":"+1 705 674 3271",
    "sg:postcode":"P3E 1P9",
    "sg:province":"ON",
    "sg:tags":[
        "art",
        "gallery",
        "dealer"
    ],
    "wof:name":"Art Gallery of Sudbury",
    "wof:placetype":"venue"
},
  "geometry": {"coordinates":[-80.988068,46.483307],"type":"Point"}
}