{
  "type": "Feature",
  "properties": {
    "addr:full":"1671 Carling Ave Ottawa ON K2A 1C4",
    "addr:housenumber":"1671",
    "addr:postcode":"k2a 1c4",
    "addr:street":"Carling Ave",
    "iso:country":"CA",
    "sg:address":"1671 Carling Ave",
    "sg:city":"Ottawa",
    "sg:classifiers":[
        {
            "category":"Restaurant",
            "type":"Food & Drink"
        }
    ],
    "sg:phone":"+1 613 729 6018",
    "sg:postcode":"K2A 1C4",
    "sg:province":"ON",
    "wof:name":"Shogun Ottawa Japanese Steak",
    "wof:placetype":"venue"
},
  "geometry": {"coordinates":[-75.749809,45.379486],"type":"Point"}
}