{
  "type": "Feature",
  "properties": {
    "addr:full":"206 2nd St NE Waldheim SK S0K 4R0",
    "addr:housenumber":"206",
    "addr:postcode":"s0k 4r0",
    "addr:street":"2Nd St Ne",
    "iso:country":"CA",
    "sg:address":"206 2nd St NE",
    "sg:city":"Waldheim",
    "sg:classifiers":[
        {
            "category":"Home & Garden",
            "subcategory":"Building Materials",
            "type":"Retail Goods"
        }
    ],
    "sg:phone":"+1 306 945 2207",
    "sg:postcode":"S0K 4R0",
    "sg:province":"SK",
    "wof:name":"M & R Building Products Ltd",
    "wof:placetype":"venue"
},
  "geometry": {"coordinates":[-106.647575,52.613106],"type":"Point"}
}