{
  "type": "Feature",
  "properties": {
    "addr:full":"334 Somerset St E Ottawa ON K1N 6W5",
    "addr:housenumber":"334",
    "addr:postcode":"k1n 6w5",
    "addr:street":"Somerset St E",
    "iso:country":"CA",
    "sg:address":"334 Somerset St E",
    "sg:city":"Ottawa",
    "sg:classifiers":[
        {
            "category":"Personal",
            "subcategory":"Beauty Salon",
            "type":"Services"
        }
    ],
    "sg:phone":"+1 613 232 2187",
    "sg:postcode":"K1N 6W5",
    "sg:province":"ON",
    "wof:name":"Joseph Beauty Salon",
    "wof:placetype":"venue"
},
  "geometry": {"coordinates":[-75.67375199999999,45.424618],"type":"Point"}
}