{
  "type": "Feature",
  "properties": {
    "addr:full":"PO Box 279 Faro YT Y0B 1K0",
    "addr:housenumber":"po",
    "addr:postcode":"y0b 1k0",
    "addr:street":"Box 279",
    "iso:country":"CA",
    "sg:address":"PO Box 279",
    "sg:city":"Faro",
    "sg:classifiers":[
        {
            "category":"Education",
            "subcategory":"Library",
            "type":"Public Place"
        }
    ],
    "sg:phone":"+1 867 994 2684",
    "sg:postcode":"Y0B 1K0",
    "sg:province":"YT",
    "wof:name":"Faro Public Library",
    "wof:placetype":"venue"
},
  "geometry": {"coordinates":[-133.35481300000001,62.229156],"type":"Point"}
}