{
  "type": "Feature",
  "properties": {
    "addr:full":"6320 Ch DE LA Cote-Des-Neiges Montreal QC H3S 2A4",
    "addr:postcode":"6320;h3s 2a4",
    "addr:street":"Ch De La Cote-Des-Neiges",
    "iso:country":"CA",
    "sg:address":"6320 Ch DE LA Cote-Des-Neiges",
    "sg:city":"Montreal",
    "sg:classifiers":[
        {
            "category":"Education",
            "subcategory":"School",
            "type":"Public Place"
        }
    ],
    "sg:phone":"+1 514 736 8100",
    "sg:postcode":"H3S 2A4",
    "sg:province":"QC",
    "wof:name":"Ecole St-Pascal-Baylon",
    "wof:placetype":"venue"
},
  "geometry": {"coordinates":[-73.6342468262,45.5016212463],"type":"Point"}
}