{
  "type": "Feature",
  "properties": {
    "addr:full":"Fredericton NB E3B 4Z9",
    "addr:postcode":"e3b 4z9",
    "iso:country":"CA",
    "sg:city":"Fredericton",
    "sg:classifiers":[
        {
            "category":"Autos & Motor Vehicles",
            "subcategory":"Automobile Sales",
            "type":"Retail Goods"
        }
    ],
    "sg:phone":"+1 506 452 2200",
    "sg:postcode":"E3B 4Z9",
    "sg:province":"NB",
    "sg:tags":[
        "car",
        "dealer"
    ],
    "wof:name":"Clark Toyota Ltd",
    "wof:placetype":"venue"
},
  "geometry": {"coordinates":[-66.635345,45.919495],"type":"Point"}
}