{
  "type": "Feature",
  "properties": {
    "addr:full":"Old Hwy 2 Shannonville ON K0K 3A0",
    "addr:postcode":"k0k 3a0",
    "addr:street":"Old Hwy 2 Shannonville",
    "iso:country":"CA",
    "sg:address":"Old Hwy 2",
    "sg:city":"Shannonville",
    "sg:classifiers":[
        {
            "category":"Professional",
            "subcategory":"Management & Consulting",
            "type":"Services"
        }
    ],
    "sg:phone":"+1 613 966 8240",
    "sg:postcode":"K0K 3A0",
    "sg:province":"ON",
    "sg:tags":[
        "break",
        "coffee",
        "supply"
    ],
    "wof:name":"Mohawk Coffee Svc",
    "wof:placetype":"venue"
},
  "geometry": {"coordinates":[-77.230011,44.197327],"type":"Point"}
}