{
  "type": "Feature",
  "properties": {
    "addr:full":"5332 St Margarets Bay Rd Upper Tantallon NS B3Z 2J1",
    "addr:housenumber":"5332",
    "addr:postcode":"b3z 2j1",
    "addr:street":"St Margarets Bay Rd",
    "iso:country":"CA",
    "sg:address":"5332 St Margarets Bay Rd",
    "sg:city":"Upper Tantallon",
    "sg:classifiers":[
        {
            "category":"Home & Garden",
            "subcategory":"Garden Supply",
            "type":"Retail Goods"
        }
    ],
    "sg:phone":"+1 902 826 7173",
    "sg:postcode":"B3Z 2J1",
    "sg:province":"NS",
    "sg:tags":[
        "center"
    ],
    "wof:name":"Boutilier Lawn & Garden",
    "wof:placetype":"venue"
},
  "geometry": {"coordinates":[-63.884601593,44.6916503906],"type":"Point"}
}