{
  "type": "Feature",
  "properties": {
    "addr:full":"60 Pippin Rd Concord ON L4K 4M8",
    "addr:housenumber":"60",
    "addr:postcode":"l4k 4m8",
    "addr:street":"Pippin Rd",
    "iso:country":"CA",
    "sg:address":"60 Pippin Rd",
    "sg:city":"Concord",
    "sg:classifiers":[
        {
            "category":"Retail",
            "subcategory":"Laundry & Dry Cleaning",
            "type":"Services"
        }
    ],
    "sg:phone":"+1 905 738 0217",
    "sg:postcode":"L4K 4M8",
    "sg:province":"ON",
    "sg:tags":[
        "linen",
        "supply"
    ],
    "wof:name":"Alpha Linen Supply Ltd",
    "wof:placetype":"venue"
},
  "geometry": {"coordinates":[-79.524788,43.809803],"type":"Point"}
}