{
  "type": "Feature",
  "properties": {
    "iso:country":"CA",
    "sg:address":"49 King E",
    "sg:city":"Bobcaygeon",
    "sg:classifiers":[
        {
            "category":"Health Services",
            "subcategory":"Doctor",
            "type":"Services"
        }
    ],
    "sg:phone":"+1 705 738 6161",
    "sg:postcode":"K0M 1A0",
    "sg:province":"ON",
    "sg:tags":[
        "physician",
        "surgeon"
    ],
    "wof:name":"Fagan, James MD",
    "wof:placetype":"venue"
},
  "geometry": {"coordinates":[-78.5405578613,44.5362014771],"type":"Point"}
}