{
  "type": "Feature",
  "properties": {
    "iso:country":"CA",
    "sg:city":"Pitt Meadows",
    "sg:classifiers":[
        {
            "category":"Manufacturing",
            "subcategory":"Rubber & Plastics",
            "type":"Manufacturing & Wholesale Goods"
        }
    ],
    "sg:phone":"+1 604 465 9181",
    "sg:postcode":"V3Y 2V4",
    "sg:province":"BC",
    "sg:tags":[
        "mold",
        "maker"
    ],
    "wof:name":"P H Molds Ltd",
    "wof:placetype":"venue"
},
  "geometry": {"coordinates":[-122.689620972,49.2207183838],"type":"Point"}
}