{
  "type": "Feature",
  "properties": {
    "addr:full":"4815 52nd St Legal AB T0G 1L0",
    "addr:housenumber":"4815",
    "addr:postcode":"t0g 1l0",
    "addr:street":"52Nd St",
    "iso:country":"CA",
    "sg:address":"4815 52nd St",
    "sg:city":"Legal",
    "sg:classifiers":[
        {
            "category":"Manufacturing",
            "subcategory":"Tools & Machinery",
            "type":"Manufacturing & Wholesale Goods"
        }
    ],
    "sg:phone":"+1 780 961 3444",
    "sg:postcode":"T0G 1L0",
    "sg:province":"AB",
    "sg:tags":[
        "machine",
        "shop"
    ],
    "wof:name":"Legal Machine & Welding",
    "wof:placetype":"venue"
},
  "geometry": {"coordinates":[-113.598739624,53.9474868774],"type":"Point"}
}