{
  "type": "Feature",
  "properties": {
    "addr:full":"Cp 667 Succ Pointe-Claire Pointe-Claire QC H9R 4S8",
    "addr:postcode":"h9r 4s8",
    "addr:street":"Succ Pointe-Claire",
    "iso:country":"CA",
    "sg:address":"Cp 667 Succ Pointe-Claire",
    "sg:city":"Pointe-Claire",
    "sg:classifiers":[
        {
            "category":"Building & Trades",
            "subcategory":"Cleaning & Sanitation",
            "type":"Services"
        }
    ],
    "sg:phone":"+1 514 426 4215",
    "sg:postcode":"H9R 4S8",
    "sg:province":"QC",
    "sg:tags":[
        "house",
        "management",
        "real estate"
    ],
    "wof:name":"Domesti-Serv",
    "wof:placetype":"venue"
},
  "geometry": {"coordinates":[-73.817314,45.448025],"type":"Point"}
}