{
  "type": "Feature",
  "properties": {
    "addr:full":"391 Boul Du Seminaire N Saint-Jean-Sur-Richelieu QC J3B 8C5",
    "addr:housenumber":"391",
    "addr:postcode":"j3b 8c5",
    "addr:street":"Boul Du Seminaire N",
    "iso:country":"CA",
    "sg:address":"391 Boul Du Seminaire N",
    "sg:city":"Saint-Jean-Sur-Richelieu",
    "sg:classifiers":[
        {
            "category":"Shopping",
            "subcategory":"Computers & Home Electronics",
            "type":"Retail Goods"
        }
    ],
    "sg:phone":"+1 450 348 9377",
    "sg:postcode":"J3B 8C5",
    "sg:province":"QC",
    "sg:tags":[
        "equipment",
        "dealer"
    ],
    "wof:name":"Dumoulin Electronique Info",
    "wof:placetype":"venue"
},
  "geometry": {"coordinates":[-73.2649765015,45.3123626709],"type":"Point"}
}