{
  "type": "Feature",
  "properties": {
    "addr:full":"4020 Av Hingston Montreal QC H4A 2J7",
    "addr:housenumber":"4020",
    "addr:postcode":"h4a 2j7",
    "addr:street":"Av Hingston",
    "iso:country":"CA",
    "sg:address":"4020 Av Hingston",
    "sg:city":"Montreal",
    "sg:classifiers":[
        {
            "category":"Organizations",
            "subcategory":"Religious Organization",
            "type":"Services"
        }
    ],
    "sg:phone":"+1 514 486 1753",
    "sg:postcode":"H4A 2J7",
    "sg:province":"QC",
    "sg:tags":[
        "church"
    ],
    "wof:name":"St Columba Anglican Church",
    "wof:placetype":"venue"
},
  "geometry": {"coordinates":[-73.6239776611,45.4686851501],"type":"Point"}
}