{
  "type": "Feature",
  "properties": {
    "addr:full":"20399 Dewdney Trunk Rd Maple Ridge BC V2X 3E2",
    "addr:housenumber":"20399",
    "addr:postcode":"v2x 3e2",
    "addr:street":"Dewdney Trunk Rd",
    "iso:country":"CA",
    "sg:address":"20399 Dewdney Trunk Rd",
    "sg:city":"Maple Ridge",
    "sg:classifiers":[
        {
            "category":"Organizations",
            "subcategory":"Religious Organization",
            "type":"Services"
        }
    ],
    "sg:phone":"+1 604 465 5717",
    "sg:postcode":"V2X 3E2",
    "sg:province":"BC",
    "sg:tags":[
        "church"
    ],
    "wof:name":"Maple Ridge Alliance Church",
    "wof:placetype":"venue"
},
  "geometry": {"coordinates":[-122.655563355,49.2215385437],"type":"Point"}
}