{
  "type": "Feature",
  "properties": {
    "iso:country":"CA",
    "sg:address":"83 Rue Des Abenaquis",
    "sg:city":"Sherbrooke",
    "sg:classifiers":[
        {
            "category":"Organizations",
            "subcategory":"Professional Association",
            "type":"Services"
        }
    ],
    "sg:phone":"+1 819 562 8222",
    "sg:postcode":"J1H 1H1",
    "sg:province":"QC",
    "sg:tags":[
        "club"
    ],
    "wof:name":"Club DE Curling DE Sherbrooke",
    "wof:placetype":"venue"
},
  "geometry": {"coordinates":[-71.893288,45.405697],"type":"Point"}
}