{
  "type": "Feature",
  "properties": {
    "addr:full":"2520 Gladwin Pl North Vancouver BC V7R 4P8",
    "addr:housenumber":"2520",
    "addr:postcode":"v7r 4p8",
    "addr:street":"Gladwin Pl",
    "iso:country":"CA",
    "sg:address":"2520 Gladwin Pl",
    "sg:city":"North Vancouver",
    "sg:classifiers":[
        {
            "category":"Home & Garden",
            "subcategory":"Home Furnishings",
            "type":"Retail Goods"
        }
    ],
    "sg:phone":"+1 604 985 3269",
    "sg:postcode":"V7R 4P8",
    "sg:province":"BC",
    "sg:tags":[
        "curtain",
        "made",
        "drapery"
    ],
    "wof:name":"Tiffany Interiors",
    "wof:placetype":"venue"
},
  "geometry": {"coordinates":[-123.103622437,49.3326301575],"type":"Point"}
}