{
  "type": "Feature",
  "properties": {
    "iso:country":"CA",
    "sg:address":"19 Erie St S",
    "sg:city":"Leamington",
    "sg:classifiers":[
        {
            "category":"Personal",
            "subcategory":"Beauty Salon",
            "type":"Services"
        }
    ],
    "sg:phone":"+1 519 326 3543",
    "sg:postcode":"N8H 3A6",
    "sg:province":"ON",
    "wof:name":"Color Plus",
    "wof:placetype":"venue"
},
  "geometry": {"coordinates":[-82.5999984741,42.0526580811],"type":"Point"}
}