{
  "type": "Feature",
  "properties": {
    "addr:full":"1080 Boul Dr Albiny-Paquette Mont-Laurier QC J9L 1M1",
    "addr:housenumber":"1080",
    "addr:postcode":"j9l 1m1",
    "addr:street":"Boul Dr Albiny-Paquette",
    "iso:country":"CA",
    "sg:address":"1080 Boul Dr Albiny-Paquette",
    "sg:city":"Mont-Laurier",
    "sg:classifiers":[
        {
            "category":"Travel",
            "subcategory":"Hotels & Motels",
            "type":"Entertainment"
        }
    ],
    "sg:phone":"+1 819 623 2744",
    "sg:postcode":"J9L 1M1",
    "sg:province":"QC",
    "wof:name":"Motel Ideal",
    "wof:placetype":"venue"
},
  "geometry": {"coordinates":[-75.482338,46.550945],"type":"Point"}
}