{
  "type": "Feature",
  "properties": {
    "addr:full":"1047 S Trans Canada Hwy Cache Creek BC V0K 1H0",
    "addr:housenumber":"1047",
    "addr:postcode":"v0k 1h0",
    "addr:street":"S Trans Canada Hwy",
    "iso:country":"CA",
    "sg:address":"1047 S Trans Canada Hwy",
    "sg:city":"Cache Creek",
    "sg:classifiers":[
        {
            "category":"Banks & Credit Unions",
            "subcategory":"Bank",
            "type":"Services"
        }
    ],
    "sg:phone":"+1 250 457 6287",
    "sg:postcode":"V0K 1H0",
    "sg:province":"BC",
    "wof:name":"Royal Bank Financial Group",
    "wof:placetype":"venue"
},
  "geometry": {"coordinates":[-121.316856,50.789642],"type":"Point"}
}