{
  "type": "Feature",
  "properties": {
    "addr:full":"205 Main St Shell Lake SK S0J 2G0",
    "addr:housenumber":"205",
    "addr:postcode":"s0j 2g0",
    "addr:street":"Main St",
    "iso:country":"CA",
    "sg:address":"205 Main St",
    "sg:city":"Shell Lake",
    "sg:classifiers":[
        {
            "category":"Insurance",
            "subcategory":"Insurance Agent",
            "type":"Services"
        }
    ],
    "sg:phone":"+1 306 427 2255",
    "sg:postcode":"S0J 2G0",
    "sg:province":"SK",
    "wof:name":"Shell Lake Agency",
    "wof:placetype":"venue"
},
  "geometry": {"coordinates":[-107.065262,53.305565],"type":"Point"}
}