{
  "type": "Feature",
  "properties": {
    "addr:full":"1636 Charles St #2 Whitby ON L1N 1B9",
    "addr:housenumber":"1636",
    "addr:postcode":"l1n 1b9",
    "addr:street":"Charles St # 2",
    "iso:country":"CA",
    "sg:address":"1636 Charles St #2",
    "sg:city":"Whitby",
    "sg:classifiers":[
        {
            "category":"Professional",
            "type":"Services"
        }
    ],
    "sg:phone":"+1 905 668 0207",
    "sg:postcode":"L1N 1B9",
    "sg:province":"ON",
    "sg:tags":[
        "equipment",
        "establishment",
        "boat",
        "supply"
    ],
    "wof:name":"Skippers Choice Products Inc",
    "wof:placetype":"venue"
},
  "geometry": {"coordinates":[-78.93607299999999,43.860909],"type":"Point"}
}