{
  "type": "Feature",
  "properties": {
    "addr:full":"Montreal QC H3C 1A8",
    "addr:postcode":"h3c 1a8",
    "iso:country":"CA",
    "sg:city":"Montreal",
    "sg:classifiers":[
        {
            "category":"Wholesale",
            "subcategory":"Furniture",
            "type":"Manufacturing & Wholesale Goods"
        }
    ],
    "sg:phone":"+1 514 866 4331",
    "sg:postcode":"H3C 1A8",
    "sg:province":"QC",
    "wof:name":"Global Upholstery CO",
    "wof:placetype":"venue"
},
  "geometry": {"coordinates":[-73.552071,45.514362],"type":"Point"}
}