{
  "type": "Feature",
  "properties": {
    "addr:full":"Calgary AB T2E 6W4",
    "addr:postcode":"t2e 6w4",
    "iso:country":"CA",
    "sg:city":"Calgary",
    "sg:classifiers":[
        {
            "category":"Home & Garden",
            "subcategory":"Building Materials",
            "type":"Retail Goods"
        }
    ],
    "sg:phone":"+1 403 250 8930",
    "sg:postcode":"T2E 6W4",
    "sg:province":"AB",
    "sg:tags":[
        "glass",
        "window",
        "plate"
    ],
    "wof:name":"Dominion Auto Glass",
    "wof:placetype":"venue"
},
  "geometry": {"coordinates":[-114.011062622,51.0840682983],"type":"Point"}
}