{
  "type": "Feature",
  "properties": {
    "addr:full":"456 5th Ave W Vancouver BC V5Y 3Z3",
    "addr:housenumber":"456",
    "addr:postcode":"v5y 3z3",
    "addr:street":"5Th Ave W",
    "iso:country":"CA",
    "sg:address":"456 5th Ave W",
    "sg:city":"Vancouver",
    "sg:classifiers":[
        {
            "category":"Insurance",
            "subcategory":"Insurance Agent",
            "type":"Services"
        }
    ],
    "sg:phone":"+1 604 871 2300",
    "sg:postcode":"V5Y 3Z3",
    "sg:province":"BC",
    "wof:name":"Insurance Corp of BC",
    "wof:placetype":"venue"
},
  "geometry": {"coordinates":[-123.113769531,49.2665176392],"type":"Point"}
}