{
  "type": "Feature",
  "properties": {
    "addr:full":"1890 Rue Notre-Dame N Thetford Mines QC G6G 2W2",
    "addr:housenumber":"1890",
    "addr:postcode":"g6g 2w2",
    "addr:street":"Rue Notre-Dame N",
    "iso:country":"CA",
    "sg:address":"1890 Rue Notre-Dame N",
    "sg:city":"Thetford Mines",
    "sg:classifiers":[
        {
            "category":"Manufacturing",
            "subcategory":"Tools & Machinery",
            "type":"Manufacturing & Wholesale Goods"
        }
    ],
    "sg:phone":"+1 418 335 7220",
    "sg:postcode":"G6G 2W2",
    "sg:province":"QC",
    "sg:tags":[
        "machine",
        "shop"
    ],
    "wof:name":"Atelier Adrien Bernard Inc",
    "wof:placetype":"venue"
},
  "geometry": {"coordinates":[-71.18993377690001,46.1587219238],"type":"Point"}
}