{
  "type": "Feature",
  "properties": {
    "addr:full":"Niagara Falls ON L2G 3V9",
    "addr:postcode":"l2g 3v9",
    "iso:country":"CA",
    "sg:city":"Niagara Falls",
    "sg:classifiers":[
        {
            "category":"Travel",
            "subcategory":"Hotels & Motels",
            "type":"Entertainment"
        }
    ],
    "sg:phone":"+1 905 357 7377",
    "sg:postcode":"L2G 3V9",
    "sg:province":"ON",
    "wof:name":"Hospitality Motels Ltd",
    "wof:placetype":"venue"
},
  "geometry": {"coordinates":[-79.0829238892,43.082824707],"type":"Point"}
}