{
  "type": "Feature",
  "properties": {
    "addr:full":"471 Pemberton Terr Kamloops BC V2C 1T6",
    "addr:housenumber":"471",
    "addr:postcode":"bc v2c 1t6",
    "addr:street":"Pemberton Terr",
    "iso:country":"CA",
    "sg:address":"471 Pemberton Terr",
    "sg:city":"Kamloops",
    "sg:classifiers":[
        {
            "category":"Home & Garden",
            "subcategory":"Garden Supply",
            "type":"Retail Goods"
        }
    ],
    "sg:phone":"+1 250 372 1835",
    "sg:postcode":"V2C 1T6",
    "sg:province":"BC",
    "sg:tags":[
        "lawn",
        "business"
    ],
    "wof:name":"All Things Organic",
    "wof:placetype":"venue"
},
  "geometry": {"coordinates":[-120.351135254,50.6725997925],"type":"Point"}
}