{
  "type": "Feature",
  "properties": {
    "addr:full":"370 King St W Kingston ON K7L 2X4",
    "addr:housenumber":"370",
    "addr:postcode":"k7l 2x4",
    "addr:street":"King St W",
    "iso:country":"CA",
    "sg:address":"370 King St W",
    "sg:city":"Kingston",
    "sg:classifiers":[
        {
            "category":"Home & Garden",
            "subcategory":"Home Furnishings",
            "type":"Retail Goods"
        }
    ],
    "sg:phone":"+1 613 546 1437",
    "sg:postcode":"K7L 2X4",
    "sg:province":"ON",
    "sg:tags":[
        "pottery"
    ],
    "wof:name":"Kingston Potter's Guild",
    "wof:placetype":"venue"
},
  "geometry": {"coordinates":[-76.506569,44.221432],"type":"Point"}
}