{
  "type": "Feature",
  "properties": {
    "iso:country":"CA",
    "sg:address":"5885 Boul Cavendish",
    "sg:city":"Cote Saint-Luc",
    "sg:classifiers":[
        {
            "category":"Health Services",
            "subcategory":"Nursing And Care Facility",
            "type":"Services"
        }
    ],
    "sg:phone":"+1 514 485 5994",
    "sg:postcode":"H4W 3H4",
    "sg:province":"QC",
    "sg:tags":[
        "home",
        "retirement",
        "community"
    ],
    "wof:name":"Manoir Montefiore",
    "wof:placetype":"venue"
},
  "geometry": {"coordinates":[-73.666252,45.478176],"type":"Point"}
}