{
  "type": "Feature",
  "properties": {
    "iso:country":"CA",
    "sg:address":"114 Rue Isabelle",
    "sg:city":"Lyster",
    "sg:classifiers":[
        {
            "category":"Organizations",
            "subcategory":"Professional Association",
            "type":"Services"
        }
    ],
    "sg:phone":"+1 819 389 5488",
    "sg:postcode":"G0S 1V0",
    "sg:province":"QC",
    "wof:name":"Chevalier DE Colomb",
    "wof:placetype":"venue"
},
  "geometry": {"coordinates":[-71.5879364014,46.3734855652],"type":"Point"}
}