{
  "type": "Feature",
  "properties": {
    "addr:full":"16 William St S Lindsay ON K9V 3A4",
    "addr:housenumber":"16",
    "addr:postcode":"k9v 3a4",
    "addr:street":"William St S",
    "iso:country":"CA",
    "sg:address":"16 William St S",
    "sg:city":"Lindsay",
    "sg:classifiers":[
        {
            "category":"Banks & Credit Unions",
            "subcategory":"Bank",
            "type":"Services"
        }
    ],
    "sg:phone":"+1 705 324 3521",
    "sg:postcode":"K9V 3A4",
    "sg:province":"ON",
    "wof:name":"Bank of Montreal",
    "wof:placetype":"venue"
},
  "geometry": {"coordinates":[-78.7366485596,44.3545532227],"type":"Point"}
}