{
  "type": "Feature",
  "properties": {
    "addr:full":"4680 Rue Principale Lourdes-DE-Joliette QC J0K 1K0",
    "addr:housenumber":"4680",
    "addr:postcode":"j0k 1k0",
    "addr:street":"Rue Principale",
    "iso:country":"CA",
    "sg:address":"4680 Rue Principale",
    "sg:city":"Lourdes-DE-Joliette",
    "sg:classifiers":[
        {
            "category":"Recreation",
            "type":"Entertainment"
        }
    ],
    "sg:phone":"+1 450 752 0385",
    "sg:postcode":"J0K 1K0",
    "sg:province":"QC",
    "sg:tags":[
        "parachute",
        "skydiving",
        "jumping"
    ],
    "wof:name":"Centre Ecole DE Parachutisme",
    "wof:placetype":"venue"
},
  "geometry": {"coordinates":[-73.42775726319999,46.0992202759],"type":"Point"}
}