{
  "type": "Feature",
  "properties": {
    "iso:country":"CA",
    "sg:address":"1038 Rang Saint-Joseph",
    "sg:city":"Saint-Flavien",
    "sg:classifiers":[
        {
            "category":"Retail",
            "subcategory":"Auto Repair",
            "type":"Services"
        }
    ],
    "sg:phone":"+1 418 728 3770",
    "sg:postcode":"G0S 2M0",
    "sg:province":"QC",
    "sg:tags":[
        "repairing",
        "automobile"
    ],
    "wof:name":"Mecanique Import Lotbiniere",
    "wof:placetype":"venue"
},
  "geometry": {"coordinates":[-71.6103210449,46.5233764648],"type":"Point"}
}