{
  "type": "Feature",
  "properties": {
    "addr:full":"11595 Rue Victoria Pointe-Aux-Trembles QC H1B 2P4",
    "addr:housenumber":"11595",
    "addr:postcode":"h1b 2p4",
    "addr:street":"Rue Victoria",
    "iso:country":"CA",
    "sg:address":"11595 Rue Victoria",
    "sg:city":"Pointe-Aux-Trembles",
    "sg:classifiers":[
        {
            "category":"Building & Trades",
            "subcategory":"Electrical",
            "type":"Services"
        }
    ],
    "sg:phone":"+1 514 645 2627",
    "sg:postcode":"H1B 2P4",
    "sg:province":"QC",
    "sg:tags":[
        "electric",
        "contractor"
    ],
    "wof:name":"B V Electrique Inc",
    "wof:placetype":"venue"
},
  "geometry": {"coordinates":[-73.49653625489999,45.6348152161],"type":"Point"}
}