{
  "type": "Feature",
  "properties": {
    "addr:full":"4001 Whistler Way Whistler BC V0N 1B4",
    "addr:housenumber":"4001",
    "addr:postcode":"v0n 1b4",
    "addr:street":"Whistler Way",
    "iso:country":"CA",
    "sg:address":"4001 Whistler Way",
    "sg:city":"Whistler",
    "sg:classifiers":[
        {
            "category":"Sports & Exercise",
            "subcategory":"Golf",
            "type":"Entertainment"
        }
    ],
    "sg:phone":"+1 604 932 3280",
    "sg:postcode":"V0N 1B4",
    "sg:province":"BC",
    "sg:tags":[
        "course"
    ],
    "wof:name":"Whistler Golf Club",
    "wof:placetype":"venue"
},
  "geometry": {"coordinates":[-122.958878,50.11496],"type":"Point"}
}