{
  "type": "Feature",
  "properties": {
    "addr:full":"Burnaby BC V5A 3C2",
    "addr:postcode":"v5a 3c2",
    "iso:country":"CA",
    "sg:city":"Burnaby",
    "sg:classifiers":[
        {
            "category":"Retail",
            "subcategory":"Repair Shop",
            "type":"Services"
        }
    ],
    "sg:phone":"+1 604 415 3456",
    "sg:postcode":"V5A 3C2",
    "sg:province":"BC",
    "sg:tags":[
        "marine",
        "electric"
    ],
    "wof:name":"G Neill Marine Electric Ltd",
    "wof:placetype":"venue"
},
  "geometry": {"coordinates":[-122.92778800000001,49.257469],"type":"Point"}
}