{
  "type": "Feature",
  "properties": {
    "iso:country":"CA",
    "sg:address":"707 Rte DE LA Ferme-Rouge",
    "sg:city":"Mont-Laurier",
    "sg:classifiers":[
        {
            "category":"Travel",
            "subcategory":"Hotels & Motels",
            "type":"Entertainment"
        }
    ],
    "sg:phone":"+1 819 623 2628",
    "sg:postcode":"J9L 3G3",
    "sg:province":"QC",
    "sg:tags":[
        "breakfast",
        "accommodation",
        "bed"
    ],
    "wof:name":"Reve Blanc",
    "wof:placetype":"venue"
},
  "geometry": {"coordinates":[-75.49495697019999,46.5242156982],"type":"Point"}
}