{
  "type": "Feature",
  "properties": {
    "addr:full":"243 Kingston St Victoria BC V8V 1V5",
    "addr:housenumber":"243",
    "addr:postcode":"v8v 1v5",
    "addr:street":"Kingston St",
    "iso:country":"CA",
    "sg:address":"243 Kingston St",
    "sg:city":"Victoria",
    "sg:classifiers":[
        {
            "category":"Travel",
            "subcategory":"Hotels & Motels",
            "type":"Entertainment"
        }
    ],
    "sg:phone":"+1 250 384 9995",
    "sg:postcode":"V8V 1V5",
    "sg:province":"BC",
    "sg:tags":[
        "breakfast",
        "accommodation",
        "bed"
    ],
    "wof:name":"Haterleigh Heritage B & B",
    "wof:placetype":"venue"
},
  "geometry": {"coordinates":[-123.378044128,48.4213104248],"type":"Point"}
}