{
  "type": "Feature",
  "properties": {
    "addr:full":"89 Rue Larivee Vaudreuil-Dorion QC J7V 8P5",
    "addr:housenumber":"89",
    "addr:postcode":"j7v 8p5",
    "addr:street":"Rue Larivee",
    "iso:country":"CA",
    "sg:address":"89 Rue Larivee",
    "sg:city":"Vaudreuil-Dorion",
    "sg:classifiers":[
        {
            "category":"Retail",
            "subcategory":"Laundry & Dry Cleaning",
            "type":"Services"
        }
    ],
    "sg:phone":"+1 450 455 9257",
    "sg:postcode":"J7V 8P5",
    "sg:province":"QC",
    "sg:tags":[
        "cleaners",
        "rug",
        "carpet"
    ],
    "wof:name":"Entreprises Sr Warburton",
    "wof:placetype":"venue"
},
  "geometry": {"coordinates":[-74.055359,45.415951],"type":"Point"}
}