{
  "type": "Feature",
  "properties": {
    "addr:full":"449 Craig St Parksville BC V9P 1L2",
    "addr:housenumber":"449",
    "addr:postcode":"v9p 1l2",
    "addr:street":"Craig St",
    "iso:country":"CA",
    "sg:address":"449 Craig St",
    "sg:city":"Parksville",
    "sg:classifiers":[
        {
            "category":"Building & Trades",
            "subcategory":"Landscaping Services",
            "type":"Services"
        }
    ],
    "sg:phone":"+1 250 954 0107",
    "sg:postcode":"V9P 1L2",
    "sg:province":"BC",
    "sg:tags":[
        "landscape",
        "contractor"
    ],
    "wof:name":"Mammoth Landscaping & Masonry",
    "wof:placetype":"venue"
},
  "geometry": {"coordinates":[-124.312202454,49.3098106384],"type":"Point"}
}