{
  "type": "Feature",
  "properties": {
    "addr:full":"538 Park St Kenora ON P9N 1A1",
    "addr:housenumber":"538",
    "addr:postcode":"p9n 1a1",
    "addr:street":"Park St",
    "iso:country":"CA",
    "sg:address":"538 Park St",
    "sg:city":"Kenora",
    "sg:classifiers":[
        {
            "category":"Food & Beverages",
            "subcategory":"Bakery",
            "type":"Retail Goods"
        }
    ],
    "sg:phone":"+1 807 468 9349",
    "sg:postcode":"P9N 1A1",
    "sg:province":"ON",
    "sg:tags":[
        "grocer"
    ],
    "wof:name":"Extra Foods Bakery",
    "wof:placetype":"venue"
},
  "geometry": {"coordinates":[-94.4841308594,49.7670707703],"type":"Point"}
}