{
  "type": "Feature",
  "properties": {
    "addr:full":"14 Carluke Cres North York ON M2L 2H8",
    "addr:housenumber":"14",
    "addr:postcode":"m2l 2h8",
    "addr:street":"Carluke Cres",
    "iso:country":"CA",
    "sg:address":"14 Carluke Cres",
    "sg:city":"North York",
    "sg:classifiers":[
        {
            "category":"Shopping",
            "subcategory":"Discount & Variety Stores",
            "type":"Retail Goods"
        }
    ],
    "sg:phone":"+1 416 221 7091",
    "sg:postcode":"M2L 2H8",
    "sg:province":"ON",
    "wof:name":"Edward's Tuck Shop",
    "wof:placetype":"venue"
},
  "geometry": {"coordinates":[-79.39118999999999,43.75983],"type":"Point"}
}