{
  "type": "Feature",
  "properties": {
    "addr:full":"711 Rue Cowie Granby QC J2G 3X5",
    "addr:housenumber":"711",
    "addr:postcode":"j2g 3x5",
    "addr:street":"Rue Cowie",
    "iso:country":"CA",
    "sg:address":"711 Rue Cowie",
    "sg:city":"Granby",
    "sg:classifiers":[
        {
            "category":"Autos & Motor Vehicles",
            "subcategory":"Motorcycle Sales",
            "type":"Retail Goods"
        }
    ],
    "sg:phone":"+1 450 378 8336",
    "sg:postcode":"J2G 3X5",
    "sg:province":"QC",
    "wof:name":"V-2 Obsession Inc",
    "wof:placetype":"venue"
},
  "geometry": {"coordinates":[-72.75007600000001,45.394543],"type":"Point"}
}