{
  "type": "Feature",
  "properties": {
    "addr:full":"Levis QC G6V 6C3",
    "addr:postcode":"g6v 6c3",
    "iso:country":"CA",
    "sg:city":"Levis",
    "sg:classifiers":[
        {
            "category":"Restaurant",
            "type":"Food & Drink"
        }
    ],
    "sg:phone":"+1 418 835 1234",
    "sg:postcode":"G6V 6C3",
    "sg:province":"QC",
    "wof:name":"Les Rotisseries St-Hubert DE L",
    "wof:placetype":"venue"
},
  "geometry": {"coordinates":[-71.177254,46.796085],"type":"Point"}
}