{
  "type": "Feature",
  "properties": {
    "iso:country":"CA",
    "sg:address":"67 Elizabeth Dr",
    "sg:city":"Gander",
    "sg:classifiers":[
        {
            "category":"Restaurant",
            "type":"Food & Drink"
        }
    ],
    "sg:phone":"+1 709 256 7429",
    "sg:postcode":"A1V 1J9",
    "sg:province":"NL",
    "wof:name":"East Ocean Restaurant",
    "wof:placetype":"venue"
},
  "geometry": {"coordinates":[-54.6084747314,48.9560928345],"type":"Point"}
}