{
  "type": "Feature",
  "properties": {
    "addr:full":"87 Av D'Amours Matane QC G4W 2X5",
    "addr:postcode":"g4w 2x5",
    "addr:street":"87 Av D'Amours",
    "iso:country":"CA",
    "sg:address":"87 Av D'Amours",
    "sg:city":"Matane",
    "sg:classifiers":[
        {
            "category":"Food & Beverages",
            "subcategory":"Groceries & Convenience Stores",
            "type":"Retail Goods"
        }
    ],
    "sg:phone":"+1 418 562 6202",
    "sg:postcode":"G4W 2X5",
    "sg:province":"QC",
    "sg:tags":[
        "grocer"
    ],
    "wof:name":"Sobeys Quebec",
    "wof:placetype":"venue"
},
  "geometry": {"coordinates":[-67.529419,48.84502],"type":"Point"}
}