{
  "type": "Feature",
  "properties": {
    "addr:full":"550 10th St Hanover ON N4N 1R5",
    "addr:housenumber":"550",
    "addr:postcode":"n4n 1r5",
    "addr:street":"10Th St",
    "iso:country":"CA",
    "sg:address":"550 10th St",
    "sg:city":"Hanover",
    "sg:classifiers":[
        {
            "category":"Health Services",
            "subcategory":"Medical Lab",
            "type":"Services"
        }
    ],
    "sg:phone":"+1 519 364 3223",
    "sg:postcode":"N4N 1R5",
    "sg:province":"ON",
    "sg:tags":[
        "hearing",
        "equipment",
        "supply",
        "impaired"
    ],
    "wof:name":"Hanover Denture Clinic",
    "wof:placetype":"venue"
},
  "geometry": {"coordinates":[-81.01849365229999,44.1535797119],"type":"Point"}
}