{
  "type": "Feature",
  "properties": {
    "addr:full":"Catalina NL A0C 1J0",
    "addr:postcode":"a0c 1j0",
    "iso:country":"CA",
    "sg:city":"Catalina",
    "sg:classifiers":[
        {
            "category":"Recreation",
            "type":"Entertainment"
        }
    ],
    "sg:phone":"+1 709 469 3344",
    "sg:postcode":"A0C 1J0",
    "sg:province":"NL",
    "sg:tags":[
        "center"
    ],
    "wof:name":"Port Union Recreation Chalet",
    "wof:placetype":"venue"
},
  "geometry": {"coordinates":[-53.0776176453,48.5178451538],"type":"Point"}
}