{
  "type": "Feature",
  "properties": {
    "addr:full":"209 Alder St W Dunnville ON N1A 1R3",
    "addr:housenumber":"209",
    "addr:postcode":"n1a 1r3",
    "addr:street":"Alder St W",
    "iso:country":"CA",
    "sg:address":"209 Alder St W",
    "sg:city":"Dunnville",
    "sg:classifiers":[
        {
            "category":"Education",
            "subcategory":"School",
            "type":"Public Place"
        }
    ],
    "sg:phone":"+1 905 774 6052",
    "sg:postcode":"N1A 1R3",
    "sg:province":"ON",
    "wof:name":"St Michael's School",
    "wof:placetype":"venue"
},
  "geometry": {"coordinates":[-79.62041499999999,42.905807],"type":"Point"}
}