{
  "type": "Feature",
  "properties": {
    "addr:full":"Kitchener ON N2K 1B2",
    "addr:postcode":"n2k 1b2",
    "iso:country":"CA",
    "sg:city":"Kitchener",
    "sg:classifiers":[
        {
            "category":"Manufacturing",
            "subcategory":"Metals",
            "type":"Manufacturing & Wholesale Goods"
        }
    ],
    "sg:phone":"+1 519 741 5080",
    "sg:postcode":"N2K 1B2",
    "sg:province":"ON",
    "sg:tags":[
        "equipment",
        "heating",
        "system"
    ],
    "wof:name":"Rapid Duct Supply",
    "wof:placetype":"venue"
},
  "geometry": {"coordinates":[-80.475815,43.479965],"type":"Point"}
}