{
  "type": "Feature",
  "properties": {
    "addr:full":"Edmonton AB T5K 2J1",
    "addr:postcode":"t5k 2j1",
    "iso:country":"CA",
    "sg:city":"Edmonton",
    "sg:classifiers":[
        {
            "category":"Health Services",
            "subcategory":"Health Practitioner",
            "type":"Services"
        }
    ],
    "sg:phone":"+1 780 454 7586",
    "sg:postcode":"T5K 2J1",
    "sg:province":"AB",
    "sg:tags":[
        "psychologist"
    ],
    "wof:name":"Sacks, Moira L PhD",
    "wof:placetype":"venue"
},
  "geometry": {"coordinates":[-113.514167786,53.5399055481],"type":"Point"}
}