{
  "type": "Feature",
  "properties": {
    "addr:full":"280 7th Ave E Vancouver BC V5T 4L7",
    "addr:housenumber":"280",
    "addr:postcode":"v5t 4l7",
    "addr:street":"7Th Ave E",
    "iso:country":"CA",
    "sg:address":"280 7th Ave E",
    "sg:city":"Vancouver",
    "sg:classifiers":[
        {
            "category":"Retail",
            "subcategory":"Auto Repair",
            "type":"Services"
        }
    ],
    "sg:phone":"+1 604 875 6666",
    "sg:postcode":"V5T 4L7",
    "sg:province":"BC",
    "sg:tags":[
        "body",
        "automobile",
        "painting"
    ],
    "wof:name":"Auto Mind Collision Repair",
    "wof:placetype":"venue"
},
  "geometry": {"coordinates":[-123.099411011,49.2644691467],"type":"Point"}
}