{
  "type": "Feature",
  "properties": {
    "addr:full":"520 Dawn Mills Rd Dresden ON N0P 1M0",
    "addr:housenumber":"520",
    "addr:postcode":"n0p 1m0",
    "addr:street":"Dawn Mills Rd",
    "iso:country":"CA",
    "sg:address":"520 Dawn Mills Rd",
    "sg:city":"Dresden",
    "sg:classifiers":[
        {
            "category":"Wholesale",
            "subcategory":"Farm Supplies",
            "type":"Manufacturing & Wholesale Goods"
        }
    ],
    "sg:phone":"+1 519 692 3918",
    "sg:postcode":"N0P 1M0",
    "sg:province":"ON",
    "wof:name":"Southwest Ag",
    "wof:placetype":"venue"
},
  "geometry": {"coordinates":[-82.179642,42.58952],"type":"Point"}
}