{
  "type": "Feature",
  "properties": {
    "addr:full":"37 Normandy Gdns London ON N6H 4B1",
    "addr:housenumber":"37",
    "addr:postcode":"n6h 4b1",
    "addr:street":"Normandy Gdns",
    "iso:country":"CA",
    "sg:address":"37 Normandy Gdns",
    "sg:city":"London",
    "sg:classifiers":[
        {
            "category":"Building & Trades",
            "subcategory":"Construction",
            "type":"Services"
        }
    ],
    "sg:phone":"+1 519 472 2243",
    "sg:postcode":"N6H 4B1",
    "sg:province":"ON",
    "sg:tags":[
        "home",
        "improvement"
    ],
    "wof:name":"Pym & Cooper Custom Homes Inc",
    "wof:placetype":"venue"
},
  "geometry": {"coordinates":[-81.328636,42.97691],"type":"Point"}
}