{
  "type": "Feature",
  "properties": {
    "addr:full":"1451 Rue Sherbrooke O Montreal QC H3G 2S8",
    "addr:housenumber":"1451",
    "addr:postcode":"h3g 2s8",
    "addr:street":"Rue Sherbrooke O",
    "iso:country":"CA",
    "sg:address":"1451 Rue Sherbrooke O",
    "sg:city":"Montreal",
    "sg:classifiers":[
        {
            "category":"Shopping",
            "type":"Retail Goods"
        }
    ],
    "sg:phone":"+1 514 989 1529",
    "sg:postcode":"H3G 2S8",
    "sg:province":"QC",
    "sg:tags":[
        "art",
        "gallery",
        "dealer"
    ],
    "wof:name":"Galerie Bernard Seguin Poirier",
    "wof:placetype":"venue"
},
  "geometry": {"coordinates":[-73.56471252439999,45.5258636475],"type":"Point"}
}