{
  "type": "Feature",
  "properties": {
    "addr:full":"130 Main St Balcarres SK S0G 0C0",
    "addr:housenumber":"130",
    "addr:postcode":"s0g 0c0",
    "addr:street":"Main St",
    "iso:country":"CA",
    "sg:address":"130 Main St",
    "sg:city":"Balcarres",
    "sg:classifiers":[
        {
            "category":"Education",
            "subcategory":"School",
            "type":"Public Place"
        }
    ],
    "sg:phone":"+1 306 334 3100",
    "sg:postcode":"S0G 0C0",
    "sg:province":"SK",
    "wof:name":"Peepeekisis Pesakastew School",
    "wof:placetype":"venue"
},
  "geometry": {"coordinates":[-103.544250488,50.8022117615],"type":"Point"}
}