{
  "type": "Feature",
  "properties": {
    "addr:full":"400 Crawford St South Porcupine ON P0N 1H0",
    "addr:housenumber":"400",
    "addr:postcode":"p0n 1h0",
    "addr:street":"Crawford St",
    "iso:country":"CA",
    "sg:address":"400 Crawford St",
    "sg:city":"South Porcupine",
    "sg:classifiers":[
        {
            "category":"Building & Trades",
            "subcategory":"Construction",
            "type":"Services"
        }
    ],
    "sg:phone":"+1 705 235 5171",
    "sg:postcode":"P0N 1H0",
    "sg:province":"ON",
    "sg:tags":[
        "general",
        "contractor"
    ],
    "wof:name":"Sangiuliano Developments Ltd",
    "wof:placetype":"venue"
},
  "geometry": {"coordinates":[-81.20849609379999,48.4885902405],"type":"Point"}
}