{
  "type": "Feature",
  "properties": {
    "iso:country":"CA",
    "sg:address":"202 Mclean Ave",
    "sg:city":"Selkirk",
    "sg:classifiers":[
        {
            "category":"Organizations",
            "subcategory":"Religious Organization",
            "type":"Services"
        }
    ],
    "sg:phone":"+1 204 482 5914",
    "sg:postcode":"R1A 0T6",
    "sg:province":"MB",
    "sg:tags":[
        "church"
    ],
    "wof:name":"United Church Selkirk",
    "wof:placetype":"venue"
},
  "geometry": {"coordinates":[-96.87255859379999,50.1413803101],"type":"Point"}
}