{
  "type": "Feature",
  "properties": {
    "iso:country":"CA",
    "sg:address":"14 Ames Cir",
    "sg:city":"North York",
    "sg:classifiers":[
        {
            "category":"Food & Beverages",
            "subcategory":"Liquor & Beverages",
            "type":"Retail Goods"
        }
    ],
    "sg:phone":"+1 416 443 2020",
    "sg:postcode":"M3B 3B8",
    "sg:province":"ON",
    "sg:tags":[
        "beer",
        "ale"
    ],
    "wof:name":"Fine Beers Agency Ltd",
    "wof:placetype":"venue"
},
  "geometry": {"coordinates":[-79.36655426030001,43.7501754761],"type":"Point"}
}