{
  "type": "Feature",
  "properties": {
    "addr:full":"579 Woodward Ave Hamilton ON L8H 6P2",
    "addr:housenumber":"579",
    "addr:postcode":"l8h 6p2",
    "addr:street":"Woodward Ave",
    "iso:country":"CA",
    "sg:address":"579 Woodward Ave",
    "sg:city":"Hamilton",
    "sg:classifiers":[
        {
            "category":"Wholesale",
            "subcategory":"Machinery & Supplies",
            "type":"Manufacturing & Wholesale Goods"
        }
    ],
    "sg:phone":"+1 905 545 5566",
    "sg:postcode":"L8H 6P2",
    "sg:province":"ON",
    "sg:tags":[
        "contractor"
    ],
    "wof:name":"Axess Rentals",
    "wof:placetype":"venue"
},
  "geometry": {"coordinates":[-79.7766799927,43.248336792],"type":"Point"}
}