{
  "type": "Feature",
  "properties": {
    "addr:full":"19 Robinson St Simcoe ON N3Y 1W3",
    "addr:housenumber":"19",
    "addr:postcode":"n3y 1w3",
    "addr:street":"Robinson St",
    "iso:country":"CA",
    "sg:address":"19 Robinson St",
    "sg:city":"Simcoe",
    "sg:classifiers":[
        {
            "category":"Home & Garden",
            "subcategory":"Household Appliances",
            "type":"Retail Goods"
        }
    ],
    "sg:phone":"+1 519 426 8124",
    "sg:postcode":"N3Y 1W3",
    "sg:province":"ON",
    "sg:tags":[
        "machine",
        "sewing"
    ],
    "wof:name":"Mark's Sewing Ctr CO",
    "wof:placetype":"venue"
},
  "geometry": {"coordinates":[-80.3046417236,42.8373031616],"type":"Point"}
}