{
  "type": "Feature",
  "properties": {
    "addr:full":"85 Morley St Hamilton ON L8H 3R8",
    "addr:housenumber":"85",
    "addr:postcode":"l8h 3r8",
    "addr:street":"Morley St",
    "iso:country":"CA",
    "sg:address":"85 Morley St",
    "sg:city":"Hamilton",
    "sg:classifiers":[
        {
            "category":"Wholesale",
            "subcategory":"Electrical",
            "type":"Manufacturing & Wholesale Goods"
        }
    ],
    "sg:phone":"+1 905 547 8040",
    "sg:postcode":"L8H 3R8",
    "sg:province":"ON",
    "sg:tags":[
        "equipment",
        "electric",
        "supply"
    ],
    "wof:name":"Graybar Electric Ontario Ltd",
    "wof:placetype":"venue"
},
  "geometry": {"coordinates":[-79.780434,43.249977],"type":"Point"}
}