{
  "type": "Feature",
  "properties": {
    "addr:full":"4403 68 Ave NW Edmonton AB T6B 2N2",
    "addr:housenumber":"4403",
    "addr:postcode":"t6b 2n2",
    "addr:street":"68 Ave Nw",
    "iso:country":"CA",
    "sg:address":"4403 68 Ave NW",
    "sg:city":"Edmonton",
    "sg:classifiers":[
        {
            "category":"Building & Trades",
            "subcategory":"Plumbing",
            "type":"Services"
        }
    ],
    "sg:phone":"+1 780 465 2931",
    "sg:postcode":"T6B 2N2",
    "sg:province":"AB",
    "sg:tags":[
        "sheet",
        "work",
        "metal",
        "contractor"
    ],
    "wof:name":"Paragon Ventilation Ltd",
    "wof:placetype":"venue"
},
  "geometry": {"coordinates":[-113.411789,53.504761],"type":"Point"}
}