{
  "type": "Feature",
  "properties": {
    "addr:full":"Hwy 16A Evansburg AB T0E 0T0",
    "addr:postcode":"t0e 0t0",
    "addr:street":"Hwy 16A",
    "iso:country":"CA",
    "sg:address":"Hwy 16A",
    "sg:city":"Evansburg",
    "sg:classifiers":[
        {
            "category":"Organizations",
            "subcategory":"Religious Organization",
            "type":"Services"
        }
    ],
    "sg:phone":"+1 780 727 2800",
    "sg:postcode":"T0E 0T0",
    "sg:province":"AB",
    "sg:tags":[
        "church"
    ],
    "wof:name":"Kingdon Hall-Jehovah's Witness",
    "wof:placetype":"venue"
},
  "geometry": {"coordinates":[-115.009598,53.599319],"type":"Point"}
}