{
  "type": "Feature",
  "properties": {
    "addr:full":"11 Victoria St # 4 Barrie ON L4N 6T3",
    "addr:housenumber":"11",
    "addr:postcode":"l4n 6t3",
    "addr:street":"Victoria St # 4",
    "iso:country":"CA",
    "sg:address":"11 Victoria St # 4",
    "sg:city":"Barrie",
    "sg:classifiers":[
        {
            "category":"Personal",
            "subcategory":"Massage",
            "type":"Services"
        }
    ],
    "sg:phone":"+1 705 721 0015",
    "sg:postcode":"L4N 6T3",
    "sg:province":"ON",
    "wof:name":"Victoria Plaza Health Spa",
    "wof:placetype":"venue"
},
  "geometry": {"coordinates":[-79.691383,44.381279],"type":"Point"}
}