{
  "type": "Feature",
  "properties": {
    "addr:full":"301 Mackenzie Ave Revelstoke BC V0E 2S0",
    "addr:housenumber":"301",
    "addr:postcode":"v0e 2s0",
    "addr:street":"Mackenzie Ave",
    "iso:country":"CA",
    "sg:address":"301 Mackenzie Ave",
    "sg:city":"Revelstoke",
    "sg:classifiers":[
        {
            "category":"Retail",
            "subcategory":"Funeral Services",
            "type":"Services"
        }
    ],
    "sg:phone":"+1 250 837 2029",
    "sg:postcode":"V0E 2S0",
    "sg:province":"BC",
    "sg:tags":[
        "director"
    ],
    "wof:name":"Brandon-Bowers Funeral Home",
    "wof:placetype":"venue"
},
  "geometry": {"coordinates":[-118.196274,50.998165],"type":"Point"}
}