{
  "type": "Feature",
  "properties": {
    "addr:full":"Montreal QC H3B 1A6",
    "addr:postcode":"h3b 1a6",
    "iso:country":"CA",
    "sg:city":"Montreal",
    "sg:classifiers":[
        {
            "category":"Professional",
            "subcategory":"Computer Services",
            "type":"Services"
        }
    ],
    "sg:phone":"+1 514 843 2022",
    "sg:postcode":"H3B 1A6",
    "sg:province":"QC",
    "sg:tags":[
        "internet"
    ],
    "wof:name":"Synopsis Solutions",
    "wof:placetype":"venue"
},
  "geometry": {"coordinates":[-73.55961600000001,45.514389],"type":"Point"}
}