{
  "type": "Feature",
  "properties": {
    "iso:country":"CA",
    "sg:city":"Dryden",
    "sg:classifiers":[
        {
            "category":"Banks & Credit Unions",
            "subcategory":"Bank",
            "type":"Services"
        }
    ],
    "sg:phone":"+1 807 223 2247",
    "sg:postcode":"P8N 1X5",
    "sg:province":"ON",
    "sg:tags":[
        "loan",
        "real estate"
    ],
    "wof:name":"Citifinancial",
    "wof:placetype":"venue"
},
  "geometry": {"coordinates":[-92.8410186768,49.7839241028],"type":"Point"}
}