{
  "type": "Feature",
  "properties": {
    "addr:full":"3154 Clearbrook Rd Abbotsford BC V2T 4N6",
    "addr:housenumber":"3154",
    "addr:postcode":"v2t 4n6",
    "addr:street":"Clearbrook Rd",
    "iso:country":"CA",
    "sg:address":"3154 Clearbrook Rd",
    "sg:city":"Abbotsford",
    "sg:classifiers":[
        {
            "category":"Social Services",
            "subcategory":"Child Care",
            "type":"Services"
        }
    ],
    "sg:phone":"+1 604 859 1436",
    "sg:postcode":"V2T 4N6",
    "sg:province":"BC",
    "wof:name":"Upper Fraser Valley Dev Pre",
    "wof:placetype":"venue"
},
  "geometry": {"coordinates":[-122.337760925,49.0593795776],"type":"Point"}
}