{
  "type": "Feature",
  "properties": {
    "addr:full":"Abbotsford BC V4X 2M9",
    "addr:postcode":"v4x 2m9",
    "iso:country":"CA",
    "sg:city":"Abbotsford",
    "sg:classifiers":[
        {
            "category":"Insurance",
            "subcategory":"Insurance Agent",
            "type":"Services"
        }
    ],
    "sg:phone":"+1 604 857 8924",
    "sg:postcode":"V4X 2M9",
    "sg:province":"BC",
    "wof:name":"Barton Insurance Brokers Ltd",
    "wof:placetype":"venue"
},
  "geometry": {"coordinates":[-122.381035,49.061794],"type":"Point"}
}