{
  "type": "Feature",
  "properties": {
    "addr:full":"9069 Rte 14 Newport NS B0N 2A0",
    "addr:housenumber":"9069",
    "addr:postcode":"b0n 2a0",
    "addr:street":"Rte 14",
    "iso:country":"CA",
    "sg:address":"9069 Rte 14",
    "sg:city":"Newport",
    "sg:classifiers":[
        {
            "category":"Home & Garden",
            "subcategory":"Home Furnishings",
            "type":"Retail Goods"
        }
    ],
    "sg:phone":"+1 902 757 2714",
    "sg:postcode":"B0N 2A0",
    "sg:province":"NS",
    "sg:tags":[
        "pottery"
    ],
    "wof:name":"Postma Pottery Ltd",
    "wof:placetype":"venue"
},
  "geometry": {"coordinates":[-63.978329,44.965488],"type":"Point"}
}