{
  "type": "Feature",
  "properties": {
    "iso:country":"CA",
    "sg:city":"Calgary",
    "sg:classifiers":[
        {
            "category":"Health Services",
            "subcategory":"Health Practitioner",
            "type":"Services"
        }
    ],
    "sg:phone":"+1 403 250 1197",
    "sg:postcode":"T2E 7C8",
    "sg:province":"AB",
    "sg:tags":[
        "nutritionist"
    ],
    "wof:name":"Alberta Egg Producers Board",
    "wof:placetype":"venue"
},
  "geometry": {"coordinates":[-114.01467895499999,51.0812835693],"type":"Point"}
}