{
  "type": "Feature",
  "properties": {
    "addr:full":"22 Rue Sainte-Marie Rimouski QC G5L 4E2",
    "addr:housenumber":"22",
    "addr:postcode":"g5l 4e2",
    "addr:street":"Rue Sainte-Marie",
    "iso:country":"CA",
    "sg:address":"22 Rue Sainte-Marie",
    "sg:city":"Rimouski",
    "sg:classifiers":[
        {
            "category":"Government",
            "subcategory":"Office",
            "type":"Public Place"
        }
    ],
    "sg:phone":"+1 418 724 0800",
    "sg:postcode":"G5L 4E2",
    "sg:province":"QC",
    "sg:tags":[
        "village"
    ],
    "wof:name":"Rimouski Societe-Diffusion",
    "wof:placetype":"venue"
},
  "geometry": {"coordinates":[-68.527145,48.450397],"type":"Point"}
}