{
  "type": "Feature",
  "properties": {
    "addr:full":"Belle Cote NS B0E 1C0",
    "addr:postcode":"b0e 1c0",
    "iso:country":"CA",
    "sg:city":"Belle Cote",
    "sg:classifiers":[
        {
            "category":"Shopping",
            "subcategory":"Discount & Variety Stores",
            "type":"Retail Goods"
        }
    ],
    "sg:phone":"+1 902 235 2055",
    "sg:postcode":"B0E 1C0",
    "sg:province":"NS",
    "wof:name":"Dis & Dat Variety Store",
    "wof:placetype":"venue"
},
  "geometry": {"coordinates":[-61.094704,46.447132],"type":"Point"}
}