{
  "type": "Feature",
  "properties": {
    "iso:country":"CA",
    "sg:address":"6509 Randolph Ave",
    "sg:city":"Burnaby",
    "sg:classifiers":[
        {
            "category":"Building & Trades",
            "subcategory":"Construction",
            "type":"Services"
        }
    ],
    "sg:phone":"+1 604 438 9874",
    "sg:postcode":"V5H 3W3",
    "sg:province":"BC",
    "sg:tags":[
        "paving",
        "contractor"
    ],
    "wof:name":"Eddy's Landscaping Ltd",
    "wof:placetype":"venue"
},
  "geometry": {"coordinates":[-122.973510742,49.2246322632],"type":"Point"}
}