{
  "type": "Feature",
  "properties": {
    "iso:country":"CA",
    "sg:address":"3801 Rue Saint-Denis",
    "sg:city":"Montreal",
    "sg:classifiers":[
        {
            "category":"Restaurant",
            "type":"Food & Drink"
        }
    ],
    "sg:phone":"+1 514 982 1717",
    "sg:postcode":"H2W 2M4",
    "sg:province":"QC",
    "wof:name":"Restaurant LA Popessa",
    "wof:placetype":"venue"
},
  "geometry": {"coordinates":[-73.571892,45.519123],"type":"Point"}
}