{
  "type": "Feature",
  "properties": {
    "addr:full":"2318 18 Ave NE Calgary AB T2E 8R1",
    "addr:housenumber":"2318",
    "addr:postcode":"t2e 8r1",
    "addr:street":"18 Ave Ne",
    "iso:country":"CA",
    "sg:address":"2318 18 Ave NE",
    "sg:city":"Calgary",
    "sg:classifiers":[
        {
            "category":"Manufacturing",
            "subcategory":"Tools & Machinery",
            "type":"Manufacturing & Wholesale Goods"
        }
    ],
    "sg:phone":"+1 403 250 2909",
    "sg:postcode":"T2E 8R1",
    "sg:province":"AB",
    "sg:tags":[
        "control"
    ],
    "wof:name":"Prologic Controls Ltd",
    "wof:placetype":"venue"
},
  "geometry": {"coordinates":[-114.007019,51.069145],"type":"Point"}
}