{
  "type": "Feature",
  "properties": {
    "addr:full":"165 St Clair Ave W Toronto ON M4V 1P7",
    "addr:housenumber":"165",
    "addr:postcode":"m4v 1p7",
    "addr:street":"St Clair Ave W",
    "iso:country":"CA",
    "sg:address":"165 St Clair Ave W",
    "sg:city":"Toronto",
    "sg:classifiers":[
        {
            "category":"Health Services",
            "subcategory":"Health Practitioner",
            "type":"Services"
        }
    ],
    "sg:phone":"+1 416 969 8706",
    "sg:postcode":"M4V 1P7",
    "sg:province":"ON",
    "sg:tags":[
        "psychologist"
    ],
    "wof:name":"Himes, Mavis",
    "wof:placetype":"venue"
},
  "geometry": {"coordinates":[-79.40255000000001,43.686275],"type":"Point"}
}