{
  "type": "Feature",
  "properties": {
    "addr:full":"30 Rue Saint-Gabriel Saint-Gabriel-DE-Brandon QC J0K 2N0",
    "addr:housenumber":"30",
    "addr:postcode":"j0k 2n0",
    "addr:street":"Rue Saint-Gabriel",
    "iso:country":"CA",
    "sg:address":"30 Rue Saint-Gabriel",
    "sg:city":"Saint-Gabriel-DE-Brandon",
    "sg:classifiers":[
        {
            "category":"Health Services",
            "subcategory":"Doctor",
            "type":"Services"
        }
    ],
    "sg:phone":"+1 450 835 4705",
    "sg:postcode":"J0K 2N0",
    "sg:province":"QC",
    "sg:tags":[
        "clinic"
    ],
    "wof:name":"Clsc D'Autray",
    "wof:placetype":"venue"
},
  "geometry": {"coordinates":[-73.383965,46.292793],"type":"Point"}
}