{
  "type": "Feature",
  "properties": {
    "iso:country":"CA",
    "sg:address":"865 Catherine St",
    "sg:city":"Victoria",
    "sg:classifiers":[
        {
            "category":"Recreation",
            "type":"Entertainment"
        }
    ],
    "sg:phone":"+1 250 383 4103",
    "sg:postcode":"V9A 3T9",
    "sg:province":"BC",
    "sg:tags":[
        "martial",
        "arts",
        "instruction"
    ],
    "wof:name":"Taoist Tai Chi Society-Canada",
    "wof:placetype":"venue"
},
  "geometry": {"coordinates":[-123.384628296,48.434425354],"type":"Point"}
}