{
  "type": "Feature",
  "properties": {
    "addr:full":"290 Rideau St Ottawa ON K1N 5Y3",
    "addr:housenumber":"290",
    "addr:postcode":"k1n 5y3",
    "addr:street":"Rideau St",
    "iso:country":"CA",
    "sg:address":"290 Rideau St",
    "sg:city":"Ottawa",
    "sg:classifiers":[
        {
            "category":"Travel",
            "subcategory":"Hotels & Motels",
            "type":"Entertainment"
        }
    ],
    "sg:phone":"+1 613 789 7511",
    "sg:postcode":"K1N 5Y3",
    "sg:province":"ON",
    "wof:name":"Quality Hotel Ottawa Downtown",
    "wof:placetype":"venue"
},
  "geometry": {"coordinates":[-75.68594360349999,45.4285545349],"type":"Point"}
}