{
  "type": "Feature",
  "properties": {
    "addr:full":"830 Barton St E Hamilton ON L8L 7Z5",
    "addr:housenumber":"830",
    "addr:postcode":"l8l 7z5",
    "addr:street":"Barton St E",
    "iso:country":"CA",
    "sg:address":"830 Barton St E",
    "sg:city":"Hamilton",
    "sg:classifiers":[
        {
            "category":"Recreation",
            "type":"Entertainment"
        }
    ],
    "sg:phone":"+1 905 545 4864",
    "sg:postcode":"L8L 7Z5",
    "sg:province":"ON",
    "sg:tags":[
        "hall",
        "auditorium"
    ],
    "wof:name":"St Anthony's Hall",
    "wof:placetype":"venue"
},
  "geometry": {"coordinates":[-79.829185,43.254555],"type":"Point"}
}