{
  "type": "Feature",
  "properties": {
    "iso:country":"CA",
    "sg:city":"Mississauga",
    "sg:classifiers":[
        {
            "category":"Professional",
            "subcategory":"Computer Services",
            "type":"Services"
        }
    ],
    "sg:phone":"+1 905 629 4465",
    "sg:postcode":"L4W 1A7",
    "sg:province":"ON",
    "sg:tags":[
        "processing",
        "datum"
    ],
    "wof:name":"Roler Data Transfer",
    "wof:placetype":"venue"
},
  "geometry": {"coordinates":[-79.62446594239999,43.6292037964],"type":"Point"}
}