{
  "type": "Feature",
  "properties": {
    "addr:full":"2 Spencer Ln Fonthill ON L0S 1E0",
    "addr:housenumber":"2",
    "addr:postcode":"l0s 1e0",
    "addr:street":"Spencer Ln",
    "iso:country":"CA",
    "sg:address":"2 Spencer Ln",
    "sg:city":"Fonthill",
    "sg:classifiers":[
        {
            "category":"Real Estate",
            "subcategory":"Real Estate Agent",
            "type":"Services"
        }
    ],
    "sg:phone":"+1 905 892 2727",
    "sg:postcode":"L0S 1E0",
    "sg:province":"ON",
    "wof:name":"Greg Woods Real Estate Ltd",
    "wof:placetype":"venue"
},
  "geometry": {"coordinates":[-79.2907791138,43.0453300476],"type":"Point"}
}