{
  "type": "Feature",
  "properties": {
    "addr:full":"398 Rue Des Frenes E Quebec QC G1L 5B2",
    "addr:housenumber":"398",
    "addr:postcode":"g1l 5b2",
    "addr:street":"Rue Des Frenes E",
    "iso:country":"CA",
    "sg:address":"398 Rue Des Frenes E",
    "sg:city":"Quebec",
    "sg:classifiers":[
        {
            "category":"Arts & Performance",
            "subcategory":"Theater",
            "type":"Entertainment"
        }
    ],
    "sg:phone":"+1 418 624 9491",
    "sg:postcode":"G1L 5B2",
    "sg:province":"QC",
    "sg:tags":[
        "bureau"
    ],
    "wof:name":"V'La L'Bon Vent",
    "wof:placetype":"venue"
},
  "geometry": {"coordinates":[-71.24095153810001,46.8404808044],"type":"Point"}
}