{
  "type": "Feature",
  "properties": {
    "addr:full":"97 Water St Baie Verte NL A0K 1B0",
    "addr:housenumber":"97",
    "addr:postcode":"a0k 1b0",
    "addr:street":"Water St",
    "iso:country":"CA",
    "sg:address":"97 Water St",
    "sg:city":"Baie Verte",
    "sg:classifiers":[
        {
            "category":"Taxi",
            "type":"Transportation"
        }
    ],
    "sg:phone":"+1 709 532 4330",
    "sg:postcode":"A0K 1B0",
    "sg:province":"NL",
    "sg:tags":[
        "taxicab"
    ],
    "wof:name":"Saunders' Taxi",
    "wof:placetype":"venue"
},
  "geometry": {"coordinates":[-56.1923103333,49.9394645691],"type":"Point"}
}