{
  "type": "Feature",
  "properties": {
    "iso:country":"CA",
    "sg:address":"262 Rue Saint-Paul E",
    "sg:city":"Montreal",
    "sg:classifiers":[
        {
            "category":"Restaurant",
            "type":"Food & Drink"
        }
    ],
    "sg:phone":"+1 514 874 7661",
    "sg:postcode":"H2Y 1G9",
    "sg:province":"QC",
    "wof:name":"Restaurant DE LA Place St Paul",
    "wof:placetype":"venue"
},
  "geometry": {"coordinates":[-73.55207799999999,45.508087],"type":"Point"}
}