{
  "type": "Feature",
  "properties": {
    "addr:full":"44 Eastbourne Dr Brampton ON L6T 3M2",
    "addr:housenumber":"44",
    "addr:postcode":"l6t 3m2",
    "addr:street":"Eastbourne Dr",
    "iso:country":"CA",
    "sg:address":"44 Eastbourne Dr",
    "sg:city":"Brampton",
    "sg:classifiers":[
        {
            "category":"Recreation",
            "type":"Entertainment"
        }
    ],
    "sg:phone":"+1 905 792 2224",
    "sg:postcode":"L6T 3M2",
    "sg:province":"ON",
    "sg:tags":[
        "center"
    ],
    "wof:name":"Earnscliffe Recreation Ctr",
    "wof:placetype":"venue"
},
  "geometry": {"coordinates":[-79.69873809809999,43.7236442566],"type":"Point"}
}