{
  "type": "Feature",
  "properties": {
    "addr:full":"Calgary AB T2E 7L4",
    "addr:postcode":"t2e 7l4",
    "iso:country":"CA",
    "sg:city":"Calgary",
    "sg:classifiers":[
        {
            "category":"Organizations",
            "subcategory":"Professional Association",
            "type":"Services"
        }
    ],
    "sg:phone":"+1 403 235 5662",
    "sg:postcode":"T2E 7L4",
    "sg:province":"AB",
    "wof:name":"Alberta Easter Seals",
    "wof:placetype":"venue"
},
  "geometry": {"coordinates":[-114.018806,51.056889],"type":"Point"}
}