{
  "type": "Feature",
  "properties": {
    "iso:country":"CA",
    "sg:address":"215 Kennedy Rd",
    "sg:city":"Scarborough",
    "sg:classifiers":[
        {
            "category":"Organizations",
            "subcategory":"Religious Organization",
            "type":"Services"
        }
    ],
    "sg:phone":"+1 416 261 5420",
    "sg:postcode":"M1N 3P4",
    "sg:province":"ON",
    "sg:tags":[
        "church"
    ],
    "wof:name":"People's Worship Ctr",
    "wof:placetype":"venue"
},
  "geometry": {"coordinates":[-79.2569656372,43.705997467],"type":"Point"}
}