{
  "type": "Feature",
  "properties": {
    "addr:full":"291 Rue Principale Saint-Cyrille-DE-L'Islet QC G0R 2W0",
    "addr:housenumber":"291",
    "addr:postcode":"g0r 2w0",
    "addr:street":"Rue Principale",
    "iso:country":"CA",
    "sg:address":"291 Rue Principale",
    "sg:city":"Saint-Cyrille-DE-L'Islet",
    "sg:classifiers":[
        {
            "category":"Organizations",
            "subcategory":"Religious Organization",
            "type":"Services"
        }
    ],
    "sg:phone":"+1 418 247 5438",
    "sg:postcode":"G0R 2W0",
    "sg:province":"QC",
    "sg:tags":[
        "church"
    ],
    "wof:name":"Presbytere St-Cyrille",
    "wof:placetype":"venue"
},
  "geometry": {"coordinates":[-70.33153533940001,47.0898017883],"type":"Point"}
}