{
  "type": "Feature",
  "properties": {
    "addr:full":"813 Main St Humboldt SK S0K 2A0",
    "addr:housenumber":"813",
    "addr:postcode":"s0k 2a0",
    "addr:street":"Main St",
    "iso:country":"CA",
    "sg:address":"813 Main St",
    "sg:city":"Humboldt",
    "sg:classifiers":[
        {
            "category":"Organizations",
            "subcategory":"Non-profit Organization",
            "type":"Services"
        }
    ],
    "sg:phone":"+1 306 682 1607",
    "sg:postcode":"S0K 2A0",
    "sg:province":"SK",
    "sg:tags":[
        "agricultural",
        "consultant",
        "institution",
        "charitable"
    ],
    "wof:name":"Genesis Land Conservancy Inc",
    "wof:placetype":"venue"
},
  "geometry": {"coordinates":[-105.12293243400001,52.2018890381],"type":"Point"}
}