{
  "type": "Feature",
  "properties": {
    "iso:country":"CA",
    "sg:city":"Uxbridge",
    "sg:classifiers":[
        {
            "category":"Health Services",
            "subcategory":"Doctor",
            "type":"Services"
        }
    ],
    "sg:phone":"+1 905 852 4767",
    "sg:postcode":"L9P 1H6",
    "sg:province":"ON",
    "sg:tags":[
        "dentist"
    ],
    "wof:name":"Quaker Dental Clinic",
    "wof:placetype":"venue"
},
  "geometry": {"coordinates":[-79.126205,44.102352],"type":"Point"}
}