{
  "type": "Feature",
  "properties": {
    "iso:country":"CA",
    "sg:address":"671 Rue Babin",
    "sg:city":"Dieppe",
    "sg:classifiers":[
        {
            "category":"Autos & Motor Vehicles",
            "subcategory":"Motorcycle Sales",
            "type":"Retail Goods"
        }
    ],
    "sg:phone":"+1 506 388 3335",
    "sg:postcode":"E1A 5M7",
    "sg:province":"NB",
    "sg:tags":[
        "all",
        "terrain"
    ],
    "wof:name":"L B Mfg Inc",
    "wof:placetype":"venue"
},
  "geometry": {"coordinates":[-64.7225189209,46.105342865],"type":"Point"}
}