{
  "type": "Feature",
  "properties": {
    "addr:full":"476 Westridge Dr Kleinburg ON L0J 1C0",
    "addr:housenumber":"476",
    "addr:postcode":"l0j 1c0",
    "addr:street":"Westridge Dr",
    "iso:country":"CA",
    "sg:address":"476 Westridge Dr",
    "sg:city":"Kleinburg",
    "sg:classifiers":[
        {
            "category":"Building & Trades",
            "subcategory":"Construction",
            "type":"Services"
        }
    ],
    "sg:phone":"+1 905 893 3315",
    "sg:postcode":"L0J 1C0",
    "sg:province":"ON",
    "sg:tags":[
        "dry wall",
        "contractor"
    ],
    "wof:name":"Guiliani Brothers & CO",
    "wof:placetype":"venue"
},
  "geometry": {"coordinates":[-79.623734,43.837677],"type":"Point"}
}