{
  "type": "Feature",
  "properties": {
    "addr:full":"1025 Finch Ave W North York ON M3J 2C7",
    "addr:housenumber":"1025",
    "addr:postcode":"m3j 2c7",
    "addr:street":"Finch Ave W",
    "iso:country":"CA",
    "sg:address":"1025 Finch Ave W",
    "sg:city":"North York",
    "sg:classifiers":[
        {
            "category":"Restaurant",
            "type":"Food & Drink"
        }
    ],
    "sg:phone":"+1 416 663 0002",
    "sg:postcode":"M3J 2C7",
    "sg:province":"ON",
    "wof:name":"Europiean Restaurant Bar",
    "wof:placetype":"venue"
},
  "geometry": {"coordinates":[-79.469971,43.76804],"type":"Point"}
}