{
  "type": "Feature",
  "properties": {
    "addr:full":"100 Rue Belvedere S Sherbrooke QC J1H 4B5",
    "addr:housenumber":"100",
    "addr:postcode":"j1h 4b5",
    "addr:street":"Rue Belvedere S",
    "iso:country":"CA",
    "sg:address":"100 Rue Belvedere S",
    "sg:city":"Sherbrooke",
    "sg:classifiers":[
        {
            "category":"Insurance",
            "subcategory":"Insurance Agent",
            "type":"Services"
        }
    ],
    "sg:phone":"+1 819 563 0363",
    "sg:postcode":"J1H 4B5",
    "sg:province":"QC",
    "wof:name":"Assurances Perreault Rouillard",
    "wof:placetype":"venue"
},
  "geometry": {"coordinates":[-71.89585099999999,45.397388],"type":"Point"}
}