{
  "type": "Feature",
  "properties": {
    "addr:full":"St Malo MB R0A 1T0",
    "addr:postcode":"r0a 1t0",
    "addr:street":"St Malo",
    "iso:country":"CA",
    "sg:city":"St Malo",
    "sg:classifiers":[
        {
            "category":"Insurance",
            "subcategory":"Insurance Agent",
            "type":"Services"
        }
    ],
    "sg:phone":"+1 204 347 5368",
    "sg:postcode":"R0A 1T0",
    "sg:province":"MB",
    "wof:name":"Barnabe & Saurette Insurance",
    "wof:placetype":"venue"
},
  "geometry": {"coordinates":[-96.95025634770001,49.3160362244],"type":"Point"}
}