{
  "type": "Feature",
  "properties": {
    "addr:full":"2364 Whaley Dr Mississauga ON L5B 2B5",
    "addr:housenumber":"2364",
    "addr:postcode":"l5b 2b5",
    "addr:street":"Whaley Dr",
    "iso:country":"CA",
    "sg:address":"2364 Whaley Dr",
    "sg:city":"Mississauga",
    "sg:classifiers":[
        {
            "category":"Home & Garden",
            "subcategory":"Household Appliances",
            "type":"Retail Goods"
        }
    ],
    "sg:phone":"+1 905 277 0292",
    "sg:postcode":"L5B 2B5",
    "sg:province":"ON",
    "wof:name":"A F Refrigeration & Appliance",
    "wof:placetype":"venue"
},
  "geometry": {"coordinates":[-79.6189956665,43.5692710876],"type":"Point"}
}