{
  "type": "Feature",
  "properties": {
    "addr:full":"91 Queen St Niagara on the Lake ON L0S 1J0",
    "addr:housenumber":"91",
    "addr:postcode":"l0s 1j0",
    "addr:street":"Queen St;On",
    "iso:country":"CA",
    "sg:address":"91 Queen St",
    "sg:city":"Niagara on the Lake",
    "sg:classifiers":[
        {
            "category":"Shopping",
            "subcategory":"Gifts & Souvenirs",
            "type":"Retail Goods"
        }
    ],
    "sg:phone":"+1 905 468 2614",
    "sg:postcode":"L0S 1J0",
    "sg:province":"ON",
    "sg:tags":[
        "shop"
    ],
    "wof:name":"Dansk Factory Outlet",
    "wof:placetype":"venue"
},
  "geometry": {"coordinates":[-79.073425293,43.2562255859],"type":"Point"}
}