{
  "type": "Feature",
  "properties": {
    "addr:full":"Quebec QC G1M 2S6",
    "addr:postcode":"g1m 2s6",
    "iso:country":"CA",
    "sg:city":"Quebec",
    "sg:classifiers":[
        {
            "category":"Restaurant",
            "type":"Food & Drink"
        }
    ],
    "sg:phone":"+1 418 648 8546",
    "sg:postcode":"G1M 2S6",
    "sg:province":"QC",
    "wof:name":"Sukiyaki Experience Japonnaise",
    "wof:placetype":"venue"
},
  "geometry": {"coordinates":[-71.2489395142,46.8203735352],"type":"Point"}
}