{
  "type": "Feature",
  "properties": {
    "addr:full":"21 Mcgivern St W Walkerton ON N0G 2V0",
    "addr:housenumber":"21",
    "addr:postcode":"n0g 2v0",
    "addr:street":"Mcgivern St W Walkerton",
    "iso:country":"CA",
    "sg:address":"21 Mcgivern St W",
    "sg:city":"Walkerton",
    "sg:classifiers":[
        {
            "category":"Health Services",
            "subcategory":"Hospital",
            "type":"Services"
        }
    ],
    "sg:phone":"+1 519 881 1220",
    "sg:postcode":"N0G 2V0",
    "sg:province":"ON",
    "wof:name":"South Bruce Gray Health Ctr",
    "wof:placetype":"venue"
},
  "geometry": {"coordinates":[-81.152916,44.122688],"type":"Point"}
}