{
  "type": "Feature",
  "properties": {
    "addr:full":"4283 Turner Rd Kelowna BC V1W 2N5",
    "addr:housenumber":"4283",
    "addr:postcode":"v1w 2n5",
    "addr:street":"Turner Rd",
    "iso:country":"CA",
    "sg:address":"4283 Turner Rd",
    "sg:city":"Kelowna",
    "sg:classifiers":[
        {
            "category":"Building & Trades",
            "subcategory":"Construction",
            "type":"Services"
        }
    ],
    "sg:phone":"+1 250 764 8797",
    "sg:postcode":"V1W 2N5",
    "sg:province":"BC",
    "sg:tags":[
        "washing",
        "deck",
        "car",
        "restoration",
        "cleaning",
        "polishing",
        "patio"
    ],
    "wof:name":"Aqua Hot Wash Ltd",
    "wof:placetype":"venue"
},
  "geometry": {"coordinates":[-119.481552124,49.8288497925],"type":"Point"}
}