{
  "type": "Feature",
  "properties": {
    "addr:full":"Ottawa ON K2P 0J2",
    "addr:postcode":"k2p 0j2",
    "iso:country":"CA",
    "sg:city":"Ottawa",
    "sg:classifiers":[
        {
            "category":"Real Estate",
            "subcategory":"Developer",
            "type":"Services"
        }
    ],
    "sg:phone":"+1 613 233 1104",
    "sg:postcode":"K2P 0J2",
    "sg:province":"ON",
    "wof:name":"Ambassador Realty Inc",
    "wof:placetype":"venue"
},
  "geometry": {"coordinates":[-75.6909332275,45.4177894592],"type":"Point"}
}