{
  "type": "Feature",
  "properties": {
    "addr:full":"Sudbury ON P3A 1X8",
    "addr:postcode":"p3a 1x8",
    "iso:country":"CA",
    "sg:city":"Sudbury",
    "sg:classifiers":[
        {
            "category":"Real Estate",
            "subcategory":"Developer",
            "type":"Services"
        }
    ],
    "sg:phone":"+1 705 566 8263",
    "sg:postcode":"P3A 1X8",
    "sg:province":"ON",
    "wof:name":"Temvest",
    "wof:placetype":"venue"
},
  "geometry": {"coordinates":[-80.960724,46.521954],"type":"Point"}
}