{
  "type": "Feature",
  "properties": {
    "addr:full":"Little Buffalo Lake Sexsmith AB T0H 3C0",
    "addr:postcode":"t0h 3c0",
    "addr:street":"Little Buffalo",
    "iso:country":"CA",
    "sg:address":"Little Buffalo Lake",
    "sg:city":"Sexsmith",
    "sg:classifiers":[
        {
            "category":"Health Services",
            "subcategory":"Clinic",
            "type":"Services"
        }
    ],
    "sg:phone":"+1 780 629 3760",
    "sg:postcode":"T0H 3C0",
    "sg:province":"AB",
    "sg:tags":[
        "information",
        "program",
        "referral"
    ],
    "wof:name":"Little Buffalo Health Ctr",
    "wof:placetype":"venue"
},
  "geometry": {"coordinates":[-118.780762,55.345112],"type":"Point"}
}