{
  "type": "Feature",
  "properties": {
    "addr:full":"71 Broadway Ave Wawa ON P0S 1K0",
    "addr:housenumber":"71",
    "addr:postcode":"p0s 1k0",
    "addr:street":"Broadway Ave",
    "iso:country":"CA",
    "sg:address":"71 Broadway Ave",
    "sg:city":"Wawa",
    "sg:classifiers":[
        {
            "category":"Restaurant",
            "type":"Food & Drink"
        }
    ],
    "sg:phone":"+1 705 856 1300",
    "sg:postcode":"P0S 1K0",
    "sg:province":"ON",
    "wof:name":"Columbia Restaurant",
    "wof:placetype":"venue"
},
  "geometry": {"coordinates":[-84.7706451416,47.9942741394],"type":"Point"}
}