{
  "type": "Feature",
  "properties": {
    "addr:full":"455 Goderich St Port Elgin ON N0H 2C4",
    "addr:housenumber":"455",
    "addr:postcode":"n0h 2c4",
    "addr:street":"Goderich St",
    "iso:country":"CA",
    "sg:address":"455 Goderich St",
    "sg:city":"Port Elgin",
    "sg:classifiers":[
        {
            "category":"Professional",
            "subcategory":"Lawyer & Legal Services",
            "type":"Services"
        }
    ],
    "sg:phone":"+1 519 389 3122",
    "sg:postcode":"N0H 2C4",
    "sg:province":"ON",
    "sg:tags":[
        "attorney"
    ],
    "wof:name":"Mann III, John R",
    "wof:placetype":"venue"
},
  "geometry": {"coordinates":[-81.39147949220001,44.4326248169],"type":"Point"}
}