{
  "type": "Feature",
  "properties": {
    "addr:full":"645 Rue Sacre-Coeur O Alma QC G8B 1M4",
    "addr:housenumber":"645",
    "addr:postcode":"g8b 1m4",
    "addr:street":"Rue Sacre-Coeur O",
    "iso:country":"CA",
    "sg:address":"645 Rue Sacre-Coeur O",
    "sg:city":"Alma",
    "sg:classifiers":[
        {
            "category":"Recreation",
            "type":"Entertainment"
        }
    ],
    "sg:phone":"+1 418 480 2741",
    "sg:postcode":"G8B 1M4",
    "sg:province":"QC",
    "sg:tags":[
        "parlor",
        "billiard"
    ],
    "wof:name":"Dooly's Alma",
    "wof:placetype":"venue"
},
  "geometry": {"coordinates":[-71.631027,48.542892],"type":"Point"}
}