{
  "type": "Feature",
  "properties": {
    "addr:full":"Whitewood SK S0G 5C0",
    "addr:postcode":"s0g 5c0",
    "iso:country":"CA",
    "sg:city":"Whitewood",
    "sg:classifiers":[
        {
            "category":"Freight",
            "type":"Transportation"
        }
    ],
    "sg:phone":"+1 306 735 2626",
    "sg:postcode":"S0G 5C0",
    "sg:province":"SK",
    "sg:tags":[
        "grain",
        "elevator"
    ],
    "wof:name":"Pioneer Grain",
    "wof:placetype":"venue"
},
  "geometry": {"coordinates":[-102.257896,50.327831],"type":"Point"}
}