{
  "type": "Feature",
  "properties": {
    "addr:full":"6112 Willow St Halifax NS B3K 1M2",
    "addr:housenumber":"6112",
    "addr:postcode":"b3k 1m2",
    "addr:street":"Willow St",
    "iso:country":"CA",
    "sg:address":"6112 Willow St",
    "sg:city":"Halifax",
    "sg:classifiers":[
        {
            "category":"Health Services",
            "subcategory":"Chiropractor",
            "type":"Services"
        }
    ],
    "sg:phone":"+1 902 423 9223",
    "sg:postcode":"B3K 1M2",
    "sg:province":"NS",
    "wof:name":"Halifax Chiropractic Clinic",
    "wof:placetype":"venue"
},
  "geometry": {"coordinates":[-63.5956764221,44.6529273987],"type":"Point"}
}