{
  "type": "Feature",
  "properties": {
    "iso:country":"CA",
    "sg:address":"777019 Hwy 10",
    "sg:city":"Holland Centre",
    "sg:classifiers":[
        {
            "category":"Autos & Motor Vehicles",
            "subcategory":"Fuel & Gas Station",
            "type":"Retail Goods"
        }
    ],
    "sg:phone":"+1 519 794 2038",
    "sg:postcode":"N0H 1R0",
    "sg:province":"ON",
    "sg:tags":[
        "oil"
    ],
    "wof:name":"Holland Auto Ctr",
    "wof:placetype":"venue"
},
  "geometry": {"coordinates":[-80.7940750122,44.3931846619],"type":"Point"}
}