{
  "type": "Feature",
  "properties": {
    "iso:country":"CA",
    "sg:address":"674 Simcoe St S",
    "sg:city":"Oshawa",
    "sg:classifiers":[
        {
            "category":"Autos & Motor Vehicles",
            "subcategory":"Fuel & Gas Station",
            "type":"Retail Goods"
        }
    ],
    "sg:phone":"+1 905 438 0808",
    "sg:postcode":"L1H 4K3",
    "sg:province":"ON",
    "sg:tags":[
        "oil"
    ],
    "wof:name":"Vlk Intl Canada Inc",
    "wof:placetype":"venue"
},
  "geometry": {"coordinates":[-78.8558044434,43.8802185059],"type":"Point"}
}