{
  "type": "Feature",
  "properties": {
    "addr:full":"78 Golden Dr Coquitlam BC V3K 6B5",
    "addr:housenumber":"78",
    "addr:postcode":"v3k 6b5",
    "addr:street":"Golden Dr",
    "iso:country":"CA",
    "sg:address":"78 Golden Dr",
    "sg:city":"Coquitlam",
    "sg:classifiers":[
        {
            "category":"Wholesale",
            "subcategory":"Construction Materials",
            "type":"Manufacturing & Wholesale Goods"
        }
    ],
    "sg:phone":"+1 604 525 2001",
    "sg:postcode":"V3K 6B5",
    "sg:province":"BC",
    "sg:tags":[
        "lumber"
    ],
    "wof:name":"Still Creek Forest Prods Ltd",
    "wof:placetype":"venue"
},
  "geometry": {"coordinates":[-122.824584961,49.230556488],"type":"Point"}
}