{
  "type": "Feature",
  "properties": {
    "iso:country":"CA",
    "sg:address":"33 Rue Royal",
    "sg:city":"Le Gardeur",
    "sg:classifiers":[
        {
            "category":"Manufacturing",
            "subcategory":"Chemicals & Compounds",
            "type":"Manufacturing & Wholesale Goods"
        }
    ],
    "sg:phone":"+1 450 654 9292",
    "sg:postcode":"J5Z 4Z3",
    "sg:province":"QC",
    "wof:name":"Auto-Chem Inc",
    "wof:placetype":"venue"
},
  "geometry": {"coordinates":[-73.488312,45.734879],"type":"Point"}
}