{
  "type": "Feature",
  "properties": {
    "addr:full":"33 Rue Royal Le Gardeur QC J5Z 4Z3",
    "addr:housenumber":"33",
    "addr:postcode":"j5z 4z3",
    "addr:street":"Rue Royal Le Gardeur",
    "iso:country":"CA",
    "sg:address":"33 Rue Royal",
    "sg:city":"Le Gardeur",
    "sg:classifiers":[
        {
            "category":"Manufacturing",
            "subcategory":"Chemicals & Compounds",
            "type":"Manufacturing & Wholesale Goods"
        }
    ],
    "sg:phone":"+1 450 654 9292",
    "sg:postcode":"J5Z 4Z3",
    "sg:province":"QC",
    "wof:name":"Auto-Chem Inc",
    "wof:placetype":"venue"
},
  "geometry": {"coordinates":[-73.48831199999999,45.734879],"type":"Point"}
}