{
  "type": "Feature",
  "properties": {
    "addr:full":"Mississauga ON L5L 5Y6",
    "addr:postcode":"l5l 5y6",
    "iso:country":"CA",
    "sg:city":"Mississauga",
    "sg:classifiers":[
        {
            "category":"Shopping",
            "subcategory":"Computers & Home Electronics",
            "type":"Retail Goods"
        }
    ],
    "sg:phone":"+1 905 569 2241",
    "sg:postcode":"L5L 5Y6",
    "sg:province":"ON",
    "sg:tags":[
        "software"
    ],
    "wof:name":"4D Concepts Inc",
    "wof:placetype":"venue"
},
  "geometry": {"coordinates":[-79.699181,43.520172],"type":"Point"}
}