{
  "type": "Feature",
  "properties": {
    "addr:full":"2112 Hastings St E Vancouver BC V5L 1V1",
    "addr:housenumber":"2112",
    "addr:postcode":"v5l 1v1",
    "addr:street":"Hastings St E",
    "iso:country":"CA",
    "sg:address":"2112 Hastings St E",
    "sg:city":"Vancouver",
    "sg:classifiers":[
        {
            "category":"Personal",
            "subcategory":"Barber",
            "type":"Services"
        }
    ],
    "sg:phone":"+1 604 251 6511",
    "sg:postcode":"V5L 1V1",
    "sg:province":"BC",
    "wof:name":"Tom's Hairstyling",
    "wof:placetype":"venue"
},
  "geometry": {"coordinates":[-123.06128692599999,49.2810630798],"type":"Point"}
}