{
  "type": "Feature",
  "properties": {
    "iso:country":"CA",
    "sg:address":"2660 Pandosy St",
    "sg:city":"Kelowna",
    "sg:classifiers":[
        {
            "category":"Retail",
            "subcategory":"Self-service Laundry",
            "type":"Services"
        }
    ],
    "sg:phone":"+1 250 763 9992",
    "sg:postcode":"V1Y 1V6",
    "sg:province":"BC",
    "wof:name":"Cullen's Cleaning Carousel",
    "wof:placetype":"venue"
},
  "geometry": {"coordinates":[-119.491386414,49.8664855957],"type":"Point"}
}