{
  "type": "Feature",
  "properties": {
    "addr:full":"15 Du Campagnard Saint-Fabien QC G0L 2Z0",
    "addr:housenumber":"15",
    "addr:postcode":"g0l 2z0",
    "addr:street":"Du Campagnard",
    "iso:country":"CA",
    "sg:address":"15 Du Campagnard",
    "sg:city":"Saint-Fabien",
    "sg:classifiers":[
        {
            "category":"Organizations",
            "subcategory":"Professional Association",
            "type":"Services"
        }
    ],
    "sg:phone":"+1 418 869 3203",
    "sg:postcode":"G0L 2Z0",
    "sg:province":"QC",
    "wof:name":"Otj St-Eugene",
    "wof:placetype":"venue"
},
  "geometry": {"coordinates":[-68.86711883540001,48.2952728271],"type":"Point"}
}