{
  "type": "Feature",
  "properties": {
    "addr:full":"975 Rue Malouin Sherbrooke QC J1J 3B7",
    "addr:housenumber":"975",
    "addr:postcode":"j1j 3b7",
    "addr:street":"Rue Malouin",
    "iso:country":"CA",
    "sg:address":"975 Rue Malouin",
    "sg:city":"Sherbrooke",
    "sg:classifiers":[
        {
            "category":"Health Services",
            "subcategory":"Health Practitioner",
            "type":"Services"
        }
    ],
    "sg:phone":"+1 819 564 2161",
    "sg:postcode":"J1J 3B7",
    "sg:province":"QC",
    "sg:tags":[
        "psychologist"
    ],
    "wof:name":"Reinbold, Jacques",
    "wof:placetype":"venue"
},
  "geometry": {"coordinates":[-71.916725,45.413826],"type":"Point"}
}