{
  "type": "Feature",
  "properties": {
    "addr:full":"1855 Rue Georges Saint-Hubert QC J4T 1W2",
    "addr:housenumber":"1855",
    "addr:postcode":"j4t 1w2",
    "addr:street":"Rue Georges",
    "iso:country":"CA",
    "sg:address":"1855 Rue Georges",
    "sg:city":"Saint-Hubert",
    "sg:classifiers":[
        {
            "category":"Manufacturing",
            "subcategory":"Tools & Machinery",
            "type":"Manufacturing & Wholesale Goods"
        }
    ],
    "sg:phone":"+1 450 443 0655",
    "sg:postcode":"J4T 1W2",
    "sg:province":"QC",
    "sg:tags":[
        "built",
        "designed"
    ],
    "wof:name":"Centre Auto Chic Inc",
    "wof:placetype":"venue"
},
  "geometry": {"coordinates":[-73.4733200073,45.4974060059],"type":"Point"}
}