{
  "type": "Feature",
  "properties": {
    "addr:full":"141 Main St Stephenville NL A2N 1J5",
    "addr:housenumber":"141",
    "addr:postcode":"a2n 1j5",
    "addr:street":"Main St",
    "iso:country":"CA",
    "sg:address":"141 Main St",
    "sg:city":"Stephenville",
    "sg:classifiers":[
        {
            "category":"Food & Beverages",
            "subcategory":"Groceries & Convenience Stores",
            "type":"Retail Goods"
        }
    ],
    "sg:phone":"+1 709 643 3331",
    "sg:postcode":"A2N 1J5",
    "sg:province":"NL",
    "sg:tags":[
        "product"
    ],
    "wof:name":"Buy the Pound",
    "wof:placetype":"venue"
},
  "geometry": {"coordinates":[-58.5774116516,48.5497512817],"type":"Point"}
}