{
  "type": "Feature",
  "properties": {
    "addr:full":"543 6th St Courtenay BC V9N 1M5",
    "addr:housenumber":"543",
    "addr:postcode":"v9n 1m5",
    "addr:street":"6Th St",
    "iso:country":"CA",
    "sg:address":"543 6th St",
    "sg:city":"Courtenay",
    "sg:classifiers":[
        {
            "category":"Organizations",
            "subcategory":"Professional Association",
            "type":"Services"
        }
    ],
    "sg:phone":"+1 250 338 0041",
    "sg:postcode":"V9N 1M5",
    "sg:province":"BC",
    "wof:name":"Alano Club of Courtenay",
    "wof:placetype":"venue"
},
  "geometry": {"coordinates":[-125.00210571300001,49.6888885498],"type":"Point"}
}