{
  "type": "Feature",
  "properties": {
    "addr:full":"7419 Edmonds St Burnaby BC V3N 1B1",
    "addr:housenumber":"7419",
    "addr:postcode":"v3n 1b1",
    "addr:street":"Edmonds St",
    "iso:country":"CA",
    "sg:address":"7419 Edmonds St",
    "sg:city":"Burnaby",
    "sg:classifiers":[
        {
            "category":"Shopping",
            "subcategory":"Pharmacy",
            "type":"Retail Goods"
        }
    ],
    "sg:phone":"+1 604 526 1110",
    "sg:postcode":"V3N 1B1",
    "sg:province":"BC",
    "wof:name":"Edmonds Pharmadrugs",
    "wof:placetype":"venue"
},
  "geometry": {"coordinates":[-122.948189,49.220409],"type":"Point"}
}