{
  "type": "Feature",
  "properties": {
    "iso:country":"CA",
    "sg:city":"Winnipeg",
    "sg:classifiers":[
        {
            "category":"Wholesale",
            "subcategory":"Jewelry",
            "type":"Manufacturing & Wholesale Goods"
        }
    ],
    "sg:phone":"+1 204 224 2416",
    "sg:postcode":"R2C 4L1",
    "sg:province":"MB",
    "sg:tags":[
        "trophy"
    ],
    "wof:name":"B & B Trophy Shack Ltd",
    "wof:placetype":"venue"
},
  "geometry": {"coordinates":[-97.02562,49.897346],"type":"Point"}
}