{
  "type": "Feature",
  "properties": {
    "iso:country":"CA",
    "sg:address":"16925 Yonge St",
    "sg:city":"Newmarket",
    "sg:classifiers":[
        {
            "category":"Shopping",
            "subcategory":"Shoes",
            "type":"Retail Goods"
        }
    ],
    "sg:phone":"+1 905 830 9737",
    "sg:postcode":"L3Y 5Y1",
    "sg:province":"ON",
    "wof:name":"Zona's II the Childrens Shoe",
    "wof:placetype":"venue"
},
  "geometry": {"coordinates":[-79.47686,44.040684],"type":"Point"}
}