{
  "type": "Feature",
  "properties": {
    "addr:full":"320 Rue DE LA Vallee-Du-Golf Sainte-Adele QC J8B 1P5",
    "addr:housenumber":"320",
    "addr:postcode":"j8b 1p5",
    "addr:street":"Rue De La Vallee-Du-Golf Sainte-Adele",
    "iso:country":"CA",
    "sg:address":"320 Rue DE LA Vallee-Du-Golf",
    "sg:city":"Sainte-Adele",
    "sg:classifiers":[
        {
            "category":"Retail",
            "subcategory":"Repair Shop",
            "type":"Services"
        }
    ],
    "sg:phone":"+1 450 229 7827",
    "sg:postcode":"J8B 1P5",
    "sg:province":"QC",
    "sg:tags":[
        "welding"
    ],
    "wof:name":"Soudure Laurentides Inc",
    "wof:placetype":"venue"
},
  "geometry": {"coordinates":[-74.1185379028,45.9476928711],"type":"Point"}
}