{
  "type": "Feature",
  "properties": {
    "addr:full":"7883 Keele St Concord ON L4K 1Y6",
    "addr:housenumber":"7883",
    "addr:postcode":"l4k 1y6",
    "addr:street":"Keele St",
    "iso:country":"CA",
    "sg:address":"7883 Keele St",
    "sg:city":"Concord",
    "sg:classifiers":[
        {
            "category":"Freight",
            "type":"Transportation"
        }
    ],
    "sg:phone":"+1 905 738 1823",
    "sg:postcode":"L4K 1Y6",
    "sg:province":"ON",
    "sg:tags":[
        "trucking"
    ],
    "wof:name":"Graphic Transportation Svc Inc",
    "wof:placetype":"venue"
},
  "geometry": {"coordinates":[-79.4999008179,43.8030891418],"type":"Point"}
}