{
  "type": "Feature",
  "properties": {
    "addr:full":"268 Grosvenor St # 117 London ON N6A 4V2",
    "addr:housenumber":"268",
    "addr:postcode":"n6a 4v2",
    "addr:street":"Grosvenor St # 117",
    "iso:country":"CA",
    "sg:address":"268 Grosvenor St # 117",
    "sg:city":"London",
    "sg:classifiers":[
        {
            "category":"Health Services",
            "subcategory":"Doctor",
            "type":"Services"
        }
    ],
    "sg:phone":"+1 519 646 6384",
    "sg:postcode":"N6A 4V2",
    "sg:province":"ON",
    "sg:tags":[
        "physician",
        "surgeon"
    ],
    "wof:name":"Paulter, Steve MD",
    "wof:placetype":"venue"
},
  "geometry": {"coordinates":[-81.25348700000001,43.000294],"type":"Point"}
}