{
  "type": "Feature",
  "properties": {
    "iso:country":"CA",
    "sg:city":"Woodbridge",
    "sg:classifiers":[
        {
            "category":"Health Services",
            "subcategory":"Clinic",
            "type":"Services"
        }
    ],
    "sg:phone":"+1 905 850 2227",
    "sg:postcode":"L4L 4V8",
    "sg:province":"ON",
    "sg:tags":[
        "holistic",
        "practitioner"
    ],
    "wof:name":"Barbara's Health Club Spa",
    "wof:placetype":"venue"
},
  "geometry": {"coordinates":[-79.564728,43.769093],"type":"Point"}
}