{
  "type": "Feature",
  "properties": {
    "addr:full":"1305 7 St Nisku AB T9E 7P8",
    "addr:housenumber":"1305 7",
    "addr:postcode":"t9e 7p8",
    "addr:street":"St",
    "iso:country":"CA",
    "sg:address":"1305 7 St",
    "sg:city":"Nisku",
    "sg:classifiers":[
        {
            "category":"Building & Trades",
            "subcategory":"Construction",
            "type":"Services"
        }
    ],
    "sg:phone":"+1 780 955 2826",
    "sg:postcode":"T9E 7P8",
    "sg:province":"AB",
    "sg:tags":[
        "sewer",
        "contractor"
    ],
    "wof:name":"Kran Construction Ltd",
    "wof:placetype":"venue"
},
  "geometry": {"coordinates":[-113.52133178699999,53.3150062561],"type":"Point"}
}