{
  "type": "Feature",
  "properties": {
    "addr:full":"Saint-Nicolas QC G7A 2V1",
    "addr:postcode":"g7a 2v1",
    "iso:country":"CA",
    "sg:city":"Saint-Nicolas",
    "sg:classifiers":[
        {
            "category":"Building & Trades",
            "subcategory":"Construction",
            "type":"Services"
        }
    ],
    "sg:phone":"+1 418 836 5039",
    "sg:postcode":"G7A 2V1",
    "sg:province":"QC",
    "sg:tags":[
        "acoustical",
        "repairing",
        "remodeling",
        "contractor"
    ],
    "wof:name":"Gypses Promark",
    "wof:placetype":"venue"
},
  "geometry": {"coordinates":[-71.295174,46.730503],"type":"Point"}
}