{
  "type": "Feature",
  "properties": {
    "addr:full":"77 Kentish Dr SW Calgary AB T2V 2L4",
    "addr:housenumber":"77",
    "addr:postcode":"t2v 2l4",
    "addr:street":"Kentish Dr Sw",
    "iso:country":"CA",
    "sg:address":"77 Kentish Dr SW",
    "sg:city":"Calgary",
    "sg:classifiers":[
        {
            "category":"Education",
            "subcategory":"Special Training",
            "type":"Public Place"
        }
    ],
    "sg:phone":"+1 403 319 0277",
    "sg:postcode":"T2V 2L4",
    "sg:province":"AB",
    "sg:tags":[
        "instruction",
        "music"
    ],
    "wof:name":"Creative Start Music School",
    "wof:placetype":"venue"
},
  "geometry": {"coordinates":[-114.07620199999999,50.985153],"type":"Point"}
}