{
  "type": "Feature",
  "properties": {
    "iso:country":"CA",
    "sg:address":"196 St. George St",
    "sg:city":"Toronto",
    "sg:classifiers":[
        {
            "category":"Organizations",
            "subcategory":"Religious Organization",
            "type":"Services"
        }
    ],
    "sg:phone":"+1 416 922 0065",
    "sg:postcode":"M5R 2N5",
    "sg:province":"ON",
    "sg:tags":[
        "church"
    ],
    "wof:name":"Christian Science",
    "wof:placetype":"venue"
},
  "geometry": {"coordinates":[-79.401085,43.67012],"type":"Point"}
}