{
  "type": "Feature",
  "properties": {
    "addr:full":"15857 116 Ave NW Edmonton AB T5M 3W1",
    "addr:housenumber":"15857",
    "addr:postcode":"t5m 3w1",
    "addr:street":"116 Ave Nw",
    "iso:country":"CA",
    "sg:address":"15857 116 Ave NW",
    "sg:city":"Edmonton",
    "sg:classifiers":[
        {
            "category":"Building & Trades",
            "subcategory":"Plumbing",
            "type":"Services"
        }
    ],
    "sg:phone":"+1 780 455 7999",
    "sg:postcode":"T5M 3W1",
    "sg:province":"AB",
    "sg:tags":[
        "conditioning",
        "air",
        "refrigeration",
        "system",
        "contractor"
    ],
    "wof:name":"Inter-City Refrigeration Ltd",
    "wof:placetype":"venue"
},
  "geometry": {"coordinates":[-113.594482422,53.5655403137],"type":"Point"}
}