{
  "type": "Feature",
  "properties": {
    "addr:full":"Delta BC V4C 6P5",
    "addr:postcode":"v4c 6p5",
    "iso:country":"CA",
    "sg:city":"Delta",
    "sg:classifiers":[
        {
            "category":"Health Services",
            "subcategory":"Doctor",
            "type":"Services"
        }
    ],
    "sg:phone":"+1 604 590 1172",
    "sg:postcode":"V4C 6P5",
    "sg:province":"BC",
    "sg:tags":[
        "dentist"
    ],
    "wof:name":"Delta Orthodontic Group",
    "wof:placetype":"venue"
},
  "geometry": {"coordinates":[-122.89057922400001,49.1360092163],"type":"Point"}
}