{
  "type": "Feature",
  "properties": {
    "addr:full":"332 Rte Du President-Kennedy Beauceville QC G5X 1N9",
    "addr:housenumber":"332",
    "addr:postcode":"g5x 1n9",
    "addr:street":"Rte Du President-Kennedy",
    "iso:country":"CA",
    "sg:address":"332 Rte Du President-Kennedy",
    "sg:city":"Beauceville",
    "sg:classifiers":[
        {
            "category":"Retail",
            "subcategory":"Auto Repair",
            "type":"Services"
        }
    ],
    "sg:phone":"+1 418 774 6077",
    "sg:postcode":"G5X 1N9",
    "sg:province":"QC",
    "sg:tags":[
        "repairing",
        "automobile"
    ],
    "wof:name":"Garage J Giroux Auto Inc",
    "wof:placetype":"venue"
},
  "geometry": {"coordinates":[-70.801315,46.235416],"type":"Point"}
}