{
  "type": "Feature",
  "properties": {
    "addr:full":"Pitt Meadows BC V3Y 2B4",
    "addr:postcode":"v3y 2b4",
    "iso:country":"CA",
    "sg:city":"Pitt Meadows",
    "sg:classifiers":[
        {
            "category":"Professional",
            "subcategory":"Research",
            "type":"Services"
        }
    ],
    "sg:phone":"+1 604 465 0009",
    "sg:postcode":"V3Y 2B4",
    "sg:province":"BC",
    "sg:tags":[
        "development",
        "electronic"
    ],
    "wof:name":"Dyna Nav Systems Inc",
    "wof:placetype":"venue"
},
  "geometry": {"coordinates":[-122.700912,49.209545],"type":"Point"}
}