{
  "type": "Feature",
  "properties": {
    "addr:full":"644 Third St London ON N5V 2C2",
    "addr:housenumber":"644",
    "addr:postcode":"n5v 2c2",
    "addr:street":"Third St",
    "iso:country":"CA",
    "sg:address":"644 Third St",
    "sg:city":"London",
    "sg:classifiers":[
        {
            "category":"Retail",
            "subcategory":"Auto Repair",
            "type":"Services"
        }
    ],
    "sg:phone":"+1 519 659 4333",
    "sg:postcode":"N5V 2C2",
    "sg:province":"ON",
    "sg:tags":[
        "repairing",
        "automobile"
    ],
    "wof:name":"Afs Auto Svc",
    "wof:placetype":"venue"
},
  "geometry": {"coordinates":[-81.1895599365,43.0112915039],"type":"Point"}
}