{
  "type": "Feature",
  "properties": {
    "addr:full":"3311 Centre St NW Calgary AB T2E 2X7",
    "addr:housenumber":"3311",
    "addr:postcode":"t2e 2x7",
    "addr:street":"Centre St Nw",
    "iso:country":"CA",
    "sg:address":"3311 Centre St NW",
    "sg:city":"Calgary",
    "sg:classifiers":[
        {
            "category":"Organizations",
            "subcategory":"Religious Organization",
            "type":"Services"
        }
    ],
    "sg:phone":"+1 403 250 1310",
    "sg:postcode":"T2E 2X7",
    "sg:province":"AB",
    "sg:tags":[
        "church"
    ],
    "wof:name":"Jesus Is Lord Fellowship",
    "wof:placetype":"venue"
},
  "geometry": {"coordinates":[-114.064147949,51.0817871094],"type":"Point"}
}