{
  "type": "Feature",
  "properties": {
    "addr:full":"186 Bartley Dr North York ON M4A 1E1",
    "addr:housenumber":"186",
    "addr:postcode":"m4a 1e1",
    "addr:street":"Bartley Dr",
    "iso:country":"CA",
    "sg:address":"186 Bartley Dr",
    "sg:city":"North York",
    "sg:classifiers":[
        {
            "category":"Retail",
            "subcategory":"Auto Repair",
            "type":"Services"
        }
    ],
    "sg:phone":"+1 416 751 6612",
    "sg:postcode":"M4A 1E1",
    "sg:province":"ON",
    "sg:tags":[
        "repairing",
        "automobile"
    ],
    "wof:name":"J B Racing",
    "wof:placetype":"venue"
},
  "geometry": {"coordinates":[-79.3130950928,43.7205543518],"type":"Point"}
}