{
  "type": "Feature",
  "properties": {
    "addr:full":"Balmertown ON P0V 1C0",
    "addr:postcode":"p0v 1c0",
    "iso:country":"CA",
    "sg:city":"Balmertown",
    "sg:classifiers":[
        {
            "category":"Utilities",
            "subcategory":"Water",
            "type":"Services"
        }
    ],
    "sg:phone":"+1 807 735 2233",
    "sg:postcode":"P0V 1C0",
    "sg:province":"ON",
    "sg:tags":[
        "plant",
        "management",
        "treatment"
    ],
    "wof:name":"Balmertown Wpcp",
    "wof:placetype":"venue"
},
  "geometry": {"coordinates":[-93.74073,51.055687],"type":"Point"}
}