{
  "type": "Feature",
  "properties": {
    "addr:full":"9212 Commercial St New Minas NS B4N 5J5",
    "addr:housenumber":"9212",
    "addr:postcode":"b4n 5j5",
    "addr:street":"Commercial St",
    "iso:country":"CA",
    "sg:address":"9212 Commercial St",
    "sg:city":"New Minas",
    "sg:classifiers":[
        {
            "category":"Autos & Motor Vehicles",
            "subcategory":"Auto Supplies",
            "type":"Retail Goods"
        }
    ],
    "sg:phone":"+1 902 681 1400",
    "sg:postcode":"B4N 5J5",
    "sg:province":"NS",
    "sg:tags":[
        "hardware",
        "automobile",
        "parts"
    ],
    "wof:name":"Canadian Tire",
    "wof:placetype":"venue"
},
  "geometry": {"coordinates":[-64.44580841059999,45.0673942566],"type":"Point"}
}