{
  "type": "Feature",
  "properties": {
    "addr:full":"345 Old Airport Rd Yellowknife NT X1A 3T4",
    "addr:housenumber":"345",
    "addr:postcode":"x1a 3t4",
    "addr:street":"Old Airport Rd",
    "iso:country":"CA",
    "sg:address":"345 Old Airport Rd",
    "sg:city":"Yellowknife",
    "sg:classifiers":[
        {
            "category":"Professional",
            "type":"Services"
        }
    ],
    "sg:phone":"+1 867 873 3003",
    "sg:postcode":"X1A 3T4",
    "sg:province":"NT",
    "sg:tags":[
        "plumbing",
        "establishment",
        "contractor"
    ],
    "wof:name":"Central Mechanical Systems Ltd",
    "wof:placetype":"venue"
},
  "geometry": {"coordinates":[-114.414024,62.464027],"type":"Point"}
}