{
  "type": "Feature",
  "properties": {
    "iso:country":"CA",
    "sg:address":"260 Mackenzie Blvd",
    "sg:city":"Mackenzie",
    "sg:classifiers":[
        {
            "category":"Autos & Motor Vehicles",
            "subcategory":"Fuel & Gas Station",
            "type":"Retail Goods"
        }
    ],
    "sg:phone":"+1 250 997 6667",
    "sg:postcode":"V0J 2C0",
    "sg:province":"BC",
    "sg:tags":[
        "oil"
    ],
    "wof:name":"Mac Kenzie Town Pantry",
    "wof:placetype":"venue"
},
  "geometry": {"coordinates":[-123.094680786,55.3355064392],"type":"Point"}
}