{
  "type": "Feature",
  "properties": {
    "addr:full":"2160 Rue Jean-Talon N Sainte-Foy QC G1N 2G3",
    "addr:housenumber":"2160",
    "addr:postcode":"g1n 2g3",
    "addr:street":"Rue Jean-Talon N Sainte-Foy",
    "iso:country":"CA",
    "sg:address":"2160 Rue Jean-Talon N",
    "sg:city":"Sainte-Foy",
    "sg:classifiers":[
        {
            "category":"Manufacturing",
            "subcategory":"Tools & Machinery",
            "type":"Manufacturing & Wholesale Goods"
        }
    ],
    "sg:phone":"+1 418 688 1538",
    "sg:postcode":"G1N 2G3",
    "sg:province":"QC",
    "sg:tags":[
        "die",
        "cutting"
    ],
    "wof:name":"Matrices Diestar Inc",
    "wof:placetype":"venue"
},
  "geometry": {"coordinates":[-71.279579,46.795368],"type":"Point"}
}