{
  "type": "Feature",
  "properties": {
    "addr:full":"51 Beattie Ave London ON N5W 2P1",
    "addr:housenumber":"51",
    "addr:postcode":"n5w 2p1",
    "addr:street":"Beattie Ave",
    "iso:country":"CA",
    "sg:address":"51 Beattie Ave",
    "sg:city":"London",
    "sg:classifiers":[
        {
            "category":"Professional",
            "subcategory":"Advertising",
            "type":"Services"
        }
    ],
    "sg:phone":"+1 519 438 5413",
    "sg:postcode":"N5W 2P1",
    "sg:province":"ON",
    "wof:name":"Home & Guide Magazine",
    "wof:placetype":"venue"
},
  "geometry": {"coordinates":[-81.19933319090001,42.9939537048],"type":"Point"}
}