{
  "type": "Feature",
  "properties": {
    "addr:full":"Gravenhurst ON P1P 1X4",
    "addr:postcode":"p1p 1x4",
    "iso:country":"CA",
    "sg:city":"Gravenhurst",
    "sg:classifiers":[
        {
            "category":"Retail",
            "subcategory":"Auto Repair",
            "type":"Services"
        }
    ],
    "sg:phone":"+1 705 684 8025",
    "sg:postcode":"P1P 1X4",
    "sg:province":"ON",
    "sg:tags":[
        "repairing",
        "automobile"
    ],
    "wof:name":"Nelson Automotive",
    "wof:placetype":"venue"
},
  "geometry": {"coordinates":[-79.3613739014,44.9374351501],"type":"Point"}
}