{
  "type": "Feature",
  "properties": {
    "iso:country":"CA",
    "sg:city":"Vancouver",
    "sg:classifiers":[
        {
            "category":"Education",
            "subcategory":"Special Training",
            "type":"Public Place"
        }
    ],
    "sg:phone":"+1 604 669 3875",
    "sg:postcode":"V6A 1B2",
    "sg:province":"BC",
    "sg:tags":[
        "school",
        "language"
    ],
    "wof:name":"Language Repair Shop",
    "wof:placetype":"venue"
},
  "geometry": {"coordinates":[-123.104003906,49.2835273743],"type":"Point"}
}