{
  "type": "Feature",
  "properties": {
    "addr:full":"4145 Aut Des Laurentides Laval QC H7L 5W5",
    "addr:postcode":"4145;h7l 5w5",
    "addr:street":"Des Laurentides",
    "iso:country":"CA",
    "sg:address":"4145 Aut Des Laurentides",
    "sg:city":"Laval",
    "sg:classifiers":[
        {
            "category":"Wholesale",
            "subcategory":"Medical Equipment & Supplies",
            "type":"Manufacturing & Wholesale Goods"
        }
    ],
    "sg:phone":"+1 450 682 0662",
    "sg:postcode":"H7L 5W5",
    "sg:province":"QC",
    "sg:tags":[
        "optical"
    ],
    "wof:name":"Instruments Ophtalmiques",
    "wof:placetype":"venue"
},
  "geometry": {"coordinates":[-73.7679672241,45.5805702209],"type":"Point"}
}