{
  "type": "Feature",
  "properties": {
    "iso:country":"CA",
    "sg:city":"Spruce Grove",
    "sg:classifiers":[
        {
            "category":"Organizations",
            "subcategory":"Religious Organization",
            "type":"Services"
        }
    ],
    "sg:phone":"+1 780 962 0488",
    "sg:postcode":"T7X 2Z3",
    "sg:province":"AB",
    "sg:tags":[
        "church"
    ],
    "wof:name":"United Church St Andrew's",
    "wof:placetype":"venue"
},
  "geometry": {"coordinates":[-113.90660099999999,53.558235],"type":"Point"}
}