{
  "type": "Feature",
  "properties": {
    "addr:full":"92 Clearwater STN Clearwater BC V0E 1N0",
    "addr:housenumber":"92",
    "addr:postcode":"v0e 1n0",
    "addr:street":"Clearwater",
    "iso:country":"CA",
    "sg:address":"92 Clearwater STN",
    "sg:city":"Clearwater",
    "sg:classifiers":[
        {
            "category":"Retail",
            "subcategory":"Repair Shop",
            "type":"Services"
        }
    ],
    "sg:phone":"+1 250 674 2451",
    "sg:postcode":"V0E 1N0",
    "sg:province":"BC",
    "sg:tags":[
        "upholsterer"
    ],
    "wof:name":"Clearwater Upholstery",
    "wof:placetype":"venue"
},
  "geometry": {"coordinates":[-120.034820557,51.6509246826],"type":"Point"}
}