{
  "type": "Feature",
  "properties": {
    "addr:full":"1016 Upper Wellington St Hamilton ON L9A 3S3",
    "addr:housenumber":"1016",
    "addr:postcode":"l9a 3s3",
    "addr:street":"Upper Wellington St",
    "iso:country":"CA",
    "sg:address":"1016 Upper Wellington St",
    "sg:city":"Hamilton",
    "sg:classifiers":[
        {
            "category":"Education",
            "subcategory":"Vocational School",
            "type":"Public Place"
        }
    ],
    "sg:phone":"+1 905 575 8311",
    "sg:postcode":"L9A 3S3",
    "sg:province":"ON",
    "sg:tags":[
        "technical",
        "trade"
    ],
    "wof:name":"Advanced Welding Techniques",
    "wof:placetype":"venue"
},
  "geometry": {"coordinates":[-79.87325286870001,43.2235336304],"type":"Point"}
}