{
  "type": "Feature",
  "properties": {
    "addr:full":"1516 Inkster Blvd Winnipeg MB R2X 2T8",
    "addr:housenumber":"1516",
    "addr:postcode":"r2x 2t8",
    "addr:street":"Inkster Blvd",
    "iso:country":"CA",
    "sg:address":"1516 Inkster Blvd",
    "sg:city":"Winnipeg",
    "sg:classifiers":[
        {
            "category":"Home & Garden",
            "subcategory":"Carpets & Floor Coverings",
            "type":"Retail Goods"
        }
    ],
    "sg:phone":"+1 204 694 7835",
    "sg:postcode":"R2X 2T8",
    "sg:province":"MB",
    "sg:tags":[
        "dealer",
        "rug"
    ],
    "wof:name":"Canadian Carpet Outlet",
    "wof:placetype":"venue"
},
  "geometry": {"coordinates":[-97.177521,49.944359],"type":"Point"}
}