{
  "type": "Feature",
  "properties": {
    "addr:full":"214 Main St Schomberg ON L0G 1T0",
    "addr:housenumber":"214",
    "addr:postcode":"l0g 1t0",
    "addr:street":"Main St",
    "iso:country":"CA",
    "sg:address":"214 Main St",
    "sg:city":"Schomberg",
    "sg:classifiers":[
        {
            "category":"Shopping",
            "subcategory":"Used Merchandise",
            "type":"Retail Goods"
        }
    ],
    "sg:phone":"+1 905 939 4582",
    "sg:postcode":"L0G 1T0",
    "sg:province":"ON",
    "sg:tags":[
        "antique"
    ],
    "wof:name":"Deruiters Mill Antiques",
    "wof:placetype":"venue"
},
  "geometry": {"coordinates":[-79.683655,44.001987],"type":"Point"}
}