{
  "type": "Feature",
  "properties": {
    "iso:country":"CA",
    "sg:address":"40 Rue Labelle",
    "sg:city":"Beauport",
    "sg:classifiers":[
        {
            "category":"Professional",
            "subcategory":"Employment Agencies",
            "type":"Services"
        }
    ],
    "sg:phone":"+1 418 664 0886",
    "sg:postcode":"G1E 5R3",
    "sg:province":"QC",
    "sg:tags":[
        "contractor"
    ],
    "wof:name":"Service Maritime Coulombe Ltee",
    "wof:placetype":"venue"
},
  "geometry": {"coordinates":[-71.18082427980001,46.8713340759],"type":"Point"}
}