{
  "type": "Feature",
  "properties": {
    "addr:full":"87 Huron St Collingwood ON L9Y 1C7",
    "addr:housenumber":"87",
    "addr:postcode":"l9y 1c7",
    "addr:street":"Huron St",
    "iso:country":"CA",
    "sg:address":"87 Huron St",
    "sg:city":"Collingwood",
    "sg:classifiers":[
        {
            "category":"Building & Trades",
            "subcategory":"Construction",
            "type":"Services"
        }
    ],
    "sg:phone":"+1 705 444 5505",
    "sg:postcode":"L9Y 1C7",
    "sg:province":"ON",
    "sg:tags":[
        "designer",
        "hot",
        "spa",
        "tub",
        "dealer",
        "pool",
        "swimming"
    ],
    "wof:name":"Shamrock Pool Svc",
    "wof:placetype":"venue"
},
  "geometry": {"coordinates":[-80.2077255249,44.5065498352],"type":"Point"}
}