{
  "type": "Feature",
  "properties": {
    "addr:full":"161 Stanford Ave E Parksville BC V9P 1M4",
    "addr:housenumber":"161",
    "addr:postcode":"v9p 1m4",
    "addr:street":"Stanford Ave E",
    "iso:country":"CA",
    "sg:address":"161 Stanford Ave E",
    "sg:city":"Parksville",
    "sg:classifiers":[
        {
            "category":"Shopping",
            "subcategory":"Clothing, Apparel, & Fashions",
            "type":"Retail Goods"
        }
    ],
    "sg:phone":"+1 250 248 6682",
    "sg:postcode":"V9P 1M4",
    "sg:province":"BC",
    "wof:name":"Kloz Haus Clothing Design Std",
    "wof:placetype":"venue"
},
  "geometry": {"coordinates":[-124.309844971,49.315486908],"type":"Point"}
}