{
  "type": "Feature",
  "properties": {
    "addr:full":"215 Bloor St E Oshawa ON L1H 3M3",
    "addr:housenumber":"215",
    "addr:postcode":"l1h 3m3",
    "addr:street":"Bloor St E",
    "iso:country":"CA",
    "sg:address":"215 Bloor St E",
    "sg:city":"Oshawa",
    "sg:classifiers":[
        {
            "category":"Shopping",
            "subcategory":"Florist",
            "type":"Retail Goods"
        }
    ],
    "sg:phone":"+1 905 434 7393",
    "sg:postcode":"L1H 3M3",
    "sg:province":"ON",
    "wof:name":"Rose's Flowers",
    "wof:placetype":"venue"
},
  "geometry": {"coordinates":[-78.84781646730001,43.8820877075],"type":"Point"}
}