{
  "type": "Feature",
  "properties": {
    "iso:country":"CA",
    "sg:address":"310 5E Rue",
    "sg:city":"Grand-Mere",
    "sg:classifiers":[
        {
            "category":"Restaurant",
            "type":"Food & Drink"
        }
    ],
    "sg:phone":"+1 819 533 4440",
    "sg:postcode":"G9T 4R8",
    "sg:province":"QC",
    "wof:name":"Distribution J Marchand Inc",
    "wof:placetype":"venue"
},
  "geometry": {"coordinates":[-72.6876983643,46.6165466309],"type":"Point"}
}