{
  "type": "Feature",
  "properties": {
    "addr:full":"Whitby ON L1N 9S2",
    "addr:postcode":"l1n 9s2",
    "iso:country":"CA",
    "sg:city":"Whitby",
    "sg:classifiers":[
        {
            "category":"Recreation",
            "type":"Entertainment"
        }
    ],
    "sg:phone":"+1 905 430 3206",
    "sg:postcode":"L1N 9S2",
    "sg:province":"ON",
    "sg:tags":[
        "course",
        "golf",
        "amusement"
    ],
    "wof:name":"Putting Edge",
    "wof:placetype":"venue"
},
  "geometry": {"coordinates":[-78.9124984741,43.8707923889],"type":"Point"}
}