{
  "type": "Feature",
  "properties": {
    "addr:full":"6342 Rue Sherbrooke E Montreal QC H1N 1C1",
    "addr:housenumber":"6342",
    "addr:postcode":"h1n 1c1",
    "addr:street":"Rue Sherbrooke E",
    "iso:country":"CA",
    "sg:address":"6342 Rue Sherbrooke E",
    "sg:city":"Montreal",
    "sg:classifiers":[
        {
            "category":"Food & Beverages",
            "subcategory":"Groceries & Convenience Stores",
            "type":"Retail Goods"
        }
    ],
    "sg:phone":"+1 514 259 8881",
    "sg:postcode":"H1N 1C1",
    "sg:province":"QC",
    "wof:name":"Depanneur Woolym",
    "wof:placetype":"venue"
},
  "geometry": {"coordinates":[-73.544594,45.579815],"type":"Point"}
}