{
  "type": "Feature",
  "properties": {
    "addr:full":"1610 Rue Eiffel Boucherville QC J4B 5Y1",
    "addr:housenumber":"1610",
    "addr:postcode":"j4b 5y1",
    "addr:street":"Rue Eiffel",
    "iso:country":"CA",
    "sg:address":"1610 Rue Eiffel",
    "sg:city":"Boucherville",
    "sg:classifiers":[
        {
            "category":"Manufacturing",
            "subcategory":"Rubber & Plastics",
            "type":"Manufacturing & Wholesale Goods"
        }
    ],
    "sg:phone":"+1 450 449 6000",
    "sg:postcode":"J4B 5Y1",
    "sg:province":"QC",
    "wof:name":"Soniplastics Inc",
    "wof:placetype":"venue"
},
  "geometry": {"coordinates":[-73.4001235962,45.5696372986],"type":"Point"}
}