{
  "type": "Feature",
  "properties": {
    "addr:full":"80 Tigi Crt Concord ON L4K 5E4",
    "addr:housenumber":"80",
    "addr:postcode":"l4k 5e4",
    "addr:street":"Tigi Crt",
    "iso:country":"CA",
    "sg:address":"80 Tigi Crt",
    "sg:city":"Concord",
    "sg:classifiers":[
        {
            "category":"Wholesale",
            "subcategory":"Construction Materials",
            "type":"Manufacturing & Wholesale Goods"
        }
    ],
    "sg:phone":"+1 905 303 5811",
    "sg:postcode":"L4K 5E4",
    "sg:province":"ON",
    "sg:tags":[
        "stone",
        "interlocking"
    ],
    "wof:name":"Technique Interlock Paving",
    "wof:placetype":"venue"
},
  "geometry": {"coordinates":[-79.5184631348,43.8316955566],"type":"Point"}
}