{
  "type": "Feature",
  "properties": {
    "addr:full":"16 Teskey Crt Collingwood ON L9Y 4R9",
    "addr:housenumber":"16",
    "addr:postcode":"l9y 4r9",
    "addr:street":"Teskey Crt",
    "iso:country":"CA",
    "sg:address":"16 Teskey Crt",
    "sg:city":"Collingwood",
    "sg:classifiers":[
        {
            "category":"Building & Trades",
            "subcategory":"Plumbing",
            "type":"Services"
        }
    ],
    "sg:phone":"+1 705 445 0644",
    "sg:postcode":"L9Y 4R9",
    "sg:province":"ON",
    "sg:tags":[
        "contractor"
    ],
    "wof:name":"Bloomfield Plumbing Ltd",
    "wof:placetype":"venue"
},
  "geometry": {"coordinates":[-80.225807,44.482544],"type":"Point"}
}