{
  "type": "Feature",
  "properties": {
    "addr:full":"221 Westney Rd S Ajax ON L1S 2C9",
    "addr:housenumber":"221",
    "addr:postcode":"l1s 2c9",
    "addr:street":"Westney Rd",
    "iso:country":"CA",
    "sg:address":"221 Westney Rd S",
    "sg:city":"Ajax",
    "sg:classifiers":[
        {
            "category":"Retail",
            "subcategory":"Car Wash",
            "type":"Services"
        }
    ],
    "sg:phone":"+1 905 619 2899",
    "sg:postcode":"L1S 2C9",
    "sg:province":"ON",
    "sg:tags":[
        "polishing",
        "washing"
    ],
    "wof:name":"Diamond Shine Car Cleaning",
    "wof:placetype":"venue"
},
  "geometry": {"coordinates":[-79.0357589722,43.8427658081],"type":"Point"}
}