{
  "type": "Feature",
  "properties": {
    "addr:full":"1443 Bellevue Ave Sudbury ON P3B 3G1",
    "addr:housenumber":"1443",
    "addr:postcode":"p3b 3g1",
    "addr:street":"Bellevue Ave",
    "iso:country":"CA",
    "sg:address":"1443 Bellevue Ave",
    "sg:city":"Sudbury",
    "sg:classifiers":[
        {
            "category":"Education",
            "subcategory":"Dance Studio",
            "type":"Public Place"
        }
    ],
    "sg:phone":"+1 705 560 0776",
    "sg:postcode":"P3B 3G1",
    "sg:province":"ON",
    "sg:tags":[
        "instruction",
        "dancing"
    ],
    "wof:name":"Bellevue Dancing Studio",
    "wof:placetype":"venue"
},
  "geometry": {"coordinates":[-80.954262,46.490425],"type":"Point"}
}