{
  "type": "Feature",
  "properties": {
    "addr:full":"Coquitlam BC V3K 6X2",
    "addr:postcode":"v3k 6x2",
    "iso:country":"CA",
    "sg:city":"Coquitlam",
    "sg:classifiers":[
        {
            "category":"Manufacturing",
            "subcategory":"Tools & Machinery",
            "type":"Manufacturing & Wholesale Goods"
        }
    ],
    "sg:phone":"+1 604 540 0256",
    "sg:postcode":"V3K 6X2",
    "sg:province":"BC",
    "sg:tags":[
        "die",
        "maker"
    ],
    "wof:name":"Western Unitool Mfg Inc",
    "wof:placetype":"venue"
},
  "geometry": {"coordinates":[-122.852715,49.227341],"type":"Point"}
}