{
  "type": "Feature",
  "properties": {
    "addr:full":"109 Front St E Strathroy ON N7G 1Y8",
    "addr:housenumber":"109",
    "addr:postcode":"n7g 1y8",
    "addr:street":"Front St E",
    "iso:country":"CA",
    "sg:address":"109 Front St E",
    "sg:city":"Strathroy",
    "sg:classifiers":[
        {
            "category":"Real Estate",
            "subcategory":"Real Estate Agent",
            "type":"Services"
        }
    ],
    "sg:phone":"+1 519 245 6655",
    "sg:postcode":"N7G 1Y8",
    "sg:province":"ON",
    "wof:name":"Progressive Realty Strathroy",
    "wof:placetype":"venue"
},
  "geometry": {"coordinates":[-81.62103999999999,42.960346],"type":"Point"}
}