{
  "type": "Feature",
  "properties": {
    "iso:country":"CA",
    "sg:address":"1373 Confederation St #1",
    "sg:city":"Sarnia",
    "sg:classifiers":[
        {
            "category":"Wholesale",
            "subcategory":"Machinery & Supplies",
            "type":"Manufacturing & Wholesale Goods"
        }
    ],
    "sg:phone":"+1 519 337 0777",
    "sg:postcode":"N7S 5P1",
    "sg:province":"ON",
    "sg:tags":[
        "valve"
    ],
    "wof:name":"Matheson Valves & Fittings Ltd",
    "wof:placetype":"venue"
},
  "geometry": {"coordinates":[-82.3562469482,42.9600257874],"type":"Point"}
}