{
  "type": "Feature",
  "properties": {
    "addr:full":"Markham ON L3R 3L4",
    "addr:postcode":"l3r 3l4",
    "iso:country":"CA",
    "sg:city":"Markham",
    "sg:classifiers":[
        {
            "category":"Airline",
            "type":"Transportation"
        }
    ],
    "sg:phone":"+1 905 940 5339",
    "sg:postcode":"L3R 3L4",
    "sg:province":"ON",
    "sg:tags":[
        "rental",
        "aircraft",
        "leasing",
        "charter"
    ],
    "wof:name":"Fex Aviation",
    "wof:placetype":"venue"
},
  "geometry": {"coordinates":[-79.33345799999999,43.834377],"type":"Point"}
}