{
  "type": "Feature",
  "properties": {
    "addr:full":"910 Cranbrook St N Cranbrook BC V1C 3S3",
    "addr:housenumber":"910",
    "addr:postcode":"v1c 3s3",
    "addr:street":"Cranbrook St N",
    "iso:country":"CA",
    "sg:address":"910 Cranbrook St N",
    "sg:city":"Cranbrook",
    "sg:classifiers":[
        {
            "category":"Travel",
            "subcategory":"Hotels & Motels",
            "type":"Entertainment"
        }
    ],
    "sg:phone":"+1 250 426 6266",
    "sg:postcode":"V1C 3S3",
    "sg:province":"BC",
    "wof:name":"Nomad Motel",
    "wof:placetype":"venue"
},
  "geometry": {"coordinates":[-115.75844600000001,49.520309],"type":"Point"}
}