{
  "type": "Feature",
  "properties": {
    "addr:full":"Napanee ON K7R 3L1",
    "addr:postcode":"k7r 3l1",
    "iso:country":"CA",
    "sg:city":"Napanee",
    "sg:classifiers":[
        {
            "category":"Wholesale",
            "subcategory":"Scrap",
            "type":"Manufacturing & Wholesale Goods"
        }
    ],
    "sg:phone":"+1 613 354 2775",
    "sg:postcode":"K7R 3L1",
    "sg:province":"ON",
    "sg:tags":[
        "metal",
        "iron"
    ],
    "wof:name":"Greater Napanee Recycling Ltd",
    "wof:placetype":"venue"
},
  "geometry": {"coordinates":[-76.9515838623,44.2483253479],"type":"Point"}
}