{
  "type": "Feature",
  "properties": {
    "addr:full":"10 Boul Saint-Benoit O Amqui QC G5J 2C6",
    "addr:housenumber":"10",
    "addr:postcode":"g5j 2c6",
    "addr:street":"Boul Saint-Benoit O",
    "iso:country":"CA",
    "sg:address":"10 Boul Saint-Benoit O",
    "sg:city":"Amqui",
    "sg:classifiers":[
        {
            "category":"Shopping",
            "subcategory":"Computers & Home Electronics",
            "type":"Retail Goods"
        }
    ],
    "sg:phone":"+1 418 629 4437",
    "sg:postcode":"G5J 2C6",
    "sg:province":"QC",
    "sg:tags":[
        "stationer",
        "equipment",
        "dealer"
    ],
    "wof:name":"Librairie D'Amqui Inc",
    "wof:placetype":"venue"
},
  "geometry": {"coordinates":[-67.42480500000001,48.464642],"type":"Point"}
}