{
  "type": "Feature",
  "properties": {
    "addr:full":"NE 26-7-6E Blumenort MB R0A 0C0",
    "addr:housenumber":"26-7-6e",
    "addr:postcode":"r0a 0c0",
    "addr:street":"Ne",
    "iso:country":"CA",
    "sg:address":"NE 26-7-6E",
    "sg:city":"Blumenort",
    "sg:classifiers":[
        {
            "category":"Building & Trades",
            "subcategory":"Electrical",
            "type":"Services"
        }
    ],
    "sg:phone":"+1 204 326 3966",
    "sg:postcode":"R0A 0C0",
    "sg:province":"MB",
    "sg:tags":[
        "electric",
        "contractor"
    ],
    "wof:name":"Barkman Electric",
    "wof:placetype":"venue"
},
  "geometry": {"coordinates":[-96.69017028810001,49.6042556763],"type":"Point"}
}