{
  "type": "Feature",
  "properties": {
    "addr:full":"34 Christopher Dr Burton NB E2V 3H7",
    "addr:housenumber":"34",
    "addr:postcode":"e2v 3h7",
    "addr:street":"Christopher Dr",
    "iso:country":"CA",
    "sg:address":"34 Christopher Dr",
    "sg:city":"Burton",
    "sg:classifiers":[
        {
            "category":"Personal",
            "subcategory":"Beauty Salon",
            "type":"Services"
        }
    ],
    "sg:phone":"+1 506 357 7221",
    "sg:postcode":"E2V 3H7",
    "sg:province":"NB",
    "wof:name":"Uli's Hair Fashions",
    "wof:placetype":"venue"
},
  "geometry": {"coordinates":[-66.37796,45.871799],"type":"Point"}
}