{
  "type": "Feature",
  "properties": {
    "addr:full":"520 Centre Ave E Airdrie AB T4B 1P8",
    "addr:housenumber":"520",
    "addr:postcode":"t4b 1p8",
    "addr:street":"Centre Ave E",
    "iso:country":"CA",
    "sg:address":"520 Centre Ave E",
    "sg:city":"Airdrie",
    "sg:classifiers":[
        {
            "category":"Retail",
            "subcategory":"Auto Repair",
            "type":"Services"
        }
    ],
    "sg:phone":"+1 403 948 4788",
    "sg:postcode":"T4B 1P8",
    "sg:province":"AB",
    "sg:tags":[
        "repairing",
        "automobile"
    ],
    "wof:name":"Highland Automotive & Muffler",
    "wof:placetype":"venue"
},
  "geometry": {"coordinates":[-114.003265,51.291531],"type":"Point"}
}