{
  "type": "Feature",
  "properties": {
    "iso:country":"CA",
    "sg:address":"158 Rue Prince-Arthur E",
    "sg:city":"Montreal",
    "sg:classifiers":[
        {
            "category":"Personal",
            "subcategory":"Tattoo Parlor",
            "type":"Services"
        }
    ],
    "sg:phone":"+1 514 350 0015",
    "sg:postcode":"H2X 1B7",
    "sg:province":"QC",
    "sg:tags":[
        "tattooing"
    ],
    "wof:name":"Imago Montreal",
    "wof:placetype":"venue"
},
  "geometry": {"coordinates":[-73.571136,45.51532],"type":"Point"}
}