{
  "type": "Feature",
  "properties": {
    "iso:country":"CA",
    "sg:address":"1414 8th St E",
    "sg:city":"Saskatoon",
    "sg:classifiers":[
        {
            "category":"Banks & Credit Unions",
            "subcategory":"Investment Brokerage",
            "type":"Services"
        }
    ],
    "sg:phone":"+1 306 955 9190",
    "sg:postcode":"S7H 0T1",
    "sg:province":"SK",
    "sg:tags":[
        "consultant",
        "planning",
        "financial"
    ],
    "wof:name":"Investors Group Financial Svc",
    "wof:placetype":"venue"
},
  "geometry": {"coordinates":[-106.636459351,52.1145629883],"type":"Point"}
}