{
  "type": "Feature",
  "properties": {
    "iso:country":"CA",
    "sg:address":"6990 Financial Dr",
    "sg:city":"Mississauga",
    "sg:classifiers":[
        {
            "category":"Restaurant",
            "type":"Food & Drink"
        }
    ],
    "sg:phone":"+1 905 821 9334",
    "sg:postcode":"L5N 8J4",
    "sg:province":"ON",
    "wof:name":"Tosca Ristorante Italiano",
    "wof:placetype":"venue"
},
  "geometry": {"coordinates":[-79.74909973139999,43.6112632751],"type":"Point"}
}