{
  "type": "Feature",
  "properties": {
    "iso:country":"CA",
    "sg:address":"Nemiah Valley Rd",
    "sg:city":"Nemaiah Valley",
    "sg:classifiers":[
        {
            "category":"Education",
            "subcategory":"School",
            "type":"Public Place"
        }
    ],
    "sg:phone":"+1 250 394 7060",
    "sg:postcode":"V0L 1X0",
    "sg:province":"BC",
    "wof:name":"Naghtaneqed Elementary & Jr",
    "wof:placetype":"venue"
},
  "geometry": {"coordinates":[-123.850830078,51.4824638367],"type":"Point"}
}