{
  "type": "Feature",
  "properties": {
    "addr:full":"575 Rue Martin Saint-Pascal QC G0L 3Y0",
    "addr:housenumber":"575",
    "addr:postcode":"g0l 3y0",
    "addr:street":"Rue Martin",
    "iso:country":"CA",
    "sg:address":"575 Rue Martin",
    "sg:city":"Saint-Pascal",
    "sg:classifiers":[
        {
            "category":"Social Services",
            "type":"Services"
        }
    ],
    "sg:phone":"+1 418 493 2006",
    "sg:postcode":"G0L 3Y0",
    "sg:province":"QC",
    "sg:tags":[
        "organization",
        "hospital",
        "welfare"
    ],
    "wof:name":"Reseau Sante Kamouraska",
    "wof:placetype":"venue"
},
  "geometry": {"coordinates":[-69.803467,47.528965],"type":"Point"}
}