{
  "type": "Feature",
  "properties": {
    "addr:full":"3000 Victoria Ave E Brandon MB R7A 7L2",
    "addr:housenumber":"3000",
    "addr:postcode":"r7a 7l2",
    "addr:street":"Victoria Ave E",
    "iso:country":"CA",
    "sg:address":"3000 Victoria Ave E",
    "sg:city":"Brandon",
    "sg:classifiers":[
        {
            "category":"Building & Trades",
            "subcategory":"Construction",
            "type":"Services"
        }
    ],
    "sg:phone":"+1 204 726 0790",
    "sg:postcode":"R7A 7L2",
    "sg:province":"MB",
    "sg:tags":[
        "excavating",
        "sewer",
        "contractor"
    ],
    "wof:name":"Cumming & Dobbie Ltd",
    "wof:placetype":"venue"
},
  "geometry": {"coordinates":[-99.902107,49.842278],"type":"Point"}
}