{
  "type": "Feature",
  "properties": {
    "iso:country":"CA",
    "sg:city":"Dorval",
    "sg:classifiers":[
        {
            "category":"Banks & Credit Unions",
            "subcategory":"Investment Brokerage",
            "type":"Services"
        }
    ],
    "sg:phone":"+1 514 421 3773",
    "sg:postcode":"H9P 2V9",
    "sg:province":"QC",
    "sg:tags":[
        "consultant",
        "planning",
        "financial"
    ],
    "wof:name":"Berkshire Investment Group",
    "wof:placetype":"venue"
},
  "geometry": {"coordinates":[-73.7737121582,45.4892539978],"type":"Point"}
}