{
  "type": "Feature",
  "properties": {
    "iso:country":"CA",
    "sg:address":"10774 Rue Berri",
    "sg:city":"Montreal",
    "sg:classifiers":[
        {
            "category":"Health Services",
            "subcategory":"Doctor",
            "type":"Services"
        }
    ],
    "sg:phone":"+1 514 388 4391",
    "sg:postcode":"H3L 2H4",
    "sg:province":"QC",
    "sg:tags":[
        "dentist"
    ],
    "wof:name":"Clinique Dentaire Belanger",
    "wof:placetype":"venue"
},
  "geometry": {"coordinates":[-73.669952,45.554722],"type":"Point"}
}