{
  "type": "Feature",
  "properties": {
    "addr:full":"Spruce Grove AB T7Y 1G1",
    "addr:postcode":"t7y 1g1",
    "iso:country":"CA",
    "sg:city":"Spruce Grove",
    "sg:classifiers":[
        {
            "category":"Manufacturing",
            "subcategory":"Tools & Machinery",
            "type":"Manufacturing & Wholesale Goods"
        }
    ],
    "sg:phone":"+1 780 987 9133",
    "sg:postcode":"T7Y 1G1",
    "sg:province":"AB",
    "sg:tags":[
        "equipment",
        "nurseryman",
        "center",
        "garden",
        "supply"
    ],
    "wof:name":"Cannor Nurseries Ltd",
    "wof:placetype":"venue"
},
  "geometry": {"coordinates":[-113.901855,53.544636],"type":"Point"}
}