{
  "type": "Feature",
  "properties": {
    "addr:full":"Richmond BC V6Y 2B6",
    "addr:postcode":"v6y 2b6",
    "iso:country":"CA",
    "sg:city":"Richmond",
    "sg:classifiers":[
        {
            "category":"Shopping",
            "subcategory":"Gifts & Souvenirs",
            "type":"Retail Goods"
        }
    ],
    "sg:phone":"+1 604 270 4972",
    "sg:postcode":"V6Y 2B6",
    "sg:province":"BC",
    "sg:tags":[
        "shop"
    ],
    "wof:name":"Great Wilderness CO",
    "wof:placetype":"venue"
},
  "geometry": {"coordinates":[-123.136657715,49.1663742065],"type":"Point"}
}