{
  "type": "Feature",
  "properties": {
    "addr:full":"117 Main St Barons AB T0L 0G0",
    "addr:housenumber":"117",
    "addr:postcode":"t0l 0g0",
    "addr:street":"Main St",
    "iso:country":"CA",
    "sg:address":"117 Main St",
    "sg:city":"Barons",
    "sg:classifiers":[
        {
            "category":"Travel",
            "subcategory":"Hotels & Motels",
            "type":"Entertainment"
        }
    ],
    "sg:phone":"+1 403 757 3767",
    "sg:postcode":"T0L 0G0",
    "sg:province":"AB",
    "wof:name":"Barons Hotel",
    "wof:placetype":"venue"
},
  "geometry": {"coordinates":[-113.084282,49.995968],"type":"Point"}
}