{
  "type": "Feature",
  "properties": {
    "addr:full":"101 Danforth Ave Toronto ON M4K 1N2",
    "addr:housenumber":"101",
    "addr:postcode":"m4k 1n2",
    "addr:street":"Danforth Ave",
    "iso:country":"CA",
    "sg:address":"101 Danforth Ave",
    "sg:city":"Toronto",
    "sg:classifiers":[
        {
            "category":"Shopping",
            "subcategory":"Discount & Variety Stores",
            "type":"Retail Goods"
        }
    ],
    "sg:phone":"+1 416 461 6439",
    "sg:postcode":"M4K 1N2",
    "sg:province":"ON",
    "wof:name":"Double D Discount Store",
    "wof:placetype":"venue"
},
  "geometry": {"coordinates":[-79.35823822019999,43.6761398315],"type":"Point"}
}