{
  "type": "Feature",
  "properties": {
    "addr:full":"6478 256 St Langley BC V4W 1T8",
    "addr:housenumber":"6478",
    "addr:postcode":"v4w 1t8",
    "addr:street":"256 St",
    "iso:country":"CA",
    "sg:address":"6478 256 St",
    "sg:city":"Langley",
    "sg:classifiers":[
        {
            "category":"Building & Trades",
            "subcategory":"Construction",
            "type":"Services"
        }
    ],
    "sg:phone":"+1 604 857 1983",
    "sg:postcode":"V4W 1T8",
    "sg:province":"BC",
    "sg:tags":[
        "masonry",
        "contractor"
    ],
    "wof:name":"Jan Van Tunen Masonry",
    "wof:placetype":"venue"
},
  "geometry": {"coordinates":[-122.514663696,49.1204605103],"type":"Point"}
}