{
  "type": "Feature",
  "properties": {
    "addr:full":"52 King St W Bowmanville ON L1C 1R4",
    "addr:housenumber":"52",
    "addr:postcode":"l1c 1r4",
    "addr:street":"King St W",
    "iso:country":"CA",
    "sg:address":"52 King St W",
    "sg:city":"Bowmanville",
    "sg:classifiers":[
        {
            "category":"Insurance",
            "subcategory":"Insurance Agent",
            "type":"Services"
        }
    ],
    "sg:phone":"+1 905 623 7688",
    "sg:postcode":"L1C 1R4",
    "sg:province":"ON",
    "wof:name":"Donald R Hutton Insurance Ltd",
    "wof:placetype":"venue"
},
  "geometry": {"coordinates":[-78.6908493042,43.9128341675],"type":"Point"}
}