{
  "type": "Feature",
  "properties": {
    "addr:full":"Vernon BC V1T 9H4",
    "addr:postcode":"v1t 9h4",
    "iso:country":"CA",
    "sg:city":"Vernon",
    "sg:classifiers":[
        {
            "category":"Government",
            "subcategory":"Office",
            "type":"Public Place"
        }
    ],
    "sg:phone":"+1 250 558 1242",
    "sg:postcode":"V1T 9H4",
    "sg:province":"BC",
    "wof:name":"Laboratory Downtown",
    "wof:placetype":"venue"
},
  "geometry": {"coordinates":[-119.279205,50.26466],"type":"Point"}
}