{
  "type": "Feature",
  "properties": {
    "addr:full":"700 University Ave Toronto ON M5G 1Z5",
    "addr:housenumber":"700",
    "addr:postcode":"m5g 1z5",
    "addr:street":"University Ave",
    "iso:country":"CA",
    "sg:address":"700 University Ave",
    "sg:city":"Toronto",
    "sg:classifiers":[
        {
            "category":"Health Services",
            "subcategory":"Chiropractor",
            "type":"Services"
        }
    ],
    "sg:phone":"+1 416 596 1771",
    "sg:postcode":"M5G 1Z5",
    "sg:province":"ON",
    "wof:name":"University Chiropractic Ctr",
    "wof:placetype":"venue"
},
  "geometry": {"coordinates":[-79.390366,43.658752],"type":"Point"}
}