{
  "type": "Feature",
  "properties": {
    "iso:country":"CA",
    "sg:address":"10611 82 St NW",
    "sg:city":"Edmonton",
    "sg:classifiers":[
        {
            "category":"Personal",
            "type":"Services"
        }
    ],
    "sg:phone":"+1 780 440 0482",
    "sg:postcode":"T6A 3N2",
    "sg:province":"AB",
    "sg:tags":[
        "therapist",
        "massage"
    ],
    "wof:name":"Pain Relief Ctr",
    "wof:placetype":"venue"
},
  "geometry": {"coordinates":[-113.453896,53.549599],"type":"Point"}
}