{
  "type": "Feature",
  "properties": {
    "addr:full":"447 Ch Main Rd Hudson QC J0P 1H0",
    "addr:housenumber":"447",
    "addr:postcode":"j0p 1h0",
    "addr:street":"Ch Main Rd",
    "iso:country":"CA",
    "sg:address":"447 Ch Main Rd",
    "sg:city":"Hudson",
    "sg:classifiers":[
        {
            "category":"Shopping",
            "subcategory":"Catalog Store",
            "type":"Retail Goods"
        }
    ],
    "sg:phone":"+1 450 458 7004",
    "sg:postcode":"J0P 1H0",
    "sg:province":"QC",
    "sg:tags":[
        "mail",
        "order",
        "internet"
    ],
    "wof:name":"Sears Canada Inc",
    "wof:placetype":"venue"
},
  "geometry": {"coordinates":[-74.140648,45.458389],"type":"Point"}
}