{
  "type": "Feature",
  "properties": {
    "addr:full":"Trans Canada Hwy Doyles NL A0N 1J0",
    "addr:postcode":"a0n 1j0",
    "addr:street":"Trans Canada Hwy",
    "iso:country":"CA",
    "sg:address":"Trans Canada Hwy",
    "sg:city":"Doyles",
    "sg:classifiers":[
        {
            "category":"Shopping",
            "subcategory":"Pharmacy",
            "type":"Retail Goods"
        }
    ],
    "sg:phone":"+1 709 955 2398",
    "sg:postcode":"A0N 1J0",
    "sg:province":"NL",
    "wof:name":"Valley Pharmacy",
    "wof:placetype":"venue"
},
  "geometry": {"coordinates":[-59.195911,47.824608],"type":"Point"}
}