{
  "type": "Feature",
  "properties": {
    "addr:full":"1 Fairview St Lewisporte NL A0G 3A0",
    "addr:housenumber":"1",
    "addr:postcode":"a0g 3a0",
    "addr:street":"Fairview St",
    "iso:country":"CA",
    "sg:address":"1 Fairview St",
    "sg:city":"Lewisporte",
    "sg:classifiers":[
        {
            "category":"Shopping",
            "subcategory":"Catalog Store",
            "type":"Retail Goods"
        }
    ],
    "sg:phone":"+1 709 535 2494",
    "sg:postcode":"A0G 3A0",
    "sg:province":"NL",
    "sg:tags":[
        "mail",
        "order",
        "internet"
    ],
    "wof:name":"Sears Canada Inc",
    "wof:placetype":"venue"
},
  "geometry": {"coordinates":[-55.059937,49.241798],"type":"Point"}
}