{
  "type": "Feature",
  "properties": {
    "addr:full":"516 Centre St Espanola ON P5E 1H1",
    "addr:housenumber":"516",
    "addr:postcode":"p5e 1h1",
    "addr:street":"Centre St",
    "iso:country":"CA",
    "sg:address":"516 Centre St",
    "sg:city":"Espanola",
    "sg:classifiers":[
        {
            "category":"Shopping",
            "subcategory":"Crafts & Fabrics",
            "type":"Retail Goods"
        }
    ],
    "sg:phone":"+1 705 869 4448",
    "sg:postcode":"P5E 1H1",
    "sg:province":"ON",
    "sg:tags":[
        "shop"
    ],
    "wof:name":"Mini Mart",
    "wof:placetype":"venue"
},
  "geometry": {"coordinates":[-81.76403000000001,46.254028],"type":"Point"}
}