{
  "type": "Feature",
  "properties": {
    "iso:country":"CA",
    "sg:address":"377 1st St E",
    "sg:city":"Stonewall",
    "sg:classifiers":[
        {
            "category":"Retail",
            "subcategory":"Auto Repair",
            "type":"Services"
        }
    ],
    "sg:phone":"+1 204 467 5595",
    "sg:postcode":"R0C 2Z0",
    "sg:province":"MB",
    "sg:tags":[
        "brake",
        "tire"
    ],
    "wof:name":"Stonewall Tire Ltd",
    "wof:placetype":"venue"
},
  "geometry": {"coordinates":[-97.325302124,50.1339912415],"type":"Point"}
}