{
  "type": "Feature",
  "properties": {
    "iso:country":"CA",
    "sg:address":"4517 Av DE L'Esplanade",
    "sg:city":"Montreal",
    "sg:classifiers":[
        {
            "category":"Professional",
            "subcategory":"Research",
            "type":"Services"
        }
    ],
    "sg:phone":"+1 514 842 3344",
    "sg:postcode":"H2T 2Y6",
    "sg:province":"QC",
    "sg:tags":[
        "assistance",
        "program",
        "technology"
    ],
    "wof:name":"Valoritech Inc",
    "wof:placetype":"venue"
},
  "geometry": {"coordinates":[-73.554359,45.51231],"type":"Point"}
}