{
  "type": "Feature",
  "properties": {
    "addr:full":"206 John St London ON N6A 1P1",
    "addr:housenumber":"206",
    "addr:postcode":"n6a 1p1",
    "addr:street":"John St",
    "iso:country":"CA",
    "sg:address":"206 John St",
    "sg:city":"London",
    "sg:classifiers":[
        {
            "category":"Personal",
            "subcategory":"Beauty Salon",
            "type":"Services"
        }
    ],
    "sg:phone":"+1 519 433 3426",
    "sg:postcode":"N6A 1P1",
    "sg:province":"ON",
    "wof:name":"Silvana's",
    "wof:placetype":"venue"
},
  "geometry": {"coordinates":[-81.252769,42.991554],"type":"Point"}
}