{
  "type": "Feature",
  "properties": {
    "addr:full":"2590 Rue Moliere Brossard QC J4Y 1L5",
    "addr:housenumber":"2590",
    "addr:postcode":"j4y 1l5",
    "addr:street":"Rue Moliere",
    "iso:country":"CA",
    "sg:address":"2590 Rue Moliere",
    "sg:city":"Brossard",
    "sg:classifiers":[
        {
            "category":"Social Services",
            "subcategory":"Child Care",
            "type":"Services"
        }
    ],
    "sg:phone":"+1 450 656 1000",
    "sg:postcode":"J4Y 1L5",
    "sg:province":"QC",
    "wof:name":"Garderie Aux Petites Biches",
    "wof:placetype":"venue"
},
  "geometry": {"coordinates":[-73.46016693120001,45.460975647],"type":"Point"}
}