{
  "type": "Feature",
  "properties": {
    "addr:full":"1576 Mountain Rd Moncton NB E1G 1A4",
    "addr:housenumber":"1576",
    "addr:postcode":"e1g 1a4",
    "addr:street":"Mountain Rd",
    "iso:country":"CA",
    "sg:address":"1576 Mountain Rd",
    "sg:city":"Moncton",
    "sg:classifiers":[
        {
            "category":"Retail",
            "subcategory":"Repair Shop",
            "type":"Services"
        }
    ],
    "sg:phone":"+1 506 858 8760",
    "sg:postcode":"E1G 1A4",
    "sg:province":"NB",
    "sg:tags":[
        "leather",
        "cleaners",
        "cleaning"
    ],
    "wof:name":"Darlington Fur & Leather Strge",
    "wof:placetype":"venue"
},
  "geometry": {"coordinates":[-64.83935546879999,46.1158638],"type":"Point"}
}