{
  "type": "Feature",
  "properties": {
    "addr:full":"755 Rue Notre-Dame Saint-Remi QC J0L 2L0",
    "addr:housenumber":"755",
    "addr:postcode":"j0l 2l0",
    "addr:street":"Rue Notre-Dame Saint-Remi",
    "iso:country":"CA",
    "sg:address":"755 Rue Notre-Dame",
    "sg:city":"Saint-Remi",
    "sg:classifiers":[
        {
            "category":"Wholesale",
            "subcategory":"Durable Goods & Equipment",
            "type":"Manufacturing & Wholesale Goods"
        }
    ],
    "sg:phone":"+1 450 454 9996",
    "sg:postcode":"J0L 2L0",
    "sg:province":"QC",
    "sg:tags":[
        "importer"
    ],
    "wof:name":"Distribution Suazo Enr",
    "wof:placetype":"venue"
},
  "geometry": {"coordinates":[-73.61650848390001,45.2614173889],"type":"Point"}
}