{
  "type": "Feature",
  "properties": {
    "addr:full":"4916 49th St Yellowknife NT X1A 2L9",
    "addr:housenumber":"4916",
    "addr:postcode":"x1a 2l9",
    "addr:street":"49Th St",
    "iso:country":"CA",
    "sg:address":"4916 49th St",
    "sg:city":"Yellowknife",
    "sg:classifiers":[
        {
            "category":"Government",
            "subcategory":"Office",
            "type":"Public Place"
        }
    ],
    "sg:phone":"+1 867 873 7469",
    "sg:postcode":"X1A 2L9",
    "sg:province":"NT",
    "wof:name":"N T Safety & Public Svc",
    "wof:placetype":"venue"
},
  "geometry": {"coordinates":[-114.373146057,62.4555130005],"type":"Point"}
}