{
  "type": "Feature",
  "properties": {
    "addr:full":"153 Day Dr Orillia ON L3V 6H5",
    "addr:housenumber":"153",
    "addr:postcode":"l3v 6h5",
    "addr:street":"Day Dr",
    "iso:country":"CA",
    "sg:address":"153 Day Dr",
    "sg:city":"Orillia",
    "sg:classifiers":[
        {
            "category":"Travel",
            "subcategory":"Hotels & Motels",
            "type":"Entertainment"
        }
    ],
    "sg:phone":"+1 705 833 2666",
    "sg:postcode":"L3V 6H5",
    "sg:province":"ON",
    "sg:tags":[
        "tourist",
        "accommodation"
    ],
    "wof:name":"Meadows End Trailer Park",
    "wof:placetype":"venue"
},
  "geometry": {"coordinates":[-79.41822814939999,44.606590271],"type":"Point"}
}