{
  "type": "Feature",
  "properties": {
    "iso:country":"CA",
    "sg:address":"823 Highway 8",
    "sg:city":"Stoney Creek",
    "sg:classifiers":[
        {
            "category":"Autos & Motor Vehicles",
            "subcategory":"Fuel & Gas Station",
            "type":"Retail Goods"
        }
    ],
    "sg:phone":"+1 905 643 4338",
    "sg:postcode":"L8E 5J3",
    "sg:province":"ON",
    "sg:tags":[
        "oil"
    ],
    "wof:name":"Pioneer Petroleums",
    "wof:placetype":"venue"
},
  "geometry": {"coordinates":[-79.6898803711,43.2120666504],"type":"Point"}
}