{
  "type": "Feature",
  "properties": {
    "addr:full":"PO Box 412 Watson Lake YT Y0A 1C0",
    "addr:housenumber":"po;412",
    "addr:postcode":"y0a 1c0",
    "addr:street":"Box",
    "iso:country":"CA",
    "sg:address":"PO Box 412",
    "sg:city":"Watson Lake",
    "sg:classifiers":[
        {
            "category":"Retail",
            "subcategory":"Auto Repair",
            "type":"Services"
        }
    ],
    "sg:phone":"+1 867 536 7506",
    "sg:postcode":"Y0A 1C0",
    "sg:province":"YT",
    "sg:tags":[
        "truck"
    ],
    "wof:name":"Ron Painchaud Svc",
    "wof:placetype":"venue"
},
  "geometry": {"coordinates":[-128.714157105,60.0629348755],"type":"Point"}
}