{
  "type": "Feature",
  "properties": {
    "addr:full":"399 Victoria Ave Belleville ON K8N 2E7",
    "addr:housenumber":"399",
    "addr:postcode":"k8n 2e7",
    "addr:street":"Victoria Ave",
    "iso:country":"CA",
    "sg:address":"399 Victoria Ave",
    "sg:city":"Belleville",
    "sg:classifiers":[
        {
            "category":"Organizations",
            "subcategory":"Religious Organization",
            "type":"Services"
        }
    ],
    "sg:phone":"+1 613 968 9950",
    "sg:postcode":"K8N 2E7",
    "sg:province":"ON",
    "sg:tags":[
        "church"
    ],
    "wof:name":"St Joseph's Church",
    "wof:placetype":"venue"
},
  "geometry": {"coordinates":[-77.358291626,44.1734046936],"type":"Point"}
}