{
  "type": "Feature",
  "properties": {
    "addr:full":"17 Worthington Cres Toronto ON M6S 3P5",
    "addr:housenumber":"17",
    "addr:postcode":"m6s 3p5",
    "addr:street":"Worthington Cres",
    "iso:country":"CA",
    "sg:address":"17 Worthington Cres",
    "sg:city":"Toronto",
    "sg:classifiers":[
        {
            "category":"Professional",
            "subcategory":"Computer Services",
            "type":"Services"
        }
    ],
    "sg:phone":"+1 416 767 3741",
    "sg:postcode":"M6S 3P5",
    "sg:province":"ON",
    "sg:tags":[
        "consultant"
    ],
    "wof:name":"Gef Consulting",
    "wof:placetype":"venue"
},
  "geometry": {"coordinates":[-79.478195,43.641914],"type":"Point"}
}