{
  "type": "Feature",
  "properties": {
    "addr:full":"London ON N6A 3C9",
    "addr:postcode":"n6a 3c9",
    "iso:country":"CA",
    "sg:city":"London",
    "sg:classifiers":[
        {
            "category":"Shopping",
            "type":"Retail Goods"
        }
    ],
    "sg:phone":"+1 519 434 7112",
    "sg:postcode":"N6A 3C9",
    "sg:province":"ON",
    "sg:tags":[
        "art",
        "gallery",
        "dealer"
    ],
    "wof:name":"Artisan's Alley",
    "wof:placetype":"venue"
},
  "geometry": {"coordinates":[-81.24987,42.984467],"type":"Point"}
}