{
  "type": "Feature",
  "properties": {
    "addr:full":"1158 Nepal Pl West Vancouver BC V7T 2H1",
    "addr:housenumber":"1158",
    "addr:postcode":"v7t 2h1",
    "addr:street":"Nepal Pl",
    "iso:country":"CA",
    "sg:address":"1158 Nepal Pl",
    "sg:city":"West Vancouver",
    "sg:classifiers":[
        {
            "category":"Professional",
            "subcategory":"Computer Services",
            "type":"Services"
        }
    ],
    "sg:phone":"+1 604 913 2002",
    "sg:postcode":"V7T 2H1",
    "sg:province":"BC",
    "wof:name":"Charter Telecom",
    "wof:placetype":"venue"
},
  "geometry": {"coordinates":[-123.14877300000001,49.339108],"type":"Point"}
}