{
  "type": "Feature",
  "properties": {
    "addr:full":"60 Lancing Dr Hamilton ON L8W 3A1",
    "addr:housenumber":"60",
    "addr:postcode":"l8w 3a1",
    "addr:street":"Lancing Dr",
    "iso:country":"CA",
    "sg:address":"60 Lancing Dr",
    "sg:city":"Hamilton",
    "sg:classifiers":[
        {
            "category":"Building & Trades",
            "subcategory":"Plumbing",
            "type":"Services"
        }
    ],
    "sg:phone":"+1 905 318 1103",
    "sg:postcode":"L8W 3A1",
    "sg:province":"ON",
    "sg:tags":[
        "conditioning",
        "air",
        "system",
        "contractor"
    ],
    "wof:name":"Aspen Air Systems",
    "wof:placetype":"venue"
},
  "geometry": {"coordinates":[-79.840569,43.192852],"type":"Point"}
}