{
  "type": "Feature",
  "properties": {
    "addr:full":"1355 Main St W Hamilton ON L8S 4M7",
    "addr:housenumber":"1355",
    "addr:postcode":"l8s 4m7",
    "addr:street":"Main St W",
    "iso:country":"CA",
    "sg:address":"1355 Main St W",
    "sg:city":"Hamilton",
    "sg:classifiers":[
        {
            "category":"Education",
            "subcategory":"School",
            "type":"Public Place"
        }
    ],
    "sg:phone":"+1 905 522 8071",
    "sg:postcode":"L8S 4M7",
    "sg:province":"ON",
    "wof:name":"Canadian Martyrs School",
    "wof:placetype":"venue"
},
  "geometry": {"coordinates":[-79.921783,43.257534],"type":"Point"}
}