{
  "type": "Feature",
  "properties": {
    "addr:full":"11313 105 St Grande Prairie AB T8V 7P1",
    "addr:housenumber":"11313",
    "addr:postcode":"t8v 7p1",
    "addr:street":"105 St",
    "iso:country":"CA",
    "sg:address":"11313 105 St",
    "sg:city":"Grande Prairie",
    "sg:classifiers":[
        {
            "category":"Government",
            "subcategory":"Office",
            "type":"Public Place"
        }
    ],
    "sg:phone":"+1 780 538 0455",
    "sg:postcode":"T8V 7P1",
    "sg:province":"AB",
    "sg:tags":[
        "village"
    ],
    "wof:name":"Leisure Centre",
    "wof:placetype":"venue"
},
  "geometry": {"coordinates":[-118.810776,55.181324],"type":"Point"}
}