{
  "type": "Feature",
  "properties": {
    "addr:full":"3508 2 Ave N Lethbridge AB T1H 0C6",
    "addr:housenumber":"3508",
    "addr:postcode":"t1h 0c6",
    "addr:street":"2 Ave N",
    "iso:country":"CA",
    "sg:address":"3508 2 Ave N",
    "sg:city":"Lethbridge",
    "sg:classifiers":[
        {
            "category":"Manufacturing",
            "subcategory":"Metals",
            "type":"Manufacturing & Wholesale Goods"
        }
    ],
    "sg:phone":"+1 403 328 9342",
    "sg:postcode":"T1H 0C6",
    "sg:province":"AB",
    "sg:tags":[
        "steel"
    ],
    "wof:name":"Value Steel & Pipe",
    "wof:placetype":"venue"
},
  "geometry": {"coordinates":[-112.789100647,49.7007484436],"type":"Point"}
}