{
  "type": "Feature",
  "properties": {
    "addr:full":"Richmond BC V6X 2A7",
    "addr:postcode":"v6x 2a7",
    "iso:country":"CA",
    "sg:city":"Richmond",
    "sg:classifiers":[
        {
            "category":"Government",
            "subcategory":"Office",
            "type":"Public Place"
        }
    ],
    "sg:phone":"+1 604 660 9260",
    "sg:postcode":"V6X 2A7",
    "sg:province":"BC",
    "wof:name":"B C Family Svc Office",
    "wof:placetype":"venue"
},
  "geometry": {"coordinates":[-123.141991,49.172874],"type":"Point"}
}