{
  "type": "Feature",
  "properties": {
    "addr:full":"11815 Boul Lacroix Saint-Georges QC G5Y 1L5",
    "addr:housenumber":"11815",
    "addr:postcode":"g5y 1l5",
    "addr:street":"Boul Lacroix",
    "iso:country":"CA",
    "sg:address":"11815 Boul Lacroix",
    "sg:city":"Saint-Georges",
    "sg:classifiers":[
        {
            "category":"Shopping",
            "subcategory":"Bicycles & Sporting Goods",
            "type":"Retail Goods"
        }
    ],
    "sg:phone":"+1 418 228 3991",
    "sg:postcode":"G5Y 1L5",
    "sg:province":"QC",
    "wof:name":"M2 Sports",
    "wof:placetype":"venue"
},
  "geometry": {"coordinates":[-70.670044,46.12281],"type":"Point"}
}