{
  "type": "Feature",
  "properties": {
    "addr:full":"1740 Bantree St Ottawa ON K1B 3W4",
    "addr:housenumber":"1740",
    "addr:postcode":"k1b 3w4",
    "addr:street":"Bantree St",
    "iso:country":"CA",
    "sg:address":"1740 Bantree St",
    "sg:city":"Ottawa",
    "sg:classifiers":[
        {
            "category":"Building & Trades",
            "subcategory":"Construction",
            "type":"Services"
        }
    ],
    "sg:phone":"+1 613 741 0911",
    "sg:postcode":"K1B 3W4",
    "sg:province":"ON",
    "sg:tags":[
        "builder",
        "material",
        "stair"
    ],
    "wof:name":"Ottawa Classic Stairs Inc",
    "wof:placetype":"venue"
},
  "geometry": {"coordinates":[-75.618469,45.407787],"type":"Point"}
}