{
  "type": "Feature",
  "properties": {
    "addr:full":"4001 Ch Saint-Louis Cap-Rouge QC G1Y 1V7",
    "addr:postcode":"4001;g1y 1v7",
    "addr:street":"Ch Saint-Louis",
    "iso:country":"CA",
    "sg:address":"4001 Ch Saint-Louis",
    "sg:city":"Cap-Rouge",
    "sg:classifiers":[
        {
            "category":"Manufacturing",
            "subcategory":"Textiles",
            "type":"Manufacturing & Wholesale Goods"
        }
    ],
    "sg:phone":"+1 418 658 0265",
    "sg:postcode":"G1Y 1V7",
    "sg:province":"QC",
    "sg:tags":[
        "equipment",
        "motel",
        "hotel",
        "supply"
    ],
    "wof:name":"Decor St Inc",
    "wof:placetype":"venue"
},
  "geometry": {"coordinates":[-71.33158874510001,46.7494239807],"type":"Point"}
}