{
  "type": "Feature",
  "properties": {
    "addr:full":"690 St Clair Ave W Toronto ON M6C 1B1",
    "addr:housenumber":"690",
    "addr:postcode":"m6c 1b1",
    "addr:street":"St Clair Ave W",
    "iso:country":"CA",
    "sg:address":"690 St Clair Ave W",
    "sg:city":"Toronto",
    "sg:classifiers":[
        {
            "category":"Food & Beverages",
            "subcategory":"Bakery",
            "type":"Retail Goods"
        }
    ],
    "sg:phone":"+1 416 654 0606",
    "sg:postcode":"M6C 1B1",
    "sg:province":"ON",
    "sg:tags":[
        "baker"
    ],
    "wof:name":"Bakery Hollywood",
    "wof:placetype":"venue"
},
  "geometry": {"coordinates":[-79.4259185791,43.6817626953],"type":"Point"}
}