{
  "type": "Feature",
  "properties": {
    "addr:full":"625 Boul Rene-Levesque O # Rc50 Montreal QC H3B 1R2",
    "addr:housenumber":"625",
    "addr:postcode":"h3b 1r2",
    "addr:street":"Boul Rene-Levesque O # Rc50",
    "iso:country":"CA",
    "sg:address":"625 Boul Rene-Levesque O # Rc50",
    "sg:city":"Montreal",
    "sg:classifiers":[
        {
            "category":"Restaurant",
            "type":"Food & Drink"
        }
    ],
    "sg:phone":"+1 514 390 8888",
    "sg:postcode":"H3B 1R2",
    "sg:province":"QC",
    "sg:tags":[
        "shop",
        "coffee"
    ],
    "wof:name":"Cafe Vienne",
    "wof:placetype":"venue"
},
  "geometry": {"coordinates":[-73.5671081543,45.5025444031],"type":"Point"}
}