{
  "type": "Feature",
  "properties": {
    "iso:country":"CA",
    "sg:city":"Newmarket",
    "sg:classifiers":[
        {
            "category":"Professional",
            "subcategory":"Accounting & Tax Preparation",
            "type":"Services"
        }
    ],
    "sg:phone":"+1 905 830 1993",
    "sg:postcode":"L3Y 8J4",
    "sg:province":"ON",
    "sg:tags":[
        "accountant"
    ],
    "wof:name":"Metcalfe, C Anna E CA",
    "wof:placetype":"venue"
},
  "geometry": {"coordinates":[-79.475929,44.036518],"type":"Point"}
}