{
  "type": "Feature",
  "properties": {
    "addr:full":"Calgary AB T2E 7W7",
    "addr:postcode":"t2e 7w7",
    "iso:country":"CA",
    "sg:city":"Calgary",
    "sg:classifiers":[
        {
            "category":"Health Services",
            "subcategory":"Doctor",
            "type":"Services"
        }
    ],
    "sg:phone":"+1 403 237 6404",
    "sg:postcode":"T2E 7W7",
    "sg:province":"AB",
    "sg:tags":[
        "physician",
        "surgeon"
    ],
    "wof:name":"Kao, Y MD",
    "wof:placetype":"venue"
},
  "geometry": {"coordinates":[-114.039245605,51.0533447266],"type":"Point"}
}