{
  "type": "Feature",
  "properties": {
    "addr:full":"105 2nd Ave W Wilkie SK S0K 4W0",
    "addr:housenumber":"105",
    "addr:postcode":"s0k 4w0",
    "addr:street":"2Nd Ave W Wilkie",
    "iso:country":"CA",
    "sg:address":"105 2nd Ave W",
    "sg:city":"Wilkie",
    "sg:classifiers":[
        {
            "category":"Shopping",
            "subcategory":"Florist",
            "type":"Retail Goods"
        }
    ],
    "sg:phone":"+1 306 843 2119",
    "sg:postcode":"S0K 4W0",
    "sg:province":"SK",
    "wof:name":"Fell's Craft & Garden Ctr",
    "wof:placetype":"venue"
},
  "geometry": {"coordinates":[-108.702538,52.411331],"type":"Point"}
}