{
  "type": "Feature",
  "properties": {
    "addr:full":"2042 70 Ave NW Edmonton AB T6P 1N6",
    "addr:housenumber":"2042",
    "addr:postcode":"t6p 1n6",
    "addr:street":"70 Ave Nw",
    "iso:country":"CA",
    "sg:address":"2042 70 Ave NW",
    "sg:city":"Edmonton",
    "sg:classifiers":[
        {
            "category":"Manufacturing",
            "subcategory":"Metals",
            "type":"Manufacturing & Wholesale Goods"
        }
    ],
    "sg:phone":"+1 780 440 4756",
    "sg:postcode":"T6P 1N6",
    "sg:province":"AB",
    "sg:tags":[
        "steel"
    ],
    "wof:name":"Kucher Steels 1992 Inc",
    "wof:placetype":"venue"
},
  "geometry": {"coordinates":[-113.375076294,53.5071144104],"type":"Point"}
}