{
  "type": "Feature",
  "properties": {
    "addr:full":"2714 Meighen Rd Windsor ON N8W 4C8",
    "addr:housenumber":"2714",
    "addr:postcode":"n8w 4c8",
    "addr:street":"Meighen Rd",
    "iso:country":"CA",
    "sg:address":"2714 Meighen Rd",
    "sg:city":"Windsor",
    "sg:classifiers":[
        {
            "category":"Building & Trades",
            "subcategory":"Plumbing",
            "type":"Services"
        }
    ],
    "sg:phone":"+1 519 945 5878",
    "sg:postcode":"N8W 4C8",
    "sg:province":"ON",
    "sg:tags":[
        "air",
        "conditioning",
        "contractor",
        "system",
        "heating"
    ],
    "wof:name":"S Candido CO Ltd",
    "wof:placetype":"venue"
},
  "geometry": {"coordinates":[-82.977722168,42.2938957214],"type":"Point"}
}