{
  "type": "Feature",
  "properties": {
    "addr:full":"563 Queen St N Harrow ON N0R 1G0",
    "addr:housenumber":"563",
    "addr:postcode":"n0r 1g0",
    "addr:street":"Queen St N",
    "iso:country":"CA",
    "sg:address":"563 Queen St N",
    "sg:city":"Harrow",
    "sg:classifiers":[
        {
            "category":"Manufacturing",
            "subcategory":"Printing",
            "type":"Manufacturing & Wholesale Goods"
        }
    ],
    "sg:phone":"+1 519 738 2542",
    "sg:postcode":"N0R 1G0",
    "sg:province":"ON",
    "sg:tags":[
        "newspaper"
    ],
    "wof:name":"Harrow News Publishing Inc",
    "wof:placetype":"venue"
},
  "geometry": {"coordinates":[-82.91780900000001,42.043636],"type":"Point"}
}