{
  "type": "Feature",
  "properties": {
    "iso:country":"CA",
    "sg:address":"96 Yellow Brick Rd",
    "sg:city":"Brampton",
    "sg:classifiers":[
        {
            "category":"Manufacturing",
            "subcategory":"Printing",
            "type":"Manufacturing & Wholesale Goods"
        }
    ],
    "sg:phone":"+1 905 459 7788",
    "sg:postcode":"L6V 4L1",
    "sg:province":"ON",
    "sg:tags":[
        "printer"
    ],
    "wof:name":"Mbl Enterprises",
    "wof:placetype":"venue"
},
  "geometry": {"coordinates":[-79.779624939,43.70677948],"type":"Point"}
}