{
  "type": "Feature",
  "properties": {
    "addr:full":"Seaforth ON N0K 1W0",
    "addr:postcode":"n0k 1w0",
    "iso:country":"CA",
    "sg:city":"Seaforth",
    "sg:classifiers":[
        {
            "category":"Government",
            "subcategory":"Office",
            "type":"Public Place"
        }
    ],
    "sg:phone":"+1 519 527 1710",
    "sg:postcode":"N0K 1W0",
    "sg:province":"ON",
    "sg:tags":[
        "village"
    ],
    "wof:name":"Seaforth Building Dept",
    "wof:placetype":"venue"
},
  "geometry": {"coordinates":[-81.3937072754,43.5530433655],"type":"Point"}
}