{
  "type": "Feature",
  "properties": {
    "iso:country":"CA",
    "sg:city":"Richmond",
    "sg:classifiers":[
        {
            "category":"Home & Garden",
            "subcategory":"Furniture",
            "type":"Retail Goods"
        }
    ],
    "sg:phone":"+1 604 278 7656",
    "sg:postcode":"V6X 2A6",
    "sg:province":"BC",
    "wof:name":"Maple Rosewood Furniture",
    "wof:placetype":"venue"
},
  "geometry": {"coordinates":[-123.137489319,49.177192688],"type":"Point"}
}