{
  "type": "Feature",
  "properties": {
    "addr:full":"668 Dundas St W Toronto ON M5T 1H9",
    "addr:housenumber":"668",
    "addr:postcode":"m5t 1h9",
    "addr:street":"Dundas St W",
    "iso:country":"CA",
    "sg:address":"668 Dundas St W",
    "sg:city":"Toronto",
    "sg:classifiers":[
        {
            "category":"Restaurant",
            "type":"Food & Drink"
        }
    ],
    "sg:phone":"+1 416 703 0668",
    "sg:postcode":"M5T 1H9",
    "sg:province":"ON",
    "wof:name":"Cafe 668",
    "wof:placetype":"venue"
},
  "geometry": {"coordinates":[-79.4035644531,43.651889801],"type":"Point"}
}