{
  "type": "Feature",
  "properties": {
    "addr:full":"323 Kerr St # 204 Oakville ON L6K 3B6",
    "addr:housenumber":"323",
    "addr:postcode":"l6k 3b6",
    "addr:street":"Kerr St # 204",
    "iso:country":"CA",
    "sg:address":"323 Kerr St # 204",
    "sg:city":"Oakville",
    "sg:classifiers":[
        {
            "category":"Health Services",
            "subcategory":"Doctor",
            "type":"Services"
        }
    ],
    "sg:phone":"+1 905 842 0287",
    "sg:postcode":"L6K 3B6",
    "sg:province":"ON",
    "sg:tags":[
        "clinic"
    ],
    "wof:name":"Oakville Massage & Wellness",
    "wof:placetype":"venue"
},
  "geometry": {"coordinates":[-79.6811752319,43.4436149597],"type":"Point"}
}