{
  "type": "Feature",
  "properties": {
    "iso:country":"CA",
    "sg:address":"189 Water St",
    "sg:city":"Summerside",
    "sg:classifiers":[
        {
            "category":"Professional",
            "subcategory":"Accounting & Tax Preparation",
            "type":"Services"
        }
    ],
    "sg:phone":"+1 902 436 2171",
    "sg:postcode":"C1N 1B2",
    "sg:province":"PE",
    "sg:tags":[
        "bookkeeping",
        "general"
    ],
    "wof:name":"Schurman Sudsbury & Assoc Ltd",
    "wof:placetype":"venue"
},
  "geometry": {"coordinates":[-63.7878417969,46.3911247253],"type":"Point"}
}