{
  "type": "Feature",
  "properties": {
    "addr:full":"Brossard QC J4Z 2B3",
    "addr:postcode":"j4z 2b3",
    "iso:country":"CA",
    "sg:city":"Brossard",
    "sg:classifiers":[
        {
            "category":"Building & Trades",
            "subcategory":"Construction",
            "type":"Services"
        }
    ],
    "sg:phone":"+1 450 676 7479",
    "sg:postcode":"J4Z 2B3",
    "sg:province":"QC",
    "sg:tags":[
        "general",
        "contractor"
    ],
    "wof:name":"Entreprises Peter Varfalvy Inc",
    "wof:placetype":"venue"
},
  "geometry": {"coordinates":[-73.453751,45.46653],"type":"Point"}
}