{
  "type": "Feature",
  "properties": {
    "addr:full":"4408 10th Ave W Vancouver BC V6R 2H9",
    "addr:housenumber":"4408",
    "addr:postcode":"v6r 2h9",
    "addr:street":"10Th Ave W",
    "iso:country":"CA",
    "sg:address":"4408 10th Ave W",
    "sg:city":"Vancouver",
    "sg:classifiers":[
        {
            "category":"Shopping",
            "subcategory":"Clothing, Apparel, & Fashions",
            "type":"Retail Goods"
        }
    ],
    "sg:phone":"+1 604 222 3321",
    "sg:postcode":"V6R 2H9",
    "sg:province":"BC",
    "sg:tags":[
        "furnishing"
    ],
    "wof:name":"X Factor",
    "wof:placetype":"venue"
},
  "geometry": {"coordinates":[-123.20661926299999,49.2636566162],"type":"Point"}
}