{
  "type": "Feature",
  "properties": {
    "iso:country":"CA",
    "sg:address":"203 Jackpine Way",
    "sg:city":"Fort Mcmurray",
    "sg:classifiers":[
        {
            "category":"Building & Trades",
            "subcategory":"Cleaning & Sanitation",
            "type":"Services"
        }
    ],
    "sg:phone":"+1 780 791 1155",
    "sg:postcode":"T9K 1A6",
    "sg:province":"AB",
    "sg:tags":[
        "janitor"
    ],
    "wof:name":"Ed's Janitorial Svc",
    "wof:placetype":"venue"
},
  "geometry": {"coordinates":[-111.434417725,56.733707428],"type":"Point"}
}