{
  "type": "Feature",
  "properties": {
    "iso:country":"CA",
    "sg:address":"855 Av Holland",
    "sg:city":"Quebec",
    "sg:classifiers":[
        {
            "category":"Social Services",
            "type":"Services"
        }
    ],
    "sg:phone":"+1 418 688 6039",
    "sg:postcode":"G1S 3S5",
    "sg:province":"QC",
    "sg:tags":[
        "pregnancy",
        "counseling",
        "information"
    ],
    "wof:name":"Collectif D'Accompagnement",
    "wof:placetype":"venue"
},
  "geometry": {"coordinates":[-71.251816,46.794201],"type":"Point"}
}