{
  "type": "Feature",
  "properties": {
    "iso:country":"CA",
    "sg:address":"150 Queen St",
    "sg:city":"North Sydney",
    "sg:classifiers":[
        {
            "category":"Building & Trades",
            "subcategory":"Electrical",
            "type":"Services"
        }
    ],
    "sg:phone":"+1 902 794 1171",
    "sg:postcode":"B2A 1B3",
    "sg:province":"NS",
    "sg:tags":[
        "electric",
        "contractor"
    ],
    "wof:name":"Galpin Electric Ltd",
    "wof:placetype":"venue"
},
  "geometry": {"coordinates":[-60.253624,46.205196],"type":"Point"}
}