{
  "type": "Feature",
  "properties": {
    "addr:full":"4209 Rue DE Bullion Montreal QC H2W 2E8",
    "addr:housenumber":"4209",
    "addr:postcode":"h2w 2e8",
    "addr:street":"Rue De Bullion",
    "iso:country":"CA",
    "sg:address":"4209 Rue DE Bullion",
    "sg:city":"Montreal",
    "sg:classifiers":[
        {
            "category":"Retail",
            "subcategory":"Auto Repair",
            "type":"Services"
        }
    ],
    "sg:phone":"+1 514 843 5300",
    "sg:postcode":"H2W 2E8",
    "sg:province":"QC",
    "sg:tags":[
        "repairing",
        "automobile"
    ],
    "wof:name":"Albert Service Station",
    "wof:placetype":"venue"
},
  "geometry": {"coordinates":[-73.5804672241,45.5195503235],"type":"Point"}
}