{
  "type": "Feature",
  "properties": {
    "iso:country":"CA",
    "sg:address":"55 Queen St S",
    "sg:city":"Tottenham",
    "sg:classifiers":[
        {
            "category":"Shopping",
            "subcategory":"Discount & Variety Stores",
            "type":"Retail Goods"
        }
    ],
    "sg:phone":"+1 905 936 5372",
    "sg:postcode":"L0G 1W0",
    "sg:province":"ON",
    "wof:name":"Smokes & Variety",
    "wof:placetype":"venue"
},
  "geometry": {"coordinates":[-79.804863,44.020035],"type":"Point"}
}