{
  "type": "Feature",
  "properties": {
    "addr:full":"265 Wilson St E Ancaster ON L9G 2B8",
    "addr:housenumber":"265",
    "addr:postcode":"l9g 2b8",
    "addr:street":"Wilson St E",
    "iso:country":"CA",
    "sg:address":"265 Wilson St E",
    "sg:city":"Ancaster",
    "sg:classifiers":[
        {
            "category":"Organizations",
            "subcategory":"Religious Organization",
            "type":"Services"
        }
    ],
    "sg:phone":"+1 905 648 2731",
    "sg:postcode":"L9G 2B8",
    "sg:province":"ON",
    "sg:tags":[
        "church"
    ],
    "wof:name":"Ryerson United Church",
    "wof:placetype":"venue"
},
  "geometry": {"coordinates":[-79.97790500000001,43.224476],"type":"Point"}
}