{
  "type": "Feature",
  "properties": {
    "iso:country":"CA",
    "sg:address":"265 Wilson St E",
    "sg:city":"Ancaster",
    "sg:classifiers":[
        {
            "category":"Organizations",
            "subcategory":"Religious Organization",
            "type":"Services"
        }
    ],
    "sg:phone":"+1 905 648 2731",
    "sg:postcode":"L9G 2B8",
    "sg:province":"ON",
    "sg:tags":[
        "church"
    ],
    "wof:name":"Ryerson United Church",
    "wof:placetype":"venue"
},
  "geometry": {"coordinates":[-79.97790500000001,43.224476],"type":"Point"}
}