{
  "type": "Feature",
  "properties": {
    "addr:full":"199 Grand River St N Paris ON N3L 2N2",
    "addr:housenumber":"199",
    "addr:postcode":"n3l 2n2",
    "addr:street":"Grand River St N",
    "iso:country":"CA",
    "sg:address":"199 Grand River St N",
    "sg:city":"Paris",
    "sg:classifiers":[
        {
            "category":"Social Services",
            "subcategory":"Child Care",
            "type":"Services"
        }
    ],
    "sg:phone":"+1 519 442 6680",
    "sg:postcode":"N3L 2N2",
    "sg:province":"ON",
    "wof:name":"Paris Child Care Inc",
    "wof:placetype":"venue"
},
  "geometry": {"coordinates":[-80.384781,43.200455],"type":"Point"}
}