{
  "type": "Feature",
  "properties": {
    "iso:country":"CA",
    "sg:city":"Brentwood Bay",
    "sg:classifiers":[
        {
            "category":"Professional",
            "subcategory":"Lawyer & Legal Services",
            "type":"Services"
        }
    ],
    "sg:phone":"+1 250 652 5151",
    "sg:postcode":"V8M 1P7",
    "sg:province":"BC",
    "sg:tags":[
        "attorney"
    ],
    "wof:name":"Jenko, Sandra E",
    "wof:placetype":"venue"
},
  "geometry": {"coordinates":[-123.44535827599999,48.5754928589],"type":"Point"}
}