{
  "type": "Feature",
  "properties": {
    "iso:country":"CA",
    "sg:address":"6602 41 Ave",
    "sg:city":"Ponoka",
    "sg:classifiers":[
        {
            "category":"Building & Trades",
            "subcategory":"Electrical",
            "type":"Services"
        }
    ],
    "sg:phone":"+1 403 783 2199",
    "sg:postcode":"T4J 1J8",
    "sg:province":"AB",
    "sg:tags":[
        "instrument",
        "electric",
        "contractor"
    ],
    "wof:name":"Phase III Electric Ponoka Ltd",
    "wof:placetype":"venue"
},
  "geometry": {"coordinates":[-113.604980469,52.6704406738],"type":"Point"}
}