{
  "type": "Feature",
  "properties": {
    "addr:full":"917 Island Hwy Campbell River BC V9W 2C2",
    "addr:housenumber":"917",
    "addr:postcode":"v9w 2c2",
    "addr:street":"Island Hwy",
    "iso:country":"CA",
    "sg:address":"917 Island Hwy",
    "sg:city":"Campbell River",
    "sg:classifiers":[
        {
            "category":"Shopping",
            "subcategory":"Computers & Home Electronics",
            "type":"Retail Goods"
        }
    ],
    "sg:phone":"+1 250 850 0111",
    "sg:postcode":"V9W 2C2",
    "sg:province":"BC",
    "sg:tags":[
        "equipment",
        "dealer"
    ],
    "wof:name":"Pier Street Computers",
    "wof:placetype":"venue"
},
  "geometry": {"coordinates":[-125.240097046,50.0238265991],"type":"Point"}
}