{
  "type": "Feature",
  "properties": {
    "iso:country":"CA",
    "sg:address":"484 Cosburn Ave",
    "sg:city":"East York",
    "sg:classifiers":[
        {
            "category":"Recreation",
            "subcategory":"Amusement Park",
            "type":"Entertainment"
        }
    ],
    "sg:phone":"+1 416 425 8280",
    "sg:postcode":"M4J 2N5",
    "sg:province":"ON",
    "wof:name":"Wiz Kids Activity Ctr",
    "wof:placetype":"venue"
},
  "geometry": {"coordinates":[-79.33381652830001,43.6930122375],"type":"Point"}
}