{
  "type": "Feature",
  "properties": {
    "addr:full":"5475 Rue Pare Mont-Royal QC H4P 1P7",
    "addr:housenumber":"5475",
    "addr:postcode":"h4p 1p7",
    "addr:street":"Rue Pare",
    "iso:country":"CA",
    "sg:address":"5475 Rue Pare",
    "sg:city":"Mont-Royal",
    "sg:classifiers":[
        {
            "category":"Freight",
            "type":"Transportation"
        }
    ],
    "sg:phone":"+1 514 731 7667",
    "sg:postcode":"H4P 1P7",
    "sg:province":"QC",
    "sg:tags":[
        "broker",
        "trucking"
    ],
    "wof:name":"Boyd's Transport",
    "wof:placetype":"venue"
},
  "geometry": {"coordinates":[-73.659531,45.493107],"type":"Point"}
}