{
  "type": "Feature",
  "properties": {
    "addr:full":"53 Higgins Ave Winnipeg MB R3B 0A8",
    "addr:housenumber":"53",
    "addr:postcode":"r3b 0a8",
    "addr:street":"Higgins Ave",
    "iso:country":"CA",
    "sg:address":"53 Higgins Ave",
    "sg:city":"Winnipeg",
    "sg:classifiers":[
        {
            "category":"Building & Trades",
            "subcategory":"Construction",
            "type":"Services"
        }
    ],
    "sg:phone":"+1 204 957 7200",
    "sg:postcode":"R3B 0A8",
    "sg:province":"MB",
    "sg:tags":[
        "front",
        "store"
    ],
    "wof:name":"Border Glass & Aluminum",
    "wof:placetype":"venue"
},
  "geometry": {"coordinates":[-97.119659,49.902336],"type":"Point"}
}