{
  "type": "Feature",
  "properties": {
    "addr:full":"23 6th St Weyburn SK S4H 1A7",
    "addr:housenumber":"23",
    "addr:postcode":"s4h 1a7",
    "addr:street":"6Th St",
    "iso:country":"CA",
    "sg:address":"23 6th St",
    "sg:city":"Weyburn",
    "sg:classifiers":[
        {
            "category":"Government",
            "subcategory":"Office",
            "type":"Public Place"
        }
    ],
    "sg:phone":"+1 306 842 2314",
    "sg:postcode":"S4H 1A7",
    "sg:province":"SK",
    "sg:tags":[
        "municipality"
    ],
    "wof:name":"Rural Municipality of Weyburn",
    "wof:placetype":"venue"
},
  "geometry": {"coordinates":[-103.850319,49.659977],"type":"Point"}
}