{
  "type": "Feature",
  "properties": {
    "addr:full":"133 Woodland Dr Williams Lake BC V2G 4P9",
    "addr:housenumber":"133",
    "addr:postcode":"v2g 4p9",
    "addr:street":"Woodland Dr",
    "iso:country":"CA",
    "sg:address":"133 Woodland Dr",
    "sg:city":"Williams Lake",
    "sg:classifiers":[
        {
            "category":"Building & Trades",
            "subcategory":"Electrical",
            "type":"Services"
        }
    ],
    "sg:phone":"+1 250 392 2466",
    "sg:postcode":"V2G 4P9",
    "sg:province":"BC",
    "sg:tags":[
        "electric",
        "contractor"
    ],
    "wof:name":"Little Eagle Electrical",
    "wof:placetype":"venue"
},
  "geometry": {"coordinates":[-122.16806,52.117809],"type":"Point"}
}