{
  "type": "Feature",
  "properties": {
    "addr:full":"401 Weber St N #D Waterloo ON N2J 3J2",
    "addr:housenumber":"401",
    "addr:postcode":"n2j 3j2",
    "addr:street":"Weber St N # D",
    "iso:country":"CA",
    "sg:address":"401 Weber St N #D",
    "sg:city":"Waterloo",
    "sg:classifiers":[
        {
            "category":"Retail",
            "subcategory":"Auto Repair",
            "type":"Services"
        }
    ],
    "sg:phone":"+1 519 884 6540",
    "sg:postcode":"N2J 3J2",
    "sg:province":"ON",
    "sg:tags":[
        "repairing",
        "automobile",
        "dealer"
    ],
    "wof:name":"Autoworks",
    "wof:placetype":"venue"
},
  "geometry": {"coordinates":[-80.525482,43.484669],"type":"Point"}
}