{
  "type": "Feature",
  "properties": {
    "iso:country":"CA",
    "sg:address":"1200 Stanley Park Dr",
    "sg:city":"Vancouver",
    "sg:classifiers":[
        {
            "category":"Social Services",
            "type":"Services"
        }
    ],
    "sg:phone":"+1 604 733 6289",
    "sg:postcode":"V6G 3E2",
    "sg:province":"BC",
    "sg:tags":[
        "youth",
        "organization",
        "center"
    ],
    "wof:name":"Navy League of Canada",
    "wof:placetype":"venue"
},
  "geometry": {"coordinates":[-123.124641419,49.297832489],"type":"Point"}
}