{
  "type": "Feature",
  "properties": {
    "addr:full":"2470 Mary Hill Rd Port Coquitlam BC V3C 3B1",
    "addr:housenumber":"2470",
    "addr:postcode":"v3c 3b1",
    "addr:street":"Mary Hill Rd",
    "iso:country":"CA",
    "sg:address":"2470 Mary Hill Rd",
    "sg:city":"Port Coquitlam",
    "sg:classifiers":[
        {
            "category":"Education",
            "subcategory":"Library",
            "type":"Public Place"
        }
    ],
    "sg:phone":"+1 604 927 7999",
    "sg:postcode":"V3C 3B1",
    "sg:province":"BC",
    "wof:name":"Port Coquitlam Terry Fox Lbry",
    "wof:placetype":"venue"
},
  "geometry": {"coordinates":[-122.778336,49.260303],"type":"Point"}
}