{
  "type": "Feature",
  "properties": {
    "iso:country":"CA",
    "sg:address":"9944 82 Ave NW",
    "sg:city":"Edmonton",
    "sg:classifiers":[
        {
            "category":"Food & Beverages",
            "subcategory":"Meat & Fish",
            "type":"Retail Goods"
        }
    ],
    "sg:phone":"+1 780 439 6913",
    "sg:postcode":"T6E 1Y9",
    "sg:province":"AB",
    "wof:name":"K & K Foodliners Ltd",
    "wof:placetype":"venue"
},
  "geometry": {"coordinates":[-113.487312,53.518337],"type":"Point"}
}