{
  "type": "Feature",
  "properties": {
    "addr:full":"1318 Lonsdale Ave North Vancouver BC V7M 2H8",
    "addr:housenumber":"1318",
    "addr:postcode":"v7m 2h8",
    "addr:street":"Lonsdale Ave",
    "iso:country":"CA",
    "sg:address":"1318 Lonsdale Ave",
    "sg:city":"North Vancouver",
    "sg:classifiers":[
        {
            "category":"Shopping",
            "subcategory":"Gifts & Souvenirs",
            "type":"Retail Goods"
        }
    ],
    "sg:phone":"+1 604 986 0858",
    "sg:postcode":"V7M 2H8",
    "sg:province":"BC",
    "sg:tags":[
        "shop"
    ],
    "wof:name":"Lily Sun Enterprises Ltd",
    "wof:placetype":"venue"
},
  "geometry": {"coordinates":[-123.072174,49.320267],"type":"Point"}
}