{
  "type": "Feature",
  "properties": {
    "iso:country":"CA",
    "sg:address":"1723 Mattawa Ave",
    "sg:city":"Mississauga",
    "sg:classifiers":[
        {
            "category":"Building & Trades",
            "subcategory":"Landscaping Services",
            "type":"Services"
        }
    ],
    "sg:phone":"+1 905 279 2050",
    "sg:postcode":"L4X 1K5",
    "sg:province":"ON",
    "sg:tags":[
        "lawn",
        "contractor",
        "landscape",
        "maintenance",
        "grounds"
    ],
    "wof:name":"Personal Touch Landscaping Ltd",
    "wof:placetype":"venue"
},
  "geometry": {"coordinates":[-79.572235,43.61385],"type":"Point"}
}