{
  "type": "Feature",
  "properties": {
    "iso:country":"CA",
    "sg:address":"4802 50 St",
    "sg:city":"St Paul",
    "sg:classifiers":[
        {
            "category":"Insurance",
            "subcategory":"Insurance Agent",
            "type":"Services"
        }
    ],
    "sg:phone":"+1 780 645 4449",
    "sg:postcode":"T0A 3A4",
    "sg:province":"AB",
    "wof:name":"V B Insurance Brokers Ltd",
    "wof:placetype":"venue"
},
  "geometry": {"coordinates":[-111.297149658,53.9894638062],"type":"Point"}
}