{
  "type": "Feature",
  "properties": {
    "addr:full":"155 Rue Saint-Sacrement Matane QC G4W 1Y9",
    "addr:housenumber":"155",
    "addr:postcode":"g4w 1y9",
    "addr:street":"Rue Saint-Sacrement",
    "iso:country":"CA",
    "sg:address":"155 Rue Saint-Sacrement",
    "sg:city":"Matane",
    "sg:classifiers":[
        {
            "category":"Communications",
            "subcategory":"Radio Station",
            "type":"Services"
        }
    ],
    "sg:phone":"+1 418 562 0290",
    "sg:postcode":"G4W 1Y9",
    "sg:province":"QC",
    "sg:tags":[
        "company",
        "broadcasting"
    ],
    "wof:name":"Radio Canada",
    "wof:placetype":"venue"
},
  "geometry": {"coordinates":[-67.533325,48.848957],"type":"Point"}
}