{
  "type": "Feature",
  "properties": {
    "addr:full":"864 Crowley Ave Kelowna BC V1Y 7G7",
    "addr:housenumber":"864",
    "addr:postcode":"v1y 7g7",
    "addr:street":"Crowley Ave",
    "iso:country":"CA",
    "sg:address":"864 Crowley Ave",
    "sg:city":"Kelowna",
    "sg:classifiers":[
        {
            "category":"Manufacturing",
            "subcategory":"Tools & Machinery",
            "type":"Manufacturing & Wholesale Goods"
        }
    ],
    "sg:phone":"+1 250 763 4161",
    "sg:postcode":"V1Y 7G7",
    "sg:province":"BC",
    "sg:tags":[
        "machine",
        "shop"
    ],
    "wof:name":"Visco Manufacturing Ltd",
    "wof:placetype":"venue"
},
  "geometry": {"coordinates":[-119.484077,49.898308],"type":"Point"}
}