{
  "type": "Feature",
  "properties": {
    "addr:full":"140 5th St NW Portage LA Prairie MB R1N 2H5",
    "addr:housenumber":"140",
    "addr:postcode":"r1n 2h5",
    "addr:street":"5Th St Nw",
    "iso:country":"CA",
    "sg:address":"140 5th St NW",
    "sg:city":"Portage LA Prairie",
    "sg:classifiers":[
        {
            "category":"Wholesale",
            "subcategory":"Electrical",
            "type":"Manufacturing & Wholesale Goods"
        }
    ],
    "sg:phone":"+1 204 857 8617",
    "sg:postcode":"R1N 2H5",
    "sg:province":"MB",
    "sg:tags":[
        "appliance"
    ],
    "wof:name":"Barkley's Appliance Repair",
    "wof:placetype":"venue"
},
  "geometry": {"coordinates":[-98.2970046997,49.9761924744],"type":"Point"}
}