{
  "type": "Feature",
  "properties": {
    "addr:full":"3925 King Edward Ave W Vancouver BC V6S 1N2",
    "addr:housenumber":"3925",
    "addr:postcode":"v6s 1n2",
    "addr:street":"King Edward Ave W",
    "iso:country":"CA",
    "sg:address":"3925 King Edward Ave W",
    "sg:city":"Vancouver",
    "sg:classifiers":[
        {
            "category":"Building & Trades",
            "subcategory":"Landscaping Services",
            "type":"Services"
        }
    ],
    "sg:phone":"+1 604 222 1498",
    "sg:postcode":"V6S 1N2",
    "sg:province":"BC",
    "sg:tags":[
        "landscape",
        "contractor"
    ],
    "wof:name":"Grandin & CO Landscaping Ltd",
    "wof:placetype":"venue"
},
  "geometry": {"coordinates":[-123.19156599999999,49.250286],"type":"Point"}
}