{
  "type": "Feature",
  "properties": {
    "addr:full":"225 Industrial Pky S Aurora ON L4G 3V5",
    "addr:housenumber":"225",
    "addr:postcode":"l4g 3v5",
    "addr:street":"Industrial Pky",
    "iso:country":"CA",
    "sg:address":"225 Industrial Pky S",
    "sg:city":"Aurora",
    "sg:classifiers":[
        {
            "category":"Manufacturing",
            "subcategory":"Signs",
            "type":"Manufacturing & Wholesale Goods"
        }
    ],
    "sg:phone":"+1 905 713 1883",
    "sg:postcode":"L4G 3V5",
    "sg:province":"ON",
    "wof:name":"Signs in the Making",
    "wof:placetype":"venue"
},
  "geometry": {"coordinates":[-79.45416299999999,43.991936],"type":"Point"}
}