{
  "type": "Feature",
  "properties": {
    "addr:full":"1272 Prom Du Saint-Maurice Shawinigan QC G9N 1L8",
    "addr:housenumber":"1272",
    "addr:postcode":"g9n 1l8",
    "addr:street":"Prom Du Saint-Maurice",
    "iso:country":"CA",
    "sg:address":"1272 Prom Du Saint-Maurice",
    "sg:city":"Shawinigan",
    "sg:classifiers":[
        {
            "category":"Real Estate",
            "subcategory":"Real Estate Agent",
            "type":"Services"
        }
    ],
    "sg:phone":"+1 819 536 5877",
    "sg:postcode":"G9N 1L8",
    "sg:province":"QC",
    "sg:tags":[
        "appraiser"
    ],
    "wof:name":"Jean-Louis Hannis Inc",
    "wof:placetype":"venue"
},
  "geometry": {"coordinates":[-72.756287,46.54137],"type":"Point"}
}