{
  "type": "Feature",
  "properties": {
    "addr:full":"Montreal QC H3A 2N4",
    "addr:postcode":"h3a 2n4",
    "iso:country":"CA",
    "sg:city":"Montreal",
    "sg:classifiers":[
        {
            "category":"Banks & Credit Unions",
            "subcategory":"Bank",
            "type":"Services"
        }
    ],
    "sg:phone":"+1 514 286 1660",
    "sg:postcode":"H3A 2N4",
    "sg:province":"QC",
    "sg:tags":[
        "financing"
    ],
    "wof:name":"Dacha Capital Inc",
    "wof:placetype":"venue"
},
  "geometry": {"coordinates":[-73.57221199999999,45.502804],"type":"Point"}
}