{
  "type": "Feature",
  "properties": {
    "iso:country":"CA",
    "sg:city":"Montreal",
    "sg:classifiers":[
        {
            "category":"Banks & Credit Unions",
            "subcategory":"Bank",
            "type":"Services"
        }
    ],
    "sg:phone":"+1 514 286 1660",
    "sg:postcode":"H3A 2N4",
    "sg:province":"QC",
    "sg:tags":[
        "financing"
    ],
    "wof:name":"Dacha Capital Inc",
    "wof:placetype":"venue"
},
  "geometry": {"coordinates":[-73.572212,45.502804],"type":"Point"}
}