{
  "type": "Feature",
  "properties": {
    "addr:full":"4305 Spring Creek Rd Vineland ON L0R 2C0",
    "addr:housenumber":"4305",
    "addr:postcode":"l0r 2c0",
    "addr:street":"Spring Creek Rd",
    "iso:country":"CA",
    "sg:address":"4305 Spring Creek Rd",
    "sg:city":"Vineland",
    "sg:classifiers":[
        {
            "category":"Manufacturing",
            "subcategory":"Rubber & Plastics",
            "type":"Manufacturing & Wholesale Goods"
        }
    ],
    "sg:phone":"+1 905 563 0226",
    "sg:postcode":"L0R 2C0",
    "sg:province":"ON",
    "sg:tags":[
        "product"
    ],
    "wof:name":"Plastruct Canada",
    "wof:placetype":"venue"
},
  "geometry": {"coordinates":[-79.394402,43.159954],"type":"Point"}
}