{
  "type": "Feature",
  "properties": {
    "iso:country":"CA",
    "sg:city":"Drayton Valley",
    "sg:classifiers":[
        {
            "category":"Shopping",
            "subcategory":"Clothing, Apparel, & Fashions",
            "type":"Retail Goods"
        }
    ],
    "sg:phone":"+1 780 514 5051",
    "sg:postcode":"T7A 1R9",
    "sg:province":"AB",
    "sg:tags":[
        "alteration"
    ],
    "wof:name":"Stitches & Dreams",
    "wof:placetype":"venue"
},
  "geometry": {"coordinates":[-114.978385925,53.2228355408],"type":"Point"}
}