{
  "type": "Feature",
  "properties": {
    "addr:full":"201 Boul DE L'Industrie # 102 Candiac QC J5R 6A6",
    "addr:housenumber":"201",
    "addr:postcode":"j5r 6a6",
    "addr:street":"Boul De L'Industrie # 102",
    "iso:country":"CA",
    "sg:address":"201 Boul DE L'Industrie # 102",
    "sg:city":"Candiac",
    "sg:classifiers":[
        {
            "category":"Health Services",
            "subcategory":"Optometrist",
            "type":"Services"
        }
    ],
    "sg:phone":"+1 450 444 9141",
    "sg:postcode":"J5R 6A6",
    "sg:province":"QC",
    "wof:name":"Optometrie Candiac",
    "wof:placetype":"venue"
},
  "geometry": {"coordinates":[-73.5154418945,45.3918418884],"type":"Point"}
}