{
  "type": "Feature",
  "properties": {
    "addr:full":"592 Hwy 2 Brookfield NS B0N 1C0",
    "addr:housenumber":"592",
    "addr:postcode":"b0n 1c0",
    "addr:street":"Hwy 2",
    "iso:country":"CA",
    "sg:address":"592 Hwy 2",
    "sg:city":"Brookfield",
    "sg:classifiers":[
        {
            "category":"Home & Garden",
            "subcategory":"Building Materials",
            "type":"Retail Goods"
        }
    ],
    "sg:phone":"+1 902 673 2323",
    "sg:postcode":"B0N 1C0",
    "sg:province":"NS",
    "wof:name":"Brookfield Lumber CO Ltd",
    "wof:placetype":"venue"
},
  "geometry": {"coordinates":[-63.279778,45.254669],"type":"Point"}
}