{
  "type": "Feature",
  "properties": {
    "addr:full":"3260 Gladwin Rd Abbotsford BC V2S 7B4",
    "addr:housenumber":"3260",
    "addr:postcode":"v2s 7b4",
    "addr:street":"Gladwin Rd",
    "iso:country":"CA",
    "sg:address":"3260 Gladwin Rd",
    "sg:city":"Abbotsford",
    "sg:classifiers":[
        {
            "category":"Organizations",
            "subcategory":"Religious Organization",
            "type":"Services"
        }
    ],
    "sg:phone":"+1 604 854 5710",
    "sg:postcode":"V2S 7B4",
    "sg:province":"BC",
    "sg:tags":[
        "church"
    ],
    "wof:name":"Bethel Reformed Church",
    "wof:placetype":"venue"
},
  "geometry": {"coordinates":[-122.31585699999999,49.0616],"type":"Point"}
}