{
  "type": "Feature",
  "properties": {
    "addr:full":"3335 Bayview Ave North York ON M2K 1G4",
    "addr:housenumber":"3335",
    "addr:postcode":"m2k 1g4",
    "addr:street":"Bayview Ave",
    "iso:country":"CA",
    "sg:address":"3335 Bayview Ave",
    "sg:city":"North York",
    "sg:classifiers":[
        {
            "category":"Shopping",
            "subcategory":"Bicycles & Sporting Goods",
            "type":"Retail Goods"
        }
    ],
    "sg:phone":"+1 416 225 2633",
    "sg:postcode":"M2K 1G4",
    "sg:province":"ON",
    "wof:name":"Bayview Cycle Ctr",
    "wof:placetype":"venue"
},
  "geometry": {"coordinates":[-79.39334106450001,43.7920379639],"type":"Point"}
}