{
  "type": "Feature",
  "properties": {
    "addr:full":"7416 Victoria Dr Vancouver BC V5P 3Z3",
    "addr:housenumber":"7416",
    "addr:postcode":"v5p 3z3",
    "addr:street":"Victoria Dr",
    "iso:country":"CA",
    "sg:address":"7416 Victoria Dr",
    "sg:city":"Vancouver",
    "sg:classifiers":[
        {
            "category":"Social Services",
            "subcategory":"Child Care",
            "type":"Services"
        }
    ],
    "sg:phone":"+1 604 325 8299",
    "sg:postcode":"V5P 3Z3",
    "sg:province":"BC",
    "wof:name":"Good Shepherd Day Care",
    "wof:placetype":"venue"
},
  "geometry": {"coordinates":[-123.065765,49.217041],"type":"Point"}
}