{
  "type": "Feature",
  "properties": {
    "addr:full":"160 Union St Toronto ON M6N 3M9",
    "addr:housenumber":"160",
    "addr:postcode":"m6n 3m9",
    "addr:street":"Union St",
    "iso:country":"CA",
    "sg:address":"160 Union St",
    "sg:city":"Toronto",
    "sg:classifiers":[
        {
            "category":"Manufacturing",
            "subcategory":"Motor Vehicles & Parts",
            "type":"Manufacturing & Wholesale Goods"
        }
    ],
    "sg:phone":"+1 416 652 3300",
    "sg:postcode":"M6N 3M9",
    "sg:province":"ON",
    "sg:tags":[
        "automobile",
        "wrecker"
    ],
    "wof:name":"Stark's Auto Parts",
    "wof:placetype":"venue"
},
  "geometry": {"coordinates":[-79.467857,43.678101],"type":"Point"}
}