{
  "type": "Feature",
  "properties": {
    "addr:full":"PO Box 174 STN Central Charlottetown PE C1A 7K4",
    "addr:housenumber":"po",
    "addr:postcode":"c1a 7k4",
    "addr:street":"Box 174",
    "iso:country":"CA",
    "sg:address":"PO Box 174 STN Central",
    "sg:city":"Charlottetown",
    "sg:classifiers":[
        {
            "category":"Building & Trades",
            "subcategory":"Plumbing",
            "type":"Services"
        }
    ],
    "sg:phone":"+1 902 629 1212",
    "sg:postcode":"C1A 7K4",
    "sg:province":"PE",
    "sg:tags":[
        "septic"
    ],
    "wof:name":"Mac Callum Sewer Septic Svc",
    "wof:placetype":"venue"
},
  "geometry": {"coordinates":[-63.12817,46.236591],"type":"Point"}
}