{
  "type": "Feature",
  "properties": {
    "addr:full":"12958 82 St NW Edmonton AB T5E 2T2",
    "addr:housenumber":"12958",
    "addr:postcode":"t5e 2t2",
    "addr:street":"82 St Nw",
    "iso:country":"CA",
    "sg:address":"12958 82 St NW",
    "sg:city":"Edmonton",
    "sg:classifiers":[
        {
            "category":"Professional",
            "subcategory":"Accounting & Tax Preparation",
            "type":"Services"
        }
    ],
    "sg:phone":"+1 780 448 2124",
    "sg:postcode":"T5E 2T2",
    "sg:province":"AB",
    "sg:tags":[
        "return",
        "filing"
    ],
    "wof:name":"H & R Block Canada Inc",
    "wof:placetype":"venue"
},
  "geometry": {"coordinates":[-113.4674,53.58765],"type":"Point"}
}