{
  "type": "Feature",
  "properties": {
    "addr:full":"Baie-Saint-Paul QC G3Z 2W2",
    "addr:postcode":"g3z 2w2",
    "iso:country":"CA",
    "sg:city":"Baie-Saint-Paul",
    "sg:classifiers":[
        {
            "category":"Autos & Motor Vehicles",
            "subcategory":"Motorcycle Sales",
            "type":"Retail Goods"
        }
    ],
    "sg:phone":"+1 418 435 5984",
    "sg:postcode":"G3Z 2W2",
    "sg:province":"QC",
    "sg:tags":[
        "automobile",
        "stereo",
        "radio"
    ],
    "wof:name":"Electro-Dan Enr",
    "wof:placetype":"venue"
},
  "geometry": {"coordinates":[-70.51750183110001,47.4475288391],"type":"Point"}
}