{
  "type": "Feature",
  "properties": {
    "addr:full":"560 Line 7 N RR 2 Oro ON L0L 2X0",
    "addr:housenumber":"560;2",
    "addr:postcode":"l0l 2x0",
    "addr:street":"Line 7 N Rr",
    "iso:country":"CA",
    "sg:address":"560 Line 7 N RR 2",
    "sg:city":"Oro",
    "sg:classifiers":[
        {
            "category":"Professional",
            "subcategory":"Advertising",
            "type":"Services"
        }
    ],
    "sg:phone":"+1 705 487 1843",
    "sg:postcode":"L0L 2X0",
    "sg:province":"ON",
    "sg:tags":[
        "aircraft",
        "school"
    ],
    "wof:name":"Barrie Regional Flight Ctr",
    "wof:placetype":"venue"
},
  "geometry": {"coordinates":[-79.6295013428,44.4940490723],"type":"Point"}
}