{
  "type": "Feature",
  "properties": {
    "iso:country":"CA",
    "sg:city":"Toronto",
    "sg:classifiers":[
        {
            "category":"Professional",
            "subcategory":"Computer Services",
            "type":"Services"
        }
    ],
    "sg:phone":"+1 416 598 7770",
    "sg:postcode":"M5T 2C2",
    "sg:province":"ON",
    "sg:tags":[
        "internet"
    ],
    "wof:name":"Usability Masters",
    "wof:placetype":"venue"
},
  "geometry": {"coordinates":[-79.397293,43.650227],"type":"Point"}
}