{
  "type": "Feature",
  "properties": {
    "iso:country":"CA",
    "sg:city":"Maple Ridge",
    "sg:classifiers":[
        {
            "category":"Restaurant",
            "type":"Food & Drink"
        }
    ],
    "sg:phone":"+1 604 466 4820",
    "sg:postcode":"V2X 2V5",
    "sg:province":"BC",
    "sg:tags":[
        "delicatessen"
    ],
    "wof:name":"Deli Station",
    "wof:placetype":"venue"
},
  "geometry": {"coordinates":[-122.593353272,49.217048645],"type":"Point"}
}