{
  "type": "Feature",
  "properties": {
    "addr:full":"1250 Rue University Montreal QC H3B 3B8",
    "addr:housenumber":"1250",
    "addr:postcode":"h3b 3b8",
    "addr:street":"Rue University",
    "iso:country":"CA",
    "sg:address":"1250 Rue University",
    "sg:city":"Montreal",
    "sg:classifiers":[
        {
            "category":"Insurance",
            "subcategory":"Insurance Agent",
            "type":"Services"
        }
    ],
    "sg:phone":"+1 514 685 4231",
    "sg:postcode":"H3B 3B8",
    "sg:province":"QC",
    "wof:name":"Justin Case Insurance.com",
    "wof:placetype":"venue"
},
  "geometry": {"coordinates":[-73.5693817139,45.5028991699],"type":"Point"}
}