{
  "type": "Feature",
  "properties": {
    "addr:full":"2976 Hwy 11 S 7th Line Oro Station ON L0L 2E0",
    "addr:housenumber":"2976",
    "addr:postcode":"l0l 2e0",
    "addr:street":"Hwy 11 S 7Th Line",
    "iso:country":"CA",
    "sg:address":"2976 Hwy 11 S 7th Line",
    "sg:city":"Oro Station",
    "sg:classifiers":[
        {
            "category":"Autos & Motor Vehicles",
            "subcategory":"Fuel & Gas Station",
            "type":"Retail Goods"
        }
    ],
    "sg:phone":"+1 705 487 0808",
    "sg:postcode":"L0L 2E0",
    "sg:province":"ON",
    "sg:tags":[
        "oil"
    ],
    "wof:name":"Petro Plus",
    "wof:placetype":"venue"
},
  "geometry": {"coordinates":[-79.513954,44.454727],"type":"Point"}
}