{
  "type": "Feature",
  "properties": {
    "addr:full":"640 Second Ruisseau St Calixa-Lavallee QC J0L 1A0",
    "addr:housenumber":"640",
    "addr:postcode":"j0l 1a0",
    "addr:street":"Second Ruisseau St",
    "iso:country":"CA",
    "sg:address":"640 Second Ruisseau St",
    "sg:city":"Calixa-Lavallee",
    "sg:classifiers":[
        {
            "category":"Restaurant",
            "type":"Food & Drink"
        }
    ],
    "sg:phone":"+1 450 583 5673",
    "sg:postcode":"J0L 1A0",
    "sg:province":"QC",
    "wof:name":"Fine Tablee Enr",
    "wof:placetype":"venue"
},
  "geometry": {"coordinates":[-73.2591705322,45.7415237427],"type":"Point"}
}