{
  "type": "Feature",
  "properties": {
    "addr:full":"2631 Cyril St Abbotsford BC V2S 2G4",
    "addr:housenumber":"2631",
    "addr:postcode":"v2s 2g4",
    "addr:street":"Cyril St",
    "iso:country":"CA",
    "sg:address":"2631 Cyril St",
    "sg:city":"Abbotsford",
    "sg:classifiers":[
        {
            "category":"Social Services",
            "type":"Services"
        }
    ],
    "sg:phone":"+1 604 853 4014",
    "sg:postcode":"V2S 2G4",
    "sg:province":"BC",
    "sg:tags":[
        "senior",
        "citizen"
    ],
    "wof:name":"Abbotsford Seniors Assn",
    "wof:placetype":"venue"
},
  "geometry": {"coordinates":[-122.286460877,49.0493774414],"type":"Point"}
}