{
  "type": "Feature",
  "properties": {
    "iso:country":"CA",
    "sg:address":"21 Proton S",
    "sg:city":"Dundalk",
    "sg:classifiers":[
        {
            "category":"Social Services",
            "subcategory":"Child Care",
            "type":"Services"
        }
    ],
    "sg:phone":"+1 519 923 3288",
    "sg:postcode":"N0C 1B0",
    "sg:province":"ON",
    "sg:tags":[
        "kindergarten",
        "academic"
    ],
    "wof:name":"Southgate Child Care",
    "wof:placetype":"venue"
},
  "geometry": {"coordinates":[-80.3923339844,44.168258667],"type":"Point"}
}