{
  "type": "Feature",
  "properties": {
    "addr:full":"108 Park St Georgetown ON L7G 2V4",
    "addr:housenumber":"108",
    "addr:postcode":"l7g 2v4",
    "addr:street":"Park St",
    "iso:country":"CA",
    "sg:address":"108 Park St",
    "sg:city":"Georgetown",
    "sg:classifiers":[
        {
            "category":"Retail",
            "subcategory":"Auto Repair",
            "type":"Services"
        }
    ],
    "sg:phone":"+1 416 255 3097",
    "sg:postcode":"L7G 2V4",
    "sg:province":"ON",
    "sg:tags":[
        "glass",
        "coating",
        "tinting"
    ],
    "wof:name":"Metro Window Tinting Inc",
    "wof:placetype":"venue"
},
  "geometry": {"coordinates":[-79.92441599999999,43.662582],"type":"Point"}
}