{
  "type": "Feature",
  "properties": {
    "addr:full":"216 Monument Pl SE Calgary AB T2A 1X3",
    "addr:housenumber":"216",
    "addr:postcode":"t2a 1x3",
    "addr:street":"Monument Pl Se",
    "iso:country":"CA",
    "sg:address":"216 Monument Pl SE",
    "sg:city":"Calgary",
    "sg:classifiers":[
        {
            "category":"Retail",
            "subcategory":"Auto Repair",
            "type":"Services"
        }
    ],
    "sg:phone":"+1 403 272 9889",
    "sg:postcode":"T2A 1X3",
    "sg:province":"AB",
    "sg:tags":[
        "repairing",
        "automobile",
        "radiator"
    ],
    "wof:name":"Crossroads Radiator Ltd",
    "wof:placetype":"venue"
},
  "geometry": {"coordinates":[-113.99653600000001,51.051682],"type":"Point"}
}