{
  "type": "Feature",
  "properties": {
    "addr:full":"30 Boyd St Stratford ON N5A 6S4",
    "addr:housenumber":"30",
    "addr:postcode":"n5a 6s4",
    "addr:street":"Boyd St",
    "iso:country":"CA",
    "sg:address":"30 Boyd St",
    "sg:city":"Stratford",
    "sg:classifiers":[
        {
            "category":"Retail",
            "subcategory":"Auto Repair",
            "type":"Services"
        }
    ],
    "sg:phone":"+1 519 273 6627",
    "sg:postcode":"N5A 6S4",
    "sg:province":"ON",
    "sg:tags":[
        "repairing",
        "automobile"
    ],
    "wof:name":"Festival City Transmissions",
    "wof:placetype":"venue"
},
  "geometry": {"coordinates":[-80.987427,43.352669],"type":"Point"}
}