{
  "type": "Feature",
  "properties": {
    "addr:full":"2432 Beacon Ave Sidney BC V8L 1X4",
    "addr:housenumber":"2432",
    "addr:postcode":"v8l 1x4",
    "addr:street":"Beacon Ave",
    "iso:country":"CA",
    "sg:address":"2432 Beacon Ave",
    "sg:city":"Sidney",
    "sg:classifiers":[
        {
            "category":"Shopping",
            "subcategory":"Jewelry",
            "type":"Retail Goods"
        }
    ],
    "sg:phone":"+1 250 656 7141",
    "sg:postcode":"V8L 1X4",
    "sg:province":"BC",
    "sg:tags":[
        "jeweler"
    ],
    "wof:name":"Christine Laurent Jewellers",
    "wof:placetype":"venue"
},
  "geometry": {"coordinates":[-123.399162,48.648994],"type":"Point"}
}