{
  "type": "Feature",
  "properties": {
    "addr:full":"396 O'Connell Dr Corner Brook NL A2H 5P1",
    "addr:housenumber":"396",
    "addr:postcode":"a2h 5p1",
    "addr:street":"O'Connell Dr",
    "iso:country":"CA",
    "sg:address":"396 O'Connell Dr",
    "sg:city":"Corner Brook",
    "sg:classifiers":[
        {
            "category":"Autos & Motor Vehicles",
            "subcategory":"Auto Supplies",
            "type":"Retail Goods"
        }
    ],
    "sg:phone":"+1 709 632 2500",
    "sg:postcode":"A2H 5P1",
    "sg:province":"NL",
    "sg:tags":[
        "tire"
    ],
    "wof:name":"Corner Brook Tire",
    "wof:placetype":"venue"
},
  "geometry": {"coordinates":[-57.937332,48.943825],"type":"Point"}
}