{
  "type": "Feature",
  "properties": {
    "addr:full":"20080 Hwy 11 Bradford ON L3Z 2B3",
    "addr:housenumber":"20080",
    "addr:postcode":"l3z 2b3",
    "addr:street":"Hwy 11",
    "iso:country":"CA",
    "sg:address":"20080 Hwy 11",
    "sg:city":"Bradford",
    "sg:classifiers":[
        {
            "category":"Autos & Motor Vehicles",
            "subcategory":"Fuel & Gas Station",
            "type":"Retail Goods"
        }
    ],
    "sg:phone":"+1 905 775 7593",
    "sg:postcode":"L3Z 2B3",
    "sg:province":"ON",
    "sg:tags":[
        "oil"
    ],
    "wof:name":"Beaver Fuels",
    "wof:placetype":"venue"
},
  "geometry": {"coordinates":[-79.566147,44.119598],"type":"Point"}
}