{
  "type": "Feature",
  "properties": {
    "addr:full":"2693 Highway 97 N Kelowna BC V1X 4J6",
    "addr:housenumber":"2693",
    "addr:postcode":"v1x 4j6",
    "addr:street":"Highway 97 N",
    "iso:country":"CA",
    "sg:address":"2693 Highway 97 N",
    "sg:city":"Kelowna",
    "sg:classifiers":[
        {
            "category":"Autos & Motor Vehicles",
            "subcategory":"Fuel & Gas Station",
            "type":"Retail Goods"
        }
    ],
    "sg:phone":"+1 250 860 5637",
    "sg:postcode":"V1X 4J6",
    "sg:province":"BC",
    "sg:tags":[
        "oil"
    ],
    "wof:name":"Leathead Superstop Express",
    "wof:placetype":"venue"
},
  "geometry": {"coordinates":[-119.49659699999999,49.886814],"type":"Point"}
}