{
  "type": "Feature",
  "properties": {
    "addr:full":"344 Boul Broadway Grand-Sault/Grand Falls NB E3Z 2K4",
    "addr:housenumber":"344",
    "addr:postcode":"e3z 2k4",
    "addr:street":"Boul Broadway",
    "iso:country":"CA",
    "sg:address":"344 Boul Broadway",
    "sg:city":"Grand-Sault/Grand Falls",
    "sg:classifiers":[
        {
            "category":"Professional",
            "subcategory":"Lawyer & Legal Services",
            "type":"Services"
        }
    ],
    "sg:phone":"+1 506 473 2750",
    "sg:postcode":"E3Z 2K4",
    "sg:province":"NB",
    "sg:tags":[
        "attorney"
    ],
    "wof:name":"Mc Carthy, Terrance A",
    "wof:placetype":"venue"
},
  "geometry": {"coordinates":[-67.736053,47.051281],"type":"Point"}
}