{
  "type": "Feature",
  "properties": {
    "addr:full":"180 Main St Vancouver BC V6A 3V5",
    "addr:housenumber":"180",
    "addr:postcode":"v6a 3v5",
    "addr:street":"Main St",
    "iso:country":"CA",
    "sg:address":"180 Main St",
    "sg:city":"Vancouver",
    "sg:classifiers":[
        {
            "category":"Government",
            "subcategory":"Office",
            "type":"Public Place"
        }
    ],
    "sg:phone":"+1 604 660 2941",
    "sg:postcode":"V6A 3V5",
    "sg:province":"BC",
    "wof:name":"B C Human Resources",
    "wof:placetype":"venue"
},
  "geometry": {"coordinates":[-123.099373,49.283432],"type":"Point"}
}