{
  "type": "Feature",
  "properties": {
    "addr:full":"2158 Gottingen St Halifax NS B3K 3B4",
    "addr:housenumber":"2158",
    "addr:postcode":"b3k 3b4",
    "addr:street":"Gottingen St",
    "iso:country":"CA",
    "sg:address":"2158 Gottingen St",
    "sg:city":"Halifax",
    "sg:classifiers":[
        {
            "category":"Education",
            "subcategory":"College",
            "type":"Public Place"
        }
    ],
    "sg:phone":"+1 902 420 1576",
    "sg:postcode":"B3K 3B4",
    "sg:province":"NS",
    "sg:tags":[
        "academic",
        "school"
    ],
    "wof:name":"Kjipuktuk Community College",
    "wof:placetype":"venue"
},
  "geometry": {"coordinates":[-63.584351,44.652496],"type":"Point"}
}