{
  "type": "Feature",
  "properties": {
    "addr:full":"4384 Boul Pie-Ix Montreal QC H1X 2B3",
    "addr:housenumber":"4384",
    "addr:postcode":"h1x 2b3",
    "addr:street":"Boul Pie-Ix",
    "iso:country":"CA",
    "sg:address":"4384 Boul Pie-Ix",
    "sg:city":"Montreal",
    "sg:classifiers":[
        {
            "category":"Insurance",
            "subcategory":"Insurance Agent",
            "type":"Services"
        }
    ],
    "sg:phone":"+1 514 259 9530",
    "sg:postcode":"H1X 2B3",
    "sg:province":"QC",
    "wof:name":"B R Svc Financiers",
    "wof:placetype":"venue"
},
  "geometry": {"coordinates":[-73.5573425293,45.5552749634],"type":"Point"}
}