{
  "type": "Feature",
  "properties": {
    "addr:full":"2 Commercial St Kensington PE C0B 1M0",
    "addr:housenumber":"2",
    "addr:postcode":"c0b 1m0",
    "addr:street":"Commercial St",
    "iso:country":"CA",
    "sg:address":"2 Commercial St",
    "sg:city":"Kensington",
    "sg:classifiers":[
        {
            "category":"Personal",
            "subcategory":"Beauty Salon",
            "type":"Services"
        }
    ],
    "sg:phone":"+1 902 836 5677",
    "sg:postcode":"C0B 1M0",
    "sg:province":"PE",
    "wof:name":"Kensington Hair Station",
    "wof:placetype":"venue"
},
  "geometry": {"coordinates":[-63.6364822388,46.4377403259],"type":"Point"}
}