{
  "type": "Feature",
  "properties": {
    "addr:full":"4088 Rue Saint-Denis Montreal QC H2W 2M5",
    "addr:housenumber":"4088",
    "addr:postcode":"h2w 2m5",
    "addr:street":"Rue Saint-Denis",
    "iso:country":"CA",
    "sg:address":"4088 Rue Saint-Denis",
    "sg:city":"Montreal",
    "sg:classifiers":[
        {
            "category":"Restaurant",
            "type":"Food & Drink"
        }
    ],
    "sg:phone":"+1 514 843 4194",
    "sg:postcode":"H2W 2M5",
    "sg:province":"QC",
    "wof:name":"Restaurant Chu Chai",
    "wof:placetype":"venue"
},
  "geometry": {"coordinates":[-73.576691,45.520981],"type":"Point"}
}