{
  "type": "Feature",
  "properties": {
    "addr:full":"103 Devlin Dr Keewatin ON P0X 1C0",
    "addr:housenumber":"103",
    "addr:postcode":"p0x 1c0",
    "addr:street":"Devlin Dr",
    "iso:country":"CA",
    "sg:address":"103 Devlin Dr",
    "sg:city":"Keewatin",
    "sg:classifiers":[
        {
            "category":"Building & Trades",
            "subcategory":"Construction",
            "type":"Services"
        }
    ],
    "sg:phone":"+1 807 547 3727",
    "sg:postcode":"P0X 1C0",
    "sg:province":"ON",
    "sg:tags":[
        "contractor",
        "general"
    ],
    "wof:name":"Custom Wood Working CO",
    "wof:placetype":"venue"
},
  "geometry": {"coordinates":[-94.55727386469999,49.7577133179],"type":"Point"}
}