{
  "type": "Feature",
  "properties": {
    "addr:full":"894 Caledonia Rd North York ON M6B 3Y1",
    "addr:housenumber":"894",
    "addr:postcode":"m6b 3y1",
    "addr:street":"Caledonia Rd",
    "iso:country":"CA",
    "sg:address":"894 Caledonia Rd",
    "sg:city":"North York",
    "sg:classifiers":[
        {
            "category":"Real Estate",
            "subcategory":"Real Estate Agent",
            "type":"Services"
        }
    ],
    "sg:phone":"+1 416 787 0652",
    "sg:postcode":"M6B 3Y1",
    "sg:province":"ON",
    "sg:tags":[
        "agency",
        "rental",
        "silverware"
    ],
    "wof:name":"Harold's Tableware Rentals",
    "wof:placetype":"venue"
},
  "geometry": {"coordinates":[-79.46481300000001,43.704109],"type":"Point"}
}