{
  "type": "Feature",
  "properties": {
    "iso:country":"CA",
    "sg:address":"650 Matheson Blvd W",
    "sg:city":"Mississauga",
    "sg:classifiers":[
        {
            "category":"Building & Trades",
            "subcategory":"Construction",
            "type":"Services"
        }
    ],
    "sg:phone":"+1 905 712 5900",
    "sg:postcode":"L5R 3T2",
    "sg:province":"ON",
    "sg:tags":[
        "home",
        "improvement"
    ],
    "wof:name":"Home Depot Canada",
    "wof:placetype":"venue"
},
  "geometry": {"coordinates":[-79.68800354,43.6102752686],"type":"Point"}
}