{
  "type": "Feature",
  "properties": {
    "iso:country":"CA",
    "sg:address":"910 Mcgill Rd",
    "sg:city":"Kamloops",
    "sg:classifiers":[
        {
            "category":"Recreation",
            "type":"Entertainment"
        }
    ],
    "sg:phone":"+1 250 828 3655",
    "sg:postcode":"V2C 6N6",
    "sg:province":"BC",
    "sg:tags":[
        "government",
        "swimming"
    ],
    "wof:name":"Canada Games Aquatic Ctr",
    "wof:placetype":"venue"
},
  "geometry": {"coordinates":[-120.364845276,50.6676864624],"type":"Point"}
}