{
  "type": "Feature",
  "properties": {
    "addr:full":"120 Muskoka Rd S Gravenhurst ON P1P 1X2",
    "addr:housenumber":"120",
    "addr:postcode":"p1p 1x2",
    "addr:street":"Muskoka Rd S",
    "iso:country":"CA",
    "sg:address":"120 Muskoka Rd S",
    "sg:city":"Gravenhurst",
    "sg:classifiers":[
        {
            "category":"Shopping",
            "subcategory":"Books",
            "type":"Retail Goods"
        }
    ],
    "sg:phone":"+1 705 687 0555",
    "sg:postcode":"P1P 1X2",
    "sg:province":"ON",
    "sg:tags":[
        "dealer"
    ],
    "wof:name":"Book Store",
    "wof:placetype":"venue"
},
  "geometry": {"coordinates":[-79.373756,44.919624],"type":"Point"}
}