{
  "type": "Feature",
  "properties": {
    "addr:full":"89 Av DE Lucerne Pointe-Claire QC H9R 2V1",
    "addr:postcode":"h9r 2v1",
    "addr:street":"89 Av De Lucerne",
    "iso:country":"CA",
    "sg:address":"89 Av DE Lucerne",
    "sg:city":"Pointe-Claire",
    "sg:classifiers":[
        {
            "category":"Restaurant",
            "type":"Food & Drink"
        }
    ],
    "sg:phone":"+1 514 426 0789",
    "sg:postcode":"H9R 2V1",
    "sg:province":"QC",
    "sg:tags":[
        "caterer"
    ],
    "wof:name":"Cuisine Anne Fraser Inc",
    "wof:placetype":"venue"
},
  "geometry": {"coordinates":[-73.78741455079999,45.4507141113],"type":"Point"}
}