{
  "type": "Feature",
  "properties": {
    "iso:country":"CA",
    "sg:address":"540 Clarke Rd # A",
    "sg:city":"Coquitlam",
    "sg:classifiers":[
        {
            "category":"Shopping",
            "subcategory":"Department Store",
            "type":"Retail Goods"
        }
    ],
    "sg:phone":"+1 604 937 7087",
    "sg:postcode":"V3J 3X5",
    "sg:province":"BC",
    "sg:tags":[
        "shop",
        "second",
        "hand"
    ],
    "wof:name":"Value Village Stores Ltd",
    "wof:placetype":"venue"
},
  "geometry": {"coordinates":[-122.890403748,49.2610664368],"type":"Point"}
}