{
  "type": "Feature",
  "properties": {
    "addr:full":"1494 Ontario St Cobourg ON K9A 4J7",
    "addr:housenumber":"1494",
    "addr:postcode":"k9a 4j7",
    "addr:street":"Ontario St",
    "iso:country":"CA",
    "sg:address":"1494 Ontario St",
    "sg:city":"Cobourg",
    "sg:classifiers":[
        {
            "category":"Building & Trades",
            "subcategory":"Landscaping Services",
            "type":"Services"
        }
    ],
    "sg:phone":"+1 905 373 0533",
    "sg:postcode":"K9A 4J7",
    "sg:province":"ON",
    "sg:tags":[
        "landscape",
        "contractor"
    ],
    "wof:name":"Skratt's Tree Svc",
    "wof:placetype":"venue"
},
  "geometry": {"coordinates":[-78.1863021851,43.9818687439],"type":"Point"}
}