{
  "type": "Feature",
  "properties": {
    "addr:full":"PO Box 72 Craigmyle AB T0J 0T0",
    "addr:housenumber":"po box 72;ab",
    "addr:postcode":"t0j 0t0",
    "addr:street":"Craigmyle",
    "iso:country":"CA",
    "sg:address":"PO Box 72",
    "sg:city":"Craigmyle",
    "sg:classifiers":[
        {
            "category":"Organizations",
            "subcategory":"Religious Organization",
            "type":"Services"
        }
    ],
    "sg:phone":"+1 403 665 2233",
    "sg:postcode":"T0J 0T0",
    "sg:province":"AB",
    "sg:tags":[
        "church"
    ],
    "wof:name":"Hutterian Brethern Church",
    "wof:placetype":"venue"
},
  "geometry": {"coordinates":[-112.24826049799999,51.6694488525],"type":"Point"}
}