{
  "type": "Feature",
  "properties": {
    "addr:full":"Chateauguay QC J6J 4Z2",
    "addr:postcode":"j6j 4z2",
    "iso:country":"CA",
    "sg:city":"Chateauguay",
    "sg:classifiers":[
        {
            "category":"Wholesale",
            "subcategory":"Motor Vehicles",
            "type":"Manufacturing & Wholesale Goods"
        }
    ],
    "sg:phone":"+1 450 699 6888",
    "sg:postcode":"J6J 4Z2",
    "sg:province":"QC",
    "sg:tags":[
        "body",
        "equipment",
        "truck"
    ],
    "wof:name":"C B Svc",
    "wof:placetype":"venue"
},
  "geometry": {"coordinates":[-73.69903600000001,45.351406],"type":"Point"}
}