{
  "type": "Feature",
  "properties": {
    "addr:full":"10 Boul Henri-Bourassa O # 100 Montreal QC H3L 3N3",
    "addr:housenumber":"10",
    "addr:postcode":"h3l 3n3",
    "addr:street":"Boul Henri-Bourassa O # 100",
    "iso:country":"CA",
    "sg:address":"10 Boul Henri-Bourassa O # 100",
    "sg:city":"Montreal",
    "sg:classifiers":[
        {
            "category":"Real Estate",
            "subcategory":"Real Estate Operator",
            "type":"Services"
        }
    ],
    "sg:phone":"+1 514 331 3125",
    "sg:postcode":"H3L 3N3",
    "sg:province":"QC",
    "sg:tags":[
        "apartment"
    ],
    "wof:name":"Jardins Ahuntsic",
    "wof:placetype":"venue"
},
  "geometry": {"coordinates":[-73.670601,45.550404],"type":"Point"}
}