{
  "type": "Feature",
  "properties": {
    "addr:full":"211 Rte 301 Portage-Du-Fort QC J0X 2T0",
    "addr:housenumber":"211",
    "addr:postcode":"j0x 2t0",
    "addr:street":"Rte 301",
    "iso:country":"CA",
    "sg:address":"211 Rte 301",
    "sg:city":"Portage-Du-Fort",
    "sg:classifiers":[
        {
            "category":"Manufacturing",
            "subcategory":"Paper Products",
            "type":"Manufacturing & Wholesale Goods"
        }
    ],
    "sg:phone":"+1 819 647 2281",
    "sg:postcode":"J0X 2T0",
    "sg:province":"QC",
    "sg:tags":[
        "pulp"
    ],
    "wof:name":"Smurfit-Stone Inc",
    "wof:placetype":"venue"
},
  "geometry": {"coordinates":[-76.66250599999999,45.591446],"type":"Point"}
}