{
  "type": "Feature",
  "properties": {
    "addr:full":"1406 Parkinson Rd Kelowna BC V1Z 3M6",
    "addr:housenumber":"1406",
    "addr:postcode":"v1z 3m6",
    "addr:street":"Parkinson Rd",
    "iso:country":"CA",
    "sg:address":"1406 Parkinson Rd",
    "sg:city":"Kelowna",
    "sg:classifiers":[
        {
            "category":"Manufacturing",
            "subcategory":"Electronics",
            "type":"Manufacturing & Wholesale Goods"
        }
    ],
    "sg:phone":"+1 250 769 0885",
    "sg:postcode":"V1Z 3M6",
    "sg:province":"BC",
    "sg:tags":[
        "instrument",
        "electronic"
    ],
    "wof:name":"Knights Bridge Technologies",
    "wof:placetype":"venue"
},
  "geometry": {"coordinates":[-119.550163,49.895012],"type":"Point"}
}