{
  "type": "Feature",
  "properties": {
    "addr:full":"12 Nelson St Leamington ON N8H 1G7",
    "addr:housenumber":"12",
    "addr:postcode":"n8h 1g7",
    "addr:street":"Nelson St",
    "iso:country":"CA",
    "sg:address":"12 Nelson St",
    "sg:city":"Leamington",
    "sg:classifiers":[
        {
            "category":"Health Services",
            "subcategory":"Doctor",
            "type":"Services"
        }
    ],
    "sg:phone":"+1 519 326 2609",
    "sg:postcode":"N8H 1G7",
    "sg:province":"ON",
    "sg:tags":[
        "dentist"
    ],
    "wof:name":"Kosy Management",
    "wof:placetype":"venue"
},
  "geometry": {"coordinates":[-82.599388,42.054256],"type":"Point"}
}