{
  "type": "Feature",
  "properties": {
    "addr:full":"2560 Matheson Blvd E Mississauga ON L4W 4Y9",
    "addr:housenumber":"2560",
    "addr:postcode":"l4w 4y9",
    "addr:street":"Matheson Blvd E",
    "iso:country":"CA",
    "sg:address":"2560 Matheson Blvd E",
    "sg:city":"Mississauga",
    "sg:classifiers":[
        {
            "category":"Freight",
            "type":"Transportation"
        }
    ],
    "sg:phone":"+1 905 602 8383",
    "sg:postcode":"L4W 4Y9",
    "sg:province":"ON",
    "wof:name":"Excel Freight Forwarding",
    "wof:placetype":"venue"
},
  "geometry": {"coordinates":[-79.602097,43.65955],"type":"Point"}
}