{
  "type": "Feature",
  "properties": {
    "addr:full":"Toronto ON M5S 3A5",
    "addr:postcode":"m5s 3a5",
    "iso:country":"CA",
    "sg:city":"Toronto",
    "sg:classifiers":[
        {
            "category":"Restaurant",
            "type":"Food & Drink"
        }
    ],
    "sg:phone":"+1 416 961 7116",
    "sg:postcode":"M5S 3A5",
    "sg:province":"ON",
    "sg:tags":[
        "cafe",
        "caterer"
    ],
    "wof:name":"Croissant Tree",
    "wof:placetype":"venue"
},
  "geometry": {"coordinates":[-79.387703,43.666058],"type":"Point"}
}