{
  "type": "Feature",
  "properties": {
    "addr:full":"259 Bank St Ottawa ON K2P 1X2",
    "addr:housenumber":"259",
    "addr:postcode":"k2p 1x2",
    "addr:street":"Bank St",
    "iso:country":"CA",
    "sg:address":"259 Bank St",
    "sg:city":"Ottawa",
    "sg:classifiers":[
        {
            "category":"Home & Garden",
            "subcategory":"Furniture",
            "type":"Retail Goods"
        }
    ],
    "sg:phone":"+1 613 232 7814",
    "sg:postcode":"K2P 1X2",
    "sg:province":"ON",
    "wof:name":"7th Heaven Futons",
    "wof:placetype":"venue"
},
  "geometry": {"coordinates":[-75.69696,45.416176],"type":"Point"}
}