{
  "type": "Feature",
  "properties": {
    "addr:full":"Lloydminster AB T9V 0Y9",
    "addr:postcode":"t9v 0y9",
    "iso:country":"CA",
    "sg:city":"Lloydminster",
    "sg:classifiers":[
        {
            "category":"Health Services",
            "subcategory":"Doctor",
            "type":"Services"
        }
    ],
    "sg:phone":"+1 780 875 4930",
    "sg:postcode":"T9V 0Y9",
    "sg:province":"AB",
    "sg:tags":[
        "physician",
        "surgeon"
    ],
    "wof:name":"Rogers, R M MD",
    "wof:placetype":"venue"
},
  "geometry": {"coordinates":[-110.010689,53.278687],"type":"Point"}
}