{
  "type": "Feature",
  "properties": {
    "addr:full":"255 Wellington Cres Winnipeg MB R3M 0A1",
    "addr:housenumber":"255",
    "addr:postcode":"r3m 0a1",
    "addr:street":"Wellington Cres",
    "iso:country":"CA",
    "sg:address":"255 Wellington Cres",
    "sg:city":"Winnipeg",
    "sg:classifiers":[
        {
            "category":"Real Estate",
            "subcategory":"Real Estate Operator",
            "type":"Services"
        }
    ],
    "sg:phone":"+1 204 453 1088",
    "sg:postcode":"R3M 0A1",
    "sg:province":"MB",
    "sg:tags":[
        "condominium"
    ],
    "wof:name":"255 Wellington",
    "wof:placetype":"venue"
},
  "geometry": {"coordinates":[-97.152023,49.873501],"type":"Point"}
}