{
  "type": "Feature",
  "properties": {
    "addr:full":"98 James St Parry Sound ON P2A 1T9",
    "addr:housenumber":"98",
    "addr:postcode":"p2a 1t9",
    "addr:street":"James St",
    "iso:country":"CA",
    "sg:address":"98 James St",
    "sg:city":"Parry Sound",
    "sg:classifiers":[
        {
            "category":"Food & Beverages",
            "subcategory":"Liquor & Beverages",
            "type":"Retail Goods"
        }
    ],
    "sg:phone":"+1 705 746 7041",
    "sg:postcode":"P2A 1T9",
    "sg:province":"ON",
    "sg:tags":[
        "equipment",
        "beer",
        "wine",
        "supply"
    ],
    "wof:name":"Wine Cellar Club",
    "wof:placetype":"venue"
},
  "geometry": {"coordinates":[-80.033852,45.347775],"type":"Point"}
}