{
  "type": "Feature",
  "properties": {
    "addr:full":"7 Plank Rd St. John's NL A1E 1H3",
    "addr:housenumber":"7",
    "addr:postcode":"a1e 1h3",
    "addr:street":"Plank Rd",
    "iso:country":"CA",
    "sg:address":"7 Plank Rd",
    "sg:city":"St. John's",
    "sg:classifiers":[
        {
            "category":"Real Estate",
            "subcategory":"Architect",
            "type":"Services"
        }
    ],
    "sg:phone":"+1 709 753 7132",
    "sg:postcode":"A1E 1H3",
    "sg:province":"NL",
    "wof:name":"Sheppard Case Architects Inc",
    "wof:placetype":"venue"
},
  "geometry": {"coordinates":[-52.7144126892,47.5544471741],"type":"Point"}
}