{
  "type": "Feature",
  "properties": {
    "addr:full":"9560 170 St NW Edmonton AB T5T 5R6",
    "addr:housenumber":"9560",
    "addr:postcode":"t5t 5r6",
    "addr:street":"170 St Nw",
    "iso:country":"CA",
    "sg:address":"9560 170 St NW",
    "sg:city":"Edmonton",
    "sg:classifiers":[
        {
            "category":"Shopping",
            "subcategory":"Computers & Home Electronics",
            "type":"Retail Goods"
        }
    ],
    "sg:phone":"+1 780 483 4590",
    "sg:postcode":"T5T 5R6",
    "sg:province":"AB",
    "sg:tags":[
        "radio",
        "television",
        "electronic",
        "equipment"
    ],
    "wof:name":"Future Shop",
    "wof:placetype":"venue"
},
  "geometry": {"coordinates":[-113.615493774,53.5330924988],"type":"Point"}
}