{
  "type": "Feature",
  "properties": {
    "iso:country":"CA",
    "sg:city":"Vancouver",
    "sg:classifiers":[
        {
            "category":"Manufacturing",
            "subcategory":"Printing",
            "type":"Manufacturing & Wholesale Goods"
        }
    ],
    "sg:phone":"+1 604 873 1800",
    "sg:postcode":"V5Y 3X2",
    "sg:province":"BC",
    "sg:tags":[
        "printer"
    ],
    "wof:name":"Reflex Printing",
    "wof:placetype":"venue"
},
  "geometry": {"coordinates":[-123.111755,49.263752],"type":"Point"}
}