{
  "type": "Feature",
  "properties": {
    "addr:full":"Surrey BC V3W 4E6",
    "addr:postcode":"v3w 4e6",
    "iso:country":"CA",
    "sg:city":"Surrey",
    "sg:classifiers":[
        {
            "category":"Professional",
            "subcategory":"Computer Services",
            "type":"Services"
        }
    ],
    "sg:phone":"+1 604 502 9666",
    "sg:postcode":"V3W 4E6",
    "sg:province":"BC",
    "sg:tags":[
        "repair"
    ],
    "wof:name":"Acura Computers & Electronics",
    "wof:placetype":"venue"
},
  "geometry": {"coordinates":[-122.868149,49.143177],"type":"Point"}
}