{
  "type": "Feature",
  "properties": {
    "addr:full":"5995 Perth Line 8 Kirkton ON N0K 1K0",
    "addr:housenumber":"5995",
    "addr:postcode":"n0k 1k0",
    "addr:street":"Perth Line 8 Kirkton",
    "iso:country":"CA",
    "sg:address":"5995 Perth Line 8",
    "sg:city":"Kirkton",
    "sg:classifiers":[
        {
            "category":"Building & Trades",
            "subcategory":"Equipment Rental",
            "type":"Services"
        }
    ],
    "sg:phone":"+1 519 229 6151",
    "sg:postcode":"N0K 1K0",
    "sg:province":"ON",
    "sg:tags":[
        "party"
    ],
    "wof:name":"Mc Brydes Rentals",
    "wof:placetype":"venue"
},
  "geometry": {"coordinates":[-81.313148,43.32391],"type":"Point"}
}