{
  "type": "Feature",
  "properties": {
    "iso:country":"CA",
    "sg:address":"1289 Boul Laird",
    "sg:city":"Mont-Royal",
    "sg:classifiers":[
        {
            "category":"Restaurant",
            "type":"Food & Drink"
        }
    ],
    "sg:phone":"+1 514 342 2166",
    "sg:postcode":"H3P 2S9",
    "sg:province":"QC",
    "wof:name":"Restaurant Del Verde",
    "wof:placetype":"venue"
},
  "geometry": {"coordinates":[-73.644096,45.517433],"type":"Point"}
}