{
  "type": "Feature",
  "properties": {
    "addr:full":"PO Box 243 STN Rosemount Montreal QC H1X 3B6",
    "addr:housenumber":"po",
    "addr:postcode":"h1x 3b6",
    "addr:street":"Box 243 Stn Rosemount",
    "iso:country":"CA",
    "sg:address":"PO Box 243 STN Rosemount",
    "sg:city":"Montreal",
    "sg:classifiers":[
        {
            "category":"Wholesale",
            "subcategory":"Non-durable Goods",
            "type":"Manufacturing & Wholesale Goods"
        }
    ],
    "sg:phone":"+1 514 322 3297",
    "sg:postcode":"H1X 3B6",
    "sg:province":"QC",
    "sg:tags":[
        "pet",
        "supply"
    ],
    "wof:name":"International Pet Supplies",
    "wof:placetype":"venue"
},
  "geometry": {"coordinates":[-73.55439,45.512287],"type":"Point"}
}