{
  "type": "Feature",
  "properties": {
    "iso:country":"CA",
    "sg:address":"107 Wellington St",
    "sg:city":"Kingston",
    "sg:classifiers":[
        {
            "category":"Social Services",
            "type":"Services"
        }
    ],
    "sg:phone":"+1 613 544 1671",
    "sg:postcode":"K7L 3C6",
    "sg:province":"ON",
    "sg:tags":[
        "organization",
        "health",
        "mental",
        "welfare"
    ],
    "wof:name":"Frontenac Community Mental",
    "wof:placetype":"venue"
},
  "geometry": {"coordinates":[-76.4840393066,44.2289733887],"type":"Point"}
}