{
  "type": "Feature",
  "properties": {
    "addr:full":"14 Thompson Cres Erin ON N0B 1T0",
    "addr:housenumber":"14",
    "addr:postcode":"n0b 1t0",
    "addr:street":"Thompson Cres",
    "iso:country":"CA",
    "sg:address":"14 Thompson Cres",
    "sg:city":"Erin",
    "sg:classifiers":[
        {
            "category":"Manufacturing",
            "subcategory":"Apparel",
            "type":"Manufacturing & Wholesale Goods"
        }
    ],
    "sg:phone":"+1 519 833 9306",
    "sg:postcode":"N0B 1T0",
    "sg:province":"ON",
    "sg:tags":[
        "flag",
        "banner"
    ],
    "wof:name":"Kennedy's Specialty Sewing Ltd",
    "wof:placetype":"venue"
},
  "geometry": {"coordinates":[-80.077003,43.781746],"type":"Point"}
}