{
  "type": "Feature",
  "properties": {
    "addr:full":"2150 Steel Rd Prince George BC V2K 5B7",
    "addr:housenumber":"2150",
    "addr:postcode":"v2k 5b7",
    "addr:street":"Steel Rd",
    "iso:country":"CA",
    "sg:address":"2150 Steel Rd",
    "sg:city":"Prince George",
    "sg:classifiers":[
        {
            "category":"Mining & Drilling",
            "type":"Manufacturing & Wholesale Goods"
        }
    ],
    "sg:phone":"+1 250 962 7273",
    "sg:postcode":"V2K 5B7",
    "sg:province":"BC",
    "sg:tags":[
        "building",
        "road",
        "contractor"
    ],
    "wof:name":"North American Construction",
    "wof:placetype":"venue"
},
  "geometry": {"coordinates":[-122.76498413100001,53.9722595215],"type":"Point"}
}