{
  "type": "Feature",
  "properties": {
    "addr:full":"48710 Chilliwack Lake Rd Chilliwack BC V4Z 1A6",
    "addr:postcode":"48710;v4z 1a6",
    "addr:street":"Lake Rd",
    "iso:country":"CA",
    "sg:address":"48710 Chilliwack Lake Rd",
    "sg:city":"Chilliwack",
    "sg:classifiers":[
        {
            "category":"Restaurant",
            "type":"Food & Drink"
        }
    ],
    "sg:phone":"+1 604 824 1551",
    "sg:postcode":"V4Z 1A6",
    "sg:province":"BC",
    "wof:name":"Pointa Vista Cafe & General",
    "wof:placetype":"venue"
},
  "geometry": {"coordinates":[-121.95320100000001,49.093601],"type":"Point"}
}