{
  "type": "Feature",
  "properties": {
    "iso:country":"CA",
    "sg:address":"6742 Rue Saint-Denis",
    "sg:city":"Montreal",
    "sg:classifiers":[
        {
            "category":"Manufacturing",
            "subcategory":"Printing",
            "type":"Manufacturing & Wholesale Goods"
        }
    ],
    "sg:phone":"+1 514 277 6178",
    "sg:postcode":"H2S 2S2",
    "sg:province":"QC",
    "sg:tags":[
        "publisher"
    ],
    "wof:name":"Recherches Amerindiennes",
    "wof:placetype":"venue"
},
  "geometry": {"coordinates":[-73.609375,45.535823822],"type":"Point"}
}