{
  "type": "Feature",
  "properties": {
    "addr:full":"5009 50 St Drayton Valley AB T7A 1S8",
    "addr:housenumber":"5009",
    "addr:postcode":"t7a 1s8",
    "addr:street":"50 St",
    "iso:country":"CA",
    "sg:address":"5009 50 St",
    "sg:city":"Drayton Valley",
    "sg:classifiers":[
        {
            "category":"Shopping",
            "subcategory":"Clothing, Apparel, & Fashions",
            "type":"Retail Goods"
        }
    ],
    "sg:phone":"+1 780 542 5414",
    "sg:postcode":"T7A 1S8",
    "sg:province":"AB",
    "wof:name":"Saan Stores Ltd",
    "wof:placetype":"venue"
},
  "geometry": {"coordinates":[-114.976395,53.221653],"type":"Point"}
}