{
  "type": "Feature",
  "properties": {
    "addr:full":"3541 River Rd W Delta BC V4K 3N2",
    "addr:housenumber":"3541",
    "addr:postcode":"v4k 3n2",
    "addr:street":"River Rd W",
    "iso:country":"CA",
    "sg:address":"3541 River Rd W",
    "sg:city":"Delta",
    "sg:classifiers":[
        {
            "category":"Building & Trades",
            "subcategory":"Construction",
            "type":"Services"
        }
    ],
    "sg:phone":"+1 604 946 2417",
    "sg:postcode":"V4K 3N2",
    "sg:province":"BC",
    "sg:tags":[
        "maker",
        "cabinet"
    ],
    "wof:name":"Solo Woodcraft Ltd",
    "wof:placetype":"venue"
},
  "geometry": {"coordinates":[-123.125404,49.080948],"type":"Point"}
}