{
  "type": "Feature",
  "properties": {
    "addr:full":"Montreal QC H3X 1V5",
    "addr:postcode":"h3x 1v5",
    "iso:country":"CA",
    "sg:city":"Montreal",
    "sg:classifiers":[
        {
            "category":"Health Services",
            "subcategory":"Medical Lab",
            "type":"Services"
        }
    ],
    "sg:phone":"+1 514 484 9881",
    "sg:postcode":"H3X 1V5",
    "sg:province":"QC",
    "sg:tags":[
        "laboratory"
    ],
    "wof:name":"Laboratoire Dentaire A-1",
    "wof:placetype":"venue"
},
  "geometry": {"coordinates":[-73.6309967041,45.4818725586],"type":"Point"}
}