{
  "type": "Feature",
  "properties": {
    "addr:full":"14729 Yonge St Aurora ON L4G 1N1",
    "addr:housenumber":"14729",
    "addr:postcode":"l4g 1n1",
    "addr:street":"Yonge St",
    "iso:country":"CA",
    "sg:address":"14729 Yonge St",
    "sg:city":"Aurora",
    "sg:classifiers":[
        {
            "category":"Shopping",
            "subcategory":"Pharmacy",
            "type":"Retail Goods"
        }
    ],
    "sg:phone":"+1 905 727 4275",
    "sg:postcode":"L4G 1N1",
    "sg:province":"ON",
    "wof:name":"Shoppers Drug Mart",
    "wof:placetype":"venue"
},
  "geometry": {"coordinates":[-79.46435546879999,43.9872093201],"type":"Point"}
}