{
  "type": "Feature",
  "properties": {
    "addr:full":"9935 75 Ave NW Edmonton AB T6E 1J3",
    "addr:housenumber":"9935",
    "addr:postcode":"t6e 1j3",
    "addr:street":"75 Ave Nw",
    "iso:country":"CA",
    "sg:address":"9935 75 Ave NW",
    "sg:city":"Edmonton",
    "sg:classifiers":[
        {
            "category":"Wholesale",
            "subcategory":"Machinery & Supplies",
            "type":"Manufacturing & Wholesale Goods"
        }
    ],
    "sg:phone":"+1 780 438 1661",
    "sg:postcode":"T6E 1J3",
    "sg:province":"AB",
    "sg:tags":[
        "tank"
    ],
    "wof:name":"Tiw Steel Platework",
    "wof:placetype":"venue"
},
  "geometry": {"coordinates":[-113.487183,53.511135],"type":"Point"}
}