{
  "type": "Feature",
  "properties": {
    "addr:full":"451 Christie St Toronto ON M6G 3C7",
    "addr:housenumber":"451",
    "addr:postcode":"m6g 3c7",
    "addr:street":"Christie St",
    "iso:country":"CA",
    "sg:address":"451 Christie St",
    "sg:city":"Toronto",
    "sg:classifiers":[
        {
            "category":"Professional",
            "subcategory":"Art Services",
            "type":"Services"
        }
    ],
    "sg:phone":"+1 416 531 6006",
    "sg:postcode":"M6G 3C7",
    "sg:province":"ON",
    "sg:tags":[
        "graphic",
        "designer"
    ],
    "wof:name":"Mental Art & Design",
    "wof:placetype":"venue"
},
  "geometry": {"coordinates":[-79.422768,43.675404],"type":"Point"}
}