{
  "type": "Feature",
  "properties": {
    "iso:country":"CA",
    "sg:address":"267 Rue Saint-Charles O",
    "sg:city":"Longueuil",
    "sg:classifiers":[
        {
            "category":"Manufacturing",
            "subcategory":"Printing",
            "type":"Manufacturing & Wholesale Goods"
        }
    ],
    "sg:phone":"+1 450 646 3333",
    "sg:postcode":"J4H 1E3",
    "sg:province":"QC",
    "sg:tags":[
        "newspaper"
    ],
    "wof:name":"Courrier Du Sud",
    "wof:placetype":"venue"
},
  "geometry": {"coordinates":[-73.510521,45.537655],"type":"Point"}
}