{
  "type": "Feature",
  "properties": {
    "addr:full":"165 Erie St Stratford ON N5A 2M6",
    "addr:housenumber":"165",
    "addr:postcode":"n5a 2m6",
    "addr:street":"Erie St",
    "iso:country":"CA",
    "sg:address":"165 Erie St",
    "sg:city":"Stratford",
    "sg:classifiers":[
        {
            "category":"Personal",
            "type":"Services"
        }
    ],
    "sg:phone":"+1 519 271 5367",
    "sg:postcode":"N5A 2M6",
    "sg:province":"ON",
    "sg:tags":[
        "therapist",
        "massage"
    ],
    "wof:name":"Art of Massage",
    "wof:placetype":"venue"
},
  "geometry": {"coordinates":[-80.985321,43.368217],"type":"Point"}
}