{
  "type": "Feature",
  "properties": {
    "addr:full":"St Albert AB T8N 2E7",
    "addr:postcode":"t8n 2e7",
    "iso:country":"CA",
    "sg:city":"St Albert",
    "sg:classifiers":[
        {
            "category":"Restaurant",
            "type":"Food & Drink"
        }
    ],
    "sg:phone":"+1 780 419 7060",
    "sg:postcode":"T8N 2E7",
    "sg:province":"AB",
    "wof:name":"Koto Japanese Restaurant",
    "wof:placetype":"venue"
},
  "geometry": {"coordinates":[-113.608864,53.62233],"type":"Point"}
}