{
  "type": "Feature",
  "properties": {
    "addr:full":"3121 Rue Principale Saint-Ferdinand QC G0N 1N0",
    "addr:housenumber":"3121",
    "addr:postcode":"g0n 1n0",
    "addr:street":"Rue Principale",
    "iso:country":"CA",
    "sg:address":"3121 Rue Principale",
    "sg:city":"Saint-Ferdinand",
    "sg:classifiers":[
        {
            "category":"Recreation",
            "type":"Entertainment"
        }
    ],
    "sg:phone":"+1 418 428 3505",
    "sg:postcode":"G0N 1N0",
    "sg:province":"QC",
    "sg:tags":[
        "campground",
        "provincial",
        "parks"
    ],
    "wof:name":"Camping Plage DE LA Baie",
    "wof:placetype":"venue"
},
  "geometry": {"coordinates":[-71.58182499999999,46.126438],"type":"Point"}
}