{
  "type": "Feature",
  "properties": {
    "addr:full":"111 Rue Dumont Vaudreuil-Dorion QC J7V 1W9",
    "addr:housenumber":"111",
    "addr:postcode":"j7v 1w9",
    "addr:street":"Rue Dumont",
    "iso:country":"CA",
    "sg:address":"111 Rue Dumont",
    "sg:city":"Vaudreuil-Dorion",
    "sg:classifiers":[
        {
            "category":"Personal",
            "subcategory":"Tanning Parlor",
            "type":"Services"
        }
    ],
    "sg:phone":"+1 450 424 2633",
    "sg:postcode":"J7V 1W9",
    "sg:province":"QC",
    "sg:tags":[
        "salon"
    ],
    "wof:name":"Dorion O Soleil",
    "wof:placetype":"venue"
},
  "geometry": {"coordinates":[-74.01042200000001,45.384506],"type":"Point"}
}