{
  "type": "Feature",
  "properties": {
    "addr:full":"512 George St Fredericton NB E3B 1K1",
    "addr:housenumber":"512",
    "addr:postcode":"e3b 1k1",
    "addr:street":"George St",
    "iso:country":"CA",
    "sg:address":"512 George St",
    "sg:city":"Fredericton",
    "sg:classifiers":[
        {
            "category":"Health Services",
            "subcategory":"Optometrist",
            "type":"Services"
        }
    ],
    "sg:phone":"+1 506 458 8986",
    "sg:postcode":"E3B 1K1",
    "sg:province":"NB",
    "wof:name":"Lenehan, T Wayne OD",
    "wof:placetype":"venue"
},
  "geometry": {"coordinates":[-66.6429901123,45.9589195251],"type":"Point"}
}