{
  "type": "Feature",
  "properties": {
    "addr:full":"3585 Grandview Hwy Vancouver BC V5M 2G7",
    "addr:housenumber":"3585",
    "addr:postcode":"v5m 2g7",
    "addr:street":"Grandview Hwy",
    "iso:country":"CA",
    "sg:address":"3585 Grandview Hwy",
    "sg:city":"Vancouver",
    "sg:classifiers":[
        {
            "category":"Professional",
            "subcategory":"Engineering",
            "type":"Services"
        }
    ],
    "sg:phone":"+1 604 431 3894",
    "sg:postcode":"V5M 2G7",
    "sg:province":"BC",
    "sg:tags":[
        "engineer"
    ],
    "wof:name":"Sks Engineering",
    "wof:placetype":"venue"
},
  "geometry": {"coordinates":[-123.026573181,49.2583656311],"type":"Point"}
}