{
  "type": "Feature",
  "properties": {
    "addr:full":"500 Kingsway Vancouver BC V5T 3J9",
    "addr:housenumber":"500",
    "addr:postcode":"v5t 3j9",
    "addr:street":"Kingsway",
    "iso:country":"CA",
    "sg:address":"500 Kingsway",
    "sg:city":"Vancouver",
    "sg:classifiers":[
        {
            "category":"Travel",
            "subcategory":"Travel Agent",
            "type":"Entertainment"
        }
    ],
    "sg:phone":"+1 604 879 0914",
    "sg:postcode":"V5T 3J9",
    "sg:province":"BC",
    "sg:tags":[
        "agency",
        "bureau"
    ],
    "wof:name":"Oscar Travel Svc Ltd",
    "wof:placetype":"venue"
},
  "geometry": {"coordinates":[-123.09312439,49.2577476501],"type":"Point"}
}