{
  "type": "Feature",
  "properties": {
    "addr:full":"435 Edenderry Line #2 Ennismore ON K0L 1T0",
    "addr:housenumber":"435",
    "addr:postcode":"k0l 1t0",
    "addr:street":"Edenderry Line # 2 Ennismore",
    "iso:country":"CA",
    "sg:address":"435 Edenderry Line #2",
    "sg:city":"Ennismore",
    "sg:classifiers":[
        {
            "category":"Building & Trades",
            "subcategory":"Construction",
            "type":"Services"
        }
    ],
    "sg:phone":"+1 705 292 8957",
    "sg:postcode":"K0L 1T0",
    "sg:province":"ON",
    "sg:tags":[
        "fire",
        "restoration",
        "general",
        "damage",
        "contractor"
    ],
    "wof:name":"John Newman Contracting Ltd",
    "wof:placetype":"venue"
},
  "geometry": {"coordinates":[-78.42817700000001,44.410664],"type":"Point"}
}