{
  "type": "Feature",
  "properties": {
    "addr:full":"850 Rue Godbout Drummondville QC J2C 5C9",
    "addr:housenumber":"850",
    "addr:postcode":"j2c 5c9",
    "addr:street":"Rue Godbout",
    "iso:country":"CA",
    "sg:address":"850 Rue Godbout",
    "sg:city":"Drummondville",
    "sg:classifiers":[
        {
            "category":"Building & Trades",
            "subcategory":"Electrical",
            "type":"Services"
        }
    ],
    "sg:phone":"+1 819 472 6295",
    "sg:postcode":"J2C 5C9",
    "sg:province":"QC",
    "sg:tags":[
        "electric",
        "contractor"
    ],
    "wof:name":"Techno-Pro Electrique Drmvl",
    "wof:placetype":"venue"
},
  "geometry": {"coordinates":[-72.50737762449999,45.8921203613],"type":"Point"}
}