{
  "type": "Feature",
  "properties": {
    "iso:country":"CA",
    "sg:address":"8155 Boul Langelier",
    "sg:city":"Saint-Leonard",
    "sg:classifiers":[
        {
            "category":"Wholesale",
            "subcategory":"Auto Parts",
            "type":"Manufacturing & Wholesale Goods"
        }
    ],
    "sg:phone":"+1 514 382 4333",
    "sg:postcode":"H1P 2B7",
    "sg:province":"QC",
    "sg:tags":[
        "automobile",
        "rebuilt"
    ],
    "wof:name":"Osaka Japanese Auto Parts Inc",
    "wof:placetype":"venue"
},
  "geometry": {"coordinates":[-73.5835800171,45.5958976746],"type":"Point"}
}