{
  "type": "Feature",
  "properties": {
    "iso:country":"CA",
    "sg:city":"Rock Forest",
    "sg:classifiers":[
        {
            "category":"Recreation",
            "type":"Entertainment"
        }
    ],
    "sg:phone":"+1 819 563 3533",
    "sg:postcode":"J1N 1X5",
    "sg:province":"QC",
    "sg:tags":[
        "hall",
        "auditorium"
    ],
    "wof:name":"Hotellerie Le Boulevard",
    "wof:placetype":"venue"
},
  "geometry": {"coordinates":[-71.9629821777,45.3835639954],"type":"Point"}
}