{
  "type": "Feature",
  "properties": {
    "addr:full":"5028 49th St Gibbons AB T0A 1N0",
    "addr:housenumber":"5028",
    "addr:postcode":"t0a 1n0",
    "addr:street":"49Th St",
    "iso:country":"CA",
    "sg:address":"5028 49th St",
    "sg:city":"Gibbons",
    "sg:classifiers":[
        {
            "category":"Professional",
            "subcategory":"Lawyer & Legal Services",
            "type":"Services"
        }
    ],
    "sg:phone":"+1 780 942 4343",
    "sg:postcode":"T0A 1N0",
    "sg:province":"AB",
    "sg:tags":[
        "attorney"
    ],
    "wof:name":"Putnam & Lawson",
    "wof:placetype":"venue"
},
  "geometry": {"coordinates":[-113.32754516599999,53.8287315369],"type":"Point"}
}