{
  "type": "Feature",
  "properties": {
    "addr:full":"1133 Yonge St Toronto ON M4T 2Y7",
    "addr:housenumber":"1133",
    "addr:postcode":"m4t 2y7",
    "addr:street":"Yonge St",
    "iso:country":"CA",
    "sg:address":"1133 Yonge St",
    "sg:city":"Toronto",
    "sg:classifiers":[
        {
            "category":"Mining & Drilling",
            "type":"Manufacturing & Wholesale Goods"
        }
    ],
    "sg:phone":"+1 416 924 4551",
    "sg:postcode":"M4T 2Y7",
    "sg:province":"ON",
    "sg:tags":[
        "company"
    ],
    "wof:name":"Sherritt International Corp",
    "wof:placetype":"venue"
},
  "geometry": {"coordinates":[-79.3912353516,43.6815872192],"type":"Point"}
}