{
  "type": "Feature",
  "properties": {
    "addr:full":"1455 1st Ave W Owen Sound ON N4K 4K8",
    "addr:housenumber":"1455",
    "addr:postcode":"n4k 4k8",
    "addr:street":"1St Ave W",
    "iso:country":"CA",
    "sg:address":"1455 1st Ave W",
    "sg:city":"Owen Sound",
    "sg:classifiers":[
        {
            "category":"Professional",
            "type":"Services"
        }
    ],
    "sg:phone":"+1 519 376 9890",
    "sg:postcode":"N4K 4K8",
    "sg:province":"ON",
    "sg:tags":[
        "marina",
        "establishment"
    ],
    "wof:name":"West Side Boat Launch",
    "wof:placetype":"venue"
},
  "geometry": {"coordinates":[-80.945076,44.576744],"type":"Point"}
}