{
  "type": "Feature",
  "properties": {
    "addr:full":"8 Yonge St Toronto ON M5E 1Y1",
    "addr:housenumber":"8",
    "addr:postcode":"m5e 1y1",
    "addr:street":"Yonge St",
    "iso:country":"CA",
    "sg:address":"8 Yonge St",
    "sg:city":"Toronto",
    "sg:classifiers":[
        {
            "category":"Organizations",
            "subcategory":"Professional Association",
            "type":"Services"
        }
    ],
    "sg:phone":"+1 416 482 9341",
    "sg:postcode":"M5E 1Y1",
    "sg:province":"ON",
    "sg:tags":[
        "club"
    ],
    "wof:name":"Saltwhistle Bay Club",
    "wof:placetype":"venue"
},
  "geometry": {"coordinates":[-79.375114,43.64233],"type":"Point"}
}