{
  "type": "Feature",
  "properties": {
    "addr:full":"22 Clarence St W Port Colborne ON L3K 3E8",
    "addr:housenumber":"22",
    "addr:postcode":"l3k 3e8",
    "addr:street":"Clarence St W",
    "iso:country":"CA",
    "sg:address":"22 Clarence St W",
    "sg:city":"Port Colborne",
    "sg:classifiers":[
        {
            "category":"Government",
            "subcategory":"Office",
            "type":"Public Place"
        }
    ],
    "sg:phone":"+1 905 835 5454",
    "sg:postcode":"L3K 3E8",
    "sg:province":"ON",
    "sg:tags":[
        "member",
        "legislative",
        "assembly"
    ],
    "wof:name":"Maloney, John",
    "wof:placetype":"venue"
},
  "geometry": {"coordinates":[-79.250869751,42.8861083984],"type":"Point"}
}