{
  "type": "Feature",
  "properties": {
    "addr:full":"366 Centre St Petrolia ON N0N 1R0",
    "addr:housenumber":"366",
    "addr:postcode":"n0n 1r0",
    "addr:street":"Centre St",
    "iso:country":"CA",
    "sg:address":"366 Centre St",
    "sg:city":"Petrolia",
    "sg:classifiers":[
        {
            "category":"Manufacturing",
            "subcategory":"Metals",
            "type":"Manufacturing & Wholesale Goods"
        }
    ],
    "sg:phone":"+1 519 882 3910",
    "sg:postcode":"N0N 1R0",
    "sg:province":"ON",
    "sg:tags":[
        "steel"
    ],
    "wof:name":"Container Design Svc Ltd",
    "wof:placetype":"venue"
},
  "geometry": {"coordinates":[-82.148155,42.884102],"type":"Point"}
}