{
  "type": "Feature",
  "properties": {
    "addr:full":"1218 Davie St Vancouver BC V6E 1N3",
    "addr:housenumber":"1218",
    "addr:postcode":"v6e 1n3",
    "addr:street":"Davie St",
    "iso:country":"CA",
    "sg:address":"1218 Davie St",
    "sg:city":"Vancouver",
    "sg:classifiers":[
        {
            "category":"Shopping",
            "subcategory":"Gifts & Souvenirs",
            "type":"Retail Goods"
        }
    ],
    "sg:phone":"+1 604 669 3223",
    "sg:postcode":"V6E 1N3",
    "sg:province":"BC",
    "sg:tags":[
        "shop"
    ],
    "wof:name":"Super 99 Ctr",
    "wof:placetype":"venue"
},
  "geometry": {"coordinates":[-123.133934,49.281963],"type":"Point"}
}