{
  "type": "Feature",
  "properties": {
    "iso:country":"CA",
    "sg:address":"275 Wellington St",
    "sg:city":"St Thomas",
    "sg:classifiers":[
        {
            "category":"Autos & Motor Vehicles",
            "subcategory":"Automobile Sales",
            "type":"Retail Goods"
        }
    ],
    "sg:phone":"+1 519 633 2200",
    "sg:postcode":"N5R 2S6",
    "sg:province":"ON",
    "sg:tags":[
        "car",
        "dealer"
    ],
    "wof:name":"Elgin Chrysler Ltd",
    "wof:placetype":"venue"
},
  "geometry": {"coordinates":[-81.1779251099,42.7751045227],"type":"Point"}
}