{
  "type": "Feature",
  "properties": {
    "addr:full":"37 Carleton Crt Dorchester ON N0L 1G2",
    "addr:housenumber":"37",
    "addr:postcode":"n0l 1g2",
    "addr:street":"Carleton Crt",
    "iso:country":"CA",
    "sg:address":"37 Carleton Crt",
    "sg:city":"Dorchester",
    "sg:classifiers":[
        {
            "category":"Insurance",
            "subcategory":"Insurance Agent",
            "type":"Services"
        }
    ],
    "sg:phone":"+1 519 268 8143",
    "sg:postcode":"N0L 1G2",
    "sg:province":"ON",
    "wof:name":"Rich, Brent",
    "wof:placetype":"venue"
},
  "geometry": {"coordinates":[-81.060005,42.986816],"type":"Point"}
}