{
  "type": "Feature",
  "properties": {
    "addr:full":"19 Rue DE Liege E Montreal QC H2P 1H8",
    "addr:housenumber":"19",
    "addr:postcode":"h2p 1h8",
    "addr:street":"Rue De Liege E",
    "iso:country":"CA",
    "sg:address":"19 Rue DE Liege E",
    "sg:city":"Montreal",
    "sg:classifiers":[
        {
            "category":"Retail",
            "subcategory":"Repair Shop",
            "type":"Services"
        }
    ],
    "sg:phone":"+1 514 388 6336",
    "sg:postcode":"H2P 1H8",
    "sg:province":"QC",
    "sg:tags":[
        "antique",
        "restoring"
    ],
    "wof:name":"Boutic Tac Toc",
    "wof:placetype":"venue"
},
  "geometry": {"coordinates":[-73.63755,45.540977],"type":"Point"}
}