{
  "type": "Feature",
  "properties": {
    "iso:country":"CA",
    "sg:city":"Regina",
    "sg:classifiers":[
        {
            "category":"Manufacturing",
            "subcategory":"Retail Goods",
            "type":"Manufacturing & Wholesale Goods"
        }
    ],
    "sg:phone":"+1 306 586 3644",
    "sg:postcode":"S4S 5C8",
    "sg:province":"SK",
    "sg:tags":[
        "marking",
        "devices"
    ],
    "wof:name":"Telic Marking Devices",
    "wof:placetype":"venue"
},
  "geometry": {"coordinates":[-104.609901428,50.4079399109],"type":"Point"}
}