{
  "type": "Feature",
  "properties": {
    "addr:full":"36 2nd St SW Portage LA Prairie MB R1N 2A1",
    "addr:housenumber":"36",
    "addr:postcode":"r1n 2a1",
    "addr:street":"2Nd St Sw",
    "iso:country":"CA",
    "sg:address":"36 2nd St SW",
    "sg:city":"Portage LA Prairie",
    "sg:classifiers":[
        {
            "category":"Social Services",
            "subcategory":"Child Care",
            "type":"Services"
        }
    ],
    "sg:phone":"+1 204 857 6226",
    "sg:postcode":"R1N 2A1",
    "sg:province":"MB",
    "wof:name":"Portage Daycare Ctr Inc",
    "wof:placetype":"venue"
},
  "geometry": {"coordinates":[-98.2935562134,49.9722976685],"type":"Point"}
}