{
  "type": "Feature",
  "properties": {
    "addr:full":"310 Viner Line Ennismore ON K0L 1T0",
    "addr:housenumber":"310",
    "addr:postcode":"k0l 1t0",
    "addr:street":"Viner Line",
    "iso:country":"CA",
    "sg:address":"310 Viner Line",
    "sg:city":"Ennismore",
    "sg:classifiers":[
        {
            "category":"Retail",
            "subcategory":"Laundry & Dry Cleaning",
            "type":"Services"
        }
    ],
    "sg:phone":"+1 705 292 9680",
    "sg:postcode":"K0L 1T0",
    "sg:province":"ON",
    "sg:tags":[
        "fire",
        "cleaners",
        "rug",
        "damage",
        "restoration",
        "carpet"
    ],
    "wof:name":"Advantage Disaster & Rstrtn",
    "wof:placetype":"venue"
},
  "geometry": {"coordinates":[-78.42817687989999,44.4106636047],"type":"Point"}
}