{
  "type": "Feature",
  "properties": {
    "iso:country":"CA",
    "sg:address":"3185 Askin Ave",
    "sg:city":"Windsor",
    "sg:classifiers":[
        {
            "category":"Real Estate",
            "subcategory":"Real Estate Agent",
            "type":"Services"
        }
    ],
    "sg:phone":"+1 519 562 2222",
    "sg:postcode":"N9E 3J4",
    "sg:province":"ON",
    "sg:tags":[
        "inspection"
    ],
    "wof:name":"A Complete Home Inspection Svc",
    "wof:placetype":"venue"
},
  "geometry": {"coordinates":[-83.0344238281,42.2613296509],"type":"Point"}
}