{
  "type": "Feature",
  "properties": {
    "addr:full":"61 Airport Rd Winnipeg MB R3H 0V5",
    "addr:housenumber":"61",
    "addr:postcode":"r3h 0v5",
    "addr:street":"Airport Rd",
    "iso:country":"CA",
    "sg:address":"61 Airport Rd",
    "sg:city":"Winnipeg",
    "sg:classifiers":[
        {
            "category":"Manufacturing",
            "subcategory":"Tools & Machinery",
            "type":"Manufacturing & Wholesale Goods"
        }
    ],
    "sg:phone":"+1 204 632 1000",
    "sg:postcode":"R3H 0V5",
    "sg:province":"MB",
    "sg:tags":[
        "farm",
        "equipment",
        "screening",
        "sifting"
    ],
    "wof:name":"Arrow Corp Inc",
    "wof:placetype":"venue"
},
  "geometry": {"coordinates":[-97.2177886963,49.915058136],"type":"Point"}
}