{
  "type": "Feature",
  "properties": {
    "addr:full":"75 Centennial Pky N Hamilton ON L8E 2P2",
    "addr:housenumber":"75",
    "addr:postcode":"l8e 2p2",
    "addr:street":"Centennial Pky N",
    "iso:country":"CA",
    "sg:address":"75 Centennial Pky N",
    "sg:city":"Hamilton",
    "sg:classifiers":[
        {
            "category":"Shopping",
            "subcategory":"Jewelry",
            "type":"Retail Goods"
        }
    ],
    "sg:phone":"+1 905 561 5740",
    "sg:postcode":"L8E 2P2",
    "sg:province":"ON",
    "sg:tags":[
        "jeweler"
    ],
    "wof:name":"Peoples Jewellers",
    "wof:placetype":"venue"
},
  "geometry": {"coordinates":[-79.763451,43.230404],"type":"Point"}
}