{
  "type": "Feature",
  "properties": {
    "addr:full":"90 Esna Park Dr Markham ON L3R 2R7",
    "addr:housenumber":"90",
    "addr:postcode":"l3r 2r7",
    "addr:street":"Esna Park Dr",
    "iso:country":"CA",
    "sg:address":"90 Esna Park Dr",
    "sg:city":"Markham",
    "sg:classifiers":[
        {
            "category":"Wholesale",
            "subcategory":"Durable Goods & Equipment",
            "type":"Manufacturing & Wholesale Goods"
        }
    ],
    "sg:phone":"+1 416 274 3827",
    "sg:postcode":"L3R 2R7",
    "sg:province":"ON",
    "sg:tags":[
        "fire",
        "extinguisher",
        "protection"
    ],
    "wof:name":"Sampson Fire Equipment",
    "wof:placetype":"venue"
},
  "geometry": {"coordinates":[-79.3398361206,43.8275680542],"type":"Point"}
}