{
  "type": "Feature",
  "properties": {
    "addr:full":"Surrey BC V3R 0Y3",
    "addr:postcode":"v3r 0y3",
    "iso:country":"CA",
    "sg:city":"Surrey",
    "sg:classifiers":[
        {
            "category":"Building & Trades",
            "subcategory":"Construction",
            "type":"Services"
        }
    ],
    "sg:phone":"+1 604 583 1174",
    "sg:postcode":"V3R 0Y3",
    "sg:province":"BC",
    "sg:tags":[
        "general",
        "contractor"
    ],
    "wof:name":"Metro-Can Construction Ltd",
    "wof:placetype":"venue"
},
  "geometry": {"coordinates":[-122.800613403,49.192653656],"type":"Point"}
}