{
  "type": "Feature",
  "properties": {
    "iso:country":"CA",
    "sg:city":"Beausejour",
    "sg:classifiers":[
        {
            "category":"Wholesale",
            "subcategory":"Non-durable Goods",
            "type":"Manufacturing & Wholesale Goods"
        }
    ],
    "sg:phone":"+1 204 268 4510",
    "sg:postcode":"R0E 0C0",
    "sg:province":"MB",
    "sg:tags":[
        "advertising"
    ],
    "wof:name":"Eastman Promotional Products",
    "wof:placetype":"venue"
},
  "geometry": {"coordinates":[-96.51429748539999,50.0617866516],"type":"Point"}
}