{
  "type": "Feature",
  "properties": {
    "addr:full":"1551 Stage Cache Creek BC V0K 1H0",
    "addr:housenumber":"1551",
    "addr:postcode":"v0k 1h0",
    "addr:street":"Stage",
    "iso:country":"CA",
    "sg:address":"1551 Stage",
    "sg:city":"Cache Creek",
    "sg:classifiers":[
        {
            "category":"Organizations",
            "subcategory":"Religious Organization",
            "type":"Services"
        }
    ],
    "sg:phone":"+1 250 457 6463",
    "sg:postcode":"V0K 1H0",
    "sg:province":"BC",
    "sg:tags":[
        "church"
    ],
    "wof:name":"Pentecostal Church",
    "wof:placetype":"venue"
},
  "geometry": {"coordinates":[-121.311302,50.813286],"type":"Point"}
}