{
  "type": "Feature",
  "properties": {
    "addr:full":"LA Tuque QC G9X 3Z8",
    "addr:postcode":"g9x 3z8",
    "iso:country":"CA",
    "sg:city":"LA Tuque",
    "sg:classifiers":[
        {
            "category":"Social Services",
            "subcategory":"Job Training",
            "type":"Services"
        }
    ],
    "sg:phone":"+1 819 523 9274",
    "sg:postcode":"G9X 3Z8",
    "sg:province":"QC",
    "sg:tags":[
        "employment"
    ],
    "wof:name":"Carrefour Jeunesse Hte",
    "wof:placetype":"venue"
},
  "geometry": {"coordinates":[-72.7857513428,47.4410858154],"type":"Point"}
}