{
  "type": "Feature",
  "properties": {
    "addr:full":"22 Poulin St W Azilda ON P0M 1B0",
    "addr:housenumber":"22",
    "addr:postcode":"p0m 1b0",
    "addr:street":"Poulin St W",
    "iso:country":"CA",
    "sg:address":"22 Poulin St W",
    "sg:city":"Azilda",
    "sg:classifiers":[
        {
            "category":"Education",
            "subcategory":"Library",
            "type":"Public Place"
        }
    ],
    "sg:phone":"+1 705 983 2650",
    "sg:postcode":"P0M 1B0",
    "sg:province":"ON",
    "wof:name":"Bibliotheque Azilda",
    "wof:placetype":"venue"
},
  "geometry": {"coordinates":[-81.1140823364,46.550693512],"type":"Point"}
}