{
  "type": "Feature",
  "properties": {
    "addr:full":"Hwy 9 S Carlyle SK S0C 0R0",
    "addr:postcode":"s0c 0r0",
    "addr:street":"Hwy 9 S Carlyle",
    "iso:country":"CA",
    "sg:address":"Hwy 9 S",
    "sg:city":"Carlyle",
    "sg:phone":"+1 306 453 2262",
    "sg:postcode":"S0C 0R0",
    "sg:province":"SK",
    "sg:tags":[
        "oil"
    ],
    "wof:name":"Girard Bulk Svc Ltd",
    "wof:placetype":"venue"
},
  "geometry": {"coordinates":[-102.257385254,49.6343002319],"type":"Point"}
}