{
  "type": "Feature",
  "properties": {
    "addr:full":"100 Princess St Kingston ON K7L 1A7",
    "addr:housenumber":"100",
    "addr:postcode":"k7l 1a7",
    "addr:street":"Princess St",
    "iso:country":"CA",
    "sg:address":"100 Princess St",
    "sg:city":"Kingston",
    "sg:classifiers":[
        {
            "category":"Shopping",
            "subcategory":"Pharmacy",
            "type":"Retail Goods"
        }
    ],
    "sg:phone":"+1 613 530 2666",
    "sg:postcode":"K7L 1A7",
    "sg:province":"ON",
    "wof:name":"Quarry Medical Pharmacy",
    "wof:placetype":"venue"
},
  "geometry": {"coordinates":[-76.4826965332,44.2314529419],"type":"Point"}
}