{
  "type": "Feature",
  "properties": {
    "addr:full":"128 Ronald Prom Montreal-Ouest QC H4X 1M8",
    "addr:housenumber":"128",
    "addr:postcode":"h4x 1m8",
    "addr:street":"Ronald Prom Montreal-Ouest",
    "iso:country":"CA",
    "sg:address":"128 Ronald Prom",
    "sg:city":"Montreal-Ouest",
    "sg:classifiers":[
        {
            "category":"Professional",
            "subcategory":"Research",
            "type":"Services"
        }
    ],
    "sg:phone":"+1 514 486 5481",
    "sg:postcode":"H4X 1M8",
    "sg:province":"QC",
    "sg:tags":[
        "development",
        "electronic"
    ],
    "wof:name":"J J Electronic Devices Inc",
    "wof:placetype":"venue"
},
  "geometry": {"coordinates":[-73.63975499999999,45.448982],"type":"Point"}
}