{
  "type": "Feature",
  "properties": {
    "addr:full":"London ON N6A 3N7",
    "addr:postcode":"n6a 3n7",
    "iso:country":"CA",
    "sg:city":"London",
    "sg:classifiers":[
        {
            "category":"Shopping",
            "subcategory":"Luggage & Leather Goods",
            "type":"Retail Goods"
        }
    ],
    "sg:phone":"+1 519 645 0991",
    "sg:postcode":"N6A 3N7",
    "sg:province":"ON",
    "wof:name":"Bently Leather",
    "wof:placetype":"venue"
},
  "geometry": {"coordinates":[-81.244568,42.983196],"type":"Point"}
}