{
  "type": "Feature",
  "properties": {
    "addr:full":"670 University Ave Charlottetown PE C1E 1E3",
    "addr:housenumber":"670",
    "addr:postcode":"c1e 1e3",
    "addr:street":"University Ave",
    "iso:country":"CA",
    "sg:address":"670 University Ave",
    "sg:city":"Charlottetown",
    "sg:classifiers":[
        {
            "category":"Shopping",
            "subcategory":"Bicycles & Sporting Goods",
            "type":"Retail Goods"
        }
    ],
    "sg:phone":"+1 902 628 6088",
    "sg:postcode":"C1E 1E3",
    "sg:province":"PE",
    "wof:name":"Sport Chek",
    "wof:placetype":"venue"
},
  "geometry": {"coordinates":[-63.1470184326,46.2647972107],"type":"Point"}
}