{
  "type": "Feature",
  "properties": {
    "addr:full":"3746 Canada Way Burnaby BC V5G 1G4",
    "addr:housenumber":"3746",
    "addr:postcode":"v5g 1g4",
    "addr:street":"Canada Way",
    "iso:country":"CA",
    "sg:address":"3746 Canada Way",
    "sg:city":"Burnaby",
    "sg:classifiers":[
        {
            "category":"Wholesale",
            "subcategory":"Groceries",
            "type":"Manufacturing & Wholesale Goods"
        }
    ],
    "sg:phone":"+1 604 437 8222",
    "sg:postcode":"V5G 1G4",
    "sg:province":"BC",
    "sg:tags":[
        "cocoa",
        "confectionery",
        "candy",
        "chocolate"
    ],
    "wof:name":"Charlie's Chocolate Factory",
    "wof:placetype":"venue"
},
  "geometry": {"coordinates":[-123.02113300000001,49.254608],"type":"Point"}
}