{
  "type": "Feature",
  "properties": {
    "iso:country":"CA",
    "sg:city":"Delta",
    "sg:classifiers":[
        {
            "category":"Health Services",
            "subcategory":"Doctor",
            "type":"Services"
        }
    ],
    "sg:phone":"+1 604 946 0149",
    "sg:postcode":"V4K 4L1",
    "sg:province":"BC",
    "sg:tags":[
        "physician",
        "surgeon"
    ],
    "wof:name":"Salloum, Sharon MD",
    "wof:placetype":"venue"
},
  "geometry": {"coordinates":[-123.064430237,49.0850639343],"type":"Point"}
}