{
  "type": "Feature",
  "properties": {
    "addr:full":"24 Third St Chatham ON N7M 5K5",
    "addr:housenumber":"24",
    "addr:postcode":"n7m 5k5",
    "addr:street":"Third St",
    "iso:country":"CA",
    "sg:address":"24 Third St",
    "sg:city":"Chatham",
    "sg:classifiers":[
        {
            "category":"Government",
            "subcategory":"Police Station",
            "type":"Public Place"
        }
    ],
    "sg:phone":"+1 519 351 8477",
    "sg:postcode":"N7M 5K5",
    "sg:province":"ON",
    "sg:tags":[
        "department"
    ],
    "wof:name":"Crime Stoppers",
    "wof:placetype":"venue"
},
  "geometry": {"coordinates":[-82.18975830079999,42.4043960571],"type":"Point"}
}