{
  "type": "Feature",
  "properties": {
    "addr:full":"2106 Rue Sainte-Famille Jonquiere QC G7X 4X1",
    "addr:housenumber":"2106",
    "addr:postcode":"g7x 4x1",
    "addr:street":"Rue Sainte-Famille",
    "iso:country":"CA",
    "sg:address":"2106 Rue Sainte-Famille",
    "sg:city":"Jonquiere",
    "sg:classifiers":[
        {
            "category":"Professional",
            "type":"Services"
        }
    ],
    "sg:phone":"+1 418 547 6648",
    "sg:postcode":"G7X 4X1",
    "sg:province":"QC",
    "sg:tags":[
        "establishment",
        "insurance"
    ],
    "wof:name":"Gravel & Levesque 1996 Inc",
    "wof:placetype":"venue"
},
  "geometry": {"coordinates":[-71.241478,48.423965],"type":"Point"}
}