{
  "type": "Feature",
  "properties": {
    "iso:country":"CA",
    "sg:city":"Victoria",
    "sg:classifiers":[
        {
            "category":"Shopping",
            "subcategory":"Clothing, Apparel, & Fashions",
            "type":"Retail Goods"
        }
    ],
    "sg:phone":"+1 250 384 2227",
    "sg:postcode":"V8W 3G9",
    "sg:province":"BC",
    "wof:name":"Turtle Express",
    "wof:placetype":"venue"
},
  "geometry": {"coordinates":[-123.367744446,48.4285888672],"type":"Point"}
}