{
  "type": "Feature",
  "properties": {
    "iso:country":"CA",
    "sg:city":"Scarborough",
    "sg:classifiers":[
        {
            "category":"Banks & Credit Unions",
            "subcategory":"Investment Brokerage",
            "type":"Services"
        }
    ],
    "sg:phone":"+1 416 438 3118",
    "sg:postcode":"M1H 3G3",
    "sg:province":"ON",
    "sg:tags":[
        "consultant",
        "planning",
        "financial"
    ],
    "wof:name":"Kinsons Investments Ltd",
    "wof:placetype":"venue"
},
  "geometry": {"coordinates":[-79.2361755371,43.7811508179],"type":"Point"}
}