{
  "type": "Feature",
  "properties": {
    "addr:full":"Bassano AB T0J 0B0",
    "addr:postcode":"t0j 0b0",
    "iso:country":"CA",
    "sg:city":"Bassano",
    "sg:classifiers":[
        {
            "category":"Shopping",
            "subcategory":"Florist",
            "type":"Retail Goods"
        }
    ],
    "sg:phone":"+1 403 641 2526",
    "sg:postcode":"T0J 0B0",
    "sg:province":"AB",
    "wof:name":"Bassano Flower & Gift",
    "wof:placetype":"venue"
},
  "geometry": {"coordinates":[-112.468559265,50.78723526],"type":"Point"}
}