{
  "type": "Feature",
  "properties": {
    "addr:full":"Saskatoon SK S7M 5W1",
    "addr:postcode":"s7m 5w1",
    "iso:country":"CA",
    "sg:city":"Saskatoon",
    "sg:classifiers":[
        {
            "category":"Health Services",
            "subcategory":"Doctor",
            "type":"Services"
        }
    ],
    "sg:phone":"+1 306 931 7712",
    "sg:postcode":"S7M 5W1",
    "sg:province":"SK",
    "sg:tags":[
        "clinic"
    ],
    "wof:name":"Chelation Centre Saskatoon",
    "wof:placetype":"venue"
},
  "geometry": {"coordinates":[-106.678673,52.129383],"type":"Point"}
}