{
  "type": "Feature",
  "properties": {
    "addr:full":"22 Rose St Tamworth ON K0K 3G0",
    "addr:housenumber":"22",
    "addr:postcode":"k0k 3g0",
    "addr:street":"Rose St",
    "iso:country":"CA",
    "sg:address":"22 Rose St",
    "sg:city":"Tamworth",
    "sg:classifiers":[
        {
            "category":"Retail",
            "subcategory":"Auto Repair",
            "type":"Services"
        }
    ],
    "sg:phone":"+1 613 379 2231",
    "sg:postcode":"K0K 3G0",
    "sg:province":"ON",
    "sg:tags":[
        "repairing",
        "automobile"
    ],
    "wof:name":"Moss' Garage",
    "wof:placetype":"venue"
},
  "geometry": {"coordinates":[-76.995514,44.489346],"type":"Point"}
}