{
  "type": "Feature",
  "properties": {
    "addr:full":"4406 Rue Wellington Verdun QC H4G 1W5",
    "addr:housenumber":"4406",
    "addr:postcode":"h4g 1w5",
    "addr:street":"Rue Wellington",
    "iso:country":"CA",
    "sg:address":"4406 Rue Wellington",
    "sg:city":"Verdun",
    "sg:classifiers":[
        {
            "category":"Shopping",
            "subcategory":"Jewelry",
            "type":"Retail Goods"
        }
    ],
    "sg:phone":"+1 514 769 5631",
    "sg:postcode":"H4G 1W5",
    "sg:province":"QC",
    "sg:tags":[
        "jeweler"
    ],
    "wof:name":"Bijouterie Denis Gouin Inc",
    "wof:placetype":"venue"
},
  "geometry": {"coordinates":[-73.5671539307,45.4599571228],"type":"Point"}
}