{
  "type": "Feature",
  "properties": {
    "addr:full":"726 Main St W Birtle MB R0M 0C0",
    "addr:housenumber":"726",
    "addr:postcode":"r0m 0c0",
    "addr:street":"Main St W Birtle",
    "iso:country":"CA",
    "sg:address":"726 Main St W",
    "sg:city":"Birtle",
    "sg:classifiers":[
        {
            "category":"Government",
            "subcategory":"Office",
            "type":"Public Place"
        }
    ],
    "sg:phone":"+1 204 842 7710",
    "sg:postcode":"R0M 0C0",
    "sg:province":"MB",
    "wof:name":"Manitoba Maintenance Yard",
    "wof:placetype":"venue"
},
  "geometry": {"coordinates":[-101.04857635499999,50.4220085144],"type":"Point"}
}