{
  "type": "Feature",
  "properties": {
    "addr:full":"272 Kensington Ave N Hamilton ON L8L 7N9",
    "addr:housenumber":"272",
    "addr:postcode":"l8l 7n9",
    "addr:street":"Kensington Ave N",
    "iso:country":"CA",
    "sg:address":"272 Kensington Ave N",
    "sg:city":"Hamilton",
    "sg:classifiers":[
        {
            "category":"Retail",
            "subcategory":"Auto Repair",
            "type":"Services"
        }
    ],
    "sg:phone":"+1 905 545 6699",
    "sg:postcode":"L8L 7N9",
    "sg:province":"ON",
    "sg:tags":[
        "repairing",
        "automobile",
        "radiator"
    ],
    "wof:name":"Autosave Discount Radiator",
    "wof:placetype":"venue"
},
  "geometry": {"coordinates":[-79.820351,43.251614],"type":"Point"}
}