{
  "type": "Feature",
  "properties": {
    "addr:full":"873 Tower Dr North Bay ON P1B 8G2",
    "addr:housenumber":"873",
    "addr:postcode":"p1b 8g2",
    "addr:street":"Tower Dr",
    "iso:country":"CA",
    "sg:address":"873 Tower Dr",
    "sg:city":"North Bay",
    "sg:classifiers":[
        {
            "category":"Building & Trades",
            "subcategory":"Plumbing",
            "type":"Services"
        }
    ],
    "sg:phone":"+1 705 497 3738",
    "sg:postcode":"P1B 8G2",
    "sg:province":"ON",
    "sg:tags":[
        "conditioning",
        "air",
        "system",
        "contractor"
    ],
    "wof:name":"Wally's Refrigeration",
    "wof:placetype":"venue"
},
  "geometry": {"coordinates":[-79.400764,46.346844],"type":"Point"}
}