{
  "type": "Feature",
  "properties": {
    "iso:country":"CA",
    "sg:address":"661 18th St",
    "sg:city":"Brandon",
    "sg:classifiers":[
        {
            "category":"Banks & Credit Unions",
            "subcategory":"Bank",
            "type":"Services"
        }
    ],
    "sg:phone":"+1 204 726 3116",
    "sg:postcode":"R7A 5B3",
    "sg:province":"MB",
    "wof:name":"Royal Bank Financial Group",
    "wof:placetype":"venue"
},
  "geometry": {"coordinates":[-99.9616470337,49.8398933411],"type":"Point"}
}