{
  "type": "Feature",
  "properties": {
    "addr:full":"70 Thickson Rd S Whitby ON L1N 7T2",
    "addr:housenumber":"70",
    "addr:postcode":"l1n 7t2",
    "addr:street":"Thickson Rd S",
    "iso:country":"CA",
    "sg:address":"70 Thickson Rd S",
    "sg:city":"Whitby",
    "sg:classifiers":[
        {
            "category":"Food & Beverages",
            "subcategory":"Liquor & Beverages",
            "type":"Retail Goods"
        }
    ],
    "sg:phone":"+1 905 430 1554",
    "sg:postcode":"L1N 7T2",
    "sg:province":"ON",
    "sg:tags":[
        "wine"
    ],
    "wof:name":"Wine Rack",
    "wof:placetype":"venue"
},
  "geometry": {"coordinates":[-78.911858,43.883709],"type":"Point"}
}