{
  "type": "Feature",
  "properties": {
    "addr:full":"Winnipeg MB R2M 3S7",
    "addr:postcode":"r2m 3s7",
    "iso:country":"CA",
    "sg:city":"Winnipeg",
    "sg:classifiers":[
        {
            "category":"Manufacturing",
            "subcategory":"Furniture",
            "type":"Manufacturing & Wholesale Goods"
        }
    ],
    "sg:phone":"+1 204 987 4700",
    "sg:postcode":"R2M 3S7",
    "sg:province":"MB",
    "sg:tags":[
        "equipment",
        "computer",
        "dealer"
    ],
    "wof:name":"Cbm Corp Business Machines",
    "wof:placetype":"venue"
},
  "geometry": {"coordinates":[-97.1364822388,49.8918914795],"type":"Point"}
}