{
  "type": "Feature",
  "properties": {
    "addr:full":"101 2nd Ave #Bsmt Vibank SK S0G 4Y0",
    "addr:housenumber":"101",
    "addr:postcode":"s0g 4y0",
    "addr:street":"2Nd Ave # Bsmt Vibank",
    "iso:country":"CA",
    "sg:address":"101 2nd Ave #Bsmt",
    "sg:city":"Vibank",
    "sg:classifiers":[
        {
            "category":"Social Services",
            "subcategory":"Child Care",
            "type":"Services"
        }
    ],
    "sg:phone":"+1 306 762 2266",
    "sg:postcode":"S0G 4Y0",
    "sg:province":"SK",
    "wof:name":"Primary Daycare",
    "wof:placetype":"venue"
},
  "geometry": {"coordinates":[-102.264587402,50.33203125],"type":"Point"}
}