{
  "type": "Feature",
  "properties": {
    "iso:country":"CA",
    "sg:address":"4755 Arthur Dr",
    "sg:city":"Delta",
    "sg:classifiers":[
        {
            "category":"Organizations",
            "subcategory":"Religious Organization",
            "type":"Services"
        }
    ],
    "sg:phone":"+1 604 946 8413",
    "sg:postcode":"V4K 2X6",
    "sg:province":"BC",
    "sg:tags":[
        "church"
    ],
    "wof:name":"All Saints Ladner Anglican Chr",
    "wof:placetype":"venue"
},
  "geometry": {"coordinates":[-123.081245,49.089153],"type":"Point"}
}