{
  "type": "Feature",
  "properties": {
    "addr:full":"2998 Bloor St W Etobicoke ON M8X 1C2",
    "addr:housenumber":"2998",
    "addr:postcode":"m8x 1c2",
    "addr:street":"Bloor St W",
    "iso:country":"CA",
    "sg:address":"2998 Bloor St W",
    "sg:city":"Etobicoke",
    "sg:classifiers":[
        {
            "category":"Personal",
            "subcategory":"Beauty Salon",
            "type":"Services"
        }
    ],
    "sg:phone":"+1 416 236 9663",
    "sg:postcode":"M8X 1C2",
    "sg:province":"ON",
    "wof:name":"Cos on the Kingsway",
    "wof:placetype":"venue"
},
  "geometry": {"coordinates":[-79.51061199999999,43.647678],"type":"Point"}
}