{
  "type": "Feature",
  "properties": {
    "iso:country":"CA",
    "sg:address":"472 River Rd",
    "sg:city":"Welland",
    "sg:classifiers":[
        {
            "category":"Manufacturing",
            "subcategory":"Tools & Machinery",
            "type":"Manufacturing & Wholesale Goods"
        }
    ],
    "sg:phone":"+1 905 732 4545",
    "sg:postcode":"L3B 5N4",
    "sg:province":"ON",
    "sg:tags":[
        "machine",
        "shop"
    ],
    "wof:name":"R & Y Tool & Die CO Ltd",
    "wof:placetype":"venue"
},
  "geometry": {"coordinates":[-79.23677062989999,43.0064735413],"type":"Point"}
}