{
  "type": "Feature",
  "properties": {
    "addr:full":"557 Dixon Rd Etobicoke ON M9W 6K1",
    "addr:housenumber":"557",
    "addr:postcode":"m9w 6k1",
    "addr:street":"Dixon Rd",
    "iso:country":"CA",
    "sg:address":"557 Dixon Rd",
    "sg:city":"Etobicoke",
    "sg:classifiers":[
        {
            "category":"Restaurant",
            "type":"Food & Drink"
        }
    ],
    "sg:phone":"+1 416 247 0110",
    "sg:postcode":"M9W 6K1",
    "sg:province":"ON",
    "sg:tags":[
        "caterer"
    ],
    "wof:name":"Sushi Gourmet Catering Inc",
    "wof:placetype":"venue"
},
  "geometry": {"coordinates":[-79.57107543950001,43.6913299561],"type":"Point"}
}