{
  "type": "Feature",
  "properties": {
    "addr:full":"2052 Filuk Pl Abbotsford BC V2S 5P2",
    "addr:housenumber":"2052",
    "addr:postcode":"v2s 5p2",
    "addr:street":"Filuk Pl",
    "iso:country":"CA",
    "sg:address":"2052 Filuk Pl",
    "sg:city":"Abbotsford",
    "sg:classifiers":[
        {
            "category":"Utilities",
            "subcategory":"Sewage",
            "type":"Services"
        }
    ],
    "sg:phone":"+1 604 309 5332",
    "sg:postcode":"V2S 5P2",
    "sg:province":"BC",
    "sg:tags":[
        "equipment",
        "treatment"
    ],
    "wof:name":"Precise Water & Waste Ltd",
    "wof:placetype":"venue"
},
  "geometry": {"coordinates":[-122.26174899999999,49.039169],"type":"Point"}
}