{
  "type": "Feature",
  "properties": {
    "addr:full":"2845 Hwy 6 Lions Head ON N0H 1W0",
    "addr:housenumber":"2845",
    "addr:postcode":"n0h 1w0",
    "addr:street":"Hwy 6 Lions Head",
    "iso:country":"CA",
    "sg:address":"2845 Hwy 6",
    "sg:city":"Lions Head",
    "sg:classifiers":[
        {
            "category":"Home & Garden",
            "subcategory":"Household Appliances",
            "type":"Retail Goods"
        }
    ],
    "sg:phone":"+1 519 793 4444",
    "sg:postcode":"N0H 1W0",
    "sg:province":"ON",
    "wof:name":"Peninsula Appliances & Tv",
    "wof:placetype":"venue"
},
  "geometry": {"coordinates":[-81.25420379640001,44.986579895],"type":"Point"}
}