{
  "type": "Feature",
  "properties": {
    "addr:full":"28 Dundas St Princeton ON N0J 1V0",
    "addr:housenumber":"28",
    "addr:postcode":"n0j 1v0",
    "addr:street":"Dundas St",
    "iso:country":"CA",
    "sg:address":"28 Dundas St",
    "sg:city":"Princeton",
    "sg:classifiers":[
        {
            "category":"Restaurant",
            "type":"Food & Drink"
        }
    ],
    "sg:phone":"+1 519 458 4444",
    "sg:postcode":"N0J 1V0",
    "sg:province":"ON",
    "wof:name":"Jim's Lunch",
    "wof:placetype":"venue"
},
  "geometry": {"coordinates":[-80.52587127690001,43.1645545959],"type":"Point"}
}