{
  "type": "Feature",
  "properties": {
    "addr:full":"111 First St Welland ON L3B 4S1",
    "addr:housenumber":"111",
    "addr:postcode":"l3b 4s1",
    "addr:street":"First St",
    "iso:country":"CA",
    "sg:address":"111 First St",
    "sg:city":"Welland",
    "sg:classifiers":[
        {
            "category":"Education",
            "subcategory":"School",
            "type":"Public Place"
        }
    ],
    "sg:phone":"+1 905 732 4110",
    "sg:postcode":"L3B 4S1",
    "sg:province":"ON",
    "wof:name":"Plymouth Elementary School",
    "wof:placetype":"venue"
},
  "geometry": {"coordinates":[-79.24601,42.982819],"type":"Point"}
}