{
  "type": "Feature",
  "properties": {
    "iso:country":"CA",
    "sg:address":"25 Av Begin",
    "sg:city":"Levis",
    "sg:classifiers":[
        {
            "category":"Personal",
            "subcategory":"Beauty Salon",
            "type":"Services"
        }
    ],
    "sg:phone":"+1 418 838 1664",
    "sg:postcode":"G6V 4B8",
    "sg:province":"QC",
    "wof:name":"Salon DE Coiffure Lucie Masse",
    "wof:placetype":"venue"
},
  "geometry": {"coordinates":[-71.1824874878,46.8073806763],"type":"Point"}
}