{
  "type": "Feature",
  "properties": {
    "addr:full":"Vernon BC V1T 8T3",
    "addr:postcode":"v1t 8t3",
    "iso:country":"CA",
    "sg:city":"Vernon",
    "sg:classifiers":[
        {
            "category":"Freight",
            "type":"Transportation"
        }
    ],
    "sg:phone":"+1 250 549 2666",
    "sg:postcode":"V1T 8T3",
    "sg:province":"BC",
    "sg:tags":[
        "trucking"
    ],
    "wof:name":"Check Transportation Mgmt Inc",
    "wof:placetype":"venue"
},
  "geometry": {"coordinates":[-119.25756800000001,50.248096],"type":"Point"}
}