{
  "type": "Feature",
  "properties": {
    "iso:country":"CA",
    "sg:address":"590 Boul Albert-DE Niverville",
    "sg:city":"Dorval",
    "sg:classifiers":[
        {
            "category":"Airport",
            "type":"Transportation"
        }
    ],
    "sg:phone":"+1 514 636 1737",
    "sg:postcode":"H4Y 1G6",
    "sg:province":"QC",
    "sg:tags":[
        "aircraft",
        "maintenance"
    ],
    "wof:name":"Techni-Air Inc",
    "wof:placetype":"venue"
},
  "geometry": {"coordinates":[-73.752663,45.452297],"type":"Point"}
}