{
  "type": "Feature",
  "properties": {
    "addr:full":"PO Box 276 STN Main Delhi ON N4B 2X1",
    "addr:housenumber":"po",
    "addr:postcode":"n4b 2x1",
    "addr:street":"Box 276 Stn Main",
    "iso:country":"CA",
    "sg:address":"PO Box 276 STN Main",
    "sg:city":"Delhi",
    "sg:classifiers":[
        {
            "category":"Building & Trades",
            "subcategory":"Plumbing",
            "type":"Services"
        }
    ],
    "sg:phone":"+1 519 429 5950",
    "sg:postcode":"N4B 2X1",
    "sg:province":"ON",
    "sg:tags":[
        "heating",
        "contractor"
    ],
    "wof:name":"Efficient Heating",
    "wof:placetype":"venue"
},
  "geometry": {"coordinates":[-80.492813,42.851845],"type":"Point"}
}