{
  "type": "Feature",
  "properties": {
    "addr:full":"20 Hope St S Port Hope ON L1A 2M8",
    "addr:housenumber":"20",
    "addr:postcode":"l1a 2m8",
    "addr:street":"Hope St S",
    "iso:country":"CA",
    "sg:address":"20 Hope St S",
    "sg:city":"Port Hope",
    "sg:classifiers":[
        {
            "category":"Health Services",
            "subcategory":"Nursing And Care Facility",
            "type":"Services"
        }
    ],
    "sg:phone":"+1 905 885 6367",
    "sg:postcode":"L1A 2M8",
    "sg:province":"ON",
    "sg:tags":[
        "home",
        "convalescent"
    ],
    "wof:name":"Community Nursing Homes",
    "wof:placetype":"venue"
},
  "geometry": {"coordinates":[-78.288116,43.95451],"type":"Point"}
}