{
  "type": "Feature",
  "properties": {
    "addr:full":"7052 Route 313 Pointe-Canot NB E8T 3B7",
    "addr:housenumber":"7052",
    "addr:postcode":"e8t 3b7",
    "addr:street":"Route 313",
    "iso:country":"CA",
    "sg:address":"7052 Route 313",
    "sg:city":"Pointe-Canot",
    "sg:classifiers":[
        {
            "category":"Food & Beverages",
            "subcategory":"Groceries & Convenience Stores",
            "type":"Retail Goods"
        }
    ],
    "sg:phone":"+1 506 344 8585",
    "sg:postcode":"E8T 3B7",
    "sg:province":"NB",
    "sg:tags":[
        "grocer"
    ],
    "wof:name":"Duguay Livain Depanneur",
    "wof:placetype":"venue"
},
  "geometry": {"coordinates":[-64.694557,47.834278],"type":"Point"}
}