{
  "type": "Feature",
  "properties": {
    "addr:full":"392 Connell St Woodstock NB E7M 5G9",
    "addr:housenumber":"392",
    "addr:postcode":"e7m 5g9",
    "addr:street":"Connell St",
    "iso:country":"CA",
    "sg:address":"392 Connell St",
    "sg:city":"Woodstock",
    "sg:classifiers":[
        {
            "category":"Restaurant",
            "type":"Food & Drink"
        }
    ],
    "sg:phone":"+1 506 328 3343",
    "sg:postcode":"E7M 5G9",
    "sg:province":"NB",
    "wof:name":"Mc Donald's",
    "wof:placetype":"venue"
},
  "geometry": {"coordinates":[-67.6011352539,46.1708908081],"type":"Point"}
}