{
  "type": "Feature",
  "properties": {
    "addr:full":"Calgary AB T2A 4T8",
    "addr:postcode":"t2a 4t8",
    "iso:country":"CA",
    "sg:city":"Calgary",
    "sg:classifiers":[
        {
            "category":"Personal",
            "subcategory":"Beauty Salon",
            "type":"Services"
        }
    ],
    "sg:phone":"+1 403 272 3775",
    "sg:postcode":"T2A 4T8",
    "sg:province":"AB",
    "wof:name":"Hair Power",
    "wof:placetype":"venue"
},
  "geometry": {"coordinates":[-113.95810699499999,51.0635528564],"type":"Point"}
}