{
  "type": "Feature",
  "properties": {
    "addr:full":"3524 Rue Cabot Jonquiere QC G7X 1R4",
    "addr:housenumber":"3524",
    "addr:postcode":"g7x 1r4",
    "addr:street":"Rue Cabot",
    "iso:country":"CA",
    "sg:address":"3524 Rue Cabot",
    "sg:city":"Jonquiere",
    "sg:classifiers":[
        {
            "category":"Professional",
            "subcategory":"Management & Consulting",
            "type":"Services"
        }
    ],
    "sg:phone":"+1 418 547 2111",
    "sg:postcode":"G7X 1R4",
    "sg:province":"QC",
    "sg:tags":[
        "consultant",
        "school",
        "instructional"
    ],
    "wof:name":"Centre Des Svc Aux Ent",
    "wof:placetype":"venue"
},
  "geometry": {"coordinates":[-71.227707,48.42432],"type":"Point"}
}