{
  "type": "Feature",
  "properties": {
    "addr:full":"1021 Av Edward Laval QC H7W 1L5",
    "addr:housenumber":"1021",
    "addr:postcode":"h7w 1l5",
    "addr:street":"Av Edward",
    "iso:country":"CA",
    "sg:address":"1021 Av Edward",
    "sg:city":"Laval",
    "sg:classifiers":[
        {
            "category":"Professional",
            "subcategory":"Accounting & Tax Preparation",
            "type":"Services"
        }
    ],
    "sg:phone":"+1 450 681 5987",
    "sg:postcode":"H7W 1L5",
    "sg:province":"QC",
    "sg:tags":[
        "accountant"
    ],
    "wof:name":"Ohayon Ncga",
    "wof:placetype":"venue"
},
  "geometry": {"coordinates":[-73.76685333250001,45.537147522],"type":"Point"}
}