{
  "type": "Feature",
  "properties": {
    "addr:full":"Mississauga ON L5C 2Z2",
    "addr:postcode":"l5c 2z2",
    "iso:country":"CA",
    "sg:city":"Mississauga",
    "sg:classifiers":[
        {
            "category":"Retail",
            "subcategory":"Repair Shop",
            "type":"Services"
        }
    ],
    "sg:phone":"+1 905 306 9757",
    "sg:postcode":"L5C 2Z2",
    "sg:province":"ON",
    "sg:tags":[
        "equipment",
        "electronic",
        "supply"
    ],
    "wof:name":"New Electronic Pl Repair Shop",
    "wof:placetype":"venue"
},
  "geometry": {"coordinates":[-79.65020800000001,43.578472],"type":"Point"}
}