{
  "type": "Feature",
  "properties": {
    "addr:full":"6126 48 St Barrhead AB T7N 1A1",
    "addr:housenumber":"6126",
    "addr:postcode":"t7n 1a1",
    "addr:street":"48 St",
    "iso:country":"CA",
    "sg:address":"6126 48 St",
    "sg:city":"Barrhead",
    "sg:classifiers":[
        {
            "category":"Retail",
            "subcategory":"Repair Shop",
            "type":"Services"
        }
    ],
    "sg:phone":"+1 780 674 2924",
    "sg:postcode":"T7N 1A1",
    "sg:province":"AB",
    "sg:tags":[
        "machine",
        "welding"
    ],
    "wof:name":"Barrhead Machine & Welding Ltd",
    "wof:placetype":"venue"
},
  "geometry": {"coordinates":[-114.39919281,54.1323699951],"type":"Point"}
}