{
  "type": "Feature",
  "properties": {
    "addr:full":"240 Trafalgar St St Marys ON N4X 1A5",
    "addr:housenumber":"240",
    "addr:postcode":"n4x 1a5",
    "addr:street":"Trafalgar St",
    "iso:country":"CA",
    "sg:address":"240 Trafalgar St",
    "sg:city":"St Marys",
    "sg:classifiers":[
        {
            "category":"Professional",
            "subcategory":"Advertising",
            "type":"Services"
        }
    ],
    "sg:phone":"+1 519 284 1460",
    "sg:postcode":"N4X 1A5",
    "sg:province":"ON",
    "sg:tags":[
        "designer",
        "display",
        "producer"
    ],
    "wof:name":"Rvs Exhibitional Draperies",
    "wof:placetype":"venue"
},
  "geometry": {"coordinates":[-81.1395568848,43.2532653809],"type":"Point"}
}