{
  "type": "Feature",
  "properties": {
    "addr:full":"422 Lake Rd Bowmanville ON L1C 4P8",
    "addr:housenumber":"422",
    "addr:postcode":"l1c 4p8",
    "addr:street":"Lake Rd",
    "iso:country":"CA",
    "sg:address":"422 Lake Rd",
    "sg:city":"Bowmanville",
    "sg:classifiers":[
        {
            "category":"Recreation",
            "type":"Entertainment"
        }
    ],
    "sg:phone":"+1 905 623 4882",
    "sg:postcode":"L1C 4P8",
    "sg:province":"ON",
    "sg:tags":[
        "instruction",
        "gymnastic"
    ],
    "wof:name":"Clarington Gymnastics",
    "wof:placetype":"venue"
},
  "geometry": {"coordinates":[-78.65989685060001,43.8980407715],"type":"Point"}
}