{
  "type": "Feature",
  "properties": {
    "addr:full":"9586 Windsor St Chilliwack BC V2P 6C2",
    "addr:housenumber":"9586",
    "addr:postcode":"v2p 6c2",
    "addr:street":"Windsor St",
    "iso:country":"CA",
    "sg:address":"9586 Windsor St",
    "sg:city":"Chilliwack",
    "sg:classifiers":[
        {
            "category":"Shopping",
            "subcategory":"Bicycles & Sporting Goods",
            "type":"Retail Goods"
        }
    ],
    "sg:phone":"+1 604 792 6198",
    "sg:postcode":"V2P 6C2",
    "sg:province":"BC",
    "sg:tags":[
        "equipment",
        "golf",
        "supply"
    ],
    "wof:name":"Golfix",
    "wof:placetype":"venue"
},
  "geometry": {"coordinates":[-121.929481506,49.176410675],"type":"Point"}
}