{
  "type": "Feature",
  "properties": {
    "addr:full":"300 John St Thornhill ON L3T 5W4",
    "addr:housenumber":"300",
    "addr:postcode":"l3t 5w4",
    "addr:street":"John St",
    "iso:country":"CA",
    "sg:address":"300 John St",
    "sg:city":"Thornhill",
    "sg:classifiers":[
        {
            "category":"Shopping",
            "subcategory":"Pharmacy",
            "type":"Retail Goods"
        }
    ],
    "sg:phone":"+1 905 886 3711",
    "sg:postcode":"L3T 5W4",
    "sg:province":"ON",
    "wof:name":"Shoppers Drug Mart",
    "wof:placetype":"venue"
},
  "geometry": {"coordinates":[-79.3972625732,43.819480896],"type":"Point"}
}