{
  "type": "Feature",
  "properties": {
    "addr:full":"176 John St Toronto ON M5T 1X5",
    "addr:housenumber":"176",
    "addr:postcode":"m5t 1x5",
    "addr:street":"John St",
    "iso:country":"CA",
    "sg:address":"176 John St",
    "sg:city":"Toronto",
    "sg:classifiers":[
        {
            "category":"Professional",
            "subcategory":"Business Services",
            "type":"Services"
        }
    ],
    "sg:phone":"+1 416 979 3456",
    "sg:postcode":"M5T 1X5",
    "sg:province":"ON",
    "sg:tags":[
        "interior",
        "consultant",
        "design",
        "decorator",
        "furniture"
    ],
    "wof:name":"Barbers Daughter",
    "wof:placetype":"venue"
},
  "geometry": {"coordinates":[-79.39157899999999,43.650539],"type":"Point"}
}