{
  "type": "Feature",
  "properties": {
    "iso:country":"CA",
    "sg:address":"76 Stuart St #1036",
    "sg:city":"Kingston",
    "sg:classifiers":[
        {
            "category":"Health Services",
            "subcategory":"Doctor",
            "type":"Services"
        }
    ],
    "sg:phone":"+1 613 549 4070",
    "sg:postcode":"K7L 2V7",
    "sg:province":"ON",
    "sg:tags":[
        "physician",
        "surgeon"
    ],
    "wof:name":"Hudson, R W MD",
    "wof:placetype":"venue"
},
  "geometry": {"coordinates":[-76.493248,44.224384],"type":"Point"}
}