{
  "type": "Feature",
  "properties": {
    "addr:full":"20676 Fraser Hwy Langley BC V3A 4G5",
    "addr:housenumber":"20676",
    "addr:postcode":"v3a 4g5",
    "addr:street":"Fraser Hwy",
    "iso:country":"CA",
    "sg:address":"20676 Fraser Hwy",
    "sg:city":"Langley",
    "sg:classifiers":[
        {
            "category":"Organizations",
            "subcategory":"Religious Organization",
            "type":"Services"
        }
    ],
    "sg:phone":"+1 604 534 3303",
    "sg:postcode":"V3A 4G5",
    "sg:province":"BC",
    "sg:tags":[
        "church"
    ],
    "wof:name":"St Joseph's Church",
    "wof:placetype":"venue"
},
  "geometry": {"coordinates":[-122.64932251,49.1029815674],"type":"Point"}
}