{
  "type": "Feature",
  "properties": {
    "addr:full":"Hamilton ON L8R 1C4",
    "addr:postcode":"l8r 1c4",
    "iso:country":"CA",
    "sg:city":"Hamilton",
    "sg:classifiers":[
        {
            "category":"Manufacturing",
            "subcategory":"Signs",
            "type":"Manufacturing & Wholesale Goods"
        }
    ],
    "sg:phone":"+1 905 528 6699",
    "sg:postcode":"L8R 1C4",
    "sg:province":"ON",
    "wof:name":"Prosigns Hamilton Inc",
    "wof:placetype":"venue"
},
  "geometry": {"coordinates":[-79.8679733276,43.2591705322],"type":"Point"}
}