{
  "type": "Feature",
  "properties": {
    "addr:full":"15 Patricia Dr Toronto ON M4C 5K2",
    "addr:housenumber":"15",
    "addr:postcode":"m4c 5k2",
    "addr:street":"Patricia Dr",
    "iso:country":"CA",
    "sg:address":"15 Patricia Dr",
    "sg:city":"Toronto",
    "sg:classifiers":[
        {
            "category":"Manufacturing",
            "subcategory":"Printing",
            "type":"Manufacturing & Wholesale Goods"
        }
    ],
    "sg:phone":"+1 416 221 4802",
    "sg:postcode":"M4C 5K2",
    "sg:province":"ON",
    "sg:tags":[
        "publisher"
    ],
    "wof:name":"Annick Press",
    "wof:placetype":"venue"
},
  "geometry": {"coordinates":[-79.3076629639,43.6847839355],"type":"Point"}
}