{
  "type": "Feature",
  "properties": {
    "addr:full":"795 Eglinton Ave E East York ON M4G 4E4",
    "addr:housenumber":"795",
    "addr:postcode":"m4g 4e4",
    "addr:street":"Eglinton Ave E",
    "iso:country":"CA",
    "sg:address":"795 Eglinton Ave E",
    "sg:city":"East York",
    "sg:classifiers":[
        {
            "category":"Health Services",
            "subcategory":"Doctor",
            "type":"Services"
        }
    ],
    "sg:phone":"+1 416 424 3145",
    "sg:postcode":"M4G 4E4",
    "sg:province":"ON",
    "sg:tags":[
        "physician",
        "surgeon"
    ],
    "wof:name":"Leaside Health Ctr",
    "wof:placetype":"venue"
},
  "geometry": {"coordinates":[-79.3659210205,43.7132110596],"type":"Point"}
}