{
  "type": "Feature",
  "properties": {
    "iso:country":"CA",
    "sg:address":"126 105th St E",
    "sg:city":"Saskatoon",
    "sg:classifiers":[
        {
            "category":"Government",
            "subcategory":"Office",
            "type":"Public Place"
        }
    ],
    "sg:phone":"+1 306 933 5269",
    "sg:postcode":"S7N 1Z3",
    "sg:province":"SK",
    "wof:name":"SK Highway Maintenance Office",
    "wof:placetype":"venue"
},
  "geometry": {"coordinates":[-106.596939087,52.133682251],"type":"Point"}
}