{
  "type": "Feature",
  "properties": {
    "addr:full":"569 Boul Richelieu Richelieu QC J3L 4Y3",
    "addr:housenumber":"569",
    "addr:postcode":"j3l 4y3",
    "addr:street":"Boul Richelieu",
    "iso:country":"CA",
    "sg:address":"569 Boul Richelieu",
    "sg:city":"Richelieu",
    "sg:classifiers":[
        {
            "category":"Shopping",
            "subcategory":"Pharmacy",
            "type":"Retail Goods"
        }
    ],
    "sg:phone":"+1 450 658 3353",
    "sg:postcode":"J3L 4Y3",
    "sg:province":"QC",
    "wof:name":"Uniprix",
    "wof:placetype":"venue"
},
  "geometry": {"coordinates":[-73.24671936039999,45.4433860779],"type":"Point"}
}