{
  "type": "Feature",
  "properties": {
    "addr:full":"3138 Penetanguishene Rd Barrie ON L4M 4Y8",
    "addr:housenumber":"3138",
    "addr:postcode":"l4m 4y8",
    "addr:street":"Penetanguishene Rd",
    "iso:country":"CA",
    "sg:address":"3138 Penetanguishene Rd",
    "sg:city":"Barrie",
    "sg:classifiers":[
        {
            "category":"Travel",
            "subcategory":"Campground",
            "type":"Entertainment"
        }
    ],
    "sg:phone":"+1 705 726 6128",
    "sg:postcode":"L4M 4Y8",
    "sg:province":"ON",
    "wof:name":"Barrie Koa Campground",
    "wof:placetype":"venue"
},
  "geometry": {"coordinates":[-79.6458816528,44.41614151],"type":"Point"}
}