{
  "type": "Feature",
  "properties": {
    "addr:full":"1438 Rue D'Arras Sherbrooke QC J1J 2B4",
    "addr:housenumber":"1438",
    "addr:postcode":"j1j 2b4",
    "addr:street":"Rue D'Arras",
    "iso:country":"CA",
    "sg:address":"1438 Rue D'Arras",
    "sg:city":"Sherbrooke",
    "sg:classifiers":[
        {
            "category":"Retail",
            "subcategory":"Portrait Studio",
            "type":"Services"
        }
    ],
    "sg:phone":"+1 819 822 2022",
    "sg:postcode":"J1J 2B4",
    "sg:province":"QC",
    "sg:tags":[
        "photographer"
    ],
    "wof:name":"Studio Yves Bolduc Enr",
    "wof:placetype":"venue"
},
  "geometry": {"coordinates":[-71.912003,45.39949],"type":"Point"}
}