{
  "type": "Feature",
  "properties": {
    "addr:full":"PO Box 118 Carcross YT Y0B 1B0",
    "addr:housenumber":"po",
    "addr:postcode":"y0b 1b0",
    "addr:street":"Box 118",
    "iso:country":"CA",
    "sg:address":"PO Box 118",
    "sg:city":"Carcross",
    "sg:classifiers":[
        {
            "category":"Government",
            "subcategory":"Office",
            "type":"Public Place"
        }
    ],
    "sg:phone":"+1 867 821 3216",
    "sg:postcode":"Y0B 1B0",
    "sg:province":"YT",
    "wof:name":"Carcross Tagish Development",
    "wof:placetype":"venue"
},
  "geometry": {"coordinates":[-134.69987499999999,60.166199],"type":"Point"}
}