{
  "type": "Feature",
  "properties": {
    "addr:full":"1450 Meyerside Dr Mississauga ON L5T 2N5",
    "addr:housenumber":"1450",
    "addr:postcode":"l5t 2n5",
    "addr:street":"Meyerside Dr",
    "iso:country":"CA",
    "sg:address":"1450 Meyerside Dr",
    "sg:city":"Mississauga",
    "sg:classifiers":[
        {
            "category":"Insurance",
            "subcategory":"Insurance Agent",
            "type":"Services"
        }
    ],
    "sg:phone":"+1 905 670 4151",
    "sg:postcode":"L5T 2N5",
    "sg:province":"ON",
    "wof:name":"Lorenzetti, B F",
    "wof:placetype":"venue"
},
  "geometry": {"coordinates":[-79.654938,43.659462],"type":"Point"}
}