{
  "type": "Feature",
  "properties": {
    "addr:full":"5458 Av Westminster Cote Saint-Luc QC H4X 2A5",
    "addr:housenumber":"5458",
    "addr:postcode":"h4x 2a5",
    "addr:street":"Av Westminster Cote",
    "iso:country":"CA",
    "sg:address":"5458 Av Westminster",
    "sg:city":"Cote Saint-Luc",
    "sg:classifiers":[
        {
            "category":"Food & Beverages",
            "subcategory":"Bakery",
            "type":"Retail Goods"
        }
    ],
    "sg:phone":"+1 514 484 1189",
    "sg:postcode":"H4X 2A5",
    "sg:province":"QC",
    "sg:tags":[
        "shop",
        "cookie"
    ],
    "wof:name":"Patisserie Adar",
    "wof:placetype":"venue"
},
  "geometry": {"coordinates":[-73.66132399999999,45.458916],"type":"Point"}
}