{
  "type": "Feature",
  "properties": {
    "iso:country":"CA",
    "sg:address":"5458 Av Westminster",
    "sg:city":"Cote Saint-Luc",
    "sg:classifiers":[
        {
            "category":"Food & Beverages",
            "subcategory":"Bakery",
            "type":"Retail Goods"
        }
    ],
    "sg:phone":"+1 514 484 1189",
    "sg:postcode":"H4X 2A5",
    "sg:province":"QC",
    "sg:tags":[
        "shop",
        "cookie"
    ],
    "wof:name":"Patisserie Adar",
    "wof:placetype":"venue"
},
  "geometry": {"coordinates":[-73.661324,45.458916],"type":"Point"}
}