{
  "type": "Feature",
  "properties": {
    "iso:country":"CA",
    "sg:city":"Montreal",
    "sg:classifiers":[
        {
            "category":"Professional",
            "subcategory":"Management & Consulting",
            "type":"Services"
        }
    ],
    "sg:phone":"+1 514 483 2278",
    "sg:postcode":"H3W 3C3",
    "sg:province":"QC",
    "sg:tags":[
        "consultant",
        "business"
    ],
    "wof:name":"Kamel Consultant & Mgmt Svc",
    "wof:placetype":"venue"
},
  "geometry": {"coordinates":[-73.6312484741,45.4849700928],"type":"Point"}
}