{
  "type": "Feature",
  "properties": {
    "addr:full":"2260 Foster Ave Windsor ON N8W 5C9",
    "addr:housenumber":"2260",
    "addr:postcode":"n8w 5c9",
    "addr:street":"Foster Ave",
    "iso:country":"CA",
    "sg:address":"2260 Foster Ave",
    "sg:city":"Windsor",
    "sg:classifiers":[
        {
            "category":"Real Estate",
            "subcategory":"Real Estate Agent",
            "type":"Services"
        }
    ],
    "sg:phone":"+1 519 966 0881",
    "sg:postcode":"N8W 5C9",
    "sg:province":"ON",
    "wof:name":"Fuerland Realty Ltd",
    "wof:placetype":"venue"
},
  "geometry": {"coordinates":[-82.978172,42.276215],"type":"Point"}
}