{
  "type": "Feature",
  "properties": {
    "iso:country":"CA",
    "sg:address":"8294 Rue Hochelaga",
    "sg:city":"Montreal",
    "sg:classifiers":[
        {
            "category":"Health Services",
            "subcategory":"Doctor",
            "type":"Services"
        }
    ],
    "sg:phone":"+1 514 354 7771",
    "sg:postcode":"H1L 2L3",
    "sg:province":"QC",
    "sg:tags":[
        "clinic"
    ],
    "wof:name":"Clinique Medicale Lapointe",
    "wof:placetype":"venue"
},
  "geometry": {"coordinates":[-73.52224,45.597015],"type":"Point"}
}