{
  "type": "Feature",
  "properties": {
    "addr:full":"1087 Hornby St Vancouver BC V6Z 2S5",
    "addr:housenumber":"1087",
    "addr:postcode":"v6z 2s5",
    "addr:street":"Hornby St",
    "iso:country":"CA",
    "sg:address":"1087 Hornby St",
    "sg:city":"Vancouver",
    "sg:classifiers":[
        {
            "category":"Government",
            "subcategory":"Office",
            "type":"Public Place"
        }
    ],
    "sg:phone":"+1 604 732 8142",
    "sg:postcode":"V6Z 2S5",
    "sg:province":"BC",
    "sg:tags":[
        "federal",
        "affairs"
    ],
    "wof:name":"Consulate General-El Salvador",
    "wof:placetype":"venue"
},
  "geometry": {"coordinates":[-123.126502991,49.2797393799],"type":"Point"}
}