{
  "type": "Feature",
  "properties": {
    "addr:full":"9 Heritage Rd Markham ON L3P 1M3",
    "addr:housenumber":"9",
    "addr:postcode":"l3p 1m3",
    "addr:street":"Heritage Rd",
    "iso:country":"CA",
    "sg:address":"9 Heritage Rd",
    "sg:city":"Markham",
    "sg:classifiers":[
        {
            "category":"Manufacturing",
            "subcategory":"Printing",
            "type":"Manufacturing & Wholesale Goods"
        }
    ],
    "sg:phone":"+1 905 294 2200",
    "sg:postcode":"L3P 1M3",
    "sg:province":"ON",
    "sg:tags":[
        "newspaper",
        "publishing",
        "advertising"
    ],
    "wof:name":"Markham Economist & Sun Newppr",
    "wof:placetype":"venue"
},
  "geometry": {"coordinates":[-79.279343,43.871017],"type":"Point"}
}