{
  "type": "Feature",
  "properties": {
    "addr:full":"345 Boul Henri-Bourassa O Montreal QC H3L 1N9",
    "addr:housenumber":"345",
    "addr:postcode":"h3l 1n9",
    "addr:street":"Boul Henri-Bourassa O",
    "iso:country":"CA",
    "sg:address":"345 Boul Henri-Bourassa O",
    "sg:city":"Montreal",
    "sg:classifiers":[
        {
            "category":"Restaurant",
            "type":"Food & Drink"
        }
    ],
    "sg:phone":"+1 514 334 1266",
    "sg:postcode":"H3L 1N9",
    "sg:province":"QC",
    "sg:tags":[
        "shop",
        "coffee"
    ],
    "wof:name":"Cafe Malibu",
    "wof:placetype":"venue"
},
  "geometry": {"coordinates":[-73.669518,45.553387],"type":"Point"}
}