{
  "type": "Feature",
  "properties": {
    "addr:full":"348 Fraser St North Bay ON P1B 3W7",
    "addr:housenumber":"348",
    "addr:postcode":"p1b 3w7",
    "addr:street":"Fraser St",
    "iso:country":"CA",
    "sg:address":"348 Fraser St",
    "sg:city":"North Bay",
    "sg:classifiers":[
        {
            "category":"Professional",
            "subcategory":"Lawyer & Legal Services",
            "type":"Services"
        }
    ],
    "sg:phone":"+1 705 474 9680",
    "sg:postcode":"P1B 3W7",
    "sg:province":"ON",
    "sg:tags":[
        "attorney"
    ],
    "wof:name":"Bowness & Murray",
    "wof:placetype":"venue"
},
  "geometry": {"coordinates":[-79.465157,46.312553],"type":"Point"}
}