{
  "type": "Feature",
  "properties": {
    "addr:full":"Edmonton AB T5T 4J2",
    "addr:postcode":"t5t 4j2",
    "iso:country":"CA",
    "sg:city":"Edmonton",
    "sg:classifiers":[
        {
            "category":"Shopping",
            "type":"Retail Goods"
        }
    ],
    "sg:phone":"+1 780 444 1156",
    "sg:postcode":"T5T 4J2",
    "sg:province":"AB",
    "sg:tags":[
        "collectible",
        "coin",
        "dealer",
        "supply"
    ],
    "wof:name":"West Edmonton Coin & Stamp CO",
    "wof:placetype":"venue"
},
  "geometry": {"coordinates":[-113.615601,53.523586],"type":"Point"}
}