{
  "type": "Feature",
  "properties": {
    "addr:full":"131 3rd Ave W Assiniboia SK S0H 0B0",
    "addr:housenumber":"131",
    "addr:postcode":"s0h 0b0",
    "addr:street":"3Rd Ave W Assiniboia",
    "iso:country":"CA",
    "sg:address":"131 3rd Ave W",
    "sg:city":"Assiniboia",
    "sg:classifiers":[
        {
            "category":"Health Services",
            "subcategory":"Doctor",
            "type":"Services"
        }
    ],
    "sg:phone":"+1 306 642 4454",
    "sg:postcode":"S0H 0B0",
    "sg:province":"SK",
    "sg:tags":[
        "physician",
        "surgeon"
    ],
    "wof:name":"Glaeske, D MD",
    "wof:placetype":"venue"
},
  "geometry": {"coordinates":[-105.995422,49.632225],"type":"Point"}
}