{
  "type": "Feature",
  "properties": {
    "addr:full":"2341 Broad St Regina SK S4P 1Y9",
    "addr:housenumber":"2341",
    "addr:postcode":"s4p 1y9",
    "addr:street":"Broad St",
    "iso:country":"CA",
    "sg:address":"2341 Broad St",
    "sg:city":"Regina",
    "sg:classifiers":[
        {
            "category":"Professional",
            "subcategory":"Business Services",
            "type":"Services"
        }
    ],
    "sg:phone":"+1 306 522 2847",
    "sg:postcode":"S4P 1Y9",
    "sg:province":"SK",
    "sg:tags":[
        "translator",
        "interpreter"
    ],
    "wof:name":"Association of Translators",
    "wof:placetype":"venue"
},
  "geometry": {"coordinates":[-104.60610199,50.441734314],"type":"Point"}
}