{
  "type": "Feature",
  "properties": {
    "addr:full":"2650 Boul Rosemont Montreal QC H1Y 1L2",
    "addr:housenumber":"2650",
    "addr:postcode":"h1y 1l2",
    "addr:street":"Boul Rosemont",
    "iso:country":"CA",
    "sg:address":"2650 Boul Rosemont",
    "sg:city":"Montreal",
    "sg:classifiers":[
        {
            "category":"Food & Beverages",
            "subcategory":"Groceries & Convenience Stores",
            "type":"Retail Goods"
        }
    ],
    "sg:phone":"+1 514 727 0312",
    "sg:postcode":"H1Y 1L2",
    "sg:province":"QC",
    "sg:tags":[
        "grocer"
    ],
    "wof:name":"Marche A Gaboury & Fils Inc",
    "wof:placetype":"venue"
},
  "geometry": {"coordinates":[-73.584442,45.548519],"type":"Point"}
}