{
  "type": "Feature",
  "properties": {
    "iso:country":"CA",
    "sg:address":"3921 Boul Leman",
    "sg:city":"Laval",
    "sg:classifiers":[
        {
            "category":"Wholesale",
            "subcategory":"Machinery & Supplies",
            "type":"Manufacturing & Wholesale Goods"
        }
    ],
    "sg:phone":"+1 514 324 0440",
    "sg:postcode":"H7E 4V7",
    "sg:province":"QC",
    "sg:tags":[
        "equipment",
        "conveyor",
        "conveying"
    ],
    "wof:name":"Robert Plante Inc Entreprises",
    "wof:placetype":"venue"
},
  "geometry": {"coordinates":[-73.6723327637,45.6126480103],"type":"Point"}
}