{
  "type": "Feature",
  "properties": {
    "addr:full":"3022 Tutt St Kelowna BC V1Y 2H5",
    "addr:housenumber":"3022",
    "addr:postcode":"v1y 2h5",
    "addr:street":"Tutt St",
    "iso:country":"CA",
    "sg:address":"3022 Tutt St",
    "sg:city":"Kelowna",
    "sg:classifiers":[
        {
            "category":"Retail",
            "subcategory":"Photofinishing",
            "type":"Services"
        }
    ],
    "sg:phone":"+1 250 860 3563",
    "sg:postcode":"V1Y 2H5",
    "sg:province":"BC",
    "sg:tags":[
        "photographic",
        "supply"
    ],
    "wof:name":"Photography West",
    "wof:placetype":"venue"
},
  "geometry": {"coordinates":[-119.489944458,49.8629226685],"type":"Point"}
}