{
  "type": "Feature",
  "properties": {
    "addr:full":"Abbotsford BC V2T 6X1",
    "addr:postcode":"v2t 6x1",
    "iso:country":"CA",
    "sg:city":"Abbotsford",
    "sg:classifiers":[
        {
            "category":"Professional",
            "subcategory":"Accounting & Tax Preparation",
            "type":"Services"
        }
    ],
    "sg:phone":"+1 604 852 5758",
    "sg:postcode":"V2T 6X1",
    "sg:province":"BC",
    "sg:tags":[
        "accountant"
    ],
    "wof:name":"Manku & CO",
    "wof:placetype":"venue"
},
  "geometry": {"coordinates":[-122.32426452599999,49.0540428162],"type":"Point"}
}