{
  "type": "Feature",
  "properties": {
    "iso:country":"CA",
    "sg:address":"Hwy 540",
    "sg:city":"M'Chigeeng",
    "sg:classifiers":[
        {
            "category":"Autos & Motor Vehicles",
            "subcategory":"Fuel & Gas Station",
            "type":"Retail Goods"
        }
    ],
    "sg:phone":"+1 705 377 4728",
    "sg:postcode":"P0P 1G0",
    "sg:province":"ON",
    "sg:tags":[
        "oil"
    ],
    "wof:name":"Paul's Corner Store",
    "wof:placetype":"venue"
},
  "geometry": {"coordinates":[-83.1132659912,45.9308586121],"type":"Point"}
}