{
  "type": "Feature",
  "properties": {
    "addr:full":"179 Victoria St S Amherstburg ON N9V 3N5",
    "addr:housenumber":"179",
    "addr:postcode":"n9v 3n5",
    "addr:street":"Victoria St S",
    "iso:country":"CA",
    "sg:address":"179 Victoria St S",
    "sg:city":"Amherstburg",
    "sg:classifiers":[
        {
            "category":"Recreation",
            "type":"Entertainment"
        }
    ],
    "sg:phone":"+1 519 736 3367",
    "sg:postcode":"N9V 3N5",
    "sg:province":"ON",
    "sg:tags":[
        "government",
        "hall",
        "auditorium"
    ],
    "wof:name":"Amherstburg Community Ctr",
    "wof:placetype":"venue"
},
  "geometry": {"coordinates":[-83.100517,42.10495],"type":"Point"}
}