{
  "type": "Feature",
  "properties": {
    "addr:full":"201 Ch Yvon-L'Heureux Mcmasterville QC J3G 5H7",
    "addr:housenumber":"201",
    "addr:postcode":"j3g 5h7",
    "addr:street":"Ch Yvon-L'Heureux",
    "iso:country":"CA",
    "sg:address":"201 Ch Yvon-L'Heureux",
    "sg:city":"Mcmasterville",
    "sg:classifiers":[
        {
            "category":"Autos & Motor Vehicles",
            "subcategory":"Auto Supplies",
            "type":"Retail Goods"
        }
    ],
    "sg:phone":"+1 450 467 8200",
    "sg:postcode":"J3G 5H7",
    "sg:province":"QC",
    "sg:tags":[
        "tire"
    ],
    "wof:name":"Sanco Recreation Inc",
    "wof:placetype":"venue"
},
  "geometry": {"coordinates":[-73.20725299999999,45.585403],"type":"Point"}
}