{
  "type": "Feature",
  "properties": {
    "addr:full":"331 Chesley Dr Saint John NB E2K 5P2",
    "addr:housenumber":"331",
    "addr:postcode":"e2k 5p2",
    "addr:street":"Chesley Dr",
    "iso:country":"CA",
    "sg:address":"331 Chesley Dr",
    "sg:city":"Saint John",
    "sg:classifiers":[
        {
            "category":"Wholesale",
            "subcategory":"Machinery & Supplies",
            "type":"Manufacturing & Wholesale Goods"
        }
    ],
    "sg:phone":"+1 506 635 8080",
    "sg:postcode":"E2K 5P2",
    "sg:province":"NB",
    "sg:tags":[
        "valve"
    ],
    "wof:name":"N L Eldridge & CO",
    "wof:placetype":"venue"
},
  "geometry": {"coordinates":[-66.0791854858,45.2665977478],"type":"Point"}
}