{
  "type": "Feature",
  "properties": {
    "addr:full":"Etobicoke ON M9B 6H7",
    "addr:postcode":"m9b 6h7",
    "iso:country":"CA",
    "sg:city":"Etobicoke",
    "sg:classifiers":[
        {
            "category":"Health Services",
            "subcategory":"Nursing And Care Facility",
            "type":"Services"
        }
    ],
    "sg:phone":"+1 416 443 0409",
    "sg:postcode":"M9B 6H7",
    "sg:province":"ON",
    "sg:tags":[
        "home",
        "convalescent"
    ],
    "wof:name":"Specialty Care Inc",
    "wof:placetype":"venue"
},
  "geometry": {"coordinates":[-79.5601730347,43.6480178833],"type":"Point"}
}