{
  "type": "Feature",
  "properties": {
    "addr:full":"160 Oak St W Bothwell ON N0P 1C0",
    "addr:housenumber":"160",
    "addr:postcode":"n0p 1c0",
    "addr:street":"Oak St W",
    "iso:country":"CA",
    "sg:address":"160 Oak St W",
    "sg:city":"Bothwell",
    "sg:classifiers":[
        {
            "category":"Food & Beverages",
            "subcategory":"Liquor & Beverages",
            "type":"Retail Goods"
        }
    ],
    "sg:phone":"+1 519 695 2731",
    "sg:postcode":"N0P 1C0",
    "sg:province":"ON",
    "sg:tags":[
        "beer",
        "ale"
    ],
    "wof:name":"Brewers' Retail Store",
    "wof:placetype":"venue"
},
  "geometry": {"coordinates":[-81.87111663819999,42.6293945312],"type":"Point"}
}