{
  "type": "Feature",
  "properties": {
    "addr:full":"300 Maclennan Cres #A Fort Mcmurray AB T9H 4G1",
    "addr:housenumber":"300",
    "addr:postcode":"t9h 4g1",
    "addr:street":"Maclennan Cres # A",
    "iso:country":"CA",
    "sg:address":"300 Maclennan Cres #A",
    "sg:city":"Fort Mcmurray",
    "sg:classifiers":[
        {
            "category":"Mining & Drilling",
            "type":"Manufacturing & Wholesale Goods"
        }
    ],
    "sg:phone":"+1 780 791 9170",
    "sg:postcode":"T9H 4G1",
    "sg:province":"AB",
    "sg:tags":[
        "laboratory",
        "oil",
        "field"
    ],
    "wof:name":"Maxxam Analytics Inc",
    "wof:placetype":"venue"
},
  "geometry": {"coordinates":[-111.323127747,56.6686668396],"type":"Point"}
}