{
  "type": "Feature",
  "properties": {
    "addr:full":"7171 Yonge St Thornhill ON L3T 2A9",
    "addr:housenumber":"7171",
    "addr:postcode":"l3t 2a9",
    "addr:street":"Yonge St",
    "iso:country":"CA",
    "sg:address":"7171 Yonge St",
    "sg:city":"Thornhill",
    "sg:classifiers":[
        {
            "category":"Retail",
            "subcategory":"Auto Repair",
            "type":"Services"
        }
    ],
    "sg:phone":"+1 416 221 2600",
    "sg:postcode":"L3T 2A9",
    "sg:province":"ON",
    "sg:tags":[
        "repairing",
        "automobile"
    ],
    "wof:name":"Murphy's Auto Svc",
    "wof:placetype":"venue"
},
  "geometry": {"coordinates":[-79.4211196899,43.8027305603],"type":"Point"}
}