{
  "type": "Feature",
  "properties": {
    "addr:full":"Burnaby BC V3N 4K4",
    "addr:postcode":"v3n 4k4",
    "iso:country":"CA",
    "sg:city":"Burnaby",
    "sg:classifiers":[
        {
            "category":"Building & Trades",
            "subcategory":"Construction",
            "type":"Services"
        }
    ],
    "sg:phone":"+1 604 521 5106",
    "sg:postcode":"V3N 4K4",
    "sg:province":"BC",
    "sg:tags":[
        "painter"
    ],
    "wof:name":"Mike's Painting & Decorating",
    "wof:placetype":"venue"
},
  "geometry": {"coordinates":[-122.940186,49.216],"type":"Point"}
}