{
  "type": "Feature",
  "properties": {
    "addr:full":"Woodbridge ON L4L 8L5",
    "addr:postcode":"l4l 8l5",
    "iso:country":"CA",
    "sg:city":"Woodbridge",
    "sg:classifiers":[
        {
            "category":"Shopping",
            "subcategory":"Computers & Home Electronics",
            "type":"Retail Goods"
        }
    ],
    "sg:phone":"+1 905 264 8886",
    "sg:postcode":"L4L 8L5",
    "sg:province":"ON",
    "sg:tags":[
        "equipment",
        "dealer"
    ],
    "wof:name":"Stratus Technologies Canada",
    "wof:placetype":"venue"
},
  "geometry": {"coordinates":[-79.55262,43.788219],"type":"Point"}
}