{
  "type": "Feature",
  "properties": {
    "addr:full":"2680 Boul Laframboise Saint-Hyacinthe QC J2S 4Y5",
    "addr:housenumber":"2680",
    "addr:postcode":"j2s 4y5",
    "addr:street":"Boul Laframboise",
    "iso:country":"CA",
    "sg:address":"2680 Boul Laframboise",
    "sg:city":"Saint-Hyacinthe",
    "sg:classifiers":[
        {
            "category":"Shopping",
            "subcategory":"Florist",
            "type":"Retail Goods"
        }
    ],
    "sg:phone":"+1 450 774 7475",
    "sg:postcode":"J2S 4Y5",
    "sg:province":"QC",
    "wof:name":"Au Jardin D'Eden Fleuriste Enr",
    "wof:placetype":"venue"
},
  "geometry": {"coordinates":[-72.95809199999999,45.633171],"type":"Point"}
}