{
  "type": "Feature",
  "properties": {
    "addr:full":"117 Rue Angers Sorel-Tracy QC J3P 5G9",
    "addr:housenumber":"117",
    "addr:postcode":"j3p 5g9",
    "addr:street":"Rue Angers",
    "iso:country":"CA",
    "sg:address":"117 Rue Angers",
    "sg:city":"Sorel-Tracy",
    "sg:classifiers":[
        {
            "category":"Building & Trades",
            "subcategory":"Electrical",
            "type":"Services"
        }
    ],
    "sg:phone":"+1 450 742 4554",
    "sg:postcode":"J3P 5G9",
    "sg:province":"QC",
    "sg:tags":[
        "electric",
        "contractor"
    ],
    "wof:name":"Conrad Lavoie Inc",
    "wof:placetype":"venue"
},
  "geometry": {"coordinates":[-73.126266,46.009701],"type":"Point"}
}