{
  "type": "Feature",
  "properties": {
    "addr:full":"950 Rue Du Centre Saint-Jude QC J0H 1P0",
    "addr:housenumber":"950",
    "addr:postcode":"j0h 1p0",
    "addr:street":"Rue Du Centre",
    "iso:country":"CA",
    "sg:address":"950 Rue Du Centre",
    "sg:city":"Saint-Jude",
    "sg:classifiers":[
        {
            "category":"Recreation",
            "type":"Entertainment"
        }
    ],
    "sg:phone":"+1 450 792 2164",
    "sg:postcode":"J0H 1P0",
    "sg:province":"QC",
    "sg:tags":[
        "center",
        "government"
    ],
    "wof:name":"St-Jude Loisirs",
    "wof:placetype":"venue"
},
  "geometry": {"coordinates":[-73.00567599999999,45.758316],"type":"Point"}
}