{
  "type": "Feature",
  "properties": {
    "iso:country":"CA",
    "sg:address":"10915 23 Ave NW",
    "sg:city":"Edmonton",
    "sg:classifiers":[
        {
            "category":"Autos & Motor Vehicles",
            "subcategory":"Fuel & Gas Station",
            "type":"Retail Goods"
        }
    ],
    "sg:phone":"+1 780 433 8467",
    "sg:postcode":"T6J 7B9",
    "sg:province":"AB",
    "sg:tags":[
        "oil"
    ],
    "wof:name":"Heritage Plaza Mohawk",
    "wof:placetype":"venue"
},
  "geometry": {"coordinates":[-113.509567,53.453583],"type":"Point"}
}