{
  "type": "Feature",
  "properties": {
    "addr:full":"Calgary AB T2S 3E6",
    "addr:postcode":"t2s 3e6",
    "iso:country":"CA",
    "sg:city":"Calgary",
    "sg:classifiers":[
        {
            "category":"Mining & Drilling",
            "type":"Manufacturing & Wholesale Goods"
        }
    ],
    "sg:phone":"+1 403 216 1855",
    "sg:postcode":"T2S 3E6",
    "sg:province":"AB",
    "sg:tags":[
        "consultant",
        "oil",
        "gas"
    ],
    "wof:name":"Image Interpretation Techs",
    "wof:placetype":"venue"
},
  "geometry": {"coordinates":[-114.06993103000001,51.0313453674],"type":"Point"}
}