{
  "type": "Feature",
  "properties": {
    "addr:full":"Ottawa ON K2P 1Y4",
    "addr:postcode":"k2p 1y4",
    "iso:country":"CA",
    "sg:city":"Ottawa",
    "sg:classifiers":[
        {
            "category":"Shopping",
            "subcategory":"Clothing, Apparel, & Fashions",
            "type":"Retail Goods"
        }
    ],
    "sg:phone":"+1 613 726 6997",
    "sg:postcode":"K2P 1Y4",
    "sg:province":"ON",
    "sg:tags":[
        "dressmaker",
        "tailor"
    ],
    "wof:name":"Ditoche's Fashion Designs",
    "wof:placetype":"venue"
},
  "geometry": {"coordinates":[-75.69491577150001,45.4134292603],"type":"Point"}
}