{
  "type": "Feature",
  "properties": {
    "addr:full":"380 Boul Arthur-Sauve Saint-Eustache QC J7R 2J4",
    "addr:housenumber":"380",
    "addr:postcode":"j7r 2j4",
    "addr:street":"Boul Arthur-Sauve",
    "iso:country":"CA",
    "sg:address":"380 Boul Arthur-Sauve",
    "sg:city":"Saint-Eustache",
    "sg:classifiers":[
        {
            "category":"Retail",
            "subcategory":"Auto Rental",
            "type":"Services"
        }
    ],
    "sg:phone":"+1 450 473 9570",
    "sg:postcode":"J7R 2J4",
    "sg:province":"QC",
    "sg:tags":[
        "renting",
        "automobile"
    ],
    "wof:name":"Location Pelletier",
    "wof:placetype":"venue"
},
  "geometry": {"coordinates":[-73.903549,45.562901],"type":"Point"}
}