{
  "type": "Feature",
  "properties": {
    "iso:country":"CA",
    "sg:city":"Kelowna",
    "sg:classifiers":[
        {
            "category":"Wholesale",
            "subcategory":"Medical Equipment & Supplies",
            "type":"Manufacturing & Wholesale Goods"
        }
    ],
    "sg:phone":"+1 250 860 1256",
    "sg:postcode":"V1Y 3H4",
    "sg:province":"BC",
    "sg:tags":[
        "physician",
        "surgeon"
    ],
    "wof:name":"Sheepskin Boutique",
    "wof:placetype":"venue"
},
  "geometry": {"coordinates":[-119.476799011,49.881023407],"type":"Point"}
}