{
  "type": "Feature",
  "properties": {
    "addr:full":"43 Rue Sainte-Anne Sainte-Anne-DE-Bellevue QC H9X 1L4",
    "addr:housenumber":"43",
    "addr:postcode":"h9x 1l4",
    "addr:street":"Rue Sainte-Anne",
    "iso:country":"CA",
    "sg:address":"43 Rue Sainte-Anne",
    "sg:city":"Sainte-Anne-DE-Bellevue",
    "sg:classifiers":[
        {
            "category":"Cinema",
            "subcategory":"Movie Rental",
            "type":"Entertainment"
        }
    ],
    "sg:phone":"+1 514 457 8777",
    "sg:postcode":"H9X 1L4",
    "sg:province":"QC",
    "sg:tags":[
        "leasing",
        "video",
        "disc",
        "tape"
    ],
    "wof:name":"Video Ouest",
    "wof:placetype":"venue"
},
  "geometry": {"coordinates":[-73.9524688721,45.4037246704],"type":"Point"}
}