{
  "type": "Feature",
  "properties": {
    "addr:full":"Victoria BC V8T 4E1",
    "addr:postcode":"v8t 4e1",
    "iso:country":"CA",
    "sg:city":"Victoria",
    "sg:classifiers":[
        {
            "category":"Personal",
            "subcategory":"Beauty Salon",
            "type":"Services"
        }
    ],
    "sg:phone":"+1 250 383 3227",
    "sg:postcode":"V8T 4E1",
    "sg:province":"BC",
    "wof:name":"Beauty Is Skin Deep Hair",
    "wof:placetype":"venue"
},
  "geometry": {"coordinates":[-123.358055115,48.4365692139],"type":"Point"}
}