{
  "type": "Feature",
  "properties": {
    "iso:country":"CA",
    "sg:address":"12186 Boul Laurentien",
    "sg:city":"Montreal",
    "sg:classifiers":[
        {
            "category":"Food & Beverages",
            "subcategory":"Bakery",
            "type":"Retail Goods"
        }
    ],
    "sg:phone":"+1 514 745 5221",
    "sg:postcode":"H4K 1M9",
    "sg:province":"QC",
    "sg:tags":[
        "baker"
    ],
    "wof:name":"Boulangerie-Patisseries Haddad",
    "wof:placetype":"venue"
},
  "geometry": {"coordinates":[-73.719254,45.527416],"type":"Point"}
}