{
  "type": "Feature",
  "properties": {
    "addr:full":"Toronto ON M5J 2T9",
    "addr:postcode":"m5j 2t9",
    "iso:country":"CA",
    "sg:city":"Toronto",
    "sg:classifiers":[
        {
            "category":"Professional",
            "subcategory":"Lawyer & Legal Services",
            "type":"Services"
        }
    ],
    "sg:phone":"+1 416 863 1500",
    "sg:postcode":"M5J 2T9",
    "sg:province":"ON",
    "sg:tags":[
        "attorney"
    ],
    "wof:name":"Bennett, Eldon J",
    "wof:placetype":"venue"
},
  "geometry": {"coordinates":[-79.37940216059999,43.6470794678],"type":"Point"}
}