{
  "type": "Feature",
  "properties": {
    "addr:full":"RR 3 STN Main Hanover ON N4N 3B9",
    "addr:postcode":"n4n 3b9",
    "addr:street":"Rr 3 Stn Main",
    "iso:country":"CA",
    "sg:address":"RR 3 STN Main",
    "sg:city":"Hanover",
    "sg:classifiers":[
        {
            "category":"Building & Trades",
            "subcategory":"Construction",
            "type":"Services"
        }
    ],
    "sg:phone":"+1 519 364 3898",
    "sg:postcode":"N4N 3B9",
    "sg:province":"ON",
    "sg:tags":[
        "maker",
        "cabinet"
    ],
    "wof:name":"Greg Robinson Construction",
    "wof:placetype":"venue"
},
  "geometry": {"coordinates":[-81.02582550050001,44.1523742676],"type":"Point"}
}