{
  "type": "Feature",
  "properties": {
    "iso:country":"CA",
    "sg:address":"5 Holland Dr",
    "sg:city":"Bolton",
    "sg:classifiers":[
        {
            "category":"Manufacturing",
            "subcategory":"Metals",
            "type":"Manufacturing & Wholesale Goods"
        }
    ],
    "sg:phone":"+1 905 857 2702",
    "sg:postcode":"L7E 1G7",
    "sg:province":"ON",
    "sg:tags":[
        "steel"
    ],
    "wof:name":"Sacco Steel",
    "wof:placetype":"venue"
},
  "geometry": {"coordinates":[-79.7294616699,43.8634757996],"type":"Point"}
}