{
  "type": "Feature",
  "properties": {
    "addr:full":"770 1 St SW Medicine Hat AB T1A 3Z6",
    "addr:housenumber":"770 1",
    "addr:postcode":"t1a 3z6",
    "addr:street":"St Sw",
    "iso:country":"CA",
    "sg:address":"770 1 St SW",
    "sg:city":"Medicine Hat",
    "sg:classifiers":[
        {
            "category":"Organizations",
            "subcategory":"Professional Association",
            "type":"Services"
        }
    ],
    "sg:phone":"+1 403 526 7877",
    "sg:postcode":"T1A 3Z6",
    "sg:province":"AB",
    "sg:tags":[
        "school"
    ],
    "wof:name":"Ymca Learning Ctr",
    "wof:placetype":"venue"
},
  "geometry": {"coordinates":[-110.70365099999999,50.039429],"type":"Point"}
}