{
  "type": "Feature",
  "properties": {
    "addr:full":"23408 Dewdney Trunk Rd Maple Ridge BC V2X 3L7",
    "addr:housenumber":"23408",
    "addr:postcode":"v2x 3l7",
    "addr:street":"Dewdney Trunk Rd",
    "iso:country":"CA",
    "sg:address":"23408 Dewdney Trunk Rd",
    "sg:city":"Maple Ridge",
    "sg:classifiers":[
        {
            "category":"Retail",
            "subcategory":"Auto Repair",
            "type":"Services"
        }
    ],
    "sg:phone":"+1 604 463 8626",
    "sg:postcode":"V2X 3L7",
    "sg:province":"BC",
    "sg:tags":[
        "repairing",
        "automobile"
    ],
    "wof:name":"Perkin Bros Automotive",
    "wof:placetype":"venue"
},
  "geometry": {"coordinates":[-122.572921753,49.2201652527],"type":"Point"}
}