{
  "type": "Feature",
  "properties": {
    "iso:country":"CA",
    "sg:address":"1086 Yonge St",
    "sg:city":"Toronto",
    "sg:classifiers":[
        {
            "category":"Restaurant",
            "type":"Food & Drink"
        }
    ],
    "sg:phone":"+1 416 929 1818",
    "sg:postcode":"M4W 2L4",
    "sg:province":"ON",
    "sg:tags":[
        "pizza"
    ],
    "wof:name":"Pizza Hut",
    "wof:placetype":"venue"
},
  "geometry": {"coordinates":[-79.390083,43.67804],"type":"Point"}
}