{
  "type": "Feature",
  "properties": {
    "addr:full":"Cambridge ON N1R 6B3",
    "addr:postcode":"n1r 6b3",
    "iso:country":"CA",
    "sg:city":"Cambridge",
    "sg:classifiers":[
        {
            "category":"Shopping",
            "subcategory":"Clothing, Apparel, & Fashions",
            "type":"Retail Goods"
        }
    ],
    "sg:phone":"+1 519 623 4835",
    "sg:postcode":"N1R 6B3",
    "sg:province":"ON",
    "wof:name":"Mariposa",
    "wof:placetype":"venue"
},
  "geometry": {"coordinates":[-80.32270050050001,43.3920707703],"type":"Point"}
}