{
  "type": "Feature",
  "properties": {
    "addr:full":"460 St Clair St Chatham ON N7L 3K8",
    "addr:housenumber":"460",
    "addr:postcode":"n7l 3k8",
    "addr:street":"St Clair St",
    "iso:country":"CA",
    "sg:address":"460 St Clair St",
    "sg:city":"Chatham",
    "sg:classifiers":[
        {
            "category":"Cinema",
            "subcategory":"Movie Rental",
            "type":"Entertainment"
        }
    ],
    "sg:phone":"+1 519 352 2772",
    "sg:postcode":"N7L 3K8",
    "sg:province":"ON",
    "sg:tags":[
        "leasing",
        "video",
        "disc",
        "tape"
    ],
    "wof:name":"Ann's Convenience & Video",
    "wof:placetype":"venue"
},
  "geometry": {"coordinates":[-82.20421600340001,42.418258667],"type":"Point"}
}