{
  "type": "Feature",
  "properties": {
    "iso:country":"CA",
    "sg:address":"26929 Fraser Hwy",
    "sg:city":"Aldergrove",
    "sg:classifiers":[
        {
            "category":"Building & Trades",
            "subcategory":"Construction",
            "type":"Services"
        }
    ],
    "sg:phone":"+1 604 856 4134",
    "sg:postcode":"V4W 3E4",
    "sg:province":"BC",
    "sg:tags":[
        "equipment",
        "kitchen",
        "maker",
        "cabinet"
    ],
    "wof:name":"Kitchen Korner",
    "wof:placetype":"venue"
},
  "geometry": {"coordinates":[-122.47845459,49.0585021973],"type":"Point"}
}