{
  "type": "Feature",
  "properties": {
    "addr:full":"884 Commercial Divers N Vancouver BC V5L 3Y5",
    "addr:housenumber":"884",
    "addr:postcode":"v5l 3y5",
    "addr:street":"Commercial Divers N",
    "iso:country":"CA",
    "sg:address":"884 Commercial Divers N",
    "sg:city":"Vancouver",
    "sg:classifiers":[
        {
            "category":"Personal",
            "subcategory":"Beauty Salon",
            "type":"Services"
        }
    ],
    "sg:phone":"+1 604 255 3659",
    "sg:postcode":"V5L 3Y5",
    "sg:province":"BC",
    "wof:name":"Vina Hair Design",
    "wof:placetype":"venue"
},
  "geometry": {"coordinates":[-123.069351,49.276909],"type":"Point"}
}