{
  "type": "Feature",
  "properties": {
    "addr:full":"Trenton ON K8V 6B1",
    "addr:postcode":"k8v 6b1",
    "iso:country":"CA",
    "sg:city":"Trenton",
    "sg:classifiers":[
        {
            "category":"Health Services",
            "subcategory":"Doctor",
            "type":"Services"
        }
    ],
    "sg:phone":"+1 613 392 3887",
    "sg:postcode":"K8V 6B1",
    "sg:province":"ON",
    "sg:tags":[
        "physician",
        "surgeon"
    ],
    "wof:name":"Gugliotta, D MD",
    "wof:placetype":"venue"
},
  "geometry": {"coordinates":[-77.57809399999999,44.101315],"type":"Point"}
}