{
  "type": "Feature",
  "properties": {
    "iso:country":"CA",
    "sg:address":"45 Rue Arcand",
    "sg:city":"Saint-Jean-Sur-Richelieu",
    "sg:classifiers":[
        {
            "category":"Freight",
            "type":"Transportation"
        }
    ],
    "sg:phone":"+1 450 358 1112",
    "sg:postcode":"J2X 5M6",
    "sg:province":"QC",
    "sg:tags":[
        "commercial",
        "storage"
    ],
    "wof:name":"Mini-Cubes Raymond & Quintal",
    "wof:placetype":"venue"
},
  "geometry": {"coordinates":[-73.2271270752,45.3181686401],"type":"Point"}
}