{
  "type": "Feature",
  "properties": {
    "iso:country":"CA",
    "sg:address":"221 West River Rd",
    "sg:city":"Cambridge",
    "sg:classifiers":[
        {
            "category":"Professional",
            "subcategory":"Computer Services",
            "type":"Services"
        }
    ],
    "sg:phone":"+1 519 622 5269",
    "sg:postcode":"N1S 2Z9",
    "sg:province":"ON",
    "sg:tags":[
        "consultant",
        "training"
    ],
    "wof:name":"Edge on Training",
    "wof:placetype":"venue"
},
  "geometry": {"coordinates":[-80.3211975098,43.336856842],"type":"Point"}
}