{
  "type": "Feature",
  "properties": {
    "addr:full":"192 Rue Saint-Germain E Rimouski QC G5L 1A8",
    "addr:housenumber":"192",
    "addr:postcode":"g5l 1a8",
    "addr:street":"Rue Saint-Germain E",
    "iso:country":"CA",
    "sg:address":"192 Rue Saint-Germain E",
    "sg:city":"Rimouski",
    "sg:classifiers":[
        {
            "category":"Insurance",
            "subcategory":"Insurance Agent",
            "type":"Services"
        }
    ],
    "sg:phone":"+1 418 723 7873",
    "sg:postcode":"G5L 1A8",
    "sg:province":"QC",
    "wof:name":"Wawanesa Cie Mutuelle D'Assur",
    "wof:placetype":"venue"
},
  "geometry": {"coordinates":[-68.519836,48.45533],"type":"Point"}
}