{
  "type": "Feature",
  "properties": {
    "addr:full":"636 Bloor St W Toronto ON M6G 1K7",
    "addr:housenumber":"636",
    "addr:postcode":"m6g 1k7",
    "addr:street":"Bloor St W",
    "iso:country":"CA",
    "sg:address":"636 Bloor St W",
    "sg:city":"Toronto",
    "sg:classifiers":[
        {
            "category":"Restaurant",
            "type":"Food & Drink"
        }
    ],
    "sg:phone":"+1 416 532 6172",
    "sg:postcode":"M6G 1K7",
    "sg:province":"ON",
    "wof:name":"Kfc",
    "wof:placetype":"venue"
},
  "geometry": {"coordinates":[-79.41467299999999,43.664501],"type":"Point"}
}