{
  "type": "Feature",
  "properties": {
    "addr:full":"600 Rue Shefford Bromont QC J2L 1C1",
    "addr:housenumber":"600",
    "addr:postcode":"j2l 1c1",
    "addr:street":"Rue Shefford",
    "iso:country":"CA",
    "sg:address":"600 Rue Shefford",
    "sg:city":"Bromont",
    "sg:classifiers":[
        {
            "category":"Real Estate",
            "subcategory":"Real Estate Agent",
            "type":"Services"
        }
    ],
    "sg:phone":"+1 450 534 2140",
    "sg:postcode":"J2L 1C1",
    "sg:province":"QC",
    "sg:tags":[
        "authorities",
        "housing"
    ],
    "wof:name":"Office Municipale D'Habitation",
    "wof:placetype":"venue"
},
  "geometry": {"coordinates":[-72.65267900000001,45.319183],"type":"Point"}
}