{
  "type": "Feature",
  "properties": {
    "addr:full":"173 Pender St E Vancouver BC V6A 1T6",
    "addr:housenumber":"173",
    "addr:postcode":"v6a 1t6",
    "addr:street":"Pender St E",
    "iso:country":"CA",
    "sg:address":"173 Pender St E",
    "sg:city":"Vancouver",
    "sg:classifiers":[
        {
            "category":"Food & Beverages",
            "subcategory":"Specialty",
            "type":"Retail Goods"
        }
    ],
    "sg:phone":"+1 604 662 3832",
    "sg:postcode":"V6A 1T6",
    "sg:province":"BC",
    "sg:tags":[
        "oriental",
        "furniture"
    ],
    "wof:name":"Yeu Hua Handicraft Industrial",
    "wof:placetype":"venue"
},
  "geometry": {"coordinates":[-123.100509644,49.2805290222],"type":"Point"}
}