{
  "type": "Feature",
  "properties": {
    "addr:full":"12 Church St St Catharines ON L2R 3B3",
    "addr:housenumber":"12",
    "addr:postcode":"l2r 3b3",
    "addr:street":"Church St",
    "iso:country":"CA",
    "sg:address":"12 Church St",
    "sg:city":"St Catharines",
    "sg:classifiers":[
        {
            "category":"Real Estate",
            "subcategory":"Real Estate Agent",
            "type":"Services"
        }
    ],
    "sg:phone":"+1 905 935 7272",
    "sg:postcode":"L2R 3B3",
    "sg:province":"ON",
    "wof:name":"Coldwell Banker Avmark Rlty",
    "wof:placetype":"venue"
},
  "geometry": {"coordinates":[-79.248817,43.157684],"type":"Point"}
}