{
  "type": "Feature",
  "properties": {
    "addr:full":"185 Sheppard Ave E North York ON M2N 3A8",
    "addr:housenumber":"185",
    "addr:postcode":"m2n 3a8",
    "addr:street":"Sheppard Ave E",
    "iso:country":"CA",
    "sg:address":"185 Sheppard Ave E",
    "sg:city":"North York",
    "sg:classifiers":[
        {
            "category":"Food & Beverages",
            "subcategory":"Bakery",
            "type":"Retail Goods"
        }
    ],
    "sg:phone":"+1 416 226 5945",
    "sg:postcode":"M2N 3A8",
    "sg:province":"ON",
    "sg:tags":[
        "doughnut"
    ],
    "wof:name":"Coffee Time Donuts",
    "wof:placetype":"venue"
},
  "geometry": {"coordinates":[-79.3994674683,43.7639389038],"type":"Point"}
}