{
  "type": "Feature",
  "properties": {
    "iso:country":"CA",
    "sg:address":"2 Orchid Pl",
    "sg:city":"Morden",
    "sg:classifiers":[
        {
            "category":"Building & Trades",
            "subcategory":"Construction",
            "type":"Services"
        }
    ],
    "sg:phone":"+1 204 822 5928",
    "sg:postcode":"R6M 1J6",
    "sg:province":"MB",
    "sg:tags":[
        "painter"
    ],
    "wof:name":"Valley Painting & Decorating",
    "wof:placetype":"venue"
},
  "geometry": {"coordinates":[-98.1165847778,49.1819267273],"type":"Point"}
}