{
  "type": "Feature",
  "properties": {
    "iso:country":"CA",
    "sg:address":"200 Mcintosh St",
    "sg:city":"Scarborough",
    "sg:classifiers":[
        {
            "category":"Organizations",
            "subcategory":"Religious Organization",
            "type":"Services"
        }
    ],
    "sg:phone":"+1 416 261 4222",
    "sg:postcode":"M1N 3Z3",
    "sg:province":"ON",
    "sg:tags":[
        "church"
    ],
    "wof:name":"St Paul's United Church",
    "wof:placetype":"venue"
},
  "geometry": {"coordinates":[-79.2511138916,43.7094230652],"type":"Point"}
}