{
  "type": "Feature",
  "properties": {
    "addr:full":"1180 Lorimar Dr Mississauga ON L5S 1M9",
    "addr:housenumber":"1180",
    "addr:postcode":"l5s 1m9",
    "addr:street":"Lorimar Dr",
    "iso:country":"CA",
    "sg:address":"1180 Lorimar Dr",
    "sg:city":"Mississauga",
    "sg:classifiers":[
        {
            "category":"Manufacturing",
            "subcategory":"Tools & Machinery",
            "type":"Manufacturing & Wholesale Goods"
        }
    ],
    "sg:phone":"+1 905 670 5110",
    "sg:postcode":"L5S 1M9",
    "sg:province":"ON",
    "sg:tags":[
        "woodworking"
    ],
    "wof:name":"Cooper & Horton Ltd Scm",
    "wof:placetype":"venue"
},
  "geometry": {"coordinates":[-79.6819152832,43.6707267761],"type":"Point"}
}