{
  "type": "Feature",
  "properties": {
    "addr:full":"116 Connell Park Rd Woodstock NB E7M 1M4",
    "addr:housenumber":"116",
    "addr:postcode":"e7m 1m4",
    "addr:street":"Connell Park Rd",
    "iso:country":"CA",
    "sg:address":"116 Connell Park Rd",
    "sg:city":"Woodstock",
    "sg:classifiers":[
        {
            "category":"Social Services",
            "subcategory":"Child Care",
            "type":"Services"
        }
    ],
    "sg:phone":"+1 506 328 3136",
    "sg:postcode":"E7M 1M4",
    "sg:province":"NB",
    "sg:tags":[
        "kindergarten",
        "academic",
        "school"
    ],
    "wof:name":"Woodstock Cooperative Preschl",
    "wof:placetype":"venue"
},
  "geometry": {"coordinates":[-67.581917,46.162971],"type":"Point"}
}