{
  "type": "Feature",
  "properties": {
    "addr:full":"Saint-Wenceslas QC G0Z 1J0",
    "addr:postcode":"g0z 1j0",
    "iso:country":"CA",
    "sg:city":"Saint-Wenceslas",
    "sg:classifiers":[
        {
            "category":"Manufacturing",
            "subcategory":"Tools & Machinery",
            "type":"Manufacturing & Wholesale Goods"
        }
    ],
    "sg:phone":"+1 819 224 4433",
    "sg:postcode":"G0Z 1J0",
    "sg:province":"QC",
    "sg:tags":[
        "machine",
        "shop",
        "equipment",
        "hydraulic",
        "supply"
    ],
    "wof:name":"Regy Hydraulique",
    "wof:placetype":"venue"
},
  "geometry": {"coordinates":[-72.303894,46.15015],"type":"Point"}
}