{
  "type": "Feature",
  "properties": {
    "addr:full":"4502 50 Ave St Paul AB T0A 3A2",
    "addr:housenumber":"4502",
    "addr:postcode":"t0a 3a2",
    "addr:street":"50 Ave",
    "iso:country":"CA",
    "sg:address":"4502 50 Ave",
    "sg:city":"St Paul",
    "sg:classifiers":[
        {
            "category":"Restaurant",
            "type":"Food & Drink"
        }
    ],
    "sg:phone":"+1 780 645 2441",
    "sg:postcode":"T0A 3A2",
    "sg:province":"AB",
    "wof:name":"Kfc",
    "wof:placetype":"venue"
},
  "geometry": {"coordinates":[-111.28238678,53.9915046692],"type":"Point"}
}