{
  "type": "Feature",
  "properties": {
    "addr:full":"1290 Outram Ave Windsor ON N9J 3S1",
    "addr:housenumber":"1290",
    "addr:postcode":"n9j 3s1",
    "addr:street":"Outram Ave",
    "iso:country":"CA",
    "sg:address":"1290 Outram Ave",
    "sg:city":"Windsor",
    "sg:classifiers":[
        {
            "category":"Building & Trades",
            "subcategory":"Construction",
            "type":"Services"
        }
    ],
    "sg:phone":"+1 519 978 9562",
    "sg:postcode":"N9J 3S1",
    "sg:province":"ON",
    "sg:tags":[
        "contractor",
        "general"
    ],
    "wof:name":"J Rauti General Contractors",
    "wof:placetype":"venue"
},
  "geometry": {"coordinates":[-83.0339126587,42.3178215027],"type":"Point"}
}