{
  "type": "Feature",
  "properties": {
    "addr:full":"907 Badke Rd Kelowna BC V1X 5Z5",
    "addr:housenumber":"907",
    "addr:postcode":"v1x 5z5",
    "addr:street":"Badke Rd",
    "iso:country":"CA",
    "sg:address":"907 Badke Rd",
    "sg:city":"Kelowna",
    "sg:classifiers":[
        {
            "category":"Education",
            "subcategory":"School",
            "type":"Public Place"
        }
    ],
    "sg:phone":"+1 250 862 2377",
    "sg:postcode":"V1X 5Z5",
    "sg:province":"BC",
    "wof:name":"Heritage Christian School",
    "wof:placetype":"venue"
},
  "geometry": {"coordinates":[-119.40428900000001,49.890881],"type":"Point"}
}