{
  "type": "Feature",
  "properties": {
    "addr:full":"455 Ch DE LA Presqu'Ile Le Gardeur QC J5Z 4C7",
    "addr:housenumber":"455",
    "addr:postcode":"j5z 4c7",
    "addr:street":"Ch De La Presqu'Ile;Gardeur",
    "iso:country":"CA",
    "sg:address":"455 Ch DE LA Presqu'Ile",
    "sg:city":"Le Gardeur",
    "sg:classifiers":[
        {
            "category":"Retail",
            "subcategory":"Animal Services",
            "type":"Services"
        }
    ],
    "sg:phone":"+1 450 470 1499",
    "sg:postcode":"J5Z 4C7",
    "sg:province":"QC",
    "sg:tags":[
        "pet",
        "boarding",
        "grooming",
        "washing",
        "sitting"
    ],
    "wof:name":"Centre Canin Legardeur",
    "wof:placetype":"venue"
},
  "geometry": {"coordinates":[-73.493752,45.768776],"type":"Point"}
}