{
  "type": "Feature",
  "properties": {
    "addr:full":"243 King St E Bowmanville ON L1C 3X1",
    "addr:housenumber":"243",
    "addr:postcode":"l1c 3x1",
    "addr:street":"King St",
    "iso:country":"CA",
    "sg:address":"243 King St E",
    "sg:city":"Bowmanville",
    "sg:classifiers":[
        {
            "category":"Food & Beverages",
            "subcategory":"Bakery",
            "type":"Retail Goods"
        }
    ],
    "sg:phone":"+1 905 623 0224",
    "sg:postcode":"L1C 3X1",
    "sg:province":"ON",
    "sg:tags":[
        "doughnut"
    ],
    "wof:name":"Coffee Time Donuts",
    "wof:placetype":"venue"
},
  "geometry": {"coordinates":[-78.674942,43.911491],"type":"Point"}
}