{
  "type": "Feature",
  "properties": {
    "iso:country":"CA",
    "sg:address":"2431 St Clair Ave W",
    "sg:city":"Toronto",
    "sg:classifiers":[
        {
            "category":"Organizations",
            "subcategory":"Religious Organization",
            "type":"Services"
        }
    ],
    "sg:phone":"+1 416 604 3447",
    "sg:postcode":"M6N 1K9",
    "sg:province":"ON",
    "sg:tags":[
        "church"
    ],
    "wof:name":"New Hope Tabernacle",
    "wof:placetype":"venue"
},
  "geometry": {"coordinates":[-79.482689,43.669025],"type":"Point"}
}