{
  "type": "Feature",
  "properties": {
    "addr:full":"9607 107 Ave Fort St John BC V1J 2P5",
    "addr:housenumber":"9607",
    "addr:postcode":"v1j 2p5",
    "addr:street":"107 Ave",
    "iso:country":"CA",
    "sg:address":"9607 107 Ave",
    "sg:city":"Fort St John",
    "sg:classifiers":[
        {
            "category":"Organizations",
            "subcategory":"Religious Organization",
            "type":"Services"
        }
    ],
    "sg:phone":"+1 250 785 4307",
    "sg:postcode":"V1J 2P5",
    "sg:province":"BC",
    "sg:tags":[
        "church"
    ],
    "wof:name":"Calvary Baptist Church",
    "wof:placetype":"venue"
},
  "geometry": {"coordinates":[-120.84073600000001,56.252689],"type":"Point"}
}