{
  "type": "Feature",
  "properties": {
    "addr:full":"426 Memorial Dr NE Calgary AB T2E 4Y7",
    "addr:housenumber":"426",
    "addr:postcode":"t2e 4y7",
    "addr:street":"Memorial Dr Ne",
    "iso:country":"CA",
    "sg:address":"426 Memorial Dr NE",
    "sg:city":"Calgary",
    "sg:classifiers":[
        {
            "category":"Retail",
            "subcategory":"Auto Repair",
            "type":"Services"
        }
    ],
    "sg:phone":"+1 403 262 9660",
    "sg:postcode":"T2E 4Y7",
    "sg:province":"AB",
    "sg:tags":[
        "body",
        "automobile",
        "painting"
    ],
    "wof:name":"Dnt Inc",
    "wof:placetype":"venue"
},
  "geometry": {"coordinates":[-114.05347399999999,51.051476],"type":"Point"}
}