{
  "type": "Feature",
  "properties": {
    "addr:full":"18550 96 Ave Surrey BC V4N 3P9",
    "addr:housenumber":"18550",
    "addr:postcode":"v4n 3p9",
    "addr:street":"96 Ave",
    "iso:country":"CA",
    "sg:address":"18550 96 Ave",
    "sg:city":"Surrey",
    "sg:classifiers":[
        {
            "category":"Manufacturing",
            "subcategory":"Motor Vehicles & Parts",
            "type":"Manufacturing & Wholesale Goods"
        }
    ],
    "sg:phone":"+1 604 882 9333",
    "sg:postcode":"V4N 3P9",
    "sg:province":"BC",
    "sg:tags":[
        "bus"
    ],
    "wof:name":"Dynamic Specialty Vehicles Ltd",
    "wof:placetype":"venue"
},
  "geometry": {"coordinates":[-122.70867200000001,49.176853],"type":"Point"}
}