{
  "type": "Feature",
  "properties": {
    "addr:full":"7770 Rte Transcanadienne Saint-Laurent QC H4T 1A5",
    "addr:postcode":"7770;h4t 1a5",
    "addr:street":"Rte Transcanadienne",
    "iso:country":"CA",
    "sg:address":"7770 Rte Transcanadienne",
    "sg:city":"Saint-Laurent",
    "sg:classifiers":[
        {
            "category":"Manufacturing",
            "subcategory":"Printing",
            "type":"Manufacturing & Wholesale Goods"
        }
    ],
    "sg:phone":"+1 514 735 7770",
    "sg:postcode":"H4T 1A5",
    "sg:province":"QC",
    "sg:tags":[
        "printer"
    ],
    "wof:name":"Impression Paragraph Inc",
    "wof:placetype":"venue"
},
  "geometry": {"coordinates":[-73.711472,45.48859],"type":"Point"}
}