{
  "type": "Feature",
  "properties": {
    "addr:full":"5151 Boul Industriel Montreal-Nord QC H1G 3H2",
    "addr:housenumber":"5151",
    "addr:postcode":"h1g 3h2",
    "addr:street":"Boul Industriel",
    "iso:country":"CA",
    "sg:address":"5151 Boul Industriel",
    "sg:city":"Montreal-Nord",
    "sg:classifiers":[
        {
            "category":"Wholesale",
            "subcategory":"Machinery & Supplies",
            "type":"Manufacturing & Wholesale Goods"
        }
    ],
    "sg:phone":"+1 514 325 9892",
    "sg:postcode":"H1G 3H2",
    "sg:province":"QC",
    "sg:tags":[
        "product",
        "wire"
    ],
    "wof:name":"Formafil Inc",
    "wof:placetype":"venue"
},
  "geometry": {"coordinates":[-73.62088,45.594799],"type":"Point"}
}