{
  "type": "Feature",
  "properties": {
    "iso:country":"CA",
    "sg:address":"540 Montreal St",
    "sg:city":"Kingston",
    "sg:classifiers":[
        {
            "category":"Manufacturing",
            "subcategory":"Tools & Machinery",
            "type":"Manufacturing & Wholesale Goods"
        }
    ],
    "sg:phone":"+1 613 548 7301",
    "sg:postcode":"K7K 3J2",
    "sg:province":"ON",
    "sg:tags":[
        "equipment",
        "hospital",
        "supply"
    ],
    "wof:name":"Kingston Oxygen Home Health",
    "wof:placetype":"venue"
},
  "geometry": {"coordinates":[-76.4875793457,44.2459983826],"type":"Point"}
}