{
  "type": "Feature",
  "properties": {
    "iso:country":"CA",
    "sg:city":"Saint-Charles-Sur-Richelieu",
    "sg:classifiers":[
        {
            "category":"Manufacturing",
            "subcategory":"Pet Food",
            "type":"Manufacturing & Wholesale Goods"
        }
    ],
    "sg:phone":"+1 450 584 2535",
    "sg:postcode":"J0H 2G0",
    "sg:province":"QC",
    "sg:tags":[
        "feed"
    ],
    "wof:name":"Agro-Bio Controle Inc",
    "wof:placetype":"venue"
},
  "geometry": {"coordinates":[-73.18409729,45.6901092529],"type":"Point"}
}