{
  "type": "Feature",
  "properties": {
    "addr:full":"718512 Hwy 6 Shallow Lake ON N0H 2K0",
    "addr:housenumber":"718512",
    "addr:postcode":"n0h 2k0",
    "addr:street":"Hwy 6 Shallow",
    "iso:country":"CA",
    "sg:address":"718512 Hwy 6",
    "sg:city":"Shallow Lake",
    "sg:classifiers":[
        {
            "category":"Building & Trades",
            "subcategory":"Plumbing",
            "type":"Services"
        }
    ],
    "sg:phone":"+1 519 376 6544",
    "sg:postcode":"N0H 2K0",
    "sg:province":"ON",
    "sg:tags":[
        "conditioning",
        "air",
        "refrigeration",
        "system",
        "contractor"
    ],
    "wof:name":"Top Air Ltd",
    "wof:placetype":"venue"
},
  "geometry": {"coordinates":[-81.04085499999999,44.594479],"type":"Point"}
}