{
  "type": "Feature",
  "properties": {
    "addr:full":"90 John St S Hamilton ON L8N 2C1",
    "addr:housenumber":"90",
    "addr:postcode":"l8n 2c1",
    "addr:street":"John St S",
    "iso:country":"CA",
    "sg:address":"90 John St S",
    "sg:city":"Hamilton",
    "sg:classifiers":[
        {
            "category":"Wholesale",
            "subcategory":"Machinery & Supplies",
            "type":"Manufacturing & Wholesale Goods"
        }
    ],
    "sg:phone":"+1 905 527 2093",
    "sg:postcode":"L8N 2C1",
    "sg:province":"ON",
    "sg:tags":[
        "salon",
        "beauty"
    ],
    "wof:name":"Laurenzo's School of Hair Dsgn",
    "wof:placetype":"venue"
},
  "geometry": {"coordinates":[-79.867828,43.25351],"type":"Point"}
}