{
  "type": "Feature",
  "properties": {
    "addr:full":"5720 Don Murie St Niagara Falls ON L2E 6X8",
    "addr:housenumber":"5720",
    "addr:postcode":"l2e 6x8",
    "addr:street":"Don Murie St",
    "iso:country":"CA",
    "sg:address":"5720 Don Murie St",
    "sg:city":"Niagara Falls",
    "sg:classifiers":[
        {
            "category":"Retail",
            "subcategory":"Auto Repair",
            "type":"Services"
        }
    ],
    "sg:phone":"+1 905 356 9060",
    "sg:postcode":"L2E 6X8",
    "sg:province":"ON",
    "sg:tags":[
        "lining",
        "brake"
    ],
    "wof:name":"Brunner Manufacturing & Sales",
    "wof:placetype":"venue"
},
  "geometry": {"coordinates":[-79.0876541138,43.0512886047],"type":"Point"}
}