{
  "type": "Feature",
  "properties": {
    "addr:full":"300 Borough Dr # 49 Scarborough ON M1P 4P5",
    "addr:housenumber":"300",
    "addr:postcode":"m1p 4p5",
    "addr:street":"Borough Dr # 49",
    "iso:country":"CA",
    "sg:address":"300 Borough Dr # 49",
    "sg:city":"Scarborough",
    "sg:classifiers":[
        {
            "category":"Shopping",
            "type":"Retail Goods"
        }
    ],
    "sg:phone":"+1 416 296 9160",
    "sg:postcode":"M1P 4P5",
    "sg:province":"ON",
    "sg:tags":[
        "telephone",
        "cellular"
    ],
    "wof:name":"Rogers At & T Wireless",
    "wof:placetype":"venue"
},
  "geometry": {"coordinates":[-79.25417299999999,43.775551],"type":"Point"}
}