{
  "type": "Feature",
  "properties": {
    "iso:country":"CA",
    "sg:address":"498 Jamison Ave",
    "sg:city":"Winnipeg",
    "sg:classifiers":[
        {
            "category":"Food & Beverages",
            "subcategory":"Groceries & Convenience Stores",
            "type":"Retail Goods"
        }
    ],
    "sg:phone":"+1 204 663 9069",
    "sg:postcode":"R2K 1N2",
    "sg:province":"MB",
    "sg:tags":[
        "grocer"
    ],
    "wof:name":"Jamison Food Mart",
    "wof:placetype":"venue"
},
  "geometry": {"coordinates":[-97.1005325317,49.9151573181],"type":"Point"}
}