{
  "type": "Feature",
  "properties": {
    "addr:full":"1221 King St W Toronto ON M6K 1G3",
    "addr:housenumber":"1221",
    "addr:postcode":"m6k 1g3",
    "addr:street":"King St W",
    "iso:country":"CA",
    "sg:address":"1221 King St W",
    "sg:city":"Toronto",
    "sg:classifiers":[
        {
            "category":"Restaurant",
            "type":"Food & Drink"
        }
    ],
    "sg:phone":"+1 416 532 8818",
    "sg:postcode":"M6K 1G3",
    "sg:province":"ON",
    "wof:name":"Mc Donald's",
    "wof:placetype":"venue"
},
  "geometry": {"coordinates":[-79.4281082153,43.6386528015],"type":"Point"}
}