{
  "type": "Feature",
  "properties": {
    "iso:country":"CA",
    "sg:address":"825 Laval Cres # D",
    "sg:city":"Kamloops",
    "sg:classifiers":[
        {
            "category":"Manufacturing",
            "subcategory":"Printing",
            "type":"Manufacturing & Wholesale Goods"
        }
    ],
    "sg:phone":"+1 250 828 0239",
    "sg:postcode":"V2C 5P2",
    "sg:province":"BC",
    "sg:tags":[
        "screen",
        "advertising"
    ],
    "wof:name":"Never Quit Promotion Inc",
    "wof:placetype":"venue"
},
  "geometry": {"coordinates":[-120.360076904,50.6614379883],"type":"Point"}
}