{
  "type": "Feature",
  "properties": {
    "iso:country":"CA",
    "sg:address":"167 Rue Bosse",
    "sg:city":"Chicoutimi",
    "sg:classifiers":[
        {
            "category":"Bars & Pubs",
            "type":"Food & Drink"
        }
    ],
    "sg:phone":"+1 418 543 0003",
    "sg:postcode":"G7J 1L5",
    "sg:province":"QC",
    "sg:tags":[
        "lounge",
        "cocktail"
    ],
    "wof:name":"Manoir Du Bassin Enr",
    "wof:placetype":"venue"
},
  "geometry": {"coordinates":[-71.073654,48.424519],"type":"Point"}
}