{
  "type": "Feature",
  "properties": {
    "addr:full":"Charlesbourg QC G1H 1Y8",
    "addr:postcode":"g1h 1y8",
    "iso:country":"CA",
    "sg:city":"Charlesbourg",
    "sg:classifiers":[
        {
            "category":"Manufacturing",
            "subcategory":"Food",
            "type":"Manufacturing & Wholesale Goods"
        }
    ],
    "sg:phone":"+1 418 627 9229",
    "sg:postcode":"G1H 1Y8",
    "sg:province":"QC",
    "sg:tags":[
        "cocoa",
        "chocolate"
    ],
    "wof:name":"Chocolat Creation Yvan Caron",
    "wof:placetype":"venue"
},
  "geometry": {"coordinates":[-71.25153400000001,46.845879],"type":"Point"}
}