{
  "type": "Feature",
  "properties": {
    "addr:full":"North York ON M5M 4A2",
    "addr:postcode":"m5m 4a2",
    "iso:country":"CA",
    "sg:city":"North York",
    "sg:classifiers":[
        {
            "category":"Shopping",
            "type":"Retail Goods"
        }
    ],
    "sg:phone":"+1 416 224 2567",
    "sg:postcode":"M5M 4A2",
    "sg:province":"ON",
    "sg:tags":[
        "cosmetic",
        "perfume"
    ],
    "wof:name":"Aloette Cosmetics of Toronto",
    "wof:placetype":"venue"
},
  "geometry": {"coordinates":[-79.41934999999999,43.733391],"type":"Point"}
}