{
  "type": "Feature",
  "properties": {
    "addr:full":"36 Rue Notre-Dame S Louiseville QC J5V 1Y3",
    "addr:housenumber":"36",
    "addr:postcode":"j5v 1y3",
    "addr:street":"Rue Notre-Dame S",
    "iso:country":"CA",
    "sg:address":"36 Rue Notre-Dame S",
    "sg:city":"Louiseville",
    "sg:classifiers":[
        {
            "category":"Food & Beverages",
            "subcategory":"Groceries & Convenience Stores",
            "type":"Retail Goods"
        }
    ],
    "sg:phone":"+1 819 228 3588",
    "sg:postcode":"J5V 1Y3",
    "sg:province":"QC",
    "wof:name":"Depanneur Notre-Dame Enr",
    "wof:placetype":"venue"
},
  "geometry": {"coordinates":[-72.93938446040001,46.2554359436],"type":"Point"}
}