{
  "type": "Feature",
  "properties": {
    "addr:full":"1214 Lincoln Rd Fredericton NB E3B 8C8",
    "addr:housenumber":"1214",
    "addr:postcode":"e3b 8c8",
    "addr:street":"Lincoln Rd",
    "iso:country":"CA",
    "sg:address":"1214 Lincoln Rd",
    "sg:city":"Fredericton",
    "sg:classifiers":[
        {
            "category":"Travel",
            "subcategory":"Hotels & Motels",
            "type":"Entertainment"
        }
    ],
    "sg:phone":"+1 506 458 8779",
    "sg:postcode":"E3B 8C8",
    "sg:province":"NB",
    "wof:name":"Budget Motel Ltd",
    "wof:placetype":"venue"
},
  "geometry": {"coordinates":[-66.60021999999999,45.922112],"type":"Point"}
}