{
  "type": "Feature",
  "properties": {
    "addr:full":"1341 Stevens Rd # 13 Kelowna BC V1Z 2S9",
    "addr:housenumber":"1341;13",
    "addr:postcode":"v1z 2s9",
    "addr:street":"Stevens Rd #",
    "iso:country":"CA",
    "sg:address":"1341 Stevens Rd # 13",
    "sg:city":"Kelowna",
    "sg:phone":"+1 250 769 6062",
    "sg:postcode":"V1Z 2S9",
    "sg:province":"BC",
    "sg:tags":[
        "equipment",
        "supply"
    ],
    "wof:name":"Arctech Food Equipment",
    "wof:placetype":"venue"
},
  "geometry": {"coordinates":[-119.57118199999999,49.866207],"type":"Point"}
}