{
  "type": "Feature",
  "properties": {
    "iso:country":"CA",
    "sg:address":"7811 Vantage Way",
    "sg:city":"Delta",
    "sg:classifiers":[
        {
            "category":"Autos & Motor Vehicles",
            "subcategory":"Boat Sales",
            "type":"Retail Goods"
        }
    ],
    "sg:phone":"+1 604 940 6308",
    "sg:postcode":"V4G 1A6",
    "sg:province":"BC",
    "sg:tags":[
        "dealer"
    ],
    "wof:name":"Inflatable Boat Sales",
    "wof:placetype":"venue"
},
  "geometry": {"coordinates":[-123.00669860799999,49.1413764954],"type":"Point"}
}