{
  "type": "Feature",
  "properties": {
    "addr:full":"5842 Hwy 34 Vankleek Hill ON K0B 1R0",
    "addr:housenumber":"5842",
    "addr:postcode":"k0b 1r0",
    "addr:street":"Hwy 34",
    "iso:country":"CA",
    "sg:address":"5842 Hwy 34",
    "sg:city":"Vankleek Hill",
    "sg:classifiers":[
        {
            "category":"Autos & Motor Vehicles",
            "subcategory":"Auto Supplies",
            "type":"Retail Goods"
        }
    ],
    "sg:phone":"+1 613 678 2005",
    "sg:postcode":"K0B 1R0",
    "sg:province":"ON",
    "sg:tags":[
        "tire"
    ],
    "wof:name":"Martin Tire Shop",
    "wof:placetype":"venue"
},
  "geometry": {"coordinates":[-74.651886,45.5205],"type":"Point"}
}