{
  "type": "Feature",
  "properties": {
    "addr:full":"Erin ON N0B 1T0",
    "addr:postcode":"n0b 1t0",
    "iso:country":"CA",
    "sg:city":"Erin",
    "sg:classifiers":[
        {
            "category":"Building & Trades",
            "subcategory":"Plumbing",
            "type":"Services"
        }
    ],
    "sg:phone":"+1 519 833 0316",
    "sg:postcode":"N0B 1T0",
    "sg:province":"ON",
    "sg:tags":[
        "refrigeration",
        "contractor"
    ],
    "wof:name":"Erin Refrigeration & Air Cond",
    "wof:placetype":"venue"
},
  "geometry": {"coordinates":[-80.079773,43.781803],"type":"Point"}
}