{
  "type": "Feature",
  "properties": {
    "addr:full":"45 Edgedale Way NW Calgary AB T3A 2P7",
    "addr:housenumber":"45",
    "addr:postcode":"t3a 2p7",
    "addr:street":"Edgedale Way Nw",
    "iso:country":"CA",
    "sg:address":"45 Edgedale Way NW",
    "sg:city":"Calgary",
    "sg:classifiers":[
        {
            "category":"Education",
            "subcategory":"Dance Studio",
            "type":"Public Place"
        }
    ],
    "sg:phone":"+1 403 239 0177",
    "sg:postcode":"T3A 2P7",
    "sg:province":"AB",
    "sg:tags":[
        "instruction",
        "dancing"
    ],
    "wof:name":"Square Dance Information",
    "wof:placetype":"venue"
},
  "geometry": {"coordinates":[-114.15982099999999,51.118225],"type":"Point"}
}