{
  "type": "Feature",
  "properties": {
    "addr:full":"Kelowna BC V1W 4V5",
    "addr:postcode":"v1w 4v5",
    "iso:country":"CA",
    "sg:city":"Kelowna",
    "sg:classifiers":[
        {
            "category":"Restaurant",
            "type":"Food & Drink"
        }
    ],
    "sg:phone":"+1 250 763 4643",
    "sg:postcode":"V1W 4V5",
    "sg:province":"BC",
    "sg:tags":[
        "caterer"
    ],
    "wof:name":"Focus Cafe",
    "wof:placetype":"venue"
},
  "geometry": {"coordinates":[-119.4895401,49.8569145203],"type":"Point"}
}