{
  "type": "Feature",
  "properties": {
    "addr:full":"114 9th St W Cornwall ON K6J 3A5",
    "addr:housenumber":"114",
    "addr:postcode":"k6j 3a5",
    "addr:street":"9Th St W",
    "iso:country":"CA",
    "sg:address":"114 9th St W",
    "sg:city":"Cornwall",
    "sg:classifiers":[
        {
            "category":"Building & Trades",
            "subcategory":"Electrical",
            "type":"Services"
        }
    ],
    "sg:phone":"+1 613 938 2429",
    "sg:postcode":"K6J 3A5",
    "sg:province":"ON",
    "sg:tags":[
        "electric",
        "contractor"
    ],
    "wof:name":"Moore Electric",
    "wof:placetype":"venue"
},
  "geometry": {"coordinates":[-74.737465,45.027767],"type":"Point"}
}