{
  "type": "Feature",
  "properties": {
    "iso:country":"CA",
    "sg:address":"3806 50 St",
    "sg:city":"Cold Lake",
    "sg:classifiers":[
        {
            "category":"Retail",
            "subcategory":"Auto Repair",
            "type":"Services"
        }
    ],
    "sg:phone":"+1 780 594 2240",
    "sg:postcode":"T9M 1S6",
    "sg:province":"AB",
    "sg:tags":[
        "body",
        "automobile",
        "painting"
    ],
    "wof:name":"Straightline Auto Body",
    "wof:placetype":"venue"
},
  "geometry": {"coordinates":[-110.20549,54.402309],"type":"Point"}
}