{
  "type": "Feature",
  "properties": {
    "addr:full":"Calgary AB T2R 1K7",
    "addr:postcode":"t2r 1k7",
    "iso:country":"CA",
    "sg:city":"Calgary",
    "sg:classifiers":[
        {
            "category":"Manufacturing",
            "subcategory":"Printing",
            "type":"Manufacturing & Wholesale Goods"
        }
    ],
    "sg:phone":"+1 403 245 9100",
    "sg:postcode":"T2R 1K7",
    "sg:province":"AB",
    "sg:tags":[
        "newspaper"
    ],
    "wof:name":"Globe & Mail Calgary",
    "wof:placetype":"venue"
},
  "geometry": {"coordinates":[-114.081893921,51.0420837402],"type":"Point"}
}