{
  "type": "Feature",
  "properties": {
    "addr:full":"1282 Alberni Hwy Parksville BC V9P 2C9",
    "addr:housenumber":"1282",
    "addr:postcode":"v9p 2c9",
    "addr:street":"Alberni Hwy",
    "iso:country":"CA",
    "sg:address":"1282 Alberni Hwy",
    "sg:city":"Parksville",
    "sg:classifiers":[
        {
            "category":"Manufacturing",
            "subcategory":"Lumber",
            "type":"Manufacturing & Wholesale Goods"
        }
    ],
    "sg:phone":"+1 250 248 5922",
    "sg:postcode":"V9P 2C9",
    "sg:province":"BC",
    "sg:tags":[
        "shingles",
        "shake"
    ],
    "wof:name":"Aquila Cedar Products Ltd",
    "wof:placetype":"venue"
},
  "geometry": {"coordinates":[-124.324532,49.307011],"type":"Point"}
}