{
  "type": "Feature",
  "properties": {
    "addr:full":"411 Ottawa St Almonte ON K0A 1A0",
    "addr:housenumber":"411",
    "addr:postcode":"k0a 1a0",
    "addr:street":"Ottawa St",
    "iso:country":"CA",
    "sg:address":"411 Ottawa St",
    "sg:city":"Almonte",
    "sg:classifiers":[
        {
            "category":"Bars & Pubs",
            "type":"Food & Drink"
        }
    ],
    "sg:phone":"+1 613 256 6336",
    "sg:postcode":"K0A 1A0",
    "sg:province":"ON",
    "wof:name":"Naismiths Sports Pub",
    "wof:placetype":"venue"
},
  "geometry": {"coordinates":[-76.184967,45.234116],"type":"Point"}
}