{
  "type": "Feature",
  "properties": {
    "addr:full":"1060 Arlington St Winnipeg MB R3E 2G3",
    "addr:housenumber":"1060",
    "addr:postcode":"r3e 2g3",
    "addr:street":"Arlington St",
    "iso:country":"CA",
    "sg:address":"1060 Arlington St",
    "sg:city":"Winnipeg",
    "sg:classifiers":[
        {
            "category":"Home & Garden",
            "subcategory":"Building Materials",
            "type":"Retail Goods"
        }
    ],
    "sg:phone":"+1 204 774 1611",
    "sg:postcode":"R3E 2G3",
    "sg:province":"MB",
    "sg:tags":[
        "glass",
        "window",
        "plate"
    ],
    "wof:name":"Ppg Canada Inc",
    "wof:placetype":"venue"
},
  "geometry": {"coordinates":[-97.16413116459999,49.9095535278],"type":"Point"}
}