{
  "type": "Feature",
  "properties": {
    "addr:full":"16 Great George St Charlottetown PE C1A 4J6",
    "addr:housenumber":"16",
    "addr:postcode":"c1a 4j6",
    "addr:street":"Great George St",
    "iso:country":"CA",
    "sg:address":"16 Great George St",
    "sg:city":"Charlottetown",
    "sg:classifiers":[
        {
            "category":"Professional",
            "subcategory":"Engineering",
            "type":"Services"
        }
    ],
    "sg:phone":"+1 902 628 8620",
    "sg:postcode":"C1A 4J6",
    "sg:province":"PE",
    "sg:tags":[
        "engineer"
    ],
    "wof:name":"Scl Engineering",
    "wof:placetype":"venue"
},
  "geometry": {"coordinates":[-63.123043,46.232876],"type":"Point"}
}