{
  "type": "Feature",
  "properties": {
    "addr:full":"67 Veronica St Cobourg ON K9A 4J9",
    "addr:housenumber":"67",
    "addr:postcode":"k9a 4j9",
    "addr:street":"Veronica St",
    "iso:country":"CA",
    "sg:address":"67 Veronica St",
    "sg:city":"Cobourg",
    "sg:classifiers":[
        {
            "category":"Government",
            "subcategory":"Office",
            "type":"Public Place"
        }
    ],
    "sg:phone":"+1 905 373 0582",
    "sg:postcode":"K9A 4J9",
    "sg:province":"ON",
    "sg:tags":[
        "village"
    ],
    "wof:name":"Cobourg Transit",
    "wof:placetype":"venue"
},
  "geometry": {"coordinates":[-78.177971,43.97953],"type":"Point"}
}