{
  "type": "Feature",
  "properties": {
    "addr:full":"135 Rang Charlotte Saint-Liboire QC J0H 1R0",
    "addr:housenumber":"135",
    "addr:postcode":"j0h 1r0",
    "addr:street":"Rang Charlotte",
    "iso:country":"CA",
    "sg:address":"135 Rang Charlotte",
    "sg:city":"Saint-Liboire",
    "sg:classifiers":[
        {
            "category":"Wholesale",
            "subcategory":"Plants",
            "type":"Manufacturing & Wholesale Goods"
        }
    ],
    "sg:phone":"+1 450 793 2765",
    "sg:postcode":"J0H 1R0",
    "sg:province":"QC",
    "sg:tags":[
        "florist"
    ],
    "wof:name":"Serres Beauregard Inc",
    "wof:placetype":"venue"
},
  "geometry": {"coordinates":[-72.76415299999999,45.690872],"type":"Point"}
}