{
  "type": "Feature",
  "properties": {
    "iso:country":"CA",
    "sg:address":"509 Bayfield St",
    "sg:city":"Barrie",
    "sg:classifiers":[
        {
            "category":"Food & Beverages",
            "subcategory":"Candy",
            "type":"Retail Goods"
        }
    ],
    "sg:phone":"+1 705 737 5405",
    "sg:postcode":"L4M 4Z8",
    "sg:province":"ON",
    "sg:tags":[
        "popcorn",
        "supply"
    ],
    "wof:name":"Kernels",
    "wof:placetype":"venue"
},
  "geometry": {"coordinates":[-79.711357,44.413925],"type":"Point"}
}