{
  "type": "Feature",
  "properties": {
    "addr:full":"220 Blind Line Orangeville ON L9W 4V2",
    "addr:housenumber":"220",
    "addr:postcode":"l9w 4v2",
    "addr:street":"Blind Line",
    "iso:country":"CA",
    "sg:address":"220 Blind Line",
    "sg:city":"Orangeville",
    "sg:classifiers":[
        {
            "category":"Education",
            "subcategory":"School",
            "type":"Public Place"
        }
    ],
    "sg:phone":"+1 519 941 7487",
    "sg:postcode":"L9W 4V2",
    "sg:province":"ON",
    "wof:name":"Credit Meadows Elementary Schl",
    "wof:placetype":"venue"
},
  "geometry": {"coordinates":[-80.116409,43.922447],"type":"Point"}
}