{
  "type": "Feature",
  "properties": {
    "iso:country":"CA",
    "sg:address":"100 Railway Ave W",
    "sg:city":"Spiritwood",
    "sg:classifiers":[
        {
            "category":"Government",
            "subcategory":"Office",
            "type":"Public Place"
        }
    ],
    "sg:phone":"+1 306 883 2905",
    "sg:postcode":"S0J 2M0",
    "sg:province":"SK",
    "wof:name":"Canada Medical Svc",
    "wof:placetype":"venue"
},
  "geometry": {"coordinates":[-107.514068603,53.3660888672],"type":"Point"}
}