{
  "type": "Feature",
  "properties": {
    "addr:full":"310 - 3495 Cambie Street Vancouver V5Z4R3",
    "addr:housenumber":"310 3495",
    "addr:postcode":"v5z4r3",
    "addr:street":"Cambie Street",
    "iso:country":"CA",
    "sg:address":"310 - 3495 Cambie Street",
    "sg:city":"Vancouver",
    "sg:classifiers":[
        {
            "category":"Professional",
            "subcategory":"Computer Services",
            "type":"Services"
        }
    ],
    "sg:postcode":"V5Z4R3",
    "sg:tags":[
        "saas",
        "cad",
        "planroom",
        "blueprint",
        "engineering",
        "architecture",
        "construction",
        "manufacturing",
        "real-estate",
        "trade-shows",
        "ajax",
        "3d"
    ],
    "sg:website":"http://www.aftercad.com",
    "wof:name":"Aftercad Software",
    "wof:placetype":"venue"
},
  "geometry": {"coordinates":[-123.1152075,49.2540299],"type":"Point"}
}