{
  "type": "Feature",
  "properties": {
    "addr:full":"1625 Northwest Blvd Creston BC V0B 1G6",
    "addr:housenumber":"1625",
    "addr:postcode":"bc v0b 1g6",
    "addr:street":"Northwest Blvd",
    "iso:country":"CA",
    "sg:address":"1625 Northwest Blvd",
    "sg:city":"Creston",
    "sg:classifiers":[
        {
            "category":"Autos & Motor Vehicles",
            "subcategory":"Automobile Sales",
            "type":"Retail Goods"
        }
    ],
    "sg:phone":"+1 250 428 5415",
    "sg:postcode":"V0B 1G6",
    "sg:province":"BC",
    "sg:tags":[
        "car",
        "dealer"
    ],
    "wof:name":"Creston Hyundai",
    "wof:placetype":"venue"
},
  "geometry": {"coordinates":[-116.523781,49.117512],"type":"Point"}
}