{
  "type": "Feature",
  "properties": {
    "addr:full":"16 Kyle Ave Mount Pearl NL A1N 4R5",
    "addr:housenumber":"16",
    "addr:postcode":"a1n 4r5",
    "addr:street":"Kyle Ave",
    "iso:country":"CA",
    "sg:address":"16 Kyle Ave",
    "sg:city":"Mount Pearl",
    "sg:classifiers":[
        {
            "category":"Mining & Drilling",
            "type":"Manufacturing & Wholesale Goods"
        }
    ],
    "sg:phone":"+1 709 748 4900",
    "sg:postcode":"A1N 4R5",
    "sg:province":"NL",
    "sg:tags":[
        "development",
        "gas",
        "oil",
        "exploration"
    ],
    "wof:name":"Baker Hughes Canada",
    "wof:placetype":"venue"
},
  "geometry": {"coordinates":[-52.8375244141,47.5158538818],"type":"Point"}
}