{
  "type": "Feature",
  "properties": {
    "addr:full":"721 Talbot St St Thomas ON N5P 1E1",
    "addr:housenumber":"721",
    "addr:postcode":"n5p 1e1",
    "addr:street":"Talbot St",
    "iso:country":"CA",
    "sg:address":"721 Talbot St",
    "sg:city":"St Thomas",
    "sg:classifiers":[
        {
            "category":"Shopping",
            "subcategory":"Jewelry",
            "type":"Retail Goods"
        }
    ],
    "sg:phone":"+1 519 631 3692",
    "sg:postcode":"N5P 1E1",
    "sg:province":"ON",
    "sg:tags":[
        "jeweler"
    ],
    "wof:name":"Muscat Jewellers",
    "wof:placetype":"venue"
},
  "geometry": {"coordinates":[-81.18779000000001,42.779072],"type":"Point"}
}