{
  "type": "Feature",
  "properties": {
    "iso:country":"CA",
    "sg:address":"Hwy 2 & Hwy 18",
    "sg:city":"Clyde",
    "sg:classifiers":[
        {
            "category":"Wholesale",
            "subcategory":"Farm Supplies",
            "type":"Manufacturing & Wholesale Goods"
        }
    ],
    "sg:phone":"+1 780 348 5893",
    "sg:postcode":"T0G 0P0",
    "sg:province":"AB",
    "sg:tags":[
        "auctioneer"
    ],
    "wof:name":"Nilsson Brothers Clyde",
    "wof:placetype":"venue"
},
  "geometry": {"coordinates":[-113.636520386,54.1469955444],"type":"Point"}
}