{
  "type": "Feature",
  "properties": {
    "iso:country":"CA",
    "sg:address":"28 Carnegie Cres",
    "sg:city":"Thornhill",
    "sg:classifiers":[
        {
            "category":"Building & Trades",
            "subcategory":"Construction",
            "type":"Services"
        }
    ],
    "sg:phone":"+1 905 889 9731",
    "sg:postcode":"L3T 5H1",
    "sg:province":"ON",
    "sg:tags":[
        "home",
        "improvement"
    ],
    "wof:name":"Provincial Design Ltd",
    "wof:placetype":"venue"
},
  "geometry": {"coordinates":[-79.39734649659999,43.8326568604],"type":"Point"}
}