{
  "type": "Feature",
  "properties": {
    "addr:full":"243 Dublin Ave Thunder Bay ON P7B 5A1",
    "addr:housenumber":"243",
    "addr:postcode":"p7b 5a1",
    "addr:street":"Dublin Ave",
    "iso:country":"CA",
    "sg:address":"243 Dublin Ave",
    "sg:city":"Thunder Bay",
    "sg:classifiers":[
        {
            "category":"Professional",
            "subcategory":"Art Services",
            "type":"Services"
        }
    ],
    "sg:phone":"+1 807 767 0343",
    "sg:postcode":"P7B 5A1",
    "sg:province":"ON",
    "sg:tags":[
        "graphic",
        "designer"
    ],
    "wof:name":"Degrazia Graphics & Design",
    "wof:placetype":"venue"
},
  "geometry": {"coordinates":[-89.25591300000001,48.449303],"type":"Point"}
}