{
  "type": "Feature",
  "properties": {
    "addr:full":"5725 Victoria Ave Niagara Falls ON L2G 3L5",
    "addr:housenumber":"5725",
    "addr:postcode":"l2g 3l5",
    "addr:street":"Victoria Ave",
    "iso:country":"CA",
    "sg:address":"5725 Victoria Ave",
    "sg:city":"Niagara Falls",
    "sg:classifiers":[
        {
            "category":"Shopping",
            "subcategory":"Gifts & Souvenirs",
            "type":"Retail Goods"
        }
    ],
    "sg:phone":"+1 905 354 8444",
    "sg:postcode":"L2G 3L5",
    "sg:province":"ON",
    "sg:tags":[
        "shop"
    ],
    "wof:name":"Super Souvenirs",
    "wof:placetype":"venue"
},
  "geometry": {"coordinates":[-79.07589,43.092342],"type":"Point"}
}