{
  "type": "Feature",
  "properties": {
    "iso:country":"CA",
    "sg:address":"PO Box 2",
    "sg:city":"Sibbald",
    "sg:classifiers":[
        {
            "category":"Travel",
            "subcategory":"Campground",
            "type":"Entertainment"
        }
    ],
    "sg:phone":"+1 403 676 0008",
    "sg:postcode":"T0J 3E0",
    "sg:province":"AB",
    "sg:tags":[
        "reservation",
        "motel",
        "hotel"
    ],
    "wof:name":"Sibbald Inn",
    "wof:placetype":"venue"
},
  "geometry": {"coordinates":[-110.148101807,51.3896751404],"type":"Point"}
}