{
  "type": "Feature",
  "properties": {
    "addr:full":"14398 Siphon Creek Rd Cecil Lake BC V0C 1G0",
    "addr:housenumber":"14398",
    "addr:postcode":"bc v0c 1g0",
    "addr:street":"Siphon Creek Rd",
    "iso:country":"CA",
    "sg:address":"14398 Siphon Creek Rd",
    "sg:city":"Cecil Lake",
    "sg:classifiers":[
        {
            "category":"Mining & Drilling",
            "type":"Manufacturing & Wholesale Goods"
        }
    ],
    "sg:phone":"+1 250 785 4835",
    "sg:postcode":"V0C 1G0",
    "sg:province":"BC",
    "sg:tags":[
        "consultant",
        "oil",
        "gas"
    ],
    "wof:name":"Joe Bell Inspections Ltd",
    "wof:placetype":"venue"
},
  "geometry": {"coordinates":[-120.622779846,56.3047103882],"type":"Point"}
}