{
  "type": "Feature",
  "properties": {
    "addr:full":"273 Centre St Drumheller AB T0J 0Y0",
    "addr:housenumber":"273",
    "addr:postcode":"t0j 0y0",
    "addr:street":"Centre St",
    "iso:country":"CA",
    "sg:address":"273 Centre St",
    "sg:city":"Drumheller",
    "sg:classifiers":[
        {
            "category":"Insurance",
            "subcategory":"Insurance Agent",
            "type":"Services"
        }
    ],
    "sg:phone":"+1 403 823 8888",
    "sg:postcode":"T0J 0Y0",
    "sg:province":"AB",
    "wof:name":"Rutz Agencies Ltd",
    "wof:placetype":"venue"
},
  "geometry": {"coordinates":[-112.592545,51.395473],"type":"Point"}
}