{
  "type": "Feature",
  "properties": {
    "addr:full":"444 George St Prince George BC V2L 1R6",
    "addr:housenumber":"444",
    "addr:postcode":"v2l 1r6",
    "addr:street":"George St",
    "iso:country":"CA",
    "sg:address":"444 George St",
    "sg:city":"Prince George",
    "sg:classifiers":[
        {
            "category":"Restaurant",
            "type":"Food & Drink"
        }
    ],
    "sg:phone":"+1 250 561 5670",
    "sg:postcode":"V2L 1R6",
    "sg:province":"BC",
    "wof:name":"Trader's Restaurant",
    "wof:placetype":"venue"
},
  "geometry": {"coordinates":[-122.74345398,53.914894104],"type":"Point"}
}