{
  "type": "Feature",
  "properties": {
    "addr:full":"Fort Nelson BC V0C 1R0",
    "addr:postcode":"bc v0c 1r0",
    "iso:country":"CA",
    "sg:city":"Fort Nelson",
    "sg:classifiers":[
        {
            "category":"Professional",
            "type":"Services"
        }
    ],
    "sg:phone":"+1 250 774 7077",
    "sg:postcode":"V0C 1R0",
    "sg:province":"BC",
    "sg:tags":[
        "establishment",
        "telephone",
        "cellular"
    ],
    "wof:name":"Quasar Communications Ltd",
    "wof:placetype":"venue"
},
  "geometry": {"coordinates":[-122.72794342,58.8047142029],"type":"Point"}
}