{
  "type": "Feature",
  "properties": {
    "addr:full":"6559 Olympia Pl Prince George BC V2K 4C4",
    "addr:housenumber":"6559",
    "addr:postcode":"v2k 4c4",
    "addr:street":"Olympia Pl",
    "iso:country":"CA",
    "sg:address":"6559 Olympia Pl",
    "sg:city":"Prince George",
    "sg:classifiers":[
        {
            "category":"Wholesale",
            "subcategory":"Construction Materials",
            "type":"Manufacturing & Wholesale Goods"
        }
    ],
    "sg:phone":"+1 250 962 2722",
    "sg:postcode":"V2K 4C4",
    "sg:province":"BC",
    "sg:tags":[
        "sand",
        "gravel"
    ],
    "wof:name":"Superior Crushing Ltd",
    "wof:placetype":"venue"
},
  "geometry": {"coordinates":[-122.764893,53.989578],"type":"Point"}
}