{
  "type": "Feature",
  "properties": {
    "iso:country":"CA",
    "sg:city":"Concord",
    "sg:classifiers":[
        {
            "category":"Building & Trades",
            "subcategory":"Plumbing",
            "type":"Services"
        }
    ],
    "sg:phone":"+1 905 738 8000",
    "sg:postcode":"L4K 3C4",
    "sg:province":"ON",
    "sg:tags":[
        "sheet",
        "work",
        "metal",
        "contractor"
    ],
    "wof:name":"Weldflow Metal Products Ltd",
    "wof:placetype":"venue"
},
  "geometry": {"coordinates":[-79.5301895142,43.7752838135],"type":"Point"}
}