{
  "type": "Feature",
  "properties": {
    "iso:country":"CA",
    "sg:city":"Calgary",
    "sg:classifiers":[
        {
            "category":"Shopping",
            "subcategory":"Stationery & Office Supplies",
            "type":"Retail Goods"
        }
    ],
    "sg:phone":"+1 403 254 9493",
    "sg:postcode":"T2X 2X7",
    "sg:province":"AB",
    "sg:tags":[
        "educational",
        "material"
    ],
    "wof:name":"Math-U-See",
    "wof:placetype":"venue"
},
  "geometry": {"coordinates":[-114.063126,50.914707],"type":"Point"}
}