{
  "type": "Feature",
  "properties": {
    "addr:full":"1 Thora Ave Scarborough ON M1L 2P7",
    "addr:housenumber":"1",
    "addr:postcode":"m1l 2p7",
    "addr:street":"Thora Ave",
    "iso:country":"CA",
    "sg:address":"1 Thora Ave",
    "sg:city":"Scarborough",
    "sg:classifiers":[
        {
            "category":"Wholesale",
            "subcategory":"Auto Parts",
            "type":"Manufacturing & Wholesale Goods"
        }
    ],
    "sg:phone":"+1 416 690 1058",
    "sg:postcode":"M1L 2P7",
    "sg:province":"ON",
    "sg:tags":[
        "automobile",
        "rebuilt",
        "wrecking"
    ],
    "wof:name":"Abe Jones Auto Wreckers",
    "wof:placetype":"venue"
},
  "geometry": {"coordinates":[-79.28578186039999,43.6899986267],"type":"Point"}
}