{
  "type": "Feature",
  "properties": {
    "iso:country":"CA",
    "sg:address":"125 Hunter Dr",
    "sg:city":"Amherstburg",
    "sg:classifiers":[
        {
            "category":"Manufacturing",
            "subcategory":"Metals",
            "type":"Manufacturing & Wholesale Goods"
        }
    ],
    "sg:phone":"+1 519 736 3523",
    "sg:postcode":"N9V 1W3",
    "sg:province":"ON",
    "sg:tags":[
        "glass"
    ],
    "wof:name":"Stained Glass Art By Larry",
    "wof:placetype":"venue"
},
  "geometry": {"coordinates":[-83.11237335209999,42.0533790588],"type":"Point"}
}