{
  "type": "Feature",
  "properties": {
    "addr:full":"2600 Rue Labrecque Quebec QC G1P 4R6",
    "addr:housenumber":"2600",
    "addr:postcode":"g1p 4r6",
    "addr:street":"Rue Labrecque",
    "iso:country":"CA",
    "sg:address":"2600 Rue Labrecque",
    "sg:city":"Quebec",
    "sg:classifiers":[
        {
            "category":"Organizations",
            "subcategory":"Religious Organization",
            "type":"Services"
        }
    ],
    "sg:phone":"+1 418 681 9663",
    "sg:postcode":"G1P 4R6",
    "sg:province":"QC",
    "sg:tags":[
        "home",
        "retirement",
        "community",
        "retreat",
        "house"
    ],
    "wof:name":"Manoir Duberger Reg",
    "wof:placetype":"venue"
},
  "geometry": {"coordinates":[-71.29606628419999,46.8120155334],"type":"Point"}
}