{
  "type": "Feature",
  "properties": {
    "addr:full":"North Vancouver BC V7L 2P7",
    "addr:postcode":"v7l 2p7",
    "iso:country":"CA",
    "sg:city":"North Vancouver",
    "sg:classifiers":[
        {
            "category":"Health Services",
            "subcategory":"Doctor",
            "type":"Services"
        }
    ],
    "sg:phone":"+1 604 988 1211",
    "sg:postcode":"V7L 2P7",
    "sg:province":"BC",
    "sg:tags":[
        "physician",
        "surgeon"
    ],
    "wof:name":"Hayward, James M MD",
    "wof:placetype":"venue"
},
  "geometry": {"coordinates":[-123.071358,49.321865],"type":"Point"}
}