{
  "type": "Feature",
  "properties": {
    "iso:country":"CA",
    "sg:city":"Montreal",
    "sg:classifiers":[
        {
            "category":"Restaurant",
            "type":"Food & Drink"
        }
    ],
    "sg:phone":"+1 514 861 9958",
    "sg:postcode":"H2Z 1Y6",
    "sg:province":"QC",
    "wof:name":"Restaurant Dobe & Andy",
    "wof:placetype":"venue"
},
  "geometry": {"coordinates":[-73.5612411499,45.5072593689],"type":"Point"}
}