{
  "type": "Feature",
  "properties": {
    "iso:country":"CA",
    "sg:address":"2840 Weston Rd",
    "sg:city":"North York",
    "sg:classifiers":[
        {
            "category":"Organizations",
            "subcategory":"Membership Organization",
            "type":"Services"
        }
    ],
    "sg:phone":"+1 416 740 3977",
    "sg:postcode":"M9M 2S3",
    "sg:province":"ON",
    "wof:name":"Era Community Living Svc",
    "wof:placetype":"venue"
},
  "geometry": {"coordinates":[-79.53756,43.720829],"type":"Point"}
}