{
  "type": "Feature",
  "properties": {
    "addr:full":"1315 Topsail Rd Ss 1 St. John's NL A1B 3N4",
    "addr:housenumber":"1315",
    "addr:postcode":"a1b 3n4",
    "addr:street":"Topsail Rd Ss 1 St.",
    "iso:country":"CA",
    "sg:address":"1315 Topsail Rd Ss 1",
    "sg:city":"St. John's",
    "sg:classifiers":[
        {
            "category":"Marine",
            "type":"Transportation"
        }
    ],
    "sg:phone":"+1 709 782 3355",
    "sg:postcode":"A1B 3N4",
    "sg:province":"NL",
    "sg:tags":[
        "company",
        "steamship"
    ],
    "wof:name":"Canship Limited",
    "wof:placetype":"venue"
},
  "geometry": {"coordinates":[-52.8462181091,47.5346450806],"type":"Point"}
}