{
  "type": "Feature",
  "properties": {
    "addr:full":"3 Worobetz Pl Saskatoon SK S7L 6R4",
    "addr:housenumber":"3",
    "addr:postcode":"s7l 6r4",
    "addr:street":"Worobetz Pl",
    "iso:country":"CA",
    "sg:address":"3 Worobetz Pl",
    "sg:city":"Saskatoon",
    "sg:classifiers":[
        {
            "category":"Food & Beverages",
            "subcategory":"Groceries & Convenience Stores",
            "type":"Retail Goods"
        }
    ],
    "sg:phone":"+1 306 384 8644",
    "sg:postcode":"S7L 6R4",
    "sg:province":"SK",
    "wof:name":"Diefenbaker Drive Self Serve",
    "wof:placetype":"venue"
},
  "geometry": {"coordinates":[-106.72783699999999,52.131493],"type":"Point"}
}