{
  "type": "Feature",
  "properties": {
    "iso:country":"CA",
    "sg:address":"6 Otter St",
    "sg:city":"Winnipeg",
    "sg:classifiers":[
        {
            "category":"Freight",
            "type":"Transportation"
        }
    ],
    "sg:phone":"+1 204 632 0366",
    "sg:postcode":"R3T 4J7",
    "sg:province":"MB",
    "wof:name":"Liaison Freight Svc",
    "wof:placetype":"venue"
},
  "geometry": {"coordinates":[-97.176971,49.841534],"type":"Point"}
}