{
  "type": "Feature",
  "properties": {
    "addr:full":"720 Rue Joseph Saint-Majorique QC J2B 8A8",
    "addr:housenumber":"720",
    "addr:postcode":"j2b 8a8",
    "addr:street":"Rue Joseph Saint-Majorique",
    "iso:country":"CA",
    "sg:address":"720 Rue Joseph",
    "sg:city":"Saint-Majorique",
    "sg:classifiers":[
        {
            "category":"Retail",
            "subcategory":"Auto Repair",
            "type":"Services"
        }
    ],
    "sg:phone":"+1 819 478 1976",
    "sg:postcode":"J2B 8A8",
    "sg:province":"QC",
    "sg:tags":[
        "repairing",
        "automobile"
    ],
    "wof:name":"Lemire Auto Suspension Inc",
    "wof:placetype":"venue"
},
  "geometry": {"coordinates":[-72.5691375732,45.9268531799],"type":"Point"}
}