{
  "type": "Feature",
  "properties": {
    "addr:full":"4725 44 Ave Bonnyville AB T9N 1N8",
    "addr:housenumber":"4725",
    "addr:postcode":"t9n 1n8",
    "addr:street":"44 Ave",
    "iso:country":"CA",
    "sg:address":"4725 44 Ave",
    "sg:city":"Bonnyville",
    "sg:classifiers":[
        {
            "category":"Restaurant",
            "type":"Food & Drink"
        }
    ],
    "sg:phone":"+1 780 826 3839",
    "sg:postcode":"T9N 1N8",
    "sg:province":"AB",
    "sg:tags":[
        "caterer"
    ],
    "wof:name":"Mrs C's Subs",
    "wof:placetype":"venue"
},
  "geometry": {"coordinates":[-110.735466,54.261902],"type":"Point"}
}