{
  "type": "Feature",
  "properties": {
    "addr:full":"Pr 231 Fraserwood MB R0C 1A0",
    "addr:postcode":"r0c 1a0",
    "addr:street":"Pr 231 Fraserwood",
    "iso:country":"CA",
    "sg:address":"Pr 231",
    "sg:city":"Fraserwood",
    "sg:classifiers":[
        {
            "category":"Retail",
            "subcategory":"Auto Repair",
            "type":"Services"
        }
    ],
    "sg:phone":"+1 204 643 5403",
    "sg:postcode":"R0C 1A0",
    "sg:province":"MB",
    "sg:tags":[
        "repairing",
        "automobile"
    ],
    "wof:name":"Welchinski Service",
    "wof:placetype":"venue"
},
  "geometry": {"coordinates":[-97.214462,50.642265],"type":"Point"}
}