{
  "type": "Feature",
  "properties": {
    "addr:full":"7325 Rue Ouimet Verdun QC H4H 2J6",
    "addr:housenumber":"7325",
    "addr:postcode":"h4h 2j6",
    "addr:street":"Rue Ouimet",
    "iso:country":"CA",
    "sg:address":"7325 Rue Ouimet",
    "sg:city":"Verdun",
    "sg:classifiers":[
        {
            "category":"Organizations",
            "subcategory":"Religious Organization",
            "type":"Services"
        }
    ],
    "sg:phone":"+1 514 766 0556",
    "sg:postcode":"H4H 2J6",
    "sg:province":"QC",
    "sg:tags":[
        "church"
    ],
    "wof:name":"All Saints Anglican Church",
    "wof:placetype":"venue"
},
  "geometry": {"coordinates":[-73.590225,45.437824],"type":"Point"}
}