{
  "type": "Feature",
  "properties": {
    "iso:country":"CA",
    "sg:address":"4210 50 Ave",
    "sg:city":"St Paul",
    "sg:classifiers":[
        {
            "category":"Shopping",
            "subcategory":"Clothing, Apparel, & Fashions",
            "type":"Retail Goods"
        }
    ],
    "sg:phone":"+1 780 645 3009",
    "sg:postcode":"T0A 3A2",
    "sg:province":"AB",
    "wof:name":"Reitmans",
    "wof:placetype":"venue"
},
  "geometry": {"coordinates":[-111.276062,53.991615],"type":"Point"}
}