{
  "type": "Feature",
  "properties": {
    "addr:full":"575 Dominion Ave Midland ON L4R 1R2",
    "addr:housenumber":"575",
    "addr:postcode":"l4r 1r2",
    "addr:street":"Dominion Ave",
    "iso:country":"CA",
    "sg:address":"575 Dominion Ave",
    "sg:city":"Midland",
    "sg:classifiers":[
        {
            "category":"Government",
            "subcategory":"Office",
            "type":"Public Place"
        }
    ],
    "sg:phone":"+1 705 526 4275",
    "sg:postcode":"L4R 1R2",
    "sg:province":"ON",
    "sg:tags":[
        "village"
    ],
    "wof:name":"Midland General Offices",
    "wof:placetype":"venue"
},
  "geometry": {"coordinates":[-79.8886642456,44.74974823],"type":"Point"}
}