{
  "type": "Feature",
  "properties": {
    "addr:full":"6651 Buswell St Richmond BC V6Y 2G9",
    "addr:housenumber":"6651",
    "addr:postcode":"v6y 2g9",
    "addr:street":"Buswell St",
    "iso:country":"CA",
    "sg:address":"6651 Buswell St",
    "sg:city":"Richmond",
    "sg:classifiers":[
        {
            "category":"Retail",
            "subcategory":"Repair Shop",
            "type":"Services"
        }
    ],
    "sg:phone":"+1 604 581 5000",
    "sg:postcode":"V6Y 2G9",
    "sg:province":"BC",
    "sg:tags":[
        "lock",
        "locksmith"
    ],
    "wof:name":"Al Scott Lock & Safe Ltd",
    "wof:placetype":"venue"
},
  "geometry": {"coordinates":[-123.133903503,49.1652793884],"type":"Point"}
}