{
  "type": "Feature",
  "properties": {
    "addr:full":"Brandon MB R7A 4G7",
    "addr:postcode":"r7a 4g7",
    "iso:country":"CA",
    "sg:city":"Brandon",
    "sg:classifiers":[
        {
            "category":"Shopping",
            "type":"Retail Goods"
        }
    ],
    "sg:phone":"+1 204 725 2531",
    "sg:postcode":"R7A 4G7",
    "sg:province":"MB",
    "sg:tags":[
        "picture",
        "frame"
    ],
    "wof:name":"Frame-Ups",
    "wof:placetype":"venue"
},
  "geometry": {"coordinates":[-99.95123291020001,49.8385925293],"type":"Point"}
}