{
  "type": "Feature",
  "properties": {
    "addr:full":"262 Catharine St Port Colborne ON L3K 4K9",
    "addr:housenumber":"262",
    "addr:postcode":"l3k 4k9",
    "addr:street":"Catharine St",
    "iso:country":"CA",
    "sg:address":"262 Catharine St",
    "sg:city":"Port Colborne",
    "sg:classifiers":[
        {
            "category":"Personal",
            "subcategory":"Beauty Salon",
            "type":"Services"
        }
    ],
    "sg:phone":"+1 905 835 9121",
    "sg:postcode":"L3K 4K9",
    "sg:province":"ON",
    "wof:name":"Golden Scissors",
    "wof:placetype":"venue"
},
  "geometry": {"coordinates":[-79.253029,42.886292],"type":"Point"}
}