{
  "type": "Feature",
  "properties": {
    "addr:full":"715 Rue Saint-Vallier E Quebec QC G1K 3P9",
    "addr:housenumber":"715",
    "addr:postcode":"g1k 3p9",
    "addr:street":"Rue Saint-Vallier E",
    "iso:country":"CA",
    "sg:address":"715 Rue Saint-Vallier E",
    "sg:city":"Quebec",
    "sg:classifiers":[
        {
            "category":"Retail",
            "subcategory":"Funeral Services",
            "type":"Services"
        }
    ],
    "sg:phone":"+1 418 529 3371",
    "sg:postcode":"G1K 3P9",
    "sg:province":"QC",
    "sg:tags":[
        "director"
    ],
    "wof:name":"Lepine-Cloutier Ltee",
    "wof:placetype":"venue"
},
  "geometry": {"coordinates":[-71.21914700000001,46.813362],"type":"Point"}
}