{
  "type": "Feature",
  "properties": {
    "addr:full":"172 King St W Brockville ON K6V 3R5",
    "addr:housenumber":"172",
    "addr:postcode":"k6v 3r5",
    "addr:street":"King St W",
    "iso:country":"CA",
    "sg:address":"172 King St W",
    "sg:city":"Brockville",
    "sg:classifiers":[
        {
            "category":"Restaurant",
            "type":"Food & Drink"
        }
    ],
    "sg:phone":"+1 613 342 0408",
    "sg:postcode":"K6V 3R5",
    "sg:province":"ON",
    "wof:name":"Golden Gate Restaurant",
    "wof:placetype":"venue"
},
  "geometry": {"coordinates":[-75.6871337891,44.588092804],"type":"Point"}
}