{
  "type": "Feature",
  "properties": {
    "addr:full":"305 Gifford Dr Ennismore ON K0L 1T0",
    "addr:housenumber":"305",
    "addr:postcode":"k0l 1t0",
    "addr:street":"Gifford Dr",
    "iso:country":"CA",
    "sg:address":"305 Gifford Dr",
    "sg:city":"Ennismore",
    "sg:classifiers":[
        {
            "category":"Building & Trades",
            "subcategory":"Plumbing",
            "type":"Services"
        }
    ],
    "sg:phone":"+1 705 292 9032",
    "sg:postcode":"K0L 1T0",
    "sg:province":"ON",
    "sg:tags":[
        "company",
        "gas",
        "heating",
        "contractor"
    ],
    "wof:name":"Quality Gas Heating & Cooling",
    "wof:placetype":"venue"
},
  "geometry": {"coordinates":[-78.42817700000001,44.410664],"type":"Point"}
}