{
  "type": "Feature",
  "properties": {
    "iso:country":"CA",
    "sg:city":"Vancouver",
    "sg:classifiers":[
        {
            "category":"Organizations",
            "subcategory":"Labor Organization",
            "type":"Services"
        }
    ],
    "sg:phone":"+1 604 876 0232",
    "sg:postcode":"V5Y 1B8",
    "sg:province":"BC",
    "wof:name":"Communications Energy Union",
    "wof:placetype":"venue"
},
  "geometry": {"coordinates":[-123.108421326,49.2694511414],"type":"Point"}
}