{
  "type": "Feature",
  "properties": {
    "iso:country":"CA",
    "sg:address":"3825 Rue DE Grenoble",
    "sg:city":"Jonquiere",
    "sg:classifiers":[
        {
            "category":"Building & Trades",
            "subcategory":"Construction",
            "type":"Services"
        }
    ],
    "sg:phone":"+1 418 542 9674",
    "sg:postcode":"G7X 9T2",
    "sg:province":"QC",
    "sg:tags":[
        "concrete",
        "contractor"
    ],
    "wof:name":"Construction Abs Inc",
    "wof:placetype":"venue"
},
  "geometry": {"coordinates":[-71.248138,48.395897],"type":"Point"}
}