{
  "type": "Feature",
  "properties": {
    "addr:full":"1439 Bloor St W Toronto ON M6P 3L7",
    "addr:housenumber":"1439",
    "addr:postcode":"m6p 3l7",
    "addr:street":"Bloor St W",
    "iso:country":"CA",
    "sg:address":"1439 Bloor St W",
    "sg:city":"Toronto",
    "sg:classifiers":[
        {
            "category":"Autos & Motor Vehicles",
            "subcategory":"Automobile Sales",
            "type":"Retail Goods"
        }
    ],
    "sg:phone":"+1 416 516 1664",
    "sg:postcode":"M6P 3L7",
    "sg:province":"ON",
    "sg:tags":[
        "car",
        "dealer"
    ],
    "wof:name":"Bloor Dundas Auto Ctr",
    "wof:placetype":"venue"
},
  "geometry": {"coordinates":[-79.4492492676,43.6568374634],"type":"Point"}
}