{
  "type": "Feature",
  "properties": {
    "iso:country":"CA",
    "sg:address":"344 High Park Ave",
    "sg:city":"Toronto",
    "sg:classifiers":[
        {
            "category":"Restaurant",
            "type":"Food & Drink"
        }
    ],
    "sg:phone":"+1 416 604 7255",
    "sg:postcode":"M6P 2S7",
    "sg:province":"ON",
    "wof:name":"Domino's Pizza",
    "wof:placetype":"venue"
},
  "geometry": {"coordinates":[-79.470085144,43.6643028259],"type":"Point"}
}