{
  "type": "Feature",
  "properties": {
    "iso:country":"CA",
    "sg:address":"1303 Av Maguire",
    "sg:city":"Sillery",
    "sg:classifiers":[
        {
            "category":"Professional",
            "subcategory":"Management & Consulting",
            "type":"Services"
        }
    ],
    "sg:phone":"+1 418 682 3157",
    "sg:postcode":"G1T 1Z2",
    "sg:province":"QC",
    "sg:tags":[
        "counselor",
        "public",
        "relations"
    ],
    "wof:name":"Alain Lemieux Affaires",
    "wof:placetype":"venue"
},
  "geometry": {"coordinates":[-71.2521514893,46.7813072205],"type":"Point"}
}