{
  "type": "Feature",
  "properties": {
    "addr:full":"3125 Spring Creek Cres Mississauga ON L5N 4S4",
    "addr:housenumber":"3125",
    "addr:postcode":"l5n 4s4",
    "addr:street":"Spring Creek Cres",
    "iso:country":"CA",
    "sg:address":"3125 Spring Creek Cres",
    "sg:city":"Mississauga",
    "sg:classifiers":[
        {
            "category":"Social Services",
            "type":"Services"
        }
    ],
    "sg:phone":"+1 905 542 0309",
    "sg:postcode":"L5N 4S4",
    "sg:province":"ON",
    "sg:tags":[
        "counselor",
        "marriage",
        "family"
    ],
    "wof:name":"Mareh Counselling Inc",
    "wof:placetype":"venue"
},
  "geometry": {"coordinates":[-79.7627029419,43.5766487122],"type":"Point"}
}