{
  "type": "Feature",
  "properties": {
    "addr:full":"109 Front St E Toronto ON M5A 4P7",
    "addr:housenumber":"109",
    "addr:postcode":"m5a 4p7",
    "addr:street":"Front St E",
    "iso:country":"CA",
    "sg:address":"109 Front St E",
    "sg:city":"Toronto",
    "sg:classifiers":[
        {
            "category":"Building & Trades",
            "subcategory":"Cleaning & Sanitation",
            "type":"Services"
        }
    ],
    "sg:phone":"+1 416 504 8766",
    "sg:postcode":"M5A 4P7",
    "sg:province":"ON",
    "sg:tags":[
        "property",
        "maintenance"
    ],
    "wof:name":"Metropolitan Toronto Condo Cor",
    "wof:placetype":"venue"
},
  "geometry": {"coordinates":[-79.3708648682,43.6495018005],"type":"Point"}
}