{
  "type": "Feature",
  "properties": {
    "addr:full":"Rosemere QC J7A 3T2",
    "addr:postcode":"j7a 3t2",
    "iso:country":"CA",
    "sg:city":"Rosemere",
    "sg:classifiers":[
        {
            "category":"Health Services",
            "subcategory":"Optometrist",
            "type":"Services"
        }
    ],
    "sg:phone":"+1 450 435 8890",
    "sg:postcode":"J7A 3T2",
    "sg:province":"QC",
    "wof:name":"Primeau, Jean-F OD",
    "wof:placetype":"venue"
},
  "geometry": {"coordinates":[-73.817199707,45.6328964233],"type":"Point"}
}