{
  "type": "Feature",
  "properties": {
    "iso:country":"CA",
    "sg:city":"Alban",
    "sg:classifiers":[
        {
            "category":"Recreation",
            "type":"Entertainment"
        }
    ],
    "sg:phone":"+1 705 857 3211",
    "sg:postcode":"P0M 1A0",
    "sg:province":"ON",
    "sg:tags":[
        "course",
        "golf"
    ],
    "wof:name":"Holiday Golf & Country Club",
    "wof:placetype":"venue"
},
  "geometry": {"coordinates":[-80.6227111816,46.1047058105],"type":"Point"}
}