{
  "type": "Feature",
  "properties": {
    "addr:full":"1490 Danforth Ave #202 Toronto ON M4J 1N4",
    "addr:housenumber":"1490",
    "addr:postcode":"m4j 1n4",
    "addr:street":"Danforth Ave # 202",
    "iso:country":"CA",
    "sg:address":"1490 Danforth Ave #202",
    "sg:city":"Toronto",
    "sg:classifiers":[
        {
            "category":"Health Services",
            "subcategory":"Doctor",
            "type":"Services"
        }
    ],
    "sg:phone":"+1 416 461 0156",
    "sg:postcode":"M4J 1N4",
    "sg:province":"ON",
    "sg:tags":[
        "dentist"
    ],
    "wof:name":"Taub, Harvey DDS",
    "wof:placetype":"venue"
},
  "geometry": {"coordinates":[-79.325768,43.682999],"type":"Point"}
}