{
  "type": "Feature",
  "properties": {
    "addr:full":"386 Ferguson Ave Ramore ON P0K 1R0",
    "addr:housenumber":"386",
    "addr:postcode":"p0k 1r0",
    "addr:street":"Ferguson Ave",
    "iso:country":"CA",
    "sg:address":"386 Ferguson Ave",
    "sg:city":"Ramore",
    "sg:classifiers":[
        {
            "category":"Restaurant",
            "type":"Food & Drink"
        }
    ],
    "sg:phone":"+1 705 236 4230",
    "sg:postcode":"P0K 1R0",
    "sg:province":"ON",
    "wof:name":"Simone Burgers & Fries",
    "wof:placetype":"venue"
},
  "geometry": {"coordinates":[-80.3252792358,48.4350814819],"type":"Point"}
}