{
  "type": "Feature",
  "properties": {
    "addr:full":"696 Bronson Ave Ottawa ON K1S 4G2",
    "addr:housenumber":"696",
    "addr:postcode":"k1s 4g2",
    "addr:street":"Bronson Ave",
    "iso:country":"CA",
    "sg:address":"696 Bronson Ave",
    "sg:city":"Ottawa",
    "sg:classifiers":[
        {
            "category":"Restaurant",
            "type":"Food & Drink"
        }
    ],
    "sg:phone":"+1 613 230 5102",
    "sg:postcode":"K1S 4G2",
    "sg:province":"ON",
    "wof:name":"Rasputin's",
    "wof:placetype":"venue"
},
  "geometry": {"coordinates":[-75.7004699707,45.4019546509],"type":"Point"}
}