{
  "type": "Feature",
  "properties": {
    "addr:full":"Calgary AB T2P 3J3",
    "addr:postcode":"t2p 3j3",
    "iso:country":"CA",
    "sg:city":"Calgary",
    "sg:classifiers":[
        {
            "category":"Real Estate",
            "subcategory":"Developer",
            "type":"Services"
        }
    ],
    "sg:phone":"+1 403 266 2029",
    "sg:postcode":"T2P 3J3",
    "sg:province":"AB",
    "sg:tags":[
        "company",
        "land"
    ],
    "wof:name":"Phasewest Corp",
    "wof:placetype":"venue"
},
  "geometry": {"coordinates":[-114.080711365,51.0471305847],"type":"Point"}
}