{
  "type": "Feature",
  "properties": {
    "addr:full":"153 Sunnyslope Ave Scarborough ON M1C 2P3",
    "addr:housenumber":"153",
    "addr:postcode":"m1c 2p3",
    "addr:street":"Sunnyslope Ave",
    "iso:country":"CA",
    "sg:address":"153 Sunnyslope Ave",
    "sg:city":"Scarborough",
    "sg:classifiers":[
        {
            "category":"Building & Trades",
            "subcategory":"Plumbing",
            "type":"Services"
        }
    ],
    "sg:phone":"+1 416 281 6910",
    "sg:postcode":"M1C 2P3",
    "sg:province":"ON",
    "sg:tags":[
        "heating",
        "contractor"
    ],
    "wof:name":"Toronto Furnace Maintenance",
    "wof:placetype":"venue"
},
  "geometry": {"coordinates":[-79.13665008540001,43.7968292236],"type":"Point"}
}