{
  "type": "Feature",
  "properties": {
    "iso:country":"CA",
    "sg:address":"3579 Mckay Ave",
    "sg:city":"Windsor",
    "sg:classifiers":[
        {
            "category":"Professional",
            "subcategory":"Lawyer & Legal Services",
            "type":"Services"
        }
    ],
    "sg:phone":"+1 519 256 7477",
    "sg:postcode":"N9E 2S1",
    "sg:province":"ON",
    "sg:tags":[
        "attorney"
    ],
    "wof:name":"Eziefule Law",
    "wof:placetype":"venue"
},
  "geometry": {"coordinates":[-83.0199050903,42.2575416565],"type":"Point"}
}