{
  "type": "Feature",
  "properties": {
    "iso:country":"CA",
    "sg:address":"Devil's Glen Country Hwy 24",
    "sg:city":"Collingwood",
    "sg:classifiers":[
        {
            "category":"Shopping",
            "subcategory":"Bicycles & Sporting Goods",
            "type":"Retail Goods"
        }
    ],
    "sg:phone":"+1 705 445 8796",
    "sg:postcode":"L9Y 3Z2",
    "sg:province":"ON",
    "sg:tags":[
        "resort",
        "skiing"
    ],
    "wof:name":"Squire John's At Devil's Glen",
    "wof:placetype":"venue"
},
  "geometry": {"coordinates":[-80.21678900000001,44.499908],"type":"Point"}
}