{
  "type": "Feature",
  "properties": {
    "addr:full":"St Pauls NL A0K 4Y0",
    "addr:postcode":"a0k 4y0",
    "iso:country":"CA",
    "sg:city":"St Pauls",
    "sg:classifiers":[
        {
            "category":"Government",
            "subcategory":"Office",
            "type":"Public Place"
        }
    ],
    "sg:phone":"+1 709 243 2279",
    "sg:postcode":"A0K 4Y0",
    "sg:province":"NL",
    "sg:tags":[
        "village"
    ],
    "wof:name":"St Pauls Community Council Ofc",
    "wof:placetype":"venue"
},
  "geometry": {"coordinates":[-57.806778,49.85223],"type":"Point"}
}