{
  "type": "Feature",
  "properties": {
    "addr:full":"9677 King George Hwy Surrey BC V3T 2V3",
    "addr:housenumber":"9677",
    "addr:postcode":"v3t 2v3",
    "addr:street":"King George Hwy",
    "iso:country":"CA",
    "sg:address":"9677 King George Hwy",
    "sg:city":"Surrey",
    "sg:classifiers":[
        {
            "category":"Restaurant",
            "type":"Food & Drink"
        }
    ],
    "sg:phone":"+1 604 588 7575",
    "sg:postcode":"V3T 2V3",
    "sg:province":"BC",
    "wof:name":"Knight & Day Restaurant",
    "wof:placetype":"venue"
},
  "geometry": {"coordinates":[-122.845985,49.178741],"type":"Point"}
}