{
  "type": "Feature",
  "properties": {
    "addr:full":"19 Pinelands Ave Stoney Creek ON L8E 3A4",
    "addr:housenumber":"19",
    "addr:postcode":"l8e 3a4",
    "addr:street":"Pinelands Ave",
    "iso:country":"CA",
    "sg:address":"19 Pinelands Ave",
    "sg:city":"Stoney Creek",
    "sg:classifiers":[
        {
            "category":"Manufacturing",
            "subcategory":"Tools & Machinery",
            "type":"Manufacturing & Wholesale Goods"
        }
    ],
    "sg:phone":"+1 905 664 2662",
    "sg:postcode":"L8E 3A4",
    "sg:province":"ON",
    "sg:tags":[
        "machine",
        "shop"
    ],
    "wof:name":"Tsw Machine Ltd",
    "wof:placetype":"venue"
},
  "geometry": {"coordinates":[-79.7347640991,43.2381095886],"type":"Point"}
}