{
  "type": "Feature",
  "properties": {
    "addr:full":"75 1st Ave Glenella MB R0J 0V0",
    "addr:housenumber":"75",
    "addr:postcode":"r0j 0v0",
    "addr:street":"1St Ave",
    "iso:country":"CA",
    "sg:address":"75 1st Ave",
    "sg:city":"Glenella",
    "sg:classifiers":[
        {
            "category":"Home & Garden",
            "subcategory":"Building Materials",
            "type":"Retail Goods"
        }
    ],
    "sg:phone":"+1 204 352 4232",
    "sg:postcode":"R0J 0V0",
    "sg:province":"MB",
    "wof:name":"Wilson Lumber",
    "wof:placetype":"venue"
},
  "geometry": {"coordinates":[-99.146553,50.572399],"type":"Point"}
}