{
  "type": "Feature",
  "properties": {
    "addr:full":"2780 Jane St # 306 North York ON M3N 2J2",
    "addr:housenumber":"2780",
    "addr:postcode":"m3n 2j2",
    "addr:street":"Jane St # 306",
    "iso:country":"CA",
    "sg:address":"2780 Jane St # 306",
    "sg:city":"North York",
    "sg:classifiers":[
        {
            "category":"Banks & Credit Unions",
            "subcategory":"Investment Brokerage",
            "type":"Services"
        }
    ],
    "sg:phone":"+1 416 742 9573",
    "sg:postcode":"M3N 2J2",
    "sg:province":"ON",
    "sg:tags":[
        "consultant",
        "planning",
        "financial"
    ],
    "wof:name":"Compare Financial Group",
    "wof:placetype":"venue"
},
  "geometry": {"coordinates":[-79.5154876709,43.7478256226],"type":"Point"}
}