{
  "type": "Feature",
  "properties": {
    "addr:full":"32 Rue Nadeau Leeds Village QC G0N 1J0",
    "addr:housenumber":"32",
    "addr:postcode":"g0n 1j0",
    "addr:street":"Rue Nadeau Leeds Village",
    "iso:country":"CA",
    "sg:address":"32 Rue Nadeau",
    "sg:city":"Leeds Village",
    "sg:classifiers":[
        {
            "category":"Manufacturing",
            "subcategory":"Buildings",
            "type":"Manufacturing & Wholesale Goods"
        }
    ],
    "sg:phone":"+1 418 424 3117",
    "sg:postcode":"G0N 1J0",
    "sg:province":"QC",
    "sg:tags":[
        "prefab"
    ],
    "wof:name":"Maitre Constructeur St-Jacques",
    "wof:placetype":"venue"
},
  "geometry": {"coordinates":[-71.33867600000001,46.288334],"type":"Point"}
}