{
  "type": "Feature",
  "properties": {
    "addr:full":"30 9th Ave E Whitehorse YT Y1A 4H1",
    "addr:housenumber":"30",
    "addr:postcode":"y1a 4h1",
    "addr:street":"9Th Ave E",
    "iso:country":"CA",
    "sg:address":"30 9th Ave E",
    "sg:city":"Whitehorse",
    "sg:classifiers":[
        {
            "category":"Building & Trades",
            "subcategory":"Landscaping Services",
            "type":"Services"
        }
    ],
    "sg:phone":"+1 867 668 4743",
    "sg:postcode":"Y1A 4H1",
    "sg:province":"YT",
    "sg:tags":[
        "excavating",
        "landscape",
        "contractor"
    ],
    "wof:name":"Whitehorse Bobcat Svc",
    "wof:placetype":"venue"
},
  "geometry": {"coordinates":[-135.128814697,60.7601165771],"type":"Point"}
}