{
  "type": "Feature",
  "properties": {
    "addr:full":"176 George St Arthur ON N0G 1A0",
    "addr:housenumber":"176",
    "addr:postcode":"n0g 1a0",
    "addr:street":"George St",
    "iso:country":"CA",
    "sg:address":"176 George St",
    "sg:city":"Arthur",
    "sg:classifiers":[
        {
            "category":"Personal",
            "subcategory":"Beauty Salon",
            "type":"Services"
        }
    ],
    "sg:phone":"+1 519 848 3300",
    "sg:postcode":"N0G 1A0",
    "sg:province":"ON",
    "wof:name":"Lady Boutique",
    "wof:placetype":"venue"
},
  "geometry": {"coordinates":[-80.536278,43.831207],"type":"Point"}
}