{
  "type": "Feature",
  "properties": {
    "addr:full":"2035 Fisher Dr Peterborough ON K9J 6X6",
    "addr:housenumber":"2035",
    "addr:postcode":"k9j 6x6",
    "addr:street":"Fisher Dr",
    "iso:country":"CA",
    "sg:address":"2035 Fisher Dr",
    "sg:city":"Peterborough",
    "sg:classifiers":[
        {
            "category":"Manufacturing",
            "subcategory":"Rubber & Plastics",
            "type":"Manufacturing & Wholesale Goods"
        }
    ],
    "sg:phone":"+1 705 742 4209",
    "sg:postcode":"K9J 6X6",
    "sg:province":"ON",
    "sg:tags":[
        "mold",
        "maker"
    ],
    "wof:name":"Merit Precision Molding Ltd",
    "wof:placetype":"venue"
},
  "geometry": {"coordinates":[-78.351624,44.262695],"type":"Point"}
}