{
  "type": "Feature",
  "properties": {
    "iso:country":"CA",
    "sg:address":"36 Harris Ave",
    "sg:city":"Truro",
    "sg:classifiers":[
        {
            "category":"Health Services",
            "subcategory":"Chiropractor",
            "type":"Services"
        }
    ],
    "sg:phone":"+1 902 895 8881",
    "sg:postcode":"B2N 3N2",
    "sg:province":"NS",
    "wof:name":"Gillam Chiropractic Clinic",
    "wof:placetype":"venue"
},
  "geometry": {"coordinates":[-63.283112,45.350842],"type":"Point"}
}