{
  "type": "Feature",
  "properties": {
    "addr:full":"New Denmark NB E7G 2T1",
    "addr:postcode":"e7g 2t1",
    "iso:country":"CA",
    "sg:city":"New Denmark",
    "sg:classifiers":[
        {
            "category":"Organizations",
            "subcategory":"Religious Organization",
            "type":"Services"
        }
    ],
    "sg:phone":"+1 506 553 6256",
    "sg:postcode":"E7G 2T1",
    "sg:province":"NB",
    "sg:tags":[
        "church"
    ],
    "wof:name":"Grace & Truth Tabernacle Inc",
    "wof:placetype":"venue"
},
  "geometry": {"coordinates":[-67.593681,46.995079],"type":"Point"}
}