{
  "type": "Feature",
  "properties": {
    "iso:country":"CA",
    "sg:address":"299 Lakeshore Dr",
    "sg:city":"Barrie",
    "sg:classifiers":[
        {
            "category":"Real Estate",
            "subcategory":"Real Estate Agent",
            "type":"Services"
        }
    ],
    "sg:phone":"+1 705 728 4067",
    "sg:postcode":"L4N 7Y9",
    "sg:province":"ON",
    "wof:name":"Royal Le Page First Contact",
    "wof:placetype":"venue"
},
  "geometry": {"coordinates":[-79.67289,44.372753],"type":"Point"}
}