{
  "type": "Feature",
  "properties": {
    "iso:country":"CA",
    "sg:address":"89 Prince William St E",
    "sg:city":"St Stephen",
    "sg:classifiers":[
        {
            "category":"Government",
            "subcategory":"Office",
            "type":"Public Place"
        }
    ],
    "sg:phone":"+1 506 466 7434",
    "sg:postcode":"E3L 1S8",
    "sg:province":"NB",
    "sg:tags":[
        "member",
        "legislative",
        "assembly"
    ],
    "wof:name":"Tony Huntiens Constituency Ofc",
    "wof:placetype":"venue"
},
  "geometry": {"coordinates":[-67.25909423829999,45.1916160583],"type":"Point"}
}