{
  "type": "Feature",
  "properties": {
    "iso:country":"CA",
    "sg:address":"4716 Curr Pl",
    "sg:city":"Burnaby",
    "sg:classifiers":[
        {
            "category":"Personal",
            "subcategory":"Beauty Salon",
            "type":"Services"
        }
    ],
    "sg:phone":"+1 604 435 1616",
    "sg:postcode":"V5G 3X9",
    "sg:province":"BC",
    "wof:name":"Cascade Beauty Salon",
    "wof:placetype":"venue"
},
  "geometry": {"coordinates":[-122.997520447,49.2375030518],"type":"Point"}
}