{
  "type": "Feature",
  "properties": {
    "iso:country":"CA",
    "sg:city":"Val-D'Or",
    "sg:classifiers":[
        {
            "category":"Health Services",
            "subcategory":"Optometrist",
            "type":"Services"
        }
    ],
    "sg:phone":"+1 819 874 8055",
    "sg:postcode":"J9P 5K1",
    "sg:province":"QC",
    "wof:name":"Greiche & Scaff",
    "wof:placetype":"venue"
},
  "geometry": {"coordinates":[-71.8758010864,48.4231758118],"type":"Point"}
}