{
  "type": "Feature",
  "properties": {
    "addr:full":"861 Rte 348 Saint-Ambroise-DE-Kildare QC J0K 1C0",
    "addr:housenumber":"861",
    "addr:postcode":"j0k 1c0",
    "addr:street":"Rte 348",
    "iso:country":"CA",
    "sg:address":"861 Rte 348",
    "sg:city":"Saint-Ambroise-DE-Kildare",
    "sg:classifiers":[
        {
            "category":"Professional",
            "subcategory":"Management & Consulting",
            "type":"Services"
        }
    ],
    "sg:phone":"+1 450 760 9999",
    "sg:postcode":"J0K 1C0",
    "sg:province":"QC",
    "sg:tags":[
        "venetian",
        "blind",
        "agricultural",
        "consultant"
    ],
    "wof:name":"Kildex Canada Ltee",
    "wof:placetype":"venue"
},
  "geometry": {"coordinates":[-73.554436,46.076778],"type":"Point"}
}