{
  "type": "Feature",
  "properties": {
    "addr:full":"170 Mcgibbon Dr Kanata ON K2L 4H5",
    "addr:housenumber":"170",
    "addr:postcode":"k2l 4h5",
    "addr:street":"Mcgibbon Dr",
    "iso:country":"CA",
    "sg:address":"170 Mcgibbon Dr",
    "sg:city":"Kanata",
    "sg:classifiers":[
        {
            "category":"Health Services",
            "subcategory":"Nursing And Care Facility",
            "type":"Services"
        }
    ],
    "sg:phone":"+1 613 271 0034",
    "sg:postcode":"K2L 4H5",
    "sg:province":"ON",
    "sg:tags":[
        "home",
        "retirement",
        "community"
    ],
    "wof:name":"Empress Kanata",
    "wof:placetype":"venue"
},
  "geometry": {"coordinates":[-75.907211,45.306881],"type":"Point"}
}