{
  "type": "Feature",
  "properties": {
    "addr:full":"195 James St S Hamilton ON L8P 3A8",
    "addr:housenumber":"195",
    "addr:postcode":"l8p 3a8",
    "addr:street":"James St S",
    "iso:country":"CA",
    "sg:address":"195 James St S",
    "sg:city":"Hamilton",
    "sg:classifiers":[
        {
            "category":"Professional",
            "subcategory":"Lawyer & Legal Services",
            "type":"Services"
        }
    ],
    "sg:phone":"+1 905 527 6900",
    "sg:postcode":"L8P 3A8",
    "sg:province":"ON",
    "sg:tags":[
        "attorney"
    ],
    "wof:name":"Mc Arthur Vereschagin",
    "wof:placetype":"venue"
},
  "geometry": {"coordinates":[-79.8715591431,43.2507743835],"type":"Point"}
}