{
  "type": "Feature",
  "properties": {
    "addr:full":"4 Fox St Leamington ON N8H 3H8",
    "addr:housenumber":"4",
    "addr:postcode":"n8h 3h8",
    "addr:street":"Fox St",
    "iso:country":"CA",
    "sg:address":"4 Fox St",
    "sg:city":"Leamington",
    "sg:classifiers":[
        {
            "category":"Health Services",
            "subcategory":"Optometrist",
            "type":"Services"
        }
    ],
    "sg:phone":"+1 519 326 8413",
    "sg:postcode":"N8H 3H8",
    "sg:province":"ON",
    "wof:name":"Adamson, B E OD",
    "wof:placetype":"venue"
},
  "geometry": {"coordinates":[-82.60230300000001,42.052357],"type":"Point"}
}