{
  "type": "Feature",
  "properties": {
    "iso:country":"CA",
    "sg:address":"1148 18th St",
    "sg:city":"Brandon",
    "sg:classifiers":[
        {
            "category":"Travel",
            "subcategory":"Hotels & Motels",
            "type":"Entertainment"
        }
    ],
    "sg:phone":"+1 204 728 5761",
    "sg:postcode":"R7A 5C2",
    "sg:province":"MB",
    "wof:name":"Western Motel Ltd",
    "wof:placetype":"venue"
},
  "geometry": {"coordinates":[-99.96212768549999,49.8321838379],"type":"Point"}
}