{
  "type": "Feature",
  "properties": {
    "addr:full":"184 Rue Principale Weedon QC J0B 3J0",
    "addr:housenumber":"184",
    "addr:postcode":"j0b 3j0",
    "addr:street":"Rue Principale",
    "iso:country":"CA",
    "sg:address":"184 Rue Principale",
    "sg:city":"Weedon",
    "sg:classifiers":[
        {
            "category":"Food & Beverages",
            "subcategory":"Groceries & Convenience Stores",
            "type":"Retail Goods"
        }
    ],
    "sg:phone":"+1 819 877 2314",
    "sg:postcode":"J0B 3J0",
    "sg:province":"QC",
    "wof:name":"Depanneur St-Gerard",
    "wof:placetype":"venue"
},
  "geometry": {"coordinates":[-71.41364299999999,45.756783],"type":"Point"}
}