{
  "type": "Feature",
  "properties": {
    "addr:full":"1112 Rymal Rd E Hamilton ON L8W 3N7",
    "addr:housenumber":"1112",
    "addr:postcode":"l8w 3n7",
    "addr:street":"Rymal Rd E",
    "iso:country":"CA",
    "sg:address":"1112 Rymal Rd E",
    "sg:city":"Hamilton",
    "sg:classifiers":[
        {
            "category":"Building & Trades",
            "subcategory":"Landscaping Services",
            "type":"Services"
        }
    ],
    "sg:phone":"+1 905 383 4488",
    "sg:postcode":"L8W 3N7",
    "sg:province":"ON",
    "sg:tags":[
        "landscape",
        "contractor"
    ],
    "wof:name":"Dicam Landscaping",
    "wof:placetype":"venue"
},
  "geometry": {"coordinates":[-79.84407,43.190392],"type":"Point"}
}