{
  "type": "Feature",
  "properties": {
    "addr:full":"Richmond BC V7A 5C6",
    "addr:postcode":"v7a 5c6",
    "iso:country":"CA",
    "sg:city":"Richmond",
    "sg:classifiers":[
        {
            "category":"Wholesale",
            "subcategory":"Machinery & Supplies",
            "type":"Manufacturing & Wholesale Goods"
        }
    ],
    "sg:phone":"+1 604 275 2750",
    "sg:postcode":"V7A 5C6",
    "sg:province":"BC",
    "sg:tags":[
        "hoist"
    ],
    "wof:name":"Kaverit Steel & Crane Ltd",
    "wof:placetype":"venue"
},
  "geometry": {"coordinates":[-123.100708,49.129486],"type":"Point"}
}