{
  "type": "Feature",
  "properties": {
    "addr:full":"2560 Rue Notre-Dame Lachine QC H8S 2G9",
    "addr:housenumber":"2560",
    "addr:postcode":"h8s 2g9",
    "addr:street":"Rue Notre-Dame",
    "iso:country":"CA",
    "sg:address":"2560 Rue Notre-Dame",
    "sg:city":"Lachine",
    "sg:classifiers":[
        {
            "category":"Home & Garden",
            "subcategory":"Home Furnishings",
            "type":"Retail Goods"
        }
    ],
    "sg:phone":"+1 514 634 9535",
    "sg:postcode":"H8S 2G9",
    "sg:province":"QC",
    "sg:tags":[
        "window",
        "covering"
    ],
    "wof:name":"Stores Mg",
    "wof:placetype":"venue"
},
  "geometry": {"coordinates":[-73.6869735718,45.434879303],"type":"Point"}
}