{
  "type": "Feature",
  "properties": {
    "addr:full":"4721 Marine Ave Powell River BC V8A 2L2",
    "addr:housenumber":"4721",
    "addr:postcode":"v8a 2l2",
    "addr:street":"Marine Ave Powell",
    "iso:country":"CA",
    "sg:address":"4721 Marine Ave",
    "sg:city":"Powell River",
    "sg:classifiers":[
        {
            "category":"Shopping",
            "subcategory":"Gifts & Souvenirs",
            "type":"Retail Goods"
        }
    ],
    "sg:phone":"+1 604 485 4820",
    "sg:postcode":"V8A 2L2",
    "sg:province":"BC",
    "sg:tags":[
        "shop"
    ],
    "wof:name":"Hindle's Camera & Stationery",
    "wof:placetype":"venue"
},
  "geometry": {"coordinates":[-124.529052734,49.8437805176],"type":"Point"}
}