{
  "type": "Feature",
  "properties": {
    "addr:full":"Mississauga ON L5B 2N6",
    "addr:postcode":"l5b 2n6",
    "iso:country":"CA",
    "sg:city":"Mississauga",
    "sg:classifiers":[
        {
            "category":"Social Services",
            "type":"Services"
        }
    ],
    "sg:phone":"+1 905 897 1644",
    "sg:postcode":"L5B 2N6",
    "sg:province":"ON",
    "sg:tags":[
        "organization",
        "counselor",
        "marriage",
        "family",
        "welfare"
    ],
    "wof:name":"Catholic Family Svc",
    "wof:placetype":"venue"
},
  "geometry": {"coordinates":[-79.6207733154,43.5766410828],"type":"Point"}
}