{
  "type": "Feature",
  "properties": {
    "iso:country":"CA",
    "sg:address":"1180 Rue Villeray",
    "sg:city":"Montreal",
    "sg:classifiers":[
        {
            "category":"Wholesale",
            "subcategory":"Meat",
            "type":"Manufacturing & Wholesale Goods"
        }
    ],
    "sg:phone":"+1 514 279 7770",
    "sg:postcode":"H2R 1J6",
    "sg:province":"QC",
    "sg:tags":[
        "butchering"
    ],
    "wof:name":"Boucherie Baderdine",
    "wof:placetype":"venue"
},
  "geometry": {"coordinates":[-73.61888885499999,45.5463638306],"type":"Point"}
}