{
  "type": "Feature",
  "properties": {
    "addr:full":"1550 Princess St Kingston ON K7M 9E3",
    "addr:housenumber":"1550",
    "addr:postcode":"k7m 9e3",
    "addr:street":"Princess St",
    "iso:country":"CA",
    "sg:address":"1550 Princess St",
    "sg:city":"Kingston",
    "sg:classifiers":[
        {
            "category":"Personal",
            "type":"Services"
        }
    ],
    "sg:phone":"+1 613 548 3574",
    "sg:postcode":"K7M 9E3",
    "sg:province":"ON",
    "sg:tags":[
        "recreation",
        "center",
        "program",
        "fitness",
        "exercise",
        "physical"
    ],
    "wof:name":"Ambassador Fun & Fitness",
    "wof:placetype":"venue"
},
  "geometry": {"coordinates":[-76.536339,44.252579],"type":"Point"}
}