{
  "type": "Feature",
  "properties": {
    "addr:full":"4839 Union Rd Beamsville ON L0R 1B4",
    "addr:housenumber":"4839",
    "addr:postcode":"l0r 1b4",
    "addr:street":"Union Rd",
    "iso:country":"CA",
    "sg:address":"4839 Union Rd",
    "sg:city":"Beamsville",
    "sg:classifiers":[
        {
            "category":"Manufacturing",
            "subcategory":"Metals",
            "type":"Manufacturing & Wholesale Goods"
        }
    ],
    "sg:phone":"+1 905 563 5306",
    "sg:postcode":"L0R 1B4",
    "sg:province":"ON",
    "sg:tags":[
        "treating",
        "heat"
    ],
    "wof:name":"Industrial Heat Treating",
    "wof:placetype":"venue"
},
  "geometry": {"coordinates":[-79.46659088129999,43.1826896667],"type":"Point"}
}