{
  "type": "Feature",
  "properties": {
    "addr:full":"1236 Rue Bergar Laval QC H7L 5A2",
    "addr:housenumber":"1236",
    "addr:postcode":"h7l 5a2",
    "addr:street":"Rue Bergar",
    "iso:country":"CA",
    "sg:address":"1236 Rue Bergar",
    "sg:city":"Laval",
    "sg:classifiers":[
        {
            "category":"Wholesale",
            "subcategory":"Metals & Minerals",
            "type":"Manufacturing & Wholesale Goods"
        }
    ],
    "sg:phone":"+1 450 975 8402",
    "sg:postcode":"H7L 5A2",
    "sg:province":"QC",
    "sg:tags":[
        "steel",
        "warehouse"
    ],
    "wof:name":"Alliages Anik Alloys Inc",
    "wof:placetype":"venue"
},
  "geometry": {"coordinates":[-73.747467,45.592457],"type":"Point"}
}