{
  "type": "Feature",
  "properties": {
    "addr:full":"420 Baseline Rd W Bowmanville ON L1C 3K3",
    "addr:housenumber":"420",
    "addr:postcode":"l1c 3k3",
    "addr:street":"Baseline Rd W",
    "iso:country":"CA",
    "sg:address":"420 Baseline Rd W",
    "sg:city":"Bowmanville",
    "sg:classifiers":[
        {
            "category":"Freight",
            "type":"Transportation"
        }
    ],
    "sg:phone":"+1 905 433 2441",
    "sg:postcode":"L1C 3K3",
    "sg:province":"ON",
    "sg:tags":[
        "mover"
    ],
    "wof:name":"Preston Moving & Storage",
    "wof:placetype":"venue"
},
  "geometry": {"coordinates":[-78.69399261469999,43.8972015381],"type":"Point"}
}