{
  "type": "Feature",
  "properties": {
    "addr:full":"2299 Mountain Dr Abbotsford BC V3G 1E6",
    "addr:housenumber":"2299",
    "addr:postcode":"v3g 1e6",
    "addr:street":"Mountain Dr",
    "iso:country":"CA",
    "sg:address":"2299 Mountain Dr",
    "sg:city":"Abbotsford",
    "sg:classifiers":[
        {
            "category":"Education",
            "subcategory":"School",
            "type":"Public Place"
        }
    ],
    "sg:phone":"+1 604 852 7299",
    "sg:postcode":"V3G 1E6",
    "sg:province":"BC",
    "wof:name":"Mountain Elementary",
    "wof:placetype":"venue"
},
  "geometry": {"coordinates":[-122.233643,49.042915],"type":"Point"}
}