{
  "type": "Feature",
  "properties": {
    "iso:country":"CA",
    "sg:city":"London",
    "sg:classifiers":[
        {
            "category":"Manufacturing",
            "subcategory":"Printing",
            "type":"Manufacturing & Wholesale Goods"
        }
    ],
    "sg:phone":"+1 519 457 1300",
    "sg:postcode":"N6G 2N3",
    "sg:province":"ON",
    "sg:tags":[
        "newspaper"
    ],
    "wof:name":"North London Beacon",
    "wof:placetype":"venue"
},
  "geometry": {"coordinates":[-81.282227,43.025509],"type":"Point"}
}