{
  "type": "Feature",
  "properties": {
    "addr:full":"605 Rue Maurice-Bois Vanier QC G1M 3G4",
    "addr:housenumber":"605",
    "addr:postcode":"g1m 3g4",
    "addr:street":"Rue Maurice-Bois",
    "iso:country":"CA",
    "sg:address":"605 Rue Maurice-Bois",
    "sg:city":"Vanier",
    "sg:classifiers":[
        {
            "category":"Autos & Motor Vehicles",
            "subcategory":"Auto Supplies",
            "type":"Retail Goods"
        }
    ],
    "sg:phone":"+1 418 687 3590",
    "sg:postcode":"G1M 3G4",
    "sg:province":"QC",
    "sg:tags":[
        "alternator",
        "generator"
    ],
    "wof:name":"Atelier Yh",
    "wof:placetype":"venue"
},
  "geometry": {"coordinates":[-71.279831,46.819664],"type":"Point"}
}