{
  "type": "Feature",
  "properties": {
    "addr:full":"2145 Ch Sainte-Foy Sainte-Foy QC G1V 1S1",
    "addr:housenumber":"2145",
    "addr:postcode":"g1v 1s1",
    "addr:street":"Ch Sainte-Foy",
    "iso:country":"CA",
    "sg:address":"2145 Ch Sainte-Foy",
    "sg:city":"Sainte-Foy",
    "sg:classifiers":[
        {
            "category":"Health Services",
            "subcategory":"Doctor",
            "type":"Services"
        }
    ],
    "sg:phone":"+1 418 683 3368",
    "sg:postcode":"G1V 1S1",
    "sg:province":"QC",
    "sg:tags":[
        "dentist"
    ],
    "wof:name":"Centre Dentaire Sainte-Foy",
    "wof:placetype":"venue"
},
  "geometry": {"coordinates":[-71.2917633057,46.7692108154],"type":"Point"}
}