{
  "type": "Feature",
  "properties": {
    "addr:full":"239 Boul Des Promenades Saint-Bruno QC J3V 5K3",
    "addr:housenumber":"239",
    "addr:postcode":"j3v 5k3",
    "addr:street":"Boul Des Promenades",
    "iso:country":"CA",
    "sg:address":"239 Boul Des Promenades",
    "sg:city":"Saint-Bruno",
    "sg:classifiers":[
        {
            "category":"Shopping",
            "subcategory":"Shoes",
            "type":"Retail Goods"
        }
    ],
    "sg:phone":"+1 450 461 1063",
    "sg:postcode":"J3V 5K3",
    "sg:province":"QC",
    "wof:name":"Naturalizer",
    "wof:placetype":"venue"
},
  "geometry": {"coordinates":[-71.67552185060001,48.4717712402],"type":"Point"}
}