{
  "type": "Feature",
  "properties": {
    "addr:full":"218 Kerr St Oakville ON L6K 3A8",
    "addr:housenumber":"218",
    "addr:postcode":"l6k 3a8",
    "addr:street":"Kerr St",
    "iso:country":"CA",
    "sg:address":"218 Kerr St",
    "sg:city":"Oakville",
    "sg:classifiers":[
        {
            "category":"Retail",
            "subcategory":"Veterinary Services",
            "type":"Services"
        }
    ],
    "sg:phone":"+1 905 845 1234",
    "sg:postcode":"L6K 3A8",
    "sg:province":"ON",
    "sg:tags":[
        "veterinarian"
    ],
    "wof:name":"Oakville Animal Clinic",
    "wof:placetype":"venue"
},
  "geometry": {"coordinates":[-79.678284,43.441658],"type":"Point"}
}