{
  "type": "Feature",
  "properties": {
    "addr:full":"169 Main St Dartmouth NS B2X 1S1",
    "addr:housenumber":"169",
    "addr:postcode":"b2x 1s1",
    "addr:street":"Main St",
    "iso:country":"CA",
    "sg:address":"169 Main St",
    "sg:city":"Dartmouth",
    "sg:classifiers":[
        {
            "category":"Personal",
            "subcategory":"Beauty Salon",
            "type":"Services"
        }
    ],
    "sg:phone":"+1 902 461 0791",
    "sg:postcode":"B2X 1S1",
    "sg:province":"NS",
    "wof:name":"Queen Nail",
    "wof:placetype":"venue"
},
  "geometry": {"coordinates":[-63.520980835,44.6863212585],"type":"Point"}
}