{
  "type": "Feature",
  "properties": {
    "addr:full":"188 E Stewart St Vanderhoof BC V0J 3A0",
    "addr:housenumber":"188",
    "addr:postcode":"v0j 3a0",
    "addr:street":"E Stewart St",
    "iso:country":"CA",
    "sg:address":"188 E Stewart St",
    "sg:city":"Vanderhoof",
    "sg:classifiers":[
        {
            "category":"Real Estate",
            "subcategory":"Real Estate Agent",
            "type":"Services"
        }
    ],
    "sg:phone":"+1 250 567 4414",
    "sg:postcode":"V0J 3A0",
    "sg:province":"BC",
    "sg:tags":[
        "cooperative"
    ],
    "wof:name":"Vanderhoof CO-OP Assn",
    "wof:placetype":"venue"
},
  "geometry": {"coordinates":[-124.00818633999999,54.0159568787],"type":"Point"}
}