{
  "type": "Feature",
  "properties": {
    "addr:full":"159 Main St Cambridge ON N1R 1W5",
    "addr:housenumber":"159",
    "addr:postcode":"n1r 1w5",
    "addr:street":"Main St",
    "iso:country":"CA",
    "sg:address":"159 Main St",
    "sg:city":"Cambridge",
    "sg:classifiers":[
        {
            "category":"Insurance",
            "subcategory":"Insurance Agent",
            "type":"Services"
        }
    ],
    "sg:phone":"+1 519 624 2150",
    "sg:postcode":"N1R 1W5",
    "sg:province":"ON",
    "wof:name":"Regal Insurance Brokers Inc",
    "wof:placetype":"venue"
},
  "geometry": {"coordinates":[-80.3097610474,43.3586273193],"type":"Point"}
}