{
  "type": "Feature",
  "properties": {
    "addr:full":"4140 Campbell Ave Prince George BC V2N 3A9",
    "addr:housenumber":"4140",
    "addr:postcode":"v2n 3a9",
    "addr:street":"Campbell Ave",
    "iso:country":"CA",
    "sg:address":"4140 Campbell Ave",
    "sg:city":"Prince George",
    "sg:classifiers":[
        {
            "category":"Education",
            "subcategory":"School",
            "type":"Public Place"
        }
    ],
    "sg:phone":"+1 250 562 5388",
    "sg:postcode":"V2N 3A9",
    "sg:province":"BC",
    "wof:name":"Pinewood Elementary School",
    "wof:placetype":"venue"
},
  "geometry": {"coordinates":[-122.798576,53.899361],"type":"Point"}
}