{
  "type": "Feature",
  "properties": {
    "iso:country":"CA",
    "sg:address":"1072 Doran Rd",
    "sg:city":"Pembroke",
    "sg:classifiers":[
        {
            "category":"Manufacturing",
            "subcategory":"Lumber",
            "type":"Manufacturing & Wholesale Goods"
        }
    ],
    "sg:phone":"+1 613 687 8107",
    "sg:postcode":"K8A 6W7",
    "sg:province":"ON",
    "wof:name":"Carson Lake Lumber Ltd",
    "wof:placetype":"venue"
},
  "geometry": {"coordinates":[-77.12036895750001,45.8183898926],"type":"Point"}
}