{
  "type": "Feature",
  "properties": {
    "iso:country":"CA",
    "sg:address":"3480 Ch Gascon",
    "sg:city":"Terrebonne",
    "sg:classifiers":[
        {
            "category":"Retail",
            "subcategory":"Animal Services",
            "type":"Services"
        }
    ],
    "sg:phone":"+1 450 477 9683",
    "sg:postcode":"J6X 4J1",
    "sg:province":"QC",
    "sg:tags":[
        "pet",
        "grooming",
        "washing"
    ],
    "wof:name":"Centre DE Tonte & Toilettage",
    "wof:placetype":"venue"
},
  "geometry": {"coordinates":[-73.6804428101,45.7340698242],"type":"Point"}
}