{
  "type": "Feature",
  "properties": {
    "addr:full":"2020 Av Jules-Verne Sainte-Foy QC G2G 2R2",
    "addr:housenumber":"2020",
    "addr:postcode":"g2g 2r2",
    "addr:street":"Av Jules-Verne",
    "iso:country":"CA",
    "sg:address":"2020 Av Jules-Verne",
    "sg:city":"Sainte-Foy",
    "sg:classifiers":[
        {
            "category":"Home & Garden",
            "subcategory":"Garden Supply",
            "type":"Retail Goods"
        }
    ],
    "sg:phone":"+1 418 872 0869",
    "sg:postcode":"G2G 2R2",
    "sg:province":"QC",
    "sg:tags":[
        "florist",
        "center"
    ],
    "wof:name":"Floralies Jouvence",
    "wof:placetype":"venue"
},
  "geometry": {"coordinates":[-71.37046051030001,46.7680435181],"type":"Point"}
}