{
  "type": "Feature",
  "properties": {
    "iso:country":"CA",
    "sg:city":"North York",
    "sg:classifiers":[
        {
            "category":"Manufacturing",
            "subcategory":"Jewelry",
            "type":"Manufacturing & Wholesale Goods"
        }
    ],
    "sg:phone":"+1 416 665 4456",
    "sg:postcode":"M3J 2X3",
    "sg:province":"ON",
    "wof:name":"Say Jewellery Inc",
    "wof:placetype":"venue"
},
  "geometry": {"coordinates":[-79.4751815796,43.7790184021],"type":"Point"}
}