{
  "type": "Feature",
  "properties": {
    "iso:country":"CA",
    "sg:address":"537 Main St W",
    "sg:city":"Winchester",
    "sg:classifiers":[
        {
            "category":"Organizations",
            "subcategory":"Religious Organization",
            "type":"Services"
        }
    ],
    "sg:phone":"+1 613 774 3137",
    "sg:postcode":"K0C 2K0",
    "sg:province":"ON",
    "sg:tags":[
        "church"
    ],
    "wof:name":"Wesleyan Church",
    "wof:placetype":"venue"
},
  "geometry": {"coordinates":[-75.35707855219999,45.0916976929],"type":"Point"}
}