{
  "type": "Feature",
  "properties": {
    "addr:full":"20 Gulfstream Rd North York ON M9M 1S3",
    "addr:housenumber":"20",
    "addr:postcode":"m9m 1s3",
    "addr:street":"Gulfstream Rd",
    "iso:country":"CA",
    "sg:address":"20 Gulfstream Rd",
    "sg:city":"North York",
    "sg:classifiers":[
        {
            "category":"Social Services",
            "type":"Services"
        }
    ],
    "sg:phone":"+1 416 746 0441",
    "sg:postcode":"M9M 1S3",
    "sg:province":"ON",
    "sg:tags":[
        "organization",
        "welfare"
    ],
    "wof:name":"Northwood Neighbourhood Svc",
    "wof:placetype":"venue"
},
  "geometry": {"coordinates":[-79.542191,43.73867],"type":"Point"}
}