{
  "type": "Feature",
  "properties": {
    "iso:country":"CA",
    "sg:city":"Moncton",
    "sg:classifiers":[
        {
            "category":"Health Services",
            "subcategory":"Podiatrist",
            "type":"Services"
        }
    ],
    "sg:phone":"+1 506 855 3668",
    "sg:postcode":"E1C 1W6",
    "sg:province":"NB",
    "wof:name":"Cormier, Monique DPM",
    "wof:placetype":"venue"
},
  "geometry": {"coordinates":[-64.784523,46.090668],"type":"Point"}
}