{
  "type": "Feature",
  "properties": {
    "addr:full":"Mississauga ON L4W 2M6",
    "addr:postcode":"l4w 2m6",
    "iso:country":"CA",
    "sg:city":"Mississauga",
    "sg:classifiers":[
        {
            "category":"Manufacturing",
            "subcategory":"Tools & Machinery",
            "type":"Manufacturing & Wholesale Goods"
        }
    ],
    "sg:phone":"+1 905 629 9951",
    "sg:postcode":"L4W 2M6",
    "sg:province":"ON",
    "sg:tags":[
        "die",
        "maker"
    ],
    "wof:name":"Tyrex Tool & Mfg",
    "wof:placetype":"venue"
},
  "geometry": {"coordinates":[-79.625557,43.631096],"type":"Point"}
}