{
  "type": "Feature",
  "properties": {
    "addr:full":"155 Tycos Dr North York ON M6B 1W6",
    "addr:housenumber":"155",
    "addr:postcode":"m6b 1w6",
    "addr:street":"Tycos Dr",
    "iso:country":"CA",
    "sg:address":"155 Tycos Dr",
    "sg:city":"North York",
    "sg:classifiers":[
        {
            "category":"Retail",
            "subcategory":"Auto Rental",
            "type":"Services"
        }
    ],
    "sg:phone":"+1 416 789 5934",
    "sg:postcode":"M6B 1W6",
    "sg:province":"ON",
    "sg:tags":[
        "renting",
        "truck",
        "leasing"
    ],
    "wof:name":"Ryder Truck Rental Inc",
    "wof:placetype":"venue"
},
  "geometry": {"coordinates":[-79.46199035639999,43.7036018372],"type":"Point"}
}