{
  "type": "Feature",
  "properties": {
    "addr:full":"99 Douglas Rd Richmond Hill ON L4E 3H1",
    "addr:housenumber":"99",
    "addr:postcode":"l4e 3h1",
    "addr:street":"Douglas Rd",
    "iso:country":"CA",
    "sg:address":"99 Douglas Rd",
    "sg:city":"Richmond Hill",
    "sg:classifiers":[
        {
            "category":"Real Estate",
            "subcategory":"Real Estate Agent",
            "type":"Services"
        }
    ],
    "sg:phone":"+1 905 773 5241",
    "sg:postcode":"L4E 3H1",
    "sg:province":"ON",
    "wof:name":"Blyth Realty Svc Ltd",
    "wof:placetype":"venue"
},
  "geometry": {"coordinates":[-79.44879899999999,43.943851],"type":"Point"}
}