{
  "type": "Feature",
  "properties": {
    "addr:full":"110 Industrial Ave Carleton Place ON K7C 3T2",
    "addr:housenumber":"110",
    "addr:postcode":"k7c 3t2",
    "addr:street":"Industrial Ave",
    "iso:country":"CA",
    "sg:address":"110 Industrial Ave",
    "sg:city":"Carleton Place",
    "sg:classifiers":[
        {
            "category":"Manufacturing",
            "subcategory":"Building Materials",
            "type":"Manufacturing & Wholesale Goods"
        }
    ],
    "sg:phone":"+1 613 257 8496",
    "sg:postcode":"K7C 3T2",
    "sg:province":"ON",
    "wof:name":"Bode's Custom Cabinets",
    "wof:placetype":"venue"
},
  "geometry": {"coordinates":[-76.14754499999999,45.149761],"type":"Point"}
}