{
  "type": "Feature",
  "properties": {
    "addr:full":"11 Charles St W #200 Toronto ON M4Y 1R4",
    "addr:housenumber":"11",
    "addr:postcode":"m4y 1r4",
    "addr:street":"Charles St W # 200",
    "iso:country":"CA",
    "sg:address":"11 Charles St W #200",
    "sg:city":"Toronto",
    "sg:classifiers":[
        {
            "category":"Shopping",
            "subcategory":"Computers & Home Electronics",
            "type":"Retail Goods"
        }
    ],
    "sg:phone":"+1 416 923 5319",
    "sg:postcode":"M4Y 1R4",
    "sg:province":"ON",
    "sg:tags":[
        "radio",
        "television",
        "video",
        "equipment"
    ],
    "wof:name":"Charles Street Electronics",
    "wof:placetype":"venue"
},
  "geometry": {"coordinates":[-79.386719,43.668465],"type":"Point"}
}