{
  "type": "Feature",
  "properties": {
    "addr:full":"2680 Skymark Ave # 120 Mississauga ON L4W 5L6",
    "addr:housenumber":"2680",
    "addr:postcode":"l4w 5l6",
    "addr:street":"Skymark Ave # 120",
    "iso:country":"CA",
    "sg:address":"2680 Skymark Ave # 120",
    "sg:city":"Mississauga",
    "sg:classifiers":[
        {
            "category":"Restaurant",
            "type":"Food & Drink"
        }
    ],
    "sg:phone":"+1 905 625 9896",
    "sg:postcode":"L4W 5L6",
    "sg:province":"ON",
    "wof:name":"Zogys Tap & Grill",
    "wof:placetype":"venue"
},
  "geometry": {"coordinates":[-79.59654999999999,43.66013],"type":"Point"}
}