{
  "type": "Feature",
  "properties": {
    "addr:full":"Outremont QC H2V 4S2",
    "addr:postcode":"h2v 4s2",
    "iso:country":"CA",
    "sg:city":"Outremont",
    "sg:classifiers":[
        {
            "category":"Health Services",
            "subcategory":"Medical Lab",
            "type":"Services"
        }
    ],
    "sg:phone":"+1 514 270 1922",
    "sg:postcode":"H2V 4S2",
    "sg:province":"QC",
    "sg:tags":[
        "laboratory"
    ],
    "wof:name":"Laboratoire Dentaire Roger",
    "wof:placetype":"venue"
},
  "geometry": {"coordinates":[-73.613838,45.52142],"type":"Point"}
}