{
  "type": "Feature",
  "properties": {
    "iso:country":"CA",
    "sg:address":"454 8th Ave NW",
    "sg:city":"Swift Current",
    "sg:classifiers":[
        {
            "category":"Education",
            "subcategory":"Special Training",
            "type":"Public Place"
        }
    ],
    "sg:phone":"+1 306 778 6732",
    "sg:postcode":"S9H 1A2",
    "sg:province":"SK",
    "sg:tags":[
        "instruction",
        "driving"
    ],
    "wof:name":"Al's Driving Svc",
    "wof:placetype":"venue"
},
  "geometry": {"coordinates":[-107.811264038,50.2889213562],"type":"Point"}
}