{
  "type": "Feature",
  "properties": {
    "iso:country":"CA",
    "sg:address":"30 Main St NW",
    "sg:city":"Erickson",
    "sg:classifiers":[
        {
            "category":"Travel",
            "subcategory":"Hotels & Motels",
            "type":"Entertainment"
        }
    ],
    "sg:phone":"+1 204 636 2601",
    "sg:postcode":"R0J 0P0",
    "sg:province":"MB",
    "wof:name":"Nordic Inn",
    "wof:placetype":"venue"
},
  "geometry": {"coordinates":[-99.91454315190001,50.4981880188],"type":"Point"}
}