{
  "type": "Feature",
  "properties": {
    "addr:full":"3953 Bostwick Rd London ON N6P 1G9",
    "addr:housenumber":"3953",
    "addr:postcode":"n6p 1g9",
    "addr:street":"Bostwick Rd",
    "iso:country":"CA",
    "sg:address":"3953 Bostwick Rd",
    "sg:city":"London",
    "sg:classifiers":[
        {
            "category":"Manufacturing",
            "subcategory":"Metals",
            "type":"Manufacturing & Wholesale Goods"
        }
    ],
    "sg:phone":"+1 519 649 4854",
    "sg:postcode":"N6P 1G9",
    "sg:province":"ON",
    "sg:tags":[
        "siding",
        "contractor"
    ],
    "wof:name":"Capor Windows & Doors",
    "wof:placetype":"venue"
},
  "geometry": {"coordinates":[-81.2846984863,42.9206161499],"type":"Point"}
}