{
  "type": "Feature",
  "properties": {
    "addr:full":"688 Rue Notre-Dame Joliette QC J6E 3J2",
    "addr:housenumber":"688",
    "addr:postcode":"j6e 3j2",
    "addr:street":"Rue Notre-Dame",
    "iso:country":"CA",
    "sg:address":"688 Rue Notre-Dame",
    "sg:city":"Joliette",
    "sg:classifiers":[
        {
            "category":"Manufacturing",
            "subcategory":"Electronics",
            "type":"Manufacturing & Wholesale Goods"
        }
    ],
    "sg:phone":"+1 450 759 4519",
    "sg:postcode":"J6E 3J2",
    "sg:province":"QC",
    "sg:tags":[
        "sound",
        "instrument",
        "musical",
        "system"
    ],
    "wof:name":"Centre Du Clavier Allard",
    "wof:placetype":"venue"
},
  "geometry": {"coordinates":[-73.442421,46.021896],"type":"Point"}
}