{
  "type": "Feature",
  "properties": {
    "addr:full":"Duncan BC V9L 4Y9",
    "addr:postcode":"v9l 4y9",
    "iso:country":"CA",
    "sg:city":"Duncan",
    "sg:classifiers":[
        {
            "category":"Organizations",
            "subcategory":"Non-profit Organization",
            "type":"Services"
        }
    ],
    "sg:phone":"+1 250 746 9778",
    "sg:postcode":"V9L 4Y9",
    "sg:province":"BC",
    "sg:tags":[
        "disability"
    ],
    "wof:name":"Thompson, Carolyn",
    "wof:placetype":"venue"
},
  "geometry": {"coordinates":[-123.707382,48.779095],"type":"Point"}
}