{
  "type": "Feature",
  "properties": {
    "iso:country":"CA",
    "sg:address":"PO Box 3043 STN Main",
    "sg:city":"Courtenay",
    "sg:classifiers":[
        {
            "category":"Professional",
            "subcategory":"Business Services",
            "type":"Services"
        }
    ],
    "sg:phone":"+1 250 337 5049",
    "sg:postcode":"V9N 5N3",
    "sg:province":"BC",
    "sg:tags":[
        "water",
        "hauling"
    ],
    "wof:name":"H2O-2Go Svc",
    "wof:placetype":"venue"
},
  "geometry": {"coordinates":[-124.993141174,49.6867218018],"type":"Point"}
}