{
  "type": "Feature",
  "properties": {
    "addr:full":"181 Main St E Milton ON L9T 1N7",
    "addr:housenumber":"181",
    "addr:postcode":"l9t 1n7",
    "addr:street":"Main St E",
    "iso:country":"CA",
    "sg:address":"181 Main St E",
    "sg:city":"Milton",
    "sg:classifiers":[
        {
            "category":"Restaurant",
            "type":"Food & Drink"
        }
    ],
    "sg:phone":"+1 905 878 9061",
    "sg:postcode":"L9T 1N7",
    "sg:province":"ON",
    "wof:name":"Lido Restaurant",
    "wof:placetype":"venue"
},
  "geometry": {"coordinates":[-79.8840789795,43.5125007629],"type":"Point"}
}