{
  "type": "Feature",
  "properties": {
    "addr:full":"1054 South Service Rd E Oakville ON L6J 2X7",
    "addr:housenumber":"1054",
    "addr:postcode":"l6j 2x7",
    "addr:street":"South Service Rd E",
    "iso:country":"CA",
    "sg:address":"1054 South Service Rd E",
    "sg:city":"Oakville",
    "sg:classifiers":[
        {
            "category":"Wholesale",
            "subcategory":"Machinery & Supplies",
            "type":"Manufacturing & Wholesale Goods"
        }
    ],
    "sg:phone":"+1 905 849 5855",
    "sg:postcode":"L6J 2X7",
    "sg:province":"ON",
    "sg:tags":[
        "truck"
    ],
    "wof:name":"Halton Lift Truck",
    "wof:placetype":"venue"
},
  "geometry": {"coordinates":[-79.674919,43.468773],"type":"Point"}
}