{
  "type": "Feature",
  "properties": {
    "addr:full":"8100 Av Blaise-Pascal Montreal QC H1E 2S7",
    "addr:housenumber":"8100",
    "addr:postcode":"h1e 2s7",
    "addr:street":"Av Blaise-Pascal",
    "iso:country":"CA",
    "sg:address":"8100 Av Blaise-Pascal",
    "sg:city":"Montreal",
    "sg:classifiers":[
        {
            "category":"Manufacturing",
            "subcategory":"Rubber & Plastics",
            "type":"Manufacturing & Wholesale Goods"
        }
    ],
    "sg:phone":"+1 514 648 8828",
    "sg:postcode":"H1E 2S7",
    "sg:province":"QC",
    "sg:tags":[
        "forming"
    ],
    "wof:name":"Casbo Plexiglass Inc",
    "wof:placetype":"venue"
},
  "geometry": {"coordinates":[-73.58433532710001,45.6307373047],"type":"Point"}
}