{
  "type": "Feature",
  "properties": {
    "addr:full":"Wyoming ON N0N 1T0",
    "addr:postcode":"n0n 1t0",
    "iso:country":"CA",
    "sg:city":"Wyoming",
    "sg:classifiers":[
        {
            "category":"Wholesale",
            "subcategory":"Meat",
            "type":"Manufacturing & Wholesale Goods"
        }
    ],
    "sg:phone":"+1 519 845 3358",
    "sg:postcode":"N0N 1T0",
    "sg:province":"ON",
    "sg:tags":[
        "packer",
        "butchering"
    ],
    "wof:name":"Lambton Meat Products",
    "wof:placetype":"venue"
},
  "geometry": {"coordinates":[-82.11869812010001,42.9502487183],"type":"Point"}
}