{
  "type": "Feature",
  "properties": {
    "addr:full":"Boucherville QC J4B 5K6",
    "addr:postcode":"j4b 5k6",
    "iso:country":"CA",
    "sg:city":"Boucherville",
    "sg:classifiers":[
        {
            "category":"Restaurant",
            "type":"Food & Drink"
        }
    ],
    "sg:phone":"+1 450 641 3011",
    "sg:postcode":"J4B 5K6",
    "sg:province":"QC",
    "wof:name":"Sportscene Restaurants Inc",
    "wof:placetype":"venue"
},
  "geometry": {"coordinates":[-73.452049,45.604111],"type":"Point"}
}