{
  "type": "Feature",
  "properties": {
    "addr:full":"800 Warden Ave Scarborough ON M1L 4T7",
    "addr:housenumber":"800",
    "addr:postcode":"m1l 4t7",
    "addr:street":"Warden Ave",
    "iso:country":"CA",
    "sg:address":"800 Warden Ave",
    "sg:city":"Scarborough",
    "sg:classifiers":[
        {
            "category":"Restaurant",
            "type":"Food & Drink"
        }
    ],
    "sg:phone":"+1 416 285 4192",
    "sg:postcode":"M1L 4T7",
    "sg:province":"ON",
    "wof:name":"Mc Donald's",
    "wof:placetype":"venue"
},
  "geometry": {"coordinates":[-79.2872390747,43.7264213562],"type":"Point"}
}