{
  "type": "Feature",
  "properties": {
    "addr:full":"Saint-Elzear QC G0S 2J0",
    "addr:postcode":"g0s 2j0",
    "iso:country":"CA",
    "sg:city":"Saint-Elzear",
    "sg:classifiers":[
        {
            "category":"Personal",
            "subcategory":"Beauty Salon",
            "type":"Services"
        }
    ],
    "sg:phone":"+1 418 389 2636",
    "sg:postcode":"G0S 2J0",
    "sg:province":"QC",
    "wof:name":"Esthetique L'Essentiel",
    "wof:placetype":"venue"
},
  "geometry": {"coordinates":[-65.393776,48.149818],"type":"Point"}
}