{
  "type": "Feature",
  "properties": {
    "addr:full":"1819 Saskatchewan Ave W Portage LA Prairie MB R1N 0R6",
    "addr:housenumber":"1819",
    "addr:postcode":"r1n 0r6",
    "addr:street":"Saskatchewan Ave W",
    "iso:country":"CA",
    "sg:address":"1819 Saskatchewan Ave W",
    "sg:city":"Portage LA Prairie",
    "sg:classifiers":[
        {
            "category":"Autos & Motor Vehicles",
            "subcategory":"Fuel & Gas Station",
            "type":"Retail Goods"
        }
    ],
    "sg:phone":"+1 204 239 4960",
    "sg:postcode":"R1N 0R6",
    "sg:province":"MB",
    "sg:tags":[
        "oil"
    ],
    "wof:name":"Fas Gas",
    "wof:placetype":"venue"
},
  "geometry": {"coordinates":[-98.31356,49.971634],"type":"Point"}
}