{
  "type": "Feature",
  "properties": {
    "addr:full":"52 Brentwood Blvd # 52 Sherwood Park AB T8A 2H6",
    "addr:housenumber":"52;52",
    "addr:postcode":"t8a 2h6",
    "addr:street":"Brentwood Blvd #;Park",
    "iso:country":"CA",
    "sg:address":"52 Brentwood Blvd # 52",
    "sg:city":"Sherwood Park",
    "sg:classifiers":[
        {
            "category":"Shopping",
            "subcategory":"Bicycles & Sporting Goods",
            "type":"Retail Goods"
        }
    ],
    "sg:phone":"+1 780 464 3100",
    "sg:postcode":"T8A 2H6",
    "sg:province":"AB",
    "wof:name":"Sabre Sports & Cycle",
    "wof:placetype":"venue"
},
  "geometry": {"coordinates":[-113.295249939,53.5148963928],"type":"Point"}
}