{
  "type": "Feature",
  "properties": {
    "addr:full":"135 Wellington St St Thomas ON N5R 2R7",
    "addr:housenumber":"135",
    "addr:postcode":"n5r 2r7",
    "addr:street":"Wellington St",
    "iso:country":"CA",
    "sg:address":"135 Wellington St",
    "sg:city":"St Thomas",
    "sg:classifiers":[
        {
            "category":"Education",
            "subcategory":"Special Training",
            "type":"Public Place"
        }
    ],
    "sg:phone":"+1 519 631 1562",
    "sg:postcode":"N5R 2R7",
    "sg:province":"ON",
    "sg:tags":[
        "instruction",
        "music"
    ],
    "wof:name":"St Thomas Central Academy",
    "wof:placetype":"venue"
},
  "geometry": {"coordinates":[-81.1910018921,42.7753372192],"type":"Point"}
}