{
  "type": "Feature",
  "properties": {
    "addr:full":"Tomslake BC V0C 2L0",
    "addr:postcode":"bc v0c 2l0",
    "iso:country":"CA",
    "sg:city":"Tomslake",
    "sg:classifiers":[
        {
            "category":"Shopping",
            "subcategory":"Gifts & Souvenirs",
            "type":"Retail Goods"
        }
    ],
    "sg:phone":"+1 250 786 5135",
    "sg:postcode":"V0C 2L0",
    "sg:province":"BC",
    "sg:tags":[
        "shop"
    ],
    "wof:name":"Cupful of Joy",
    "wof:placetype":"venue"
},
  "geometry": {"coordinates":[-120.078948975,55.5601196289],"type":"Point"}
}