{
  "type": "Feature",
  "properties": {
    "addr:full":"175 116 Rte O Plessisville QC G6L 2Y2",
    "addr:housenumber":"116",
    "addr:postcode":"g6l 2y2",
    "addr:street":"Rte O",
    "iso:country":"CA",
    "sg:address":"175 116 Rte O",
    "sg:city":"Plessisville",
    "sg:classifiers":[
        {
            "category":"Retail",
            "subcategory":"Auto Repair",
            "type":"Services"
        }
    ],
    "sg:phone":"+1 819 362 2325",
    "sg:postcode":"G6L 2Y2",
    "sg:province":"QC",
    "sg:tags":[
        "wrecker"
    ],
    "wof:name":"Remorquage Pneus Desjardins",
    "wof:placetype":"venue"
},
  "geometry": {"coordinates":[-71.76544199999999,46.214893],"type":"Point"}
}