{
  "type": "Feature",
  "properties": {
    "iso:country":"CA",
    "sg:address":"5505 Broadway Ave",
    "sg:city":"Blackfalds",
    "sg:classifiers":[
        {
            "category":"Freight",
            "type":"Transportation"
        }
    ],
    "sg:phone":"+1 403 885 4663",
    "sg:postcode":"T0M 0J0",
    "sg:province":"AB",
    "sg:tags":[
        "mobile",
        "home"
    ],
    "wof:name":"Millennium Manufactured Home",
    "wof:placetype":"venue"
},
  "geometry": {"coordinates":[-113.795425415,52.3833312988],"type":"Point"}
}