{
  "type": "Feature",
  "properties": {
    "iso:country":"CA",
    "sg:address":"39 Progress Crt",
    "sg:city":"Brampton",
    "sg:classifiers":[
        {
            "category":"Manufacturing",
            "subcategory":"Metals",
            "type":"Manufacturing & Wholesale Goods"
        }
    ],
    "sg:phone":"+1 905 799 3324",
    "sg:postcode":"L6S 5X2",
    "sg:province":"ON",
    "sg:tags":[
        "steel"
    ],
    "wof:name":"Austin Steel Group Inc",
    "wof:placetype":"venue"
},
  "geometry": {"coordinates":[-79.6943664551,43.7553749084],"type":"Point"}
}