{
  "type": "Feature",
  "properties": {
    "iso:country":"CA",
    "sg:address":"500 Av Broadway",
    "sg:city":"Shawinigan",
    "sg:classifiers":[
        {
            "category":"Manufacturing",
            "subcategory":"Lumber",
            "type":"Manufacturing & Wholesale Goods"
        }
    ],
    "sg:phone":"+1 819 536 1001",
    "sg:postcode":"G9N 1M3",
    "sg:province":"QC",
    "sg:tags":[
        "forester"
    ],
    "wof:name":"Association Forestiere-Vallee",
    "wof:placetype":"venue"
},
  "geometry": {"coordinates":[-72.7437210083,46.5411148071],"type":"Point"}
}