{
  "type": "Feature",
  "properties": {
    "addr:full":"9673 Rue Clement Lasalle QC H8R 4B4",
    "addr:housenumber":"9673",
    "addr:postcode":"h8r 4b4",
    "addr:street":"Rue Clement",
    "iso:country":"CA",
    "sg:address":"9673 Rue Clement",
    "sg:city":"Lasalle",
    "sg:classifiers":[
        {
            "category":"Professional",
            "subcategory":"Testing Lab",
            "type":"Services"
        }
    ],
    "sg:phone":"+1 514 365 8386",
    "sg:postcode":"H8R 4B4",
    "sg:province":"QC",
    "sg:tags":[
        "laboratory"
    ],
    "wof:name":"Pharmatest",
    "wof:placetype":"venue"
},
  "geometry": {"coordinates":[-73.653206,45.434856],"type":"Point"}
}