{
  "type": "Feature",
  "properties": {
    "addr:full":"Dartmouth NS B2W 6C4",
    "addr:postcode":"b2w 6c4",
    "iso:country":"CA",
    "sg:city":"Dartmouth",
    "sg:classifiers":[
        {
            "category":"Shopping",
            "subcategory":"Books",
            "type":"Retail Goods"
        }
    ],
    "sg:phone":"+1 902 434 7333",
    "sg:postcode":"B2W 6C4",
    "sg:province":"NS",
    "sg:tags":[
        "dealer"
    ],
    "wof:name":"Book Rack",
    "wof:placetype":"venue"
},
  "geometry": {"coordinates":[-63.5272598267,44.671245575],"type":"Point"}
}