{
  "type": "Feature",
  "properties": {
    "addr:full":"6692 Rue Saint-Denis Montreal QC H2S 2R9",
    "addr:housenumber":"6692",
    "addr:postcode":"h2s 2r9",
    "addr:street":"Rue Saint-Denis",
    "iso:country":"CA",
    "sg:address":"6692 Rue Saint-Denis",
    "sg:city":"Montreal",
    "sg:classifiers":[
        {
            "category":"Retail",
            "subcategory":"Laundry & Dry Cleaning",
            "type":"Services"
        }
    ],
    "sg:phone":"+1 514 272 5945",
    "sg:postcode":"H2S 2R9",
    "sg:province":"QC",
    "sg:tags":[
        "cleaners"
    ],
    "wof:name":"B L Nettoyeur Enr",
    "wof:placetype":"venue"
},
  "geometry": {"coordinates":[-73.6081161499,45.5352478027],"type":"Point"}
}