{
  "type": "Feature",
  "properties": {
    "addr:full":"179 3E Ave L'Isletville QC G0R 2C0",
    "addr:housenumber":"179",
    "addr:postcode":"g0r 2c0",
    "addr:street":"3E Ave",
    "iso:country":"CA",
    "sg:address":"179 3E Ave",
    "sg:city":"L'Isletville",
    "sg:classifiers":[
        {
            "category":"Manufacturing",
            "subcategory":"Furniture",
            "type":"Manufacturing & Wholesale Goods"
        }
    ],
    "sg:phone":"+1 418 247 5113",
    "sg:postcode":"G0R 2C0",
    "sg:province":"QC",
    "wof:name":"Mobilier Poitras",
    "wof:placetype":"venue"
},
  "geometry": {"coordinates":[-70.33502960209999,47.1145896912],"type":"Point"}
}