{
  "type": "Feature",
  "properties": {
    "addr:full":"150 West St Kingston ON K7L 5E7",
    "addr:housenumber":"150",
    "addr:postcode":"k7l 5e7",
    "addr:street":"West St",
    "iso:country":"CA",
    "sg:address":"150 West St",
    "sg:city":"Kingston",
    "sg:classifiers":[
        {
            "category":"Health Services",
            "subcategory":"Clinic",
            "type":"Services"
        }
    ],
    "sg:phone":"+1 613 548 4929",
    "sg:postcode":"K7L 5E7",
    "sg:province":"ON",
    "sg:tags":[
        "social",
        "organization",
        "first",
        "aid",
        "welfare"
    ],
    "wof:name":"Canadian Red Cross Society",
    "wof:placetype":"venue"
},
  "geometry": {"coordinates":[-76.489227,44.228439],"type":"Point"}
}