{
  "type": "Feature",
  "properties": {
    "addr:full":"1727 Carrick St Victoria BC V8R 2M1",
    "addr:housenumber":"1727",
    "addr:postcode":"v8r 2m1",
    "addr:street":"Carrick St",
    "iso:country":"CA",
    "sg:address":"1727 Carrick St",
    "sg:city":"Victoria",
    "sg:classifiers":[
        {
            "category":"Professional",
            "type":"Services"
        }
    ],
    "sg:phone":"+1 250 592 8480",
    "sg:postcode":"V8R 2M1",
    "sg:province":"BC",
    "sg:tags":[
        "scientist"
    ],
    "wof:name":"Fultech Services Inc",
    "wof:placetype":"venue"
},
  "geometry": {"coordinates":[-123.33123000000001,48.436699],"type":"Point"}
}