{
  "type": "Feature",
  "properties": {
    "addr:full":"183 Hughson St S Hamilton ON L8N 2B6",
    "addr:housenumber":"183",
    "addr:postcode":"l8n 2b6",
    "addr:street":"Hughson St S",
    "iso:country":"CA",
    "sg:address":"183 Hughson St S",
    "sg:city":"Hamilton",
    "sg:classifiers":[
        {
            "category":"Health Services",
            "subcategory":"Doctor",
            "type":"Services"
        }
    ],
    "sg:phone":"+1 905 528 0303",
    "sg:postcode":"L8N 2B6",
    "sg:province":"ON",
    "sg:tags":[
        "dentist"
    ],
    "wof:name":"Hughson South Dental",
    "wof:placetype":"venue"
},
  "geometry": {"coordinates":[-79.870499,43.249973],"type":"Point"}
}