{
  "type": "Feature",
  "properties": {
    "addr:full":"1088 Rue Saint-Andre Acton Vale QC J0H 1A0",
    "addr:housenumber":"1088",
    "addr:postcode":"j0h 1a0",
    "addr:street":"Rue Saint-Andre",
    "iso:country":"CA",
    "sg:address":"1088 Rue Saint-Andre",
    "sg:city":"Acton Vale",
    "sg:classifiers":[
        {
            "category":"Shopping",
            "subcategory":"Stationery & Office Supplies",
            "type":"Retail Goods"
        }
    ],
    "sg:phone":"+1 450 546 0555",
    "sg:postcode":"J0H 1A0",
    "sg:province":"QC",
    "sg:tags":[
        "stationer"
    ],
    "wof:name":"Papeterie Valoise",
    "wof:placetype":"venue"
},
  "geometry": {"coordinates":[-72.564629,45.649643],"type":"Point"}
}