{
  "type": "Feature",
  "properties": {
    "addr:full":"Winnipeg MB R3C 0B9",
    "addr:postcode":"r3c 0b9",
    "iso:country":"CA",
    "sg:city":"Winnipeg",
    "sg:classifiers":[
        {
            "category":"Banks & Credit Unions",
            "subcategory":"Bank",
            "type":"Services"
        }
    ],
    "sg:phone":"+1 204 943 6001",
    "sg:postcode":"R3C 0B9",
    "sg:province":"MB",
    "sg:tags":[
        "cashing",
        "check"
    ],
    "wof:name":"Money Mart",
    "wof:placetype":"venue"
},
  "geometry": {"coordinates":[-97.142746,49.893661],"type":"Point"}
}