{
  "type": "Feature",
  "properties": {
    "addr:full":"6114 Yonge St North York ON M2M 3W7",
    "addr:housenumber":"6114",
    "addr:postcode":"m2m 3w7",
    "addr:street":"Yonge St",
    "iso:country":"CA",
    "sg:address":"6114 Yonge St",
    "sg:city":"North York",
    "sg:classifiers":[
        {
            "category":"Restaurant",
            "type":"Food & Drink"
        }
    ],
    "sg:phone":"+1 416 223 4320",
    "sg:postcode":"M2M 3W7",
    "sg:province":"ON",
    "wof:name":"Kfc",
    "wof:placetype":"venue"
},
  "geometry": {"coordinates":[-79.41854858400001,43.7915153503],"type":"Point"}
}