{
  "type": "Feature",
  "properties": {
    "addr:full":"4540 Bolduc Rd Vernon BC V1B 3J1",
    "addr:postcode":"4540;bc v1b 3j1",
    "addr:street":"Bolduc Rd",
    "iso:country":"CA",
    "sg:address":"4540 Bolduc Rd",
    "sg:city":"Vernon",
    "sg:classifiers":[
        {
            "category":"Building & Trades",
            "subcategory":"Construction",
            "type":"Services"
        }
    ],
    "sg:phone":"+1 250 542 6392",
    "sg:postcode":"V1B 3J1",
    "sg:province":"BC",
    "sg:tags":[
        "general",
        "contractor"
    ],
    "wof:name":"Kal Construction Ltd",
    "wof:placetype":"venue"
},
  "geometry": {"coordinates":[-119.273804,50.265686],"type":"Point"}
}