{
  "type": "Feature",
  "properties": {
    "iso:country":"CA",
    "sg:city":"Ottawa",
    "sg:classifiers":[
        {
            "category":"Professional",
            "subcategory":"Lawyer & Legal Services",
            "type":"Services"
        }
    ],
    "sg:phone":"+1 613 563 1270",
    "sg:postcode":"K1P 5V9",
    "sg:province":"ON",
    "sg:tags":[
        "attorney"
    ],
    "wof:name":"Martin, Shannon H",
    "wof:placetype":"venue"
},
  "geometry": {"coordinates":[-75.701302,45.420193],"type":"Point"}
}