{
  "type": "Feature",
  "properties": {
    "addr:full":"Clinton BC V0K 1K0",
    "addr:postcode":"v0k 1k0",
    "iso:country":"CA",
    "sg:city":"Clinton",
    "sg:classifiers":[
        {
            "category":"Real Estate",
            "subcategory":"Real Estate Operator",
            "type":"Services"
        }
    ],
    "sg:phone":"+1 250 459 2550",
    "sg:postcode":"V0K 1K0",
    "sg:province":"BC",
    "sg:tags":[
        "mobile",
        "home",
        "community"
    ],
    "wof:name":"Cut Off Valley Trailer Court",
    "wof:placetype":"venue"
},
  "geometry": {"coordinates":[-121.59232299999999,51.09053],"type":"Point"}
}