{
  "type": "Feature",
  "properties": {
    "addr:full":"Guelph ON N1G 4T7",
    "addr:postcode":"n1g 4t7",
    "iso:country":"CA",
    "sg:city":"Guelph",
    "sg:classifiers":[
        {
            "category":"Health Services",
            "subcategory":"Doctor",
            "type":"Services"
        }
    ],
    "sg:phone":"+1 519 763 7378",
    "sg:postcode":"N1G 4T7",
    "sg:province":"ON",
    "sg:tags":[
        "dentist"
    ],
    "wof:name":"Clark, Gary DDS",
    "wof:placetype":"venue"
},
  "geometry": {"coordinates":[-80.237785,43.514095],"type":"Point"}
}