{
  "type": "Feature",
  "properties": {
    "iso:country":"CA",
    "sg:address":"12660 Boul Becancour",
    "sg:city":"Becancour",
    "sg:classifiers":[
        {
            "category":"Retail",
            "subcategory":"Auto Repair",
            "type":"Services"
        }
    ],
    "sg:phone":"+1 819 222 5444",
    "sg:postcode":"G9H 2J4",
    "sg:province":"QC",
    "sg:tags":[
        "repairing",
        "automobile"
    ],
    "wof:name":"Garage Gerard Bellefeuille",
    "wof:placetype":"venue"
},
  "geometry": {"coordinates":[-72.5056762695,46.3366241455],"type":"Point"}
}