{
  "type": "Feature",
  "properties": {
    "addr:full":"907 Front St # 3 Hearst ON P0L 1N0",
    "addr:housenumber":"907",
    "addr:postcode":"p0l 1n0",
    "addr:street":"Front St # 3",
    "iso:country":"CA",
    "sg:address":"907 Front St # 3",
    "sg:city":"Hearst",
    "sg:classifiers":[
        {
            "category":"Food & Beverages",
            "subcategory":"Specialty",
            "type":"Retail Goods"
        }
    ],
    "sg:phone":"+1 705 362 5886",
    "sg:postcode":"P0L 1N0",
    "sg:province":"ON",
    "wof:name":"Pole",
    "wof:placetype":"venue"
},
  "geometry": {"coordinates":[-83.6652755737,49.6895675659],"type":"Point"}
}