{
  "type": "Feature",
  "properties": {
    "addr:full":"8130 Rue Champ D'Eau Saint-Leonard QC H1P 1Y3",
    "addr:housenumber":"8130",
    "addr:postcode":"h1p 1y3",
    "addr:street":"Rue Champ D'Eau",
    "iso:country":"CA",
    "sg:address":"8130 Rue Champ D'Eau",
    "sg:city":"Saint-Leonard",
    "sg:classifiers":[
        {
            "category":"Building & Trades",
            "subcategory":"Construction",
            "type":"Services"
        }
    ],
    "sg:phone":"+1 514 582 5983",
    "sg:postcode":"H1P 1Y3",
    "sg:province":"QC",
    "sg:tags":[
        "paving",
        "contractor"
    ],
    "wof:name":"Pavages & Beton Du Quebec",
    "wof:placetype":"venue"
},
  "geometry": {"coordinates":[-73.595337,45.58939],"type":"Point"}
}