{
  "type": "Feature",
  "properties": {
    "addr:full":"9 Rue Du Couvent Petite-Riviere-Saint-Francois QC G0A 2L0",
    "addr:housenumber":"9",
    "addr:postcode":"g0a 2l0",
    "addr:street":"Rue Du Couvent",
    "iso:country":"CA",
    "sg:address":"9 Rue Du Couvent",
    "sg:city":"Petite-Riviere-Saint-Francois",
    "sg:classifiers":[
        {
            "category":"Education",
            "subcategory":"School",
            "type":"Public Place"
        }
    ],
    "sg:phone":"+1 418 632 5817",
    "sg:postcode":"G0A 2L0",
    "sg:province":"QC",
    "wof:name":"Ecole St Francois",
    "wof:placetype":"venue"
},
  "geometry": {"coordinates":[-70.565147,47.311382],"type":"Point"}
}