{
  "type": "Feature",
  "properties": {
    "iso:country":"CA",
    "sg:address":"PO Box 633 STN Main",
    "sg:city":"Athabasca",
    "sg:classifiers":[
        {
            "category":"Professional",
            "subcategory":"Business Services",
            "type":"Services"
        }
    ],
    "sg:phone":"+1 780 675 4885",
    "sg:postcode":"T9S 2A5",
    "sg:province":"AB",
    "wof:name":"South Bend Vacuum Truck Svc",
    "wof:placetype":"venue"
},
  "geometry": {"coordinates":[-113.28351592999999,54.7212333679],"type":"Point"}
}