{
  "type": "Feature",
  "properties": {
    "addr:full":"3380 Parkwood Ave Windsor ON N8W 2L1",
    "addr:housenumber":"3380",
    "addr:postcode":"n8w 2l1",
    "addr:street":"Parkwood Ave",
    "iso:country":"CA",
    "sg:address":"3380 Parkwood Ave",
    "sg:city":"Windsor",
    "sg:classifiers":[
        {
            "category":"Building & Trades",
            "subcategory":"Construction",
            "type":"Services"
        }
    ],
    "sg:phone":"+1 519 969 9777",
    "sg:postcode":"N8W 2L1",
    "sg:province":"ON",
    "sg:tags":[
        "concrete",
        "contractor",
        "general"
    ],
    "wof:name":"Filippo Liburdi Constr Ltd",
    "wof:placetype":"venue"
},
  "geometry": {"coordinates":[-82.9896469116,42.2729110718],"type":"Point"}
}