{
  "type": "Feature",
  "properties": {
    "addr:full":"110 Longworth St Maryfield SK S0G 3K0",
    "addr:housenumber":"110",
    "addr:postcode":"s0g 3k0",
    "addr:street":"Longworth St",
    "iso:country":"CA",
    "sg:address":"110 Longworth St",
    "sg:city":"Maryfield",
    "sg:classifiers":[
        {
            "category":"Health Services",
            "subcategory":"Nursing And Care Facility",
            "type":"Services"
        }
    ],
    "sg:phone":"+1 306 646 4988",
    "sg:postcode":"S0G 3K0",
    "sg:province":"SK",
    "sg:tags":[
        "home",
        "rest"
    ],
    "wof:name":"Sunrise Villa Inc",
    "wof:placetype":"venue"
},
  "geometry": {"coordinates":[-101.53153228799999,49.8375396729],"type":"Point"}
}