{
  "type": "Feature",
  "properties": {
    "addr:full":"831 Rue DE Saint-Hubert Canton-DE-Granby QC J2H 2K7",
    "addr:housenumber":"831",
    "addr:postcode":"j2h 2k7",
    "addr:street":"Rue De Saint-Hubert Canton-De-Granby",
    "iso:country":"CA",
    "sg:address":"831 Rue DE Saint-Hubert",
    "sg:city":"Canton-DE-Granby",
    "sg:classifiers":[
        {
            "category":"Education",
            "subcategory":"School",
            "type":"Public Place"
        }
    ],
    "sg:phone":"+1 450 777 3804",
    "sg:postcode":"J2H 2K7",
    "sg:province":"QC",
    "wof:name":"Ecole Joseph-Poitevin",
    "wof:placetype":"venue"
},
  "geometry": {"coordinates":[-72.721771,45.397995],"type":"Point"}
}