{
  "type": "Feature",
  "properties": {
    "addr:full":"Ottawa ON K1V 8B9",
    "addr:postcode":"k1v 8b9",
    "iso:country":"CA",
    "sg:city":"Ottawa",
    "sg:classifiers":[
        {
            "category":"Manufacturing",
            "subcategory":"Signs",
            "type":"Manufacturing & Wholesale Goods"
        }
    ],
    "sg:phone":"+1 613 733 6683",
    "sg:postcode":"K1V 8B9",
    "sg:province":"ON",
    "wof:name":"Compu Sign Xpress",
    "wof:placetype":"venue"
},
  "geometry": {"coordinates":[-75.670952,45.375244],"type":"Point"}
}