{
  "type": "Feature",
  "properties": {
    "addr:full":"3 Government Rd W Kirkland Lake ON P2N 2C9",
    "addr:housenumber":"3",
    "addr:postcode":"p2n 2c9",
    "addr:street":"Rd W",
    "iso:country":"CA",
    "sg:address":"3 Government Rd W",
    "sg:city":"Kirkland Lake",
    "sg:classifiers":[
        {
            "category":"Utilities",
            "subcategory":"Mobile Phone",
            "type":"Services"
        }
    ],
    "sg:phone":"+1 705 567 7212",
    "sg:postcode":"P2N 2C9",
    "sg:province":"ON",
    "sg:tags":[
        "stationer",
        "telephone",
        "cellular"
    ],
    "wof:name":"Carl's Office Supply Ltd",
    "wof:placetype":"venue"
},
  "geometry": {"coordinates":[-80.033164978,48.1507873535],"type":"Point"}
}