{
  "type": "Feature",
  "properties": {
    "addr:full":"4812 61 St Stettler AB T0C 2L1",
    "addr:housenumber":"4812",
    "addr:postcode":"t0c 2l1",
    "addr:street":"61 St",
    "iso:country":"CA",
    "sg:address":"4812 61 St",
    "sg:city":"Stettler",
    "sg:classifiers":[
        {
            "category":"Travel",
            "subcategory":"Hotels & Motels",
            "type":"Entertainment"
        }
    ],
    "sg:phone":"+1 403 742 3491",
    "sg:postcode":"T0C 2L1",
    "sg:province":"AB",
    "wof:name":"Plains Motor Inn",
    "wof:placetype":"venue"
},
  "geometry": {"coordinates":[-112.727714539,52.3246192932],"type":"Point"}
}