{
  "type": "Feature",
  "properties": {
    "addr:full":"2351 Boul Rosemont Montreal QC H2G 1T9",
    "addr:housenumber":"2351",
    "addr:postcode":"h2g 1t9",
    "addr:street":"Boul Rosemont",
    "iso:country":"CA",
    "sg:address":"2351 Boul Rosemont",
    "sg:city":"Montreal",
    "sg:classifiers":[
        {
            "category":"Health Services",
            "subcategory":"Nursing And Care Facility",
            "type":"Services"
        }
    ],
    "sg:phone":"+1 514 728 7907",
    "sg:postcode":"H2G 1T9",
    "sg:province":"QC",
    "sg:tags":[
        "home",
        "retirement",
        "community"
    ],
    "wof:name":"Maison Des Orchidees Enr",
    "wof:placetype":"venue"
},
  "geometry": {"coordinates":[-73.5874328613,45.5452728271],"type":"Point"}
}