{
  "type": "Feature",
  "properties": {
    "addr:full":"Surrey BC V3W 4G3",
    "addr:postcode":"v3w 4g3",
    "iso:country":"CA",
    "sg:city":"Surrey",
    "sg:classifiers":[
        {
            "category":"Shopping",
            "subcategory":"Clothing, Apparel, & Fashions",
            "type":"Retail Goods"
        }
    ],
    "sg:phone":"+1 604 572 5113",
    "sg:postcode":"V3W 4G3",
    "sg:province":"BC",
    "wof:name":"Lakhan Cloth House",
    "wof:placetype":"venue"
},
  "geometry": {"coordinates":[-122.867897,49.156181],"type":"Point"}
}