{
  "type": "Feature",
  "properties": {
    "addr:full":"659 Lake Shore Blvd W Toronto ON M5V 1A7",
    "addr:housenumber":"659",
    "addr:postcode":"m5v 1a7",
    "addr:street":"Lake Shore Blvd W",
    "iso:country":"CA",
    "sg:address":"659 Lake Shore Blvd W",
    "sg:city":"Toronto",
    "sg:classifiers":[
        {
            "category":"Government",
            "subcategory":"Office",
            "type":"Public Place"
        }
    ],
    "sg:phone":"+1 416 635 4400",
    "sg:postcode":"M5V 1A7",
    "sg:province":"ON",
    "wof:name":"Canada National Reserve Force",
    "wof:placetype":"venue"
},
  "geometry": {"coordinates":[-79.402916,43.635689],"type":"Point"}
}