{
  "type": "Feature",
  "properties": {
    "addr:full":"134 1st Ave NE Dauphin MB R7N 1A5",
    "addr:housenumber":"134",
    "addr:postcode":"r7n 1a5",
    "addr:street":"1St Ave Ne",
    "iso:country":"CA",
    "sg:address":"134 1st Ave NE",
    "sg:city":"Dauphin",
    "sg:classifiers":[
        {
            "category":"Retail",
            "subcategory":"Repair Shop",
            "type":"Services"
        }
    ],
    "sg:phone":"+1 204 638 4155",
    "sg:postcode":"R7N 1A5",
    "sg:province":"MB",
    "sg:tags":[
        "upholsterer"
    ],
    "wof:name":"Westmore Upholstering Svc",
    "wof:placetype":"venue"
},
  "geometry": {"coordinates":[-100.04705,51.148506],"type":"Point"}
}