{
  "type": "Feature",
  "properties": {
    "addr:full":"41 Clarinda Dr North York ON M2K 2W4",
    "addr:housenumber":"41",
    "addr:postcode":"m2k 2w4",
    "addr:street":"Clarinda Dr",
    "iso:country":"CA",
    "sg:address":"41 Clarinda Dr",
    "sg:city":"North York",
    "sg:classifiers":[
        {
            "category":"Real Estate",
            "subcategory":"Real Estate Agent",
            "type":"Services"
        }
    ],
    "sg:phone":"+1 416 733 8155",
    "sg:postcode":"M2K 2W4",
    "sg:province":"ON",
    "wof:name":"Gta Realty Ltd",
    "wof:placetype":"venue"
},
  "geometry": {"coordinates":[-79.370453,43.774754],"type":"Point"}
}