{
  "type": "Feature",
  "properties": {
    "iso:country":"CA",
    "sg:city":"Mississauga",
    "sg:classifiers":[
        {
            "category":"Restaurant",
            "type":"Food & Drink"
        }
    ],
    "sg:phone":"+1 905 238 5222",
    "sg:postcode":"L4W 4Y1",
    "sg:province":"ON",
    "wof:name":"Druxy's Famous Deli Sandwiches",
    "wof:placetype":"venue"
},
  "geometry": {"coordinates":[-79.6100311279,43.6601676941],"type":"Point"}
}