{
  "type": "Feature",
  "properties": {
    "addr:full":"Deep River ON K0J 1P0",
    "addr:postcode":"k0j 1p0",
    "iso:country":"CA",
    "sg:city":"Deep River",
    "sg:classifiers":[
        {
            "category":"Autos & Motor Vehicles",
            "subcategory":"Auto Supplies",
            "type":"Retail Goods"
        }
    ],
    "sg:phone":"+1 613 584 3337",
    "sg:postcode":"K0J 1P0",
    "sg:province":"ON",
    "sg:tags":[
        "repairing",
        "automobile",
        "parts"
    ],
    "wof:name":"Canadian Tire",
    "wof:placetype":"venue"
},
  "geometry": {"coordinates":[-77.477013,46.076801],"type":"Point"}
}