{
  "type": "Feature",
  "properties": {
    "addr:full":"142 Main St Winnipeg MB R3C 1A4",
    "addr:housenumber":"142",
    "addr:postcode":"r3c 1a4",
    "addr:street":"Main St",
    "iso:country":"CA",
    "sg:address":"142 Main St",
    "sg:city":"Winnipeg",
    "sg:classifiers":[
        {
            "category":"Autos & Motor Vehicles",
            "subcategory":"Fuel & Gas Station",
            "type":"Retail Goods"
        }
    ],
    "sg:phone":"+1 204 956 0516",
    "sg:postcode":"R3C 1A4",
    "sg:province":"MB",
    "sg:tags":[
        "oil"
    ],
    "wof:name":"Petro-Canada",
    "wof:placetype":"venue"
},
  "geometry": {"coordinates":[-97.1348648071,49.8881645203],"type":"Point"}
}