{
  "type": "Feature",
  "properties": {
    "iso:country":"CA",
    "sg:address":"4841 Yonge St",
    "sg:city":"North York",
    "sg:classifiers":[
        {
            "category":"Banks & Credit Unions",
            "subcategory":"Bank",
            "type":"Services"
        }
    ],
    "sg:phone":"+1 416 590 7757",
    "sg:postcode":"M2N 5X2",
    "sg:province":"ON",
    "wof:name":"Bank of Montreal",
    "wof:placetype":"venue"
},
  "geometry": {"coordinates":[-79.4108428955,43.7619781494],"type":"Point"}
}