{
  "type": "Feature",
  "properties": {
    "addr:full":"55 Grenfell Cres Nepean ON K2G 0G3",
    "addr:housenumber":"55",
    "addr:postcode":"k2g 0g3",
    "addr:street":"Grenfell Cres",
    "iso:country":"CA",
    "sg:address":"55 Grenfell Cres",
    "sg:city":"Nepean",
    "sg:classifiers":[
        {
            "category":"Manufacturing",
            "subcategory":"Electronics",
            "type":"Manufacturing & Wholesale Goods"
        }
    ],
    "sg:phone":"+1 613 226 5772",
    "sg:postcode":"K2G 0G3",
    "sg:province":"ON",
    "sg:tags":[
        "instrument",
        "electronic"
    ],
    "wof:name":"Avtech Electrosystem Ltd",
    "wof:placetype":"venue"
},
  "geometry": {"coordinates":[-75.7218322754,45.3204460144],"type":"Point"}
}