{
  "type": "Feature",
  "properties": {
    "addr:full":"Toronto ON M5V 1E7",
    "addr:postcode":"m5v 1e7",
    "iso:country":"CA",
    "sg:city":"Toronto",
    "sg:classifiers":[
        {
            "category":"Professional",
            "subcategory":"Employment Agencies",
            "type":"Services"
        }
    ],
    "sg:phone":"+1 416 595 9855",
    "sg:postcode":"M5V 1E7",
    "sg:province":"ON",
    "sg:tags":[
        "modeling"
    ],
    "wof:name":"Testing Board",
    "wof:placetype":"venue"
},
  "geometry": {"coordinates":[-79.396294,43.643501],"type":"Point"}
}