{
  "type": "Feature",
  "properties": {
    "iso:country":"CA",
    "sg:address":"4095 Rue Tupper",
    "sg:city":"Westmount",
    "sg:classifiers":[
        {
            "category":"Shopping",
            "subcategory":"Optical Goods",
            "type":"Retail Goods"
        }
    ],
    "sg:phone":"+1 514 989 7340",
    "sg:postcode":"H3Z 3E5",
    "sg:province":"QC",
    "sg:tags":[
        "optician"
    ],
    "wof:name":"Optique Celine",
    "wof:placetype":"venue"
},
  "geometry": {"coordinates":[-73.585091,45.487972],"type":"Point"}
}