{
  "type": "Feature",
  "properties": {
    "addr:full":"PO Box 156 Tomahawk AB T0E 2H0",
    "addr:housenumber":"po",
    "addr:postcode":"t0e 2h0",
    "addr:street":"Box 156",
    "iso:country":"CA",
    "sg:address":"PO Box 156",
    "sg:city":"Tomahawk",
    "sg:classifiers":[
        {
            "category":"Organizations",
            "subcategory":"Religious Organization",
            "type":"Services"
        }
    ],
    "sg:phone":"+1 780 339 3733",
    "sg:postcode":"T0E 2H0",
    "sg:province":"AB",
    "sg:tags":[
        "church"
    ],
    "wof:name":"Immanuel Lutheran Church",
    "wof:placetype":"venue"
},
  "geometry": {"coordinates":[-114.76325199999999,53.396599],"type":"Point"}
}