{
  "type": "Feature",
  "properties": {
    "addr:full":"416 Queen St W Cambridge ON N3C 1H1",
    "addr:housenumber":"416",
    "addr:postcode":"n3c 1h1",
    "addr:street":"Queen St W",
    "iso:country":"CA",
    "sg:address":"416 Queen St W",
    "sg:city":"Cambridge",
    "sg:classifiers":[
        {
            "category":"Local Transit",
            "type":"Transportation"
        }
    ],
    "sg:phone":"+1 519 651 0000",
    "sg:postcode":"N3C 1H1",
    "sg:province":"ON",
    "sg:tags":[
        "limousine"
    ],
    "wof:name":"Hermi's Limousine Svc",
    "wof:placetype":"venue"
},
  "geometry": {"coordinates":[-80.326195,43.421257],"type":"Point"}
}