{
  "type": "Feature",
  "properties": {
    "addr:full":"10738 178 St NW Edmonton AB T5S 1J3",
    "addr:housenumber":"10738",
    "addr:postcode":"t5s 1j3",
    "addr:street":"178 St Nw",
    "iso:country":"CA",
    "sg:address":"10738 178 St NW",
    "sg:city":"Edmonton",
    "sg:classifiers":[
        {
            "category":"Wholesale",
            "subcategory":"Office Equipment",
            "type":"Manufacturing & Wholesale Goods"
        }
    ],
    "sg:phone":"+1 780 472 8072",
    "sg:postcode":"T5S 1J3",
    "sg:province":"AB",
    "sg:tags":[
        "register",
        "cash",
        "supply"
    ],
    "wof:name":"4S Systems Ltd",
    "wof:placetype":"venue"
},
  "geometry": {"coordinates":[-113.627571,53.553955],"type":"Point"}
}