{
  "type": "Feature",
  "properties": {
    "addr:full":"20 Ch Valley Wakefield QC J0X 3G0",
    "addr:housenumber":"20",
    "addr:postcode":"j0x 3g0",
    "addr:street":"Ch Valley",
    "iso:country":"CA",
    "sg:address":"20 Ch Valley",
    "sg:city":"Wakefield",
    "sg:classifiers":[
        {
            "category":"Education",
            "subcategory":"Library",
            "type":"Public Place"
        }
    ],
    "sg:phone":"+1 819 459 3266",
    "sg:postcode":"J0X 3G0",
    "sg:province":"QC",
    "wof:name":"Wakefield Library",
    "wof:placetype":"venue"
},
  "geometry": {"coordinates":[-75.935196,45.626415],"type":"Point"}
}