{
  "type": "Feature",
  "properties": {
    "addr:full":"Hamilton ON L8W 3K8",
    "addr:postcode":"l8w 3k8",
    "iso:country":"CA",
    "sg:city":"Hamilton",
    "sg:classifiers":[
        {
            "category":"Restaurant",
            "type":"Food & Drink"
        }
    ],
    "sg:phone":"+1 905 389 3074",
    "sg:postcode":"L8W 3K8",
    "sg:province":"ON",
    "sg:tags":[
        "parlor",
        "ice",
        "cream"
    ],
    "wof:name":"Dairy Queen",
    "wof:placetype":"venue"
},
  "geometry": {"coordinates":[-79.8418121338,43.1993560791],"type":"Point"}
}