{
  "type": "Feature",
  "properties": {
    "addr:full":"Hwy 17 Terrace Bay ON P0T 2W0",
    "addr:postcode":"p0t 2w0",
    "addr:street":"Hwy 17",
    "iso:country":"CA",
    "sg:address":"Hwy 17",
    "sg:city":"Terrace Bay",
    "sg:classifiers":[
        {
            "category":"Travel",
            "subcategory":"Campground",
            "type":"Entertainment"
        }
    ],
    "sg:phone":"+1 807 825 9773",
    "sg:postcode":"P0T 2W0",
    "sg:province":"ON",
    "sg:tags":[
        "sporting",
        "good"
    ],
    "wof:name":"Aguasabon Falls Camp Ground",
    "wof:placetype":"venue"
},
  "geometry": {"coordinates":[-87.084518,48.798721],"type":"Point"}
}