{
  "type": "Feature",
  "properties": {
    "addr:full":"PO Box 89 Entwistle AB T0E 0S0",
    "addr:housenumber":"po box 89;ab",
    "addr:postcode":"t0e 0s0",
    "addr:street":"Entwistle",
    "iso:country":"CA",
    "sg:address":"PO Box 89",
    "sg:city":"Entwistle",
    "sg:classifiers":[
        {
            "category":"Freight",
            "type":"Transportation"
        }
    ],
    "sg:phone":"+1 780 727 2422",
    "sg:postcode":"T0E 0S0",
    "sg:province":"AB",
    "sg:tags":[
        "field",
        "oil"
    ],
    "wof:name":"Roy Catt Water Hauling Ltd",
    "wof:placetype":"venue"
},
  "geometry": {"coordinates":[-114.992645264,53.5988540649],"type":"Point"}
}