{
  "type": "Feature",
  "properties": {
    "addr:full":"Indian Head SK S0G 2K0",
    "addr:postcode":"s0g 2k0",
    "iso:country":"CA",
    "sg:city":"Indian Head",
    "sg:classifiers":[
        {
            "category":"Government",
            "subcategory":"Office",
            "type":"Public Place"
        }
    ],
    "sg:phone":"+1 306 695 2274",
    "sg:postcode":"S0G 2K0",
    "sg:province":"SK",
    "wof:name":"Canada Agriculture & Agri-Food",
    "wof:placetype":"venue"
},
  "geometry": {"coordinates":[-103.678802,50.531769],"type":"Point"}
}