{
  "type": "Feature",
  "properties": {
    "iso:country":"CA",
    "sg:city":"Scarborough",
    "sg:classifiers":[
        {
            "category":"Shopping",
            "subcategory":"Optical Goods",
            "type":"Retail Goods"
        }
    ],
    "sg:phone":"+1 416 286 2020",
    "sg:postcode":"M1B 5M5",
    "sg:province":"ON",
    "sg:tags":[
        "optician"
    ],
    "wof:name":"Optical 20/20",
    "wof:placetype":"venue"
},
  "geometry": {"coordinates":[-79.1509170532,43.7980041504],"type":"Point"}
}