{
  "type": "Feature",
  "properties": {
    "addr:full":"210 Westpm Ave W Maidstone SK S0M 1M0",
    "addr:housenumber":"210",
    "addr:postcode":"s0m 1m0",
    "addr:street":"Westpm Ave W",
    "iso:country":"CA",
    "sg:address":"210 Westpm Ave W",
    "sg:city":"Maidstone",
    "sg:classifiers":[
        {
            "category":"Mining & Drilling",
            "type":"Manufacturing & Wholesale Goods"
        }
    ],
    "sg:phone":"+1 306 893 4500",
    "sg:postcode":"S0M 1M0",
    "sg:province":"SK",
    "sg:tags":[
        "excavating",
        "oil",
        "well",
        "contractor"
    ],
    "wof:name":"Twb Construction",
    "wof:placetype":"venue"
},
  "geometry": {"coordinates":[-109.296607971,53.0874595642],"type":"Point"}
}