{
  "type": "Feature",
  "properties": {
    "iso:country":"CA",
    "sg:address":"8 Elson St",
    "sg:city":"Markham",
    "sg:classifiers":[
        {
            "category":"Organizations",
            "subcategory":"Religious Organization",
            "type":"Services"
        }
    ],
    "sg:phone":"+1 905 472 3100",
    "sg:postcode":"L3S 2C4",
    "sg:province":"ON",
    "sg:tags":[
        "church"
    ],
    "wof:name":"Miliken Gospel Church",
    "wof:placetype":"venue"
},
  "geometry": {"coordinates":[-79.27564239500001,43.8354606628],"type":"Point"}
}