{
  "type": "Feature",
  "properties": {
    "addr:full":"1420 Walkley Rd Ottawa ON K1V 6P5",
    "addr:housenumber":"1420",
    "addr:postcode":"k1v 6p5",
    "addr:street":"Walkley Rd",
    "iso:country":"CA",
    "sg:address":"1420 Walkley Rd",
    "sg:city":"Ottawa",
    "sg:classifiers":[
        {
            "category":"Food & Beverages",
            "subcategory":"Groceries & Convenience Stores",
            "type":"Retail Goods"
        }
    ],
    "sg:phone":"+1 613 731 9002",
    "sg:postcode":"K1V 6P5",
    "sg:province":"ON",
    "sg:tags":[
        "grocer"
    ],
    "wof:name":"Mac's Convenience Stores Ltd",
    "wof:placetype":"venue"
},
  "geometry": {"coordinates":[-75.65374799999999,45.374046],"type":"Point"}
}