{
  "type": "Feature",
  "properties": {
    "addr:full":"1017 Monarch Rd Lindsay ON K9V 4R1",
    "addr:housenumber":"1017",
    "addr:postcode":"k9v 4r1",
    "addr:street":"Monarch Rd",
    "iso:country":"CA",
    "sg:address":"1017 Monarch Rd",
    "sg:city":"Lindsay",
    "sg:classifiers":[
        {
            "category":"Retail",
            "subcategory":"Portrait Studio",
            "type":"Services"
        }
    ],
    "sg:phone":"+1 705 324 3077",
    "sg:postcode":"K9V 4R1",
    "sg:province":"ON",
    "sg:tags":[
        "photographer"
    ],
    "wof:name":"Burns Photography",
    "wof:placetype":"venue"
},
  "geometry": {"coordinates":[-78.7986831665,44.3772697449],"type":"Point"}
}