{
  "type": "Feature",
  "properties": {
    "addr:full":"RR 1 Midhurst ON L0L 1X0",
    "addr:postcode":"l0l 1x0",
    "addr:street":"Rr 1",
    "iso:country":"CA",
    "sg:address":"RR 1",
    "sg:city":"Midhurst",
    "sg:classifiers":[
        {
            "category":"Building & Trades",
            "subcategory":"Construction",
            "type":"Services"
        }
    ],
    "sg:phone":"+1 705 725 1239",
    "sg:postcode":"L0L 1X0",
    "sg:province":"ON",
    "sg:tags":[
        "maker",
        "cabinet"
    ],
    "wof:name":"Paul's Cabinetworks",
    "wof:placetype":"venue"
},
  "geometry": {"coordinates":[-79.73015599999999,44.444496],"type":"Point"}
}