{
  "type": "Feature",
  "properties": {
    "iso:country":"CA",
    "sg:address":"1388 Spruce St",
    "sg:city":"Winnipeg",
    "sg:classifiers":[
        {
            "category":"Professional",
            "subcategory":"Computer Services",
            "type":"Services"
        }
    ],
    "sg:phone":"+1 204 774 1741",
    "sg:postcode":"R3E 2V7",
    "sg:province":"MB",
    "sg:tags":[
        "repair",
        "dealer",
        "equipment"
    ],
    "wof:name":"Tellier Electronics Ltd",
    "wof:placetype":"venue"
},
  "geometry": {"coordinates":[-97.1864929199,49.9060173035],"type":"Point"}
}