{
  "type": "Feature",
  "properties": {
    "addr:full":"1541 Star Top Rd Gloucester ON K1B 3W5",
    "addr:housenumber":"1541",
    "addr:postcode":"k1b 3w5",
    "addr:street":"Star Top Rd",
    "iso:country":"CA",
    "sg:address":"1541 Star Top Rd",
    "sg:city":"Gloucester",
    "sg:classifiers":[
        {
            "category":"Building & Trades",
            "subcategory":"Electrical",
            "type":"Services"
        }
    ],
    "sg:phone":"+1 613 744 2088",
    "sg:postcode":"K1B 3W5",
    "sg:province":"ON",
    "sg:tags":[
        "electric",
        "contractor"
    ],
    "wof:name":"Farley Electric Ltd",
    "wof:placetype":"venue"
},
  "geometry": {"coordinates":[-75.61573799999999,45.416031],"type":"Point"}
}