{
  "type": "Feature",
  "properties": {
    "iso:country":"CA",
    "sg:address":"106 Saunders Rd",
    "sg:city":"Barrie",
    "sg:classifiers":[
        {
            "category":"Insurance",
            "subcategory":"Insurance Agent",
            "type":"Services"
        }
    ],
    "sg:phone":"+1 705 726 6670",
    "sg:postcode":"L4N 9A8",
    "sg:province":"ON",
    "wof:name":"State Farm Insurance CO",
    "wof:placetype":"venue"
},
  "geometry": {"coordinates":[-79.681091,44.330406],"type":"Point"}
}