{
  "type": "Feature",
  "properties": {
    "addr:full":"3557 Melbourne Rd Windsor ON N9C 1Y6",
    "addr:housenumber":"3557",
    "addr:postcode":"n9c 1y6",
    "addr:street":"Melbourne Rd",
    "iso:country":"CA",
    "sg:address":"3557 Melbourne Rd",
    "sg:city":"Windsor",
    "sg:classifiers":[
        {
            "category":"Education",
            "subcategory":"School",
            "type":"Public Place"
        }
    ],
    "sg:phone":"+1 519 254 2881",
    "sg:postcode":"N9C 1Y6",
    "sg:province":"ON",
    "wof:name":"Marlborough Public Elementary",
    "wof:placetype":"venue"
},
  "geometry": {"coordinates":[-83.064781189,42.289894104],"type":"Point"}
}