{
  "type": "Feature",
  "properties": {
    "addr:full":"8597 156 St Surrey BC V3S 3R8",
    "addr:housenumber":"8597",
    "addr:postcode":"v3s 3r8",
    "addr:street":"156 St",
    "iso:country":"CA",
    "sg:address":"8597 156 St",
    "sg:city":"Surrey",
    "sg:classifiers":[
        {
            "category":"Social Services",
            "subcategory":"Child Care",
            "type":"Services"
        }
    ],
    "sg:phone":"+1 604 597 0638",
    "sg:postcode":"V3S 3R8",
    "sg:province":"BC",
    "wof:name":"Maria Montessori School",
    "wof:placetype":"venue"
},
  "geometry": {"coordinates":[-122.790268,49.159065],"type":"Point"}
}