{
  "type": "Feature",
  "properties": {
    "addr:full":"2677 Boul Albiny-Paquette Mont-Laurier QC J9L 3G5",
    "addr:housenumber":"2677",
    "addr:postcode":"j9l 3g5",
    "addr:street":"Boul Albiny-Paquette",
    "iso:country":"CA",
    "sg:address":"2677 Boul Albiny-Paquette",
    "sg:city":"Mont-Laurier",
    "sg:classifiers":[
        {
            "category":"Wholesale",
            "subcategory":"Construction Materials",
            "type":"Manufacturing & Wholesale Goods"
        }
    ],
    "sg:phone":"+1 819 623 3278",
    "sg:postcode":"J9L 3G5",
    "sg:province":"QC",
    "sg:tags":[
        "concrete",
        "form"
    ],
    "wof:name":"Coffrages Laurentiens Inc",
    "wof:placetype":"venue"
},
  "geometry": {"coordinates":[-75.42968,46.546227],"type":"Point"}
}