{
  "type": "Feature",
  "properties": {
    "iso:country":"CA",
    "sg:address":"200 Bloor St E",
    "sg:city":"Toronto",
    "sg:classifiers":[
        {
            "category":"Banks & Credit Unions",
            "subcategory":"Investment Brokerage",
            "type":"Services"
        }
    ],
    "sg:phone":"+1 416 581 8300",
    "sg:postcode":"M4W 1E5",
    "sg:province":"ON",
    "sg:tags":[
        "funds",
        "mutual"
    ],
    "wof:name":"Elliott & Page Ltd",
    "wof:placetype":"venue"
},
  "geometry": {"coordinates":[-79.3817977905,43.6714515686],"type":"Point"}
}