{
  "type": "Feature",
  "properties": {
    "addr:full":"322 King St W Toronto ON M5V 1J2",
    "addr:housenumber":"322",
    "addr:postcode":"m5v 1j2",
    "addr:street":"King St W",
    "iso:country":"CA",
    "sg:address":"322 King St W",
    "sg:city":"Toronto",
    "sg:classifiers":[
        {
            "category":"Shopping",
            "subcategory":"Gifts & Souvenirs",
            "type":"Retail Goods"
        }
    ],
    "sg:phone":"+1 416 343 4999",
    "sg:postcode":"M5V 1J2",
    "sg:province":"ON",
    "sg:tags":[
        "collectible"
    ],
    "wof:name":"Theatre Q's",
    "wof:placetype":"venue"
},
  "geometry": {"coordinates":[-79.38957977290001,43.6467704773],"type":"Point"}
}