{
  "type": "Feature",
  "properties": {
    "iso:country":"CA",
    "sg:address":"95 9E Rue N",
    "sg:city":"Thetford Mines",
    "sg:classifiers":[
        {
            "category":"Organizations",
            "subcategory":"Professional Association",
            "type":"Services"
        }
    ],
    "sg:phone":"+1 418 335 7366",
    "sg:postcode":"G6G 5J1",
    "sg:province":"QC",
    "wof:name":"Club DE L'Age D'Or St-Noel",
    "wof:placetype":"venue"
},
  "geometry": {"coordinates":[-71.280724,46.103832],"type":"Point"}
}