{
  "type": "Feature",
  "properties": {
    "addr:full":"North York ON M3J 2E5",
    "addr:postcode":"m3j 2e5",
    "iso:country":"CA",
    "sg:city":"North York",
    "sg:classifiers":[
        {
            "category":"Professional",
            "subcategory":"Lawyer & Legal Services",
            "type":"Services"
        }
    ],
    "sg:phone":"+1 416 661 3605",
    "sg:postcode":"M3J 2E5",
    "sg:province":"ON",
    "sg:tags":[
        "naturalization",
        "immigration"
    ],
    "wof:name":"Omega Consultants",
    "wof:placetype":"venue"
},
  "geometry": {"coordinates":[-79.4723739624,43.7674980164],"type":"Point"}
}