{
  "type": "Feature",
  "properties": {
    "addr:full":"225 Boul Saint-Joseph Saint-Jean-Sur-Richelieu QC J3B 1W8",
    "addr:housenumber":"225",
    "addr:postcode":"j3b 1w8",
    "addr:street":"Boul Saint-Joseph",
    "iso:country":"CA",
    "sg:address":"225 Boul Saint-Joseph",
    "sg:city":"Saint-Jean-Sur-Richelieu",
    "sg:classifiers":[
        {
            "category":"Travel",
            "subcategory":"Travel Agent",
            "type":"Entertainment"
        }
    ],
    "sg:phone":"+1 450 349 2320",
    "sg:postcode":"J3B 1W8",
    "sg:province":"QC",
    "sg:tags":[
        "agency",
        "bureau"
    ],
    "wof:name":"Voyages Mv",
    "wof:placetype":"venue"
},
  "geometry": {"coordinates":[-73.262657,45.314495],"type":"Point"}
}