{
  "type": "Feature",
  "properties": {
    "iso:country":"CA",
    "sg:city":"Richmond",
    "sg:classifiers":[
        {
            "category":"Manufacturing",
            "subcategory":"Metals",
            "type":"Manufacturing & Wholesale Goods"
        }
    ],
    "sg:phone":"+1 604 273 3220",
    "sg:postcode":"V6X 1X5",
    "sg:province":"BC",
    "sg:tags":[
        "engraver",
        "name"
    ],
    "wof:name":"Richmond Recognition",
    "wof:placetype":"venue"
},
  "geometry": {"coordinates":[-123.147880554,49.177318573],"type":"Point"}
}