{
  "type": "Feature",
  "properties": {
    "addr:full":"600 Vine St St Catharines ON L2M 3V1",
    "addr:housenumber":"600",
    "addr:postcode":"l2m 3v1",
    "addr:street":"Vine St",
    "iso:country":"CA",
    "sg:address":"600 Vine St",
    "sg:city":"St Catharines",
    "sg:classifiers":[
        {
            "category":"Education",
            "subcategory":"School",
            "type":"Public Place"
        }
    ],
    "sg:phone":"+1 905 934 2525",
    "sg:postcode":"L2M 3V1",
    "sg:province":"ON",
    "wof:name":"Prince Philip School",
    "wof:placetype":"venue"
},
  "geometry": {"coordinates":[-79.2315292358,43.2070236206],"type":"Point"}
}