{
  "type": "Feature",
  "properties": {
    "addr:full":"Fort St James BC V0J 1P0",
    "addr:postcode":"v0j 1p0",
    "addr:street":"Fort St",
    "iso:country":"CA",
    "sg:city":"Fort St James",
    "sg:classifiers":[
        {
            "category":"Professional",
            "subcategory":"Lawyer & Legal Services",
            "type":"Services"
        }
    ],
    "sg:phone":"+1 250 996 8687",
    "sg:postcode":"V0J 1P0",
    "sg:province":"BC",
    "sg:tags":[
        "attorney"
    ],
    "wof:name":"Hope Heinrich",
    "wof:placetype":"venue"
},
  "geometry": {"coordinates":[-124.264282227,54.4468955994],"type":"Point"}
}