{
  "type": "Feature",
  "properties": {
    "iso:country":"CA",
    "sg:address":"3983 Boul Lite",
    "sg:city":"Laval",
    "sg:classifiers":[
        {
            "category":"Building & Trades",
            "subcategory":"Construction",
            "type":"Services"
        }
    ],
    "sg:phone":"+1 450 661 1102",
    "sg:postcode":"H7E 1A3",
    "sg:province":"QC",
    "sg:tags":[
        "general",
        "contractor"
    ],
    "wof:name":"Construction & Dev Cris Ltee",
    "wof:placetype":"venue"
},
  "geometry": {"coordinates":[-73.66684,45.6119],"type":"Point"}
}