{
  "type": "Feature",
  "properties": {
    "addr:full":"12816 St Albert Trail NW Edmonton AB T5L 4H6",
    "addr:housenumber":"12816",
    "addr:postcode":"t5l 4h6",
    "addr:street":"St Albert Trail Nw",
    "iso:country":"CA",
    "sg:address":"12816 St Albert Trail NW",
    "sg:city":"Edmonton",
    "sg:classifiers":[
        {
            "category":"Insurance",
            "subcategory":"Insurance Agent",
            "type":"Services"
        }
    ],
    "sg:phone":"+1 780 451 3666",
    "sg:postcode":"T5L 4H6",
    "sg:province":"AB",
    "wof:name":"D M Provost Insurance",
    "wof:placetype":"venue"
},
  "geometry": {"coordinates":[-113.561927795,53.5859184265],"type":"Point"}
}