{
  "type": "Feature",
  "properties": {
    "addr:full":"1750 Rue Du Perigord Charlesbourg QC G1G 5X3",
    "addr:housenumber":"1750",
    "addr:postcode":"g1g 5x3",
    "addr:street":"Rue Du Perigord",
    "iso:country":"CA",
    "sg:address":"1750 Rue Du Perigord",
    "sg:city":"Charlesbourg",
    "sg:classifiers":[
        {
            "category":"Personal",
            "subcategory":"Beauty Salon",
            "type":"Services"
        }
    ],
    "sg:phone":"+1 418 623 6692",
    "sg:postcode":"G1G 5X3",
    "sg:province":"QC",
    "wof:name":"Capri International",
    "wof:placetype":"venue"
},
  "geometry": {"coordinates":[-71.289795,46.86771],"type":"Point"}
}