{
  "type": "Feature",
  "properties": {
    "addr:full":"Toronto ON M6H 4H4",
    "addr:postcode":"m6h 4h4",
    "iso:country":"CA",
    "sg:city":"Toronto",
    "sg:classifiers":[
        {
            "category":"Health Services",
            "subcategory":"Doctor",
            "type":"Services"
        }
    ],
    "sg:phone":"+1 416 652 3000",
    "sg:postcode":"M6H 4H4",
    "sg:province":"ON",
    "sg:tags":[
        "physician",
        "surgeon"
    ],
    "wof:name":"Stefou, V MD",
    "wof:placetype":"venue"
},
  "geometry": {"coordinates":[-79.4423294067,43.6764564514],"type":"Point"}
}