{
  "type": "Feature",
  "properties": {
    "iso:country":"CA",
    "sg:address":"285 Geneva St",
    "sg:city":"St Catharines",
    "sg:classifiers":[
        {
            "category":"Travel",
            "subcategory":"Travel Agent",
            "type":"Entertainment"
        }
    ],
    "sg:phone":"+1 905 937 0550",
    "sg:postcode":"L2N 2G1",
    "sg:province":"ON",
    "sg:tags":[
        "agency",
        "bureau"
    ],
    "wof:name":"Raptim Travel",
    "wof:placetype":"venue"
},
  "geometry": {"coordinates":[-79.2409896851,43.1771812439],"type":"Point"}
}