{
  "type": "Feature",
  "properties": {
    "addr:full":"1056 Boul Dr Camille Marcoux Lourdes-DE-Blanc-Sablon QC G0G 1W0",
    "addr:housenumber":"1056",
    "addr:postcode":"g0g 1w0",
    "addr:street":"Boul Dr Camille Marcoux",
    "iso:country":"CA",
    "sg:address":"1056 Boul Dr Camille Marcoux",
    "sg:city":"Lourdes-DE-Blanc-Sablon",
    "sg:classifiers":[
        {
            "category":"Banks & Credit Unions",
            "subcategory":"Bank",
            "type":"Services"
        }
    ],
    "sg:phone":"+1 418 461 2020",
    "sg:postcode":"G0G 1W0",
    "sg:province":"QC",
    "wof:name":"Caisse Desjardins Blanc-Sablon",
    "wof:placetype":"venue"
},
  "geometry": {"coordinates":[-57.2050590515,51.4142684937],"type":"Point"}
}