{
  "type": "Feature",
  "properties": {
    "addr:full":"290 Guelph St Georgetown ON L7G 4B1",
    "addr:housenumber":"290",
    "addr:postcode":"l7g 4b1",
    "addr:street":"Guelph St",
    "iso:country":"CA",
    "sg:address":"290 Guelph St",
    "sg:city":"Georgetown",
    "sg:classifiers":[
        {
            "category":"Shopping",
            "subcategory":"Pharmacy",
            "type":"Retail Goods"
        }
    ],
    "sg:phone":"+1 905 877 2291",
    "sg:postcode":"L7G 4B1",
    "sg:province":"ON",
    "wof:name":"Shoppers Drug Mart",
    "wof:placetype":"venue"
},
  "geometry": {"coordinates":[-79.8943481445,43.6496238708],"type":"Point"}
}