{
  "type": "Feature",
  "properties": {
    "addr:full":"7736 Rue Saint-Hubert Montreal QC H2R 2N8",
    "addr:housenumber":"7736",
    "addr:postcode":"h2r 2n8",
    "addr:street":"Rue Saint-Hubert",
    "iso:country":"CA",
    "sg:address":"7736 Rue Saint-Hubert",
    "sg:city":"Montreal",
    "sg:classifiers":[
        {
            "category":"Personal",
            "subcategory":"Barber",
            "type":"Services"
        }
    ],
    "sg:phone":"+1 514 272 3220",
    "sg:postcode":"H2R 2N8",
    "sg:province":"QC",
    "wof:name":"Salon Emilio",
    "wof:placetype":"venue"
},
  "geometry": {"coordinates":[-73.62190246580001,45.5446014404],"type":"Point"}
}