{
  "type": "Feature",
  "properties": {
    "addr:full":"160 Av Maplewood Outremont QC H2V 2M5",
    "addr:housenumber":"160",
    "addr:postcode":"h2v 2m5",
    "addr:street":"Av Maplewood",
    "iso:country":"CA",
    "sg:address":"160 Av Maplewood",
    "sg:city":"Outremont",
    "sg:classifiers":[
        {
            "category":"Wholesale",
            "subcategory":"Durable Goods & Equipment",
            "type":"Manufacturing & Wholesale Goods"
        }
    ],
    "sg:phone":"+1 514 277 3536",
    "sg:postcode":"H2V 2M5",
    "sg:province":"QC",
    "sg:tags":[
        "importer"
    ],
    "wof:name":"Jamal Collection Inc",
    "wof:placetype":"venue"
},
  "geometry": {"coordinates":[-73.60335540769999,45.513469696],"type":"Point"}
}