{
  "type": "Feature",
  "properties": {
    "addr:full":"960 Brimorton Dr Scarborough ON M1G 2V2",
    "addr:housenumber":"960",
    "addr:postcode":"m1g 2v2",
    "addr:street":"Brimorton Dr",
    "iso:country":"CA",
    "sg:address":"960 Brimorton Dr",
    "sg:city":"Scarborough",
    "sg:classifiers":[
        {
            "category":"Home & Garden",
            "subcategory":"Household Appliances",
            "type":"Retail Goods"
        }
    ],
    "sg:phone":"+1 416 431 7323",
    "sg:postcode":"M1G 2V2",
    "sg:province":"ON",
    "wof:name":"Bawa Appliances",
    "wof:placetype":"venue"
},
  "geometry": {"coordinates":[-79.210067749,43.7712936401],"type":"Point"}
}