{
  "type": "Feature",
  "properties": {
    "addr:full":"390 Main St E Palmerston ON N0G 2P0",
    "addr:housenumber":"390",
    "addr:postcode":"n0g 2p0",
    "addr:street":"Main St E",
    "iso:country":"CA",
    "sg:address":"390 Main St E",
    "sg:city":"Palmerston",
    "sg:classifiers":[
        {
            "category":"Professional",
            "subcategory":"Printing & Photocopies",
            "type":"Services"
        }
    ],
    "sg:phone":"+1 519 343 3806",
    "sg:postcode":"N0G 2P0",
    "sg:province":"ON",
    "sg:tags":[
        "duplicating",
        "copying",
        "supply"
    ],
    "wof:name":"Solutions Office Svc & Supls",
    "wof:placetype":"venue"
},
  "geometry": {"coordinates":[-80.8439941406,43.8347434998],"type":"Point"}
}