{
  "type": "Feature",
  "properties": {
    "addr:full":"Pembroke ON K8A 6W5",
    "addr:postcode":"k8a 6w5",
    "iso:country":"CA",
    "sg:city":"Pembroke",
    "sg:classifiers":[
        {
            "category":"Manufacturing",
            "subcategory":"Tools & Machinery",
            "type":"Manufacturing & Wholesale Goods"
        }
    ],
    "sg:phone":"+1 613 732 0055",
    "sg:postcode":"K8A 6W5",
    "sg:province":"ON",
    "sg:tags":[
        "equipment",
        "lighting"
    ],
    "wof:name":"Srb Technologies Canada Inc",
    "wof:placetype":"venue"
},
  "geometry": {"coordinates":[-77.1170883179,45.8050422668],"type":"Point"}
}