{
  "type": "Feature",
  "properties": {
    "addr:full":"Anjou QC H1J 2A1",
    "addr:postcode":"h1j 2a1",
    "iso:country":"CA",
    "sg:city":"Anjou",
    "sg:classifiers":[
        {
            "category":"Home & Garden",
            "subcategory":"Building Materials",
            "type":"Retail Goods"
        }
    ],
    "sg:phone":"+1 514 493 6706",
    "sg:postcode":"H1J 2A1",
    "sg:province":"QC",
    "sg:tags":[
        "windows"
    ],
    "wof:name":"Ultra Aluminium Inc",
    "wof:placetype":"venue"
},
  "geometry": {"coordinates":[-73.568192,45.609962],"type":"Point"}
}