{
  "type": "Feature",
  "properties": {
    "addr:full":"344 Wilson Ave North York ON M3H 1S9",
    "addr:housenumber":"344",
    "addr:postcode":"m3h 1s9",
    "addr:street":"Wilson Ave",
    "iso:country":"CA",
    "sg:address":"344 Wilson Ave",
    "sg:city":"North York",
    "sg:classifiers":[
        {
            "category":"Food & Beverages",
            "subcategory":"Fruits & Vegetables",
            "type":"Retail Goods"
        }
    ],
    "sg:phone":"+1 416 638 4086",
    "sg:postcode":"M3H 1S9",
    "sg:province":"ON",
    "sg:tags":[
        "produce"
    ],
    "wof:name":"Wilson Oriental Foods",
    "wof:placetype":"venue"
},
  "geometry": {"coordinates":[-79.4377288818,43.7367401123],"type":"Point"}
}