{
  "type": "Feature",
  "properties": {
    "addr:full":"1167 Westmount Shopping Ctr NW # 224 Edmonton AB T5M 3L7",
    "addr:housenumber":"1167",
    "addr:postcode":"t5m 3l7",
    "addr:street":"Westmount Shopping Ctr Nw # 224",
    "iso:country":"CA",
    "sg:address":"1167 Westmount Shopping Ctr NW # 224",
    "sg:city":"Edmonton",
    "sg:classifiers":[
        {
            "category":"Cinema",
            "subcategory":"Movie Rental",
            "type":"Entertainment"
        }
    ],
    "sg:phone":"+1 780 455 9269",
    "sg:postcode":"T5M 3L7",
    "sg:province":"AB",
    "sg:tags":[
        "player",
        "recorder",
        "video",
        "leasing",
        "tape"
    ],
    "wof:name":"Blockbuster Video",
    "wof:placetype":"venue"
},
  "geometry": {"coordinates":[-113.49037199999999,53.546219],"type":"Point"}
}