{
  "type": "Feature",
  "properties": {
    "addr:full":"Montreal QC H2Y 1N3",
    "addr:postcode":"h2y 1n3",
    "iso:country":"CA",
    "sg:city":"Montreal",
    "sg:classifiers":[
        {
            "category":"Professional",
            "subcategory":"Lawyer & Legal Services",
            "type":"Services"
        }
    ],
    "sg:phone":"+1 514 842 1126",
    "sg:postcode":"H2Y 1N3",
    "sg:province":"QC",
    "sg:tags":[
        "attorney"
    ],
    "wof:name":"Deschenes & Assoc",
    "wof:placetype":"venue"
},
  "geometry": {"coordinates":[-73.558876,45.502983],"type":"Point"}
}