{
  "type": "Feature",
  "properties": {
    "addr:full":"Thetford Mines QC G6G 5V9",
    "addr:postcode":"g6g 5v9",
    "iso:country":"CA",
    "sg:city":"Thetford Mines",
    "sg:classifiers":[
        {
            "category":"Health Services",
            "subcategory":"Optometrist",
            "type":"Services"
        }
    ],
    "sg:phone":"+1 418 335 7393",
    "sg:postcode":"G6G 5V9",
    "sg:province":"QC",
    "wof:name":"Clinique D'Optometrie Mines",
    "wof:placetype":"venue"
},
  "geometry": {"coordinates":[-71.29926300050001,46.0905761719],"type":"Point"}
}