{
  "type": "Feature",
  "properties": {
    "addr:full":"19 Waxwing Way Brantford ON N3R 6W5",
    "addr:housenumber":"19",
    "addr:postcode":"n3r 6w5",
    "addr:street":"Waxwing Way",
    "iso:country":"CA",
    "sg:address":"19 Waxwing Way",
    "sg:city":"Brantford",
    "sg:classifiers":[
        {
            "category":"Organizations",
            "subcategory":"Professional Association",
            "type":"Services"
        }
    ],
    "sg:phone":"+1 519 754 0877",
    "sg:postcode":"N3R 6W5",
    "sg:province":"ON",
    "wof:name":"Girl Guides of Canada",
    "wof:placetype":"venue"
},
  "geometry": {"coordinates":[-80.26160400000001,43.186275],"type":"Point"}
}