{
  "type": "Feature",
  "properties": {
    "iso:country":"CA",
    "sg:city":"Quebec",
    "sg:classifiers":[
        {
            "category":"Real Estate",
            "subcategory":"Real Estate Operator",
            "type":"Services"
        }
    ],
    "sg:phone":"+1 418 872 7836",
    "sg:postcode":"G1P 3X4",
    "sg:province":"QC",
    "sg:tags":[
        "apartment"
    ],
    "wof:name":"Immeuble Gestion Houle Enr",
    "wof:placetype":"venue"
},
  "geometry": {"coordinates":[-71.3309249878,46.8254013062],"type":"Point"}
}