{
  "type": "Feature",
  "properties": {
    "addr:full":"290 Petite Noraie Rg Saint-Charles-Borromee QC J6E 3Z1",
    "addr:housenumber":"290",
    "addr:postcode":"j6e 3z1",
    "addr:street":"Petite Noraie",
    "iso:country":"CA",
    "sg:address":"290 Petite Noraie Rg",
    "sg:city":"Saint-Charles-Borromee",
    "sg:classifiers":[
        {
            "category":"Personal",
            "subcategory":"Beauty Salon",
            "type":"Services"
        }
    ],
    "sg:phone":"+1 450 759 9491",
    "sg:postcode":"J6E 3Z1",
    "sg:province":"QC",
    "wof:name":"Salon DE Coiffure Creation",
    "wof:placetype":"venue"
},
  "geometry": {"coordinates":[-73.47650146479999,46.03490448],"type":"Point"}
}