{
  "type": "Feature",
  "properties": {
    "addr:full":"10628 75 Ave NW Edmonton AB T6E 1J7",
    "addr:housenumber":"10628",
    "addr:postcode":"t6e 1j7",
    "addr:street":"75 Ave Nw",
    "iso:country":"CA",
    "sg:address":"10628 75 Ave NW",
    "sg:city":"Edmonton",
    "sg:classifiers":[
        {
            "category":"Building & Trades",
            "subcategory":"Cleaning & Sanitation",
            "type":"Services"
        }
    ],
    "sg:phone":"+1 780 438 2816",
    "sg:postcode":"T6E 1J7",
    "sg:province":"AB",
    "sg:tags":[
        "window"
    ],
    "wof:name":"Whirlwind-Murray",
    "wof:placetype":"venue"
},
  "geometry": {"coordinates":[-113.505058289,53.5114517212],"type":"Point"}
}