{
  "type": "Feature",
  "properties": {
    "addr:full":"14 Clinton St Teeswater ON N0G 2S0",
    "addr:housenumber":"14",
    "addr:postcode":"n0g 2s0",
    "addr:street":"Clinton St",
    "iso:country":"CA",
    "sg:address":"14 Clinton St",
    "sg:city":"Teeswater",
    "sg:classifiers":[
        {
            "category":"Restaurant",
            "type":"Food & Drink"
        }
    ],
    "sg:phone":"+1 519 392 6888",
    "sg:postcode":"N0G 2S0",
    "sg:province":"ON",
    "wof:name":"Boomer's Cosy Restaurant",
    "wof:placetype":"venue"
},
  "geometry": {"coordinates":[-81.28743,44.000217],"type":"Point"}
}