{
  "type": "Feature",
  "properties": {
    "addr:full":"34 Ossington Ave Toronto ON M6J 2Y7",
    "addr:housenumber":"34",
    "addr:postcode":"m6j 2y7",
    "addr:street":"Ossington Ave",
    "iso:country":"CA",
    "sg:address":"34 Ossington Ave",
    "sg:city":"Toronto",
    "sg:classifiers":[
        {
            "category":"Freight",
            "type":"Transportation"
        }
    ],
    "sg:phone":"+1 416 534 4232",
    "sg:postcode":"M6J 2Y7",
    "sg:province":"ON",
    "sg:tags":[
        "commercial",
        "storage"
    ],
    "wof:name":"Ossington Self Storage",
    "wof:placetype":"venue"
},
  "geometry": {"coordinates":[-79.4193344116,43.6451072693],"type":"Point"}
}