{
  "type": "Feature",
  "properties": {
    "iso:country":"CA",
    "sg:address":"13377 72 Ave",
    "sg:city":"Surrey",
    "sg:classifiers":[
        {
            "category":"Recreation",
            "type":"Entertainment"
        }
    ],
    "sg:phone":"+1 604 501 9966",
    "sg:postcode":"V3W 2N5",
    "sg:province":"BC",
    "sg:tags":[
        "paint",
        "game",
        "ball",
        "sport"
    ],
    "wof:name":"Tsawwassen Paintball Games",
    "wof:placetype":"venue"
},
  "geometry": {"coordinates":[-122.867919922,49.1339607239],"type":"Point"}
}