{
  "type": "Feature",
  "properties": {
    "addr:full":"524 74E Av Laval QC H7V 2Y1",
    "addr:housenumber":"524",
    "addr:postcode":"h7v 2y1",
    "addr:street":"74E Av",
    "iso:country":"CA",
    "sg:address":"524 74E Av",
    "sg:city":"Laval",
    "sg:classifiers":[
        {
            "category":"Manufacturing",
            "subcategory":"Metals",
            "type":"Manufacturing & Wholesale Goods"
        }
    ],
    "sg:phone":"+1 450 687 0631",
    "sg:postcode":"H7V 2Y1",
    "sg:province":"QC",
    "sg:tags":[
        "solder",
        "welding"
    ],
    "wof:name":"Soudure F Pelletier",
    "wof:placetype":"venue"
},
  "geometry": {"coordinates":[-73.73657989500001,45.5390167236],"type":"Point"}
}