{
  "type": "Feature",
  "properties": {
    "addr:full":"PO Box 7983 STN Main Edson AB T7E 1W2",
    "addr:housenumber":"po",
    "addr:postcode":"t7e 1w2",
    "addr:street":"Box 7983 Stn Main",
    "iso:country":"CA",
    "sg:address":"PO Box 7983 STN Main",
    "sg:city":"Edson",
    "sg:classifiers":[
        {
            "category":"Wholesale",
            "subcategory":"Durable Goods & Equipment",
            "type":"Manufacturing & Wholesale Goods"
        }
    ],
    "sg:phone":"+1 780 723 7705",
    "sg:postcode":"T7E 1W2",
    "sg:province":"AB",
    "sg:tags":[
        "water",
        "environmental",
        "product",
        "well",
        "drilling"
    ],
    "wof:name":"Craig Waterwell & Drilling Ltd",
    "wof:placetype":"venue"
},
  "geometry": {"coordinates":[-116.43409699999999,53.58213],"type":"Point"}
}