{
  "type": "Feature",
  "properties": {
    "addr:full":"41 Rue Rodrigue S Amqui QC G5J 1T1",
    "addr:housenumber":"41",
    "addr:postcode":"g5j 1t1",
    "addr:street":"Rue Rodrigue S",
    "iso:country":"CA",
    "sg:address":"41 Rue Rodrigue S",
    "sg:city":"Amqui",
    "sg:classifiers":[
        {
            "category":"Social Services",
            "type":"Services"
        }
    ],
    "sg:phone":"+1 418 629 1445",
    "sg:postcode":"G5J 1T1",
    "sg:province":"QC",
    "sg:tags":[
        "home",
        "senior",
        "retirement",
        "community",
        "citizen"
    ],
    "wof:name":"Residence Rodrigue Enr",
    "wof:placetype":"venue"
},
  "geometry": {"coordinates":[-67.4263763428,48.4628372192],"type":"Point"}
}