{
  "type": "Feature",
  "properties": {
    "addr:full":"600 Boul Lafleche Baie-Comeau QC G5C 2X8",
    "addr:housenumber":"600",
    "addr:postcode":"g5c 2x8",
    "addr:street":"Boul Lafleche",
    "iso:country":"CA",
    "sg:address":"600 Boul Lafleche",
    "sg:city":"Baie-Comeau",
    "sg:classifiers":[
        {
            "category":"Shopping",
            "subcategory":"Pharmacy",
            "type":"Retail Goods"
        }
    ],
    "sg:phone":"+1 418 589 9908",
    "sg:postcode":"G5C 2X8",
    "sg:province":"QC",
    "wof:name":"Pharmaprix",
    "wof:placetype":"venue"
},
  "geometry": {"coordinates":[-68.256905,49.200821],"type":"Point"}
}