{
  "type": "Feature",
  "properties": {
    "addr:full":"Farnham QC J2N 2P9",
    "addr:postcode":"j2n 2p9",
    "iso:country":"CA",
    "sg:city":"Farnham",
    "sg:classifiers":[
        {
            "category":"Travel",
            "subcategory":"Campground",
            "type":"Entertainment"
        }
    ],
    "sg:phone":"+1 450 293 6427",
    "sg:postcode":"J2N 2P9",
    "sg:province":"QC",
    "sg:tags":[
        "camp"
    ],
    "wof:name":"Club DE Chasse & DE Peche",
    "wof:placetype":"venue"
},
  "geometry": {"coordinates":[-72.9752655029,45.2833518982],"type":"Point"}
}