{
  "type": "Feature",
  "properties": {
    "addr:full":"2713 Old Lakeshore Rd Brights Grove ON N0N 1C0",
    "addr:housenumber":"2713",
    "addr:postcode":"n0n 1c0",
    "addr:street":"Old Lakeshore Rd",
    "iso:country":"CA",
    "sg:address":"2713 Old Lakeshore Rd",
    "sg:city":"Brights Grove",
    "sg:classifiers":[
        {
            "category":"Restaurant",
            "type":"Food & Drink"
        }
    ],
    "sg:phone":"+1 519 869 2794",
    "sg:postcode":"N0N 1C0",
    "sg:province":"ON",
    "wof:name":"Skeeter Barlow's Grill & Bar",
    "wof:placetype":"venue"
},
  "geometry": {"coordinates":[-82.25173950200001,43.0335426331],"type":"Point"}
}