{
  "type": "Feature",
  "properties": {
    "addr:full":"33 Rue Des Forges Amqui QC G5J 3A5",
    "addr:housenumber":"33",
    "addr:postcode":"g5j 3a5",
    "addr:street":"Rue Des Forges",
    "iso:country":"CA",
    "sg:address":"33 Rue Des Forges",
    "sg:city":"Amqui",
    "sg:classifiers":[
        {
            "category":"Shopping",
            "subcategory":"Computers & Home Electronics",
            "type":"Retail Goods"
        }
    ],
    "sg:phone":"+1 418 629 2400",
    "sg:postcode":"G5J 3A5",
    "sg:province":"QC",
    "sg:tags":[
        "equipment",
        "electronic",
        "telephone",
        "cellular"
    ],
    "wof:name":"Stereo Plus",
    "wof:placetype":"venue"
},
  "geometry": {"coordinates":[-67.4332351685,48.4647102356],"type":"Point"}
}