{
  "type": "Feature",
  "properties": {
    "addr:full":"15 Av Palmer Otter Lake QC J0X 2P0",
    "addr:postcode":"j0x 2p0",
    "addr:street":"15 Av Palmer",
    "iso:country":"CA",
    "sg:address":"15 Av Palmer",
    "sg:city":"Otter Lake",
    "sg:classifiers":[
        {
            "category":"Government",
            "subcategory":"Office",
            "type":"Public Place"
        }
    ],
    "sg:phone":"+1 819 453 7049",
    "sg:postcode":"J0X 2P0",
    "sg:province":"QC",
    "sg:tags":[
        "village"
    ],
    "wof:name":"Leslie-Clapham-Huddersfields",
    "wof:placetype":"venue"
},
  "geometry": {"coordinates":[-76.4348602295,45.8527565002],"type":"Point"}
}