{
  "type": "Feature",
  "properties": {
    "addr:full":"375 Mcarthur Ave Vanier ON K1L 6N5",
    "addr:housenumber":"375",
    "addr:postcode":"k1l 6n5",
    "addr:street":"Mcarthur Ave",
    "iso:country":"CA",
    "sg:address":"375 Mcarthur Ave",
    "sg:city":"Vanier",
    "sg:classifiers":[
        {
            "category":"Shopping",
            "subcategory":"Clothing, Apparel, & Fashions",
            "type":"Retail Goods"
        }
    ],
    "sg:phone":"+1 613 740 0400",
    "sg:postcode":"K1L 6N5",
    "sg:province":"ON",
    "sg:tags":[
        "uniform"
    ],
    "wof:name":"Uniform G",
    "wof:placetype":"venue"
},
  "geometry": {"coordinates":[-75.651093,45.432083],"type":"Point"}
}