{
  "type": "Feature",
  "properties": {
    "addr:full":"8059 Boul Saint-Michel Montreal QC H1Z 3C9",
    "addr:housenumber":"8059",
    "addr:postcode":"h1z 3c9",
    "addr:street":"Boul Saint-Michel",
    "iso:country":"CA",
    "sg:address":"8059 Boul Saint-Michel",
    "sg:city":"Montreal",
    "sg:classifiers":[
        {
            "category":"Organizations",
            "subcategory":"Professional Association",
            "type":"Services"
        }
    ],
    "sg:phone":"+1 514 729 6666",
    "sg:postcode":"H1Z 3C9",
    "sg:province":"QC",
    "wof:name":"Federation Des Associations",
    "wof:placetype":"venue"
},
  "geometry": {"coordinates":[-73.6087646484,45.563659668],"type":"Point"}
}