{
  "type": "Feature",
  "properties": {
    "addr:full":"152 Boul Begin Sainte-Claire QC G0R 2V0",
    "addr:housenumber":"152",
    "addr:postcode":"g0r 2v0",
    "addr:street":"Boul Begin",
    "iso:country":"CA",
    "sg:address":"152 Boul Begin",
    "sg:city":"Sainte-Claire",
    "sg:classifiers":[
        {
            "category":"Restaurant",
            "type":"Food & Drink"
        }
    ],
    "sg:phone":"+1 418 883 2258",
    "sg:postcode":"G0R 2V0",
    "sg:province":"QC",
    "sg:tags":[
        "motel",
        "hotel"
    ],
    "wof:name":"Motel Au Petit Rocher",
    "wof:placetype":"venue"
},
  "geometry": {"coordinates":[-70.860283,46.600109],"type":"Point"}
}