{
  "type": "Feature",
  "properties": {
    "iso:country":"CA",
    "sg:address":"231 Highway 32",
    "sg:city":"Gananoque",
    "sg:classifiers":[
        {
            "category":"Retail",
            "subcategory":"Veterinary Services",
            "type":"Services"
        }
    ],
    "sg:phone":"+1 613 382 3429",
    "sg:postcode":"K7G 2V3",
    "sg:province":"ON",
    "sg:tags":[
        "veterinarian"
    ],
    "wof:name":"Gananoque Veterinary Clinic",
    "wof:placetype":"venue"
},
  "geometry": {"coordinates":[-76.1642608643,44.3284797668],"type":"Point"}
}