{
  "type": "Feature",
  "properties": {
    "addr:full":"3480 Boul Industriel Laval QC H7L 4R9",
    "addr:housenumber":"3480",
    "addr:postcode":"h7l 4r9",
    "addr:street":"Boul Industriel",
    "iso:country":"CA",
    "sg:address":"3480 Boul Industriel",
    "sg:city":"Laval",
    "sg:classifiers":[
        {
            "category":"Shopping",
            "subcategory":"Shoes",
            "type":"Retail Goods"
        }
    ],
    "sg:phone":"+1 450 662 6055",
    "sg:postcode":"H7L 4R9",
    "sg:province":"QC",
    "wof:name":"Brown Shoe CO of Canada Ltd",
    "wof:placetype":"venue"
},
  "geometry": {"coordinates":[-73.746696,45.593937],"type":"Point"}
}