{
  "type": "Feature",
  "properties": {
    "iso:country":"CA",
    "sg:address":"5876 Tecumseh Rd E",
    "sg:city":"Windsor",
    "sg:classifiers":[
        {
            "category":"Professional",
            "subcategory":"Engineering",
            "type":"Services"
        }
    ],
    "sg:phone":"+1 519 974 1500",
    "sg:postcode":"N8T 1E2",
    "sg:province":"ON",
    "sg:tags":[
        "designer",
        "engineer"
    ],
    "wof:name":"Afridi Design Inc",
    "wof:placetype":"venue"
},
  "geometry": {"coordinates":[-82.95487213129999,42.3099899292],"type":"Point"}
}