{
  "type": "Feature",
  "properties": {
    "addr:full":"3070 Ch Capelton North Hatley QC J0B 2C0",
    "addr:postcode":"3070;j0b 2c0",
    "addr:street":"Ch Capelton",
    "iso:country":"CA",
    "sg:address":"3070 Ch Capelton",
    "sg:city":"North Hatley",
    "sg:classifiers":[
        {
            "category":"Home & Garden",
            "subcategory":"Hardware",
            "type":"Retail Goods"
        }
    ],
    "sg:phone":"+1 819 842 2394",
    "sg:postcode":"J0B 2C0",
    "sg:province":"QC",
    "wof:name":"Quincaillerie North Hatley Inc",
    "wof:placetype":"venue"
},
  "geometry": {"coordinates":[-71.9732589722,45.2787971497],"type":"Point"}
}