{
  "type": "Feature",
  "properties": {
    "addr:full":"20 Prince Edward St Saint John NB E2L 3S2",
    "addr:housenumber":"20",
    "addr:postcode":"nb e2l 3s2",
    "addr:street":"Prince Edward St",
    "iso:country":"CA",
    "sg:address":"20 Prince Edward St",
    "sg:city":"Saint John",
    "sg:classifiers":[
        {
            "category":"Food & Beverages",
            "subcategory":"Liquor & Beverages",
            "type":"Retail Goods"
        }
    ],
    "sg:phone":"+1 506 693 4128",
    "sg:postcode":"E2L 3S2",
    "sg:province":"NB",
    "sg:tags":[
        "store"
    ],
    "wof:name":"New Brunswick Liquor Corp",
    "wof:placetype":"venue"
},
  "geometry": {"coordinates":[-66.0559921265,45.275680542],"type":"Point"}
}