{
  "type": "Feature",
  "properties": {
    "addr:full":"1390 Prince of Wales Dr #307 Ottawa ON K2C 3N6",
    "addr:housenumber":"1390",
    "addr:postcode":"k2c 3n6",
    "addr:street":"Prince Of Wales Dr # 307",
    "iso:country":"CA",
    "sg:address":"1390 Prince of Wales Dr #307",
    "sg:city":"Ottawa",
    "sg:classifiers":[
        {
            "category":"Health Services",
            "subcategory":"Doctor",
            "type":"Services"
        }
    ],
    "sg:phone":"+1 613 225 8777",
    "sg:postcode":"K2C 3N6",
    "sg:province":"ON",
    "sg:tags":[
        "physician",
        "surgeon"
    ],
    "wof:name":"Reiser, Glenda L MD",
    "wof:placetype":"venue"
},
  "geometry": {"coordinates":[-75.70265999999999,45.369843],"type":"Point"}
}