{
  "type": "Feature",
  "properties": {
    "addr:full":"190 Wortley Rd London ON N6C 4Y7",
    "addr:housenumber":"190",
    "addr:postcode":"n6c 4y7",
    "addr:street":"Wortley Rd",
    "iso:country":"CA",
    "sg:address":"190 Wortley Rd",
    "sg:city":"London",
    "sg:classifiers":[
        {
            "category":"Social Services",
            "type":"Services"
        }
    ],
    "sg:phone":"+1 519 645 7393",
    "sg:postcode":"N6C 4Y7",
    "sg:province":"ON",
    "sg:tags":[
        "counselor",
        "marriage",
        "family"
    ],
    "wof:name":"Personal Rehabilitation Svc",
    "wof:placetype":"venue"
},
  "geometry": {"coordinates":[-81.2521972656,42.9714622498],"type":"Point"}
}