{
  "type": "Feature",
  "properties": {
    "addr:full":"154 Rue Dunkin Drummondville QC J2B 5V1",
    "addr:housenumber":"154",
    "addr:postcode":"j2b 5v1",
    "addr:street":"Rue Dunkin",
    "iso:country":"CA",
    "sg:address":"154 Rue Dunkin",
    "sg:city":"Drummondville",
    "sg:classifiers":[
        {
            "category":"Organizations",
            "subcategory":"Professional Association",
            "type":"Services"
        }
    ],
    "sg:phone":"+1 819 472 3351",
    "sg:postcode":"J2B 5V1",
    "sg:province":"QC",
    "wof:name":"Partance Bureau D'Emploi Pour",
    "wof:placetype":"venue"
},
  "geometry": {"coordinates":[-72.4782028198,45.8773880005],"type":"Point"}
}