{
  "type": "Feature",
  "properties": {
    "addr:full":"836 Rue Valois Longueuil QC J4J 1V3",
    "addr:housenumber":"836",
    "addr:postcode":"j4j 1v3",
    "addr:street":"Rue Valois",
    "iso:country":"CA",
    "sg:address":"836 Rue Valois",
    "sg:city":"Longueuil",
    "sg:classifiers":[
        {
            "category":"Manufacturing",
            "subcategory":"Buildings",
            "type":"Manufacturing & Wholesale Goods"
        }
    ],
    "sg:phone":"+1 514 598 1663",
    "sg:postcode":"J4J 1V3",
    "sg:province":"QC",
    "sg:tags":[
        "prefab",
        "roof",
        "structure"
    ],
    "wof:name":"Fermco Limitee",
    "wof:placetype":"venue"
},
  "geometry": {"coordinates":[-73.47917200000001,45.539307],"type":"Point"}
}