{
  "type": "Feature",
  "properties": {
    "addr:full":"2612 Turner St Victoria BC V8T 4T9",
    "addr:housenumber":"2612",
    "addr:postcode":"v8t 4t9",
    "addr:street":"Turner St",
    "iso:country":"CA",
    "sg:address":"2612 Turner St",
    "sg:city":"Victoria",
    "sg:classifiers":[
        {
            "category":"Wholesale",
            "subcategory":"Machinery & Supplies",
            "type":"Manufacturing & Wholesale Goods"
        }
    ],
    "sg:phone":"+1 250 386 2136",
    "sg:postcode":"V8T 4T9",
    "sg:province":"BC",
    "sg:tags":[
        "bearing"
    ],
    "wof:name":"Goodall Rubber",
    "wof:placetype":"venue"
},
  "geometry": {"coordinates":[-123.37508392300001,48.4359550476],"type":"Point"}
}