{
  "type": "Feature",
  "properties": {
    "addr:full":"Brackendale BC V0N 1H0",
    "addr:postcode":"v0n 1h0",
    "iso:country":"CA",
    "sg:city":"Brackendale",
    "sg:classifiers":[
        {
            "category":"Recreation",
            "type":"Entertainment"
        }
    ],
    "sg:phone":"+1 604 898 3678",
    "sg:postcode":"V0N 1H0",
    "sg:province":"BC",
    "sg:tags":[
        "provincial",
        "parks",
        "government"
    ],
    "wof:name":"British Columbia Parks",
    "wof:placetype":"venue"
},
  "geometry": {"coordinates":[-123.139481,49.76593],"type":"Point"}
}