{
  "type": "Feature",
  "properties": {
    "addr:full":"66 Main St S Carman MB R0G 0J0",
    "addr:housenumber":"66",
    "addr:postcode":"r0g 0j0",
    "addr:street":"Main St S",
    "iso:country":"CA",
    "sg:address":"66 Main St S",
    "sg:city":"Carman",
    "sg:classifiers":[
        {
            "category":"Shopping",
            "subcategory":"Pharmacy",
            "type":"Retail Goods"
        }
    ],
    "sg:phone":"+1 204 745 2781",
    "sg:postcode":"R0G 0J0",
    "sg:province":"MB",
    "wof:name":"Stevens Drug Store Ltd",
    "wof:placetype":"venue"
},
  "geometry": {"coordinates":[-98.001823,49.507515],"type":"Point"}
}