{
  "type": "Feature",
  "properties": {
    "iso:country":"CA",
    "sg:address":"2069 Rte Marie-Victorin",
    "sg:city":"Varennes",
    "sg:classifiers":[
        {
            "category":"Shopping",
            "subcategory":"Used Merchandise",
            "type":"Retail Goods"
        }
    ],
    "sg:phone":"+1 450 929 3557",
    "sg:postcode":"J3X 1R3",
    "sg:province":"QC",
    "sg:tags":[
        "clothing"
    ],
    "wof:name":"Frip-Allure",
    "wof:placetype":"venue"
},
  "geometry": {"coordinates":[-73.437485,45.679138],"type":"Point"}
}