{
  "type": "Feature",
  "properties": {
    "addr:full":"485 Sackville Dr Lower Sackville NS B4C 2S1",
    "addr:housenumber":"485",
    "addr:postcode":"b4c 2s1",
    "addr:street":"Sackville Dr",
    "iso:country":"CA",
    "sg:address":"485 Sackville Dr",
    "sg:city":"Lower Sackville",
    "sg:classifiers":[
        {
            "category":"Retail",
            "subcategory":"Veterinary Services",
            "type":"Services"
        }
    ],
    "sg:phone":"+1 902 865 6400",
    "sg:postcode":"B4C 2S1",
    "sg:province":"NS",
    "sg:tags":[
        "veterinarian"
    ],
    "wof:name":"Sackville Animal Hospital",
    "wof:placetype":"venue"
},
  "geometry": {"coordinates":[-63.680531,44.765747],"type":"Point"}
}