{
  "type": "Feature",
  "properties": {
    "addr:full":"4885 Rue Jarry E Saint-Leonard QC H1R 1Y1",
    "addr:housenumber":"4885",
    "addr:postcode":"h1r 1y1",
    "addr:street":"Rue Jarry E",
    "iso:country":"CA",
    "sg:address":"4885 Rue Jarry E",
    "sg:city":"Saint-Leonard",
    "sg:classifiers":[
        {
            "category":"Home & Garden",
            "subcategory":"Building Materials",
            "type":"Retail Goods"
        }
    ],
    "sg:phone":"+1 514 321 7550",
    "sg:postcode":"H1R 1Y1",
    "sg:province":"QC",
    "sg:tags":[
        "paint"
    ],
    "wof:name":"Peinture Micca Jarry",
    "wof:placetype":"venue"
},
  "geometry": {"coordinates":[-73.595947,45.579353],"type":"Point"}
}