{
  "type": "Feature",
  "properties": {
    "addr:full":"Calgary AB T2C 2H9",
    "addr:postcode":"t2c 2h9",
    "iso:country":"CA",
    "sg:city":"Calgary",
    "sg:classifiers":[
        {
            "category":"Building & Trades",
            "subcategory":"Plumbing",
            "type":"Services"
        }
    ],
    "sg:phone":"+1 403 279 1914",
    "sg:postcode":"T2C 2H9",
    "sg:province":"AB",
    "sg:tags":[
        "sheet",
        "work",
        "metal",
        "contractor"
    ],
    "wof:name":"Keller Industries Ltd",
    "wof:placetype":"venue"
},
  "geometry": {"coordinates":[-113.97919464100001,50.9879875183],"type":"Point"}
}