{
  "type": "Feature",
  "properties": {
    "iso:country":"CA",
    "sg:address":"2346 Rte Marie-Victorin",
    "sg:city":"Saint-Nicolas",
    "sg:classifiers":[
        {
            "category":"Wholesale",
            "subcategory":"Plants",
            "type":"Manufacturing & Wholesale Goods"
        }
    ],
    "sg:phone":"+1 418 831 9134",
    "sg:postcode":"G7A 4H7",
    "sg:province":"QC",
    "sg:tags":[
        "florist"
    ],
    "wof:name":"Serres Tlb Inc",
    "wof:placetype":"venue"
},
  "geometry": {"coordinates":[-71.47872924799999,46.6873893738],"type":"Point"}
}