{
  "type": "Feature",
  "properties": {
    "addr:full":"Kanata ON K2K 2X3",
    "addr:postcode":"k2k 2x3",
    "iso:country":"CA",
    "sg:city":"Kanata",
    "sg:classifiers":[
        {
            "category":"Personal",
            "subcategory":"Beauty Salon",
            "type":"Services"
        }
    ],
    "sg:phone":"+1 613 599 5110",
    "sg:postcode":"K2K 2X3",
    "sg:province":"ON",
    "wof:name":"Salon",
    "wof:placetype":"venue"
},
  "geometry": {"coordinates":[-75.9195861816,45.3477210999],"type":"Point"}
}