{
  "type": "Feature",
  "properties": {
    "addr:full":"513 Mount Pleasant Rd Toronto ON M4S 2M4",
    "addr:housenumber":"513",
    "addr:postcode":"m4s 2m4",
    "addr:street":"Mount Pleasant Rd",
    "iso:country":"CA",
    "sg:address":"513 Mount Pleasant Rd",
    "sg:city":"Toronto",
    "sg:classifiers":[
        {
            "category":"Restaurant",
            "type":"Food & Drink"
        }
    ],
    "sg:phone":"+1 416 481 6101",
    "sg:postcode":"M4S 2M4",
    "sg:province":"ON",
    "wof:name":"South China",
    "wof:placetype":"venue"
},
  "geometry": {"coordinates":[-79.387383,43.701893],"type":"Point"}
}