{
  "type": "Feature",
  "properties": {
    "addr:full":"19 Rue Perreault E Rouyn-Noranda QC J9X 3C1",
    "addr:housenumber":"19",
    "addr:postcode":"j9x 3c1",
    "addr:street":"Rue Perreault E",
    "iso:country":"CA",
    "sg:address":"19 Rue Perreault E",
    "sg:city":"Rouyn-Noranda",
    "sg:classifiers":[
        {
            "category":"Shopping",
            "subcategory":"Clothing, Apparel, & Fashions",
            "type":"Retail Goods"
        }
    ],
    "sg:phone":"+1 819 762 4735",
    "sg:postcode":"J9X 3C1",
    "sg:province":"QC",
    "sg:tags":[
        "shop",
        "bridal"
    ],
    "wof:name":"Josee-Nat Inc",
    "wof:placetype":"venue"
},
  "geometry": {"coordinates":[-79.0193099976,48.238368988],"type":"Point"}
}