{
  "type": "Feature",
  "properties": {
    "addr:full":"220 Boul Cartier Beloeil QC J3G 3R5",
    "addr:housenumber":"220",
    "addr:postcode":"j3g 3r5",
    "addr:street":"Boul Cartier",
    "iso:country":"CA",
    "sg:address":"220 Boul Cartier",
    "sg:city":"Beloeil",
    "sg:classifiers":[
        {
            "category":"Building & Trades",
            "subcategory":"Construction",
            "type":"Services"
        }
    ],
    "sg:phone":"+1 450 467 0572",
    "sg:postcode":"J3G 3R5",
    "sg:province":"QC",
    "sg:tags":[
        "repairing",
        "remodeling",
        "aluminum",
        "contractor"
    ],
    "wof:name":"Jmr Aluminium Enr",
    "wof:placetype":"venue"
},
  "geometry": {"coordinates":[-73.2152328491,45.5539970398],"type":"Point"}
}