{
  "type": "Feature",
  "properties": {
    "addr:full":"7835 Champlain Cres Vancouver BC V5S 4J6",
    "addr:housenumber":"7835",
    "addr:postcode":"v5s 4j6",
    "addr:street":"Champlain Cres",
    "iso:country":"CA",
    "sg:address":"7835 Champlain Cres",
    "sg:city":"Vancouver",
    "sg:classifiers":[
        {
            "category":"Education",
            "subcategory":"School",
            "type":"Public Place"
        }
    ],
    "sg:phone":"+1 604 713 4880",
    "sg:postcode":"V5S 4J6",
    "sg:province":"BC",
    "wof:name":"Champlain Heights Annex School",
    "wof:placetype":"venue"
},
  "geometry": {"coordinates":[-123.030052185,49.2134857178],"type":"Point"}
}