{
  "type": "Feature",
  "properties": {
    "iso:country":"CA",
    "sg:address":"1275 2nd Ave E",
    "sg:city":"Vancouver",
    "sg:classifiers":[
        {
            "category":"Building & Trades",
            "subcategory":"Landscaping Services",
            "type":"Services"
        }
    ],
    "sg:phone":"+1 604 255 6500",
    "sg:postcode":"V6A 3T9",
    "sg:province":"BC",
    "sg:tags":[
        "landscape",
        "contractor"
    ],
    "wof:name":"Meridan Landscaping",
    "wof:placetype":"venue"
},
  "geometry": {"coordinates":[-123.077774,49.268883],"type":"Point"}
}