{
  "type": "Feature",
  "properties": {
    "addr:full":"74 Firth St Inuvik NT X0E 0T0",
    "addr:housenumber":"74",
    "addr:postcode":"x0e 0t0",
    "addr:street":"Firth St",
    "iso:country":"CA",
    "sg:address":"74 Firth St",
    "sg:city":"Inuvik",
    "sg:classifiers":[
        {
            "category":"Utilities",
            "subcategory":"Cable",
            "type":"Services"
        }
    ],
    "sg:phone":"+1 867 777 2111",
    "sg:postcode":"X0E 0T0",
    "sg:province":"NT",
    "sg:tags":[
        "television"
    ],
    "wof:name":"New North Networks Ltd",
    "wof:placetype":"venue"
},
  "geometry": {"coordinates":[-133.734939575,68.3610534668],"type":"Point"}
}