{
  "type": "Feature",
  "properties": {
    "addr:full":"10001 Grenville St St Peters NS B0E 3B0",
    "addr:housenumber":"10001",
    "addr:postcode":"b0e 3b0",
    "addr:street":"Grenville St",
    "iso:country":"CA",
    "sg:address":"10001 Grenville St",
    "sg:city":"St Peters",
    "sg:classifiers":[
        {
            "category":"Shopping",
            "subcategory":"Catalog Store",
            "type":"Retail Goods"
        }
    ],
    "sg:phone":"+1 902 535 3010",
    "sg:postcode":"B0E 3B0",
    "sg:province":"NS",
    "sg:tags":[
        "mail",
        "order",
        "internet"
    ],
    "wof:name":"Sears Canada Inc",
    "wof:placetype":"venue"
},
  "geometry": {"coordinates":[-60.873768,45.656635],"type":"Point"}
}