{
  "type": "Feature",
  "properties": {
    "addr:full":"1458 London Rd Sarnia ON N7S 1P7",
    "addr:housenumber":"1458",
    "addr:postcode":"n7s 1p7",
    "addr:street":"London Rd",
    "iso:country":"CA",
    "sg:address":"1458 London Rd",
    "sg:city":"Sarnia",
    "sg:classifiers":[
        {
            "category":"Autos & Motor Vehicles",
            "subcategory":"Boat Sales",
            "type":"Retail Goods"
        }
    ],
    "sg:phone":"+1 519 542 2771",
    "sg:postcode":"N7S 1P7",
    "sg:province":"ON",
    "sg:tags":[
        "equipment",
        "marine",
        "supply"
    ],
    "wof:name":"Abbott Boats Inc",
    "wof:placetype":"venue"
},
  "geometry": {"coordinates":[-82.34918999999999,42.980782],"type":"Point"}
}