{
  "type": "Feature",
  "properties": {
    "addr:full":"1660 Boul Industriel Farnham QC J2N 2X8",
    "addr:housenumber":"1660",
    "addr:postcode":"j2n 2x8",
    "addr:street":"Boul Industriel",
    "iso:country":"CA",
    "sg:address":"1660 Boul Industriel",
    "sg:city":"Farnham",
    "sg:classifiers":[
        {
            "category":"Freight",
            "type":"Transportation"
        }
    ],
    "sg:phone":"+1 450 293 3909",
    "sg:postcode":"J2N 2X8",
    "sg:province":"QC",
    "sg:tags":[
        "trucking"
    ],
    "wof:name":"Distribution Marcel Dion Inc",
    "wof:placetype":"venue"
},
  "geometry": {"coordinates":[-72.96202850340001,45.292930603],"type":"Point"}
}