{
  "type": "Feature",
  "properties": {
    "iso:country":"CA",
    "sg:city":"Vancouver",
    "sg:classifiers":[
        {
            "category":"Health Services",
            "subcategory":"Doctor",
            "type":"Services"
        }
    ],
    "sg:phone":"+1 604 739 4373",
    "sg:postcode":"V6K 2E4",
    "sg:province":"BC",
    "sg:tags":[
        "physician",
        "surgeon"
    ],
    "wof:name":"Baff, Mario F MD",
    "wof:placetype":"venue"
},
  "geometry": {"coordinates":[-123.156311,49.264042],"type":"Point"}
}