{
  "type": "Feature",
  "properties": {
    "addr:full":"Pownal PE C0A 1Z0",
    "addr:postcode":"c0a 1z0",
    "iso:country":"CA",
    "sg:city":"Pownal",
    "sg:classifiers":[
        {
            "category":"Building & Trades",
            "subcategory":"Plumbing",
            "type":"Services"
        }
    ],
    "sg:phone":"+1 902 651 2510",
    "sg:postcode":"C0A 1Z0",
    "sg:province":"PE",
    "sg:tags":[
        "tank",
        "septic"
    ],
    "wof:name":"Duffy Backhoeing & Trucking",
    "wof:placetype":"venue"
},
  "geometry": {"coordinates":[-62.995121,46.196602],"type":"Point"}
}