{
  "type": "Feature",
  "properties": {
    "addr:full":"1190 Michener Rd Sarnia ON N7S 4B1",
    "addr:housenumber":"1190",
    "addr:postcode":"n7s 4b1",
    "addr:street":"Michener Rd",
    "iso:country":"CA",
    "sg:address":"1190 Michener Rd",
    "sg:city":"Sarnia",
    "sg:classifiers":[
        {
            "category":"Professional",
            "subcategory":"Management & Consulting",
            "type":"Services"
        }
    ],
    "sg:phone":"+1 519 332 0044",
    "sg:postcode":"N7S 4B1",
    "sg:province":"ON",
    "sg:tags":[
        "supply",
        "equipment",
        "industrial",
        "safety",
        "consultant"
    ],
    "wof:name":"Crs Technologies Inc",
    "wof:placetype":"venue"
},
  "geometry": {"coordinates":[-82.371346,42.958439],"type":"Point"}
}