{
  "type": "Feature",
  "properties": {
    "iso:country":"CA",
    "sg:address":"1110 Howe St",
    "sg:city":"Vancouver",
    "sg:classifiers":[
        {
            "category":"Travel",
            "subcategory":"Hotels & Motels",
            "type":"Entertainment"
        }
    ],
    "sg:phone":"+1 604 684 2151",
    "sg:postcode":"V6Z 1R2",
    "sg:province":"BC",
    "wof:name":"Holiday Inn Vancouver Downtown",
    "wof:placetype":"venue"
},
  "geometry": {"coordinates":[-123.12567901600001,49.2785263062],"type":"Point"}
}