{
  "type": "Feature",
  "properties": {
    "addr:full":"3700 Mcgillivray Blvd Winnipeg MB R3T 5S3",
    "addr:housenumber":"3700",
    "addr:postcode":"r3t 5s3",
    "addr:street":"Mcgillivray Blvd",
    "iso:country":"CA",
    "sg:address":"3700 Mcgillivray Blvd",
    "sg:city":"Winnipeg",
    "sg:classifiers":[
        {
            "category":"Wholesale",
            "subcategory":"Machinery & Supplies",
            "type":"Manufacturing & Wholesale Goods"
        }
    ],
    "sg:phone":"+1 204 231 2333",
    "sg:postcode":"R3T 5S3",
    "sg:province":"MB",
    "sg:tags":[
        "contractor"
    ],
    "wof:name":"Brandt Tractor Ltd",
    "wof:placetype":"venue"
},
  "geometry": {"coordinates":[-97.179397583,49.830619812],"type":"Point"}
}