{
  "type": "Feature",
  "properties": {
    "addr:full":"Levis QC G6V 6W8",
    "addr:postcode":"g6v 6w8",
    "iso:country":"CA",
    "sg:city":"Levis",
    "sg:classifiers":[
        {
            "category":"Personal",
            "subcategory":"Barber",
            "type":"Services"
        }
    ],
    "sg:phone":"+1 418 837 0033",
    "sg:postcode":"G6V 6W8",
    "sg:province":"QC",
    "wof:name":"Coiffure Normand Enr",
    "wof:placetype":"venue"
},
  "geometry": {"coordinates":[-71.17609400000001,46.794746],"type":"Point"}
}