{
  "type": "Feature",
  "properties": {
    "addr:full":"2 Commerce St Deer Lake NL A8A 1E6",
    "addr:housenumber":"2",
    "addr:postcode":"a8a 1e6",
    "addr:street":"Commerce St",
    "iso:country":"CA",
    "sg:address":"2 Commerce St",
    "sg:city":"Deer Lake",
    "sg:classifiers":[
        {
            "category":"Food & Beverages",
            "subcategory":"Groceries & Convenience Stores",
            "type":"Retail Goods"
        }
    ],
    "sg:phone":"+1 709 635 5408",
    "sg:postcode":"A8A 1E6",
    "sg:province":"NL",
    "sg:tags":[
        "grocer"
    ],
    "wof:name":"Deer Lake Foodland",
    "wof:placetype":"venue"
},
  "geometry": {"coordinates":[-57.431552887,49.1762084961],"type":"Point"}
}