{
  "type": "Feature",
  "properties": {
    "iso:country":"CA",
    "sg:city":"Calgary",
    "sg:classifiers":[
        {
            "category":"Health Services",
            "subcategory":"Doctor",
            "type":"Services"
        }
    ],
    "sg:phone":"+1 403 264 6565",
    "sg:postcode":"T2R 0H6",
    "sg:province":"AB",
    "sg:tags":[
        "dentist"
    ],
    "wof:name":"Beltline Dental Care",
    "wof:placetype":"venue"
},
  "geometry": {"coordinates":[-114.074935913,51.0418663025],"type":"Point"}
}