{
  "type": "Feature",
  "properties": {
    "iso:country":"CA",
    "sg:city":"Scarborough",
    "sg:classifiers":[
        {
            "category":"Retail",
            "subcategory":"Auto Repair",
            "type":"Services"
        }
    ],
    "sg:phone":"+1 416 285 8608",
    "sg:postcode":"M1L 4C2",
    "sg:province":"ON",
    "sg:tags":[
        "repairing",
        "automobile"
    ],
    "wof:name":"Promoters Auto Ctr",
    "wof:placetype":"venue"
},
  "geometry": {"coordinates":[-79.2857666016,43.7238464355],"type":"Point"}
}