{
  "type": "Feature",
  "properties": {
    "addr:full":"2615 Lancaster Rd Ottawa ON K1B 5N2",
    "addr:housenumber":"2615",
    "addr:postcode":"k1b 5n2",
    "addr:street":"Lancaster Rd",
    "iso:country":"CA",
    "sg:address":"2615 Lancaster Rd",
    "sg:city":"Ottawa",
    "sg:classifiers":[
        {
            "category":"Social Services",
            "subcategory":"Job Training",
            "type":"Services"
        }
    ],
    "sg:phone":"+1 613 564 2929",
    "sg:postcode":"K1B 5N2",
    "sg:province":"ON",
    "sg:tags":[
        "rehabilitation"
    ],
    "wof:name":"Creative Hands",
    "wof:placetype":"venue"
},
  "geometry": {"coordinates":[-75.611794,45.399433],"type":"Point"}
}