{
  "type": "Feature",
  "properties": {
    "addr:full":"158 Cushman Rd St Catharines ON L2M 6T6",
    "addr:housenumber":"158",
    "addr:postcode":"l2m 6t6",
    "addr:street":"Cushman Rd",
    "iso:country":"CA",
    "sg:address":"158 Cushman Rd",
    "sg:city":"St Catharines",
    "sg:classifiers":[
        {
            "category":"Retail",
            "subcategory":"Auto Repair",
            "type":"Services"
        }
    ],
    "sg:phone":"+1 905 684 7341",
    "sg:postcode":"L2M 6T6",
    "sg:province":"ON",
    "sg:tags":[
        "repairing",
        "automobile"
    ],
    "wof:name":"City Wide Auto Ctr",
    "wof:placetype":"venue"
},
  "geometry": {"coordinates":[-79.199654,43.178024],"type":"Point"}
}