{
  "type": "Feature",
  "properties": {
    "addr:full":"SE 14-6-1E Morris MB R0G 1K0",
    "addr:housenumber":"14-6-1e",
    "addr:postcode":"r0g 1k0",
    "addr:street":"Se",
    "iso:country":"CA",
    "sg:address":"SE 14-6-1E",
    "sg:city":"Morris",
    "sg:classifiers":[
        {
            "category":"Farming",
            "subcategory":"Farm",
            "type":"Manufacturing & Wholesale Goods"
        }
    ],
    "sg:phone":"+1 204 746 8457",
    "sg:postcode":"R0G 1K0",
    "sg:province":"MB",
    "wof:name":"Southernwood Farm Inc",
    "wof:placetype":"venue"
},
  "geometry": {"coordinates":[-97.366043,49.354687],"type":"Point"}
}