{
  "type": "Feature",
  "properties": {
    "addr:full":"Woodbridge ON L4L 9L3",
    "addr:postcode":"l4l 9l3",
    "iso:country":"CA",
    "sg:city":"Woodbridge",
    "sg:classifiers":[
        {
            "category":"Restaurant",
            "type":"Food & Drink"
        }
    ],
    "sg:phone":"+1 905 851 5151",
    "sg:postcode":"L4L 9L3",
    "sg:province":"ON",
    "sg:tags":[
        "parlor",
        "ice",
        "cream"
    ],
    "wof:name":"Paloma Gelateria & Cafe",
    "wof:placetype":"venue"
},
  "geometry": {"coordinates":[-79.5572814941,43.7895202637],"type":"Point"}
}