{
  "type": "Feature",
  "properties": {
    "iso:country":"CA",
    "sg:address":"Main St",
    "sg:city":"Port Saunders",
    "sg:classifiers":[
        {
            "category":"Education",
            "subcategory":"School",
            "type":"Public Place"
        }
    ],
    "sg:phone":"+1 709 861 3625",
    "sg:postcode":"A0K 4H0",
    "sg:province":"NL",
    "wof:name":"Roncalli Central High",
    "wof:placetype":"venue"
},
  "geometry": {"coordinates":[-57.2128486633,50.6732444763],"type":"Point"}
}