{
  "type": "Feature",
  "properties": {
    "addr:full":"205 Rue Du Palmier Laval QC H7K 1B3",
    "addr:housenumber":"205",
    "addr:postcode":"qc h7k 1b3",
    "addr:street":"Rue Du Palmier",
    "iso:country":"CA",
    "sg:address":"205 Rue Du Palmier",
    "sg:city":"Laval",
    "sg:classifiers":[
        {
            "category":"Organizations",
            "subcategory":"Religious Organization",
            "type":"Services"
        }
    ],
    "sg:phone":"+1 450 622 8677",
    "sg:postcode":"H7K 1B3",
    "sg:province":"QC",
    "sg:tags":[
        "church"
    ],
    "wof:name":"Eglise Ev Baptiste Lumiere",
    "wof:placetype":"venue"
},
  "geometry": {"coordinates":[-73.749184,45.62751],"type":"Point"}
}