{
  "type": "Feature",
  "properties": {
    "addr:full":"2271 Rue Guenette Saint-Laurent QC H4R 2E9",
    "addr:housenumber":"2271",
    "addr:postcode":"h4r 2e9",
    "addr:street":"Rue Guenette",
    "iso:country":"CA",
    "sg:address":"2271 Rue Guenette",
    "sg:city":"Saint-Laurent",
    "sg:classifiers":[
        {
            "category":"Wholesale",
            "subcategory":"Electrical",
            "type":"Manufacturing & Wholesale Goods"
        }
    ],
    "sg:phone":"+1 514 337 7540",
    "sg:postcode":"H4R 2E9",
    "sg:province":"QC",
    "sg:tags":[
        "equipment",
        "electronic",
        "supply"
    ],
    "wof:name":"Tech-Trek Ltd",
    "wof:placetype":"venue"
},
  "geometry": {"coordinates":[-73.7258071899,45.4986343384],"type":"Point"}
}