{
  "type": "Feature",
  "properties": {
    "addr:full":"Brampton ON L6W 3J3",
    "addr:postcode":"l6w 3j3",
    "iso:country":"CA",
    "sg:city":"Brampton",
    "sg:classifiers":[
        {
            "category":"Manufacturing",
            "subcategory":"Signs",
            "type":"Manufacturing & Wholesale Goods"
        }
    ],
    "sg:phone":"+1 905 453 1234",
    "sg:postcode":"L6W 3J3",
    "sg:province":"ON",
    "wof:name":"Instant Custom Signs",
    "wof:placetype":"venue"
},
  "geometry": {"coordinates":[-79.73455800000001,43.695721],"type":"Point"}
}