{
  "type": "Feature",
  "properties": {
    "addr:full":"45 Wingold Ave North York ON M6B 1P8",
    "addr:housenumber":"45",
    "addr:postcode":"m6b 1p8",
    "addr:street":"Wingold Ave",
    "iso:country":"CA",
    "sg:address":"45 Wingold Ave",
    "sg:city":"North York",
    "sg:classifiers":[
        {
            "category":"Building & Trades",
            "subcategory":"Construction",
            "type":"Services"
        }
    ],
    "sg:phone":"+1 416 785 5129",
    "sg:postcode":"M6B 1P8",
    "sg:province":"ON",
    "sg:tags":[
        "roofing",
        "contractor"
    ],
    "wof:name":"Avenue Road Roofing Ltd",
    "wof:placetype":"venue"
},
  "geometry": {"coordinates":[-79.45575700000001,43.702934],"type":"Point"}
}