{
  "type": "Feature",
  "properties": {
    "iso:country":"CA",
    "sg:address":"45 Wingold Ave",
    "sg:city":"North York",
    "sg:classifiers":[
        {
            "category":"Building & Trades",
            "subcategory":"Construction",
            "type":"Services"
        }
    ],
    "sg:phone":"+1 416 785 5129",
    "sg:postcode":"M6B 1P8",
    "sg:province":"ON",
    "sg:tags":[
        "roofing",
        "contractor"
    ],
    "wof:name":"Avenue Road Roofing Ltd",
    "wof:placetype":"venue"
},
  "geometry": {"coordinates":[-79.455757,43.702934],"type":"Point"}
}