{
  "type": "Feature",
  "properties": {
    "addr:full":"1165 Oxford St E London ON N5Y 3L7",
    "addr:housenumber":"1165",
    "addr:postcode":"n5y 3l7",
    "addr:street":"Oxford St E",
    "iso:country":"CA",
    "sg:address":"1165 Oxford St E",
    "sg:city":"London",
    "sg:classifiers":[
        {
            "category":"Recreation",
            "type":"Entertainment"
        }
    ],
    "sg:phone":"+1 519 659 2504",
    "sg:postcode":"N5Y 3L7",
    "sg:province":"ON",
    "sg:tags":[
        "martial",
        "arts",
        "instruction"
    ],
    "wof:name":"Bernardo Karate Academy",
    "wof:placetype":"venue"
},
  "geometry": {"coordinates":[-81.215248,43.00642],"type":"Point"}
}