{
  "type": "Feature",
  "properties": {
    "addr:full":"430 Columbia St E New Westminster BC V3L 3W9",
    "addr:housenumber":"430",
    "addr:postcode":"v3l 3w9",
    "addr:street":"Columbia St E",
    "iso:country":"CA",
    "sg:address":"430 Columbia St E",
    "sg:city":"New Westminster",
    "sg:classifiers":[
        {
            "category":"Retail",
            "subcategory":"Self-service Laundry",
            "type":"Services"
        }
    ],
    "sg:phone":"+1 604 525 3590",
    "sg:postcode":"V3L 3W9",
    "sg:province":"BC",
    "wof:name":"Happy Coin Laundry",
    "wof:placetype":"venue"
},
  "geometry": {"coordinates":[-122.89257000000001,49.229088],"type":"Point"}
}