{
  "type": "Feature",
  "properties": {
    "addr:full":"Edmonton AB T5C 3C1",
    "addr:postcode":"t5c 3c1",
    "iso:country":"CA",
    "sg:city":"Edmonton",
    "sg:classifiers":[
        {
            "category":"Professional",
            "subcategory":"Research",
            "type":"Services"
        }
    ],
    "sg:phone":"+1 780 475 1836",
    "sg:postcode":"T5C 3C1",
    "sg:province":"AB",
    "sg:tags":[
        "development",
        "laboratory"
    ],
    "wof:name":"Pro Consulting Scientific",
    "wof:placetype":"venue"
},
  "geometry": {"coordinates":[-113.445183,53.584335],"type":"Point"}
}