{
  "type": "Feature",
  "properties": {
    "addr:full":"Langley BC V3A 4E6",
    "addr:postcode":"v3a 4e6",
    "iso:country":"CA",
    "sg:city":"Langley",
    "sg:classifiers":[
        {
            "category":"Restaurant",
            "type":"Food & Drink"
        }
    ],
    "sg:phone":"+1 604 534 4802",
    "sg:postcode":"V3A 4E6",
    "sg:province":"BC",
    "sg:tags":[
        "shop",
        "coffee"
    ],
    "wof:name":"Castle Bay Coffee House",
    "wof:placetype":"venue"
},
  "geometry": {"coordinates":[-122.659958,49.105305],"type":"Point"}
}