{
  "type": "Feature",
  "properties": {
    "iso:country":"CA",
    "sg:city":"Parent",
    "sg:classifiers":[
        {
            "category":"Building & Trades",
            "subcategory":"Construction",
            "type":"Services"
        }
    ],
    "sg:phone":"+1 819 667 2644",
    "sg:postcode":"G0X 3P0",
    "sg:province":"QC",
    "sg:tags":[
        "repairing",
        "automobile",
        "road",
        "contractor"
    ],
    "wof:name":"Entreprises Gillbro Inc",
    "wof:placetype":"venue"
},
  "geometry": {"coordinates":[-74.6245880127,47.9204139709],"type":"Point"}
}