{
  "type": "Feature",
  "properties": {
    "addr:full":"11940 Highway 48 Stouffville ON L4A 7X5",
    "addr:housenumber":"11940",
    "addr:postcode":"l4a 7x5",
    "addr:street":"Highway 48",
    "iso:country":"CA",
    "sg:address":"11940 Highway 48",
    "sg:city":"Stouffville",
    "sg:classifiers":[
        {
            "category":"Autos & Motor Vehicles",
            "subcategory":"Auto Supplies",
            "type":"Retail Goods"
        }
    ],
    "sg:phone":"+1 905 642 6289",
    "sg:postcode":"L4A 7X5",
    "sg:province":"ON",
    "sg:tags":[
        "equipment",
        "racing",
        "car",
        "automobile"
    ],
    "wof:name":"Stefko Racing Svc",
    "wof:placetype":"venue"
},
  "geometry": {"coordinates":[-79.248024,43.971085],"type":"Point"}
}