{
  "type": "Feature",
  "properties": {
    "addr:full":"Montreal QC H2S 3L5",
    "addr:postcode":"h2s 3l5",
    "iso:country":"CA",
    "sg:city":"Montreal",
    "sg:classifiers":[
        {
            "category":"Manufacturing",
            "subcategory":"Apparel",
            "type":"Manufacturing & Wholesale Goods"
        }
    ],
    "sg:phone":"+1 514 274 3052",
    "sg:postcode":"H2S 3L5",
    "sg:province":"QC",
    "wof:name":"Creation Mai Enr",
    "wof:placetype":"venue"
},
  "geometry": {"coordinates":[-73.5981063843,45.5306968689],"type":"Point"}
}