{
  "type": "Feature",
  "properties": {
    "addr:full":"2592 Skaha Lake Rd Penticton BC V2A 6G1",
    "addr:housenumber":"2592",
    "addr:postcode":"v2a 6g1",
    "addr:street":"Skaha Lake Rd",
    "iso:country":"CA",
    "sg:address":"2592 Skaha Lake Rd",
    "sg:city":"Penticton",
    "sg:classifiers":[
        {
            "category":"Travel",
            "subcategory":"Hotels & Motels",
            "type":"Entertainment"
        }
    ],
    "sg:phone":"+1 250 493 2144",
    "sg:postcode":"V2A 6G1",
    "sg:province":"BC",
    "wof:name":"Granada Motor Inn",
    "wof:placetype":"venue"
},
  "geometry": {"coordinates":[-119.585121155,49.4675140381],"type":"Point"}
}