{
  "type": "Feature",
  "properties": {
    "addr:full":"2378 Bloor St W Toronto ON M6S 1P5",
    "addr:housenumber":"2378",
    "addr:postcode":"m6s 1p5",
    "addr:street":"Bloor St W",
    "iso:country":"CA",
    "sg:address":"2378 Bloor St W",
    "sg:city":"Toronto",
    "sg:classifiers":[
        {
            "category":"Shopping",
            "subcategory":"Clothing, Apparel, & Fashions",
            "type":"Retail Goods"
        }
    ],
    "sg:phone":"+1 416 766 4511",
    "sg:postcode":"M6S 1P5",
    "sg:province":"ON",
    "wof:name":"Danya Fashion Shoppe",
    "wof:placetype":"venue"
},
  "geometry": {"coordinates":[-79.482315,43.649952],"type":"Point"}
}