{
  "type": "Feature",
  "properties": {
    "addr:full":"192 Mary St Brantford ON N3S 3C2",
    "addr:housenumber":"192",
    "addr:postcode":"n3s 3c2",
    "addr:street":"Mary St",
    "iso:country":"CA",
    "sg:address":"192 Mary St",
    "sg:city":"Brantford",
    "sg:classifiers":[
        {
            "category":"Home & Garden",
            "subcategory":"Building Materials",
            "type":"Retail Goods"
        }
    ],
    "sg:phone":"+1 519 759 3521",
    "sg:postcode":"N3S 3C2",
    "sg:province":"ON",
    "sg:tags":[
        "windows"
    ],
    "wof:name":"Round Top Windows",
    "wof:placetype":"venue"
},
  "geometry": {"coordinates":[-80.2432479858,43.1366653442],"type":"Point"}
}