{
  "type": "Feature",
  "properties": {
    "addr:full":"3336 Dundas St W Toronto ON M6P 2A4",
    "addr:housenumber":"3336",
    "addr:postcode":"m6p 2a4",
    "addr:street":"Dundas St W",
    "iso:country":"CA",
    "sg:address":"3336 Dundas St W",
    "sg:city":"Toronto",
    "sg:classifiers":[
        {
            "category":"Organizations",
            "subcategory":"Professional Association",
            "type":"Services"
        }
    ],
    "sg:phone":"+1 416 763 5317",
    "sg:postcode":"M6P 2A4",
    "sg:province":"ON",
    "sg:tags":[
        "club"
    ],
    "wof:name":"Melita Soccer Club",
    "wof:placetype":"venue"
},
  "geometry": {"coordinates":[-79.48123200000001,43.66571],"type":"Point"}
}