{
  "type": "Feature",
  "properties": {
    "iso:country":"CA",
    "sg:address":"1530 Mcknight Blvd NE",
    "sg:city":"Calgary",
    "sg:classifiers":[
        {
            "category":"Retail",
            "subcategory":"Auto Repair",
            "type":"Services"
        }
    ],
    "sg:phone":"+1 403 275 2211",
    "sg:postcode":"T2E 5T5",
    "sg:province":"AB",
    "sg:tags":[
        "repairing",
        "automobile",
        "oil"
    ],
    "wof:name":"Airport Mohawk Svc",
    "wof:placetype":"venue"
},
  "geometry": {"coordinates":[-114.023200989,51.0930786133],"type":"Point"}
}