{
  "type": "Feature",
  "properties": {
    "addr:full":"250 Bayly St W # 19 Ajax ON L1S 3V4",
    "addr:housenumber":"250",
    "addr:postcode":"l1s 3v4",
    "addr:street":"Bayly St W # 19",
    "iso:country":"CA",
    "sg:address":"250 Bayly St W # 19",
    "sg:city":"Ajax",
    "sg:classifiers":[
        {
            "category":"Social Services",
            "subcategory":"Job Training",
            "type":"Services"
        }
    ],
    "sg:phone":"+1 905 426 8337",
    "sg:postcode":"L1S 3V4",
    "sg:province":"ON",
    "sg:tags":[
        "employment"
    ],
    "wof:name":"Northern Lights Vocational Svc",
    "wof:placetype":"venue"
},
  "geometry": {"coordinates":[-79.026695,43.842293],"type":"Point"}
}