{
  "type": "Feature",
  "properties": {
    "addr:full":"23 Horning Dr Hamilton ON L9C 6L2",
    "addr:housenumber":"23",
    "addr:postcode":"l9c 6l2",
    "addr:street":"Horning Dr",
    "iso:country":"CA",
    "sg:address":"23 Horning Dr",
    "sg:city":"Hamilton",
    "sg:classifiers":[
        {
            "category":"Professional",
            "subcategory":"Accounting & Tax Preparation",
            "type":"Services"
        }
    ],
    "sg:phone":"+1 905 388 9122",
    "sg:postcode":"L9C 6L2",
    "sg:province":"ON",
    "sg:tags":[
        "bookkeeping",
        "general"
    ],
    "wof:name":"A1 Bookkeeping Svc",
    "wof:placetype":"venue"
},
  "geometry": {"coordinates":[-79.9253311157,43.2293357849],"type":"Point"}
}