{
  "type": "Feature",
  "properties": {
    "addr:full":"Paynton SK S0M 2J0",
    "addr:postcode":"s0m 2j0",
    "addr:street":"Paynton",
    "iso:country":"CA",
    "sg:city":"Paynton",
    "sg:classifiers":[
        {
            "category":"Government",
            "subcategory":"Office",
            "type":"Public Place"
        }
    ],
    "sg:phone":"+1 306 895 4700",
    "sg:postcode":"S0M 2J0",
    "sg:province":"SK",
    "wof:name":"Canada Paynton Community Past",
    "wof:placetype":"venue"
},
  "geometry": {"coordinates":[-108.934708,53.016293],"type":"Point"}
}