{
  "type": "Feature",
  "properties": {
    "addr:full":"9745 St George St Annapolis Royal NS B0S 1A0",
    "addr:housenumber":"9745",
    "addr:postcode":"b0s 1a0",
    "addr:street":"St George St",
    "iso:country":"CA",
    "sg:address":"9745 St George St",
    "sg:city":"Annapolis Royal",
    "sg:classifiers":[
        {
            "category":"Health Services",
            "subcategory":"Health Practitioner",
            "type":"Services"
        }
    ],
    "sg:phone":"+1 902 532 1640",
    "sg:postcode":"B0S 1A0",
    "sg:province":"NS",
    "sg:tags":[
        "physiotherapist"
    ],
    "wof:name":"Cornwallis Physiotherapy",
    "wof:placetype":"venue"
},
  "geometry": {"coordinates":[-65.50054900000001,44.736813],"type":"Point"}
}