{
  "type": "Feature",
  "properties": {
    "addr:full":"66 St Paul St Moose Creek ON K0C 1W0",
    "addr:housenumber":"66",
    "addr:postcode":"k0c 1w0",
    "addr:street":"St Paul St",
    "iso:country":"CA",
    "sg:address":"66 St Paul St",
    "sg:city":"Moose Creek",
    "sg:classifiers":[
        {
            "category":"Health Services",
            "subcategory":"Doctor",
            "type":"Services"
        }
    ],
    "sg:phone":"+1 613 538 2710",
    "sg:postcode":"K0C 1W0",
    "sg:province":"ON",
    "sg:tags":[
        "clinic"
    ],
    "wof:name":"Moose Creek Medical Ctr",
    "wof:placetype":"venue"
},
  "geometry": {"coordinates":[-74.9701919556,45.2617721558],"type":"Point"}
}