{
  "type": "Feature",
  "properties": {
    "addr:full":"102 Rue Saint-Laurent Saint-Donat QC G0K 1L0",
    "addr:housenumber":"102",
    "addr:postcode":"g0k 1l0",
    "addr:street":"Rue Saint-Laurent",
    "iso:country":"CA",
    "sg:address":"102 Rue Saint-Laurent",
    "sg:city":"Saint-Donat",
    "sg:classifiers":[
        {
            "category":"Wholesale",
            "subcategory":"Seafood",
            "type":"Manufacturing & Wholesale Goods"
        }
    ],
    "sg:phone":"+1 418 739 3453",
    "sg:postcode":"G0K 1L0",
    "sg:province":"QC",
    "wof:name":"Fumoirs Mouski Inc",
    "wof:placetype":"venue"
},
  "geometry": {"coordinates":[-68.25704193120001,48.4974441528],"type":"Point"}
}