{
  "type": "Feature",
  "properties": {
    "addr:full":"121 Johnson St Kingston ON K7L 1X9",
    "addr:housenumber":"121",
    "addr:postcode":"k7l 1x9",
    "addr:street":"Johnson St",
    "iso:country":"CA",
    "sg:address":"121 Johnson St",
    "sg:city":"Kingston",
    "sg:classifiers":[
        {
            "category":"Restaurant",
            "type":"Food & Drink"
        }
    ],
    "sg:phone":"+1 613 546 6525",
    "sg:postcode":"K7L 1X9",
    "sg:province":"ON",
    "sg:tags":[
        "caterer"
    ],
    "wof:name":"Hellenic Banquet Hall",
    "wof:placetype":"venue"
},
  "geometry": {"coordinates":[-76.48434399999999,44.229816],"type":"Point"}
}