{
  "type": "Feature",
  "properties": {
    "addr:full":"76 Av DE Gaspe O Saint-Jean-Port-Joli QC G0R 3G0",
    "addr:postcode":"g0r 3g0",
    "addr:street":"76 Av De Gaspe O",
    "iso:country":"CA",
    "sg:address":"76 Av DE Gaspe O",
    "sg:city":"Saint-Jean-Port-Joli",
    "sg:classifiers":[
        {
            "category":"Travel",
            "subcategory":"Campground",
            "type":"Entertainment"
        }
    ],
    "sg:phone":"+1 418 598 3088",
    "sg:postcode":"G0R 3G0",
    "sg:province":"QC",
    "wof:name":"Au Bonnet Rouge Inc",
    "wof:placetype":"venue"
},
  "geometry": {"coordinates":[-70.26467100000001,47.217987],"type":"Point"}
}