{
  "type": "Feature",
  "properties": {
    "addr:full":"14 Tophmar Rd Kemptville ON K0G 1J0",
    "addr:housenumber":"14",
    "addr:postcode":"k0g 1j0",
    "addr:street":"Tophmar Rd",
    "iso:country":"CA",
    "sg:address":"14 Tophmar Rd",
    "sg:city":"Kemptville",
    "sg:classifiers":[
        {
            "category":"Social Services",
            "subcategory":"Child Care",
            "type":"Services"
        }
    ],
    "sg:phone":"+1 613 258 4710",
    "sg:postcode":"K0G 1J0",
    "sg:province":"ON",
    "wof:name":"Mtjb Childcare Ctr",
    "wof:placetype":"venue"
},
  "geometry": {"coordinates":[-75.64561500000001,45.015919],"type":"Point"}
}