{
  "type": "Feature",
  "properties": {
    "addr:full":"219 Baldwin Ave Cornwall ON K6H 4J3",
    "addr:housenumber":"219",
    "addr:postcode":"k6h 4j3",
    "addr:street":"Baldwin Ave",
    "iso:country":"CA",
    "sg:address":"219 Baldwin Ave",
    "sg:city":"Cornwall",
    "sg:classifiers":[
        {
            "category":"Health Services",
            "subcategory":"Doctor",
            "type":"Services"
        }
    ],
    "sg:phone":"+1 613 936 1505",
    "sg:postcode":"K6H 4J3",
    "sg:province":"ON",
    "sg:tags":[
        "physician",
        "surgeon"
    ],
    "wof:name":"Foley, Garrett MD",
    "wof:placetype":"venue"
},
  "geometry": {"coordinates":[-74.71574401860001,45.0222892761],"type":"Point"}
}