{
  "type": "Feature",
  "properties": {
    "addr:full":"706 Balmoral Ave Arcola SK S0C 0G0",
    "addr:housenumber":"706",
    "addr:postcode":"s0c 0g0",
    "addr:street":"Balmoral Ave",
    "iso:country":"CA",
    "sg:address":"706 Balmoral Ave",
    "sg:city":"Arcola",
    "sg:classifiers":[
        {
            "category":"Recreation",
            "type":"Entertainment"
        }
    ],
    "sg:phone":"+1 306 455 2565",
    "sg:postcode":"S0C 0G0",
    "sg:province":"SK",
    "sg:tags":[
        "hall",
        "auditorium"
    ],
    "wof:name":"Arcola Prairie Place",
    "wof:placetype":"venue"
},
  "geometry": {"coordinates":[-102.49179100000001,49.634789],"type":"Point"}
}