{
  "type": "Feature",
  "properties": {
    "addr:full":"42 Broadview Ave Keswick ON L4P 3C8",
    "addr:housenumber":"42",
    "addr:postcode":"l4p 3c8",
    "addr:street":"Broadview Ave",
    "iso:country":"CA",
    "sg:address":"42 Broadview Ave",
    "sg:city":"Keswick",
    "sg:classifiers":[
        {
            "category":"Home & Garden",
            "subcategory":"Building Materials",
            "type":"Retail Goods"
        }
    ],
    "sg:phone":"+1 905 853 2020",
    "sg:postcode":"L4P 3C8",
    "sg:province":"ON",
    "sg:tags":[
        "plate",
        "window",
        "mirror"
    ],
    "wof:name":"Shaw's Mirror CO",
    "wof:placetype":"venue"
},
  "geometry": {"coordinates":[-79.479477,44.252441],"type":"Point"}
}