{
  "type": "Feature",
  "properties": {
    "addr:full":"471 304th St # A Marysville BC V1A 3H4",
    "addr:housenumber":"471",
    "addr:postcode":"v1a 3h4",
    "addr:street":"304Th St # A",
    "iso:country":"CA",
    "sg:address":"471 304th St # A",
    "sg:city":"Marysville",
    "sg:classifiers":[
        {
            "category":"Cinema",
            "subcategory":"Movie Rental",
            "type":"Entertainment"
        }
    ],
    "sg:phone":"+1 250 427 7836",
    "sg:postcode":"V1A 3H4",
    "sg:province":"BC",
    "sg:tags":[
        "leasing",
        "video",
        "disc",
        "tape"
    ],
    "wof:name":"Bootleg Mountain Video",
    "wof:placetype":"venue"
},
  "geometry": {"coordinates":[-115.88213348399999,49.606174469],"type":"Point"}
}