{
  "type": "Feature",
  "properties": {
    "addr:full":"Vancouver BC V6G 2Z4",
    "addr:postcode":"v6g 2z4",
    "iso:country":"CA",
    "sg:city":"Vancouver",
    "sg:classifiers":[
        {
            "category":"Professional",
            "subcategory":"Business Services",
            "type":"Services"
        }
    ],
    "sg:phone":"+1 604 688 9655",
    "sg:postcode":"V6G 2Z4",
    "sg:province":"BC",
    "sg:tags":[
        "convention",
        "meeting",
        "facility"
    ],
    "wof:name":"Advance Cruise Specialists",
    "wof:placetype":"venue"
},
  "geometry": {"coordinates":[-123.129898071,49.2892227173],"type":"Point"}
}