{
  "type": "Feature",
  "properties": {
    "addr:full":"78 Main St S Newmarket ON L3Y 3Y6",
    "addr:housenumber":"78",
    "addr:postcode":"l3y 3y6",
    "addr:street":"Main St S",
    "iso:country":"CA",
    "sg:address":"78 Main St S",
    "sg:city":"Newmarket",
    "sg:classifiers":[
        {
            "category":"Manufacturing",
            "subcategory":"Printing",
            "type":"Manufacturing & Wholesale Goods"
        }
    ],
    "sg:phone":"+1 905 898 8585",
    "sg:postcode":"L3Y 3Y6",
    "sg:province":"ON",
    "sg:tags":[
        "publisher"
    ],
    "wof:name":"Ontario Snowmobiler Publishing",
    "wof:placetype":"venue"
},
  "geometry": {"coordinates":[-79.46003723139999,44.0565032959],"type":"Point"}
}