{
  "type": "Feature",
  "properties": {
    "addr:full":"127 Admiral St Admiral SK S0N 0B0",
    "addr:housenumber":"127",
    "addr:postcode":"s0n 0b0",
    "addr:street":"Admiral St",
    "iso:country":"CA",
    "sg:address":"127 Admiral St",
    "sg:city":"Admiral",
    "sg:classifiers":[
        {
            "category":"Banks & Credit Unions",
            "subcategory":"Bank",
            "type":"Services"
        }
    ],
    "sg:phone":"+1 306 297 6367",
    "sg:postcode":"S0N 0B0",
    "sg:province":"SK",
    "wof:name":"Shaunavon Credit Union",
    "wof:placetype":"venue"
},
  "geometry": {"coordinates":[-107.996346,49.713051],"type":"Point"}
}