{
  "type": "Feature",
  "properties": {
    "addr:full":"Cranbrook BC V1C 4M4",
    "addr:postcode":"v1c 4m4",
    "iso:country":"CA",
    "sg:city":"Cranbrook",
    "sg:classifiers":[
        {
            "category":"Government",
            "subcategory":"Office",
            "type":"Public Place"
        }
    ],
    "sg:phone":"+1 250 417 2250",
    "sg:postcode":"V1C 4M4",
    "sg:province":"BC",
    "wof:name":"Canada Members of Parliament",
    "wof:placetype":"venue"
},
  "geometry": {"coordinates":[-115.769203186,49.515422821],"type":"Point"}
}