{
  "type": "Feature",
  "properties": {
    "addr:full":"7701 Rue George Lasalle QC H8P 3J9",
    "addr:housenumber":"7701",
    "addr:postcode":"h8p 3j9",
    "addr:street":"Rue George",
    "iso:country":"CA",
    "sg:address":"7701 Rue George",
    "sg:city":"Lasalle",
    "sg:classifiers":[
        {
            "category":"Retail",
            "subcategory":"Auto Repair",
            "type":"Services"
        }
    ],
    "sg:phone":"+1 514 363 1511",
    "sg:postcode":"H8P 3J9",
    "sg:province":"QC",
    "sg:tags":[
        "repairing",
        "automobile",
        "painting"
    ],
    "wof:name":"Autolift Collision Inc",
    "wof:placetype":"venue"
},
  "geometry": {"coordinates":[-73.60498800000001,45.431179],"type":"Point"}
}