{
  "type": "Feature",
  "properties": {
    "addr:full":"521 Niagara St Welland ON L3C 1L7",
    "addr:housenumber":"521",
    "addr:postcode":"l3c 1l7",
    "addr:street":"Niagara St",
    "iso:country":"CA",
    "sg:address":"521 Niagara St",
    "sg:city":"Welland",
    "sg:classifiers":[
        {
            "category":"Personal",
            "subcategory":"Tanning Parlor",
            "type":"Services"
        }
    ],
    "sg:phone":"+1 905 732 3143",
    "sg:postcode":"L3C 1L7",
    "sg:province":"ON",
    "sg:tags":[
        "salon"
    ],
    "wof:name":"Electric Beach",
    "wof:placetype":"venue"
},
  "geometry": {"coordinates":[-79.253044,43.004784],"type":"Point"}
}