{
  "type": "Feature",
  "properties": {
    "addr:full":"5682 Hacienda Pl Chilliwack BC V2R 3K5",
    "addr:housenumber":"5682",
    "addr:postcode":"v2r 3k5",
    "addr:street":"Hacienda Pl",
    "iso:country":"CA",
    "sg:address":"5682 Hacienda Pl",
    "sg:city":"Chilliwack",
    "sg:classifiers":[
        {
            "category":"Professional",
            "subcategory":"Detective & Security Services",
            "type":"Services"
        }
    ],
    "sg:phone":"+1 604 858 7181",
    "sg:postcode":"V2R 3K5",
    "sg:province":"BC",
    "sg:tags":[
        "system"
    ],
    "wof:name":"Tri-Star Security",
    "wof:placetype":"venue"
},
  "geometry": {"coordinates":[-121.988213,49.105316],"type":"Point"}
}