{
  "type": "Feature",
  "properties": {
    "iso:country":"CA",
    "sg:address":"2686 Howard Ave",
    "sg:city":"Windsor",
    "sg:classifiers":[
        {
            "category":"Restaurant",
            "type":"Food & Drink"
        }
    ],
    "sg:phone":"+1 519 969 3845",
    "sg:postcode":"N8X 3X3",
    "sg:province":"ON",
    "sg:tags":[
        "parlor",
        "ice",
        "cream"
    ],
    "wof:name":"Dari DE Lite",
    "wof:placetype":"venue"
},
  "geometry": {"coordinates":[-83.011581,42.284557],"type":"Point"}
}