{
  "type": "Feature",
  "properties": {
    "addr:full":"700 Lone Pine Dr Kelowna BC V1P 1A1",
    "addr:housenumber":"700",
    "addr:postcode":"v1p 1a1",
    "addr:street":"Lone Pine Dr",
    "iso:country":"CA",
    "sg:address":"700 Lone Pine Dr",
    "sg:city":"Kelowna",
    "sg:classifiers":[
        {
            "category":"Building & Trades",
            "subcategory":"Construction",
            "type":"Services"
        }
    ],
    "sg:phone":"+1 250 862 6212",
    "sg:postcode":"V1P 1A1",
    "sg:province":"BC",
    "sg:tags":[
        "repairing",
        "remodeling",
        "contractor"
    ],
    "wof:name":"Maric Construction Ltd",
    "wof:placetype":"venue"
},
  "geometry": {"coordinates":[-119.36428832999999,49.880771637],"type":"Point"}
}