{
  "type": "Feature",
  "properties": {
    "addr:full":"5812 Terrace Rd NW Edmonton AB T6A 3Y8",
    "addr:housenumber":"5812",
    "addr:postcode":"t6a 3y8",
    "addr:street":"Terrace Rd Nw",
    "iso:country":"CA",
    "sg:address":"5812 Terrace Rd NW",
    "sg:city":"Edmonton",
    "sg:classifiers":[
        {
            "category":"Professional",
            "subcategory":"Accounting & Tax Preparation",
            "type":"Services"
        }
    ],
    "sg:phone":"+1 780 448 2188",
    "sg:postcode":"T6A 3Y8",
    "sg:province":"AB",
    "sg:tags":[
        "return",
        "filing"
    ],
    "wof:name":"H & R Block Canada Inc",
    "wof:placetype":"venue"
},
  "geometry": {"coordinates":[-113.425216675,53.5403709412],"type":"Point"}
}