{
  "type": "Feature",
  "properties": {
    "addr:full":"65 Rollingwood Cir London ON N6G 1R1",
    "addr:housenumber":"65",
    "addr:postcode":"n6g 1r1",
    "addr:street":"Rollingwood Cir",
    "iso:country":"CA",
    "sg:address":"65 Rollingwood Cir",
    "sg:city":"London",
    "sg:classifiers":[
        {
            "category":"Professional",
            "subcategory":"Accounting & Tax Preparation",
            "type":"Services"
        }
    ],
    "sg:phone":"+1 519 474 0367",
    "sg:postcode":"N6G 1R1",
    "sg:province":"ON",
    "sg:tags":[
        "bookkeeping",
        "general"
    ],
    "wof:name":"Due North Business Svc",
    "wof:placetype":"venue"
},
  "geometry": {"coordinates":[-81.2905578613,43.0020637512],"type":"Point"}
}