{
  "type": "Feature",
  "properties": {
    "addr:full":"4391 Gallant Ave North Vancouver BC V7G 1L1",
    "addr:housenumber":"4391",
    "addr:postcode":"v7g 1l1",
    "addr:street":"Gallant Ave",
    "iso:country":"CA",
    "sg:address":"4391 Gallant Ave",
    "sg:city":"North Vancouver",
    "sg:classifiers":[
        {
            "category":"Shopping",
            "subcategory":"Used Merchandise",
            "type":"Retail Goods"
        }
    ],
    "sg:phone":"+1 604 929 9882",
    "sg:postcode":"V7G 1L1",
    "sg:province":"BC",
    "sg:tags":[
        "apparel",
        "shop",
        "consignment"
    ],
    "wof:name":"Mystic Wardrobe",
    "wof:placetype":"venue"
},
  "geometry": {"coordinates":[-122.949478,49.326626],"type":"Point"}
}