{
  "type": "Feature",
  "properties": {
    "iso:country":"CA",
    "sg:address":"20204 110 Ave NW",
    "sg:city":"Edmonton",
    "sg:classifiers":[
        {
            "category":"Manufacturing",
            "subcategory":"Tools & Machinery",
            "type":"Manufacturing & Wholesale Goods"
        }
    ],
    "sg:phone":"+1 780 447 5052",
    "sg:postcode":"T5S 1X8",
    "sg:province":"AB",
    "sg:tags":[
        "incinerator"
    ],
    "wof:name":"Westland Incinerators CO Ltd",
    "wof:placetype":"venue"
},
  "geometry": {"coordinates":[-113.669021606,53.5568313599],"type":"Point"}
}