{
  "type": "Feature",
  "properties": {
    "iso:country":"CA",
    "sg:address":"540 Clyde Ave",
    "sg:city":"West Vancouver",
    "sg:classifiers":[
        {
            "category":"Travel",
            "subcategory":"Hotels & Motels",
            "type":"Entertainment"
        }
    ],
    "sg:phone":"+1 604 926 5511",
    "sg:postcode":"V7T 2J7",
    "sg:province":"BC",
    "wof:name":"Park Royal Hotel",
    "wof:placetype":"venue"
},
  "geometry": {"coordinates":[-123.132156372,49.3281326294],"type":"Point"}
}