{
  "type": "Feature",
  "properties": {
    "addr:full":"1100 Upper Prince St Sydney NS B1P 5P6",
    "addr:housenumber":"1100",
    "addr:postcode":"b1p 5p6",
    "addr:street":"Upper Prince St",
    "iso:country":"CA",
    "sg:address":"1100 Upper Prince St",
    "sg:city":"Sydney",
    "sg:classifiers":[
        {
            "category":"Wholesale",
            "subcategory":"Electrical",
            "type":"Manufacturing & Wholesale Goods"
        }
    ],
    "sg:phone":"+1 902 564 5504",
    "sg:postcode":"B1P 5P6",
    "sg:province":"NS",
    "sg:tags":[
        "equipment",
        "electric",
        "supply"
    ],
    "wof:name":"Harris & Roome Supply Ltd",
    "wof:placetype":"venue"
},
  "geometry": {"coordinates":[-60.1537895203,46.1417694092],"type":"Point"}
}