{
  "type": "Feature",
  "properties": {
    "addr:full":"Nepean ON K2E 8A5",
    "addr:postcode":"k2e 8a5",
    "iso:country":"CA",
    "sg:city":"Nepean",
    "sg:classifiers":[
        {
            "category":"Utilities",
            "subcategory":"Telephone",
            "type":"Services"
        }
    ],
    "sg:phone":"+1 613 723 2226",
    "sg:postcode":"K2E 8A5",
    "sg:province":"ON",
    "sg:tags":[
        "company"
    ],
    "wof:name":"Primus Canada",
    "wof:placetype":"venue"
},
  "geometry": {"coordinates":[-75.705254,45.330959],"type":"Point"}
}