{
  "type": "Feature",
  "properties": {
    "addr:full":"35 Percy St Colborne ON K0K 1S0",
    "addr:housenumber":"35",
    "addr:postcode":"k0k 1s0",
    "addr:street":"Percy St",
    "iso:country":"CA",
    "sg:address":"35 Percy St",
    "sg:city":"Colborne",
    "sg:classifiers":[
        {
            "category":"Building & Trades",
            "subcategory":"Cleaning & Sanitation",
            "type":"Services"
        }
    ],
    "sg:phone":"+1 905 355 1546",
    "sg:postcode":"K0K 1S0",
    "sg:province":"ON",
    "sg:tags":[
        "butler",
        "maid",
        "house"
    ],
    "wof:name":"Clean N' Sweep",
    "wof:placetype":"venue"
},
  "geometry": {"coordinates":[-77.890213,44.009338],"type":"Point"}
}