{
  "type": "Feature",
  "properties": {
    "iso:country":"CA",
    "sg:address":"20424 Trans Canada Hwy",
    "sg:city":"Crapaud",
    "sg:classifiers":[
        {
            "category":"Shopping",
            "subcategory":"Catalog Store",
            "type":"Retail Goods"
        }
    ],
    "sg:phone":"+1 902 658 2024",
    "sg:postcode":"C0A 1J0",
    "sg:province":"PE",
    "sg:tags":[
        "mail",
        "order",
        "internet"
    ],
    "wof:name":"Sears Canada Inc",
    "wof:placetype":"venue"
},
  "geometry": {"coordinates":[-63.4988594055,46.2360115051],"type":"Point"}
}