{
  "type": "Feature",
  "properties": {
    "addr:full":"695 9th Ave E Owen Sound ON N4K 3E4",
    "addr:housenumber":"695",
    "addr:postcode":"n4k 3e4",
    "addr:street":"9Th Ave E",
    "iso:country":"CA",
    "sg:address":"695 9th Ave E",
    "sg:city":"Owen Sound",
    "sg:classifiers":[
        {
            "category":"Health Services",
            "subcategory":"Doctor",
            "type":"Services"
        }
    ],
    "sg:phone":"+1 519 371 0905",
    "sg:postcode":"N4K 3E4",
    "sg:province":"ON",
    "sg:tags":[
        "dentist"
    ],
    "wof:name":"Klym, Alexander DDS",
    "wof:placetype":"venue"
},
  "geometry": {"coordinates":[-80.9267425537,44.5634880066],"type":"Point"}
}