{
  "type": "Feature",
  "properties": {
    "addr:full":"4506 46th Ave Fort Vermilion AB T0H 1N0",
    "addr:housenumber":"4506",
    "addr:postcode":"t0h 1n0",
    "addr:street":"46Th Ave Fort",
    "iso:country":"CA",
    "sg:address":"4506 46th Ave",
    "sg:city":"Fort Vermilion",
    "sg:classifiers":[
        {
            "category":"Health Services",
            "subcategory":"Hospital",
            "type":"Services"
        }
    ],
    "sg:phone":"+1 780 927 3761",
    "sg:postcode":"T0H 1N0",
    "sg:province":"AB",
    "wof:name":"St Theresa General Hospital",
    "wof:placetype":"venue"
},
  "geometry": {"coordinates":[-116.003707886,58.3868904114],"type":"Point"}
}