{
  "type": "Feature",
  "properties": {
    "addr:full":"151 Victoria Rd N Guelph ON N1E 5H4",
    "addr:housenumber":"151",
    "addr:postcode":"n1e 5h4",
    "addr:street":"Victoria Rd N",
    "iso:country":"CA",
    "sg:address":"151 Victoria Rd N",
    "sg:city":"Guelph",
    "sg:classifiers":[
        {
            "category":"Recreation",
            "type":"Entertainment"
        }
    ],
    "sg:phone":"+1 519 763 4523",
    "sg:postcode":"N1E 5H4",
    "sg:province":"ON",
    "sg:tags":[
        "club",
        "hockey"
    ],
    "wof:name":"Guelph Jr B Dominators",
    "wof:placetype":"venue"
},
  "geometry": {"coordinates":[-80.2401046753,43.5636901855],"type":"Point"}
}