{
  "type": "Feature",
  "properties": {
    "addr:full":"145 Simpson St Thunder Bay ON P7C 3H3",
    "addr:housenumber":"145",
    "addr:postcode":"p7c 3h3",
    "addr:street":"Simpson St",
    "iso:country":"CA",
    "sg:address":"145 Simpson St",
    "sg:city":"Thunder Bay",
    "sg:classifiers":[
        {
            "category":"Shopping",
            "subcategory":"Used Merchandise",
            "type":"Retail Goods"
        }
    ],
    "sg:phone":"+1 807 623 2312",
    "sg:postcode":"P7C 3H3",
    "sg:province":"ON",
    "sg:tags":[
        "appliance"
    ],
    "wof:name":"General Appliance Ctr",
    "wof:placetype":"venue"
},
  "geometry": {"coordinates":[-89.2421569824,48.3853416443],"type":"Point"}
}