{
  "type": "Feature",
  "properties": {
    "addr:full":"280 Rue Sauve O Montreal QC H3L 1Z4",
    "addr:housenumber":"280",
    "addr:postcode":"h3l 1z4",
    "addr:street":"Rue Sauve O",
    "iso:country":"CA",
    "sg:address":"280 Rue Sauve O",
    "sg:city":"Montreal",
    "sg:classifiers":[
        {
            "category":"Manufacturing",
            "subcategory":"Apparel",
            "type":"Manufacturing & Wholesale Goods"
        }
    ],
    "sg:phone":"+1 514 336 0301",
    "sg:postcode":"H3L 1Z4",
    "sg:province":"QC",
    "sg:tags":[
        "clothing"
    ],
    "wof:name":"Ianelle Designs Inc",
    "wof:placetype":"venue"
},
  "geometry": {"coordinates":[-73.657768,45.549129],"type":"Point"}
}