{
  "type": "Feature",
  "properties": {
    "iso:country":"CA",
    "sg:address":"791 Park Rd",
    "sg:city":"Zenon Park",
    "sg:classifiers":[
        {
            "category":"Retail",
            "subcategory":"Auto Repair",
            "type":"Services"
        }
    ],
    "sg:phone":"+1 306 767 2252",
    "sg:postcode":"S0E 1W0",
    "sg:province":"SK",
    "sg:tags":[
        "repairing",
        "automobile"
    ],
    "wof:name":"A & L Motors",
    "wof:placetype":"venue"
},
  "geometry": {"coordinates":[-103.758285523,53.0650596619],"type":"Point"}
}