{
  "type": "Feature",
  "properties": {
    "addr:full":"Rorketon MB R0L 1R0",
    "addr:postcode":"r0l 1r0",
    "iso:country":"CA",
    "sg:city":"Rorketon",
    "sg:classifiers":[
        {
            "category":"Food & Beverages",
            "subcategory":"Groceries & Convenience Stores",
            "type":"Retail Goods"
        }
    ],
    "sg:phone":"+1 204 732 2718",
    "sg:postcode":"R0L 1R0",
    "sg:province":"MB",
    "sg:tags":[
        "grocer"
    ],
    "wof:name":"P J's Corner",
    "wof:placetype":"venue"
},
  "geometry": {"coordinates":[-99.59604644780001,51.3908615112],"type":"Point"}
}