{
  "type": "Feature",
  "properties": {
    "iso:country":"CA",
    "sg:address":"400 Duke Point Hwy",
    "sg:city":"Nanaimo",
    "sg:classifiers":[
        {
            "category":"Ferry",
            "type":"Transportation"
        }
    ],
    "sg:phone":"+1 250 722 0181",
    "sg:postcode":"V9X 1H6",
    "sg:province":"BC",
    "wof:name":"British Columbia Ferry Corp",
    "wof:placetype":"venue"
},
  "geometry": {"coordinates":[-123.892028809,49.1596794128],"type":"Point"}
}