{
  "type": "Feature",
  "properties": {
    "addr:full":"4908 Rue Jean-Talon O Montreal QC H4P 1W9",
    "addr:housenumber":"4908",
    "addr:postcode":"h4p 1w9",
    "addr:street":"Rue Jean-Talon O",
    "iso:country":"CA",
    "sg:address":"4908 Rue Jean-Talon O",
    "sg:city":"Montreal",
    "sg:classifiers":[
        {
            "category":"Shopping",
            "subcategory":"Clothing, Apparel, & Fashions",
            "type":"Retail Goods"
        }
    ],
    "sg:phone":"+1 514 739 4065",
    "sg:postcode":"H4P 1W9",
    "sg:province":"QC",
    "sg:tags":[
        "item",
        "boutique"
    ],
    "wof:name":"Cohoe's Fashion",
    "wof:placetype":"venue"
},
  "geometry": {"coordinates":[-73.649055,45.49749],"type":"Point"}
}