{
  "type": "Feature",
  "properties": {
    "addr:full":"2451 Kingston Rd Scarborough ON M1N 1V4",
    "addr:housenumber":"2451",
    "addr:postcode":"m1n 1v4",
    "addr:street":"Kingston Rd",
    "iso:country":"CA",
    "sg:address":"2451 Kingston Rd",
    "sg:city":"Scarborough",
    "sg:classifiers":[
        {
            "category":"Health Services",
            "subcategory":"Doctor",
            "type":"Services"
        }
    ],
    "sg:phone":"+1 416 265 3368",
    "sg:postcode":"M1N 1V4",
    "sg:province":"ON",
    "sg:tags":[
        "dentist"
    ],
    "wof:name":"Cliffside Plaza Dental Office",
    "wof:placetype":"venue"
},
  "geometry": {"coordinates":[-79.24900054930001,43.7095222473],"type":"Point"}
}