{
  "type": "Feature",
  "properties": {
    "iso:country":"CA",
    "sg:address":"3319 Rue Jean-Talon E",
    "sg:city":"Montreal",
    "sg:classifiers":[
        {
            "category":"Shopping",
            "subcategory":"Used Merchandise",
            "type":"Retail Goods"
        }
    ],
    "sg:phone":"+1 514 898 0616",
    "sg:postcode":"H2A 1W6",
    "sg:province":"QC",
    "sg:tags":[
        "pawnbroker"
    ],
    "wof:name":"Pret Mobile",
    "wof:placetype":"venue"
},
  "geometry": {"coordinates":[-73.597488,45.559887],"type":"Point"}
}