{
  "type": "Feature",
  "properties": {
    "iso:country":"CA",
    "sg:city":"Oakville",
    "sg:classifiers":[
        {
            "category":"Professional",
            "subcategory":"Business Services",
            "type":"Services"
        }
    ],
    "sg:phone":"+1 905 844 2062",
    "sg:postcode":"L6H 2R3",
    "sg:province":"ON",
    "sg:tags":[
        "water",
        "treatment"
    ],
    "wof:name":"Biolab Equipment Canada Ltd",
    "wof:placetype":"venue"
},
  "geometry": {"coordinates":[-79.681808,43.467682],"type":"Point"}
}