{
  "type": "Feature",
  "properties": {
    "addr:full":"4021 Upper Middle Rd Burlington ON L7R 3X5",
    "addr:housenumber":"4021",
    "addr:postcode":"l7r 3x5",
    "addr:street":"Upper Middle Rd",
    "iso:country":"CA",
    "sg:address":"4021 Upper Middle Rd",
    "sg:city":"Burlington",
    "sg:classifiers":[
        {
            "category":"Autos & Motor Vehicles",
            "subcategory":"Fuel & Gas Station",
            "type":"Retail Goods"
        }
    ],
    "sg:phone":"+1 905 336 2557",
    "sg:postcode":"L7R 3X5",
    "sg:province":"ON",
    "sg:tags":[
        "oil"
    ],
    "wof:name":"Upper Middle Shell",
    "wof:placetype":"venue"
},
  "geometry": {"coordinates":[-79.805092,43.380413],"type":"Point"}
}