{
  "type": "Feature",
  "properties": {
    "addr:full":"1016 King St E Hamilton ON L8M 1C8",
    "addr:housenumber":"1016",
    "addr:postcode":"l8m 1c8",
    "addr:street":"King St E",
    "iso:country":"CA",
    "sg:address":"1016 King St E",
    "sg:city":"Hamilton",
    "sg:classifiers":[
        {
            "category":"Restaurant",
            "type":"Food & Drink"
        }
    ],
    "sg:phone":"+1 905 544 4440",
    "sg:postcode":"L8M 1C8",
    "sg:province":"ON",
    "sg:tags":[
        "out",
        "pizza"
    ],
    "wof:name":"Mario Pizza",
    "wof:placetype":"venue"
},
  "geometry": {"coordinates":[-79.83309199999999,43.25021],"type":"Point"}
}