{
  "type": "Feature",
  "properties": {
    "addr:full":"742 King St E Cambridge ON N3H 3N9",
    "addr:housenumber":"742",
    "addr:postcode":"n3h 3n9",
    "addr:street":"King St E",
    "iso:country":"CA",
    "sg:address":"742 King St E",
    "sg:city":"Cambridge",
    "sg:classifiers":[
        {
            "category":"Shopping",
            "subcategory":"Used Merchandise",
            "type":"Retail Goods"
        }
    ],
    "sg:phone":"+1 519 653 4162",
    "sg:postcode":"N3H 3N9",
    "sg:province":"ON",
    "sg:tags":[
        "second",
        "store",
        "hand"
    ],
    "wof:name":"St Vincent DE Paul Value Ctr",
    "wof:placetype":"venue"
},
  "geometry": {"coordinates":[-80.35777299999999,43.395378],"type":"Point"}
}