{
  "type": "Feature",
  "properties": {
    "addr:full":"100 Judson St Etobicoke ON M8Z 5Z5",
    "addr:housenumber":"100",
    "addr:postcode":"m8z 5z5",
    "addr:street":"Judson St",
    "iso:country":"CA",
    "sg:address":"100 Judson St",
    "sg:city":"Etobicoke",
    "sg:classifiers":[
        {
            "category":"Real Estate",
            "subcategory":"Real Estate Agent",
            "type":"Services"
        }
    ],
    "sg:phone":"+1 416 503 8088",
    "sg:postcode":"M8Z 5Z5",
    "sg:province":"ON",
    "wof:name":"Mow Huat Intl Ltd",
    "wof:placetype":"venue"
},
  "geometry": {"coordinates":[-79.5040435791,43.6147766113],"type":"Point"}
}