{
  "type": "Feature",
  "properties": {
    "iso:country":"CA",
    "sg:address":"5785 Place Turcot",
    "sg:city":"Montreal",
    "sg:classifiers":[
        {
            "category":"Manufacturing",
            "subcategory":"Motor Vehicles & Parts",
            "type":"Manufacturing & Wholesale Goods"
        }
    ],
    "sg:phone":"+1 514 937 1670",
    "sg:postcode":"H4C 1V9",
    "sg:province":"QC",
    "sg:tags":[
        "trailer"
    ],
    "wof:name":"Citernes Bedard Inc",
    "wof:placetype":"venue"
},
  "geometry": {"coordinates":[-73.60377502439999,45.4628295898],"type":"Point"}
}