{
  "type": "Feature",
  "properties": {
    "addr:full":"64 Boul Renard E Gaspe QC G4X 5R2",
    "addr:housenumber":"64",
    "addr:postcode":"g4x 5r2",
    "addr:street":"Boul Renard E Gaspe",
    "iso:country":"CA",
    "sg:address":"64 Boul Renard E",
    "sg:city":"Gaspe",
    "sg:classifiers":[
        {
            "category":"Shopping",
            "subcategory":"Florist",
            "type":"Retail Goods"
        }
    ],
    "sg:phone":"+1 418 269 3376",
    "sg:postcode":"G4X 5R2",
    "sg:province":"QC",
    "wof:name":"Fleuriste Creations Diane Enr",
    "wof:placetype":"venue"
},
  "geometry": {"coordinates":[-64.390366,48.992329],"type":"Point"}
}