{
  "type": "Feature",
  "properties": {
    "addr:full":"Calgary AB T2P 0Z3",
    "addr:postcode":"t2p 0z3",
    "iso:country":"CA",
    "sg:city":"Calgary",
    "sg:classifiers":[
        {
            "category":"Wholesale",
            "subcategory":"Chemicals & Plastics",
            "type":"Manufacturing & Wholesale Goods"
        }
    ],
    "sg:phone":"+1 403 262 7846",
    "sg:postcode":"T2P 0Z3",
    "sg:province":"AB",
    "wof:name":"Clariant Canada Inc",
    "wof:placetype":"venue"
},
  "geometry": {"coordinates":[-114.076843,51.046734],"type":"Point"}
}