{
  "type": "Feature",
  "properties": {
    "addr:full":"80 Macewan Park Green NW Calgary AB T3K 4E5",
    "addr:housenumber":"80",
    "addr:postcode":"t3k 4e5",
    "addr:street":"Macewan Park Green Nw",
    "iso:country":"CA",
    "sg:address":"80 Macewan Park Green NW",
    "sg:city":"Calgary",
    "sg:classifiers":[
        {
            "category":"Home & Garden",
            "subcategory":"Garden Supply",
            "type":"Retail Goods"
        }
    ],
    "sg:phone":"+1 403 275 4484",
    "sg:postcode":"T3K 4E5",
    "sg:province":"AB",
    "sg:tags":[
        "sprinkler"
    ],
    "wof:name":"Rfk Irrigation",
    "wof:placetype":"venue"
},
  "geometry": {"coordinates":[-114.117058,51.133404],"type":"Point"}
}