{
  "type": "Feature",
  "properties": {
    "addr:full":"1046 King St L'Orignal ON K0B 1K0",
    "addr:housenumber":"1046",
    "addr:postcode":"k0b 1k0",
    "addr:street":"King St",
    "iso:country":"CA",
    "sg:address":"1046 King St",
    "sg:city":"L'Orignal",
    "sg:classifiers":[
        {
            "category":"Building & Trades",
            "subcategory":"Construction",
            "type":"Services"
        }
    ],
    "sg:phone":"+1 613 675 2728",
    "sg:postcode":"K0B 1K0",
    "sg:province":"ON",
    "sg:tags":[
        "contractor"
    ],
    "wof:name":"Russell Prescott Construction",
    "wof:placetype":"venue"
},
  "geometry": {"coordinates":[-74.69111599999999,45.620441],"type":"Point"}
}