{
  "type": "Feature",
  "properties": {
    "addr:full":"175 Rue Belanger Saint-Jerome QC J7Y 1K5",
    "addr:housenumber":"175",
    "addr:postcode":"j7y 1k5",
    "addr:street":"Rue Belanger Saint-Jerome",
    "iso:country":"CA",
    "sg:address":"175 Rue Belanger",
    "sg:city":"Saint-Jerome",
    "sg:classifiers":[
        {
            "category":"Retail",
            "subcategory":"Laundry & Dry Cleaning",
            "type":"Services"
        }
    ],
    "sg:phone":"+1 450 438 0378",
    "sg:postcode":"J7Y 1K5",
    "sg:province":"QC",
    "sg:tags":[
        "dressmaker"
    ],
    "wof:name":"Couture Eliane Enr",
    "wof:placetype":"venue"
},
  "geometry": {"coordinates":[-74.00633999999999,45.794544],"type":"Point"}
}