{
  "type": "Feature",
  "properties": {
    "iso:country":"CA",
    "sg:address":"221 King St E",
    "sg:city":"Kingston",
    "sg:classifiers":[
        {
            "category":"Social Services",
            "type":"Services"
        }
    ],
    "sg:phone":"+1 613 547 9814",
    "sg:postcode":"K7L 3A7",
    "sg:province":"ON",
    "sg:tags":[
        "counselor",
        "marriage",
        "family"
    ],
    "wof:name":"Whynot, Chris",
    "wof:placetype":"venue"
},
  "geometry": {"coordinates":[-76.483673,44.227413],"type":"Point"}
}