{
  "type": "Feature",
  "properties": {
    "iso:country":"CA",
    "sg:address":"810 Royal Ave",
    "sg:city":"New Westminster",
    "sg:classifiers":[
        {
            "category":"Manufacturing",
            "subcategory":"Printing",
            "type":"Manufacturing & Wholesale Goods"
        }
    ],
    "sg:phone":"+1 604 521 1610",
    "sg:postcode":"V3M 1J9",
    "sg:province":"BC",
    "sg:tags":[
        "printer"
    ],
    "wof:name":"Pacific Canadian Printers Ltd",
    "wof:placetype":"venue"
},
  "geometry": {"coordinates":[-122.91490936300001,49.2032623291],"type":"Point"}
}