{
  "type": "Feature",
  "properties": {
    "addr:full":"Vancouver BC V5K 1Z9",
    "addr:postcode":"v5k 1z9",
    "iso:country":"CA",
    "sg:city":"Vancouver",
    "sg:classifiers":[
        {
            "category":"Health Services",
            "subcategory":"Podiatrist",
            "type":"Services"
        }
    ],
    "sg:phone":"+1 604 253 3166",
    "sg:postcode":"V5K 1Z9",
    "sg:province":"BC",
    "wof:name":"Karasz, Paul DPM",
    "wof:placetype":"venue"
},
  "geometry": {"coordinates":[-123.04830932599999,49.2809257507],"type":"Point"}
}