{
  "type": "Feature",
  "properties": {
    "addr:full":"Abbotsford BC V2T 6G1",
    "addr:postcode":"v2t 6g1",
    "iso:country":"CA",
    "sg:city":"Abbotsford",
    "sg:classifiers":[
        {
            "category":"Professional",
            "subcategory":"Management & Consulting",
            "type":"Services"
        }
    ],
    "sg:phone":"+1 604 854 5405",
    "sg:postcode":"V2T 6G1",
    "sg:province":"BC",
    "sg:tags":[
        "construction"
    ],
    "wof:name":"Highview Homes Ltd",
    "wof:placetype":"venue"
},
  "geometry": {"coordinates":[-122.36024500000001,49.044617],"type":"Point"}
}