{
  "type": "Feature",
  "properties": {
    "addr:full":"478 Dutrisac Rd S Sturgeon Falls ON P2B 2J8",
    "addr:housenumber":"478",
    "addr:postcode":"p2b 2j8",
    "addr:street":"Dutrisac Rd S",
    "iso:country":"CA",
    "sg:address":"478 Dutrisac Rd S",
    "sg:city":"Sturgeon Falls",
    "sg:classifiers":[
        {
            "category":"Organizations",
            "subcategory":"Non-profit Organization",
            "type":"Services"
        }
    ],
    "sg:phone":"+1 705 753 6128",
    "sg:postcode":"P2B 2J8",
    "sg:province":"ON",
    "sg:tags":[
        "addiction",
        "treatment",
        "center"
    ],
    "wof:name":"Eclipse Counselling & Edctn",
    "wof:placetype":"venue"
},
  "geometry": {"coordinates":[-79.903503,46.355034],"type":"Point"}
}