{
  "type": "Feature",
  "properties": {
    "addr:full":"624 40E Av Saint-Jerome QC J7Z 7H2",
    "addr:housenumber":"624",
    "addr:postcode":"j7z 7h2",
    "addr:street":"40E Av Saint-Jerome",
    "iso:country":"CA",
    "sg:address":"624 40E Av",
    "sg:city":"Saint-Jerome",
    "sg:classifiers":[
        {
            "category":"Personal",
            "type":"Services"
        }
    ],
    "sg:phone":"+1 450 431 1683",
    "sg:postcode":"J7Z 7H2",
    "sg:province":"QC",
    "sg:tags":[
        "therapist",
        "massage"
    ],
    "wof:name":"Clinique Massotherapie",
    "wof:placetype":"venue"
},
  "geometry": {"coordinates":[-74.00351000000001,45.775009],"type":"Point"}
}