{
  "type": "Feature",
  "properties": {
    "addr:full":"2153 Boul Industriel Chambly QC J3L 4W3",
    "addr:housenumber":"2153",
    "addr:postcode":"j3l 4w3",
    "addr:street":"Boul Industriel",
    "iso:country":"CA",
    "sg:address":"2153 Boul Industriel",
    "sg:city":"Chambly",
    "sg:classifiers":[
        {
            "category":"Manufacturing",
            "subcategory":"Tools & Machinery",
            "type":"Manufacturing & Wholesale Goods"
        }
    ],
    "sg:phone":"+1 450 658 1976",
    "sg:postcode":"J3L 4W3",
    "sg:province":"QC",
    "sg:tags":[
        "machine",
        "shop",
        "mold"
    ],
    "wof:name":"Atelier D'Usinage Giguere Enr",
    "wof:placetype":"venue"
},
  "geometry": {"coordinates":[-73.274635,45.433178],"type":"Point"}
}