{
  "type": "Feature",
  "properties": {
    "addr:full":"Waterloo ON N2V 1A2",
    "addr:postcode":"n2v 1a2",
    "iso:country":"CA",
    "sg:city":"Waterloo",
    "sg:classifiers":[
        {
            "category":"Manufacturing",
            "subcategory":"Signs",
            "type":"Manufacturing & Wholesale Goods"
        }
    ],
    "sg:phone":"+1 519 886 1179",
    "sg:postcode":"N2V 1A2",
    "sg:province":"ON",
    "wof:name":"Signs Now",
    "wof:placetype":"venue"
},
  "geometry": {"coordinates":[-80.5404281616,43.5059318542],"type":"Point"}
}