{
  "type": "Feature",
  "properties": {
    "iso:country":"CA",
    "sg:address":"127 Garafraxa St S",
    "sg:city":"Durham",
    "sg:classifiers":[
        {
            "category":"Shopping",
            "subcategory":"Florist",
            "type":"Retail Goods"
        }
    ],
    "sg:phone":"+1 519 369 6815",
    "sg:postcode":"N0G 1R0",
    "sg:province":"ON",
    "wof:name":"Eckhardt's Floral Treasures",
    "wof:placetype":"venue"
},
  "geometry": {"coordinates":[-80.8181304932,44.1757354736],"type":"Point"}
}