{
  "type": "Feature",
  "properties": {
    "iso:country":"CA",
    "sg:city":"Griswold",
    "sg:classifiers":[
        {
            "category":"Organizations",
            "subcategory":"Professional Association",
            "type":"Services"
        }
    ],
    "sg:phone":"+1 204 855 2671",
    "sg:postcode":"R0M 0S0",
    "sg:province":"MB",
    "wof:name":"Sioux Valley Dakota Nation",
    "wof:placetype":"venue"
},
  "geometry": {"coordinates":[-100.471992493,49.7767944336],"type":"Point"}
}