{
  "type": "Feature",
  "properties": {
    "addr:full":"1 Rue DE Aereport Senneterre QC J0Y 2M0",
    "addr:housenumber":"1",
    "addr:postcode":"j0y 2m0",
    "addr:street":"Rue De Aereport",
    "iso:country":"CA",
    "sg:address":"1 Rue DE Aereport",
    "sg:city":"Senneterre",
    "sg:classifiers":[
        {
            "category":"Travel",
            "subcategory":"Campground",
            "type":"Entertainment"
        }
    ],
    "sg:phone":"+1 819 737 4567",
    "sg:postcode":"J0Y 2M0",
    "sg:province":"QC",
    "sg:tags":[
        "camp",
        "fishing"
    ],
    "wof:name":"Domaine Forsythe",
    "wof:placetype":"venue"
},
  "geometry": {"coordinates":[-77.18524932859999,48.3444747925],"type":"Point"}
}