{
  "type": "Feature",
  "properties": {
    "iso:country":"CA",
    "sg:city":"Sorel-Tracy",
    "sg:classifiers":[
        {
            "category":"Personal",
            "subcategory":"Beauty Salon",
            "type":"Services"
        }
    ],
    "sg:phone":"+1 450 742 0158",
    "sg:postcode":"J3P 1L2",
    "sg:province":"QC",
    "wof:name":"Coiffure Julie",
    "wof:placetype":"venue"
},
  "geometry": {"coordinates":[-73.1142883301,46.0422172546],"type":"Point"}
}