{
  "type": "Feature",
  "properties": {
    "addr:full":"2135 Ch DE Montreal O Masson-Angers QC J8M 1P3",
    "addr:postcode":"2135;j8m 1p3",
    "addr:street":"Ch De Montreal O",
    "iso:country":"CA",
    "sg:address":"2135 Ch DE Montreal O",
    "sg:city":"Masson-Angers",
    "sg:classifiers":[
        {
            "category":"Home & Garden",
            "subcategory":"Building Materials",
            "type":"Retail Goods"
        }
    ],
    "sg:phone":"+1 819 986 3190",
    "sg:postcode":"J8M 1P3",
    "sg:province":"QC",
    "sg:tags":[
        "windows",
        "door"
    ],
    "wof:name":"A Theo Mineault Inc",
    "wof:placetype":"venue"
},
  "geometry": {"coordinates":[-75.52465100000001,45.515297],"type":"Point"}
}