{
  "type": "Feature",
  "properties": {
    "addr:full":"Toronto ON M4M 2S1",
    "addr:postcode":"m4m 2s1",
    "iso:country":"CA",
    "sg:city":"Toronto",
    "sg:classifiers":[
        {
            "category":"Real Estate",
            "subcategory":"Real Estate Operator",
            "type":"Services"
        }
    ],
    "sg:phone":"+1 416 466 2642",
    "sg:postcode":"M4M 2S1",
    "sg:province":"ON",
    "sg:tags":[
        "management",
        "apartment"
    ],
    "wof:name":"O'Shanter Development CO",
    "wof:placetype":"venue"
},
  "geometry": {"coordinates":[-79.34058400000001,43.662785],"type":"Point"}
}