{
  "type": "Feature",
  "properties": {
    "addr:full":"1802 Centre Ave NE Calgary AB T2E 0A6",
    "addr:housenumber":"1802",
    "addr:postcode":"t2e 0a6",
    "addr:street":"Centre Ave Ne",
    "iso:country":"CA",
    "sg:address":"1802 Centre Ave NE",
    "sg:city":"Calgary",
    "sg:classifiers":[
        {
            "category":"Organizations",
            "subcategory":"Non-profit Organization",
            "type":"Services"
        }
    ],
    "sg:phone":"+1 403 235 8555",
    "sg:postcode":"T2E 0A6",
    "sg:province":"AB",
    "sg:tags":[
        "food",
        "fund",
        "counselor",
        "raising"
    ],
    "wof:name":"Bridge Brand Food Svc Ltd",
    "wof:placetype":"venue"
},
  "geometry": {"coordinates":[-114.014359,51.052532],"type":"Point"}
}