{
  "type": "Feature",
  "properties": {
    "addr:full":"Pointe-Claire QC H9R 5J2",
    "addr:postcode":"h9r 5j2",
    "iso:country":"CA",
    "sg:city":"Pointe-Claire",
    "sg:classifiers":[
        {
            "category":"Shopping",
            "subcategory":"Bicycles & Sporting Goods",
            "type":"Retail Goods"
        }
    ],
    "sg:phone":"+1 514 694 8181",
    "sg:postcode":"H9R 5J2",
    "sg:province":"QC",
    "wof:name":"Sports Experts",
    "wof:placetype":"venue"
},
  "geometry": {"coordinates":[-73.816757,45.468361],"type":"Point"}
}