{
  "type": "Feature",
  "properties": {
    "iso:country":"CA",
    "sg:address":"3324 Rue Monselet",
    "sg:city":"Montreal-Nord",
    "sg:classifiers":[
        {
            "category":"Manufacturing",
            "subcategory":"Printing",
            "type":"Manufacturing & Wholesale Goods"
        }
    ],
    "sg:phone":"+1 514 323 8431",
    "sg:postcode":"H1H 1Z5",
    "sg:province":"QC",
    "sg:tags":[
        "printer"
    ],
    "wof:name":"Imprimerie Econo-Prix Inc",
    "wof:placetype":"venue"
},
  "geometry": {"coordinates":[-73.64762115480001,45.5842933655],"type":"Point"}
}