{
  "type": "Feature",
  "properties": {
    "addr:full":"1089 Rue DE Fontenay Cap-Rouge QC G1Y 2Y2",
    "addr:housenumber":"1089",
    "addr:postcode":"g1y 2y2",
    "addr:street":"Rue De Fontenay",
    "iso:country":"CA",
    "sg:address":"1089 Rue DE Fontenay",
    "sg:city":"Cap-Rouge",
    "sg:classifiers":[
        {
            "category":"Health Services",
            "subcategory":"Doctor",
            "type":"Services"
        }
    ],
    "sg:phone":"+1 418 658 3730",
    "sg:postcode":"G1Y 2Y2",
    "sg:province":"QC",
    "sg:tags":[
        "psychoanalyst"
    ],
    "wof:name":"Marceau, Lise",
    "wof:placetype":"venue"
},
  "geometry": {"coordinates":[-71.36711120610001,46.7510452271],"type":"Point"}
}