{
  "type": "Feature",
  "properties": {
    "addr:full":"800 Hunt Club Rd # 3 Ottawa ON K1V 1C3",
    "addr:housenumber":"800",
    "addr:postcode":"k1v 1c3",
    "addr:street":"Hunt Club Rd # 3",
    "iso:country":"CA",
    "sg:address":"800 Hunt Club Rd # 3",
    "sg:city":"Ottawa",
    "sg:classifiers":[
        {
            "category":"Personal",
            "subcategory":"Barber",
            "type":"Services"
        }
    ],
    "sg:phone":"+1 613 736 5014",
    "sg:postcode":"K1V 1C3",
    "sg:province":"ON",
    "wof:name":"Thee Barber Shop",
    "wof:placetype":"venue"
},
  "geometry": {"coordinates":[-75.66651153559999,45.3445892334],"type":"Point"}
}