{
  "type": "Feature",
  "properties": {
    "addr:full":"16 Charing Cross St Brantford ON N3R 2H2",
    "addr:housenumber":"16",
    "addr:postcode":"n3r 2h2",
    "addr:street":"Charing Cross St",
    "iso:country":"CA",
    "sg:address":"16 Charing Cross St",
    "sg:city":"Brantford",
    "sg:classifiers":[
        {
            "category":"Building & Trades",
            "subcategory":"Construction",
            "type":"Services"
        }
    ],
    "sg:phone":"+1 519 754 0820",
    "sg:postcode":"N3R 2H2",
    "sg:province":"ON",
    "sg:tags":[
        "tile",
        "dealer"
    ],
    "wof:name":"Accardo Tile",
    "wof:placetype":"venue"
},
  "geometry": {"coordinates":[-80.272285,43.161884],"type":"Point"}
}