{
  "type": "Feature",
  "properties": {
    "iso:country":"CA",
    "sg:address":"205 Doney Cres",
    "sg:city":"Concord",
    "sg:classifiers":[
        {
            "category":"Freight",
            "type":"Transportation"
        }
    ],
    "sg:phone":"+1 905 761 8253",
    "sg:postcode":"L4K 1P6",
    "sg:province":"ON",
    "sg:tags":[
        "trucking"
    ],
    "wof:name":"Muir's Cartage Ltd",
    "wof:placetype":"venue"
},
  "geometry": {"coordinates":[-79.504494,43.794949],"type":"Point"}
}