{
  "type": "Feature",
  "properties": {
    "addr:full":"275 Erie St S Leamington ON N8H 3C4",
    "addr:housenumber":"275",
    "addr:postcode":"n8h 3c4",
    "addr:street":"Erie St S",
    "iso:country":"CA",
    "sg:address":"275 Erie St S",
    "sg:city":"Leamington",
    "sg:classifiers":[
        {
            "category":"Shopping",
            "subcategory":"Department Store",
            "type":"Retail Goods"
        }
    ],
    "sg:phone":"+1 519 325 0732",
    "sg:postcode":"N8H 3C4",
    "sg:province":"ON",
    "sg:tags":[
        "shop"
    ],
    "wof:name":"Dollarama",
    "wof:placetype":"venue"
},
  "geometry": {"coordinates":[-82.600998,42.038013],"type":"Point"}
}