{
  "type": "Feature",
  "properties": {
    "addr:full":"Didsbury AB T0M 0W0",
    "addr:postcode":"t0m 0w0",
    "iso:country":"CA",
    "sg:city":"Didsbury",
    "sg:classifiers":[
        {
            "category":"Retail",
            "subcategory":"Animal Services",
            "type":"Services"
        }
    ],
    "sg:phone":"+1 403 335 3174",
    "sg:postcode":"T0M 0W0",
    "sg:province":"AB",
    "sg:tags":[
        "pet",
        "grooming",
        "washing"
    ],
    "wof:name":"Pet Salon",
    "wof:placetype":"venue"
},
  "geometry": {"coordinates":[-114.122803,51.656933],"type":"Point"}
}