{
  "type": "Feature",
  "properties": {
    "addr:full":"3020 Blanshard St Victoria BC V8T 5C7",
    "addr:housenumber":"3020",
    "addr:postcode":"v8t 5c7",
    "addr:street":"Blanshard St",
    "iso:country":"CA",
    "sg:address":"3020 Blanshard St",
    "sg:city":"Victoria",
    "sg:classifiers":[
        {
            "category":"Restaurant",
            "type":"Food & Drink"
        }
    ],
    "sg:phone":"+1 250 382 7262",
    "sg:postcode":"V8T 5C7",
    "sg:province":"BC",
    "wof:name":"Redd's Roadhouse",
    "wof:placetype":"venue"
},
  "geometry": {"coordinates":[-123.36586800000001,48.443867],"type":"Point"}
}