{
  "type": "Feature",
  "properties": {
    "addr:full":"1195 Kingston Rd Pickering ON L1V 1B5",
    "addr:housenumber":"1195",
    "addr:postcode":"l1v 1b5",
    "addr:street":"Kingston Rd",
    "iso:country":"CA",
    "sg:address":"1195 Kingston Rd",
    "sg:city":"Pickering",
    "sg:classifiers":[
        {
            "category":"Retail",
            "subcategory":"Auto Repair",
            "type":"Services"
        }
    ],
    "sg:phone":"+1 905 839 1744",
    "sg:postcode":"L1V 1B5",
    "sg:province":"ON",
    "sg:tags":[
        "repairing",
        "automobile",
        "lubrication"
    ],
    "wof:name":"Mr Lube",
    "wof:placetype":"venue"
},
  "geometry": {"coordinates":[-79.09507751460001,43.8319473267],"type":"Point"}
}