{
  "type": "Feature",
  "properties": {
    "addr:full":"Burnaby BC V5C 6C6",
    "addr:postcode":"v5c 6c6",
    "iso:country":"CA",
    "sg:city":"Burnaby",
    "sg:classifiers":[
        {
            "category":"Banks & Credit Unions",
            "subcategory":"Financial Services",
            "type":"Services"
        }
    ],
    "sg:phone":"+1 604 293 0053",
    "sg:postcode":"V5C 6C6",
    "sg:province":"BC",
    "sg:tags":[
        "educational",
        "plan",
        "scholarship"
    ],
    "wof:name":"Canadian Scholarship Trust",
    "wof:placetype":"venue"
},
  "geometry": {"coordinates":[-123.01173400899999,49.2599639893],"type":"Point"}
}