{
  "type": "Feature",
  "properties": {
    "iso:country":"CA",
    "sg:address":"69 Homestead Rd",
    "sg:city":"Scarborough",
    "sg:classifiers":[
        {
            "category":"Professional",
            "subcategory":"Employment Agencies",
            "type":"Services"
        }
    ],
    "sg:phone":"+1 416 283 9127",
    "sg:postcode":"M1E 3S1",
    "sg:province":"ON",
    "sg:tags":[
        "opportunity"
    ],
    "wof:name":"Family Caregiver Intl Svc",
    "wof:placetype":"venue"
},
  "geometry": {"coordinates":[-79.177711,43.764431],"type":"Point"}
}