{
  "type": "Feature",
  "properties": {
    "addr:full":"198 Hastings St W Vancouver BC V6B 1H2",
    "addr:housenumber":"198",
    "addr:postcode":"v6b 1h2",
    "addr:street":"Hastings St W",
    "iso:country":"CA",
    "sg:address":"198 Hastings St W",
    "sg:city":"Vancouver",
    "sg:classifiers":[
        {
            "category":"Real Estate",
            "subcategory":"Developer",
            "type":"Services"
        }
    ],
    "sg:phone":"+1 604 688 2300",
    "sg:postcode":"V6B 1H2",
    "sg:province":"BC",
    "sg:tags":[
        "company",
        "land"
    ],
    "wof:name":"Millennium Development Corp",
    "wof:placetype":"venue"
},
  "geometry": {"coordinates":[-123.10945892300001,49.2823104858],"type":"Point"}
}