{
  "type": "Feature",
  "properties": {
    "addr:full":"842 Yonge St Toronto ON M4W 2H1",
    "addr:housenumber":"842",
    "addr:postcode":"m4w 2h1",
    "addr:street":"Yonge St",
    "iso:country":"CA",
    "sg:address":"842 Yonge St",
    "sg:city":"Toronto",
    "sg:classifiers":[
        {
            "category":"Home & Garden",
            "subcategory":"Home Furnishings",
            "type":"Retail Goods"
        }
    ],
    "sg:phone":"+1 416 924 3014",
    "sg:postcode":"M4W 2H1",
    "sg:province":"ON",
    "sg:tags":[
        "willow",
        "rattan",
        "reed",
        "furniture"
    ],
    "wof:name":"China Panda",
    "wof:placetype":"venue"
},
  "geometry": {"coordinates":[-79.38752700000001,43.6716],"type":"Point"}
}