{
  "type": "Feature",
  "properties": {
    "addr:full":"8060 Silver Springs Blvd NW # 156 Calgary AB T3B 5K1",
    "addr:housenumber":"8060",
    "addr:postcode":"t3b 5k1",
    "addr:street":"Silver Springs Blvd Nw # 156",
    "iso:country":"CA",
    "sg:address":"8060 Silver Springs Blvd NW # 156",
    "sg:city":"Calgary",
    "sg:classifiers":[
        {
            "category":"Restaurant",
            "type":"Food & Drink"
        }
    ],
    "sg:phone":"+1 403 286 0099",
    "sg:postcode":"T3B 5K1",
    "sg:province":"AB",
    "sg:tags":[
        "pizza"
    ],
    "wof:name":"Little Caesars Pizza",
    "wof:placetype":"venue"
},
  "geometry": {"coordinates":[-114.20512390099999,51.1156425476],"type":"Point"}
}