{
  "type": "Feature",
  "properties": {
    "addr:full":"555 Panneton St Saint-Narcisse QC G0X 2Y0",
    "addr:housenumber":"555",
    "addr:postcode":"g0x 2y0",
    "addr:street":"Panneton St",
    "iso:country":"CA",
    "sg:address":"555 Panneton St",
    "sg:city":"Saint-Narcisse",
    "sg:classifiers":[
        {
            "category":"Home & Garden",
            "subcategory":"Furniture",
            "type":"Retail Goods"
        }
    ],
    "sg:phone":"+1 418 328 3361",
    "sg:postcode":"G0X 2Y0",
    "sg:province":"QC",
    "sg:tags":[
        "mattress"
    ],
    "wof:name":"Matelas Centurion Inc",
    "wof:placetype":"venue"
},
  "geometry": {"coordinates":[-72.469894,46.564007],"type":"Point"}
}