{
  "type": "Feature",
  "properties": {
    "addr:full":"412 Saskatchewan Ave W Portage LA Prairie MB R1N 0M4",
    "addr:housenumber":"412",
    "addr:postcode":"r1n 0m4",
    "addr:street":"Saskatchewan Ave W",
    "iso:country":"CA",
    "sg:address":"412 Saskatchewan Ave W",
    "sg:city":"Portage LA Prairie",
    "sg:classifiers":[
        {
            "category":"Home & Garden",
            "subcategory":"Carpets & Floor Coverings",
            "type":"Retail Goods"
        }
    ],
    "sg:phone":"+1 204 856 2050",
    "sg:postcode":"R1N 0M4",
    "sg:province":"MB",
    "sg:tags":[
        "material",
        "rug"
    ],
    "wof:name":"Newport Design Interiors",
    "wof:placetype":"venue"
},
  "geometry": {"coordinates":[-98.29650100000001,49.973579],"type":"Point"}
}