{
  "type": "Feature",
  "properties": {
    "addr:full":"1961 Mccreary Rd Winnipeg MB R3P 2K9",
    "addr:housenumber":"1961",
    "addr:postcode":"r3p 2k9",
    "addr:street":"Mccreary Rd",
    "iso:country":"CA",
    "sg:address":"1961 Mccreary Rd",
    "sg:city":"Winnipeg",
    "sg:classifiers":[
        {
            "category":"Restaurant",
            "type":"Food & Drink"
        }
    ],
    "sg:phone":"+1 204 989 8353",
    "sg:postcode":"R3P 2K9",
    "sg:province":"MB",
    "sg:tags":[
        "nature",
        "rooms",
        "banquet",
        "center"
    ],
    "wof:name":"Fort Whyte Nature Ctr",
    "wof:placetype":"venue"
},
  "geometry": {"coordinates":[-97.23370361329999,49.8185386658],"type":"Point"}
}