{
  "type": "Feature",
  "properties": {
    "addr:full":"PO Box 6278 STN Main Fort Mcmurray AB T9H 4W1",
    "addr:housenumber":"po",
    "addr:postcode":"6278;t9h 4w1",
    "addr:street":"Box;Stn Main",
    "iso:country":"CA",
    "sg:address":"PO Box 6278 STN Main",
    "sg:city":"Fort Mcmurray",
    "sg:classifiers":[
        {
            "category":"Building & Trades",
            "subcategory":"Equipment Rental",
            "type":"Services"
        }
    ],
    "sg:phone":"+1 780 790 4852",
    "sg:postcode":"T9H 4W1",
    "sg:province":"AB",
    "sg:tags":[
        "scaffolding"
    ],
    "wof:name":"Aluma Systems Canada Inc",
    "wof:placetype":"venue"
},
  "geometry": {"coordinates":[-111.380302429,56.7271881104],"type":"Point"}
}