{
  "type": "Feature",
  "properties": {
    "iso:country":"CA",
    "sg:address":"65 Rue Principale",
    "sg:city":"Saint-Andre-Du-Lac-Saint-Jean",
    "sg:classifiers":[
        {
            "category":"Organizations",
            "subcategory":"Religious Organization",
            "type":"Services"
        }
    ],
    "sg:phone":"+1 418 349 2662",
    "sg:postcode":"G0W 2K0",
    "sg:province":"QC",
    "sg:tags":[
        "church"
    ],
    "wof:name":"Presbytere St Andre",
    "wof:placetype":"venue"
},
  "geometry": {"coordinates":[-70.8897018433,46.9212303162],"type":"Point"}
}