{
  "type": "Feature",
  "properties": {
    "addr:full":"1307 14 St SW Calgary AB T3C 1C6",
    "addr:housenumber":"1307",
    "addr:postcode":"t3c 1c6",
    "addr:street":"14 St Sw",
    "iso:country":"CA",
    "sg:address":"1307 14 St SW",
    "sg:city":"Calgary",
    "sg:classifiers":[
        {
            "category":"Organizations",
            "subcategory":"Religious Organization",
            "type":"Services"
        }
    ],
    "sg:phone":"+1 403 244 2741",
    "sg:postcode":"T3C 1C6",
    "sg:province":"AB",
    "sg:tags":[
        "church"
    ],
    "wof:name":"Sacred Heart Church",
    "wof:placetype":"venue"
},
  "geometry": {"coordinates":[-114.09481,51.041172],"type":"Point"}
}