{
  "type": "Feature",
  "properties": {
    "addr:full":"99 Crown's Lane Toronto ON M5R 3P4",
    "addr:housenumber":"99",
    "addr:postcode":"m5r 3p4",
    "addr:street":"Crown'S Lane",
    "iso:country":"CA",
    "sg:address":"99 Crown's Lane",
    "sg:city":"Toronto",
    "sg:classifiers":[
        {
            "category":"Professional",
            "subcategory":"Management & Consulting",
            "type":"Services"
        }
    ],
    "sg:phone":"+1 416 515 0815",
    "sg:postcode":"M5R 3P4",
    "sg:province":"ON",
    "sg:tags":[
        "consultant",
        "business"
    ],
    "wof:name":"Tci Management Consultants",
    "wof:placetype":"venue"
},
  "geometry": {"coordinates":[-79.51834106450001,43.6240005493],"type":"Point"}
}