{
  "type": "Feature",
  "properties": {
    "addr:full":"126 Rue Fleury O Montreal QC H3L 1T4",
    "addr:housenumber":"126",
    "addr:postcode":"h3l 1t4",
    "addr:street":"Rue Fleury O",
    "iso:country":"CA",
    "sg:address":"126 Rue Fleury O",
    "sg:city":"Montreal",
    "sg:classifiers":[
        {
            "category":"Shopping",
            "subcategory":"Department Store",
            "type":"Retail Goods"
        }
    ],
    "sg:phone":"+1 514 384 3680",
    "sg:postcode":"H3L 1T4",
    "sg:province":"QC",
    "sg:tags":[
        "shop"
    ],
    "wof:name":"Fureur Du Dollar",
    "wof:placetype":"venue"
},
  "geometry": {"coordinates":[-73.66445922849999,45.5488319397],"type":"Point"}
}