{
  "type": "Feature",
  "properties": {
    "iso:country":"CA",
    "sg:city":"Grande Prairie",
    "sg:classifiers":[
        {
            "category":"Health Services",
            "subcategory":"Doctor",
            "type":"Services"
        }
    ],
    "sg:phone":"+1 780 539 3305",
    "sg:postcode":"T8V 5B6",
    "sg:province":"AB",
    "sg:tags":[
        "physician",
        "surgeon"
    ],
    "wof:name":"Sendziak, Joseph MD",
    "wof:placetype":"venue"
},
  "geometry": {"coordinates":[-118.78715515099999,55.1720504761],"type":"Point"}
}