{
  "type": "Feature",
  "properties": {
    "addr:full":"13872 Crescent Rd Surrey BC V4P 1K8",
    "addr:housenumber":"13872",
    "addr:postcode":"v4p 1k8",
    "addr:street":"Crescent Rd",
    "iso:country":"CA",
    "sg:address":"13872 Crescent Rd",
    "sg:city":"Surrey",
    "sg:classifiers":[
        {
            "category":"Personal",
            "type":"Services"
        }
    ],
    "sg:phone":"+1 604 538 5175",
    "sg:postcode":"V4P 1K8",
    "sg:province":"BC",
    "sg:tags":[
        "therapist",
        "massage"
    ],
    "wof:name":"Crescent Road Massage Therapy",
    "wof:placetype":"venue"
},
  "geometry": {"coordinates":[-122.838058,49.06562],"type":"Point"}
}