{
  "type": "Feature",
  "properties": {
    "addr:full":"31 Shoreham Dr North York ON M3N 2S6",
    "addr:housenumber":"31",
    "addr:postcode":"m3n 2s6",
    "addr:street":"Shoreham Dr",
    "iso:country":"CA",
    "sg:address":"31 Shoreham Dr",
    "sg:city":"North York",
    "sg:classifiers":[
        {
            "category":"Social Services",
            "subcategory":"Child Care",
            "type":"Services"
        }
    ],
    "sg:phone":"+1 416 392 8599",
    "sg:postcode":"M3N 2S6",
    "sg:province":"ON",
    "sg:tags":[
        "government"
    ],
    "wof:name":"Toronto Child Care Ctr",
    "wof:placetype":"venue"
},
  "geometry": {"coordinates":[-79.5183792114,43.7690467834],"type":"Point"}
}