{
  "type": "Feature",
  "properties": {
    "iso:country":"CA",
    "sg:city":"Vegreville",
    "sg:classifiers":[
        {
            "category":"Shopping",
            "subcategory":"Clothing, Apparel, & Fashions",
            "type":"Retail Goods"
        }
    ],
    "sg:phone":"+1 780 632 3610",
    "sg:postcode":"T9C 1P8",
    "sg:province":"AB",
    "wof:name":"Field Stores Ltd",
    "wof:placetype":"venue"
},
  "geometry": {"coordinates":[-112.061706543,53.498210907],"type":"Point"}
}