{
  "type": "Feature",
  "properties": {
    "addr:full":"Montreal QC H3T 1X8",
    "addr:postcode":"h3t 1x8",
    "iso:country":"CA",
    "sg:city":"Montreal",
    "sg:classifiers":[
        {
            "category":"Freight",
            "type":"Transportation"
        }
    ],
    "sg:phone":"+1 514 489 7888",
    "sg:postcode":"H3T 1X8",
    "sg:province":"QC",
    "sg:tags":[
        "shipping",
        "agent"
    ],
    "wof:name":"Time Sensitive Demenagement",
    "wof:placetype":"venue"
},
  "geometry": {"coordinates":[-73.6206283569,45.4955215454],"type":"Point"}
}