{
  "type": "Feature",
  "properties": {
    "iso:country":"CA",
    "sg:address":"101 Rue Lucie",
    "sg:city":"Repentigny",
    "sg:classifiers":[
        {
            "category":"Personal",
            "subcategory":"Beauty Salon",
            "type":"Services"
        }
    ],
    "sg:phone":"+1 450 654 1520",
    "sg:postcode":"J6A 4K1",
    "sg:province":"QC",
    "wof:name":"Casse Tete Coiffure Familiale",
    "wof:placetype":"venue"
},
  "geometry": {"coordinates":[-73.4604797363,45.7379112244],"type":"Point"}
}