{
  "type": "Feature",
  "properties": {
    "addr:full":"3427 Derry Rd E # 205C Mississauga ON L4T 4H7",
    "addr:housenumber":"3427",
    "addr:postcode":"l4t 4h7",
    "addr:street":"Derry Rd E # 205C",
    "iso:country":"CA",
    "sg:address":"3427 Derry Rd E # 205C",
    "sg:city":"Mississauga",
    "sg:classifiers":[
        {
            "category":"Health Services",
            "subcategory":"Health Practitioner",
            "type":"Services"
        }
    ],
    "sg:phone":"+1 905 678 8889",
    "sg:postcode":"L4T 4H7",
    "sg:province":"ON",
    "sg:tags":[
        "acupuncture"
    ],
    "wof:name":"Alimvegs Health Consulting",
    "wof:placetype":"venue"
},
  "geometry": {"coordinates":[-79.6335449219,43.7123146057],"type":"Point"}
}