{
  "type": "Feature",
  "properties": {
    "addr:full":"1634 Franklin St Vancouver BC V5L 1P4",
    "addr:housenumber":"1634",
    "addr:postcode":"v5l 1p4",
    "addr:street":"Franklin St",
    "iso:country":"CA",
    "sg:address":"1634 Franklin St",
    "sg:city":"Vancouver",
    "sg:classifiers":[
        {
            "category":"Manufacturing",
            "subcategory":"Furniture",
            "type":"Manufacturing & Wholesale Goods"
        }
    ],
    "sg:phone":"+1 604 254 5451",
    "sg:postcode":"V5L 1P4",
    "sg:province":"BC",
    "wof:name":"West Brothers Frames & Chairs",
    "wof:placetype":"venue"
},
  "geometry": {"coordinates":[-123.07172393800001,49.2820930481],"type":"Point"}
}