{
  "type": "Feature",
  "properties": {
    "addr:full":"3330 Dundas St W Toronto ON M6P 2A4",
    "addr:housenumber":"3330",
    "addr:postcode":"m6p 2a4",
    "addr:street":"Dundas St W",
    "iso:country":"CA",
    "sg:address":"3330 Dundas St W",
    "sg:city":"Toronto",
    "sg:classifiers":[
        {
            "category":"Health Services",
            "subcategory":"Medical Lab",
            "type":"Services"
        }
    ],
    "sg:phone":"+1 416 763 7539",
    "sg:postcode":"M6P 2A4",
    "sg:province":"ON",
    "sg:tags":[
        "laboratory"
    ],
    "wof:name":"Peters Dental Ceramic Studio",
    "wof:placetype":"venue"
},
  "geometry": {"coordinates":[-79.481049,43.665707],"type":"Point"}
}