{
  "type": "Feature",
  "properties": {
    "addr:full":"1995 Cornwall Ave Vancouver BC V6J 1C9",
    "addr:housenumber":"1995",
    "addr:postcode":"v6j 1c9",
    "addr:street":"Cornwall Ave",
    "iso:country":"CA",
    "sg:address":"1995 Cornwall Ave",
    "sg:city":"Vancouver",
    "sg:classifiers":[
        {
            "category":"Restaurant",
            "type":"Food & Drink"
        }
    ],
    "sg:phone":"+1 604 734 8971",
    "sg:postcode":"V6J 1C9",
    "sg:province":"BC",
    "wof:name":"Octopus's Garden Restaurant",
    "wof:placetype":"venue"
},
  "geometry": {"coordinates":[-123.149956,49.272659],"type":"Point"}
}