{
  "type": "Feature",
  "properties": {
    "iso:country":"CA",
    "sg:address":"276 Park Ave",
    "sg:city":"Thunder Bay",
    "sg:classifiers":[
        {
            "category":"Health Services",
            "subcategory":"Doctor",
            "type":"Services"
        }
    ],
    "sg:phone":"+1 807 345 6331",
    "sg:postcode":"P7B 1C5",
    "sg:province":"ON",
    "sg:tags":[
        "dentist"
    ],
    "wof:name":"Scott Family Dental Centres",
    "wof:placetype":"venue"
},
  "geometry": {"coordinates":[-89.2239532471,48.4355697632],"type":"Point"}
}