{
  "type": "Feature",
  "properties": {
    "addr:full":"5010 Boul Samson Laval QC H7W 2J1",
    "addr:housenumber":"5010",
    "addr:postcode":"h7w 2j1",
    "addr:street":"Boul Samson",
    "iso:country":"CA",
    "sg:address":"5010 Boul Samson",
    "sg:city":"Laval",
    "sg:classifiers":[
        {
            "category":"Social Services",
            "subcategory":"Child Care",
            "type":"Services"
        }
    ],
    "sg:phone":"+1 450 681 1113",
    "sg:postcode":"H7W 2J1",
    "sg:province":"QC",
    "wof:name":"Garderie Educative Les Amis",
    "wof:placetype":"venue"
},
  "geometry": {"coordinates":[-73.766373,45.526455],"type":"Point"}
}