{
  "type": "Feature",
  "properties": {
    "addr:full":"7903 Webster Rd Delta BC V4G 1E4",
    "addr:housenumber":"7903",
    "addr:postcode":"v4g 1e4",
    "addr:street":"Webster Rd",
    "iso:country":"CA",
    "sg:address":"7903 Webster Rd",
    "sg:city":"Delta",
    "sg:classifiers":[
        {
            "category":"Manufacturing",
            "subcategory":"Glass & Minerals",
            "type":"Manufacturing & Wholesale Goods"
        }
    ],
    "sg:phone":"+1 604 946 7688",
    "sg:postcode":"V4G 1E4",
    "sg:province":"BC",
    "sg:tags":[
        "fabricator",
        "fiber"
    ],
    "wof:name":"Chemposite Inc",
    "wof:placetype":"venue"
},
  "geometry": {"coordinates":[-122.99435424799999,49.146446228],"type":"Point"}
}