{
  "type": "Feature",
  "properties": {
    "addr:full":"585 Boul Du Cure-Boivin Boisbriand QC J7G 2A8",
    "addr:housenumber":"585",
    "addr:postcode":"j7g 2a8",
    "addr:street":"Boul Du Cure-Boivin",
    "iso:country":"CA",
    "sg:address":"585 Boul Du Cure-Boivin",
    "sg:city":"Boisbriand",
    "sg:classifiers":[
        {
            "category":"Wholesale",
            "subcategory":"Machinery & Supplies",
            "type":"Manufacturing & Wholesale Goods"
        }
    ],
    "sg:phone":"+1 450 434 9911",
    "sg:postcode":"J7G 2A8",
    "sg:province":"QC",
    "sg:tags":[
        "preparation",
        "toilet",
        "beauty"
    ],
    "wof:name":"Guay Beaute Beauty Inc",
    "wof:placetype":"venue"
},
  "geometry": {"coordinates":[-73.827675,45.621964],"type":"Point"}
}