{
  "type": "Feature",
  "properties": {
    "iso:country":"CA",
    "sg:address":"205 Quigley Rd",
    "sg:city":"Hamilton",
    "sg:classifiers":[
        {
            "category":"Shopping",
            "subcategory":"Pharmacy",
            "type":"Retail Goods"
        }
    ],
    "sg:phone":"+1 905 578 2665",
    "sg:postcode":"L8K 5M8",
    "sg:province":"ON",
    "wof:name":"Danmar Pharmacy",
    "wof:placetype":"venue"
},
  "geometry": {"coordinates":[-79.784195,43.216648],"type":"Point"}
}