{
  "type": "Feature",
  "properties": {
    "addr:full":"116 11th St Weyburn SK S4H 1J5",
    "addr:housenumber":"116",
    "addr:postcode":"s4h 1j5",
    "addr:street":"11Th St",
    "iso:country":"CA",
    "sg:address":"116 11th St",
    "sg:city":"Weyburn",
    "sg:classifiers":[
        {
            "category":"Building & Trades",
            "subcategory":"Construction",
            "type":"Services"
        }
    ],
    "sg:phone":"+1 306 842 7810",
    "sg:postcode":"S4H 1J5",
    "sg:province":"SK",
    "sg:tags":[
        "concrete",
        "contractor"
    ],
    "wof:name":"R Moffatt Construction Ltd",
    "wof:placetype":"venue"
},
  "geometry": {"coordinates":[-103.842422,49.661316],"type":"Point"}
}