{
  "type": "Feature",
  "properties": {
    "addr:full":"3685 Nafziger Rd Wellesley ON N0B 2T0",
    "addr:housenumber":"3685",
    "addr:postcode":"n0b 2t0",
    "addr:street":"Nafziger Rd",
    "iso:country":"CA",
    "sg:address":"3685 Nafziger Rd",
    "sg:city":"Wellesley",
    "sg:classifiers":[
        {
            "category":"Restaurant",
            "type":"Food & Drink"
        }
    ],
    "sg:phone":"+1 519 656 2430",
    "sg:postcode":"N0B 2T0",
    "sg:province":"ON",
    "sg:tags":[
        "shop",
        "gift"
    ],
    "wof:name":"Schmidtsville Restaurant & Gft",
    "wof:placetype":"venue"
},
  "geometry": {"coordinates":[-80.76424400000001,43.475388],"type":"Point"}
}