{
  "type": "Feature",
  "properties": {
    "addr:full":"439 Edward St Prescott ON K0E 1T0",
    "addr:housenumber":"439",
    "addr:postcode":"k0e 1t0",
    "addr:street":"Edward St",
    "iso:country":"CA",
    "sg:address":"439 Edward St",
    "sg:city":"Prescott",
    "sg:classifiers":[
        {
            "category":"Museum",
            "type":"Entertainment"
        }
    ],
    "sg:phone":"+1 613 925 0489",
    "sg:postcode":"K0E 1T0",
    "sg:province":"ON",
    "sg:tags":[
        "archives"
    ],
    "wof:name":"Grenville County Historical",
    "wof:placetype":"venue"
},
  "geometry": {"coordinates":[-75.51494598390001,44.7119560242],"type":"Point"}
}