{
  "type": "Feature",
  "properties": {
    "addr:full":"9800 Rte Marie-Victorin Sorel-Tracy QC J3R 1T9",
    "addr:postcode":"9800;j3r 1t9",
    "addr:street":"Rte Marie-Victorin",
    "iso:country":"CA",
    "sg:address":"9800 Rte Marie-Victorin",
    "sg:city":"Sorel-Tracy",
    "sg:classifiers":[
        {
            "category":"Retail",
            "subcategory":"Auto Repair",
            "type":"Services"
        }
    ],
    "sg:phone":"+1 450 743 6553",
    "sg:postcode":"J3R 1T9",
    "sg:province":"QC",
    "sg:tags":[
        "body",
        "automobile",
        "painting"
    ],
    "wof:name":"Perron & Cote Ltee",
    "wof:placetype":"venue"
},
  "geometry": {"coordinates":[-73.16450500489999,46.0085334778],"type":"Point"}
}