{
  "type": "Feature",
  "properties": {
    "addr:full":"100 Buckingham Dr Conception Bay South NL A1W 5S2",
    "addr:housenumber":"100",
    "addr:postcode":"a1w 5s2",
    "addr:street":"Buckingham Dr",
    "iso:country":"CA",
    "sg:address":"100 Buckingham Dr",
    "sg:city":"Conception Bay South",
    "sg:classifiers":[
        {
            "category":"Professional",
            "subcategory":"Business Services",
            "type":"Services"
        }
    ],
    "sg:phone":"+1 709 834 8876",
    "sg:postcode":"A1W 5S2",
    "sg:province":"NL",
    "sg:tags":[
        "water",
        "treatment"
    ],
    "wof:name":"Atlantic Technical Svc Ltd",
    "wof:placetype":"venue"
},
  "geometry": {"coordinates":[-52.9262084961,47.5237159729],"type":"Point"}
}