{
  "type": "Feature",
  "properties": {
    "addr:full":"970 Rue DE LA Concorde Saint-Romuald QC G6W 8A8",
    "addr:housenumber":"970",
    "addr:postcode":"g6w 8a8",
    "addr:street":"Rue De La Concorde",
    "iso:country":"CA",
    "sg:address":"970 Rue DE LA Concorde",
    "sg:city":"Saint-Romuald",
    "sg:classifiers":[
        {
            "category":"Education",
            "subcategory":"Vocational School",
            "type":"Public Place"
        }
    ],
    "sg:phone":"+1 418 834 4202",
    "sg:postcode":"G6W 8A8",
    "sg:province":"QC",
    "sg:tags":[
        "training",
        "computer"
    ],
    "wof:name":"Centre D'Informatique Applique",
    "wof:placetype":"venue"
},
  "geometry": {"coordinates":[-71.270256,46.728455],"type":"Point"}
}