{
  "type": "Feature",
  "properties": {
    "iso:country":"CA",
    "sg:address":"221 Ch Freeman",
    "sg:city":"Hull",
    "sg:classifiers":[
        {
            "category":"Wholesale",
            "subcategory":"Machinery & Supplies",
            "type":"Manufacturing & Wholesale Goods"
        }
    ],
    "sg:phone":"+1 819 246 7848",
    "sg:postcode":"J8Z 2A8",
    "sg:province":"QC",
    "sg:tags":[
        "equipment",
        "printing"
    ],
    "wof:name":"Techno-Pro Enr",
    "wof:placetype":"venue"
},
  "geometry": {"coordinates":[-75.7476654053,45.4722099304],"type":"Point"}
}