{
  "type": "Feature",
  "properties": {
    "addr:full":"75 Water St S Cambridge ON N1R 3C9",
    "addr:housenumber":"75",
    "addr:postcode":"n1r 3c9",
    "addr:street":"Water St S",
    "iso:country":"CA",
    "sg:address":"75 Water St S",
    "sg:city":"Cambridge",
    "sg:classifiers":[
        {
            "category":"Autos & Motor Vehicles",
            "subcategory":"Automobile Sales",
            "type":"Retail Goods"
        }
    ],
    "sg:phone":"+1 519 622 4955",
    "sg:postcode":"N1R 3C9",
    "sg:province":"ON",
    "sg:tags":[
        "car",
        "dealer"
    ],
    "wof:name":"Special Interest Automobiles",
    "wof:placetype":"venue"
},
  "geometry": {"coordinates":[-80.3152999878,43.355556488],"type":"Point"}
}