{
  "type": "Feature",
  "properties": {
    "addr:full":"4837 Albion Rd Gloucester ON K1X 1A3",
    "addr:housenumber":"4837",
    "addr:postcode":"k1x 1a3",
    "addr:street":"Albion Rd",
    "iso:country":"CA",
    "sg:address":"4837 Albion Rd",
    "sg:city":"Gloucester",
    "sg:classifiers":[
        {
            "category":"Shopping",
            "subcategory":"Bicycles & Sporting Goods",
            "type":"Retail Goods"
        }
    ],
    "sg:phone":"+1 613 822 8674",
    "sg:postcode":"K1X 1A3",
    "sg:province":"ON",
    "sg:tags":[
        "horse",
        "furnishing"
    ],
    "wof:name":"Gml Tack Shop",
    "wof:placetype":"venue"
},
  "geometry": {"coordinates":[-75.60799400000001,45.29377],"type":"Point"}
}