{
  "type": "Feature",
  "properties": {
    "iso:country":"CA",
    "sg:address":"309 2nd Ave E",
    "sg:city":"Lampman",
    "sg:classifiers":[
        {
            "category":"Health Services",
            "subcategory":"Clinic",
            "type":"Services"
        }
    ],
    "sg:phone":"+1 306 487 2561",
    "sg:postcode":"S0C 1N0",
    "sg:province":"SK",
    "wof:name":"Lampman Community Health Ctr",
    "wof:placetype":"venue"
},
  "geometry": {"coordinates":[-102.764145,49.377258],"type":"Point"}
}