{
  "type": "Feature",
  "properties": {
    "addr:full":"560 Boul Saint-Joseph O Drummondville QC J2E 1G4",
    "addr:housenumber":"560",
    "addr:postcode":"j2e 1g4",
    "addr:street":"Boul Saint-Joseph O",
    "iso:country":"CA",
    "sg:address":"560 Boul Saint-Joseph O",
    "sg:city":"Drummondville",
    "sg:classifiers":[
        {
            "category":"Shopping",
            "subcategory":"Bicycles & Sporting Goods",
            "type":"Retail Goods"
        }
    ],
    "sg:phone":"+1 819 475 9997",
    "sg:postcode":"J2E 1G4",
    "sg:province":"QC",
    "wof:name":"Aux Trois Archers",
    "wof:placetype":"venue"
},
  "geometry": {"coordinates":[-72.5146179199,45.8935089111],"type":"Point"}
}