{
  "type": "Feature",
  "properties": {
    "addr:full":"1475 2nd Ave E Owen Sound ON N4K 2J6",
    "addr:housenumber":"1475",
    "addr:postcode":"n4k 2j6",
    "addr:street":"2Nd Ave E",
    "iso:country":"CA",
    "sg:address":"1475 2nd Ave E",
    "sg:city":"Owen Sound",
    "sg:classifiers":[
        {
            "category":"Wholesale",
            "subcategory":"Electrical",
            "type":"Manufacturing & Wholesale Goods"
        }
    ],
    "sg:phone":"+1 519 376 4120",
    "sg:postcode":"N4K 2J6",
    "sg:province":"ON",
    "sg:tags":[
        "equipment",
        "electric",
        "supply"
    ],
    "wof:name":"Grey Bruce Electric Supply Ltd",
    "wof:placetype":"venue"
},
  "geometry": {"coordinates":[-80.93775177000001,44.5758781433],"type":"Point"}
}