{
  "type": "Feature",
  "properties": {
    "iso:country":"CA",
    "sg:address":"30 Caledonia Rd",
    "sg:city":"Dartmouth",
    "sg:classifiers":[
        {
            "category":"Organizations",
            "subcategory":"Non-profit Organization",
            "type":"Services"
        }
    ],
    "sg:phone":"+1 902 435 3204",
    "sg:postcode":"B2X 1K8",
    "sg:province":"NS",
    "sg:tags":[
        "charitable",
        "institution"
    ],
    "wof:name":"East Dartmouth Boys & Girls",
    "wof:placetype":"venue"
},
  "geometry": {"coordinates":[-63.575340271,44.6740112305],"type":"Point"}
}