{
  "type": "Feature",
  "properties": {
    "iso:country":"CA",
    "sg:address":"1000 S 14th Ave",
    "sg:city":"Golden",
    "sg:classifiers":[
        {
            "category":"Education",
            "subcategory":"School",
            "type":"Public Place"
        }
    ],
    "sg:phone":"+1 250 344 5513",
    "sg:postcode":"V0A 1H0",
    "sg:province":"BC",
    "wof:name":"Alexander Park Elementary",
    "wof:placetype":"venue"
},
  "geometry": {"coordinates":[-116.954048157,51.295085907],"type":"Point"}
}