{
  "type": "Feature",
  "properties": {
    "addr:full":"117 Heath St W Toronto ON M4V 2Y6",
    "addr:housenumber":"117",
    "addr:postcode":"m4v 2y6",
    "addr:street":"Heath St W",
    "iso:country":"CA",
    "sg:address":"117 Heath St W",
    "sg:city":"Toronto",
    "sg:classifiers":[
        {
            "category":"Professional",
            "type":"Services"
        }
    ],
    "sg:phone":"+1 416 944 3282",
    "sg:postcode":"M4V 2Y6",
    "sg:province":"ON",
    "sg:tags":[
        "consultant",
        "management",
        "establishment",
        "business"
    ],
    "wof:name":"Rnm Enterprises",
    "wof:placetype":"venue"
},
  "geometry": {"coordinates":[-79.400955,43.688835],"type":"Point"}
}