{
  "type": "Feature",
  "properties": {
    "addr:full":"522 Ritson Rd S Oshawa ON L1H 5K4",
    "addr:housenumber":"522",
    "addr:postcode":"l1h 5k4",
    "addr:street":"Ritson Rd",
    "iso:country":"CA",
    "sg:address":"522 Ritson Rd S",
    "sg:city":"Oshawa",
    "sg:classifiers":[
        {
            "category":"Restaurant",
            "type":"Food & Drink"
        }
    ],
    "sg:phone":"+1 905 434 1669",
    "sg:postcode":"L1H 5K4",
    "sg:province":"ON",
    "wof:name":"Down Omer Bar & Grill",
    "wof:placetype":"venue"
},
  "geometry": {"coordinates":[-78.84773300000001,43.886086],"type":"Point"}
}