{
  "type": "Feature",
  "properties": {
    "iso:country":"CA",
    "sg:address":"522 Ritson Rd S",
    "sg:city":"Oshawa",
    "sg:classifiers":[
        {
            "category":"Restaurant",
            "type":"Food & Drink"
        }
    ],
    "sg:phone":"+1 905 434 1669",
    "sg:postcode":"L1H 5K4",
    "sg:province":"ON",
    "wof:name":"Down Omer Bar & Grill",
    "wof:placetype":"venue"
},
  "geometry": {"coordinates":[-78.847733,43.886086],"type":"Point"}
}