{
  "type": "Feature",
  "properties": {
    "addr:full":"45 Summer St Summerside PE C1N 3H7",
    "addr:housenumber":"45",
    "addr:postcode":"c1n 3h7",
    "addr:street":"Summer St",
    "iso:country":"CA",
    "sg:address":"45 Summer St",
    "sg:city":"Summerside",
    "sg:classifiers":[
        {
            "category":"Government",
            "subcategory":"Office",
            "type":"Public Place"
        }
    ],
    "sg:phone":"+1 902 432 1244",
    "sg:postcode":"C1N 3H7",
    "sg:province":"PE",
    "sg:tags":[
        "village"
    ],
    "wof:name":"Summerside Mayor's Office",
    "wof:placetype":"venue"
},
  "geometry": {"coordinates":[-63.7908096313,46.3930702209],"type":"Point"}
}