{
  "type": "Feature",
  "properties": {
    "addr:full":"2672 Danforth Ave Toronto ON M4C 1L7",
    "addr:housenumber":"2672",
    "addr:postcode":"m4c 1l7",
    "addr:street":"Danforth Ave",
    "iso:country":"CA",
    "sg:address":"2672 Danforth Ave",
    "sg:city":"Toronto",
    "sg:classifiers":[
        {
            "category":"Home & Garden",
            "subcategory":"Building Materials",
            "type":"Retail Goods"
        }
    ],
    "sg:phone":"+1 416 699 2669",
    "sg:postcode":"M4C 1L7",
    "sg:province":"ON",
    "sg:tags":[
        "paint"
    ],
    "wof:name":"Cook's Wallpaper & Paints",
    "wof:placetype":"venue"
},
  "geometry": {"coordinates":[-79.299103,43.688889],"type":"Point"}
}