{
  "type": "Feature",
  "properties": {
    "addr:full":"850 Rue Des Calfats Levis QC G6V 9E6",
    "addr:housenumber":"850",
    "addr:postcode":"g6v 9e6",
    "addr:street":"Rue Des Calfats",
    "iso:country":"CA",
    "sg:address":"850 Rue Des Calfats",
    "sg:city":"Levis",
    "sg:classifiers":[
        {
            "category":"Building & Trades",
            "subcategory":"Construction",
            "type":"Services"
        }
    ],
    "sg:phone":"+1 418 835 5588",
    "sg:postcode":"G6V 9E6",
    "sg:province":"QC",
    "sg:tags":[
        "maker",
        "cabinet"
    ],
    "wof:name":"Ebenisterie Fabrica Inc",
    "wof:placetype":"venue"
},
  "geometry": {"coordinates":[-71.12447400000001,46.819744],"type":"Point"}
}