{
  "type": "Feature",
  "properties": {
    "iso:country":"CA",
    "sg:city":"Sainte-Foy",
    "sg:classifiers":[
        {
            "category":"Shopping",
            "subcategory":"Computers & Home Electronics",
            "type":"Retail Goods"
        }
    ],
    "sg:phone":"+1 418 650 2875",
    "sg:postcode":"G1P 4P3",
    "sg:province":"QC",
    "sg:tags":[
        "software"
    ],
    "wof:name":"Ctrl Informatique Ltee",
    "wof:placetype":"venue"
},
  "geometry": {"coordinates":[-71.311165,46.793739],"type":"Point"}
}