{
  "type": "Feature",
  "properties": {
    "iso:country":"CA",
    "sg:city":"Vercheres",
    "sg:classifiers":[
        {
            "category":"Building & Trades",
            "subcategory":"Landscaping Services",
            "type":"Services"
        }
    ],
    "sg:phone":"+1 450 583 0007",
    "sg:postcode":"J0L 2R0",
    "sg:province":"QC",
    "sg:tags":[
        "lawn",
        "maintenance",
        "grounds"
    ],
    "wof:name":"Bo-Gars-Zons",
    "wof:placetype":"venue"
},
  "geometry": {"coordinates":[-73.362495,45.770893],"type":"Point"}
}