{
  "type": "Feature",
  "properties": {
    "addr:full":"44 Rue Gratton Sainte-Therese QC J7E 3B2",
    "addr:housenumber":"44",
    "addr:postcode":"j7e 3b2",
    "addr:street":"Rue Gratton Sainte-Therese",
    "iso:country":"CA",
    "sg:address":"44 Rue Gratton",
    "sg:city":"Sainte-Therese",
    "sg:classifiers":[
        {
            "category":"Bus Charters",
            "type":"Transportation"
        }
    ],
    "sg:phone":"+1 450 971 1900",
    "sg:postcode":"J7E 3B2",
    "sg:province":"QC",
    "sg:tags":[
        "rental"
    ],
    "wof:name":"Autocar Preference Coaches",
    "wof:placetype":"venue"
},
  "geometry": {"coordinates":[-73.825264,45.633297],"type":"Point"}
}