{
  "type": "Feature",
  "properties": {
    "addr:full":"210 - 131 Water St. Vancouver V6B 4M3",
    "addr:housenumber":"131",
    "addr:postcode":"v6b 4m3",
    "addr:street":"Water St.",
    "iso:country":"CA",
    "sg:address":"210 - 131 Water St.",
    "sg:city":"Vancouver",
    "sg:classifiers":[
        {
            "category":"Professional",
            "subcategory":"Computer Services",
            "type":"Services"
        }
    ],
    "sg:postcode":"V6B 4M3",
    "sg:tags":[
        "conference-registration"
    ],
    "sg:website":"http://attendease.com",
    "wof:name":"AttendEase",
    "wof:placetype":"venue"
},
  "geometry": {"coordinates":[-123.106786,49.283957],"type":"Point"}
}