{
  "type": "Feature",
  "properties": {
    "addr:full":"1300 Selby St Nelson BC V1L 2W3",
    "addr:housenumber":"1300",
    "addr:postcode":"bc v1l 2w3",
    "addr:street":"Selby St",
    "iso:country":"CA",
    "sg:address":"1300 Selby St",
    "sg:city":"Nelson",
    "sg:classifiers":[
        {
            "category":"Building & Trades",
            "subcategory":"Construction",
            "type":"Services"
        }
    ],
    "sg:phone":"+1 250 352 9805",
    "sg:postcode":"V1L 2W3",
    "sg:province":"BC",
    "sg:tags":[
        "painter"
    ],
    "wof:name":"Guy Burton Painting",
    "wof:placetype":"venue"
},
  "geometry": {"coordinates":[-117.280449,49.494175],"type":"Point"}
}