{
  "type": "Feature",
  "properties": {
    "addr:full":"414 Main St Selkirk MB R1A 1V3",
    "addr:housenumber":"414",
    "addr:postcode":"r1a 1v3",
    "addr:street":"Main St",
    "iso:country":"CA",
    "sg:address":"414 Main St",
    "sg:city":"Selkirk",
    "sg:classifiers":[
        {
            "category":"Restaurant",
            "type":"Food & Drink"
        }
    ],
    "sg:phone":"+1 204 482 6464",
    "sg:postcode":"R1A 1V3",
    "sg:province":"MB",
    "sg:tags":[
        "caterer"
    ],
    "wof:name":"Baker Boy Catering",
    "wof:placetype":"venue"
},
  "geometry": {"coordinates":[-96.872253,50.1451],"type":"Point"}
}