{
  "type": "Feature",
  "properties": {
    "iso:country":"CA",
    "sg:address":"1071 Bathurst St",
    "sg:city":"Toronto",
    "sg:classifiers":[
        {
            "category":"Shopping",
            "type":"Retail Goods"
        }
    ],
    "sg:phone":"+1 416 588 8801",
    "sg:postcode":"M5R 3G8",
    "sg:province":"ON",
    "sg:tags":[
        "art",
        "gallery",
        "dealer"
    ],
    "wof:name":"Creative Spirit Art Ctr",
    "wof:placetype":"venue"
},
  "geometry": {"coordinates":[-79.41389465330001,43.6724395752],"type":"Point"}
}