{
  "type": "Feature",
  "properties": {
    "addr:full":"1071 Bathurst St Toronto ON M5R 3G8",
    "addr:housenumber":"1071",
    "addr:postcode":"m5r 3g8",
    "addr:street":"Bathurst St",
    "iso:country":"CA",
    "sg:address":"1071 Bathurst St",
    "sg:city":"Toronto",
    "sg:classifiers":[
        {
            "category":"Shopping",
            "type":"Retail Goods"
        }
    ],
    "sg:phone":"+1 416 588 8801",
    "sg:postcode":"M5R 3G8",
    "sg:province":"ON",
    "sg:tags":[
        "art",
        "gallery",
        "dealer"
    ],
    "wof:name":"Creative Spirit Art Ctr",
    "wof:placetype":"venue"
},
  "geometry": {"coordinates":[-79.41389465330001,43.6724395752],"type":"Point"}
}