{
  "type": "Feature",
  "properties": {
    "addr:full":"209 Rue DE Woodstock Saint-Lambert QC J4P 1W7",
    "addr:housenumber":"209",
    "addr:postcode":"j4p 1w7",
    "addr:street":"Rue De Woodstock",
    "iso:country":"CA",
    "sg:address":"209 Rue DE Woodstock",
    "sg:city":"Saint-Lambert",
    "sg:classifiers":[
        {
            "category":"Health Services",
            "subcategory":"Doctor",
            "type":"Services"
        }
    ],
    "sg:phone":"+1 450 466 8583",
    "sg:postcode":"J4P 1W7",
    "sg:province":"QC",
    "sg:tags":[
        "physician",
        "surgeon"
    ],
    "wof:name":"Lambert, Jacques MD",
    "wof:placetype":"venue"
},
  "geometry": {"coordinates":[-73.5097961426,45.5005569458],"type":"Point"}
}