{
  "type": "Feature",
  "properties": {
    "iso:country":"CA",
    "sg:address":"872 Rue DE LA Station",
    "sg:city":"Prevost",
    "sg:classifiers":[
        {
            "category":"Health Services",
            "subcategory":"Nursing And Care Facility",
            "type":"Services"
        }
    ],
    "sg:phone":"+1 450 224 4315",
    "sg:postcode":"J0R 1T0",
    "sg:province":"QC",
    "sg:tags":[
        "home",
        "retirement",
        "community"
    ],
    "wof:name":"Manoir L'Emeraude",
    "wof:placetype":"venue"
},
  "geometry": {"coordinates":[-74.07112884519999,45.874874115],"type":"Point"}
}