{
  "type": "Feature",
  "properties": {
    "iso:country":"CA",
    "sg:city":"Vancouver",
    "sg:classifiers":[
        {
            "category":"Professional",
            "subcategory":"Advertising",
            "type":"Services"
        }
    ],
    "sg:phone":"+1 604 688 2441",
    "sg:postcode":"V6B 4M9",
    "sg:province":"BC",
    "sg:tags":[
        "counselor"
    ],
    "wof:name":"Tmp Worldwide",
    "wof:placetype":"venue"
},
  "geometry": {"coordinates":[-123.115631103,49.281124115],"type":"Point"}
}