{
  "type": "Feature",
  "properties": {
    "addr:full":"95 Boul Labelle Sainte-Therese QC J7E 2X6",
    "addr:housenumber":"95",
    "addr:postcode":"j7e 2x6",
    "addr:street":"Boul Labelle Sainte-Therese",
    "iso:country":"CA",
    "sg:address":"95 Boul Labelle",
    "sg:city":"Sainte-Therese",
    "sg:classifiers":[
        {
            "category":"Shopping",
            "subcategory":"Photographic Equipment",
            "type":"Retail Goods"
        }
    ],
    "sg:phone":"+1 450 437 3113",
    "sg:postcode":"J7E 2X6",
    "sg:province":"QC",
    "sg:tags":[
        "photo",
        "finishing"
    ],
    "wof:name":"Camera Expert",
    "wof:placetype":"venue"
},
  "geometry": {"coordinates":[-73.834419,45.643536],"type":"Point"}
}