{
  "type": "Feature",
  "properties": {
    "addr:full":"894 Westminster Ave Winnipeg MB R3G 1B5",
    "addr:housenumber":"894",
    "addr:postcode":"r3g 1b5",
    "addr:street":"Westminster Ave",
    "iso:country":"CA",
    "sg:address":"894 Westminster Ave",
    "sg:city":"Winnipeg",
    "sg:classifiers":[
        {
            "category":"Food & Beverages",
            "subcategory":"Groceries & Convenience Stores",
            "type":"Retail Goods"
        }
    ],
    "sg:phone":"+1 204 783 0162",
    "sg:postcode":"R3G 1B5",
    "sg:province":"MB",
    "sg:tags":[
        "grocer"
    ],
    "wof:name":"Global Food Mart",
    "wof:placetype":"venue"
},
  "geometry": {"coordinates":[-97.17205800000001,49.881523],"type":"Point"}
}