{
  "type": "Feature",
  "properties": {
    "addr:full":"4228 46 Ave Rocky Mountain House AB T4T 1B1",
    "addr:housenumber":"4228",
    "addr:postcode":"t4t 1b1",
    "addr:street":"46 Ave",
    "iso:country":"CA",
    "sg:address":"4228 46 Ave",
    "sg:city":"Rocky Mountain House",
    "sg:classifiers":[
        {
            "category":"Retail",
            "subcategory":"Auto Repair",
            "type":"Services"
        }
    ],
    "sg:phone":"+1 403 845 4505",
    "sg:postcode":"T4T 1B1",
    "sg:province":"AB",
    "sg:tags":[
        "repairing",
        "automobile"
    ],
    "wof:name":"Barbaric 4X4 & Auto Repair",
    "wof:placetype":"venue"
},
  "geometry": {"coordinates":[-114.90284699999999,52.369698],"type":"Point"}
}