{
  "type": "Feature",
  "properties": {
    "addr:full":"117 Kennedy Rd S Brampton ON L6W 3G3",
    "addr:housenumber":"117",
    "addr:postcode":"l6w 3g3",
    "addr:street":"Kennedy Rd S",
    "iso:country":"CA",
    "sg:address":"117 Kennedy Rd S",
    "sg:city":"Brampton",
    "sg:classifiers":[
        {
            "category":"Retail",
            "subcategory":"Auto Rental",
            "type":"Services"
        }
    ],
    "sg:phone":"+1 905 453 4099",
    "sg:postcode":"L6W 3G3",
    "sg:province":"ON",
    "sg:tags":[
        "renting",
        "automobile",
        "leasing",
        "truck"
    ],
    "wof:name":"Hertz Rent A Car",
    "wof:placetype":"venue"
},
  "geometry": {"coordinates":[-79.7369384766,43.6861038208],"type":"Point"}
}