{
  "type": "Feature",
  "properties": {
    "addr:full":"Montreal QC H2Z 1S8",
    "addr:postcode":"h2z 1s8",
    "iso:country":"CA",
    "sg:city":"Montreal",
    "sg:classifiers":[
        {
            "category":"Restaurant",
            "type":"Food & Drink"
        }
    ],
    "sg:phone":"+1 514 871 1777",
    "sg:postcode":"H2Z 1S8",
    "sg:province":"QC",
    "wof:name":"Cafe Trattoria Pane E Vino",
    "wof:placetype":"venue"
},
  "geometry": {"coordinates":[-73.5652084351,45.5023918152],"type":"Point"}
}