{
  "type": "Feature",
  "properties": {
    "addr:full":"1525 Rue King E Fleurimont QC J1G 1E8",
    "addr:housenumber":"1525",
    "addr:postcode":"j1g 1e8",
    "addr:street":"Rue King E Fleurimont",
    "iso:country":"CA",
    "sg:address":"1525 Rue King E",
    "sg:city":"Fleurimont",
    "sg:classifiers":[
        {
            "category":"Social Services",
            "subcategory":"Child Care",
            "type":"Services"
        }
    ],
    "sg:phone":"+1 819 346 1944",
    "sg:postcode":"J1G 1E8",
    "sg:province":"QC",
    "wof:name":"Cpe Fleurimont",
    "wof:placetype":"venue"
},
  "geometry": {"coordinates":[-71.8533706665,45.4089393616],"type":"Point"}
}