{
  "type": "Feature",
  "properties": {
    "addr:full":"915 Rue Commerciale Saint-Jean-Chrysostome QC G6Z 2E4",
    "addr:housenumber":"915",
    "addr:postcode":"g6z 2e4",
    "addr:street":"Rue Commerciale Saint-Jean-Chrysostome",
    "iso:country":"CA",
    "sg:address":"915 Rue Commerciale",
    "sg:city":"Saint-Jean-Chrysostome",
    "sg:classifiers":[
        {
            "category":"Restaurant",
            "type":"Food & Drink"
        }
    ],
    "sg:phone":"+1 418 839 3560",
    "sg:postcode":"G6Z 2E4",
    "sg:province":"QC",
    "wof:name":"Petit Castor Enr",
    "wof:placetype":"venue"
},
  "geometry": {"coordinates":[-71.200928,46.723511],"type":"Point"}
}