{
  "type": "Feature",
  "properties": {
    "addr:full":"Abbotsford BC V2S 3E5",
    "addr:postcode":"v2s 3e5",
    "iso:country":"CA",
    "sg:city":"Abbotsford",
    "sg:classifiers":[
        {
            "category":"Retail",
            "subcategory":"Animal Services",
            "type":"Services"
        }
    ],
    "sg:phone":"+1 604 850 1213",
    "sg:postcode":"V2S 3E5",
    "sg:province":"BC",
    "sg:tags":[
        "pet",
        "grooming",
        "washing"
    ],
    "wof:name":"Danielle's Dog Grooming Salon",
    "wof:placetype":"venue"
},
  "geometry": {"coordinates":[-122.304169,49.048927],"type":"Point"}
}