{
  "type": "Feature",
  "properties": {
    "addr:full":"92 Myrtle Ave Yorkton SK S3N 1P7",
    "addr:housenumber":"92",
    "addr:postcode":"s3n 1p7",
    "addr:street":"Myrtle Ave",
    "iso:country":"CA",
    "sg:address":"92 Myrtle Ave",
    "sg:city":"Yorkton",
    "sg:classifiers":[
        {
            "category":"Wholesale",
            "subcategory":"Machinery & Supplies",
            "type":"Manufacturing & Wholesale Goods"
        }
    ],
    "sg:phone":"+1 306 782 2704",
    "sg:postcode":"S3N 1P7",
    "sg:province":"SK",
    "sg:tags":[
        "contractor"
    ],
    "wof:name":"Triod Supply Ltd",
    "wof:placetype":"venue"
},
  "geometry": {"coordinates":[-102.465729,51.213306],"type":"Point"}
}