{
  "type": "Feature",
  "properties": {
    "addr:full":"Calgary AB T2S 2T2",
    "addr:postcode":"t2s 2t2",
    "iso:country":"CA",
    "sg:city":"Calgary",
    "sg:classifiers":[
        {
            "category":"Social Services",
            "subcategory":"Child Care",
            "type":"Services"
        }
    ],
    "sg:phone":"+1 403 262 5692",
    "sg:postcode":"T2S 2T2",
    "sg:province":"AB",
    "wof:name":"Cross Cultural Childrens Ctr",
    "wof:placetype":"venue"
},
  "geometry": {"coordinates":[-114.064217,51.038033],"type":"Point"}
}