{
  "type": "Feature",
  "properties": {
    "iso:country":"CA",
    "sg:address":"289 Third Ave N",
    "sg:city":"Williams Lake",
    "sg:classifiers":[
        {
            "category":"Restaurant",
            "type":"Food & Drink"
        }
    ],
    "sg:phone":"+1 250 398 2275",
    "sg:postcode":"V2G 2A6",
    "sg:province":"BC",
    "wof:name":"Flavours",
    "wof:placetype":"venue"
},
  "geometry": {"coordinates":[-122.143981934,52.1330566406],"type":"Point"}
}