{
  "type": "Feature",
  "properties": {
    "addr:full":"Embro ON N0J 1J0",
    "addr:postcode":"n0j 1j0",
    "iso:country":"CA",
    "sg:city":"Embro",
    "sg:classifiers":[
        {
            "category":"Professional",
            "subcategory":"Business Services",
            "type":"Services"
        }
    ],
    "sg:phone":"+1 519 475 4000",
    "sg:postcode":"N0J 1J0",
    "sg:province":"ON",
    "sg:tags":[
        "fund",
        "promotion",
        "raising"
    ],
    "wof:name":"Novus National Retail Svc Corp",
    "wof:placetype":"venue"
},
  "geometry": {"coordinates":[-80.9012374878,43.1561164856],"type":"Point"}
}