{
  "type": "Feature",
  "properties": {
    "addr:full":"369 Tupper St Hawkesbury ON K6A 3T6",
    "addr:housenumber":"369",
    "addr:postcode":"k6a 3t6",
    "addr:street":"Tupper St",
    "iso:country":"CA",
    "sg:address":"369 Tupper St",
    "sg:city":"Hawkesbury",
    "sg:classifiers":[
        {
            "category":"Retail",
            "subcategory":"Car Wash",
            "type":"Services"
        }
    ],
    "sg:phone":"+1 613 632 7324",
    "sg:postcode":"K6A 3T6",
    "sg:province":"ON",
    "sg:tags":[
        "polishing",
        "washing"
    ],
    "wof:name":"Bigras Car Wash",
    "wof:placetype":"venue"
},
  "geometry": {"coordinates":[-74.583611,45.605232],"type":"Point"}
}