{
  "type": "Feature",
  "properties": {
    "iso:country":"CA",
    "sg:address":"221 Adams Rd",
    "sg:city":"Kelowna",
    "sg:classifiers":[
        {
            "category":"Manufacturing",
            "subcategory":"Metals",
            "type":"Manufacturing & Wholesale Goods"
        }
    ],
    "sg:phone":"+1 250 765 5255",
    "sg:postcode":"V1X 7R1",
    "sg:province":"BC",
    "sg:tags":[
        "door"
    ],
    "wof:name":"Shanahan's Limited",
    "wof:placetype":"venue"
},
  "geometry": {"coordinates":[-119.389274597,49.9204177856],"type":"Point"}
}