{
  "type": "Feature",
  "properties": {
    "addr:full":"PO Box 327 Big Trout Lake ON P0V 1G0",
    "addr:housenumber":"po",
    "addr:postcode":"p0v 1g0",
    "addr:street":"Box 327;Trout",
    "iso:country":"CA",
    "sg:address":"PO Box 327",
    "sg:city":"Big Trout Lake",
    "sg:classifiers":[
        {
            "category":"Organizations",
            "subcategory":"Non-profit Organization",
            "type":"Services"
        }
    ],
    "sg:phone":"+1 807 537 2265",
    "sg:postcode":"P0V 1G0",
    "sg:province":"ON",
    "sg:tags":[
        "addiction",
        "treatment",
        "center"
    ],
    "wof:name":"Big Trout Lake First Nation",
    "wof:placetype":"venue"
},
  "geometry": {"coordinates":[-89.8350906372,53.8187599182],"type":"Point"}
}