{
  "type": "Feature",
  "properties": {
    "addr:full":"77 Rue DE LA Lumiere Baie-Saint-Paul QC G3Z 1Z1",
    "addr:housenumber":"77",
    "addr:postcode":"g3z 1z1",
    "addr:street":"Rue De La Lumiere",
    "iso:country":"CA",
    "sg:address":"77 Rue DE LA Lumiere",
    "sg:city":"Baie-Saint-Paul",
    "sg:classifiers":[
        {
            "category":"Shopping",
            "subcategory":"Computers & Home Electronics",
            "type":"Retail Goods"
        }
    ],
    "sg:phone":"+1 418 435 2474",
    "sg:postcode":"G3Z 1Z1",
    "sg:province":"QC",
    "sg:tags":[
        "radio",
        "television",
        "video",
        "equipment"
    ],
    "wof:name":"Baie St-Paul Radio Tv",
    "wof:placetype":"venue"
},
  "geometry": {"coordinates":[-70.521873,47.436951],"type":"Point"}
}