{
  "type": "Feature",
  "properties": {
    "addr:full":"540 Newbold St London ON N6E 2S5",
    "addr:housenumber":"540",
    "addr:postcode":"n6e 2s5",
    "addr:street":"Newbold St",
    "iso:country":"CA",
    "sg:address":"540 Newbold St",
    "sg:city":"London",
    "sg:classifiers":[
        {
            "category":"Wholesale",
            "subcategory":"Electrical",
            "type":"Manufacturing & Wholesale Goods"
        }
    ],
    "sg:phone":"+1 519 681 6600",
    "sg:postcode":"N6E 2S5",
    "sg:province":"ON",
    "sg:tags":[
        "transmission",
        "bearing",
        "power",
        "equipment"
    ],
    "wof:name":"Bdi Canada Inc",
    "wof:placetype":"venue"
},
  "geometry": {"coordinates":[-81.205635,42.934891],"type":"Point"}
}