{
  "type": "Feature",
  "properties": {
    "addr:full":"20 Rue Des Ursulines Loretteville QC G2B 2V1",
    "addr:housenumber":"20",
    "addr:postcode":"g2b 2v1",
    "addr:street":"Rue Des Ursulines",
    "iso:country":"CA",
    "sg:address":"20 Rue Des Ursulines",
    "sg:city":"Loretteville",
    "sg:classifiers":[
        {
            "category":"Organizations",
            "subcategory":"Religious Organization",
            "type":"Services"
        }
    ],
    "sg:phone":"+1 418 842 1421",
    "sg:postcode":"G2B 2V1",
    "sg:province":"QC",
    "wof:name":"Soeurs Ursulines",
    "wof:placetype":"venue"
},
  "geometry": {"coordinates":[-71.352867,46.852737],"type":"Point"}
}