{
  "type": "Feature",
  "properties": {
    "addr:full":"155 2E Av Iberville QC J2X 2B2",
    "addr:housenumber":"155",
    "addr:postcode":"j2x 2b2",
    "addr:street":"2E Av",
    "iso:country":"CA",
    "sg:address":"155 2E Av",
    "sg:city":"Iberville",
    "sg:classifiers":[
        {
            "category":"Retail",
            "subcategory":"Auto Repair",
            "type":"Services"
        }
    ],
    "sg:phone":"+1 450 346 6486",
    "sg:postcode":"J2X 2B2",
    "sg:province":"QC",
    "sg:tags":[
        "repairing",
        "automobile",
        "brake"
    ],
    "wof:name":"Garage Andre Ruest Inc",
    "wof:placetype":"venue"
},
  "geometry": {"coordinates":[-73.23973846440001,45.3041038513],"type":"Point"}
}