{
  "type": "Feature",
  "properties": {
    "addr:full":"237 Auburn Dr Dartmouth NS B2W 6G2",
    "addr:housenumber":"237",
    "addr:postcode":"b2w 6g2",
    "addr:street":"Auburn Dr",
    "iso:country":"CA",
    "sg:address":"237 Auburn Dr",
    "sg:city":"Dartmouth",
    "sg:classifiers":[
        {
            "category":"Building & Trades",
            "subcategory":"Plumbing",
            "type":"Services"
        }
    ],
    "sg:phone":"+1 902 443 0015",
    "sg:postcode":"B2W 6G2",
    "sg:province":"NS",
    "sg:tags":[
        "cleaning",
        "boiler"
    ],
    "wof:name":"D & J Davidson Boiler Repairs",
    "wof:placetype":"venue"
},
  "geometry": {"coordinates":[-63.484032,44.689957],"type":"Point"}
}