{
  "type": "Feature",
  "properties": {
    "addr:full":"1130 Rue Deschaillons Sherbrooke QC J1G 1X7",
    "addr:housenumber":"1130",
    "addr:postcode":"j1g 1x7",
    "addr:street":"Rue Deschaillons",
    "iso:country":"CA",
    "sg:address":"1130 Rue Deschaillons",
    "sg:city":"Sherbrooke",
    "sg:classifiers":[
        {
            "category":"Building & Trades",
            "subcategory":"Electrical",
            "type":"Services"
        }
    ],
    "sg:phone":"+1 819 564 1313",
    "sg:postcode":"J1G 1X7",
    "sg:province":"QC",
    "sg:tags":[
        "electric",
        "contractor"
    ],
    "wof:name":"Roland Veilleux Inc",
    "wof:placetype":"venue"
},
  "geometry": {"coordinates":[-71.863373,45.398903],"type":"Point"}
}