{
  "type": "Feature",
  "properties": {
    "addr:full":"Sudbury ON P3C 4Y9",
    "addr:postcode":"p3c 4y9",
    "iso:country":"CA",
    "sg:city":"Sudbury",
    "sg:classifiers":[
        {
            "category":"Professional",
            "subcategory":"Lawyer & Legal Services",
            "type":"Services"
        }
    ],
    "sg:phone":"+1 705 673 1200",
    "sg:postcode":"P3C 4Y9",
    "sg:province":"ON",
    "sg:tags":[
        "attorney"
    ],
    "wof:name":"Orendorff & Assoc",
    "wof:placetype":"venue"
},
  "geometry": {"coordinates":[-80.998268,46.493679],"type":"Point"}
}