{
  "type": "Feature",
  "properties": {
    "iso:country":"CA",
    "sg:address":"13484 24 Ave",
    "sg:city":"Surrey",
    "sg:classifiers":[
        {
            "category":"Education",
            "subcategory":"School",
            "type":"Public Place"
        }
    ],
    "sg:phone":"+1 604 538 6678",
    "sg:postcode":"V4A 2G5",
    "sg:province":"BC",
    "wof:name":"Elgin Park Secondary School",
    "wof:placetype":"venue"
},
  "geometry": {"coordinates":[-122.848548889,49.0456352234],"type":"Point"}
}