{
  "type": "Feature",
  "properties": {
    "iso:country":"CA",
    "sg:address":"123 Third Ave",
    "sg:city":"Timmins",
    "sg:classifiers":[
        {
            "category":"Manufacturing",
            "subcategory":"Tools & Machinery",
            "type":"Manufacturing & Wholesale Goods"
        }
    ],
    "sg:phone":"+1 705 267 6555",
    "sg:postcode":"P4N 1C6",
    "sg:province":"ON",
    "sg:tags":[
        "water",
        "pharmacy"
    ],
    "wof:name":"Vogl's Pharmacy",
    "wof:placetype":"venue"
},
  "geometry": {"coordinates":[-81.33190917970001,48.4747886658],"type":"Point"}
}