{
  "type": "Feature",
  "properties": {
    "addr:full":"3513 Dundas St W York ON M6S 2S6",
    "addr:housenumber":"3513",
    "addr:postcode":"m6s 2s6",
    "addr:street":"Dundas St W",
    "iso:country":"CA",
    "sg:address":"3513 Dundas St W",
    "sg:city":"York",
    "sg:classifiers":[
        {
            "category":"Restaurant",
            "type":"Food & Drink"
        }
    ],
    "sg:phone":"+1 416 762 0458",
    "sg:postcode":"M6S 2S6",
    "sg:province":"ON",
    "wof:name":"Texas Pit Restaurant",
    "wof:placetype":"venue"
},
  "geometry": {"coordinates":[-79.5056610107,43.6627502441],"type":"Point"}
}