{
  "type": "Feature",
  "properties": {
    "addr:full":"4200 49 Ave Innisfail AB T4G 1M6",
    "addr:housenumber":"4200",
    "addr:postcode":"t4g 1m6",
    "addr:street":"49 Ave",
    "iso:country":"CA",
    "sg:address":"4200 49 Ave",
    "sg:city":"Innisfail",
    "sg:classifiers":[
        {
            "category":"Retail",
            "subcategory":"Funeral Services",
            "type":"Services"
        }
    ],
    "sg:phone":"+1 403 227 3123",
    "sg:postcode":"T4G 1M6",
    "sg:province":"AB",
    "sg:tags":[
        "director",
        "crematory"
    ],
    "wof:name":"Metcalf Funeral Chapel",
    "wof:placetype":"venue"
},
  "geometry": {"coordinates":[-113.94684599999999,52.02029],"type":"Point"}
}