{
  "type": "Feature",
  "properties": {
    "addr:full":"615 Jack Ross Ave Woodstock ON N4V 1B7",
    "addr:housenumber":"615",
    "addr:postcode":"n4v 1b7",
    "addr:street":"Jack Ross Ave",
    "iso:country":"CA",
    "sg:address":"615 Jack Ross Ave",
    "sg:city":"Woodstock",
    "sg:classifiers":[
        {
            "category":"Manufacturing",
            "subcategory":"Food",
            "type":"Manufacturing & Wholesale Goods"
        }
    ],
    "sg:phone":"+1 519 537 3461",
    "sg:postcode":"N4V 1B7",
    "sg:province":"ON",
    "sg:tags":[
        "product",
        "manufacturer"
    ],
    "wof:name":"Kerry Canada Inc",
    "wof:placetype":"venue"
},
  "geometry": {"coordinates":[-80.720016,43.113335],"type":"Point"}
}