{
  "type": "Feature",
  "properties": {
    "addr:full":"755 St Mary's Rd Winnipeg MB R2M 3N6",
    "addr:housenumber":"755",
    "addr:postcode":"r2m 3n6",
    "addr:street":"St Mary'S Rd",
    "iso:country":"CA",
    "sg:address":"755 St Mary's Rd",
    "sg:city":"Winnipeg",
    "sg:classifiers":[
        {
            "category":"Insurance",
            "subcategory":"Insurance Agent",
            "type":"Services"
        }
    ],
    "sg:phone":"+1 204 256 4311",
    "sg:postcode":"R2M 3N6",
    "sg:province":"MB",
    "wof:name":"Ducharme Agencies Ltd",
    "wof:placetype":"venue"
},
  "geometry": {"coordinates":[-97.11167144780001,49.8541030884],"type":"Point"}
}