{
  "type": "Feature",
  "properties": {
    "addr:full":"Baie-Comeau QC G4Z 1R6",
    "addr:postcode":"g4z 1r6",
    "iso:country":"CA",
    "sg:city":"Baie-Comeau",
    "sg:classifiers":[
        {
            "category":"Professional",
            "subcategory":"Management & Consulting",
            "type":"Services"
        }
    ],
    "sg:phone":"+1 418 296 3633",
    "sg:postcode":"G4Z 1R6",
    "sg:province":"QC",
    "sg:tags":[
        "town",
        "city",
        "regional",
        "planner"
    ],
    "wof:name":"Societe D'Amenagement Rousseau",
    "wof:placetype":"venue"
},
  "geometry": {"coordinates":[-68.154121,49.220226],"type":"Point"}
}