{
  "type": "Feature",
  "properties": {
    "iso:country":"CA",
    "sg:city":"Delta",
    "sg:classifiers":[
        {
            "category":"Personal",
            "type":"Services"
        }
    ],
    "sg:phone":"+1 604 943 9677",
    "sg:postcode":"V4M 2B2",
    "sg:province":"BC",
    "sg:tags":[
        "therapist",
        "massage"
    ],
    "wof:name":"Tsawwassen Massage Therapy",
    "wof:placetype":"venue"
},
  "geometry": {"coordinates":[-123.074111938,49.0248641968],"type":"Point"}
}