{
  "type": "Feature",
  "properties": {
    "addr:full":"London ON N6G 3Y9",
    "addr:postcode":"n6g 3y9",
    "iso:country":"CA",
    "sg:city":"London",
    "sg:classifiers":[
        {
            "category":"Restaurant",
            "type":"Food & Drink"
        }
    ],
    "sg:phone":"+1 519 660 4379",
    "sg:postcode":"N6G 3Y9",
    "sg:province":"ON",
    "wof:name":"Manchu Wok",
    "wof:placetype":"venue"
},
  "geometry": {"coordinates":[-81.28170799999999,43.025272],"type":"Point"}
}