{
  "type": "Feature",
  "properties": {
    "addr:full":"RR 8 STN Main Lethbridge AB T1J 4P4",
    "addr:postcode":"t1j 4p4",
    "addr:street":"Rr 8 Stn Main",
    "iso:country":"CA",
    "sg:address":"RR 8 STN Main",
    "sg:city":"Lethbridge",
    "sg:classifiers":[
        {
            "category":"Organizations",
            "subcategory":"Professional Association",
            "type":"Services"
        }
    ],
    "sg:phone":"+1 403 328 6022",
    "sg:postcode":"T1J 4P4",
    "sg:province":"AB",
    "sg:tags":[
        "club"
    ],
    "wof:name":"Shrine Club Lethbridge",
    "wof:placetype":"venue"
},
  "geometry": {"coordinates":[-112.833740234,49.6938362122],"type":"Point"}
}