{
  "type": "Feature",
  "properties": {
    "addr:full":"Hythe AB T0H 2C0",
    "addr:postcode":"t0h 2c0",
    "iso:country":"CA",
    "sg:city":"Hythe",
    "sg:classifiers":[
        {
            "category":"Travel",
            "subcategory":"Hotels & Motels",
            "type":"Entertainment"
        }
    ],
    "sg:phone":"+1 780 356 2151",
    "sg:postcode":"T0H 2C0",
    "sg:province":"AB",
    "wof:name":"Hythe Motor Inn",
    "wof:placetype":"venue"
},
  "geometry": {"coordinates":[-119.562111,55.33316],"type":"Point"}
}