{
  "type": "Feature",
  "properties": {
    "addr:full":"1502 Brown St Regina SK S4N 4R6",
    "addr:housenumber":"1502",
    "addr:postcode":"s4n 4r6",
    "addr:street":"Brown St",
    "iso:country":"CA",
    "sg:address":"1502 Brown St",
    "sg:city":"Regina",
    "sg:classifiers":[
        {
            "category":"Professional",
            "subcategory":"Accounting & Tax Preparation",
            "type":"Services"
        }
    ],
    "sg:phone":"+1 306 789 2324",
    "sg:postcode":"S4N 4R6",
    "sg:province":"SK",
    "sg:tags":[
        "accountant"
    ],
    "wof:name":"Manual Accounting Systems",
    "wof:placetype":"venue"
},
  "geometry": {"coordinates":[-104.540741,50.454998],"type":"Point"}
}