{
  "type": "Feature",
  "properties": {
    "iso:country":"CA",
    "sg:address":"4011 Francis Rd",
    "sg:city":"Richmond",
    "sg:classifiers":[
        {
            "category":"Autos & Motor Vehicles",
            "subcategory":"Fuel & Gas Station",
            "type":"Retail Goods"
        }
    ],
    "sg:phone":"+1 604 277 3620",
    "sg:postcode":"V7C 1J8",
    "sg:province":"BC",
    "sg:tags":[
        "repairing",
        "automobile",
        "oil"
    ],
    "wof:name":"Seafair Service Ctr",
    "wof:placetype":"venue"
},
  "geometry": {"coordinates":[-123.180771,49.148468],"type":"Point"}
}