{
  "type": "Feature",
  "properties": {
    "addr:full":"736 Sixth Ave New Westminster BC V3M 2B4",
    "addr:housenumber":"736",
    "addr:postcode":"v3m 2b4",
    "addr:street":"Sixth Ave",
    "iso:country":"CA",
    "sg:address":"736 Sixth Ave",
    "sg:city":"New Westminster",
    "sg:classifiers":[
        {
            "category":"Retail",
            "subcategory":"Car Wash",
            "type":"Services"
        }
    ],
    "sg:phone":"+1 604 525 6682",
    "sg:postcode":"V3M 2B4",
    "sg:province":"BC",
    "sg:tags":[
        "polishing",
        "washing"
    ],
    "wof:name":"Moody Park Esso",
    "wof:placetype":"venue"
},
  "geometry": {"coordinates":[-122.92248499999999,49.2118],"type":"Point"}
}