{
  "type": "Feature",
  "properties": {
    "addr:full":"2485 King George Hwy # 15 Miramichi NB E1V 6W3",
    "addr:housenumber":"2485;15",
    "addr:postcode":"e1v 6w3",
    "addr:street":"King George Hwy #",
    "iso:country":"CA",
    "sg:address":"2485 King George Hwy # 15",
    "sg:city":"Miramichi",
    "sg:classifiers":[
        {
            "category":"Shopping",
            "subcategory":"Books",
            "type":"Retail Goods"
        }
    ],
    "sg:phone":"+1 506 773 9515",
    "sg:postcode":"E1V 6W3",
    "sg:province":"NB",
    "sg:tags":[
        "dealer"
    ],
    "wof:name":"Son-Light Christian Book Store",
    "wof:placetype":"venue"
},
  "geometry": {"coordinates":[-65.4898757935,47.0308265686],"type":"Point"}
}