{
  "type": "Feature",
  "properties": {
    "addr:full":"123 Monticello Rd Winnipeg MB R3Y 1L5",
    "addr:housenumber":"123",
    "addr:postcode":"r3y 1l5",
    "addr:street":"Monticello Rd",
    "iso:country":"CA",
    "sg:address":"123 Monticello Rd",
    "sg:city":"Winnipeg",
    "sg:classifiers":[
        {
            "category":"Professional",
            "subcategory":"Management & Consulting",
            "type":"Services"
        }
    ],
    "sg:phone":"+1 204 487 2876",
    "sg:postcode":"R3Y 1L5",
    "sg:province":"MB",
    "sg:tags":[
        "consultant",
        "business"
    ],
    "wof:name":"Millennium 3 Inc",
    "wof:placetype":"venue"
},
  "geometry": {"coordinates":[-97.20928955079999,49.8107185364],"type":"Point"}
}