{
  "type": "Feature",
  "properties": {
    "addr:full":"340 Wilson Ave Burlington ON L7L 2M9",
    "addr:housenumber":"340",
    "addr:postcode":"l7l 2m9",
    "addr:street":"Wilson Ave",
    "iso:country":"CA",
    "sg:address":"340 Wilson Ave",
    "sg:city":"Burlington",
    "sg:classifiers":[
        {
            "category":"Personal",
            "subcategory":"Beauty Salon",
            "type":"Services"
        }
    ],
    "sg:phone":"+1 905 634 3024",
    "sg:postcode":"L7L 2M9",
    "sg:province":"ON",
    "wof:name":"Soul Retreat",
    "wof:placetype":"venue"
},
  "geometry": {"coordinates":[-79.7555236816,43.3597297668],"type":"Point"}
}