{
  "type": "Feature",
  "properties": {
    "addr:full":"Bay Roberts NL A0A 1G0",
    "addr:postcode":"a0a 1g0",
    "iso:country":"CA",
    "sg:city":"Bay Roberts",
    "sg:classifiers":[
        {
            "category":"Education",
            "subcategory":"Vocational School",
            "type":"Public Place"
        }
    ],
    "sg:phone":"+1 709 786 2400",
    "sg:postcode":"A0A 1G0",
    "sg:province":"NL",
    "sg:tags":[
        "technical",
        "instruction",
        "driving",
        "trade"
    ],
    "wof:name":"Canadian Training Institute",
    "wof:placetype":"venue"
},
  "geometry": {"coordinates":[-53.2815093994,47.5839805603],"type":"Point"}
}