{
  "type": "Feature",
  "properties": {
    "addr:full":"5968 Bathurst St North York ON M2R 1Z1",
    "addr:housenumber":"5968",
    "addr:postcode":"m2r 1z1",
    "addr:street":"Bathurst St",
    "iso:country":"CA",
    "sg:address":"5968 Bathurst St",
    "sg:city":"North York",
    "sg:classifiers":[
        {
            "category":"Banks & Credit Unions",
            "subcategory":"Bank",
            "type":"Services"
        }
    ],
    "sg:phone":"+1 416 663 7620",
    "sg:postcode":"M2R 1Z1",
    "sg:province":"ON",
    "wof:name":"Royal Bank Financial Group",
    "wof:placetype":"venue"
},
  "geometry": {"coordinates":[-79.44589999999999,43.784637],"type":"Point"}
}