{
  "type": "Feature",
  "properties": {
    "addr:full":"Burnaby BC V5B 3M7",
    "addr:postcode":"v5b 3m7",
    "iso:country":"CA",
    "sg:city":"Burnaby",
    "sg:classifiers":[
        {
            "category":"Building & Trades",
            "subcategory":"Construction",
            "type":"Services"
        }
    ],
    "sg:phone":"+1 604 689 9928",
    "sg:postcode":"V5B 3M7",
    "sg:province":"BC",
    "sg:tags":[
        "resurfacing",
        "laying",
        "refinishing",
        "floor"
    ],
    "wof:name":"B C Floor Covering Assn",
    "wof:placetype":"venue"
},
  "geometry": {"coordinates":[-122.987038,49.264347],"type":"Point"}
}