{
  "type": "Feature",
  "properties": {
    "iso:country":"CA",
    "sg:city":"St Stephen",
    "sg:classifiers":[
        {
            "category":"Manufacturing",
            "subcategory":"Lumber",
            "type":"Manufacturing & Wholesale Goods"
        }
    ],
    "sg:phone":"+1 506 466 5914",
    "sg:postcode":"E3L 1S8",
    "sg:province":"NB",
    "sg:tags":[
        "marketing",
        "consultant"
    ],
    "wof:name":"Ysc Forest Products Mktg",
    "wof:placetype":"venue"
},
  "geometry": {"coordinates":[-67.2591629028,45.191619873],"type":"Point"}
}