{
  "type": "Feature",
  "properties": {
    "addr:full":"6072 Rue Sherbrooke E Montreal QC H1N 1C1",
    "addr:housenumber":"6072",
    "addr:postcode":"h1n 1c1",
    "addr:street":"Rue Sherbrooke E",
    "iso:country":"CA",
    "sg:address":"6072 Rue Sherbrooke E",
    "sg:city":"Montreal",
    "sg:classifiers":[
        {
            "category":"Cinema",
            "subcategory":"Movie Rental",
            "type":"Entertainment"
        }
    ],
    "sg:phone":"+1 514 899 1570",
    "sg:postcode":"H1N 1C1",
    "sg:province":"QC",
    "sg:tags":[
        "leasing",
        "video",
        "disc",
        "tape"
    ],
    "wof:name":"Superclub Videotron Ltee",
    "wof:placetype":"venue"
},
  "geometry": {"coordinates":[-73.54573822019999,45.5778694153],"type":"Point"}
}