{
  "type": "Feature",
  "properties": {
    "addr:full":"Burlington ON L7L 6E9",
    "addr:postcode":"l7l 6e9",
    "iso:country":"CA",
    "sg:city":"Burlington",
    "sg:classifiers":[
        {
            "category":"Manufacturing",
            "subcategory":"Tools & Machinery",
            "type":"Manufacturing & Wholesale Goods"
        }
    ],
    "sg:phone":"+1 905 634 7022",
    "sg:postcode":"L7L 6E9",
    "sg:province":"ON",
    "sg:tags":[
        "incinerator"
    ],
    "wof:name":"Eco Waste Solutions",
    "wof:placetype":"venue"
},
  "geometry": {"coordinates":[-79.7626037598,43.3823547363],"type":"Point"}
}