{
  "type": "Feature",
  "properties": {
    "addr:full":"3732 10E Rang Lac-Megantic QC G6B 2S3",
    "addr:housenumber":"3732",
    "addr:postcode":"g6b 2s3",
    "addr:street":"10E Rang Lac-Megantic",
    "iso:country":"CA",
    "sg:address":"3732 10E Rang",
    "sg:city":"Lac-Megantic",
    "sg:classifiers":[
        {
            "category":"Manufacturing",
            "subcategory":"Lumber",
            "type":"Manufacturing & Wholesale Goods"
        }
    ],
    "sg:phone":"+1 819 583 1760",
    "sg:postcode":"G6B 2S3",
    "sg:province":"QC",
    "sg:tags":[
        "syrup",
        "maple",
        "sugar"
    ],
    "wof:name":"Cabane A Sucre Megantic",
    "wof:placetype":"venue"
},
  "geometry": {"coordinates":[-70.880173,45.572571],"type":"Point"}
}