{
  "type": "Feature",
  "properties": {
    "addr:full":"28 Rue Foch Saint-Jean-Sur-Richelieu QC J3B 2A3",
    "addr:housenumber":"28",
    "addr:postcode":"j3b 2a3",
    "addr:street":"Rue Foch",
    "iso:country":"CA",
    "sg:address":"28 Rue Foch",
    "sg:city":"Saint-Jean-Sur-Richelieu",
    "sg:classifiers":[
        {
            "category":"Manufacturing",
            "subcategory":"Tools & Machinery",
            "type":"Manufacturing & Wholesale Goods"
        }
    ],
    "sg:phone":"+1 450 347 4148",
    "sg:postcode":"J3B 2A3",
    "sg:province":"QC",
    "sg:tags":[
        "machine",
        "shop"
    ],
    "wof:name":"Atelier DE Mecanique Durocher",
    "wof:placetype":"venue"
},
  "geometry": {"coordinates":[-73.2525253296,45.3091621399],"type":"Point"}
}