{
  "type": "Feature",
  "properties": {
    "addr:full":"106 Kensington Rd Charlottetown PE C1A 5J5",
    "addr:housenumber":"106",
    "addr:postcode":"c1a 5j5",
    "addr:street":"Kensington Rd",
    "iso:country":"CA",
    "sg:address":"106 Kensington Rd",
    "sg:city":"Charlottetown",
    "sg:classifiers":[
        {
            "category":"Building & Trades",
            "subcategory":"Electrical",
            "type":"Services"
        }
    ],
    "sg:phone":"+1 902 566 1532",
    "sg:postcode":"C1A 5J5",
    "sg:province":"PE",
    "sg:tags":[
        "electric",
        "contractor"
    ],
    "wof:name":"Hansen Electric Ltd",
    "wof:placetype":"venue"
},
  "geometry": {"coordinates":[-63.115192,46.253689],"type":"Point"}
}