{
  "type": "Feature",
  "properties": {
    "addr:full":"Saint-Laurent QC H4M 2V2",
    "addr:postcode":"h4m 2v2",
    "iso:country":"CA",
    "sg:city":"Saint-Laurent",
    "sg:classifiers":[
        {
            "category":"Insurance",
            "subcategory":"Insurance Agent",
            "type":"Services"
        }
    ],
    "sg:phone":"+1 514 333 4630",
    "sg:postcode":"H4M 2V2",
    "sg:province":"QC",
    "wof:name":"Courtiers D'Assurance L",
    "wof:placetype":"venue"
},
  "geometry": {"coordinates":[-73.6998214722,45.4961509705],"type":"Point"}
}