{
  "type": "Feature",
  "properties": {
    "addr:full":"902 Mckay Rd Pickering ON L1W 3X8",
    "addr:housenumber":"902",
    "addr:postcode":"l1w 3x8",
    "addr:street":"Mckay Rd",
    "iso:country":"CA",
    "sg:address":"902 Mckay Rd",
    "sg:city":"Pickering",
    "sg:classifiers":[
        {
            "category":"Manufacturing",
            "subcategory":"Tools & Machinery",
            "type":"Manufacturing & Wholesale Goods"
        }
    ],
    "sg:phone":"+1 905 428 6387",
    "sg:postcode":"L1W 3X8",
    "sg:province":"ON",
    "sg:tags":[
        "mold"
    ],
    "wof:name":"Msb Industries Inc",
    "wof:placetype":"venue"
},
  "geometry": {"coordinates":[-79.04993399999999,43.821915],"type":"Point"}
}