{
  "type": "Feature",
  "properties": {
    "addr:full":"1173 2nd Ave E Owen Sound ON N4K 2J1",
    "addr:housenumber":"1173",
    "addr:postcode":"n4k 2j1",
    "addr:street":"2Nd Ave E",
    "iso:country":"CA",
    "sg:address":"1173 2nd Ave E",
    "sg:city":"Owen Sound",
    "sg:classifiers":[
        {
            "category":"Taxi",
            "type":"Transportation"
        }
    ],
    "sg:phone":"+1 519 376 5050",
    "sg:postcode":"N4K 2J1",
    "sg:province":"ON",
    "sg:tags":[
        "taxicab"
    ],
    "wof:name":"Red Line Taxi",
    "wof:placetype":"venue"
},
  "geometry": {"coordinates":[-80.94078063960001,44.5712471008],"type":"Point"}
}