{
  "type": "Feature",
  "properties": {
    "addr:full":"PO Box 324 Wildwood AB T0E 2M0",
    "addr:housenumber":"po",
    "addr:postcode":"t0e 2m0",
    "addr:street":"Box 324",
    "iso:country":"CA",
    "sg:address":"PO Box 324",
    "sg:city":"Wildwood",
    "sg:classifiers":[
        {
            "category":"Mining & Drilling",
            "type":"Manufacturing & Wholesale Goods"
        }
    ],
    "sg:phone":"+1 780 795 2395",
    "sg:postcode":"T0E 2M0",
    "sg:province":"AB",
    "sg:tags":[
        "field",
        "oil"
    ],
    "wof:name":"Lea-Man Svc Ltd",
    "wof:placetype":"venue"
},
  "geometry": {"coordinates":[-115.23608400000001,53.604092],"type":"Point"}
}