{
  "type": "Feature",
  "properties": {
    "addr:full":"Jasper AB T0E 1E0",
    "addr:postcode":"t0e 1e0",
    "iso:country":"CA",
    "sg:city":"Jasper",
    "sg:classifiers":[
        {
            "category":"Shopping",
            "subcategory":"Jewelry",
            "type":"Retail Goods"
        }
    ],
    "sg:phone":"+1 780 852 3631",
    "sg:postcode":"T0E 1E0",
    "sg:province":"AB",
    "sg:tags":[
        "shop",
        "gift"
    ],
    "wof:name":"Jasper Rock & Jade Shop",
    "wof:placetype":"venue"
},
  "geometry": {"coordinates":[-118.080437,52.875965],"type":"Point"}
}