{
  "type": "Feature",
  "properties": {
    "addr:full":"Winnipeg MB R2K 3Z2",
    "addr:postcode":"r2k 3z2",
    "iso:country":"CA",
    "sg:city":"Winnipeg",
    "sg:classifiers":[
        {
            "category":"Real Estate",
            "subcategory":"Real Estate Operator",
            "type":"Services"
        }
    ],
    "sg:phone":"+1 204 669 0754",
    "sg:postcode":"R2K 3Z2",
    "sg:province":"MB",
    "sg:tags":[
        "apartment"
    ],
    "wof:name":"Kildonan Horizons Inc",
    "wof:placetype":"venue"
},
  "geometry": {"coordinates":[-97.0972900391,49.9177055359],"type":"Point"}
}