{
  "type": "Feature",
  "properties": {
    "addr:full":"Calgary AB T2E 6V2",
    "addr:postcode":"t2e 6v2",
    "iso:country":"CA",
    "sg:city":"Calgary",
    "sg:classifiers":[
        {
            "category":"Autos & Motor Vehicles",
            "subcategory":"Auto Supplies",
            "type":"Retail Goods"
        }
    ],
    "sg:phone":"+1 403 250 3195",
    "sg:postcode":"T2E 6V2",
    "sg:province":"AB",
    "sg:tags":[
        "automobile",
        "parts"
    ],
    "wof:name":"Calalta Automotive Supply Ltd",
    "wof:placetype":"venue"
},
  "geometry": {"coordinates":[-114.011543,51.086143],"type":"Point"}
}