{
  "type": "Feature",
  "properties": {
    "addr:full":"119 Donald St Belleville ON K8P 2J6",
    "addr:housenumber":"119",
    "addr:postcode":"k8p 2j6",
    "addr:street":"Donald St",
    "iso:country":"CA",
    "sg:address":"119 Donald St",
    "sg:city":"Belleville",
    "sg:classifiers":[
        {
            "category":"Organizations",
            "subcategory":"Religious Organization",
            "type":"Services"
        }
    ],
    "sg:phone":"+1 613 968 6829",
    "sg:postcode":"K8P 2J6",
    "sg:province":"ON",
    "sg:tags":[
        "church"
    ],
    "wof:name":"Holy Rosary Church",
    "wof:placetype":"venue"
},
  "geometry": {"coordinates":[-77.38649700000001,44.179241],"type":"Point"}
}