{
  "type": "Feature",
  "properties": {
    "iso:country":"CA",
    "sg:address":"3 Main St",
    "sg:city":"Barrington Passage",
    "sg:classifiers":[
        {
            "category":"Shopping",
            "subcategory":"Clothing, Apparel, & Fashions",
            "type":"Retail Goods"
        }
    ],
    "sg:phone":"+1 902 637 3762",
    "sg:postcode":"B0W 1G0",
    "sg:province":"NS",
    "sg:tags":[
        "infant",
        "wear"
    ],
    "wof:name":"Teener Totter Fashion",
    "wof:placetype":"venue"
},
  "geometry": {"coordinates":[-65.610458374,43.5258712769],"type":"Point"}
}