{
  "type": "Feature",
  "properties": {
    "addr:full":"999 36 St NE # 1075 Calgary AB T2A 7X6",
    "addr:housenumber":"36",
    "addr:postcode":"t2a 7x6",
    "addr:street":"999;St Ne # 1075",
    "iso:country":"CA",
    "sg:address":"999 36 St NE # 1075",
    "sg:city":"Calgary",
    "sg:classifiers":[
        {
            "category":"Shopping",
            "subcategory":"Used Merchandise",
            "type":"Retail Goods"
        }
    ],
    "sg:phone":"+1 403 735 3200",
    "sg:postcode":"T2A 7X6",
    "sg:province":"AB",
    "sg:tags":[
        "clothing"
    ],
    "wof:name":"Salvation Army Thrift Stores",
    "wof:placetype":"venue"
},
  "geometry": {"coordinates":[-113.982094,51.062008],"type":"Point"}
}