{
  "type": "Feature",
  "properties": {
    "iso:country":"CA",
    "sg:address":"1 Ferndale Dr N # 3",
    "sg:city":"Barrie",
    "sg:classifiers":[
        {
            "category":"Wholesale",
            "subcategory":"Electrical",
            "type":"Manufacturing & Wholesale Goods"
        }
    ],
    "sg:phone":"+1 705 720 2137",
    "sg:postcode":"L4N 9V3",
    "sg:province":"ON",
    "sg:tags":[
        "battery"
    ],
    "wof:name":"Battery House",
    "wof:placetype":"venue"
},
  "geometry": {"coordinates":[-79.714607,44.369873],"type":"Point"}
}