{
  "type": "Feature",
  "properties": {
    "iso:country":"CA",
    "sg:address":"596 Champlain St",
    "sg:city":"Dieppe",
    "sg:classifiers":[
        {
            "category":"Retail",
            "subcategory":"Auto Repair",
            "type":"Services"
        }
    ],
    "sg:phone":"+1 506 857 0222",
    "sg:postcode":"E1A 1P4",
    "sg:province":"NB",
    "sg:tags":[
        "body",
        "automobile",
        "painting"
    ],
    "wof:name":"Champlain Auto Body",
    "wof:placetype":"venue"
},
  "geometry": {"coordinates":[-64.730255,46.098995],"type":"Point"}
}