{
  "type": "Feature",
  "properties": {
    "addr:full":"75 Brydon Dr Etobicoke ON M9W 4N3",
    "addr:housenumber":"75",
    "addr:postcode":"m9w 4n3",
    "addr:street":"Brydon Dr",
    "iso:country":"CA",
    "sg:address":"75 Brydon Dr",
    "sg:city":"Etobicoke",
    "sg:classifiers":[
        {
            "category":"Manufacturing",
            "subcategory":"Tools & Machinery",
            "type":"Manufacturing & Wholesale Goods"
        }
    ],
    "sg:phone":"+1 416 740 1337",
    "sg:postcode":"M9W 4N3",
    "sg:province":"ON",
    "sg:tags":[
        "alternator",
        "starter"
    ],
    "wof:name":"Delta Auto Electric & Sales",
    "wof:placetype":"venue"
},
  "geometry": {"coordinates":[-79.57266199999999,43.718536],"type":"Point"}
}