{
  "type": "Feature",
  "properties": {
    "addr:full":"68 Rue Rouillier Saint-Philippe QC J0L 2K0",
    "addr:housenumber":"68",
    "addr:postcode":"j0l 2k0",
    "addr:street":"Rue Rouillier",
    "iso:country":"CA",
    "sg:address":"68 Rue Rouillier",
    "sg:city":"Saint-Philippe",
    "sg:classifiers":[
        {
            "category":"Building & Trades",
            "subcategory":"Electrical",
            "type":"Services"
        }
    ],
    "sg:phone":"+1 450 659 7075",
    "sg:postcode":"J0L 2K0",
    "sg:province":"QC",
    "sg:tags":[
        "electric",
        "contractor"
    ],
    "wof:name":"J M Jubinville Enr",
    "wof:placetype":"venue"
},
  "geometry": {"coordinates":[-73.464043,45.379875],"type":"Point"}
}