{
  "type": "Feature",
  "properties": {
    "addr:full":"5817 Av Du Parc Montreal QC H2V 4H4",
    "addr:housenumber":"5817",
    "addr:postcode":"h2v 4h4",
    "addr:street":"Av Du Parc",
    "iso:country":"CA",
    "sg:address":"5817 Av Du Parc",
    "sg:city":"Montreal",
    "sg:classifiers":[
        {
            "category":"Retail",
            "subcategory":"Laundry & Dry Cleaning",
            "type":"Services"
        }
    ],
    "sg:phone":"+1 514 277 4736",
    "sg:postcode":"H2V 4H4",
    "sg:province":"QC",
    "sg:tags":[
        "cleaners"
    ],
    "wof:name":"Caplan Cleaners",
    "wof:placetype":"venue"
},
  "geometry": {"coordinates":[-73.606049,45.524063],"type":"Point"}
}