{
  "type": "Feature",
  "properties": {
    "addr:full":"2541 Churchill Rd Westbank BC V4T 2B4",
    "addr:housenumber":"2541",
    "addr:postcode":"v4t 2b4",
    "addr:street":"Churchill Rd",
    "iso:country":"CA",
    "sg:address":"2541 Churchill Rd",
    "sg:city":"Westbank",
    "sg:classifiers":[
        {
            "category":"Shopping",
            "type":"Retail Goods"
        }
    ],
    "sg:phone":"+1 250 768 1187",
    "sg:postcode":"V4T 2B4",
    "sg:province":"BC",
    "sg:tags":[
        "monument"
    ],
    "wof:name":"Arbor Valley Monument CO",
    "wof:placetype":"venue"
},
  "geometry": {"coordinates":[-119.632255554,49.8288421631],"type":"Point"}
}