{
  "type": "Feature",
  "properties": {
    "addr:full":"Ridgeway ON L0S 1N0",
    "addr:postcode":"l0s 1n0",
    "addr:street":"Ridgeway",
    "iso:country":"CA",
    "sg:city":"Ridgeway",
    "sg:classifiers":[
        {
            "category":"Personal",
            "subcategory":"Beauty Salon",
            "type":"Services"
        }
    ],
    "sg:phone":"+1 905 894 5675",
    "sg:postcode":"L0S 1N0",
    "sg:province":"ON",
    "wof:name":"Heaven's Hair Studio",
    "wof:placetype":"venue"
},
  "geometry": {"coordinates":[-79.05837200000001,42.884907],"type":"Point"}
}