{
  "type": "Feature",
  "properties": {
    "addr:full":"2600 Rue Ontario E # 119 Montreal QC H2K 4K4",
    "addr:housenumber":"2600",
    "addr:postcode":"h2k 4k4",
    "addr:street":"Rue Ontario E # 119",
    "iso:country":"CA",
    "sg:address":"2600 Rue Ontario E # 119",
    "sg:city":"Montreal",
    "sg:classifiers":[
        {
            "category":"Food & Beverages",
            "subcategory":"Groceries & Convenience Stores",
            "type":"Retail Goods"
        }
    ],
    "sg:phone":"+1 514 525 4281",
    "sg:postcode":"H2K 4K4",
    "sg:province":"QC",
    "sg:tags":[
        "grocer"
    ],
    "wof:name":"Super Marche Sauro Enr",
    "wof:placetype":"venue"
},
  "geometry": {"coordinates":[-73.55201721189999,45.5335884094],"type":"Point"}
}