{
  "type": "Feature",
  "properties": {
    "addr:full":"Carcross YT Y0B 1B0",
    "addr:postcode":"y0b 1b0",
    "iso:country":"CA",
    "sg:city":"Carcross",
    "sg:classifiers":[
        {
            "category":"Professional",
            "subcategory":"Computer Services",
            "type":"Services"
        }
    ],
    "sg:phone":"+1 867 821 3307",
    "sg:postcode":"Y0B 1B0",
    "sg:province":"YT",
    "sg:tags":[
        "internet"
    ],
    "wof:name":"Y K Net",
    "wof:placetype":"venue"
},
  "geometry": {"coordinates":[-134.699874878,60.1661987305],"type":"Point"}
}