{
  "type": "Feature",
  "properties": {
    "iso:country":"CA",
    "sg:address":"2570 Clearbrook Rd",
    "sg:city":"Abbotsford",
    "sg:classifiers":[
        {
            "category":"Home & Garden",
            "subcategory":"Building Materials",
            "type":"Retail Goods"
        }
    ],
    "sg:phone":"+1 604 853 6909",
    "sg:postcode":"V2T 2Y5",
    "sg:province":"BC",
    "sg:tags":[
        "paint"
    ],
    "wof:name":"Clearbrook Decorating Ctr Inc",
    "wof:placetype":"venue"
},
  "geometry": {"coordinates":[-122.33719635,49.0488700867],"type":"Point"}
}