{
  "type": "Feature",
  "properties": {
    "addr:full":"1520 Steeles Ave W #103 Concord ON L4K 3B9",
    "addr:housenumber":"1520",
    "addr:postcode":"l4k 3b9",
    "addr:street":"Steeles Ave W # 103",
    "iso:country":"CA",
    "sg:address":"1520 Steeles Ave W #103",
    "sg:city":"Concord",
    "sg:classifiers":[
        {
            "category":"Restaurant",
            "type":"Food & Drink"
        }
    ],
    "sg:phone":"+1 905 738 6668",
    "sg:postcode":"L4K 3B9",
    "sg:province":"ON",
    "wof:name":"Gourmets of China",
    "wof:placetype":"venue"
},
  "geometry": {"coordinates":[-79.4709854126,43.7871932983],"type":"Point"}
}