{
  "type": "Feature",
  "properties": {
    "addr:full":"Delburne AB T0M 0V0",
    "addr:postcode":"t0m 0v0",
    "iso:country":"CA",
    "sg:city":"Delburne",
    "sg:classifiers":[
        {
            "category":"Manufacturing",
            "subcategory":"Chemicals & Compounds",
            "type":"Manufacturing & Wholesale Goods"
        }
    ],
    "sg:phone":"+1 403 749 3177",
    "sg:postcode":"T0M 0V0",
    "sg:province":"AB",
    "sg:tags":[
        "fertilizer"
    ],
    "wof:name":"Parkland Agri Svc",
    "wof:placetype":"venue"
},
  "geometry": {"coordinates":[-113.243041992,52.1956558228],"type":"Point"}
}