{
  "type": "Feature",
  "properties": {
    "iso:country":"CA",
    "sg:address":"897842 Gillies Lake Rd",
    "sg:city":"Cobalt",
    "sg:classifiers":[
        {
            "category":"Building & Trades",
            "subcategory":"Construction",
            "type":"Services"
        }
    ],
    "sg:phone":"+1 705 679 8145",
    "sg:postcode":"P0J 1C0",
    "sg:province":"ON",
    "sg:tags":[
        "sand",
        "gravel",
        "general",
        "contractor"
    ],
    "wof:name":"Alex Adshead Construction",
    "wof:placetype":"venue"
},
  "geometry": {"coordinates":[-79.6888122559,47.392780304],"type":"Point"}
}