{
  "type": "Feature",
  "properties": {
    "addr:full":"Vancouver BC V6B 1E5",
    "addr:postcode":"v6b 1e5",
    "iso:country":"CA",
    "sg:city":"Vancouver",
    "sg:classifiers":[
        {
            "category":"Manufacturing",
            "subcategory":"Jewelry",
            "type":"Manufacturing & Wholesale Goods"
        }
    ],
    "sg:phone":"+1 604 684 4403",
    "sg:postcode":"V6B 1E5",
    "sg:province":"BC",
    "sg:tags":[
        "jeweler"
    ],
    "wof:name":"Metal Garden",
    "wof:placetype":"venue"
},
  "geometry": {"coordinates":[-123.109130859,49.283657074],"type":"Point"}
}