{
  "type": "Feature",
  "properties": {
    "addr:full":"35 Mccleary Crt Concord ON L4K 3Y9",
    "addr:housenumber":"35",
    "addr:postcode":"l4k 3y9",
    "addr:street":"Mccleary Crt",
    "iso:country":"CA",
    "sg:address":"35 Mccleary Crt",
    "sg:city":"Concord",
    "sg:classifiers":[
        {
            "category":"Shopping",
            "subcategory":"Computers & Home Electronics",
            "type":"Retail Goods"
        }
    ],
    "sg:phone":"+1 905 660 7968",
    "sg:postcode":"L4K 3Y9",
    "sg:province":"ON",
    "sg:tags":[
        "equipment",
        "dealer"
    ],
    "wof:name":"Seoul Computers Inc",
    "wof:placetype":"venue"
},
  "geometry": {"coordinates":[-79.51699829099999,43.7969665527],"type":"Point"}
}