{
  "type": "Feature",
  "properties": {
    "iso:country":"CA",
    "sg:city":"Collingwood",
    "sg:classifiers":[
        {
            "category":"Wholesale",
            "subcategory":"Construction Materials",
            "type":"Manufacturing & Wholesale Goods"
        }
    ],
    "sg:phone":"+1 705 446 1304",
    "sg:postcode":"L9Y 3Z1",
    "sg:province":"ON",
    "sg:tags":[
        "fence"
    ],
    "wof:name":"Fence Factory",
    "wof:placetype":"venue"
},
  "geometry": {"coordinates":[-80.2168273926,44.4998893738],"type":"Point"}
}