{
  "type": "Feature",
  "properties": {
    "addr:full":"Sainte-Foy QC G1N 4P4",
    "addr:postcode":"g1n 4p4",
    "iso:country":"CA",
    "sg:city":"Sainte-Foy",
    "sg:classifiers":[
        {
            "category":"Building & Trades",
            "subcategory":"Construction",
            "type":"Services"
        }
    ],
    "sg:phone":"+1 418 688 5921",
    "sg:postcode":"G1N 4P4",
    "sg:province":"QC",
    "sg:tags":[
        "designer",
        "marine",
        "diver",
        "contractor"
    ],
    "wof:name":"Services Subaquatiques Blm",
    "wof:placetype":"venue"
},
  "geometry": {"coordinates":[-71.2917633057,46.7692108154],"type":"Point"}
}