{
  "type": "Feature",
  "properties": {
    "iso:country":"CA",
    "sg:address":"3900 Island Hwy N",
    "sg:city":"Nanaimo",
    "sg:classifiers":[
        {
            "category":"Home & Garden",
            "subcategory":"Building Materials",
            "type":"Retail Goods"
        }
    ],
    "sg:phone":"+1 250 758 3374",
    "sg:postcode":"V9T 1W5",
    "sg:province":"BC",
    "sg:tags":[
        "windows",
        "plate",
        "window"
    ],
    "wof:name":"Budget Glass",
    "wof:placetype":"venue"
},
  "geometry": {"coordinates":[-124.014663696,49.2068023682],"type":"Point"}
}