{
  "type": "Feature",
  "properties": {
    "iso:country":"CA",
    "sg:address":"62 Ontario Rd",
    "sg:city":"Mitchell",
    "sg:classifiers":[
        {
            "category":"Real Estate",
            "subcategory":"Real Estate Agent",
            "type":"Services"
        }
    ],
    "sg:phone":"+1 519 348 4706",
    "sg:postcode":"N0K 1N0",
    "sg:province":"ON",
    "wof:name":"Culligan Real Estate Ltd",
    "wof:placetype":"venue"
},
  "geometry": {"coordinates":[-81.1967926025,43.4674186707],"type":"Point"}
}