{
  "type": "Feature",
  "properties": {
    "addr:full":"516 Atlantic Ave W Beausejour MB R0E 0C0",
    "addr:housenumber":"516",
    "addr:postcode":"r0e 0c0",
    "addr:street":"Atlantic Ave W",
    "iso:country":"CA",
    "sg:address":"516 Atlantic Ave W",
    "sg:city":"Beausejour",
    "sg:classifiers":[
        {
            "category":"Organizations",
            "subcategory":"Religious Organization",
            "type":"Services"
        }
    ],
    "sg:phone":"+1 204 268 2453",
    "sg:postcode":"R0E 0C0",
    "sg:province":"MB",
    "wof:name":"St Mary's Roman Catholic Rect",
    "wof:placetype":"venue"
},
  "geometry": {"coordinates":[-96.51853179930001,50.058971405],"type":"Point"}
}