{
  "type": "Feature",
  "properties": {
    "addr:full":"436 Rue Du Sud Cowansville QC J2K 2X7",
    "addr:housenumber":"436",
    "addr:postcode":"j2k 2x7",
    "addr:street":"Rue Du Sud",
    "iso:country":"CA",
    "sg:address":"436 Rue Du Sud",
    "sg:city":"Cowansville",
    "sg:classifiers":[
        {
            "category":"Professional",
            "subcategory":"Lawyer & Legal Services",
            "type":"Services"
        }
    ],
    "sg:phone":"+1 450 263 5458",
    "sg:postcode":"J2K 2X7",
    "sg:province":"QC",
    "sg:tags":[
        "attorney"
    ],
    "wof:name":"Aide Juridique",
    "wof:placetype":"venue"
},
  "geometry": {"coordinates":[-72.7468948364,45.2045021057],"type":"Point"}
}