{
  "type": "Feature",
  "properties": {
    "addr:full":"Winnipeg MB R2H 0C4",
    "addr:postcode":"r2h 0c4",
    "iso:country":"CA",
    "sg:city":"Winnipeg",
    "sg:classifiers":[
        {
            "category":"Government",
            "subcategory":"Office",
            "type":"Public Place"
        }
    ],
    "sg:phone":"+1 204 945 2806",
    "sg:postcode":"R2H 0C4",
    "sg:province":"MB",
    "wof:name":"Manitoba Immigration Promotion",
    "wof:placetype":"venue"
},
  "geometry": {"coordinates":[-97.1218414307,49.894367218],"type":"Point"}
}