{
  "type": "Feature",
  "properties": {
    "addr:full":"Water St Trinity Tb NL A0C 2S0",
    "addr:postcode":"a0c 2s0",
    "addr:street":"Water St",
    "iso:country":"CA",
    "sg:address":"Water St",
    "sg:city":"Trinity Tb",
    "sg:classifiers":[
        {
            "category":"Shopping",
            "subcategory":"Pharmacy",
            "type":"Retail Goods"
        }
    ],
    "sg:phone":"+1 709 464 3575",
    "sg:postcode":"A0C 2S0",
    "sg:province":"NL",
    "wof:name":"Trinity Drugs",
    "wof:placetype":"venue"
},
  "geometry": {"coordinates":[-53.3597106934,48.3690681458],"type":"Point"}
}