{
  "type": "Feature",
  "properties": {
    "addr:full":"Pembroke ON K8A 6W8",
    "addr:postcode":"k8a 6w8",
    "iso:country":"CA",
    "sg:city":"Pembroke",
    "sg:classifiers":[
        {
            "category":"Manufacturing",
            "subcategory":"Tools & Machinery",
            "type":"Manufacturing & Wholesale Goods"
        }
    ],
    "sg:phone":"+1 613 732 1865",
    "sg:postcode":"K8A 6W8",
    "sg:province":"ON",
    "sg:tags":[
        "machine",
        "shop"
    ],
    "wof:name":"P & R Precision Tooling Inc",
    "wof:placetype":"venue"
},
  "geometry": {"coordinates":[-77.1122131348,45.8264808655],"type":"Point"}
}