{
  "type": "Feature",
  "properties": {
    "addr:full":"91 Oxford St Toronto ON M5T 1P2",
    "addr:housenumber":"91",
    "addr:postcode":"m5t 1p2",
    "addr:street":"Oxford St",
    "iso:country":"CA",
    "sg:address":"91 Oxford St",
    "sg:city":"Toronto",
    "sg:classifiers":[
        {
            "category":"Manufacturing",
            "subcategory":"Rubber & Plastics",
            "type":"Manufacturing & Wholesale Goods"
        }
    ],
    "sg:phone":"+1 416 603 7451",
    "sg:postcode":"M5T 1P2",
    "sg:province":"ON",
    "sg:tags":[
        "packaging",
        "forming"
    ],
    "wof:name":"Precision Vacuum Products Ltd",
    "wof:placetype":"venue"
},
  "geometry": {"coordinates":[-79.4037704468,43.6557693481],"type":"Point"}
}