{
  "type": "Feature",
  "properties": {
    "addr:full":"925 8th Ave W # 100 Vancouver BC V5Z 1E4",
    "addr:housenumber":"925",
    "addr:postcode":"v5z 1e4",
    "addr:street":"8Th Ave W # 100",
    "iso:country":"CA",
    "sg:address":"925 8th Ave W # 100",
    "sg:city":"Vancouver",
    "sg:classifiers":[
        {
            "category":"Arts & Performance",
            "subcategory":"Theater",
            "type":"Entertainment"
        }
    ],
    "sg:phone":"+1 604 737 1110",
    "sg:postcode":"V5Z 1E4",
    "sg:province":"BC",
    "sg:tags":[
        "musician",
        "bureau"
    ],
    "wof:name":"Vancouver Musicians' Assn",
    "wof:placetype":"venue"
},
  "geometry": {"coordinates":[-123.124893,49.264427],"type":"Point"}
}