{
  "type": "Feature",
  "properties": {
    "iso:country":"CA",
    "sg:address":"1551 North Railway St W",
    "sg:city":"Swift Current",
    "sg:classifiers":[
        {
            "category":"Manufacturing",
            "subcategory":"Apparel",
            "type":"Manufacturing & Wholesale Goods"
        }
    ],
    "sg:phone":"+1 306 773 2076",
    "sg:postcode":"S9H 5G3",
    "sg:province":"SK",
    "sg:tags":[
        "training",
        "program"
    ],
    "wof:name":"Saskatchewan Abilities Council",
    "wof:placetype":"venue"
},
  "geometry": {"coordinates":[-107.821327209,50.2825965881],"type":"Point"}
}