{
  "type": "Feature",
  "properties": {
    "addr:full":"Port Coquitlam BC V3B 5Y9",
    "addr:postcode":"v3b 5y9",
    "iso:country":"CA",
    "sg:city":"Port Coquitlam",
    "sg:classifiers":[
        {
            "category":"Food & Beverages",
            "subcategory":"Bakery",
            "type":"Retail Goods"
        }
    ],
    "sg:phone":"+1 604 944 0045",
    "sg:postcode":"V3B 5Y9",
    "sg:province":"BC",
    "sg:tags":[
        "baker"
    ],
    "wof:name":"Bagel Garden",
    "wof:placetype":"venue"
},
  "geometry": {"coordinates":[-122.789024,49.273098],"type":"Point"}
}