{
  "type": "Feature",
  "properties": {
    "addr:full":"Etobicoke ON M9C 5K6",
    "addr:postcode":"m9c 5k6",
    "iso:country":"CA",
    "sg:city":"Etobicoke",
    "sg:classifiers":[
        {
            "category":"Education",
            "subcategory":"School",
            "type":"Public Place"
        }
    ],
    "sg:phone":"+1 416 695 8737",
    "sg:postcode":"M9C 5K6",
    "sg:province":"ON",
    "wof:name":"Smart Serve Ontario",
    "wof:placetype":"venue"
},
  "geometry": {"coordinates":[-79.59065200000001,43.662792],"type":"Point"}
}