{
  "type": "Feature",
  "properties": {
    "addr:full":"159 Kedey St Fitzroy Harbour ON K0A 1X0",
    "addr:housenumber":"159",
    "addr:postcode":"k0a 1x0",
    "addr:street":"Kedey St",
    "iso:country":"CA",
    "sg:address":"159 Kedey St",
    "sg:city":"Fitzroy Harbour",
    "sg:classifiers":[
        {
            "category":"Education",
            "subcategory":"School",
            "type":"Public Place"
        }
    ],
    "sg:phone":"+1 613 623 3114",
    "sg:postcode":"K0A 1X0",
    "sg:province":"ON",
    "wof:name":"St Michael's School",
    "wof:placetype":"venue"
},
  "geometry": {"coordinates":[-76.21602630620001,45.4717559814],"type":"Point"}
}