{
  "type": "Feature",
  "properties": {
    "addr:full":"Vancouver BC V6Z 1S4",
    "addr:postcode":"v6z 1s4",
    "iso:country":"CA",
    "sg:city":"Vancouver",
    "sg:classifiers":[
        {
            "category":"Professional",
            "subcategory":"Management & Consulting",
            "type":"Services"
        }
    ],
    "sg:phone":"+1 604 688 8279",
    "sg:postcode":"V6Z 1S4",
    "sg:province":"BC",
    "sg:tags":[
        "marketing",
        "consultant"
    ],
    "wof:name":"Imi Marketing Inc",
    "wof:placetype":"venue"
},
  "geometry": {"coordinates":[-123.121360779,49.2830276489],"type":"Point"}
}