{
  "type": "Feature",
  "properties": {
    "iso:country":"CA",
    "sg:address":"1180 Addison Dr",
    "sg:city":"London",
    "sg:classifiers":[
        {
            "category":"Communications",
            "subcategory":"Film & Video Production",
            "type":"Services"
        }
    ],
    "sg:phone":"+1 519 453 9828",
    "sg:postcode":"N5V 2N9",
    "sg:province":"ON",
    "sg:tags":[
        "taping"
    ],
    "wof:name":"Signature Video Productions",
    "wof:placetype":"venue"
},
  "geometry": {"coordinates":[-81.191727,43.021969],"type":"Point"}
}