{
  "type": "Feature",
  "properties": {
    "addr:full":"10138 Newene Rd Winfield BC V4V 1V2",
    "addr:housenumber":"10138",
    "addr:postcode":"v4v 1v2",
    "addr:street":"Newene Rd",
    "iso:country":"CA",
    "sg:address":"10138 Newene Rd",
    "sg:city":"Winfield",
    "sg:classifiers":[
        {
            "category":"Retail",
            "subcategory":"Repair Shop",
            "type":"Services"
        }
    ],
    "sg:phone":"+1 250 766 2254",
    "sg:postcode":"V4V 1V2",
    "sg:province":"BC",
    "sg:tags":[
        "upholsterer"
    ],
    "wof:name":"Lake Country Upholstery",
    "wof:placetype":"venue"
},
  "geometry": {"coordinates":[-119.405822754,50.0303268433],"type":"Point"}
}