{
  "type": "Feature",
  "properties": {
    "addr:full":"15850 Rue Notre-Dame E Pointe-Aux-Trembles QC H1A 1X6",
    "addr:housenumber":"15850",
    "addr:postcode":"h1a 1x6",
    "addr:street":"Rue Notre-Dame E Pointe-Aux-Trembles",
    "iso:country":"CA",
    "sg:address":"15850 Rue Notre-Dame E",
    "sg:city":"Pointe-Aux-Trembles",
    "sg:classifiers":[
        {
            "category":"Banks & Credit Unions",
            "subcategory":"Bank",
            "type":"Services"
        }
    ],
    "sg:phone":"+1 514 640 5200",
    "sg:postcode":"H1A 1X6",
    "sg:province":"QC",
    "wof:name":"Caisse Populaire",
    "wof:placetype":"venue"
},
  "geometry": {"coordinates":[-73.488159,45.693287],"type":"Point"}
}