{
  "type": "Feature",
  "properties": {
    "addr:full":"1150 Boul DE LA Grande-Allee Boisbriand QC J7G 2T4",
    "addr:housenumber":"1150",
    "addr:postcode":"j7g 2t4",
    "addr:street":"Boul De La Grande-Allee",
    "iso:country":"CA",
    "sg:address":"1150 Boul DE LA Grande-Allee",
    "sg:city":"Boisbriand",
    "sg:classifiers":[
        {
            "category":"Health Services",
            "subcategory":"Doctor",
            "type":"Services"
        }
    ],
    "sg:phone":"+1 450 435 8801",
    "sg:postcode":"J7G 2T4",
    "sg:province":"QC",
    "sg:tags":[
        "dentist"
    ],
    "wof:name":"Clinique Dentaire Mathieu",
    "wof:placetype":"venue"
},
  "geometry": {"coordinates":[-73.83916473390001,45.615436554],"type":"Point"}
}