{
  "type": "Feature",
  "properties": {
    "addr:full":"10152 Clifton Pl NW Edmonton AB T5N 3J1",
    "addr:housenumber":"10152",
    "addr:postcode":"t5n 3j1",
    "addr:street":"Clifton Pl Nw",
    "iso:country":"CA",
    "sg:address":"10152 Clifton Pl NW",
    "sg:city":"Edmonton",
    "sg:classifiers":[
        {
            "category":"Professional",
            "subcategory":"Management & Consulting",
            "type":"Services"
        }
    ],
    "sg:phone":"+1 780 455 6611",
    "sg:postcode":"T5N 3J1",
    "sg:province":"AB",
    "sg:tags":[
        "town",
        "city",
        "regional",
        "planner"
    ],
    "wof:name":"Mac Kenzie Associates Consult",
    "wof:placetype":"venue"
},
  "geometry": {"coordinates":[-113.539108,53.542278],"type":"Point"}
}