{
  "type": "Feature",
  "properties": {
    "addr:full":"3 Centre St Markham ON L3P 3P9",
    "addr:housenumber":"3",
    "addr:postcode":"l3p 3p9",
    "addr:street":"Centre St",
    "iso:country":"CA",
    "sg:address":"3 Centre St",
    "sg:city":"Markham",
    "sg:classifiers":[
        {
            "category":"Personal",
            "type":"Services"
        }
    ],
    "sg:phone":"+1 905 471 6349",
    "sg:postcode":"L3P 3P9",
    "sg:province":"ON",
    "sg:tags":[
        "therapist",
        "massage"
    ],
    "wof:name":"Solace Natural Health & Thrpy",
    "wof:placetype":"venue"
},
  "geometry": {"coordinates":[-79.2599945068,43.8758049011],"type":"Point"}
}