{
  "type": "Feature",
  "properties": {
    "addr:full":"640 Route 774 Welshpool NB E5E 1A5",
    "addr:housenumber":"640",
    "addr:postcode":"e5e 1a5",
    "addr:street":"Route 774",
    "iso:country":"CA",
    "sg:address":"640 Route 774",
    "sg:city":"Welshpool",
    "sg:classifiers":[
        {
            "category":"Health Services",
            "subcategory":"Doctor",
            "type":"Services"
        }
    ],
    "sg:phone":"+1 506 752 4100",
    "sg:postcode":"E5E 1A5",
    "sg:province":"NB",
    "sg:tags":[
        "physician",
        "clinic",
        "surgeon"
    ],
    "wof:name":"Campobello Health Ctr",
    "wof:placetype":"venue"
},
  "geometry": {"coordinates":[-66.95464324949999,44.8897399902],"type":"Point"}
}