{
  "type": "Feature",
  "properties": {
    "addr:full":"1839 Rte Du Carrefour Val-Des-Monts QC J8N 7M6",
    "addr:housenumber":"1839",
    "addr:postcode":"j8n 7m6",
    "addr:street":"Rte Du Carrefour",
    "iso:country":"CA",
    "sg:address":"1839 Rte Du Carrefour",
    "sg:city":"Val-Des-Monts",
    "sg:classifiers":[
        {
            "category":"Building & Trades",
            "subcategory":"Construction",
            "type":"Services"
        }
    ],
    "sg:phone":"+1 819 671 2171",
    "sg:postcode":"J8N 7M6",
    "sg:province":"QC",
    "sg:tags":[
        "excavating",
        "contractor",
        "general"
    ],
    "wof:name":"Mja Entreprises",
    "wof:placetype":"venue"
},
  "geometry": {"coordinates":[-75.617477417,45.5898361206],"type":"Point"}
}