{
  "type": "Feature",
  "properties": {
    "iso:country":"CA",
    "sg:address":"5341 Tecumseh Rd E",
    "sg:city":"Windsor",
    "sg:classifiers":[
        {
            "category":"Personal",
            "subcategory":"Shoe Repair & Shine",
            "type":"Services"
        }
    ],
    "sg:phone":"+1 519 945 1041",
    "sg:postcode":"N8T 1C5",
    "sg:province":"ON",
    "sg:tags":[
        "repairing",
        "boot"
    ],
    "wof:name":"Henry's Shoe Repair",
    "wof:placetype":"venue"
},
  "geometry": {"coordinates":[-82.9600067139,42.3087272644],"type":"Point"}
}