{
  "type": "Feature",
  "properties": {
    "addr:full":"4600 Rue Des Cageux Pierrefonds QC H9J 3R4",
    "addr:housenumber":"4600",
    "addr:postcode":"h9j 3r4",
    "addr:street":"Rue Des Cageux",
    "iso:country":"CA",
    "sg:address":"4600 Rue Des Cageux",
    "sg:city":"Pierrefonds",
    "sg:classifiers":[
        {
            "category":"Organizations",
            "subcategory":"Professional Association",
            "type":"Services"
        }
    ],
    "sg:phone":"+1 514 696 2505",
    "sg:postcode":"H9J 3R4",
    "sg:province":"QC",
    "wof:name":"Pierrefonds Soccer Assn",
    "wof:placetype":"venue"
},
  "geometry": {"coordinates":[-73.8805770874,45.4577140808],"type":"Point"}
}