{
  "type": "Feature",
  "properties": {
    "addr:full":"1600 California Ave Brockville ON K6V 5T8",
    "addr:housenumber":"1600",
    "addr:postcode":"k6v 5t8",
    "addr:street":"California Ave",
    "iso:country":"CA",
    "sg:address":"1600 California Ave",
    "sg:city":"Brockville",
    "sg:classifiers":[
        {
            "category":"Manufacturing",
            "subcategory":"Printing",
            "type":"Manufacturing & Wholesale Goods"
        }
    ],
    "sg:phone":"+1 613 342 4441",
    "sg:postcode":"K6V 5T8",
    "sg:province":"ON",
    "sg:tags":[
        "newspaper"
    ],
    "wof:name":"Recorder & Times Ltd",
    "wof:placetype":"venue"
},
  "geometry": {"coordinates":[-75.6984786987,44.6248130798],"type":"Point"}
}