{
  "type": "Feature",
  "properties": {
    "iso:country":"CA",
    "sg:address":"1150 Ch Des Patriotes",
    "sg:city":"Richelieu",
    "sg:classifiers":[
        {
            "category":"Personal",
            "subcategory":"Tanning Parlor",
            "type":"Services"
        }
    ],
    "sg:phone":"+1 450 658 3371",
    "sg:postcode":"J3L 4S6",
    "sg:province":"QC",
    "sg:tags":[
        "salon"
    ],
    "wof:name":"Bronzage Unic Xxiii",
    "wof:placetype":"venue"
},
  "geometry": {"coordinates":[-73.245735,45.441677],"type":"Point"}
}