{
  "type": "Feature",
  "properties": {
    "addr:full":"1251 Rue Saint-Zotique E Montreal QC H2S 1N8",
    "addr:housenumber":"1251",
    "addr:postcode":"h2s 1n8",
    "addr:street":"Rue Saint-Zotique E",
    "iso:country":"CA",
    "sg:address":"1251 Rue Saint-Zotique E",
    "sg:city":"Montreal",
    "sg:classifiers":[
        {
            "category":"Food & Beverages",
            "subcategory":"Groceries & Convenience Stores",
            "type":"Retail Goods"
        }
    ],
    "sg:phone":"+1 514 278 6927",
    "sg:postcode":"H2S 1N8",
    "sg:province":"QC",
    "sg:tags":[
        "grocer"
    ],
    "wof:name":"Depanneur Pamela Enr",
    "wof:placetype":"venue"
},
  "geometry": {"coordinates":[-73.6037139893,45.5409469604],"type":"Point"}
}