{
  "type": "Feature",
  "properties": {
    "addr:full":"17 Stewart Crt Orangeville ON L9W 3Z9",
    "addr:housenumber":"17",
    "addr:postcode":"l9w 3z9",
    "addr:street":"Stewart Crt",
    "iso:country":"CA",
    "sg:address":"17 Stewart Crt",
    "sg:city":"Orangeville",
    "sg:classifiers":[
        {
            "category":"Wholesale",
            "subcategory":"Electrical",
            "type":"Manufacturing & Wholesale Goods"
        }
    ],
    "sg:phone":"+1 519 941 6845",
    "sg:postcode":"L9W 3Z9",
    "sg:province":"ON",
    "sg:tags":[
        "equipment",
        "electric"
    ],
    "wof:name":"E E Controls",
    "wof:placetype":"venue"
},
  "geometry": {"coordinates":[-80.1137542725,43.9082489014],"type":"Point"}
}