{
  "type": "Feature",
  "properties": {
    "addr:full":"2 1Ere Av E Mont-Louis QC G0E 1T0",
    "addr:housenumber":"2",
    "addr:postcode":"g0e 1t0",
    "addr:street":"1Ere Av E",
    "iso:country":"CA",
    "sg:address":"2 1Ere Av E",
    "sg:city":"Mont-Louis",
    "sg:classifiers":[
        {
            "category":"Organizations",
            "subcategory":"Religious Organization",
            "type":"Services"
        }
    ],
    "sg:phone":"+1 418 797 2963",
    "sg:postcode":"G0E 1T0",
    "sg:province":"QC",
    "sg:tags":[
        "church"
    ],
    "wof:name":"Mont-Louis Presbytere",
    "wof:placetype":"venue"
},
  "geometry": {"coordinates":[-65.730492,49.229252],"type":"Point"}
}