{
  "type": "Feature",
  "properties": {
    "addr:full":"Trois-Rivieres-Ouest QC G9A 5Z9",
    "addr:postcode":"g9a 5z9",
    "iso:country":"CA",
    "sg:city":"Trois-Rivieres-Ouest",
    "sg:classifiers":[
        {
            "category":"Professional",
            "subcategory":"Management & Consulting",
            "type":"Services"
        }
    ],
    "sg:phone":"+1 819 374 8750",
    "sg:postcode":"G9A 5Z9",
    "sg:province":"QC",
    "sg:tags":[
        "consultant",
        "instructional"
    ],
    "wof:name":"Diffex Inc",
    "wof:placetype":"venue"
},
  "geometry": {"coordinates":[-72.5725784302,46.3178710938],"type":"Point"}
}