{
  "type": "Feature",
  "properties": {
    "addr:full":"30 Nevilles St New Hamburg ON N3A 4G7",
    "addr:housenumber":"30",
    "addr:postcode":"n3a 4g7",
    "addr:street":"Nevilles St",
    "iso:country":"CA",
    "sg:address":"30 Nevilles St",
    "sg:city":"New Hamburg",
    "sg:classifiers":[
        {
            "category":"Wholesale",
            "subcategory":"Machinery & Supplies",
            "type":"Manufacturing & Wholesale Goods"
        }
    ],
    "sg:phone":"+1 519 662 2352",
    "sg:postcode":"N3A 4G7",
    "sg:province":"ON",
    "sg:tags":[
        "glass",
        "tank",
        "plastic"
    ],
    "wof:name":"Alpine Plant Food Corp",
    "wof:placetype":"venue"
},
  "geometry": {"coordinates":[-80.70560500000001,43.383881],"type":"Point"}
}