{
  "type": "Feature",
  "properties": {
    "iso:country":"CA",
    "sg:address":"215 Pearsonlittle Ave",
    "sg:city":"Maidstone",
    "sg:classifiers":[
        {
            "category":"Mining & Drilling",
            "type":"Manufacturing & Wholesale Goods"
        }
    ],
    "sg:phone":"+1 306 893 4241",
    "sg:postcode":"S0M 1M0",
    "sg:province":"SK",
    "sg:tags":[
        "company",
        "oil"
    ],
    "wof:name":"Canadian Natural Resources Ltd",
    "wof:placetype":"venue"
},
  "geometry": {"coordinates":[-109.296607971,53.0874595642],"type":"Point"}
}