{
  "type": "Feature",
  "properties": {
    "iso:country":"CA",
    "sg:address":"329 Rayette Rd",
    "sg:city":"Concord",
    "sg:classifiers":[
        {
            "category":"Manufacturing",
            "subcategory":"Signs",
            "type":"Manufacturing & Wholesale Goods"
        }
    ],
    "sg:phone":"+1 905 761 0838",
    "sg:postcode":"L4K 2G1",
    "sg:province":"ON",
    "wof:name":"United Road Signs Corp",
    "wof:placetype":"venue"
},
  "geometry": {"coordinates":[-79.497131,43.812023],"type":"Point"}
}