{
  "type": "Feature",
  "properties": {
    "addr:full":"Calgary AB T1Y 3R6",
    "addr:postcode":"t1y 3r6",
    "iso:country":"CA",
    "sg:city":"Calgary",
    "sg:classifiers":[
        {
            "category":"Personal",
            "subcategory":"Beauty Salon",
            "type":"Services"
        }
    ],
    "sg:phone":"+1 403 285 6949",
    "sg:postcode":"T1Y 3R6",
    "sg:province":"AB",
    "wof:name":"Natural Concept Hair Styling",
    "wof:placetype":"venue"
},
  "geometry": {"coordinates":[-113.958275,51.075523],"type":"Point"}
}