{
  "type": "Feature",
  "properties": {
    "addr:full":"Bridgewater NS B4V 2W1",
    "addr:postcode":"b4v 2w1",
    "iso:country":"CA",
    "sg:city":"Bridgewater",
    "sg:classifiers":[
        {
            "category":"Retail",
            "subcategory":"Repair Shop",
            "type":"Services"
        }
    ],
    "sg:phone":"+1 902 543 6019",
    "sg:postcode":"B4V 2W1",
    "sg:province":"NS",
    "sg:tags":[
        "upholsterer"
    ],
    "wof:name":"Bridgewater Uphlstry & Supls",
    "wof:placetype":"venue"
},
  "geometry": {"coordinates":[-64.5230331421,44.3804969788],"type":"Point"}
}