{
  "type": "Feature",
  "properties": {
    "iso:country":"CA",
    "sg:address":"21 Water St W",
    "sg:city":"Elora",
    "sg:classifiers":[
        {
            "category":"Shopping",
            "subcategory":"Bicycles & Sporting Goods",
            "type":"Retail Goods"
        }
    ],
    "sg:phone":"+1 519 846 8196",
    "sg:postcode":"N0B 1S0",
    "sg:province":"ON",
    "wof:name":"Water Street Cycleworks",
    "wof:placetype":"venue"
},
  "geometry": {"coordinates":[-80.4295578003,43.678653717],"type":"Point"}
}