{
  "type": "Feature",
  "properties": {
    "addr:full":"2430 133 Rte Saint-Jean-Sur-Richelieu QC J2X 5V3",
    "addr:housenumber":"2430",
    "addr:postcode":"j2x 5v3",
    "addr:street":"133 Rte",
    "iso:country":"CA",
    "sg:address":"2430 133 Rte",
    "sg:city":"Saint-Jean-Sur-Richelieu",
    "sg:classifiers":[
        {
            "category":"Manufacturing",
            "subcategory":"Metals",
            "type":"Manufacturing & Wholesale Goods"
        }
    ],
    "sg:phone":"+1 450 346 0755",
    "sg:postcode":"J2X 5V3",
    "sg:province":"QC",
    "sg:tags":[
        "brass",
        "foundry",
        "bronze"
    ],
    "wof:name":"Bedard Aluminium",
    "wof:placetype":"venue"
},
  "geometry": {"coordinates":[-73.24575042719999,45.4399604797],"type":"Point"}
}