{
  "type": "Feature",
  "properties": {
    "addr:full":"709 100B Ave Dawson Creek BC V1G 1Y2",
    "addr:housenumber":"709",
    "addr:postcode":"v1g 1y2",
    "addr:street":"100B Ave",
    "iso:country":"CA",
    "sg:address":"709 100B Ave",
    "sg:city":"Dawson Creek",
    "sg:classifiers":[
        {
            "category":"Freight",
            "type":"Transportation"
        }
    ],
    "sg:phone":"+1 250 782 1567",
    "sg:postcode":"V1G 1Y2",
    "sg:province":"BC",
    "sg:tags":[
        "building",
        "commercial"
    ],
    "wof:name":"Busy Bee Storage Systems",
    "wof:placetype":"venue"
},
  "geometry": {"coordinates":[-120.237060547,55.7617263794],"type":"Point"}
}