{
  "type": "Feature",
  "properties": {
    "addr:full":"39 Reaney Crt Kanata ON K2K 1W7",
    "addr:housenumber":"39",
    "addr:postcode":"k2k 1w7",
    "addr:street":"Reaney Crt",
    "iso:country":"CA",
    "sg:address":"39 Reaney Crt",
    "sg:city":"Kanata",
    "sg:classifiers":[
        {
            "category":"Building & Trades",
            "subcategory":"Construction",
            "type":"Services"
        }
    ],
    "sg:phone":"+1 613 599 1114",
    "sg:postcode":"K2K 1W7",
    "sg:province":"ON",
    "sg:tags":[
        "home",
        "improvement"
    ],
    "wof:name":"Meticulous Renovations",
    "wof:placetype":"venue"
},
  "geometry": {"coordinates":[-75.901253,45.320328],"type":"Point"}
}