{
  "type": "Feature",
  "properties": {
    "addr:full":"111 Ch Du Parc-Industriel Senneterre QC J0Y 2M0",
    "addr:housenumber":"111",
    "addr:postcode":"j0y 2m0",
    "addr:street":"Ch Du Parc-Industriel",
    "iso:country":"CA",
    "sg:address":"111 Ch Du Parc-Industriel",
    "sg:city":"Senneterre",
    "sg:classifiers":[
        {
            "category":"Manufacturing",
            "subcategory":"Tools & Machinery",
            "type":"Manufacturing & Wholesale Goods"
        }
    ],
    "sg:phone":"+1 819 737 4040",
    "sg:postcode":"J0Y 2M0",
    "sg:province":"QC",
    "sg:tags":[
        "machine",
        "shop"
    ],
    "wof:name":"Usipro Inc",
    "wof:placetype":"venue"
},
  "geometry": {"coordinates":[-77.220596,48.374416],"type":"Point"}
}