{
  "type": "Feature",
  "properties": {
    "addr:full":"3857 Rue Martial Montreal-Nord QC H1H 1W6",
    "addr:housenumber":"3857",
    "addr:postcode":"h1h 1w6",
    "addr:street":"Rue Martial",
    "iso:country":"CA",
    "sg:address":"3857 Rue Martial",
    "sg:city":"Montreal-Nord",
    "sg:classifiers":[
        {
            "category":"Food & Beverages",
            "subcategory":"Groceries & Convenience Stores",
            "type":"Retail Goods"
        }
    ],
    "sg:phone":"+1 514 323 2192",
    "sg:postcode":"H1H 1W6",
    "sg:province":"QC",
    "sg:tags":[
        "grocer"
    ],
    "wof:name":"Marche Cherrier",
    "wof:placetype":"venue"
},
  "geometry": {"coordinates":[-73.642044,45.590439],"type":"Point"}
}