{
  "type": "Feature",
  "properties": {
    "iso:country":"CA",
    "sg:address":"6491 Jeanne D'Arc Blvd N",
    "sg:city":"Orleans",
    "sg:classifiers":[
        {
            "category":"Government",
            "subcategory":"Post Office",
            "type":"Public Place"
        }
    ],
    "sg:phone":"+1 613 837 1521",
    "sg:postcode":"K1C 2R1",
    "sg:province":"ON",
    "sg:tags":[
        "pharmacy"
    ],
    "wof:name":"Shoppers Drug Mart",
    "wof:placetype":"venue"
},
  "geometry": {"coordinates":[-75.53759765620001,45.4789581299],"type":"Point"}
}