{
  "type": "Feature",
  "properties": {
    "iso:country":"CA",
    "sg:address":"1105 Wellington Rd",
    "sg:city":"London",
    "sg:classifiers":[
        {
            "category":"Shopping",
            "subcategory":"Jewelry",
            "type":"Retail Goods"
        }
    ],
    "sg:phone":"+1 519 681 5730",
    "sg:postcode":"N6E 1V4",
    "sg:province":"ON",
    "sg:tags":[
        "jeweler"
    ],
    "wof:name":"Mappins Jewellers",
    "wof:placetype":"venue"
},
  "geometry": {"coordinates":[-81.221642,42.931622],"type":"Point"}
}