{
  "type": "Feature",
  "properties": {
    "addr:full":"30 Corby Ave York ON M6E 1V1",
    "addr:housenumber":"30",
    "addr:postcode":"m6e 1v1",
    "addr:street":"Corby Ave",
    "iso:country":"CA",
    "sg:address":"30 Corby Ave",
    "sg:city":"York",
    "sg:classifiers":[
        {
            "category":"Shopping",
            "subcategory":"Discount & Variety Stores",
            "type":"Retail Goods"
        }
    ],
    "sg:phone":"+1 416 656 9228",
    "sg:postcode":"M6E 1V1",
    "sg:province":"ON",
    "wof:name":"Caledonia Variety",
    "wof:placetype":"venue"
},
  "geometry": {"coordinates":[-79.4585647583,43.6847801208],"type":"Point"}
}