{
  "type": "Feature",
  "properties": {
    "addr:full":"303 5th St E Cornwall ON K6H 2L9",
    "addr:housenumber":"303",
    "addr:postcode":"k6h 2l9",
    "addr:street":"5Th St E",
    "iso:country":"CA",
    "sg:address":"303 5th St E",
    "sg:city":"Cornwall",
    "sg:classifiers":[
        {
            "category":"Building & Trades",
            "subcategory":"Construction",
            "type":"Services"
        }
    ],
    "sg:phone":"+1 613 936 2518",
    "sg:postcode":"K6H 2L9",
    "sg:province":"ON",
    "sg:tags":[
        "repair",
        "general",
        "concrete",
        "restoration",
        "cleaning",
        "contractor"
    ],
    "wof:name":"Porter's Restoration",
    "wof:placetype":"venue"
},
  "geometry": {"coordinates":[-74.72473144529999,45.0247268677],"type":"Point"}
}