{
  "type": "Feature",
  "properties": {
    "addr:full":"5407 51 St Eckville AB T0M 0X0",
    "addr:housenumber":"5407",
    "addr:postcode":"t0m 0x0",
    "addr:street":"51 St",
    "iso:country":"CA",
    "sg:address":"5407 51 St",
    "sg:city":"Eckville",
    "sg:classifiers":[
        {
            "category":"Government",
            "subcategory":"Office",
            "type":"Public Place"
        }
    ],
    "sg:phone":"+1 403 746 2335",
    "sg:postcode":"T0M 0X0",
    "sg:province":"AB",
    "sg:tags":[
        "village"
    ],
    "wof:name":"Eckville Work Shop",
    "wof:placetype":"venue"
},
  "geometry": {"coordinates":[-114.37030792199999,52.3631019592],"type":"Point"}
}