{
  "type": "Feature",
  "properties": {
    "addr:full":"871 13th Ave Campbell River BC V9W 4G9",
    "addr:housenumber":"871",
    "addr:postcode":"v9w 4g9",
    "addr:street":"13Th Ave",
    "iso:country":"CA",
    "sg:address":"871 13th Ave",
    "sg:city":"Campbell River",
    "sg:classifiers":[
        {
            "category":"Shopping",
            "subcategory":"Bicycles & Sporting Goods",
            "type":"Retail Goods"
        }
    ],
    "sg:phone":"+1 250 286 0500",
    "sg:postcode":"V9W 4G9",
    "sg:province":"BC",
    "wof:name":"Spokes",
    "wof:placetype":"venue"
},
  "geometry": {"coordinates":[-125.25352478000001,50.0279388428],"type":"Point"}
}