{
  "type": "Feature",
  "properties": {
    "addr:full":"510 Danforth Ave Toronto ON M4K 1P6",
    "addr:housenumber":"510",
    "addr:postcode":"m4k 1p6",
    "addr:street":"Danforth Ave",
    "iso:country":"CA",
    "sg:address":"510 Danforth Ave",
    "sg:city":"Toronto",
    "sg:classifiers":[
        {
            "category":"Shopping",
            "subcategory":"Shoes",
            "type":"Retail Goods"
        }
    ],
    "sg:phone":"+1 416 465 7253",
    "sg:postcode":"M4K 1P6",
    "sg:province":"ON",
    "wof:name":"Signature Shoes",
    "wof:placetype":"venue"
},
  "geometry": {"coordinates":[-79.348854,43.678272],"type":"Point"}
}