{
  "type": "Feature",
  "properties": {
    "addr:full":"Endeavour SK S0A 0W0",
    "addr:postcode":"s0a 0w0",
    "iso:country":"CA",
    "sg:city":"Endeavour",
    "sg:classifiers":[
        {
            "category":"Autos & Motor Vehicles",
            "subcategory":"Fuel & Gas Station",
            "type":"Retail Goods"
        }
    ],
    "sg:phone":"+1 306 547 4756",
    "sg:postcode":"S0A 0W0",
    "sg:province":"SK",
    "sg:tags":[
        "oil"
    ],
    "wof:name":"Usherville Corner Svc",
    "wof:placetype":"venue"
},
  "geometry": {"coordinates":[-102.65838599999999,52.158249],"type":"Point"}
}