{
  "type": "Feature",
  "properties": {
    "addr:full":"5490 Montee Saint-Hubert Saint-Hubert QC J3Y 1V9",
    "addr:housenumber":"5490",
    "addr:postcode":"j3y 1v9",
    "addr:street":"Montee Saint-Hubert",
    "iso:country":"CA",
    "sg:address":"5490 Montee Saint-Hubert",
    "sg:city":"Saint-Hubert",
    "sg:classifiers":[
        {
            "category":"Bars & Pubs",
            "type":"Food & Drink"
        }
    ],
    "sg:phone":"+1 450 445 1599",
    "sg:postcode":"J3Y 1V9",
    "sg:province":"QC",
    "wof:name":"Brasserie Lexus",
    "wof:placetype":"venue"
},
  "geometry": {"coordinates":[-73.4494400024,45.4792327881],"type":"Point"}
}