{
  "type": "Feature",
  "properties": {
    "addr:full":"369 Townsend St Sydney NS B1P 5G3",
    "addr:housenumber":"369",
    "addr:postcode":"b1p 5g3",
    "addr:street":"Townsend St",
    "iso:country":"CA",
    "sg:address":"369 Townsend St",
    "sg:city":"Sydney",
    "sg:classifiers":[
        {
            "category":"Organizations",
            "subcategory":"Non-profit Organization",
            "type":"Services"
        }
    ],
    "sg:phone":"+1 902 562 6016",
    "sg:postcode":"B1P 5G3",
    "sg:province":"NS",
    "sg:tags":[
        "charitable",
        "institution"
    ],
    "wof:name":"Resi-Care Cb Assoc",
    "wof:placetype":"venue"
},
  "geometry": {"coordinates":[-60.1830101013,46.1371154785],"type":"Point"}
}