{
  "type": "Feature",
  "properties": {
    "addr:full":"271 Boul Arthur-Sauve Saint-Eustache QC J7P 2A9",
    "addr:housenumber":"271",
    "addr:postcode":"j7p 2a9",
    "addr:street":"Boul Arthur-Sauve",
    "iso:country":"CA",
    "sg:address":"271 Boul Arthur-Sauve",
    "sg:city":"Saint-Eustache",
    "sg:classifiers":[
        {
            "category":"Professional",
            "subcategory":"Accounting & Tax Preparation",
            "type":"Services"
        }
    ],
    "sg:phone":"+1 450 491 1155",
    "sg:postcode":"J7P 2A9",
    "sg:province":"QC",
    "sg:tags":[
        "accountant",
        "management"
    ],
    "wof:name":"Boisvert & Boisvert Gestion",
    "wof:placetype":"venue"
},
  "geometry": {"coordinates":[-73.89872,45.561089],"type":"Point"}
}