{
  "type": "Feature",
  "properties": {
    "addr:full":"431 Rue Soumande Vanier QC G1M 2X6",
    "addr:housenumber":"431",
    "addr:postcode":"g1m 2x6",
    "addr:street":"Rue Soumande",
    "iso:country":"CA",
    "sg:address":"431 Rue Soumande",
    "sg:city":"Vanier",
    "sg:classifiers":[
        {
            "category":"Personal",
            "subcategory":"Beauty Salon",
            "type":"Services"
        }
    ],
    "sg:phone":"+1 418 688 3038",
    "sg:postcode":"G1M 2X6",
    "sg:province":"QC",
    "wof:name":"Coiffure Pro-Style Inc",
    "wof:placetype":"venue"
},
  "geometry": {"coordinates":[-71.2550201416,46.8210334778],"type":"Point"}
}