{
  "type": "Feature",
  "properties": {
    "addr:full":"Sainte-Foy QC G1V 2M2",
    "addr:postcode":"g1v 2m2",
    "iso:country":"CA",
    "sg:city":"Sainte-Foy",
    "sg:classifiers":[
        {
            "category":"Professional",
            "type":"Services"
        }
    ],
    "sg:phone":"+1 418 657 3853",
    "sg:postcode":"G1V 2M2",
    "sg:province":"QC",
    "sg:tags":[
        "scientist"
    ],
    "wof:name":"Centre Quebecois Valorisation",
    "wof:placetype":"venue"
},
  "geometry": {"coordinates":[-71.2896194458,46.7663269043],"type":"Point"}
}