{
  "type": "Feature",
  "properties": {
    "iso:country":"CA",
    "sg:address":"54 Rue Saint-Jacques",
    "sg:city":"Saint-Jean-Sur-Richelieu",
    "sg:classifiers":[
        {
            "category":"Professional",
            "subcategory":"Accounting & Tax Preparation",
            "type":"Services"
        }
    ],
    "sg:phone":"+1 450 347 2666",
    "sg:postcode":"J3B 2J9",
    "sg:province":"QC",
    "sg:tags":[
        "accountant"
    ],
    "wof:name":"Boulais Derrien Senc",
    "wof:placetype":"venue"
},
  "geometry": {"coordinates":[-73.2523727417,45.3059196472],"type":"Point"}
}