{
  "type": "Feature",
  "properties": {
    "addr:full":"Calgary AB T2V 4J8",
    "addr:postcode":"t2v 4j8",
    "iso:country":"CA",
    "sg:city":"Calgary",
    "sg:classifiers":[
        {
            "category":"Professional",
            "subcategory":"Business Services",
            "type":"Services"
        }
    ],
    "sg:phone":"+1 403 251 0311",
    "sg:postcode":"T2V 4J8",
    "sg:province":"AB",
    "sg:tags":[
        "license"
    ],
    "wof:name":"Wild Rose License & Registry",
    "wof:placetype":"venue"
},
  "geometry": {"coordinates":[-114.121002197,50.9610977173],"type":"Point"}
}