{
  "type": "Feature",
  "properties": {
    "addr:full":"484 Grand Lake Rd Sydney NS B1P 5S8",
    "addr:housenumber":"484",
    "addr:postcode":"b1p 5s8",
    "addr:street":"Grand Lake Rd",
    "iso:country":"CA",
    "sg:address":"484 Grand Lake Rd",
    "sg:city":"Sydney",
    "sg:classifiers":[
        {
            "category":"Shopping",
            "subcategory":"Computers & Home Electronics",
            "type":"Retail Goods"
        }
    ],
    "sg:phone":"+1 902 564 9400",
    "sg:postcode":"B1P 5S8",
    "sg:province":"NS",
    "sg:tags":[
        "equipment",
        "dealer"
    ],
    "wof:name":"Soundafex",
    "wof:placetype":"venue"
},
  "geometry": {"coordinates":[-60.128559,46.153339],"type":"Point"}
}