{
  "type": "Feature",
  "properties": {
    "addr:full":"1175 Main St E Hamilton ON L8M 1P3",
    "addr:housenumber":"1175",
    "addr:postcode":"l8m 1p3",
    "addr:street":"Main St E",
    "iso:country":"CA",
    "sg:address":"1175 Main St E",
    "sg:city":"Hamilton",
    "sg:classifiers":[
        {
            "category":"Education",
            "subcategory":"School",
            "type":"Public Place"
        }
    ],
    "sg:phone":"+1 905 549 3095",
    "sg:postcode":"L8M 1P3",
    "sg:province":"ON",
    "wof:name":"Memorial School",
    "wof:placetype":"venue"
},
  "geometry": {"coordinates":[-79.8203201294,43.2428283691],"type":"Point"}
}