{
  "type": "Feature",
  "properties": {
    "addr:full":"8627 91 St NW # 303 Edmonton AB T6C 3N1",
    "addr:housenumber":"8627",
    "addr:postcode":"t6c 3n1",
    "addr:street":"91 St Nw # 303",
    "iso:country":"CA",
    "sg:address":"8627 91 St NW # 303",
    "sg:city":"Edmonton",
    "sg:classifiers":[
        {
            "category":"Organizations",
            "subcategory":"Professional Association",
            "type":"Services"
        }
    ],
    "sg:phone":"+1 780 466 1680",
    "sg:postcode":"T6C 3N1",
    "sg:province":"AB",
    "wof:name":"Association Canadienne-Frncs",
    "wof:placetype":"venue"
},
  "geometry": {"coordinates":[-113.467209,53.522552],"type":"Point"}
}