{
  "type": "Feature",
  "properties": {
    "addr:full":"103 Queensway E Simcoe ON N3Y 4M5",
    "addr:housenumber":"103",
    "addr:postcode":"n3y 4m5",
    "addr:street":"Queensway E",
    "iso:country":"CA",
    "sg:address":"103 Queensway E",
    "sg:city":"Simcoe",
    "sg:classifiers":[
        {
            "category":"Real Estate",
            "subcategory":"Real Estate Agent",
            "type":"Services"
        }
    ],
    "sg:phone":"+1 519 426 0081",
    "sg:postcode":"N3Y 4M5",
    "sg:province":"ON",
    "wof:name":"Proctor, Don",
    "wof:placetype":"venue"
},
  "geometry": {"coordinates":[-80.29596710209999,42.8479804993],"type":"Point"}
}