{
  "type": "Feature",
  "properties": {
    "addr:full":"Burnaby BC V5H 4T9",
    "addr:postcode":"v5h 4t9",
    "iso:country":"CA",
    "sg:city":"Burnaby",
    "sg:classifiers":[
        {
            "category":"Organizations",
            "subcategory":"Religious Organization",
            "type":"Services"
        }
    ],
    "sg:phone":"+1 604 438 2848",
    "sg:postcode":"V5H 4T9",
    "sg:province":"BC",
    "sg:tags":[
        "church"
    ],
    "wof:name":"Passing on Mission",
    "wof:placetype":"venue"
},
  "geometry": {"coordinates":[-123.00403595,49.2298088074],"type":"Point"}
}