{
  "type": "Feature",
  "properties": {
    "addr:full":"Concord ON L4K 1K7",
    "addr:postcode":"l4k 1k7",
    "iso:country":"CA",
    "sg:city":"Concord",
    "sg:classifiers":[
        {
            "category":"Wholesale",
            "subcategory":"Groceries",
            "type":"Manufacturing & Wholesale Goods"
        }
    ],
    "sg:phone":"+1 905 660 9989",
    "sg:postcode":"L4K 1K7",
    "sg:province":"ON",
    "sg:tags":[
        "beverage"
    ],
    "wof:name":"Damon Industries Canada Ltd",
    "wof:placetype":"venue"
},
  "geometry": {"coordinates":[-79.487793,43.815418],"type":"Point"}
}