{
  "type": "Feature",
  "properties": {
    "addr:full":"130 6E Rue Ferme-Neuve QC J0W 1C0",
    "addr:housenumber":"130",
    "addr:postcode":"j0w 1c0",
    "addr:street":"6E Rue",
    "iso:country":"CA",
    "sg:address":"130 6E Rue",
    "sg:city":"Ferme-Neuve",
    "sg:classifiers":[
        {
            "category":"Personal",
            "subcategory":"Tanning Parlor",
            "type":"Services"
        }
    ],
    "sg:phone":"+1 819 587 4414",
    "sg:postcode":"J0W 1C0",
    "sg:province":"QC",
    "sg:tags":[
        "salon"
    ],
    "wof:name":"Salon D'Esthetique Manon Enr",
    "wof:placetype":"venue"
},
  "geometry": {"coordinates":[-75.45246899999999,46.696735],"type":"Point"}
}