{
  "type": "Feature",
  "properties": {
    "addr:full":"1532 Pelham St Fonthill ON L0S 1E3",
    "addr:housenumber":"1532",
    "addr:postcode":"l0s 1e3",
    "addr:street":"Pelham St",
    "iso:country":"CA",
    "sg:address":"1532 Pelham St",
    "sg:city":"Fonthill",
    "sg:classifiers":[
        {
            "category":"Health Services",
            "subcategory":"Nursing And Care Facility",
            "type":"Services"
        }
    ],
    "sg:phone":"+1 905 892 5094",
    "sg:postcode":"L0S 1E3",
    "sg:province":"ON",
    "sg:tags":[
        "home",
        "retirement",
        "community"
    ],
    "wof:name":"Shorthills Villa Retirement",
    "wof:placetype":"venue"
},
  "geometry": {"coordinates":[-79.285645,43.046631],"type":"Point"}
}