{
  "type": "Feature",
  "properties": {
    "addr:full":"300 King St W Hamilton ON L8P 1B1",
    "addr:housenumber":"300",
    "addr:postcode":"l8p 1b1",
    "addr:street":"King St W",
    "iso:country":"CA",
    "sg:address":"300 King St W",
    "sg:city":"Hamilton",
    "sg:classifiers":[
        {
            "category":"Shopping",
            "subcategory":"Clothing, Apparel, & Fashions",
            "type":"Retail Goods"
        }
    ],
    "sg:phone":"+1 905 521 9577",
    "sg:postcode":"L8P 1B1",
    "sg:province":"ON",
    "sg:tags":[
        "infant",
        "wear"
    ],
    "wof:name":"Mon Petit Chou",
    "wof:placetype":"venue"
},
  "geometry": {"coordinates":[-79.878326,43.25938],"type":"Point"}
}