{
  "type": "Feature",
  "properties": {
    "addr:full":"301 1st St Reston MB R0M 1X0",
    "addr:housenumber":"301",
    "addr:postcode":"r0m 1x0",
    "addr:street":"1St St",
    "iso:country":"CA",
    "sg:address":"301 1st St",
    "sg:city":"Reston",
    "sg:classifiers":[
        {
            "category":"Recreation",
            "type":"Entertainment"
        }
    ],
    "sg:phone":"+1 204 877 3511",
    "sg:postcode":"R0M 1X0",
    "sg:province":"MB",
    "sg:tags":[
        "course",
        "golf"
    ],
    "wof:name":"Reston Golf Club",
    "wof:placetype":"venue"
},
  "geometry": {"coordinates":[-101.094970703,49.5622596741],"type":"Point"}
}