{
  "type": "Feature",
  "properties": {
    "addr:full":"990 3rd Ave W Owen Sound ON N4K 4P6",
    "addr:housenumber":"990",
    "addr:postcode":"n4k 4p6",
    "addr:street":"3Rd Ave W",
    "iso:country":"CA",
    "sg:address":"990 3rd Ave W",
    "sg:city":"Owen Sound",
    "sg:classifiers":[
        {
            "category":"Health Services",
            "subcategory":"Doctor",
            "type":"Services"
        }
    ],
    "sg:phone":"+1 519 376 9144",
    "sg:postcode":"N4K 4P6",
    "sg:province":"ON",
    "sg:tags":[
        "physician",
        "surgeon"
    ],
    "wof:name":"Lewis, David C MD",
    "wof:placetype":"venue"
},
  "geometry": {"coordinates":[-80.94789886469999,44.5668373108],"type":"Point"}
}