{
  "type": "Feature",
  "properties": {
    "addr:full":"7366 Industrial Way Pemberton BC V0N 2L0",
    "addr:housenumber":"7366",
    "addr:postcode":"v0n 2l0",
    "addr:street":"Industrial Way",
    "iso:country":"CA",
    "sg:address":"7366 Industrial Way",
    "sg:city":"Pemberton",
    "sg:classifiers":[
        {
            "category":"Freight",
            "type":"Transportation"
        }
    ],
    "sg:phone":"+1 604 894 6995",
    "sg:postcode":"V0N 2L0",
    "sg:province":"BC",
    "sg:tags":[
        "commercial",
        "storage"
    ],
    "wof:name":"Mountainview Storage",
    "wof:placetype":"venue"
},
  "geometry": {"coordinates":[-122.726837158,50.311290741],"type":"Point"}
}