{
  "type": "Feature",
  "properties": {
    "addr:full":"Three Hills AB T0M 2A0",
    "addr:postcode":"t0m 2a0",
    "iso:country":"CA",
    "sg:city":"Three Hills",
    "sg:classifiers":[
        {
            "category":"Mining & Drilling",
            "type":"Manufacturing & Wholesale Goods"
        }
    ],
    "sg:phone":"+1 403 443 2202",
    "sg:postcode":"T0M 2A0",
    "sg:province":"AB",
    "sg:tags":[
        "field",
        "oil"
    ],
    "wof:name":"Three Hills Light Oilfield Svc",
    "wof:placetype":"venue"
},
  "geometry": {"coordinates":[-113.274635,51.699562],"type":"Point"}
}