{
  "type": "Feature",
  "properties": {
    "addr:full":"6320 Highway 6 Coldstream BC V1B 3C7",
    "addr:housenumber":"6320",
    "addr:postcode":"bc v1b 3c7",
    "addr:street":"Highway 6",
    "iso:country":"CA",
    "sg:address":"6320 Highway 6",
    "sg:city":"Coldstream",
    "sg:classifiers":[
        {
            "category":"Food & Beverages",
            "subcategory":"Groceries & Convenience Stores",
            "type":"Retail Goods"
        }
    ],
    "sg:phone":"+1 250 545 8370",
    "sg:postcode":"V1B 3C7",
    "sg:province":"BC",
    "wof:name":"Lavington Shell Market",
    "wof:placetype":"venue"
},
  "geometry": {"coordinates":[-119.23594665500001,50.2440376282],"type":"Point"}
}