{
  "type": "Feature",
  "properties": {
    "addr:full":"Red Deer AB T4N 4L2",
    "addr:postcode":"t4n 4l2",
    "iso:country":"CA",
    "sg:city":"Red Deer",
    "sg:classifiers":[
        {
            "category":"Manufacturing",
            "subcategory":"Metals",
            "type":"Manufacturing & Wholesale Goods"
        }
    ],
    "sg:phone":"+1 403 314 3208",
    "sg:postcode":"T4N 4L2",
    "sg:province":"AB",
    "sg:tags":[
        "coating"
    ],
    "wof:name":"Canwest Protective Coatings",
    "wof:placetype":"venue"
},
  "geometry": {"coordinates":[-113.816650391,52.2938423157],"type":"Point"}
}