{
  "type": "Feature",
  "properties": {
    "addr:full":"384 Richmond St Chatham ON N7M 1P9",
    "addr:housenumber":"384",
    "addr:postcode":"n7m 1p9",
    "addr:street":"Richmond St",
    "iso:country":"CA",
    "sg:address":"384 Richmond St",
    "sg:city":"Chatham",
    "sg:classifiers":[
        {
            "category":"Autos & Motor Vehicles",
            "subcategory":"Automobile Sales",
            "type":"Retail Goods"
        }
    ],
    "sg:phone":"+1 519 354 5530",
    "sg:postcode":"N7M 1P9",
    "sg:province":"ON",
    "sg:tags":[
        "car",
        "dealer"
    ],
    "wof:name":"Honda House Chatham Ont",
    "wof:placetype":"venue"
},
  "geometry": {"coordinates":[-82.19555699999999,42.392998],"type":"Point"}
}