{
  "type": "Feature",
  "properties": {
    "iso:country":"CA",
    "sg:address":"10 Croft St",
    "sg:city":"Amherst",
    "sg:classifiers":[
        {
            "category":"Manufacturing",
            "subcategory":"Retail Goods",
            "type":"Manufacturing & Wholesale Goods"
        }
    ],
    "sg:phone":"+1 902 667 8433",
    "sg:postcode":"B4H 2Z4",
    "sg:province":"NS",
    "sg:tags":[
        "charitable",
        "button",
        "institution",
        "maker"
    ],
    "wof:name":"Bridge Adult Svc Ctr",
    "wof:placetype":"venue"
},
  "geometry": {"coordinates":[-64.20821380620001,45.83045578],"type":"Point"}
}