{
  "type": "Feature",
  "properties": {
    "addr:full":"108 Industrial Dr Balcarres SK S0G 0C0",
    "addr:housenumber":"108",
    "addr:postcode":"s0g 0c0",
    "addr:street":"Industrial Dr",
    "iso:country":"CA",
    "sg:address":"108 Industrial Dr",
    "sg:city":"Balcarres",
    "sg:classifiers":[
        {
            "category":"Manufacturing",
            "subcategory":"Glass & Minerals",
            "type":"Manufacturing & Wholesale Goods"
        }
    ],
    "sg:phone":"+1 306 334 2662",
    "sg:postcode":"S0G 0C0",
    "sg:province":"SK",
    "sg:tags":[
        "fabricator",
        "fiber"
    ],
    "wof:name":"Ecl Fibreglass Mfg Inc",
    "wof:placetype":"venue"
},
  "geometry": {"coordinates":[-103.54782104500001,50.798160553],"type":"Point"}
}