{
  "type": "Feature",
  "properties": {
    "addr:full":"346 Ch Saint-Charles Sud Saint-Charles NB E4W 4X4",
    "addr:housenumber":"346",
    "addr:postcode":"e4w 4x4",
    "addr:street":"Ch Saint-Charles Sud",
    "iso:country":"CA",
    "sg:address":"346 Ch Saint-Charles Sud",
    "sg:city":"Saint-Charles",
    "sg:classifiers":[
        {
            "category":"Retail",
            "subcategory":"Auto Repair",
            "type":"Services"
        }
    ],
    "sg:phone":"+1 506 876 4587",
    "sg:postcode":"E4W 4X4",
    "sg:province":"NB",
    "sg:tags":[
        "repairing",
        "automobile"
    ],
    "wof:name":"Richard Gilles Auto Repair",
    "wof:placetype":"venue"
},
  "geometry": {"coordinates":[-64.93640899659999,46.6980819702],"type":"Point"}
}