{
  "type": "Feature",
  "properties": {
    "addr:full":"Sussex NB E4E 3E6",
    "addr:postcode":"e4e 3e6",
    "iso:country":"CA",
    "sg:city":"Sussex",
    "sg:classifiers":[
        {
            "category":"Restaurant",
            "type":"Food & Drink"
        }
    ],
    "sg:phone":"+1 506 433 5156",
    "sg:postcode":"E4E 3E6",
    "sg:province":"NB",
    "wof:name":"Kfc",
    "wof:placetype":"venue"
},
  "geometry": {"coordinates":[-65.52615400000001,45.724743],"type":"Point"}
}