{
  "type": "Feature",
  "properties": {
    "iso:country":"CA",
    "sg:city":"Terrace",
    "sg:classifiers":[
        {
            "category":"Shopping",
            "subcategory":"Gifts & Souvenirs",
            "type":"Retail Goods"
        }
    ],
    "sg:phone":"+1 250 638 7788",
    "sg:postcode":"V8G 4R9",
    "sg:province":"BC",
    "sg:tags":[
        "collectible"
    ],
    "wof:name":"Sonny's Collectibles",
    "wof:placetype":"venue"
},
  "geometry": {"coordinates":[-128.595504761,54.5169334412],"type":"Point"}
}