{
  "type": "Feature",
  "properties": {
    "addr:full":"185106 Cornell Rd Tillsonburg ON N4G 4G8",
    "addr:housenumber":"185106",
    "addr:postcode":"n4g 4g8",
    "addr:street":"Cornell Rd",
    "iso:country":"CA",
    "sg:address":"185106 Cornell Rd",
    "sg:city":"Tillsonburg",
    "sg:classifiers":[
        {
            "category":"Wholesale",
            "subcategory":"Farm Supplies",
            "type":"Manufacturing & Wholesale Goods"
        }
    ],
    "sg:phone":"+1 519 842 5618",
    "sg:postcode":"N4G 4G8",
    "sg:province":"ON",
    "wof:name":"Canest Equipment Ltd",
    "wof:placetype":"venue"
},
  "geometry": {"coordinates":[-80.7278671265,42.8606758118],"type":"Point"}
}