{
  "type": "Feature",
  "properties": {
    "addr:full":"Etobicoke ON M9A 3T7",
    "addr:postcode":"m9a 3t7",
    "iso:country":"CA",
    "sg:city":"Etobicoke",
    "sg:classifiers":[
        {
            "category":"Shopping",
            "subcategory":"Shoes",
            "type":"Retail Goods"
        }
    ],
    "sg:phone":"+1 416 237 9757",
    "sg:postcode":"M9A 3T7",
    "sg:province":"ON",
    "wof:name":"Adrian's",
    "wof:placetype":"venue"
},
  "geometry": {"coordinates":[-79.5201034546,43.6628723145],"type":"Point"}
}