{
  "type": "Feature",
  "properties": {
    "addr:full":"2825 Rue Sabourin Saint-Laurent QC H4S 1M9",
    "addr:housenumber":"2825",
    "addr:postcode":"h4s 1m9",
    "addr:street":"Rue Sabourin",
    "iso:country":"CA",
    "sg:address":"2825 Rue Sabourin",
    "sg:city":"Saint-Laurent",
    "sg:classifiers":[
        {
            "category":"Retail",
            "subcategory":"Repair Shop",
            "type":"Services"
        }
    ],
    "sg:phone":"+1 514 745 1007",
    "sg:postcode":"H4S 1M9",
    "sg:province":"QC",
    "sg:tags":[
        "equipment"
    ],
    "wof:name":"Thomas Pieces & Accessoires",
    "wof:placetype":"venue"
},
  "geometry": {"coordinates":[-73.749352,45.493027],"type":"Point"}
}