{
  "type": "Feature",
  "properties": {
    "iso:country":"CA",
    "sg:address":"311 Rothesay Ave",
    "sg:city":"Saint John",
    "sg:classifiers":[
        {
            "category":"Wholesale",
            "subcategory":"Machinery & Supplies",
            "type":"Manufacturing & Wholesale Goods"
        }
    ],
    "sg:phone":"+1 506 634 7763",
    "sg:postcode":"E2J 2C1",
    "sg:province":"NB",
    "sg:tags":[
        "equipment",
        "pneumatic",
        "component",
        "valve"
    ],
    "wof:name":"Cowper Inc",
    "wof:placetype":"venue"
},
  "geometry": {"coordinates":[-66.042152,45.294323],"type":"Point"}
}