{
  "type": "Feature",
  "properties": {
    "addr:full":"2121 39 Ave NE #E Calgary AB T2E 6R7",
    "addr:housenumber":"2121",
    "addr:postcode":"t2e 6r7",
    "addr:street":"39 Ave Ne # E",
    "iso:country":"CA",
    "sg:address":"2121 39 Ave NE #E",
    "sg:city":"Calgary",
    "sg:classifiers":[
        {
            "category":"Manufacturing",
            "subcategory":"Glass & Minerals",
            "type":"Manufacturing & Wholesale Goods"
        }
    ],
    "sg:phone":"+1 403 443 7147",
    "sg:postcode":"T2E 6R7",
    "sg:province":"AB",
    "sg:tags":[
        "instrument",
        "scientific",
        "apparatus"
    ],
    "wof:name":"Automation Instruments Mfg Inc",
    "wof:placetype":"venue"
},
  "geometry": {"coordinates":[-114.00981140099999,51.0882072449],"type":"Point"}
}