{
  "type": "Feature",
  "properties": {
    "addr:full":"6205 10 St SE Calgary AB T2H 2Z9",
    "addr:housenumber":"6205",
    "addr:postcode":"t2h 2z9",
    "addr:street":"10 St Se",
    "iso:country":"CA",
    "sg:address":"6205 10 St SE",
    "sg:city":"Calgary",
    "sg:classifiers":[
        {
            "category":"Manufacturing",
            "subcategory":"Tools & Machinery",
            "type":"Manufacturing & Wholesale Goods"
        }
    ],
    "sg:phone":"+1 403 571 7273",
    "sg:postcode":"T2H 2Z9",
    "sg:province":"AB",
    "sg:tags":[
        "equipment",
        "system",
        "automation"
    ],
    "wof:name":"Advanced Measurements",
    "wof:placetype":"venue"
},
  "geometry": {"coordinates":[-114.04048899999999,50.997566],"type":"Point"}
}