{
  "type": "Feature",
  "properties": {
    "iso:country":"CA",
    "sg:address":"5396 Rue Frontenac",
    "sg:city":"Lac-Megantic",
    "sg:classifiers":[
        {
            "category":"Restaurant",
            "type":"Food & Drink"
        }
    ],
    "sg:phone":"+1 819 583 5353",
    "sg:postcode":"G6B 1H3",
    "sg:province":"QC",
    "wof:name":"Manoir Morrison",
    "wof:placetype":"venue"
},
  "geometry": {"coordinates":[-70.8824234009,45.5751838684],"type":"Point"}
}