{
  "type": "Feature",
  "properties": {
    "addr:full":"5019 47A Ave Sylvan Lake AB T4S 1G8",
    "addr:housenumber":"5019",
    "addr:postcode":"t4s 1g8",
    "addr:street":"47A Ave",
    "iso:country":"CA",
    "sg:address":"5019 47A Ave",
    "sg:city":"Sylvan Lake",
    "sg:classifiers":[
        {
            "category":"Retail",
            "subcategory":"Funeral Services",
            "type":"Services"
        }
    ],
    "sg:phone":"+1 403 887 2151",
    "sg:postcode":"T4S 1G8",
    "sg:province":"AB",
    "sg:tags":[
        "director"
    ],
    "wof:name":"Sylvan Lake Funeral Home",
    "wof:placetype":"venue"
},
  "geometry": {"coordinates":[-114.09750366199999,52.3054771423],"type":"Point"}
}