{
  "type": "Feature",
  "properties": {
    "addr:full":"60 St David St Mitchell ON N0K 1N0",
    "addr:housenumber":"60",
    "addr:postcode":"n0k 1n0",
    "addr:street":"St David St",
    "iso:country":"CA",
    "sg:address":"60 St David St",
    "sg:city":"Mitchell",
    "sg:classifiers":[
        {
            "category":"Wholesale",
            "subcategory":"Construction Materials",
            "type":"Manufacturing & Wholesale Goods"
        }
    ],
    "sg:phone":"+1 519 348 8855",
    "sg:postcode":"N0K 1N0",
    "sg:province":"ON",
    "sg:tags":[
        "fence"
    ],
    "wof:name":"Mc Iver Enterprises",
    "wof:placetype":"venue"
},
  "geometry": {"coordinates":[-81.19731899999999,43.462479],"type":"Point"}
}