{
  "type": "Feature",
  "properties": {
    "addr:full":"12 Ch Chapleau Kiamika QC J0W 1G0",
    "addr:housenumber":"12",
    "addr:postcode":"j0w 1g0",
    "addr:street":"Ch Chapleau",
    "iso:country":"CA",
    "sg:address":"12 Ch Chapleau",
    "sg:city":"Kiamika",
    "sg:classifiers":[
        {
            "category":"Manufacturing",
            "subcategory":"Lumber",
            "type":"Manufacturing & Wholesale Goods"
        }
    ],
    "sg:phone":"+1 819 585 3081",
    "sg:postcode":"J0W 1G0",
    "sg:province":"QC",
    "sg:tags":[
        "trucking"
    ],
    "wof:name":"Plouffe & Lefebvre Inc",
    "wof:placetype":"venue"
},
  "geometry": {"coordinates":[-75.375771,46.416203],"type":"Point"}
}