{
  "type": "Feature",
  "properties": {
    "addr:full":"240 Rue Domagaya Gaspe QC G4X 1K8",
    "addr:housenumber":"240",
    "addr:postcode":"g4x 1k8",
    "addr:street":"Rue Domagaya",
    "iso:country":"CA",
    "sg:address":"240 Rue Domagaya",
    "sg:city":"Gaspe",
    "sg:classifiers":[
        {
            "category":"Real Estate",
            "subcategory":"Architect",
            "type":"Services"
        }
    ],
    "sg:phone":"+1 418 368 6778",
    "sg:postcode":"G4X 1K8",
    "sg:province":"QC",
    "wof:name":"Vachon & Roy",
    "wof:placetype":"venue"
},
  "geometry": {"coordinates":[-64.496483,48.832554],"type":"Point"}
}