{
  "type": "Feature",
  "properties": {
    "addr:full":"783 Rue Saint-Joseph E Quebec QC G1K 3C6",
    "addr:housenumber":"783",
    "addr:postcode":"g1k 3c6",
    "addr:street":"Rue Saint-Joseph E",
    "iso:country":"CA",
    "sg:address":"783 Rue Saint-Joseph E",
    "sg:city":"Quebec",
    "sg:classifiers":[
        {
            "category":"Manufacturing",
            "subcategory":"Food",
            "type":"Manufacturing & Wholesale Goods"
        }
    ],
    "sg:phone":"+1 418 652 0708",
    "sg:postcode":"G1K 3C6",
    "sg:province":"QC",
    "sg:tags":[
        "cocoa",
        "chocolate"
    ],
    "wof:name":"Champagne Le Maitre Confiseur",
    "wof:placetype":"venue"
},
  "geometry": {"coordinates":[-71.21932983400001,46.8157196045],"type":"Point"}
}