{
  "type": "Feature",
  "properties": {
    "addr:full":"564 Queen St Chatham ON N7M 2J6",
    "addr:housenumber":"564",
    "addr:postcode":"n7m 2j6",
    "addr:street":"Queen St",
    "iso:country":"CA",
    "sg:address":"564 Queen St",
    "sg:city":"Chatham",
    "sg:classifiers":[
        {
            "category":"Restaurant",
            "type":"Food & Drink"
        }
    ],
    "sg:phone":"+1 519 352 2251",
    "sg:postcode":"N7M 2J6",
    "sg:province":"ON",
    "wof:name":"Mike's Place",
    "wof:placetype":"venue"
},
  "geometry": {"coordinates":[-82.17361450200001,42.393661499],"type":"Point"}
}