{
  "type": "Feature",
  "properties": {
    "addr:full":"700 Rue Ouellette Marieville QC J3M 1P6",
    "addr:housenumber":"700",
    "addr:postcode":"j3m 1p6",
    "addr:street":"Rue Ouellette",
    "iso:country":"CA",
    "sg:address":"700 Rue Ouellette",
    "sg:city":"Marieville",
    "sg:classifiers":[
        {
            "category":"Manufacturing",
            "subcategory":"Metals",
            "type":"Manufacturing & Wholesale Goods"
        }
    ],
    "sg:phone":"+1 450 658 8741",
    "sg:postcode":"J3M 1P6",
    "sg:province":"QC",
    "sg:tags":[
        "fastener",
        "bolt"
    ],
    "wof:name":"Infasco Division",
    "wof:placetype":"venue"
},
  "geometry": {"coordinates":[-73.167305,45.429985],"type":"Point"}
}