{
  "type": "Feature",
  "properties": {
    "addr:full":"90 Canora St Winnipeg MB R3G 1S9",
    "addr:housenumber":"90",
    "addr:postcode":"r3g 1s9",
    "addr:street":"Canora St",
    "iso:country":"CA",
    "sg:address":"90 Canora St",
    "sg:city":"Winnipeg",
    "sg:classifiers":[
        {
            "category":"Real Estate",
            "subcategory":"Architect",
            "type":"Services"
        }
    ],
    "sg:phone":"+1 204 783 4310",
    "sg:postcode":"R3G 1S9",
    "sg:province":"MB",
    "sg:tags":[
        "building",
        "construction"
    ],
    "wof:name":"Bartel Brothers Ltd",
    "wof:placetype":"venue"
},
  "geometry": {"coordinates":[-97.166405,49.881004],"type":"Point"}
}