{
  "type": "Feature",
  "properties": {
    "addr:full":"114 Markham Rd Scarborough ON M1M 2Z7",
    "addr:housenumber":"114",
    "addr:postcode":"m1m 2z7",
    "addr:street":"Markham Rd",
    "iso:country":"CA",
    "sg:address":"114 Markham Rd",
    "sg:city":"Scarborough",
    "sg:classifiers":[
        {
            "category":"Personal",
            "subcategory":"Beauty Salon",
            "type":"Services"
        }
    ],
    "sg:phone":"+1 416 261 3001",
    "sg:postcode":"M1M 2Z7",
    "sg:province":"ON",
    "wof:name":"Ed of Hair",
    "wof:placetype":"venue"
},
  "geometry": {"coordinates":[-79.217567,43.739464],"type":"Point"}
}