{
  "type": "Feature",
  "properties": {
    "addr:full":"170 Muskoka Rd S Gravenhurst ON P1P 1X3",
    "addr:housenumber":"170",
    "addr:postcode":"p1p 1x3",
    "addr:street":"Muskoka Rd S",
    "iso:country":"CA",
    "sg:address":"170 Muskoka Rd S",
    "sg:city":"Gravenhurst",
    "sg:classifiers":[
        {
            "category":"Professional",
            "subcategory":"Accounting & Tax Preparation",
            "type":"Services"
        }
    ],
    "sg:phone":"+1 705 687 7715",
    "sg:postcode":"P1P 1X3",
    "sg:province":"ON",
    "sg:tags":[
        "consultant",
        "return",
        "filing"
    ],
    "wof:name":"H & R Block Canada Inc",
    "wof:placetype":"venue"
},
  "geometry": {"coordinates":[-79.3735961914,44.9192733765],"type":"Point"}
}