{
  "type": "Feature",
  "properties": {
    "iso:country":"CA",
    "sg:address":"5618 54 St NW",
    "sg:city":"Edmonton",
    "sg:classifiers":[
        {
            "category":"Retail",
            "subcategory":"Auto Rental",
            "type":"Services"
        }
    ],
    "sg:phone":"+1 780 496 9410",
    "sg:postcode":"T6B 3G1",
    "sg:province":"AB",
    "sg:tags":[
        "renting",
        "truck",
        "leasing"
    ],
    "wof:name":"U-Haul CO Ltd",
    "wof:placetype":"venue"
},
  "geometry": {"coordinates":[-113.421211243,53.4936981201],"type":"Point"}
}