{
  "type": "Feature",
  "properties": {
    "iso:country":"CA",
    "sg:city":"Coquitlam",
    "sg:classifiers":[
        {
            "category":"Professional",
            "subcategory":"Accounting & Tax Preparation",
            "type":"Services"
        }
    ],
    "sg:phone":"+1 604 931 3585",
    "sg:postcode":"V3K 3P5",
    "sg:province":"BC",
    "sg:tags":[
        "accountant"
    ],
    "wof:name":"Carlyle Shepherd & CO",
    "wof:placetype":"venue"
},
  "geometry": {"coordinates":[-122.860923767,49.248840332],"type":"Point"}
}