{
  "type": "Feature",
  "properties": {
    "addr:full":"Yellowknife NT X1A 1L8",
    "addr:postcode":"x1a 1l8",
    "iso:country":"CA",
    "sg:city":"Yellowknife",
    "sg:classifiers":[
        {
            "category":"Organizations",
            "subcategory":"Professional Association",
            "type":"Services"
        }
    ],
    "sg:phone":"+1 867 920 4555",
    "sg:postcode":"X1A 1L8",
    "sg:province":"NT",
    "sg:tags":[
        "engineer"
    ],
    "wof:name":"Dillon Consulting Ltd",
    "wof:placetype":"venue"
},
  "geometry": {"coordinates":[-114.37035400000001,62.456509],"type":"Point"}
}