{
  "type": "Feature",
  "properties": {
    "iso:country":"CA",
    "sg:address":"16120 89 St NW",
    "sg:city":"Edmonton",
    "sg:classifiers":[
        {
            "category":"Building & Trades",
            "subcategory":"Construction",
            "type":"Services"
        }
    ],
    "sg:phone":"+1 780 414 6884",
    "sg:postcode":"T5Z 3M3",
    "sg:province":"AB",
    "sg:tags":[
        "contractor"
    ],
    "wof:name":"Budget Construction",
    "wof:placetype":"venue"
},
  "geometry": {"coordinates":[-113.47926330599999,53.6222000122],"type":"Point"}
}