{
  "type": "Feature",
  "properties": {
    "addr:full":"1623 Bay St Victoria BC V8R 2B7",
    "addr:housenumber":"1623",
    "addr:postcode":"v8r 2b7",
    "addr:street":"Bay St",
    "iso:country":"CA",
    "sg:address":"1623 Bay St",
    "sg:city":"Victoria",
    "sg:classifiers":[
        {
            "category":"Shopping",
            "subcategory":"Bicycles & Sporting Goods",
            "type":"Retail Goods"
        }
    ],
    "sg:phone":"+1 250 370 2282",
    "sg:postcode":"V8R 2B7",
    "sg:province":"BC",
    "wof:name":"Bicycleitis H K's",
    "wof:placetype":"venue"
},
  "geometry": {"coordinates":[-123.334892,48.433895],"type":"Point"}
}