{
  "type": "Feature",
  "properties": {
    "addr:full":"92 Elm St Brantford ON N3R 4V2",
    "addr:housenumber":"92",
    "addr:postcode":"n3r 4v2",
    "addr:street":"Elm St",
    "iso:country":"CA",
    "sg:address":"92 Elm St",
    "sg:city":"Brantford",
    "sg:classifiers":[
        {
            "category":"Personal",
            "type":"Services"
        }
    ],
    "sg:phone":"+1 519 756 8171",
    "sg:postcode":"N3R 4V2",
    "sg:province":"ON",
    "sg:tags":[
        "therapist",
        "massage"
    ],
    "wof:name":"DE Rubeis, Robert",
    "wof:placetype":"venue"
},
  "geometry": {"coordinates":[-80.27381099999999,43.160637],"type":"Point"}
}