{
  "type": "Feature",
  "properties": {
    "iso:country":"CA",
    "sg:address":"30 Prospect Rd",
    "sg:city":"Morrisburg",
    "sg:classifiers":[
        {
            "category":"Retail",
            "subcategory":"Repair Shop",
            "type":"Services"
        }
    ],
    "sg:phone":"+1 613 543 3730",
    "sg:postcode":"K0C 1X0",
    "sg:province":"ON",
    "sg:tags":[
        "welding"
    ],
    "wof:name":"Eastern Ontario Millwright Inc",
    "wof:placetype":"venue"
},
  "geometry": {"coordinates":[-75.1771621704,44.9066810608],"type":"Point"}
}