{
  "type": "Feature",
  "properties": {
    "addr:full":"1240 Depot Rd Brackendale BC V0N 1H0",
    "addr:housenumber":"1240",
    "addr:postcode":"v0n 1h0",
    "addr:street":"Depot Rd",
    "iso:country":"CA",
    "sg:address":"1240 Depot Rd",
    "sg:city":"Brackendale",
    "sg:classifiers":[
        {
            "category":"Building & Trades",
            "subcategory":"Construction",
            "type":"Services"
        }
    ],
    "sg:phone":"+1 604 898 2648",
    "sg:postcode":"V0N 1H0",
    "sg:province":"BC",
    "sg:tags":[
        "painter"
    ],
    "wof:name":"Cutting Edge Painting CO",
    "wof:placetype":"venue"
},
  "geometry": {"coordinates":[-123.152275,49.765907],"type":"Point"}
}