{
  "type": "Feature",
  "properties": {
    "addr:full":"4453 10th Ave W Vancouver BC V6R 2H8",
    "addr:housenumber":"4453",
    "addr:postcode":"v6r 2h8",
    "addr:street":"10Th Ave W",
    "iso:country":"CA",
    "sg:address":"4453 10th Ave W",
    "sg:city":"Vancouver",
    "sg:classifiers":[
        {
            "category":"Shopping",
            "subcategory":"News",
            "type":"Retail Goods"
        }
    ],
    "sg:phone":"+1 604 222 8333",
    "sg:postcode":"V6R 2H8",
    "sg:province":"BC",
    "sg:tags":[
        "dealer"
    ],
    "wof:name":"International News",
    "wof:placetype":"venue"
},
  "geometry": {"coordinates":[-123.207657,49.263947],"type":"Point"}
}