{
  "type": "Feature",
  "properties": {
    "iso:country":"CA",
    "sg:address":"380 Admiral Dr #201",
    "sg:city":"London",
    "sg:classifiers":[
        {
            "category":"Organizations",
            "subcategory":"Religious Organization",
            "type":"Services"
        }
    ],
    "sg:phone":"+1 519 652 2771",
    "sg:postcode":"N5V 3C2",
    "sg:province":"ON",
    "sg:tags":[
        "church"
    ],
    "wof:name":"St Sava's Church",
    "wof:placetype":"venue"
},
  "geometry": {"coordinates":[-81.1601715088,43.0014953613],"type":"Point"}
}