{
  "type": "Feature",
  "properties": {
    "addr:full":"18212 89 Ave NW Edmonton AB T5T 2K6",
    "addr:housenumber":"18212",
    "addr:postcode":"t5t 2k6",
    "addr:street":"89 Ave Nw",
    "iso:country":"CA",
    "sg:address":"18212 89 Ave NW",
    "sg:city":"Edmonton",
    "sg:classifiers":[
        {
            "category":"Restaurant",
            "type":"Food & Drink"
        }
    ],
    "sg:phone":"+1 780 487 6322",
    "sg:postcode":"T5T 2K6",
    "sg:province":"AB",
    "wof:name":"Leng's Chinese Food",
    "wof:placetype":"venue"
},
  "geometry": {"coordinates":[-113.638442993,53.5238380432],"type":"Point"}
}