{
  "type": "Feature",
  "properties": {
    "addr:full":"115 Pleasant Rd Guelph ON N1E 3Z7",
    "addr:housenumber":"115",
    "addr:postcode":"n1e 3z7",
    "addr:street":"Pleasant Rd",
    "iso:country":"CA",
    "sg:address":"115 Pleasant Rd",
    "sg:city":"Guelph",
    "sg:classifiers":[
        {
            "category":"Building & Trades",
            "subcategory":"Construction",
            "type":"Services"
        }
    ],
    "sg:phone":"+1 519 824 0257",
    "sg:postcode":"N1E 3Z7",
    "sg:province":"ON",
    "sg:tags":[
        "general",
        "contractor"
    ],
    "wof:name":"G Gatto Construction Ltd",
    "wof:placetype":"venue"
},
  "geometry": {"coordinates":[-80.25205200000001,43.560379],"type":"Point"}
}