{
  "type": "Feature",
  "properties": {
    "addr:full":"185 Rue Bernard Saint-Charles-Borromee QC J6E 2C4",
    "addr:housenumber":"185",
    "addr:postcode":"j6e 2c4",
    "addr:street":"Rue Bernard Saint-Charles-Borromee",
    "iso:country":"CA",
    "sg:address":"185 Rue Bernard",
    "sg:city":"Saint-Charles-Borromee",
    "sg:classifiers":[
        {
            "category":"Health Services",
            "subcategory":"Health Practitioner",
            "type":"Services"
        }
    ],
    "sg:phone":"+1 450 759 3420",
    "sg:postcode":"J6E 2C4",
    "sg:province":"QC",
    "sg:tags":[
        "physiotherapist"
    ],
    "wof:name":"Clinique DE Physiotherapie",
    "wof:placetype":"venue"
},
  "geometry": {"coordinates":[-73.45175170900001,46.0366287231],"type":"Point"}
}