{
  "type": "Feature",
  "properties": {
    "addr:full":"119 Emo Rd Emo ON P0W 1E0",
    "addr:housenumber":"119",
    "addr:postcode":"p0w 1e0",
    "addr:street":"Emo Rd",
    "iso:country":"CA",
    "sg:address":"119 Emo Rd",
    "sg:city":"Emo",
    "sg:classifiers":[
        {
            "category":"Building & Trades",
            "subcategory":"Construction",
            "type":"Services"
        }
    ],
    "sg:phone":"+1 807 482 2607",
    "sg:postcode":"P0W 1E0",
    "sg:province":"ON",
    "sg:tags":[
        "contractor"
    ],
    "wof:name":"Veldhuisen Construction Inc",
    "wof:placetype":"venue"
},
  "geometry": {"coordinates":[-93.8289260864,48.6405792236],"type":"Point"}
}