{
  "type": "Feature",
  "properties": {
    "addr:full":"1965 Main St Vancouver BC V5T 3C1",
    "addr:housenumber":"1965",
    "addr:postcode":"v5t 3c1",
    "addr:street":"Main St",
    "iso:country":"CA",
    "sg:address":"1965 Main St",
    "sg:city":"Vancouver",
    "sg:classifiers":[
        {
            "category":"Freight",
            "type":"Transportation"
        }
    ],
    "sg:phone":"+1 604 876 3453",
    "sg:postcode":"V5T 3C1",
    "sg:province":"BC",
    "sg:tags":[
        "commercial",
        "storage"
    ],
    "wof:name":"Alderbridge Mini Storage",
    "wof:placetype":"venue"
},
  "geometry": {"coordinates":[-123.100998,49.267681],"type":"Point"}
}