{
  "type": "Feature",
  "properties": {
    "addr:full":"22095 Gibson Rd Mount Brydges ON N0L 1W0",
    "addr:housenumber":"22095",
    "addr:postcode":"n0l 1w0",
    "addr:street":"Gibson Rd",
    "iso:country":"CA",
    "sg:address":"22095 Gibson Rd",
    "sg:city":"Mount Brydges",
    "sg:classifiers":[
        {
            "category":"Building & Trades",
            "subcategory":"Construction",
            "type":"Services"
        }
    ],
    "sg:phone":"+1 519 264 2782",
    "sg:postcode":"N0L 1W0",
    "sg:province":"ON",
    "sg:tags":[
        "excavating",
        "contractor"
    ],
    "wof:name":"Steve Kozachuk Ltd",
    "wof:placetype":"venue"
},
  "geometry": {"coordinates":[-81.4505310059,42.8977890015],"type":"Point"}
}