{
  "type": "Feature",
  "properties": {
    "iso:country":"CA",
    "sg:city":"Edmonton",
    "sg:classifiers":[
        {
            "category":"Professional",
            "subcategory":"Accounting & Tax Preparation",
            "type":"Services"
        }
    ],
    "sg:phone":"+1 780 484 5182",
    "sg:postcode":"T5S 1M7",
    "sg:province":"AB",
    "sg:tags":[
        "accountant"
    ],
    "wof:name":"Krawchuk, Dale M CA",
    "wof:placetype":"venue"
},
  "geometry": {"coordinates":[-113.618591309,53.551776886],"type":"Point"}
}