{
  "type": "Feature",
  "properties": {
    "addr:full":"1363 Main St Murray Harbour PE C0A 1V0",
    "addr:housenumber":"1363",
    "addr:postcode":"c0a 1v0",
    "addr:street":"Main St",
    "iso:country":"CA",
    "sg:address":"1363 Main St",
    "sg:city":"Murray Harbour",
    "sg:classifiers":[
        {
            "category":"Food & Beverages",
            "subcategory":"Groceries & Convenience Stores",
            "type":"Retail Goods"
        }
    ],
    "sg:phone":"+1 902 962 2526",
    "sg:postcode":"C0A 1V0",
    "sg:province":"PE",
    "sg:tags":[
        "grocer"
    ],
    "wof:name":"L & O Butler Ltd",
    "wof:placetype":"venue"
},
  "geometry": {"coordinates":[-62.520683,46.003223],"type":"Point"}
}