{
  "type": "Feature",
  "properties": {
    "addr:full":"43 Ave Dr Bigue Normetal QC J0Z 3A0",
    "addr:postcode":"j0z 3a0",
    "addr:street":"43 Ave Dr;Normetal",
    "iso:country":"CA",
    "sg:address":"43 Ave Dr Bigue",
    "sg:city":"Normetal",
    "sg:classifiers":[
        {
            "category":"Food & Beverages",
            "subcategory":"Groceries & Convenience Stores",
            "type":"Retail Goods"
        }
    ],
    "sg:phone":"+1 819 788 2633",
    "sg:postcode":"J0Z 3A0",
    "sg:province":"QC",
    "wof:name":"Depanneur Chez Stephane",
    "wof:placetype":"venue"
},
  "geometry": {"coordinates":[-79.364594,48.996872],"type":"Point"}
}