{
  "type": "Feature",
  "properties": {
    "addr:full":"46 Elm Grove Ave Richmond Hill ON L4E 2V3",
    "addr:housenumber":"46",
    "addr:postcode":"l4e 2v3",
    "addr:street":"Elm Grove Ave",
    "iso:country":"CA",
    "sg:address":"46 Elm Grove Ave",
    "sg:city":"Richmond Hill",
    "sg:classifiers":[
        {
            "category":"Building & Trades",
            "subcategory":"Construction",
            "type":"Services"
        }
    ],
    "sg:phone":"+1 905 773 6094",
    "sg:postcode":"L4E 2V3",
    "sg:province":"ON",
    "wof:name":"Pioneer 1",
    "wof:placetype":"venue"
},
  "geometry": {"coordinates":[-79.46090700000001,43.949429],"type":"Point"}
}