{
  "type": "Feature",
  "properties": {
    "iso:country":"CA",
    "sg:address":"3900 Viking Way",
    "sg:city":"Richmond",
    "sg:classifiers":[
        {
            "category":"Freight",
            "type":"Transportation"
        }
    ],
    "sg:phone":"+1 604 273 0783",
    "sg:postcode":"V6V 1N6",
    "sg:province":"BC",
    "sg:tags":[
        "trucking"
    ],
    "wof:name":"Shoreline Tank Svc",
    "wof:placetype":"venue"
},
  "geometry": {"coordinates":[-123.073150635,49.1855583191],"type":"Point"}
}