{
  "type": "Feature",
  "properties": {
    "addr:full":"1438 Aldersbrook Rd London ON N6G 3V7",
    "addr:housenumber":"1438",
    "addr:postcode":"n6g 3v7",
    "addr:street":"Aldersbrook Rd",
    "iso:country":"CA",
    "sg:address":"1438 Aldersbrook Rd",
    "sg:city":"London",
    "sg:classifiers":[
        {
            "category":"Personal",
            "subcategory":"Beauty Salon",
            "type":"Services"
        }
    ],
    "sg:phone":"+1 519 474 3305",
    "sg:postcode":"N6G 3V7",
    "sg:province":"ON",
    "wof:name":"Vickie & CO",
    "wof:placetype":"venue"
},
  "geometry": {"coordinates":[-81.314697,43.001495],"type":"Point"}
}