{
  "type": "Feature",
  "properties": {
    "addr:full":"6664 Deer Lake Ave Burnaby BC V5E 4H3",
    "addr:housenumber":"6664",
    "addr:postcode":"v5e 4h3",
    "addr:street":"Deer Lake Ave",
    "iso:country":"CA",
    "sg:address":"6664 Deer Lake Ave",
    "sg:city":"Burnaby",
    "sg:classifiers":[
        {
            "category":"Restaurant",
            "type":"Food & Drink"
        }
    ],
    "sg:phone":"+1 604 298 4278",
    "sg:postcode":"V5E 4H3",
    "sg:province":"BC",
    "sg:tags":[
        "caterer"
    ],
    "wof:name":"Hart House",
    "wof:placetype":"venue"
},
  "geometry": {"coordinates":[-122.965713501,49.238609314],"type":"Point"}
}