{
  "type": "Feature",
  "properties": {
    "addr:full":"555 Arcola St Esterhazy SK S0A 0X0",
    "addr:housenumber":"555",
    "addr:postcode":"s0a 0x0",
    "addr:street":"Arcola St",
    "iso:country":"CA",
    "sg:address":"555 Arcola St",
    "sg:city":"Esterhazy",
    "sg:classifiers":[
        {
            "category":"Education",
            "subcategory":"School",
            "type":"Public Place"
        }
    ],
    "sg:phone":"+1 306 745 6618",
    "sg:postcode":"S0A 0X0",
    "sg:province":"SK",
    "wof:name":"Esterhazy High School",
    "wof:placetype":"venue"
},
  "geometry": {"coordinates":[-102.070297,50.655773],"type":"Point"}
}