{
  "type": "Feature",
  "properties": {
    "addr:full":"103 Crowfoot Terr NW Calgary AB T3G 4J8",
    "addr:housenumber":"103",
    "addr:postcode":"t3g 4j8",
    "addr:street":"Crowfoot Terr Nw",
    "iso:country":"CA",
    "sg:address":"103 Crowfoot Terr NW",
    "sg:city":"Calgary",
    "sg:classifiers":[
        {
            "category":"Restaurant",
            "type":"Food & Drink"
        }
    ],
    "sg:phone":"+1 403 241 2400",
    "sg:postcode":"T3G 4J8",
    "sg:province":"AB",
    "wof:name":"Schanks Athletic Club",
    "wof:placetype":"venue"
},
  "geometry": {"coordinates":[-114.20192,51.12711],"type":"Point"}
}