{
  "type": "Feature",
  "properties": {
    "addr:full":"Petrolia ON N0N 1R0",
    "addr:postcode":"n0n 1r0",
    "iso:country":"CA",
    "sg:city":"Petrolia",
    "sg:classifiers":[
        {
            "category":"Building & Trades",
            "subcategory":"Construction",
            "type":"Services"
        }
    ],
    "sg:phone":"+1 519 882 2543",
    "sg:postcode":"N0N 1R0",
    "sg:province":"ON",
    "sg:tags":[
        "drainage",
        "contractor"
    ],
    "wof:name":"Jardine Farm Drainage",
    "wof:placetype":"venue"
},
  "geometry": {"coordinates":[-82.1464,42.881405],"type":"Point"}
}