{
  "type": "Feature",
  "properties": {
    "addr:full":"7 Martin Dr N Sauble Beach ON N0H 2G0",
    "addr:housenumber":"7",
    "addr:postcode":"n0h 2g0",
    "addr:street":"Martin Dr N",
    "iso:country":"CA",
    "sg:address":"7 Martin Dr N",
    "sg:city":"Sauble Beach",
    "sg:classifiers":[
        {
            "category":"Building & Trades",
            "subcategory":"Plumbing",
            "type":"Services"
        }
    ],
    "sg:phone":"+1 519 422 1339",
    "sg:postcode":"N0H 2G0",
    "sg:province":"ON",
    "sg:tags":[
        "contractor"
    ],
    "wof:name":"Steve Rosenberg Custom Plbg",
    "wof:placetype":"venue"
},
  "geometry": {"coordinates":[-81.25251799999999,44.645016],"type":"Point"}
}