{
  "type": "Feature",
  "properties": {
    "addr:full":"821 Rue Du Parc Saint-Frederic QC G0N 1P0",
    "addr:housenumber":"821",
    "addr:postcode":"g0n 1p0",
    "addr:street":"Rue Du Parc Saint-Frederic",
    "iso:country":"CA",
    "sg:address":"821 Rue Du Parc",
    "sg:city":"Saint-Frederic",
    "sg:classifiers":[
        {
            "category":"Wholesale",
            "subcategory":"Motor Vehicles",
            "type":"Manufacturing & Wholesale Goods"
        }
    ],
    "sg:phone":"+1 418 426 3666",
    "sg:postcode":"G0N 1P0",
    "sg:province":"QC",
    "sg:tags":[
        "recreational",
        "camper"
    ],
    "wof:name":"Par Nado Inc",
    "wof:placetype":"venue"
},
  "geometry": {"coordinates":[-70.96985599999999,46.297619],"type":"Point"}
}