{
  "type": "Feature",
  "properties": {
    "iso:country":"CA",
    "sg:address":"9805 Rue Clark",
    "sg:city":"Montreal",
    "sg:classifiers":[
        {
            "category":"Manufacturing",
            "subcategory":"Pottery",
            "type":"Manufacturing & Wholesale Goods"
        }
    ],
    "sg:phone":"+1 514 381 4141",
    "sg:postcode":"H3L 2R5",
    "sg:province":"QC",
    "sg:tags":[
        "bathroom",
        "importer"
    ],
    "wof:name":"Aquabrass Inc",
    "wof:placetype":"venue"
},
  "geometry": {"coordinates":[-73.659042,45.545845],"type":"Point"}
}