{
  "type": "Feature",
  "properties": {
    "iso:country":"CA",
    "sg:address":"461 Rue Gosselin",
    "sg:city":"Wotton",
    "sg:classifiers":[
        {
            "category":"Wholesale",
            "subcategory":"Machinery & Supplies",
            "type":"Manufacturing & Wholesale Goods"
        }
    ],
    "sg:phone":"+1 819 828 2662",
    "sg:postcode":"J0A 1N0",
    "sg:province":"QC",
    "sg:tags":[
        "farm",
        "equipment"
    ],
    "wof:name":"Garage E Comtois Inc",
    "wof:placetype":"venue"
},
  "geometry": {"coordinates":[-71.8076171875,45.7374801636],"type":"Point"}
}