{
  "type": "Feature",
  "properties": {
    "addr:full":"13319 149 Ave NW Edmonton AB T6V 1L1",
    "addr:housenumber":"13319",
    "addr:postcode":"t6v 1l1",
    "addr:street":"149 Ave Nw",
    "iso:country":"CA",
    "sg:address":"13319 149 Ave NW",
    "sg:city":"Edmonton",
    "sg:classifiers":[
        {
            "category":"Home & Garden",
            "subcategory":"Building Materials",
            "type":"Retail Goods"
        }
    ],
    "sg:phone":"+1 780 478 0694",
    "sg:postcode":"T6V 1L1",
    "sg:province":"AB",
    "sg:tags":[
        "glass",
        "window",
        "plate"
    ],
    "wof:name":"Quick-Fix Windshield Repair",
    "wof:placetype":"venue"
},
  "geometry": {"coordinates":[-113.54987300000001,53.611378],"type":"Point"}
}