{
  "type": "Feature",
  "properties": {
    "iso:country":"CA",
    "sg:address":"1520 Rang Saint-Mathieu E",
    "sg:city":"Shawinigan-Sud",
    "sg:classifiers":[
        {
            "category":"Retail",
            "subcategory":"Auto Repair",
            "type":"Services"
        }
    ],
    "sg:phone":"+1 819 536 5425",
    "sg:postcode":"G9N 6T5",
    "sg:province":"QC",
    "sg:tags":[
        "body",
        "automobile",
        "painting"
    ],
    "wof:name":"Atelier Brouillette & Gagnon",
    "wof:placetype":"venue"
},
  "geometry": {"coordinates":[-72.7259674072,46.5304489136],"type":"Point"}
}