{
  "type": "Feature",
  "properties": {
    "addr:full":"300 Thomas St St Marys ON N4X 1B1",
    "addr:housenumber":"300",
    "addr:postcode":"n4x 1b1",
    "addr:street":"Thomas St",
    "iso:country":"CA",
    "sg:address":"300 Thomas St",
    "sg:city":"St Marys",
    "sg:classifiers":[
        {
            "category":"Restaurant",
            "type":"Food & Drink"
        }
    ],
    "sg:phone":"+1 519 284 2977",
    "sg:postcode":"N4X 1B1",
    "sg:province":"ON",
    "sg:tags":[
        "motel",
        "hotel"
    ],
    "wof:name":"Westover Inn",
    "wof:placetype":"venue"
},
  "geometry": {"coordinates":[-81.156425,43.246052],"type":"Point"}
}