{
  "type": "Feature",
  "properties": {
    "iso:country":"CA",
    "sg:address":"14 Av Saint-Jean-Baptiste",
    "sg:city":"Vaudreuil-Dorion",
    "sg:classifiers":[
        {
            "category":"Health Services",
            "subcategory":"Doctor",
            "type":"Services"
        }
    ],
    "sg:phone":"+1 450 455 5793",
    "sg:postcode":"J7V 2N9",
    "sg:province":"QC",
    "sg:tags":[
        "clinic",
        "veterinarian"
    ],
    "wof:name":"Bureau Veterinaire DE Dorion",
    "wof:placetype":"venue"
},
  "geometry": {"coordinates":[-74.010536,45.383179],"type":"Point"}
}