{
  "type": "Feature",
  "properties": {
    "addr:full":"9309 Macleod Trail SW Calgary AB T2J 0P6",
    "addr:housenumber":"9309",
    "addr:postcode":"t2j 0p6",
    "addr:street":"Macleod Trail Sw",
    "iso:country":"CA",
    "sg:address":"9309 Macleod Trail SW",
    "sg:city":"Calgary",
    "sg:classifiers":[
        {
            "category":"Manufacturing",
            "subcategory":"Tools & Machinery",
            "type":"Manufacturing & Wholesale Goods"
        }
    ],
    "sg:phone":"+1 403 252 2266",
    "sg:postcode":"T2J 0P6",
    "sg:province":"AB",
    "sg:tags":[
        "physician",
        "surgeon"
    ],
    "wof:name":"Home Care Medical Supply Ctr",
    "wof:placetype":"venue"
},
  "geometry": {"coordinates":[-114.071937561,50.9717597961],"type":"Point"}
}