{
  "type": "Feature",
  "properties": {
    "addr:full":"1922 Labonte St Clarence Creek ON K0A 1N0",
    "addr:housenumber":"1922",
    "addr:postcode":"k0a 1n0",
    "addr:street":"Labonte St",
    "iso:country":"CA",
    "sg:address":"1922 Labonte St",
    "sg:city":"Clarence Creek",
    "sg:classifiers":[
        {
            "category":"Shopping",
            "subcategory":"Pharmacy",
            "type":"Retail Goods"
        }
    ],
    "sg:phone":"+1 613 488 2366",
    "sg:postcode":"K0A 1N0",
    "sg:province":"ON",
    "wof:name":"Pharmacie Clarence Creek",
    "wof:placetype":"venue"
},
  "geometry": {"coordinates":[-75.2146224976,45.5076828003],"type":"Point"}
}