{
  "type": "Feature",
  "properties": {
    "addr:full":"314 1st Ave NW Sturgis SK S0A 4A0",
    "addr:housenumber":"314",
    "addr:postcode":"s0a 4a0",
    "addr:street":"1St Ave Nw",
    "iso:country":"CA",
    "sg:address":"314 1st Ave NW",
    "sg:city":"Sturgis",
    "sg:classifiers":[
        {
            "category":"Travel",
            "subcategory":"Hotels & Motels",
            "type":"Entertainment"
        }
    ],
    "sg:phone":"+1 306 548 2965",
    "sg:postcode":"S0A 4A0",
    "sg:province":"SK",
    "wof:name":"Sturgis Motel",
    "wof:placetype":"venue"
},
  "geometry": {"coordinates":[-102.540847778,51.9384918213],"type":"Point"}
}