{
  "type": "Feature",
  "properties": {
    "addr:full":"162 Wyse Rd Dartmouth NS B3A 1M6",
    "addr:housenumber":"162",
    "addr:postcode":"b3a 1m6",
    "addr:street":"Wyse Rd",
    "iso:country":"CA",
    "sg:address":"162 Wyse Rd",
    "sg:city":"Dartmouth",
    "sg:classifiers":[
        {
            "category":"Shopping",
            "subcategory":"Clothing, Apparel, & Fashions",
            "type":"Retail Goods"
        }
    ],
    "sg:phone":"+1 902 461 0488",
    "sg:postcode":"B3A 1M6",
    "sg:province":"NS",
    "wof:name":"Jay Set",
    "wof:placetype":"venue"
},
  "geometry": {"coordinates":[-63.5791893005,44.6711502075],"type":"Point"}
}