{
  "type": "Feature",
  "properties": {
    "addr:full":"L'Amable ON K0L 2L0",
    "addr:postcode":"k0l 2l0",
    "iso:country":"CA",
    "sg:city":"L'Amable",
    "sg:classifiers":[
        {
            "category":"Retail",
            "subcategory":"Auto Repair",
            "type":"Services"
        }
    ],
    "sg:phone":"+1 613 332 2661",
    "sg:postcode":"K0L 2L0",
    "sg:province":"ON",
    "sg:tags":[
        "repairing",
        "automobile",
        "equipment",
        "hydraulic",
        "supply"
    ],
    "wof:name":"Ron's General Repairs",
    "wof:placetype":"venue"
},
  "geometry": {"coordinates":[-77.78713999999999,45.011921],"type":"Point"}
}