{
  "type": "Feature",
  "properties": {
    "addr:full":"2000 15th Ave Prince George BC V2M 1S2",
    "addr:housenumber":"2000",
    "addr:postcode":"v2m 1s2",
    "addr:street":"15Th Ave",
    "iso:country":"CA",
    "sg:address":"2000 15th Ave",
    "sg:city":"Prince George",
    "sg:classifiers":[
        {
            "category":"Government",
            "subcategory":"Office",
            "type":"Public Place"
        }
    ],
    "sg:phone":"+1 250 565 2649",
    "sg:postcode":"V2M 1S2",
    "sg:province":"BC",
    "wof:name":"Health Board Adm Office",
    "wof:placetype":"venue"
},
  "geometry": {"coordinates":[-122.764663696,53.9104919434],"type":"Point"}
}