{
  "type": "Feature",
  "properties": {
    "addr:full":"288 Erie St S Leamington ON N8H 3C5",
    "addr:housenumber":"288",
    "addr:postcode":"n8h 3c5",
    "addr:street":"Erie St S",
    "iso:country":"CA",
    "sg:address":"288 Erie St S",
    "sg:city":"Leamington",
    "sg:classifiers":[
        {
            "category":"Personal",
            "subcategory":"Beauty Salon",
            "type":"Services"
        }
    ],
    "sg:phone":"+1 519 322 5173",
    "sg:postcode":"N8H 3C5",
    "sg:province":"ON",
    "wof:name":"First Choice Haircutters",
    "wof:placetype":"venue"
},
  "geometry": {"coordinates":[-82.600723,42.036816],"type":"Point"}
}