{
  "type": "Feature",
  "properties": {
    "addr:full":"3610 8 Ave N Lethbridge AB T1H 5E2",
    "addr:housenumber":"3610",
    "addr:postcode":"t1h 5e2",
    "addr:street":"8 Ave N",
    "iso:country":"CA",
    "sg:address":"3610 8 Ave N",
    "sg:city":"Lethbridge",
    "sg:classifiers":[
        {
            "category":"Manufacturing",
            "subcategory":"Tools & Machinery",
            "type":"Manufacturing & Wholesale Goods"
        }
    ],
    "sg:phone":"+1 403 329 6234",
    "sg:postcode":"T1H 5E2",
    "sg:province":"AB",
    "sg:tags":[
        "equipment",
        "dairy",
        "supply"
    ],
    "wof:name":"Lethbridge Dairy Mart Ltd",
    "wof:placetype":"venue"
},
  "geometry": {"coordinates":[-112.788696289,49.7109603882],"type":"Point"}
}