{
  "type": "Feature",
  "properties": {
    "addr:full":"3790 Av Barclay Montreal QC H3S 1K7",
    "addr:housenumber":"3790",
    "addr:postcode":"h3s 1k7",
    "addr:street":"Av Barclay",
    "iso:country":"CA",
    "sg:address":"3790 Av Barclay",
    "sg:city":"Montreal",
    "sg:classifiers":[
        {
            "category":"Real Estate",
            "subcategory":"Real Estate Agent",
            "type":"Services"
        }
    ],
    "sg:phone":"+1 514 739 9211",
    "sg:postcode":"H3S 1K7",
    "sg:province":"QC",
    "wof:name":"Immeubles Perina",
    "wof:placetype":"venue"
},
  "geometry": {"coordinates":[-73.636383,45.501457],"type":"Point"}
}