{
  "type": "Feature",
  "properties": {
    "addr:full":"50 Empire Lane Windsor NS B0N 2T0",
    "addr:housenumber":"50",
    "addr:postcode":"b0n 2t0",
    "addr:street":"Empire Lane",
    "iso:country":"CA",
    "sg:address":"50 Empire Lane",
    "sg:city":"Windsor",
    "sg:classifiers":[
        {
            "category":"Personal",
            "subcategory":"Beauty Salon",
            "type":"Services"
        }
    ],
    "sg:phone":"+1 902 798 5994",
    "sg:postcode":"B0N 2T0",
    "sg:province":"NS",
    "wof:name":"Best Choice Hair Fashions",
    "wof:placetype":"venue"
},
  "geometry": {"coordinates":[-64.13067599999999,44.989857],"type":"Point"}
}