{
  "type": "Feature",
  "properties": {
    "addr:full":"2376 Boul Du Cure-Labelle Saint-Jerome QC J7Y 5E9",
    "addr:housenumber":"2376",
    "addr:postcode":"j7y 5e9",
    "addr:street":"Boul Du Cure-Labelle Saint-Jerome",
    "iso:country":"CA",
    "sg:address":"2376 Boul Du Cure-Labelle",
    "sg:city":"Saint-Jerome",
    "sg:classifiers":[
        {
            "category":"Autos & Motor Vehicles",
            "subcategory":"Automobile Sales",
            "type":"Retail Goods"
        }
    ],
    "sg:phone":"+1 450 432 1688",
    "sg:postcode":"J7Y 5E9",
    "sg:province":"QC",
    "sg:tags":[
        "car",
        "dealer"
    ],
    "wof:name":"Autos Mc",
    "wof:placetype":"venue"
},
  "geometry": {"coordinates":[-74.0384674072,45.8164138794],"type":"Point"}
}