{
  "type": "Feature",
  "properties": {
    "addr:full":"6 Jubilee Rd Placentia NL A0B 2Y0",
    "addr:housenumber":"6",
    "addr:postcode":"a0b 2y0",
    "addr:street":"Jubilee Rd",
    "iso:country":"CA",
    "sg:address":"6 Jubilee Rd",
    "sg:city":"Placentia",
    "sg:classifiers":[
        {
            "category":"Personal",
            "subcategory":"Beauty Salon",
            "type":"Services"
        }
    ],
    "sg:phone":"+1 709 227 3339",
    "sg:postcode":"A0B 2Y0",
    "sg:province":"NL",
    "wof:name":"Modern Unisex Salon",
    "wof:placetype":"venue"
},
  "geometry": {"coordinates":[-53.962219,47.254074],"type":"Point"}
}