{
  "type": "Feature",
  "properties": {
    "addr:full":"590 Av Du Pont S Alma QC G8B 2V2",
    "addr:postcode":"g8b 2v2",
    "addr:street":"590 Av Du Pont S",
    "iso:country":"CA",
    "sg:address":"590 Av Du Pont S",
    "sg:city":"Alma",
    "sg:classifiers":[
        {
            "category":"Autos & Motor Vehicles",
            "subcategory":"Automobile Sales",
            "type":"Retail Goods"
        }
    ],
    "sg:phone":"+1 418 662 6528",
    "sg:postcode":"G8B 2V2",
    "sg:province":"QC",
    "sg:tags":[
        "car",
        "dealer",
        "detail"
    ],
    "wof:name":"Dupont Auto Enr Svc",
    "wof:placetype":"venue"
},
  "geometry": {"coordinates":[-71.6456375122,48.5413246155],"type":"Point"}
}