{
  "type": "Feature",
  "properties": {
    "addr:full":"51 Talbot St N Essex ON N8M 1A3",
    "addr:housenumber":"51",
    "addr:postcode":"n8m 1a3",
    "addr:street":"Talbot St N",
    "iso:country":"CA",
    "sg:address":"51 Talbot St N",
    "sg:city":"Essex",
    "sg:classifiers":[
        {
            "category":"Restaurant",
            "type":"Food & Drink"
        }
    ],
    "sg:phone":"+1 519 776 8112",
    "sg:postcode":"N8M 1A3",
    "sg:province":"ON",
    "wof:name":"Deluxe Restaurant",
    "wof:placetype":"venue"
},
  "geometry": {"coordinates":[-82.82218899999999,42.175053],"type":"Point"}
}