{
  "type": "Feature",
  "properties": {
    "addr:full":"2000 Ontario St Vancouver BC V5T 2W7",
    "addr:housenumber":"2000",
    "addr:postcode":"v5t 2w7",
    "addr:street":"Ontario St",
    "iso:country":"CA",
    "sg:address":"2000 Ontario St",
    "sg:city":"Vancouver",
    "sg:classifiers":[
        {
            "category":"Professional",
            "subcategory":"Art Services",
            "type":"Services"
        }
    ],
    "sg:phone":"+1 604 872 6002",
    "sg:postcode":"V5T 2W7",
    "sg:province":"BC",
    "sg:tags":[
        "advertising"
    ],
    "wof:name":"Hattenberger Photography",
    "wof:placetype":"venue"
},
  "geometry": {"coordinates":[-123.104645,49.2673],"type":"Point"}
}