{
  "type": "Feature",
  "properties": {
    "addr:full":"309 Belleville St Victoria BC V8V 1X2",
    "addr:housenumber":"309",
    "addr:postcode":"v8v 1x2",
    "addr:street":"Belleville St",
    "iso:country":"CA",
    "sg:address":"309 Belleville St",
    "sg:city":"Victoria",
    "sg:classifiers":[
        {
            "category":"Restaurant",
            "type":"Food & Drink"
        }
    ],
    "sg:phone":"+1 250 388 9191",
    "sg:postcode":"V8V 1X2",
    "sg:province":"BC",
    "sg:tags":[
        "breakfast",
        "accommodation",
        "bed"
    ],
    "wof:name":"Gatsby Mansion",
    "wof:placetype":"venue"
},
  "geometry": {"coordinates":[-123.37478637700001,48.4218559265],"type":"Point"}
}