{
  "type": "Feature",
  "properties": {
    "addr:full":"243 Hamilton St Neepawa MB R0J 1H0",
    "addr:housenumber":"243",
    "addr:postcode":"r0j 1h0",
    "addr:street":"Hamilton St",
    "iso:country":"CA",
    "sg:address":"243 Hamilton St",
    "sg:city":"Neepawa",
    "sg:classifiers":[
        {
            "category":"Manufacturing",
            "subcategory":"Printing",
            "type":"Manufacturing & Wholesale Goods"
        }
    ],
    "sg:phone":"+1 204 476 3401",
    "sg:postcode":"R0J 1H0",
    "sg:province":"MB",
    "sg:tags":[
        "newspaper"
    ],
    "wof:name":"Neepawa Banner",
    "wof:placetype":"venue"
},
  "geometry": {"coordinates":[-99.47068023680001,50.2284965515],"type":"Point"}
}