{
  "type": "Feature",
  "properties": {
    "iso:country":"CA",
    "sg:city":"Montreal",
    "sg:classifiers":[
        {
            "category":"Professional",
            "subcategory":"Lawyer & Legal Services",
            "type":"Services"
        }
    ],
    "sg:phone":"+1 514 878 9629",
    "sg:postcode":"H3B 2B2",
    "sg:province":"QC",
    "sg:tags":[
        "attorney"
    ],
    "wof:name":"Bottino, Presha",
    "wof:placetype":"venue"
},
  "geometry": {"coordinates":[-73.56797,45.50182],"type":"Point"}
}