{
  "type": "Feature",
  "properties": {
    "iso:country":"CA",
    "sg:address":"2600 Rue Badeaux",
    "sg:city":"Saint-Laurent",
    "sg:classifiers":[
        {
            "category":"Organizations",
            "subcategory":"Religious Organization",
            "type":"Services"
        }
    ],
    "sg:phone":"+1 514 748 6559",
    "sg:postcode":"H4M 1M5",
    "sg:province":"QC",
    "sg:tags":[
        "synagogue"
    ],
    "wof:name":"Congregation Beth Ora",
    "wof:placetype":"venue"
},
  "geometry": {"coordinates":[-73.6893692017,45.4970283508],"type":"Point"}
}