{
  "type": "Feature",
  "properties": {
    "addr:full":"710 51st St E Saskatoon SK S7K 4K4",
    "addr:housenumber":"710",
    "addr:postcode":"s7k 4k4",
    "addr:street":"51St St E",
    "iso:country":"CA",
    "sg:address":"710 51st St E",
    "sg:city":"Saskatoon",
    "sg:classifiers":[
        {
            "category":"Building & Trades",
            "subcategory":"Electrical",
            "type":"Services"
        }
    ],
    "sg:phone":"+1 306 665 5366",
    "sg:postcode":"S7K 4K4",
    "sg:province":"SK",
    "sg:tags":[
        "plumbing",
        "electric",
        "contractor"
    ],
    "wof:name":"Centennial Plumbing & Heating",
    "wof:placetype":"venue"
},
  "geometry": {"coordinates":[-106.656585693,52.173210144],"type":"Point"}
}