{
  "type": "Feature",
  "properties": {
    "addr:full":"1801 Centennial Cres North Battleford SK S9A 3J2",
    "addr:housenumber":"1801",
    "addr:postcode":"s9a 3j2",
    "addr:street":"Centennial Cres",
    "iso:country":"CA",
    "sg:address":"1801 Centennial Cres",
    "sg:city":"North Battleford",
    "sg:classifiers":[
        {
            "category":"Retail",
            "subcategory":"Animal Services",
            "type":"Services"
        }
    ],
    "sg:phone":"+1 306 445 9288",
    "sg:postcode":"S9A 3J2",
    "sg:province":"SK",
    "sg:tags":[
        "pet",
        "grooming",
        "washing"
    ],
    "wof:name":"Dirty Dogs Grooming",
    "wof:placetype":"venue"
},
  "geometry": {"coordinates":[-108.281784058,52.7835960388],"type":"Point"}
}