{
  "type": "Feature",
  "properties": {
    "addr:full":"675 Main St #8776 Birtle MB R0M 0C0",
    "addr:housenumber":"675",
    "addr:postcode":"r0m 0c0",
    "addr:street":"Main St # 8776",
    "iso:country":"CA",
    "sg:address":"675 Main St #8776",
    "sg:city":"Birtle",
    "sg:classifiers":[
        {
            "category":"Shopping",
            "subcategory":"Catalog Store",
            "type":"Retail Goods"
        }
    ],
    "sg:phone":"+1 204 842 3325",
    "sg:postcode":"R0M 0C0",
    "sg:province":"MB",
    "sg:tags":[
        "mail",
        "order",
        "internet"
    ],
    "wof:name":"Sears Canada Inc",
    "wof:placetype":"venue"
},
  "geometry": {"coordinates":[-101.049263,50.42226],"type":"Point"}
}