{
  "type": "Feature",
  "properties": {
    "addr:full":"2012 Rue Jean-Talon N Sainte-Foy QC G1N 2E8",
    "addr:housenumber":"2012",
    "addr:postcode":"g1n 2e8",
    "addr:street":"Rue Jean-Talon N Sainte-Foy",
    "iso:country":"CA",
    "sg:address":"2012 Rue Jean-Talon N",
    "sg:city":"Sainte-Foy",
    "sg:classifiers":[
        {
            "category":"Government",
            "subcategory":"Office",
            "type":"Public Place"
        }
    ],
    "sg:phone":"+1 418 683 3383",
    "sg:postcode":"G1N 2E8",
    "sg:province":"QC",
    "wof:name":"Quebec Mandataires",
    "wof:placetype":"venue"
},
  "geometry": {"coordinates":[-71.27076700000001,46.796139],"type":"Point"}
}