{
  "type": "Feature",
  "properties": {
    "addr:full":"Coquitlam BC V3K 3V9",
    "addr:postcode":"v3k 3v9",
    "iso:country":"CA",
    "sg:city":"Coquitlam",
    "sg:classifiers":[
        {
            "category":"Shopping",
            "subcategory":"Florist",
            "type":"Retail Goods"
        }
    ],
    "sg:phone":"+1 604 931 3522",
    "sg:postcode":"V3K 3V9",
    "sg:province":"BC",
    "wof:name":"Blue Mountain Florist",
    "wof:placetype":"venue"
},
  "geometry": {"coordinates":[-122.892539978,49.2475662231],"type":"Point"}
}