{
  "type": "Feature",
  "properties": {
    "addr:full":"332 Main St Bath NB E7J 1A2",
    "addr:housenumber":"332",
    "addr:postcode":"e7j 1a2",
    "addr:street":"Main St",
    "iso:country":"CA",
    "sg:address":"332 Main St",
    "sg:city":"Bath",
    "sg:classifiers":[
        {
            "category":"Wholesale",
            "subcategory":"Scrap",
            "type":"Manufacturing & Wholesale Goods"
        }
    ],
    "sg:phone":"+1 506 278 3264",
    "sg:postcode":"E7J 1A2",
    "sg:province":"NB",
    "sg:tags":[
        "recycling",
        "can",
        "bottle",
        "depot"
    ],
    "wof:name":"K C's Place",
    "wof:placetype":"venue"
},
  "geometry": {"coordinates":[-67.594871521,46.5093688965],"type":"Point"}
}