{
  "type": "Feature",
  "properties": {
    "addr:full":"50 Allen St E Waterloo QC J0E 2N0",
    "addr:housenumber":"50",
    "addr:postcode":"j0e 2n0",
    "addr:street":"Allen St E",
    "iso:country":"CA",
    "sg:address":"50 Allen St E",
    "sg:city":"Waterloo",
    "sg:classifiers":[
        {
            "category":"Building & Trades",
            "subcategory":"Construction",
            "type":"Services"
        }
    ],
    "sg:phone":"+1 450 539 1858",
    "sg:postcode":"J0E 2N0",
    "sg:province":"QC",
    "sg:tags":[
        "material",
        "roof",
        "structure"
    ],
    "wof:name":"Adam Lumber Inc",
    "wof:placetype":"venue"
},
  "geometry": {"coordinates":[-72.51165771479999,45.3505363464],"type":"Point"}
}