{
  "type": "Feature",
  "properties": {
    "iso:country":"CA",
    "sg:city":"Kirkland",
    "sg:classifiers":[
        {
            "category":"Restaurant",
            "type":"Food & Drink"
        }
    ],
    "sg:phone":"+1 514 630 6666",
    "sg:postcode":"H9H 3C3",
    "sg:province":"QC",
    "sg:tags":[
        "pizza"
    ],
    "wof:name":"Pizzalinni Restaurant",
    "wof:placetype":"venue"
},
  "geometry": {"coordinates":[-73.8638763428,45.4573554993],"type":"Point"}
}