{
  "type": "Feature",
  "properties": {
    "addr:full":"131 1E Ave E Saint-Martin QC G0M 1B0",
    "addr:housenumber":"131",
    "addr:postcode":"g0m 1b0",
    "addr:street":"1E Ave E Saint-Martin",
    "iso:country":"CA",
    "sg:address":"131 1E Ave E",
    "sg:city":"Saint-Martin",
    "sg:classifiers":[
        {
            "category":"Social Services",
            "type":"Services"
        }
    ],
    "sg:phone":"+1 418 382 3870",
    "sg:postcode":"G0M 1B0",
    "sg:province":"QC",
    "sg:tags":[
        "youth",
        "organization",
        "recreation",
        "center"
    ],
    "wof:name":"Maison Des Jeunes DE St-George",
    "wof:placetype":"venue"
},
  "geometry": {"coordinates":[-70.65643300000001,45.959202],"type":"Point"}
}