{
  "type": "Feature",
  "properties": {
    "iso:country":"CA",
    "sg:address":"55 Eccles St N",
    "sg:city":"Barrie",
    "sg:classifiers":[
        {
            "category":"Building & Trades",
            "subcategory":"Construction",
            "type":"Services"
        }
    ],
    "sg:phone":"+1 705 728 6628",
    "sg:postcode":"L4N 1Y3",
    "sg:province":"ON",
    "sg:tags":[
        "roofing",
        "contractor"
    ],
    "wof:name":"Graham Roofing Repair Svc",
    "wof:placetype":"venue"
},
  "geometry": {"coordinates":[-79.699585,44.388161],"type":"Point"}
}