{
  "type": "Feature",
  "properties": {
    "addr:full":"4392 Rue Des Martinets Charlesbourg QC G1G 6P8",
    "addr:housenumber":"4392",
    "addr:postcode":"g1g 6p8",
    "addr:street":"Rue Des Martinets",
    "iso:country":"CA",
    "sg:address":"4392 Rue Des Martinets",
    "sg:city":"Charlesbourg",
    "sg:classifiers":[
        {
            "category":"Recreation",
            "type":"Entertainment"
        }
    ],
    "sg:phone":"+1 418 623 8174",
    "sg:postcode":"G1G 6P8",
    "sg:province":"QC",
    "sg:tags":[
        "parachute",
        "skydiving",
        "jumping"
    ],
    "wof:name":"Centre Ecole DE Parachutisme",
    "wof:placetype":"venue"
},
  "geometry": {"coordinates":[-71.293701,46.877506],"type":"Point"}
}