{
  "type": "Feature",
  "properties": {
    "addr:full":"Kilworthy ON P0E 1G0",
    "addr:postcode":"p0e 1g0",
    "iso:country":"CA",
    "sg:city":"Kilworthy",
    "sg:classifiers":[
        {
            "category":"Building & Trades",
            "subcategory":"Construction",
            "type":"Services"
        }
    ],
    "sg:phone":"+1 705 689 5646",
    "sg:postcode":"P0E 1G0",
    "sg:province":"ON",
    "sg:tags":[
        "dock",
        "designer",
        "marine",
        "contractor"
    ],
    "wof:name":"Docks By Muskoka Leisure",
    "wof:placetype":"venue"
},
  "geometry": {"coordinates":[-79.3479309082,44.8502349854],"type":"Point"}
}