{
  "type": "Feature",
  "properties": {
    "addr:full":"115 Hazen St Saint John NB E2L 3L3",
    "addr:housenumber":"115",
    "addr:postcode":"nb e2l 3l3",
    "addr:street":"Hazen St",
    "iso:country":"CA",
    "sg:address":"115 Hazen St",
    "sg:city":"Saint John",
    "sg:classifiers":[
        {
            "category":"Health Services",
            "subcategory":"Health Practitioner",
            "type":"Services"
        }
    ],
    "sg:phone":"+1 506 693 2114",
    "sg:postcode":"E2L 3L3",
    "sg:province":"NB",
    "sg:tags":[
        "acupuncture",
        "physician"
    ],
    "wof:name":"Cathleen K Coleman Naturopath",
    "wof:placetype":"venue"
},
  "geometry": {"coordinates":[-66.059235,45.278587],"type":"Point"}
}