{
  "type": "Feature",
  "properties": {
    "addr:full":"Montreal QC H3A 3M8",
    "addr:postcode":"h3a 3m8",
    "iso:country":"CA",
    "sg:city":"Montreal",
    "sg:classifiers":[
        {
            "category":"Professional",
            "subcategory":"Lawyer & Legal Services",
            "type":"Services"
        }
    ],
    "sg:phone":"+1 514 284 3663",
    "sg:postcode":"H3A 3M8",
    "sg:province":"QC",
    "sg:tags":[
        "attorney"
    ],
    "wof:name":"Colby Monet Demers Delage",
    "wof:placetype":"venue"
},
  "geometry": {"coordinates":[-73.57151,45.502453],"type":"Point"}
}