{
  "type": "Feature",
  "properties": {
    "addr:full":"380 Harvey Ave Kelowna BC V1Y 6C4",
    "addr:housenumber":"380",
    "addr:postcode":"v1y 6c4",
    "addr:street":"Harvey Ave",
    "iso:country":"CA",
    "sg:address":"380 Harvey Ave",
    "sg:city":"Kelowna",
    "sg:classifiers":[
        {
            "category":"Retail",
            "subcategory":"Auto Rental",
            "type":"Services"
        }
    ],
    "sg:phone":"+1 250 763 4668",
    "sg:postcode":"V1Y 6C4",
    "sg:province":"BC",
    "sg:tags":[
        "scooter",
        "recreational",
        "leasing",
        "motorcycle",
        "motor"
    ],
    "wof:name":"Mc Scoot's Scotter Rentals",
    "wof:placetype":"venue"
},
  "geometry": {"coordinates":[-119.49543799999999,49.883755],"type":"Point"}
}