{
  "type": "Feature",
  "properties": {
    "addr:full":"Mississauga ON L5T 1Y4",
    "addr:postcode":"l5t 1y4",
    "iso:country":"CA",
    "sg:city":"Mississauga",
    "sg:classifiers":[
        {
            "category":"Wholesale",
            "subcategory":"Durable Goods & Equipment",
            "type":"Manufacturing & Wholesale Goods"
        }
    ],
    "sg:phone":"+1 905 565 8298",
    "sg:postcode":"L5T 1Y4",
    "sg:province":"ON",
    "sg:tags":[
        "importer"
    ],
    "wof:name":"Comet Strip E Enterprises Ltd",
    "wof:placetype":"venue"
},
  "geometry": {"coordinates":[-79.668442,43.653156],"type":"Point"}
}