{
  "type": "Feature",
  "properties": {
    "addr:full":"2496 Bank St Ottawa ON K1V 8S2",
    "addr:housenumber":"2496",
    "addr:postcode":"k1v 8s2",
    "addr:street":"Bank St",
    "iso:country":"CA",
    "sg:address":"2496 Bank St",
    "sg:city":"Ottawa",
    "sg:classifiers":[
        {
            "category":"Autos & Motor Vehicles",
            "subcategory":"Automobile Sales",
            "type":"Retail Goods"
        }
    ],
    "sg:phone":"+1 613 733 6931",
    "sg:postcode":"K1V 8S2",
    "sg:province":"ON",
    "sg:tags":[
        "car",
        "dealer"
    ],
    "wof:name":"Donnelly Ford Lincoln",
    "wof:placetype":"venue"
},
  "geometry": {"coordinates":[-75.6435852051,45.353679657],"type":"Point"}
}