{
  "type": "Feature",
  "properties": {
    "addr:full":"7174 Boul Provencher Saint-Leonard QC H1S 3B6",
    "addr:housenumber":"7174",
    "addr:postcode":"h1s 3b6",
    "addr:street":"Boul Provencher",
    "iso:country":"CA",
    "sg:address":"7174 Boul Provencher",
    "sg:city":"Saint-Leonard",
    "sg:classifiers":[
        {
            "category":"Building & Trades",
            "subcategory":"Construction",
            "type":"Services"
        }
    ],
    "sg:phone":"+1 514 725 2961",
    "sg:postcode":"H1S 3B6",
    "sg:province":"QC",
    "sg:tags":[
        "demolition",
        "contractor"
    ],
    "wof:name":"Giovanni Demolition Ltee",
    "wof:placetype":"venue"
},
  "geometry": {"coordinates":[-73.586899,45.57098],"type":"Point"}
}