{
  "type": "Feature",
  "properties": {
    "addr:full":"2956 Eglinton Ave E Scarborough ON M1J 2E7",
    "addr:housenumber":"2956",
    "addr:postcode":"m1j 2e7",
    "addr:street":"Eglinton Ave E",
    "iso:country":"CA",
    "sg:address":"2956 Eglinton Ave E",
    "sg:city":"Scarborough",
    "sg:classifiers":[
        {
            "category":"Cinema",
            "subcategory":"Movie Rental",
            "type":"Entertainment"
        }
    ],
    "sg:phone":"+1 416 289 3720",
    "sg:postcode":"M1J 2E7",
    "sg:province":"ON",
    "sg:tags":[
        "leasing",
        "video",
        "disc",
        "tape"
    ],
    "wof:name":"Video Express",
    "wof:placetype":"venue"
},
  "geometry": {"coordinates":[-79.234222,43.739941],"type":"Point"}
}