{
  "type": "Feature",
  "properties": {
    "addr:full":"990 Cole Harbour Rd Dartmouth NS B2V 1E7",
    "addr:housenumber":"990",
    "addr:postcode":"b2v 1e7",
    "addr:street":"Cole Harbour Rd",
    "iso:country":"CA",
    "sg:address":"990 Cole Harbour Rd",
    "sg:city":"Dartmouth",
    "sg:classifiers":[
        {
            "category":"Professional",
            "subcategory":"Lawyer & Legal Services",
            "type":"Services"
        }
    ],
    "sg:phone":"+1 902 462 2009",
    "sg:postcode":"B2V 1E7",
    "sg:province":"NS",
    "sg:tags":[
        "attorney"
    ],
    "wof:name":"Cole Harbour Law Office",
    "wof:placetype":"venue"
},
  "geometry": {"coordinates":[-63.492561,44.671379],"type":"Point"}
}