{
  "type": "Feature",
  "properties": {
    "addr:full":"559 Exmouth St Sarnia ON N7T 5P6",
    "addr:housenumber":"559",
    "addr:postcode":"n7t 5p6",
    "addr:street":"Exmouth St",
    "iso:country":"CA",
    "sg:address":"559 Exmouth St",
    "sg:city":"Sarnia",
    "sg:classifiers":[
        {
            "category":"Real Estate",
            "subcategory":"Real Estate Agent",
            "type":"Services"
        }
    ],
    "sg:phone":"+1 519 332 1815",
    "sg:postcode":"N7T 5P6",
    "sg:province":"ON",
    "wof:name":"William R Dennis Real Estate",
    "wof:placetype":"venue"
},
  "geometry": {"coordinates":[-82.38562,42.985126],"type":"Point"}
}