{
  "type": "Feature",
  "properties": {
    "addr:full":"Arcadia NS B0W 1B0",
    "addr:postcode":"b0w 1b0",
    "iso:country":"CA",
    "sg:city":"Arcadia",
    "sg:classifiers":[
        {
            "category":"Organizations",
            "subcategory":"Religious Organization",
            "type":"Services"
        }
    ],
    "sg:phone":"+1 902 742 7591",
    "sg:postcode":"B0W 1B0",
    "sg:province":"NS",
    "sg:tags":[
        "church"
    ],
    "wof:name":"Cornerstone Church of God",
    "wof:placetype":"venue"
},
  "geometry": {"coordinates":[-66.0688323975,43.8255081177],"type":"Point"}
}