{
  "type": "Feature",
  "properties": {
    "iso:country":"CA",
    "sg:address":"736 Davis Dr",
    "sg:city":"Newmarket",
    "sg:classifiers":[
        {
            "category":"Organizations",
            "subcategory":"Religious Organization",
            "type":"Services"
        }
    ],
    "sg:phone":"+1 905 853 1430",
    "sg:postcode":"L3Y 2R4",
    "sg:province":"ON",
    "sg:tags":[
        "church"
    ],
    "wof:name":"Newmarket Gospel Hall",
    "wof:placetype":"venue"
},
  "geometry": {"coordinates":[-79.44676971440001,44.0622596741],"type":"Point"}
}