{
  "type": "Feature",
  "properties": {
    "iso:country":"CA",
    "sg:address":"672 Rue Jacques-Cartier E",
    "sg:city":"Chicoutimi",
    "sg:classifiers":[
        {
            "category":"Health Services",
            "subcategory":"Doctor",
            "type":"Services"
        }
    ],
    "sg:phone":"+1 418 696 1626",
    "sg:postcode":"G7H 2A4",
    "sg:province":"QC",
    "sg:tags":[
        "dentist"
    ],
    "wof:name":"Clinique Dentaire M Desautels",
    "wof:placetype":"venue"
},
  "geometry": {"coordinates":[-71.047997,48.424854],"type":"Point"}
}