{
  "type": "Feature",
  "properties": {
    "addr:full":"Arkona ON N0M 1B0",
    "addr:postcode":"n0m 1b0",
    "iso:country":"CA",
    "sg:city":"Arkona",
    "sg:classifiers":[
        {
            "category":"Manufacturing",
            "subcategory":"Pet Food",
            "type":"Manufacturing & Wholesale Goods"
        }
    ],
    "sg:phone":"+1 519 828 3385",
    "sg:postcode":"N0M 1B0",
    "sg:province":"ON",
    "sg:tags":[
        "feed"
    ],
    "wof:name":"Cargill Limited",
    "wof:placetype":"venue"
},
  "geometry": {"coordinates":[-81.8341369629,43.0743637085],"type":"Point"}
}