{
  "type": "Feature",
  "properties": {
    "addr:full":"2210 Rue Lesperance Montreal QC H2K 2N9",
    "addr:housenumber":"2210",
    "addr:postcode":"h2k 2n9",
    "addr:street":"Rue Lesperance",
    "iso:country":"CA",
    "sg:address":"2210 Rue Lesperance",
    "sg:city":"Montreal",
    "sg:classifiers":[
        {
            "category":"Retail",
            "subcategory":"Auto Repair",
            "type":"Services"
        }
    ],
    "sg:phone":"+1 514 522 1234",
    "sg:postcode":"H2K 2N9",
    "sg:province":"QC",
    "sg:tags":[
        "wrecker"
    ],
    "wof:name":"Remourquage Groupe Pichou",
    "wof:placetype":"venue"
},
  "geometry": {"coordinates":[-73.55207799999999,45.538441],"type":"Point"}
}