{
  "type": "Feature",
  "properties": {
    "iso:country":"CA",
    "sg:address":"2210 Rue Lesperance",
    "sg:city":"Montreal",
    "sg:classifiers":[
        {
            "category":"Retail",
            "subcategory":"Auto Repair",
            "type":"Services"
        }
    ],
    "sg:phone":"+1 514 522 1234",
    "sg:postcode":"H2K 2N9",
    "sg:province":"QC",
    "sg:tags":[
        "wrecker"
    ],
    "wof:name":"Remourquage Groupe Pichou",
    "wof:placetype":"venue"
},
  "geometry": {"coordinates":[-73.552078,45.538441],"type":"Point"}
}