{
  "type": "Feature",
  "properties": {
    "addr:full":"520 Mcdonald St New Westminster BC V3L 4L6",
    "addr:housenumber":"520",
    "addr:postcode":"v3l 4l6",
    "addr:street":"Mcdonald St",
    "iso:country":"CA",
    "sg:address":"520 Mcdonald St",
    "sg:city":"New Westminster",
    "sg:classifiers":[
        {
            "category":"Organizations",
            "subcategory":"Religious Organization",
            "type":"Services"
        }
    ],
    "sg:phone":"+1 604 526 3131",
    "sg:postcode":"V3L 4L6",
    "sg:province":"BC",
    "sg:tags":[
        "church"
    ],
    "wof:name":"Shiloh United Church",
    "wof:placetype":"venue"
},
  "geometry": {"coordinates":[-122.894722,49.232254],"type":"Point"}
}