{
  "type": "Feature",
  "properties": {
    "addr:full":"10372 58 Ave NW Edmonton AB T6H 1B6",
    "addr:housenumber":"10372",
    "addr:postcode":"t6h 1b6",
    "addr:street":"58 Ave Nw",
    "iso:country":"CA",
    "sg:address":"10372 58 Ave NW",
    "sg:city":"Edmonton",
    "sg:classifiers":[
        {
            "category":"Mining & Drilling",
            "type":"Manufacturing & Wholesale Goods"
        }
    ],
    "sg:phone":"+1 780 431 0641",
    "sg:postcode":"T6H 1B6",
    "sg:province":"AB",
    "sg:tags":[
        "field",
        "oil"
    ],
    "wof:name":"Cofex Limited",
    "wof:placetype":"venue"
},
  "geometry": {"coordinates":[-113.496155,53.495258],"type":"Point"}
}