{
  "type": "Feature",
  "properties": {
    "iso:country":"CA",
    "sg:address":"4230 Cedar Hill Rd",
    "sg:city":"Victoria",
    "sg:classifiers":[
        {
            "category":"Home & Garden",
            "subcategory":"Building Materials",
            "type":"Retail Goods"
        }
    ],
    "sg:phone":"+1 250 380 8064",
    "sg:postcode":"V8N 3C5",
    "sg:province":"BC",
    "sg:tags":[
        "windows",
        "skylight"
    ],
    "wof:name":"Garanzda Window Installations",
    "wof:placetype":"venue"
},
  "geometry": {"coordinates":[-123.34403228799999,48.4483108521],"type":"Point"}
}