{
  "type": "Feature",
  "properties": {
    "iso:country":"CA",
    "sg:address":"Sadler Ave",
    "sg:city":"Gainsborough",
    "sg:classifiers":[
        {
            "category":"Personal",
            "type":"Services"
        }
    ],
    "sg:phone":"+1 306 685 4467",
    "sg:postcode":"S0C 0Z0",
    "sg:province":"SK",
    "sg:tags":[
        "therapist",
        "massage"
    ],
    "wof:name":"Rhonda Huish Registered Mssge",
    "wof:placetype":"venue"
},
  "geometry": {"coordinates":[-101.45195770300001,49.1773643494],"type":"Point"}
}