{
  "type": "Feature",
  "properties": {
    "addr:full":"Etobicoke ON M8V 2C8",
    "addr:postcode":"m8v 2c8",
    "iso:country":"CA",
    "sg:city":"Etobicoke",
    "sg:classifiers":[
        {
            "category":"Retail",
            "subcategory":"Auto Repair",
            "type":"Services"
        }
    ],
    "sg:phone":"+1 416 201 8040",
    "sg:postcode":"M8V 2C8",
    "sg:province":"ON",
    "sg:tags":[
        "automobile",
        "parts",
        "wrecker"
    ],
    "wof:name":"Top Bashaw",
    "wof:placetype":"venue"
},
  "geometry": {"coordinates":[-79.51373291020001,43.6017532349],"type":"Point"}
}