{
  "type": "Feature",
  "properties": {
    "addr:full":"PO Box 239 Rainbow Lake AB T0H 2Y0",
    "addr:housenumber":"po",
    "addr:postcode":"t0h 2y0",
    "addr:street":"Box 239 Rainbow",
    "iso:country":"CA",
    "sg:address":"PO Box 239",
    "sg:city":"Rainbow Lake",
    "sg:classifiers":[
        {
            "category":"Mining & Drilling",
            "type":"Manufacturing & Wholesale Goods"
        }
    ],
    "sg:phone":"+1 780 956 3736",
    "sg:postcode":"T0H 2Y0",
    "sg:province":"AB",
    "sg:tags":[
        "field",
        "oil"
    ],
    "wof:name":"Circle R Oilfield Rentals Ltd",
    "wof:placetype":"venue"
},
  "geometry": {"coordinates":[-119.410248,58.499573],"type":"Point"}
}