{
  "type": "Feature",
  "properties": {
    "addr:full":"3540 Pembina Hwy Winnipeg MB R3V 1A6",
    "addr:housenumber":"3540",
    "addr:postcode":"r3v 1a6",
    "addr:street":"Pembina Hwy",
    "iso:country":"CA",
    "sg:address":"3540 Pembina Hwy",
    "sg:city":"Winnipeg",
    "sg:classifiers":[
        {
            "category":"Travel",
            "subcategory":"Hotels & Motels",
            "type":"Entertainment"
        }
    ],
    "sg:phone":"+1 204 269 1290",
    "sg:postcode":"R3V 1A6",
    "sg:province":"MB",
    "wof:name":"St Norbert Motor Hotel",
    "wof:placetype":"venue"
},
  "geometry": {"coordinates":[-97.15344238279999,49.7654342651],"type":"Point"}
}