{
  "type": "Feature",
  "properties": {
    "addr:full":"1870 6E Av Grand-Mere QC G9T 2K7",
    "addr:housenumber":"1870",
    "addr:postcode":"g9t 2k7",
    "addr:street":"6E Av Grand-Mere",
    "iso:country":"CA",
    "sg:address":"1870 6E Av",
    "sg:city":"Grand-Mere",
    "sg:classifiers":[
        {
            "category":"Autos & Motor Vehicles",
            "subcategory":"Automobile Sales",
            "type":"Retail Goods"
        }
    ],
    "sg:phone":"+1 819 538 3357",
    "sg:postcode":"G9T 2K7",
    "sg:province":"QC",
    "sg:tags":[
        "car",
        "dealer"
    ],
    "wof:name":"St-Onge Ford Inc",
    "wof:placetype":"venue"
},
  "geometry": {"coordinates":[-72.70751953120001,46.604385376],"type":"Point"}
}