{
  "type": "Feature",
  "properties": {
    "addr:full":"700 Sixth St New Westminster BC V3L 3C5",
    "addr:housenumber":"700",
    "addr:postcode":"v3l 3c5",
    "addr:street":"Sixth St",
    "iso:country":"CA",
    "sg:address":"700 Sixth St",
    "sg:city":"New Westminster",
    "sg:classifiers":[
        {
            "category":"Cinema",
            "subcategory":"Movie Rental",
            "type":"Entertainment"
        }
    ],
    "sg:phone":"+1 604 517 0357",
    "sg:postcode":"V3L 3C5",
    "sg:province":"BC",
    "sg:tags":[
        "leasing",
        "video",
        "disc",
        "tape"
    ],
    "wof:name":"Blockbuster Video",
    "wof:placetype":"venue"
},
  "geometry": {"coordinates":[-122.92215728799999,49.2145080566],"type":"Point"}
}