{
  "type": "Feature",
  "properties": {
    "addr:full":"865 Hugel Ave Midland ON L4R 1X8",
    "addr:housenumber":"865",
    "addr:postcode":"l4r 1x8",
    "addr:street":"Hugel Ave",
    "iso:country":"CA",
    "sg:address":"865 Hugel Ave",
    "sg:city":"Midland",
    "sg:classifiers":[
        {
            "category":"Education",
            "subcategory":"School",
            "type":"Public Place"
        }
    ],
    "sg:phone":"+1 705 526 7817",
    "sg:postcode":"L4R 1X8",
    "sg:province":"ON",
    "wof:name":"Midland Secondary School",
    "wof:placetype":"venue"
},
  "geometry": {"coordinates":[-79.899643,44.743584],"type":"Point"}
}