{
  "type": "Feature",
  "properties": {
    "addr:full":"Langley BC V2Y 1A5",
    "addr:postcode":"v2y 1a5",
    "iso:country":"CA",
    "sg:city":"Langley",
    "sg:classifiers":[
        {
            "category":"Restaurant",
            "type":"Food & Drink"
        }
    ],
    "sg:phone":"+1 604 533 7988",
    "sg:postcode":"V2Y 1A5",
    "sg:province":"BC",
    "wof:name":"C & U Vietnamese Restaurant",
    "wof:placetype":"venue"
},
  "geometry": {"coordinates":[-122.67861175500001,49.1159706116],"type":"Point"}
}