{
  "type": "Feature",
  "properties": {
    "addr:full":"42 Rue Monseigneur-Rheaume E Rouyn-Noranda QC J9X 3J5",
    "addr:housenumber":"42",
    "addr:postcode":"j9x 3j5",
    "addr:street":"Rue Monseigneur-Rheaume E",
    "iso:country":"CA",
    "sg:address":"42 Rue Monseigneur-Rheaume E",
    "sg:city":"Rouyn-Noranda",
    "sg:classifiers":[
        {
            "category":"Personal",
            "subcategory":"Beauty Salon",
            "type":"Services"
        }
    ],
    "sg:phone":"+1 819 762 9292",
    "sg:postcode":"J9X 3J5",
    "sg:province":"QC",
    "wof:name":"Salon Ciseaux D'Or",
    "wof:placetype":"venue"
},
  "geometry": {"coordinates":[-79.0085449219,48.2359580994],"type":"Point"}
}