{
  "type": "Feature",
  "properties": {
    "addr:full":"315 Boul Saint-Martin O # 200 Laval QC H7M 1Y7",
    "addr:housenumber":"315",
    "addr:postcode":"h7m 1y7",
    "addr:street":"Boul Saint-Martin O # 200",
    "iso:country":"CA",
    "sg:address":"315 Boul Saint-Martin O # 200",
    "sg:city":"Laval",
    "sg:classifiers":[
        {
            "category":"Health Services",
            "subcategory":"Chiropractor",
            "type":"Services"
        }
    ],
    "sg:phone":"+1 450 662 0100",
    "sg:postcode":"H7M 1Y7",
    "sg:province":"QC",
    "wof:name":"Chiropractique St Martin",
    "wof:placetype":"venue"
},
  "geometry": {"coordinates":[-73.7100143433,45.5789413452],"type":"Point"}
}