{
  "type": "Feature",
  "properties": {
    "addr:full":"571 Brookridge Cres Orleans ON K4A 1Z3",
    "addr:housenumber":"571",
    "addr:postcode":"k4a 1z3",
    "addr:street":"Brookridge Cres",
    "iso:country":"CA",
    "sg:address":"571 Brookridge Cres",
    "sg:city":"Orleans",
    "sg:classifiers":[
        {
            "category":"Wholesale",
            "subcategory":"Photographic Equipment",
            "type":"Manufacturing & Wholesale Goods"
        }
    ],
    "sg:phone":"+1 613 830 2333",
    "sg:postcode":"K4A 1Z3",
    "sg:province":"ON",
    "sg:tags":[
        "live",
        "music",
        "entertainment"
    ],
    "wof:name":"Capital Sound & Light",
    "wof:placetype":"venue"
},
  "geometry": {"coordinates":[-75.4937286377,45.4852027893],"type":"Point"}
}