{
  "type": "Feature",
  "properties": {
    "addr:full":"2065 Rue Mansfield Montreal QC H3A 1Y7",
    "addr:housenumber":"2065",
    "addr:postcode":"h3a 1y7",
    "addr:street":"Rue Mansfield",
    "iso:country":"CA",
    "sg:address":"2065 Rue Mansfield",
    "sg:city":"Montreal",
    "sg:classifiers":[
        {
            "category":"Travel",
            "subcategory":"Travel Agent",
            "type":"Entertainment"
        }
    ],
    "sg:phone":"+1 514 845 4664",
    "sg:postcode":"H3A 1Y7",
    "sg:province":"QC",
    "sg:tags":[
        "agency",
        "bureau"
    ],
    "wof:name":"Agence DE Voyages Laurier Du",
    "wof:placetype":"venue"
},
  "geometry": {"coordinates":[-73.57443237299999,45.5029563904],"type":"Point"}
}