{
  "type": "Feature",
  "properties": {
    "addr:full":"Sidney BC V8L 4Z9",
    "addr:postcode":"v8l 4z9",
    "iso:country":"CA",
    "sg:city":"Sidney",
    "sg:classifiers":[
        {
            "category":"Personal",
            "subcategory":"Beauty Salon",
            "type":"Services"
        }
    ],
    "sg:phone":"+1 250 656 1522",
    "sg:postcode":"V8L 4Z9",
    "sg:province":"BC",
    "wof:name":"House of Russell Hair Stylists",
    "wof:placetype":"venue"
},
  "geometry": {"coordinates":[-123.401573,48.647865],"type":"Point"}
}