{
  "type": "Feature",
  "properties": {
    "addr:full":"7083 120 St Delta BC V4E 2A9",
    "addr:housenumber":"7083",
    "addr:postcode":"v4e 2a9",
    "addr:street":"120 St",
    "iso:country":"CA",
    "sg:address":"7083 120 St",
    "sg:city":"Delta",
    "sg:classifiers":[
        {
            "category":"Shopping",
            "subcategory":"Clothing, Apparel, & Fashions",
            "type":"Retail Goods"
        }
    ],
    "sg:phone":"+1 604 590 7329",
    "sg:postcode":"V4E 2A9",
    "sg:province":"BC",
    "sg:tags":[
        "furnishing"
    ],
    "wof:name":"Base Line Clothing",
    "wof:placetype":"venue"
},
  "geometry": {"coordinates":[-122.890556335,49.1319313049],"type":"Point"}
}