{
  "type": "Feature",
  "properties": {
    "addr:full":"172 Hwy 9 Winnipeg Beach MB R0C 3G0",
    "addr:housenumber":"172",
    "addr:postcode":"r0c 3g0",
    "addr:street":"Hwy 9",
    "iso:country":"CA",
    "sg:address":"172 Hwy 9",
    "sg:city":"Winnipeg Beach",
    "sg:classifiers":[
        {
            "category":"Building & Trades",
            "subcategory":"Electrical",
            "type":"Services"
        }
    ],
    "sg:phone":"+1 204 389 2171",
    "sg:postcode":"R0C 3G0",
    "sg:province":"MB",
    "sg:tags":[
        "electric",
        "contractor"
    ],
    "wof:name":"Jerry's Electric",
    "wof:placetype":"venue"
},
  "geometry": {"coordinates":[-96.975227,50.493752],"type":"Point"}
}