{
  "type": "Feature",
  "properties": {
    "addr:full":"1163 Frances St London ON N5W 2L9",
    "addr:housenumber":"1163",
    "addr:postcode":"n5w 2l9",
    "addr:street":"Frances St",
    "iso:country":"CA",
    "sg:address":"1163 Frances St",
    "sg:city":"London",
    "sg:classifiers":[
        {
            "category":"Building & Trades",
            "subcategory":"Construction",
            "type":"Services"
        }
    ],
    "sg:phone":"+1 519 452 3122",
    "sg:postcode":"N5W 2L9",
    "sg:province":"ON",
    "sg:tags":[
        "concrete",
        "contractor"
    ],
    "wof:name":"Forest City Concrete Finishing",
    "wof:placetype":"venue"
},
  "geometry": {"coordinates":[-81.209602,42.990414],"type":"Point"}
}