{
  "type": "Feature",
  "properties": {
    "addr:full":"105 Valley Cres Markdale ON N0C 1H0",
    "addr:housenumber":"105",
    "addr:postcode":"n0c 1h0",
    "addr:street":"Valley Cres",
    "iso:country":"CA",
    "sg:address":"105 Valley Cres",
    "sg:city":"Markdale",
    "sg:classifiers":[
        {
            "category":"Professional",
            "subcategory":"Business Services",
            "type":"Services"
        }
    ],
    "sg:phone":"+1 519 986 4783",
    "sg:postcode":"N0C 1H0",
    "sg:province":"ON",
    "sg:tags":[
        "consultant",
        "computer"
    ],
    "wof:name":"Synectics Business Solutions",
    "wof:placetype":"venue"
},
  "geometry": {"coordinates":[-80.563019,44.344612],"type":"Point"}
}