{
  "type": "Feature",
  "properties": {
    "addr:full":"7032 Cranberry St Powell River BC V8A 3Z8",
    "addr:housenumber":"7032",
    "addr:postcode":"v8a 3z8",
    "addr:street":"Cranberry St",
    "iso:country":"CA",
    "sg:address":"7032 Cranberry St",
    "sg:city":"Powell River",
    "sg:classifiers":[
        {
            "category":"Social Services",
            "subcategory":"Child Care",
            "type":"Services"
        }
    ],
    "sg:phone":"+1 604 483 2099",
    "sg:postcode":"V8A 3Z8",
    "sg:province":"BC",
    "wof:name":"Lakeside Preschool",
    "wof:placetype":"venue"
},
  "geometry": {"coordinates":[-124.518836975,49.8729629517],"type":"Point"}
}