{
  "type": "Feature",
  "properties": {
    "addr:full":"295 Ch Sainte-Foy Quebec QC G1R 1T5",
    "addr:housenumber":"295",
    "addr:postcode":"g1r 1t5",
    "addr:street":"Ch Sainte-Foy",
    "iso:country":"CA",
    "sg:address":"295 Ch Sainte-Foy",
    "sg:city":"Quebec",
    "sg:classifiers":[
        {
            "category":"Organizations",
            "subcategory":"Professional Association",
            "type":"Services"
        }
    ],
    "sg:phone":"+1 418 525 7779",
    "sg:postcode":"G1R 1T5",
    "sg:province":"QC",
    "wof:name":"Gremm",
    "wof:placetype":"venue"
},
  "geometry": {"coordinates":[-71.23152160639999,46.8042259216],"type":"Point"}
}