{
  "type": "Feature",
  "properties": {
    "addr:full":"511 Notre Dame St Belle River ON N0R 1A0",
    "addr:housenumber":"511",
    "addr:postcode":"n0r 1a0",
    "addr:street":"Notre Dame St",
    "iso:country":"CA",
    "sg:address":"511 Notre Dame St",
    "sg:city":"Belle River",
    "sg:classifiers":[
        {
            "category":"Personal",
            "type":"Services"
        }
    ],
    "sg:phone":"+1 519 728 0600",
    "sg:postcode":"N0R 1A0",
    "sg:province":"ON",
    "sg:tags":[
        "therapist",
        "massage"
    ],
    "wof:name":"Hands For Health",
    "wof:placetype":"venue"
},
  "geometry": {"coordinates":[-82.70674099999999,42.293209],"type":"Point"}
}