{
  "type": "Feature",
  "properties": {
    "addr:full":"2410 Finch Ave W North York ON M9M 2E1",
    "addr:housenumber":"2410",
    "addr:postcode":"m9m 2e1",
    "addr:street":"Finch Ave W",
    "iso:country":"CA",
    "sg:address":"2410 Finch Ave W",
    "sg:city":"North York",
    "sg:classifiers":[
        {
            "category":"Retail",
            "subcategory":"Auto Repair",
            "type":"Services"
        }
    ],
    "sg:phone":"+1 416 748 0444",
    "sg:postcode":"M9M 2E1",
    "sg:province":"ON",
    "sg:tags":[
        "repairing",
        "automobile",
        "lubrication"
    ],
    "wof:name":"Express Lube Ctr",
    "wof:placetype":"venue"
},
  "geometry": {"coordinates":[-79.5494842529,43.7507019043],"type":"Point"}
}