{
  "type": "Feature",
  "properties": {
    "addr:full":"Forest ON N0N 1J0",
    "addr:postcode":"n0n 1j0",
    "iso:country":"CA",
    "sg:city":"Forest",
    "sg:classifiers":[
        {
            "category":"Building & Trades",
            "subcategory":"Construction",
            "type":"Services"
        }
    ],
    "sg:phone":"+1 519 243 3011",
    "sg:postcode":"N0N 1J0",
    "sg:province":"ON",
    "sg:tags":[
        "home",
        "improvement"
    ],
    "wof:name":"Mike Kenny Aluminum",
    "wof:placetype":"venue"
},
  "geometry": {"coordinates":[-81.97662353520001,43.2055702209],"type":"Point"}
}