{
  "type": "Feature",
  "properties": {
    "addr:full":"East York ON M4G 4E8",
    "addr:postcode":"m4g 4e8",
    "iso:country":"CA",
    "sg:city":"East York",
    "sg:classifiers":[
        {
            "category":"Manufacturing",
            "subcategory":"Electronics",
            "type":"Manufacturing & Wholesale Goods"
        }
    ],
    "sg:phone":"+1 416 424 2002",
    "sg:postcode":"M4G 4E8",
    "sg:province":"ON",
    "sg:tags":[
        "control",
        "security",
        "patrol",
        "guard"
    ],
    "wof:name":"Intertec Security Ltd",
    "wof:placetype":"venue"
},
  "geometry": {"coordinates":[-79.359932,43.714493],"type":"Point"}
}