{
  "type": "Feature",
  "properties": {
    "iso:country":"CA",
    "sg:address":"5191 Joyce St",
    "sg:city":"Vancouver",
    "sg:classifiers":[
        {
            "category":"Food & Beverages",
            "subcategory":"Groceries & Convenience Stores",
            "type":"Retail Goods"
        }
    ],
    "sg:phone":"+1 604 436 0146",
    "sg:postcode":"V5R 4G8",
    "sg:province":"BC",
    "sg:tags":[
        "grocer"
    ],
    "wof:name":"Sari Sari Store",
    "wof:placetype":"venue"
},
  "geometry": {"coordinates":[-123.032753,49.237644],"type":"Point"}
}