{
  "type": "Feature",
  "properties": {
    "iso:country":"CA",
    "sg:address":"450 Rue Leveille",
    "sg:city":"Terrebonne",
    "sg:classifiers":[
        {
            "category":"Wholesale",
            "subcategory":"Home Furnishings",
            "type":"Manufacturing & Wholesale Goods"
        }
    ],
    "sg:phone":"+1 450 471 4778",
    "sg:postcode":"J6W 1Z5",
    "sg:province":"QC",
    "sg:tags":[
        "picture",
        "frame"
    ],
    "wof:name":"Encadrements Rg",
    "wof:placetype":"venue"
},
  "geometry": {"coordinates":[-73.62478637700001,45.697517395],"type":"Point"}
}