{
  "type": "Feature",
  "properties": {
    "iso:country":"CA",
    "sg:city":"Chilliwack",
    "sg:classifiers":[
        {
            "category":"Shopping",
            "type":"Retail Goods"
        }
    ],
    "sg:phone":"+1 604 792 1186",
    "sg:postcode":"V2P 1T5",
    "sg:province":"BC",
    "sg:tags":[
        "hearing",
        "equipment",
        "supply",
        "impaired"
    ],
    "wof:name":"Beltone Better Hearing Ctr",
    "wof:placetype":"venue"
},
  "geometry": {"coordinates":[-121.95703125,49.1695594788],"type":"Point"}
}