{
  "type": "Feature",
  "properties": {
    "addr:full":"1620 Rossi St Oldcastle ON N0R 1L0",
    "addr:housenumber":"1620",
    "addr:postcode":"n0r 1l0",
    "addr:street":"Rossi St",
    "iso:country":"CA",
    "sg:address":"1620 Rossi St",
    "sg:city":"Oldcastle",
    "sg:classifiers":[
        {
            "category":"Building & Trades",
            "subcategory":"Construction",
            "type":"Services"
        }
    ],
    "sg:phone":"+1 519 737 7131",
    "sg:postcode":"N0R 1L0",
    "sg:province":"ON",
    "sg:tags":[
        "equipment",
        "kitchen",
        "maker",
        "cabinet"
    ],
    "wof:name":"Kitchen Korner",
    "wof:placetype":"venue"
},
  "geometry": {"coordinates":[-82.975098,42.23711],"type":"Point"}
}