{
  "type": "Feature",
  "properties": {
    "addr:full":"50 Herbert St E Swift Current SK S9H 1M2",
    "addr:housenumber":"50",
    "addr:postcode":"s9h 1m2",
    "addr:street":"Herbert St E",
    "iso:country":"CA",
    "sg:address":"50 Herbert St E",
    "sg:city":"Swift Current",
    "sg:classifiers":[
        {
            "category":"Professional",
            "subcategory":"Accounting & Tax Preparation",
            "type":"Services"
        }
    ],
    "sg:phone":"+1 306 773 9614",
    "sg:postcode":"S9H 1M2",
    "sg:province":"SK",
    "sg:tags":[
        "return",
        "filing"
    ],
    "wof:name":"H & R Block Canada Inc",
    "wof:placetype":"venue"
},
  "geometry": {"coordinates":[-107.794685,50.286709],"type":"Point"}
}