{
  "type": "Feature",
  "properties": {
    "addr:full":"Etobicoke ON M9W 6H8",
    "addr:postcode":"m9w 6h8",
    "iso:country":"CA",
    "sg:city":"Etobicoke",
    "sg:classifiers":[
        {
            "category":"Professional",
            "subcategory":"Advertising",
            "type":"Services"
        }
    ],
    "sg:phone":"+1 416 679 9600",
    "sg:postcode":"M9W 6H8",
    "sg:province":"ON",
    "sg:tags":[
        "counselor"
    ],
    "wof:name":"Impact Media Group",
    "wof:placetype":"venue"
},
  "geometry": {"coordinates":[-79.5875244141,43.6893577576],"type":"Point"}
}