{
  "type": "Feature",
  "properties": {
    "addr:full":"6020 Rue Saint-Jacques Montreal QC H4A 2E9",
    "addr:housenumber":"6020",
    "addr:postcode":"h4a 2e9",
    "addr:street":"Rue Saint-Jacques",
    "iso:country":"CA",
    "sg:address":"6020 Rue Saint-Jacques",
    "sg:city":"Montreal",
    "sg:classifiers":[
        {
            "category":"Home & Garden",
            "subcategory":"Building Materials",
            "type":"Retail Goods"
        }
    ],
    "sg:phone":"+1 514 369 6556",
    "sg:postcode":"H4A 2E9",
    "sg:province":"QC",
    "sg:tags":[
        "paint"
    ],
    "wof:name":"Peinture Micca Inc",
    "wof:placetype":"venue"
},
  "geometry": {"coordinates":[-73.6158218384,45.4642601013],"type":"Point"}
}