{
  "type": "Feature",
  "properties": {
    "addr:full":"136 Ch Des Raymond Riviere-Du-Loup QC G5R 5X6",
    "addr:housenumber":"136",
    "addr:postcode":"g5r 5x6",
    "addr:street":"Ch Des Raymond Riviere-Du-Loup",
    "iso:country":"CA",
    "sg:address":"136 Ch Des Raymond",
    "sg:city":"Riviere-Du-Loup",
    "sg:classifiers":[
        {
            "category":"Autos & Motor Vehicles",
            "subcategory":"Automobile Sales",
            "type":"Retail Goods"
        }
    ],
    "sg:phone":"+1 418 867 1420",
    "sg:postcode":"G5R 5X6",
    "sg:province":"QC",
    "sg:tags":[
        "car",
        "dealer"
    ],
    "wof:name":"Prima Automobiles Inc",
    "wof:placetype":"venue"
},
  "geometry": {"coordinates":[-69.502403,47.835594],"type":"Point"}
}