{
  "type": "Feature",
  "properties": {
    "addr:full":"32717 Chilcotin Dr Abbotsford BC V2T 5S5",
    "addr:housenumber":"32717",
    "addr:postcode":"v2t 5s5",
    "addr:street":"Chilcotin Dr",
    "iso:country":"CA",
    "sg:address":"32717 Chilcotin Dr",
    "sg:city":"Abbotsford",
    "sg:classifiers":[
        {
            "category":"Education",
            "subcategory":"School",
            "type":"Public Place"
        }
    ],
    "sg:phone":"+1 604 864 8572",
    "sg:postcode":"V2T 5S5",
    "sg:province":"BC",
    "wof:name":"Dr Roberta Bondar Elementary",
    "wof:placetype":"venue"
},
  "geometry": {"coordinates":[-122.318992615,49.0713539124],"type":"Point"}
}