{
  "type": "Feature",
  "properties": {
    "iso:country":"CA",
    "sg:address":"25 Atkins Ave",
    "sg:city":"Toronto",
    "sg:classifiers":[
        {
            "category":"Retail",
            "subcategory":"Auto Repair",
            "type":"Services"
        }
    ],
    "sg:phone":"+1 416 535 7297",
    "sg:postcode":"M6K 1V9",
    "sg:province":"ON",
    "sg:tags":[
        "wrecker"
    ],
    "wof:name":"Gta Autow",
    "wof:placetype":"venue"
},
  "geometry": {"coordinates":[-79.4345397949,43.6505775452],"type":"Point"}
}