{
  "type": "Feature",
  "properties": {
    "addr:full":"533 1/2 Simcoe St London ON N6B 1K3",
    "addr:housenumber":"533 1 / 2",
    "addr:postcode":"n6b 1k3",
    "addr:street":"Simcoe St",
    "iso:country":"CA",
    "sg:address":"533 1/2 Simcoe St",
    "sg:city":"London",
    "sg:classifiers":[
        {
            "category":"Building & Trades",
            "subcategory":"Cleaning & Sanitation",
            "type":"Services"
        }
    ],
    "sg:phone":"+1 519 870 1093",
    "sg:postcode":"N6B 1K3",
    "sg:province":"ON",
    "sg:tags":[
        "janitor"
    ],
    "wof:name":"Georgio Building Maintenance",
    "wof:placetype":"venue"
},
  "geometry": {"coordinates":[-81.232292,42.981579],"type":"Point"}
}