{
  "type": "Feature",
  "properties": {
    "addr:full":"1364 Rue Principale Saint-Come-Liniere QC G0M 1J0",
    "addr:housenumber":"1364",
    "addr:postcode":"g0m 1j0",
    "addr:street":"Rue Principale",
    "iso:country":"CA",
    "sg:address":"1364 Rue Principale",
    "sg:city":"Saint-Come-Liniere",
    "sg:classifiers":[
        {
            "category":"Health Services",
            "subcategory":"Doctor",
            "type":"Services"
        }
    ],
    "sg:phone":"+1 418 685 3311",
    "sg:postcode":"G0M 1J0",
    "sg:province":"QC",
    "sg:tags":[
        "physician",
        "surgeon"
    ],
    "wof:name":"Clinique Medicale St Come",
    "wof:placetype":"venue"
},
  "geometry": {"coordinates":[-70.521935,46.058182],"type":"Point"}
}