{
  "type": "Feature",
  "properties": {
    "addr:full":"1025 Bloor St W Toronto ON M6H 1M1",
    "addr:housenumber":"1025",
    "addr:postcode":"m6h 1m1",
    "addr:street":"Bloor St W",
    "iso:country":"CA",
    "sg:address":"1025 Bloor St W",
    "sg:city":"Toronto",
    "sg:classifiers":[
        {
            "category":"Shopping",
            "subcategory":"Catalog Store",
            "type":"Retail Goods"
        }
    ],
    "sg:phone":"+1 416 537 4271",
    "sg:postcode":"M6H 1M1",
    "sg:province":"ON",
    "sg:tags":[
        "mail",
        "order",
        "internet"
    ],
    "wof:name":"Sears Canada Inc",
    "wof:placetype":"venue"
},
  "geometry": {"coordinates":[-79.4309005737,43.6606750488],"type":"Point"}
}