{
  "type": "Feature",
  "properties": {
    "addr:full":"5280 Creekbank Rd Mississauga ON L4W 1N4",
    "addr:housenumber":"5280",
    "addr:postcode":"l4w 1n4",
    "addr:street":"Creekbank Rd",
    "iso:country":"CA",
    "sg:address":"5280 Creekbank Rd",
    "sg:city":"Mississauga",
    "sg:classifiers":[
        {
            "category":"Retail",
            "subcategory":"Auto Repair",
            "type":"Services"
        }
    ],
    "sg:phone":"+1 905 624 7414",
    "sg:postcode":"L4W 1N4",
    "sg:province":"ON",
    "sg:tags":[
        "automobile",
        "customizing"
    ],
    "wof:name":"Asc Canada Inc",
    "wof:placetype":"venue"
},
  "geometry": {"coordinates":[-79.6208953857,43.6482620239],"type":"Point"}
}