{
  "type": "Feature",
  "properties": {
    "addr:full":"245 Commercial St Milton ON L9T 2J3",
    "addr:housenumber":"245",
    "addr:postcode":"l9t 2j3",
    "addr:street":"Commercial St",
    "iso:country":"CA",
    "sg:address":"245 Commercial St",
    "sg:city":"Milton",
    "sg:classifiers":[
        {
            "category":"Education",
            "subcategory":"Special Training",
            "type":"Public Place"
        }
    ],
    "sg:phone":"+1 905 878 4135",
    "sg:postcode":"L9T 2J3",
    "sg:province":"ON",
    "sg:tags":[
        "instruction",
        "driving"
    ],
    "wof:name":"Wheels Driver Training",
    "wof:placetype":"venue"
},
  "geometry": {"coordinates":[-79.874756,43.510281],"type":"Point"}
}