{
  "type": "Feature",
  "properties": {
    "addr:full":"740 Tsse Varin Sainte-Agathe-Des-Monts QC J8C 3M9",
    "addr:housenumber":"740",
    "addr:postcode":"j8c 3m9",
    "addr:street":"Tsse Varin",
    "iso:country":"CA",
    "sg:address":"740 Tsse Varin",
    "sg:city":"Sainte-Agathe-Des-Monts",
    "sg:classifiers":[
        {
            "category":"Personal",
            "subcategory":"Beauty Salon",
            "type":"Services"
        }
    ],
    "sg:phone":"+1 819 326 6161",
    "sg:postcode":"J8C 3M9",
    "sg:province":"QC",
    "wof:name":"Salon Muguette Poulin",
    "wof:placetype":"venue"
},
  "geometry": {"coordinates":[-74.26973700000001,46.046082],"type":"Point"}
}