{
  "type": "Feature",
  "properties": {
    "addr:full":"2 Rte 101 N Notre-Dame-Du-Nord QC J0Z 3B0",
    "addr:housenumber":"2",
    "addr:postcode":"j0z 3b0",
    "addr:street":"Rte 101 N",
    "iso:country":"CA",
    "sg:address":"2 Rte 101 N",
    "sg:city":"Notre-Dame-Du-Nord",
    "sg:classifiers":[
        {
            "category":"Taxi",
            "type":"Transportation"
        }
    ],
    "sg:phone":"+1 819 723 2283",
    "sg:postcode":"J0Z 3B0",
    "sg:province":"QC",
    "sg:tags":[
        "taxicab"
    ],
    "wof:name":"Taxi Royal Du Nord Inc",
    "wof:placetype":"venue"
},
  "geometry": {"coordinates":[-79.43821,47.541012],"type":"Point"}
}