{
  "type": "Feature",
  "properties": {
    "iso:country":"CA",
    "sg:address":"Rte Du Quai",
    "sg:city":"Paspebiac",
    "sg:classifiers":[
        {
            "category":"Wholesale",
            "subcategory":"Seafood",
            "type":"Manufacturing & Wholesale Goods"
        }
    ],
    "sg:phone":"+1 418 752 6700",
    "sg:postcode":"G0C 2K0",
    "sg:province":"QC",
    "wof:name":"Unipeche Mdm Ltee",
    "wof:placetype":"venue"
},
  "geometry": {"coordinates":[-65.2492675781,48.028968811],"type":"Point"}
}