{
  "type": "Feature",
  "properties": {
    "addr:full":"Mississauga ON L5C 4G4",
    "addr:postcode":"l5c 4g4",
    "iso:country":"CA",
    "sg:city":"Mississauga",
    "sg:classifiers":[
        {
            "category":"Wholesale",
            "subcategory":"Electrical",
            "type":"Manufacturing & Wholesale Goods"
        }
    ],
    "sg:phone":"+1 905 896 3344",
    "sg:postcode":"L5C 4G4",
    "sg:province":"ON",
    "sg:tags":[
        "control",
        "security",
        "door"
    ],
    "wof:name":"Beam & Alarm Superstore",
    "wof:placetype":"venue"
},
  "geometry": {"coordinates":[-79.66156768800001,43.5703926086],"type":"Point"}
}