{
  "type": "Feature",
  "properties": {
    "addr:full":"30 King St #205 Trenton ON K8V 6B1",
    "addr:housenumber":"30",
    "addr:postcode":"k8v 6b1",
    "addr:street":"King St # 205",
    "iso:country":"CA",
    "sg:address":"30 King St #205",
    "sg:city":"Trenton",
    "sg:classifiers":[
        {
            "category":"Health Services",
            "subcategory":"Health Practitioner",
            "type":"Services"
        }
    ],
    "sg:phone":"+1 613 392 7823",
    "sg:postcode":"K8V 6B1",
    "sg:province":"ON",
    "sg:tags":[
        "physiotherapist"
    ],
    "wof:name":"Physio Centre",
    "wof:placetype":"venue"
},
  "geometry": {"coordinates":[-77.57809399999999,44.101315],"type":"Point"}
}