{
  "type": "Feature",
  "properties": {
    "addr:full":"15 Harwood Ave S Ajax ON L1S 2B9",
    "addr:housenumber":"15",
    "addr:postcode":"l1s 2b9",
    "addr:street":"Harwood Ave S",
    "iso:country":"CA",
    "sg:address":"15 Harwood Ave S",
    "sg:city":"Ajax",
    "sg:classifiers":[
        {
            "category":"Professional",
            "subcategory":"Accounting & Tax Preparation",
            "type":"Services"
        }
    ],
    "sg:phone":"+1 905 686 1395",
    "sg:postcode":"L1S 2B9",
    "sg:province":"ON",
    "sg:tags":[
        "return",
        "filing"
    ],
    "wof:name":"H & R Block Canada Inc",
    "wof:placetype":"venue"
},
  "geometry": {"coordinates":[-79.024979,43.859612],"type":"Point"}
}