{
  "type": "Feature",
  "properties": {
    "addr:full":"4816 53 Ave Camrose AB T4V 0Y2",
    "addr:housenumber":"4816",
    "addr:postcode":"t4v 0y2",
    "addr:street":"53 Ave",
    "iso:country":"CA",
    "sg:address":"4816 53 Ave",
    "sg:city":"Camrose",
    "sg:classifiers":[
        {
            "category":"Education",
            "subcategory":"School",
            "type":"Public Place"
        }
    ],
    "sg:phone":"+1 780 672 2177",
    "sg:postcode":"T4V 0Y2",
    "sg:province":"AB",
    "wof:name":"St Patrick School",
    "wof:placetype":"venue"
},
  "geometry": {"coordinates":[-112.822357178,53.0272636414],"type":"Point"}
}