{
  "type": "Feature",
  "properties": {
    "addr:full":"65 Ormond St N Thorold ON L2V 1Z3",
    "addr:housenumber":"65",
    "addr:postcode":"l2v 1z3",
    "addr:street":"Ormond St N",
    "iso:country":"CA",
    "sg:address":"65 Ormond St N",
    "sg:city":"Thorold",
    "sg:classifiers":[
        {
            "category":"Home & Garden",
            "subcategory":"Building Materials",
            "type":"Retail Goods"
        }
    ],
    "sg:phone":"+1 905 680 1212",
    "sg:postcode":"L2V 1Z3",
    "sg:province":"ON",
    "sg:tags":[
        "insulation",
        "heat",
        "contractor"
    ],
    "wof:name":"Losier Insulation Ltd",
    "wof:placetype":"venue"
},
  "geometry": {"coordinates":[-79.199448,43.130169],"type":"Point"}
}