{
  "type": "Feature",
  "properties": {
    "addr:full":"256 East Main St Welland ON L3B 3W9",
    "addr:housenumber":"256",
    "addr:postcode":"l3b 3w9",
    "addr:street":"East Main St",
    "iso:country":"CA",
    "sg:address":"256 East Main St",
    "sg:city":"Welland",
    "sg:classifiers":[
        {
            "category":"Restaurant",
            "type":"Food & Drink"
        }
    ],
    "sg:phone":"+1 905 735 3716",
    "sg:postcode":"L3B 3W9",
    "sg:province":"ON",
    "wof:name":"Volcano Pizzeria",
    "wof:placetype":"venue"
},
  "geometry": {"coordinates":[-79.24282073969999,42.9932632446],"type":"Point"}
}