{
  "type": "Feature",
  "properties": {
    "addr:full":"Brampton ON L6Y 1M3",
    "addr:postcode":"l6y 1m3",
    "iso:country":"CA",
    "sg:city":"Brampton",
    "sg:classifiers":[
        {
            "category":"Health Services",
            "subcategory":"Doctor",
            "type":"Services"
        }
    ],
    "sg:phone":"+1 905 453 6900",
    "sg:postcode":"L6Y 1M3",
    "sg:province":"ON",
    "sg:tags":[
        "dentist"
    ],
    "wof:name":"Allum, Theresa DDS",
    "wof:placetype":"venue"
},
  "geometry": {"coordinates":[-79.76197052000001,43.6837692261],"type":"Point"}
}