{
  "type": "Feature",
  "properties": {
    "iso:country":"CA",
    "sg:address":"1186 Stone Church Rd E",
    "sg:city":"Hamilton",
    "sg:classifiers":[
        {
            "category":"Education",
            "subcategory":"Special Training",
            "type":"Public Place"
        }
    ],
    "sg:phone":"+1 905 318 6923",
    "sg:postcode":"L8W 2C7",
    "sg:province":"ON",
    "sg:tags":[
        "instruction",
        "music"
    ],
    "wof:name":"Hamilton School of Music",
    "wof:placetype":"venue"
},
  "geometry": {"coordinates":[-79.836937,43.198212],"type":"Point"}
}