{
  "type": "Feature",
  "properties": {
    "addr:full":"5000 Rue Eadie Montreal QC H4E 4P2",
    "addr:housenumber":"5000",
    "addr:postcode":"h4e 4p2",
    "addr:street":"Rue Eadie",
    "iso:country":"CA",
    "sg:address":"5000 Rue Eadie",
    "sg:city":"Montreal",
    "sg:classifiers":[
        {
            "category":"Wholesale",
            "subcategory":"Stationery",
            "type":"Manufacturing & Wholesale Goods"
        }
    ],
    "sg:phone":"+1 514 762 6069",
    "sg:postcode":"H4E 4P2",
    "sg:province":"QC",
    "sg:tags":[
        "school",
        "supply"
    ],
    "wof:name":"Lamarche Importation",
    "wof:placetype":"venue"
},
  "geometry": {"coordinates":[-73.5897064209,45.4665527344],"type":"Point"}
}