{
  "type": "Feature",
  "properties": {
    "iso:country":"CA",
    "sg:address":"64 Mcnaughton Ave",
    "sg:city":"Wallaceburg",
    "sg:classifiers":[
        {
            "category":"Food & Beverages",
            "subcategory":"Liquor & Beverages",
            "type":"Retail Goods"
        }
    ],
    "sg:phone":"+1 519 627 2141",
    "sg:postcode":"N8A 1R9",
    "sg:province":"ON",
    "sg:tags":[
        "beer",
        "ale"
    ],
    "wof:name":"Brewers Retail Store",
    "wof:placetype":"venue"
},
  "geometry": {"coordinates":[-82.383316,42.58559],"type":"Point"}
}