{
  "type": "Feature",
  "properties": {
    "addr:full":"644 Berford St Wiarton ON N0H 2T0",
    "addr:housenumber":"644",
    "addr:postcode":"n0h 2t0",
    "addr:street":"Berford St",
    "iso:country":"CA",
    "sg:address":"644 Berford St",
    "sg:city":"Wiarton",
    "sg:classifiers":[
        {
            "category":"Insurance",
            "subcategory":"Insurance Agent",
            "type":"Services"
        }
    ],
    "sg:phone":"+1 519 534 1930",
    "sg:postcode":"N0H 2T0",
    "sg:province":"ON",
    "wof:name":"Wiarton Insurance Brokers Ltd",
    "wof:placetype":"venue"
},
  "geometry": {"coordinates":[-81.14115905760001,44.7444076538],"type":"Point"}
}