{
  "type": "Feature",
  "properties": {
    "addr:full":"5615 48th St Elk Point AB T0A 1A0",
    "addr:housenumber":"5615",
    "addr:postcode":"t0a 1a0",
    "addr:street":"48Th St",
    "iso:country":"CA",
    "sg:address":"5615 48th St",
    "sg:city":"Elk Point",
    "sg:classifiers":[
        {
            "category":"Education",
            "subcategory":"Library",
            "type":"Public Place"
        }
    ],
    "sg:phone":"+1 780 724 2596",
    "sg:postcode":"T0A 1A0",
    "sg:province":"AB",
    "wof:name":"Northern Lights Library System",
    "wof:placetype":"venue"
},
  "geometry": {"coordinates":[-110.89663696300001,53.9040794373],"type":"Point"}
}