{
  "type": "Feature",
  "properties": {
    "addr:full":"North York ON M2H 1J8",
    "addr:postcode":"m2h 1j8",
    "iso:country":"CA",
    "sg:city":"North York",
    "sg:classifiers":[
        {
            "category":"Shopping",
            "subcategory":"Clothing, Apparel, & Fashions",
            "type":"Retail Goods"
        }
    ],
    "sg:phone":"+1 416 491 4766",
    "sg:postcode":"M2H 1J8",
    "sg:province":"ON",
    "sg:tags":[
        "swimwear",
        "accessory"
    ],
    "wof:name":"Beachwear Unlimited",
    "wof:placetype":"venue"
},
  "geometry": {"coordinates":[-79.37027,43.800323],"type":"Point"}
}