{
  "type": "Feature",
  "properties": {
    "iso:country":"CA",
    "sg:city":"Richmond",
    "sg:classifiers":[
        {
            "category":"Home & Garden",
            "subcategory":"Home Furnishings",
            "type":"Retail Goods"
        }
    ],
    "sg:phone":"+1 604 270 3456",
    "sg:postcode":"V6Y 1Z1",
    "sg:province":"BC",
    "sg:tags":[
        "curtain",
        "made",
        "drapery"
    ],
    "wof:name":"Janzen's Draperies",
    "wof:placetype":"venue"
},
  "geometry": {"coordinates":[-123.141304,49.165649],"type":"Point"}
}