{
  "type": "Feature",
  "properties": {
    "iso:country":"CA",
    "sg:address":"701 Rue Duhamel",
    "sg:city":"Longueuil",
    "sg:classifiers":[
        {
            "category":"Organizations",
            "subcategory":"Religious Organization",
            "type":"Services"
        }
    ],
    "sg:phone":"+1 450 679 2600",
    "sg:postcode":"J4L 4M2",
    "sg:province":"QC",
    "sg:tags":[
        "church"
    ],
    "wof:name":"St-Robert Eglise",
    "wof:placetype":"venue"
},
  "geometry": {"coordinates":[-73.461617,45.511543],"type":"Point"}
}