{
  "type": "Feature",
  "properties": {
    "addr:full":"Vancouver BC V5S 1M1",
    "addr:postcode":"v5s 1m1",
    "iso:country":"CA",
    "sg:city":"Vancouver",
    "sg:classifiers":[
        {
            "category":"Retail",
            "subcategory":"Repair Shop",
            "type":"Services"
        }
    ],
    "sg:phone":"+1 604 432 6556",
    "sg:postcode":"V5S 1M1",
    "sg:province":"BC",
    "sg:tags":[
        "refinishing",
        "furniture"
    ],
    "wof:name":"Acacia",
    "wof:placetype":"venue"
},
  "geometry": {"coordinates":[-123.030525208,49.2245445251],"type":"Point"}
}