{
  "type": "Feature",
  "properties": {
    "addr:full":"4571 Joyce St Vancouver BC V5R 4E7",
    "addr:housenumber":"4571",
    "addr:postcode":"v5r 4e7",
    "addr:street":"Joyce St",
    "iso:country":"CA",
    "sg:address":"4571 Joyce St",
    "sg:city":"Vancouver",
    "sg:classifiers":[
        {
            "category":"Building & Trades",
            "subcategory":"Plumbing",
            "type":"Services"
        }
    ],
    "sg:phone":"+1 604 682 8549",
    "sg:postcode":"V5R 4E7",
    "sg:province":"BC",
    "sg:tags":[
        "contractor"
    ],
    "wof:name":"Prowest Mechanical Ltd",
    "wof:placetype":"venue"
},
  "geometry": {"coordinates":[-123.02684000000001,49.243797],"type":"Point"}
}