{
  "type": "Feature",
  "properties": {
    "addr:full":"4223 Rue Ontario E Montreal QC H1V 1K2",
    "addr:housenumber":"4223",
    "addr:postcode":"h1v 1k2",
    "addr:street":"Rue Ontario E",
    "iso:country":"CA",
    "sg:address":"4223 Rue Ontario E",
    "sg:city":"Montreal",
    "sg:classifiers":[
        {
            "category":"Restaurant",
            "type":"Food & Drink"
        }
    ],
    "sg:phone":"+1 514 255 6558",
    "sg:postcode":"H1V 1K2",
    "sg:province":"QC",
    "wof:name":"New Casa DE LA Pizza Inc",
    "wof:placetype":"venue"
},
  "geometry": {"coordinates":[-73.540657,45.551529],"type":"Point"}
}