{
  "type": "Feature",
  "properties": {
    "addr:full":"2116 Hwy 138 Moose Creek ON K0C 1W0",
    "addr:housenumber":"2116",
    "addr:postcode":"k0c 1w0",
    "addr:street":"Hwy 138 Moose",
    "iso:country":"CA",
    "sg:address":"2116 Hwy 138",
    "sg:city":"Moose Creek",
    "sg:classifiers":[
        {
            "category":"Autos & Motor Vehicles",
            "subcategory":"Motorcycle Sales",
            "type":"Retail Goods"
        }
    ],
    "sg:phone":"+1 613 538 2887",
    "sg:postcode":"K0C 1W0",
    "sg:province":"ON",
    "wof:name":"Ron's Service Shop",
    "wof:placetype":"venue"
},
  "geometry": {"coordinates":[-74.944480896,45.2727127075],"type":"Point"}
}