{
  "type": "Feature",
  "properties": {
    "addr:full":"196 Rue Principale Saint-Cyprien QC G0L 2P0",
    "addr:housenumber":"196",
    "addr:postcode":"g0l 2p0",
    "addr:street":"Rue Principale",
    "iso:country":"CA",
    "sg:address":"196 Rue Principale",
    "sg:city":"Saint-Cyprien",
    "sg:classifiers":[
        {
            "category":"Travel",
            "subcategory":"Hotels & Motels",
            "type":"Entertainment"
        }
    ],
    "sg:phone":"+1 418 963 3527",
    "sg:postcode":"G0L 2P0",
    "sg:province":"QC",
    "wof:name":"Restaurant Bar Le Mirage Enr",
    "wof:placetype":"venue"
},
  "geometry": {"coordinates":[-69.016441,47.894466],"type":"Point"}
}