{
  "type": "Feature",
  "properties": {
    "addr:full":"1400 Boul Rene-Levesque E Montreal QC H2L 2M2",
    "addr:housenumber":"1400",
    "addr:postcode":"h2l 2m2",
    "addr:street":"Boul Rene-Levesque E",
    "iso:country":"CA",
    "sg:address":"1400 Boul Rene-Levesque E",
    "sg:city":"Montreal",
    "sg:classifiers":[
        {
            "category":"Professional",
            "subcategory":"Management & Consulting",
            "type":"Services"
        }
    ],
    "sg:phone":"+1 514 597 4283",
    "sg:postcode":"H2L 2M2",
    "sg:province":"QC",
    "sg:tags":[
        "marketing",
        "program"
    ],
    "wof:name":"Societe Radio-Canada",
    "wof:placetype":"venue"
},
  "geometry": {"coordinates":[-73.5521469116,45.5186424255],"type":"Point"}
}