{
  "type": "Feature",
  "properties": {
    "addr:full":"658 Danforth Ave Toronto ON M4J 5B9",
    "addr:housenumber":"658",
    "addr:postcode":"m4j 5b9",
    "addr:street":"Danforth Ave",
    "iso:country":"CA",
    "sg:address":"658 Danforth Ave",
    "sg:city":"Toronto",
    "sg:classifiers":[
        {
            "category":"Wholesale",
            "subcategory":"Durable Goods & Equipment",
            "type":"Manufacturing & Wholesale Goods"
        }
    ],
    "sg:phone":"+1 416 463 9822",
    "sg:postcode":"M4J 5B9",
    "sg:province":"ON",
    "sg:tags":[
        "importer"
    ],
    "wof:name":"Test Rite Products",
    "wof:placetype":"venue"
},
  "geometry": {"coordinates":[-79.34453600000001,43.679077],"type":"Point"}
}