{
  "type": "Feature",
  "properties": {
    "addr:full":"890 Boul Cremazie O Montreal QC H3N 1A4",
    "addr:housenumber":"890",
    "addr:postcode":"h3n 1a4",
    "addr:street":"Boul Cremazie O",
    "iso:country":"CA",
    "sg:address":"890 Boul Cremazie O",
    "sg:city":"Montreal",
    "sg:classifiers":[
        {
            "category":"Building & Trades",
            "subcategory":"Electrical",
            "type":"Services"
        }
    ],
    "sg:phone":"+1 514 276 8551",
    "sg:postcode":"H3N 1A4",
    "sg:province":"QC",
    "sg:tags":[
        "electric",
        "contractor"
    ],
    "wof:name":"Laurentien Electrique Inc",
    "wof:placetype":"venue"
},
  "geometry": {"coordinates":[-73.63331604,45.5494270325],"type":"Point"}
}