{
  "type": "Feature",
  "properties": {
    "addr:full":"Toronto ON M5G 2L3",
    "addr:postcode":"m5g 2l3",
    "iso:country":"CA",
    "sg:city":"Toronto",
    "sg:classifiers":[
        {
            "category":"Wholesale",
            "subcategory":"Durable Goods & Equipment",
            "type":"Manufacturing & Wholesale Goods"
        }
    ],
    "sg:phone":"+1 416 340 8818",
    "sg:postcode":"M5G 2L3",
    "sg:province":"ON",
    "sg:tags":[
        "laboratory",
        "dental",
        "supply"
    ],
    "wof:name":"Innova Life Sciences Corp",
    "wof:placetype":"venue"
},
  "geometry": {"coordinates":[-79.3884735107,43.6559486389],"type":"Point"}
}