{
  "type": "Feature",
  "properties": {
    "iso:country":"CA",
    "sg:address":"526 Guelph Line",
    "sg:city":"Burlington",
    "sg:classifiers":[
        {
            "category":"Health Services",
            "subcategory":"Doctor",
            "type":"Services"
        }
    ],
    "sg:phone":"+1 905 633 7767",
    "sg:postcode":"L7R 3M4",
    "sg:province":"ON",
    "sg:tags":[
        "physician",
        "surgeon",
        "counselor",
        "marriage",
        "family"
    ],
    "wof:name":"Nicholson Medical Group",
    "wof:placetype":"venue"
},
  "geometry": {"coordinates":[-79.7876968384,43.3398628235],"type":"Point"}
}