{
  "type": "Feature",
  "properties": {
    "iso:country":"CA",
    "sg:address":"305 Dewdney Ave",
    "sg:city":"Regina",
    "sg:classifiers":[
        {
            "category":"Manufacturing",
            "subcategory":"Tools & Machinery",
            "type":"Manufacturing & Wholesale Goods"
        }
    ],
    "sg:phone":"+1 306 352 4505",
    "sg:postcode":"S4N 0E7",
    "sg:province":"SK",
    "sg:tags":[
        "transmission",
        "power",
        "electric",
        "motor"
    ],
    "wof:name":"Stockdale's Electric Motor",
    "wof:placetype":"venue"
},
  "geometry": {"coordinates":[-104.585281372,50.4550476074],"type":"Point"}
}