{
  "type": "Feature",
  "properties": {
    "addr:full":"20415 43A Ave Langley BC V3A 3C7",
    "addr:housenumber":"20415",
    "addr:postcode":"v3a 3c7",
    "addr:street":"43A Ave",
    "iso:country":"CA",
    "sg:address":"20415 43A Ave",
    "sg:city":"Langley",
    "sg:classifiers":[
        {
            "category":"Professional",
            "subcategory":"Accounting & Tax Preparation",
            "type":"Services"
        }
    ],
    "sg:phone":"+1 604 607 7287",
    "sg:postcode":"V3A 3C7",
    "sg:province":"BC",
    "sg:tags":[
        "accountant"
    ],
    "wof:name":"First Syndicate Management Svc",
    "wof:placetype":"venue"
},
  "geometry": {"coordinates":[-122.65657043500001,49.1041221619],"type":"Point"}
}