{
  "type": "Feature",
  "properties": {
    "addr:full":"London ON N5Z 3M5",
    "addr:postcode":"n5z 3m5",
    "iso:country":"CA",
    "sg:city":"London",
    "sg:classifiers":[
        {
            "category":"Manufacturing",
            "subcategory":"Metals",
            "type":"Manufacturing & Wholesale Goods"
        }
    ],
    "sg:phone":"+1 519 685 0073",
    "sg:postcode":"N5Z 3M5",
    "sg:province":"ON",
    "sg:tags":[
        "painter"
    ],
    "wof:name":"Boone Painting Inc",
    "wof:placetype":"venue"
},
  "geometry": {"coordinates":[-81.21435546879999,42.9614906311],"type":"Point"}
}