{
  "type": "Feature",
  "properties": {
    "addr:full":"1742 Hoxton St RR 6 Pickering ON L1Y 1A3",
    "addr:housenumber":"1742",
    "addr:postcode":"l1y 1a3",
    "addr:street":"Hoxton St Rr 6",
    "iso:country":"CA",
    "sg:address":"1742 Hoxton St RR 6",
    "sg:city":"Pickering",
    "sg:classifiers":[
        {
            "category":"Manufacturing",
            "subcategory":"Metals",
            "type":"Manufacturing & Wholesale Goods"
        }
    ],
    "sg:phone":"+1 905 649 2661",
    "sg:postcode":"L1Y 1A3",
    "sg:province":"ON",
    "sg:tags":[
        "fabricator",
        "aluminum",
        "welding"
    ],
    "wof:name":"Blue Spring Welding",
    "wof:placetype":"venue"
},
  "geometry": {"coordinates":[-79.082306,43.83765],"type":"Point"}
}