{
  "type": "Feature",
  "properties": {
    "iso:country":"CA",
    "sg:address":"247 Grey St",
    "sg:city":"London",
    "sg:classifiers":[
        {
            "category":"Real Estate",
            "subcategory":"Developer",
            "type":"Services"
        }
    ],
    "sg:phone":"+1 519 850 3505",
    "sg:postcode":"N6B 1G4",
    "sg:province":"ON",
    "sg:tags":[
        "company",
        "land"
    ],
    "wof:name":"Zebro Developments",
    "wof:placetype":"venue"
},
  "geometry": {"coordinates":[-81.2428894043,42.9773139954],"type":"Point"}
}