{
  "type": "Feature",
  "properties": {
    "addr:full":"6414 Rue Principale Sainte-Croix QC G0S 2H0",
    "addr:housenumber":"6414",
    "addr:postcode":"g0s 2h0",
    "addr:street":"Rue Principale",
    "iso:country":"CA",
    "sg:address":"6414 Rue Principale",
    "sg:city":"Sainte-Croix",
    "sg:classifiers":[
        {
            "category":"Professional",
            "subcategory":"Accounting & Tax Preparation",
            "type":"Services"
        }
    ],
    "sg:phone":"+1 418 926 2188",
    "sg:postcode":"G0S 2H0",
    "sg:province":"QC",
    "sg:tags":[
        "accountant"
    ],
    "wof:name":"Dessureault Lemire Desaulniers",
    "wof:placetype":"venue"
},
  "geometry": {"coordinates":[-71.742783,46.623421],"type":"Point"}
}