{
  "type": "Feature",
  "properties": {
    "iso:country":"CA",
    "sg:address":"30 Regent St",
    "sg:city":"North Sydney",
    "sg:classifiers":[
        {
            "category":"Education",
            "subcategory":"School",
            "type":"Public Place"
        }
    ],
    "sg:phone":"+1 902 794 2492",
    "sg:postcode":"B2A 2E6",
    "sg:province":"NS",
    "wof:name":"Thompson Jr High School",
    "wof:placetype":"venue"
},
  "geometry": {"coordinates":[-60.258575,46.204422],"type":"Point"}
}