{
  "type": "Feature",
  "properties": {
    "addr:full":"3636 Steeles Ave E # 105C Markham ON L3R 1K9",
    "addr:housenumber":"3636",
    "addr:postcode":"l3r 1k9",
    "addr:street":"Steeles Ave E # 105C",
    "iso:country":"CA",
    "sg:address":"3636 Steeles Ave E # 105C",
    "sg:city":"Markham",
    "sg:classifiers":[
        {
            "category":"Restaurant",
            "type":"Food & Drink"
        }
    ],
    "sg:phone":"+1 905 513 0303",
    "sg:postcode":"L3R 1K9",
    "sg:province":"ON",
    "wof:name":"Noodles Express",
    "wof:placetype":"venue"
},
  "geometry": {"coordinates":[-79.3302230835,43.8184661865],"type":"Point"}
}