{
  "type": "Feature",
  "properties": {
    "iso:country":"CA",
    "sg:address":"74 Broadway Ave N",
    "sg:city":"Williams Lake",
    "sg:classifiers":[
        {
            "category":"Shopping",
            "type":"Retail Goods"
        }
    ],
    "sg:phone":"+1 250 392 4818",
    "sg:postcode":"V2G 1C1",
    "sg:province":"BC",
    "sg:tags":[
        "spa",
        "hot",
        "tub"
    ],
    "wof:name":"New Waves Pool & Spa",
    "wof:placetype":"venue"
},
  "geometry": {"coordinates":[-122.12940979,52.1308708191],"type":"Point"}
}