{
  "type": "Feature",
  "properties": {
    "addr:full":"122 Locke St S Hamilton ON L8P 4A8",
    "addr:housenumber":"122",
    "addr:postcode":"l8p 4a8",
    "addr:street":"Locke St S",
    "iso:country":"CA",
    "sg:address":"122 Locke St S",
    "sg:city":"Hamilton",
    "sg:classifiers":[
        {
            "category":"Shopping",
            "subcategory":"Bicycles & Sporting Goods",
            "type":"Retail Goods"
        }
    ],
    "sg:phone":"+1 905 522 1131",
    "sg:postcode":"L8P 4A8",
    "sg:province":"ON",
    "sg:tags":[
        "gun",
        "gunsmith"
    ],
    "wof:name":"Al Simmons Gun Shop",
    "wof:placetype":"venue"
},
  "geometry": {"coordinates":[-79.885109,43.257267],"type":"Point"}
}