{
  "type": "Feature",
  "properties": {
    "iso:country":"CA",
    "sg:address":"11008 151 St NW",
    "sg:city":"Edmonton",
    "sg:classifiers":[
        {
            "category":"Professional",
            "subcategory":"Engineering",
            "type":"Services"
        }
    ],
    "sg:phone":"+1 780 483 0456",
    "sg:postcode":"T5P 1W3",
    "sg:province":"AB",
    "sg:tags":[
        "engineer"
    ],
    "wof:name":"Ace Engineering Ltd",
    "wof:placetype":"venue"
},
  "geometry": {"coordinates":[-113.581375122,53.5562934875],"type":"Point"}
}