{
  "type": "Feature",
  "properties": {
    "iso:country":"CA",
    "sg:city":"Smeaton",
    "sg:classifiers":[
        {
            "category":"Wholesale",
            "subcategory":"Construction Materials",
            "type":"Manufacturing & Wholesale Goods"
        }
    ],
    "sg:phone":"+1 306 426 2305",
    "sg:postcode":"S0J 2J0",
    "sg:province":"SK",
    "sg:tags":[
        "fence"
    ],
    "wof:name":"Smeaton Fence Supplies Ltd",
    "wof:placetype":"venue"
},
  "geometry": {"coordinates":[-104.806282044,53.4919166565],"type":"Point"}
}