{
  "type": "Feature",
  "properties": {
    "addr:full":"8802 Franklin Ave Fort Mcmurray AB T9H 2J7",
    "addr:housenumber":"8802",
    "addr:postcode":"t9h 2j7",
    "addr:street":"Franklin Ave",
    "iso:country":"CA",
    "sg:address":"8802 Franklin Ave",
    "sg:city":"Fort Mcmurray",
    "sg:classifiers":[
        {
            "category":"Shopping",
            "subcategory":"Clothing, Apparel, & Fashions",
            "type":"Retail Goods"
        }
    ],
    "sg:phone":"+1 780 743 4055",
    "sg:postcode":"T9H 2J7",
    "sg:province":"AB",
    "sg:tags":[
        "work"
    ],
    "wof:name":"Protective Clothing Supplies",
    "wof:placetype":"venue"
},
  "geometry": {"coordinates":[-111.366196,56.721935],"type":"Point"}
}