{
  "type": "Feature",
  "properties": {
    "addr:full":"55 Pacific Trans Hwy 331 Oakville MB R0H 0Y0",
    "addr:housenumber":"55",
    "addr:postcode":"r0h 0y0",
    "addr:street":"Pacific Trans Hwy 331",
    "iso:country":"CA",
    "sg:address":"55 Pacific Trans Hwy 331",
    "sg:city":"Oakville",
    "sg:classifiers":[
        {
            "category":"Recreation",
            "type":"Entertainment"
        }
    ],
    "sg:phone":"+1 204 267 2741",
    "sg:postcode":"R0H 0Y0",
    "sg:province":"MB",
    "sg:tags":[
        "hall",
        "auditorium"
    ],
    "wof:name":"Oakville Community Hall",
    "wof:placetype":"venue"
},
  "geometry": {"coordinates":[-98.0039520264,49.9297599792],"type":"Point"}
}