{
  "type": "Feature",
  "properties": {
    "iso:country":"CA",
    "sg:city":"Guelph",
    "sg:classifiers":[
        {
            "category":"Education",
            "subcategory":"Special Training",
            "type":"Public Place"
        }
    ],
    "sg:phone":"+1 519 822 5122",
    "sg:postcode":"N1H 2Z4",
    "sg:province":"ON",
    "sg:tags":[
        "instruction",
        "driving"
    ],
    "wof:name":"Abc College Driving School",
    "wof:placetype":"venue"
},
  "geometry": {"coordinates":[-80.24894,43.544182],"type":"Point"}
}