{
  "type": "Feature",
  "properties": {
    "addr:full":"Richmond Hill ON L4B 3Z4",
    "addr:postcode":"l4b 3z4",
    "iso:country":"CA",
    "sg:city":"Richmond Hill",
    "sg:classifiers":[
        {
            "category":"Restaurant",
            "type":"Food & Drink"
        }
    ],
    "sg:phone":"+1 905 881 2583",
    "sg:postcode":"L4B 3Z4",
    "sg:province":"ON",
    "sg:tags":[
        "out"
    ],
    "wof:name":"Kims Ichiban",
    "wof:placetype":"venue"
},
  "geometry": {"coordinates":[-79.37847137449999,43.8465538025],"type":"Point"}
}