{
  "type": "Feature",
  "properties": {
    "addr:full":"Sidney BC V8L 3H6",
    "addr:postcode":"v8l 3h6",
    "iso:country":"CA",
    "sg:city":"Sidney",
    "sg:classifiers":[
        {
            "category":"Professional",
            "subcategory":"Art Services",
            "type":"Services"
        }
    ],
    "sg:phone":"+1 250 656 5133",
    "sg:postcode":"V8L 3H6",
    "sg:province":"BC",
    "sg:tags":[
        "photographer"
    ],
    "wof:name":"Russ Heinl Group",
    "wof:placetype":"venue"
},
  "geometry": {"coordinates":[-123.411766,48.666245],"type":"Point"}
}