{
  "type": "Feature",
  "properties": {
    "addr:full":"84 Railway Ave W Pierson MB R0M 1S0",
    "addr:housenumber":"84",
    "addr:postcode":"r0m 1s0",
    "addr:street":"Railway Ave W",
    "iso:country":"CA",
    "sg:address":"84 Railway Ave W",
    "sg:city":"Pierson",
    "sg:classifiers":[
        {
            "category":"Real Estate",
            "subcategory":"Real Estate Agent",
            "type":"Services"
        }
    ],
    "sg:phone":"+1 204 634 2521",
    "sg:postcode":"R0M 1S0",
    "sg:province":"MB",
    "wof:name":"Cameron, Murray",
    "wof:placetype":"venue"
},
  "geometry": {"coordinates":[-101.267303,49.178043],"type":"Point"}
}