{
  "type": "Feature",
  "properties": {
    "addr:full":"530 St Clair Ave W Toronto ON M6C 1A2",
    "addr:housenumber":"530",
    "addr:postcode":"m6c 1a2",
    "addr:street":"St Clair Ave W",
    "iso:country":"CA",
    "sg:address":"530 St Clair Ave W",
    "sg:city":"Toronto",
    "sg:classifiers":[
        {
            "category":"Food & Beverages",
            "subcategory":"Groceries & Convenience Stores",
            "type":"Retail Goods"
        }
    ],
    "sg:phone":"+1 416 658 0018",
    "sg:postcode":"M6C 1A2",
    "sg:province":"ON",
    "sg:tags":[
        "grocer"
    ],
    "wof:name":"Jlb Piliponio Store",
    "wof:placetype":"venue"
},
  "geometry": {"coordinates":[-79.41925048829999,43.6831016541],"type":"Point"}
}