{
  "type": "Feature",
  "properties": {
    "addr:full":"1381 Rue Simard Sherbrooke QC J1J 3K5",
    "addr:housenumber":"1381",
    "addr:postcode":"j1j 3k5",
    "addr:street":"Rue Simard",
    "iso:country":"CA",
    "sg:address":"1381 Rue Simard",
    "sg:city":"Sherbrooke",
    "sg:classifiers":[
        {
            "category":"Health Services",
            "subcategory":"Doctor",
            "type":"Services"
        }
    ],
    "sg:phone":"+1 819 569 1293",
    "sg:postcode":"J1J 3K5",
    "sg:province":"QC",
    "sg:tags":[
        "physician",
        "surgeon"
    ],
    "wof:name":"Morin, Luc MD",
    "wof:placetype":"venue"
},
  "geometry": {"coordinates":[-71.9132614136,45.4190483093],"type":"Point"}
}