{
  "type": "Feature",
  "properties": {
    "iso:country":"CA",
    "sg:city":"Saint-Pamphile",
    "sg:classifiers":[
        {
            "category":"Shopping",
            "subcategory":"Jewelry",
            "type":"Retail Goods"
        }
    ],
    "sg:phone":"+1 418 356 3732",
    "sg:postcode":"G0R 3X0",
    "sg:province":"QC",
    "sg:tags":[
        "jeweler"
    ],
    "wof:name":"Maison Du Bijou Enr",
    "wof:placetype":"venue"
},
  "geometry": {"coordinates":[-69.7789382935,46.9608879089],"type":"Point"}
}