{
  "type": "Feature",
  "properties": {
    "addr:full":"8762 Hwy 1 Meteghan Centre NS B0W 2K0",
    "addr:housenumber":"8762",
    "addr:postcode":"b0w 2k0",
    "addr:street":"Hwy 1",
    "iso:country":"CA",
    "sg:address":"8762 Hwy 1",
    "sg:city":"Meteghan Centre",
    "sg:classifiers":[
        {
            "category":"Retail",
            "subcategory":"Auto Repair",
            "type":"Services"
        }
    ],
    "sg:phone":"+1 902 645 2270",
    "sg:postcode":"B0W 2K0",
    "sg:province":"NS",
    "sg:tags":[
        "repairing",
        "automobile"
    ],
    "wof:name":"Delbert Thimot Svc Ctr",
    "wof:placetype":"venue"
},
  "geometry": {"coordinates":[-66.144386,44.198757],"type":"Point"}
}