{
  "type": "Feature",
  "properties": {
    "addr:full":"3000 Christmas Way Coquitlam BC V3C 2M2",
    "addr:housenumber":"3000",
    "addr:postcode":"bc v3c 2m2",
    "addr:street":"Christmas Way",
    "iso:country":"CA",
    "sg:address":"3000 Christmas Way",
    "sg:city":"Coquitlam",
    "sg:classifiers":[
        {
            "category":"Sports & Exercise",
            "subcategory":"Gym",
            "type":"Entertainment"
        }
    ],
    "sg:phone":"+1 604 945 5135",
    "sg:postcode":"V3C 2M2",
    "sg:province":"BC",
    "sg:tags":[
        "club",
        "health",
        "studio",
        "gymnasium"
    ],
    "wof:name":"Just Ladies Fitness",
    "wof:placetype":"venue"
},
  "geometry": {"coordinates":[-122.792892456,49.2719230652],"type":"Point"}
}