{
  "type": "Feature",
  "properties": {
    "iso:country":"CA",
    "sg:address":"3930 Rue Saint-Jacques",
    "sg:city":"Montreal",
    "sg:classifiers":[
        {
            "category":"Real Estate",
            "subcategory":"Real Estate Agent",
            "type":"Services"
        }
    ],
    "sg:phone":"+1 514 934 0617",
    "sg:postcode":"H4C 1H8",
    "sg:province":"QC",
    "wof:name":"Societe D'Habitation Loge",
    "wof:placetype":"venue"
},
  "geometry": {"coordinates":[-73.5844039917,45.4789390564],"type":"Point"}
}