{
  "type": "Feature",
  "properties": {
    "iso:country":"CA",
    "sg:address":"366 Rue Saint-Hubert",
    "sg:city":"Laval",
    "sg:classifiers":[
        {
            "category":"Home & Garden",
            "subcategory":"Furniture",
            "type":"Retail Goods"
        }
    ],
    "sg:phone":"+1 450 669 9790",
    "sg:postcode":"H7G 2Y7",
    "sg:province":"QC",
    "wof:name":"Beaudoin Maison Mederic",
    "wof:placetype":"venue"
},
  "geometry": {"coordinates":[-73.6867599487,45.5669975281],"type":"Point"}
}