{
  "type": "Feature",
  "properties": {
    "addr:full":"3115 Winston Churchill Blvd Mississauga ON L5L 2W1",
    "addr:housenumber":"3115",
    "addr:postcode":"l5l 2w1",
    "addr:street":"Winston Churchill Blvd",
    "iso:country":"CA",
    "sg:address":"3115 Winston Churchill Blvd",
    "sg:city":"Mississauga",
    "sg:classifiers":[
        {
            "category":"Restaurant",
            "type":"Food & Drink"
        }
    ],
    "sg:phone":"+1 905 820 4444",
    "sg:postcode":"L5L 2W1",
    "sg:province":"ON",
    "wof:name":"Twice the Deal Pizza",
    "wof:placetype":"venue"
},
  "geometry": {"coordinates":[-79.68408203120001,43.5247917175],"type":"Point"}
}