{
  "type": "Feature",
  "properties": {
    "iso:country":"CA",
    "sg:address":"1481 Rue Begin",
    "sg:city":"Saint-Laurent",
    "sg:classifiers":[
        {
            "category":"Shopping",
            "type":"Retail Goods"
        }
    ],
    "sg:phone":"+1 514 336 4821",
    "sg:postcode":"H4R 1V8",
    "sg:province":"QC",
    "sg:tags":[
        "orthopedic",
        "appliance"
    ],
    "wof:name":"Formedica Limitee",
    "wof:placetype":"venue"
},
  "geometry": {"coordinates":[-73.714249,45.495094],"type":"Point"}
}