{
  "type": "Feature",
  "properties": {
    "addr:full":"1481 Rue Begin Saint-Laurent QC H4R 1V8",
    "addr:housenumber":"1481",
    "addr:postcode":"h4r 1v8",
    "addr:street":"Rue Begin",
    "iso:country":"CA",
    "sg:address":"1481 Rue Begin",
    "sg:city":"Saint-Laurent",
    "sg:classifiers":[
        {
            "category":"Shopping",
            "type":"Retail Goods"
        }
    ],
    "sg:phone":"+1 514 336 4821",
    "sg:postcode":"H4R 1V8",
    "sg:province":"QC",
    "sg:tags":[
        "orthopedic",
        "appliance"
    ],
    "wof:name":"Formedica Limitee",
    "wof:placetype":"venue"
},
  "geometry": {"coordinates":[-73.714249,45.495094],"type":"Point"}
}