{
  "type": "Feature",
  "properties": {
    "addr:full":"4489 Marguerite St Vancouver BC V6J 4G5",
    "addr:housenumber":"4489",
    "addr:postcode":"v6j 4g5",
    "addr:street":"Marguerite St",
    "iso:country":"CA",
    "sg:address":"4489 Marguerite St",
    "sg:city":"Vancouver",
    "sg:classifiers":[
        {
            "category":"Social Services",
            "subcategory":"Job Training",
            "type":"Services"
        }
    ],
    "sg:phone":"+1 604 736 9509",
    "sg:postcode":"V6J 4G5",
    "sg:province":"BC",
    "sg:tags":[
        "occupational",
        "therapist",
        "rehabilitation"
    ],
    "wof:name":"Northwest Rehabilitation",
    "wof:placetype":"venue"
},
  "geometry": {"coordinates":[-123.144119,49.24575],"type":"Point"}
}