{
  "type": "Feature",
  "properties": {
    "addr:full":"569 20E Av Deux-Montagnes QC J7R 6B2",
    "addr:housenumber":"569",
    "addr:postcode":"j7r 6b2",
    "addr:street":"20E Av Deux-Montagnes",
    "iso:country":"CA",
    "sg:address":"569 20E Av",
    "sg:city":"Deux-Montagnes",
    "sg:classifiers":[
        {
            "category":"Banks & Credit Unions",
            "subcategory":"Bank",
            "type":"Services"
        }
    ],
    "sg:phone":"+1 450 472 4610",
    "sg:postcode":"J7R 6B2",
    "sg:province":"QC",
    "wof:name":"Cibc",
    "wof:placetype":"venue"
},
  "geometry": {"coordinates":[-73.91345200000001,45.542706],"type":"Point"}
}