{
  "type": "Feature",
  "properties": {
    "iso:country":"CA",
    "sg:city":"Calgary",
    "sg:classifiers":[
        {
            "category":"Health Services",
            "subcategory":"Doctor",
            "type":"Services"
        }
    ],
    "sg:phone":"+1 403 208 9555",
    "sg:postcode":"T3A 2N1",
    "sg:province":"AB",
    "sg:tags":[
        "physician",
        "surgeon"
    ],
    "wof:name":"Fitness MD",
    "wof:placetype":"venue"
},
  "geometry": {"coordinates":[-114.157112,51.088032],"type":"Point"}
}