{
  "type": "Feature",
  "properties": {
    "addr:full":"1034 Rue Jorcan Saint-Jean-Chrysostome QC G6Z 1L4",
    "addr:housenumber":"1034",
    "addr:postcode":"g6z 1l4",
    "addr:street":"Rue Jorcan Saint-Jean-Chrysostome",
    "iso:country":"CA",
    "sg:address":"1034 Rue Jorcan",
    "sg:city":"Saint-Jean-Chrysostome",
    "sg:classifiers":[
        {
            "category":"Home & Garden",
            "subcategory":"Building Materials",
            "type":"Retail Goods"
        }
    ],
    "sg:phone":"+1 418 839 1999",
    "sg:postcode":"G6Z 1L4",
    "sg:province":"QC",
    "sg:tags":[
        "door"
    ],
    "wof:name":"Portes DE Garage St-Jean Enr",
    "wof:placetype":"venue"
},
  "geometry": {"coordinates":[-71.201752,46.71983],"type":"Point"}
}