{
  "type": "Feature",
  "properties": {
    "iso:country":"CA",
    "sg:address":"7290 11 St SE",
    "sg:city":"Calgary",
    "sg:classifiers":[
        {
            "category":"Shopping",
            "subcategory":"Clothing, Apparel, & Fashions",
            "type":"Retail Goods"
        }
    ],
    "sg:phone":"+1 403 258 3831",
    "sg:postcode":"T2H 2S9",
    "sg:province":"AB",
    "sg:tags":[
        "infant",
        "wear"
    ],
    "wof:name":"Kacz' Kids",
    "wof:placetype":"venue"
},
  "geometry": {"coordinates":[-114.039337158,50.9884223938],"type":"Point"}
}