{
  "type": "Feature",
  "properties": {
    "iso:country":"CA",
    "sg:city":"Montreal",
    "sg:classifiers":[
        {
            "category":"Building & Trades",
            "subcategory":"Construction",
            "type":"Services"
        }
    ],
    "sg:phone":"+1 514 739 2423",
    "sg:postcode":"H4P 1W9",
    "sg:province":"QC",
    "sg:tags":[
        "general",
        "contractor"
    ],
    "wof:name":"Argo Construction Inc",
    "wof:placetype":"venue"
},
  "geometry": {"coordinates":[-73.6490097046,45.4975395203],"type":"Point"}
}