{
  "type": "Feature",
  "properties": {
    "iso:country":"CA",
    "sg:city":"Richmond",
    "sg:classifiers":[
        {
            "category":"Sports & Exercise",
            "subcategory":"Gym",
            "type":"Entertainment"
        }
    ],
    "sg:phone":"+1 604 279 9220",
    "sg:postcode":"V6X 3X2",
    "sg:province":"BC",
    "sg:tags":[
        "club",
        "health",
        "studio",
        "gymnasium"
    ],
    "wof:name":"Fitness Unlimited Athletic Clb",
    "wof:placetype":"venue"
},
  "geometry": {"coordinates":[-123.091698,49.195553],"type":"Point"}
}