{
  "type": "Feature",
  "properties": {
    "addr:full":"Toronto ON M5R 1V9",
    "addr:postcode":"m5r 1v9",
    "iso:country":"CA",
    "sg:city":"Toronto",
    "sg:classifiers":[
        {
            "category":"Health Services",
            "subcategory":"Health Practitioner",
            "type":"Services"
        }
    ],
    "sg:phone":"+1 416 944 2265",
    "sg:postcode":"M5R 1V9",
    "sg:province":"ON",
    "sg:tags":[
        "acupuncture"
    ],
    "wof:name":"Ontario Assoc of Acupuncture",
    "wof:placetype":"venue"
},
  "geometry": {"coordinates":[-79.41023300000001,43.674164],"type":"Point"}
}