{
  "type": "Feature",
  "properties": {
    "addr:full":"Chestermere AB T1X 1L6",
    "addr:postcode":"t1x 1l6",
    "iso:country":"CA",
    "sg:city":"Chestermere",
    "sg:classifiers":[
        {
            "category":"Sports & Exercise",
            "subcategory":"Gym",
            "type":"Entertainment"
        }
    ],
    "sg:phone":"+1 403 272 4007",
    "sg:postcode":"T1X 1L6",
    "sg:province":"AB",
    "sg:tags":[
        "club",
        "health",
        "studio",
        "gymnasium"
    ],
    "wof:name":"Curves For Women",
    "wof:placetype":"venue"
},
  "geometry": {"coordinates":[-113.84204099999999,51.036251],"type":"Point"}
}