{
  "type": "Feature",
  "properties": {
    "iso:country":"CA",
    "sg:address":"11522 168 St NW",
    "sg:city":"Edmonton",
    "sg:classifiers":[
        {
            "category":"Shopping",
            "subcategory":"Stationery & Office Supplies",
            "type":"Retail Goods"
        }
    ],
    "sg:phone":"+1 780 930 6910",
    "sg:postcode":"T5M 3T9",
    "sg:province":"AB",
    "wof:name":"Grand & Toy",
    "wof:placetype":"venue"
},
  "geometry": {"coordinates":[-113.610824585,53.5644340515],"type":"Point"}
}