{
  "type": "Feature",
  "properties": {
    "addr:full":"270 George Ave Winkler MB R6W 4A8",
    "addr:housenumber":"270",
    "addr:postcode":"r6w 4a8",
    "addr:street":"George Ave",
    "iso:country":"CA",
    "sg:address":"270 George Ave",
    "sg:city":"Winkler",
    "sg:classifiers":[
        {
            "category":"Wholesale",
            "subcategory":"Meat",
            "type":"Manufacturing & Wholesale Goods"
        }
    ],
    "sg:phone":"+1 204 325 9593",
    "sg:postcode":"R6W 4A8",
    "sg:province":"MB",
    "sg:tags":[
        "product"
    ],
    "wof:name":"Winkler Meat Ltd",
    "wof:placetype":"venue"
},
  "geometry": {"coordinates":[-97.9277801514,49.1807136536],"type":"Point"}
}