{
  "type": "Feature",
  "properties": {
    "iso:country":"CA",
    "sg:address":"1230 Barton St E",
    "sg:city":"Hamilton",
    "sg:classifiers":[
        {
            "category":"Autos & Motor Vehicles",
            "subcategory":"Auto Supplies",
            "type":"Retail Goods"
        }
    ],
    "sg:phone":"+1 905 544 6250",
    "sg:postcode":"L8H 2V8",
    "sg:province":"ON",
    "sg:tags":[
        "automobile",
        "parts"
    ],
    "wof:name":"East End Tire",
    "wof:placetype":"venue"
},
  "geometry": {"coordinates":[-79.81047058110001,43.2500076294],"type":"Point"}
}