{
  "type": "Feature",
  "properties": {
    "addr:full":"1400 Rue Sainte-Anne Yamachiche QC G0X 3L0",
    "addr:housenumber":"1400",
    "addr:postcode":"g0x 3l0",
    "addr:street":"Rue Sainte-Anne",
    "iso:country":"CA",
    "sg:address":"1400 Rue Sainte-Anne",
    "sg:city":"Yamachiche",
    "sg:classifiers":[
        {
            "category":"Autos & Motor Vehicles",
            "subcategory":"Fuel & Gas Station",
            "type":"Retail Goods"
        }
    ],
    "sg:phone":"+1 819 228 5620",
    "sg:postcode":"G0X 3L0",
    "sg:province":"QC",
    "sg:tags":[
        "oil"
    ],
    "wof:name":"Porte DE LA Mauricie",
    "wof:placetype":"venue"
},
  "geometry": {"coordinates":[-72.771896,46.292076],"type":"Point"}
}