{
  "type": "Feature",
  "properties": {
    "addr:full":"176 Rothesay Ave Saint John NB E2J 2B5",
    "addr:housenumber":"176",
    "addr:postcode":"e2j 2b5",
    "addr:street":"Rothesay Ave",
    "iso:country":"CA",
    "sg:address":"176 Rothesay Ave",
    "sg:city":"Saint John",
    "sg:classifiers":[
        {
            "category":"Shopping",
            "subcategory":"Stationery & Office Supplies",
            "type":"Retail Goods"
        }
    ],
    "sg:phone":"+1 506 646 7530",
    "sg:postcode":"E2J 2B5",
    "sg:province":"NB",
    "sg:tags":[
        "equipment",
        "computer",
        "dealer"
    ],
    "wof:name":"Staples Business Depot",
    "wof:placetype":"venue"
},
  "geometry": {"coordinates":[-66.04388427729999,45.2900161743],"type":"Point"}
}