{
  "type": "Feature",
  "properties": {
    "iso:country":"CA",
    "sg:address":"RR 4 STN Main",
    "sg:city":"Sherwood Park",
    "sg:classifiers":[
        {
            "category":"Recreation",
            "type":"Entertainment"
        }
    ],
    "sg:phone":"+1 780 464 0447",
    "sg:postcode":"T8A 3K4",
    "sg:province":"AB",
    "sg:tags":[
        "riding",
        "academy"
    ],
    "wof:name":"Good News Riding Ctr",
    "wof:placetype":"venue"
},
  "geometry": {"coordinates":[-113.29573822,53.5264015198],"type":"Point"}
}