{
  "type": "Feature",
  "properties": {
    "addr:full":"275 Geneva St St Catharines ON L2N 2E9",
    "addr:housenumber":"275",
    "addr:postcode":"l2n 2e9",
    "addr:street":"Geneva St",
    "iso:country":"CA",
    "sg:address":"275 Geneva St",
    "sg:city":"St Catharines",
    "sg:classifiers":[
        {
            "category":"Food & Beverages",
            "subcategory":"Groceries & Convenience Stores",
            "type":"Retail Goods"
        }
    ],
    "sg:phone":"+1 905 937 6523",
    "sg:postcode":"L2N 2E9",
    "sg:province":"ON",
    "sg:tags":[
        "grocer"
    ],
    "wof:name":"Duggan's Food Basics",
    "wof:placetype":"venue"
},
  "geometry": {"coordinates":[-79.2409744263,43.1767578125],"type":"Point"}
}