{
  "type": "Feature",
  "properties": {
    "addr:full":"Saskatoon SK S7K 1X5",
    "addr:postcode":"s7k 1x5",
    "iso:country":"CA",
    "sg:city":"Saskatoon",
    "sg:classifiers":[
        {
            "category":"Health Services",
            "subcategory":"Doctor",
            "type":"Services"
        }
    ],
    "sg:phone":"+1 306 664 5005",
    "sg:postcode":"S7K 1X5",
    "sg:province":"SK",
    "sg:tags":[
        "dentist"
    ],
    "wof:name":"Dutton, Darrell DDS",
    "wof:placetype":"venue"
},
  "geometry": {"coordinates":[-106.663307,52.134037],"type":"Point"}
}