{
  "type": "Feature",
  "properties": {
    "addr:full":"PO Box 70 Dorintosh SK S0M 0T0",
    "addr:housenumber":"po box 70",
    "addr:postcode":"s0m 0t0",
    "addr:street":"Dorintosh",
    "iso:country":"CA",
    "sg:address":"PO Box 70",
    "sg:city":"Dorintosh",
    "sg:classifiers":[
        {
            "category":"Government",
            "subcategory":"Office",
            "type":"Public Place"
        }
    ],
    "sg:phone":"+1 306 236 7680",
    "sg:postcode":"S0M 0T0",
    "sg:province":"SK",
    "wof:name":"Sask Conservation Officers",
    "wof:placetype":"venue"
},
  "geometry": {"coordinates":[-108.627945,54.355129],"type":"Point"}
}