{
  "type": "Feature",
  "properties": {
    "addr:full":"Montreal QC H4J 2P1",
    "addr:postcode":"h4j 2p1",
    "iso:country":"CA",
    "sg:city":"Montreal",
    "sg:classifiers":[
        {
            "category":"Health Services",
            "subcategory":"Doctor",
            "type":"Services"
        }
    ],
    "sg:phone":"+1 514 337 3017",
    "sg:postcode":"H4J 2P1",
    "sg:province":"QC",
    "sg:tags":[
        "dentist"
    ],
    "wof:name":"Derkevorkian, Harry DDS",
    "wof:placetype":"venue"
},
  "geometry": {"coordinates":[-73.706757,45.53244],"type":"Point"}
}