{
  "type": "Feature",
  "properties": {
    "addr:full":"Williams Lake BC V2G 1J8",
    "addr:postcode":"bc v2g 1j8",
    "iso:country":"CA",
    "sg:city":"Williams Lake",
    "sg:classifiers":[
        {
            "category":"Health Services",
            "subcategory":"Doctor",
            "type":"Services"
        }
    ],
    "sg:phone":"+1 250 398 8319",
    "sg:postcode":"V2G 1J8",
    "sg:province":"BC",
    "sg:tags":[
        "physician",
        "surgeon"
    ],
    "wof:name":"Klepsch, R MD",
    "wof:placetype":"venue"
},
  "geometry": {"coordinates":[-122.141052246,52.126209259],"type":"Point"}
}