{
  "type": "Feature",
  "properties": {
    "addr:full":"12321 Tecumseh Rd E Windsor ON N8N 1M5",
    "addr:housenumber":"12321",
    "addr:postcode":"n8n 1m5",
    "addr:street":"Tecumseh Rd E",
    "iso:country":"CA",
    "sg:address":"12321 Tecumseh Rd E",
    "sg:city":"Windsor",
    "sg:classifiers":[
        {
            "category":"Banks & Credit Unions",
            "subcategory":"Bank",
            "type":"Services"
        }
    ],
    "sg:phone":"+1 519 735 2168",
    "sg:postcode":"N8N 1M5",
    "sg:province":"ON",
    "wof:name":"National Bank of Canada",
    "wof:placetype":"venue"
},
  "geometry": {"coordinates":[-82.900932,42.312481],"type":"Point"}
}