{
  "type": "Feature",
  "properties": {
    "addr:full":"1041 Marley Cres Burlington ON L7T 3S3",
    "addr:housenumber":"1041",
    "addr:postcode":"l7t 3s3",
    "addr:street":"Marley Cres",
    "iso:country":"CA",
    "sg:address":"1041 Marley Cres",
    "sg:city":"Burlington",
    "sg:classifiers":[
        {
            "category":"Communications",
            "subcategory":"Film & Video Production",
            "type":"Services"
        }
    ],
    "sg:phone":"+1 905 639 4490",
    "sg:postcode":"L7T 3S3",
    "sg:province":"ON",
    "sg:tags":[
        "taping"
    ],
    "wof:name":"Bob Salo Visual Communications",
    "wof:placetype":"venue"
},
  "geometry": {"coordinates":[-79.821594,43.322216],"type":"Point"}
}