{
  "type": "Feature",
  "properties": {
    "addr:full":"303 Main St Atikokan ON P0T 1C0",
    "addr:housenumber":"303",
    "addr:postcode":"p0t 1c0",
    "addr:street":"Main St",
    "iso:country":"CA",
    "sg:address":"303 Main St",
    "sg:city":"Atikokan",
    "sg:classifiers":[
        {
            "category":"Food & Beverages",
            "subcategory":"Groceries & Convenience Stores",
            "type":"Retail Goods"
        }
    ],
    "sg:phone":"+1 807 597 4226",
    "sg:postcode":"P0T 1C0",
    "sg:province":"ON",
    "wof:name":"Atikokan Newstand",
    "wof:placetype":"venue"
},
  "geometry": {"coordinates":[-91.62487,48.757404],"type":"Point"}
}