{
  "type": "Feature",
  "properties": {
    "addr:full":"200 1st Ave Avonlea SK S0H 0C0",
    "addr:housenumber":"200",
    "addr:postcode":"s0h 0c0",
    "addr:street":"1St Ave",
    "iso:country":"CA",
    "sg:address":"200 1st Ave",
    "sg:city":"Avonlea",
    "sg:classifiers":[
        {
            "category":"Organizations",
            "subcategory":"Religious Organization",
            "type":"Services"
        }
    ],
    "sg:phone":"+1 306 868 2255",
    "sg:postcode":"S0H 0C0",
    "sg:province":"SK",
    "sg:tags":[
        "church"
    ],
    "wof:name":"Avonlea Briercrest United Chr",
    "wof:placetype":"venue"
},
  "geometry": {"coordinates":[-105.055336,50.015781],"type":"Point"}
}