{
  "type": "Feature",
  "properties": {
    "iso:country":"CA",
    "sg:address":"840 Coxwell Ave",
    "sg:city":"East York",
    "sg:classifiers":[
        {
            "category":"Education",
            "subcategory":"School",
            "type":"Public Place"
        }
    ],
    "sg:phone":"+1 416 397 3000",
    "sg:postcode":"M4C 5T2",
    "sg:province":"ON",
    "wof:name":"East York Board of Education",
    "wof:placetype":"venue"
},
  "geometry": {"coordinates":[-79.3266448975,43.6902923584],"type":"Point"}
}