{
  "type": "Feature",
  "properties": {
    "addr:full":"4046 Rumble St Burnaby BC V5J 1Z6",
    "addr:housenumber":"4046",
    "addr:postcode":"v5j 1z6",
    "addr:street":"Rumble St",
    "iso:country":"CA",
    "sg:address":"4046 Rumble St",
    "sg:city":"Burnaby",
    "sg:classifiers":[
        {
            "category":"Building & Trades",
            "subcategory":"Construction",
            "type":"Services"
        }
    ],
    "sg:phone":"+1 604 438 2780",
    "sg:postcode":"V5J 1Z6",
    "sg:province":"BC",
    "sg:tags":[
        "railing"
    ],
    "wof:name":"Tito Aluminum Custom Railings",
    "wof:placetype":"venue"
},
  "geometry": {"coordinates":[-123.01385500000001,49.214642],"type":"Point"}
}