{
  "type": "Feature",
  "properties": {
    "iso:country":"CA",
    "sg:address":"381 Trans Canada Hwy",
    "sg:city":"Duncan",
    "sg:classifiers":[
        {
            "category":"Organizations",
            "subcategory":"Professional Association",
            "type":"Services"
        }
    ],
    "sg:phone":"+1 250 748 1111",
    "sg:postcode":"V9L 3R5",
    "sg:province":"BC",
    "sg:tags":[
        "chambers",
        "commerce"
    ],
    "wof:name":"Duncan-Cowichan Chamber-Comm",
    "wof:placetype":"venue"
},
  "geometry": {"coordinates":[-123.699020386,48.7783279419],"type":"Point"}
}