{
  "type": "Feature",
  "properties": {
    "iso:country":"CA",
    "sg:address":"679 Rue Saint-Roch",
    "sg:city":"Montreal",
    "sg:classifiers":[
        {
            "category":"Restaurant",
            "type":"Food & Drink"
        }
    ],
    "sg:phone":"+1 514 277 4689",
    "sg:postcode":"H3N 1L2",
    "sg:province":"QC",
    "wof:name":"Tripolis Souvlaki Restaurant",
    "wof:placetype":"venue"
},
  "geometry": {"coordinates":[-73.629875,45.528954],"type":"Point"}
}