{
  "type": "Feature",
  "properties": {
    "addr:full":"Brampton ON L6Y 1N7",
    "addr:postcode":"l6y 1n7",
    "iso:country":"CA",
    "sg:city":"Brampton",
    "sg:classifiers":[
        {
            "category":"Shopping",
            "subcategory":"Optical Goods",
            "type":"Retail Goods"
        }
    ],
    "sg:phone":"+1 905 450 3220",
    "sg:postcode":"L6Y 1N7",
    "sg:province":"ON",
    "sg:tags":[
        "optician"
    ],
    "wof:name":"Lenscrafters",
    "wof:placetype":"venue"
},
  "geometry": {"coordinates":[-79.73579406739999,43.6675834656],"type":"Point"}
}