{
  "type": "Feature",
  "properties": {
    "addr:full":"3205 9 St SE Calgary AB T2G 3C1",
    "addr:housenumber":"3205 9",
    "addr:postcode":"t2g 3c1",
    "addr:street":"St Se",
    "iso:country":"CA",
    "sg:address":"3205 9 St SE",
    "sg:city":"Calgary",
    "sg:classifiers":[
        {
            "category":"Retail",
            "subcategory":"Auto Repair",
            "type":"Services"
        }
    ],
    "sg:phone":"+1 403 287 0082",
    "sg:postcode":"T2G 3C1",
    "sg:province":"AB",
    "sg:tags":[
        "repairing",
        "shop",
        "tire"
    ],
    "wof:name":"Raynard Supply Ltd",
    "wof:placetype":"venue"
},
  "geometry": {"coordinates":[-114.040604,51.025883],"type":"Point"}
}