{
  "type": "Feature",
  "properties": {
    "addr:full":"1390 3rd Ave E Vancouver BC V5N 5R8",
    "addr:housenumber":"1390",
    "addr:postcode":"v5n 5r8",
    "addr:street":"3Rd Ave E",
    "iso:country":"CA",
    "sg:address":"1390 3rd Ave E",
    "sg:city":"Vancouver",
    "sg:classifiers":[
        {
            "category":"Wholesale",
            "subcategory":"Metals & Minerals",
            "type":"Manufacturing & Wholesale Goods"
        }
    ],
    "sg:phone":"+1 604 254 9868",
    "sg:postcode":"V5N 5R8",
    "sg:province":"BC",
    "sg:tags":[
        "product",
        "wire"
    ],
    "wof:name":"Structa Wire Corp",
    "wof:placetype":"venue"
},
  "geometry": {"coordinates":[-123.07575199999999,49.267689],"type":"Point"}
}