{
  "type": "Feature",
  "properties": {
    "addr:full":"780 Av Sainte-Croix Saint-Laurent QC H4L 3Y2",
    "addr:housenumber":"780",
    "addr:postcode":"h4l 3y2",
    "addr:street":"Av Sainte-Croix",
    "iso:country":"CA",
    "sg:address":"780 Av Sainte-Croix",
    "sg:city":"Saint-Laurent",
    "sg:classifiers":[
        {
            "category":"Health Services",
            "subcategory":"Doctor",
            "type":"Services"
        }
    ],
    "sg:phone":"+1 514 748 2020",
    "sg:postcode":"H4L 3Y2",
    "sg:province":"QC",
    "sg:tags":[
        "dentist"
    ],
    "wof:name":"Centre Dentaire Ste-Croix",
    "wof:placetype":"venue"
},
  "geometry": {"coordinates":[-73.67512499999999,45.513107],"type":"Point"}
}