{
  "type": "Feature",
  "properties": {
    "addr:full":"1717 Boul Le Corbusier Laval QC H7S 2K7",
    "addr:housenumber":"1717",
    "addr:postcode":"h7s 2k7",
    "addr:street":"Boul Le Corbusier",
    "iso:country":"CA",
    "sg:address":"1717 Boul Le Corbusier",
    "sg:city":"Laval",
    "sg:classifiers":[
        {
            "category":"Recreation",
            "type":"Entertainment"
        }
    ],
    "sg:phone":"+1 514 333 6000",
    "sg:postcode":"H7S 2K7",
    "sg:province":"QC",
    "sg:tags":[
        "hall",
        "auditorium"
    ],
    "wof:name":"Salle DE Reception Palace",
    "wof:placetype":"venue"
},
  "geometry": {"coordinates":[-73.7329406738,45.5658454895],"type":"Point"}
}