{
  "type": "Feature",
  "properties": {
    "addr:full":"3870 Rue Queen Rawdon QC J0K 1S0",
    "addr:housenumber":"3870",
    "addr:postcode":"j0k 1s0",
    "addr:street":"Rue Queen",
    "iso:country":"CA",
    "sg:address":"3870 Rue Queen",
    "sg:city":"Rawdon",
    "sg:classifiers":[
        {
            "category":"Sports & Exercise",
            "subcategory":"Bowling",
            "type":"Entertainment"
        }
    ],
    "sg:phone":"+1 450 834 2700",
    "sg:postcode":"J0K 1S0",
    "sg:province":"QC",
    "sg:tags":[
        "center"
    ],
    "wof:name":"Salle DE Quilles DE Rawdon",
    "wof:placetype":"venue"
},
  "geometry": {"coordinates":[-73.715401,46.048218],"type":"Point"}
}