{
  "type": "Feature",
  "properties": {
    "addr:full":"Charlesbourg QC G1H 1H1",
    "addr:postcode":"g1h 1h1",
    "iso:country":"CA",
    "sg:city":"Charlesbourg",
    "sg:classifiers":[
        {
            "category":"Organizations",
            "subcategory":"Professional Association",
            "type":"Services"
        }
    ],
    "sg:phone":"+1 418 624 4612",
    "sg:postcode":"G1H 1H1",
    "sg:province":"QC",
    "sg:tags":[
        "club"
    ],
    "wof:name":"Club Aquatique Charlesbourg",
    "wof:placetype":"venue"
},
  "geometry": {"coordinates":[-71.25490600000001,46.864021],"type":"Point"}
}