{
  "type": "Feature",
  "properties": {
    "iso:country":"CA",
    "sg:address":"1904 31 St SW",
    "sg:city":"Calgary",
    "sg:classifiers":[
        {
            "category":"Personal",
            "subcategory":"Beauty Salon",
            "type":"Services"
        }
    ],
    "sg:phone":"+1 403 242 3464",
    "sg:postcode":"T3E 2M9",
    "sg:province":"AB",
    "wof:name":"Hair Peace",
    "wof:placetype":"venue"
},
  "geometry": {"coordinates":[-114.132522583,51.0375823975],"type":"Point"}
}