{
  "type": "Feature",
  "properties": {
    "iso:country":"CA",
    "sg:address":"150 Rue Saint-Andre",
    "sg:city":"Saint-Remi",
    "sg:classifiers":[
        {
            "category":"Retail",
            "subcategory":"Auto Repair",
            "type":"Services"
        }
    ],
    "sg:phone":"+1 450 454 7523",
    "sg:postcode":"J0L 2L0",
    "sg:province":"QC",
    "sg:tags":[
        "repairing",
        "automobile"
    ],
    "wof:name":"Station Service Jm Inc",
    "wof:placetype":"venue"
},
  "geometry": {"coordinates":[-73.613327,45.256763],"type":"Point"}
}