{
  "type": "Feature",
  "properties": {
    "addr:full":"3477 Portage Rd Niagara Falls ON L2J 2K5",
    "addr:housenumber":"3477",
    "addr:postcode":"l2j 2k5",
    "addr:street":"Portage Rd",
    "iso:country":"CA",
    "sg:address":"3477 Portage Rd",
    "sg:city":"Niagara Falls",
    "sg:classifiers":[
        {
            "category":"Personal",
            "subcategory":"Beauty Salon",
            "type":"Services"
        }
    ],
    "sg:phone":"+1 905 357 4247",
    "sg:postcode":"L2J 2K5",
    "sg:province":"ON",
    "wof:name":"Sharp Looks Hair Styling",
    "wof:placetype":"venue"
},
  "geometry": {"coordinates":[-79.099808,43.121754],"type":"Point"}
}