{
  "type": "Feature",
  "properties": {
    "addr:full":"367 Rue Saint-Jean-Baptiste N Princeville QC G6L 4Z4",
    "addr:housenumber":"367",
    "addr:postcode":"g6l 4z4",
    "addr:street":"Rue Saint-Jean-Baptiste N",
    "iso:country":"CA",
    "sg:address":"367 Rue Saint-Jean-Baptiste N",
    "sg:city":"Princeville",
    "sg:classifiers":[
        {
            "category":"Retail",
            "subcategory":"Auto Repair",
            "type":"Services"
        }
    ],
    "sg:phone":"+1 819 364 5123",
    "sg:postcode":"G6L 4Z4",
    "sg:province":"QC",
    "sg:tags":[
        "repairing",
        "automobile"
    ],
    "wof:name":"Garage R Cote Inc",
    "wof:placetype":"venue"
},
  "geometry": {"coordinates":[-71.88061500000001,46.176929],"type":"Point"}
}