{
  "type": "Feature",
  "properties": {
    "addr:full":"225 Balmoral Dr Brampton ON L6T 1V4",
    "addr:housenumber":"225",
    "addr:postcode":"l6t 1v4",
    "addr:street":"Balmoral Dr",
    "iso:country":"CA",
    "sg:address":"225 Balmoral Dr",
    "sg:city":"Brampton",
    "sg:classifiers":[
        {
            "category":"Recreation",
            "type":"Entertainment"
        }
    ],
    "sg:phone":"+1 905 792 8970",
    "sg:postcode":"L6T 1V4",
    "sg:province":"ON",
    "sg:tags":[
        "boxing",
        "instruction"
    ],
    "wof:name":"Bramalea Boxing Club",
    "wof:placetype":"venue"
},
  "geometry": {"coordinates":[-79.712807,43.708893],"type":"Point"}
}