{
  "type": "Feature",
  "properties": {
    "addr:full":"86 Angeline St S #102 Lindsay ON K9V 6C5",
    "addr:housenumber":"86;102",
    "addr:postcode":"k9v 6c5",
    "addr:street":"Angeline St S #",
    "iso:country":"CA",
    "sg:address":"86 Angeline St S #102",
    "sg:city":"Lindsay",
    "sg:classifiers":[
        {
            "category":"Shopping",
            "subcategory":"Pharmacy",
            "type":"Retail Goods"
        }
    ],
    "sg:phone":"+1 705 878 4701",
    "sg:postcode":"K9V 6C5",
    "sg:province":"ON",
    "wof:name":"Pharma Plus Drugmart",
    "wof:placetype":"venue"
},
  "geometry": {"coordinates":[-78.74826,44.34531],"type":"Point"}
}