{
  "type": "Feature",
  "properties": {
    "addr:full":"201 Ch Pinard Stoke QC J0B 3G0",
    "addr:housenumber":"201",
    "addr:postcode":"j0b 3g0",
    "addr:street":"Ch Pinard",
    "iso:country":"CA",
    "sg:address":"201 Ch Pinard",
    "sg:city":"Stoke",
    "sg:classifiers":[
        {
            "category":"Manufacturing",
            "subcategory":"Tools & Machinery",
            "type":"Manufacturing & Wholesale Goods"
        }
    ],
    "sg:phone":"+1 819 878 3532",
    "sg:postcode":"J0B 3G0",
    "sg:province":"QC",
    "sg:tags":[
        "pump"
    ],
    "wof:name":"Entreprises Andre Pepin Inc",
    "wof:placetype":"venue"
},
  "geometry": {"coordinates":[-71.8034744263,45.4870491028],"type":"Point"}
}