{
  "type": "Feature",
  "properties": {
    "addr:full":"Manning AB T0H 2M0",
    "addr:postcode":"t0h 2m0",
    "iso:country":"CA",
    "sg:city":"Manning",
    "sg:phone":"+1 780 836 3363",
    "sg:postcode":"T0H 2M0",
    "sg:province":"AB",
    "sg:tags":[
        "agricultural",
        "product",
        "greenhouse"
    ],
    "wof:name":"Agricore United",
    "wof:placetype":"venue"
},
  "geometry": {"coordinates":[-117.628410339,56.9239768982],"type":"Point"}
}