{
  "type": "Feature",
  "properties": {
    "addr:full":"31 Front St Rockport ON K0E 1V0",
    "addr:housenumber":"31",
    "addr:postcode":"k0e 1v0",
    "addr:street":"Front St",
    "iso:country":"CA",
    "sg:address":"31 Front St",
    "sg:city":"Rockport",
    "sg:classifiers":[
        {
            "category":"Autos & Motor Vehicles",
            "subcategory":"Boat Sales",
            "type":"Retail Goods"
        }
    ],
    "sg:phone":"+1 613 659 3471",
    "sg:postcode":"K0E 1V0",
    "sg:province":"ON",
    "sg:tags":[
        "equipment",
        "supply"
    ],
    "wof:name":"Andress Boat Works",
    "wof:placetype":"venue"
},
  "geometry": {"coordinates":[-75.932991,44.378555],"type":"Point"}
}