{
  "type": "Feature",
  "properties": {
    "addr:full":"508 Latimer St Nelson BC V1L 4T9",
    "addr:housenumber":"508",
    "addr:postcode":"bc v1l 4t9",
    "addr:street":"Latimer St",
    "iso:country":"CA",
    "sg:address":"508 Latimer St",
    "sg:city":"Nelson",
    "sg:classifiers":[
        {
            "category":"Home & Garden",
            "subcategory":"Building Materials",
            "type":"Retail Goods"
        }
    ],
    "sg:phone":"+1 250 352 3101",
    "sg:postcode":"V1L 4T9",
    "sg:province":"BC",
    "sg:tags":[
        "door"
    ],
    "wof:name":"Custom Wood Doors",
    "wof:placetype":"venue"
},
  "geometry": {"coordinates":[-117.290260315,49.4881401062],"type":"Point"}
}