{
  "type": "Feature",
  "properties": {
    "addr:full":"Calgary AB T2B 3N4",
    "addr:postcode":"t2b 3n4",
    "iso:country":"CA",
    "sg:city":"Calgary",
    "sg:classifiers":[
        {
            "category":"Building & Trades",
            "subcategory":"Construction",
            "type":"Services"
        }
    ],
    "sg:phone":"+1 403 250 3333",
    "sg:postcode":"T2B 3N4",
    "sg:province":"AB",
    "sg:tags":[
        "general",
        "contractor"
    ],
    "wof:name":"Highview Construction Ltd",
    "wof:placetype":"venue"
},
  "geometry": {"coordinates":[-113.970252991,51.010093689],"type":"Point"}
}