{
  "type": "Feature",
  "properties": {
    "addr:full":"4903 47 St Yellowknife NT X1A 1L7",
    "addr:housenumber":"4903",
    "addr:postcode":"x1a 1l7",
    "addr:street":"47 St",
    "iso:country":"CA",
    "sg:address":"4903 47 St",
    "sg:city":"Yellowknife",
    "sg:classifiers":[
        {
            "category":"Professional",
            "subcategory":"Engineering",
            "type":"Services"
        }
    ],
    "sg:phone":"+1 867 873 2395",
    "sg:postcode":"X1A 1L7",
    "sg:province":"NT",
    "sg:tags":[
        "engineer"
    ],
    "wof:name":"A D Williams Engineering Inc",
    "wof:placetype":"venue"
},
  "geometry": {"coordinates":[-114.370293,62.456871],"type":"Point"}
}