{
  "type": "Feature",
  "properties": {
    "addr:full":"356 Boul Evain O Evain QC J0Z 1Y0",
    "addr:housenumber":"356",
    "addr:postcode":"j0z 1y0",
    "addr:street":"Boul Evain O Evain",
    "iso:country":"CA",
    "sg:address":"356 Boul Evain O",
    "sg:city":"Evain",
    "sg:classifiers":[
        {
            "category":"Retail",
            "subcategory":"Auto Repair",
            "type":"Services"
        }
    ],
    "sg:phone":"+1 819 279 2524",
    "sg:postcode":"J0Z 1Y0",
    "sg:province":"QC",
    "sg:tags":[
        "repairing",
        "automobile"
    ],
    "wof:name":"Garage Le Mecano",
    "wof:placetype":"venue"
},
  "geometry": {"coordinates":[-79.2306976318,48.322769165],"type":"Point"}
}