{
  "type": "Feature",
  "properties": {
    "addr:full":"245 Powell St Vancouver BC V6A 1G3",
    "addr:housenumber":"245",
    "addr:postcode":"v6a 1g3",
    "addr:street":"Powell St",
    "iso:country":"CA",
    "sg:address":"245 Powell St",
    "sg:city":"Vancouver",
    "sg:classifiers":[
        {
            "category":"Real Estate",
            "subcategory":"Real Estate Agent",
            "type":"Services"
        }
    ],
    "sg:phone":"+1 604 682 1189",
    "sg:postcode":"V6A 1G3",
    "sg:province":"BC",
    "sg:tags":[
        "authorities",
        "housing"
    ],
    "wof:name":"Shiloh Housing Society",
    "wof:placetype":"venue"
},
  "geometry": {"coordinates":[-123.098709,49.283325],"type":"Point"}
}