{
  "type": "Feature",
  "properties": {
    "addr:full":"4707 50th St Valleyview AB T0H 3N0",
    "addr:housenumber":"4707",
    "addr:postcode":"ab t0h 3n0",
    "addr:street":"50Th St",
    "iso:country":"CA",
    "sg:address":"4707 50th St",
    "sg:city":"Valleyview",
    "sg:classifiers":[
        {
            "category":"Government",
            "subcategory":"Office",
            "type":"Public Place"
        }
    ],
    "sg:phone":"+1 780 524 7600",
    "sg:postcode":"T0H 3N0",
    "sg:province":"AB",
    "sg:tags":[
        "municipality"
    ],
    "wof:name":"Municipal District-Greenview",
    "wof:placetype":"venue"
},
  "geometry": {"coordinates":[-117.280647,55.064201],"type":"Point"}
}