{
  "type": "Feature",
  "properties": {
    "addr:full":"48 Major Wm. Sharpe Dr Brampton ON L6X 3J2",
    "addr:housenumber":"48",
    "addr:postcode":"l6x 3j2",
    "addr:street":"Major Wm. Sharpe Dr",
    "iso:country":"CA",
    "sg:address":"48 Major Wm. Sharpe Dr",
    "sg:city":"Brampton",
    "sg:classifiers":[
        {
            "category":"Building & Trades",
            "subcategory":"Electrical",
            "type":"Services"
        }
    ],
    "sg:phone":"+1 905 459 5762",
    "sg:postcode":"L6X 3J2",
    "sg:province":"ON",
    "sg:tags":[
        "electric",
        "contractor"
    ],
    "wof:name":"Easynet Services Ltd",
    "wof:placetype":"venue"
},
  "geometry": {"coordinates":[-79.7827758789,43.6713294983],"type":"Point"}
}