{
  "type": "Feature",
  "properties": {
    "addr:full":"Stratford ON N5A 7K2",
    "addr:postcode":"n5a 7k2",
    "iso:country":"CA",
    "sg:city":"Stratford",
    "sg:classifiers":[
        {
            "category":"Organizations",
            "subcategory":"Non-profit Organization",
            "type":"Services"
        }
    ],
    "sg:phone":"+1 519 271 7391",
    "sg:postcode":"N5A 7K2",
    "sg:province":"ON",
    "sg:tags":[
        "disability"
    ],
    "wof:name":"Cheshire Homes of London",
    "wof:placetype":"venue"
},
  "geometry": {"coordinates":[-80.97673,43.385204],"type":"Point"}
}