{
  "type": "Feature",
  "properties": {
    "addr:full":"2163 Trans Canada Hwy Belle River PE C0A 1B0",
    "addr:housenumber":"2163",
    "addr:postcode":"c0a 1b0",
    "addr:street":"Trans Canada Hwy",
    "iso:country":"CA",
    "sg:address":"2163 Trans Canada Hwy",
    "sg:city":"Belle River",
    "sg:classifiers":[
        {
            "category":"Professional",
            "subcategory":"Management & Consulting",
            "type":"Services"
        }
    ],
    "sg:phone":"+1 902 659 2626",
    "sg:postcode":"C0A 1B0",
    "sg:province":"PE",
    "sg:tags":[
        "food",
        "facility"
    ],
    "wof:name":"Eastern Food Safety Consulting",
    "wof:placetype":"venue"
},
  "geometry": {"coordinates":[-62.8495407104,45.9988098145],"type":"Point"}
}