{
  "type": "Feature",
  "properties": {
    "addr:full":"1787 Rue Saint-Calixte Plessisville QC G6L 1R4",
    "addr:housenumber":"1787",
    "addr:postcode":"g6l 1r4",
    "addr:street":"Rue Saint-Calixte",
    "iso:country":"CA",
    "sg:address":"1787 Rue Saint-Calixte",
    "sg:city":"Plessisville",
    "sg:classifiers":[
        {
            "category":"Insurance",
            "subcategory":"Insurance Agent",
            "type":"Services"
        }
    ],
    "sg:phone":"+1 819 362 6367",
    "sg:postcode":"G6L 1R4",
    "sg:province":"QC",
    "wof:name":"Assurance Beliveau Michaud",
    "wof:placetype":"venue"
},
  "geometry": {"coordinates":[-71.770882,46.219833],"type":"Point"}
}