{
  "type": "Feature",
  "properties": {
    "addr:full":"65 Pembroke St W Pembroke ON K8A 5M5",
    "addr:housenumber":"65",
    "addr:postcode":"k8a 5m5",
    "addr:street":"Pembroke St W",
    "iso:country":"CA",
    "sg:address":"65 Pembroke St W",
    "sg:city":"Pembroke",
    "sg:classifiers":[
        {
            "category":"Shopping",
            "type":"Retail Goods"
        }
    ],
    "sg:phone":"+1 613 732 8733",
    "sg:postcode":"K8A 5M5",
    "sg:province":"ON",
    "sg:tags":[
        "trophy",
        "medal",
        "award"
    ],
    "wof:name":"Pembroke Trophy Ctr",
    "wof:placetype":"venue"
},
  "geometry": {"coordinates":[-77.11428070069999,45.8260002136],"type":"Point"}
}