{
  "type": "Feature",
  "properties": {
    "iso:country":"CA",
    "sg:address":"1600 Rue Notre-Dame O #210",
    "sg:city":"Montreal",
    "sg:classifiers":[
        {
            "category":"Professional",
            "subcategory":"Art Services",
            "type":"Services"
        }
    ],
    "sg:phone":"+1 514 932 9922",
    "sg:postcode":"H3J 1M1",
    "sg:province":"QC",
    "sg:tags":[
        "graphic",
        "designer"
    ],
    "wof:name":"Productions Mr",
    "wof:placetype":"venue"
},
  "geometry": {"coordinates":[-73.547958,45.51823],"type":"Point"}
}