{
  "type": "Feature",
  "properties": {
    "addr:full":"381 Princess St Kingston ON K7L 1B9",
    "addr:housenumber":"381",
    "addr:postcode":"k7l 1b9",
    "addr:street":"Princess St",
    "iso:country":"CA",
    "sg:address":"381 Princess St",
    "sg:city":"Kingston",
    "sg:classifiers":[
        {
            "category":"Shopping",
            "subcategory":"Music",
            "type":"Retail Goods"
        }
    ],
    "sg:phone":"+1 613 542 2452",
    "sg:postcode":"K7L 1B9",
    "sg:province":"ON",
    "sg:tags":[
        "compact",
        "record",
        "disc",
        "tape"
    ],
    "wof:name":"Brian's Record Option",
    "wof:placetype":"venue"
},
  "geometry": {"coordinates":[-76.4913482666,44.2330474854],"type":"Point"}
}