{
  "type": "Feature",
  "properties": {
    "iso:country":"CA",
    "sg:city":"Saint-Barnabe-Sud",
    "sg:classifiers":[
        {
            "category":"Manufacturing",
            "subcategory":"Motor Vehicles & Parts",
            "type":"Manufacturing & Wholesale Goods"
        }
    ],
    "sg:phone":"+1 450 792 3380",
    "sg:postcode":"J0H 1G0",
    "sg:province":"QC",
    "sg:tags":[
        "designer",
        "trailer"
    ],
    "wof:name":"Remorques A Chevaux Du QC Inc",
    "wof:placetype":"venue"
},
  "geometry": {"coordinates":[-72.9237823486,45.7290458679],"type":"Point"}
}