{
  "type": "Feature",
  "properties": {
    "addr:full":"1010 Rue DE L'Ontario Sherbrooke QC J1J 3S3",
    "addr:housenumber":"1010",
    "addr:postcode":"j1j 3s3",
    "addr:street":"Rue De L'Ontario",
    "iso:country":"CA",
    "sg:address":"1010 Rue DE L'Ontario",
    "sg:city":"Sherbrooke",
    "sg:classifiers":[
        {
            "category":"Manufacturing",
            "subcategory":"Musical Instruments",
            "type":"Manufacturing & Wholesale Goods"
        }
    ],
    "sg:phone":"+1 819 822 0815",
    "sg:postcode":"J1J 3S3",
    "sg:province":"QC",
    "sg:tags":[
        "violin",
        "maker"
    ],
    "wof:name":"Atelier DE Lutherie",
    "wof:placetype":"venue"
},
  "geometry": {"coordinates":[-71.908058,45.399338],"type":"Point"}
}