{
  "type": "Feature",
  "properties": {
    "iso:country":"CA",
    "sg:address":"765 Rue Notre-Dame E",
    "sg:city":"Victoriaville",
    "sg:classifiers":[
        {
            "category":"Education",
            "subcategory":"College",
            "type":"Public Place"
        }
    ],
    "sg:phone":"+1 819 758 8219",
    "sg:postcode":"G6P 4B2",
    "sg:province":"QC",
    "sg:tags":[
        "academic",
        "school"
    ],
    "wof:name":"Eqmbo Entreprises",
    "wof:placetype":"venue"
},
  "geometry": {"coordinates":[-71.9408569336,46.0652122498],"type":"Point"}
}