{
  "type": "Feature",
  "properties": {
    "addr:full":"711 the Queensway Etobicoke ON M8Y 1L2",
    "addr:housenumber":"711",
    "addr:postcode":"m8y 1l2",
    "addr:street":"The Queensway",
    "iso:country":"CA",
    "sg:address":"711 the Queensway",
    "sg:city":"Etobicoke",
    "sg:classifiers":[
        {
            "category":"Real Estate",
            "subcategory":"Architect",
            "type":"Services"
        }
    ],
    "sg:phone":"+1 416 253 8072",
    "sg:postcode":"M8Y 1L2",
    "sg:province":"ON",
    "wof:name":"Wilkinson, James B",
    "wof:placetype":"venue"
},
  "geometry": {"coordinates":[-79.50122833250001,43.6265144348],"type":"Point"}
}