{
  "type": "Feature",
  "properties": {
    "iso:country":"CA",
    "sg:address":"York Point Rd",
    "sg:city":"Cornwall",
    "sg:classifiers":[
        {
            "category":"Building & Trades",
            "subcategory":"Plumbing",
            "type":"Services"
        }
    ],
    "sg:phone":"+1 902 676 2647",
    "sg:postcode":"C0A 1H0",
    "sg:province":"PE",
    "sg:tags":[
        "contractor"
    ],
    "wof:name":"Lea & Mac Ewen Ltd",
    "wof:placetype":"venue"
},
  "geometry": {"coordinates":[-63.1919937134,46.2538566589],"type":"Point"}
}