{
  "type": "Feature",
  "properties": {
    "addr:full":"113 Arsini St E Russell MB R0J 1W0",
    "addr:housenumber":"113",
    "addr:postcode":"r0j 1w0",
    "addr:street":"Arsini St E",
    "iso:country":"CA",
    "sg:address":"113 Arsini St E",
    "sg:city":"Russell",
    "sg:classifiers":[
        {
            "category":"Health Services",
            "subcategory":"Nursing And Care Facility",
            "type":"Services"
        }
    ],
    "sg:phone":"+1 204 773 3117",
    "sg:postcode":"R0J 1W0",
    "sg:province":"MB",
    "sg:tags":[
        "personal",
        "home"
    ],
    "wof:name":"Russell Health Svc",
    "wof:placetype":"venue"
},
  "geometry": {"coordinates":[-101.288269043,50.7731285095],"type":"Point"}
}