{
  "type": "Feature",
  "properties": {
    "addr:full":"4000 Rue Steinberg Saint-Laurent QC H4R 2G7",
    "addr:housenumber":"4000",
    "addr:postcode":"h4r 2g7",
    "addr:street":"Rue Steinberg",
    "iso:country":"CA",
    "sg:address":"4000 Rue Steinberg",
    "sg:city":"Saint-Laurent",
    "sg:classifiers":[
        {
            "category":"Shopping",
            "subcategory":"Computers & Home Electronics",
            "type":"Retail Goods"
        }
    ],
    "sg:phone":"+1 514 745 4010",
    "sg:postcode":"H4R 2G7",
    "sg:province":"QC",
    "sg:tags":[
        "software"
    ],
    "wof:name":"Bnh Expert Software Inc",
    "wof:placetype":"venue"
},
  "geometry": {"coordinates":[-73.724648,45.497547],"type":"Point"}
}