{
  "type": "Feature",
  "properties": {
    "addr:full":"120 Villarboit Cres Concord ON L4K 4K2",
    "addr:housenumber":"120",
    "addr:postcode":"l4k 4k2",
    "addr:street":"Villarboit Cres",
    "iso:country":"CA",
    "sg:address":"120 Villarboit Cres",
    "sg:city":"Concord",
    "sg:classifiers":[
        {
            "category":"Home & Garden",
            "subcategory":"Home Furnishings",
            "type":"Retail Goods"
        }
    ],
    "sg:phone":"+1 905 669 5023",
    "sg:postcode":"L4K 4K2",
    "sg:province":"ON",
    "sg:tags":[
        "bathroom",
        "fixture",
        "marble"
    ],
    "wof:name":"State Marble Ltd",
    "wof:placetype":"venue"
},
  "geometry": {"coordinates":[-79.494827,43.827045],"type":"Point"}
}