{
  "type": "Feature",
  "properties": {
    "addr:full":"2140 Pumphouse Ave SW Calgary AB T3C 3P5",
    "addr:housenumber":"2140",
    "addr:postcode":"t3c 3p5",
    "addr:street":"Pumphouse Ave Sw",
    "iso:country":"CA",
    "sg:address":"2140 Pumphouse Ave SW",
    "sg:city":"Calgary",
    "sg:classifiers":[
        {
            "category":"Arts & Performance",
            "subcategory":"Theater",
            "type":"Entertainment"
        }
    ],
    "sg:phone":"+1 403 263 0079",
    "sg:postcode":"T3C 3P5",
    "sg:province":"AB",
    "wof:name":"Pumphouse Theatre",
    "wof:placetype":"venue"
},
  "geometry": {"coordinates":[-114.10805499999999,51.045689],"type":"Point"}
}