{
  "type": "Feature",
  "properties": {
    "iso:country":"CA",
    "sg:city":"Vancouver",
    "sg:classifiers":[
        {
            "category":"Manufacturing",
            "subcategory":"Apparel",
            "type":"Manufacturing & Wholesale Goods"
        }
    ],
    "sg:phone":"+1 604 879 8801",
    "sg:postcode":"V5Y 1K6",
    "sg:province":"BC",
    "sg:tags":[
        "clothing"
    ],
    "wof:name":"Wing Wing Garments Ltd",
    "wof:placetype":"venue"
},
  "geometry": {"coordinates":[-123.107414,49.265495],"type":"Point"}
}