{
  "type": "Feature",
  "properties": {
    "addr:full":"320 3rd Ave N Champion AB T0L 0R0",
    "addr:housenumber":"320",
    "addr:postcode":"t0l 0r0",
    "addr:street":"3Rd Ave N",
    "iso:country":"CA",
    "sg:address":"320 3rd Ave N",
    "sg:city":"Champion",
    "sg:classifiers":[
        {
            "category":"Education",
            "subcategory":"School",
            "type":"Public Place"
        }
    ],
    "sg:phone":"+1 403 897 3019",
    "sg:postcode":"T0L 0R0",
    "sg:province":"AB",
    "wof:name":"Hope Christian School",
    "wof:placetype":"venue"
},
  "geometry": {"coordinates":[-113.149704,50.243675],"type":"Point"}
}