{
  "type": "Feature",
  "properties": {
    "iso:country":"CA",
    "sg:city":"Burnaby",
    "sg:classifiers":[
        {
            "category":"Shopping",
            "subcategory":"Clothing, Apparel, & Fashions",
            "type":"Retail Goods"
        }
    ],
    "sg:phone":"+1 604 434 2429",
    "sg:postcode":"V5H 4M1",
    "sg:province":"BC",
    "sg:tags":[
        "tailor"
    ],
    "wof:name":"Stitch International",
    "wof:placetype":"venue"
},
  "geometry": {"coordinates":[-122.999435,49.228325],"type":"Point"}
}