{
  "type": "Feature",
  "properties": {
    "iso:country":"CA",
    "sg:address":"3504 51 St NW",
    "sg:city":"Edmonton",
    "sg:classifiers":[
        {
            "category":"Wholesale",
            "subcategory":"Electrical",
            "type":"Manufacturing & Wholesale Goods"
        }
    ],
    "sg:phone":"+1 780 414 0282",
    "sg:postcode":"T6L 1C6",
    "sg:province":"AB",
    "sg:tags":[
        "communication",
        "radio",
        "system"
    ],
    "wof:name":"Credibility Inc",
    "wof:placetype":"venue"
},
  "geometry": {"coordinates":[-113.419387817,53.4681549072],"type":"Point"}
}