{
  "type": "Feature",
  "properties": {
    "addr:full":"245 Boul Lachapelle Saint-Jerome QC J7Z 7L2",
    "addr:housenumber":"245",
    "addr:postcode":"j7z 7l2",
    "addr:street":"Boul Lachapelle Saint-Jerome",
    "iso:country":"CA",
    "sg:address":"245 Boul Lachapelle",
    "sg:city":"Saint-Jerome",
    "sg:classifiers":[
        {
            "category":"Organizations",
            "subcategory":"Professional Association",
            "type":"Services"
        }
    ],
    "sg:phone":"+1 450 438 2831",
    "sg:postcode":"J7Z 7L2",
    "sg:province":"QC",
    "sg:tags":[
        "club"
    ],
    "wof:name":"Club Optimiste St-Antoine Inc",
    "wof:placetype":"venue"
},
  "geometry": {"coordinates":[-73.99611663819999,45.7564125061],"type":"Point"}
}