{
  "type": "Feature",
  "properties": {
    "addr:full":"Vancouver BC V6A 1S9",
    "addr:postcode":"v6a 1s9",
    "iso:country":"CA",
    "sg:city":"Vancouver",
    "sg:classifiers":[
        {
            "category":"Banks & Credit Unions",
            "subcategory":"Investment Brokerage",
            "type":"Services"
        }
    ],
    "sg:phone":"+1 604 682 4695",
    "sg:postcode":"V6A 1S9",
    "sg:province":"BC",
    "sg:tags":[
        "consultant",
        "planning",
        "financial"
    ],
    "wof:name":"Wilco Consulting CO",
    "wof:placetype":"venue"
},
  "geometry": {"coordinates":[-123.10269165,49.2805747986],"type":"Point"}
}