{
  "type": "Feature",
  "properties": {
    "iso:country":"CA",
    "sg:address":"1220 Davie St",
    "sg:city":"Vancouver",
    "sg:classifiers":[
        {
            "category":"Restaurant",
            "type":"Food & Drink"
        }
    ],
    "sg:phone":"+1 604 688 3442",
    "sg:postcode":"V6E 1N3",
    "sg:province":"BC",
    "sg:tags":[
        "delicatessen"
    ],
    "wof:name":"European Delicatessen",
    "wof:placetype":"venue"
},
  "geometry": {"coordinates":[-123.13395690900001,49.2819824219],"type":"Point"}
}