{
  "type": "Feature",
  "properties": {
    "addr:full":"Calgary AB T3A 5K8",
    "addr:postcode":"t3a 5k8",
    "iso:country":"CA",
    "sg:city":"Calgary",
    "sg:classifiers":[
        {
            "category":"Real Estate",
            "subcategory":"Real Estate Agent",
            "type":"Services"
        }
    ],
    "sg:phone":"+1 403 547 8987",
    "sg:postcode":"T3A 5K8",
    "sg:province":"AB",
    "wof:name":"Ewing Properties",
    "wof:placetype":"venue"
},
  "geometry": {"coordinates":[-114.159759522,51.1385574341],"type":"Point"}
}