{
  "type": "Feature",
  "properties": {
    "addr:full":"3503 Boul Saint-Martin O Laval QC H7T 1A2",
    "addr:housenumber":"3503",
    "addr:postcode":"h7t 1a2",
    "addr:street":"Boul Saint-Martin O",
    "iso:country":"CA",
    "sg:address":"3503 Boul Saint-Martin O",
    "sg:city":"Laval",
    "sg:classifiers":[
        {
            "category":"Personal",
            "subcategory":"Beauty Salon",
            "type":"Services"
        }
    ],
    "sg:phone":"+1 450 682 7627",
    "sg:postcode":"H7T 1A2",
    "sg:province":"QC",
    "wof:name":"Coiffure Concept 2",
    "wof:placetype":"venue"
},
  "geometry": {"coordinates":[-73.752556,45.555157],"type":"Point"}
}