{
  "type": "Feature",
  "properties": {
    "addr:full":"124 Mcphillips Ave Salt Spring Island BC V8K 2T5",
    "addr:housenumber":"124",
    "addr:postcode":"v8k 2t5",
    "addr:street":"Mcphillips Ave",
    "iso:country":"CA",
    "sg:address":"124 Mcphillips Ave",
    "sg:city":"Salt Spring Island",
    "sg:classifiers":[
        {
            "category":"Banks & Credit Unions",
            "subcategory":"Investment Brokerage",
            "type":"Services"
        }
    ],
    "sg:phone":"+1 250 537 8868",
    "sg:postcode":"V8K 2T5",
    "sg:province":"BC",
    "sg:tags":[
        "consultant",
        "planning",
        "financial"
    ],
    "wof:name":"Credential Securities",
    "wof:placetype":"venue"
},
  "geometry": {"coordinates":[-123.501389,48.852798],"type":"Point"}
}