{
  "type": "Feature",
  "properties": {
    "iso:country":"CA",
    "sg:city":"Alberton",
    "sg:classifiers":[
        {
            "category":"Food & Beverages",
            "subcategory":"Meat & Fish",
            "type":"Retail Goods"
        }
    ],
    "sg:phone":"+1 902 853 4088",
    "sg:postcode":"C0B 1B0",
    "sg:province":"PE",
    "sg:tags":[
        "seafood"
    ],
    "wof:name":"Kildare Fisheries Ltd",
    "wof:placetype":"venue"
},
  "geometry": {"coordinates":[-64.065322876,46.8134651184],"type":"Point"}
}