{
  "type": "Feature",
  "properties": {
    "addr:full":"Edmonton AB T5K 2J8",
    "addr:postcode":"t5k 2j8",
    "iso:country":"CA",
    "sg:city":"Edmonton",
    "sg:classifiers":[
        {
            "category":"Professional",
            "subcategory":"Research",
            "type":"Services"
        }
    ],
    "sg:phone":"+1 780 702 0200",
    "sg:postcode":"T5K 2J8",
    "sg:province":"AB",
    "sg:tags":[
        "development",
        "laboratory"
    ],
    "wof:name":"Breast Cancer Intl Research",
    "wof:placetype":"venue"
},
  "geometry": {"coordinates":[-113.50829299999999,53.537724],"type":"Point"}
}