{
  "type": "Feature",
  "properties": {
    "addr:full":"142 Victoria St Truro NS B2N 1Z1",
    "addr:housenumber":"142",
    "addr:postcode":"b2n 1z1",
    "addr:street":"Victoria St",
    "iso:country":"CA",
    "sg:address":"142 Victoria St",
    "sg:city":"Truro",
    "sg:classifiers":[
        {
            "category":"Professional",
            "subcategory":"Business Services",
            "type":"Services"
        }
    ],
    "sg:phone":"+1 902 895 1711",
    "sg:postcode":"B2N 1Z1",
    "sg:province":"NS",
    "sg:tags":[
        "paging",
        "answering"
    ],
    "wof:name":"Truro Answering Svc",
    "wof:placetype":"venue"
},
  "geometry": {"coordinates":[-63.280166626,45.362827301],"type":"Point"}
}