{
  "type": "Feature",
  "properties": {
    "addr:full":"2500 Meadowpine Blvd #3 Mississauga ON L5N 6C4",
    "addr:housenumber":"2500",
    "addr:postcode":"l5n 6c4",
    "addr:street":"Meadowpine Blvd # 3",
    "iso:country":"CA",
    "sg:address":"2500 Meadowpine Blvd #3",
    "sg:city":"Mississauga",
    "sg:classifiers":[
        {
            "category":"Wholesale",
            "subcategory":"Machinery & Supplies",
            "type":"Manufacturing & Wholesale Goods"
        }
    ],
    "sg:phone":"+1 905 826 1089",
    "sg:postcode":"L5N 6C4",
    "sg:province":"ON",
    "sg:tags":[
        "baker"
    ],
    "wof:name":"Aic Canada Flour Svc",
    "wof:placetype":"venue"
},
  "geometry": {"coordinates":[-79.77570299999999,43.603626],"type":"Point"}
}