{
  "type": "Feature",
  "properties": {
    "addr:full":"863 Jane St York ON M6N 4C4",
    "addr:housenumber":"863",
    "addr:postcode":"m6n 4c4",
    "addr:street":"Jane St",
    "iso:country":"CA",
    "sg:address":"863 Jane St",
    "sg:city":"York",
    "sg:classifiers":[
        {
            "category":"Retail",
            "subcategory":"Laundry & Dry Cleaning",
            "type":"Services"
        }
    ],
    "sg:phone":"+1 416 763 1633",
    "sg:postcode":"M6N 4C4",
    "sg:province":"ON",
    "sg:tags":[
        "cleaners"
    ],
    "wof:name":"Jane Park Plaza Cleaners",
    "wof:placetype":"venue"
},
  "geometry": {"coordinates":[-79.4956893921,43.6766815186],"type":"Point"}
}