{
  "type": "Feature",
  "properties": {
    "addr:full":"4289 Boul Saint-Jean Dollard-Des-Ormeaux QC H9G 2R4",
    "addr:housenumber":"4289",
    "addr:postcode":"h9g 2r4",
    "addr:street":"Boul Saint-Jean",
    "iso:country":"CA",
    "sg:address":"4289 Boul Saint-Jean",
    "sg:city":"Dollard-Des-Ormeaux",
    "sg:classifiers":[
        {
            "category":"Restaurant",
            "type":"Food & Drink"
        }
    ],
    "sg:phone":"+1 514 620 6143",
    "sg:postcode":"H9G 2R4",
    "sg:province":"QC",
    "wof:name":"Dagwoods Sandwichs & Salads",
    "wof:placetype":"venue"
},
  "geometry": {"coordinates":[-73.841194,45.47982],"type":"Point"}
}