{
  "type": "Feature",
  "properties": {
    "iso:country":"CA",
    "sg:address":"150 Rue St Catherine O # 709",
    "sg:city":"Montreal",
    "sg:classifiers":[
        {
            "category":"Shopping",
            "subcategory":"Photographic Equipment",
            "type":"Retail Goods"
        }
    ],
    "sg:phone":"+1 514 843 8219",
    "sg:postcode":"H5B 1B8",
    "sg:province":"QC",
    "sg:tags":[
        "supply"
    ],
    "wof:name":"Astral Photo",
    "wof:placetype":"venue"
},
  "geometry": {"coordinates":[-73.5625534058,45.5111656189],"type":"Point"}
}