{
  "type": "Feature",
  "properties": {
    "addr:full":"SW 28-7-14W & Hwy 5 Glenboro MB R0K 0X0",
    "addr:postcode":"r0k 0x0",
    "addr:street":"Sw;& Hwy 5 Glenboro",
    "iso:country":"CA",
    "sg:address":"SW 28-7-14W & Hwy 5",
    "sg:city":"Glenboro",
    "sg:classifiers":[
        {
            "category":"Travel",
            "subcategory":"Hotels & Motels",
            "type":"Entertainment"
        }
    ],
    "sg:phone":"+1 204 827 2607",
    "sg:postcode":"R0K 0X0",
    "sg:province":"MB",
    "sg:tags":[
        "campground",
        "resort"
    ],
    "wof:name":"Spirits Sands Lodging",
    "wof:placetype":"venue"
},
  "geometry": {"coordinates":[-99.290207,49.558319],"type":"Point"}
}