{
  "type": "Feature",
  "properties": {
    "iso:country":"CA",
    "sg:city":"Fort-Coulonge",
    "sg:classifiers":[
        {
            "category":"Communications",
            "subcategory":"Radio Station",
            "type":"Services"
        }
    ],
    "sg:phone":"+1 819 683 3155",
    "sg:postcode":"J0X 1V0",
    "sg:province":"QC",
    "sg:tags":[
        "company",
        "broadcasting"
    ],
    "wof:name":"Radio Du Pontiac Chip FM",
    "wof:placetype":"venue"
},
  "geometry": {"coordinates":[-76.7392425537,45.8430175781],"type":"Point"}
}