{
  "type": "Feature",
  "properties": {
    "addr:full":"37 Main St Chesterville ON K0C 1H0",
    "addr:housenumber":"37",
    "addr:postcode":"k0c 1h0",
    "addr:street":"Main St",
    "iso:country":"CA",
    "sg:address":"37 Main St",
    "sg:city":"Chesterville",
    "sg:classifiers":[
        {
            "category":"Education",
            "subcategory":"School",
            "type":"Public Place"
        }
    ],
    "sg:phone":"+1 613 448 2158",
    "sg:postcode":"K0C 1H0",
    "sg:province":"ON",
    "wof:name":"St Mary's Catholic School",
    "wof:placetype":"venue"
},
  "geometry": {"coordinates":[-75.22997283940001,45.1031951904],"type":"Point"}
}