{
  "type": "Feature",
  "properties": {
    "addr:full":"88 Erskine Ave Toronto ON M4P 1Y3",
    "addr:housenumber":"88",
    "addr:postcode":"m4p 1y3",
    "addr:street":"Erskine Ave",
    "iso:country":"CA",
    "sg:address":"88 Erskine Ave",
    "sg:city":"Toronto",
    "sg:classifiers":[
        {
            "category":"Real Estate",
            "subcategory":"Real Estate Operator",
            "type":"Services"
        }
    ],
    "sg:phone":"+1 416 481 5646",
    "sg:postcode":"M4P 1Y3",
    "sg:province":"ON",
    "sg:tags":[
        "apartment"
    ],
    "wof:name":"Erskine Green",
    "wof:placetype":"venue"
},
  "geometry": {"coordinates":[-79.39604199999999,43.711864],"type":"Point"}
}