{
  "type": "Feature",
  "properties": {
    "addr:full":"2700 Broadway W Vancouver BC V6K 2G4",
    "addr:housenumber":"2700",
    "addr:postcode":"v6k 2g4",
    "addr:street":"Broadway W",
    "iso:country":"CA",
    "sg:address":"2700 Broadway W",
    "sg:city":"Vancouver",
    "sg:classifiers":[
        {
            "category":"Shopping",
            "subcategory":"Clothing, Apparel, & Fashions",
            "type":"Retail Goods"
        }
    ],
    "sg:phone":"+1 604 733 7332",
    "sg:postcode":"V6K 2G4",
    "sg:province":"BC",
    "wof:name":"Serena Fashions Ltd",
    "wof:placetype":"venue"
},
  "geometry": {"coordinates":[-123.166557,49.263939],"type":"Point"}
}