{
  "type": "Feature",
  "properties": {
    "addr:full":"24 Mews Pl St. John's NL A1B 4M3",
    "addr:housenumber":"24",
    "addr:postcode":"a1b 4m3",
    "addr:street":"Mews Pl",
    "iso:country":"CA",
    "sg:address":"24 Mews Pl",
    "sg:city":"St. John's",
    "sg:classifiers":[
        {
            "category":"Building & Trades",
            "subcategory":"Electrical",
            "type":"Services"
        }
    ],
    "sg:phone":"+1 709 722 6220",
    "sg:postcode":"A1B 4M3",
    "sg:province":"NL",
    "sg:tags":[
        "electric",
        "contractor"
    ],
    "wof:name":"Bayview Electrical Ltd",
    "wof:placetype":"venue"
},
  "geometry": {"coordinates":[-52.773765564,47.5606193542],"type":"Point"}
}