{
  "type": "Feature",
  "properties": {
    "addr:full":"1871 O'Connor Dr North York ON M4A 1X1",
    "addr:housenumber":"1871",
    "addr:postcode":"m4a 1x1",
    "addr:street":"O'Connor Dr",
    "iso:country":"CA",
    "sg:address":"1871 O'Connor Dr",
    "sg:city":"North York",
    "sg:classifiers":[
        {
            "category":"Restaurant",
            "type":"Food & Drink"
        }
    ],
    "sg:phone":"+1 416 752 7091",
    "sg:postcode":"M4A 1X1",
    "sg:province":"ON",
    "wof:name":"Pizza Hut",
    "wof:placetype":"venue"
},
  "geometry": {"coordinates":[-79.353553772,43.6924667358],"type":"Point"}
}