{
  "type": "Feature",
  "properties": {
    "addr:full":"236 Briar Ave Kamloops BC V2B 1C1",
    "addr:housenumber":"236",
    "addr:postcode":"bc v2b 1c1",
    "addr:street":"Briar Ave",
    "iso:country":"CA",
    "sg:address":"236 Briar Ave",
    "sg:city":"Kamloops",
    "sg:classifiers":[
        {
            "category":"Wholesale",
            "subcategory":"Groceries",
            "type":"Manufacturing & Wholesale Goods"
        }
    ],
    "sg:phone":"+1 250 376 1117",
    "sg:postcode":"V2B 1C1",
    "sg:province":"BC",
    "sg:tags":[
        "food",
        "product",
        "manufacturer"
    ],
    "wof:name":"European Bakery",
    "wof:placetype":"venue"
},
  "geometry": {"coordinates":[-120.35446167000001,50.6861610413],"type":"Point"}
}