{
  "type": "Feature",
  "properties": {
    "addr:full":"Bridgewater NS B4V 1W8",
    "addr:postcode":"b4v 1w8",
    "iso:country":"CA",
    "sg:city":"Bridgewater",
    "sg:classifiers":[
        {
            "category":"Food & Beverages",
            "subcategory":"Meat & Fish",
            "type":"Retail Goods"
        }
    ],
    "sg:phone":"+1 902 543 2441",
    "sg:postcode":"B4V 1W8",
    "sg:province":"NS",
    "sg:tags":[
        "sausage"
    ],
    "wof:name":"Lunenburg Pudding & Sausage",
    "wof:placetype":"venue"
},
  "geometry": {"coordinates":[-64.523033,44.380489],"type":"Point"}
}