{
  "type": "Feature",
  "properties": {
    "addr:full":"467 Emily Park Rd Omemee ON K0L 2W0",
    "addr:housenumber":"467",
    "addr:postcode":"k0l 2w0",
    "addr:street":"Emily Park Rd",
    "iso:country":"CA",
    "sg:address":"467 Emily Park Rd",
    "sg:city":"Omemee",
    "sg:classifiers":[
        {
            "category":"Building & Trades",
            "subcategory":"Construction",
            "type":"Services"
        }
    ],
    "sg:phone":"+1 705 799 5871",
    "sg:postcode":"K0L 2W0",
    "sg:province":"ON",
    "sg:tags":[
        "water",
        "well",
        "drilling"
    ],
    "wof:name":"William Burgess & Son Drilling",
    "wof:placetype":"venue"
},
  "geometry": {"coordinates":[-78.51997375489999,44.3132820129],"type":"Point"}
}