{
  "type": "Feature",
  "properties": {
    "addr:full":"Courtenay BC V9N 7S7",
    "addr:postcode":"v9n 7s7",
    "iso:country":"CA",
    "sg:city":"Courtenay",
    "sg:classifiers":[
        {
            "category":"Home & Garden",
            "subcategory":"Carpets & Floor Coverings",
            "type":"Retail Goods"
        }
    ],
    "sg:phone":"+1 250 338 5747",
    "sg:postcode":"V9N 7S7",
    "sg:province":"BC",
    "wof:name":"Superior Carpets & Drapery Ltd",
    "wof:placetype":"venue"
},
  "geometry": {"coordinates":[-124.984261,49.669666],"type":"Point"}
}