{
  "type": "Feature",
  "properties": {
    "addr:full":"Victoria BC V8W 3G3",
    "addr:postcode":"v8w 3g3",
    "iso:country":"CA",
    "sg:city":"Victoria",
    "sg:classifiers":[
        {
            "category":"Real Estate",
            "subcategory":"Real Estate Agent",
            "type":"Services"
        }
    ],
    "sg:phone":"+1 250 386 6071",
    "sg:postcode":"V8W 3G3",
    "sg:province":"BC",
    "wof:name":"Equitex Realty & Management",
    "wof:placetype":"venue"
},
  "geometry": {"coordinates":[-123.365005,48.424351],"type":"Point"}
}