{
  "type": "Feature",
  "properties": {
    "addr:full":"119 Rue Wallenberg Dollard-Des-Ormeaux QC H9A 3G2",
    "addr:housenumber":"119",
    "addr:postcode":"h9a 3g2",
    "addr:street":"Rue Wallenberg",
    "iso:country":"CA",
    "sg:address":"119 Rue Wallenberg",
    "sg:city":"Dollard-Des-Ormeaux",
    "sg:classifiers":[
        {
            "category":"Professional",
            "subcategory":"Art Services",
            "type":"Services"
        }
    ],
    "sg:phone":"+1 514 696 5477",
    "sg:postcode":"H9A 3G2",
    "sg:province":"QC",
    "sg:tags":[
        "production",
        "layout",
        "advertising"
    ],
    "wof:name":"Auriga Productions Ltee",
    "wof:placetype":"venue"
},
  "geometry": {"coordinates":[-73.836349,45.487659],"type":"Point"}
}