{
  "type": "Feature",
  "properties": {
    "addr:full":"7015 120 St Delta BC V4E 2A9",
    "addr:housenumber":"7015",
    "addr:postcode":"v4e 2a9",
    "addr:street":"120 St",
    "iso:country":"CA",
    "sg:address":"7015 120 St",
    "sg:city":"Delta",
    "sg:classifiers":[
        {
            "category":"Food & Beverages",
            "subcategory":"Groceries & Convenience Stores",
            "type":"Retail Goods"
        }
    ],
    "sg:phone":"+1 604 596 2944",
    "sg:postcode":"V4E 2A9",
    "sg:province":"BC",
    "sg:tags":[
        "grocer"
    ],
    "wof:name":"Save-On-Foods & Drugs",
    "wof:placetype":"venue"
},
  "geometry": {"coordinates":[-122.890556,49.130909],"type":"Point"}
}