{
  "type": "Feature",
  "properties": {
    "addr:full":"4634 11 St NE Calgary AB T2E 2W7",
    "addr:housenumber":"4634",
    "addr:postcode":"t2e 2w7",
    "addr:street":"11 St Ne",
    "iso:country":"CA",
    "sg:address":"4634 11 St NE",
    "sg:city":"Calgary",
    "sg:classifiers":[
        {
            "category":"Wholesale",
            "subcategory":"Machinery & Supplies",
            "type":"Manufacturing & Wholesale Goods"
        }
    ],
    "sg:phone":"+1 403 250 7657",
    "sg:postcode":"T2E 2W7",
    "sg:province":"AB",
    "sg:tags":[
        "concrete",
        "equipment"
    ],
    "wof:name":"A Galka Agencies",
    "wof:placetype":"venue"
},
  "geometry": {"coordinates":[-114.036537,51.093796],"type":"Point"}
}