{
  "type": "Feature",
  "properties": {
    "addr:full":"325 Blessington Rd Corbyville ON K0K 1V0",
    "addr:housenumber":"325",
    "addr:postcode":"k0k 1v0",
    "addr:street":"Blessington Rd",
    "iso:country":"CA",
    "sg:address":"325 Blessington Rd",
    "sg:city":"Corbyville",
    "sg:classifiers":[
        {
            "category":"Building & Trades",
            "subcategory":"Pest Control",
            "type":"Services"
        }
    ],
    "sg:phone":"+1 613 969 7032",
    "sg:postcode":"K0K 1V0",
    "sg:province":"ON",
    "wof:name":"Complete Pest Control",
    "wof:placetype":"venue"
},
  "geometry": {"coordinates":[-77.388329,44.219978],"type":"Point"}
}