{
  "type": "Feature",
  "properties": {
    "iso:country":"CA",
    "sg:address":"1483 Dundas St W",
    "sg:city":"Toronto",
    "sg:classifiers":[
        {
            "category":"Shopping",
            "subcategory":"Optical Goods",
            "type":"Retail Goods"
        }
    ],
    "sg:phone":"+1 416 532 3351",
    "sg:postcode":"M6J 1Y8",
    "sg:province":"ON",
    "sg:tags":[
        "optician"
    ],
    "wof:name":"Hakim Optical Factory Outlet",
    "wof:placetype":"venue"
},
  "geometry": {"coordinates":[-79.4313583374,43.6495819092],"type":"Point"}
}