{
  "type": "Feature",
  "properties": {
    "addr:full":"181 Cross St E Dunnville ON N1A 1B7",
    "addr:housenumber":"181",
    "addr:postcode":"n1a 1b7",
    "addr:street":"Cross St E",
    "iso:country":"CA",
    "sg:address":"181 Cross St E",
    "sg:city":"Dunnville",
    "sg:classifiers":[
        {
            "category":"Organizations",
            "subcategory":"Religious Organization",
            "type":"Services"
        }
    ],
    "sg:phone":"+1 905 774 5111",
    "sg:postcode":"N1A 1B7",
    "sg:province":"ON",
    "sg:tags":[
        "church"
    ],
    "wof:name":"Free Methodist Church",
    "wof:placetype":"venue"
},
  "geometry": {"coordinates":[-79.612213,42.907227],"type":"Point"}
}