{
  "type": "Feature",
  "properties": {
    "addr:full":"Vancouver BC V6A 1R2",
    "addr:postcode":"v6a 1r2",
    "iso:country":"CA",
    "sg:city":"Vancouver",
    "sg:classifiers":[
        {
            "category":"Travel",
            "subcategory":"Hotels & Motels",
            "type":"Entertainment"
        }
    ],
    "sg:phone":"+1 604 255 3769",
    "sg:postcode":"V6A 1R2",
    "sg:province":"BC",
    "wof:name":"Shamrock Hotel",
    "wof:placetype":"venue"
},
  "geometry": {"coordinates":[-123.090675354,49.2812843323],"type":"Point"}
}