{
  "type": "Feature",
  "properties": {
    "addr:full":"31 Pemberton Rd Richmond Hill ON L4C 3T5",
    "addr:housenumber":"31",
    "addr:postcode":"l4c 3t5",
    "addr:street":"Pemberton Rd",
    "iso:country":"CA",
    "sg:address":"31 Pemberton Rd",
    "sg:city":"Richmond Hill",
    "sg:classifiers":[
        {
            "category":"Building & Trades",
            "subcategory":"Landscaping Services",
            "type":"Services"
        }
    ],
    "sg:phone":"+1 905 884 4121",
    "sg:postcode":"L4C 3T5",
    "sg:province":"ON",
    "sg:tags":[
        "landscape",
        "contractor"
    ],
    "wof:name":"Boot's Landscaping & Mntnc Ltd",
    "wof:placetype":"venue"
},
  "geometry": {"coordinates":[-79.4493942261,43.8594093323],"type":"Point"}
}