{
  "type": "Feature",
  "properties": {
    "addr:full":"Walkerton ON N0G 2V0",
    "addr:postcode":"n0g 2v0",
    "addr:street":"Walkerton",
    "iso:country":"CA",
    "sg:city":"Walkerton",
    "sg:classifiers":[
        {
            "category":"Retail",
            "subcategory":"Auto Repair",
            "type":"Services"
        }
    ],
    "sg:phone":"+1 519 881 3040",
    "sg:postcode":"N0G 2V0",
    "sg:province":"ON",
    "sg:tags":[
        "equipment",
        "parts",
        "truck"
    ],
    "wof:name":"A & M Truck Parts Ltd",
    "wof:placetype":"venue"
},
  "geometry": {"coordinates":[-81.1480484009,44.1342849731],"type":"Point"}
}