{
  "type": "Feature",
  "properties": {
    "addr:full":"615 Anderson Ave Theodore SK S0A 4C0",
    "addr:housenumber":"615",
    "addr:postcode":"s0a 4c0",
    "addr:street":"Anderson Ave",
    "iso:country":"CA",
    "sg:address":"615 Anderson Ave",
    "sg:city":"Theodore",
    "sg:classifiers":[
        {
            "category":"Health Services",
            "subcategory":"Nursing And Care Facility",
            "type":"Services"
        }
    ],
    "sg:phone":"+1 306 647 2115",
    "sg:postcode":"S0A 4C0",
    "sg:province":"SK",
    "sg:tags":[
        "home",
        "convalescent"
    ],
    "wof:name":"Theodore Health Ctr",
    "wof:placetype":"venue"
},
  "geometry": {"coordinates":[-102.92276,51.424477],"type":"Point"}
}