{
  "type": "Feature",
  "properties": {
    "addr:full":"Lakeview Rd Atikokan ON P0T 1C0",
    "addr:postcode":"p0t 1c0",
    "addr:street":"Lakeview Rd",
    "iso:country":"CA",
    "sg:address":"Lakeview Rd",
    "sg:city":"Atikokan",
    "sg:classifiers":[
        {
            "category":"Travel",
            "subcategory":"Hotels & Motels",
            "type":"Entertainment"
        }
    ],
    "sg:phone":"+1 807 929 1156",
    "sg:postcode":"P0T 1C0",
    "sg:province":"ON",
    "sg:tags":[
        "campground",
        "resort"
    ],
    "wof:name":"Crystal Beach Resort",
    "wof:placetype":"venue"
},
  "geometry": {"coordinates":[-91.592873,48.759232],"type":"Point"}
}