{
  "type": "Feature",
  "properties": {
    "addr:full":"1845 Rue Antonio-Barbeau Laval QC H7M 4C2",
    "addr:housenumber":"1845",
    "addr:postcode":"h7m 4c2",
    "addr:street":"Rue Antonio-Barbeau",
    "iso:country":"CA",
    "sg:address":"1845 Rue Antonio-Barbeau",
    "sg:city":"Laval",
    "sg:classifiers":[
        {
            "category":"Health Services",
            "subcategory":"Doctor",
            "type":"Services"
        }
    ],
    "sg:phone":"+1 450 663 6643",
    "sg:postcode":"H7M 4C2",
    "sg:province":"QC",
    "sg:tags":[
        "clinic"
    ],
    "wof:name":"Christian Laflamme Denturologi",
    "wof:placetype":"venue"
},
  "geometry": {"coordinates":[-73.7096939087,45.6100311279],"type":"Point"}
}