{
  "type": "Feature",
  "properties": {
    "addr:full":"128 Germain St Saint John NB E2L 2E7",
    "addr:housenumber":"128",
    "addr:postcode":"nb e2l 2e7",
    "addr:street":"Germain St",
    "iso:country":"CA",
    "sg:address":"128 Germain St",
    "sg:city":"Saint John",
    "sg:classifiers":[
        {
            "category":"Shopping",
            "type":"Retail Goods"
        }
    ],
    "sg:phone":"+1 506 634 1611",
    "sg:postcode":"E2L 2E7",
    "sg:province":"NB",
    "sg:tags":[
        "art",
        "gallery",
        "dealer"
    ],
    "wof:name":"Trinity Galleries",
    "wof:placetype":"venue"
},
  "geometry": {"coordinates":[-66.0600204468,45.2719573975],"type":"Point"}
}