{
  "type": "Feature",
  "properties": {
    "addr:full":"Surrey BC V4P 1J6",
    "addr:postcode":"v4p 1j6",
    "iso:country":"CA",
    "sg:city":"Surrey",
    "sg:classifiers":[
        {
            "category":"Food & Beverages",
            "subcategory":"Bakery",
            "type":"Retail Goods"
        }
    ],
    "sg:phone":"+1 604 531 7880",
    "sg:postcode":"V4P 1J6",
    "sg:province":"BC",
    "sg:tags":[
        "baker"
    ],
    "wof:name":"Fieldstone Artisan Breads",
    "wof:placetype":"venue"
},
  "geometry": {"coordinates":[-122.866539002,49.0532684326],"type":"Point"}
}