{
  "type": "Feature",
  "properties": {
    "addr:full":"1687 Montreal Rd Gloucester ON K1J 6N6",
    "addr:housenumber":"1687",
    "addr:postcode":"k1j 6n6",
    "addr:street":"Montreal Rd",
    "iso:country":"CA",
    "sg:address":"1687 Montreal Rd",
    "sg:city":"Gloucester",
    "sg:classifiers":[
        {
            "category":"Restaurant",
            "type":"Food & Drink"
        }
    ],
    "sg:phone":"+1 613 746 9511",
    "sg:postcode":"K1J 6N6",
    "sg:province":"ON",
    "wof:name":"Kfc",
    "wof:placetype":"venue"
},
  "geometry": {"coordinates":[-75.612961,45.44648],"type":"Point"}
}