{
  "type": "Feature",
  "properties": {
    "addr:full":"1 Weston Crt Dartmouth NS B3B 2C8",
    "addr:housenumber":"1",
    "addr:postcode":"b3b 2c8",
    "addr:street":"Weston Crt",
    "iso:country":"CA",
    "sg:address":"1 Weston Crt",
    "sg:city":"Dartmouth",
    "sg:classifiers":[
        {
            "category":"Manufacturing",
            "subcategory":"Metals",
            "type":"Manufacturing & Wholesale Goods"
        }
    ],
    "sg:phone":"+1 902 468 7191",
    "sg:postcode":"B3B 2C8",
    "sg:province":"NS",
    "sg:tags":[
        "fabricator",
        "aluminum"
    ],
    "wof:name":"Weld-Pro Ltd",
    "wof:placetype":"venue"
},
  "geometry": {"coordinates":[-63.5835609436,44.7133255005],"type":"Point"}
}