{
  "type": "Feature",
  "properties": {
    "addr:full":"1069 Northwest Rd Denman Island BC V0R 1T0",
    "addr:housenumber":"1069",
    "addr:postcode":"v0r 1t0",
    "addr:street":"Northwest Rd",
    "iso:country":"CA",
    "sg:address":"1069 Northwest Rd",
    "sg:city":"Denman Island",
    "sg:classifiers":[
        {
            "category":"Restaurant",
            "type":"Food & Drink"
        }
    ],
    "sg:phone":"+1 250 335 2999",
    "sg:postcode":"V0R 1T0",
    "sg:province":"BC",
    "wof:name":"Denman Island Cafe",
    "wof:placetype":"venue"
},
  "geometry": {"coordinates":[-124.816917,49.53511],"type":"Point"}
}