{
  "type": "Feature",
  "properties": {
    "iso:country":"CA",
    "sg:address":"1525 Hyde Park Rd",
    "sg:city":"London",
    "sg:classifiers":[
        {
            "category":"Wholesale",
            "subcategory":"Hardware",
            "type":"Manufacturing & Wholesale Goods"
        }
    ],
    "sg:phone":"+1 519 471 8093",
    "sg:postcode":"N6H 5L4",
    "sg:province":"ON",
    "sg:tags":[
        "plumbing",
        "fixture",
        "supply"
    ],
    "wof:name":"Tasc Sales",
    "wof:placetype":"venue"
},
  "geometry": {"coordinates":[-81.33112300000001,42.997189],"type":"Point"}
}