{
  "type": "Feature",
  "properties": {
    "addr:full":"7464 Rue Saint-Denis Montreal QC H2R 2E4",
    "addr:housenumber":"7464",
    "addr:postcode":"h2r 2e4",
    "addr:street":"Rue Saint-Denis",
    "iso:country":"CA",
    "sg:address":"7464 Rue Saint-Denis",
    "sg:city":"Montreal",
    "sg:classifiers":[
        {
            "category":"Health Services",
            "subcategory":"Health Practitioner",
            "type":"Services"
        }
    ],
    "sg:phone":"+1 514 490 9313",
    "sg:postcode":"H2R 2E4",
    "sg:province":"QC",
    "sg:tags":[
        "speech",
        "therapy",
        "hearing"
    ],
    "wof:name":"Tremblay, Chantale",
    "wof:placetype":"venue"
},
  "geometry": {"coordinates":[-73.6195526123,45.5396690369],"type":"Point"}
}