{
  "type": "Feature",
  "properties": {
    "iso:country":"CA",
    "sg:address":"250 Marion St",
    "sg:city":"Winnipeg",
    "sg:classifiers":[
        {
            "category":"Autos & Motor Vehicles",
            "subcategory":"Fuel & Gas Station",
            "type":"Retail Goods"
        }
    ],
    "sg:phone":"+1 204 231 9405",
    "sg:postcode":"R2H 0T7",
    "sg:province":"MB",
    "sg:tags":[
        "oil"
    ],
    "wof:name":"Marion Esso",
    "wof:placetype":"venue"
},
  "geometry": {"coordinates":[-97.11633300779999,49.8815612793],"type":"Point"}
}