{
  "type": "Feature",
  "properties": {
    "addr:full":"Drumheller AB T0J 0Y0",
    "addr:postcode":"t0j 0y0",
    "iso:country":"CA",
    "sg:city":"Drumheller",
    "sg:classifiers":[
        {
            "category":"Arts & Performance",
            "subcategory":"Theater",
            "type":"Entertainment"
        }
    ],
    "sg:phone":"+1 403 823 2001",
    "sg:postcode":"T0J 0Y0",
    "sg:province":"AB",
    "wof:name":"Canadian Badlands Passion Play",
    "wof:placetype":"venue"
},
  "geometry": {"coordinates":[-112.74762725799999,51.4627456665],"type":"Point"}
}