{
  "type": "Feature",
  "properties": {
    "iso:country":"CA",
    "sg:address":"501 St Mary's Rd",
    "sg:city":"Winnipeg",
    "sg:classifiers":[
        {
            "category":"Manufacturing",
            "subcategory":"Tools & Machinery",
            "type":"Manufacturing & Wholesale Goods"
        }
    ],
    "sg:phone":"+1 204 237 7631",
    "sg:postcode":"R2M 3L2",
    "sg:province":"MB",
    "sg:tags":[
        "machine",
        "duplicating",
        "copying"
    ],
    "wof:name":"Bio-Static Systems Ltd",
    "wof:placetype":"venue"
},
  "geometry": {"coordinates":[-97.151604,49.889118],"type":"Point"}
}