{
  "type": "Feature",
  "properties": {
    "iso:country":"CA",
    "sg:address":"19 Weatherhead Rd",
    "sg:city":"Upper Rawdon",
    "sg:classifiers":[
        {
            "category":"Manufacturing",
            "subcategory":"Tools & Machinery",
            "type":"Manufacturing & Wholesale Goods"
        }
    ],
    "sg:phone":"+1 902 632 2702",
    "sg:postcode":"B0N 2N0",
    "sg:province":"NS",
    "sg:tags":[
        "topsoil"
    ],
    "wof:name":"Weatherwood Products Ltd",
    "wof:placetype":"venue"
},
  "geometry": {"coordinates":[-63.7135734558,45.0664558411],"type":"Point"}
}