{
  "type": "Feature",
  "properties": {
    "addr:full":"1118 Richards St Vancouver BC V6B 3E6",
    "addr:housenumber":"1118",
    "addr:postcode":"bc v6b 3e6",
    "addr:street":"Richards St",
    "iso:country":"CA",
    "sg:address":"1118 Richards St",
    "sg:city":"Vancouver",
    "sg:classifiers":[
        {
            "category":"Real Estate",
            "subcategory":"Real Estate Agent",
            "type":"Services"
        }
    ],
    "sg:phone":"+1 604 687 0876",
    "sg:postcode":"V6B 3E6",
    "sg:province":"BC",
    "wof:name":"Archer Realty Ltd",
    "wof:placetype":"venue"
},
  "geometry": {"coordinates":[-123.122917175,49.2765884399],"type":"Point"}
}