{
  "type": "Feature",
  "properties": {
    "addr:full":"55 King St Truro NS B2N 3K8",
    "addr:housenumber":"55",
    "addr:postcode":"b2n 3k8",
    "addr:street":"King St",
    "iso:country":"CA",
    "sg:address":"55 King St",
    "sg:city":"Truro",
    "sg:classifiers":[
        {
            "category":"Social Services",
            "subcategory":"Child Care",
            "type":"Services"
        }
    ],
    "sg:phone":"+1 902 895 5105",
    "sg:postcode":"B2N 3K8",
    "sg:province":"NS",
    "wof:name":"Making Friends Preschool",
    "wof:placetype":"venue"
},
  "geometry": {"coordinates":[-63.2855148315,45.3635787964],"type":"Point"}
}