{
  "type": "Feature",
  "properties": {
    "iso:country":"CA",
    "sg:address":"1144 Trans-Canada Hwy",
    "sg:city":"Sorrento",
    "sg:classifiers":[
        {
            "category":"Organizations",
            "subcategory":"Religious Organization",
            "type":"Services"
        }
    ],
    "sg:phone":"+1 250 675 2294",
    "sg:postcode":"V0E 2W0",
    "sg:province":"BC",
    "sg:tags":[
        "church"
    ],
    "wof:name":"St Mary's Anglican Church",
    "wof:placetype":"venue"
},
  "geometry": {"coordinates":[-119.470092773,50.8769607544],"type":"Point"}
}