{
  "type": "Feature",
  "properties": {
    "addr:full":"Hwy 16 Radisson SK S0K 3L0",
    "addr:postcode":"s0k 3l0",
    "addr:street":"Hwy 16 Radisson",
    "iso:country":"CA",
    "sg:address":"Hwy 16",
    "sg:city":"Radisson",
    "sg:classifiers":[
        {
            "category":"Travel",
            "subcategory":"Hotels & Motels",
            "type":"Entertainment"
        }
    ],
    "sg:phone":"+1 306 827 2116",
    "sg:postcode":"S0K 3L0",
    "sg:province":"SK",
    "wof:name":"Midway Motel",
    "wof:placetype":"venue"
},
  "geometry": {"coordinates":[-107.396271,52.468548],"type":"Point"}
}