{
  "type": "Feature",
  "properties": {
    "addr:full":"11855 Av Lucien-Gendron Montreal QC H1E 7A9",
    "addr:housenumber":"11855",
    "addr:postcode":"h1e 7a9",
    "addr:street":"Av Lucien-Gendron",
    "iso:country":"CA",
    "sg:address":"11855 Av Lucien-Gendron",
    "sg:city":"Montreal",
    "sg:classifiers":[
        {
            "category":"Manufacturing",
            "subcategory":"Furniture",
            "type":"Manufacturing & Wholesale Goods"
        }
    ],
    "sg:phone":"+1 514 494 7997",
    "sg:postcode":"H1E 7A9",
    "sg:province":"QC",
    "sg:tags":[
        "chair"
    ],
    "wof:name":"Keca International Inc",
    "wof:placetype":"venue"
},
  "geometry": {"coordinates":[-73.566734314,45.6466293335],"type":"Point"}
}