{
  "type": "Feature",
  "properties": {
    "addr:full":"2625 Carling Ave Ottawa ON K2B 6V3",
    "addr:housenumber":"2625",
    "addr:postcode":"k2b 6v3",
    "addr:street":"Carling Ave",
    "iso:country":"CA",
    "sg:address":"2625 Carling Ave",
    "sg:city":"Ottawa",
    "sg:classifiers":[
        {
            "category":"Restaurant",
            "type":"Food & Drink"
        }
    ],
    "sg:phone":"+1 613 820 7575",
    "sg:postcode":"K2B 6V3",
    "sg:province":"ON",
    "wof:name":"Mc Donald's",
    "wof:placetype":"venue"
},
  "geometry": {"coordinates":[-75.789818,45.362038],"type":"Point"}
}