{
  "type": "Feature",
  "properties": {
    "iso:country":"CA",
    "sg:address":"2625 Carling Ave",
    "sg:city":"Ottawa",
    "sg:classifiers":[
        {
            "category":"Restaurant",
            "type":"Food & Drink"
        }
    ],
    "sg:phone":"+1 613 820 7575",
    "sg:postcode":"K2B 6V3",
    "sg:province":"ON",
    "wof:name":"Mc Donald's",
    "wof:placetype":"venue"
},
  "geometry": {"coordinates":[-75.789818,45.362038],"type":"Point"}
}