{
  "type": "Feature",
  "properties": {
    "addr:full":"5220 Ch DE LA Cote-Saint-Antoi Montreal QC H4A 1P3",
    "addr:postcode":"5220;h4a 1p3",
    "addr:street":"Ch De La Cote-Saint-Antoi",
    "iso:country":"CA",
    "sg:address":"5220 Ch DE LA Cote-Saint-Antoi",
    "sg:city":"Montreal",
    "sg:classifiers":[
        {
            "category":"Professional",
            "subcategory":"Business Services",
            "type":"Services"
        }
    ],
    "sg:phone":"+1 514 488 5220",
    "sg:postcode":"H4A 1P3",
    "sg:province":"QC",
    "sg:tags":[
        "broker"
    ],
    "wof:name":"W Diamond Textile Agency",
    "wof:placetype":"venue"
},
  "geometry": {"coordinates":[-73.61228179930001,45.4770469666],"type":"Point"}
}