{
  "type": "Feature",
  "properties": {
    "addr:full":"980 Rue Saint-Joseph Valcourt QC J0E 2L0",
    "addr:housenumber":"980",
    "addr:postcode":"j0e 2l0",
    "addr:street":"Rue Saint-Joseph",
    "iso:country":"CA",
    "sg:address":"980 Rue Saint-Joseph",
    "sg:city":"Valcourt",
    "sg:classifiers":[
        {
            "category":"Shopping",
            "subcategory":"Jewelry",
            "type":"Retail Goods"
        }
    ],
    "sg:phone":"+1 450 532 2428",
    "sg:postcode":"J0E 2L0",
    "sg:province":"QC",
    "sg:tags":[
        "jeweler"
    ],
    "wof:name":"Drainville, Denis",
    "wof:placetype":"venue"
},
  "geometry": {"coordinates":[-72.315254,45.494839],"type":"Point"}
}