{
  "type": "Feature",
  "properties": {
    "iso:country":"CA",
    "sg:city":"Sarnia",
    "sg:classifiers":[
        {
            "category":"Real Estate",
            "subcategory":"Real Estate Operator",
            "type":"Services"
        }
    ],
    "sg:phone":"+1 519 344 6456",
    "sg:postcode":"N7T 2R8",
    "sg:province":"ON",
    "sg:tags":[
        "apartment"
    ],
    "wof:name":"Miller Apartments",
    "wof:placetype":"venue"
},
  "geometry": {"coordinates":[-82.40766143800001,42.9663352966],"type":"Point"}
}