{
  "type": "Feature",
  "properties": {
    "addr:full":"2865 Boul Masson Quebec QC G1P 1J7",
    "addr:housenumber":"2865",
    "addr:postcode":"g1p 1j7",
    "addr:street":"Boul Masson",
    "iso:country":"CA",
    "sg:address":"2865 Boul Masson",
    "sg:city":"Quebec",
    "sg:classifiers":[
        {
            "category":"Restaurant",
            "type":"Food & Drink"
        }
    ],
    "sg:phone":"+1 418 872 2422",
    "sg:postcode":"G1P 1J7",
    "sg:province":"QC",
    "wof:name":"H & H Pizzas",
    "wof:placetype":"venue"
},
  "geometry": {"coordinates":[-71.321442,46.811237],"type":"Point"}
}