{
  "type": "Feature",
  "properties": {
    "addr:full":"147 5th St Balmertown ON P0V 1C0",
    "addr:housenumber":"147",
    "addr:postcode":"p0v 1c0",
    "addr:street":"5Th St",
    "iso:country":"CA",
    "sg:address":"147 5th St",
    "sg:city":"Balmertown",
    "sg:classifiers":[
        {
            "category":"Travel",
            "subcategory":"Hotels & Motels",
            "type":"Entertainment"
        }
    ],
    "sg:phone":"+1 807 735 2076",
    "sg:postcode":"P0V 1C0",
    "sg:province":"ON",
    "wof:name":"Balmer Motor Hotel",
    "wof:placetype":"venue"
},
  "geometry": {"coordinates":[-93.744179,51.059872],"type":"Point"}
}