{
  "type": "Feature",
  "properties": {
    "addr:full":"Nolalu ON P0T 2K0",
    "addr:postcode":"p0t 2k0",
    "iso:country":"CA",
    "sg:city":"Nolalu",
    "sg:classifiers":[
        {
            "category":"Shopping",
            "subcategory":"Bicycles & Sporting Goods",
            "type":"Retail Goods"
        }
    ],
    "sg:phone":"+1 807 475 0132",
    "sg:postcode":"P0T 2K0",
    "sg:province":"ON",
    "sg:tags":[
        "gun",
        "gunsmith"
    ],
    "wof:name":"J R's Gunshop",
    "wof:placetype":"venue"
},
  "geometry": {"coordinates":[-89.8164215088,48.2915039062],"type":"Point"}
}