{
  "type": "Feature",
  "properties": {
    "addr:full":"201 East Main St Welland ON L3B 3W7",
    "addr:housenumber":"201",
    "addr:postcode":"l3b 3w7",
    "addr:street":"East Main St",
    "iso:country":"CA",
    "sg:address":"201 East Main St",
    "sg:city":"Welland",
    "sg:classifiers":[
        {
            "category":"Professional",
            "subcategory":"Engineering",
            "type":"Services"
        }
    ],
    "sg:phone":"+1 905 714 0325",
    "sg:postcode":"L3B 3W7",
    "sg:province":"ON",
    "sg:tags":[
        "engineer"
    ],
    "wof:name":"Planco Engineering Ltd",
    "wof:placetype":"venue"
},
  "geometry": {"coordinates":[-79.244759,42.992622],"type":"Point"}
}