{
  "type": "Feature",
  "properties": {
    "addr:full":"3209 30 Ave Vernon BC V1T 2C6",
    "addr:housenumber":"3209",
    "addr:postcode":"v1t 2c6",
    "addr:street":"30 Ave",
    "iso:country":"CA",
    "sg:address":"3209 30 Ave",
    "sg:city":"Vernon",
    "sg:classifiers":[
        {
            "category":"Travel",
            "subcategory":"Travel Agent",
            "type":"Entertainment"
        }
    ],
    "sg:phone":"+1 250 545 2154",
    "sg:postcode":"V1T 2C6",
    "sg:province":"BC",
    "sg:tags":[
        "agency",
        "bureau"
    ],
    "wof:name":"Carefree Travel Ltd",
    "wof:placetype":"venue"
},
  "geometry": {"coordinates":[-119.274032593,50.2638664246],"type":"Point"}
}