{
  "type": "Feature",
  "properties": {
    "addr:full":"912 Rosser Ave Brandon MB R7A 0L4",
    "addr:housenumber":"912",
    "addr:postcode":"r7a 0l4",
    "addr:street":"Rosser Ave",
    "iso:country":"CA",
    "sg:address":"912 Rosser Ave",
    "sg:city":"Brandon",
    "sg:classifiers":[
        {
            "category":"Shopping",
            "subcategory":"Clothing, Apparel, & Fashions",
            "type":"Retail Goods"
        }
    ],
    "sg:phone":"+1 204 726 8099",
    "sg:postcode":"R7A 0L4",
    "sg:province":"MB",
    "wof:name":"Caroline's Consignment Clthng",
    "wof:placetype":"venue"
},
  "geometry": {"coordinates":[-99.9503707886,49.8482627869],"type":"Point"}
}