{
  "type": "Feature",
  "properties": {
    "addr:full":"877 Bruce Ave Nanaimo BC V9R 4A1",
    "addr:housenumber":"877",
    "addr:postcode":"v9r 4a1",
    "addr:street":"Bruce Ave",
    "iso:country":"CA",
    "sg:address":"877 Bruce Ave",
    "sg:city":"Nanaimo",
    "sg:classifiers":[
        {
            "category":"Wholesale",
            "subcategory":"Scrap",
            "type":"Manufacturing & Wholesale Goods"
        }
    ],
    "sg:phone":"+1 250 716 0021",
    "sg:postcode":"V9R 4A1",
    "sg:province":"BC",
    "sg:tags":[
        "recycling",
        "container",
        "center",
        "depot"
    ],
    "wof:name":"Harewood Bottle Depot",
    "wof:placetype":"venue"
},
  "geometry": {"coordinates":[-123.94987500000001,49.144852],"type":"Point"}
}