{
  "type": "Feature",
  "properties": {
    "addr:full":"51 Wellington St S Woodstock ON N4S 3H5",
    "addr:housenumber":"51",
    "addr:postcode":"n4s 3h5",
    "addr:street":"Wellington St S",
    "iso:country":"CA",
    "sg:address":"51 Wellington St S",
    "sg:city":"Woodstock",
    "sg:classifiers":[
        {
            "category":"Personal",
            "subcategory":"Beauty Salon",
            "type":"Services"
        }
    ],
    "sg:phone":"+1 519 536 9361",
    "sg:postcode":"N4S 3H5",
    "sg:province":"ON",
    "wof:name":"Ela European Skin Care & Spa",
    "wof:placetype":"venue"
},
  "geometry": {"coordinates":[-80.754013,43.128536],"type":"Point"}
}