{
  "type": "Feature",
  "properties": {
    "addr:full":"4704 50th St Rycroft AB T0H 3A0",
    "addr:housenumber":"4704",
    "addr:postcode":"t0h 3a0",
    "addr:street":"50Th St",
    "iso:country":"CA",
    "sg:address":"4704 50th St",
    "sg:city":"Rycroft",
    "sg:classifiers":[
        {
            "category":"Shopping",
            "type":"Retail Goods"
        }
    ],
    "sg:phone":"+1 780 765 3663",
    "sg:postcode":"T0H 3A0",
    "sg:province":"AB",
    "sg:tags":[
        "monument"
    ],
    "wof:name":"Peace Country Memorials Ltd",
    "wof:placetype":"venue"
},
  "geometry": {"coordinates":[-118.71006,55.756107],"type":"Point"}
}