{
  "type": "Feature",
  "properties": {
    "iso:country":"CA",
    "sg:address":"11330 Av Pigeon",
    "sg:city":"Montreal-Nord",
    "sg:classifiers":[
        {
            "category":"Wholesale",
            "subcategory":"Durable Goods & Equipment",
            "type":"Manufacturing & Wholesale Goods"
        }
    ],
    "sg:phone":"+1 514 327 4472",
    "sg:postcode":"H1G 5V7",
    "sg:province":"QC",
    "sg:tags":[
        "importer"
    ],
    "wof:name":"Voga Import Export Inc",
    "wof:placetype":"venue"
},
  "geometry": {"coordinates":[-73.6319274902,45.5996589661],"type":"Point"}
}