{
  "type": "Feature",
  "properties": {
    "addr:full":"Alberta Beach AB T0E 0A0",
    "addr:postcode":"t0e 0a0",
    "iso:country":"CA",
    "sg:city":"Alberta Beach",
    "sg:classifiers":[
        {
            "category":"Organizations",
            "subcategory":"Religious Organization",
            "type":"Services"
        }
    ],
    "sg:phone":"+1 780 924 3351",
    "sg:postcode":"T0E 0A0",
    "sg:province":"AB",
    "sg:tags":[
        "church"
    ],
    "wof:name":"United Church of Canada-Zion",
    "wof:placetype":"venue"
},
  "geometry": {"coordinates":[-114.360534668,53.6718482971],"type":"Point"}
}