{
  "type": "Feature",
  "properties": {
    "addr:full":"19620 88 Ave Langley BC V2Y 1Z9",
    "addr:housenumber":"19620",
    "addr:postcode":"v2y 1z9",
    "addr:street":"88 Ave",
    "iso:country":"CA",
    "sg:address":"19620 88 Ave",
    "sg:city":"Langley",
    "sg:classifiers":[
        {
            "category":"Building & Trades",
            "subcategory":"Construction",
            "type":"Services"
        }
    ],
    "sg:phone":"+1 604 888 5501",
    "sg:postcode":"V2Y 1Z9",
    "sg:province":"BC",
    "sg:tags":[
        "roofing",
        "contractor"
    ],
    "wof:name":"Patch's Surrey Dome Roofing",
    "wof:placetype":"venue"
},
  "geometry": {"coordinates":[-122.67784899999999,49.162746],"type":"Point"}
}