{
  "type": "Feature",
  "properties": {
    "addr:full":"260 Nugget Ave Scarborough ON M1S 3A7",
    "addr:housenumber":"260",
    "addr:postcode":"m1s 3a7",
    "addr:street":"Nugget Ave",
    "iso:country":"CA",
    "sg:address":"260 Nugget Ave",
    "sg:city":"Scarborough",
    "sg:classifiers":[
        {
            "category":"Manufacturing",
            "subcategory":"Textiles",
            "type":"Manufacturing & Wholesale Goods"
        }
    ],
    "sg:phone":"+1 416 291 2799",
    "sg:postcode":"M1S 3A7",
    "sg:province":"ON",
    "sg:tags":[
        "label"
    ],
    "wof:name":"Whk Woven Labels Ltd",
    "wof:placetype":"venue"
},
  "geometry": {"coordinates":[-79.25281524659999,43.7954978943],"type":"Point"}
}