{
  "type": "Feature",
  "properties": {
    "addr:full":"Oshawa ON L1J 2K5",
    "addr:postcode":"l1j 2k5",
    "iso:country":"CA",
    "sg:city":"Oshawa",
    "sg:classifiers":[
        {
            "category":"Personal",
            "type":"Services"
        }
    ],
    "sg:phone":"+1 905 571 3222",
    "sg:postcode":"L1J 2K5",
    "sg:province":"ON",
    "sg:tags":[
        "wear",
        "formal"
    ],
    "wof:name":"Classy Formal Wear Inc",
    "wof:placetype":"venue"
},
  "geometry": {"coordinates":[-78.880028,43.893684],"type":"Point"}
}