{
  "type": "Feature",
  "properties": {
    "addr:full":"1348 Lasalle Blvd Sudbury ON P3A 1Z6",
    "addr:housenumber":"1348",
    "addr:postcode":"p3a 1z6",
    "addr:street":"Lasalle Blvd",
    "iso:country":"CA",
    "sg:address":"1348 Lasalle Blvd",
    "sg:city":"Sudbury",
    "sg:classifiers":[
        {
            "category":"Health Services",
            "subcategory":"Optometrist",
            "type":"Services"
        }
    ],
    "sg:phone":"+1 705 674 4014",
    "sg:postcode":"P3A 1Z6",
    "sg:province":"ON",
    "wof:name":"Young, Roger A OD",
    "wof:placetype":"venue"
},
  "geometry": {"coordinates":[-80.9468612671,46.5222244263],"type":"Point"}
}