{
  "type": "Feature",
  "properties": {
    "addr:full":"40 Barton St E Hamilton ON L8L 2V8",
    "addr:housenumber":"40",
    "addr:postcode":"l8l 2v8",
    "addr:street":"Barton St E",
    "iso:country":"CA",
    "sg:address":"40 Barton St E",
    "sg:city":"Hamilton",
    "sg:classifiers":[
        {
            "category":"Social Services",
            "type":"Services"
        }
    ],
    "sg:phone":"+1 905 527 3677",
    "sg:postcode":"L8L 2V8",
    "sg:province":"ON",
    "sg:tags":[
        "organization",
        "welfare"
    ],
    "wof:name":"Birthright Pregnancy Svc",
    "wof:placetype":"venue"
},
  "geometry": {"coordinates":[-79.864166,43.263508],"type":"Point"}
}