{
  "type": "Feature",
  "properties": {
    "addr:full":"1432 Brunette Ave Coquitlam BC V3K 1G5",
    "addr:housenumber":"1432",
    "addr:postcode":"v3k 1g5",
    "addr:street":"Brunette Ave",
    "iso:country":"CA",
    "sg:address":"1432 Brunette Ave",
    "sg:city":"Coquitlam",
    "sg:classifiers":[
        {
            "category":"Education",
            "subcategory":"School",
            "type":"Public Place"
        }
    ],
    "sg:phone":"+1 604 521 0728",
    "sg:postcode":"V3K 1G5",
    "sg:province":"BC",
    "wof:name":"Millside Elementary School",
    "wof:placetype":"venue"
},
  "geometry": {"coordinates":[-122.853928,49.240395],"type":"Point"}
}