{
  "type": "Feature",
  "properties": {
    "iso:country":"CA",
    "sg:city":"Vancouver",
    "sg:classifiers":[
        {
            "category":"Wholesale",
            "subcategory":"Home Furnishings",
            "type":"Manufacturing & Wholesale Goods"
        }
    ],
    "sg:phone":"+1 604 254 2611",
    "sg:postcode":"V6A 2H2",
    "sg:province":"BC",
    "sg:tags":[
        "linen"
    ],
    "wof:name":"Roydon Distributors Ltd",
    "wof:placetype":"venue"
},
  "geometry": {"coordinates":[-123.081329346,49.2758483887],"type":"Point"}
}