{
  "type": "Feature",
  "properties": {
    "addr:full":"45 Ripley Ave Toronto ON M6S 3P2",
    "addr:housenumber":"45",
    "addr:postcode":"m6s 3p2",
    "addr:street":"Ripley Ave",
    "iso:country":"CA",
    "sg:address":"45 Ripley Ave",
    "sg:city":"Toronto",
    "sg:classifiers":[
        {
            "category":"Food & Beverages",
            "subcategory":"Dairy",
            "type":"Retail Goods"
        }
    ],
    "sg:phone":"+1 416 762 6292",
    "sg:postcode":"M6S 3P2",
    "sg:province":"ON",
    "sg:tags":[
        "delicatessen"
    ],
    "wof:name":"Cheese Boutique",
    "wof:placetype":"venue"
},
  "geometry": {"coordinates":[-79.4747924805,43.6378631592],"type":"Point"}
}