{
  "type": "Feature",
  "properties": {
    "addr:full":"90 Pearl St E Brockville ON K6V 1P8",
    "addr:housenumber":"90",
    "addr:postcode":"k6v 1p8",
    "addr:street":"Pearl St",
    "iso:country":"CA",
    "sg:address":"90 Pearl St E",
    "sg:city":"Brockville",
    "sg:classifiers":[
        {
            "category":"Education",
            "subcategory":"School",
            "type":"Public Place"
        }
    ],
    "sg:phone":"+1 613 345 5641",
    "sg:postcode":"K6V 1P8",
    "sg:province":"ON",
    "wof:name":"Brockville Collegiate Inst",
    "wof:placetype":"venue"
},
  "geometry": {"coordinates":[-75.682182,44.595764],"type":"Point"}
}