{
  "type": "Feature",
  "properties": {
    "iso:country":"CA",
    "sg:address":"2020 Winston Park Dr",
    "sg:city":"Oakville",
    "sg:classifiers":[
        {
            "category":"Real Estate",
            "subcategory":"Real Estate Operator",
            "type":"Services"
        }
    ],
    "sg:phone":"+1 905 829 8101",
    "sg:postcode":"L6H 6X7",
    "sg:province":"ON",
    "sg:tags":[
        "building",
        "parks"
    ],
    "wof:name":"Westbury Office Park",
    "wof:placetype":"venue"
},
  "geometry": {"coordinates":[-79.6683731079,43.5076522827],"type":"Point"}
}