{
  "type": "Feature",
  "properties": {
    "addr:full":"Sherwood Park AB T8A 4L7",
    "addr:postcode":"t8a 4l7",
    "iso:country":"CA",
    "sg:city":"Sherwood Park",
    "sg:classifiers":[
        {
            "category":"Shopping",
            "type":"Retail Goods"
        }
    ],
    "sg:phone":"+1 780 449 4333",
    "sg:postcode":"T8A 4L7",
    "sg:province":"AB",
    "sg:tags":[
        "miscellaneous",
        "store"
    ],
    "wof:name":"Love Boutique",
    "wof:placetype":"venue"
},
  "geometry": {"coordinates":[-113.32991800000001,53.513317],"type":"Point"}
}