{
  "type": "Feature",
  "properties": {
    "addr:full":"Toronto ON M5H 2A4",
    "addr:postcode":"m5h 2a4",
    "iso:country":"CA",
    "sg:city":"Toronto",
    "sg:classifiers":[
        {
            "category":"Professional",
            "subcategory":"Business Services",
            "type":"Services"
        }
    ],
    "sg:phone":"+1 416 364 9700",
    "sg:postcode":"M5H 2A4",
    "sg:province":"ON",
    "sg:tags":[
        "appraiser"
    ],
    "wof:name":"Cole & Partners",
    "wof:placetype":"venue"
},
  "geometry": {"coordinates":[-79.382507,43.651009],"type":"Point"}
}