{
  "type": "Feature",
  "properties": {
    "addr:full":"852 Rue Notre-Dame Saint-Sulpice QC J5W 3W5",
    "addr:housenumber":"852",
    "addr:postcode":"j5w 3w5",
    "addr:street":"Rue Notre-Dame",
    "iso:country":"CA",
    "sg:address":"852 Rue Notre-Dame",
    "sg:city":"Saint-Sulpice",
    "sg:classifiers":[
        {
            "category":"Retail",
            "subcategory":"Auto Repair",
            "type":"Services"
        }
    ],
    "sg:phone":"+1 450 589 2228",
    "sg:postcode":"J5W 3W5",
    "sg:province":"QC",
    "sg:tags":[
        "repairing",
        "automobile"
    ],
    "wof:name":"Garage Denis Boisclair Inc",
    "wof:placetype":"venue"
},
  "geometry": {"coordinates":[-73.36675262449999,45.8214263916],"type":"Point"}
}