{
  "type": "Feature",
  "properties": {
    "addr:full":"610 2nd Ave NE Moose Jaw SK S6H 1B5",
    "addr:housenumber":"610",
    "addr:postcode":"s6h 1b5",
    "addr:street":"2Nd Ave Ne",
    "iso:country":"CA",
    "sg:address":"610 2nd Ave NE",
    "sg:city":"Moose Jaw",
    "sg:classifiers":[
        {
            "category":"Real Estate",
            "subcategory":"Real Estate Operator",
            "type":"Services"
        }
    ],
    "sg:phone":"+1 306 692 5174",
    "sg:postcode":"S6H 1B5",
    "sg:province":"SK",
    "sg:tags":[
        "apartment"
    ],
    "wof:name":"Athabasca Tower Ltd",
    "wof:placetype":"venue"
},
  "geometry": {"coordinates":[-105.52971599999999,50.395432],"type":"Point"}
}