{
  "type": "Feature",
  "properties": {
    "addr:full":"1476 Rue Frontenac Montreal QC H2K 2Y7",
    "addr:housenumber":"1476",
    "addr:postcode":"h2k 2y7",
    "addr:street":"Rue Frontenac",
    "iso:country":"CA",
    "sg:address":"1476 Rue Frontenac",
    "sg:city":"Montreal",
    "sg:classifiers":[
        {
            "category":"Wholesale",
            "subcategory":"Chemicals & Plastics",
            "type":"Manufacturing & Wholesale Goods"
        }
    ],
    "sg:phone":"+1 514 528 8729",
    "sg:postcode":"H2K 2Y7",
    "sg:province":"QC",
    "wof:name":"Netbec Inc",
    "wof:placetype":"venue"
},
  "geometry": {"coordinates":[-73.546677,45.530441],"type":"Point"}
}