{
  "type": "Feature",
  "properties": {
    "addr:full":"Levis QC G6V 4C2",
    "addr:postcode":"g6v 4c2",
    "iso:country":"CA",
    "sg:city":"Levis",
    "sg:classifiers":[
        {
            "category":"Retail",
            "subcategory":"Auto Rental",
            "type":"Services"
        }
    ],
    "sg:phone":"+1 418 838 4440",
    "sg:postcode":"G6V 4C2",
    "sg:province":"QC",
    "sg:tags":[
        "renting",
        "automobile",
        "limousine"
    ],
    "wof:name":"Service DE Limousine Toxedo",
    "wof:placetype":"venue"
},
  "geometry": {"coordinates":[-71.181122,46.808132],"type":"Point"}
}