{
  "type": "Feature",
  "properties": {
    "addr:full":"505 Boul Temiscamingue Rouyn-Noranda QC J9X 7C8",
    "addr:housenumber":"505",
    "addr:postcode":"j9x 7c8",
    "addr:street":"Boul Temiscamingue",
    "iso:country":"CA",
    "sg:address":"505 Boul Temiscamingue",
    "sg:city":"Rouyn-Noranda",
    "sg:classifiers":[
        {
            "category":"Wholesale",
            "subcategory":"Machinery & Supplies",
            "type":"Manufacturing & Wholesale Goods"
        }
    ],
    "sg:phone":"+1 819 797 5018",
    "sg:postcode":"J9X 7C8",
    "sg:province":"QC",
    "sg:tags":[
        "cargo",
        "container",
        "freight"
    ],
    "wof:name":"Service Sanitaire Div Intersan",
    "wof:placetype":"venue"
},
  "geometry": {"coordinates":[-79.040482,48.232216],"type":"Point"}
}