{
  "type": "Feature",
  "properties": {
    "addr:full":"4120 78 Ave NW Edmonton AB T6B 3M8",
    "addr:housenumber":"4120",
    "addr:postcode":"t6b 3m8",
    "addr:street":"78 Ave Nw",
    "iso:country":"CA",
    "sg:address":"4120 78 Ave NW",
    "sg:city":"Edmonton",
    "sg:classifiers":[
        {
            "category":"Professional",
            "type":"Services"
        }
    ],
    "sg:phone":"+1 780 440 3506",
    "sg:postcode":"T6B 3M8",
    "sg:province":"AB",
    "sg:tags":[
        "field",
        "oil",
        "establishment",
        "equipment"
    ],
    "wof:name":"Keddco Manufacturing Ltd",
    "wof:placetype":"venue"
},
  "geometry": {"coordinates":[-113.404205322,53.5143966675],"type":"Point"}
}