{
  "type": "Feature",
  "properties": {
    "addr:full":"Winnipeg MB R2X 1R3",
    "addr:postcode":"r2x 1r3",
    "iso:country":"CA",
    "sg:city":"Winnipeg",
    "sg:classifiers":[
        {
            "category":"Restaurant",
            "type":"Food & Drink"
        }
    ],
    "sg:phone":"+1 204 697 1237",
    "sg:postcode":"R2X 1R3",
    "sg:province":"MB",
    "wof:name":"Windows Restaurant",
    "wof:placetype":"venue"
},
  "geometry": {"coordinates":[-97.1932144165,49.9462394714],"type":"Point"}
}