{
  "type": "Feature",
  "properties": {
    "addr:full":"226 Rue Blain Mont-Saint-Hilaire QC J3H 3B3",
    "addr:housenumber":"226",
    "addr:postcode":"j3h 3b3",
    "addr:street":"Rue Blain",
    "iso:country":"CA",
    "sg:address":"226 Rue Blain",
    "sg:city":"Mont-Saint-Hilaire",
    "sg:classifiers":[
        {
            "category":"Organizations",
            "subcategory":"Religious Organization",
            "type":"Services"
        }
    ],
    "sg:phone":"+1 450 467 4189",
    "sg:postcode":"J3H 3B3",
    "sg:province":"QC",
    "sg:tags":[
        "home",
        "retirement",
        "community",
        "retreat",
        "house"
    ],
    "wof:name":"Residence DE LA Montagne",
    "wof:placetype":"venue"
},
  "geometry": {"coordinates":[-73.18970489500001,45.5673751831],"type":"Point"}
}