{
  "type": "Feature",
  "properties": {
    "addr:full":"635 DE L'Entente Saint-Cleophas-DE-Brandon QC J0K 2A0",
    "addr:housenumber":"635",
    "addr:postcode":"j0k 2a0",
    "addr:street":"De L'Entente Saint-Cleophas-De-Brandon",
    "iso:country":"CA",
    "sg:address":"635 DE L'Entente",
    "sg:city":"Saint-Cleophas-DE-Brandon",
    "sg:classifiers":[
        {
            "category":"Building & Trades",
            "subcategory":"Plumbing",
            "type":"Services"
        }
    ],
    "sg:phone":"+1 450 755 2552",
    "sg:postcode":"J0K 2A0",
    "sg:province":"QC",
    "sg:tags":[
        "contractor"
    ],
    "wof:name":"Plomberie Serge Gaudet",
    "wof:placetype":"venue"
},
  "geometry": {"coordinates":[-73.412521,46.225288],"type":"Point"}
}