{
  "type": "Feature",
  "properties": {
    "addr:full":"Shamattawa MB R0B 1K0",
    "addr:postcode":"r0b 1k0",
    "iso:country":"CA",
    "sg:city":"Shamattawa",
    "sg:classifiers":[
        {
            "category":"Utilities",
            "subcategory":"Sewage",
            "type":"Services"
        }
    ],
    "sg:phone":"+1 204 565 2079",
    "sg:postcode":"R0B 1K0",
    "sg:province":"MB",
    "sg:tags":[
        "equipment",
        "treatment"
    ],
    "wof:name":"Sewage Treatment Plant",
    "wof:placetype":"venue"
},
  "geometry": {"coordinates":[-92.0985488892,55.8598556519],"type":"Point"}
}