{
  "type": "Feature",
  "properties": {
    "addr:full":"123 Ch Du Lac Saint-Juste-Du-Lac QC G0L 3R0",
    "addr:housenumber":"123",
    "addr:postcode":"g0l 3r0",
    "addr:street":"Ch Du Lac",
    "iso:country":"CA",
    "sg:address":"123 Ch Du Lac",
    "sg:city":"Saint-Juste-Du-Lac",
    "sg:classifiers":[
        {
            "category":"Travel",
            "subcategory":"Campground",
            "type":"Entertainment"
        }
    ],
    "sg:phone":"+1 418 899 6468",
    "sg:postcode":"G0L 3R0",
    "sg:province":"QC",
    "sg:tags":[
        "government"
    ],
    "wof:name":"St-Juste-Du-Lac Garage Muni",
    "wof:placetype":"venue"
},
  "geometry": {"coordinates":[-68.786125,47.634769],"type":"Point"}
}