{
  "type": "Feature",
  "properties": {
    "addr:full":"Saint-Donat-DE-Montcalm QC J0T 2C0",
    "addr:postcode":"j0t 2c0",
    "addr:street":"Saint-Donat-De-Montcalm",
    "iso:country":"CA",
    "sg:city":"Saint-Donat-DE-Montcalm",
    "sg:classifiers":[
        {
            "category":"Restaurant",
            "type":"Food & Drink"
        }
    ],
    "sg:phone":"+1 819 424 2422",
    "sg:postcode":"J0T 2C0",
    "sg:province":"QC",
    "wof:name":"St-Donat Pizzeria",
    "wof:placetype":"venue"
},
  "geometry": {"coordinates":[-74.22322800000001,46.319412],"type":"Point"}
}