{
  "type": "Feature",
  "properties": {
    "addr:full":"10017 101st Ave Lac LA Biche AB T0A 2C0",
    "addr:housenumber":"10017",
    "addr:postcode":"t0a 2c0",
    "addr:street":"101St Ave",
    "iso:country":"CA",
    "sg:address":"10017 101st Ave",
    "sg:city":"Lac LA Biche",
    "sg:classifiers":[
        {
            "category":"Shopping",
            "subcategory":"Pharmacy",
            "type":"Retail Goods"
        }
    ],
    "sg:phone":"+1 780 623 4151",
    "sg:postcode":"T0A 2C0",
    "sg:province":"AB",
    "wof:name":"Cedar Pharmacy Ltd",
    "wof:placetype":"venue"
},
  "geometry": {"coordinates":[-111.973595,54.771271],"type":"Point"}
}