{
  "type": "Feature",
  "properties": {
    "addr:full":"1018 Rue Dubois Acton Vale QC J0H 1A0",
    "addr:housenumber":"1018",
    "addr:postcode":"j0h 1a0",
    "addr:street":"Rue Dubois",
    "iso:country":"CA",
    "sg:address":"1018 Rue Dubois",
    "sg:city":"Acton Vale",
    "sg:classifiers":[
        {
            "category":"Restaurant",
            "type":"Food & Drink"
        }
    ],
    "sg:phone":"+1 450 546 0222",
    "sg:postcode":"J0H 1A0",
    "sg:province":"QC",
    "wof:name":"Cuisine Des Cousines",
    "wof:placetype":"venue"
},
  "geometry": {"coordinates":[-72.5653915405,45.6498298645],"type":"Point"}
}