{
  "type": "Feature",
  "properties": {
    "addr:full":"Chilliwack BC V2R 3G3",
    "addr:postcode":"v2r 3g3",
    "iso:country":"CA",
    "sg:city":"Chilliwack",
    "sg:classifiers":[
        {
            "category":"Banks & Credit Unions",
            "subcategory":"Investment Brokerage",
            "type":"Services"
        }
    ],
    "sg:phone":"+1 604 824 6810",
    "sg:postcode":"V2R 3G3",
    "sg:province":"BC",
    "wof:name":"Cibc Wood Gundy Inc",
    "wof:placetype":"venue"
},
  "geometry": {"coordinates":[-121.958778,49.137989],"type":"Point"}
}