{
  "type": "Feature",
  "properties": {
    "addr:full":"General Delivery Port Au Choix NL A0K 4C0",
    "addr:postcode":"a0k 4c0",
    "addr:street":"Port",
    "iso:country":"CA",
    "sg:address":"General Delivery",
    "sg:city":"Port Au Choix",
    "sg:classifiers":[
        {
            "category":"Retail",
            "subcategory":"Funeral Services",
            "type":"Services"
        }
    ],
    "sg:phone":"+1 709 861 2255",
    "sg:postcode":"A0K 4C0",
    "sg:province":"NL",
    "sg:tags":[
        "plan"
    ],
    "wof:name":"Fillatre's Funeral Homes Ltd",
    "wof:placetype":"venue"
},
  "geometry": {"coordinates":[-57.3145866394,50.7183265686],"type":"Point"}
}