{
  "type": "Feature",
  "properties": {
    "addr:full":"Vancouver BC V6B 6A7",
    "addr:postcode":"v6b 6a7",
    "iso:country":"CA",
    "sg:city":"Vancouver",
    "sg:classifiers":[
        {
            "category":"Professional",
            "subcategory":"Management & Consulting",
            "type":"Services"
        }
    ],
    "sg:phone":"+1 604 899 0806",
    "sg:postcode":"V6B 6A7",
    "sg:province":"BC",
    "sg:tags":[
        "consultant",
        "business"
    ],
    "wof:name":"G B Graphics Ltd",
    "wof:placetype":"venue"
},
  "geometry": {"coordinates":[-123.12509900000001,49.273884],"type":"Point"}
}