{
  "type": "Feature",
  "properties": {
    "addr:full":"1425 Pembina Hwy Winnipeg MB R3T 2C2",
    "addr:housenumber":"1425",
    "addr:postcode":"r3t 2c2",
    "addr:street":"Pembina Hwy",
    "iso:country":"CA",
    "sg:address":"1425 Pembina Hwy",
    "sg:city":"Winnipeg",
    "sg:classifiers":[
        {
            "category":"Restaurant",
            "type":"Food & Drink"
        }
    ],
    "sg:phone":"+1 204 475 7867",
    "sg:postcode":"R3T 2C2",
    "sg:province":"MB",
    "wof:name":"Sweet Palace Restaurant",
    "wof:placetype":"venue"
},
  "geometry": {"coordinates":[-97.1513290405,49.8373756409],"type":"Point"}
}