{
  "type": "Feature",
  "properties": {
    "addr:full":"Bellevue AB T0K 0C0",
    "addr:postcode":"t0k 0c0",
    "iso:country":"CA",
    "sg:city":"Bellevue",
    "sg:classifiers":[
        {
            "category":"Utilities",
            "subcategory":"Mobile Phone",
            "type":"Services"
        }
    ],
    "sg:phone":"+1 403 564 4999",
    "sg:postcode":"T0K 0C0",
    "sg:province":"AB",
    "sg:tags":[
        "telephone",
        "cellular"
    ],
    "wof:name":"Tns Communications",
    "wof:placetype":"venue"
},
  "geometry": {"coordinates":[-114.365067,49.5765],"type":"Point"}
}