{
  "type": "Feature",
  "properties": {
    "addr:full":"59 Spruce Ave Sherwood Park AB T8A 2B7",
    "addr:housenumber":"59",
    "addr:postcode":"t8a 2b7",
    "addr:street":"Spruce Ave",
    "iso:country":"CA",
    "sg:address":"59 Spruce Ave",
    "sg:city":"Sherwood Park",
    "sg:classifiers":[
        {
            "category":"Building & Trades",
            "subcategory":"Plumbing",
            "type":"Services"
        }
    ],
    "sg:phone":"+1 780 467 9707",
    "sg:postcode":"T8A 2B7",
    "sg:province":"AB",
    "sg:tags":[
        "contractor"
    ],
    "wof:name":"T-J Plumbing & Heating Ltd",
    "wof:placetype":"venue"
},
  "geometry": {"coordinates":[-113.31004299999999,53.516678],"type":"Point"}
}