{
  "type": "Feature",
  "properties": {
    "addr:full":"109 Boul Tessier Lachute QC J8H 1C2",
    "addr:housenumber":"109",
    "addr:postcode":"j8h 1c2",
    "addr:street":"Boul Tessier",
    "iso:country":"CA",
    "sg:address":"109 Boul Tessier",
    "sg:city":"Lachute",
    "sg:classifiers":[
        {
            "category":"Food & Beverages",
            "subcategory":"Groceries & Convenience Stores",
            "type":"Retail Goods"
        }
    ],
    "sg:phone":"+1 450 562 8223",
    "sg:postcode":"J8H 1C2",
    "sg:province":"QC",
    "wof:name":"Depanneur 89-906 Enr",
    "wof:placetype":"venue"
},
  "geometry": {"coordinates":[-74.34293365480001,45.6482276917],"type":"Point"}
}