{
  "type": "Feature",
  "properties": {
    "iso:country":"CA",
    "sg:address":"139 Rue Claude-Jodouin",
    "sg:city":"Boucherville",
    "sg:classifiers":[
        {
            "category":"Building & Trades",
            "subcategory":"Electrical",
            "type":"Services"
        }
    ],
    "sg:phone":"+1 450 655 0195",
    "sg:postcode":"J4B 5B7",
    "sg:province":"QC",
    "sg:tags":[
        "electric",
        "contractor"
    ],
    "wof:name":"Jean Goulet Serge Inc",
    "wof:placetype":"venue"
},
  "geometry": {"coordinates":[-73.4494400024,45.6076927185],"type":"Point"}
}