{
  "type": "Feature",
  "properties": {
    "iso:country":"CA",
    "sg:address":"11144 40 Ave NW",
    "sg:city":"Edmonton",
    "sg:classifiers":[
        {
            "category":"Building & Trades",
            "subcategory":"Plumbing",
            "type":"Services"
        }
    ],
    "sg:phone":"+1 780 436 0553",
    "sg:postcode":"T6J 0R1",
    "sg:province":"AB",
    "sg:tags":[
        "product",
        "management",
        "energy",
        "system"
    ],
    "wof:name":"U-Save Energy Ltd",
    "wof:placetype":"venue"
},
  "geometry": {"coordinates":[-113.519005,53.476067],"type":"Point"}
}