{
  "type": "Feature",
  "properties": {
    "addr:full":"11045 124 St NW Edmonton AB T5M 0J5",
    "addr:housenumber":"11045",
    "addr:postcode":"t5m 0j5",
    "addr:street":"124 St Nw",
    "iso:country":"CA",
    "sg:address":"11045 124 St NW",
    "sg:city":"Edmonton",
    "sg:classifiers":[
        {
            "category":"Retail",
            "subcategory":"Laundry & Dry Cleaning",
            "type":"Services"
        }
    ],
    "sg:phone":"+1 780 454 1534",
    "sg:postcode":"T5M 0J5",
    "sg:province":"AB",
    "sg:tags":[
        "cleaners"
    ],
    "wof:name":"Todd Cleaners Ltd",
    "wof:placetype":"venue"
},
  "geometry": {"coordinates":[-113.535751,53.558029],"type":"Point"}
}