{
  "type": "Feature",
  "properties": {
    "iso:country":"CA",
    "sg:address":"1540 Cornwall Rd",
    "sg:city":"Oakville",
    "sg:classifiers":[
        {
            "category":"Insurance",
            "subcategory":"Insurance Agent",
            "type":"Services"
        }
    ],
    "sg:phone":"+1 905 845 2300",
    "sg:postcode":"L6J 7W5",
    "sg:province":"ON",
    "wof:name":"Cregoe Mealing & Clarke Ltd",
    "wof:placetype":"venue"
},
  "geometry": {"coordinates":[-79.6598739624,43.4776306152],"type":"Point"}
}