{
  "type": "Feature",
  "properties": {
    "addr:full":"11581 256 St Maple Ridge BC V4R 1Z6",
    "addr:housenumber":"11581",
    "addr:postcode":"bc v4r 1z6",
    "addr:street":"256 St",
    "iso:country":"CA",
    "sg:address":"11581 256 St",
    "sg:city":"Maple Ridge",
    "sg:classifiers":[
        {
            "category":"Health Services",
            "subcategory":"Nursing And Care Facility",
            "type":"Services"
        }
    ],
    "sg:phone":"+1 604 462 9614",
    "sg:postcode":"V4R 1Z6",
    "sg:province":"BC",
    "sg:tags":[
        "home",
        "retirement",
        "community"
    ],
    "wof:name":"Kanaka Creek Lodge",
    "wof:placetype":"venue"
},
  "geometry": {"coordinates":[-122.512474,49.212288],"type":"Point"}
}