{
  "type": "Feature",
  "properties": {
    "addr:full":"1706 Hampton Dr Coquitlam BC V3E 3C9",
    "addr:housenumber":"1706",
    "addr:postcode":"v3e 3c9",
    "addr:street":"Hampton Dr",
    "iso:country":"CA",
    "sg:address":"1706 Hampton Dr",
    "sg:city":"Coquitlam",
    "sg:classifiers":[
        {
            "category":"Wholesale",
            "subcategory":"Machinery & Supplies",
            "type":"Manufacturing & Wholesale Goods"
        }
    ],
    "sg:phone":"+1 604 552 1433",
    "sg:postcode":"V3E 3C9",
    "sg:province":"BC",
    "sg:tags":[
        "machine",
        "tool"
    ],
    "wof:name":"Danha's International Tech",
    "wof:placetype":"venue"
},
  "geometry": {"coordinates":[-122.784294128,49.3090515137],"type":"Point"}
}