{
  "type": "Feature",
  "properties": {
    "addr:full":"127 Tillson Ave Tillsonburg ON N4G 3A6",
    "addr:housenumber":"127",
    "addr:postcode":"n4g 3a6",
    "addr:street":"Tillson Ave",
    "iso:country":"CA",
    "sg:address":"127 Tillson Ave",
    "sg:city":"Tillsonburg",
    "sg:classifiers":[
        {
            "category":"Retail",
            "subcategory":"Car Wash",
            "type":"Services"
        }
    ],
    "sg:phone":"+1 519 842 5061",
    "sg:postcode":"N4G 3A6",
    "sg:province":"ON",
    "sg:tags":[
        "polishing",
        "washing"
    ],
    "wof:name":"Mister Auto Wash",
    "wof:placetype":"venue"
},
  "geometry": {"coordinates":[-80.724152,42.867393],"type":"Point"}
}