{
  "type": "Feature",
  "properties": {
    "addr:full":"26 Cawthra Ave Toronto ON M6N 5B3",
    "addr:housenumber":"26",
    "addr:postcode":"m6n 5b3",
    "addr:street":"Cawthra Ave",
    "iso:country":"CA",
    "sg:address":"26 Cawthra Ave",
    "sg:city":"Toronto",
    "sg:classifiers":[
        {
            "category":"Building & Trades",
            "subcategory":"Plumbing",
            "type":"Services"
        }
    ],
    "sg:phone":"+1 416 769 7668",
    "sg:postcode":"M6N 5B3",
    "sg:province":"ON",
    "sg:tags":[
        "conditioning",
        "air",
        "system",
        "contractor"
    ],
    "wof:name":"Alpha Mechanical",
    "wof:placetype":"venue"
},
  "geometry": {"coordinates":[-79.46379089360001,43.6690101624],"type":"Point"}
}