{
  "type": "Feature",
  "properties": {
    "addr:full":"800 Bay St Toronto ON M5S 3A9",
    "addr:housenumber":"800",
    "addr:postcode":"m5s 3a9",
    "addr:street":"Bay St",
    "iso:country":"CA",
    "sg:address":"800 Bay St",
    "sg:city":"Toronto",
    "sg:classifiers":[
        {
            "category":"Restaurant",
            "type":"Food & Drink"
        }
    ],
    "sg:phone":"+1 416 921 7020",
    "sg:postcode":"M5S 3A9",
    "sg:province":"ON",
    "wof:name":"Select Sandwich",
    "wof:placetype":"venue"
},
  "geometry": {"coordinates":[-79.38597900000001,43.660881],"type":"Point"}
}