{
  "type": "Feature",
  "properties": {
    "iso:country":"CA",
    "sg:address":"67 Flett Ave",
    "sg:city":"Winnipeg",
    "sg:classifiers":[
        {
            "category":"Wholesale",
            "subcategory":"Books, Periodicals, & Newspapers",
            "type":"Manufacturing & Wholesale Goods"
        }
    ],
    "sg:phone":"+1 204 668 7475",
    "sg:postcode":"R2K 3N3",
    "sg:province":"MB",
    "sg:tags":[
        "publisher"
    ],
    "wof:name":"Windflower Communications",
    "wof:placetype":"venue"
},
  "geometry": {"coordinates":[-97.072632,49.92197],"type":"Point"}
}