{
  "type": "Feature",
  "properties": {
    "addr:full":"Chaffey Township Rd Huntsville ON P1H 1C8",
    "addr:postcode":"p1h 1c8",
    "addr:street":"Chaffey Township Rd",
    "iso:country":"CA",
    "sg:address":"Chaffey Township Rd",
    "sg:city":"Huntsville",
    "sg:classifiers":[
        {
            "category":"Government",
            "subcategory":"Fire Station",
            "type":"Public Place"
        }
    ],
    "sg:phone":"+1 ",
    "sg:postcode":"P1H 1C8",
    "sg:province":"ON",
    "sg:tags":[
        "department"
    ],
    "wof:name":"Huntsville Fire Dept",
    "wof:placetype":"venue"
},
  "geometry": {"coordinates":[-79.1988372803,45.3451385498],"type":"Point"}
}