{
  "type": "Feature",
  "properties": {
    "addr:full":"5107 Kingsway Burnaby BC V5H 2E6",
    "addr:housenumber":"5107",
    "addr:postcode":"v5h 2e6",
    "addr:street":"Kingsway",
    "iso:country":"CA",
    "sg:address":"5107 Kingsway",
    "sg:city":"Burnaby",
    "sg:classifiers":[
        {
            "category":"Personal",
            "subcategory":"Beauty Salon",
            "type":"Services"
        }
    ],
    "sg:phone":"+1 604 433 6365",
    "sg:postcode":"V5H 2E6",
    "sg:province":"BC",
    "wof:name":"Sonja",
    "wof:placetype":"venue"
},
  "geometry": {"coordinates":[-122.990303,49.225597],"type":"Point"}
}