{
  "type": "Feature",
  "properties": {
    "addr:full":"24 Austin St Moncton NB E1C 1Z6",
    "addr:housenumber":"24",
    "addr:postcode":"e1c 1z6",
    "addr:street":"Austin St",
    "iso:country":"CA",
    "sg:address":"24 Austin St",
    "sg:city":"Moncton",
    "sg:classifiers":[
        {
            "category":"Wholesale",
            "subcategory":"Seafood",
            "type":"Manufacturing & Wholesale Goods"
        }
    ],
    "sg:phone":"+1 506 857 9424",
    "sg:postcode":"E1C 1Z6",
    "sg:province":"NB",
    "sg:tags":[
        "fish"
    ],
    "wof:name":"E T & Assoc Inc",
    "wof:placetype":"venue"
},
  "geometry": {"coordinates":[-64.780182,46.092487],"type":"Point"}
}