{
  "type": "Feature",
  "properties": {
    "iso:country":"CA",
    "sg:address":"7264 Rue Saint-Zotique",
    "sg:city":"Anjou",
    "sg:classifiers":[
        {
            "category":"Restaurant",
            "type":"Food & Drink"
        }
    ],
    "sg:phone":"+1 514 351 6024",
    "sg:postcode":"H1M 3G6",
    "sg:province":"QC",
    "wof:name":"Restaurant Ritz",
    "wof:placetype":"venue"
},
  "geometry": {"coordinates":[-73.55899,45.597347],"type":"Point"}
}