{
  "type": "Feature",
  "properties": {
    "addr:full":"21428 Stonehouse Ave Maple Ridge BC V2X 3Z4",
    "addr:housenumber":"21428",
    "addr:postcode":"v2x 3z4",
    "addr:street":"Stonehouse Ave",
    "iso:country":"CA",
    "sg:address":"21428 Stonehouse Ave",
    "sg:city":"Maple Ridge",
    "sg:classifiers":[
        {
            "category":"Building & Trades",
            "subcategory":"Construction",
            "type":"Services"
        }
    ],
    "sg:phone":"+1 604 467 3078",
    "sg:postcode":"V2X 3Z4",
    "sg:province":"BC",
    "sg:tags":[
        "downspouts",
        "gutter"
    ],
    "wof:name":"Coast Mountain Gutters Ltd",
    "wof:placetype":"venue"
},
  "geometry": {"coordinates":[-122.626358032,49.2254180908],"type":"Point"}
}