{
  "type": "Feature",
  "properties": {
    "addr:full":"260 Hartley Ave Fort Macleod AB T0L 0Z0",
    "addr:housenumber":"260",
    "addr:postcode":"t0l 0z0",
    "addr:street":"Hartley Ave Fort",
    "iso:country":"CA",
    "sg:address":"260 Hartley Ave",
    "sg:city":"Fort Macleod",
    "sg:classifiers":[
        {
            "category":"Manufacturing",
            "subcategory":"Motor Vehicles & Parts",
            "type":"Manufacturing & Wholesale Goods"
        }
    ],
    "sg:phone":"+1 403 553 2114",
    "sg:postcode":"T0L 0Z0",
    "sg:province":"AB",
    "sg:tags":[
        "farm",
        "equipment"
    ],
    "wof:name":"Fal Can Ind",
    "wof:placetype":"venue"
},
  "geometry": {"coordinates":[-113.423134,49.70966],"type":"Point"}
}