{
  "type": "Feature",
  "properties": {
    "addr:full":"3795 Ch DE LA Cote-DE-Liesse Saint-Laurent QC H4N 2N5",
    "addr:housenumber":"3795",
    "addr:postcode":"h4n 2n5",
    "addr:street":"Ch De La Cote-De-Liesse",
    "iso:country":"CA",
    "sg:address":"3795 Ch DE LA Cote-DE-Liesse",
    "sg:city":"Saint-Laurent",
    "sg:classifiers":[
        {
            "category":"Professional",
            "subcategory":"Printing & Photocopies",
            "type":"Services"
        }
    ],
    "sg:phone":"+1 514 747 4477",
    "sg:postcode":"H4N 2N5",
    "sg:province":"QC",
    "sg:tags":[
        "printer",
        "duplicating",
        "copying"
    ],
    "wof:name":"Copie Rapide Montreal Inc",
    "wof:placetype":"venue"
},
  "geometry": {"coordinates":[-73.661659,45.510654],"type":"Point"}
}