{
  "type": "Feature",
  "properties": {
    "addr:full":"465 Rue Soumande Vanier QC G1M 2X6",
    "addr:housenumber":"465",
    "addr:postcode":"g1m 2x6",
    "addr:street":"Rue Soumande",
    "iso:country":"CA",
    "sg:address":"465 Rue Soumande",
    "sg:city":"Vanier",
    "sg:classifiers":[
        {
            "category":"Shopping",
            "subcategory":"Clothing, Apparel, & Fashions",
            "type":"Retail Goods"
        }
    ],
    "sg:phone":"+1 418 622 1425",
    "sg:postcode":"G1M 2X6",
    "sg:province":"QC",
    "sg:tags":[
        "department",
        "boutique",
        "store"
    ],
    "wof:name":"Mode Choc",
    "wof:placetype":"venue"
},
  "geometry": {"coordinates":[-71.255486,46.821526],"type":"Point"}
}