{
  "type": "Feature",
  "properties": {
    "addr:full":"386 10th St E Owen Sound ON N4K 1S6",
    "addr:housenumber":"386",
    "addr:postcode":"n4k 1s6",
    "addr:street":"10Th St E",
    "iso:country":"CA",
    "sg:address":"386 10th St E",
    "sg:city":"Owen Sound",
    "sg:classifiers":[
        {
            "category":"Organizations",
            "subcategory":"Religious Organization",
            "type":"Services"
        }
    ],
    "sg:phone":"+1 519 376 0688",
    "sg:postcode":"N4K 1S6",
    "sg:province":"ON",
    "sg:tags":[
        "church"
    ],
    "wof:name":"Church of the Nazarene",
    "wof:placetype":"venue"
},
  "geometry": {"coordinates":[-80.94000200000001,44.568218],"type":"Point"}
}