{
  "type": "Feature",
  "properties": {
    "addr:full":"Vancouver BC V5R 5L1",
    "addr:postcode":"v5r 5l1",
    "iso:country":"CA",
    "sg:city":"Vancouver",
    "sg:classifiers":[
        {
            "category":"Insurance",
            "subcategory":"Insurance Agent",
            "type":"Services"
        }
    ],
    "sg:phone":"+1 604 437 7878",
    "sg:postcode":"V5R 5L1",
    "sg:province":"BC",
    "wof:name":"Active Insurance & Financial",
    "wof:placetype":"venue"
},
  "geometry": {"coordinates":[-123.034553528,49.2332954407],"type":"Point"}
}