{
  "type": "Feature",
  "properties": {
    "iso:country":"CA",
    "sg:address":"162 Rue Principale",
    "sg:city":"Pointe-Verte",
    "sg:classifiers":[
        {
            "category":"Shopping",
            "subcategory":"Clothing, Apparel, & Fashions",
            "type":"Retail Goods"
        }
    ],
    "sg:phone":"+1 506 783 8456",
    "sg:postcode":"E8J 2W5",
    "sg:province":"NB",
    "sg:tags":[
        "brassiere"
    ],
    "wof:name":"Brasserie Au Au Feur Follet",
    "wof:placetype":"venue"
},
  "geometry": {"coordinates":[-65.782409668,47.8659477234],"type":"Point"}
}