{
  "type": "Feature",
  "properties": {
    "addr:full":"1957 Weston Rd York ON M9N 1W8",
    "addr:housenumber":"1957",
    "addr:postcode":"m9n 1w8",
    "addr:street":"Weston Rd",
    "iso:country":"CA",
    "sg:address":"1957 Weston Rd",
    "sg:city":"York",
    "sg:classifiers":[
        {
            "category":"Shopping",
            "subcategory":"Clothing, Apparel, & Fashions",
            "type":"Retail Goods"
        }
    ],
    "sg:phone":"+1 416 248 8288",
    "sg:postcode":"M9N 1W8",
    "sg:province":"ON",
    "sg:tags":[
        "accessory"
    ],
    "wof:name":"Club Franco Weston",
    "wof:placetype":"venue"
},
  "geometry": {"coordinates":[-79.51847839360001,43.7009315491],"type":"Point"}
}