{
  "type": "Feature",
  "properties": {
    "addr:full":"2033 Ch Sainte-Angelique Saint-Lazare QC J7T 2Y5",
    "addr:postcode":"2033;j7t 2y5",
    "addr:street":"Ch Sainte-Angelique",
    "iso:country":"CA",
    "sg:address":"2033 Ch Sainte-Angelique",
    "sg:city":"Saint-Lazare",
    "sg:classifiers":[
        {
            "category":"Personal",
            "subcategory":"Beauty Salon",
            "type":"Services"
        }
    ],
    "sg:phone":"+1 450 455 1231",
    "sg:postcode":"J7T 2Y5",
    "sg:province":"QC",
    "wof:name":"Salon Style Mode Enr",
    "wof:placetype":"venue"
},
  "geometry": {"coordinates":[-74.14444,45.40078],"type":"Point"}
}