{
  "type": "Feature",
  "properties": {
    "addr:full":"59 Main St Seaforth ON N0K 1W0",
    "addr:housenumber":"59",
    "addr:postcode":"n0k 1w0",
    "addr:street":"Main St",
    "iso:country":"CA",
    "sg:address":"59 Main St",
    "sg:city":"Seaforth",
    "sg:classifiers":[
        {
            "category":"Personal",
            "subcategory":"Beauty Salon",
            "type":"Services"
        }
    ],
    "sg:phone":"+1 519 527 0780",
    "sg:postcode":"N0K 1W0",
    "sg:province":"ON",
    "wof:name":"Total Image II",
    "wof:placetype":"venue"
},
  "geometry": {"coordinates":[-81.39199829099999,43.5552902222],"type":"Point"}
}