{
  "type": "Feature",
  "properties": {
    "addr:full":"860 Bradford St Winnipeg MB R3H 0N5",
    "addr:housenumber":"860",
    "addr:postcode":"r3h 0n5",
    "addr:street":"Bradford St",
    "iso:country":"CA",
    "sg:address":"860 Bradford St",
    "sg:city":"Winnipeg",
    "sg:classifiers":[
        {
            "category":"Building & Trades",
            "subcategory":"Plumbing",
            "type":"Services"
        }
    ],
    "sg:phone":"+1 204 774 2404",
    "sg:postcode":"R3H 0N5",
    "sg:province":"MB",
    "sg:tags":[
        "contractor"
    ],
    "wof:name":"Mechanical Contractors Assn",
    "wof:placetype":"venue"
},
  "geometry": {"coordinates":[-97.20464324949999,49.9032402039],"type":"Point"}
}