{
  "type": "Feature",
  "properties": {
    "iso:country":"CA",
    "sg:address":"335 Welland Ave",
    "sg:city":"St Catharines",
    "sg:classifiers":[
        {
            "category":"Retail",
            "subcategory":"Auto Repair",
            "type":"Services"
        }
    ],
    "sg:phone":"+1 905 684 6551",
    "sg:postcode":"L2R 2R2",
    "sg:province":"ON",
    "sg:tags":[
        "body",
        "automobile",
        "painting"
    ],
    "wof:name":"Peninsula Collision Svc Ltd",
    "wof:placetype":"venue"
},
  "geometry": {"coordinates":[-79.22588348390001,43.1709060669],"type":"Point"}
}