{
  "type": "Feature",
  "properties": {
    "addr:full":"600 Av DE LA Concorde N Saint-Hyacinthe QC J2S 4P4",
    "addr:housenumber":"600",
    "addr:postcode":"j2s 4p4",
    "addr:street":"Av De La Concorde N",
    "iso:country":"CA",
    "sg:address":"600 Av DE LA Concorde N",
    "sg:city":"Saint-Hyacinthe",
    "sg:classifiers":[
        {
            "category":"Personal",
            "subcategory":"Beauty Salon",
            "type":"Services"
        }
    ],
    "sg:phone":"+1 450 778 3611",
    "sg:postcode":"J2S 4P4",
    "sg:province":"QC",
    "wof:name":"Magie Noire Coiffure",
    "wof:placetype":"venue"
},
  "geometry": {"coordinates":[-72.944221,45.62698],"type":"Point"}
}