{
  "type": "Feature",
  "properties": {
    "addr:full":"Edmonton AB T6A 0T5",
    "addr:postcode":"t6a 0t5",
    "iso:country":"CA",
    "sg:city":"Edmonton",
    "sg:classifiers":[
        {
            "category":"Retail",
            "subcategory":"Laundry & Dry Cleaning",
            "type":"Services"
        }
    ],
    "sg:phone":"+1 780 435 8977",
    "sg:postcode":"T6A 0T5",
    "sg:province":"AB",
    "sg:tags":[
        "cleaners",
        "rug",
        "carpet"
    ],
    "wof:name":"Cleaning By Jack Inc",
    "wof:placetype":"venue"
},
  "geometry": {"coordinates":[-113.426078796,53.5445785522],"type":"Point"}
}