{
  "type": "Feature",
  "properties": {
    "addr:full":"10281 133A St Surrey BC V3T 4A1",
    "addr:housenumber":"10281",
    "addr:postcode":"v3t 4a1",
    "addr:street":"133A St",
    "iso:country":"CA",
    "sg:address":"10281 133A St",
    "sg:city":"Surrey",
    "sg:classifiers":[
        {
            "category":"Manufacturing",
            "subcategory":"Printing",
            "type":"Manufacturing & Wholesale Goods"
        }
    ],
    "sg:phone":"+1 604 585 2004",
    "sg:postcode":"V3T 4A1",
    "sg:province":"BC",
    "sg:tags":[
        "printer"
    ],
    "wof:name":"New Century Press Inc",
    "wof:placetype":"venue"
},
  "geometry": {"coordinates":[-122.830215454,49.105178833],"type":"Point"}
}