{
  "type": "Feature",
  "properties": {
    "iso:country":"CA",
    "sg:address":"7668 Hwy 6",
    "sg:city":"Port Howe",
    "sg:classifiers":[
        {
            "category":"Food & Beverages",
            "subcategory":"Groceries & Convenience Stores",
            "type":"Retail Goods"
        }
    ],
    "sg:phone":"+1 902 243 2394",
    "sg:postcode":"B0K 1K0",
    "sg:province":"NS",
    "wof:name":"Chandler's General Store",
    "wof:placetype":"venue"
},
  "geometry": {"coordinates":[-63.7483406067,45.8541946411],"type":"Point"}
}