{
  "type": "Feature",
  "properties": {
    "addr:full":"247 Elizabeth Dr Gander NL A1V 1J3",
    "addr:housenumber":"247",
    "addr:postcode":"a1v 1j3",
    "addr:street":"Elizabeth Dr",
    "iso:country":"CA",
    "sg:address":"247 Elizabeth Dr",
    "sg:city":"Gander",
    "sg:classifiers":[
        {
            "category":"Wholesale",
            "subcategory":"Construction Materials",
            "type":"Manufacturing & Wholesale Goods"
        }
    ],
    "sg:phone":"+1 709 256 7485",
    "sg:postcode":"A1V 1J3",
    "sg:province":"NL",
    "sg:tags":[
        "lumber"
    ],
    "wof:name":"Central Forest Products",
    "wof:placetype":"venue"
},
  "geometry": {"coordinates":[-54.622002,48.957481],"type":"Point"}
}