{
  "type": "Feature",
  "properties": {
    "iso:country":"CA",
    "sg:address":"2166 Boul Lafontaine",
    "sg:city":"Saint-Jerome",
    "sg:classifiers":[
        {
            "category":"Building & Trades",
            "subcategory":"Construction",
            "type":"Services"
        }
    ],
    "sg:phone":"+1 450 436 5417",
    "sg:postcode":"J7Y 1T7",
    "sg:province":"QC",
    "sg:tags":[
        "excavating",
        "demolition",
        "contractor"
    ],
    "wof:name":"Dynamitage DE Lafontaine Inc",
    "wof:placetype":"venue"
},
  "geometry": {"coordinates":[-74.0157165527,45.8017845154],"type":"Point"}
}