{
  "type": "Feature",
  "properties": {
    "iso:country":"CA",
    "sg:address":"330 Johnson Ave W",
    "sg:city":"Winnipeg",
    "sg:classifiers":[
        {
            "category":"Government",
            "subcategory":"Office",
            "type":"Public Place"
        }
    ],
    "sg:phone":"+1 204 949 0048",
    "sg:postcode":"R2L 0J1",
    "sg:province":"MB",
    "wof:name":"Manitoba Teachers' Retirement",
    "wof:placetype":"venue"
},
  "geometry": {"coordinates":[-97.10692596440001,49.9117164612],"type":"Point"}
}