{
  "type": "Feature",
  "properties": {
    "iso:country":"CA",
    "sg:address":"1902 Mattawa Ave",
    "sg:city":"Mississauga",
    "sg:classifiers":[
        {
            "category":"Retail",
            "subcategory":"Auto Repair",
            "type":"Services"
        }
    ],
    "sg:phone":"+1 905 275 5085",
    "sg:postcode":"L4X 1K1",
    "sg:province":"ON",
    "sg:tags":[
        "repairing",
        "automobile"
    ],
    "wof:name":"A W Auto",
    "wof:placetype":"venue"
},
  "geometry": {"coordinates":[-79.568275,43.617855],"type":"Point"}
}