{
  "type": "Feature",
  "properties": {
    "addr:full":"4115 116 Ave SE Calgary AB T2Z 3Z4",
    "addr:housenumber":"4115",
    "addr:postcode":"t2z 3z4",
    "addr:street":"116 Ave Se",
    "iso:country":"CA",
    "sg:address":"4115 116 Ave SE",
    "sg:city":"Calgary",
    "sg:classifiers":[
        {
            "category":"Building & Trades",
            "subcategory":"Equipment Rental",
            "type":"Services"
        }
    ],
    "sg:phone":"+1 403 571 6800",
    "sg:postcode":"T2Z 3Z4",
    "sg:province":"AB",
    "sg:tags":[
        "crane"
    ],
    "wof:name":"Stampede Crane & Rigging Inc",
    "wof:placetype":"venue"
},
  "geometry": {"coordinates":[-113.97737100000001,50.946918],"type":"Point"}
}