{
  "type": "Feature",
  "properties": {
    "addr:full":"999 Giroux St Rockland ON K4K 1C2",
    "addr:housenumber":"999",
    "addr:postcode":"k4k 1c2",
    "addr:street":"Giroux St",
    "iso:country":"CA",
    "sg:address":"999 Giroux St",
    "sg:city":"Rockland",
    "sg:classifiers":[
        {
            "category":"Social Services",
            "subcategory":"Child Care",
            "type":"Services"
        }
    ],
    "sg:phone":"+1 613 446 6001",
    "sg:postcode":"K4K 1C2",
    "sg:province":"ON",
    "wof:name":"Rockland Public Day Care",
    "wof:placetype":"venue"
},
  "geometry": {"coordinates":[-75.288055,45.5452],"type":"Point"}
}