{
  "type": "Feature",
  "properties": {
    "addr:full":"610 James St N Lumsden SK S0G 3C0",
    "addr:housenumber":"610",
    "addr:postcode":"s0g 3c0",
    "addr:street":"James St N",
    "iso:country":"CA",
    "sg:address":"610 James St N",
    "sg:city":"Lumsden",
    "sg:classifiers":[
        {
            "category":"Shopping",
            "type":"Retail Goods"
        }
    ],
    "sg:phone":"+1 306 731 2097",
    "sg:postcode":"S0G 3C0",
    "sg:province":"SK",
    "sg:tags":[
        "equipment",
        "care",
        "health",
        "home"
    ],
    "wof:name":"Special Need Equipment",
    "wof:placetype":"venue"
},
  "geometry": {"coordinates":[-104.866913,50.646812],"type":"Point"}
}