{
  "type": "Feature",
  "properties": {
    "iso:country":"CA",
    "sg:address":"2178 Ch Gascon",
    "sg:city":"Terrebonne",
    "sg:classifiers":[
        {
            "category":"Food & Beverages",
            "subcategory":"Bakery",
            "type":"Retail Goods"
        }
    ],
    "sg:phone":"+1 450 492 4880",
    "sg:postcode":"J6X 3A1",
    "sg:province":"QC",
    "sg:tags":[
        "baker"
    ],
    "wof:name":"Boulangerie Patisserie Gascon",
    "wof:placetype":"venue"
},
  "geometry": {"coordinates":[-73.662468,45.721989],"type":"Point"}
}