{
  "type": "Feature",
  "properties": {
    "addr:full":"3460 Rue Fleury E Montreal-Nord QC H1H 2R9",
    "addr:housenumber":"3460",
    "addr:postcode":"h1h 2r9",
    "addr:street":"Rue Fleury E",
    "iso:country":"CA",
    "sg:address":"3460 Rue Fleury E",
    "sg:city":"Montreal-Nord",
    "sg:classifiers":[
        {
            "category":"Personal",
            "subcategory":"Barber",
            "type":"Services"
        }
    ],
    "sg:phone":"+1 514 852 9108",
    "sg:postcode":"H1H 2R9",
    "sg:province":"QC",
    "wof:name":"Salon Fayad",
    "wof:placetype":"venue"
},
  "geometry": {"coordinates":[-73.640739,45.58112],"type":"Point"}
}