{
  "type": "Feature",
  "properties": {
    "addr:full":"315 Kensington Ave Estevan SK S4A 2A4",
    "addr:housenumber":"315",
    "addr:postcode":"s4a 2a4",
    "addr:street":"Kensington Ave",
    "iso:country":"CA",
    "sg:address":"315 Kensington Ave",
    "sg:city":"Estevan",
    "sg:classifiers":[
        {
            "category":"Retail",
            "subcategory":"Auto Repair",
            "type":"Services"
        }
    ],
    "sg:phone":"+1 306 634 1950",
    "sg:postcode":"S4A 2A4",
    "sg:province":"SK",
    "sg:tags":[
        "agricultural",
        "implement",
        "supply"
    ],
    "wof:name":"T & T Repair",
    "wof:placetype":"venue"
},
  "geometry": {"coordinates":[-102.96890999999999,49.136341],"type":"Point"}
}