{
  "type": "Feature",
  "properties": {
    "addr:full":"397 Rue Des Colibris Saint-Redempteur QC G6K 1L1",
    "addr:housenumber":"397",
    "addr:postcode":"g6k 1l1",
    "addr:street":"Rue Des Colibris",
    "iso:country":"CA",
    "sg:address":"397 Rue Des Colibris",
    "sg:city":"Saint-Redempteur",
    "sg:classifiers":[
        {
            "category":"Wholesale",
            "subcategory":"Construction Materials",
            "type":"Manufacturing & Wholesale Goods"
        }
    ],
    "sg:phone":"+1 418 836 5099",
    "sg:postcode":"G6K 1L1",
    "sg:province":"QC",
    "sg:tags":[
        "lumber"
    ],
    "wof:name":"Flakeboard CO Ltd",
    "wof:placetype":"venue"
},
  "geometry": {"coordinates":[-71.2936553955,46.6954574585],"type":"Point"}
}