{
  "type": "Feature",
  "properties": {
    "iso:country":"CA",
    "sg:address":"6601 Boul Monk",
    "sg:city":"Montreal",
    "sg:classifiers":[
        {
            "category":"Food & Beverages",
            "subcategory":"Fruits & Vegetables",
            "type":"Retail Goods"
        }
    ],
    "sg:phone":"+1 514 762 4691",
    "sg:postcode":"H4E 3J2",
    "sg:province":"QC",
    "sg:tags":[
        "produce"
    ],
    "wof:name":"Fruiterie Shaana",
    "wof:placetype":"venue"
},
  "geometry": {"coordinates":[-73.5941238403,45.4529418945],"type":"Point"}
}