{
  "type": "Feature",
  "properties": {
    "addr:full":"148 Grand Rg Lac-Etchemin QC G0R 1S0",
    "addr:housenumber":"148",
    "addr:postcode":"g0r 1s0",
    "addr:street":"Grand Rg",
    "iso:country":"CA",
    "sg:address":"148 Grand Rg",
    "sg:city":"Lac-Etchemin",
    "sg:classifiers":[
        {
            "category":"Home & Garden",
            "subcategory":"Household Appliances",
            "type":"Retail Goods"
        }
    ],
    "sg:phone":"+1 418 625 7772",
    "sg:postcode":"G0R 1S0",
    "sg:province":"QC",
    "wof:name":"Centre Electro Enr",
    "wof:placetype":"venue"
},
  "geometry": {"coordinates":[-70.464546,46.39159],"type":"Point"}
}