{
  "type": "Feature",
  "properties": {
    "iso:country":"CA",
    "sg:address":"210 Old Kennedy Rd",
    "sg:city":"Markham",
    "sg:classifiers":[
        {
            "category":"Retail",
            "subcategory":"Auto Repair",
            "type":"Services"
        }
    ],
    "sg:phone":"+1 905 947 9911",
    "sg:postcode":"L3R 0L5",
    "sg:province":"ON",
    "sg:tags":[
        "repairing",
        "automobile"
    ],
    "wof:name":"2 Tang's Automotive Ctr Ltd",
    "wof:placetype":"venue"
},
  "geometry": {"coordinates":[-79.30158996580001,43.8301582336],"type":"Point"}
}