{
  "type": "Feature",
  "properties": {
    "addr:full":"Windsor ON N8Y 2R1",
    "addr:postcode":"n8y 2r1",
    "iso:country":"CA",
    "sg:city":"Windsor",
    "sg:classifiers":[
        {
            "category":"Organizations",
            "subcategory":"Professional Association",
            "type":"Services"
        }
    ],
    "sg:phone":"+1 519 973 7671",
    "sg:postcode":"N8Y 2R1",
    "sg:province":"ON",
    "wof:name":"One in Ten",
    "wof:placetype":"venue"
},
  "geometry": {"coordinates":[-82.998268,42.318928],"type":"Point"}
}