{
  "type": "Feature",
  "properties": {
    "iso:country":"CA",
    "sg:city":"Hull",
    "sg:classifiers":[
        {
            "category":"Health Services",
            "subcategory":"Doctor",
            "type":"Services"
        }
    ],
    "sg:phone":"+1 819 595 5700",
    "sg:postcode":"J9A 3G7",
    "sg:province":"QC",
    "sg:tags":[
        "dentist"
    ],
    "wof:name":"Centre Dentaire Huynh & Assoc",
    "wof:placetype":"venue"
},
  "geometry": {"coordinates":[-75.710487,45.427853],"type":"Point"}
}