{
  "type": "Feature",
  "properties": {
    "addr:full":"216 Main St Antigonish NS B2G 2B9",
    "addr:housenumber":"216",
    "addr:postcode":"b2g 2b9",
    "addr:street":"Main St",
    "iso:country":"CA",
    "sg:address":"216 Main St",
    "sg:city":"Antigonish",
    "sg:classifiers":[
        {
            "category":"Professional",
            "subcategory":"Accounting & Tax Preparation",
            "type":"Services"
        }
    ],
    "sg:phone":"+1 902 863 6101",
    "sg:postcode":"B2G 2B9",
    "sg:province":"NS",
    "sg:tags":[
        "accountant"
    ],
    "wof:name":"William Draper Management Ltd",
    "wof:placetype":"venue"
},
  "geometry": {"coordinates":[-61.9893875122,45.6226539612],"type":"Point"}
}