{
  "type": "Feature",
  "properties": {
    "addr:full":"300 King George Rd Brantford ON N3R 5L8",
    "addr:housenumber":"300",
    "addr:postcode":"n3r 5l8",
    "addr:street":"King George Rd",
    "iso:country":"CA",
    "sg:address":"300 King George Rd",
    "sg:city":"Brantford",
    "sg:classifiers":[
        {
            "category":"Banks & Credit Unions",
            "subcategory":"Bank",
            "type":"Services"
        }
    ],
    "sg:phone":"+1 519 752 6529",
    "sg:postcode":"N3R 5L8",
    "sg:province":"ON",
    "wof:name":"Cibc",
    "wof:placetype":"venue"
},
  "geometry": {"coordinates":[-80.2811050415,43.181968689],"type":"Point"}
}