{
  "type": "Feature",
  "properties": {
    "addr:full":"378 Richmond Rd Ottawa ON K2A 0E8",
    "addr:housenumber":"378",
    "addr:postcode":"k2a 0e8",
    "addr:street":"Richmond Rd",
    "iso:country":"CA",
    "sg:address":"378 Richmond Rd",
    "sg:city":"Ottawa",
    "sg:classifiers":[
        {
            "category":"Shopping",
            "subcategory":"Bicycles & Sporting Goods",
            "type":"Retail Goods"
        }
    ],
    "sg:phone":"+1 613 722 5759",
    "sg:postcode":"K2A 0E8",
    "sg:province":"ON",
    "wof:name":"Auto Racks Ottawa Inc",
    "wof:placetype":"venue"
},
  "geometry": {"coordinates":[-75.75550800000001,45.391171],"type":"Point"}
}