{
  "type": "Feature",
  "properties": {
    "addr:full":"3100 28 Ave Vernon BC V1T 1W3",
    "addr:housenumber":"3100",
    "addr:postcode":"v1t 1w3",
    "addr:street":"28 Ave",
    "iso:country":"CA",
    "sg:address":"3100 28 Ave",
    "sg:city":"Vernon",
    "sg:classifiers":[
        {
            "category":"Organizations",
            "subcategory":"Professional Association",
            "type":"Services"
        }
    ],
    "sg:phone":"+1 250 542 6155",
    "sg:postcode":"V1T 1W3",
    "sg:province":"BC",
    "wof:name":"Peer Outreach Program",
    "wof:placetype":"venue"
},
  "geometry": {"coordinates":[-119.27233123800001,50.2621688843],"type":"Point"}
}