{
  "type": "Feature",
  "properties": {
    "addr:full":"Vancouver BC V6E 2E9",
    "addr:postcode":"v6e 2e9",
    "iso:country":"CA",
    "sg:city":"Vancouver",
    "sg:classifiers":[
        {
            "category":"Mining & Drilling",
            "type":"Manufacturing & Wholesale Goods"
        }
    ],
    "sg:phone":"+1 604 331 8772",
    "sg:postcode":"V6E 2E9",
    "sg:province":"BC",
    "sg:tags":[
        "company"
    ],
    "wof:name":"Oromin Explorations Ltd",
    "wof:placetype":"venue"
},
  "geometry": {"coordinates":[-123.11832428,49.287612915],"type":"Point"}
}