{
  "type": "Feature",
  "properties": {
    "addr:full":"Toronto ON M5H 2M5",
    "addr:postcode":"m5h 2m5",
    "iso:country":"CA",
    "sg:city":"Toronto",
    "sg:classifiers":[
        {
            "category":"Professional",
            "subcategory":"Employment Agencies",
            "type":"Services"
        }
    ],
    "sg:phone":"+1 416 368 0050",
    "sg:postcode":"M5H 2M5",
    "sg:province":"ON",
    "sg:tags":[
        "opportunity"
    ],
    "wof:name":"Fromm & Assoc Personnel",
    "wof:placetype":"venue"
},
  "geometry": {"coordinates":[-79.381866,43.651711],"type":"Point"}
}