{
  "type": "Feature",
  "properties": {
    "addr:full":"120 Dawson Rd Guelph ON N1H 1A6",
    "addr:housenumber":"120",
    "addr:postcode":"n1h 1a6",
    "addr:street":"Dawson Rd",
    "iso:country":"CA",
    "sg:address":"120 Dawson Rd",
    "sg:city":"Guelph",
    "sg:classifiers":[
        {
            "category":"Wholesale",
            "subcategory":"Electrical",
            "type":"Manufacturing & Wholesale Goods"
        }
    ],
    "sg:phone":"+1 519 763 8899",
    "sg:postcode":"N1H 1A6",
    "sg:province":"ON",
    "sg:tags":[
        "equipment",
        "industrial",
        "electric",
        "supply"
    ],
    "wof:name":"Guillevin International Inc",
    "wof:placetype":"venue"
},
  "geometry": {"coordinates":[-80.28113555909999,43.5505180359],"type":"Point"}
}