{
  "type": "Feature",
  "properties": {
    "addr:full":"105 Upton St Minto NB E4B 2R2",
    "addr:housenumber":"105",
    "addr:postcode":"e4b 2r2",
    "addr:street":"Upton St",
    "iso:country":"CA",
    "sg:address":"105 Upton St",
    "sg:city":"Minto",
    "sg:classifiers":[
        {
            "category":"Restaurant",
            "type":"Food & Drink"
        }
    ],
    "sg:phone":"+1 506 327 3759",
    "sg:postcode":"E4B 2R2",
    "sg:province":"NB",
    "wof:name":"Omega Restaurant Ltd",
    "wof:placetype":"venue"
},
  "geometry": {"coordinates":[-66.0573959351,46.0723152161],"type":"Point"}
}