{
  "type": "Feature",
  "properties": {
    "addr:full":"330 Rue DE Sainte-Helene Quebec QC G1K 3L7",
    "addr:housenumber":"330",
    "addr:postcode":"g1k 3l7",
    "addr:street":"Rue De Sainte-Helene",
    "iso:country":"CA",
    "sg:address":"330 Rue DE Sainte-Helene",
    "sg:city":"Quebec",
    "sg:classifiers":[
        {
            "category":"Home & Garden",
            "subcategory":"Building Materials",
            "type":"Retail Goods"
        }
    ],
    "sg:phone":"+1 418 529 8484",
    "sg:postcode":"G1K 3L7",
    "sg:province":"QC",
    "sg:tags":[
        "glass",
        "leaded"
    ],
    "wof:name":"Atelier Verre & Creation",
    "wof:placetype":"venue"
},
  "geometry": {"coordinates":[-71.224861,46.812973],"type":"Point"}
}