{
  "type": "Feature",
  "properties": {
    "addr:full":"6135 Fairway Ave Sechelt BC V0N 3A5",
    "addr:housenumber":"6135",
    "addr:postcode":"v0n 3a5",
    "addr:street":"Fairway Ave",
    "iso:country":"CA",
    "sg:address":"6135 Fairway Ave",
    "sg:city":"Sechelt",
    "sg:classifiers":[
        {
            "category":"Building & Trades",
            "subcategory":"Cleaning & Sanitation",
            "type":"Services"
        }
    ],
    "sg:phone":"+1 604 740 9905",
    "sg:postcode":"V0N 3A5",
    "sg:province":"BC",
    "sg:tags":[
        "house",
        "janitor"
    ],
    "wof:name":"Jiffy Maid Home Cleaning Svc",
    "wof:placetype":"venue"
},
  "geometry": {"coordinates":[-123.774597168,49.4948577881],"type":"Point"}
}