{
  "type": "Feature",
  "properties": {
    "iso:country":"CA",
    "sg:city":"Vancouver",
    "sg:classifiers":[
        {
            "category":"Government",
            "subcategory":"Office",
            "type":"Public Place"
        }
    ],
    "sg:phone":"+1 604 681 9162",
    "sg:postcode":"V6E 4E6",
    "sg:province":"BC",
    "sg:tags":[
        "federal",
        "affairs"
    ],
    "wof:name":"Consulate General of Chile",
    "wof:placetype":"venue"
},
  "geometry": {"coordinates":[-123.124649,49.28693],"type":"Point"}
}