{
  "type": "Feature",
  "properties": {
    "addr:full":"30 Dussek St Belleville ON K8N 5R8",
    "addr:housenumber":"30",
    "addr:postcode":"k8n 5r8",
    "addr:street":"Dussek St",
    "iso:country":"CA",
    "sg:address":"30 Dussek St",
    "sg:city":"Belleville",
    "sg:classifiers":[
        {
            "category":"Manufacturing",
            "subcategory":"Chemicals & Compounds",
            "type":"Manufacturing & Wholesale Goods"
        }
    ],
    "sg:phone":"+1 613 966 8881",
    "sg:postcode":"K8N 5R8",
    "sg:province":"ON",
    "wof:name":"Omg Belleville Inc",
    "wof:placetype":"venue"
},
  "geometry": {"coordinates":[-77.368736,44.179249],"type":"Point"}
}