{
  "type": "Feature",
  "properties": {
    "addr:full":"10302 123 St Grande Prairie AB T8V 8B8",
    "addr:housenumber":"10302",
    "addr:postcode":"t8v 8b8",
    "addr:street":"123 St",
    "iso:country":"CA",
    "sg:address":"10302 123 St",
    "sg:city":"Grande Prairie",
    "sg:classifiers":[
        {
            "category":"Professional",
            "subcategory":"Business Services",
            "type":"Services"
        }
    ],
    "sg:phone":"+1 780 539 9951",
    "sg:postcode":"T8V 8B8",
    "sg:province":"AB",
    "sg:tags":[
        "water",
        "field",
        "oil",
        "hauling"
    ],
    "wof:name":"J B Water & Vacuum Svc",
    "wof:placetype":"venue"
},
  "geometry": {"coordinates":[-118.86988100000001,55.179249],"type":"Point"}
}