{
  "type": "Feature",
  "properties": {
    "addr:full":"1724 Rue DE Limoges Chicoutimi QC G7H 7A9",
    "addr:housenumber":"1724",
    "addr:postcode":"g7h 7a9",
    "addr:street":"Rue De Limoges",
    "iso:country":"CA",
    "sg:address":"1724 Rue DE Limoges",
    "sg:city":"Chicoutimi",
    "sg:classifiers":[
        {
            "category":"Building & Trades",
            "subcategory":"Landscaping Services",
            "type":"Services"
        }
    ],
    "sg:phone":"+1 418 696 4746",
    "sg:postcode":"G7H 7A9",
    "sg:province":"QC",
    "sg:tags":[
        "landscape",
        "contractor"
    ],
    "wof:name":"Carl Gagne Paysagiste Inc",
    "wof:placetype":"venue"
},
  "geometry": {"coordinates":[-71.0153503418,48.4299812317],"type":"Point"}
}