{
  "type": "Feature",
  "properties": {
    "iso:country":"CA",
    "sg:address":"1340 Pandora Ave W",
    "sg:city":"Winnipeg",
    "sg:classifiers":[
        {
            "category":"Building & Trades",
            "subcategory":"Construction",
            "type":"Services"
        }
    ],
    "sg:phone":"+1 204 233 0644",
    "sg:postcode":"R2C 3B7",
    "sg:province":"MB",
    "sg:tags":[
        "marking",
        "maintenance",
        "parking"
    ],
    "wof:name":"Custom Sweeping",
    "wof:placetype":"venue"
},
  "geometry": {"coordinates":[-97.04745483400001,49.8943557739],"type":"Point"}
}