{
  "type": "Feature",
  "properties": {
    "addr:full":"312 7th Ave S Virden MB R0M 2C0",
    "addr:housenumber":"312",
    "addr:postcode":"r0m 2c0",
    "addr:street":"7Th Ave S Virden",
    "iso:country":"CA",
    "sg:address":"312 7th Ave S",
    "sg:city":"Virden",
    "sg:classifiers":[
        {
            "category":"Education",
            "subcategory":"Library",
            "type":"Public Place"
        }
    ],
    "sg:phone":"+1 204 748 3862",
    "sg:postcode":"R0M 2C0",
    "sg:province":"MB",
    "wof:name":"Border Regional Library",
    "wof:placetype":"venue"
},
  "geometry": {"coordinates":[-100.932258606,49.851348877],"type":"Point"}
}