{
  "type": "Feature",
  "properties": {
    "addr:full":"4876 Av Lacombe Montreal QC H3W 1R5",
    "addr:housenumber":"4876",
    "addr:postcode":"h3w 1r5",
    "addr:street":"Av Lacombe",
    "iso:country":"CA",
    "sg:address":"4876 Av Lacombe",
    "sg:city":"Montreal",
    "sg:classifiers":[
        {
            "category":"Real Estate",
            "subcategory":"Architect",
            "type":"Services"
        }
    ],
    "sg:phone":"+1 514 341 0051",
    "sg:postcode":"H3W 1R5",
    "sg:province":"QC",
    "wof:name":"Cohen & Rubin",
    "wof:placetype":"venue"
},
  "geometry": {"coordinates":[-73.6299133301,45.4892272949],"type":"Point"}
}