{
  "type": "Feature",
  "properties": {
    "addr:full":"50 Reeves St Sydney NS B1P 3C5",
    "addr:housenumber":"50",
    "addr:postcode":"b1p 3c5",
    "addr:street":"Reeves St",
    "iso:country":"CA",
    "sg:address":"50 Reeves St",
    "sg:city":"Sydney",
    "sg:classifiers":[
        {
            "category":"Bars & Pubs",
            "type":"Food & Drink"
        }
    ],
    "sg:phone":"+1 902 567 1510",
    "sg:postcode":"B1P 3C5",
    "sg:province":"NS",
    "wof:name":"Bonnie Prince Beverage Room",
    "wof:placetype":"venue"
},
  "geometry": {"coordinates":[-60.1603622437,46.1437034607],"type":"Point"}
}