{
  "type": "Feature",
  "properties": {
    "iso:country":"CA",
    "sg:address":"2475 Boul Laurier",
    "sg:city":"Sillery",
    "sg:classifiers":[
        {
            "category":"Insurance",
            "subcategory":"Insurance Agent",
            "type":"Services"
        }
    ],
    "sg:phone":"+1 418 780 2400",
    "sg:postcode":"G1T 1C4",
    "sg:province":"QC",
    "wof:name":"L'Union Canadienne CO D'Assrnc",
    "wof:placetype":"venue"
},
  "geometry": {"coordinates":[-71.274216,46.774014],"type":"Point"}
}