{
  "type": "Feature",
  "properties": {
    "iso:country":"CA",
    "sg:city":"North York",
    "sg:classifiers":[
        {
            "category":"Real Estate",
            "subcategory":"Real Estate Agent",
            "type":"Services"
        }
    ],
    "sg:phone":"+1 416 781 8162",
    "sg:postcode":"M6B 3A3",
    "sg:province":"ON",
    "sg:tags":[
        "management"
    ],
    "wof:name":"H D Property Management",
    "wof:placetype":"venue"
},
  "geometry": {"coordinates":[-79.42823028559999,43.712184906],"type":"Point"}
}