{
  "type": "Feature",
  "properties": {
    "addr:full":"3217 Harmony Rd N Oshawa ON L1H 8L7",
    "addr:housenumber":"3217",
    "addr:postcode":"l1h 8l7",
    "addr:street":"Harmony Rd N",
    "iso:country":"CA",
    "sg:address":"3217 Harmony Rd N",
    "sg:city":"Oshawa",
    "sg:classifiers":[
        {
            "category":"Autos & Motor Vehicles",
            "subcategory":"Auto Supplies",
            "type":"Retail Goods"
        }
    ],
    "sg:phone":"+1 905 655 5644",
    "sg:postcode":"L1H 8L7",
    "sg:province":"ON",
    "sg:tags":[
        "equipment",
        "racing",
        "car",
        "automobile"
    ],
    "wof:name":"Harmony Road Porsche Parts",
    "wof:placetype":"venue"
},
  "geometry": {"coordinates":[-78.87027740480001,43.9873352051],"type":"Point"}
}