{
  "type": "Feature",
  "properties": {
    "addr:full":"777 Ch DE Saint-Adolphe Morin-Heights QC J0R 1H0",
    "addr:housenumber":"777",
    "addr:postcode":"j0r 1h0",
    "addr:street":"Ch De Saint-Adolphe",
    "iso:country":"CA",
    "sg:address":"777 Ch DE Saint-Adolphe",
    "sg:city":"Morin-Heights",
    "sg:classifiers":[
        {
            "category":"Personal",
            "subcategory":"Beauty Salon",
            "type":"Services"
        }
    ],
    "sg:phone":"+1 450 226 2442",
    "sg:postcode":"J0R 1H0",
    "sg:province":"QC",
    "sg:tags":[
        "therapist",
        "day",
        "massage"
    ],
    "wof:name":"Ofuro Spa",
    "wof:placetype":"venue"
},
  "geometry": {"coordinates":[-74.27391815190001,45.9259033203],"type":"Point"}
}