{
  "type": "Feature",
  "properties": {
    "addr:full":"38 Main St N Minnedosa MB R0J 1E0",
    "addr:housenumber":"38",
    "addr:postcode":"r0j 1e0",
    "addr:street":"Main St N",
    "iso:country":"CA",
    "sg:address":"38 Main St N",
    "sg:city":"Minnedosa",
    "sg:classifiers":[
        {
            "category":"Home & Garden",
            "subcategory":"Building Materials",
            "type":"Retail Goods"
        }
    ],
    "sg:phone":"+1 204 867 3294",
    "sg:postcode":"R0J 1E0",
    "sg:province":"MB",
    "sg:tags":[
        "lumber"
    ],
    "wof:name":"North American Lumber Ltd",
    "wof:placetype":"venue"
},
  "geometry": {"coordinates":[-99.83878300000001,50.253868],"type":"Point"}
}