{
  "type": "Feature",
  "properties": {
    "addr:full":"235 Rue Sherbrooke O # 100 Montreal QC H2X 1X8",
    "addr:housenumber":"235",
    "addr:postcode":"h2x 1x8",
    "addr:street":"Rue Sherbrooke O # 100",
    "iso:country":"CA",
    "sg:address":"235 Rue Sherbrooke O # 100",
    "sg:city":"Montreal",
    "sg:classifiers":[
        {
            "category":"Real Estate",
            "subcategory":"Real Estate Operator",
            "type":"Services"
        }
    ],
    "sg:phone":"+1 514 288 1253",
    "sg:postcode":"H2X 1X8",
    "sg:province":"QC",
    "sg:tags":[
        "apartment"
    ],
    "wof:name":"Appartements Le Colisee",
    "wof:placetype":"venue"
},
  "geometry": {"coordinates":[-73.56849699999999,45.515015],"type":"Point"}
}