{
  "type": "Feature",
  "properties": {
    "addr:full":"9452 118 Ave NW Edmonton AB T5G 0N6",
    "addr:housenumber":"9452",
    "addr:postcode":"t5g 0n6",
    "addr:street":"118 Ave Nw",
    "iso:country":"CA",
    "sg:address":"9452 118 Ave NW",
    "sg:city":"Edmonton",
    "sg:classifiers":[
        {
            "category":"Shopping",
            "subcategory":"Pharmacy",
            "type":"Retail Goods"
        }
    ],
    "sg:phone":"+1 780 479 4093",
    "sg:postcode":"T5G 0N6",
    "sg:province":"AB",
    "wof:name":"Shoppers Drug Mart",
    "wof:placetype":"venue"
},
  "geometry": {"coordinates":[-113.486565,53.570534],"type":"Point"}
}