{
  "type": "Feature",
  "properties": {
    "addr:full":"170 Attwell Dr # 300 Etobicoke ON M9W 5Z5",
    "addr:housenumber":"170",
    "addr:postcode":"m9w 5z5",
    "addr:street":"Attwell Dr # 300",
    "iso:country":"CA",
    "sg:address":"170 Attwell Dr # 300",
    "sg:city":"Etobicoke",
    "sg:classifiers":[
        {
            "category":"Professional",
            "subcategory":"Business Services",
            "type":"Services"
        }
    ],
    "sg:phone":"+1 416 368 5856",
    "sg:postcode":"M9W 5Z5",
    "sg:province":"ON",
    "sg:tags":[
        "arbitration",
        "convention",
        "meeting",
        "facility"
    ],
    "wof:name":"Mediation Place",
    "wof:placetype":"venue"
},
  "geometry": {"coordinates":[-79.587509,43.689041],"type":"Point"}
}