{
  "type": "Feature",
  "properties": {
    "iso:country":"CA",
    "sg:address":"1134 Mill St",
    "sg:city":"Manotick",
    "sg:classifiers":[
        {
            "category":"Shopping",
            "subcategory":"Clothing, Apparel, & Fashions",
            "type":"Retail Goods"
        }
    ],
    "sg:phone":"+1 613 692 6926",
    "sg:postcode":"K4M 1A9",
    "sg:province":"ON",
    "sg:tags":[
        "dressmaker"
    ],
    "wof:name":"Manotick Alterations",
    "wof:placetype":"venue"
},
  "geometry": {"coordinates":[-75.6835479736,45.2261505127],"type":"Point"}
}