{
  "type": "Feature",
  "properties": {
    "addr:full":"5 High St Grand Falls-Windsor NL A2A 1C3",
    "addr:housenumber":"5",
    "addr:postcode":"a2a 1c3",
    "addr:street":"High St",
    "iso:country":"CA",
    "sg:address":"5 High St",
    "sg:city":"Grand Falls-Windsor",
    "sg:classifiers":[
        {
            "category":"Travel",
            "subcategory":"Travel Agent",
            "type":"Entertainment"
        }
    ],
    "sg:phone":"+1 709 489 9629",
    "sg:postcode":"A2A 1C3",
    "sg:province":"NL",
    "sg:tags":[
        "information",
        "tourist"
    ],
    "wof:name":"Exploits Valley Tourism Assoc",
    "wof:placetype":"venue"
},
  "geometry": {"coordinates":[-55.6591796875,48.9276809692],"type":"Point"}
}