{
  "type": "Feature",
  "properties": {
    "addr:full":"3659 19 St NE Calgary AB T2E 6S8",
    "addr:housenumber":"3659",
    "addr:postcode":"t2e 6s8",
    "addr:street":"19 St Ne",
    "iso:country":"CA",
    "sg:address":"3659 19 St NE",
    "sg:city":"Calgary",
    "sg:classifiers":[
        {
            "category":"Manufacturing",
            "subcategory":"Tools & Machinery",
            "type":"Manufacturing & Wholesale Goods"
        }
    ],
    "sg:phone":"+1 403 250 2832",
    "sg:postcode":"T2E 6S8",
    "sg:province":"AB",
    "sg:tags":[
        "steel",
        "machine",
        "shop"
    ],
    "wof:name":"Cactus Machine Ltd",
    "wof:placetype":"venue"
},
  "geometry": {"coordinates":[-114.01190200000001,51.084888],"type":"Point"}
}