{
  "type": "Feature",
  "properties": {
    "addr:full":"7938 Menard St Windsor ON N8S 1V9",
    "addr:housenumber":"7938",
    "addr:postcode":"n8s 1v9",
    "addr:street":"Menard St",
    "iso:country":"CA",
    "sg:address":"7938 Menard St",
    "sg:city":"Windsor",
    "sg:classifiers":[
        {
            "category":"Personal",
            "subcategory":"Beauty Salon",
            "type":"Services"
        }
    ],
    "sg:phone":"+1 519 945 5915",
    "sg:postcode":"N8S 1V9",
    "sg:province":"ON",
    "wof:name":"Effective Hair Studio",
    "wof:placetype":"venue"
},
  "geometry": {"coordinates":[-82.94319915769999,42.3337287903],"type":"Point"}
}