{
  "type": "Feature",
  "properties": {
    "addr:full":"4521 Hwy 97 N Quesnel BC V2J 6W9",
    "addr:housenumber":"4521",
    "addr:postcode":"v2j 6w9",
    "addr:street":"Hwy 97 N",
    "iso:country":"CA",
    "sg:address":"4521 Hwy 97 N",
    "sg:city":"Quesnel",
    "sg:classifiers":[
        {
            "category":"Manufacturing",
            "subcategory":"Lumber",
            "type":"Manufacturing & Wholesale Goods"
        }
    ],
    "sg:phone":"+1 250 992 2660",
    "sg:postcode":"V2J 6W9",
    "sg:province":"BC",
    "sg:tags":[
        "sawmill"
    ],
    "wof:name":"M & K Sawmills Ltd",
    "wof:placetype":"venue"
},
  "geometry": {"coordinates":[-122.495087,53.01519],"type":"Point"}
}