{
  "type": "Feature",
  "properties": {
    "addr:full":"8 Walton Crt Ottawa ON K1V 9T1",
    "addr:housenumber":"8",
    "addr:postcode":"k1v 9t1",
    "addr:street":"Walton Crt",
    "iso:country":"CA",
    "sg:address":"8 Walton Crt",
    "sg:city":"Ottawa",
    "sg:classifiers":[
        {
            "category":"Wholesale",
            "subcategory":"Electrical",
            "type":"Manufacturing & Wholesale Goods"
        }
    ],
    "sg:phone":"+1 613 737 1953",
    "sg:postcode":"K1V 9T1",
    "sg:province":"ON",
    "sg:tags":[
        "equipment",
        "electronic",
        "supply"
    ],
    "wof:name":"Neering Technologies Inc",
    "wof:placetype":"venue"
},
  "geometry": {"coordinates":[-75.684006,45.362392],"type":"Point"}
}