{
  "type": "Feature",
  "properties": {
    "addr:full":"10615 96 St Fort St John BC V1J 3R3",
    "addr:housenumber":"10615",
    "addr:postcode":"v1j 3r3",
    "addr:street":"96 St",
    "iso:country":"CA",
    "sg:address":"10615 96 St",
    "sg:city":"Fort St John",
    "sg:classifiers":[
        {
            "category":"Education",
            "subcategory":"School",
            "type":"Public Place"
        }
    ],
    "sg:phone":"+1 250 785 6125",
    "sg:postcode":"V1J 3R3",
    "sg:province":"BC",
    "wof:name":"Alwin Holland Elementary",
    "wof:placetype":"venue"
},
  "geometry": {"coordinates":[-120.840011597,56.2527122498],"type":"Point"}
}