{
  "type": "Feature",
  "properties": {
    "addr:full":"50 Place DE LA Cite Sherbrooke QC J1H 4G9",
    "addr:housenumber":"50",
    "addr:postcode":"j1h 4g9",
    "addr:street":"Place De La Cite",
    "iso:country":"CA",
    "sg:address":"50 Place DE LA Cite",
    "sg:city":"Sherbrooke",
    "sg:classifiers":[
        {
            "category":"Government",
            "subcategory":"Office",
            "type":"Public Place"
        }
    ],
    "sg:phone":"+1 819 573 2070",
    "sg:postcode":"J1H 4G9",
    "sg:province":"QC",
    "wof:name":"Canada Services Douaniers",
    "wof:placetype":"venue"
},
  "geometry": {"coordinates":[-71.8949890137,45.3999671936],"type":"Point"}
}