{
  "type": "Feature",
  "properties": {
    "addr:full":"94 Rue Bourget Montreal QC H4C 2M2",
    "addr:housenumber":"94",
    "addr:postcode":"h4c 2m2",
    "addr:street":"Rue Bourget",
    "iso:country":"CA",
    "sg:address":"94 Rue Bourget",
    "sg:city":"Montreal",
    "sg:classifiers":[
        {
            "category":"Wholesale",
            "subcategory":"Machinery & Supplies",
            "type":"Manufacturing & Wholesale Goods"
        }
    ],
    "sg:phone":"+1 514 933 8073",
    "sg:postcode":"H4C 2M2",
    "sg:province":"QC",
    "sg:tags":[
        "equipment",
        "material",
        "handling"
    ],
    "wof:name":"M R Tanguay & Fils Inc",
    "wof:placetype":"venue"
},
  "geometry": {"coordinates":[-73.57872,45.477943],"type":"Point"}
}