{
  "type": "Feature",
  "properties": {
    "iso:country":"CA",
    "sg:address":"6560 Av Du Parc",
    "sg:city":"Montreal",
    "sg:classifiers":[
        {
            "category":"Home & Garden",
            "subcategory":"Furniture",
            "type":"Retail Goods"
        }
    ],
    "sg:phone":"+1 514 274 1900",
    "sg:postcode":"H2V 4H9",
    "sg:province":"QC",
    "wof:name":"Mobilier Masson Inc",
    "wof:placetype":"venue"
},
  "geometry": {"coordinates":[-73.613731,45.527161],"type":"Point"}
}