{
  "type": "Feature",
  "properties": {
    "addr:full":"Sault Ste Marie ON P6B 4Y9",
    "addr:postcode":"p6b 4y9",
    "iso:country":"CA",
    "sg:city":"Sault Ste Marie",
    "sg:classifiers":[
        {
            "category":"Health Services",
            "subcategory":"Chiropractor",
            "type":"Services"
        }
    ],
    "sg:phone":"+1 705 759 1075",
    "sg:postcode":"P6B 4Y9",
    "sg:province":"ON",
    "wof:name":"Myers, Rodney L DC",
    "wof:placetype":"venue"
},
  "geometry": {"coordinates":[-84.31964111329999,46.5297546387],"type":"Point"}
}