{
  "type": "Feature",
  "properties": {
    "iso:country":"CA",
    "sg:address":"6 James St",
    "sg:city":"Courtland",
    "sg:classifiers":[
        {
            "category":"Organizations",
            "subcategory":"Religious Organization",
            "type":"Services"
        }
    ],
    "sg:phone":"+1 519 688 2116",
    "sg:postcode":"N0J 1E0",
    "sg:province":"ON",
    "sg:tags":[
        "church"
    ],
    "wof:name":"Courtland Fellowship Baptist",
    "wof:placetype":"venue"
},
  "geometry": {"coordinates":[-80.63349151609999,42.8422660828],"type":"Point"}
}