{
  "type": "Feature",
  "properties": {
    "addr:full":"PO Box 180 Baker Lake NU X0C 0A0",
    "addr:housenumber":"po",
    "addr:postcode":"x0c 0a0",
    "addr:street":"Box 180 Baker",
    "iso:country":"CA",
    "sg:address":"PO Box 180",
    "sg:city":"Baker Lake",
    "sg:classifiers":[
        {
            "category":"Government",
            "subcategory":"Office",
            "type":"Public Place"
        }
    ],
    "sg:phone":"+1 867 793 2839",
    "sg:postcode":"X0C 0A0",
    "sg:province":"NU",
    "wof:name":"Nunavut Health & Social Svc",
    "wof:placetype":"venue"
},
  "geometry": {"coordinates":[-96.020386,64.317345],"type":"Point"}
}