{
  "type": "Feature",
  "properties": {
    "addr:full":"581 Murphy Rd Sarnia ON N7S 5B6",
    "addr:housenumber":"581",
    "addr:postcode":"n7s 5b6",
    "addr:street":"Murphy Rd",
    "iso:country":"CA",
    "sg:address":"581 Murphy Rd",
    "sg:city":"Sarnia",
    "sg:classifiers":[
        {
            "category":"Restaurant",
            "type":"Food & Drink"
        }
    ],
    "sg:phone":"+1 519 383 8600",
    "sg:postcode":"N7S 5B6",
    "sg:province":"ON",
    "wof:name":"Wharf the Fish & Chips",
    "wof:placetype":"venue"
},
  "geometry": {"coordinates":[-82.366867,42.976879],"type":"Point"}
}