{
  "type": "Feature",
  "properties": {
    "addr:full":"120 Dorothy St Atikokan ON P0T 1C0",
    "addr:housenumber":"120",
    "addr:postcode":"p0t 1c0",
    "addr:street":"Dorothy St",
    "iso:country":"CA",
    "sg:address":"120 Dorothy St",
    "sg:city":"Atikokan",
    "sg:classifiers":[
        {
            "category":"Health Services",
            "subcategory":"Hospital",
            "type":"Services"
        }
    ],
    "sg:phone":"+1 807 597 4215",
    "sg:postcode":"P0T 1C0",
    "sg:province":"ON",
    "wof:name":"Atikokan General Hospital",
    "wof:placetype":"venue"
},
  "geometry": {"coordinates":[-91.59935760499999,48.7540817261],"type":"Point"}
}