{
  "type": "Feature",
  "properties": {
    "addr:full":"PO Box 309 Ear Falls ON P0V 1T0",
    "addr:housenumber":"po",
    "addr:postcode":"p0v 1t0",
    "addr:street":"Box 309",
    "iso:country":"CA",
    "sg:address":"PO Box 309",
    "sg:city":"Ear Falls",
    "sg:classifiers":[
        {
            "category":"Recreation",
            "type":"Entertainment"
        }
    ],
    "sg:phone":"+1 807 222 3716",
    "sg:postcode":"P0V 1T0",
    "sg:province":"ON",
    "sg:tags":[
        "center"
    ],
    "wof:name":"Ear Falls Recreation Dept",
    "wof:placetype":"venue"
},
  "geometry": {"coordinates":[-93.234421,50.638622],"type":"Point"}
}