{
  "type": "Feature",
  "properties": {
    "addr:full":"10 Great Lakes Dr Brampton ON L6R 2K7",
    "addr:housenumber":"10",
    "addr:postcode":"l6r 2k7",
    "addr:street":"Great Lakes Dr",
    "iso:country":"CA",
    "sg:address":"10 Great Lakes Dr",
    "sg:city":"Brampton",
    "sg:classifiers":[
        {
            "category":"Autos & Motor Vehicles",
            "subcategory":"Auto Supplies",
            "type":"Retail Goods"
        }
    ],
    "sg:phone":"+1 905 793 4800",
    "sg:postcode":"L6R 2K7",
    "sg:province":"ON",
    "sg:tags":[
        "repairing",
        "automobile",
        "parts"
    ],
    "wof:name":"Canadian Tire",
    "wof:placetype":"venue"
},
  "geometry": {"coordinates":[-79.76084899999999,43.73069],"type":"Point"}
}