{
  "type": "Feature",
  "properties": {
    "iso:country":"CA",
    "sg:address":"10 Great Lakes Dr",
    "sg:city":"Brampton",
    "sg:classifiers":[
        {
            "category":"Autos & Motor Vehicles",
            "subcategory":"Auto Supplies",
            "type":"Retail Goods"
        }
    ],
    "sg:phone":"+1 905 793 4800",
    "sg:postcode":"L6R 2K7",
    "sg:province":"ON",
    "sg:tags":[
        "repairing",
        "automobile",
        "parts"
    ],
    "wof:name":"Canadian Tire",
    "wof:placetype":"venue"
},
  "geometry": {"coordinates":[-79.760849,43.73069],"type":"Point"}
}