{
  "type": "Feature",
  "properties": {
    "iso:country":"CA",
    "sg:city":"Port Coquitlam",
    "sg:classifiers":[
        {
            "category":"Building & Trades",
            "subcategory":"Construction",
            "type":"Services"
        }
    ],
    "sg:phone":"+1 604 464 6499",
    "sg:postcode":"V3C 1N1",
    "sg:province":"BC",
    "sg:tags":[
        "railing"
    ],
    "wof:name":"Arc Aluminum Works",
    "wof:placetype":"venue"
},
  "geometry": {"coordinates":[-122.772232,49.253433],"type":"Point"}
}