{
  "type": "Feature",
  "properties": {
    "addr:full":"8497 Rue Hochelaga Montreal QC H1L 2M1",
    "addr:housenumber":"8497",
    "addr:postcode":"h1l 2m1",
    "addr:street":"Rue Hochelaga",
    "iso:country":"CA",
    "sg:address":"8497 Rue Hochelaga",
    "sg:city":"Montreal",
    "sg:classifiers":[
        {
            "category":"Building & Trades",
            "subcategory":"Construction",
            "type":"Services"
        }
    ],
    "sg:phone":"+1 514 351 9760",
    "sg:postcode":"H1L 2M1",
    "sg:province":"QC",
    "sg:tags":[
        "repairing",
        "remodeling",
        "contractor"
    ],
    "wof:name":"Renovations Ray Angers",
    "wof:placetype":"venue"
},
  "geometry": {"coordinates":[-73.521446,45.599121],"type":"Point"}
}