{
  "type": "Feature",
  "properties": {
    "addr:full":"2001 University Ave E # 101 Waterloo ON N2K 4K4",
    "addr:housenumber":"2001",
    "addr:postcode":"n2k 4k4",
    "addr:street":"University Ave E # 101",
    "iso:country":"CA",
    "sg:address":"2001 University Ave E # 101",
    "sg:city":"Waterloo",
    "sg:classifiers":[
        {
            "category":"Personal",
            "type":"Services"
        }
    ],
    "sg:phone":"+1 519 580 9905",
    "sg:postcode":"N2K 4K4",
    "sg:province":"ON",
    "sg:tags":[
        "program",
        "physical",
        "exercise",
        "fitness"
    ],
    "wof:name":"Physico Performance Personal",
    "wof:placetype":"venue"
},
  "geometry": {"coordinates":[-80.5090103149,43.5186195374],"type":"Point"}
}