{
  "type": "Feature",
  "properties": {
    "addr:full":"1070 Boul Des Laurentides Laval QC H7G 2W1",
    "addr:housenumber":"1070",
    "addr:postcode":"qc h7g 2w1",
    "addr:street":"Boul Des Laurentides",
    "iso:country":"CA",
    "sg:address":"1070 Boul Des Laurentides",
    "sg:city":"Laval",
    "sg:classifiers":[
        {
            "category":"Autos & Motor Vehicles",
            "subcategory":"Automobile Sales",
            "type":"Retail Goods"
        }
    ],
    "sg:phone":"+1 450 975 7787",
    "sg:postcode":"H7G 2W1",
    "sg:province":"QC",
    "sg:tags":[
        "car",
        "dealer"
    ],
    "wof:name":"Groupe Automobile Enr",
    "wof:placetype":"venue"
},
  "geometry": {"coordinates":[-73.699051,45.576275],"type":"Point"}
}