{
  "type": "Feature",
  "properties": {
    "addr:full":"Perth ON K7H 3C8",
    "addr:postcode":"k7h 3c8",
    "iso:country":"CA",
    "sg:city":"Perth",
    "sg:classifiers":[
        {
            "category":"Arts & Performance",
            "subcategory":"Theater",
            "type":"Entertainment"
        }
    ],
    "sg:phone":"+1 613 267 0008",
    "sg:postcode":"K7H 3C8",
    "sg:province":"ON",
    "sg:tags":[
        "live",
        "music"
    ],
    "wof:name":"Ashby's Orca Sound",
    "wof:placetype":"venue"
},
  "geometry": {"coordinates":[-76.2483291626,44.8989448547],"type":"Point"}
}