{
  "type": "Feature",
  "properties": {
    "addr:full":"1011 Victoria Rd Revelstoke BC V0E 2S0",
    "addr:housenumber":"1011",
    "addr:postcode":"v0e 2s0",
    "addr:street":"Victoria Rd",
    "iso:country":"CA",
    "sg:address":"1011 Victoria Rd",
    "sg:city":"Revelstoke",
    "sg:classifiers":[
        {
            "category":"Autos & Motor Vehicles",
            "subcategory":"Fuel & Gas Station",
            "type":"Retail Goods"
        }
    ],
    "sg:phone":"+1 250 837 4107",
    "sg:postcode":"V0E 2S0",
    "sg:province":"BC",
    "sg:tags":[
        "oil"
    ],
    "wof:name":"Fas Gas Mountain Peaks Svc",
    "wof:placetype":"venue"
},
  "geometry": {"coordinates":[-118.196281,50.990639],"type":"Point"}
}