{
  "type": "Feature",
  "properties": {
    "iso:country":"CA",
    "sg:address":"366 North Front St",
    "sg:city":"Belleville",
    "sg:classifiers":[
        {
            "category":"Shopping",
            "subcategory":"Used Merchandise",
            "type":"Retail Goods"
        }
    ],
    "sg:phone":"+1 613 968 4088",
    "sg:postcode":"K8P 5E6",
    "sg:province":"ON",
    "sg:tags":[
        "second",
        "store",
        "hand"
    ],
    "wof:name":"Goodwill",
    "wof:placetype":"venue"
},
  "geometry": {"coordinates":[-77.396111,44.187332],"type":"Point"}
}