{
  "type": "Feature",
  "properties": {
    "addr:full":"Toronto ON M5H 3K6",
    "addr:postcode":"m5h 3k6",
    "iso:country":"CA",
    "sg:city":"Toronto",
    "sg:classifiers":[
        {
            "category":"Professional",
            "subcategory":"Secretarial Services",
            "type":"Services"
        }
    ],
    "sg:phone":"+1 416 861 0835",
    "sg:postcode":"M5H 3K6",
    "sg:province":"ON",
    "sg:tags":[
        "convention",
        "court",
        "reporter"
    ],
    "wof:name":"Anshan Alternative Dispute",
    "wof:placetype":"venue"
},
  "geometry": {"coordinates":[-79.3835678101,43.6508178711],"type":"Point"}
}