{
  "type": "Feature",
  "properties": {
    "addr:full":"12909 127 St NW Edmonton AB T5L 1B1",
    "addr:housenumber":"12909",
    "addr:postcode":"t5l 1b1",
    "addr:street":"127 St Nw",
    "iso:country":"CA",
    "sg:address":"12909 127 St NW",
    "sg:city":"Edmonton",
    "sg:classifiers":[
        {
            "category":"Building & Trades",
            "subcategory":"Equipment Rental",
            "type":"Services"
        }
    ],
    "sg:phone":"+1 780 413 9469",
    "sg:postcode":"T5L 1B1",
    "sg:province":"AB",
    "sg:tags":[
        "player",
        "recorder",
        "video"
    ],
    "wof:name":"Adult Super Store",
    "wof:placetype":"venue"
},
  "geometry": {"coordinates":[-113.54098500000001,53.587837],"type":"Point"}
}