{
  "type": "Feature",
  "properties": {
    "addr:full":"1045 Elgin St N Cambridge ON N1R 8J4",
    "addr:housenumber":"1045",
    "addr:postcode":"n1r 8j4",
    "addr:street":"Elgin St N",
    "iso:country":"CA",
    "sg:address":"1045 Elgin St N",
    "sg:city":"Cambridge",
    "sg:classifiers":[
        {
            "category":"Restaurant",
            "type":"Food & Drink"
        }
    ],
    "sg:phone":"+1 519 621 7777",
    "sg:postcode":"N1R 8J4",
    "sg:province":"ON",
    "wof:name":"Pizza Nova",
    "wof:placetype":"venue"
},
  "geometry": {"coordinates":[-80.303307,43.391129],"type":"Point"}
}