{
  "type": "Feature",
  "properties": {
    "addr:full":"Quebec QC G2J 1A7",
    "addr:postcode":"g2j 1a7",
    "iso:country":"CA",
    "sg:city":"Quebec",
    "sg:classifiers":[
        {
            "category":"Restaurant",
            "type":"Food & Drink"
        }
    ],
    "sg:phone":"+1 418 627 7766",
    "sg:postcode":"G2J 1A7",
    "sg:province":"QC",
    "wof:name":"Restaurant Le Preben Inc",
    "wof:placetype":"venue"
},
  "geometry": {"coordinates":[-71.270943,46.834949],"type":"Point"}
}