{
  "type": "Feature",
  "properties": {
    "addr:full":"231 Huot St South Porcupine ON P0N 1H0",
    "addr:housenumber":"231",
    "addr:postcode":"p0n 1h0",
    "addr:street":"Huot St",
    "iso:country":"CA",
    "sg:address":"231 Huot St",
    "sg:city":"South Porcupine",
    "sg:classifiers":[
        {
            "category":"Social Services",
            "type":"Services"
        }
    ],
    "sg:phone":"+1 705 235 4831",
    "sg:postcode":"P0N 1H0",
    "sg:province":"ON",
    "sg:tags":[
        "organization",
        "welfare"
    ],
    "wof:name":"Finnish Social Svc",
    "wof:placetype":"venue"
},
  "geometry": {"coordinates":[-81.206284,48.4855],"type":"Point"}
}