{
  "type": "Feature",
  "properties": {
    "addr:full":"94 Rue Jacques-Cartier E Chicoutimi QC G7H 1Y3",
    "addr:housenumber":"94",
    "addr:postcode":"g7h 1y3",
    "addr:street":"Rue Jacques-Cartier E",
    "iso:country":"CA",
    "sg:address":"94 Rue Jacques-Cartier E",
    "sg:city":"Chicoutimi",
    "sg:classifiers":[
        {
            "category":"Travel",
            "subcategory":"Travel Agent",
            "type":"Entertainment"
        }
    ],
    "sg:phone":"+1 418 690 2840",
    "sg:postcode":"G7H 1Y3",
    "sg:province":"QC",
    "sg:tags":[
        "agency",
        "bureau"
    ],
    "wof:name":"Voyages Aqua-Sud Enr",
    "wof:placetype":"venue"
},
  "geometry": {"coordinates":[-71.0656051636,48.4264373779],"type":"Point"}
}