{
  "type": "Feature",
  "properties": {
    "addr:full":"Kelowna BC V1Y 8C7",
    "addr:postcode":"v1y 8c7",
    "iso:country":"CA",
    "sg:city":"Kelowna",
    "sg:classifiers":[
        {
            "category":"Social Services",
            "type":"Services"
        }
    ],
    "sg:phone":"+1 250 763 4613",
    "sg:postcode":"V1Y 8C7",
    "sg:province":"BC",
    "sg:tags":[
        "organization",
        "welfare"
    ],
    "wof:name":"Elizabeth Fry Society",
    "wof:placetype":"venue"
},
  "geometry": {"coordinates":[-119.49587200000001,49.884403],"type":"Point"}
}