{
  "type": "Feature",
  "properties": {
    "iso:country":"CA",
    "sg:address":"47 Peninsula Rd",
    "sg:city":"Marathon",
    "sg:classifiers":[
        {
            "category":"Wholesale",
            "subcategory":"Machinery & Supplies",
            "type":"Manufacturing & Wholesale Goods"
        }
    ],
    "sg:phone":"+1 807 229 1853",
    "sg:postcode":"P0T 2E0",
    "sg:province":"ON",
    "sg:tags":[
        "equipment",
        "safety",
        "clothing"
    ],
    "wof:name":"Superior Safety",
    "wof:placetype":"venue"
},
  "geometry": {"coordinates":[-86.376083374,48.7220001221],"type":"Point"}
}