{
  "type": "Feature",
  "properties": {
    "addr:full":"808 132 Rte RR 1 Cloridorme QC G0E 1G0",
    "addr:housenumber":"132",
    "addr:postcode":"g0e 1g0",
    "addr:street":"Rte Rr 1",
    "iso:country":"CA",
    "sg:address":"808 132 Rte RR 1",
    "sg:city":"Cloridorme",
    "sg:classifiers":[
        {
            "category":"Government",
            "subcategory":"Office",
            "type":"Public Place"
        }
    ],
    "sg:phone":"+1 418 395 2222",
    "sg:postcode":"G0E 1G0",
    "sg:province":"QC",
    "wof:name":"Quebec Transports",
    "wof:placetype":"venue"
},
  "geometry": {"coordinates":[-64.808296,49.165771],"type":"Point"}
}