{
  "type": "Feature",
  "properties": {
    "addr:full":"Gold River BC V0P 1G0",
    "addr:postcode":"v0p 1g0",
    "iso:country":"CA",
    "sg:city":"Gold River",
    "sg:classifiers":[
        {
            "category":"Building & Trades",
            "subcategory":"Equipment Rental",
            "type":"Services"
        }
    ],
    "sg:phone":"+1 250 283 2255",
    "sg:postcode":"V0P 1G0",
    "sg:province":"BC",
    "sg:tags":[
        "aircraft",
        "charter",
        "leasing",
        "company",
        "airline"
    ],
    "wof:name":"Air Nootka",
    "wof:placetype":"venue"
},
  "geometry": {"coordinates":[-126.11862182599999,49.6908302307],"type":"Point"}
}