{
  "type": "Feature",
  "properties": {
    "iso:country":"CA",
    "sg:address":"25 Fairway Heights Dr",
    "sg:city":"Thornhill",
    "sg:classifiers":[
        {
            "category":"Recreation",
            "type":"Entertainment"
        }
    ],
    "sg:phone":"+1 905 889 4833",
    "sg:postcode":"L3T 3X1",
    "sg:province":"ON",
    "sg:tags":[
        "course",
        "golf"
    ],
    "wof:name":"Bayview Country Club Ltd",
    "wof:placetype":"venue"
},
  "geometry": {"coordinates":[-79.376251,43.809647],"type":"Point"}
}