{
  "type": "Feature",
  "properties": {
    "addr:full":"1235 Osprey Dr Ancaster ON L9G 4V5",
    "addr:housenumber":"1235",
    "addr:postcode":"l9g 4v5",
    "addr:street":"Osprey Dr",
    "iso:country":"CA",
    "sg:address":"1235 Osprey Dr",
    "sg:city":"Ancaster",
    "sg:classifiers":[
        {
            "category":"Freight",
            "type":"Transportation"
        }
    ],
    "sg:phone":"+1 905 648 5575",
    "sg:postcode":"L9G 4V5",
    "sg:province":"ON",
    "sg:tags":[
        "commercial",
        "storage"
    ],
    "wof:name":"Ancaster Mini Storage Ltd",
    "wof:placetype":"venue"
},
  "geometry": {"coordinates":[-80.0224227905,43.1933059692],"type":"Point"}
}