{
  "type": "Feature",
  "properties": {
    "addr:full":"Dorval QC H9S 2B7",
    "addr:postcode":"h9s 2b7",
    "iso:country":"CA",
    "sg:city":"Dorval",
    "sg:classifiers":[
        {
            "category":"Health Services",
            "subcategory":"Doctor",
            "type":"Services"
        }
    ],
    "sg:phone":"+1 514 633 1510",
    "sg:postcode":"H9S 2B7",
    "sg:province":"QC",
    "sg:tags":[
        "physician",
        "surgeon"
    ],
    "wof:name":"Lefebvre, Chantal MD",
    "wof:placetype":"venue"
},
  "geometry": {"coordinates":[-73.77886199949999,45.4455871582],"type":"Point"}
}