{
  "type": "Feature",
  "properties": {
    "addr:full":"27 Rue Du Camarguais Blainville QC J7C 4P4",
    "addr:housenumber":"27",
    "addr:postcode":"j7c 4p4",
    "addr:street":"Rue Du Camarguais",
    "iso:country":"CA",
    "sg:address":"27 Rue Du Camarguais",
    "sg:city":"Blainville",
    "sg:classifiers":[
        {
            "category":"Building & Trades",
            "subcategory":"Construction",
            "type":"Services"
        }
    ],
    "sg:phone":"+1 450 433 1804",
    "sg:postcode":"J7C 4P4",
    "sg:province":"QC",
    "sg:tags":[
        "repairing",
        "remodeling",
        "contractor"
    ],
    "wof:name":"Cjo Construction Inc",
    "wof:placetype":"venue"
},
  "geometry": {"coordinates":[-73.8732452393,45.6870117188],"type":"Point"}
}