{
  "type": "Feature",
  "properties": {
    "addr:full":"Vancouver BC V5R 5G8",
    "addr:postcode":"v5r 5g8",
    "iso:country":"CA",
    "sg:city":"Vancouver",
    "sg:classifiers":[
        {
            "category":"Travel",
            "subcategory":"Travel Agent",
            "type":"Entertainment"
        }
    ],
    "sg:phone":"+1 604 438 9454",
    "sg:postcode":"V5R 5G8",
    "sg:province":"BC",
    "sg:tags":[
        "agency",
        "bureau"
    ],
    "wof:name":"Sharman Travel",
    "wof:placetype":"venue"
},
  "geometry": {"coordinates":[-123.055717,49.240925],"type":"Point"}
}