{
  "type": "Feature",
  "properties": {
    "iso:country":"CA",
    "sg:address":"2 Amelia Cres",
    "sg:city":"Winnipeg",
    "sg:classifiers":[
        {
            "category":"Professional",
            "subcategory":"Business Services",
            "type":"Services"
        }
    ],
    "sg:phone":"+1 204 667 9108",
    "sg:postcode":"R2K 3Z3",
    "sg:province":"MB",
    "sg:tags":[
        "drafting"
    ],
    "wof:name":"A & H Design",
    "wof:placetype":"venue"
},
  "geometry": {"coordinates":[-97.0678405762,49.9260482788],"type":"Point"}
}