{
  "type": "Feature",
  "properties": {
    "addr:full":"638 the Queensway Etobicoke ON M8Y 1K5",
    "addr:housenumber":"638",
    "addr:postcode":"m8y 1k5",
    "addr:street":"The Queensway",
    "iso:country":"CA",
    "sg:address":"638 the Queensway",
    "sg:city":"Etobicoke",
    "sg:classifiers":[
        {
            "category":"Travel",
            "subcategory":"Hotels & Motels",
            "type":"Entertainment"
        }
    ],
    "sg:phone":"+1 416 252 5821",
    "sg:postcode":"M8Y 1K5",
    "sg:province":"ON",
    "wof:name":"Queensway Motel",
    "wof:placetype":"venue"
},
  "geometry": {"coordinates":[-79.49691,43.62775],"type":"Point"}
}