{
  "type": "Feature",
  "properties": {
    "addr:full":"411 Main St Grandview MB R0L 0Y0",
    "addr:housenumber":"411",
    "addr:postcode":"r0l 0y0",
    "addr:street":"Main St",
    "iso:country":"CA",
    "sg:address":"411 Main St",
    "sg:city":"Grandview",
    "sg:classifiers":[
        {
            "category":"Professional",
            "subcategory":"Accounting & Tax Preparation",
            "type":"Services"
        }
    ],
    "sg:phone":"+1 204 546 2304",
    "sg:postcode":"R0L 0Y0",
    "sg:province":"MB",
    "sg:tags":[
        "return",
        "filing"
    ],
    "wof:name":"H & R Block Canada Inc",
    "wof:placetype":"venue"
},
  "geometry": {"coordinates":[-100.6996,51.168411],"type":"Point"}
}