{
  "type": "Feature",
  "properties": {
    "addr:full":"2481 Rue Saint-Dominique Jonquiere QC G7X 6K4",
    "addr:housenumber":"2481",
    "addr:postcode":"g7x 6k4",
    "addr:street":"Rue Saint-Dominique",
    "iso:country":"CA",
    "sg:address":"2481 Rue Saint-Dominique",
    "sg:city":"Jonquiere",
    "sg:classifiers":[
        {
            "category":"Personal",
            "subcategory":"Beauty Salon",
            "type":"Services"
        }
    ],
    "sg:phone":"+1 418 695 2223",
    "sg:postcode":"G7X 6K4",
    "sg:province":"QC",
    "wof:name":"Institut Matis Legale Beaute",
    "wof:placetype":"venue"
},
  "geometry": {"coordinates":[-71.255554,48.410957],"type":"Point"}
}