{
  "type": "Feature",
  "properties": {
    "addr:full":"Resolute NU X0A 0V0",
    "addr:postcode":"x0a 0v0",
    "iso:country":"CA",
    "sg:city":"Resolute",
    "sg:classifiers":[
        {
            "category":"Education",
            "subcategory":"College",
            "type":"Public Place"
        }
    ],
    "sg:phone":"+1 867 252 3782",
    "sg:postcode":"X0A 0V0",
    "sg:province":"NU",
    "sg:tags":[
        "academic",
        "school"
    ],
    "wof:name":"Arctic College",
    "wof:placetype":"venue"
},
  "geometry": {"coordinates":[-94.8399353027,74.6945266724],"type":"Point"}
}