{
  "type": "Feature",
  "properties": {
    "addr:full":"721 Bernard Ave Kelowna BC V1Y 6P6",
    "addr:housenumber":"721",
    "addr:postcode":"v1y 6p6",
    "addr:street":"Bernard Ave",
    "iso:country":"CA",
    "sg:address":"721 Bernard Ave",
    "sg:city":"Kelowna",
    "sg:classifiers":[
        {
            "category":"Organizations",
            "subcategory":"Religious Organization",
            "type":"Services"
        }
    ],
    "sg:phone":"+1 250 762 5777",
    "sg:postcode":"V1Y 6P6",
    "sg:province":"BC",
    "sg:tags":[
        "church"
    ],
    "wof:name":"Kamploops Okanagan Presbytery",
    "wof:placetype":"venue"
},
  "geometry": {"coordinates":[-119.48744201700001,49.8861579895],"type":"Point"}
}