{
  "type": "Feature",
  "properties": {
    "addr:full":"24 11th St Weyburn SK S4H 1H9",
    "addr:housenumber":"24",
    "addr:postcode":"s4h 1h9",
    "addr:street":"11Th St",
    "iso:country":"CA",
    "sg:address":"24 11th St",
    "sg:city":"Weyburn",
    "sg:classifiers":[
        {
            "category":"Building & Trades",
            "subcategory":"Construction",
            "type":"Services"
        }
    ],
    "sg:phone":"+1 306 842 7162",
    "sg:postcode":"S4H 1H9",
    "sg:province":"SK",
    "sg:tags":[
        "concrete",
        "product",
        "general",
        "contractor"
    ],
    "wof:name":"Concrete Jungle",
    "wof:placetype":"venue"
},
  "geometry": {"coordinates":[-103.84279600000001,49.658249],"type":"Point"}
}