{
  "type": "Feature",
  "properties": {
    "addr:full":"84 Boul Harwood Vaudreuil-Dorion QC J7V 1X8",
    "addr:housenumber":"84",
    "addr:postcode":"j7v 1x8",
    "addr:street":"Boul Harwood",
    "iso:country":"CA",
    "sg:address":"84 Boul Harwood",
    "sg:city":"Vaudreuil-Dorion",
    "sg:classifiers":[
        {
            "category":"Recreation",
            "type":"Entertainment"
        }
    ],
    "sg:phone":"+1 450 455 3610",
    "sg:postcode":"J7V 1X8",
    "sg:province":"QC",
    "sg:tags":[
        "parlor",
        "billiard"
    ],
    "wof:name":"Billard Riviera",
    "wof:placetype":"venue"
},
  "geometry": {"coordinates":[-74.008827,45.384434],"type":"Point"}
}