{
  "type": "Feature",
  "properties": {
    "addr:full":"26 Willow St Waubaushene ON L0K 2C0",
    "addr:housenumber":"26",
    "addr:postcode":"l0k 2c0",
    "addr:street":"Willow St",
    "iso:country":"CA",
    "sg:address":"26 Willow St",
    "sg:city":"Waubaushene",
    "sg:classifiers":[
        {
            "category":"Organizations",
            "subcategory":"Community Association",
            "type":"Services"
        }
    ],
    "sg:phone":"+1 705 538 2344",
    "sg:postcode":"L0K 2C0",
    "sg:province":"ON",
    "sg:tags":[
        "club"
    ],
    "wof:name":"Royal Canadian Legion",
    "wof:placetype":"venue"
},
  "geometry": {"coordinates":[-79.7060546875,44.7573509216],"type":"Point"}
}