{
  "type": "Feature",
  "properties": {
    "addr:full":"Waterloo ON N2V 2C9",
    "addr:postcode":"n2v 2c9",
    "iso:country":"CA",
    "sg:city":"Waterloo",
    "sg:classifiers":[
        {
            "category":"Banks & Credit Unions",
            "subcategory":"Investment Brokerage",
            "type":"Services"
        }
    ],
    "sg:phone":"+1 519 747 3253",
    "sg:postcode":"N2V 2C9",
    "sg:province":"ON",
    "sg:tags":[
        "consultant",
        "planning",
        "financial"
    ],
    "wof:name":"Wellman & Assoc",
    "wof:placetype":"venue"
},
  "geometry": {"coordinates":[-80.52690124510001,43.5064125061],"type":"Point"}
}