{
  "type": "Feature",
  "properties": {
    "addr:full":"1881 Portage Ave Winnipeg MB R3J 0H3",
    "addr:housenumber":"1881",
    "addr:postcode":"r3j 0h3",
    "addr:street":"Portage Ave",
    "iso:country":"CA",
    "sg:address":"1881 Portage Ave",
    "sg:city":"Winnipeg",
    "sg:classifiers":[
        {
            "category":"Organizations",
            "subcategory":"Religious Organization",
            "type":"Services"
        }
    ],
    "sg:phone":"+1 204 885 1694",
    "sg:postcode":"R3J 0H3",
    "sg:province":"MB",
    "sg:tags":[
        "church"
    ],
    "wof:name":"Assiniboine Pentecostal Church",
    "wof:placetype":"venue"
},
  "geometry": {"coordinates":[-97.2193603516,49.8788032532],"type":"Point"}
}