{
  "type": "Feature",
  "properties": {
    "addr:full":"7 Carlson St Kitimat BC V8C 1A9",
    "addr:housenumber":"7",
    "addr:postcode":"bc v8c 1a9",
    "addr:street":"Carlson St",
    "iso:country":"CA",
    "sg:address":"7 Carlson St",
    "sg:city":"Kitimat",
    "sg:classifiers":[
        {
            "category":"Education",
            "subcategory":"School",
            "type":"Public Place"
        }
    ],
    "sg:phone":"+1 250 632 7180",
    "sg:postcode":"V8C 1A9",
    "sg:province":"BC",
    "wof:name":"Roy Wilcox Elementary School",
    "wof:placetype":"venue"
},
  "geometry": {"coordinates":[-128.64596557600001,54.0656242371],"type":"Point"}
}