{
  "type": "Feature",
  "properties": {
    "iso:country":"CA",
    "sg:address":"4842 Av Carlton",
    "sg:city":"Montreal",
    "sg:classifiers":[
        {
            "category":"Freight",
            "type":"Transportation"
        }
    ],
    "sg:phone":"+1 514 738 7411",
    "sg:postcode":"H3W 1G6",
    "sg:province":"QC",
    "sg:tags":[
        "cartage"
    ],
    "wof:name":"L Finkelstein Cartage",
    "wof:placetype":"venue"
},
  "geometry": {"coordinates":[-73.6400680542,45.4944572449],"type":"Point"}
}