{
  "type": "Feature",
  "properties": {
    "addr:full":"Pefferlaw ON L0E 1N0",
    "addr:postcode":"l0e 1n0",
    "iso:country":"CA",
    "sg:city":"Pefferlaw",
    "sg:classifiers":[
        {
            "category":"Social Services",
            "type":"Services"
        }
    ],
    "sg:phone":"+1 705 437 3811",
    "sg:postcode":"L0E 1N0",
    "sg:province":"ON",
    "sg:tags":[
        "housing",
        "assistance"
    ],
    "wof:name":"Pefferlaw & Lions Housing Corp",
    "wof:placetype":"venue"
},
  "geometry": {"coordinates":[-79.19379425050001,44.3113632202],"type":"Point"}
}