{
  "type": "Feature",
  "properties": {
    "iso:country":"CA",
    "sg:address":"5734 Gateway Blvd NW",
    "sg:city":"Edmonton",
    "sg:classifiers":[
        {
            "category":"Retail",
            "subcategory":"Repair Shop",
            "type":"Services"
        }
    ],
    "sg:phone":"+1 780 434 7637",
    "sg:postcode":"T6H 2H5",
    "sg:province":"AB",
    "sg:tags":[
        "welding"
    ],
    "wof:name":"Lennox Welding & Supply Ltd",
    "wof:placetype":"venue"
},
  "geometry": {"coordinates":[-113.492104,53.493954],"type":"Point"}
}