{
  "type": "Feature",
  "properties": {
    "addr:full":"909 15 St SW Calgary AB T3C 1E5",
    "addr:housenumber":"15",
    "addr:postcode":"t3c 1e5",
    "addr:street":"909;St Sw",
    "iso:country":"CA",
    "sg:address":"909 15 St SW",
    "sg:city":"Calgary",
    "sg:classifiers":[
        {
            "category":"Autos & Motor Vehicles",
            "subcategory":"Automobile Sales",
            "type":"Retail Goods"
        }
    ],
    "sg:phone":"+1 403 232 6400",
    "sg:postcode":"T3C 1E5",
    "sg:province":"AB",
    "sg:tags":[
        "car",
        "dealer"
    ],
    "wof:name":"Hyatt Mercedes-Benz",
    "wof:placetype":"venue"
},
  "geometry": {"coordinates":[-114.096160889,51.0461044312],"type":"Point"}
}