{
  "type": "Feature",
  "properties": {
    "addr:full":"91 Cumberland St Toronto ON M5R 3N7",
    "addr:housenumber":"91",
    "addr:postcode":"m5r 3n7",
    "addr:street":"Cumberland St",
    "iso:country":"CA",
    "sg:address":"91 Cumberland St",
    "sg:city":"Toronto",
    "sg:classifiers":[
        {
            "category":"Shopping",
            "subcategory":"Hobbies, Toys, & Games",
            "type":"Retail Goods"
        }
    ],
    "sg:phone":"+1 416 926 8996",
    "sg:postcode":"M5R 3N7",
    "sg:province":"ON",
    "wof:name":"Kidding Awound",
    "wof:placetype":"venue"
},
  "geometry": {"coordinates":[-79.390221,43.670319],"type":"Point"}
}