{
  "type": "Feature",
  "properties": {
    "addr:full":"4750 Boul Des Forges Trois-Rivieres QC G8Y 1W8",
    "addr:housenumber":"4750",
    "addr:postcode":"g8y 1w8",
    "addr:street":"Boul Des Forges Trois-Rivieres",
    "iso:country":"CA",
    "sg:address":"4750 Boul Des Forges",
    "sg:city":"Trois-Rivieres",
    "sg:classifiers":[
        {
            "category":"Insurance",
            "subcategory":"Insurance Agent",
            "type":"Services"
        }
    ],
    "sg:phone":"+1 819 379 6211",
    "sg:postcode":"G8Y 1W8",
    "sg:province":"QC",
    "wof:name":"Assurances Generales-Caisses",
    "wof:placetype":"venue"
},
  "geometry": {"coordinates":[-72.5908050537,46.3601646423],"type":"Point"}
}