{
  "type": "Feature",
  "properties": {
    "addr:full":"19881 Charing Cross Rd Cedar Springs ON N0P 1E0",
    "addr:housenumber":"19881",
    "addr:postcode":"n0p 1e0",
    "addr:street":"Charing Cross Rd",
    "iso:country":"CA",
    "sg:address":"19881 Charing Cross Rd",
    "sg:city":"Cedar Springs",
    "sg:classifiers":[
        {
            "category":"Food & Beverages",
            "subcategory":"Fruits & Vegetables",
            "type":"Retail Goods"
        }
    ],
    "sg:phone":"+1 519 676 8464",
    "sg:postcode":"N0P 1E0",
    "sg:province":"ON",
    "sg:tags":[
        "produce"
    ],
    "wof:name":"Thompson's Orchards",
    "wof:placetype":"venue"
},
  "geometry": {"coordinates":[-82.04834700000001,42.294308],"type":"Point"}
}