{
  "type": "Feature",
  "properties": {
    "addr:full":"St Albert AB T8N 1M9",
    "addr:postcode":"t8n 1m9",
    "iso:country":"CA",
    "sg:city":"St Albert",
    "sg:classifiers":[
        {
            "category":"Retail",
            "subcategory":"Repair Shop",
            "type":"Services"
        }
    ],
    "sg:phone":"+1 780 973 6518",
    "sg:postcode":"T8N 1M9",
    "sg:province":"AB",
    "sg:tags":[
        "welding"
    ],
    "wof:name":"St Albert Welding & Fab Ltd",
    "wof:placetype":"venue"
},
  "geometry": {"coordinates":[-113.62735000000001,53.633518],"type":"Point"}
}