{
  "type": "Feature",
  "properties": {
    "addr:full":"25 Boul Du Plateau # C Hull QC J9A 3G1",
    "addr:housenumber":"25",
    "addr:postcode":"j9a 3g1",
    "addr:street":"Boul Du Plateau # C",
    "iso:country":"CA",
    "sg:address":"25 Boul Du Plateau # C",
    "sg:city":"Hull",
    "sg:classifiers":[
        {
            "category":"Shopping",
            "subcategory":"Bicycles & Sporting Goods",
            "type":"Retail Goods"
        }
    ],
    "sg:phone":"+1 819 777 2222",
    "sg:postcode":"J9A 3G1",
    "sg:province":"QC",
    "wof:name":"Sports Experts Hull",
    "wof:placetype":"venue"
},
  "geometry": {"coordinates":[-75.769203186,45.4366531372],"type":"Point"}
}