{
  "type": "Feature",
  "properties": {
    "addr:full":"443 Bell St Cowansville QC J2K 3E3",
    "addr:housenumber":"443",
    "addr:postcode":"j2k 3e3",
    "addr:street":"Bell St",
    "iso:country":"CA",
    "sg:address":"443 Bell St",
    "sg:city":"Cowansville",
    "sg:classifiers":[
        {
            "category":"Social Services",
            "type":"Services"
        }
    ],
    "sg:phone":"+1 450 263 1505",
    "sg:postcode":"J2K 3E3",
    "sg:province":"QC",
    "sg:tags":[
        "organization",
        "welfare"
    ],
    "wof:name":"Anglophone Brome-Missiquoi",
    "wof:placetype":"venue"
},
  "geometry": {"coordinates":[-72.7668762207,45.21667099],"type":"Point"}
}