{
  "type": "Feature",
  "properties": {
    "addr:full":"290 19th Ave NE Swift Current SK S9H 2Y3",
    "addr:housenumber":"290",
    "addr:postcode":"s9h 2y3",
    "addr:street":"19Th Ave Ne",
    "iso:country":"CA",
    "sg:address":"290 19th Ave NE",
    "sg:city":"Swift Current",
    "sg:classifiers":[
        {
            "category":"Organizations",
            "subcategory":"Religious Organization",
            "type":"Services"
        }
    ],
    "sg:phone":"+1 306 773 2362",
    "sg:postcode":"S9H 2Y3",
    "sg:province":"SK",
    "sg:tags":[
        "church"
    ],
    "wof:name":"Church of the Open Bible Agc",
    "wof:placetype":"venue"
},
  "geometry": {"coordinates":[-107.77357499999999,50.286961],"type":"Point"}
}