{
  "type": "Feature",
  "properties": {
    "addr:full":"1180 Simcoe St N Oshawa ON L1G 4W8",
    "addr:housenumber":"1180",
    "addr:postcode":"l1g 4w8",
    "addr:street":"Simcoe St N",
    "iso:country":"CA",
    "sg:address":"1180 Simcoe St N",
    "sg:city":"Oshawa",
    "sg:classifiers":[
        {
            "category":"Restaurant",
            "type":"Food & Drink"
        }
    ],
    "sg:phone":"+1 905 436 9333",
    "sg:postcode":"L1G 4W8",
    "sg:province":"ON",
    "wof:name":"Amadeus Seafood Steak House",
    "wof:placetype":"venue"
},
  "geometry": {"coordinates":[-78.877342,43.928707],"type":"Point"}
}