{
  "type": "Feature",
  "properties": {
    "addr:full":"3077 New St Burlington ON L7N 1M6",
    "addr:housenumber":"3077",
    "addr:postcode":"l7n 1m6",
    "addr:street":"New St",
    "iso:country":"CA",
    "sg:address":"3077 New St",
    "sg:city":"Burlington",
    "sg:classifiers":[
        {
            "category":"Health Services",
            "subcategory":"Medical Lab",
            "type":"Services"
        }
    ],
    "sg:phone":"+1 905 631 3200",
    "sg:postcode":"L7N 1M6",
    "sg:province":"ON",
    "sg:tags":[
        "laboratory"
    ],
    "wof:name":"Ceram Art",
    "wof:placetype":"venue"
},
  "geometry": {"coordinates":[-79.7831039429,43.3405570984],"type":"Point"}
}