{
  "type": "Feature",
  "properties": {
    "addr:full":"5054 Rue DE Charleroi Montreal-Nord QC H1G 2Z5",
    "addr:housenumber":"5054",
    "addr:postcode":"h1g 2z5",
    "addr:street":"Rue De Charleroi",
    "iso:country":"CA",
    "sg:address":"5054 Rue DE Charleroi",
    "sg:city":"Montreal-Nord",
    "sg:classifiers":[
        {
            "category":"Shopping",
            "subcategory":"Clothing, Apparel, & Fashions",
            "type":"Retail Goods"
        }
    ],
    "sg:phone":"+1 514 326 3842",
    "sg:postcode":"H1G 2Z5",
    "sg:province":"QC",
    "sg:tags":[
        "work"
    ],
    "wof:name":"Vetements-Travail Charbonneau",
    "wof:placetype":"venue"
},
  "geometry": {"coordinates":[-73.62665557859999,45.5990715027],"type":"Point"}
}