{
  "type": "Feature",
  "properties": {
    "addr:full":"Hamilton ON L9C 3A6",
    "addr:postcode":"l9c 3a6",
    "iso:country":"CA",
    "sg:city":"Hamilton",
    "sg:classifiers":[
        {
            "category":"Building & Trades",
            "subcategory":"Equipment Rental",
            "type":"Services"
        }
    ],
    "sg:phone":"+1 905 385 3226",
    "sg:postcode":"L9C 3A6",
    "sg:province":"ON",
    "sg:tags":[
        "yard",
        "contractor"
    ],
    "wof:name":"Stephenson's Rental Ctr",
    "wof:placetype":"venue"
},
  "geometry": {"coordinates":[-79.8843841553,43.2218818665],"type":"Point"}
}