{
  "type": "Feature",
  "properties": {
    "iso:country":"CA",
    "sg:city":"London",
    "sg:classifiers":[
        {
            "category":"Food & Beverages",
            "subcategory":"Groceries & Convenience Stores",
            "type":"Retail Goods"
        }
    ],
    "sg:phone":"+1 519 672 2363",
    "sg:postcode":"N6A 1C5",
    "sg:province":"ON",
    "sg:tags":[
        "product"
    ],
    "wof:name":"Snack 'N Bake",
    "wof:placetype":"venue"
},
  "geometry": {"coordinates":[-81.2505950928,42.9822502136],"type":"Point"}
}