{
  "type": "Feature",
  "properties": {
    "addr:full":"764 Notre Dame Ave Winnipeg MB R3E 0L9",
    "addr:housenumber":"764",
    "addr:postcode":"r3e 0l9",
    "addr:street":"Notre Dame Ave",
    "iso:country":"CA",
    "sg:address":"764 Notre Dame Ave",
    "sg:city":"Winnipeg",
    "sg:classifiers":[
        {
            "category":"Retail",
            "subcategory":"Self-service Laundry",
            "type":"Services"
        }
    ],
    "sg:phone":"+1 204 772 4263",
    "sg:postcode":"R3E 0L9",
    "sg:province":"MB",
    "wof:name":"Imperial Coin-Op Laundry",
    "wof:placetype":"venue"
},
  "geometry": {"coordinates":[-97.1626205444,49.902256012],"type":"Point"}
}