{
  "type": "Feature",
  "properties": {
    "addr:full":"1835 Gordon Dr Kelowna BC V1Y 3H5",
    "addr:housenumber":"1835",
    "addr:postcode":"v1y 3h5",
    "addr:street":"Gordon Dr",
    "iso:country":"CA",
    "sg:address":"1835 Gordon Dr",
    "sg:city":"Kelowna",
    "sg:classifiers":[
        {
            "category":"Shopping",
            "subcategory":"Clothing, Apparel, & Fashions",
            "type":"Retail Goods"
        }
    ],
    "sg:phone":"+1 250 860 0267",
    "sg:postcode":"V1Y 3H5",
    "sg:province":"BC",
    "wof:name":"Winners Apparel Ltd",
    "wof:placetype":"venue"
},
  "geometry": {"coordinates":[-119.476799011,49.881023407],"type":"Point"}
}