{
  "type": "Feature",
  "properties": {
    "addr:full":"75 Hale Rd Brampton ON L6W 3J9",
    "addr:housenumber":"75",
    "addr:postcode":"l6w 3j9",
    "addr:street":"Hale Rd",
    "iso:country":"CA",
    "sg:address":"75 Hale Rd",
    "sg:city":"Brampton",
    "sg:classifiers":[
        {
            "category":"Autos & Motor Vehicles",
            "subcategory":"Auto Supplies",
            "type":"Retail Goods"
        }
    ],
    "sg:phone":"+1 905 455 9595",
    "sg:postcode":"L6W 3J9",
    "sg:province":"ON",
    "sg:tags":[
        "automobile",
        "parts"
    ],
    "wof:name":"Carquest",
    "wof:placetype":"venue"
},
  "geometry": {"coordinates":[-79.7220535278,43.6864967346],"type":"Point"}
}