{
  "type": "Feature",
  "properties": {
    "addr:full":"200 Picton St E Hamilton ON L8L 3W9",
    "addr:housenumber":"200",
    "addr:postcode":"l8l 3w9",
    "addr:street":"Picton St E",
    "iso:country":"CA",
    "sg:address":"200 Picton St E",
    "sg:city":"Hamilton",
    "sg:classifiers":[
        {
            "category":"Building & Trades",
            "subcategory":"Construction",
            "type":"Services"
        }
    ],
    "sg:phone":"+1 905 528 5491",
    "sg:postcode":"L8L 3W9",
    "sg:province":"ON",
    "sg:tags":[
        "stone",
        "repairer",
        "builder",
        "chimney"
    ],
    "wof:name":"Harms, Hilton H",
    "wof:placetype":"venue"
},
  "geometry": {"coordinates":[-79.855301,43.267666],"type":"Point"}
}