{
  "type": "Feature",
  "properties": {
    "addr:full":"55 Meighen Ave Portage LA Prairie MB R1N 3K7",
    "addr:housenumber":"55",
    "addr:postcode":"r1n 3k7",
    "addr:street":"Meighen Ave",
    "iso:country":"CA",
    "sg:address":"55 Meighen Ave",
    "sg:city":"Portage LA Prairie",
    "sg:classifiers":[
        {
            "category":"Building & Trades",
            "subcategory":"Construction",
            "type":"Services"
        }
    ],
    "sg:phone":"+1 204 857 7794",
    "sg:postcode":"R1N 3K7",
    "sg:province":"MB",
    "wof:name":"Shirden Enterprises",
    "wof:placetype":"venue"
},
  "geometry": {"coordinates":[-98.287216,49.954704],"type":"Point"}
}