{
  "type": "Feature",
  "properties": {
    "addr:full":"388 Holloway Bay Rd S Sherkston ON L0S 1R0",
    "addr:housenumber":"388",
    "addr:postcode":"l0s 1r0",
    "addr:street":"Holloway Bay Rd",
    "iso:country":"CA",
    "sg:address":"388 Holloway Bay Rd S",
    "sg:city":"Sherkston",
    "sg:classifiers":[
        {
            "category":"Freight",
            "type":"Transportation"
        }
    ],
    "sg:phone":"+1 905 328 1206",
    "sg:postcode":"L0S 1R0",
    "sg:province":"ON",
    "sg:tags":[
        "horse",
        "transporting"
    ],
    "wof:name":"Seancroft",
    "wof:placetype":"venue"
},
  "geometry": {"coordinates":[-79.13442999999999,42.877571],"type":"Point"}
}