{
  "type": "Feature",
  "properties": {
    "addr:full":"86 Fitzroy St Charlottetown PE C1A 1R7",
    "addr:housenumber":"86",
    "addr:postcode":"c1a 1r7",
    "addr:street":"Fitzroy St",
    "iso:country":"CA",
    "sg:address":"86 Fitzroy St",
    "sg:city":"Charlottetown",
    "sg:classifiers":[
        {
            "category":"Health Services",
            "subcategory":"Doctor",
            "type":"Services"
        }
    ],
    "sg:phone":"+1 902 892 7705",
    "sg:postcode":"C1A 1R7",
    "sg:province":"PE",
    "sg:tags":[
        "dentist"
    ],
    "wof:name":"Hodgson, James G DDS",
    "wof:placetype":"venue"
},
  "geometry": {"coordinates":[-63.1298103333,46.2361335754],"type":"Point"}
}