{
  "type": "Feature",
  "properties": {
    "addr:full":"1060 Montee L'Epiphanie L'Assomption QC J5W 2W3",
    "addr:housenumber":"1060",
    "addr:postcode":"j5w 2w3",
    "addr:street":"Montee L'Epiphanie",
    "iso:country":"CA",
    "sg:address":"1060 Montee L'Epiphanie",
    "sg:city":"L'Assomption",
    "sg:classifiers":[
        {
            "category":"Home & Garden",
            "subcategory":"Building Materials",
            "type":"Retail Goods"
        }
    ],
    "sg:phone":"+1 450 589 8456",
    "sg:postcode":"J5W 2W3",
    "sg:province":"QC",
    "sg:tags":[
        "windows",
        "plate",
        "window"
    ],
    "wof:name":"Vitrerie Supreme Enr",
    "wof:placetype":"venue"
},
  "geometry": {"coordinates":[-73.417587,45.833038],"type":"Point"}
}