{
  "type": "Feature",
  "properties": {
    "addr:full":"5240 Woodwards Rd Richmond BC V7E 1H1",
    "addr:housenumber":"5240",
    "addr:postcode":"v7e 1h1",
    "addr:street":"Woodwards Rd",
    "iso:country":"CA",
    "sg:address":"5240 Woodwards Rd",
    "sg:city":"Richmond",
    "sg:classifiers":[
        {
            "category":"Education",
            "subcategory":"School",
            "type":"Public Place"
        }
    ],
    "sg:phone":"+1 604 272 5720",
    "sg:postcode":"V7E 1H1",
    "sg:province":"BC",
    "wof:name":"Richmond Christian School",
    "wof:placetype":"venue"
},
  "geometry": {"coordinates":[-123.166374,49.143814],"type":"Point"}
}