{
  "type": "Feature",
  "properties": {
    "addr:full":"55 Yonge St Toronto ON M5E 1J4",
    "addr:housenumber":"55",
    "addr:postcode":"m5e 1j4",
    "addr:street":"Yonge St",
    "iso:country":"CA",
    "sg:address":"55 Yonge St",
    "sg:city":"Toronto",
    "sg:classifiers":[
        {
            "category":"Banks & Credit Unions",
            "subcategory":"Investment Brokerage",
            "type":"Services"
        }
    ],
    "sg:phone":"+1 416 361 1754",
    "sg:postcode":"M5E 1J4",
    "sg:province":"ON",
    "wof:name":"Norstar Global Finance",
    "wof:placetype":"venue"
},
  "geometry": {"coordinates":[-79.377296,43.648212],"type":"Point"}
}