{
  "type": "Feature",
  "properties": {
    "addr:full":"Vancouver BC V6E 1K7",
    "addr:postcode":"v6e 1k7",
    "iso:country":"CA",
    "sg:city":"Vancouver",
    "sg:classifiers":[
        {
            "category":"Home & Garden",
            "subcategory":"Home Furnishings",
            "type":"Retail Goods"
        }
    ],
    "sg:phone":"+1 604 669 0521",
    "sg:postcode":"V6E 1K7",
    "sg:province":"BC",
    "sg:tags":[
        "venetian",
        "blind"
    ],
    "wof:name":"Blinds For Less",
    "wof:placetype":"venue"
},
  "geometry": {"coordinates":[-123.132484436,49.2838058472],"type":"Point"}
}