{
  "type": "Feature",
  "properties": {
    "addr:full":"228 Norseman St Etobicoke ON M8Z 2R4",
    "addr:housenumber":"228",
    "addr:postcode":"m8z 2r4",
    "addr:street":"Norseman St",
    "iso:country":"CA",
    "sg:address":"228 Norseman St",
    "sg:city":"Etobicoke",
    "sg:classifiers":[
        {
            "category":"Retail",
            "subcategory":"Auto Repair",
            "type":"Services"
        }
    ],
    "sg:phone":"+1 416 236 1168",
    "sg:postcode":"M8Z 2R4",
    "sg:province":"ON",
    "sg:tags":[
        "repairing",
        "automobile"
    ],
    "wof:name":"Superior Auto Ctr Ltd",
    "wof:placetype":"venue"
},
  "geometry": {"coordinates":[-79.5255279541,43.6328392029],"type":"Point"}
}