{
  "type": "Feature",
  "properties": {
    "addr:full":"1223 Cedar Creek Rd Cambridge ON N1R 5S5",
    "addr:housenumber":"1223",
    "addr:postcode":"n1r 5s5",
    "addr:street":"Cedar Creek Rd",
    "iso:country":"CA",
    "sg:address":"1223 Cedar Creek Rd",
    "sg:city":"Cambridge",
    "sg:classifiers":[
        {
            "category":"Retail",
            "subcategory":"Veterinary Services",
            "type":"Services"
        }
    ],
    "sg:phone":"+1 519 623 3347",
    "sg:postcode":"N1R 5S5",
    "sg:province":"ON",
    "sg:tags":[
        "veterinarian"
    ],
    "wof:name":"Cambridge Veterinary Svc",
    "wof:placetype":"venue"
},
  "geometry": {"coordinates":[-80.3153305054,43.3614082336],"type":"Point"}
}