{
  "type": "Feature",
  "properties": {
    "iso:country":"CA",
    "sg:address":"1227 Catherwood Ave",
    "sg:city":"Saskatoon",
    "sg:classifiers":[
        {
            "category":"Building & Trades",
            "subcategory":"Construction",
            "type":"Services"
        }
    ],
    "sg:phone":"+1 306 221 0491",
    "sg:postcode":"S7L 7G6",
    "sg:province":"SK",
    "sg:tags":[
        "general",
        "contractor"
    ],
    "wof:name":"Bondi Developments Ltd",
    "wof:placetype":"venue"
},
  "geometry": {"coordinates":[-106.71442413299999,52.1451416016],"type":"Point"}
}