{
  "type": "Feature",
  "properties": {
    "addr:full":"100 Marlborough Dr Fredericton NB E3B 6K1",
    "addr:housenumber":"100",
    "addr:postcode":"e3b 6k1",
    "addr:street":"Marlborough Dr",
    "iso:country":"CA",
    "sg:address":"100 Marlborough Dr",
    "sg:city":"Fredericton",
    "sg:classifiers":[
        {
            "category":"Real Estate",
            "subcategory":"Real Estate Agent",
            "type":"Services"
        }
    ],
    "sg:phone":"+1 506 458 5551",
    "sg:postcode":"E3B 6K1",
    "sg:province":"NB",
    "sg:tags":[
        "appraiser"
    ],
    "wof:name":"A & A Real Est Appraisal Svc",
    "wof:placetype":"venue"
},
  "geometry": {"coordinates":[-66.67308800000001,45.959106],"type":"Point"}
}