{
  "type": "Feature",
  "properties": {
    "addr:full":"Preeceville SK S0A 3B0",
    "addr:postcode":"s0a 3b0",
    "iso:country":"CA",
    "sg:city":"Preeceville",
    "sg:classifiers":[
        {
            "category":"Retail",
            "subcategory":"Auto Repair",
            "type":"Services"
        }
    ],
    "sg:phone":"+1 306 547 4345",
    "sg:postcode":"S0A 3B0",
    "sg:province":"SK",
    "sg:tags":[
        "repairing",
        "automobile"
    ],
    "wof:name":"Wayne's Country Auto Repair",
    "wof:placetype":"venue"
},
  "geometry": {"coordinates":[-102.668121,51.95631],"type":"Point"}
}