{
  "type": "Feature",
  "properties": {
    "addr:full":"Cambridge ON N1R 5S3",
    "addr:postcode":"n1r 5s3",
    "iso:country":"CA",
    "sg:city":"Cambridge",
    "sg:classifiers":[
        {
            "category":"Home & Garden",
            "subcategory":"Building Materials",
            "type":"Retail Goods"
        }
    ],
    "sg:phone":"+1 519 621 3300",
    "sg:postcode":"N1R 5S3",
    "sg:province":"ON",
    "sg:tags":[
        "mixed",
        "concrete"
    ],
    "wof:name":"Blue Circle Cbm",
    "wof:placetype":"venue"
},
  "geometry": {"coordinates":[-80.320892,43.361599],"type":"Point"}
}