{
  "type": "Feature",
  "properties": {
    "addr:full":"14 Boul Desjardins E Sainte-Therese QC J7E 1C1",
    "addr:housenumber":"14",
    "addr:postcode":"j7e 1c1",
    "addr:street":"Boul Desjardins E Sainte-Therese",
    "iso:country":"CA",
    "sg:address":"14 Boul Desjardins E",
    "sg:city":"Sainte-Therese",
    "sg:classifiers":[
        {
            "category":"Professional",
            "type":"Services"
        }
    ],
    "sg:phone":"+1 450 433 9088",
    "sg:postcode":"J7E 1C1",
    "sg:province":"QC",
    "sg:tags":[
        "infant",
        "establishment",
        "wear"
    ],
    "wof:name":"J Croteau Inc",
    "wof:placetype":"venue"
},
  "geometry": {"coordinates":[-73.832138,45.633434],"type":"Point"}
}