{
  "type": "Feature",
  "properties": {
    "addr:full":"200 8th Ave S Martensville SK S0K 2T0",
    "addr:housenumber":"200",
    "addr:postcode":"s0k 2t0",
    "addr:street":"8Th Ave S",
    "iso:country":"CA",
    "sg:address":"200 8th Ave S",
    "sg:city":"Martensville",
    "sg:classifiers":[
        {
            "category":"Education",
            "subcategory":"School",
            "type":"Public Place"
        }
    ],
    "sg:phone":"+1 306 931 2233",
    "sg:postcode":"S0K 2T0",
    "sg:province":"SK",
    "wof:name":"Valley Manor Elementary School",
    "wof:placetype":"venue"
},
  "geometry": {"coordinates":[-106.67073059099999,52.2962646484],"type":"Point"}
}