{
  "type": "Feature",
  "properties": {
    "addr:full":"17 Crois Roselawn Mont-Royal QC H3P 1H8",
    "addr:housenumber":"17",
    "addr:postcode":"h3p 1h8",
    "addr:street":"Crois Roselawn",
    "iso:country":"CA",
    "sg:address":"17 Crois Roselawn",
    "sg:city":"Mont-Royal",
    "sg:classifiers":[
        {
            "category":"Professional",
            "subcategory":"Engineering",
            "type":"Services"
        }
    ],
    "sg:phone":"+1 514 731 1956",
    "sg:postcode":"H3P 1H8",
    "sg:province":"QC",
    "sg:tags":[
        "engineer"
    ],
    "wof:name":"Jean C Paolucci & Assoc",
    "wof:placetype":"venue"
},
  "geometry": {"coordinates":[-73.642807,45.523136],"type":"Point"}
}