{
  "type": "Feature",
  "properties": {
    "addr:full":"Burlington ON L7L 5M3",
    "addr:postcode":"l7l 5m3",
    "iso:country":"CA",
    "sg:city":"Burlington",
    "sg:classifiers":[
        {
            "category":"Retail",
            "subcategory":"Auto Repair",
            "type":"Services"
        }
    ],
    "sg:phone":"+1 905 637 1122",
    "sg:postcode":"L7L 5M3",
    "sg:province":"ON",
    "sg:tags":[
        "repairing",
        "automobile"
    ],
    "wof:name":"Pretsell's Auto Svc",
    "wof:placetype":"venue"
},
  "geometry": {"coordinates":[-79.7793045044,43.3666191101],"type":"Point"}
}