{
  "type": "Feature",
  "properties": {
    "addr:full":"London ON N6E 2R6",
    "addr:postcode":"n6e 2r6",
    "iso:country":"CA",
    "sg:city":"London",
    "sg:classifiers":[
        {
            "category":"Food & Beverages",
            "subcategory":"Bakery",
            "type":"Retail Goods"
        }
    ],
    "sg:phone":"+1 519 685 1905",
    "sg:postcode":"N6E 2R6",
    "sg:province":"ON",
    "sg:tags":[
        "baker"
    ],
    "wof:name":"Fantasyland Specialty Cakes",
    "wof:placetype":"venue"
},
  "geometry": {"coordinates":[-81.2318191528,42.9258804321],"type":"Point"}
}