{
  "type": "Feature",
  "properties": {
    "addr:full":"1475 David Fife Line Keene ON K0L 2G0",
    "addr:housenumber":"1475",
    "addr:postcode":"k0l 2g0",
    "addr:street":"David Fife Line",
    "iso:country":"CA",
    "sg:address":"1475 David Fife Line",
    "sg:city":"Keene",
    "sg:classifiers":[
        {
            "category":"Building & Trades",
            "subcategory":"Construction",
            "type":"Services"
        }
    ],
    "sg:phone":"+1 705 295 4033",
    "sg:postcode":"K0L 2G0",
    "sg:province":"ON",
    "sg:tags":[
        "contractor"
    ],
    "wof:name":"Van Bruinessen Farm Building",
    "wof:placetype":"venue"
},
  "geometry": {"coordinates":[-78.1632156372,44.240146637],"type":"Point"}
}