{
  "type": "Feature",
  "properties": {
    "addr:full":"297 Rue Notre-Dame Repentigny QC J6A 2R9",
    "addr:housenumber":"297",
    "addr:postcode":"j6a 2r9",
    "addr:street":"Rue Notre-Dame",
    "iso:country":"CA",
    "sg:address":"297 Rue Notre-Dame",
    "sg:city":"Repentigny",
    "sg:classifiers":[
        {
            "category":"Shopping",
            "subcategory":"Bicycles & Sporting Goods",
            "type":"Retail Goods"
        }
    ],
    "sg:phone":"+1 450 581 6670",
    "sg:postcode":"J6A 2R9",
    "sg:province":"QC",
    "wof:name":"Au Coin Du Pedaleur Inc",
    "wof:placetype":"venue"
},
  "geometry": {"coordinates":[-73.457314,45.728046],"type":"Point"}
}