{
  "type": "Feature",
  "properties": {
    "addr:full":"2 Peace Way Nepean ON K2R 1E3",
    "addr:housenumber":"2",
    "addr:postcode":"k2r 1e3",
    "addr:street":"Peace Way",
    "iso:country":"CA",
    "sg:address":"2 Peace Way",
    "sg:city":"Nepean",
    "sg:classifiers":[
        {
            "category":"Building & Trades",
            "subcategory":"Construction",
            "type":"Services"
        }
    ],
    "sg:phone":"+1 613 591 1131",
    "sg:postcode":"K2R 1E3",
    "sg:province":"ON",
    "sg:tags":[
        "general",
        "contractor"
    ],
    "wof:name":"Garvey Millwork Ltd",
    "wof:placetype":"venue"
},
  "geometry": {"coordinates":[-75.82623291020001,45.2646827698],"type":"Point"}
}