{
  "type": "Feature",
  "properties": {
    "addr:full":"161 Bay St # 2700 Toronto ON M5J 2S1",
    "addr:housenumber":"161",
    "addr:postcode":"m5j 2s1",
    "addr:street":"Bay St # 2700",
    "iso:country":"CA",
    "sg:address":"161 Bay St # 2700",
    "sg:city":"Toronto",
    "sg:classifiers":[
        {
            "category":"Real Estate",
            "subcategory":"Real Estate Agent",
            "type":"Services"
        }
    ],
    "sg:phone":"+1 416 815 3185",
    "sg:postcode":"M5J 2S1",
    "sg:province":"ON",
    "wof:name":"Goldwin Realty Corp",
    "wof:placetype":"venue"
},
  "geometry": {"coordinates":[-79.37915802000001,43.6465110779],"type":"Point"}
}