{
  "type": "Feature",
  "properties": {
    "addr:full":"Concord ON L4K 3P6",
    "addr:postcode":"l4k 3p6",
    "iso:country":"CA",
    "sg:city":"Concord",
    "sg:classifiers":[
        {
            "category":"Manufacturing",
            "subcategory":"Tools & Machinery",
            "type":"Manufacturing & Wholesale Goods"
        }
    ],
    "sg:phone":"+1 905 738 0815",
    "sg:postcode":"L4K 3P6",
    "sg:province":"ON",
    "sg:tags":[
        "machine",
        "shop"
    ],
    "wof:name":"Artinian Precision Parts Ltd",
    "wof:placetype":"venue"
},
  "geometry": {"coordinates":[-79.483177,43.818317],"type":"Point"}
}