{
  "type": "Feature",
  "properties": {
    "addr:full":"480 Guelph Line Burlington ON L7R 3M1",
    "addr:housenumber":"480",
    "addr:postcode":"l7r 3m1",
    "addr:street":"Guelph Line",
    "iso:country":"CA",
    "sg:address":"480 Guelph Line",
    "sg:city":"Burlington",
    "sg:classifiers":[
        {
            "category":"Health Services",
            "subcategory":"Doctor",
            "type":"Services"
        }
    ],
    "sg:phone":"+1 905 637 2340",
    "sg:postcode":"L7R 3M1",
    "sg:province":"ON",
    "sg:tags":[
        "physician",
        "surgeon"
    ],
    "wof:name":"Procter, W C MD",
    "wof:placetype":"venue"
},
  "geometry": {"coordinates":[-79.78638458250001,43.3388977051],"type":"Point"}
}