{
  "type": "Feature",
  "properties": {
    "iso:country":"CA",
    "sg:address":"1 10E Rue",
    "sg:city":"Forestville",
    "sg:classifiers":[
        {
            "category":"Organizations",
            "subcategory":"Religious Organization",
            "type":"Services"
        }
    ],
    "sg:phone":"+1 418 587 4018",
    "sg:postcode":"G0T 1E0",
    "sg:province":"QC",
    "sg:tags":[
        "church"
    ],
    "wof:name":"Forestville Presbytere",
    "wof:placetype":"venue"
},
  "geometry": {"coordinates":[-69.0790481567,48.7448959351],"type":"Point"}
}