{
  "type": "Feature",
  "properties": {
    "addr:full":"1055 Boul Des Laurentides Laval QC H7G 2W2",
    "addr:housenumber":"1055",
    "addr:postcode":"qc h7g 2w2",
    "addr:street":"Boul Des Laurentides",
    "iso:country":"CA",
    "sg:address":"1055 Boul Des Laurentides",
    "sg:city":"Laval",
    "sg:classifiers":[
        {
            "category":"Cinema",
            "subcategory":"Movie Theater",
            "type":"Entertainment"
        }
    ],
    "sg:phone":"+1 450 967 4455",
    "sg:postcode":"H7G 2W2",
    "sg:province":"QC",
    "wof:name":"Megaplex Point Viau 16",
    "wof:placetype":"venue"
},
  "geometry": {"coordinates":[-73.69812011720001,45.5759086609],"type":"Point"}
}