{
  "type": "Feature",
  "properties": {
    "iso:country":"CA",
    "sg:address":"2465 Boul Ford",
    "sg:city":"Chateauguay",
    "sg:classifiers":[
        {
            "category":"Autos & Motor Vehicles",
            "subcategory":"Automobile Sales",
            "type":"Retail Goods"
        }
    ],
    "sg:phone":"+1 450 699 8490",
    "sg:postcode":"J6J 4Z2",
    "sg:province":"QC",
    "sg:tags":[
        "car",
        "dealer"
    ],
    "wof:name":"Automobiles Jc Enr",
    "wof:placetype":"venue"
},
  "geometry": {"coordinates":[-73.681877,45.344826],"type":"Point"}
}