{
  "type": "Feature",
  "properties": {
    "addr:full":"7272 Buller Ave Burnaby BC V5J 4S3",
    "addr:housenumber":"7272",
    "addr:postcode":"v5j 4s3",
    "addr:street":"Buller Ave",
    "iso:country":"CA",
    "sg:address":"7272 Buller Ave",
    "sg:city":"Burnaby",
    "sg:classifiers":[
        {
            "category":"Manufacturing",
            "subcategory":"Printing",
            "type":"Manufacturing & Wholesale Goods"
        }
    ],
    "sg:phone":"+1 604 439 2456",
    "sg:postcode":"V5J 4S3",
    "sg:province":"BC",
    "sg:tags":[
        "printer"
    ],
    "wof:name":"Hemlock Express Ltd",
    "wof:placetype":"venue"
},
  "geometry": {"coordinates":[-122.977341,49.218498],"type":"Point"}
}