{
  "type": "Feature",
  "properties": {
    "addr:full":"1335 Caribou St W Moose Jaw SK S6H 7K5",
    "addr:housenumber":"1335",
    "addr:postcode":"s6h 7k5",
    "addr:street":"Caribou St W",
    "iso:country":"CA",
    "sg:address":"1335 Caribou St W",
    "sg:city":"Moose Jaw",
    "sg:classifiers":[
        {
            "category":"Autos & Motor Vehicles",
            "subcategory":"Motorcycle Sales",
            "type":"Retail Goods"
        }
    ],
    "sg:phone":"+1 306 693 0111",
    "sg:postcode":"S6H 7K5",
    "sg:province":"SK",
    "sg:tags":[
        "recreational"
    ],
    "wof:name":"Pro Twin Cycle",
    "wof:placetype":"venue"
},
  "geometry": {"coordinates":[-105.57284545900001,50.3967285156],"type":"Point"}
}