{
  "type": "Feature",
  "properties": {
    "addr:full":"Cabano QC G0L 1E0",
    "addr:postcode":"g0l 1e0",
    "iso:country":"CA",
    "sg:city":"Cabano",
    "sg:classifiers":[
        {
            "category":"Organizations",
            "subcategory":"Professional Association",
            "type":"Services"
        }
    ],
    "sg:phone":"+1 418 854 3110",
    "sg:postcode":"G0L 1E0",
    "sg:province":"QC",
    "sg:tags":[
        "club"
    ],
    "wof:name":"Club DE L'Age D'Or DE Cabano",
    "wof:placetype":"venue"
},
  "geometry": {"coordinates":[-68.8816146851,47.6812515259],"type":"Point"}
}