{
  "type": "Feature",
  "properties": {
    "addr:full":"Mississauga ON L5L 5Y4",
    "addr:postcode":"l5l 5y4",
    "iso:country":"CA",
    "sg:city":"Mississauga",
    "sg:classifiers":[
        {
            "category":"Home & Garden",
            "subcategory":"Furniture",
            "type":"Retail Goods"
        }
    ],
    "sg:phone":"+1 905 607 6541",
    "sg:postcode":"L5L 5Y4",
    "sg:province":"ON",
    "sg:tags":[
        "kitchen",
        "maker",
        "cabinet"
    ],
    "wof:name":"Sherwood Cabinetry",
    "wof:placetype":"venue"
},
  "geometry": {"coordinates":[-79.6979980469,43.5165481567],"type":"Point"}
}