{
  "type": "Feature",
  "properties": {
    "addr:full":"4632 Yonge St North York ON M2N 5M1",
    "addr:housenumber":"4632",
    "addr:postcode":"m2n 5m1",
    "addr:street":"Yonge St",
    "iso:country":"CA",
    "sg:address":"4632 Yonge St",
    "sg:city":"North York",
    "sg:classifiers":[
        {
            "category":"Retail",
            "subcategory":"Laundry & Dry Cleaning",
            "type":"Services"
        }
    ],
    "sg:phone":"+1 416 221 7545",
    "sg:postcode":"M2N 5M1",
    "sg:province":"ON",
    "sg:tags":[
        "cleaners"
    ],
    "wof:name":"P C Custom Cleaners",
    "wof:placetype":"venue"
},
  "geometry": {"coordinates":[-79.4101028442,43.7574081421],"type":"Point"}
}