{
  "type": "Feature",
  "properties": {
    "addr:full":"5506 Route 8 Astle NB E6A 1P2",
    "addr:housenumber":"5506",
    "addr:postcode":"e6a 1p2",
    "addr:street":"Route 8",
    "iso:country":"CA",
    "sg:address":"5506 Route 8",
    "sg:city":"Astle",
    "sg:classifiers":[
        {
            "category":"Autos & Motor Vehicles",
            "subcategory":"Motorcycle Sales",
            "type":"Retail Goods"
        }
    ],
    "sg:phone":"+1 506 369 7167",
    "sg:postcode":"E6A 1P2",
    "sg:province":"NB",
    "sg:tags":[
        "satellite",
        "equipment",
        "all",
        "terrain",
        "system"
    ],
    "wof:name":"Davis Equipment",
    "wof:placetype":"venue"
},
  "geometry": {"coordinates":[-66.470451,46.41214],"type":"Point"}
}