{
  "type": "Feature",
  "properties": {
    "addr:full":"685741 Hwy 2 Woodstock ON N4S 7V9",
    "addr:housenumber":"685741",
    "addr:postcode":"n4s 7v9",
    "addr:street":"Hwy 2",
    "iso:country":"CA",
    "sg:address":"685741 Hwy 2",
    "sg:city":"Woodstock",
    "sg:classifiers":[
        {
            "category":"Autos & Motor Vehicles",
            "subcategory":"Automobile Sales",
            "type":"Retail Goods"
        }
    ],
    "sg:phone":"+1 519 467 5621",
    "sg:postcode":"N4S 7V9",
    "sg:province":"ON",
    "sg:tags":[
        "repairing",
        "car"
    ],
    "wof:name":"Klingenberg Auto Repair",
    "wof:placetype":"venue"
},
  "geometry": {"coordinates":[-80.67213439939999,43.1423416138],"type":"Point"}
}