{
  "type": "Feature",
  "properties": {
    "iso:country":"CA",
    "sg:address":"408 Canterbury Cres",
    "sg:city":"Oakville",
    "sg:classifiers":[
        {
            "category":"Banks & Credit Unions",
            "subcategory":"Investment Brokerage",
            "type":"Services"
        }
    ],
    "sg:phone":"+1 905 339 2751",
    "sg:postcode":"L6J 5K7",
    "sg:province":"ON",
    "sg:tags":[
        "consultant",
        "financing"
    ],
    "wof:name":"Letaba Corporate Finance Inc",
    "wof:placetype":"venue"
},
  "geometry": {"coordinates":[-79.6492614746,43.481716156],"type":"Point"}
}