{
  "type": "Feature",
  "properties": {
    "addr:full":"2140 Bedard St Hawkesbury ON K6A 2R2",
    "addr:housenumber":"2140",
    "addr:postcode":"k6a 2r2",
    "addr:street":"Bedard St",
    "iso:country":"CA",
    "sg:address":"2140 Bedard St",
    "sg:city":"Hawkesbury",
    "sg:classifiers":[
        {
            "category":"Wholesale",
            "subcategory":"Office Equipment",
            "type":"Manufacturing & Wholesale Goods"
        }
    ],
    "sg:phone":"+1 613 632 1828",
    "sg:postcode":"K6A 2R2",
    "sg:province":"ON",
    "sg:tags":[
        "accounting",
        "bookkeeping",
        "system"
    ],
    "wof:name":"Carriere & Millette",
    "wof:placetype":"venue"
},
  "geometry": {"coordinates":[-74.61414337159999,45.6078948975],"type":"Point"}
}