{
  "type": "Feature",
  "properties": {
    "iso:country":"CA",
    "sg:address":"4628 Boul Kimber",
    "sg:city":"Saint-Hubert",
    "sg:classifiers":[
        {
            "category":"Professional",
            "subcategory":"Detective & Security Services",
            "type":"Services"
        }
    ],
    "sg:phone":"+1 450 676 3212",
    "sg:postcode":"J3Y 8K5",
    "sg:province":"QC",
    "sg:tags":[
        "burglary",
        "protective",
        "robbery"
    ],
    "wof:name":"Systemes DE Securite Atl",
    "wof:placetype":"venue"
},
  "geometry": {"coordinates":[-73.445282,45.497028],"type":"Point"}
}