{
  "type": "Feature",
  "properties": {
    "addr:full":"Waterloo ON N2L 6H7",
    "addr:postcode":"n2l 6h7",
    "iso:country":"CA",
    "sg:city":"Waterloo",
    "sg:classifiers":[
        {
            "category":"Insurance",
            "subcategory":"Insurance Agent",
            "type":"Services"
        }
    ],
    "sg:phone":"+1 519 747 3324",
    "sg:postcode":"N2L 6H7",
    "sg:province":"ON",
    "sg:tags":[
        "consultant"
    ],
    "wof:name":"Pwi Insurance Svc",
    "wof:placetype":"venue"
},
  "geometry": {"coordinates":[-80.538597,43.493969],"type":"Point"}
}