{
  "type": "Feature",
  "properties": {
    "addr:full":"26426 Fraser Hwy Aldergrove BC V4W 3E2",
    "addr:housenumber":"26426",
    "addr:postcode":"v4w 3e2",
    "addr:street":"Fraser Hwy",
    "iso:country":"CA",
    "sg:address":"26426 Fraser Hwy",
    "sg:city":"Aldergrove",
    "sg:classifiers":[
        {
            "category":"Autos & Motor Vehicles",
            "subcategory":"Fuel & Gas Station",
            "type":"Retail Goods"
        }
    ],
    "sg:phone":"+1 604 856 0664",
    "sg:postcode":"V4W 3E2",
    "sg:province":"BC",
    "sg:tags":[
        "oil"
    ],
    "wof:name":"Aldergrove Husky",
    "wof:placetype":"venue"
},
  "geometry": {"coordinates":[-122.491737,49.059326],"type":"Point"}
}