{
  "type": "Feature",
  "properties": {
    "addr:full":"Saint-Etienne-Des-Gres QC G0X 2P0",
    "addr:postcode":"g0x 2p0",
    "iso:country":"CA",
    "sg:city":"Saint-Etienne-Des-Gres",
    "sg:classifiers":[
        {
            "category":"Shopping",
            "subcategory":"Shoes",
            "type":"Retail Goods"
        }
    ],
    "sg:phone":"+1 819 535 1166",
    "sg:postcode":"G0X 2P0",
    "sg:province":"QC",
    "wof:name":"Boutique Western Gerard Nolet",
    "wof:placetype":"venue"
},
  "geometry": {"coordinates":[-72.800049,46.484608],"type":"Point"}
}