{
  "type": "Feature",
  "properties": {
    "addr:full":"1186 Weston Rd York ON M6M 4P4",
    "addr:housenumber":"1186",
    "addr:postcode":"m6m 4p4",
    "addr:street":"Weston Rd",
    "iso:country":"CA",
    "sg:address":"1186 Weston Rd",
    "sg:city":"York",
    "sg:classifiers":[
        {
            "category":"Personal",
            "subcategory":"Beauty Salon",
            "type":"Services"
        }
    ],
    "sg:phone":"+1 416 248 1171",
    "sg:postcode":"M6M 4P4",
    "sg:province":"ON",
    "wof:name":"J & R Professional Hair Place",
    "wof:placetype":"venue"
},
  "geometry": {"coordinates":[-79.4912261963,43.6874809265],"type":"Point"}
}