{
  "type": "Feature",
  "properties": {
    "iso:country":"CA",
    "sg:address":"14 Fifth Ave",
    "sg:city":"Orangeville",
    "sg:classifiers":[
        {
            "category":"Shopping",
            "subcategory":"Pharmacy",
            "type":"Retail Goods"
        }
    ],
    "sg:phone":"+1 519 941 9921",
    "sg:postcode":"L9W 1G2",
    "sg:province":"ON",
    "wof:name":"Fifth Avenue Pharmacy",
    "wof:placetype":"venue"
},
  "geometry": {"coordinates":[-80.09877,43.927811],"type":"Point"}
}