{
  "type": "Feature",
  "properties": {
    "iso:country":"CA",
    "sg:city":"Ottawa",
    "sg:classifiers":[
        {
            "category":"Shopping",
            "subcategory":"Luggage & Leather Goods",
            "type":"Retail Goods"
        }
    ],
    "sg:phone":"+1 613 729 5393",
    "sg:postcode":"K1Z 7L3",
    "sg:province":"ON",
    "wof:name":"Satchels Luggage & Handbags",
    "wof:placetype":"venue"
},
  "geometry": {"coordinates":[-75.734306,45.386238],"type":"Point"}
}