{
  "type": "Feature",
  "properties": {
    "addr:full":"5745 Ch DE LA Cote-Saint-Luc Hampstead QC H3X 2E5",
    "addr:postcode":"5745;h3x 2e5",
    "addr:street":"Ch De La Cote-Saint-Luc",
    "iso:country":"CA",
    "sg:address":"5745 Ch DE LA Cote-Saint-Luc",
    "sg:city":"Hampstead",
    "sg:classifiers":[
        {
            "category":"Freight",
            "type":"Transportation"
        }
    ],
    "sg:phone":"+1 514 487 5762",
    "sg:postcode":"H3X 2E5",
    "sg:province":"QC",
    "sg:tags":[
        "mover"
    ],
    "wof:name":"Corvin Transport Inc",
    "wof:placetype":"venue"
},
  "geometry": {"coordinates":[-73.6323547363,45.4779548645],"type":"Point"}
}