{
  "type": "Feature",
  "properties": {
    "addr:full":"120 40 Ave NW Calgary AB T2K 0E3",
    "addr:housenumber":"120",
    "addr:postcode":"t2k 0e3",
    "addr:street":"40 Ave Nw",
    "iso:country":"CA",
    "sg:address":"120 40 Ave NW",
    "sg:city":"Calgary",
    "sg:classifiers":[
        {
            "category":"Food & Beverages",
            "subcategory":"Meat & Fish",
            "type":"Retail Goods"
        }
    ],
    "sg:phone":"+1 403 277 5002",
    "sg:postcode":"T2K 0E3",
    "sg:province":"AB",
    "wof:name":"Master Meats Ltd",
    "wof:placetype":"venue"
},
  "geometry": {"coordinates":[-114.064049,51.088867],"type":"Point"}
}