{
  "type": "Feature",
  "properties": {
    "iso:country":"CA",
    "sg:address":"5178 Boul Saint-Laurent",
    "sg:city":"Montreal",
    "sg:classifiers":[
        {
            "category":"Recreation",
            "type":"Entertainment"
        }
    ],
    "sg:phone":"+1 514 279 3545",
    "sg:postcode":"H2T 1R8",
    "sg:province":"QC",
    "sg:tags":[
        "instruction",
        "yoga"
    ],
    "wof:name":"Sivananda Yoga Vedanta Ctr",
    "wof:placetype":"venue"
},
  "geometry": {"coordinates":[-73.5941772461,45.5235214233],"type":"Point"}
}