{
  "type": "Feature",
  "properties": {
    "addr:full":"460 Starchuk Rd Grand Forks BC V0H 1H9",
    "addr:housenumber":"460",
    "addr:postcode":"v0h 1h9",
    "addr:street":"Starchuk Rd",
    "iso:country":"CA",
    "sg:address":"460 Starchuk Rd",
    "sg:city":"Grand Forks",
    "sg:classifiers":[
        {
            "category":"Retail",
            "subcategory":"Repair Shop",
            "type":"Services"
        }
    ],
    "sg:phone":"+1 250 442 2993",
    "sg:postcode":"V0H 1H9",
    "sg:province":"BC",
    "sg:tags":[
        "taxidermist"
    ],
    "wof:name":"Alpine Taxidermy",
    "wof:placetype":"venue"
},
  "geometry": {"coordinates":[-118.44326,49.032372],"type":"Point"}
}