{
  "type": "Feature",
  "properties": {
    "addr:full":"628 Main St Woodstock NB E7M 2C5",
    "addr:housenumber":"628",
    "addr:postcode":"e7m 2c5",
    "addr:street":"Main St",
    "iso:country":"CA",
    "sg:address":"628 Main St",
    "sg:city":"Woodstock",
    "sg:classifiers":[
        {
            "category":"Shopping",
            "subcategory":"Shoes",
            "type":"Retail Goods"
        }
    ],
    "sg:phone":"+1 506 328 3119",
    "sg:postcode":"E7M 2C5",
    "sg:province":"NB",
    "wof:name":"Laurie's Shoes Ltd",
    "wof:placetype":"venue"
},
  "geometry": {"coordinates":[-67.573341,46.149818],"type":"Point"}
}