{
  "type": "Feature",
  "properties": {
    "addr:full":"Alexander St Maxville ON K0C 1T0",
    "addr:postcode":"k0c 1t0",
    "addr:street":"Alexander St",
    "iso:country":"CA",
    "sg:address":"Alexander St",
    "sg:city":"Maxville",
    "sg:classifiers":[
        {
            "category":"Recreation",
            "type":"Entertainment"
        }
    ],
    "sg:phone":"+1 613 527 2155",
    "sg:postcode":"K0C 1T0",
    "sg:province":"ON",
    "sg:tags":[
        "club",
        "curling"
    ],
    "wof:name":"Maxville & District Curling",
    "wof:placetype":"venue"
},
  "geometry": {"coordinates":[-74.85521697999999,45.2897796631],"type":"Point"}
}