{
  "type": "Feature",
  "properties": {
    "iso:country":"CA",
    "sg:address":"511 Riverside Dr",
    "sg:city":"London",
    "sg:classifiers":[
        {
            "category":"Home & Garden",
            "subcategory":"Building Materials",
            "type":"Retail Goods"
        }
    ],
    "sg:phone":"+1 519 471 0741",
    "sg:postcode":"N6H 2S1",
    "sg:province":"ON",
    "sg:tags":[
        "windows",
        "improvement"
    ],
    "wof:name":"Gemini Exterior Remodelling",
    "wof:placetype":"venue"
},
  "geometry": {"coordinates":[-81.2892913818,42.9766273499],"type":"Point"}
}