{
  "type": "Feature",
  "properties": {
    "iso:country":"CA",
    "sg:address":"1545 Rue DE Courtrai",
    "sg:city":"Val-Belair",
    "sg:classifiers":[
        {
            "category":"Building & Trades",
            "subcategory":"Construction",
            "type":"Services"
        }
    ],
    "sg:phone":"+1 418 843 3253",
    "sg:postcode":"G3K 1N9",
    "sg:province":"QC",
    "sg:tags":[
        "general",
        "contractor"
    ],
    "wof:name":"Constructions Claveau Inc",
    "wof:placetype":"venue"
},
  "geometry": {"coordinates":[-71.413597,46.85181],"type":"Point"}
}