{
  "type": "Feature",
  "properties": {
    "addr:full":"6980 Vedder Rd Chilliwack BC V2R 4E1",
    "addr:postcode":"6980;v2r 4e1",
    "addr:street":"Vedder Rd",
    "iso:country":"CA",
    "sg:address":"6980 Vedder Rd",
    "sg:city":"Chilliwack",
    "sg:classifiers":[
        {
            "category":"Health Services",
            "subcategory":"Nursing And Care Facility",
            "type":"Services"
        }
    ],
    "sg:phone":"+1 604 824 0109",
    "sg:postcode":"V2R 4E1",
    "sg:province":"BC",
    "sg:tags":[
        "home",
        "senior",
        "retirement",
        "community",
        "citizen"
    ],
    "wof:name":"Chilliwack Lifestyles",
    "wof:placetype":"venue"
},
  "geometry": {"coordinates":[-121.95983099999999,49.122768],"type":"Point"}
}