{
  "type": "Feature",
  "properties": {
    "addr:full":"Duncan BC V9L 6E1",
    "addr:postcode":"v9l 6e1",
    "iso:country":"CA",
    "sg:city":"Duncan",
    "sg:classifiers":[
        {
            "category":"Shopping",
            "subcategory":"Used Merchandise",
            "type":"Retail Goods"
        }
    ],
    "sg:phone":"+1 250 746 6066",
    "sg:postcode":"V9L 6E1",
    "sg:province":"BC",
    "sg:tags":[
        "antique"
    ],
    "wof:name":"Streit Bros Trading Ltd",
    "wof:placetype":"venue"
},
  "geometry": {"coordinates":[-123.65522799999999,48.740791],"type":"Point"}
}