{
  "type": "Feature",
  "properties": {
    "addr:full":"Papineauville QC J0V 1R0",
    "addr:postcode":"j0v 1r0",
    "iso:country":"CA",
    "sg:city":"Papineauville",
    "sg:classifiers":[
        {
            "category":"Autos & Motor Vehicles",
            "subcategory":"Auto Supplies",
            "type":"Retail Goods"
        }
    ],
    "sg:phone":"+1 819 427 6494",
    "sg:postcode":"J0V 1R0",
    "sg:province":"QC",
    "sg:tags":[
        "tire"
    ],
    "wof:name":"Pneus Robert Bernard Ltee",
    "wof:placetype":"venue"
},
  "geometry": {"coordinates":[-75.0172653198,45.6198005676],"type":"Point"}
}