{
  "type": "Feature",
  "properties": {
    "addr:full":"8460 Moose River Rd Middle Musquodoboit NS B0N 1X0",
    "addr:housenumber":"8460",
    "addr:postcode":"b0n 1x0",
    "addr:street":"Moose River Rd",
    "iso:country":"CA",
    "sg:address":"8460 Moose River Rd",
    "sg:city":"Middle Musquodoboit",
    "sg:classifiers":[
        {
            "category":"Building & Trades",
            "subcategory":"Construction",
            "type":"Services"
        }
    ],
    "sg:phone":"+1 902 384 2693",
    "sg:postcode":"B0N 1X0",
    "sg:province":"NS",
    "sg:tags":[
        "concrete",
        "contractor"
    ],
    "wof:name":"Water Stoppers Basement Repair",
    "wof:placetype":"venue"
},
  "geometry": {"coordinates":[-63.141224,45.046673],"type":"Point"}
}