{
  "type": "Feature",
  "properties": {
    "addr:full":"10840 82 Ave Delta BC V4C 2B3",
    "addr:housenumber":"10840",
    "addr:postcode":"v4c 2b3",
    "addr:street":"82 Ave",
    "iso:country":"CA",
    "sg:address":"10840 82 Ave",
    "sg:city":"Delta",
    "sg:classifiers":[
        {
            "category":"Education",
            "subcategory":"School",
            "type":"Public Place"
        }
    ],
    "sg:phone":"+1 604 594 3474",
    "sg:postcode":"V4C 2B3",
    "sg:province":"BC",
    "wof:name":"Sands Jr Secondary School",
    "wof:placetype":"venue"
},
  "geometry": {"coordinates":[-122.922706604,49.1521186829],"type":"Point"}
}