{
  "type": "Feature",
  "properties": {
    "addr:full":"622 St Paul St Kamloops BC V2C 2K2",
    "addr:housenumber":"622",
    "addr:postcode":"bc v2c 2k2",
    "addr:street":"St Paul St",
    "iso:country":"CA",
    "sg:address":"622 St Paul St",
    "sg:city":"Kamloops",
    "sg:classifiers":[
        {
            "category":"Real Estate",
            "subcategory":"Real Estate Agent",
            "type":"Services"
        }
    ],
    "sg:phone":"+1 250 372 0787",
    "sg:postcode":"V2C 2K2",
    "sg:province":"BC",
    "sg:tags":[
        "management"
    ],
    "wof:name":"Full Service Rentals",
    "wof:placetype":"venue"
},
  "geometry": {"coordinates":[-120.32627100000001,50.674271],"type":"Point"}
}