{
  "type": "Feature",
  "properties": {
    "addr:full":"9904 111 Ave Grande Prairie AB T8V 4C3",
    "addr:housenumber":"9904",
    "addr:postcode":"t8v 4c3",
    "addr:street":"111 Ave",
    "iso:country":"CA",
    "sg:address":"9904 111 Ave",
    "sg:city":"Grande Prairie",
    "sg:classifiers":[
        {
            "category":"Retail",
            "subcategory":"Car Wash",
            "type":"Services"
        }
    ],
    "sg:phone":"+1 780 513 0706",
    "sg:postcode":"T8V 4C3",
    "sg:province":"AB",
    "sg:tags":[
        "polishing",
        "washing"
    ],
    "wof:name":"Auto Village Car Wash & Clean",
    "wof:placetype":"venue"
},
  "geometry": {"coordinates":[-118.791428,55.180691],"type":"Point"}
}