{
  "type": "Feature",
  "properties": {
    "addr:full":"616 Park Royal N West Vancouver BC V7T 1H9",
    "addr:housenumber":"616",
    "addr:postcode":"v7t 1h9",
    "addr:street":"Park Royal N",
    "iso:country":"CA",
    "sg:address":"616 Park Royal N",
    "sg:city":"West Vancouver",
    "sg:classifiers":[
        {
            "category":"Retail",
            "subcategory":"Laundry & Dry Cleaning",
            "type":"Services"
        }
    ],
    "sg:phone":"+1 604 922 4811",
    "sg:postcode":"V7T 1H9",
    "sg:province":"BC",
    "sg:tags":[
        "cleaners"
    ],
    "wof:name":"Carousel Cleaners",
    "wof:placetype":"venue"
},
  "geometry": {"coordinates":[-123.135384,49.327705],"type":"Point"}
}