{
  "type": "Feature",
  "properties": {
    "iso:country":"CA",
    "sg:address":"5728 East Blvd",
    "sg:city":"Vancouver",
    "sg:classifiers":[
        {
            "category":"Professional",
            "subcategory":"Business Services",
            "type":"Services"
        }
    ],
    "sg:phone":"+1 604 261 3771",
    "sg:postcode":"V6M 4M4",
    "sg:province":"BC",
    "sg:tags":[
        "notary"
    ],
    "wof:name":"Tang, Ruth M K",
    "wof:placetype":"venue"
},
  "geometry": {"coordinates":[-123.154831,49.234219],"type":"Point"}
}