{
  "type": "Feature",
  "properties": {
    "addr:full":"144 Frederica St W Thunder Bay ON P7E 3V7",
    "addr:housenumber":"144",
    "addr:postcode":"p7e 3v7",
    "addr:street":"Frederica St W",
    "iso:country":"CA",
    "sg:address":"144 Frederica St W",
    "sg:city":"Thunder Bay",
    "sg:classifiers":[
        {
            "category":"Home & Garden",
            "subcategory":"Furniture",
            "type":"Retail Goods"
        }
    ],
    "sg:phone":"+1 807 577 5731",
    "sg:postcode":"P7E 3V7",
    "sg:province":"ON",
    "wof:name":"Arrow Electric CO Ltd",
    "wof:placetype":"venue"
},
  "geometry": {"coordinates":[-89.2798843384,48.3649520874],"type":"Point"}
}