{
  "type": "Feature",
  "properties": {
    "addr:full":"Montreal QC H3B 2K4",
    "addr:postcode":"h3b 2k4",
    "iso:country":"CA",
    "sg:city":"Montreal",
    "sg:classifiers":[
        {
            "category":"Professional",
            "subcategory":"Management & Consulting",
            "type":"Services"
        }
    ],
    "sg:phone":"+1 514 398 9150",
    "sg:postcode":"H3B 2K4",
    "sg:province":"QC",
    "sg:tags":[
        "marketing",
        "consultant"
    ],
    "wof:name":"Lord Marketing",
    "wof:placetype":"venue"
},
  "geometry": {"coordinates":[-73.554436,45.517063],"type":"Point"}
}