{
  "type": "Feature",
  "properties": {
    "addr:full":"5895 Reef Rd Sechelt BC V0N 3A6",
    "addr:housenumber":"5895",
    "addr:postcode":"v0n 3a6",
    "addr:street":"Reef Rd",
    "iso:country":"CA",
    "sg:address":"5895 Reef Rd",
    "sg:city":"Sechelt",
    "sg:classifiers":[
        {
            "category":"Organizations",
            "subcategory":"Religious Organization",
            "type":"Services"
        }
    ],
    "sg:phone":"+1 604 885 4775",
    "sg:postcode":"V0N 3A6",
    "sg:province":"BC",
    "sg:tags":[
        "church"
    ],
    "wof:name":"Sechelt Community Church",
    "wof:placetype":"venue"
},
  "geometry": {"coordinates":[-123.770782471,49.4860343933],"type":"Point"}
}