{
  "type": "Feature",
  "properties": {
    "addr:full":"298 Pioneer Way Burns Lake BC V0J 1E0",
    "addr:housenumber":"298",
    "addr:postcode":"v0j 1e0",
    "addr:street":"Pioneer Way Burns",
    "iso:country":"CA",
    "sg:address":"298 Pioneer Way",
    "sg:city":"Burns Lake",
    "sg:classifiers":[
        {
            "category":"Retail",
            "subcategory":"Repair Shop",
            "type":"Services"
        }
    ],
    "sg:phone":"+1 250 692 7331",
    "sg:postcode":"V0J 1E0",
    "sg:province":"BC",
    "sg:tags":[
        "appliance"
    ],
    "wof:name":"Nordic Appliance Svc",
    "wof:placetype":"venue"
},
  "geometry": {"coordinates":[-125.759102,54.223625],"type":"Point"}
}