{
  "type": "Feature",
  "properties": {
    "addr:full":"Victoria BC V8W 2E7",
    "addr:postcode":"v8w 2e7",
    "iso:country":"CA",
    "sg:city":"Victoria",
    "sg:classifiers":[
        {
            "category":"Personal",
            "subcategory":"Beauty Salon",
            "type":"Services"
        }
    ],
    "sg:phone":"+1 250 383 2334",
    "sg:postcode":"V8W 2E7",
    "sg:province":"BC",
    "wof:name":"Terry's Beauty Salon",
    "wof:placetype":"venue"
},
  "geometry": {"coordinates":[-123.365021,48.425594],"type":"Point"}
}