{
  "type": "Feature",
  "properties": {
    "addr:full":"800 Rosser Ave Brandon MB R7A 6N5",
    "addr:housenumber":"800",
    "addr:postcode":"r7a 6n5",
    "addr:street":"Rosser Ave",
    "iso:country":"CA",
    "sg:address":"800 Rosser Ave",
    "sg:city":"Brandon",
    "sg:classifiers":[
        {
            "category":"Shopping",
            "subcategory":"Clothing, Apparel, & Fashions",
            "type":"Retail Goods"
        }
    ],
    "sg:phone":"+1 204 728 7486",
    "sg:postcode":"R7A 6N5",
    "sg:province":"MB",
    "wof:name":"Friend's Fashion Boutique",
    "wof:placetype":"venue"
},
  "geometry": {"coordinates":[-99.94883,49.848347],"type":"Point"}
}