{
  "type": "Feature",
  "properties": {
    "addr:full":"100 Steelcase Rd E # 105 Markham ON L3R 1E8",
    "addr:housenumber":"100",
    "addr:postcode":"l3r 1e8",
    "addr:street":"Steelcase Rd E # 105",
    "iso:country":"CA",
    "sg:address":"100 Steelcase Rd E # 105",
    "sg:city":"Markham",
    "sg:classifiers":[
        {
            "category":"Wholesale",
            "subcategory":"Stationery",
            "type":"Manufacturing & Wholesale Goods"
        }
    ],
    "sg:phone":"+1 416 499 8199",
    "sg:postcode":"L3R 1E8",
    "sg:province":"ON",
    "wof:name":"Chestwood Stationery",
    "wof:placetype":"venue"
},
  "geometry": {"coordinates":[-79.347427,43.820358],"type":"Point"}
}