{
  "type": "Feature",
  "properties": {
    "addr:full":"1218 Michigan Ave Sarnia ON N7S 6L1",
    "addr:housenumber":"1218",
    "addr:postcode":"n7s 6l1",
    "addr:street":"Michigan Ave",
    "iso:country":"CA",
    "sg:address":"1218 Michigan Ave",
    "sg:city":"Sarnia",
    "sg:classifiers":[
        {
            "category":"Health Services",
            "subcategory":"Nursing And Care Facility",
            "type":"Services"
        }
    ],
    "sg:phone":"+1 519 542 8814",
    "sg:postcode":"N7S 6L1",
    "sg:province":"ON",
    "sg:tags":[
        "home",
        "retirement",
        "community"
    ],
    "wof:name":"Fairwinds Lodge",
    "wof:placetype":"venue"
},
  "geometry": {"coordinates":[-82.36328899999999,42.999924],"type":"Point"}
}