{
  "type": "Feature",
  "properties": {
    "addr:full":"1570 Hyde Park Rd London ON N6H 5L5",
    "addr:housenumber":"1570",
    "addr:postcode":"n6h 5l5",
    "addr:street":"Hyde Park Rd",
    "iso:country":"CA",
    "sg:address":"1570 Hyde Park Rd",
    "sg:city":"London",
    "sg:classifiers":[
        {
            "category":"Professional",
            "subcategory":"Accounting & Tax Preparation",
            "type":"Services"
        }
    ],
    "sg:phone":"+1 519 471 6900",
    "sg:postcode":"N6H 5L5",
    "sg:province":"ON",
    "sg:tags":[
        "accountant"
    ],
    "wof:name":"Rozeluk & CO",
    "wof:placetype":"venue"
},
  "geometry": {"coordinates":[-81.331902,42.99799],"type":"Point"}
}