{
  "type": "Feature",
  "properties": {
    "addr:full":"40 William St N Lindsay ON K9V 4A1",
    "addr:housenumber":"40",
    "addr:postcode":"k9v 4a1",
    "addr:street":"William St N",
    "iso:country":"CA",
    "sg:address":"40 William St N",
    "sg:city":"Lindsay",
    "sg:classifiers":[
        {
            "category":"Organizations",
            "subcategory":"Religious Organization",
            "type":"Services"
        }
    ],
    "sg:phone":"+1 705 324 4842",
    "sg:postcode":"K9V 4A1",
    "sg:province":"ON",
    "sg:tags":[
        "church"
    ],
    "wof:name":"St Andrews Presbyterian Church",
    "wof:placetype":"venue"
},
  "geometry": {"coordinates":[-78.73732,44.356113],"type":"Point"}
}