{
  "type": "Feature",
  "properties": {
    "addr:full":"1859 Hwy 17 Corbeil ON P0H 1K0",
    "addr:housenumber":"1859",
    "addr:postcode":"p0h 1k0",
    "addr:street":"Hwy 17 Corbeil",
    "iso:country":"CA",
    "sg:address":"1859 Hwy 17",
    "sg:city":"Corbeil",
    "sg:classifiers":[
        {
            "category":"Travel",
            "subcategory":"Campground",
            "type":"Entertainment"
        }
    ],
    "sg:phone":"+1 705 752 2800",
    "sg:postcode":"P0H 1K0",
    "sg:province":"ON",
    "wof:name":"Dreany Haven Campground",
    "wof:placetype":"venue"
},
  "geometry": {"coordinates":[-79.29141235349999,46.2617683411],"type":"Point"}
}