{
  "type": "Feature",
  "properties": {
    "addr:full":"1 Macdonald Rd Domain MB R0G 0M0",
    "addr:housenumber":"1",
    "addr:postcode":"r0g 0m0",
    "addr:street":"Macdonald Rd",
    "iso:country":"CA",
    "sg:address":"1 Macdonald Rd",
    "sg:city":"Domain",
    "sg:classifiers":[
        {
            "category":"Wholesale",
            "subcategory":"Farm Supplies",
            "type":"Manufacturing & Wholesale Goods"
        }
    ],
    "sg:phone":"+1 204 736 4321",
    "sg:postcode":"R0G 0M0",
    "sg:province":"MB",
    "sg:tags":[
        "fertilizer"
    ],
    "wof:name":"Domain CO-OP Oil CO",
    "wof:placetype":"venue"
},
  "geometry": {"coordinates":[-97.3221130371,49.6170158386],"type":"Point"}
}