{
  "type": "Feature",
  "properties": {
    "iso:country":"CA",
    "sg:address":"80 Tiverton Crt # 202",
    "sg:city":"Markham",
    "sg:classifiers":[
        {
            "category":"Banks & Credit Unions",
            "subcategory":"Investment Brokerage",
            "type":"Services"
        }
    ],
    "sg:phone":"+1 905 470 5989",
    "sg:postcode":"L3R 0G4",
    "sg:province":"ON",
    "sg:tags":[
        "consultant",
        "planning",
        "financial"
    ],
    "wof:name":"Dundee Securities Corp",
    "wof:placetype":"venue"
},
  "geometry": {"coordinates":[-79.3701095581,43.8548355103],"type":"Point"}
}