{
  "type": "Feature",
  "properties": {
    "addr:full":"7912 16E Av Montreal QC H1Z 3P5",
    "addr:housenumber":"7912",
    "addr:postcode":"h1z 3p5",
    "addr:street":"16E Av",
    "iso:country":"CA",
    "sg:address":"7912 16E Av",
    "sg:city":"Montreal",
    "sg:classifiers":[
        {
            "category":"Manufacturing",
            "subcategory":"Tools & Machinery",
            "type":"Manufacturing & Wholesale Goods"
        }
    ],
    "sg:phone":"+1 514 722 8627",
    "sg:postcode":"H1Z 3P5",
    "sg:province":"QC",
    "sg:tags":[
        "machine",
        "shop"
    ],
    "wof:name":"Ateliers D'Usinage Papineau in",
    "wof:placetype":"venue"
},
  "geometry": {"coordinates":[-73.60495,45.566528],"type":"Point"}
}