{
  "type": "Feature",
  "properties": {
    "addr:full":"624 Magnetic Dr North York ON M3J 2C4",
    "addr:housenumber":"624",
    "addr:postcode":"m3j 2c4",
    "addr:street":"Magnetic Dr",
    "iso:country":"CA",
    "sg:address":"624 Magnetic Dr",
    "sg:city":"North York",
    "sg:classifiers":[
        {
            "category":"Real Estate",
            "subcategory":"Real Estate Agent",
            "type":"Services"
        }
    ],
    "sg:phone":"+1 416 663 4664",
    "sg:postcode":"M3J 2C4",
    "sg:province":"ON",
    "sg:tags":[
        "management"
    ],
    "wof:name":"Glen Corp",
    "wof:placetype":"venue"
},
  "geometry": {"coordinates":[-79.475571,43.78373],"type":"Point"}
}