{
  "type": "Feature",
  "properties": {
    "addr:full":"1750 Rue Eiffel Boucherville QC J4B 7W1",
    "addr:housenumber":"1750",
    "addr:postcode":"j4b 7w1",
    "addr:street":"Rue Eiffel",
    "iso:country":"CA",
    "sg:address":"1750 Rue Eiffel",
    "sg:city":"Boucherville",
    "sg:classifiers":[
        {
            "category":"Banks & Credit Unions",
            "subcategory":"Bank",
            "type":"Services"
        }
    ],
    "sg:phone":"+1 450 641 9062",
    "sg:postcode":"J4B 7W1",
    "sg:province":"QC",
    "sg:tags":[
        "automobile",
        "financing",
        "parts",
        "car",
        "supply"
    ],
    "wof:name":"Honda Canada Finances Inc",
    "wof:placetype":"venue"
},
  "geometry": {"coordinates":[-73.3759460449,45.5721054077],"type":"Point"}
}