{
  "type": "Feature",
  "properties": {
    "addr:full":"333 Boul Lebeau Saint-Laurent QC H4N 1S3",
    "addr:housenumber":"333",
    "addr:postcode":"h4n 1s3",
    "addr:street":"Boul Lebeau",
    "iso:country":"CA",
    "sg:address":"333 Boul Lebeau",
    "sg:city":"Saint-Laurent",
    "sg:classifiers":[
        {
            "category":"Farming",
            "subcategory":"Dairy Farm",
            "type":"Manufacturing & Wholesale Goods"
        }
    ],
    "sg:phone":"+1 514 332 2220",
    "sg:postcode":"H4N 1S3",
    "sg:province":"QC",
    "wof:name":"Natrel Inc",
    "wof:placetype":"venue"
},
  "geometry": {"coordinates":[-73.65868377690001,45.526096344],"type":"Point"}
}