{
  "type": "Feature",
  "properties": {
    "addr:full":"5100 South Service Rd # 19 Burlington ON L7L 6A5",
    "addr:housenumber":"5100",
    "addr:postcode":"l7l 6a5",
    "addr:street":"South Service Rd # 19",
    "iso:country":"CA",
    "sg:address":"5100 South Service Rd # 19",
    "sg:city":"Burlington",
    "sg:classifiers":[
        {
            "category":"Manufacturing",
            "subcategory":"Tools & Machinery",
            "type":"Manufacturing & Wholesale Goods"
        }
    ],
    "sg:phone":"+1 905 632 4040",
    "sg:postcode":"L7L 6A5",
    "sg:province":"ON",
    "sg:tags":[
        "recording",
        "instrument",
        "testing",
        "electronic",
        "equipment"
    ],
    "wof:name":"Text Fusion Systems",
    "wof:placetype":"venue"
},
  "geometry": {"coordinates":[-79.76959991459999,43.3819694519],"type":"Point"}
}