{
  "type": "Feature",
  "properties": {
    "addr:full":"419 King St W Oshawa ON L1J 2K5",
    "addr:housenumber":"419",
    "addr:postcode":"l1j 2k5",
    "addr:street":"King St W",
    "iso:country":"CA",
    "sg:address":"419 King St W",
    "sg:city":"Oshawa",
    "sg:classifiers":[
        {
            "category":"Shopping",
            "subcategory":"Hobbies, Toys, & Games",
            "type":"Retail Goods"
        }
    ],
    "sg:phone":"+1 905 433 9327",
    "sg:postcode":"L1J 2K5",
    "sg:province":"ON",
    "sg:tags":[
        "craft",
        "supply"
    ],
    "wof:name":"Lewiscraft",
    "wof:placetype":"venue"
},
  "geometry": {"coordinates":[-78.880028,43.893684],"type":"Point"}
}