{
  "type": "Feature",
  "properties": {
    "addr:full":"145 Rue DE Courval Aston-Jonction QC G0Z 1A0",
    "addr:housenumber":"145",
    "addr:postcode":"g0z 1a0",
    "addr:street":"Rue De Courval",
    "iso:country":"CA",
    "sg:address":"145 Rue DE Courval",
    "sg:city":"Aston-Jonction",
    "sg:classifiers":[
        {
            "category":"Manufacturing",
            "subcategory":"Furniture",
            "type":"Manufacturing & Wholesale Goods"
        }
    ],
    "sg:phone":"+1 819 226 3478",
    "sg:postcode":"G0Z 1A0",
    "sg:province":"QC",
    "wof:name":"Meubles Rene Blais",
    "wof:placetype":"venue"
},
  "geometry": {"coordinates":[-72.2279510498,46.1695785522],"type":"Point"}
}