{
  "type": "Feature",
  "properties": {
    "addr:full":"2465 Mcdougall St # 100 Windsor ON N8X 3N9",
    "addr:housenumber":"2465",
    "addr:postcode":"n8x 3n9",
    "addr:street":"Mcdougall St # 100",
    "iso:country":"CA",
    "sg:address":"2465 Mcdougall St # 100",
    "sg:city":"Windsor",
    "sg:classifiers":[
        {
            "category":"Professional",
            "subcategory":"Engineering",
            "type":"Services"
        }
    ],
    "sg:phone":"+1 519 250 3733",
    "sg:postcode":"N8X 3N9",
    "sg:province":"ON",
    "sg:tags":[
        "engineer"
    ],
    "wof:name":"Golder Associates Ltd",
    "wof:placetype":"venue"
},
  "geometry": {"coordinates":[-83.01722700000001,42.291286],"type":"Point"}
}