{
  "type": "Feature",
  "properties": {
    "addr:full":"3425 Dundas St W York ON M6S 2S4",
    "addr:housenumber":"3425",
    "addr:postcode":"m6s 2s4",
    "addr:street":"Dundas St W",
    "iso:country":"CA",
    "sg:address":"3425 Dundas St W",
    "sg:city":"York",
    "sg:classifiers":[
        {
            "category":"Building & Trades",
            "subcategory":"Construction",
            "type":"Services"
        }
    ],
    "sg:phone":"+1 905 276 2641",
    "sg:postcode":"M6S 2S4",
    "sg:province":"ON",
    "sg:tags":[
        "excavating",
        "contractor"
    ],
    "wof:name":"Ljs Construction Ltd",
    "wof:placetype":"venue"
},
  "geometry": {"coordinates":[-79.505661,43.66275],"type":"Point"}
}