{
  "type": "Feature",
  "properties": {
    "addr:full":"1220 6th Ave Prince George BC V2L 3M8",
    "addr:housenumber":"1220",
    "addr:postcode":"v2l 3m8",
    "addr:street":"6Th Ave",
    "iso:country":"CA",
    "sg:address":"1220 6th Ave",
    "sg:city":"Prince George",
    "sg:classifiers":[
        {
            "category":"Professional",
            "type":"Services"
        }
    ],
    "sg:phone":"+1 250 564 8861",
    "sg:postcode":"V2L 3M8",
    "sg:province":"BC",
    "sg:tags":[
        "establishment",
        "company",
        "broadcasting",
        "radio"
    ],
    "wof:name":"Ckpg Radio & Tv",
    "wof:placetype":"venue"
},
  "geometry": {"coordinates":[-122.746704102,53.9144973755],"type":"Point"}
}