{
  "type": "Feature",
  "properties": {
    "addr:full":"RR 2 STN Main Strathmore AB T1P 1K5",
    "addr:postcode":"t1p 1k5",
    "addr:street":"Rr 2 Stn Main",
    "iso:country":"CA",
    "sg:address":"RR 2 STN Main",
    "sg:city":"Strathmore",
    "sg:classifiers":[
        {
            "category":"Professional",
            "subcategory":"Testing Lab",
            "type":"Services"
        }
    ],
    "sg:phone":"+1 403 934 3131",
    "sg:postcode":"T1P 1K5",
    "sg:province":"AB",
    "sg:tags":[
        "x"
    ],
    "wof:name":"Gammatech Inspection Svc Ltd",
    "wof:placetype":"venue"
},
  "geometry": {"coordinates":[-113.400291,51.041306],"type":"Point"}
}