{
  "type": "Feature",
  "properties": {
    "addr:full":"5 Britannia Rd W Goderich ON N7A 2A8",
    "addr:housenumber":"5",
    "addr:postcode":"n7a 2a8",
    "addr:street":"Britannia Rd W",
    "iso:country":"CA",
    "sg:address":"5 Britannia Rd W",
    "sg:city":"Goderich",
    "sg:classifiers":[
        {
            "category":"Professional",
            "subcategory":"Computer Services",
            "type":"Services"
        }
    ],
    "sg:phone":"+1 519 524 7212",
    "sg:postcode":"N7A 2A8",
    "sg:province":"ON",
    "sg:tags":[
        "processing",
        "datum"
    ],
    "wof:name":"Bentley Financial Data Proc",
    "wof:placetype":"venue"
},
  "geometry": {"coordinates":[-81.711449,43.739082],"type":"Point"}
}