{
  "type": "Feature",
  "properties": {
    "addr:full":"New Westminster BC V3L 5H1",
    "addr:postcode":"v3l 5h1",
    "iso:country":"CA",
    "sg:city":"New Westminster",
    "sg:classifiers":[
        {
            "category":"Professional",
            "subcategory":"Accounting & Tax Preparation",
            "type":"Services"
        }
    ],
    "sg:phone":"+1 604 525 4686",
    "sg:postcode":"V3L 5H1",
    "sg:province":"BC",
    "sg:tags":[
        "accountant"
    ],
    "wof:name":"Seymour & Assoc",
    "wof:placetype":"venue"
},
  "geometry": {"coordinates":[-122.91954,49.212696],"type":"Point"}
}