{
  "type": "Feature",
  "properties": {
    "addr:full":"350 Seneca Hill Dr # 314 North York ON M2J 4S7",
    "addr:housenumber":"350",
    "addr:postcode":"m2j 4s7",
    "addr:street":"Seneca Hill Dr # 314",
    "iso:country":"CA",
    "sg:address":"350 Seneca Hill Dr # 314",
    "sg:city":"North York",
    "sg:classifiers":[
        {
            "category":"Wholesale",
            "subcategory":"Non-durable Goods",
            "type":"Manufacturing & Wholesale Goods"
        }
    ],
    "sg:phone":"+1 416 499 9104",
    "sg:postcode":"M2J 4S7",
    "sg:province":"ON",
    "sg:tags":[
        "advertising"
    ],
    "wof:name":"Apt Marketing Corp",
    "wof:placetype":"venue"
},
  "geometry": {"coordinates":[-79.355423,43.790173],"type":"Point"}
}