{
  "type": "Feature",
  "properties": {
    "addr:full":"Welland ON L3C 6T8",
    "addr:postcode":"l3c 6t8",
    "iso:country":"CA",
    "sg:city":"Welland",
    "sg:classifiers":[
        {
            "category":"Retail",
            "subcategory":"Auto Rental",
            "type":"Services"
        }
    ],
    "sg:phone":"+1 905 788 3373",
    "sg:postcode":"L3C 6T8",
    "sg:province":"ON",
    "sg:tags":[
        "renting",
        "automobile"
    ],
    "wof:name":"Discount Car & Truck Rentals",
    "wof:placetype":"venue"
},
  "geometry": {"coordinates":[-79.251587,43.00687],"type":"Point"}
}