{
  "type": "Feature",
  "properties": {
    "iso:country":"CA",
    "sg:address":"152 Fair View Ln",
    "sg:city":"Powassan",
    "sg:classifiers":[
        {
            "category":"Education",
            "subcategory":"School",
            "type":"Public Place"
        }
    ],
    "sg:phone":"+1 705 724 3482",
    "sg:postcode":"P0H 1Z0",
    "sg:province":"ON",
    "wof:name":"St Gregory School",
    "wof:placetype":"venue"
},
  "geometry": {"coordinates":[-79.3640594482,46.0820159912],"type":"Point"}
}