{
  "type": "Feature",
  "properties": {
    "addr:full":"Saint-Charles-Sur-Richelieu QC J0H 2G0",
    "addr:postcode":"j0h 2g0",
    "iso:country":"CA",
    "sg:city":"Saint-Charles-Sur-Richelieu",
    "sg:classifiers":[
        {
            "category":"Manufacturing",
            "subcategory":"Glass & Minerals",
            "type":"Manufacturing & Wholesale Goods"
        }
    ],
    "sg:phone":"+1 450 584 2101",
    "sg:postcode":"J0H 2G0",
    "sg:province":"QC",
    "sg:tags":[
        "fabricator",
        "fiber",
        "plastic"
    ],
    "wof:name":"Fibre Cnc Inc",
    "wof:placetype":"venue"
},
  "geometry": {"coordinates":[-73.1838226318,45.6899375916],"type":"Point"}
}