{
  "type": "Feature",
  "properties": {
    "addr:full":"208 393 Rte LA Sarre QC J9Z 2X2",
    "addr:housenumber":"393",
    "addr:postcode":"j9z 2x2",
    "addr:street":"Rte La Sarre",
    "iso:country":"CA",
    "sg:address":"208 393 Rte",
    "sg:city":"LA Sarre",
    "sg:classifiers":[
        {
            "category":"Autos & Motor Vehicles",
            "subcategory":"Motorcycle Sales",
            "type":"Retail Goods"
        }
    ],
    "sg:phone":"+1 819 333 3030",
    "sg:postcode":"J9Z 2X2",
    "sg:province":"QC",
    "sg:tags":[
        "dealer",
        "boat"
    ],
    "wof:name":"Dimension Sport Inc",
    "wof:placetype":"venue"
},
  "geometry": {"coordinates":[-79.200317,48.797562],"type":"Point"}
}