{
  "type": "Feature",
  "properties": {
    "iso:country":"CA",
    "sg:address":"51 Graniteridge Rd",
    "sg:city":"Concord",
    "sg:classifiers":[
        {
            "category":"Manufacturing",
            "subcategory":"Glass & Minerals",
            "type":"Manufacturing & Wholesale Goods"
        }
    ],
    "sg:phone":"+1 905 660 6671",
    "sg:postcode":"L4K 5M9",
    "sg:province":"ON",
    "sg:tags":[
        "bottle"
    ],
    "wof:name":"Trident Plastics Ltd",
    "wof:placetype":"venue"
},
  "geometry": {"coordinates":[-79.52634429930001,43.8264350891],"type":"Point"}
}