{
  "type": "Feature",
  "properties": {
    "addr:full":"130 Forest Park Dr Winnipeg MB R2V 2R8",
    "addr:housenumber":"130",
    "addr:postcode":"r2v 2r8",
    "addr:street":"Forest Park Dr",
    "iso:country":"CA",
    "sg:address":"130 Forest Park Dr",
    "sg:city":"Winnipeg",
    "sg:classifiers":[
        {
            "category":"Education",
            "subcategory":"School",
            "type":"Public Place"
        }
    ],
    "sg:phone":"+1 204 338 9341",
    "sg:postcode":"R2V 2R8",
    "sg:province":"MB",
    "wof:name":"Forest Park School",
    "wof:placetype":"venue"
},
  "geometry": {"coordinates":[-97.138374,49.943661],"type":"Point"}
}