{
  "type": "Feature",
  "properties": {
    "addr:full":"255 Hamilton Ave Winnipeg MB R2Y 2C3",
    "addr:housenumber":"255",
    "addr:postcode":"r2y 2c3",
    "addr:street":"Hamilton Ave",
    "iso:country":"CA",
    "sg:address":"255 Hamilton Ave",
    "sg:city":"Winnipeg",
    "sg:classifiers":[
        {
            "category":"Retail",
            "subcategory":"Repair Shop",
            "type":"Services"
        }
    ],
    "sg:phone":"+1 204 299 9304",
    "sg:postcode":"R2Y 2C3",
    "sg:province":"MB",
    "sg:tags":[
        "sharpening",
        "skate"
    ],
    "wof:name":"Vimy Arena Skate Sharpening",
    "wof:placetype":"venue"
},
  "geometry": {"coordinates":[-97.291222,49.893063],"type":"Point"}
}