{
  "type": "Feature",
  "properties": {
    "iso:country":"CA",
    "sg:address":"566 Paul St",
    "sg:city":"Dieppe",
    "sg:classifiers":[
        {
            "category":"Retail",
            "subcategory":"Auto Rental",
            "type":"Services"
        }
    ],
    "sg:phone":"+1 506 857 2323",
    "sg:postcode":"E1A 5Z1",
    "sg:province":"NB",
    "sg:tags":[
        "renting",
        "automobile"
    ],
    "wof:name":"Discount Car & Truck Rentals",
    "wof:placetype":"venue"
},
  "geometry": {"coordinates":[-64.7560043335,46.0952796936],"type":"Point"}
}