{
  "type": "Feature",
  "properties": {
    "addr:full":"St Catharines ON L2M 7T9",
    "addr:postcode":"l2m 7t9",
    "iso:country":"CA",
    "sg:city":"St Catharines",
    "sg:classifiers":[
        {
            "category":"Education",
            "subcategory":"Special Training",
            "type":"Public Place"
        }
    ],
    "sg:phone":"+1 905 646 2772",
    "sg:postcode":"L2M 7T9",
    "sg:province":"ON",
    "sg:tags":[
        "instruction",
        "driving"
    ],
    "wof:name":"Foster's Driving School Ltd",
    "wof:placetype":"venue"
},
  "geometry": {"coordinates":[-79.2103500366,43.1774253845],"type":"Point"}
}