{
  "type": "Feature",
  "properties": {
    "addr:full":"337 Queen St Sarnia ON N7T 2S3",
    "addr:housenumber":"337",
    "addr:postcode":"n7t 2s3",
    "addr:street":"Queen St",
    "iso:country":"CA",
    "sg:address":"337 Queen St",
    "sg:city":"Sarnia",
    "sg:classifiers":[
        {
            "category":"Manufacturing",
            "subcategory":"Metals",
            "type":"Manufacturing & Wholesale Goods"
        }
    ],
    "sg:phone":"+1 519 332 2313",
    "sg:postcode":"N7T 2S3",
    "sg:province":"ON",
    "sg:tags":[
        "treating",
        "heat"
    ],
    "wof:name":"Clysdale Heat Treating Ltd",
    "wof:placetype":"venue"
},
  "geometry": {"coordinates":[-82.407699585,42.9613838196],"type":"Point"}
}