{
  "type": "Feature",
  "properties": {
    "addr:full":"725 Boul Perron Carleton QC G0C 1J0",
    "addr:housenumber":"725",
    "addr:postcode":"g0c 1j0",
    "addr:street":"Boul Perron",
    "iso:country":"CA",
    "sg:address":"725 Boul Perron",
    "sg:city":"Carleton",
    "sg:classifiers":[
        {
            "category":"Shopping",
            "subcategory":"Clothing, Apparel, & Fashions",
            "type":"Retail Goods"
        }
    ],
    "sg:phone":"+1 418 364 3885",
    "sg:postcode":"G0C 1J0",
    "sg:province":"QC",
    "sg:tags":[
        "boutique",
        "sportswear"
    ],
    "wof:name":"Boutique Aux Quatre Vents Enr",
    "wof:placetype":"venue"
},
  "geometry": {"coordinates":[-66.112572,48.101234],"type":"Point"}
}