{
  "type": "Feature",
  "properties": {
    "addr:full":"Nepean ON K2B 8C1",
    "addr:postcode":"k2b 8c1",
    "iso:country":"CA",
    "sg:city":"Nepean",
    "sg:classifiers":[
        {
            "category":"Shopping",
            "subcategory":"Shoes",
            "type":"Retail Goods"
        }
    ],
    "sg:phone":"+1 613 828 3300",
    "sg:postcode":"K2B 8C1",
    "sg:province":"ON",
    "wof:name":"Aldo Shoes Inc",
    "wof:placetype":"venue"
},
  "geometry": {"coordinates":[-75.805138,45.349049],"type":"Point"}
}