{
  "type": "Feature",
  "properties": {
    "addr:full":"Saint-Andre-D'Argenteuil QC J0V 1X0",
    "addr:postcode":"j0v 1x0",
    "iso:country":"CA",
    "sg:city":"Saint-Andre-D'Argenteuil",
    "sg:classifiers":[
        {
            "category":"Personal",
            "subcategory":"Beauty Salon",
            "type":"Services"
        }
    ],
    "sg:phone":"+1 450 537 8351",
    "sg:postcode":"J0V 1X0",
    "sg:province":"QC",
    "wof:name":"Coiffure France Enr",
    "wof:placetype":"venue"
},
  "geometry": {"coordinates":[-74.34289550779999,45.6451225281],"type":"Point"}
}