{
  "type": "Feature",
  "properties": {
    "addr:full":"11 Locust St Kitchener ON N2H 1W6",
    "addr:housenumber":"11",
    "addr:postcode":"n2h 1w6",
    "addr:street":"Locust St",
    "iso:country":"CA",
    "sg:address":"11 Locust St",
    "sg:city":"Kitchener",
    "sg:classifiers":[
        {
            "category":"Professional",
            "subcategory":"Business Services",
            "type":"Services"
        }
    ],
    "sg:phone":"+1 519 570 0065",
    "sg:postcode":"N2H 1W6",
    "sg:province":"ON",
    "sg:tags":[
        "water",
        "equipment",
        "treatment",
        "softening"
    ],
    "wof:name":"A Soft Touch",
    "wof:placetype":"venue"
},
  "geometry": {"coordinates":[-80.4798126221,43.4589653015],"type":"Point"}
}