{
  "type": "Feature",
  "properties": {
    "addr:full":"98 Boul Du Portage-Des-Mousses Port-Cartier QC G5B 1E1",
    "addr:housenumber":"98",
    "addr:postcode":"g5b 1e1",
    "addr:street":"Boul Du Portage-Des-Mousses",
    "iso:country":"CA",
    "sg:address":"98 Boul Du Portage-Des-Mousses",
    "sg:city":"Port-Cartier",
    "sg:classifiers":[
        {
            "category":"Real Estate",
            "subcategory":"Real Estate Agent",
            "type":"Services"
        }
    ],
    "sg:phone":"+1 418 766 2240",
    "sg:postcode":"G5B 1E1",
    "sg:province":"QC",
    "sg:tags":[
        "excavating",
        "agency",
        "rental",
        "contractor"
    ],
    "wof:name":"Equipement Lev Inc",
    "wof:placetype":"venue"
},
  "geometry": {"coordinates":[-66.84809875489999,50.0346412659],"type":"Point"}
}