{
  "type": "Feature",
  "properties": {
    "addr:full":"1272 Wallace St Regina SK S4N 3Z3",
    "addr:housenumber":"1272",
    "addr:postcode":"s4n 3z3",
    "addr:street":"Wallace St",
    "iso:country":"CA",
    "sg:address":"1272 Wallace St",
    "sg:city":"Regina",
    "sg:classifiers":[
        {
            "category":"Building & Trades",
            "subcategory":"Plumbing",
            "type":"Services"
        }
    ],
    "sg:phone":"+1 306 757 8828",
    "sg:postcode":"S4N 3Z3",
    "sg:province":"SK",
    "sg:tags":[
        "contractor"
    ],
    "wof:name":"Academy Plumbing & Heating Ltd",
    "wof:placetype":"venue"
},
  "geometry": {"coordinates":[-104.593955994,50.458782196],"type":"Point"}
}