{
  "type": "Feature",
  "properties": {
    "iso:country":"CA",
    "sg:address":"PO Box 508",
    "sg:city":"Nampa",
    "sg:classifiers":[
        {
            "category":"Travel",
            "subcategory":"Hotels & Motels",
            "type":"Entertainment"
        }
    ],
    "sg:phone":"+1 780 322 3730",
    "sg:postcode":"T0H 2R0",
    "sg:province":"AB",
    "wof:name":"Big Country Inn",
    "wof:placetype":"venue"
},
  "geometry": {"coordinates":[-117.134315,56.038799],"type":"Point"}
}