{
  "type": "Feature",
  "properties": {
    "iso:country":"CA",
    "sg:city":"Oakville",
    "sg:classifiers":[
        {
            "category":"Real Estate",
            "subcategory":"Real Estate Agent",
            "type":"Services"
        }
    ],
    "sg:phone":"+1 905 469 8776",
    "sg:postcode":"L6M 2G2",
    "sg:province":"ON",
    "sg:tags":[
        "management"
    ],
    "wof:name":"Bentall Real Estate Svc",
    "wof:placetype":"venue"
},
  "geometry": {"coordinates":[-79.71241,43.436306],"type":"Point"}
}