{
  "type": "Feature",
  "properties": {
    "iso:country":"CA",
    "sg:address":"78 Ormond St N",
    "sg:city":"Thorold",
    "sg:classifiers":[
        {
            "category":"Food & Beverages",
            "subcategory":"Liquor & Beverages",
            "type":"Retail Goods"
        }
    ],
    "sg:phone":"+1 905 227 1119",
    "sg:postcode":"L2V 1Z4",
    "sg:province":"ON",
    "sg:tags":[
        "beer",
        "ale"
    ],
    "wof:name":"Beer Store",
    "wof:placetype":"venue"
},
  "geometry": {"coordinates":[-79.199158,43.131691],"type":"Point"}
}