{
  "type": "Feature",
  "properties": {
    "addr:full":"9751 Bridgeport Rd Richmond BC V6X 1S3",
    "addr:housenumber":"9751",
    "addr:postcode":"v6x 1s3",
    "addr:street":"Bridgeport Rd",
    "iso:country":"CA",
    "sg:address":"9751 Bridgeport Rd",
    "sg:city":"Richmond",
    "sg:classifiers":[
        {
            "category":"Shopping",
            "subcategory":"Stationery & Office Supplies",
            "type":"Retail Goods"
        }
    ],
    "sg:phone":"+1 604 303 9677",
    "sg:postcode":"V6X 1S3",
    "sg:province":"BC",
    "wof:name":"Office Depot",
    "wof:placetype":"venue"
},
  "geometry": {"coordinates":[-123.11481499999999,49.192055],"type":"Point"}
}