{
  "type": "Feature",
  "properties": {
    "addr:full":"10040 Galaran Rd Sidney BC V8L 5X9",
    "addr:housenumber":"10040",
    "addr:postcode":"v8l 5x9",
    "addr:street":"Galaran Rd",
    "iso:country":"CA",
    "sg:address":"10040 Galaran Rd",
    "sg:city":"Sidney",
    "sg:classifiers":[
        {
            "category":"Autos & Motor Vehicles",
            "subcategory":"Recreational Vehicle Sales",
            "type":"Retail Goods"
        }
    ],
    "sg:phone":"+1 250 655 1119",
    "sg:postcode":"V8L 5X9",
    "sg:province":"BC",
    "wof:name":"Arbutus Rv & Marine Sales",
    "wof:placetype":"venue"
},
  "geometry": {"coordinates":[-123.412598,48.654095],"type":"Point"}
}