{
  "type": "Feature",
  "properties": {
    "addr:full":"21 Mill St N Waterdown ON L0R 2H0",
    "addr:housenumber":"21",
    "addr:postcode":"l0r 2h0",
    "addr:street":"Mill St N",
    "iso:country":"CA",
    "sg:address":"21 Mill St N",
    "sg:city":"Waterdown",
    "sg:classifiers":[
        {
            "category":"Organizations",
            "subcategory":"Religious Organization",
            "type":"Services"
        }
    ],
    "sg:phone":"+1 905 689 6019",
    "sg:postcode":"L0R 2H0",
    "sg:province":"ON",
    "sg:tags":[
        "church"
    ],
    "wof:name":"Waterdown Alliance Church",
    "wof:placetype":"venue"
},
  "geometry": {"coordinates":[-79.8925628662,43.3347663879],"type":"Point"}
}