{
  "type": "Feature",
  "properties": {
    "addr:full":"94 Rue Saint-Fidele LA Malbaie QC G5A 2K9",
    "addr:housenumber":"94",
    "addr:postcode":"g5a 2k9",
    "addr:street":"Rue Saint-Fidele",
    "iso:country":"CA",
    "sg:address":"94 Rue Saint-Fidele",
    "sg:city":"LA Malbaie",
    "sg:classifiers":[
        {
            "category":"Banks & Credit Unions",
            "subcategory":"Bank",
            "type":"Services"
        }
    ],
    "sg:phone":"+1 418 665 4443",
    "sg:postcode":"G5A 2K9",
    "sg:province":"QC",
    "wof:name":"Caisses Desjardins",
    "wof:placetype":"venue"
},
  "geometry": {"coordinates":[-69.99318695069999,47.7380752563],"type":"Point"}
}