{
  "type": "Feature",
  "properties": {
    "addr:full":"363 Maidstone Ave E Essex ON N8M 2X1",
    "addr:housenumber":"363",
    "addr:postcode":"n8m 2x1",
    "addr:street":"Maidstone Ave E",
    "iso:country":"CA",
    "sg:address":"363 Maidstone Ave E",
    "sg:city":"Essex",
    "sg:classifiers":[
        {
            "category":"Retail",
            "subcategory":"Auto Repair",
            "type":"Services"
        }
    ],
    "sg:phone":"+1 519 776 5894",
    "sg:postcode":"N8M 2X1",
    "sg:province":"ON",
    "sg:tags":[
        "body",
        "automobile",
        "painting"
    ],
    "wof:name":"Fairview Carstar Collision",
    "wof:placetype":"venue"
},
  "geometry": {"coordinates":[-82.80536651609999,42.1774215698],"type":"Point"}
}