{
  "type": "Feature",
  "properties": {
    "addr:full":"3058 Kingsway Vancouver BC V5R 5J7",
    "addr:housenumber":"3058",
    "addr:postcode":"v5r 5j7",
    "addr:street":"Kingsway",
    "iso:country":"CA",
    "sg:address":"3058 Kingsway",
    "sg:city":"Vancouver",
    "sg:classifiers":[
        {
            "category":"Utilities",
            "subcategory":"Mobile Phone",
            "type":"Services"
        }
    ],
    "sg:phone":"+1 604 451 8260",
    "sg:postcode":"V5R 5J7",
    "sg:province":"BC",
    "sg:tags":[
        "telephone",
        "cellular"
    ],
    "wof:name":"Tan-Van Media Ltd",
    "wof:placetype":"venue"
},
  "geometry": {"coordinates":[-123.040649,49.235664],"type":"Point"}
}