{
  "type": "Feature",
  "properties": {
    "addr:full":"39 Rue Laval Hull QC J8X 3G8",
    "addr:housenumber":"39",
    "addr:postcode":"j8x 3g8",
    "addr:street":"Rue Laval",
    "iso:country":"CA",
    "sg:address":"39 Rue Laval",
    "sg:city":"Hull",
    "sg:classifiers":[
        {
            "category":"Restaurant",
            "type":"Food & Drink"
        }
    ],
    "sg:phone":"+1 819 770 7227",
    "sg:postcode":"J8X 3G8",
    "sg:province":"QC",
    "wof:name":"Chez Le Thai",
    "wof:placetype":"venue"
},
  "geometry": {"coordinates":[-75.716506958,45.4267921448],"type":"Point"}
}