{
  "type": "Feature",
  "properties": {
    "addr:full":"4303 Varsity Dr NW Calgary AB T3A 0Z7",
    "addr:housenumber":"4303",
    "addr:postcode":"t3a 0z7",
    "addr:street":"Varsity Dr Nw",
    "iso:country":"CA",
    "sg:address":"4303 Varsity Dr NW",
    "sg:city":"Calgary",
    "sg:classifiers":[
        {
            "category":"Organizations",
            "subcategory":"Religious Organization",
            "type":"Services"
        }
    ],
    "sg:phone":"+1 403 286 4477",
    "sg:postcode":"T3A 0Z7",
    "sg:province":"AB",
    "sg:tags":[
        "church"
    ],
    "wof:name":"Northwest Victory Church",
    "wof:placetype":"venue"
},
  "geometry": {"coordinates":[-114.149337769,51.092250824],"type":"Point"}
}