{
  "type": "Feature",
  "properties": {
    "addr:full":"Sidney BC V8L 4M9",
    "addr:postcode":"v8l 4m9",
    "iso:country":"CA",
    "sg:city":"Sidney",
    "sg:classifiers":[
        {
            "category":"Health Services",
            "subcategory":"Doctor",
            "type":"Services"
        }
    ],
    "sg:phone":"+1 250 656 6464",
    "sg:postcode":"V8L 4M9",
    "sg:province":"BC",
    "sg:tags":[
        "dentist"
    ],
    "wof:name":"Boyd, Ian DDS",
    "wof:placetype":"venue"
},
  "geometry": {"coordinates":[-123.401573,48.647457],"type":"Point"}
}