{
  "type": "Feature",
  "properties": {
    "iso:country":"CA",
    "sg:address":"70 North Park Gdns",
    "sg:city":"Belleville",
    "sg:classifiers":[
        {
            "category":"Building & Trades",
            "subcategory":"Plumbing",
            "type":"Services"
        }
    ],
    "sg:phone":"+1 613 962 4234",
    "sg:postcode":"K8P 2M3",
    "sg:province":"ON",
    "sg:tags":[
        "contractor"
    ],
    "wof:name":"Chapman Plumbing & Heating",
    "wof:placetype":"venue"
},
  "geometry": {"coordinates":[-77.386169,44.184242],"type":"Point"}
}