{
  "type": "Feature",
  "properties": {
    "addr:full":"4801 50 St Camrose AB T4V 1P4",
    "addr:housenumber":"4801",
    "addr:postcode":"t4v 1p4",
    "addr:street":"50 St",
    "iso:country":"CA",
    "sg:address":"4801 50 St",
    "sg:city":"Camrose",
    "sg:classifiers":[
        {
            "category":"Banks & Credit Unions",
            "subcategory":"Bank",
            "type":"Services"
        }
    ],
    "sg:phone":"+1 780 672 9261",
    "sg:postcode":"T4V 1P4",
    "sg:province":"AB",
    "wof:name":"Scotiabank",
    "wof:placetype":"venue"
},
  "geometry": {"coordinates":[-112.825637817,53.0184020996],"type":"Point"}
}