{
  "type": "Feature",
  "properties": {
    "addr:full":"1120 15 Ave S Creston BC V0B 1G1",
    "addr:housenumber":"1120",
    "addr:postcode":"bc v0b 1g1",
    "addr:street":"15 Ave S",
    "iso:country":"CA",
    "sg:address":"1120 15 Ave S",
    "sg:city":"Creston",
    "sg:classifiers":[
        {
            "category":"Retail",
            "subcategory":"Laundry & Dry Cleaning",
            "type":"Services"
        }
    ],
    "sg:phone":"+1 250 428 7814",
    "sg:postcode":"V0B 1G1",
    "sg:province":"BC",
    "sg:tags":[
        "cleaners",
        "rug",
        "carpet"
    ],
    "wof:name":"Cleaner Carpet Care",
    "wof:placetype":"venue"
},
  "geometry": {"coordinates":[-116.508308,49.094761],"type":"Point"}
}