{
  "type": "Feature",
  "properties": {
    "addr:full":"786 Annette St Toronto ON M6S 2E2",
    "addr:housenumber":"786",
    "addr:postcode":"m6s 2e2",
    "addr:street":"Annette St",
    "iso:country":"CA",
    "sg:address":"786 Annette St",
    "sg:city":"Toronto",
    "sg:classifiers":[
        {
            "category":"Shopping",
            "subcategory":"Discount & Variety Stores",
            "type":"Retail Goods"
        }
    ],
    "sg:phone":"+1 416 766 5138",
    "sg:postcode":"M6S 2E2",
    "sg:province":"ON",
    "wof:name":"Wally's Smoke & Variety Shop",
    "wof:placetype":"venue"
},
  "geometry": {"coordinates":[-79.4876708984,43.6584968567],"type":"Point"}
}