{
  "type": "Feature",
  "properties": {
    "addr:full":"Thornhill ON L4J 2L1",
    "addr:postcode":"l4j 2l1",
    "iso:country":"CA",
    "sg:city":"Thornhill",
    "sg:classifiers":[
        {
            "category":"Shopping",
            "subcategory":"Shoes",
            "type":"Retail Goods"
        }
    ],
    "sg:phone":"+1 905 886 2363",
    "sg:postcode":"L4J 2L1",
    "sg:province":"ON",
    "wof:name":"Canly Shoes",
    "wof:placetype":"venue"
},
  "geometry": {"coordinates":[-79.4261627197,43.7968215942],"type":"Point"}
}