{
  "type": "Feature",
  "properties": {
    "iso:country":"CA",
    "sg:address":"4552 Long Lake Rd",
    "sg:city":"Sudbury",
    "sg:classifiers":[
        {
            "category":"Building & Trades",
            "subcategory":"Electrical",
            "type":"Services"
        }
    ],
    "sg:phone":"+1 705 522 5106",
    "sg:postcode":"P3G 1K5",
    "sg:province":"ON",
    "sg:tags":[
        "electric",
        "contractor"
    ],
    "wof:name":"Hkh Electric Ltd",
    "wof:placetype":"venue"
},
  "geometry": {"coordinates":[-80.9982376099,46.4058761597],"type":"Point"}
}