{
  "type": "Feature",
  "properties": {
    "addr:full":"331100 Hwy 17 E Deep River ON K0J 1P0",
    "addr:housenumber":"331100",
    "addr:postcode":"k0j 1p0",
    "addr:street":"Hwy 17 E",
    "iso:country":"CA",
    "sg:address":"331100 Hwy 17 E",
    "sg:city":"Deep River",
    "sg:classifiers":[
        {
            "category":"Education",
            "subcategory":"School",
            "type":"Public Place"
        }
    ],
    "sg:phone":"+1 613 584 3567",
    "sg:postcode":"K0J 1P0",
    "sg:province":"ON",
    "wof:name":"St Mary's School",
    "wof:placetype":"venue"
},
  "geometry": {"coordinates":[-77.48290299999999,46.081635],"type":"Point"}
}