{
  "type": "Feature",
  "properties": {
    "iso:country":"CA",
    "sg:address":"245 Rang Saint-Antoine",
    "sg:city":"Saint-Elphege",
    "sg:classifiers":[
        {
            "category":"Government",
            "subcategory":"Office",
            "type":"Public Place"
        }
    ],
    "sg:phone":"+1 450 568 0288",
    "sg:postcode":"J0G 1J0",
    "sg:province":"QC",
    "sg:tags":[
        "village"
    ],
    "wof:name":"St Elphege Municipalite",
    "wof:placetype":"venue"
},
  "geometry": {"coordinates":[-72.70185089109999,46.0585746765],"type":"Point"}
}