{
  "type": "Feature",
  "properties": {
    "addr:full":"4001 16A St SE Calgary AB T2G 3T5",
    "addr:housenumber":"4001",
    "addr:postcode":"t2g 3t5",
    "addr:street":"16A St Se",
    "iso:country":"CA",
    "sg:address":"4001 16A St SE",
    "sg:city":"Calgary",
    "sg:classifiers":[
        {
            "category":"Building & Trades",
            "subcategory":"Plumbing",
            "type":"Services"
        }
    ],
    "sg:phone":"+1 403 234 9799",
    "sg:postcode":"T2G 3T5",
    "sg:province":"AB",
    "sg:tags":[
        "refrigeration",
        "contractor"
    ],
    "wof:name":"Pace Industrial Refrigeration",
    "wof:placetype":"venue"
},
  "geometry": {"coordinates":[-114.020844,51.020042],"type":"Point"}
}