{
  "type": "Feature",
  "properties": {
    "iso:country":"CA",
    "sg:address":"25 Rue Laurier",
    "sg:city":"Hull",
    "sg:classifiers":[
        {
            "category":"Government",
            "subcategory":"Office",
            "type":"Public Place"
        }
    ],
    "sg:phone":"+1 819 595 8200",
    "sg:postcode":"J8X 4C8",
    "sg:province":"QC",
    "sg:tags":[
        "village"
    ],
    "wof:name":"Legal Affairs",
    "wof:placetype":"venue"
},
  "geometry": {"coordinates":[-75.710655,45.427956],"type":"Point"}
}