{
  "type": "Feature",
  "properties": {
    "addr:full":"420 Rue Champagnat Disraeli QC G0N 1E0",
    "addr:housenumber":"420",
    "addr:postcode":"g0n 1e0",
    "addr:street":"Rue Champagnat Disraeli",
    "iso:country":"CA",
    "sg:address":"420 Rue Champagnat",
    "sg:city":"Disraeli",
    "sg:classifiers":[
        {
            "category":"Personal",
            "subcategory":"Beauty Salon",
            "type":"Services"
        }
    ],
    "sg:phone":"+1 418 449 3737",
    "sg:postcode":"G0N 1E0",
    "sg:province":"QC",
    "wof:name":"Coiffure 420",
    "wof:placetype":"venue"
},
  "geometry": {"coordinates":[-71.36837768549999,45.9006500244],"type":"Point"}
}