{
  "type": "Feature",
  "properties": {
    "addr:full":"Etobicoke ON M9V 4B8",
    "addr:postcode":"m9v 4b8",
    "iso:country":"CA",
    "sg:city":"Etobicoke",
    "sg:classifiers":[
        {
            "category":"Health Services",
            "subcategory":"Doctor",
            "type":"Services"
        }
    ],
    "sg:phone":"+1 416 743 6063",
    "sg:postcode":"M9V 4B8",
    "sg:province":"ON",
    "sg:tags":[
        "physician",
        "surgeon"
    ],
    "wof:name":"Mmd Management Svc Ltd",
    "wof:placetype":"venue"
},
  "geometry": {"coordinates":[-79.598213,43.73101],"type":"Point"}
}