{
  "type": "Feature",
  "properties": {
    "iso:country":"CA",
    "sg:address":"1411 Upper Wellington St",
    "sg:city":"Hamilton",
    "sg:classifiers":[
        {
            "category":"Organizations",
            "subcategory":"Religious Organization",
            "type":"Services"
        }
    ],
    "sg:phone":"+1 905 383 8315",
    "sg:postcode":"L9A 3S8",
    "sg:province":"ON",
    "sg:tags":[
        "church"
    ],
    "wof:name":"Christian Reformed Church",
    "wof:placetype":"venue"
},
  "geometry": {"coordinates":[-79.878883,43.209278],"type":"Point"}
}