{
  "type": "Feature",
  "properties": {
    "iso:country":"CA",
    "sg:address":"PO Box 1547",
    "sg:city":"Lac LA Biche",
    "sg:classifiers":[
        {
            "category":"Building & Trades",
            "subcategory":"Construction",
            "type":"Services"
        }
    ],
    "sg:phone":"+1 780 623 2378",
    "sg:postcode":"T0A 2C0",
    "sg:province":"AB",
    "sg:tags":[
        "excavating",
        "contractor"
    ],
    "wof:name":"Van-Ross Contracting",
    "wof:placetype":"venue"
},
  "geometry": {"coordinates":[-111.97445678699999,54.77110672],"type":"Point"}
}