{
  "type": "Feature",
  "properties": {
    "addr:full":"95 Royal Crest Crt Markham ON L3R 9X5",
    "addr:housenumber":"95",
    "addr:postcode":"l3r 9x5",
    "addr:street":"Royal Crest Crt",
    "iso:country":"CA",
    "sg:address":"95 Royal Crest Crt",
    "sg:city":"Markham",
    "sg:classifiers":[
        {
            "category":"Building & Trades",
            "subcategory":"Cleaning & Sanitation",
            "type":"Services"
        }
    ],
    "sg:phone":"+1 905 940 5648",
    "sg:postcode":"L3R 9X5",
    "sg:province":"ON",
    "sg:tags":[
        "window"
    ],
    "wof:name":"Real Clean",
    "wof:placetype":"venue"
},
  "geometry": {"coordinates":[-79.3264923096,43.8409233093],"type":"Point"}
}