{
  "type": "Feature",
  "properties": {
    "addr:full":"215 Traders Blvd E # 16 Mississauga ON L4Z 3K5",
    "addr:housenumber":"215",
    "addr:postcode":"l4z 3k5",
    "addr:street":"Traders Blvd E # 16",
    "iso:country":"CA",
    "sg:address":"215 Traders Blvd E # 16",
    "sg:city":"Mississauga",
    "sg:classifiers":[
        {
            "category":"Professional",
            "subcategory":"Computer Services",
            "type":"Services"
        }
    ],
    "sg:phone":"+1 905 502 5660",
    "sg:postcode":"L4Z 3K5",
    "sg:province":"ON",
    "sg:tags":[
        "consultant"
    ],
    "wof:name":"Tsunami Technology Group Inc",
    "wof:placetype":"venue"
},
  "geometry": {"coordinates":[-79.669785,43.627407],"type":"Point"}
}