{
  "type": "Feature",
  "properties": {
    "addr:full":"Calgary AB T2A 0Y1",
    "addr:postcode":"t2a 0y1",
    "iso:country":"CA",
    "sg:city":"Calgary",
    "sg:classifiers":[
        {
            "category":"Professional",
            "subcategory":"Computer Services",
            "type":"Services"
        }
    ],
    "sg:phone":"+1 403 287 8551",
    "sg:postcode":"T2A 0Y1",
    "sg:province":"AB",
    "sg:tags":[
        "repair"
    ],
    "wof:name":"Computer Perfect",
    "wof:placetype":"venue"
},
  "geometry": {"coordinates":[-113.99543,51.042641],"type":"Point"}
}