{
  "type": "Feature",
  "properties": {
    "addr:full":"369 Island Park Dr Ottawa ON K1Y 0B1",
    "addr:housenumber":"369",
    "addr:postcode":"k1y 0b1",
    "addr:street":"Island Park Dr",
    "iso:country":"CA",
    "sg:address":"369 Island Park Dr",
    "sg:city":"Ottawa",
    "sg:classifiers":[
        {
            "category":"Autos & Motor Vehicles",
            "subcategory":"Fuel & Gas Station",
            "type":"Retail Goods"
        }
    ],
    "sg:phone":"+1 613 728 7120",
    "sg:postcode":"K1Y 0B1",
    "sg:province":"ON",
    "sg:tags":[
        "oil"
    ],
    "wof:name":"Island Park Esso Svc Ctr",
    "wof:placetype":"venue"
},
  "geometry": {"coordinates":[-75.742661,45.39753],"type":"Point"}
}