{
  "type": "Feature",
  "properties": {
    "addr:full":"L'Ile-Perrot QC J7V 6X2",
    "addr:postcode":"j7v 6x2",
    "iso:country":"CA",
    "sg:city":"L'Ile-Perrot",
    "sg:classifiers":[
        {
            "category":"Professional",
            "subcategory":"Research",
            "type":"Services"
        }
    ],
    "sg:phone":"+1 514 453 4060",
    "sg:postcode":"J7V 6X2",
    "sg:province":"QC",
    "sg:tags":[
        "consultant",
        "biology",
        "biologist"
    ],
    "wof:name":"E R Thompson & Assoc Inc",
    "wof:placetype":"venue"
},
  "geometry": {"coordinates":[-73.965813,45.390926],"type":"Point"}
}