{
  "type": "Feature",
  "properties": {
    "addr:full":"307 Manitoba Ave Selkirk MB R1A 0Y6",
    "addr:housenumber":"307",
    "addr:postcode":"r1a 0y6",
    "addr:street":"Manitoba Ave",
    "iso:country":"CA",
    "sg:address":"307 Manitoba Ave",
    "sg:city":"Selkirk",
    "sg:classifiers":[
        {
            "category":"Autos & Motor Vehicles",
            "subcategory":"Auto Supplies",
            "type":"Retail Goods"
        }
    ],
    "sg:phone":"+1 204 785 8301",
    "sg:postcode":"R1A 0Y6",
    "sg:province":"MB",
    "sg:tags":[
        "automobile",
        "parts"
    ],
    "wof:name":"Uap Napa Auto Parts",
    "wof:placetype":"venue"
},
  "geometry": {"coordinates":[-96.8728713989,50.1454353333],"type":"Point"}
}