{
  "type": "Feature",
  "properties": {
    "addr:full":"1817 Centre St NW Calgary AB T2E 2S5",
    "addr:housenumber":"1817",
    "addr:postcode":"t2e 2s5",
    "addr:street":"Centre St Nw",
    "iso:country":"CA",
    "sg:address":"1817 Centre St NW",
    "sg:city":"Calgary",
    "sg:classifiers":[
        {
            "category":"Banks & Credit Unions",
            "subcategory":"Investment Brokerage",
            "type":"Services"
        }
    ],
    "sg:phone":"+1 403 230 3483",
    "sg:postcode":"T2E 2S5",
    "sg:province":"AB",
    "wof:name":"Edward Jones",
    "wof:placetype":"venue"
},
  "geometry": {"coordinates":[-114.062737,51.068073],"type":"Point"}
}