{
  "type": "Feature",
  "properties": {
    "addr:full":"171 Boul Saint-Luc Saint-Luc QC J2W 2G7",
    "addr:housenumber":"171",
    "addr:postcode":"j2w 2g7",
    "addr:street":"Boul Saint-Luc",
    "iso:country":"CA",
    "sg:address":"171 Boul Saint-Luc",
    "sg:city":"Saint-Luc",
    "sg:classifiers":[
        {
            "category":"Building & Trades",
            "subcategory":"Plumbing",
            "type":"Services"
        }
    ],
    "sg:phone":"+1 450 349 2436",
    "sg:postcode":"J2W 2G7",
    "sg:province":"QC",
    "sg:tags":[
        "contractor"
    ],
    "wof:name":"Plomberie Ac Enr",
    "wof:placetype":"venue"
},
  "geometry": {"coordinates":[-73.2819900513,45.3413238525],"type":"Point"}
}