{
  "type": "Feature",
  "properties": {
    "addr:full":"Coquitlam BC V3E 1J7",
    "addr:postcode":"v3e 1j7",
    "iso:country":"CA",
    "sg:city":"Coquitlam",
    "sg:classifiers":[
        {
            "category":"Health Services",
            "subcategory":"Doctor",
            "type":"Services"
        }
    ],
    "sg:phone":"+1 604 552 1018",
    "sg:postcode":"V3E 1J7",
    "sg:province":"BC",
    "sg:tags":[
        "dentist"
    ],
    "wof:name":"Gleneagle Dental Ctr",
    "wof:placetype":"venue"
},
  "geometry": {"coordinates":[-122.80947876,49.283706665],"type":"Point"}
}