{
  "type": "Feature",
  "properties": {
    "addr:full":"329 Reid St Peterborough ON K9H 4G3",
    "addr:housenumber":"329",
    "addr:postcode":"k9h 4g3",
    "addr:street":"Reid St",
    "iso:country":"CA",
    "sg:address":"329 Reid St",
    "sg:city":"Peterborough",
    "sg:classifiers":[
        {
            "category":"Banks & Credit Unions",
            "subcategory":"Bank",
            "type":"Services"
        }
    ],
    "sg:phone":"+1 705 745 7334",
    "sg:postcode":"K9H 4G3",
    "sg:province":"ON",
    "sg:tags":[
        "loan",
        "real estate"
    ],
    "wof:name":"Mortgage Plus",
    "wof:placetype":"venue"
},
  "geometry": {"coordinates":[-78.3279266357,44.3032531738],"type":"Point"}
}