{
  "type": "Feature",
  "properties": {
    "addr:full":"57 Ontario St S Grand Bend ON N0M 1T0",
    "addr:housenumber":"57",
    "addr:postcode":"n0m 1t0",
    "addr:street":"Ontario St S",
    "iso:country":"CA",
    "sg:address":"57 Ontario St S",
    "sg:city":"Grand Bend",
    "sg:classifiers":[
        {
            "category":"Home & Garden",
            "subcategory":"Hardware",
            "type":"Retail Goods"
        }
    ],
    "sg:phone":"+1 519 238 5500",
    "sg:postcode":"N0M 1T0",
    "sg:province":"ON",
    "wof:name":"Pineland Pro Hardware",
    "wof:placetype":"venue"
},
  "geometry": {"coordinates":[-81.75982666020001,43.3087463379],"type":"Point"}
}