{
  "type": "Feature",
  "properties": {
    "addr:full":"241 Carnegie St Campbell River BC V9W 2J4",
    "addr:housenumber":"241",
    "addr:postcode":"v9w 2j4",
    "addr:street":"Carnegie St",
    "iso:country":"CA",
    "sg:address":"241 Carnegie St",
    "sg:city":"Campbell River",
    "sg:classifiers":[
        {
            "category":"Personal",
            "subcategory":"Beauty Salon",
            "type":"Services"
        }
    ],
    "sg:phone":"+1 250 286 3069",
    "sg:postcode":"V9W 2J4",
    "sg:province":"BC",
    "wof:name":"Venus Hair Boutique",
    "wof:placetype":"venue"
},
  "geometry": {"coordinates":[-125.233757,50.002953],"type":"Point"}
}