{
  "type": "Feature",
  "properties": {
    "addr:full":"Hanna AB T0J 1P0",
    "addr:postcode":"t0j 1p0",
    "iso:country":"CA",
    "sg:city":"Hanna",
    "sg:classifiers":[
        {
            "category":"Restaurant",
            "type":"Food & Drink"
        }
    ],
    "sg:phone":"+1 403 854 3144",
    "sg:postcode":"T0J 1P0",
    "sg:province":"AB",
    "wof:name":"York Restaurant",
    "wof:placetype":"venue"
},
  "geometry": {"coordinates":[-111.928291,51.643398],"type":"Point"}
}