{
  "type": "Feature",
  "properties": {
    "iso:country":"CA",
    "sg:address":"12 Blair Rd",
    "sg:city":"Cambridge",
    "sg:classifiers":[
        {
            "category":"Organizations",
            "subcategory":"Religious Organization",
            "type":"Services"
        }
    ],
    "sg:phone":"+1 519 621 8860",
    "sg:postcode":"N1S 2H5",
    "sg:province":"ON",
    "sg:tags":[
        "church"
    ],
    "wof:name":"Trinity Anglican Church",
    "wof:placetype":"venue"
},
  "geometry": {"coordinates":[-80.31732177729999,43.3609085083],"type":"Point"}
}