{
  "type": "Feature",
  "properties": {
    "addr:full":"2223 Rue Saint-Adrien Jonquiere QC G7S 4A8",
    "addr:housenumber":"2223",
    "addr:postcode":"g7s 4a8",
    "addr:street":"Rue Saint-Adrien",
    "iso:country":"CA",
    "sg:address":"2223 Rue Saint-Adrien",
    "sg:city":"Jonquiere",
    "sg:classifiers":[
        {
            "category":"Manufacturing",
            "subcategory":"Lumber",
            "type":"Manufacturing & Wholesale Goods"
        }
    ],
    "sg:phone":"+1 418 548 4040",
    "sg:postcode":"G7S 4A8",
    "sg:province":"QC",
    "sg:tags":[
        "forester"
    ],
    "wof:name":"Plantations D'Arbres Mm Inc",
    "wof:placetype":"venue"
},
  "geometry": {"coordinates":[-71.14070100000001,48.436195],"type":"Point"}
}