{
  "type": "Feature",
  "properties": {
    "addr:full":"Humphrey Rd Labrador City NL A2V 2K7",
    "addr:postcode":"a2v 2k7",
    "addr:street":"Humphrey Rd",
    "iso:country":"CA",
    "sg:address":"Humphrey Rd",
    "sg:city":"Labrador City",
    "sg:classifiers":[
        {
            "category":"Building & Trades",
            "subcategory":"Construction",
            "type":"Services"
        }
    ],
    "sg:phone":"+1 709 944 2995",
    "sg:postcode":"A2V 2K7",
    "sg:province":"NL",
    "sg:tags":[
        "general",
        "contractor"
    ],
    "wof:name":"Rsm Mining Svc Inc",
    "wof:placetype":"venue"
},
  "geometry": {"coordinates":[-66.894363,52.944324],"type":"Point"}
}