{
  "type": "Feature",
  "properties": {
    "addr:full":"Chilliwack BC V2R 1A1",
    "addr:postcode":"v2r 1a1",
    "iso:country":"CA",
    "sg:city":"Chilliwack",
    "sg:classifiers":[
        {
            "category":"Shopping",
            "subcategory":"Gifts & Souvenirs",
            "type":"Retail Goods"
        }
    ],
    "sg:phone":"+1 604 858 5131",
    "sg:postcode":"V2R 1A1",
    "sg:province":"BC",
    "sg:tags":[
        "cards",
        "greeting"
    ],
    "wof:name":"Carlton Card Shop",
    "wof:placetype":"venue"
},
  "geometry": {"coordinates":[-121.961967468,49.1408920288],"type":"Point"}
}