{
  "type": "Feature",
  "properties": {
    "addr:full":"Calgary AB T2G 4C9",
    "addr:postcode":"t2g 4c9",
    "iso:country":"CA",
    "sg:city":"Calgary",
    "sg:classifiers":[
        {
            "category":"Manufacturing",
            "subcategory":"Printing",
            "type":"Manufacturing & Wholesale Goods"
        }
    ],
    "sg:phone":"+1 403 287 1007",
    "sg:postcode":"T2G 4C9",
    "sg:province":"AB",
    "sg:tags":[
        "printer"
    ],
    "wof:name":"Anchor Printing & Graphics Inc",
    "wof:placetype":"venue"
},
  "geometry": {"coordinates":[-114.032867432,51.0131912231],"type":"Point"}
}