{
  "type": "Feature",
  "properties": {
    "iso:country":"CA",
    "sg:address":"84 Mount Bernard Ave",
    "sg:city":"Corner Brook",
    "sg:classifiers":[
        {
            "category":"Government",
            "subcategory":"Office",
            "type":"Public Place"
        }
    ],
    "sg:phone":"+1 709 637 2497",
    "sg:postcode":"A2H 5G2",
    "sg:province":"NL",
    "wof:name":"Motor Vehicle Registration",
    "wof:placetype":"venue"
},
  "geometry": {"coordinates":[-57.9431190491,48.9443321228],"type":"Point"}
}