{
  "type": "Feature",
  "properties": {
    "addr:full":"893 Bayly St Pickering ON L1W 3P6",
    "addr:housenumber":"893",
    "addr:postcode":"l1w 3p6",
    "addr:street":"Bayly St",
    "iso:country":"CA",
    "sg:address":"893 Bayly St",
    "sg:city":"Pickering",
    "sg:classifiers":[
        {
            "category":"Manufacturing",
            "subcategory":"Food",
            "type":"Manufacturing & Wholesale Goods"
        }
    ],
    "sg:phone":"+1 905 420 7517",
    "sg:postcode":"L1W 3P6",
    "sg:province":"ON",
    "sg:tags":[
        "baker",
        "cookie",
        "bakery"
    ],
    "wof:name":"Breadhouse Bakery",
    "wof:placetype":"venue"
},
  "geometry": {"coordinates":[-79.10739898680001,43.8201141357],"type":"Point"}
}