{
  "type": "Feature",
  "properties": {
    "addr:full":"36 Discovery Ridge Cres SW Calgary AB T3H 4R4",
    "addr:housenumber":"36",
    "addr:postcode":"t3h 4r4",
    "addr:street":"Discovery Ridge Cres Sw",
    "iso:country":"CA",
    "sg:address":"36 Discovery Ridge Cres SW",
    "sg:city":"Calgary",
    "sg:classifiers":[
        {
            "category":"Professional",
            "subcategory":"Computer Services",
            "type":"Services"
        }
    ],
    "sg:phone":"+1 403 281 8701",
    "sg:postcode":"T3H 4R4",
    "sg:province":"AB",
    "wof:name":"Stealth Network Svc",
    "wof:placetype":"venue"
},
  "geometry": {"coordinates":[-114.20246899999999,51.014046],"type":"Point"}
}