{
  "type": "Feature",
  "properties": {
    "addr:full":"73 Stafford Dr Brampton ON L6W 1L3",
    "addr:housenumber":"73",
    "addr:postcode":"l6w 1l3",
    "addr:street":"Stafford Dr",
    "iso:country":"CA",
    "sg:address":"73 Stafford Dr",
    "sg:city":"Brampton",
    "sg:classifiers":[
        {
            "category":"Retail",
            "subcategory":"Auto Repair",
            "type":"Services"
        }
    ],
    "sg:phone":"+1 905 459 9679",
    "sg:postcode":"L6W 1L3",
    "sg:province":"ON",
    "sg:tags":[
        "repairing",
        "automobile"
    ],
    "wof:name":"Morrison Automotive",
    "wof:placetype":"venue"
},
  "geometry": {"coordinates":[-79.7340164185,43.6874427795],"type":"Point"}
}