{
  "type": "Feature",
  "properties": {
    "addr:full":"2180 Robie St Halifax NS B3K 4M6",
    "addr:housenumber":"2180",
    "addr:postcode":"b3k 4m6",
    "addr:street":"Robie St",
    "iso:country":"CA",
    "sg:address":"2180 Robie St",
    "sg:city":"Halifax",
    "sg:classifiers":[
        {
            "category":"Food & Beverages",
            "subcategory":"Groceries & Convenience Stores",
            "type":"Retail Goods"
        }
    ],
    "sg:phone":"+1 902 422 1529",
    "sg:postcode":"B3K 4M6",
    "sg:province":"NS",
    "sg:tags":[
        "grocer"
    ],
    "wof:name":"Tony's Variety",
    "wof:placetype":"venue"
},
  "geometry": {"coordinates":[-63.5923156738,44.6503105164],"type":"Point"}
}