{
  "type": "Feature",
  "properties": {
    "addr:full":"2112 Lakeview Rd Cambridge-Narrows NB E4C 1N6",
    "addr:housenumber":"2112",
    "addr:postcode":"e4c 1n6",
    "addr:street":"Lakeview Rd",
    "iso:country":"CA",
    "sg:address":"2112 Lakeview Rd",
    "sg:city":"Cambridge-Narrows",
    "sg:classifiers":[
        {
            "category":"Health Services",
            "subcategory":"Doctor",
            "type":"Services"
        }
    ],
    "sg:phone":"+1 506 488 2240",
    "sg:postcode":"E4C 1N6",
    "sg:province":"NB",
    "sg:tags":[
        "clinic"
    ],
    "wof:name":"Cambridge Narrows Medical Clnc",
    "wof:placetype":"venue"
},
  "geometry": {"coordinates":[-65.95546,45.830135],"type":"Point"}
}