{
  "type": "Feature",
  "properties": {
    "addr:full":"405 Queen St E Sault Ste Marie ON P6A 1Z5",
    "addr:housenumber":"405",
    "addr:postcode":"p6a 1z5",
    "addr:street":"Queen St E",
    "iso:country":"CA",
    "sg:address":"405 Queen St E",
    "sg:city":"Sault Ste Marie",
    "sg:classifiers":[
        {
            "category":"Manufacturing",
            "subcategory":"Metals",
            "type":"Manufacturing & Wholesale Goods"
        }
    ],
    "sg:phone":"+1 705 949 8661",
    "sg:postcode":"P6A 1Z5",
    "sg:province":"ON",
    "sg:tags":[
        "steel",
        "mills",
        "engineer"
    ],
    "wof:name":"Danieli-Corus Canada Inc",
    "wof:placetype":"venue"
},
  "geometry": {"coordinates":[-84.3336257935,46.511882782],"type":"Point"}
}