{
  "type": "Feature",
  "properties": {
    "addr:full":"Foot of Gore Ave Vancouver BC V6A 2Y7",
    "addr:postcode":"v6a 2y7",
    "addr:street":"Ave",
    "iso:country":"CA",
    "sg:address":"Foot of Gore Ave",
    "sg:city":"Vancouver",
    "sg:classifiers":[
        {
            "category":"Manufacturing",
            "subcategory":"Food",
            "type":"Manufacturing & Wholesale Goods"
        }
    ],
    "sg:phone":"+1 604 681 0211",
    "sg:postcode":"V6A 2Y7",
    "sg:province":"BC",
    "sg:tags":[
        "packer",
        "seafood",
        "fish",
        "product",
        "prepared"
    ],
    "wof:name":"Canadian Fishing CO",
    "wof:placetype":"venue"
},
  "geometry": {"coordinates":[-123.11403656,49.2604408264],"type":"Point"}
}