{
  "type": "Feature",
  "properties": {
    "addr:full":"4911 52 Ave Stony Plain AB T7Z 1C4",
    "addr:housenumber":"4911",
    "addr:postcode":"t7z 1c4",
    "addr:street":"52 Ave",
    "iso:country":"CA",
    "sg:address":"4911 52 Ave",
    "sg:city":"Stony Plain",
    "sg:classifiers":[
        {
            "category":"Restaurant",
            "type":"Food & Drink"
        }
    ],
    "sg:phone":"+1 780 963 0120",
    "sg:postcode":"T7Z 1C4",
    "sg:province":"AB",
    "wof:name":"Early Stage Saloon",
    "wof:placetype":"venue"
},
  "geometry": {"coordinates":[-114.004440308,53.528049469],"type":"Point"}
}