{
  "type": "Feature",
  "properties": {
    "addr:full":"109 Victoria St W Kensington PE C0B 1M0",
    "addr:housenumber":"109",
    "addr:postcode":"c0b 1m0",
    "addr:street":"Victoria St W",
    "iso:country":"CA",
    "sg:address":"109 Victoria St W",
    "sg:city":"Kensington",
    "sg:classifiers":[
        {
            "category":"Restaurant",
            "type":"Food & Drink"
        }
    ],
    "sg:phone":"+1 902 836 3000",
    "sg:postcode":"C0B 1M0",
    "sg:province":"PE",
    "wof:name":"Frosty Treat Dairy Bar",
    "wof:placetype":"venue"
},
  "geometry": {"coordinates":[-63.641415,46.435284],"type":"Point"}
}