{
  "type": "Feature",
  "properties": {
    "addr:full":"5000 3E Av O # 202 Charlesbourg QC G1H 7J1",
    "addr:housenumber":"5000",
    "addr:postcode":"g1h 7j1",
    "addr:street":"3E Av O # 202",
    "iso:country":"CA",
    "sg:address":"5000 3E Av O # 202",
    "sg:city":"Charlesbourg",
    "sg:classifiers":[
        {
            "category":"Social Services",
            "type":"Services"
        }
    ],
    "sg:phone":"+1 418 623 4636",
    "sg:postcode":"G1H 7J1",
    "sg:province":"QC",
    "sg:tags":[
        "organization",
        "welfare"
    ],
    "wof:name":"Cercle Polaire",
    "wof:placetype":"venue"
},
  "geometry": {"coordinates":[-71.250114,46.848171],"type":"Point"}
}