{
  "type": "Feature",
  "properties": {
    "addr:full":"Haliburton ON K0M 1S0",
    "addr:postcode":"k0m 1s0",
    "iso:country":"CA",
    "sg:city":"Haliburton",
    "sg:classifiers":[
        {
            "category":"Health Services",
            "subcategory":"Doctor",
            "type":"Services"
        }
    ],
    "sg:phone":"+1 705 457 1212",
    "sg:postcode":"K0M 1S0",
    "sg:province":"ON",
    "sg:tags":[
        "physician",
        "surgeon"
    ],
    "wof:name":"Conway, A MD",
    "wof:placetype":"venue"
},
  "geometry": {"coordinates":[-78.510628,45.046513],"type":"Point"}
}