{
  "type": "Feature",
  "properties": {
    "addr:full":"153 138 Rte Baie-Comeau QC G4Z 2L6",
    "addr:housenumber":"138",
    "addr:postcode":"g4z 2l6",
    "addr:street":"Rte Baie-Comeau",
    "iso:country":"CA",
    "sg:address":"153 138 Rte",
    "sg:city":"Baie-Comeau",
    "sg:classifiers":[
        {
            "category":"Manufacturing",
            "subcategory":"Rubber & Plastics",
            "type":"Manufacturing & Wholesale Goods"
        }
    ],
    "sg:phone":"+1 418 296 2133",
    "sg:postcode":"G4Z 2L6",
    "sg:province":"QC",
    "sg:tags":[
        "container"
    ],
    "wof:name":"Roland Munger Inc",
    "wof:placetype":"venue"
},
  "geometry": {"coordinates":[-68.190201,49.228439],"type":"Point"}
}