{
  "type": "Feature",
  "properties": {
    "addr:full":"761 Brant St # 205 Burlington ON L7R 2H7",
    "addr:housenumber":"761",
    "addr:postcode":"l7r 2h7",
    "addr:street":"Brant St # 205",
    "iso:country":"CA",
    "sg:address":"761 Brant St # 205",
    "sg:city":"Burlington",
    "sg:classifiers":[
        {
            "category":"Social Services",
            "type":"Services"
        }
    ],
    "sg:phone":"+1 905 639 8141",
    "sg:postcode":"L7R 2H7",
    "sg:province":"ON",
    "sg:tags":[
        "counselor",
        "marriage",
        "family"
    ],
    "wof:name":"Walker, Dennis J",
    "wof:placetype":"venue"
},
  "geometry": {"coordinates":[-79.80838012700001,43.3331069946],"type":"Point"}
}