{
  "type": "Feature",
  "properties": {
    "addr:full":"24 Goldenrod Cove Winnipeg MB R2J 3Z8",
    "addr:housenumber":"24",
    "addr:postcode":"r2j 3z8",
    "addr:street":"Goldenrod Cove",
    "iso:country":"CA",
    "sg:address":"24 Goldenrod Cove",
    "sg:city":"Winnipeg",
    "sg:classifiers":[
        {
            "category":"Building & Trades",
            "subcategory":"Construction",
            "type":"Services"
        }
    ],
    "sg:phone":"+1 204 255 1004",
    "sg:postcode":"R2J 3Z8",
    "sg:province":"MB",
    "sg:tags":[
        "masonry",
        "contractor"
    ],
    "wof:name":"Mrb Masonry Ltd",
    "wof:placetype":"venue"
},
  "geometry": {"coordinates":[-97.04787399999999,49.849545],"type":"Point"}
}