{
  "type": "Feature",
  "properties": {
    "addr:full":"1759 Rue Grenet Saint-Laurent QC H4L 2R6",
    "addr:housenumber":"1759",
    "addr:postcode":"h4l 2r6",
    "addr:street":"Rue Grenet",
    "iso:country":"CA",
    "sg:address":"1759 Rue Grenet",
    "sg:city":"Saint-Laurent",
    "sg:classifiers":[
        {
            "category":"Retail",
            "subcategory":"Car Wash",
            "type":"Services"
        }
    ],
    "sg:phone":"+1 514 748 7666",
    "sg:postcode":"H4L 2R6",
    "sg:province":"QC",
    "sg:tags":[
        "polishing",
        "washing"
    ],
    "wof:name":"Car Care",
    "wof:placetype":"venue"
},
  "geometry": {"coordinates":[-73.6972808838,45.5181427002],"type":"Point"}
}