{
  "type": "Feature",
  "properties": {
    "iso:country":"CA",
    "sg:address":"3333 Rue DE Rouen",
    "sg:city":"Montreal",
    "sg:classifiers":[
        {
            "category":"Retail",
            "subcategory":"Auto Repair",
            "type":"Services"
        }
    ],
    "sg:phone":"+1 514 526 4383",
    "sg:postcode":"H1W 1L4",
    "sg:province":"QC",
    "sg:tags":[
        "repairing",
        "automobile"
    ],
    "wof:name":"R & R Svc Station",
    "wof:placetype":"venue"
},
  "geometry": {"coordinates":[-73.5500030518,45.5436897278],"type":"Point"}
}