{
  "type": "Feature",
  "properties": {
    "addr:full":"76 Mary St Barrie ON L4N 1T1",
    "addr:housenumber":"76",
    "addr:postcode":"l4n 1t1",
    "addr:street":"Mary St",
    "iso:country":"CA",
    "sg:address":"76 Mary St",
    "sg:city":"Barrie",
    "sg:classifiers":[
        {
            "category":"Real Estate",
            "subcategory":"Architect",
            "type":"Services"
        }
    ],
    "sg:phone":"+1 705 734 3580",
    "sg:postcode":"L4N 1T1",
    "sg:province":"ON",
    "wof:name":"Ted Handy & Assoc",
    "wof:placetype":"venue"
},
  "geometry": {"coordinates":[-79.6936721802,44.3895874023],"type":"Point"}
}