{
  "type": "Feature",
  "properties": {
    "addr:full":"Wynyard SK S0A 4T0",
    "addr:postcode":"s0a 4t0",
    "addr:street":"Wynyard",
    "iso:country":"CA",
    "sg:city":"Wynyard",
    "sg:classifiers":[
        {
            "category":"Education",
            "subcategory":"School",
            "type":"Public Place"
        }
    ],
    "sg:phone":"+1 306 554 3767",
    "sg:postcode":"S0A 4T0",
    "sg:province":"SK",
    "wof:name":"Carlton Trail Regional College",
    "wof:placetype":"venue"
},
  "geometry": {"coordinates":[-104.180091858,51.7652015686],"type":"Point"}
}