{
  "type": "Feature",
  "properties": {
    "addr:full":"Toronto ON M4P 2H7",
    "addr:postcode":"m4p 2h7",
    "iso:country":"CA",
    "sg:city":"Toronto",
    "sg:classifiers":[
        {
            "category":"Professional",
            "subcategory":"Business Services",
            "type":"Services"
        }
    ],
    "sg:phone":"+1 416 440 4060",
    "sg:postcode":"M4P 2H7",
    "sg:province":"ON",
    "sg:tags":[
        "interior",
        "consultant",
        "design",
        "decorator"
    ],
    "wof:name":"Sweeney Dale Interior Design",
    "wof:placetype":"venue"
},
  "geometry": {"coordinates":[-79.39960499999999,43.712208],"type":"Point"}
}