{
  "type": "Feature",
  "properties": {
    "addr:full":"PO Box 1361 STN Main Lethbridge AB T1J 4K1",
    "addr:housenumber":"po",
    "addr:postcode":"t1j 4k1",
    "addr:street":"Box 1361 Stn Main",
    "iso:country":"CA",
    "sg:address":"PO Box 1361 STN Main",
    "sg:city":"Lethbridge",
    "sg:classifiers":[
        {
            "category":"Home & Garden",
            "subcategory":"Carpets & Floor Coverings",
            "type":"Retail Goods"
        }
    ],
    "sg:phone":"+1 403 327 9673",
    "sg:postcode":"T1J 4K1",
    "sg:province":"AB",
    "sg:tags":[
        "resurfacing",
        "material",
        "refinishing"
    ],
    "wof:name":"Maple Ridge Floors",
    "wof:placetype":"venue"
},
  "geometry": {"coordinates":[-112.83374000000001,49.693836],"type":"Point"}
}