{
  "type": "Feature",
  "properties": {
    "iso:country":"CA",
    "sg:address":"2044 Av Chartier",
    "sg:city":"Dorval",
    "sg:classifiers":[
        {
            "category":"Restaurant",
            "type":"Food & Drink"
        }
    ],
    "sg:phone":"+1 514 631 1681",
    "sg:postcode":"H9P 1H2",
    "sg:province":"QC",
    "wof:name":"55 Restaurant",
    "wof:placetype":"venue"
},
  "geometry": {"coordinates":[-73.7251663208,45.4631233215],"type":"Point"}
}