{
  "type": "Feature",
  "properties": {
    "addr:full":"550 Boul Pere-Lelievre Vanier QC G1M 3R2",
    "addr:housenumber":"550",
    "addr:postcode":"g1m 3r2",
    "addr:street":"Boul Pere-Lelievre",
    "iso:country":"CA",
    "sg:address":"550 Boul Pere-Lelievre",
    "sg:city":"Vanier",
    "sg:classifiers":[
        {
            "category":"Government",
            "subcategory":"Office",
            "type":"Public Place"
        }
    ],
    "sg:phone":"+1 418 646 1950",
    "sg:postcode":"G1M 3R2",
    "sg:province":"QC",
    "wof:name":"Quebec Ministere DE L'Emploi",
    "wof:placetype":"venue"
},
  "geometry": {"coordinates":[-71.272301,46.81369],"type":"Point"}
}