{
  "type": "Feature",
  "properties": {
    "addr:full":"193 Rang DE L'Eglise Saint-Liguori QC J0K 2X0",
    "addr:housenumber":"193",
    "addr:postcode":"j0k 2x0",
    "addr:street":"Rang De L'Eglise",
    "iso:country":"CA",
    "sg:address":"193 Rang DE L'Eglise",
    "sg:city":"Saint-Liguori",
    "sg:classifiers":[
        {
            "category":"Autos & Motor Vehicles",
            "subcategory":"Auto Supplies",
            "type":"Retail Goods"
        }
    ],
    "sg:phone":"+1 450 754 4222",
    "sg:postcode":"J0K 2X0",
    "sg:province":"QC",
    "sg:tags":[
        "filter",
        "gas"
    ],
    "wof:name":"Filtration Lab",
    "wof:placetype":"venue"
},
  "geometry": {"coordinates":[-73.8513259888,45.9491424561],"type":"Point"}
}