{
  "type": "Feature",
  "properties": {
    "addr:full":"174 Spadina Ave # 410 Toronto ON M5T 2C2",
    "addr:housenumber":"174",
    "addr:postcode":"m5t 2c2",
    "addr:street":"Spadina Ave # 410",
    "iso:country":"CA",
    "sg:address":"174 Spadina Ave # 410",
    "sg:city":"Toronto",
    "sg:classifiers":[
        {
            "category":"Professional",
            "subcategory":"Business Services",
            "type":"Services"
        }
    ],
    "sg:phone":"+1 416 703 8507",
    "sg:postcode":"M5T 2C2",
    "sg:province":"ON",
    "sg:tags":[
        "embroidery"
    ],
    "wof:name":"Sai Embroidery",
    "wof:placetype":"venue"
},
  "geometry": {"coordinates":[-79.3968429565,43.6491394043],"type":"Point"}
}