{
  "type": "Feature",
  "properties": {
    "addr:full":"305 Gloucester Ave Oakville ON L6J 3W8",
    "addr:housenumber":"305",
    "addr:postcode":"l6j 3w8",
    "addr:street":"Gloucester Ave",
    "iso:country":"CA",
    "sg:address":"305 Gloucester Ave",
    "sg:city":"Oakville",
    "sg:classifiers":[
        {
            "category":"Building & Trades",
            "subcategory":"Construction",
            "type":"Services"
        }
    ],
    "sg:phone":"+1 905 844 2092",
    "sg:postcode":"L6J 3W8",
    "sg:province":"ON",
    "sg:tags":[
        "painter"
    ],
    "wof:name":"Johnson & Law",
    "wof:placetype":"venue"
},
  "geometry": {"coordinates":[-79.669044,43.456306],"type":"Point"}
}