{
  "type": "Feature",
  "properties": {
    "iso:country":"CA",
    "sg:address":"2943 Major Mackenzie Dr # 3",
    "sg:city":"Maple",
    "sg:classifiers":[
        {
            "category":"Shopping",
            "subcategory":"Florist",
            "type":"Retail Goods"
        }
    ],
    "sg:phone":"+1 905 417 9866",
    "sg:postcode":"L6A 3N9",
    "sg:province":"ON",
    "wof:name":"Jennifer's Flowers & Gifts",
    "wof:placetype":"venue"
},
  "geometry": {"coordinates":[-79.5342330933,43.8501319885],"type":"Point"}
}