{
  "type": "Feature",
  "properties": {
    "iso:country":"CA",
    "sg:address":"1110 8th St W",
    "sg:city":"Nipawin",
    "sg:classifiers":[
        {
            "category":"Wholesale",
            "subcategory":"Machinery & Supplies",
            "type":"Manufacturing & Wholesale Goods"
        }
    ],
    "sg:phone":"+1 306 862 9858",
    "sg:postcode":"S0E 1E0",
    "sg:province":"SK",
    "sg:tags":[
        "forestry",
        "bearing",
        "timber"
    ],
    "wof:name":"Aim Supply Ltd",
    "wof:placetype":"venue"
},
  "geometry": {"coordinates":[-104.026611328,53.3531494141],"type":"Point"}
}