{
  "type": "Feature",
  "properties": {
    "addr:full":"Woodbridge ON L4L 4Y4",
    "addr:postcode":"l4l 4y4",
    "iso:country":"CA",
    "sg:city":"Woodbridge",
    "sg:classifiers":[
        {
            "category":"Professional",
            "subcategory":"Art Services",
            "type":"Services"
        }
    ],
    "sg:phone":"+1 905 850 8656",
    "sg:postcode":"L4L 4Y4",
    "sg:province":"ON",
    "sg:tags":[
        "photographer"
    ],
    "wof:name":"Castlerock Studios Inc",
    "wof:placetype":"venue"
},
  "geometry": {"coordinates":[-79.5634765625,43.7669639587],"type":"Point"}
}