{
  "type": "Feature",
  "properties": {
    "addr:full":"283 Rue DE LA Voliere Sainte-Anne-Des-Plaines QC J0N 1H0",
    "addr:housenumber":"283",
    "addr:postcode":"j0n 1h0",
    "addr:street":"Rue De La Voliere",
    "iso:country":"CA",
    "sg:address":"283 Rue DE LA Voliere",
    "sg:city":"Sainte-Anne-Des-Plaines",
    "sg:classifiers":[
        {
            "category":"Personal",
            "subcategory":"Beauty Salon",
            "type":"Services"
        }
    ],
    "sg:phone":"+1 450 478 6287",
    "sg:postcode":"J0N 1H0",
    "sg:province":"QC",
    "wof:name":"Coiffure Sylvie Enr",
    "wof:placetype":"venue"
},
  "geometry": {"coordinates":[-73.79964447019999,45.7662506104],"type":"Point"}
}