{
  "type": "Feature",
  "properties": {
    "iso:country":"CA",
    "sg:city":"Melfort",
    "sg:classifiers":[
        {
            "category":"Government",
            "subcategory":"Office",
            "type":"Public Place"
        }
    ],
    "sg:phone":"+1 306 752 6615",
    "sg:postcode":"S0E 1A0",
    "sg:province":"SK",
    "wof:name":"SK Human Resource Ctr",
    "wof:placetype":"venue"
},
  "geometry": {"coordinates":[-104.61795044,52.861366272],"type":"Point"}
}