{
  "type": "Feature",
  "properties": {
    "addr:full":"Moncton NB E1C 4X5",
    "addr:postcode":"e1c 4x5",
    "iso:country":"CA",
    "sg:city":"Moncton",
    "sg:classifiers":[
        {
            "category":"Shopping",
            "type":"Retail Goods"
        }
    ],
    "sg:phone":"+1 506 854 5381",
    "sg:postcode":"E1C 4X5",
    "sg:province":"NB",
    "sg:tags":[
        "art",
        "gallery",
        "dealer"
    ],
    "wof:name":"Galerie Sans Nom CO-OP Ltee",
    "wof:placetype":"venue"
},
  "geometry": {"coordinates":[-64.77755000000001,46.092472],"type":"Point"}
}