{
  "type": "Feature",
  "properties": {
    "addr:full":"18 Garfield St Charlottetown PE C1A 6A5",
    "addr:housenumber":"18",
    "addr:postcode":"c1a 6a5",
    "addr:street":"Garfield St",
    "iso:country":"CA",
    "sg:address":"18 Garfield St",
    "sg:city":"Charlottetown",
    "sg:classifiers":[
        {
            "category":"Personal",
            "subcategory":"Beauty Salon",
            "type":"Services"
        }
    ],
    "sg:phone":"+1 902 566 2679",
    "sg:postcode":"C1A 6A5",
    "sg:province":"PE",
    "wof:name":"Mane Connection",
    "wof:placetype":"venue"
},
  "geometry": {"coordinates":[-63.112347,46.252518],"type":"Point"}
}