{
  "type": "Feature",
  "properties": {
    "addr:full":"43830 South Sumas Rd Chilliwack BC V2R 4L6",
    "addr:housenumber":"43830",
    "addr:postcode":"v2r 4l6",
    "addr:street":"South Sumas Rd",
    "iso:country":"CA",
    "sg:address":"43830 South Sumas Rd",
    "sg:city":"Chilliwack",
    "sg:classifiers":[
        {
            "category":"Farming",
            "subcategory":"Nursery",
            "type":"Manufacturing & Wholesale Goods"
        }
    ],
    "sg:phone":"+1 604 858 8100",
    "sg:postcode":"V2R 4L6",
    "sg:province":"BC",
    "sg:tags":[
        "greenhouse"
    ],
    "wof:name":"Rainbow Greenhouses",
    "wof:placetype":"venue"
},
  "geometry": {"coordinates":[-122.013412,49.118229],"type":"Point"}
}