{
  "type": "Feature",
  "properties": {
    "addr:full":"2081 Merivale Rd Nepean ON K2G 1G9",
    "addr:housenumber":"2081",
    "addr:postcode":"k2g 1g9",
    "addr:street":"Merivale Rd",
    "iso:country":"CA",
    "sg:address":"2081 Merivale Rd",
    "sg:city":"Nepean",
    "sg:classifiers":[
        {
            "category":"Museum",
            "type":"Entertainment"
        }
    ],
    "sg:phone":"+1 613 224 8189",
    "sg:postcode":"K2G 1G9",
    "sg:province":"ON",
    "sg:tags":[
        "organization",
        "arts",
        "information"
    ],
    "wof:name":"Inuit Art Foundation",
    "wof:placetype":"venue"
},
  "geometry": {"coordinates":[-75.714607,45.318481],"type":"Point"}
}