{
  "type": "Feature",
  "properties": {
    "addr:full":"1329 Rosser Ave E Brandon MB R7A 7J2",
    "addr:housenumber":"1329",
    "addr:postcode":"r7a 7j2",
    "addr:street":"Rosser Ave E",
    "iso:country":"CA",
    "sg:address":"1329 Rosser Ave E",
    "sg:city":"Brandon",
    "sg:classifiers":[
        {
            "category":"Farming",
            "subcategory":"Nursery",
            "type":"Manufacturing & Wholesale Goods"
        }
    ],
    "sg:phone":"+1 204 727 5884",
    "sg:postcode":"R7A 7J2",
    "sg:province":"MB",
    "sg:tags":[
        "center",
        "greenhouse",
        "garden"
    ],
    "wof:name":"Green Spot",
    "wof:placetype":"venue"
},
  "geometry": {"coordinates":[-99.9560012817,49.8486061096],"type":"Point"}
}