{
  "type": "Feature",
  "properties": {
    "addr:full":"Hwy 11 Atikokan ON P0T 1C0",
    "addr:postcode":"p0t 1c0",
    "addr:street":"Hwy 11 Atikokan",
    "iso:country":"CA",
    "sg:address":"Hwy 11",
    "sg:city":"Atikokan",
    "sg:classifiers":[
        {
            "category":"Travel",
            "subcategory":"Campground",
            "type":"Entertainment"
        }
    ],
    "sg:phone":"+1 807 929 3561",
    "sg:postcode":"P0T 1C0",
    "sg:province":"ON",
    "sg:tags":[
        "outfitter",
        "canoe",
        "trip",
        "camp"
    ],
    "wof:name":"Quetico North",
    "wof:placetype":"venue"
},
  "geometry": {"coordinates":[-91.7286224365,48.7368545532],"type":"Point"}
}