{
  "type": "Feature",
  "properties": {
    "addr:full":"8369 Peggys Cove Rd Indian Harbour NS B3Z 3R2",
    "addr:housenumber":"8369",
    "addr:postcode":"b3z 3r2",
    "addr:street":"Peggys Cove Rd",
    "iso:country":"CA",
    "sg:address":"8369 Peggys Cove Rd",
    "sg:city":"Indian Harbour",
    "sg:classifiers":[
        {
            "category":"Restaurant",
            "type":"Food & Drink"
        }
    ],
    "sg:phone":"+1 902 823 1908",
    "sg:postcode":"B3Z 3R2",
    "sg:province":"NS",
    "sg:tags":[
        "tea",
        "rooms"
    ],
    "wof:name":"Tea & Treasures",
    "wof:placetype":"venue"
},
  "geometry": {"coordinates":[-63.936164856,44.5104026794],"type":"Point"}
}