{
  "type": "Feature",
  "properties": {
    "addr:full":"5481 Dundas St W Etobicoke ON M9B 1B5",
    "addr:housenumber":"5481",
    "addr:postcode":"m9b 1b5",
    "addr:street":"Dundas St W",
    "iso:country":"CA",
    "sg:address":"5481 Dundas St W",
    "sg:city":"Etobicoke",
    "sg:classifiers":[
        {
            "category":"Home & Garden",
            "subcategory":"Garden Supply",
            "type":"Retail Goods"
        }
    ],
    "sg:phone":"+1 416 239 2024",
    "sg:postcode":"M9B 1B5",
    "sg:province":"ON",
    "sg:tags":[
        "center"
    ],
    "wof:name":"Kipling Feed & Garden Ctr",
    "wof:placetype":"venue"
},
  "geometry": {"coordinates":[-79.54411315919999,43.6323013306],"type":"Point"}
}