{
  "type": "Feature",
  "properties": {
    "addr:full":"Mississauga ON L5J 1K5",
    "addr:postcode":"l5j 1k5",
    "iso:country":"CA",
    "sg:city":"Mississauga",
    "sg:classifiers":[
        {
            "category":"Freight",
            "type":"Transportation"
        }
    ],
    "sg:phone":"+1 905 822 4888",
    "sg:postcode":"L5J 1K5",
    "sg:province":"ON",
    "sg:tags":[
        "mover"
    ],
    "wof:name":"Kms Van Lines Inc",
    "wof:placetype":"venue"
},
  "geometry": {"coordinates":[-79.63562774659999,43.5059661865],"type":"Point"}
}