{
  "type": "Feature",
  "properties": {
    "addr:full":"2213 Broad St Regina SK S4P 1Y7",
    "addr:housenumber":"2213",
    "addr:postcode":"s4p 1y7",
    "addr:street":"Broad St",
    "iso:country":"CA",
    "sg:address":"2213 Broad St",
    "sg:city":"Regina",
    "sg:classifiers":[
        {
            "category":"Retail",
            "subcategory":"Self-service Laundry",
            "type":"Services"
        }
    ],
    "sg:phone":"+1 306 352 3908",
    "sg:postcode":"S4P 1Y7",
    "sg:province":"SK",
    "wof:name":"Broad & 14th Ave Coin Laundry",
    "wof:placetype":"venue"
},
  "geometry": {"coordinates":[-104.606133,50.443634],"type":"Point"}
}