{
  "type": "Feature",
  "properties": {
    "addr:full":"701 Eighth Ave New Westminster BC V3M 2R2",
    "addr:housenumber":"701",
    "addr:postcode":"v3m 2r2",
    "addr:street":"Eighth Ave",
    "iso:country":"CA",
    "sg:address":"701 Eighth Ave",
    "sg:city":"New Westminster",
    "sg:classifiers":[
        {
            "category":"Government",
            "subcategory":"Office",
            "type":"Public Place"
        }
    ],
    "sg:phone":"+1 604 525 5301",
    "sg:postcode":"V3M 2R2",
    "sg:province":"BC",
    "sg:tags":[
        "village"
    ],
    "wof:name":"New Westminster Moody Pk Arena",
    "wof:placetype":"venue"
},
  "geometry": {"coordinates":[-122.925873,49.21513],"type":"Point"}
}