{
  "type": "Feature",
  "properties": {
    "iso:country":"CA",
    "sg:address":"547 Darlington Dr",
    "sg:city":"Dalhousie",
    "sg:classifiers":[
        {
            "category":"Autos & Motor Vehicles",
            "subcategory":"Automobile Sales",
            "type":"Retail Goods"
        }
    ],
    "sg:phone":"+1 506 684 5533",
    "sg:postcode":"E8C 1M6",
    "sg:province":"NB",
    "sg:tags":[
        "car",
        "dealer"
    ],
    "wof:name":"Central Motors Ltd",
    "wof:placetype":"venue"
},
  "geometry": {"coordinates":[-66.401794,48.040089],"type":"Point"}
}