{
  "type": "Feature",
  "properties": {
    "iso:country":"CA",
    "sg:address":"1184 Rue Sainte-Catherine O",
    "sg:city":"Montreal",
    "sg:classifiers":[
        {
            "category":"Social Services",
            "subcategory":"Job Training",
            "type":"Services"
        }
    ],
    "sg:phone":"+1 514 875 9770",
    "sg:postcode":"H3B 1K1",
    "sg:province":"QC",
    "sg:tags":[
        "employment"
    ],
    "wof:name":"Carrefour Jeunesse-Emploi",
    "wof:placetype":"venue"
},
  "geometry": {"coordinates":[-73.55619,45.51815],"type":"Point"}
}