{
  "type": "Feature",
  "properties": {
    "addr:full":"805 Boul Arthur-Sauve Saint-Eustache QC J7R 4K3",
    "addr:housenumber":"805",
    "addr:postcode":"j7r 4k3",
    "addr:street":"Boul Arthur-Sauve",
    "iso:country":"CA",
    "sg:address":"805 Boul Arthur-Sauve",
    "sg:city":"Saint-Eustache",
    "sg:classifiers":[
        {
            "category":"Wholesale",
            "subcategory":"Auto Parts",
            "type":"Manufacturing & Wholesale Goods"
        }
    ],
    "sg:phone":"+1 450 472 9000",
    "sg:postcode":"J7R 4K3",
    "sg:province":"QC",
    "sg:tags":[
        "automobile",
        "rebuilt",
        "wrecker"
    ],
    "wof:name":"Automobiles M Miller Inc",
    "wof:placetype":"venue"
},
  "geometry": {"coordinates":[-73.923721,45.58363],"type":"Point"}
}