{
  "type": "Feature",
  "properties": {
    "addr:full":"3789 Av DE Hampton Montreal QC H4A 2K7",
    "addr:housenumber":"3789",
    "addr:postcode":"h4a 2k7",
    "addr:street":"Av De Hampton",
    "iso:country":"CA",
    "sg:address":"3789 Av DE Hampton",
    "sg:city":"Montreal",
    "sg:classifiers":[
        {
            "category":"Professional",
            "subcategory":"Business Services",
            "type":"Services"
        }
    ],
    "sg:phone":"+1 514 485 6373",
    "sg:postcode":"H4A 2K7",
    "sg:province":"QC",
    "wof:name":"Health Training Group",
    "wof:placetype":"venue"
},
  "geometry": {"coordinates":[-73.621368,45.468712],"type":"Point"}
}