{
  "type": "Feature",
  "properties": {
    "addr:full":"Red Deer AB T4N 4R7",
    "addr:postcode":"t4n 4r7",
    "iso:country":"CA",
    "sg:city":"Red Deer",
    "sg:classifiers":[
        {
            "category":"Real Estate",
            "subcategory":"Real Estate Agent",
            "type":"Services"
        }
    ],
    "sg:phone":"+1 403 341 7800",
    "sg:postcode":"T4N 4R7",
    "sg:province":"AB",
    "sg:tags":[
        "loan"
    ],
    "wof:name":"Source Mortgage Ctr",
    "wof:placetype":"venue"
},
  "geometry": {"coordinates":[-113.829742,52.257809],"type":"Point"}
}