{
  "type": "Feature",
  "properties": {
    "addr:full":"Edmonton AB T6B 0A7",
    "addr:postcode":"t6b 0a7",
    "iso:country":"CA",
    "sg:city":"Edmonton",
    "sg:classifiers":[
        {
            "category":"Retail",
            "subcategory":"Repair Shop",
            "type":"Services"
        }
    ],
    "sg:phone":"+1 780 466 1224",
    "sg:postcode":"T6B 0A7",
    "sg:province":"AB",
    "sg:tags":[
        "welding"
    ],
    "wof:name":"Golden Rod Welding Ltd",
    "wof:placetype":"venue"
},
  "geometry": {"coordinates":[-113.42627,53.512299],"type":"Point"}
}