{
  "type": "Feature",
  "properties": {
    "addr:full":"1275 Dundas St Woodstock ON N4S 7V9",
    "addr:housenumber":"1275",
    "addr:postcode":"n4s 7v9",
    "addr:street":"Dundas St",
    "iso:country":"CA",
    "sg:address":"1275 Dundas St",
    "sg:city":"Woodstock",
    "sg:classifiers":[
        {
            "category":"Travel",
            "subcategory":"Hotels & Motels",
            "type":"Entertainment"
        }
    ],
    "sg:phone":"+1 519 537 3446",
    "sg:postcode":"N4S 7V9",
    "sg:province":"ON",
    "wof:name":"Tulip Motel",
    "wof:placetype":"venue"
},
  "geometry": {"coordinates":[-80.716042,43.13625],"type":"Point"}
}