{
  "type": "Feature",
  "properties": {
    "addr:full":"2711 St Etienne Blvd Windsor ON N8W 5B1",
    "addr:housenumber":"2711",
    "addr:postcode":"n8w 5b1",
    "addr:street":"St Etienne Blvd",
    "iso:country":"CA",
    "sg:address":"2711 St Etienne Blvd",
    "sg:city":"Windsor",
    "sg:classifiers":[
        {
            "category":"Manufacturing",
            "subcategory":"Tools & Machinery",
            "type":"Manufacturing & Wholesale Goods"
        }
    ],
    "sg:phone":"+1 519 945 5639",
    "sg:postcode":"N8W 5B1",
    "sg:province":"ON",
    "sg:tags":[
        "mold"
    ],
    "wof:name":"Smi Sales Inc",
    "wof:placetype":"venue"
},
  "geometry": {"coordinates":[-82.97288500000001,42.27895],"type":"Point"}
}