{
  "type": "Feature",
  "properties": {
    "iso:country":"CA",
    "sg:address":"5900 Boul Des Grandes-Prairies",
    "sg:city":"Saint-Leonard",
    "sg:classifiers":[
        {
            "category":"Retail",
            "subcategory":"Car Wash",
            "type":"Services"
        }
    ],
    "sg:phone":"+1 514 327 7798",
    "sg:postcode":"H1P 1A2",
    "sg:province":"QC",
    "sg:tags":[
        "polishing",
        "wrecker",
        "washing"
    ],
    "wof:name":"Garage Formula 1",
    "wof:placetype":"venue"
},
  "geometry": {"coordinates":[-73.6109695435,45.5998687744],"type":"Point"}
}