{
  "type": "Feature",
  "properties": {
    "addr:full":"780 Rang York Saint-Barthelemy QC J0K 1X0",
    "addr:housenumber":"780",
    "addr:postcode":"j0k 1x0",
    "addr:street":"Rang York Saint-Barthelemy",
    "iso:country":"CA",
    "sg:address":"780 Rang York",
    "sg:city":"Saint-Barthelemy",
    "sg:classifiers":[
        {
            "category":"Government",
            "subcategory":"Office",
            "type":"Public Place"
        }
    ],
    "sg:phone":"+1 450 885 2173",
    "sg:postcode":"J0K 1X0",
    "sg:province":"QC",
    "sg:tags":[
        "village"
    ],
    "wof:name":"St-Barthelemy Usine-Filtration",
    "wof:placetype":"venue"
},
  "geometry": {"coordinates":[-73.1281204224,46.1918334961],"type":"Point"}
}