{
  "type": "Feature",
  "properties": {
    "iso:country":"CA",
    "sg:address":"168 Garafraxa St",
    "sg:city":"Chatsworth",
    "sg:classifiers":[
        {
            "category":"Shopping",
            "subcategory":"Catalog Store",
            "type":"Retail Goods"
        }
    ],
    "sg:phone":"+1 519 794 3402",
    "sg:postcode":"N0H 1G0",
    "sg:province":"ON",
    "sg:tags":[
        "mail",
        "order",
        "internet"
    ],
    "wof:name":"Sears Canada Inc",
    "wof:placetype":"venue"
},
  "geometry": {"coordinates":[-80.8978424072,44.4544715881],"type":"Point"}
}