{
  "type": "Feature",
  "properties": {
    "addr:full":"1783 Oxford St E London ON N5V 2Z6",
    "addr:housenumber":"1783",
    "addr:postcode":"n5v 2z6",
    "addr:street":"Oxford St E",
    "iso:country":"CA",
    "sg:address":"1783 Oxford St E",
    "sg:city":"London",
    "sg:classifiers":[
        {
            "category":"Retail",
            "subcategory":"Auto Repair",
            "type":"Services"
        }
    ],
    "sg:phone":"+1 519 457 2265",
    "sg:postcode":"N5V 2Z6",
    "sg:province":"ON",
    "sg:tags":[
        "repairing",
        "automobile"
    ],
    "wof:name":"Liem's Auto Repairs",
    "wof:placetype":"venue"
},
  "geometry": {"coordinates":[-81.18853759770001,43.0141410828],"type":"Point"}
}