{
  "type": "Feature",
  "properties": {
    "addr:full":"79 Broadway Orangeville ON L9W 1K1",
    "addr:housenumber":"79",
    "addr:postcode":"l9w 1k1",
    "addr:street":"Broadway",
    "iso:country":"CA",
    "sg:address":"79 Broadway",
    "sg:city":"Orangeville",
    "sg:classifiers":[
        {
            "category":"Health Services",
            "subcategory":"Doctor",
            "type":"Services"
        }
    ],
    "sg:phone":"+1 519 941 9341",
    "sg:postcode":"L9W 1K1",
    "sg:province":"ON",
    "sg:tags":[
        "dentist"
    ],
    "wof:name":"Playfair Dental Ctr",
    "wof:placetype":"venue"
},
  "geometry": {"coordinates":[-80.0936126709,43.9202308655],"type":"Point"}
}