{
  "type": "Feature",
  "properties": {
    "addr:full":"500 Rue DE L'Expansion Rimouski QC G5M 1A9",
    "addr:housenumber":"500",
    "addr:postcode":"g5m 1a9",
    "addr:street":"Rue De L'Expansion",
    "iso:country":"CA",
    "sg:address":"500 Rue DE L'Expansion",
    "sg:city":"Rimouski",
    "sg:classifiers":[
        {
            "category":"Manufacturing",
            "subcategory":"Tools & Machinery",
            "type":"Manufacturing & Wholesale Goods"
        }
    ],
    "sg:phone":"+1 418 724 5811",
    "sg:postcode":"G5M 1A9",
    "sg:province":"QC",
    "sg:tags":[
        "machine",
        "shop"
    ],
    "wof:name":"Usinage DE Rimouski",
    "wof:placetype":"venue"
},
  "geometry": {"coordinates":[-68.51050600000001,48.468452],"type":"Point"}
}