{
  "type": "Feature",
  "properties": {
    "addr:full":"Barrie ON L4N 5R7",
    "addr:postcode":"l4n 5r7",
    "iso:country":"CA",
    "sg:city":"Barrie",
    "sg:classifiers":[
        {
            "category":"Restaurant",
            "type":"Food & Drink"
        }
    ],
    "sg:phone":"+1 705 722 6633",
    "sg:postcode":"L4N 5R7",
    "sg:province":"ON",
    "wof:name":"Caddy's Steakhouse",
    "wof:placetype":"venue"
},
  "geometry": {"coordinates":[-79.7120895386,44.3819503784],"type":"Point"}
}