{
  "type": "Feature",
  "properties": {
    "addr:full":"9534 61 Ave Grande Prairie AB T8W 2C5",
    "addr:housenumber":"9534",
    "addr:postcode":"t8w 2c5",
    "addr:street":"61 Ave",
    "iso:country":"CA",
    "sg:address":"9534 61 Ave",
    "sg:city":"Grande Prairie",
    "sg:classifiers":[
        {
            "category":"Retail",
            "subcategory":"Repair Shop",
            "type":"Services"
        }
    ],
    "sg:phone":"+1 780 532 0287",
    "sg:postcode":"T8W 2C5",
    "sg:province":"AB",
    "sg:tags":[
        "welding"
    ],
    "wof:name":"Bill Chascha's Welding Ltd",
    "wof:placetype":"venue"
},
  "geometry": {"coordinates":[-118.777938843,55.135055542],"type":"Point"}
}