{
  "type": "Feature",
  "properties": {
    "addr:full":"26 Rue DE Valcourt Gatineau QC J8T 8G8",
    "addr:housenumber":"26",
    "addr:postcode":"j8t 8g8",
    "addr:street":"Rue De Valcourt",
    "iso:country":"CA",
    "sg:address":"26 Rue DE Valcourt",
    "sg:city":"Gatineau",
    "sg:classifiers":[
        {
            "category":"Home & Garden",
            "subcategory":"Building Materials",
            "type":"Retail Goods"
        }
    ],
    "sg:phone":"+1 819 561 0135",
    "sg:postcode":"J8T 8G8",
    "sg:province":"QC",
    "sg:tags":[
        "type",
        "door"
    ],
    "wof:name":"Exitech Inc Les Sepcialistes",
    "wof:placetype":"venue"
},
  "geometry": {"coordinates":[-75.707382,45.491554],"type":"Point"}
}