{
  "type": "Feature",
  "properties": {
    "iso:country":"CA",
    "sg:address":"333 Rue Notre-Dame E",
    "sg:city":"Montreal",
    "sg:classifiers":[
        {
            "category":"Sports & Exercise",
            "subcategory":"Gym",
            "type":"Entertainment"
        }
    ],
    "sg:phone":"+1 514 866 3110",
    "sg:postcode":"H2Y 3Z2",
    "sg:province":"QC",
    "sg:tags":[
        "club",
        "health",
        "studio",
        "gymnasium"
    ],
    "wof:name":"Energie Cardio",
    "wof:placetype":"venue"
},
  "geometry": {"coordinates":[-73.553223,45.509537],"type":"Point"}
}