{
  "type": "Feature",
  "properties": {
    "addr:full":"146 Isabella St Toronto ON M4Y 1P6",
    "addr:housenumber":"146",
    "addr:postcode":"m4y 1p6",
    "addr:street":"Isabella St",
    "iso:country":"CA",
    "sg:address":"146 Isabella St",
    "sg:city":"Toronto",
    "sg:classifiers":[
        {
            "category":"Education",
            "subcategory":"School",
            "type":"Public Place"
        }
    ],
    "sg:phone":"+1 416 393 5533",
    "sg:postcode":"M4Y 1P6",
    "sg:province":"ON",
    "wof:name":"Monsignor Fraser College",
    "wof:placetype":"venue"
},
  "geometry": {"coordinates":[-79.3776016235,43.6693840027],"type":"Point"}
}