{
  "type": "Feature",
  "properties": {
    "iso:country":"CA",
    "sg:address":"215 Villa Marie Dr",
    "sg:city":"Marystown",
    "sg:classifiers":[
        {
            "category":"Insurance",
            "subcategory":"Insurance Agent",
            "type":"Services"
        }
    ],
    "sg:phone":"+1 709 279 2416",
    "sg:postcode":"A0E 2M0",
    "sg:province":"NL",
    "wof:name":"Wiscombe's Insurance Ltd",
    "wof:placetype":"venue"
},
  "geometry": {"coordinates":[-55.1523895264,47.1673469543],"type":"Point"}
}