{
  "type": "Feature",
  "properties": {
    "addr:full":"136 117 Rte Sainte-Anne-Des-Lacs QC J0R 1B0",
    "addr:housenumber":"117",
    "addr:postcode":"j0r 1b0",
    "addr:street":"Rte Sainte-Anne-Des-Lacs",
    "iso:country":"CA",
    "sg:address":"136 117 Rte",
    "sg:city":"Sainte-Anne-Des-Lacs",
    "sg:classifiers":[
        {
            "category":"Building & Trades",
            "subcategory":"Construction",
            "type":"Services"
        }
    ],
    "sg:phone":"+1 450 227 1579",
    "sg:postcode":"J0R 1B0",
    "sg:province":"QC",
    "sg:tags":[
        "maker",
        "cabinet"
    ],
    "wof:name":"Ebenisteries Pierre Ziliani",
    "wof:placetype":"venue"
},
  "geometry": {"coordinates":[-74.127579,45.859848],"type":"Point"}
}