{
  "type": "Feature",
  "properties": {
    "iso:country":"CA",
    "sg:address":"2660 Dunsmuir Ave",
    "sg:city":"Cumberland",
    "sg:classifiers":[
        {
            "category":"Professional",
            "type":"Services"
        }
    ],
    "sg:phone":"+1 250 336 3221",
    "sg:postcode":"V0R 1S0",
    "sg:province":"BC",
    "sg:tags":[
        "establishment"
    ],
    "wof:name":"Upper Island Comm Health",
    "wof:placetype":"venue"
},
  "geometry": {"coordinates":[-125.031052,49.618938],"type":"Point"}
}