{
  "type": "Feature",
  "properties": {
    "addr:full":"865 Rangeview Rd Mississauga ON L5E 1H1",
    "addr:housenumber":"865",
    "addr:postcode":"l5e 1h1",
    "addr:street":"Rangeview Rd",
    "iso:country":"CA",
    "sg:address":"865 Rangeview Rd",
    "sg:city":"Mississauga",
    "sg:classifiers":[
        {
            "category":"Wholesale",
            "subcategory":"Stationery",
            "type":"Manufacturing & Wholesale Goods"
        }
    ],
    "sg:phone":"+1 905 271 1523",
    "sg:postcode":"L5E 1H1",
    "sg:province":"ON",
    "sg:tags":[
        "packaging",
        "equipment",
        "hospital",
        "supply"
    ],
    "wof:name":"G S Medical Packaging Inc",
    "wof:placetype":"venue"
},
  "geometry": {"coordinates":[-79.559883,43.572784],"type":"Point"}
}