{
  "type": "Feature",
  "properties": {
    "addr:full":"RR 8 Lcd Main Orangeville ON L9W 3T5",
    "addr:postcode":"l9w 3t5",
    "addr:street":"Rr 8 Lcd Main",
    "iso:country":"CA",
    "sg:address":"RR 8 Lcd Main",
    "sg:city":"Orangeville",
    "sg:classifiers":[
        {
            "category":"Marine",
            "type":"Transportation"
        }
    ],
    "sg:phone":"+1 519 941 6323",
    "sg:postcode":"L9W 3T5",
    "sg:province":"ON",
    "sg:tags":[
        "surveyor"
    ],
    "wof:name":"Baxter Marine Svc Inc",
    "wof:placetype":"venue"
},
  "geometry": {"coordinates":[-80.09349060060001,43.9201164246],"type":"Point"}
}