{
  "type": "Feature",
  "properties": {
    "addr:full":"Mississauga ON L4Z 3N1",
    "addr:postcode":"l4z 3n1",
    "iso:country":"CA",
    "sg:city":"Mississauga",
    "sg:classifiers":[
        {
            "category":"Banks & Credit Unions",
            "subcategory":"Bank",
            "type":"Services"
        }
    ],
    "sg:phone":"+1 905 501 5000",
    "sg:postcode":"L4Z 3N1",
    "sg:province":"ON",
    "sg:tags":[
        "financing"
    ],
    "wof:name":"J D Factors",
    "wof:placetype":"venue"
},
  "geometry": {"coordinates":[-79.67647599999999,43.627888],"type":"Point"}
}