{
  "type": "Feature",
  "properties": {
    "addr:full":"190 Cedar St Sudbury ON P3E 1B4",
    "addr:housenumber":"190",
    "addr:postcode":"p3e 1b4",
    "addr:street":"Cedar St",
    "iso:country":"CA",
    "sg:address":"190 Cedar St",
    "sg:city":"Sudbury",
    "sg:classifiers":[
        {
            "category":"Food & Beverages",
            "subcategory":"Liquor & Beverages",
            "type":"Retail Goods"
        }
    ],
    "sg:phone":"+1 705 675 5391",
    "sg:postcode":"P3E 1B4",
    "sg:province":"ON",
    "sg:tags":[
        "store"
    ],
    "wof:name":"Regie Des Alcools DE L'Ontario",
    "wof:placetype":"venue"
},
  "geometry": {"coordinates":[-80.9904327393,46.4923477173],"type":"Point"}
}