{
  "type": "Feature",
  "properties": {
    "addr:full":"343 County Rd 14 Cottam ON N0R 1B0",
    "addr:housenumber":"343;14",
    "addr:postcode":"n0r 1b0",
    "addr:street":"County Rd",
    "iso:country":"CA",
    "sg:address":"343 County Rd 14",
    "sg:city":"Cottam",
    "sg:classifiers":[
        {
            "category":"Shopping",
            "subcategory":"Florist",
            "type":"Retail Goods"
        }
    ],
    "sg:phone":"+1 519 839 4700",
    "sg:postcode":"N0R 1B0",
    "sg:province":"ON",
    "sg:tags":[
        "plant"
    ],
    "wof:name":"Albuna Plant Farm",
    "wof:placetype":"venue"
},
  "geometry": {"coordinates":[-82.74350738530001,42.1289863586],"type":"Point"}
}