{
  "type": "Feature",
  "properties": {
    "addr:full":"Contrecoeur QC J0L 1C0",
    "addr:postcode":"j0l 1c0",
    "iso:country":"CA",
    "sg:city":"Contrecoeur",
    "sg:classifiers":[
        {
            "category":"Banks & Credit Unions",
            "subcategory":"Bank",
            "type":"Services"
        }
    ],
    "sg:phone":"+1 450 587 2005",
    "sg:postcode":"J0L 1C0",
    "sg:province":"QC",
    "wof:name":"Banque Nationale Du Canada",
    "wof:placetype":"venue"
},
  "geometry": {"coordinates":[-73.2399215698,45.8561401367],"type":"Point"}
}