{
  "type": "Feature",
  "properties": {
    "addr:full":"Vancouver BC V6E 4A2",
    "addr:postcode":"v6e 4a2",
    "iso:country":"CA",
    "sg:city":"Vancouver",
    "sg:classifiers":[
        {
            "category":"Utilities",
            "subcategory":"Telephone",
            "type":"Services"
        }
    ],
    "sg:phone":"+1 604 684 4111",
    "sg:postcode":"V6E 4A2",
    "sg:province":"BC",
    "sg:tags":[
        "company"
    ],
    "wof:name":"Primus Canada",
    "wof:placetype":"venue"
},
  "geometry": {"coordinates":[-123.125007629,49.2867851257],"type":"Point"}
}