{
  "type": "Feature",
  "properties": {
    "addr:full":"2805 44 Ave Vernon BC V1T 7P4",
    "addr:housenumber":"2805",
    "addr:postcode":"v1t 7p4",
    "addr:street":"44 Ave",
    "iso:country":"CA",
    "sg:address":"2805 44 Ave",
    "sg:city":"Vernon",
    "sg:classifiers":[
        {
            "category":"Building & Trades",
            "subcategory":"Electrical",
            "type":"Services"
        }
    ],
    "sg:phone":"+1 250 542 2307",
    "sg:postcode":"V1T 7P4",
    "sg:province":"BC",
    "sg:tags":[
        "electric",
        "contractor"
    ],
    "wof:name":"Kal West Contractors Ltd",
    "wof:placetype":"venue"
},
  "geometry": {"coordinates":[-119.268677,50.276363],"type":"Point"}
}