{
  "type": "Feature",
  "properties": {
    "iso:country":"CA",
    "sg:address":"503 5th Conc W",
    "sg:city":"Waterdown",
    "sg:classifiers":[
        {
            "category":"Building & Trades",
            "subcategory":"Landscaping Services",
            "type":"Services"
        }
    ],
    "sg:phone":"+1 905 689 6338",
    "sg:postcode":"L0R 2H2",
    "sg:province":"ON",
    "sg:tags":[
        "topsoil"
    ],
    "wof:name":"London Brothers",
    "wof:placetype":"venue"
},
  "geometry": {"coordinates":[-79.90232086180001,43.3624839783],"type":"Point"}
}