{
  "type": "Feature",
  "properties": {
    "addr:full":"Mississauga ON L5N 5E5",
    "addr:postcode":"l5n 5e5",
    "iso:country":"CA",
    "sg:city":"Mississauga",
    "sg:classifiers":[
        {
            "category":"Personal",
            "subcategory":"Beauty Salon",
            "type":"Services"
        }
    ],
    "sg:phone":"+1 905 824 5101",
    "sg:postcode":"L5N 5E5",
    "sg:province":"ON",
    "wof:name":"Salon Successo & Esthetics",
    "wof:placetype":"venue"
},
  "geometry": {"coordinates":[-79.773895,43.586475],"type":"Point"}
}