{
  "type": "Feature",
  "properties": {
    "iso:country":"CA",
    "sg:city":"Brampton",
    "sg:classifiers":[
        {
            "category":"Building & Trades",
            "subcategory":"Plumbing",
            "type":"Services"
        }
    ],
    "sg:phone":"+1 905 790 9700",
    "sg:postcode":"L6S 5N5",
    "sg:province":"ON",
    "sg:tags":[
        "equipment",
        "industrial",
        "humidifying",
        "apparatus",
        "supply"
    ],
    "wof:name":"Northern Industrial Supply CO",
    "wof:placetype":"venue"
},
  "geometry": {"coordinates":[-79.709648,43.75597],"type":"Point"}
}