{
  "type": "Feature",
  "properties": {
    "iso:country":"CA",
    "sg:address":"480 Boul Saint-Joseph",
    "sg:city":"Drummondville",
    "sg:classifiers":[
        {
            "category":"Manufacturing",
            "subcategory":"Tools & Machinery",
            "type":"Manufacturing & Wholesale Goods"
        }
    ],
    "sg:phone":"+1 819 478 4717",
    "sg:postcode":"J2C 2B4",
    "sg:province":"QC",
    "sg:tags":[
        "machine",
        "sharpening",
        "honing",
        "equipment"
    ],
    "wof:name":"Affutage St-Pierre Inc",
    "wof:placetype":"venue"
},
  "geometry": {"coordinates":[-72.516960144,45.8948974609],"type":"Point"}
}