{
  "type": "Feature",
  "properties": {
    "iso:country":"CA",
    "sg:address":"20 Logan Ave",
    "sg:city":"Toronto",
    "sg:classifiers":[
        {
            "category":"Manufacturing",
            "subcategory":"Tools & Machinery",
            "type":"Manufacturing & Wholesale Goods"
        }
    ],
    "sg:phone":"+1 416 778 4114",
    "sg:postcode":"M4M 2M8",
    "sg:province":"ON",
    "sg:tags":[
        "motion",
        "picture",
        "supply"
    ],
    "wof:name":"Hotsets Film Ltd",
    "wof:placetype":"venue"
},
  "geometry": {"coordinates":[-79.34001159669999,43.6542739868],"type":"Point"}
}