{
  "type": "Feature",
  "properties": {
    "addr:full":"Toronto ON M6H 4B5",
    "addr:postcode":"m6h 4b5",
    "iso:country":"CA",
    "sg:city":"Toronto",
    "sg:classifiers":[
        {
            "category":"Health Services",
            "subcategory":"Doctor",
            "type":"Services"
        }
    ],
    "sg:phone":"+1 416 537 2438",
    "sg:postcode":"M6H 4B5",
    "sg:province":"ON",
    "sg:tags":[
        "physician",
        "surgeon"
    ],
    "wof:name":"Hailemeskel, Yemisrach MD",
    "wof:placetype":"venue"
},
  "geometry": {"coordinates":[-79.4353103638,43.6602401733],"type":"Point"}
}