{
  "type": "Feature",
  "properties": {
    "addr:full":"146 8E Rang O Caplan QC G0C 1H0",
    "addr:housenumber":"146",
    "addr:postcode":"g0c 1h0",
    "addr:street":"8E Rang O",
    "iso:country":"CA",
    "sg:address":"146 8E Rang O",
    "sg:city":"Caplan",
    "sg:classifiers":[
        {
            "category":"Organizations",
            "subcategory":"Religious Organization",
            "type":"Services"
        }
    ],
    "sg:phone":"+1 418 388 2154",
    "sg:postcode":"G0C 1H0",
    "sg:province":"QC",
    "sg:tags":[
        "church"
    ],
    "wof:name":"St-Alphonse-Caplan Eglises",
    "wof:placetype":"venue"
},
  "geometry": {"coordinates":[-65.67287445069999,48.1610984802],"type":"Point"}
}