{
  "type": "Feature",
  "properties": {
    "iso:country":"CA",
    "sg:city":"Weyburn",
    "sg:classifiers":[
        {
            "category":"Social Services",
            "type":"Services"
        }
    ],
    "sg:phone":"+1 306 842 8693",
    "sg:postcode":"S4H 2Z9",
    "sg:province":"SK",
    "sg:tags":[
        "information",
        "organization",
        "treatment",
        "alcoholism",
        "welfare"
    ],
    "wof:name":"Addiction Services South",
    "wof:placetype":"venue"
},
  "geometry": {"coordinates":[-103.858192444,49.6680297852],"type":"Point"}
}