{
  "type": "Feature",
  "properties": {
    "iso:country":"CA",
    "sg:address":"4282 Rue DE Neuville",
    "sg:city":"Terrebonne",
    "sg:classifiers":[
        {
            "category":"Wholesale",
            "subcategory":"Office Equipment",
            "type":"Manufacturing & Wholesale Goods"
        }
    ],
    "sg:phone":"+1 450 492 2121",
    "sg:postcode":"J6X 1A5",
    "sg:province":"QC",
    "sg:tags":[
        "accounting",
        "bookkeeping",
        "system"
    ],
    "wof:name":"Mise A Jour",
    "wof:placetype":"venue"
},
  "geometry": {"coordinates":[-73.66538238530001,45.6990127563],"type":"Point"}
}