{
  "type": "Feature",
  "properties": {
    "addr:full":"Parksville BC V9P 2B7",
    "addr:postcode":"v9p 2b7",
    "iso:country":"CA",
    "sg:city":"Parksville",
    "sg:classifiers":[
        {
            "category":"Food & Beverages",
            "subcategory":"Liquor & Beverages",
            "type":"Retail Goods"
        }
    ],
    "sg:phone":"+1 250 248 3724",
    "sg:postcode":"V9P 2B7",
    "sg:province":"BC",
    "sg:tags":[
        "store"
    ],
    "wof:name":"Liquor Store-Government",
    "wof:placetype":"venue"
},
  "geometry": {"coordinates":[-124.345871,49.332443],"type":"Point"}
}