{
  "type": "Feature",
  "properties": {
    "addr:full":"10307 100 Ave Fort Saskatchewan AB T8L 1Y9",
    "addr:housenumber":"10307",
    "addr:postcode":"t8l 1y9",
    "addr:street":"100 Ave",
    "iso:country":"CA",
    "sg:address":"10307 100 Ave",
    "sg:city":"Fort Saskatchewan",
    "sg:classifiers":[
        {
            "category":"Shopping",
            "subcategory":"Jewelry",
            "type":"Retail Goods"
        }
    ],
    "sg:phone":"+1 780 998 3463",
    "sg:postcode":"T8L 1Y9",
    "sg:province":"AB",
    "sg:tags":[
        "jeweler"
    ],
    "wof:name":"Roland's Jewelry",
    "wof:placetype":"venue"
},
  "geometry": {"coordinates":[-113.212226868,53.7126426697],"type":"Point"}
}