{
  "type": "Feature",
  "properties": {
    "addr:full":"785 Main St E #8D Milton ON L9T 3Z3",
    "addr:housenumber":"785",
    "addr:postcode":"l9t 3z3",
    "addr:street":"Main St E # 8D",
    "iso:country":"CA",
    "sg:address":"785 Main St E #8D",
    "sg:city":"Milton",
    "sg:classifiers":[
        {
            "category":"Manufacturing",
            "subcategory":"Furniture",
            "type":"Manufacturing & Wholesale Goods"
        }
    ],
    "sg:phone":"+1 905 878 9177",
    "sg:postcode":"L9T 3Z3",
    "sg:province":"ON",
    "sg:tags":[
        "equipment",
        "kitchen",
        "store",
        "cabinet"
    ],
    "wof:name":"Concept Cabinets",
    "wof:placetype":"venue"
},
  "geometry": {"coordinates":[-79.870834,43.524761],"type":"Point"}
}