{
  "type": "Feature",
  "properties": {
    "addr:full":"13 Salisbury Ave Sault Ste Marie ON P6B 1L8",
    "addr:housenumber":"13",
    "addr:postcode":"p6b 1l8",
    "addr:street":"Salisbury Ave",
    "iso:country":"CA",
    "sg:address":"13 Salisbury Ave",
    "sg:city":"Sault Ste Marie",
    "sg:classifiers":[
        {
            "category":"Social Services",
            "subcategory":"Child Care",
            "type":"Services"
        }
    ],
    "sg:phone":"+1 705 759 2840",
    "sg:postcode":"P6B 1L8",
    "sg:province":"ON",
    "wof:name":"Maycourt Children's Ctr",
    "wof:placetype":"venue"
},
  "geometry": {"coordinates":[-84.32763671879999,46.5213356018],"type":"Point"}
}