{
  "type": "Feature",
  "properties": {
    "addr:full":"4912 53 St Yellowknife NT X1A 1V2",
    "addr:housenumber":"4912",
    "addr:postcode":"x1a 1v2",
    "addr:street":"53 St",
    "iso:country":"CA",
    "sg:address":"4912 53 St",
    "sg:city":"Yellowknife",
    "sg:classifiers":[
        {
            "category":"Organizations",
            "subcategory":"Professional Association",
            "type":"Services"
        }
    ],
    "sg:phone":"+1 867 920 2644",
    "sg:postcode":"X1A 1V2",
    "sg:province":"NT",
    "sg:tags":[
        "government"
    ],
    "wof:name":"Yellowknife Association-Cmnty",
    "wof:placetype":"venue"
},
  "geometry": {"coordinates":[-114.37657900000001,62.452728],"type":"Point"}
}