{
  "type": "Feature",
  "properties": {
    "addr:full":"11100 Bridgeport Rd # 120 Richmond BC V6X 1T2",
    "addr:housenumber":"11100;120",
    "addr:postcode":"v6x 1t2",
    "addr:street":"Bridgeport Rd #",
    "iso:country":"CA",
    "sg:address":"11100 Bridgeport Rd # 120",
    "sg:city":"Richmond",
    "sg:classifiers":[
        {
            "category":"Professional",
            "type":"Services"
        }
    ],
    "sg:phone":"+1 604 214 6620",
    "sg:postcode":"V6X 1T2",
    "sg:province":"BC",
    "sg:tags":[
        "equipment",
        "hydroponics",
        "supply"
    ],
    "wof:name":"Garden Effects",
    "wof:placetype":"venue"
},
  "geometry": {"coordinates":[-123.10115051299999,49.1918792725],"type":"Point"}
}