{
  "type": "Feature",
  "properties": {
    "addr:full":"500 Rang Saint-Georges Saint-Edouard-DE-Napierville QC J0L 1Y0",
    "addr:housenumber":"500",
    "addr:postcode":"j0l 1y0",
    "addr:street":"Rang Saint-Georges Saint-Edouard-De-Napierville",
    "iso:country":"CA",
    "sg:address":"500 Rang Saint-Georges",
    "sg:city":"Saint-Edouard-DE-Napierville",
    "sg:classifiers":[
        {
            "category":"Retail",
            "subcategory":"Auto Repair",
            "type":"Services"
        }
    ],
    "sg:phone":"+1 450 454 2371",
    "sg:postcode":"J0L 1Y0",
    "sg:province":"QC",
    "sg:tags":[
        "repairing",
        "automobile"
    ],
    "wof:name":"Jeleco",
    "wof:placetype":"venue"
},
  "geometry": {"coordinates":[-73.41564200000001,45.193989],"type":"Point"}
}