{
  "type": "Feature",
  "properties": {
    "addr:full":"65 Burtch St Woodstock ON N4S 3M4",
    "addr:housenumber":"65",
    "addr:postcode":"n4s 3m4",
    "addr:street":"Burtch St",
    "iso:country":"CA",
    "sg:address":"65 Burtch St",
    "sg:city":"Woodstock",
    "sg:classifiers":[
        {
            "category":"Personal",
            "subcategory":"Beauty Salon",
            "type":"Services"
        }
    ],
    "sg:phone":"+1 519 539 1411",
    "sg:postcode":"N4S 3M4",
    "sg:province":"ON",
    "wof:name":"Debonair Hair Styling",
    "wof:placetype":"venue"
},
  "geometry": {"coordinates":[-80.74805499999999,43.129623],"type":"Point"}
}