{
  "type": "Feature",
  "properties": {
    "addr:full":"814A16 Ave SW # A Calgary AB T2R 0S9",
    "addr:postcode":"t2r 0s9",
    "addr:street":"814A16 Ave Sw # A",
    "iso:country":"CA",
    "sg:address":"814A16 Ave SW # A",
    "sg:city":"Calgary",
    "sg:classifiers":[
        {
            "category":"Shopping",
            "subcategory":"Clothing, Apparel, & Fashions",
            "type":"Retail Goods"
        }
    ],
    "sg:phone":"+1 403 244 4404",
    "sg:postcode":"T2R 0S9",
    "sg:province":"AB",
    "wof:name":"Primitive Culture",
    "wof:placetype":"venue"
},
  "geometry": {"coordinates":[-114.063186645,51.0450706482],"type":"Point"}
}