{
  "type": "Feature",
  "properties": {
    "addr:full":"421 Bayview Dr Barrie ON L4N 8Y2",
    "addr:housenumber":"421",
    "addr:postcode":"l4n 8y2",
    "addr:street":"Bayview Dr",
    "iso:country":"CA",
    "sg:address":"421 Bayview Dr",
    "sg:city":"Barrie",
    "sg:classifiers":[
        {
            "category":"Freight",
            "type":"Transportation"
        }
    ],
    "sg:phone":"+1 705 739 7722",
    "sg:postcode":"L4N 8Y2",
    "sg:province":"ON",
    "sg:tags":[
        "commercial",
        "storage"
    ],
    "wof:name":"Barrie Space Station Mini Strg",
    "wof:placetype":"venue"
},
  "geometry": {"coordinates":[-79.678406,44.344776],"type":"Point"}
}