{
  "type": "Feature",
  "properties": {
    "addr:full":"1565 Dogwood St Prince George BC V2L 1C1",
    "addr:housenumber":"1565",
    "addr:postcode":"v2l 1c1",
    "addr:street":"Dogwood St",
    "iso:country":"CA",
    "sg:address":"1565 Dogwood St",
    "sg:city":"Prince George",
    "sg:classifiers":[
        {
            "category":"Professional",
            "subcategory":"Management & Consulting",
            "type":"Services"
        }
    ],
    "sg:phone":"+1 250 564 9404",
    "sg:postcode":"V2L 1C1",
    "sg:province":"BC",
    "sg:tags":[
        "break",
        "coffee",
        "supply"
    ],
    "wof:name":"Select Food Svc",
    "wof:placetype":"venue"
},
  "geometry": {"coordinates":[-122.73400116000001,53.9097595215],"type":"Point"}
}