{
  "type": "Feature",
  "properties": {
    "addr:full":"50 Lisgar St Sudbury ON P3E 3L8",
    "addr:housenumber":"50",
    "addr:postcode":"p3e 3l8",
    "addr:street":"Lisgar St",
    "iso:country":"CA",
    "sg:address":"50 Lisgar St",
    "sg:city":"Sudbury",
    "sg:classifiers":[
        {
            "category":"Health Services",
            "subcategory":"Medical Lab",
            "type":"Services"
        }
    ],
    "sg:phone":"+1 705 675 3771",
    "sg:postcode":"P3E 3L8",
    "sg:province":"ON",
    "wof:name":"Allan Delsaut Denture Clinics",
    "wof:placetype":"venue"
},
  "geometry": {"coordinates":[-80.992767,46.492138],"type":"Point"}
}