{
  "type": "Feature",
  "properties": {
    "iso:country":"CA",
    "sg:address":"520 Av Miller",
    "sg:city":"Murdochville",
    "sg:classifiers":[
        {
            "category":"Retail",
            "subcategory":"Auto Repair",
            "type":"Services"
        }
    ],
    "sg:phone":"+1 418 784 2341",
    "sg:postcode":"G0E 1W0",
    "sg:province":"QC",
    "sg:tags":[
        "wrecker"
    ],
    "wof:name":"Station DE Svc Ultramar",
    "wof:placetype":"venue"
},
  "geometry": {"coordinates":[-65.49742126460001,48.9578933716],"type":"Point"}
}