{
  "type": "Feature",
  "properties": {
    "iso:country":"CA",
    "sg:address":"70 Jacqueline St",
    "sg:city":"London",
    "sg:classifiers":[
        {
            "category":"Professional",
            "subcategory":"Computer Services",
            "type":"Services"
        }
    ],
    "sg:phone":"+1 519 663 0040",
    "sg:postcode":"N5Z 3P7",
    "sg:province":"ON",
    "sg:tags":[
        "consultant"
    ],
    "wof:name":"Computers For Schools",
    "wof:placetype":"venue"
},
  "geometry": {"coordinates":[-81.2212600708,42.9713821411],"type":"Point"}
}