{
  "type": "Feature",
  "properties": {
    "addr:full":"Secondary Hwy 893 Marwayne AB T0B 2X0",
    "addr:postcode":"t0b 2x0",
    "addr:street":"Secondary Hwy 893",
    "iso:country":"CA",
    "sg:address":"Secondary Hwy 893",
    "sg:city":"Marwayne",
    "sg:classifiers":[
        {
            "category":"Professional",
            "type":"Services"
        }
    ],
    "sg:phone":"+1 780 847 3608",
    "sg:postcode":"T0B 2X0",
    "sg:province":"AB",
    "sg:tags":[
        "development",
        "gas",
        "oil",
        "exploration",
        "establishment"
    ],
    "wof:name":"Bonavista Petroleum Ltd",
    "wof:placetype":"venue"
},
  "geometry": {"coordinates":[-110.332214355,53.5189781189],"type":"Point"}
}