{
  "type": "Feature",
  "properties": {
    "iso:country":"CA",
    "sg:address":"37 Queen St",
    "sg:city":"Ripley",
    "sg:classifiers":[
        {
            "category":"Autos & Motor Vehicles",
            "subcategory":"Fuel & Gas Station",
            "type":"Retail Goods"
        }
    ],
    "sg:phone":"+1 519 395 2985",
    "sg:postcode":"N0G 2R0",
    "sg:province":"ON",
    "sg:tags":[
        "oil"
    ],
    "wof:name":"Brian's Automotive Svc",
    "wof:placetype":"venue"
},
  "geometry": {"coordinates":[-81.578812,44.071693],"type":"Point"}
}