{
  "type": "Feature",
  "properties": {
    "addr:full":"1201 Queens Bush Rd # C Wellesley ON N0B 2T0",
    "addr:housenumber":"1201",
    "addr:postcode":"n0b 2t0",
    "addr:street":"Queens Bush Rd # C",
    "iso:country":"CA",
    "sg:address":"1201 Queens Bush Rd # C",
    "sg:city":"Wellesley",
    "sg:classifiers":[
        {
            "category":"Shopping",
            "subcategory":"Pharmacy",
            "type":"Retail Goods"
        }
    ],
    "sg:phone":"+1 519 656 2240",
    "sg:postcode":"N0B 2T0",
    "sg:province":"ON",
    "wof:name":"Cook's Pharmacy",
    "wof:placetype":"venue"
},
  "geometry": {"coordinates":[-80.764793,43.477619],"type":"Point"}
}