{
  "type": "Feature",
  "properties": {
    "addr:full":"106 Central Ave N Swift Current SK S9H 0L1",
    "addr:housenumber":"106",
    "addr:postcode":"s9h 0l1",
    "addr:street":"Central Ave N",
    "iso:country":"CA",
    "sg:address":"106 Central Ave N",
    "sg:city":"Swift Current",
    "sg:classifiers":[
        {
            "category":"Restaurant",
            "type":"Food & Drink"
        }
    ],
    "sg:phone":"+1 306 773 6217",
    "sg:postcode":"S9H 0L1",
    "sg:province":"SK",
    "sg:tags":[
        "shop",
        "coffee"
    ],
    "wof:name":"John's Country Cafe",
    "wof:placetype":"venue"
},
  "geometry": {"coordinates":[-107.800156,50.283718],"type":"Point"}
}