{
  "type": "Feature",
  "properties": {
    "addr:full":"151 Queen St Dunnville ON N1A 1H6",
    "addr:housenumber":"151",
    "addr:postcode":"n1a 1h6",
    "addr:street":"Queen St",
    "iso:country":"CA",
    "sg:address":"151 Queen St",
    "sg:city":"Dunnville",
    "sg:classifiers":[
        {
            "category":"Shopping",
            "subcategory":"Bicycles & Sporting Goods",
            "type":"Retail Goods"
        }
    ],
    "sg:phone":"+1 905 774 8871",
    "sg:postcode":"N1A 1H6",
    "sg:province":"ON",
    "wof:name":"Buckner's Source For Sports",
    "wof:placetype":"venue"
},
  "geometry": {"coordinates":[-79.61758399999999,42.902203],"type":"Point"}
}