{
  "type": "Feature",
  "properties": {
    "addr:full":"469 Glendale Ave St Catharines ON L2P 3Y2",
    "addr:housenumber":"469",
    "addr:postcode":"l2p 3y2",
    "addr:street":"Glendale Ave",
    "iso:country":"CA",
    "sg:address":"469 Glendale Ave",
    "sg:city":"St Catharines",
    "sg:classifiers":[
        {
            "category":"Professional",
            "type":"Services"
        }
    ],
    "sg:phone":"+1 905 227 8767",
    "sg:postcode":"L2P 3Y2",
    "sg:province":"ON",
    "sg:tags":[
        "venetian",
        "blind",
        "made",
        "establishment",
        "drapery"
    ],
    "wof:name":"Better Shade CO Ltd",
    "wof:placetype":"venue"
},
  "geometry": {"coordinates":[-79.19902,43.142666],"type":"Point"}
}