{
  "type": "Feature",
  "properties": {
    "addr:full":"Hull QC J8Y 3Y3",
    "addr:postcode":"j8y 3y3",
    "iso:country":"CA",
    "sg:city":"Hull",
    "sg:classifiers":[
        {
            "category":"Health Services",
            "subcategory":"Health Practitioner",
            "type":"Services"
        }
    ],
    "sg:phone":"+1 819 776 5111",
    "sg:postcode":"J8Y 3Y3",
    "sg:province":"QC",
    "sg:tags":[
        "physician"
    ],
    "wof:name":"Centre Mission Sante",
    "wof:placetype":"venue"
},
  "geometry": {"coordinates":[-75.732749939,45.4382667542],"type":"Point"}
}