{
  "type": "Feature",
  "properties": {
    "addr:full":"Etobicoke ON M8W 4H6",
    "addr:postcode":"m8w 4h6",
    "iso:country":"CA",
    "sg:city":"Etobicoke",
    "sg:classifiers":[
        {
            "category":"Building & Trades",
            "subcategory":"Construction",
            "type":"Services"
        }
    ],
    "sg:phone":"+1 416 252 9070",
    "sg:postcode":"M8W 4H6",
    "sg:province":"ON",
    "sg:tags":[
        "tile",
        "dealer"
    ],
    "wof:name":"Arc Tile Contractors CO",
    "wof:placetype":"venue"
},
  "geometry": {"coordinates":[-79.53973388670001,43.6057434082],"type":"Point"}
}