{
  "type": "Feature",
  "properties": {
    "addr:full":"3169 Petawawa Blvd Petawawa ON K8H 1X9",
    "addr:housenumber":"3169",
    "addr:postcode":"k8h 1x9",
    "addr:street":"Petawawa Blvd",
    "iso:country":"CA",
    "sg:address":"3169 Petawawa Blvd",
    "sg:city":"Petawawa",
    "sg:classifiers":[
        {
            "category":"Retail",
            "subcategory":"Auto Repair",
            "type":"Services"
        }
    ],
    "sg:phone":"+1 613 687 6536",
    "sg:postcode":"K8H 1X9",
    "sg:province":"ON",
    "sg:tags":[
        "repairing",
        "automobile"
    ],
    "wof:name":"Red's Garage",
    "wof:placetype":"venue"
},
  "geometry": {"coordinates":[-77.268349,45.891953],"type":"Point"}
}