{
  "type": "Feature",
  "properties": {
    "addr:full":"815 Rue Mccaffrey Saint-Laurent QC H4T 1N3",
    "addr:housenumber":"815",
    "addr:postcode":"h4t 1n3",
    "addr:street":"Rue Mccaffrey",
    "iso:country":"CA",
    "sg:address":"815 Rue Mccaffrey",
    "sg:city":"Saint-Laurent",
    "sg:classifiers":[
        {
            "category":"Manufacturing",
            "subcategory":"Printing",
            "type":"Manufacturing & Wholesale Goods"
        }
    ],
    "sg:phone":"+1 514 343 5513",
    "sg:postcode":"H4T 1N3",
    "sg:province":"QC",
    "sg:tags":[
        "printer"
    ],
    "wof:name":"Imprimerie Ke Inc",
    "wof:placetype":"venue"
},
  "geometry": {"coordinates":[-73.710899353,45.4871406555],"type":"Point"}
}