{
  "type": "Feature",
  "properties": {
    "addr:full":"Quebec QC G1P 4M3",
    "addr:postcode":"g1p 4m3",
    "iso:country":"CA",
    "sg:city":"Quebec",
    "sg:classifiers":[
        {
            "category":"Wholesale",
            "subcategory":"Machinery & Supplies",
            "type":"Manufacturing & Wholesale Goods"
        }
    ],
    "sg:phone":"+1 418 877 1833",
    "sg:postcode":"G1P 4M3",
    "sg:province":"QC",
    "sg:tags":[
        "crane",
        "derrick"
    ],
    "wof:name":"Kone Crane Canada Inc",
    "wof:placetype":"venue"
},
  "geometry": {"coordinates":[-71.3040390015,46.8048286438],"type":"Point"}
}