{
  "type": "Feature",
  "properties": {
    "addr:full":"510 Brudell Rd Saskatoon SK S7J 5G4",
    "addr:housenumber":"510",
    "addr:postcode":"s7j 5g4",
    "addr:street":"Brudell Rd",
    "iso:country":"CA",
    "sg:address":"510 Brudell Rd",
    "sg:city":"Saskatoon",
    "sg:classifiers":[
        {
            "category":"Building & Trades",
            "subcategory":"Electrical",
            "type":"Services"
        }
    ],
    "sg:phone":"+1 306 221 8940",
    "sg:postcode":"S7J 5G4",
    "sg:province":"SK",
    "sg:tags":[
        "electric",
        "contractor"
    ],
    "wof:name":"Inter-City Electric Ltd",
    "wof:placetype":"venue"
},
  "geometry": {"coordinates":[-106.575272,52.099083],"type":"Point"}
}