{
  "type": "Feature",
  "properties": {
    "addr:full":"8620 120 St Surrey BC V3W 3N6",
    "addr:housenumber":"8620",
    "addr:postcode":"v3w 3n6",
    "addr:street":"120 St",
    "iso:country":"CA",
    "sg:address":"8620 120 St",
    "sg:city":"Surrey",
    "sg:classifiers":[
        {
            "category":"Health Services",
            "subcategory":"Health Practitioner",
            "type":"Services"
        }
    ],
    "sg:phone":"+1 604 590 2804",
    "sg:postcode":"V3W 3N6",
    "sg:province":"BC",
    "sg:tags":[
        "physiotherapist",
        "rehabilitation"
    ],
    "wof:name":"Scott-Navarro Physiotherapy",
    "wof:placetype":"venue"
},
  "geometry": {"coordinates":[-122.890236,49.160183],"type":"Point"}
}