{
  "type": "Feature",
  "properties": {
    "addr:full":"128 Rg Riviere Nord Saint-Esprit QC J0K 2L0",
    "addr:housenumber":"128 rg",
    "addr:postcode":"j0k 2l0",
    "addr:street":"Riviere Nord",
    "iso:country":"CA",
    "sg:address":"128 Rg Riviere Nord",
    "sg:city":"Saint-Esprit",
    "sg:classifiers":[
        {
            "category":"Freight",
            "type":"Transportation"
        }
    ],
    "sg:phone":"+1 450 839 6612",
    "sg:postcode":"J0K 2L0",
    "sg:province":"QC",
    "sg:tags":[
        "trucking"
    ],
    "wof:name":"Excavation Transport Syl-20",
    "wof:placetype":"venue"
},
  "geometry": {"coordinates":[-73.622345,45.900917],"type":"Point"}
}