{
  "type": "Feature",
  "properties": {
    "addr:full":"27302 Fraser Hwy Aldergrove BC V4W 3P8",
    "addr:housenumber":"27302",
    "addr:postcode":"v4w 3p8",
    "addr:street":"Fraser Hwy",
    "iso:country":"CA",
    "sg:address":"27302 Fraser Hwy",
    "sg:city":"Aldergrove",
    "sg:classifiers":[
        {
            "category":"Personal",
            "subcategory":"Beauty Salon",
            "type":"Services"
        }
    ],
    "sg:phone":"+1 604 856 7161",
    "sg:postcode":"V4W 3P8",
    "sg:province":"BC",
    "wof:name":"Basically Hair Ltd",
    "wof:placetype":"venue"
},
  "geometry": {"coordinates":[-122.468102,49.057777],"type":"Point"}
}