{
  "type": "Feature",
  "properties": {
    "addr:full":"2881 111 Rte E Amos QC J9T 3A1",
    "addr:housenumber":"2881",
    "addr:postcode":"j9t 3a1",
    "addr:street":"111 Rte E Amos",
    "iso:country":"CA",
    "sg:address":"2881 111 Rte E",
    "sg:city":"Amos",
    "sg:classifiers":[
        {
            "category":"Travel",
            "subcategory":"Hotels & Motels",
            "type":"Entertainment"
        }
    ],
    "sg:phone":"+1 819 732 1627",
    "sg:postcode":"J9T 3A1",
    "sg:province":"QC",
    "wof:name":"Motel Le Crepuscule",
    "wof:placetype":"venue"
},
  "geometry": {"coordinates":[-78.079567,48.560398],"type":"Point"}
}