{
  "type": "Feature",
  "properties": {
    "addr:full":"Red Deer AB T4P 1M2",
    "addr:postcode":"t4p 1m2",
    "iso:country":"CA",
    "sg:city":"Red Deer",
    "sg:classifiers":[
        {
            "category":"Manufacturing",
            "subcategory":"Tools & Machinery",
            "type":"Manufacturing & Wholesale Goods"
        }
    ],
    "sg:phone":"+1 403 346 6476",
    "sg:postcode":"T4P 1M2",
    "sg:province":"AB",
    "sg:tags":[
        "equipment",
        "oil",
        "well",
        "supply"
    ],
    "wof:name":"Fil-Trek Corp",
    "wof:placetype":"venue"
},
  "geometry": {"coordinates":[-113.813828,52.288502],"type":"Point"}
}