{
  "type": "Feature",
  "properties": {
    "addr:full":"Calgary AB T2A 2K2",
    "addr:postcode":"t2a 2k2",
    "iso:country":"CA",
    "sg:city":"Calgary",
    "sg:classifiers":[
        {
            "category":"Shopping",
            "subcategory":"Gifts & Souvenirs",
            "type":"Retail Goods"
        }
    ],
    "sg:phone":"+1 403 272 1022",
    "sg:postcode":"T2A 2K2",
    "sg:province":"AB",
    "sg:tags":[
        "shop"
    ],
    "wof:name":"Loonie Plus Store",
    "wof:placetype":"venue"
},
  "geometry": {"coordinates":[-113.979934692,51.0525283813],"type":"Point"}
}