{
  "type": "Feature",
  "properties": {
    "addr:full":"Pembroke ON K8A 5R4",
    "addr:postcode":"k8a 5r4",
    "iso:country":"CA",
    "sg:city":"Pembroke",
    "sg:classifiers":[
        {
            "category":"Autos & Motor Vehicles",
            "subcategory":"Automobile Sales",
            "type":"Retail Goods"
        }
    ],
    "sg:phone":"+1 613 735 5879",
    "sg:postcode":"K8A 5R4",
    "sg:province":"ON",
    "sg:tags":[
        "car",
        "dealer"
    ],
    "wof:name":"Bill Premo Auto Sales",
    "wof:placetype":"venue"
},
  "geometry": {"coordinates":[-77.142319,45.831116],"type":"Point"}
}