{
  "type": "Feature",
  "properties": {
    "addr:full":"521 Boul Saint-Joseph E Montreal QC H2J 1K1",
    "addr:housenumber":"521",
    "addr:postcode":"h2j 1k1",
    "addr:street":"Boul Saint-Joseph E",
    "iso:country":"CA",
    "sg:address":"521 Boul Saint-Joseph E",
    "sg:city":"Montreal",
    "sg:classifiers":[
        {
            "category":"Health Services",
            "subcategory":"Health Practitioner",
            "type":"Services"
        }
    ],
    "sg:phone":"+1 514 288 2457",
    "sg:postcode":"H2J 1K1",
    "sg:province":"QC",
    "sg:tags":[
        "psychologist"
    ],
    "wof:name":"Campion, Nicole",
    "wof:placetype":"venue"
},
  "geometry": {"coordinates":[-73.586899,45.527611],"type":"Point"}
}