{
  "type": "Feature",
  "properties": {
    "addr:full":"231 Wellington St London ON N6B 2L2",
    "addr:housenumber":"231",
    "addr:postcode":"n6b 2l2",
    "addr:street":"Wellington St",
    "iso:country":"CA",
    "sg:address":"231 Wellington St",
    "sg:city":"London",
    "sg:classifiers":[
        {
            "category":"Education",
            "subcategory":"School",
            "type":"Public Place"
        }
    ],
    "sg:phone":"+1 519 471 3187",
    "sg:postcode":"N6B 2L2",
    "sg:province":"ON",
    "sg:tags":[
        "instruction",
        "driving"
    ],
    "wof:name":"Western Driving Academy",
    "wof:placetype":"venue"
},
  "geometry": {"coordinates":[-81.2427444458,42.9795875549],"type":"Point"}
}