{
  "type": "Feature",
  "properties": {
    "addr:full":"900 Jalna Blvd London ON N6E 3A4",
    "addr:housenumber":"900",
    "addr:postcode":"n6e 3a4",
    "addr:street":"Jalna Blvd",
    "iso:country":"CA",
    "sg:address":"900 Jalna Blvd",
    "sg:city":"London",
    "sg:classifiers":[
        {
            "category":"Health Services",
            "subcategory":"Health Practitioner",
            "type":"Services"
        }
    ],
    "sg:phone":"+1 519 641 6625",
    "sg:postcode":"N6E 3A4",
    "sg:province":"ON",
    "sg:tags":[
        "physiotherapist"
    ],
    "wof:name":"Body Mechanics Physiotherapy",
    "wof:placetype":"venue"
},
  "geometry": {"coordinates":[-81.2388305664,42.9414138794],"type":"Point"}
}