{
  "type": "Feature",
  "properties": {
    "iso:country":"CA",
    "sg:address":"180 Station St",
    "sg:city":"Ajax",
    "sg:classifiers":[
        {
            "category":"Utilities",
            "type":"Services"
        }
    ],
    "sg:phone":"+1 905 852 0766",
    "sg:postcode":"L1S 1R9",
    "sg:province":"ON",
    "sg:tags":[
        "sweeping"
    ],
    "wof:name":"Hanntech Power Sweeping",
    "wof:placetype":"venue"
},
  "geometry": {"coordinates":[-79.02838897709999,43.8500137329],"type":"Point"}
}