{
  "type": "Feature",
  "properties": {
    "addr:full":"162 Robbinstone Dr Scarborough ON M1B 2E7",
    "addr:housenumber":"162",
    "addr:postcode":"m1b 2e7",
    "addr:street":"Robbinstone Dr",
    "iso:country":"CA",
    "sg:address":"162 Robbinstone Dr",
    "sg:city":"Scarborough",
    "sg:classifiers":[
        {
            "category":"Professional",
            "subcategory":"Computer Services",
            "type":"Services"
        }
    ],
    "sg:phone":"+1 416 293 7852",
    "sg:postcode":"M1B 2E7",
    "sg:province":"ON",
    "sg:tags":[
        "consultant"
    ],
    "wof:name":"Imareal Technologies",
    "wof:placetype":"venue"
},
  "geometry": {"coordinates":[-79.23835800000001,43.798794],"type":"Point"}
}