{
  "type": "Feature",
  "properties": {
    "addr:full":"43 Rue Du Roi Sorel-Tracy QC J3P 4M6",
    "addr:housenumber":"43",
    "addr:postcode":"j3p 4m6",
    "addr:street":"Rue Du Roi",
    "iso:country":"CA",
    "sg:address":"43 Rue Du Roi",
    "sg:city":"Sorel-Tracy",
    "sg:classifiers":[
        {
            "category":"Wholesale",
            "subcategory":"Machinery & Supplies",
            "type":"Manufacturing & Wholesale Goods"
        }
    ],
    "sg:phone":"+1 450 743 5268",
    "sg:postcode":"J3P 4M6",
    "sg:province":"QC",
    "sg:tags":[
        "equipment",
        "safety",
        "clothing"
    ],
    "wof:name":"Eloi Dore Inc",
    "wof:placetype":"venue"
},
  "geometry": {"coordinates":[-73.116287,46.0448],"type":"Point"}
}