{
  "type": "Feature",
  "properties": {
    "addr:full":"209 Yale Ave W Winnipeg MB R2C 1T9",
    "addr:housenumber":"209",
    "addr:postcode":"r2c 1t9",
    "addr:street":"Yale Ave W",
    "iso:country":"CA",
    "sg:address":"209 Yale Ave W",
    "sg:city":"Winnipeg",
    "sg:classifiers":[
        {
            "category":"Social Services",
            "subcategory":"Child Care",
            "type":"Services"
        }
    ],
    "sg:phone":"+1 204 222 0390",
    "sg:postcode":"R2C 1T9",
    "sg:province":"MB",
    "wof:name":"Children's Choice Nursery Schl",
    "wof:placetype":"venue"
},
  "geometry": {"coordinates":[-97.00592,49.896889],"type":"Point"}
}