{
  "type": "Feature",
  "properties": {
    "addr:full":"404 50th St Saddle Lake AB T0A 3T0",
    "addr:housenumber":"404",
    "addr:postcode":"t0a 3t0",
    "addr:street":"50Th St",
    "iso:country":"CA",
    "sg:address":"404 50th St",
    "sg:city":"Saddle Lake",
    "sg:classifiers":[
        {
            "category":"Recreation",
            "type":"Entertainment"
        }
    ],
    "sg:phone":"+1 780 726 2828",
    "sg:postcode":"T0A 3T0",
    "sg:province":"AB",
    "sg:tags":[
        "hall",
        "auditorium"
    ],
    "wof:name":"Ayiwakes Cultural Ctr",
    "wof:placetype":"venue"
},
  "geometry": {"coordinates":[-111.699997,54.002914],"type":"Point"}
}