{
  "type": "Feature",
  "properties": {
    "iso:country":"CA",
    "sg:address":"4713 Route 134",
    "sg:city":"Cocagne",
    "sg:classifiers":[
        {
            "category":"Food & Beverages",
            "subcategory":"Specialty",
            "type":"Retail Goods"
        }
    ],
    "sg:phone":"+1 506 576 0714",
    "sg:postcode":"E4R 2Y1",
    "sg:province":"NB",
    "sg:tags":[
        "health",
        "diet"
    ],
    "wof:name":"Angel's Nutri-Clinic",
    "wof:placetype":"venue"
},
  "geometry": {"coordinates":[-64.6198272705,46.3403816223],"type":"Point"}
}