{
  "type": "Feature",
  "properties": {
    "addr:full":"14821 Ninth Line Stouffville ON L4A 7X3",
    "addr:housenumber":"14821",
    "addr:postcode":"l4a 7x3",
    "addr:street":"Ninth Line",
    "iso:country":"CA",
    "sg:address":"14821 Ninth Line",
    "sg:city":"Stouffville",
    "sg:classifiers":[
        {
            "category":"Home & Garden",
            "subcategory":"Building Materials",
            "type":"Retail Goods"
        }
    ],
    "sg:phone":"+1 905 642 0400",
    "sg:postcode":"L4A 7X3",
    "sg:province":"ON",
    "sg:tags":[
        "door"
    ],
    "wof:name":"Suncoast Sales Ltd",
    "wof:placetype":"venue"
},
  "geometry": {"coordinates":[-79.26670799999999,44.032497],"type":"Point"}
}