{
  "type": "Feature",
  "properties": {
    "addr:full":"18 Park Ave Lac Du Bonnet MB R0E 1A0",
    "addr:housenumber":"18",
    "addr:postcode":"r0e 1a0",
    "addr:street":"Park Ave",
    "iso:country":"CA",
    "sg:address":"18 Park Ave",
    "sg:city":"Lac Du Bonnet",
    "sg:classifiers":[
        {
            "category":"Shopping",
            "subcategory":"Florist",
            "type":"Retail Goods"
        }
    ],
    "sg:phone":"+1 204 345 9450",
    "sg:postcode":"R0E 1A0",
    "sg:province":"MB",
    "wof:name":"Carnation Corner Plus",
    "wof:placetype":"venue"
},
  "geometry": {"coordinates":[-96.05903600000001,50.258011],"type":"Point"}
}