{
  "type": "Feature",
  "properties": {
    "iso:country":"CA",
    "sg:address":"12807 53 St NW",
    "sg:city":"Edmonton",
    "sg:classifiers":[
        {
            "category":"Wholesale",
            "subcategory":"Scrap",
            "type":"Manufacturing & Wholesale Goods"
        }
    ],
    "sg:phone":"+1 780 476 1841",
    "sg:postcode":"T5A 4J6",
    "sg:province":"AB",
    "sg:tags":[
        "recycling",
        "can",
        "bottle",
        "depot"
    ],
    "wof:name":"Clareview Bottle Drop Ltd",
    "wof:placetype":"venue"
},
  "geometry": {"coordinates":[-113.42276,53.5863],"type":"Point"}
}