{
  "type": "Feature",
  "properties": {
    "addr:full":"White Rock BC V4B 3Z4",
    "addr:postcode":"v4b 3z4",
    "iso:country":"CA",
    "sg:city":"White Rock",
    "sg:classifiers":[
        {
            "category":"Insurance",
            "subcategory":"Insurance Agent",
            "type":"Services"
        }
    ],
    "sg:phone":"+1 604 538 8833",
    "sg:postcode":"V4B 3Z4",
    "sg:province":"BC",
    "wof:name":"Koch B & Y Insurance Svc Ltd",
    "wof:placetype":"venue"
},
  "geometry": {"coordinates":[-122.801338,49.028599],"type":"Point"}
}