{
  "type": "Feature",
  "properties": {
    "iso:country":"CA",
    "sg:address":"7195 Highway 9",
    "sg:city":"Schomberg",
    "sg:classifiers":[
        {
            "category":"Retail",
            "subcategory":"Repair Shop",
            "type":"Services"
        }
    ],
    "sg:phone":"+1 905 939 2810",
    "sg:postcode":"L0G 1T0",
    "sg:province":"ON",
    "sg:tags":[
        "upholsterer"
    ],
    "wof:name":"R & R Upholstery",
    "wof:placetype":"venue"
},
  "geometry": {"coordinates":[-79.6841049194,44.0028152466],"type":"Point"}
}