{
  "type": "Feature",
  "properties": {
    "addr:full":"200 Locke St S Hamilton ON L8P 4B4",
    "addr:housenumber":"200",
    "addr:postcode":"l8p 4b4",
    "addr:street":"Locke St S",
    "iso:country":"CA",
    "sg:address":"200 Locke St S",
    "sg:city":"Hamilton",
    "sg:classifiers":[
        {
            "category":"Shopping",
            "subcategory":"Used Merchandise",
            "type":"Retail Goods"
        }
    ],
    "sg:phone":"+1 905 526 6553",
    "sg:postcode":"L8P 4B4",
    "sg:province":"ON",
    "sg:tags":[
        "antique"
    ],
    "wof:name":"Locke Street Antiques",
    "wof:placetype":"venue"
},
  "geometry": {"coordinates":[-79.8860778809,43.2548027039],"type":"Point"}
}