{
  "type": "Feature",
  "properties": {
    "addr:full":"586 Berford St Wiarton ON N0H 2T0",
    "addr:housenumber":"586",
    "addr:postcode":"n0h 2t0",
    "addr:street":"Berford St",
    "iso:country":"CA",
    "sg:address":"586 Berford St",
    "sg:city":"Wiarton",
    "sg:classifiers":[
        {
            "category":"Shopping",
            "subcategory":"Books",
            "type":"Retail Goods"
        }
    ],
    "sg:phone":"+1 519 534 3219",
    "sg:postcode":"N0H 2T0",
    "sg:province":"ON",
    "sg:tags":[
        "dealer"
    ],
    "wof:name":"Vision Christian Books & Gifts",
    "wof:placetype":"venue"
},
  "geometry": {"coordinates":[-81.141052,44.74287],"type":"Point"}
}