{
  "type": "Feature",
  "properties": {
    "iso:country":"CA",
    "sg:address":"755 Boul Rene-Levesque",
    "sg:city":"Drummondville",
    "sg:classifiers":[
        {
            "category":"Shopping",
            "subcategory":"Jewelry",
            "type":"Retail Goods"
        }
    ],
    "sg:phone":"+1 819 478 8844",
    "sg:postcode":"J2C 6Y7",
    "sg:province":"QC",
    "sg:tags":[
        "watch"
    ],
    "wof:name":"Boutique Timing",
    "wof:placetype":"venue"
},
  "geometry": {"coordinates":[-72.515709,45.89925],"type":"Point"}
}