{
  "type": "Feature",
  "properties": {
    "iso:country":"CA",
    "sg:address":"7250 Market St",
    "sg:city":"Port Hardy",
    "sg:classifiers":[
        {
            "category":"Professional",
            "subcategory":"Business Services",
            "type":"Services"
        }
    ],
    "sg:phone":"+1 250 949 7622",
    "sg:postcode":"V0N 2P0",
    "sg:province":"BC",
    "sg:tags":[
        "information",
        "referral"
    ],
    "wof:name":"Chamber of Commerce",
    "wof:placetype":"venue"
},
  "geometry": {"coordinates":[-127.492363,50.723522],"type":"Point"}
}