{
  "type": "Feature",
  "properties": {
    "addr:full":"9549 Boul Gouin O Pierrefonds QC H8Y 1R2",
    "addr:housenumber":"9549",
    "addr:postcode":"h8y 1r2",
    "addr:street":"Boul Gouin O",
    "iso:country":"CA",
    "sg:address":"9549 Boul Gouin O",
    "sg:city":"Pierrefonds",
    "sg:classifiers":[
        {
            "category":"Food & Beverages",
            "subcategory":"Groceries & Convenience Stores",
            "type":"Retail Goods"
        }
    ],
    "sg:phone":"+1 514 683 0018",
    "sg:postcode":"H8Y 1R2",
    "sg:province":"QC",
    "sg:tags":[
        "grocer"
    ],
    "wof:name":"100 Miracles",
    "wof:placetype":"venue"
},
  "geometry": {"coordinates":[-73.779343,45.504364],"type":"Point"}
}