{
  "type": "Feature",
  "properties": {
    "addr:full":"79 Huron St Ripley ON N0G 2R0",
    "addr:housenumber":"79",
    "addr:postcode":"n0g 2r0",
    "addr:street":"Huron St",
    "iso:country":"CA",
    "sg:address":"79 Huron St",
    "sg:city":"Ripley",
    "sg:classifiers":[
        {
            "category":"Food & Beverages",
            "subcategory":"Groceries & Convenience Stores",
            "type":"Retail Goods"
        }
    ],
    "sg:phone":"+1 519 395 3700",
    "sg:postcode":"N0G 2R0",
    "sg:province":"ON",
    "sg:tags":[
        "grocer"
    ],
    "wof:name":"Mac Adam's Mini Mart",
    "wof:placetype":"venue"
},
  "geometry": {"coordinates":[-81.5788192749,44.0708656311],"type":"Point"}
}