{
  "type": "Feature",
  "properties": {
    "iso:country":"CA",
    "sg:address":"1856 Boul Marie-Victorin",
    "sg:city":"Longueuil",
    "sg:classifiers":[
        {
            "category":"Wholesale",
            "subcategory":"Machinery & Supplies",
            "type":"Manufacturing & Wholesale Goods"
        }
    ],
    "sg:phone":"+1 450 679 2221",
    "sg:postcode":"J4G 1Y9",
    "sg:province":"QC",
    "sg:tags":[
        "heat",
        "exchanger"
    ],
    "wof:name":"Air P 8000",
    "wof:placetype":"venue"
},
  "geometry": {"coordinates":[-73.484795,45.570602],"type":"Point"}
}