{
  "type": "Feature",
  "properties": {
    "addr:full":"61 Barton St E Hamilton ON L8L 2V7",
    "addr:housenumber":"61",
    "addr:postcode":"l8l 2v7",
    "addr:street":"Barton St E",
    "iso:country":"CA",
    "sg:address":"61 Barton St E",
    "sg:city":"Hamilton",
    "sg:classifiers":[
        {
            "category":"Restaurant",
            "type":"Food & Drink"
        }
    ],
    "sg:phone":"+1 905 527 7918",
    "sg:postcode":"L8L 2V7",
    "sg:province":"ON",
    "sg:tags":[
        "pizza"
    ],
    "wof:name":"Mattina Pizzeria",
    "wof:placetype":"venue"
},
  "geometry": {"coordinates":[-79.86331199999999,43.263557],"type":"Point"}
}