{
  "type": "Feature",
  "properties": {
    "addr:full":"27 Rue Notre-Dame Riviere-Eternite QC G0V 1P0",
    "addr:housenumber":"27",
    "addr:postcode":"g0v 1p0",
    "addr:street":"Rue Notre-Dame Riviere-Eternite",
    "iso:country":"CA",
    "sg:address":"27 Rue Notre-Dame",
    "sg:city":"Riviere-Eternite",
    "sg:classifiers":[
        {
            "category":"Personal",
            "subcategory":"Beauty Salon",
            "type":"Services"
        }
    ],
    "sg:phone":"+1 418 272 3220",
    "sg:postcode":"G0V 1P0",
    "sg:province":"QC",
    "wof:name":"Salon Manon",
    "wof:placetype":"venue"
},
  "geometry": {"coordinates":[-70.411827,48.256729],"type":"Point"}
}