{
  "type": "Feature",
  "properties": {
    "addr:full":"675 College St Toronto ON M6G 1B9",
    "addr:housenumber":"675",
    "addr:postcode":"m6g 1b9",
    "addr:street":"College St",
    "iso:country":"CA",
    "sg:address":"675 College St",
    "sg:city":"Toronto",
    "sg:classifiers":[
        {
            "category":"Shopping",
            "subcategory":"Clothing, Apparel, & Fashions",
            "type":"Retail Goods"
        }
    ],
    "sg:phone":"+1 416 534 0088",
    "sg:postcode":"M6G 1B9",
    "sg:province":"ON",
    "wof:name":"Jasmine Boutique",
    "wof:placetype":"venue"
},
  "geometry": {"coordinates":[-79.4172668457,43.6550750732],"type":"Point"}
}