{
  "type": "Feature",
  "properties": {
    "addr:full":"1043 Rue Du Parc-Industriel Saint-Jean-Chrysostome QC G6Z 1C5",
    "addr:housenumber":"1043",
    "addr:postcode":"g6z 1c5",
    "addr:street":"Rue Du Parc-Industriel Saint-Jean-Chrysostome",
    "iso:country":"CA",
    "sg:address":"1043 Rue Du Parc-Industriel",
    "sg:city":"Saint-Jean-Chrysostome",
    "sg:classifiers":[
        {
            "category":"Retail",
            "subcategory":"Auto Repair",
            "type":"Services"
        }
    ],
    "sg:phone":"+1 418 834 3133",
    "sg:postcode":"G6Z 1C5",
    "sg:province":"QC",
    "sg:tags":[
        "bus"
    ],
    "wof:name":"Autobus LA Quebecoise",
    "wof:placetype":"venue"
},
  "geometry": {"coordinates":[-71.211861,46.730701],"type":"Point"}
}