{
  "type": "Feature",
  "properties": {
    "addr:full":"204 Rue Jacques-Cartier Salaberry-DE-Valleyfield QC J6T 4S5",
    "addr:housenumber":"204",
    "addr:postcode":"j6t 4s5",
    "addr:street":"Rue Jacques-Cartier",
    "iso:country":"CA",
    "sg:address":"204 Rue Jacques-Cartier",
    "sg:city":"Salaberry-DE-Valleyfield",
    "sg:classifiers":[
        {
            "category":"Freight",
            "type":"Transportation"
        }
    ],
    "sg:phone":"+1 450 371 1307",
    "sg:postcode":"J6T 4S5",
    "sg:province":"QC",
    "sg:tags":[
        "trucking"
    ],
    "wof:name":"Transport Andre Leroux Inc",
    "wof:placetype":"venue"
},
  "geometry": {"coordinates":[-74.124359,45.248299],"type":"Point"}
}