{
  "type": "Feature",
  "properties": {
    "addr:full":"25 Rue Webster Saint-Lambert QC J4P 1W9",
    "addr:housenumber":"25",
    "addr:postcode":"j4p 1w9",
    "addr:street":"Rue Webster",
    "iso:country":"CA",
    "sg:address":"25 Rue Webster",
    "sg:city":"Saint-Lambert",
    "sg:classifiers":[
        {
            "category":"Shopping",
            "subcategory":"Books",
            "type":"Retail Goods"
        }
    ],
    "sg:phone":"+1 450 465 5597",
    "sg:postcode":"J4P 1W9",
    "sg:province":"QC",
    "sg:tags":[
        "dealer"
    ],
    "wof:name":"Librairie Le Fureteur Inc",
    "wof:placetype":"venue"
},
  "geometry": {"coordinates":[-73.50897999999999,45.501205],"type":"Point"}
}