{
  "type": "Feature",
  "properties": {
    "addr:full":"185 16th Ave E Vancouver BC V5T 4R2",
    "addr:housenumber":"185",
    "addr:postcode":"v5t 4r2",
    "addr:street":"16Th Ave E",
    "iso:country":"CA",
    "sg:address":"185 16th Ave E",
    "sg:city":"Vancouver",
    "sg:classifiers":[
        {
            "category":"Shopping",
            "subcategory":"Clothing, Apparel, & Fashions",
            "type":"Retail Goods"
        }
    ],
    "sg:phone":"+1 604 708 4166",
    "sg:postcode":"V5T 4R2",
    "sg:province":"BC",
    "sg:tags":[
        "infant",
        "wear"
    ],
    "wof:name":"Pagasa Childrens Wear",
    "wof:placetype":"venue"
},
  "geometry": {"coordinates":[-123.101585,49.256752],"type":"Point"}
}