{
  "type": "Feature",
  "properties": {
    "addr:full":"5526 Kingsway Burnaby BC V5H 2G2",
    "addr:housenumber":"5526",
    "addr:postcode":"v5h 2g2",
    "addr:street":"Kingsway",
    "iso:country":"CA",
    "sg:address":"5526 Kingsway",
    "sg:city":"Burnaby",
    "sg:classifiers":[
        {
            "category":"Building & Trades",
            "subcategory":"Construction",
            "type":"Services"
        }
    ],
    "sg:phone":"+1 604 430 2303",
    "sg:postcode":"V5H 2G2",
    "sg:province":"BC",
    "sg:tags":[
        "contractor",
        "waterproofing",
        "general"
    ],
    "wof:name":"B C Restorations Ltd",
    "wof:placetype":"venue"
},
  "geometry": {"coordinates":[-122.98440600000001,49.223454],"type":"Point"}
}