{
  "type": "Feature",
  "properties": {
    "addr:full":"7 Ch Du Lac-Des-Pins Ste-Famille-D'Aumond QC J0W 1W0",
    "addr:housenumber":"7",
    "addr:postcode":"j0w 1w0",
    "addr:street":"Ch Du Lac-Des-Pins Ste-Famille-D'Aumond",
    "iso:country":"CA",
    "sg:address":"7 Ch Du Lac-Des-Pins",
    "sg:city":"Ste-Famille-D'Aumond",
    "sg:classifiers":[
        {
            "category":"Home & Garden",
            "subcategory":"Garden Supply",
            "type":"Retail Goods"
        }
    ],
    "sg:phone":"+1 819 449 5909",
    "sg:postcode":"J0W 1W0",
    "sg:province":"QC",
    "sg:tags":[
        "nurseryman"
    ],
    "wof:name":"Planford",
    "wof:placetype":"venue"
},
  "geometry": {"coordinates":[-75.823639,46.477886],"type":"Point"}
}