{
  "type": "Feature",
  "properties": {
    "addr:full":"1085 Main St Sussex Corner NB E4E 3A1",
    "addr:housenumber":"1085",
    "addr:postcode":"e4e 3a1",
    "addr:street":"Main St",
    "iso:country":"CA",
    "sg:address":"1085 Main St",
    "sg:city":"Sussex Corner",
    "sg:classifiers":[
        {
            "category":"Education",
            "subcategory":"Special Training",
            "type":"Public Place"
        }
    ],
    "sg:phone":"+1 506 432 6299",
    "sg:postcode":"E4E 3A1",
    "sg:province":"NB",
    "sg:tags":[
        "instruction",
        "driving"
    ],
    "wof:name":"First Time Driver Education",
    "wof:placetype":"venue"
},
  "geometry": {"coordinates":[-65.4879684448,45.7143363953],"type":"Point"}
}