{
  "type": "Feature",
  "properties": {
    "iso:country":"CA",
    "sg:address":"861 Medway Park Crt # 1",
    "sg:city":"London",
    "sg:classifiers":[
        {
            "category":"Manufacturing",
            "subcategory":"Metals",
            "type":"Manufacturing & Wholesale Goods"
        }
    ],
    "sg:phone":"+1 519 641 7663",
    "sg:postcode":"N6G 5C7",
    "sg:province":"ON",
    "sg:tags":[
        "roofing",
        "contractor",
        "copper",
        "fabricator"
    ],
    "wof:name":"Davidoff Roofing Ltd",
    "wof:placetype":"venue"
},
  "geometry": {"coordinates":[-81.313393,43.021648],"type":"Point"}
}