{
  "type": "Feature",
  "properties": {
    "iso:country":"CA",
    "sg:address":"465 Highland Rd W",
    "sg:city":"Kitchener",
    "sg:classifiers":[
        {
            "category":"Cinema",
            "subcategory":"Movie Rental",
            "type":"Entertainment"
        }
    ],
    "sg:phone":"+1 519 570 2374",
    "sg:postcode":"N2M 3C6",
    "sg:province":"ON",
    "sg:tags":[
        "leasing",
        "video",
        "disc",
        "tape"
    ],
    "wof:name":"Rogers Video",
    "wof:placetype":"venue"
},
  "geometry": {"coordinates":[-80.513557,43.436043],"type":"Point"}
}