{
  "type": "Feature",
  "properties": {
    "addr:full":"38 King St W Cobourg ON K9A 2L9",
    "addr:housenumber":"38",
    "addr:postcode":"k9a 2l9",
    "addr:street":"King St W",
    "iso:country":"CA",
    "sg:address":"38 King St W",
    "sg:city":"Cobourg",
    "sg:classifiers":[
        {
            "category":"Shopping",
            "subcategory":"Used Merchandise",
            "type":"Retail Goods"
        }
    ],
    "sg:phone":"+1 905 372 3027",
    "sg:postcode":"K9A 2L9",
    "sg:province":"ON",
    "sg:tags":[
        "shop",
        "consignment"
    ],
    "wof:name":"Twice As Nice",
    "wof:placetype":"venue"
},
  "geometry": {"coordinates":[-78.1670227051,43.9598197937],"type":"Point"}
}