{
  "type": "Feature",
  "properties": {
    "addr:full":"3304 8 Ave NE Calgary AB T2A 7H3",
    "addr:housenumber":"3304",
    "addr:postcode":"t2a 7h3",
    "addr:street":"8 Ave Ne",
    "iso:country":"CA",
    "sg:address":"3304 8 Ave NE",
    "sg:city":"Calgary",
    "sg:classifiers":[
        {
            "category":"Autos & Motor Vehicles",
            "subcategory":"Fuel & Gas Station",
            "type":"Retail Goods"
        }
    ],
    "sg:phone":"+1 403 272 4944",
    "sg:postcode":"T2A 7H3",
    "sg:province":"AB",
    "sg:tags":[
        "polishing",
        "car",
        "oil",
        "washing"
    ],
    "wof:name":"Franklin Husky U-Wash Car Wash",
    "wof:placetype":"venue"
},
  "geometry": {"coordinates":[-113.986755371,51.0596809387],"type":"Point"}
}