{
  "type": "Feature",
  "properties": {
    "addr:full":"PO Box 149 Pilger SK S0K 3G0",
    "addr:housenumber":"po",
    "addr:postcode":"s0k 3g0",
    "addr:street":"Box 149 Pilger",
    "iso:country":"CA",
    "sg:address":"PO Box 149",
    "sg:city":"Pilger",
    "sg:classifiers":[
        {
            "category":"Travel",
            "subcategory":"Hotels & Motels",
            "type":"Entertainment"
        }
    ],
    "sg:phone":"+1 306 367 4700",
    "sg:postcode":"S0K 3G0",
    "sg:province":"SK",
    "wof:name":"Pilger Hotel",
    "wof:placetype":"venue"
},
  "geometry": {"coordinates":[-105.26786,52.42218],"type":"Point"}
}