{
  "type": "Feature",
  "properties": {
    "addr:full":"3340 54th Ave E Vancouver BC V5S 1Z3",
    "addr:housenumber":"3340",
    "addr:postcode":"v5s 1z3",
    "addr:street":"54Th Ave E",
    "iso:country":"CA",
    "sg:address":"3340 54th Ave E",
    "sg:city":"Vancouver",
    "sg:classifiers":[
        {
            "category":"Education",
            "subcategory":"School",
            "type":"Public Place"
        }
    ],
    "sg:phone":"+1 604 713 4828",
    "sg:postcode":"V5S 1Z3",
    "sg:province":"BC",
    "wof:name":"Captain James Cook Elem School",
    "wof:placetype":"venue"
},
  "geometry": {"coordinates":[-123.035736,49.219933],"type":"Point"}
}