{
  "type": "Feature",
  "properties": {
    "addr:full":"255 Barclay Parade SW Calgary AB T2P 5C2",
    "addr:housenumber":"255",
    "addr:postcode":"t2p 5c2",
    "addr:street":"Barclay Parade Sw",
    "iso:country":"CA",
    "sg:address":"255 Barclay Parade SW",
    "sg:city":"Calgary",
    "sg:classifiers":[
        {
            "category":"Restaurant",
            "type":"Food & Drink"
        }
    ],
    "sg:phone":"+1 403 517 6699",
    "sg:postcode":"T2P 5C2",
    "sg:province":"AB",
    "wof:name":"Fionn Mac Cool's Irish Pub",
    "wof:placetype":"venue"
},
  "geometry": {"coordinates":[-114.069649,51.05225],"type":"Point"}
}