{
  "type": "Feature",
  "properties": {
    "iso:country":"CA",
    "sg:address":"106 Rue Cormier",
    "sg:city":"New Richmond",
    "sg:classifiers":[
        {
            "category":"Retail",
            "subcategory":"Animal Services",
            "type":"Services"
        }
    ],
    "sg:phone":"+1 418 392 6778",
    "sg:postcode":"G0C 2B0",
    "sg:province":"QC",
    "sg:tags":[
        "pet",
        "grooming",
        "washing"
    ],
    "wof:name":"Centre Professionnel Canin",
    "wof:placetype":"venue"
},
  "geometry": {"coordinates":[-65.83605194090001,48.1456871033],"type":"Point"}
}