{
  "type": "Feature",
  "properties": {
    "iso:country":"CA",
    "sg:address":"6150 Boul Sainte-Anne",
    "sg:city":"L'Ange Gardien",
    "sg:classifiers":[
        {
            "category":"Home & Garden",
            "subcategory":"Building Materials",
            "type":"Retail Goods"
        }
    ],
    "sg:phone":"+1 418 822 0643",
    "sg:postcode":"G0A 2K0",
    "sg:province":"QC",
    "sg:tags":[
        "door"
    ],
    "wof:name":"Solaris Quebec Inc",
    "wof:placetype":"venue"
},
  "geometry": {"coordinates":[-72.9380264282,45.357460022],"type":"Point"}
}