{
  "type": "Feature",
  "properties": {
    "addr:full":"3590 Rue Queen Rawdon QC J0K 1S0",
    "addr:housenumber":"3590",
    "addr:postcode":"j0k 1s0",
    "addr:street":"Rue Queen",
    "iso:country":"CA",
    "sg:address":"3590 Rue Queen",
    "sg:city":"Rawdon",
    "sg:classifiers":[
        {
            "category":"Health Services",
            "subcategory":"Medical Lab",
            "type":"Services"
        }
    ],
    "sg:phone":"+1 450 834 2634",
    "sg:postcode":"J0K 1S0",
    "sg:province":"QC",
    "wof:name":"Chalifoux Pierre Rostand",
    "wof:placetype":"venue"
},
  "geometry": {"coordinates":[-73.705124,46.041248],"type":"Point"}
}