{
  "type": "Feature",
  "properties": {
    "addr:full":"14 Hiawatha Pky Mississauga ON L5G 3R8",
    "addr:housenumber":"14",
    "addr:postcode":"l5g 3r8",
    "addr:street":"Hiawatha Pky",
    "iso:country":"CA",
    "sg:address":"14 Hiawatha Pky",
    "sg:city":"Mississauga",
    "sg:classifiers":[
        {
            "category":"Building & Trades",
            "subcategory":"Landscaping Services",
            "type":"Services"
        }
    ],
    "sg:phone":"+1 905 274 9430",
    "sg:postcode":"L5G 3R8",
    "sg:province":"ON",
    "sg:tags":[
        "lawn",
        "maintenance",
        "grounds"
    ],
    "wof:name":"Hiawatha Tree & Lawn",
    "wof:placetype":"venue"
},
  "geometry": {"coordinates":[-79.57484436039999,43.5597496033],"type":"Point"}
}