{
  "type": "Feature",
  "properties": {
    "addr:full":"1524 Albert St Regina SK S4P 2S4",
    "addr:housenumber":"1524",
    "addr:postcode":"s4p 2s4",
    "addr:street":"Albert St",
    "iso:country":"CA",
    "sg:address":"1524 Albert St",
    "sg:city":"Regina",
    "sg:classifiers":[
        {
            "category":"Health Services",
            "subcategory":"Health Practitioner",
            "type":"Services"
        }
    ],
    "sg:phone":"+1 306 522 4995",
    "sg:postcode":"S4P 2S4",
    "sg:province":"SK",
    "sg:tags":[
        "therapist",
        "physical"
    ],
    "wof:name":"Kachur, S",
    "wof:placetype":"venue"
},
  "geometry": {"coordinates":[-104.618431,50.454601],"type":"Point"}
}