{
  "type": "Feature",
  "properties": {
    "iso:country":"CA",
    "sg:address":"255 Broadview Ave",
    "sg:city":"Toronto",
    "sg:classifiers":[
        {
            "category":"Shopping",
            "subcategory":"Pharmacy",
            "type":"Retail Goods"
        }
    ],
    "sg:phone":"+1 416 469 5669",
    "sg:postcode":"M4M 2G6",
    "sg:province":"ON",
    "wof:name":"Jimmy's Pharmacy",
    "wof:placetype":"venue"
},
  "geometry": {"coordinates":[-79.3513412476,43.6629142761],"type":"Point"}
}