{
  "type": "Feature",
  "properties": {
    "addr:full":"207 61 Ave SE Calgary AB T2H 0R4",
    "addr:postcode":"t2h 0r4",
    "addr:street":"207 61 Ave Se",
    "iso:country":"CA",
    "sg:address":"207 61 Ave SE",
    "sg:city":"Calgary",
    "sg:classifiers":[
        {
            "category":"Autos & Motor Vehicles",
            "subcategory":"Automobile Sales",
            "type":"Retail Goods"
        }
    ],
    "sg:phone":"+1 403 255 1899",
    "sg:postcode":"T2H 0R4",
    "sg:province":"AB",
    "sg:tags":[
        "car",
        "dealer"
    ],
    "wof:name":"Lorez Auto Sales",
    "wof:placetype":"venue"
},
  "geometry": {"coordinates":[-114.061806,50.997566],"type":"Point"}
}