{
  "type": "Feature",
  "properties": {
    "iso:country":"CA",
    "sg:address":"10546 105 St NW",
    "sg:city":"Edmonton",
    "sg:classifiers":[
        {
            "category":"Home & Garden",
            "subcategory":"Furniture",
            "type":"Retail Goods"
        }
    ],
    "sg:phone":"+1 780 448 1044",
    "sg:postcode":"T5H 2W7",
    "sg:province":"AB",
    "wof:name":"Envirodesigns Inc",
    "wof:placetype":"venue"
},
  "geometry": {"coordinates":[-113.50138855,53.548740387],"type":"Point"}
}