{
  "type": "Feature",
  "properties": {
    "addr:full":"382 Old Kingston Rd Scarborough ON M1C 1B6",
    "addr:housenumber":"382",
    "addr:postcode":"m1c 1b6",
    "addr:street":"Old Kingston Rd",
    "iso:country":"CA",
    "sg:address":"382 Old Kingston Rd",
    "sg:city":"Scarborough",
    "sg:classifiers":[
        {
            "category":"Home & Garden",
            "subcategory":"Building Materials",
            "type":"Retail Goods"
        }
    ],
    "sg:phone":"+1 416 282 0961",
    "sg:postcode":"M1C 1B6",
    "sg:province":"ON",
    "sg:tags":[
        "paint"
    ],
    "wof:name":"Charles A Bradley & Son Ltd",
    "wof:placetype":"venue"
},
  "geometry": {"coordinates":[-79.17005899999999,43.783855],"type":"Point"}
}