{
  "type": "Feature",
  "properties": {
    "iso:country":"CA",
    "sg:city":"Lethbridge",
    "sg:classifiers":[
        {
            "category":"Manufacturing",
            "subcategory":"Metals",
            "type":"Manufacturing & Wholesale Goods"
        }
    ],
    "sg:phone":"+1 403 329 1026",
    "sg:postcode":"T1H 2J2",
    "sg:province":"AB",
    "sg:tags":[
        "lock",
        "safe",
        "locksmith"
    ],
    "wof:name":"Active Lock & Safe Ltd",
    "wof:placetype":"venue"
},
  "geometry": {"coordinates":[-112.82827758800001,49.7023200989],"type":"Point"}
}