{
  "type": "Feature",
  "properties": {
    "addr:full":"2122 Bridletowne Cir Scarborough ON M1W 2L1",
    "addr:housenumber":"2122",
    "addr:postcode":"m1w 2l1",
    "addr:street":"Bridletowne Cir",
    "iso:country":"CA",
    "sg:address":"2122 Bridletowne Cir",
    "sg:city":"Scarborough",
    "sg:classifiers":[
        {
            "category":"Banks & Credit Unions",
            "subcategory":"Bank",
            "type":"Services"
        }
    ],
    "sg:phone":"+1 416 497 2863",
    "sg:postcode":"M1W 2L1",
    "sg:province":"ON",
    "wof:name":"Bank of Montreal",
    "wof:placetype":"venue"
},
  "geometry": {"coordinates":[-79.3132858276,43.7989234924],"type":"Point"}
}