{
  "type": "Feature",
  "properties": {
    "addr:full":"20 Wertheim Crt Richmond Hill ON L4B 3A8",
    "addr:housenumber":"20",
    "addr:postcode":"l4b 3a8",
    "addr:street":"Wertheim Crt",
    "iso:country":"CA",
    "sg:address":"20 Wertheim Crt",
    "sg:city":"Richmond Hill",
    "sg:classifiers":[
        {
            "category":"Real Estate",
            "subcategory":"Real Estate Agent",
            "type":"Services"
        }
    ],
    "sg:phone":"+1 905 889 6008",
    "sg:postcode":"L4B 3A8",
    "sg:province":"ON",
    "sg:tags":[
        "management"
    ],
    "wof:name":"Mfs Realty Svc",
    "wof:placetype":"venue"
},
  "geometry": {"coordinates":[-79.386467,43.845337],"type":"Point"}
}