{
  "type": "Feature",
  "properties": {
    "iso:country":"CA",
    "sg:city":"Cranbrook",
    "sg:classifiers":[
        {
            "category":"Personal",
            "subcategory":"Beauty Salon",
            "type":"Services"
        }
    ],
    "sg:phone":"+1 250 426 7098",
    "sg:postcode":"V1C 2J1",
    "sg:province":"BC",
    "sg:tags":[
        "tanning"
    ],
    "wof:name":"Koko Beach",
    "wof:placetype":"venue"
},
  "geometry": {"coordinates":[-115.77156829800001,49.5112876892],"type":"Point"}
}