{
  "type": "Feature",
  "properties": {
    "addr:full":"1210 Ch Principal Saint-Mathieu-Du-Parc QC G0X 1N0",
    "addr:postcode":"1210;g0x 1n0",
    "addr:street":"Ch Principal",
    "iso:country":"CA",
    "sg:address":"1210 Ch Principal",
    "sg:city":"Saint-Mathieu-Du-Parc",
    "sg:classifiers":[
        {
            "category":"Museum",
            "type":"Entertainment"
        }
    ],
    "sg:phone":"+1 819 532 2641",
    "sg:postcode":"G0X 1N0",
    "sg:province":"QC",
    "sg:tags":[
        "information",
        "recreation",
        "consultant",
        "arts",
        "program",
        "organization"
    ],
    "wof:name":"Voix DE Femmes",
    "wof:placetype":"venue"
},
  "geometry": {"coordinates":[-72.87251281739999,46.6005096436],"type":"Point"}
}