{
  "type": "Feature",
  "properties": {
    "addr:full":"1024 Kent Ave Oakville ON L6H 1Z6",
    "addr:postcode":"1024;l6h 1z6",
    "addr:street":"Kent Ave",
    "iso:country":"CA",
    "sg:address":"1024 Kent Ave",
    "sg:city":"Oakville",
    "sg:classifiers":[
        {
            "category":"Wholesale",
            "subcategory":"Construction Materials",
            "type":"Manufacturing & Wholesale Goods"
        }
    ],
    "sg:phone":"+1 905 331 5383",
    "sg:postcode":"L6H 1Z6",
    "sg:province":"ON",
    "sg:tags":[
        "stone",
        "interlocking"
    ],
    "wof:name":"Forestview Landscaping",
    "wof:placetype":"venue"
},
  "geometry": {"coordinates":[-79.690979,43.456715],"type":"Point"}
}