{
  "type": "Feature",
  "properties": {
    "iso:country":"CA",
    "sg:address":"2540 Ch DE LA Lievre S",
    "sg:city":"Mont-Laurier",
    "sg:classifiers":[
        {
            "category":"Shopping",
            "subcategory":"Used Merchandise",
            "type":"Retail Goods"
        }
    ],
    "sg:phone":"+1 819 623 1324",
    "sg:postcode":"J9L 3G3",
    "sg:province":"QC",
    "sg:tags":[
        "flea",
        "market"
    ],
    "wof:name":"Parc Laurier",
    "wof:placetype":"venue"
},
  "geometry": {"coordinates":[-75.51568603520001,46.5483818054],"type":"Point"}
}