{
  "type": "Feature",
  "properties": {
    "addr:full":"Etobicoke ON M9W 4Y5",
    "addr:postcode":"m9w 4y5",
    "iso:country":"CA",
    "sg:city":"Etobicoke",
    "sg:classifiers":[
        {
            "category":"Freight",
            "type":"Transportation"
        }
    ],
    "sg:phone":"+1 416 798 2100",
    "sg:postcode":"M9W 4Y5",
    "sg:province":"ON",
    "sg:tags":[
        "courier"
    ],
    "wof:name":"Sunrise Xpress Messenger Svc",
    "wof:placetype":"venue"
},
  "geometry": {"coordinates":[-79.58899700000001,43.681976],"type":"Point"}
}