{
  "type": "Feature",
  "properties": {
    "addr:full":"460 Boul Louis-Frechette Nicolet QC J3T 1Y2",
    "addr:housenumber":"460",
    "addr:postcode":"j3t 1y2",
    "addr:street":"Boul Louis-Frechette",
    "iso:country":"CA",
    "sg:address":"460 Boul Louis-Frechette",
    "sg:city":"Nicolet",
    "sg:classifiers":[
        {
            "category":"Government",
            "subcategory":"Office",
            "type":"Public Place"
        }
    ],
    "sg:phone":"+1 819 293 6106",
    "sg:postcode":"J3T 1Y2",
    "sg:province":"QC",
    "wof:name":"Quebec Societe-Financement",
    "wof:placetype":"venue"
},
  "geometry": {"coordinates":[-72.615257,46.228943],"type":"Point"}
}