{
  "type": "Feature",
  "properties": {
    "addr:full":"2555 Av Dollard # 139 Lasalle QC H8N 3A9",
    "addr:housenumber":"2555",
    "addr:postcode":"h8n 3a9",
    "addr:street":"Av Dollard # 139",
    "iso:country":"CA",
    "sg:address":"2555 Av Dollard # 139",
    "sg:city":"Lasalle",
    "sg:classifiers":[
        {
            "category":"Wholesale",
            "subcategory":"Scrap",
            "type":"Manufacturing & Wholesale Goods"
        }
    ],
    "sg:phone":"+1 514 595 1212",
    "sg:postcode":"H8N 3A9",
    "sg:province":"QC",
    "sg:tags":[
        "recycling",
        "center"
    ],
    "wof:name":"Recuperaction Marronniers",
    "wof:placetype":"venue"
},
  "geometry": {"coordinates":[-73.6402053833,45.4357261658],"type":"Point"}
}