{
  "type": "Feature",
  "properties": {
    "addr:full":"145 Queen St E # 1 Brampton ON L6W 3P8",
    "addr:housenumber":"145",
    "addr:postcode":"l6w 3p8",
    "addr:street":"Queen St E # 1",
    "iso:country":"CA",
    "sg:address":"145 Queen St E # 1",
    "sg:city":"Brampton",
    "sg:classifiers":[
        {
            "category":"Personal",
            "subcategory":"Beauty Salon",
            "type":"Services"
        }
    ],
    "sg:phone":"+1 905 457 7775",
    "sg:postcode":"L6W 3P8",
    "sg:province":"ON",
    "wof:name":"Charlie's Angels Hair Studio",
    "wof:placetype":"venue"
},
  "geometry": {"coordinates":[-79.7538604736,43.6914520264],"type":"Point"}
}