{
  "type": "Feature",
  "properties": {
    "addr:full":"1421 Ch Gascon Terrebonne QC J6X 4L9",
    "addr:housenumber":"1421",
    "addr:postcode":"j6x 4l9",
    "addr:street":"Ch Gascon",
    "iso:country":"CA",
    "sg:address":"1421 Ch Gascon",
    "sg:city":"Terrebonne",
    "sg:classifiers":[
        {
            "category":"Restaurant",
            "type":"Food & Drink"
        }
    ],
    "sg:phone":"+1 450 964 4046",
    "sg:postcode":"J6X 4L9",
    "sg:province":"QC",
    "wof:name":"Grizzly's Pasta Grill",
    "wof:placetype":"venue"
},
  "geometry": {"coordinates":[-73.652092,45.710155],"type":"Point"}
}