{
  "type": "Feature",
  "properties": {
    "addr:full":"1431 Lansdowne St Hawkesbury ON K6A 1J5",
    "addr:housenumber":"1431",
    "addr:postcode":"k6a 1j5",
    "addr:street":"Lansdowne St",
    "iso:country":"CA",
    "sg:address":"1431 Lansdowne St",
    "sg:city":"Hawkesbury",
    "sg:classifiers":[
        {
            "category":"Sports & Exercise",
            "subcategory":"Bowling",
            "type":"Entertainment"
        }
    ],
    "sg:phone":"+1 613 632 7176",
    "sg:postcode":"K6A 1J5",
    "sg:province":"ON",
    "sg:tags":[
        "center"
    ],
    "wof:name":"Olympia Bowl",
    "wof:placetype":"venue"
},
  "geometry": {"coordinates":[-74.587097,45.605629],"type":"Point"}
}