{
  "type": "Feature",
  "properties": {
    "addr:full":"Vancouver BC V6E 4R6",
    "addr:postcode":"v6e 4r6",
    "iso:country":"CA",
    "sg:city":"Vancouver",
    "sg:classifiers":[
        {
            "category":"Banks & Credit Unions",
            "subcategory":"Investment Brokerage",
            "type":"Services"
        }
    ],
    "sg:phone":"+1 604 642 2282",
    "sg:postcode":"V6E 4R6",
    "sg:province":"BC",
    "sg:tags":[
        "consultant",
        "planning",
        "financial"
    ],
    "wof:name":"Clearlease Financial Group",
    "wof:placetype":"venue"
},
  "geometry": {"coordinates":[-123.124664,49.285641],"type":"Point"}
}