{
  "type": "Feature",
  "properties": {
    "addr:full":"407 17th St W Prince Albert SK S6V 3X8",
    "addr:housenumber":"407",
    "addr:postcode":"s6v 3x8",
    "addr:street":"17Th St",
    "iso:country":"CA",
    "sg:address":"407 17th St W",
    "sg:city":"Prince Albert",
    "sg:classifiers":[
        {
            "category":"Retail",
            "subcategory":"Laundry & Dry Cleaning",
            "type":"Services"
        }
    ],
    "sg:phone":"+1 306 763 7257",
    "sg:postcode":"S6V 3X8",
    "sg:province":"SK",
    "sg:tags":[
        "linen",
        "supply"
    ],
    "wof:name":"Four Seasons Cleaning Ltd",
    "wof:placetype":"venue"
},
  "geometry": {"coordinates":[-105.76532,53.19743],"type":"Point"}
}