{
  "type": "Feature",
  "properties": {
    "addr:full":"334 Rue Principale Granby QC J2G 2W4",
    "addr:housenumber":"334",
    "addr:postcode":"j2g 2w4",
    "addr:street":"Rue Principale",
    "iso:country":"CA",
    "sg:address":"334 Rue Principale",
    "sg:city":"Granby",
    "sg:classifiers":[
        {
            "category":"Shopping",
            "subcategory":"Used Merchandise",
            "type":"Retail Goods"
        }
    ],
    "sg:phone":"+1 450 378 0202",
    "sg:postcode":"J2G 2W4",
    "sg:province":"QC",
    "sg:tags":[
        "pawnbroker"
    ],
    "wof:name":"Cash Express",
    "wof:placetype":"venue"
},
  "geometry": {"coordinates":[-72.731606,45.401924],"type":"Point"}
}