{
  "type": "Feature",
  "properties": {
    "addr:full":"305 Queen St Dunnville ON N1A 1J1",
    "addr:housenumber":"305",
    "addr:postcode":"n1a 1j1",
    "addr:street":"Queen St",
    "iso:country":"CA",
    "sg:address":"305 Queen St",
    "sg:city":"Dunnville",
    "sg:classifiers":[
        {
            "category":"Organizations",
            "subcategory":"Professional Association",
            "type":"Services"
        }
    ],
    "sg:phone":"+1 905 774 5942",
    "sg:postcode":"N1A 1J1",
    "sg:province":"ON",
    "wof:name":"Royal Canadian Legion",
    "wof:placetype":"venue"
},
  "geometry": {"coordinates":[-79.6149520874,42.9024276733],"type":"Point"}
}