{
  "type": "Feature",
  "properties": {
    "iso:country":"CA",
    "sg:address":"1861 Meadowbrook Dr SE",
    "sg:city":"Airdrie",
    "sg:classifiers":[
        {
            "category":"Autos & Motor Vehicles",
            "subcategory":"Fuel & Gas Station",
            "type":"Retail Goods"
        }
    ],
    "sg:phone":"+1 403 948 7600",
    "sg:postcode":"T4A 1V3",
    "sg:province":"AB",
    "sg:tags":[
        "oil"
    ],
    "wof:name":"Hi Ho Gas & Grocery",
    "wof:placetype":"venue"
},
  "geometry": {"coordinates":[-113.98843383800001,51.2757873535],"type":"Point"}
}