{
  "type": "Feature",
  "properties": {
    "addr:full":"14525 100 St Grande Prairie AB T8V 7C1",
    "addr:housenumber":"14525",
    "addr:postcode":"t8v 7c1",
    "addr:street":"100 St",
    "iso:country":"CA",
    "sg:address":"14525 100 St",
    "sg:city":"Grande Prairie",
    "sg:classifiers":[
        {
            "category":"Manufacturing",
            "subcategory":"Building Materials",
            "type":"Manufacturing & Wholesale Goods"
        }
    ],
    "sg:phone":"+1 780 538 8787",
    "sg:postcode":"T8V 7C1",
    "sg:province":"AB",
    "wof:name":"Intercoast Truss",
    "wof:placetype":"venue"
},
  "geometry": {"coordinates":[-118.794197,55.199711],"type":"Point"}
}