{
  "type": "Feature",
  "properties": {
    "addr:full":"2231 Neil Dr Nanaimo BC V9R 6T5",
    "addr:housenumber":"2231",
    "addr:postcode":"v9r 6t5",
    "addr:street":"Neil Dr",
    "iso:country":"CA",
    "sg:address":"2231 Neil Dr",
    "sg:city":"Nanaimo",
    "sg:classifiers":[
        {
            "category":"Professional",
            "subcategory":"Research",
            "type":"Services"
        }
    ],
    "sg:phone":"+1 250 753 1055",
    "sg:postcode":"V9R 6T5",
    "sg:province":"BC",
    "sg:tags":[
        "environmental",
        "ecological"
    ],
    "wof:name":"M C Wright & Assoc",
    "wof:placetype":"venue"
},
  "geometry": {"coordinates":[-123.996788025,49.1688652039],"type":"Point"}
}