{
  "type": "Feature",
  "properties": {
    "addr:full":"9110 Macleod Trail SE Calgary AB T2J 0P5",
    "addr:housenumber":"9110",
    "addr:postcode":"t2j 0p5",
    "addr:street":"Macleod Trail Se",
    "iso:country":"CA",
    "sg:address":"9110 Macleod Trail SE",
    "sg:city":"Calgary",
    "sg:classifiers":[
        {
            "category":"Restaurant",
            "type":"Food & Drink"
        }
    ],
    "sg:phone":"+1 403 301 3731",
    "sg:postcode":"T2J 0P5",
    "sg:province":"AB",
    "sg:tags":[
        "shop",
        "tea",
        "coffee"
    ],
    "wof:name":"Second Cup",
    "wof:placetype":"venue"
},
  "geometry": {"coordinates":[-114.07125854500001,50.971862793],"type":"Point"}
}