{
  "type": "Feature",
  "properties": {
    "iso:country":"CA",
    "sg:address":"2965 Day St",
    "sg:city":"Winnipeg",
    "sg:classifiers":[
        {
            "category":"Building & Trades",
            "subcategory":"Construction",
            "type":"Services"
        }
    ],
    "sg:phone":"+1 204 222 3259",
    "sg:postcode":"R2C 2Z2",
    "sg:province":"MB",
    "sg:tags":[
        "maker",
        "cabinet"
    ],
    "wof:name":"Koss Cabinets Ltd",
    "wof:placetype":"venue"
},
  "geometry": {"coordinates":[-97.14073944090001,49.8994255066],"type":"Point"}
}