{
  "type": "Feature",
  "properties": {
    "addr:full":"2795 Pooley Ave Merritt BC V1K 1C2",
    "addr:housenumber":"2795",
    "addr:postcode":"v1k 1c2",
    "addr:street":"Pooley Ave",
    "iso:country":"CA",
    "sg:address":"2795 Pooley Ave",
    "sg:city":"Merritt",
    "sg:classifiers":[
        {
            "category":"Retail",
            "subcategory":"Repair Shop",
            "type":"Services"
        }
    ],
    "sg:phone":"+1 250 378 5395",
    "sg:postcode":"V1K 1C2",
    "sg:province":"BC",
    "sg:tags":[
        "welding"
    ],
    "wof:name":"Alpha Design",
    "wof:placetype":"venue"
},
  "geometry": {"coordinates":[-120.774643,50.097778],"type":"Point"}
}