{
  "type": "Feature",
  "properties": {
    "addr:full":"4705 Rue Laval Lac-Megantic QC G6B 1C4",
    "addr:housenumber":"4705",
    "addr:postcode":"g6b 1c4",
    "addr:street":"Rue Laval Lac-Megantic",
    "iso:country":"CA",
    "sg:address":"4705 Rue Laval",
    "sg:city":"Lac-Megantic",
    "sg:classifiers":[
        {
            "category":"Manufacturing",
            "subcategory":"Printing",
            "type":"Manufacturing & Wholesale Goods"
        }
    ],
    "sg:phone":"+1 819 583 2960",
    "sg:postcode":"G6B 1C4",
    "sg:province":"QC",
    "sg:tags":[
        "newspaper"
    ],
    "wof:name":"Journal Mrg Enr",
    "wof:placetype":"venue"
},
  "geometry": {"coordinates":[-70.889465,45.580128],"type":"Point"}
}