{
  "type": "Feature",
  "properties": {
    "addr:full":"205 Railway Ave W Outlook SK S0L 2N0",
    "addr:housenumber":"205",
    "addr:postcode":"s0l 2n0",
    "addr:street":"Railway Ave W Outlook",
    "iso:country":"CA",
    "sg:address":"205 Railway Ave W",
    "sg:city":"Outlook",
    "sg:classifiers":[
        {
            "category":"Retail",
            "subcategory":"Auto Repair",
            "type":"Services"
        }
    ],
    "sg:phone":"+1 306 867 2266",
    "sg:postcode":"S0L 2N0",
    "sg:province":"SK",
    "sg:tags":[
        "body",
        "automobile",
        "painting"
    ],
    "wof:name":"Dynamic Autobody",
    "wof:placetype":"venue"
},
  "geometry": {"coordinates":[-107.049004,51.489155],"type":"Point"}
}