{
  "type": "Feature",
  "properties": {
    "addr:full":"5402 43 St Olds AB T4H 1B5",
    "addr:housenumber":"5402",
    "addr:postcode":"t4h 1b5",
    "addr:street":"43 St",
    "iso:country":"CA",
    "sg:address":"5402 43 St",
    "sg:city":"Olds",
    "sg:classifiers":[
        {
            "category":"Organizations",
            "subcategory":"Religious Organization",
            "type":"Services"
        }
    ],
    "sg:phone":"+1 403 556 8820",
    "sg:postcode":"T4H 1B5",
    "sg:province":"AB",
    "sg:tags":[
        "church"
    ],
    "wof:name":"Church of the Nazarene",
    "wof:placetype":"venue"
},
  "geometry": {"coordinates":[-114.114113,51.799095],"type":"Point"}
}