{
  "type": "Feature",
  "properties": {
    "addr:full":"Sullivan QC J0Y 2N0",
    "addr:postcode":"j0y 2n0",
    "iso:country":"CA",
    "sg:city":"Sullivan",
    "sg:classifiers":[
        {
            "category":"Food & Beverages",
            "subcategory":"Groceries & Convenience Stores",
            "type":"Retail Goods"
        }
    ],
    "sg:phone":"+1 819 824 6859",
    "sg:postcode":"J0Y 2N0",
    "sg:province":"QC",
    "wof:name":"Depanneur Sullivan",
    "wof:placetype":"venue"
},
  "geometry": {"coordinates":[-77.7123794556,48.0861320496],"type":"Point"}
}