{
  "type": "Feature",
  "properties": {
    "addr:full":"4811 51 Ave Camrose AB T4V 0V4",
    "addr:housenumber":"4811",
    "addr:postcode":"t4v 0v4",
    "addr:street":"51 Ave",
    "iso:country":"CA",
    "sg:address":"4811 51 Ave",
    "sg:city":"Camrose",
    "sg:classifiers":[
        {
            "category":"Shopping",
            "subcategory":"Computers & Home Electronics",
            "type":"Retail Goods"
        }
    ],
    "sg:phone":"+1 780 679 0091",
    "sg:postcode":"T4V 0V4",
    "sg:province":"AB",
    "sg:tags":[
        "equipment",
        "television",
        "radio",
        "satellite"
    ],
    "wof:name":"Simstech Electronics Ltd",
    "wof:placetype":"venue"
},
  "geometry": {"coordinates":[-112.821777344,53.0233726501],"type":"Point"}
}