{
  "type": "Feature",
  "properties": {
    "addr:full":"9911 Main St Summerland BC V0H 1Z0",
    "addr:housenumber":"9911",
    "addr:postcode":"v0h 1z0",
    "addr:street":"Main St",
    "iso:country":"CA",
    "sg:address":"9911 Main St",
    "sg:city":"Summerland",
    "sg:classifiers":[
        {
            "category":"Health Services",
            "subcategory":"Medical Lab",
            "type":"Services"
        }
    ],
    "sg:phone":"+1 250 494 9642",
    "sg:postcode":"V0H 1Z0",
    "sg:province":"BC",
    "wof:name":"Summerland Denture Clinic",
    "wof:placetype":"venue"
},
  "geometry": {"coordinates":[-119.681808472,49.6012191772],"type":"Point"}
}