{
  "type": "Feature",
  "properties": {
    "addr:full":"1330 Fairfield Rd Victoria BC V8S 5J1",
    "addr:housenumber":"1330",
    "addr:postcode":"v8s 5j1",
    "addr:street":"Fairfield Rd",
    "iso:country":"CA",
    "sg:address":"1330 Fairfield Rd",
    "sg:city":"Victoria",
    "sg:classifiers":[
        {
            "category":"Recreation",
            "type":"Entertainment"
        }
    ],
    "sg:phone":"+1 250 382 4604",
    "sg:postcode":"V8S 5J1",
    "sg:province":"BC",
    "sg:tags":[
        "government",
        "hall",
        "auditorium"
    ],
    "wof:name":"Victoria Fairfield Comm Place",
    "wof:placetype":"venue"
},
  "geometry": {"coordinates":[-123.347191,48.414719],"type":"Point"}
}