{
  "type": "Feature",
  "properties": {
    "addr:full":"278 Breithaupt St Kitchener ON N2H 5H5",
    "addr:housenumber":"278",
    "addr:postcode":"n2h 5h5",
    "addr:street":"Breithaupt St",
    "iso:country":"CA",
    "sg:address":"278 Breithaupt St",
    "sg:city":"Kitchener",
    "sg:classifiers":[
        {
            "category":"Building & Trades",
            "subcategory":"Construction",
            "type":"Services"
        }
    ],
    "sg:phone":"+1 519 742 2834",
    "sg:postcode":"N2H 5H5",
    "sg:province":"ON",
    "sg:tags":[
        "painter"
    ],
    "wof:name":"Expert Painting",
    "wof:placetype":"venue"
},
  "geometry": {"coordinates":[-80.48784637449999,43.4584083557],"type":"Point"}
}