{
  "type": "Feature",
  "properties": {
    "addr:full":"Valcourt QC J0E 2L0",
    "addr:postcode":"j0e 2l0",
    "iso:country":"CA",
    "sg:city":"Valcourt",
    "sg:classifiers":[
        {
            "category":"Personal",
            "subcategory":"Beauty Salon",
            "type":"Services"
        }
    ],
    "sg:phone":"+1 450 532 3533",
    "sg:postcode":"J0E 2L0",
    "sg:province":"QC",
    "wof:name":"Coiffure Lui D'Elle",
    "wof:placetype":"venue"
},
  "geometry": {"coordinates":[-72.302368,45.495747],"type":"Point"}
}