{
  "type": "Feature",
  "properties": {
    "addr:full":"347 Broadview Ave Toronto ON M4M 2H1",
    "addr:housenumber":"347",
    "addr:postcode":"m4m 2h1",
    "addr:street":"Broadview Ave",
    "iso:country":"CA",
    "sg:address":"347 Broadview Ave",
    "sg:city":"Toronto",
    "sg:classifiers":[
        {
            "category":"Food & Beverages",
            "subcategory":"Groceries & Convenience Stores",
            "type":"Retail Goods"
        }
    ],
    "sg:phone":"+1 416 406 3668",
    "sg:postcode":"M4M 2H1",
    "sg:province":"ON",
    "sg:tags":[
        "grocer"
    ],
    "wof:name":"Shin Seng Market",
    "wof:placetype":"venue"
},
  "geometry": {"coordinates":[-79.35225699999999,43.6651],"type":"Point"}
}