{
  "type": "Feature",
  "properties": {
    "addr:full":"38 Edgar Dr Brantford ON N3R 6X8",
    "addr:housenumber":"38",
    "addr:postcode":"n3r 6x8",
    "addr:street":"Edgar Dr",
    "iso:country":"CA",
    "sg:address":"38 Edgar Dr",
    "sg:city":"Brantford",
    "sg:classifiers":[
        {
            "category":"Building & Trades",
            "subcategory":"Landscaping Services",
            "type":"Services"
        }
    ],
    "sg:phone":"+1 519 753 8822",
    "sg:postcode":"N3R 6X8",
    "sg:province":"ON",
    "sg:tags":[
        "lawn",
        "maintenance",
        "grounds"
    ],
    "wof:name":"Professional Landscaping Svc",
    "wof:placetype":"venue"
},
  "geometry": {"coordinates":[-80.27175099999999,43.180992],"type":"Point"}
}