{
  "type": "Feature",
  "properties": {
    "addr:full":"2698 Ch Sainte-Marie Mascouche QC J7K 1M9",
    "addr:housenumber":"2698",
    "addr:postcode":"j7k 1m9",
    "addr:street":"Ch Sainte-Marie",
    "iso:country":"CA",
    "sg:address":"2698 Ch Sainte-Marie",
    "sg:city":"Mascouche",
    "sg:classifiers":[
        {
            "category":"Food & Beverages",
            "subcategory":"Groceries & Convenience Stores",
            "type":"Retail Goods"
        }
    ],
    "sg:phone":"+1 450 474 1200",
    "sg:postcode":"J7K 1M9",
    "sg:province":"QC",
    "sg:tags":[
        "grocer"
    ],
    "wof:name":"Depanneur Central",
    "wof:placetype":"venue"
},
  "geometry": {"coordinates":[-73.61196136469999,45.7513923645],"type":"Point"}
}