{
  "type": "Feature",
  "properties": {
    "addr:full":"1991 Boul DE Perigny Chambly QC J3L 4C3",
    "addr:housenumber":"1991",
    "addr:postcode":"j3l 4c3",
    "addr:street":"Boul De Perigny",
    "iso:country":"CA",
    "sg:address":"1991 Boul DE Perigny",
    "sg:city":"Chambly",
    "sg:classifiers":[
        {
            "category":"Professional",
            "subcategory":"Lawyer & Legal Services",
            "type":"Services"
        }
    ],
    "sg:phone":"+1 450 658 0426",
    "sg:postcode":"J3L 4C3",
    "sg:province":"QC",
    "sg:tags":[
        "attorney"
    ],
    "wof:name":"Pelletier, Gilles R",
    "wof:placetype":"venue"
},
  "geometry": {"coordinates":[-73.272148,45.442352],"type":"Point"}
}