{
  "type": "Feature",
  "properties": {
    "addr:full":"20 Rue Paiement Sainte-Genevieve QC H9H 2S5",
    "addr:housenumber":"20",
    "addr:postcode":"h9h 2s5",
    "addr:street":"Rue Paiement",
    "iso:country":"CA",
    "sg:address":"20 Rue Paiement",
    "sg:city":"Sainte-Genevieve",
    "sg:classifiers":[
        {
            "category":"Building & Trades",
            "subcategory":"Construction",
            "type":"Services"
        }
    ],
    "sg:phone":"+1 514 626 2266",
    "sg:postcode":"H9H 2S5",
    "sg:province":"QC",
    "sg:tags":[
        "excavating",
        "contractor"
    ],
    "wof:name":"Roy & Boily Excavation Inc",
    "wof:placetype":"venue"
},
  "geometry": {"coordinates":[-73.867073,45.482964],"type":"Point"}
}