{
  "type": "Feature",
  "properties": {
    "addr:full":"7939 Hwy 7 Musquodoboit Harbour NS B0J 2L0",
    "addr:housenumber":"7939",
    "addr:postcode":"b0j 2l0",
    "addr:street":"Hwy 7",
    "iso:country":"CA",
    "sg:address":"7939 Hwy 7",
    "sg:city":"Musquodoboit Harbour",
    "sg:classifiers":[
        {
            "category":"Real Estate",
            "subcategory":"Real Estate Agent",
            "type":"Services"
        }
    ],
    "sg:phone":"+1 902 889 2979",
    "sg:postcode":"B0J 2L0",
    "sg:province":"NS",
    "wof:name":"Mike Cox Real Estate",
    "wof:placetype":"venue"
},
  "geometry": {"coordinates":[-63.1470069885,44.788143158],"type":"Point"}
}