{
  "type": "Feature",
  "properties": {
    "addr:full":"43 Boul Desjardins E Sainte-Therese QC J7E 1C2",
    "addr:housenumber":"43",
    "addr:postcode":"j7e 1c2",
    "addr:street":"Boul Desjardins E Sainte-Therese",
    "iso:country":"CA",
    "sg:address":"43 Boul Desjardins E",
    "sg:city":"Sainte-Therese",
    "sg:classifiers":[
        {
            "category":"Autos & Motor Vehicles",
            "subcategory":"Auto Supplies",
            "type":"Retail Goods"
        }
    ],
    "sg:phone":"+1 450 434 3655",
    "sg:postcode":"J7E 1C2",
    "sg:province":"QC",
    "sg:tags":[
        "tire"
    ],
    "wof:name":"Centre DE Pneus & Mecanique",
    "wof:placetype":"venue"
},
  "geometry": {"coordinates":[-73.8315124512,45.6342964172],"type":"Point"}
}