{
  "type": "Feature",
  "properties": {
    "iso:country":"CA",
    "sg:address":"550 Centennial Park Blvd",
    "sg:city":"Etobicoke",
    "sg:classifiers":[
        {
            "category":"Sports & Exercise",
            "subcategory":"Golf",
            "type":"Entertainment"
        }
    ],
    "sg:phone":"+1 416 620 1392",
    "sg:postcode":"M9C 5R5",
    "sg:province":"ON",
    "sg:tags":[
        "course"
    ],
    "wof:name":"Centennial Park Golf Ctr",
    "wof:placetype":"venue"
},
  "geometry": {"coordinates":[-79.5961532593,43.6497955322],"type":"Point"}
}