{
  "type": "Feature",
  "properties": {
    "iso:country":"CA",
    "sg:address":"76 Rte 60",
    "sg:city":"Avondale",
    "sg:classifiers":[
        {
            "category":"Shopping",
            "subcategory":"Discount & Variety Stores",
            "type":"Retail Goods"
        }
    ],
    "sg:phone":"+1 709 229 3881",
    "sg:postcode":"A0A 1B0",
    "sg:province":"NL",
    "sg:tags":[
        "merchandise",
        "general"
    ],
    "wof:name":"Flynn's Store",
    "wof:placetype":"venue"
},
  "geometry": {"coordinates":[-53.1849822998,47.4245872498],"type":"Point"}
}