{
  "type": "Feature",
  "properties": {
    "iso:country":"CA",
    "sg:address":"490 Adelaide St W",
    "sg:city":"Toronto",
    "sg:classifiers":[
        {
            "category":"Professional",
            "subcategory":"Computer Services",
            "type":"Services"
        }
    ],
    "sg:phone":"+1 416 203 2135",
    "sg:postcode":"M5V 1T2",
    "sg:province":"ON",
    "sg:tags":[
        "internet"
    ],
    "wof:name":"Etellinet",
    "wof:placetype":"venue"
},
  "geometry": {"coordinates":[-79.4001159668,43.6459541321],"type":"Point"}
}