{
  "type": "Feature",
  "properties": {
    "iso:country":"CA",
    "sg:address":"19 1st St SW",
    "sg:city":"Portage LA Prairie",
    "sg:classifiers":[
        {
            "category":"Health Services",
            "subcategory":"Chiropractor",
            "type":"Services"
        }
    ],
    "sg:phone":"+1 204 239 6078",
    "sg:postcode":"R1N 1Y5",
    "sg:province":"MB",
    "wof:name":"Hewett, W John DC",
    "wof:placetype":"venue"
},
  "geometry": {"coordinates":[-98.2926940918,49.972568512],"type":"Point"}
}