{
  "type": "Feature",
  "properties": {
    "addr:full":"1320 Yonge St Toronto ON M4T 1X2",
    "addr:housenumber":"1320",
    "addr:postcode":"m4t 1x2",
    "addr:street":"Yonge St",
    "iso:country":"CA",
    "sg:address":"1320 Yonge St",
    "sg:city":"Toronto",
    "sg:classifiers":[
        {
            "category":"Education",
            "subcategory":"School",
            "type":"Public Place"
        }
    ],
    "sg:phone":"+1 416 926 1325",
    "sg:postcode":"M4T 1X2",
    "sg:province":"ON",
    "wof:name":"York School",
    "wof:placetype":"venue"
},
  "geometry": {"coordinates":[-79.392822,43.684612],"type":"Point"}
}