{
  "type": "Feature",
  "properties": {
    "addr:full":"8 Sunnyside Ave Cornwall ON K6H 6N1",
    "addr:housenumber":"8",
    "addr:postcode":"k6h 6n1",
    "addr:street":"Sunnyside Ave",
    "iso:country":"CA",
    "sg:address":"8 Sunnyside Ave",
    "sg:city":"Cornwall",
    "sg:classifiers":[
        {
            "category":"Home & Garden",
            "subcategory":"Building Materials",
            "type":"Retail Goods"
        }
    ],
    "sg:phone":"+1 613 933 8812",
    "sg:postcode":"K6H 6N1",
    "sg:province":"ON",
    "sg:tags":[
        "glass",
        "window",
        "plate"
    ],
    "wof:name":"Apple Auto Glass",
    "wof:placetype":"venue"
},
  "geometry": {"coordinates":[-74.7417297363,45.0360412598],"type":"Point"}
}