{
  "type": "Feature",
  "properties": {
    "iso:country":"CA",
    "sg:address":"11 Clyde Ave",
    "sg:city":"Sydney Mines",
    "sg:classifiers":[
        {
            "category":"Organizations",
            "subcategory":"Non-profit Organization",
            "type":"Services"
        }
    ],
    "sg:phone":"+1 902 736 9805",
    "sg:postcode":"B1V 2E3",
    "sg:province":"NS",
    "sg:tags":[
        "charitable",
        "institution"
    ],
    "wof:name":"Resi-Care Cb Assoc",
    "wof:placetype":"venue"
},
  "geometry": {"coordinates":[-60.229724884,46.2412490845],"type":"Point"}
}