{
  "type": "Feature",
  "properties": {
    "addr:full":"895 Bank St Ottawa ON K1S 3W4",
    "addr:housenumber":"895",
    "addr:postcode":"k1s 3w4",
    "addr:street":"Bank St",
    "iso:country":"CA",
    "sg:address":"895 Bank St",
    "sg:city":"Ottawa",
    "sg:classifiers":[
        {
            "category":"Restaurant",
            "type":"Food & Drink"
        }
    ],
    "sg:phone":"+1 613 236 9499",
    "sg:postcode":"K1S 3W4",
    "sg:province":"ON",
    "wof:name":"Mexicali Rosa's",
    "wof:placetype":"venue"
},
  "geometry": {"coordinates":[-75.6868362427,45.4006309509],"type":"Point"}
}