{
  "type": "Feature",
  "properties": {
    "addr:full":"73 Devonport Blvd Winnipeg MB R3P 0B1",
    "addr:housenumber":"73",
    "addr:postcode":"r3p 0b1",
    "addr:street":"Devonport Blvd",
    "iso:country":"CA",
    "sg:address":"73 Devonport Blvd",
    "sg:city":"Winnipeg",
    "sg:classifiers":[
        {
            "category":"Health Services",
            "subcategory":"Doctor",
            "type":"Services"
        }
    ],
    "sg:phone":"+1 204 885 3917",
    "sg:postcode":"R3P 0B1",
    "sg:province":"MB",
    "sg:tags":[
        "physician",
        "surgeon"
    ],
    "wof:name":"Prober, Mark MD",
    "wof:placetype":"venue"
},
  "geometry": {"coordinates":[-97.214088,49.861961],"type":"Point"}
}