{
  "type": "Feature",
  "properties": {
    "addr:full":"Nattinaak Ctr Pond Inlet NU X0A 0S0",
    "addr:postcode":"x0a 0s0",
    "addr:street":"Nattinaak Ctr Pond",
    "iso:country":"CA",
    "sg:address":"Nattinaak Ctr",
    "sg:city":"Pond Inlet",
    "sg:classifiers":[
        {
            "category":"Government",
            "subcategory":"Office",
            "type":"Public Place"
        }
    ],
    "sg:phone":"+1 867 899 8226",
    "sg:postcode":"X0A 0S0",
    "sg:province":"NU",
    "sg:tags":[
        "village"
    ],
    "wof:name":"Pond Inlet Nattinaak Ctr",
    "wof:placetype":"venue"
},
  "geometry": {"coordinates":[-77.953941,72.698143],"type":"Point"}
}