{
  "type": "Feature",
  "properties": {
    "addr:full":"417 Railway Ave Wawota SK S0G 5A0",
    "addr:housenumber":"417",
    "addr:postcode":"s0g 5a0",
    "addr:street":"Railway Ave",
    "iso:country":"CA",
    "sg:address":"417 Railway Ave",
    "sg:city":"Wawota",
    "sg:classifiers":[
        {
            "category":"Travel",
            "subcategory":"Hotels & Motels",
            "type":"Entertainment"
        }
    ],
    "sg:phone":"+1 306 739 2551",
    "sg:postcode":"S0G 5A0",
    "sg:province":"SK",
    "wof:name":"Wawota Hotel",
    "wof:placetype":"venue"
},
  "geometry": {"coordinates":[-102.028183,49.90321],"type":"Point"}
}