{
  "type": "Feature",
  "properties": {
    "addr:full":"300 Rue Quinlan Lasalle QC H8R 3V6",
    "addr:housenumber":"300",
    "addr:postcode":"h8r 3v6",
    "addr:street":"Rue Quinlan",
    "iso:country":"CA",
    "sg:address":"300 Rue Quinlan",
    "sg:city":"Lasalle",
    "sg:classifiers":[
        {
            "category":"Wholesale",
            "subcategory":"Auto Parts",
            "type":"Manufacturing & Wholesale Goods"
        }
    ],
    "sg:phone":"+1 514 363 1020",
    "sg:postcode":"H8R 3V6",
    "sg:province":"QC",
    "sg:tags":[
        "equipment",
        "truck"
    ],
    "wof:name":"O M Truck Ctr Inc",
    "wof:placetype":"venue"
},
  "geometry": {"coordinates":[-73.6459732056,45.430103302],"type":"Point"}
}