{
  "type": "Feature",
  "properties": {
    "addr:full":"420 Crawforth St Whitby ON L1N 3R5",
    "addr:housenumber":"420",
    "addr:postcode":"l1n 3r5",
    "addr:street":"Crawforth St",
    "iso:country":"CA",
    "sg:address":"420 Crawforth St",
    "sg:city":"Whitby",
    "sg:classifiers":[
        {
            "category":"Health Services",
            "subcategory":"Chiropractor",
            "type":"Services"
        }
    ],
    "sg:phone":"+1 905 430 0830",
    "sg:postcode":"L1N 3R5",
    "sg:province":"ON",
    "sg:tags":[
        "therapist",
        "massage"
    ],
    "wof:name":"Durham Massage Therapy",
    "wof:placetype":"venue"
},
  "geometry": {"coordinates":[-78.9150772095,43.8884506226],"type":"Point"}
}