{
  "type": "Feature",
  "properties": {
    "iso:country":"CA",
    "sg:address":"159 Pembina Trl",
    "sg:city":"Ste Agathe",
    "sg:classifiers":[
        {
            "category":"Professional",
            "subcategory":"Computer Services",
            "type":"Services"
        }
    ],
    "sg:phone":"+1 204 882 2438",
    "sg:postcode":"R0G 1Y0",
    "sg:province":"MB",
    "sg:tags":[
        "repair"
    ],
    "wof:name":"Cac Exchange Inc",
    "wof:placetype":"venue"
},
  "geometry": {"coordinates":[-97.1465911865,49.6004867554],"type":"Point"}
}