{
  "type": "Feature",
  "properties": {
    "addr:full":"1870 Sperling Ave Burnaby BC V5B 4K5",
    "addr:housenumber":"1870",
    "addr:postcode":"v5b 4k5",
    "addr:street":"Sperling Ave",
    "iso:country":"CA",
    "sg:address":"1870 Sperling Ave",
    "sg:city":"Burnaby",
    "sg:classifiers":[
        {
            "category":"Education",
            "subcategory":"Special Training",
            "type":"Public Place"
        }
    ],
    "sg:phone":"+1 604 420 3213",
    "sg:postcode":"V5B 4K5",
    "sg:province":"BC",
    "sg:tags":[
        "school",
        "arts"
    ],
    "wof:name":"Jennings Institute For Artists",
    "wof:placetype":"venue"
},
  "geometry": {"coordinates":[-122.964409,49.267258],"type":"Point"}
}