{
  "type": "Feature",
  "properties": {
    "addr:full":"47 Kenton Dr North York ON M2R 2H9",
    "addr:housenumber":"47",
    "addr:postcode":"m2r 2h9",
    "addr:street":"Kenton Dr",
    "iso:country":"CA",
    "sg:address":"47 Kenton Dr",
    "sg:city":"North York",
    "sg:classifiers":[
        {
            "category":"Building & Trades",
            "subcategory":"Electrical",
            "type":"Services"
        }
    ],
    "sg:phone":"+1 416 225 8242",
    "sg:postcode":"M2R 2H9",
    "sg:province":"ON",
    "sg:tags":[
        "electric",
        "contractor"
    ],
    "wof:name":"Finn Electric Inc",
    "wof:placetype":"venue"
},
  "geometry": {"coordinates":[-79.43929300000001,43.779358],"type":"Point"}
}