{
  "type": "Feature",
  "properties": {
    "addr:full":"815 143 Rte S Windsor QC J1S 2X2",
    "addr:housenumber":"143",
    "addr:postcode":"j1s 2x2",
    "addr:street":"Rte S",
    "iso:country":"CA",
    "sg:address":"815 143 Rte S",
    "sg:city":"Windsor",
    "sg:classifiers":[
        {
            "category":"Home & Garden",
            "subcategory":"Garden Supply",
            "type":"Retail Goods"
        }
    ],
    "sg:phone":"+1 819 845 2210",
    "sg:postcode":"J1S 2X2",
    "sg:province":"QC",
    "sg:tags":[
        "nurseryman"
    ],
    "wof:name":"Pepiniere Laurendiere Enr",
    "wof:placetype":"venue"
},
  "geometry": {"coordinates":[-72.0065002441,45.5690193176],"type":"Point"}
}