{
  "type": "Feature",
  "properties": {
    "addr:full":"Kitchener ON N2G 3A3",
    "addr:postcode":"n2g 3a3",
    "iso:country":"CA",
    "sg:city":"Kitchener",
    "sg:classifiers":[
        {
            "category":"Retail",
            "subcategory":"Auto Repair",
            "type":"Services"
        }
    ],
    "sg:phone":"+1 519 743 9086",
    "sg:postcode":"N2G 3A3",
    "sg:province":"ON",
    "sg:tags":[
        "repairing",
        "automobile",
        "electric"
    ],
    "wof:name":"B K Auto Electric & Mechanic",
    "wof:placetype":"venue"
},
  "geometry": {"coordinates":[-80.47801200000001,43.438431],"type":"Point"}
}