{
  "type": "Feature",
  "properties": {
    "addr:full":"450 Rue Cantin Victoriaville QC G6P 7E6",
    "addr:housenumber":"450",
    "addr:postcode":"g6p 7e6",
    "addr:street":"Rue Cantin",
    "iso:country":"CA",
    "sg:address":"450 Rue Cantin",
    "sg:city":"Victoriaville",
    "sg:classifiers":[
        {
            "category":"Building & Trades",
            "subcategory":"Construction",
            "type":"Services"
        }
    ],
    "sg:phone":"+1 819 758 1351",
    "sg:postcode":"G6P 7E6",
    "sg:province":"QC",
    "sg:tags":[
        "painter"
    ],
    "wof:name":"Marcel Messervier Inc",
    "wof:placetype":"venue"
},
  "geometry": {"coordinates":[-71.964546,46.068882],"type":"Point"}
}