{
  "type": "Feature",
  "properties": {
    "addr:full":"103 Orfus Rd North York ON M6A 1M4",
    "addr:housenumber":"103",
    "addr:postcode":"m6a 1m4",
    "addr:street":"Orfus Rd",
    "iso:country":"CA",
    "sg:address":"103 Orfus Rd",
    "sg:city":"North York",
    "sg:classifiers":[
        {
            "category":"Shopping",
            "subcategory":"Clothing, Apparel, & Fashions",
            "type":"Retail Goods"
        }
    ],
    "sg:phone":"+1 416 789 5855",
    "sg:postcode":"M6A 1M4",
    "sg:province":"ON",
    "sg:tags":[
        "shop",
        "bridal"
    ],
    "wof:name":"Windsor Bridal",
    "wof:placetype":"venue"
},
  "geometry": {"coordinates":[-79.464805603,43.718334198],"type":"Point"}
}