{
  "type": "Feature",
  "properties": {
    "addr:full":"9355 Elk Dr Port Hardy BC V0N 2P0",
    "addr:housenumber":"9355",
    "addr:postcode":"v0n 2p0",
    "addr:street":"Elk Dr",
    "iso:country":"CA",
    "sg:address":"9355 Elk Dr",
    "sg:city":"Port Hardy",
    "sg:classifiers":[
        {
            "category":"Retail",
            "subcategory":"Repair Shop",
            "type":"Services"
        }
    ],
    "sg:phone":"+1 250 949 7737",
    "sg:postcode":"V0N 2P0",
    "sg:province":"BC",
    "sg:tags":[
        "contractor"
    ],
    "wof:name":"Pro Heavy Duty Repair",
    "wof:placetype":"venue"
},
  "geometry": {"coordinates":[-127.50955200200001,50.7186317444],"type":"Point"}
}