{
  "type": "Feature",
  "properties": {
    "addr:full":"Burnaby BC V5A 4H1",
    "addr:postcode":"v5a 4h1",
    "iso:country":"CA",
    "sg:city":"Burnaby",
    "sg:classifiers":[
        {
            "category":"Bars & Pubs",
            "type":"Food & Drink"
        }
    ],
    "sg:phone":"+1 604 421 1092",
    "sg:postcode":"V5A 4H1",
    "sg:province":"BC",
    "wof:name":"Hop & Vine Neighborhood Pub",
    "wof:placetype":"venue"
},
  "geometry": {"coordinates":[-122.94536590600001,49.2700881958],"type":"Point"}
}