{
  "type": "Feature",
  "properties": {
    "addr:full":"Campbellville ON L0P 1B0",
    "addr:postcode":"l0p 1b0",
    "iso:country":"CA",
    "sg:city":"Campbellville",
    "sg:classifiers":[
        {
            "category":"Building & Trades",
            "subcategory":"Landscaping Services",
            "type":"Services"
        }
    ],
    "sg:phone":"+1 905 854 0422",
    "sg:postcode":"L0P 1B0",
    "sg:province":"ON",
    "sg:tags":[
        "landscape",
        "contractor"
    ],
    "wof:name":"Peter Harding Landscaping Svc",
    "wof:placetype":"venue"
},
  "geometry": {"coordinates":[-79.98304748539999,43.487739563],"type":"Point"}
}