{
  "type": "Feature",
  "properties": {
    "iso:country":"CA",
    "sg:city":"Vancouver",
    "sg:classifiers":[
        {
            "category":"Museum",
            "type":"Entertainment"
        }
    ],
    "sg:phone":"+1 604 689 2755",
    "sg:postcode":"V5Z 3A4",
    "sg:province":"BC",
    "sg:tags":[
        "organization",
        "arts",
        "information"
    ],
    "wof:name":"Canadian Society For Asian Art",
    "wof:placetype":"venue"
},
  "geometry": {"coordinates":[-123.11650848399999,49.2340240479],"type":"Point"}
}