{
  "type": "Feature",
  "properties": {
    "addr:full":"3087 Sumas Mtn Rd Abbotsford BC V3G 2G5",
    "addr:housenumber":"3087",
    "addr:postcode":"v3g 2g5",
    "addr:street":"Sumas Mtn Rd",
    "iso:country":"CA",
    "sg:address":"3087 Sumas Mtn Rd",
    "sg:city":"Abbotsford",
    "sg:classifiers":[
        {
            "category":"Manufacturing",
            "subcategory":"Glass & Minerals",
            "type":"Manufacturing & Wholesale Goods"
        }
    ],
    "sg:phone":"+1 604 852 4100",
    "sg:postcode":"V3G 2G5",
    "sg:province":"BC",
    "sg:tags":[
        "brick",
        "common"
    ],
    "wof:name":"Sumas Clay Products Ltd",
    "wof:placetype":"venue"
},
  "geometry": {"coordinates":[-122.195587158,49.0605430603],"type":"Point"}
}