{
  "type": "Feature",
  "properties": {
    "addr:full":"1521 Dublin Ave Winnipeg MB R3E 3M8",
    "addr:housenumber":"1521",
    "addr:postcode":"r3e 3m8",
    "addr:street":"Dublin Ave",
    "iso:country":"CA",
    "sg:address":"1521 Dublin Ave",
    "sg:city":"Winnipeg",
    "sg:classifiers":[
        {
            "category":"Manufacturing",
            "subcategory":"Tools & Machinery",
            "type":"Manufacturing & Wholesale Goods"
        }
    ],
    "sg:phone":"+1 204 786 7436",
    "sg:postcode":"R3E 3M8",
    "sg:province":"MB",
    "sg:tags":[
        "equipment",
        "hydraulic",
        "supply"
    ],
    "wof:name":"Berendsen Fluid Power Ltd",
    "wof:placetype":"venue"
},
  "geometry": {"coordinates":[-97.1953125,49.9114532471],"type":"Point"}
}