{
  "type": "Feature",
  "properties": {
    "addr:full":"6600 Boul Les Galeries D'Anjou Anjou QC H1M 2T4",
    "addr:housenumber":"6600",
    "addr:postcode":"h1m 2t4",
    "addr:street":"Boul Les Galeries D'Anjou",
    "iso:country":"CA",
    "sg:address":"6600 Boul Les Galeries D'Anjou",
    "sg:city":"Anjou",
    "sg:classifiers":[
        {
            "category":"Food & Beverages",
            "subcategory":"Groceries & Convenience Stores",
            "type":"Retail Goods"
        }
    ],
    "sg:phone":"+1 514 352 0121",
    "sg:postcode":"H1M 2T4",
    "sg:province":"QC",
    "sg:tags":[
        "grocer"
    ],
    "wof:name":"Depanneur Rp",
    "wof:placetype":"venue"
},
  "geometry": {"coordinates":[-73.538673,45.612267],"type":"Point"}
}