{
  "type": "Feature",
  "properties": {
    "iso:country":"CA",
    "sg:city":"Calgary",
    "sg:classifiers":[
        {
            "category":"Professional",
            "subcategory":"Detective & Security Services",
            "type":"Services"
        }
    ],
    "sg:phone":"+1 403 250 8947",
    "sg:postcode":"T1Y 5R8",
    "sg:province":"AB",
    "sg:tags":[
        "investigator"
    ],
    "wof:name":"Shepp Johnman & Assoc Invstgtn",
    "wof:placetype":"venue"
},
  "geometry": {"coordinates":[-113.99687194800001,51.0865058899],"type":"Point"}
}