{
  "type": "Feature",
  "properties": {
    "addr:full":"175 Railway St Nipigon ON P0T 2J0",
    "addr:housenumber":"175",
    "addr:postcode":"p0t 2j0",
    "addr:street":"Railway St",
    "iso:country":"CA",
    "sg:address":"175 Railway St",
    "sg:city":"Nipigon",
    "sg:classifiers":[
        {
            "category":"Retail",
            "subcategory":"Funeral Services",
            "type":"Services"
        }
    ],
    "sg:phone":"+1 807 887 2919",
    "sg:postcode":"P0T 2J0",
    "sg:province":"ON",
    "sg:tags":[
        "director"
    ],
    "wof:name":"Elliott Funeral Home Ltd",
    "wof:placetype":"venue"
},
  "geometry": {"coordinates":[-88.258926,49.016636],"type":"Point"}
}