{
  "type": "Feature",
  "properties": {
    "iso:country":"CA",
    "sg:address":"1655 Rue DE Louiseville",
    "sg:city":"Laval",
    "sg:classifiers":[
        {
            "category":"Building & Trades",
            "subcategory":"Construction",
            "type":"Services"
        }
    ],
    "sg:phone":"+1 514 722 7118",
    "sg:postcode":"H7E 4K9",
    "sg:province":"QC",
    "sg:tags":[
        "concrete",
        "paving",
        "contractor"
    ],
    "wof:name":"Tony Asphalte Inc",
    "wof:placetype":"venue"
},
  "geometry": {"coordinates":[-73.6835784912,45.5931053162],"type":"Point"}
}