{
  "type": "Feature",
  "properties": {
    "addr:full":"1125 Rue Ontario E Montreal QC H2L 1R2",
    "addr:housenumber":"1125",
    "addr:postcode":"h2l 1r2",
    "addr:street":"Rue Ontario E",
    "iso:country":"CA",
    "sg:address":"1125 Rue Ontario E",
    "sg:city":"Montreal",
    "sg:classifiers":[
        {
            "category":"Government",
            "subcategory":"Office",
            "type":"Public Place"
        }
    ],
    "sg:phone":"+1 514 872 4262",
    "sg:postcode":"H2L 1R2",
    "sg:province":"QC",
    "sg:tags":[
        "village"
    ],
    "wof:name":"Montreal Solidarite Sociale",
    "wof:placetype":"venue"
},
  "geometry": {"coordinates":[-73.562935,45.520462],"type":"Point"}
}