{
  "type": "Feature",
  "properties": {
    "addr:full":"2609 Queensway Prince George BC V2L 1N3",
    "addr:housenumber":"2609",
    "addr:postcode":"v2l 1n3",
    "addr:street":"Queensway",
    "iso:country":"CA",
    "sg:address":"2609 Queensway",
    "sg:city":"Prince George",
    "sg:classifiers":[
        {
            "category":"Real Estate",
            "subcategory":"Real Estate Agent",
            "type":"Services"
        }
    ],
    "sg:phone":"+1 250 563 1236",
    "sg:postcode":"V2L 1N3",
    "sg:province":"BC",
    "wof:name":"B C Northern Real Estate Board",
    "wof:placetype":"venue"
},
  "geometry": {"coordinates":[-122.741508,53.896538],"type":"Point"}
}