{
  "type": "Feature",
  "properties": {
    "addr:full":"Kitchener ON N2M 5A2",
    "addr:postcode":"n2m 5a2",
    "iso:country":"CA",
    "sg:city":"Kitchener",
    "sg:classifiers":[
        {
            "category":"Food & Beverages",
            "subcategory":"Groceries & Convenience Stores",
            "type":"Retail Goods"
        }
    ],
    "sg:phone":"+1 519 745 4699",
    "sg:postcode":"N2M 5A2",
    "sg:province":"ON",
    "sg:tags":[
        "grocer"
    ],
    "wof:name":"Onkar Foods & Spices Inc",
    "wof:placetype":"venue"
},
  "geometry": {"coordinates":[-80.52624511720001,43.4400138855],"type":"Point"}
}