{
  "type": "Feature",
  "properties": {
    "addr:full":"316 Somerset St Saint John NB E2K 2Y4",
    "addr:housenumber":"316",
    "addr:postcode":"e2k 2y4",
    "addr:street":"Somerset St",
    "iso:country":"CA",
    "sg:address":"316 Somerset St",
    "sg:city":"Saint John",
    "sg:classifiers":[
        {
            "category":"Organizations",
            "subcategory":"Religious Organization",
            "type":"Services"
        }
    ],
    "sg:phone":"+1 506 653 6830",
    "sg:postcode":"E2K 2Y4",
    "sg:province":"NB",
    "sg:tags":[
        "church"
    ],
    "wof:name":"St Pius X Rectory",
    "wof:placetype":"venue"
},
  "geometry": {"coordinates":[-66.075371,45.285439],"type":"Point"}
}