{
  "type": "Feature",
  "properties": {
    "addr:full":"23 Bright Oaks Bay Winnipeg MB R2M 2L9",
    "addr:housenumber":"23",
    "addr:postcode":"r2m 2l9",
    "addr:street":"Bright Oaks Bay",
    "iso:country":"CA",
    "sg:address":"23 Bright Oaks Bay",
    "sg:city":"Winnipeg",
    "sg:classifiers":[
        {
            "category":"Building & Trades",
            "subcategory":"Cleaning & Sanitation",
            "type":"Services"
        }
    ],
    "sg:phone":"+1 204 255 9426",
    "sg:postcode":"R2M 2L9",
    "sg:province":"MB",
    "sg:tags":[
        "steam"
    ],
    "wof:name":"Wash-All Mobile High Pressure",
    "wof:placetype":"venue"
},
  "geometry": {"coordinates":[-97.12222300000001,49.825901],"type":"Point"}
}