{
  "type": "Feature",
  "properties": {
    "iso:country":"CA",
    "sg:address":"4324 Garnet St",
    "sg:city":"Regina",
    "sg:classifiers":[
        {
            "category":"Professional",
            "subcategory":"Computer Services",
            "type":"Services"
        }
    ],
    "sg:phone":"+1 306 584 0641",
    "sg:postcode":"S4S 3H4",
    "sg:province":"SK",
    "sg:tags":[
        "consultant"
    ],
    "wof:name":"Tda Systems Inc",
    "wof:placetype":"venue"
},
  "geometry": {"coordinates":[-104.627007,50.410412],"type":"Point"}
}