{
  "type": "Feature",
  "properties": {
    "addr:full":"5186 Elmridge Dr Mississauga ON L5M 5A4",
    "addr:housenumber":"5186",
    "addr:postcode":"l5m 5a4",
    "addr:street":"Elmridge Dr",
    "iso:country":"CA",
    "sg:address":"5186 Elmridge Dr",
    "sg:city":"Mississauga",
    "sg:classifiers":[
        {
            "category":"Professional",
            "subcategory":"Business Services",
            "type":"Services"
        }
    ],
    "sg:phone":"+1 905 569 6115",
    "sg:postcode":"L5M 5A4",
    "sg:province":"ON",
    "wof:name":"Rkw Wine Imports",
    "wof:placetype":"venue"
},
  "geometry": {"coordinates":[-79.7044830322,43.5686454773],"type":"Point"}
}