{
  "type": "Feature",
  "properties": {
    "addr:full":"702 7th St E North Vancouver BC V7L 1S6",
    "addr:housenumber":"702",
    "addr:postcode":"v7l 1s6",
    "addr:street":"7Th St E",
    "iso:country":"CA",
    "sg:address":"702 7th St E",
    "sg:city":"North Vancouver",
    "sg:classifiers":[
        {
            "category":"Health Services",
            "subcategory":"Chiropractor",
            "type":"Services"
        }
    ],
    "sg:phone":"+1 604 985 7485",
    "sg:postcode":"V7L 1S6",
    "sg:province":"BC",
    "wof:name":"Cameron, William A DC",
    "wof:placetype":"venue"
},
  "geometry": {"coordinates":[-123.056786,49.312599],"type":"Point"}
}