{
  "type": "Feature",
  "properties": {
    "addr:full":"1117 Av Olier-Payette Laval QC H7L 5L3",
    "addr:housenumber":"1117",
    "addr:postcode":"h7l 5l3",
    "addr:street":"Av Olier-Payette",
    "iso:country":"CA",
    "sg:address":"1117 Av Olier-Payette",
    "sg:city":"Laval",
    "sg:classifiers":[
        {
            "category":"Building & Trades",
            "subcategory":"Construction",
            "type":"Services"
        }
    ],
    "sg:phone":"+1 450 625 1502",
    "sg:postcode":"H7L 5L3",
    "sg:province":"QC",
    "sg:tags":[
        "excavating",
        "contractor"
    ],
    "wof:name":"Excavation Gaetan Vanier",
    "wof:placetype":"venue"
},
  "geometry": {"coordinates":[-73.7763519287,45.6224746704],"type":"Point"}
}