{
  "type": "Feature",
  "properties": {
    "iso:country":"CA",
    "sg:address":"578 Cook St",
    "sg:city":"Boissevain",
    "sg:classifiers":[
        {
            "category":"Health Services",
            "subcategory":"Health Practitioner",
            "type":"Services"
        }
    ],
    "sg:phone":"+1 204 534 7220",
    "sg:postcode":"R0K 0E0",
    "sg:province":"MB",
    "sg:tags":[
        "physiotherapist"
    ],
    "wof:name":"Turtle Mountain Physiotherapy",
    "wof:placetype":"venue"
},
  "geometry": {"coordinates":[-100.059455872,49.2296257019],"type":"Point"}
}