{
  "type": "Feature",
  "properties": {
    "iso:country":"CA",
    "sg:city":"Mississauga",
    "sg:classifiers":[
        {
            "category":"Manufacturing",
            "subcategory":"Rubber & Plastics",
            "type":"Manufacturing & Wholesale Goods"
        }
    ],
    "sg:phone":"+1 905 564 3455",
    "sg:postcode":"L5T 1N3",
    "sg:province":"ON",
    "sg:tags":[
        "mold",
        "maker"
    ],
    "wof:name":"Top Tech Specialist",
    "wof:placetype":"venue"
},
  "geometry": {"coordinates":[-79.64302062989999,43.6630859375],"type":"Point"}
}