{
  "type": "Feature",
  "properties": {
    "addr:full":"280 North Service Rd W Oakville ON L6M 2S2",
    "addr:housenumber":"280",
    "addr:postcode":"l6m 2s2",
    "addr:street":"North Service Rd W",
    "iso:country":"CA",
    "sg:address":"280 North Service Rd W",
    "sg:city":"Oakville",
    "sg:classifiers":[
        {
            "category":"Real Estate",
            "subcategory":"Real Estate Agent",
            "type":"Services"
        }
    ],
    "sg:phone":"+1 905 634 0166",
    "sg:postcode":"L6M 2S2",
    "sg:province":"ON",
    "sg:tags":[
        "relocation"
    ],
    "wof:name":"Orbis International Inc",
    "wof:placetype":"venue"
},
  "geometry": {"coordinates":[-79.70639,43.446381],"type":"Point"}
}