{
  "type": "Feature",
  "properties": {
    "addr:full":"8997 Hwy 11 N Cumberland Beach ON L0K 1G0",
    "addr:housenumber":"8997",
    "addr:postcode":"l0k 1g0",
    "addr:street":"Hwy 11 N",
    "iso:country":"CA",
    "sg:address":"8997 Hwy 11 N",
    "sg:city":"Cumberland Beach",
    "sg:classifiers":[
        {
            "category":"Autos & Motor Vehicles",
            "subcategory":"Boat Sales",
            "type":"Retail Goods"
        }
    ],
    "sg:phone":"+1 705 689 5533",
    "sg:postcode":"L0K 1G0",
    "sg:province":"ON",
    "sg:tags":[
        "dealer"
    ],
    "wof:name":"Bayou Park Marine",
    "wof:placetype":"venue"
},
  "geometry": {"coordinates":[-79.396683,44.698536],"type":"Point"}
}