{
  "type": "Feature",
  "properties": {
    "addr:full":"239 Westbrook Rd Carp ON K0A 1L0",
    "addr:housenumber":"239",
    "addr:postcode":"k0a 1l0",
    "addr:street":"Westbrook Rd",
    "iso:country":"CA",
    "sg:address":"239 Westbrook Rd",
    "sg:city":"Carp",
    "sg:classifiers":[
        {
            "category":"Building & Trades",
            "subcategory":"Electrical",
            "type":"Services"
        }
    ],
    "sg:phone":"+1 613 831 4033",
    "sg:postcode":"K0A 1L0",
    "sg:province":"ON",
    "sg:tags":[
        "electric",
        "contractor"
    ],
    "wof:name":"Betron Electric Ltd",
    "wof:placetype":"venue"
},
  "geometry": {"coordinates":[-76.042587,45.350044],"type":"Point"}
}