{
  "type": "Feature",
  "properties": {
    "addr:full":"22 Vienna St Hamilton ON L8G 4R3",
    "addr:housenumber":"22",
    "addr:postcode":"l8g 4r3",
    "addr:street":"Vienna St",
    "iso:country":"CA",
    "sg:address":"22 Vienna St",
    "sg:city":"Hamilton",
    "sg:classifiers":[
        {
            "category":"Building & Trades",
            "subcategory":"Construction",
            "type":"Services"
        }
    ],
    "sg:phone":"+1 905 561 8758",
    "sg:postcode":"L8G 4R3",
    "sg:province":"ON",
    "sg:tags":[
        "tile",
        "dealer"
    ],
    "wof:name":"Queens Tile",
    "wof:placetype":"venue"
},
  "geometry": {"coordinates":[-79.77211800000001,43.219013],"type":"Point"}
}