{
  "type": "Feature",
  "properties": {
    "addr:full":"1869 Rue L.-O.-David Montreal QC H2E 1K5",
    "addr:housenumber":"1869",
    "addr:postcode":"h2e 1k5",
    "addr:street":"Rue L.-O.-David",
    "iso:country":"CA",
    "sg:address":"1869 Rue L.-O.-David",
    "sg:city":"Montreal",
    "sg:classifiers":[
        {
            "category":"Cinema",
            "subcategory":"Movie Rental",
            "type":"Entertainment"
        }
    ],
    "sg:phone":"+1 514 723 6068",
    "sg:postcode":"H2E 1K5",
    "sg:province":"QC",
    "sg:tags":[
        "leasing",
        "video",
        "disc",
        "tape"
    ],
    "wof:name":"Video Luxe Inc",
    "wof:placetype":"venue"
},
  "geometry": {"coordinates":[-73.61315917970001,45.551197052],"type":"Point"}
}