{
  "type": "Feature",
  "properties": {
    "addr:full":"121 Ontario St Sarnia ON N7T 1K9",
    "addr:housenumber":"121",
    "addr:postcode":"n7t 1k9",
    "addr:street":"Ontario St",
    "iso:country":"CA",
    "sg:address":"121 Ontario St",
    "sg:city":"Sarnia",
    "sg:classifiers":[
        {
            "category":"Restaurant",
            "type":"Food & Drink"
        }
    ],
    "sg:phone":"+1 519 336 2776",
    "sg:postcode":"N7T 1K9",
    "sg:province":"ON",
    "wof:name":"Dempsey's Bar & Grill",
    "wof:placetype":"venue"
},
  "geometry": {"coordinates":[-82.397507,42.967918],"type":"Point"}
}