{
  "type": "Feature",
  "properties": {
    "addr:full":"14370 Upper Mud River Rd Prince George BC V2N 6K6",
    "addr:housenumber":"14370",
    "addr:postcode":"v2n 6k6",
    "addr:street":"Upper Mud River Rd",
    "iso:country":"CA",
    "sg:address":"14370 Upper Mud River Rd",
    "sg:city":"Prince George",
    "sg:classifiers":[
        {
            "category":"Wholesale",
            "subcategory":"Machinery & Supplies",
            "type":"Manufacturing & Wholesale Goods"
        }
    ],
    "sg:phone":"+1 250 560 5502",
    "sg:postcode":"V2N 6K6",
    "sg:province":"BC",
    "sg:tags":[
        "farm",
        "equipment"
    ],
    "wof:name":"Huber Farm Equipment Ltd",
    "wof:placetype":"venue"
},
  "geometry": {"coordinates":[-122.745087,53.91235],"type":"Point"}
}