{
  "type": "Feature",
  "properties": {
    "addr:full":"4444 10th Ave W Vancouver BC V6R 2H9",
    "addr:housenumber":"4444",
    "addr:postcode":"v6r 2h9",
    "addr:street":"10Th Ave W",
    "iso:country":"CA",
    "sg:address":"4444 10th Ave W",
    "sg:city":"Vancouver",
    "sg:classifiers":[
        {
            "category":"Shopping",
            "subcategory":"Books",
            "type":"Retail Goods"
        }
    ],
    "sg:phone":"+1 604 221 5744",
    "sg:postcode":"V6R 2H9",
    "sg:province":"BC",
    "sg:tags":[
        "dealer"
    ],
    "wof:name":"Book Warehouse",
    "wof:placetype":"venue"
},
  "geometry": {"coordinates":[-123.207481384,49.263671875],"type":"Point"}
}