{
  "type": "Feature",
  "properties": {
    "addr:full":"876 Rue Perreault Chibougamau QC G8P 2K3",
    "addr:housenumber":"876",
    "addr:postcode":"g8p 2k3",
    "addr:street":"Rue Perreault",
    "iso:country":"CA",
    "sg:address":"876 Rue Perreault",
    "sg:city":"Chibougamau",
    "sg:classifiers":[
        {
            "category":"Manufacturing",
            "subcategory":"Tools & Machinery",
            "type":"Manufacturing & Wholesale Goods"
        }
    ],
    "sg:phone":"+1 418 748 6442",
    "sg:postcode":"G8P 2K3",
    "sg:province":"QC",
    "wof:name":"Metallisation Du Nord Inc",
    "wof:placetype":"venue"
},
  "geometry": {"coordinates":[-74.3858718872,49.9128341675],"type":"Point"}
}