{
  "type": "Feature",
  "properties": {
    "addr:full":"345 Melrose Ave North York ON M5M 1Z5",
    "addr:housenumber":"345",
    "addr:postcode":"m5m 1z5",
    "addr:street":"Melrose Ave",
    "iso:country":"CA",
    "sg:address":"345 Melrose Ave",
    "sg:city":"North York",
    "sg:classifiers":[
        {
            "category":"Shopping",
            "type":"Retail Goods"
        }
    ],
    "sg:phone":"+1 416 781 7450",
    "sg:postcode":"M5M 1Z5",
    "sg:province":"ON",
    "sg:tags":[
        "art",
        "gallery",
        "restoring",
        "dealer"
    ],
    "wof:name":"In Restauro",
    "wof:placetype":"venue"
},
  "geometry": {"coordinates":[-79.41793800000001,43.729874],"type":"Point"}
}