{
  "type": "Feature",
  "properties": {
    "addr:full":"Mississauga ON L4W 2Z4",
    "addr:postcode":"l4w 2z4",
    "iso:country":"CA",
    "sg:city":"Mississauga",
    "sg:classifiers":[
        {
            "category":"Manufacturing",
            "subcategory":"Tools & Machinery",
            "type":"Manufacturing & Wholesale Goods"
        }
    ],
    "sg:phone":"+1 905 206 0640",
    "sg:postcode":"L4W 2Z4",
    "sg:province":"ON",
    "sg:tags":[
        "machine",
        "shop"
    ],
    "wof:name":"Dieroll Tool Inc",
    "wof:placetype":"venue"
},
  "geometry": {"coordinates":[-79.6459350586,43.6364631653],"type":"Point"}
}