{
  "type": "Feature",
  "properties": {
    "addr:full":"733 Main St E Hawkesbury ON K6A 1B3",
    "addr:housenumber":"733",
    "addr:postcode":"k6a 1b3",
    "addr:street":"Main St E",
    "iso:country":"CA",
    "sg:address":"733 Main St E",
    "sg:city":"Hawkesbury",
    "sg:classifiers":[
        {
            "category":"Manufacturing",
            "subcategory":"Glass & Minerals",
            "type":"Manufacturing & Wholesale Goods"
        }
    ],
    "sg:phone":"+1 613 632 8115",
    "sg:postcode":"K6A 1B3",
    "sg:province":"ON",
    "sg:tags":[
        "granite",
        "monument"
    ],
    "wof:name":"Gaboriault & Nevers Regd",
    "wof:placetype":"venue"
},
  "geometry": {"coordinates":[-74.59903,45.610626],"type":"Point"}
}