{
  "type": "Feature",
  "properties": {
    "iso:country":"CA",
    "sg:city":"Surrey",
    "sg:classifiers":[
        {
            "category":"Personal",
            "subcategory":"Beauty Salon",
            "type":"Services"
        }
    ],
    "sg:phone":"+1 604 581 1153",
    "sg:postcode":"V4N 1P3",
    "sg:province":"BC",
    "wof:name":"Champers",
    "wof:placetype":"venue"
},
  "geometry": {"coordinates":[-122.778869629,49.1993484497],"type":"Point"}
}