{
  "type": "Feature",
  "properties": {
    "iso:country":"CA",
    "sg:address":"170 St. George St",
    "sg:city":"Toronto",
    "sg:classifiers":[
        {
            "category":"Health Services",
            "subcategory":"Health Practitioner",
            "type":"Services"
        }
    ],
    "sg:phone":"+1 416 961 8962",
    "sg:postcode":"M5R 2M8",
    "sg:province":"ON",
    "sg:tags":[
        "psychologist"
    ],
    "wof:name":"Fisher & Trachtenberg",
    "wof:placetype":"venue"
},
  "geometry": {"coordinates":[-79.40009307859999,43.6676902771],"type":"Point"}
}