{
  "type": "Feature",
  "properties": {
    "addr:full":"864 Saint Marys St Fredericton NB E3A 8S8",
    "addr:housenumber":"864",
    "addr:postcode":"e3a 8s8",
    "addr:street":"Saint Marys St",
    "iso:country":"CA",
    "sg:address":"864 Saint Marys St",
    "sg:city":"Fredericton",
    "sg:classifiers":[
        {
            "category":"Retail",
            "subcategory":"Auto Repair",
            "type":"Services"
        }
    ],
    "sg:phone":"+1 506 450 8317",
    "sg:postcode":"E3A 8S8",
    "sg:province":"NB",
    "sg:tags":[
        "repairing",
        "automobile"
    ],
    "wof:name":"Gunther's Repair & Svc",
    "wof:placetype":"venue"
},
  "geometry": {"coordinates":[-66.6391220093,45.9606399536],"type":"Point"}
}