{
  "type": "Feature",
  "properties": {
    "iso:country":"CA",
    "sg:address":"519 14th St W",
    "sg:city":"North Vancouver",
    "sg:classifiers":[
        {
            "category":"Organizations",
            "subcategory":"Professional Association",
            "type":"Services"
        }
    ],
    "sg:phone":"+1 604 987 0524",
    "sg:postcode":"V7M 1R1",
    "sg:province":"BC",
    "wof:name":"Gurdjieff Foundation of BC",
    "wof:placetype":"venue"
},
  "geometry": {"coordinates":[-123.085327148,49.3209991455],"type":"Point"}
}