{
  "type": "Feature",
  "properties": {
    "addr:full":"299 Northfield Dr E #2 Waterloo ON N2K 4H2",
    "addr:housenumber":"299",
    "addr:postcode":"n2k 4h2",
    "addr:street":"Northfield Dr E # 2",
    "iso:country":"CA",
    "sg:address":"299 Northfield Dr E #2",
    "sg:city":"Waterloo",
    "sg:classifiers":[
        {
            "category":"Building & Trades",
            "subcategory":"Construction",
            "type":"Services"
        }
    ],
    "sg:phone":"+1 519 888 7831",
    "sg:postcode":"N2K 4H2",
    "sg:province":"ON",
    "sg:tags":[
        "resurfacing",
        "material",
        "laying",
        "refinishing",
        "floor"
    ],
    "wof:name":"Pinecrest Custom Flooring",
    "wof:placetype":"venue"
},
  "geometry": {"coordinates":[-80.51960800000001,43.513931],"type":"Point"}
}