{
  "type": "Feature",
  "properties": {
    "addr:full":"176 Arlington Ave Ottawa ON K1R 5S7",
    "addr:housenumber":"176",
    "addr:postcode":"k1r 5s7",
    "addr:street":"Arlington Ave",
    "iso:country":"CA",
    "sg:address":"176 Arlington Ave",
    "sg:city":"Ottawa",
    "sg:classifiers":[
        {
            "category":"Social Services",
            "type":"Services"
        }
    ],
    "sg:phone":"+1 613 232 4667",
    "sg:postcode":"K1R 5S7",
    "sg:province":"ON",
    "sg:tags":[
        "organization",
        "welfare"
    ],
    "wof:name":"Horizon House",
    "wof:placetype":"venue"
},
  "geometry": {"coordinates":[-75.697593689,45.4078941345],"type":"Point"}
}