{
  "type": "Feature",
  "properties": {
    "addr:full":"7760 Rue LA Fontaine Montreal QC H1L 3H2",
    "addr:housenumber":"7760",
    "addr:postcode":"h1l 3h2",
    "addr:street":"Rue La Fontaine",
    "iso:country":"CA",
    "sg:address":"7760 Rue LA Fontaine",
    "sg:city":"Montreal",
    "sg:classifiers":[
        {
            "category":"Education",
            "subcategory":"School",
            "type":"Public Place"
        }
    ],
    "sg:phone":"+1 514 596 4889",
    "sg:postcode":"H1L 3H2",
    "sg:province":"QC",
    "wof:name":"Boucher-DE-LA Bruere Ecole",
    "wof:placetype":"venue"
},
  "geometry": {"coordinates":[-73.513519,45.588066],"type":"Point"}
}