{
  "type": "Feature",
  "properties": {
    "addr:full":"151 High St Southampton ON N0H 2L0",
    "addr:housenumber":"151",
    "addr:postcode":"n0h 2l0",
    "addr:street":"High St",
    "iso:country":"CA",
    "sg:address":"151 High St",
    "sg:city":"Southampton",
    "sg:classifiers":[
        {
            "category":"Restaurant",
            "type":"Food & Drink"
        }
    ],
    "sg:phone":"+1 519 797 5972",
    "sg:postcode":"N0H 2L0",
    "sg:province":"ON",
    "wof:name":"Duffy's Famous Fish & Chips",
    "wof:placetype":"venue"
},
  "geometry": {"coordinates":[-81.37311553959999,44.4961051941],"type":"Point"}
}