{
  "type": "Feature",
  "properties": {
    "addr:full":"66 Barrie View Dr Barrie ON L4N 8V4",
    "addr:housenumber":"66",
    "addr:postcode":"l4n 8v4",
    "addr:street":"Barrie View Dr",
    "iso:country":"CA",
    "sg:address":"66 Barrie View Dr",
    "sg:city":"Barrie",
    "sg:classifiers":[
        {
            "category":"Restaurant",
            "type":"Food & Drink"
        }
    ],
    "sg:phone":"+1 705 726 3375",
    "sg:postcode":"L4N 8V4",
    "sg:province":"ON",
    "wof:name":"Montana's Cookhouse Saloon",
    "wof:placetype":"venue"
},
  "geometry": {"coordinates":[-79.68810999999999,44.33672],"type":"Point"}
}