{
  "type": "Feature",
  "properties": {
    "addr:full":"352 Danforth Ave Ottawa ON K2A 0E2",
    "addr:housenumber":"352",
    "addr:postcode":"k2a 0e2",
    "addr:street":"Danforth Ave",
    "iso:country":"CA",
    "sg:address":"352 Danforth Ave",
    "sg:city":"Ottawa",
    "sg:classifiers":[
        {
            "category":"Real Estate",
            "subcategory":"Real Estate Agent",
            "type":"Services"
        }
    ],
    "sg:phone":"+1 613 722 2239",
    "sg:postcode":"K2A 0E2",
    "sg:province":"ON",
    "sg:tags":[
        "management"
    ],
    "wof:name":"Quality Control Intl",
    "wof:placetype":"venue"
},
  "geometry": {"coordinates":[-75.75488300000001,45.390583],"type":"Point"}
}