{
  "type": "Feature",
  "properties": {
    "iso:country":"CA",
    "sg:address":"79 Denvale Rd",
    "sg:city":"East York",
    "sg:classifiers":[
        {
            "category":"Building & Trades",
            "subcategory":"Construction",
            "type":"Services"
        }
    ],
    "sg:phone":"+1 416 463 2424",
    "sg:postcode":"M4B 3B3",
    "sg:province":"ON",
    "sg:tags":[
        "resurfacing",
        "laying",
        "refinishing",
        "floor"
    ],
    "wof:name":"Olympic Floor Sanding",
    "wof:placetype":"venue"
},
  "geometry": {"coordinates":[-79.31755065919999,43.7079391479],"type":"Point"}
}