{
  "type": "Feature",
  "properties": {
    "iso:country":"CA",
    "sg:address":"354 Pape Ave",
    "sg:city":"Toronto",
    "sg:classifiers":[
        {
            "category":"Building & Trades",
            "subcategory":"Construction",
            "type":"Services"
        }
    ],
    "sg:phone":"+1 416 469 1754",
    "sg:postcode":"M4M 2X1",
    "sg:province":"ON",
    "sg:tags":[
        "general",
        "contractor"
    ],
    "wof:name":"Global Industrial Comm Engr",
    "wof:placetype":"venue"
},
  "geometry": {"coordinates":[-79.340675354,43.668422699],"type":"Point"}
}