{
  "type": "Feature",
  "properties": {
    "iso:country":"CA",
    "sg:address":"1551 Rue Dagenais",
    "sg:city":"Sherbrooke",
    "sg:classifiers":[
        {
            "category":"Building & Trades",
            "subcategory":"Construction",
            "type":"Services"
        }
    ],
    "sg:phone":"+1 819 563 1342",
    "sg:postcode":"J1G 2B4",
    "sg:province":"QC",
    "sg:tags":[
        "general",
        "contractor"
    ],
    "wof:name":"Tardec Construction Inc",
    "wof:placetype":"venue"
},
  "geometry": {"coordinates":[-71.8598251343,45.3883399963],"type":"Point"}
}