{
  "type": "Feature",
  "properties": {
    "addr:full":"1670 75th Ave W Vancouver BC V6P 6G2",
    "addr:housenumber":"1670",
    "addr:postcode":"v6p 6g2",
    "addr:street":"75Th Ave W",
    "iso:country":"CA",
    "sg:address":"1670 75th Ave W",
    "sg:city":"Vancouver",
    "sg:classifiers":[
        {
            "category":"Professional",
            "subcategory":"Management & Consulting",
            "type":"Services"
        }
    ],
    "sg:phone":"+1 604 731 3131",
    "sg:postcode":"V6P 6G2",
    "sg:province":"BC",
    "sg:tags":[
        "agricultural",
        "consultant"
    ],
    "wof:name":"Talisman Land Resource Conslnt",
    "wof:placetype":"venue"
},
  "geometry": {"coordinates":[-123.14566000000001,49.20557],"type":"Point"}
}