{
  "type": "Feature",
  "properties": {
    "addr:full":"8218 30 St SE Calgary AB T2C 1H8",
    "addr:housenumber":"8218",
    "addr:postcode":"t2c 1h8",
    "addr:street":"30 St Se",
    "iso:country":"CA",
    "sg:address":"8218 30 St SE",
    "sg:city":"Calgary",
    "sg:classifiers":[
        {
            "category":"Autos & Motor Vehicles",
            "subcategory":"Boat Sales",
            "type":"Retail Goods"
        }
    ],
    "sg:phone":"+1 403 279 5510",
    "sg:postcode":"T2C 1H8",
    "sg:province":"AB",
    "sg:tags":[
        "dealer"
    ],
    "wof:name":"B & L Marine",
    "wof:placetype":"venue"
},
  "geometry": {"coordinates":[-113.98893700000001,50.981544],"type":"Point"}
}