{
  "type": "Feature",
  "properties": {
    "addr:full":"994 Bathurst St Toronto ON M5R 3G7",
    "addr:housenumber":"994",
    "addr:postcode":"m5r 3g7",
    "addr:street":"Bathurst St",
    "iso:country":"CA",
    "sg:address":"994 Bathurst St",
    "sg:city":"Toronto",
    "sg:classifiers":[
        {
            "category":"Food & Beverages",
            "subcategory":"Groceries & Convenience Stores",
            "type":"Retail Goods"
        }
    ],
    "sg:phone":"+1 416 537 0844",
    "sg:postcode":"M5R 3G7",
    "sg:province":"ON",
    "wof:name":"Olive Convenience",
    "wof:placetype":"venue"
},
  "geometry": {"coordinates":[-79.4135055542,43.6705207825],"type":"Point"}
}