{
  "type": "Feature",
  "properties": {
    "addr:full":"815 7 Ave SW Calgary AB T2P 1A2",
    "addr:housenumber":"815",
    "addr:postcode":"t2p 1a2",
    "addr:street":"7 Ave Sw",
    "iso:country":"CA",
    "sg:address":"815 7 Ave SW",
    "sg:city":"Calgary",
    "sg:classifiers":[
        {
            "category":"Restaurant",
            "type":"Food & Drink"
        }
    ],
    "sg:phone":"+1 403 266 1551",
    "sg:postcode":"T2P 1A2",
    "sg:province":"AB",
    "wof:name":"Oh Canada Restaurant & Bar",
    "wof:placetype":"venue"
},
  "geometry": {"coordinates":[-114.079285,51.046814],"type":"Point"}
}