{
  "type": "Feature",
  "properties": {
    "addr:full":"200 Westhill Estate Penticton BC V2A 6J7",
    "addr:housenumber":"200",
    "addr:postcode":"v2a 6j7",
    "addr:street":"Westhill Estate",
    "iso:country":"CA",
    "sg:address":"200 Westhill Estate",
    "sg:city":"Penticton",
    "sg:classifiers":[
        {
            "category":"Organizations",
            "subcategory":"Professional Association",
            "type":"Services"
        }
    ],
    "sg:phone":"+1 250 770 3210",
    "sg:postcode":"V2A 6J7",
    "sg:province":"BC",
    "sg:tags":[
        "school"
    ],
    "wof:name":"Penticton Indian Band Edctn",
    "wof:placetype":"venue"
},
  "geometry": {"coordinates":[-119.593857,49.500229],"type":"Point"}
}