{
  "type": "Feature",
  "properties": {
    "addr:full":"Mascouche QC J7K 2L7",
    "addr:postcode":"j7k 2l7",
    "iso:country":"CA",
    "sg:city":"Mascouche",
    "sg:classifiers":[
        {
            "category":"Health Services",
            "subcategory":"Health Practitioner",
            "type":"Services"
        }
    ],
    "sg:phone":"+1 450 474 5583",
    "sg:postcode":"J7K 2L7",
    "sg:province":"QC",
    "sg:tags":[
        "physiotherapist",
        "clinic"
    ],
    "wof:name":"Physiotherapie DE Mascouche",
    "wof:placetype":"venue"
},
  "geometry": {"coordinates":[-73.60869599999999,45.743694],"type":"Point"}
}