{
  "type": "Feature",
  "properties": {
    "addr:full":"1100 Dundas St W # 14 Mississauga ON L5C 4E7",
    "addr:housenumber":"1100",
    "addr:postcode":"l5c 4e7",
    "addr:street":"Dundas St W # 14",
    "iso:country":"CA",
    "sg:address":"1100 Dundas St W # 14",
    "sg:city":"Mississauga",
    "sg:classifiers":[
        {
            "category":"Shopping",
            "type":"Retail Goods"
        }
    ],
    "sg:phone":"+1 905 566 5955",
    "sg:postcode":"L5C 4E7",
    "sg:province":"ON",
    "sg:tags":[
        "art",
        "gallery",
        "dealer"
    ],
    "wof:name":"Lily of the Valley Art Gallery",
    "wof:placetype":"venue"
},
  "geometry": {"coordinates":[-79.64318799999999,43.556862],"type":"Point"}
}