{
  "type": "Feature",
  "properties": {
    "addr:full":"138 Main St Toronto ON M4E 2V8",
    "addr:housenumber":"138",
    "addr:postcode":"m4e 2v8",
    "addr:street":"Main St",
    "iso:country":"CA",
    "sg:address":"138 Main St",
    "sg:city":"Toronto",
    "sg:classifiers":[
        {
            "category":"Manufacturing",
            "subcategory":"Printing",
            "type":"Manufacturing & Wholesale Goods"
        }
    ],
    "sg:phone":"+1 416 698 7608",
    "sg:postcode":"M4E 2V8",
    "sg:province":"ON",
    "sg:tags":[
        "printer"
    ],
    "wof:name":"Britannia Printers",
    "wof:placetype":"venue"
},
  "geometry": {"coordinates":[-79.300034,43.683094],"type":"Point"}
}