{
  "type": "Feature",
  "properties": {
    "addr:full":"522 Glen Morris Rd E Glen Morris ON N0B 1W0",
    "addr:housenumber":"522",
    "addr:postcode":"n0b 1w0",
    "addr:street":"Glen Morris Rd E Glen",
    "iso:country":"CA",
    "sg:address":"522 Glen Morris Rd E",
    "sg:city":"Glen Morris",
    "sg:classifiers":[
        {
            "category":"Education",
            "subcategory":"School",
            "type":"Public Place"
        }
    ],
    "sg:phone":"+1 519 740 2133",
    "sg:postcode":"N0B 1W0",
    "sg:province":"ON",
    "wof:name":"Glen Morris Central School",
    "wof:placetype":"venue"
},
  "geometry": {"coordinates":[-80.34446699999999,43.27322],"type":"Point"}
}