{
  "type": "Feature",
  "properties": {
    "addr:full":"900 Av Lariviere Rouyn-Noranda QC J9X 4K5",
    "addr:housenumber":"900",
    "addr:postcode":"j9x 4k5",
    "addr:street":"Av Lariviere",
    "iso:country":"CA",
    "sg:address":"900 Av Lariviere",
    "sg:city":"Rouyn-Noranda",
    "sg:classifiers":[
        {
            "category":"Wholesale",
            "subcategory":"Meat",
            "type":"Manufacturing & Wholesale Goods"
        }
    ],
    "sg:phone":"+1 819 762 9291",
    "sg:postcode":"J9X 4K5",
    "sg:province":"QC",
    "sg:tags":[
        "butchering"
    ],
    "wof:name":"Maison Des Viandes",
    "wof:placetype":"venue"
},
  "geometry": {"coordinates":[-79.00103759770001,48.225151062],"type":"Point"}
}