{
  "type": "Feature",
  "properties": {
    "addr:full":"933 Barton St Stoney Creek ON L8E 5P5",
    "addr:housenumber":"933",
    "addr:postcode":"l8e 5p5",
    "addr:street":"Barton St",
    "iso:country":"CA",
    "sg:address":"933 Barton St",
    "sg:city":"Stoney Creek",
    "sg:classifiers":[
        {
            "category":"Manufacturing",
            "subcategory":"Tools & Machinery",
            "type":"Manufacturing & Wholesale Goods"
        }
    ],
    "sg:phone":"+1 905 643 7778",
    "sg:postcode":"L8E 5P5",
    "sg:province":"ON",
    "sg:tags":[
        "equipment",
        "hydraulic",
        "supply"
    ],
    "wof:name":"Berendsen Fluid Power Ltd",
    "wof:placetype":"venue"
},
  "geometry": {"coordinates":[-79.676582,43.216961],"type":"Point"}
}