{
  "type": "Feature",
  "properties": {
    "iso:country":"CA",
    "sg:address":"1420 Johnson Rd",
    "sg:city":"Agassiz",
    "sg:classifiers":[
        {
            "category":"Building & Trades",
            "subcategory":"Construction",
            "type":"Services"
        }
    ],
    "sg:phone":"+1 604 991 0900",
    "sg:postcode":"V0M 1A2",
    "sg:province":"BC",
    "sg:tags":[
        "excavating",
        "contractor"
    ],
    "wof:name":"Sam's Bobcat Svc",
    "wof:placetype":"venue"
},
  "geometry": {"coordinates":[-121.76375579800001,49.2383041382],"type":"Point"}
}