{
  "type": "Feature",
  "properties": {
    "iso:country":"CA",
    "sg:address":"132 Willow Rd",
    "sg:city":"Atikokan",
    "sg:classifiers":[
        {
            "category":"Building & Trades",
            "subcategory":"Construction",
            "type":"Services"
        }
    ],
    "sg:phone":"+1 807 597 2212",
    "sg:postcode":"P0T 1C0",
    "sg:province":"ON",
    "sg:tags":[
        "general",
        "contractor"
    ],
    "wof:name":"Eric Rasinaho Contracting",
    "wof:placetype":"venue"
},
  "geometry": {"coordinates":[-91.5977096558,48.7617912292],"type":"Point"}
}