{
  "type": "Feature",
  "properties": {
    "addr:full":"75 Advance Blvd Brampton ON L6T 4N1",
    "addr:housenumber":"75",
    "addr:postcode":"l6t 4n1",
    "addr:street":"Advance Blvd",
    "iso:country":"CA",
    "sg:address":"75 Advance Blvd",
    "sg:city":"Brampton",
    "sg:classifiers":[
        {
            "category":"Manufacturing",
            "subcategory":"Chemicals & Compounds",
            "type":"Manufacturing & Wholesale Goods"
        }
    ],
    "sg:phone":"+1 905 793 4311",
    "sg:postcode":"L6T 4N1",
    "sg:province":"ON",
    "wof:name":"Kleen Flo Tumbler Industries",
    "wof:placetype":"venue"
},
  "geometry": {"coordinates":[-79.69425200000001,43.696693],"type":"Point"}
}