{
  "type": "Feature",
  "properties": {
    "addr:full":"2451 Boul Fernand-Lafontaine Longueuil QC J4N 1N7",
    "addr:housenumber":"2451",
    "addr:postcode":"j4n 1n7",
    "addr:street":"Boul Fernand-Lafontaine",
    "iso:country":"CA",
    "sg:address":"2451 Boul Fernand-Lafontaine",
    "sg:city":"Longueuil",
    "sg:classifiers":[
        {
            "category":"Building & Trades",
            "subcategory":"Electrical",
            "type":"Services"
        }
    ],
    "sg:phone":"+1 514 890 6152",
    "sg:postcode":"J4N 1N7",
    "sg:province":"QC",
    "sg:tags":[
        "fiber",
        "optics",
        "electric",
        "contractor"
    ],
    "wof:name":"Enixum",
    "wof:placetype":"venue"
},
  "geometry": {"coordinates":[-73.45291137700001,45.5619735718],"type":"Point"}
}