{
  "type": "Feature",
  "properties": {
    "addr:full":"33775 South Fraser Way Abbotsford BC V2S 2C3",
    "addr:housenumber":"33775",
    "addr:postcode":"v2s 2c3",
    "addr:street":"South Fraser Way",
    "iso:country":"CA",
    "sg:address":"33775 South Fraser Way",
    "sg:city":"Abbotsford",
    "sg:classifiers":[
        {
            "category":"Shopping",
            "subcategory":"Jewelry",
            "type":"Retail Goods"
        }
    ],
    "sg:phone":"+1 604 852 3848",
    "sg:postcode":"V2S 2C3",
    "sg:province":"BC",
    "sg:tags":[
        "jeweler"
    ],
    "wof:name":"Spotlight Jewellers",
    "wof:placetype":"venue"
},
  "geometry": {"coordinates":[-122.289558411,49.0472564697],"type":"Point"}
}