{
  "type": "Feature",
  "properties": {
    "addr:full":"28 Ottawa St Morrisburg ON K0C 1X0",
    "addr:housenumber":"28",
    "addr:postcode":"k0c 1x0",
    "addr:street":"Ottawa St",
    "iso:country":"CA",
    "sg:address":"28 Ottawa St",
    "sg:city":"Morrisburg",
    "sg:classifiers":[
        {
            "category":"Education",
            "subcategory":"Library",
            "type":"Public Place"
        }
    ],
    "sg:phone":"+1 613 543 3384",
    "sg:postcode":"K0C 1X0",
    "sg:province":"ON",
    "wof:name":"Morrisburg Public Library",
    "wof:placetype":"venue"
},
  "geometry": {"coordinates":[-75.182243,44.896542],"type":"Point"}
}