{
  "type": "Feature",
  "properties": {
    "iso:country":"CA",
    "sg:address":"110 Old Kingston Rd",
    "sg:city":"Ajax",
    "sg:classifiers":[
        {
            "category":"Professional",
            "subcategory":"Engineering",
            "type":"Services"
        }
    ],
    "sg:phone":"+1 905 426 9451",
    "sg:postcode":"L1T 2Z9",
    "sg:province":"ON",
    "sg:tags":[
        "engineer"
    ],
    "wof:name":"Sabourin Kimble & Assocs Ltd",
    "wof:placetype":"venue"
},
  "geometry": {"coordinates":[-79.0600814819,43.8543891907],"type":"Point"}
}