{
  "type": "Feature",
  "properties": {
    "addr:full":"1 Jones St Baddeck NS B0E 1B0",
    "addr:housenumber":"1",
    "addr:postcode":"b0e 1b0",
    "addr:street":"Jones St",
    "iso:country":"CA",
    "sg:address":"1 Jones St",
    "sg:city":"Baddeck",
    "sg:classifiers":[
        {
            "category":"Recreation",
            "subcategory":"Marina",
            "type":"Entertainment"
        }
    ],
    "sg:phone":"+1 902 295 2107",
    "sg:postcode":"B0E 1B0",
    "sg:province":"NS",
    "wof:name":"Bras D'Or Yacht Club",
    "wof:placetype":"venue"
},
  "geometry": {"coordinates":[-60.752605,46.099873],"type":"Point"}
}