{
  "type": "Feature",
  "properties": {
    "addr:full":"601 Rte Lagueux Saint-Nicolas QC G7A 1A7",
    "addr:housenumber":"601",
    "addr:postcode":"g7a 1a7",
    "addr:street":"Rte Lagueux",
    "iso:country":"CA",
    "sg:address":"601 Rte Lagueux",
    "sg:city":"Saint-Nicolas",
    "sg:classifiers":[
        {
            "category":"Professional",
            "subcategory":"Business Services",
            "type":"Services"
        }
    ],
    "sg:phone":"+1 418 831 7656",
    "sg:postcode":"G7A 1A7",
    "sg:province":"QC",
    "sg:tags":[
        "auctioneer"
    ],
    "wof:name":"Encheres Fly Quebec Inc",
    "wof:placetype":"venue"
},
  "geometry": {"coordinates":[-71.338638,46.670601],"type":"Point"}
}