{
  "type": "Feature",
  "properties": {
    "addr:full":"3 Rue DE LA Gare Masson-Angers QC J8M 1B2",
    "addr:housenumber":"3",
    "addr:postcode":"j8m 1b2",
    "addr:street":"Rue De La Gare",
    "iso:country":"CA",
    "sg:address":"3 Rue DE LA Gare",
    "sg:city":"Masson-Angers",
    "sg:classifiers":[
        {
            "category":"Travel",
            "subcategory":"Hotels & Motels",
            "type":"Entertainment"
        }
    ],
    "sg:phone":"+1 819 986 3765",
    "sg:postcode":"J8M 1B2",
    "sg:province":"QC",
    "wof:name":"Hotel Masson Enr",
    "wof:placetype":"venue"
},
  "geometry": {"coordinates":[-75.42082977290001,45.5467147827],"type":"Point"}
}