{
  "type": "Feature",
  "properties": {
    "addr:full":"576 England Ave # A Courtenay BC V9N 2N3",
    "addr:housenumber":"576",
    "addr:postcode":"v9n 2n3",
    "addr:street":"England Ave # A",
    "iso:country":"CA",
    "sg:address":"576 England Ave # A",
    "sg:city":"Courtenay",
    "sg:classifiers":[
        {
            "category":"Banks & Credit Unions",
            "subcategory":"Bank",
            "type":"Services"
        }
    ],
    "sg:phone":"+1 250 703 0040",
    "sg:postcode":"V9N 2N3",
    "sg:province":"BC",
    "sg:tags":[
        "financing",
        "loan"
    ],
    "wof:name":"Sorensen's Loans 'Til Payday",
    "wof:placetype":"venue"
},
  "geometry": {"coordinates":[-124.999443054,49.6899871826],"type":"Point"}
}