{
  "type": "Feature",
  "properties": {
    "addr:full":"1476 Rue Principale Memramcook NB E4K 2W4",
    "addr:housenumber":"1476",
    "addr:postcode":"e4k 2w4",
    "addr:street":"Rue Principale",
    "iso:country":"CA",
    "sg:address":"1476 Rue Principale",
    "sg:city":"Memramcook",
    "sg:classifiers":[
        {
            "category":"Retail",
            "subcategory":"Auto Repair",
            "type":"Services"
        }
    ],
    "sg:phone":"+1 506 758 9344",
    "sg:postcode":"E4K 2W4",
    "sg:province":"NB",
    "sg:tags":[
        "body",
        "automobile",
        "painting"
    ],
    "wof:name":"Leon Le Blanc Auto Body",
    "wof:placetype":"venue"
},
  "geometry": {"coordinates":[-64.6047744751,45.9395256042],"type":"Point"}
}