{
  "type": "Feature",
  "properties": {
    "iso:country":"CA",
    "sg:address":"393 Roncesvalles Ave",
    "sg:city":"Toronto",
    "sg:classifiers":[
        {
            "category":"Shopping",
            "subcategory":"Music",
            "type":"Retail Goods"
        }
    ],
    "sg:phone":"+1 416 531 6843",
    "sg:postcode":"M6R 2N1",
    "sg:province":"ON",
    "sg:tags":[
        "compact",
        "record",
        "disc",
        "tape"
    ],
    "wof:name":"She Said Boom Records & Books",
    "wof:placetype":"venue"
},
  "geometry": {"coordinates":[-79.4505996704,43.6507759094],"type":"Point"}
}