{
  "type": "Feature",
  "properties": {
    "addr:full":"890 Rue Royale Malartic QC J0Y 1Z0",
    "addr:housenumber":"890",
    "addr:postcode":"j0y 1z0",
    "addr:street":"Rue Royale",
    "iso:country":"CA",
    "sg:address":"890 Rue Royale",
    "sg:city":"Malartic",
    "sg:classifiers":[
        {
            "category":"Health Services",
            "subcategory":"Hospital",
            "type":"Services"
        }
    ],
    "sg:phone":"+1 819 757 6032",
    "sg:postcode":"J0Y 1Z0",
    "sg:province":"QC",
    "sg:tags":[
        "mental"
    ],
    "wof:name":"Groupe Conseil DE Malartic Inc",
    "wof:placetype":"venue"
},
  "geometry": {"coordinates":[-78.12663999999999,48.136326],"type":"Point"}
}