{
  "type": "Feature",
  "properties": {
    "addr:full":"Main St Glentworth SK S0H 1V0",
    "addr:postcode":"s0h 1v0",
    "addr:street":"Main St",
    "iso:country":"CA",
    "sg:address":"Main St",
    "sg:city":"Glentworth",
    "sg:classifiers":[
        {
            "category":"Food & Beverages",
            "subcategory":"Groceries & Convenience Stores",
            "type":"Retail Goods"
        }
    ],
    "sg:phone":"+1 306 266 4224",
    "sg:postcode":"S0H 1V0",
    "sg:province":"SK",
    "sg:tags":[
        "grocer"
    ],
    "wof:name":"Glentworth Country Store Ltd",
    "wof:placetype":"venue"
},
  "geometry": {"coordinates":[-106.68055699999999,49.423367],"type":"Point"}
}