{
  "type": "Feature",
  "properties": {
    "addr:full":"899 Ashburn Rd Saint John NB E2K 5J9",
    "addr:housenumber":"899",
    "addr:postcode":"e2k 5j9",
    "addr:street":"Ashburn Rd",
    "iso:country":"CA",
    "sg:address":"899 Ashburn Rd",
    "sg:city":"Saint John",
    "sg:classifiers":[
        {
            "category":"Manufacturing",
            "subcategory":"Metals",
            "type":"Manufacturing & Wholesale Goods"
        }
    ],
    "sg:phone":"+1 506 634 0034",
    "sg:postcode":"E2K 5J9",
    "sg:province":"NB",
    "sg:tags":[
        "siding",
        "material"
    ],
    "wof:name":"Procanna Siding Materials",
    "wof:placetype":"venue"
},
  "geometry": {"coordinates":[-66.031921,45.30872],"type":"Point"}
}