{
  "type": "Feature",
  "properties": {
    "addr:full":"Lacolle QC J0J 1J0",
    "addr:postcode":"j0j 1j0",
    "iso:country":"CA",
    "sg:city":"Lacolle",
    "sg:classifiers":[
        {
            "category":"Organizations",
            "subcategory":"Religious Organization",
            "type":"Services"
        }
    ],
    "sg:phone":"+1 450 246 2243",
    "sg:postcode":"J0J 1J0",
    "sg:province":"QC",
    "sg:tags":[
        "church"
    ],
    "wof:name":"Lacolle United Church",
    "wof:placetype":"venue"
},
  "geometry": {"coordinates":[-73.37287902830001,45.0811462402],"type":"Point"}
}