{
  "type": "Feature",
  "properties": {
    "addr:full":"22 Housers Lane Woodstock ON N4S 7V9",
    "addr:housenumber":"22",
    "addr:postcode":"n4s 7v9",
    "addr:street":"Housers Lane",
    "iso:country":"CA",
    "sg:address":"22 Housers Lane",
    "sg:city":"Woodstock",
    "sg:classifiers":[
        {
            "category":"Retail",
            "subcategory":"Auto Repair",
            "type":"Services"
        }
    ],
    "sg:phone":"+1 519 421 0550",
    "sg:postcode":"N4S 7V9",
    "sg:province":"ON",
    "sg:tags":[
        "truck"
    ],
    "wof:name":"Spicer's Truck Svc",
    "wof:placetype":"venue"
},
  "geometry": {"coordinates":[-80.71458435060001,43.136932373],"type":"Point"}
}