{
  "type": "Feature",
  "properties": {
    "addr:full":"Orangeville ON L9W 1K1",
    "addr:postcode":"l9w 1k1",
    "iso:country":"CA",
    "sg:city":"Orangeville",
    "sg:classifiers":[
        {
            "category":"Banks & Credit Unions",
            "subcategory":"Investment Brokerage",
            "type":"Services"
        }
    ],
    "sg:phone":"+1 519 938 9295",
    "sg:postcode":"L9W 1K1",
    "sg:province":"ON",
    "wof:name":"Edward Jones",
    "wof:placetype":"venue"
},
  "geometry": {"coordinates":[-80.09345999999999,43.920261],"type":"Point"}
}