{
  "type": "Feature",
  "properties": {
    "addr:full":"LA Guadeloupe QC G0M 1G0",
    "addr:postcode":"g0m 1g0",
    "iso:country":"CA",
    "sg:city":"LA Guadeloupe",
    "sg:classifiers":[
        {
            "category":"Organizations",
            "subcategory":"Religious Organization",
            "type":"Services"
        }
    ],
    "sg:phone":"+1 418 459 3485",
    "sg:postcode":"G0M 1G0",
    "sg:province":"QC",
    "sg:tags":[
        "church"
    ],
    "wof:name":"Presbytere LA Guadeloupe",
    "wof:placetype":"venue"
},
  "geometry": {"coordinates":[-70.939414978,45.9620475769],"type":"Point"}
}