{
  "type": "Feature",
  "properties": {
    "addr:full":"71 Claudette Gate Hamilton ON L9B 2S3",
    "addr:housenumber":"71",
    "addr:postcode":"l9b 2s3",
    "addr:street":"Claudette Gate",
    "iso:country":"CA",
    "sg:address":"71 Claudette Gate",
    "sg:city":"Hamilton",
    "sg:classifiers":[
        {
            "category":"Health Services",
            "subcategory":"Health Practitioner",
            "type":"Services"
        }
    ],
    "sg:phone":"+1 905 389 0869",
    "sg:postcode":"L9B 2S3",
    "sg:province":"ON",
    "sg:tags":[
        "physiotherapist"
    ],
    "wof:name":"Maureen Sawyer Physiotherapy",
    "wof:placetype":"venue"
},
  "geometry": {"coordinates":[-79.9127044678,43.2118453979],"type":"Point"}
}