{
  "type": "Feature",
  "properties": {
    "iso:country":"CA",
    "sg:address":"1 Cove Rd",
    "sg:city":"London",
    "sg:classifiers":[
        {
            "category":"Recreation",
            "type":"Entertainment"
        }
    ],
    "sg:phone":"+1 519 472 9105",
    "sg:postcode":"N6J 1H7",
    "sg:province":"ON",
    "sg:tags":[
        "tennis",
        "instruction"
    ],
    "wof:name":"Hjr Tennis School",
    "wof:placetype":"venue"
},
  "geometry": {"coordinates":[-81.26359558110001,42.9724617004],"type":"Point"}
}