{
  "type": "Feature",
  "properties": {
    "addr:full":"837 Granville St Vancouver BC V6Z 1K7",
    "addr:housenumber":"837",
    "addr:postcode":"v6z 1k7",
    "addr:street":"Granville St",
    "iso:country":"CA",
    "sg:address":"837 Granville St",
    "sg:city":"Vancouver",
    "sg:classifiers":[
        {
            "category":"Shopping",
            "subcategory":"Shoes",
            "type":"Retail Goods"
        }
    ],
    "sg:phone":"+1 604 688 2828",
    "sg:postcode":"V6Z 1K7",
    "sg:province":"BC",
    "wof:name":"John Fluevog Boots & Shoes Ltd",
    "wof:placetype":"venue"
},
  "geometry": {"coordinates":[-123.120605469,49.2810401917],"type":"Point"}
}