{
  "type": "Feature",
  "properties": {
    "addr:full":"North York ON M3J 2Z1",
    "addr:postcode":"m3j 2z1",
    "iso:country":"CA",
    "sg:city":"North York",
    "sg:classifiers":[
        {
            "category":"Building & Trades",
            "subcategory":"Plumbing",
            "type":"Services"
        }
    ],
    "sg:phone":"+1 416 636 3499",
    "sg:postcode":"M3J 2Z1",
    "sg:province":"ON",
    "sg:tags":[
        "contractor"
    ],
    "wof:name":"Royal Plumbing & Heating",
    "wof:placetype":"venue"
},
  "geometry": {"coordinates":[-79.48421478269999,43.760974884],"type":"Point"}
}