{
  "type": "Feature",
  "properties": {
    "addr:full":"18 Main St S St George Brant ON N0E 1N0",
    "addr:housenumber":"18",
    "addr:postcode":"n0e 1n0",
    "addr:street":"Main St S St",
    "iso:country":"CA",
    "sg:address":"18 Main St S",
    "sg:city":"St George Brant",
    "sg:classifiers":[
        {
            "category":"Shopping",
            "subcategory":"Gifts & Souvenirs",
            "type":"Retail Goods"
        }
    ],
    "sg:phone":"+1 519 448 3285",
    "sg:postcode":"N0E 1N0",
    "sg:province":"ON",
    "sg:tags":[
        "shop"
    ],
    "wof:name":"Tiffany Garden",
    "wof:placetype":"venue"
},
  "geometry": {"coordinates":[-80.2531661987,43.2445030212],"type":"Point"}
}