{
  "type": "Feature",
  "properties": {
    "addr:full":"57 Ch Val Ombreuse Notre-Dame-Du-Laus QC J0X 2M0",
    "addr:housenumber":"57",
    "addr:postcode":"j0x 2m0",
    "addr:street":"Ch Val Ombreuse",
    "iso:country":"CA",
    "sg:address":"57 Ch Val Ombreuse",
    "sg:city":"Notre-Dame-Du-Laus",
    "sg:classifiers":[
        {
            "category":"Autos & Motor Vehicles",
            "subcategory":"Motorcycle Sales",
            "type":"Retail Goods"
        }
    ],
    "sg:phone":"+1 819 767 2107",
    "sg:postcode":"J0X 2M0",
    "sg:province":"QC",
    "sg:tags":[
        "all",
        "terrain"
    ],
    "wof:name":"Atelier DE Petits Moteurs",
    "wof:placetype":"venue"
},
  "geometry": {"coordinates":[-75.624886,46.081913],"type":"Point"}
}