{
  "type": "Feature",
  "properties": {
    "addr:full":"140 Champlain St # 103 Dieppe NB E1A 1N8",
    "addr:housenumber":"140",
    "addr:postcode":"e1a 1n8",
    "addr:street":"Champlain St # 103",
    "iso:country":"CA",
    "sg:address":"140 Champlain St # 103",
    "sg:city":"Dieppe",
    "sg:classifiers":[
        {
            "category":"Health Services",
            "subcategory":"Doctor",
            "type":"Services"
        }
    ],
    "sg:phone":"+1 506 862 0110",
    "sg:postcode":"E1A 1N8",
    "sg:province":"NB",
    "sg:tags":[
        "physician",
        "surgeon"
    ],
    "wof:name":"Cardiology Clinique Dumont",
    "wof:placetype":"venue"
},
  "geometry": {"coordinates":[-64.751884,46.0947],"type":"Point"}
}