{
  "type": "Feature",
  "properties": {
    "addr:full":"51 Clearwater Rd Winnipeg MB R2J 2T4",
    "addr:housenumber":"51",
    "addr:postcode":"r2j 2t4",
    "addr:street":"Clearwater Rd",
    "iso:country":"CA",
    "sg:address":"51 Clearwater Rd",
    "sg:city":"Winnipeg",
    "sg:classifiers":[
        {
            "category":"Professional",
            "subcategory":"Accounting & Tax Preparation",
            "type":"Services"
        }
    ],
    "sg:phone":"+1 204 257 3308",
    "sg:postcode":"R2J 2T4",
    "sg:province":"MB",
    "sg:tags":[
        "accountant"
    ],
    "wof:name":"Mc Intyre, A R",
    "wof:placetype":"venue"
},
  "geometry": {"coordinates":[-97.074546814,49.8515815735],"type":"Point"}
}