{
  "type": "Feature",
  "properties": {
    "addr:full":"Landmark MB R0A 0X0",
    "addr:postcode":"r0a 0x0",
    "iso:country":"CA",
    "sg:city":"Landmark",
    "sg:classifiers":[
        {
            "category":"Organizations",
            "subcategory":"Religious Organization",
            "type":"Services"
        }
    ],
    "sg:phone":"+1 204 355 4511",
    "sg:postcode":"R0A 0X0",
    "sg:province":"MB",
    "sg:tags":[
        "church"
    ],
    "wof:name":"Prairie Rose Evangelical Chr",
    "wof:placetype":"venue"
},
  "geometry": {"coordinates":[-96.81996917719999,49.6641654968],"type":"Point"}
}