{
  "type": "Feature",
  "properties": {
    "addr:full":"Port Coquitlam BC V3B 6P2",
    "addr:postcode":"v3b 6p2",
    "iso:country":"CA",
    "sg:city":"Port Coquitlam",
    "sg:classifiers":[
        {
            "category":"Personal",
            "type":"Services"
        }
    ],
    "sg:phone":"+1 604 942 1684",
    "sg:postcode":"V3B 6P2",
    "sg:province":"BC",
    "sg:tags":[
        "wear",
        "formal"
    ],
    "wof:name":"Black & Lee Formal Wear Rntls",
    "wof:placetype":"venue"
},
  "geometry": {"coordinates":[-122.78939800000001,49.272785],"type":"Point"}
}