{
  "type": "Feature",
  "properties": {
    "addr:full":"Toronto ON M4K 1N8",
    "addr:postcode":"m4k 1n8",
    "iso:country":"CA",
    "sg:city":"Toronto",
    "sg:classifiers":[
        {
            "category":"Social Services",
            "type":"Services"
        }
    ],
    "sg:phone":"+1 416 698 8198",
    "sg:postcode":"M4K 1N8",
    "sg:province":"ON",
    "sg:tags":[
        "counselor",
        "marriage",
        "family"
    ],
    "wof:name":"Fraser, Allen",
    "wof:placetype":"venue"
},
  "geometry": {"coordinates":[-79.353195,43.677319],"type":"Point"}
}