{
  "type": "Feature",
  "properties": {
    "addr:full":"1576 Dupont St Toronto ON M6P 3S6",
    "addr:housenumber":"1576",
    "addr:postcode":"m6p 3s6",
    "addr:street":"Dupont St",
    "iso:country":"CA",
    "sg:address":"1576 Dupont St",
    "sg:city":"Toronto",
    "sg:classifiers":[
        {
            "category":"Personal",
            "subcategory":"Beauty Salon",
            "type":"Services"
        }
    ],
    "sg:phone":"+1 416 763 6342",
    "sg:postcode":"M6P 3S6",
    "sg:province":"ON",
    "wof:name":"Casa Blanca Hairstyling",
    "wof:placetype":"venue"
},
  "geometry": {"coordinates":[-79.45365099999999,43.665382],"type":"Point"}
}