{
  "type": "Feature",
  "properties": {
    "iso:country":"CA",
    "sg:address":"209 Carl Ave E",
    "sg:city":"Langenburg",
    "sg:classifiers":[
        {
            "category":"Organizations",
            "subcategory":"Religious Organization",
            "type":"Services"
        }
    ],
    "sg:phone":"+1 306 743 5454",
    "sg:postcode":"S0A 2A0",
    "sg:province":"SK",
    "sg:tags":[
        "church"
    ],
    "wof:name":"St Paul's Lutheran Church",
    "wof:placetype":"venue"
},
  "geometry": {"coordinates":[-101.70337677000001,50.8420333862],"type":"Point"}
}