{
  "type": "Feature",
  "properties": {
    "addr:full":"170 Rue Benjamin-Hudon Saint-Laurent QC H4N 1H8",
    "addr:housenumber":"170",
    "addr:postcode":"h4n 1h8",
    "addr:street":"Rue Benjamin-Hudon",
    "iso:country":"CA",
    "sg:address":"170 Rue Benjamin-Hudon",
    "sg:city":"Saint-Laurent",
    "sg:classifiers":[
        {
            "category":"Wholesale",
            "subcategory":"Groceries",
            "type":"Manufacturing & Wholesale Goods"
        }
    ],
    "sg:phone":"+1 514 272 2512",
    "sg:postcode":"H4N 1H8",
    "sg:province":"QC",
    "sg:tags":[
        "food",
        "broker"
    ],
    "wof:name":"Agrocan Inc",
    "wof:placetype":"venue"
},
  "geometry": {"coordinates":[-73.65678405760001,45.5281143188],"type":"Point"}
}