{
  "type": "Feature",
  "properties": {
    "iso:country":"CA",
    "sg:address":"13751 112 Ave",
    "sg:city":"Surrey",
    "sg:classifiers":[
        {
            "category":"Education",
            "subcategory":"School",
            "type":"Public Place"
        }
    ],
    "sg:phone":"+1 604 588 3021",
    "sg:postcode":"V3R 2G4",
    "sg:province":"BC",
    "wof:name":"James Ardiel Elementary School",
    "wof:placetype":"venue"
},
  "geometry": {"coordinates":[-122.84142303500001,49.2062606812],"type":"Point"}
}