{
  "type": "Feature",
  "properties": {
    "addr:full":"92 Grey St Brantford ON N3T 2T5",
    "addr:housenumber":"92",
    "addr:postcode":"n3t 2t5",
    "addr:street":"Grey St",
    "iso:country":"CA",
    "sg:address":"92 Grey St",
    "sg:city":"Brantford",
    "sg:classifiers":[
        {
            "category":"Autos & Motor Vehicles",
            "subcategory":"Auto Supplies",
            "type":"Retail Goods"
        }
    ],
    "sg:phone":"+1 519 756 7914",
    "sg:postcode":"N3T 2T5",
    "sg:province":"ON",
    "sg:tags":[
        "equipment",
        "racing",
        "car",
        "automobile"
    ],
    "wof:name":"Brant Performance Equipment",
    "wof:placetype":"venue"
},
  "geometry": {"coordinates":[-80.25843811039999,43.146270752],"type":"Point"}
}