{
  "type": "Feature",
  "properties": {
    "addr:full":"33 Roydon Pl Nepean ON K2E 1A3",
    "addr:housenumber":"33",
    "addr:postcode":"k2e 1a3",
    "addr:street":"Roydon Pl",
    "iso:country":"CA",
    "sg:address":"33 Roydon Pl",
    "sg:city":"Nepean",
    "sg:classifiers":[
        {
            "category":"Communications",
            "subcategory":"Film & Video Production",
            "type":"Services"
        }
    ],
    "sg:phone":"+1 613 727 0202",
    "sg:postcode":"K2E 1A3",
    "sg:province":"ON",
    "sg:tags":[
        "taping"
    ],
    "wof:name":"Hyperactive Productions",
    "wof:placetype":"venue"
},
  "geometry": {"coordinates":[-75.72313699999999,45.338905],"type":"Point"}
}