{
  "type": "Feature",
  "properties": {
    "addr:full":"606 Rue Saint-Laurent Magog QC J1X 4Y8",
    "addr:housenumber":"606",
    "addr:postcode":"j1x 4y8",
    "addr:street":"Rue Saint-Laurent",
    "iso:country":"CA",
    "sg:address":"606 Rue Saint-Laurent",
    "sg:city":"Magog",
    "sg:classifiers":[
        {
            "category":"Health Services",
            "subcategory":"Medical Lab",
            "type":"Services"
        }
    ],
    "sg:phone":"+1 819 843 1020",
    "sg:postcode":"J1X 4Y8",
    "sg:province":"QC",
    "sg:tags":[
        "laboratory"
    ],
    "wof:name":"Laboratoire Ivo-Dent",
    "wof:placetype":"venue"
},
  "geometry": {"coordinates":[-72.15222900000001,45.27634],"type":"Point"}
}