{
  "type": "Feature",
  "properties": {
    "iso:country":"CA",
    "sg:address":"102 William St S",
    "sg:city":"Lindsay",
    "sg:classifiers":[
        {
            "category":"Restaurant",
            "type":"Food & Drink"
        }
    ],
    "sg:phone":"+1 705 878 3853",
    "sg:postcode":"K9V 3B1",
    "sg:province":"ON",
    "wof:name":"Durham Cafe",
    "wof:placetype":"venue"
},
  "geometry": {"coordinates":[-78.73504638670001,44.3510475159],"type":"Point"}
}