{
  "type": "Feature",
  "properties": {
    "addr:full":"51 Pirates Lane Nanaimo BC V9R 6R1",
    "addr:housenumber":"51",
    "addr:postcode":"v9r 6r1",
    "addr:street":"Pirates Lane",
    "iso:country":"CA",
    "sg:address":"51 Pirates Lane",
    "sg:city":"Nanaimo",
    "sg:classifiers":[
        {
            "category":"Shopping",
            "subcategory":"Computers & Home Electronics",
            "type":"Retail Goods"
        }
    ],
    "sg:phone":"+1 250 716 0655",
    "sg:postcode":"V9R 6R1",
    "sg:province":"BC",
    "sg:tags":[
        "software"
    ],
    "wof:name":"Andornot Consulting Inc",
    "wof:placetype":"venue"
},
  "geometry": {"coordinates":[-123.92162322999999,49.1816635132],"type":"Point"}
}