{
  "type": "Feature",
  "properties": {
    "addr:full":"616 Pitt St Cornwall ON K6J 3R7",
    "addr:housenumber":"616",
    "addr:postcode":"k6j 3r7",
    "addr:street":"Pitt St",
    "iso:country":"CA",
    "sg:address":"616 Pitt St",
    "sg:city":"Cornwall",
    "sg:classifiers":[
        {
            "category":"Restaurant",
            "type":"Food & Drink"
        }
    ],
    "sg:phone":"+1 613 936 9898",
    "sg:postcode":"K6J 3R7",
    "sg:province":"ON",
    "sg:tags":[
        "pub"
    ],
    "wof:name":"Lola's Pub & Grub",
    "wof:placetype":"venue"
},
  "geometry": {"coordinates":[-74.732468,45.024506],"type":"Point"}
}