{
  "type": "Feature",
  "properties": {
    "iso:country":"CA",
    "sg:city":"Hamilton",
    "sg:classifiers":[
        {
            "category":"Retail",
            "subcategory":"Auto Repair",
            "type":"Services"
        }
    ],
    "sg:phone":"+1 905 560 1124",
    "sg:postcode":"L8E 2W8",
    "sg:province":"ON",
    "sg:tags":[
        "scooter",
        "wrecker",
        "motorcycle",
        "motor"
    ],
    "wof:name":"Ultimate Cycle",
    "wof:placetype":"venue"
},
  "geometry": {"coordinates":[-79.76908874510001,43.2389831543],"type":"Point"}
}