{
  "type": "Feature",
  "properties": {
    "addr:full":"Waterloo ON N2K 3N2",
    "addr:postcode":"n2k 3n2",
    "iso:country":"CA",
    "sg:city":"Waterloo",
    "sg:classifiers":[
        {
            "category":"Banks & Credit Unions",
            "subcategory":"Investment Brokerage",
            "type":"Services"
        }
    ],
    "sg:phone":"+1 519 746 5092",
    "sg:postcode":"N2K 3N2",
    "sg:province":"ON",
    "wof:name":"Edward Jones",
    "wof:placetype":"venue"
},
  "geometry": {"coordinates":[-80.494736,43.489178],"type":"Point"}
}