{
  "type": "Feature",
  "properties": {
    "iso:country":"CA",
    "sg:address":"3 Regina St N",
    "sg:city":"Waterloo",
    "sg:classifiers":[
        {
            "category":"Shopping",
            "subcategory":"Musical Instruments",
            "type":"Retail Goods"
        }
    ],
    "sg:phone":"+1 519 886 4990",
    "sg:postcode":"N2J 2Z7",
    "sg:province":"ON",
    "sg:tags":[
        "music",
        "dealer"
    ],
    "wof:name":"Waterloo Music Ltd",
    "wof:placetype":"venue"
},
  "geometry": {"coordinates":[-80.521523,43.465492],"type":"Point"}
}