{
  "type": "Feature",
  "properties": {
    "addr:full":"6150 88 St NW Edmonton AB T6E 5H7",
    "addr:housenumber":"6150",
    "addr:postcode":"t6e 5h7",
    "addr:street":"88 St Nw",
    "iso:country":"CA",
    "sg:address":"6150 88 St NW",
    "sg:city":"Edmonton",
    "sg:classifiers":[
        {
            "category":"Home & Garden",
            "subcategory":"Building Materials",
            "type":"Retail Goods"
        }
    ],
    "sg:phone":"+1 780 465 1699",
    "sg:postcode":"T6E 5H7",
    "sg:province":"AB",
    "sg:tags":[
        "door"
    ],
    "wof:name":"Regency Doors",
    "wof:placetype":"venue"
},
  "geometry": {"coordinates":[-113.462646484,53.4977874756],"type":"Point"}
}