{
  "type": "Feature",
  "properties": {
    "addr:full":"9486 210 St Langley BC V1M 2A7",
    "addr:housenumber":"9486",
    "addr:postcode":"v1m 2a7",
    "addr:street":"210 St",
    "iso:country":"CA",
    "sg:address":"9486 210 St",
    "sg:city":"Langley",
    "sg:classifiers":[
        {
            "category":"Utilities",
            "subcategory":"Refuse",
            "type":"Services"
        }
    ],
    "sg:phone":"+1 604 835 4441",
    "sg:postcode":"V1M 2A7",
    "sg:province":"BC",
    "sg:tags":[
        "garbage",
        "collection"
    ],
    "wof:name":"Casey's Disposal",
    "wof:placetype":"venue"
},
  "geometry": {"coordinates":[-122.638763428,49.1751403809],"type":"Point"}
}