{
  "type": "Feature",
  "properties": {
    "addr:full":"919 Broadway Ave Saskatoon SK S7N 1B8",
    "addr:housenumber":"919",
    "addr:postcode":"s7n 1b8",
    "addr:street":"Broadway Ave",
    "iso:country":"CA",
    "sg:address":"919 Broadway Ave",
    "sg:city":"Saskatoon",
    "sg:classifiers":[
        {
            "category":"Education",
            "subcategory":"School",
            "type":"Public Place"
        }
    ],
    "sg:phone":"+1 306 668 7490",
    "sg:postcode":"S7N 1B8",
    "sg:province":"SK",
    "wof:name":"Joe Duquette High School",
    "wof:placetype":"venue"
},
  "geometry": {"coordinates":[-106.65645600000001,52.116455],"type":"Point"}
}