{
  "type": "Feature",
  "properties": {
    "addr:full":"Amherst NS B4H 1X9",
    "addr:postcode":"b4h 1x9",
    "iso:country":"CA",
    "sg:city":"Amherst",
    "sg:classifiers":[
        {
            "category":"Education",
            "subcategory":"Special Training",
            "type":"Public Place"
        }
    ],
    "sg:phone":"+1 902 661 0153",
    "sg:postcode":"B4H 1X9",
    "sg:province":"NS",
    "sg:tags":[
        "instruction",
        "tutoring",
        "reading",
        "improvement"
    ],
    "wof:name":"Cumberland Adult Network",
    "wof:placetype":"venue"
},
  "geometry": {"coordinates":[-64.2111282349,45.835773468],"type":"Point"}
}