{
  "type": "Feature",
  "properties": {
    "iso:country":"CA",
    "sg:address":"1191 Rue DE LA Montagne",
    "sg:city":"Montreal",
    "sg:classifiers":[
        {
            "category":"Education",
            "subcategory":"College",
            "type":"Public Place"
        }
    ],
    "sg:phone":"+1 514 866 4622",
    "sg:postcode":"H3G 1Z2",
    "sg:province":"QC",
    "sg:tags":[
        "academic",
        "school"
    ],
    "wof:name":"O'Sullivan College",
    "wof:placetype":"venue"
},
  "geometry": {"coordinates":[-73.5734863281,45.4973373413],"type":"Point"}
}