{
  "type": "Feature",
  "properties": {
    "iso:country":"CA",
    "sg:address":"289 2E Rue E",
    "sg:city":"LA Sarre",
    "sg:classifiers":[
        {
            "category":"Home & Garden",
            "subcategory":"Building Materials",
            "type":"Retail Goods"
        }
    ],
    "sg:phone":"+1 819 333 5377",
    "sg:postcode":"J9Z 2H1",
    "sg:province":"QC",
    "sg:tags":[
        "glass",
        "window",
        "plate"
    ],
    "wof:name":"Vitrerie Pomerleau",
    "wof:placetype":"venue"
},
  "geometry": {"coordinates":[-79.2004852295,48.8155822754],"type":"Point"}
}