{
  "type": "Feature",
  "properties": {
    "addr:full":"500 Boul DE L'Hopital #200 Gatineau QC J8V 2P5",
    "addr:housenumber":"500",
    "addr:postcode":"j8v 2p5",
    "addr:street":"Boul De L'Hopital # 200",
    "iso:country":"CA",
    "sg:address":"500 Boul DE L'Hopital #200",
    "sg:city":"Gatineau",
    "sg:classifiers":[
        {
            "category":"Health Services",
            "subcategory":"Doctor",
            "type":"Services"
        }
    ],
    "sg:phone":"+1 819 561 8739",
    "sg:postcode":"J8V 2P5",
    "sg:province":"QC",
    "sg:tags":[
        "physician",
        "surgeon"
    ],
    "wof:name":"Thompson, Tracey MD",
    "wof:placetype":"venue"
},
  "geometry": {"coordinates":[-75.710503,45.427849],"type":"Point"}
}