{
  "type": "Feature",
  "properties": {
    "addr:full":"74 Frontenac Ave Mount Pearl NL A1N 4Z4",
    "addr:housenumber":"74",
    "addr:postcode":"a1n 4z4",
    "addr:street":"Frontenac Ave",
    "iso:country":"CA",
    "sg:address":"74 Frontenac Ave",
    "sg:city":"Mount Pearl",
    "sg:classifiers":[
        {
            "category":"Building & Trades",
            "subcategory":"Construction",
            "type":"Services"
        }
    ],
    "sg:phone":"+1 709 364 2380",
    "sg:postcode":"A1N 4Z4",
    "sg:province":"NL",
    "sg:tags":[
        "painter"
    ],
    "wof:name":"Doug Butler Painting Contrs",
    "wof:placetype":"venue"
},
  "geometry": {"coordinates":[-52.811977,47.530872],"type":"Point"}
}