{
  "type": "Feature",
  "properties": {
    "addr:full":"PO Box 1145 Lac LA Biche AB T0A 2C0",
    "addr:housenumber":"po",
    "addr:postcode":"t0a 2c0",
    "addr:street":"Box 1145 Lac La Biche",
    "iso:country":"CA",
    "sg:address":"PO Box 1145",
    "sg:city":"Lac LA Biche",
    "sg:classifiers":[
        {
            "category":"Building & Trades",
            "subcategory":"Plumbing",
            "type":"Services"
        }
    ],
    "sg:phone":"+1 780 623 2810",
    "sg:postcode":"T0A 2C0",
    "sg:province":"AB",
    "sg:tags":[
        "contractor"
    ],
    "wof:name":"Peco Plumbing & Gasfitting Ltd",
    "wof:placetype":"venue"
},
  "geometry": {"coordinates":[-111.97445678699999,54.77110672],"type":"Point"}
}