{
  "type": "Feature",
  "properties": {
    "addr:full":"Sherbrooke QC J1L 2B4",
    "addr:postcode":"j1l 2b4",
    "iso:country":"CA",
    "sg:city":"Sherbrooke",
    "sg:classifiers":[
        {
            "category":"Personal",
            "subcategory":"Beauty Salon",
            "type":"Services"
        }
    ],
    "sg:phone":"+1 819 820 4182",
    "sg:postcode":"J1L 2B4",
    "sg:province":"QC",
    "wof:name":"Marie-Claire Spa Esthetique",
    "wof:placetype":"venue"
},
  "geometry": {"coordinates":[-71.94403839109999,45.4115753174],"type":"Point"}
}