{
  "type": "Feature",
  "properties": {
    "addr:full":"145 Rue Canada Saint-Quentin NB E8A 1J4",
    "addr:housenumber":"145",
    "addr:postcode":"e8a 1j4",
    "addr:street":"Rue",
    "iso:country":"CA",
    "sg:address":"145 Rue Canada",
    "sg:city":"Saint-Quentin",
    "sg:classifiers":[
        {
            "category":"Food & Beverages",
            "subcategory":"Liquor & Beverages",
            "type":"Retail Goods"
        }
    ],
    "sg:phone":"+1 506 235 2083",
    "sg:postcode":"E8A 1J4",
    "sg:province":"NB",
    "sg:tags":[
        "store"
    ],
    "wof:name":"CO-Operative DE St-Quentin",
    "wof:placetype":"venue"
},
  "geometry": {"coordinates":[-67.3924407959,47.5073127747],"type":"Point"}
}