{
  "type": "Feature",
  "properties": {
    "addr:full":"41 Dovercourt Rd Toronto ON M6J 3C2",
    "addr:housenumber":"41",
    "addr:postcode":"m6j 3c2",
    "addr:street":"Dovercourt Rd",
    "iso:country":"CA",
    "sg:address":"41 Dovercourt Rd",
    "sg:city":"Toronto",
    "sg:classifiers":[
        {
            "category":"Wholesale",
            "subcategory":"Groceries",
            "type":"Manufacturing & Wholesale Goods"
        }
    ],
    "sg:phone":"+1 416 536 1330",
    "sg:postcode":"M6J 3C2",
    "sg:province":"ON",
    "sg:tags":[
        "baker"
    ],
    "wof:name":"Dufflet Pastries",
    "wof:placetype":"venue"
},
  "geometry": {"coordinates":[-79.421745,43.642323],"type":"Point"}
}