{
  "type": "Feature",
  "properties": {
    "addr:full":"18 Kensington Rd # 407 Brampton ON L6T 4S5",
    "addr:housenumber":"18",
    "addr:postcode":"l6t 4s5",
    "addr:street":"Kensington Rd # 407",
    "iso:country":"CA",
    "sg:address":"18 Kensington Rd # 407",
    "sg:city":"Brampton",
    "sg:classifiers":[
        {
            "category":"Health Services",
            "subcategory":"Doctor",
            "type":"Services"
        }
    ],
    "sg:phone":"+1 905 791 1620",
    "sg:postcode":"L6T 4S5",
    "sg:province":"ON",
    "sg:tags":[
        "dentist"
    ],
    "wof:name":"Bramalea Oral Surgery Inc",
    "wof:placetype":"venue"
},
  "geometry": {"coordinates":[-79.7182769775,43.7218399048],"type":"Point"}
}