{
  "type": "Feature",
  "properties": {
    "iso:country":"CA",
    "sg:address":"4246 Bathurst St",
    "sg:city":"North York",
    "sg:classifiers":[
        {
            "category":"Health Services",
            "subcategory":"Doctor",
            "type":"Services"
        }
    ],
    "sg:phone":"+1 416 635 2886",
    "sg:postcode":"M3H 3R3",
    "sg:province":"ON",
    "sg:tags":[
        "physician",
        "surgeon"
    ],
    "wof:name":"Kazdan, Jerome J MD",
    "wof:placetype":"venue"
},
  "geometry": {"coordinates":[-79.437461853,43.7505493164],"type":"Point"}
}