{
  "type": "Feature",
  "properties": {
    "addr:full":"55 East Main St Welland ON L3B 3W4",
    "addr:housenumber":"55",
    "addr:postcode":"l3b 3w4",
    "addr:street":"East Main St",
    "iso:country":"CA",
    "sg:address":"55 East Main St",
    "sg:city":"Welland",
    "sg:classifiers":[
        {
            "category":"Insurance",
            "subcategory":"Insurance Agent",
            "type":"Services"
        }
    ],
    "sg:phone":"+1 905 735 7212",
    "sg:postcode":"L3B 3W4",
    "sg:province":"ON",
    "wof:name":"Youngs Insurance",
    "wof:placetype":"venue"
},
  "geometry": {"coordinates":[-79.24923706049999,42.9917831421],"type":"Point"}
}