{
  "type": "Feature",
  "properties": {
    "addr:full":"610 Rue Notre-Dame Saint-Casimir QC G0A 3L0",
    "addr:housenumber":"610",
    "addr:postcode":"g0a 3l0",
    "addr:street":"Rue Notre-Dame",
    "iso:country":"CA",
    "sg:address":"610 Rue Notre-Dame",
    "sg:city":"Saint-Casimir",
    "sg:classifiers":[
        {
            "category":"Restaurant",
            "type":"Food & Drink"
        }
    ],
    "sg:phone":"+1 418 339 3410",
    "sg:postcode":"G0A 3L0",
    "sg:province":"QC",
    "wof:name":"Marmite DE L'Ouest",
    "wof:placetype":"venue"
},
  "geometry": {"coordinates":[-72.110046,46.666954],"type":"Point"}
}