{
  "type": "Feature",
  "properties": {
    "addr:full":"114 Roseberry St Campbellton NB E3N 2G8",
    "addr:housenumber":"114",
    "addr:postcode":"e3n 2g8",
    "addr:street":"Roseberry St",
    "iso:country":"CA",
    "sg:address":"114 Roseberry St",
    "sg:city":"Campbellton",
    "sg:classifiers":[
        {
            "category":"Health Services",
            "subcategory":"Doctor",
            "type":"Services"
        }
    ],
    "sg:phone":"+1 506 753 6433",
    "sg:postcode":"E3N 2G8",
    "sg:province":"NB",
    "sg:tags":[
        "physician",
        "surgeon"
    ],
    "wof:name":"Fuzesi, Gabor MD",
    "wof:placetype":"venue"
},
  "geometry": {"coordinates":[-66.680008,48.003918],"type":"Point"}
}