{
  "type": "Feature",
  "properties": {
    "addr:full":"18 Salisbury Cres Bloomingdale ON N0B 1K0",
    "addr:housenumber":"18",
    "addr:postcode":"n0b 1k0",
    "addr:street":"Salisbury Cres",
    "iso:country":"CA",
    "sg:address":"18 Salisbury Cres",
    "sg:city":"Bloomingdale",
    "sg:classifiers":[
        {
            "category":"Building & Trades",
            "subcategory":"Construction",
            "type":"Services"
        }
    ],
    "sg:phone":"+1 519 578 1933",
    "sg:postcode":"N0B 1K0",
    "sg:province":"ON",
    "sg:tags":[
        "excavating",
        "contractor"
    ],
    "wof:name":"Double A Excavating",
    "wof:placetype":"venue"
},
  "geometry": {"coordinates":[-80.459953,43.509869],"type":"Point"}
}