{
  "type": "Feature",
  "properties": {
    "addr:full":"221 Fourth Ave Strathmore AB T1P 1B9",
    "addr:housenumber":"221",
    "addr:postcode":"t1p 1b9",
    "addr:street":"Fourth Ave",
    "iso:country":"CA",
    "sg:address":"221 Fourth Ave",
    "sg:city":"Strathmore",
    "sg:classifiers":[
        {
            "category":"Food & Beverages",
            "subcategory":"Groceries & Convenience Stores",
            "type":"Retail Goods"
        }
    ],
    "sg:phone":"+1 403 934 4512",
    "sg:postcode":"T1P 1B9",
    "sg:province":"AB",
    "sg:tags":[
        "grocer"
    ],
    "wof:name":"Strathmore Garden Market Iga",
    "wof:placetype":"venue"
},
  "geometry": {"coordinates":[-113.395126343,51.0412406921],"type":"Point"}
}