{
  "type": "Feature",
  "properties": {
    "addr:full":"1080 Skeena Dr Port Edward BC V0V 1G0",
    "addr:housenumber":"1080",
    "addr:postcode":"v0v 1g0",
    "addr:street":"Skeena Dr",
    "iso:country":"CA",
    "sg:address":"1080 Skeena Dr",
    "sg:city":"Port Edward",
    "sg:classifiers":[
        {
            "category":"Manufacturing",
            "subcategory":"Food",
            "type":"Manufacturing & Wholesale Goods"
        }
    ],
    "sg:phone":"+1 250 628 3227",
    "sg:postcode":"V0V 1G0",
    "sg:province":"BC",
    "sg:tags":[
        "packer",
        "seafood",
        "fish"
    ],
    "wof:name":"Aero Trading CO",
    "wof:placetype":"venue"
},
  "geometry": {"coordinates":[-130.28717,54.214016],"type":"Point"}
}