{
  "type": "Feature",
  "properties": {
    "addr:full":"505 4th Ave N Saskatoon SK S7K 2M5",
    "addr:housenumber":"505",
    "addr:postcode":"s7k 2m5",
    "addr:street":"4Th Ave N",
    "iso:country":"CA",
    "sg:address":"505 4th Ave N",
    "sg:city":"Saskatoon",
    "sg:classifiers":[
        {
            "category":"Health Services",
            "subcategory":"Health Practitioner",
            "type":"Services"
        }
    ],
    "sg:phone":"+1 306 374 2557",
    "sg:postcode":"S7K 2M5",
    "sg:province":"SK",
    "sg:tags":[
        "psychologist"
    ],
    "wof:name":"Nicholaichuk, Terry PhD",
    "wof:placetype":"venue"
},
  "geometry": {"coordinates":[-106.65774500000001,52.135056],"type":"Point"}
}