{
  "type": "Feature",
  "properties": {
    "addr:full":"4250 Rue Sere Saint-Laurent QC H4T 1A6",
    "addr:housenumber":"4250",
    "addr:postcode":"h4t 1a6",
    "addr:street":"Rue Sere",
    "iso:country":"CA",
    "sg:address":"4250 Rue Sere",
    "sg:city":"Saint-Laurent",
    "sg:classifiers":[
        {
            "category":"Wholesale",
            "subcategory":"Durable Goods & Equipment",
            "type":"Manufacturing & Wholesale Goods"
        }
    ],
    "sg:phone":"+1 514 344 0420",
    "sg:postcode":"H4T 1A6",
    "sg:province":"QC",
    "sg:tags":[
        "representative",
        "manufacturer"
    ],
    "wof:name":"Electronic Sales Professional",
    "wof:placetype":"venue"
},
  "geometry": {"coordinates":[-73.70523834230001,45.4863166809],"type":"Point"}
}