{
  "type": "Feature",
  "properties": {
    "addr:full":"1349 Lasalle Blvd #104 Sudbury ON P3A 1Z2",
    "addr:housenumber":"1349",
    "addr:postcode":"p3a 1z2",
    "addr:street":"Lasalle Blvd # 104",
    "iso:country":"CA",
    "sg:address":"1349 Lasalle Blvd #104",
    "sg:city":"Sudbury",
    "sg:classifiers":[
        {
            "category":"Restaurant",
            "type":"Food & Drink"
        }
    ],
    "sg:phone":"+1 705 560 2646",
    "sg:postcode":"P3A 1Z2",
    "sg:province":"ON",
    "sg:tags":[
        "sandwich"
    ],
    "wof:name":"Subway Sandwiches & Salads",
    "wof:placetype":"venue"
},
  "geometry": {"coordinates":[-80.949989,46.52198],"type":"Point"}
}