{
  "type": "Feature",
  "properties": {
    "addr:full":"315 Ash St Porcupine Plain SK S0E 1H0",
    "addr:housenumber":"315",
    "addr:postcode":"s0e 1h0",
    "addr:street":"Ash St;Plain",
    "iso:country":"CA",
    "sg:address":"315 Ash St",
    "sg:city":"Porcupine Plain",
    "sg:classifiers":[
        {
            "category":"Recreation",
            "type":"Entertainment"
        }
    ],
    "sg:phone":"+1 306 278 2282",
    "sg:postcode":"S0E 1H0",
    "sg:province":"SK",
    "sg:tags":[
        "pool",
        "swimming"
    ],
    "wof:name":"Larwood-Shaw Memorial Pool",
    "wof:placetype":"venue"
},
  "geometry": {"coordinates":[-103.254333496,52.5980644226],"type":"Point"}
}