{
  "type": "Feature",
  "properties": {
    "addr:full":"260 Rue Papineau # A Papineauville QC J0V 1R0",
    "addr:housenumber":"260",
    "addr:postcode":"j0v 1r0",
    "addr:street":"Rue Papineau # A",
    "iso:country":"CA",
    "sg:address":"260 Rue Papineau # A",
    "sg:city":"Papineauville",
    "sg:classifiers":[
        {
            "category":"Personal",
            "subcategory":"Beauty Salon",
            "type":"Services"
        }
    ],
    "sg:phone":"+1 819 427 5673",
    "sg:postcode":"J0V 1R0",
    "sg:province":"QC",
    "wof:name":"Salon DE Coiffure Jacques",
    "wof:placetype":"venue"
},
  "geometry": {"coordinates":[-75.0172653198,45.6173934937],"type":"Point"}
}