{
  "type": "Feature",
  "properties": {
    "addr:full":"340 Rue Bellarmin Montreal QC H2P 1G5",
    "addr:housenumber":"340",
    "addr:postcode":"h2p 1g5",
    "addr:street":"Rue Bellarmin",
    "iso:country":"CA",
    "sg:address":"340 Rue Bellarmin",
    "sg:city":"Montreal",
    "sg:classifiers":[
        {
            "category":"Wholesale",
            "subcategory":"Fruits & Vegetables",
            "type":"Manufacturing & Wholesale Goods"
        }
    ],
    "sg:phone":"+1 514 858 7540",
    "sg:postcode":"H2P 1G5",
    "sg:province":"QC",
    "wof:name":"Chenail Fruits & Legumes",
    "wof:placetype":"venue"
},
  "geometry": {"coordinates":[-73.64186100000001,45.53677],"type":"Point"}
}