{
  "type": "Feature",
  "properties": {
    "iso:country":"CA",
    "sg:address":"194 Willow Dr",
    "sg:city":"Wetaskiwin",
    "sg:classifiers":[
        {
            "category":"Building & Trades",
            "subcategory":"Construction",
            "type":"Services"
        }
    ],
    "sg:phone":"+1 780 352 0600",
    "sg:postcode":"T9A 2T2",
    "sg:province":"AB",
    "sg:tags":[
        "masonry",
        "contractor"
    ],
    "wof:name":"Elligott Construction Ltd",
    "wof:placetype":"venue"
},
  "geometry": {"coordinates":[-113.384735107,52.9787025452],"type":"Point"}
}