{
  "type": "Feature",
  "properties": {
    "addr:full":"3772 N Frontage Rd # 1 Spences Bridge BC V0K 2L0",
    "addr:housenumber":"3772",
    "addr:postcode":"bc v0k 2l0",
    "addr:street":"N Frontage Rd # 1 Spences Bridge",
    "iso:country":"CA",
    "sg:address":"3772 N Frontage Rd # 1",
    "sg:city":"Spences Bridge",
    "sg:classifiers":[
        {
            "category":"Restaurant",
            "type":"Food & Drink"
        }
    ],
    "sg:phone":"+1 250 458 2254",
    "sg:postcode":"V0K 2L0",
    "sg:province":"BC",
    "wof:name":"Rumor's Restaurant & Bakery",
    "wof:placetype":"venue"
},
  "geometry": {"coordinates":[-121.342765808,50.4245223999],"type":"Point"}
}