{
  "type": "Feature",
  "properties": {
    "addr:full":"1542 Bloor St W Toronto ON M6P 1A4",
    "addr:housenumber":"1542",
    "addr:postcode":"m6p 1a4",
    "addr:street":"Bloor St W",
    "iso:country":"CA",
    "sg:address":"1542 Bloor St W",
    "sg:city":"Toronto",
    "sg:classifiers":[
        {
            "category":"Shopping",
            "subcategory":"Stationery & Office Supplies",
            "type":"Retail Goods"
        }
    ],
    "sg:phone":"+1 416 531 1544",
    "sg:postcode":"M6P 1A4",
    "sg:province":"ON",
    "sg:tags":[
        "rubber",
        "stamp",
        "printer",
        "plastic"
    ],
    "wof:name":"J B Business Graphics",
    "wof:placetype":"venue"
},
  "geometry": {"coordinates":[-79.452759,43.656467],"type":"Point"}
}