{
  "type": "Feature",
  "properties": {
    "addr:full":"548 Av Pine Saint-Lambert QC J4P 2P3",
    "addr:postcode":"j4p 2p3",
    "addr:street":"548 Av Pine",
    "iso:country":"CA",
    "sg:address":"548 Av Pine",
    "sg:city":"Saint-Lambert",
    "sg:classifiers":[
        {
            "category":"Professional",
            "type":"Services"
        }
    ],
    "sg:phone":"+1 514 875 6202",
    "sg:postcode":"J4P 2P3",
    "sg:province":"QC",
    "sg:tags":[
        "establishment",
        "appraiser"
    ],
    "wof:name":"Denis Chauvette Evaluateur",
    "wof:placetype":"venue"
},
  "geometry": {"coordinates":[-73.507881,45.503727],"type":"Point"}
}