{
  "type": "Feature",
  "properties": {
    "addr:full":"Scarborough ON M1S 5C8",
    "addr:postcode":"m1s 5c8",
    "iso:country":"CA",
    "sg:city":"Scarborough",
    "sg:classifiers":[
        {
            "category":"Health Services",
            "subcategory":"Chiropractor",
            "type":"Services"
        }
    ],
    "sg:phone":"+1 416 291 1235",
    "sg:postcode":"M1S 5C8",
    "sg:province":"ON",
    "wof:name":"Szaraz, David J DC",
    "wof:placetype":"venue"
},
  "geometry": {"coordinates":[-79.285179,43.781013],"type":"Point"}
}