{
  "type": "Feature",
  "properties": {
    "addr:full":"17 Rue Des Jesuites Loretteville QC G2A 2Z2",
    "addr:housenumber":"17",
    "addr:postcode":"g2a 2z2",
    "addr:street":"Rue Des Jesuites",
    "iso:country":"CA",
    "sg:address":"17 Rue Des Jesuites",
    "sg:city":"Loretteville",
    "sg:classifiers":[
        {
            "category":"Real Estate",
            "subcategory":"Surveying",
            "type":"Services"
        }
    ],
    "sg:phone":"+1 418 842 8868",
    "sg:postcode":"G2A 2Z2",
    "sg:province":"QC",
    "sg:tags":[
        "surveyor"
    ],
    "wof:name":"Gagne, Rosaire",
    "wof:placetype":"venue"
},
  "geometry": {"coordinates":[-71.374016,46.851604],"type":"Point"}
}