{
  "type": "Feature",
  "properties": {
    "addr:full":"10350 68 Ave NW Edmonton AB T6H 2A7",
    "addr:housenumber":"10350",
    "addr:postcode":"t6h 2a7",
    "addr:street":"68 Ave Nw",
    "iso:country":"CA",
    "sg:address":"10350 68 Ave NW",
    "sg:city":"Edmonton",
    "sg:classifiers":[
        {
            "category":"Retail",
            "subcategory":"Auto Repair",
            "type":"Services"
        }
    ],
    "sg:phone":"+1 780 436 3905",
    "sg:postcode":"T6H 2A7",
    "sg:province":"AB",
    "sg:tags":[
        "repairing",
        "automobile"
    ],
    "wof:name":"Euro Cana Automotive",
    "wof:placetype":"venue"
},
  "geometry": {"coordinates":[-113.49745900000001,53.504456],"type":"Point"}
}