{
  "type": "Feature",
  "properties": {
    "addr:full":"188 Rue DE LA Mer Baie-Des-Sables QC G0J 1C0",
    "addr:housenumber":"188",
    "addr:postcode":"g0j 1c0",
    "addr:street":"Rue De La Mer",
    "iso:country":"CA",
    "sg:address":"188 Rue DE LA Mer",
    "sg:city":"Baie-Des-Sables",
    "sg:classifiers":[
        {
            "category":"Retail",
            "subcategory":"Auto Repair",
            "type":"Services"
        }
    ],
    "sg:phone":"+1 418 772 6868",
    "sg:postcode":"G0J 1C0",
    "sg:province":"QC",
    "sg:tags":[
        "repairing",
        "automobile"
    ],
    "wof:name":"Garage Shell B Santerre & Fils",
    "wof:placetype":"venue"
},
  "geometry": {"coordinates":[-67.887856,48.726292],"type":"Point"}
}