{
  "type": "Feature",
  "properties": {
    "addr:full":"2724 Station Rd River John NS B0K 1N0",
    "addr:housenumber":"2724",
    "addr:postcode":"b0k 1n0",
    "addr:street":"Station Rd",
    "iso:country":"CA",
    "sg:address":"2724 Station Rd",
    "sg:city":"River John",
    "sg:classifiers":[
        {
            "category":"Organizations",
            "subcategory":"Professional Association",
            "type":"Services"
        }
    ],
    "sg:phone":"+1 902 351 2700",
    "sg:postcode":"B0K 1N0",
    "sg:province":"NS",
    "wof:name":"River John Lions Club",
    "wof:placetype":"venue"
},
  "geometry": {"coordinates":[-63.0590324402,45.7513961792],"type":"Point"}
}