{
  "type": "Feature",
  "properties": {
    "iso:country":"CA",
    "sg:city":"Montreal",
    "sg:classifiers":[
        {
            "category":"Professional",
            "subcategory":"Art Services",
            "type":"Services"
        }
    ],
    "sg:phone":"+1 514 866 7442",
    "sg:postcode":"H3G 1P9",
    "sg:province":"QC",
    "sg:tags":[
        "graphic",
        "designer"
    ],
    "wof:name":"Studio Andree Robillard Inc",
    "wof:placetype":"venue"
},
  "geometry": {"coordinates":[-73.5542297363,45.5203857422],"type":"Point"}
}