{
  "type": "Feature",
  "properties": {
    "addr:full":"4960 Rue Courval Saint-Laurent QC H4T 1L4",
    "addr:housenumber":"4960",
    "addr:postcode":"h4t 1l4",
    "addr:street":"Rue Courval",
    "iso:country":"CA",
    "sg:address":"4960 Rue Courval",
    "sg:city":"Saint-Laurent",
    "sg:classifiers":[
        {
            "category":"Manufacturing",
            "subcategory":"Electronics",
            "type":"Manufacturing & Wholesale Goods"
        }
    ],
    "sg:phone":"+1 514 344 5333",
    "sg:postcode":"H4T 1L4",
    "sg:province":"QC",
    "sg:tags":[
        "printed",
        "circuit",
        "etched"
    ],
    "wof:name":"Circuits Grm Enr",
    "wof:placetype":"venue"
},
  "geometry": {"coordinates":[-73.6949462891,45.4684371948],"type":"Point"}
}