{
  "type": "Feature",
  "properties": {
    "addr:full":"160 Main St Thessalon ON P0R 1L0",
    "addr:housenumber":"160",
    "addr:postcode":"p0r 1l0",
    "addr:street":"Main St",
    "iso:country":"CA",
    "sg:address":"160 Main St",
    "sg:city":"Thessalon",
    "sg:classifiers":[
        {
            "category":"Food & Beverages",
            "subcategory":"Groceries & Convenience Stores",
            "type":"Retail Goods"
        }
    ],
    "sg:phone":"+1 705 842 1050",
    "sg:postcode":"P0R 1L0",
    "sg:province":"ON",
    "sg:tags":[
        "product"
    ],
    "wof:name":"Country Bins Bulk Food",
    "wof:placetype":"venue"
},
  "geometry": {"coordinates":[-83.557281,46.25602],"type":"Point"}
}