{
  "type": "Feature",
  "properties": {
    "addr:full":"95 Mayfield Cres Winnipeg MB R3R 3A9",
    "addr:housenumber":"95",
    "addr:postcode":"r3r 3a9",
    "addr:street":"Mayfield Cres",
    "iso:country":"CA",
    "sg:address":"95 Mayfield Cres",
    "sg:city":"Winnipeg",
    "sg:classifiers":[
        {
            "category":"Organizations",
            "subcategory":"Labor Organization",
            "type":"Services"
        }
    ],
    "sg:phone":"+1 204 888 1323",
    "sg:postcode":"R3R 3A9",
    "sg:province":"MB",
    "wof:name":"Communications Energy & Pprwrk",
    "wof:placetype":"venue"
},
  "geometry": {"coordinates":[-97.257935,49.854805],"type":"Point"}
}