{
  "type": "Feature",
  "properties": {
    "addr:full":"596 Paisley Rd Guelph ON N1H 7J2",
    "addr:housenumber":"596",
    "addr:postcode":"n1h 7j2",
    "addr:street":"Paisley Rd",
    "iso:country":"CA",
    "sg:address":"596 Paisley Rd",
    "sg:city":"Guelph",
    "sg:classifiers":[
        {
            "category":"Building & Trades",
            "subcategory":"Construction",
            "type":"Services"
        }
    ],
    "sg:phone":"+1 519 822 6277",
    "sg:postcode":"N1H 7J2",
    "sg:province":"ON",
    "sg:tags":[
        "general",
        "carpenter",
        "contractor"
    ],
    "wof:name":"C Ostrynik Carpenter & General",
    "wof:placetype":"venue"
},
  "geometry": {"coordinates":[-80.272194,43.533634],"type":"Point"}
}