{
  "type": "Feature",
  "properties": {
    "iso:country":"CA",
    "sg:address":"29 Rue Vaillancourt",
    "sg:city":"Sept-Iles",
    "sg:classifiers":[
        {
            "category":"Health Services",
            "subcategory":"Medical Lab",
            "type":"Services"
        }
    ],
    "sg:phone":"+1 418 962 6966",
    "sg:postcode":"G4R 5A5",
    "sg:province":"QC",
    "wof:name":"Clinique DE Denturologie",
    "wof:placetype":"venue"
},
  "geometry": {"coordinates":[-66.34981536870001,50.2239723206],"type":"Point"}
}