{
  "type": "Feature",
  "properties": {
    "addr:full":"29 Rue Vaillancourt Sept-Iles QC G4R 5A5",
    "addr:housenumber":"29",
    "addr:postcode":"g4r 5a5",
    "addr:street":"Rue Vaillancourt",
    "iso:country":"CA",
    "sg:address":"29 Rue Vaillancourt",
    "sg:city":"Sept-Iles",
    "sg:classifiers":[
        {
            "category":"Health Services",
            "subcategory":"Medical Lab",
            "type":"Services"
        }
    ],
    "sg:phone":"+1 418 962 6966",
    "sg:postcode":"G4R 5A5",
    "sg:province":"QC",
    "wof:name":"Clinique DE Denturologie",
    "wof:placetype":"venue"
},
  "geometry": {"coordinates":[-66.34981536870001,50.2239723206],"type":"Point"}
}