{
  "type": "Feature",
  "properties": {
    "addr:full":"Mississauga ON L5T 2L9",
    "addr:postcode":"l5t 2l9",
    "iso:country":"CA",
    "sg:city":"Mississauga",
    "sg:classifiers":[
        {
            "category":"Professional",
            "subcategory":"Employment Agencies",
            "type":"Services"
        }
    ],
    "sg:phone":"+1 905 670 0835",
    "sg:postcode":"L5T 2L9",
    "sg:province":"ON",
    "sg:tags":[
        "opportunity"
    ],
    "wof:name":"Kee Transport Group Inc",
    "wof:placetype":"venue"
},
  "geometry": {"coordinates":[-79.6695022583,43.6690330505],"type":"Point"}
}