{
  "type": "Feature",
  "properties": {
    "addr:full":"3511 Hastings St E Vancouver BC V5K 2A8",
    "addr:housenumber":"3511",
    "addr:postcode":"v5k 2a8",
    "addr:street":"Hastings St E",
    "iso:country":"CA",
    "sg:address":"3511 Hastings St E",
    "sg:city":"Vancouver",
    "sg:classifiers":[
        {
            "category":"Shopping",
            "type":"Retail Goods"
        }
    ],
    "sg:phone":"+1 604 299 4848",
    "sg:postcode":"V5K 2A8",
    "sg:province":"BC",
    "sg:tags":[
        "equipment",
        "wine",
        "supply"
    ],
    "wof:name":"Bacchus Grape Connection",
    "wof:placetype":"venue"
},
  "geometry": {"coordinates":[-123.027732849,49.2813148499],"type":"Point"}
}