{
  "type": "Feature",
  "properties": {
    "addr:full":"341 Hiawatha Rd Keene ON K0L 2G0",
    "addr:housenumber":"341",
    "addr:postcode":"k0l 2g0",
    "addr:street":"Hiawatha Rd",
    "iso:country":"CA",
    "sg:address":"341 Hiawatha Rd",
    "sg:city":"Keene",
    "sg:classifiers":[
        {
            "category":"Restaurant",
            "type":"Food & Drink"
        }
    ],
    "sg:phone":"+1 705 295 7126",
    "sg:postcode":"K0L 2G0",
    "sg:province":"ON",
    "wof:name":"Old Railroad Stop Store Cntr",
    "wof:placetype":"venue"
},
  "geometry": {"coordinates":[-78.16321600000001,44.240147],"type":"Point"}
}