{
  "type": "Feature",
  "properties": {
    "addr:full":"Mount Hope ON L0R 1W0",
    "addr:postcode":"l0r 1w0",
    "iso:country":"CA",
    "sg:city":"Mount Hope",
    "sg:classifiers":[
        {
            "category":"Building & Trades",
            "subcategory":"Plumbing",
            "type":"Services"
        }
    ],
    "sg:phone":"+1 905 692 5670",
    "sg:postcode":"L0R 1W0",
    "sg:province":"ON",
    "sg:tags":[
        "contractor"
    ],
    "wof:name":"H & D Plumbing & Heating",
    "wof:placetype":"venue"
},
  "geometry": {"coordinates":[-79.91278076170001,43.1599464417],"type":"Point"}
}