{
  "type": "Feature",
  "properties": {
    "addr:full":"2540 5 Ave NW Calgary AB T2N 0T5",
    "addr:housenumber":"2540",
    "addr:postcode":"t2n 0t5",
    "addr:street":"5 Ave Nw",
    "iso:country":"CA",
    "sg:address":"2540 5 Ave NW",
    "sg:city":"Calgary",
    "sg:classifiers":[
        {
            "category":"Social Services",
            "type":"Services"
        }
    ],
    "sg:phone":"+1 403 291 1195",
    "sg:postcode":"T2N 0T5",
    "sg:province":"AB",
    "sg:tags":[
        "youth",
        "organization",
        "center"
    ],
    "wof:name":"Youth For Christ Canada",
    "wof:placetype":"venue"
},
  "geometry": {"coordinates":[-114.119308,51.057045],"type":"Point"}
}