{
  "type": "Feature",
  "properties": {
    "addr:full":"106 Aviva Park Dr Woodbridge ON L4L 9C7",
    "addr:housenumber":"106",
    "addr:postcode":"l4l 9c7",
    "addr:street":"Aviva Park Dr",
    "iso:country":"CA",
    "sg:address":"106 Aviva Park Dr",
    "sg:city":"Woodbridge",
    "sg:classifiers":[
        {
            "category":"Shopping",
            "subcategory":"Computers & Home Electronics",
            "type":"Retail Goods"
        }
    ],
    "sg:phone":"+1 905 265 0083",
    "sg:postcode":"L4L 9C7",
    "sg:province":"ON",
    "sg:tags":[
        "equipment",
        "dealer"
    ],
    "wof:name":"Unimatrix Computer Solutions",
    "wof:placetype":"venue"
},
  "geometry": {"coordinates":[-79.548851,43.777966],"type":"Point"}
}