{
  "type": "Feature",
  "properties": {
    "addr:full":"40 Church St Stirling ON K0K 3E0",
    "addr:housenumber":"40",
    "addr:postcode":"k0k 3e0",
    "addr:street":"Church St",
    "iso:country":"CA",
    "sg:address":"40 Church St",
    "sg:city":"Stirling",
    "sg:classifiers":[
        {
            "category":"Education",
            "subcategory":"School",
            "type":"Public Place"
        }
    ],
    "sg:phone":"+1 613 395 3308",
    "sg:postcode":"K0K 3E0",
    "sg:province":"ON",
    "wof:name":"Stirling Primary School",
    "wof:placetype":"venue"
},
  "geometry": {"coordinates":[-77.5494766235,44.2968673706],"type":"Point"}
}