{
  "type": "Feature",
  "properties": {
    "addr:full":"3311 4th Ave W Vancouver BC V6R 1N6",
    "addr:housenumber":"3311",
    "addr:postcode":"v6r 1n6",
    "addr:street":"4Th Ave W",
    "iso:country":"CA",
    "sg:address":"3311 4th Ave W",
    "sg:city":"Vancouver",
    "sg:classifiers":[
        {
            "category":"Food & Beverages",
            "subcategory":"Groceries & Convenience Stores",
            "type":"Retail Goods"
        }
    ],
    "sg:phone":"+1 604 736 1161",
    "sg:postcode":"V6R 1N6",
    "sg:province":"BC",
    "sg:tags":[
        "grocer"
    ],
    "wof:name":"Blenheim Food Market & Florist",
    "wof:placetype":"venue"
},
  "geometry": {"coordinates":[-123.177970886,49.2686271667],"type":"Point"}
}