{
  "type": "Feature",
  "properties": {
    "addr:full":"Edmonton AB T5H 4H8",
    "addr:postcode":"t5h 4h8",
    "iso:country":"CA",
    "sg:city":"Edmonton",
    "sg:classifiers":[
        {
            "category":"Organizations",
            "subcategory":"Professional Association",
            "type":"Services"
        }
    ],
    "sg:phone":"+1 780 424 7709",
    "sg:postcode":"T5H 4H8",
    "sg:province":"AB",
    "wof:name":"Mennonite Centre For Newcomers",
    "wof:placetype":"venue"
},
  "geometry": {"coordinates":[-113.492828,53.551727],"type":"Point"}
}