{
  "type": "Feature",
  "properties": {
    "addr:full":"Kelowna BC V1Y 6L2",
    "addr:postcode":"v1y 6l2",
    "iso:country":"CA",
    "sg:city":"Kelowna",
    "sg:classifiers":[
        {
            "category":"Health Services",
            "subcategory":"Health Practitioner",
            "type":"Services"
        }
    ],
    "sg:phone":"+1 250 868 0816",
    "sg:postcode":"V1Y 6L2",
    "sg:province":"BC",
    "sg:tags":[
        "psychologist"
    ],
    "wof:name":"Griffin, H Richard",
    "wof:placetype":"venue"
},
  "geometry": {"coordinates":[-119.498009,49.885208],"type":"Point"}
}