{
  "type": "Feature",
  "properties": {
    "addr:full":"1148 King St E Oshawa ON L1H 1H8",
    "addr:housenumber":"1148",
    "addr:postcode":"l1h 1h8",
    "addr:street":"King St E",
    "iso:country":"CA",
    "sg:address":"1148 King St E",
    "sg:city":"Oshawa",
    "sg:classifiers":[
        {
            "category":"Organizations",
            "subcategory":"Religious Organization",
            "type":"Services"
        }
    ],
    "sg:phone":"+1 905 433 0011",
    "sg:postcode":"L1H 1H8",
    "sg:province":"ON",
    "wof:name":"Seventh Day Adventist National",
    "wof:placetype":"venue"
},
  "geometry": {"coordinates":[-78.821518,43.90591],"type":"Point"}
}