{
  "type": "Feature",
  "properties": {
    "addr:full":"2405 Centennial Dr Sorrento BC V0E 2W0",
    "addr:housenumber":"2405",
    "addr:postcode":"v0e 2w0",
    "addr:street":"Centennial Dr",
    "iso:country":"CA",
    "sg:address":"2405 Centennial Dr",
    "sg:city":"Sorrento",
    "sg:classifiers":[
        {
            "category":"Organizations",
            "subcategory":"Religious Organization",
            "type":"Services"
        }
    ],
    "sg:phone":"+1 250 675 3636",
    "sg:postcode":"V0E 2W0",
    "sg:province":"BC",
    "sg:tags":[
        "church"
    ],
    "wof:name":"River of Life Community Church",
    "wof:placetype":"venue"
},
  "geometry": {"coordinates":[-119.3829422,50.8703117371],"type":"Point"}
}