{
  "type": "Feature",
  "properties": {
    "addr:full":"2600 Draper Ave Ottawa ON K2H 9A9",
    "addr:housenumber":"2600",
    "addr:postcode":"k2h 9a9",
    "addr:street":"Draper Ave",
    "iso:country":"CA",
    "sg:address":"2600 Draper Ave",
    "sg:city":"Ottawa",
    "sg:classifiers":[
        {
            "category":"Real Estate",
            "subcategory":"Real Estate Operator",
            "type":"Services"
        }
    ],
    "sg:phone":"+1 613 726 0070",
    "sg:postcode":"K2H 9A9",
    "sg:province":"ON",
    "sg:tags":[
        "apartment"
    ],
    "wof:name":"Greenbank Towers",
    "wof:placetype":"venue"
},
  "geometry": {"coordinates":[-75.78987100000001,45.343315],"type":"Point"}
}