{
  "type": "Feature",
  "properties": {
    "addr:full":"Regina Beach SK S0G 4C0",
    "addr:postcode":"s0g 4c0",
    "addr:street":"Regina Beach",
    "iso:country":"CA",
    "sg:city":"Regina Beach",
    "sg:classifiers":[
        {
            "category":"Travel",
            "subcategory":"Campground",
            "type":"Entertainment"
        }
    ],
    "sg:phone":"+1 306 729 2629",
    "sg:postcode":"S0G 4C0",
    "sg:province":"SK",
    "wof:name":"Regina Beach Campground",
    "wof:placetype":"venue"
},
  "geometry": {"coordinates":[-104.97403,50.787136],"type":"Point"}
}