{
  "type": "Feature",
  "properties": {
    "addr:full":"62 North St Goderich ON N7A 2T4",
    "addr:housenumber":"62",
    "addr:postcode":"n7a 2t4",
    "addr:street":"North St",
    "iso:country":"CA",
    "sg:address":"62 North St",
    "sg:city":"Goderich",
    "sg:classifiers":[
        {
            "category":"Professional",
            "subcategory":"Engineering",
            "type":"Services"
        }
    ],
    "sg:phone":"+1 519 524 2641",
    "sg:postcode":"N7A 2T4",
    "sg:province":"ON",
    "sg:tags":[
        "engineer"
    ],
    "wof:name":"B M Ross & Assoc Ltd",
    "wof:placetype":"venue"
},
  "geometry": {"coordinates":[-81.710999,43.744946],"type":"Point"}
}