{
  "type": "Feature",
  "properties": {
    "iso:country":"CA",
    "sg:city":"Calgary",
    "sg:classifiers":[
        {
            "category":"Freight",
            "type":"Transportation"
        }
    ],
    "sg:phone":"+1 403 253 1181",
    "sg:postcode":"T2H 2J7",
    "sg:province":"AB",
    "sg:tags":[
        "delivery",
        "courier"
    ],
    "wof:name":"Stampede Messenger & Express",
    "wof:placetype":"venue"
},
  "geometry": {"coordinates":[-114.03793335,50.9951705933],"type":"Point"}
}