{
  "type": "Feature",
  "properties": {
    "addr:full":"8888 Rue Sherbrooke E Montreal QC H1L 1C6",
    "addr:housenumber":"8888",
    "addr:postcode":"h1l 1c6",
    "addr:street":"Rue Sherbrooke E",
    "iso:country":"CA",
    "sg:address":"8888 Rue Sherbrooke E",
    "sg:city":"Montreal",
    "sg:classifiers":[
        {
            "category":"Personal",
            "subcategory":"Beauty Salon",
            "type":"Services"
        }
    ],
    "sg:phone":"+1 514 356 3067",
    "sg:postcode":"H1L 1C6",
    "sg:province":"QC",
    "wof:name":"Coiffure Flam-Meche",
    "wof:placetype":"venue"
},
  "geometry": {"coordinates":[-73.52887699999999,45.606365],"type":"Point"}
}