{
  "type": "Feature",
  "properties": {
    "addr:full":"3 Rue Prefontaine E Sainte-Agathe-Des-Monts QC J8C 1R5",
    "addr:housenumber":"3",
    "addr:postcode":"j8c 1r5",
    "addr:street":"Rue Prefontaine E Sainte-Agathe-Des-Monts",
    "iso:country":"CA",
    "sg:address":"3 Rue Prefontaine E",
    "sg:city":"Sainte-Agathe-Des-Monts",
    "sg:classifiers":[
        {
            "category":"Professional",
            "subcategory":"Lawyer & Legal Services",
            "type":"Services"
        }
    ],
    "sg:phone":"+1 819 326 3032",
    "sg:postcode":"J8C 1R5",
    "sg:province":"QC",
    "sg:tags":[
        "attorney"
    ],
    "wof:name":"Godard, Guy",
    "wof:placetype":"venue"
},
  "geometry": {"coordinates":[-74.287903,46.049728],"type":"Point"}
}