{
  "type": "Feature",
  "properties": {
    "iso:country":"CA",
    "sg:city":"Mississauga",
    "sg:classifiers":[
        {
            "category":"Professional",
            "subcategory":"Accounting & Tax Preparation",
            "type":"Services"
        }
    ],
    "sg:phone":"+1 905 826 5110",
    "sg:postcode":"L5M 4Y4",
    "sg:province":"ON",
    "sg:tags":[
        "accountant"
    ],
    "wof:name":"Oberc, Mathew CA",
    "wof:placetype":"venue"
},
  "geometry": {"coordinates":[-79.721947,43.588837],"type":"Point"}
}