{
  "type": "Feature",
  "properties": {
    "addr:full":"430 Rue St-Francois Portneuf-Station QC G0A 2Z0",
    "addr:housenumber":"430",
    "addr:postcode":"g0a 2z0",
    "addr:street":"Rue St-Francois Portneuf-Station",
    "iso:country":"CA",
    "sg:address":"430 Rue St-Francois",
    "sg:city":"Portneuf-Station",
    "sg:classifiers":[
        {
            "category":"Organizations",
            "subcategory":"Religious Organization",
            "type":"Services"
        }
    ],
    "sg:phone":"+1 418 286 6146",
    "sg:postcode":"G0A 2Z0",
    "sg:province":"QC",
    "sg:tags":[
        "house",
        "retreat"
    ],
    "wof:name":"Maison Des Ainees Portneuf",
    "wof:placetype":"venue"
},
  "geometry": {"coordinates":[-71.88864100000001,46.711823],"type":"Point"}
}