{
  "type": "Feature",
  "properties": {
    "addr:full":"24 Bramalea Rd Brampton ON L6T 2W7",
    "addr:housenumber":"24",
    "addr:postcode":"l6t 2w7",
    "addr:street":"Bramalea Rd",
    "iso:country":"CA",
    "sg:address":"24 Bramalea Rd",
    "sg:city":"Brampton",
    "sg:classifiers":[
        {
            "category":"Retail",
            "subcategory":"Auto Repair",
            "type":"Services"
        }
    ],
    "sg:phone":"+1 905 799 6440",
    "sg:postcode":"L6T 2W7",
    "sg:province":"ON",
    "sg:tags":[
        "repairing",
        "automobile"
    ],
    "wof:name":"Cloverdale Automotive",
    "wof:placetype":"venue"
},
  "geometry": {"coordinates":[-79.6922,43.705494],"type":"Point"}
}