{
  "type": "Feature",
  "properties": {
    "addr:full":"Calgary AB T3H 3C8",
    "addr:postcode":"t3h 3c8",
    "iso:country":"CA",
    "sg:city":"Calgary",
    "sg:classifiers":[
        {
            "category":"Shopping",
            "subcategory":"Computers & Home Electronics",
            "type":"Retail Goods"
        }
    ],
    "sg:phone":"+1 403 215 9299",
    "sg:postcode":"T3H 3C8",
    "sg:province":"AB",
    "sg:tags":[
        "equipment",
        "satellite",
        "system"
    ],
    "wof:name":"Innovative Edge Inc",
    "wof:placetype":"venue"
},
  "geometry": {"coordinates":[-114.16911315900001,51.015247345],"type":"Point"}
}