{
  "type": "Feature",
  "properties": {
    "iso:country":"CA",
    "sg:city":"Charlesbourg",
    "sg:classifiers":[
        {
            "category":"Wholesale",
            "subcategory":"Apparel",
            "type":"Manufacturing & Wholesale Goods"
        }
    ],
    "sg:phone":"+1 418 623 4308",
    "sg:postcode":"G1H 5M1",
    "sg:province":"QC",
    "sg:tags":[
        "clothing"
    ],
    "wof:name":"Agences Brisson Inc",
    "wof:placetype":"venue"
},
  "geometry": {"coordinates":[-71.2544174194,46.8398323059],"type":"Point"}
}