{
  "type": "Feature",
  "properties": {
    "addr:full":"2446 Lakeshore Rd W Oakville ON L6L 1H7",
    "addr:housenumber":"2446",
    "addr:postcode":"l6l 1h7",
    "addr:street":"Lakeshore Rd W",
    "iso:country":"CA",
    "sg:address":"2446 Lakeshore Rd W",
    "sg:city":"Oakville",
    "sg:classifiers":[
        {
            "category":"Professional",
            "subcategory":"Management & Consulting",
            "type":"Services"
        }
    ],
    "sg:phone":"+1 905 827 7800",
    "sg:postcode":"L6L 1H7",
    "sg:province":"ON",
    "sg:tags":[
        "communications",
        "consultant"
    ],
    "wof:name":"Jem Communications",
    "wof:placetype":"venue"
},
  "geometry": {"coordinates":[-79.7114105225,43.3944740295],"type":"Point"}
}