{
  "type": "Feature",
  "properties": {
    "iso:country":"CA",
    "sg:address":"2452 Boul Laurier",
    "sg:city":"Sainte-Foy",
    "sg:classifiers":[
        {
            "category":"Wholesale",
            "subcategory":"Drugs",
            "type":"Manufacturing & Wholesale Goods"
        }
    ],
    "sg:phone":"+1 418 654 0316",
    "sg:postcode":"G1V 2L1",
    "sg:province":"QC",
    "sg:tags":[
        "preparation",
        "toilet"
    ],
    "wof:name":"Crabtree & Evelyn",
    "wof:placetype":"venue"
},
  "geometry": {"coordinates":[-71.276314,46.773682],"type":"Point"}
}