{
  "type": "Feature",
  "properties": {
    "addr:full":"311 Connie Cres Concord ON L4K 5R2",
    "addr:housenumber":"311",
    "addr:postcode":"l4k 5r2",
    "addr:street":"Connie Cres",
    "iso:country":"CA",
    "sg:address":"311 Connie Cres",
    "sg:city":"Concord",
    "sg:classifiers":[
        {
            "category":"Manufacturing",
            "subcategory":"Tools & Machinery",
            "type":"Manufacturing & Wholesale Goods"
        }
    ],
    "sg:phone":"+1 905 669 2253",
    "sg:postcode":"L4K 5R2",
    "sg:province":"ON",
    "sg:tags":[
        "equipment",
        "hydraulic",
        "supply"
    ],
    "wof:name":"Macrodyne Technologies Inc",
    "wof:placetype":"venue"
},
  "geometry": {"coordinates":[-79.482361,43.820213],"type":"Point"}
}