{
  "type": "Feature",
  "properties": {
    "addr:full":"Wellesley ON N0B 2T0",
    "addr:postcode":"n0b 2t0",
    "iso:country":"CA",
    "sg:city":"Wellesley",
    "sg:classifiers":[
        {
            "category":"Retail",
            "subcategory":"Auto Repair",
            "type":"Services"
        }
    ],
    "sg:phone":"+1 519 656 2725",
    "sg:postcode":"N0B 2T0",
    "sg:province":"ON",
    "sg:tags":[
        "repairing",
        "automobile"
    ],
    "wof:name":"Wellesley Service Ctr Ltd",
    "wof:placetype":"venue"
},
  "geometry": {"coordinates":[-80.76667785639999,43.4775161743],"type":"Point"}
}