{
  "type": "Feature",
  "properties": {
    "iso:country":"CA",
    "sg:city":"London",
    "sg:classifiers":[
        {
            "category":"Recreation",
            "type":"Entertainment"
        }
    ],
    "sg:phone":"+1 519 685 2730",
    "sg:postcode":"N6E 1N9",
    "sg:province":"ON",
    "sg:tags":[
        "bingo",
        "game"
    ],
    "wof:name":"London Bingo Country",
    "wof:placetype":"venue"
},
  "geometry": {"coordinates":[-81.220268,42.933224],"type":"Point"}
}