{
  "type": "Feature",
  "properties": {
    "addr:full":"Rock Forest QC J1N 3B9",
    "addr:postcode":"j1n 3b9",
    "iso:country":"CA",
    "sg:city":"Rock Forest",
    "sg:classifiers":[
        {
            "category":"Banks & Credit Unions",
            "subcategory":"Bank",
            "type":"Services"
        }
    ],
    "sg:phone":"+1 819 564 1644",
    "sg:postcode":"J1N 3B9",
    "sg:province":"QC",
    "wof:name":"Banque Nationale Du Canada",
    "wof:placetype":"venue"
},
  "geometry": {"coordinates":[-71.977722168,45.3754959106],"type":"Point"}
}