{
  "type": "Feature",
  "properties": {
    "addr:full":"709 Main St W Hamilton ON L8S 1A2",
    "addr:housenumber":"709",
    "addr:postcode":"l8s 1a2",
    "addr:street":"Main St W",
    "iso:country":"CA",
    "sg:address":"709 Main St W",
    "sg:city":"Hamilton",
    "sg:classifiers":[
        {
            "category":"Professional",
            "subcategory":"Credit Reporting & Collection",
            "type":"Services"
        }
    ],
    "sg:phone":"+1 905 525 4420",
    "sg:postcode":"L8S 1A2",
    "sg:province":"ON",
    "sg:tags":[
        "agency"
    ],
    "wof:name":"Trans Union of Canada Inc",
    "wof:placetype":"venue"
},
  "geometry": {"coordinates":[-79.897865,43.259869],"type":"Point"}
}