{
  "type": "Feature",
  "properties": {
    "iso:country":"CA",
    "sg:address":"NW 26 19 19W",
    "sg:city":"Rivers",
    "sg:classifiers":[
        {
            "category":"Travel",
            "subcategory":"Campground",
            "type":"Entertainment"
        }
    ],
    "sg:phone":"+1 204 848 2268",
    "sg:postcode":"R0K 1X0",
    "sg:province":"MB",
    "sg:tags":[
        "camp"
    ],
    "wof:name":"Camp Wasaga",
    "wof:placetype":"venue"
},
  "geometry": {"coordinates":[-100.23764038100001,50.0292854309],"type":"Point"}
}