{
  "type": "Feature",
  "properties": {
    "addr:full":"3841 Rue Masson Montreal QC H1X 1S9",
    "addr:housenumber":"3841",
    "addr:postcode":"h1x 1s9",
    "addr:street":"Rue Masson",
    "iso:country":"CA",
    "sg:address":"3841 Rue Masson",
    "sg:city":"Montreal",
    "sg:classifiers":[
        {
            "category":"Restaurant",
            "type":"Food & Drink"
        }
    ],
    "sg:phone":"+1 514 729 0835",
    "sg:postcode":"H1X 1S9",
    "sg:province":"QC",
    "wof:name":"Daoust Yan",
    "wof:placetype":"venue"
},
  "geometry": {"coordinates":[-73.57032,45.556469],"type":"Point"}
}