{
  "type": "Feature",
  "properties": {
    "addr:full":"65 Speedvale Ave W # 53 Guelph ON N1H 1J7",
    "addr:housenumber":"65",
    "addr:postcode":"n1h 1j7",
    "addr:street":"Speedvale Ave W # 53",
    "iso:country":"CA",
    "sg:address":"65 Speedvale Ave W # 53",
    "sg:city":"Guelph",
    "sg:classifiers":[
        {
            "category":"Real Estate",
            "subcategory":"Real Estate Operator",
            "type":"Services"
        }
    ],
    "sg:phone":"+1 519 837 1440",
    "sg:postcode":"N1H 1J7",
    "sg:province":"ON",
    "sg:tags":[
        "apartment"
    ],
    "wof:name":"Twin Towers Guelph",
    "wof:placetype":"venue"
},
  "geometry": {"coordinates":[-80.272087,43.555798],"type":"Point"}
}