{
  "type": "Feature",
  "properties": {
    "addr:full":"149 College St Toronto ON M5T 1P5",
    "addr:housenumber":"149",
    "addr:postcode":"m5t 1p5",
    "addr:street":"College St",
    "iso:country":"CA",
    "sg:address":"149 College St",
    "sg:city":"Toronto",
    "sg:classifiers":[
        {
            "category":"Education",
            "subcategory":"College",
            "type":"Public Place"
        }
    ],
    "sg:phone":"+1 416 966 3066",
    "sg:postcode":"M5T 1P5",
    "sg:province":"ON",
    "sg:tags":[
        "academic",
        "school"
    ],
    "wof:name":"Trebas Institute",
    "wof:placetype":"venue"
},
  "geometry": {"coordinates":[-79.39250946040001,43.6592521667],"type":"Point"}
}