{
  "type": "Feature",
  "properties": {
    "iso:country":"CA",
    "sg:address":"15750 Boul Lacroix",
    "sg:city":"Saint-Georges",
    "sg:classifiers":[
        {
            "category":"Building & Trades",
            "subcategory":"Construction",
            "type":"Services"
        }
    ],
    "sg:phone":"+1 418 228 9180",
    "sg:postcode":"G5Y 1S2",
    "sg:province":"QC",
    "sg:tags":[
        "excavating",
        "contractor"
    ],
    "wof:name":"Excavation Transco Inc",
    "wof:placetype":"venue"
},
  "geometry": {"coordinates":[-70.65479278559999,46.102596283],"type":"Point"}
}