{
  "type": "Feature",
  "properties": {
    "iso:country":"CA",
    "sg:address":"10250 101 St NW # G6",
    "sg:city":"Edmonton",
    "sg:classifiers":[
        {
            "category":"Manufacturing",
            "subcategory":"Jewelry",
            "type":"Manufacturing & Wholesale Goods"
        }
    ],
    "sg:phone":"+1 780 421 4367",
    "sg:postcode":"T5J 3P4",
    "sg:province":"AB",
    "wof:name":"Mark Katzeff Designer Goldsmth",
    "wof:placetype":"venue"
},
  "geometry": {"coordinates":[-113.49385100000001,53.544888],"type":"Point"}
}