{
  "type": "Feature",
  "properties": {
    "addr:full":"144 Bennett Dr Gander NL A1V 2E4",
    "addr:housenumber":"144",
    "addr:postcode":"a1v 2e4",
    "addr:street":"Bennett Dr",
    "iso:country":"CA",
    "sg:address":"144 Bennett Dr",
    "sg:city":"Gander",
    "sg:classifiers":[
        {
            "category":"Home & Garden",
            "subcategory":"Building Materials",
            "type":"Retail Goods"
        }
    ],
    "sg:phone":"+1 709 651 3282",
    "sg:postcode":"A1V 2E4",
    "sg:province":"NL",
    "sg:tags":[
        "paint"
    ],
    "wof:name":"Allan's Matchless Decor",
    "wof:placetype":"venue"
},
  "geometry": {"coordinates":[-54.6047477722,48.952495575],"type":"Point"}
}