{
  "type": "Feature",
  "properties": {
    "addr:full":"366 Carpathia Rd Winnipeg MB R3N 1T5",
    "addr:housenumber":"366",
    "addr:postcode":"r3n 1t5",
    "addr:street":"Carpathia Rd",
    "iso:country":"CA",
    "sg:address":"366 Carpathia Rd",
    "sg:city":"Winnipeg",
    "sg:classifiers":[
        {
            "category":"Shopping",
            "subcategory":"Gifts & Souvenirs",
            "type":"Retail Goods"
        }
    ],
    "sg:phone":"+1 204 487 4386",
    "sg:postcode":"R3N 1T5",
    "sg:province":"MB",
    "sg:tags":[
        "party",
        "game",
        "supply"
    ],
    "wof:name":"Party Works Interactive Games",
    "wof:placetype":"venue"
},
  "geometry": {"coordinates":[-97.204216,49.864944],"type":"Point"}
}