{
  "type": "Feature",
  "properties": {
    "addr:full":"855 8th St Kamloops BC V2B 8E1",
    "addr:housenumber":"855",
    "addr:postcode":"bc v2b 8e1",
    "addr:street":"8Th St",
    "iso:country":"CA",
    "sg:address":"855 8th St",
    "sg:city":"Kamloops",
    "sg:classifiers":[
        {
            "category":"Restaurant",
            "type":"Food & Drink"
        }
    ],
    "sg:phone":"+1 250 376 3301",
    "sg:postcode":"V2B 8E1",
    "sg:province":"BC",
    "wof:name":"Kfc",
    "wof:placetype":"venue"
},
  "geometry": {"coordinates":[-120.36331199999999,50.70023],"type":"Point"}
}