{
  "type": "Feature",
  "properties": {
    "iso:country":"CA",
    "sg:address":"855 8th St",
    "sg:city":"Kamloops",
    "sg:classifiers":[
        {
            "category":"Restaurant",
            "type":"Food & Drink"
        }
    ],
    "sg:phone":"+1 250 376 3301",
    "sg:postcode":"V2B 8E1",
    "sg:province":"BC",
    "wof:name":"Kfc",
    "wof:placetype":"venue"
},
  "geometry": {"coordinates":[-120.363312,50.70023],"type":"Point"}
}