{
  "type": "Feature",
  "properties": {
    "addr:full":"Surrey BC V3R 7S2",
    "addr:postcode":"v3r 7s2",
    "iso:country":"CA",
    "sg:city":"Surrey",
    "sg:classifiers":[
        {
            "category":"Manufacturing",
            "subcategory":"Metals",
            "type":"Manufacturing & Wholesale Goods"
        }
    ],
    "sg:phone":"+1 604 580 2210",
    "sg:postcode":"V3R 7S2",
    "sg:province":"BC",
    "sg:tags":[
        "welding"
    ],
    "wof:name":"Kjb Welding & Fabricating",
    "wof:placetype":"venue"
},
  "geometry": {"coordinates":[-122.830215,49.105179],"type":"Point"}
}