{
  "type": "Feature",
  "properties": {
    "addr:full":"125 Rue Saint-Thomas Montmagny QC G5V 1M3",
    "addr:housenumber":"125",
    "addr:postcode":"g5v 1m3",
    "addr:street":"Rue Saint-Thomas",
    "iso:country":"CA",
    "sg:address":"125 Rue Saint-Thomas",
    "sg:city":"Montmagny",
    "sg:classifiers":[
        {
            "category":"Organizations",
            "subcategory":"Labor Organization",
            "type":"Services"
        }
    ],
    "sg:phone":"+1 418 248 2030",
    "sg:postcode":"G5V 1M3",
    "sg:province":"QC",
    "wof:name":"Conseil Central DE Quebec",
    "wof:placetype":"venue"
},
  "geometry": {"coordinates":[-70.557762,46.980785],"type":"Point"}
}