{
  "type": "Feature",
  "properties": {
    "iso:country":"CA",
    "sg:address":"1160 Sanford St",
    "sg:city":"Winnipeg",
    "sg:classifiers":[
        {
            "category":"Manufacturing",
            "subcategory":"Tools & Machinery",
            "type":"Manufacturing & Wholesale Goods"
        }
    ],
    "sg:phone":"+1 204 788 1692",
    "sg:postcode":"R3E 2Z9",
    "sg:province":"MB",
    "sg:tags":[
        "lubricating",
        "system",
        "devices"
    ],
    "wof:name":"A & H Petroleum Svc Ltd",
    "wof:placetype":"venue"
},
  "geometry": {"coordinates":[-97.19375610349999,49.8996391296],"type":"Point"}
}