{
  "type": "Feature",
  "properties": {
    "addr:full":"10 University Ave Baysville ON P0B 1A0",
    "addr:housenumber":"10",
    "addr:postcode":"p0b 1a0",
    "addr:street":"University Ave",
    "iso:country":"CA",
    "sg:address":"10 University Ave",
    "sg:city":"Baysville",
    "sg:classifiers":[
        {
            "category":"Education",
            "subcategory":"Library",
            "type":"Public Place"
        }
    ],
    "sg:phone":"+1 705 767 2361",
    "sg:postcode":"P0B 1A0",
    "sg:province":"ON",
    "wof:name":"Baysville Public Library",
    "wof:placetype":"venue"
},
  "geometry": {"coordinates":[-79.11772155760001,45.1474456787],"type":"Point"}
}