{
  "type": "Feature",
  "properties": {
    "iso:country":"CA",
    "sg:address":"475 3rd Ave",
    "sg:city":"Rapid City",
    "sg:classifiers":[
        {
            "category":"Shopping",
            "type":"Retail Goods"
        }
    ],
    "sg:phone":"+1 204 826 2161",
    "sg:postcode":"R0K 1W0",
    "sg:province":"MB",
    "sg:tags":[
        "monument"
    ],
    "wof:name":"Rapid City Granite",
    "wof:placetype":"venue"
},
  "geometry": {"coordinates":[-100.037284851,50.1199836731],"type":"Point"}
}