{
  "type": "Feature",
  "properties": {
    "addr:full":"36 Ottawa St Morrisburg ON K0C 1X0",
    "addr:housenumber":"36",
    "addr:postcode":"k0c 1x0",
    "addr:street":"Ottawa St",
    "iso:country":"CA",
    "sg:address":"36 Ottawa St",
    "sg:city":"Morrisburg",
    "sg:classifiers":[
        {
            "category":"Health Services",
            "subcategory":"Doctor",
            "type":"Services"
        }
    ],
    "sg:phone":"+1 613 543 2963",
    "sg:postcode":"K0C 1X0",
    "sg:province":"ON",
    "sg:tags":[
        "physician",
        "surgeon"
    ],
    "wof:name":"Houze, G N MD",
    "wof:placetype":"venue"
},
  "geometry": {"coordinates":[-75.1827697754,44.8971366882],"type":"Point"}
}