{
  "type": "Feature",
  "properties": {
    "iso:country":"CA",
    "sg:city":"L'Orignal",
    "sg:classifiers":[
        {
            "category":"Wholesale",
            "subcategory":"Machinery & Supplies",
            "type":"Manufacturing & Wholesale Goods"
        }
    ],
    "sg:phone":"+1 613 632 0005",
    "sg:postcode":"K0B 1K0",
    "sg:province":"ON",
    "sg:tags":[
        "equipment",
        "welding"
    ],
    "wof:name":"Wathier Welding Products",
    "wof:placetype":"venue"
},
  "geometry": {"coordinates":[-74.691116333,45.6204414368],"type":"Point"}
}