{
  "type": "Feature",
  "properties": {
    "addr:full":"167 Beatty St Sudbury ON P3C 4E7",
    "addr:housenumber":"167",
    "addr:postcode":"p3c 4e7",
    "addr:street":"Beatty St",
    "iso:country":"CA",
    "sg:address":"167 Beatty St",
    "sg:city":"Sudbury",
    "sg:classifiers":[
        {
            "category":"Professional",
            "subcategory":"Management & Consulting",
            "type":"Services"
        }
    ],
    "sg:phone":"+1 705 674 3866",
    "sg:postcode":"P3C 4E7",
    "sg:province":"ON",
    "sg:tags":[
        "party",
        "planning",
        "supply"
    ],
    "wof:name":"Bouncing Merryland Inflatables",
    "wof:placetype":"venue"
},
  "geometry": {"coordinates":[-81.00721,46.49707],"type":"Point"}
}