{
  "type": "Feature",
  "properties": {
    "addr:full":"143 Rue Du Roi Sorel-Tracy QC J3P 4N4",
    "addr:housenumber":"143",
    "addr:postcode":"j3p 4n4",
    "addr:street":"Rue Du Roi",
    "iso:country":"CA",
    "sg:address":"143 Rue Du Roi",
    "sg:city":"Sorel-Tracy",
    "sg:classifiers":[
        {
            "category":"Personal",
            "subcategory":"Barber",
            "type":"Services"
        }
    ],
    "sg:phone":"+1 450 743 3188",
    "sg:postcode":"J3P 4N4",
    "sg:province":"QC",
    "wof:name":"Roberge, Yves",
    "wof:placetype":"venue"
},
  "geometry": {"coordinates":[-73.114609,46.040874],"type":"Point"}
}