{
  "type": "Feature",
  "properties": {
    "addr:full":"1800 8th St E Owen Sound ON N4K 6M9",
    "addr:housenumber":"1800",
    "addr:postcode":"n4k 6m9",
    "addr:street":"8Th St E",
    "iso:country":"CA",
    "sg:address":"1800 8th St E",
    "sg:city":"Owen Sound",
    "sg:classifiers":[
        {
            "category":"Health Services",
            "subcategory":"Doctor",
            "type":"Services"
        }
    ],
    "sg:phone":"+1 519 371 2125",
    "sg:postcode":"N4K 6M9",
    "sg:province":"ON",
    "sg:tags":[
        "physician",
        "surgeon"
    ],
    "wof:name":"Ostrander, J J MD",
    "wof:placetype":"venue"
},
  "geometry": {"coordinates":[-80.912109,44.567593],"type":"Point"}
}