{
  "type": "Feature",
  "properties": {
    "addr:full":"1064 Austin Ave Coquitlam BC V3K 3P3",
    "addr:housenumber":"1064",
    "addr:postcode":"v3k 3p3",
    "addr:street":"Austin Ave",
    "iso:country":"CA",
    "sg:address":"1064 Austin Ave",
    "sg:city":"Coquitlam",
    "sg:classifiers":[
        {
            "category":"Manufacturing",
            "subcategory":"Printing",
            "type":"Manufacturing & Wholesale Goods"
        }
    ],
    "sg:phone":"+1 604 937 3212",
    "sg:postcode":"V3K 3P3",
    "sg:province":"BC",
    "sg:tags":[
        "printer"
    ],
    "wof:name":"Coquitlam Printers Ltd",
    "wof:placetype":"venue"
},
  "geometry": {"coordinates":[-122.863739,49.248775],"type":"Point"}
}