{
  "type": "Feature",
  "properties": {
    "addr:full":"60 S 1st St W Magrath AB T0K 1J0",
    "addr:housenumber":"60",
    "addr:postcode":"t0k 1j0",
    "addr:street":"S 1St St W Magrath",
    "iso:country":"CA",
    "sg:address":"60 S 1st St W",
    "sg:city":"Magrath",
    "sg:classifiers":[
        {
            "category":"Wholesale",
            "subcategory":"Machinery & Supplies",
            "type":"Manufacturing & Wholesale Goods"
        }
    ],
    "sg:phone":"+1 403 758 3155",
    "sg:postcode":"T0K 1J0",
    "sg:province":"AB",
    "sg:tags":[
        "farm",
        "equipment"
    ],
    "wof:name":"Magrath CO-Operative Assn Ltd",
    "wof:placetype":"venue"
},
  "geometry": {"coordinates":[-112.862213,49.418282],"type":"Point"}
}