{
  "type": "Feature",
  "properties": {
    "addr:full":"2540 Eglinton Ave W York ON M6M 1T1",
    "addr:housenumber":"2540",
    "addr:postcode":"m6m 1t1",
    "addr:street":"Eglinton Ave W",
    "iso:country":"CA",
    "sg:address":"2540 Eglinton Ave W",
    "sg:city":"York",
    "sg:classifiers":[
        {
            "category":"Restaurant",
            "type":"Food & Drink"
        }
    ],
    "sg:phone":"+1 416 651 1166",
    "sg:postcode":"M6M 1T1",
    "sg:province":"ON",
    "sg:tags":[
        "pizza"
    ],
    "wof:name":"Alnoor Halal Pizza & Chicken",
    "wof:placetype":"venue"
},
  "geometry": {"coordinates":[-79.471024,43.691216],"type":"Point"}
}