{
  "type": "Feature",
  "properties": {
    "addr:full":"Burford ON N0E 1A0",
    "addr:postcode":"n0e 1a0",
    "iso:country":"CA",
    "sg:city":"Burford",
    "sg:classifiers":[
        {
            "category":"Organizations",
            "subcategory":"Community Association",
            "type":"Services"
        }
    ],
    "sg:phone":"+1 519 449 5339",
    "sg:postcode":"N0E 1A0",
    "sg:province":"ON",
    "sg:tags":[
        "club"
    ],
    "wof:name":"Royal Canadian Legion",
    "wof:placetype":"venue"
},
  "geometry": {"coordinates":[-80.425011,43.099052],"type":"Point"}
}