{
  "type": "Feature",
  "properties": {
    "iso:country":"CA",
    "sg:city":"Sherbrooke",
    "sg:classifiers":[
        {
            "category":"Wholesale",
            "subcategory":"Construction Materials",
            "type":"Manufacturing & Wholesale Goods"
        }
    ],
    "sg:phone":"+1 819 563 8080",
    "sg:postcode":"J1L 1W5",
    "sg:province":"QC",
    "sg:tags":[
        "asbestos",
        "product"
    ],
    "wof:name":"Garlock Du Canada Ltee",
    "wof:placetype":"venue"
},
  "geometry": {"coordinates":[-71.9644317627,45.407371521],"type":"Point"}
}