{
  "type": "Feature",
  "properties": {
    "addr:full":"62 Miller St Toronto ON M6N 2Z9",
    "addr:housenumber":"62",
    "addr:postcode":"m6n 2z9",
    "addr:street":"Miller St",
    "iso:country":"CA",
    "sg:address":"62 Miller St",
    "sg:city":"Toronto",
    "sg:classifiers":[
        {
            "category":"Manufacturing",
            "subcategory":"Motor Vehicles & Parts",
            "type":"Manufacturing & Wholesale Goods"
        }
    ],
    "sg:phone":"+1 416 656 3861",
    "sg:postcode":"M6N 2Z9",
    "sg:province":"ON",
    "sg:tags":[
        "automobile",
        "supply"
    ],
    "wof:name":"Gino's Waterpump Rebuilders",
    "wof:placetype":"venue"
},
  "geometry": {"coordinates":[-79.460205,43.668839],"type":"Point"}
}