{
  "type": "Feature",
  "properties": {
    "addr:full":"551 Richmond St London ON N6A 3E9",
    "addr:housenumber":"551",
    "addr:postcode":"n6a 3e9",
    "addr:street":"Richmond St",
    "iso:country":"CA",
    "sg:address":"551 Richmond St",
    "sg:city":"London",
    "sg:classifiers":[
        {
            "category":"Restaurant",
            "type":"Food & Drink"
        }
    ],
    "sg:phone":"+1 519 850 8080",
    "sg:postcode":"N6A 3E9",
    "sg:province":"ON",
    "wof:name":"Barakat Restaurant",
    "wof:placetype":"venue"
},
  "geometry": {"coordinates":[-81.2507553101,42.9885787964],"type":"Point"}
}