{
  "type": "Feature",
  "properties": {
    "addr:full":"1035 Av DE Peribonka Boisbriand QC J7G 2C3",
    "addr:housenumber":"1035",
    "addr:postcode":"j7g 2c3",
    "addr:street":"Av De Peribonka",
    "iso:country":"CA",
    "sg:address":"1035 Av DE Peribonka",
    "sg:city":"Boisbriand",
    "sg:classifiers":[
        {
            "category":"Wholesale",
            "subcategory":"Motor Vehicles",
            "type":"Manufacturing & Wholesale Goods"
        }
    ],
    "sg:phone":"+1 450 971 0033",
    "sg:postcode":"J7G 2C3",
    "sg:province":"QC",
    "sg:tags":[
        "automobile",
        "truck",
        "broker"
    ],
    "wof:name":"Accessurauto",
    "wof:placetype":"venue"
},
  "geometry": {"coordinates":[-73.82627100000001,45.62471],"type":"Point"}
}