{
  "type": "Feature",
  "properties": {
    "addr:full":"1930 Boul Lemire Drummondville QC J2B 7M4",
    "addr:housenumber":"1930",
    "addr:postcode":"j2b 7m4",
    "addr:street":"Boul Lemire",
    "iso:country":"CA",
    "sg:address":"1930 Boul Lemire",
    "sg:city":"Drummondville",
    "sg:classifiers":[
        {
            "category":"Bars & Pubs",
            "type":"Food & Drink"
        }
    ],
    "sg:phone":"+1 819 475 2588",
    "sg:postcode":"J2B 7M4",
    "sg:province":"QC",
    "sg:tags":[
        "lounge",
        "cocktail"
    ],
    "wof:name":"Bar Terrasse Du Blvd Lemire",
    "wof:placetype":"venue"
},
  "geometry": {"coordinates":[-72.502037,45.86602],"type":"Point"}
}