{
  "type": "Feature",
  "properties": {
    "addr:full":"General Delivery Hudson ON P0V 1X0",
    "addr:postcode":"p0v 1x0",
    "iso:country":"CA",
    "sg:address":"General Delivery",
    "sg:city":"Hudson",
    "sg:classifiers":[
        {
            "category":"Government",
            "subcategory":"Office",
            "type":"Public Place"
        }
    ],
    "sg:phone":"+1 807 582 3523",
    "sg:postcode":"P0V 1X0",
    "sg:province":"ON",
    "wof:name":"Lac Seul First Nation",
    "wof:placetype":"venue"
},
  "geometry": {"coordinates":[-92.169304,50.090839],"type":"Point"}
}