{
  "type": "Feature",
  "properties": {
    "addr:full":"Abbotsford BC V2S 6A4",
    "addr:postcode":"v2s 6a4",
    "iso:country":"CA",
    "sg:city":"Abbotsford",
    "sg:classifiers":[
        {
            "category":"Government",
            "subcategory":"Office",
            "type":"Public Place"
        }
    ],
    "sg:phone":"+1 604 870 7900",
    "sg:postcode":"V2S 6A4",
    "sg:province":"BC",
    "wof:name":"B C Fraser Health Valley Reg",
    "wof:placetype":"venue"
},
  "geometry": {"coordinates":[-122.310089,49.052586],"type":"Point"}
}