{
  "type": "Feature",
  "properties": {
    "addr:full":"Ottawa ON K1V 0W3",
    "addr:postcode":"k1v 0w3",
    "iso:country":"CA",
    "sg:city":"Ottawa",
    "sg:classifiers":[
        {
            "category":"Shopping",
            "type":"Retail Goods"
        }
    ],
    "sg:phone":"+1 613 523 1112",
    "sg:postcode":"K1V 0W3",
    "sg:province":"ON",
    "sg:tags":[
        "picture",
        "frame",
        "art",
        "gallery",
        "dealer"
    ],
    "wof:name":"Frames By Rockwell",
    "wof:placetype":"venue"
},
  "geometry": {"coordinates":[-75.664185,45.371906],"type":"Point"}
}