{
  "type": "Feature",
  "properties": {
    "iso:country":"CA",
    "sg:address":"206 Toronto S",
    "sg:city":"Markdale",
    "sg:classifiers":[
        {
            "category":"Professional",
            "subcategory":"Management & Consulting",
            "type":"Services"
        }
    ],
    "sg:phone":"+1 519 986 3756",
    "sg:postcode":"N0C 1H0",
    "sg:province":"ON",
    "sg:tags":[
        "agricultural",
        "government",
        "consultant"
    ],
    "wof:name":"Agricultural Services Ctr",
    "wof:placetype":"venue"
},
  "geometry": {"coordinates":[-80.64246368409999,44.3151054382],"type":"Point"}
}