{
  "type": "Feature",
  "properties": {
    "addr:full":"119 1E Av O Sainte-Anne-Des-Monts QC G4V 1B8",
    "addr:housenumber":"119",
    "addr:postcode":"g4v 1b8",
    "addr:street":"1E Av O",
    "iso:country":"CA",
    "sg:address":"119 1E Av O",
    "sg:city":"Sainte-Anne-Des-Monts",
    "sg:classifiers":[
        {
            "category":"Shopping",
            "subcategory":"Used Merchandise",
            "type":"Retail Goods"
        }
    ],
    "sg:phone":"+1 418 763 7223",
    "sg:postcode":"G4V 1B8",
    "sg:province":"QC",
    "sg:tags":[
        "furniture"
    ],
    "wof:name":"Aubaines Des Monts Enr",
    "wof:placetype":"venue"
},
  "geometry": {"coordinates":[-66.486397,49.129215],"type":"Point"}
}