{
  "type": "Feature",
  "properties": {
    "addr:full":"Red Deer AB T4R 1N9",
    "addr:postcode":"t4r 1n9",
    "iso:country":"CA",
    "sg:city":"Red Deer",
    "sg:classifiers":[
        {
            "category":"Shopping",
            "type":"Retail Goods"
        }
    ],
    "sg:phone":"+1 403 314 0962",
    "sg:postcode":"T4R 1N9",
    "sg:province":"AB",
    "sg:tags":[
        "cosmetic",
        "perfume"
    ],
    "wof:name":"Body Shop",
    "wof:placetype":"venue"
},
  "geometry": {"coordinates":[-113.807007,52.245056],"type":"Point"}
}