{
  "type": "Feature",
  "properties": {
    "addr:full":"Sainte-Thecle QC G0X 3G0",
    "addr:postcode":"g0x 3g0",
    "iso:country":"CA",
    "sg:city":"Sainte-Thecle",
    "sg:classifiers":[
        {
            "category":"Local Transit",
            "type":"Transportation"
        }
    ],
    "sg:phone":"+1 418 289 3723",
    "sg:postcode":"G0X 3G0",
    "sg:province":"QC",
    "sg:tags":[
        "handicapped"
    ],
    "wof:name":"Corporation DE Transport",
    "wof:placetype":"venue"
},
  "geometry": {"coordinates":[-72.5065,46.814606],"type":"Point"}
}