{
  "type": "Feature",
  "properties": {
    "iso:country":"CA",
    "sg:address":"710 Rte DE LA Mer",
    "sg:city":"Sainte-Flavie",
    "sg:classifiers":[
        {
            "category":"Restaurant",
            "type":"Food & Drink"
        }
    ],
    "sg:phone":"+1 418 775 7813",
    "sg:postcode":"G0J 2L0",
    "sg:province":"QC",
    "wof:name":"Centre Chouin'Art Le Pecheur",
    "wof:placetype":"venue"
},
  "geometry": {"coordinates":[-68.1854934692,48.6326332092],"type":"Point"}
}