{
  "type": "Feature",
  "properties": {
    "addr:full":"7103 42 Ave Camrose AB T4V 3V5",
    "addr:housenumber":"7103",
    "addr:postcode":"t4v 3v5",
    "addr:street":"42 Ave",
    "iso:country":"CA",
    "sg:address":"7103 42 Ave",
    "sg:city":"Camrose",
    "sg:classifiers":[
        {
            "category":"Retail",
            "subcategory":"Laundry & Dry Cleaning",
            "type":"Services"
        }
    ],
    "sg:phone":"+1 780 672 1515",
    "sg:postcode":"T4V 3V5",
    "sg:province":"AB",
    "sg:tags":[
        "cleaners",
        "rug",
        "carpet"
    ],
    "wof:name":"Mr Kleen Carpet & Upholstery",
    "wof:placetype":"venue"
},
  "geometry": {"coordinates":[-112.86389200000001,53.008942],"type":"Point"}
}