{
  "type": "Feature",
  "properties": {
    "iso:country":"CA",
    "sg:address":"161 Kenmount Rd",
    "sg:city":"St. John's",
    "sg:classifiers":[
        {
            "category":"Real Estate",
            "subcategory":"Real Estate Agent",
            "type":"Services"
        }
    ],
    "sg:phone":"+1 709 722 8993",
    "sg:postcode":"A1B 3P9",
    "sg:province":"NL",
    "wof:name":"Coldwell Banker Proco",
    "wof:placetype":"venue"
},
  "geometry": {"coordinates":[-52.7648429871,47.5556106567],"type":"Point"}
}