{
  "type": "Feature",
  "properties": {
    "addr:full":"1630 Danforth Ave Toronto ON M4C 1H6",
    "addr:housenumber":"1630",
    "addr:postcode":"m4c 1h6",
    "addr:street":"Danforth Ave",
    "iso:country":"CA",
    "sg:address":"1630 Danforth Ave",
    "sg:city":"Toronto",
    "sg:classifiers":[
        {
            "category":"Shopping",
            "subcategory":"Pharmacy",
            "type":"Retail Goods"
        }
    ],
    "sg:phone":"+1 416 461 2453",
    "sg:postcode":"M4C 1H6",
    "sg:province":"ON",
    "wof:name":"Shoppers Drug Mart",
    "wof:placetype":"venue"
},
  "geometry": {"coordinates":[-79.322388,43.68375],"type":"Point"}
}