{
  "type": "Feature",
  "properties": {
    "addr:full":"115 Ainslie St N Cambridge ON N1R 3P2",
    "addr:housenumber":"115",
    "addr:postcode":"n1r 3p2",
    "addr:street":"Ainslie St N",
    "iso:country":"CA",
    "sg:address":"115 Ainslie St N",
    "sg:city":"Cambridge",
    "sg:classifiers":[
        {
            "category":"Real Estate",
            "subcategory":"Real Estate Operator",
            "type":"Services"
        }
    ],
    "sg:phone":"+1 519 621 0920",
    "sg:postcode":"N1R 3P2",
    "sg:province":"ON",
    "sg:tags":[
        "apartment"
    ],
    "wof:name":"Dorschell Developments Ltd",
    "wof:placetype":"venue"
},
  "geometry": {"coordinates":[-80.313866,43.362553],"type":"Point"}
}