{
  "type": "Feature",
  "properties": {
    "addr:full":"81 Pleasant Rd Guelph ON N1E 3Z5",
    "addr:housenumber":"81",
    "addr:postcode":"n1e 3z5",
    "addr:street":"Pleasant Rd",
    "iso:country":"CA",
    "sg:address":"81 Pleasant Rd",
    "sg:city":"Guelph",
    "sg:classifiers":[
        {
            "category":"Building & Trades",
            "subcategory":"Construction",
            "type":"Services"
        }
    ],
    "sg:phone":"+1 519 821 7142",
    "sg:postcode":"N1E 3Z5",
    "sg:province":"ON",
    "sg:tags":[
        "painter"
    ],
    "wof:name":"John Benvie Painting",
    "wof:placetype":"venue"
},
  "geometry": {"coordinates":[-80.253494,43.55912],"type":"Point"}
}