{
  "type": "Feature",
  "properties": {
    "iso:country":"CA",
    "sg:city":"Montreal",
    "sg:classifiers":[
        {
            "category":"Restaurant",
            "type":"Food & Drink"
        }
    ],
    "sg:phone":"+1 514 841 1992",
    "sg:postcode":"H2Y 2M4",
    "sg:province":"QC",
    "sg:tags":[
        "shop",
        "coffee"
    ],
    "wof:name":"Cafe Du Port 417",
    "wof:placetype":"venue"
},
  "geometry": {"coordinates":[-73.55670166020001,45.5015830994],"type":"Point"}
}