{
  "type": "Feature",
  "properties": {
    "iso:country":"CA",
    "sg:city":"Calgary",
    "sg:classifiers":[
        {
            "category":"Education",
            "subcategory":"School",
            "type":"Public Place"
        }
    ],
    "sg:phone":"+1 403 232 8551",
    "sg:postcode":"T2P 3N8",
    "sg:province":"AB",
    "wof:name":"Educere International College",
    "wof:placetype":"venue"
},
  "geometry": {"coordinates":[-114.081619,51.047165],"type":"Point"}
}