{
  "type": "Feature",
  "properties": {
    "addr:full":"1423 Bourcier Dr Orleans ON K1E 3K9",
    "addr:housenumber":"1423",
    "addr:postcode":"k1e 3k9",
    "addr:street":"Bourcier Dr",
    "iso:country":"CA",
    "sg:address":"1423 Bourcier Dr",
    "sg:city":"Orleans",
    "sg:classifiers":[
        {
            "category":"Home & Garden",
            "subcategory":"Household Appliances",
            "type":"Retail Goods"
        }
    ],
    "sg:phone":"+1 613 824 9950",
    "sg:postcode":"K1E 3K9",
    "sg:province":"ON",
    "wof:name":"Independent Appliance Svc",
    "wof:placetype":"venue"
},
  "geometry": {"coordinates":[-75.50825500000001,45.475143],"type":"Point"}
}