{
  "type": "Feature",
  "properties": {
    "iso:country":"CA",
    "sg:address":"2346 Ch Lucerne # A",
    "sg:city":"Mont-Royal",
    "sg:classifiers":[
        {
            "category":"Personal",
            "subcategory":"Shoe Repair & Shine",
            "type":"Services"
        }
    ],
    "sg:phone":"+1 514 344 8836",
    "sg:postcode":"H3R 2J8",
    "sg:province":"QC",
    "sg:tags":[
        "repairing",
        "boot"
    ],
    "wof:name":"Cordonnerie Vmr",
    "wof:placetype":"venue"
},
  "geometry": {"coordinates":[-73.66143035890001,45.5072555542],"type":"Point"}
}