{
  "type": "Feature",
  "properties": {
    "iso:country":"CA",
    "sg:address":"121 Rue Saint-Germain O",
    "sg:city":"Rimouski",
    "sg:classifiers":[
        {
            "category":"Restaurant",
            "type":"Food & Drink"
        }
    ],
    "sg:phone":"+1 418 725 5411",
    "sg:postcode":"G5L 4B6",
    "sg:province":"QC",
    "wof:name":"Cafe Des Halles Enr",
    "wof:placetype":"venue"
},
  "geometry": {"coordinates":[-68.522263,48.45335],"type":"Point"}
}