{
  "type": "Feature",
  "properties": {
    "addr:full":"2135 Rue Roussel Chicoutimi QC G7G 1W4",
    "addr:housenumber":"2135",
    "addr:postcode":"g7g 1w4",
    "addr:street":"Rue Roussel",
    "iso:country":"CA",
    "sg:address":"2135 Rue Roussel",
    "sg:city":"Chicoutimi",
    "sg:classifiers":[
        {
            "category":"Autos & Motor Vehicles",
            "subcategory":"Automobile Sales",
            "type":"Retail Goods"
        }
    ],
    "sg:phone":"+1 418 693 8230",
    "sg:postcode":"G7G 1W4",
    "sg:province":"QC",
    "sg:tags":[
        "car",
        "dealer"
    ],
    "wof:name":"Automobiles Fsd Enr",
    "wof:placetype":"venue"
},
  "geometry": {"coordinates":[-71.0637435913,48.4375839233],"type":"Point"}
}