{
  "type": "Feature",
  "properties": {
    "iso:country":"CA",
    "sg:address":"356 Queen St",
    "sg:city":"Fredericton",
    "sg:classifiers":[
        {
            "category":"Professional",
            "subcategory":"Lawyer & Legal Services",
            "type":"Services"
        }
    ],
    "sg:phone":"+1 506 451 1459",
    "sg:postcode":"E3B 1B2",
    "sg:province":"NB",
    "sg:tags":[
        "attorney"
    ],
    "wof:name":"Aide Juridique Du Nouveau",
    "wof:placetype":"venue"
},
  "geometry": {"coordinates":[-66.6441955566,45.9633216858],"type":"Point"}
}