{
  "type": "Feature",
  "properties": {
    "iso:country":"CA",
    "sg:address":"407 W 2nd St",
    "sg:city":"Revelstoke",
    "sg:classifiers":[
        {
            "category":"Personal",
            "subcategory":"Beauty Salon",
            "type":"Services"
        }
    ],
    "sg:phone":"+1 250 837 5964",
    "sg:postcode":"V0E 2S0",
    "sg:province":"BC",
    "wof:name":"Country Chair Hair Affairs",
    "wof:placetype":"venue"
},
  "geometry": {"coordinates":[-118.19913482699999,50.9998550415],"type":"Point"}
}