{
  "type": "Feature",
  "properties": {
    "addr:full":"RR 1 Lions Head ON N0H 1W0",
    "addr:postcode":"n0h 1w0",
    "addr:street":"Rr 1 Lions Head",
    "iso:country":"CA",
    "sg:address":"RR 1",
    "sg:city":"Lions Head",
    "sg:classifiers":[
        {
            "category":"Manufacturing",
            "subcategory":"Tools & Machinery",
            "type":"Manufacturing & Wholesale Goods"
        }
    ],
    "sg:phone":"+1 519 793 3352",
    "sg:postcode":"N0H 1W0",
    "sg:province":"ON",
    "sg:tags":[
        "machine",
        "shop"
    ],
    "wof:name":"Campbell's Welding & Machine",
    "wof:placetype":"venue"
},
  "geometry": {"coordinates":[-81.254204,44.98658],"type":"Point"}
}