{
  "type": "Feature",
  "properties": {
    "addr:full":"7004 Rue Hutchison # 2 Montreal QC H3N 1Y6",
    "addr:housenumber":"7004",
    "addr:postcode":"h3n 1y6",
    "addr:street":"Rue Hutchison # 2",
    "iso:country":"CA",
    "sg:address":"7004 Rue Hutchison # 2",
    "sg:city":"Montreal",
    "sg:classifiers":[
        {
            "category":"Social Services",
            "type":"Services"
        }
    ],
    "sg:phone":"+1 514 273 2700",
    "sg:postcode":"H3N 1Y6",
    "sg:province":"QC",
    "sg:tags":[
        "organization",
        "welfare"
    ],
    "wof:name":"Heberjeune DE Parc Extension",
    "wof:placetype":"venue"
},
  "geometry": {"coordinates":[-73.62016300000001,45.528912],"type":"Point"}
}