{
  "type": "Feature",
  "properties": {
    "addr:full":"250 Pleasant St Miramichi NB E1V 1Y5",
    "addr:housenumber":"250",
    "addr:postcode":"e1v 1y5",
    "addr:street":"Pleasant St",
    "iso:country":"CA",
    "sg:address":"250 Pleasant St",
    "sg:city":"Miramichi",
    "sg:classifiers":[
        {
            "category":"Health Services",
            "subcategory":"Doctor",
            "type":"Services"
        }
    ],
    "sg:phone":"+1 506 622 6562",
    "sg:postcode":"E1V 1Y5",
    "sg:province":"NB",
    "sg:tags":[
        "clinic"
    ],
    "wof:name":"Pleasant St After Hours Clinic",
    "wof:placetype":"venue"
},
  "geometry": {"coordinates":[-65.566925,46.999866],"type":"Point"}
}