{
  "type": "Feature",
  "properties": {
    "addr:full":"1260 Clarence Ave Winnipeg MB R3T 1T2",
    "addr:housenumber":"1260",
    "addr:postcode":"r3t 1t2",
    "addr:street":"Clarence Ave",
    "iso:country":"CA",
    "sg:address":"1260 Clarence Ave",
    "sg:city":"Winnipeg",
    "sg:classifiers":[
        {
            "category":"Manufacturing",
            "subcategory":"Tools & Machinery",
            "type":"Manufacturing & Wholesale Goods"
        }
    ],
    "sg:phone":"+1 204 284 6100",
    "sg:postcode":"R3T 1T2",
    "sg:province":"MB",
    "sg:tags":[
        "farm",
        "equipment"
    ],
    "wof:name":"Buhler Versatile Inc",
    "wof:placetype":"venue"
},
  "geometry": {"coordinates":[-97.16287199999999,49.832329],"type":"Point"}
}