{
  "type": "Feature",
  "properties": {
    "addr:full":"Stayner ON L0M 1S0",
    "addr:postcode":"l0m 1s0",
    "iso:country":"CA",
    "sg:city":"Stayner",
    "sg:classifiers":[
        {
            "category":"Manufacturing",
            "subcategory":"Pottery",
            "type":"Manufacturing & Wholesale Goods"
        }
    ],
    "sg:phone":"+1 705 428 0221",
    "sg:postcode":"L0M 1S0",
    "sg:province":"ON",
    "wof:name":"Miss Mollie's Country Crafts",
    "wof:placetype":"venue"
},
  "geometry": {"coordinates":[-80.07830800000001,44.422199],"type":"Point"}
}