{
  "type": "Feature",
  "properties": {
    "iso:country":"CA",
    "sg:city":"Victoria",
    "sg:classifiers":[
        {
            "category":"Health Services",
            "subcategory":"Doctor",
            "type":"Services"
        }
    ],
    "sg:phone":"+1 250 383 3015",
    "sg:postcode":"V8W 2E7",
    "sg:province":"BC",
    "sg:tags":[
        "dentist"
    ],
    "wof:name":"S Bruce Masson Inc",
    "wof:placetype":"venue"
},
  "geometry": {"coordinates":[-123.36502075200001,48.4255943298],"type":"Point"}
}