{
  "type": "Feature",
  "properties": {
    "addr:full":"2900 Kellys Rd Port Severn ON L0K 1S0",
    "addr:housenumber":"2900",
    "addr:postcode":"l0k 1s0",
    "addr:street":"Kellys Rd",
    "iso:country":"CA",
    "sg:address":"2900 Kellys Rd",
    "sg:city":"Port Severn",
    "sg:classifiers":[
        {
            "category":"Travel",
            "subcategory":"Hotels & Motels",
            "type":"Entertainment"
        }
    ],
    "sg:phone":"+1 705 538 2272",
    "sg:postcode":"L0K 1S0",
    "sg:province":"ON",
    "sg:tags":[
        "resort"
    ],
    "wof:name":"Rawley Lodge",
    "wof:placetype":"venue"
},
  "geometry": {"coordinates":[-79.71777299999999,44.806072],"type":"Point"}
}