{
  "type": "Feature",
  "properties": {
    "addr:full":"4 Parry Sound Dr Parry Sound ON P2A 2X2",
    "addr:housenumber":"4",
    "addr:postcode":"p2a 2x2",
    "addr:street":"Parry Sound Dr",
    "iso:country":"CA",
    "sg:address":"4 Parry Sound Dr",
    "sg:city":"Parry Sound",
    "sg:classifiers":[
        {
            "category":"Organizations",
            "subcategory":"Religious Organization",
            "type":"Services"
        }
    ],
    "sg:phone":"+1 705 746 5882",
    "sg:postcode":"P2A 2X2",
    "sg:province":"ON",
    "sg:tags":[
        "church"
    ],
    "wof:name":"Pentecostal Tabernacle",
    "wof:placetype":"venue"
},
  "geometry": {"coordinates":[-80.040154,45.361145],"type":"Point"}
}