{
  "type": "Feature",
  "properties": {
    "addr:full":"638 Broadway Ave Saskatoon SK S7N 1A9",
    "addr:housenumber":"638",
    "addr:postcode":"s7n 1a9",
    "addr:street":"Broadway Ave",
    "iso:country":"CA",
    "sg:address":"638 Broadway Ave",
    "sg:city":"Saskatoon",
    "sg:classifiers":[
        {
            "category":"Shopping",
            "subcategory":"Shoes",
            "type":"Retail Goods"
        }
    ],
    "sg:phone":"+1 306 652 4399",
    "sg:postcode":"S7N 1A9",
    "sg:province":"SK",
    "sg:tags":[
        "repairing",
        "boot",
        "shoe"
    ],
    "wof:name":"Broadway Shoe Repair Shop",
    "wof:placetype":"venue"
},
  "geometry": {"coordinates":[-106.65699768099999,52.1194000244],"type":"Point"}
}