{
  "type": "Feature",
  "properties": {
    "addr:full":"Ottawa ON K1S 5K4",
    "addr:postcode":"k1s 5k4",
    "iso:country":"CA",
    "sg:city":"Ottawa",
    "sg:classifiers":[
        {
            "category":"Professional",
            "subcategory":"Accounting & Tax Preparation",
            "type":"Services"
        }
    ],
    "sg:phone":"+1 613 567 6434",
    "sg:postcode":"K1S 5K4",
    "sg:province":"ON",
    "sg:tags":[
        "accountant",
        "bankruptcy",
        "trustee"
    ],
    "wof:name":"Surgeson Carson Assoc",
    "wof:placetype":"venue"
},
  "geometry": {"coordinates":[-75.687477,45.401878],"type":"Point"}
}