{
  "type": "Feature",
  "properties": {
    "addr:full":"1111 Creditstone Rd Concord ON L4K 4N7",
    "addr:housenumber":"1111",
    "addr:postcode":"l4k 4n7",
    "addr:street":"Creditstone Rd",
    "iso:country":"CA",
    "sg:address":"1111 Creditstone Rd",
    "sg:city":"Concord",
    "sg:classifiers":[
        {
            "category":"Building & Trades",
            "subcategory":"Construction",
            "type":"Services"
        }
    ],
    "sg:phone":"+1 705 725 9065",
    "sg:postcode":"L4K 4N7",
    "sg:province":"ON",
    "sg:tags":[
        "general",
        "contractor"
    ],
    "wof:name":"North Rock Group Ltd",
    "wof:placetype":"venue"
},
  "geometry": {"coordinates":[-79.5222244263,43.8162269592],"type":"Point"}
}