{
  "type": "Feature",
  "properties": {
    "addr:full":"1449 Powell St Vancouver BC V5L 1G8",
    "addr:housenumber":"1449",
    "addr:postcode":"v5l 1g8",
    "addr:street":"Powell St",
    "iso:country":"CA",
    "sg:address":"1449 Powell St",
    "sg:city":"Vancouver",
    "sg:classifiers":[
        {
            "category":"Manufacturing",
            "subcategory":"Toys & Sporting Goods",
            "type":"Manufacturing & Wholesale Goods"
        }
    ],
    "sg:phone":"+1 604 251 2453",
    "sg:postcode":"V5L 1G8",
    "sg:province":"BC",
    "sg:tags":[
        "athletic",
        "bicycle"
    ],
    "wof:name":"Giant Bicycle Canada Inc",
    "wof:placetype":"venue"
},
  "geometry": {"coordinates":[-123.07489,49.28339],"type":"Point"}
}