{
  "type": "Feature",
  "properties": {
    "addr:full":"3374 Av Des Fauvettes Charlesbourg QC G1G 4S1",
    "addr:housenumber":"3374",
    "addr:postcode":"g1g 4s1",
    "addr:street":"Av Des Fauvettes",
    "iso:country":"CA",
    "sg:address":"3374 Av Des Fauvettes",
    "sg:city":"Charlesbourg",
    "sg:classifiers":[
        {
            "category":"Arts & Performance",
            "subcategory":"Theater",
            "type":"Entertainment"
        }
    ],
    "sg:phone":"+1 418 626 0409",
    "sg:postcode":"G1G 4S1",
    "sg:province":"QC",
    "sg:tags":[
        "mobile",
        "sound",
        "system",
        "discotheque",
        "equipment"
    ],
    "wof:name":"Disco-Mobile Apocalypse",
    "wof:placetype":"venue"
},
  "geometry": {"coordinates":[-71.287735,46.875317],"type":"Point"}
}