{
  "type": "Feature",
  "properties": {
    "addr:full":"622 Kingsway Sudbury ON P3B 2E5",
    "addr:housenumber":"622",
    "addr:postcode":"p3b 2e5",
    "addr:street":"Kingsway",
    "iso:country":"CA",
    "sg:address":"622 Kingsway",
    "sg:city":"Sudbury",
    "sg:classifiers":[
        {
            "category":"Retail",
            "subcategory":"Auto Repair",
            "type":"Services"
        }
    ],
    "sg:phone":"+1 705 675 6339",
    "sg:postcode":"P3B 2E5",
    "sg:province":"ON",
    "sg:tags":[
        "repairing",
        "automobile",
        "welding"
    ],
    "wof:name":"Andy's Welding Shop",
    "wof:placetype":"venue"
},
  "geometry": {"coordinates":[-80.9754104614,46.496887207],"type":"Point"}
}