{
  "type": "Feature",
  "properties": {
    "addr:full":"1320 Boul Lionel-Boulet Varennes QC J3X 1P7",
    "addr:housenumber":"1320",
    "addr:postcode":"j3x 1p7",
    "addr:street":"Boul Lionel-Boulet",
    "iso:country":"CA",
    "sg:address":"1320 Boul Lionel-Boulet",
    "sg:city":"Varennes",
    "sg:classifiers":[
        {
            "category":"Professional",
            "subcategory":"Testing Lab",
            "type":"Services"
        }
    ],
    "sg:phone":"+1 450 652 0838",
    "sg:postcode":"J3X 1P7",
    "sg:province":"QC",
    "sg:tags":[
        "laboratory"
    ],
    "wof:name":"Air-Ins Inc",
    "wof:placetype":"venue"
},
  "geometry": {"coordinates":[-73.400673,45.639523],"type":"Point"}
}