{
  "type": "Feature",
  "properties": {
    "addr:full":"1696 Cadillac St Windsor ON N8Y 2V5",
    "addr:housenumber":"1696",
    "addr:postcode":"n8y 2v5",
    "addr:street":"Cadillac St",
    "iso:country":"CA",
    "sg:address":"1696 Cadillac St",
    "sg:city":"Windsor",
    "sg:classifiers":[
        {
            "category":"Organizations",
            "subcategory":"Religious Organization",
            "type":"Services"
        }
    ],
    "sg:phone":"+1 519 948 7450",
    "sg:postcode":"N8Y 2V5",
    "sg:province":"ON",
    "sg:tags":[
        "church"
    ],
    "wof:name":"First Romanian Baptist Church",
    "wof:placetype":"venue"
},
  "geometry": {"coordinates":[-82.990562,42.308563],"type":"Point"}
}