{
  "type": "Feature",
  "properties": {
    "addr:full":"Edmonton AB T5P 3X6",
    "addr:postcode":"t5p 3x6",
    "iso:country":"CA",
    "sg:city":"Edmonton",
    "sg:classifiers":[
        {
            "category":"Building & Trades",
            "subcategory":"Construction",
            "type":"Services"
        }
    ],
    "sg:phone":"+1 780 484 5811",
    "sg:postcode":"T5P 3X6",
    "sg:province":"AB",
    "sg:tags":[
        "contractor"
    ],
    "wof:name":"Skilite Construction Ltd",
    "wof:placetype":"venue"
},
  "geometry": {"coordinates":[-113.613297,53.551048],"type":"Point"}
}