{
  "type": "Feature",
  "properties": {
    "addr:full":"Toronto ON M5T 3B3",
    "addr:postcode":"m5t 3b3",
    "iso:country":"CA",
    "sg:city":"Toronto",
    "sg:classifiers":[
        {
            "category":"Personal",
            "subcategory":"Beauty Salon",
            "type":"Services"
        }
    ],
    "sg:phone":"+1 416 597 6633",
    "sg:postcode":"M5T 3B3",
    "sg:province":"ON",
    "wof:name":"Vince Cosmetics & Accessories",
    "wof:placetype":"venue"
},
  "geometry": {"coordinates":[-79.397575,43.650982],"type":"Point"}
}