{
  "type": "Feature",
  "properties": {
    "addr:full":"251 Mcmurchy Ave S Brampton ON L6Y 1Z4",
    "addr:housenumber":"251",
    "addr:postcode":"l6y 1z4",
    "addr:street":"Mcmurchy Ave S",
    "iso:country":"CA",
    "sg:address":"251 Mcmurchy Ave S",
    "sg:city":"Brampton",
    "sg:classifiers":[
        {
            "category":"Social Services",
            "subcategory":"Child Care",
            "type":"Services"
        }
    ],
    "sg:phone":"+1 905 451 3232",
    "sg:postcode":"L6Y 1Z4",
    "sg:province":"ON",
    "sg:tags":[
        "school"
    ],
    "wof:name":"Brampton Centennial Playschool",
    "wof:placetype":"venue"
},
  "geometry": {"coordinates":[-79.747505,43.667488],"type":"Point"}
}