{
  "type": "Feature",
  "properties": {
    "iso:country":"CA",
    "sg:address":"251 Mcmurchy Ave S",
    "sg:city":"Brampton",
    "sg:classifiers":[
        {
            "category":"Social Services",
            "subcategory":"Child Care",
            "type":"Services"
        }
    ],
    "sg:phone":"+1 905 451 3232",
    "sg:postcode":"L6Y 1Z4",
    "sg:province":"ON",
    "sg:tags":[
        "school"
    ],
    "wof:name":"Brampton Centennial Playschool",
    "wof:placetype":"venue"
},
  "geometry": {"coordinates":[-79.747505,43.667488],"type":"Point"}
}