{
  "type": "Feature",
  "properties": {
    "addr:full":"Scarborough ON M1J 2E4",
    "addr:postcode":"m1j 2e4",
    "iso:country":"CA",
    "sg:city":"Scarborough",
    "sg:classifiers":[
        {
            "category":"Restaurant",
            "type":"Food & Drink"
        }
    ],
    "sg:phone":"+1 416 431 4242",
    "sg:postcode":"M1J 2E4",
    "sg:province":"ON",
    "wof:name":"Roland's Dining & Take Out",
    "wof:placetype":"venue"
},
  "geometry": {"coordinates":[-79.238068,43.739082],"type":"Point"}
}