{
  "type": "Feature",
  "properties": {
    "addr:full":"958 Branion Dr Prince Albert SK S6V 2S5",
    "addr:housenumber":"958",
    "addr:postcode":"s6v 2s5",
    "addr:street":"Branion Dr",
    "iso:country":"CA",
    "sg:address":"958 Branion Dr",
    "sg:city":"Prince Albert",
    "sg:classifiers":[
        {
            "category":"Social Services",
            "subcategory":"Child Care",
            "type":"Services"
        }
    ],
    "sg:phone":"+1 306 922 6212",
    "sg:postcode":"S6V 2S5",
    "sg:province":"SK",
    "wof:name":"Montessori Preschool Daycare",
    "wof:placetype":"venue"
},
  "geometry": {"coordinates":[-105.72767639200001,53.189655304],"type":"Point"}
}