{
  "type": "Feature",
  "properties": {
    "addr:full":"77 Deschene Ave Hamilton ON L9A 3J8",
    "addr:housenumber":"77",
    "addr:postcode":"l9a 3j8",
    "addr:street":"Deschene Ave",
    "iso:country":"CA",
    "sg:address":"77 Deschene Ave",
    "sg:city":"Hamilton",
    "sg:classifiers":[
        {
            "category":"Building & Trades",
            "subcategory":"Construction",
            "type":"Services"
        }
    ],
    "sg:phone":"+1 905 575 3466",
    "sg:postcode":"L9A 3J8",
    "sg:province":"ON",
    "sg:tags":[
        "home",
        "improvement"
    ],
    "wof:name":"Built Rite Construction",
    "wof:placetype":"venue"
},
  "geometry": {"coordinates":[-79.876228,43.223766],"type":"Point"}
}