{
  "type": "Feature",
  "properties": {
    "addr:full":"150 Robson St #203 Vancouver BC V6B 2A7",
    "addr:housenumber":"150",
    "addr:postcode":"v6b 2a7",
    "addr:street":"Robson St # 203",
    "iso:country":"CA",
    "sg:address":"150 Robson St #203",
    "sg:city":"Vancouver",
    "sg:classifiers":[
        {
            "category":"Education",
            "subcategory":"School",
            "type":"Public Place"
        }
    ],
    "sg:phone":"+1 604 684 6023",
    "sg:postcode":"V6B 2A7",
    "sg:province":"BC",
    "wof:name":"Federation of Independent Schl",
    "wof:placetype":"venue"
},
  "geometry": {"coordinates":[-123.11460099999999,49.277798],"type":"Point"}
}