{
  "type": "Feature",
  "properties": {
    "addr:full":"3300 8 St SE Calgary AB T2G 5S7",
    "addr:housenumber":"3300 8",
    "addr:postcode":"t2g 5s7",
    "addr:street":"St Se",
    "iso:country":"CA",
    "sg:address":"3300 8 St SE",
    "sg:city":"Calgary",
    "sg:classifiers":[
        {
            "category":"Manufacturing",
            "subcategory":"Glass & Minerals",
            "type":"Manufacturing & Wholesale Goods"
        }
    ],
    "sg:phone":"+1 403 243 3393",
    "sg:postcode":"T2G 5S7",
    "sg:province":"AB",
    "sg:tags":[
        "granite",
        "monument"
    ],
    "wof:name":"Sunset Memorial & Stone Ltd",
    "wof:placetype":"venue"
},
  "geometry": {"coordinates":[-114.043891907,51.0240707397],"type":"Point"}
}