{
  "type": "Feature",
  "properties": {
    "addr:full":"Lloydminster AB T9V 0E8",
    "addr:postcode":"t9v 0e8",
    "iso:country":"CA",
    "sg:city":"Lloydminster",
    "sg:classifiers":[
        {
            "category":"Professional",
            "subcategory":"Lawyer & Legal Services",
            "type":"Services"
        }
    ],
    "sg:phone":"+1 780 875 2288",
    "sg:postcode":"T9V 0E8",
    "sg:province":"AB",
    "sg:tags":[
        "attorney"
    ],
    "wof:name":"Milen, Derek G",
    "wof:placetype":"venue"
},
  "geometry": {"coordinates":[-110.00579071,53.2805747986],"type":"Point"}
}