{
  "type": "Feature",
  "properties": {
    "addr:full":"Church Point NS B0W 1M0",
    "addr:postcode":"b0w 1m0",
    "iso:country":"CA",
    "sg:city":"Church Point",
    "sg:classifiers":[
        {
            "category":"Manufacturing",
            "subcategory":"Food",
            "type":"Manufacturing & Wholesale Goods"
        }
    ],
    "sg:phone":"+1 902 769 2172",
    "sg:postcode":"B0W 1M0",
    "sg:province":"NS",
    "sg:tags":[
        "product",
        "manufacturer"
    ],
    "wof:name":"Rapure Acadienne",
    "wof:placetype":"venue"
},
  "geometry": {"coordinates":[-66.1160736084,44.3369903564],"type":"Point"}
}