{
  "type": "Feature",
  "properties": {
    "addr:full":"Vancouver BC V6B 1P1",
    "addr:postcode":"v6b 1p1",
    "iso:country":"CA",
    "sg:city":"Vancouver",
    "sg:classifiers":[
        {
            "category":"Government",
            "subcategory":"Office",
            "type":"Public Place"
        }
    ],
    "sg:phone":"+1 604 681 1381",
    "sg:postcode":"V6B 1P1",
    "sg:province":"BC",
    "sg:tags":[
        "federal",
        "affairs"
    ],
    "wof:name":"Consulate of Greece",
    "wof:placetype":"venue"
},
  "geometry": {"coordinates":[-123.113739,49.285091],"type":"Point"}
}