{
  "type": "Feature",
  "properties": {
    "iso:country":"CA",
    "sg:address":"4936 50th Ave",
    "sg:city":"Breton",
    "sg:classifiers":[
        {
            "category":"Home & Garden",
            "subcategory":"Hardware",
            "type":"Retail Goods"
        }
    ],
    "sg:phone":"+1 780 696 3557",
    "sg:postcode":"T0C 0P0",
    "sg:province":"AB",
    "wof:name":"True Value Hardware",
    "wof:placetype":"venue"
},
  "geometry": {"coordinates":[-114.47233581499999,53.1100959778],"type":"Point"}
}