{
  "type": "Feature",
  "properties": {
    "addr:full":"43 Roydon Pl Nepean ON K2E 1A3",
    "addr:housenumber":"43",
    "addr:postcode":"k2e 1a3",
    "addr:street":"Roydon Pl",
    "iso:country":"CA",
    "sg:address":"43 Roydon Pl",
    "sg:city":"Nepean",
    "sg:classifiers":[
        {
            "category":"Autos & Motor Vehicles",
            "subcategory":"Motorcycle Sales",
            "type":"Retail Goods"
        }
    ],
    "sg:phone":"+1 613 225 2892",
    "sg:postcode":"K2E 1A3",
    "sg:province":"ON",
    "sg:tags":[
        "scooter"
    ],
    "wof:name":"Motor Sports World",
    "wof:placetype":"venue"
},
  "geometry": {"coordinates":[-75.722488,45.338963],"type":"Point"}
}