{
  "type": "Feature",
  "properties": {
    "addr:full":"Vancouver BC V6B 1H7",
    "addr:postcode":"v6b 1h7",
    "iso:country":"CA",
    "sg:city":"Vancouver",
    "sg:classifiers":[
        {
            "category":"Organizations",
            "subcategory":"Professional Association",
            "type":"Services"
        }
    ],
    "sg:phone":"+1 604 646 4677",
    "sg:postcode":"V6B 1H7",
    "sg:province":"BC",
    "wof:name":"Confederation of University",
    "wof:placetype":"venue"
},
  "geometry": {"coordinates":[-123.10958862299999,49.2825927734],"type":"Point"}
}