{
  "type": "Feature",
  "properties": {
    "addr:full":"400 University Ave W Windsor ON N9A 5P8",
    "addr:housenumber":"400",
    "addr:postcode":"n9a 5p8",
    "addr:street":"University Ave W",
    "iso:country":"CA",
    "sg:address":"400 University Ave W",
    "sg:city":"Windsor",
    "sg:classifiers":[
        {
            "category":"Food & Beverages",
            "subcategory":"Liquor & Beverages",
            "type":"Retail Goods"
        }
    ],
    "sg:phone":"+1 519 253 2221",
    "sg:postcode":"N9A 5P8",
    "sg:province":"ON",
    "sg:tags":[
        "store"
    ],
    "wof:name":"Liquor Control Board of Ont",
    "wof:placetype":"venue"
},
  "geometry": {"coordinates":[-83.04341100000001,42.316635],"type":"Point"}
}