{
  "type": "Feature",
  "properties": {
    "addr:full":"3725 Old Sambro Rd Sambro NS B3V 1G1",
    "addr:housenumber":"3725",
    "addr:postcode":"b3v 1g1",
    "addr:street":"Old Sambro Rd",
    "iso:country":"CA",
    "sg:address":"3725 Old Sambro Rd",
    "sg:city":"Sambro",
    "sg:classifiers":[
        {
            "category":"Education",
            "subcategory":"School",
            "type":"Public Place"
        }
    ],
    "sg:phone":"+1 902 868 2717",
    "sg:postcode":"B3V 1G1",
    "sg:province":"NS",
    "wof:name":"Sambro School",
    "wof:placetype":"venue"
},
  "geometry": {"coordinates":[-63.603481,44.474628],"type":"Point"}
}