{
  "type": "Feature",
  "properties": {
    "addr:full":"235 Dixon Rd Etobicoke ON M9P 2M5",
    "addr:housenumber":"235",
    "addr:postcode":"m9p 2m5",
    "addr:street":"Dixon Rd",
    "iso:country":"CA",
    "sg:address":"235 Dixon Rd",
    "sg:city":"Etobicoke",
    "sg:classifiers":[
        {
            "category":"Travel",
            "subcategory":"Travel Agent",
            "type":"Entertainment"
        }
    ],
    "sg:phone":"+1 416 241 4654",
    "sg:postcode":"M9P 2M5",
    "sg:province":"ON",
    "sg:tags":[
        "agency",
        "bureau"
    ],
    "wof:name":"Travel Expressions Ltd",
    "wof:placetype":"venue"
},
  "geometry": {"coordinates":[-79.54402899999999,43.697617],"type":"Point"}
}