{
  "type": "Feature",
  "properties": {
    "addr:full":"360 Colborne St Brantford ON N3S 3N3",
    "addr:housenumber":"360",
    "addr:postcode":"n3s 3n3",
    "addr:street":"Colborne St",
    "iso:country":"CA",
    "sg:address":"360 Colborne St",
    "sg:city":"Brantford",
    "sg:classifiers":[
        {
            "category":"Organizations",
            "subcategory":"Religious Organization",
            "type":"Services"
        }
    ],
    "sg:phone":"+1 519 753 1931",
    "sg:postcode":"N3S 3N3",
    "sg:province":"ON",
    "sg:tags":[
        "church"
    ],
    "wof:name":"Heritage United Church",
    "wof:placetype":"venue"
},
  "geometry": {"coordinates":[-80.25616455079999,43.139175415],"type":"Point"}
}