{
  "type": "Feature",
  "properties": {
    "addr:full":"2 Croham Rd York ON M6E 4X8",
    "addr:housenumber":"2",
    "addr:postcode":"m6e 4x8",
    "addr:street":"Croham Rd",
    "iso:country":"CA",
    "sg:address":"2 Croham Rd",
    "sg:city":"York",
    "sg:classifiers":[
        {
            "category":"Retail",
            "subcategory":"Repair Shop",
            "type":"Services"
        }
    ],
    "sg:phone":"+1 416 784 9555",
    "sg:postcode":"M6E 4X8",
    "sg:province":"ON",
    "sg:tags":[
        "upholsterer"
    ],
    "wof:name":"Lance Custom Upholstery",
    "wof:placetype":"venue"
},
  "geometry": {"coordinates":[-79.46412658689999,43.6925086975],"type":"Point"}
}