{
  "type": "Feature",
  "properties": {
    "addr:full":"69 Acton Blvd Acton ON L7J 2H4",
    "addr:housenumber":"69",
    "addr:postcode":"l7j 2h4",
    "addr:street":"Acton Blvd",
    "iso:country":"CA",
    "sg:address":"69 Acton Blvd",
    "sg:city":"Acton",
    "sg:classifiers":[
        {
            "category":"Recreation",
            "type":"Entertainment"
        }
    ],
    "sg:phone":"+1 519 853 3140",
    "sg:postcode":"L7J 2H4",
    "sg:province":"ON",
    "sg:tags":[
        "pool",
        "swimming"
    ],
    "wof:name":"Acton Lions Club Swimming Pool",
    "wof:placetype":"venue"
},
  "geometry": {"coordinates":[-80.0322113037,43.6377105713],"type":"Point"}
}