{
  "type": "Feature",
  "properties": {
    "addr:full":"20026 Fraser Hwy Langley BC V3A 4E5",
    "addr:housenumber":"20026",
    "addr:postcode":"v3a 4e5",
    "addr:street":"Fraser Hwy",
    "iso:country":"CA",
    "sg:address":"20026 Fraser Hwy",
    "sg:city":"Langley",
    "sg:classifiers":[
        {
            "category":"Retail",
            "subcategory":"Auto Rental",
            "type":"Services"
        }
    ],
    "sg:phone":"+1 604 532 8828",
    "sg:postcode":"V3A 4E5",
    "sg:province":"BC",
    "sg:tags":[
        "renting",
        "automobile"
    ],
    "wof:name":"Canadian Car & Truck Rental",
    "wof:placetype":"venue"
},
  "geometry": {"coordinates":[-122.667778015,49.1082382202],"type":"Point"}
}