{
  "type": "Feature",
  "properties": {
    "addr:full":"269 Main St Parrsboro NS B0M 1S0",
    "addr:housenumber":"269",
    "addr:postcode":"b0m 1s0",
    "addr:street":"Main St",
    "iso:country":"CA",
    "sg:address":"269 Main St",
    "sg:city":"Parrsboro",
    "sg:classifiers":[
        {
            "category":"Home & Garden",
            "subcategory":"Hardware",
            "type":"Retail Goods"
        }
    ],
    "sg:phone":"+1 902 254 3232",
    "sg:postcode":"B0M 1S0",
    "sg:province":"NS",
    "wof:name":"Parrsboro Hardware Ltd",
    "wof:placetype":"venue"
},
  "geometry": {"coordinates":[-64.32634,45.404499],"type":"Point"}
}