{
  "type": "Feature",
  "properties": {
    "iso:country":"CA",
    "sg:address":"1420 Grosvenor St",
    "sg:city":"Oakville",
    "sg:classifiers":[
        {
            "category":"Education",
            "subcategory":"School",
            "type":"Public Place"
        }
    ],
    "sg:phone":"+1 905 845 6987",
    "sg:postcode":"L6H 2X8",
    "sg:province":"ON",
    "wof:name":"Holy Family School",
    "wof:placetype":"venue"
},
  "geometry": {"coordinates":[-79.68677520750001,43.4817771912],"type":"Point"}
}