{
  "type": "Feature",
  "properties": {
    "addr:full":"2440 York Ave Armstrong BC V0E 1B1",
    "addr:housenumber":"2440",
    "addr:postcode":"v0e 1b1",
    "addr:street":"York Ave",
    "iso:country":"CA",
    "sg:address":"2440 York Ave",
    "sg:city":"Armstrong",
    "sg:classifiers":[
        {
            "category":"Sports & Exercise",
            "subcategory":"Golf",
            "type":"Entertainment"
        }
    ],
    "sg:phone":"+1 250 546 9700",
    "sg:postcode":"V0E 1B1",
    "sg:province":"BC",
    "sg:tags":[
        "course"
    ],
    "wof:name":"Royal York Golf Course-Rv Park",
    "wof:placetype":"venue"
},
  "geometry": {"coordinates":[-119.190582275,50.4343070984],"type":"Point"}
}