{
  "type": "Feature",
  "properties": {
    "addr:full":"621 Rue DE L'Eglise Saint-Ignace-DE-Loyola QC J0K 2P0",
    "addr:housenumber":"621",
    "addr:postcode":"j0k 2p0",
    "addr:street":"Rue De L'Eglise",
    "iso:country":"CA",
    "sg:address":"621 Rue DE L'Eglise",
    "sg:city":"Saint-Ignace-DE-Loyola",
    "sg:classifiers":[
        {
            "category":"Education",
            "subcategory":"Library",
            "type":"Public Place"
        }
    ],
    "sg:phone":"+1 450 836 1831",
    "sg:postcode":"J0K 2P0",
    "sg:province":"QC",
    "wof:name":"St-Ignace-Loyola Bibliotheque",
    "wof:placetype":"venue"
},
  "geometry": {"coordinates":[-73.126846,46.059792],"type":"Point"}
}