{
  "type": "Feature",
  "properties": {
    "addr:full":"33 Rte Du Fleuve O Sainte-Luce QC G0K 1P0",
    "addr:housenumber":"33",
    "addr:postcode":"g0k 1p0",
    "addr:street":"Rte Du Fleuve O",
    "iso:country":"CA",
    "sg:address":"33 Rte Du Fleuve O",
    "sg:city":"Sainte-Luce",
    "sg:classifiers":[
        {
            "category":"Shopping",
            "subcategory":"Clothing, Apparel, & Fashions",
            "type":"Retail Goods"
        }
    ],
    "sg:phone":"+1 418 739 3585",
    "sg:postcode":"G0K 1P0",
    "sg:province":"QC",
    "sg:tags":[
        "shop",
        "boutique",
        "gift"
    ],
    "wof:name":"Boutiqued Normade",
    "wof:placetype":"venue"
},
  "geometry": {"coordinates":[-68.36325836180001,48.5460700989],"type":"Point"}
}