{
  "type": "Feature",
  "properties": {
    "iso:country":"CA",
    "sg:city":"Calgary",
    "sg:classifiers":[
        {
            "category":"Health Services",
            "subcategory":"Doctor",
            "type":"Services"
        }
    ],
    "sg:phone":"+1 403 221 4364",
    "sg:postcode":"T2P 3C5",
    "sg:province":"AB",
    "sg:tags":[
        "physician",
        "surgeon"
    ],
    "wof:name":"Murphy, V J MD",
    "wof:placetype":"venue"
},
  "geometry": {"coordinates":[-114.070808411,51.0446777344],"type":"Point"}
}