{
  "type": "Feature",
  "properties": {
    "addr:full":"922 King St W Toronto ON M5V 1P5",
    "addr:housenumber":"922",
    "addr:postcode":"m5v 1p5",
    "addr:street":"King St W",
    "iso:country":"CA",
    "sg:address":"922 King St W",
    "sg:city":"Toronto",
    "sg:classifiers":[
        {
            "category":"Food & Beverages",
            "subcategory":"Groceries & Convenience Stores",
            "type":"Retail Goods"
        }
    ],
    "sg:phone":"+1 416 504 6278",
    "sg:postcode":"M5V 1P5",
    "sg:province":"ON",
    "sg:tags":[
        "grocer"
    ],
    "wof:name":"Sweet Mini Mart",
    "wof:placetype":"venue"
},
  "geometry": {"coordinates":[-79.410904,43.642338],"type":"Point"}
}