{
  "type": "Feature",
  "properties": {
    "addr:full":"11 Mount Hope Ave Dartmouth NS B2Y 4S1",
    "addr:housenumber":"11",
    "addr:postcode":"b2y 4s1",
    "addr:street":"Mount Hope Ave",
    "iso:country":"CA",
    "sg:address":"11 Mount Hope Ave",
    "sg:city":"Dartmouth",
    "sg:classifiers":[
        {
            "category":"Manufacturing",
            "subcategory":"Furniture",
            "type":"Manufacturing & Wholesale Goods"
        }
    ],
    "sg:phone":"+1 902 461 1010",
    "sg:postcode":"B2Y 4S1",
    "sg:province":"NS",
    "sg:tags":[
        "food",
        "equipment",
        "processing"
    ],
    "wof:name":"Advantage Food Equipment",
    "wof:placetype":"venue"
},
  "geometry": {"coordinates":[-63.545536,44.654236],"type":"Point"}
}