{
  "type": "Feature",
  "properties": {
    "addr:full":"36 Walcot St Little Current ON P0P 1K0",
    "addr:housenumber":"36",
    "addr:postcode":"p0p 1k0",
    "addr:street":"Walcot St",
    "iso:country":"CA",
    "sg:address":"36 Walcot St",
    "sg:city":"Little Current",
    "sg:classifiers":[
        {
            "category":"Bus Charters",
            "type":"Transportation"
        }
    ],
    "sg:phone":"+1 705 368 0262",
    "sg:postcode":"P0P 1K0",
    "sg:province":"ON",
    "sg:tags":[
        "rental"
    ],
    "wof:name":"A J Bus Lines",
    "wof:placetype":"venue"
},
  "geometry": {"coordinates":[-81.9230957031,45.9775123596],"type":"Point"}
}