{
  "type": "Feature",
  "properties": {
    "addr:full":"800 Rue Rachel E Montreal QC H2J 2H6",
    "addr:housenumber":"800",
    "addr:postcode":"h2j 2h6",
    "addr:street":"Rue Rachel E",
    "iso:country":"CA",
    "sg:address":"800 Rue Rachel E",
    "sg:city":"Montreal",
    "sg:classifiers":[
        {
            "category":"Bars & Pubs",
            "type":"Food & Drink"
        }
    ],
    "sg:phone":"+1 514 522 0113",
    "sg:postcode":"H2J 2H6",
    "sg:province":"QC",
    "wof:name":"Taverne Boudrias",
    "wof:placetype":"venue"
},
  "geometry": {"coordinates":[-73.576447,45.523567],"type":"Point"}
}