{
  "type": "Feature",
  "properties": {
    "addr:full":"125 Sparling Crt Oakville ON L6K 2J8",
    "addr:housenumber":"125",
    "addr:postcode":"l6k 2j8",
    "addr:street":"Sparling Crt",
    "iso:country":"CA",
    "sg:address":"125 Sparling Crt",
    "sg:city":"Oakville",
    "sg:classifiers":[
        {
            "category":"Building & Trades",
            "subcategory":"Construction",
            "type":"Services"
        }
    ],
    "sg:phone":"+1 905 842 0219",
    "sg:postcode":"L6K 2J8",
    "sg:province":"ON",
    "sg:tags":[
        "tile",
        "dealer"
    ],
    "wof:name":"Tile Man",
    "wof:placetype":"venue"
},
  "geometry": {"coordinates":[-79.689041,43.428612],"type":"Point"}
}