{
  "type": "Feature",
  "properties": {
    "iso:country":"CA",
    "sg:address":"13655 Sixth Line",
    "sg:city":"Limehouse",
    "sg:classifiers":[
        {
            "category":"Wholesale",
            "subcategory":"Machinery & Supplies",
            "type":"Manufacturing & Wholesale Goods"
        }
    ],
    "sg:phone":"+1 905 873 6008",
    "sg:postcode":"L0P 1H0",
    "sg:province":"ON",
    "sg:tags":[
        "equipment",
        "mining"
    ],
    "wof:name":"Global Equipment & Supplies",
    "wof:placetype":"venue"
},
  "geometry": {"coordinates":[-79.978951,43.638409],"type":"Point"}
}