{
  "type": "Feature",
  "properties": {
    "addr:full":"101 Parent St Plantagenet ON K0B 1L0",
    "addr:housenumber":"101",
    "addr:postcode":"k0b 1l0",
    "addr:street":"Parent St",
    "iso:country":"CA",
    "sg:address":"101 Parent St",
    "sg:city":"Plantagenet",
    "sg:classifiers":[
        {
            "category":"Health Services",
            "subcategory":"Nursing And Care Facility",
            "type":"Services"
        }
    ],
    "sg:phone":"+1 613 673 4835",
    "sg:postcode":"K0B 1L0",
    "sg:province":"ON",
    "sg:tags":[
        "home",
        "convalescent"
    ],
    "wof:name":"Pinecrest Nursing Home",
    "wof:placetype":"venue"
},
  "geometry": {"coordinates":[-74.998558,45.54245],"type":"Point"}
}