{
  "type": "Feature",
  "properties": {
    "addr:full":"9 Redpath Row Montreal QC H3G 1E6",
    "addr:housenumber":"9",
    "addr:postcode":"h3g 1e6",
    "addr:street":"Redpath Row",
    "iso:country":"CA",
    "sg:address":"9 Redpath Row",
    "sg:city":"Montreal",
    "sg:classifiers":[
        {
            "category":"Professional",
            "subcategory":"Business Services",
            "type":"Services"
        }
    ],
    "sg:phone":"+1 514 933 6677",
    "sg:postcode":"H3G 1E6",
    "sg:province":"QC",
    "wof:name":"Elvinco International Ltd",
    "wof:placetype":"venue"
},
  "geometry": {"coordinates":[-73.58181762700001,45.4982147217],"type":"Point"}
}