{
  "type": "Feature",
  "properties": {
    "addr:full":"418 Rue Martine Saint-Jerome QC J7Z 6V9",
    "addr:housenumber":"418",
    "addr:postcode":"j7z 6v9",
    "addr:street":"Rue Martine Saint-Jerome",
    "iso:country":"CA",
    "sg:address":"418 Rue Martine",
    "sg:city":"Saint-Jerome",
    "sg:classifiers":[
        {
            "category":"Home & Garden",
            "subcategory":"Household Appliances",
            "type":"Retail Goods"
        }
    ],
    "sg:phone":"+1 450 432 1232",
    "sg:postcode":"J7Z 6V9",
    "sg:province":"QC",
    "wof:name":"Services Du Nord Enr",
    "wof:placetype":"venue"
},
  "geometry": {"coordinates":[-73.984047,45.78091],"type":"Point"}
}