{
  "type": "Feature",
  "properties": {
    "addr:full":"3845 Rue Saint-Dominique Montreal QC H2W 2A2",
    "addr:housenumber":"3845",
    "addr:postcode":"h2w 2a2",
    "addr:street":"Rue Saint-Dominique",
    "iso:country":"CA",
    "sg:address":"3845 Rue Saint-Dominique",
    "sg:city":"Montreal",
    "sg:classifiers":[
        {
            "category":"Real Estate",
            "subcategory":"Real Estate Operator",
            "type":"Services"
        }
    ],
    "sg:phone":"+1 514 287 9511",
    "sg:postcode":"H2W 2A2",
    "sg:province":"QC",
    "sg:tags":[
        "boarding",
        "house"
    ],
    "wof:name":"Ma Chambre Inc",
    "wof:placetype":"venue"
},
  "geometry": {"coordinates":[-73.575974,45.51627],"type":"Point"}
}