{
  "type": "Feature",
  "properties": {
    "addr:full":"7360 Lombard Rd Richmond BC V7C 3N1",
    "addr:housenumber":"7360",
    "addr:postcode":"bc v7c 3n1",
    "addr:street":"Lombard Rd",
    "iso:country":"CA",
    "sg:address":"7360 Lombard Rd",
    "sg:city":"Richmond",
    "sg:classifiers":[
        {
            "category":"Education",
            "subcategory":"School",
            "type":"Public Place"
        }
    ],
    "sg:phone":"+1 604 668 6470",
    "sg:postcode":"V7C 3N1",
    "sg:province":"BC",
    "wof:name":"Donald E Mc Kay Elementary",
    "wof:placetype":"venue"
},
  "geometry": {"coordinates":[-123.16680100000001,49.158714],"type":"Point"}
}