{
  "type": "Feature",
  "properties": {
    "iso:country":"CA",
    "sg:address":"7360 Lombard Rd",
    "sg:city":"Richmond",
    "sg:classifiers":[
        {
            "category":"Education",
            "subcategory":"School",
            "type":"Public Place"
        }
    ],
    "sg:phone":"+1 604 668 6470",
    "sg:postcode":"V7C 3N1",
    "sg:province":"BC",
    "wof:name":"Donald E Mc Kay Elementary",
    "wof:placetype":"venue"
},
  "geometry": {"coordinates":[-123.16680100000001,49.158714],"type":"Point"}
}