{
  "type": "Feature",
  "properties": {
    "addr:full":"361 Main St N Moose Jaw SK S6H 0W2",
    "addr:housenumber":"361",
    "addr:postcode":"s6h 0w2",
    "addr:street":"Main St N",
    "iso:country":"CA",
    "sg:address":"361 Main St N",
    "sg:city":"Moose Jaw",
    "sg:classifiers":[
        {
            "category":"Banks & Credit Unions",
            "subcategory":"Investment Brokerage",
            "type":"Services"
        }
    ],
    "sg:phone":"+1 306 692 8175",
    "sg:postcode":"S6H 0W2",
    "sg:province":"SK",
    "wof:name":"Edward Jones",
    "wof:placetype":"venue"
},
  "geometry": {"coordinates":[-105.534386,50.393112],"type":"Point"}
}