{
  "type": "Feature",
  "properties": {
    "addr:full":"3399 4th Ave W Vancouver BC V6R 1N6",
    "addr:housenumber":"3399",
    "addr:postcode":"v6r 1n6",
    "addr:street":"4Th Ave W",
    "iso:country":"CA",
    "sg:address":"3399 4th Ave W",
    "sg:city":"Vancouver",
    "sg:classifiers":[
        {
            "category":"Real Estate",
            "subcategory":"Real Estate Agent",
            "type":"Services"
        }
    ],
    "sg:phone":"+1 604 733 8722",
    "sg:postcode":"V6R 1N6",
    "sg:province":"BC",
    "sg:tags":[
        "management"
    ],
    "wof:name":"Balfour Properties Ltd",
    "wof:placetype":"venue"
},
  "geometry": {"coordinates":[-123.179382324,49.2686195374],"type":"Point"}
}