{
  "type": "Feature",
  "properties": {
    "addr:full":"4906 46A St Barrhead AB T7N 1H6",
    "addr:housenumber":"4906",
    "addr:postcode":"t7n 1h6",
    "addr:street":"46A St",
    "iso:country":"CA",
    "sg:address":"4906 46A St",
    "sg:city":"Barrhead",
    "sg:classifiers":[
        {
            "category":"Shopping",
            "subcategory":"Bicycles & Sporting Goods",
            "type":"Retail Goods"
        }
    ],
    "sg:phone":"+1 780 674 3638",
    "sg:postcode":"T7N 1H6",
    "sg:province":"AB",
    "wof:name":"Kenney Golf Pro Shop",
    "wof:placetype":"venue"
},
  "geometry": {"coordinates":[-114.395866,54.116447],"type":"Point"}
}