{
  "type": "Feature",
  "properties": {
    "addr:full":"Burnaby BC V3J 1M2",
    "addr:postcode":"v3j 1m2",
    "iso:country":"CA",
    "sg:city":"Burnaby",
    "sg:classifiers":[
        {
            "category":"Professional",
            "type":"Services"
        }
    ],
    "sg:phone":"+1 604 421 0015",
    "sg:postcode":"V3J 1M2",
    "sg:province":"BC",
    "sg:tags":[
        "shop",
        "retail",
        "establishment"
    ],
    "wof:name":"Dollars & Sense Blvd",
    "wof:placetype":"venue"
},
  "geometry": {"coordinates":[-122.898277283,49.253326416],"type":"Point"}
}