{
  "type": "Feature",
  "properties": {
    "addr:full":"Smiths Falls ON K7A 2B2",
    "addr:postcode":"k7a 2b2",
    "iso:country":"CA",
    "sg:city":"Smiths Falls",
    "sg:classifiers":[
        {
            "category":"Banks & Credit Unions",
            "subcategory":"Investment Brokerage",
            "type":"Services"
        }
    ],
    "sg:phone":"+1 613 283 9195",
    "sg:postcode":"K7A 2B2",
    "sg:province":"ON",
    "sg:tags":[
        "consultant",
        "planning",
        "financial"
    ],
    "wof:name":"Linden Duncalfe Financial Plng",
    "wof:placetype":"venue"
},
  "geometry": {"coordinates":[-76.021034,44.900238],"type":"Point"}
}