{
  "type": "Feature",
  "properties": {
    "addr:full":"1645 Boul Trudel E Saint-Boniface-DE-Shawinigan QC G0X 2L0",
    "addr:housenumber":"1645",
    "addr:postcode":"g0x 2l0",
    "addr:street":"Boul Trudel E Saint-Boniface-De-Shawinigan",
    "iso:country":"CA",
    "sg:address":"1645 Boul Trudel E",
    "sg:city":"Saint-Boniface-DE-Shawinigan",
    "sg:classifiers":[
        {
            "category":"Building & Trades",
            "subcategory":"Construction",
            "type":"Services"
        }
    ],
    "sg:phone":"+1 819 535 2647",
    "sg:postcode":"G0X 2L0",
    "sg:province":"QC",
    "sg:tags":[
        "excavating",
        "contractor"
    ],
    "wof:name":"Yvan Flageol Excavation",
    "wof:placetype":"venue"
},
  "geometry": {"coordinates":[-72.810799,46.523502],"type":"Point"}
}