{
  "type": "Feature",
  "properties": {
    "addr:full":"Toronto ON M4L 1H1",
    "addr:postcode":"m4l 1h1",
    "iso:country":"CA",
    "sg:city":"Toronto",
    "sg:classifiers":[
        {
            "category":"Professional",
            "subcategory":"Computer Services",
            "type":"Services"
        }
    ],
    "sg:phone":"+1 416 482 2854",
    "sg:postcode":"M4L 1H1",
    "sg:province":"ON",
    "wof:name":"Dexagon Inc",
    "wof:placetype":"venue"
},
  "geometry": {"coordinates":[-79.307495,43.668518],"type":"Point"}
}