{
  "type": "Feature",
  "properties": {
    "iso:country":"CA",
    "sg:address":"71 Strada Dr",
    "sg:city":"Woodbridge",
    "sg:classifiers":[
        {
            "category":"Building & Trades",
            "subcategory":"Construction",
            "type":"Services"
        }
    ],
    "sg:phone":"+1 905 850 3158",
    "sg:postcode":"L4L 5V9",
    "sg:province":"ON",
    "sg:tags":[
        "carpenter"
    ],
    "wof:name":"P S Carpentry CO",
    "wof:placetype":"venue"
},
  "geometry": {"coordinates":[-79.569489,43.780502],"type":"Point"}
}