{
  "type": "Feature",
  "properties": {
    "addr:full":"1060 Boul Ducharme LA Tuque QC G9X 3C4",
    "addr:housenumber":"1060",
    "addr:postcode":"g9x 3c4",
    "addr:street":"Boul Ducharme",
    "iso:country":"CA",
    "sg:address":"1060 Boul Ducharme",
    "sg:city":"LA Tuque",
    "sg:classifiers":[
        {
            "category":"Government",
            "subcategory":"Office",
            "type":"Public Place"
        }
    ],
    "sg:phone":"+1 819 523 9522",
    "sg:postcode":"G9X 3C4",
    "sg:province":"QC",
    "sg:tags":[
        "village"
    ],
    "wof:name":"LA Tuque Securite Publique",
    "wof:placetype":"venue"
},
  "geometry": {"coordinates":[-72.784866333,47.4233932495],"type":"Point"}
}