{
  "type": "Feature",
  "properties": {
    "addr:full":"3500 Boul Du Souvenir Laval QC H7V 1X2",
    "addr:housenumber":"3500",
    "addr:postcode":"h7v 1x2",
    "addr:street":"Boul Du Souvenir",
    "iso:country":"CA",
    "sg:address":"3500 Boul Du Souvenir",
    "sg:city":"Laval",
    "sg:classifiers":[
        {
            "category":"Recreation",
            "type":"Entertainment"
        }
    ],
    "sg:phone":"+1 514 333 1000",
    "sg:postcode":"H7V 1X2",
    "sg:province":"QC",
    "sg:tags":[
        "hall",
        "auditorium"
    ],
    "wof:name":"Chateau Royal Salles Recept",
    "wof:placetype":"venue"
},
  "geometry": {"coordinates":[-73.74783325200001,45.5508460999],"type":"Point"}
}