{
  "type": "Feature",
  "properties": {
    "addr:full":"153 Rue Laviolette Trois-Rivieres QC G9A 1T7",
    "addr:housenumber":"153",
    "addr:postcode":"g9a 1t7",
    "addr:street":"Rue Laviolette",
    "iso:country":"CA",
    "sg:address":"153 Rue Laviolette",
    "sg:city":"Trois-Rivieres",
    "sg:classifiers":[
        {
            "category":"Professional",
            "subcategory":"Business Services",
            "type":"Services"
        }
    ],
    "sg:phone":"+1 819 375 7733",
    "sg:postcode":"G9A 1T7",
    "sg:province":"QC",
    "sg:tags":[
        "notary"
    ],
    "wof:name":"Martin Martin & Poisson",
    "wof:placetype":"venue"
},
  "geometry": {"coordinates":[-72.5397644043,46.3437728882],"type":"Point"}
}