{
  "type": "Feature",
  "properties": {
    "iso:country":"CA",
    "sg:address":"675 Main St",
    "sg:city":"Lillooet",
    "sg:classifiers":[
        {
            "category":"Food & Beverages",
            "subcategory":"Groceries & Convenience Stores",
            "type":"Retail Goods"
        }
    ],
    "sg:phone":"+1 250 256 7114",
    "sg:postcode":"V0K 1V0",
    "sg:province":"BC",
    "sg:tags":[
        "grocer"
    ],
    "wof:name":"Lillooet Foods",
    "wof:placetype":"venue"
},
  "geometry": {"coordinates":[-121.93284606900001,50.6827888489],"type":"Point"}
}