{
  "type": "Feature",
  "properties": {
    "addr:full":"473 Rue Cyr N Thetford Mines QC G6G 4E6",
    "addr:housenumber":"473",
    "addr:postcode":"g6g 4e6",
    "addr:street":"Rue Cyr N",
    "iso:country":"CA",
    "sg:address":"473 Rue Cyr N",
    "sg:city":"Thetford Mines",
    "sg:classifiers":[
        {
            "category":"Retail",
            "subcategory":"Auto Repair",
            "type":"Services"
        }
    ],
    "sg:phone":"+1 418 335 7227",
    "sg:postcode":"G6G 4E6",
    "sg:province":"QC",
    "sg:tags":[
        "repairing",
        "automobile"
    ],
    "wof:name":"Garage Daniel Bourque",
    "wof:placetype":"venue"
},
  "geometry": {"coordinates":[-71.302834,46.0984],"type":"Point"}
}