{
  "type": "Feature",
  "properties": {
    "addr:full":"140 First St Tofino BC V0R 2Z0",
    "addr:housenumber":"140",
    "addr:postcode":"v0r 2z0",
    "addr:street":"First St",
    "iso:country":"CA",
    "sg:address":"140 First St",
    "sg:city":"Tofino",
    "sg:classifiers":[
        {
            "category":"Food & Beverages",
            "subcategory":"Groceries & Convenience Stores",
            "type":"Retail Goods"
        }
    ],
    "sg:phone":"+1 250 725 3226",
    "sg:postcode":"V0R 2Z0",
    "sg:province":"BC",
    "sg:tags":[
        "grocer"
    ],
    "wof:name":"Tofino Consumers CO-OP",
    "wof:placetype":"venue"
},
  "geometry": {"coordinates":[-125.908508301,49.1528434753],"type":"Point"}
}