{
  "type": "Feature",
  "properties": {
    "addr:full":"530 Topping Lane London ON N6J 3M7",
    "addr:housenumber":"530",
    "addr:postcode":"n6j 3m7",
    "addr:street":"Topping Lane",
    "iso:country":"CA",
    "sg:address":"530 Topping Lane",
    "sg:city":"London",
    "sg:classifiers":[
        {
            "category":"Organizations",
            "subcategory":"Religious Organization",
            "type":"Services"
        }
    ],
    "sg:phone":"+1 519 473 5257",
    "sg:postcode":"N6J 3M7",
    "sg:province":"ON",
    "sg:tags":[
        "church"
    ],
    "wof:name":"Korean Christian Church",
    "wof:placetype":"venue"
},
  "geometry": {"coordinates":[-81.2834701538,42.9577293396],"type":"Point"}
}