{
  "type": "Feature",
  "properties": {
    "addr:full":"237 Manitoba Ave Selkirk MB R1A 0Y4",
    "addr:housenumber":"237",
    "addr:postcode":"r1a 0y4",
    "addr:street":"Manitoba Ave",
    "iso:country":"CA",
    "sg:address":"237 Manitoba Ave",
    "sg:city":"Selkirk",
    "sg:classifiers":[
        {
            "category":"Government",
            "subcategory":"Office",
            "type":"Public Place"
        }
    ],
    "sg:phone":"+1 204 785 6200",
    "sg:postcode":"R1A 0Y4",
    "sg:province":"MB",
    "wof:name":"Canada Human Resource Ctr",
    "wof:placetype":"venue"
},
  "geometry": {"coordinates":[-96.8704071045,50.1443557739],"type":"Point"}
}