{
  "type": "Feature",
  "properties": {
    "addr:full":"Petitcodiac NB E4Z 4L9",
    "addr:postcode":"e4z 4l9",
    "iso:country":"CA",
    "sg:city":"Petitcodiac",
    "sg:classifiers":[
        {
            "category":"Shopping",
            "subcategory":"Pharmacy",
            "type":"Retail Goods"
        }
    ],
    "sg:phone":"+1 506 756 3391",
    "sg:postcode":"E4Z 4L9",
    "sg:province":"NB",
    "wof:name":"Petitcodiac Drug Mart",
    "wof:placetype":"venue"
},
  "geometry": {"coordinates":[-65.17681899999999,45.930889],"type":"Point"}
}