{
  "type": "Feature",
  "properties": {
    "addr:full":"1135 Av Des Erables Quebec QC G1R 2N3",
    "addr:housenumber":"1135",
    "addr:postcode":"g1r 2n3",
    "addr:street":"Av Des Erables",
    "iso:country":"CA",
    "sg:address":"1135 Av Des Erables",
    "sg:city":"Quebec",
    "sg:classifiers":[
        {
            "category":"Shopping",
            "subcategory":"Computers & Home Electronics",
            "type":"Retail Goods"
        }
    ],
    "sg:phone":"+1 418 651 8250",
    "sg:postcode":"G1R 2N3",
    "sg:province":"QC",
    "sg:tags":[
        "equipment",
        "dealer"
    ],
    "wof:name":"Informatique Depannage Domicil",
    "wof:placetype":"venue"
},
  "geometry": {"coordinates":[-71.2282791138,46.8014678955],"type":"Point"}
}