{
  "type": "Feature",
  "properties": {
    "addr:full":"113 Rang 1Ere Chaloupe Notre-Dame-Des-Prairies QC J6E 7Y8",
    "addr:housenumber":"113",
    "addr:postcode":"j6e 7y8",
    "addr:street":"Rang 1Ere Chaloupe",
    "iso:country":"CA",
    "sg:address":"113 Rang 1Ere Chaloupe",
    "sg:city":"Notre-Dame-Des-Prairies",
    "sg:classifiers":[
        {
            "category":"Building & Trades",
            "subcategory":"Plumbing",
            "type":"Services"
        }
    ],
    "sg:phone":"+1 450 759 5651",
    "sg:postcode":"J6E 7Y8",
    "sg:province":"QC",
    "sg:tags":[
        "contractor"
    ],
    "wof:name":"Marcel Picard Inc",
    "wof:placetype":"venue"
},
  "geometry": {"coordinates":[-73.412369,46.06823],"type":"Point"}
}