{
  "type": "Feature",
  "properties": {
    "addr:full":"9201 Boul Du Centre-Hospitalie Charny QC G6X 1L5",
    "addr:housenumber":"9201",
    "addr:postcode":"g6x 1l5",
    "addr:street":"Boul Du Centre-Hospitalie",
    "iso:country":"CA",
    "sg:address":"9201 Boul Du Centre-Hospitalie",
    "sg:city":"Charny",
    "sg:classifiers":[
        {
            "category":"Wholesale",
            "subcategory":"Construction Materials",
            "type":"Manufacturing & Wholesale Goods"
        }
    ],
    "sg:phone":"+1 418 832 6181",
    "sg:postcode":"G6X 1L5",
    "sg:province":"QC",
    "sg:tags":[
        "lumber"
    ],
    "wof:name":"Sovebec Inc",
    "wof:placetype":"venue"
},
  "geometry": {"coordinates":[-71.26222229,46.7234115601],"type":"Point"}
}