{
  "type": "Feature",
  "properties": {
    "iso:country":"CA",
    "sg:address":"331 Sammon Ave",
    "sg:city":"East York",
    "sg:classifiers":[
        {
            "category":"Retail",
            "subcategory":"Auto Repair",
            "type":"Services"
        }
    ],
    "sg:phone":"+1 416 461 5376",
    "sg:postcode":"M4J 2A4",
    "sg:province":"ON",
    "sg:tags":[
        "repairing",
        "automobile"
    ],
    "wof:name":"Greenwood Auto Ctr Ltd",
    "wof:placetype":"venue"
},
  "geometry": {"coordinates":[-79.3343429565,43.6868019104],"type":"Point"}
}