{
  "type": "Feature",
  "properties": {
    "iso:country":"CA",
    "sg:city":"Vancouver",
    "sg:classifiers":[
        {
            "category":"Shopping",
            "subcategory":"Bicycles & Sporting Goods",
            "type":"Retail Goods"
        }
    ],
    "sg:phone":"+1 604 221 7662",
    "sg:postcode":"V6T 1V6",
    "sg:province":"BC",
    "wof:name":"Thriller",
    "wof:placetype":"venue"
},
  "geometry": {"coordinates":[-123.24339294400001,49.2660140991],"type":"Point"}
}