{
  "type": "Feature",
  "properties": {
    "addr:full":"9912 101 Ave Grande Prairie AB T8V 0X8",
    "addr:housenumber":"9912",
    "addr:postcode":"t8v 0x8",
    "addr:street":"101 Ave",
    "iso:country":"CA",
    "sg:address":"9912 101 Ave",
    "sg:city":"Grande Prairie",
    "sg:classifiers":[
        {
            "category":"Organizations",
            "subcategory":"Professional Association",
            "type":"Services"
        }
    ],
    "sg:phone":"+1 780 532 3110",
    "sg:postcode":"T8V 0X8",
    "sg:province":"AB",
    "wof:name":"Royal Canadian Legion",
    "wof:placetype":"venue"
},
  "geometry": {"coordinates":[-118.792213,55.171806],"type":"Point"}
}