{
  "type": "Feature",
  "properties": {
    "addr:full":"North York ON M3J 2P6",
    "addr:postcode":"m3j 2p6",
    "iso:country":"CA",
    "sg:city":"North York",
    "sg:classifiers":[
        {
            "category":"Social Services",
            "subcategory":"Job Training",
            "type":"Services"
        }
    ],
    "sg:phone":"+1 416 631 0272",
    "sg:postcode":"M3J 2P6",
    "sg:province":"ON",
    "sg:tags":[
        "rehabilitation"
    ],
    "wof:name":"Chesswood Rehab",
    "wof:placetype":"venue"
},
  "geometry": {"coordinates":[-79.474075,43.755787],"type":"Point"}
}