{
  "type": "Feature",
  "properties": {
    "addr:full":"241 Wilson St E Ancaster ON L9G 2B8",
    "addr:housenumber":"241",
    "addr:postcode":"l9g 2b8",
    "addr:street":"Wilson St E",
    "iso:country":"CA",
    "sg:address":"241 Wilson St E",
    "sg:city":"Ancaster",
    "sg:classifiers":[
        {
            "category":"Banks & Credit Unions",
            "subcategory":"Investment Brokerage",
            "type":"Services"
        }
    ],
    "sg:phone":"+1 905 648 9559",
    "sg:postcode":"L9G 2B8",
    "sg:province":"ON",
    "sg:tags":[
        "funds",
        "mutual"
    ],
    "wof:name":"Bick Financial Security Corp",
    "wof:placetype":"venue"
},
  "geometry": {"coordinates":[-79.978714,43.223633],"type":"Point"}
}