{
  "type": "Feature",
  "properties": {
    "iso:country":"CA",
    "sg:address":"53 Sydney St",
    "sg:city":"Digby",
    "sg:classifiers":[
        {
            "category":"Communications",
            "subcategory":"Radio Station",
            "type":"Services"
        }
    ],
    "sg:phone":"+1 902 245 2111",
    "sg:postcode":"B0V 1A0",
    "sg:province":"NS",
    "sg:tags":[
        "company",
        "broadcasting"
    ],
    "wof:name":"Ckdy",
    "wof:placetype":"venue"
},
  "geometry": {"coordinates":[-65.76222229,44.6232223511],"type":"Point"}
}