{
  "type": "Feature",
  "properties": {
    "addr:full":"Richmond BC V6V 1L4",
    "addr:postcode":"v6v 1l4",
    "iso:country":"CA",
    "sg:city":"Richmond",
    "sg:classifiers":[
        {
            "category":"Professional",
            "subcategory":"Engineering",
            "type":"Services"
        }
    ],
    "sg:phone":"+1 604 273 6080",
    "sg:postcode":"V6V 1L4",
    "sg:province":"BC",
    "sg:tags":[
        "equipment",
        "supply",
        "sawmill",
        "engineer"
    ],
    "wof:name":"Ats Automation Inc",
    "wof:placetype":"venue"
},
  "geometry": {"coordinates":[-123.062386,49.202629],"type":"Point"}
}