{
  "type": "Feature",
  "properties": {
    "addr:full":"2507 Rue DE L'Eglise Val-David QC J0T 2N0",
    "addr:housenumber":"2507",
    "addr:postcode":"j0t 2n0",
    "addr:street":"Rue De L'Eglise",
    "iso:country":"CA",
    "sg:address":"2507 Rue DE L'Eglise",
    "sg:city":"Val-David",
    "sg:classifiers":[
        {
            "category":"Personal",
            "subcategory":"Beauty Salon",
            "type":"Services"
        }
    ],
    "sg:phone":"+1 819 322 5858",
    "sg:postcode":"J0T 2N0",
    "sg:province":"QC",
    "wof:name":"Coiffure Rita",
    "wof:placetype":"venue"
},
  "geometry": {"coordinates":[-74.471886,46.130566],"type":"Point"}
}