{
  "type": "Feature",
  "properties": {
    "iso:country":"CA",
    "sg:address":"52 Armthorpe Rd",
    "sg:city":"Brampton",
    "sg:classifiers":[
        {
            "category":"Retail",
            "subcategory":"Repair Shop",
            "type":"Services"
        }
    ],
    "sg:phone":"+1 905 790 2211",
    "sg:postcode":"L6T 5M4",
    "sg:province":"ON",
    "sg:tags":[
        "refrigerating"
    ],
    "wof:name":"Tfi Food Equipment Solutions",
    "wof:placetype":"venue"
},
  "geometry": {"coordinates":[-79.6723937988,43.7458724976],"type":"Point"}
}