{
  "type": "Feature",
  "properties": {
    "iso:country":"CA",
    "sg:address":"671 Rue Woodland",
    "sg:city":"Verdun",
    "sg:classifiers":[
        {
            "category":"Building & Trades",
            "subcategory":"Plumbing",
            "type":"Services"
        }
    ],
    "sg:phone":"+1 514 761 7668",
    "sg:postcode":"H4H 1V7",
    "sg:province":"QC",
    "sg:tags":[
        "contractor"
    ],
    "wof:name":"Robert Dubuc Plomberie/Chauffg",
    "wof:placetype":"venue"
},
  "geometry": {"coordinates":[-73.573402,45.45269],"type":"Point"}
}