{
  "type": "Feature",
  "properties": {
    "addr:full":"1007 Pescod Ave Cornwall ON K6J 2K1",
    "addr:housenumber":"1007",
    "addr:postcode":"k6j 2k1",
    "addr:street":"Pescod Ave",
    "iso:country":"CA",
    "sg:address":"1007 Pescod Ave",
    "sg:city":"Cornwall",
    "sg:classifiers":[
        {
            "category":"Building & Trades",
            "subcategory":"Plumbing",
            "type":"Services"
        }
    ],
    "sg:phone":"+1 613 932 4236",
    "sg:postcode":"K6J 2K1",
    "sg:province":"ON",
    "sg:tags":[
        "contractor"
    ],
    "wof:name":"Laperriere Mechanical",
    "wof:placetype":"venue"
},
  "geometry": {"coordinates":[-74.76973,45.016991],"type":"Point"}
}