{
  "type": "Feature",
  "properties": {
    "addr:full":"94 Wellington St S Goderich ON N7A 3S9",
    "addr:housenumber":"94",
    "addr:postcode":"n7a 3s9",
    "addr:street":"Wellington St S",
    "iso:country":"CA",
    "sg:address":"94 Wellington St S",
    "sg:city":"Goderich",
    "sg:classifiers":[
        {
            "category":"Banks & Credit Unions",
            "subcategory":"Investment Brokerage",
            "type":"Services"
        }
    ],
    "sg:phone":"+1 519 524 2451",
    "sg:postcode":"N7A 3S9",
    "sg:province":"ON",
    "sg:tags":[
        "consultant",
        "planning",
        "financial"
    ],
    "wof:name":"Petrie Financial Svc",
    "wof:placetype":"venue"
},
  "geometry": {"coordinates":[-81.717896,43.740154],"type":"Point"}
}