{
  "type": "Feature",
  "properties": {
    "addr:full":"Quebec QC G1S 1T5",
    "addr:postcode":"g1s 1t5",
    "iso:country":"CA",
    "sg:city":"Quebec",
    "sg:classifiers":[
        {
            "category":"Health Services",
            "subcategory":"Medical Lab",
            "type":"Services"
        }
    ],
    "sg:phone":"+1 418 687 3016",
    "sg:postcode":"G1S 1T5",
    "sg:province":"QC",
    "wof:name":"Bernard, Paul",
    "wof:placetype":"venue"
},
  "geometry": {"coordinates":[-71.2147064209,46.8099517822],"type":"Point"}
}