{
  "type": "Feature",
  "properties": {
    "addr:full":"Twillingate NL A0G 4M0",
    "addr:postcode":"a0g 4m0",
    "addr:street":"Twillingate",
    "iso:country":"CA",
    "sg:city":"Twillingate",
    "sg:classifiers":[
        {
            "category":"Recreation",
            "type":"Entertainment"
        }
    ],
    "sg:phone":"+1 709 884 5999",
    "sg:postcode":"A0G 4M0",
    "sg:province":"NL",
    "sg:tags":[
        "charter",
        "boat"
    ],
    "wof:name":"Twillingate Adventure Tours",
    "wof:placetype":"venue"
},
  "geometry": {"coordinates":[-54.75288,49.644932],"type":"Point"}
}