{
  "type": "Feature",
  "properties": {
    "addr:full":"614 Eastvale Dr Gloucester ON K1J 6Z6",
    "addr:housenumber":"614",
    "addr:postcode":"k1j 6z6",
    "addr:street":"Eastvale Dr",
    "iso:country":"CA",
    "sg:address":"614 Eastvale Dr",
    "sg:city":"Gloucester",
    "sg:classifiers":[
        {
            "category":"Education",
            "subcategory":"School",
            "type":"Public Place"
        }
    ],
    "sg:phone":"+1 613 749 2349",
    "sg:postcode":"K1J 6Z6",
    "sg:province":"ON",
    "wof:name":"Ecole LA Verendrye",
    "wof:placetype":"venue"
},
  "geometry": {"coordinates":[-75.597008,45.460686],"type":"Point"}
}