{
  "type": "Feature",
  "properties": {
    "iso:country":"CA",
    "sg:address":"319 Av Leonidas S",
    "sg:city":"Rimouski",
    "sg:classifiers":[
        {
            "category":"Home & Garden",
            "subcategory":"Garden Supply",
            "type":"Retail Goods"
        }
    ],
    "sg:phone":"+1 418 723 9640",
    "sg:postcode":"G5L 2V1",
    "sg:province":"QC",
    "sg:tags":[
        "engine"
    ],
    "wof:name":"Auto-Moteur Rimouski Inc",
    "wof:placetype":"venue"
},
  "geometry": {"coordinates":[-68.5026016235,48.458065033],"type":"Point"}
}