{
  "type": "Feature",
  "properties": {
    "addr:full":"3248 Radison Ave #1 Chelmsford ON P0M 1L0",
    "addr:housenumber":"3248",
    "addr:postcode":"p0m 1l0",
    "addr:street":"Radison Ave # 1",
    "iso:country":"CA",
    "sg:address":"3248 Radison Ave #1",
    "sg:city":"Chelmsford",
    "sg:classifiers":[
        {
            "category":"Retail",
            "subcategory":"Auto Repair",
            "type":"Services"
        }
    ],
    "sg:phone":"+1 705 855 6676",
    "sg:postcode":"P0M 1L0",
    "sg:province":"ON",
    "sg:tags":[
        "body",
        "automobile",
        "painting"
    ],
    "wof:name":"Norm's Collision Ctr Ltd",
    "wof:placetype":"venue"
},
  "geometry": {"coordinates":[-81.1973571777,46.5688743591],"type":"Point"}
}