{
  "type": "Feature",
  "properties": {
    "addr:full":"11531 80 Ave Delta BC V4C 1X5",
    "addr:housenumber":"11531",
    "addr:postcode":"v4c 1x5",
    "addr:street":"80 Ave",
    "iso:country":"CA",
    "sg:address":"11531 80 Ave",
    "sg:city":"Delta",
    "sg:classifiers":[
        {
            "category":"Education",
            "subcategory":"School",
            "type":"Public Place"
        }
    ],
    "sg:phone":"+1 604 596 9554",
    "sg:postcode":"V4C 1X5",
    "sg:province":"BC",
    "wof:name":"Mc Closkey Elementary School",
    "wof:placetype":"venue"
},
  "geometry": {"coordinates":[-122.903221,49.148876],"type":"Point"}
}