{
  "type": "Feature",
  "properties": {
    "addr:full":"Caraquet NB E1W 1B8",
    "addr:postcode":"e1w 1b8",
    "iso:country":"CA",
    "sg:city":"Caraquet",
    "sg:classifiers":[
        {
            "category":"Shopping",
            "subcategory":"Florist",
            "type":"Retail Goods"
        }
    ],
    "sg:phone":"+1 506 727 2819",
    "sg:postcode":"E1W 1B8",
    "sg:province":"NB",
    "wof:name":"Marchande DE Fleurs",
    "wof:placetype":"venue"
},
  "geometry": {"coordinates":[-64.93448600000001,47.794857],"type":"Point"}
}