{
  "type": "Feature",
  "properties": {
    "iso:country":"CA",
    "sg:address":"348 King St E",
    "sg:city":"Cambridge",
    "sg:classifiers":[
        {
            "category":"Personal",
            "type":"Services"
        }
    ],
    "sg:phone":"+1 519 650 5768",
    "sg:postcode":"N3H 3M8",
    "sg:province":"ON",
    "sg:tags":[
        "therapist",
        "massage"
    ],
    "wof:name":"Sparkes Massage Clinic",
    "wof:placetype":"venue"
},
  "geometry": {"coordinates":[-80.36261,43.397926],"type":"Point"}
}