{
  "type": "Feature",
  "properties": {
    "addr:full":"1213 Av Bernard Outremont QC H2V 1V7",
    "addr:housenumber":"1213",
    "addr:postcode":"h2v 1v7",
    "addr:street":"Av Bernard",
    "iso:country":"CA",
    "sg:address":"1213 Av Bernard",
    "sg:city":"Outremont",
    "sg:classifiers":[
        {
            "category":"Home & Garden",
            "subcategory":"Furniture",
            "type":"Retail Goods"
        }
    ],
    "sg:phone":"+1 514 272 9876",
    "sg:postcode":"H2V 1V7",
    "sg:province":"QC",
    "wof:name":"Nuits D'Hubert",
    "wof:placetype":"venue"
},
  "geometry": {"coordinates":[-73.608681,45.520432],"type":"Point"}
}