{
  "type": "Feature",
  "properties": {
    "addr:full":"25 Boul St-Pierre O Caraquet NB E1W 1B6",
    "addr:housenumber":"25",
    "addr:postcode":"e1w 1b6",
    "addr:street":"Boul St-Pierre O",
    "iso:country":"CA",
    "sg:address":"25 Boul St-Pierre O",
    "sg:city":"Caraquet",
    "sg:classifiers":[
        {
            "category":"Personal",
            "subcategory":"Beauty Salon",
            "type":"Services"
        }
    ],
    "sg:phone":"+1 506 727 2267",
    "sg:postcode":"E1W 1B6",
    "sg:province":"NB",
    "wof:name":"Salon Studio 25",
    "wof:placetype":"venue"
},
  "geometry": {"coordinates":[-64.9344863892,47.7948570251],"type":"Point"}
}