{
  "type": "Feature",
  "properties": {
    "addr:full":"329 Boul Des Bois-Francs S Victoriaville QC G6P 4T2",
    "addr:housenumber":"329",
    "addr:postcode":"g6p 4t2",
    "addr:street":"Boul Des Bois-Francs S",
    "iso:country":"CA",
    "sg:address":"329 Boul Des Bois-Francs S",
    "sg:city":"Victoriaville",
    "sg:classifiers":[
        {
            "category":"Professional",
            "subcategory":"Business Services",
            "type":"Services"
        }
    ],
    "sg:phone":"+1 819 751 0041",
    "sg:postcode":"G6P 4T2",
    "sg:province":"QC",
    "sg:tags":[
        "painter",
        "sign"
    ],
    "wof:name":"Ben Tar Inc",
    "wof:placetype":"venue"
},
  "geometry": {"coordinates":[-71.942284,46.053795],"type":"Point"}
}