{
  "type": "Feature",
  "properties": {
    "addr:full":"888 South Service Rd Mississauga ON L5E 1T9",
    "addr:housenumber":"888",
    "addr:postcode":"l5e 1t9",
    "addr:street":"South Service",
    "iso:country":"CA",
    "sg:address":"888 South Service Rd",
    "sg:city":"Mississauga",
    "sg:classifiers":[
        {
            "category":"Shopping",
            "type":"Retail Goods"
        }
    ],
    "sg:phone":"+1 905 275 0000",
    "sg:postcode":"L5E 1T9",
    "sg:province":"ON",
    "sg:tags":[
        "equipment",
        "telephone",
        "supply"
    ],
    "wof:name":"Phone Guys",
    "wof:placetype":"venue"
},
  "geometry": {"coordinates":[-79.579208374,43.5865898132],"type":"Point"}
}