{
  "type": "Feature",
  "properties": {
    "addr:full":"18 Park St Charlottetown PE C1A 5G7",
    "addr:housenumber":"18",
    "addr:postcode":"c1a 5g7",
    "addr:street":"Park St",
    "iso:country":"CA",
    "sg:address":"18 Park St",
    "sg:city":"Charlottetown",
    "sg:classifiers":[
        {
            "category":"Manufacturing",
            "subcategory":"Metals",
            "type":"Manufacturing & Wholesale Goods"
        }
    ],
    "sg:phone":"+1 902 628 6282",
    "sg:postcode":"C1A 5G7",
    "sg:province":"PE",
    "sg:tags":[
        "engraver"
    ],
    "wof:name":"Engraving Excellence",
    "wof:placetype":"venue"
},
  "geometry": {"coordinates":[-63.117039,46.24408],"type":"Point"}
}