{
  "type": "Feature",
  "properties": {
    "addr:full":"3435 Rue Drummond Montreal QC H3G 1X8",
    "addr:housenumber":"3435",
    "addr:postcode":"h3g 1x8",
    "addr:street":"Rue Drummond",
    "iso:country":"CA",
    "sg:address":"3435 Rue Drummond",
    "sg:city":"Montreal",
    "sg:classifiers":[
        {
            "category":"Real Estate",
            "subcategory":"Real Estate Operator",
            "type":"Services"
        }
    ],
    "sg:phone":"+1 514 842 4370",
    "sg:postcode":"H3G 1X8",
    "sg:province":"QC",
    "sg:tags":[
        "apartment"
    ],
    "wof:name":"Drummond Plaza Apartments",
    "wof:placetype":"venue"
},
  "geometry": {"coordinates":[-73.5791549683,45.5012054443],"type":"Point"}
}