{
  "type": "Feature",
  "properties": {
    "addr:full":"680 Bayview Dr Barrie ON L4N 9A6",
    "addr:housenumber":"680",
    "addr:postcode":"l4n 9a6",
    "addr:street":"Bayview Dr",
    "iso:country":"CA",
    "sg:address":"680 Bayview Dr",
    "sg:city":"Barrie",
    "sg:classifiers":[
        {
            "category":"Building & Trades",
            "subcategory":"Construction",
            "type":"Services"
        }
    ],
    "sg:phone":"+1 705 733 3737",
    "sg:postcode":"L4N 9A6",
    "sg:province":"ON",
    "sg:tags":[
        "designer",
        "dealer",
        "pool",
        "swimming"
    ],
    "wof:name":"Christal Pools & Spas",
    "wof:placetype":"venue"
},
  "geometry": {"coordinates":[-79.677437,44.33091],"type":"Point"}
}