{
  "type": "Feature",
  "properties": {
    "iso:country":"CA",
    "sg:address":"6270 Lakeview Ave",
    "sg:city":"Burnaby",
    "sg:classifiers":[
        {
            "category":"Building & Trades",
            "subcategory":"Construction",
            "type":"Services"
        }
    ],
    "sg:phone":"+1 604 435 6159",
    "sg:postcode":"V5E 2P2",
    "sg:province":"BC",
    "sg:tags":[
        "repairing",
        "remodeling",
        "contractor"
    ],
    "wof:name":"Globus Contractors Ltd",
    "wof:placetype":"venue"
},
  "geometry": {"coordinates":[-122.969200134,49.2272033691],"type":"Point"}
}