{
  "type": "Feature",
  "properties": {
    "iso:country":"CA",
    "sg:address":"747 Rue Saint-Christophe",
    "sg:city":"Trois-Rivieres",
    "sg:classifiers":[
        {
            "category":"Food & Beverages",
            "subcategory":"Groceries & Convenience Stores",
            "type":"Retail Goods"
        }
    ],
    "sg:phone":"+1 819 371 2444",
    "sg:postcode":"G9A 3L9",
    "sg:province":"QC",
    "wof:name":"Depanneur Beaulieu",
    "wof:placetype":"venue"
},
  "geometry": {"coordinates":[-72.55028533940001,46.3558578491],"type":"Point"}
}