{
  "type": "Feature",
  "properties": {
    "addr:full":"240 Main St Beardmore ON P0T 1G0",
    "addr:housenumber":"240",
    "addr:postcode":"p0t 1g0",
    "addr:street":"Main St",
    "iso:country":"CA",
    "sg:address":"240 Main St",
    "sg:city":"Beardmore",
    "sg:classifiers":[
        {
            "category":"Banks & Credit Unions",
            "subcategory":"Bank",
            "type":"Services"
        }
    ],
    "sg:phone":"+1 807 875 2015",
    "sg:postcode":"P0T 1G0",
    "sg:province":"ON",
    "wof:name":"Scotiabank",
    "wof:placetype":"venue"
},
  "geometry": {"coordinates":[-87.9595870972,49.6016769409],"type":"Point"}
}