{
  "type": "Feature",
  "properties": {
    "addr:full":"Winnipeg MB R2M 3K1",
    "addr:postcode":"r2m 3k1",
    "iso:country":"CA",
    "sg:city":"Winnipeg",
    "sg:classifiers":[
        {
            "category":"Restaurant",
            "type":"Food & Drink"
        }
    ],
    "sg:phone":"+1 204 254 3901",
    "sg:postcode":"R2M 3K1",
    "sg:province":"MB",
    "sg:tags":[
        "pizza"
    ],
    "wof:name":"Quality Pizza",
    "wof:placetype":"venue"
},
  "geometry": {"coordinates":[-97.1120147705,49.8354377747],"type":"Point"}
}