{
  "type": "Feature",
  "properties": {
    "addr:full":"856 Lawrence Rd Hamilton ON L8K 2A2",
    "addr:housenumber":"856",
    "addr:postcode":"l8k 2a2",
    "addr:street":"Lawrence Rd",
    "iso:country":"CA",
    "sg:address":"856 Lawrence Rd",
    "sg:city":"Hamilton",
    "sg:classifiers":[
        {
            "category":"Food & Beverages",
            "subcategory":"Groceries & Convenience Stores",
            "type":"Retail Goods"
        }
    ],
    "sg:phone":"+1 905 549 4511",
    "sg:postcode":"L8K 2A2",
    "sg:province":"ON",
    "sg:tags":[
        "variety"
    ],
    "wof:name":"Big Bee Convenience",
    "wof:placetype":"venue"
},
  "geometry": {"coordinates":[-79.8041305542,43.2291030884],"type":"Point"}
}