{
  "type": "Feature",
  "properties": {
    "addr:full":"3470 Rue DE L'Energie Jonquiere QC G7X 9H3",
    "addr:housenumber":"3470",
    "addr:postcode":"g7x 9h3",
    "addr:street":"Rue De L'Energie",
    "iso:country":"CA",
    "sg:address":"3470 Rue DE L'Energie",
    "sg:city":"Jonquiere",
    "sg:classifiers":[
        {
            "category":"Wholesale",
            "subcategory":"Scrap",
            "type":"Manufacturing & Wholesale Goods"
        }
    ],
    "sg:phone":"+1 418 542 2244",
    "sg:postcode":"G7X 9H3",
    "sg:province":"QC",
    "sg:tags":[
        "recycling",
        "center"
    ],
    "wof:name":"Triage Trim Ltd",
    "wof:placetype":"venue"
},
  "geometry": {"coordinates":[-71.21891021730001,48.4080810547],"type":"Point"}
}