{
  "type": "Feature",
  "properties": {
    "addr:full":"Hamilton ON L8W 3N7",
    "addr:postcode":"l8w 3n7",
    "iso:country":"CA",
    "sg:city":"Hamilton",
    "sg:classifiers":[
        {
            "category":"Retail",
            "subcategory":"Auto Repair",
            "type":"Services"
        }
    ],
    "sg:phone":"+1 905 574 6733",
    "sg:postcode":"L8W 3N7",
    "sg:province":"ON",
    "sg:tags":[
        "repairing",
        "automobile"
    ],
    "wof:name":"Top Value Transmission & Auto",
    "wof:placetype":"venue"
},
  "geometry": {"coordinates":[-79.8419494629,43.1897506714],"type":"Point"}
}