{
  "type": "Feature",
  "properties": {
    "iso:country":"CA",
    "sg:city":"Saint-Laurent",
    "sg:classifiers":[
        {
            "category":"Real Estate",
            "subcategory":"Real Estate Operator",
            "type":"Services"
        }
    ],
    "sg:phone":"+1 514 336 5450",
    "sg:postcode":"H4N 1N9",
    "sg:province":"QC",
    "sg:tags":[
        "apartment"
    ],
    "wof:name":"Immeubles Joie DE Vivre Enr",
    "wof:placetype":"venue"
},
  "geometry": {"coordinates":[-73.6744,45.531372],"type":"Point"}
}