{
  "type": "Feature",
  "properties": {
    "addr:full":"113 12E Av Drummondville QC J2B 2Y6",
    "addr:housenumber":"113",
    "addr:postcode":"j2b 2y6",
    "addr:street":"12E Av",
    "iso:country":"CA",
    "sg:address":"113 12E Av",
    "sg:city":"Drummondville",
    "sg:classifiers":[
        {
            "category":"Personal",
            "subcategory":"Beauty Salon",
            "type":"Services"
        }
    ],
    "sg:phone":"+1 819 472 4248",
    "sg:postcode":"J2B 2Y6",
    "sg:province":"QC",
    "wof:name":"Salon Esthetique Louise",
    "wof:placetype":"venue"
},
  "geometry": {"coordinates":[-72.49202,45.870071],"type":"Point"}
}