{
  "type": "Feature",
  "properties": {
    "addr:full":"6 Timothy Ave N Hanwell NB E3C 2B7",
    "addr:housenumber":"6",
    "addr:postcode":"e3c 2b7",
    "addr:street":"Timothy Ave N",
    "iso:country":"CA",
    "sg:address":"6 Timothy Ave N",
    "sg:city":"Hanwell",
    "sg:phone":"+1 506 459 3222",
    "sg:postcode":"E3C 2B7",
    "sg:province":"NB",
    "sg:tags":[
        "oil"
    ],
    "wof:name":"Taylor Petroleum Ltd",
    "wof:placetype":"venue"
},
  "geometry": {"coordinates":[-66.795441,45.868484],"type":"Point"}
}