{
  "type": "Feature",
  "properties": {
    "addr:full":"329 Glasgow St Kitchener ON N2M 2M9",
    "addr:housenumber":"329",
    "addr:postcode":"n2m 2m9",
    "addr:street":"Glasgow St",
    "iso:country":"CA",
    "sg:address":"329 Glasgow St",
    "sg:city":"Kitchener",
    "sg:classifiers":[
        {
            "category":"Education",
            "subcategory":"School",
            "type":"Public Place"
        }
    ],
    "sg:phone":"+1 519 578 5430",
    "sg:postcode":"N2M 2M9",
    "sg:province":"ON",
    "wof:name":"Westmount Public School",
    "wof:placetype":"venue"
},
  "geometry": {"coordinates":[-80.5216217041,43.4500770569],"type":"Point"}
}