{
  "type": "Feature",
  "properties": {
    "iso:country":"CA",
    "sg:address":"2555 Rue Saint-Philippe",
    "sg:city":"Trois-Rivieres",
    "sg:classifiers":[
        {
            "category":"Retail",
            "subcategory":"Auto Repair",
            "type":"Services"
        }
    ],
    "sg:phone":"+1 819 371 3636",
    "sg:postcode":"G9A 4W2",
    "sg:province":"QC",
    "sg:tags":[
        "repairing",
        "automobile"
    ],
    "wof:name":"Garage Daniel Ouellette Enr",
    "wof:placetype":"venue"
},
  "geometry": {"coordinates":[-72.549545,46.332756],"type":"Point"}
}