{
  "type": "Feature",
  "properties": {
    "iso:country":"CA",
    "sg:address":"3360 Roblin Blvd",
    "sg:city":"Winnipeg",
    "sg:classifiers":[
        {
            "category":"Health Services",
            "subcategory":"Doctor",
            "type":"Services"
        }
    ],
    "sg:phone":"+1 204 889 7200",
    "sg:postcode":"R3R 0C5",
    "sg:province":"MB",
    "sg:tags":[
        "physician",
        "surgeon"
    ],
    "wof:name":"Charleswood Medical Clinic",
    "wof:placetype":"venue"
},
  "geometry": {"coordinates":[-97.256073,49.868198],"type":"Point"}
}