{
  "type": "Feature",
  "properties": {
    "addr:full":"10032 113 Ave Grande Prairie AB T8V 7B3",
    "addr:housenumber":"10032",
    "addr:postcode":"t8v 7b3",
    "addr:street":"113 Ave",
    "iso:country":"CA",
    "sg:address":"10032 113 Ave",
    "sg:city":"Grande Prairie",
    "sg:classifiers":[
        {
            "category":"Wholesale",
            "subcategory":"Machinery & Supplies",
            "type":"Manufacturing & Wholesale Goods"
        }
    ],
    "sg:phone":"+1 780 532 2808",
    "sg:postcode":"T8V 7B3",
    "sg:province":"AB",
    "sg:tags":[
        "salon",
        "beauty"
    ],
    "wof:name":"International Beauty Svc",
    "wof:placetype":"venue"
},
  "geometry": {"coordinates":[-118.795914,55.182571],"type":"Point"}
}