{
  "type": "Feature",
  "properties": {
    "addr:full":"824 Rue Papineau Joliette QC J6E 2L5",
    "addr:housenumber":"824",
    "addr:postcode":"j6e 2l5",
    "addr:street":"Rue Papineau",
    "iso:country":"CA",
    "sg:address":"824 Rue Papineau",
    "sg:city":"Joliette",
    "sg:classifiers":[
        {
            "category":"Building & Trades",
            "subcategory":"Plumbing",
            "type":"Services"
        }
    ],
    "sg:phone":"+1 450 753 5660",
    "sg:postcode":"J6E 2L5",
    "sg:province":"QC",
    "sg:tags":[
        "contractor"
    ],
    "wof:name":"Centre DE Plomberie Lafortune",
    "wof:placetype":"venue"
},
  "geometry": {"coordinates":[-73.454971,46.027592],"type":"Point"}
}