{
  "type": "Feature",
  "properties": {
    "addr:full":"220 Main St Turtleford SK S0M 2Y0",
    "addr:housenumber":"220",
    "addr:postcode":"s0m 2y0",
    "addr:street":"Main St",
    "iso:country":"CA",
    "sg:address":"220 Main St",
    "sg:city":"Turtleford",
    "sg:classifiers":[
        {
            "category":"Food & Beverages",
            "subcategory":"Groceries & Convenience Stores",
            "type":"Retail Goods"
        }
    ],
    "sg:phone":"+1 306 845 2081",
    "sg:postcode":"S0M 2Y0",
    "sg:province":"SK",
    "sg:tags":[
        "grocer"
    ],
    "wof:name":"Turtleford Main Street Market",
    "wof:placetype":"venue"
},
  "geometry": {"coordinates":[-108.959076,53.38847],"type":"Point"}
}