{
  "type": "Feature",
  "properties": {
    "addr:full":"748 Vimy St North Bay ON P1B 5B4",
    "addr:housenumber":"748",
    "addr:postcode":"p1b 5b4",
    "addr:street":"Vimy St",
    "iso:country":"CA",
    "sg:address":"748 Vimy St",
    "sg:city":"North Bay",
    "sg:classifiers":[
        {
            "category":"Building & Trades",
            "subcategory":"Landscaping Services",
            "type":"Services"
        }
    ],
    "sg:phone":"+1 705 497 0876",
    "sg:postcode":"P1B 5B4",
    "sg:province":"ON",
    "sg:tags":[
        "landscape",
        "contractor"
    ],
    "wof:name":"Gateway Landscaping",
    "wof:placetype":"venue"
},
  "geometry": {"coordinates":[-79.4696731567,46.3241958618],"type":"Point"}
}