{
  "type": "Feature",
  "properties": {
    "addr:full":"382 6th Ave SE Swift Current SK S9H 3P1",
    "addr:housenumber":"382",
    "addr:postcode":"s9h 3p1",
    "addr:street":"6Th Ave Se",
    "iso:country":"CA",
    "sg:address":"382 6th Ave SE",
    "sg:city":"Swift Current",
    "sg:classifiers":[
        {
            "category":"Building & Trades",
            "subcategory":"Plumbing",
            "type":"Services"
        }
    ],
    "sg:phone":"+1 306 773 4490",
    "sg:postcode":"S9H 3P1",
    "sg:province":"SK",
    "sg:tags":[
        "tank",
        "septic"
    ],
    "wof:name":"Swift Sanitary Svc",
    "wof:placetype":"venue"
},
  "geometry": {"coordinates":[-107.792266846,50.2739944458],"type":"Point"}
}