{
  "type": "Feature",
  "properties": {
    "addr:full":"Markdale ON N0C 1H0",
    "addr:postcode":"n0c 1h0",
    "iso:country":"CA",
    "sg:city":"Markdale",
    "sg:classifiers":[
        {
            "category":"Restaurant",
            "type":"Food & Drink"
        }
    ],
    "sg:phone":"+1 519 986 3665",
    "sg:postcode":"N0C 1H0",
    "sg:province":"ON",
    "sg:tags":[
        "pizza"
    ],
    "wof:name":"Big Cheese Pizza",
    "wof:placetype":"venue"
},
  "geometry": {"coordinates":[-80.64801,44.318436],"type":"Point"}
}