{
  "type": "Feature",
  "properties": {
    "addr:full":"130 Rue Roy Saint-Pie QC J0H 1W0",
    "addr:housenumber":"130",
    "addr:postcode":"j0h 1w0",
    "addr:street":"Rue Roy",
    "iso:country":"CA",
    "sg:address":"130 Rue Roy",
    "sg:city":"Saint-Pie",
    "sg:classifiers":[
        {
            "category":"Manufacturing",
            "subcategory":"Furniture",
            "type":"Manufacturing & Wholesale Goods"
        }
    ],
    "sg:phone":"+1 450 772 2977",
    "sg:postcode":"J0H 1W0",
    "sg:province":"QC",
    "wof:name":"Mobilier DE Bureau H Moquin",
    "wof:placetype":"venue"
},
  "geometry": {"coordinates":[-72.90464799999999,45.502888],"type":"Point"}
}