{
  "type": "Feature",
  "properties": {
    "addr:full":"618 Major Mackenzie Dr E Richmond Hill ON L4C 1J9",
    "addr:housenumber":"618",
    "addr:postcode":"l4c 1j9",
    "addr:street":"Major Mackenzie Dr E",
    "iso:country":"CA",
    "sg:address":"618 Major Mackenzie Dr E",
    "sg:city":"Richmond Hill",
    "sg:classifiers":[
        {
            "category":"Personal",
            "subcategory":"Beauty Salon",
            "type":"Services"
        }
    ],
    "sg:phone":"+1 905 884 4581",
    "sg:postcode":"L4C 1J9",
    "sg:province":"ON",
    "wof:name":"Oro Hair Studio",
    "wof:placetype":"venue"
},
  "geometry": {"coordinates":[-79.417328,43.875759],"type":"Point"}
}