{
  "type": "Feature",
  "properties": {
    "addr:full":"Buck Lake AB T0C 0T0",
    "addr:postcode":"t0c 0t0",
    "iso:country":"CA",
    "sg:city":"Buck Lake",
    "sg:classifiers":[
        {
            "category":"Home & Garden",
            "subcategory":"Hardware",
            "type":"Retail Goods"
        }
    ],
    "sg:phone":"+1 780 388 2450",
    "sg:postcode":"T0C 0T0",
    "sg:province":"AB",
    "wof:name":"Buck Lake Hardware",
    "wof:placetype":"venue"
},
  "geometry": {"coordinates":[-114.77557400000001,52.95319],"type":"Point"}
}