{
  "type": "Feature",
  "properties": {
    "addr:full":"10916 Av Drapeau Montreal-Nord QC H1H 3J9",
    "addr:housenumber":"10916",
    "addr:postcode":"h1h 3j9",
    "addr:street":"Av Drapeau",
    "iso:country":"CA",
    "sg:address":"10916 Av Drapeau",
    "sg:city":"Montreal-Nord",
    "sg:classifiers":[
        {
            "category":"Freight",
            "type":"Transportation"
        }
    ],
    "sg:phone":"+1 514 955 0333",
    "sg:postcode":"H1H 3J9",
    "sg:province":"QC",
    "sg:tags":[
        "courier"
    ],
    "wof:name":"Courrier A-1",
    "wof:placetype":"venue"
},
  "geometry": {"coordinates":[-73.631073,45.594635],"type":"Point"}
}