{
  "type": "Feature",
  "properties": {
    "iso:country":"CA",
    "sg:city":"Markham",
    "sg:classifiers":[
        {
            "category":"Manufacturing",
            "subcategory":"Signs",
            "type":"Manufacturing & Wholesale Goods"
        }
    ],
    "sg:phone":"+1 905 479 3355",
    "sg:postcode":"L3R 5J6",
    "sg:province":"ON",
    "wof:name":"Thinex Technologies",
    "wof:placetype":"venue"
},
  "geometry": {"coordinates":[-79.344299,43.83205],"type":"Point"}
}