{
  "type": "Feature",
  "properties": {
    "iso:country":"CA",
    "sg:address":"7793 Old Scugog Rd",
    "sg:city":"Hampton",
    "sg:classifiers":[
        {
            "category":"Organizations",
            "subcategory":"Religious Organization",
            "type":"Services"
        }
    ],
    "sg:phone":"+1 905 263 4190",
    "sg:postcode":"L0B 1J0",
    "sg:province":"ON",
    "sg:tags":[
        "church"
    ],
    "wof:name":"Enniskillen United Church",
    "wof:placetype":"venue"
},
  "geometry": {"coordinates":[-78.7625961304,43.9984016418],"type":"Point"}
}