{
  "type": "Feature",
  "properties": {
    "iso:country":"CA",
    "sg:city":"Abbotsford",
    "sg:classifiers":[
        {
            "category":"Personal",
            "subcategory":"Barber",
            "type":"Services"
        }
    ],
    "sg:phone":"+1 604 504 7334",
    "sg:postcode":"V2S 2C7",
    "sg:province":"BC",
    "sg:tags":[
        "salon",
        "beauty"
    ],
    "wof:name":"Magicuts",
    "wof:placetype":"venue"
},
  "geometry": {"coordinates":[-122.26799774200001,49.0375213623],"type":"Point"}
}