{
  "type": "Feature",
  "properties": {
    "addr:full":"North York ON M3N 1X3",
    "addr:postcode":"m3n 1x3",
    "iso:country":"CA",
    "sg:city":"North York",
    "sg:classifiers":[
        {
            "category":"Wholesale",
            "subcategory":"Durable Goods & Equipment",
            "type":"Manufacturing & Wholesale Goods"
        }
    ],
    "sg:phone":"+1 416 661 1220",
    "sg:postcode":"M3N 1X3",
    "sg:province":"ON",
    "sg:tags":[
        "fire",
        "extinguisher"
    ],
    "wof:name":"Acme Fire Extinguisher CO",
    "wof:placetype":"venue"
},
  "geometry": {"coordinates":[-79.5290527344,43.7590332031],"type":"Point"}
}