{
  "type": "Feature",
  "properties": {
    "iso:country":"CA",
    "sg:city":"Langley",
    "sg:classifiers":[
        {
            "category":"Banks & Credit Unions",
            "subcategory":"Bank",
            "type":"Services"
        }
    ],
    "sg:phone":"+1 604 882 2200",
    "sg:postcode":"V1M 2K4",
    "sg:province":"BC",
    "wof:name":"Royal Bank Financial Group",
    "wof:placetype":"venue"
},
  "geometry": {"coordinates":[-122.657203674,49.163646698],"type":"Point"}
}