{
  "type": "Feature",
  "properties": {
    "addr:full":"16 Rang Saint-Laurent Saint-Isidore QC G0S 2S0",
    "addr:housenumber":"16",
    "addr:postcode":"g0s 2s0",
    "addr:street":"Rang Saint-Laurent",
    "iso:country":"CA",
    "sg:address":"16 Rang Saint-Laurent",
    "sg:city":"Saint-Isidore",
    "sg:classifiers":[
        {
            "category":"Manufacturing",
            "subcategory":"Metals",
            "type":"Manufacturing & Wholesale Goods"
        }
    ],
    "sg:phone":"+1 418 882 5764",
    "sg:postcode":"G0S 2S0",
    "sg:province":"QC",
    "sg:tags":[
        "solder"
    ],
    "wof:name":"Soudure Jl Nadeau Inc",
    "wof:placetype":"venue"
},
  "geometry": {"coordinates":[-71.085014,46.554214],"type":"Point"}
}