{
  "type": "Feature",
  "properties": {
    "iso:country":"CA",
    "sg:address":"175 Barker Blvd",
    "sg:city":"Winnipeg",
    "sg:classifiers":[
        {
            "category":"Professional",
            "subcategory":"Engineering",
            "type":"Services"
        }
    ],
    "sg:phone":"+1 204 895 1474",
    "sg:postcode":"R3R 2E3",
    "sg:province":"MB",
    "sg:tags":[
        "engineer"
    ],
    "wof:name":"Charleson Engineering Ltd",
    "wof:placetype":"venue"
},
  "geometry": {"coordinates":[-97.3189315796,49.8685264587],"type":"Point"}
}