{
  "type": "Feature",
  "properties": {
    "addr:full":"416 Maple St Nelson BC V1L 2J5",
    "addr:housenumber":"416",
    "addr:postcode":"bc v1l 2j5",
    "addr:street":"Maple St",
    "iso:country":"CA",
    "sg:address":"416 Maple St",
    "sg:city":"Nelson",
    "sg:classifiers":[
        {
            "category":"Wholesale",
            "subcategory":"Electrical",
            "type":"Manufacturing & Wholesale Goods"
        }
    ],
    "sg:phone":"+1 250 352 3464",
    "sg:postcode":"V1L 2J5",
    "sg:province":"BC",
    "sg:tags":[
        "fire",
        "equipment",
        "protection"
    ],
    "wof:name":"West Kootenay Fire Safety Ltd",
    "wof:placetype":"venue"
},
  "geometry": {"coordinates":[-117.282608,49.501373],"type":"Point"}
}