{
  "type": "Feature",
  "properties": {
    "iso:country":"CA",
    "sg:address":"9001 Boul DE L'Acadie",
    "sg:city":"Montreal",
    "sg:classifiers":[
        {
            "category":"Recreation",
            "type":"Entertainment"
        }
    ],
    "sg:phone":"+1 514 858 5611",
    "sg:postcode":"H4N 3K1",
    "sg:province":"QC",
    "sg:tags":[
        "club",
        "bridge"
    ],
    "wof:name":"Mirage Club DE Bridge",
    "wof:placetype":"venue"
},
  "geometry": {"coordinates":[-73.3577804565,45.3339691162],"type":"Point"}
}