{
  "type": "Feature",
  "properties": {
    "addr:full":"North York ON M6A 1R8",
    "addr:postcode":"m6a 1r8",
    "iso:country":"CA",
    "sg:city":"North York",
    "sg:classifiers":[
        {
            "category":"Real Estate",
            "subcategory":"Real Estate Agent",
            "type":"Services"
        }
    ],
    "sg:phone":"+1 416 789 7128",
    "sg:postcode":"M6A 1R8",
    "sg:province":"ON",
    "sg:tags":[
        "loan"
    ],
    "wof:name":"Michael Fiorillo Real Estate",
    "wof:placetype":"venue"
},
  "geometry": {"coordinates":[-79.441498,43.725601],"type":"Point"}
}