{
  "type": "Feature",
  "properties": {
    "addr:full":"220 Wexford Rd Brampton ON L6Z 4N7",
    "addr:housenumber":"220",
    "addr:postcode":"l6z 4n7",
    "addr:street":"Wexford Rd",
    "iso:country":"CA",
    "sg:address":"220 Wexford Rd",
    "sg:city":"Brampton",
    "sg:classifiers":[
        {
            "category":"Retail",
            "subcategory":"Veterinary Services",
            "type":"Services"
        }
    ],
    "sg:phone":"+1 905 846 2332",
    "sg:postcode":"L6Z 4N7",
    "sg:province":"ON",
    "sg:tags":[
        "veterinarian"
    ],
    "wof:name":"Kennedy Road Veterinary Hosp",
    "wof:placetype":"venue"
},
  "geometry": {"coordinates":[-79.78227200000001,43.718727],"type":"Point"}
}