{
  "type": "Feature",
  "properties": {
    "addr:full":"11387 Boul Gouin O Roxboro QC H8Y 1X7",
    "addr:housenumber":"11387",
    "addr:postcode":"h8y 1x7",
    "addr:street":"Boul Gouin O",
    "iso:country":"CA",
    "sg:address":"11387 Boul Gouin O",
    "sg:city":"Roxboro",
    "sg:classifiers":[
        {
            "category":"Autos & Motor Vehicles",
            "subcategory":"Automobile Sales",
            "type":"Retail Goods"
        }
    ],
    "sg:phone":"+1 514 684 7000",
    "sg:postcode":"H8Y 1X7",
    "sg:province":"QC",
    "sg:tags":[
        "car",
        "dealer"
    ],
    "wof:name":"Premiere Auto",
    "wof:placetype":"venue"
},
  "geometry": {"coordinates":[-73.816406,45.510708],"type":"Point"}
}