{
  "type": "Feature",
  "properties": {
    "addr:full":"33 Rue Des Saules Amqui QC G5J 1Y8",
    "addr:housenumber":"33",
    "addr:postcode":"g5j 1y8",
    "addr:street":"Rue Des Saules",
    "iso:country":"CA",
    "sg:address":"33 Rue Des Saules",
    "sg:city":"Amqui",
    "sg:classifiers":[
        {
            "category":"Manufacturing",
            "subcategory":"Lumber",
            "type":"Manufacturing & Wholesale Goods"
        }
    ],
    "sg:phone":"+1 418 629 5413",
    "sg:postcode":"G5J 1Y8",
    "sg:province":"QC",
    "sg:tags":[
        "forester"
    ],
    "wof:name":"Entreprises Forestieres",
    "wof:placetype":"venue"
},
  "geometry": {"coordinates":[-67.446022,48.459763],"type":"Point"}
}