{
  "type": "Feature",
  "properties": {
    "addr:full":"200 1 Ave Dead Man's Flats AB T1W 2W4",
    "addr:housenumber":"200",
    "addr:postcode":"t1w 2w4",
    "addr:street":"1 Ave",
    "iso:country":"CA",
    "sg:address":"200 1 Ave",
    "sg:city":"Dead Man's Flats",
    "sg:classifiers":[
        {
            "category":"Restaurant",
            "type":"Food & Drink"
        }
    ],
    "sg:phone":"+1 403 678 4333",
    "sg:postcode":"T1W 2W4",
    "sg:province":"AB",
    "wof:name":"Deadman's Flats Husky House",
    "wof:placetype":"venue"
},
  "geometry": {"coordinates":[-115.001457,54.498371],"type":"Point"}
}