{
  "type": "Feature",
  "properties": {
    "addr:full":"634 Boul Hebert Saint-Pascal QC G0L 3Y0",
    "addr:housenumber":"634",
    "addr:postcode":"g0l 3y0",
    "addr:street":"Boul Hebert",
    "iso:country":"CA",
    "sg:address":"634 Boul Hebert",
    "sg:city":"Saint-Pascal",
    "sg:classifiers":[
        {
            "category":"Personal",
            "subcategory":"Beauty Salon",
            "type":"Services"
        }
    ],
    "sg:phone":"+1 418 492 1483",
    "sg:postcode":"G0L 3Y0",
    "sg:province":"QC",
    "wof:name":"Salon D'Esthetique Au Teint",
    "wof:placetype":"venue"
},
  "geometry": {"coordinates":[-69.7968673706,47.5282363892],"type":"Point"}
}