{
  "type": "Feature",
  "properties": {
    "iso:country":"CA",
    "sg:address":"1001 Boul Mont-Royal",
    "sg:city":"Outremont",
    "sg:classifiers":[
        {
            "category":"Restaurant",
            "type":"Food & Drink"
        }
    ],
    "sg:phone":"+1 514 523 3670",
    "sg:postcode":"H2V 2H4",
    "sg:province":"QC",
    "wof:name":"Mont-Royal Hot Dog Inc",
    "wof:placetype":"venue"
},
  "geometry": {"coordinates":[-73.590942,45.515263],"type":"Point"}
}