{
  "type": "Feature",
  "properties": {
    "addr:full":"10 Lockview Rd Fall River NS B2T 1J1",
    "addr:housenumber":"10",
    "addr:postcode":"b2t 1j1",
    "addr:street":"Lockview Rd",
    "iso:country":"CA",
    "sg:address":"10 Lockview Rd",
    "sg:city":"Fall River",
    "sg:classifiers":[
        {
            "category":"Education",
            "subcategory":"School",
            "type":"Public Place"
        }
    ],
    "sg:phone":"+1 902 860 4163",
    "sg:postcode":"B2T 1J1",
    "sg:province":"NS",
    "wof:name":"Ash Lee Jefferson School",
    "wof:placetype":"venue"
},
  "geometry": {"coordinates":[-63.616032,44.817711],"type":"Point"}
}