{
  "type": "Feature",
  "properties": {
    "addr:full":"10166 114 St NW Edmonton AB T5K 1R7",
    "addr:housenumber":"10166",
    "addr:postcode":"t5k 1r7",
    "addr:street":"114 St Nw",
    "iso:country":"CA",
    "sg:address":"10166 114 St NW",
    "sg:city":"Edmonton",
    "sg:classifiers":[
        {
            "category":"Restaurant",
            "type":"Food & Drink"
        }
    ],
    "sg:phone":"+1 780 488 4841",
    "sg:postcode":"T5K 1R7",
    "sg:province":"AB",
    "sg:tags":[
        "club",
        "night"
    ],
    "wof:name":"Gas Pump Night Club & Bar",
    "wof:placetype":"venue"
},
  "geometry": {"coordinates":[-113.517868042,53.5422554016],"type":"Point"}
}