{
  "type": "Feature",
  "properties": {
    "addr:full":"671 Rue Notre-Dame St-Barnabe-Nord QC G0X 2K0",
    "addr:housenumber":"671",
    "addr:postcode":"g0x 2k0",
    "addr:street":"Rue Notre-Dame St-Barnabe-Nord",
    "iso:country":"CA",
    "sg:address":"671 Rue Notre-Dame",
    "sg:city":"St-Barnabe-Nord",
    "sg:classifiers":[
        {
            "category":"Manufacturing",
            "subcategory":"Metals",
            "type":"Manufacturing & Wholesale Goods"
        }
    ],
    "sg:phone":"+1 819 221 3014",
    "sg:postcode":"G0X 2K0",
    "sg:province":"QC",
    "sg:tags":[
        "solder"
    ],
    "wof:name":"Metaux Ouvres Inc",
    "wof:placetype":"venue"
},
  "geometry": {"coordinates":[-72.88002,46.393902],"type":"Point"}
}