{
  "type": "Feature",
  "properties": {
    "addr:full":"North York ON M3N 1A3",
    "addr:postcode":"m3n 1a3",
    "iso:country":"CA",
    "sg:city":"North York",
    "sg:classifiers":[
        {
            "category":"Real Estate",
            "subcategory":"Real Estate Operator",
            "type":"Services"
        }
    ],
    "sg:phone":"+1 416 742 2225",
    "sg:postcode":"M3N 1A3",
    "sg:province":"ON",
    "sg:tags":[
        "apartment"
    ],
    "wof:name":"LA Fayette Apt",
    "wof:placetype":"venue"
},
  "geometry": {"coordinates":[-79.5163574219,43.738822937],"type":"Point"}
}