{
  "type": "Feature",
  "properties": {
    "iso:country":"CA",
    "sg:address":"318 11 Ave SE",
    "sg:city":"Calgary",
    "sg:classifiers":[
        {
            "category":"Home & Garden",
            "subcategory":"Hardware",
            "type":"Retail Goods"
        }
    ],
    "sg:phone":"+1 403 262 6994",
    "sg:postcode":"T2G 0Y2",
    "sg:province":"AB",
    "wof:name":"Ribtor Sales",
    "wof:placetype":"venue"
},
  "geometry": {"coordinates":[-114.05770874,51.0423278809],"type":"Point"}
}