{
  "type": "Feature",
  "properties": {
    "iso:country":"CA",
    "sg:address":"Armanda St",
    "sg:city":"Vanguard",
    "sg:classifiers":[
        {
            "category":"Wholesale",
            "subcategory":"Meat",
            "type":"Manufacturing & Wholesale Goods"
        }
    ],
    "sg:phone":"+1 306 582 2211",
    "sg:postcode":"S0N 2V0",
    "sg:province":"SK",
    "sg:tags":[
        "packer"
    ],
    "wof:name":"Whiska Creek Abattoir Ltd",
    "wof:placetype":"venue"
},
  "geometry": {"coordinates":[-107.300987244,49.905128479],"type":"Point"}
}