{
  "type": "Feature",
  "properties": {
    "addr:full":"30 Boudrie Rd Frankford ON K0K 2C0",
    "addr:housenumber":"30",
    "addr:postcode":"k0k 2c0",
    "addr:street":"Boudrie Rd",
    "iso:country":"CA",
    "sg:address":"30 Boudrie Rd",
    "sg:city":"Frankford",
    "sg:classifiers":[
        {
            "category":"Social Services",
            "subcategory":"Child Care",
            "type":"Services"
        }
    ],
    "sg:phone":"+1 613 398 8659",
    "sg:postcode":"K0K 2C0",
    "sg:province":"ON",
    "sg:tags":[
        "school"
    ],
    "wof:name":"Quinte Montessori School",
    "wof:placetype":"venue"
},
  "geometry": {"coordinates":[-77.621208,44.210888],"type":"Point"}
}