{
  "type": "Feature",
  "properties": {
    "addr:full":"175 Tower St Beaconsfield QC H9W 5T3",
    "addr:housenumber":"175",
    "addr:postcode":"h9w 5t3",
    "addr:street":"Tower St",
    "iso:country":"CA",
    "sg:address":"175 Tower St",
    "sg:city":"Beaconsfield",
    "sg:classifiers":[
        {
            "category":"Retail",
            "subcategory":"Auto Rental",
            "type":"Services"
        }
    ],
    "sg:phone":"+1 514 695 3805",
    "sg:postcode":"H9W 5T3",
    "sg:province":"QC",
    "sg:tags":[
        "renting",
        "truck",
        "leasing"
    ],
    "wof:name":"Pac Lease Truck Rental",
    "wof:placetype":"venue"
},
  "geometry": {"coordinates":[-73.874413,45.431438],"type":"Point"}
}