{
  "type": "Feature",
  "properties": {
    "addr:full":"54 Rue Tremblay Petit-Saguenay QC G0V 1N0",
    "addr:housenumber":"54",
    "addr:postcode":"g0v 1n0",
    "addr:street":"Rue Tremblay",
    "iso:country":"CA",
    "sg:address":"54 Rue Tremblay",
    "sg:city":"Petit-Saguenay",
    "sg:classifiers":[
        {
            "category":"Education",
            "subcategory":"School",
            "type":"Public Place"
        }
    ],
    "sg:phone":"+1 418 272 2933",
    "sg:postcode":"G0V 1N0",
    "sg:province":"QC",
    "wof:name":"Ecole Du Vallon",
    "wof:placetype":"venue"
},
  "geometry": {"coordinates":[-70.072716,48.214344],"type":"Point"}
}