{
  "type": "Feature",
  "properties": {
    "addr:full":"1102 Winnipeg Ave Winnipeg MB R3E 0S3",
    "addr:housenumber":"1102",
    "addr:postcode":"r3e 0s3",
    "addr:street":"Winnipeg Ave",
    "iso:country":"CA",
    "sg:address":"1102 Winnipeg Ave",
    "sg:city":"Winnipeg",
    "sg:classifiers":[
        {
            "category":"Building & Trades",
            "subcategory":"Cleaning & Sanitation",
            "type":"Services"
        }
    ],
    "sg:phone":"+1 204 786 7070",
    "sg:postcode":"R3E 0S3",
    "sg:province":"MB",
    "sg:tags":[
        "janitor"
    ],
    "wof:name":"Villa Cleaning Svc",
    "wof:placetype":"venue"
},
  "geometry": {"coordinates":[-97.174294,49.906895],"type":"Point"}
}