{
  "type": "Feature",
  "properties": {
    "addr:full":"700 Markham Rd Scarborough ON M1H 2A7",
    "addr:housenumber":"700",
    "addr:postcode":"m1h 2a7",
    "addr:street":"Markham Rd",
    "iso:country":"CA",
    "sg:address":"700 Markham Rd",
    "sg:city":"Scarborough",
    "sg:classifiers":[
        {
            "category":"Retail",
            "subcategory":"Veterinary Services",
            "type":"Services"
        }
    ],
    "sg:phone":"+1 416 439 0299",
    "sg:postcode":"M1H 2A7",
    "sg:province":"ON",
    "sg:tags":[
        "veterinarian"
    ],
    "wof:name":"Cedarbrae Animal Clinic",
    "wof:placetype":"venue"
},
  "geometry": {"coordinates":[-79.22631800000001,43.761898],"type":"Point"}
}