{
  "type": "Feature",
  "properties": {
    "addr:full":"Victoria BC V8V 3N1",
    "addr:postcode":"v8v 3n1",
    "iso:country":"CA",
    "sg:city":"Victoria",
    "sg:classifiers":[
        {
            "category":"Personal",
            "type":"Services"
        }
    ],
    "sg:phone":"+1 250 382 5577",
    "sg:postcode":"V8V 3N1",
    "sg:province":"BC",
    "sg:tags":[
        "therapist",
        "massage"
    ],
    "wof:name":"Dayman, Barry",
    "wof:placetype":"venue"
},
  "geometry": {"coordinates":[-123.352608,48.424858],"type":"Point"}
}