{
  "type": "Feature",
  "properties": {
    "addr:full":"Brampton ON L6V 1B2",
    "addr:postcode":"l6v 1b2",
    "iso:country":"CA",
    "sg:city":"Brampton",
    "sg:classifiers":[
        {
            "category":"Professional",
            "subcategory":"Lawyer & Legal Services",
            "type":"Services"
        }
    ],
    "sg:phone":"+1 905 459 6160",
    "sg:postcode":"L6V 1B2",
    "sg:province":"ON",
    "sg:tags":[
        "attorney"
    ],
    "wof:name":"Furlan, Daniel R",
    "wof:placetype":"venue"
},
  "geometry": {"coordinates":[-79.7547531128,43.6909942627],"type":"Point"}
}