{
  "type": "Feature",
  "properties": {
    "addr:full":"316 Wellington St E Sault Ste Marie ON P6A 2L9",
    "addr:housenumber":"316",
    "addr:postcode":"p6a 2l9",
    "addr:street":"Wellington St E",
    "iso:country":"CA",
    "sg:address":"316 Wellington St E",
    "sg:city":"Sault Ste Marie",
    "sg:classifiers":[
        {
            "category":"Retail",
            "subcategory":"Portrait Studio",
            "type":"Services"
        }
    ],
    "sg:phone":"+1 705 256 2826",
    "sg:postcode":"P6A 2L9",
    "sg:province":"ON",
    "sg:tags":[
        "photo",
        "finishing"
    ],
    "wof:name":"Cln Colour Factory",
    "wof:placetype":"venue"
},
  "geometry": {"coordinates":[-84.33266448969999,46.5153083801],"type":"Point"}
}