{
  "type": "Feature",
  "properties": {
    "addr:full":"5 Av Du Parc Sainte-Clotilde-DE-Beauce QC G0N 1C0",
    "addr:postcode":"g0n 1c0",
    "addr:street":"Av Du Parc",
    "iso:country":"CA",
    "sg:address":"5 Av Du Parc",
    "sg:city":"Sainte-Clotilde-DE-Beauce",
    "sg:classifiers":[
        {
            "category":"Manufacturing",
            "subcategory":"Glass & Minerals",
            "type":"Manufacturing & Wholesale Goods"
        }
    ],
    "sg:phone":"+1 418 427 2132",
    "sg:postcode":"G0N 1C0",
    "sg:province":"QC",
    "sg:tags":[
        "fabricator",
        "fiber"
    ],
    "wof:name":"Compositech Inc",
    "wof:placetype":"venue"
},
  "geometry": {"coordinates":[-71.033821,46.129402],"type":"Point"}
}