{
  "type": "Feature",
  "properties": {
    "addr:full":"36 Rue Principale Saint-Leonard-D'Aston QC J0C 1M0",
    "addr:housenumber":"36",
    "addr:postcode":"j0c 1m0",
    "addr:street":"Rue Principale",
    "iso:country":"CA",
    "sg:address":"36 Rue Principale",
    "sg:city":"Saint-Leonard-D'Aston",
    "sg:classifiers":[
        {
            "category":"Retail",
            "subcategory":"Repair Shop",
            "type":"Services"
        }
    ],
    "sg:phone":"+1 819 399 3535",
    "sg:postcode":"J0C 1M0",
    "sg:province":"QC",
    "sg:tags":[
        "jewelry"
    ],
    "wof:name":"Bijouterie AR",
    "wof:placetype":"venue"
},
  "geometry": {"coordinates":[-68.13432312010001,48.4621658325],"type":"Point"}
}