{
  "type": "Feature",
  "properties": {
    "addr:full":"PO Box 297 Coronation AB T0C 1C0",
    "addr:housenumber":"po;297;ab",
    "addr:postcode":"t0c 1c0",
    "addr:street":"Box;Coronation",
    "iso:country":"CA",
    "sg:address":"PO Box 297",
    "sg:city":"Coronation",
    "sg:classifiers":[
        {
            "category":"Freight",
            "type":"Transportation"
        }
    ],
    "sg:phone":"+1 403 578 4137",
    "sg:postcode":"T0C 1C0",
    "sg:province":"AB",
    "sg:tags":[
        "trucking"
    ],
    "wof:name":"Goulet Trucking Ltd",
    "wof:placetype":"venue"
},
  "geometry": {"coordinates":[-111.44655609100001,52.0909194946],"type":"Point"}
}