{
  "type": "Feature",
  "properties": {
    "addr:full":"56 Mary St Barrie ON L4N 1T1",
    "addr:housenumber":"56",
    "addr:postcode":"l4n 1t1",
    "addr:street":"Mary St",
    "iso:country":"CA",
    "sg:address":"56 Mary St",
    "sg:city":"Barrie",
    "sg:classifiers":[
        {
            "category":"Professional",
            "subcategory":"Accounting & Tax Preparation",
            "type":"Services"
        }
    ],
    "sg:phone":"+1 705 722 6610",
    "sg:postcode":"L4N 1T1",
    "sg:province":"ON",
    "sg:tags":[
        "accountant"
    ],
    "wof:name":"Skjelmose, J William CA",
    "wof:placetype":"venue"
},
  "geometry": {"coordinates":[-79.6930236816,44.3888168335],"type":"Point"}
}