{
  "type": "Feature",
  "properties": {
    "iso:country":"CA",
    "sg:address":"11140 109 St NW",
    "sg:city":"Edmonton",
    "sg:classifiers":[
        {
            "category":"Government",
            "subcategory":"Police Station",
            "type":"Public Place"
        }
    ],
    "sg:phone":"+1 780 412 5424",
    "sg:postcode":"T5G 2T4",
    "sg:province":"AB",
    "sg:tags":[
        "department"
    ],
    "wof:name":"Royal Canadian Mounted Police",
    "wof:placetype":"venue"
},
  "geometry": {"coordinates":[-113.50865173299999,53.5597343445],"type":"Point"}
}