{
  "type": "Feature",
  "properties": {
    "addr:full":"1760 South Island Hwy Campbell River BC V9W 1B8",
    "addr:housenumber":"1760",
    "addr:postcode":"v9w 1b8",
    "addr:street":"South Island Hwy",
    "iso:country":"CA",
    "sg:address":"1760 South Island Hwy",
    "sg:city":"Campbell River",
    "sg:classifiers":[
        {
            "category":"Restaurant",
            "type":"Food & Drink"
        }
    ],
    "sg:phone":"+1 250 287 2777",
    "sg:postcode":"V9W 1B8",
    "sg:province":"BC",
    "sg:tags":[
        "pub"
    ],
    "wof:name":"Local Bar Grill & Patios",
    "wof:placetype":"venue"
},
  "geometry": {"coordinates":[-125.221313477,49.9778060913],"type":"Point"}
}