{
  "type": "Feature",
  "properties": {
    "addr:full":"9912 Lougheed Hwy Burnaby BC V3J 1N3",
    "addr:housenumber":"9912",
    "addr:postcode":"v3j 1n3",
    "addr:street":"Lougheed Hwy",
    "iso:country":"CA",
    "sg:address":"9912 Lougheed Hwy",
    "sg:city":"Burnaby",
    "sg:classifiers":[
        {
            "category":"Building & Trades",
            "subcategory":"Cleaning & Sanitation",
            "type":"Services"
        }
    ],
    "sg:phone":"+1 604 420 5237",
    "sg:postcode":"V3J 1N3",
    "sg:province":"BC",
    "sg:tags":[
        "janitor"
    ],
    "wof:name":"Janicorp",
    "wof:placetype":"venue"
},
  "geometry": {"coordinates":[-122.893913,49.246338],"type":"Point"}
}