{
  "type": "Feature",
  "properties": {
    "addr:full":"2556 Ch Du Lac Longueuil QC J4N 1G7",
    "addr:housenumber":"2556",
    "addr:postcode":"j4n 1g7",
    "addr:street":"Ch Du Lac",
    "iso:country":"CA",
    "sg:address":"2556 Ch Du Lac",
    "sg:city":"Longueuil",
    "sg:classifiers":[
        {
            "category":"Retail",
            "subcategory":"Auto Repair",
            "type":"Services"
        }
    ],
    "sg:phone":"+1 450 674 1555",
    "sg:postcode":"J4N 1G7",
    "sg:province":"QC",
    "sg:tags":[
        "body",
        "automobile",
        "painting"
    ],
    "wof:name":"Amelioration Carrosserie Gb",
    "wof:placetype":"venue"
},
  "geometry": {"coordinates":[-73.45594,45.565701],"type":"Point"}
}