{
  "type": "Feature",
  "properties": {
    "addr:full":"Oakville ON L6H 5V5",
    "addr:postcode":"l6h 5v5",
    "iso:country":"CA",
    "sg:city":"Oakville",
    "sg:classifiers":[
        {
            "category":"Wholesale",
            "subcategory":"Machinery & Supplies",
            "type":"Manufacturing & Wholesale Goods"
        }
    ],
    "sg:phone":"+1 905 829 5096",
    "sg:postcode":"L6H 5V5",
    "sg:province":"ON",
    "sg:tags":[
        "mill",
        "paper"
    ],
    "wof:name":"Glenco Products Inc",
    "wof:placetype":"venue"
},
  "geometry": {"coordinates":[-79.6730041504,43.5091056824],"type":"Point"}
}