{
  "type": "Feature",
  "properties": {
    "addr:full":"4720 Hwy 3 Chester Basin NS B0J 1K0",
    "addr:housenumber":"4720",
    "addr:postcode":"b0j 1k0",
    "addr:street":"Hwy 3",
    "iso:country":"CA",
    "sg:address":"4720 Hwy 3",
    "sg:city":"Chester Basin",
    "sg:classifiers":[
        {
            "category":"Professional",
            "subcategory":"Lawyer & Legal Services",
            "type":"Services"
        }
    ],
    "sg:phone":"+1 902 275 2155",
    "sg:postcode":"B0J 1K0",
    "sg:province":"NS",
    "sg:tags":[
        "attorney"
    ],
    "wof:name":"Preeper, Bruce J QC",
    "wof:placetype":"venue"
},
  "geometry": {"coordinates":[-64.302666,44.569592],"type":"Point"}
}