{
  "type": "Feature",
  "properties": {
    "addr:full":"30 Pineway Blvd North York ON M2H 1A1",
    "addr:housenumber":"30",
    "addr:postcode":"m2h 1a1",
    "addr:street":"Pineway Blvd",
    "iso:country":"CA",
    "sg:address":"30 Pineway Blvd",
    "sg:city":"North York",
    "sg:classifiers":[
        {
            "category":"Insurance",
            "subcategory":"Insurance Agent",
            "type":"Services"
        }
    ],
    "sg:phone":"+1 416 226 5131",
    "sg:postcode":"M2H 1A1",
    "sg:province":"ON",
    "wof:name":"Concord Insurance Brokers Ltd",
    "wof:placetype":"venue"
},
  "geometry": {"coordinates":[-79.3740386963,43.79164505],"type":"Point"}
}