{
  "type": "Feature",
  "properties": {
    "addr:full":"11250 Boul Saint-Jean-Baptiste Montreal QC H1B 4B4",
    "addr:housenumber":"11250",
    "addr:postcode":"h1b 4b4",
    "addr:street":"Boul Saint-Jean-Baptiste",
    "iso:country":"CA",
    "sg:address":"11250 Boul Saint-Jean-Baptiste",
    "sg:city":"Montreal",
    "sg:classifiers":[
        {
            "category":"Wholesale",
            "subcategory":"Auto Parts",
            "type":"Manufacturing & Wholesale Goods"
        }
    ],
    "sg:phone":"+1 514 648 2050",
    "sg:postcode":"H1B 4B4",
    "sg:province":"QC",
    "sg:tags":[
        "automobile",
        "rebuilt"
    ],
    "wof:name":"Rta Pieces D'Auto Usagees",
    "wof:placetype":"venue"
},
  "geometry": {"coordinates":[-73.536736,45.652786],"type":"Point"}
}