{
  "type": "Feature",
  "properties": {
    "addr:full":"55 Innes Ave Toronto ON M6E 1N1",
    "addr:housenumber":"55",
    "addr:postcode":"m6e 1n1",
    "addr:street":"Innes Ave",
    "iso:country":"CA",
    "sg:address":"55 Innes Ave",
    "sg:city":"Toronto",
    "sg:classifiers":[
        {
            "category":"Building & Trades",
            "subcategory":"Plumbing",
            "type":"Services"
        }
    ],
    "sg:phone":"+1 416 654 7078",
    "sg:postcode":"M6E 1N1",
    "sg:province":"ON",
    "sg:tags":[
        "refrigeration",
        "contractor"
    ],
    "wof:name":"Quinn Refrigeration Air Cond",
    "wof:placetype":"venue"
},
  "geometry": {"coordinates":[-79.457825,43.680729],"type":"Point"}
}