{
  "type": "Feature",
  "properties": {
    "addr:full":"160 Main St S Brampton ON L6W 2E1",
    "addr:housenumber":"160",
    "addr:postcode":"l6w 2e1",
    "addr:street":"Main St S",
    "iso:country":"CA",
    "sg:address":"160 Main St S",
    "sg:city":"Brampton",
    "sg:classifiers":[
        {
            "category":"Sports & Exercise",
            "subcategory":"Bowling",
            "type":"Entertainment"
        }
    ],
    "sg:phone":"+1 905 451 0340",
    "sg:postcode":"L6W 2E1",
    "sg:province":"ON",
    "sg:tags":[
        "center"
    ],
    "wof:name":"Crystal Bowl",
    "wof:placetype":"venue"
},
  "geometry": {"coordinates":[-79.7487487793,43.6777687073],"type":"Point"}
}