{
  "type": "Feature",
  "properties": {
    "addr:full":"2578 Finch Ave W North York ON M9M 2G3",
    "addr:housenumber":"2578",
    "addr:postcode":"m9m 2g3",
    "addr:street":"Finch Ave W",
    "iso:country":"CA",
    "sg:address":"2578 Finch Ave W",
    "sg:city":"North York",
    "sg:classifiers":[
        {
            "category":"Retail",
            "subcategory":"Laundry & Dry Cleaning",
            "type":"Services"
        }
    ],
    "sg:phone":"+1 416 741 2536",
    "sg:postcode":"M9M 2G3",
    "sg:province":"ON",
    "sg:tags":[
        "cleaners"
    ],
    "wof:name":"Finchdale Custom Cleaners",
    "wof:placetype":"venue"
},
  "geometry": {"coordinates":[-79.5615768433,43.748085022],"type":"Point"}
}