{
  "type": "Feature",
  "properties": {
    "addr:full":"44 Highland Dr Tide Head NB E3N 4L8",
    "addr:housenumber":"44",
    "addr:postcode":"e3n 4l8",
    "addr:street":"Highland Dr Tide",
    "iso:country":"CA",
    "sg:address":"44 Highland Dr",
    "sg:city":"Tide Head",
    "sg:classifiers":[
        {
            "category":"Wholesale",
            "subcategory":"Electrical",
            "type":"Manufacturing & Wholesale Goods"
        }
    ],
    "sg:phone":"+1 506 759 9941",
    "sg:postcode":"E3N 4L8",
    "sg:province":"NB",
    "sg:tags":[
        "fire",
        "equipment",
        "protection"
    ],
    "wof:name":"Campbellton-Dalhousie Stop Flm",
    "wof:placetype":"venue"
},
  "geometry": {"coordinates":[-66.77198,47.979485],"type":"Point"}
}