{
  "type": "Feature",
  "properties": {
    "iso:country":"CA",
    "sg:city":"Nakina",
    "sg:classifiers":[
        {
            "category":"Professional",
            "subcategory":"Management & Consulting",
            "type":"Services"
        }
    ],
    "sg:phone":"+1 807 329 8623",
    "sg:postcode":"P0T 2H0",
    "sg:province":"ON",
    "sg:tags":[
        "consultant",
        "business"
    ],
    "wof:name":"More Than Words",
    "wof:placetype":"venue"
},
  "geometry": {"coordinates":[-86.7165527344,50.1790618896],"type":"Point"}
}