{
  "type": "Feature",
  "properties": {
    "addr:full":"214 Kent St Charlottetown PE C1A 1P2",
    "addr:housenumber":"214",
    "addr:postcode":"c1a 1p2",
    "addr:street":"Kent St",
    "iso:country":"CA",
    "sg:address":"214 Kent St",
    "sg:city":"Charlottetown",
    "sg:classifiers":[
        {
            "category":"Health Services",
            "subcategory":"Nursing And Care Facility",
            "type":"Services"
        }
    ],
    "sg:phone":"+1 902 628 8228",
    "sg:postcode":"C1A 1P2",
    "sg:province":"PE",
    "sg:tags":[
        "home",
        "rest",
        "community"
    ],
    "wof:name":"Langille House",
    "wof:placetype":"venue"
},
  "geometry": {"coordinates":[-63.125153,46.237583],"type":"Point"}
}