{
  "type": "Feature",
  "properties": {
    "addr:full":"Edmonton AB T5R 1B6",
    "addr:postcode":"t5r 1b6",
    "iso:country":"CA",
    "sg:city":"Edmonton",
    "sg:classifiers":[
        {
            "category":"Wholesale",
            "subcategory":"Non-durable Goods",
            "type":"Manufacturing & Wholesale Goods"
        }
    ],
    "sg:phone":"+1 780 489 8810",
    "sg:postcode":"T5R 1B6",
    "sg:province":"AB",
    "wof:name":"David E Jerke Sales",
    "wof:placetype":"venue"
},
  "geometry": {"coordinates":[-113.578231812,53.5205078125],"type":"Point"}
}