{
  "type": "Feature",
  "properties": {
    "addr:full":"415 Rue Saint-Gabriel Montreal QC H2Y 3A1",
    "addr:housenumber":"415",
    "addr:postcode":"h2y 3a1",
    "addr:street":"Rue Saint-Gabriel",
    "iso:country":"CA",
    "sg:address":"415 Rue Saint-Gabriel",
    "sg:city":"Montreal",
    "sg:classifiers":[
        {
            "category":"Professional",
            "subcategory":"Art Services",
            "type":"Services"
        }
    ],
    "sg:phone":"+1 514 861 1965",
    "sg:postcode":"H2Y 3A1",
    "sg:province":"QC",
    "sg:tags":[
        "graphic",
        "designer"
    ],
    "wof:name":"Logos Design Inc",
    "wof:placetype":"venue"
},
  "geometry": {"coordinates":[-73.5535354614,45.5064506531],"type":"Point"}
}