{
  "type": "Feature",
  "properties": {
    "addr:full":"43 Kenmount Rd St. John's NL A1B 1W1",
    "addr:housenumber":"43",
    "addr:postcode":"a1b 1w1",
    "addr:street":"Kenmount Rd",
    "iso:country":"CA",
    "sg:address":"43 Kenmount Rd",
    "sg:city":"St. John's",
    "sg:classifiers":[
        {
            "category":"Organizations",
            "subcategory":"Religious Organization",
            "type":"Services"
        }
    ],
    "sg:phone":"+1 709 726 8242",
    "sg:postcode":"A1B 1W1",
    "sg:province":"NL",
    "sg:tags":[
        "church"
    ],
    "wof:name":"Faith Bible Chapel",
    "wof:placetype":"venue"
},
  "geometry": {"coordinates":[-52.7514419556,47.559173584],"type":"Point"}
}