{
  "type": "Feature",
  "properties": {
    "addr:full":"620 Dennis St Brandon MB R7A 5E7",
    "addr:housenumber":"620",
    "addr:postcode":"r7a 5e7",
    "addr:street":"Dennis St",
    "iso:country":"CA",
    "sg:address":"620 Dennis St",
    "sg:city":"Brandon",
    "sg:classifiers":[
        {
            "category":"Health Services",
            "subcategory":"Doctor",
            "type":"Services"
        }
    ],
    "sg:phone":"+1 204 728 4440",
    "sg:postcode":"R7A 5E7",
    "sg:province":"MB",
    "sg:tags":[
        "physician",
        "surgeon"
    ],
    "wof:name":"Turabian, M B MD",
    "wof:placetype":"venue"
},
  "geometry": {"coordinates":[-99.937866,49.840214],"type":"Point"}
}