{
  "type": "Feature",
  "properties": {
    "addr:full":"719 Main St Pincher Creek AB T0K 1W0",
    "addr:housenumber":"719",
    "addr:postcode":"t0k 1w0",
    "addr:street":"Main St",
    "iso:country":"CA",
    "sg:address":"719 Main St",
    "sg:city":"Pincher Creek",
    "sg:classifiers":[
        {
            "category":"Home & Garden",
            "subcategory":"Furniture",
            "type":"Retail Goods"
        }
    ],
    "sg:phone":"+1 403 627 2211",
    "sg:postcode":"T0K 1W0",
    "sg:province":"AB",
    "sg:tags":[
        "kitchen",
        "accessory"
    ],
    "wof:name":"Walking Ducks Inc",
    "wof:placetype":"venue"
},
  "geometry": {"coordinates":[-113.948730469,49.485786438],"type":"Point"}
}