{
  "type": "Feature",
  "properties": {
    "addr:full":"650 Pearson College Dr Victoria BC V9C 4H7",
    "addr:housenumber":"650",
    "addr:postcode":"bc v9c 4h7",
    "addr:street":"Pearson College Dr",
    "iso:country":"CA",
    "sg:address":"650 Pearson College Dr",
    "sg:city":"Victoria",
    "sg:classifiers":[
        {
            "category":"Education",
            "subcategory":"College",
            "type":"Public Place"
        }
    ],
    "sg:phone":"+1 250 391 2411",
    "sg:postcode":"V9C 4H7",
    "sg:province":"BC",
    "sg:tags":[
        "academic",
        "school"
    ],
    "wof:name":"Lester B Pearson College",
    "wof:placetype":"venue"
},
  "geometry": {"coordinates":[-123.36451700000001,48.428314],"type":"Point"}
}