{
  "type": "Feature",
  "properties": {
    "addr:full":"PO Box 1133 STN M Calgary AB T2P 2K9",
    "addr:housenumber":"po",
    "addr:postcode":"t2p 2k9",
    "addr:street":"Box 1133 Stn M",
    "iso:country":"CA",
    "sg:address":"PO Box 1133 STN M",
    "sg:city":"Calgary",
    "sg:classifiers":[
        {
            "category":"Organizations",
            "subcategory":"Professional Association",
            "type":"Services"
        }
    ],
    "sg:phone":"+1 403 266 2799",
    "sg:postcode":"T2P 2K9",
    "sg:province":"AB",
    "wof:name":"China Canada Business Assn",
    "wof:placetype":"venue"
},
  "geometry": {"coordinates":[-114.063194275,51.0450744629],"type":"Point"}
}