{
  "type": "Feature",
  "properties": {
    "addr:full":"5126 50 Ave Barrhead AB T7N 1L1",
    "addr:housenumber":"5126",
    "addr:postcode":"t7n 1l1",
    "addr:street":"50 Ave",
    "iso:country":"CA",
    "sg:address":"5126 50 Ave",
    "sg:city":"Barrhead",
    "sg:classifiers":[
        {
            "category":"Personal",
            "subcategory":"Beauty Salon",
            "type":"Services"
        }
    ],
    "sg:phone":"+1 780 674 2488",
    "sg:postcode":"T7N 1L1",
    "sg:province":"AB",
    "wof:name":"Wil's His & Hers Hairstyling",
    "wof:placetype":"venue"
},
  "geometry": {"coordinates":[-114.406906128,54.1196594238],"type":"Point"}
}