{
  "type": "Feature",
  "properties": {
    "iso:country":"CA",
    "sg:city":"Langley",
    "sg:classifiers":[
        {
            "category":"Organizations",
            "subcategory":"Professional Association",
            "type":"Services"
        }
    ],
    "sg:phone":"+1 604 514 3525",
    "sg:postcode":"V3A 6S7",
    "sg:province":"BC",
    "wof:name":"Horse Protection Society-BC",
    "wof:placetype":"venue"
},
  "geometry": {"coordinates":[-122.657051086,49.0987052917],"type":"Point"}
}