{
  "type": "Feature",
  "properties": {
    "addr:full":"Calgary AB T2A 6K3",
    "addr:postcode":"t2a 6k3",
    "iso:country":"CA",
    "sg:city":"Calgary",
    "sg:classifiers":[
        {
            "category":"Professional",
            "subcategory":"Accounting & Tax Preparation",
            "type":"Services"
        }
    ],
    "sg:phone":"+1 403 235 1400",
    "sg:postcode":"T2A 6K3",
    "sg:province":"AB",
    "sg:tags":[
        "accountant"
    ],
    "wof:name":"Layton & Assoc Inc",
    "wof:placetype":"venue"
},
  "geometry": {"coordinates":[-113.98221599999999,51.05584],"type":"Point"}
}