{
  "type": "Feature",
  "properties": {
    "addr:full":"7175 Boul Wilfrid-Hamel Sainte-Foy QC G2G 1B6",
    "addr:housenumber":"7175",
    "addr:postcode":"g2g 1b6",
    "addr:street":"Boul Wilfrid-Hamel",
    "iso:country":"CA",
    "sg:address":"7175 Boul Wilfrid-Hamel",
    "sg:city":"Sainte-Foy",
    "sg:classifiers":[
        {
            "category":"Sports & Exercise",
            "subcategory":"Gym",
            "type":"Entertainment"
        }
    ],
    "sg:phone":"+1 418 872 3020",
    "sg:postcode":"G2G 1B6",
    "sg:province":"QC",
    "sg:tags":[
        "club",
        "health",
        "studio",
        "gymnasium"
    ],
    "wof:name":"Club Action",
    "wof:placetype":"venue"
},
  "geometry": {"coordinates":[-71.361542,46.784447],"type":"Point"}
}