{
  "type": "Feature",
  "properties": {
    "iso:country":"CA",
    "sg:address":"470 Second Dughill Rd",
    "sg:city":"Trenton",
    "sg:classifiers":[
        {
            "category":"Retail",
            "subcategory":"Portrait Studio",
            "type":"Services"
        }
    ],
    "sg:phone":"+1 613 394 4744",
    "sg:postcode":"K8V 5P4",
    "sg:province":"ON",
    "sg:tags":[
        "photographer"
    ],
    "wof:name":"Pca Intl",
    "wof:placetype":"venue"
},
  "geometry": {"coordinates":[-77.5763092041,44.1011390686],"type":"Point"}
}