{
  "type": "Feature",
  "properties": {
    "addr:full":"170 Lintens Rd Port Severn ON L0K 1S0",
    "addr:housenumber":"170",
    "addr:postcode":"l0k 1s0",
    "addr:street":"Lintens Rd",
    "iso:country":"CA",
    "sg:address":"170 Lintens Rd",
    "sg:city":"Port Severn",
    "sg:classifiers":[
        {
            "category":"Travel",
            "subcategory":"Hotels & Motels",
            "type":"Entertainment"
        }
    ],
    "sg:phone":"+1 705 756 2610",
    "sg:postcode":"L0K 1S0",
    "sg:province":"ON",
    "sg:tags":[
        "cottage",
        "cabin"
    ],
    "wof:name":"South Bay Cottages",
    "wof:placetype":"venue"
},
  "geometry": {"coordinates":[-79.44055175779999,44.6300849915],"type":"Point"}
}