{
  "type": "Feature",
  "properties": {
    "iso:country":"CA",
    "sg:address":"151 2nd St NW",
    "sg:city":"Glenwood",
    "sg:classifiers":[
        {
            "category":"Education",
            "subcategory":"School",
            "type":"Public Place"
        }
    ],
    "sg:phone":"+1 403 626 3611",
    "sg:postcode":"T0K 2R0",
    "sg:province":"AB",
    "wof:name":"Glenwood School",
    "wof:placetype":"venue"
},
  "geometry": {"coordinates":[-113.515090942,49.3673782349],"type":"Point"}
}