{
  "type": "Feature",
  "properties": {
    "addr:full":"8140 Saunders Rd Richmond BC V7A 2A5",
    "addr:housenumber":"8140",
    "addr:postcode":"v7a 2a5",
    "addr:street":"Saunders Rd",
    "iso:country":"CA",
    "sg:address":"8140 Saunders Rd",
    "sg:city":"Richmond",
    "sg:classifiers":[
        {
            "category":"Organizations",
            "subcategory":"Religious Organization",
            "type":"Services"
        }
    ],
    "sg:phone":"+1 604 277 8012",
    "sg:postcode":"V7A 2A5",
    "sg:province":"BC",
    "sg:tags":[
        "church"
    ],
    "wof:name":"Broadmoor Baptist Church",
    "wof:placetype":"venue"
},
  "geometry": {"coordinates":[-123.13453699999999,49.143475],"type":"Point"}
}