{
  "type": "Feature",
  "properties": {
    "addr:full":"61 Boul Gagne Sacre-Coeur-Saguenay QC G0T 1Y0",
    "addr:housenumber":"61",
    "addr:postcode":"g0t 1y0",
    "addr:street":"Boul Gagne Sacre-Coeur-Saguenay",
    "iso:country":"CA",
    "sg:address":"61 Boul Gagne",
    "sg:city":"Sacre-Coeur-Saguenay",
    "sg:classifiers":[
        {
            "category":"Freight",
            "type":"Transportation"
        }
    ],
    "sg:phone":"+1 418 236 9263",
    "sg:postcode":"G0T 1Y0",
    "sg:province":"QC",
    "sg:tags":[
        "trucking"
    ],
    "wof:name":"Dufour Transport",
    "wof:placetype":"venue"
},
  "geometry": {"coordinates":[-69.79869100000001,48.229855],"type":"Point"}
}