{
  "type": "Feature",
  "properties": {
    "iso:country":"CA",
    "sg:city":"Aurora",
    "sg:classifiers":[
        {
            "category":"Shopping",
            "subcategory":"Jewelry",
            "type":"Retail Goods"
        }
    ],
    "sg:phone":"+1 905 727 0056",
    "sg:postcode":"L4G 1M5",
    "sg:province":"ON",
    "sg:tags":[
        "jeweler"
    ],
    "wof:name":"Lapis Lazuli Jewellers",
    "wof:placetype":"venue"
},
  "geometry": {"coordinates":[-79.46593475340001,43.9936637878],"type":"Point"}
}