{
  "type": "Feature",
  "properties": {
    "addr:full":"4825 15A Ave NW Edmonton AB T6L 6H8",
    "addr:housenumber":"4825",
    "addr:postcode":"t6l 6h8",
    "addr:street":"15A Ave Nw",
    "iso:country":"CA",
    "sg:address":"4825 15A Ave NW",
    "sg:city":"Edmonton",
    "sg:classifiers":[
        {
            "category":"Building & Trades",
            "subcategory":"Cleaning & Sanitation",
            "type":"Services"
        }
    ],
    "sg:phone":"+1 780 463 6284",
    "sg:postcode":"T6L 6H8",
    "sg:province":"AB",
    "sg:tags":[
        "equipment"
    ],
    "wof:name":"Hydro Blast Ltd",
    "wof:placetype":"venue"
},
  "geometry": {"coordinates":[-113.41520690900001,53.444896698],"type":"Point"}
}