{
  "type": "Feature",
  "properties": {
    "addr:full":"491 Queensway W Simcoe ON N3Y 4R5",
    "addr:housenumber":"491",
    "addr:postcode":"n3y 4r5",
    "addr:street":"Queensway W",
    "iso:country":"CA",
    "sg:address":"491 Queensway W",
    "sg:city":"Simcoe",
    "sg:classifiers":[
        {
            "category":"Professional",
            "subcategory":"Business Services",
            "type":"Services"
        }
    ],
    "sg:phone":"+1 519 426 3920",
    "sg:postcode":"N3Y 4R5",
    "sg:province":"ON",
    "sg:tags":[
        "pool",
        "swimming"
    ],
    "wof:name":"Edgil Pool Svc Ltd",
    "wof:placetype":"venue"
},
  "geometry": {"coordinates":[-80.328316,42.841324],"type":"Point"}
}