{
  "type": "Feature",
  "properties": {
    "iso:country":"CA",
    "sg:address":"321 Ch Saint-Louis",
    "sg:city":"Beauharnois",
    "sg:classifiers":[
        {
            "category":"Food & Beverages",
            "subcategory":"Groceries & Convenience Stores",
            "type":"Retail Goods"
        }
    ],
    "sg:phone":"+1 450 429 2572",
    "sg:postcode":"J6N 2J8",
    "sg:province":"QC",
    "sg:tags":[
        "grocer"
    ],
    "wof:name":"Depanneur Beauharnois Inc",
    "wof:placetype":"venue"
},
  "geometry": {"coordinates":[-73.879875,45.30558],"type":"Point"}
}