{
  "type": "Feature",
  "properties": {
    "addr:full":"113 Smith St E Yorkton SK S3N 0H8",
    "addr:housenumber":"113",
    "addr:postcode":"s3n 0h8",
    "addr:street":"Smith St E",
    "iso:country":"CA",
    "sg:address":"113 Smith St E",
    "sg:city":"Yorkton",
    "sg:classifiers":[
        {
            "category":"Shopping",
            "subcategory":"Florist",
            "type":"Retail Goods"
        }
    ],
    "sg:phone":"+1 306 786 7673",
    "sg:postcode":"S3N 0H8",
    "sg:province":"SK",
    "wof:name":"Grower Direct Fresh Cut Flwrs",
    "wof:placetype":"venue"
},
  "geometry": {"coordinates":[-102.45549800000001,51.212345],"type":"Point"}
}