{
  "type": "Feature",
  "properties": {
    "addr:full":"Saskatoon SK S7K 5X2",
    "addr:postcode":"s7k 5x2",
    "iso:country":"CA",
    "sg:city":"Saskatoon",
    "sg:classifiers":[
        {
            "category":"Professional",
            "subcategory":"Lawyer & Legal Services",
            "type":"Services"
        }
    ],
    "sg:phone":"+1 306 933 0004",
    "sg:postcode":"S7K 5X2",
    "sg:province":"SK",
    "sg:tags":[
        "attorney"
    ],
    "wof:name":"Connick, Erin A",
    "wof:placetype":"venue"
},
  "geometry": {"coordinates":[-106.660828,52.127804],"type":"Point"}
}