{
  "type": "Feature",
  "properties": {
    "addr:full":"1420 Rue Du Sud Cowansville QC J2K 2Y8",
    "addr:housenumber":"1420",
    "addr:postcode":"j2k 2y8",
    "addr:street":"Rue Du Sud",
    "iso:country":"CA",
    "sg:address":"1420 Rue Du Sud",
    "sg:city":"Cowansville",
    "sg:phone":"+1 450 266 9999",
    "sg:postcode":"J2K 2Y8",
    "sg:province":"QC",
    "sg:tags":[
        "equipment",
        "supply"
    ],
    "wof:name":"Equipements DE Restaurant",
    "wof:placetype":"venue"
},
  "geometry": {"coordinates":[-72.7520370483,45.1943778992],"type":"Point"}
}