{
  "type": "Feature",
  "properties": {
    "addr:full":"Scarborough ON M1H 1B3",
    "addr:postcode":"m1h 1b3",
    "iso:country":"CA",
    "sg:city":"Scarborough",
    "sg:classifiers":[
        {
            "category":"Shopping",
            "subcategory":"Clothing, Apparel, & Fashions",
            "type":"Retail Goods"
        }
    ],
    "sg:phone":"+1 416 289 0835",
    "sg:postcode":"M1H 1B3",
    "sg:province":"ON",
    "wof:name":"Smart Set",
    "wof:placetype":"venue"
},
  "geometry": {"coordinates":[-79.22868347169999,43.7589149475],"type":"Point"}
}