{
  "type": "Feature",
  "properties": {
    "addr:full":"Edmonton AB T5M 3L7",
    "addr:postcode":"t5m 3l7",
    "iso:country":"CA",
    "sg:city":"Edmonton",
    "sg:classifiers":[
        {
            "category":"Restaurant",
            "type":"Food & Drink"
        }
    ],
    "sg:phone":"+1 780 451 7661",
    "sg:postcode":"T5M 3L7",
    "sg:province":"AB",
    "wof:name":"Discovery Cafe",
    "wof:placetype":"venue"
},
  "geometry": {"coordinates":[-113.551331,53.55896],"type":"Point"}
}