{
  "type": "Feature",
  "properties": {
    "addr:full":"1 Seaview Dr Burin NL A0E 1E0",
    "addr:housenumber":"1",
    "addr:postcode":"a0e 1e0",
    "addr:street":"Seaview Dr",
    "iso:country":"CA",
    "sg:address":"1 Seaview Dr",
    "sg:city":"Burin",
    "sg:classifiers":[
        {
            "category":"Manufacturing",
            "subcategory":"Food",
            "type":"Manufacturing & Wholesale Goods"
        }
    ],
    "sg:phone":"+1 709 891 1290",
    "sg:postcode":"A0E 1E0",
    "sg:province":"NL",
    "sg:tags":[
        "packer",
        "fish"
    ],
    "wof:name":"Fishery Products Intl",
    "wof:placetype":"venue"
},
  "geometry": {"coordinates":[-55.1793899536,47.0261383057],"type":"Point"}
}