{
  "type": "Feature",
  "properties": {
    "addr:full":"75 Saskatchewan Rd Outlook SK S0L 2N0",
    "addr:housenumber":"75",
    "addr:postcode":"s0l 2n0",
    "addr:street":"Saskatchewan Rd",
    "iso:country":"CA",
    "sg:address":"75 Saskatchewan Rd",
    "sg:city":"Outlook",
    "sg:classifiers":[
        {
            "category":"Manufacturing",
            "subcategory":"Retail Goods",
            "type":"Manufacturing & Wholesale Goods"
        }
    ],
    "sg:phone":"+1 306 867 8482",
    "sg:postcode":"S0L 2N0",
    "sg:province":"SK",
    "sg:tags":[
        "manufacturer"
    ],
    "wof:name":"Triple S Industries",
    "wof:placetype":"venue"
},
  "geometry": {"coordinates":[-107.05696106000001,51.4880485535],"type":"Point"}
}