{
  "type": "Feature",
  "properties": {
    "iso:country":"CA",
    "sg:address":"71 Caledonia Ave",
    "sg:city":"Nanaimo",
    "sg:classifiers":[
        {
            "category":"Organizations",
            "subcategory":"Professional Association",
            "type":"Services"
        }
    ],
    "sg:phone":"+1 250 753 0743",
    "sg:postcode":"V9S 4K5",
    "sg:province":"BC",
    "sg:tags":[
        "club"
    ],
    "wof:name":"Canadian Society of Culture",
    "wof:placetype":"venue"
},
  "geometry": {"coordinates":[-123.936157227,49.1642684937],"type":"Point"}
}