{
  "type": "Feature",
  "properties": {
    "addr:full":"33 Rue Du College Saint-Louis-DE-Kent NB E4X 1C2",
    "addr:housenumber":"33",
    "addr:postcode":"e4x 1c2",
    "addr:street":"Rue Du College Saint-Louis-De-Kent",
    "iso:country":"CA",
    "sg:address":"33 Rue Du College",
    "sg:city":"Saint-Louis-DE-Kent",
    "sg:classifiers":[
        {
            "category":"Recreation",
            "type":"Entertainment"
        }
    ],
    "sg:phone":"+1 506 876 3422",
    "sg:postcode":"E4X 1C2",
    "sg:province":"NB",
    "sg:tags":[
        "center"
    ],
    "wof:name":"Centre Recreatif St Louis",
    "wof:placetype":"venue"
},
  "geometry": {"coordinates":[-64.974586,46.739639],"type":"Point"}
}