{
  "type": "Feature",
  "properties": {
    "addr:full":"14 Rue Des Erables Franquelin QC G0H 1E0",
    "addr:housenumber":"14",
    "addr:postcode":"g0h 1e0",
    "addr:street":"Rue Des Erables",
    "iso:country":"CA",
    "sg:address":"14 Rue Des Erables",
    "sg:city":"Franquelin",
    "sg:classifiers":[
        {
            "category":"Recreation",
            "type":"Entertainment"
        }
    ],
    "sg:phone":"+1 418 296 1522",
    "sg:postcode":"G0H 1E0",
    "sg:province":"QC",
    "sg:tags":[
        "center"
    ],
    "wof:name":"Service Des Loisirs",
    "wof:placetype":"venue"
},
  "geometry": {"coordinates":[-67.8946609497,49.2928504944],"type":"Point"}
}