{
  "type": "Feature",
  "properties": {
    "iso:country":"CA",
    "sg:city":"Mission",
    "sg:classifiers":[
        {
            "category":"Health Services",
            "subcategory":"Doctor",
            "type":"Services"
        }
    ],
    "sg:phone":"+1 604 820 8702",
    "sg:postcode":"V2V 1A3",
    "sg:province":"BC",
    "sg:tags":[
        "dentist"
    ],
    "wof:name":"Flagg, Larry DDS",
    "wof:placetype":"venue"
},
  "geometry": {"coordinates":[-122.33635711700001,49.1331748962],"type":"Point"}
}