{
  "type": "Feature",
  "properties": {
    "addr:full":"3858 Chesswood Dr North York ON M3J 2W6",
    "addr:housenumber":"3858",
    "addr:postcode":"m3j 2w6",
    "addr:street":"Chesswood Dr",
    "iso:country":"CA",
    "sg:address":"3858 Chesswood Dr",
    "sg:city":"North York",
    "sg:classifiers":[
        {
            "category":"Freight",
            "type":"Transportation"
        }
    ],
    "sg:phone":"+1 416 398 5155",
    "sg:postcode":"M3J 2W6",
    "sg:province":"ON",
    "sg:tags":[
        "courier"
    ],
    "wof:name":"Kjv Courier Svc",
    "wof:placetype":"venue"
},
  "geometry": {"coordinates":[-79.474678,43.756432],"type":"Point"}
}