{
  "type": "Feature",
  "properties": {
    "addr:full":"3138 Rue Du Roi-Georges Jonquiere QC G7S 4R6",
    "addr:housenumber":"3138",
    "addr:postcode":"g7s 4r6",
    "addr:street":"Rue Du Roi-Georges",
    "iso:country":"CA",
    "sg:address":"3138 Rue Du Roi-Georges",
    "sg:city":"Jonquiere",
    "sg:classifiers":[
        {
            "category":"Food & Beverages",
            "subcategory":"Groceries & Convenience Stores",
            "type":"Retail Goods"
        }
    ],
    "sg:phone":"+1 418 548 3039",
    "sg:postcode":"G7S 4R6",
    "sg:province":"QC",
    "wof:name":"Super Sagamie",
    "wof:placetype":"venue"
},
  "geometry": {"coordinates":[-71.200699,48.427238],"type":"Point"}
}