{
  "type": "Feature",
  "properties": {
    "addr:full":"10379 Ladner Trunk Rd Delta BC V4G 1K2",
    "addr:housenumber":"10379",
    "addr:postcode":"v4g 1k2",
    "addr:street":"Ladner Trunk Rd",
    "iso:country":"CA",
    "sg:address":"10379 Ladner Trunk Rd",
    "sg:city":"Delta",
    "sg:classifiers":[
        {
            "category":"Recreation",
            "type":"Entertainment"
        }
    ],
    "sg:phone":"+1 604 543 2830",
    "sg:postcode":"V4G 1K2",
    "sg:province":"BC",
    "sg:tags":[
        "hall",
        "auditorium"
    ],
    "wof:name":"East Delta Community Hall",
    "wof:placetype":"venue"
},
  "geometry": {"coordinates":[-122.93751525899999,49.0953483582],"type":"Point"}
}