{
  "type": "Feature",
  "properties": {
    "iso:country":"CA",
    "sg:address":"5055 Av Gatineau",
    "sg:city":"Montreal",
    "sg:classifiers":[
        {
            "category":"Real Estate",
            "subcategory":"Real Estate Agent",
            "type":"Services"
        }
    ],
    "sg:phone":"+1 514 342 5401",
    "sg:postcode":"H3V 1E4",
    "sg:province":"QC",
    "sg:tags":[
        "management"
    ],
    "wof:name":"Bocar Administration",
    "wof:placetype":"venue"
},
  "geometry": {"coordinates":[-73.6177978516,45.495475769],"type":"Point"}
}