{
  "type": "Feature",
  "properties": {
    "addr:full":"754 Rue Shefford Bromont QC J2L 1C1",
    "addr:housenumber":"754",
    "addr:postcode":"j2l 1c1",
    "addr:street":"Rue Shefford",
    "iso:country":"CA",
    "sg:address":"754 Rue Shefford",
    "sg:city":"Bromont",
    "sg:classifiers":[
        {
            "category":"Professional",
            "subcategory":"Detective & Security Services",
            "type":"Services"
        }
    ],
    "sg:phone":"+1 450 534 1022",
    "sg:postcode":"J2L 1C1",
    "sg:province":"QC",
    "sg:tags":[
        "burglary",
        "protective",
        "robbery"
    ],
    "wof:name":"Gestion C Laplante Inc",
    "wof:placetype":"venue"
},
  "geometry": {"coordinates":[-72.65625,45.318275],"type":"Point"}
}