{
  "type": "Feature",
  "properties": {
    "addr:full":"365 Westwood Dr Cobourg ON K9A 4M5",
    "addr:housenumber":"365",
    "addr:postcode":"k9a 4m5",
    "addr:street":"Westwood Dr",
    "iso:country":"CA",
    "sg:address":"365 Westwood Dr",
    "sg:city":"Cobourg",
    "sg:classifiers":[
        {
            "category":"Real Estate",
            "subcategory":"Real Estate Agent",
            "type":"Services"
        }
    ],
    "sg:phone":"+1 905 372 3355",
    "sg:postcode":"K9A 4M5",
    "sg:province":"ON",
    "wof:name":"Century 21 All Pro Realty Ltd",
    "wof:placetype":"venue"
},
  "geometry": {"coordinates":[-78.1888961792,43.9598808289],"type":"Point"}
}