{
  "type": "Feature",
  "properties": {
    "addr:full":"Mississauga ON L5B 3X9",
    "addr:postcode":"l5b 3x9",
    "iso:country":"CA",
    "sg:city":"Mississauga",
    "sg:classifiers":[
        {
            "category":"Personal",
            "subcategory":"Beauty Salon",
            "type":"Services"
        }
    ],
    "sg:phone":"+1 905 277 2723",
    "sg:postcode":"L5B 3X9",
    "sg:province":"ON",
    "wof:name":"Studio 23 Hair Design",
    "wof:placetype":"venue"
},
  "geometry": {"coordinates":[-79.637306,43.582817],"type":"Point"}
}