{
  "type": "Feature",
  "properties": {
    "addr:full":"Calgary AB T2P 0T8",
    "addr:postcode":"t2p 0t8",
    "iso:country":"CA",
    "sg:city":"Calgary",
    "sg:classifiers":[
        {
            "category":"Shopping",
            "subcategory":"Computers & Home Electronics",
            "type":"Retail Goods"
        }
    ],
    "sg:phone":"+1 403 263 7676",
    "sg:postcode":"T2P 0T8",
    "sg:province":"AB",
    "sg:tags":[
        "equipment",
        "dealer"
    ],
    "wof:name":"Onward Computer Systems",
    "wof:placetype":"venue"
},
  "geometry": {"coordinates":[-114.076416016,51.0479431152],"type":"Point"}
}