{
  "type": "Feature",
  "properties": {
    "iso:country":"CA",
    "sg:city":"Kitchener",
    "sg:classifiers":[
        {
            "category":"Building & Trades",
            "subcategory":"Landscaping Services",
            "type":"Services"
        }
    ],
    "sg:phone":"+1 519 743 8580",
    "sg:postcode":"N2C 2N9",
    "sg:province":"ON",
    "sg:tags":[
        "lawn",
        "tree",
        "maintenance",
        "grounds"
    ],
    "wof:name":"Green & White CO Lawn Care",
    "wof:placetype":"venue"
},
  "geometry": {"coordinates":[-80.442139,43.421009],"type":"Point"}
}