{
  "type": "Feature",
  "properties": {
    "addr:full":"9870 63 Ave NW Edmonton AB T6E 0G6",
    "addr:housenumber":"9870",
    "addr:postcode":"t6e 0g6",
    "addr:street":"63 Ave Nw",
    "iso:country":"CA",
    "sg:address":"9870 63 Ave NW",
    "sg:city":"Edmonton",
    "sg:classifiers":[
        {
            "category":"Food & Beverages",
            "subcategory":"Specialty",
            "type":"Retail Goods"
        }
    ],
    "sg:phone":"+1 780 431 8010",
    "sg:postcode":"T6E 0G6",
    "sg:province":"AB",
    "sg:tags":[
        "health",
        "diet"
    ],
    "wof:name":"Popeyes Fitness Shop",
    "wof:placetype":"venue"
},
  "geometry": {"coordinates":[-113.485046,53.500137],"type":"Point"}
}