{
  "type": "Feature",
  "properties": {
    "addr:full":"11799 85A Ave Delta BC V4C 2V8",
    "addr:housenumber":"11799",
    "addr:postcode":"v4c 2v8",
    "addr:street":"85A Ave",
    "iso:country":"CA",
    "sg:address":"11799 85A Ave",
    "sg:city":"Delta",
    "sg:classifiers":[
        {
            "category":"Building & Trades",
            "subcategory":"Construction",
            "type":"Services"
        }
    ],
    "sg:phone":"+1 604 599 6499",
    "sg:postcode":"V4C 2V8",
    "sg:province":"BC",
    "sg:tags":[
        "contractor"
    ],
    "wof:name":"Kruger Development Ltd",
    "wof:placetype":"venue"
},
  "geometry": {"coordinates":[-123.05961600000001,49.084801],"type":"Point"}
}