{
  "type": "Feature",
  "properties": {
    "addr:full":"329 Church St Belleville ON K8N 3C8",
    "addr:housenumber":"329",
    "addr:postcode":"k8n 3c8",
    "addr:street":"Church St",
    "iso:country":"CA",
    "sg:address":"329 Church St",
    "sg:city":"Belleville",
    "sg:classifiers":[
        {
            "category":"Manufacturing",
            "subcategory":"Metals",
            "type":"Manufacturing & Wholesale Goods"
        }
    ],
    "sg:phone":"+1 613 962 2511",
    "sg:postcode":"K8N 3C8",
    "sg:province":"ON",
    "sg:tags":[
        "windows"
    ],
    "wof:name":"View Tech Window & Door",
    "wof:placetype":"venue"
},
  "geometry": {"coordinates":[-77.38339233400001,44.1696434021],"type":"Point"}
}