{
  "type": "Feature",
  "properties": {
    "addr:full":"3500 Portage Ave # 1 Winnipeg MB R3K 0Z6",
    "addr:housenumber":"3500",
    "addr:postcode":"r3k 0z6",
    "addr:street":"Portage Ave # 1",
    "iso:country":"CA",
    "sg:address":"3500 Portage Ave # 1",
    "sg:city":"Winnipeg",
    "sg:classifiers":[
        {
            "category":"Cinema",
            "subcategory":"Movie Rental",
            "type":"Entertainment"
        }
    ],
    "sg:phone":"+1 204 837 1234",
    "sg:postcode":"R3K 0Z6",
    "sg:province":"MB",
    "sg:tags":[
        "video",
        "game",
        "tape",
        "leasing"
    ],
    "wof:name":"Rogers Video",
    "wof:placetype":"venue"
},
  "geometry": {"coordinates":[-97.3050918579,49.8827476501],"type":"Point"}
}