{
  "type": "Feature",
  "properties": {
    "addr:full":"111 Sunbank Way SE Calgary AB T2X 2A5",
    "addr:housenumber":"111",
    "addr:postcode":"t2x 2a5",
    "addr:street":"Sunbank Way Se",
    "iso:country":"CA",
    "sg:address":"111 Sunbank Way SE",
    "sg:city":"Calgary",
    "sg:classifiers":[
        {
            "category":"Building & Trades",
            "subcategory":"Plumbing",
            "type":"Services"
        }
    ],
    "sg:phone":"+1 403 256 7922",
    "sg:postcode":"T2X 2A5",
    "sg:province":"AB",
    "sg:tags":[
        "contractor"
    ],
    "wof:name":"Ace Plumbing & Heating Ind Ltd",
    "wof:placetype":"venue"
},
  "geometry": {"coordinates":[-114.051185608,50.9029197693],"type":"Point"}
}