{
  "type": "Feature",
  "properties": {
    "addr:full":"Athens ON K0E 1B0",
    "addr:postcode":"k0e 1b0",
    "iso:country":"CA",
    "sg:city":"Athens",
    "sg:classifiers":[
        {
            "category":"Sports & Exercise",
            "subcategory":"Golf",
            "type":"Entertainment"
        }
    ],
    "sg:phone":"+1 613 924 4653",
    "sg:postcode":"K0E 1B0",
    "sg:province":"ON",
    "sg:tags":[
        "course"
    ],
    "wof:name":"Village Green Golf Club",
    "wof:placetype":"venue"
},
  "geometry": {"coordinates":[-75.9534378052,44.6254501343],"type":"Point"}
}