{
  "type": "Feature",
  "properties": {
    "iso:country":"CA",
    "sg:address":"19166 Mcmyn Rd",
    "sg:city":"Pitt Meadows",
    "sg:classifiers":[
        {
            "category":"Shopping",
            "subcategory":"Bicycles & Sporting Goods",
            "type":"Retail Goods"
        }
    ],
    "sg:phone":"+1 604 465 5515",
    "sg:postcode":"V3Y 2J3",
    "sg:province":"BC",
    "wof:name":"Scoff's Hockey Shop",
    "wof:placetype":"venue"
},
  "geometry": {"coordinates":[-122.689911,49.22958],"type":"Point"}
}