{
  "type": "Feature",
  "properties": {
    "addr:full":"RR 1 Baysville ON P0B 1A0",
    "addr:postcode":"p0b 1a0",
    "addr:street":"Rr 1",
    "iso:country":"CA",
    "sg:address":"RR 1",
    "sg:city":"Baysville",
    "sg:classifiers":[
        {
            "category":"Building & Trades",
            "subcategory":"Plumbing",
            "type":"Services"
        }
    ],
    "sg:phone":"+1 705 767 2350",
    "sg:postcode":"P0B 1A0",
    "sg:province":"ON",
    "sg:tags":[
        "septic"
    ],
    "wof:name":"Baysville Sanitation",
    "wof:placetype":"venue"
},
  "geometry": {"coordinates":[-79.114311,45.149929],"type":"Point"}
}