{
  "type": "Feature",
  "properties": {
    "addr:full":"1107 37 St SW Calgary AB T3C 1S5",
    "addr:housenumber":"1107",
    "addr:postcode":"t3c 1s5",
    "addr:street":"37 St Sw",
    "iso:country":"CA",
    "sg:address":"1107 37 St SW",
    "sg:city":"Calgary",
    "sg:classifiers":[
        {
            "category":"Health Services",
            "subcategory":"Doctor",
            "type":"Services"
        }
    ],
    "sg:phone":"+1 403 242 5777",
    "sg:postcode":"T3C 1S5",
    "sg:province":"AB",
    "sg:tags":[
        "dentist"
    ],
    "wof:name":"Innes, James DDS",
    "wof:placetype":"venue"
},
  "geometry": {"coordinates":[-114.141296,51.042942],"type":"Point"}
}