{
  "type": "Feature",
  "properties": {
    "addr:full":"PO Box 259 Plamondon AB T0A 2T0",
    "addr:housenumber":"po",
    "addr:postcode":"t0a 2t0",
    "addr:street":"Box 259 Plamondon",
    "iso:country":"CA",
    "sg:address":"PO Box 259",
    "sg:city":"Plamondon",
    "sg:classifiers":[
        {
            "category":"Building & Trades",
            "subcategory":"Construction",
            "type":"Services"
        }
    ],
    "sg:phone":"+1 780 798 3747",
    "sg:postcode":"T0A 2T0",
    "sg:province":"AB",
    "sg:tags":[
        "maker",
        "cabinet"
    ],
    "wof:name":"Meldon Custom Built Cabinets",
    "wof:placetype":"venue"
},
  "geometry": {"coordinates":[-112.344475,54.849781],"type":"Point"}
}