{
  "type": "Feature",
  "properties": {
    "addr:full":"724 Selkirk Ave Winnipeg MB R2W 2N3",
    "addr:housenumber":"724",
    "addr:postcode":"r2w 2n3",
    "addr:street":"Selkirk Ave",
    "iso:country":"CA",
    "sg:address":"724 Selkirk Ave",
    "sg:city":"Winnipeg",
    "sg:classifiers":[
        {
            "category":"Retail",
            "subcategory":"Funeral Services",
            "type":"Services"
        }
    ],
    "sg:phone":"+1 204 586 7700",
    "sg:postcode":"R2W 2N3",
    "sg:province":"MB",
    "sg:tags":[
        "director"
    ],
    "wof:name":"Aborginal Funeral Chapel",
    "wof:placetype":"venue"
},
  "geometry": {"coordinates":[-97.1533584595,49.9182052612],"type":"Point"}
}