{
  "type": "Feature",
  "properties": {
    "addr:full":"325 Keil Dr S Chatham ON N7M 6J5",
    "addr:housenumber":"325",
    "addr:postcode":"n7m 6j5",
    "addr:street":"Keil Dr S",
    "iso:country":"CA",
    "sg:address":"325 Keil Dr S",
    "sg:city":"Chatham",
    "sg:classifiers":[
        {
            "category":"Retail",
            "subcategory":"Auto Repair",
            "type":"Services"
        }
    ],
    "sg:phone":"+1 519 352 8170",
    "sg:postcode":"N7M 6J5",
    "sg:province":"ON",
    "sg:tags":[
        "automobile",
        "co",
        "drive",
        "transporter"
    ],
    "wof:name":"Active Canada Inc",
    "wof:placetype":"venue"
},
  "geometry": {"coordinates":[-82.198082,42.384632],"type":"Point"}
}