{
  "type": "Feature",
  "properties": {
    "addr:full":"3255 Cook St #406 Victoria BC V8X 1A4",
    "addr:housenumber":"3255",
    "addr:postcode":"v8x 1a4",
    "addr:street":"Cook St # 406",
    "iso:country":"CA",
    "sg:address":"3255 Cook St #406",
    "sg:city":"Victoria",
    "sg:classifiers":[
        {
            "category":"Real Estate",
            "subcategory":"Real Estate Operator",
            "type":"Services"
        }
    ],
    "sg:phone":"+1 250 384 3601",
    "sg:postcode":"V8X 1A4",
    "sg:province":"BC",
    "sg:tags":[
        "apartment"
    ],
    "wof:name":"Maplewood Green Apartments",
    "wof:placetype":"venue"
},
  "geometry": {"coordinates":[-123.35050200000001,48.450211],"type":"Point"}
}