{
  "type": "Feature",
  "properties": {
    "addr:full":"1035 Boul Lemire O Drummondville QC J2B 8A9",
    "addr:housenumber":"1035",
    "addr:postcode":"j2b 8a9",
    "addr:street":"Boul Lemire O",
    "iso:country":"CA",
    "sg:address":"1035 Boul Lemire O",
    "sg:city":"Drummondville",
    "sg:classifiers":[
        {
            "category":"Autos & Motor Vehicles",
            "subcategory":"Automobile Sales",
            "type":"Retail Goods"
        }
    ],
    "sg:phone":"+1 819 474 3323",
    "sg:postcode":"J2B 8A9",
    "sg:province":"QC",
    "sg:tags":[
        "car",
        "dealer"
    ],
    "wof:name":"Chauvin Automobiles",
    "wof:placetype":"venue"
},
  "geometry": {"coordinates":[-72.521698,45.87645],"type":"Point"}
}