{
  "type": "Feature",
  "properties": {
    "addr:full":"2363 North Service Rd W Oakville ON L6M 3H8",
    "addr:housenumber":"2363",
    "addr:postcode":"l6m 3h8",
    "addr:street":"North Service Rd W",
    "iso:country":"CA",
    "sg:address":"2363 North Service Rd W",
    "sg:city":"Oakville",
    "sg:classifiers":[
        {
            "category":"Recreation",
            "type":"Entertainment"
        }
    ],
    "sg:phone":"+1 905 847 5555",
    "sg:postcode":"L6M 3H8",
    "sg:province":"ON",
    "sg:tags":[
        "course",
        "golf"
    ],
    "wof:name":"Deerfield Golf & Recreation",
    "wof:placetype":"venue"
},
  "geometry": {"coordinates":[-79.735176,43.415691],"type":"Point"}
}