{
  "type": "Feature",
  "properties": {
    "addr:full":"10024 107 Ave Westlock AB T7P 2E3",
    "addr:housenumber":"10024",
    "addr:postcode":"t7p 2e3",
    "addr:street":"107 Ave",
    "iso:country":"CA",
    "sg:address":"10024 107 Ave",
    "sg:city":"Westlock",
    "sg:classifiers":[
        {
            "category":"Health Services",
            "subcategory":"Clinic",
            "type":"Services"
        }
    ],
    "sg:phone":"+1 780 349 5246",
    "sg:postcode":"T7P 2E3",
    "sg:province":"AB",
    "sg:tags":[
        "counseling"
    ],
    "wof:name":"Westlock Mental Health Svc",
    "wof:placetype":"venue"
},
  "geometry": {"coordinates":[-113.84131622300001,54.1534957886],"type":"Point"}
}