{
  "type": "Feature",
  "properties": {
    "addr:full":"770 Rue Bertrand Saint-Laurent QC H4M 1V9",
    "addr:housenumber":"770",
    "addr:postcode":"h4m 1v9",
    "addr:street":"Rue Bertrand",
    "iso:country":"CA",
    "sg:address":"770 Rue Bertrand",
    "sg:city":"Saint-Laurent",
    "sg:classifiers":[
        {
            "category":"Manufacturing",
            "subcategory":"Printing",
            "type":"Manufacturing & Wholesale Goods"
        }
    ],
    "sg:phone":"+1 514 747 9492",
    "sg:postcode":"H4M 1V9",
    "sg:province":"QC",
    "sg:tags":[
        "publisher",
        "art"
    ],
    "wof:name":"Classcom Inc",
    "wof:placetype":"venue"
},
  "geometry": {"coordinates":[-73.6919631958,45.5000457764],"type":"Point"}
}