{
  "type": "Feature",
  "properties": {
    "iso:country":"CA",
    "sg:address":"89 Ch Saint-Francois-Xavier",
    "sg:city":"Candiac",
    "sg:classifiers":[
        {
            "category":"Utilities",
            "subcategory":"Mobile Phone",
            "type":"Services"
        }
    ],
    "sg:phone":"+1 450 635 5480",
    "sg:postcode":"J5R 4V4",
    "sg:province":"QC",
    "sg:tags":[
        "telephone",
        "cellular"
    ],
    "wof:name":"D 2 Technology",
    "wof:placetype":"venue"
},
  "geometry": {"coordinates":[-73.534798,45.382977],"type":"Point"}
}