{
  "type": "Feature",
  "properties": {
    "addr:full":"Granton ON N0M 1V0",
    "addr:postcode":"n0m 1v0",
    "iso:country":"CA",
    "sg:city":"Granton",
    "sg:classifiers":[
        {
            "category":"Home & Garden",
            "subcategory":"Hardware",
            "type":"Retail Goods"
        }
    ],
    "sg:phone":"+1 519 225 2260",
    "sg:postcode":"N0M 1V0",
    "sg:province":"ON",
    "wof:name":"Granton Handy Hardware",
    "wof:placetype":"venue"
},
  "geometry": {"coordinates":[-81.30154400000001,43.219002],"type":"Point"}
}