{
  "type": "Feature",
  "properties": {
    "addr:full":"400 King St Estevan SK S4A 2B4",
    "addr:housenumber":"400",
    "addr:postcode":"s4a 2b4",
    "addr:street":"King St",
    "iso:country":"CA",
    "sg:address":"400 King St",
    "sg:city":"Estevan",
    "sg:classifiers":[
        {
            "category":"Shopping",
            "subcategory":"Luggage & Leather Goods",
            "type":"Retail Goods"
        }
    ],
    "sg:phone":"+1 306 634 1011",
    "sg:postcode":"S4A 2B4",
    "sg:province":"SK",
    "wof:name":"Bentley Leather",
    "wof:placetype":"venue"
},
  "geometry": {"coordinates":[-102.976677,49.146629],"type":"Point"}
}