{
  "type": "Feature",
  "properties": {
    "addr:full":"23324 Cabot Trail Pleasant Bay NS B0E 2P0",
    "addr:housenumber":"23324",
    "addr:postcode":"b0e 2p0",
    "addr:street":"Cabot Trail",
    "iso:country":"CA",
    "sg:address":"23324 Cabot Trail",
    "sg:city":"Pleasant Bay",
    "sg:classifiers":[
        {
            "category":"Shopping",
            "subcategory":"Gifts & Souvenirs",
            "type":"Retail Goods"
        }
    ],
    "sg:phone":"+1 902 224 1364",
    "sg:postcode":"B0E 2P0",
    "sg:province":"NS",
    "sg:tags":[
        "shop"
    ],
    "wof:name":"Cardinal Points",
    "wof:placetype":"venue"
},
  "geometry": {"coordinates":[-60.801708,46.82618],"type":"Point"}
}