{
  "type": "Feature",
  "properties": {
    "iso:country":"CA",
    "sg:address":"5255 Steeles Ave W",
    "sg:city":"North York",
    "sg:classifiers":[
        {
            "category":"Wholesale",
            "subcategory":"Hardware",
            "type":"Manufacturing & Wholesale Goods"
        }
    ],
    "sg:phone":"+1 416 749 9494",
    "sg:postcode":"M9L 2W2",
    "sg:province":"ON",
    "wof:name":"Berenson Inc",
    "wof:placetype":"venue"
},
  "geometry": {"coordinates":[-79.553619,43.7687],"type":"Point"}
}