{
  "type": "Feature",
  "properties": {
    "addr:full":"33455 Harbour Ave Mission BC V2V 2W3",
    "addr:housenumber":"33455",
    "addr:postcode":"v2v 2w3",
    "addr:street":"Harbour Ave",
    "iso:country":"CA",
    "sg:address":"33455 Harbour Ave",
    "sg:city":"Mission",
    "sg:classifiers":[
        {
            "category":"Retail",
            "subcategory":"Auto Repair",
            "type":"Services"
        }
    ],
    "sg:phone":"+1 604 826 3907",
    "sg:postcode":"V2V 2W3",
    "sg:province":"BC",
    "sg:tags":[
        "repairing",
        "automobile"
    ],
    "wof:name":"Waarden Automotive",
    "wof:placetype":"venue"
},
  "geometry": {"coordinates":[-122.299194336,49.1302947998],"type":"Point"}
}