{
  "type": "Feature",
  "properties": {
    "addr:full":"664 Queen St W Toronto ON M6J 1E5",
    "addr:housenumber":"664",
    "addr:postcode":"m6j 1e5",
    "addr:street":"Queen St W",
    "iso:country":"CA",
    "sg:address":"664 Queen St W",
    "sg:city":"Toronto",
    "sg:classifiers":[
        {
            "category":"Home & Garden",
            "subcategory":"Furniture",
            "type":"Retail Goods"
        }
    ],
    "sg:phone":"+1 416 703 8423",
    "sg:postcode":"M6J 1E5",
    "sg:province":"ON",
    "sg:tags":[
        "craft",
        "gallery",
        "dealer"
    ],
    "wof:name":"Tibet Shoppe",
    "wof:placetype":"venue"
},
  "geometry": {"coordinates":[-79.407059,43.646721],"type":"Point"}
}