{
  "type": "Feature",
  "properties": {
    "addr:full":"3700 Mayor Magrath Dr S Lethbridge AB T1K 7T6",
    "addr:postcode":"3700;t1k 7t6",
    "addr:street":"Mayor Magrath Dr S",
    "iso:country":"CA",
    "sg:address":"3700 Mayor Magrath Dr S",
    "sg:city":"Lethbridge",
    "sg:classifiers":[
        {
            "category":"Shopping",
            "subcategory":"Department Store",
            "type":"Retail Goods"
        }
    ],
    "sg:phone":"+1 403 328 6277",
    "sg:postcode":"T1K 7T6",
    "sg:province":"AB",
    "wof:name":"Wal-Mart",
    "wof:placetype":"venue"
},
  "geometry": {"coordinates":[-112.793503,49.658936],"type":"Point"}
}