{
  "type": "Feature",
  "properties": {
    "iso:country":"CA",
    "sg:address":"137 Brock St",
    "sg:city":"Barrie",
    "sg:classifiers":[
        {
            "category":"Local Transit",
            "type":"Transportation"
        }
    ],
    "sg:phone":"+1 705 728 1100",
    "sg:postcode":"L4N 2M3",
    "sg:province":"ON",
    "sg:tags":[
        "bus",
        "line"
    ],
    "wof:name":"Allandale School Transit Ltd",
    "wof:placetype":"venue"
},
  "geometry": {"coordinates":[-79.7021484375,44.3734092712],"type":"Point"}
}