{
  "type": "Feature",
  "properties": {
    "addr:full":"702 Boul Des Bois-Francs S Victoriaville QC G6P 5W6",
    "addr:housenumber":"702",
    "addr:postcode":"g6p 5w6",
    "addr:street":"Boul Des Bois-Francs S",
    "iso:country":"CA",
    "sg:address":"702 Boul Des Bois-Francs S",
    "sg:city":"Victoriaville",
    "sg:classifiers":[
        {
            "category":"Health Services",
            "subcategory":"Health Practitioner",
            "type":"Services"
        }
    ],
    "sg:phone":"+1 819 357 1996",
    "sg:postcode":"G6P 5W6",
    "sg:province":"QC",
    "sg:tags":[
        "psychologist"
    ],
    "wof:name":"Forgues, Nancy",
    "wof:placetype":"venue"
},
  "geometry": {"coordinates":[-71.926041,46.04451],"type":"Point"}
}