{
  "type": "Feature",
  "properties": {
    "addr:full":"Westlock AB T7P 2K2",
    "addr:postcode":"t7p 2k2",
    "iso:country":"CA",
    "sg:city":"Westlock",
    "sg:classifiers":[
        {
            "category":"Professional",
            "subcategory":"Business Services",
            "type":"Services"
        }
    ],
    "sg:phone":"+1 780 349 3933",
    "sg:postcode":"T7P 2K2",
    "sg:province":"AB",
    "sg:tags":[
        "paging",
        "answering",
        "telephone",
        "cellular"
    ],
    "wof:name":"Kyetech Canada Inc",
    "wof:placetype":"venue"
},
  "geometry": {"coordinates":[-113.86316680900001,54.1543998718],"type":"Point"}
}