{
  "type": "Feature",
  "properties": {
    "addr:full":"9419 51 Ave NW Edmonton AB T6E 4W8",
    "addr:housenumber":"9419",
    "addr:postcode":"t6e 4w8",
    "addr:street":"51 Ave Nw",
    "iso:country":"CA",
    "sg:address":"9419 51 Ave NW",
    "sg:city":"Edmonton",
    "sg:classifiers":[
        {
            "category":"Retail",
            "subcategory":"Auto Repair",
            "type":"Services"
        }
    ],
    "sg:phone":"+1 780 435 7852",
    "sg:postcode":"T6E 4W8",
    "sg:province":"AB",
    "sg:tags":[
        "repairing",
        "glass",
        "automobile"
    ],
    "wof:name":"Jeff's Auto Electric",
    "wof:placetype":"venue"
},
  "geometry": {"coordinates":[-113.47370100000001,53.487865],"type":"Point"}
}