{
  "type": "Feature",
  "properties": {
    "addr:full":"Mississauga ON L5N 6J2",
    "addr:postcode":"l5n 6j2",
    "iso:country":"CA",
    "sg:city":"Mississauga",
    "sg:classifiers":[
        {
            "category":"Wholesale",
            "subcategory":"Machinery & Supplies",
            "type":"Manufacturing & Wholesale Goods"
        }
    ],
    "sg:phone":"+1 905 542 3947",
    "sg:postcode":"L5N 6J2",
    "sg:province":"ON",
    "sg:tags":[
        "crane",
        "parts"
    ],
    "wof:name":"Veco",
    "wof:placetype":"venue"
},
  "geometry": {"coordinates":[-79.7359237671,43.6032867432],"type":"Point"}
}