{
  "type": "Feature",
  "properties": {
    "addr:full":"265 Eddystone Ave North York ON M3N 1H8",
    "addr:housenumber":"265",
    "addr:postcode":"m3n 1h8",
    "addr:street":"Eddystone Ave",
    "iso:country":"CA",
    "sg:address":"265 Eddystone Ave",
    "sg:city":"North York",
    "sg:classifiers":[
        {
            "category":"Home & Garden",
            "subcategory":"Home Furnishings",
            "type":"Retail Goods"
        }
    ],
    "sg:phone":"+1 416 746 8266",
    "sg:postcode":"M3N 1H8",
    "sg:province":"ON",
    "sg:tags":[
        "glassware",
        "chinaware"
    ],
    "wof:name":"Famtrea Exclusives",
    "wof:placetype":"venue"
},
  "geometry": {"coordinates":[-79.5212097168,43.7477264404],"type":"Point"}
}