{
  "type": "Feature",
  "properties": {
    "addr:full":"Winnipeg MB R3B 3K6",
    "addr:postcode":"r3b 3k6",
    "iso:country":"CA",
    "sg:city":"Winnipeg",
    "sg:classifiers":[
        {
            "category":"Mining & Drilling",
            "type":"Manufacturing & Wholesale Goods"
        }
    ],
    "sg:phone":"+1 204 949 4261",
    "sg:postcode":"R3B 3K6",
    "sg:province":"MB",
    "sg:tags":[
        "company"
    ],
    "wof:name":"Hudson Bay Mining & Smelting",
    "wof:placetype":"venue"
},
  "geometry": {"coordinates":[-97.13912999999999,49.89539],"type":"Point"}
}