{
  "type": "Feature",
  "properties": {
    "addr:full":"541 Rue Berry Lachute QC J8H 1S4",
    "addr:housenumber":"541",
    "addr:postcode":"j8h 1s4",
    "addr:street":"Rue Berry",
    "iso:country":"CA",
    "sg:address":"541 Rue Berry",
    "sg:city":"Lachute",
    "sg:classifiers":[
        {
            "category":"Retail",
            "subcategory":"Repair Shop",
            "type":"Services"
        }
    ],
    "sg:phone":"+1 450 562 6035",
    "sg:postcode":"J8H 1S4",
    "sg:province":"QC",
    "sg:tags":[
        "welding"
    ],
    "wof:name":"J Gordon Metal Inc",
    "wof:placetype":"venue"
},
  "geometry": {"coordinates":[-74.33367200000001,45.656418],"type":"Point"}
}