{
  "type": "Feature",
  "properties": {
    "addr:full":"Maple Ridge BC V2X 9B6",
    "addr:postcode":"v2x 9b6",
    "iso:country":"CA",
    "sg:city":"Maple Ridge",
    "sg:classifiers":[
        {
            "category":"Home & Garden",
            "subcategory":"Furniture",
            "type":"Retail Goods"
        }
    ],
    "sg:phone":"+1 604 460 8077",
    "sg:postcode":"V2X 9B6",
    "sg:province":"BC",
    "sg:tags":[
        "mail",
        "catalog",
        "shopping",
        "order"
    ],
    "wof:name":"Sears Canada Inc",
    "wof:placetype":"venue"
},
  "geometry": {"coordinates":[-122.65388488799999,49.2188682556],"type":"Point"}
}