{
  "type": "Feature",
  "properties": {
    "addr:full":"5400 Tecumseh Rd E Windsor ON N8T 1C7",
    "addr:housenumber":"5400",
    "addr:postcode":"n8t 1c7",
    "addr:street":"Tecumseh Rd E",
    "iso:country":"CA",
    "sg:address":"5400 Tecumseh Rd E",
    "sg:city":"Windsor",
    "sg:classifiers":[
        {
            "category":"Health Services",
            "subcategory":"Doctor",
            "type":"Services"
        }
    ],
    "sg:phone":"+1 519 945 2555",
    "sg:postcode":"N8T 1C7",
    "sg:province":"ON",
    "sg:tags":[
        "dentist"
    ],
    "wof:name":"Friedl, Walter L M DDS",
    "wof:placetype":"venue"
},
  "geometry": {"coordinates":[-82.95951100000001,42.309097],"type":"Point"}
}