{
  "type": "Feature",
  "properties": {
    "addr:full":"28 Penhorn Dr Dartmouth NS B2Y 3K3",
    "addr:housenumber":"28",
    "addr:postcode":"b2y 3k3",
    "addr:street":"Penhorn Dr",
    "iso:country":"CA",
    "sg:address":"28 Penhorn Dr",
    "sg:city":"Dartmouth",
    "sg:classifiers":[
        {
            "category":"Building & Trades",
            "subcategory":"Construction",
            "type":"Services"
        }
    ],
    "sg:phone":"+1 902 461 9300",
    "sg:postcode":"B2Y 3K3",
    "sg:province":"NS",
    "sg:tags":[
        "general",
        "contractor"
    ],
    "wof:name":"Forrest Brothers Constr Ltd",
    "wof:placetype":"venue"
},
  "geometry": {"coordinates":[-63.5442085266,44.6782035828],"type":"Point"}
}