{
  "type": "Feature",
  "properties": {
    "addr:full":"11305 100 Ave NW Edmonton AB T5K 0J3",
    "addr:housenumber":"11305",
    "addr:postcode":"t5k 0j3",
    "addr:street":"100 Ave Nw",
    "iso:country":"CA",
    "sg:address":"11305 100 Ave NW",
    "sg:city":"Edmonton",
    "sg:classifiers":[
        {
            "category":"Health Services",
            "subcategory":"Doctor",
            "type":"Services"
        }
    ],
    "sg:phone":"+1 780 488 6538",
    "sg:postcode":"T5K 0J3",
    "sg:province":"AB",
    "sg:tags":[
        "dentist"
    ],
    "wof:name":"100th Avenue Dental",
    "wof:placetype":"venue"
},
  "geometry": {"coordinates":[-113.516037,53.538635],"type":"Point"}
}