{
  "type": "Feature",
  "properties": {
    "addr:full":"108 Main St S Sauble Beach ON N0H 2G0",
    "addr:housenumber":"108",
    "addr:postcode":"n0h 2g0",
    "addr:street":"Main St S Sauble Beach",
    "iso:country":"CA",
    "sg:address":"108 Main St S",
    "sg:city":"Sauble Beach",
    "sg:classifiers":[
        {
            "category":"Shopping",
            "subcategory":"Clothing, Apparel, & Fashions",
            "type":"Retail Goods"
        }
    ],
    "sg:phone":"+1 519 422 3789",
    "sg:postcode":"N0H 2G0",
    "sg:province":"ON",
    "sg:tags":[
        "swimwear",
        "accessory"
    ],
    "wof:name":"Bikini Paradise",
    "wof:placetype":"venue"
},
  "geometry": {"coordinates":[-81.27024841310001,44.6293373108],"type":"Point"}
}