{
  "type": "Feature",
  "properties": {
    "addr:full":"228 Glendale Ave St Catharines ON L2T 2K5",
    "addr:housenumber":"228",
    "addr:postcode":"l2t 2k5",
    "addr:street":"Glendale Ave",
    "iso:country":"CA",
    "sg:address":"228 Glendale Ave",
    "sg:city":"St Catharines",
    "sg:classifiers":[
        {
            "category":"Banks & Credit Unions",
            "subcategory":"Bank",
            "type":"Services"
        }
    ],
    "sg:phone":"+1 905 641 7874",
    "sg:postcode":"L2T 2K5",
    "sg:province":"ON",
    "wof:name":"Bank of Montreal",
    "wof:placetype":"venue"
},
  "geometry": {"coordinates":[-79.2246246338,43.1329231262],"type":"Point"}
}