{
  "type": "Feature",
  "properties": {
    "addr:full":"458 Simcoe St S Oshawa ON L1H 4J6",
    "addr:housenumber":"458",
    "addr:postcode":"l1h 4j6",
    "addr:street":"Simcoe St S",
    "iso:country":"CA",
    "sg:address":"458 Simcoe St S",
    "sg:city":"Oshawa",
    "sg:classifiers":[
        {
            "category":"Food & Beverages",
            "subcategory":"Groceries & Convenience Stores",
            "type":"Retail Goods"
        }
    ],
    "sg:phone":"+1 905 579 3751",
    "sg:postcode":"L1H 4J6",
    "sg:province":"ON",
    "sg:tags":[
        "grocer"
    ],
    "wof:name":"Oshawa Discount Ctr",
    "wof:placetype":"venue"
},
  "geometry": {"coordinates":[-78.85817,43.885532],"type":"Point"}
}