{
  "type": "Feature",
  "properties": {
    "addr:full":"2877 Ch DE Chambly # 1 Longueuil QC J4L 1M8",
    "addr:housenumber":"2877",
    "addr:postcode":"j4l 1m8",
    "addr:street":"Ch De Chambly # 1",
    "iso:country":"CA",
    "sg:address":"2877 Ch DE Chambly # 1",
    "sg:city":"Longueuil",
    "sg:classifiers":[
        {
            "category":"Shopping",
            "subcategory":"Tobacco",
            "type":"Retail Goods"
        }
    ],
    "sg:phone":"+1 450 463 1995",
    "sg:postcode":"J4L 1M8",
    "sg:province":"QC",
    "sg:tags":[
        "cigarette",
        "cigar",
        "dealer"
    ],
    "wof:name":"Tabatiere",
    "wof:placetype":"venue"
},
  "geometry": {"coordinates":[-73.460663,45.520828],"type":"Point"}
}