{
  "type": "Feature",
  "properties": {
    "addr:full":"245 Rue St Alphonse Manseau QC G0X 1V0",
    "addr:housenumber":"245",
    "addr:postcode":"g0x 1v0",
    "addr:street":"Rue St Alphonse",
    "iso:country":"CA",
    "sg:address":"245 Rue St Alphonse",
    "sg:city":"Manseau",
    "sg:classifiers":[
        {
            "category":"Education",
            "subcategory":"School",
            "type":"Public Place"
        }
    ],
    "sg:phone":"+1 819 356 2262",
    "sg:postcode":"G0X 1V0",
    "sg:province":"QC",
    "wof:name":"Ecole Rayons DE Soleil",
    "wof:placetype":"venue"
},
  "geometry": {"coordinates":[-72.0029754639,46.3677597046],"type":"Point"}
}