{
  "type": "Feature",
  "properties": {
    "iso:country":"CA",
    "sg:address":"5 Main St N",
    "sg:city":"St George Brant",
    "sg:classifiers":[
        {
            "category":"Organizations",
            "subcategory":"Professional Association",
            "type":"Services"
        }
    ],
    "sg:phone":"+1 519 448 1714",
    "sg:postcode":"N0E 1N0",
    "sg:province":"ON",
    "sg:tags":[
        "government"
    ],
    "wof:name":"Brant Resource Stewardship",
    "wof:placetype":"venue"
},
  "geometry": {"coordinates":[-80.2720870972,43.2933158875],"type":"Point"}
}