{
  "type": "Feature",
  "properties": {
    "addr:full":"Botwood NL A0H 1E0",
    "iso:country":"CA",
    "sg:city":"Botwood",
    "sg:classifiers":[
        {
            "category":"Government",
            "subcategory":"Office",
            "type":"Public Place"
        }
    ],
    "sg:phone":"+1 709 257 2424",
    "sg:postcode":"A0H 1E0",
    "sg:province":"NL",
    "wof:name":"Newfoundland Human Resources",
    "wof:placetype":"venue"
},
  "geometry": {"coordinates":[-55.3669052124,49.130859375],"type":"Point"}
}