{
  "type": "Feature",
  "properties": {
    "addr:full":"1584 Robie St Halifax NS B3H 3E6",
    "addr:housenumber":"1584",
    "addr:postcode":"b3h 3e6",
    "addr:street":"Robie St",
    "iso:country":"CA",
    "sg:address":"1584 Robie St",
    "sg:city":"Halifax",
    "sg:classifiers":[
        {
            "category":"Health Services",
            "subcategory":"Doctor",
            "type":"Services"
        }
    ],
    "sg:phone":"+1 902 422 9550",
    "sg:postcode":"B3H 3E6",
    "sg:province":"NS",
    "sg:tags":[
        "dentist"
    ],
    "wof:name":"Boyle, Thomas H DDS",
    "wof:placetype":"venue"
},
  "geometry": {"coordinates":[-63.587971,44.642029],"type":"Point"}
}