{
  "type": "Feature",
  "properties": {
    "iso:country":"CA",
    "sg:address":"220 Industrial Pky S",
    "sg:city":"Aurora",
    "sg:classifiers":[
        {
            "category":"Real Estate",
            "subcategory":"Surveying",
            "type":"Services"
        }
    ],
    "sg:phone":"+1 905 841 8526",
    "sg:postcode":"L4G 3V6",
    "sg:province":"ON",
    "sg:tags":[
        "surveyor"
    ],
    "wof:name":"Delph & Jenkins Ltd",
    "wof:placetype":"venue"
},
  "geometry": {"coordinates":[-79.454575,43.99202],"type":"Point"}
}