{
  "type": "Feature",
  "properties": {
    "addr:full":"Millet AB T0C 1Z0",
    "addr:postcode":"t0c 1z0",
    "iso:country":"CA",
    "sg:city":"Millet",
    "sg:classifiers":[
        {
            "category":"Autos & Motor Vehicles",
            "subcategory":"Fuel & Gas Station",
            "type":"Retail Goods"
        }
    ],
    "sg:phone":"+1 780 387 5329",
    "sg:postcode":"T0C 1Z0",
    "sg:province":"AB",
    "sg:tags":[
        "oil"
    ],
    "wof:name":"Fas Gas Oil Ltd",
    "wof:placetype":"venue"
},
  "geometry": {"coordinates":[-113.47048950200001,53.0919723511],"type":"Point"}
}