{
  "type": "Feature",
  "properties": {
    "iso:country":"CA",
    "sg:address":"21 Amberwood Crt",
    "sg:city":"Markham",
    "sg:classifiers":[
        {
            "category":"Building & Trades",
            "subcategory":"Electrical",
            "type":"Services"
        }
    ],
    "sg:phone":"+1 905 415 1984",
    "sg:postcode":"L3R 9N2",
    "sg:province":"ON",
    "sg:tags":[
        "electric",
        "contractor"
    ],
    "wof:name":"Chuck Stokes Electric Ltd",
    "wof:placetype":"venue"
},
  "geometry": {"coordinates":[-79.325287,43.862152],"type":"Point"}
}