{
  "type": "Feature",
  "properties": {
    "addr:full":"643 3 St SE Medicine Hat AB T1A 0H4",
    "addr:housenumber":"643 3",
    "addr:postcode":"t1a 0h4",
    "addr:street":"St Se",
    "iso:country":"CA",
    "sg:address":"643 3 St SE",
    "sg:city":"Medicine Hat",
    "sg:classifiers":[
        {
            "category":"Personal",
            "subcategory":"Tattoo Parlor",
            "type":"Services"
        }
    ],
    "sg:phone":"+1 403 504 0052",
    "sg:postcode":"T1A 0H4",
    "sg:province":"AB",
    "sg:tags":[
        "tattooing"
    ],
    "wof:name":"Extreme Tattoos Inc",
    "wof:placetype":"venue"
},
  "geometry": {"coordinates":[-110.674622,50.040005],"type":"Point"}
}