{
  "type": "Feature",
  "properties": {
    "addr:full":"57 Brant Ave Brantford ON N3T 3G9",
    "addr:housenumber":"57",
    "addr:postcode":"n3t 3g9",
    "addr:street":"Brant Ave",
    "iso:country":"CA",
    "sg:address":"57 Brant Ave",
    "sg:city":"Brantford",
    "sg:classifiers":[
        {
            "category":"Organizations",
            "subcategory":"Religious Organization",
            "type":"Services"
        }
    ],
    "sg:phone":"+1 519 753 3833",
    "sg:postcode":"N3T 3G9",
    "sg:province":"ON",
    "sg:tags":[
        "church"
    ],
    "wof:name":"Faith Lutheran Church",
    "wof:placetype":"venue"
},
  "geometry": {"coordinates":[-80.27029418950001,43.1403007507],"type":"Point"}
}