{
  "type": "Feature",
  "properties": {
    "iso:country":"CA",
    "sg:address":"98 Shade St",
    "sg:city":"Cambridge",
    "sg:classifiers":[
        {
            "category":"Recreation",
            "type":"Entertainment"
        }
    ],
    "sg:phone":"+1 519 623 8404",
    "sg:postcode":"N1R 4J8",
    "sg:province":"ON",
    "sg:tags":[
        "skating",
        "instruction"
    ],
    "wof:name":"Cambridge Skating Club",
    "wof:placetype":"venue"
},
  "geometry": {"coordinates":[-80.3070907593,43.3618774414],"type":"Point"}
}