{
  "type": "Feature",
  "properties": {
    "addr:full":"Calgary AB T2G 4X6",
    "addr:postcode":"t2g 4x6",
    "iso:country":"CA",
    "sg:city":"Calgary",
    "sg:classifiers":[
        {
            "category":"Home & Garden",
            "subcategory":"Furniture",
            "type":"Retail Goods"
        }
    ],
    "sg:phone":"+1 403 294 0838",
    "sg:postcode":"T2G 4X6",
    "sg:province":"AB",
    "wof:name":"Oriental Art & Furniture",
    "wof:placetype":"venue"
},
  "geometry": {"coordinates":[-114.062592,51.049904],"type":"Point"}
}