{
  "type": "Feature",
  "properties": {
    "addr:full":"Calgary AB T2G 4X3",
    "addr:postcode":"t2g 4x3",
    "iso:country":"CA",
    "sg:city":"Calgary",
    "sg:classifiers":[
        {
            "category":"Government",
            "subcategory":"Office",
            "type":"Public Place"
        }
    ],
    "sg:phone":"+1 403 974 2900",
    "sg:postcode":"T2G 4X3",
    "sg:province":"AB",
    "wof:name":"Canadian Forces Recruiting Ctr",
    "wof:placetype":"venue"
},
  "geometry": {"coordinates":[-114.059555,51.049423],"type":"Point"}
}