{
  "type": "Feature",
  "properties": {
    "iso:country":"CA",
    "sg:address":"505 Victoria Ave N",
    "sg:city":"Cranbrook",
    "sg:classifiers":[
        {
            "category":"Food & Beverages",
            "subcategory":"Groceries & Convenience Stores",
            "type":"Retail Goods"
        }
    ],
    "sg:phone":"+1 250 489 3461",
    "sg:postcode":"V1C 6S3",
    "sg:province":"BC",
    "sg:tags":[
        "grocer"
    ],
    "wof:name":"Save on Foods",
    "wof:placetype":"venue"
},
  "geometry": {"coordinates":[-115.75377655,49.5163536072],"type":"Point"}
}