{
  "type": "Feature",
  "properties": {
    "addr:full":"243 Mc Keller St Glencoe ON N0L 1M0",
    "addr:housenumber":"243",
    "addr:postcode":"n0l 1m0",
    "addr:street":"Mc Keller St",
    "iso:country":"CA",
    "sg:address":"243 Mc Keller St",
    "sg:city":"Glencoe",
    "sg:classifiers":[
        {
            "category":"Freight",
            "type":"Transportation"
        }
    ],
    "sg:phone":"+1 519 287 3541",
    "sg:postcode":"N0L 1M0",
    "sg:province":"ON",
    "sg:tags":[
        "trucking"
    ],
    "wof:name":"Gary Graham Transport Ltd",
    "wof:placetype":"venue"
},
  "geometry": {"coordinates":[-81.70528411870001,42.7524299622],"type":"Point"}
}