{
  "type": "Feature",
  "properties": {
    "addr:full":"6722 Highway 522 Nipissing ON P0H 1W0",
    "addr:housenumber":"6722",
    "addr:postcode":"p0h 1w0",
    "addr:street":"Highway 522",
    "iso:country":"CA",
    "sg:address":"6722 Highway 522",
    "sg:city":"Nipissing",
    "sg:classifiers":[
        {
            "category":"Travel",
            "subcategory":"Hotels & Motels",
            "type":"Entertainment"
        }
    ],
    "sg:phone":"+1 705 729 2115",
    "sg:postcode":"P0H 1W0",
    "sg:province":"ON",
    "sg:tags":[
        "tourist",
        "accommodation"
    ],
    "wof:name":"North Star Cottages",
    "wof:placetype":"venue"
},
  "geometry": {"coordinates":[-79.5144195557,46.0986175537],"type":"Point"}
}