{
  "type": "Feature",
  "properties": {
    "addr:full":"1260 Davie St Vancouver BC V6E 1N3",
    "addr:housenumber":"1260",
    "addr:postcode":"v6e 1n3",
    "addr:street":"Davie St",
    "iso:country":"CA",
    "sg:address":"1260 Davie St",
    "sg:city":"Vancouver",
    "sg:classifiers":[
        {
            "category":"Restaurant",
            "type":"Food & Drink"
        }
    ],
    "sg:phone":"+1 604 801 6663",
    "sg:postcode":"V6E 1N3",
    "sg:province":"BC",
    "wof:name":"Sandy's Cafe",
    "wof:placetype":"venue"
},
  "geometry": {"coordinates":[-123.13446,49.28231],"type":"Point"}
}