{
  "type": "Feature",
  "properties": {
    "addr:full":"Vanier ON K1L 8B4",
    "addr:postcode":"k1l 8b4",
    "iso:country":"CA",
    "sg:city":"Vanier",
    "sg:classifiers":[
        {
            "category":"Professional",
            "subcategory":"Management & Consulting",
            "type":"Services"
        }
    ],
    "sg:phone":"+1 613 746 2554",
    "sg:postcode":"K1L 8B4",
    "sg:province":"ON",
    "sg:tags":[
        "consultant",
        "business"
    ],
    "wof:name":"Policy Research Intl Inc",
    "wof:placetype":"venue"
},
  "geometry": {"coordinates":[-75.6774139404,45.4385528564],"type":"Point"}
}