{
  "type": "Feature",
  "properties": {
    "addr:full":"3618 Broadway W Vancouver BC V6R 2B7",
    "addr:housenumber":"3618",
    "addr:postcode":"v6r 2b7",
    "addr:street":"Broadway W",
    "iso:country":"CA",
    "sg:address":"3618 Broadway W",
    "sg:city":"Vancouver",
    "sg:classifiers":[
        {
            "category":"Restaurant",
            "type":"Food & Drink"
        }
    ],
    "sg:phone":"+1 604 731 4135",
    "sg:postcode":"V6R 2B7",
    "sg:province":"BC",
    "wof:name":"Athene's Restaurant",
    "wof:placetype":"venue"
},
  "geometry": {"coordinates":[-123.184189,49.264156],"type":"Point"}
}