{
  "type": "Feature",
  "properties": {
    "iso:country":"CA",
    "sg:address":"145 Kingslake Rd",
    "sg:city":"North York",
    "sg:classifiers":[
        {
            "category":"Shopping",
            "subcategory":"Computers & Home Electronics",
            "type":"Retail Goods"
        }
    ],
    "sg:phone":"+1 416 495 7677",
    "sg:postcode":"M2J 3G2",
    "sg:province":"ON",
    "sg:tags":[
        "equipment",
        "dealer"
    ],
    "wof:name":"Gts Group",
    "wof:placetype":"venue"
},
  "geometry": {"coordinates":[-79.34358978269999,43.7875213623],"type":"Point"}
}