{
  "type": "Feature",
  "properties": {
    "addr:full":"25 Cartier St Ottawa ON K2P 1J2",
    "addr:housenumber":"25",
    "addr:postcode":"k2p 1j2",
    "addr:street":"Cartier St",
    "iso:country":"CA",
    "sg:address":"25 Cartier St",
    "sg:city":"Ottawa",
    "sg:classifiers":[
        {
            "category":"Travel",
            "subcategory":"Hotels & Motels",
            "type":"Entertainment"
        }
    ],
    "sg:phone":"+1 613 237 2111",
    "sg:postcode":"K2P 1J2",
    "sg:province":"ON",
    "wof:name":"Embassy Hotel",
    "wof:placetype":"venue"
},
  "geometry": {"coordinates":[-75.689018,45.419502],"type":"Point"}
}