{
  "type": "Feature",
  "properties": {
    "addr:full":"Scarborough ON M1S 1T9",
    "addr:postcode":"m1s 1t9",
    "iso:country":"CA",
    "sg:city":"Scarborough",
    "sg:classifiers":[
        {
            "category":"Food & Beverages",
            "subcategory":"Bakery",
            "type":"Retail Goods"
        }
    ],
    "sg:phone":"+1 416 335 5500",
    "sg:postcode":"M1S 1T9",
    "sg:province":"ON",
    "sg:tags":[
        "baker"
    ],
    "wof:name":"Tokyo Bakery",
    "wof:placetype":"venue"
},
  "geometry": {"coordinates":[-79.27021026609999,43.7870407104],"type":"Point"}
}