{
  "type": "Feature",
  "properties": {
    "addr:full":"Whitehorse YT Y1A 3S4",
    "addr:postcode":"y1a 3s4",
    "iso:country":"CA",
    "sg:city":"Whitehorse",
    "sg:classifiers":[
        {
            "category":"Organizations",
            "subcategory":"Professional Association",
            "type":"Services"
        }
    ],
    "sg:phone":"+1 867 668 7812",
    "sg:postcode":"Y1A 3S4",
    "sg:province":"YT",
    "wof:name":"Training Policy Committee",
    "wof:placetype":"venue"
},
  "geometry": {"coordinates":[-135.035751,60.705601],"type":"Point"}
}