{
  "type": "Feature",
  "properties": {
    "addr:full":"Montreal QC H3L 3R9",
    "addr:postcode":"h3l 3r9",
    "iso:country":"CA",
    "sg:city":"Montreal",
    "sg:classifiers":[
        {
            "category":"Health Services",
            "subcategory":"Doctor",
            "type":"Services"
        }
    ],
    "sg:phone":"+1 514 389 1359",
    "sg:postcode":"H3L 3R9",
    "sg:province":"QC",
    "sg:tags":[
        "dentist"
    ],
    "wof:name":"Dubuc, Andree DDS",
    "wof:placetype":"venue"
},
  "geometry": {"coordinates":[-73.6715011597,45.5553894043],"type":"Point"}
}