{
  "type": "Feature",
  "properties": {
    "addr:full":"Coquitlam BC V3B 6S2",
    "addr:postcode":"v3b 6s2",
    "iso:country":"CA",
    "sg:city":"Coquitlam",
    "sg:classifiers":[
        {
            "category":"Shopping",
            "type":"Retail Goods"
        }
    ],
    "sg:phone":"+1 604 464 9955",
    "sg:postcode":"V3B 6S2",
    "sg:province":"BC",
    "sg:tags":[
        "pet",
        "grooming",
        "washing",
        "supply"
    ],
    "wof:name":"Petcetera",
    "wof:placetype":"venue"
},
  "geometry": {"coordinates":[-122.792243958,49.274433136],"type":"Point"}
}