{
  "type": "Feature",
  "properties": {
    "iso:country":"CA",
    "sg:address":"3526 Boul Industriel",
    "sg:city":"Montreal-Nord",
    "sg:classifiers":[
        {
            "category":"Manufacturing",
            "subcategory":"Paper Products",
            "type":"Manufacturing & Wholesale Goods"
        }
    ],
    "sg:phone":"+1 514 326 7000",
    "sg:postcode":"H1H 2Y4",
    "sg:province":"QC",
    "sg:tags":[
        "converter"
    ],
    "wof:name":"Emballages Quebec Inc",
    "wof:placetype":"venue"
},
  "geometry": {"coordinates":[-73.63571929930001,45.5772972107],"type":"Point"}
}