{
  "type": "Feature",
  "properties": {
    "addr:full":"7 Banigan Dr East York ON M4H 1G3",
    "addr:housenumber":"7",
    "addr:postcode":"m4h 1g3",
    "addr:street":"Banigan Dr",
    "iso:country":"CA",
    "sg:address":"7 Banigan Dr",
    "sg:city":"East York",
    "sg:classifiers":[
        {
            "category":"Professional",
            "subcategory":"Business Services",
            "type":"Services"
        }
    ],
    "sg:phone":"+1 416 467 9418",
    "sg:postcode":"M4H 1G3",
    "sg:province":"ON",
    "sg:tags":[
        "paper",
        "lamination"
    ],
    "wof:name":"Plax Plus",
    "wof:placetype":"venue"
},
  "geometry": {"coordinates":[-79.35322600000001,43.703983],"type":"Point"}
}