{
  "type": "Feature",
  "properties": {
    "addr:full":"535 Portland St Dartmouth NS B2Y 4B1",
    "addr:housenumber":"535",
    "addr:postcode":"b2y 4b1",
    "addr:street":"Portland St",
    "iso:country":"CA",
    "sg:address":"535 Portland St",
    "sg:city":"Dartmouth",
    "sg:classifiers":[
        {
            "category":"Retail",
            "subcategory":"Repair Shop",
            "type":"Services"
        }
    ],
    "sg:phone":"+1 902 466 8740",
    "sg:postcode":"B2Y 4B1",
    "sg:province":"NS",
    "sg:tags":[
        "repairing",
        "sporting",
        "boot",
        "shoe"
    ],
    "wof:name":"Moneysworth & Best Qlty Shoe",
    "wof:placetype":"venue"
},
  "geometry": {"coordinates":[-63.53838,44.670326],"type":"Point"}
}