{
  "type": "Feature",
  "properties": {
    "iso:country":"CA",
    "sg:address":"1134 Plains Rd W",
    "sg:city":"Burlington",
    "sg:classifiers":[
        {
            "category":"Shopping",
            "subcategory":"Florist",
            "type":"Retail Goods"
        }
    ],
    "sg:phone":"+1 905 570 1500",
    "sg:postcode":"L7T 1H3",
    "sg:province":"ON",
    "wof:name":"Rendezvous Gardens",
    "wof:placetype":"venue"
},
  "geometry": {"coordinates":[-79.881088,43.29163],"type":"Point"}
}