{
  "type": "Feature",
  "properties": {
    "addr:full":"Bonaventure QC G0C 1E0",
    "addr:postcode":"g0c 1e0",
    "iso:country":"CA",
    "sg:city":"Bonaventure",
    "sg:classifiers":[
        {
            "category":"Shopping",
            "subcategory":"Discount & Variety Stores",
            "type":"Retail Goods"
        }
    ],
    "sg:phone":"+1 418 534 2020",
    "sg:postcode":"G0C 1E0",
    "sg:province":"QC",
    "sg:tags":[
        "merchandise",
        "general"
    ],
    "wof:name":"Magasin CO-OP",
    "wof:placetype":"venue"
},
  "geometry": {"coordinates":[-65.484261,48.049248],"type":"Point"}
}