{
  "type": "Feature",
  "properties": {
    "iso:country":"CA",
    "sg:address":"17846 Rue Montego",
    "sg:city":"Pierrefonds",
    "sg:classifiers":[
        {
            "category":"Wholesale",
            "subcategory":"Durable Goods & Equipment",
            "type":"Manufacturing & Wholesale Goods"
        }
    ],
    "sg:phone":"+1 514 696 4594",
    "sg:postcode":"H9J 3V2",
    "sg:province":"QC",
    "sg:tags":[
        "exporter"
    ],
    "wof:name":"Bois Dorial Inc",
    "wof:placetype":"venue"
},
  "geometry": {"coordinates":[-73.881683,45.455509],"type":"Point"}
}