{
  "type": "Feature",
  "properties": {
    "addr:full":"424 Boul Cure-Poirier O Longueuil QC J4J 2H2",
    "addr:housenumber":"424",
    "addr:postcode":"j4j 2h2",
    "addr:street":"Boul Cure-Poirier O",
    "iso:country":"CA",
    "sg:address":"424 Boul Cure-Poirier O",
    "sg:city":"Longueuil",
    "sg:classifiers":[
        {
            "category":"Manufacturing",
            "subcategory":"Glass & Minerals",
            "type":"Manufacturing & Wholesale Goods"
        }
    ],
    "sg:phone":"+1 450 442 7000",
    "sg:postcode":"J4J 2H2",
    "sg:province":"QC",
    "sg:tags":[
        "granite",
        "monument"
    ],
    "wof:name":"Monuments St Georges Inc",
    "wof:placetype":"venue"
},
  "geometry": {"coordinates":[-73.4789810181,45.5339241028],"type":"Point"}
}