{
  "type": "Feature",
  "properties": {
    "addr:full":"Gatineau QC J8T 2L7",
    "addr:postcode":"j8t 2l7",
    "iso:country":"CA",
    "sg:city":"Gatineau",
    "sg:classifiers":[
        {
            "category":"Personal",
            "subcategory":"Beauty Salon",
            "type":"Services"
        }
    ],
    "sg:phone":"+1 819 561 0475",
    "sg:postcode":"J8T 2L7",
    "sg:province":"QC",
    "wof:name":"Coiffure Sylvie Theriault",
    "wof:placetype":"venue"
},
  "geometry": {"coordinates":[-75.743317,45.443897],"type":"Point"}
}