{
  "type": "Feature",
  "properties": {
    "addr:full":"St George NB E5C 3H9",
    "addr:postcode":"e5c 3h9",
    "iso:country":"CA",
    "sg:city":"St George",
    "sg:classifiers":[
        {
            "category":"Health Services",
            "subcategory":"Doctor",
            "type":"Services"
        }
    ],
    "sg:phone":"+1 506 755 3765",
    "sg:postcode":"E5C 3H9",
    "sg:province":"NB",
    "sg:tags":[
        "physician",
        "surgeon"
    ],
    "wof:name":"Kaminska, Irena MD",
    "wof:placetype":"venue"
},
  "geometry": {"coordinates":[-66.82379899999999,45.13015],"type":"Point"}
}