{
  "type": "Feature",
  "properties": {
    "addr:full":"4427 Davidson Rd Inverary ON K0H 1X0",
    "addr:housenumber":"4427",
    "addr:postcode":"k0h 1x0",
    "addr:street":"Davidson Rd",
    "iso:country":"CA",
    "sg:address":"4427 Davidson Rd",
    "sg:city":"Inverary",
    "sg:classifiers":[
        {
            "category":"Wholesale",
            "subcategory":"Apparel",
            "type":"Manufacturing & Wholesale Goods"
        }
    ],
    "sg:phone":"+1 613 353 7000",
    "sg:postcode":"K0H 1X0",
    "sg:province":"ON",
    "sg:tags":[
        "advertising"
    ],
    "wof:name":"Eagle Eye Marketing",
    "wof:placetype":"venue"
},
  "geometry": {"coordinates":[-76.47435760499999,44.3861961365],"type":"Point"}
}