{
  "type": "Feature",
  "properties": {
    "addr:full":"Val-Belair QC G3K 1L2",
    "addr:postcode":"g3k 1l2",
    "iso:country":"CA",
    "sg:city":"Val-Belair",
    "sg:classifiers":[
        {
            "category":"Health Services",
            "subcategory":"Doctor",
            "type":"Services"
        }
    ],
    "sg:phone":"+1 418 845 2502",
    "sg:postcode":"G3K 1L2",
    "sg:province":"QC",
    "sg:tags":[
        "clinic"
    ],
    "wof:name":"Clinique DE Physiotherapie Pie",
    "wof:placetype":"venue"
},
  "geometry": {"coordinates":[-71.4114151001,46.8548736572],"type":"Point"}
}