{
  "type": "Feature",
  "properties": {
    "addr:full":"377 Ivan Rd Etobicoke ON M9W 3P4",
    "addr:housenumber":"377",
    "addr:postcode":"m9w 3p4",
    "addr:street":"Ivan Rd",
    "iso:country":"CA",
    "sg:address":"377 Ivan Rd",
    "sg:city":"Etobicoke",
    "sg:classifiers":[
        {
            "category":"Personal",
            "subcategory":"Shoe Repair & Shine",
            "type":"Services"
        }
    ],
    "sg:phone":"+1 416 741 8311",
    "sg:postcode":"M9W 3P4",
    "sg:province":"ON",
    "sg:tags":[
        "repairing",
        "boot"
    ],
    "wof:name":"Albion Cleners & Repair",
    "wof:placetype":"venue"
},
  "geometry": {"coordinates":[-79.56669599999999,43.643394],"type":"Point"}
}