{
  "type": "Feature",
  "properties": {
    "addr:full":"Thornhill ON L3T 7M8",
    "addr:postcode":"l3t 7m8",
    "iso:country":"CA",
    "sg:city":"Thornhill",
    "sg:classifiers":[
        {
            "category":"Real Estate",
            "subcategory":"Real Estate Agent",
            "type":"Services"
        }
    ],
    "sg:phone":"+1 416 730 8100",
    "sg:postcode":"L3T 7M8",
    "sg:province":"ON",
    "sg:tags":[
        "attorney"
    ],
    "wof:name":"Tanco Corp",
    "wof:placetype":"venue"
},
  "geometry": {"coordinates":[-79.38190460209999,43.8421783447],"type":"Point"}
}