{
  "type": "Feature",
  "properties": {
    "addr:full":"Courtenay BC V9N 7J5",
    "addr:postcode":"v9n 7j5",
    "iso:country":"CA",
    "sg:city":"Courtenay",
    "sg:classifiers":[
        {
            "category":"Shopping",
            "subcategory":"Clothing, Apparel, & Fashions",
            "type":"Retail Goods"
        }
    ],
    "sg:phone":"+1 250 334 2447",
    "sg:postcode":"V9N 7J5",
    "sg:province":"BC",
    "wof:name":"Penny Tyme Fashions Ltd",
    "wof:placetype":"venue"
},
  "geometry": {"coordinates":[-124.99879455599999,49.6914176941],"type":"Point"}
}