{
  "type": "Feature",
  "properties": {
    "iso:country":"CA",
    "sg:address":"12094 Eighth Line",
    "sg:city":"Georgetown",
    "sg:classifiers":[
        {
            "category":"Professional",
            "subcategory":"Business Services",
            "type":"Services"
        }
    ],
    "sg:phone":"+1 905 877 0624",
    "sg:postcode":"L7G 4S4",
    "sg:province":"ON",
    "sg:tags":[
        "lecture",
        "bureau",
        "seminar"
    ],
    "wof:name":"Service Excellence Group Inc",
    "wof:placetype":"venue"
},
  "geometry": {"coordinates":[-79.941429,43.660725],"type":"Point"}
}