{
  "type": "Feature",
  "properties": {
    "iso:country":"CA",
    "sg:address":"35 Corriveau Ave",
    "sg:city":"St Albert",
    "sg:classifiers":[
        {
            "category":"Home & Garden",
            "subcategory":"Building Materials",
            "type":"Retail Goods"
        }
    ],
    "sg:phone":"+1 780 458 3611",
    "sg:postcode":"T8N 5A3",
    "sg:province":"AB",
    "sg:tags":[
        "door",
        "gate",
        "operating",
        "devices"
    ],
    "wof:name":"Advanced Access Systems",
    "wof:placetype":"venue"
},
  "geometry": {"coordinates":[-113.573791504,53.6424942017],"type":"Point"}
}