{
  "type": "Feature",
  "properties": {
    "addr:full":"80 Morrow Rd Barrie ON L4N 3V8",
    "addr:housenumber":"80",
    "addr:postcode":"l4n 3v8",
    "addr:street":"Morrow Rd",
    "iso:country":"CA",
    "sg:address":"80 Morrow Rd",
    "sg:city":"Barrie",
    "sg:classifiers":[
        {
            "category":"Wholesale",
            "subcategory":"Electrical",
            "type":"Manufacturing & Wholesale Goods"
        }
    ],
    "sg:phone":"+1 705 726 2331",
    "sg:postcode":"L4N 3V8",
    "sg:province":"ON",
    "sg:tags":[
        "equipment",
        "electric",
        "supply"
    ],
    "wof:name":"Westburne Ruddy Electric",
    "wof:placetype":"venue"
},
  "geometry": {"coordinates":[-79.7037124634,44.3628807068],"type":"Point"}
}