{
  "type": "Feature",
  "properties": {
    "addr:full":"555 Legget Drive 1001 Ottawa K2K 2X3",
    "addr:housenumber":"555;1001",
    "addr:postcode":"k2k 2x3",
    "addr:street":"Legget Drive",
    "iso:country":"CA",
    "sg:address":"555 Legget Drive 1001",
    "sg:city":"Ottawa",
    "sg:classifiers":[
        {
            "category":"Professional",
            "subcategory":"Computer Services",
            "type":"Services"
        }
    ],
    "sg:postcode":"K2K 2X3",
    "sg:website":"http://www.neurolanguage.com",
    "wof:name":"neuroLanguage",
    "wof:placetype":"venue"
},
  "geometry": {"coordinates":[-75.9200142,45.3479463],"type":"Point"}
}