{
  "type": "Feature",
  "properties": {
    "addr:full":"RR 2 Wallenstein ON N0B 2S0",
    "addr:postcode":"n0b 2s0",
    "addr:street":"Rr 2",
    "iso:country":"CA",
    "sg:address":"RR 2",
    "sg:city":"Wallenstein",
    "sg:classifiers":[
        {
            "category":"Travel",
            "subcategory":"Campground",
            "type":"Entertainment"
        }
    ],
    "sg:phone":"+1 519 638 2873",
    "sg:postcode":"N0B 2S0",
    "sg:province":"ON",
    "wof:name":"Grand River Conservation Auth",
    "wof:placetype":"venue"
},
  "geometry": {"coordinates":[-80.634216,43.599659],"type":"Point"}
}