{
  "type": "Feature",
  "properties": {
    "addr:full":"2281 Mills Rd Sidney BC V8L 2C3",
    "addr:housenumber":"2281",
    "addr:postcode":"v8l 2c3",
    "addr:street":"Mills Rd",
    "iso:country":"CA",
    "sg:address":"2281 Mills Rd",
    "sg:city":"Sidney",
    "sg:classifiers":[
        {
            "category":"Social Services",
            "subcategory":"Adult Care",
            "type":"Services"
        }
    ],
    "sg:phone":"+1 250 656 0717",
    "sg:postcode":"V8L 2C3",
    "sg:province":"BC",
    "sg:tags":[
        "community",
        "facility"
    ],
    "wof:name":"Rest Haven Lodge",
    "wof:placetype":"venue"
},
  "geometry": {"coordinates":[-123.405235,48.655209],"type":"Point"}
}