{
  "type": "Feature",
  "properties": {
    "addr:full":"431 Spadina Ave Toronto ON M5T 2G6",
    "addr:housenumber":"431",
    "addr:postcode":"m5t 2g6",
    "addr:street":"Spadina Ave",
    "iso:country":"CA",
    "sg:address":"431 Spadina Ave",
    "sg:city":"Toronto",
    "sg:classifiers":[
        {
            "category":"Wholesale",
            "subcategory":"Toys & Hobbies",
            "type":"Manufacturing & Wholesale Goods"
        }
    ],
    "sg:phone":"+1 416 977 2773",
    "sg:postcode":"M5T 2G6",
    "sg:province":"ON",
    "wof:name":"Leeway Trading CO",
    "wof:placetype":"venue"
},
  "geometry": {"coordinates":[-79.399513,43.657364],"type":"Point"}
}