{
  "type": "Feature",
  "properties": {
    "addr:full":"24330 66 Ave Langley BC V2Y 2H2",
    "addr:housenumber":"24330",
    "addr:postcode":"v2y 2h2",
    "addr:street":"66 Ave",
    "iso:country":"CA",
    "sg:address":"24330 66 Ave",
    "sg:city":"Langley",
    "sg:classifiers":[
        {
            "category":"Wholesale",
            "subcategory":"Computers",
            "type":"Manufacturing & Wholesale Goods"
        }
    ],
    "sg:phone":"+1 604 534 6607",
    "sg:postcode":"V2Y 2H2",
    "sg:province":"BC",
    "sg:tags":[
        "communications",
        "datum"
    ],
    "wof:name":"Pa L Industries Ltd",
    "wof:placetype":"venue"
},
  "geometry": {"coordinates":[-122.55088000000001,49.122231],"type":"Point"}
}