{
  "type": "Feature",
  "properties": {
    "addr:full":"125 Paynter Cres Regina SK S4X 2A9",
    "addr:housenumber":"125",
    "addr:postcode":"s4x 2a9",
    "addr:street":"Paynter Cres",
    "iso:country":"CA",
    "sg:address":"125 Paynter Cres",
    "sg:city":"Regina",
    "sg:classifiers":[
        {
            "category":"Education",
            "subcategory":"School",
            "type":"Public Place"
        }
    ],
    "sg:phone":"+1 306 791 8496",
    "sg:postcode":"S4X 2A9",
    "sg:province":"SK",
    "wof:name":"Mc Lurg Public Elementary Schl",
    "wof:placetype":"venue"
},
  "geometry": {"coordinates":[-104.681205749,50.4721908569],"type":"Point"}
}