{
  "type": "Feature",
  "properties": {
    "addr:full":"270 University Ave W Cobourg ON K9A 2H7",
    "addr:housenumber":"270",
    "addr:postcode":"k9a 2h7",
    "addr:street":"University Ave W",
    "iso:country":"CA",
    "sg:address":"270 University Ave W",
    "sg:city":"Cobourg",
    "sg:classifiers":[
        {
            "category":"Building & Trades",
            "subcategory":"Construction",
            "type":"Services"
        }
    ],
    "sg:phone":"+1 905 372 8849",
    "sg:postcode":"K9A 2H7",
    "sg:province":"ON",
    "sg:tags":[
        "designer",
        "dealer",
        "pool",
        "swimming"
    ],
    "wof:name":"Northumberland Pools & Spas",
    "wof:placetype":"venue"
},
  "geometry": {"coordinates":[-78.177719,43.961941],"type":"Point"}
}