{
  "type": "Feature",
  "properties": {
    "addr:full":"1190 Rue Vincent-Massey Quebec QC G1N 4T9",
    "addr:housenumber":"1190",
    "addr:postcode":"g1n 4t9",
    "addr:street":"Rue Vincent-Massey",
    "iso:country":"CA",
    "sg:address":"1190 Rue Vincent-Massey",
    "sg:city":"Quebec",
    "sg:classifiers":[
        {
            "category":"Manufacturing",
            "subcategory":"Metals",
            "type":"Manufacturing & Wholesale Goods"
        }
    ],
    "sg:phone":"+1 418 527 5325",
    "sg:postcode":"G1N 4T9",
    "sg:province":"QC",
    "sg:tags":[
        "enameling",
        "japanning",
        "lacquering"
    ],
    "wof:name":"Fontaine & Girard Inc",
    "wof:placetype":"venue"
},
  "geometry": {"coordinates":[-71.25430299999999,46.804665],"type":"Point"}
}