{
  "type": "Feature",
  "properties": {
    "addr:full":"1550 Lansdowne St W Peterborough ON K9J 2A2",
    "addr:housenumber":"1550",
    "addr:postcode":"k9j 2a2",
    "addr:street":"Lansdowne St W",
    "iso:country":"CA",
    "sg:address":"1550 Lansdowne St W",
    "sg:city":"Peterborough",
    "sg:classifiers":[
        {
            "category":"Food & Beverages",
            "subcategory":"Bakery",
            "type":"Retail Goods"
        }
    ],
    "sg:phone":"+1 705 740 1926",
    "sg:postcode":"K9J 2A2",
    "sg:province":"ON",
    "sg:tags":[
        "doughnut"
    ],
    "wof:name":"Country Style Donuts",
    "wof:placetype":"venue"
},
  "geometry": {"coordinates":[-78.364632,44.277451],"type":"Point"}
}