{
  "type": "Feature",
  "properties": {
    "addr:full":"Tulliby Lake AB T0A 3K0",
    "addr:postcode":"t0a 3k0",
    "iso:country":"CA",
    "sg:city":"Tulliby Lake",
    "sg:classifiers":[
        {
            "category":"Education",
            "subcategory":"School",
            "type":"Public Place"
        }
    ],
    "sg:phone":"+1 780 847 2655",
    "sg:postcode":"T0A 3K0",
    "sg:province":"AB",
    "wof:name":"Tulliby Lake School",
    "wof:placetype":"venue"
},
  "geometry": {"coordinates":[-110.153412,53.715172],"type":"Point"}
}