{
  "type": "Feature",
  "properties": {
    "addr:full":"250 Boul Talbot Stoneham QC G0A 4P0",
    "addr:housenumber":"250",
    "addr:postcode":"g0a 4p0",
    "addr:street":"Boul Talbot",
    "iso:country":"CA",
    "sg:address":"250 Boul Talbot",
    "sg:city":"Stoneham",
    "sg:classifiers":[
        {
            "category":"Autos & Motor Vehicles",
            "subcategory":"Automobile Sales",
            "type":"Retail Goods"
        }
    ],
    "sg:phone":"+1 418 849 0499",
    "sg:postcode":"G0A 4P0",
    "sg:province":"QC",
    "sg:tags":[
        "scooter",
        "motorcycle",
        "snowmobile"
    ],
    "wof:name":"Jrb Sports",
    "wof:placetype":"venue"
},
  "geometry": {"coordinates":[-71.362679,46.948242],"type":"Point"}
}