{
  "type": "Feature",
  "properties": {
    "addr:full":"455 Boul Marie-Victorin Kingsey Falls QC J0A 1B0",
    "addr:housenumber":"455",
    "addr:postcode":"j0a 1b0",
    "addr:street":"Boul Marie-Victorin",
    "iso:country":"CA",
    "sg:address":"455 Boul Marie-Victorin",
    "sg:city":"Kingsey Falls",
    "sg:classifiers":[
        {
            "category":"Manufacturing",
            "subcategory":"Rubber & Plastics",
            "type":"Manufacturing & Wholesale Goods"
        }
    ],
    "sg:phone":"+1 819 363 5300",
    "sg:postcode":"J0A 1B0",
    "sg:province":"QC",
    "wof:name":"Plastiques Cascades Inc",
    "wof:placetype":"venue"
},
  "geometry": {"coordinates":[-72.07251739500001,45.8596954346],"type":"Point"}
}