{
  "type": "Feature",
  "properties": {
    "addr:full":"Surrey BC V4P 1B8",
    "addr:postcode":"v4p 1b8",
    "iso:country":"CA",
    "sg:city":"Surrey",
    "sg:classifiers":[
        {
            "category":"Shopping",
            "type":"Retail Goods"
        }
    ],
    "sg:phone":"+1 604 538 5471",
    "sg:postcode":"V4P 1B8",
    "sg:province":"BC",
    "sg:tags":[
        "orthopedic",
        "appliance"
    ],
    "wof:name":"Superfeet Canada",
    "wof:placetype":"venue"
},
  "geometry": {"coordinates":[-122.80798299999999,49.057056],"type":"Point"}
}