{
  "type": "Feature",
  "properties": {
    "addr:full":"Toronto ON M4M 2G3",
    "addr:postcode":"m4m 2g3",
    "iso:country":"CA",
    "sg:city":"Toronto",
    "sg:classifiers":[
        {
            "category":"Communications",
            "subcategory":"Film & Video Production",
            "type":"Services"
        }
    ],
    "sg:phone":"+1 416 465 5850",
    "sg:postcode":"M4M 2G3",
    "sg:province":"ON",
    "sg:tags":[
        "audio"
    ],
    "wof:name":"Vcg Creative Imaging",
    "wof:placetype":"venue"
},
  "geometry": {"coordinates":[-79.35092899999999,43.661957],"type":"Point"}
}