{
  "type": "Feature",
  "properties": {
    "addr:full":"1333 1E Av Quebec QC G1L 3L2",
    "addr:housenumber":"1333",
    "addr:postcode":"g1l 3l2",
    "addr:street":"1E Av",
    "iso:country":"CA",
    "sg:address":"1333 1E Av",
    "sg:city":"Quebec",
    "sg:classifiers":[
        {
            "category":"Education",
            "subcategory":"College",
            "type":"Public Place"
        }
    ],
    "sg:phone":"+1 418 648 6737",
    "sg:postcode":"G1L 3L2",
    "sg:province":"QC",
    "sg:tags":[
        "academic",
        "school"
    ],
    "wof:name":"Centre DE Formation Chretienne",
    "wof:placetype":"venue"
},
  "geometry": {"coordinates":[-71.23522949220001,46.8272628784],"type":"Point"}
}