{
  "type": "Feature",
  "properties": {
    "addr:full":"768 Blackburn Mews Kingston ON K7P 2N7",
    "addr:housenumber":"768",
    "addr:postcode":"k7p 2n7",
    "addr:street":"Blackburn Mews",
    "iso:country":"CA",
    "sg:address":"768 Blackburn Mews",
    "sg:city":"Kingston",
    "sg:classifiers":[
        {
            "category":"Banks & Credit Unions",
            "subcategory":"Investment Brokerage",
            "type":"Services"
        }
    ],
    "sg:phone":"+1 613 384 7114",
    "sg:postcode":"K7P 2N7",
    "sg:province":"ON",
    "wof:name":"Edward Jones",
    "wof:placetype":"venue"
},
  "geometry": {"coordinates":[-76.57081599999999,44.250946],"type":"Point"}
}