{
  "type": "Feature",
  "properties": {
    "addr:full":"Langley BC V3A 2W3",
    "addr:postcode":"v3a 2w3",
    "iso:country":"CA",
    "sg:city":"Langley",
    "sg:classifiers":[
        {
            "category":"Health Services",
            "subcategory":"Doctor",
            "type":"Services"
        }
    ],
    "sg:phone":"+1 604 533 6626",
    "sg:postcode":"V3A 2W3",
    "sg:province":"BC",
    "sg:tags":[
        "physician",
        "surgeon"
    ],
    "wof:name":"Shore, Stephen M MD",
    "wof:placetype":"venue"
},
  "geometry": {"coordinates":[-122.666679382,49.0748405457],"type":"Point"}
}