{
  "type": "Feature",
  "properties": {
    "iso:country":"CA",
    "sg:city":"Grand Bank",
    "sg:classifiers":[
        {
            "category":"Organizations",
            "subcategory":"Professional Association",
            "type":"Services"
        }
    ],
    "sg:phone":"+1 709 832 1574",
    "sg:postcode":"A0E 1W0",
    "sg:province":"NL",
    "sg:tags":[
        "museum"
    ],
    "wof:name":"Grand Bank Heritage Society",
    "wof:placetype":"venue"
},
  "geometry": {"coordinates":[-55.757942,47.094414],"type":"Point"}
}