{
  "type": "Feature",
  "properties": {
    "iso:country":"CA",
    "sg:city":"Barrie",
    "sg:classifiers":[
        {
            "category":"Education",
            "subcategory":"Dance Studio",
            "type":"Public Place"
        }
    ],
    "sg:phone":"+1 705 726 5126",
    "sg:postcode":"L4N 2E3",
    "sg:province":"ON",
    "sg:tags":[
        "instruction",
        "dancing"
    ],
    "wof:name":"Huronia Dance Ctr",
    "wof:placetype":"venue"
},
  "geometry": {"coordinates":[-79.699371,44.375378],"type":"Point"}
}