{
  "type": "Feature",
  "properties": {
    "iso:country":"CA",
    "sg:city":"Fort Erie",
    "sg:classifiers":[
        {
            "category":"Shopping",
            "subcategory":"Clothing, Apparel, & Fashions",
            "type":"Retail Goods"
        }
    ],
    "sg:phone":"+1 905 991 9332",
    "sg:postcode":"L2A 5S6",
    "sg:province":"ON",
    "wof:name":"Jay Set",
    "wof:placetype":"venue"
},
  "geometry": {"coordinates":[-78.92087554930001,42.9055023193],"type":"Point"}
}