{
  "type": "Feature",
  "properties": {
    "addr:full":"345 Queen St W #6 Brampton ON L6Y 3A9",
    "addr:housenumber":"345",
    "addr:postcode":"l6y 3a9",
    "addr:street":"Queen St W # 6",
    "iso:country":"CA",
    "sg:address":"345 Queen St W #6",
    "sg:city":"Brampton",
    "sg:classifiers":[
        {
            "category":"Shopping",
            "subcategory":"Florist",
            "type":"Retail Goods"
        }
    ],
    "sg:phone":"+1 905 452 9500",
    "sg:postcode":"L6Y 3A9",
    "sg:province":"ON",
    "wof:name":"Artistry in Flowers",
    "wof:placetype":"venue"
},
  "geometry": {"coordinates":[-79.769875,43.676762],"type":"Point"}
}