{
  "type": "Feature",
  "properties": {
    "addr:full":"1845 Kryczka Pl Kamloops BC V1S 1S4",
    "addr:housenumber":"1845",
    "addr:postcode":"bc v1s 1s4",
    "addr:street":"Kryczka Pl",
    "iso:country":"CA",
    "sg:address":"1845 Kryczka Pl",
    "sg:city":"Kamloops",
    "sg:classifiers":[
        {
            "category":"Wholesale",
            "subcategory":"Furniture",
            "type":"Manufacturing & Wholesale Goods"
        }
    ],
    "sg:phone":"+1 250 372 9321",
    "sg:postcode":"V1S 1S4",
    "sg:province":"BC",
    "wof:name":"Gbc Canada Inc",
    "wof:placetype":"venue"
},
  "geometry": {"coordinates":[-120.3993,50.656776],"type":"Point"}
}