{
  "type": "Feature",
  "properties": {
    "iso:country":"CA",
    "sg:address":"854 Fennell Ave E",
    "sg:city":"Hamilton",
    "sg:classifiers":[
        {
            "category":"Shopping",
            "subcategory":"Clothing, Apparel, & Fashions",
            "type":"Retail Goods"
        }
    ],
    "sg:phone":"+1 905 389 9300",
    "sg:postcode":"L8V 1W1",
    "sg:province":"ON",
    "sg:tags":[
        "tailor"
    ],
    "wof:name":"Fennell Tailoring & Altrtns",
    "wof:placetype":"venue"
},
  "geometry": {"coordinates":[-79.8455505371,43.2294883728],"type":"Point"}
}