{
  "type": "Feature",
  "properties": {
    "addr:full":"Industiral Park Rd Channel-Port-Aux-Basques NL A0M 1C0",
    "addr:postcode":"a0m 1c0",
    "addr:street":"Park Rd",
    "iso:country":"CA",
    "sg:address":"Industiral Park Rd",
    "sg:city":"Channel-Port-Aux-Basques",
    "sg:classifiers":[
        {
            "category":"Home & Garden",
            "subcategory":"Furniture",
            "type":"Retail Goods"
        }
    ],
    "sg:phone":"+1 709 695 7490",
    "sg:postcode":"A0M 1C0",
    "sg:province":"NL",
    "sg:tags":[
        "building",
        "material"
    ],
    "wof:name":"Notre Dame Castle Building Ctr",
    "wof:placetype":"venue"
},
  "geometry": {"coordinates":[-59.18475,47.593288],"type":"Point"}
}