{
  "type": "Feature",
  "properties": {
    "addr:full":"5058 214 St Langley BC V3A 5B7",
    "addr:housenumber":"5058",
    "addr:postcode":"v3a 5b7",
    "addr:street":"214 St",
    "iso:country":"CA",
    "sg:address":"5058 214 St",
    "sg:city":"Langley",
    "sg:classifiers":[
        {
            "category":"Manufacturing",
            "subcategory":"Printing",
            "type":"Manufacturing & Wholesale Goods"
        }
    ],
    "sg:phone":"+1 604 530 0001",
    "sg:postcode":"V3A 5B7",
    "sg:province":"BC",
    "sg:tags":[
        "printer"
    ],
    "wof:name":"Pear Creative",
    "wof:placetype":"venue"
},
  "geometry": {"coordinates":[-122.630203247,49.0941314697],"type":"Point"}
}