{
  "type": "Feature",
  "properties": {
    "addr:full":"33 Rue Notre-Dame E Victoriaville QC G6P 3Z4",
    "addr:housenumber":"33",
    "addr:postcode":"g6p 3z4",
    "addr:street":"Rue Notre-Dame E",
    "iso:country":"CA",
    "sg:address":"33 Rue Notre-Dame E",
    "sg:city":"Victoriaville",
    "sg:classifiers":[
        {
            "category":"Banks & Credit Unions",
            "subcategory":"Bank",
            "type":"Services"
        }
    ],
    "sg:phone":"+1 819 758 2141",
    "sg:postcode":"G6P 3Z4",
    "sg:province":"QC",
    "wof:name":"Centre DE Financement Desjard",
    "wof:placetype":"venue"
},
  "geometry": {"coordinates":[-71.9578781128,46.0558738708],"type":"Point"}
}