{
  "type": "Feature",
  "properties": {
    "addr:full":"Scarborough ON M1B 5P3",
    "addr:postcode":"m1b 5p3",
    "iso:country":"CA",
    "sg:city":"Scarborough",
    "sg:classifiers":[
        {
            "category":"Wholesale",
            "subcategory":"Groceries",
            "type":"Manufacturing & Wholesale Goods"
        }
    ],
    "sg:phone":"+1 416 208 7050",
    "sg:postcode":"M1B 5P3",
    "sg:province":"ON",
    "sg:tags":[
        "food",
        "product"
    ],
    "wof:name":"Pak Fok Food Products Inc",
    "wof:placetype":"venue"
},
  "geometry": {"coordinates":[-79.1939315796,43.8069000244],"type":"Point"}
}