{
  "type": "Feature",
  "properties": {
    "addr:full":"2880 Ch Des Quatre-Bourgeois Sainte-Foy QC G1V 4X7",
    "addr:postcode":"2880;g1v 4x7",
    "addr:street":"Ch Des Quatre-Bourgeois",
    "iso:country":"CA",
    "sg:address":"2880 Ch Des Quatre-Bourgeois",
    "sg:city":"Sainte-Foy",
    "sg:classifiers":[
        {
            "category":"Shopping",
            "subcategory":"Pharmacy",
            "type":"Retail Goods"
        }
    ],
    "sg:phone":"+1 418 659 1000",
    "sg:postcode":"G1V 4X7",
    "sg:province":"QC",
    "wof:name":"Centre D'Escompte Racine",
    "wof:placetype":"venue"
},
  "geometry": {"coordinates":[-71.30061340330001,46.7737617493],"type":"Point"}
}