{
  "type": "Feature",
  "properties": {
    "addr:full":"448 Rue Zephyr Laval QC H7X 2P8",
    "addr:housenumber":"448",
    "addr:postcode":"h7x 2p8",
    "addr:street":"Rue Zephyr",
    "iso:country":"CA",
    "sg:address":"448 Rue Zephyr",
    "sg:city":"Laval",
    "sg:classifiers":[
        {
            "category":"Organizations",
            "subcategory":"Membership Organization",
            "type":"Services"
        }
    ],
    "sg:phone":"+1 450 689 2489",
    "sg:postcode":"H7X 2P8",
    "sg:province":"QC",
    "wof:name":"Canadian Citizens Movement",
    "wof:placetype":"venue"
},
  "geometry": {"coordinates":[-73.74463653559999,45.5515670776],"type":"Point"}
}