{
  "type": "Feature",
  "properties": {
    "addr:full":"425 Explorer Cres Prince George BC V2M 5S3",
    "addr:housenumber":"425",
    "addr:postcode":"v2m 5s3",
    "addr:street":"Explorer Cres",
    "iso:country":"CA",
    "sg:address":"425 Explorer Cres",
    "sg:city":"Prince George",
    "sg:classifiers":[
        {
            "category":"Building & Trades",
            "subcategory":"Construction",
            "type":"Services"
        }
    ],
    "sg:phone":"+1 250 564 7921",
    "sg:postcode":"V2M 5S3",
    "sg:province":"BC",
    "sg:tags":[
        "general",
        "contractor"
    ],
    "wof:name":"Maple Masonry Ltd",
    "wof:placetype":"venue"
},
  "geometry": {"coordinates":[-122.804451,53.921707],"type":"Point"}
}