{
  "type": "Feature",
  "properties": {
    "addr:full":"1783 Plessis Rd #14 Winnipeg MB R3W 1N3",
    "addr:housenumber":"1783",
    "addr:postcode":"r3w 1n3",
    "addr:street":"Plessis Rd # 14",
    "iso:country":"CA",
    "sg:address":"1783 Plessis Rd #14",
    "sg:city":"Winnipeg",
    "sg:classifiers":[
        {
            "category":"Personal",
            "subcategory":"Beauty Salon",
            "type":"Services"
        }
    ],
    "sg:phone":"+1 204 669 2713",
    "sg:postcode":"R3W 1N3",
    "sg:province":"MB",
    "wof:name":"Gale, Roberta",
    "wof:placetype":"venue"
},
  "geometry": {"coordinates":[-97.0249862671,49.91065979],"type":"Point"}
}