{
  "type": "Feature",
  "properties": {
    "addr:full":"1307 10 Ave SE Calgary AB T2G 0W8",
    "addr:housenumber":"1307",
    "addr:postcode":"t2g 0w8",
    "addr:street":"10 Ave Se",
    "iso:country":"CA",
    "sg:address":"1307 10 Ave SE",
    "sg:city":"Calgary",
    "sg:classifiers":[
        {
            "category":"Organizations",
            "subcategory":"Religious Organization",
            "type":"Services"
        }
    ],
    "sg:phone":"+1 403 265 5876",
    "sg:postcode":"T2G 0W8",
    "sg:province":"AB",
    "sg:tags":[
        "church"
    ],
    "wof:name":"Standard Church of America",
    "wof:placetype":"venue"
},
  "geometry": {"coordinates":[-114.03482099999999,51.040134],"type":"Point"}
}