{
  "type": "Feature",
  "properties": {
    "addr:full":"5210 Highway 69 N Hanmer ON P3P 1C4",
    "addr:housenumber":"5210",
    "addr:postcode":"p3p 1c4",
    "addr:street":"Highway 69 N",
    "iso:country":"CA",
    "sg:address":"5210 Highway 69 N",
    "sg:city":"Hanmer",
    "sg:classifiers":[
        {
            "category":"Utilities",
            "subcategory":"Fuel Oil & Lpg",
            "type":"Services"
        }
    ],
    "sg:phone":"+1 705 969 7241",
    "sg:postcode":"P3P 1C4",
    "sg:province":"ON",
    "sg:tags":[
        "firewood"
    ],
    "wof:name":"Ray Trepanier Firewood",
    "wof:placetype":"venue"
},
  "geometry": {"coordinates":[-80.9448013306,46.6524963379],"type":"Point"}
}