{
  "type": "Feature",
  "properties": {
    "addr:full":"Calgary AB T2H 2V2",
    "addr:postcode":"t2h 2v2",
    "iso:country":"CA",
    "sg:city":"Calgary",
    "sg:classifiers":[
        {
            "category":"Shopping",
            "subcategory":"Shoes",
            "type":"Retail Goods"
        }
    ],
    "sg:phone":"+1 403 252 7229",
    "sg:postcode":"T2H 2V2",
    "sg:province":"AB",
    "sg:tags":[
        "uniform"
    ],
    "wof:name":"Nursing Station Inc",
    "wof:placetype":"venue"
},
  "geometry": {"coordinates":[-114.063187,51.045071],"type":"Point"}
}