{
  "type": "Feature",
  "properties": {
    "addr:full":"426 Huron St Stratford ON N5A 5T7",
    "addr:housenumber":"426",
    "addr:postcode":"stratford;n5a 5t7",
    "addr:street":"Huron St",
    "iso:country":"CA",
    "sg:address":"426 Huron St",
    "sg:city":"Stratford",
    "sg:classifiers":[
        {
            "category":"Shopping",
            "subcategory":"Music",
            "type":"Retail Goods"
        }
    ],
    "sg:phone":"+1 519 273 5531",
    "sg:postcode":"N5A 5T7",
    "sg:province":"ON",
    "sg:tags":[
        "compact",
        "video",
        "disc",
        "tape",
        "record"
    ],
    "wof:name":"Video Plus Books",
    "wof:placetype":"venue"
},
  "geometry": {"coordinates":[-80.99844400000001,43.378807],"type":"Point"}
}