{
  "type": "Feature",
  "properties": {
    "iso:country":"CA",
    "sg:address":"Railway Ave",
    "sg:city":"Consul",
    "sg:classifiers":[
        {
            "category":"Travel",
            "subcategory":"Hotels & Motels",
            "type":"Entertainment"
        }
    ],
    "sg:phone":"+1 306 299 5666",
    "sg:postcode":"S0N 0P0",
    "sg:province":"SK",
    "wof:name":"South Country Inn",
    "wof:placetype":"venue"
},
  "geometry": {"coordinates":[-109.520584106,49.2942886353],"type":"Point"}
}