{
  "type": "Feature",
  "properties": {
    "addr:full":"415 Martin Pl Oyen AB T0J 2J0",
    "addr:housenumber":"415",
    "addr:postcode":"t0j 2j0",
    "addr:street":"Martin Pl",
    "iso:country":"CA",
    "sg:address":"415 Martin Pl",
    "sg:city":"Oyen",
    "sg:classifiers":[
        {
            "category":"Organizations",
            "subcategory":"Religious Organization",
            "type":"Services"
        }
    ],
    "sg:phone":"+1 403 664 3603",
    "sg:postcode":"T0J 2J0",
    "sg:province":"AB",
    "sg:tags":[
        "church"
    ],
    "wof:name":"Catholic Rectory",
    "wof:placetype":"venue"
},
  "geometry": {"coordinates":[-110.476570129,51.3506698608],"type":"Point"}
}