{
  "type": "Feature",
  "properties": {
    "iso:country":"CA",
    "sg:city":"North York",
    "sg:phone":"+1 416 740 5678",
    "sg:postcode":"M9L 1V9",
    "sg:province":"ON",
    "sg:tags":[
        "equipment",
        "supply"
    ],
    "wof:name":"Hrd Kitchen Svc Toronto Ltd",
    "wof:placetype":"venue"
},
  "geometry": {"coordinates":[-79.54373168950001,43.7579841614],"type":"Point"}
}