{
  "type": "Feature",
  "properties": {
    "addr:full":"91 Rue Tremblay Sainte-Brigitte-DE-Laval QC G0A 3K0",
    "addr:housenumber":"91",
    "addr:postcode":"g0a 3k0",
    "addr:street":"Rue Tremblay",
    "iso:country":"CA",
    "sg:address":"91 Rue Tremblay",
    "sg:city":"Sainte-Brigitte-DE-Laval",
    "sg:classifiers":[
        {
            "category":"Building & Trades",
            "subcategory":"Electrical",
            "type":"Services"
        }
    ],
    "sg:phone":"+1 418 683 4981",
    "sg:postcode":"G0A 3K0",
    "sg:province":"QC",
    "sg:tags":[
        "electric",
        "contractor"
    ],
    "wof:name":"Luminore Electrique Inc",
    "wof:placetype":"venue"
},
  "geometry": {"coordinates":[-71.213882,46.993851],"type":"Point"}
}