{
  "type": "Feature",
  "properties": {
    "addr:full":"717 Belfast Rd Ottawa ON K1G 0Z4",
    "addr:housenumber":"717",
    "addr:postcode":"k1g 0z4",
    "addr:street":"Belfast Rd",
    "iso:country":"CA",
    "sg:address":"717 Belfast Rd",
    "sg:city":"Ottawa",
    "sg:classifiers":[
        {
            "category":"Recreation",
            "type":"Entertainment"
        }
    ],
    "sg:phone":"+1 613 244 1267",
    "sg:postcode":"K1G 0Z4",
    "sg:province":"ON",
    "sg:tags":[
        "club",
        "bridge"
    ],
    "wof:name":"Ottawa Bridge Ctr",
    "wof:placetype":"venue"
},
  "geometry": {"coordinates":[-75.643906,45.415298],"type":"Point"}
}