{
  "type": "Feature",
  "properties": {
    "addr:full":"236 Barrie St Thornton ON L0L 2N0",
    "addr:housenumber":"236",
    "addr:postcode":"l0l 2n0",
    "addr:street":"Barrie St",
    "iso:country":"CA",
    "sg:address":"236 Barrie St",
    "sg:city":"Thornton",
    "sg:classifiers":[
        {
            "category":"Restaurant",
            "type":"Food & Drink"
        }
    ],
    "sg:phone":"+1 705 458 1500",
    "sg:postcode":"L0L 2N0",
    "sg:province":"ON",
    "sg:tags":[
        "parlor",
        "ice",
        "cream"
    ],
    "wof:name":"Thornton Ice Cream Parlour",
    "wof:placetype":"venue"
},
  "geometry": {"coordinates":[-79.721733,44.270432],"type":"Point"}
}