{
  "type": "Feature",
  "properties": {
    "addr:full":"2455 6th Ave W Vancouver BC V6K 1W2",
    "addr:housenumber":"2455",
    "addr:postcode":"v6k 1w2",
    "addr:street":"6Th Ave W",
    "iso:country":"CA",
    "sg:address":"2455 6th Ave W",
    "sg:city":"Vancouver",
    "sg:classifiers":[
        {
            "category":"Travel",
            "subcategory":"Hotels & Motels",
            "type":"Entertainment"
        }
    ],
    "sg:phone":"+1 604 732 8004",
    "sg:postcode":"V6K 1W2",
    "sg:province":"BC",
    "sg:tags":[
        "breakfast",
        "accommodation",
        "bed"
    ],
    "wof:name":"Kitsilano Heritage House B & B",
    "wof:placetype":"venue"
},
  "geometry": {"coordinates":[-123.161095,49.266743],"type":"Point"}
}