{
  "type": "Feature",
  "properties": {
    "addr:full":"11700 96A Ave Surrey BC V3V 2A1",
    "addr:housenumber":"11700",
    "addr:postcode":"v3v 2a1",
    "addr:street":"96A Ave",
    "iso:country":"CA",
    "sg:address":"11700 96A Ave",
    "sg:city":"Surrey",
    "sg:classifiers":[
        {
            "category":"Professional",
            "subcategory":"Business Services",
            "type":"Services"
        }
    ],
    "sg:phone":"+1 604 582 4848",
    "sg:postcode":"V3V 2A1",
    "sg:province":"BC",
    "sg:tags":[
        "inspection"
    ],
    "wof:name":"All BC Home Inspection",
    "wof:placetype":"venue"
},
  "geometry": {"coordinates":[-122.830215,49.105179],"type":"Point"}
}