{
  "type": "Feature",
  "properties": {
    "addr:full":"1601 Tricont Ave Whitby ON L1N 7N5",
    "addr:housenumber":"1601",
    "addr:postcode":"l1n 7n5",
    "addr:street":"Tricont Ave",
    "iso:country":"CA",
    "sg:address":"1601 Tricont Ave",
    "sg:city":"Whitby",
    "sg:classifiers":[
        {
            "category":"Freight",
            "type":"Transportation"
        }
    ],
    "sg:phone":"+1 905 434 8577",
    "sg:postcode":"L1N 7N5",
    "sg:province":"ON",
    "sg:tags":[
        "trucking"
    ],
    "wof:name":"Tst Automotive Svc Inc",
    "wof:placetype":"venue"
},
  "geometry": {"coordinates":[-78.9015197754,43.8624000549],"type":"Point"}
}