{
  "type": "Feature",
  "properties": {
    "addr:full":"300 Applewood Cres Concord ON L4K 5C7",
    "addr:housenumber":"300",
    "addr:postcode":"l4k 5c7",
    "addr:street":"Applewood Cres",
    "iso:country":"CA",
    "sg:address":"300 Applewood Cres",
    "sg:city":"Concord",
    "sg:classifiers":[
        {
            "category":"Wholesale",
            "subcategory":"Electrical",
            "type":"Manufacturing & Wholesale Goods"
        }
    ],
    "sg:phone":"+1 905 760 9944",
    "sg:postcode":"L4K 5C7",
    "sg:province":"ON",
    "sg:tags":[
        "appliance"
    ],
    "wof:name":"Sanyo Fisher Canada Inc",
    "wof:placetype":"venue"
},
  "geometry": {"coordinates":[-79.539658,43.807049],"type":"Point"}
}