{
  "type": "Feature",
  "properties": {
    "addr:full":"115 King St Stellarton NS B0K 1S0",
    "addr:housenumber":"115",
    "addr:postcode":"b0k 1s0",
    "addr:street":"King St",
    "iso:country":"CA",
    "sg:address":"115 King St",
    "sg:city":"Stellarton",
    "sg:classifiers":[
        {
            "category":"Food & Beverages",
            "subcategory":"Groceries & Convenience Stores",
            "type":"Retail Goods"
        }
    ],
    "sg:phone":"+1 902 752 8371",
    "sg:postcode":"B0K 1S0",
    "sg:province":"NS",
    "sg:tags":[
        "product",
        "snack"
    ],
    "wof:name":"Sobeys Inc",
    "wof:placetype":"venue"
},
  "geometry": {"coordinates":[-62.6572,45.56057],"type":"Point"}
}