{
  "type": "Feature",
  "properties": {
    "addr:full":"11562 139 Ave NW Edmonton AB T5X 3L6",
    "addr:housenumber":"11562",
    "addr:postcode":"t5x 3l6",
    "addr:street":"139 Ave Nw",
    "iso:country":"CA",
    "sg:address":"11562 139 Ave NW",
    "sg:city":"Edmonton",
    "sg:classifiers":[
        {
            "category":"Building & Trades",
            "subcategory":"Construction",
            "type":"Services"
        }
    ],
    "sg:phone":"+1 780 456 5930",
    "sg:postcode":"T5X 3L6",
    "sg:province":"AB",
    "sg:tags":[
        "painter"
    ],
    "wof:name":"N Aleks Painting & Decorating",
    "wof:placetype":"venue"
},
  "geometry": {"coordinates":[-113.520309,53.601986],"type":"Point"}
}