{
  "type": "Feature",
  "properties": {
    "iso:country":"CA",
    "sg:city":"Mississauga",
    "sg:classifiers":[
        {
            "category":"Social Services",
            "type":"Services"
        }
    ],
    "sg:phone":"+1 905 795 3521",
    "sg:postcode":"L5T 2Y6",
    "sg:province":"ON",
    "sg:tags":[
        "counselor",
        "marriage",
        "family"
    ],
    "wof:name":"Peel Collaborative Child",
    "wof:placetype":"venue"
},
  "geometry": {"coordinates":[-79.703049,43.646336],"type":"Point"}
}