{
  "type": "Feature",
  "properties": {
    "iso:country":"CA",
    "sg:city":"Bonavista",
    "sg:classifiers":[
        {
            "category":"Government",
            "subcategory":"Office",
            "type":"Public Place"
        }
    ],
    "sg:phone":"+1 709 468 7914",
    "sg:postcode":"A0C 1B0",
    "sg:province":"NL",
    "wof:name":"Newfoundland Fisheries Dept",
    "wof:placetype":"venue"
},
  "geometry": {"coordinates":[-53.0991287231,48.6561279297],"type":"Point"}
}