{
  "type": "Feature",
  "properties": {
    "addr:full":"94 Front E Bobcaygeon ON K0M 1A0",
    "addr:housenumber":"94",
    "addr:postcode":"k0m 1a0",
    "addr:street":"Front E Bobcaygeon",
    "iso:country":"CA",
    "sg:address":"94 Front E",
    "sg:city":"Bobcaygeon",
    "sg:classifiers":[
        {
            "category":"Travel",
            "subcategory":"Hotels & Motels",
            "type":"Entertainment"
        }
    ],
    "sg:phone":"+1 705 738 2295",
    "sg:postcode":"K0M 1A0",
    "sg:province":"ON",
    "sg:tags":[
        "cottage",
        "resort",
        "cabin"
    ],
    "wof:name":"Southwinds Resort & Marina",
    "wof:placetype":"venue"
},
  "geometry": {"coordinates":[-78.54167200000001,44.541088],"type":"Point"}
}