{
  "type": "Feature",
  "properties": {
    "addr:full":"163 Main St W Shelburne ON L0N 1S0",
    "addr:housenumber":"163",
    "addr:postcode":"l0n 1s0",
    "addr:street":"Main St W",
    "iso:country":"CA",
    "sg:address":"163 Main St W",
    "sg:city":"Shelburne",
    "sg:classifiers":[
        {
            "category":"Professional",
            "subcategory":"Employment Agencies",
            "type":"Services"
        }
    ],
    "sg:phone":"+1 519 925 9004",
    "sg:postcode":"L0N 1S0",
    "sg:province":"ON",
    "sg:tags":[
        "opportunity"
    ],
    "wof:name":"Adecco Employment Svc",
    "wof:placetype":"venue"
},
  "geometry": {"coordinates":[-80.20645141599999,44.0777778625],"type":"Point"}
}