{
  "type": "Feature",
  "properties": {
    "iso:country":"CA",
    "sg:address":"1030 Rue Sainte-Angele",
    "sg:city":"Trois-Rivieres",
    "sg:classifiers":[
        {
            "category":"Shopping",
            "subcategory":"Pharmacy",
            "type":"Retail Goods"
        }
    ],
    "sg:phone":"+1 819 378 4043",
    "sg:postcode":"G9A 1M8",
    "sg:province":"QC",
    "wof:name":"Jacob & Jacob",
    "wof:placetype":"venue"
},
  "geometry": {"coordinates":[-72.543526,46.35125],"type":"Point"}
}