{
  "type": "Feature",
  "properties": {
    "addr:full":"204 Main St Carlyle SK S0C 0R0",
    "addr:housenumber":"204",
    "addr:postcode":"s0c 0r0",
    "addr:street":"Main St",
    "iso:country":"CA",
    "sg:address":"204 Main St",
    "sg:city":"Carlyle",
    "sg:classifiers":[
        {
            "category":"Mining & Drilling",
            "type":"Manufacturing & Wholesale Goods"
        }
    ],
    "sg:phone":"+1 306 453 6000",
    "sg:postcode":"S0C 0R0",
    "sg:province":"SK",
    "sg:tags":[
        "development",
        "gas",
        "oil",
        "exploration"
    ],
    "wof:name":"Spectrum Resource Group Inc",
    "wof:placetype":"venue"
},
  "geometry": {"coordinates":[-102.26783,49.633331],"type":"Point"}
}