{
  "type": "Feature",
  "properties": {
    "addr:full":"730 Rue Child Coaticook QC J1A 2C2",
    "addr:housenumber":"730",
    "addr:postcode":"j1a 2c2",
    "addr:street":"Rue Child",
    "iso:country":"CA",
    "sg:address":"730 Rue Child",
    "sg:city":"Coaticook",
    "sg:classifiers":[
        {
            "category":"Shopping",
            "subcategory":"Bicycles & Sporting Goods",
            "type":"Retail Goods"
        }
    ],
    "sg:phone":"+1 819 849 7130",
    "sg:postcode":"J1A 2C2",
    "sg:province":"QC",
    "sg:tags":[
        "equipment",
        "archery",
        "supply"
    ],
    "wof:name":"Repere Du Chasseur Enr",
    "wof:placetype":"venue"
},
  "geometry": {"coordinates":[-71.8103179932,45.1473846436],"type":"Point"}
}