{
  "type": "Feature",
  "properties": {
    "addr:full":"Flin Flon MB R8A 1K2",
    "addr:postcode":"r8a 1k2",
    "iso:country":"CA",
    "sg:city":"Flin Flon",
    "sg:classifiers":[
        {
            "category":"Government",
            "subcategory":"Office",
            "type":"Public Place"
        }
    ],
    "sg:phone":"+1 204 687 1615",
    "sg:postcode":"R8A 1K2",
    "sg:province":"MB",
    "wof:name":"Manitoba Justice",
    "wof:placetype":"venue"
},
  "geometry": {"coordinates":[-101.877449,54.768303],"type":"Point"}
}