{
  "type": "Feature",
  "properties": {
    "addr:full":"4758 Gulch Rd Armstrong BC V0E 1B4",
    "addr:housenumber":"4758",
    "addr:postcode":"v0e 1b4",
    "addr:street":"Gulch Rd",
    "iso:country":"CA",
    "sg:address":"4758 Gulch Rd",
    "sg:city":"Armstrong",
    "sg:classifiers":[
        {
            "category":"Manufacturing",
            "subcategory":"Food",
            "type":"Manufacturing & Wholesale Goods"
        }
    ],
    "sg:phone":"+1 250 546 2164",
    "sg:postcode":"V0E 1B4",
    "sg:province":"BC",
    "sg:tags":[
        "winery"
    ],
    "wof:name":"Hunting Hawk Vineyards",
    "wof:placetype":"venue"
},
  "geometry": {"coordinates":[-119.183701,50.441818],"type":"Point"}
}