{
  "type": "Feature",
  "properties": {
    "iso:country":"CA",
    "sg:address":"7900 Rue Saint-Denis",
    "sg:city":"Montreal",
    "sg:classifiers":[
        {
            "category":"Autos & Motor Vehicles",
            "subcategory":"Fuel & Gas Station",
            "type":"Retail Goods"
        }
    ],
    "sg:phone":"+1 514 387 5255",
    "sg:postcode":"H2R 2G1",
    "sg:province":"QC",
    "sg:tags":[
        "oil"
    ],
    "wof:name":"Centre DE L'Auto Michel Gravel",
    "wof:placetype":"venue"
},
  "geometry": {"coordinates":[-73.626503,45.541676],"type":"Point"}
}