{
  "type": "Feature",
  "properties": {
    "iso:country":"CA",
    "sg:address":"30 Cedar St",
    "sg:city":"Sudbury",
    "sg:classifiers":[
        {
            "category":"Restaurant",
            "type":"Food & Drink"
        }
    ],
    "sg:phone":"+1 705 673 5151",
    "sg:postcode":"P3E 1A4",
    "sg:province":"ON",
    "wof:name":"Tower Cafe",
    "wof:placetype":"venue"
},
  "geometry": {"coordinates":[-80.996284,46.492344],"type":"Point"}
}