{
  "type": "Feature",
  "properties": {
    "addr:full":"575 Boul Leclerc O Granby QC J2G 1W8",
    "addr:housenumber":"575",
    "addr:postcode":"j2g 1w8",
    "addr:street":"Boul Leclerc O",
    "iso:country":"CA",
    "sg:address":"575 Boul Leclerc O",
    "sg:city":"Granby",
    "sg:classifiers":[
        {
            "category":"Building & Trades",
            "subcategory":"Construction",
            "type":"Services"
        }
    ],
    "sg:phone":"+1 450 378 7454",
    "sg:postcode":"J2G 1W8",
    "sg:province":"QC",
    "sg:tags":[
        "plastering",
        "contractor"
    ],
    "wof:name":"Claude Cordeau Stucco Inc",
    "wof:placetype":"venue"
},
  "geometry": {"coordinates":[-72.73814400000001,45.409546],"type":"Point"}
}