{
  "type": "Feature",
  "properties": {
    "addr:full":"481 King St E Kitchener ON N2G 2L7",
    "addr:housenumber":"481",
    "addr:postcode":"n2g 2l7",
    "addr:street":"King St E",
    "iso:country":"CA",
    "sg:address":"481 King St E",
    "sg:city":"Kitchener",
    "sg:classifiers":[
        {
            "category":"Autos & Motor Vehicles",
            "subcategory":"Automobile Sales",
            "type":"Retail Goods"
        }
    ],
    "sg:phone":"+1 519 744 3306",
    "sg:postcode":"N2G 2L7",
    "sg:province":"ON",
    "sg:tags":[
        "car",
        "dealer"
    ],
    "wof:name":"Gascho Automotive Ltd",
    "wof:placetype":"venue"
},
  "geometry": {"coordinates":[-80.48174285890001,43.4462890625],"type":"Point"}
}