{
  "type": "Feature",
  "properties": {
    "addr:full":"2365 Valley Stream Pl Oakville ON L6H 6X1",
    "addr:housenumber":"2365",
    "addr:postcode":"l6h 6x1",
    "addr:street":"Valley;Pl",
    "iso:country":"CA",
    "sg:address":"2365 Valley Stream Pl",
    "sg:city":"Oakville",
    "sg:classifiers":[
        {
            "category":"Building & Trades",
            "subcategory":"Electrical",
            "type":"Services"
        }
    ],
    "sg:phone":"+1 905 257 3502",
    "sg:postcode":"L6H 6X1",
    "sg:province":"ON",
    "sg:tags":[
        "electric",
        "contractor"
    ],
    "wof:name":"Genbro Electric",
    "wof:placetype":"venue"
},
  "geometry": {"coordinates":[-79.74365997309999,43.4616622925],"type":"Point"}
}