{
  "type": "Feature",
  "properties": {
    "iso:country":"CA",
    "sg:address":"971 Germain St",
    "sg:city":"Sarnia",
    "sg:classifiers":[
        {
            "category":"Organizations",
            "subcategory":"Professional Association",
            "type":"Services"
        }
    ],
    "sg:phone":"+1 519 542 4298",
    "sg:postcode":"N7S 1L9",
    "sg:province":"ON",
    "wof:name":"Christian Horizons",
    "wof:placetype":"venue"
},
  "geometry": {"coordinates":[-82.373283,42.97525],"type":"Point"}
}