{
  "type": "Feature",
  "properties": {
    "addr:full":"Cap-DE-LA-Madeleine QC G8T 7A6",
    "addr:postcode":"g8t 7a6",
    "iso:country":"CA",
    "sg:city":"Cap-DE-LA-Madeleine",
    "sg:classifiers":[
        {
            "category":"Professional",
            "subcategory":"Business Services",
            "type":"Services"
        }
    ],
    "sg:phone":"+1 819 376 5646",
    "sg:postcode":"G8T 7A6",
    "sg:province":"QC",
    "sg:tags":[
        "notary"
    ],
    "wof:name":"Pothier, Nancy",
    "wof:placetype":"venue"
},
  "geometry": {"coordinates":[-72.549767,46.386002],"type":"Point"}
}