{
  "type": "Feature",
  "properties": {
    "addr:full":"2 Moores Dr Mount Pearl NL A1N 2L9",
    "addr:housenumber":"2",
    "addr:postcode":"a1n 2l9",
    "addr:street":"Moores Dr",
    "iso:country":"CA",
    "sg:address":"2 Moores Dr",
    "sg:city":"Mount Pearl",
    "sg:classifiers":[
        {
            "category":"Shopping",
            "type":"Retail Goods"
        }
    ],
    "sg:phone":"+1 709 364 1727",
    "sg:postcode":"A1N 2L9",
    "sg:province":"NL",
    "sg:tags":[
        "art",
        "gallery",
        "dealer"
    ],
    "wof:name":"Butler Framing & Gallery Inc",
    "wof:placetype":"venue"
},
  "geometry": {"coordinates":[-52.819668,47.51783],"type":"Point"}
}