{
  "type": "Feature",
  "properties": {
    "addr:full":"47 Maillard St Sydney NS B1S 2P5",
    "addr:housenumber":"47",
    "addr:postcode":"b1s 2p5",
    "addr:street":"Maillard St",
    "iso:country":"CA",
    "sg:address":"47 Maillard St",
    "sg:city":"Sydney",
    "sg:classifiers":[
        {
            "category":"Organizations",
            "subcategory":"Non-profit Organization",
            "type":"Services"
        }
    ],
    "sg:phone":"+1 902 567 0336",
    "sg:postcode":"B1S 2P5",
    "sg:province":"NS",
    "sg:tags":[
        "charitable",
        "institution"
    ],
    "wof:name":"Mi'Kmaw Kina Matnewey",
    "wof:placetype":"venue"
},
  "geometry": {"coordinates":[-60.195366,46.117867],"type":"Point"}
}