{
  "type": "Feature",
  "properties": {
    "iso:country":"CA",
    "sg:city":"Calgary",
    "sg:classifiers":[
        {
            "category":"Education",
            "subcategory":"College",
            "type":"Public Place"
        }
    ],
    "sg:phone":"+1 403 270 0936",
    "sg:postcode":"T2N 3P7",
    "sg:province":"AB",
    "sg:tags":[
        "academic",
        "school"
    ],
    "wof:name":"Wild Rose College-Ntrl Healing",
    "wof:placetype":"venue"
},
  "geometry": {"coordinates":[-114.09065246599999,51.0526199341],"type":"Point"}
}