{
  "type": "Feature",
  "properties": {
    "iso:country":"CA",
    "sg:address":"130 Adelaide St W",
    "sg:city":"Toronto",
    "sg:classifiers":[
        {
            "category":"Travel",
            "subcategory":"Campground",
            "type":"Entertainment"
        }
    ],
    "sg:phone":"+1 416 862 1231",
    "sg:postcode":"M5H 3P5",
    "sg:province":"ON",
    "sg:tags":[
        "camp"
    ],
    "wof:name":"Explore Canada",
    "wof:placetype":"venue"
},
  "geometry": {"coordinates":[-79.3838882446,43.6493530273],"type":"Point"}
}