{
  "type": "Feature",
  "properties": {
    "addr:full":"Richmond BC V6V 1J4",
    "addr:postcode":"v6v 1j4",
    "iso:country":"CA",
    "sg:city":"Richmond",
    "sg:classifiers":[
        {
            "category":"Home & Garden",
            "subcategory":"Furniture",
            "type":"Retail Goods"
        }
    ],
    "sg:phone":"+1 604 248 2180",
    "sg:postcode":"V6V 1J4",
    "sg:province":"BC",
    "sg:tags":[
        "interior",
        "consultant",
        "design",
        "decorator"
    ],
    "wof:name":"Jordans Casual Home",
    "wof:placetype":"venue"
},
  "geometry": {"coordinates":[-123.083809,49.192196],"type":"Point"}
}