{
  "type": "Feature",
  "properties": {
    "iso:country":"CA",
    "sg:address":"112 5th St",
    "sg:city":"Hague",
    "sg:classifiers":[
        {
            "category":"Organizations",
            "subcategory":"Religious Organization",
            "type":"Services"
        }
    ],
    "sg:phone":"+1 306 225 2264",
    "sg:postcode":"S0K 1X0",
    "sg:province":"SK",
    "sg:tags":[
        "church"
    ],
    "wof:name":"Hague Gospel Church",
    "wof:placetype":"venue"
},
  "geometry": {"coordinates":[-106.418701172,52.5095367432],"type":"Point"}
}