{
  "type": "Feature",
  "properties": {
    "addr:full":"Mississauga ON L4W 1A5",
    "addr:postcode":"l4w 1a5",
    "iso:country":"CA",
    "sg:city":"Mississauga",
    "sg:classifiers":[
        {
            "category":"Manufacturing",
            "subcategory":"Printing",
            "type":"Manufacturing & Wholesale Goods"
        }
    ],
    "sg:phone":"+1 905 602 1701",
    "sg:postcode":"L4W 1A5",
    "sg:province":"ON",
    "sg:tags":[
        "printer"
    ],
    "wof:name":"Sunnyshine Graphic & Printing",
    "wof:placetype":"venue"
},
  "geometry": {"coordinates":[-79.6180648804,43.6301078796],"type":"Point"}
}