{
  "type": "Feature",
  "properties": {
    "addr:full":"2289 Hwy 2 Milford Station NS B0N 1Y0",
    "addr:housenumber":"2289",
    "addr:postcode":"b0n 1y0",
    "addr:street":"Hwy 2 Milford",
    "iso:country":"CA",
    "sg:address":"2289 Hwy 2",
    "sg:city":"Milford Station",
    "sg:classifiers":[
        {
            "category":"Banks & Credit Unions",
            "subcategory":"Bank",
            "type":"Services"
        }
    ],
    "sg:phone":"+1 902 758 2927",
    "sg:postcode":"B0N 1Y0",
    "sg:province":"NS",
    "wof:name":"Heritage Credit Union Ltd",
    "wof:placetype":"venue"
},
  "geometry": {"coordinates":[-63.4336395264,45.0511436462],"type":"Point"}
}