{
  "type": "Feature",
  "properties": {
    "addr:full":"Guelph ON N1H 8N9",
    "addr:postcode":"n1h 8n9",
    "iso:country":"CA",
    "sg:city":"Guelph",
    "sg:classifiers":[
        {
            "category":"Health Services",
            "subcategory":"Clinic",
            "type":"Services"
        }
    ],
    "sg:phone":"+1 519 824 5544",
    "sg:postcode":"N1H 8N9",
    "sg:province":"ON",
    "sg:tags":[
        "information",
        "medical"
    ],
    "wof:name":"Community Mental Health Clinic",
    "wof:placetype":"venue"
},
  "geometry": {"coordinates":[-80.250694,43.547325],"type":"Point"}
}