{
  "type": "Feature",
  "properties": {
    "addr:full":"21 Connemara Pl St. John's NL A1A 3E3",
    "addr:housenumber":"21",
    "addr:postcode":"a1a 3e3",
    "addr:street":"Connemara Pl",
    "iso:country":"CA",
    "sg:address":"21 Connemara Pl",
    "sg:city":"St. John's",
    "sg:classifiers":[
        {
            "category":"Education",
            "subcategory":"Special Training",
            "type":"Public Place"
        }
    ],
    "sg:phone":"+1 709 753 0218",
    "sg:postcode":"A1A 3E3",
    "sg:province":"NL",
    "sg:tags":[
        "instruction",
        "music"
    ],
    "wof:name":"Music For Young Children",
    "wof:placetype":"venue"
},
  "geometry": {"coordinates":[-52.710449,47.608768],"type":"Point"}
}