{
  "type": "Feature",
  "properties": {
    "addr:full":"80 Davidson St Cannington ON L0E 1E0",
    "addr:housenumber":"80",
    "addr:postcode":"l0e 1e0",
    "addr:street":"Davidson St",
    "iso:country":"CA",
    "sg:address":"80 Davidson St",
    "sg:city":"Cannington",
    "sg:classifiers":[
        {
            "category":"Manufacturing",
            "subcategory":"Glass & Minerals",
            "type":"Manufacturing & Wholesale Goods"
        }
    ],
    "sg:phone":"+1 705 432 2748",
    "sg:postcode":"L0E 1E0",
    "sg:province":"ON",
    "sg:tags":[
        "mirror"
    ],
    "wof:name":"Ideal Glass & Mirror Makers",
    "wof:placetype":"venue"
},
  "geometry": {"coordinates":[-79.033615,44.347126],"type":"Point"}
}