{
  "type": "Feature",
  "properties": {
    "iso:country":"CA",
    "sg:city":"Whistler",
    "sg:classifiers":[
        {
            "category":"Health Services",
            "subcategory":"Chiropractor",
            "type":"Services"
        }
    ],
    "sg:phone":"+1 604 932 1922",
    "sg:postcode":"V0N 1B4",
    "sg:province":"BC",
    "wof:name":"Brusset, Jaqueline DC",
    "wof:placetype":"venue"
},
  "geometry": {"coordinates":[-122.954345703,50.1148262024],"type":"Point"}
}