{
  "type": "Feature",
  "properties": {
    "addr:full":"32 Hunt St Ajax ON L1S 3M2",
    "addr:housenumber":"32",
    "addr:postcode":"l1s 3m2",
    "addr:street":"Hunt St",
    "iso:country":"CA",
    "sg:address":"32 Hunt St",
    "sg:city":"Ajax",
    "sg:classifiers":[
        {
            "category":"Shopping",
            "subcategory":"Department Store",
            "type":"Retail Goods"
        }
    ],
    "sg:phone":"+1 905 428 2779",
    "sg:postcode":"L1S 3M2",
    "sg:province":"ON",
    "sg:tags":[
        "shop"
    ],
    "wof:name":"Bargain Zone",
    "wof:placetype":"venue"
},
  "geometry": {"coordinates":[-79.021034,43.847324],"type":"Point"}
}