{
  "type": "Feature",
  "properties": {
    "addr:full":"575 Palmer Rd NE Calgary AB T2E 7G4",
    "addr:housenumber":"575",
    "addr:postcode":"t2e 7g4",
    "addr:street":"Palmer Rd Ne",
    "iso:country":"CA",
    "sg:address":"575 Palmer Rd NE",
    "sg:city":"Calgary",
    "sg:classifiers":[
        {
            "category":"Autos & Motor Vehicles",
            "subcategory":"Automobile Sales",
            "type":"Retail Goods"
        }
    ],
    "sg:phone":"+1 403 296 0096",
    "sg:postcode":"T2E 7G4",
    "sg:province":"AB",
    "sg:tags":[
        "equipment",
        "aircraft",
        "parts",
        "supply"
    ],
    "wof:name":"Calgary Pilot Supply",
    "wof:placetype":"venue"
},
  "geometry": {"coordinates":[-114.01159699999999,51.099403],"type":"Point"}
}