{
  "type": "Feature",
  "properties": {
    "addr:full":"3641 Av Prud'Homme Montreal QC H4A 3H6",
    "addr:housenumber":"3641",
    "addr:postcode":"h4a 3h6",
    "addr:street":"Av Prud'Homme",
    "iso:country":"CA",
    "sg:address":"3641 Av Prud'Homme",
    "sg:city":"Montreal",
    "sg:classifiers":[
        {
            "category":"Education",
            "subcategory":"School",
            "type":"Public Place"
        }
    ],
    "sg:phone":"+1 514 486 5533",
    "sg:postcode":"H4A 3H6",
    "sg:province":"QC",
    "wof:name":"Centennial Academy Inc",
    "wof:placetype":"venue"
},
  "geometry": {"coordinates":[-73.554359436,45.5123100281],"type":"Point"}
}