{
  "type": "Feature",
  "properties": {
    "addr:full":"131 Wolf Willow Rd NW Edmonton AB T5T 7T7",
    "addr:housenumber":"131",
    "addr:postcode":"t5t 7t7",
    "addr:street":"Wolf Willow Rd Nw",
    "iso:country":"CA",
    "sg:address":"131 Wolf Willow Rd NW",
    "sg:city":"Edmonton",
    "sg:classifiers":[
        {
            "category":"Organizations",
            "subcategory":"Religious Organization",
            "type":"Services"
        }
    ],
    "sg:phone":"+1 780 488 8315",
    "sg:postcode":"T5T 7T7",
    "sg:province":"AB",
    "sg:tags":[
        "church"
    ],
    "wof:name":"Beth Israel Synagogue",
    "wof:placetype":"venue"
},
  "geometry": {"coordinates":[-113.61386899999999,53.504463],"type":"Point"}
}