{
  "type": "Feature",
  "properties": {
    "addr:full":"112 Reid Rd Kentville NS B4N 3V7",
    "addr:housenumber":"112",
    "addr:postcode":"b4n 3v7",
    "addr:street":"Reid Rd",
    "iso:country":"CA",
    "sg:address":"112 Reid Rd",
    "sg:city":"Kentville",
    "sg:classifiers":[
        {
            "category":"Retail",
            "subcategory":"Auto Repair",
            "type":"Services"
        }
    ],
    "sg:phone":"+1 902 678 2886",
    "sg:postcode":"B4N 3V7",
    "sg:province":"NS",
    "sg:tags":[
        "repairing",
        "automobile"
    ],
    "wof:name":"Perrys Auto Svc",
    "wof:placetype":"venue"
},
  "geometry": {"coordinates":[-64.494438,45.07692],"type":"Point"}
}