{
  "type": "Feature",
  "properties": {
    "addr:full":"4442 10th Ave Port Alberni BC V9Y 4X7",
    "addr:housenumber":"4442",
    "addr:postcode":"v9y 4x7",
    "addr:street":"10Th Ave",
    "iso:country":"CA",
    "sg:address":"4442 10th Ave",
    "sg:city":"Port Alberni",
    "sg:classifiers":[
        {
            "category":"Building & Trades",
            "subcategory":"Construction",
            "type":"Services"
        }
    ],
    "sg:phone":"+1 250 724 0611",
    "sg:postcode":"V9Y 4X7",
    "sg:province":"BC",
    "sg:tags":[
        "general",
        "contractor"
    ],
    "wof:name":"Rayner & Bracht Ltd",
    "wof:placetype":"venue"
},
  "geometry": {"coordinates":[-124.797966003,49.255657196],"type":"Point"}
}