{
  "type": "Feature",
  "properties": {
    "addr:full":"100 Boul DE Montarville # 200 Boucherville QC J4B 5M4",
    "addr:housenumber":"100",
    "addr:postcode":"j4b 5m4",
    "addr:street":"Boul De Montarville # 200",
    "iso:country":"CA",
    "sg:address":"100 Boul DE Montarville # 200",
    "sg:city":"Boucherville",
    "sg:classifiers":[
        {
            "category":"Shopping",
            "type":"Retail Goods"
        }
    ],
    "sg:phone":"+1 450 655 7886",
    "sg:postcode":"J4B 5M4",
    "sg:province":"QC",
    "sg:tags":[
        "hearing",
        "equipment",
        "supply",
        "impaired"
    ],
    "wof:name":"Dumais, Caroline",
    "wof:placetype":"venue"
},
  "geometry": {"coordinates":[-73.45313299999999,45.603718],"type":"Point"}
}