{
  "type": "Feature",
  "properties": {
    "iso:country":"CA",
    "sg:address":"2725 Rue Jules-Vachon",
    "sg:city":"Trois-Rivieres",
    "sg:classifiers":[
        {
            "category":"Building & Trades",
            "subcategory":"Construction",
            "type":"Services"
        }
    ],
    "sg:phone":"+1 819 371 3421",
    "sg:postcode":"G9A 5E1",
    "sg:province":"QC",
    "sg:tags":[
        "painter"
    ],
    "wof:name":"Sablex Inc",
    "wof:placetype":"venue"
},
  "geometry": {"coordinates":[-72.65643300000001,46.378613],"type":"Point"}
}