{
  "type": "Feature",
  "properties": {
    "addr:full":"1239 Lakeshore Rd Niagara on the Lake ON L0S 1J0",
    "addr:housenumber":"1239",
    "addr:postcode":"l0s 1j0",
    "addr:street":"Lakeshore Rd;On",
    "iso:country":"CA",
    "sg:address":"1239 Lakeshore Rd",
    "sg:city":"Niagara on the Lake",
    "sg:classifiers":[
        {
            "category":"Farming",
            "subcategory":"Farm",
            "type":"Manufacturing & Wholesale Goods"
        }
    ],
    "sg:phone":"+1 905 934 1319",
    "sg:postcode":"L0S 1J0",
    "sg:province":"ON",
    "wof:name":"Falk Family Farms Inc",
    "wof:placetype":"venue"
},
  "geometry": {"coordinates":[-79.13155399999999,43.252579],"type":"Point"}
}