{
  "type": "Feature",
  "properties": {
    "addr:full":"Gaspe QC G4X 1T5",
    "addr:postcode":"g4x 1t5",
    "iso:country":"CA",
    "sg:city":"Gaspe",
    "sg:classifiers":[
        {
            "category":"Professional",
            "subcategory":"Lawyer & Legal Services",
            "type":"Services"
        }
    ],
    "sg:phone":"+1 418 368 2633",
    "sg:postcode":"G4X 1T5",
    "sg:province":"QC",
    "sg:tags":[
        "attorney"
    ],
    "wof:name":"Cyr & Minville",
    "wof:placetype":"venue"
},
  "geometry": {"coordinates":[-64.483284,48.829861],"type":"Point"}
}