{
  "type": "Feature",
  "properties": {
    "addr:full":"Moose Jaw SK S6H 1X4",
    "addr:postcode":"s6h 1x4",
    "iso:country":"CA",
    "sg:city":"Moose Jaw",
    "sg:classifiers":[
        {
            "category":"Building & Trades",
            "subcategory":"Construction",
            "type":"Services"
        }
    ],
    "sg:phone":"+1 306 694 5224",
    "sg:postcode":"S6H 1X4",
    "sg:province":"SK",
    "sg:tags":[
        "general",
        "door",
        "contractor"
    ],
    "wof:name":"Moose Jaw Overhead Door CO",
    "wof:placetype":"venue"
},
  "geometry": {"coordinates":[-105.541275,50.393616],"type":"Point"}
}