{
  "type": "Feature",
  "properties": {
    "addr:full":"2 Davis Downs Pl Scarborough ON M1E 3L4",
    "addr:housenumber":"2",
    "addr:postcode":"m1e 3l4",
    "addr:street":"Davis Downs Pl",
    "iso:country":"CA",
    "sg:address":"2 Davis Downs Pl",
    "sg:city":"Scarborough",
    "sg:classifiers":[
        {
            "category":"Insurance",
            "subcategory":"Insurance Agent",
            "type":"Services"
        }
    ],
    "sg:phone":"+1 416 284 5226",
    "sg:postcode":"M1E 3L4",
    "sg:province":"ON",
    "wof:name":"J Russell Insurance Ltd",
    "wof:placetype":"venue"
},
  "geometry": {"coordinates":[-79.16831970210001,43.771572113],"type":"Point"}
}