{
  "type": "Feature",
  "properties": {
    "addr:full":"705 Fenmar Dr North York ON M9L 1C8",
    "addr:housenumber":"705",
    "addr:postcode":"m9l 1c8",
    "addr:street":"Fenmar Dr",
    "iso:country":"CA",
    "sg:address":"705 Fenmar Dr",
    "sg:city":"North York",
    "sg:classifiers":[
        {
            "category":"Retail",
            "subcategory":"Auto Repair",
            "type":"Services"
        }
    ],
    "sg:phone":"+1 416 748 7329",
    "sg:postcode":"M9L 1C8",
    "sg:province":"ON",
    "sg:tags":[
        "repairing",
        "automobile"
    ],
    "wof:name":"Loyal Auto Repair",
    "wof:placetype":"venue"
},
  "geometry": {"coordinates":[-79.5612792969,43.7645263672],"type":"Point"}
}