{
  "type": "Feature",
  "properties": {
    "iso:country":"CA",
    "sg:address":"405 Barrie St",
    "sg:city":"Kingston",
    "sg:classifiers":[
        {
            "category":"Restaurant",
            "type":"Food & Drink"
        }
    ],
    "sg:phone":"+1 613 546 1914",
    "sg:postcode":"K7K 3T8",
    "sg:province":"ON",
    "wof:name":"Frank's Fish & Chips",
    "wof:placetype":"venue"
},
  "geometry": {"coordinates":[-76.4898300171,44.2358665466],"type":"Point"}
}