{
  "type": "Feature",
  "properties": {
    "iso:country":"CA",
    "sg:address":"10220 Boul Saint-Laurent",
    "sg:city":"Montreal",
    "sg:classifiers":[
        {
            "category":"Autos & Motor Vehicles",
            "subcategory":"Auto Supplies",
            "type":"Retail Goods"
        }
    ],
    "sg:phone":"+1 514 858 7638",
    "sg:postcode":"H3L 2N8",
    "sg:province":"QC",
    "sg:tags":[
        "repairing",
        "automobile"
    ],
    "wof:name":"Centre Du Pneu Gounod",
    "wof:placetype":"venue"
},
  "geometry": {"coordinates":[-73.663574,45.547958],"type":"Point"}
}