{
  "type": "Feature",
  "properties": {
    "addr:full":"8535 Coronet Rd NW Edmonton AB T6E 4N7",
    "addr:housenumber":"8535",
    "addr:postcode":"t6e 4n7",
    "addr:street":"Coronet Rd Nw",
    "iso:country":"CA",
    "sg:address":"8535 Coronet Rd NW",
    "sg:city":"Edmonton",
    "sg:classifiers":[
        {
            "category":"Building & Trades",
            "subcategory":"Construction",
            "type":"Services"
        }
    ],
    "sg:phone":"+1 780 466 4849",
    "sg:postcode":"T6E 4N7",
    "sg:province":"AB",
    "sg:tags":[
        "concrete",
        "restoration",
        "repair",
        "cleaning",
        "consultant"
    ],
    "wof:name":"Interstress Structural Ltd",
    "wof:placetype":"venue"
},
  "geometry": {"coordinates":[-113.45578,53.500359],"type":"Point"}
}