{
  "type": "Feature",
  "properties": {
    "addr:full":"1651 Ch DE Chertsey Chertsey QC J0K 3K0",
    "addr:housenumber":"1651",
    "addr:postcode":"j0k 3k0",
    "addr:street":"Ch De Chertsey",
    "iso:country":"CA",
    "sg:address":"1651 Ch DE Chertsey",
    "sg:city":"Chertsey",
    "sg:classifiers":[
        {
            "category":"Travel",
            "subcategory":"Campground",
            "type":"Entertainment"
        }
    ],
    "sg:phone":"+1 450 882 4719",
    "sg:postcode":"J0K 3K0",
    "sg:province":"QC",
    "sg:tags":[
        "camp"
    ],
    "wof:name":"Camp Familial St-Urbain",
    "wof:placetype":"venue"
},
  "geometry": {"coordinates":[-73.959442,46.084858],"type":"Point"}
}