{
  "type": "Feature",
  "properties": {
    "addr:full":"240 Waltham Rd Brockville ON K6V 7K3",
    "addr:housenumber":"240",
    "addr:postcode":"k6v 7k3",
    "addr:street":"Waltham Rd",
    "iso:country":"CA",
    "sg:address":"240 Waltham Rd",
    "sg:city":"Brockville",
    "sg:classifiers":[
        {
            "category":"Food & Beverages",
            "subcategory":"Specialty",
            "type":"Retail Goods"
        }
    ],
    "sg:phone":"+1 613 498 2830",
    "sg:postcode":"K6V 7K3",
    "sg:province":"ON",
    "sg:tags":[
        "water",
        "bulk",
        "company"
    ],
    "wof:name":"Culligan",
    "wof:placetype":"venue"
},
  "geometry": {"coordinates":[-75.68699599999999,44.615929],"type":"Point"}
}