{
  "type": "Feature",
  "properties": {
    "addr:full":"Quebec QC G1P 4M2",
    "addr:postcode":"g1p 4m2",
    "iso:country":"CA",
    "sg:city":"Quebec",
    "sg:classifiers":[
        {
            "category":"Wholesale",
            "subcategory":"Durable Goods & Equipment",
            "type":"Manufacturing & Wholesale Goods"
        }
    ],
    "sg:phone":"+1 418 872 7152",
    "sg:postcode":"G1P 4M2",
    "sg:province":"QC",
    "sg:tags":[
        "engineering",
        "supply",
        "contractor"
    ],
    "wof:name":"Ernest Joubert Inc",
    "wof:placetype":"venue"
},
  "geometry": {"coordinates":[-71.3031997681,46.803943634],"type":"Point"}
}