{
  "type": "Feature",
  "properties": {
    "addr:full":"81 Rue Du Rosaire Lac-Au-Saumon QC G0J 1M0",
    "addr:housenumber":"81",
    "addr:postcode":"g0j 1m0",
    "addr:street":"Rue Du Rosaire",
    "iso:country":"CA",
    "sg:address":"81 Rue Du Rosaire",
    "sg:city":"Lac-Au-Saumon",
    "sg:classifiers":[
        {
            "category":"Education",
            "subcategory":"School",
            "type":"Public Place"
        }
    ],
    "sg:phone":"+1 418 778 3363",
    "sg:postcode":"G0J 1M0",
    "sg:province":"QC",
    "wof:name":"Ecole Lac-Au-Saumon",
    "wof:placetype":"venue"
},
  "geometry": {"coordinates":[-67.346992,48.422043],"type":"Point"}
}