{
  "type": "Feature",
  "properties": {
    "addr:full":"821 Rue Principale Saint-Come QC J0K 2B0",
    "addr:housenumber":"821",
    "addr:postcode":"j0k 2b0",
    "addr:street":"Rue Principale",
    "iso:country":"CA",
    "sg:address":"821 Rue Principale",
    "sg:city":"Saint-Come",
    "sg:classifiers":[
        {
            "category":"Manufacturing",
            "subcategory":"Motor Vehicles & Parts",
            "type":"Manufacturing & Wholesale Goods"
        }
    ],
    "sg:phone":"+1 450 883 3340",
    "sg:postcode":"J0K 2B0",
    "sg:province":"QC",
    "sg:tags":[
        "equipment",
        "truck",
        "automobile",
        "supply"
    ],
    "wof:name":"Distribution Dm Ltee",
    "wof:placetype":"venue"
},
  "geometry": {"coordinates":[-73.752075,46.282055],"type":"Point"}
}