{
  "type": "Feature",
  "properties": {
    "iso:country":"CA",
    "sg:address":"300 Main St",
    "sg:city":"Moncton",
    "sg:classifiers":[
        {
            "category":"Insurance",
            "subcategory":"Insurance Agent",
            "type":"Services"
        }
    ],
    "sg:phone":"+1 506 857 3246",
    "sg:postcode":"E1C 1B9",
    "sg:province":"NB",
    "wof:name":"Combined Insurance CO-America",
    "wof:placetype":"venue"
},
  "geometry": {"coordinates":[-64.767715,46.09169],"type":"Point"}
}