{
  "type": "Feature",
  "properties": {
    "iso:country":"CA",
    "sg:address":"4th & Pine St",
    "sg:city":"Blue River",
    "sg:classifiers":[
        {
            "category":"Organizations",
            "subcategory":"Religious Organization",
            "type":"Services"
        }
    ],
    "sg:phone":"+1 604 673 2381",
    "sg:postcode":"V0E 1J0",
    "sg:province":"BC",
    "sg:tags":[
        "church"
    ],
    "wof:name":"Blue River Ev Free Church",
    "wof:placetype":"venue"
},
  "geometry": {"coordinates":[-119.301147461,52.1067504883],"type":"Point"}
}