{
  "type": "Feature",
  "properties": {
    "addr:full":"30 Pearl St Mississauga ON L5M 1X2",
    "addr:housenumber":"30",
    "addr:postcode":"l5m 1x2",
    "addr:street":"Pearl St",
    "iso:country":"CA",
    "sg:address":"30 Pearl St",
    "sg:city":"Mississauga",
    "sg:classifiers":[
        {
            "category":"Personal",
            "subcategory":"Beauty Salon",
            "type":"Services"
        }
    ],
    "sg:phone":"+1 905 821 2421",
    "sg:postcode":"L5M 1X2",
    "sg:province":"ON",
    "wof:name":"Tracey's Esthetic & Elctrlys",
    "wof:placetype":"venue"
},
  "geometry": {"coordinates":[-79.7135772705,43.5808258057],"type":"Point"}
}