{
  "type": "Feature",
  "properties": {
    "addr:full":"Barrie ON L4M 6L2",
    "addr:postcode":"l4m 6l2",
    "iso:country":"CA",
    "sg:city":"Barrie",
    "sg:classifiers":[
        {
            "category":"Health Services",
            "subcategory":"Doctor",
            "type":"Services"
        }
    ],
    "sg:phone":"+1 705 727 4050",
    "sg:postcode":"L4M 6L2",
    "sg:province":"ON",
    "sg:tags":[
        "physician",
        "surgeon"
    ],
    "wof:name":"Ikejiani, Charles MD",
    "wof:placetype":"venue"
},
  "geometry": {"coordinates":[-79.67688,44.410202],"type":"Point"}
}