{
  "type": "Feature",
  "properties": {
    "addr:full":"4200 Sheppard Ave E Scarborough ON M1S 1T3",
    "addr:housenumber":"4200",
    "addr:postcode":"m1s 1t3",
    "addr:street":"Sheppard Ave E",
    "iso:country":"CA",
    "sg:address":"4200 Sheppard Ave E",
    "sg:city":"Scarborough",
    "sg:classifiers":[
        {
            "category":"Restaurant",
            "type":"Food & Drink"
        }
    ],
    "sg:phone":"+1 416 293 4954",
    "sg:postcode":"M1S 1T3",
    "sg:province":"ON",
    "wof:name":"Kfc",
    "wof:placetype":"venue"
},
  "geometry": {"coordinates":[-79.2794494629,43.7852897644],"type":"Point"}
}