{
  "type": "Feature",
  "properties": {
    "addr:full":"3 Little Brehat Rd St Anthony NL A0K 4S0",
    "addr:housenumber":"3",
    "addr:postcode":"a0k 4s0",
    "addr:street":"Little Brehat Rd",
    "iso:country":"CA",
    "sg:address":"3 Little Brehat Rd",
    "sg:city":"St Anthony",
    "sg:classifiers":[
        {
            "category":"Personal",
            "subcategory":"Beauty Salon",
            "type":"Services"
        }
    ],
    "sg:phone":"+1 709 454 3039",
    "sg:postcode":"A0K 4S0",
    "sg:province":"NL",
    "wof:name":"One Stop Beauty Shop",
    "wof:placetype":"venue"
},
  "geometry": {"coordinates":[-55.613354,51.366562],"type":"Point"}
}