{
  "type": "Feature",
  "properties": {
    "iso:country":"CA",
    "sg:city":"Cold Lake",
    "sg:classifiers":[
        {
            "category":"Freight",
            "type":"Transportation"
        }
    ],
    "sg:phone":"+1 780 639 3119",
    "sg:postcode":"T9M 1N1",
    "sg:province":"AB",
    "sg:tags":[
        "commercial",
        "storage"
    ],
    "wof:name":"Mini-Storage",
    "wof:placetype":"venue"
},
  "geometry": {"coordinates":[-110.173789978,54.4650268555],"type":"Point"}
}