{
  "type": "Feature",
  "properties": {
    "addr:full":"2800 Rue Dessaulles Saint-Hyacinthe QC J2S 2V7",
    "addr:housenumber":"2800",
    "addr:postcode":"j2s 2v7",
    "addr:street":"Rue Dessaulles",
    "iso:country":"CA",
    "sg:address":"2800 Rue Dessaulles",
    "sg:city":"Saint-Hyacinthe",
    "sg:classifiers":[
        {
            "category":"Retail",
            "subcategory":"Auto Repair",
            "type":"Services"
        }
    ],
    "sg:phone":"+1 450 771 1132",
    "sg:postcode":"J2S 2V7",
    "sg:province":"QC",
    "sg:tags":[
        "repairing",
        "automobile",
        "painting"
    ],
    "wof:name":"Garage Claude Leclerc",
    "wof:placetype":"venue"
},
  "geometry": {"coordinates":[-72.958794,45.620605],"type":"Point"}
}