{
  "type": "Feature",
  "properties": {
    "addr:full":"182 Rue Des Metiers Amos QC J9T 4M6",
    "addr:housenumber":"182",
    "addr:postcode":"j9t 4m6",
    "addr:street":"Rue Des Metiers",
    "iso:country":"CA",
    "sg:address":"182 Rue Des Metiers",
    "sg:city":"Amos",
    "sg:classifiers":[
        {
            "category":"Manufacturing",
            "subcategory":"Tools & Machinery",
            "type":"Manufacturing & Wholesale Goods"
        }
    ],
    "sg:phone":"+1 819 732 9884",
    "sg:postcode":"J9T 4M6",
    "sg:province":"QC",
    "sg:tags":[
        "aluminum",
        "trencher"
    ],
    "wof:name":"Alumi-Nord Rmg Inc",
    "wof:placetype":"venue"
},
  "geometry": {"coordinates":[-78.12291,48.562294],"type":"Point"}
}