{
  "type": "Feature",
  "properties": {
    "addr:full":"North York ON M3C 3A1",
    "addr:postcode":"m3c 3a1",
    "iso:country":"CA",
    "sg:city":"North York",
    "sg:classifiers":[
        {
            "category":"Shopping",
            "subcategory":"Pharmacy",
            "type":"Retail Goods"
        }
    ],
    "sg:phone":"+1 416 424 3131",
    "sg:postcode":"M3C 3A1",
    "sg:province":"ON",
    "wof:name":"Overlea Pharmacy",
    "wof:placetype":"venue"
},
  "geometry": {"coordinates":[-79.33322099999999,43.710175],"type":"Point"}
}