{
  "type": "Feature",
  "properties": {
    "addr:full":"80 Rue Lafontaine # A Riviere-Du-Loup QC G5R 2Z7",
    "addr:housenumber":"80",
    "addr:postcode":"g5r 2z7",
    "addr:street":"Rue Lafontaine # A Riviere-Du-Loup",
    "iso:country":"CA",
    "sg:address":"80 Rue Lafontaine # A",
    "sg:city":"Riviere-Du-Loup",
    "sg:classifiers":[
        {
            "category":"Personal",
            "subcategory":"Beauty Salon",
            "type":"Services"
        }
    ],
    "sg:phone":"+1 418 868 0895",
    "sg:postcode":"G5R 2Z7",
    "sg:province":"QC",
    "wof:name":"Centre DE Beaute Mirage",
    "wof:placetype":"venue"
},
  "geometry": {"coordinates":[-69.538651,47.837082],"type":"Point"}
}