{
  "type": "Feature",
  "properties": {
    "addr:full":"Techumseh Rd Wallaceburg ON N8A 4K9",
    "addr:postcode":"n8a 4k9",
    "addr:street":"Techumseh Rd",
    "iso:country":"CA",
    "sg:address":"Techumseh Rd",
    "sg:city":"Wallaceburg",
    "sg:classifiers":[
        {
            "category":"Education",
            "subcategory":"Library",
            "type":"Public Place"
        }
    ],
    "sg:phone":"+1 519 627 7034",
    "sg:postcode":"N8A 4K9",
    "sg:province":"ON",
    "sg:tags":[
        "government"
    ],
    "wof:name":"Walpole Island Library",
    "wof:placetype":"venue"
},
  "geometry": {"coordinates":[-82.39503499999999,42.592976],"type":"Point"}
}