{
  "type": "Feature",
  "properties": {
    "addr:full":"1649 Chappus St Windsor ON N9C 3T1",
    "addr:housenumber":"1649",
    "addr:postcode":"n9c 3t1",
    "addr:street":"Chappus St",
    "iso:country":"CA",
    "sg:address":"1649 Chappus St",
    "sg:city":"Windsor",
    "sg:classifiers":[
        {
            "category":"Travel",
            "subcategory":"Hotels & Motels",
            "type":"Entertainment"
        }
    ],
    "sg:phone":"+1 519 966 2334",
    "sg:postcode":"N9C 3T1",
    "sg:province":"ON",
    "sg:tags":[
        "breakfast",
        "accommodation",
        "bed"
    ],
    "wof:name":"Branteaney's Bed & Breakfast",
    "wof:placetype":"venue"
},
  "geometry": {"coordinates":[-83.0618438721,42.2691497803],"type":"Point"}
}