{
  "type": "Feature",
  "properties": {
    "addr:full":"1801 Dundas St E Whitby ON L1N 7C5",
    "addr:housenumber":"1801",
    "addr:postcode":"l1n 7c5",
    "addr:street":"Dundas St E",
    "iso:country":"CA",
    "sg:address":"1801 Dundas St E",
    "sg:city":"Whitby",
    "sg:classifiers":[
        {
            "category":"Food & Beverages",
            "subcategory":"Groceries & Convenience Stores",
            "type":"Retail Goods"
        }
    ],
    "sg:phone":"+1 905 436 3066",
    "sg:postcode":"L1N 7C5",
    "sg:province":"ON",
    "sg:tags":[
        "frozen"
    ],
    "wof:name":"M & M Meat Shop",
    "wof:placetype":"venue"
},
  "geometry": {"coordinates":[-78.9042510986,43.8882904053],"type":"Point"}
}