{
  "type": "Feature",
  "properties": {
    "addr:full":"5 Bradford St Barrie ON L4N 3A6",
    "addr:housenumber":"5",
    "addr:postcode":"l4n 3a6",
    "addr:street":"Bradford St",
    "iso:country":"CA",
    "sg:address":"5 Bradford St",
    "sg:city":"Barrie",
    "sg:classifiers":[
        {
            "category":"Health Services",
            "subcategory":"Medical Lab",
            "type":"Services"
        }
    ],
    "sg:phone":"+1 705 728 9898",
    "sg:postcode":"L4N 3A6",
    "sg:province":"ON",
    "wof:name":"Barrie Denture Clinic",
    "wof:placetype":"venue"
},
  "geometry": {"coordinates":[-79.69385528559999,44.387260437],"type":"Point"}
}