{
  "type": "Feature",
  "properties": {
    "addr:full":"Winnipeg MB R3C 4H4",
    "addr:postcode":"r3c 4h4",
    "iso:country":"CA",
    "sg:city":"Winnipeg",
    "sg:classifiers":[
        {
            "category":"Health Services",
            "subcategory":"Doctor",
            "type":"Services"
        }
    ],
    "sg:phone":"+1 204 942 5064",
    "sg:postcode":"R3C 4H4",
    "sg:province":"MB",
    "sg:tags":[
        "physician",
        "surgeon"
    ],
    "wof:name":"Bolton, David MD",
    "wof:placetype":"venue"
},
  "geometry": {"coordinates":[-97.1368179321,49.8872337341],"type":"Point"}
}