{
  "type": "Feature",
  "properties": {
    "addr:full":"944 Garner Rd E Ancaster ON L9G 3K9",
    "addr:housenumber":"944",
    "addr:postcode":"l9g 3k9",
    "addr:street":"Garner Rd E",
    "iso:country":"CA",
    "sg:address":"944 Garner Rd E",
    "sg:city":"Ancaster",
    "sg:classifiers":[
        {
            "category":"Farming",
            "subcategory":"Orchard",
            "type":"Manufacturing & Wholesale Goods"
        }
    ],
    "sg:phone":"+1 905 648 6878",
    "sg:postcode":"L9G 3K9",
    "sg:province":"ON",
    "sg:tags":[
        "vegetable",
        "cider",
        "fruit",
        "mills",
        "produce"
    ],
    "wof:name":"Bennett's Apples & Cider Ltd",
    "wof:placetype":"venue"
},
  "geometry": {"coordinates":[-79.939003,43.208641],"type":"Point"}
}