{
  "type": "Feature",
  "properties": {
    "addr:full":"2553 Warden Ave Scarborough ON M1W 2H5",
    "addr:housenumber":"2553",
    "addr:postcode":"m1w 2h5",
    "addr:street":"Warden Ave",
    "iso:country":"CA",
    "sg:address":"2553 Warden Ave",
    "sg:city":"Scarborough",
    "sg:classifiers":[
        {
            "category":"Retail",
            "subcategory":"Laundry & Dry Cleaning",
            "type":"Services"
        }
    ],
    "sg:phone":"+1 416 499 2467",
    "sg:postcode":"M1W 2H5",
    "sg:province":"ON",
    "sg:tags":[
        "cleaners"
    ],
    "wof:name":"Cadet Cleaners",
    "wof:placetype":"venue"
},
  "geometry": {"coordinates":[-79.312744,43.790051],"type":"Point"}
}