{
  "type": "Feature",
  "properties": {
    "addr:full":"36 Dickson St Cambridge ON N1R 1T4",
    "addr:housenumber":"36",
    "addr:postcode":"n1r 1t4",
    "addr:street":"Dickson St",
    "iso:country":"CA",
    "sg:address":"36 Dickson St",
    "sg:city":"Cambridge",
    "sg:classifiers":[
        {
            "category":"Shopping",
            "subcategory":"Used Merchandise",
            "type":"Retail Goods"
        }
    ],
    "sg:phone":"+1 519 740 7880",
    "sg:postcode":"N1R 1T4",
    "sg:province":"ON",
    "sg:tags":[
        "book",
        "rare",
        "dealer"
    ],
    "wof:name":"Paperbacks Unlimited",
    "wof:placetype":"venue"
},
  "geometry": {"coordinates":[-80.313225,43.360001],"type":"Point"}
}