{
  "type": "Feature",
  "properties": {
    "addr:full":"Calgary AB T2C 2J9",
    "addr:postcode":"t2c 2j9",
    "iso:country":"CA",
    "sg:city":"Calgary",
    "sg:classifiers":[
        {
            "category":"Wholesale",
            "subcategory":"Machinery & Supplies",
            "type":"Manufacturing & Wholesale Goods"
        }
    ],
    "sg:phone":"+1 403 279 6644",
    "sg:postcode":"T2C 2J9",
    "sg:province":"AB",
    "sg:tags":[
        "equipment",
        "pneumatic",
        "component",
        "valve"
    ],
    "wof:name":"Skeans Engineering Alberta Ltd",
    "wof:placetype":"venue"
},
  "geometry": {"coordinates":[-113.976745605,50.9958190918],"type":"Point"}
}