{
  "type": "Feature",
  "properties": {
    "addr:full":"11205 156 St NW Edmonton AB T5M 1Y2",
    "addr:housenumber":"11205",
    "addr:postcode":"t5m 1y2",
    "addr:street":"156 St Nw",
    "iso:country":"CA",
    "sg:address":"11205 156 St NW",
    "sg:city":"Edmonton",
    "sg:classifiers":[
        {
            "category":"Home & Garden",
            "subcategory":"Household Appliances",
            "type":"Retail Goods"
        }
    ],
    "sg:phone":"+1 780 454 7688",
    "sg:postcode":"T5M 1Y2",
    "sg:province":"AB",
    "wof:name":"Best Appliances Ctr",
    "wof:placetype":"venue"
},
  "geometry": {"coordinates":[-113.59016418500001,53.5610618591],"type":"Point"}
}