{
  "type": "Feature",
  "properties": {
    "addr:full":"15621 112 Ave NW Edmonton AB T5M 2V8",
    "addr:housenumber":"15621",
    "addr:postcode":"t5m 2v8",
    "addr:street":"112 Ave Nw",
    "iso:country":"CA",
    "sg:address":"15621 112 Ave NW",
    "sg:city":"Edmonton",
    "sg:classifiers":[
        {
            "category":"Professional",
            "subcategory":"Art Services",
            "type":"Services"
        }
    ],
    "sg:phone":"+1 780 496 7791",
    "sg:postcode":"T5M 2V8",
    "sg:province":"AB",
    "sg:tags":[
        "graphic",
        "designer"
    ],
    "wof:name":"Aartvark Communications",
    "wof:placetype":"venue"
},
  "geometry": {"coordinates":[-113.591095,53.560646],"type":"Point"}
}