{
  "type": "Feature",
  "properties": {
    "addr:full":"Montreal QC H3W 2P9",
    "addr:postcode":"h3w 2p9",
    "iso:country":"CA",
    "sg:city":"Montreal",
    "sg:classifiers":[
        {
            "category":"Shopping",
            "subcategory":"Florist",
            "type":"Retail Goods"
        }
    ],
    "sg:phone":"+1 514 343 9565",
    "sg:postcode":"H3W 2P9",
    "sg:province":"QC",
    "wof:name":"Fleurtiste Lotus Blanc",
    "wof:placetype":"venue"
},
  "geometry": {"coordinates":[-73.63121032710001,45.4916992188],"type":"Point"}
}