{
  "type": "Feature",
  "properties": {
    "addr:full":"Lanoraie QC J0K 1E0",
    "addr:postcode":"j0k 1e0",
    "iso:country":"CA",
    "sg:city":"Lanoraie",
    "sg:classifiers":[
        {
            "category":"Building & Trades",
            "subcategory":"Construction",
            "type":"Services"
        }
    ],
    "sg:phone":"+1 450 586 3114",
    "sg:postcode":"J0K 1E0",
    "sg:province":"QC",
    "sg:tags":[
        "repairing",
        "remodeling",
        "contractor"
    ],
    "wof:name":"Construction J & R Deschenes",
    "wof:placetype":"venue"
},
  "geometry": {"coordinates":[-73.257515,45.906193],"type":"Point"}
}