{
  "type": "Feature",
  "properties": {
    "addr:full":"11 Hardy Ave Grand Falls-Windsor NL A2A 2P8",
    "addr:housenumber":"11",
    "addr:postcode":"a2a 2p8",
    "addr:street":"Hardy Ave",
    "iso:country":"CA",
    "sg:address":"11 Hardy Ave",
    "sg:city":"Grand Falls-Windsor",
    "sg:classifiers":[
        {
            "category":"Manufacturing",
            "subcategory":"Signs",
            "type":"Manufacturing & Wholesale Goods"
        }
    ],
    "sg:phone":"+1 709 489 3060",
    "sg:postcode":"A2A 2P8",
    "sg:province":"NL",
    "wof:name":"Stagg Signs & Graphics",
    "wof:placetype":"venue"
},
  "geometry": {"coordinates":[-55.6432914734,48.9521789551],"type":"Point"}
}