{
  "type": "Feature",
  "properties": {
    "addr:full":"85 Victoria St W Alliston ON L9R 1T2",
    "addr:housenumber":"85",
    "addr:postcode":"l9r 1t2",
    "addr:street":"Victoria St W Alliston",
    "iso:country":"CA",
    "sg:address":"85 Victoria St W",
    "sg:city":"Alliston",
    "sg:classifiers":[
        {
            "category":"Shopping",
            "subcategory":"Clothing, Apparel, & Fashions",
            "type":"Retail Goods"
        }
    ],
    "sg:phone":"+1 705 435 6481",
    "sg:postcode":"L9R 1T2",
    "sg:province":"ON",
    "sg:tags":[
        "western"
    ],
    "wof:name":"Herbert's Western Boots & Wear",
    "wof:placetype":"venue"
},
  "geometry": {"coordinates":[-79.8716506958,44.1533279419],"type":"Point"}
}