{
  "type": "Feature",
  "properties": {
    "addr:full":"Enderby BC V0E 1V5",
    "addr:postcode":"v0e 1v5",
    "iso:country":"CA",
    "sg:city":"Enderby",
    "sg:classifiers":[
        {
            "category":"Freight",
            "type":"Transportation"
        }
    ],
    "sg:phone":"+1 250 838 7709",
    "sg:postcode":"V0E 1V5",
    "sg:province":"BC",
    "sg:tags":[
        "trucking"
    ],
    "wof:name":"V L Brandt Trucking",
    "wof:placetype":"venue"
},
  "geometry": {"coordinates":[-119.14015999999999,50.550701],"type":"Point"}
}