{
  "type": "Feature",
  "properties": {
    "addr:full":"100 Salome Dr Scarborough ON M1S 2A8",
    "addr:housenumber":"100",
    "addr:postcode":"m1s 2a8",
    "addr:street":"Salome Dr",
    "iso:country":"CA",
    "sg:address":"100 Salome Dr",
    "sg:city":"Scarborough",
    "sg:classifiers":[
        {
            "category":"Organizations",
            "subcategory":"Professional Association",
            "type":"Services"
        }
    ],
    "sg:phone":"+1 416 292 6125",
    "sg:postcode":"M1S 2A8",
    "sg:province":"ON",
    "wof:name":"Royal Canadian Legion",
    "wof:placetype":"venue"
},
  "geometry": {"coordinates":[-79.274506,43.78495],"type":"Point"}
}