{
  "type": "Feature",
  "properties": {
    "addr:full":"1426 Garibaldi Pl Coquitlam BC V3E 2S6",
    "addr:housenumber":"1426",
    "addr:postcode":"v3e 2s6",
    "addr:street":"Garibaldi Pl",
    "iso:country":"CA",
    "sg:address":"1426 Garibaldi Pl",
    "sg:city":"Coquitlam",
    "sg:classifiers":[
        {
            "category":"Professional",
            "subcategory":"Management & Consulting",
            "type":"Services"
        }
    ],
    "sg:phone":"+1 604 464 5185",
    "sg:postcode":"V3E 2S6",
    "sg:province":"BC",
    "sg:tags":[
        "consultant",
        "business"
    ],
    "wof:name":"Mdr Management",
    "wof:placetype":"venue"
},
  "geometry": {"coordinates":[-122.785416,49.298759],"type":"Point"}
}