{
  "type": "Feature",
  "properties": {
    "addr:full":"112 West Ave S Hamilton ON L8N 2S4",
    "addr:housenumber":"112",
    "addr:postcode":"l8n 2s4",
    "addr:street":"West Ave S",
    "iso:country":"CA",
    "sg:address":"112 West Ave S",
    "sg:city":"Hamilton",
    "sg:classifiers":[
        {
            "category":"Home & Garden",
            "subcategory":"Building Materials",
            "type":"Retail Goods"
        }
    ],
    "sg:phone":"+1 905 529 3614",
    "sg:postcode":"L8N 2S4",
    "sg:province":"ON",
    "sg:tags":[
        "windows"
    ],
    "wof:name":"Sentry Aluminum Products",
    "wof:placetype":"venue"
},
  "geometry": {"coordinates":[-79.860336,43.249271],"type":"Point"}
}