{
  "type": "Feature",
  "properties": {
    "addr:full":"273 Rd Charlie Lake BC V0C 1H0",
    "addr:housenumber":"273",
    "addr:postcode":"bc v0c 1h0",
    "addr:street":"Rd",
    "iso:country":"CA",
    "sg:address":"273 Rd",
    "sg:city":"Charlie Lake",
    "sg:classifiers":[
        {
            "category":"Government",
            "subcategory":"Office",
            "type":"Public Place"
        }
    ],
    "sg:phone":"+1 250 785 0414",
    "sg:postcode":"V0C 1H0",
    "sg:province":"BC",
    "sg:tags":[
        "village"
    ],
    "wof:name":"Peace River Charlie Lake",
    "wof:placetype":"venue"
},
  "geometry": {"coordinates":[-120.964912415,56.2806358337],"type":"Point"}
}