{
  "type": "Feature",
  "properties": {
    "addr:full":"368 Queen St W Cambridge ON N3C 1G8",
    "addr:housenumber":"368",
    "addr:postcode":"n3c 1g8",
    "addr:street":"Queen St W",
    "iso:country":"CA",
    "sg:address":"368 Queen St W",
    "sg:city":"Cambridge",
    "sg:classifiers":[
        {
            "category":"Food & Beverages",
            "subcategory":"Groceries & Convenience Stores",
            "type":"Retail Goods"
        }
    ],
    "sg:phone":"+1 519 651 3383",
    "sg:postcode":"N3C 1G8",
    "sg:province":"ON",
    "wof:name":"Hespeler Gas Bar & Convenience",
    "wof:placetype":"venue"
},
  "geometry": {"coordinates":[-80.32402,43.423332],"type":"Point"}
}