{
  "type": "Feature",
  "properties": {
    "addr:full":"4107 Quarry Rd Beamsville ON L0R 1B2",
    "addr:housenumber":"4107",
    "addr:postcode":"l0r 1b2",
    "addr:street":"Quarry Rd",
    "iso:country":"CA",
    "sg:address":"4107 Quarry Rd",
    "sg:city":"Beamsville",
    "sg:classifiers":[
        {
            "category":"Shopping",
            "subcategory":"Clothing, Apparel, & Fashions",
            "type":"Retail Goods"
        }
    ],
    "sg:phone":"+1 905 563 1174",
    "sg:postcode":"L0R 1B2",
    "sg:province":"ON",
    "sg:tags":[
        "riding",
        "equipment"
    ],
    "wof:name":"Tack Connection",
    "wof:placetype":"venue"
},
  "geometry": {"coordinates":[-79.4563827515,43.159538269],"type":"Point"}
}