{
  "type": "Feature",
  "properties": {
    "addr:full":"1429 George St Sydney NS B1P 1P2",
    "addr:housenumber":"1429",
    "addr:postcode":"b1p 1p2",
    "addr:street":"George St",
    "iso:country":"CA",
    "sg:address":"1429 George St",
    "sg:city":"Sydney",
    "sg:classifiers":[
        {
            "category":"Food & Beverages",
            "subcategory":"Bakery",
            "type":"Retail Goods"
        }
    ],
    "sg:phone":"+1 902 539 2951",
    "sg:postcode":"B1P 1P2",
    "sg:province":"NS",
    "sg:tags":[
        "baker"
    ],
    "wof:name":"Tony's Bakery",
    "wof:placetype":"venue"
},
  "geometry": {"coordinates":[-60.1713638306,46.1180458069],"type":"Point"}
}