{
  "type": "Feature",
  "properties": {
    "iso:country":"CA",
    "sg:city":"Hamilton",
    "sg:classifiers":[
        {
            "category":"Shopping",
            "subcategory":"Department Store",
            "type":"Retail Goods"
        }
    ],
    "sg:phone":"+1 905 560 2592",
    "sg:postcode":"L8E 4A1",
    "sg:province":"ON",
    "sg:tags":[
        "shop"
    ],
    "wof:name":"Dollar Blitz",
    "wof:placetype":"venue"
},
  "geometry": {"coordinates":[-79.7611618042,43.2348365784],"type":"Point"}
}