{
  "type": "Feature",
  "properties": {
    "addr:full":"1712 13 Ave SW Calgary AB T3C 0T9",
    "addr:housenumber":"1712",
    "addr:postcode":"t3c 0t9",
    "addr:street":"13 Ave Sw",
    "iso:country":"CA",
    "sg:address":"1712 13 Ave SW",
    "sg:city":"Calgary",
    "sg:classifiers":[
        {
            "category":"Professional",
            "subcategory":"Research",
            "type":"Services"
        }
    ],
    "sg:phone":"+1 403 244 3556",
    "sg:postcode":"T3C 0T9",
    "sg:province":"AB",
    "sg:tags":[
        "environmental",
        "ecological"
    ],
    "wof:name":"Graecam Enterprises",
    "wof:placetype":"venue"
},
  "geometry": {"coordinates":[-114.09986114500001,51.0415992737],"type":"Point"}
}