{
  "type": "Feature",
  "properties": {
    "addr:full":"80 Saskatchewan Ave E Portage LA Prairie MB R1N 0L2",
    "addr:housenumber":"80",
    "addr:postcode":"r1n 0l2",
    "addr:street":"Saskatchewan Ave E",
    "iso:country":"CA",
    "sg:address":"80 Saskatchewan Ave E",
    "sg:city":"Portage LA Prairie",
    "sg:classifiers":[
        {
            "category":"Shopping",
            "subcategory":"Clothing, Apparel, & Fashions",
            "type":"Retail Goods"
        }
    ],
    "sg:phone":"+1 204 857 4020",
    "sg:postcode":"R1N 0L2",
    "sg:province":"MB",
    "wof:name":"Saan Stores Ltd",
    "wof:placetype":"venue"
},
  "geometry": {"coordinates":[-98.2902374268,49.9732017517],"type":"Point"}
}