{
  "type": "Feature",
  "properties": {
    "addr:full":"Orangeville ON L9W 1K2",
    "addr:postcode":"l9w 1k2",
    "iso:country":"CA",
    "sg:city":"Orangeville",
    "sg:classifiers":[
        {
            "category":"Education",
            "subcategory":"School",
            "type":"Public Place"
        }
    ],
    "sg:phone":"+1 519 942 4520",
    "sg:postcode":"L9W 1K2",
    "sg:province":"ON",
    "sg:tags":[
        "instruction",
        "driving"
    ],
    "wof:name":"Young Drivers of Canada",
    "wof:placetype":"venue"
},
  "geometry": {"coordinates":[-80.095215,43.919899],"type":"Point"}
}