{
  "type": "Feature",
  "properties": {
    "iso:country":"CA",
    "sg:address":"4930 Rue Bourg",
    "sg:city":"Saint-Laurent",
    "sg:classifiers":[
        {
            "category":"Manufacturing",
            "subcategory":"Tools & Machinery",
            "type":"Manufacturing & Wholesale Goods"
        }
    ],
    "sg:phone":"+1 514 735 4503",
    "sg:postcode":"H4T 1J2",
    "sg:province":"QC",
    "sg:tags":[
        "baling",
        "equipment"
    ],
    "wof:name":"Gerrard-Ovalstrapping",
    "wof:placetype":"venue"
},
  "geometry": {"coordinates":[-73.7011871338,45.4724731445],"type":"Point"}
}