{
  "type": "Feature",
  "properties": {
    "iso:country":"CA",
    "sg:address":"15 Martha St",
    "sg:city":"Hawkesville",
    "sg:classifiers":[
        {
            "category":"Organizations",
            "subcategory":"Religious Organization",
            "type":"Services"
        }
    ],
    "sg:phone":"+1 519 699 5522",
    "sg:postcode":"N0B 1X0",
    "sg:province":"ON",
    "sg:tags":[
        "church"
    ],
    "wof:name":"Hawkesville Mennonite Church",
    "wof:placetype":"venue"
},
  "geometry": {"coordinates":[-80.63837432859999,43.5630187988],"type":"Point"}
}