{
  "type": "Feature",
  "properties": {
    "iso:country":"CA",
    "sg:address":"739 Dufferin St",
    "sg:city":"Toronto",
    "sg:classifiers":[
        {
            "category":"Social Services",
            "type":"Services"
        }
    ],
    "sg:phone":"+1 416 533 9767",
    "sg:postcode":"M6H 3K5",
    "sg:province":"ON",
    "sg:tags":[
        "organization",
        "welfare"
    ],
    "wof:name":"My Brothers' Place",
    "wof:placetype":"venue"
},
  "geometry": {"coordinates":[-79.43254852290001,43.6529808044],"type":"Point"}
}