{
  "type": "Feature",
  "properties": {
    "addr:full":"9802 Thatcher Ave North Battleford SK S9A 3M1",
    "addr:housenumber":"9802",
    "addr:postcode":"s9a 3m1",
    "addr:street":"Thatcher Ave",
    "iso:country":"CA",
    "sg:address":"9802 Thatcher Ave",
    "sg:city":"North Battleford",
    "sg:classifiers":[
        {
            "category":"Wholesale",
            "subcategory":"Machinery & Supplies",
            "type":"Manufacturing & Wholesale Goods"
        }
    ],
    "sg:phone":"+1 306 937 7741",
    "sg:postcode":"S9A 3M1",
    "sg:province":"SK",
    "sg:tags":[
        "water",
        "pump",
        "system"
    ],
    "wof:name":"Anderson Pump House Ltd",
    "wof:placetype":"venue"
},
  "geometry": {"coordinates":[-108.26481628400001,52.7525787354],"type":"Point"}
}