{
  "type": "Feature",
  "properties": {
    "addr:full":"2021 3 Ave S Lethbridge AB T1J 0L9",
    "addr:housenumber":"2021",
    "addr:postcode":"t1j 0l9",
    "addr:street":"3 Ave S",
    "iso:country":"CA",
    "sg:address":"2021 3 Ave S",
    "sg:city":"Lethbridge",
    "sg:classifiers":[
        {
            "category":"Restaurant",
            "type":"Food & Drink"
        }
    ],
    "sg:phone":"+1 403 327 1193",
    "sg:postcode":"T1J 0L9",
    "sg:province":"AB",
    "wof:name":"Kfc",
    "wof:placetype":"venue"
},
  "geometry": {"coordinates":[-112.812644959,49.6966819763],"type":"Point"}
}