{
  "type": "Feature",
  "properties": {
    "addr:full":"700 Ferry Rd East Selkirk MB R0E 0M0",
    "addr:housenumber":"700",
    "addr:postcode":"r0e 0m0",
    "addr:street":"Ferry Rd East",
    "iso:country":"CA",
    "sg:address":"700 Ferry Rd",
    "sg:city":"East Selkirk",
    "sg:classifiers":[
        {
            "category":"Autos & Motor Vehicles",
            "subcategory":"Automobile Sales",
            "type":"Retail Goods"
        }
    ],
    "sg:phone":"+1 204 482 7966",
    "sg:postcode":"R0E 0M0",
    "sg:province":"MB",
    "sg:tags":[
        "snowmobile"
    ],
    "wof:name":"Lad Enterprises",
    "wof:placetype":"venue"
},
  "geometry": {"coordinates":[-96.87390899659999,50.1457252502],"type":"Point"}
}