{
  "type": "Feature",
  "properties": {
    "addr:full":"1485 Kingsway Vancouver BC V5N 2R6",
    "addr:housenumber":"1485",
    "addr:postcode":"v5n 2r6",
    "addr:street":"Kingsway",
    "iso:country":"CA",
    "sg:address":"1485 Kingsway",
    "sg:city":"Vancouver",
    "sg:classifiers":[
        {
            "category":"Restaurant",
            "type":"Food & Drink"
        }
    ],
    "sg:phone":"+1 604 873 6411",
    "sg:postcode":"V5N 2R6",
    "sg:province":"BC",
    "wof:name":"Little Johnny's Restaurant",
    "wof:placetype":"venue"
},
  "geometry": {"coordinates":[-123.07353999999999,49.249187],"type":"Point"}
}