{
  "type": "Feature",
  "properties": {
    "addr:full":"2043 Boul Sainte-Sophie Sainte-Sophie QC J5J 2V2",
    "addr:housenumber":"2043",
    "addr:postcode":"j5j 2v2",
    "addr:street":"Boul Sainte-Sophie",
    "iso:country":"CA",
    "sg:address":"2043 Boul Sainte-Sophie",
    "sg:city":"Sainte-Sophie",
    "sg:classifiers":[
        {
            "category":"Autos & Motor Vehicles",
            "subcategory":"Fuel & Gas Station",
            "type":"Retail Goods"
        }
    ],
    "sg:phone":"+1 450 431 6727",
    "sg:postcode":"J5J 2V2",
    "sg:province":"QC",
    "sg:tags":[
        "oil"
    ],
    "wof:name":"Super Gaz Ltee",
    "wof:placetype":"venue"
},
  "geometry": {"coordinates":[-73.89660644529999,45.8193588257],"type":"Point"}
}