{
  "type": "Feature",
  "properties": {
    "addr:full":"Parksville BC V9P 1K8",
    "addr:postcode":"v9p 1k8",
    "iso:country":"CA",
    "sg:city":"Parksville",
    "sg:classifiers":[
        {
            "category":"Shopping",
            "subcategory":"Pharmacy",
            "type":"Retail Goods"
        }
    ],
    "sg:phone":"+1 250 954 1980",
    "sg:postcode":"V9P 1K8",
    "sg:province":"BC",
    "wof:name":"Peoples Drug Mart",
    "wof:placetype":"venue"
},
  "geometry": {"coordinates":[-124.319069,49.322197],"type":"Point"}
}