{
  "type": "Feature",
  "properties": {
    "addr:full":"1255 Rue Beaubien E Montreal QC H2S 1V1",
    "addr:housenumber":"1255",
    "addr:postcode":"h2s 1v1",
    "addr:street":"Rue Beaubien E",
    "iso:country":"CA",
    "sg:address":"1255 Rue Beaubien E",
    "sg:city":"Montreal",
    "sg:classifiers":[
        {
            "category":"Health Services",
            "subcategory":"Health Practitioner",
            "type":"Services"
        }
    ],
    "sg:phone":"+1 514 276 2712",
    "sg:postcode":"H2S 1V1",
    "sg:province":"QC",
    "sg:tags":[
        "acupuncture"
    ],
    "wof:name":"Pepin, Francois",
    "wof:placetype":"venue"
},
  "geometry": {"coordinates":[-73.600189,45.539459],"type":"Point"}
}