{
  "type": "Feature",
  "properties": {
    "addr:full":"1341 Boul Wallberg Dolbeau-Mistassini QC G8L 1H3",
    "addr:housenumber":"1341",
    "addr:postcode":"g8l 1h3",
    "addr:street":"Boul Wallberg",
    "iso:country":"CA",
    "sg:address":"1341 Boul Wallberg",
    "sg:city":"Dolbeau-Mistassini",
    "sg:classifiers":[
        {
            "category":"Cinema",
            "subcategory":"Movie Theater",
            "type":"Entertainment"
        }
    ],
    "sg:phone":"+1 418 239 0707",
    "sg:postcode":"G8L 1H3",
    "sg:province":"QC",
    "wof:name":"Cinema Chaplin II",
    "wof:placetype":"venue"
},
  "geometry": {"coordinates":[-72.22840118409999,48.8779296875],"type":"Point"}
}