{
  "type": "Feature",
  "properties": {
    "addr:full":"6800 Rue DE Pertuis Quebec QC G2C 1G2",
    "addr:housenumber":"6800",
    "addr:postcode":"qc g2c 1g2",
    "addr:street":"Rue De Pertuis",
    "iso:country":"CA",
    "sg:address":"6800 Rue DE Pertuis",
    "sg:city":"Quebec",
    "sg:classifiers":[
        {
            "category":"Real Estate",
            "subcategory":"Real Estate Agent",
            "type":"Services"
        }
    ],
    "sg:phone":"+1 418 847 5671",
    "sg:postcode":"G2C 1G2",
    "sg:province":"QC",
    "sg:tags":[
        "authorities",
        "housing"
    ],
    "wof:name":"Cooperative D'Habitation Saule",
    "wof:placetype":"venue"
},
  "geometry": {"coordinates":[-71.3357162476,46.8260498047],"type":"Point"}
}