{
  "type": "Feature",
  "properties": {
    "iso:country":"CA",
    "sg:city":"Mississauga",
    "sg:classifiers":[
        {
            "category":"Professional",
            "subcategory":"Printing & Photocopies",
            "type":"Services"
        }
    ],
    "sg:phone":"+1 905 890 4611",
    "sg:postcode":"L4Z 2Z1",
    "sg:province":"ON",
    "sg:tags":[
        "blueprinting",
        "printer"
    ],
    "wof:name":"Sherwood Digital Copy Ctr",
    "wof:placetype":"venue"
},
  "geometry": {"coordinates":[-79.671768,43.621677],"type":"Point"}
}