{
  "type": "Feature",
  "properties": {
    "addr:full":"1411 17 Ave SW Calgary AB T2T 0C6",
    "addr:housenumber":"1411",
    "addr:postcode":"t2t 0c6",
    "addr:street":"17 Ave Sw",
    "iso:country":"CA",
    "sg:address":"1411 17 Ave SW",
    "sg:city":"Calgary",
    "sg:classifiers":[
        {
            "category":"Restaurant",
            "type":"Food & Drink"
        }
    ],
    "sg:phone":"+1 403 228 7798",
    "sg:postcode":"T2T 0C6",
    "sg:province":"AB",
    "wof:name":"CO DO Vietnamese Restaurant",
    "wof:placetype":"venue"
},
  "geometry": {"coordinates":[-114.093727,51.03767],"type":"Point"}
}