{
  "type": "Feature",
  "properties": {
    "addr:full":"Spruce Grove AB T7X 2Z8",
    "addr:postcode":"t7x 2z8",
    "iso:country":"CA",
    "sg:city":"Spruce Grove",
    "sg:classifiers":[
        {
            "category":"Health Services",
            "subcategory":"Doctor",
            "type":"Services"
        }
    ],
    "sg:phone":"+1 780 962 9888",
    "sg:postcode":"T7X 2Z8",
    "sg:province":"AB",
    "sg:tags":[
        "physician",
        "surgeon"
    ],
    "wof:name":"Westgrove Clinic",
    "wof:placetype":"venue"
},
  "geometry": {"coordinates":[-113.908485,53.541546],"type":"Point"}
}