{
  "type": "Feature",
  "properties": {
    "addr:full":"1525 Taylor Way West Vancouver BC V7S 1N5",
    "addr:housenumber":"1525",
    "addr:postcode":"v7s 1n5",
    "addr:street":"Taylor Way",
    "iso:country":"CA",
    "sg:address":"1525 Taylor Way",
    "sg:city":"West Vancouver",
    "sg:classifiers":[
        {
            "category":"Organizations",
            "subcategory":"Religious Organization",
            "type":"Services"
        }
    ],
    "sg:phone":"+1 604 922 3961",
    "sg:postcode":"V7S 1N5",
    "sg:province":"BC",
    "sg:tags":[
        "church"
    ],
    "wof:name":"St David's United Church",
    "wof:placetype":"venue"
},
  "geometry": {"coordinates":[-123.13513946499999,49.338634491],"type":"Point"}
}