{
  "type": "Feature",
  "properties": {
    "addr:full":"Alameda SK S0C 0A0",
    "addr:postcode":"s0c 0a0",
    "addr:street":"Alameda Sk",
    "iso:country":"CA",
    "sg:city":"Alameda",
    "sg:classifiers":[
        {
            "category":"Wholesale",
            "subcategory":"Farm Supplies",
            "type":"Manufacturing & Wholesale Goods"
        }
    ],
    "sg:phone":"+1 306 489 2009",
    "sg:postcode":"S0C 0A0",
    "sg:province":"SK",
    "sg:tags":[
        "fertilizer"
    ],
    "wof:name":"Sask Wheat Pool",
    "wof:placetype":"venue"
},
  "geometry": {"coordinates":[-102.282341003,49.2667160034],"type":"Point"}
}