{
  "type": "Feature",
  "properties": {
    "addr:full":"188 138 Rte Saint-Augustin-DE-Desmaures QC G3A 1W7",
    "addr:housenumber":"138",
    "addr:postcode":"g3a 1w7",
    "addr:street":"Rte Saint-Augustin-De-Desmaures",
    "iso:country":"CA",
    "sg:address":"188 138 Rte",
    "sg:city":"Saint-Augustin-DE-Desmaures",
    "sg:classifiers":[
        {
            "category":"Wholesale",
            "subcategory":"Furniture",
            "type":"Manufacturing & Wholesale Goods"
        }
    ],
    "sg:phone":"+1 418 878 2486",
    "sg:postcode":"G3A 1W7",
    "sg:province":"QC",
    "wof:name":"Maber Distribution Inc",
    "wof:placetype":"venue"
},
  "geometry": {"coordinates":[-71.384727,46.749176],"type":"Point"}
}