{
  "type": "Feature",
  "properties": {
    "iso:country":"CA",
    "sg:address":"5896 Rue Saint-Jacques",
    "sg:city":"Montreal",
    "sg:classifiers":[
        {
            "category":"Building & Trades",
            "subcategory":"Construction",
            "type":"Services"
        }
    ],
    "sg:phone":"+1 514 481 6773",
    "sg:postcode":"H4A 2E9",
    "sg:province":"QC",
    "sg:tags":[
        "roofing",
        "contractor"
    ],
    "wof:name":"Pagani & Fils Couvreurs",
    "wof:placetype":"venue"
},
  "geometry": {"coordinates":[-73.6158218384,45.4642601013],"type":"Point"}
}