{
  "type": "Feature",
  "properties": {
    "addr:full":"16 South St Glace Bay NS B1A 1T6",
    "addr:housenumber":"16",
    "addr:postcode":"b1a 1t6",
    "addr:street":"South St",
    "iso:country":"CA",
    "sg:address":"16 South St",
    "sg:city":"Glace Bay",
    "sg:classifiers":[
        {
            "category":"Recreation",
            "type":"Entertainment"
        }
    ],
    "sg:phone":"+1 902 849 1742",
    "sg:postcode":"B1A 1T6",
    "sg:province":"NS",
    "sg:tags":[
        "martial",
        "arts",
        "instruction"
    ],
    "wof:name":"Clarke's Black Belt Academy",
    "wof:placetype":"venue"
},
  "geometry": {"coordinates":[-59.9536628723,46.1930503845],"type":"Point"}
}