{
  "type": "Feature",
  "properties": {
    "addr:full":"7371 Ash St Richmond BC V6Y 2R9",
    "addr:housenumber":"7371",
    "addr:postcode":"v6y 2r9",
    "addr:street":"Ash St",
    "iso:country":"CA",
    "sg:address":"7371 Ash St",
    "sg:city":"Richmond",
    "sg:classifiers":[
        {
            "category":"Building & Trades",
            "subcategory":"Construction",
            "type":"Services"
        }
    ],
    "sg:phone":"+1 604 278 8031",
    "sg:postcode":"V6Y 2R9",
    "sg:province":"BC",
    "sg:tags":[
        "plastering",
        "stucco",
        "contractor"
    ],
    "wof:name":"Americo Silva Plstr & Stcc Ltd",
    "wof:placetype":"venue"
},
  "geometry": {"coordinates":[-123.120010376,49.160118103],"type":"Point"}
}