{
  "type": "Feature",
  "properties": {
    "iso:country":"CA",
    "sg:address":"151 116 Rte",
    "sg:city":"Cleveland",
    "sg:classifiers":[
        {
            "category":"Autos & Motor Vehicles",
            "subcategory":"Automobile Sales",
            "type":"Retail Goods"
        }
    ],
    "sg:phone":"+1 819 826 5923",
    "sg:postcode":"J0B 2H0",
    "sg:province":"QC",
    "sg:tags":[
        "car",
        "dealer"
    ],
    "wof:name":"Toyota Richmond Inc",
    "wof:placetype":"venue"
},
  "geometry": {"coordinates":[-72.12139892579999,45.6763916016],"type":"Point"}
}