{
  "type": "Feature",
  "properties": {
    "iso:country":"CA",
    "sg:address":"180 Boul Rene-Levesque E",
    "sg:city":"Montreal",
    "sg:classifiers":[
        {
            "category":"Real Estate",
            "subcategory":"Real Estate Agent",
            "type":"Services"
        }
    ],
    "sg:phone":"+1 514 932 1451",
    "sg:postcode":"H2X 1N6",
    "sg:province":"QC",
    "sg:tags":[
        "management"
    ],
    "wof:name":"Kspe Management Inc",
    "wof:placetype":"venue"
},
  "geometry": {"coordinates":[-73.5598373413,45.5104675293],"type":"Point"}
}