{
  "type": "Feature",
  "properties": {
    "addr:full":"Powell River BC V8A 2L4",
    "addr:postcode":"v8a 2l4",
    "iso:country":"CA",
    "sg:city":"Powell River",
    "sg:classifiers":[
        {
            "category":"Organizations",
            "subcategory":"Professional Association",
            "type":"Services"
        }
    ],
    "sg:phone":"+1 604 485 6965",
    "sg:postcode":"V8A 2L4",
    "sg:province":"BC",
    "wof:name":"Women's Outreach",
    "wof:placetype":"venue"
},
  "geometry": {"coordinates":[-124.528541565,49.8436470032],"type":"Point"}
}