{
  "type": "Feature",
  "properties": {
    "iso:country":"CA",
    "sg:address":"1400 Barrydowne Rd",
    "sg:city":"Sudbury",
    "sg:classifiers":[
        {
            "category":"Arts & Performance",
            "subcategory":"Theater",
            "type":"Entertainment"
        }
    ],
    "sg:phone":"+1 705 524 7317",
    "sg:postcode":"P3A 3V8",
    "sg:province":"ON",
    "wof:name":"Theatre Cambrian",
    "wof:placetype":"venue"
},
  "geometry": {"coordinates":[-80.9439239502,46.5293083191],"type":"Point"}
}