{
  "type": "Feature",
  "properties": {
    "addr:full":"1170 Simcoe St N Oshawa ON L1G 4W8",
    "addr:housenumber":"1170",
    "addr:postcode":"l1g 4w8",
    "addr:street":"Simcoe St N",
    "iso:country":"CA",
    "sg:address":"1170 Simcoe St N",
    "sg:city":"Oshawa",
    "sg:classifiers":[
        {
            "category":"Freight",
            "type":"Transportation"
        }
    ],
    "sg:phone":"+1 905 723 6118",
    "sg:postcode":"L1G 4W8",
    "sg:province":"ON",
    "sg:tags":[
        "consultant"
    ],
    "wof:name":"Excel Highway Support Svc",
    "wof:placetype":"venue"
},
  "geometry": {"coordinates":[-78.877258,43.928516],"type":"Point"}
}