{
  "type": "Feature",
  "properties": {
    "iso:country":"CA",
    "sg:city":"Whitehorse",
    "sg:classifiers":[
        {
            "category":"Shopping",
            "subcategory":"Optical Goods",
            "type":"Retail Goods"
        }
    ],
    "sg:phone":"+1 867 668 4262",
    "sg:postcode":"Y1A 1A3",
    "sg:province":"YT",
    "wof:name":"Vision Express Optical Ltd",
    "wof:placetype":"venue"
},
  "geometry": {"coordinates":[-135.05091857900001,60.7205085754],"type":"Point"}
}