{
  "type": "Feature",
  "properties": {
    "addr:full":"Yorkton SK S3N 3N9",
    "addr:postcode":"s3n 3n9",
    "iso:country":"CA",
    "sg:city":"Yorkton",
    "sg:classifiers":[
        {
            "category":"Government",
            "subcategory":"Office",
            "type":"Public Place"
        }
    ],
    "sg:phone":"+1 306 786 5712",
    "sg:postcode":"S3N 3N9",
    "sg:province":"SK",
    "wof:name":"Saskatchewan Livestock Inspctr",
    "wof:placetype":"venue"
},
  "geometry": {"coordinates":[-102.447296143,51.224861145],"type":"Point"}
}