{
  "type": "Feature",
  "properties": {
    "addr:full":"703 23 Ave Nisku AB T9E 7Y5",
    "addr:postcode":"t9e 7y5",
    "addr:street":"703 23 Ave",
    "iso:country":"CA",
    "sg:address":"703 23 Ave",
    "sg:city":"Nisku",
    "sg:classifiers":[
        {
            "category":"Mining & Drilling",
            "type":"Manufacturing & Wholesale Goods"
        }
    ],
    "sg:phone":"+1 780 955 2567",
    "sg:postcode":"T9E 7Y5",
    "sg:province":"AB",
    "sg:tags":[
        "field",
        "oil"
    ],
    "wof:name":"Roneil Ventures Ltd",
    "wof:placetype":"venue"
},
  "geometry": {"coordinates":[-113.52047,53.343994],"type":"Point"}
}