{
  "type": "Feature",
  "properties": {
    "addr:full":"5964 Rue Saint-Laurent Levis QC G6V 3P4",
    "addr:housenumber":"5964",
    "addr:postcode":"g6v 3p4",
    "addr:street":"Rue Saint-Laurent",
    "iso:country":"CA",
    "sg:address":"5964 Rue Saint-Laurent",
    "sg:city":"Levis",
    "sg:classifiers":[
        {
            "category":"Retail",
            "subcategory":"Auto Repair",
            "type":"Services"
        }
    ],
    "sg:phone":"+1 418 835 1200",
    "sg:postcode":"G6V 3P4",
    "sg:province":"QC",
    "sg:tags":[
        "repairing",
        "automobile"
    ],
    "wof:name":"Garage DE LA Traverse Enr",
    "wof:placetype":"venue"
},
  "geometry": {"coordinates":[-71.1865158081,46.8094291687],"type":"Point"}
}