{
  "type": "Feature",
  "properties": {
    "addr:full":"43 Glenayr Rd Richmond Hill ON L4B 2V8",
    "addr:housenumber":"43",
    "addr:postcode":"l4b 2v8",
    "addr:street":"Glenayr Rd",
    "iso:country":"CA",
    "sg:address":"43 Glenayr Rd",
    "sg:city":"Richmond Hill",
    "sg:classifiers":[
        {
            "category":"Shopping",
            "subcategory":"Computers & Home Electronics",
            "type":"Retail Goods"
        }
    ],
    "sg:phone":"+1 905 780 8200",
    "sg:postcode":"L4B 2V8",
    "sg:province":"ON",
    "sg:tags":[
        "equipment",
        "dealer"
    ],
    "wof:name":"Microserve",
    "wof:placetype":"venue"
},
  "geometry": {"coordinates":[-79.403824,43.865868],"type":"Point"}
}