{
  "type": "Feature",
  "properties": {
    "iso:country":"CA",
    "sg:address":"1387 Av DE Valleyfield",
    "sg:city":"Laval",
    "sg:classifiers":[
        {
            "category":"Wholesale",
            "subcategory":"Machinery & Supplies",
            "type":"Manufacturing & Wholesale Goods"
        }
    ],
    "sg:phone":"+1 450 661 9483",
    "sg:postcode":"H7C 2K5",
    "sg:province":"QC",
    "sg:tags":[
        "machine",
        "tool"
    ],
    "wof:name":"Angelo Machinage Enr",
    "wof:placetype":"venue"
},
  "geometry": {"coordinates":[-73.66148376460001,45.6169395447],"type":"Point"}
}