{
  "type": "Feature",
  "properties": {
    "addr:full":"Calgary AB T2E 6K9",
    "addr:postcode":"t2e 6k9",
    "iso:country":"CA",
    "sg:city":"Calgary",
    "sg:classifiers":[
        {
            "category":"Retail",
            "subcategory":"Auto Repair",
            "type":"Services"
        }
    ],
    "sg:phone":"+1 403 250 9116",
    "sg:postcode":"T2E 6K9",
    "sg:province":"AB",
    "sg:tags":[
        "repairing",
        "automobile",
        "electric"
    ],
    "wof:name":"Rna Auto Electric",
    "wof:placetype":"venue"
},
  "geometry": {"coordinates":[-114.031867981,51.0891838074],"type":"Point"}
}