{
  "type": "Feature",
  "properties": {
    "iso:country":"CA",
    "sg:city":"Toronto",
    "sg:classifiers":[
        {
            "category":"Shopping",
            "subcategory":"Gifts & Souvenirs",
            "type":"Retail Goods"
        }
    ],
    "sg:phone":"+1 416 971 8848",
    "sg:postcode":"M5V 1J2",
    "sg:province":"ON",
    "sg:tags":[
        "collectible"
    ],
    "wof:name":"Legends of the Game",
    "wof:placetype":"venue"
},
  "geometry": {"coordinates":[-79.38962554930001,43.6467514038],"type":"Point"}
}