{
  "type": "Feature",
  "properties": {
    "addr:full":"2400 Sixth Line Oakville ON L6H 3N8",
    "addr:housenumber":"2400",
    "addr:postcode":"l6h 3n8",
    "addr:street":"Sixth Line",
    "iso:country":"CA",
    "sg:address":"2400 Sixth Line",
    "sg:city":"Oakville",
    "sg:classifiers":[
        {
            "category":"Recreation",
            "type":"Entertainment"
        }
    ],
    "sg:phone":"+1 905 338 4186",
    "sg:postcode":"L6H 3N8",
    "sg:province":"ON",
    "sg:tags":[
        "government",
        "hall",
        "auditorium"
    ],
    "wof:name":"Oakville River Oaks Comm Ctr",
    "wof:placetype":"venue"
},
  "geometry": {"coordinates":[-79.723297,43.471432],"type":"Point"}
}