{
  "type": "Feature",
  "properties": {
    "addr:full":"201 Milton St Nanaimo BC V9R 2K5",
    "addr:housenumber":"201",
    "addr:postcode":"v9r 2k5",
    "addr:street":"Milton St",
    "iso:country":"CA",
    "sg:address":"201 Milton St",
    "sg:city":"Nanaimo",
    "sg:classifiers":[
        {
            "category":"Professional",
            "subcategory":"Lawyer & Legal Services",
            "type":"Services"
        }
    ],
    "sg:phone":"+1 250 741 9053",
    "sg:postcode":"V9R 2K5",
    "sg:province":"BC",
    "sg:tags":[
        "attorney"
    ],
    "wof:name":"Merrill Long & CO",
    "wof:placetype":"venue"
},
  "geometry": {"coordinates":[-123.94632,49.166325],"type":"Point"}
}