{
  "type": "Feature",
  "properties": {
    "addr:full":"Saint-Eustache QC J7R 5V3",
    "addr:postcode":"j7r 5v3",
    "iso:country":"CA",
    "sg:city":"Saint-Eustache",
    "sg:classifiers":[
        {
            "category":"Building & Trades",
            "subcategory":"Construction",
            "type":"Services"
        }
    ],
    "sg:phone":"+1 450 623 4765",
    "sg:postcode":"J7R 5V3",
    "sg:province":"QC",
    "sg:tags":[
        "plastic",
        "weather",
        "stripping",
        "contractor"
    ],
    "wof:name":"Extrusions Du Nord",
    "wof:placetype":"venue"
},
  "geometry": {"coordinates":[-73.920883,45.553741],"type":"Point"}
}