{
  "type": "Feature",
  "properties": {
    "addr:full":"1451 Avenue Rd North York ON M5N 2H9",
    "addr:housenumber":"1451",
    "addr:postcode":"m5n 2h9",
    "addr:street":"Avenue Rd",
    "iso:country":"CA",
    "sg:address":"1451 Avenue Rd",
    "sg:city":"North York",
    "sg:classifiers":[
        {
            "category":"Education",
            "subcategory":"School",
            "type":"Public Place"
        }
    ],
    "sg:phone":"+1 416 483 3519",
    "sg:postcode":"M5N 2H9",
    "sg:province":"ON",
    "wof:name":"Havergal College",
    "wof:placetype":"venue"
},
  "geometry": {"coordinates":[-79.414642,43.719452],"type":"Point"}
}