{
  "type": "Feature",
  "properties": {
    "addr:full":"545 Rue Saint-Alphonse Saint-Bruno-Lac-Saint-Jean QC G0W 2L0",
    "addr:housenumber":"545",
    "addr:postcode":"g0w 2l0",
    "addr:street":"Rue Saint-Alphonse Saint-Bruno-Lac-Saint-Jean",
    "iso:country":"CA",
    "sg:address":"545 Rue Saint-Alphonse",
    "sg:city":"Saint-Bruno-Lac-Saint-Jean",
    "sg:classifiers":[
        {
            "category":"Organizations",
            "subcategory":"Professional Association",
            "type":"Services"
        }
    ],
    "sg:phone":"+1 418 343 3874",
    "sg:postcode":"G0W 2L0",
    "sg:province":"QC",
    "wof:name":"Maison Des Jeunes St-Bruno",
    "wof:placetype":"venue"
},
  "geometry": {"coordinates":[-71.65371704099999,48.4710044861],"type":"Point"}
}