{
  "type": "Feature",
  "properties": {
    "iso:country":"CA",
    "sg:address":"1819 Rue Belanger",
    "sg:city":"Montreal",
    "sg:classifiers":[
        {
            "category":"Food & Beverages",
            "subcategory":"Groceries & Convenience Stores",
            "type":"Retail Goods"
        }
    ],
    "sg:phone":"+1 514 593 1188",
    "sg:postcode":"H2G 1B3",
    "sg:province":"QC",
    "wof:name":"Depanneur Belanger-Plus",
    "wof:placetype":"venue"
},
  "geometry": {"coordinates":[-73.6035003662,45.546672821],"type":"Point"}
}