{
  "type": "Feature",
  "properties": {
    "addr:full":"287 Rang Lafreniere Saint-Edouard-DE-Napierville QC J0L 1Y0",
    "addr:housenumber":"287",
    "addr:postcode":"j0l 1y0",
    "addr:street":"Rang Lafreniere Saint-Edouard-De-Napierville",
    "iso:country":"CA",
    "sg:address":"287 Rang Lafreniere",
    "sg:city":"Saint-Edouard-DE-Napierville",
    "sg:classifiers":[
        {
            "category":"Freight",
            "type":"Transportation"
        }
    ],
    "sg:phone":"+1 450 454 3624",
    "sg:postcode":"J0L 1Y0",
    "sg:province":"QC",
    "sg:tags":[
        "trucking"
    ],
    "wof:name":"D C Dumouchel Transport",
    "wof:placetype":"venue"
},
  "geometry": {"coordinates":[-73.510757,45.234589],"type":"Point"}
}