{
  "type": "Feature",
  "properties": {
    "addr:full":"880 Rue Belvedere S Sherbrooke QC J1H 4C2",
    "addr:housenumber":"880",
    "addr:postcode":"j1h 4c2",
    "addr:street":"Rue Belvedere S",
    "iso:country":"CA",
    "sg:address":"880 Rue Belvedere S",
    "sg:city":"Sherbrooke",
    "sg:classifiers":[
        {
            "category":"Professional",
            "subcategory":"Management & Consulting",
            "type":"Services"
        }
    ],
    "sg:phone":"+1 819 564 6448",
    "sg:postcode":"J1H 4C2",
    "sg:province":"QC",
    "sg:tags":[
        "consultant",
        "business"
    ],
    "wof:name":"Service D'Organisation Inc",
    "wof:placetype":"venue"
},
  "geometry": {"coordinates":[-71.895996,45.39323],"type":"Point"}
}