{
  "type": "Feature",
  "properties": {
    "addr:full":"Debert NS B0M 1G0",
    "addr:postcode":"b0m 1g0",
    "iso:country":"CA",
    "sg:city":"Debert",
    "sg:classifiers":[
        {
            "category":"Wholesale",
            "subcategory":"Farm Supplies",
            "type":"Manufacturing & Wholesale Goods"
        }
    ],
    "sg:phone":"+1 902 662 3440",
    "sg:postcode":"B0M 1G0",
    "sg:province":"NS",
    "sg:tags":[
        "bulb",
        "seed"
    ],
    "wof:name":"Halifax Seed CO",
    "wof:placetype":"venue"
},
  "geometry": {"coordinates":[-63.4477386475,45.430480957],"type":"Point"}
}