{
  "type": "Feature",
  "properties": {
    "iso:country":"CA",
    "sg:address":"451 Church St",
    "sg:city":"Toronto",
    "sg:classifiers":[
        {
            "category":"Restaurant",
            "type":"Food & Drink"
        }
    ],
    "sg:phone":"+1 416 920 8991",
    "sg:postcode":"M4Y 2C5",
    "sg:province":"ON",
    "wof:name":"Omi Japanese Restaurant",
    "wof:placetype":"venue"
},
  "geometry": {"coordinates":[-79.3800354004,43.6640472412],"type":"Point"}
}