{
  "type": "Feature",
  "properties": {
    "addr:full":"200 University Ave Toronto ON M5H 3C6",
    "addr:housenumber":"200",
    "addr:postcode":"m5h 3c6",
    "addr:street":"University Ave",
    "iso:country":"CA",
    "sg:address":"200 University Ave",
    "sg:city":"Toronto",
    "sg:classifiers":[
        {
            "category":"Shopping",
            "subcategory":"Computers & Home Electronics",
            "type":"Retail Goods"
        }
    ],
    "sg:phone":"+1 905 477 6745",
    "sg:postcode":"M5H 3C6",
    "sg:province":"ON",
    "sg:tags":[
        "software"
    ],
    "wof:name":"Sun Microsystems of Canada Inc",
    "wof:placetype":"venue"
},
  "geometry": {"coordinates":[-79.386482,43.649834],"type":"Point"}
}