{
  "type": "Feature",
  "properties": {
    "addr:full":"50850 Yale Rd Rosedale BC V0X 1X0",
    "addr:housenumber":"50850",
    "addr:postcode":"v0x 1x0",
    "addr:street":"Yale Rd",
    "iso:country":"CA",
    "sg:address":"50850 Yale Rd",
    "sg:city":"Rosedale",
    "sg:classifiers":[
        {
            "category":"Education",
            "subcategory":"School",
            "type":"Public Place"
        }
    ],
    "sg:phone":"+1 604 794 7124",
    "sg:postcode":"V0X 1X0",
    "sg:province":"BC",
    "wof:name":"Rosedale Middle School",
    "wof:placetype":"venue"
},
  "geometry": {"coordinates":[-121.817238,49.175385],"type":"Point"}
}