{
  "type": "Feature",
  "properties": {
    "iso:country":"CA",
    "sg:address":"1612 Northfield Rd",
    "sg:city":"Nanaimo",
    "sg:classifiers":[
        {
            "category":"Manufacturing",
            "subcategory":"Furniture",
            "type":"Manufacturing & Wholesale Goods"
        }
    ],
    "sg:phone":"+1 250 758 3033",
    "sg:postcode":"V9S 3A7",
    "sg:province":"BC",
    "sg:tags":[
        "curtain",
        "coating",
        "drapery",
        "tinting",
        "glass"
    ],
    "wof:name":"Con-Rod Installations",
    "wof:placetype":"venue"
},
  "geometry": {"coordinates":[-123.973694,49.192043],"type":"Point"}
}