{
  "type": "Feature",
  "properties": {
    "addr:full":"690 River St Port Elgin ON N0H 2C3",
    "addr:housenumber":"690",
    "addr:postcode":"n0h 2c3",
    "addr:street":"River St",
    "iso:country":"CA",
    "sg:address":"690 River St",
    "sg:city":"Port Elgin",
    "sg:classifiers":[
        {
            "category":"Retail",
            "subcategory":"Repair Shop",
            "type":"Services"
        }
    ],
    "sg:phone":"+1 519 832 5963",
    "sg:postcode":"N0H 2C3",
    "sg:province":"ON",
    "sg:tags":[
        "equipment",
        "golf",
        "refinishing"
    ],
    "wof:name":"Sale Ag",
    "wof:placetype":"venue"
},
  "geometry": {"coordinates":[-81.3828582764,44.4386825562],"type":"Point"}
}