{
  "type": "Feature",
  "properties": {
    "addr:full":"105 Mcgovern Dr Cambridge ON N3H 4R7",
    "addr:housenumber":"105",
    "addr:postcode":"n3h 4r7",
    "addr:street":"Mcgovern Dr",
    "iso:country":"CA",
    "sg:address":"105 Mcgovern Dr",
    "sg:city":"Cambridge",
    "sg:classifiers":[
        {
            "category":"Wholesale",
            "subcategory":"Durable Goods & Equipment",
            "type":"Manufacturing & Wholesale Goods"
        }
    ],
    "sg:phone":"+1 519 653 9853",
    "sg:postcode":"N3H 4R7",
    "sg:province":"ON",
    "sg:tags":[
        "tarpaulin"
    ],
    "wof:name":"Cambridge Canvas Ctr Ltd",
    "wof:placetype":"venue"
},
  "geometry": {"coordinates":[-80.32996368409999,43.4112129211],"type":"Point"}
}