{
  "type": "Feature",
  "properties": {
    "addr:full":"163 Pellham St Lunenburg NS B0J 2C0",
    "addr:housenumber":"163",
    "addr:postcode":"b0j 2c0",
    "addr:street":"Pellham St",
    "iso:country":"CA",
    "sg:address":"163 Pellham St",
    "sg:city":"Lunenburg",
    "sg:classifiers":[
        {
            "category":"Wholesale",
            "subcategory":"Durable Goods & Equipment",
            "type":"Manufacturing & Wholesale Goods"
        }
    ],
    "sg:phone":"+1 902 634 7222",
    "sg:postcode":"B0J 2C0",
    "sg:province":"NS",
    "sg:tags":[
        "representative",
        "manufacturer"
    ],
    "wof:name":"H E Wathen & CO Ltd",
    "wof:placetype":"venue"
},
  "geometry": {"coordinates":[-64.30744934080001,44.3767242432],"type":"Point"}
}