{
  "type": "Feature",
  "properties": {
    "addr:full":"4335 Blackcomb Way Whistler BC V0N 1B4",
    "addr:housenumber":"4335",
    "addr:postcode":"v0n 1b4",
    "addr:street":"Blackcomb Way",
    "iso:country":"CA",
    "sg:address":"4335 Blackcomb Way",
    "sg:city":"Whistler",
    "sg:classifiers":[
        {
            "category":"Recreation",
            "type":"Entertainment"
        }
    ],
    "sg:phone":"+1 604 935 8410",
    "sg:postcode":"V0N 1B4",
    "sg:province":"BC",
    "sg:tags":[
        "ticket"
    ],
    "wof:name":"Maurice Young Millennium Place",
    "wof:placetype":"venue"
},
  "geometry": {"coordinates":[-122.953934,50.117893],"type":"Point"}
}