{
  "type": "Feature",
  "properties": {
    "addr:full":"Vernon BC V1T 7G7",
    "addr:postcode":"v1t 7g7",
    "iso:country":"CA",
    "sg:city":"Vernon",
    "sg:classifiers":[
        {
            "category":"Restaurant",
            "type":"Food & Drink"
        }
    ],
    "sg:phone":"+1 250 542 2919",
    "sg:postcode":"V1T 7G7",
    "sg:province":"BC",
    "wof:name":"Taco Time",
    "wof:placetype":"venue"
},
  "geometry": {"coordinates":[-119.266853,50.283592],"type":"Point"}
}