{
  "type": "Feature",
  "properties": {
    "addr:full":"67 Water St St Jacobs ON N0B 2N0",
    "addr:housenumber":"67",
    "addr:postcode":"n0b 2n0",
    "addr:street":"Water St St",
    "iso:country":"CA",
    "sg:address":"67 Water St",
    "sg:city":"St Jacobs",
    "sg:classifiers":[
        {
            "category":"Wholesale",
            "subcategory":"Home Furnishings",
            "type":"Manufacturing & Wholesale Goods"
        }
    ],
    "sg:phone":"+1 519 664 2834",
    "sg:postcode":"N0B 2N0",
    "sg:province":"ON",
    "sg:tags":[
        "janitor",
        "mat",
        "matting"
    ],
    "wof:name":"Sanway Supply CO",
    "wof:placetype":"venue"
},
  "geometry": {"coordinates":[-80.5516052246,43.5357208252],"type":"Point"}
}