{
  "type": "Feature",
  "properties": {
    "addr:full":"557 Pembroke St E Pembroke ON K8A 3L5",
    "addr:housenumber":"557",
    "addr:postcode":"k8a 3l5",
    "addr:street":"Pembroke St E",
    "iso:country":"CA",
    "sg:address":"557 Pembroke St E",
    "sg:city":"Pembroke",
    "sg:classifiers":[
        {
            "category":"Shopping",
            "subcategory":"Musical Instruments",
            "type":"Retail Goods"
        }
    ],
    "sg:phone":"+1 613 735 3624",
    "sg:postcode":"K8A 3L5",
    "sg:province":"ON",
    "wof:name":"Musical Encounters",
    "wof:placetype":"venue"
},
  "geometry": {"coordinates":[-77.09799957280001,45.8280334473],"type":"Point"}
}