{
  "type": "Feature",
  "properties": {
    "addr:full":"Scarborough ON M1J 2H6",
    "addr:postcode":"m1j 2h6",
    "iso:country":"CA",
    "sg:city":"Scarborough",
    "sg:classifiers":[
        {
            "category":"Restaurant",
            "type":"Food & Drink"
        }
    ],
    "sg:phone":"+1 416 261 7042",
    "sg:postcode":"M1J 2H6",
    "sg:province":"ON",
    "wof:name":"Hot Rotti Hut",
    "wof:placetype":"venue"
},
  "geometry": {"coordinates":[-79.21802520750001,43.7435646057],"type":"Point"}
}