{
  "type": "Feature",
  "properties": {
    "addr:full":"Roberval QC G8H 2M9",
    "addr:postcode":"g8h 2m9",
    "iso:country":"CA",
    "sg:city":"Roberval",
    "sg:classifiers":[
        {
            "category":"Retail",
            "subcategory":"Auto Rental",
            "type":"Services"
        }
    ],
    "sg:phone":"+1 418 275 7911",
    "sg:postcode":"G8H 2M9",
    "sg:province":"QC",
    "sg:tags":[
        "renting",
        "automobile"
    ],
    "wof:name":"Location National",
    "wof:placetype":"venue"
},
  "geometry": {"coordinates":[-72.250038,48.531261],"type":"Point"}
}