{
  "type": "Feature",
  "properties": {
    "addr:full":"Saskatoon SK S7J 2G2",
    "addr:postcode":"s7j 2g2",
    "iso:country":"CA",
    "sg:city":"Saskatoon",
    "sg:classifiers":[
        {
            "category":"Shopping",
            "subcategory":"Clothing, Apparel, & Fashions",
            "type":"Retail Goods"
        }
    ],
    "sg:phone":"+1 306 978 7250",
    "sg:postcode":"S7J 2G2",
    "sg:province":"SK",
    "wof:name":"Cotton Ginny",
    "wof:placetype":"venue"
},
  "geometry": {"coordinates":[-106.62247467,52.1013145447],"type":"Point"}
}