{
  "type": "Feature",
  "properties": {
    "iso:country":"CA",
    "sg:address":"36 Water St S",
    "sg:city":"St Marys",
    "sg:classifiers":[
        {
            "category":"Shopping",
            "type":"Retail Goods"
        }
    ],
    "sg:phone":"+1 519 284 3634",
    "sg:postcode":"N4X 1B1",
    "sg:province":"ON",
    "sg:tags":[
        "equipment",
        "wine",
        "supply"
    ],
    "wof:name":"St Marys Wines",
    "wof:placetype":"venue"
},
  "geometry": {"coordinates":[-81.143524,43.258545],"type":"Point"}
}