{
  "type": "Feature",
  "properties": {
    "addr:full":"352 Wilson Ave North York ON M3H 1S9",
    "addr:housenumber":"352",
    "addr:postcode":"m3h 1s9",
    "addr:street":"Wilson Ave",
    "iso:country":"CA",
    "sg:address":"352 Wilson Ave",
    "sg:city":"North York",
    "sg:classifiers":[
        {
            "category":"Retail",
            "subcategory":"Veterinary Services",
            "type":"Services"
        }
    ],
    "sg:phone":"+1 416 635 9090",
    "sg:postcode":"M3H 1S9",
    "sg:province":"ON",
    "sg:tags":[
        "veterinarian"
    ],
    "wof:name":"Bathurst Animal Clinic",
    "wof:placetype":"venue"
},
  "geometry": {"coordinates":[-79.438301,43.736645],"type":"Point"}
}