{
  "type": "Feature",
  "properties": {
    "addr:full":"PO Box 119 Kings Point NL A0J 1H0",
    "addr:housenumber":"po",
    "addr:postcode":"a0j 1h0",
    "addr:street":"Box 119 Kings Point",
    "iso:country":"CA",
    "sg:address":"PO Box 119",
    "sg:city":"Kings Point",
    "sg:classifiers":[
        {
            "category":"Organizations",
            "subcategory":"Religious Organization",
            "type":"Services"
        }
    ],
    "sg:phone":"+1 709 268 2234",
    "sg:postcode":"A0J 1H0",
    "sg:province":"NL",
    "sg:tags":[
        "church"
    ],
    "wof:name":"Kings Point United Church",
    "wof:placetype":"venue"
},
  "geometry": {"coordinates":[-57.961231,48.949078],"type":"Point"}
}