{
  "type": "Feature",
  "properties": {
    "addr:full":"2525 St Laurent Blvd Ottawa ON K1H 8P5",
    "addr:housenumber":"2525",
    "addr:postcode":"k1h 8p5",
    "addr:street":"St Laurent Blvd",
    "iso:country":"CA",
    "sg:address":"2525 St Laurent Blvd",
    "sg:city":"Ottawa",
    "sg:classifiers":[
        {
            "category":"Organizations",
            "subcategory":"Labor Organization",
            "type":"Services"
        }
    ],
    "sg:phone":"+1 613 739 9100",
    "sg:postcode":"K1H 8P5",
    "sg:province":"ON",
    "wof:name":"Ontario Public Svc Employees",
    "wof:placetype":"venue"
},
  "geometry": {"coordinates":[-75.6293792725,45.3804588318],"type":"Point"}
}