{
  "type": "Feature",
  "properties": {
    "addr:full":"75 Ch Napoleon Mont-Tremblant QC J8E 2G5",
    "addr:housenumber":"75",
    "addr:postcode":"j8e 2g5",
    "addr:street":"Ch Napoleon",
    "iso:country":"CA",
    "sg:address":"75 Ch Napoleon",
    "sg:city":"Mont-Tremblant",
    "sg:classifiers":[
        {
            "category":"Government",
            "subcategory":"Office",
            "type":"Public Place"
        }
    ],
    "sg:phone":"+1 819 425 8614",
    "sg:postcode":"J8E 2G5",
    "sg:province":"QC",
    "sg:tags":[
        "village"
    ],
    "wof:name":"St-Jovite Travaux Publics",
    "wof:placetype":"venue"
},
  "geometry": {"coordinates":[-74.61541699999999,46.137032],"type":"Point"}
}