{
  "type": "Feature",
  "properties": {
    "addr:full":"53 Andrea Lane Woodbridge ON L4L 1E6",
    "addr:housenumber":"53",
    "addr:postcode":"l4l 1e6",
    "addr:street":"Andrea Lane",
    "iso:country":"CA",
    "sg:address":"53 Andrea Lane",
    "sg:city":"Woodbridge",
    "sg:classifiers":[
        {
            "category":"Building & Trades",
            "subcategory":"Landscaping Services",
            "type":"Services"
        }
    ],
    "sg:phone":"+1 905 851 2577",
    "sg:postcode":"L4L 1E6",
    "sg:province":"ON",
    "sg:tags":[
        "landscape",
        "contractor"
    ],
    "wof:name":"Uprite Fence CO",
    "wof:placetype":"venue"
},
  "geometry": {"coordinates":[-79.56745910639999,43.80103302],"type":"Point"}
}