{
  "type": "Feature",
  "properties": {
    "addr:full":"930 Boul Decarie Saint-Laurent QC H4L 3M4",
    "addr:housenumber":"930",
    "addr:postcode":"h4l 3m4",
    "addr:street":"Boul Decarie",
    "iso:country":"CA",
    "sg:address":"930 Boul Decarie",
    "sg:city":"Saint-Laurent",
    "sg:classifiers":[
        {
            "category":"Restaurant",
            "type":"Food & Drink"
        }
    ],
    "sg:phone":"+1 514 747 4805",
    "sg:postcode":"H4L 3M4",
    "sg:province":"QC",
    "wof:name":"Restaurant Ban Lao Thai",
    "wof:placetype":"venue"
},
  "geometry": {"coordinates":[-73.68119799999999,45.513031],"type":"Point"}
}