{
  "type": "Feature",
  "properties": {
    "addr:full":"4 Du Moulin Saint-Urbain-DE-Charlevoix QC G0A 4K0",
    "addr:housenumber":"4",
    "addr:postcode":"g0a 4k0",
    "addr:street":"Du Moulin Saint-Urbain-De-Charlevoix",
    "iso:country":"CA",
    "sg:address":"4 Du Moulin",
    "sg:city":"Saint-Urbain-DE-Charlevoix",
    "sg:classifiers":[
        {
            "category":"Building & Trades",
            "subcategory":"Construction",
            "type":"Services"
        }
    ],
    "sg:phone":"+1 418 639 2111",
    "sg:postcode":"G0A 4K0",
    "sg:province":"QC",
    "sg:tags":[
        "excavating",
        "contractor"
    ],
    "wof:name":"Entreprise Ger-Si Inc",
    "wof:placetype":"venue"
},
  "geometry": {"coordinates":[-70.546143,47.560684],"type":"Point"}
}