{
  "type": "Feature",
  "properties": {
    "iso:country":"CA",
    "sg:address":"10 Water Street Parkway",
    "sg:city":"Charlottetown",
    "sg:classifiers":[
        {
            "category":"Government",
            "subcategory":"Office",
            "type":"Public Place"
        }
    ],
    "sg:phone":"+1 902 368 0414",
    "sg:postcode":"C1A 9M5",
    "sg:province":"PE",
    "wof:name":"Hmcs Queen Charlotte",
    "wof:placetype":"venue"
},
  "geometry": {"coordinates":[-63.1165275574,46.2387504578],"type":"Point"}
}