{
  "type": "Feature",
  "properties": {
    "iso:country":"CA",
    "sg:address":"983 Helmcken St",
    "sg:city":"Vancouver",
    "sg:classifiers":[
        {
            "category":"Restaurant",
            "type":"Food & Drink"
        }
    ],
    "sg:phone":"+1 604 331 0203",
    "sg:postcode":"V6Z 2S5",
    "sg:province":"BC",
    "sg:tags":[
        "delicatessen"
    ],
    "wof:name":"Deli O",
    "wof:placetype":"venue"
},
  "geometry": {"coordinates":[-123.127007,49.279816],"type":"Point"}
}