{
  "type": "Feature",
  "properties": {
    "addr:full":"12830 24 Ave Surrey BC V4A 2E8",
    "addr:housenumber":"12830",
    "addr:postcode":"v4a 2e8",
    "addr:street":"24 Ave",
    "iso:country":"CA",
    "sg:address":"12830 24 Ave",
    "sg:city":"Surrey",
    "sg:classifiers":[
        {
            "category":"Building & Trades",
            "subcategory":"Construction",
            "type":"Services"
        }
    ],
    "sg:phone":"+1 604 535 6700",
    "sg:postcode":"V4A 2E8",
    "sg:province":"BC",
    "sg:tags":[
        "painter"
    ],
    "wof:name":"Personal Touch Painting",
    "wof:placetype":"venue"
},
  "geometry": {"coordinates":[-122.866356,49.045586],"type":"Point"}
}