{
  "type": "Feature",
  "properties": {
    "addr:full":"2144 Rue King O Sherbrooke QC J1J 2E8",
    "addr:housenumber":"2144",
    "addr:postcode":"j1j 2e8",
    "addr:street":"Rue King O",
    "iso:country":"CA",
    "sg:address":"2144 Rue King O",
    "sg:city":"Sherbrooke",
    "sg:classifiers":[
        {
            "category":"Manufacturing",
            "subcategory":"Rubber & Plastics",
            "type":"Manufacturing & Wholesale Goods"
        }
    ],
    "sg:phone":"+1 819 823 1777",
    "sg:postcode":"J1J 2E8",
    "sg:province":"QC",
    "sg:tags":[
        "product"
    ],
    "wof:name":"Camoplast Inc",
    "wof:placetype":"venue"
},
  "geometry": {"coordinates":[-71.9252243042,45.3979530334],"type":"Point"}
}