{
  "type": "Feature",
  "properties": {
    "addr:full":"Arnstein ON P0H 1A0",
    "addr:postcode":"p0h 1a0",
    "iso:country":"CA",
    "sg:city":"Arnstein",
    "sg:classifiers":[
        {
            "category":"Autos & Motor Vehicles",
            "subcategory":"Fuel & Gas Station",
            "type":"Retail Goods"
        }
    ],
    "sg:phone":"+1 705 757 2070",
    "sg:postcode":"P0H 1A0",
    "sg:province":"ON",
    "sg:tags":[
        "repairing",
        "automobile",
        "oil"
    ],
    "wof:name":"Arnstein Garage",
    "wof:placetype":"venue"
},
  "geometry": {"coordinates":[-79.928932,45.921021],"type":"Point"}
}