{
  "type": "Feature",
  "properties": {
    "iso:country":"CA",
    "sg:address":"110 3 St W",
    "sg:city":"Drumheller",
    "sg:classifiers":[
        {
            "category":"Banks & Credit Unions",
            "subcategory":"Bank",
            "type":"Services"
        }
    ],
    "sg:phone":"+1 403 823 4414",
    "sg:postcode":"T0J 0Y4",
    "sg:province":"AB",
    "wof:name":"Royal Bank Financial Group",
    "wof:placetype":"venue"
},
  "geometry": {"coordinates":[-112.712089539,51.4663047791],"type":"Point"}
}