{
  "type": "Feature",
  "properties": {
    "addr:full":"Toronto ON M5T 1R6",
    "addr:postcode":"m5t 1r6",
    "iso:country":"CA",
    "sg:city":"Toronto",
    "sg:classifiers":[
        {
            "category":"Restaurant",
            "type":"Food & Drink"
        }
    ],
    "sg:phone":"+1 416 591 9999",
    "sg:postcode":"M5T 1R6",
    "sg:province":"ON",
    "wof:name":"Burger King",
    "wof:placetype":"venue"
},
  "geometry": {"coordinates":[-79.3996124268,43.6578330994],"type":"Point"}
}