{
  "type": "Feature",
  "properties": {
    "addr:full":"2392 Ospika Blvd S Prince George BC V2N 3N5",
    "addr:housenumber":"2392",
    "addr:postcode":"v2n 3n5",
    "addr:street":"Ospika Blvd S",
    "iso:country":"CA",
    "sg:address":"2392 Ospika Blvd S",
    "sg:city":"Prince George",
    "sg:classifiers":[
        {
            "category":"Shopping",
            "type":"Retail Goods"
        }
    ],
    "sg:phone":"+1 250 563 1993",
    "sg:postcode":"V2N 3N5",
    "sg:province":"BC",
    "sg:tags":[
        "pet",
        "food",
        "supply"
    ],
    "wof:name":"Ospika Pet & Farm Supplies",
    "wof:placetype":"venue"
},
  "geometry": {"coordinates":[-122.791603088,53.899597168],"type":"Point"}
}