{
  "type": "Feature",
  "properties": {
    "addr:full":"Toronto ON M6P 1T7",
    "addr:postcode":"m6p 1t7",
    "iso:country":"CA",
    "sg:city":"Toronto",
    "sg:classifiers":[
        {
            "category":"Restaurant",
            "type":"Food & Drink"
        }
    ],
    "sg:phone":"+1 416 763 4171",
    "sg:postcode":"M6P 1T7",
    "sg:province":"ON",
    "wof:name":"Lotus Inn Chinese Cuisine",
    "wof:placetype":"venue"
},
  "geometry": {"coordinates":[-79.4744186401,43.6652297974],"type":"Point"}
}