{
  "type": "Feature",
  "properties": {
    "addr:full":"301 Joslyn St Hartney MB R0M 0X0",
    "addr:housenumber":"301",
    "addr:postcode":"r0m 0x0",
    "addr:street":"Joslyn St",
    "iso:country":"CA",
    "sg:address":"301 Joslyn St",
    "sg:city":"Hartney",
    "sg:classifiers":[
        {
            "category":"Autos & Motor Vehicles",
            "subcategory":"Auto Supplies",
            "type":"Retail Goods"
        }
    ],
    "sg:phone":"+1 204 858 2100",
    "sg:postcode":"R0M 0X0",
    "sg:province":"MB",
    "sg:tags":[
        "farm",
        "equipment"
    ],
    "wof:name":"Mills Farm Equipment Ltd",
    "wof:placetype":"venue"
},
  "geometry": {"coordinates":[-100.528015137,49.4774780273],"type":"Point"}
}