{
  "type": "Feature",
  "properties": {
    "iso:country":"CA",
    "sg:address":"8 Dundas St",
    "sg:city":"Princeton",
    "sg:classifiers":[
        {
            "category":"Manufacturing",
            "subcategory":"Motor Vehicles & Parts",
            "type":"Manufacturing & Wholesale Goods"
        }
    ],
    "sg:phone":"+1 519 458 4774",
    "sg:postcode":"N0J 1V0",
    "sg:province":"ON",
    "sg:tags":[
        "designer",
        "trailer"
    ],
    "wof:name":"T & M Mfg Inc",
    "wof:placetype":"venue"
},
  "geometry": {"coordinates":[-80.5254898071,43.1646118164],"type":"Point"}
}