{
  "type": "Feature",
  "properties": {
    "addr:full":"12 Rue Verville Baie-Du-Febvre QC J0G 1A0",
    "addr:housenumber":"12",
    "addr:postcode":"j0g 1a0",
    "addr:street":"Rue Verville",
    "iso:country":"CA",
    "sg:address":"12 Rue Verville",
    "sg:city":"Baie-Du-Febvre",
    "sg:classifiers":[
        {
            "category":"Building & Trades",
            "subcategory":"Construction",
            "type":"Services"
        }
    ],
    "sg:phone":"+1 450 783 6964",
    "sg:postcode":"J0G 1A0",
    "sg:province":"QC",
    "sg:tags":[
        "contractor"
    ],
    "wof:name":"Construction Andre Manseau Inc",
    "wof:placetype":"venue"
},
  "geometry": {"coordinates":[-72.715057,46.138691],"type":"Point"}
}