{
  "type": "Feature",
  "properties": {
    "addr:full":"Carleton Place ON K7C 3P2",
    "addr:postcode":"k7c 3p2",
    "iso:country":"CA",
    "sg:city":"Carleton Place",
    "sg:classifiers":[
        {
            "category":"Organizations",
            "subcategory":"Religious Organization",
            "type":"Services"
        }
    ],
    "sg:phone":"+1 613 257 8376",
    "sg:postcode":"K7C 3P2",
    "sg:province":"ON",
    "sg:tags":[
        "church"
    ],
    "wof:name":"Beckwith Baptist Church",
    "wof:placetype":"venue"
},
  "geometry": {"coordinates":[-76.146812,45.14045],"type":"Point"}
}