{
  "type": "Feature",
  "properties": {
    "addr:full":"2005 Pembina Hwy Winnipeg MB R3T 5W7",
    "addr:housenumber":"2005",
    "addr:postcode":"r3t 5w7",
    "addr:street":"Pembina Hwy",
    "iso:country":"CA",
    "sg:address":"2005 Pembina Hwy",
    "sg:city":"Winnipeg",
    "sg:classifiers":[
        {
            "category":"Restaurant",
            "type":"Food & Drink"
        }
    ],
    "sg:phone":"+1 204 275 1250",
    "sg:postcode":"R3T 5W7",
    "sg:province":"MB",
    "wof:name":"Earl's Restaurant",
    "wof:placetype":"venue"
},
  "geometry": {"coordinates":[-97.15242000000001,49.818027],"type":"Point"}
}