{
  "type": "Feature",
  "properties": {
    "addr:full":"Brampton ON L6W 3P4",
    "addr:postcode":"l6w 3p4",
    "iso:country":"CA",
    "sg:city":"Brampton",
    "sg:classifiers":[
        {
            "category":"Manufacturing",
            "subcategory":"Glass & Minerals",
            "type":"Manufacturing & Wholesale Goods"
        }
    ],
    "sg:phone":"+1 905 874 0798",
    "sg:postcode":"L6W 3P4",
    "sg:province":"ON",
    "sg:tags":[
        "fabricator",
        "fiber"
    ],
    "wof:name":"Fibresteel Corrosion Control",
    "wof:placetype":"venue"
},
  "geometry": {"coordinates":[-79.729713,43.689156],"type":"Point"}
}