{
  "type": "Feature",
  "properties": {
    "addr:full":"Vanscoy SK S0L 3J0",
    "addr:postcode":"s0l 3j0",
    "iso:country":"CA",
    "sg:city":"Vanscoy",
    "sg:classifiers":[
        {
            "category":"Wholesale",
            "subcategory":"Farm Supplies",
            "type":"Manufacturing & Wholesale Goods"
        }
    ],
    "sg:phone":"+1 306 249 9236",
    "sg:postcode":"S0L 3J0",
    "sg:province":"SK",
    "sg:tags":[
        "seed",
        "grain",
        "cleaning"
    ],
    "wof:name":"Prairie Pulse Inc",
    "wof:placetype":"venue"
},
  "geometry": {"coordinates":[-106.971168518,52.0019683838],"type":"Point"}
}