{
  "type": "Feature",
  "properties": {
    "addr:full":"84 Whyte Ave Dryden ON P8N 1Z5",
    "addr:housenumber":"84",
    "addr:postcode":"p8n 1z5",
    "addr:street":"Whyte Ave",
    "iso:country":"CA",
    "sg:address":"84 Whyte Ave",
    "sg:city":"Dryden",
    "sg:classifiers":[
        {
            "category":"Organizations",
            "subcategory":"Professional Association",
            "type":"Services"
        }
    ],
    "sg:phone":"+1 807 223 3642",
    "sg:postcode":"P8N 1Z5",
    "sg:province":"ON",
    "wof:name":"Dryden Minor Hockey Assoc",
    "wof:placetype":"venue"
},
  "geometry": {"coordinates":[-92.83899700000001,49.780727],"type":"Point"}
}