{
  "type": "Feature",
  "properties": {
    "addr:full":"236 Boul Saint-Joseph Hull QC J8Y 3X4",
    "addr:housenumber":"236",
    "addr:postcode":"j8y 3x4",
    "addr:street":"Boul Saint-Joseph",
    "iso:country":"CA",
    "sg:address":"236 Boul Saint-Joseph",
    "sg:city":"Hull",
    "sg:classifiers":[
        {
            "category":"Restaurant",
            "type":"Food & Drink"
        }
    ],
    "sg:phone":"+1 819 777 5699",
    "sg:postcode":"J8Y 3X4",
    "sg:province":"QC",
    "wof:name":"Cafe Blanka",
    "wof:placetype":"venue"
},
  "geometry": {"coordinates":[-75.732941,45.435699],"type":"Point"}
}