{
  "type": "Feature",
  "properties": {
    "addr:full":"1001 Rue Lenoir Montreal QC H4C 2Z6",
    "addr:housenumber":"1001",
    "addr:postcode":"h4c 2z6",
    "addr:street":"Rue Lenoir",
    "iso:country":"CA",
    "sg:address":"1001 Rue Lenoir",
    "sg:city":"Montreal",
    "sg:classifiers":[
        {
            "category":"Manufacturing",
            "subcategory":"Printing",
            "type":"Manufacturing & Wholesale Goods"
        }
    ],
    "sg:phone":"+1 514 934 5373",
    "sg:postcode":"H4C 2Z6",
    "sg:province":"QC",
    "sg:tags":[
        "printer"
    ],
    "wof:name":"Kellmaire",
    "wof:placetype":"venue"
},
  "geometry": {"coordinates":[-73.5925521851,45.4768371582],"type":"Point"}
}