{
  "type": "Feature",
  "properties": {
    "addr:full":"626 Dufferin Ave Selkirk MB R1A 2J2",
    "addr:housenumber":"626",
    "addr:postcode":"r1a 2j2",
    "addr:street":"Dufferin Ave",
    "iso:country":"CA",
    "sg:address":"626 Dufferin Ave",
    "sg:city":"Selkirk",
    "sg:classifiers":[
        {
            "category":"Taxi",
            "type":"Transportation"
        }
    ],
    "sg:phone":"+1 204 785 2826",
    "sg:postcode":"R1A 2J2",
    "sg:province":"MB",
    "sg:tags":[
        "taxicab"
    ],
    "wof:name":"Kurt's Taxi",
    "wof:placetype":"venue"
},
  "geometry": {"coordinates":[-96.8803100586,50.1512947083],"type":"Point"}
}