{
  "type": "Feature",
  "properties": {
    "addr:full":"7082 Wallace Dr Brentwood Bay BC V8M 1E9",
    "addr:housenumber":"7082",
    "addr:postcode":"v8m 1e9",
    "addr:street":"Wallace Dr",
    "iso:country":"CA",
    "sg:address":"7082 Wallace Dr",
    "sg:city":"Brentwood Bay",
    "sg:classifiers":[
        {
            "category":"Organizations",
            "subcategory":"Professional Association",
            "type":"Services"
        }
    ],
    "sg:phone":"+1 250 652 4834",
    "sg:postcode":"V8M 1E9",
    "sg:province":"BC",
    "sg:tags":[
        "club"
    ],
    "wof:name":"Brentwood Community Club",
    "wof:placetype":"venue"
},
  "geometry": {"coordinates":[-123.44654800000001,48.575031],"type":"Point"}
}