{
  "type": "Feature",
  "properties": {
    "addr:full":"854 1st St E Cornwall ON K6H 1M6",
    "addr:housenumber":"854",
    "addr:postcode":"k6h 1m6",
    "addr:street":"1St St E",
    "iso:country":"CA",
    "sg:address":"854 1st St E",
    "sg:city":"Cornwall",
    "sg:classifiers":[
        {
            "category":"Recreation",
            "type":"Entertainment"
        }
    ],
    "sg:phone":"+1 613 938 6815",
    "sg:postcode":"K6H 1M6",
    "sg:province":"ON",
    "sg:tags":[
        "parlor",
        "billiard"
    ],
    "wof:name":"A & F Billiards",
    "wof:placetype":"venue"
},
  "geometry": {"coordinates":[-74.711128,45.021748],"type":"Point"}
}