{
  "type": "Feature",
  "properties": {
    "iso:country":"CA",
    "sg:city":"Drumheller",
    "sg:classifiers":[
        {
            "category":"Autos & Motor Vehicles",
            "subcategory":"Automobile Sales",
            "type":"Retail Goods"
        }
    ],
    "sg:phone":"+1 403 823 8898",
    "sg:postcode":"T0J 0Y0",
    "sg:province":"AB",
    "sg:tags":[
        "car",
        "dealer"
    ],
    "wof:name":"Drumheller Chrysler Ltd",
    "wof:placetype":"venue"
},
  "geometry": {"coordinates":[-112.706924438,51.4610099792],"type":"Point"}
}