{
  "type": "Feature",
  "properties": {
    "addr:full":"Riverview Beach Rd Pefferlaw ON L0E 1N0",
    "addr:postcode":"l0e 1n0",
    "addr:street":"Riverview Beach Rd",
    "iso:country":"CA",
    "sg:address":"Riverview Beach Rd",
    "sg:city":"Pefferlaw",
    "sg:classifiers":[
        {
            "category":"Recreation",
            "subcategory":"Marina",
            "type":"Entertainment"
        }
    ],
    "sg:phone":"+1 705 437 2373",
    "sg:postcode":"L0E 1N0",
    "sg:province":"ON",
    "wof:name":"Flying Bridge Marina Ltd",
    "wof:placetype":"venue"
},
  "geometry": {"coordinates":[-79.206177,44.336159],"type":"Point"}
}