{
  "type": "Feature",
  "properties": {
    "addr:full":"821 Ch Michel Chertsey QC J0K 3K0",
    "addr:housenumber":"821",
    "addr:postcode":"j0k 3k0",
    "addr:street":"Ch Michel",
    "iso:country":"CA",
    "sg:address":"821 Ch Michel",
    "sg:city":"Chertsey",
    "sg:classifiers":[
        {
            "category":"Building & Trades",
            "subcategory":"Construction",
            "type":"Services"
        }
    ],
    "sg:phone":"+1 450 882 2538",
    "sg:postcode":"J0K 3K0",
    "sg:province":"QC",
    "sg:tags":[
        "contractor"
    ],
    "wof:name":"Yves Rochon Construction",
    "wof:placetype":"venue"
},
  "geometry": {"coordinates":[-73.8834152222,46.1126937866],"type":"Point"}
}