{
  "type": "Feature",
  "properties": {
    "addr:full":"381 Yonge St Toronto ON M5B 1S1",
    "addr:housenumber":"381",
    "addr:postcode":"m5b 1s1",
    "addr:street":"Yonge St",
    "iso:country":"CA",
    "sg:address":"381 Yonge St",
    "sg:city":"Toronto",
    "sg:classifiers":[
        {
            "category":"Social Services",
            "type":"Services"
        }
    ],
    "sg:phone":"+1 416 977 7259",
    "sg:postcode":"M5B 1S1",
    "sg:province":"ON",
    "sg:tags":[
        "organization",
        "welfare"
    ],
    "wof:name":"Yonge Street Mission",
    "wof:placetype":"venue"
},
  "geometry": {"coordinates":[-79.38185882569999,43.6587905884],"type":"Point"}
}