{
  "type": "Feature",
  "properties": {
    "addr:full":"34 Deyncourt St Lakefield ON K0L 2H0",
    "addr:housenumber":"34",
    "addr:postcode":"k0l 2h0",
    "addr:street":"Deyncourt St",
    "iso:country":"CA",
    "sg:address":"34 Deyncourt St",
    "sg:city":"Lakefield",
    "sg:classifiers":[
        {
            "category":"Manufacturing",
            "subcategory":"Building Materials",
            "type":"Manufacturing & Wholesale Goods"
        }
    ],
    "sg:phone":"+1 705 652 3361",
    "sg:postcode":"K0L 2H0",
    "sg:province":"ON",
    "sg:tags":[
        "truss"
    ],
    "wof:name":"Kingdon Truss",
    "wof:placetype":"venue"
},
  "geometry": {"coordinates":[-78.2766571045,44.4248733521],"type":"Point"}
}