{
  "type": "Feature",
  "properties": {
    "addr:full":"70 Summerlea Rd Brampton ON L6T 4X3",
    "addr:housenumber":"70",
    "addr:postcode":"l6t 4x3",
    "addr:street":"Summerlea Rd",
    "iso:country":"CA",
    "sg:address":"70 Summerlea Rd",
    "sg:city":"Brampton",
    "sg:classifiers":[
        {
            "category":"Professional",
            "subcategory":"Art Services",
            "type":"Services"
        }
    ],
    "sg:phone":"+1 905 799 2225",
    "sg:postcode":"L6T 4X3",
    "sg:province":"ON",
    "sg:tags":[
        "graphic",
        "printer",
        "designer"
    ],
    "wof:name":"Pine Valley Graphics",
    "wof:placetype":"venue"
},
  "geometry": {"coordinates":[-79.683784,43.722618],"type":"Point"}
}