{
  "type": "Feature",
  "properties": {
    "addr:full":"6348 Lundy's Lane Niagara Falls ON L2G 1T6",
    "addr:housenumber":"6348",
    "addr:postcode":"l2g 1t6",
    "addr:street":"Lundy'S Lane",
    "iso:country":"CA",
    "sg:address":"6348 Lundy's Lane",
    "sg:city":"Niagara Falls",
    "sg:classifiers":[
        {
            "category":"Restaurant",
            "type":"Food & Drink"
        }
    ],
    "sg:phone":"+1 905 356 4048",
    "sg:postcode":"L2G 1T6",
    "sg:province":"ON",
    "wof:name":"Pizza Hut",
    "wof:placetype":"venue"
},
  "geometry": {"coordinates":[-77.56536865229999,45.0424156189],"type":"Point"}
}