{
  "type": "Feature",
  "properties": {
    "iso:country":"CA",
    "sg:city":"Lac Du Bonnet",
    "sg:classifiers":[
        {
            "category":"Autos & Motor Vehicles",
            "subcategory":"Auto Supplies",
            "type":"Retail Goods"
        }
    ],
    "sg:phone":"+1 204 345 8666",
    "sg:postcode":"R0E 1A0",
    "sg:province":"MB",
    "sg:tags":[
        "automobile",
        "parts"
    ],
    "wof:name":"Relay Auto & Farm Supplies Ltd",
    "wof:placetype":"venue"
},
  "geometry": {"coordinates":[-96.0619430542,50.250541687],"type":"Point"}
}