{
  "type": "Feature",
  "properties": {
    "iso:country":"CA",
    "sg:address":"723 Lawrence Ave W",
    "sg:city":"North York",
    "sg:classifiers":[
        {
            "category":"Professional",
            "subcategory":"Lawyer & Legal Services",
            "type":"Services"
        }
    ],
    "sg:phone":"+1 416 785 8135",
    "sg:postcode":"M6A 1B4",
    "sg:province":"ON",
    "sg:tags":[
        "attorney"
    ],
    "wof:name":"Di Gregorio & Assoc",
    "wof:placetype":"venue"
},
  "geometry": {"coordinates":[-79.4488143921,43.7149963379],"type":"Point"}
}