{
  "type": "Feature",
  "properties": {
    "addr:full":"15 Church St N St Marys ON N4X 1B4",
    "addr:housenumber":"15",
    "addr:postcode":"n4x 1b4",
    "addr:street":"Church St N",
    "iso:country":"CA",
    "sg:address":"15 Church St N",
    "sg:city":"St Marys",
    "sg:classifiers":[
        {
            "category":"Education",
            "subcategory":"Library",
            "type":"Public Place"
        }
    ],
    "sg:phone":"+1 519 284 3346",
    "sg:postcode":"N4X 1B4",
    "sg:province":"ON",
    "wof:name":"St Marys Public Library",
    "wof:placetype":"venue"
},
  "geometry": {"coordinates":[-81.14068603520001,43.2602882385],"type":"Point"}
}