{
  "type": "Feature",
  "properties": {
    "addr:full":"86 Doe Lake Rd Katrine ON P0A 1L0",
    "addr:housenumber":"86",
    "addr:postcode":"p0a 1l0",
    "addr:street":"Doe Lake Rd",
    "iso:country":"CA",
    "sg:address":"86 Doe Lake Rd",
    "sg:city":"Katrine",
    "sg:classifiers":[
        {
            "category":"Recreation",
            "subcategory":"Marina",
            "type":"Entertainment"
        }
    ],
    "sg:phone":"+1 705 382 3806",
    "sg:postcode":"P0A 1L0",
    "sg:province":"ON",
    "wof:name":"Katrine Marine",
    "wof:placetype":"venue"
},
  "geometry": {"coordinates":[-79.35251599999999,45.573498],"type":"Point"}
}