{
  "type": "Feature",
  "properties": {
    "addr:full":"1310 Ch Saint-Louis Saint-Lazare QC J7T 2A2",
    "addr:housenumber":"1310",
    "addr:postcode":"j7t 2a2",
    "addr:street":"Ch Saint-Louis",
    "iso:country":"CA",
    "sg:address":"1310 Ch Saint-Louis",
    "sg:city":"Saint-Lazare",
    "sg:classifiers":[
        {
            "category":"Building & Trades",
            "subcategory":"Electrical",
            "type":"Services"
        }
    ],
    "sg:phone":"+1 450 455 9951",
    "sg:postcode":"J7T 2A2",
    "sg:province":"QC",
    "sg:tags":[
        "electric",
        "contractor"
    ],
    "wof:name":"Raymond Therrien Electrique",
    "wof:placetype":"venue"
},
  "geometry": {"coordinates":[-74.0966339111,45.3886413574],"type":"Point"}
}