{
  "type": "Feature",
  "properties": {
    "addr:full":"Richmond BC V6X 3M4",
    "addr:postcode":"v6x 3m4",
    "iso:country":"CA",
    "sg:city":"Richmond",
    "sg:classifiers":[
        {
            "category":"Professional",
            "subcategory":"Testing Lab",
            "type":"Services"
        }
    ],
    "sg:phone":"+1 604 270 1844",
    "sg:postcode":"V6X 3M4",
    "sg:province":"BC",
    "sg:tags":[
        "measuring",
        "air",
        "pollution"
    ],
    "wof:name":"Bbc Indoor Air Quality Ltd",
    "wof:placetype":"venue"
},
  "geometry": {"coordinates":[-123.103027344,49.1794166565],"type":"Point"}
}