{
  "type": "Feature",
  "properties": {
    "addr:full":"94 Wentzell Rd Bridgewater NS B4V 3V4",
    "addr:housenumber":"94",
    "addr:postcode":"b4v 3v4",
    "addr:street":"Wentzell Rd",
    "iso:country":"CA",
    "sg:address":"94 Wentzell Rd",
    "sg:city":"Bridgewater",
    "sg:classifiers":[
        {
            "category":"Manufacturing",
            "subcategory":"Tools & Machinery",
            "type":"Manufacturing & Wholesale Goods"
        }
    ],
    "sg:phone":"+1 902 543 9966",
    "sg:postcode":"B4V 3V4",
    "sg:province":"NS",
    "sg:tags":[
        "machine",
        "shop"
    ],
    "wof:name":"L & B Electric Ltd",
    "wof:placetype":"venue"
},
  "geometry": {"coordinates":[-64.5369262695,44.3870811462],"type":"Point"}
}