{
  "type": "Feature",
  "properties": {
    "addr:full":"6666 Av Papineau Montreal QC H2G 2X2",
    "addr:housenumber":"6666",
    "addr:postcode":"h2g 2x2",
    "addr:street":"Av Papineau",
    "iso:country":"CA",
    "sg:address":"6666 Av Papineau",
    "sg:city":"Montreal",
    "sg:classifiers":[
        {
            "category":"Retail",
            "subcategory":"Repair Shop",
            "type":"Services"
        }
    ],
    "sg:phone":"+1 514 727 7171",
    "sg:postcode":"H2G 2X2",
    "sg:province":"QC",
    "sg:tags":[
        "sharpening"
    ],
    "wof:name":"Aiguiserie",
    "wof:placetype":"venue"
},
  "geometry": {"coordinates":[-73.599396,45.544277],"type":"Point"}
}