{
  "type": "Feature",
  "properties": {
    "addr:full":"1435 Rte Transcanadienne Grand-Remous QC J0W 1E0",
    "addr:housenumber":"1435",
    "addr:postcode":"j0w 1e0",
    "addr:street":"Rte Transcanadienne",
    "iso:country":"CA",
    "sg:address":"1435 Rte Transcanadienne",
    "sg:city":"Grand-Remous",
    "sg:classifiers":[
        {
            "category":"Food & Beverages",
            "subcategory":"Groceries & Convenience Stores",
            "type":"Retail Goods"
        }
    ],
    "sg:phone":"+1 819 438 2880",
    "sg:postcode":"J0W 1E0",
    "sg:province":"QC",
    "sg:tags":[
        "grocer"
    ],
    "wof:name":"J B Levesque Inc",
    "wof:placetype":"venue"
},
  "geometry": {"coordinates":[-75.904258728,46.6123466492],"type":"Point"}
}