{
  "type": "Feature",
  "properties": {
    "addr:full":"Salmon Arm BC V1E 4N2",
    "addr:postcode":"v1e 4n2",
    "iso:country":"CA",
    "sg:city":"Salmon Arm",
    "sg:classifiers":[
        {
            "category":"Retail",
            "subcategory":"Auto Repair",
            "type":"Services"
        }
    ],
    "sg:phone":"+1 250 832 7543",
    "sg:postcode":"V1E 4N2",
    "sg:province":"BC",
    "sg:tags":[
        "repairing",
        "automobile"
    ],
    "wof:name":"Eric's Shuswap Automotive",
    "wof:placetype":"venue"
},
  "geometry": {"coordinates":[-119.32496643099999,50.7496261597],"type":"Point"}
}