{
  "type": "Feature",
  "properties": {
    "iso:country":"CA",
    "sg:address":"169 Sparks St",
    "sg:city":"Ottawa",
    "sg:classifiers":[
        {
            "category":"Restaurant",
            "type":"Food & Drink"
        }
    ],
    "sg:phone":"+1 613 230 8327",
    "sg:postcode":"K1P 5B9",
    "sg:province":"ON",
    "wof:name":"Ashtar Restaurant",
    "wof:placetype":"venue"
},
  "geometry": {"coordinates":[-75.6998062134,45.4219894409],"type":"Point"}
}