{
  "type": "Feature",
  "properties": {
    "addr:full":"1219 Main St Canora SK S0A 0L0",
    "addr:housenumber":"1219",
    "addr:postcode":"s0a 0l0",
    "addr:street":"Main St",
    "iso:country":"CA",
    "sg:address":"1219 Main St",
    "sg:city":"Canora",
    "sg:classifiers":[
        {
            "category":"Health Services",
            "subcategory":"Hospital",
            "type":"Services"
        }
    ],
    "sg:phone":"+1 306 563 5621",
    "sg:postcode":"S0A 0L0",
    "sg:province":"SK",
    "wof:name":"Canora Hospital",
    "wof:placetype":"venue"
},
  "geometry": {"coordinates":[-102.43960571300001,51.6287193298],"type":"Point"}
}