{
  "type": "Feature",
  "properties": {
    "addr:full":"9 Church Rd Rainbow Lake AB T0H 2Y0",
    "addr:housenumber":"9",
    "addr:postcode":"t0h 2y0",
    "addr:street":"Church Rd",
    "iso:country":"CA",
    "sg:address":"9 Church Rd",
    "sg:city":"Rainbow Lake",
    "sg:classifiers":[
        {
            "category":"Organizations",
            "subcategory":"Religious Organization",
            "type":"Services"
        }
    ],
    "sg:phone":"+1 780 956 3118",
    "sg:postcode":"T0H 2Y0",
    "sg:province":"AB",
    "sg:tags":[
        "church"
    ],
    "wof:name":"St Peter & St Paul Catholic",
    "wof:placetype":"venue"
},
  "geometry": {"coordinates":[-119.410248,58.499573],"type":"Point"}
}