{
  "type": "Feature",
  "properties": {
    "iso:country":"CA",
    "sg:address":"242 Pender St E",
    "sg:city":"Vancouver",
    "sg:classifiers":[
        {
            "category":"Food & Beverages",
            "subcategory":"Groceries & Convenience Stores",
            "type":"Retail Goods"
        }
    ],
    "sg:phone":"+1 604 681 2286",
    "sg:postcode":"V6A 1T7",
    "sg:province":"BC",
    "sg:tags":[
        "grocer"
    ],
    "wof:name":"Yue Wah Canada Ltd",
    "wof:placetype":"venue"
},
  "geometry": {"coordinates":[-123.098625183,49.2801971436],"type":"Point"}
}