{
  "type": "Feature",
  "properties": {
    "addr:full":"128 Morrison Rd Longview AB T0L 1H0",
    "addr:housenumber":"128",
    "addr:postcode":"t0l 1h0",
    "addr:street":"Morrison Rd",
    "iso:country":"CA",
    "sg:address":"128 Morrison Rd",
    "sg:city":"Longview",
    "sg:classifiers":[
        {
            "category":"Government",
            "subcategory":"Office",
            "type":"Public Place"
        }
    ],
    "sg:phone":"+1 403 558 3922",
    "sg:postcode":"T0L 1H0",
    "sg:province":"AB",
    "sg:tags":[
        "municipality"
    ],
    "wof:name":"Village of Longview",
    "wof:placetype":"venue"
},
  "geometry": {"coordinates":[-114.23097199999999,50.531216],"type":"Point"}
}