{
  "type": "Feature",
  "properties": {
    "addr:full":"Saskatoon SK S7K 1X5",
    "addr:postcode":"s7k 1x5",
    "iso:country":"CA",
    "sg:city":"Saskatoon",
    "sg:classifiers":[
        {
            "category":"Shopping",
            "subcategory":"Used Merchandise",
            "type":"Retail Goods"
        }
    ],
    "sg:phone":"+1 306 242 8002",
    "sg:postcode":"S7K 1X5",
    "sg:province":"SK",
    "sg:tags":[
        "clothing"
    ],
    "wof:name":"Ywca Opportunity Shop",
    "wof:placetype":"venue"
},
  "geometry": {"coordinates":[-106.662498474,52.1358261108],"type":"Point"}
}