{
  "type": "Feature",
  "properties": {
    "addr:full":"808 Abbey Rd Kincardine ON N2Z 1P6",
    "addr:housenumber":"808",
    "addr:postcode":"n2z 1p6",
    "addr:street":"Abbey Rd",
    "iso:country":"CA",
    "sg:address":"808 Abbey Rd",
    "sg:city":"Kincardine",
    "sg:classifiers":[
        {
            "category":"Building & Trades",
            "subcategory":"Cleaning & Sanitation",
            "type":"Services"
        }
    ],
    "sg:phone":"+1 519 396 4745",
    "sg:postcode":"N2Z 1P6",
    "sg:province":"ON",
    "sg:tags":[
        "janitor"
    ],
    "wof:name":"Jack's Superior Maintenance",
    "wof:placetype":"venue"
},
  "geometry": {"coordinates":[-81.613159,44.218578],"type":"Point"}
}