{
  "type": "Feature",
  "properties": {
    "addr:full":"132 Rue Verret Loretteville QC G2B 1G8",
    "addr:housenumber":"132",
    "addr:postcode":"g2b 1g8",
    "addr:street":"Rue Verret",
    "iso:country":"CA",
    "sg:address":"132 Rue Verret",
    "sg:city":"Loretteville",
    "sg:classifiers":[
        {
            "category":"Retail",
            "subcategory":"Auto Repair",
            "type":"Services"
        }
    ],
    "sg:phone":"+1 418 847 9823",
    "sg:postcode":"G2B 1G8",
    "sg:province":"QC",
    "sg:tags":[
        "repairing",
        "automobile"
    ],
    "wof:name":"Centre Mecanique Fb",
    "wof:placetype":"venue"
},
  "geometry": {"coordinates":[-71.36990400000001,46.847401],"type":"Point"}
}