{
  "type": "Feature",
  "properties": {
    "addr:full":"253 Hammond St Shelburne NS B0T 1W0",
    "addr:housenumber":"253",
    "addr:postcode":"b0t 1w0",
    "addr:street":"Hammond St",
    "iso:country":"CA",
    "sg:address":"253 Hammond St",
    "sg:city":"Shelburne",
    "sg:classifiers":[
        {
            "category":"Personal",
            "subcategory":"Beauty Salon",
            "type":"Services"
        }
    ],
    "sg:phone":"+1 902 875 4720",
    "sg:postcode":"B0T 1W0",
    "sg:province":"NS",
    "wof:name":"Unisex Style Ctr",
    "wof:placetype":"venue"
},
  "geometry": {"coordinates":[-65.31564331049999,43.7656593323],"type":"Point"}
}