{
  "type": "Feature",
  "properties": {
    "addr:full":"460 117 Rte Val-D'Or QC J9P 7C3",
    "addr:housenumber":"460 117",
    "addr:postcode":"j9p 7c3",
    "addr:street":"Rte",
    "iso:country":"CA",
    "sg:address":"460 117 Rte",
    "sg:city":"Val-D'Or",
    "sg:classifiers":[
        {
            "category":"Restaurant",
            "type":"Food & Drink"
        }
    ],
    "sg:phone":"+1 819 736 3541",
    "sg:postcode":"J9P 7C3",
    "sg:province":"QC",
    "wof:name":"L'Oree Des Bois",
    "wof:placetype":"venue"
},
  "geometry": {"coordinates":[-71.0033187866,45.3835067749],"type":"Point"}
}