{
  "type": "Feature",
  "properties": {
    "iso:country":"CA",
    "sg:city":"Kelowna",
    "sg:classifiers":[
        {
            "category":"Wholesale",
            "subcategory":"Construction Materials",
            "type":"Manufacturing & Wholesale Goods"
        }
    ],
    "sg:phone":"+1 250 491 1772",
    "sg:postcode":"V1X 6N6",
    "sg:province":"BC",
    "sg:tags":[
        "building"
    ],
    "wof:name":"E Roko Distributors Ltd",
    "wof:placetype":"venue"
},
  "geometry": {"coordinates":[-119.384155273,49.9200515747],"type":"Point"}
}