{
  "type": "Feature",
  "properties": {
    "addr:full":"350 MT Nebo Rd Omemee ON K0L 2W0",
    "addr:housenumber":"350",
    "addr:postcode":"k0l 2w0",
    "addr:street":"Mt Nebo Rd",
    "iso:country":"CA",
    "sg:address":"350 MT Nebo Rd",
    "sg:city":"Omemee",
    "sg:classifiers":[
        {
            "category":"Retail",
            "subcategory":"Animal Services",
            "type":"Services"
        }
    ],
    "sg:phone":"+1 705 799 1514",
    "sg:postcode":"K0L 2W0",
    "sg:province":"ON",
    "sg:tags":[
        "pet",
        "grooming",
        "washing"
    ],
    "wof:name":"Bowser's Nook",
    "wof:placetype":"venue"
},
  "geometry": {"coordinates":[-78.54805755620001,44.2909469604],"type":"Point"}
}