{
  "type": "Feature",
  "properties": {
    "addr:full":"744 Line 11 N Hawkestone ON L0L 1T0",
    "addr:housenumber":"744",
    "addr:postcode":"l0l 1t0",
    "addr:street":"Line 11 N",
    "iso:country":"CA",
    "sg:address":"744 Line 11 N",
    "sg:city":"Hawkestone",
    "sg:classifiers":[
        {
            "category":"Education",
            "subcategory":"School",
            "type":"Public Place"
        }
    ],
    "sg:phone":"+1 705 487 2047",
    "sg:postcode":"L0L 1T0",
    "sg:province":"ON",
    "wof:name":"East Oro School",
    "wof:placetype":"venue"
},
  "geometry": {"coordinates":[-79.4937667847,44.5273513794],"type":"Point"}
}