{
  "type": "Feature",
  "properties": {
    "addr:full":"7886 Yonge St Innisfil ON L9S 1L4",
    "addr:housenumber":"7886",
    "addr:postcode":"l9s 1l4",
    "addr:street":"Yonge St",
    "iso:country":"CA",
    "sg:address":"7886 Yonge St",
    "sg:city":"Innisfil",
    "sg:classifiers":[
        {
            "category":"Real Estate",
            "subcategory":"Real Estate Agent",
            "type":"Services"
        }
    ],
    "sg:phone":"+1 705 436 5111",
    "sg:postcode":"L9S 1L4",
    "sg:province":"ON",
    "wof:name":"Homelife Kempenfelt Kelly Rlty",
    "wof:placetype":"venue"
},
  "geometry": {"coordinates":[-79.616196,44.312691],"type":"Point"}
}