{
  "type": "Feature",
  "properties": {
    "addr:full":"214 St Clair St Chatham ON N7L 3J7",
    "addr:housenumber":"214",
    "addr:postcode":"n7l 3j7",
    "addr:street":"St Clair St",
    "iso:country":"CA",
    "sg:address":"214 St Clair St",
    "sg:city":"Chatham",
    "sg:classifiers":[
        {
            "category":"Health Services",
            "subcategory":"Medical Lab",
            "type":"Services"
        }
    ],
    "sg:phone":"+1 519 354 0853",
    "sg:postcode":"N7L 3J7",
    "sg:province":"ON",
    "wof:name":"A Jedlinski Denture Clinic",
    "wof:placetype":"venue"
},
  "geometry": {"coordinates":[-82.19508399999999,42.410889],"type":"Point"}
}