{
  "type": "Feature",
  "properties": {
    "addr:full":"1100 Rue DE Port-Royal E Montreal QC H2C 2B4",
    "addr:housenumber":"1100",
    "addr:postcode":"h2c 2b4",
    "addr:street":"Rue De Port-Royal E",
    "iso:country":"CA",
    "sg:address":"1100 Rue DE Port-Royal E",
    "sg:city":"Montreal",
    "sg:classifiers":[
        {
            "category":"Manufacturing",
            "subcategory":"Apparel",
            "type":"Manufacturing & Wholesale Goods"
        }
    ],
    "sg:phone":"+1 514 384 8290",
    "sg:postcode":"H2C 2B4",
    "sg:province":"QC",
    "sg:tags":[
        "textile",
        "interior",
        "manufacturer"
    ],
    "wof:name":"Commonwealth Home Fashions",
    "wof:placetype":"venue"
},
  "geometry": {"coordinates":[-73.650818,45.556305],"type":"Point"}
}