{
  "type": "Feature",
  "properties": {
    "addr:full":"2212 343 Rte L'Assomption QC J5W 4R5",
    "addr:housenumber":"2212",
    "addr:postcode":"j5w 4r5",
    "addr:street":"343 Rte",
    "iso:country":"CA",
    "sg:address":"2212 343 Rte",
    "sg:city":"L'Assomption",
    "sg:classifiers":[
        {
            "category":"Home & Garden",
            "subcategory":"Carpets & Floor Coverings",
            "type":"Retail Goods"
        }
    ],
    "sg:phone":"+1 450 588 6997",
    "sg:postcode":"J5W 4R5",
    "sg:province":"QC",
    "sg:tags":[
        "material"
    ],
    "wof:name":"Bois DE Parquet Vaucluse Inc",
    "wof:placetype":"venue"
},
  "geometry": {"coordinates":[-73.43860599999999,45.876045],"type":"Point"}
}