{
  "type": "Feature",
  "properties": {
    "addr:full":"1506 9 St SW Calgary AB T2R 1H8",
    "addr:housenumber":"1506 9",
    "addr:postcode":"t2r 1h8",
    "addr:street":"St Sw",
    "iso:country":"CA",
    "sg:address":"1506 9 St SW",
    "sg:city":"Calgary",
    "sg:classifiers":[
        {
            "category":"Social Services",
            "subcategory":"Adult Care",
            "type":"Services"
        }
    ],
    "sg:phone":"+1 403 244 1634",
    "sg:postcode":"T2R 1H8",
    "sg:province":"AB",
    "sg:tags":[
        "senior",
        "housing",
        "citizen"
    ],
    "wof:name":"Grace Manor",
    "wof:placetype":"venue"
},
  "geometry": {"coordinates":[-114.083984375,51.0389976501],"type":"Point"}
}