{
  "type": "Feature",
  "properties": {
    "addr:full":"62 Walton St Port Hope ON L1A 1N1",
    "addr:housenumber":"62",
    "addr:postcode":"l1a 1n1",
    "addr:street":"Walton St",
    "iso:country":"CA",
    "sg:address":"62 Walton St",
    "sg:city":"Port Hope",
    "sg:classifiers":[
        {
            "category":"Shopping",
            "subcategory":"Florist",
            "type":"Retail Goods"
        }
    ],
    "sg:phone":"+1 905 885 7439",
    "sg:postcode":"L1A 1N1",
    "sg:province":"ON",
    "wof:name":"Holton Flowers",
    "wof:placetype":"venue"
},
  "geometry": {"coordinates":[-78.293823,43.951599],"type":"Point"}
}