{
  "type": "Feature",
  "properties": {
    "addr:full":"418 Blackthorn Ave York ON M6M 3C3",
    "addr:housenumber":"418",
    "addr:postcode":"m6m 3c3",
    "addr:street":"Blackthorn Ave",
    "iso:country":"CA",
    "sg:address":"418 Blackthorn Ave",
    "sg:city":"York",
    "sg:classifiers":[
        {
            "category":"Retail",
            "subcategory":"Repair Shop",
            "type":"Services"
        }
    ],
    "sg:phone":"+1 416 651 4453",
    "sg:postcode":"M6M 3C3",
    "sg:province":"ON",
    "sg:tags":[
        "appliance"
    ],
    "wof:name":"Carby Heating & Air Cond",
    "wof:placetype":"venue"
},
  "geometry": {"coordinates":[-79.4632492065,43.6864471436],"type":"Point"}
}