{
  "type": "Feature",
  "properties": {
    "addr:full":"355 Durham St W Mount Forest ON N0G 2L1",
    "addr:housenumber":"355",
    "addr:postcode":"n0g 2l1",
    "addr:street":"Durham St W",
    "iso:country":"CA",
    "sg:address":"355 Durham St W",
    "sg:city":"Mount Forest",
    "sg:classifiers":[
        {
            "category":"Education",
            "subcategory":"School",
            "type":"Public Place"
        }
    ],
    "sg:phone":"+1 519 323 1660",
    "sg:postcode":"N0G 2L1",
    "sg:province":"ON",
    "wof:name":"Mount Forest District High",
    "wof:placetype":"venue"
},
  "geometry": {"coordinates":[-80.7422409058,43.9819221497],"type":"Point"}
}