{
  "type": "Feature",
  "properties": {
    "addr:full":"48 East 9th St Hamilton ON L9A 3M7",
    "addr:housenumber":"48",
    "addr:postcode":"l9a 3m7",
    "addr:street":"East 9Th St",
    "iso:country":"CA",
    "sg:address":"48 East 9th St",
    "sg:city":"Hamilton",
    "sg:classifiers":[
        {
            "category":"Building & Trades",
            "subcategory":"Construction",
            "type":"Services"
        }
    ],
    "sg:phone":"+1 905 574 7792",
    "sg:postcode":"L9A 3M7",
    "sg:province":"ON",
    "sg:tags":[
        "home",
        "improvement"
    ],
    "wof:name":"B James Home Improvements",
    "wof:placetype":"venue"
},
  "geometry": {"coordinates":[-79.86835499999999,43.238113],"type":"Point"}
}