{
  "type": "Feature",
  "properties": {
    "iso:country":"CA",
    "sg:address":"609 Grand Lake Rd",
    "sg:city":"Sydney",
    "sg:classifiers":[
        {
            "category":"Retail",
            "subcategory":"Veterinary Services",
            "type":"Services"
        }
    ],
    "sg:phone":"+1 902 562 5551",
    "sg:postcode":"B1P 5T3",
    "sg:province":"NS",
    "sg:tags":[
        "veterinarian"
    ],
    "wof:name":"Mesher, Madonna DVM",
    "wof:placetype":"venue"
},
  "geometry": {"coordinates":[-60.1285591125,46.153339386],"type":"Point"}
}