{
  "type": "Feature",
  "properties": {
    "addr:full":"Hafford SK S0J 1A0",
    "addr:postcode":"s0j 1a0",
    "addr:street":"Hafford",
    "iso:country":"CA",
    "sg:city":"Hafford",
    "sg:classifiers":[
        {
            "category":"Autos & Motor Vehicles",
            "subcategory":"Fuel & Gas Station",
            "type":"Retail Goods"
        }
    ],
    "sg:phone":"+1 306 549 2205",
    "sg:postcode":"S0J 1A0",
    "sg:province":"SK",
    "sg:tags":[
        "oil"
    ],
    "wof:name":"Hafford Hiway Svc Ltd",
    "wof:placetype":"venue"
},
  "geometry": {"coordinates":[-107.358749,52.72908],"type":"Point"}
}