{
  "type": "Feature",
  "properties": {
    "addr:full":"3079 Princess St Kingston ON K7L 4V2",
    "addr:housenumber":"3079",
    "addr:postcode":"k7l 4v2",
    "addr:street":"Princess St",
    "iso:country":"CA",
    "sg:address":"3079 Princess St",
    "sg:city":"Kingston",
    "sg:classifiers":[
        {
            "category":"Retail",
            "subcategory":"Repair Shop",
            "type":"Services"
        }
    ],
    "sg:phone":"+1 613 389 8020",
    "sg:postcode":"K7L 4V2",
    "sg:province":"ON",
    "sg:tags":[
        "sharpening"
    ],
    "wof:name":"Eddy's Saw & Tool Sharpening",
    "wof:placetype":"venue"
},
  "geometry": {"coordinates":[-76.59767913819999,44.2617073059],"type":"Point"}
}