{
  "type": "Feature",
  "properties": {
    "iso:country":"CA",
    "sg:address":"8 Blais",
    "sg:city":"Embrun",
    "sg:classifiers":[
        {
            "category":"Sports & Exercise",
            "subcategory":"Bowling",
            "type":"Entertainment"
        }
    ],
    "sg:phone":"+1 613 443 3036",
    "sg:postcode":"K0A 1W0",
    "sg:province":"ON",
    "sg:tags":[
        "center"
    ],
    "wof:name":"Salle DE Quilles D'Embrun",
    "wof:placetype":"venue"
},
  "geometry": {"coordinates":[-75.2813339233,45.2749671936],"type":"Point"}
}