{
  "type": "Feature",
  "properties": {
    "addr:full":"511 Bond St W Oshawa ON L1J 2M2",
    "addr:housenumber":"511",
    "addr:postcode":"l1j 2m2",
    "addr:street":"Bond St W",
    "iso:country":"CA",
    "sg:address":"511 Bond St W",
    "sg:city":"Oshawa",
    "sg:classifiers":[
        {
            "category":"Professional",
            "subcategory":"Accounting & Tax Preparation",
            "type":"Services"
        }
    ],
    "sg:phone":"+1 905 576 4619",
    "sg:postcode":"L1J 2M2",
    "sg:province":"ON",
    "sg:tags":[
        "accountant"
    ],
    "wof:name":"Gould, Doug",
    "wof:placetype":"venue"
},
  "geometry": {"coordinates":[-78.882858,43.894009],"type":"Point"}
}