{
  "type": "Feature",
  "properties": {
    "addr:full":"303 Woodvale Road West NW Edmonton AB T6L 3Z7",
    "addr:housenumber":"303",
    "addr:postcode":"t6l 3z7",
    "addr:street":"Woodvale Road West Nw",
    "iso:country":"CA",
    "sg:address":"303 Woodvale Road West NW",
    "sg:city":"Edmonton",
    "sg:classifiers":[
        {
            "category":"Education",
            "subcategory":"Special Training",
            "type":"Public Place"
        }
    ],
    "sg:phone":"+1 780 465 2992",
    "sg:postcode":"T6L 3Z7",
    "sg:province":"AB",
    "sg:tags":[
        "school"
    ],
    "wof:name":"Handicraft Production Ctr",
    "wof:placetype":"venue"
},
  "geometry": {"coordinates":[-113.43150300000001,53.467693],"type":"Point"}
}