{
  "type": "Feature",
  "properties": {
    "addr:full":"122 Crystal Ave W Crystal City MB R0K 0N0",
    "addr:housenumber":"122",
    "addr:postcode":"r0k 0n0",
    "addr:street":"Crystal Ave W",
    "iso:country":"CA",
    "sg:address":"122 Crystal Ave W",
    "sg:city":"Crystal City",
    "sg:classifiers":[
        {
            "category":"Recreation",
            "type":"Entertainment"
        }
    ],
    "sg:phone":"+1 204 873 2316",
    "sg:postcode":"R0K 0N0",
    "sg:province":"MB",
    "sg:tags":[
        "hall",
        "auditorium"
    ],
    "wof:name":"Crystal City Community Hall",
    "wof:placetype":"venue"
},
  "geometry": {"coordinates":[-98.9430007935,49.1477165222],"type":"Point"}
}