{
  "type": "Feature",
  "properties": {
    "addr:full":"207 11th St Nobleford AB T0L 1S0",
    "addr:housenumber":"207",
    "addr:postcode":"t0l 1s0",
    "addr:street":"11Th St",
    "iso:country":"CA",
    "sg:address":"207 11th St",
    "sg:city":"Nobleford",
    "sg:classifiers":[
        {
            "category":"Manufacturing",
            "subcategory":"Tools & Machinery",
            "type":"Manufacturing & Wholesale Goods"
        }
    ],
    "sg:phone":"+1 403 824 3737",
    "sg:postcode":"T0L 1S0",
    "sg:province":"AB",
    "sg:tags":[
        "machine",
        "shop",
        "farm"
    ],
    "wof:name":"Agri-Tech Mfg Ltd",
    "wof:placetype":"venue"
},
  "geometry": {"coordinates":[-113.055618,49.885906],"type":"Point"}
}