{
  "type": "Feature",
  "properties": {
    "addr:full":"671 2E Rue E LA Sarre QC J9Z 3J7",
    "addr:housenumber":"671",
    "addr:postcode":"j9z 3j7",
    "addr:street":"2E Rue E La Sarre",
    "iso:country":"CA",
    "sg:address":"671 2E Rue E",
    "sg:city":"LA Sarre",
    "sg:classifiers":[
        {
            "category":"Health Services",
            "subcategory":"Doctor",
            "type":"Services"
        }
    ],
    "sg:phone":"+1 819 333 4500",
    "sg:postcode":"J9Z 3J7",
    "sg:province":"QC",
    "sg:tags":[
        "clinic",
        "chiropractor"
    ],
    "wof:name":"Clinique Chiropratique",
    "wof:placetype":"venue"
},
  "geometry": {"coordinates":[-79.2004852295,48.8155822754],"type":"Point"}
}