{
  "type": "Feature",
  "properties": {
    "addr:full":"RR 5 Mount Stewart PE C0A 1T0",
    "addr:postcode":"c0a 1t0",
    "addr:street":"Rr 5",
    "iso:country":"CA",
    "sg:address":"RR 5",
    "sg:city":"Mount Stewart",
    "sg:classifiers":[
        {
            "category":"Building & Trades",
            "subcategory":"Construction",
            "type":"Services"
        }
    ],
    "sg:phone":"+1 902 676 2122",
    "sg:postcode":"C0A 1T0",
    "sg:province":"PE",
    "sg:tags":[
        "home",
        "improvement"
    ],
    "wof:name":"Collings Construction",
    "wof:placetype":"venue"
},
  "geometry": {"coordinates":[-62.862743,46.36451],"type":"Point"}
}