{
  "type": "Feature",
  "properties": {
    "addr:full":"22 Rue Des Flandres Gatineau QC J8T 4R7",
    "addr:housenumber":"22",
    "addr:postcode":"j8t 4r7",
    "addr:street":"Rue Des Flandres",
    "iso:country":"CA",
    "sg:address":"22 Rue Des Flandres",
    "sg:city":"Gatineau",
    "sg:classifiers":[
        {
            "category":"Personal",
            "subcategory":"Barber",
            "type":"Services"
        }
    ],
    "sg:phone":"+1 819 561 4120",
    "sg:postcode":"J8T 4R7",
    "sg:province":"QC",
    "wof:name":"Coiffure Pour Hommes Lorraine",
    "wof:placetype":"venue"
},
  "geometry": {"coordinates":[-75.719025,45.470852],"type":"Point"}
}