{
  "type": "Feature",
  "properties": {
    "iso:country":"CA",
    "sg:address":"799 Bloor St W",
    "sg:city":"Toronto",
    "sg:classifiers":[
        {
            "category":"Health Services",
            "subcategory":"Doctor",
            "type":"Services"
        }
    ],
    "sg:phone":"+1 416 531 5332",
    "sg:postcode":"M6G 1L8",
    "sg:province":"ON",
    "sg:tags":[
        "physiotherapist",
        "clinic",
        "surgeon",
        "physician"
    ],
    "wof:name":"Bloor Christie Medical Clinic",
    "wof:placetype":"venue"
},
  "geometry": {"coordinates":[-79.4213027954,43.6627845764],"type":"Point"}
}