{
  "type": "Feature",
  "properties": {
    "iso:country":"CA",
    "sg:address":"8487 Boul Saint-Laurent",
    "sg:city":"Montreal",
    "sg:classifiers":[
        {
            "category":"Building & Trades",
            "subcategory":"Plumbing",
            "type":"Services"
        }
    ],
    "sg:phone":"+1 514 384 3152",
    "sg:postcode":"H2P 2M7",
    "sg:province":"QC",
    "sg:tags":[
        "contractor"
    ],
    "wof:name":"Plomberie Parenti Inc",
    "wof:placetype":"venue"
},
  "geometry": {"coordinates":[-73.636955,45.540779],"type":"Point"}
}