{
  "type": "Feature",
  "properties": {
    "addr:full":"4197 Catherine St Dorchester ON N0L 1G0",
    "addr:housenumber":"4197",
    "addr:postcode":"n0l 1g0",
    "addr:street":"Catherine St",
    "iso:country":"CA",
    "sg:address":"4197 Catherine St",
    "sg:city":"Dorchester",
    "sg:classifiers":[
        {
            "category":"Insurance",
            "subcategory":"Insurance Agent",
            "type":"Services"
        }
    ],
    "sg:phone":"+1 519 268 3731",
    "sg:postcode":"N0L 1G0",
    "sg:province":"ON",
    "wof:name":"Bill Blaney Insurance Brokers",
    "wof:placetype":"venue"
},
  "geometry": {"coordinates":[-81.062721,42.99017],"type":"Point"}
}