{
  "type": "Feature",
  "properties": {
    "addr:full":"6918 118 Ave NW Edmonton AB T5B 4P3",
    "addr:housenumber":"6918",
    "addr:postcode":"t5b 4p3",
    "addr:street":"118 Ave Nw",
    "iso:country":"CA",
    "sg:address":"6918 118 Ave NW",
    "sg:city":"Edmonton",
    "sg:classifiers":[
        {
            "category":"Travel",
            "subcategory":"Hotels & Motels",
            "type":"Entertainment"
        }
    ],
    "sg:phone":"+1 780 471 2610",
    "sg:postcode":"T5B 4P3",
    "sg:province":"AB",
    "wof:name":"Eastglen Motor Inn",
    "wof:placetype":"venue"
},
  "geometry": {"coordinates":[-113.448287964,53.5706367493],"type":"Point"}
}