{
  "type": "Feature",
  "properties": {
    "iso:country":"CA",
    "sg:address":"479 Chilcotin St",
    "sg:city":"Kamloops",
    "sg:classifiers":[
        {
            "category":"Sports & Exercise",
            "subcategory":"Race Track",
            "type":"Entertainment"
        }
    ],
    "sg:phone":"+1 250 374 3882",
    "sg:postcode":"V2H 1G4",
    "sg:province":"BC",
    "wof:name":"Tbc Teletheatres BC Ltd",
    "wof:placetype":"venue"
},
  "geometry": {"coordinates":[-120.32933044400001,50.6904296875],"type":"Point"}
}