{
  "type": "Feature",
  "properties": {
    "iso:country":"CA",
    "sg:city":"Calgary",
    "sg:classifiers":[
        {
            "category":"Wholesale",
            "subcategory":"Groceries",
            "type":"Manufacturing & Wholesale Goods"
        }
    ],
    "sg:phone":"+1 403 262 2566",
    "sg:postcode":"T2P 4J7",
    "sg:province":"AB",
    "sg:tags":[
        "cocoa",
        "chocolate"
    ],
    "wof:name":"Candy Shoppe Lewis Chocolates",
    "wof:placetype":"venue"
},
  "geometry": {"coordinates":[-114.068199,51.045181],"type":"Point"}
}