{
  "type": "Feature",
  "properties": {
    "addr:full":"Montreal QC H3B 3Y1",
    "addr:postcode":"h3b 3y1",
    "iso:country":"CA",
    "sg:city":"Montreal",
    "sg:classifiers":[
        {
            "category":"Shopping",
            "subcategory":"Clothing, Apparel, & Fashions",
            "type":"Retail Goods"
        }
    ],
    "sg:phone":"+1 514 866 9339",
    "sg:postcode":"H3B 3Y1",
    "sg:province":"QC",
    "wof:name":"Joenette Inc",
    "wof:placetype":"venue"
},
  "geometry": {"coordinates":[-73.5679702759,45.5018196106],"type":"Point"}
}