{
  "type": "Feature",
  "properties": {
    "addr:full":"Newbury ON N0L 1Z0",
    "addr:postcode":"n0l 1z0",
    "iso:country":"CA",
    "sg:city":"Newbury",
    "sg:classifiers":[
        {
            "category":"Health Services",
            "subcategory":"Doctor",
            "type":"Services"
        }
    ],
    "sg:phone":"+1 519 693 7058",
    "sg:postcode":"N0L 1Z0",
    "sg:province":"ON",
    "sg:tags":[
        "physician",
        "surgeon"
    ],
    "wof:name":"Sharma, S MD",
    "wof:placetype":"venue"
},
  "geometry": {"coordinates":[-81.80001799999999,42.684792],"type":"Point"}
}