{
  "type": "Feature",
  "properties": {
    "addr:full":"113 3rd St W Eston SK S0L 1A0",
    "addr:housenumber":"113",
    "addr:postcode":"s0l 1a0",
    "addr:street":"3Rd St W Eston",
    "iso:country":"CA",
    "sg:address":"113 3rd St W",
    "sg:city":"Eston",
    "sg:classifiers":[
        {
            "category":"Travel",
            "subcategory":"Hotels & Motels",
            "type":"Entertainment"
        }
    ],
    "sg:phone":"+1 306 962 3639",
    "sg:postcode":"S0L 1A0",
    "sg:province":"SK",
    "wof:name":"Double T Motor Inn",
    "wof:placetype":"venue"
},
  "geometry": {"coordinates":[-108.75975036600001,51.1521263123],"type":"Point"}
}