{
  "type": "Feature",
  "properties": {
    "addr:full":"39 Pottinger St Lindsay ON K9V 3X6",
    "addr:housenumber":"39",
    "addr:postcode":"k9v 3x6",
    "addr:street":"Pottinger St",
    "iso:country":"CA",
    "sg:address":"39 Pottinger St",
    "sg:city":"Lindsay",
    "sg:classifiers":[
        {
            "category":"Health Services",
            "subcategory":"Podiatrist",
            "type":"Services"
        }
    ],
    "sg:phone":"+1 705 324 9715",
    "sg:postcode":"K9V 3X6",
    "sg:province":"ON",
    "wof:name":"Treat Your Feet",
    "wof:placetype":"venue"
},
  "geometry": {"coordinates":[-78.744446,44.363392],"type":"Point"}
}