{
  "type": "Feature",
  "properties": {
    "addr:full":"21 Court St N Thunder Bay ON P7A 4T4",
    "addr:housenumber":"21",
    "addr:postcode":"p7a 4t4",
    "addr:street":"Court St N",
    "iso:country":"CA",
    "sg:address":"21 Court St N",
    "sg:city":"Thunder Bay",
    "sg:classifiers":[
        {
            "category":"Retail",
            "subcategory":"Funeral Services",
            "type":"Services"
        }
    ],
    "sg:phone":"+1 807 345 5351",
    "sg:postcode":"P7A 4T4",
    "sg:province":"ON",
    "sg:tags":[
        "director"
    ],
    "wof:name":"Sargent & Son Ltd Funeral Home",
    "wof:placetype":"venue"
},
  "geometry": {"coordinates":[-89.221062,48.43639],"type":"Point"}
}