{
  "type": "Feature",
  "properties": {
    "iso:country":"CA",
    "sg:address":"150 Redwood Ave W",
    "sg:city":"Thunder Bay",
    "sg:classifiers":[
        {
            "category":"Education",
            "subcategory":"School",
            "type":"Public Place"
        }
    ],
    "sg:phone":"+1 807 577 3823",
    "sg:postcode":"P7C 1Z6",
    "sg:province":"ON",
    "wof:name":"St Vincent School",
    "wof:placetype":"venue"
},
  "geometry": {"coordinates":[-89.2832183838,48.3938827515],"type":"Point"}
}