{
  "type": "Feature",
  "properties": {
    "addr:full":"Barrie ON L4N 1L7",
    "addr:postcode":"l4n 1l7",
    "iso:country":"CA",
    "sg:city":"Barrie",
    "sg:classifiers":[
        {
            "category":"Shopping",
            "subcategory":"Department Store",
            "type":"Retail Goods"
        }
    ],
    "sg:phone":"+1 705 733 9566",
    "sg:postcode":"L4N 1L7",
    "sg:province":"ON",
    "sg:tags":[
        "shop"
    ],
    "wof:name":"Dynamic Deals",
    "wof:placetype":"venue"
},
  "geometry": {"coordinates":[-79.70462000000001,44.388767],"type":"Point"}
}