{
  "type": "Feature",
  "properties": {
    "addr:full":"New Richmond QC G0C 2B0",
    "addr:postcode":"g0c 2b0",
    "iso:country":"CA",
    "sg:city":"New Richmond",
    "sg:classifiers":[
        {
            "category":"Shopping",
            "subcategory":"Pharmacy",
            "type":"Retail Goods"
        }
    ],
    "sg:phone":"+1 418 392 4451",
    "sg:postcode":"G0C 2B0",
    "sg:province":"QC",
    "wof:name":"Jean Coutu",
    "wof:placetype":"venue"
},
  "geometry": {"coordinates":[-65.85498046879999,48.1645965576],"type":"Point"}
}