{
  "type": "Feature",
  "properties": {
    "addr:full":"Spruce Grove AB T7X 2Z8",
    "addr:postcode":"t7x 2z8",
    "iso:country":"CA",
    "sg:city":"Spruce Grove",
    "sg:classifiers":[
        {
            "category":"Health Services",
            "subcategory":"Chiropractor",
            "type":"Services"
        }
    ],
    "sg:phone":"+1 780 962 8883",
    "sg:postcode":"T7X 2Z8",
    "sg:province":"AB",
    "wof:name":"Bamber, Lori DC",
    "wof:placetype":"venue"
},
  "geometry": {"coordinates":[-113.90848541299999,53.5415458679],"type":"Point"}
}