{
  "type": "Feature",
  "properties": {
    "addr:full":"Plamondon AB T0A 2T0",
    "addr:postcode":"t0a 2t0",
    "iso:country":"CA",
    "sg:city":"Plamondon",
    "sg:classifiers":[
        {
            "category":"Food & Beverages",
            "subcategory":"Liquor & Beverages",
            "type":"Retail Goods"
        }
    ],
    "sg:phone":"+1 780 798 3759",
    "sg:postcode":"T0A 2T0",
    "sg:province":"AB",
    "sg:tags":[
        "motel",
        "hotel"
    ],
    "wof:name":"Pelican Hotel",
    "wof:placetype":"venue"
},
  "geometry": {"coordinates":[-112.344482422,54.8477935791],"type":"Point"}
}