{
  "type": "Feature",
  "properties": {
    "iso:country":"CA",
    "sg:address":"10 Waterbridge Lane",
    "sg:city":"Markham",
    "sg:classifiers":[
        {
            "category":"Organizations",
            "subcategory":"Religious Organization",
            "type":"Services"
        }
    ],
    "sg:phone":"+1 905 513 8611",
    "sg:postcode":"L3R 8W9",
    "sg:province":"ON",
    "sg:tags":[
        "church"
    ],
    "wof:name":"Bridal Trail Baptist Church",
    "wof:placetype":"venue"
},
  "geometry": {"coordinates":[-79.304184,43.871304],"type":"Point"}
}