{
  "type": "Feature",
  "properties": {
    "addr:full":"249 Mckellar St Glencoe ON N0L 1M0",
    "addr:housenumber":"249",
    "addr:postcode":"n0l 1m0",
    "addr:street":"Mckellar St",
    "iso:country":"CA",
    "sg:address":"249 Mckellar St",
    "sg:city":"Glencoe",
    "sg:classifiers":[
        {
            "category":"Autos & Motor Vehicles",
            "subcategory":"Auto Supplies",
            "type":"Retail Goods"
        }
    ],
    "sg:phone":"+1 519 287 2222",
    "sg:postcode":"N0L 1M0",
    "sg:province":"ON",
    "sg:tags":[
        "tire"
    ],
    "wof:name":"Glencoe Automotive",
    "wof:placetype":"venue"
},
  "geometry": {"coordinates":[-81.70513916020001,42.7525367737],"type":"Point"}
}