{
  "type": "Feature",
  "properties": {
    "addr:full":"27 Milliken Blvd #D16 Scarborough ON M1V 5H9",
    "addr:housenumber":"27",
    "addr:postcode":"m1v 5h9",
    "addr:street":"Milliken Blvd # D16",
    "iso:country":"CA",
    "sg:address":"27 Milliken Blvd #D16",
    "sg:city":"Scarborough",
    "sg:classifiers":[
        {
            "category":"Manufacturing",
            "subcategory":"Food",
            "type":"Manufacturing & Wholesale Goods"
        }
    ],
    "sg:phone":"+1 416 298 8893",
    "sg:postcode":"M1V 5H9",
    "sg:province":"ON",
    "sg:tags":[
        "product",
        "manufacturer"
    ],
    "wof:name":"Masic Food CO",
    "wof:placetype":"venue"
},
  "geometry": {"coordinates":[-79.2947845459,43.8036422729],"type":"Point"}
}