{
  "type": "Feature",
  "properties": {
    "addr:full":"10508 101 St NW Edmonton AB T5H 2R8",
    "addr:housenumber":"10508",
    "addr:postcode":"t5h 2r8",
    "addr:street":"101 St Nw",
    "iso:country":"CA",
    "sg:address":"10508 101 St NW",
    "sg:city":"Edmonton",
    "sg:classifiers":[
        {
            "category":"Restaurant",
            "type":"Food & Drink"
        }
    ],
    "sg:phone":"+1 780 413 3338",
    "sg:postcode":"T5H 2R8",
    "sg:province":"AB",
    "wof:name":"101 Noodle House",
    "wof:placetype":"venue"
},
  "geometry": {"coordinates":[-113.493812561,53.5480041504],"type":"Point"}
}