{
  "type": "Feature",
  "properties": {
    "addr:full":"125 Crowfoot Way NW Calgary AB T3G 2R2",
    "addr:housenumber":"125",
    "addr:postcode":"t3g 2r2",
    "addr:street":"Crowfoot Way Nw",
    "iso:country":"CA",
    "sg:address":"125 Crowfoot Way NW",
    "sg:city":"Calgary",
    "sg:classifiers":[
        {
            "category":"Autos & Motor Vehicles",
            "subcategory":"Automobile Sales",
            "type":"Retail Goods"
        }
    ],
    "sg:phone":"+1 403 239 6677",
    "sg:postcode":"T3G 2R2",
    "sg:province":"AB",
    "sg:tags":[
        "car",
        "dealer"
    ],
    "wof:name":"Northwest Acura",
    "wof:placetype":"venue"
},
  "geometry": {"coordinates":[-114.206703,51.125282],"type":"Point"}
}