{
  "type": "Feature",
  "properties": {
    "addr:full":"Smiths Falls ON K7A 5K9",
    "addr:postcode":"k7a 5k9",
    "iso:country":"CA",
    "sg:city":"Smiths Falls",
    "sg:classifiers":[
        {
            "category":"Government",
            "subcategory":"Office",
            "type":"Public Place"
        }
    ],
    "sg:phone":"+1 613 283 6837",
    "sg:postcode":"K7A 5K9",
    "sg:province":"ON",
    "sg:tags":[
        "license"
    ],
    "wof:name":"Motor Vehicle Licensing Bureau",
    "wof:placetype":"venue"
},
  "geometry": {"coordinates":[-76.0289840698,44.9063262939],"type":"Point"}
}