{
  "type": "Feature",
  "properties": {
    "iso:country":"CA",
    "sg:city":"Tilbury",
    "sg:classifiers":[
        {
            "category":"Banks & Credit Unions",
            "subcategory":"Bank",
            "type":"Services"
        }
    ],
    "sg:phone":"+1 519 682 2373",
    "sg:postcode":"N0P 2L0",
    "sg:province":"ON",
    "wof:name":"Bank of Montreal",
    "wof:placetype":"venue"
},
  "geometry": {"coordinates":[-82.4323348999,42.2595214844],"type":"Point"}
}