{
  "type": "Feature",
  "properties": {
    "addr:full":"Barrie ON L4N 2N4",
    "addr:postcode":"l4n 2n4",
    "iso:country":"CA",
    "sg:city":"Barrie",
    "sg:classifiers":[
        {
            "category":"Retail",
            "subcategory":"Auto Repair",
            "type":"Services"
        }
    ],
    "sg:phone":"+1 705 728 6712",
    "sg:postcode":"L4N 2N4",
    "sg:province":"ON",
    "sg:tags":[
        "repairing",
        "automobile"
    ],
    "wof:name":"Wardle Harris Auto Svc",
    "wof:placetype":"venue"
},
  "geometry": {"coordinates":[-79.7014160156,44.3722572327],"type":"Point"}
}