{
  "type": "Feature",
  "properties": {
    "addr:full":"54 Parkway Dr Dartmouth NS B2V 1E2",
    "addr:housenumber":"54",
    "addr:postcode":"b2v 1e2",
    "addr:street":"Parkway Dr",
    "iso:country":"CA",
    "sg:address":"54 Parkway Dr",
    "sg:city":"Dartmouth",
    "sg:classifiers":[
        {
            "category":"Retail",
            "subcategory":"Repair Shop",
            "type":"Services"
        }
    ],
    "sg:phone":"+1 902 462 8743",
    "sg:postcode":"B2V 1E2",
    "sg:province":"NS",
    "sg:tags":[
        "refinishing",
        "furniture"
    ],
    "wof:name":"Furniture Doctor",
    "wof:placetype":"venue"
},
  "geometry": {"coordinates":[-63.471264,44.644405],"type":"Point"}
}