{
  "type": "Feature",
  "properties": {
    "addr:full":"236 Rue Notre-Dame E Thetford Mines QC G6G 2S2",
    "addr:housenumber":"236",
    "addr:postcode":"g6g 2s2",
    "addr:street":"Rue Notre-Dame E",
    "iso:country":"CA",
    "sg:address":"236 Rue Notre-Dame E",
    "sg:city":"Thetford Mines",
    "sg:classifiers":[
        {
            "category":"Professional",
            "subcategory":"Computer Services",
            "type":"Services"
        }
    ],
    "sg:phone":"+1 418 338 2740",
    "sg:postcode":"G6G 2S2",
    "sg:province":"QC",
    "sg:tags":[
        "game",
        "video",
        "internet"
    ],
    "wof:name":"Zone Virtuelle",
    "wof:placetype":"venue"
},
  "geometry": {"coordinates":[-71.29669199999999,46.094028],"type":"Point"}
}