{
  "type": "Feature",
  "properties": {
    "addr:full":"1837 1/2 Portage Ave Winnipeg MB R3J 0G7",
    "addr:housenumber":"1837 1 / 2",
    "addr:postcode":"r3j 0g7",
    "addr:street":"Portage Ave",
    "iso:country":"CA",
    "sg:address":"1837 1/2 Portage Ave",
    "sg:city":"Winnipeg",
    "sg:classifiers":[
        {
            "category":"Recreation",
            "type":"Entertainment"
        }
    ],
    "sg:phone":"+1 204 889 2486",
    "sg:postcode":"R3J 0G7",
    "sg:province":"MB",
    "sg:tags":[
        "parlor",
        "billiard"
    ],
    "wof:name":"Classic Cafe & Billiards",
    "wof:placetype":"venue"
},
  "geometry": {"coordinates":[-97.2155380249,49.8788833618],"type":"Point"}
}