{
  "type": "Feature",
  "properties": {
    "addr:full":"1092 Cloverdale Ave Victoria BC V8X 2T9",
    "addr:housenumber":"1092",
    "addr:postcode":"v8x 2t9",
    "addr:street":"Cloverdale Ave",
    "iso:country":"CA",
    "sg:address":"1092 Cloverdale Ave",
    "sg:city":"Victoria",
    "sg:classifiers":[
        {
            "category":"Shopping",
            "subcategory":"Bicycles & Sporting Goods",
            "type":"Retail Goods"
        }
    ],
    "sg:phone":"+1 250 381 1125",
    "sg:postcode":"V8X 2T9",
    "sg:province":"BC",
    "wof:name":"Riders Cycle Ltd",
    "wof:placetype":"venue"
},
  "geometry": {"coordinates":[-123.36451700000001,48.428314],"type":"Point"}
}