{
  "type": "Feature",
  "properties": {
    "addr:full":"34 Southport St Toronto ON M6S 3N3",
    "addr:housenumber":"34",
    "addr:postcode":"m6s 3n3",
    "addr:street":"Southport St",
    "iso:country":"CA",
    "sg:address":"34 Southport St",
    "sg:city":"Toronto",
    "sg:classifiers":[
        {
            "category":"Building & Trades",
            "subcategory":"Equipment Rental",
            "type":"Services"
        }
    ],
    "sg:phone":"+1 416 766 7308",
    "sg:postcode":"M6S 3N3",
    "sg:province":"ON",
    "sg:tags":[
        "leasing"
    ],
    "wof:name":"Target Financial Leasing Corp",
    "wof:placetype":"venue"
},
  "geometry": {"coordinates":[-79.47165679930001,43.6374015808],"type":"Point"}
}