{
  "type": "Feature",
  "properties": {
    "addr:full":"2231 Rue DE L'Hopital Jonquiere QC G7X 9Y4",
    "addr:housenumber":"2231",
    "addr:postcode":"g7x 9y4",
    "addr:street":"Rue De L'Hopital",
    "iso:country":"CA",
    "sg:address":"2231 Rue DE L'Hopital",
    "sg:city":"Jonquiere",
    "sg:classifiers":[
        {
            "category":"Health Services",
            "subcategory":"Doctor",
            "type":"Services"
        }
    ],
    "sg:phone":"+1 418 542 8153",
    "sg:postcode":"G7X 9Y4",
    "sg:province":"QC",
    "sg:tags":[
        "physician",
        "surgeon"
    ],
    "wof:name":"Clinique Medicale Champoux",
    "wof:placetype":"venue"
},
  "geometry": {"coordinates":[-71.2339248657,48.4123268127],"type":"Point"}
}