{
  "type": "Feature",
  "properties": {
    "addr:full":"Shawinigan QC G9N 7C1",
    "addr:postcode":"g9n 7c1",
    "iso:country":"CA",
    "sg:city":"Shawinigan",
    "sg:classifiers":[
        {
            "category":"Shopping",
            "subcategory":"Clothing, Apparel, & Fashions",
            "type":"Retail Goods"
        }
    ],
    "sg:phone":"+1 819 539 4093",
    "sg:postcode":"G9N 7C1",
    "sg:province":"QC",
    "sg:tags":[
        "item",
        "boutique"
    ],
    "wof:name":"Boutique Pentagone Inc",
    "wof:placetype":"venue"
},
  "geometry": {"coordinates":[-72.74050099999999,46.563961],"type":"Point"}
}