{
  "type": "Feature",
  "properties": {
    "addr:full":"Bedford NS B4A 2X9",
    "addr:postcode":"b4a 2x9",
    "iso:country":"CA",
    "sg:city":"Bedford",
    "sg:classifiers":[
        {
            "category":"Shopping",
            "subcategory":"Clothing, Apparel, & Fashions",
            "type":"Retail Goods"
        }
    ],
    "sg:phone":"+1 902 835 3788",
    "sg:postcode":"B4A 2X9",
    "sg:province":"NS",
    "sg:tags":[
        "jean"
    ],
    "wof:name":"Bluenotes",
    "wof:placetype":"venue"
},
  "geometry": {"coordinates":[-63.6547851562,44.7364234924],"type":"Point"}
}