{
  "type": "Feature",
  "properties": {
    "iso:country":"CA",
    "sg:address":"400 Augier Ave",
    "sg:city":"Winnipeg",
    "sg:classifiers":[
        {
            "category":"Recreation",
            "type":"Entertainment"
        }
    ],
    "sg:phone":"+1 204 832 1306",
    "sg:postcode":"R3K 1S4",
    "sg:province":"MB",
    "sg:tags":[
        "course",
        "golf"
    ],
    "wof:name":"Glendale Golf & Country Club",
    "wof:placetype":"venue"
},
  "geometry": {"coordinates":[-97.3209,49.874634],"type":"Point"}
}