{
  "type": "Feature",
  "properties": {
    "addr:full":"110 Stinson St Hamilton ON L8N 1S5",
    "addr:housenumber":"110",
    "addr:postcode":"l8n 1s5",
    "addr:street":"Stinson St",
    "iso:country":"CA",
    "sg:address":"110 Stinson St",
    "sg:city":"Hamilton",
    "sg:classifiers":[
        {
            "category":"Health Services",
            "subcategory":"Nursing And Care Facility",
            "type":"Services"
        }
    ],
    "sg:phone":"+1 905 521 9112",
    "sg:postcode":"L8N 1S5",
    "sg:province":"ON",
    "sg:tags":[
        "home",
        "retirement",
        "community"
    ],
    "wof:name":"Stinson Manor",
    "wof:placetype":"venue"
},
  "geometry": {"coordinates":[-79.85660552980001,43.2483940125],"type":"Point"}
}