{
  "type": "Feature",
  "properties": {
    "addr:full":"Toronto ON M4W 3K3",
    "addr:postcode":"m4w 3k3",
    "iso:country":"CA",
    "sg:city":"Toronto",
    "sg:classifiers":[
        {
            "category":"Wholesale",
            "subcategory":"Groceries",
            "type":"Manufacturing & Wholesale Goods"
        }
    ],
    "sg:phone":"+1 416 967 6000",
    "sg:postcode":"M4W 3K3",
    "sg:province":"ON",
    "sg:tags":[
        "food",
        "broker"
    ],
    "wof:name":"Ronald A Chisholm Ltd",
    "wof:placetype":"venue"
},
  "geometry": {"coordinates":[-79.387428,43.670231],"type":"Point"}
}