{
  "type": "Feature",
  "properties": {
    "addr:full":"Cacouna QC G0L 1G0",
    "addr:postcode":"g0l 1g0",
    "iso:country":"CA",
    "sg:city":"Cacouna",
    "sg:classifiers":[
        {
            "category":"Professional",
            "subcategory":"Employment Agencies",
            "type":"Services"
        }
    ],
    "sg:phone":"+1 418 862 9753",
    "sg:postcode":"G0L 1G0",
    "sg:province":"QC",
    "sg:tags":[
        "contractor"
    ],
    "wof:name":"Terminaux Portuaires DE Quebec",
    "wof:placetype":"venue"
},
  "geometry": {"coordinates":[-69.50769805909999,47.909614563],"type":"Point"}
}