{
  "type": "Feature",
  "properties": {
    "iso:country":"CA",
    "sg:address":"1125 Meadowlands Dr E",
    "sg:city":"Nepean",
    "sg:classifiers":[
        {
            "category":"Food & Beverages",
            "subcategory":"Groceries & Convenience Stores",
            "type":"Retail Goods"
        }
    ],
    "sg:phone":"+1 613 224 5202",
    "sg:postcode":"K2E 6J5",
    "sg:province":"ON",
    "sg:tags":[
        "grocer"
    ],
    "wof:name":"Parkwood Hills Foodland",
    "wof:placetype":"venue"
},
  "geometry": {"coordinates":[-75.7125015259,45.3623428345],"type":"Point"}
}