{
  "type": "Feature",
  "properties": {
    "addr:full":"62 Rue DE LA Gauchetiere O Montreal QC H2Z 1C1",
    "addr:housenumber":"62",
    "addr:postcode":"h2z 1c1",
    "addr:street":"Rue De La Gauchetiere O",
    "iso:country":"CA",
    "sg:address":"62 Rue DE LA Gauchetiere O",
    "sg:city":"Montreal",
    "sg:classifiers":[
        {
            "category":"Shopping",
            "subcategory":"Clothing, Apparel, & Fashions",
            "type":"Retail Goods"
        }
    ],
    "sg:phone":"+1 514 861 3388",
    "sg:postcode":"H2Z 1C1",
    "sg:province":"QC",
    "sg:tags":[
        "item",
        "boutique"
    ],
    "wof:name":"Boutique May",
    "wof:placetype":"venue"
},
  "geometry": {"coordinates":[-73.5592575073,45.5088272095],"type":"Point"}
}