{
  "type": "Feature",
  "properties": {
    "addr:full":"4700 Dufferin St North York ON M3H 5S7",
    "addr:housenumber":"4700",
    "addr:postcode":"m3h 5s7",
    "addr:street":"Dufferin St",
    "iso:country":"CA",
    "sg:address":"4700 Dufferin St",
    "sg:city":"North York",
    "sg:classifiers":[
        {
            "category":"Restaurant",
            "type":"Food & Drink"
        }
    ],
    "sg:phone":"+1 416 663 4555",
    "sg:postcode":"M3H 5S7",
    "sg:province":"ON",
    "sg:tags":[
        "delicatessen"
    ],
    "wof:name":"Gastronom",
    "wof:placetype":"venue"
},
  "geometry": {"coordinates":[-79.468704,43.775455],"type":"Point"}
}