{
  "type": "Feature",
  "properties": {
    "addr:full":"688 Denman St Vancouver BC V6G 2L4",
    "addr:housenumber":"688",
    "addr:postcode":"v6g 2l4",
    "addr:street":"Denman St",
    "iso:country":"CA",
    "sg:address":"688 Denman St",
    "sg:city":"Vancouver",
    "sg:classifiers":[
        {
            "category":"Shopping",
            "type":"Retail Goods"
        }
    ],
    "sg:phone":"+1 604 685 8894",
    "sg:postcode":"V6G 2L4",
    "sg:province":"BC",
    "sg:tags":[
        "art",
        "gallery",
        "dealer"
    ],
    "wof:name":"Devon Gallery",
    "wof:placetype":"venue"
},
  "geometry": {"coordinates":[-123.134178162,49.2922172546],"type":"Point"}
}