{
  "type": "Feature",
  "properties": {
    "iso:country":"CA",
    "sg:address":"70 Mississaga St E",
    "sg:city":"Orillia",
    "sg:classifiers":[
        {
            "category":"Home & Garden",
            "subcategory":"Home Furnishings",
            "type":"Retail Goods"
        }
    ],
    "sg:phone":"+1 705 326 5461",
    "sg:postcode":"L3V 1V5",
    "sg:province":"ON",
    "sg:tags":[
        "utensil",
        "cooking"
    ],
    "wof:name":"Hudson's Kitchen & Homewares",
    "wof:placetype":"venue"
},
  "geometry": {"coordinates":[-79.4181900024,44.6090583801],"type":"Point"}
}