{
  "type": "Feature",
  "properties": {
    "addr:full":"4551 Rue Belanger Montreal QC H1T 1B8",
    "addr:housenumber":"4551",
    "addr:postcode":"h1t 1b8",
    "addr:street":"Rue Belanger",
    "iso:country":"CA",
    "sg:address":"4551 Rue Belanger",
    "sg:city":"Montreal",
    "sg:classifiers":[
        {
            "category":"Restaurant",
            "type":"Food & Drink"
        }
    ],
    "sg:phone":"+1 514 721 0747",
    "sg:postcode":"H1T 1B8",
    "sg:province":"QC",
    "sg:tags":[
        "shop",
        "coffee"
    ],
    "wof:name":"Cafe Portofino",
    "wof:placetype":"venue"
},
  "geometry": {"coordinates":[-73.583298,45.569656],"type":"Point"}
}