{
  "type": "Feature",
  "properties": {
    "addr:full":"390 Rue Langevin Saint-Odilon QC G0S 3A0",
    "addr:housenumber":"390",
    "addr:postcode":"g0s 3a0",
    "addr:street":"Rue Langevin",
    "iso:country":"CA",
    "sg:address":"390 Rue Langevin",
    "sg:city":"Saint-Odilon",
    "sg:classifiers":[
        {
            "category":"Banks & Credit Unions",
            "subcategory":"Bank",
            "type":"Services"
        }
    ],
    "sg:phone":"+1 418 464 2381",
    "sg:postcode":"G0S 3A0",
    "sg:province":"QC",
    "wof:name":"Caisses Desjardins",
    "wof:placetype":"venue"
},
  "geometry": {"coordinates":[-70.676315,46.358009],"type":"Point"}
}