{
  "type": "Feature",
  "properties": {
    "addr:full":"533 Rue Belanger Montreal QC H2S 1G5",
    "addr:housenumber":"533",
    "addr:postcode":"h2s 1g5",
    "addr:street":"Rue Belanger",
    "iso:country":"CA",
    "sg:address":"533 Rue Belanger",
    "sg:city":"Montreal",
    "sg:classifiers":[
        {
            "category":"Freight",
            "type":"Transportation"
        }
    ],
    "sg:phone":"+1 514 278 6185",
    "sg:postcode":"H2S 1G5",
    "sg:province":"QC",
    "sg:tags":[
        "courier"
    ],
    "wof:name":"Geant Courrier Canada Inc",
    "wof:placetype":"venue"
},
  "geometry": {"coordinates":[-73.6111373901,45.5382423401],"type":"Point"}
}