{
  "type": "Feature",
  "properties": {
    "iso:country":"CA",
    "sg:address":"1082 Place Verner",
    "sg:city":"Laval",
    "sg:classifiers":[
        {
            "category":"Home & Garden",
            "subcategory":"Furniture",
            "type":"Retail Goods"
        }
    ],
    "sg:phone":"+1 450 664 0999",
    "sg:postcode":"H7E 4P2",
    "sg:province":"QC",
    "sg:tags":[
        "equipment",
        "kitchen",
        "cabinet"
    ],
    "wof:name":"A D Prodesign",
    "wof:placetype":"venue"
},
  "geometry": {"coordinates":[-73.64014434809999,45.6340065002],"type":"Point"}
}