{
  "type": "Feature",
  "properties": {
    "iso:country":"CA",
    "sg:address":"3855 Rue Isabelle",
    "sg:city":"Brossard",
    "sg:classifiers":[
        {
            "category":"Home & Garden",
            "subcategory":"Building Materials",
            "type":"Retail Goods"
        }
    ],
    "sg:phone":"+1 450 444 8726",
    "sg:postcode":"J4Y 2R2",
    "sg:province":"QC",
    "sg:tags":[
        "mixed",
        "concrete"
    ],
    "wof:name":"Lafarge Canada Inc",
    "wof:placetype":"venue"
},
  "geometry": {"coordinates":[-73.467124939,45.4273681641],"type":"Point"}
}