{
  "type": "Feature",
  "properties": {
    "addr:full":"70 Colonnade Rd Nepean ON K2E 7L2",
    "addr:housenumber":"70",
    "addr:postcode":"k2e 7l2",
    "addr:street":"Colonnade Rd",
    "iso:country":"CA",
    "sg:address":"70 Colonnade Rd",
    "sg:city":"Nepean",
    "sg:classifiers":[
        {
            "category":"Professional",
            "subcategory":"Engineering",
            "type":"Services"
        }
    ],
    "sg:phone":"+1 613 727 3880",
    "sg:postcode":"K2E 7L2",
    "sg:province":"ON",
    "sg:tags":[
        "designer",
        "engineer"
    ],
    "wof:name":"D W Product Development Inc",
    "wof:placetype":"venue"
},
  "geometry": {"coordinates":[-75.7119064331,45.3462677002],"type":"Point"}
}