{
  "type": "Feature",
  "properties": {
    "addr:full":"2001 Av Lajoie Montreal QC H3S 1V6",
    "addr:housenumber":"2001",
    "addr:postcode":"h3s 1v6",
    "addr:street":"Av Lajoie",
    "iso:country":"CA",
    "sg:address":"2001 Av Lajoie",
    "sg:city":"Montreal",
    "sg:classifiers":[
        {
            "category":"Organizations",
            "subcategory":"Religious Organization",
            "type":"Services"
        }
    ],
    "sg:phone":"+1 514 738 4480",
    "sg:postcode":"H3S 1V6",
    "sg:province":"QC",
    "sg:tags":[
        "church"
    ],
    "wof:name":"St Raphael the Archangel",
    "wof:placetype":"venue"
},
  "geometry": {"coordinates":[-73.61842300000001,45.512302],"type":"Point"}
}