{
  "type": "Feature",
  "properties": {
    "addr:full":"RR 1 Spring Bay ON P0P 2B0",
    "addr:postcode":"p0p 2b0",
    "addr:street":"Rr 1 Spring",
    "iso:country":"CA",
    "sg:address":"RR 1",
    "sg:city":"Spring Bay",
    "sg:classifiers":[
        {
            "category":"Travel",
            "subcategory":"Hotels & Motels",
            "type":"Entertainment"
        }
    ],
    "sg:phone":"+1 705 377 4638",
    "sg:postcode":"P0P 2B0",
    "sg:province":"ON",
    "sg:tags":[
        "cottage",
        "cabin"
    ],
    "wof:name":"Oakes Cottages",
    "wof:placetype":"venue"
},
  "geometry": {"coordinates":[-82.1673202515,45.6774749756],"type":"Point"}
}