{
  "type": "Feature",
  "properties": {
    "iso:country":"CA",
    "sg:address":"5196 Hwy 23",
    "sg:city":"Palmerston",
    "sg:classifiers":[
        {
            "category":"Retail",
            "subcategory":"Auto Repair",
            "type":"Services"
        }
    ],
    "sg:phone":"+1 519 343 3100",
    "sg:postcode":"N0G 2P0",
    "sg:province":"ON",
    "sg:tags":[
        "truck"
    ],
    "wof:name":"Bramhill Truck Ctr",
    "wof:placetype":"venue"
},
  "geometry": {"coordinates":[-80.8767776489,43.8683815002],"type":"Point"}
}