{
  "type": "Feature",
  "properties": {
    "iso:country":"CA",
    "sg:address":"2801 44 Ave",
    "sg:city":"Vernon",
    "sg:classifiers":[
        {
            "category":"Home & Garden",
            "subcategory":"Home Furnishings",
            "type":"Retail Goods"
        }
    ],
    "sg:phone":"+1 250 545 7370",
    "sg:postcode":"V1T 7P4",
    "sg:province":"BC",
    "sg:tags":[
        "lighting",
        "fixture"
    ],
    "wof:name":"Sun Dial Lighting",
    "wof:placetype":"venue"
},
  "geometry": {"coordinates":[-119.26862335200001,50.2763214111],"type":"Point"}
}