{
  "type": "Feature",
  "properties": {
    "addr:full":"215 Josephine St Nelson BC V1L 1W2",
    "addr:housenumber":"215",
    "addr:postcode":"bc v1l 1w2",
    "addr:street":"Josephine St",
    "iso:country":"CA",
    "sg:address":"215 Josephine St",
    "sg:city":"Nelson",
    "sg:classifiers":[
        {
            "category":"Restaurant",
            "type":"Food & Drink"
        }
    ],
    "sg:phone":"+1 250 354 1999",
    "sg:postcode":"V1L 1W2",
    "sg:province":"BC",
    "wof:name":"Canadian 2 For 1 Pizza",
    "wof:placetype":"venue"
},
  "geometry": {"coordinates":[-117.294235,49.494476],"type":"Point"}
}