{
  "type": "Feature",
  "properties": {
    "addr:full":"354A Aylesworth Ave Scarborough ON M1N 2K2",
    "addr:housenumber":"354a",
    "addr:postcode":"m1n 2k2",
    "addr:street":"Aylesworth Ave",
    "iso:country":"CA",
    "sg:address":"354A Aylesworth Ave",
    "sg:city":"Scarborough",
    "sg:classifiers":[
        {
            "category":"Food & Beverages",
            "subcategory":"Specialty",
            "type":"Retail Goods"
        }
    ],
    "sg:phone":"+1 416 265 8435",
    "sg:postcode":"M1N 2K2",
    "sg:province":"ON",
    "sg:tags":[
        "health",
        "diet"
    ],
    "wof:name":"Matol Botanical Intl",
    "wof:placetype":"venue"
},
  "geometry": {"coordinates":[-79.25971199999999,43.708889],"type":"Point"}
}