{
  "type": "Feature",
  "properties": {
    "iso:country":"CA",
    "sg:address":"7015 Ch Kildare",
    "sg:city":"Cote Saint-Luc",
    "sg:classifiers":[
        {
            "category":"Organizations",
            "subcategory":"Religious Organization",
            "type":"Services"
        }
    ],
    "sg:phone":"+1 514 487 5581",
    "sg:postcode":"H4W 1C1",
    "sg:province":"QC",
    "sg:tags":[
        "synagogue"
    ],
    "wof:name":"Mikvah Israel",
    "wof:placetype":"venue"
},
  "geometry": {"coordinates":[-73.6649856567,45.4709472656],"type":"Point"}
}