{
  "type": "Feature",
  "properties": {
    "addr:full":"3145 Rue Sicotte Saint-Hyacinthe QC J2S 2L9",
    "addr:housenumber":"3145",
    "addr:postcode":"j2s 2l9",
    "addr:street":"Rue Sicotte",
    "iso:country":"CA",
    "sg:address":"3145 Rue Sicotte",
    "sg:city":"Saint-Hyacinthe",
    "sg:classifiers":[
        {
            "category":"Autos & Motor Vehicles",
            "subcategory":"Auto Supplies",
            "type":"Retail Goods"
        }
    ],
    "sg:phone":"+1 450 774 6409",
    "sg:postcode":"J2S 2L9",
    "sg:province":"QC",
    "sg:tags":[
        "automobile",
        "parts"
    ],
    "wof:name":"Pieces D'Auto St-Hyacinthe Inc",
    "wof:placetype":"venue"
},
  "geometry": {"coordinates":[-72.9625549316,45.6198730469],"type":"Point"}
}