{
  "type": "Feature",
  "properties": {
    "addr:full":"St Laurent MB R0C 2S0",
    "addr:postcode":"r0c 2s0",
    "iso:country":"CA",
    "sg:city":"St Laurent",
    "sg:classifiers":[
        {
            "category":"Government",
            "subcategory":"Office",
            "type":"Public Place"
        }
    ],
    "sg:phone":"+1 204 646 2259",
    "sg:postcode":"R0C 2S0",
    "sg:province":"MB",
    "sg:tags":[
        "village"
    ],
    "wof:name":"St Laurent Rural Municipality",
    "wof:placetype":"venue"
},
  "geometry": {"coordinates":[-97.93555499999999,50.409664],"type":"Point"}
}