{
  "type": "Feature",
  "properties": {
    "iso:country":"CA",
    "sg:address":"145 Stewart Ave",
    "sg:city":"Cambridge",
    "sg:classifiers":[
        {
            "category":"Education",
            "subcategory":"School",
            "type":"Public Place"
        }
    ],
    "sg:phone":"+1 519 621 4171",
    "sg:postcode":"N1R 2V5",
    "sg:province":"ON",
    "wof:name":"Stewart Avenue Public School",
    "wof:placetype":"venue"
},
  "geometry": {"coordinates":[-80.302826,43.34911],"type":"Point"}
}