{
  "type": "Feature",
  "properties": {
    "addr:full":"227 Rang Lepage Sainte-Anne-Des-Plaines QC J0N 1H0",
    "addr:housenumber":"227",
    "addr:postcode":"j0n 1h0",
    "addr:street":"Rang Lepage",
    "iso:country":"CA",
    "sg:address":"227 Rang Lepage",
    "sg:city":"Sainte-Anne-Des-Plaines",
    "sg:classifiers":[
        {
            "category":"Professional",
            "subcategory":"Research",
            "type":"Services"
        }
    ],
    "sg:phone":"+1 450 838 0000",
    "sg:postcode":"J0N 1H0",
    "sg:province":"QC",
    "sg:tags":[
        "foundation",
        "philanthropic"
    ],
    "wof:name":"Fondation Normand Clark",
    "wof:placetype":"venue"
},
  "geometry": {"coordinates":[-73.815376,45.731628],"type":"Point"}
}