{
  "type": "Feature",
  "properties": {
    "addr:full":"368 Main St E Hamilton ON L8N 1J5",
    "addr:housenumber":"368",
    "addr:postcode":"l8n 1j5",
    "addr:street":"Main St E",
    "iso:country":"CA",
    "sg:address":"368 Main St E",
    "sg:city":"Hamilton",
    "sg:classifiers":[
        {
            "category":"Shopping",
            "subcategory":"Discount & Variety Stores",
            "type":"Retail Goods"
        }
    ],
    "sg:phone":"+1 905 528 5450",
    "sg:postcode":"L8N 1J5",
    "sg:province":"ON",
    "wof:name":"Emerald Convenience Variety",
    "wof:placetype":"venue"
},
  "geometry": {"coordinates":[-79.855453,43.251553],"type":"Point"}
}