{
  "type": "Feature",
  "properties": {
    "iso:country":"CA",
    "sg:address":"614 Norris Crt # 10",
    "sg:city":"Kingston",
    "sg:classifiers":[
        {
            "category":"Shopping",
            "subcategory":"Computers & Home Electronics",
            "type":"Retail Goods"
        }
    ],
    "sg:phone":"+1 613 634 1550",
    "sg:postcode":"K7P 2R9",
    "sg:province":"ON",
    "sg:tags":[
        "equipment",
        "dealer"
    ],
    "wof:name":"Nexinnovations",
    "wof:placetype":"venue"
},
  "geometry": {"coordinates":[-76.567467,44.263515],"type":"Point"}
}