{
  "type": "Feature",
  "properties": {
    "addr:full":"614 Norris Crt # 10 Kingston ON K7P 2R9",
    "addr:housenumber":"614",
    "addr:postcode":"k7p 2r9",
    "addr:street":"Norris Crt # 10",
    "iso:country":"CA",
    "sg:address":"614 Norris Crt # 10",
    "sg:city":"Kingston",
    "sg:classifiers":[
        {
            "category":"Shopping",
            "subcategory":"Computers & Home Electronics",
            "type":"Retail Goods"
        }
    ],
    "sg:phone":"+1 613 634 1550",
    "sg:postcode":"K7P 2R9",
    "sg:province":"ON",
    "sg:tags":[
        "equipment",
        "dealer"
    ],
    "wof:name":"Nexinnovations",
    "wof:placetype":"venue"
},
  "geometry": {"coordinates":[-76.56746699999999,44.263515],"type":"Point"}
}