{
  "type": "Feature",
  "properties": {
    "addr:full":"2425 St. Johns St Port Moody BC V3H 2B2",
    "addr:housenumber":"2425",
    "addr:postcode":"v3h 2b2",
    "addr:street":"St. Johns St",
    "iso:country":"CA",
    "sg:address":"2425 St. Johns St",
    "sg:city":"Port Moody",
    "sg:classifiers":[
        {
            "category":"Government",
            "subcategory":"Office",
            "type":"Public Place"
        }
    ],
    "sg:phone":"+1 604 931 2008",
    "sg:postcode":"V3H 2B2",
    "sg:province":"BC",
    "sg:tags":[
        "information",
        "arts",
        "village",
        "organization"
    ],
    "wof:name":"Port Moody Arts Ctr",
    "wof:placetype":"venue"
},
  "geometry": {"coordinates":[-122.858055115,49.2765960693],"type":"Point"}
}