{
  "type": "Feature",
  "properties": {
    "iso:country":"CA",
    "sg:address":"61 Dalhousie Ave",
    "sg:city":"Hamilton",
    "sg:classifiers":[
        {
            "category":"Retail",
            "subcategory":"Auto Repair",
            "type":"Services"
        }
    ],
    "sg:phone":"+1 905 547 2223",
    "sg:postcode":"L8L 3J4",
    "sg:province":"ON",
    "sg:tags":[
        "repairing",
        "automobile"
    ],
    "wof:name":"Bill's Garage",
    "wof:placetype":"venue"
},
  "geometry": {"coordinates":[-79.8162231445,43.2546157837],"type":"Point"}
}