{
  "type": "Feature",
  "properties": {
    "addr:full":"1041 37E Av Lac-A-LA-Tortue QC G0X 1L0",
    "addr:housenumber":"1041",
    "addr:postcode":"g0x 1l0",
    "addr:street":"37E Av Lac-A-La-Tortue",
    "iso:country":"CA",
    "sg:address":"1041 37E Av",
    "sg:city":"Lac-A-LA-Tortue",
    "sg:classifiers":[
        {
            "category":"Organizations",
            "subcategory":"Religious Organization",
            "type":"Services"
        }
    ],
    "sg:phone":"+1 819 538 2193",
    "sg:postcode":"G0X 1L0",
    "sg:province":"QC",
    "sg:tags":[
        "church"
    ],
    "wof:name":"Presbytere St-Theophile-Du-Lac",
    "wof:placetype":"venue"
},
  "geometry": {"coordinates":[-72.63427734379999,46.6106567383],"type":"Point"}
}