{
  "type": "Feature",
  "properties": {
    "addr:full":"525 Cavan St Palmerston ON N0G 2P0",
    "addr:housenumber":"525",
    "addr:postcode":"n0g 2p0",
    "addr:street":"Cavan St",
    "iso:country":"CA",
    "sg:address":"525 Cavan St",
    "sg:city":"Palmerston",
    "sg:classifiers":[
        {
            "category":"Recreation",
            "type":"Entertainment"
        }
    ],
    "sg:phone":"+1 519 343 3860",
    "sg:postcode":"N0G 2P0",
    "sg:province":"ON",
    "sg:tags":[
        "government",
        "hall",
        "auditorium"
    ],
    "wof:name":"Palmerston & District Comm Ctr",
    "wof:placetype":"venue"
},
  "geometry": {"coordinates":[-80.850281,43.827686],"type":"Point"}
}