{
  "type": "Feature",
  "properties": {
    "iso:country":"CA",
    "sg:address":"70 Rue Principale E",
    "sg:city":"Sainte-Agathe-Des-Monts",
    "sg:classifiers":[
        {
            "category":"Personal",
            "subcategory":"Beauty Salon",
            "type":"Services"
        }
    ],
    "sg:phone":"+1 819 326 4227",
    "sg:postcode":"J8C 1J7",
    "sg:province":"QC",
    "wof:name":"Salon Menard Bernard",
    "wof:placetype":"venue"
},
  "geometry": {"coordinates":[-74.2848434448,46.0466957092],"type":"Point"}
}