{
  "type": "Feature",
  "properties": {
    "addr:full":"Edmonton AB T5J 3G2",
    "addr:postcode":"t5j 3g2",
    "iso:country":"CA",
    "sg:city":"Edmonton",
    "sg:classifiers":[
        {
            "category":"Professional",
            "subcategory":"Lawyer & Legal Services",
            "type":"Services"
        }
    ],
    "sg:phone":"+1 780 422 6207",
    "sg:postcode":"T5J 3G2",
    "sg:province":"AB",
    "sg:tags":[
        "attorney"
    ],
    "wof:name":"Ingersoll & Ingersoll",
    "wof:placetype":"venue"
},
  "geometry": {"coordinates":[-113.491004944,53.5423774719],"type":"Point"}
}