{
  "type": "Feature",
  "properties": {
    "addr:full":"4245 Rue DE Verdun Verdun QC H4G 1L4",
    "addr:housenumber":"4245",
    "addr:postcode":"h4g 1l4",
    "addr:street":"Rue De Verdun",
    "iso:country":"CA",
    "sg:address":"4245 Rue DE Verdun",
    "sg:city":"Verdun",
    "sg:classifiers":[
        {
            "category":"Insurance",
            "subcategory":"Insurance Agent",
            "type":"Services"
        }
    ],
    "sg:phone":"+1 514 766 2339",
    "sg:postcode":"H4G 1L4",
    "sg:province":"QC",
    "wof:name":"Marcil & Cote Assurance Enrg",
    "wof:placetype":"venue"
},
  "geometry": {"coordinates":[-73.57172393800001,45.4616775513],"type":"Point"}
}