{
  "type": "Feature",
  "properties": {
    "addr:full":"2336 Sinclair Cir Burlington ON L7P 3B3",
    "addr:housenumber":"2336",
    "addr:postcode":"l7p 3b3",
    "addr:street":"Sinclair Cir",
    "iso:country":"CA",
    "sg:address":"2336 Sinclair Cir",
    "sg:city":"Burlington",
    "sg:classifiers":[
        {
            "category":"Wholesale",
            "subcategory":"Non-durable Goods",
            "type":"Manufacturing & Wholesale Goods"
        }
    ],
    "sg:phone":"+1 905 335 9784",
    "sg:postcode":"L7P 3B3",
    "sg:province":"ON",
    "sg:tags":[
        "advertising"
    ],
    "wof:name":"Excel Advertising Specialties",
    "wof:placetype":"venue"
},
  "geometry": {"coordinates":[-79.8352890015,43.3624916077],"type":"Point"}
}