{
  "type": "Feature",
  "properties": {
    "addr:full":"7210 Malden Rd Windsor ON N9J 2T7",
    "addr:housenumber":"7210",
    "addr:postcode":"n9j 2t7",
    "addr:street":"Malden Rd",
    "iso:country":"CA",
    "sg:address":"7210 Malden Rd",
    "sg:city":"Windsor",
    "sg:classifiers":[
        {
            "category":"Wholesale",
            "subcategory":"Home Furnishings",
            "type":"Manufacturing & Wholesale Goods"
        }
    ],
    "sg:phone":"+1 519 978 3169",
    "sg:postcode":"N9J 2T7",
    "sg:province":"ON",
    "sg:tags":[
        "closet",
        "accessory"
    ],
    "wof:name":"Evelyn Bennett Closet Concepts",
    "wof:placetype":"venue"
},
  "geometry": {"coordinates":[-83.060508728,42.2527389526],"type":"Point"}
}