{
  "type": "Feature",
  "properties": {
    "addr:full":"Farm Rd Bay Bulls NL A0A 1C0",
    "addr:postcode":"a0a 1c0",
    "addr:street":"Farm Rd",
    "iso:country":"CA",
    "sg:address":"Farm Rd",
    "sg:city":"Bay Bulls",
    "sg:classifiers":[
        {
            "category":"Farming",
            "subcategory":"Farm",
            "type":"Manufacturing & Wholesale Goods"
        }
    ],
    "sg:phone":"+1 709 334 3606",
    "sg:postcode":"A0A 1C0",
    "sg:province":"NL",
    "wof:name":"Oceanview Farms",
    "wof:placetype":"venue"
},
  "geometry": {"coordinates":[-52.818604,47.317017],"type":"Point"}
}