{
  "type": "Feature",
  "properties": {
    "addr:full":"116 Centre St Kingston ON K7L 4E6",
    "addr:housenumber":"116",
    "addr:postcode":"k7l 4e6",
    "addr:street":"Centre St",
    "iso:country":"CA",
    "sg:address":"116 Centre St",
    "sg:city":"Kingston",
    "sg:classifiers":[
        {
            "category":"Organizations",
            "subcategory":"Religious Organization",
            "type":"Services"
        }
    ],
    "sg:phone":"+1 613 542 5012",
    "sg:postcode":"K7L 4E6",
    "sg:province":"ON",
    "sg:tags":[
        "synagogue"
    ],
    "wof:name":"Beth Israel Congregation",
    "wof:placetype":"venue"
},
  "geometry": {"coordinates":[-76.5050201416,44.22473526],"type":"Point"}
}