{
  "type": "Feature",
  "properties": {
    "addr:full":"163 King St E Hamilton ON L8N 1B1",
    "addr:housenumber":"163",
    "addr:postcode":"l8n 1b1",
    "addr:street":"King St E",
    "iso:country":"CA",
    "sg:address":"163 King St E",
    "sg:city":"Hamilton",
    "sg:classifiers":[
        {
            "category":"Restaurant",
            "type":"Food & Drink"
        }
    ],
    "sg:phone":"+1 905 527 0527",
    "sg:postcode":"L8N 1B1",
    "sg:province":"ON",
    "wof:name":"Pizza House",
    "wof:placetype":"venue"
},
  "geometry": {"coordinates":[-79.86428070069999,43.2551765442],"type":"Point"}
}