{
  "type": "Feature",
  "properties": {
    "addr:full":"5 Brunel Rd Huntsville ON P1H 2A8",
    "addr:housenumber":"5",
    "addr:postcode":"p1h 2a8",
    "addr:street":"Brunel Rd",
    "iso:country":"CA",
    "sg:address":"5 Brunel Rd",
    "sg:city":"Huntsville",
    "sg:classifiers":[
        {
            "category":"Home & Garden",
            "subcategory":"Furniture",
            "type":"Retail Goods"
        }
    ],
    "sg:phone":"+1 705 789 1171",
    "sg:postcode":"P1H 2A8",
    "sg:province":"ON",
    "wof:name":"Pinestead",
    "wof:placetype":"venue"
},
  "geometry": {"coordinates":[-79.21653000000001,45.326717],"type":"Point"}
}