{
  "type": "Feature",
  "properties": {
    "addr:full":"901 Rutherford Rd Maple ON L6A 1S2",
    "addr:housenumber":"901",
    "addr:postcode":"l6a 1s2",
    "addr:street":"Rutherford Rd",
    "iso:country":"CA",
    "sg:address":"901 Rutherford Rd",
    "sg:city":"Maple",
    "sg:classifiers":[
        {
            "category":"Organizations",
            "subcategory":"Religious Organization",
            "type":"Services"
        }
    ],
    "sg:phone":"+1 905 709 4544",
    "sg:postcode":"L6A 1S2",
    "sg:province":"ON",
    "sg:tags":[
        "church"
    ],
    "wof:name":"Christian Community Church",
    "wof:placetype":"venue"
},
  "geometry": {"coordinates":[-79.5061798096,43.8378715515],"type":"Point"}
}