{
  "type": "Feature",
  "properties": {
    "addr:full":"51 Ridgemont Dr Fernie BC V0B 1M2",
    "addr:housenumber":"51",
    "addr:postcode":"bc v0b 1m2",
    "addr:street":"Ridgemont Dr",
    "iso:country":"CA",
    "sg:address":"51 Ridgemont Dr",
    "sg:city":"Fernie",
    "sg:classifiers":[
        {
            "category":"Real Estate",
            "subcategory":"Real Estate Operator",
            "type":"Services"
        }
    ],
    "sg:phone":"+1 250 423 6560",
    "sg:postcode":"V0B 1M2",
    "sg:province":"BC",
    "sg:tags":[
        "condominium"
    ],
    "wof:name":"Snow Valley Condos",
    "wof:placetype":"venue"
},
  "geometry": {"coordinates":[-115.05317700000001,49.504646],"type":"Point"}
}