{
  "type": "Feature",
  "properties": {
    "addr:full":"111 10th St Beaverlodge AB T0H 0C0",
    "addr:housenumber":"111",
    "addr:postcode":"t0h 0c0",
    "addr:street":"10Th St",
    "iso:country":"CA",
    "sg:address":"111 10th St",
    "sg:city":"Beaverlodge",
    "sg:classifiers":[
        {
            "category":"Real Estate",
            "subcategory":"Real Estate Agent",
            "type":"Services"
        }
    ],
    "sg:phone":"+1 780 354 3313",
    "sg:postcode":"T0H 0C0",
    "sg:province":"AB",
    "sg:tags":[
        "consultant"
    ],
    "wof:name":"All Peace Realty",
    "wof:placetype":"venue"
},
  "geometry": {"coordinates":[-119.429543,55.209347],"type":"Point"}
}