{
  "type": "Feature",
  "properties": {
    "addr:full":"284 Friel St Ottawa ON K1N 7W1",
    "addr:housenumber":"284",
    "addr:postcode":"k1n 7w1",
    "addr:street":"Friel St",
    "iso:country":"CA",
    "sg:address":"284 Friel St",
    "sg:city":"Ottawa",
    "sg:classifiers":[
        {
            "category":"Professional",
            "subcategory":"Management & Consulting",
            "type":"Services"
        }
    ],
    "sg:phone":"+1 613 241 7166",
    "sg:postcode":"K1N 7W1",
    "sg:province":"ON",
    "sg:tags":[
        "project"
    ],
    "wof:name":"Padam Management Ltd",
    "wof:placetype":"venue"
},
  "geometry": {"coordinates":[-75.68171700000001,45.428925],"type":"Point"}
}