{
  "type": "Feature",
  "properties": {
    "addr:full":"2446 New St Burlington ON L7R 1J6",
    "addr:housenumber":"2446",
    "addr:postcode":"l7r 1j6",
    "addr:street":"New St",
    "iso:country":"CA",
    "sg:address":"2446 New St",
    "sg:city":"Burlington",
    "sg:classifiers":[
        {
            "category":"Professional",
            "subcategory":"Business Services",
            "type":"Services"
        }
    ],
    "sg:phone":"+1 905 633 8837",
    "sg:postcode":"L7R 1J6",
    "sg:province":"ON",
    "sg:tags":[
        "recording",
        "studio"
    ],
    "wof:name":"Westmoreland Recording Studio",
    "wof:placetype":"venue"
},
  "geometry": {"coordinates":[-79.7862625122,43.3371925354],"type":"Point"}
}