{
  "type": "Feature",
  "properties": {
    "addr:full":"4045 11 Ave Smithers BC V0J 2N0",
    "addr:housenumber":"4045",
    "addr:postcode":"v0j 2n0",
    "addr:street":"11 Ave",
    "iso:country":"CA",
    "sg:address":"4045 11 Ave",
    "sg:city":"Smithers",
    "sg:classifiers":[
        {
            "category":"Real Estate",
            "subcategory":"Real Estate Agent",
            "type":"Services"
        }
    ],
    "sg:phone":"+1 250 847 3153",
    "sg:postcode":"V0J 2N0",
    "sg:province":"BC",
    "sg:tags":[
        "appraiser"
    ],
    "wof:name":"Northcountry Appraisals",
    "wof:placetype":"venue"
},
  "geometry": {"coordinates":[-127.15924835200001,54.78565979],"type":"Point"}
}