{
  "type": "Feature",
  "properties": {
    "iso:country":"CA",
    "sg:city":"Surrey",
    "sg:classifiers":[
        {
            "category":"Health Services",
            "subcategory":"Doctor",
            "type":"Services"
        }
    ],
    "sg:phone":"+1 604 531 0888",
    "sg:postcode":"V4A 9E3",
    "sg:province":"BC",
    "sg:tags":[
        "physician",
        "surgeon"
    ],
    "wof:name":"Raffle, Valerie J MD",
    "wof:placetype":"venue"
},
  "geometry": {"coordinates":[-122.801369,49.037582],"type":"Point"}
}