{
  "type": "Feature",
  "properties": {
    "addr:full":"Queen Charlotte BC V0T 1S0",
    "addr:postcode":"v0t 1s0",
    "iso:country":"CA",
    "sg:city":"Queen Charlotte",
    "sg:classifiers":[
        {
            "category":"Building & Trades",
            "subcategory":"Construction",
            "type":"Services"
        }
    ],
    "sg:phone":"+1 250 559 2335",
    "sg:postcode":"V0T 1S0",
    "sg:province":"BC",
    "sg:tags":[
        "general",
        "contractor"
    ],
    "wof:name":"Berg-Mac Ind Ltd",
    "wof:placetype":"venue"
},
  "geometry": {"coordinates":[-132.09429931599999,53.2542495728],"type":"Point"}
}