{
  "type": "Feature",
  "properties": {
    "addr:full":"Sutton West ON L0E 1R0",
    "addr:postcode":"l0e 1r0",
    "iso:country":"CA",
    "sg:city":"Sutton West",
    "sg:classifiers":[
        {
            "category":"Home & Garden",
            "subcategory":"Building Materials",
            "type":"Retail Goods"
        }
    ],
    "sg:phone":"+1 905 473 3462",
    "sg:postcode":"L0E 1R0",
    "sg:province":"ON",
    "wof:name":"National Building Supplies",
    "wof:placetype":"venue"
},
  "geometry": {"coordinates":[-79.348167,44.286381],"type":"Point"}
}