{
  "type": "Feature",
  "properties": {
    "addr:full":"67 Clarence St Ottawa ON K1N 5P5",
    "addr:housenumber":"67",
    "addr:postcode":"k1n 5p5",
    "addr:street":"Clarence St",
    "iso:country":"CA",
    "sg:address":"67 Clarence St",
    "sg:city":"Ottawa",
    "sg:classifiers":[
        {
            "category":"Restaurant",
            "type":"Food & Drink"
        }
    ],
    "sg:phone":"+1 613 562 0674",
    "sg:postcode":"K1N 5P5",
    "sg:province":"ON",
    "wof:name":"Heart & Crown",
    "wof:placetype":"venue"
},
  "geometry": {"coordinates":[-75.693428,45.429066],"type":"Point"}
}