{
  "type": "Feature",
  "properties": {
    "addr:full":"151 Av Du Lac Rouyn-Noranda QC J9X 4N6",
    "addr:postcode":"j9x 4n6",
    "addr:street":"151 Av Du Lac",
    "iso:country":"CA",
    "sg:address":"151 Av Du Lac",
    "sg:city":"Rouyn-Noranda",
    "sg:classifiers":[
        {
            "category":"Government",
            "subcategory":"Office",
            "type":"Public Place"
        }
    ],
    "sg:phone":"+1 819 764 6711",
    "sg:postcode":"J9X 4N6",
    "sg:province":"QC",
    "wof:name":"Canada Assurance-Emploi",
    "wof:placetype":"venue"
},
  "geometry": {"coordinates":[-79.016762,48.239082],"type":"Point"}
}