{
  "type": "Feature",
  "properties": {
    "addr:full":"Calgary AB T2T 0A3",
    "addr:postcode":"t2t 0a3",
    "iso:country":"CA",
    "sg:city":"Calgary",
    "sg:classifiers":[
        {
            "category":"Health Services",
            "subcategory":"Health Practitioner",
            "type":"Services"
        }
    ],
    "sg:phone":"+1 403 541 9005",
    "sg:postcode":"T2T 0A3",
    "sg:province":"AB",
    "sg:tags":[
        "psychologist"
    ],
    "wof:name":"Bobey, Mary J PhD",
    "wof:placetype":"venue"
},
  "geometry": {"coordinates":[-114.082207,51.037941],"type":"Point"}
}