{
  "type": "Feature",
  "properties": {
    "addr:full":"RR 3 STN Main Simcoe ON N3Y 4K2",
    "addr:postcode":"n3y 4k2",
    "addr:street":"Rr 3 Stn Main",
    "iso:country":"CA",
    "sg:address":"RR 3 STN Main",
    "sg:city":"Simcoe",
    "sg:classifiers":[
        {
            "category":"Food & Beverages",
            "subcategory":"Fruits & Vegetables",
            "type":"Retail Goods"
        }
    ],
    "sg:phone":"+1 519 428 1563",
    "sg:postcode":"N3Y 4K2",
    "sg:province":"ON",
    "sg:tags":[
        "produce"
    ],
    "wof:name":"Powell's Patch Blueberries",
    "wof:placetype":"venue"
},
  "geometry": {"coordinates":[-80.29964447019999,42.7979278564],"type":"Point"}
}