{
  "type": "Feature",
  "properties": {
    "addr:full":"2077 Bloor St Bowmanville ON L1C 3K3",
    "addr:housenumber":"2077",
    "addr:postcode":"l1c 3k3",
    "addr:street":"Bloor St",
    "iso:country":"CA",
    "sg:address":"2077 Bloor St",
    "sg:city":"Bowmanville",
    "sg:classifiers":[
        {
            "category":"Recreation",
            "type":"Entertainment"
        }
    ],
    "sg:phone":"+1 905 623 7536",
    "sg:postcode":"L1C 3K3",
    "sg:province":"ON",
    "sg:tags":[
        "riding",
        "academy"
    ],
    "wof:name":"Chance Stables Equestrian Ctr",
    "wof:placetype":"venue"
},
  "geometry": {"coordinates":[-78.73223900000001,43.906559],"type":"Point"}
}