{
  "type": "Feature",
  "properties": {
    "addr:full":"Alma Elmsdale PE C0B 1K0",
    "addr:postcode":"c0b 1k0",
    "iso:country":"CA",
    "sg:address":"Alma",
    "sg:city":"Elmsdale",
    "sg:classifiers":[
        {
            "category":"Building & Trades",
            "subcategory":"Construction",
            "type":"Services"
        }
    ],
    "sg:phone":"+1 902 853 3169",
    "sg:postcode":"C0B 1K0",
    "sg:province":"PE",
    "sg:tags":[
        "concrete",
        "contractor"
    ],
    "wof:name":"G E Mac Neill Construction Ltd",
    "wof:placetype":"venue"
},
  "geometry": {"coordinates":[-64.13841247560001,46.8203582764],"type":"Point"}
}