{
  "type": "Feature",
  "properties": {
    "addr:full":"838 Roselawn Ave York ON M6B 1B3",
    "addr:housenumber":"838",
    "addr:postcode":"m6b 1b3",
    "addr:street":"Roselawn Ave",
    "iso:country":"CA",
    "sg:address":"838 Roselawn Ave",
    "sg:city":"York",
    "sg:classifiers":[
        {
            "category":"Shopping",
            "subcategory":"Discount & Variety Stores",
            "type":"Retail Goods"
        }
    ],
    "sg:phone":"+1 416 783 3298",
    "sg:postcode":"M6B 1B3",
    "sg:province":"ON",
    "wof:name":"Jin Mini Mart",
    "wof:placetype":"venue"
},
  "geometry": {"coordinates":[-79.44016999999999,43.702522],"type":"Point"}
}