{
  "type": "Feature",
  "properties": {
    "iso:country":"CA",
    "sg:city":"London",
    "sg:classifiers":[
        {
            "category":"Restaurant",
            "type":"Food & Drink"
        }
    ],
    "sg:phone":"+1 519 661 4080",
    "sg:postcode":"N6A 3K7",
    "sg:province":"ON",
    "wof:name":"Michaels Dining Room",
    "wof:placetype":"venue"
},
  "geometry": {"coordinates":[-81.246216,42.986897],"type":"Point"}
}