{
  "type": "Feature",
  "properties": {
    "addr:full":"6526 Throup Rd Sooke BC V0S 1N0",
    "addr:housenumber":"6526",
    "addr:postcode":"v0s 1n0",
    "addr:street":"Throup Rd",
    "iso:country":"CA",
    "sg:address":"6526 Throup Rd",
    "sg:city":"Sooke",
    "sg:classifiers":[
        {
            "category":"Education",
            "subcategory":"School",
            "type":"Public Place"
        }
    ],
    "sg:phone":"+1 250 642 0500",
    "sg:postcode":"V0S 1N0",
    "sg:province":"BC",
    "wof:name":"Ecole Poirier",
    "wof:placetype":"venue"
},
  "geometry": {"coordinates":[-123.71627807599999,48.3853034973],"type":"Point"}
}