{
  "type": "Feature",
  "properties": {
    "iso:country":"CA",
    "sg:address":"56 Broadway Ave",
    "sg:city":"Wawa",
    "sg:classifiers":[
        {
            "category":"Insurance",
            "subcategory":"Insurance Agent",
            "type":"Services"
        }
    ],
    "sg:phone":"+1 705 856 2225",
    "sg:postcode":"P0S 1K0",
    "sg:province":"ON",
    "wof:name":"Wawa General Insurance",
    "wof:placetype":"venue"
},
  "geometry": {"coordinates":[-84.7710571289,47.9946517944],"type":"Point"}
}