{
  "type": "Feature",
  "properties": {
    "addr:full":"2431 Cousins Ave Courtenay BC V9N 3N6",
    "addr:housenumber":"2431",
    "addr:postcode":"v9n 3n6",
    "addr:street":"Cousins Ave",
    "iso:country":"CA",
    "sg:address":"2431 Cousins Ave",
    "sg:city":"Courtenay",
    "sg:classifiers":[
        {
            "category":"Freight",
            "type":"Transportation"
        }
    ],
    "sg:phone":"+1 250 338 7799",
    "sg:postcode":"V9N 3N6",
    "sg:province":"BC",
    "sg:tags":[
        "trucking"
    ],
    "wof:name":"Gord Corrigall Trucking",
    "wof:placetype":"venue"
},
  "geometry": {"coordinates":[-124.99826,49.669495],"type":"Point"}
}