{
  "type": "Feature",
  "properties": {
    "addr:full":"1005 Boul Laure Sept-Iles QC G4R 4S6",
    "addr:housenumber":"1005",
    "addr:postcode":"g4r 4s6",
    "addr:street":"Boul Laure Sept-Iles",
    "iso:country":"CA",
    "sg:address":"1005 Boul Laure",
    "sg:city":"Sept-Iles",
    "sg:classifiers":[
        {
            "category":"Restaurant",
            "type":"Food & Drink"
        }
    ],
    "sg:phone":"+1 418 968 9191",
    "sg:postcode":"G4R 4S6",
    "sg:province":"QC",
    "wof:name":"Rotisserie St-Hubert",
    "wof:placetype":"venue"
},
  "geometry": {"coordinates":[-66.39180755620001,50.2270050049],"type":"Point"}
}