{
  "type": "Feature",
  "properties": {
    "addr:full":"1111 Elgin St W # D4 Cobourg ON K9A 5H7",
    "addr:housenumber":"1111",
    "addr:postcode":"k9a 5h7",
    "addr:street":"Elgin St W # D4",
    "iso:country":"CA",
    "sg:address":"1111 Elgin St W # D4",
    "sg:city":"Cobourg",
    "sg:classifiers":[
        {
            "category":"Shopping",
            "subcategory":"Gifts & Souvenirs",
            "type":"Retail Goods"
        }
    ],
    "sg:phone":"+1 905 373 0366",
    "sg:postcode":"K9A 5H7",
    "sg:province":"ON",
    "sg:tags":[
        "shop"
    ],
    "wof:name":"Hallmark",
    "wof:placetype":"venue"
},
  "geometry": {"coordinates":[-78.2000961304,43.9710502625],"type":"Point"}
}