{
  "type": "Feature",
  "properties": {
    "addr:full":"2184 Wyton Crt Mississauga ON L4Y 1X2",
    "addr:housenumber":"2184",
    "addr:postcode":"l4y 1x2",
    "addr:street":"Wyton Crt",
    "iso:country":"CA",
    "sg:address":"2184 Wyton Crt",
    "sg:city":"Mississauga",
    "sg:classifiers":[
        {
            "category":"Manufacturing",
            "subcategory":"Chemicals & Compounds",
            "type":"Manufacturing & Wholesale Goods"
        }
    ],
    "sg:phone":"+1 905 279 3527",
    "sg:postcode":"L4Y 1X2",
    "sg:province":"ON",
    "sg:tags":[
        "plastic"
    ],
    "wof:name":"Helbo Polymers Inc",
    "wof:placetype":"venue"
},
  "geometry": {"coordinates":[-79.5801620483,43.594078064],"type":"Point"}
}