{
  "type": "Feature",
  "properties": {
    "addr:full":"Brampton ON L6T 5N2",
    "addr:postcode":"l6t 5n2",
    "iso:country":"CA",
    "sg:city":"Brampton",
    "sg:classifiers":[
        {
            "category":"Wholesale",
            "subcategory":"Construction Materials",
            "type":"Manufacturing & Wholesale Goods"
        }
    ],
    "sg:phone":"+1 905 456 2435",
    "sg:postcode":"L6T 5N2",
    "sg:province":"ON",
    "sg:tags":[
        "sand",
        "gravel"
    ],
    "wof:name":"Fsi Landscape Supplies",
    "wof:placetype":"venue"
},
  "geometry": {"coordinates":[-79.70560500000001,43.689541],"type":"Point"}
}