{
  "type": "Feature",
  "properties": {
    "addr:full":"501 Rolla Rd Dawson Creek BC V1G 4E9",
    "addr:housenumber":"501",
    "addr:postcode":"v1g 4e9",
    "addr:street":"Rolla Rd",
    "iso:country":"CA",
    "sg:address":"501 Rolla Rd",
    "sg:city":"Dawson Creek",
    "sg:classifiers":[
        {
            "category":"Building & Trades",
            "subcategory":"Construction",
            "type":"Services"
        }
    ],
    "sg:phone":"+1 250 782 7966",
    "sg:postcode":"V1G 4E9",
    "sg:province":"BC",
    "sg:tags":[
        "paving",
        "contractor"
    ],
    "wof:name":"Dgs Astro Paving Ltd",
    "wof:placetype":"venue"
},
  "geometry": {"coordinates":[-120.237061,55.761726],"type":"Point"}
}