{
  "type": "Feature",
  "properties": {
    "iso:country":"CA",
    "sg:address":"1074 Bathurst St",
    "sg:city":"Toronto",
    "sg:classifiers":[
        {
            "category":"Retail",
            "subcategory":"Veterinary Services",
            "type":"Services"
        }
    ],
    "sg:phone":"+1 416 588 3056",
    "sg:postcode":"M5R 3G9",
    "sg:province":"ON",
    "sg:tags":[
        "veterinarian"
    ],
    "wof:name":"Koroknai, M DVM",
    "wof:placetype":"venue"
},
  "geometry": {"coordinates":[-79.41423,43.672306],"type":"Point"}
}