{
  "type": "Feature",
  "properties": {
    "addr:full":"Garafraxa St Durham ON N0G 1R0",
    "addr:postcode":"n0g 1r0",
    "addr:street":"Garafraxa St",
    "iso:country":"CA",
    "sg:address":"Garafraxa St",
    "sg:city":"Durham",
    "sg:classifiers":[
        {
            "category":"Organizations",
            "subcategory":"Religious Organization",
            "type":"Services"
        }
    ],
    "sg:phone":"+1 519 369 2605",
    "sg:postcode":"N0G 1R0",
    "sg:province":"ON",
    "sg:tags":[
        "church"
    ],
    "wof:name":"St Peter Catholic Church",
    "wof:placetype":"venue"
},
  "geometry": {"coordinates":[-80.81871,44.177143],"type":"Point"}
}