{
  "type": "Feature",
  "properties": {
    "addr:full":"17 Rue Saint-Stanislas Quebec QC G1R 4G7",
    "addr:housenumber":"17",
    "addr:postcode":"g1r 4g7",
    "addr:street":"Rue Saint-Stanislas",
    "iso:country":"CA",
    "sg:address":"17 Rue Saint-Stanislas",
    "sg:city":"Quebec",
    "sg:classifiers":[
        {
            "category":"Restaurant",
            "type":"Food & Drink"
        }
    ],
    "sg:phone":"+1 418 692 5488",
    "sg:postcode":"G1R 4G7",
    "sg:province":"QC",
    "wof:name":"Restaurant Le Patriarche Enr",
    "wof:placetype":"venue"
},
  "geometry": {"coordinates":[-71.21138000489999,46.8138885498],"type":"Point"}
}