{
  "type": "Feature",
  "properties": {
    "iso:country":"CA",
    "sg:city":"London",
    "sg:classifiers":[
        {
            "category":"Building & Trades",
            "subcategory":"Construction",
            "type":"Services"
        }
    ],
    "sg:phone":"+1 519 455 6970",
    "sg:postcode":"N5Y 4V6",
    "sg:province":"ON",
    "sg:tags":[
        "general",
        "contractor"
    ],
    "wof:name":"Icorr Construction Inc",
    "wof:placetype":"venue"
},
  "geometry": {"coordinates":[-81.22663116459999,43.0164985657],"type":"Point"}
}