{
  "type": "Feature",
  "properties": {
    "addr:full":"2868 Lake Shore Blvd W Etobicoke ON M8V 1J2",
    "addr:housenumber":"2868",
    "addr:postcode":"m8v 1j2",
    "addr:street":"Lake Shore Blvd W",
    "iso:country":"CA",
    "sg:address":"2868 Lake Shore Blvd W",
    "sg:city":"Etobicoke",
    "sg:classifiers":[
        {
            "category":"Restaurant",
            "type":"Food & Drink"
        }
    ],
    "sg:phone":"+1 416 251 4033",
    "sg:postcode":"M8V 1J2",
    "sg:province":"ON",
    "wof:name":"Lucky Dice Hamburger",
    "wof:placetype":"venue"
},
  "geometry": {"coordinates":[-79.50318145750001,43.6013298035],"type":"Point"}
}