{
  "type": "Feature",
  "properties": {
    "addr:full":"45 Ontario St N Milton ON L9T 2T2",
    "addr:housenumber":"45",
    "addr:postcode":"l9t 2t2",
    "addr:street":"Ontario St N",
    "iso:country":"CA",
    "sg:address":"45 Ontario St N",
    "sg:city":"Milton",
    "sg:classifiers":[
        {
            "category":"Manufacturing",
            "subcategory":"Tools & Machinery",
            "type":"Manufacturing & Wholesale Goods"
        }
    ],
    "sg:phone":"+1 905 693 1107",
    "sg:postcode":"L9T 2T2",
    "sg:province":"ON",
    "sg:tags":[
        "machine",
        "shop"
    ],
    "wof:name":"Reliance Machine Works CO",
    "wof:placetype":"venue"
},
  "geometry": {"coordinates":[-79.8785247803,43.5193328857],"type":"Point"}
}