{
  "type": "Feature",
  "properties": {
    "addr:full":"3 Valmount Ave Scarborough ON M1C 1P3",
    "addr:housenumber":"3",
    "addr:postcode":"m1c 1p3",
    "addr:street":"Valmount Ave",
    "iso:country":"CA",
    "sg:address":"3 Valmount Ave",
    "sg:city":"Scarborough",
    "sg:classifiers":[
        {
            "category":"Retail",
            "subcategory":"Auto Repair",
            "type":"Services"
        }
    ],
    "sg:phone":"+1 416 287 1793",
    "sg:postcode":"M1C 1P3",
    "sg:province":"ON",
    "sg:tags":[
        "repairing",
        "automobile"
    ],
    "wof:name":"Ross' Auto Svc",
    "wof:placetype":"venue"
},
  "geometry": {"coordinates":[-79.155754,43.791317],"type":"Point"}
}