{
  "type": "Feature",
  "properties": {
    "addr:full":"Chicoutimi QC G7H 6K9",
    "addr:postcode":"g7h 6k9",
    "iso:country":"CA",
    "sg:city":"Chicoutimi",
    "sg:classifiers":[
        {
            "category":"Real Estate",
            "subcategory":"Real Estate Operator",
            "type":"Services"
        }
    ],
    "sg:phone":"+1 418 545 6464",
    "sg:postcode":"G7H 6K9",
    "sg:province":"QC",
    "sg:tags":[
        "building",
        "parks"
    ],
    "wof:name":"Edifice A Bureaux Le 345",
    "wof:placetype":"venue"
},
  "geometry": {"coordinates":[-71.06107299999999,48.403706],"type":"Point"}
}