{
  "type": "Feature",
  "properties": {
    "iso:country":"CA",
    "sg:city":"Guelph",
    "sg:classifiers":[
        {
            "category":"Retail",
            "subcategory":"Auto Repair",
            "type":"Services"
        }
    ],
    "sg:phone":"+1 519 824 8600",
    "sg:postcode":"N1K 1B6",
    "sg:province":"ON",
    "sg:tags":[
        "transmission",
        "automobile",
        "repairing"
    ],
    "wof:name":"Haist Transmission",
    "wof:placetype":"venue"
},
  "geometry": {"coordinates":[-80.302696,43.550549],"type":"Point"}
}