{
  "type": "Feature",
  "properties": {
    "addr:full":"4992 King St Beamsville ON L0R 1B0",
    "addr:housenumber":"4992",
    "addr:postcode":"l0r 1b0",
    "addr:street":"King St",
    "iso:country":"CA",
    "sg:address":"4992 King St",
    "sg:city":"Beamsville",
    "sg:classifiers":[
        {
            "category":"Home & Garden",
            "subcategory":"Hardware",
            "type":"Retail Goods"
        }
    ],
    "sg:phone":"+1 905 563 8254",
    "sg:postcode":"L0R 1B0",
    "sg:province":"ON",
    "wof:name":"Beamsville Home Hardware Ctr",
    "wof:placetype":"venue"
},
  "geometry": {"coordinates":[-79.4759521484,43.1654472351],"type":"Point"}
}