{
  "type": "Feature",
  "properties": {
    "addr:full":"Calgary AB T3G 3N7",
    "addr:postcode":"t3g 3n7",
    "iso:country":"CA",
    "sg:city":"Calgary",
    "sg:classifiers":[
        {
            "category":"Professional",
            "subcategory":"Management & Consulting",
            "type":"Services"
        }
    ],
    "sg:phone":"+1 403 272 1161",
    "sg:postcode":"T3G 3N7",
    "sg:province":"AB",
    "sg:tags":[
        "consultant",
        "business"
    ],
    "wof:name":"Richardson Group",
    "wof:placetype":"venue"
},
  "geometry": {"coordinates":[-114.19718170199999,51.1264648438],"type":"Point"}
}