{
  "type": "Feature",
  "properties": {
    "addr:full":"284 Ivens St Virden MB R0M 2C0",
    "addr:housenumber":"284",
    "addr:postcode":"r0m 2c0",
    "addr:street":"Ivens St",
    "iso:country":"CA",
    "sg:address":"284 Ivens St",
    "sg:city":"Virden",
    "sg:classifiers":[
        {
            "category":"Mining & Drilling",
            "type":"Manufacturing & Wholesale Goods"
        }
    ],
    "sg:phone":"+1 204 748 2796",
    "sg:postcode":"R0M 2C0",
    "sg:province":"MB",
    "sg:tags":[
        "field",
        "oil"
    ],
    "wof:name":"Sparks Oil Field Svc",
    "wof:placetype":"venue"
},
  "geometry": {"coordinates":[-100.91971599999999,49.856026],"type":"Point"}
}