{
  "type": "Feature",
  "properties": {
    "iso:country":"CA",
    "sg:address":"22 Paget St",
    "sg:city":"New Liskeard",
    "sg:classifiers":[
        {
            "category":"Professional",
            "subcategory":"Lawyer & Legal Services",
            "type":"Services"
        }
    ],
    "sg:phone":"+1 705 647 7307",
    "sg:postcode":"P0J 1P0",
    "sg:province":"ON",
    "sg:tags":[
        "attorney"
    ],
    "wof:name":"Wowk, John W",
    "wof:placetype":"venue"
},
  "geometry": {"coordinates":[-79.6745834351,47.5091514587],"type":"Point"}
}