{
  "type": "Feature",
  "properties": {
    "iso:country":"CA",
    "sg:address":"3219 Yonge St",
    "sg:city":"Toronto",
    "sg:classifiers":[
        {
            "category":"Professional",
            "subcategory":"Accounting & Tax Preparation",
            "type":"Services"
        }
    ],
    "sg:phone":"+1 416 480 0886",
    "sg:postcode":"M4N 3S1",
    "sg:province":"ON",
    "sg:tags":[
        "accountant"
    ],
    "wof:name":"Slater, Leslie CA",
    "wof:placetype":"venue"
},
  "geometry": {"coordinates":[-79.40284729,43.728187561],"type":"Point"}
}