{
  "type": "Feature",
  "properties": {
    "iso:country":"CA",
    "sg:address":"1160 Rang Saint-David",
    "sg:city":"Saint-Gabriel-DE-Brandon",
    "sg:classifiers":[
        {
            "category":"Travel",
            "subcategory":"Campground",
            "type":"Entertainment"
        }
    ],
    "sg:phone":"+1 450 835 1649",
    "sg:postcode":"J0K 2N0",
    "sg:province":"QC",
    "wof:name":"Camping Soleil Le Vent",
    "wof:placetype":"venue"
},
  "geometry": {"coordinates":[-73.363182,46.306637],"type":"Point"}
}