{
  "type": "Feature",
  "properties": {
    "addr:full":"1160 Rang Saint-David Saint-Gabriel-DE-Brandon QC J0K 2N0",
    "addr:housenumber":"1160",
    "addr:postcode":"j0k 2n0",
    "addr:street":"Rang Saint-David",
    "iso:country":"CA",
    "sg:address":"1160 Rang Saint-David",
    "sg:city":"Saint-Gabriel-DE-Brandon",
    "sg:classifiers":[
        {
            "category":"Travel",
            "subcategory":"Campground",
            "type":"Entertainment"
        }
    ],
    "sg:phone":"+1 450 835 1649",
    "sg:postcode":"J0K 2N0",
    "sg:province":"QC",
    "wof:name":"Camping Soleil Le Vent",
    "wof:placetype":"venue"
},
  "geometry": {"coordinates":[-73.36318199999999,46.306637],"type":"Point"}
}