{
  "type": "Feature",
  "properties": {
    "addr:full":"Brandon MB R7A 3H6",
    "addr:postcode":"r7a 3h6",
    "iso:country":"CA",
    "sg:city":"Brandon",
    "sg:classifiers":[
        {
            "category":"Building & Trades",
            "subcategory":"Construction",
            "type":"Services"
        }
    ],
    "sg:phone":"+1 204 726 4084",
    "sg:postcode":"R7A 3H6",
    "sg:province":"MB",
    "sg:tags":[
        "tile",
        "dealer"
    ],
    "wof:name":"Tile Center",
    "wof:placetype":"venue"
},
  "geometry": {"coordinates":[-99.943031,49.838726],"type":"Point"}
}