{
  "type": "Feature",
  "properties": {
    "addr:full":"3474 Cedar Hill Rd Victoria BC V8P 3Z1",
    "addr:housenumber":"3474",
    "addr:postcode":"v8p 3z1",
    "addr:street":"Cedar Hill Rd",
    "iso:country":"CA",
    "sg:address":"3474 Cedar Hill Rd",
    "sg:city":"Victoria",
    "sg:classifiers":[
        {
            "category":"Health Services",
            "subcategory":"Chiropractor",
            "type":"Services"
        }
    ],
    "sg:phone":"+1 250 598 2199",
    "sg:postcode":"V8P 3Z1",
    "sg:province":"BC",
    "wof:name":"Pennimpede, Irene DC",
    "wof:placetype":"venue"
},
  "geometry": {"coordinates":[-123.34403228799999,48.4483108521],"type":"Point"}
}