{
  "type": "Feature",
  "properties": {
    "addr:full":"770 Grosvenor St Woodstock ON N4S 5G4",
    "addr:housenumber":"770",
    "addr:postcode":"n4s 5g4",
    "addr:street":"Grosvenor St",
    "iso:country":"CA",
    "sg:address":"770 Grosvenor St",
    "sg:city":"Woodstock",
    "sg:classifiers":[
        {
            "category":"Retail",
            "subcategory":"Repair Shop",
            "type":"Services"
        }
    ],
    "sg:phone":"+1 519 421 0891",
    "sg:postcode":"N4S 5G4",
    "sg:province":"ON",
    "sg:tags":[
        "lock",
        "locksmith"
    ],
    "wof:name":"Brad's Lock & Key",
    "wof:placetype":"venue"
},
  "geometry": {"coordinates":[-80.747444,43.140709],"type":"Point"}
}