{
  "type": "Feature",
  "properties": {
    "addr:full":"Brossard QC J4W 2T8",
    "addr:postcode":"j4w 2t8",
    "iso:country":"CA",
    "sg:city":"Brossard",
    "sg:classifiers":[
        {
            "category":"Health Services",
            "subcategory":"Doctor",
            "type":"Services"
        }
    ],
    "sg:phone":"+1 450 465 1220",
    "sg:postcode":"J4W 2T8",
    "sg:province":"QC",
    "sg:tags":[
        "dentist"
    ],
    "wof:name":"Samson, Michel DDS",
    "wof:placetype":"venue"
},
  "geometry": {"coordinates":[-73.474518,45.473713],"type":"Point"}
}