{
  "type": "Feature",
  "properties": {
    "addr:full":"1020 Rue Therrien Mont-Tremblant QC J8E 2Y6",
    "addr:housenumber":"1020",
    "addr:postcode":"j8e 2y6",
    "addr:street":"Rue Therrien",
    "iso:country":"CA",
    "sg:address":"1020 Rue Therrien",
    "sg:city":"Mont-Tremblant",
    "sg:classifiers":[
        {
            "category":"Manufacturing",
            "subcategory":"Lumber",
            "type":"Manufacturing & Wholesale Goods"
        }
    ],
    "sg:phone":"+1 819 425 6678",
    "sg:postcode":"J8E 2Y6",
    "sg:province":"QC",
    "sg:tags":[
        "forester"
    ],
    "wof:name":"Entreprises Forestieres",
    "wof:placetype":"venue"
},
  "geometry": {"coordinates":[-74.5962905884,46.1318321228],"type":"Point"}
}