{
  "type": "Feature",
  "properties": {
    "addr:full":"564 Pleasant Park Rd Ottawa ON K1H 5N1",
    "addr:housenumber":"564",
    "addr:postcode":"k1h 5n1",
    "addr:street":"Pleasant Park Rd",
    "iso:country":"CA",
    "sg:address":"564 Pleasant Park Rd",
    "sg:city":"Ottawa",
    "sg:classifiers":[
        {
            "category":"Education",
            "subcategory":"School",
            "type":"Public Place"
        }
    ],
    "sg:phone":"+1 613 733 5253",
    "sg:postcode":"K1H 5N1",
    "sg:province":"ON",
    "wof:name":"Pleasant Park School",
    "wof:placetype":"venue"
},
  "geometry": {"coordinates":[-75.64765199999999,45.394035],"type":"Point"}
}