{
  "type": "Feature",
  "properties": {
    "iso:country":"CA",
    "sg:address":"564 Pleasant Park Rd",
    "sg:city":"Ottawa",
    "sg:classifiers":[
        {
            "category":"Education",
            "subcategory":"School",
            "type":"Public Place"
        }
    ],
    "sg:phone":"+1 613 733 5253",
    "sg:postcode":"K1H 5N1",
    "sg:province":"ON",
    "wof:name":"Pleasant Park School",
    "wof:placetype":"venue"
},
  "geometry": {"coordinates":[-75.647652,45.394035],"type":"Point"}
}