{
  "type": "Feature",
  "properties": {
    "addr:full":"2900 Woodroffe Ave Nepean ON K2J 4G3",
    "addr:housenumber":"2900",
    "addr:postcode":"k2j 4g3",
    "addr:street":"Woodroffe Ave",
    "iso:country":"CA",
    "sg:address":"2900 Woodroffe Ave",
    "sg:city":"Nepean",
    "sg:classifiers":[
        {
            "category":"Personal",
            "subcategory":"Beauty Salon",
            "type":"Services"
        }
    ],
    "sg:phone":"+1 613 825 3232",
    "sg:postcode":"K2J 4G3",
    "sg:province":"ON",
    "wof:name":"Shear & Tan",
    "wof:placetype":"venue"
},
  "geometry": {"coordinates":[-75.728363,45.292973],"type":"Point"}
}