{
  "type": "Feature",
  "properties": {
    "iso:country":"CA",
    "sg:address":"2515 Beverly St",
    "sg:city":"Duncan",
    "sg:classifiers":[
        {
            "category":"Education",
            "subcategory":"School",
            "type":"Public Place"
        }
    ],
    "sg:phone":"+1 250 746 6168",
    "sg:postcode":"V9L 3A5",
    "sg:province":"BC",
    "wof:name":"Quamichan Middle School",
    "wof:placetype":"venue"
},
  "geometry": {"coordinates":[-123.708526611,48.7846641541],"type":"Point"}
}