{
  "type": "Feature",
  "properties": {
    "addr:full":"240 Place Salvail Pl Laval QC H7H 2S9",
    "addr:housenumber":"240",
    "addr:postcode":"h7h 2s9",
    "addr:street":"Place Salvail Pl",
    "iso:country":"CA",
    "sg:address":"240 Place Salvail Pl",
    "sg:city":"Laval",
    "sg:classifiers":[
        {
            "category":"Arts & Performance",
            "subcategory":"Theater",
            "type":"Entertainment"
        }
    ],
    "sg:phone":"+1 450 625 5557",
    "sg:postcode":"H7H 2S9",
    "sg:province":"QC",
    "sg:tags":[
        "mobile",
        "discotheque"
    ],
    "wof:name":"Disco Sauvageau",
    "wof:placetype":"venue"
},
  "geometry": {"coordinates":[-73.744637,45.551567],"type":"Point"}
}