{
  "type": "Feature",
  "properties": {
    "addr:full":"Richmond BC V7A 4X9",
    "addr:postcode":"v7a 4x9",
    "iso:country":"CA",
    "sg:city":"Richmond",
    "sg:classifiers":[
        {
            "category":"Wholesale",
            "subcategory":"Machinery & Supplies",
            "type":"Manufacturing & Wholesale Goods"
        }
    ],
    "sg:phone":"+1 604 277 2284",
    "sg:postcode":"V7A 4X9",
    "sg:province":"BC",
    "sg:tags":[
        "hair"
    ],
    "wof:name":"International Cosmeticare Inc",
    "wof:placetype":"venue"
},
  "geometry": {"coordinates":[-123.10024300000001,49.123962],"type":"Point"}
}