{
  "type": "Feature",
  "properties": {
    "addr:full":"1820 Mast Tower Rd Vancouver BC V6H 4B6",
    "addr:housenumber":"1820",
    "addr:postcode":"v6h 4b6",
    "addr:street":"Mast Tower Rd",
    "iso:country":"CA",
    "sg:address":"1820 Mast Tower Rd",
    "sg:city":"Vancouver",
    "sg:classifiers":[
        {
            "category":"Retail",
            "subcategory":"Repair Shop",
            "type":"Services"
        }
    ],
    "sg:phone":"+1 604 688 1088",
    "sg:postcode":"V6H 4B6",
    "sg:province":"BC",
    "sg:tags":[
        "upholsterer"
    ],
    "wof:name":"Granville Island Upholstery",
    "wof:placetype":"venue"
},
  "geometry": {"coordinates":[-123.136260986,49.2712745667],"type":"Point"}
}