{
  "type": "Feature",
  "properties": {
    "addr:full":"330 Rue Ellice Beauharnois QC J6N 1X3",
    "addr:housenumber":"330",
    "addr:postcode":"j6n 1x3",
    "addr:street":"Rue Ellice",
    "iso:country":"CA",
    "sg:address":"330 Rue Ellice",
    "sg:city":"Beauharnois",
    "sg:classifiers":[
        {
            "category":"Shopping",
            "subcategory":"Pharmacy",
            "type":"Retail Goods"
        }
    ],
    "sg:phone":"+1 450 429 3004",
    "sg:postcode":"J6N 1X3",
    "sg:province":"QC",
    "wof:name":"Pharmacie Michel Menard",
    "wof:placetype":"venue"
},
  "geometry": {"coordinates":[-73.8732757568,45.3146324158],"type":"Point"}
}