{
  "type": "Feature",
  "properties": {
    "addr:full":"3687 Boul Dagenais O Laval QC H7P 5C9",
    "addr:housenumber":"3687",
    "addr:postcode":"h7p 5c9",
    "addr:street":"Boul Dagenais O",
    "iso:country":"CA",
    "sg:address":"3687 Boul Dagenais O",
    "sg:city":"Laval",
    "sg:classifiers":[
        {
            "category":"Health Services",
            "subcategory":"Doctor",
            "type":"Services"
        }
    ],
    "sg:phone":"+1 450 625 9688",
    "sg:postcode":"H7P 5C9",
    "sg:province":"QC",
    "sg:tags":[
        "dentist"
    ],
    "wof:name":"Clinique Dentaire Talbot",
    "wof:placetype":"venue"
},
  "geometry": {"coordinates":[-73.8182296753,45.5731811523],"type":"Point"}
}