{
  "type": "Feature",
  "properties": {
    "iso:country":"CA",
    "sg:address":"307 Rideau St",
    "sg:city":"Ottawa",
    "sg:classifiers":[
        {
            "category":"Personal",
            "subcategory":"Barber",
            "type":"Services"
        }
    ],
    "sg:phone":"+1 613 789 3798",
    "sg:postcode":"K1N 5Y4",
    "sg:province":"ON",
    "wof:name":"Bern Hairstylist Shop",
    "wof:placetype":"venue"
},
  "geometry": {"coordinates":[-75.6851654053,45.4291915894],"type":"Point"}
}