{
  "type": "Feature",
  "properties": {
    "addr:full":"210 Telson Rd Markham ON L3R 1E6",
    "addr:housenumber":"210",
    "addr:postcode":"l3r 1e6",
    "addr:street":"Telson Rd",
    "iso:country":"CA",
    "sg:address":"210 Telson Rd",
    "sg:city":"Markham",
    "sg:classifiers":[
        {
            "category":"Wholesale",
            "subcategory":"Construction Materials",
            "type":"Manufacturing & Wholesale Goods"
        }
    ],
    "sg:phone":"+1 416 499 3508",
    "sg:postcode":"L3R 1E6",
    "sg:province":"ON",
    "sg:tags":[
        "marble"
    ],
    "wof:name":"Mirolin Industries Inc",
    "wof:placetype":"venue"
},
  "geometry": {"coordinates":[-79.338387,43.820946],"type":"Point"}
}