{
  "type": "Feature",
  "properties": {
    "addr:full":"Saint-Jerome QC J5L 1G2",
    "addr:postcode":"j5l 1g2",
    "iso:country":"CA",
    "sg:city":"Saint-Jerome",
    "sg:classifiers":[
        {
            "category":"Home & Garden",
            "subcategory":"Household Appliances",
            "type":"Retail Goods"
        }
    ],
    "sg:phone":"+1 450 438 7086",
    "sg:postcode":"J5L 1G2",
    "sg:province":"QC",
    "wof:name":"Jacques Lafontaine Inc",
    "wof:placetype":"venue"
},
  "geometry": {"coordinates":[-74.021973,45.754906],"type":"Point"}
}