{
  "type": "Feature",
  "properties": {
    "addr:full":"2900 Warden Ave # 217A Scarborough ON M1W 2S8",
    "addr:housenumber":"2900",
    "addr:postcode":"m1w 2s8",
    "addr:street":"Warden Ave # 217A",
    "iso:country":"CA",
    "sg:address":"2900 Warden Ave # 217A",
    "sg:city":"Scarborough",
    "sg:classifiers":[
        {
            "category":"Shopping",
            "subcategory":"Shoes",
            "type":"Retail Goods"
        }
    ],
    "sg:phone":"+1 416 497 8931",
    "sg:postcode":"M1W 2S8",
    "sg:province":"ON",
    "wof:name":"Payless Shoe Source",
    "wof:placetype":"venue"
},
  "geometry": {"coordinates":[-79.31596374510001,43.7968978882],"type":"Point"}
}