{
  "type": "Feature",
  "properties": {
    "addr:full":"Vancouver BC V6Z 2A9",
    "addr:postcode":"v6z 2a9",
    "iso:country":"CA",
    "sg:city":"Vancouver",
    "sg:classifiers":[
        {
            "category":"Professional",
            "subcategory":"Engineering",
            "type":"Services"
        }
    ],
    "sg:phone":"+1 604 684 5900",
    "sg:postcode":"V6Z 2A9",
    "sg:province":"BC",
    "sg:tags":[
        "engineer"
    ],
    "wof:name":"Bgc Engineering Inc",
    "wof:placetype":"venue"
},
  "geometry": {"coordinates":[-123.124786,49.279503],"type":"Point"}
}