{
  "type": "Feature",
  "properties": {
    "iso:country":"CA",
    "sg:city":"Ste-Famille-D'Aumond",
    "sg:classifiers":[
        {
            "category":"Food & Beverages",
            "subcategory":"Groceries & Convenience Stores",
            "type":"Retail Goods"
        }
    ],
    "sg:phone":"+1 819 449 4646",
    "sg:postcode":"J0W 1W0",
    "sg:province":"QC",
    "wof:name":"Epicerie Aumond",
    "wof:placetype":"venue"
},
  "geometry": {"coordinates":[-75.84944915769999,46.4713668823],"type":"Point"}
}