{
  "type": "Feature",
  "properties": {
    "iso:country":"CA",
    "sg:city":"London",
    "sg:classifiers":[
        {
            "category":"Professional",
            "subcategory":"Engineering",
            "type":"Services"
        }
    ],
    "sg:phone":"+1 519 471 0033",
    "sg:postcode":"N6H 5L7",
    "sg:province":"ON",
    "sg:tags":[
        "engineer"
    ],
    "wof:name":"K T Engineering Assoc",
    "wof:placetype":"venue"
},
  "geometry": {"coordinates":[-81.333664,43.00164],"type":"Point"}
}