{
  "type": "Feature",
  "properties": {
    "addr:full":"16 Huron St Collingwood ON L9Y 1C4",
    "addr:housenumber":"16",
    "addr:postcode":"l9y 1c4",
    "addr:street":"Huron St",
    "iso:country":"CA",
    "sg:address":"16 Huron St",
    "sg:city":"Collingwood",
    "sg:classifiers":[
        {
            "category":"Shopping",
            "subcategory":"Gifts & Souvenirs",
            "type":"Retail Goods"
        }
    ],
    "sg:phone":"+1 705 445 0125",
    "sg:postcode":"L9Y 1C4",
    "sg:province":"ON",
    "sg:tags":[
        "novelty"
    ],
    "wof:name":"Passionate Kisses Too",
    "wof:placetype":"venue"
},
  "geometry": {"coordinates":[-80.216537,44.502766],"type":"Point"}
}