{
  "type": "Feature",
  "properties": {
    "addr:full":"1944 Peninsula Rd Ucluelet BC V0R 3A0",
    "addr:housenumber":"1944",
    "addr:postcode":"bc v0r 3a0",
    "addr:street":"Peninsula Rd",
    "iso:country":"CA",
    "sg:address":"1944 Peninsula Rd",
    "sg:city":"Ucluelet",
    "sg:classifiers":[
        {
            "category":"Retail",
            "subcategory":"Auto Repair",
            "type":"Services"
        }
    ],
    "sg:phone":"+1 250 726 4221",
    "sg:postcode":"V0R 3A0",
    "sg:province":"BC",
    "sg:tags":[
        "wrecker"
    ],
    "wof:name":"Noel Enterprises Ltd",
    "wof:placetype":"venue"
},
  "geometry": {"coordinates":[-125.542610169,48.9380264282],"type":"Point"}
}