{
  "type": "Feature",
  "properties": {
    "iso:country":"CA",
    "sg:address":"2001 18 Ave SW",
    "sg:city":"Calgary",
    "sg:classifiers":[
        {
            "category":"Organizations",
            "subcategory":"Professional Association",
            "type":"Services"
        }
    ],
    "sg:phone":"+1 403 245 1282",
    "sg:postcode":"T2T 0H4",
    "sg:province":"AB",
    "wof:name":"Scouts Canada",
    "wof:placetype":"venue"
},
  "geometry": {"coordinates":[-114.106269836,51.0368995667],"type":"Point"}
}