{
  "type": "Feature",
  "properties": {
    "addr:full":"Belmont ON N0L 1B0",
    "addr:postcode":"n0l 1b0",
    "iso:country":"CA",
    "sg:city":"Belmont",
    "sg:classifiers":[
        {
            "category":"Personal",
            "subcategory":"Beauty Salon",
            "type":"Services"
        }
    ],
    "sg:phone":"+1 519 644 0380",
    "sg:postcode":"N0L 1B0",
    "sg:province":"ON",
    "wof:name":"Joe's Beauty Salon",
    "wof:placetype":"venue"
},
  "geometry": {"coordinates":[-81.088882,42.886074],"type":"Point"}
}