{
  "type": "Feature",
  "properties": {
    "addr:full":"199 Steelcase Rd W Markham ON L3R 2M4",
    "addr:housenumber":"199",
    "addr:postcode":"l3r 2m4",
    "addr:street":"Steelcase Rd W",
    "iso:country":"CA",
    "sg:address":"199 Steelcase Rd W",
    "sg:city":"Markham",
    "sg:classifiers":[
        {
            "category":"Manufacturing",
            "subcategory":"Printing",
            "type":"Manufacturing & Wholesale Goods"
        }
    ],
    "sg:phone":"+1 905 475 3242",
    "sg:postcode":"L3R 2M4",
    "sg:province":"ON",
    "sg:tags":[
        "printer"
    ],
    "wof:name":"Stanley Printing CO",
    "wof:placetype":"venue"
},
  "geometry": {"coordinates":[-79.35855865480001,43.8199462891],"type":"Point"}
}