{
  "type": "Feature",
  "properties": {
    "addr:full":"16 Complex Dr Wikwemikong ON P0P 2J0",
    "addr:housenumber":"16",
    "addr:postcode":"p0p 2j0",
    "addr:street":"Complex Dr",
    "iso:country":"CA",
    "sg:address":"16 Complex Dr",
    "sg:city":"Wikwemikong",
    "sg:classifiers":[
        {
            "category":"Health Services",
            "subcategory":"Doctor",
            "type":"Services"
        }
    ],
    "sg:phone":"+1 705 859 3476",
    "sg:postcode":"P0P 2J0",
    "sg:province":"ON",
    "sg:tags":[
        "dentist"
    ],
    "wof:name":"Wikwemikong Dental Office",
    "wof:placetype":"venue"
},
  "geometry": {"coordinates":[-81.728477,45.797279],"type":"Point"}
}