{
  "type": "Feature",
  "properties": {
    "addr:full":"244 Augusta Ave Toronto ON M5T 2L7",
    "addr:housenumber":"244",
    "addr:postcode":"m5t 2l7",
    "addr:street":"Augusta Ave",
    "iso:country":"CA",
    "sg:address":"244 Augusta Ave",
    "sg:city":"Toronto",
    "sg:classifiers":[
        {
            "category":"Home & Garden",
            "subcategory":"Furniture",
            "type":"Retail Goods"
        }
    ],
    "sg:phone":"+1 416 603 9093",
    "sg:postcode":"M5T 2L7",
    "sg:province":"ON",
    "wof:name":"Miramar Furniture & Appliances",
    "wof:placetype":"venue"
},
  "geometry": {"coordinates":[-79.4026641846,43.6556549072],"type":"Point"}
}