{
  "type": "Feature",
  "properties": {
    "addr:full":"9775 Rue Tolhurst Montreal QC H3L 2Z7",
    "addr:housenumber":"9775",
    "addr:postcode":"h3l 2z7",
    "addr:street":"Rue Tolhurst",
    "iso:country":"CA",
    "sg:address":"9775 Rue Tolhurst",
    "sg:city":"Montreal",
    "sg:classifiers":[
        {
            "category":"Restaurant",
            "type":"Food & Drink"
        }
    ],
    "sg:phone":"+1 514 385 0002",
    "sg:postcode":"H3L 2Z7",
    "sg:province":"QC",
    "sg:tags":[
        "caterer"
    ],
    "wof:name":"Ernie the Caterer Inc",
    "wof:placetype":"venue"
},
  "geometry": {"coordinates":[-73.6617736816,45.5426177979],"type":"Point"}
}