{
  "type": "Feature",
  "properties": {
    "addr:full":"411 Bradwick Dr Concord ON L4K 2P4",
    "addr:housenumber":"411",
    "addr:postcode":"l4k 2p4",
    "addr:street":"Bradwick Dr",
    "iso:country":"CA",
    "sg:address":"411 Bradwick Dr",
    "sg:city":"Concord",
    "sg:classifiers":[
        {
            "category":"Wholesale",
            "subcategory":"Home Furnishings",
            "type":"Manufacturing & Wholesale Goods"
        }
    ],
    "sg:phone":"+1 905 738 8218",
    "sg:postcode":"L4K 2P4",
    "sg:province":"ON",
    "sg:tags":[
        "closet",
        "accessory"
    ],
    "wof:name":"Hang Up Custom Closet & Mirror",
    "wof:placetype":"venue"
},
  "geometry": {"coordinates":[-79.48211669920001,43.8166694641],"type":"Point"}
}