{
  "type": "Feature",
  "properties": {
    "iso:country":"CA",
    "sg:address":"1 Rue Beausoleil",
    "sg:city":"Beaupre",
    "sg:classifiers":[
        {
            "category":"Travel",
            "subcategory":"Hotels & Motels",
            "type":"Entertainment"
        }
    ],
    "sg:phone":"+1 418 827 5776",
    "sg:postcode":"G0A 1E0",
    "sg:province":"QC",
    "sg:tags":[
        "cottage",
        "reservation",
        "cabin"
    ],
    "wof:name":"Chalets Mont Ste-Anne",
    "wof:placetype":"venue"
},
  "geometry": {"coordinates":[-70.9058456421,47.0718688965],"type":"Point"}
}