{
  "type": "Feature",
  "properties": {
    "iso:country":"CA",
    "sg:address":"352 Av Dorval # 7",
    "sg:city":"Dorval",
    "sg:classifiers":[
        {
            "category":"Personal",
            "subcategory":"Beauty Salon",
            "type":"Services"
        }
    ],
    "sg:phone":"+1 514 631 0808",
    "sg:postcode":"H9S 3H8",
    "sg:province":"QC",
    "sg:tags":[
        "manicuring"
    ],
    "wof:name":"Jolis Ongles",
    "wof:placetype":"venue"
},
  "geometry": {"coordinates":[-73.7411117554,45.4441452026],"type":"Point"}
}