{
  "type": "Feature",
  "properties": {
    "iso:country":"CA",
    "sg:address":"1215 Frances St",
    "sg:city":"Vancouver",
    "sg:classifiers":[
        {
            "category":"Retail",
            "subcategory":"Auto Repair",
            "type":"Services"
        }
    ],
    "sg:phone":"+1 604 251 6600",
    "sg:postcode":"V6A 1Z4",
    "sg:province":"BC",
    "sg:tags":[
        "repairing",
        "automobile"
    ],
    "wof:name":"Loyale Automotive",
    "wof:placetype":"venue"
},
  "geometry": {"coordinates":[-123.078742981,49.2795906067],"type":"Point"}
}