{
  "type": "Feature",
  "properties": {
    "addr:full":"1049 7th Ave Hanover ON N4N 2K4",
    "addr:housenumber":"1049",
    "addr:postcode":"n4n 2k4",
    "addr:street":"7Th Ave",
    "iso:country":"CA",
    "sg:address":"1049 7th Ave",
    "sg:city":"Hanover",
    "sg:classifiers":[
        {
            "category":"Retail",
            "subcategory":"Laundry & Dry Cleaning",
            "type":"Services"
        }
    ],
    "sg:phone":"+1 519 364 1317",
    "sg:postcode":"N4N 2K4",
    "sg:province":"ON",
    "sg:tags":[
        "cleaners",
        "rug",
        "carpet"
    ],
    "wof:name":"Durrer Carpet Svc Ltd",
    "wof:placetype":"venue"
},
  "geometry": {"coordinates":[-81.0351867676,44.1676559448],"type":"Point"}
}