{
  "type": "Feature",
  "properties": {
    "addr:full":"Calgary AB T2G 2R7",
    "addr:postcode":"t2g 2r7",
    "iso:country":"CA",
    "sg:city":"Calgary",
    "sg:classifiers":[
        {
            "category":"Real Estate",
            "subcategory":"Architect",
            "type":"Services"
        }
    ],
    "sg:phone":"+1 403 287 3530",
    "sg:postcode":"T2G 2R7",
    "sg:province":"AB",
    "wof:name":"John Barlot Ltd",
    "wof:placetype":"venue"
},
  "geometry": {"coordinates":[-114.062645,51.018215],"type":"Point"}
}