{
  "type": "Feature",
  "properties": {
    "addr:full":"5015 48 St Red Deer AB T4N 1S9",
    "addr:housenumber":"5015",
    "addr:postcode":"t4n 1s9",
    "addr:street":"48 St",
    "iso:country":"CA",
    "sg:address":"5015 48 St",
    "sg:city":"Red Deer",
    "sg:classifiers":[
        {
            "category":"Education",
            "subcategory":"School",
            "type":"Public Place"
        }
    ],
    "sg:phone":"+1 403 343 1354",
    "sg:postcode":"T4N 1S9",
    "sg:province":"AB",
    "wof:name":"Outreach School Ctr",
    "wof:placetype":"venue"
},
  "geometry": {"coordinates":[-113.81632232699999,52.266910553],"type":"Point"}
}