{
  "type": "Feature",
  "properties": {
    "iso:country":"CA",
    "sg:address":"981 Wellington Rd",
    "sg:city":"London",
    "sg:classifiers":[
        {
            "category":"Shopping",
            "subcategory":"Shoes",
            "type":"Retail Goods"
        }
    ],
    "sg:phone":"+1 519 681 9498",
    "sg:postcode":"N6E 3A9",
    "sg:province":"ON",
    "wof:name":"Tallcrest Shoes",
    "wof:placetype":"venue"
},
  "geometry": {"coordinates":[-81.2250289917,42.9396095276],"type":"Point"}
}