{
  "type": "Feature",
  "properties": {
    "addr:full":"15 Niagara St Welland ON L3C 1H8",
    "addr:housenumber":"15",
    "addr:postcode":"l3c 1h8",
    "addr:street":"Niagara St",
    "iso:country":"CA",
    "sg:address":"15 Niagara St",
    "sg:city":"Welland",
    "sg:classifiers":[
        {
            "category":"Personal",
            "subcategory":"Beauty Salon",
            "type":"Services"
        }
    ],
    "sg:phone":"+1 905 734 4156",
    "sg:postcode":"L3C 1H8",
    "sg:province":"ON",
    "wof:name":"Niagara Hair Design",
    "wof:placetype":"venue"
},
  "geometry": {"coordinates":[-79.252838,42.991901],"type":"Point"}
}