{
  "type": "Feature",
  "properties": {
    "addr:full":"Oshawa ON L1G 3R5",
    "addr:postcode":"l1g 3r5",
    "iso:country":"CA",
    "sg:city":"Oshawa",
    "sg:classifiers":[
        {
            "category":"Home & Garden",
            "subcategory":"Building Materials",
            "type":"Retail Goods"
        }
    ],
    "sg:phone":"+1 905 728 9660",
    "sg:postcode":"L1G 3R5",
    "sg:province":"ON",
    "sg:tags":[
        "glass",
        "window",
        "plate"
    ],
    "wof:name":"A Apple Auto Glass",
    "wof:placetype":"venue"
},
  "geometry": {"coordinates":[-78.880959,43.930168],"type":"Point"}
}