{
  "type": "Feature",
  "properties": {
    "addr:full":"227 King St Midland ON L4R 3M1",
    "addr:housenumber":"227",
    "addr:postcode":"l4r 3m1",
    "addr:street":"King St",
    "iso:country":"CA",
    "sg:address":"227 King St",
    "sg:city":"Midland",
    "sg:classifiers":[
        {
            "category":"Cinema",
            "subcategory":"Movie Rental",
            "type":"Entertainment"
        }
    ],
    "sg:phone":"+1 705 527 0123",
    "sg:postcode":"L4R 3M1",
    "sg:province":"ON",
    "sg:tags":[
        "leasing",
        "video",
        "disc",
        "tape"
    ],
    "wof:name":"Downtown Video",
    "wof:placetype":"venue"
},
  "geometry": {"coordinates":[-79.886421,44.751411],"type":"Point"}
}