{
  "type": "Feature",
  "properties": {
    "addr:full":"198 King St St Stephen NB E3L 2E2",
    "addr:housenumber":"198",
    "addr:postcode":"nb e3l 2e2",
    "addr:street":"King St",
    "iso:country":"CA",
    "sg:address":"198 King St",
    "sg:city":"St Stephen",
    "sg:classifiers":[
        {
            "category":"Travel",
            "subcategory":"Hotels & Motels",
            "type":"Entertainment"
        }
    ],
    "sg:phone":"+1 506 466 2130",
    "sg:postcode":"E3L 2E2",
    "sg:province":"NB",
    "wof:name":"Winsome Inn",
    "wof:placetype":"venue"
},
  "geometry": {"coordinates":[-67.2735748291,45.20129776],"type":"Point"}
}