{
  "type": "Feature",
  "properties": {
    "addr:full":"PO Box 338 Fort Vermilion AB T0H 1N0",
    "addr:housenumber":"po",
    "addr:postcode":"t0h 1n0",
    "addr:street":"Box 338 Fort",
    "iso:country":"CA",
    "sg:address":"PO Box 338",
    "sg:city":"Fort Vermilion",
    "sg:classifiers":[
        {
            "category":"Sports & Exercise",
            "subcategory":"Golf",
            "type":"Entertainment"
        }
    ],
    "sg:phone":"+1 780 927 4800",
    "sg:postcode":"T0H 1N0",
    "sg:province":"AB",
    "sg:tags":[
        "course"
    ],
    "wof:name":"Fantasy North Golf Course & Rv",
    "wof:placetype":"venue"
},
  "geometry": {"coordinates":[-110.858521,53.351669],"type":"Point"}
}