{
  "type": "Feature",
  "properties": {
    "addr:full":"Castlegar BC V1N 2W1",
    "addr:postcode":"v1n 2w1",
    "iso:country":"CA",
    "sg:city":"Castlegar",
    "sg:classifiers":[
        {
            "category":"Manufacturing",
            "subcategory":"Printing",
            "type":"Manufacturing & Wholesale Goods"
        }
    ],
    "sg:phone":"+1 250 365 2323",
    "sg:postcode":"V1N 2W1",
    "sg:province":"BC",
    "sg:tags":[
        "equipment",
        "multimedia",
        "computer",
        "dealer"
    ],
    "wof:name":"Kootenay Computers Inc",
    "wof:placetype":"venue"
},
  "geometry": {"coordinates":[-117.65418200000001,49.296249],"type":"Point"}
}