{
  "type": "Feature",
  "properties": {
    "addr:full":"2 Pembina Rd Sherwood Park AB T8H 2G9",
    "addr:housenumber":"2",
    "addr:postcode":"t8h 2g9",
    "addr:street":"Pembina Rd",
    "iso:country":"CA",
    "sg:address":"2 Pembina Rd",
    "sg:city":"Sherwood Park",
    "sg:classifiers":[
        {
            "category":"Food & Beverages",
            "subcategory":"Bakery",
            "type":"Retail Goods"
        }
    ],
    "sg:phone":"+1 780 417 4643",
    "sg:postcode":"T8H 2G9",
    "sg:province":"AB",
    "sg:tags":[
        "shop",
        "doughnut",
        "coffee"
    ],
    "wof:name":"Tim Hortons",
    "wof:placetype":"venue"
},
  "geometry": {"coordinates":[-113.319489,53.565857],"type":"Point"}
}