{
  "type": "Feature",
  "properties": {
    "iso:country":"CA",
    "sg:city":"Le Gardeur",
    "sg:classifiers":[
        {
            "category":"Wholesale",
            "subcategory":"Stationery",
            "type":"Manufacturing & Wholesale Goods"
        }
    ],
    "sg:phone":"+1 514 640 9111",
    "sg:postcode":"J5Z 4C7",
    "sg:province":"QC",
    "sg:tags":[
        "sanitary",
        "product",
        "supply"
    ],
    "wof:name":"Produits Sanitaires Royal-Net",
    "wof:placetype":"venue"
},
  "geometry": {"coordinates":[-73.487984,45.76091],"type":"Point"}
}