{
  "type": "Feature",
  "properties": {
    "addr:full":"14 Rue Richard Cap-Pele NB E4N 1Y3",
    "addr:housenumber":"14",
    "addr:postcode":"e4n 1y3",
    "addr:street":"Rue Richard",
    "iso:country":"CA",
    "sg:address":"14 Rue Richard",
    "sg:city":"Cap-Pele",
    "sg:phone":"+1 506 577 4250",
    "sg:postcode":"E4N 1Y3",
    "sg:province":"NB",
    "sg:tags":[
        "equipment",
        "station"
    ],
    "wof:name":"J P Pump Svc",
    "wof:placetype":"venue"
},
  "geometry": {"coordinates":[-64.25866699220001,46.212677002],"type":"Point"}
}