{
  "type": "Feature",
  "properties": {
    "addr:full":"42 Jason Ave North Tetagouche NB E2A 4Y8",
    "addr:housenumber":"42",
    "addr:postcode":"e2a 4y8",
    "addr:street":"Jason Ave North",
    "iso:country":"CA",
    "sg:address":"42 Jason Ave",
    "sg:city":"North Tetagouche",
    "sg:classifiers":[
        {
            "category":"Building & Trades",
            "subcategory":"Construction",
            "type":"Services"
        }
    ],
    "sg:phone":"+1 506 548 5714",
    "sg:postcode":"E2A 4Y8",
    "sg:province":"NB",
    "sg:tags":[
        "masonry",
        "contractor"
    ],
    "wof:name":"Ljb Masonry & Svc",
    "wof:placetype":"venue"
},
  "geometry": {"coordinates":[-65.744392,47.638206],"type":"Point"}
}