{
  "type": "Feature",
  "properties": {
    "addr:full":"1032 Victoria Ave Windsor ON N9A 4N6",
    "addr:housenumber":"1032",
    "addr:postcode":"n9a 4n6",
    "addr:street":"Victoria Ave",
    "iso:country":"CA",
    "sg:address":"1032 Victoria Ave",
    "sg:city":"Windsor",
    "sg:classifiers":[
        {
            "category":"Real Estate",
            "subcategory":"Real Estate Agent",
            "type":"Services"
        }
    ],
    "sg:phone":"+1 519 255 7330",
    "sg:postcode":"N9A 4N6",
    "sg:province":"ON",
    "wof:name":"Step Saver Real Estate Inc",
    "wof:placetype":"venue"
},
  "geometry": {"coordinates":[-83.034904,42.307709],"type":"Point"}
}