{
  "type": "Feature",
  "properties": {
    "addr:full":"Waterloo ON N2L 6H7",
    "addr:postcode":"n2l 6h7",
    "iso:country":"CA",
    "sg:city":"Waterloo",
    "sg:classifiers":[
        {
            "category":"Building & Trades",
            "subcategory":"Plumbing",
            "type":"Services"
        }
    ],
    "sg:phone":"+1 519 747 3502",
    "sg:postcode":"N2L 6H7",
    "sg:province":"ON",
    "sg:tags":[
        "conditioning",
        "air",
        "system",
        "contractor"
    ],
    "wof:name":"Elite Air Inc",
    "wof:placetype":"venue"
},
  "geometry": {"coordinates":[-80.5385971069,43.4939689636],"type":"Point"}
}