{
  "type": "Feature",
  "properties": {
    "addr:full":"4857 Boul Bourque Rock Forest QC J1N 1E8",
    "addr:housenumber":"4857",
    "addr:postcode":"j1n 1e8",
    "addr:street":"Boul Bourque",
    "iso:country":"CA",
    "sg:address":"4857 Boul Bourque",
    "sg:city":"Rock Forest",
    "sg:classifiers":[
        {
            "category":"Real Estate",
            "subcategory":"Real Estate Operator",
            "type":"Services"
        }
    ],
    "sg:phone":"+1 819 564 0120",
    "sg:postcode":"J1N 1E8",
    "sg:province":"QC",
    "sg:tags":[
        "mall",
        "shopping",
        "center"
    ],
    "wof:name":"Terrasses Rock Forest Ctr",
    "wof:placetype":"venue"
},
  "geometry": {"coordinates":[-71.9866027832,45.3724403381],"type":"Point"}
}