{
  "type": "Feature",
  "properties": {
    "addr:full":"Calgary AB T2E 2N3",
    "addr:postcode":"t2e 2n3",
    "iso:country":"CA",
    "sg:city":"Calgary",
    "sg:classifiers":[
        {
            "category":"Building & Trades",
            "subcategory":"Plumbing",
            "type":"Services"
        }
    ],
    "sg:phone":"+1 403 230 0580",
    "sg:postcode":"T2E 2N3",
    "sg:province":"AB",
    "sg:tags":[
        "mechanical",
        "contractor"
    ],
    "wof:name":"Larmco Industries Ltd",
    "wof:placetype":"venue"
},
  "geometry": {"coordinates":[-114.05766300000001,51.090153],"type":"Point"}
}