{
  "type": "Feature",
  "properties": {
    "addr:full":"3555 Forest Glade Dr Windsor ON N8R 1X8",
    "addr:housenumber":"3555",
    "addr:postcode":"n8r 1x8",
    "addr:street":"Forest Glade Dr",
    "iso:country":"CA",
    "sg:address":"3555 Forest Glade Dr",
    "sg:city":"Windsor",
    "sg:classifiers":[
        {
            "category":"Education",
            "subcategory":"School",
            "type":"Public Place"
        }
    ],
    "sg:phone":"+1 519 735 6087",
    "sg:postcode":"N8R 1X8",
    "sg:province":"ON",
    "wof:name":"Eastwood Public Elementary",
    "wof:placetype":"venue"
},
  "geometry": {"coordinates":[-82.92357635499999,42.2996139526],"type":"Point"}
}