{
  "type": "Feature",
  "properties": {
    "addr:full":"2558 Danforth Ave Toronto ON M4C 1L3",
    "addr:housenumber":"2558",
    "addr:postcode":"m4c 1l3",
    "addr:street":"Danforth Ave",
    "iso:country":"CA",
    "sg:address":"2558 Danforth Ave",
    "sg:city":"Toronto",
    "sg:classifiers":[
        {
            "category":"Health Services",
            "subcategory":"Doctor",
            "type":"Services"
        }
    ],
    "sg:phone":"+1 416 690 2438",
    "sg:postcode":"M4C 1L3",
    "sg:province":"ON",
    "sg:tags":[
        "dentist"
    ],
    "wof:name":"Dental Office",
    "wof:placetype":"venue"
},
  "geometry": {"coordinates":[-79.301582,43.68832],"type":"Point"}
}