{
  "type": "Feature",
  "properties": {
    "addr:full":"1500 Boul DE Maisonneuve O Montreal QC H3G 1N1",
    "addr:housenumber":"1500",
    "addr:postcode":"h3g 1n1",
    "addr:street":"Boul De Maisonneuve O",
    "iso:country":"CA",
    "sg:address":"1500 Boul DE Maisonneuve O",
    "sg:city":"Montreal",
    "sg:classifiers":[
        {
            "category":"Professional",
            "subcategory":"Computer Services",
            "type":"Services"
        }
    ],
    "sg:phone":"+1 514 395 1026",
    "sg:postcode":"H3G 1N1",
    "sg:province":"QC",
    "sg:tags":[
        "information",
        "system",
        "consultant"
    ],
    "wof:name":"Proc-Data Si Inc",
    "wof:placetype":"venue"
},
  "geometry": {"coordinates":[-73.555313,45.521378],"type":"Point"}
}