{
  "type": "Feature",
  "properties": {
    "addr:full":"9 Laxton Twp 5th Line Coboconk ON K0M 1K0",
    "addr:housenumber":"9;twp",
    "addr:postcode":"k0m 1k0",
    "addr:street":"Laxton;5Th Line",
    "iso:country":"CA",
    "sg:address":"9 Laxton Twp 5th Line",
    "sg:city":"Coboconk",
    "sg:classifiers":[
        {
            "category":"Building & Trades",
            "subcategory":"Construction",
            "type":"Services"
        }
    ],
    "sg:phone":"+1 705 454 3693",
    "sg:postcode":"K0M 1K0",
    "sg:province":"ON",
    "sg:tags":[
        "masonry",
        "contractor"
    ],
    "wof:name":"Baldwin Masonry",
    "wof:placetype":"venue"
},
  "geometry": {"coordinates":[-78.797676,44.658997],"type":"Point"}
}