{
  "type": "Feature",
  "properties": {
    "iso:country":"CA",
    "sg:address":"110 Cumberland St",
    "sg:city":"Toronto",
    "sg:classifiers":[
        {
            "category":"Shopping",
            "subcategory":"Clothing, Apparel, & Fashions",
            "type":"Retail Goods"
        }
    ],
    "sg:phone":"+1 416 921 3116",
    "sg:postcode":"M5R 1A6",
    "sg:province":"ON",
    "sg:tags":[
        "maternity"
    ],
    "wof:name":"Rhonda Maternity",
    "wof:placetype":"venue"
},
  "geometry": {"coordinates":[-79.391708374,43.6703033447],"type":"Point"}
}