{
  "type": "Feature",
  "properties": {
    "addr:full":"Toronto ON M6E 1B5",
    "addr:postcode":"m6e 1b5",
    "iso:country":"CA",
    "sg:city":"Toronto",
    "sg:classifiers":[
        {
            "category":"Personal",
            "subcategory":"Beauty Salon",
            "type":"Services"
        }
    ],
    "sg:phone":"+1 416 656 0412",
    "sg:postcode":"M6E 1B5",
    "sg:province":"ON",
    "wof:name":"Elle Esthetics Ltd",
    "wof:placetype":"venue"
},
  "geometry": {"coordinates":[-79.444480896,43.6774902344],"type":"Point"}
}