{
  "type": "Feature",
  "properties": {
    "iso:country":"CA",
    "sg:address":"434804 Zorra Line",
    "sg:city":"Beachville",
    "sg:classifiers":[
        {
            "category":"Education",
            "subcategory":"School",
            "type":"Public Place"
        }
    ],
    "sg:phone":"+1 519 423 1939",
    "sg:postcode":"N0J 1A0",
    "sg:province":"ON",
    "wof:name":"Beachville Public School",
    "wof:placetype":"venue"
},
  "geometry": {"coordinates":[-80.8307418823,43.0914077759],"type":"Point"}
}