{
  "type": "Feature",
  "properties": {
    "addr:full":"Victoria BC V8Z 3P3",
    "addr:postcode":"v8z 3p3",
    "iso:country":"CA",
    "sg:city":"Victoria",
    "sg:classifiers":[
        {
            "category":"Freight",
            "type":"Transportation"
        }
    ],
    "sg:phone":"+1 250 953 5330",
    "sg:postcode":"V8Z 3P3",
    "sg:province":"BC",
    "sg:tags":[
        "commercial",
        "storage"
    ],
    "wof:name":"Adams Town & Country Storage",
    "wof:placetype":"venue"
},
  "geometry": {"coordinates":[-123.377831,48.450169],"type":"Point"}
}