{
  "type": "Feature",
  "properties": {
    "addr:full":"357 Raglan St S Renfrew ON K7V 1R6",
    "addr:housenumber":"357",
    "addr:postcode":"k7v 1r6",
    "addr:street":"Raglan St S",
    "iso:country":"CA",
    "sg:address":"357 Raglan St S",
    "sg:city":"Renfrew",
    "sg:classifiers":[
        {
            "category":"Government",
            "subcategory":"Office",
            "type":"Public Place"
        }
    ],
    "sg:phone":"+1 613 432 4886",
    "sg:postcode":"K7V 1R6",
    "sg:province":"ON",
    "wof:name":"Ontario Employment Supports",
    "wof:placetype":"venue"
},
  "geometry": {"coordinates":[-76.6810455322,45.4696388245],"type":"Point"}
}