{
  "type": "Feature",
  "properties": {
    "addr:full":"10527 96 St NW Edmonton AB T5H 2H6",
    "addr:housenumber":"10527",
    "addr:postcode":"t5h 2h6",
    "addr:street":"96 St Nw",
    "iso:country":"CA",
    "sg:address":"10527 96 St NW",
    "sg:city":"Edmonton",
    "sg:classifiers":[
        {
            "category":"Social Services",
            "type":"Services"
        }
    ],
    "sg:phone":"+1 780 423 2285",
    "sg:postcode":"T5H 2H6",
    "sg:province":"AB",
    "sg:tags":[
        "organization",
        "welfare"
    ],
    "wof:name":"Bissell Centre",
    "wof:placetype":"venue"
},
  "geometry": {"coordinates":[-113.484634399,53.5496330261],"type":"Point"}
}