{
  "type": "Feature",
  "properties": {
    "addr:full":"85 William St S Chatham ON N7M 4S5",
    "addr:housenumber":"85",
    "addr:postcode":"n7m 4s5",
    "addr:street":"William St S",
    "iso:country":"CA",
    "sg:address":"85 William St S",
    "sg:city":"Chatham",
    "sg:classifiers":[
        {
            "category":"Organizations",
            "subcategory":"Religious Organization",
            "type":"Services"
        }
    ],
    "sg:phone":"+1 519 352 0010",
    "sg:postcode":"N7M 4S5",
    "sg:province":"ON",
    "sg:tags":[
        "church"
    ],
    "wof:name":"St Andrew's United Church",
    "wof:placetype":"venue"
},
  "geometry": {"coordinates":[-82.18042,42.403229],"type":"Point"}
}