{
  "type": "Feature",
  "properties": {
    "addr:full":"Kensington PE C0B 1M0",
    "addr:postcode":"c0b 1m0",
    "iso:country":"CA",
    "sg:city":"Kensington",
    "sg:classifiers":[
        {
            "category":"Restaurant",
            "type":"Food & Drink"
        }
    ],
    "sg:phone":"+1 902 836 5055",
    "sg:postcode":"C0B 1M0",
    "sg:province":"PE",
    "wof:name":"Lotus Garden Restaurant",
    "wof:placetype":"venue"
},
  "geometry": {"coordinates":[-63.6373901367,46.4371261597],"type":"Point"}
}