{
  "type": "Feature",
  "properties": {
    "addr:full":"3711 Lawrence Ave E Scarborough ON M1G 1P7",
    "addr:housenumber":"3711",
    "addr:postcode":"m1g 1p7",
    "addr:street":"Lawrence Ave E",
    "iso:country":"CA",
    "sg:address":"3711 Lawrence Ave E",
    "sg:city":"Scarborough",
    "sg:classifiers":[
        {
            "category":"Shopping",
            "subcategory":"Clothing, Apparel, & Fashions",
            "type":"Retail Goods"
        }
    ],
    "sg:phone":"+1 416 439 5088",
    "sg:postcode":"M1G 1P7",
    "sg:province":"ON",
    "sg:tags":[
        "furnishing"
    ],
    "wof:name":"Moore's the Suit People",
    "wof:placetype":"venue"
},
  "geometry": {"coordinates":[-79.2200469971,43.7607841492],"type":"Point"}
}