{
  "type": "Feature",
  "properties": {
    "addr:full":"Hudson Blind River ON P0R 1B0",
    "addr:postcode":"p0r 1b0",
    "iso:country":"CA",
    "sg:address":"Hudson",
    "sg:city":"Blind River",
    "sg:classifiers":[
        {
            "category":"Government",
            "subcategory":"Fire Station",
            "type":"Public Place"
        }
    ],
    "sg:phone":"+1 ",
    "sg:postcode":"P0R 1B0",
    "sg:province":"ON",
    "sg:tags":[
        "department"
    ],
    "wof:name":"Blind River Fire Dept",
    "wof:placetype":"venue"
},
  "geometry": {"coordinates":[-82.9604110718,46.1881217957],"type":"Point"}
}