{
  "type": "Feature",
  "properties": {
    "iso:country":"CA",
    "sg:address":"520 Rue Principale",
    "sg:city":"Pohenegamook",
    "sg:classifiers":[
        {
            "category":"Farming",
            "subcategory":"Farm",
            "type":"Manufacturing & Wholesale Goods"
        }
    ],
    "sg:phone":"+1 418 893 5225",
    "sg:postcode":"G0L 1J0",
    "sg:province":"QC",
    "wof:name":"Ferme Roy & Fils Inc",
    "wof:placetype":"venue"
},
  "geometry": {"coordinates":[-69.166206,47.459969],"type":"Point"}
}