{
  "type": "Feature",
  "properties": {
    "iso:country":"CA",
    "sg:address":"1305 Queen St",
    "sg:city":"Smithers",
    "sg:classifiers":[
        {
            "category":"Manufacturing",
            "subcategory":"Printing",
            "type":"Manufacturing & Wholesale Goods"
        }
    ],
    "sg:phone":"+1 250 847 3294",
    "sg:postcode":"V0J 2N0",
    "sg:province":"BC",
    "sg:tags":[
        "printer"
    ],
    "wof:name":"Bulkley Valley Printers Ltd",
    "wof:placetype":"venue"
},
  "geometry": {"coordinates":[-127.17063140899999,54.7826843262],"type":"Point"}
}