{
  "type": "Feature",
  "properties": {
    "addr:full":"Richibucto NB E4W 3W7",
    "addr:postcode":"e4w 3w7",
    "iso:country":"CA",
    "sg:city":"Richibucto",
    "sg:classifiers":[
        {
            "category":"Shopping",
            "subcategory":"Jewelry",
            "type":"Retail Goods"
        }
    ],
    "sg:phone":"+1 506 523 9777",
    "sg:postcode":"E4W 3W7",
    "sg:province":"NB",
    "sg:tags":[
        "jeweler"
    ],
    "wof:name":"Bijouterie Kent Jewellers",
    "wof:placetype":"venue"
},
  "geometry": {"coordinates":[-64.87339019780001,46.6743965149],"type":"Point"}
}