{
  "type": "Feature",
  "properties": {
    "addr:full":"250 Av Du Bois-Franc Aylmer QC J9J 2C7",
    "addr:housenumber":"250",
    "addr:postcode":"j9j 2c7",
    "addr:street":"Av Du Bois-Franc",
    "iso:country":"CA",
    "sg:address":"250 Av Du Bois-Franc",
    "sg:city":"Aylmer",
    "sg:classifiers":[
        {
            "category":"Organizations",
            "subcategory":"Professional Association",
            "type":"Services"
        }
    ],
    "sg:phone":"+1 819 682 2084",
    "sg:postcode":"J9J 2C7",
    "sg:province":"QC",
    "wof:name":"Club DE Soccer D'Aylmer",
    "wof:placetype":"venue"
},
  "geometry": {"coordinates":[-75.8415756226,45.4175376892],"type":"Point"}
}