{
  "type": "Feature",
  "properties": {
    "iso:country":"CA",
    "sg:address":"350 Pim St",
    "sg:city":"Sault Ste Marie",
    "sg:classifiers":[
        {
            "category":"Shopping",
            "subcategory":"Computers & Home Electronics",
            "type":"Retail Goods"
        }
    ],
    "sg:phone":"+1 705 256 7127",
    "sg:postcode":"P6B 2T8",
    "sg:province":"ON",
    "sg:tags":[
        "equipment",
        "satellite"
    ],
    "wof:name":"Central Service",
    "wof:placetype":"venue"
},
  "geometry": {"coordinates":[-84.31933600000001,46.516006],"type":"Point"}
}