{
  "type": "Feature",
  "properties": {
    "addr:full":"Sherbrooke QC J1H 5C5",
    "addr:postcode":"j1h 5c5",
    "iso:country":"CA",
    "sg:city":"Sherbrooke",
    "sg:classifiers":[
        {
            "category":"Professional",
            "subcategory":"Business Services",
            "type":"Services"
        }
    ],
    "sg:phone":"+1 819 566 7178",
    "sg:postcode":"J1H 5C5",
    "sg:province":"QC",
    "sg:tags":[
        "notary"
    ],
    "wof:name":"Laliberte, Jacques P",
    "wof:placetype":"venue"
},
  "geometry": {"coordinates":[-71.8914260864,45.4034996033],"type":"Point"}
}