{
  "type": "Feature",
  "properties": {
    "addr:full":"115 Montague Row Digby NS B0V 1A0",
    "addr:housenumber":"115",
    "addr:postcode":"b0v 1a0",
    "addr:street":"Montague Row",
    "iso:country":"CA",
    "sg:address":"115 Montague Row",
    "sg:city":"Digby",
    "sg:classifiers":[
        {
            "category":"Travel",
            "subcategory":"Hotels & Motels",
            "type":"Entertainment"
        }
    ],
    "sg:phone":"+1 902 245 2247",
    "sg:postcode":"B0V 1A0",
    "sg:province":"NS",
    "sg:tags":[
        "breakfast",
        "accommodation",
        "bed"
    ],
    "wof:name":"Bayside Bed & Breakfast",
    "wof:placetype":"venue"
},
  "geometry": {"coordinates":[-65.755318,44.621235],"type":"Point"}
}