{
  "type": "Feature",
  "properties": {
    "iso:country":"CA",
    "sg:city":"Quebec",
    "sg:classifiers":[
        {
            "category":"Organizations",
            "subcategory":"Labor Organization",
            "type":"Services"
        }
    ],
    "sg:phone":"+1 418 683 1765",
    "sg:postcode":"G1P 2X5",
    "sg:province":"QC",
    "wof:name":"International Assn DE Bridge",
    "wof:placetype":"venue"
},
  "geometry": {"coordinates":[-71.2982177734,46.8117828369],"type":"Point"}
}