{
  "type": "Feature",
  "properties": {
    "addr:full":"572 Rue Notre-Dame E Victoriaville QC G6P 4B6",
    "addr:housenumber":"572",
    "addr:postcode":"g6p 4b6",
    "addr:street":"Rue Notre-Dame E",
    "iso:country":"CA",
    "sg:address":"572 Rue Notre-Dame E",
    "sg:city":"Victoriaville",
    "sg:classifiers":[
        {
            "category":"Education",
            "subcategory":"School",
            "type":"Public Place"
        }
    ],
    "sg:phone":"+1 819 795 4683",
    "sg:postcode":"G6P 4B6",
    "sg:province":"QC",
    "sg:tags":[
        "academic",
        "instruction",
        "music",
        "special"
    ],
    "wof:name":"Ecole DE Musique LA Clef",
    "wof:placetype":"venue"
},
  "geometry": {"coordinates":[-71.943184,46.062279],"type":"Point"}
}