{
  "type": "Feature",
  "properties": {
    "addr:full":"9100 Blundell Rd Richmond BC V6Y 1K3",
    "addr:housenumber":"9100",
    "addr:postcode":"v6y 1k3",
    "addr:street":"Blundell Rd",
    "iso:country":"CA",
    "sg:address":"9100 Blundell Rd",
    "sg:city":"Richmond",
    "sg:classifiers":[
        {
            "category":"Food & Beverages",
            "subcategory":"Groceries & Convenience Stores",
            "type":"Retail Goods"
        }
    ],
    "sg:phone":"+1 604 444 6211",
    "sg:postcode":"V6Y 1K3",
    "sg:province":"BC",
    "sg:tags":[
        "grocer"
    ],
    "wof:name":"Iga Stores",
    "wof:placetype":"venue"
},
  "geometry": {"coordinates":[-123.123847961,49.1553230286],"type":"Point"}
}