{
  "type": "Feature",
  "properties": {
    "iso:country":"CA",
    "sg:address":"1 Lobstick St",
    "sg:city":"Churchill Falls",
    "sg:classifiers":[
        {
            "category":"Education",
            "subcategory":"School",
            "type":"Public Place"
        }
    ],
    "sg:phone":"+1 709 925 3371",
    "sg:postcode":"A0R 1A0",
    "sg:province":"NL",
    "wof:name":"Eric G Lambert School",
    "wof:placetype":"venue"
},
  "geometry": {"coordinates":[-64.00151824949999,53.5303649902],"type":"Point"}
}