{
  "type": "Feature",
  "properties": {
    "addr:full":"201 E Railway St Hartney MB R0M 0X0",
    "addr:housenumber":"201",
    "addr:postcode":"r0m 0x0",
    "addr:street":"E Railway St",
    "iso:country":"CA",
    "sg:address":"201 E Railway St",
    "sg:city":"Hartney",
    "sg:classifiers":[
        {
            "category":"Shopping",
            "subcategory":"Discount & Variety Stores",
            "type":"Retail Goods"
        }
    ],
    "sg:phone":"+1 204 858 2276",
    "sg:postcode":"R0M 0X0",
    "sg:province":"MB",
    "sg:tags":[
        "merchandise",
        "general"
    ],
    "wof:name":"Hartney Consumers CO-OP Ltd",
    "wof:placetype":"venue"
},
  "geometry": {"coordinates":[-100.528015137,49.4774780273],"type":"Point"}
}