{
  "type": "Feature",
  "properties": {
    "addr:full":"337 Reid St Quesnel BC V2J 2M5",
    "addr:housenumber":"337",
    "addr:postcode":"v2j 2m5",
    "addr:street":"Reid St",
    "iso:country":"CA",
    "sg:address":"337 Reid St",
    "sg:city":"Quesnel",
    "sg:classifiers":[
        {
            "category":"Shopping",
            "subcategory":"Bicycles & Sporting Goods",
            "type":"Retail Goods"
        }
    ],
    "sg:phone":"+1 250 992 7065",
    "sg:postcode":"V2J 2M5",
    "sg:province":"BC",
    "wof:name":"Quesnel Ski & Sports Ltd",
    "wof:placetype":"venue"
},
  "geometry": {"coordinates":[-122.496994019,52.9780158997],"type":"Point"}
}