{
  "type": "Feature",
  "properties": {
    "addr:full":"4309 49 St St Paul AB T0A 3A4",
    "addr:housenumber":"4309",
    "addr:postcode":"t0a 3a4",
    "addr:street":"49 St",
    "iso:country":"CA",
    "sg:address":"4309 49 St",
    "sg:city":"St Paul",
    "sg:classifiers":[
        {
            "category":"Wholesale",
            "subcategory":"Meat",
            "type":"Manufacturing & Wholesale Goods"
        }
    ],
    "sg:phone":"+1 780 645 4799",
    "sg:postcode":"T0A 3A4",
    "sg:province":"AB",
    "sg:tags":[
        "packer"
    ],
    "wof:name":"Lakeland Poultry Processors",
    "wof:placetype":"venue"
},
  "geometry": {"coordinates":[-111.29431200000001,53.984337],"type":"Point"}
}