{
  "type": "Feature",
  "properties": {
    "addr:full":"130 King St # M8 London ON N6A 1C5",
    "addr:housenumber":"130",
    "addr:postcode":"n6a 1c5",
    "addr:street":"King St # M8",
    "iso:country":"CA",
    "sg:address":"130 King St # M8",
    "sg:city":"London",
    "sg:classifiers":[
        {
            "category":"Shopping",
            "type":"Retail Goods"
        }
    ],
    "sg:phone":"+1 519 679 2202",
    "sg:postcode":"N6A 1C5",
    "sg:province":"ON",
    "sg:tags":[
        "wedding",
        "supply"
    ],
    "wof:name":"Red Thread Creations",
    "wof:placetype":"venue"
},
  "geometry": {"coordinates":[-81.25057983400001,42.9822425842],"type":"Point"}
}