{
  "type": "Feature",
  "properties": {
    "addr:full":"1610 Charles St Whitby ON L1N 1B9",
    "addr:housenumber":"1610",
    "addr:postcode":"l1n 1b9",
    "addr:street":"Charles St",
    "iso:country":"CA",
    "sg:address":"1610 Charles St",
    "sg:city":"Whitby",
    "sg:classifiers":[
        {
            "category":"Retail",
            "subcategory":"Auto Repair",
            "type":"Services"
        }
    ],
    "sg:phone":"+1 905 430 4514",
    "sg:postcode":"L1N 1B9",
    "sg:province":"ON",
    "sg:tags":[
        "truck"
    ],
    "wof:name":"Oshawa Truck Repair Ltd",
    "wof:placetype":"venue"
},
  "geometry": {"coordinates":[-78.936302,43.86145],"type":"Point"}
}