{
  "type": "Feature",
  "properties": {
    "iso:country":"CA",
    "sg:address":"320 Rue Notre-Dame E",
    "sg:city":"Montreal",
    "sg:classifiers":[
        {
            "category":"Professional",
            "subcategory":"Engineering",
            "type":"Services"
        }
    ],
    "sg:phone":"+1 514 395 8789",
    "sg:postcode":"H2Y 1C7",
    "sg:province":"QC",
    "sg:tags":[
        "engineer"
    ],
    "wof:name":"Hagop, Angaladian PE",
    "wof:placetype":"venue"
},
  "geometry": {"coordinates":[-73.5529632568,45.5093002319],"type":"Point"}
}