{
  "type": "Feature",
  "properties": {
    "iso:country":"CA",
    "sg:city":"Vancouver",
    "sg:classifiers":[
        {
            "category":"Professional",
            "type":"Services"
        }
    ],
    "sg:phone":"+1 604 688 6788",
    "sg:postcode":"V6C 2T5",
    "sg:province":"BC",
    "sg:tags":[
        "consultant",
        "geological"
    ],
    "wof:name":"Orequest Consultants Ltd",
    "wof:placetype":"venue"
},
  "geometry": {"coordinates":[-123.117279,49.284355],"type":"Point"}
}