{
  "type": "Feature",
  "properties": {
    "addr:full":"505 3 St SW # 610 Calgary AB T2P 3E6",
    "addr:housenumber":"505 3",
    "addr:postcode":"t2p 3e6",
    "addr:street":"St Sw # 610",
    "iso:country":"CA",
    "sg:address":"505 3 St SW # 610",
    "sg:city":"Calgary",
    "sg:classifiers":[
        {
            "category":"Professional",
            "subcategory":"Accounting & Tax Preparation",
            "type":"Services"
        }
    ],
    "sg:phone":"+1 403 571 4180",
    "sg:postcode":"T2P 3E6",
    "sg:province":"AB",
    "sg:tags":[
        "accountant"
    ],
    "wof:name":"Roper, Gordon F CA",
    "wof:placetype":"venue"
},
  "geometry": {"coordinates":[-114.07032775899999,51.0484352112],"type":"Point"}
}