{
  "type": "Feature",
  "properties": {
    "addr:full":"1290 1E Av Quebec QC G1L 3K9",
    "addr:housenumber":"1290",
    "addr:postcode":"g1l 3k9",
    "addr:street":"1E Av",
    "iso:country":"CA",
    "sg:address":"1290 1E Av",
    "sg:city":"Quebec",
    "sg:classifiers":[
        {
            "category":"Retail",
            "subcategory":"Funeral Services",
            "type":"Services"
        }
    ],
    "sg:phone":"+1 418 529 3371",
    "sg:postcode":"G1L 3K9",
    "sg:province":"QC",
    "sg:tags":[
        "director"
    ],
    "wof:name":"J Bouchard & Fils Enr",
    "wof:placetype":"venue"
},
  "geometry": {"coordinates":[-71.234589,46.826996],"type":"Point"}
}