{
  "type": "Feature",
  "properties": {
    "addr:full":"1812 Government St Victoria BC V8T 4N5",
    "addr:housenumber":"1812",
    "addr:postcode":"v8t 4n5",
    "addr:street":"Government St",
    "iso:country":"CA",
    "sg:address":"1812 Government St",
    "sg:city":"Victoria",
    "sg:classifiers":[
        {
            "category":"Manufacturing",
            "subcategory":"Food",
            "type":"Manufacturing & Wholesale Goods"
        }
    ],
    "sg:phone":"+1 250 380 6606",
    "sg:postcode":"V8T 4N5",
    "sg:province":"BC",
    "sg:tags":[
        "baker",
        "cookie",
        "bakery"
    ],
    "wof:name":"Cascadia Bakery",
    "wof:placetype":"venue"
},
  "geometry": {"coordinates":[-123.367355,48.430374],"type":"Point"}
}