{
  "type": "Feature",
  "properties": {
    "addr:full":"2532 Estevan Ave Victoria BC V8R 2S7",
    "addr:housenumber":"2532",
    "addr:postcode":"v8r 2s7",
    "addr:street":"Estevan Ave",
    "iso:country":"CA",
    "sg:address":"2532 Estevan Ave",
    "sg:city":"Victoria",
    "sg:classifiers":[
        {
            "category":"Shopping",
            "subcategory":"Used Merchandise",
            "type":"Retail Goods"
        }
    ],
    "sg:phone":"+1 250 598 2049",
    "sg:postcode":"V8R 2S7",
    "sg:province":"BC",
    "sg:tags":[
        "shop",
        "consignment"
    ],
    "wof:name":"Twice As Nice Clothing Etc",
    "wof:placetype":"venue"
},
  "geometry": {"coordinates":[-123.36451700000001,48.428314],"type":"Point"}
}