{
  "type": "Feature",
  "properties": {
    "addr:full":"4810 Tecumseh Rd E Windsor ON N8T 1B8",
    "addr:housenumber":"4810",
    "addr:postcode":"n8t 1b8",
    "addr:street":"Tecumseh Rd E",
    "iso:country":"CA",
    "sg:address":"4810 Tecumseh Rd E",
    "sg:city":"Windsor",
    "sg:classifiers":[
        {
            "category":"Restaurant",
            "type":"Food & Drink"
        }
    ],
    "sg:phone":"+1 519 944 2122",
    "sg:postcode":"N8T 1B8",
    "sg:province":"ON",
    "sg:tags":[
        "out",
        "pizza"
    ],
    "wof:name":"Toni's Pizza",
    "wof:placetype":"venue"
},
  "geometry": {"coordinates":[-82.966881,42.30772],"type":"Point"}
}