{
  "type": "Feature",
  "properties": {
    "addr:full":"1420 Boul Saint-Elzear O Laval QC H7L 3N2",
    "addr:housenumber":"1420",
    "addr:postcode":"h7l 3n2",
    "addr:street":"Boul Saint-Elzear O",
    "iso:country":"CA",
    "sg:address":"1420 Boul Saint-Elzear O",
    "sg:city":"Laval",
    "sg:classifiers":[
        {
            "category":"Retail",
            "subcategory":"Auto Repair",
            "type":"Services"
        }
    ],
    "sg:phone":"+1 450 662 0077",
    "sg:postcode":"H7L 3N2",
    "sg:province":"QC",
    "sg:tags":[
        "body",
        "automobile",
        "painting"
    ],
    "wof:name":"Garage Kamicar Inc",
    "wof:placetype":"venue"
},
  "geometry": {"coordinates":[-73.74247,45.589077],"type":"Point"}
}