{
  "type": "Feature",
  "properties": {
    "addr:full":"9335 Main St Chilliwack BC V2P 4M3",
    "addr:housenumber":"9335",
    "addr:postcode":"v2p 4m3",
    "addr:street":"Main St",
    "iso:country":"CA",
    "sg:address":"9335 Main St",
    "sg:city":"Chilliwack",
    "sg:classifiers":[
        {
            "category":"Shopping",
            "subcategory":"Discount & Variety Stores",
            "type":"Retail Goods"
        }
    ],
    "sg:phone":"+1 604 795 4490",
    "sg:postcode":"V2P 4M3",
    "sg:province":"BC",
    "wof:name":"Lucky Loonies Dollar Store",
    "wof:placetype":"venue"
},
  "geometry": {"coordinates":[-121.955467,49.171375],"type":"Point"}
}