{
  "type": "Feature",
  "properties": {
    "addr:full":"105 Main St Ottawa ON K1S 1B7",
    "addr:housenumber":"105",
    "addr:postcode":"k1s 1b7",
    "addr:street":"Main St",
    "iso:country":"CA",
    "sg:address":"105 Main St",
    "sg:city":"Ottawa",
    "sg:classifiers":[
        {
            "category":"Restaurant",
            "type":"Food & Drink"
        }
    ],
    "sg:phone":"+1 613 235 0988",
    "sg:postcode":"K1S 1B7",
    "sg:province":"ON",
    "wof:name":"Peach Gardens Restaurant",
    "wof:placetype":"venue"
},
  "geometry": {"coordinates":[-75.67931400000001,45.411377],"type":"Point"}
}