{
  "type": "Feature",
  "properties": {
    "addr:full":"Brampton ON L6T 5E9",
    "addr:postcode":"l6t 5e9",
    "iso:country":"CA",
    "sg:city":"Brampton",
    "sg:classifiers":[
        {
            "category":"Building & Trades",
            "subcategory":"Construction",
            "type":"Services"
        }
    ],
    "sg:phone":"+1 905 799 2277",
    "sg:postcode":"L6T 5E9",
    "sg:province":"ON",
    "sg:tags":[
        "concrete"
    ],
    "wof:name":"Paramount Structures Ltd",
    "wof:placetype":"venue"
},
  "geometry": {"coordinates":[-79.68766021730001,43.7394866943],"type":"Point"}
}