{
  "type": "Feature",
  "properties": {
    "addr:full":"7401 Rue Hochelaga Montreal QC H1N 3M5",
    "addr:housenumber":"7401",
    "addr:postcode":"h1n 3m5",
    "addr:street":"Rue Hochelaga",
    "iso:country":"CA",
    "sg:address":"7401 Rue Hochelaga",
    "sg:city":"Montreal",
    "sg:classifiers":[
        {
            "category":"Organizations",
            "subcategory":"Professional Association",
            "type":"Services"
        }
    ],
    "sg:phone":"+1 514 251 4000",
    "sg:postcode":"H1N 3M5",
    "sg:province":"QC",
    "wof:name":"Societe Quebecoise DE LA",
    "wof:placetype":"venue"
},
  "geometry": {"coordinates":[-73.526726,45.588066],"type":"Point"}
}