{
  "type": "Feature",
  "properties": {
    "addr:full":"12 Cote DE L'Eglise Saint-Philippe-DE-Neri QC G0L 4A0",
    "addr:housenumber":"12",
    "addr:postcode":"g0l 4a0",
    "addr:street":"Cote De L'Eglise Saint-Philippe-De-Neri",
    "iso:country":"CA",
    "sg:address":"12 Cote DE L'Eglise",
    "sg:city":"Saint-Philippe-DE-Neri",
    "sg:classifiers":[
        {
            "category":"Government",
            "subcategory":"Office",
            "type":"Public Place"
        }
    ],
    "sg:phone":"+1 418 498 2744",
    "sg:postcode":"G0L 4A0",
    "sg:province":"QC",
    "sg:tags":[
        "village"
    ],
    "wof:name":"St-Philippe-DE-Neri Municipale",
    "wof:placetype":"venue"
},
  "geometry": {"coordinates":[-69.048149,48.217106],"type":"Point"}
}