{
  "type": "Feature",
  "properties": {
    "iso:country":"CA",
    "sg:address":"385 Frederick St # 12",
    "sg:city":"Kitchener",
    "sg:classifiers":[
        {
            "category":"Food & Beverages",
            "subcategory":"Specialty",
            "type":"Retail Goods"
        }
    ],
    "sg:phone":"+1 519 742 0691",
    "sg:postcode":"N2H 2P2",
    "sg:province":"ON",
    "sg:tags":[
        "health",
        "diet"
    ],
    "wof:name":"Basic Bulk & Natural Foods",
    "wof:placetype":"venue"
},
  "geometry": {"coordinates":[-80.473801,43.457722],"type":"Point"}
}