{
  "type": "Feature",
  "properties": {
    "iso:country":"CA",
    "sg:address":"3894 Commercial St",
    "sg:city":"Vancouver",
    "sg:classifiers":[
        {
            "category":"Social Services",
            "type":"Services"
        }
    ],
    "sg:phone":"+1 604 736 3601",
    "sg:postcode":"V5N 4G2",
    "sg:province":"BC",
    "sg:tags":[
        "organization",
        "welfare"
    ],
    "wof:name":"Folkstone Family Homes",
    "wof:placetype":"venue"
},
  "geometry": {"coordinates":[-123.067802429,49.2506217957],"type":"Point"}
}