{
  "type": "Feature",
  "properties": {
    "addr:full":"905 Rue Basile-Moreau Saint-Laurent QC H4L 4A1",
    "addr:housenumber":"905",
    "addr:postcode":"h4l 4a1",
    "addr:street":"Rue Basile-Moreau",
    "iso:country":"CA",
    "sg:address":"905 Rue Basile-Moreau",
    "sg:city":"Saint-Laurent",
    "sg:classifiers":[
        {
            "category":"Organizations",
            "subcategory":"Religious Organization",
            "type":"Services"
        }
    ],
    "sg:phone":"+1 514 747 1892",
    "sg:postcode":"H4L 4A1",
    "sg:province":"QC",
    "wof:name":"Soeurs DE Sainte-Croix",
    "wof:placetype":"venue"
},
  "geometry": {"coordinates":[-73.67878,45.516632],"type":"Point"}
}