{
  "type": "Feature",
  "properties": {
    "addr:full":"1962 Danforth Ave Toronto ON M4C 1J6",
    "addr:housenumber":"1962",
    "addr:postcode":"m4c 1j6",
    "addr:street":"Danforth Ave",
    "iso:country":"CA",
    "sg:address":"1962 Danforth Ave",
    "sg:city":"Toronto",
    "sg:classifiers":[
        {
            "category":"Shopping",
            "subcategory":"Discount & Variety Stores",
            "type":"Retail Goods"
        }
    ],
    "sg:phone":"+1 416 421 0823",
    "sg:postcode":"M4C 1J6",
    "sg:province":"ON",
    "wof:name":"Convenience",
    "wof:placetype":"venue"
},
  "geometry": {"coordinates":[-79.315094,43.685307],"type":"Point"}
}