{
  "type": "Feature",
  "properties": {
    "iso:country":"CA",
    "sg:address":"494 Av Lariviere",
    "sg:city":"Rouyn-Noranda",
    "sg:classifiers":[
        {
            "category":"Autos & Motor Vehicles",
            "subcategory":"Automobile Sales",
            "type":"Retail Goods"
        }
    ],
    "sg:phone":"+1 819 762 1741",
    "sg:postcode":"J9X 4J2",
    "sg:province":"QC",
    "sg:tags":[
        "car",
        "dealer"
    ],
    "wof:name":"Dynastie Automobile Ltee",
    "wof:placetype":"venue"
},
  "geometry": {"coordinates":[-79.014236,48.229233],"type":"Point"}
}