{
  "type": "Feature",
  "properties": {
    "addr:full":"50 Rue Tamarack Morin-Heights QC J0R 1H0",
    "addr:housenumber":"50",
    "addr:postcode":"j0r 1h0",
    "addr:street":"Rue Tamarack",
    "iso:country":"CA",
    "sg:address":"50 Rue Tamarack",
    "sg:city":"Morin-Heights",
    "sg:classifiers":[
        {
            "category":"Recreation",
            "type":"Entertainment"
        }
    ],
    "sg:phone":"+1 450 226 2687",
    "sg:postcode":"J0R 1H0",
    "sg:province":"QC",
    "sg:tags":[
        "riding",
        "academy",
        "stable"
    ],
    "wof:name":"Centre Equestre Des Laurentide",
    "wof:placetype":"venue"
},
  "geometry": {"coordinates":[-74.21727,45.903397],"type":"Point"}
}