{
  "type": "Feature",
  "properties": {
    "addr:full":"632 Rue Lafleche Winnipeg MB R2J 0E3",
    "addr:housenumber":"632",
    "addr:postcode":"r2j 0e3",
    "addr:street":"Rue Lafleche",
    "iso:country":"CA",
    "sg:address":"632 Rue Lafleche",
    "sg:city":"Winnipeg",
    "sg:classifiers":[
        {
            "category":"Bars & Pubs",
            "type":"Food & Drink"
        }
    ],
    "sg:phone":"+1 204 237 3144",
    "sg:postcode":"R2J 0E3",
    "sg:province":"MB",
    "sg:tags":[
        "motel",
        "hotel"
    ],
    "wof:name":"Nicolett Inn",
    "wof:placetype":"venue"
},
  "geometry": {"coordinates":[-97.10717,49.895111],"type":"Point"}
}