{
  "type": "Feature",
  "properties": {
    "addr:full":"2599 Jackson Ave Merritt BC V1K 1B8",
    "addr:housenumber":"2599",
    "addr:postcode":"v1k 1b8",
    "addr:street":"Jackson Ave",
    "iso:country":"CA",
    "sg:address":"2599 Jackson Ave",
    "sg:city":"Merritt",
    "sg:classifiers":[
        {
            "category":"Food & Beverages",
            "subcategory":"Groceries & Convenience Stores",
            "type":"Retail Goods"
        }
    ],
    "sg:phone":"+1 250 378 4025",
    "sg:postcode":"V1K 1B8",
    "sg:province":"BC",
    "sg:tags":[
        "grocer"
    ],
    "wof:name":"Happy Valley Grocery",
    "wof:placetype":"venue"
},
  "geometry": {"coordinates":[-120.777412415,50.1053962708],"type":"Point"}
}