{
  "type": "Feature",
  "properties": {
    "iso:country":"CA",
    "sg:address":"225 Rutland Rd S",
    "sg:city":"Kelowna",
    "sg:classifiers":[
        {
            "category":"Health Services",
            "subcategory":"Chiropractor",
            "type":"Services"
        }
    ],
    "sg:phone":"+1 250 765 1466",
    "sg:postcode":"V1X 2Z3",
    "sg:province":"BC",
    "wof:name":"Forsythe Chiropractic Office",
    "wof:placetype":"venue"
},
  "geometry": {"coordinates":[-119.386719,49.887299],"type":"Point"}
}