{
  "type": "Feature",
  "properties": {
    "addr:full":"5850 River Rd Qualicum Beach BC V9K 1Z5",
    "addr:housenumber":"5850",
    "addr:postcode":"v9k 1z5",
    "addr:street":"River Rd",
    "iso:country":"CA",
    "sg:address":"5850 River Rd",
    "sg:city":"Qualicum Beach",
    "sg:classifiers":[
        {
            "category":"Organizations",
            "subcategory":"Professional Association",
            "type":"Services"
        }
    ],
    "sg:phone":"+1 250 757 9337",
    "sg:postcode":"V9K 1Z5",
    "sg:province":"BC",
    "sg:tags":[
        "smoking",
        "fish",
        "curing"
    ],
    "wof:name":"Qualicum First Nation",
    "wof:placetype":"venue"
},
  "geometry": {"coordinates":[-124.441703796,49.3467063904],"type":"Point"}
}