{
  "type": "Feature",
  "properties": {
    "addr:full":"893 Campbell St Sarnia ON N7T 2J9",
    "addr:housenumber":"893",
    "addr:postcode":"n7t 2j9",
    "addr:street":"Campbell St",
    "iso:country":"CA",
    "sg:address":"893 Campbell St",
    "sg:city":"Sarnia",
    "sg:classifiers":[
        {
            "category":"Wholesale",
            "subcategory":"Machinery & Supplies",
            "type":"Manufacturing & Wholesale Goods"
        }
    ],
    "sg:phone":"+1 519 336 7419",
    "sg:postcode":"N7T 2J9",
    "sg:province":"ON",
    "sg:tags":[
        "cleaning"
    ],
    "wof:name":"Ontario Chemical Cleaning Inc",
    "wof:placetype":"venue"
},
  "geometry": {"coordinates":[-82.37983699999999,42.958584],"type":"Point"}
}