{
  "type": "Feature",
  "properties": {
    "iso:country":"CA",
    "sg:address":"893 Campbell St",
    "sg:city":"Sarnia",
    "sg:classifiers":[
        {
            "category":"Wholesale",
            "subcategory":"Machinery & Supplies",
            "type":"Manufacturing & Wholesale Goods"
        }
    ],
    "sg:phone":"+1 519 336 7419",
    "sg:postcode":"N7T 2J9",
    "sg:province":"ON",
    "sg:tags":[
        "cleaning"
    ],
    "wof:name":"Ontario Chemical Cleaning Inc",
    "wof:placetype":"venue"
},
  "geometry": {"coordinates":[-82.379837,42.958584],"type":"Point"}
}