{
  "type": "Feature",
  "properties": {
    "addr:full":"1567 William Ave W Winnipeg MB R3E 1A7",
    "addr:housenumber":"1567",
    "addr:postcode":"r3e 1a7",
    "addr:street":"William Ave W",
    "iso:country":"CA",
    "sg:address":"1567 William Ave W",
    "sg:city":"Winnipeg",
    "sg:classifiers":[
        {
            "category":"Organizations",
            "subcategory":"Religious Organization",
            "type":"Services"
        }
    ],
    "sg:phone":"+1 204 775 1107",
    "sg:postcode":"R3E 1A7",
    "sg:province":"MB",
    "sg:tags":[
        "church"
    ],
    "wof:name":"St Thomas Anglican Church",
    "wof:placetype":"venue"
},
  "geometry": {"coordinates":[-97.191704,49.916199],"type":"Point"}
}