{
  "type": "Feature",
  "properties": {
    "addr:full":"1750 Ralph St North Vancouver BC V7K 2W8",
    "addr:housenumber":"1750",
    "addr:postcode":"v7k 2w8",
    "addr:street":"Ralph St",
    "iso:country":"CA",
    "sg:address":"1750 Ralph St",
    "sg:city":"North Vancouver",
    "sg:classifiers":[
        {
            "category":"Building & Trades",
            "subcategory":"Construction",
            "type":"Services"
        }
    ],
    "sg:phone":"+1 604 986 3103",
    "sg:postcode":"V7K 2W8",
    "sg:province":"BC",
    "sg:tags":[
        "concrete",
        "builder",
        "contractor",
        "patio",
        "deck"
    ],
    "wof:name":"Aggrapox Inc",
    "wof:placetype":"venue"
},
  "geometry": {"coordinates":[-123.023597717,49.3497505188],"type":"Point"}
}