{
  "type": "Feature",
  "properties": {
    "addr:full":"120 Ellison Ave Leamington ON N8H 5C7",
    "addr:housenumber":"120",
    "addr:postcode":"n8h 5c7",
    "addr:street":"Ellison Ave",
    "iso:country":"CA",
    "sg:address":"120 Ellison Ave",
    "sg:city":"Leamington",
    "sg:classifiers":[
        {
            "category":"Education",
            "subcategory":"School",
            "type":"Public Place"
        }
    ],
    "sg:phone":"+1 519 322 2804",
    "sg:postcode":"N8H 5C7",
    "sg:province":"ON",
    "wof:name":"Cardinal Carter Secondary Schl",
    "wof:placetype":"venue"
},
  "geometry": {"coordinates":[-82.6159667969,42.0424232483],"type":"Point"}
}