{
  "type": "Feature",
  "properties": {
    "addr:full":"Rte 11 Tracadie-Sheila NB E1X 1B5",
    "addr:postcode":"e1x 1b5",
    "addr:street":"Rte 11",
    "iso:country":"CA",
    "sg:address":"Rte 11",
    "sg:city":"Tracadie-Sheila",
    "sg:classifiers":[
        {
            "category":"Retail",
            "subcategory":"Auto Repair",
            "type":"Services"
        }
    ],
    "sg:phone":"+1 506 395 6834",
    "sg:postcode":"E1X 1B5",
    "sg:province":"NB",
    "sg:tags":[
        "repairing",
        "automobile"
    ],
    "wof:name":"Bertrand Ferguson Garage",
    "wof:placetype":"venue"
},
  "geometry": {"coordinates":[-64.9120178223,47.4726600647],"type":"Point"}
}