{
  "type": "Feature",
  "properties": {
    "iso:country":"CA",
    "sg:address":"190 Brookside Ave",
    "sg:city":"York",
    "sg:classifiers":[
        {
            "category":"Personal",
            "subcategory":"Beauty Salon",
            "type":"Services"
        }
    ],
    "sg:phone":"+1 416 766 5251",
    "sg:postcode":"M6S 4G9",
    "sg:province":"ON",
    "wof:name":"Krystyna's Hair Fashion",
    "wof:placetype":"venue"
},
  "geometry": {"coordinates":[-79.49211883540001,43.661441803],"type":"Point"}
}