{
  "type": "Feature",
  "properties": {
    "addr:full":"77 Goulet St Winnipeg MB R2H 0R5",
    "addr:housenumber":"77",
    "addr:postcode":"r2h 0r5",
    "addr:street":"Goulet St",
    "iso:country":"CA",
    "sg:address":"77 Goulet St",
    "sg:city":"Winnipeg",
    "sg:classifiers":[
        {
            "category":"Restaurant",
            "type":"Food & Drink"
        }
    ],
    "sg:phone":"+1 204 949 6018",
    "sg:postcode":"R2H 0R5",
    "sg:province":"MB",
    "wof:name":"Mc Donald's",
    "wof:placetype":"venue"
},
  "geometry": {"coordinates":[-97.124710083,49.8821983337],"type":"Point"}
}