{
  "type": "Feature",
  "properties": {
    "addr:full":"125 Evelyn Cres Toronto ON M6P 3E3",
    "addr:housenumber":"125",
    "addr:postcode":"m6p 3e3",
    "addr:street":"Evelyn Cres",
    "iso:country":"CA",
    "sg:address":"125 Evelyn Cres",
    "sg:city":"Toronto",
    "sg:classifiers":[
        {
            "category":"Education",
            "subcategory":"School",
            "type":"Public Place"
        }
    ],
    "sg:phone":"+1 416 393 9639",
    "sg:postcode":"M6P 3E3",
    "sg:province":"ON",
    "wof:name":"Student School",
    "wof:placetype":"venue"
},
  "geometry": {"coordinates":[-79.475174,43.657356],"type":"Point"}
}