{
  "type": "Feature",
  "properties": {
    "addr:full":"110 Boul DE LA Cite Des Jeunes Vaudreuil-Dorion QC J7V 8B7",
    "addr:housenumber":"110",
    "addr:postcode":"j7v 8b7",
    "addr:street":"Boul De La Cite Des Jeunes",
    "iso:country":"CA",
    "sg:address":"110 Boul DE LA Cite Des Jeunes",
    "sg:city":"Vaudreuil-Dorion",
    "sg:classifiers":[
        {
            "category":"Freight",
            "type":"Transportation"
        }
    ],
    "sg:phone":"+1 514 990 5502",
    "sg:postcode":"J7V 8B7",
    "sg:province":"QC",
    "sg:tags":[
        "trucking"
    ],
    "wof:name":"Transport Gestion Luc Theoret",
    "wof:placetype":"venue"
},
  "geometry": {"coordinates":[-74.033592,45.395],"type":"Point"}
}