{
  "type": "Feature",
  "properties": {
    "addr:full":"223 Oakdale Rd North York ON M3N 1W4",
    "addr:housenumber":"223",
    "addr:postcode":"m3n 1w4",
    "addr:street":"Oakdale Rd",
    "iso:country":"CA",
    "sg:address":"223 Oakdale Rd",
    "sg:city":"North York",
    "sg:classifiers":[
        {
            "category":"Home & Garden",
            "subcategory":"Furniture",
            "type":"Retail Goods"
        }
    ],
    "sg:phone":"+1 416 743 8393",
    "sg:postcode":"M3N 1W4",
    "sg:province":"ON",
    "wof:name":"Glory Wooden Furniture Mfg",
    "wof:placetype":"venue"
},
  "geometry": {"coordinates":[-79.5259552002,43.7456092834],"type":"Point"}
}