{
  "type": "Feature",
  "properties": {
    "addr:full":"10528 Alaska Rd Fort St John BC V1J 1B3",
    "addr:housenumber":"10528",
    "addr:postcode":"v1j 1b3",
    "addr:street":"Alaska Rd",
    "iso:country":"CA",
    "sg:address":"10528 Alaska Rd",
    "sg:city":"Fort St John",
    "sg:classifiers":[
        {
            "category":"Home & Garden",
            "subcategory":"Building Materials",
            "type":"Retail Goods"
        }
    ],
    "sg:phone":"+1 250 787 8888",
    "sg:postcode":"V1J 1B3",
    "sg:province":"BC",
    "sg:tags":[
        "glass",
        "window",
        "plate"
    ],
    "wof:name":"Peace Glass",
    "wof:placetype":"venue"
},
  "geometry": {"coordinates":[-120.856086731,56.2406654358],"type":"Point"}
}