{
  "type": "Feature",
  "properties": {
    "iso:country":"CA",
    "sg:address":"6342 Rue Jean-Talon E",
    "sg:city":"Saint-Leonard",
    "sg:classifiers":[
        {
            "category":"Personal",
            "subcategory":"Beauty Salon",
            "type":"Services"
        }
    ],
    "sg:phone":"+1 514 253 9790",
    "sg:postcode":"H1S 1M8",
    "sg:province":"QC",
    "wof:name":"Intime Coiffure Inc",
    "wof:placetype":"venue"
},
  "geometry": {"coordinates":[-73.5759887695,45.5909309387],"type":"Point"}
}