{
  "type": "Feature",
  "properties": {
    "addr:full":"3586 4th Ave W Vancouver BC V6R 1N8",
    "addr:housenumber":"3586",
    "addr:postcode":"v6r 1n8",
    "addr:street":"4Th Ave W",
    "iso:country":"CA",
    "sg:address":"3586 4th Ave W",
    "sg:city":"Vancouver",
    "sg:classifiers":[
        {
            "category":"Personal",
            "subcategory":"Tanning Parlor",
            "type":"Services"
        }
    ],
    "sg:phone":"+1 604 738 9767",
    "sg:postcode":"V6R 1N8",
    "sg:province":"BC",
    "sg:tags":[
        "salon"
    ],
    "wof:name":"Kitsilano Sun Ctr",
    "wof:placetype":"venue"
},
  "geometry": {"coordinates":[-123.183144,49.268429],"type":"Point"}
}