{
  "type": "Feature",
  "properties": {
    "addr:full":"5510 Rue Vanden-Abeele Saint-Laurent QC H4S 1P9",
    "addr:housenumber":"5510",
    "addr:postcode":"h4s 1p9",
    "addr:street":"Rue Vanden-Abeele",
    "iso:country":"CA",
    "sg:address":"5510 Rue Vanden-Abeele",
    "sg:city":"Saint-Laurent",
    "sg:classifiers":[
        {
            "category":"Wholesale",
            "subcategory":"Machinery & Supplies",
            "type":"Manufacturing & Wholesale Goods"
        }
    ],
    "sg:phone":"+1 514 332 6562",
    "sg:postcode":"H4S 1P9",
    "sg:province":"QC",
    "sg:tags":[
        "tubing",
        "hose",
        "plastic"
    ],
    "wof:name":"Equipements Rapco Inc",
    "wof:placetype":"venue"
},
  "geometry": {"coordinates":[-73.74260700000001,45.48632],"type":"Point"}
}