{
  "type": "Feature",
  "properties": {
    "iso:country":"CA",
    "sg:address":"5510 Rue Vanden-Abeele",
    "sg:city":"Saint-Laurent",
    "sg:classifiers":[
        {
            "category":"Wholesale",
            "subcategory":"Machinery & Supplies",
            "type":"Manufacturing & Wholesale Goods"
        }
    ],
    "sg:phone":"+1 514 332 6562",
    "sg:postcode":"H4S 1P9",
    "sg:province":"QC",
    "sg:tags":[
        "tubing",
        "hose",
        "plastic"
    ],
    "wof:name":"Equipements Rapco Inc",
    "wof:placetype":"venue"
},
  "geometry": {"coordinates":[-73.742607,45.48632],"type":"Point"}
}