{
  "type": "Feature",
  "properties": {
    "addr:full":"65 Larch St Sudbury ON P3E 1B8",
    "addr:housenumber":"65",
    "addr:postcode":"p3e 1b8",
    "addr:street":"Larch St",
    "iso:country":"CA",
    "sg:address":"65 Larch St",
    "sg:city":"Sudbury",
    "sg:classifiers":[
        {
            "category":"Shopping",
            "subcategory":"Pharmacy",
            "type":"Retail Goods"
        }
    ],
    "sg:phone":"+1 705 675 1900",
    "sg:postcode":"P3E 1B8",
    "sg:province":"ON",
    "wof:name":"Michaud Medical Pharmacy",
    "wof:placetype":"venue"
},
  "geometry": {"coordinates":[-80.9941864014,46.4912185669],"type":"Point"}
}