{
  "type": "Feature",
  "properties": {
    "addr:full":"3365 Spruce Ave Burlington ON L7N 1J7",
    "addr:housenumber":"3365",
    "addr:postcode":"l7n 1j7",
    "addr:street":"Spruce Ave",
    "iso:country":"CA",
    "sg:address":"3365 Spruce Ave",
    "sg:city":"Burlington",
    "sg:classifiers":[
        {
            "category":"Education",
            "subcategory":"School",
            "type":"Public Place"
        }
    ],
    "sg:phone":"+1 905 637 3881",
    "sg:postcode":"L7N 1J7",
    "sg:province":"ON",
    "wof:name":"John T Tuck Elementary School",
    "wof:placetype":"venue"
},
  "geometry": {"coordinates":[-79.76978302000001,43.3450622559],"type":"Point"}
}