{
  "type": "Feature",
  "properties": {
    "addr:full":"Thornhill ON L4J 7L2",
    "addr:postcode":"l4j 7l2",
    "iso:country":"CA",
    "sg:city":"Thornhill",
    "sg:classifiers":[
        {
            "category":"Shopping",
            "subcategory":"Computers & Home Electronics",
            "type":"Retail Goods"
        }
    ],
    "sg:phone":"+1 905 761 2155",
    "sg:postcode":"L4J 7L2",
    "sg:province":"ON",
    "sg:tags":[
        "equipment",
        "dealer"
    ],
    "wof:name":"Rgb Electronics Inc",
    "wof:placetype":"venue"
},
  "geometry": {"coordinates":[-79.423553,43.81554],"type":"Point"}
}