{
  "type": "Feature",
  "properties": {
    "iso:country":"CA",
    "sg:address":"1458 Rue DE LA Montagne",
    "sg:city":"Montreal",
    "sg:classifiers":[
        {
            "category":"Bars & Pubs",
            "type":"Food & Drink"
        }
    ],
    "sg:phone":"+1 514 284 3844",
    "sg:postcode":"H3G 1Z5",
    "sg:province":"QC",
    "sg:tags":[
        "club",
        "night"
    ],
    "wof:name":"Diamond",
    "wof:placetype":"venue"
},
  "geometry": {"coordinates":[-73.5761642456,45.498298645],"type":"Point"}
}