{
  "type": "Feature",
  "properties": {
    "addr:full":"Vancouver BC V6Z 2T1",
    "addr:postcode":"v6z 2t1",
    "iso:country":"CA",
    "sg:city":"Vancouver",
    "sg:classifiers":[
        {
            "category":"Health Services",
            "subcategory":"Doctor",
            "type":"Services"
        }
    ],
    "sg:phone":"+1 604 681 1080",
    "sg:postcode":"V6Z 2T1",
    "sg:province":"BC",
    "sg:tags":[
        "physician",
        "surgeon"
    ],
    "wof:name":"Spectrum Health Care Ltd",
    "wof:placetype":"venue"
},
  "geometry": {"coordinates":[-123.124961853,49.2789993286],"type":"Point"}
}