{
  "type": "Feature",
  "properties": {
    "addr:full":"416 Av Rouleau Rimouski QC G5L 7S5",
    "addr:housenumber":"416",
    "addr:postcode":"g5l 7s5",
    "addr:street":"Av Rouleau",
    "iso:country":"CA",
    "sg:address":"416 Av Rouleau",
    "sg:city":"Rimouski",
    "sg:classifiers":[
        {
            "category":"Recreation",
            "type":"Entertainment"
        }
    ],
    "sg:phone":"+1 418 724 6149",
    "sg:postcode":"G5L 7S5",
    "sg:province":"QC",
    "sg:tags":[
        "tennis",
        "center"
    ],
    "wof:name":"Tennis DE Rimouski",
    "wof:placetype":"venue"
},
  "geometry": {"coordinates":[-68.518265,48.438129],"type":"Point"}
}