{
  "type": "Feature",
  "properties": {
    "iso:country":"CA",
    "sg:city":"Dolbeau-Mistassini",
    "sg:classifiers":[
        {
            "category":"Real Estate",
            "subcategory":"Real Estate Operator",
            "type":"Services"
        }
    ],
    "sg:phone":"+1 418 276 8404",
    "sg:postcode":"G8L 1H1",
    "sg:province":"QC",
    "sg:tags":[
        "mall",
        "shopping",
        "center"
    ],
    "wof:name":"Promenades Du Blvd Wallberg",
    "wof:placetype":"venue"
},
  "geometry": {"coordinates":[-72.22793579099999,48.8779373169],"type":"Point"}
}