{
  "type": "Feature",
  "properties": {
    "addr:full":"150 Rue Fleury O Montreal QC H3L 1T5",
    "addr:housenumber":"150",
    "addr:postcode":"h3l 1t5",
    "addr:street":"Rue Fleury O",
    "iso:country":"CA",
    "sg:address":"150 Rue Fleury O",
    "sg:city":"Montreal",
    "sg:classifiers":[
        {
            "category":"Health Services",
            "subcategory":"Doctor",
            "type":"Services"
        }
    ],
    "sg:phone":"+1 514 387 4242",
    "sg:postcode":"H3L 1T5",
    "sg:province":"QC",
    "sg:tags":[
        "clinic"
    ],
    "wof:name":"Centre Chiropratique Optimale",
    "wof:placetype":"venue"
},
  "geometry": {"coordinates":[-73.66429100000001,45.549095],"type":"Point"}
}