{
  "type": "Feature",
  "properties": {
    "iso:country":"CA",
    "sg:city":"Montreal",
    "sg:classifiers":[
        {
            "category":"Health Services",
            "subcategory":"Chiropractor",
            "type":"Services"
        }
    ],
    "sg:phone":"+1 514 270 1517",
    "sg:postcode":"H1Y 3G4",
    "sg:province":"QC",
    "wof:name":"Clinique Chiro-Sante Rosemont",
    "wof:placetype":"venue"
},
  "geometry": {"coordinates":[-73.596214,45.555004],"type":"Point"}
}