{
  "type": "Feature",
  "properties": {
    "addr:full":"Sherwood Park AB T8H 1X1",
    "addr:postcode":"t8h 1x1",
    "iso:country":"CA",
    "sg:city":"Sherwood Park",
    "sg:classifiers":[
        {
            "category":"Personal",
            "subcategory":"Beauty Salon",
            "type":"Services"
        }
    ],
    "sg:phone":"+1 780 467 6060",
    "sg:postcode":"T8H 1X1",
    "sg:province":"AB",
    "wof:name":"Just Your Style Hair Design",
    "wof:placetype":"venue"
},
  "geometry": {"coordinates":[-113.301086,53.541374],"type":"Point"}
}