{
  "type": "Feature",
  "properties": {
    "addr:full":"35 Raglin Rd Cambridge ON N1R 7J2",
    "addr:housenumber":"35",
    "addr:postcode":"n1r 7j2",
    "addr:street":"Raglin Rd",
    "iso:country":"CA",
    "sg:address":"35 Raglin Rd",
    "sg:city":"Cambridge",
    "sg:classifiers":[
        {
            "category":"Manufacturing",
            "subcategory":"Tools & Machinery",
            "type":"Manufacturing & Wholesale Goods"
        }
    ],
    "sg:phone":"+1 519 624 9262",
    "sg:postcode":"N1R 7J2",
    "sg:province":"ON",
    "sg:tags":[
        "machine",
        "shop"
    ],
    "wof:name":"Piedmont Manufacturing Inc",
    "wof:placetype":"venue"
},
  "geometry": {"coordinates":[-80.3062210083,43.400352478],"type":"Point"}
}