{
  "type": "Feature",
  "properties": {
    "addr:full":"North Vancouver BC V7M 1A5",
    "addr:postcode":"v7m 1a5",
    "iso:country":"CA",
    "sg:city":"North Vancouver",
    "sg:classifiers":[
        {
            "category":"Social Services",
            "subcategory":"Job Training",
            "type":"Services"
        }
    ],
    "sg:phone":"+1 604 982 0144",
    "sg:postcode":"V7M 1A5",
    "sg:province":"BC",
    "sg:tags":[
        "career",
        "counseling",
        "vocational"
    ],
    "wof:name":"Oceana Counselling Svc Ltd",
    "wof:placetype":"venue"
},
  "geometry": {"coordinates":[-123.084808,49.31319],"type":"Point"}
}