{
  "type": "Feature",
  "properties": {
    "addr:full":"4855 Delta St Delta BC V4K 2T9",
    "addr:housenumber":"4855",
    "addr:postcode":"v4k 2t9",
    "addr:street":"Delta St",
    "iso:country":"CA",
    "sg:address":"4855 Delta St",
    "sg:city":"Delta",
    "sg:classifiers":[
        {
            "category":"Restaurant",
            "type":"Food & Drink"
        }
    ],
    "sg:phone":"+1 604 940 3323",
    "sg:postcode":"V4K 2T9",
    "sg:province":"BC",
    "wof:name":"Go-Go Sushi",
    "wof:placetype":"venue"
},
  "geometry": {"coordinates":[-123.08622,49.091228],"type":"Point"}
}