{
  "type": "Feature",
  "properties": {
    "addr:full":"48 Government Rd Kapuskasing ON P5N 2W6",
    "addr:housenumber":"48",
    "addr:postcode":"p5n 2w6",
    "addr:street":"Rd",
    "iso:country":"CA",
    "sg:address":"48 Government Rd",
    "sg:city":"Kapuskasing",
    "sg:classifiers":[
        {
            "category":"Autos & Motor Vehicles",
            "subcategory":"Fuel & Gas Station",
            "type":"Retail Goods"
        }
    ],
    "sg:phone":"+1 705 335 3345",
    "sg:postcode":"P5N 2W6",
    "sg:province":"ON",
    "sg:tags":[
        "oil"
    ],
    "wof:name":"Kap Imperial Esso",
    "wof:placetype":"venue"
},
  "geometry": {"coordinates":[-82.4186630249,49.4131774902],"type":"Point"}
}