{
  "type": "Feature",
  "properties": {
    "addr:full":"460 Wellington St St Thomas ON N5R 6H9",
    "addr:housenumber":"460",
    "addr:postcode":"n5r 6h9",
    "addr:street":"Wellington St",
    "iso:country":"CA",
    "sg:address":"460 Wellington St",
    "sg:city":"St Thomas",
    "sg:classifiers":[
        {
            "category":"Health Services",
            "subcategory":"Doctor",
            "type":"Services"
        }
    ],
    "sg:phone":"+1 519 631 5670",
    "sg:postcode":"N5R 6H9",
    "sg:province":"ON",
    "sg:tags":[
        "physician",
        "surgeon"
    ],
    "wof:name":"Dougherty, D J MD",
    "wof:placetype":"venue"
},
  "geometry": {"coordinates":[-81.15904999999999,42.774448],"type":"Point"}
}