{
  "type": "Feature",
  "properties": {
    "iso:country":"CA",
    "sg:address":"795 Rte Lagueux",
    "sg:city":"Saint-Etienne-DE-Lauzon",
    "sg:classifiers":[
        {
            "category":"Building & Trades",
            "subcategory":"Electrical",
            "type":"Services"
        }
    ],
    "sg:phone":"+1 418 836 5086",
    "sg:postcode":"G6J 1Y1",
    "sg:province":"QC",
    "sg:tags":[
        "equipment",
        "supply",
        "wine",
        "electric",
        "contractor"
    ],
    "wof:name":"Coin Du Brasseur",
    "wof:placetype":"venue"
},
  "geometry": {"coordinates":[-71.336128,46.668713],"type":"Point"}
}