{
  "type": "Feature",
  "properties": {
    "iso:country":"CA",
    "sg:address":"607 Mccall St",
    "sg:city":"Oxbow",
    "sg:classifiers":[
        {
            "category":"Education",
            "subcategory":"Special Training",
            "type":"Public Place"
        }
    ],
    "sg:phone":"+1 306 483 2473",
    "sg:postcode":"S0C 2B0",
    "sg:province":"SK",
    "sg:tags":[
        "tutoring"
    ],
    "wof:name":"Marek Webb Communications",
    "wof:placetype":"venue"
},
  "geometry": {"coordinates":[-102.17251586899999,49.2280731201],"type":"Point"}
}