{
  "type": "Feature",
  "properties": {
    "addr:full":"3601 15 St SE Calgary AB T2G 3M6",
    "addr:housenumber":"3601",
    "addr:postcode":"t2g 3m6",
    "addr:street":"15 St Se",
    "iso:country":"CA",
    "sg:address":"3601 15 St SE",
    "sg:city":"Calgary",
    "sg:classifiers":[
        {
            "category":"Retail",
            "subcategory":"Repair Shop",
            "type":"Services"
        }
    ],
    "sg:phone":"+1 403 233 2342",
    "sg:postcode":"T2G 3M6",
    "sg:province":"AB",
    "sg:tags":[
        "welding"
    ],
    "wof:name":"Jimstar Welding Inc",
    "wof:placetype":"venue"
},
  "geometry": {"coordinates":[-114.025291,51.023052],"type":"Point"}
}