{
  "type": "Feature",
  "properties": {
    "iso:country":"CA",
    "sg:address":"10 Hillyard St",
    "sg:city":"Hamilton",
    "sg:classifiers":[
        {
            "category":"Manufacturing",
            "subcategory":"Metals",
            "type":"Manufacturing & Wholesale Goods"
        }
    ],
    "sg:phone":"+1 905 527 9178",
    "sg:postcode":"L8L 6B1",
    "sg:province":"ON",
    "sg:tags":[
        "die",
        "nonferrous",
        "casting",
        "alum"
    ],
    "wof:name":"Amcan Castings Ltd",
    "wof:placetype":"venue"
},
  "geometry": {"coordinates":[-79.8407897949,43.2645492554],"type":"Point"}
}