{
  "type": "Feature",
  "properties": {
    "iso:country":"CA",
    "sg:address":"501 Rue Notre-Dame",
    "sg:city":"Saint-Tite",
    "sg:classifiers":[
        {
            "category":"Professional",
            "subcategory":"Business Services",
            "type":"Services"
        }
    ],
    "sg:phone":"+1 418 365 6461",
    "sg:postcode":"G0X 3H0",
    "sg:province":"QC",
    "sg:tags":[
        "notary"
    ],
    "wof:name":"Francoeur, Rene",
    "wof:placetype":"venue"
},
  "geometry": {"coordinates":[-72.5650405884,46.7281951904],"type":"Point"}
}