{
  "type": "Feature",
  "properties": {
    "addr:full":"2768 Boul Beliveau Longueuil QC J4M 2A2",
    "addr:housenumber":"2768",
    "addr:postcode":"j4m 2a2",
    "addr:street":"Boul Beliveau",
    "iso:country":"CA",
    "sg:address":"2768 Boul Beliveau",
    "sg:city":"Longueuil",
    "sg:classifiers":[
        {
            "category":"Professional",
            "subcategory":"Advertising",
            "type":"Services"
        }
    ],
    "sg:phone":"+1 450 647 0800",
    "sg:postcode":"J4M 2A2",
    "sg:province":"QC",
    "sg:tags":[
        "publicity"
    ],
    "wof:name":"A C Fax Inc",
    "wof:placetype":"venue"
},
  "geometry": {"coordinates":[-73.450592,45.53722],"type":"Point"}
}