{
  "type": "Feature",
  "properties": {
    "addr:full":"Calgary AB T2P 3G3",
    "addr:postcode":"t2p 3g3",
    "iso:country":"CA",
    "sg:city":"Calgary",
    "sg:classifiers":[
        {
            "category":"Mining & Drilling",
            "type":"Manufacturing & Wholesale Goods"
        }
    ],
    "sg:phone":"+1 403 269 6749",
    "sg:postcode":"T2P 3G3",
    "sg:province":"AB",
    "sg:tags":[
        "company",
        "oil"
    ],
    "wof:name":"Chemnor Industries Ltd",
    "wof:placetype":"venue"
},
  "geometry": {"coordinates":[-114.078918457,51.0480194092],"type":"Point"}
}