{
  "type": "Feature",
  "properties": {
    "addr:full":"594766 Hwy 59 S Woodstock ON N4S 7V8",
    "addr:housenumber":"594766",
    "addr:postcode":"n4s 7v8",
    "addr:street":"Hwy 59 S",
    "iso:country":"CA",
    "sg:address":"594766 Hwy 59 S",
    "sg:city":"Woodstock",
    "sg:classifiers":[
        {
            "category":"Travel",
            "subcategory":"Hotels & Motels",
            "type":"Entertainment"
        }
    ],
    "sg:phone":"+1 519 456 8721",
    "sg:postcode":"N4S 7V8",
    "sg:province":"ON",
    "sg:tags":[
        "breakfast",
        "accommodation",
        "bed"
    ],
    "wof:name":"Heritage Guest House",
    "wof:placetype":"venue"
},
  "geometry": {"coordinates":[-80.768822,43.14732],"type":"Point"}
}