{
  "type": "Feature",
  "properties": {
    "iso:country":"CA",
    "sg:address":"277 6th Ave",
    "sg:city":"Cochrane",
    "sg:classifiers":[
        {
            "category":"Organizations",
            "subcategory":"Religious Organization",
            "type":"Services"
        }
    ],
    "sg:phone":"+1 705 272 4927",
    "sg:postcode":"P0L 1C0",
    "sg:province":"ON",
    "sg:tags":[
        "church"
    ],
    "wof:name":"First Baptist Church",
    "wof:placetype":"venue"
},
  "geometry": {"coordinates":[-81.02523040769999,49.0657119751],"type":"Point"}
}