{
  "type": "Feature",
  "properties": {
    "iso:country":"CA",
    "sg:address":"104 Clarence St",
    "sg:city":"Ottawa",
    "sg:classifiers":[
        {
            "category":"Bars & Pubs",
            "type":"Food & Drink"
        }
    ],
    "sg:phone":"+1 613 241 6581",
    "sg:postcode":"K1N 5P6",
    "sg:province":"ON",
    "sg:tags":[
        "club",
        "night"
    ],
    "wof:name":"China White Nightclub",
    "wof:placetype":"venue"
},
  "geometry": {"coordinates":[-75.692406,45.429199],"type":"Point"}
}