{
  "type": "Feature",
  "properties": {
    "addr:full":"104 Clarence St Ottawa ON K1N 5P6",
    "addr:housenumber":"104",
    "addr:postcode":"k1n 5p6",
    "addr:street":"Clarence St",
    "iso:country":"CA",
    "sg:address":"104 Clarence St",
    "sg:city":"Ottawa",
    "sg:classifiers":[
        {
            "category":"Bars & Pubs",
            "type":"Food & Drink"
        }
    ],
    "sg:phone":"+1 613 241 6581",
    "sg:postcode":"K1N 5P6",
    "sg:province":"ON",
    "sg:tags":[
        "club",
        "night"
    ],
    "wof:name":"China White Nightclub",
    "wof:placetype":"venue"
},
  "geometry": {"coordinates":[-75.69240600000001,45.429199],"type":"Point"}
}