{
  "type": "Feature",
  "properties": {
    "iso:country":"CA",
    "sg:address":"26 Rue Martial",
    "sg:city":"Berthierville",
    "sg:classifiers":[
        {
            "category":"Personal",
            "subcategory":"Beauty Salon",
            "type":"Services"
        }
    ],
    "sg:phone":"+1 450 836 4478",
    "sg:postcode":"J0K 1A0",
    "sg:province":"QC",
    "wof:name":"Salon DE Coiffure France",
    "wof:placetype":"venue"
},
  "geometry": {"coordinates":[-73.1784667969,46.0809059143],"type":"Point"}
}