{
  "type": "Feature",
  "properties": {
    "addr:full":"19320 Hammond Rd Pitt Meadows BC V3Y 1C2",
    "addr:housenumber":"19320",
    "addr:postcode":"v3y 1c2",
    "addr:street":"Hammond Rd",
    "iso:country":"CA",
    "sg:address":"19320 Hammond Rd",
    "sg:city":"Pitt Meadows",
    "sg:classifiers":[
        {
            "category":"Organizations",
            "subcategory":"Professional Association",
            "type":"Services"
        }
    ],
    "sg:phone":"+1 604 465 5119",
    "sg:postcode":"V3Y 1C2",
    "sg:province":"BC",
    "wof:name":"Manufactured Housing Assn-BC",
    "wof:placetype":"venue"
},
  "geometry": {"coordinates":[-122.686249,49.217018],"type":"Point"}
}