{
  "type": "Feature",
  "properties": {
    "addr:full":"8 School St Hartland NB E7P 1N8",
    "addr:housenumber":"8",
    "addr:postcode":"e7p 1n8",
    "addr:street":"School St",
    "iso:country":"CA",
    "sg:address":"8 School St",
    "sg:city":"Hartland",
    "sg:classifiers":[
        {
            "category":"Education",
            "subcategory":"School",
            "type":"Public Place"
        }
    ],
    "sg:phone":"+1 506 375 3000",
    "sg:postcode":"E7P 1N8",
    "sg:province":"NB",
    "wof:name":"Hartland High School",
    "wof:placetype":"venue"
},
  "geometry": {"coordinates":[-67.526016,46.300957],"type":"Point"}
}