{
  "type": "Feature",
  "properties": {
    "iso:country":"CA",
    "sg:address":"2491 Kingsway",
    "sg:city":"Vancouver",
    "sg:classifiers":[
        {
            "category":"Professional",
            "subcategory":"Accounting & Tax Preparation",
            "type":"Services"
        }
    ],
    "sg:phone":"+1 604 438 1611",
    "sg:postcode":"V5R 5G8",
    "sg:province":"BC",
    "sg:tags":[
        "consultant"
    ],
    "wof:name":"Bargate Services Ltd",
    "wof:placetype":"venue"
},
  "geometry": {"coordinates":[-123.05509948700001,49.2406387329],"type":"Point"}
}