{
  "type": "Feature",
  "properties": {
    "addr:full":"5445 Main St Weymouth NS B0W 3T0",
    "addr:housenumber":"5445",
    "addr:postcode":"b0w 3t0",
    "addr:street":"Main St",
    "iso:country":"CA",
    "sg:address":"5445 Main St",
    "sg:city":"Weymouth",
    "sg:classifiers":[
        {
            "category":"Food & Beverages",
            "subcategory":"Groceries & Convenience Stores",
            "type":"Retail Goods"
        }
    ],
    "sg:phone":"+1 902 837 7788",
    "sg:postcode":"B0W 3T0",
    "sg:province":"NS",
    "wof:name":"Weymouth Kwik-Way",
    "wof:placetype":"venue"
},
  "geometry": {"coordinates":[-66.00505065919999,44.4054450989],"type":"Point"}
}