{
  "type": "Feature",
  "properties": {
    "addr:full":"5103 Rice Lake Dr Bewdley ON K0L 1E0",
    "addr:housenumber":"5103",
    "addr:postcode":"k0l 1e0",
    "addr:street":"Rice Lake Dr",
    "iso:country":"CA",
    "sg:address":"5103 Rice Lake Dr",
    "sg:city":"Bewdley",
    "sg:classifiers":[
        {
            "category":"Shopping",
            "subcategory":"Bicycles & Sporting Goods",
            "type":"Retail Goods"
        }
    ],
    "sg:phone":"+1 905 797 2632",
    "sg:postcode":"K0L 1E0",
    "sg:province":"ON",
    "sg:tags":[
        "tackle",
        "fishing"
    ],
    "wof:name":"B J Tackle",
    "wof:placetype":"venue"
},
  "geometry": {"coordinates":[-78.32266235349999,44.0901298523],"type":"Point"}
}