{
  "type": "Feature",
  "properties": {
    "addr:full":"Winnipeg MB R3B 0W5",
    "addr:postcode":"r3b 0w5",
    "iso:country":"CA",
    "sg:city":"Winnipeg",
    "sg:classifiers":[
        {
            "category":"Social Services",
            "type":"Services"
        }
    ],
    "sg:phone":"+1 204 943 1377",
    "sg:postcode":"R3B 0W5",
    "sg:province":"MB",
    "sg:tags":[
        "counselor",
        "marriage",
        "family"
    ],
    "wof:name":"Sellick & Assoc",
    "wof:placetype":"venue"
},
  "geometry": {"coordinates":[-97.137421,49.896297],"type":"Point"}
}