{
  "type": "Feature",
  "properties": {
    "addr:full":"1222 Boul Cure-Labelle Laval QC H7V 2V5",
    "addr:housenumber":"1222",
    "addr:postcode":"h7v 2v5",
    "addr:street":"Boul Cure-Labelle",
    "iso:country":"CA",
    "sg:address":"1222 Boul Cure-Labelle",
    "sg:city":"Laval",
    "sg:classifiers":[
        {
            "category":"Manufacturing",
            "subcategory":"Signs",
            "type":"Manufacturing & Wholesale Goods"
        }
    ],
    "sg:phone":"+1 450 681 7180",
    "sg:postcode":"H7V 2V5",
    "sg:province":"QC",
    "wof:name":"Graphoteque Cesar",
    "wof:placetype":"venue"
},
  "geometry": {"coordinates":[-73.75338000000001,45.545345],"type":"Point"}
}