{
  "type": "Feature",
  "properties": {
    "addr:full":"1320 Rue Saint-Antoine O Montreal QC H3C 1C2",
    "addr:housenumber":"1320",
    "addr:postcode":"h3c 1c2",
    "addr:street":"Rue Saint-Antoine O",
    "iso:country":"CA",
    "sg:address":"1320 Rue Saint-Antoine O",
    "sg:city":"Montreal",
    "sg:classifiers":[
        {
            "category":"Travel",
            "subcategory":"Hotels & Motels",
            "type":"Entertainment"
        }
    ],
    "sg:phone":"+1 514 989 0300",
    "sg:postcode":"H3C 1C2",
    "sg:province":"QC",
    "wof:name":"Hotel Du Nouveau Forum",
    "wof:placetype":"venue"
},
  "geometry": {"coordinates":[-73.56926,45.494785],"type":"Point"}
}