{
  "type": "Feature",
  "properties": {
    "addr:full":"790 2nd Ave E Owen Sound ON N4K 2H1",
    "addr:housenumber":"790",
    "addr:postcode":"n4k 2h1",
    "addr:street":"2Nd Ave E",
    "iso:country":"CA",
    "sg:address":"790 2nd Ave E",
    "sg:city":"Owen Sound",
    "sg:classifiers":[
        {
            "category":"Home & Garden",
            "subcategory":"Furniture",
            "type":"Retail Goods"
        }
    ],
    "sg:phone":"+1 519 376 0476",
    "sg:postcode":"N4K 2H1",
    "sg:province":"ON",
    "wof:name":"Legate Furniture CO Ltd",
    "wof:placetype":"venue"
},
  "geometry": {"coordinates":[-80.942497,44.563576],"type":"Point"}
}