{
  "type": "Feature",
  "properties": {
    "addr:full":"2813 Boul Laurier Sainte-Foy QC G1V 2L9",
    "addr:housenumber":"2813",
    "addr:postcode":"g1v 2l9",
    "addr:street":"Boul Laurier",
    "iso:country":"CA",
    "sg:address":"2813 Boul Laurier",
    "sg:city":"Sainte-Foy",
    "sg:classifiers":[
        {
            "category":"Restaurant",
            "type":"Food & Drink"
        }
    ],
    "sg:phone":"+1 418 652 2001",
    "sg:postcode":"G1V 2L9",
    "sg:province":"QC",
    "wof:name":"Cosmos",
    "wof:placetype":"venue"
},
  "geometry": {"coordinates":[-71.2867889404,46.7677879333],"type":"Point"}
}