{
  "type": "Feature",
  "properties": {
    "addr:full":"4312 15 St SW Calgary AB T2T 4B2",
    "addr:housenumber":"4312",
    "addr:postcode":"t2t 4b2",
    "addr:street":"15 St Sw",
    "iso:country":"CA",
    "sg:address":"4312 15 St SW",
    "sg:city":"Calgary",
    "sg:classifiers":[
        {
            "category":"Travel",
            "subcategory":"Hotels & Motels",
            "type":"Entertainment"
        }
    ],
    "sg:phone":"+1 403 287 3820",
    "sg:postcode":"T2T 4B2",
    "sg:province":"AB",
    "sg:tags":[
        "breakfast",
        "accommodation",
        "bed"
    ],
    "wof:name":"Sanderson Manor B & B",
    "wof:placetype":"venue"
},
  "geometry": {"coordinates":[-114.09736599999999,51.015636],"type":"Point"}
}