{
  "type": "Feature",
  "properties": {
    "addr:full":"160 Boul Cure-Labelle Sainte-Rose QC H7L 2Z7",
    "addr:housenumber":"160",
    "addr:postcode":"h7l 2z7",
    "addr:street":"Boul Cure-Labelle",
    "iso:country":"CA",
    "sg:address":"160 Boul Cure-Labelle",
    "sg:city":"Sainte-Rose",
    "sg:classifiers":[
        {
            "category":"Wholesale",
            "subcategory":"Furniture",
            "type":"Manufacturing & Wholesale Goods"
        }
    ],
    "sg:phone":"+1 450 622 3344",
    "sg:postcode":"H7L 2Z7",
    "sg:province":"QC",
    "wof:name":"Industries Okaply Ltee",
    "wof:placetype":"venue"
},
  "geometry": {"coordinates":[-73.7908248901,45.6068763733],"type":"Point"}
}