{
  "type": "Feature",
  "properties": {
    "addr:full":"635 James St N Lumsden SK S0G 3C0",
    "addr:housenumber":"635",
    "addr:postcode":"s0g 3c0",
    "addr:street":"James St N",
    "iso:country":"CA",
    "sg:address":"635 James St N",
    "sg:city":"Lumsden",
    "sg:classifiers":[
        {
            "category":"Personal",
            "subcategory":"Beauty Salon",
            "type":"Services"
        }
    ],
    "sg:phone":"+1 306 731 3655",
    "sg:postcode":"S0G 3C0",
    "sg:province":"SK",
    "wof:name":"Kathleen's Hair Shop",
    "wof:placetype":"venue"
},
  "geometry": {"coordinates":[-104.866692,50.64719],"type":"Point"}
}