{
  "type": "Feature",
  "properties": {
    "addr:full":"1128 Hastings St W # 449 Vancouver BC V6E 4R5",
    "addr:housenumber":"1128",
    "addr:postcode":"v6e 4r5",
    "addr:street":"Hastings St W # 449",
    "iso:country":"CA",
    "sg:address":"1128 Hastings St W # 449",
    "sg:city":"Vancouver",
    "sg:classifiers":[
        {
            "category":"Shopping",
            "subcategory":"Tobacco",
            "type":"Retail Goods"
        }
    ],
    "sg:phone":"+1 604 684 7784",
    "sg:postcode":"V6E 4R5",
    "sg:province":"BC",
    "sg:tags":[
        "cigarette",
        "cigar",
        "dealer"
    ],
    "wof:name":"Picadilly Place",
    "wof:placetype":"venue"
},
  "geometry": {"coordinates":[-123.120788574,49.2881088257],"type":"Point"}
}