{
  "type": "Feature",
  "properties": {
    "addr:full":"55 Patterson Rd Barrie ON L4N 3V9",
    "addr:housenumber":"55",
    "addr:postcode":"l4n 3v9",
    "addr:street":"Patterson Rd",
    "iso:country":"CA",
    "sg:address":"55 Patterson Rd",
    "sg:city":"Barrie",
    "sg:classifiers":[
        {
            "category":"Professional",
            "subcategory":"Computer Services",
            "type":"Services"
        }
    ],
    "sg:phone":"+1 705 722 7300",
    "sg:postcode":"L4N 3V9",
    "sg:province":"ON",
    "sg:tags":[
        "consultant",
        "telecommunication",
        "internet"
    ],
    "wof:name":"Scbn Telecommunications Inc",
    "wof:placetype":"venue"
},
  "geometry": {"coordinates":[-79.7077865601,44.3663368225],"type":"Point"}
}