{
  "type": "Feature",
  "properties": {
    "addr:full":"13657 20A Ave Surrey BC V4A 9V7",
    "addr:housenumber":"13657",
    "addr:postcode":"v4a 9v7",
    "addr:street":"20A Ave",
    "iso:country":"CA",
    "sg:address":"13657 20A Ave",
    "sg:city":"Surrey",
    "sg:classifiers":[
        {
            "category":"Real Estate",
            "subcategory":"Surveying",
            "type":"Services"
        }
    ],
    "sg:phone":"+1 604 535 5800",
    "sg:postcode":"V4A 9V7",
    "sg:province":"BC",
    "sg:tags":[
        "surveyor"
    ],
    "wof:name":"James Bush & Assoc",
    "wof:placetype":"venue"
},
  "geometry": {"coordinates":[-122.830215,49.105179],"type":"Point"}
}