{
  "type": "Feature",
  "properties": {
    "addr:full":"839 Boul Saint-Germain Rimouski QC G5L 3T5",
    "addr:housenumber":"839",
    "addr:postcode":"g5l 3t5",
    "addr:street":"Boul Saint-Germain",
    "iso:country":"CA",
    "sg:address":"839 Boul Saint-Germain",
    "sg:city":"Rimouski",
    "sg:classifiers":[
        {
            "category":"Organizations",
            "subcategory":"Religious Organization",
            "type":"Services"
        }
    ],
    "sg:phone":"+1 418 723 2853",
    "sg:postcode":"G5L 3T5",
    "sg:province":"QC",
    "sg:tags":[
        "church"
    ],
    "wof:name":"Presbytere Sacre-Coeur",
    "wof:placetype":"venue"
},
  "geometry": {"coordinates":[-68.5903091431,48.4277648926],"type":"Point"}
}