{
  "type": "Feature",
  "properties": {
    "addr:full":"330 Main St Bath NB E7J 1A2",
    "addr:housenumber":"330",
    "addr:postcode":"e7j 1a2",
    "addr:street":"Main St",
    "iso:country":"CA",
    "sg:address":"330 Main St",
    "sg:city":"Bath",
    "sg:classifiers":[
        {
            "category":"Personal",
            "subcategory":"Beauty Salon",
            "type":"Services"
        }
    ],
    "sg:phone":"+1 506 278 5646",
    "sg:postcode":"E7J 1A2",
    "sg:province":"NB",
    "wof:name":"Hair 4U",
    "wof:placetype":"venue"
},
  "geometry": {"coordinates":[-67.59474945069999,46.5092964172],"type":"Point"}
}