{
  "type": "Feature",
  "properties": {
    "addr:full":"35 Rue Lisa Saint-Etienne-Des-Gres QC G0X 2P0",
    "addr:housenumber":"35",
    "addr:postcode":"g0x 2p0",
    "addr:street":"Rue Lisa Saint-Etienne-Des-Gres",
    "iso:country":"CA",
    "sg:address":"35 Rue Lisa",
    "sg:city":"Saint-Etienne-Des-Gres",
    "sg:classifiers":[
        {
            "category":"Building & Trades",
            "subcategory":"Construction",
            "type":"Services"
        }
    ],
    "sg:phone":"+1 819 535 5376",
    "sg:postcode":"G0X 2P0",
    "sg:province":"QC",
    "sg:tags":[
        "repairing",
        "contractor",
        "remodeling",
        "general"
    ],
    "wof:name":"Renovation Guy Lord Inc",
    "wof:placetype":"venue"
},
  "geometry": {"coordinates":[-72.79486799999999,46.436058],"type":"Point"}
}