{
  "type": "Feature",
  "properties": {
    "addr:full":"139 Rue Commerciale Cabano QC G0L 1E0",
    "addr:housenumber":"139",
    "addr:postcode":"g0l 1e0",
    "addr:street":"Rue Commerciale",
    "iso:country":"CA",
    "sg:address":"139 Rue Commerciale",
    "sg:city":"Cabano",
    "sg:classifiers":[
        {
            "category":"Social Services",
            "subcategory":"Child Care",
            "type":"Services"
        }
    ],
    "sg:phone":"+1 418 854 0255",
    "sg:postcode":"G0L 1E0",
    "sg:province":"QC",
    "wof:name":"Centre DE LA Petite Enfance",
    "wof:placetype":"venue"
},
  "geometry": {"coordinates":[-68.87696099999999,47.682659],"type":"Point"}
}