{
  "type": "Feature",
  "properties": {
    "addr:full":"50 Rue Cartier Saint-Lambert QC J4R 2S4",
    "addr:housenumber":"50",
    "addr:postcode":"j4r 2s4",
    "addr:street":"Rue Cartier",
    "iso:country":"CA",
    "sg:address":"50 Rue Cartier",
    "sg:city":"Saint-Lambert",
    "sg:classifiers":[
        {
            "category":"Professional",
            "subcategory":"Art Services",
            "type":"Services"
        }
    ],
    "sg:phone":"+1 450 672 6880",
    "sg:postcode":"J4R 2S4",
    "sg:province":"QC",
    "sg:tags":[
        "graphic",
        "designer"
    ],
    "wof:name":"Rive Sud Typo Svc Inc",
    "wof:placetype":"venue"
},
  "geometry": {"coordinates":[-73.504662,45.498817],"type":"Point"}
}