{
  "type": "Feature",
  "properties": {
    "addr:full":"397 S Edgeware Rd St Thomas ON N5P 4B8",
    "addr:housenumber":"397",
    "addr:postcode":"n5p 4b8",
    "addr:street":"S Edgeware Rd",
    "iso:country":"CA",
    "sg:address":"397 S Edgeware Rd",
    "sg:city":"St Thomas",
    "sg:classifiers":[
        {
            "category":"Retail",
            "subcategory":"Auto Repair",
            "type":"Services"
        }
    ],
    "sg:phone":"+1 519 637 9861",
    "sg:postcode":"N5P 4B8",
    "sg:province":"ON",
    "sg:tags":[
        "repairing",
        "automobile"
    ],
    "wof:name":"Witlox Automotive",
    "wof:placetype":"venue"
},
  "geometry": {"coordinates":[-81.154793,42.79245],"type":"Point"}
}