{
  "type": "Feature",
  "properties": {
    "addr:full":"RR 1 Lcd 1 Red Deer AB T4N 5E1",
    "addr:housenumber":"1",
    "addr:postcode":"t4n 5e1",
    "addr:street":"Rr 1 Lcd",
    "iso:country":"CA",
    "sg:address":"RR 1 Lcd 1",
    "sg:city":"Red Deer",
    "sg:classifiers":[
        {
            "category":"Professional",
            "subcategory":"Business Services",
            "type":"Services"
        }
    ],
    "sg:phone":"+1 403 347 6100",
    "sg:postcode":"T4N 5E1",
    "sg:province":"AB",
    "sg:tags":[
        "livestock",
        "auctioneer"
    ],
    "wof:name":"Burnt Lake Livestock Mart Ltd",
    "wof:placetype":"venue"
},
  "geometry": {"coordinates":[-113.817436,52.262302],"type":"Point"}
}