{
  "type": "Feature",
  "properties": {
    "iso:country":"CA",
    "sg:address":"731 Belfast Rd",
    "sg:city":"Ottawa",
    "sg:classifiers":[
        {
            "category":"Manufacturing",
            "subcategory":"Paper Products",
            "type":"Manufacturing & Wholesale Goods"
        }
    ],
    "sg:phone":"+1 613 244 7225",
    "sg:postcode":"K1G 0Z4",
    "sg:province":"ON",
    "sg:tags":[
        "corrugated",
        "solid",
        "fiber",
        "box"
    ],
    "wof:name":"Cartier Supply & Rentals Ltd",
    "wof:placetype":"venue"
},
  "geometry": {"coordinates":[-75.6415557861,45.4146766663],"type":"Point"}
}