{
  "type": "Feature",
  "properties": {
    "addr:full":"Bedford NS B4A 3Y4",
    "addr:postcode":"b4a 3y4",
    "iso:country":"CA",
    "sg:city":"Bedford",
    "sg:classifiers":[
        {
            "category":"Education",
            "subcategory":"Dance Studio",
            "type":"Public Place"
        }
    ],
    "sg:phone":"+1 902 835 5776",
    "sg:postcode":"B4A 3Y4",
    "sg:province":"NS",
    "sg:tags":[
        "instruction",
        "dancing"
    ],
    "wof:name":"Maritime Dance Academy",
    "wof:placetype":"venue"
},
  "geometry": {"coordinates":[-63.655972,44.73278],"type":"Point"}
}