{
  "type": "Feature",
  "properties": {
    "addr:full":"Toronto ON M4X 1W4",
    "addr:postcode":"m4x 1w4",
    "iso:country":"CA",
    "sg:city":"Toronto",
    "sg:classifiers":[
        {
            "category":"Health Services",
            "subcategory":"Doctor",
            "type":"Services"
        }
    ],
    "sg:phone":"+1 416 925 8181",
    "sg:postcode":"M4X 1W4",
    "sg:province":"ON",
    "sg:tags":[
        "physician",
        "surgeon"
    ],
    "wof:name":"Patricio, Rodolfo V MD",
    "wof:placetype":"venue"
},
  "geometry": {"coordinates":[-79.376671,43.671528],"type":"Point"}
}