{
  "type": "Feature",
  "properties": {
    "addr:full":"120 Barton St E Hamilton ON L8L 2W3",
    "addr:housenumber":"120",
    "addr:postcode":"l8l 2w3",
    "addr:street":"Barton St E",
    "iso:country":"CA",
    "sg:address":"120 Barton St E",
    "sg:city":"Hamilton",
    "sg:classifiers":[
        {
            "category":"Manufacturing",
            "subcategory":"Printing",
            "type":"Manufacturing & Wholesale Goods"
        }
    ],
    "sg:phone":"+1 905 570 1953",
    "sg:postcode":"L8L 2W3",
    "sg:province":"ON",
    "sg:tags":[
        "printer"
    ],
    "wof:name":"Maroc Printing",
    "wof:placetype":"venue"
},
  "geometry": {"coordinates":[-79.86113,43.262791],"type":"Point"}
}