{
  "type": "Feature",
  "properties": {
    "addr:full":"Ottawa ON K2P 0G5",
    "addr:postcode":"k2p 0g5",
    "iso:country":"CA",
    "sg:city":"Ottawa",
    "sg:classifiers":[
        {
            "category":"Professional",
            "subcategory":"Management & Consulting",
            "type":"Services"
        }
    ],
    "sg:phone":"+1 613 235 4778",
    "sg:postcode":"K2P 0G5",
    "sg:province":"ON",
    "sg:tags":[
        "consultant",
        "telecommunication"
    ],
    "wof:name":"Comgate Engineering",
    "wof:placetype":"venue"
},
  "geometry": {"coordinates":[-75.6942977905,45.4173049927],"type":"Point"}
}