{
  "type": "Feature",
  "properties": {
    "addr:full":"Missanabie ON P0M 2H0",
    "addr:postcode":"p0m 2h0",
    "iso:country":"CA",
    "sg:city":"Missanabie",
    "sg:classifiers":[
        {
            "category":"Health Services",
            "subcategory":"Doctor",
            "type":"Services"
        }
    ],
    "sg:phone":"+1 705 234 2581",
    "sg:postcode":"P0M 2H0",
    "sg:province":"ON",
    "sg:tags":[
        "clinic"
    ],
    "wof:name":"Missanabie Health Ctr",
    "wof:placetype":"venue"
},
  "geometry": {"coordinates":[-84.052155,48.316563],"type":"Point"}
}