{
  "type": "Feature",
  "properties": {
    "addr:full":"1319 Marine Dr SE Vancouver BC V5X 4L1",
    "addr:housenumber":"1319",
    "addr:postcode":"v5x 4l1",
    "addr:street":"Marine Dr Se",
    "iso:country":"CA",
    "sg:address":"1319 Marine Dr SE",
    "sg:city":"Vancouver",
    "sg:classifiers":[
        {
            "category":"Manufacturing",
            "subcategory":"Signs",
            "type":"Manufacturing & Wholesale Goods"
        }
    ],
    "sg:phone":"+1 604 327 1880",
    "sg:postcode":"V5X 4L1",
    "sg:province":"BC",
    "wof:name":"Irresistable Signage-Displays",
    "wof:placetype":"venue"
},
  "geometry": {"coordinates":[-123.079865,49.21106],"type":"Point"}
}