{
  "type": "Feature",
  "properties": {
    "addr:full":"Victoriaville QC G6P 7E4",
    "addr:postcode":"g6p 7e4",
    "iso:country":"CA",
    "sg:city":"Victoriaville",
    "sg:classifiers":[
        {
            "category":"Professional",
            "subcategory":"Art Services",
            "type":"Services"
        }
    ],
    "sg:phone":"+1 819 752 2498",
    "sg:postcode":"G6P 7E4",
    "sg:province":"QC",
    "sg:tags":[
        "graphic",
        "designer"
    ],
    "wof:name":"Imprimerie Hebert Inc",
    "wof:placetype":"venue"
},
  "geometry": {"coordinates":[-71.960251,46.071274],"type":"Point"}
}