{
  "type": "Feature",
  "properties": {
    "iso:country":"CA",
    "sg:city":"Newmarket",
    "sg:classifiers":[
        {
            "category":"Travel",
            "subcategory":"Hotels & Motels",
            "type":"Entertainment"
        }
    ],
    "sg:phone":"+1 905 895 4585",
    "sg:postcode":"L3Y 4V8",
    "sg:province":"ON",
    "wof:name":"Newmarket Inn",
    "wof:placetype":"venue"
},
  "geometry": {"coordinates":[-79.4585723877,44.0401802063],"type":"Point"}
}