{
  "type": "Feature",
  "properties": {
    "addr:full":"67 Front St E Toronto ON M5E 1B5",
    "addr:housenumber":"67",
    "addr:postcode":"m5e 1b5",
    "addr:street":"Front St E",
    "iso:country":"CA",
    "sg:address":"67 Front St E",
    "sg:city":"Toronto",
    "sg:classifiers":[
        {
            "category":"Shopping",
            "subcategory":"Shoes",
            "type":"Retail Goods"
        }
    ],
    "sg:phone":"+1 416 363 2015",
    "sg:postcode":"M5E 1B5",
    "sg:province":"ON",
    "wof:name":"Harry Young Shoes",
    "wof:placetype":"venue"
},
  "geometry": {"coordinates":[-79.3734130859,43.6484909058],"type":"Point"}
}