{
  "type": "Feature",
  "properties": {
    "addr:full":"52 Lawrence Cres Toronto ON M4N 1N2",
    "addr:housenumber":"52",
    "addr:postcode":"m4n 1n2",
    "addr:street":"Lawrence Cres",
    "iso:country":"CA",
    "sg:address":"52 Lawrence Cres",
    "sg:city":"Toronto",
    "sg:classifiers":[
        {
            "category":"Professional",
            "subcategory":"Management & Consulting",
            "type":"Services"
        }
    ],
    "sg:phone":"+1 416 482 5030",
    "sg:postcode":"M4N 1N2",
    "sg:province":"ON",
    "sg:tags":[
        "consultant",
        "business"
    ],
    "wof:name":"Jar Corp",
    "wof:placetype":"venue"
},
  "geometry": {"coordinates":[-79.395233,43.724243],"type":"Point"}
}