{
  "type": "Feature",
  "properties": {
    "addr:full":"8395 Ruskin Pl Richmond BC V7A 2E3",
    "addr:housenumber":"8395",
    "addr:postcode":"v7a 2e3",
    "addr:street":"Ruskin Pl",
    "iso:country":"CA",
    "sg:address":"8395 Ruskin Pl",
    "sg:city":"Richmond",
    "sg:classifiers":[
        {
            "category":"Autos & Motor Vehicles",
            "subcategory":"Boat Sales",
            "type":"Retail Goods"
        }
    ],
    "sg:phone":"+1 604 612 4950",
    "sg:postcode":"V7A 2E3",
    "sg:province":"BC",
    "sg:tags":[
        "top",
        "upholstery",
        "cover"
    ],
    "wof:name":"Gary's Boat Tops",
    "wof:placetype":"venue"
},
  "geometry": {"coordinates":[-123.13153800000001,49.139233],"type":"Point"}
}