{
  "type": "Feature",
  "properties": {
    "addr:full":"Saint-Alexis-Des-Monts QC J0K 1V0",
    "addr:postcode":"j0k 1v0",
    "iso:country":"CA",
    "sg:city":"Saint-Alexis-Des-Monts",
    "sg:classifiers":[
        {
            "category":"Organizations",
            "subcategory":"Professional Association",
            "type":"Services"
        }
    ],
    "sg:phone":"+1 819 265 3889",
    "sg:postcode":"J0K 1V0",
    "sg:province":"QC",
    "wof:name":"Festival DE LA Truite Mouchete",
    "wof:placetype":"venue"
},
  "geometry": {"coordinates":[-73.1437759399,46.463104248],"type":"Point"}
}