{
  "type": "Feature",
  "properties": {
    "iso:country":"CA",
    "sg:address":"166 Rue Saint-Redempteur",
    "sg:city":"Hull",
    "sg:classifiers":[
        {
            "category":"Food & Beverages",
            "subcategory":"Groceries & Convenience Stores",
            "type":"Retail Goods"
        }
    ],
    "sg:phone":"+1 819 777 3843",
    "sg:postcode":"J8X 2S3",
    "sg:province":"QC",
    "sg:tags":[
        "grocer"
    ],
    "wof:name":"Depanneur 7 Jours",
    "wof:placetype":"venue"
},
  "geometry": {"coordinates":[-75.721634,45.431015],"type":"Point"}
}