{
  "type": "Feature",
  "properties": {
    "addr:full":"11 Carlaw Ave # 6 Toronto ON M4M 2R6",
    "addr:housenumber":"11",
    "addr:postcode":"m4m 2r6",
    "addr:street":"Carlaw Ave # 6",
    "iso:country":"CA",
    "sg:address":"11 Carlaw Ave # 6",
    "sg:city":"Toronto",
    "sg:classifiers":[
        {
            "category":"Professional",
            "subcategory":"Art Services",
            "type":"Services"
        }
    ],
    "sg:phone":"+1 416 463 3914",
    "sg:postcode":"M4M 2R6",
    "sg:province":"ON",
    "sg:tags":[
        "photographer"
    ],
    "wof:name":"Matthew Plexman Photography",
    "wof:placetype":"venue"
},
  "geometry": {"coordinates":[-79.337677,43.655762],"type":"Point"}
}