{
  "type": "Feature",
  "properties": {
    "addr:full":"1295 North Service Rd Burlington ON L7P 4W1",
    "addr:housenumber":"1295",
    "addr:postcode":"l7p 4w1",
    "addr:street":"North Service Rd",
    "iso:country":"CA",
    "sg:address":"1295 North Service Rd",
    "sg:city":"Burlington",
    "sg:classifiers":[
        {
            "category":"Organizations",
            "subcategory":"Religious Organization",
            "type":"Services"
        }
    ],
    "sg:phone":"+1 905 331 1830",
    "sg:postcode":"L7P 4W1",
    "sg:province":"ON",
    "wof:name":"Promise Keepers Canada",
    "wof:placetype":"venue"
},
  "geometry": {"coordinates":[-79.83358800000001,43.337315],"type":"Point"}
}