{
  "type": "Feature",
  "properties": {
    "iso:country":"CA",
    "sg:address":"206 King George Rd",
    "sg:city":"Brantford",
    "sg:classifiers":[
        {
            "category":"Shopping",
            "subcategory":"Gifts & Souvenirs",
            "type":"Retail Goods"
        }
    ],
    "sg:phone":"+1 519 753 2056",
    "sg:postcode":"N3R 5L3",
    "sg:province":"ON",
    "sg:tags":[
        "party",
        "supply"
    ],
    "wof:name":"Party Particulars",
    "wof:placetype":"venue"
},
  "geometry": {"coordinates":[-80.27825164790001,43.1746826172],"type":"Point"}
}