{
  "type": "Feature",
  "properties": {
    "addr:full":"204 Huron St Woodstock ON N4S 7A1",
    "addr:housenumber":"204",
    "addr:postcode":"n4s 7a1",
    "addr:street":"Huron St",
    "iso:country":"CA",
    "sg:address":"204 Huron St",
    "sg:city":"Woodstock",
    "sg:classifiers":[
        {
            "category":"Social Services",
            "subcategory":"Child Care",
            "type":"Services"
        }
    ],
    "sg:phone":"+1 519 539 4419",
    "sg:postcode":"N4S 7A1",
    "sg:province":"ON",
    "wof:name":"Oxford Community Child Care",
    "wof:placetype":"venue"
},
  "geometry": {"coordinates":[-80.7493515015,43.1383552551],"type":"Point"}
}