{
  "type": "Feature",
  "properties": {
    "addr:full":"Montreal QC H1V 3R9",
    "addr:postcode":"h1v 3r9",
    "iso:country":"CA",
    "sg:city":"Montreal",
    "sg:classifiers":[
        {
            "category":"Professional",
            "subcategory":"Engineering",
            "type":"Services"
        }
    ],
    "sg:phone":"+1 514 257 0707",
    "sg:postcode":"H1V 3R9",
    "sg:province":"QC",
    "sg:tags":[
        "engineer"
    ],
    "wof:name":"Genivel Bpr Inc",
    "wof:placetype":"venue"
},
  "geometry": {"coordinates":[-73.553223,45.566692],"type":"Point"}
}