{
  "type": "Feature",
  "properties": {
    "addr:full":"1419 6E Av Grand-Mere QC G9T 2J9",
    "addr:housenumber":"1419",
    "addr:postcode":"g9t 2j9",
    "addr:street":"6E Av Grand-Mere",
    "iso:country":"CA",
    "sg:address":"1419 6E Av",
    "sg:city":"Grand-Mere",
    "sg:classifiers":[
        {
            "category":"Restaurant",
            "type":"Food & Drink"
        }
    ],
    "sg:phone":"+1 819 538 5451",
    "sg:postcode":"G9T 2J9",
    "sg:province":"QC",
    "wof:name":"Restaurant Jeannot",
    "wof:placetype":"venue"
},
  "geometry": {"coordinates":[-72.701965332,46.607837677],"type":"Point"}
}