{
  "type": "Feature",
  "properties": {
    "addr:full":"56 Water St Port Perry ON L9L 1J2",
    "addr:housenumber":"56",
    "addr:postcode":"l9l 1j2",
    "addr:street":"Water St",
    "iso:country":"CA",
    "sg:address":"56 Water St",
    "sg:city":"Port Perry",
    "sg:classifiers":[
        {
            "category":"Restaurant",
            "type":"Food & Drink"
        }
    ],
    "sg:phone":"+1 905 985 6776",
    "sg:postcode":"L9L 1J2",
    "sg:province":"ON",
    "wof:name":"Duke of Durham",
    "wof:placetype":"venue"
},
  "geometry": {"coordinates":[-78.9403839111,44.1024589539],"type":"Point"}
}