{
  "type": "Feature",
  "properties": {
    "addr:full":"485 York St London ON N6B 1R4",
    "addr:housenumber":"485",
    "addr:postcode":"n6b 1r4",
    "addr:street":"York St",
    "iso:country":"CA",
    "sg:address":"485 York St",
    "sg:city":"London",
    "sg:classifiers":[
        {
            "category":"Retail",
            "subcategory":"Auto Repair",
            "type":"Services"
        }
    ],
    "sg:phone":"+1 519 438 5175",
    "sg:postcode":"N6B 1R4",
    "sg:province":"ON",
    "sg:tags":[
        "body",
        "automobile",
        "painting"
    ],
    "wof:name":"Burwell Auto Body Ltd",
    "wof:placetype":"venue"
},
  "geometry": {"coordinates":[-81.234932,42.984909],"type":"Point"}
}