{
  "type": "Feature",
  "properties": {
    "iso:country":"CA",
    "sg:city":"Coquitlam",
    "sg:classifiers":[
        {
            "category":"Banks & Credit Unions",
            "subcategory":"Bank",
            "type":"Services"
        }
    ],
    "sg:phone":"+1 604 931 6599",
    "sg:postcode":"V3K 3V8",
    "sg:province":"BC",
    "sg:tags":[
        "check",
        "exchange",
        "cashing",
        "broker",
        "foreign",
        "dealer"
    ],
    "wof:name":"Best Currency Exchange Ltd",
    "wof:placetype":"venue"
},
  "geometry": {"coordinates":[-122.89241,49.243439],"type":"Point"}
}