{
  "type": "Feature",
  "properties": {
    "addr:full":"Montreal QC H3W 1X3",
    "addr:postcode":"h3w 1x3",
    "iso:country":"CA",
    "sg:city":"Montreal",
    "sg:classifiers":[
        {
            "category":"Personal",
            "type":"Services"
        }
    ],
    "sg:phone":"+1 514 369 4647",
    "sg:postcode":"H3W 1X3",
    "sg:province":"QC",
    "sg:tags":[
        "dating"
    ],
    "wof:name":"A 2 Agence DE Rencontre",
    "wof:placetype":"venue"
},
  "geometry": {"coordinates":[-73.6264801025,45.4864845276],"type":"Point"}
}