{
  "type": "Feature",
  "properties": {
    "addr:full":"1711 Boul Des Laurentides Laval QC H7M 2P5",
    "addr:housenumber":"1711",
    "addr:postcode":"h7m 2p5",
    "addr:street":"Boul Des Laurentides",
    "iso:country":"CA",
    "sg:address":"1711 Boul Des Laurentides",
    "sg:city":"Laval",
    "sg:classifiers":[
        {
            "category":"Personal",
            "subcategory":"Barber",
            "type":"Services"
        }
    ],
    "sg:phone":"+1 450 667 2863",
    "sg:postcode":"H7M 2P5",
    "sg:province":"QC",
    "sg:tags":[
        "salon",
        "beauty"
    ],
    "wof:name":"Salon Coiff Plus Pour Lui",
    "wof:placetype":"venue"
},
  "geometry": {"coordinates":[-73.7221374512,45.5972824097],"type":"Point"}
}