{
  "type": "Feature",
  "properties": {
    "addr:full":"3125 Steele St Victoria BC V8Z 3N7",
    "addr:housenumber":"3125",
    "addr:postcode":"v8z 3n7",
    "addr:street":"Steele St",
    "iso:country":"CA",
    "sg:address":"3125 Steele St",
    "sg:city":"Victoria",
    "sg:classifiers":[
        {
            "category":"Wholesale",
            "subcategory":"Electrical",
            "type":"Manufacturing & Wholesale Goods"
        }
    ],
    "sg:phone":"+1 250 383 1116",
    "sg:postcode":"V8Z 3N7",
    "sg:province":"BC",
    "sg:tags":[
        "equipment",
        "electric",
        "supply"
    ],
    "wof:name":"Nedco",
    "wof:placetype":"venue"
},
  "geometry": {"coordinates":[-123.374130249,48.4454421997],"type":"Point"}
}