{
  "type": "Feature",
  "properties": {
    "addr:full":"1 Greenleaf Crt Belleville ON K8N 5T5",
    "addr:housenumber":"1",
    "addr:postcode":"k8n 5t5",
    "addr:street":"Greenleaf Crt",
    "iso:country":"CA",
    "sg:address":"1 Greenleaf Crt",
    "sg:city":"Belleville",
    "sg:classifiers":[
        {
            "category":"Manufacturing",
            "subcategory":"Motor Vehicles & Parts",
            "type":"Manufacturing & Wholesale Goods"
        }
    ],
    "sg:phone":"+1 613 969 9522",
    "sg:postcode":"K8N 5T5",
    "sg:province":"ON",
    "sg:tags":[
        "automobile",
        "supply"
    ],
    "wof:name":"Prime Auto Machinery Corp",
    "wof:placetype":"venue"
},
  "geometry": {"coordinates":[-77.36408996580001,44.1874008179],"type":"Point"}
}