{
  "type": "Feature",
  "properties": {
    "addr:full":"Dieppe NB E1A 1P6",
    "addr:postcode":"e1a 1p6",
    "iso:country":"CA",
    "sg:city":"Dieppe",
    "sg:classifiers":[
        {
            "category":"Health Services",
            "subcategory":"Doctor",
            "type":"Services"
        }
    ],
    "sg:phone":"+1 506 862 4182",
    "sg:postcode":"E1A 1P6",
    "sg:province":"NB",
    "sg:tags":[
        "clinic"
    ],
    "wof:name":"Family Medicine Unit",
    "wof:placetype":"venue"
},
  "geometry": {"coordinates":[-64.72597500000001,46.100136],"type":"Point"}
}