{
  "type": "Feature",
  "properties": {
    "addr:full":"218 10 St Wainwright AB T9W 1P7",
    "addr:housenumber":"10",
    "addr:postcode":"t9w 1p7",
    "addr:street":"218;St",
    "iso:country":"CA",
    "sg:address":"218 10 St",
    "sg:city":"Wainwright",
    "sg:classifiers":[
        {
            "category":"Shopping",
            "subcategory":"Department Store",
            "type":"Retail Goods"
        }
    ],
    "sg:phone":"+1 780 842 5200",
    "sg:postcode":"T9W 1P7",
    "sg:province":"AB",
    "sg:tags":[
        "shop",
        "liquidator"
    ],
    "wof:name":"Liquidation World Inc",
    "wof:placetype":"venue"
},
  "geometry": {"coordinates":[-110.86096999999999,52.833797],"type":"Point"}
}