{
  "type": "Feature",
  "properties": {
    "addr:full":"2 Sunset Cres Orillia ON L3V 7Z6",
    "addr:housenumber":"2",
    "addr:postcode":"l3v 7z6",
    "addr:street":"Sunset Cres",
    "iso:country":"CA",
    "sg:address":"2 Sunset Cres",
    "sg:city":"Orillia",
    "sg:classifiers":[
        {
            "category":"Manufacturing",
            "subcategory":"Signs",
            "type":"Manufacturing & Wholesale Goods"
        }
    ],
    "sg:phone":"+1 705 326 5646",
    "sg:postcode":"L3V 7Z6",
    "sg:province":"ON",
    "wof:name":"Creechers Design",
    "wof:placetype":"venue"
},
  "geometry": {"coordinates":[-79.41822814939999,44.606590271],"type":"Point"}
}