{
  "type": "Feature",
  "properties": {
    "addr:full":"Lemoyne QC J4R 2K5",
    "addr:postcode":"j4r 2k5",
    "iso:country":"CA",
    "sg:city":"Lemoyne",
    "sg:classifiers":[
        {
            "category":"Food & Beverages",
            "subcategory":"Groceries & Convenience Stores",
            "type":"Retail Goods"
        }
    ],
    "sg:phone":"+1 450 923 5111",
    "sg:postcode":"J4R 2K5",
    "sg:province":"QC",
    "sg:tags":[
        "grocer"
    ],
    "wof:name":"Depanneur Les Copines",
    "wof:placetype":"venue"
},
  "geometry": {"coordinates":[-73.4968414307,45.4968986511],"type":"Point"}
}