{
  "type": "Feature",
  "properties": {
    "addr:full":"2047 Rogers Rd Perth ON K7H 3P4",
    "addr:housenumber":"2047",
    "addr:postcode":"k7h 3p4",
    "addr:street":"Rogers Rd",
    "iso:country":"CA",
    "sg:address":"2047 Rogers Rd",
    "sg:city":"Perth",
    "sg:classifiers":[
        {
            "category":"Wholesale",
            "subcategory":"Hardware",
            "type":"Manufacturing & Wholesale Goods"
        }
    ],
    "sg:phone":"+1 613 267 9555",
    "sg:postcode":"K7H 3P4",
    "sg:province":"ON",
    "sg:tags":[
        "fastener"
    ],
    "wof:name":"Valley Tool & Fastener",
    "wof:placetype":"venue"
},
  "geometry": {"coordinates":[-76.24241600000001,44.886063],"type":"Point"}
}