{
  "type": "Feature",
  "properties": {
    "addr:full":"1560 Yonge St Toronto ON M4T 2S9",
    "addr:housenumber":"1560",
    "addr:postcode":"m4t 2s9",
    "addr:street":"Yonge St",
    "iso:country":"CA",
    "sg:address":"1560 Yonge St",
    "sg:city":"Toronto",
    "sg:classifiers":[
        {
            "category":"Food & Beverages",
            "subcategory":"Groceries & Convenience Stores",
            "type":"Retail Goods"
        }
    ],
    "sg:phone":"+1 416 923 1311",
    "sg:postcode":"M4T 2S9",
    "sg:province":"ON",
    "sg:tags":[
        "grocer"
    ],
    "wof:name":"Bruno's Fine Foods",
    "wof:placetype":"venue"
},
  "geometry": {"coordinates":[-79.39501199999999,43.6898],"type":"Point"}
}