{
  "type": "Feature",
  "properties": {
    "addr:full":"55 St Clair Ave W Toronto ON M4V 2Y7",
    "addr:housenumber":"55",
    "addr:postcode":"m4v 2y7",
    "addr:street":"St Clair Ave W",
    "iso:country":"CA",
    "sg:address":"55 St Clair Ave W",
    "sg:city":"Toronto",
    "sg:classifiers":[
        {
            "category":"Restaurant",
            "type":"Food & Drink"
        }
    ],
    "sg:phone":"+1 416 920 0338",
    "sg:postcode":"M4V 2Y7",
    "sg:province":"ON",
    "wof:name":"Gourmet Cafe",
    "wof:placetype":"venue"
},
  "geometry": {"coordinates":[-79.398697,43.687016],"type":"Point"}
}