{
  "type": "Feature",
  "properties": {
    "addr:full":"301 Forest Ave N Orillia ON L3V 6H9",
    "addr:housenumber":"301",
    "addr:postcode":"l3v 6h9",
    "addr:street":"Forest Ave N",
    "iso:country":"CA",
    "sg:address":"301 Forest Ave N",
    "sg:city":"Orillia",
    "sg:classifiers":[
        {
            "category":"Manufacturing",
            "subcategory":"Paper Products",
            "type":"Manufacturing & Wholesale Goods"
        }
    ],
    "sg:phone":"+1 705 329 2266",
    "sg:postcode":"L3V 6H9",
    "sg:province":"ON",
    "sg:tags":[
        "bag"
    ],
    "wof:name":"Polyethics Industries Inc",
    "wof:placetype":"venue"
},
  "geometry": {"coordinates":[-79.39724699999999,44.605892],"type":"Point"}
}