{
  "type": "Feature",
  "properties": {
    "addr:full":"1351 Rue Gay-Lussac Boucherville QC J4B 7K1",
    "addr:housenumber":"1351",
    "addr:postcode":"j4b 7k1",
    "addr:street":"Rue Gay-Lussac",
    "iso:country":"CA",
    "sg:address":"1351 Rue Gay-Lussac",
    "sg:city":"Boucherville",
    "sg:classifiers":[
        {
            "category":"Shopping",
            "subcategory":"Stationery & Office Supplies",
            "type":"Retail Goods"
        }
    ],
    "sg:phone":"+1 450 641 9696",
    "sg:postcode":"J4B 7K1",
    "sg:province":"QC",
    "sg:tags":[
        "educational",
        "material"
    ],
    "wof:name":"Chameleon Informatique",
    "wof:placetype":"venue"
},
  "geometry": {"coordinates":[-73.426864624,45.5714797974],"type":"Point"}
}