{
  "type": "Feature",
  "properties": {
    "addr:full":"20534 Fraser Hwy Langley BC V3A 4G2",
    "addr:housenumber":"20534",
    "addr:postcode":"v3a 4g2",
    "addr:street":"Fraser Hwy",
    "iso:country":"CA",
    "sg:address":"20534 Fraser Hwy",
    "sg:city":"Langley",
    "sg:classifiers":[
        {
            "category":"Food & Beverages",
            "subcategory":"Meat & Fish",
            "type":"Retail Goods"
        }
    ],
    "sg:phone":"+1 604 532 5226",
    "sg:postcode":"V3A 4G2",
    "sg:province":"BC",
    "sg:tags":[
        "seafood"
    ],
    "wof:name":"1 Fish 2 Fish",
    "wof:placetype":"venue"
},
  "geometry": {"coordinates":[-122.653709412,49.103969574],"type":"Point"}
}