{
  "type": "Feature",
  "properties": {
    "addr:full":"224 Lakeshore Rd E Mississauga ON L5H 1G6",
    "addr:housenumber":"224",
    "addr:postcode":"l5h 1g6",
    "addr:street":"Lakeshore Rd E",
    "iso:country":"CA",
    "sg:address":"224 Lakeshore Rd E",
    "sg:city":"Mississauga",
    "sg:classifiers":[
        {
            "category":"Health Services",
            "subcategory":"Doctor",
            "type":"Services"
        }
    ],
    "sg:phone":"+1 905 278 7470",
    "sg:postcode":"L5H 1G6",
    "sg:province":"ON",
    "sg:tags":[
        "dentist"
    ],
    "wof:name":"Port Credit Dental",
    "wof:placetype":"venue"
},
  "geometry": {"coordinates":[-79.57813299999999,43.558861],"type":"Point"}
}