{
  "type": "Feature",
  "properties": {
    "addr:full":"3101 Victoria Ave Brandon MB R7B 3P3",
    "addr:housenumber":"3101",
    "addr:postcode":"r7b 3p3",
    "addr:street":"Victoria Ave",
    "iso:country":"CA",
    "sg:address":"3101 Victoria Ave",
    "sg:city":"Brandon",
    "sg:classifiers":[
        {
            "category":"Social Services",
            "subcategory":"Child Care",
            "type":"Services"
        }
    ],
    "sg:phone":"+1 204 728 8407",
    "sg:postcode":"R7B 3P3",
    "sg:province":"MB",
    "sg:tags":[
        "kindergarten",
        "academic",
        "school"
    ],
    "wof:name":"Beginnings Preschool Inc",
    "wof:placetype":"venue"
},
  "geometry": {"coordinates":[-99.9802474976,49.8424377441],"type":"Point"}
}