{
  "type": "Feature",
  "properties": {
    "addr:full":"90 Royal Crest Crt # A Markham ON L3R 9X6",
    "addr:housenumber":"90",
    "addr:postcode":"l3r 9x6",
    "addr:street":"Royal Crest Crt # A",
    "iso:country":"CA",
    "sg:address":"90 Royal Crest Crt # A",
    "sg:city":"Markham",
    "sg:classifiers":[
        {
            "category":"Shopping",
            "subcategory":"Stationery & Office Supplies",
            "type":"Retail Goods"
        }
    ],
    "sg:phone":"+1 905 477 8480",
    "sg:postcode":"L3R 9X6",
    "sg:province":"ON",
    "sg:tags":[
        "map"
    ],
    "wof:name":"Rand Mc Nally Canada Inc",
    "wof:placetype":"venue"
},
  "geometry": {"coordinates":[-79.3266906738,43.8411636353],"type":"Point"}
}