{
  "type": "Feature",
  "properties": {
    "addr:full":"Vercheres QC J0L 2R0",
    "addr:postcode":"j0l 2r0",
    "iso:country":"CA",
    "sg:city":"Vercheres",
    "sg:classifiers":[
        {
            "category":"Autos & Motor Vehicles",
            "subcategory":"Fuel & Gas Station",
            "type":"Retail Goods"
        }
    ],
    "sg:phone":"+1 450 583 6345",
    "sg:postcode":"J0L 2R0",
    "sg:province":"QC",
    "sg:tags":[
        "oil"
    ],
    "wof:name":"Station DE Svc H Roy Ltee",
    "wof:placetype":"venue"
},
  "geometry": {"coordinates":[-73.3674087524,45.769569397],"type":"Point"}
}