{
  "type": "Feature",
  "properties": {
    "addr:full":"115 City Rd Saint John NB E2L 3M6",
    "addr:housenumber":"115",
    "addr:postcode":"nb e2l 3m6",
    "addr:street":"City Rd",
    "iso:country":"CA",
    "sg:address":"115 City Rd",
    "sg:city":"Saint John",
    "sg:classifiers":[
        {
            "category":"Manufacturing",
            "subcategory":"Food",
            "type":"Manufacturing & Wholesale Goods"
        }
    ],
    "sg:phone":"+1 506 658 0722",
    "sg:postcode":"E2L 3M6",
    "sg:province":"NB",
    "sg:tags":[
        "baker",
        "cookie",
        "bakery"
    ],
    "wof:name":"City Road Bakery",
    "wof:placetype":"venue"
},
  "geometry": {"coordinates":[-66.058739,45.28059],"type":"Point"}
}