{
  "type": "Feature",
  "properties": {
    "addr:full":"Spruce Grove AB T7X 3V4",
    "addr:postcode":"t7x 3v4",
    "iso:country":"CA",
    "sg:city":"Spruce Grove",
    "sg:classifiers":[
        {
            "category":"Personal",
            "type":"Services"
        }
    ],
    "sg:phone":"+1 780 963 0022",
    "sg:postcode":"T7X 3V4",
    "sg:province":"AB",
    "sg:tags":[
        "salon",
        "therapist",
        "beauty",
        "massage"
    ],
    "wof:name":"Country Escapes Inc",
    "wof:placetype":"venue"
},
  "geometry": {"coordinates":[-113.901855,53.544636],"type":"Point"}
}