{
  "type": "Feature",
  "properties": {
    "addr:full":"50 Pelham Town Sq Fonthill ON L0S 1E0",
    "addr:housenumber":"50",
    "addr:postcode":"l0s 1e0",
    "addr:street":"Pelham Town Sq",
    "iso:country":"CA",
    "sg:address":"50 Pelham Town Sq",
    "sg:city":"Fonthill",
    "sg:classifiers":[
        {
            "category":"Organizations",
            "subcategory":"Religious Organization",
            "type":"Services"
        }
    ],
    "sg:phone":"+1 905 892 3090",
    "sg:postcode":"L0S 1E0",
    "sg:province":"ON",
    "sg:tags":[
        "church"
    ],
    "wof:name":"St Alexander's Church",
    "wof:placetype":"venue"
},
  "geometry": {"coordinates":[-79.282028,43.044231],"type":"Point"}
}