{
  "type": "Feature",
  "properties": {
    "addr:full":"Oakville ON L6H 3P1",
    "addr:postcode":"l6h 3p1",
    "iso:country":"CA",
    "sg:city":"Oakville",
    "sg:classifiers":[
        {
            "category":"Health Services",
            "subcategory":"Doctor",
            "type":"Services"
        }
    ],
    "sg:phone":"+1 905 844 3281",
    "sg:postcode":"L6H 3P1",
    "sg:province":"ON",
    "sg:tags":[
        "physician",
        "surgeon"
    ],
    "wof:name":"Inkster, J R MD",
    "wof:placetype":"venue"
},
  "geometry": {"coordinates":[-79.6905212402,43.4670753479],"type":"Point"}
}