{
  "type": "Feature",
  "properties": {
    "addr:full":"3836 Eton St Burnaby BC V5C 1J4",
    "addr:housenumber":"3836",
    "addr:postcode":"v5c 1j4",
    "addr:street":"Eton St",
    "iso:country":"CA",
    "sg:address":"3836 Eton St",
    "sg:city":"Burnaby",
    "sg:classifiers":[
        {
            "category":"Building & Trades",
            "subcategory":"Construction",
            "type":"Services"
        }
    ],
    "sg:phone":"+1 604 291 8063",
    "sg:postcode":"V5C 1J4",
    "sg:province":"BC",
    "sg:tags":[
        "painter"
    ],
    "wof:name":"Ed's Painting & Decorating Ltd",
    "wof:placetype":"venue"
},
  "geometry": {"coordinates":[-123.019714355,49.2872543335],"type":"Point"}
}