{
  "type": "Feature",
  "properties": {
    "iso:country":"CA",
    "sg:address":"152 Holland St E",
    "sg:city":"Bradford",
    "sg:classifiers":[
        {
            "category":"Health Services",
            "subcategory":"Chiropractor",
            "type":"Services"
        }
    ],
    "sg:phone":"+1 905 775 1022",
    "sg:postcode":"L3Z 2A9",
    "sg:province":"ON",
    "wof:name":"Bradford Chiropractic Walk in",
    "wof:placetype":"venue"
},
  "geometry": {"coordinates":[-79.5592575073,44.1154174805],"type":"Point"}
}