{
  "type": "Feature",
  "properties": {
    "addr:full":"19 Center St Bath NB E7J 1C9",
    "addr:housenumber":"19",
    "addr:postcode":"e7j 1c9",
    "addr:street":"Center St",
    "iso:country":"CA",
    "sg:address":"19 Center St",
    "sg:city":"Bath",
    "sg:classifiers":[
        {
            "category":"Wholesale",
            "subcategory":"Fruits & Vegetables",
            "type":"Manufacturing & Wholesale Goods"
        }
    ],
    "sg:phone":"+1 506 278 5266",
    "sg:postcode":"E7J 1C9",
    "sg:province":"NB",
    "sg:tags":[
        "potato"
    ],
    "wof:name":"T J Brennan & Sons Ltd",
    "wof:placetype":"venue"
},
  "geometry": {"coordinates":[-67.5965957642,46.5108604431],"type":"Point"}
}