{
  "type": "Feature",
  "properties": {
    "addr:full":"237 Jasper Dr Logan Lake BC V0K 1W0",
    "addr:housenumber":"237",
    "addr:postcode":"v0k 1w0",
    "addr:street":"Jasper Dr",
    "iso:country":"CA",
    "sg:address":"237 Jasper Dr",
    "sg:city":"Logan Lake",
    "sg:classifiers":[
        {
            "category":"Organizations",
            "subcategory":"Religious Organization",
            "type":"Services"
        }
    ],
    "sg:phone":"+1 250 523 6918",
    "sg:postcode":"V0K 1W0",
    "sg:province":"BC",
    "sg:tags":[
        "church"
    ],
    "wof:name":"Logan Lake Pentecostal Assmbly",
    "wof:placetype":"venue"
},
  "geometry": {"coordinates":[-120.80393981900001,50.4880256653],"type":"Point"}
}