{
  "type": "Feature",
  "properties": {
    "addr:full":"2400 Sixth Line Oakville ON L6H 3N8",
    "addr:housenumber":"2400",
    "addr:postcode":"l6h 3n8",
    "addr:street":"Sixth Line",
    "iso:country":"CA",
    "sg:address":"2400 Sixth Line",
    "sg:city":"Oakville",
    "sg:classifiers":[
        {
            "category":"Retail",
            "subcategory":"Repair Shop",
            "type":"Services"
        }
    ],
    "sg:phone":"+1 905 257 2155",
    "sg:postcode":"L6H 3N8",
    "sg:province":"ON",
    "sg:tags":[
        "sharpening"
    ],
    "wof:name":"Fisher Skates Sharpening",
    "wof:placetype":"venue"
},
  "geometry": {"coordinates":[-79.7232971191,43.4714317322],"type":"Point"}
}