{
  "type": "Feature",
  "properties": {
    "addr:full":"32 Rue Du Bel-Air Levis QC G6V 6K8",
    "addr:housenumber":"32",
    "addr:postcode":"g6v 6k8",
    "addr:street":"Rue Du Bel-Air",
    "iso:country":"CA",
    "sg:address":"32 Rue Du Bel-Air",
    "sg:city":"Levis",
    "sg:classifiers":[
        {
            "category":"Building & Trades",
            "subcategory":"Electrical",
            "type":"Services"
        }
    ],
    "sg:phone":"+1 418 837 2900",
    "sg:postcode":"G6V 6K8",
    "sg:province":"QC",
    "sg:tags":[
        "electric",
        "contractor"
    ],
    "wof:name":"Ernest Boutin Inc",
    "wof:placetype":"venue"
},
  "geometry": {"coordinates":[-71.18445587159999,46.7932777405],"type":"Point"}
}