{
  "type": "Feature",
  "properties": {
    "addr:full":"Henryville QC J0J 1E0",
    "addr:postcode":"j0j 1e0",
    "iso:country":"CA",
    "sg:city":"Henryville",
    "sg:classifiers":[
        {
            "category":"Sports & Exercise",
            "subcategory":"Bowling",
            "type":"Entertainment"
        }
    ],
    "sg:phone":"+1 450 299 2767",
    "sg:postcode":"J0J 1E0",
    "sg:province":"QC",
    "sg:tags":[
        "center"
    ],
    "wof:name":"Salle DE Quilles L'Allee",
    "wof:placetype":"venue"
},
  "geometry": {"coordinates":[-73.1842498779,45.1390609741],"type":"Point"}
}