{
  "type": "Feature",
  "properties": {
    "addr:full":"2275 Willingdon Ave Burnaby BC V5C 5J5",
    "addr:housenumber":"2275",
    "addr:postcode":"v5c 5j5",
    "addr:street":"Willingdon Ave",
    "iso:country":"CA",
    "sg:address":"2275 Willingdon Ave",
    "sg:city":"Burnaby",
    "sg:classifiers":[
        {
            "category":"Retail",
            "subcategory":"Auto Repair",
            "type":"Services"
        }
    ],
    "sg:phone":"+1 604 291 6678",
    "sg:postcode":"V5C 5J5",
    "sg:province":"BC",
    "sg:tags":[
        "repairing",
        "automobile"
    ],
    "wof:name":"Minit-Tune & Brake Auto Ctr",
    "wof:placetype":"venue"
},
  "geometry": {"coordinates":[-123.003448486,49.2638893127],"type":"Point"}
}