{
  "type": "Feature",
  "properties": {
    "addr:full":"Vancouver BC V6M 1Z1",
    "addr:postcode":"v6m 1z1",
    "iso:country":"CA",
    "sg:city":"Vancouver",
    "sg:classifiers":[
        {
            "category":"Education",
            "subcategory":"Special Training",
            "type":"Public Place"
        }
    ],
    "sg:phone":"+1 604 263 1655",
    "sg:postcode":"V6M 1Z1",
    "sg:province":"BC",
    "sg:tags":[
        "instruction",
        "driving"
    ],
    "wof:name":"Young Drivers of Canada",
    "wof:placetype":"venue"
},
  "geometry": {"coordinates":[-123.157051,49.234455],"type":"Point"}
}