{
  "type": "Feature",
  "properties": {
    "iso:country":"CA",
    "sg:city":"Calgary",
    "sg:classifiers":[
        {
            "category":"Retail",
            "subcategory":"Laundry & Dry Cleaning",
            "type":"Services"
        }
    ],
    "sg:phone":"+1 403 288 8796",
    "sg:postcode":"T3A 0Z9",
    "sg:province":"AB",
    "sg:tags":[
        "cleaners"
    ],
    "wof:name":"Martinizing-Varsity Acres",
    "wof:placetype":"venue"
},
  "geometry": {"coordinates":[-114.152702331,51.0928382874],"type":"Point"}
}