{
  "type": "Feature",
  "properties": {
    "addr:full":"7747 Rue George Lasalle QC H8P 1C6",
    "addr:housenumber":"7747",
    "addr:postcode":"h8p 1c6",
    "addr:street":"Rue George",
    "iso:country":"CA",
    "sg:address":"7747 Rue George",
    "sg:city":"Lasalle",
    "sg:classifiers":[
        {
            "category":"Building & Trades",
            "subcategory":"Construction",
            "type":"Services"
        }
    ],
    "sg:phone":"+1 514 367 4466",
    "sg:postcode":"H8P 1C6",
    "sg:province":"QC",
    "sg:tags":[
        "painter"
    ],
    "wof:name":"Reno Paint Gd",
    "wof:placetype":"venue"
},
  "geometry": {"coordinates":[-73.6054840088,45.4296035767],"type":"Point"}
}