{
  "type": "Feature",
  "properties": {
    "addr:full":"887 Wembley Rd Parksville BC V9P 2E6",
    "addr:housenumber":"887",
    "addr:postcode":"v9p 2e6",
    "addr:street":"Wembley Rd",
    "iso:country":"CA",
    "sg:address":"887 Wembley Rd",
    "sg:city":"Parksville",
    "sg:classifiers":[
        {
            "category":"Organizations",
            "subcategory":"Religious Organization",
            "type":"Services"
        }
    ],
    "sg:phone":"+1 250 248 3747",
    "sg:postcode":"V9P 2E6",
    "sg:province":"BC",
    "sg:tags":[
        "church"
    ],
    "wof:name":"Catholic Church-the Ascension",
    "wof:placetype":"venue"
},
  "geometry": {"coordinates":[-124.34433,49.329109],"type":"Point"}
}