{
  "type": "Feature",
  "properties": {
    "iso:country":"CA",
    "sg:city":"Cambridge",
    "sg:classifiers":[
        {
            "category":"Home & Garden",
            "subcategory":"Building Materials",
            "type":"Retail Goods"
        }
    ],
    "sg:phone":"+1 519 624 2422",
    "sg:postcode":"N1R 6R3",
    "sg:province":"ON",
    "sg:tags":[
        "glass",
        "window",
        "plate"
    ],
    "wof:name":"Cambridge Auto Glass & Trim",
    "wof:placetype":"venue"
},
  "geometry": {"coordinates":[-80.3210220337,43.3907546997],"type":"Point"}
}