{
  "type": "Feature",
  "properties": {
    "addr:full":"777 Moray St Winnipeg MB R3J 3W8",
    "addr:housenumber":"777",
    "addr:postcode":"r3j 3w8",
    "addr:street":"Moray St",
    "iso:country":"CA",
    "sg:address":"777 Moray St",
    "sg:city":"Winnipeg",
    "sg:classifiers":[
        {
            "category":"Airport",
            "type":"Transportation"
        }
    ],
    "sg:phone":"+1 204 983 8568",
    "sg:postcode":"R3J 3W8",
    "sg:province":"MB",
    "sg:tags":[
        "support",
        "establishment",
        "airline"
    ],
    "wof:name":"Nav Canada",
    "wof:placetype":"venue"
},
  "geometry": {"coordinates":[-97.260513,49.900867],"type":"Point"}
}