{
  "type": "Feature",
  "properties": {
    "addr:full":"859 Jane St York ON M6N 4C4",
    "addr:housenumber":"859",
    "addr:postcode":"m6n 4c4",
    "addr:street":"Jane St",
    "iso:country":"CA",
    "sg:address":"859 Jane St",
    "sg:city":"York",
    "sg:classifiers":[
        {
            "category":"Food & Beverages",
            "subcategory":"Dairy",
            "type":"Retail Goods"
        }
    ],
    "sg:phone":"+1 416 769 1931",
    "sg:postcode":"M6N 4C4",
    "sg:province":"ON",
    "sg:tags":[
        "delicatessen"
    ],
    "wof:name":"International Delicatessen",
    "wof:placetype":"venue"
},
  "geometry": {"coordinates":[-79.49565887449999,43.6766281128],"type":"Point"}
}