{
  "type": "Feature",
  "properties": {
    "iso:country":"CA",
    "sg:address":"7181 Woodbine Ave",
    "sg:city":"Markham",
    "sg:classifiers":[
        {
            "category":"Shopping",
            "type":"Retail Goods"
        }
    ],
    "sg:phone":"+1 905 415 9888",
    "sg:postcode":"L3R 1A3",
    "sg:province":"ON",
    "sg:tags":[
        "orthopedic",
        "appliance"
    ],
    "wof:name":"Ortho Pro Active Consultants",
    "wof:placetype":"venue"
},
  "geometry": {"coordinates":[-79.349617,43.818329],"type":"Point"}
}