{
  "type": "Feature",
  "properties": {
    "addr:full":"23 Earnscliffe Ave Wolfville NS B4P 1X4",
    "addr:housenumber":"23",
    "addr:postcode":"b4p 1x4",
    "addr:street":"Earnscliffe Ave",
    "iso:country":"CA",
    "sg:address":"23 Earnscliffe Ave",
    "sg:city":"Wolfville",
    "sg:classifiers":[
        {
            "category":"Health Services",
            "subcategory":"Doctor",
            "type":"Services"
        }
    ],
    "sg:phone":"+1 902 542 2266",
    "sg:postcode":"B4P 1X4",
    "sg:province":"NS",
    "sg:tags":[
        "clinic",
        "hospital"
    ],
    "wof:name":"Eastern Kings Memorial Cmnty",
    "wof:placetype":"venue"
},
  "geometry": {"coordinates":[-64.371529,45.088753],"type":"Point"}
}