{
  "type": "Feature",
  "properties": {
    "addr:full":"1 27th St Virginiatown ON P0K 1X0",
    "addr:housenumber":"1",
    "addr:postcode":"p0k 1x0",
    "addr:street":"27Th St",
    "iso:country":"CA",
    "sg:address":"1 27th St",
    "sg:city":"Virginiatown",
    "sg:classifiers":[
        {
            "category":"Education",
            "subcategory":"Library",
            "type":"Public Place"
        }
    ],
    "sg:phone":"+1 705 634 2312",
    "sg:postcode":"P0K 1X0",
    "sg:province":"ON",
    "wof:name":"Mc Garry Public Library",
    "wof:placetype":"venue"
},
  "geometry": {"coordinates":[-79.58136,48.141846],"type":"Point"}
}