{
  "type": "Feature",
  "properties": {
    "addr:full":"91 John St N Arnprior ON K7S 2N4",
    "addr:housenumber":"91",
    "addr:postcode":"k7s 2n4",
    "addr:street":"John St N",
    "iso:country":"CA",
    "sg:address":"91 John St N",
    "sg:city":"Arnprior",
    "sg:classifiers":[
        {
            "category":"Banks & Credit Unions",
            "subcategory":"Bank",
            "type":"Services"
        }
    ],
    "sg:phone":"+1 613 623 6526",
    "sg:postcode":"K7S 2N4",
    "sg:province":"ON",
    "wof:name":"Royal Bank Financial Group",
    "wof:placetype":"venue"
},
  "geometry": {"coordinates":[-76.35463,45.433083],"type":"Point"}
}