{
  "type": "Feature",
  "properties": {
    "iso:country":"CA",
    "sg:address":"744 Centre St # B",
    "sg:city":"Burns Lake",
    "sg:classifiers":[
        {
            "category":"Social Services",
            "type":"Services"
        }
    ],
    "sg:phone":"+1 250 692 7577",
    "sg:postcode":"V0J 1E0",
    "sg:province":"BC",
    "sg:tags":[
        "counselor"
    ],
    "wof:name":"Lakes District Counselling",
    "wof:placetype":"venue"
},
  "geometry": {"coordinates":[-125.759895325,54.2355690002],"type":"Point"}
}