{
  "type": "Feature",
  "properties": {
    "iso:country":"CA",
    "sg:city":"Burlington",
    "sg:classifiers":[
        {
            "category":"Shopping",
            "subcategory":"Books",
            "type":"Retail Goods"
        }
    ],
    "sg:phone":"+1 905 637 8734",
    "sg:postcode":"L7L 4J1",
    "sg:province":"ON",
    "sg:tags":[
        "dealer"
    ],
    "wof:name":"Ulverscroft Large Print Books",
    "wof:placetype":"venue"
},
  "geometry": {"coordinates":[-79.751266,43.376305],"type":"Point"}
}