{
  "type": "Feature",
  "properties": {
    "addr:full":"Saint-Jerome QC J7Y 1S4",
    "addr:postcode":"j7y 1s4",
    "iso:country":"CA",
    "sg:city":"Saint-Jerome",
    "sg:classifiers":[
        {
            "category":"Building & Trades",
            "subcategory":"Construction",
            "type":"Services"
        }
    ],
    "sg:phone":"+1 450 436 1888",
    "sg:postcode":"J7Y 1S4",
    "sg:province":"QC",
    "sg:tags":[
        "home",
        "builder",
        "general",
        "contractor"
    ],
    "wof:name":"Laurent Charron & Fils Inc",
    "wof:placetype":"venue"
},
  "geometry": {"coordinates":[-74.010239,45.797421],"type":"Point"}
}