{
  "type": "Feature",
  "properties": {
    "addr:full":"1902 Rue Charles-Aubert Lachenaie QC J6W 5Y7",
    "addr:housenumber":"1902",
    "addr:postcode":"j6w 5y7",
    "addr:street":"Rue Charles-Aubert",
    "iso:country":"CA",
    "sg:address":"1902 Rue Charles-Aubert",
    "sg:city":"Lachenaie",
    "sg:classifiers":[
        {
            "category":"Retail",
            "subcategory":"Auto Repair",
            "type":"Services"
        }
    ],
    "sg:phone":"+1 450 471 3646",
    "sg:postcode":"J6W 5Y7",
    "sg:province":"QC",
    "sg:tags":[
        "repairing",
        "automobile"
    ],
    "wof:name":"Garage Jr Messier Inc",
    "wof:placetype":"venue"
},
  "geometry": {"coordinates":[-73.603012085,45.6961479187],"type":"Point"}
}