{
  "type": "Feature",
  "properties": {
    "addr:full":"390 Queen St Fredericton NB E3B 1B2",
    "addr:housenumber":"390",
    "addr:postcode":"e3b 1b2",
    "addr:street":"Queen St",
    "iso:country":"CA",
    "sg:address":"390 Queen St",
    "sg:city":"Fredericton",
    "sg:classifiers":[
        {
            "category":"Shopping",
            "subcategory":"Used Merchandise",
            "type":"Retail Goods"
        }
    ],
    "sg:phone":"+1 506 458 5509",
    "sg:postcode":"E3B 1B2",
    "sg:province":"NB",
    "sg:tags":[
        "book",
        "rare",
        "dealer"
    ],
    "wof:name":"Owl's Nest Book Store",
    "wof:placetype":"venue"
},
  "geometry": {"coordinates":[-66.6436004639,45.9630737305],"type":"Point"}
}