{
  "type": "Feature",
  "properties": {
    "iso:country":"CA",
    "sg:address":"3 Irving Ave",
    "sg:city":"Ottawa",
    "sg:classifiers":[
        {
            "category":"Manufacturing",
            "subcategory":"Printing",
            "type":"Manufacturing & Wholesale Goods"
        }
    ],
    "sg:phone":"+1 613 725 2600",
    "sg:postcode":"K1Y 1Z2",
    "sg:province":"ON",
    "sg:tags":[
        "printer"
    ],
    "wof:name":"Tina & CO",
    "wof:placetype":"venue"
},
  "geometry": {"coordinates":[-75.72271,45.405285],"type":"Point"}
}