{
  "type": "Feature",
  "properties": {
    "addr:full":"3 Irving Ave Ottawa ON K1Y 1Z2",
    "addr:housenumber":"3",
    "addr:postcode":"k1y 1z2",
    "addr:street":"Irving Ave",
    "iso:country":"CA",
    "sg:address":"3 Irving Ave",
    "sg:city":"Ottawa",
    "sg:classifiers":[
        {
            "category":"Manufacturing",
            "subcategory":"Printing",
            "type":"Manufacturing & Wholesale Goods"
        }
    ],
    "sg:phone":"+1 613 725 2600",
    "sg:postcode":"K1Y 1Z2",
    "sg:province":"ON",
    "sg:tags":[
        "printer"
    ],
    "wof:name":"Tina & CO",
    "wof:placetype":"venue"
},
  "geometry": {"coordinates":[-75.72271000000001,45.405285],"type":"Point"}
}