{
  "type": "Feature",
  "properties": {
    "addr:full":"58 Main St N Exeter ON N0M 1S3",
    "addr:housenumber":"58",
    "addr:postcode":"n0m 1s3",
    "addr:street":"Main St N",
    "iso:country":"CA",
    "sg:address":"58 Main St N",
    "sg:city":"Exeter",
    "sg:classifiers":[
        {
            "category":"Bars & Pubs",
            "type":"Food & Drink"
        }
    ],
    "sg:phone":"+1 519 235 2773",
    "sg:postcode":"N0M 1S3",
    "sg:province":"ON",
    "wof:name":"Gar's Bar & Grill",
    "wof:placetype":"venue"
},
  "geometry": {"coordinates":[-81.4825286865,43.3577842712],"type":"Point"}
}