{
  "type": "Feature",
  "properties": {
    "addr:full":"90 Whitewood Ave New Liskeard ON P0J 1P0",
    "addr:housenumber":"90",
    "addr:postcode":"p0j 1p0",
    "addr:street":"Whitewood Ave",
    "iso:country":"CA",
    "sg:address":"90 Whitewood Ave",
    "sg:city":"New Liskeard",
    "sg:classifiers":[
        {
            "category":"Government",
            "subcategory":"Fire Station",
            "type":"Public Place"
        }
    ],
    "sg:phone":"+1 ",
    "sg:postcode":"P0J 1P0",
    "sg:province":"ON",
    "sg:tags":[
        "department"
    ],
    "wof:name":"New Liskeard Municipal Ofc",
    "wof:placetype":"venue"
},
  "geometry": {"coordinates":[-79.6696472168,47.5084991455],"type":"Point"}
}