{
  "type": "Feature",
  "properties": {
    "addr:full":"123 John St New Glasgow NS B2H 2N1",
    "addr:housenumber":"123",
    "addr:postcode":"b2h 2n1",
    "addr:street":"John St",
    "iso:country":"CA",
    "sg:address":"123 John St",
    "sg:city":"New Glasgow",
    "sg:classifiers":[
        {
            "category":"Home & Garden",
            "subcategory":"Building Materials",
            "type":"Retail Goods"
        }
    ],
    "sg:phone":"+1 902 752 0861",
    "sg:postcode":"B2H 2N1",
    "sg:province":"NS",
    "sg:tags":[
        "mixed",
        "concrete"
    ],
    "wof:name":"Keltic Concrete Ltd",
    "wof:placetype":"venue"
},
  "geometry": {"coordinates":[-62.643784,45.593464],"type":"Point"}
}