{
  "type": "Feature",
  "properties": {
    "addr:full":"Surrey BC V3S 4C5",
    "addr:postcode":"v3s 4c5",
    "iso:country":"CA",
    "sg:city":"Surrey",
    "sg:classifiers":[
        {
            "category":"Organizations",
            "subcategory":"Labor Organization",
            "type":"Services"
        }
    ],
    "sg:phone":"+1 604 574 5785",
    "sg:postcode":"V3S 4C5",
    "sg:province":"BC",
    "wof:name":"Surrey Firefighters",
    "wof:placetype":"venue"
},
  "geometry": {"coordinates":[-122.734909,49.10397],"type":"Point"}
}