{
  "type": "Feature",
  "properties": {
    "addr:full":"5015 51st Ave Sangudo AB T0E 2A0",
    "addr:housenumber":"5015",
    "addr:postcode":"t0e 2a0",
    "addr:street":"51St Ave",
    "iso:country":"CA",
    "sg:address":"5015 51st Ave",
    "sg:city":"Sangudo",
    "sg:classifiers":[
        {
            "category":"Retail",
            "subcategory":"Auto Repair",
            "type":"Services"
        }
    ],
    "sg:phone":"+1 780 785 2251",
    "sg:postcode":"T0E 2A0",
    "sg:province":"AB",
    "sg:tags":[
        "repairing",
        "automobile",
        "wrecker"
    ],
    "wof:name":"Ray's Auto Repair",
    "wof:placetype":"venue"
},
  "geometry": {"coordinates":[-114.902283,53.888741],"type":"Point"}
}