{
  "type": "Feature",
  "properties": {
    "addr:full":"423 Rue Des Chutes Saint-Nicolas QC G7A 1E7",
    "addr:housenumber":"423",
    "addr:postcode":"g7a 1e7",
    "addr:street":"Rue Des Chutes",
    "iso:country":"CA",
    "sg:address":"423 Rue Des Chutes",
    "sg:city":"Saint-Nicolas",
    "sg:classifiers":[
        {
            "category":"Retail",
            "subcategory":"Veterinary Services",
            "type":"Services"
        }
    ],
    "sg:phone":"+1 418 831 1144",
    "sg:postcode":"G7A 1E7",
    "sg:province":"QC",
    "sg:tags":[
        "veterinarian"
    ],
    "wof:name":"Clinique Veterinaire",
    "wof:placetype":"venue"
},
  "geometry": {"coordinates":[-71.2908172607,46.7131538391],"type":"Point"}
}