{
  "type": "Feature",
  "properties": {
    "addr:full":"10441 82 Ave NW Edmonton AB T6E 2A1",
    "addr:housenumber":"10441",
    "addr:postcode":"t6e 2a1",
    "addr:street":"82 Ave Nw",
    "iso:country":"CA",
    "sg:address":"10441 82 Ave NW",
    "sg:city":"Edmonton",
    "sg:classifiers":[
        {
            "category":"Shopping",
            "subcategory":"Clothing, Apparel, & Fashions",
            "type":"Retail Goods"
        }
    ],
    "sg:phone":"+1 780 439 2977",
    "sg:postcode":"T6E 2A1",
    "sg:province":"AB",
    "wof:name":"Divine Body Piercing & Tattoos",
    "wof:placetype":"venue"
},
  "geometry": {"coordinates":[-113.498848,53.517796],"type":"Point"}
}