{
  "type": "Feature",
  "properties": {
    "addr:full":"508 Douglas St Victoria BC V8V 2P7",
    "addr:housenumber":"508",
    "addr:postcode":"v8v 2p7",
    "addr:street":"Douglas St",
    "iso:country":"CA",
    "sg:address":"508 Douglas St",
    "sg:city":"Victoria",
    "sg:classifiers":[
        {
            "category":"Education",
            "subcategory":"School",
            "type":"Public Place"
        }
    ],
    "sg:phone":"+1 250 382 5234",
    "sg:postcode":"V8V 2P7",
    "sg:province":"BC",
    "wof:name":"South Park Elementary School",
    "wof:placetype":"venue"
},
  "geometry": {"coordinates":[-123.365867615,48.4175949097],"type":"Point"}
}