{
  "type": "Feature",
  "properties": {
    "addr:full":"Hwy 566 Matachewan ON P0K 1M0",
    "addr:postcode":"p0k 1m0",
    "addr:street":"Hwy 566",
    "iso:country":"CA",
    "sg:address":"Hwy 566",
    "sg:city":"Matachewan",
    "sg:classifiers":[
        {
            "category":"Mining & Drilling",
            "type":"Manufacturing & Wholesale Goods"
        }
    ],
    "sg:phone":"+1 705 565 2323",
    "sg:postcode":"P0K 1M0",
    "sg:province":"ON",
    "sg:tags":[
        "company"
    ],
    "wof:name":"Extender Minerals Ltd",
    "wof:placetype":"venue"
},
  "geometry": {"coordinates":[-80.753761,48.005722],"type":"Point"}
}