{
  "type": "Feature",
  "properties": {
    "addr:full":"Gloucester ON K1J 9E8",
    "addr:postcode":"k1j 9e8",
    "iso:country":"CA",
    "sg:city":"Gloucester",
    "sg:classifiers":[
        {
            "category":"Wholesale",
            "subcategory":"Electrical",
            "type":"Manufacturing & Wholesale Goods"
        }
    ],
    "sg:phone":"+1 613 748 7377",
    "sg:postcode":"K1J 9E8",
    "sg:province":"ON",
    "sg:tags":[
        "hardware",
        "control",
        "security"
    ],
    "wof:name":"Brunet Goulard Inc",
    "wof:placetype":"venue"
},
  "geometry": {"coordinates":[-75.582436,45.456139],"type":"Point"}
}