{
  "type": "Feature",
  "properties": {
    "addr:full":"473 Bernard Ave Kelowna BC V1Y 6N8",
    "addr:housenumber":"473",
    "addr:postcode":"v1y 6n8",
    "addr:street":"Bernard Ave",
    "iso:country":"CA",
    "sg:address":"473 Bernard Ave",
    "sg:city":"Kelowna",
    "sg:classifiers":[
        {
            "category":"Shopping",
            "subcategory":"Clothing, Apparel, & Fashions",
            "type":"Retail Goods"
        }
    ],
    "sg:phone":"+1 250 762 2261",
    "sg:postcode":"V1Y 6N8",
    "sg:province":"BC",
    "sg:tags":[
        "furnishing"
    ],
    "wof:name":"King's Men's Wear",
    "wof:placetype":"venue"
},
  "geometry": {"coordinates":[-119.494033813,49.8861732483],"type":"Point"}
}