{
  "type": "Feature",
  "properties": {
    "addr:full":"271 Av Dunbar Mont-Royal QC H3P 2H4",
    "addr:housenumber":"271",
    "addr:postcode":"h3p 2h4",
    "addr:street":"Av Dunbar",
    "iso:country":"CA",
    "sg:address":"271 Av Dunbar",
    "sg:city":"Mont-Royal",
    "sg:classifiers":[
        {
            "category":"Retail",
            "subcategory":"Auto Repair",
            "type":"Services"
        }
    ],
    "sg:phone":"+1 514 738 3696",
    "sg:postcode":"H3P 2H4",
    "sg:province":"QC",
    "sg:tags":[
        "body",
        "automobile",
        "painting"
    ],
    "wof:name":"Windsor Auto Body Ltd",
    "wof:placetype":"venue"
},
  "geometry": {"coordinates":[-73.6276168823,45.5195388794],"type":"Point"}
}