{
  "type": "Feature",
  "properties": {
    "addr:full":"1407 Lonsdale Ave North Vancouver BC V7M 2H9",
    "addr:housenumber":"1407",
    "addr:postcode":"v7m 2h9",
    "addr:street":"Lonsdale Ave",
    "iso:country":"CA",
    "sg:address":"1407 Lonsdale Ave",
    "sg:city":"North Vancouver",
    "sg:classifiers":[
        {
            "category":"Shopping",
            "subcategory":"Florist",
            "type":"Retail Goods"
        }
    ],
    "sg:phone":"+1 604 987 0742",
    "sg:postcode":"V7M 2H9",
    "sg:province":"BC",
    "wof:name":"North Van Florist",
    "wof:placetype":"venue"
},
  "geometry": {"coordinates":[-123.072548,49.321205],"type":"Point"}
}