{
  "type": "Feature",
  "properties": {
    "addr:full":"24 College View Ave Toronto ON M5P 1J4",
    "addr:housenumber":"24",
    "addr:postcode":"m5p 1j4",
    "addr:street":"College View Ave",
    "iso:country":"CA",
    "sg:address":"24 College View Ave",
    "sg:city":"Toronto",
    "sg:classifiers":[
        {
            "category":"Real Estate",
            "subcategory":"Real Estate Agent",
            "type":"Services"
        }
    ],
    "sg:phone":"+1 416 966 1234",
    "sg:postcode":"M5P 1J4",
    "sg:province":"ON",
    "wof:name":"St George Realty Ltd",
    "wof:placetype":"venue"
},
  "geometry": {"coordinates":[-79.406685,43.702118],"type":"Point"}
}