{
  "type": "Feature",
  "properties": {
    "addr:full":"4313 31 St Vernon BC V1T 5J8",
    "addr:housenumber":"4313",
    "addr:postcode":"v1t 5j8",
    "addr:street":"31 St",
    "iso:country":"CA",
    "sg:address":"4313 31 St",
    "sg:city":"Vernon",
    "sg:classifiers":[
        {
            "category":"Retail",
            "subcategory":"Auto Repair",
            "type":"Services"
        }
    ],
    "sg:phone":"+1 250 542 9111",
    "sg:postcode":"V1T 5J8",
    "sg:province":"BC",
    "sg:tags":[
        "repairing",
        "automobile"
    ],
    "wof:name":"Courtesy Motors",
    "wof:placetype":"venue"
},
  "geometry": {"coordinates":[-119.272499084,50.2752342224],"type":"Point"}
}