{
  "type": "Feature",
  "properties": {
    "addr:full":"114 3rd St N Uranium City SK S0J 2W0",
    "addr:housenumber":"114",
    "addr:postcode":"s0j 2w0",
    "addr:street":"3Rd St N Uranium",
    "iso:country":"CA",
    "sg:address":"114 3rd St N",
    "sg:city":"Uranium City",
    "sg:classifiers":[
        {
            "category":"Organizations",
            "subcategory":"Religious Organization",
            "type":"Services"
        }
    ],
    "sg:phone":"+1 306 498 3000",
    "sg:postcode":"S0J 2W0",
    "sg:province":"SK",
    "sg:tags":[
        "church"
    ],
    "wof:name":"Beacon Baptist Church",
    "wof:placetype":"venue"
},
  "geometry": {"coordinates":[-108.607613,59.57066],"type":"Point"}
}