{
  "type": "Feature",
  "properties": {
    "addr:full":"1170 Broad St Regina SK S4R 1X8",
    "addr:housenumber":"1170",
    "addr:postcode":"s4r 1x8",
    "addr:street":"Broad St",
    "iso:country":"CA",
    "sg:address":"1170 Broad St",
    "sg:city":"Regina",
    "sg:classifiers":[
        {
            "category":"Home & Garden",
            "subcategory":"Furniture",
            "type":"Retail Goods"
        }
    ],
    "sg:phone":"+1 306 347 3472",
    "sg:postcode":"S4R 1X8",
    "sg:province":"SK",
    "wof:name":"Urbane Furniture",
    "wof:placetype":"venue"
},
  "geometry": {"coordinates":[-104.606735,50.460373],"type":"Point"}
}