{
  "type": "Feature",
  "properties": {
    "addr:full":"Edmonton AB T5P 3Y2",
    "addr:postcode":"t5p 3y2",
    "iso:country":"CA",
    "sg:city":"Edmonton",
    "sg:classifiers":[
        {
            "category":"Shopping",
            "subcategory":"Used Merchandise",
            "type":"Retail Goods"
        }
    ],
    "sg:phone":"+1 780 489 0747",
    "sg:postcode":"T5P 3Y2",
    "sg:province":"AB",
    "sg:tags":[
        "book",
        "rare",
        "dealer"
    ],
    "wof:name":"Wee Book Inn Enterprises Ltd",
    "wof:placetype":"venue"
},
  "geometry": {"coordinates":[-113.581718,53.541153],"type":"Point"}
}