{
  "type": "Feature",
  "properties": {
    "addr:full":"Saskatoon SK S7H 0T8",
    "addr:postcode":"s7h 0t8",
    "iso:country":"CA",
    "sg:city":"Saskatoon",
    "sg:classifiers":[
        {
            "category":"Personal",
            "subcategory":"Beauty Salon",
            "type":"Services"
        }
    ],
    "sg:phone":"+1 306 374 0855",
    "sg:postcode":"S7H 0T8",
    "sg:province":"SK",
    "sg:tags":[
        "barber"
    ],
    "wof:name":"Sir's For Men",
    "wof:placetype":"venue"
},
  "geometry": {"coordinates":[-106.62412261999999,52.115032196],"type":"Point"}
}