{
  "type": "Feature",
  "properties": {
    "addr:full":"12966 Hwy 27 Nobleton ON L0G 1N0",
    "addr:housenumber":"12966",
    "addr:postcode":"l0g 1n0",
    "addr:street":"Hwy 27",
    "iso:country":"CA",
    "sg:address":"12966 Hwy 27",
    "sg:city":"Nobleton",
    "sg:classifiers":[
        {
            "category":"Retail",
            "subcategory":"Repair Shop",
            "type":"Services"
        }
    ],
    "sg:phone":"+1 905 859 0353",
    "sg:postcode":"L0G 1N0",
    "sg:province":"ON",
    "sg:tags":[
        "fabricator",
        "aluminum",
        "welding"
    ],
    "wof:name":"Nobleton Welding Svc",
    "wof:placetype":"venue"
},
  "geometry": {"coordinates":[-79.65271,43.901337],"type":"Point"}
}