{
  "type": "Feature",
  "properties": {
    "addr:full":"4802 49 St Camrose AB T4V 1M9",
    "addr:housenumber":"4802",
    "addr:postcode":"t4v 1m9",
    "addr:street":"49 St",
    "iso:country":"CA",
    "sg:address":"4802 49 St",
    "sg:city":"Camrose",
    "sg:classifiers":[
        {
            "category":"Real Estate",
            "subcategory":"Real Estate Agent",
            "type":"Services"
        }
    ],
    "sg:phone":"+1 780 672 7761",
    "sg:postcode":"T4V 1M9",
    "sg:province":"AB",
    "wof:name":"Battle River Realty Ltd",
    "wof:placetype":"venue"
},
  "geometry": {"coordinates":[-112.82450900000001,53.018345],"type":"Point"}
}