{
  "type": "Feature",
  "properties": {
    "addr:full":"17010 90 Ave NW Edmonton AB T5T 1L6",
    "addr:housenumber":"17010",
    "addr:postcode":"t5t 1l6",
    "addr:street":"90 Ave Nw",
    "iso:country":"CA",
    "sg:address":"17010 90 Ave NW",
    "sg:city":"Edmonton",
    "sg:classifiers":[
        {
            "category":"Shopping",
            "subcategory":"Hobbies, Toys, & Games",
            "type":"Retail Goods"
        }
    ],
    "sg:phone":"+1 780 944 1441",
    "sg:postcode":"T5T 1L6",
    "sg:province":"AB",
    "sg:tags":[
        "model",
        "supply"
    ],
    "wof:name":"Creative Scrap Books & Gifts",
    "wof:placetype":"venue"
},
  "geometry": {"coordinates":[-113.615821838,53.5249862671],"type":"Point"}
}