{
  "type": "Feature",
  "properties": {
    "addr:full":"30 Major Mackenzie Dr E Richmond Hill ON L4C 1G7",
    "addr:housenumber":"30",
    "addr:postcode":"l4c 1g7",
    "addr:street":"Major Mackenzie Dr E",
    "iso:country":"CA",
    "sg:address":"30 Major Mackenzie Dr E",
    "sg:city":"Richmond Hill",
    "sg:classifiers":[
        {
            "category":"Autos & Motor Vehicles",
            "subcategory":"Automobile Sales",
            "type":"Retail Goods"
        }
    ],
    "sg:phone":"+1 905 737 3352",
    "sg:postcode":"L4C 1G7",
    "sg:province":"ON",
    "sg:tags":[
        "car",
        "dealer"
    ],
    "wof:name":"P J's Auto Sales & Auto Svc",
    "wof:placetype":"venue"
},
  "geometry": {"coordinates":[-79.43626399999999,43.871601],"type":"Point"}
}