{
  "type": "Feature",
  "properties": {
    "addr:full":"811 Queen St Kincardine ON N2Z 2Y2",
    "addr:housenumber":"811",
    "addr:postcode":"n2z 2y2",
    "addr:street":"Queen St",
    "iso:country":"CA",
    "sg:address":"811 Queen St",
    "sg:city":"Kincardine",
    "sg:classifiers":[
        {
            "category":"Shopping",
            "subcategory":"Computers & Home Electronics",
            "type":"Retail Goods"
        }
    ],
    "sg:phone":"+1 519 396 3274",
    "sg:postcode":"N2Z 2Y2",
    "sg:province":"ON",
    "sg:tags":[
        "equipment",
        "dealer"
    ],
    "wof:name":"Mtc Computer Systems",
    "wof:placetype":"venue"
},
  "geometry": {"coordinates":[-81.63482666020001,44.1772727966],"type":"Point"}
}