{
  "type": "Feature",
  "properties": {
    "addr:full":"21 Coughlen St Ajax ON L1T 2M9",
    "addr:housenumber":"21",
    "addr:postcode":"l1t 2m9",
    "addr:street":"Coughlen St",
    "iso:country":"CA",
    "sg:address":"21 Coughlen St",
    "sg:city":"Ajax",
    "sg:classifiers":[
        {
            "category":"Education",
            "subcategory":"School",
            "type":"Public Place"
        }
    ],
    "sg:phone":"+1 905 427 4658",
    "sg:postcode":"L1T 2M9",
    "sg:province":"ON",
    "wof:name":"Lester B Pearson Public School",
    "wof:placetype":"venue"
},
  "geometry": {"coordinates":[-79.04317500000001,43.871826],"type":"Point"}
}