{
  "type": "Feature",
  "properties": {
    "addr:full":"Montreal QC H3H 2P2",
    "addr:postcode":"h3h 2p2",
    "iso:country":"CA",
    "sg:city":"Montreal",
    "sg:classifiers":[
        {
            "category":"Food & Beverages",
            "subcategory":"Groceries & Convenience Stores",
            "type":"Retail Goods"
        }
    ],
    "sg:phone":"+1 514 932 8896",
    "sg:postcode":"H3H 2P2",
    "sg:province":"QC",
    "wof:name":"Depanneur Atwater",
    "wof:placetype":"venue"
},
  "geometry": {"coordinates":[-73.585983,45.490345],"type":"Point"}
}