{
  "type": "Feature",
  "properties": {
    "addr:full":"Surrey BC V3W 0A6",
    "addr:postcode":"v3w 0a6",
    "iso:country":"CA",
    "sg:city":"Surrey",
    "sg:classifiers":[
        {
            "category":"Home & Garden",
            "subcategory":"Furniture",
            "type":"Retail Goods"
        }
    ],
    "sg:phone":"+1 604 590 5057",
    "sg:postcode":"V3W 0A6",
    "sg:province":"BC",
    "sg:tags":[
        "equipment",
        "kitchen",
        "cabinet"
    ],
    "wof:name":"Dream Cabinets",
    "wof:placetype":"venue"
},
  "geometry": {"coordinates":[-122.865295,49.15451],"type":"Point"}
}