{
  "type": "Feature",
  "properties": {
    "iso:country":"CA",
    "sg:address":"13311 Delwood Rd NW",
    "sg:city":"Edmonton",
    "sg:classifiers":[
        {
            "category":"Building & Trades",
            "subcategory":"Cleaning & Sanitation",
            "type":"Services"
        }
    ],
    "sg:phone":"+1 780 433 7019",
    "sg:postcode":"T5C 3B5",
    "sg:province":"AB",
    "sg:tags":[
        "ceiling"
    ],
    "wof:name":"Clean Ceilings Edmonton",
    "wof:placetype":"venue"
},
  "geometry": {"coordinates":[-113.463539123,53.5941886902],"type":"Point"}
}