{
  "type": "Feature",
  "properties": {
    "addr:full":"6257 34 St NW Edmonton AB T6B 2V6",
    "addr:housenumber":"6257",
    "addr:postcode":"t6b 2v6",
    "addr:street":"34 St Nw",
    "iso:country":"CA",
    "sg:address":"6257 34 St NW",
    "sg:city":"Edmonton",
    "sg:classifiers":[
        {
            "category":"Wholesale",
            "subcategory":"Scrap",
            "type":"Manufacturing & Wholesale Goods"
        }
    ],
    "sg:phone":"+1 780 440 2597",
    "sg:postcode":"T6B 2V6",
    "sg:province":"AB",
    "sg:tags":[
        "automobile",
        "crushing",
        "truck",
        "parts",
        "equipment"
    ],
    "wof:name":"Heart's Auto Wreckers & Svc",
    "wof:placetype":"venue"
},
  "geometry": {"coordinates":[-113.393585,53.499886],"type":"Point"}
}