{
  "type": "Feature",
  "properties": {
    "addr:full":"85 Rue Therrien Sherbrooke QC J1H 5Y8",
    "addr:housenumber":"85",
    "addr:postcode":"j1h 5y8",
    "addr:street":"Rue Therrien",
    "iso:country":"CA",
    "sg:address":"85 Rue Therrien",
    "sg:city":"Sherbrooke",
    "sg:classifiers":[
        {
            "category":"Bars & Pubs",
            "type":"Food & Drink"
        }
    ],
    "sg:phone":"+1 819 566 4161",
    "sg:postcode":"J1H 5Y8",
    "sg:province":"QC",
    "sg:tags":[
        "club",
        "lounge",
        "cocktail",
        "night"
    ],
    "wof:name":"Studio Sex",
    "wof:placetype":"venue"
},
  "geometry": {"coordinates":[-71.8892211914,45.3999328613],"type":"Point"}
}