{
  "type": "Feature",
  "properties": {
    "addr:full":"3607 Broadway W Vancouver BC V6R 2B8",
    "addr:housenumber":"3607",
    "addr:postcode":"v6r 2b8",
    "addr:street":"Broadway W",
    "iso:country":"CA",
    "sg:address":"3607 Broadway W",
    "sg:city":"Vancouver",
    "sg:classifiers":[
        {
            "category":"Shopping",
            "subcategory":"Musical Instruments",
            "type":"Retail Goods"
        }
    ],
    "sg:phone":"+1 604 736 3036",
    "sg:postcode":"V6R 2B8",
    "sg:province":"BC",
    "wof:name":"Prussin Music Inc",
    "wof:placetype":"venue"
},
  "geometry": {"coordinates":[-123.183959961,49.2644195557],"type":"Point"}
}