{
  "type": "Feature",
  "properties": {
    "addr:full":"North Battleford SK S9A 3K2",
    "addr:postcode":"s9a 3k2",
    "iso:country":"CA",
    "sg:city":"North Battleford",
    "sg:classifiers":[
        {
            "category":"Food & Beverages",
            "subcategory":"Groceries & Convenience Stores",
            "type":"Retail Goods"
        }
    ],
    "sg:phone":"+1 306 445 8211",
    "sg:postcode":"S9A 3K2",
    "sg:province":"SK",
    "wof:name":"Vista Gas Bar & C Store",
    "wof:placetype":"venue"
},
  "geometry": {"coordinates":[-108.287475586,52.7602500916],"type":"Point"}
}