{
  "type": "Feature",
  "properties": {
    "addr:full":"10430 169 St NW Edmonton AB T5P 3X6",
    "addr:housenumber":"10430",
    "addr:postcode":"t5p 3x6",
    "addr:street":"169 St Nw",
    "iso:country":"CA",
    "sg:address":"10430 169 St NW",
    "sg:city":"Edmonton",
    "sg:classifiers":[
        {
            "category":"Shopping",
            "subcategory":"Bicycles & Sporting Goods",
            "type":"Retail Goods"
        }
    ],
    "sg:phone":"+1 780 444 8887",
    "sg:postcode":"T5P 3X6",
    "sg:province":"AB",
    "sg:tags":[
        "exercise"
    ],
    "wof:name":"Fitness Depot",
    "wof:placetype":"venue"
},
  "geometry": {"coordinates":[-113.613304,53.549637],"type":"Point"}
}