{
  "type": "Feature",
  "properties": {
    "addr:full":"5904 Cowrie St Sechelt BC V0N 3A0",
    "addr:housenumber":"5904",
    "addr:postcode":"v0n 3a0",
    "addr:street":"Cowrie St",
    "iso:country":"CA",
    "sg:address":"5904 Cowrie St",
    "sg:city":"Sechelt",
    "sg:classifiers":[
        {
            "category":"Education",
            "subcategory":"School",
            "type":"Public Place"
        }
    ],
    "sg:phone":"+1 604 885 3216",
    "sg:postcode":"V0N 3A0",
    "sg:province":"BC",
    "wof:name":"Chatelech Secondary School",
    "wof:placetype":"venue"
},
  "geometry": {"coordinates":[-123.768433,49.472473],"type":"Point"}
}