{
  "type": "Feature",
  "properties": {
    "addr:full":"2518 Eglinton Ave E Scarborough ON M1K 2R5",
    "addr:housenumber":"2518",
    "addr:postcode":"m1k 2r5",
    "addr:street":"Eglinton Ave E",
    "iso:country":"CA",
    "sg:address":"2518 Eglinton Ave E",
    "sg:city":"Scarborough",
    "sg:classifiers":[
        {
            "category":"Personal",
            "subcategory":"Beauty Salon",
            "type":"Services"
        }
    ],
    "sg:phone":"+1 416 267 0507",
    "sg:postcode":"M1K 2R5",
    "sg:province":"ON",
    "wof:name":"Way A Head Stylist",
    "wof:placetype":"venue"
},
  "geometry": {"coordinates":[-79.256615,43.735035],"type":"Point"}
}