{
  "type": "Feature",
  "properties": {
    "iso:country":"CA",
    "sg:address":"918 Queen St E",
    "sg:city":"Toronto",
    "sg:classifiers":[
        {
            "category":"Health Services",
            "subcategory":"Doctor",
            "type":"Services"
        }
    ],
    "sg:phone":"+1 416 469 5261",
    "sg:postcode":"M4M 1J5",
    "sg:province":"ON",
    "sg:tags":[
        "clinic",
        "dentist"
    ],
    "wof:name":"Queen Street Dental Ctr",
    "wof:placetype":"venue"
},
  "geometry": {"coordinates":[-79.3420639038,43.6607551575],"type":"Point"}
}