{
  "type": "Feature",
  "properties": {
    "iso:country":"CA",
    "sg:address":"1401 Walkers Line",
    "sg:city":"Burlington",
    "sg:classifiers":[
        {
            "category":"Recreation",
            "type":"Entertainment"
        }
    ],
    "sg:phone":"+1 905 331 3170",
    "sg:postcode":"L7M 4N9",
    "sg:province":"ON",
    "sg:tags":[
        "center"
    ],
    "wof:name":"Wedgewood Community",
    "wof:placetype":"venue"
},
  "geometry": {"coordinates":[-79.819786,43.393822],"type":"Point"}
}