{
  "type": "Feature",
  "properties": {
    "iso:country":"CA",
    "sg:address":"11293 Tecumseh Rd E #2",
    "sg:city":"Windsor",
    "sg:classifiers":[
        {
            "category":"Travel",
            "subcategory":"Travel Agent",
            "type":"Entertainment"
        }
    ],
    "sg:phone":"+1 519 739 3600",
    "sg:postcode":"N8R 1B1",
    "sg:province":"ON",
    "sg:tags":[
        "agency",
        "bureau"
    ],
    "wof:name":"Travel Designers",
    "wof:placetype":"venue"
},
  "geometry": {"coordinates":[-82.9040298462,42.3127861023],"type":"Point"}
}