{
  "type": "Feature",
  "properties": {
    "addr:full":"1100 Boul Maloney O Gatineau QC J8T 6G3",
    "addr:housenumber":"1100",
    "addr:postcode":"j8t 6g3",
    "addr:street":"Boul Maloney O",
    "iso:country":"CA",
    "sg:address":"1100 Boul Maloney O",
    "sg:city":"Gatineau",
    "sg:classifiers":[
        {
            "category":"Manufacturing",
            "subcategory":"Food",
            "type":"Manufacturing & Wholesale Goods"
        }
    ],
    "sg:phone":"+1 819 561 0597",
    "sg:postcode":"J8T 6G3",
    "sg:province":"QC",
    "sg:tags":[
        "basket",
        "parcel",
        "gift",
        "chocolate"
    ],
    "wof:name":"Laura Secord",
    "wof:placetype":"venue"
},
  "geometry": {"coordinates":[-75.5879745483,45.492099762],"type":"Point"}
}