{
  "type": "Feature",
  "properties": {
    "addr:full":"331 Richmond St New Westminster BC V3L 4B7",
    "addr:housenumber":"331",
    "addr:postcode":"v3l 4b7",
    "addr:street":"Richmond St",
    "iso:country":"CA",
    "sg:address":"331 Richmond St",
    "sg:city":"New Westminster",
    "sg:classifiers":[
        {
            "category":"Education",
            "subcategory":"School",
            "type":"Public Place"
        }
    ],
    "sg:phone":"+1 604 517 6090",
    "sg:postcode":"V3L 4B7",
    "sg:province":"BC",
    "wof:name":"Richard Mc Bride Elementary",
    "wof:placetype":"venue"
},
  "geometry": {"coordinates":[-122.898666382,49.2263717651],"type":"Point"}
}