{
  "type": "Feature",
  "properties": {
    "addr:full":"2100 South Sheridan Way Mississauga ON L5J 2M4",
    "addr:housenumber":"2100",
    "addr:postcode":"l5j 2m4",
    "addr:street":"South Sheridan Way",
    "iso:country":"CA",
    "sg:address":"2100 South Sheridan Way",
    "sg:city":"Mississauga",
    "sg:classifiers":[
        {
            "category":"Shopping",
            "subcategory":"Clothing, Apparel, & Fashions",
            "type":"Retail Goods"
        }
    ],
    "sg:phone":"+1 905 822 4331",
    "sg:postcode":"L5J 2M4",
    "sg:province":"ON",
    "sg:tags":[
        "uniform"
    ],
    "wof:name":"Mississauga Uniforms",
    "wof:placetype":"venue"
},
  "geometry": {"coordinates":[-79.648476,43.522106],"type":"Point"}
}