{
  "type": "Feature",
  "properties": {
    "addr:full":"393 Kerr St Oakville ON L6K 3B9",
    "addr:housenumber":"393",
    "addr:postcode":"l6k 3b9",
    "addr:street":"Kerr St",
    "iso:country":"CA",
    "sg:address":"393 Kerr St",
    "sg:city":"Oakville",
    "sg:classifiers":[
        {
            "category":"Shopping",
            "subcategory":"Clothing, Apparel, & Fashions",
            "type":"Retail Goods"
        }
    ],
    "sg:phone":"+1 905 844 7735",
    "sg:postcode":"L6K 3B9",
    "sg:province":"ON",
    "wof:name":"Joia Boutique",
    "wof:placetype":"venue"
},
  "geometry": {"coordinates":[-79.6834640503,43.4448623657],"type":"Point"}
}