{
  "type": "Feature",
  "properties": {
    "iso:country":"CA",
    "sg:address":"111 Cavers St N",
    "sg:city":"Deloraine",
    "sg:classifiers":[
        {
            "category":"Recreation",
            "type":"Entertainment"
        }
    ],
    "sg:phone":"+1 204 747 2412",
    "sg:postcode":"R0M 0M0",
    "sg:province":"MB",
    "sg:tags":[
        "hall",
        "auditorium"
    ],
    "wof:name":"Elks Lodge",
    "wof:placetype":"venue"
},
  "geometry": {"coordinates":[-100.496070862,49.1933364868],"type":"Point"}
}