{
  "type": "Feature",
  "properties": {
    "iso:country":"CA",
    "sg:address":"10241 Bottom Wood Lake Rd",
    "sg:city":"Winfield",
    "sg:classifiers":[
        {
            "category":"Education",
            "subcategory":"School",
            "type":"Public Place"
        }
    ],
    "sg:phone":"+1 250 766 2734",
    "sg:postcode":"V4V 1Y7",
    "sg:province":"BC",
    "wof:name":"George Elliot Secondary",
    "wof:placetype":"venue"
},
  "geometry": {"coordinates":[-119.40222168,50.032371521],"type":"Point"}
}