{
  "type": "Feature",
  "properties": {
    "addr:full":"Sioux Lookout ON P8T 1A5",
    "addr:postcode":"p8t 1a5",
    "iso:country":"CA",
    "sg:city":"Sioux Lookout",
    "sg:classifiers":[
        {
            "category":"Shopping",
            "subcategory":"Department Store",
            "type":"Retail Goods"
        }
    ],
    "sg:phone":"+1 807 737 2640",
    "sg:postcode":"P8T 1A5",
    "sg:province":"ON",
    "wof:name":"Northern Stores",
    "wof:placetype":"venue"
},
  "geometry": {"coordinates":[-91.91670999999999,50.098969],"type":"Point"}
}