{
  "type": "Feature",
  "properties": {
    "addr:full":"71 Water St Digby NS B0V 1A0",
    "addr:housenumber":"71",
    "addr:postcode":"b0v 1a0",
    "addr:street":"Water St",
    "iso:country":"CA",
    "sg:address":"71 Water St",
    "sg:city":"Digby",
    "sg:classifiers":[
        {
            "category":"Restaurant",
            "type":"Food & Drink"
        }
    ],
    "sg:phone":"+1 902 245 4645",
    "sg:postcode":"B0V 1A0",
    "sg:province":"NS",
    "wof:name":"Subway Sandwiches & Salads",
    "wof:placetype":"venue"
},
  "geometry": {"coordinates":[-65.756889,44.624722],"type":"Point"}
}