{
  "type": "Feature",
  "properties": {
    "addr:full":"North York ON M3J 3A4",
    "addr:postcode":"m3j 3a4",
    "iso:country":"CA",
    "sg:city":"North York",
    "sg:classifiers":[
        {
            "category":"Retail",
            "subcategory":"Auto Repair",
            "type":"Services"
        }
    ],
    "sg:phone":"+1 416 665 1781",
    "sg:postcode":"M3J 3A4",
    "sg:province":"ON",
    "sg:tags":[
        "repairing",
        "automobile"
    ],
    "wof:name":"Tony's Service Ctr",
    "wof:placetype":"venue"
},
  "geometry": {"coordinates":[-79.493782,43.775646],"type":"Point"}
}