{
  "type": "Feature",
  "properties": {
    "addr:full":"Ottawa ON K2P 0J2",
    "addr:postcode":"k2p 0j2",
    "iso:country":"CA",
    "sg:city":"Ottawa",
    "sg:classifiers":[
        {
            "category":"Professional",
            "subcategory":"Research",
            "type":"Services"
        }
    ],
    "sg:phone":"+1 613 233 5528",
    "sg:postcode":"K2P 0J2",
    "sg:province":"ON",
    "sg:tags":[
        "development",
        "laboratory"
    ],
    "wof:name":"Canadian Fitness & Lifestyle",
    "wof:placetype":"venue"
},
  "geometry": {"coordinates":[-75.690933,45.417789],"type":"Point"}
}