{
  "type": "Feature",
  "properties": {
    "addr:full":"Burlington ON L7R 4E2",
    "addr:postcode":"l7r 4e2",
    "iso:country":"CA",
    "sg:city":"Burlington",
    "sg:classifiers":[
        {
            "category":"Wholesale",
            "subcategory":"Jewelry",
            "type":"Manufacturing & Wholesale Goods"
        }
    ],
    "sg:phone":"+1 905 637 6377",
    "sg:postcode":"L7R 4E2",
    "sg:province":"ON",
    "sg:tags":[
        "jeweler"
    ],
    "wof:name":"Williams Distinctive Gems",
    "wof:placetype":"venue"
},
  "geometry": {"coordinates":[-79.794495,43.344933],"type":"Point"}
}