{
  "type": "Feature",
  "properties": {
    "addr:full":"45 Rue DE Rotterdam Saint-Augustin-DE-Desmaures QC G3A 1S8",
    "addr:housenumber":"45",
    "addr:postcode":"g3a 1s8",
    "addr:street":"Rue De Rotterdam",
    "iso:country":"CA",
    "sg:address":"45 Rue DE Rotterdam",
    "sg:city":"Saint-Augustin-DE-Desmaures",
    "sg:classifiers":[
        {
            "category":"Wholesale",
            "subcategory":"Metals & Minerals",
            "type":"Manufacturing & Wholesale Goods"
        }
    ],
    "sg:phone":"+1 418 878 2000",
    "sg:postcode":"G3A 1S8",
    "sg:province":"QC",
    "sg:tags":[
        "aluminum"
    ],
    "wof:name":"Acrofab Inc",
    "wof:placetype":"venue"
},
  "geometry": {"coordinates":[-71.43821699999999,46.751534],"type":"Point"}
}