{
  "type": "Feature",
  "properties": {
    "addr:full":"661 Rue Saint-Cyrille Normandin QC G8M 4H3",
    "addr:housenumber":"661",
    "addr:postcode":"g8m 4h3",
    "addr:street":"Rue Saint-Cyrille",
    "iso:country":"CA",
    "sg:address":"661 Rue Saint-Cyrille",
    "sg:city":"Normandin",
    "sg:classifiers":[
        {
            "category":"Utilities",
            "subcategory":"Refuse",
            "type":"Services"
        }
    ],
    "sg:phone":"+1 418 679 1767",
    "sg:postcode":"G8M 4H3",
    "sg:province":"QC",
    "sg:tags":[
        "waste",
        "liquid",
        "removal"
    ],
    "wof:name":"Sani-Terre Inc",
    "wof:placetype":"venue"
},
  "geometry": {"coordinates":[-72.5104217529,48.8206214905],"type":"Point"}
}