{
  "type": "Feature",
  "properties": {
    "addr:full":"31 Front St Pictou NS B0K 1H0",
    "addr:housenumber":"31",
    "addr:postcode":"b0k 1h0",
    "addr:street":"Front St",
    "iso:country":"CA",
    "sg:address":"31 Front St",
    "sg:city":"Pictou",
    "sg:classifiers":[
        {
            "category":"Retail",
            "subcategory":"Auto Repair",
            "type":"Services"
        }
    ],
    "sg:phone":"+1 902 485 1122",
    "sg:postcode":"B0K 1H0",
    "sg:province":"NS",
    "sg:tags":[
        "repairing",
        "automobile"
    ],
    "wof:name":"Heighton Auto Care",
    "wof:placetype":"venue"
},
  "geometry": {"coordinates":[-62.708424,45.675934],"type":"Point"}
}