{
  "type": "Feature",
  "properties": {
    "addr:full":"4704 49th St Fort Nelson BC V0C 1R0",
    "addr:housenumber":"4704",
    "addr:postcode":"bc v0c 1r0",
    "addr:street":"49Th St",
    "iso:country":"CA",
    "sg:address":"4704 49th St",
    "sg:city":"Fort Nelson",
    "sg:classifiers":[
        {
            "category":"Professional",
            "subcategory":"Accounting & Tax Preparation",
            "type":"Services"
        }
    ],
    "sg:phone":"+1 250 774 7500",
    "sg:postcode":"V0C 1R0",
    "sg:province":"BC",
    "sg:tags":[
        "bookkeeping",
        "general"
    ],
    "wof:name":"Deales Enterprises",
    "wof:placetype":"venue"
},
  "geometry": {"coordinates":[-122.699226,58.802055],"type":"Point"}
}