{
  "type": "Feature",
  "properties": {
    "addr:full":"567 Empire Rd Sherkston ON L0S 1R0",
    "addr:housenumber":"567",
    "addr:postcode":"l0s 1r0",
    "addr:street":"Empire Rd",
    "iso:country":"CA",
    "sg:address":"567 Empire Rd",
    "sg:city":"Sherkston",
    "sg:classifiers":[
        {
            "category":"Home & Garden",
            "subcategory":"Garden Supply",
            "type":"Retail Goods"
        }
    ],
    "sg:phone":"+1 905 894 1662",
    "sg:postcode":"L0S 1R0",
    "sg:province":"ON",
    "sg:tags":[
        "landscaping",
        "equipment"
    ],
    "wof:name":"Shisler Brothers",
    "wof:placetype":"venue"
},
  "geometry": {"coordinates":[-79.1342926025,42.8758811951],"type":"Point"}
}