{
  "type": "Feature",
  "properties": {
    "iso:country":"CA",
    "sg:address":"9 Place Park",
    "sg:city":"Westmount",
    "sg:classifiers":[
        {
            "category":"Education",
            "subcategory":"School",
            "type":"Public Place"
        }
    ],
    "sg:phone":"+1 514 933 7488",
    "sg:postcode":"H3Z 2K4",
    "sg:province":"QC",
    "wof:name":"Outreach Ecole",
    "wof:placetype":"venue"
},
  "geometry": {"coordinates":[-73.59466552729999,45.48021698],"type":"Point"}
}