{
  "type": "Feature",
  "properties": {
    "addr:full":"Dartmouth NS B2Y 2N6",
    "addr:postcode":"b2y 2n6",
    "iso:country":"CA",
    "sg:city":"Dartmouth",
    "sg:classifiers":[
        {
            "category":"Real Estate",
            "subcategory":"Real Estate Agent",
            "type":"Services"
        }
    ],
    "sg:phone":"+1 902 422 1591",
    "sg:postcode":"B2Y 2N6",
    "sg:province":"NS",
    "sg:tags":[
        "management"
    ],
    "wof:name":"Rjc Real Estate Mgmt Ltd",
    "wof:placetype":"venue"
},
  "geometry": {"coordinates":[-63.5696601868,44.6653747559],"type":"Point"}
}