{
  "type": "Feature",
  "properties": {
    "addr:full":"9884 82 Ave NW Edmonton AB T6E 1Y8",
    "addr:housenumber":"9884",
    "addr:postcode":"t6e 1y8",
    "addr:street":"82 Ave Nw",
    "iso:country":"CA",
    "sg:address":"9884 82 Ave NW",
    "sg:city":"Edmonton",
    "sg:classifiers":[
        {
            "category":"Retail",
            "subcategory":"Car Wash",
            "type":"Services"
        }
    ],
    "sg:phone":"+1 780 433 5329",
    "sg:postcode":"T6E 1Y8",
    "sg:province":"AB",
    "sg:tags":[
        "polishing",
        "washing"
    ],
    "wof:name":"Whyte Avenue Esso",
    "wof:placetype":"venue"
},
  "geometry": {"coordinates":[-113.485389709,53.5183372498],"type":"Point"}
}