{
  "type": "Feature",
  "properties": {
    "addr:full":"297 Lesmill Rd North York ON M3B 2V1",
    "addr:housenumber":"297",
    "addr:postcode":"m3b 2v1",
    "addr:street":"Lesmill Rd",
    "iso:country":"CA",
    "sg:address":"297 Lesmill Rd",
    "sg:city":"North York",
    "sg:classifiers":[
        {
            "category":"Professional",
            "subcategory":"Business Services",
            "type":"Services"
        }
    ],
    "sg:phone":"+1 416 444 6778",
    "sg:postcode":"M3B 2V1",
    "sg:province":"ON",
    "sg:tags":[
        "recording",
        "studio"
    ],
    "wof:name":"Lacquer Channel",
    "wof:placetype":"venue"
},
  "geometry": {"coordinates":[-79.35998499999999,43.762703],"type":"Point"}
}