{
  "type": "Feature",
  "properties": {
    "addr:full":"Main Rd Fort Liard NT X0G 0A0",
    "addr:postcode":"x0g 0a0",
    "addr:street":"Main Rd",
    "iso:country":"CA",
    "sg:address":"Main Rd",
    "sg:city":"Fort Liard",
    "sg:classifiers":[
        {
            "category":"Shopping",
            "subcategory":"Discount & Variety Stores",
            "type":"Retail Goods"
        }
    ],
    "sg:phone":"+1 867 770 4411",
    "sg:postcode":"X0G 0A0",
    "sg:province":"NT",
    "sg:tags":[
        "merchandise",
        "general"
    ],
    "wof:name":"Northern Store",
    "wof:placetype":"venue"
},
  "geometry": {"coordinates":[-123.46453099999999,60.24374],"type":"Point"}
}