{
  "type": "Feature",
  "properties": {
    "addr:full":"2136 Gottingen St Halifax NS B3K 3B3",
    "addr:housenumber":"2136",
    "addr:postcode":"b3k 3b3",
    "addr:street":"Gottingen St",
    "iso:country":"CA",
    "sg:address":"2136 Gottingen St",
    "sg:city":"Halifax",
    "sg:classifiers":[
        {
            "category":"Organizations",
            "subcategory":"Professional Association",
            "type":"Services"
        }
    ],
    "sg:phone":"+1 902 424 7036",
    "sg:postcode":"B3K 3B3",
    "sg:province":"NS",
    "sg:tags":[
        "government"
    ],
    "wof:name":"Black Educators Assn NS",
    "wof:placetype":"venue"
},
  "geometry": {"coordinates":[-63.5837478638,44.6520767212],"type":"Point"}
}