{
  "type": "Feature",
  "properties": {
    "addr:full":"Spencerville ON K0E 1X0",
    "addr:postcode":"k0e 1x0",
    "iso:country":"CA",
    "sg:city":"Spencerville",
    "sg:classifiers":[
        {
            "category":"Home & Garden",
            "subcategory":"Hardware",
            "type":"Retail Goods"
        }
    ],
    "sg:phone":"+1 613 658 2004",
    "sg:postcode":"K0E 1X0",
    "sg:province":"ON",
    "wof:name":"Home Hardware Stores",
    "wof:placetype":"venue"
},
  "geometry": {"coordinates":[-75.552933,44.838982],"type":"Point"}
}