{
  "type": "Feature",
  "properties": {
    "addr:full":"Vernon BC V1T 5M2",
    "addr:postcode":"v1t 5m2",
    "iso:country":"CA",
    "sg:city":"Vernon",
    "sg:classifiers":[
        {
            "category":"Real Estate",
            "subcategory":"Developer",
            "type":"Services"
        }
    ],
    "sg:phone":"+1 250 549 3853",
    "sg:postcode":"V1T 5M2",
    "sg:province":"BC",
    "sg:tags":[
        "company",
        "land"
    ],
    "wof:name":"Phoenix Land Developments",
    "wof:placetype":"venue"
},
  "geometry": {"coordinates":[-119.273696899,50.263053894],"type":"Point"}
}