{
  "type": "Feature",
  "properties": {
    "iso:country":"CA",
    "sg:address":"2048 Sheppard Ave E",
    "sg:city":"North York",
    "sg:classifiers":[
        {
            "category":"Health Services",
            "subcategory":"Doctor",
            "type":"Services"
        }
    ],
    "sg:phone":"+1 416 497 6161",
    "sg:postcode":"M2J 5B3",
    "sg:province":"ON",
    "sg:tags":[
        "dentist"
    ],
    "wof:name":"Rayman, Richard DDS",
    "wof:placetype":"venue"
},
  "geometry": {"coordinates":[-79.33029174799999,43.7751274109],"type":"Point"}
}