{
  "type": "Feature",
  "properties": {
    "addr:full":"2002 76th St Coleman AB T0K 0M0",
    "addr:housenumber":"2002",
    "addr:postcode":"t0k 0m0",
    "addr:street":"76Th St",
    "iso:country":"CA",
    "sg:address":"2002 76th St",
    "sg:city":"Coleman",
    "sg:classifiers":[
        {
            "category":"Education",
            "subcategory":"School",
            "type":"Public Place"
        }
    ],
    "sg:phone":"+1 403 563 3998",
    "sg:postcode":"T0K 0M0",
    "sg:province":"AB",
    "wof:name":"Horace Allen School",
    "wof:placetype":"venue"
},
  "geometry": {"coordinates":[-114.50608800000001,49.637871],"type":"Point"}
}