{
  "type": "Feature",
  "properties": {
    "iso:country":"CA",
    "sg:address":"2002 76th St",
    "sg:city":"Coleman",
    "sg:classifiers":[
        {
            "category":"Education",
            "subcategory":"School",
            "type":"Public Place"
        }
    ],
    "sg:phone":"+1 403 563 3998",
    "sg:postcode":"T0K 0M0",
    "sg:province":"AB",
    "wof:name":"Horace Allen School",
    "wof:placetype":"venue"
},
  "geometry": {"coordinates":[-114.506088,49.637871],"type":"Point"}
}