{
  "type": "Feature",
  "properties": {
    "addr:full":"3 Exploits St Lewisporte NL A0G 3A0",
    "addr:housenumber":"3",
    "addr:postcode":"a0g 3a0",
    "addr:street":"Exploits St",
    "iso:country":"CA",
    "sg:address":"3 Exploits St",
    "sg:city":"Lewisporte",
    "sg:classifiers":[
        {
            "category":"Organizations",
            "subcategory":"Community Association",
            "type":"Services"
        }
    ],
    "sg:phone":"+1 709 535 2364",
    "sg:postcode":"A0G 3A0",
    "sg:province":"NL",
    "sg:tags":[
        "club"
    ],
    "wof:name":"Royal Canadian Legion",
    "wof:placetype":"venue"
},
  "geometry": {"coordinates":[-55.059937,49.241798],"type":"Point"}
}