{
  "type": "Feature",
  "properties": {
    "addr:full":"475 Welham Rd Barrie ON L4N 8Z6",
    "addr:housenumber":"475",
    "addr:postcode":"l4n 8z6",
    "addr:street":"Welham Rd",
    "iso:country":"CA",
    "sg:address":"475 Welham Rd",
    "sg:city":"Barrie",
    "sg:classifiers":[
        {
            "category":"Wholesale",
            "subcategory":"Machinery & Supplies",
            "type":"Manufacturing & Wholesale Goods"
        }
    ],
    "sg:phone":"+1 705 721 4200",
    "sg:postcode":"L4N 8Z6",
    "sg:province":"ON",
    "sg:tags":[
        "machine",
        "equipment",
        "tool",
        "industrial"
    ],
    "wof:name":"F K Machinery Ltd",
    "wof:placetype":"venue"
},
  "geometry": {"coordinates":[-79.66952514650001,44.3472747803],"type":"Point"}
}