{
  "type": "Feature",
  "properties": {
    "addr:full":"Gatineau QC J8T 7W3",
    "addr:postcode":"j8t 7w3",
    "iso:country":"CA",
    "sg:city":"Gatineau",
    "sg:classifiers":[
        {
            "category":"Health Services",
            "subcategory":"Health Practitioner",
            "type":"Services"
        }
    ],
    "sg:phone":"+1 819 246 3321",
    "sg:postcode":"J8T 7W3",
    "sg:province":"QC",
    "sg:tags":[
        "physiotherapist"
    ],
    "wof:name":"Clinique DE Physiotherapie",
    "wof:placetype":"venue"
},
  "geometry": {"coordinates":[-75.702904,45.488617],"type":"Point"}
}