{
  "type": "Feature",
  "properties": {
    "addr:full":"233 Rue Saint-Paul Quebec QC G1K 3W3",
    "addr:housenumber":"233",
    "addr:postcode":"g1k 3w3",
    "addr:street":"Rue Saint-Paul",
    "iso:country":"CA",
    "sg:address":"233 Rue Saint-Paul",
    "sg:city":"Quebec",
    "sg:classifiers":[
        {
            "category":"Restaurant",
            "type":"Food & Drink"
        }
    ],
    "sg:phone":"+1 418 692 5642",
    "sg:postcode":"G1K 3W3",
    "sg:province":"QC",
    "wof:name":"Restaurant Peche Veniel",
    "wof:placetype":"venue"
},
  "geometry": {"coordinates":[-71.20932000000001,46.816822],"type":"Point"}
}