{
  "type": "Feature",
  "properties": {
    "addr:full":"788 14E Av LA Guadeloupe QC G0M 1G0",
    "addr:housenumber":"788",
    "addr:postcode":"g0m 1g0",
    "addr:street":"14E Av",
    "iso:country":"CA",
    "sg:address":"788 14E Av",
    "sg:city":"LA Guadeloupe",
    "sg:classifiers":[
        {
            "category":"Autos & Motor Vehicles",
            "subcategory":"Fuel & Gas Station",
            "type":"Retail Goods"
        }
    ],
    "sg:phone":"+1 418 459 6410",
    "sg:postcode":"G0M 1G0",
    "sg:province":"QC",
    "sg:tags":[
        "oil"
    ],
    "wof:name":"Petro-Canada",
    "wof:placetype":"venue"
},
  "geometry": {"coordinates":[-70.941986,45.969105],"type":"Point"}
}