{
  "type": "Feature",
  "properties": {
    "addr:full":"69 Light St # 12 Woodstock ON N4S 6G9",
    "addr:housenumber":"69",
    "addr:postcode":"n4s 6g9",
    "addr:street":"Light St # 12",
    "iso:country":"CA",
    "sg:address":"69 Light St # 12",
    "sg:city":"Woodstock",
    "sg:classifiers":[
        {
            "category":"Insurance",
            "subcategory":"Insurance Agent",
            "type":"Services"
        }
    ],
    "sg:phone":"+1 519 539 2076",
    "sg:postcode":"N4S 6G9",
    "sg:province":"ON",
    "sg:tags":[
        "consultant",
        "planning",
        "financial"
    ],
    "wof:name":"Investment Planning Counsel",
    "wof:placetype":"venue"
},
  "geometry": {"coordinates":[-80.7610702515,43.1318473816],"type":"Point"}
}