{
  "type": "Feature",
  "properties": {
    "addr:full":"4553 Townline Rd Thunder Bay ON P7B 5E2",
    "addr:housenumber":"4553",
    "addr:postcode":"p7b 5e2",
    "addr:street":"Townline Rd",
    "iso:country":"CA",
    "sg:address":"4553 Townline Rd",
    "sg:city":"Thunder Bay",
    "sg:classifiers":[
        {
            "category":"Wholesale",
            "subcategory":"Machinery & Supplies",
            "type":"Manufacturing & Wholesale Goods"
        }
    ],
    "sg:phone":"+1 807 935 2878",
    "sg:postcode":"P7B 5E2",
    "sg:province":"ON",
    "sg:tags":[
        "equipment",
        "dairy"
    ],
    "wof:name":"Oliver Dairy Supply",
    "wof:placetype":"venue"
},
  "geometry": {"coordinates":[-88.524727,48.837799],"type":"Point"}
}