{
  "type": "Feature",
  "properties": {
    "addr:full":"920 Derwent Way Delta BC V3M 5R1",
    "addr:housenumber":"920",
    "addr:postcode":"v3m 5r1",
    "addr:street":"Derwent Way",
    "iso:country":"CA",
    "sg:address":"920 Derwent Way",
    "sg:city":"Delta",
    "sg:classifiers":[
        {
            "category":"Wholesale",
            "subcategory":"Construction Materials",
            "type":"Manufacturing & Wholesale Goods"
        }
    ],
    "sg:phone":"+1 604 524 3770",
    "sg:postcode":"V3M 5R1",
    "sg:province":"BC",
    "sg:tags":[
        "importer",
        "lumber"
    ],
    "wof:name":"Mountainview Reload Inc",
    "wof:placetype":"venue"
},
  "geometry": {"coordinates":[-122.935249329,49.1715393066],"type":"Point"}
}