{
  "type": "Feature",
  "properties": {
    "addr:full":"103 3E Av Quebec QC G1L 2V3",
    "addr:housenumber":"103",
    "addr:postcode":"g1l 2v3",
    "addr:street":"3E Av",
    "iso:country":"CA",
    "sg:address":"103 3E Av",
    "sg:city":"Quebec",
    "sg:classifiers":[
        {
            "category":"Retail",
            "subcategory":"Auto Repair",
            "type":"Services"
        }
    ],
    "sg:phone":"+1 418 529 5378",
    "sg:postcode":"G1L 2V3",
    "sg:province":"QC",
    "sg:tags":[
        "repairing",
        "automobile",
        "tire"
    ],
    "wof:name":"Pneus Ratte Inc",
    "wof:placetype":"venue"
},
  "geometry": {"coordinates":[-71.2246551514,46.8204841614],"type":"Point"}
}