{
  "type": "Feature",
  "properties": {
    "iso:country":"CA",
    "sg:address":"257 Lemarchant Rd",
    "sg:city":"St. John's",
    "sg:classifiers":[
        {
            "category":"Organizations",
            "subcategory":"Non-profit Organization",
            "type":"Services"
        }
    ],
    "sg:phone":"+1 709 579 6472",
    "sg:postcode":"A1E 1P8",
    "sg:province":"NL",
    "sg:tags":[
        "physician",
        "surgeon",
        "institution",
        "charitable"
    ],
    "wof:name":"Matercare Canada",
    "wof:placetype":"venue"
},
  "geometry": {"coordinates":[-52.723427,47.553879],"type":"Point"}
}