{
  "type": "Feature",
  "properties": {
    "addr:full":"880 Hastings St E Vancouver BC V6A 1R6",
    "addr:housenumber":"880",
    "addr:postcode":"v6a 1r6",
    "addr:street":"Hastings St E",
    "iso:country":"CA",
    "sg:address":"880 Hastings St E",
    "sg:city":"Vancouver",
    "sg:classifiers":[
        {
            "category":"Food & Beverages",
            "subcategory":"Groceries & Convenience Stores",
            "type":"Retail Goods"
        }
    ],
    "sg:phone":"+1 604 251 4674",
    "sg:postcode":"V6A 1R6",
    "sg:province":"BC",
    "sg:tags":[
        "grocer"
    ],
    "wof:name":"Tham's Market",
    "wof:placetype":"venue"
},
  "geometry": {"coordinates":[-123.085350037,49.2809448242],"type":"Point"}
}