{
  "type": "Feature",
  "properties": {
    "addr:full":"19811 Fraser Hwy Langley BC V3A 4E1",
    "addr:housenumber":"19811",
    "addr:postcode":"v3a 4e1",
    "addr:street":"Fraser Hwy",
    "iso:country":"CA",
    "sg:address":"19811 Fraser Hwy",
    "sg:city":"Langley",
    "sg:classifiers":[
        {
            "category":"Autos & Motor Vehicles",
            "subcategory":"Fuel & Gas Station",
            "type":"Retail Goods"
        }
    ],
    "sg:phone":"+1 604 530 8222",
    "sg:postcode":"V3A 4E1",
    "sg:province":"BC",
    "sg:tags":[
        "oil"
    ],
    "wof:name":"Husky Food Store",
    "wof:placetype":"venue"
},
  "geometry": {"coordinates":[-122.67467498800001,49.1116790771],"type":"Point"}
}