{
  "type": "Feature",
  "properties": {
    "addr:full":"4605 Boul DE L'Auvergne Quebec QC G2C 1H7",
    "addr:housenumber":"4605",
    "addr:postcode":"qc g2c 1h7",
    "addr:street":"Boul De L'Auvergne",
    "iso:country":"CA",
    "sg:address":"4605 Boul DE L'Auvergne",
    "sg:city":"Quebec",
    "sg:classifiers":[
        {
            "category":"Real Estate",
            "subcategory":"Real Estate Operator",
            "type":"Services"
        }
    ],
    "sg:phone":"+1 418 843 1580",
    "sg:postcode":"G2C 1H7",
    "sg:province":"QC",
    "sg:tags":[
        "mall",
        "shopping",
        "center"
    ],
    "wof:name":"Centre Commercial Neufchatel",
    "wof:placetype":"venue"
},
  "geometry": {"coordinates":[-71.348129,46.830212],"type":"Point"}
}