{
  "type": "Feature",
  "properties": {
    "addr:full":"3924 Rue Montcalm Rawdon QC J0K 1S0",
    "addr:housenumber":"3924",
    "addr:postcode":"j0k 1s0",
    "addr:street":"Rue Montcalm",
    "iso:country":"CA",
    "sg:address":"3924 Rue Montcalm",
    "sg:city":"Rawdon",
    "sg:classifiers":[
        {
            "category":"Home & Garden",
            "subcategory":"Household Appliances",
            "type":"Retail Goods"
        }
    ],
    "sg:phone":"+1 450 834 3093",
    "sg:postcode":"J0K 1S0",
    "sg:province":"QC",
    "wof:name":"Frederic Refrigeration Enr",
    "wof:placetype":"venue"
},
  "geometry": {"coordinates":[-73.729637,46.054634],"type":"Point"}
}