{
  "type": "Feature",
  "properties": {
    "addr:full":"1101 Boul Ducharme LA Tuque QC G9X 3C3",
    "addr:housenumber":"1101",
    "addr:postcode":"g9x 3c3",
    "addr:street":"Boul Ducharme",
    "iso:country":"CA",
    "sg:address":"1101 Boul Ducharme",
    "sg:city":"LA Tuque",
    "sg:classifiers":[
        {
            "category":"Shopping",
            "type":"Retail Goods"
        }
    ],
    "sg:phone":"+1 819 523 7636",
    "sg:postcode":"G9X 3C3",
    "sg:province":"QC",
    "wof:name":"John Lewis Industrie Ltee",
    "wof:placetype":"venue"
},
  "geometry": {"coordinates":[-72.78527099999999,47.422451],"type":"Point"}
}