{
  "type": "Feature",
  "properties": {
    "addr:full":"2 Vata Crt Aurora ON L4G 4B6",
    "addr:housenumber":"2",
    "addr:postcode":"l4g 4b6",
    "addr:street":"Vata Crt",
    "iso:country":"CA",
    "sg:address":"2 Vata Crt",
    "sg:city":"Aurora",
    "sg:classifiers":[
        {
            "category":"Wholesale",
            "subcategory":"Electrical",
            "type":"Manufacturing & Wholesale Goods"
        }
    ],
    "sg:phone":"+1 905 841 2490",
    "sg:postcode":"L4G 4B6",
    "sg:province":"ON",
    "sg:tags":[
        "alarm",
        "burglar",
        "system"
    ],
    "wof:name":"Maximum Monitoring Svc",
    "wof:placetype":"venue"
},
  "geometry": {"coordinates":[-79.458206,43.988255],"type":"Point"}
}