{
  "type": "Feature",
  "properties": {
    "iso:country":"CA",
    "sg:address":"100 Waterloo Rd # C",
    "sg:city":"Timmins",
    "sg:classifiers":[
        {
            "category":"Shopping",
            "subcategory":"Tobacco",
            "type":"Retail Goods"
        }
    ],
    "sg:phone":"+1 705 264 5700",
    "sg:postcode":"P4N 4X5",
    "sg:province":"ON",
    "sg:tags":[
        "cigarette",
        "cigar",
        "dealer"
    ],
    "wof:name":"Den's Smoke Shop",
    "wof:placetype":"venue"
},
  "geometry": {"coordinates":[-81.33805084230001,48.4787979126],"type":"Point"}
}