{
  "type": "Feature",
  "properties": {
    "iso:country":"CA",
    "sg:city":"Dollard-Des-Ormeaux",
    "sg:classifiers":[
        {
            "category":"Real Estate",
            "subcategory":"Real Estate Agent",
            "type":"Services"
        }
    ],
    "sg:phone":"+1 514 696 7700",
    "sg:postcode":"H9H 2A7",
    "sg:province":"QC",
    "wof:name":"Re/Max Invest",
    "wof:placetype":"venue"
},
  "geometry": {"coordinates":[-73.848541,45.487194],"type":"Point"}
}