{
  "type": "Feature",
  "properties": {
    "addr:full":"Burnaby BC V5J 3H6",
    "addr:postcode":"v5j 3h6",
    "iso:country":"CA",
    "sg:city":"Burnaby",
    "sg:classifiers":[
        {
            "category":"Wholesale",
            "subcategory":"Meat",
            "type":"Manufacturing & Wholesale Goods"
        }
    ],
    "sg:phone":"+1 604 435 7644",
    "sg:postcode":"V5J 3H6",
    "sg:province":"BC",
    "wof:name":"Kwongtat Meats",
    "wof:placetype":"venue"
},
  "geometry": {"coordinates":[-122.99642900000001,49.194138],"type":"Point"}
}