{
  "type": "Feature",
  "properties": {
    "addr:full":"454 Boul Des Laurentides Laval QC H7G 2V1",
    "addr:housenumber":"454",
    "addr:postcode":"qc h7g 2v1",
    "addr:street":"Boul Des Laurentides",
    "iso:country":"CA",
    "sg:address":"454 Boul Des Laurentides",
    "sg:city":"Laval",
    "sg:classifiers":[
        {
            "category":"Manufacturing",
            "subcategory":"Printing",
            "type":"Manufacturing & Wholesale Goods"
        }
    ],
    "sg:phone":"+1 450 668 9634",
    "sg:postcode":"H7G 2V1",
    "sg:province":"QC",
    "sg:tags":[
        "printer",
        "duplicating",
        "copying"
    ],
    "wof:name":"Copie Rapide Laval Inc",
    "wof:placetype":"venue"
},
  "geometry": {"coordinates":[-73.690865,45.56908],"type":"Point"}
}