{
  "type": "Feature",
  "properties": {
    "addr:full":"110 Water St Sarnia ON N7T 5T3",
    "addr:housenumber":"110",
    "addr:postcode":"n7t 5t3",
    "addr:street":"Water St",
    "iso:country":"CA",
    "sg:address":"110 Water St",
    "sg:city":"Sarnia",
    "sg:classifiers":[
        {
            "category":"Health Services",
            "subcategory":"Doctor",
            "type":"Services"
        }
    ],
    "sg:phone":"+1 519 344 8442",
    "sg:postcode":"N7T 5T3",
    "sg:province":"ON",
    "sg:tags":[
        "dentist"
    ],
    "wof:name":"Sproviero, Frank DDS",
    "wof:placetype":"venue"
},
  "geometry": {"coordinates":[-82.403519,42.981632],"type":"Point"}
}