{
  "type": "Feature",
  "properties": {
    "iso:country":"CA",
    "sg:address":"981 Larkin St # 2",
    "sg:city":"Ottawa",
    "sg:classifiers":[
        {
            "category":"Building & Trades",
            "subcategory":"Construction",
            "type":"Services"
        }
    ],
    "sg:phone":"+1 613 860 9986",
    "sg:postcode":"K1Z 5R5",
    "sg:province":"ON",
    "sg:tags":[
        "water",
        "well",
        "drilling"
    ],
    "wof:name":"J R Drilling CO Ltd",
    "wof:placetype":"venue"
},
  "geometry": {"coordinates":[-75.738823,45.375828],"type":"Point"}
}