{
  "type": "Feature",
  "properties": {
    "addr:full":"63 Ch DE Montreal E Masson-Angers QC J8M 1K3",
    "addr:housenumber":"63",
    "addr:postcode":"j8m 1k3",
    "addr:street":"Ch De Montreal E Masson-Angers",
    "iso:country":"CA",
    "sg:address":"63 Ch DE Montreal E",
    "sg:city":"Masson-Angers",
    "sg:classifiers":[
        {
            "category":"Banks & Credit Unions",
            "subcategory":"Bank",
            "type":"Services"
        }
    ],
    "sg:phone":"+1 819 986 3364",
    "sg:postcode":"J8M 1K3",
    "sg:province":"QC",
    "wof:name":"Caisse Populaire Desjardins",
    "wof:placetype":"venue"
},
  "geometry": {"coordinates":[-75.413696,45.544846],"type":"Point"}
}