{
  "type": "Feature",
  "properties": {
    "addr:full":"Hunter River PE C0A 1N0",
    "addr:postcode":"c0a 1n0",
    "iso:country":"CA",
    "sg:city":"Hunter River",
    "sg:classifiers":[
        {
            "category":"Home & Garden",
            "subcategory":"Garden Supply",
            "type":"Retail Goods"
        }
    ],
    "sg:phone":"+1 902 964 3051",
    "sg:postcode":"C0A 1N0",
    "sg:province":"PE",
    "sg:tags":[
        "tree",
        "christmas"
    ],
    "wof:name":"Silverbell Christmas Tree Farm",
    "wof:placetype":"venue"
},
  "geometry": {"coordinates":[-63.3431472778,46.3517608643],"type":"Point"}
}