{
  "type": "Feature",
  "properties": {
    "addr:full":"77 Campbellville Rd Campbellville ON L0P 1B0",
    "addr:housenumber":"77",
    "addr:postcode":"l0p 1b0",
    "addr:street":"Campbellville Rd",
    "iso:country":"CA",
    "sg:address":"77 Campbellville Rd",
    "sg:city":"Campbellville",
    "sg:classifiers":[
        {
            "category":"Building & Trades",
            "subcategory":"Plumbing",
            "type":"Services"
        }
    ],
    "sg:phone":"+1 905 659 2929",
    "sg:postcode":"L0P 1B0",
    "sg:province":"ON",
    "sg:tags":[
        "contractor",
        "system",
        "solar",
        "heating"
    ],
    "wof:name":"Enersol Solar Products Inc",
    "wof:placetype":"venue"
},
  "geometry": {"coordinates":[-79.9838256836,43.4856681824],"type":"Point"}
}