{
  "type": "Feature",
  "properties": {
    "addr:full":"PO Box 161 Tomahawk AB T0E 2H0",
    "addr:housenumber":"po",
    "addr:postcode":"t0e 2h0",
    "addr:street":"Box 161",
    "iso:country":"CA",
    "sg:address":"PO Box 161",
    "sg:city":"Tomahawk",
    "sg:classifiers":[
        {
            "category":"Food & Beverages",
            "subcategory":"Groceries & Convenience Stores",
            "type":"Retail Goods"
        }
    ],
    "sg:phone":"+1 780 339 3930",
    "sg:postcode":"T0E 2H0",
    "sg:province":"AB",
    "sg:tags":[
        "grocer"
    ],
    "wof:name":"Tomahawk General Store",
    "wof:placetype":"venue"
},
  "geometry": {"coordinates":[-114.76325199999999,53.396599],"type":"Point"}
}