{
  "type": "Feature",
  "properties": {
    "addr:full":"Sainte-Thecle QC G0X 3G0",
    "addr:postcode":"g0x 3g0",
    "iso:country":"CA",
    "sg:city":"Sainte-Thecle",
    "sg:classifiers":[
        {
            "category":"Taxi",
            "type":"Transportation"
        }
    ],
    "sg:phone":"+1 418 289 2055",
    "sg:postcode":"G0X 3G0",
    "sg:province":"QC",
    "sg:tags":[
        "taxicab"
    ],
    "wof:name":"Taxi Marcotte",
    "wof:placetype":"venue"
},
  "geometry": {"coordinates":[-72.48381000000001,46.84346],"type":"Point"}
}