{
  "type": "Feature",
  "properties": {
    "addr:full":"1051 Av Saint-Charles Vaudreuil-Dorion QC J7V 8P5",
    "addr:housenumber":"1051",
    "addr:postcode":"j7v 8p5",
    "addr:street":"Av Saint-Charles",
    "iso:country":"CA",
    "sg:address":"1051 Av Saint-Charles",
    "sg:city":"Vaudreuil-Dorion",
    "sg:classifiers":[
        {
            "category":"Food & Beverages",
            "subcategory":"Groceries & Convenience Stores",
            "type":"Retail Goods"
        }
    ],
    "sg:phone":"+1 450 455 9222",
    "sg:postcode":"J7V 8P5",
    "sg:province":"QC",
    "wof:name":"Depanneur Au Bord Du Lac",
    "wof:placetype":"venue"
},
  "geometry": {"coordinates":[-74.0487442017,45.4173698425],"type":"Point"}
}