{
  "type": "Feature",
  "properties": {
    "addr:full":"448 Rue Blainville E Sainte-Therese QC J7E 1N9",
    "addr:housenumber":"448",
    "addr:postcode":"j7e 1n9",
    "addr:street":"Rue Blainville E Sainte-Therese",
    "iso:country":"CA",
    "sg:address":"448 Rue Blainville E",
    "sg:city":"Sainte-Therese",
    "sg:classifiers":[
        {
            "category":"Cinema",
            "subcategory":"Movie Rental",
            "type":"Entertainment"
        }
    ],
    "sg:phone":"+1 450 430 5005",
    "sg:postcode":"J7E 1N9",
    "sg:province":"QC",
    "sg:tags":[
        "leasing",
        "video",
        "disc",
        "tape"
    ],
    "wof:name":"Video Hbo",
    "wof:placetype":"venue"
},
  "geometry": {"coordinates":[-73.815712,45.642471],"type":"Point"}
}