{
  "type": "Feature",
  "properties": {
    "addr:full":"West Vancouver BC V7V 1H9",
    "addr:postcode":"v7v 1h9",
    "iso:country":"CA",
    "sg:city":"West Vancouver",
    "sg:classifiers":[
        {
            "category":"Health Services",
            "subcategory":"Health Practitioner",
            "type":"Services"
        }
    ],
    "sg:phone":"+1 604 926 6868",
    "sg:postcode":"V7V 1H9",
    "sg:province":"BC",
    "sg:tags":[
        "physiotherapist"
    ],
    "wof:name":"Hollyburn Physiotherapy Clinic",
    "wof:placetype":"venue"
},
  "geometry": {"coordinates":[-123.157768,49.32859],"type":"Point"}
}