{
  "type": "Feature",
  "properties": {
    "addr:full":"2233 Quinn St S Prince George BC V2N 2X4",
    "addr:housenumber":"2233",
    "addr:postcode":"v2n 2x4",
    "addr:street":"Quinn St S",
    "iso:country":"CA",
    "sg:address":"2233 Quinn St S",
    "sg:city":"Prince George",
    "sg:classifiers":[
        {
            "category":"Shopping",
            "subcategory":"Pharmacy",
            "type":"Retail Goods"
        }
    ],
    "sg:phone":"+1 250 960 4300",
    "sg:postcode":"V2N 2X4",
    "sg:province":"BC",
    "sg:tags":[
        "supply",
        "fire",
        "equipment",
        "protection",
        "aid",
        "first"
    ],
    "wof:name":"Guillevin International Inc",
    "wof:placetype":"venue"
},
  "geometry": {"coordinates":[-122.791931152,53.9030036926],"type":"Point"}
}