{
  "type": "Feature",
  "properties": {
    "addr:full":"610 Rte Chasse Sainte-Marie QC G6E 1C9",
    "addr:housenumber":"610",
    "addr:postcode":"g6e 1c9",
    "addr:street":"Rte Chasse",
    "iso:country":"CA",
    "sg:address":"610 Rte Chasse",
    "sg:city":"Sainte-Marie",
    "sg:classifiers":[
        {
            "category":"Manufacturing",
            "subcategory":"Wood Products",
            "type":"Manufacturing & Wholesale Goods"
        }
    ],
    "sg:phone":"+1 418 387 5441",
    "sg:postcode":"G6E 1C9",
    "sg:province":"QC",
    "sg:tags":[
        "pallet",
        "skid"
    ],
    "wof:name":"Chasse Inc",
    "wof:placetype":"venue"
},
  "geometry": {"coordinates":[-71.02958700000001,46.457611],"type":"Point"}
}