{
  "type": "Feature",
  "properties": {
    "addr:full":"412 Thickwood Blvd Fort Mcmurray AB T9K 1P1",
    "addr:housenumber":"412",
    "addr:postcode":"t9k 1p1",
    "addr:street":"Thickwood Blvd",
    "iso:country":"CA",
    "sg:address":"412 Thickwood Blvd",
    "sg:city":"Fort Mcmurray",
    "sg:classifiers":[
        {
            "category":"Restaurant",
            "type":"Food & Drink"
        }
    ],
    "sg:phone":"+1 780 791 4040",
    "sg:postcode":"T9K 1P1",
    "sg:province":"AB",
    "wof:name":"Fish Place",
    "wof:placetype":"venue"
},
  "geometry": {"coordinates":[-111.428764,56.733093],"type":"Point"}
}