{
  "type": "Feature",
  "properties": {
    "iso:country":"CA",
    "sg:address":"5692 Victoria Dr",
    "sg:city":"Vancouver",
    "sg:classifiers":[
        {
            "category":"Food & Beverages",
            "subcategory":"Bakery",
            "type":"Retail Goods"
        }
    ],
    "sg:phone":"+1 604 325 3323",
    "sg:postcode":"V5P 3W4",
    "sg:province":"BC",
    "sg:tags":[
        "baker"
    ],
    "wof:name":"King Wah Bakery",
    "wof:placetype":"venue"
},
  "geometry": {"coordinates":[-123.06529998800001,49.2329788208],"type":"Point"}
}