{
  "type": "Feature",
  "properties": {
    "addr:full":"119 St. George St Toronto ON M5S 2E8",
    "addr:housenumber":"119",
    "addr:postcode":"m5s 2e8",
    "addr:street":"St. George St",
    "iso:country":"CA",
    "sg:address":"119 St. George St",
    "sg:city":"Toronto",
    "sg:classifiers":[
        {
            "category":"Restaurant",
            "type":"Food & Drink"
        }
    ],
    "sg:phone":"+1 416 593 7187",
    "sg:postcode":"M5S 2E8",
    "sg:province":"ON",
    "sg:tags":[
        "shop",
        "coffee"
    ],
    "wof:name":"Second Cup",
    "wof:placetype":"venue"
},
  "geometry": {"coordinates":[-79.399162,43.666363],"type":"Point"}
}