{
  "type": "Feature",
  "properties": {
    "addr:full":"1105 Boul Auger O Alma QC G8B 2C2",
    "addr:housenumber":"1105",
    "addr:postcode":"g8b 2c2",
    "addr:street":"Boul Auger O",
    "iso:country":"CA",
    "sg:address":"1105 Boul Auger O",
    "sg:city":"Alma",
    "sg:classifiers":[
        {
            "category":"Health Services",
            "subcategory":"Chiropractor",
            "type":"Services"
        }
    ],
    "sg:phone":"+1 418 668 3559",
    "sg:postcode":"G8B 2C2",
    "sg:province":"QC",
    "wof:name":"Clinique Chiropratique St-Jude",
    "wof:placetype":"venue"
},
  "geometry": {"coordinates":[-71.6153717041,48.5343208313],"type":"Point"}
}