{
  "type": "Feature",
  "properties": {
    "iso:country":"CA",
    "sg:city":"Mississauga",
    "sg:classifiers":[
        {
            "category":"Social Services",
            "type":"Services"
        }
    ],
    "sg:phone":"+1 905 567 4156",
    "sg:postcode":"L5N 4B7",
    "sg:province":"ON",
    "sg:tags":[
        "organization",
        "welfare"
    ],
    "wof:name":"Mississauga Parent Child",
    "wof:placetype":"venue"
},
  "geometry": {"coordinates":[-79.7585906982,43.5803565979],"type":"Point"}
}