{
  "type": "Feature",
  "properties": {
    "addr:full":"250 Regina Rd #1 Woodbridge L4L 8N2",
    "addr:housenumber":"250",
    "addr:postcode":"l4l 8n2",
    "addr:street":"Regina Rd # 1",
    "iso:country":"CA",
    "sg:address":"250 Regina Rd #1",
    "sg:city":"Woodbridge",
    "sg:classifiers":[
        {
            "category":"Professional",
            "subcategory":"Management & Consulting",
            "type":"Services"
        }
    ],
    "sg:postcode":"L4L 8N2",
    "sg:tags":[
        "seo",
        "sem",
        "search-engine-optimization"
    ],
    "sg:website":"http://striderseo.com",
    "wof:name":"Strider SEO",
    "wof:placetype":"venue"
},
  "geometry": {"coordinates":[-79.611182,43.768232],"type":"Point"}
}