{
  "type": "Feature",
  "properties": {
    "addr:full":"319 Main St Antigonish NS B2G 2C3",
    "addr:housenumber":"319",
    "addr:postcode":"b2g 2c3",
    "addr:street":"Main St",
    "iso:country":"CA",
    "sg:address":"319 Main St",
    "sg:city":"Antigonish",
    "sg:classifiers":[
        {
            "category":"Wholesale",
            "subcategory":"Electrical",
            "type":"Manufacturing & Wholesale Goods"
        }
    ],
    "sg:phone":"+1 902 863 1680",
    "sg:postcode":"B2G 2C3",
    "sg:province":"NS",
    "sg:tags":[
        "control",
        "security",
        "investigator"
    ],
    "wof:name":"Serco Security & Investigation",
    "wof:placetype":"venue"
},
  "geometry": {"coordinates":[-61.993176,45.622383],"type":"Point"}
}