{
  "type": "Feature",
  "properties": {
    "addr:full":"12275 County Rd 16 Coldwater ON L0K 1E0",
    "addr:housenumber":"12275;16",
    "addr:postcode":"l0k 1e0",
    "addr:street":"County Rd",
    "iso:country":"CA",
    "sg:address":"12275 County Rd 16",
    "sg:city":"Coldwater",
    "sg:classifiers":[
        {
            "category":"Wholesale",
            "subcategory":"Seafood",
            "type":"Manufacturing & Wholesale Goods"
        }
    ],
    "sg:phone":"+1 705 686 7756",
    "sg:postcode":"L0K 1E0",
    "sg:province":"ON",
    "wof:name":"Cold Water Fisheries Inc",
    "wof:placetype":"venue"
},
  "geometry": {"coordinates":[-79.644363,44.710224],"type":"Point"}
}