{
  "type": "Feature",
  "properties": {
    "addr:full":"550 Barriere Town Rd Barriere BC V0E 1E0",
    "addr:housenumber":"550",
    "addr:postcode":"bc v0e 1e0",
    "addr:street":"Barriere Town Rd",
    "iso:country":"CA",
    "sg:address":"550 Barriere Town Rd",
    "sg:city":"Barriere",
    "sg:classifiers":[
        {
            "category":"Shopping",
            "subcategory":"Department Store",
            "type":"Retail Goods"
        }
    ],
    "sg:phone":"+1 250 672 5756",
    "sg:postcode":"V0E 1E0",
    "sg:province":"BC",
    "wof:name":"Sears Canada Inc",
    "wof:placetype":"venue"
},
  "geometry": {"coordinates":[-120.12667083700001,51.1882743835],"type":"Point"}
}