{
  "type": "Feature",
  "properties": {
    "addr:full":"5663 Cornwallis St Halifax NS B3K 1B6",
    "addr:housenumber":"5663",
    "addr:postcode":"b3k 1b6",
    "addr:street":"Cornwallis St",
    "iso:country":"CA",
    "sg:address":"5663 Cornwallis St",
    "sg:city":"Halifax",
    "sg:classifiers":[
        {
            "category":"Health Services",
            "subcategory":"Health Practitioner",
            "type":"Services"
        }
    ],
    "sg:phone":"+1 902 492 1588",
    "sg:postcode":"B3K 1B6",
    "sg:province":"NS",
    "sg:tags":[
        "psychologist"
    ],
    "wof:name":"Godbout, Lise",
    "wof:placetype":"venue"
},
  "geometry": {"coordinates":[-63.5859947205,44.6511421204],"type":"Point"}
}