{
  "type": "Feature",
  "properties": {
    "iso:country":"CA",
    "sg:address":"3414 13th Ave",
    "sg:city":"Regina",
    "sg:classifiers":[
        {
            "category":"Restaurant",
            "type":"Food & Drink"
        }
    ],
    "sg:phone":"+1 306 352 4448",
    "sg:postcode":"S4T 1P7",
    "sg:province":"SK",
    "wof:name":"Creek in Cathedral Bistro",
    "wof:placetype":"venue"
},
  "geometry": {"coordinates":[-104.63002014200001,50.4457321167],"type":"Point"}
}