{
  "type": "Feature",
  "properties": {
    "iso:country":"CA",
    "sg:city":"Mississauga",
    "sg:classifiers":[
        {
            "category":"Shopping",
            "subcategory":"Jewelry",
            "type":"Retail Goods"
        }
    ],
    "sg:phone":"+1 905 405 0061",
    "sg:postcode":"L5P 1C4",
    "sg:province":"ON",
    "sg:tags":[
        "jeweler"
    ],
    "wof:name":"Pax Jewellers",
    "wof:placetype":"venue"
},
  "geometry": {"coordinates":[-79.64372253419999,43.5882835388],"type":"Point"}
}