{
  "type": "Feature",
  "properties": {
    "addr:full":"Vancouver BC V6J 4R1",
    "addr:postcode":"v6j 4r1",
    "iso:country":"CA",
    "sg:city":"Vancouver",
    "sg:classifiers":[
        {
            "category":"Real Estate",
            "subcategory":"Real Estate Agent",
            "type":"Services"
        }
    ],
    "sg:phone":"+1 604 738 4900",
    "sg:postcode":"V6J 4R1",
    "sg:province":"BC",
    "wof:name":"Select Properties",
    "wof:placetype":"venue"
},
  "geometry": {"coordinates":[-123.15348053,49.2483253479],"type":"Point"}
}