{
  "type": "Feature",
  "properties": {
    "addr:full":"10010 99th St Grande Cache AB T0E 0Y0",
    "addr:housenumber":"10010",
    "addr:postcode":"t0e 0y0",
    "addr:street":"99Th St",
    "iso:country":"CA",
    "sg:address":"10010 99th St",
    "sg:city":"Grande Cache",
    "sg:classifiers":[
        {
            "category":"Restaurant",
            "type":"Food & Drink"
        }
    ],
    "sg:phone":"+1 780 827 5522",
    "sg:postcode":"T0E 0Y0",
    "sg:province":"AB",
    "wof:name":"Big Horn Dining Lounge & Pizza",
    "wof:placetype":"venue"
},
  "geometry": {"coordinates":[-119.11264799999999,53.889469],"type":"Point"}
}