{
  "type": "Feature",
  "properties": {
    "addr:full":"Langley BC V3A 3Y5",
    "addr:postcode":"v3a 3y5",
    "iso:country":"CA",
    "sg:city":"Langley",
    "sg:classifiers":[
        {
            "category":"Restaurant",
            "type":"Food & Drink"
        }
    ],
    "sg:phone":"+1 604 514 9399",
    "sg:postcode":"V3A 3Y5",
    "sg:province":"BC",
    "wof:name":"Silver Dragon Restaurant",
    "wof:placetype":"venue"
},
  "geometry": {"coordinates":[-122.661407,49.104191],"type":"Point"}
}