{
  "type": "Feature",
  "properties": {
    "iso:country":"CA",
    "sg:address":"163 25E Av",
    "sg:city":"Saint-Eustache",
    "sg:classifiers":[
        {
            "category":"Restaurant",
            "type":"Food & Drink"
        }
    ],
    "sg:phone":"+1 450 491 7685",
    "sg:postcode":"J7P 2V1",
    "sg:province":"QC",
    "wof:name":"Subway Sandwiches & Salads",
    "wof:placetype":"venue"
},
  "geometry": {"coordinates":[-73.8889007568,45.5580482483],"type":"Point"}
}