{
  "type": "Feature",
  "properties": {
    "addr:full":"Richmond BC V6Y 3X9",
    "addr:postcode":"v6y 3x9",
    "iso:country":"CA",
    "sg:city":"Richmond",
    "sg:classifiers":[
        {
            "category":"Shopping",
            "subcategory":"Pharmacy",
            "type":"Retail Goods"
        }
    ],
    "sg:phone":"+1 604 276 0067",
    "sg:postcode":"V6Y 3X9",
    "sg:province":"BC",
    "wof:name":"Shoppers Drug Mart",
    "wof:placetype":"venue"
},
  "geometry": {"coordinates":[-123.123848,49.155323],"type":"Point"}
}