{
  "type": "Feature",
  "properties": {
    "addr:full":"8135 Wyandotte St E Windsor ON N8S 1T4",
    "addr:housenumber":"8135",
    "addr:postcode":"n8s 1t4",
    "addr:street":"Wyandotte St E",
    "iso:country":"CA",
    "sg:address":"8135 Wyandotte St E",
    "sg:city":"Windsor",
    "sg:classifiers":[
        {
            "category":"Banks & Credit Unions",
            "subcategory":"Bank",
            "type":"Services"
        }
    ],
    "sg:phone":"+1 519 944 5977",
    "sg:postcode":"N8S 1T4",
    "sg:province":"ON",
    "wof:name":"Royal Bank Financial Group",
    "wof:placetype":"venue"
},
  "geometry": {"coordinates":[-82.94096399999999,42.333279],"type":"Point"}
}