{
  "type": "Feature",
  "properties": {
    "iso:country":"CA",
    "sg:city":"Vancouver",
    "sg:classifiers":[
        {
            "category":"Organizations",
            "subcategory":"Professional Association",
            "type":"Services"
        }
    ],
    "sg:phone":"+1 604 733 9440",
    "sg:postcode":"V6J 1Y6",
    "sg:province":"BC",
    "wof:name":"B C Apartment Owners & Manager",
    "wof:placetype":"venue"
},
  "geometry": {"coordinates":[-123.14683532700001,49.2638778687],"type":"Point"}
}