{
  "type": "Feature",
  "properties": {
    "addr:full":"201 Thickwood Blvd Fort Mcmurray AB T9H 5A9",
    "addr:housenumber":"201",
    "addr:postcode":"t9h 5a9",
    "addr:street":"Thickwood Blvd",
    "iso:country":"CA",
    "sg:address":"201 Thickwood Blvd",
    "sg:city":"Fort Mcmurray",
    "sg:classifiers":[
        {
            "category":"Health Services",
            "subcategory":"Doctor",
            "type":"Services"
        }
    ],
    "sg:phone":"+1 780 790 1733",
    "sg:postcode":"T9H 5A9",
    "sg:province":"AB",
    "sg:tags":[
        "dentist"
    ],
    "wof:name":"Mc Coy, Brad DDS",
    "wof:placetype":"venue"
},
  "geometry": {"coordinates":[-111.411514282,56.7428627014],"type":"Point"}
}