{
  "type": "Feature",
  "properties": {
    "addr:full":"1429 Portugal Cove Rd Portugal Cove-St Philips NL A1M 3J8",
    "addr:housenumber":"1429",
    "addr:postcode":"a1m 3j8",
    "addr:street":"Portugal Cove Rd",
    "iso:country":"CA",
    "sg:address":"1429 Portugal Cove Rd",
    "sg:city":"Portugal Cove-St Philips",
    "sg:classifiers":[
        {
            "category":"Food & Beverages",
            "subcategory":"Groceries & Convenience Stores",
            "type":"Retail Goods"
        }
    ],
    "sg:phone":"+1 709 895 2995",
    "sg:postcode":"A1M 3J8",
    "sg:province":"NL",
    "wof:name":"Needs Convenience Store",
    "wof:placetype":"venue"
},
  "geometry": {"coordinates":[-52.849174,47.628063],"type":"Point"}
}