{
  "type": "Feature",
  "properties": {
    "addr:full":"484 Rue Martel Saint-Germain-DE-Grantham QC J0C 1K0",
    "addr:housenumber":"484",
    "addr:postcode":"j0c 1k0",
    "addr:street":"Rue Martel",
    "iso:country":"CA",
    "sg:address":"484 Rue Martel",
    "sg:city":"Saint-Germain-DE-Grantham",
    "sg:classifiers":[
        {
            "category":"Farming",
            "subcategory":"Farm & Veterinary Services",
            "type":"Manufacturing & Wholesale Goods"
        }
    ],
    "sg:phone":"+1 819 395 4752",
    "sg:postcode":"J0C 1K0",
    "sg:province":"QC",
    "sg:tags":[
        "insemination"
    ],
    "wof:name":"Marc Mc Clure Insemination",
    "wof:placetype":"venue"
},
  "geometry": {"coordinates":[-72.5912857056,45.8251533508],"type":"Point"}
}