{
  "type": "Feature",
  "properties": {
    "addr:full":"1540 Stage Rd Cache Creek BC V0K 1H0",
    "addr:housenumber":"1540",
    "addr:postcode":"v0k 1h0",
    "addr:street":"Stage Rd",
    "iso:country":"CA",
    "sg:address":"1540 Stage Rd",
    "sg:city":"Cache Creek",
    "sg:classifiers":[
        {
            "category":"Organizations",
            "subcategory":"Religious Organization",
            "type":"Services"
        }
    ],
    "sg:phone":"+1 250 457 9930",
    "sg:postcode":"V0K 1H0",
    "sg:province":"BC",
    "sg:tags":[
        "church"
    ],
    "wof:name":"Catholic Churches & Insts",
    "wof:placetype":"venue"
},
  "geometry": {"coordinates":[-121.311302,50.813286],"type":"Point"}
}