{
  "type": "Feature",
  "properties": {
    "addr:full":"PO Box 190 Innisfree AB T0B 2G0",
    "addr:housenumber":"po",
    "addr:postcode":"t0b 2g0",
    "addr:street":"Box 190",
    "iso:country":"CA",
    "sg:address":"PO Box 190",
    "sg:city":"Innisfree",
    "sg:classifiers":[
        {
            "category":"Utilities",
            "subcategory":"Natural Gas",
            "type":"Services"
        }
    ],
    "sg:phone":"+1 780 592 3911",
    "sg:postcode":"T0B 2G0",
    "sg:province":"AB",
    "sg:tags":[
        "company"
    ],
    "wof:name":"Minco Gas CO-OP Ltd",
    "wof:placetype":"venue"
},
  "geometry": {"coordinates":[-111.531265,53.380836],"type":"Point"}
}