{
  "type": "Feature",
  "properties": {
    "addr:full":"1158 Albion Rd Etobicoke ON M9V 1A8",
    "addr:housenumber":"1158",
    "addr:postcode":"m9v 1a8",
    "addr:street":"Albion Rd",
    "iso:country":"CA",
    "sg:address":"1158 Albion Rd",
    "sg:city":"Etobicoke",
    "sg:classifiers":[
        {
            "category":"Wholesale",
            "subcategory":"Groceries",
            "type":"Manufacturing & Wholesale Goods"
        }
    ],
    "sg:phone":"+1 416 740 7779",
    "sg:postcode":"M9V 1A8",
    "sg:province":"ON",
    "sg:tags":[
        "grocer"
    ],
    "wof:name":"Sultan Foods",
    "wof:placetype":"venue"
},
  "geometry": {"coordinates":[-79.568321,43.737907],"type":"Point"}
}