{
  "type": "Feature",
  "properties": {
    "addr:full":"50 Camden St Toronto ON M5V 3N1",
    "addr:housenumber":"50",
    "addr:postcode":"m5v 3n1",
    "addr:street":"Camden St",
    "iso:country":"CA",
    "sg:address":"50 Camden St",
    "sg:city":"Toronto",
    "sg:classifiers":[
        {
            "category":"Professional",
            "type":"Services"
        }
    ],
    "sg:phone":"+1 416 703 0191",
    "sg:postcode":"M5V 3N1",
    "sg:province":"ON",
    "sg:tags":[
        "establishment",
        "duplicating",
        "copying"
    ],
    "wof:name":"Checkmate Photographic Ctr Ltd",
    "wof:placetype":"venue"
},
  "geometry": {"coordinates":[-79.39720153810001,43.6472396851],"type":"Point"}
}