{
  "type": "Feature",
  "properties": {
    "addr:full":"Trois-Pistoles QC G0L 4K0",
    "addr:postcode":"g0l 4k0",
    "iso:country":"CA",
    "sg:city":"Trois-Pistoles",
    "sg:classifiers":[
        {
            "category":"Travel",
            "subcategory":"Travel Agent",
            "type":"Entertainment"
        }
    ],
    "sg:phone":"+1 418 851 4949",
    "sg:postcode":"G0L 4K0",
    "sg:province":"QC",
    "sg:tags":[
        "consultant"
    ],
    "wof:name":"Centre Local DE Developpement",
    "wof:placetype":"venue"
},
  "geometry": {"coordinates":[-69.1722946167,48.1232414246],"type":"Point"}
}