{
  "type": "Feature",
  "properties": {
    "addr:full":"3460 Rue Richelieu Saint-Hubert QC J3Y 7B1",
    "addr:housenumber":"3460",
    "addr:postcode":"j3y 7b1",
    "addr:street":"Rue Richelieu",
    "iso:country":"CA",
    "sg:address":"3460 Rue Richelieu",
    "sg:city":"Saint-Hubert",
    "sg:classifiers":[
        {
            "category":"Manufacturing",
            "subcategory":"Tools & Machinery",
            "type":"Manufacturing & Wholesale Goods"
        }
    ],
    "sg:phone":"+1 450 676 0113",
    "sg:postcode":"J3Y 7B1",
    "sg:province":"QC",
    "sg:tags":[
        "machine",
        "shop"
    ],
    "wof:name":"Usinage Netur Ltee",
    "wof:placetype":"venue"
},
  "geometry": {"coordinates":[-73.44412199999999,45.501667],"type":"Point"}
}