{
  "type": "Feature",
  "properties": {
    "addr:full":"Hull QC J8Y 1W7",
    "addr:postcode":"j8y 1w7",
    "iso:country":"CA",
    "sg:city":"Hull",
    "sg:classifiers":[
        {
            "category":"Organizations",
            "subcategory":"Labor Organization",
            "type":"Services"
        }
    ],
    "sg:phone":"+1 819 771 2931",
    "sg:postcode":"J8Y 1W7",
    "sg:province":"QC",
    "wof:name":"Chro",
    "wof:placetype":"venue"
},
  "geometry": {"coordinates":[-75.747185,45.443268],"type":"Point"}
}