{
  "type": "Feature",
  "properties": {
    "addr:full":"Woodbridge ON L4L 8P7",
    "addr:postcode":"l4l 8p7",
    "iso:country":"CA",
    "sg:city":"Woodbridge",
    "sg:classifiers":[
        {
            "category":"Shopping",
            "subcategory":"Crafts & Fabrics",
            "type":"Retail Goods"
        }
    ],
    "sg:phone":"+1 905 856 2106",
    "sg:postcode":"L4L 8P7",
    "sg:province":"ON",
    "sg:tags":[
        "shop"
    ],
    "wof:name":"Fabricland",
    "wof:placetype":"venue"
},
  "geometry": {"coordinates":[-79.5983963013,43.7781982422],"type":"Point"}
}