{
  "type": "Feature",
  "properties": {
    "iso:country":"CA",
    "sg:address":"75 Palmer Rd",
    "sg:city":"Hamilton",
    "sg:classifiers":[
        {
            "category":"Education",
            "subcategory":"School",
            "type":"Public Place"
        }
    ],
    "sg:phone":"+1 905 389 2234",
    "sg:postcode":"L8T 3G1",
    "sg:province":"ON",
    "wof:name":"Barton Secondary School",
    "wof:placetype":"venue"
},
  "geometry": {"coordinates":[-79.8415985107,43.2151451111],"type":"Point"}
}