{
  "type": "Feature",
  "properties": {
    "iso:country":"CA",
    "sg:address":"1151 Melsandra Ave",
    "sg:city":"London",
    "sg:classifiers":[
        {
            "category":"Real Estate",
            "subcategory":"Real Estate Agent",
            "type":"Services"
        }
    ],
    "sg:phone":"+1 519 433 5010",
    "sg:postcode":"N5Y 4N8",
    "sg:province":"ON",
    "wof:name":"Douglas Paul Real Estate",
    "wof:placetype":"venue"
},
  "geometry": {"coordinates":[-81.228706,43.019684],"type":"Point"}
}