{
  "type": "Feature",
  "properties": {
    "addr:full":"221 Baribeau St Vanier ON K1L 7R7",
    "addr:housenumber":"221",
    "addr:postcode":"k1l 7r7",
    "addr:street":"Baribeau St",
    "iso:country":"CA",
    "sg:address":"221 Baribeau St",
    "sg:city":"Vanier",
    "sg:classifiers":[
        {
            "category":"Organizations",
            "subcategory":"Religious Organization",
            "type":"Services"
        }
    ],
    "sg:phone":"+1 613 749 8092",
    "sg:postcode":"K1L 7R7",
    "sg:province":"ON",
    "wof:name":"Lift Jesus Higher",
    "wof:placetype":"venue"
},
  "geometry": {"coordinates":[-75.667091,45.437786],"type":"Point"}
}