{
  "type": "Feature",
  "properties": {
    "addr:full":"PO Box 343 Shawnigan Lake BC V0R 2W0",
    "addr:housenumber":"po",
    "addr:postcode":"bc v0r 2w0",
    "addr:street":"Box 343 Shawnigan",
    "iso:country":"CA",
    "sg:address":"PO Box 343",
    "sg:city":"Shawnigan Lake",
    "sg:classifiers":[
        {
            "category":"Building & Trades",
            "subcategory":"Construction",
            "type":"Services"
        }
    ],
    "sg:phone":"+1 250 748 9012",
    "sg:postcode":"V0R 2W0",
    "sg:province":"BC",
    "sg:tags":[
        "insulation",
        "heat",
        "general",
        "contractor"
    ],
    "wof:name":"Insolex Home Svc Ltd",
    "wof:placetype":"venue"
},
  "geometry": {"coordinates":[-123.61454000000001,48.653748],"type":"Point"}
}