{
  "type": "Feature",
  "properties": {
    "addr:full":"1880 1st Ave W Vancouver BC V6J 1G5",
    "addr:housenumber":"1880",
    "addr:postcode":"v6j 1g5",
    "addr:street":"1St Ave W",
    "iso:country":"CA",
    "sg:address":"1880 1st Ave W",
    "sg:city":"Vancouver",
    "sg:classifiers":[
        {
            "category":"Restaurant",
            "type":"Food & Drink"
        }
    ],
    "sg:phone":"+1 604 738 6684",
    "sg:postcode":"V6J 1G5",
    "sg:province":"BC",
    "wof:name":"Bread Garden Bakery & Cafe",
    "wof:placetype":"venue"
},
  "geometry": {"coordinates":[-123.147362,49.270443],"type":"Point"}
}