{
  "type": "Feature",
  "properties": {
    "addr:full":"100 Wilson St Woodstock ON N4S 3N9",
    "addr:housenumber":"100",
    "addr:postcode":"n4s 3n9",
    "addr:street":"Wilson St",
    "iso:country":"CA",
    "sg:address":"100 Wilson St",
    "sg:city":"Woodstock",
    "sg:classifiers":[
        {
            "category":"Building & Trades",
            "subcategory":"Equipment Rental",
            "type":"Services"
        }
    ],
    "sg:phone":"+1 519 421 0501",
    "sg:postcode":"N4S 3N9",
    "sg:province":"ON",
    "sg:tags":[
        "yard",
        "contractor"
    ],
    "wof:name":"Battlefield Equipment Rentals",
    "wof:placetype":"venue"
},
  "geometry": {"coordinates":[-80.746346,43.127666],"type":"Point"}
}