{
  "type": "Feature",
  "properties": {
    "addr:full":"9430 Rue Jean-Milot Lasalle QC H8R 3V9",
    "addr:housenumber":"9430",
    "addr:postcode":"h8r 3v9",
    "addr:street":"Rue Jean-Milot",
    "iso:country":"CA",
    "sg:address":"9430 Rue Jean-Milot",
    "sg:city":"Lasalle",
    "sg:classifiers":[
        {
            "category":"Wholesale",
            "subcategory":"Drugs",
            "type":"Manufacturing & Wholesale Goods"
        }
    ],
    "sg:phone":"+1 514 363 0432",
    "sg:postcode":"H8R 3V9",
    "sg:province":"QC",
    "sg:tags":[
        "perfume"
    ],
    "wof:name":"Geurlain Canada Ltd-Ltee",
    "wof:placetype":"venue"
},
  "geometry": {"coordinates":[-73.6440124512,45.429775238],"type":"Point"}
}