{
  "type": "Feature",
  "properties": {
    "addr:full":"Belleville ON K8N 4Z5",
    "addr:postcode":"k8n 4z5",
    "iso:country":"CA",
    "sg:city":"Belleville",
    "sg:classifiers":[
        {
            "category":"Building & Trades",
            "subcategory":"Plumbing",
            "type":"Services"
        }
    ],
    "sg:phone":"+1 613 966 8848",
    "sg:postcode":"K8N 4Z5",
    "sg:province":"ON",
    "sg:tags":[
        "conditioning",
        "air",
        "system",
        "contractor"
    ],
    "wof:name":"Friel Heating & Air Cond",
    "wof:placetype":"venue"
},
  "geometry": {"coordinates":[-77.3851547241,44.1842002869],"type":"Point"}
}