{
  "type": "Feature",
  "properties": {
    "iso:country":"CA",
    "sg:address":"621 Rock Haven Rd",
    "sg:city":"Selkirk",
    "sg:classifiers":[
        {
            "category":"Building & Trades",
            "subcategory":"Electrical",
            "type":"Services"
        }
    ],
    "sg:phone":"+1 204 757 2790",
    "sg:postcode":"R1A 2A8",
    "sg:province":"MB",
    "sg:tags":[
        "electric",
        "contractor"
    ],
    "wof:name":"Hoffmann's Electric",
    "wof:placetype":"venue"
},
  "geometry": {"coordinates":[-96.87390899659999,50.1457252502],"type":"Point"}
}