{
  "type": "Feature",
  "properties": {
    "addr:full":"Otterville ON N0J 1R0",
    "addr:postcode":"n0j 1r0",
    "iso:country":"CA",
    "sg:city":"Otterville",
    "sg:classifiers":[
        {
            "category":"Professional",
            "subcategory":"Engineering",
            "type":"Services"
        }
    ],
    "sg:phone":"+1 519 879 6875",
    "sg:postcode":"N0J 1R0",
    "sg:province":"ON",
    "sg:tags":[
        "engineer"
    ],
    "wof:name":"L A Girard Engineering Ltd",
    "wof:placetype":"venue"
},
  "geometry": {"coordinates":[-80.60432434080001,42.9264907837],"type":"Point"}
}