{
  "type": "Feature",
  "properties": {
    "addr:full":"172 Rue Loyola Repentigny QC J6A 5X2",
    "addr:housenumber":"172",
    "addr:postcode":"j6a 5x2",
    "addr:street":"Rue Loyola",
    "iso:country":"CA",
    "sg:address":"172 Rue Loyola",
    "sg:city":"Repentigny",
    "sg:classifiers":[
        {
            "category":"Personal",
            "subcategory":"Beauty Salon",
            "type":"Services"
        }
    ],
    "sg:phone":"+1 450 585 5445",
    "sg:postcode":"J6A 5X2",
    "sg:province":"QC",
    "wof:name":"Studio Seduction",
    "wof:placetype":"venue"
},
  "geometry": {"coordinates":[-73.46453099999999,45.744324],"type":"Point"}
}