{
  "type": "Feature",
  "properties": {
    "addr:full":"Montreal QC H2L 4S5",
    "addr:postcode":"h2l 4s5",
    "iso:country":"CA",
    "sg:city":"Montreal",
    "sg:classifiers":[
        {
            "category":"Professional",
            "subcategory":"Business Services",
            "type":"Services"
        }
    ],
    "sg:phone":"+1 514 282 1999",
    "sg:postcode":"H2L 4S5",
    "sg:province":"QC",
    "sg:tags":[
        "recording",
        "studio",
        "library"
    ],
    "wof:name":"Magnetotheque",
    "wof:placetype":"venue"
},
  "geometry": {"coordinates":[-73.55526733400001,45.5163497925],"type":"Point"}
}