{
  "type": "Feature",
  "properties": {
    "iso:country":"CA",
    "sg:city":"Windsor",
    "sg:classifiers":[
        {
            "category":"Professional",
            "subcategory":"Secretarial Services",
            "type":"Services"
        }
    ],
    "sg:phone":"+1 519 252 1134",
    "sg:postcode":"N9A 4K4",
    "sg:province":"ON",
    "sg:tags":[
        "convention",
        "court",
        "reporter"
    ],
    "wof:name":"E Beryl Mac Millan Examiner",
    "wof:placetype":"venue"
},
  "geometry": {"coordinates":[-83.040352,42.317505],"type":"Point"}
}