{
  "type": "Feature",
  "properties": {
    "iso:country":"CA",
    "sg:city":"Montreal",
    "sg:classifiers":[
        {
            "category":"Wholesale",
            "subcategory":"Medical Equipment & Supplies",
            "type":"Manufacturing & Wholesale Goods"
        }
    ],
    "sg:phone":"+1 514 333 3279",
    "sg:postcode":"H3M 1L2",
    "sg:province":"QC",
    "sg:tags":[
        "hospital"
    ],
    "wof:name":"Mrt Recherches & Dev Medical",
    "wof:placetype":"venue"
},
  "geometry": {"coordinates":[-73.69844818120001,45.5387763977],"type":"Point"}
}