{
  "type": "Feature",
  "properties": {
    "addr:full":"685 Erskine Ave Peterborough ON K9J 5T7",
    "addr:housenumber":"685",
    "addr:postcode":"k9j 5t7",
    "addr:street":"Erskine Ave",
    "iso:country":"CA",
    "sg:address":"685 Erskine Ave",
    "sg:city":"Peterborough",
    "sg:classifiers":[
        {
            "category":"Home & Garden",
            "subcategory":"Building Materials",
            "type":"Retail Goods"
        }
    ],
    "sg:phone":"+1 705 741 6259",
    "sg:postcode":"K9J 5T7",
    "sg:province":"ON",
    "sg:tags":[
        "door"
    ],
    "wof:name":"Peterborough Door Systems",
    "wof:placetype":"venue"
},
  "geometry": {"coordinates":[-78.334641,44.279106],"type":"Point"}
}