{
  "type": "Feature",
  "properties": {
    "addr:full":"4290 12E Av Shawinigan-Sud QC G9P 4G2",
    "addr:housenumber":"4290",
    "addr:postcode":"g9p 4g2",
    "addr:street":"12E Av Shawinigan-Sud",
    "iso:country":"CA",
    "sg:address":"4290 12E Av",
    "sg:city":"Shawinigan-Sud",
    "sg:classifiers":[
        {
            "category":"Retail",
            "subcategory":"Repair Shop",
            "type":"Services"
        }
    ],
    "sg:phone":"+1 819 537 1251",
    "sg:postcode":"G9P 4G2",
    "sg:province":"QC",
    "sg:tags":[
        "upholsterer"
    ],
    "wof:name":"Rembourrage Expert 2000",
    "wof:placetype":"venue"
},
  "geometry": {"coordinates":[-72.72698200000001,46.502262],"type":"Point"}
}