{
  "type": "Feature",
  "properties": {
    "addr:full":"41 Gordon Ave Essex ON N8M 2M5",
    "addr:housenumber":"41",
    "addr:postcode":"n8m 2m5",
    "addr:street":"Gordon Ave",
    "iso:country":"CA",
    "sg:address":"41 Gordon Ave",
    "sg:city":"Essex",
    "sg:classifiers":[
        {
            "category":"Retail",
            "subcategory":"Auto Repair",
            "type":"Services"
        }
    ],
    "sg:phone":"+1 519 776 8491",
    "sg:postcode":"N8M 2M5",
    "sg:province":"ON",
    "sg:tags":[
        "repairing",
        "automobile"
    ],
    "wof:name":"D B Automotive",
    "wof:placetype":"venue"
},
  "geometry": {"coordinates":[-82.819862,42.174961],"type":"Point"}
}