{
  "type": "Feature",
  "properties": {
    "iso:country":"CA",
    "sg:address":"126 Sussex St",
    "sg:city":"Oshawa",
    "sg:classifiers":[
        {
            "category":"Shopping",
            "subcategory":"Computers & Home Electronics",
            "type":"Retail Goods"
        }
    ],
    "sg:phone":"+1 905 571 4493",
    "sg:postcode":"L1G 1V9",
    "sg:province":"ON",
    "sg:tags":[
        "software"
    ],
    "wof:name":"Nerds Software",
    "wof:placetype":"venue"
},
  "geometry": {"coordinates":[-78.8430862427,43.9068565369],"type":"Point"}
}