{
  "type": "Feature",
  "properties": {
    "iso:country":"CA",
    "sg:city":"Lunenburg",
    "sg:classifiers":[
        {
            "category":"Shopping",
            "type":"Retail Goods"
        }
    ],
    "sg:phone":"+1 902 634 3166",
    "sg:postcode":"B0J 2C0",
    "sg:province":"NS",
    "sg:tags":[
        "monument"
    ],
    "wof:name":"Tingley Monuments Ltd",
    "wof:placetype":"venue"
},
  "geometry": {"coordinates":[-64.3184432983,44.3772125244],"type":"Point"}
}