{
  "type": "Feature",
  "properties": {
    "addr:full":"#1150 10180-101 Street Edmonton, Alberta T5J 3S4",
    "addr:housenumber":"10180-101",
    "addr:postcode":"t5j 3s4",
    "addr:street":"Street",
    "iso:country":"CA",
    "sg:address":"#1150 10180-101 Street",
    "sg:city":"Edmonton, Alberta",
    "sg:classifiers":[
        {
            "category":"Professional",
            "subcategory":"Computer Services",
            "type":"Services"
        }
    ],
    "sg:postcode":"T5J 3S4",
    "sg:tags":[
        "doorbell",
        "smibs",
        "sales",
        "professional-networking",
        "CRM"
    ],
    "sg:website":"http://www.smibs.com",
    "wof:name":"Smibs",
    "wof:placetype":"venue"
},
  "geometry": {"coordinates":[-113.50667199999999,53.543854],"type":"Point"}
}