{
  "type": "Feature",
  "properties": {
    "addr:full":"Elie MB R0H 0H0",
    "addr:postcode":"r0h 0h0",
    "iso:country":"CA",
    "sg:city":"Elie",
    "sg:classifiers":[
        {
            "category":"Manufacturing",
            "subcategory":"Metals",
            "type":"Manufacturing & Wholesale Goods"
        }
    ],
    "sg:phone":"+1 204 353 2741",
    "sg:postcode":"R0H 0H0",
    "sg:province":"MB",
    "sg:tags":[
        "steel"
    ],
    "wof:name":"Milltown Metal Shop",
    "wof:placetype":"venue"
},
  "geometry": {"coordinates":[-97.7596740723,49.901424408],"type":"Point"}
}