{
  "type": "Feature",
  "properties": {
    "addr:full":"3813 208 St Langley BC V3A 4X6",
    "addr:housenumber":"3813",
    "addr:postcode":"v3a 4x6",
    "addr:street":"208 St",
    "iso:country":"CA",
    "sg:address":"3813 208 St",
    "sg:city":"Langley",
    "sg:classifiers":[
        {
            "category":"Building & Trades",
            "subcategory":"Construction",
            "type":"Services"
        }
    ],
    "sg:phone":"+1 604 534 3689",
    "sg:postcode":"V3A 4X6",
    "sg:province":"BC",
    "sg:tags":[
        "designer",
        "dealer",
        "pool",
        "swimming"
    ],
    "wof:name":"Brookswood Pool & Spa Svc",
    "wof:placetype":"venue"
},
  "geometry": {"coordinates":[-122.647682,49.071178],"type":"Point"}
}