{
  "type": "Feature",
  "properties": {
    "iso:country":"CA",
    "sg:address":"2220 Av Beaconsfield",
    "sg:city":"Montreal",
    "sg:classifiers":[
        {
            "category":"Professional",
            "subcategory":"Business Services",
            "type":"Services"
        }
    ],
    "sg:phone":"+1 514 481 8855",
    "sg:postcode":"H4A 2G8",
    "sg:province":"QC",
    "sg:tags":[
        "recording",
        "studio"
    ],
    "wof:name":"Studio Fast Forward Inc",
    "wof:placetype":"venue"
},
  "geometry": {"coordinates":[-73.619698,45.46595],"type":"Point"}
}