{
  "type": "Feature",
  "properties": {
    "addr:full":"1222 Yonge St Toronto ON M4T 1W3",
    "addr:housenumber":"1222",
    "addr:postcode":"m4t 1w3",
    "addr:street":"Yonge St",
    "iso:country":"CA",
    "sg:address":"1222 Yonge St",
    "sg:city":"Toronto",
    "sg:classifiers":[
        {
            "category":"Shopping",
            "subcategory":"Gifts & Souvenirs",
            "type":"Retail Goods"
        }
    ],
    "sg:phone":"+1 416 921 3040",
    "sg:postcode":"M4T 1W3",
    "sg:province":"ON",
    "sg:tags":[
        "shop"
    ],
    "wof:name":"Quintessence Designs",
    "wof:placetype":"venue"
},
  "geometry": {"coordinates":[-79.391769,43.682224],"type":"Point"}
}