{
  "type": "Feature",
  "properties": {
    "addr:full":"22 Maxwell Pl St. John's NL A1A 1G7",
    "addr:housenumber":"22",
    "addr:postcode":"a1a 1g7",
    "addr:street":"Maxwell Pl",
    "iso:country":"CA",
    "sg:address":"22 Maxwell Pl",
    "sg:city":"St. John's",
    "sg:classifiers":[
        {
            "category":"Health Services",
            "subcategory":"Medical Lab",
            "type":"Services"
        }
    ],
    "sg:phone":"+1 709 579 7007",
    "sg:postcode":"A1A 1G7",
    "sg:province":"NL",
    "sg:tags":[
        "laboratory"
    ],
    "wof:name":"Kings Orthodontic Laboratory",
    "wof:placetype":"venue"
},
  "geometry": {"coordinates":[-52.6831474304,47.5781402588],"type":"Point"}
}