{
  "type": "Feature",
  "properties": {
    "addr:full":"3115 Rue DE Miniac Saint-Laurent QC H4S 1S9",
    "addr:housenumber":"3115",
    "addr:postcode":"h4s 1s9",
    "addr:street":"Rue De Miniac",
    "iso:country":"CA",
    "sg:address":"3115 Rue DE Miniac",
    "sg:city":"Saint-Laurent",
    "sg:classifiers":[
        {
            "category":"Freight",
            "type":"Transportation"
        }
    ],
    "sg:phone":"+1 514 335 3100",
    "sg:postcode":"H4S 1S9",
    "sg:province":"QC",
    "sg:tags":[
        "delivery"
    ],
    "wof:name":"M A Sort Livraison Inc",
    "wof:placetype":"venue"
},
  "geometry": {"coordinates":[-73.753075,45.496838],"type":"Point"}
}