{
  "type": "Feature",
  "properties": {
    "addr:full":"130 Wyatt Rd Winnipeg MB R2X 2X6",
    "addr:housenumber":"130",
    "addr:postcode":"r2x 2x6",
    "addr:street":"Wyatt Rd",
    "iso:country":"CA",
    "sg:address":"130 Wyatt Rd",
    "sg:city":"Winnipeg",
    "sg:classifiers":[
        {
            "category":"Home & Garden",
            "subcategory":"Home Furnishings",
            "type":"Retail Goods"
        }
    ],
    "sg:phone":"+1 204 632 0770",
    "sg:postcode":"R2X 2X6",
    "sg:province":"MB",
    "sg:tags":[
        "quilting"
    ],
    "wof:name":"Major Quilting Ltd",
    "wof:placetype":"venue"
},
  "geometry": {"coordinates":[-97.1864929199,49.947883606],"type":"Point"}
}