{
  "type": "Feature",
  "properties": {
    "iso:country":"CA",
    "sg:address":"974 Queen St E # 208",
    "sg:city":"Sault Ste Marie",
    "sg:classifiers":[
        {
            "category":"Health Services",
            "subcategory":"Doctor",
            "type":"Services"
        }
    ],
    "sg:phone":"+1 705 942 6845",
    "sg:postcode":"P6A 2C5",
    "sg:province":"ON",
    "sg:tags":[
        "physician",
        "surgeon"
    ],
    "wof:name":"Hergott, Paul MD",
    "wof:placetype":"venue"
},
  "geometry": {"coordinates":[-84.31806182859999,46.5055541992],"type":"Point"}
}