{
  "type": "Feature",
  "properties": {
    "iso:country":"CA",
    "sg:address":"1071 Rue Saint-Andre",
    "sg:city":"Acton Vale",
    "sg:classifiers":[
        {
            "category":"Restaurant",
            "type":"Food & Drink"
        }
    ],
    "sg:phone":"+1 450 546 2729",
    "sg:postcode":"J0H 1A0",
    "sg:province":"QC",
    "wof:name":"Restaurant Sandro Pizzeria Enr",
    "wof:placetype":"venue"
},
  "geometry": {"coordinates":[-72.5648345947,45.649433136],"type":"Point"}
}