{
  "type": "Feature",
  "properties": {
    "addr:full":"12 Fairway Pl Winnipeg MB R3R 2P3",
    "addr:housenumber":"12",
    "addr:postcode":"r3r 2p3",
    "addr:street":"Fairway Pl",
    "iso:country":"CA",
    "sg:address":"12 Fairway Pl",
    "sg:city":"Winnipeg",
    "sg:classifiers":[
        {
            "category":"Manufacturing",
            "subcategory":"Food",
            "type":"Manufacturing & Wholesale Goods"
        }
    ],
    "sg:phone":"+1 204 885 4312",
    "sg:postcode":"R3R 2P3",
    "sg:province":"MB",
    "sg:tags":[
        "packer",
        "fish"
    ],
    "wof:name":"Northwest Cooperative Fish",
    "wof:placetype":"venue"
},
  "geometry": {"coordinates":[-97.27504,49.866207],"type":"Point"}
}