{
  "type": "Feature",
  "properties": {
    "addr:full":"55 Saint Phillips Rd Etobicoke ON M9P 2N8",
    "addr:housenumber":"55",
    "addr:postcode":"m9p 2n8",
    "addr:street":"Saint Phillips Rd",
    "iso:country":"CA",
    "sg:address":"55 Saint Phillips Rd",
    "sg:city":"Etobicoke",
    "sg:classifiers":[
        {
            "category":"Organizations",
            "subcategory":"Religious Organization",
            "type":"Services"
        }
    ],
    "sg:phone":"+1 416 249 8769",
    "sg:postcode":"M9P 2N8",
    "sg:province":"ON",
    "sg:tags":[
        "church"
    ],
    "wof:name":"Unitarian Fellowship of NW",
    "wof:placetype":"venue"
},
  "geometry": {"coordinates":[-79.53140999999999,43.703667],"type":"Point"}
}