{
  "type": "Feature",
  "properties": {
    "addr:full":"418 John St N Hamilton ON L8L 4R3",
    "addr:housenumber":"418",
    "addr:postcode":"l8l 4r3",
    "addr:street":"John St N",
    "iso:country":"CA",
    "sg:address":"418 John St N",
    "sg:city":"Hamilton",
    "sg:classifiers":[
        {
            "category":"Retail",
            "subcategory":"Auto Repair",
            "type":"Services"
        }
    ],
    "sg:phone":"+1 905 577 4706",
    "sg:postcode":"L8L 4R3",
    "sg:province":"ON",
    "sg:tags":[
        "repairing",
        "automobile"
    ],
    "wof:name":"Baker Performance Works",
    "wof:placetype":"venue"
},
  "geometry": {"coordinates":[-79.860764,43.2686],"type":"Point"}
}