{
  "type": "Feature",
  "properties": {
    "addr:full":"160 Fourth Ave St Catharines ON L2R 6P9",
    "addr:housenumber":"160",
    "addr:postcode":"l2r 6p9",
    "addr:street":"Fourth Ave",
    "iso:country":"CA",
    "sg:address":"160 Fourth Ave",
    "sg:city":"St Catharines",
    "sg:classifiers":[
        {
            "category":"Government",
            "subcategory":"Office",
            "type":"Public Place"
        }
    ],
    "sg:phone":"+1 905 682 0767",
    "sg:postcode":"L2R 6P9",
    "sg:province":"ON",
    "sg:tags":[
        "organization",
        "protection",
        "animal",
        "village"
    ],
    "wof:name":"Humane Society Lincoln County",
    "wof:placetype":"venue"
},
  "geometry": {"coordinates":[-79.26574707029999,43.1554985046],"type":"Point"}
}