{
  "type": "Feature",
  "properties": {
    "addr:full":"Campbell River BC V9W 2C5",
    "addr:postcode":"v9w 2c5",
    "iso:country":"CA",
    "sg:city":"Campbell River",
    "sg:classifiers":[
        {
            "category":"Personal",
            "type":"Services"
        }
    ],
    "sg:phone":"+1 250 287 9714",
    "sg:postcode":"V9W 2C5",
    "sg:province":"BC",
    "sg:tags":[
        "electrolysis"
    ],
    "wof:name":"Angela's Electrolysis Studio",
    "wof:placetype":"venue"
},
  "geometry": {"coordinates":[-125.24307251,50.0257453918],"type":"Point"}
}