{
  "type": "Feature",
  "properties": {
    "iso:country":"CA",
    "sg:address":"25 Sass Side Rd",
    "sg:city":"Chatham",
    "sg:classifiers":[
        {
            "category":"Wholesale",
            "subcategory":"Machinery & Supplies",
            "type":"Manufacturing & Wholesale Goods"
        }
    ],
    "sg:phone":"+1 519 354 5474",
    "sg:postcode":"N7M 5J4",
    "sg:province":"ON",
    "sg:tags":[
        "cleaners",
        "rug",
        "vacuum",
        "cleaning",
        "carpet"
    ],
    "wof:name":"Sinclair Sales & Svc",
    "wof:placetype":"venue"
},
  "geometry": {"coordinates":[-82.1652297974,42.4121589661],"type":"Point"}
}