{
  "type": "Feature",
  "properties": {
    "addr:full":"846 Av Champlain Disraeli QC G0N 1E0",
    "addr:postcode":"g0n 1e0",
    "addr:street":"846 Av Champlain",
    "iso:country":"CA",
    "sg:address":"846 Av Champlain",
    "sg:city":"Disraeli",
    "sg:classifiers":[
        {
            "category":"Professional",
            "subcategory":"Business Services",
            "type":"Services"
        }
    ],
    "sg:phone":"+1 418 449 2955",
    "sg:postcode":"G0N 1E0",
    "sg:province":"QC",
    "sg:tags":[
        "notary"
    ],
    "wof:name":"Aubert & Aubert",
    "wof:placetype":"venue"
},
  "geometry": {"coordinates":[-71.3599853516,45.9061660767],"type":"Point"}
}