{
  "type": "Feature",
  "properties": {
    "addr:full":"Terrace BC V8G 1T2",
    "addr:postcode":"v8g 1t2",
    "iso:country":"CA",
    "sg:city":"Terrace",
    "sg:classifiers":[
        {
            "category":"Travel",
            "subcategory":"Travel Agent",
            "type":"Entertainment"
        }
    ],
    "sg:phone":"+1 250 638 8522",
    "sg:postcode":"V8G 1T2",
    "sg:province":"BC",
    "sg:tags":[
        "agency",
        "bureau"
    ],
    "wof:name":"Uniglobe Courtesy Travel",
    "wof:placetype":"venue"
},
  "geometry": {"coordinates":[-128.594131,54.518063],"type":"Point"}
}