{
  "type": "Feature",
  "properties": {
    "addr:full":"269 South Industrial Dr Prince Albert SK S6V 7L7",
    "addr:housenumber":"269",
    "addr:postcode":"s6v 7l7",
    "addr:street":"South Industrial Dr",
    "iso:country":"CA",
    "sg:address":"269 South Industrial Dr",
    "sg:city":"Prince Albert",
    "sg:classifiers":[
        {
            "category":"Wholesale",
            "subcategory":"Machinery & Supplies",
            "type":"Manufacturing & Wholesale Goods"
        }
    ],
    "sg:phone":"+1 306 763 2602",
    "sg:postcode":"S6V 7L7",
    "sg:province":"SK",
    "sg:tags":[
        "equipment",
        "industrial",
        "clothing",
        "safety"
    ],
    "wof:name":"Acklands-Grainger Inc",
    "wof:placetype":"venue"
},
  "geometry": {"coordinates":[-105.747406,53.180519],"type":"Point"}
}