{
  "type": "Feature",
  "properties": {
    "addr:full":"146 Main St S Newmarket ON L3Y 3Z1",
    "addr:housenumber":"146",
    "addr:postcode":"l3y 3z1",
    "addr:street":"Main St S",
    "iso:country":"CA",
    "sg:address":"146 Main St S",
    "sg:city":"Newmarket",
    "sg:classifiers":[
        {
            "category":"Shopping",
            "type":"Retail Goods"
        }
    ],
    "sg:phone":"+1 905 953 1449",
    "sg:postcode":"L3Y 3Z1",
    "sg:province":"ON",
    "sg:tags":[
        "wedding",
        "supply"
    ],
    "wof:name":"Abovo Event Planning Inc",
    "wof:placetype":"venue"
},
  "geometry": {"coordinates":[-79.4583969116,44.0544166565],"type":"Point"}
}