{
  "type": "Feature",
  "properties": {
    "addr:full":"11060 1E Av Saint-Georges QC G5Y 5S3",
    "addr:housenumber":"11060",
    "addr:postcode":"g5y 5s3",
    "addr:street":"1E Av",
    "iso:country":"CA",
    "sg:address":"11060 1E Av",
    "sg:city":"Saint-Georges",
    "sg:classifiers":[
        {
            "category":"Restaurant",
            "type":"Food & Drink"
        }
    ],
    "sg:phone":"+1 418 228 4094",
    "sg:postcode":"G5Y 5S3",
    "sg:province":"QC",
    "wof:name":"Gestion Lotus St-Georges Inc",
    "wof:placetype":"venue"
},
  "geometry": {"coordinates":[-70.67115,46.123348],"type":"Point"}
}