{
  "type": "Feature",
  "properties": {
    "addr:full":"York ON M9N 1X7",
    "addr:postcode":"m9n 1x7",
    "iso:country":"CA",
    "sg:city":"York",
    "sg:classifiers":[
        {
            "category":"Retail",
            "subcategory":"Laundry & Dry Cleaning",
            "type":"Services"
        }
    ],
    "sg:phone":"+1 416 242 3986",
    "sg:postcode":"M9N 1X7",
    "sg:province":"ON",
    "sg:tags":[
        "cleaners"
    ],
    "wof:name":"Weston Laundromat Cafe",
    "wof:placetype":"venue"
},
  "geometry": {"coordinates":[-79.52233099999999,43.702003],"type":"Point"}
}