{
  "type": "Feature",
  "properties": {
    "addr:full":"21 Alworth Pl Sault Ste Marie ON P6B 5W5",
    "addr:housenumber":"21",
    "addr:postcode":"p6b 5w5",
    "addr:street":"Alworth Pl",
    "iso:country":"CA",
    "sg:address":"21 Alworth Pl",
    "sg:city":"Sault Ste Marie",
    "sg:classifiers":[
        {
            "category":"Health Services",
            "subcategory":"Doctor",
            "type":"Services"
        }
    ],
    "sg:phone":"+1 705 946 5068",
    "sg:postcode":"P6B 5W5",
    "sg:province":"ON",
    "sg:tags":[
        "physician",
        "surgeon"
    ],
    "wof:name":"Stevenson, Robert F MD",
    "wof:placetype":"venue"
},
  "geometry": {"coordinates":[-84.31108093260001,46.5150413513],"type":"Point"}
}