{
  "type": "Feature",
  "properties": {
    "iso:country":"CA",
    "sg:address":"21 Alworth Pl",
    "sg:city":"Sault Ste Marie",
    "sg:classifiers":[
        {
            "category":"Health Services",
            "subcategory":"Doctor",
            "type":"Services"
        }
    ],
    "sg:phone":"+1 705 946 5068",
    "sg:postcode":"P6B 5W5",
    "sg:province":"ON",
    "sg:tags":[
        "physician",
        "surgeon"
    ],
    "wof:name":"Stevenson, Robert F MD",
    "wof:placetype":"venue"
},
  "geometry": {"coordinates":[-84.31108093260001,46.5150413513],"type":"Point"}
}