{
  "type": "Feature",
  "properties": {
    "addr:full":"5975 Boul Monk Montreal QC H4E 3H5",
    "addr:housenumber":"5975",
    "addr:postcode":"h4e 3h5",
    "addr:street":"Boul Monk",
    "iso:country":"CA",
    "sg:address":"5975 Boul Monk",
    "sg:city":"Montreal",
    "sg:classifiers":[
        {
            "category":"Health Services",
            "subcategory":"Optometrist",
            "type":"Services"
        }
    ],
    "sg:phone":"+1 514 768 4148",
    "sg:postcode":"H4E 3H5",
    "sg:province":"QC",
    "wof:name":"Cote, Andre OD",
    "wof:placetype":"venue"
},
  "geometry": {"coordinates":[-73.596199,45.458473],"type":"Point"}
}