{
  "type": "Feature",
  "properties": {
    "addr:full":"1010 Polytek St #31 Gloucester ON K1J 9J2",
    "addr:housenumber":"1010;31",
    "addr:postcode":"k1j 9j2",
    "addr:street":"Polytek St #",
    "iso:country":"CA",
    "sg:address":"1010 Polytek St #31",
    "sg:city":"Gloucester",
    "sg:classifiers":[
        {
            "category":"Manufacturing",
            "subcategory":"Rubber & Plastics",
            "type":"Manufacturing & Wholesale Goods"
        }
    ],
    "sg:phone":"+1 613 744 7004",
    "sg:postcode":"K1J 9J2",
    "sg:province":"ON",
    "sg:tags":[
        "equipment",
        "bookbinder",
        "laminating",
        "supply"
    ],
    "wof:name":"Southwest Binding Systems",
    "wof:placetype":"venue"
},
  "geometry": {"coordinates":[-75.58419036870001,45.4564933777],"type":"Point"}
}