{
  "type": "Feature",
  "properties": {
    "addr:full":"803 S 11 Ave Golden BC V0A 1H0",
    "addr:housenumber":"803",
    "addr:postcode":"v0a 1h0",
    "addr:street":"S 11 Ave",
    "iso:country":"CA",
    "sg:address":"803 S 11 Ave",
    "sg:city":"Golden",
    "sg:classifiers":[
        {
            "category":"Retail",
            "subcategory":"Funeral Services",
            "type":"Services"
        }
    ],
    "sg:phone":"+1 250 344 2958",
    "sg:postcode":"V0A 1H0",
    "sg:province":"BC",
    "sg:tags":[
        "director"
    ],
    "wof:name":"Hindman-Bowers Funeral Home",
    "wof:placetype":"venue"
},
  "geometry": {"coordinates":[-116.960838,51.297211],"type":"Point"}
}