{
  "type": "Feature",
  "properties": {
    "addr:full":"1240 Deer River Cir SE Calgary AB T2J 6Z2",
    "addr:housenumber":"1240",
    "addr:postcode":"t2j 6z2",
    "addr:street":"Deer River Cir Se",
    "iso:country":"CA",
    "sg:address":"1240 Deer River Cir SE",
    "sg:city":"Calgary",
    "sg:classifiers":[
        {
            "category":"Professional",
            "subcategory":"Computer Services",
            "type":"Services"
        }
    ],
    "sg:phone":"+1 403 271 1699",
    "sg:postcode":"T2J 6Z2",
    "sg:province":"AB",
    "sg:tags":[
        "repair"
    ],
    "wof:name":"Everett-Douglas Consulting Inc",
    "wof:placetype":"venue"
},
  "geometry": {"coordinates":[-114.010498047,50.9358978271],"type":"Point"}
}