{
  "type": "Feature",
  "properties": {
    "addr:full":"Dundas ON L9H 5P8",
    "addr:postcode":"l9h 5p8",
    "iso:country":"CA",
    "sg:city":"Dundas",
    "sg:classifiers":[
        {
            "category":"Professional",
            "subcategory":"Management & Consulting",
            "type":"Services"
        }
    ],
    "sg:phone":"+1 905 627 6863",
    "sg:postcode":"L9H 5P8",
    "sg:province":"ON",
    "sg:tags":[
        "food"
    ],
    "wof:name":"Chartwells",
    "wof:placetype":"venue"
},
  "geometry": {"coordinates":[-79.94348144529999,43.2610588074],"type":"Point"}
}