{
  "type": "Feature",
  "properties": {
    "addr:full":"18 Gordon St Teeswater ON N0G 2S0",
    "addr:housenumber":"18",
    "addr:postcode":"n0g 2s0",
    "addr:street":"Gordon St",
    "iso:country":"CA",
    "sg:address":"18 Gordon St",
    "sg:city":"Teeswater",
    "sg:classifiers":[
        {
            "category":"Education",
            "subcategory":"School",
            "type":"Public Place"
        }
    ],
    "sg:phone":"+1 519 392 6854",
    "sg:postcode":"N0G 2S0",
    "sg:province":"ON",
    "wof:name":"Sacred Heart School",
    "wof:placetype":"venue"
},
  "geometry": {"coordinates":[-81.28331756590001,43.9960708618],"type":"Point"}
}