{
  "type": "Feature",
  "properties": {
    "addr:full":"1400 Chief Louis Way Kamloops BC V2H 1J8",
    "addr:housenumber":"1400",
    "addr:postcode":"bc v2h 1j8",
    "addr:street":"Chief Louis Way",
    "iso:country":"CA",
    "sg:address":"1400 Chief Louis Way",
    "sg:city":"Kamloops",
    "sg:classifiers":[
        {
            "category":"Freight",
            "type":"Transportation"
        }
    ],
    "sg:phone":"+1 250 372 9566",
    "sg:postcode":"V2H 1J8",
    "sg:province":"BC",
    "sg:tags":[
        "trucking"
    ],
    "wof:name":"Darlen Transport Ltd",
    "wof:placetype":"venue"
},
  "geometry": {"coordinates":[-120.33039092999999,50.7164535522],"type":"Point"}
}