{
  "type": "Feature",
  "properties": {
    "iso:country":"CA",
    "sg:address":"1414 Boul Rene-Levesque O",
    "sg:city":"Quebec",
    "sg:classifiers":[
        {
            "category":"Health Services",
            "subcategory":"Doctor",
            "type":"Services"
        }
    ],
    "sg:phone":"+1 418 688 7281",
    "sg:postcode":"G1S 1X2",
    "sg:province":"QC",
    "sg:tags":[
        "clinic"
    ],
    "wof:name":"Centre DE Prelevements Medic",
    "wof:placetype":"venue"
},
  "geometry": {"coordinates":[-71.2520370483,46.7900733948],"type":"Point"}
}