{
  "type": "Feature",
  "properties": {
    "iso:country":"CA",
    "sg:address":"Conception Bay Hwy",
    "sg:city":"Conception Harbour",
    "sg:classifiers":[
        {
            "category":"Government",
            "subcategory":"Post Office",
            "type":"Public Place"
        }
    ],
    "sg:phone":"+1 709 229 6277",
    "sg:postcode":"A0A 1Z0",
    "sg:province":"NL",
    "wof:name":"Canada Post Corp",
    "wof:placetype":"venue"
},
  "geometry": {"coordinates":[-53.2116241455,47.4401931763],"type":"Point"}
}