{
  "type": "Feature",
  "properties": {
    "addr:full":"5656 Rue Sherbrooke E Montreal QC H1N 1A1",
    "addr:housenumber":"5656",
    "addr:postcode":"h1n 1a1",
    "addr:street":"Rue Sherbrooke E",
    "iso:country":"CA",
    "sg:address":"5656 Rue Sherbrooke E",
    "sg:city":"Montreal",
    "sg:classifiers":[
        {
            "category":"Restaurant",
            "type":"Food & Drink"
        }
    ],
    "sg:phone":"+1 514 252 4446",
    "sg:postcode":"H1N 1A1",
    "sg:province":"QC",
    "wof:name":"Vinnie Gambini Restaurant",
    "wof:placetype":"venue"
},
  "geometry": {"coordinates":[-73.5492172241,45.5726509094],"type":"Point"}
}