{
  "type": "Feature",
  "properties": {
    "iso:country":"CA",
    "sg:address":"701 Pape Ave",
    "sg:city":"Toronto",
    "sg:classifiers":[
        {
            "category":"Education",
            "subcategory":"Library",
            "type":"Public Place"
        }
    ],
    "sg:phone":"+1 416 393 7727",
    "sg:postcode":"M4K 3S6",
    "sg:province":"ON",
    "wof:name":"Toronto Public Library",
    "wof:placetype":"venue"
},
  "geometry": {"coordinates":[-79.34452056879999,43.6785964966],"type":"Point"}
}