{
  "type": "Feature",
  "properties": {
    "addr:full":"Kingston ON K7L 1H4",
    "addr:postcode":"k7l 1h4",
    "iso:country":"CA",
    "sg:city":"Kingston",
    "sg:classifiers":[
        {
            "category":"Shopping",
            "subcategory":"Used Merchandise",
            "type":"Retail Goods"
        }
    ],
    "sg:phone":"+1 613 536 1050",
    "sg:postcode":"K7L 1H4",
    "sg:province":"ON",
    "sg:tags":[
        "flea",
        "market"
    ],
    "wof:name":"Olde Circle Flea Market",
    "wof:placetype":"venue"
},
  "geometry": {"coordinates":[-76.512878418,44.2410163879],"type":"Point"}
}