{
  "type": "Feature",
  "properties": {
    "addr:full":"1423 Boul Saint-Laurent Montreal QC H2X 2S8",
    "addr:housenumber":"1423",
    "addr:postcode":"h2x 2s8",
    "addr:street":"Boul Saint-Laurent",
    "iso:country":"CA",
    "sg:address":"1423 Boul Saint-Laurent",
    "sg:city":"Montreal",
    "sg:classifiers":[
        {
            "category":"Shopping",
            "subcategory":"Bicycles & Sporting Goods",
            "type":"Retail Goods"
        }
    ],
    "sg:phone":"+1 514 842 3465",
    "sg:postcode":"H2X 2S8",
    "sg:province":"QC",
    "sg:tags":[
        "salvage",
        "surplus",
        "merchandise"
    ],
    "wof:name":"Canam Surplus D'Armee",
    "wof:placetype":"venue"
},
  "geometry": {"coordinates":[-73.564117,45.510185],"type":"Point"}
}