{
  "type": "Feature",
  "properties": {
    "addr:full":"2205 Keene Rd Peterborough ON K9J 6X9",
    "addr:housenumber":"2205",
    "addr:postcode":"k9j 6x9",
    "addr:street":"Keene Rd",
    "iso:country":"CA",
    "sg:address":"2205 Keene Rd",
    "sg:city":"Peterborough",
    "sg:classifiers":[
        {
            "category":"Restaurant",
            "type":"Food & Drink"
        }
    ],
    "sg:phone":"+1 705 740 0558",
    "sg:postcode":"K9J 6X9",
    "sg:province":"ON",
    "wof:name":"Marty Moo's",
    "wof:placetype":"venue"
},
  "geometry": {"coordinates":[-78.2764587402,44.2944412231],"type":"Point"}
}