{
  "type": "Feature",
  "properties": {
    "addr:full":"900 Boul Pierre-Bertrand # 100 Vanier QC G1M 3K2",
    "addr:housenumber":"900",
    "addr:postcode":"g1m 3k2",
    "addr:street":"Boul Pierre-Bertrand # 100",
    "iso:country":"CA",
    "sg:address":"900 Boul Pierre-Bertrand # 100",
    "sg:city":"Vanier",
    "sg:classifiers":[
        {
            "category":"Shopping",
            "subcategory":"Stationery & Office Supplies",
            "type":"Retail Goods"
        }
    ],
    "sg:phone":"+1 418 683 6800",
    "sg:postcode":"G1M 3K2",
    "sg:province":"QC",
    "sg:tags":[
        "furniture"
    ],
    "wof:name":"Specialiste Du Stylo-Papeterie",
    "wof:placetype":"venue"
},
  "geometry": {"coordinates":[-71.274307251,46.8266983032],"type":"Point"}
}