{
  "type": "Feature",
  "properties": {
    "addr:full":"402 Harmony Rd Ayr ON N0B 1E0",
    "addr:housenumber":"402",
    "addr:postcode":"n0b 1e0",
    "addr:street":"Harmony Rd",
    "iso:country":"CA",
    "sg:address":"402 Harmony Rd",
    "sg:city":"Ayr",
    "sg:classifiers":[
        {
            "category":"Manufacturing",
            "subcategory":"Tools & Machinery",
            "type":"Manufacturing & Wholesale Goods"
        }
    ],
    "sg:phone":"+1 519 740 6035",
    "sg:postcode":"N0B 1E0",
    "sg:province":"ON",
    "sg:tags":[
        "equipment",
        "system",
        "automation"
    ],
    "wof:name":"Cambridge Metal Products Inc",
    "wof:placetype":"venue"
},
  "geometry": {"coordinates":[-80.449997,43.285656],"type":"Point"}
}