{
  "type": "Feature",
  "properties": {
    "addr:full":"136 Grand Trunk Ave Dryden ON P8N 2W6",
    "addr:housenumber":"136",
    "addr:postcode":"p8n 2w6",
    "addr:street":"Grand Trunk Ave",
    "iso:country":"CA",
    "sg:address":"136 Grand Trunk Ave",
    "sg:city":"Dryden",
    "sg:classifiers":[
        {
            "category":"Restaurant",
            "type":"Food & Drink"
        }
    ],
    "sg:phone":"+1 807 223 5224",
    "sg:postcode":"P8N 2W6",
    "sg:province":"ON",
    "wof:name":"Kfc",
    "wof:placetype":"venue"
},
  "geometry": {"coordinates":[-92.84749603269999,49.7890815735],"type":"Point"}
}