{
  "type": "Feature",
  "properties": {
    "addr:full":"2 Elm St #A Toronto ON M5G 1G7",
    "addr:housenumber":"2",
    "addr:postcode":"m5g 1g7",
    "addr:street":"Elm St # A",
    "iso:country":"CA",
    "sg:address":"2 Elm St #A",
    "sg:city":"Toronto",
    "sg:classifiers":[
        {
            "category":"Social Services",
            "type":"Services"
        }
    ],
    "sg:phone":"+1 416 598 2919",
    "sg:postcode":"M5G 1G7",
    "sg:province":"ON",
    "sg:tags":[
        "organization",
        "welfare"
    ],
    "wof:name":"Our Place Drop in Ctr",
    "wof:placetype":"venue"
},
  "geometry": {"coordinates":[-79.3817901611,43.6579780579],"type":"Point"}
}