{
  "type": "Feature",
  "properties": {
    "addr:full":"41 Rue D'Autray Saint-Felix-DE-Valois QC J0K 2M0",
    "addr:housenumber":"41",
    "addr:postcode":"j0k 2m0",
    "addr:street":"Rue D'Autray Saint-Felix-De-Valois",
    "iso:country":"CA",
    "sg:address":"41 Rue D'Autray",
    "sg:city":"Saint-Felix-DE-Valois",
    "sg:classifiers":[
        {
            "category":"Health Services",
            "subcategory":"Optometrist",
            "type":"Services"
        }
    ],
    "sg:phone":"+1 450 889 4444",
    "sg:postcode":"J0K 2M0",
    "sg:province":"QC",
    "wof:name":"Lapierre, Diane",
    "wof:placetype":"venue"
},
  "geometry": {"coordinates":[-73.43103000000001,46.156181],"type":"Point"}
}