{
  "type": "Feature",
  "properties": {
    "iso:country":"CA",
    "sg:address":"6350 204 St # 1",
    "sg:city":"Langley",
    "sg:classifiers":[
        {
            "category":"Wholesale",
            "subcategory":"Hardware",
            "type":"Manufacturing & Wholesale Goods"
        }
    ],
    "sg:phone":"+1 604 533 9445",
    "sg:postcode":"V2Y 2V1",
    "sg:province":"BC",
    "sg:tags":[
        "equipment",
        "used",
        "heating",
        "system"
    ],
    "wof:name":"Viessmann Manufacturing CO Inc",
    "wof:placetype":"venue"
},
  "geometry": {"coordinates":[-122.655212402,49.1176872253],"type":"Point"}
}