{
  "type": "Feature",
  "properties": {
    "addr:full":"4307 25 Ave Vernon BC V1T 1P5",
    "addr:housenumber":"4307",
    "addr:postcode":"v1t 1p5",
    "addr:street":"25 Ave",
    "iso:country":"CA",
    "sg:address":"4307 25 Ave",
    "sg:city":"Vernon",
    "sg:classifiers":[
        {
            "category":"Freight",
            "type":"Transportation"
        }
    ],
    "sg:phone":"+1 250 837 4288",
    "sg:postcode":"V1T 1P5",
    "sg:province":"BC",
    "sg:tags":[
        "trucking"
    ],
    "wof:name":"Van-Kam Freightways Ltd",
    "wof:placetype":"venue"
},
  "geometry": {"coordinates":[-119.297714,50.258839],"type":"Point"}
}