{
  "type": "Feature",
  "properties": {
    "addr:full":"2015 Main St Moncton NB E1E 1J2",
    "addr:housenumber":"2015",
    "addr:postcode":"e1e 1j2",
    "addr:street":"Main St",
    "iso:country":"CA",
    "sg:address":"2015 Main St",
    "sg:city":"Moncton",
    "sg:classifiers":[
        {
            "category":"Autos & Motor Vehicles",
            "subcategory":"Fuel & Gas Station",
            "type":"Retail Goods"
        }
    ],
    "sg:phone":"+1 506 858 0940",
    "sg:postcode":"E1E 1J2",
    "sg:province":"NB",
    "sg:tags":[
        "oil"
    ],
    "wof:name":"Lumac Service Ctr",
    "wof:placetype":"venue"
},
  "geometry": {"coordinates":[-64.8088150024,46.0750007629],"type":"Point"}
}