{
  "type": "Feature",
  "properties": {
    "iso:country":"CA",
    "sg:address":"7908 Rue Birnam",
    "sg:city":"Montreal",
    "sg:classifiers":[
        {
            "category":"Building & Trades",
            "subcategory":"Cleaning & Sanitation",
            "type":"Services"
        }
    ],
    "sg:phone":"+1 514 279 4957",
    "sg:postcode":"H3N 2T7",
    "sg:province":"QC",
    "sg:tags":[
        "janitor"
    ],
    "wof:name":"Nsm Maintenance Inc",
    "wof:placetype":"venue"
},
  "geometry": {"coordinates":[-73.634827,45.527317],"type":"Point"}
}