{
  "type": "Feature",
  "properties": {
    "addr:full":"169 Danforth Ave Toronto ON M4K 1N2",
    "addr:housenumber":"169",
    "addr:postcode":"m4k 1n2",
    "addr:street":"Danforth Ave",
    "iso:country":"CA",
    "sg:address":"169 Danforth Ave",
    "sg:city":"Toronto",
    "sg:classifiers":[
        {
            "category":"Real Estate",
            "subcategory":"Real Estate Agent",
            "type":"Services"
        }
    ],
    "sg:phone":"+1 416 465 7527",
    "sg:postcode":"M4K 1N2",
    "sg:province":"ON",
    "wof:name":"Bosley Real Estate Ltd",
    "wof:placetype":"venue"
},
  "geometry": {"coordinates":[-79.3561248779,43.6765899658],"type":"Point"}
}