{
  "type": "Feature",
  "properties": {
    "addr:full":"4384 Sheppard Ave E Scarborough ON M1S 1T8",
    "addr:housenumber":"4384",
    "addr:postcode":"m1s 1t8",
    "addr:street":"Sheppard Ave E",
    "iso:country":"CA",
    "sg:address":"4384 Sheppard Ave E",
    "sg:city":"Scarborough",
    "sg:classifiers":[
        {
            "category":"Autos & Motor Vehicles",
            "subcategory":"Automobile Sales",
            "type":"Retail Goods"
        }
    ],
    "sg:phone":"+1 416 412 3838",
    "sg:postcode":"M1S 1T8",
    "sg:province":"ON",
    "sg:tags":[
        "car",
        "dealer"
    ],
    "wof:name":"R & S Auto Sales",
    "wof:placetype":"venue"
},
  "geometry": {"coordinates":[-79.270065,43.78735],"type":"Point"}
}