{
  "type": "Feature",
  "properties": {
    "addr:full":"505 Gallerno St Port Lambton ON N0P 2B0",
    "addr:housenumber":"505",
    "addr:postcode":"n0p 2b0",
    "addr:street":"Gallerno St",
    "iso:country":"CA",
    "sg:address":"505 Gallerno St",
    "sg:city":"Port Lambton",
    "sg:classifiers":[
        {
            "category":"Wholesale",
            "subcategory":"Construction Materials",
            "type":"Manufacturing & Wholesale Goods"
        }
    ],
    "sg:phone":"+1 519 677 5935",
    "sg:postcode":"N0P 2B0",
    "sg:province":"ON",
    "sg:tags":[
        "sand",
        "gravel"
    ],
    "wof:name":"Gravel Doctor",
    "wof:placetype":"venue"
},
  "geometry": {"coordinates":[-82.50505099999999,42.664616],"type":"Point"}
}