{
  "type": "Feature",
  "properties": {
    "addr:full":"1074 Rue Vaudreuil Saint-Felicien QC G8K 2R3",
    "addr:housenumber":"1074",
    "addr:postcode":"g8k 2r3",
    "addr:street":"Rue Vaudreuil Saint-Felicien",
    "iso:country":"CA",
    "sg:address":"1074 Rue Vaudreuil",
    "sg:city":"Saint-Felicien",
    "sg:classifiers":[
        {
            "category":"Organizations",
            "subcategory":"Professional Association",
            "type":"Services"
        }
    ],
    "sg:phone":"+1 418 679 4312",
    "sg:postcode":"G8K 2R3",
    "sg:province":"QC",
    "wof:name":"Chevaliers DE Colomb",
    "wof:placetype":"venue"
},
  "geometry": {"coordinates":[-72.44692999999999,48.65007],"type":"Point"}
}