{
  "type": "Feature",
  "properties": {
    "addr:full":"484 Ch DE Price St-Jean-Baptiste QC G5H 3K6",
    "addr:housenumber":"484",
    "addr:postcode":"g5h 3k6",
    "addr:street":"Ch De Price St-Jean-Baptiste",
    "iso:country":"CA",
    "sg:address":"484 Ch DE Price",
    "sg:city":"St-Jean-Baptiste",
    "sg:classifiers":[
        {
            "category":"Building & Trades",
            "subcategory":"Plumbing",
            "type":"Services"
        }
    ],
    "sg:phone":"+1 418 775 2529",
    "sg:postcode":"G5H 3K6",
    "sg:province":"QC",
    "sg:tags":[
        "contractor"
    ],
    "wof:name":"Plomberie Charles-David Rioux",
    "wof:placetype":"venue"
},
  "geometry": {"coordinates":[-68.16250599999999,48.589825],"type":"Point"}
}