{
  "type": "Feature",
  "properties": {
    "addr:full":"406 Mcdiarmid Dr Brandon MB R7B 2H4",
    "addr:housenumber":"406",
    "addr:postcode":"r7b 2h4",
    "addr:street":"Mcdiarmid Dr",
    "iso:country":"CA",
    "sg:address":"406 Mcdiarmid Dr",
    "sg:city":"Brandon",
    "sg:classifiers":[
        {
            "category":"Professional",
            "subcategory":"Management & Consulting",
            "type":"Services"
        }
    ],
    "sg:phone":"+1 204 727 0124",
    "sg:postcode":"R7B 2H4",
    "sg:province":"MB",
    "sg:tags":[
        "building",
        "construction"
    ],
    "wof:name":"Ian Bobiak Project Mgmt Ltd",
    "wof:placetype":"venue"
},
  "geometry": {"coordinates":[-99.97616600000001,49.843754],"type":"Point"}
}