{
  "type": "Feature",
  "properties": {
    "addr:full":"11 Rue Saint-Germain O Rimouski QC G5L 4B4",
    "addr:housenumber":"11",
    "addr:postcode":"g5l 4b4",
    "addr:street":"Rue Saint-Germain O",
    "iso:country":"CA",
    "sg:address":"11 Rue Saint-Germain O",
    "sg:city":"Rimouski",
    "sg:classifiers":[
        {
            "category":"Organizations",
            "subcategory":"Religious Organization",
            "type":"Services"
        }
    ],
    "sg:phone":"+1 418 723 6539",
    "sg:postcode":"G5L 4B4",
    "sg:province":"QC",
    "sg:tags":[
        "church"
    ],
    "wof:name":"Presbytere Cathedrale DE",
    "wof:placetype":"venue"
},
  "geometry": {"coordinates":[-68.5271224976,48.4514045715],"type":"Point"}
}