{
  "type": "Feature",
  "properties": {
    "addr:full":"130 Newcastle Blvd Miramichi NB E1V 2L7",
    "addr:housenumber":"130",
    "addr:postcode":"e1v 2l7",
    "addr:street":"Newcastle Blvd",
    "iso:country":"CA",
    "sg:address":"130 Newcastle Blvd",
    "sg:city":"Miramichi",
    "sg:classifiers":[
        {
            "category":"Shopping",
            "subcategory":"Clothing, Apparel, & Fashions",
            "type":"Retail Goods"
        }
    ],
    "sg:phone":"+1 506 622 4557",
    "sg:postcode":"E1V 2L7",
    "sg:province":"NB",
    "sg:tags":[
        "furnishing"
    ],
    "wof:name":"Crockers Mens & Boys Wear Ltd",
    "wof:placetype":"venue"
},
  "geometry": {"coordinates":[-65.564651,47.001511],"type":"Point"}
}