{
  "type": "Feature",
  "properties": {
    "addr:full":"Komoka ON N0L 1R0",
    "addr:postcode":"n0l 1r0",
    "iso:country":"CA",
    "sg:city":"Komoka",
    "sg:classifiers":[
        {
            "category":"Social Services",
            "type":"Services"
        }
    ],
    "sg:phone":"+1 519 657 6775",
    "sg:postcode":"N0L 1R0",
    "sg:province":"ON",
    "sg:tags":[
        "mission"
    ],
    "wof:name":"Send International of Canada",
    "wof:placetype":"venue"
},
  "geometry": {"coordinates":[-81.408241,42.958961],"type":"Point"}
}