{
  "type": "Feature",
  "properties": {
    "addr:full":"5th Ave Arborfield SK S0E 0A0",
    "addr:postcode":"s0e 0a0",
    "addr:street":"5Th Ave",
    "iso:country":"CA",
    "sg:address":"5th Ave",
    "sg:city":"Arborfield",
    "sg:classifiers":[
        {
            "category":"Health Services",
            "subcategory":"Doctor",
            "type":"Services"
        }
    ],
    "sg:phone":"+1 306 769 8757",
    "sg:postcode":"S0E 0A0",
    "sg:province":"SK",
    "sg:tags":[
        "clinic"
    ],
    "wof:name":"Arborfield & District Health",
    "wof:placetype":"venue"
},
  "geometry": {"coordinates":[-103.66078949,53.1037483215],"type":"Point"}
}