{
  "type": "Feature",
  "properties": {
    "addr:full":"550 Gardiners Rd Kingston ON K7M 3X9",
    "addr:housenumber":"550",
    "addr:postcode":"k7m 3x9",
    "addr:street":"Gardiners Rd",
    "iso:country":"CA",
    "sg:address":"550 Gardiners Rd",
    "sg:city":"Kingston",
    "sg:classifiers":[
        {
            "category":"Manufacturing",
            "subcategory":"Glass & Minerals",
            "type":"Manufacturing & Wholesale Goods"
        }
    ],
    "sg:phone":"+1 613 389 4566",
    "sg:postcode":"K7M 3X9",
    "sg:province":"ON",
    "sg:tags":[
        "concrete",
        "brick",
        "block"
    ],
    "wof:name":"Patterson Concrete Prods Ltd",
    "wof:placetype":"venue"
},
  "geometry": {"coordinates":[-76.567459,44.239708],"type":"Point"}
}