{
  "type": "Feature",
  "properties": {
    "addr:full":"32 Railway Ave Pierson MB R0M 1S0",
    "addr:housenumber":"32",
    "addr:postcode":"r0m 1s0",
    "addr:street":"Railway Ave",
    "iso:country":"CA",
    "sg:address":"32 Railway Ave",
    "sg:city":"Pierson",
    "sg:classifiers":[
        {
            "category":"Retail",
            "subcategory":"Auto Repair",
            "type":"Services"
        }
    ],
    "sg:phone":"+1 204 634 2350",
    "sg:postcode":"R0M 1S0",
    "sg:province":"MB",
    "sg:tags":[
        "repairing",
        "automobile"
    ],
    "wof:name":"Nicholls Farm Equipment",
    "wof:placetype":"venue"
},
  "geometry": {"coordinates":[-101.267303467,49.1780433655],"type":"Point"}
}