{
  "type": "Feature",
  "properties": {
    "addr:full":"795 Ryan Rd #K Courtenay BC V9N 3R6",
    "addr:housenumber":"795",
    "addr:postcode":"v9n 3r6",
    "addr:street":"Ryan Rd # K",
    "iso:country":"CA",
    "sg:address":"795 Ryan Rd #K",
    "sg:city":"Courtenay",
    "sg:classifiers":[
        {
            "category":"Insurance",
            "subcategory":"Insurance Agent",
            "type":"Services"
        }
    ],
    "sg:phone":"+1 250 334 3443",
    "sg:postcode":"V9N 3R6",
    "sg:province":"BC",
    "wof:name":"Coast Country Insurance Svc",
    "wof:placetype":"venue"
},
  "geometry": {"coordinates":[-124.98732800000001,49.698708],"type":"Point"}
}