{
  "type": "Feature",
  "properties": {
    "iso:country":"CA",
    "sg:address":"39 Rue Lavigne",
    "sg:city":"Repentigny",
    "sg:classifiers":[
        {
            "category":"Wholesale",
            "subcategory":"Hardware",
            "type":"Manufacturing & Wholesale Goods"
        }
    ],
    "sg:phone":"+1 450 582 8839",
    "sg:postcode":"J6A 6B4",
    "sg:province":"QC",
    "sg:tags":[
        "plumbing",
        "fixture",
        "supply"
    ],
    "wof:name":"Dra Marketing Inc",
    "wof:placetype":"venue"
},
  "geometry": {"coordinates":[-73.470085,45.740768],"type":"Point"}
}