{
  "type": "Feature",
  "properties": {
    "addr:full":"17 Rue Lacroix Carleton QC G0C 1J0",
    "addr:housenumber":"17",
    "addr:postcode":"g0c 1j0",
    "addr:street":"Rue Lacroix",
    "iso:country":"CA",
    "sg:address":"17 Rue Lacroix",
    "sg:city":"Carleton",
    "sg:classifiers":[
        {
            "category":"Government",
            "subcategory":"Office",
            "type":"Public Place"
        }
    ],
    "sg:phone":"+1 418 364 7956",
    "sg:postcode":"G0C 1J0",
    "sg:province":"QC",
    "wof:name":"Quebec Substitut Du Procureur",
    "wof:placetype":"venue"
},
  "geometry": {"coordinates":[-66.125038147,48.105052948],"type":"Point"}
}