{
  "type": "Feature",
  "properties": {
    "addr:full":"581 Coronation Blvd Cambridge ON N1R 3E9",
    "addr:housenumber":"581",
    "addr:postcode":"n1r 3e9",
    "addr:street":"Coronation Blvd",
    "iso:country":"CA",
    "sg:address":"581 Coronation Blvd",
    "sg:city":"Cambridge",
    "sg:classifiers":[
        {
            "category":"Wholesale",
            "subcategory":"Hardware",
            "type":"Manufacturing & Wholesale Goods"
        }
    ],
    "sg:phone":"+1 519 621 2130",
    "sg:postcode":"N1R 3E9",
    "sg:province":"ON",
    "sg:tags":[
        "school",
        "used"
    ],
    "wof:name":"Babcock & Wilcox Canada",
    "wof:placetype":"venue"
},
  "geometry": {"coordinates":[-80.322136,43.375698],"type":"Point"}
}