{
  "type": "Feature",
  "properties": {
    "addr:full":"8468 Adams Crt Grand Bend ON N0M 1T0",
    "addr:housenumber":"8468",
    "addr:postcode":"n0m 1t0",
    "addr:street":"Adams Crt",
    "iso:country":"CA",
    "sg:address":"8468 Adams Crt",
    "sg:city":"Grand Bend",
    "sg:classifiers":[
        {
            "category":"Professional",
            "subcategory":"Computer Services",
            "type":"Services"
        }
    ],
    "sg:phone":"+1 519 243 2295",
    "sg:postcode":"N0M 1T0",
    "sg:province":"ON",
    "sg:tags":[
        "internet"
    ],
    "wof:name":"Rainbow Bridge",
    "wof:placetype":"venue"
},
  "geometry": {"coordinates":[-81.8315734863,43.2069625854],"type":"Point"}
}