{
  "type": "Feature",
  "properties": {
    "iso:country":"CA",
    "sg:address":"2938 Danforth Ave",
    "sg:city":"East York",
    "sg:classifiers":[
        {
            "category":"Professional",
            "subcategory":"Lawyer & Legal Services",
            "type":"Services"
        }
    ],
    "sg:phone":"+1 416 699 1131",
    "sg:postcode":"M4C 1M5",
    "sg:province":"ON",
    "sg:tags":[
        "attorney"
    ],
    "wof:name":"Reid Mc Lean Scott",
    "wof:placetype":"venue"
},
  "geometry": {"coordinates":[-79.2930221558,43.6902732849],"type":"Point"}
}