{
  "type": "Feature",
  "properties": {
    "addr:full":"197 Browning Blvd Winnipeg MB R3K 0L1",
    "addr:housenumber":"197",
    "addr:postcode":"r3k 0l1",
    "addr:street":"Browning Blvd",
    "iso:country":"CA",
    "sg:address":"197 Browning Blvd",
    "sg:city":"Winnipeg",
    "sg:classifiers":[
        {
            "category":"Organizations",
            "subcategory":"Religious Organization",
            "type":"Services"
        }
    ],
    "sg:phone":"+1 204 837 5706",
    "sg:postcode":"R3K 0L1",
    "sg:province":"MB",
    "sg:tags":[
        "church"
    ],
    "wof:name":"Westwood Presbyterian Church",
    "wof:placetype":"venue"
},
  "geometry": {"coordinates":[-97.29382324220001,49.8720664978],"type":"Point"}
}