{
  "type": "Feature",
  "properties": {
    "iso:country":"CA",
    "sg:address":"PO Box 1137",
    "sg:city":"Blackfalds",
    "sg:classifiers":[
        {
            "category":"Building & Trades",
            "subcategory":"Construction",
            "type":"Services"
        }
    ],
    "sg:phone":"+1 403 885 5999",
    "sg:postcode":"T0M 0J0",
    "sg:province":"AB",
    "sg:tags":[
        "carpenter"
    ],
    "wof:name":"D Tarr Construction Inc",
    "wof:placetype":"venue"
},
  "geometry": {"coordinates":[-113.79022979699999,52.3801498413],"type":"Point"}
}