{
  "type": "Feature",
  "properties": {
    "addr:full":"Woodbridge ON L4L 8K5",
    "addr:postcode":"l4l 8k5",
    "iso:country":"CA",
    "sg:city":"Woodbridge",
    "sg:classifiers":[
        {
            "category":"Arts & Performance",
            "subcategory":"Theater",
            "type":"Entertainment"
        }
    ],
    "sg:phone":"+1 905 850 8870",
    "sg:postcode":"L4L 8K5",
    "sg:province":"ON",
    "sg:tags":[
        "live",
        "music"
    ],
    "wof:name":"Twilight Disc Jockey Svc",
    "wof:placetype":"venue"
},
  "geometry": {"coordinates":[-79.60424041749999,43.7741699219],"type":"Point"}
}