{
  "type": "Feature",
  "properties": {
    "addr:full":"5 Maple St Craven SK S0G 0W0",
    "addr:housenumber":"5",
    "addr:postcode":"s0g 0w0",
    "addr:street":"Maple St",
    "iso:country":"CA",
    "sg:address":"5 Maple St",
    "sg:city":"Craven",
    "sg:classifiers":[
        {
            "category":"Social Services",
            "type":"Services"
        }
    ],
    "sg:phone":"+1 306 731 3819",
    "sg:postcode":"S0G 0W0",
    "sg:province":"SK",
    "sg:tags":[
        "organization",
        "welfare"
    ],
    "wof:name":"Socio-Tech Consulting Svc",
    "wof:placetype":"venue"
},
  "geometry": {"coordinates":[-104.808792,50.707989],"type":"Point"}
}