{
  "type": "Feature",
  "properties": {
    "addr:full":"1130 Riverside Rd Sicamous BC V0E 2V0",
    "addr:housenumber":"1130",
    "addr:postcode":"v0e 2v0",
    "addr:street":"Riverside Rd",
    "iso:country":"CA",
    "sg:address":"1130 Riverside Rd",
    "sg:city":"Sicamous",
    "sg:classifiers":[
        {
            "category":"Recreation",
            "type":"Entertainment"
        }
    ],
    "sg:phone":"+1 250 836 3399",
    "sg:postcode":"V0E 2V0",
    "sg:province":"BC",
    "sg:tags":[
        "center",
        "boat"
    ],
    "wof:name":"Portside Houseboat Rentals",
    "wof:placetype":"venue"
},
  "geometry": {"coordinates":[-118.98896000000001,50.831844],"type":"Point"}
}