{
  "type": "Feature",
  "properties": {
    "addr:full":"454 Whitney Ave Sydney NS B1P 5A7",
    "addr:housenumber":"454",
    "addr:postcode":"b1p 5a7",
    "addr:street":"Whitney Ave",
    "iso:country":"CA",
    "sg:address":"454 Whitney Ave",
    "sg:city":"Sydney",
    "sg:classifiers":[
        {
            "category":"Real Estate",
            "subcategory":"Real Estate Operator",
            "type":"Services"
        }
    ],
    "sg:phone":"+1 902 567 0646",
    "sg:postcode":"B1P 5A7",
    "sg:province":"NS",
    "sg:tags":[
        "apartment"
    ],
    "wof:name":"Lyn Way Investments",
    "wof:placetype":"venue"
},
  "geometry": {"coordinates":[-60.175567627,46.1409835815],"type":"Point"}
}