{
  "type": "Feature",
  "properties": {
    "addr:full":"281 Pefferlaw Rd Pefferlaw ON L0E 1N0",
    "addr:housenumber":"281",
    "addr:postcode":"l0e 1n0",
    "addr:street":"Pefferlaw Rd",
    "iso:country":"CA",
    "sg:address":"281 Pefferlaw Rd",
    "sg:city":"Pefferlaw",
    "sg:classifiers":[
        {
            "category":"Food & Beverages",
            "subcategory":"Groceries & Convenience Stores",
            "type":"Retail Goods"
        }
    ],
    "sg:phone":"+1 705 437 1886",
    "sg:postcode":"L0E 1N0",
    "sg:province":"ON",
    "sg:tags":[
        "grocer"
    ],
    "wof:name":"Lim's Grocery",
    "wof:placetype":"venue"
},
  "geometry": {"coordinates":[-79.202354,44.314426],"type":"Point"}
}