{
  "type": "Feature",
  "properties": {
    "addr:full":"2467 Reece Rd Westbank BC V4T 1N2",
    "addr:housenumber":"2467",
    "addr:postcode":"v4t 1n2",
    "addr:street":"Reece Rd",
    "iso:country":"CA",
    "sg:address":"2467 Reece Rd",
    "sg:city":"Westbank",
    "sg:classifiers":[
        {
            "category":"Shopping",
            "subcategory":"Computers & Home Electronics",
            "type":"Retail Goods"
        }
    ],
    "sg:phone":"+1 250 768 3977",
    "sg:postcode":"V4T 1N2",
    "sg:province":"BC",
    "sg:tags":[
        "publishing"
    ],
    "wof:name":"Janice Harvey & Assoc",
    "wof:placetype":"venue"
},
  "geometry": {"coordinates":[-119.62966919,49.8439102173],"type":"Point"}
}