{
  "type": "Feature",
  "properties": {
    "addr:full":"Mississauga ON L4W 4K4",
    "addr:postcode":"l4w 4k4",
    "iso:country":"CA",
    "sg:city":"Mississauga",
    "sg:classifiers":[
        {
            "category":"Manufacturing",
            "subcategory":"Tools & Machinery",
            "type":"Manufacturing & Wholesale Goods"
        }
    ],
    "sg:phone":"+1 905 238 0796",
    "sg:postcode":"L4W 4K4",
    "sg:province":"ON",
    "sg:tags":[
        "equipment",
        "system",
        "automation"
    ],
    "wof:name":"Willtech Industries Inc",
    "wof:placetype":"venue"
},
  "geometry": {"coordinates":[-79.61158752439999,43.6391181946],"type":"Point"}
}