{
  "type": "Feature",
  "properties": {
    "addr:full":"765 Ch Des Patriotes Saint-Denis-Sur-Richelieu QC J0H 1K0",
    "addr:housenumber":"765",
    "addr:postcode":"j0h 1k0",
    "addr:street":"Ch Des Patriotes",
    "iso:country":"CA",
    "sg:address":"765 Ch Des Patriotes",
    "sg:city":"Saint-Denis-Sur-Richelieu",
    "sg:classifiers":[
        {
            "category":"Retail",
            "subcategory":"Repair Shop",
            "type":"Services"
        }
    ],
    "sg:phone":"+1 450 787 3832",
    "sg:postcode":"J0H 1K0",
    "sg:province":"QC",
    "sg:tags":[
        "refinishing",
        "furniture"
    ],
    "wof:name":"Atelier 1837 Enr",
    "wof:placetype":"venue"
},
  "geometry": {"coordinates":[-73.167717,45.774288],"type":"Point"}
}