{
  "type": "Feature",
  "properties": {
    "addr:full":"1618 Ketch Harbour Rd Sambro NS B3V 1L4",
    "addr:housenumber":"1618",
    "addr:postcode":"b3v 1l4",
    "addr:street":"Ketch Harbour Rd",
    "iso:country":"CA",
    "sg:address":"1618 Ketch Harbour Rd",
    "sg:city":"Sambro",
    "sg:classifiers":[
        {
            "category":"Restaurant",
            "type":"Food & Drink"
        }
    ],
    "sg:phone":"+1 902 868 2453",
    "sg:postcode":"B3V 1L4",
    "sg:province":"NS",
    "sg:tags":[
        "banquet",
        "rooms"
    ],
    "wof:name":"Silver Seas Social Club",
    "wof:placetype":"venue"
},
  "geometry": {"coordinates":[-63.603863,44.475025],"type":"Point"}
}