{
  "type": "Feature",
  "properties": {
    "addr:full":"1431 Victoria Ave Regina SK S4P 0P4",
    "addr:housenumber":"1431",
    "addr:postcode":"s4p 0p4",
    "addr:street":"Victoria Ave",
    "iso:country":"CA",
    "sg:address":"1431 Victoria Ave",
    "sg:city":"Regina",
    "sg:classifiers":[
        {
            "category":"Social Services",
            "type":"Services"
        }
    ],
    "sg:phone":"+1 306 522 0902",
    "sg:postcode":"S4P 0P4",
    "sg:province":"SK",
    "sg:tags":[
        "information",
        "planning",
        "center",
        "family"
    ],
    "wof:name":"Planned Parenthood Regina",
    "wof:placetype":"venue"
},
  "geometry": {"coordinates":[-104.601104736,50.4469795227],"type":"Point"}
}