{
  "type": "Feature",
  "properties": {
    "addr:full":"410 Colborne St Brantford ON N3S 3N6",
    "addr:housenumber":"410",
    "addr:postcode":"n3s 3n6",
    "addr:street":"Colborne St",
    "iso:country":"CA",
    "sg:address":"410 Colborne St",
    "sg:city":"Brantford",
    "sg:classifiers":[
        {
            "category":"Organizations",
            "subcategory":"Religious Organization",
            "type":"Services"
        }
    ],
    "sg:phone":"+1 519 753 1602",
    "sg:postcode":"N3S 3N6",
    "sg:province":"ON",
    "sg:tags":[
        "church"
    ],
    "wof:name":"Alexandra Presbyterian Church",
    "wof:placetype":"venue"
},
  "geometry": {"coordinates":[-80.254654,43.139263],"type":"Point"}
}