{
  "type": "Feature",
  "properties": {
    "addr:full":"654 King Edward St Winnipeg MB R3H 0P2",
    "addr:housenumber":"654",
    "addr:postcode":"r3h 0p2",
    "addr:street":"King Edward St",
    "iso:country":"CA",
    "sg:address":"654 King Edward St",
    "sg:city":"Winnipeg",
    "sg:classifiers":[
        {
            "category":"Recreation",
            "subcategory":"Amusement Park",
            "type":"Entertainment"
        }
    ],
    "sg:phone":"+1 204 779 1702",
    "sg:postcode":"R3H 0P2",
    "sg:province":"MB",
    "wof:name":"Wolf Billiard Table Mfg Inc",
    "wof:placetype":"venue"
},
  "geometry": {"coordinates":[-97.20774841310001,49.8964004517],"type":"Point"}
}