{
  "type": "Feature",
  "properties": {
    "addr:full":"15 Main St Falher AB T0H 1M0",
    "addr:housenumber":"15",
    "addr:postcode":"t0h 1m0",
    "addr:street":"Main St",
    "iso:country":"CA",
    "sg:address":"15 Main St",
    "sg:city":"Falher",
    "sg:classifiers":[
        {
            "category":"Banks & Credit Unions",
            "subcategory":"Bank",
            "type":"Services"
        }
    ],
    "sg:phone":"+1 780 837 2215",
    "sg:postcode":"T0H 1M0",
    "sg:province":"AB",
    "wof:name":"Bank of Montreal",
    "wof:placetype":"venue"
},
  "geometry": {"coordinates":[-117.201896667,55.7411308289],"type":"Point"}
}