{
  "type": "Feature",
  "properties": {
    "iso:country":"CA",
    "sg:address":"55 Miller Cres",
    "sg:city":"Simcoe",
    "sg:classifiers":[
        {
            "category":"Building & Trades",
            "subcategory":"Plumbing",
            "type":"Services"
        }
    ],
    "sg:phone":"+1 519 428 5614",
    "sg:postcode":"N3Y 4P9",
    "sg:province":"ON",
    "sg:tags":[
        "air",
        "conditioning",
        "contractor",
        "system",
        "heating"
    ],
    "wof:name":"Simcoe Heating & Air Cond",
    "wof:placetype":"venue"
},
  "geometry": {"coordinates":[-80.3128356934,42.8251495361],"type":"Point"}
}