{
  "type": "Feature",
  "properties": {
    "addr:full":"27 Notre Dame O Lorrainville QC J0Z 2R0",
    "addr:housenumber":"27",
    "addr:postcode":"j0z 2r0",
    "addr:street":"Notre Dame O",
    "iso:country":"CA",
    "sg:address":"27 Notre Dame O",
    "sg:city":"Lorrainville",
    "sg:classifiers":[
        {
            "category":"Organizations",
            "subcategory":"Religious Organization",
            "type":"Services"
        }
    ],
    "sg:phone":"+1 819 625 2392",
    "sg:postcode":"J0Z 2R0",
    "sg:province":"QC",
    "sg:tags":[
        "church"
    ],
    "wof:name":"Eglise Evangelique Du Temis",
    "wof:placetype":"venue"
},
  "geometry": {"coordinates":[-79.351433,47.354012],"type":"Point"}
}