{
  "type": "Feature",
  "properties": {
    "iso:country":"CA",
    "sg:address":"32 Shaw St S",
    "sg:city":"Herbert",
    "sg:classifiers":[
        {
            "category":"Local Transit",
            "type":"Transportation"
        }
    ],
    "sg:phone":"+1 306 784 2233",
    "sg:postcode":"S0H 2A0",
    "sg:province":"SK",
    "sg:tags":[
        "bus",
        "line",
        "courier"
    ],
    "wof:name":"Greyhound Canada",
    "wof:placetype":"venue"
},
  "geometry": {"coordinates":[-107.21916198700001,50.4309844971],"type":"Point"}
}