{
  "type": "Feature",
  "properties": {
    "iso:country":"CA",
    "sg:address":"PO Box 90",
    "sg:city":"English Harbour East",
    "sg:classifiers":[
        {
            "category":"Education",
            "subcategory":"School",
            "type":"Public Place"
        }
    ],
    "sg:phone":"+1 709 245 4381",
    "sg:postcode":"A0E 1M0",
    "sg:province":"NL",
    "wof:name":"St George's School",
    "wof:placetype":"venue"
},
  "geometry": {"coordinates":[-54.891998291,47.6429824829],"type":"Point"}
}