{
  "type": "Feature",
  "properties": {
    "addr:full":"Humboldt SK S0K 2A0",
    "addr:postcode":"s0k 2a0",
    "addr:street":"Humboldt",
    "iso:country":"CA",
    "sg:city":"Humboldt",
    "sg:classifiers":[
        {
            "category":"Manufacturing",
            "subcategory":"Metals",
            "type":"Manufacturing & Wholesale Goods"
        }
    ],
    "sg:phone":"+1 306 682 5573",
    "sg:postcode":"S0K 2A0",
    "sg:province":"SK",
    "sg:tags":[
        "steel"
    ],
    "wof:name":"Standard Construction Inc",
    "wof:placetype":"venue"
},
  "geometry": {"coordinates":[-105.12146799999999,52.2019],"type":"Point"}
}