{
  "type": "Feature",
  "properties": {
    "addr:full":"6724 Golden West Ave Red Deer AB T4P 1A8",
    "addr:housenumber":"6724",
    "addr:postcode":"t4p 1a8",
    "addr:street":"Golden West Ave",
    "iso:country":"CA",
    "sg:address":"6724 Golden West Ave",
    "sg:city":"Red Deer",
    "sg:classifiers":[
        {
            "category":"Manufacturing",
            "subcategory":"Metals",
            "type":"Manufacturing & Wholesale Goods"
        }
    ],
    "sg:phone":"+1 403 346 2096",
    "sg:postcode":"T4P 1A8",
    "sg:province":"AB",
    "sg:tags":[
        "steel"
    ],
    "wof:name":"Russel Metals Inc",
    "wof:placetype":"venue"
},
  "geometry": {"coordinates":[-113.846832275,52.2909965515],"type":"Point"}
}