{
  "type": "Feature",
  "properties": {
    "addr:full":"Williams Lake BC V2G 3W3",
    "addr:postcode":"bc v2g 3w3",
    "iso:country":"CA",
    "sg:city":"Williams Lake",
    "sg:classifiers":[
        {
            "category":"Personal",
            "subcategory":"Beauty Salon",
            "type":"Services"
        }
    ],
    "sg:phone":"+1 250 398 7663",
    "sg:postcode":"V2G 3W3",
    "sg:province":"BC",
    "wof:name":"First Choice Haircutters",
    "wof:placetype":"venue"
},
  "geometry": {"coordinates":[-122.144058,52.127815],"type":"Point"}
}