{
  "type": "Feature",
  "properties": {
    "addr:full":"201 Boul Rene-Levesque O Quebec QC G1R 2A7",
    "addr:housenumber":"201",
    "addr:postcode":"g1r 2a7",
    "addr:street":"Boul Rene-Levesque O",
    "iso:country":"CA",
    "sg:address":"201 Boul Rene-Levesque O",
    "sg:city":"Quebec",
    "sg:classifiers":[
        {
            "category":"Personal",
            "subcategory":"Beauty Salon",
            "type":"Services"
        }
    ],
    "sg:phone":"+1 418 569 6733",
    "sg:postcode":"G1R 2A7",
    "sg:province":"QC",
    "wof:name":"Clinique D'Electrolyse Paramed",
    "wof:placetype":"venue"
},
  "geometry": {"coordinates":[-71.2229003906,46.8062019348],"type":"Point"}
}