{
  "type": "Feature",
  "properties": {
    "addr:full":"1312 Mclorg St Saskatoon SK S7J 0N4",
    "addr:housenumber":"1312",
    "addr:postcode":"s7j 0n4",
    "addr:street":"Mclorg St",
    "iso:country":"CA",
    "sg:address":"1312 Mclorg St",
    "sg:city":"Saskatoon",
    "sg:classifiers":[
        {
            "category":"Retail",
            "subcategory":"Laundry & Dry Cleaning",
            "type":"Services"
        }
    ],
    "sg:phone":"+1 306 955 5967",
    "sg:postcode":"S7J 0N4",
    "sg:province":"SK",
    "sg:tags":[
        "cleaners",
        "rug",
        "carpet"
    ],
    "wof:name":"Dave's Professional Carpet",
    "wof:placetype":"venue"
},
  "geometry": {"coordinates":[-106.637688,52.096397],"type":"Point"}
}