{
  "type": "Feature",
  "properties": {
    "addr:full":"1230 Boul Mercure Drummondville QC J2B 3L9",
    "addr:housenumber":"1230",
    "addr:postcode":"j2b 3l9",
    "addr:street":"Boul Mercure",
    "iso:country":"CA",
    "sg:address":"1230 Boul Mercure",
    "sg:city":"Drummondville",
    "sg:classifiers":[
        {
            "category":"Personal",
            "subcategory":"Beauty Salon",
            "type":"Services"
        }
    ],
    "sg:phone":"+1 819 477 1833",
    "sg:postcode":"J2B 3L9",
    "sg:province":"QC",
    "wof:name":"Institut DE Beaute Nicole Inc",
    "wof:placetype":"venue"
},
  "geometry": {"coordinates":[-72.472008,45.866158],"type":"Point"}
}