{
  "type": "Feature",
  "properties": {
    "iso:country":"CA",
    "sg:address":"204 Boul Saint-Joseph",
    "sg:city":"Hull",
    "sg:classifiers":[
        {
            "category":"Restaurant",
            "type":"Food & Drink"
        }
    ],
    "sg:phone":"+1 819 778 1228",
    "sg:postcode":"J8Y 3W9",
    "sg:province":"QC",
    "wof:name":"Patate Frite Chez Rejean",
    "wof:placetype":"venue"
},
  "geometry": {"coordinates":[-75.73295593260001,45.4342002869],"type":"Point"}
}