{
  "type": "Feature",
  "properties": {
    "addr:full":"20 Crown Steel Dr Markham ON L3R 9X9",
    "addr:housenumber":"20",
    "addr:postcode":"l3r 9x9",
    "addr:street":"Crown Steel Dr",
    "iso:country":"CA",
    "sg:address":"20 Crown Steel Dr",
    "sg:city":"Markham",
    "sg:classifiers":[
        {
            "category":"Building & Trades",
            "subcategory":"Landscaping Services",
            "type":"Services"
        }
    ],
    "sg:phone":"+1 905 940 4443",
    "sg:postcode":"L3R 9X9",
    "sg:province":"ON",
    "sg:tags":[
        "designer",
        "landscape"
    ],
    "wof:name":"Paul Cosburn Assoc Ltd",
    "wof:placetype":"venue"
},
  "geometry": {"coordinates":[-79.325378418,43.8393135071],"type":"Point"}
}