{
  "type": "Feature",
  "properties": {
    "iso:country":"CA",
    "sg:address":"8285 Av Mountain Sights",
    "sg:city":"Montreal",
    "sg:classifiers":[
        {
            "category":"Building & Trades",
            "subcategory":"Plumbing",
            "type":"Services"
        }
    ],
    "sg:phone":"+1 514 342 2835",
    "sg:postcode":"H4P 2B3",
    "sg:province":"QC",
    "sg:tags":[
        "conditioning",
        "air",
        "system",
        "contractor"
    ],
    "wof:name":"Climatisation Morrison Inc",
    "wof:placetype":"venue"
},
  "geometry": {"coordinates":[-73.658005,45.500858],"type":"Point"}
}