{
  "type": "Feature",
  "properties": {
    "iso:country":"CA",
    "sg:address":"1030 Eighth Line",
    "sg:city":"Oakville",
    "sg:classifiers":[
        {
            "category":"Autos & Motor Vehicles",
            "subcategory":"Recreational Vehicle Sales",
            "type":"Retail Goods"
        }
    ],
    "sg:phone":"+1 905 845 7558",
    "sg:postcode":"L6H 2H1",
    "sg:province":"ON",
    "wof:name":"G L Products",
    "wof:placetype":"venue"
},
  "geometry": {"coordinates":[-79.678527832,43.4681968689],"type":"Point"}
}