{
  "type": "Feature",
  "properties": {
    "iso:country":"CA",
    "sg:address":"2126 Westmount Dr",
    "sg:city":"Oakville",
    "sg:classifiers":[
        {
            "category":"Freight",
            "type":"Transportation"
        }
    ],
    "sg:phone":"+1 905 257 6683",
    "sg:postcode":"L6M 3N8",
    "sg:province":"ON",
    "sg:tags":[
        "mover"
    ],
    "wof:name":"Saturn Movers Ltd",
    "wof:placetype":"venue"
},
  "geometry": {"coordinates":[-79.7507095337,43.4356384277],"type":"Point"}
}