{
  "type": "Feature",
  "properties": {
    "addr:full":"328 19th St E Prince Albert SK S6V 1J7",
    "addr:housenumber":"328",
    "addr:postcode":"s6v 1j7",
    "addr:street":"19Th St",
    "iso:country":"CA",
    "sg:address":"328 19th St E",
    "sg:city":"Prince Albert",
    "sg:classifiers":[
        {
            "category":"Organizations",
            "subcategory":"Non-profit Organization",
            "type":"Services"
        }
    ],
    "sg:phone":"+1 306 922 7713",
    "sg:postcode":"S6V 1J7",
    "sg:province":"SK",
    "sg:tags":[
        "information",
        "welfare",
        "treatment",
        "alcoholism",
        "social"
    ],
    "wof:name":"Metis Addictions Council Inc",
    "wof:placetype":"venue"
},
  "geometry": {"coordinates":[-105.746307,53.195976],"type":"Point"}
}