{
  "type": "Feature",
  "properties": {
    "addr:full":"510 Finley Ave Ajax ON L1S 2E3",
    "addr:housenumber":"510",
    "addr:postcode":"l1s 2e3",
    "addr:street":"Finley Ave",
    "iso:country":"CA",
    "sg:address":"510 Finley Ave",
    "sg:city":"Ajax",
    "sg:classifiers":[
        {
            "category":"Manufacturing",
            "subcategory":"Paper Products",
            "type":"Manufacturing & Wholesale Goods"
        }
    ],
    "sg:phone":"+1 905 426 4989",
    "sg:postcode":"L1S 2E3",
    "sg:province":"ON",
    "sg:tags":[
        "bag"
    ],
    "wof:name":"Malpack Limited",
    "wof:placetype":"venue"
},
  "geometry": {"coordinates":[-79.028656,43.836098],"type":"Point"}
}