{
  "type": "Feature",
  "properties": {
    "addr:full":"3501 11th St W Saskatoon SK S7M 1K6",
    "addr:housenumber":"3501",
    "addr:postcode":"s7m 1k6",
    "addr:street":"11Th St W",
    "iso:country":"CA",
    "sg:address":"3501 11th St W",
    "sg:city":"Saskatoon",
    "sg:classifiers":[
        {
            "category":"Food & Beverages",
            "subcategory":"Groceries & Convenience Stores",
            "type":"Retail Goods"
        }
    ],
    "sg:phone":"+1 306 978 7990",
    "sg:postcode":"S7M 1K6",
    "sg:province":"SK",
    "sg:tags":[
        "grocer"
    ],
    "wof:name":"Greg's Grocery Plus",
    "wof:placetype":"venue"
},
  "geometry": {"coordinates":[-106.741821,52.114632],"type":"Point"}
}