{
  "type": "Feature",
  "properties": {
    "addr:full":"498 Eagle St N Cambridge ON N3H 1C2",
    "addr:housenumber":"498",
    "addr:postcode":"n3h 1c2",
    "addr:street":"Eagle St N",
    "iso:country":"CA",
    "sg:address":"498 Eagle St N",
    "sg:city":"Cambridge",
    "sg:classifiers":[
        {
            "category":"Manufacturing",
            "subcategory":"Chemicals & Compounds",
            "type":"Manufacturing & Wholesale Goods"
        }
    ],
    "sg:phone":"+1 519 653 5031",
    "sg:postcode":"N3H 1C2",
    "sg:province":"ON",
    "sg:tags":[
        "plastic"
    ],
    "wof:name":"Aclo Compounders Inc",
    "wof:placetype":"venue"
},
  "geometry": {"coordinates":[-80.3568649292,43.4032363892],"type":"Point"}
}