{
  "type": "Feature",
  "properties": {
    "addr:full":"North York ON M2N 6L7",
    "addr:postcode":"m2n 6l7",
    "iso:country":"CA",
    "sg:city":"North York",
    "sg:classifiers":[
        {
            "category":"Banks & Credit Unions",
            "subcategory":"Investment Brokerage",
            "type":"Services"
        }
    ],
    "sg:phone":"+1 416 590 7600",
    "sg:postcode":"M2N 6L7",
    "sg:province":"ON",
    "wof:name":"Bmo Nesbitt Burns Inc",
    "wof:placetype":"venue"
},
  "geometry": {"coordinates":[-79.41297149659999,43.7687797546],"type":"Point"}
}