{
  "type": "Feature",
  "properties": {
    "addr:full":"1400 Kent St SE High River AB T1V 1R9",
    "addr:housenumber":"1400",
    "addr:postcode":"t1v 1r9",
    "addr:street":"Kent St Se",
    "iso:country":"CA",
    "sg:address":"1400 Kent St SE",
    "sg:city":"High River",
    "sg:classifiers":[
        {
            "category":"Professional",
            "type":"Services"
        }
    ],
    "sg:phone":"+1 403 652 8504",
    "sg:postcode":"T1V 1R9",
    "sg:province":"AB",
    "sg:tags":[
        "establishment"
    ],
    "wof:name":"Alcatel Inc",
    "wof:placetype":"venue"
},
  "geometry": {"coordinates":[-113.859123,50.577999],"type":"Point"}
}