{
  "type": "Feature",
  "properties": {
    "addr:full":"1254 Bloor St W Toronto ON M6H 1N5",
    "addr:housenumber":"1254",
    "addr:postcode":"m6h 1n5",
    "addr:street":"Bloor St W",
    "iso:country":"CA",
    "sg:address":"1254 Bloor St W",
    "sg:city":"Toronto",
    "sg:classifiers":[
        {
            "category":"Home & Garden",
            "subcategory":"Furniture",
            "type":"Retail Goods"
        }
    ],
    "sg:phone":"+1 416 532 7166",
    "sg:postcode":"M6H 1N5",
    "sg:province":"ON",
    "wof:name":"Payless Furniture & Rug",
    "wof:placetype":"venue"
},
  "geometry": {"coordinates":[-79.440521,43.658867],"type":"Point"}
}