{
  "type": "Feature",
  "properties": {
    "addr:full":"1240 County Rd 124 Singhampton ON N0C 1M0",
    "addr:housenumber":"1240",
    "addr:postcode":"n0c 1m0",
    "addr:street":"County Rd 124",
    "iso:country":"CA",
    "sg:address":"1240 County Rd 124",
    "sg:city":"Singhampton",
    "sg:classifiers":[
        {
            "category":"Wholesale",
            "subcategory":"Construction Materials",
            "type":"Manufacturing & Wholesale Goods"
        }
    ],
    "sg:phone":"+1 705 445 3957",
    "sg:postcode":"N0C 1M0",
    "sg:province":"ON",
    "sg:tags":[
        "sand",
        "gravel"
    ],
    "wof:name":"Winters Aggregates Ltd",
    "wof:placetype":"venue"
},
  "geometry": {"coordinates":[-80.235771,44.354671],"type":"Point"}
}