{
  "type": "Feature",
  "properties": {
    "addr:full":"37 Simcoe St Collingwood ON L9Y 1H5",
    "addr:housenumber":"37",
    "addr:postcode":"l9y 1h5",
    "addr:street":"Simcoe St",
    "iso:country":"CA",
    "sg:address":"37 Simcoe St",
    "sg:city":"Collingwood",
    "sg:classifiers":[
        {
            "category":"Autos & Motor Vehicles",
            "subcategory":"Auto Supplies",
            "type":"Retail Goods"
        }
    ],
    "sg:phone":"+1 705 445 3550",
    "sg:postcode":"L9Y 1H5",
    "sg:province":"ON",
    "sg:tags":[
        "automobile",
        "parts"
    ],
    "wof:name":"Carquest Auto Parts",
    "wof:placetype":"venue"
},
  "geometry": {"coordinates":[-80.21636199949999,44.501083374],"type":"Point"}
}