{
  "type": "Feature",
  "properties": {
    "addr:full":"907M Rue M.-A.-Fortin Saint-Jean-Chrysostome QC G6Z 2X3",
    "addr:housenumber":"907m",
    "addr:postcode":"g6z 2x3",
    "addr:street":"Rue M.-A.-Fortin Saint-Jean-Chrysostome",
    "iso:country":"CA",
    "sg:address":"907M Rue M.-A.-Fortin",
    "sg:city":"Saint-Jean-Chrysostome",
    "sg:classifiers":[
        {
            "category":"Professional",
            "subcategory":"Accounting & Tax Preparation",
            "type":"Services"
        }
    ],
    "sg:phone":"+1 418 839 1231",
    "sg:postcode":"G6Z 2X3",
    "sg:province":"QC",
    "sg:tags":[
        "accountant",
        "return",
        "filing"
    ],
    "wof:name":"Thibault, Bruno CA",
    "wof:placetype":"venue"
},
  "geometry": {"coordinates":[-71.2001113892,46.733039856],"type":"Point"}
}