{
  "type": "Feature",
  "properties": {
    "addr:full":"22 Talbot St E Aylmer ON N5H 1H4",
    "addr:housenumber":"22",
    "addr:postcode":"n5h 1h4",
    "addr:street":"Talbot St E",
    "iso:country":"CA",
    "sg:address":"22 Talbot St E",
    "sg:city":"Aylmer",
    "sg:classifiers":[
        {
            "category":"Restaurant",
            "type":"Food & Drink"
        }
    ],
    "sg:phone":"+1 519 773 8182",
    "sg:postcode":"N5H 1H4",
    "sg:province":"ON",
    "wof:name":"Clarke's Restaurant",
    "wof:placetype":"venue"
},
  "geometry": {"coordinates":[-80.982491,42.772858],"type":"Point"}
}