{
  "type": "Feature",
  "properties": {
    "addr:full":"1000 Cumberland Rd Courtenay BC V9N 2E6",
    "addr:housenumber":"1000",
    "addr:postcode":"v9n 2e6",
    "addr:street":"Cumberland Rd",
    "iso:country":"CA",
    "sg:address":"1000 Cumberland Rd",
    "sg:city":"Courtenay",
    "sg:classifiers":[
        {
            "category":"Social Services",
            "subcategory":"Child Care",
            "type":"Services"
        }
    ],
    "sg:phone":"+1 250 338 8511",
    "sg:postcode":"V9N 2E6",
    "sg:province":"BC",
    "wof:name":"Merry Andrew Day Care Ctr",
    "wof:placetype":"venue"
},
  "geometry": {"coordinates":[-125.00318900000001,49.681847],"type":"Point"}
}