{
  "type": "Feature",
  "properties": {
    "addr:full":"480 Ch Dalhousie Dalhousie QC J0P 1G0",
    "addr:housenumber":"480",
    "addr:postcode":"j0p 1g0",
    "addr:street":"Ch Dalhousie",
    "iso:country":"CA",
    "sg:address":"480 Ch Dalhousie",
    "sg:city":"Dalhousie",
    "sg:classifiers":[
        {
            "category":"Wholesale",
            "subcategory":"Machinery & Supplies",
            "type":"Manufacturing & Wholesale Goods"
        }
    ],
    "sg:phone":"+1 450 269 2737",
    "sg:postcode":"J0P 1G0",
    "sg:province":"QC",
    "sg:tags":[
        "farm",
        "equipment"
    ],
    "wof:name":"Fernand Campeau & Fils Inc",
    "wof:placetype":"venue"
},
  "geometry": {"coordinates":[-74.456802,45.298756],"type":"Point"}
}