{
  "type": "Feature",
  "properties": {
    "iso:country":"CA",
    "sg:city":"High Level",
    "sg:classifiers":[
        {
            "category":"Manufacturing",
            "subcategory":"Printing",
            "type":"Manufacturing & Wholesale Goods"
        }
    ],
    "sg:phone":"+1 780 926 3507",
    "sg:postcode":"T0H 1Z0",
    "sg:province":"AB",
    "sg:tags":[
        "printer"
    ],
    "wof:name":"Print Perfect Inc",
    "wof:placetype":"venue"
},
  "geometry": {"coordinates":[-117.129127502,58.5172309875],"type":"Point"}
}