{
  "type": "Feature",
  "properties": {
    "addr:full":"Geikie St & Miette Ave Jasper AB T0E 1E0",
    "addr:postcode":"t0e 1e0",
    "addr:street":"Geikie St & Miette Ave",
    "iso:country":"CA",
    "sg:address":"Geikie St & Miette Ave",
    "sg:city":"Jasper",
    "sg:classifiers":[
        {
            "category":"Organizations",
            "subcategory":"Religious Organization",
            "type":"Services"
        }
    ],
    "sg:phone":"+1 780 852 4505",
    "sg:postcode":"T0E 1E0",
    "sg:province":"AB",
    "sg:tags":[
        "church"
    ],
    "wof:name":"St Mary & St George Anglican",
    "wof:placetype":"venue"
},
  "geometry": {"coordinates":[-118.08300800000001,52.875629],"type":"Point"}
}