{
  "type": "Feature",
  "properties": {
    "iso:country":"CA",
    "sg:address":"257 Centennial Pky N",
    "sg:city":"Hamilton",
    "sg:classifiers":[
        {
            "category":"Home & Garden",
            "subcategory":"Building Materials",
            "type":"Retail Goods"
        }
    ],
    "sg:phone":"+1 905 561 3576",
    "sg:postcode":"L8E 2X3",
    "sg:province":"ON",
    "sg:tags":[
        "plywood",
        "veneer"
    ],
    "wof:name":"Ontario Plywood Spec Ltd",
    "wof:placetype":"venue"
},
  "geometry": {"coordinates":[-79.7600860596,43.2382392883],"type":"Point"}
}