{
  "type": "Feature",
  "properties": {
    "addr:full":"75 Palmer Rd Hamilton ON L8T 3G1",
    "addr:housenumber":"75",
    "addr:postcode":"l8t 3g1",
    "addr:street":"Palmer Rd",
    "iso:country":"CA",
    "sg:address":"75 Palmer Rd",
    "sg:city":"Hamilton",
    "sg:classifiers":[
        {
            "category":"Professional",
            "subcategory":"Management & Consulting",
            "type":"Services"
        }
    ],
    "sg:phone":"+1 905 575 7833",
    "sg:postcode":"L8T 3G1",
    "sg:province":"ON",
    "sg:tags":[
        "food"
    ],
    "wof:name":"Chartwells",
    "wof:placetype":"venue"
},
  "geometry": {"coordinates":[-79.8415985107,43.2151451111],"type":"Point"}
}