{
  "type": "Feature",
  "properties": {
    "addr:full":"773 Snowdrop Ave Victoria BC V8Z 2N3",
    "addr:housenumber":"773",
    "addr:postcode":"v8z 2n3",
    "addr:street":"Snowdrop Ave",
    "iso:country":"CA",
    "sg:address":"773 Snowdrop Ave",
    "sg:city":"Victoria",
    "sg:classifiers":[
        {
            "category":"Home & Garden",
            "subcategory":"Building Materials",
            "type":"Retail Goods"
        }
    ],
    "sg:phone":"+1 250 744 3345",
    "sg:postcode":"V8Z 2N3",
    "sg:province":"BC",
    "sg:tags":[
        "door",
        "closet",
        "accessory"
    ],
    "wof:name":"Canadian Closet Shop",
    "wof:placetype":"venue"
},
  "geometry": {"coordinates":[-123.364517212,48.428314209],"type":"Point"}
}