{
  "type": "Feature",
  "properties": {
    "iso:country":"CA",
    "sg:address":"295 Rue Hebert",
    "sg:city":"Saint-Stanislas-DE-Kostka",
    "sg:classifiers":[
        {
            "category":"Travel",
            "subcategory":"Campground",
            "type":"Entertainment"
        }
    ],
    "sg:phone":"+1 450 373 7099",
    "sg:postcode":"J0S 1W0",
    "sg:province":"QC",
    "wof:name":"Camping A LA Claire Fontaine",
    "wof:placetype":"venue"
},
  "geometry": {"coordinates":[-74.12660980219999,45.1806716919],"type":"Point"}
}