{
  "type": "Feature",
  "properties": {
    "addr:full":"6551 Barnard Dr Richmond BC V7C 5P9",
    "addr:housenumber":"6551",
    "addr:postcode":"v7c 5p9",
    "addr:street":"Barnard Dr",
    "iso:country":"CA",
    "sg:address":"6551 Barnard Dr",
    "sg:city":"Richmond",
    "sg:classifiers":[
        {
            "category":"Wholesale",
            "subcategory":"Electrical",
            "type":"Manufacturing & Wholesale Goods"
        }
    ],
    "sg:phone":"+1 604 821 0189",
    "sg:postcode":"V7C 5P9",
    "sg:province":"BC",
    "sg:tags":[
        "light",
        "tube",
        "bulb"
    ],
    "wof:name":"Wanglo Enterprises",
    "wof:placetype":"venue"
},
  "geometry": {"coordinates":[-123.185104,49.16724],"type":"Point"}
}