{
  "type": "Feature",
  "properties": {
    "iso:country":"CA",
    "sg:address":"160 Crow Trail",
    "sg:city":"Scarborough",
    "sg:classifiers":[
        {
            "category":"Education",
            "subcategory":"School",
            "type":"Public Place"
        }
    ],
    "sg:phone":"+1 416 393 5377",
    "sg:postcode":"M1B 1Y3",
    "sg:province":"ON",
    "wof:name":"Saint Gabriel Lalemant Elem",
    "wof:placetype":"venue"
},
  "geometry": {"coordinates":[-79.2266464233,43.8120727539],"type":"Point"}
}