{
  "type": "Feature",
  "properties": {
    "iso:country":"CA",
    "sg:address":"247 Second St",
    "sg:city":"Collingwood",
    "sg:classifiers":[
        {
            "category":"Personal",
            "subcategory":"Beauty Salon",
            "type":"Services"
        }
    ],
    "sg:phone":"+1 705 444 0524",
    "sg:postcode":"L9Y 1G3",
    "sg:province":"ON",
    "sg:tags":[
        "manicuring"
    ],
    "wof:name":"Nails By Kelly",
    "wof:placetype":"venue"
},
  "geometry": {"coordinates":[-80.2238235474,44.5003128052],"type":"Point"}
}