{
  "type": "Feature",
  "properties": {
    "iso:country":"CA",
    "sg:address":"1205 Av Papineau",
    "sg:city":"Montreal",
    "sg:classifiers":[
        {
            "category":"Communications",
            "subcategory":"Television Station",
            "type":"Services"
        }
    ],
    "sg:phone":"+1 514 495 6100",
    "sg:postcode":"H2K 4R2",
    "sg:province":"QC",
    "sg:tags":[
        "broadcasting",
        "co",
        "representative"
    ],
    "wof:name":"Cfcf/Ctv",
    "wof:placetype":"venue"
},
  "geometry": {"coordinates":[-73.550003,45.521667],"type":"Point"}
}