{
  "type": "Feature",
  "properties": {
    "addr:full":"1850 Main St Winnipeg MB R2V 3J4",
    "addr:housenumber":"1850",
    "addr:postcode":"r2v 3j4",
    "addr:street":"Main St",
    "iso:country":"CA",
    "sg:address":"1850 Main St",
    "sg:city":"Winnipeg",
    "sg:classifiers":[
        {
            "category":"Health Services",
            "subcategory":"Chiropractor",
            "type":"Services"
        }
    ],
    "sg:phone":"+1 204 942 3128",
    "sg:postcode":"R2V 3J4",
    "sg:province":"MB",
    "wof:name":"Capitano, E DC",
    "wof:placetype":"venue"
},
  "geometry": {"coordinates":[-97.11599731450001,49.939250946],"type":"Point"}
}