{
  "type": "Feature",
  "properties": {
    "addr:full":"2205 Rue Beaubien E Montreal QC H2G 1M8",
    "addr:housenumber":"2205",
    "addr:postcode":"h2g 1m8",
    "addr:street":"Rue Beaubien E",
    "iso:country":"CA",
    "sg:address":"2205 Rue Beaubien E",
    "sg:city":"Montreal",
    "sg:classifiers":[
        {
            "category":"Food & Beverages",
            "subcategory":"Groceries & Convenience Stores",
            "type":"Retail Goods"
        }
    ],
    "sg:phone":"+1 514 725 9903",
    "sg:postcode":"H2G 1M8",
    "sg:province":"QC",
    "sg:tags":[
        "grocer"
    ],
    "wof:name":"Depanneur 7 Jours",
    "wof:placetype":"venue"
},
  "geometry": {"coordinates":[-73.59396362299999,45.54637146],"type":"Point"}
}