{
  "type": "Feature",
  "properties": {
    "addr:full":"Campbell's Bay QC J0X 1K0",
    "addr:postcode":"j0x 1k0",
    "addr:street":"Bay",
    "iso:country":"CA",
    "sg:city":"Campbell's Bay",
    "sg:classifiers":[
        {
            "category":"Retail",
            "subcategory":"Auto Repair",
            "type":"Services"
        }
    ],
    "sg:phone":"+1 819 648 5777",
    "sg:postcode":"J0X 1K0",
    "sg:province":"QC",
    "sg:tags":[
        "body",
        "automobile",
        "painting"
    ],
    "wof:name":"Auto-Royale Collision",
    "wof:placetype":"venue"
},
  "geometry": {"coordinates":[-74.80162,45.647354],"type":"Point"}
}