{
  "type": "Feature",
  "properties": {
    "addr:full":"1020 1 Ave Wainwright AB T9W 1G9",
    "addr:housenumber":"1020",
    "addr:postcode":"t9w 1g9",
    "addr:street":"1 Ave",
    "iso:country":"CA",
    "sg:address":"1020 1 Ave",
    "sg:city":"Wainwright",
    "sg:classifiers":[
        {
            "category":"Organizations",
            "subcategory":"Non-profit Organization",
            "type":"Services"
        }
    ],
    "sg:phone":"+1 780 842 7619",
    "sg:postcode":"T9W 1G9",
    "sg:province":"AB",
    "sg:tags":[
        "info",
        "addiction",
        "abuse",
        "treatment",
        "drug"
    ],
    "wof:name":"Alberta Alcohol & Drug Abuse",
    "wof:placetype":"venue"
},
  "geometry": {"coordinates":[-110.861526489,52.8326148987],"type":"Point"}
}