{
  "type": "Feature",
  "properties": {
    "addr:full":"3115 Kennedy Rd Scarborough ON M1V 4Y1",
    "addr:housenumber":"3115",
    "addr:postcode":"m1v 4y1",
    "addr:street":"Kennedy Rd",
    "iso:country":"CA",
    "sg:address":"3115 Kennedy Rd",
    "sg:city":"Scarborough",
    "sg:classifiers":[
        {
            "category":"Manufacturing",
            "subcategory":"Metals",
            "type":"Manufacturing & Wholesale Goods"
        }
    ],
    "sg:phone":"+1 416 298 7077",
    "sg:postcode":"M1V 4Y1",
    "sg:province":"ON",
    "sg:tags":[
        "treating",
        "heat"
    ],
    "wof:name":"Exactatherm Limited",
    "wof:placetype":"venue"
},
  "geometry": {"coordinates":[-79.301987,43.812664],"type":"Point"}
}