{
  "type": "Feature",
  "properties": {
    "addr:full":"121 White Oak Dr E Sault Ste Marie ON P6B 4J7",
    "addr:housenumber":"121",
    "addr:postcode":"p6b 4j7",
    "addr:street":"White Oak Dr E",
    "iso:country":"CA",
    "sg:address":"121 White Oak Dr E",
    "sg:city":"Sault Ste Marie",
    "sg:classifiers":[
        {
            "category":"Manufacturing",
            "subcategory":"Metals",
            "type":"Manufacturing & Wholesale Goods"
        }
    ],
    "sg:phone":"+1 705 949 5733",
    "sg:postcode":"P6B 4J7",
    "sg:province":"ON",
    "sg:tags":[
        "glass"
    ],
    "wof:name":"Glass Employees Ltd",
    "wof:placetype":"venue"
},
  "geometry": {"coordinates":[-84.331909,46.537136],"type":"Point"}
}