{
  "type": "Feature",
  "properties": {
    "addr:full":"Richmond Hill ON L4B 1H3",
    "addr:postcode":"l4b 1h3",
    "iso:country":"CA",
    "sg:city":"Richmond Hill",
    "sg:classifiers":[
        {
            "category":"Manufacturing",
            "subcategory":"Signs",
            "type":"Manufacturing & Wholesale Goods"
        }
    ],
    "sg:phone":"+1 905 709 5772",
    "sg:postcode":"L4B 1H3",
    "sg:province":"ON",
    "sg:tags":[
        "luminous",
        "product"
    ],
    "wof:name":"Enviromate Products Corp",
    "wof:placetype":"venue"
},
  "geometry": {"coordinates":[-79.393562,43.853977],"type":"Point"}
}