{
  "type": "Feature",
  "properties": {
    "addr:full":"30 Mcgill St N Smiths Falls ON K7A 2J4",
    "addr:housenumber":"30",
    "addr:postcode":"k7a 2j4",
    "addr:street":"Mcgill St N",
    "iso:country":"CA",
    "sg:address":"30 Mcgill St N",
    "sg:city":"Smiths Falls",
    "sg:classifiers":[
        {
            "category":"Recreation",
            "type":"Entertainment"
        }
    ],
    "sg:phone":"+1 613 283 1784",
    "sg:postcode":"K7A 2J4",
    "sg:province":"ON",
    "sg:tags":[
        "hall",
        "auditorium"
    ],
    "wof:name":"Hanley Hall",
    "wof:placetype":"venue"
},
  "geometry": {"coordinates":[-76.017517,44.90168],"type":"Point"}
}