{
  "type": "Feature",
  "properties": {
    "addr:full":"Calgary AB T2C 2R9",
    "addr:postcode":"t2c 2r9",
    "iso:country":"CA",
    "sg:city":"Calgary",
    "sg:classifiers":[
        {
            "category":"Wholesale",
            "subcategory":"Electrical",
            "type":"Manufacturing & Wholesale Goods"
        }
    ],
    "sg:phone":"+1 403 531 1555",
    "sg:postcode":"T2C 2R9",
    "sg:province":"AB",
    "sg:tags":[
        "control",
        "security",
        "system"
    ],
    "wof:name":"A E Security Corp",
    "wof:placetype":"venue"
},
  "geometry": {"coordinates":[-113.969002,50.979309],"type":"Point"}
}