{
  "type": "Feature",
  "properties": {
    "addr:full":"675 Cartier St Casselman ON K0A 1M0",
    "addr:housenumber":"675",
    "addr:postcode":"k0a 1m0",
    "addr:street":"Cartier St",
    "iso:country":"CA",
    "sg:address":"675 Cartier St",
    "sg:city":"Casselman",
    "sg:classifiers":[
        {
            "category":"Autos & Motor Vehicles",
            "subcategory":"Auto Supplies",
            "type":"Retail Goods"
        }
    ],
    "sg:phone":"+1 613 764 3183",
    "sg:postcode":"K0A 1M0",
    "sg:province":"ON",
    "sg:tags":[
        "automobile",
        "parts"
    ],
    "wof:name":"Autoparts Extra",
    "wof:placetype":"venue"
},
  "geometry": {"coordinates":[-75.088013,45.312908],"type":"Point"}
}