{
  "type": "Feature",
  "properties": {
    "addr:full":"2180 Howard Ave Windsor ON N8X 3V1",
    "addr:housenumber":"2180",
    "addr:postcode":"n8x 3v1",
    "addr:street":"Howard Ave",
    "iso:country":"CA",
    "sg:address":"2180 Howard Ave",
    "sg:city":"Windsor",
    "sg:classifiers":[
        {
            "category":"Organizations",
            "subcategory":"Religious Organization",
            "type":"Services"
        }
    ],
    "sg:phone":"+1 519 252 8831",
    "sg:postcode":"N8X 3V1",
    "sg:province":"ON",
    "sg:tags":[
        "church"
    ],
    "wof:name":"Good Shepherd Pentecostal Ch",
    "wof:placetype":"venue"
},
  "geometry": {"coordinates":[-83.016479,42.297039],"type":"Point"}
}