{
  "type": "Feature",
  "properties": {
    "iso:country":"CA",
    "sg:address":"934 Kingsway",
    "sg:city":"Vancouver",
    "sg:classifiers":[
        {
            "category":"Professional",
            "subcategory":"Accounting & Tax Preparation",
            "type":"Services"
        }
    ],
    "sg:phone":"+1 604 872 8297",
    "sg:postcode":"V5V 3C4",
    "sg:province":"BC",
    "sg:tags":[
        "consultant"
    ],
    "wof:name":"Tran-Vu Tax Svc",
    "wof:placetype":"venue"
},
  "geometry": {"coordinates":[-123.084869385,49.2542381287],"type":"Point"}
}