{
  "type": "Feature",
  "properties": {
    "addr:full":"10282 Reeves Rd Chilliwack BC V2P 6H4",
    "addr:housenumber":"10282",
    "addr:postcode":"v2p 6h4",
    "addr:street":"Reeves Rd",
    "iso:country":"CA",
    "sg:address":"10282 Reeves Rd",
    "sg:city":"Chilliwack",
    "sg:classifiers":[
        {
            "category":"Farming",
            "subcategory":"Livestock Farm",
            "type":"Manufacturing & Wholesale Goods"
        }
    ],
    "sg:phone":"+1 604 795 7890",
    "sg:postcode":"V2P 6H4",
    "sg:province":"BC",
    "sg:tags":[
        "fur"
    ],
    "wof:name":"Dargatz Mink Ranch",
    "wof:placetype":"venue"
},
  "geometry": {"coordinates":[-121.886543274,49.1884918213],"type":"Point"}
}