{
  "type": "Feature",
  "properties": {
    "iso:country":"CA",
    "sg:city":"New Minas",
    "sg:classifiers":[
        {
            "category":"Personal",
            "subcategory":"Tanning Parlor",
            "type":"Services"
        }
    ],
    "sg:phone":"+1 902 681 0988",
    "sg:postcode":"B4N 3E5",
    "sg:province":"NS",
    "sg:tags":[
        "salon",
        "beauty"
    ],
    "wof:name":"Ultimate Tan",
    "wof:placetype":"venue"
},
  "geometry": {"coordinates":[-64.45269,45.067226],"type":"Point"}
}