{
  "type": "Feature",
  "properties": {
    "iso:country":"CA",
    "sg:city":"Hull",
    "sg:classifiers":[
        {
            "category":"Shopping",
            "subcategory":"Books",
            "type":"Retail Goods"
        }
    ],
    "sg:phone":"+1 819 595 2377",
    "sg:postcode":"J9A 1L8",
    "sg:province":"QC",
    "sg:tags":[
        "dealer"
    ],
    "wof:name":"Librairie Coopsco",
    "wof:placetype":"venue"
},
  "geometry": {"coordinates":[-75.73882293699999,45.4227104187],"type":"Point"}
}