{
  "type": "Feature",
  "properties": {
    "addr:full":"808 Main St Hampton NB E5N 6E1",
    "addr:housenumber":"808",
    "addr:postcode":"e5n 6e1",
    "addr:street":"Main St",
    "iso:country":"CA",
    "sg:address":"808 Main St",
    "sg:city":"Hampton",
    "sg:classifiers":[
        {
            "category":"Arena",
            "subcategory":"Sports Club",
            "type":"Entertainment"
        }
    ],
    "sg:phone":"+1 506 832 6102",
    "sg:postcode":"E5N 6E1",
    "sg:province":"NB",
    "sg:tags":[
        "athletic",
        "fields",
        "stadium"
    ],
    "wof:name":"Hampton Community Ctr",
    "wof:placetype":"venue"
},
  "geometry": {"coordinates":[-65.8318939209,45.5334129333],"type":"Point"}
}