{
  "type": "Feature",
  "properties": {
    "iso:country":"CA",
    "sg:address":"60 Fife Rd",
    "sg:city":"Guelph",
    "sg:classifiers":[
        {
            "category":"Real Estate",
            "subcategory":"Real Estate Agent",
            "type":"Services"
        }
    ],
    "sg:phone":"+1 519 767 6706",
    "sg:postcode":"N1H 6Y2",
    "sg:province":"ON",
    "sg:tags":[
        "management"
    ],
    "wof:name":"Dar Mir Investments",
    "wof:placetype":"venue"
},
  "geometry": {"coordinates":[-80.2702331543,43.5175666809],"type":"Point"}
}