{
  "type": "Feature",
  "properties": {
    "addr:full":"Richmond BC V6V 2L3",
    "addr:postcode":"v6v 2l3",
    "iso:country":"CA",
    "sg:city":"Richmond",
    "sg:classifiers":[
        {
            "category":"Building & Trades",
            "subcategory":"Plumbing",
            "type":"Services"
        }
    ],
    "sg:phone":"+1 604 278 3553",
    "sg:postcode":"V6V 2L3",
    "sg:province":"BC",
    "sg:tags":[
        "mechanical",
        "contractor"
    ],
    "wof:name":"William Kelly & Sons Plumbing",
    "wof:placetype":"venue"
},
  "geometry": {"coordinates":[-123.069397,49.180519],"type":"Point"}
}