{
  "type": "Feature",
  "properties": {
    "iso:country":"CA",
    "sg:address":"35 Rue Principale",
    "sg:city":"Saint-Severe",
    "sg:classifiers":[
        {
            "category":"Retail",
            "subcategory":"Auto Repair",
            "type":"Services"
        }
    ],
    "sg:phone":"+1 819 264 5625",
    "sg:postcode":"G0X 3B0",
    "sg:province":"QC",
    "sg:tags":[
        "repairing",
        "automobile"
    ],
    "wof:name":"Garage Marcel Gelinas Enrg",
    "wof:placetype":"venue"
},
  "geometry": {"coordinates":[-72.8898773193,46.3402900696],"type":"Point"}
}