{
  "type": "Feature",
  "properties": {
    "addr:full":"413 Sherbourne St Toronto ON M4X 1K5",
    "addr:housenumber":"413",
    "addr:postcode":"m4x 1k5",
    "addr:street":"Sherbourne St",
    "iso:country":"CA",
    "sg:address":"413 Sherbourne St",
    "sg:city":"Toronto",
    "sg:classifiers":[
        {
            "category":"Health Services",
            "subcategory":"Optometrist",
            "type":"Services"
        }
    ],
    "sg:phone":"+1 416 961 2010",
    "sg:postcode":"M4X 1K5",
    "sg:province":"ON",
    "wof:name":"Peaker & Kwun",
    "wof:placetype":"venue"
},
  "geometry": {"coordinates":[-79.37348175050001,43.6646881104],"type":"Point"}
}