{
  "type": "Feature",
  "properties": {
    "addr:full":"6385 Rue Sherbrooke O Montreal QC H4B 1N1",
    "addr:housenumber":"6385",
    "addr:postcode":"h4b 1n1",
    "addr:street":"Rue Sherbrooke O",
    "iso:country":"CA",
    "sg:address":"6385 Rue Sherbrooke O",
    "sg:city":"Montreal",
    "sg:classifiers":[
        {
            "category":"Retail",
            "subcategory":"Auto Repair",
            "type":"Services"
        }
    ],
    "sg:phone":"+1 514 486 9411",
    "sg:postcode":"H4B 1N1",
    "sg:province":"QC",
    "sg:tags":[
        "repairing",
        "automobile"
    ],
    "wof:name":"Veloce Bellon Auto Svc Inc",
    "wof:placetype":"venue"
},
  "geometry": {"coordinates":[-73.5447921753,45.5804786682],"type":"Point"}
}