{
  "type": "Feature",
  "properties": {
    "addr:full":"67 St Georges Rd Lytton BC V0K 1Z0",
    "addr:housenumber":"67",
    "addr:postcode":"v0k 1z0",
    "addr:street":"St Georges Rd",
    "iso:country":"CA",
    "sg:address":"67 St Georges Rd",
    "sg:city":"Lytton",
    "sg:classifiers":[
        {
            "category":"Health Services",
            "subcategory":"Clinic",
            "type":"Services"
        }
    ],
    "sg:phone":"+1 250 455 2115",
    "sg:postcode":"V0K 1Z0",
    "sg:province":"BC",
    "wof:name":"Lytton First Nations Health",
    "wof:placetype":"venue"
},
  "geometry": {"coordinates":[-121.577271,50.225925],"type":"Point"}
}