{
  "type": "Feature",
  "properties": {
    "iso:country":"CA",
    "sg:address":"1819 Boul Rene-Levesque O",
    "sg:city":"Montreal",
    "sg:classifiers":[
        {
            "category":"Manufacturing",
            "subcategory":"Chemicals & Compounds",
            "type":"Manufacturing & Wholesale Goods"
        }
    ],
    "sg:phone":"+1 514 483 5500",
    "sg:postcode":"H3H 2P5",
    "sg:province":"QC",
    "sg:tags":[
        "plastic"
    ],
    "wof:name":"Microban Canada Inc",
    "wof:placetype":"venue"
},
  "geometry": {"coordinates":[-73.54927062989999,45.5222892761],"type":"Point"}
}