{
  "type": "Feature",
  "properties": {
    "addr:full":"5027 Trelle Dr NE Calgary AB T2K 3T9",
    "addr:housenumber":"5027",
    "addr:postcode":"t2k 3t9",
    "addr:street":"Trelle Dr Ne",
    "iso:country":"CA",
    "sg:address":"5027 Trelle Dr NE",
    "sg:city":"Calgary",
    "sg:classifiers":[
        {
            "category":"Building & Trades",
            "subcategory":"Construction",
            "type":"Services"
        }
    ],
    "sg:phone":"+1 403 274 9757",
    "sg:postcode":"T2K 3T9",
    "sg:province":"AB",
    "sg:tags":[
        "dry wall",
        "contractor"
    ],
    "wof:name":"Tape-All Drywall Ltd",
    "wof:placetype":"venue"
},
  "geometry": {"coordinates":[-114.058364868,51.0969085693],"type":"Point"}
}