{
  "type": "Feature",
  "properties": {
    "iso:country":"CA",
    "sg:address":"85 Broadview Ave",
    "sg:city":"Toronto",
    "sg:classifiers":[
        {
            "category":"Professional",
            "subcategory":"Computer Services",
            "type":"Services"
        }
    ],
    "sg:phone":"+1 416 469 4243",
    "sg:postcode":"M4M 2E4",
    "sg:province":"ON",
    "sg:tags":[
        "website",
        "design"
    ],
    "wof:name":"Sysology Hosting",
    "wof:placetype":"venue"
},
  "geometry": {"coordinates":[-79.349472,43.658497],"type":"Point"}
}