{
  "type": "Feature",
  "properties": {
    "addr:full":"North Vancouver BC V7J 2L1",
    "addr:postcode":"v7j 2l1",
    "iso:country":"CA",
    "sg:city":"North Vancouver",
    "sg:classifiers":[
        {
            "category":"Building & Trades",
            "subcategory":"Construction",
            "type":"Services"
        }
    ],
    "sg:phone":"+1 604 985 6116",
    "sg:postcode":"V7J 2L1",
    "sg:province":"BC",
    "sg:tags":[
        "general",
        "contractor"
    ],
    "wof:name":"Timberline Construction Group",
    "wof:placetype":"venue"
},
  "geometry": {"coordinates":[-123.032447815,49.3094711304],"type":"Point"}
}