{
  "type": "Feature",
  "properties": {
    "addr:full":"Panet QC G0R 2J0",
    "addr:postcode":"g0r 2j0",
    "iso:country":"CA",
    "sg:city":"Panet",
    "sg:classifiers":[
        {
            "category":"Building & Trades",
            "subcategory":"Construction",
            "type":"Services"
        }
    ],
    "sg:phone":"+1 418 249 2060",
    "sg:postcode":"G0R 2J0",
    "sg:province":"QC",
    "sg:tags":[
        "home",
        "improvement"
    ],
    "wof:name":"Habitation Panet Inc",
    "wof:placetype":"venue"
},
  "geometry": {"coordinates":[-70.145157,46.655987],"type":"Point"}
}