{
  "type": "Feature",
  "properties": {
    "addr:full":"Kamloops BC V1S 1L8",
    "addr:postcode":"bc v1s 1l8",
    "iso:country":"CA",
    "sg:city":"Kamloops",
    "sg:classifiers":[
        {
            "category":"Shopping",
            "subcategory":"Bicycles & Sporting Goods",
            "type":"Retail Goods"
        }
    ],
    "sg:phone":"+1 250 377 8461",
    "sg:postcode":"V1S 1L8",
    "sg:province":"BC",
    "wof:name":"Kamloops Fly Shop",
    "wof:placetype":"venue"
},
  "geometry": {"coordinates":[-120.374969482,50.6510276794],"type":"Point"}
}