{
  "type": "Feature",
  "properties": {
    "addr:full":"15 George St Barrie ON L4N 2G5",
    "addr:housenumber":"15",
    "addr:postcode":"l4n 2g5",
    "addr:street":"George St",
    "iso:country":"CA",
    "sg:address":"15 George St",
    "sg:city":"Barrie",
    "sg:classifiers":[
        {
            "category":"Retail",
            "subcategory":"Auto Repair",
            "type":"Services"
        }
    ],
    "sg:phone":"+1 705 737 3742",
    "sg:postcode":"L4N 2G5",
    "sg:province":"ON",
    "sg:tags":[
        "repairing",
        "automobile"
    ],
    "wof:name":"Northtown Service Ctr",
    "wof:placetype":"venue"
},
  "geometry": {"coordinates":[-79.704674,44.380116],"type":"Point"}
}