{
  "type": "Feature",
  "properties": {
    "iso:country":"CA",
    "sg:address":"5067 Forest Grove Cres",
    "sg:city":"Burlington",
    "sg:classifiers":[
        {
            "category":"Personal",
            "type":"Services"
        }
    ],
    "sg:phone":"+1 905 331 7776",
    "sg:postcode":"L7L 6G6",
    "sg:province":"ON",
    "sg:tags":[
        "therapist",
        "massage"
    ],
    "wof:name":"Caring Hands Massage Therapy",
    "wof:placetype":"venue"
},
  "geometry": {"coordinates":[-79.793022,43.397606],"type":"Point"}
}