{
  "type": "Feature",
  "properties": {
    "addr:full":"5067 Forest Grove Cres Burlington ON L7L 6G6",
    "addr:housenumber":"5067",
    "addr:postcode":"l7l 6g6",
    "addr:street":"Forest Grove Cres",
    "iso:country":"CA",
    "sg:address":"5067 Forest Grove Cres",
    "sg:city":"Burlington",
    "sg:classifiers":[
        {
            "category":"Personal",
            "type":"Services"
        }
    ],
    "sg:phone":"+1 905 331 7776",
    "sg:postcode":"L7L 6G6",
    "sg:province":"ON",
    "sg:tags":[
        "therapist",
        "massage"
    ],
    "wof:name":"Caring Hands Massage Therapy",
    "wof:placetype":"venue"
},
  "geometry": {"coordinates":[-79.79302199999999,43.397606],"type":"Point"}
}