{
  "type": "Feature",
  "properties": {
    "addr:full":"11 Bradford St Barrie ON L4N 3A6",
    "addr:housenumber":"11",
    "addr:postcode":"l4n 3a6",
    "addr:street":"Bradford St",
    "iso:country":"CA",
    "sg:address":"11 Bradford St",
    "sg:city":"Barrie",
    "sg:classifiers":[
        {
            "category":"Professional",
            "subcategory":"Advertising",
            "type":"Services"
        }
    ],
    "sg:phone":"+1 705 721 8000",
    "sg:postcode":"L4N 3A6",
    "sg:province":"ON",
    "sg:tags":[
        "counselor"
    ],
    "wof:name":"Crosson Marketing Svc",
    "wof:placetype":"venue"
},
  "geometry": {"coordinates":[-79.69383999999999,44.387001],"type":"Point"}
}