{
  "type": "Feature",
  "properties": {
    "addr:full":"Calgary AB T2P 2W1",
    "addr:postcode":"t2p 2w1",
    "iso:country":"CA",
    "sg:city":"Calgary",
    "sg:classifiers":[
        {
            "category":"Mining & Drilling",
            "type":"Manufacturing & Wholesale Goods"
        }
    ],
    "sg:phone":"+1 403 290 5335",
    "sg:postcode":"T2P 2W1",
    "sg:province":"AB",
    "sg:tags":[
        "mud",
        "oil",
        "well",
        "additive"
    ],
    "wof:name":"Federal Wholesale Drilling Mud",
    "wof:placetype":"venue"
},
  "geometry": {"coordinates":[-114.067741,51.046486],"type":"Point"}
}