{
  "type": "Feature",
  "properties": {
    "addr:full":"Saint-Boniface-DE-Shawinigan QC G0X 2L0",
    "addr:postcode":"g0x 2l0",
    "iso:country":"CA",
    "sg:city":"Saint-Boniface-DE-Shawinigan",
    "sg:classifiers":[
        {
            "category":"Government",
            "subcategory":"Office",
            "type":"Public Place"
        }
    ],
    "sg:phone":"+1 819 535 2635",
    "sg:postcode":"G0X 2L0",
    "sg:province":"QC",
    "sg:tags":[
        "village"
    ],
    "wof:name":"St-Boniface Svc DE Loisirs",
    "wof:placetype":"venue"
},
  "geometry": {"coordinates":[-72.83049800000001,46.503323],"type":"Point"}
}