{
  "type": "Feature",
  "properties": {
    "addr:full":"10 Rue Principale O Sainte-Agathe-Des-Monts QC J8C 1A3",
    "addr:housenumber":"10",
    "addr:postcode":"j8c 1a3",
    "addr:street":"Rue Principale O",
    "iso:country":"CA",
    "sg:address":"10 Rue Principale O",
    "sg:city":"Sainte-Agathe-Des-Monts",
    "sg:classifiers":[
        {
            "category":"Restaurant",
            "type":"Food & Drink"
        }
    ],
    "sg:phone":"+1 819 324 2075",
    "sg:postcode":"J8C 1A3",
    "sg:province":"QC",
    "sg:tags":[
        "parlor",
        "ice",
        "cream"
    ],
    "wof:name":"Cremiere",
    "wof:placetype":"venue"
},
  "geometry": {"coordinates":[-74.28768920900001,46.04712677],"type":"Point"}
}