{
  "type": "Feature",
  "properties": {
    "addr:full":"London ON N5V 3B1",
    "addr:postcode":"n5v 3b1",
    "iso:country":"CA",
    "sg:city":"London",
    "sg:classifiers":[
        {
            "category":"Professional",
            "subcategory":"Business Services",
            "type":"Services"
        }
    ],
    "sg:phone":"+1 519 451 9882",
    "sg:postcode":"N5V 3B1",
    "sg:province":"ON",
    "sg:tags":[
        "water",
        "treatment"
    ],
    "wof:name":"Wps 2000 Inc",
    "wof:placetype":"venue"
},
  "geometry": {"coordinates":[-81.15876,42.970734],"type":"Point"}
}