{
  "type": "Feature",
  "properties": {
    "iso:country":"CA",
    "sg:city":"Guelph",
    "sg:classifiers":[
        {
            "category":"Professional",
            "subcategory":"Computer Services",
            "type":"Services"
        }
    ],
    "sg:phone":"+1 519 763 3391",
    "sg:postcode":"N1E 6T9",
    "sg:province":"ON",
    "wof:name":"System Resale Solutions IV Ltd",
    "wof:placetype":"venue"
},
  "geometry": {"coordinates":[-80.224098,43.551899],"type":"Point"}
}