{
  "type": "Feature",
  "properties": {
    "iso:country":"CA",
    "sg:address":"5858 Ch DE LA Cote-Des-Neiges # 614",
    "sg:city":"Montreal",
    "sg:classifiers":[
        {
            "category":"Health Services",
            "subcategory":"Doctor",
            "type":"Services"
        }
    ],
    "sg:phone":"+1 514 739 4037",
    "sg:postcode":"H3S 1Z1",
    "sg:province":"QC",
    "sg:tags":[
        "physician",
        "surgeon"
    ],
    "wof:name":"Rodier, Irwin J MD",
    "wof:placetype":"venue"
},
  "geometry": {"coordinates":[-73.629784,45.499706],"type":"Point"}
}