{
  "type": "Feature",
  "properties": {
    "addr:full":"130 Carlton St Toronto ON M5A 4K3",
    "addr:housenumber":"130",
    "addr:postcode":"m5a 4k3",
    "addr:street":"Carlton St",
    "iso:country":"CA",
    "sg:address":"130 Carlton St",
    "sg:city":"Toronto",
    "sg:classifiers":[
        {
            "category":"Real Estate",
            "subcategory":"Real Estate Agent",
            "type":"Services"
        }
    ],
    "sg:phone":"+1 416 925 1581",
    "sg:postcode":"M5A 4K3",
    "sg:province":"ON",
    "sg:tags":[
        "management"
    ],
    "wof:name":"Deborah J Shaver & Assoc Ltd",
    "wof:placetype":"venue"
},
  "geometry": {"coordinates":[-79.37613677980001,43.662612915],"type":"Point"}
}