{
  "type": "Feature",
  "properties": {
    "addr:full":"Toronto ON M5G 1Z6",
    "addr:postcode":"m5g 1z6",
    "iso:country":"CA",
    "sg:city":"Toronto",
    "sg:classifiers":[
        {
            "category":"Professional",
            "subcategory":"Management & Consulting",
            "type":"Services"
        }
    ],
    "sg:phone":"+1 416 979 1115",
    "sg:postcode":"M5G 1Z6",
    "sg:province":"ON",
    "sg:tags":[
        "consultant",
        "government"
    ],
    "wof:name":"Capital Hill Group",
    "wof:placetype":"venue"
},
  "geometry": {"coordinates":[-79.3849639893,43.6582374573],"type":"Point"}
}