{
  "type": "Feature",
  "properties": {
    "addr:full":"940 Chew Ave Quesnel BC V2J 6R8",
    "addr:housenumber":"940",
    "addr:postcode":"v2j 6r8",
    "addr:street":"Chew Ave",
    "iso:country":"CA",
    "sg:address":"940 Chew Ave",
    "sg:city":"Quesnel",
    "sg:classifiers":[
        {
            "category":"Travel",
            "subcategory":"Hotels & Motels",
            "type":"Entertainment"
        }
    ],
    "sg:phone":"+1 250 747 3511",
    "sg:postcode":"V2J 6R8",
    "sg:province":"BC",
    "wof:name":"Sandman Hotels & Inns",
    "wof:placetype":"venue"
},
  "geometry": {"coordinates":[-122.441917,52.963638],"type":"Point"}
}