{
  "type": "Feature",
  "properties": {
    "addr:full":"33451 Hawthorne Ave Abbotsford BC V2S 1B7",
    "addr:housenumber":"33451",
    "addr:postcode":"v2s 1b7",
    "addr:street":"Hawthorne Ave",
    "iso:country":"CA",
    "sg:address":"33451 Hawthorne Ave",
    "sg:city":"Abbotsford",
    "sg:classifiers":[
        {
            "category":"Utilities",
            "subcategory":"Refuse",
            "type":"Services"
        }
    ],
    "sg:phone":"+1 604 864 1051",
    "sg:postcode":"V2S 1B7",
    "sg:province":"BC",
    "sg:tags":[
        "garbage",
        "collection"
    ],
    "wof:name":"Citywide Disposal",
    "wof:placetype":"venue"
},
  "geometry": {"coordinates":[-122.297119141,49.0335693359],"type":"Point"}
}