{
  "type": "Feature",
  "properties": {
    "addr:full":"960 Pembina Hwy Winnipeg MB R3T 1Z5",
    "addr:housenumber":"960",
    "addr:postcode":"r3t 1z5",
    "addr:street":"Pembina Hwy",
    "iso:country":"CA",
    "sg:address":"960 Pembina Hwy",
    "sg:city":"Winnipeg",
    "sg:classifiers":[
        {
            "category":"Retail",
            "subcategory":"Auto Repair",
            "type":"Services"
        }
    ],
    "sg:phone":"+1 204 453 8618",
    "sg:postcode":"R3T 1Z5",
    "sg:province":"MB",
    "sg:tags":[
        "repairing",
        "automobile",
        "tire"
    ],
    "wof:name":"Fountain Tire",
    "wof:placetype":"venue"
},
  "geometry": {"coordinates":[-97.151886,49.851936],"type":"Point"}
}