{
  "type": "Feature",
  "properties": {
    "addr:full":"North York ON M2M 3T9",
    "addr:postcode":"m2m 3t9",
    "iso:country":"CA",
    "sg:city":"North York",
    "sg:classifiers":[
        {
            "category":"Banks & Credit Unions",
            "subcategory":"Bank",
            "type":"Services"
        }
    ],
    "sg:phone":"+1 416 222 6668",
    "sg:postcode":"M2M 3T9",
    "sg:province":"ON",
    "sg:tags":[
        "broker",
        "foreign",
        "dealer",
        "exchange"
    ],
    "wof:name":"A M Exchange",
    "wof:placetype":"venue"
},
  "geometry": {"coordinates":[-79.416481,43.784363],"type":"Point"}
}