{
  "type": "Feature",
  "properties": {
    "addr:full":"5 Park Home Ave # 630 North York ON M2N 6L4",
    "addr:housenumber":"5",
    "addr:postcode":"m2n 6l4",
    "addr:street":"Park Home Ave # 630",
    "iso:country":"CA",
    "sg:address":"5 Park Home Ave # 630",
    "sg:city":"North York",
    "sg:classifiers":[
        {
            "category":"Social Services",
            "type":"Services"
        }
    ],
    "sg:phone":"+1 416 410 4357",
    "sg:postcode":"M2N 6L4",
    "sg:province":"ON",
    "sg:tags":[
        "counselor",
        "marriage",
        "family"
    ],
    "wof:name":"Family Therapy & Mediation",
    "wof:placetype":"venue"
},
  "geometry": {"coordinates":[-79.41355896,43.7689819336],"type":"Point"}
}