{
  "type": "Feature",
  "properties": {
    "iso:country":"CA",
    "sg:address":"4235 Departure Bay Rd",
    "sg:city":"Nanaimo",
    "sg:classifiers":[
        {
            "category":"Organizations",
            "subcategory":"Religious Organization",
            "type":"Services"
        }
    ],
    "sg:phone":"+1 250 758 2676",
    "sg:postcode":"V9T 1C9",
    "sg:province":"BC",
    "sg:tags":[
        "church"
    ],
    "wof:name":"Presbyterian Church St Andrews",
    "wof:placetype":"venue"
},
  "geometry": {"coordinates":[-124.00151062,49.2068862915],"type":"Point"}
}