{
  "type": "Feature",
  "properties": {
    "addr:full":"York ON M6S 4W3",
    "addr:postcode":"m6s 4w3",
    "iso:country":"CA",
    "sg:city":"York",
    "sg:classifiers":[
        {
            "category":"Professional",
            "subcategory":"Lawyer & Legal Services",
            "type":"Services"
        }
    ],
    "sg:phone":"+1 416 766 0488",
    "sg:postcode":"M6S 4W3",
    "sg:province":"ON",
    "sg:tags":[
        "attorney"
    ],
    "wof:name":"Firchuk, John",
    "wof:placetype":"venue"
},
  "geometry": {"coordinates":[-79.49880981450001,43.6844596863],"type":"Point"}
}