{
  "type": "Feature",
  "properties": {
    "addr:full":"975 English Line Warsaw ON K0L 3A0",
    "addr:housenumber":"975",
    "addr:postcode":"k0l 3a0",
    "addr:street":"English Line",
    "iso:country":"CA",
    "sg:address":"975 English Line",
    "sg:city":"Warsaw",
    "sg:classifiers":[
        {
            "category":"Education",
            "subcategory":"School",
            "type":"Public Place"
        }
    ],
    "sg:phone":"+1 705 652 8332",
    "sg:postcode":"K0L 3A0",
    "sg:province":"ON",
    "wof:name":"Warsaw Public School",
    "wof:placetype":"venue"
},
  "geometry": {"coordinates":[-78.13324,44.436871],"type":"Point"}
}