{
  "type": "Feature",
  "properties": {
    "addr:full":"390 Bay St # 300 Sault Ste Marie ON P6A 1X2",
    "addr:housenumber":"390",
    "addr:postcode":"p6a 1x2",
    "addr:street":"Bay St # 300",
    "iso:country":"CA",
    "sg:address":"390 Bay St # 300",
    "sg:city":"Sault Ste Marie",
    "sg:classifiers":[
        {
            "category":"Professional",
            "subcategory":"Lawyer & Legal Services",
            "type":"Services"
        }
    ],
    "sg:phone":"+1 705 541 9400",
    "sg:postcode":"P6A 1X2",
    "sg:province":"ON",
    "sg:tags":[
        "attorney"
    ],
    "wof:name":"Reilly & Pitcher",
    "wof:placetype":"venue"
},
  "geometry": {"coordinates":[-84.334808,46.511227],"type":"Point"}
}