{
  "type": "Feature",
  "properties": {
    "addr:full":"12626 85 St NW Calgary AB T3R 1J3",
    "addr:housenumber":"12626",
    "addr:postcode":"t3r 1j3",
    "addr:street":"85 St Nw",
    "iso:country":"CA",
    "sg:address":"12626 85 St NW",
    "sg:city":"Calgary",
    "sg:classifiers":[
        {
            "category":"Education",
            "subcategory":"School",
            "type":"Public Place"
        }
    ],
    "sg:phone":"+1 403 662 3547",
    "sg:postcode":"T3R 1J3",
    "sg:province":"AB",
    "wof:name":"West View Secondary School",
    "wof:placetype":"venue"
},
  "geometry": {"coordinates":[-114.21088409399999,51.1652870178],"type":"Point"}
}