{
  "type": "Feature",
  "properties": {
    "addr:full":"Provost AB T0B 3S0",
    "addr:postcode":"t0b 3s0",
    "iso:country":"CA",
    "sg:city":"Provost",
    "sg:classifiers":[
        {
            "category":"Banks & Credit Unions",
            "subcategory":"Investment Brokerage",
            "type":"Services"
        }
    ],
    "sg:phone":"+1 780 753 4944",
    "sg:postcode":"T0B 3S0",
    "sg:province":"AB",
    "sg:tags":[
        "consultant",
        "planning",
        "financial"
    ],
    "wof:name":"Investors Group",
    "wof:placetype":"venue"
},
  "geometry": {"coordinates":[-110.26480100000001,52.352859],"type":"Point"}
}