{
  "type": "Feature",
  "properties": {
    "addr:full":"13 Rapids-View St Gloucester ON K1V 1G9",
    "addr:housenumber":"13",
    "addr:postcode":"k1v 1g9",
    "addr:street":"Rapids-View St",
    "iso:country":"CA",
    "sg:address":"13 Rapids-View St",
    "sg:city":"Gloucester",
    "sg:classifiers":[
        {
            "category":"Building & Trades",
            "subcategory":"Construction",
            "type":"Services"
        }
    ],
    "sg:phone":"+1 613 521 0911",
    "sg:postcode":"K1V 1G9",
    "sg:province":"ON",
    "sg:tags":[
        "masonry",
        "contractor"
    ],
    "wof:name":"Federal Masonry Contrs Ltd",
    "wof:placetype":"venue"
},
  "geometry": {"coordinates":[-75.6937789917,45.3202781677],"type":"Point"}
}