{
  "type": "Feature",
  "properties": {
    "addr:full":"270 Farquhar St Gravenhurst ON P1P 1V3",
    "addr:housenumber":"270",
    "addr:postcode":"p1p 1v3",
    "addr:street":"Farquhar St",
    "iso:country":"CA",
    "sg:address":"270 Farquhar St",
    "sg:city":"Gravenhurst",
    "sg:classifiers":[
        {
            "category":"Manufacturing",
            "subcategory":"Jewelry",
            "type":"Manufacturing & Wholesale Goods"
        }
    ],
    "sg:phone":"+1 705 687 8180",
    "sg:postcode":"P1P 1V3",
    "sg:province":"ON",
    "sg:tags":[
        "goldsmith",
        "silversmith",
        "product",
        "jeweler"
    ],
    "wof:name":"Peter M Weber Ltd",
    "wof:placetype":"venue"
},
  "geometry": {"coordinates":[-79.379181,44.925503],"type":"Point"}
}