{
  "type": "Feature",
  "properties": {
    "addr:full":"364 Lakeshore Rd E Mississauga ON L5G 1H5",
    "addr:housenumber":"364",
    "addr:postcode":"l5g 1h5",
    "addr:street":"Lakeshore Rd E",
    "iso:country":"CA",
    "sg:address":"364 Lakeshore Rd E",
    "sg:city":"Mississauga",
    "sg:classifiers":[
        {
            "category":"Food & Beverages",
            "subcategory":"Bakery",
            "type":"Retail Goods"
        }
    ],
    "sg:phone":"+1 905 271 1778",
    "sg:postcode":"L5G 1H5",
    "sg:province":"ON",
    "sg:tags":[
        "doughnut"
    ],
    "wof:name":"Country Style Donuts",
    "wof:placetype":"venue"
},
  "geometry": {"coordinates":[-79.5729751587,43.5632972717],"type":"Point"}
}