{
  "type": "Feature",
  "properties": {
    "iso:country":"CA",
    "sg:city":"Grande Prairie",
    "sg:classifiers":[
        {
            "category":"Shopping",
            "type":"Retail Goods"
        }
    ],
    "sg:phone":"+1 780 831 0200",
    "sg:postcode":"T8V 7L3",
    "sg:province":"AB",
    "sg:tags":[
        "stamp",
        "collector",
        "for"
    ],
    "wof:name":"Canada Post Corp",
    "wof:placetype":"venue"
},
  "geometry": {"coordinates":[-118.830261,55.172466],"type":"Point"}
}