{
  "type": "Feature",
  "properties": {
    "addr:full":"Edmonton AB T6X 1A3",
    "addr:postcode":"t6x 1a3",
    "iso:country":"CA",
    "sg:city":"Edmonton",
    "sg:classifiers":[
        {
            "category":"Shopping",
            "subcategory":"Clothing, Apparel, & Fashions",
            "type":"Retail Goods"
        }
    ],
    "sg:phone":"+1 780 461 2271",
    "sg:postcode":"T6X 1A3",
    "sg:province":"AB",
    "sg:tags":[
        "tailor"
    ],
    "wof:name":"Millwood Tailors",
    "wof:placetype":"venue"
},
  "geometry": {"coordinates":[-113.44249000000001,53.410645],"type":"Point"}
}