{
  "type": "Feature",
  "properties": {
    "addr:full":"26 Westwyn Crt Brampton ON L6T 4T5",
    "addr:housenumber":"26",
    "addr:postcode":"l6t 4t5",
    "addr:street":"Westwyn Crt",
    "iso:country":"CA",
    "sg:address":"26 Westwyn Crt",
    "sg:city":"Brampton",
    "sg:classifiers":[
        {
            "category":"Manufacturing",
            "subcategory":"Tools & Machinery",
            "type":"Manufacturing & Wholesale Goods"
        }
    ],
    "sg:phone":"+1 905 451 4221",
    "sg:postcode":"L6T 4T5",
    "sg:province":"ON",
    "sg:tags":[
        "machine",
        "shop"
    ],
    "wof:name":"John Thurston Machine Ltd",
    "wof:placetype":"venue"
},
  "geometry": {"coordinates":[-79.694565,43.685162],"type":"Point"}
}