{
  "type": "Feature",
  "properties": {
    "iso:country":"CA",
    "sg:address":"51 Esandar Dr",
    "sg:city":"Toronto",
    "sg:classifiers":[
        {
            "category":"Building & Trades",
            "subcategory":"Equipment Rental",
            "type":"Services"
        }
    ],
    "sg:phone":"+1 416 759 2611",
    "sg:postcode":"M4G 4C5",
    "sg:province":"ON",
    "sg:tags":[
        "yard"
    ],
    "wof:name":"Exclusive Affair Rentals Inc",
    "wof:placetype":"venue"
},
  "geometry": {"coordinates":[-79.3573684692,43.705909729],"type":"Point"}
}