{
  "type": "Feature",
  "properties": {
    "addr:full":"964 Parkhill Rd W Peterborough ON K9J 6P3",
    "addr:housenumber":"964",
    "addr:postcode":"k9j 6p3",
    "addr:street":"Parkhill Rd W",
    "iso:country":"CA",
    "sg:address":"964 Parkhill Rd W",
    "sg:city":"Peterborough",
    "sg:classifiers":[
        {
            "category":"Building & Trades",
            "subcategory":"Construction",
            "type":"Services"
        }
    ],
    "sg:phone":"+1 705 875 7433",
    "sg:postcode":"K9J 6P3",
    "sg:province":"ON",
    "sg:tags":[
        "home",
        "improvement"
    ],
    "wof:name":"Vern Endicott Contracting",
    "wof:placetype":"venue"
},
  "geometry": {"coordinates":[-78.357353,44.307289],"type":"Point"}
}