{
  "type": "Feature",
  "properties": {
    "addr:full":"234 Clements Rd W # 1 Ajax ON L1S 3K5",
    "addr:housenumber":"234",
    "addr:postcode":"l1s 3k5",
    "addr:street":"Clements Rd W # 1",
    "iso:country":"CA",
    "sg:address":"234 Clements Rd W # 1",
    "sg:city":"Ajax",
    "sg:classifiers":[
        {
            "category":"Manufacturing",
            "subcategory":"Furniture",
            "type":"Manufacturing & Wholesale Goods"
        }
    ],
    "sg:phone":"+1 905 427 2674",
    "sg:postcode":"L1S 3K5",
    "sg:province":"ON",
    "wof:name":"Malgray Furniture Product Inc",
    "wof:placetype":"venue"
},
  "geometry": {"coordinates":[-79.02337646479999,43.834236145],"type":"Point"}
}