{
  "type": "Feature",
  "properties": {
    "addr:full":"2325 Mckee Ave Saskatoon SK S7K 2T9",
    "addr:housenumber":"2325",
    "addr:postcode":"s7k 2t9",
    "addr:street":"Mckee Ave",
    "iso:country":"CA",
    "sg:address":"2325 Mckee Ave",
    "sg:city":"Saskatoon",
    "sg:classifiers":[
        {
            "category":"Manufacturing",
            "subcategory":"Metals",
            "type":"Manufacturing & Wholesale Goods"
        }
    ],
    "sg:phone":"+1 306 652 7151",
    "sg:postcode":"S7K 2T9",
    "sg:province":"SK",
    "sg:tags":[
        "steel"
    ],
    "wof:name":"Wilkinson Steel & Metals",
    "wof:placetype":"venue"
},
  "geometry": {"coordinates":[-106.653434753,52.1631164551],"type":"Point"}
}