{
  "type": "Feature",
  "properties": {
    "addr:full":"3107 Harriet Rd Victoria BC V9A 1T7",
    "addr:housenumber":"3107",
    "addr:postcode":"v9a 1t7",
    "addr:street":"Harriet Rd",
    "iso:country":"CA",
    "sg:address":"3107 Harriet Rd",
    "sg:city":"Victoria",
    "sg:classifiers":[
        {
            "category":"Building & Trades",
            "subcategory":"Construction",
            "type":"Services"
        }
    ],
    "sg:phone":"+1 250 883 5553",
    "sg:postcode":"V9A 1T7",
    "sg:province":"BC",
    "sg:tags":[
        "excavating",
        "contractor"
    ],
    "wof:name":"Ari's Bobcat & Trucking",
    "wof:placetype":"venue"
},
  "geometry": {"coordinates":[-123.38623,48.447647],"type":"Point"}
}