{
  "type": "Feature",
  "properties": {
    "addr:full":"48 Twenty Second St Etobicoke ON M8V 3M1",
    "addr:housenumber":"48",
    "addr:postcode":"m8v 3m1",
    "addr:street":"Twenty Second St",
    "iso:country":"CA",
    "sg:address":"48 Twenty Second St",
    "sg:city":"Etobicoke",
    "sg:classifiers":[
        {
            "category":"Professional",
            "subcategory":"Art Services",
            "type":"Services"
        }
    ],
    "sg:phone":"+1 416 201 9295",
    "sg:postcode":"M8V 3M1",
    "sg:province":"ON",
    "sg:tags":[
        "graphic",
        "designer"
    ],
    "wof:name":"Interrobang Graphic Design Inc",
    "wof:placetype":"venue"
},
  "geometry": {"coordinates":[-79.52216339109999,43.5987930298],"type":"Point"}
}