{
  "type": "Feature",
  "properties": {
    "addr:full":"6030 3 St SE Calgary AB T2H 1K2",
    "addr:housenumber":"6030 3",
    "addr:postcode":"t2h 1k2",
    "addr:street":"St Se",
    "iso:country":"CA",
    "sg:address":"6030 3 St SE",
    "sg:city":"Calgary",
    "sg:classifiers":[
        {
            "category":"Freight",
            "type":"Transportation"
        }
    ],
    "sg:phone":"+1 403 252 5460",
    "sg:postcode":"T2H 1K2",
    "sg:province":"AB",
    "sg:tags":[
        "mover"
    ],
    "wof:name":"Mayflower Transit",
    "wof:placetype":"venue"
},
  "geometry": {"coordinates":[-114.05689239500001,51.00050354],"type":"Point"}
}