{
  "type": "Feature",
  "properties": {
    "addr:full":"200 Mcnab Walkerton ON N0G 2V0",
    "addr:housenumber":"200",
    "addr:postcode":"n0g 2v0",
    "addr:street":"Mcnab Walkerton",
    "iso:country":"CA",
    "sg:address":"200 Mcnab",
    "sg:city":"Walkerton",
    "sg:classifiers":[
        {
            "category":"Government",
            "subcategory":"Office",
            "type":"Public Place"
        }
    ],
    "sg:phone":"+1 519 881 2010",
    "sg:postcode":"N0G 2V0",
    "sg:province":"ON",
    "wof:name":"Canada Human Resources Ctr",
    "wof:placetype":"venue"
},
  "geometry": {"coordinates":[-81.1446,44.130386],"type":"Point"}
}