{
  "type": "Feature",
  "properties": {
    "addr:full":"9701 Highway 50 Woodbridge ON L4H 2G4",
    "addr:housenumber":"9701",
    "addr:postcode":"l4h 2g4",
    "addr:street":"Highway 50",
    "iso:country":"CA",
    "sg:address":"9701 Highway 50",
    "sg:city":"Woodbridge",
    "sg:classifiers":[
        {
            "category":"Freight",
            "type":"Transportation"
        }
    ],
    "sg:phone":"+1 905 893 2600",
    "sg:postcode":"L4H 2G4",
    "sg:province":"ON",
    "sg:tags":[
        "trucking"
    ],
    "wof:name":"Consolidated Fastfrate Inc",
    "wof:placetype":"venue"
},
  "geometry": {"coordinates":[-79.59215500000001,43.785065],"type":"Point"}
}