{
  "type": "Feature",
  "properties": {
    "addr:full":"2520 Bristol Cir Oakville ON L6H 5S1",
    "addr:housenumber":"2520",
    "addr:postcode":"l6h 5s1",
    "addr:street":"Bristol Cir",
    "iso:country":"CA",
    "sg:address":"2520 Bristol Cir",
    "sg:city":"Oakville",
    "sg:classifiers":[
        {
            "category":"Home & Garden",
            "subcategory":"Furniture",
            "type":"Retail Goods"
        }
    ],
    "sg:phone":"+1 905 829 0906",
    "sg:postcode":"L6H 5S1",
    "sg:province":"ON",
    "sg:tags":[
        "mattress"
    ],
    "wof:name":"Home & Patio Warehouse",
    "wof:placetype":"venue"
},
  "geometry": {"coordinates":[-79.6825332642,43.518573761],"type":"Point"}
}