{
  "type": "Feature",
  "properties": {
    "addr:full":"1090 Kenaston Blvd Winnipeg MB R3P 0R7",
    "addr:housenumber":"1090",
    "addr:postcode":"r3p 0r7",
    "addr:street":"Kenaston Blvd",
    "iso:country":"CA",
    "sg:address":"1090 Kenaston Blvd",
    "sg:city":"Winnipeg",
    "sg:classifiers":[
        {
            "category":"Manufacturing",
            "subcategory":"Petroleum Products",
            "type":"Manufacturing & Wholesale Goods"
        }
    ],
    "sg:phone":"+1 204 987 9600",
    "sg:postcode":"R3P 0R7",
    "sg:province":"MB",
    "sg:tags":[
        "recycling",
        "center",
        "oil"
    ],
    "wof:name":"Enviro West Inc",
    "wof:placetype":"venue"
},
  "geometry": {"coordinates":[-97.2087402344,49.8393783569],"type":"Point"}
}