{
  "type": "Feature",
  "properties": {
    "addr:full":"868 Falconbridge Rd #17 Sudbury ON P3A 5K7",
    "addr:housenumber":"868",
    "addr:postcode":"p3a 5k7",
    "addr:street":"Falconbridge Rd # 17",
    "iso:country":"CA",
    "sg:address":"868 Falconbridge Rd #17",
    "sg:city":"Sudbury",
    "sg:classifiers":[
        {
            "category":"Wholesale",
            "subcategory":"Machinery & Supplies",
            "type":"Manufacturing & Wholesale Goods"
        }
    ],
    "sg:phone":"+1 705 524 2101",
    "sg:postcode":"P3A 5K7",
    "sg:province":"ON",
    "sg:tags":[
        "equipment",
        "industrial",
        "hydraulic"
    ],
    "wof:name":"Pioneer Power Industries Ltd",
    "wof:placetype":"venue"
},
  "geometry": {"coordinates":[-80.9246673584,46.5167808533],"type":"Point"}
}