{
  "type": "Feature",
  "properties": {
    "addr:full":"RR 1 Busby AB T0G 0H0",
    "addr:postcode":"t0g 0h0",
    "addr:street":"Rr 1 Busby",
    "iso:country":"CA",
    "sg:address":"RR 1",
    "sg:city":"Busby",
    "sg:classifiers":[
        {
            "category":"Travel",
            "subcategory":"Campground",
            "type":"Entertainment"
        }
    ],
    "sg:phone":"+1 780 967 5585",
    "sg:postcode":"T0G 0H0",
    "sg:province":"AB",
    "sg:tags":[
        "camp"
    ],
    "wof:name":"Camp Nakamun",
    "wof:placetype":"venue"
},
  "geometry": {"coordinates":[-113.90522,53.949017],"type":"Point"}
}