{
  "type": "Feature",
  "properties": {
    "iso:country":"CA",
    "sg:address":"1156 Pacific Blvd",
    "sg:city":"Vancouver",
    "sg:classifiers":[
        {
            "category":"Health Services",
            "subcategory":"Doctor",
            "type":"Services"
        }
    ],
    "sg:phone":"+1 604 629 0386",
    "sg:postcode":"V6Z 2X7",
    "sg:province":"BC",
    "sg:tags":[
        "dentist"
    ],
    "wof:name":"Aarm Dental Group",
    "wof:placetype":"venue"
},
  "geometry": {"coordinates":[-123.120331,49.27412],"type":"Point"}
}