{
  "type": "Feature",
  "properties": {
    "addr:full":"1156 Pacific Blvd Vancouver BC V6Z 2X7",
    "addr:housenumber":"1156",
    "addr:postcode":"v6z 2x7",
    "addr:street":"Pacific Blvd",
    "iso:country":"CA",
    "sg:address":"1156 Pacific Blvd",
    "sg:city":"Vancouver",
    "sg:classifiers":[
        {
            "category":"Health Services",
            "subcategory":"Doctor",
            "type":"Services"
        }
    ],
    "sg:phone":"+1 604 629 0386",
    "sg:postcode":"V6Z 2X7",
    "sg:province":"BC",
    "sg:tags":[
        "dentist"
    ],
    "wof:name":"Aarm Dental Group",
    "wof:placetype":"venue"
},
  "geometry": {"coordinates":[-123.12033099999999,49.27412],"type":"Point"}
}