{
  "type": "Feature",
  "properties": {
    "addr:full":"50 Boul Taschereau LA Prairie QC J5R 4V3",
    "addr:housenumber":"50",
    "addr:postcode":"j5r 4v3",
    "addr:street":"Boul Taschereau",
    "iso:country":"CA",
    "sg:address":"50 Boul Taschereau",
    "sg:city":"LA Prairie",
    "sg:classifiers":[
        {
            "category":"Personal",
            "subcategory":"Shoe Repair & Shine",
            "type":"Services"
        }
    ],
    "sg:phone":"+1 450 659 6446",
    "sg:postcode":"J5R 4V3",
    "sg:province":"QC",
    "sg:tags":[
        "repairing",
        "boot"
    ],
    "wof:name":"Cordonnerie Nettoyeur Maximum",
    "wof:placetype":"venue"
},
  "geometry": {"coordinates":[-73.484116,45.423779],"type":"Point"}
}