{
  "type": "Feature",
  "properties": {
    "addr:full":"2725 Jane St North York ON M3L 1S3",
    "addr:housenumber":"2725",
    "addr:postcode":"m3l 1s3",
    "addr:street":"Jane St",
    "iso:country":"CA",
    "sg:address":"2725 Jane St",
    "sg:city":"North York",
    "sg:classifiers":[
        {
            "category":"Food & Beverages",
            "subcategory":"Bakery",
            "type":"Retail Goods"
        }
    ],
    "sg:phone":"+1 416 745 4371",
    "sg:postcode":"M3L 1S3",
    "sg:province":"ON",
    "sg:tags":[
        "baker"
    ],
    "wof:name":"Stella Patisserie",
    "wof:placetype":"venue"
},
  "geometry": {"coordinates":[-79.51332855219999,43.7406311035],"type":"Point"}
}