{
  "type": "Feature",
  "properties": {
    "addr:full":"1470 Dundas St W Toronto ON M6J 1Y6",
    "addr:housenumber":"1470",
    "addr:postcode":"m6j 1y6",
    "addr:street":"Dundas St W",
    "iso:country":"CA",
    "sg:address":"1470 Dundas St W",
    "sg:city":"Toronto",
    "sg:classifiers":[
        {
            "category":"Restaurant",
            "type":"Food & Drink"
        }
    ],
    "sg:phone":"+1 416 532 2885",
    "sg:postcode":"M6J 1Y6",
    "sg:province":"ON",
    "sg:tags":[
        "pizza"
    ],
    "wof:name":"Tony's & Nick's Place",
    "wof:placetype":"venue"
},
  "geometry": {"coordinates":[-79.4310379028,43.6497039795],"type":"Point"}
}