{
  "type": "Feature",
  "properties": {
    "addr:full":"1970 Du Golf Ch Saint-Remi QC J0L 2L0",
    "addr:housenumber":"1970",
    "addr:postcode":"j0l 2l0",
    "addr:street":"Du Golf;Saint-Remi",
    "iso:country":"CA",
    "sg:address":"1970 Du Golf Ch",
    "sg:city":"Saint-Remi",
    "sg:classifiers":[
        {
            "category":"Recreation",
            "type":"Entertainment"
        }
    ],
    "sg:phone":"+1 450 454 2052",
    "sg:postcode":"J0L 2L0",
    "sg:province":"QC",
    "sg:tags":[
        "hall",
        "auditorium"
    ],
    "wof:name":"Resto Bar Du Golf",
    "wof:placetype":"venue"
},
  "geometry": {"coordinates":[-73.6164932251,45.2612342834],"type":"Point"}
}