{
  "type": "Feature",
  "properties": {
    "addr:full":"1350 Boul Saint-Charles Saint-Charles-DE-Drummond QC J2C 4Z5",
    "addr:housenumber":"1350",
    "addr:postcode":"j2c 4z5",
    "addr:street":"Boul Saint-Charles",
    "iso:country":"CA",
    "sg:address":"1350 Boul Saint-Charles",
    "sg:city":"Saint-Charles-DE-Drummond",
    "sg:classifiers":[
        {
            "category":"Autos & Motor Vehicles",
            "subcategory":"Automobile Sales",
            "type":"Retail Goods"
        }
    ],
    "sg:phone":"+1 819 477 9565",
    "sg:postcode":"J2C 4Z5",
    "sg:province":"QC",
    "sg:tags":[
        "car",
        "dealer"
    ],
    "wof:name":"Michel Automobiles Inc",
    "wof:placetype":"venue"
},
  "geometry": {"coordinates":[-72.462547,45.90123],"type":"Point"}
}