{
  "type": "Feature",
  "properties": {
    "addr:full":"343 Clearwater Valley Rd Clearwater BC V0E 1N0",
    "addr:housenumber":"343",
    "addr:postcode":"v0e 1n0",
    "addr:street":"Clearwater Valley Rd",
    "iso:country":"CA",
    "sg:address":"343 Clearwater Valley Rd",
    "sg:city":"Clearwater",
    "sg:classifiers":[
        {
            "category":"Retail",
            "subcategory":"Auto Repair",
            "type":"Services"
        }
    ],
    "sg:phone":"+1 250 674 3310",
    "sg:postcode":"V0E 1N0",
    "sg:province":"BC",
    "sg:tags":[
        "repairing",
        "automobile"
    ],
    "wof:name":"Tnt Transmission Svc",
    "wof:placetype":"venue"
},
  "geometry": {"coordinates":[-120.044265747,51.6445808411],"type":"Point"}
}