{
  "type": "Feature",
  "properties": {
    "addr:full":"Ajax ON L1S 6W4",
    "addr:postcode":"l1s 6w4",
    "iso:country":"CA",
    "sg:city":"Ajax",
    "sg:classifiers":[
        {
            "category":"Building & Trades",
            "subcategory":"Construction",
            "type":"Services"
        }
    ],
    "sg:phone":"+1 905 428 3848",
    "sg:postcode":"L1S 6W4",
    "sg:province":"ON",
    "sg:tags":[
        "fire",
        "restoration",
        "damage"
    ],
    "wof:name":"Premier Restoration",
    "wof:placetype":"venue"
},
  "geometry": {"coordinates":[-79.0327529907,43.8312225342],"type":"Point"}
}