{
  "type": "Feature",
  "properties": {
    "iso:country":"CA",
    "sg:address":"122 Stanley St",
    "sg:city":"Ayr",
    "sg:classifiers":[
        {
            "category":"Shopping",
            "subcategory":"Hobbies, Toys, & Games",
            "type":"Retail Goods"
        }
    ],
    "sg:phone":"+1 519 632 8618",
    "sg:postcode":"N0B 1E0",
    "sg:province":"ON",
    "sg:tags":[
        "equipment",
        "ceramic",
        "supply"
    ],
    "wof:name":"D's Ceramic Ctr",
    "wof:placetype":"venue"
},
  "geometry": {"coordinates":[-80.4493255615,43.2858314514],"type":"Point"}
}