{
  "type": "Feature",
  "properties": {
    "addr:full":"5 Lakeshore Niagara on the Lake ON L0S 1J0",
    "addr:housenumber":"5",
    "addr:postcode":"l0s 1j0",
    "addr:street":"Lakeshore;On",
    "iso:country":"CA",
    "sg:address":"5 Lakeshore",
    "sg:city":"Niagara on the Lake",
    "sg:classifiers":[
        {
            "category":"Home & Garden",
            "subcategory":"Garden Supply",
            "type":"Retail Goods"
        }
    ],
    "sg:phone":"+1 905 938 0804",
    "sg:postcode":"L0S 1J0",
    "sg:province":"ON",
    "sg:tags":[
        "center"
    ],
    "wof:name":"Eileen's Garden",
    "wof:placetype":"venue"
},
  "geometry": {"coordinates":[-79.200554,43.219074],"type":"Point"}
}