{
  "type": "Feature",
  "properties": {
    "addr:full":"1679 Boul Saint-Antoine Saint-Jerome QC J7Z 7M1",
    "addr:housenumber":"1679",
    "addr:postcode":"j7z 7m1",
    "addr:street":"Boul Saint-Antoine",
    "iso:country":"CA",
    "sg:address":"1679 Boul Saint-Antoine",
    "sg:city":"Saint-Jerome",
    "sg:classifiers":[
        {
            "category":"Building & Trades",
            "subcategory":"Electrical",
            "type":"Services"
        }
    ],
    "sg:phone":"+1 450 438 0911",
    "sg:postcode":"J7Z 7M1",
    "sg:province":"QC",
    "sg:tags":[
        "electric",
        "contractor"
    ],
    "wof:name":"Installations Electriques Inc",
    "wof:placetype":"venue"
},
  "geometry": {"coordinates":[-73.96896362299999,45.7737197876],"type":"Point"}
}