{
  "type": "Feature",
  "properties": {
    "addr:full":"Whitehorse YT Y1A 2C5",
    "addr:postcode":"y1a 2c5",
    "iso:country":"CA",
    "sg:city":"Whitehorse",
    "sg:classifiers":[
        {
            "category":"Museum",
            "type":"Entertainment"
        }
    ],
    "sg:phone":"+1 867 668 2695",
    "sg:postcode":"Y1A 2C5",
    "sg:province":"YT",
    "sg:tags":[
        "organization",
        "arts",
        "information"
    ],
    "wof:name":"Society of Yukon Artists",
    "wof:placetype":"venue"
},
  "geometry": {"coordinates":[-135.055175781,60.7201576233],"type":"Point"}
}