{
  "type": "Feature",
  "properties": {
    "addr:full":"70 Morven Dr West Vancouver BC V7S 1B2",
    "addr:housenumber":"70",
    "addr:postcode":"v7s 1b2",
    "addr:street":"Morven Dr",
    "iso:country":"CA",
    "sg:address":"70 Morven Dr",
    "sg:city":"West Vancouver",
    "sg:classifiers":[
        {
            "category":"Education",
            "subcategory":"School",
            "type":"Public Place"
        }
    ],
    "sg:phone":"+1 604 925 3331",
    "sg:postcode":"V7S 1B2",
    "sg:province":"BC",
    "wof:name":"Collingwood School",
    "wof:placetype":"venue"
},
  "geometry": {"coordinates":[-123.11930099999999,49.361145],"type":"Point"}
}