{
  "type": "Feature",
  "properties": {
    "addr:full":"285 Rue DE L'Eglise # 100 Charlesbourg QC G2N 1E3",
    "addr:housenumber":"285",
    "addr:postcode":"g2n 1e3",
    "addr:street":"Rue De L'Eglise # 100",
    "iso:country":"CA",
    "sg:address":"285 Rue DE L'Eglise # 100",
    "sg:city":"Charlesbourg",
    "sg:classifiers":[
        {
            "category":"Professional",
            "subcategory":"Business Services",
            "type":"Services"
        }
    ],
    "sg:phone":"+1 418 849 4421",
    "sg:postcode":"G2N 1E3",
    "sg:province":"QC",
    "sg:tags":[
        "arbitration"
    ],
    "wof:name":"Villeneuve, Elise",
    "wof:placetype":"venue"
},
  "geometry": {"coordinates":[-71.341393,46.911499],"type":"Point"}
}