{
  "type": "Feature",
  "properties": {
    "addr:full":"316 Hector Dougall Way Thunder Bay ON P7E 6M6",
    "addr:housenumber":"316",
    "addr:postcode":"p7e 6m6",
    "addr:street":"Hector Dougall Way",
    "iso:country":"CA",
    "sg:address":"316 Hector Dougall Way",
    "sg:city":"Thunder Bay",
    "sg:classifiers":[
        {
            "category":"Airport",
            "type":"Transportation"
        }
    ],
    "sg:phone":"+1 807 475 5915",
    "sg:postcode":"P7E 6M6",
    "sg:province":"ON",
    "sg:tags":[
        "aircraft",
        "maintenance"
    ],
    "wof:name":"Maintair Aviation Svc Ltd",
    "wof:placetype":"venue"
},
  "geometry": {"coordinates":[-89.3156738281,48.370552063],"type":"Point"}
}