{
  "type": "Feature",
  "properties": {
    "addr:full":"5505 Boul Saint-Laurent # 3010 Montreal QC H2T 1S6",
    "addr:housenumber":"5505",
    "addr:postcode":"h2t 1s6",
    "addr:street":"Boul Saint-Laurent # 3010",
    "iso:country":"CA",
    "sg:address":"5505 Boul Saint-Laurent # 3010",
    "sg:city":"Montreal",
    "sg:classifiers":[
        {
            "category":"Education",
            "subcategory":"School",
            "type":"Public Place"
        }
    ],
    "sg:phone":"+1 514 271 2244",
    "sg:postcode":"H2T 1S6",
    "sg:province":"QC",
    "wof:name":"Ecole Du Show Business",
    "wof:placetype":"venue"
},
  "geometry": {"coordinates":[-73.5984573364,45.5257911682],"type":"Point"}
}