{
  "type": "Feature",
  "properties": {
    "addr:full":"1771 Cedar Rd Nanaimo BC V9X 1L5",
    "addr:housenumber":"1771",
    "addr:postcode":"v9x 1l5",
    "addr:street":"Cedar Rd",
    "iso:country":"CA",
    "sg:address":"1771 Cedar Rd",
    "sg:city":"Nanaimo",
    "sg:classifiers":[
        {
            "category":"Food & Beverages",
            "subcategory":"Groceries & Convenience Stores",
            "type":"Retail Goods"
        }
    ],
    "sg:phone":"+1 250 722 3232",
    "sg:postcode":"V9X 1L5",
    "sg:province":"BC",
    "sg:tags":[
        "grocer"
    ],
    "wof:name":"Cedar General Store",
    "wof:placetype":"venue"
},
  "geometry": {"coordinates":[-123.877289,49.11507],"type":"Point"}
}