{
  "type": "Feature",
  "properties": {
    "iso:country":"CA",
    "sg:address":"464 Ch Duchenier",
    "sg:city":"Saint-Narcisse-DE-Rimouski",
    "sg:classifiers":[
        {
            "category":"Banks & Credit Unions",
            "subcategory":"Bank",
            "type":"Services"
        }
    ],
    "sg:phone":"+1 418 735 2815",
    "sg:postcode":"G0K 1S0",
    "sg:province":"QC",
    "wof:name":"Caisses Desjardins",
    "wof:placetype":"venue"
},
  "geometry": {"coordinates":[-68.43604278559999,48.289150238],"type":"Point"}
}