{
  "type": "Feature",
  "properties": {
    "addr:full":"Richmond BC V6Y 4B6",
    "addr:postcode":"v6y 4b6",
    "iso:country":"CA",
    "sg:city":"Richmond",
    "sg:classifiers":[
        {
            "category":"Health Services",
            "subcategory":"Doctor",
            "type":"Services"
        }
    ],
    "sg:phone":"+1 604 273 6641",
    "sg:postcode":"V6Y 4B6",
    "sg:province":"BC",
    "sg:tags":[
        "physician",
        "surgeon"
    ],
    "wof:name":"Bhopal, Jaswant MD",
    "wof:placetype":"venue"
},
  "geometry": {"coordinates":[-123.13203430199999,49.1690063477],"type":"Point"}
}