{
  "type": "Feature",
  "properties": {
    "addr:full":"898 Henderson Hwy Winnipeg MB R2K 3T4",
    "addr:housenumber":"898",
    "addr:postcode":"r2k 3t4",
    "addr:street":"Henderson Hwy",
    "iso:country":"CA",
    "sg:address":"898 Henderson Hwy",
    "sg:city":"Winnipeg",
    "sg:classifiers":[
        {
            "category":"Organizations",
            "subcategory":"Religious Organization",
            "type":"Services"
        }
    ],
    "sg:phone":"+1 204 661 2579",
    "sg:postcode":"R2K 3T4",
    "sg:province":"MB",
    "sg:tags":[
        "church"
    ],
    "wof:name":"John Black Memorial United Chr",
    "wof:placetype":"venue"
},
  "geometry": {"coordinates":[-97.09963999999999,49.932495],"type":"Point"}
}