{
  "type": "Feature",
  "properties": {
    "iso:country":"CA",
    "sg:city":"Scarborough",
    "sg:classifiers":[
        {
            "category":"Freight",
            "type":"Transportation"
        }
    ],
    "sg:phone":"+1 416 335 7307",
    "sg:postcode":"M1X 1B1",
    "sg:province":"ON",
    "sg:tags":[
        "mover"
    ],
    "wof:name":"Ace Moving & Installations Inc",
    "wof:placetype":"venue"
},
  "geometry": {"coordinates":[-79.233086,43.818848],"type":"Point"}
}