{
  "type": "Feature",
  "properties": {
    "addr:full":"1197 Lawrence Ave W North York ON M6A 1E2",
    "addr:housenumber":"1197",
    "addr:postcode":"m6a 1e2",
    "addr:street":"Lawrence Ave W",
    "iso:country":"CA",
    "sg:address":"1197 Lawrence Ave W",
    "sg:city":"North York",
    "sg:classifiers":[
        {
            "category":"Retail",
            "subcategory":"Auto Repair",
            "type":"Services"
        }
    ],
    "sg:phone":"+1 416 783 7329",
    "sg:postcode":"M6A 1E2",
    "sg:province":"ON",
    "sg:tags":[
        "repairing",
        "automobile"
    ],
    "wof:name":"Ital Motors",
    "wof:placetype":"venue"
},
  "geometry": {"coordinates":[-79.467781,43.711079],"type":"Point"}
}