{
  "type": "Feature",
  "properties": {
    "addr:full":"334 Boul Des Ruisseaux Mont-Laurier QC J9L 3G6",
    "addr:housenumber":"334",
    "addr:postcode":"j9l 3g6",
    "addr:street":"Boul Des Ruisseaux",
    "iso:country":"CA",
    "sg:address":"334 Boul Des Ruisseaux",
    "sg:city":"Mont-Laurier",
    "sg:classifiers":[
        {
            "category":"Building & Trades",
            "subcategory":"Landscaping Services",
            "type":"Services"
        }
    ],
    "sg:phone":"+1 819 623 4945",
    "sg:postcode":"J9L 3G6",
    "sg:province":"QC",
    "sg:tags":[
        "landscape",
        "contractor"
    ],
    "wof:name":"Depanneur Des Ruisseaux Inc",
    "wof:placetype":"venue"
},
  "geometry": {"coordinates":[-75.52572600000001,46.552368],"type":"Point"}
}