{
  "type": "Feature",
  "properties": {
    "iso:country":"CA",
    "sg:address":"52 Seguin St",
    "sg:city":"Parry Sound",
    "sg:classifiers":[
        {
            "category":"Government",
            "subcategory":"Office",
            "type":"Public Place"
        }
    ],
    "sg:phone":"+1 705 746 2101",
    "sg:postcode":"P2A 1B4",
    "sg:province":"ON",
    "sg:tags":[
        "village"
    ],
    "wof:name":"Parry Sound Municipal Office",
    "wof:placetype":"venue"
},
  "geometry": {"coordinates":[-80.0353012085,45.3435211182],"type":"Point"}
}