{
  "type": "Feature",
  "properties": {
    "addr:full":"Scarborough ON M1S 4Z6",
    "addr:postcode":"m1s 4z6",
    "iso:country":"CA",
    "sg:city":"Scarborough",
    "sg:classifiers":[
        {
            "category":"Food & Beverages",
            "subcategory":"Bakery",
            "type":"Retail Goods"
        }
    ],
    "sg:phone":"+1 416 297 5907",
    "sg:postcode":"M1S 4Z6",
    "sg:province":"ON",
    "sg:tags":[
        "baker"
    ],
    "wof:name":"Golden Bakery & Deli",
    "wof:placetype":"venue"
},
  "geometry": {"coordinates":[-79.256828,43.810177],"type":"Point"}
}