{
  "type": "Feature",
  "properties": {
    "addr:full":"6455 Macleod Trail SW #1113 Calgary AB T2H 0K3",
    "addr:housenumber":"6455",
    "addr:postcode":"t2h 0k3",
    "addr:street":"Macleod Trail Sw # 1113",
    "iso:country":"CA",
    "sg:address":"6455 Macleod Trail SW #1113",
    "sg:city":"Calgary",
    "sg:classifiers":[
        {
            "category":"Shopping",
            "subcategory":"Clothing, Apparel, & Fashions",
            "type":"Retail Goods"
        }
    ],
    "sg:phone":"+1 403 255 5510",
    "sg:postcode":"T2H 0K3",
    "sg:province":"AB",
    "sg:tags":[
        "jean"
    ],
    "wof:name":"Below the Belt Store Ltd",
    "wof:placetype":"venue"
},
  "geometry": {"coordinates":[-114.071830749,50.9961624146],"type":"Point"}
}