{
  "type": "Feature",
  "properties": {
    "addr:full":"200 Hwy 14 Perdue SK S0K 3C0",
    "addr:housenumber":"200",
    "addr:postcode":"s0k 3c0",
    "addr:street":"Hwy 14 Perdue",
    "iso:country":"CA",
    "sg:address":"200 Hwy 14",
    "sg:city":"Perdue",
    "sg:classifiers":[
        {
            "category":"Recreation",
            "type":"Entertainment"
        }
    ],
    "sg:phone":"+1 306 237 4639",
    "sg:postcode":"S0K 3C0",
    "sg:province":"SK",
    "sg:tags":[
        "oil",
        "lottery",
        "agent"
    ],
    "wof:name":"Feudal CO-OP",
    "wof:placetype":"venue"
},
  "geometry": {"coordinates":[-107.538696289,52.0596656799],"type":"Point"}
}