{
  "type": "Feature",
  "properties": {
    "addr:full":"12740 Boul Industriel Pointe-Aux-Trembles QC H1A 3V2",
    "addr:housenumber":"12740",
    "addr:postcode":"h1a 3v2",
    "addr:street":"Boul Industriel",
    "iso:country":"CA",
    "sg:address":"12740 Boul Industriel",
    "sg:city":"Pointe-Aux-Trembles",
    "sg:classifiers":[
        {
            "category":"Wholesale",
            "subcategory":"Hardware",
            "type":"Manufacturing & Wholesale Goods"
        }
    ],
    "sg:phone":"+1 514 498 4114",
    "sg:postcode":"H1A 3V2",
    "sg:province":"QC",
    "sg:tags":[
        "refrigerating"
    ],
    "wof:name":"Refrigeration Superieure Inc",
    "wof:placetype":"venue"
},
  "geometry": {"coordinates":[-73.51612091059999,45.6552810669],"type":"Point"}
}