{
  "type": "Feature",
  "properties": {
    "addr:full":"9940 Elbow Dr SW Calgary AB T2W 1E5",
    "addr:housenumber":"9940",
    "addr:postcode":"t2w 1e5",
    "addr:street":"Elbow Dr Sw",
    "iso:country":"CA",
    "sg:address":"9940 Elbow Dr SW",
    "sg:city":"Calgary",
    "sg:classifiers":[
        {
            "category":"Retail",
            "subcategory":"Auto Repair",
            "type":"Services"
        }
    ],
    "sg:phone":"+1 403 281 1303",
    "sg:postcode":"T2W 1E5",
    "sg:province":"AB",
    "sg:tags":[
        "repairing",
        "automobile"
    ],
    "wof:name":"Kingsboro Auto Svc Ltd",
    "wof:placetype":"venue"
},
  "geometry": {"coordinates":[-114.084587,50.963997],"type":"Point"}
}