{
  "type": "Feature",
  "properties": {
    "iso:country":"CA",
    "sg:address":"330 Rang DE LA Montagne",
    "sg:city":"Mont-Saint-Gregoire",
    "sg:classifiers":[
        {
            "category":"Manufacturing",
            "subcategory":"Food",
            "type":"Manufacturing & Wholesale Goods"
        }
    ],
    "sg:phone":"+1 450 358 4868",
    "sg:postcode":"J0J 1K0",
    "sg:province":"QC",
    "sg:tags":[
        "winery"
    ],
    "wof:name":"Vignoble Clos DE LA Montagne",
    "wof:placetype":"venue"
},
  "geometry": {"coordinates":[-73.15776062010001,45.3419113159],"type":"Point"}
}