{
  "type": "Feature",
  "properties": {
    "addr:full":"172 Church St Penetanguishene ON L9M 1E6",
    "addr:housenumber":"172",
    "addr:postcode":"l9m 1e6",
    "addr:street":"Church St",
    "iso:country":"CA",
    "sg:address":"172 Church St",
    "sg:city":"Penetanguishene",
    "sg:classifiers":[
        {
            "category":"Building & Trades",
            "subcategory":"Landscaping Services",
            "type":"Services"
        }
    ],
    "sg:phone":"+1 705 549 5808",
    "sg:postcode":"L9M 1E6",
    "sg:province":"ON",
    "sg:tags":[
        "landscape",
        "contractor"
    ],
    "wof:name":"Maurice Landscaping",
    "wof:placetype":"venue"
},
  "geometry": {"coordinates":[-79.9266281128,44.7849960327],"type":"Point"}
}