{
  "type": "Feature",
  "properties": {
    "addr:full":"145 Silvercreek Pky N Guelph ON N1H 3T2",
    "addr:housenumber":"145",
    "addr:postcode":"n1h 3t2",
    "addr:street":"Silvercreek Pky N",
    "iso:country":"CA",
    "sg:address":"145 Silvercreek Pky N",
    "sg:city":"Guelph",
    "sg:classifiers":[
        {
            "category":"Shopping",
            "subcategory":"Clothing, Apparel, & Fashions",
            "type":"Retail Goods"
        }
    ],
    "sg:phone":"+1 519 829 3012",
    "sg:postcode":"N1H 3T2",
    "sg:province":"ON",
    "wof:name":"Reitmans",
    "wof:placetype":"venue"
},
  "geometry": {"coordinates":[-80.2806777954,43.5403404236],"type":"Point"}
}