{
  "type": "Feature",
  "properties": {
    "addr:full":"2077 Rue Principale Saint-Gilles QC G0S 2P0",
    "addr:housenumber":"2077",
    "addr:postcode":"g0s 2p0",
    "addr:street":"Rue Principale",
    "iso:country":"CA",
    "sg:address":"2077 Rue Principale",
    "sg:city":"Saint-Gilles",
    "sg:classifiers":[
        {
            "category":"Personal",
            "subcategory":"Beauty Salon",
            "type":"Services"
        }
    ],
    "sg:phone":"+1 418 888 5058",
    "sg:postcode":"G0S 2P0",
    "sg:province":"QC",
    "wof:name":"Salon France Montminy",
    "wof:placetype":"venue"
},
  "geometry": {"coordinates":[-71.355125,46.504421],"type":"Point"}
}