{
  "type": "Feature",
  "properties": {
    "addr:full":"Winnipeg MB R2G 0M3",
    "addr:postcode":"r2g 0m3",
    "iso:country":"CA",
    "sg:city":"Winnipeg",
    "sg:classifiers":[
        {
            "category":"Real Estate",
            "subcategory":"Real Estate Operator",
            "type":"Services"
        }
    ],
    "sg:phone":"+1 204 940 3487",
    "sg:postcode":"R2G 0M3",
    "sg:province":"MB",
    "sg:tags":[
        "apartment"
    ],
    "wof:name":"L-B Towers",
    "wof:placetype":"venue"
},
  "geometry": {"coordinates":[-97.07862091059999,49.9379234314],"type":"Point"}
}