{
  "type": "Feature",
  "properties": {
    "addr:full":"Napierville QC J0J 1L0",
    "addr:postcode":"j0j 1l0",
    "iso:country":"CA",
    "sg:city":"Napierville",
    "sg:classifiers":[
        {
            "category":"Personal",
            "subcategory":"Beauty Salon",
            "type":"Services"
        }
    ],
    "sg:phone":"+1 450 245 3325",
    "sg:postcode":"J0J 1L0",
    "sg:province":"QC",
    "wof:name":"Salon Diane",
    "wof:placetype":"venue"
},
  "geometry": {"coordinates":[-73.4156417847,45.1939888],"type":"Point"}
}