{
  "type": "Feature",
  "properties": {
    "addr:full":"285 Rue Principale E Farnham QC J2N 1L5",
    "addr:housenumber":"285",
    "addr:postcode":"j2n 1l5",
    "addr:street":"Rue Principale E",
    "iso:country":"CA",
    "sg:address":"285 Rue Principale E",
    "sg:city":"Farnham",
    "sg:classifiers":[
        {
            "category":"Health Services",
            "subcategory":"Optometrist",
            "type":"Services"
        }
    ],
    "sg:phone":"+1 450 293 3221",
    "sg:postcode":"J2N 1L5",
    "sg:province":"QC",
    "wof:name":"Centre Optometrique",
    "wof:placetype":"venue"
},
  "geometry": {"coordinates":[-72.976944,45.284306],"type":"Point"}
}