{
  "type": "Feature",
  "properties": {
    "iso:country":"CA",
    "sg:city":"London",
    "sg:classifiers":[
        {
            "category":"Restaurant",
            "type":"Food & Drink"
        }
    ],
    "sg:phone":"+1 519 652 6130",
    "sg:postcode":"N6L 1C6",
    "sg:province":"ON",
    "wof:name":"Coffee Plus",
    "wof:placetype":"venue"
},
  "geometry": {"coordinates":[-81.266464,42.920132],"type":"Point"}
}