{
  "type": "Feature",
  "properties": {
    "addr:full":"Burlington ON L7N 3N1",
    "addr:postcode":"l7n 3n1",
    "iso:country":"CA",
    "sg:city":"Burlington",
    "sg:classifiers":[
        {
            "category":"Wholesale",
            "subcategory":"Chemicals & Plastics",
            "type":"Manufacturing & Wholesale Goods"
        }
    ],
    "sg:phone":"+1 905 639 9700",
    "sg:postcode":"L7N 3N1",
    "sg:province":"ON",
    "wof:name":"Storchem Inc",
    "wof:placetype":"venue"
},
  "geometry": {"coordinates":[-79.788071,43.360313],"type":"Point"}
}