{
  "type": "Feature",
  "properties": {
    "addr:full":"40 Alderney Dr Dartmouth NS B2Y 2N5",
    "addr:housenumber":"40",
    "addr:postcode":"b2y 2n5",
    "addr:street":"Alderney Dr",
    "iso:country":"CA",
    "sg:address":"40 Alderney Dr",
    "sg:city":"Dartmouth",
    "sg:classifiers":[
        {
            "category":"Parking",
            "type":"Transportation"
        }
    ],
    "sg:phone":"+1 902 465 8642",
    "sg:postcode":"B2Y 2N5",
    "sg:province":"NS",
    "sg:tags":[
        "garage"
    ],
    "wof:name":"Alderney Gate Parking",
    "wof:placetype":"venue"
},
  "geometry": {"coordinates":[-63.5698318481,44.6652374268],"type":"Point"}
}