{
  "type": "Feature",
  "properties": {
    "iso:country":"CA",
    "sg:address":"64 Racine Rd",
    "sg:city":"Etobicoke",
    "sg:classifiers":[
        {
            "category":"Retail",
            "subcategory":"Auto Repair",
            "type":"Services"
        }
    ],
    "sg:phone":"+1 416 740 1063",
    "sg:postcode":"M9W 2Z7",
    "sg:province":"ON",
    "sg:tags":[
        "repairing",
        "automobile",
        "tire"
    ],
    "wof:name":"Delta Tire",
    "wof:placetype":"venue"
},
  "geometry": {"coordinates":[-79.5796585083,43.7170524597],"type":"Point"}
}