{
  "type": "Feature",
  "properties": {
    "addr:full":"2608 7 Ave Fort Macleod AB T0L 0Z0",
    "addr:housenumber":"2608",
    "addr:postcode":"t0l 0z0",
    "addr:street":"7 Ave Fort",
    "iso:country":"CA",
    "sg:address":"2608 7 Ave",
    "sg:city":"Fort Macleod",
    "sg:classifiers":[
        {
            "category":"Organizations",
            "subcategory":"Religious Organization",
            "type":"Services"
        }
    ],
    "sg:phone":"+1 403 553 4770",
    "sg:postcode":"T0L 0Z0",
    "sg:province":"AB",
    "sg:tags":[
        "church"
    ],
    "wof:name":"Reformed Congregation Church",
    "wof:placetype":"venue"
},
  "geometry": {"coordinates":[-113.394592,49.727673],"type":"Point"}
}