{
  "type": "Feature",
  "properties": {
    "addr:full":"1225 Lake Shore Blvd W Toronto ON M6K 3C1",
    "addr:housenumber":"1225",
    "addr:postcode":"m6k 3c1",
    "addr:street":"Lake Shore Blvd W",
    "iso:country":"CA",
    "sg:address":"1225 Lake Shore Blvd W",
    "sg:city":"Toronto",
    "sg:classifiers":[
        {
            "category":"Personal",
            "type":"Services"
        }
    ],
    "sg:phone":"+1 416 532 2803",
    "sg:postcode":"M6K 3C1",
    "sg:province":"ON",
    "sg:tags":[
        "recreation",
        "program",
        "amusement",
        "fitness",
        "exercise",
        "physical"
    ],
    "wof:name":"Argonaut Rowing Club",
    "wof:placetype":"venue"
},
  "geometry": {"coordinates":[-79.4355010986,43.6322975159],"type":"Point"}
}