{
  "type": "Feature",
  "properties": {
    "addr:full":"2678 Rue Laurier Rockland ON K4K 1A2",
    "addr:housenumber":"2678",
    "addr:postcode":"k4k 1a2",
    "addr:street":"Rue Laurier",
    "iso:country":"CA",
    "sg:address":"2678 Rue Laurier",
    "sg:city":"Rockland",
    "sg:classifiers":[
        {
            "category":"Home & Garden",
            "subcategory":"Building Materials",
            "type":"Retail Goods"
        }
    ],
    "sg:phone":"+1 613 446 4772",
    "sg:postcode":"K4K 1A2",
    "sg:province":"ON",
    "sg:tags":[
        "hardware"
    ],
    "wof:name":"Bytown Lumber Inc",
    "wof:placetype":"venue"
},
  "geometry": {"coordinates":[-75.29954499999999,45.542965],"type":"Point"}
}