{
  "type": "Feature",
  "properties": {
    "addr:full":"3055 Boul DE L'Assomption Montreal QC H1N 2H1",
    "addr:housenumber":"3055",
    "addr:postcode":"h1n 2h1",
    "addr:street":"Boul De L'Assomption",
    "iso:country":"CA",
    "sg:address":"3055 Boul DE L'Assomption",
    "sg:city":"Montreal",
    "sg:classifiers":[
        {
            "category":"Professional",
            "subcategory":"Lawyer & Legal Services",
            "type":"Services"
        }
    ],
    "sg:phone":"+1 514 899 5375",
    "sg:postcode":"H1N 2H1",
    "sg:province":"QC",
    "sg:tags":[
        "attorney"
    ],
    "wof:name":"Mannella & Assoc",
    "wof:placetype":"venue"
},
  "geometry": {"coordinates":[-73.548103,45.569508],"type":"Point"}
}