{
  "type": "Feature",
  "properties": {
    "addr:full":"310 Hall St Nelson BC V1L 1Y8",
    "addr:housenumber":"310",
    "addr:postcode":"bc v1l 1y8",
    "addr:street":"Hall St",
    "iso:country":"CA",
    "sg:address":"310 Hall St",
    "sg:city":"Nelson",
    "sg:classifiers":[
        {
            "category":"Health Services",
            "subcategory":"Doctor",
            "type":"Services"
        }
    ],
    "sg:phone":"+1 250 354 4354",
    "sg:postcode":"V1L 1Y8",
    "sg:province":"BC",
    "sg:tags":[
        "dentist"
    ],
    "wof:name":"Bibby, Kathryn J DDS",
    "wof:placetype":"venue"
},
  "geometry": {"coordinates":[-117.292724609,49.494430542],"type":"Point"}
}