{
  "type": "Feature",
  "properties": {
    "addr:full":"59 Montclair Dr Woodstock ON N4V 1C5",
    "addr:housenumber":"59",
    "addr:postcode":"n4v 1c5",
    "addr:street":"Montclair Dr",
    "iso:country":"CA",
    "sg:address":"59 Montclair Dr",
    "sg:city":"Woodstock",
    "sg:classifiers":[
        {
            "category":"Manufacturing",
            "subcategory":"Electronics",
            "type":"Manufacturing & Wholesale Goods"
        }
    ],
    "sg:phone":"+1 519 539 4891",
    "sg:postcode":"N4V 1C5",
    "sg:province":"ON",
    "sg:tags":[
        "electronic",
        "capacitor"
    ],
    "wof:name":"Dura Cap Intl Inc",
    "wof:placetype":"venue"
},
  "geometry": {"coordinates":[-80.73613,43.117241],"type":"Point"}
}