{
  "type": "Feature",
  "properties": {
    "iso:country":"CA",
    "sg:address":"100 Beaurepaire Dr",
    "sg:city":"Beaconsfield",
    "sg:classifiers":[
        {
            "category":"Retail",
            "subcategory":"Auto Rental",
            "type":"Services"
        }
    ],
    "sg:phone":"+1 514 426 3310",
    "sg:postcode":"H9W 3B5",
    "sg:province":"QC",
    "sg:tags":[
        "renting",
        "truck",
        "leasing"
    ],
    "wof:name":"U-Haul Cie Ltee",
    "wof:placetype":"venue"
},
  "geometry": {"coordinates":[-73.84535980219999,45.4342346191],"type":"Point"}
}