{
  "type": "Feature",
  "properties": {
    "addr:full":"Longueuil QC J4J 5H4",
    "addr:postcode":"j4j 5h4",
    "iso:country":"CA",
    "sg:city":"Longueuil",
    "sg:classifiers":[
        {
            "category":"Professional",
            "subcategory":"Accounting & Tax Preparation",
            "type":"Services"
        }
    ],
    "sg:phone":"+1 514 649 1544",
    "sg:postcode":"J4J 5H4",
    "sg:province":"QC",
    "sg:tags":[
        "accountant"
    ],
    "wof:name":"Jutras & Giroux",
    "wof:placetype":"venue"
},
  "geometry": {"coordinates":[-73.4818572998,45.5385322571],"type":"Point"}
}