{
  "type": "Feature",
  "properties": {
    "addr:full":"100 Mountain St Strasbourg SK S0G 4V0",
    "addr:housenumber":"100",
    "addr:postcode":"s0g 4v0",
    "addr:street":"Mountain St",
    "iso:country":"CA",
    "sg:address":"100 Mountain St",
    "sg:city":"Strasbourg",
    "sg:classifiers":[
        {
            "category":"Travel",
            "subcategory":"Hotels & Motels",
            "type":"Entertainment"
        }
    ],
    "sg:phone":"+1 306 725 3630",
    "sg:postcode":"S0G 4V0",
    "sg:province":"SK",
    "wof:name":"Royal Hotel",
    "wof:placetype":"venue"
},
  "geometry": {"coordinates":[-104.952003479,51.0706253052],"type":"Point"}
}