{
  "type": "Feature",
  "properties": {
    "iso:country":"CA",
    "sg:address":"500 Donald St E",
    "sg:city":"Thunder Bay",
    "sg:classifiers":[
        {
            "category":"Government",
            "subcategory":"Office",
            "type":"Public Place"
        }
    ],
    "sg:phone":"+1 807 625 2609",
    "sg:postcode":"P7E 5V3",
    "sg:province":"ON",
    "sg:tags":[
        "village"
    ],
    "wof:name":"City Hall",
    "wof:placetype":"venue"
},
  "geometry": {"coordinates":[-89.2458190918,48.3823051453],"type":"Point"}
}