{
  "type": "Feature",
  "properties": {
    "addr:full":"3737 Roger St Port Alberni BC V9Y 8J4",
    "addr:housenumber":"3737",
    "addr:postcode":"v9y 8j4",
    "addr:street":"Roger St",
    "iso:country":"CA",
    "sg:address":"3737 Roger St",
    "sg:city":"Port Alberni",
    "sg:classifiers":[
        {
            "category":"Recreation",
            "type":"Entertainment"
        }
    ],
    "sg:phone":"+1 250 720 8999",
    "sg:postcode":"V9Y 8J4",
    "sg:province":"BC",
    "sg:tags":[
        "skating",
        "instruction"
    ],
    "wof:name":"Mount Arrowsmith Skating Club",
    "wof:placetype":"venue"
},
  "geometry": {"coordinates":[-124.79338836700001,49.2543792725],"type":"Point"}
}