{
  "type": "Feature",
  "properties": {
    "addr:full":"5400 Dixie Rd Mississauga ON L4W 4T4",
    "addr:housenumber":"5400",
    "addr:postcode":"l4w 4t4",
    "addr:street":"Dixie Rd",
    "iso:country":"CA",
    "sg:address":"5400 Dixie Rd",
    "sg:city":"Mississauga",
    "sg:classifiers":[
        {
            "category":"Personal",
            "subcategory":"Hair Removal",
            "type":"Services"
        }
    ],
    "sg:phone":"+1 905 602 1295",
    "sg:postcode":"L4W 4T4",
    "sg:province":"ON",
    "sg:tags":[
        "removing",
        "salon",
        "beauty"
    ],
    "wof:name":"Stars Beauty Ctr Inc",
    "wof:placetype":"venue"
},
  "geometry": {"coordinates":[-79.6317443848,43.6434402466],"type":"Point"}
}