{
  "type": "Feature",
  "properties": {
    "addr:full":"Calgary AB T2E 7A6",
    "addr:postcode":"t2e 7a6",
    "iso:country":"CA",
    "sg:city":"Calgary",
    "sg:classifiers":[
        {
            "category":"Professional",
            "subcategory":"Lawyer & Legal Services",
            "type":"Services"
        }
    ],
    "sg:phone":"+1 403 250 7100",
    "sg:postcode":"T2E 7A6",
    "sg:province":"AB",
    "sg:tags":[
        "attorney"
    ],
    "wof:name":"Everard & Kubitz",
    "wof:placetype":"venue"
},
  "geometry": {"coordinates":[-114.010215759,51.0771255493],"type":"Point"}
}