{
  "type": "Feature",
  "properties": {
    "addr:full":"3505 Rang Du Haut-Saint-Franco Laval QC H7E 4P2",
    "addr:housenumber":"3505",
    "addr:postcode":"h7e 4p2",
    "addr:street":"Rang Du Haut-Saint-Franco",
    "iso:country":"CA",
    "sg:address":"3505 Rang Du Haut-Saint-Franco",
    "sg:city":"Laval",
    "sg:classifiers":[
        {
            "category":"Freight",
            "type":"Transportation"
        }
    ],
    "sg:phone":"+1 450 661 2083",
    "sg:postcode":"H7E 4P2",
    "sg:province":"QC",
    "sg:tags":[
        "trucking"
    ],
    "wof:name":"Alain Bergeron Transport",
    "wof:placetype":"venue"
},
  "geometry": {"coordinates":[-73.691467,45.62421],"type":"Point"}
}