{
  "type": "Feature",
  "properties": {
    "addr:full":"2075 Tryon Rd RR 30 Sidney BC V8L 3X9",
    "addr:housenumber":"2075;30",
    "addr:postcode":"v8l 3x9",
    "addr:street":"Tryon Rd",
    "iso:country":"CA",
    "sg:address":"2075 Tryon Rd RR 30",
    "sg:city":"Sidney",
    "sg:classifiers":[
        {
            "category":"Recreation",
            "subcategory":"Marina",
            "type":"Entertainment"
        }
    ],
    "sg:phone":"+1 250 656 1221",
    "sg:postcode":"V8L 3X9",
    "sg:province":"BC",
    "sg:tags":[
        "repair",
        "marine"
    ],
    "wof:name":"Tsehum Marine Ltd",
    "wof:placetype":"venue"
},
  "geometry": {"coordinates":[-123.398422,48.650215],"type":"Point"}
}