{
  "type": "Feature",
  "properties": {
    "iso:country":"CA",
    "sg:address":"911 Av Ogilvy",
    "sg:city":"Montreal",
    "sg:classifiers":[
        {
            "category":"Professional",
            "subcategory":"Lawyer & Legal Services",
            "type":"Services"
        }
    ],
    "sg:phone":"+1 514 495 8080",
    "sg:postcode":"H3N 1P2",
    "sg:province":"QC",
    "sg:tags":[
        "naturalization",
        "immigration"
    ],
    "wof:name":"Immigration Consultants",
    "wof:placetype":"venue"
},
  "geometry": {"coordinates":[-73.6272888184,45.5260047913],"type":"Point"}
}