{
  "type": "Feature",
  "properties": {
    "addr:full":"265 Dundas St E Belleville ON K8N 5A9",
    "addr:housenumber":"265",
    "addr:postcode":"k8n 5a9",
    "addr:street":"Dundas St E",
    "iso:country":"CA",
    "sg:address":"265 Dundas St E",
    "sg:city":"Belleville",
    "sg:classifiers":[
        {
            "category":"Health Services",
            "subcategory":"Hospital",
            "type":"Services"
        }
    ],
    "sg:phone":"+1 613 969 7400",
    "sg:postcode":"K8N 5A9",
    "sg:province":"ON",
    "wof:name":"Quinte Health Care Corp",
    "wof:placetype":"venue"
},
  "geometry": {"coordinates":[-77.36492919920001,44.1635780334],"type":"Point"}
}