{
  "type": "Feature",
  "properties": {
    "addr:full":"4885 Rte Uniforet L'Ascension-DE-Notre-Seigneur QC G0W 1Y0",
    "addr:housenumber":"4885",
    "addr:postcode":"g0w 1y0",
    "addr:street":"Rte Uniforet",
    "iso:country":"CA",
    "sg:address":"4885 Rte Uniforet",
    "sg:city":"L'Ascension-DE-Notre-Seigneur",
    "sg:classifiers":[
        {
            "category":"Restaurant",
            "type":"Food & Drink"
        }
    ],
    "sg:phone":"+1 418 347 4747",
    "sg:postcode":"G0W 1Y0",
    "sg:province":"QC",
    "wof:name":"Restaurant Jos Bonka",
    "wof:placetype":"venue"
},
  "geometry": {"coordinates":[-71.6514205933,48.7401313782],"type":"Point"}
}