{
  "type": "Feature",
  "properties": {
    "addr:full":"2580 Southland Dr SW Calgary AB T2V 4J8",
    "addr:housenumber":"2580",
    "addr:postcode":"t2v 4j8",
    "addr:street":"Southland Dr Sw",
    "iso:country":"CA",
    "sg:address":"2580 Southland Dr SW",
    "sg:city":"Calgary",
    "sg:classifiers":[
        {
            "category":"Cinema",
            "subcategory":"Movie Rental",
            "type":"Entertainment"
        }
    ],
    "sg:phone":"+1 403 281 8900",
    "sg:postcode":"T2V 4J8",
    "sg:province":"AB",
    "sg:tags":[
        "player",
        "recorder",
        "video",
        "leasing",
        "tape"
    ],
    "wof:name":"Blockbuster Video",
    "wof:placetype":"venue"
},
  "geometry": {"coordinates":[-114.121002,50.961098],"type":"Point"}
}