{
  "type": "Feature",
  "properties": {
    "addr:full":"115 Berkeley St Toronto ON M5A 2W8",
    "addr:housenumber":"115",
    "addr:postcode":"m5a 2w8",
    "addr:street":"Berkeley St",
    "iso:country":"CA",
    "sg:address":"115 Berkeley St",
    "sg:city":"Toronto",
    "sg:classifiers":[
        {
            "category":"Professional",
            "subcategory":"Lawyer & Legal Services",
            "type":"Services"
        }
    ],
    "sg:phone":"+1 416 362 1234",
    "sg:postcode":"M5A 2W8",
    "sg:province":"ON",
    "sg:tags":[
        "attorney"
    ],
    "wof:name":"Swadron Associates",
    "wof:placetype":"venue"
},
  "geometry": {"coordinates":[-79.3649978638,43.6539916992],"type":"Point"}
}