{
  "type": "Feature",
  "properties": {
    "addr:full":"335 Spokane St Kimberley BC V1A 1Y9",
    "addr:housenumber":"335",
    "addr:postcode":"v1a 1y9",
    "addr:street":"Spokane St",
    "iso:country":"CA",
    "sg:address":"335 Spokane St",
    "sg:city":"Kimberley",
    "sg:classifiers":[
        {
            "category":"Manufacturing",
            "subcategory":"Printing",
            "type":"Manufacturing & Wholesale Goods"
        }
    ],
    "sg:phone":"+1 250 427 5333",
    "sg:postcode":"V1A 1Y9",
    "sg:province":"BC",
    "sg:tags":[
        "newspaper"
    ],
    "wof:name":"Daily Bulletin",
    "wof:placetype":"venue"
},
  "geometry": {"coordinates":[-115.981949,49.685539],"type":"Point"}
}