{
  "type": "Feature",
  "properties": {
    "addr:full":"900 Boul Grignon Saint-Jerome QC J7Y 3S7",
    "addr:housenumber":"900",
    "addr:postcode":"j7y 3s7",
    "addr:street":"Boul Grignon Saint-Jerome",
    "iso:country":"CA",
    "sg:address":"900 Boul Grignon",
    "sg:city":"Saint-Jerome",
    "sg:classifiers":[
        {
            "category":"Health Services",
            "subcategory":"Optometrist",
            "type":"Services"
        }
    ],
    "sg:phone":"+1 450 432 1905",
    "sg:postcode":"J7Y 3S7",
    "sg:province":"QC",
    "wof:name":"Lunetterie Sears",
    "wof:placetype":"venue"
},
  "geometry": {"coordinates":[-74.015625,45.79472],"type":"Point"}
}