{
  "type": "Feature",
  "properties": {
    "addr:full":"163 Clark Dr Brandon MB R7B 0V3",
    "addr:housenumber":"163",
    "addr:postcode":"r7b 0v3",
    "addr:street":"Clark Dr",
    "iso:country":"CA",
    "sg:address":"163 Clark Dr",
    "sg:city":"Brandon",
    "sg:classifiers":[
        {
            "category":"Building & Trades",
            "subcategory":"Construction",
            "type":"Services"
        }
    ],
    "sg:phone":"+1 204 729 6721",
    "sg:postcode":"R7B 0V3",
    "sg:province":"MB",
    "sg:tags":[
        "roofing",
        "contractor"
    ],
    "wof:name":"Rene's Roofing & Eavestrough",
    "wof:placetype":"venue"
},
  "geometry": {"coordinates":[-99.9400634766,49.8842735291],"type":"Point"}
}