{
  "type": "Feature",
  "properties": {
    "addr:full":"5770 Rue Ferrier Mont-Royal QC H4P 1M7",
    "addr:housenumber":"5770",
    "addr:postcode":"h4p 1m7",
    "addr:street":"Rue Ferrier",
    "iso:country":"CA",
    "sg:address":"5770 Rue Ferrier",
    "sg:city":"Mont-Royal",
    "sg:classifiers":[
        {
            "category":"Wholesale",
            "subcategory":"Drugs",
            "type":"Manufacturing & Wholesale Goods"
        }
    ],
    "sg:phone":"+1 514 388 1440",
    "sg:postcode":"H4P 1M7",
    "sg:province":"QC",
    "sg:tags":[
        "pharmaceutical",
        "product"
    ],
    "wof:name":"Jenere Sales",
    "wof:placetype":"venue"
},
  "geometry": {"coordinates":[-73.66735799999999,45.489368],"type":"Point"}
}