{
  "type": "Feature",
  "properties": {
    "addr:full":"1900 Heritage Dr SW Calgary AB T2V 2X3",
    "addr:housenumber":"1900",
    "addr:postcode":"t2v 2x3",
    "addr:street":"Heritage Dr Sw",
    "iso:country":"CA",
    "sg:address":"1900 Heritage Dr SW",
    "sg:city":"Calgary",
    "sg:classifiers":[
        {
            "category":"Museum",
            "type":"Entertainment"
        }
    ],
    "sg:phone":"+1 403 268 8526",
    "sg:postcode":"T2V 2X3",
    "sg:province":"AB",
    "sg:tags":[
        "banquet",
        "rooms"
    ],
    "wof:name":"Heritage Park Historical Vlg",
    "wof:placetype":"venue"
},
  "geometry": {"coordinates":[-114.10297393800001,50.9830474854],"type":"Point"}
}