{
  "type": "Feature",
  "properties": {
    "addr:full":"3464 Av Du Parc Montreal QC H2X 2H5",
    "addr:housenumber":"3464",
    "addr:postcode":"h2x 2h5",
    "addr:street":"Av Du Parc",
    "iso:country":"CA",
    "sg:address":"3464 Av Du Parc",
    "sg:city":"Montreal",
    "sg:classifiers":[
        {
            "category":"Recreation",
            "subcategory":"Amusement Park",
            "type":"Entertainment"
        }
    ],
    "sg:phone":"+1 514 844 6552",
    "sg:postcode":"H2X 2H5",
    "sg:province":"QC",
    "wof:name":"Cafe Amusement Du Parc",
    "wof:placetype":"venue"
},
  "geometry": {"coordinates":[-73.572906,45.508961],"type":"Point"}
}