{
  "type": "Feature",
  "properties": {
    "iso:country":"CA",
    "sg:address":"1590 Dundas St E",
    "sg:city":"Mississauga",
    "sg:classifiers":[
        {
            "category":"Personal",
            "subcategory":"Beauty Salon",
            "type":"Services"
        }
    ],
    "sg:phone":"+1 905 276 1158",
    "sg:postcode":"L4X 2Z2",
    "sg:province":"ON",
    "wof:name":"Eternal Beauty",
    "wof:placetype":"venue"
},
  "geometry": {"coordinates":[-79.578293,43.614151],"type":"Point"}
}