{
  "type": "Feature",
  "properties": {
    "addr:full":"11 Manitoba St Bracebridge ON P1L 1S4",
    "addr:housenumber":"11",
    "addr:postcode":"p1l 1s4",
    "addr:street":"Manitoba St",
    "iso:country":"CA",
    "sg:address":"11 Manitoba St",
    "sg:city":"Bracebridge",
    "sg:classifiers":[
        {
            "category":"Shopping",
            "subcategory":"Used Merchandise",
            "type":"Retail Goods"
        }
    ],
    "sg:phone":"+1 705 646 2291",
    "sg:postcode":"P1L 1S4",
    "sg:province":"ON",
    "sg:tags":[
        "shop",
        "consignment"
    ],
    "wof:name":"Consignment Closet",
    "wof:placetype":"venue"
},
  "geometry": {"coordinates":[-79.30896,45.040619],"type":"Point"}
}