{
  "type": "Feature",
  "properties": {
    "iso:country":"CA",
    "sg:address":"4308 4 Ave",
    "sg:city":"Edson",
    "sg:classifiers":[
        {
            "category":"Restaurant",
            "type":"Food & Drink"
        }
    ],
    "sg:phone":"+1 780 723 4811",
    "sg:postcode":"T7E 1B8",
    "sg:province":"AB",
    "wof:name":"Legends Pizza & Family Rstrnt",
    "wof:placetype":"venue"
},
  "geometry": {"coordinates":[-116.41596984900001,53.5878143311],"type":"Point"}
}