{
  "type": "Feature",
  "properties": {
    "addr:full":"Windsor ON N8X 1T6",
    "addr:postcode":"n8x 1t6",
    "iso:country":"CA",
    "sg:city":"Windsor",
    "sg:classifiers":[
        {
            "category":"Insurance",
            "subcategory":"Insurance Agent",
            "type":"Services"
        }
    ],
    "sg:phone":"+1 519 972 5119",
    "sg:postcode":"N8X 1T6",
    "sg:province":"ON",
    "sg:tags":[
        "adjuster"
    ],
    "wof:name":"Cgi",
    "wof:placetype":"venue"
},
  "geometry": {"coordinates":[-83.02076,42.283897],"type":"Point"}
}