{
  "type": "Feature",
  "properties": {
    "addr:full":"Calgary AB T3C 1E4",
    "addr:postcode":"t3c 1e4",
    "iso:country":"CA",
    "sg:city":"Calgary",
    "sg:classifiers":[
        {
            "category":"Organizations",
            "subcategory":"Community Association",
            "type":"Services"
        }
    ],
    "sg:phone":"+1 403 244 9995",
    "sg:postcode":"T3C 1E4",
    "sg:province":"AB",
    "sg:tags":[
        "club"
    ],
    "wof:name":"Killarney Swim Club",
    "wof:placetype":"venue"
},
  "geometry": {"coordinates":[-114.094841,51.038342],"type":"Point"}
}