{
  "type": "Feature",
  "properties": {
    "addr:full":"Minden ON K0M 2K0",
    "addr:postcode":"k0m 2k0",
    "iso:country":"CA",
    "sg:city":"Minden",
    "sg:classifiers":[
        {
            "category":"Sports & Exercise",
            "subcategory":"Golf",
            "type":"Entertainment"
        }
    ],
    "sg:phone":"+1 705 286 1378",
    "sg:postcode":"K0M 2K0",
    "sg:province":"ON",
    "sg:tags":[
        "course"
    ],
    "wof:name":"Beaverbrook Golf Course",
    "wof:placetype":"venue"
},
  "geometry": {"coordinates":[-78.71611799999999,44.93137],"type":"Point"}
}