{
  "type": "Feature",
  "properties": {
    "addr:full":"50 Ch Marquant Aldouane NB E4W 5G2",
    "addr:housenumber":"50",
    "addr:postcode":"e4w 5g2",
    "addr:street":"Ch Marquant Aldouane",
    "iso:country":"CA",
    "sg:address":"50 Ch Marquant",
    "sg:city":"Aldouane",
    "sg:classifiers":[
        {
            "category":"Personal",
            "subcategory":"Beauty Salon",
            "type":"Services"
        }
    ],
    "sg:phone":"+1 506 524 9801",
    "sg:postcode":"E4W 5G2",
    "sg:province":"NB",
    "wof:name":"Coupe DE Ville",
    "wof:placetype":"venue"
},
  "geometry": {"coordinates":[-65.056892,46.625565],"type":"Point"}
}