{
  "type": "Feature",
  "properties": {
    "iso:country":"CA",
    "sg:city":"Twillingate",
    "sg:classifiers":[
        {
            "category":"Government",
            "subcategory":"Office",
            "type":"Public Place"
        }
    ],
    "sg:phone":"+1 709 884 2413",
    "sg:postcode":"A0G 4M0",
    "sg:province":"NL",
    "wof:name":"Newfoundland Human Resources",
    "wof:placetype":"venue"
},
  "geometry": {"coordinates":[-54.7759742737,49.6569213867],"type":"Point"}
}