{
  "type": "Feature",
  "properties": {
    "addr:full":"65 Industrial Court B Sault Ste Marie ON P6B 5Z9",
    "addr:housenumber":"65",
    "addr:postcode":"p6b 5z9",
    "addr:street":"Industrial Court B",
    "iso:country":"CA",
    "sg:address":"65 Industrial Court B",
    "sg:city":"Sault Ste Marie",
    "sg:classifiers":[
        {
            "category":"Building & Trades",
            "subcategory":"Electrical",
            "type":"Services"
        }
    ],
    "sg:phone":"+1 705 946 8788",
    "sg:postcode":"P6B 5Z9",
    "sg:province":"ON",
    "sg:tags":[
        "furnace",
        "electric",
        "contractor"
    ],
    "wof:name":"Red Star Electric",
    "wof:placetype":"venue"
},
  "geometry": {"coordinates":[-84.326767,46.550827],"type":"Point"}
}