{
  "type": "Feature",
  "properties": {
    "iso:country":"CA",
    "sg:address":"3520 Av Van Horne",
    "sg:city":"Montreal",
    "sg:classifiers":[
        {
            "category":"Professional",
            "subcategory":"Business Services",
            "type":"Services"
        }
    ],
    "sg:phone":"+1 514 737 7331",
    "sg:postcode":"H3S 1R5",
    "sg:province":"QC",
    "sg:tags":[
        "notary"
    ],
    "wof:name":"Darha, Maria",
    "wof:placetype":"venue"
},
  "geometry": {"coordinates":[-73.630844,45.502144],"type":"Point"}
}