{
  "type": "Feature",
  "properties": {
    "iso:country":"CA",
    "sg:address":"621 349 Rte",
    "sg:city":"Saint-Alexis-Des-Monts",
    "sg:classifiers":[
        {
            "category":"Retail",
            "subcategory":"Auto Repair",
            "type":"Services"
        }
    ],
    "sg:phone":"+1 819 265 2344",
    "sg:postcode":"J0K 1V0",
    "sg:province":"QC",
    "sg:tags":[
        "repairing",
        "automobile"
    ],
    "wof:name":"Garage Claude Lacoursiere Inc",
    "wof:placetype":"venue"
},
  "geometry": {"coordinates":[-73.14385986329999,46.461151123],"type":"Point"}
}