{
  "type": "Feature",
  "properties": {
    "addr:full":"Cornwall ON K6H 6X5",
    "addr:postcode":"k6h 6x5",
    "iso:country":"CA",
    "sg:city":"Cornwall",
    "sg:classifiers":[
        {
            "category":"Professional",
            "subcategory":"Lawyer & Legal Services",
            "type":"Services"
        }
    ],
    "sg:phone":"+1 613 938 2800",
    "sg:postcode":"K6H 6X5",
    "sg:province":"ON",
    "sg:tags":[
        "attorney"
    ],
    "wof:name":"Leduc, Jacques O",
    "wof:placetype":"venue"
},
  "geometry": {"coordinates":[-74.687157,45.034943],"type":"Point"}
}