{
  "type": "Feature",
  "properties": {
    "addr:full":"5 Lavington Dr Etobicoke ON M9R 2H1",
    "addr:housenumber":"5",
    "addr:postcode":"m9r 2h1",
    "addr:street":"Lavington Dr",
    "iso:country":"CA",
    "sg:address":"5 Lavington Dr",
    "sg:city":"Etobicoke",
    "sg:classifiers":[
        {
            "category":"Restaurant",
            "type":"Food & Drink"
        }
    ],
    "sg:phone":"+1 416 244 7630",
    "sg:postcode":"M9R 2H1",
    "sg:province":"ON",
    "wof:name":"Martin Grove Fish & Chips",
    "wof:placetype":"venue"
},
  "geometry": {"coordinates":[-79.561989,43.690453],"type":"Point"}
}