{
  "type": "Feature",
  "properties": {
    "addr:full":"161 Rue Des Erables Weedon QC J0B 3J0",
    "addr:housenumber":"161",
    "addr:postcode":"j0b 3j0",
    "addr:street":"Rue Des Erables",
    "iso:country":"CA",
    "sg:address":"161 Rue Des Erables",
    "sg:city":"Weedon",
    "sg:classifiers":[
        {
            "category":"Shopping",
            "type":"Retail Goods"
        }
    ],
    "sg:phone":"+1 819 877 2344",
    "sg:postcode":"J0B 3J0",
    "sg:province":"QC",
    "sg:tags":[
        "picture",
        "frame"
    ],
    "wof:name":"Cadres Ljm DE L'Est Inc",
    "wof:placetype":"venue"
},
  "geometry": {"coordinates":[-71.462890625,45.7017326355],"type":"Point"}
}