{
  "type": "Feature",
  "properties": {
    "iso:country":"CA",
    "sg:address":"441 Fountain St S",
    "sg:city":"Cambridge",
    "sg:classifiers":[
        {
            "category":"Shopping",
            "subcategory":"Florist",
            "type":"Retail Goods"
        }
    ],
    "sg:phone":"+1 519 653 3233",
    "sg:postcode":"N3H 1J2",
    "sg:province":"ON",
    "wof:name":"Gmelin's Flowers & Gifts Ltd",
    "wof:placetype":"venue"
},
  "geometry": {"coordinates":[-80.37330627439999,43.3953704834],"type":"Point"}
}