{
  "type": "Feature",
  "properties": {
    "addr:full":"Gander NL A1V 1A1",
    "addr:postcode":"a1v 1a1",
    "iso:country":"CA",
    "sg:city":"Gander",
    "sg:classifiers":[
        {
            "category":"Building & Trades",
            "subcategory":"Construction",
            "type":"Services"
        }
    ],
    "sg:phone":"+1 709 651 3225",
    "sg:postcode":"A1V 1A1",
    "sg:province":"NL",
    "sg:tags":[
        "general",
        "fiber",
        "optics",
        "contractor"
    ],
    "wof:name":"Bnr Distribution & Transmiss",
    "wof:placetype":"venue"
},
  "geometry": {"coordinates":[-54.6248092651,48.9639663696],"type":"Point"}
}