{
  "type": "Feature",
  "properties": {
    "iso:country":"CA",
    "sg:address":"6 of 15",
    "sg:city":"Blackie",
    "sg:classifiers":[
        {
            "category":"Mining & Drilling",
            "type":"Manufacturing & Wholesale Goods"
        }
    ],
    "sg:phone":"+1 403 684 3710",
    "sg:postcode":"T0L 0J0",
    "sg:province":"AB",
    "sg:tags":[
        "company",
        "oil"
    ],
    "wof:name":"Compton Petroleum Corp",
    "wof:placetype":"venue"
},
  "geometry": {"coordinates":[-113.622573852,50.6062660217],"type":"Point"}
}