{
  "type": "Feature",
  "properties": {
    "addr:full":"1141 Boul Vachon N Sainte-Marie QC G6E 1M9",
    "addr:housenumber":"1141",
    "addr:postcode":"g6e 1m9",
    "addr:street":"Boul Vachon N",
    "iso:country":"CA",
    "sg:address":"1141 Boul Vachon N",
    "sg:city":"Sainte-Marie",
    "sg:classifiers":[
        {
            "category":"Shopping",
            "subcategory":"Clothing, Apparel, & Fashions",
            "type":"Retail Goods"
        }
    ],
    "sg:phone":"+1 418 386 3776",
    "sg:postcode":"G6E 1M9",
    "sg:province":"QC",
    "wof:name":"Boutique Mode & Cie",
    "wof:placetype":"venue"
},
  "geometry": {"coordinates":[-71.038651,46.456867],"type":"Point"}
}