{
  "type": "Feature",
  "properties": {
    "iso:country":"CA",
    "sg:address":"333 Denison St # 21",
    "sg:city":"Markham",
    "sg:classifiers":[
        {
            "category":"Wholesale",
            "subcategory":"Machinery & Supplies",
            "type":"Manufacturing & Wholesale Goods"
        }
    ],
    "sg:phone":"+1 905 475 6277",
    "sg:postcode":"L3R 2Z4",
    "sg:province":"ON",
    "sg:tags":[
        "gage"
    ],
    "wof:name":"Marposs Canada Corp",
    "wof:placetype":"venue"
},
  "geometry": {"coordinates":[-79.34889221189999,43.8222618103],"type":"Point"}
}