{
  "type": "Feature",
  "properties": {
    "addr:full":"Surrey BC V3R 8X2",
    "addr:postcode":"v3r 8x2",
    "iso:country":"CA",
    "sg:city":"Surrey",
    "sg:classifiers":[
        {
            "category":"Personal",
            "subcategory":"Beauty Salon",
            "type":"Services"
        }
    ],
    "sg:phone":"+1 604 581 6828",
    "sg:postcode":"V3R 8X2",
    "sg:province":"BC",
    "wof:name":"Splash Hair",
    "wof:placetype":"venue"
},
  "geometry": {"coordinates":[-122.798973084,49.1844406128],"type":"Point"}
}