{
  "type": "Feature",
  "properties": {
    "addr:full":"Burlington ON L7S 2E8",
    "addr:postcode":"l7s 2e8",
    "iso:country":"CA",
    "sg:city":"Burlington",
    "sg:classifiers":[
        {
            "category":"Health Services",
            "subcategory":"Doctor",
            "type":"Services"
        }
    ],
    "sg:phone":"+1 905 333 4050",
    "sg:postcode":"L7S 2E8",
    "sg:province":"ON",
    "sg:tags":[
        "dentist"
    ],
    "wof:name":"Maple Dental Office",
    "wof:placetype":"venue"
},
  "geometry": {"coordinates":[-79.807838,43.321964],"type":"Point"}
}