{
  "type": "Feature",
  "properties": {
    "addr:full":"446 Kingscourt Dr Waterloo ON N2K 3R9",
    "addr:housenumber":"446",
    "addr:postcode":"n2k 3r9",
    "addr:street":"Kingscourt Dr",
    "iso:country":"CA",
    "sg:address":"446 Kingscourt Dr",
    "sg:city":"Waterloo",
    "sg:classifiers":[
        {
            "category":"Real Estate",
            "subcategory":"Real Estate Agent",
            "type":"Services"
        }
    ],
    "sg:phone":"+1 519 746 7921",
    "sg:postcode":"N2K 3R9",
    "sg:province":"ON",
    "sg:tags":[
        "cooperative"
    ],
    "wof:name":"Shamrock Cooperatives",
    "wof:placetype":"venue"
},
  "geometry": {"coordinates":[-80.52393341059999,43.4956283569],"type":"Point"}
}