{
  "type": "Feature",
  "properties": {
    "addr:full":"125 Montague St Lunenburg NS B0J 2C0",
    "addr:housenumber":"125",
    "addr:postcode":"b0j 2c0",
    "addr:street":"Montague St",
    "iso:country":"CA",
    "sg:address":"125 Montague St",
    "sg:city":"Lunenburg",
    "sg:classifiers":[
        {
            "category":"Food & Beverages",
            "subcategory":"Candy",
            "type":"Retail Goods"
        }
    ],
    "sg:phone":"+1 902 634 4949",
    "sg:postcode":"B0J 2C0",
    "sg:province":"NS",
    "sg:tags":[
        "confectionery"
    ],
    "wof:name":"Sweet Treasures Confectionery",
    "wof:placetype":"venue"
},
  "geometry": {"coordinates":[-64.3093719482,44.376449585],"type":"Point"}
}