{
  "type": "Feature",
  "properties": {
    "iso:country":"CA",
    "sg:address":"4505 52nd Ave",
    "sg:city":"Mayerthorpe",
    "sg:classifiers":[
        {
            "category":"Manufacturing",
            "subcategory":"Pet Food",
            "type":"Manufacturing & Wholesale Goods"
        }
    ],
    "sg:phone":"+1 780 786 2702",
    "sg:postcode":"T0E 1N0",
    "sg:province":"AB",
    "sg:tags":[
        "feed"
    ],
    "wof:name":"Paddle Valley Products Ltd",
    "wof:placetype":"venue"
},
  "geometry": {"coordinates":[-115.135437,53.957191],"type":"Point"}
}