{
  "type": "Feature",
  "properties": {
    "addr:full":"5443 111A St NW Edmonton AB T6H 3H2",
    "addr:housenumber":"5443",
    "addr:postcode":"t6h 3h2",
    "addr:street":"111A St Nw",
    "iso:country":"CA",
    "sg:address":"5443 111A St NW",
    "sg:city":"Edmonton",
    "sg:classifiers":[
        {
            "category":"Real Estate",
            "subcategory":"Architect",
            "type":"Services"
        }
    ],
    "sg:phone":"+1 780 437 6499",
    "sg:postcode":"T6H 3H2",
    "sg:province":"AB",
    "wof:name":"Powley, Kenneth R",
    "wof:placetype":"venue"
},
  "geometry": {"coordinates":[-113.517807,53.492458],"type":"Point"}
}