{
  "type": "Feature",
  "properties": {
    "addr:full":"4190 46A St Delta BC V4K 3N2",
    "addr:housenumber":"4190",
    "addr:postcode":"v4k 3n2",
    "addr:street":"46A St",
    "iso:country":"CA",
    "sg:address":"4190 46A St",
    "sg:city":"Delta",
    "sg:classifiers":[
        {
            "category":"Wholesale",
            "subcategory":"Apparel",
            "type":"Manufacturing & Wholesale Goods"
        }
    ],
    "sg:phone":"+1 604 940 0517",
    "sg:postcode":"V4K 3N2",
    "sg:province":"BC",
    "sg:tags":[
        "clothing"
    ],
    "wof:name":"Signature Accessories",
    "wof:placetype":"venue"
},
  "geometry": {"coordinates":[-123.059616089,49.0848007202],"type":"Point"}
}