{
  "type": "Feature",
  "properties": {
    "addr:full":"1230 Boul Laure Sept-Iles QC G4S 1C5",
    "addr:housenumber":"1230",
    "addr:postcode":"g4s 1c5",
    "addr:street":"Boul Laure Sept-Iles",
    "iso:country":"CA",
    "sg:address":"1230 Boul Laure",
    "sg:city":"Sept-Iles",
    "sg:classifiers":[
        {
            "category":"Wholesale",
            "subcategory":"Electrical",
            "type":"Manufacturing & Wholesale Goods"
        }
    ],
    "sg:phone":"+1 418 962 6568",
    "sg:postcode":"G4S 1C5",
    "sg:province":"QC",
    "sg:tags":[
        "communication",
        "radio",
        "telephone",
        "cellular"
    ],
    "wof:name":"Telecommunications DE L'Est",
    "wof:placetype":"venue"
},
  "geometry": {"coordinates":[-66.3949203491,50.2360725403],"type":"Point"}
}