{
  "type": "Feature",
  "properties": {
    "addr:full":"34 Saugeen Airport Rd Walkerton ON N0G 2V0",
    "addr:housenumber":"34",
    "addr:postcode":"n0g 2v0",
    "addr:street":"Saugeen Airport Rd",
    "iso:country":"CA",
    "sg:address":"34 Saugeen Airport Rd",
    "sg:city":"Walkerton",
    "sg:classifiers":[
        {
            "category":"Building & Trades",
            "subcategory":"Equipment Rental",
            "type":"Services"
        }
    ],
    "sg:phone":"+1 519 881 7559",
    "sg:postcode":"N0G 2V0",
    "sg:province":"ON",
    "sg:tags":[
        "aircraft",
        "leasing",
        "charter",
        "school"
    ],
    "wof:name":"Evans Aviation",
    "wof:placetype":"venue"
},
  "geometry": {"coordinates":[-81.15213,44.128181],"type":"Point"}
}