{
  "type": "Feature",
  "properties": {
    "addr:full":"262 Main St W Palmerston ON N0G 2P0",
    "addr:housenumber":"262",
    "addr:postcode":"n0g 2p0",
    "addr:street":"Main St W",
    "iso:country":"CA",
    "sg:address":"262 Main St W",
    "sg:city":"Palmerston",
    "sg:classifiers":[
        {
            "category":"Banks & Credit Unions",
            "subcategory":"Bank",
            "type":"Services"
        }
    ],
    "sg:phone":"+1 519 343 2127",
    "sg:postcode":"N0G 2P0",
    "sg:province":"ON",
    "wof:name":"Cibc",
    "wof:placetype":"venue"
},
  "geometry": {"coordinates":[-80.8508987427,43.8339653015],"type":"Point"}
}