{
  "type": "Feature",
  "properties": {
    "addr:full":"9749 Boul #Anne Sainte-Anne-DE-Beaupre QC G0A 3C0",
    "addr:housenumber":"9749;#",
    "addr:postcode":"g0a 3c0",
    "addr:street":"Boul",
    "iso:country":"CA",
    "sg:address":"9749 Boul #Anne",
    "sg:city":"Sainte-Anne-DE-Beaupre",
    "sg:classifiers":[
        {
            "category":"Restaurant",
            "type":"Food & Drink"
        }
    ],
    "sg:phone":"+1 418 827 3446",
    "sg:postcode":"G0A 3C0",
    "sg:province":"QC",
    "wof:name":"Restaurant Le Marie Beaupre",
    "wof:placetype":"venue"
},
  "geometry": {"coordinates":[-71.89045,46.713318],"type":"Point"}
}