{
  "type": "Feature",
  "properties": {
    "addr:full":"178 Anson Dr Iroquois Falls ON P0K 1E0",
    "addr:housenumber":"178",
    "addr:postcode":"p0k 1e0",
    "addr:street":"Anson Dr",
    "iso:country":"CA",
    "sg:address":"178 Anson Dr",
    "sg:city":"Iroquois Falls",
    "sg:classifiers":[
        {
            "category":"Autos & Motor Vehicles",
            "subcategory":"Automobile Sales",
            "type":"Retail Goods"
        }
    ],
    "sg:phone":"+1 705 232 6461",
    "sg:postcode":"P0K 1E0",
    "sg:province":"ON",
    "sg:tags":[
        "parts",
        "snowmobile",
        "accessory"
    ],
    "wof:name":"Montrock Small Motors",
    "wof:placetype":"venue"
},
  "geometry": {"coordinates":[-80.69558000000001,48.768639],"type":"Point"}
}