{
  "type": "Feature",
  "properties": {
    "addr:full":"55 Rue Des Cascades Levis QC G6V 6T9",
    "addr:housenumber":"55",
    "addr:postcode":"g6v 6t9",
    "addr:street":"Rue Des Cascades",
    "iso:country":"CA",
    "sg:address":"55 Rue Des Cascades",
    "sg:city":"Levis",
    "sg:classifiers":[
        {
            "category":"Manufacturing",
            "subcategory":"Printing",
            "type":"Manufacturing & Wholesale Goods"
        }
    ],
    "sg:phone":"+1 418 833 9840",
    "sg:postcode":"G6V 6T9",
    "sg:province":"QC",
    "sg:tags":[
        "printer"
    ],
    "wof:name":"Impressions Interpro",
    "wof:placetype":"venue"
},
  "geometry": {"coordinates":[-71.16480300000001,46.823441],"type":"Point"}
}