{
  "type": "Feature",
  "properties": {
    "iso:country":"CA",
    "sg:city":"Woodbridge",
    "sg:classifiers":[
        {
            "category":"Manufacturing",
            "subcategory":"Tools & Machinery",
            "type":"Manufacturing & Wholesale Goods"
        }
    ],
    "sg:phone":"+1 905 264 7263",
    "sg:postcode":"L4L 4V8",
    "sg:province":"ON",
    "sg:tags":[
        "die",
        "maker"
    ],
    "wof:name":"Brit Moulds",
    "wof:placetype":"venue"
},
  "geometry": {"coordinates":[-79.564728,43.769093],"type":"Point"}
}