{
  "type": "Feature",
  "properties": {
    "addr:full":"23 Queensway Cres Winnipeg MB R2J 3P3",
    "addr:housenumber":"23",
    "addr:postcode":"r2j 3p3",
    "addr:street":"Queensway Cres",
    "iso:country":"CA",
    "sg:address":"23 Queensway Cres",
    "sg:city":"Winnipeg",
    "sg:classifiers":[
        {
            "category":"Professional",
            "subcategory":"Research",
            "type":"Services"
        }
    ],
    "sg:phone":"+1 204 256 3894",
    "sg:postcode":"R2J 3P3",
    "sg:province":"MB",
    "sg:tags":[
        "development",
        "energy",
        "solar"
    ],
    "wof:name":"Solar Energy Society Manitoba",
    "wof:placetype":"venue"
},
  "geometry": {"coordinates":[-97.071411,49.843922],"type":"Point"}
}