{
  "type": "Feature",
  "properties": {
    "iso:country":"CA",
    "sg:city":"Calgary",
    "sg:classifiers":[
        {
            "category":"Organizations",
            "subcategory":"Non-profit Organization",
            "type":"Services"
        }
    ],
    "sg:phone":"+1 403 282 1872",
    "sg:postcode":"T2M 3N4",
    "sg:province":"AB",
    "sg:tags":[
        "disability"
    ],
    "wof:name":"Accessible Housing Society",
    "wof:placetype":"venue"
},
  "geometry": {"coordinates":[-114.108017,51.064945],"type":"Point"}
}