{
  "type": "Feature",
  "properties": {
    "addr:full":"9805 100 St Grande Prairie AB T8V 6X3",
    "addr:housenumber":"9805",
    "addr:postcode":"t8v 6x3",
    "addr:street":"100 St",
    "iso:country":"CA",
    "sg:address":"9805 100 St",
    "sg:city":"Grande Prairie",
    "sg:classifiers":[
        {
            "category":"Travel",
            "subcategory":"Hotels & Motels",
            "type":"Entertainment"
        }
    ],
    "sg:phone":"+1 780 513 5555",
    "sg:postcode":"T8V 6X3",
    "sg:province":"AB",
    "wof:name":"Sandman Hotels & Inns",
    "wof:placetype":"venue"
},
  "geometry": {"coordinates":[-118.79454,55.168961],"type":"Point"}
}