{
  "type": "Feature",
  "properties": {
    "addr:full":"PO Box 89 Clyde River NU X0A 0E0",
    "addr:housenumber":"po box 89",
    "addr:postcode":"x0a 0e0",
    "iso:country":"CA",
    "sg:address":"PO Box 89",
    "sg:city":"Clyde River",
    "sg:classifiers":[
        {
            "category":"Government",
            "subcategory":"Office",
            "type":"Public Place"
        }
    ],
    "sg:phone":"+1 867 924 6706",
    "sg:postcode":"X0A 0E0",
    "sg:province":"NU",
    "sg:tags":[
        "village"
    ],
    "wof:name":"Clyde River Cedo",
    "wof:placetype":"venue"
},
  "geometry": {"coordinates":[-68.586037,70.472916],"type":"Point"}
}