{
  "type": "Feature",
  "properties": {
    "iso:country":"CA",
    "sg:address":"1122 Denman St",
    "sg:city":"Vancouver",
    "sg:classifiers":[
        {
            "category":"Restaurant",
            "type":"Food & Drink"
        }
    ],
    "sg:phone":"+1 604 681 7777",
    "sg:postcode":"V6G 2M8",
    "sg:province":"BC",
    "wof:name":"Tanpopo Japanese Restaurant",
    "wof:placetype":"venue"
},
  "geometry": {"coordinates":[-123.14050293,49.2879829407],"type":"Point"}
}