{
  "type": "Feature",
  "properties": {
    "addr:full":"Oak Bluff Sanford MB R0G 2J0",
    "addr:postcode":"r0g 2j0",
    "addr:street":"Oak Bluff",
    "iso:country":"CA",
    "sg:address":"Oak Bluff",
    "sg:city":"Sanford",
    "sg:classifiers":[
        {
            "category":"Organizations",
            "subcategory":"Professional Association",
            "type":"Services"
        }
    ],
    "sg:phone":"+1 204 736 2779",
    "sg:postcode":"R0G 2J0",
    "sg:province":"MB",
    "sg:tags":[
        "club"
    ],
    "wof:name":"Winnipeg Trap & Skeet Club",
    "wof:placetype":"venue"
},
  "geometry": {"coordinates":[-97.44637299999999,49.680466],"type":"Point"}
}