{
  "type": "Feature",
  "properties": {
    "addr:full":"19959 Silverview Rd Hope BC V0X 1L2",
    "addr:housenumber":"19959",
    "addr:postcode":"v0x 1l2",
    "addr:street":"Silverview Rd",
    "iso:country":"CA",
    "sg:address":"19959 Silverview Rd",
    "sg:city":"Hope",
    "sg:classifiers":[
        {
            "category":"Food & Beverages",
            "subcategory":"Groceries & Convenience Stores",
            "type":"Retail Goods"
        }
    ],
    "sg:phone":"+1 604 869 9999",
    "sg:postcode":"V0X 1L2",
    "sg:province":"BC",
    "sg:tags":[
        "grocer"
    ],
    "wof:name":"Harv's Country Food Ltd",
    "wof:placetype":"venue"
},
  "geometry": {"coordinates":[-121.465736389,49.3613815308],"type":"Point"}
}