{
  "type": "Feature",
  "properties": {
    "addr:full":"305 Armstrong Ave Georgetown ON L7G 4X6",
    "addr:housenumber":"305",
    "addr:postcode":"l7g 4x6",
    "addr:street":"Armstrong Ave",
    "iso:country":"CA",
    "sg:address":"305 Armstrong Ave",
    "sg:city":"Georgetown",
    "sg:classifiers":[
        {
            "category":"Retail",
            "subcategory":"Auto Repair",
            "type":"Services"
        }
    ],
    "sg:phone":"+1 905 877 0873",
    "sg:postcode":"L7G 4X6",
    "sg:province":"ON",
    "sg:tags":[
        "body",
        "automobile",
        "painting"
    ],
    "wof:name":"Tra Enterprises",
    "wof:placetype":"venue"
},
  "geometry": {"coordinates":[-79.88586425779999,43.6525306702],"type":"Point"}
}