{
  "type": "Feature",
  "properties": {
    "iso:country":"CA",
    "sg:address":"5419 44th St",
    "sg:city":"Provost",
    "sg:classifiers":[
        {
            "category":"Government",
            "subcategory":"Office",
            "type":"Public Place"
        }
    ],
    "sg:phone":"+1 780 753 2150",
    "sg:postcode":"T0B 3S0",
    "sg:province":"AB",
    "wof:name":"Alberta Financial Svc Corp",
    "wof:placetype":"venue"
},
  "geometry": {"coordinates":[-110.256332398,52.3574867249],"type":"Point"}
}