{
  "type": "Feature",
  "properties": {
    "iso:country":"CA",
    "sg:address":"1345 Rue Fleury E",
    "sg:city":"Montreal",
    "sg:classifiers":[
        {
            "category":"Restaurant",
            "type":"Food & Drink"
        }
    ],
    "sg:phone":"+1 514 384 0806",
    "sg:postcode":"H2C 1R4",
    "sg:province":"QC",
    "wof:name":"Restaurant Le Gout-Thailande",
    "wof:placetype":"venue"
},
  "geometry": {"coordinates":[-73.657997,45.56036],"type":"Point"}
}