{
  "type": "Feature",
  "properties": {
    "iso:country":"CA",
    "sg:address":"349 Stephanie Dr",
    "sg:city":"Guelph",
    "sg:classifiers":[
        {
            "category":"Building & Trades",
            "subcategory":"Construction",
            "type":"Services"
        }
    ],
    "sg:phone":"+1 519 822 0988",
    "sg:postcode":"N1K 1R3",
    "sg:province":"ON",
    "sg:tags":[
        "dry wall",
        "contractor"
    ],
    "wof:name":"Donald Cyr Drywall",
    "wof:placetype":"venue"
},
  "geometry": {"coordinates":[-80.285637,43.522701],"type":"Point"}
}