{
  "type": "Feature",
  "properties": {
    "addr:full":"Brockville ON K6V 3G9",
    "addr:postcode":"k6v 3g9",
    "iso:country":"CA",
    "sg:city":"Brockville",
    "sg:classifiers":[
        {
            "category":"Shopping",
            "subcategory":"Clothing, Apparel, & Fashions",
            "type":"Retail Goods"
        }
    ],
    "sg:phone":"+1 613 342 5631",
    "sg:postcode":"K6V 3G9",
    "sg:province":"ON",
    "sg:tags":[
        "shoes"
    ],
    "wof:name":"Limestone Ivy",
    "wof:placetype":"venue"
},
  "geometry": {"coordinates":[-75.69933319090001,44.6044769287],"type":"Point"}
}