{
  "type": "Feature",
  "properties": {
    "addr:full":"326 Rue Principale St-Octave QC G0J 3B0",
    "addr:housenumber":"326",
    "addr:postcode":"g0j 3b0",
    "addr:street":"Rue Principale",
    "iso:country":"CA",
    "sg:address":"326 Rue Principale",
    "sg:city":"St-Octave",
    "sg:classifiers":[
        {
            "category":"Retail",
            "subcategory":"Funeral Services",
            "type":"Services"
        }
    ],
    "sg:phone":"+1 418 775 7863",
    "sg:postcode":"G0J 3B0",
    "sg:province":"QC",
    "sg:tags":[
        "director"
    ],
    "wof:name":"Salon Funeraire A Pelletier",
    "wof:placetype":"venue"
},
  "geometry": {"coordinates":[-68.0774307251,48.6039505005],"type":"Point"}
}