{
  "type": "Feature",
  "properties": {
    "iso:country":"CA",
    "sg:city":"Atmore",
    "sg:classifiers":[
        {
            "category":"Retail",
            "subcategory":"Repair Shop",
            "type":"Services"
        }
    ],
    "sg:phone":"+1 780 525 2559",
    "sg:postcode":"T0A 0E0",
    "sg:province":"AB",
    "sg:tags":[
        "repairing",
        "saw"
    ],
    "wof:name":"D Adams Saw Svc",
    "wof:placetype":"venue"
},
  "geometry": {"coordinates":[-112.528930664,54.8203201294],"type":"Point"}
}