{
  "type": "Feature",
  "properties": {
    "addr:full":"15042 92 Ave Surrey BC V3R 5V7",
    "addr:housenumber":"15042",
    "addr:postcode":"v3r 5v7",
    "addr:street":"92 Ave",
    "iso:country":"CA",
    "sg:address":"15042 92 Ave",
    "sg:city":"Surrey",
    "sg:classifiers":[
        {
            "category":"Organizations",
            "subcategory":"Religious Organization",
            "type":"Services"
        }
    ],
    "sg:phone":"+1 604 588 6717",
    "sg:postcode":"V3R 5V7",
    "sg:province":"BC",
    "sg:tags":[
        "church"
    ],
    "wof:name":"Church of Christ",
    "wof:placetype":"venue"
},
  "geometry": {"coordinates":[-122.80529,49.169933],"type":"Point"}
}