{
  "type": "Feature",
  "properties": {
    "iso:country":"CA",
    "sg:city":"Selkirk",
    "sg:classifiers":[
        {
            "category":"Banks & Credit Unions",
            "subcategory":"Bank",
            "type":"Services"
        }
    ],
    "sg:phone":"+1 204 482 3608",
    "sg:postcode":"R1A 2J7",
    "sg:province":"MB",
    "wof:name":"Royal Bank Financial Group",
    "wof:placetype":"venue"
},
  "geometry": {"coordinates":[-96.8744735718,50.1433296204],"type":"Point"}
}