{
  "type": "Feature",
  "properties": {
    "addr:full":"13915 Rue Lucie Mirabel QC J7J 1G5",
    "addr:housenumber":"13915",
    "addr:postcode":"j7j 1g5",
    "addr:street":"Rue Lucie",
    "iso:country":"CA",
    "sg:address":"13915 Rue Lucie",
    "sg:city":"Mirabel",
    "sg:classifiers":[
        {
            "category":"Health Services",
            "subcategory":"Clinic",
            "type":"Services"
        }
    ],
    "sg:phone":"+1 450 435 6737",
    "sg:postcode":"J7J 1G5",
    "sg:province":"QC",
    "sg:tags":[
        "aid",
        "first"
    ],
    "wof:name":"Sauvetage Ag",
    "wof:placetype":"venue"
},
  "geometry": {"coordinates":[-73.921516,45.706535],"type":"Point"}
}