{
  "type": "Feature",
  "properties": {
    "addr:full":"701 1st Ave W Nipawin SK S0E 1E0",
    "addr:housenumber":"701",
    "addr:postcode":"s0e 1e0",
    "addr:street":"1St Ave W Nipawin",
    "iso:country":"CA",
    "sg:address":"701 1st Ave W",
    "sg:city":"Nipawin",
    "sg:classifiers":[
        {
            "category":"Retail",
            "subcategory":"Auto Repair",
            "type":"Services"
        }
    ],
    "sg:phone":"+1 306 862 9579",
    "sg:postcode":"S0E 1E0",
    "sg:province":"SK",
    "sg:tags":[
        "repairing",
        "automobile"
    ],
    "wof:name":"D W Auto",
    "wof:placetype":"venue"
},
  "geometry": {"coordinates":[-104.018226623,53.3617210388],"type":"Point"}
}