{
  "type": "Feature",
  "properties": {
    "addr:full":"Port Coquitlam BC V3C 6N2",
    "addr:postcode":"v3c 6n2",
    "iso:country":"CA",
    "sg:city":"Port Coquitlam",
    "sg:classifiers":[
        {
            "category":"Professional",
            "subcategory":"Management & Consulting",
            "type":"Services"
        }
    ],
    "sg:phone":"+1 604 468 0841",
    "sg:postcode":"V3C 6N2",
    "sg:province":"BC",
    "sg:tags":[
        "consultant",
        "mining"
    ],
    "wof:name":"Modular Mining Systems Canada",
    "wof:placetype":"venue"
},
  "geometry": {"coordinates":[-122.773208618,49.2575378418],"type":"Point"}
}