{
  "type": "Feature",
  "properties": {
    "addr:full":"217 Main St E Grimsby ON L3M 1P5",
    "addr:housenumber":"217",
    "addr:postcode":"l3m 1p5",
    "addr:street":"Main St E",
    "iso:country":"CA",
    "sg:address":"217 Main St E",
    "sg:city":"Grimsby",
    "sg:classifiers":[
        {
            "category":"Education",
            "subcategory":"School",
            "type":"Public Place"
        }
    ],
    "sg:phone":"+1 905 945 2445",
    "sg:postcode":"L3M 1P5",
    "sg:province":"ON",
    "wof:name":"Park School",
    "wof:placetype":"venue"
},
  "geometry": {"coordinates":[-79.53499603269999,43.1859550476],"type":"Point"}
}