{
  "type": "Feature",
  "properties": {
    "addr:full":"8000 Boul Gouin O Montreal QC H4K 1C2",
    "addr:housenumber":"8000",
    "addr:postcode":"h4k 1c2",
    "addr:street":"Boul Gouin O",
    "iso:country":"CA",
    "sg:address":"8000 Boul Gouin O",
    "sg:city":"Montreal",
    "sg:classifiers":[
        {
            "category":"Building & Trades",
            "subcategory":"Construction",
            "type":"Services"
        }
    ],
    "sg:phone":"+1 514 331 8853",
    "sg:postcode":"H4K 1C2",
    "sg:province":"QC",
    "sg:tags":[
        "general",
        "contractor"
    ],
    "wof:name":"Remo Construction Inc",
    "wof:placetype":"venue"
},
  "geometry": {"coordinates":[-73.59907531739999,45.6423797607],"type":"Point"}
}