{
  "type": "Feature",
  "properties": {
    "iso:country":"CA",
    "sg:address":"1219 10 Ave SE",
    "sg:city":"Calgary",
    "sg:classifiers":[
        {
            "category":"Travel",
            "subcategory":"Travel Agent",
            "type":"Entertainment"
        }
    ],
    "sg:phone":"+1 403 244 7222",
    "sg:postcode":"T2G 0W6",
    "sg:province":"AB",
    "sg:tags":[
        "agency",
        "bureau"
    ],
    "wof:name":"Exclusively Cruises Ltd",
    "wof:placetype":"venue"
},
  "geometry": {"coordinates":[-114.036445618,51.0407791138],"type":"Point"}
}