{
  "type": "Feature",
  "properties": {
    "iso:country":"CA",
    "sg:address":"40 Pacific Ave",
    "sg:city":"Maple Creek",
    "sg:classifiers":[
        {
            "category":"Building & Trades",
            "subcategory":"Plumbing",
            "type":"Services"
        }
    ],
    "sg:phone":"+1 306 662 2666",
    "sg:postcode":"S0N 1N0",
    "sg:province":"SK",
    "sg:tags":[
        "furnace",
        "heating",
        "contractor"
    ],
    "wof:name":"Maple Plumbing & Heating Ltd",
    "wof:placetype":"venue"
},
  "geometry": {"coordinates":[-109.47336578399999,49.908416748],"type":"Point"}
}