{
  "type": "Feature",
  "properties": {
    "addr:full":"976 Aspen Rd Comox BC V9M 3Y8",
    "addr:housenumber":"976",
    "addr:postcode":"v9m 3y8",
    "addr:street":"Aspen Rd",
    "iso:country":"CA",
    "sg:address":"976 Aspen Rd",
    "sg:city":"Comox",
    "sg:classifiers":[
        {
            "category":"Building & Trades",
            "subcategory":"Construction",
            "type":"Services"
        }
    ],
    "sg:phone":"+1 250 339 3360",
    "sg:postcode":"V9M 3Y8",
    "sg:province":"BC",
    "sg:tags":[
        "tile",
        "dealer"
    ],
    "wof:name":"Mike's Industrial Svc",
    "wof:placetype":"venue"
},
  "geometry": {"coordinates":[-124.943146,49.6898],"type":"Point"}
}