{
  "type": "Feature",
  "properties": {
    "iso:country":"CA",
    "sg:city":"Whistler",
    "sg:classifiers":[
        {
            "category":"Restaurant",
            "type":"Food & Drink"
        }
    ],
    "sg:phone":"+1 604 905 0155",
    "sg:postcode":"V0N 1B4",
    "sg:province":"BC",
    "wof:name":"Sushi-Ya",
    "wof:placetype":"venue"
},
  "geometry": {"coordinates":[-122.95552063,50.1202888489],"type":"Point"}
}