{
  "type": "Feature",
  "properties": {
    "addr:full":"St-Sauveur-Des-Monts QC J0R 1R4",
    "addr:postcode":"j0r 1r4",
    "iso:country":"CA",
    "sg:city":"St-Sauveur-Des-Monts",
    "sg:classifiers":[
        {
            "category":"Building & Trades",
            "subcategory":"Electrical",
            "type":"Services"
        }
    ],
    "sg:phone":"+1 450 227 2789",
    "sg:postcode":"J0R 1R4",
    "sg:province":"QC",
    "sg:tags":[
        "electric",
        "contractor"
    ],
    "wof:name":"Robert Filion & Fils Inc",
    "wof:placetype":"venue"
},
  "geometry": {"coordinates":[-74.157021,45.895332],"type":"Point"}
}