{
  "type": "Feature",
  "properties": {
    "addr:full":"32763 Sixth Ave Mission BC V2V 1Y8",
    "addr:housenumber":"32763",
    "addr:postcode":"v2v 1y8",
    "addr:street":"Sixth Ave",
    "iso:country":"CA",
    "sg:address":"32763 Sixth Ave",
    "sg:city":"Mission",
    "sg:classifiers":[
        {
            "category":"Building & Trades",
            "subcategory":"Electrical",
            "type":"Services"
        }
    ],
    "sg:phone":"+1 604 820 0656",
    "sg:postcode":"V2V 1Y8",
    "sg:province":"BC",
    "sg:tags":[
        "electric",
        "contractor"
    ],
    "wof:name":"Mc Kay Electric",
    "wof:placetype":"venue"
},
  "geometry": {"coordinates":[-122.316406,49.138969],"type":"Point"}
}