{
  "type": "Feature",
  "properties": {
    "addr:full":"1470 Ch DE LA Riviere Val-David QC J0T 2N0",
    "addr:postcode":"1470;j0t 2n0",
    "addr:street":"Ch De La Riviere",
    "iso:country":"CA",
    "sg:address":"1470 Ch DE LA Riviere",
    "sg:city":"Val-David",
    "sg:classifiers":[
        {
            "category":"Travel",
            "subcategory":"Hotels & Motels",
            "type":"Entertainment"
        }
    ],
    "sg:phone":"+1 819 322 3528",
    "sg:postcode":"J0T 2N0",
    "sg:province":"QC",
    "sg:tags":[
        "breakfast",
        "accommodation",
        "bed"
    ],
    "wof:name":"Maison DE Baiviere",
    "wof:placetype":"venue"
},
  "geometry": {"coordinates":[-74.21116600000001,46.033047],"type":"Point"}
}