{
  "type": "Feature",
  "properties": {
    "addr:full":"Burnaby BC V5J 5J2",
    "addr:postcode":"v5j 5j2",
    "iso:country":"CA",
    "sg:city":"Burnaby",
    "sg:classifiers":[
        {
            "category":"Wholesale",
            "subcategory":"Durable Goods & Equipment",
            "type":"Manufacturing & Wholesale Goods"
        }
    ],
    "sg:phone":"+1 604 324 5677",
    "sg:postcode":"V5J 5J2",
    "sg:province":"BC",
    "sg:tags":[
        "representative",
        "manufacturer"
    ],
    "wof:name":"B & W Sales",
    "wof:placetype":"venue"
},
  "geometry": {"coordinates":[-123.02259826700001,49.2026062012],"type":"Point"}
}