{
  "type": "Feature",
  "properties": {
    "addr:full":"528 Hood Rd Markham ON L3R 3K9",
    "addr:housenumber":"528",
    "addr:postcode":"l3r 3k9",
    "addr:street":"Hood Rd",
    "iso:country":"CA",
    "sg:address":"528 Hood Rd",
    "sg:city":"Markham",
    "sg:classifiers":[
        {
            "category":"Shopping",
            "subcategory":"Department Store",
            "type":"Retail Goods"
        }
    ],
    "sg:phone":"+1 905 620 0327",
    "sg:postcode":"L3R 3K9",
    "sg:province":"ON",
    "sg:tags":[
        "shop"
    ],
    "wof:name":"Mighty Dollar Inc",
    "wof:placetype":"venue"
},
  "geometry": {"coordinates":[-79.33001708979999,43.8335533142],"type":"Point"}
}