{
  "type": "Feature",
  "properties": {
    "iso:country":"CA",
    "sg:address":"193 Leigh Cres",
    "sg:city":"Fort Mcmurray",
    "sg:classifiers":[
        {
            "category":"Retail",
            "subcategory":"Animal Services",
            "type":"Services"
        }
    ],
    "sg:phone":"+1 780 791 1483",
    "sg:postcode":"T9K 1K2",
    "sg:province":"AB",
    "sg:tags":[
        "pet",
        "grooming",
        "washing"
    ],
    "wof:name":"Peticare Dog Grooming",
    "wof:placetype":"venue"
},
  "geometry": {"coordinates":[-111.462097168,56.7380065918],"type":"Point"}
}