{
  "type": "Feature",
  "properties": {
    "iso:country":"CA",
    "sg:address":"2107 Weston Rd",
    "sg:city":"York",
    "sg:classifiers":[
        {
            "category":"Personal",
            "subcategory":"Beauty Salon",
            "type":"Services"
        }
    ],
    "sg:phone":"+1 416 614 1717",
    "sg:postcode":"M9N 1X7",
    "sg:province":"ON",
    "wof:name":"Beauty By Betty",
    "wof:placetype":"venue"
},
  "geometry": {"coordinates":[-79.52299499510001,43.7022476196],"type":"Point"}
}