{
  "type": "Feature",
  "properties": {
    "addr:full":"4672 Adelaide St Port Alberni BC V9Y 6N4",
    "addr:housenumber":"4672",
    "addr:postcode":"v9y 6n4",
    "addr:street":"Adelaide St",
    "iso:country":"CA",
    "sg:address":"4672 Adelaide St",
    "sg:city":"Port Alberni",
    "sg:classifiers":[
        {
            "category":"Wholesale",
            "subcategory":"Groceries",
            "type":"Manufacturing & Wholesale Goods"
        }
    ],
    "sg:phone":"+1 250 723 2699",
    "sg:postcode":"V9Y 6N4",
    "sg:province":"BC",
    "sg:tags":[
        "food",
        "product",
        "health"
    ],
    "wof:name":"Pro Built Nutrition",
    "wof:placetype":"venue"
},
  "geometry": {"coordinates":[-124.80931099999999,49.260277],"type":"Point"}
}