{
  "type": "Feature",
  "properties": {
    "iso:country":"CA",
    "sg:address":"3610 Sarcee Rd SW",
    "sg:city":"Calgary",
    "sg:classifiers":[
        {
            "category":"Organizations",
            "subcategory":"Religious Organization",
            "type":"Services"
        }
    ],
    "sg:phone":"+1 403 249 8562",
    "sg:postcode":"T3E 6V6",
    "sg:province":"AB",
    "sg:tags":[
        "church"
    ],
    "wof:name":"Grace Lutheran Church",
    "wof:placetype":"venue"
},
  "geometry": {"coordinates":[-114.129898,51.022011],"type":"Point"}
}