{
  "type": "Feature",
  "properties": {
    "addr:full":"165 Rue Delage Saint-Cyrille-DE-Wendover QC J1Z 1N6",
    "addr:housenumber":"165",
    "addr:postcode":"j1z 1n6",
    "addr:street":"Rue Delage",
    "iso:country":"CA",
    "sg:address":"165 Rue Delage",
    "sg:city":"Saint-Cyrille-DE-Wendover",
    "sg:classifiers":[
        {
            "category":"Government",
            "subcategory":"Fire Station",
            "type":"Public Place"
        }
    ],
    "sg:phone":"+1 ",
    "sg:postcode":"J1Z 1N6",
    "sg:province":"QC",
    "sg:tags":[
        "department"
    ],
    "wof:name":"St-Cyrille DE Wendover D'Hbtn",
    "wof:placetype":"venue"
},
  "geometry": {"coordinates":[-72.3955078125,45.9522361755],"type":"Point"}
}