{
  "type": "Feature",
  "properties": {
    "addr:full":"72 Rue Napoleon Sept-Iles QC G4R 3L2",
    "addr:housenumber":"72",
    "addr:postcode":"g4r 3l2",
    "addr:street":"Rue Napoleon Sept-Iles",
    "iso:country":"CA",
    "sg:address":"72 Rue Napoleon",
    "sg:city":"Sept-Iles",
    "sg:classifiers":[
        {
            "category":"Restaurant",
            "type":"Food & Drink"
        }
    ],
    "sg:phone":"+1 418 962 2113",
    "sg:postcode":"G4R 3L2",
    "sg:province":"QC",
    "wof:name":"Restaurant Le Chaudron Inc",
    "wof:placetype":"venue"
},
  "geometry": {"coordinates":[-66.3785476685,50.2078819275],"type":"Point"}
}