{
  "type": "Feature",
  "properties": {
    "iso:country":"CA",
    "sg:address":"956 Redonda St",
    "sg:city":"Winnipeg",
    "sg:classifiers":[
        {
            "category":"Building & Trades",
            "subcategory":"Construction",
            "type":"Services"
        }
    ],
    "sg:phone":"+1 204 261 4903",
    "sg:postcode":"R2C 2Z2",
    "sg:province":"MB",
    "sg:tags":[
        "excavating",
        "sewer",
        "contractor"
    ],
    "wof:name":"Ron Dor Excavations Ltd",
    "wof:placetype":"venue"
},
  "geometry": {"coordinates":[-96.9795227051,49.9155311584],"type":"Point"}
}