{
  "type": "Feature",
  "properties": {
    "addr:full":"7 Kirk St Bristol NB E7L 2G9",
    "addr:housenumber":"7",
    "addr:postcode":"e7l 2g9",
    "addr:street":"Kirk St",
    "iso:country":"CA",
    "sg:address":"7 Kirk St",
    "sg:city":"Bristol",
    "sg:classifiers":[
        {
            "category":"Organizations",
            "subcategory":"Religious Organization",
            "type":"Services"
        }
    ],
    "sg:phone":"+1 506 392 6963",
    "sg:postcode":"E7L 2G9",
    "sg:province":"NB",
    "sg:tags":[
        "church"
    ],
    "wof:name":"Trinity Wesleyan Church",
    "wof:placetype":"venue"
},
  "geometry": {"coordinates":[-67.575104,46.467403],"type":"Point"}
}