{
  "type": "Feature",
  "properties": {
    "addr:full":"168 Main St E North Bay ON P1B 1A8",
    "addr:housenumber":"168",
    "addr:postcode":"p1b 1a8",
    "addr:street":"Main St E",
    "iso:country":"CA",
    "sg:address":"168 Main St E",
    "sg:city":"North Bay",
    "sg:classifiers":[
        {
            "category":"Restaurant",
            "type":"Food & Drink"
        }
    ],
    "sg:phone":"+1 705 476 2374",
    "sg:postcode":"P1B 1A8",
    "sg:province":"ON",
    "sg:tags":[
        "caterer"
    ],
    "wof:name":"Windmill Cafe",
    "wof:placetype":"venue"
},
  "geometry": {"coordinates":[-79.463104,46.309574],"type":"Point"}
}