{
  "type": "Feature",
  "properties": {
    "addr:full":"Vancouver BC V6B 2N7",
    "addr:postcode":"v6b 2n7",
    "iso:country":"CA",
    "sg:city":"Vancouver",
    "sg:classifiers":[
        {
            "category":"Communications",
            "subcategory":"Film & Video Production",
            "type":"Services"
        }
    ],
    "sg:phone":"+1 604 682 2822",
    "sg:postcode":"V6B 2N7",
    "sg:province":"BC",
    "sg:tags":[
        "motion",
        "picture",
        "studio",
        "producer"
    ],
    "wof:name":"Pathway Films Inc",
    "wof:placetype":"venue"
},
  "geometry": {"coordinates":[-123.110405,49.281006],"type":"Point"}
}