{
  "type": "Feature",
  "properties": {
    "addr:full":"RR 2 New Sarepta AB T0B 3M0",
    "addr:postcode":"t0b 3m0",
    "addr:street":"Rr 2",
    "iso:country":"CA",
    "sg:address":"RR 2",
    "sg:city":"New Sarepta",
    "sg:classifiers":[
        {
            "category":"Organizations",
            "subcategory":"Religious Organization",
            "type":"Services"
        }
    ],
    "sg:phone":"+1 403 941 2177",
    "sg:postcode":"T0B 3M0",
    "sg:province":"AB",
    "sg:tags":[
        "church"
    ],
    "wof:name":"New Sarepta Moravian Church",
    "wof:placetype":"venue"
},
  "geometry": {"coordinates":[-113.14743042000001,53.27891922],"type":"Point"}
}