{
  "type": "Feature",
  "properties": {
    "addr:full":"1092 Robson St Vancouver BC V6E 1A7",
    "addr:housenumber":"1092",
    "addr:postcode":"v6e 1a7",
    "addr:street":"Robson St",
    "iso:country":"CA",
    "sg:address":"1092 Robson St",
    "sg:city":"Vancouver",
    "sg:classifiers":[
        {
            "category":"Shopping",
            "subcategory":"News",
            "type":"Retail Goods"
        }
    ],
    "sg:phone":"+1 604 688 0609",
    "sg:postcode":"V6E 1A7",
    "sg:province":"BC",
    "sg:tags":[
        "magazine"
    ],
    "wof:name":"Great Canadian News CO",
    "wof:placetype":"venue"
},
  "geometry": {"coordinates":[-123.124664307,49.2842979431],"type":"Point"}
}