{
  "type": "Feature",
  "properties": {
    "addr:full":"368 Concordia Crt Oshawa ON L1G 8C3",
    "addr:housenumber":"368",
    "addr:postcode":"l1g 8c3",
    "addr:street":"Concordia Crt",
    "iso:country":"CA",
    "sg:address":"368 Concordia Crt",
    "sg:city":"Oshawa",
    "sg:classifiers":[
        {
            "category":"Manufacturing",
            "subcategory":"Lumber",
            "type":"Manufacturing & Wholesale Goods"
        }
    ],
    "sg:phone":"+1 905 723 3309",
    "sg:postcode":"L1G 8C3",
    "sg:province":"ON",
    "sg:tags":[
        "sawmill"
    ],
    "wof:name":"Mobile Sawmill Svc",
    "wof:placetype":"venue"
},
  "geometry": {"coordinates":[-78.8922653198,43.9420852661],"type":"Point"}
}