{
  "type": "Feature",
  "properties": {
    "iso:country":"CA",
    "sg:address":"830 Boul Cadieux",
    "sg:city":"Beauharnois",
    "sg:classifiers":[
        {
            "category":"Health Services",
            "subcategory":"Doctor",
            "type":"Services"
        }
    ],
    "sg:phone":"+1 450 429 7408",
    "sg:postcode":"J6N 2G2",
    "sg:province":"QC",
    "sg:tags":[
        "physician",
        "surgeon"
    ],
    "wof:name":"Gendron, J P MD",
    "wof:placetype":"venue"
},
  "geometry": {"coordinates":[-73.8718490601,45.3028259277],"type":"Point"}
}