{
  "type": "Feature",
  "properties": {
    "iso:country":"CA",
    "sg:address":"620 Rang Du Fleuve",
    "sg:city":"Saint-Barthelemy",
    "sg:classifiers":[
        {
            "category":"Retail",
            "subcategory":"Auto Repair",
            "type":"Services"
        }
    ],
    "sg:phone":"+1 450 885 3625",
    "sg:postcode":"J0K 1X0",
    "sg:province":"QC",
    "sg:tags":[
        "repairing",
        "automobile",
        "body"
    ],
    "wof:name":"Garage Gervais Harmel",
    "wof:placetype":"venue"
},
  "geometry": {"coordinates":[-73.0599899292,46.1550750732],"type":"Point"}
}