{
  "type": "Feature",
  "properties": {
    "addr:full":"Beiseker AB T0M 0G0",
    "addr:postcode":"t0m 0g0",
    "iso:country":"CA",
    "sg:city":"Beiseker",
    "sg:classifiers":[
        {
            "category":"Health Services",
            "subcategory":"Chiropractor",
            "type":"Services"
        }
    ],
    "sg:phone":"+1 403 947 2273",
    "sg:postcode":"T0M 0G0",
    "sg:province":"AB",
    "wof:name":"Mc Clean, K DC",
    "wof:placetype":"venue"
},
  "geometry": {"coordinates":[-113.537696838,51.3847846985],"type":"Point"}
}