{
  "type": "Feature",
  "properties": {
    "addr:full":"465 1E Ave Sainte-Marie QC G6E 3M1",
    "addr:housenumber":"465",
    "addr:postcode":"g6e 3m1",
    "addr:street":"1E Ave",
    "iso:country":"CA",
    "sg:address":"465 1E Ave",
    "sg:city":"Sainte-Marie",
    "sg:classifiers":[
        {
            "category":"Building & Trades",
            "subcategory":"Electrical",
            "type":"Services"
        }
    ],
    "sg:phone":"+1 418 387 6390",
    "sg:postcode":"G6E 3M1",
    "sg:province":"QC",
    "sg:tags":[
        "electric",
        "contractor"
    ],
    "wof:name":"Gilles Grondin Electricite Inc",
    "wof:placetype":"venue"
},
  "geometry": {"coordinates":[-65.98382599999999,48.172626],"type":"Point"}
}