{
  "type": "Feature",
  "properties": {
    "addr:full":"232 Silvercreek Pky N Guelph ON N1H 7P8",
    "addr:housenumber":"232",
    "addr:postcode":"n1h 7p8",
    "addr:street":"Silvercreek Pky N",
    "iso:country":"CA",
    "sg:address":"232 Silvercreek Pky N",
    "sg:city":"Guelph",
    "sg:classifiers":[
        {
            "category":"Food & Beverages",
            "subcategory":"Bakery",
            "type":"Retail Goods"
        }
    ],
    "sg:phone":"+1 519 836 5858",
    "sg:postcode":"N1H 7P8",
    "sg:province":"ON",
    "sg:tags":[
        "doughnut"
    ],
    "wof:name":"Tim Hortons",
    "wof:placetype":"venue"
},
  "geometry": {"coordinates":[-80.28615570069999,43.5439186096],"type":"Point"}
}