{
  "type": "Feature",
  "properties": {
    "addr:full":"1737 Richmond St London ON N5X 3Y2",
    "addr:housenumber":"1737",
    "addr:postcode":"n5x 3y2",
    "addr:street":"Richmond St",
    "iso:country":"CA",
    "sg:address":"1737 Richmond St",
    "sg:city":"London",
    "sg:classifiers":[
        {
            "category":"Shopping",
            "subcategory":"Clothing, Apparel, & Fashions",
            "type":"Retail Goods"
        }
    ],
    "sg:phone":"+1 519 850 9980",
    "sg:postcode":"N5X 3Y2",
    "sg:province":"ON",
    "sg:tags":[
        "furnishing"
    ],
    "wof:name":"Mark's Work Wearhouse Ltd",
    "wof:placetype":"venue"
},
  "geometry": {"coordinates":[-81.2833938599,43.0277328491],"type":"Point"}
}