{
  "type": "Feature",
  "properties": {
    "iso:country":"CA",
    "sg:address":"14 Wright St",
    "sg:city":"St Catharines",
    "sg:classifiers":[
        {
            "category":"Wholesale",
            "subcategory":"Machinery & Supplies",
            "type":"Manufacturing & Wholesale Goods"
        }
    ],
    "sg:phone":"+1 905 688 3810",
    "sg:postcode":"L2P 3J3",
    "sg:province":"ON",
    "sg:tags":[
        "equipment",
        "industrial"
    ],
    "wof:name":"R W Hamilton Ltd",
    "wof:placetype":"venue"
},
  "geometry": {"coordinates":[-79.217201,43.165852],"type":"Point"}
}