{
  "type": "Feature",
  "properties": {
    "addr:full":"29 King St Dryden ON P8N 1B4",
    "addr:housenumber":"29",
    "addr:postcode":"p8n 1b4",
    "addr:street":"King St",
    "iso:country":"CA",
    "sg:address":"29 King St",
    "sg:city":"Dryden",
    "sg:classifiers":[
        {
            "category":"Shopping",
            "subcategory":"Gifts & Souvenirs",
            "type":"Retail Goods"
        }
    ],
    "sg:phone":"+1 807 221 2333",
    "sg:postcode":"P8N 1B4",
    "sg:province":"ON",
    "sg:tags":[
        "shop"
    ],
    "wof:name":"Pam's Pantry",
    "wof:placetype":"venue"
},
  "geometry": {"coordinates":[-92.8396,49.784367],"type":"Point"}
}