{
  "type": "Feature",
  "properties": {
    "addr:full":"491 Chebucto St Baddeck NS B0E 1B0",
    "addr:housenumber":"491",
    "addr:postcode":"b0e 1b0",
    "addr:street":"Chebucto St",
    "iso:country":"CA",
    "sg:address":"491 Chebucto St",
    "sg:city":"Baddeck",
    "sg:classifiers":[
        {
            "category":"Home & Garden",
            "subcategory":"Hardware",
            "type":"Retail Goods"
        }
    ],
    "sg:phone":"+1 902 295 2170",
    "sg:postcode":"B0E 1B0",
    "sg:province":"NS",
    "wof:name":"Baddeck Home Hardware",
    "wof:placetype":"venue"
},
  "geometry": {"coordinates":[-60.749546,46.100815],"type":"Point"}
}