{
  "type": "Feature",
  "properties": {
    "addr:full":"Victoria BC V8T 4N4",
    "addr:postcode":"v8t 4n4",
    "iso:country":"CA",
    "sg:city":"Victoria",
    "sg:classifiers":[
        {
            "category":"Organizations",
            "subcategory":"Professional Association",
            "type":"Services"
        }
    ],
    "sg:phone":"+1 250 386 6196",
    "sg:postcode":"V8T 4N4",
    "sg:province":"BC",
    "wof:name":"Greater Victoria Labour Assn",
    "wof:placetype":"venue"
},
  "geometry": {"coordinates":[-123.369652,48.442844],"type":"Point"}
}