{
  "type": "Feature",
  "properties": {
    "addr:full":"2111 Ch Du Sault Saint-Romuald QC G6W 2K7",
    "addr:postcode":"2111;g6w 2k7",
    "addr:street":"Ch Du Sault",
    "iso:country":"CA",
    "sg:address":"2111 Ch Du Sault",
    "sg:city":"Saint-Romuald",
    "sg:classifiers":[
        {
            "category":"Education",
            "subcategory":"School",
            "type":"Public Place"
        }
    ],
    "sg:phone":"+1 418 839 8851",
    "sg:postcode":"G6W 2K7",
    "sg:province":"QC",
    "wof:name":"Pavillon Du Meandre",
    "wof:placetype":"venue"
},
  "geometry": {"coordinates":[-71.237991333,46.7547988892],"type":"Point"}
}