{
  "type": "Feature",
  "properties": {
    "addr:full":"150 Rue Marchand # 401 Drummondville QC J2C 4N1",
    "addr:housenumber":"150",
    "addr:postcode":"j2c 4n1",
    "addr:street":"Rue Marchand # 401",
    "iso:country":"CA",
    "sg:address":"150 Rue Marchand # 401",
    "sg:city":"Drummondville",
    "sg:classifiers":[
        {
            "category":"Banks & Credit Unions",
            "subcategory":"Investment Brokerage",
            "type":"Services"
        }
    ],
    "sg:phone":"+1 819 477 5024",
    "sg:postcode":"J2C 4N1",
    "sg:province":"QC",
    "wof:name":"Financiere Banque Nationale",
    "wof:placetype":"venue"
},
  "geometry": {"coordinates":[-72.48803700000001,45.883862],"type":"Point"}
}