{
  "type": "Feature",
  "properties": {
    "addr:full":"2617 Argyle St Regina SK S4S 0K2",
    "addr:housenumber":"2617",
    "addr:postcode":"s4s 0k2",
    "addr:street":"Argyle St",
    "iso:country":"CA",
    "sg:address":"2617 Argyle St",
    "sg:city":"Regina",
    "sg:classifiers":[
        {
            "category":"Shopping",
            "subcategory":"Computers & Home Electronics",
            "type":"Retail Goods"
        }
    ],
    "sg:phone":"+1 306 522 3377",
    "sg:postcode":"S4S 0K2",
    "sg:province":"SK",
    "sg:tags":[
        "television",
        "radio"
    ],
    "wof:name":"Zenith Electric",
    "wof:placetype":"venue"
},
  "geometry": {"coordinates":[-104.63239299999999,50.437714],"type":"Point"}
}