{
  "type": "Feature",
  "properties": {
    "iso:country":"CA",
    "sg:address":"2430 Dougall Ave",
    "sg:city":"Windsor",
    "sg:classifiers":[
        {
            "category":"Personal",
            "subcategory":"Beauty Salon",
            "type":"Services"
        }
    ],
    "sg:phone":"+1 519 250 4390",
    "sg:postcode":"N8X 1T2",
    "sg:province":"ON",
    "wof:name":"Frisco's Family Hair Care",
    "wof:placetype":"venue"
},
  "geometry": {"coordinates":[-83.023125,42.287575],"type":"Point"}
}