{
  "type": "Feature",
  "properties": {
    "addr:full":"726 15th St E North Vancouver BC V7L 2S4",
    "addr:housenumber":"726",
    "addr:postcode":"v7l 2s4",
    "addr:street":"15Th St E",
    "iso:country":"CA",
    "sg:address":"726 15th St E",
    "sg:city":"North Vancouver",
    "sg:classifiers":[
        {
            "category":"Manufacturing",
            "subcategory":"Metals",
            "type":"Manufacturing & Wholesale Goods"
        }
    ],
    "sg:phone":"+1 604 988 0006",
    "sg:postcode":"V7L 2S4",
    "sg:province":"BC",
    "sg:tags":[
        "steel"
    ],
    "wof:name":"Abco Enterprises Ltd",
    "wof:placetype":"venue"
},
  "geometry": {"coordinates":[-123.053436,49.322025],"type":"Point"}
}