{
  "type": "Feature",
  "properties": {
    "addr:full":"67 Archibald St Winnipeg MB R2J 0V7",
    "addr:housenumber":"67",
    "addr:postcode":"r2j 0v7",
    "addr:street":"Archibald St",
    "iso:country":"CA",
    "sg:address":"67 Archibald St",
    "sg:city":"Winnipeg",
    "sg:classifiers":[
        {
            "category":"Manufacturing",
            "subcategory":"Printing",
            "type":"Manufacturing & Wholesale Goods"
        }
    ],
    "sg:phone":"+1 204 589 5315",
    "sg:postcode":"R2J 0V7",
    "sg:province":"MB",
    "sg:tags":[
        "printer"
    ],
    "wof:name":"M C Printing",
    "wof:placetype":"venue"
},
  "geometry": {"coordinates":[-97.107376,49.900215],"type":"Point"}
}