{
  "type": "Feature",
  "properties": {
    "addr:full":"1604 Lonsdale Ave North Vancouver BC V7M 2J3",
    "addr:housenumber":"1604",
    "addr:postcode":"v7m 2j3",
    "addr:street":"Lonsdale Ave",
    "iso:country":"CA",
    "sg:address":"1604 Lonsdale Ave",
    "sg:city":"North Vancouver",
    "sg:classifiers":[
        {
            "category":"Retail",
            "subcategory":"Photofinishing",
            "type":"Services"
        }
    ],
    "sg:phone":"+1 604 987 1413",
    "sg:postcode":"V7M 2J3",
    "sg:province":"BC",
    "sg:tags":[
        "photo",
        "production",
        "video",
        "taping"
    ],
    "wof:name":"Unex Professional Group",
    "wof:placetype":"venue"
},
  "geometry": {"coordinates":[-123.072044373,49.3232765198],"type":"Point"}
}