{
  "type": "Feature",
  "properties": {
    "addr:full":"Leduc AB T9E 7L1",
    "addr:postcode":"t9e 7l1",
    "iso:country":"CA",
    "sg:city":"Leduc",
    "sg:classifiers":[
        {
            "category":"Banks & Credit Unions",
            "subcategory":"Investment Brokerage",
            "type":"Services"
        }
    ],
    "sg:phone":"+1 780 986 7412",
    "sg:postcode":"T9E 7L1",
    "sg:province":"AB",
    "sg:tags":[
        "consultant",
        "planning",
        "financial"
    ],
    "wof:name":"Financial Services Group",
    "wof:placetype":"venue"
},
  "geometry": {"coordinates":[-113.545418,53.29187],"type":"Point"}
}