{
  "type": "Feature",
  "properties": {
    "addr:full":"216 2E Av Lac-Etchemin QC G0R 1S0",
    "addr:housenumber":"216",
    "addr:postcode":"g0r 1s0",
    "addr:street":"2E Av Lac-Etchemin",
    "iso:country":"CA",
    "sg:address":"216 2E Av",
    "sg:city":"Lac-Etchemin",
    "sg:classifiers":[
        {
            "category":"Shopping",
            "subcategory":"Catalog Store",
            "type":"Retail Goods"
        }
    ],
    "sg:phone":"+1 418 625 8301",
    "sg:postcode":"G0R 1S0",
    "sg:province":"QC",
    "sg:tags":[
        "mail",
        "order",
        "internet"
    ],
    "wof:name":"Sears Canada Inc",
    "wof:placetype":"venue"
},
  "geometry": {"coordinates":[-70.50494384770001,46.3966026306],"type":"Point"}
}