{
  "type": "Feature",
  "properties": {
    "iso:country":"CA",
    "sg:address":"10839 124 St NW",
    "sg:city":"Edmonton",
    "sg:classifiers":[
        {
            "category":"Health Services",
            "subcategory":"Doctor",
            "type":"Services"
        }
    ],
    "sg:phone":"+1 780 455 6740",
    "sg:postcode":"T5M 0H4",
    "sg:province":"AB",
    "sg:tags":[
        "physician",
        "surgeon"
    ],
    "wof:name":"Yan, Alexander MD",
    "wof:placetype":"venue"
},
  "geometry": {"coordinates":[-113.53566741900001,53.5531272888],"type":"Point"}
}