{
  "type": "Feature",
  "properties": {
    "addr:full":"North York ON M3J 3E5",
    "addr:postcode":"m3j 3e5",
    "iso:country":"CA",
    "sg:city":"North York",
    "sg:classifiers":[
        {
            "category":"Restaurant",
            "type":"Food & Drink"
        }
    ],
    "sg:phone":"+1 416 398 1332",
    "sg:postcode":"M3J 3E5",
    "sg:province":"ON",
    "wof:name":"Deli Break",
    "wof:placetype":"venue"
},
  "geometry": {"coordinates":[-79.46663700000001,43.755348],"type":"Point"}
}