{
  "type": "Feature",
  "properties": {
    "addr:full":"2947 Victoria Rd Carrying Place ON K0K 1L0",
    "addr:housenumber":"2947",
    "addr:postcode":"k0k 1l0",
    "addr:street":"Victoria Rd",
    "iso:country":"CA",
    "sg:address":"2947 Victoria Rd",
    "sg:city":"Carrying Place",
    "sg:classifiers":[
        {
            "category":"Autos & Motor Vehicles",
            "subcategory":"Auto Supplies",
            "type":"Retail Goods"
        }
    ],
    "sg:phone":"+1 613 394 3221",
    "sg:postcode":"K0K 1L0",
    "sg:province":"ON",
    "sg:tags":[
        "equipment",
        "parts",
        "racing",
        "car",
        "automobile"
    ],
    "wof:name":"Quinte Speed & Custom",
    "wof:placetype":"venue"
},
  "geometry": {"coordinates":[-77.580658,44.048294],"type":"Point"}
}