{
  "type": "Feature",
  "properties": {
    "addr:full":"1144 Eglinton Ave W Toronto ON M6C 2E2",
    "addr:housenumber":"1144",
    "addr:postcode":"m6c 2e2",
    "addr:street":"Eglinton Ave W",
    "iso:country":"CA",
    "sg:address":"1144 Eglinton Ave W",
    "sg:city":"Toronto",
    "sg:classifiers":[
        {
            "category":"Restaurant",
            "type":"Food & Drink"
        }
    ],
    "sg:phone":"+1 416 783 5829",
    "sg:postcode":"M6C 2E2",
    "sg:province":"ON",
    "wof:name":"Sabatino's Ristorante",
    "wof:placetype":"venue"
},
  "geometry": {"coordinates":[-79.432541,43.699627],"type":"Point"}
}