{
  "type": "Feature",
  "properties": {
    "addr:full":"3557 Rue Georges-Corbeil Terrebonne QC J6X 4J5",
    "addr:housenumber":"3557",
    "addr:postcode":"j6x 4j5",
    "addr:street":"Rue Georges-Corbeil",
    "iso:country":"CA",
    "sg:address":"3557 Rue Georges-Corbeil",
    "sg:city":"Terrebonne",
    "sg:classifiers":[
        {
            "category":"Wholesale",
            "subcategory":"Machinery & Supplies",
            "type":"Manufacturing & Wholesale Goods"
        }
    ],
    "sg:phone":"+1 450 477 0712",
    "sg:postcode":"J6X 4J5",
    "sg:province":"QC",
    "sg:tags":[
        "compressor",
        "gas"
    ],
    "wof:name":"Compresseur Laval Inc",
    "wof:placetype":"venue"
},
  "geometry": {"coordinates":[-73.6766662598,45.7267303467],"type":"Point"}
}