{
  "type": "Feature",
  "properties": {
    "addr:full":"869 Mcrae Ave Kingsville ON N9Y 2R9",
    "addr:housenumber":"869",
    "addr:postcode":"n9y 2r9",
    "addr:street":"Mcrae Ave",
    "iso:country":"CA",
    "sg:address":"869 Mcrae Ave",
    "sg:city":"Kingsville",
    "sg:classifiers":[
        {
            "category":"Professional",
            "subcategory":"Lawyer & Legal Services",
            "type":"Services"
        }
    ],
    "sg:phone":"+1 519 733 4656",
    "sg:postcode":"N9Y 2R9",
    "sg:province":"ON",
    "sg:tags":[
        "attorney"
    ],
    "wof:name":"Marley, Kenneth",
    "wof:placetype":"venue"
},
  "geometry": {"coordinates":[-82.702003,42.032681],"type":"Point"}
}