{
  "type": "Feature",
  "properties": {
    "addr:full":"Mississauga ON L5T 1Z2",
    "addr:postcode":"l5t 1z2",
    "iso:country":"CA",
    "sg:city":"Mississauga",
    "sg:classifiers":[
        {
            "category":"Manufacturing",
            "subcategory":"Chemicals & Compounds",
            "type":"Manufacturing & Wholesale Goods"
        }
    ],
    "sg:phone":"+1 905 564 0018",
    "sg:postcode":"L5T 1Z2",
    "sg:province":"ON",
    "sg:tags":[
        "preventive",
        "remover",
        "rust"
    ],
    "wof:name":"Lear Chemical Research Corp",
    "wof:placetype":"venue"
},
  "geometry": {"coordinates":[-79.665863,43.64727],"type":"Point"}
}