{
  "type": "Feature",
  "properties": {
    "iso:country":"CA",
    "sg:address":"190 Richmond St",
    "sg:city":"Amherstburg",
    "sg:classifiers":[
        {
            "category":"Recreation",
            "type":"Entertainment"
        }
    ],
    "sg:phone":"+1 519 736 4870",
    "sg:postcode":"N9V 1G4",
    "sg:province":"ON",
    "sg:tags":[
        "hall",
        "auditorium"
    ],
    "wof:name":"Knights of Columbus Hall",
    "wof:placetype":"venue"
},
  "geometry": {"coordinates":[-83.10614013670001,42.1040077209],"type":"Point"}
}