{
  "type": "Feature",
  "properties": {
    "addr:full":"21 Ch Cocagne Sud Cocagne NB E4R 2J7",
    "addr:housenumber":"21",
    "addr:postcode":"e4r 2j7",
    "addr:street":"Ch Cocagne Sud",
    "iso:country":"CA",
    "sg:address":"21 Ch Cocagne Sud",
    "sg:city":"Cocagne",
    "sg:classifiers":[
        {
            "category":"Building & Trades",
            "subcategory":"Construction",
            "type":"Services"
        }
    ],
    "sg:phone":"+1 506 576 7751",
    "sg:postcode":"E4R 2J7",
    "sg:province":"NB",
    "sg:tags":[
        "designer",
        "marine",
        "contractor"
    ],
    "wof:name":"Acadian Dredging Ltd",
    "wof:placetype":"venue"
},
  "geometry": {"coordinates":[-64.6160583496,46.3341026306],"type":"Point"}
}