{
  "type": "Feature",
  "properties": {
    "addr:full":"9938 70 Ave NW Edmonton AB T6E 0V7",
    "addr:housenumber":"9938",
    "addr:postcode":"t6e 0v7",
    "addr:street":"70 Ave Nw",
    "iso:country":"CA",
    "sg:address":"9938 70 Ave NW",
    "sg:city":"Edmonton",
    "sg:classifiers":[
        {
            "category":"Retail",
            "subcategory":"Repair Shop",
            "type":"Services"
        }
    ],
    "sg:phone":"+1 780 439 4618",
    "sg:postcode":"T6E 0V7",
    "sg:province":"AB",
    "sg:tags":[
        "upholsterer"
    ],
    "wof:name":"Grundau's Furniture Edmonton",
    "wof:placetype":"venue"
},
  "geometry": {"coordinates":[-113.487312317,53.506855011],"type":"Point"}
}