{
  "type": "Feature",
  "properties": {
    "addr:full":"650 Kingston Rd Pickering ON L1V 1A6",
    "addr:housenumber":"650",
    "addr:postcode":"l1v 1a6",
    "addr:street":"Kingston Rd",
    "iso:country":"CA",
    "sg:address":"650 Kingston Rd",
    "sg:city":"Pickering",
    "sg:classifiers":[
        {
            "category":"Personal",
            "subcategory":"Beauty Salon",
            "type":"Services"
        }
    ],
    "sg:phone":"+1 905 837 8166",
    "sg:postcode":"L1V 1A6",
    "sg:province":"ON",
    "sg:tags":[
        "manicuring"
    ],
    "wof:name":"Hiphop Nails",
    "wof:placetype":"venue"
},
  "geometry": {"coordinates":[-79.117317,43.817837],"type":"Point"}
}