{
  "type": "Feature",
  "properties": {
    "iso:country":"CA",
    "sg:address":"11989 Place Du Beau-Bois",
    "sg:city":"Montreal",
    "sg:classifiers":[
        {
            "category":"Real Estate",
            "subcategory":"Real Estate Agent",
            "type":"Services"
        }
    ],
    "sg:phone":"+1 514 339 1757",
    "sg:postcode":"H4K 2Y6",
    "sg:province":"QC",
    "sg:tags":[
        "management"
    ],
    "wof:name":"Placements Lomarez Inc",
    "wof:placetype":"venue"
},
  "geometry": {"coordinates":[-73.7340011597,45.5188407898],"type":"Point"}
}