{
  "type": "Feature",
  "properties": {
    "addr:full":"Surrey BC V4A 1R6",
    "addr:postcode":"v4a 1r6",
    "iso:country":"CA",
    "sg:city":"Surrey",
    "sg:classifiers":[
        {
            "category":"Health Services",
            "subcategory":"Doctor",
            "type":"Services"
        }
    ],
    "sg:phone":"+1 604 531 5575",
    "sg:postcode":"V4A 1R6",
    "sg:province":"BC",
    "sg:tags":[
        "physician",
        "surgeon"
    ],
    "wof:name":"Chen, D MD",
    "wof:placetype":"venue"
},
  "geometry": {"coordinates":[-122.798065185,49.0313034058],"type":"Point"}
}