{
  "type": "Feature",
  "properties": {
    "addr:full":"133 Prince William St # 12 Saint John NB E2L 2B5",
    "addr:housenumber":"133;12",
    "addr:postcode":"e2l 2b5",
    "addr:street":"Prince William St #",
    "iso:country":"CA",
    "sg:address":"133 Prince William St # 12",
    "sg:city":"Saint John",
    "sg:classifiers":[
        {
            "category":"Professional",
            "subcategory":"Lawyer & Legal Services",
            "type":"Services"
        }
    ],
    "sg:phone":"+1 506 642 6520",
    "sg:postcode":"E2L 2B5",
    "sg:province":"NB",
    "sg:tags":[
        "attorney"
    ],
    "wof:name":"Roderick, M Barry",
    "wof:placetype":"venue"
},
  "geometry": {"coordinates":[-66.061897,45.270832],"type":"Point"}
}