{
  "type": "Feature",
  "properties": {
    "iso:country":"CA",
    "sg:address":"1200 St Laurent Blvd # 142",
    "sg:city":"Ottawa",
    "sg:classifiers":[
        {
            "category":"Shopping",
            "subcategory":"Jewelry",
            "type":"Retail Goods"
        }
    ],
    "sg:phone":"+1 613 749 3040",
    "sg:postcode":"K1K 3B8",
    "sg:province":"ON",
    "sg:tags":[
        "jeweler"
    ],
    "wof:name":"S D Thompson Jewellers Ltd",
    "wof:placetype":"venue"
},
  "geometry": {"coordinates":[-75.637352,45.423752],"type":"Point"}
}