{
  "type": "Feature",
  "properties": {
    "addr:full":"140 Garden Ave Brantford ON N3S 7W4",
    "addr:housenumber":"140",
    "addr:postcode":"n3s 7w4",
    "addr:street":"Garden Ave",
    "iso:country":"CA",
    "sg:address":"140 Garden Ave",
    "sg:city":"Brantford",
    "sg:classifiers":[
        {
            "category":"Manufacturing",
            "subcategory":"Chemicals & Compounds",
            "type":"Manufacturing & Wholesale Goods"
        }
    ],
    "sg:phone":"+1 519 758 1508",
    "sg:postcode":"N3S 7W4",
    "sg:province":"ON",
    "sg:tags":[
        "paint"
    ],
    "wof:name":"Becker Acroma Inc",
    "wof:placetype":"venue"
},
  "geometry": {"coordinates":[-80.20959499999999,43.155834],"type":"Point"}
}