{
  "type": "Feature",
  "properties": {
    "addr:full":"Calgary AB T2N 3P9",
    "addr:postcode":"t2n 3p9",
    "iso:country":"CA",
    "sg:city":"Calgary",
    "sg:classifiers":[
        {
            "category":"Health Services",
            "subcategory":"Chiropractor",
            "type":"Services"
        }
    ],
    "sg:phone":"+1 403 521 5234",
    "sg:postcode":"T2N 3P9",
    "sg:province":"AB",
    "wof:name":"Alberta Health Institute",
    "wof:placetype":"venue"
},
  "geometry": {"coordinates":[-114.093475,51.052639],"type":"Point"}
}