{
  "type": "Feature",
  "properties": {
    "addr:full":"3 Dunsdon St Brantford ON N3R 3J2",
    "addr:housenumber":"3",
    "addr:postcode":"n3r 3j2",
    "addr:street":"Dunsdon St",
    "iso:country":"CA",
    "sg:address":"3 Dunsdon St",
    "sg:city":"Brantford",
    "sg:classifiers":[
        {
            "category":"Restaurant",
            "type":"Food & Drink"
        }
    ],
    "sg:phone":"+1 519 751 1305",
    "sg:postcode":"N3R 3J2",
    "sg:province":"ON",
    "wof:name":"Taco Bell",
    "wof:placetype":"venue"
},
  "geometry": {"coordinates":[-80.2769699097,43.1730232239],"type":"Point"}
}