{
  "type": "Feature",
  "properties": {
    "addr:full":"505 Harbour Rd Sarnia ON N7T 5R8",
    "addr:housenumber":"505",
    "addr:postcode":"n7t 5r8",
    "addr:street":"Harbour Rd",
    "iso:country":"CA",
    "sg:address":"505 Harbour Rd",
    "sg:city":"Sarnia",
    "sg:classifiers":[
        {
            "category":"Travel",
            "subcategory":"Hotels & Motels",
            "type":"Entertainment"
        }
    ],
    "sg:phone":"+1 519 337 5434",
    "sg:postcode":"N7T 5R8",
    "sg:province":"ON",
    "wof:name":"Harbourfront Inn",
    "wof:placetype":"venue"
},
  "geometry": {"coordinates":[-82.407921,42.984997],"type":"Point"}
}