{
  "type": "Feature",
  "properties": {
    "addr:full":"5 Faulkner St Orangeville ON L9W 2G2",
    "addr:housenumber":"5",
    "addr:postcode":"l9w 2g2",
    "addr:street":"Faulkner St",
    "iso:country":"CA",
    "sg:address":"5 Faulkner St",
    "sg:city":"Orangeville",
    "sg:classifiers":[
        {
            "category":"Organizations",
            "subcategory":"Religious Organization",
            "type":"Services"
        }
    ],
    "sg:phone":"+1 519 941 0690",
    "sg:postcode":"L9W 2G2",
    "sg:province":"ON",
    "wof:name":"Highlands Youth For Christ",
    "wof:placetype":"venue"
},
  "geometry": {"coordinates":[-80.1005783081,43.9208488464],"type":"Point"}
}