{
  "type": "Feature",
  "properties": {
    "addr:full":"Vancouver BC V5Y 3X2",
    "addr:postcode":"v5y 3x2",
    "iso:country":"CA",
    "sg:city":"Vancouver",
    "sg:classifiers":[
        {
            "category":"Professional",
            "subcategory":"Art Services",
            "type":"Services"
        }
    ],
    "sg:phone":"+1 604 687 4812",
    "sg:postcode":"V5Y 3X2",
    "sg:province":"BC",
    "sg:tags":[
        "photographer"
    ],
    "wof:name":"Photex Studio Inc",
    "wof:placetype":"venue"
},
  "geometry": {"coordinates":[-123.111755,49.263752],"type":"Point"}
}