{
  "type": "Feature",
  "properties": {
    "addr:full":"468 Thorold Rd Welland ON L3C 3W6",
    "addr:housenumber":"468",
    "addr:postcode":"l3c 3w6",
    "addr:street":"Thorold Rd",
    "iso:country":"CA",
    "sg:address":"468 Thorold Rd",
    "sg:city":"Welland",
    "sg:classifiers":[
        {
            "category":"Education",
            "subcategory":"School",
            "type":"Public Place"
        }
    ],
    "sg:phone":"+1 905 734 3730",
    "sg:postcode":"L3C 3W6",
    "sg:province":"ON",
    "wof:name":"Gordon School",
    "wof:placetype":"venue"
},
  "geometry": {"coordinates":[-79.27924299999999,43.003883],"type":"Point"}
}