{
  "type": "Feature",
  "properties": {
    "iso:country":"CA",
    "sg:address":"10913 156 St NW",
    "sg:city":"Edmonton",
    "sg:classifiers":[
        {
            "category":"Personal",
            "subcategory":"Beauty Salon",
            "type":"Services"
        }
    ],
    "sg:phone":"+1 780 944 0647",
    "sg:postcode":"T5P 2S7",
    "sg:province":"AB",
    "wof:name":"Cynthia's Family Hair Care",
    "wof:placetype":"venue"
},
  "geometry": {"coordinates":[-113.590164,53.554523],"type":"Point"}
}