{
  "type": "Feature",
  "properties": {
    "addr:full":"1705 4th Ave W Vancouver BC V6J 1M2",
    "addr:housenumber":"1705",
    "addr:postcode":"v6j 1m2",
    "addr:street":"4Th Ave W",
    "iso:country":"CA",
    "sg:address":"1705 4th Ave W",
    "sg:city":"Vancouver",
    "sg:classifiers":[
        {
            "category":"Retail",
            "subcategory":"Animal Services",
            "type":"Services"
        }
    ],
    "sg:phone":"+1 604 732 5416",
    "sg:postcode":"V6J 1M2",
    "sg:province":"BC",
    "sg:tags":[
        "pet",
        "grooming",
        "washing"
    ],
    "wof:name":"Kitsipet Grooming",
    "wof:placetype":"venue"
},
  "geometry": {"coordinates":[-123.143562317,49.2681427002],"type":"Point"}
}