{
  "type": "Feature",
  "properties": {
    "iso:country":"CA",
    "sg:address":"67 Finch Ave W",
    "sg:city":"North York",
    "sg:classifiers":[
        {
            "category":"Building & Trades",
            "subcategory":"Plumbing",
            "type":"Services"
        }
    ],
    "sg:phone":"+1 416 512 0376",
    "sg:postcode":"M2N 2H3",
    "sg:province":"ON",
    "sg:tags":[
        "purifying",
        "system",
        "air",
        "cleaning",
        "contractor",
        "conditioning"
    ],
    "wof:name":"Clean Air Systems Ltd",
    "wof:placetype":"venue"
},
  "geometry": {"coordinates":[-79.42115783689999,43.7783927917],"type":"Point"}
}