{
  "type": "Feature",
  "properties": {
    "addr:full":"Mississauga ON L5P 1A2",
    "addr:postcode":"l5p 1a2",
    "iso:country":"CA",
    "sg:city":"Mississauga",
    "sg:classifiers":[
        {
            "category":"Freight",
            "type":"Transportation"
        }
    ],
    "sg:phone":"+1 905 677 9888",
    "sg:postcode":"L5P 1A2",
    "sg:province":"ON",
    "sg:tags":[
        "broker",
        "customs"
    ],
    "wof:name":"Counselor Customs Brokers Ltd",
    "wof:placetype":"venue"
},
  "geometry": {"coordinates":[-79.63297300000001,43.666271],"type":"Point"}
}