{
  "type": "Feature",
  "properties": {
    "addr:full":"536 Sandford Rd Uxbridge ON L9P 1R1",
    "addr:housenumber":"536",
    "addr:postcode":"l9p 1r1",
    "addr:street":"Sandford Rd",
    "iso:country":"CA",
    "sg:address":"536 Sandford Rd",
    "sg:city":"Uxbridge",
    "sg:classifiers":[
        {
            "category":"Wholesale",
            "subcategory":"Construction Materials",
            "type":"Manufacturing & Wholesale Goods"
        }
    ],
    "sg:phone":"+1 905 852 4335",
    "sg:postcode":"L9P 1R1",
    "sg:province":"ON",
    "sg:tags":[
        "sand",
        "gravel",
        "topsoil"
    ],
    "wof:name":"Sandford Sand & Gravel Inc",
    "wof:placetype":"venue"
},
  "geometry": {"coordinates":[-79.177559,44.142616],"type":"Point"}
}