{
  "type": "Feature",
  "properties": {
    "addr:full":"80 Clyde Ave Mount Pearl NL A1N 4S2",
    "addr:housenumber":"80",
    "addr:postcode":"a1n 4s2",
    "addr:street":"Clyde Ave",
    "iso:country":"CA",
    "sg:address":"80 Clyde Ave",
    "sg:city":"Mount Pearl",
    "sg:classifiers":[
        {
            "category":"Professional",
            "subcategory":"Business Services",
            "type":"Services"
        }
    ],
    "sg:phone":"+1 709 364 3250",
    "sg:postcode":"A1N 4S2",
    "sg:province":"NL",
    "sg:tags":[
        "auctioneer"
    ],
    "wof:name":"Adesa-St Johns",
    "wof:placetype":"venue"
},
  "geometry": {"coordinates":[-52.836029,47.523468],"type":"Point"}
}