{
  "type": "Feature",
  "properties": {
    "addr:full":"PO Box 5844 STN Main Fort Mcmurray AB T9H 4V9",
    "addr:housenumber":"po",
    "addr:postcode":"t9h 4v9",
    "addr:street":"Box 5844 Stn",
    "iso:country":"CA",
    "sg:address":"PO Box 5844 STN Main",
    "sg:city":"Fort Mcmurray",
    "sg:classifiers":[
        {
            "category":"Recreation",
            "type":"Entertainment"
        }
    ],
    "sg:phone":"+1 780 791 1707",
    "sg:postcode":"T9H 4V9",
    "sg:province":"AB",
    "sg:tags":[
        "charter",
        "boat"
    ],
    "wof:name":"Bishop River Hauling",
    "wof:placetype":"venue"
},
  "geometry": {"coordinates":[-111.380302429,56.7271881104],"type":"Point"}
}