{
  "type": "Feature",
  "properties": {
    "addr:full":"499 Dundas St W Trenton ON K8V 6C4",
    "addr:housenumber":"499",
    "addr:postcode":"k8v 6c4",
    "addr:street":"Dundas St W",
    "iso:country":"CA",
    "sg:address":"499 Dundas St W",
    "sg:city":"Trenton",
    "sg:classifiers":[
        {
            "category":"Social Services",
            "type":"Services"
        }
    ],
    "sg:phone":"+1 613 394 4831",
    "sg:postcode":"K8V 6C4",
    "sg:province":"ON",
    "sg:tags":[
        "information",
        "center",
        "family",
        "planning",
        "welfare",
        "organization"
    ],
    "wof:name":"Hastings & Prince Edward Count",
    "wof:placetype":"venue"
},
  "geometry": {"coordinates":[-77.59648900000001,44.094788],"type":"Point"}
}