{
  "type": "Feature",
  "properties": {
    "addr:full":"Windsor ON N9A 4L2",
    "addr:postcode":"n9a 4l2",
    "iso:country":"CA",
    "sg:city":"Windsor",
    "sg:classifiers":[
        {
            "category":"Professional",
            "subcategory":"Business Services",
            "type":"Services"
        }
    ],
    "sg:phone":"+1 519 259 8957",
    "sg:postcode":"N9A 4L2",
    "sg:province":"ON",
    "sg:tags":[
        "paralegal"
    ],
    "wof:name":"AAA Traffic Ticket",
    "wof:placetype":"venue"
},
  "geometry": {"coordinates":[-83.038391,42.314453],"type":"Point"}
}