{
  "type": "Feature",
  "properties": {
    "addr:full":"47 Sturdies Bay Rd Galiano BC V0N 1P0",
    "addr:housenumber":"47",
    "addr:postcode":"v0n 1p0",
    "addr:street":"Sturdies Bay Rd",
    "iso:country":"CA",
    "sg:address":"47 Sturdies Bay Rd",
    "sg:city":"Galiano",
    "sg:classifiers":[
        {
            "category":"Bars & Pubs",
            "type":"Food & Drink"
        }
    ],
    "sg:phone":"+1 250 539 5472",
    "sg:postcode":"V0N 1P0",
    "sg:province":"BC",
    "wof:name":"Hummingbird Inn",
    "wof:placetype":"venue"
},
  "geometry": {"coordinates":[-123.344261,48.890125],"type":"Point"}
}