{
  "type": "Feature",
  "properties": {
    "addr:full":"22833 110 Ave NW Edmonton AB T5S 1Y2",
    "addr:housenumber":"22833",
    "addr:postcode":"t5s 1y2",
    "addr:street":"110 Ave Nw",
    "iso:country":"CA",
    "sg:address":"22833 110 Ave NW",
    "sg:city":"Edmonton",
    "sg:classifiers":[
        {
            "category":"Building & Trades",
            "subcategory":"Construction",
            "type":"Services"
        }
    ],
    "sg:phone":"+1 780 484 4276",
    "sg:postcode":"T5S 1Y2",
    "sg:province":"AB",
    "sg:tags":[
        "foundation",
        "boring",
        "drilling",
        "contractor"
    ],
    "wof:name":"Double Star Drilling Ltd",
    "wof:placetype":"venue"
},
  "geometry": {"coordinates":[-113.709221,53.55706],"type":"Point"}
}