{
  "type": "Feature",
  "properties": {
    "addr:full":"2306 Nepawassi Lake Rd Sudbury ON P3E 4N1",
    "addr:housenumber":"2306",
    "addr:postcode":"p3e 4n1",
    "addr:street":"Nepawassi Lake Rd",
    "iso:country":"CA",
    "sg:address":"2306 Nepawassi Lake Rd",
    "sg:city":"Sudbury",
    "sg:classifiers":[
        {
            "category":"Travel",
            "subcategory":"Campground",
            "type":"Entertainment"
        }
    ],
    "sg:phone":"+1 705 695 2177",
    "sg:postcode":"P3E 4N1",
    "sg:province":"ON",
    "wof:name":"Vacationland Campground",
    "wof:placetype":"venue"
},
  "geometry": {"coordinates":[-80.9896621704,46.4895935059],"type":"Point"}
}