{
  "type": "Feature",
  "properties": {
    "addr:full":"Mississauga ON L4Y 4C1",
    "addr:postcode":"l4y 4c1",
    "iso:country":"CA",
    "sg:city":"Mississauga",
    "sg:classifiers":[
        {
            "category":"Professional",
            "subcategory":"Business Services",
            "type":"Services"
        }
    ],
    "sg:phone":"+1 905 897 9855",
    "sg:postcode":"L4Y 4C1",
    "sg:province":"ON",
    "sg:tags":[
        "appraiser"
    ],
    "wof:name":"Manders Appraisal Inc",
    "wof:placetype":"venue"
},
  "geometry": {"coordinates":[-79.581406,43.598194],"type":"Point"}
}