{
  "type": "Feature",
  "properties": {
    "addr:full":"79 Caradoc St N Strathroy ON N7G 2M5",
    "addr:housenumber":"79",
    "addr:postcode":"n7g 2m5",
    "addr:street":"Caradoc St N",
    "iso:country":"CA",
    "sg:address":"79 Caradoc St N",
    "sg:city":"Strathroy",
    "sg:classifiers":[
        {
            "category":"Insurance",
            "subcategory":"Insurance Agent",
            "type":"Services"
        }
    ],
    "sg:phone":"+1 519 246 1132",
    "sg:postcode":"N7G 2M5",
    "sg:province":"ON",
    "wof:name":"Crossan, Penny",
    "wof:placetype":"venue"
},
  "geometry": {"coordinates":[-81.62329864500001,42.9580345154],"type":"Point"}
}