{
  "type": "Feature",
  "properties": {
    "iso:country":"CA",
    "sg:address":"451 Queensway W",
    "sg:city":"Simcoe",
    "sg:classifiers":[
        {
            "category":"Wholesale",
            "subcategory":"Machinery & Supplies",
            "type":"Manufacturing & Wholesale Goods"
        }
    ],
    "sg:phone":"+1 519 426 3229",
    "sg:postcode":"N3Y 2N4",
    "sg:province":"ON",
    "sg:tags":[
        "contractor"
    ],
    "wof:name":"Phil's Supplies",
    "wof:placetype":"venue"
},
  "geometry": {"coordinates":[-80.3238449097,42.8430137634],"type":"Point"}
}