{
  "type": "Feature",
  "properties": {
    "iso:country":"CA",
    "sg:address":"551 Champlain Blvd",
    "sg:city":"Cambridge",
    "sg:classifiers":[
        {
            "category":"Personal",
            "subcategory":"Beauty Salon",
            "type":"Services"
        }
    ],
    "sg:phone":"+1 519 740 1550",
    "sg:postcode":"N1R 7V1",
    "sg:province":"ON",
    "wof:name":"Zone 26 Hairstyling",
    "wof:placetype":"venue"
},
  "geometry": {"coordinates":[-80.287094,43.348305],"type":"Point"}
}