{
  "type": "Feature",
  "properties": {
    "addr:full":"1123 Glenashton Dr Oakville ON L6H 5M1",
    "addr:housenumber":"1123",
    "addr:postcode":"l6h 5m1",
    "addr:street":"Glenashton Dr",
    "iso:country":"CA",
    "sg:address":"1123 Glenashton Dr",
    "sg:city":"Oakville",
    "sg:classifiers":[
        {
            "category":"Education",
            "subcategory":"School",
            "type":"Public Place"
        }
    ],
    "sg:phone":"+1 905 845 0012",
    "sg:postcode":"L6H 5M1",
    "sg:province":"ON",
    "wof:name":"Iroquois Ridge High School",
    "wof:placetype":"venue"
},
  "geometry": {"coordinates":[-79.6980209351,43.4888877869],"type":"Point"}
}