{
  "type": "Feature",
  "properties": {
    "addr:full":"707 Circle Dr E Saskatoon SK S7K 0V1",
    "addr:housenumber":"707",
    "addr:postcode":"s7k 0v1",
    "addr:street":"Circle Dr E",
    "iso:country":"CA",
    "sg:address":"707 Circle Dr E",
    "sg:city":"Saskatoon",
    "sg:classifiers":[
        {
            "category":"Restaurant",
            "type":"Food & Drink"
        }
    ],
    "sg:phone":"+1 306 933 4430",
    "sg:postcode":"S7K 0V1",
    "sg:province":"SK",
    "wof:name":"Harvey'S/Toast Cafe",
    "wof:placetype":"venue"
},
  "geometry": {"coordinates":[-106.657532,52.157784],"type":"Point"}
}