{
  "type": "Feature",
  "properties": {
    "addr:full":"650 Island Hwy E Parksville BC V9P 1V6",
    "addr:housenumber":"650",
    "addr:postcode":"v9p 1v6",
    "addr:street":"Island Hwy E",
    "iso:country":"CA",
    "sg:address":"650 Island Hwy E",
    "sg:city":"Parksville",
    "sg:classifiers":[
        {
            "category":"Retail",
            "subcategory":"Car Wash",
            "type":"Services"
        }
    ],
    "sg:phone":"+1 250 248 3744",
    "sg:postcode":"V9P 1V6",
    "sg:province":"BC",
    "sg:tags":[
        "polishing",
        "washing"
    ],
    "wof:name":"Husky Parksville Svc",
    "wof:placetype":"venue"
},
  "geometry": {"coordinates":[-124.28993988000001,49.3163871765],"type":"Point"}
}