{
  "type": "Feature",
  "properties": {
    "iso:country":"CA",
    "sg:city":"Acton Vale",
    "sg:classifiers":[
        {
            "category":"Shopping",
            "subcategory":"Clothing, Apparel, & Fashions",
            "type":"Retail Goods"
        }
    ],
    "sg:phone":"+1 450 546 3606",
    "sg:postcode":"J0H 1A0",
    "sg:province":"QC",
    "wof:name":"Lingerie Choiniere",
    "wof:placetype":"venue"
},
  "geometry": {"coordinates":[-72.5658569336,45.6469955444],"type":"Point"}
}