{
  "type": "Feature",
  "properties": {
    "addr:full":"3401 Portage Ave Winnipeg MB R3K 0W9",
    "addr:housenumber":"3401",
    "addr:postcode":"r3k 0w9",
    "addr:street":"Portage Ave",
    "iso:country":"CA",
    "sg:address":"3401 Portage Ave",
    "sg:city":"Winnipeg",
    "sg:classifiers":[
        {
            "category":"Restaurant",
            "type":"Food & Drink"
        }
    ],
    "sg:phone":"+1 204 949 6022",
    "sg:postcode":"R3K 0W9",
    "sg:province":"MB",
    "wof:name":"Mc Donald's",
    "wof:placetype":"venue"
},
  "geometry": {"coordinates":[-97.29945373539999,49.8829269409],"type":"Point"}
}