{
  "type": "Feature",
  "properties": {
    "iso:country":"CA",
    "sg:address":"7725 Rue Cordner",
    "sg:city":"Lasalle",
    "sg:classifiers":[
        {
            "category":"Manufacturing",
            "subcategory":"Food",
            "type":"Manufacturing & Wholesale Goods"
        }
    ],
    "sg:phone":"+1 514 367 0228",
    "sg:postcode":"H8N 2X2",
    "sg:province":"QC",
    "sg:tags":[
        "grocer",
        "product",
        "manufacturer"
    ],
    "wof:name":"Cuisine Bern-Art Inc",
    "wof:placetype":"venue"
},
  "geometry": {"coordinates":[-73.63117200000001,45.440933],"type":"Point"}
}