{
  "type": "Feature",
  "properties": {
    "addr:full":"Ridgetown ON N0P 2C0",
    "addr:postcode":"n0p 2c0",
    "iso:country":"CA",
    "sg:city":"Ridgetown",
    "sg:classifiers":[
        {
            "category":"Travel",
            "subcategory":"Hotels & Motels",
            "type":"Entertainment"
        }
    ],
    "sg:phone":"+1 519 674 5454",
    "sg:postcode":"N0P 2C0",
    "sg:province":"ON",
    "wof:name":"Econo Lodge",
    "wof:placetype":"venue"
},
  "geometry": {"coordinates":[-81.886574,42.439571],"type":"Point"}
}