{
  "type": "Feature",
  "properties": {
    "iso:country":"CA",
    "sg:address":"200 Provost St",
    "sg:city":"New Glasgow",
    "sg:classifiers":[
        {
            "category":"Organizations",
            "subcategory":"Professional Association",
            "type":"Services"
        }
    ],
    "sg:phone":"+1 902 755 9441",
    "sg:postcode":"B2H 2R3",
    "sg:province":"NS",
    "wof:name":"Canadian Mental Health Assn",
    "wof:placetype":"venue"
},
  "geometry": {"coordinates":[-62.6452980042,45.5863304138],"type":"Point"}
}