{
  "type": "Feature",
  "properties": {
    "addr:full":"120 Broad St Regina SK S4R 1W9",
    "addr:housenumber":"120",
    "addr:postcode":"s4r 1w9",
    "addr:street":"Broad St",
    "iso:country":"CA",
    "sg:address":"120 Broad St",
    "sg:city":"Regina",
    "sg:classifiers":[
        {
            "category":"Organizations",
            "subcategory":"Religious Organization",
            "type":"Services"
        }
    ],
    "sg:phone":"+1 306 543 4224",
    "sg:postcode":"S4R 1W9",
    "sg:province":"SK",
    "sg:tags":[
        "church"
    ],
    "wof:name":"Zion United Church",
    "wof:placetype":"venue"
},
  "geometry": {"coordinates":[-104.60667419400001,50.4766311646],"type":"Point"}
}