{
  "type": "Feature",
  "properties": {
    "addr:full":"4300 William St Beamsville ON L0R 1B0",
    "addr:housenumber":"4300",
    "addr:postcode":"l0r 1b0",
    "addr:street":"William St",
    "iso:country":"CA",
    "sg:address":"4300 William St",
    "sg:city":"Beamsville",
    "sg:classifiers":[
        {
            "category":"Education",
            "subcategory":"School",
            "type":"Public Place"
        }
    ],
    "sg:phone":"+1 905 563 8209",
    "sg:postcode":"L0R 1B0",
    "sg:province":"ON",
    "wof:name":"Jacob Beam School",
    "wof:placetype":"venue"
},
  "geometry": {"coordinates":[-79.47895800000001,43.159229],"type":"Point"}
}