{
  "type": "Feature",
  "properties": {
    "iso:country":"CA",
    "sg:address":"82 Groome Ave",
    "sg:city":"Regina",
    "sg:classifiers":[
        {
            "category":"Shopping",
            "subcategory":"Hobbies, Toys, & Games",
            "type":"Retail Goods"
        }
    ],
    "sg:phone":"+1 306 584 5155",
    "sg:postcode":"S4S 6S4",
    "sg:province":"SK",
    "sg:tags":[
        "model",
        "supply"
    ],
    "wof:name":"Trains For Vip",
    "wof:placetype":"venue"
},
  "geometry": {"coordinates":[-104.63069900000001,50.400391],"type":"Point"}
}