{
  "type": "Feature",
  "properties": {
    "addr:full":"Lloydminster AB T9V 2G4",
    "addr:postcode":"t9v 2g4",
    "iso:country":"CA",
    "sg:city":"Lloydminster",
    "sg:classifiers":[
        {
            "category":"Freight",
            "type":"Transportation"
        }
    ],
    "sg:phone":"+1 780 875 5622",
    "sg:postcode":"T9V 2G4",
    "sg:province":"AB",
    "sg:tags":[
        "trucking"
    ],
    "wof:name":"Unrau's Trucking Ltd",
    "wof:placetype":"venue"
},
  "geometry": {"coordinates":[-110.03272247300001,53.2806854248],"type":"Point"}
}