{
  "type": "Feature",
  "properties": {
    "iso:country":"CA",
    "sg:address":"1990 Rue William # B",
    "sg:city":"Montreal",
    "sg:classifiers":[
        {
            "category":"Wholesale",
            "subcategory":"Scrap",
            "type":"Manufacturing & Wholesale Goods"
        }
    ],
    "sg:phone":"+1 514 895 2946",
    "sg:postcode":"H3J 1R8",
    "sg:province":"QC",
    "sg:tags":[
        "metal",
        "iron"
    ],
    "wof:name":"Auto Recyclage",
    "wof:placetype":"venue"
},
  "geometry": {"coordinates":[-73.5680389404,45.4861793518],"type":"Point"}
}