{
  "type": "Feature",
  "properties": {
    "addr:full":"2858 Main St Shubenacadie NS B0N 2H0",
    "addr:housenumber":"2858",
    "addr:postcode":"b0n 2h0",
    "addr:street":"Main St",
    "iso:country":"CA",
    "sg:address":"2858 Main St",
    "sg:city":"Shubenacadie",
    "sg:classifiers":[
        {
            "category":"Health Services",
            "subcategory":"Chiropractor",
            "type":"Services"
        }
    ],
    "sg:phone":"+1 902 758 2240",
    "sg:postcode":"B0N 2H0",
    "sg:province":"NS",
    "wof:name":"East Hants Chiropractic Clinic",
    "wof:placetype":"venue"
},
  "geometry": {"coordinates":[-63.4054489136,45.0886688232],"type":"Point"}
}