{
  "type": "Feature",
  "properties": {
    "iso:country":"CA",
    "sg:address":"5695 Boul Des Forges",
    "sg:city":"Trois-Rivieres",
    "sg:classifiers":[
        {
            "category":"Shopping",
            "subcategory":"Computers & Home Electronics",
            "type":"Retail Goods"
        }
    ],
    "sg:phone":"+1 819 373 7628",
    "sg:postcode":"G8Y 5L5",
    "sg:province":"QC",
    "sg:tags":[
        "supply",
        "high",
        "equipment",
        "stereophonic",
        "fidelity",
        "electronic"
    ],
    "wof:name":"Atelier Electro-Acoustique Tr",
    "wof:placetype":"venue"
},
  "geometry": {"coordinates":[-72.597351,46.364773],"type":"Point"}
}