{
  "type": "Feature",
  "properties": {
    "addr:full":"Burnaby BC V5G 4G3",
    "addr:postcode":"v5g 4g3",
    "iso:country":"CA",
    "sg:city":"Burnaby",
    "sg:classifiers":[
        {
            "category":"Insurance",
            "subcategory":"Insurance Agent",
            "type":"Services"
        }
    ],
    "sg:phone":"+1 604 639 8849",
    "sg:postcode":"V5G 4G3",
    "sg:province":"BC",
    "wof:name":"Travel Insurance Coordinators",
    "wof:placetype":"venue"
},
  "geometry": {"coordinates":[-123.006591797,49.2561950684],"type":"Point"}
}