{
  "type": "Feature",
  "properties": {
    "addr:full":"464 Chilco Ave Kamloops BC V2H 1L9",
    "addr:housenumber":"464",
    "addr:postcode":"bc v2h 1l9",
    "addr:street":"Chilco Ave",
    "iso:country":"CA",
    "sg:address":"464 Chilco Ave",
    "sg:city":"Kamloops",
    "sg:classifiers":[
        {
            "category":"Building & Trades",
            "subcategory":"Construction",
            "type":"Services"
        }
    ],
    "sg:phone":"+1 250 214 4430",
    "sg:postcode":"V2H 1L9",
    "sg:province":"BC",
    "sg:tags":[
        "repairing",
        "remodeling",
        "contractor"
    ],
    "wof:name":"Timberwolf Contracting",
    "wof:placetype":"venue"
},
  "geometry": {"coordinates":[-120.311775208,50.8028450012],"type":"Point"}
}