{
  "type": "Feature",
  "properties": {
    "addr:full":"380 Wellington St London ON N6A 5B5",
    "addr:housenumber":"380",
    "addr:postcode":"n6a 5b5",
    "addr:street":"Wellington St",
    "iso:country":"CA",
    "sg:address":"380 Wellington St",
    "sg:city":"London",
    "sg:classifiers":[
        {
            "category":"Communications",
            "subcategory":"Radio Station",
            "type":"Services"
        }
    ],
    "sg:phone":"+1 519 931 6000",
    "sg:postcode":"N6A 5B5",
    "sg:province":"ON",
    "sg:tags":[
        "company",
        "broadcasting"
    ],
    "wof:name":"Cfpl",
    "wof:placetype":"venue"
},
  "geometry": {"coordinates":[-81.244621,42.9841],"type":"Point"}
}