{
  "type": "Feature",
  "properties": {
    "iso:country":"CA",
    "sg:city":"Strathroy",
    "sg:classifiers":[
        {
            "category":"Retail",
            "subcategory":"Auto Repair",
            "type":"Services"
        }
    ],
    "sg:phone":"+1 519 245 4503",
    "sg:postcode":"N7G 1P1",
    "sg:province":"ON",
    "sg:tags":[
        "repairing",
        "automobile"
    ],
    "wof:name":"Mufflerman",
    "wof:placetype":"venue"
},
  "geometry": {"coordinates":[-81.6212387085,42.9563713074],"type":"Point"}
}