{
  "type": "Feature",
  "properties": {
    "addr:full":"393 Jones Ave Toronto ON M4J 3G5",
    "addr:housenumber":"393",
    "addr:postcode":"m4j 3g5",
    "addr:street":"Jones Ave",
    "iso:country":"CA",
    "sg:address":"393 Jones Ave",
    "sg:city":"Toronto",
    "sg:classifiers":[
        {
            "category":"Building & Trades",
            "subcategory":"Electrical",
            "type":"Services"
        }
    ],
    "sg:phone":"+1 416 463 8639",
    "sg:postcode":"M4J 3G5",
    "sg:province":"ON",
    "sg:tags":[
        "electric",
        "contractor"
    ],
    "wof:name":"Chung's Electric",
    "wof:placetype":"venue"
},
  "geometry": {"coordinates":[-79.3373336792,43.673740387],"type":"Point"}
}