{
  "type": "Feature",
  "properties": {
    "addr:full":"8250 Boul Decarie Montreal QC H4P 2P5",
    "addr:housenumber":"8250",
    "addr:postcode":"h4p 2p5",
    "addr:street":"Boul Decarie",
    "iso:country":"CA",
    "sg:address":"8250 Boul Decarie",
    "sg:city":"Montreal",
    "sg:classifiers":[
        {
            "category":"Professional",
            "subcategory":"Advertising",
            "type":"Services"
        }
    ],
    "sg:phone":"+1 514 735 5191",
    "sg:postcode":"H4P 2P5",
    "sg:province":"QC",
    "sg:tags":[
        "publicity"
    ],
    "wof:name":"Mc Gown-Intermac",
    "wof:placetype":"venue"
},
  "geometry": {"coordinates":[-73.66160600000001,45.499249],"type":"Point"}
}