{
  "type": "Feature",
  "properties": {
    "addr:full":"8249 Mount Olive Cres Niagara Falls ON L2H 2Y9",
    "addr:housenumber":"8249",
    "addr:postcode":"l2h 2y9",
    "addr:street":"Mount Olive Cres",
    "iso:country":"CA",
    "sg:address":"8249 Mount Olive Cres",
    "sg:city":"Niagara Falls",
    "sg:classifiers":[
        {
            "category":"Manufacturing",
            "subcategory":"Food",
            "type":"Manufacturing & Wholesale Goods"
        }
    ],
    "sg:phone":"+1 905 354 7878",
    "sg:postcode":"L2H 2Y9",
    "sg:province":"ON",
    "sg:tags":[
        "winery"
    ],
    "wof:name":"J W Ciatti Wine Brokers",
    "wof:placetype":"venue"
},
  "geometry": {"coordinates":[-79.137046814,43.1203041077],"type":"Point"}
}