{
  "type": "Feature",
  "properties": {
    "addr:full":"400 Rue Des Sagueneens Chicoutimi QC G7H 5S5",
    "addr:housenumber":"400",
    "addr:postcode":"g7h 5s5",
    "addr:street":"Rue Des Sagueneens",
    "iso:country":"CA",
    "sg:address":"400 Rue Des Sagueneens",
    "sg:city":"Chicoutimi",
    "sg:classifiers":[
        {
            "category":"Health Services",
            "subcategory":"Optometrist",
            "type":"Services"
        }
    ],
    "sg:phone":"+1 418 545 9391",
    "sg:postcode":"G7H 5S5",
    "sg:province":"QC",
    "sg:tags":[
        "clinic"
    ],
    "wof:name":"Arseneau & Tremblay",
    "wof:placetype":"venue"
},
  "geometry": {"coordinates":[-71.0593414307,48.4025764465],"type":"Point"}
}