{
  "type": "Feature",
  "properties": {
    "addr:full":"Gravenhurst ON P1P 1X4",
    "addr:postcode":"p1p 1x4",
    "iso:country":"CA",
    "sg:city":"Gravenhurst",
    "sg:classifiers":[
        {
            "category":"Retail",
            "subcategory":"Auto Repair",
            "type":"Services"
        }
    ],
    "sg:phone":"+1 705 687 4746",
    "sg:postcode":"P1P 1X4",
    "sg:province":"ON",
    "sg:tags":[
        "body",
        "automobile",
        "painting"
    ],
    "wof:name":"T & M Autobody",
    "wof:placetype":"venue"
},
  "geometry": {"coordinates":[-79.361649,44.937653],"type":"Point"}
}