{
  "type": "Feature",
  "properties": {
    "iso:country":"CA",
    "sg:address":"245 Mill St",
    "sg:city":"Dundas",
    "sg:classifiers":[
        {
            "category":"Organizations",
            "subcategory":"Religious Organization",
            "type":"Services"
        }
    ],
    "sg:phone":"+1 905 627 2059",
    "sg:postcode":"L9H 2L6",
    "sg:province":"ON",
    "sg:tags":[
        "church"
    ],
    "wof:name":"Christian Science Society",
    "wof:placetype":"venue"
},
  "geometry": {"coordinates":[-79.96611,43.266087],"type":"Point"}
}