{
  "type": "Feature",
  "properties": {
    "addr:full":"1277 St Clair Ave W Toronto ON M6E 1B8",
    "addr:housenumber":"1277",
    "addr:postcode":"m6e 1b8",
    "addr:street":"St Clair Ave W",
    "iso:country":"CA",
    "sg:address":"1277 St Clair Ave W",
    "sg:city":"Toronto",
    "sg:classifiers":[
        {
            "category":"Organizations",
            "subcategory":"Religious Organization",
            "type":"Services"
        }
    ],
    "sg:phone":"+1 416 654 8908",
    "sg:postcode":"M6E 1B8",
    "sg:province":"ON",
    "sg:tags":[
        "church"
    ],
    "wof:name":"St Nicholas of Bari Cath Ch",
    "wof:placetype":"venue"
},
  "geometry": {"coordinates":[-79.44722,43.676933],"type":"Point"}
}