{
  "type": "Feature",
  "properties": {
    "addr:full":"Saint John NB E2J 3T5",
    "addr:postcode":"e2j 3t5",
    "iso:country":"CA",
    "sg:city":"Saint John",
    "sg:classifiers":[
        {
            "category":"Food & Beverages",
            "subcategory":"Groceries & Convenience Stores",
            "type":"Retail Goods"
        }
    ],
    "sg:phone":"+1 506 633 1197",
    "sg:postcode":"E2J 3T5",
    "sg:province":"NB",
    "wof:name":"Handi's Convenience",
    "wof:placetype":"venue"
},
  "geometry": {"coordinates":[-66.027458,45.308449],"type":"Point"}
}