{
  "type": "Feature",
  "properties": {
    "iso:country":"CA",
    "sg:city":"Concord",
    "sg:classifiers":[
        {
            "category":"Manufacturing",
            "subcategory":"Tools & Machinery",
            "type":"Manufacturing & Wholesale Goods"
        }
    ],
    "sg:phone":"+1 905 669 1433",
    "sg:postcode":"L4K 2G4",
    "sg:province":"ON",
    "sg:tags":[
        "machine",
        "shop"
    ],
    "wof:name":"Apollo Machine Shop Ltd",
    "wof:placetype":"venue"
},
  "geometry": {"coordinates":[-79.4971160889,43.8063774109],"type":"Point"}
}