{
  "type": "Feature",
  "properties": {
    "addr:full":"1215 Rainbow St Gloucester ON K1J 6X8",
    "addr:housenumber":"1215",
    "addr:postcode":"k1j 6x8",
    "addr:street":"Rainbow St",
    "iso:country":"CA",
    "sg:address":"1215 Rainbow St",
    "sg:city":"Gloucester",
    "sg:classifiers":[
        {
            "category":"Building & Trades",
            "subcategory":"Construction",
            "type":"Services"
        }
    ],
    "sg:phone":"+1 613 741 8952",
    "sg:postcode":"K1J 6X8",
    "sg:province":"ON",
    "sg:tags":[
        "painter"
    ],
    "wof:name":"Spanish Painting & Decorating",
    "wof:placetype":"venue"
},
  "geometry": {"coordinates":[-75.58678399999999,45.452328],"type":"Point"}
}