{
  "type": "Feature",
  "properties": {
    "addr:full":"360 Mather Blvd Fort Erie ON L2A 4B4",
    "addr:housenumber":"360",
    "addr:postcode":"l2a 4b4",
    "addr:street":"Mather Blvd",
    "iso:country":"CA",
    "sg:address":"360 Mather Blvd",
    "sg:city":"Fort Erie",
    "sg:classifiers":[
        {
            "category":"Manufacturing",
            "subcategory":"Printing",
            "type":"Manufacturing & Wholesale Goods"
        }
    ],
    "sg:phone":"+1 905 871 4131",
    "sg:postcode":"L2A 4B4",
    "sg:province":"ON",
    "sg:tags":[
        "printer"
    ],
    "wof:name":"Printamat Inc",
    "wof:placetype":"venue"
},
  "geometry": {"coordinates":[-78.92372899999999,42.906368],"type":"Point"}
}