{
  "type": "Feature",
  "properties": {
    "iso:country":"CA",
    "sg:address":"1077 Ch DE Saint-Jean",
    "sg:city":"LA Prairie",
    "sg:classifiers":[
        {
            "category":"Health Services",
            "subcategory":"Doctor",
            "type":"Services"
        }
    ],
    "sg:phone":"+1 450 444 3786",
    "sg:postcode":"J5R 2L6",
    "sg:province":"QC",
    "sg:tags":[
        "dentist"
    ],
    "wof:name":"Godin, Daniel DDS",
    "wof:placetype":"venue"
},
  "geometry": {"coordinates":[-73.478508,45.411839],"type":"Point"}
}