{
  "type": "Feature",
  "properties": {
    "addr:full":"5212 Rue Principale Saint-Felix-DE-Valois QC J0K 2M0",
    "addr:housenumber":"5212",
    "addr:postcode":"j0k 2m0",
    "addr:street":"Rue Principale",
    "iso:country":"CA",
    "sg:address":"5212 Rue Principale",
    "sg:city":"Saint-Felix-DE-Valois",
    "sg:classifiers":[
        {
            "category":"Recreation",
            "type":"Entertainment"
        }
    ],
    "sg:phone":"+1 450 889 1888",
    "sg:postcode":"J0K 2M0",
    "sg:province":"QC",
    "sg:tags":[
        "instruction",
        "gymnastic"
    ],
    "wof:name":"Nrj Sante",
    "wof:placetype":"venue"
},
  "geometry": {"coordinates":[-73.4343032837,46.1678771973],"type":"Point"}
}