{
  "type": "Feature",
  "properties": {
    "addr:full":"2011 Av Papineau Montreal QC H2K 4J5",
    "addr:housenumber":"2011",
    "addr:postcode":"h2k 4j5",
    "addr:street":"Av Papineau",
    "iso:country":"CA",
    "sg:address":"2011 Av Papineau",
    "sg:city":"Montreal",
    "sg:classifiers":[
        {
            "category":"Manufacturing",
            "subcategory":"Signs",
            "type":"Manufacturing & Wholesale Goods"
        }
    ],
    "sg:phone":"+1 514 522 7144",
    "sg:postcode":"H2K 4J5",
    "sg:province":"QC",
    "wof:name":"Global Neon",
    "wof:placetype":"venue"
},
  "geometry": {"coordinates":[-73.559578,45.526108],"type":"Point"}
}