{
  "type": "Feature",
  "properties": {
    "addr:full":"Calgary AB T2P 0W7",
    "addr:postcode":"t2p 0w7",
    "iso:country":"CA",
    "sg:city":"Calgary",
    "sg:classifiers":[
        {
            "category":"Mining & Drilling",
            "type":"Manufacturing & Wholesale Goods"
        }
    ],
    "sg:phone":"+1 403 234 0800",
    "sg:postcode":"T2P 0W7",
    "sg:province":"AB",
    "sg:tags":[
        "consultant",
        "oil",
        "gas"
    ],
    "wof:name":"Strat West Ventures Corp",
    "wof:placetype":"venue"
},
  "geometry": {"coordinates":[-114.06577301,51.0466651917],"type":"Point"}
}