{
  "type": "Feature",
  "properties": {
    "addr:full":"Montreal QC H3V 1H8",
    "addr:postcode":"h3v 1h8",
    "iso:country":"CA",
    "sg:city":"Montreal",
    "sg:classifiers":[
        {
            "category":"Health Services",
            "subcategory":"Doctor",
            "type":"Services"
        }
    ],
    "sg:phone":"+1 514 735 5909",
    "sg:postcode":"H3V 1H8",
    "sg:province":"QC",
    "sg:tags":[
        "dentist"
    ],
    "wof:name":"Pham, Huan DDS",
    "wof:placetype":"venue"
},
  "geometry": {"coordinates":[-73.618881,45.495567],"type":"Point"}
}