{
  "type": "Feature",
  "properties": {
    "addr:full":"546 W Island Hwy Parksville BC V9P 1H2",
    "addr:housenumber":"546",
    "addr:postcode":"v9p 1h2",
    "addr:street":"W Island Hwy",
    "iso:country":"CA",
    "sg:address":"546 W Island Hwy",
    "sg:city":"Parksville",
    "sg:classifiers":[
        {
            "category":"Health Services",
            "subcategory":"Medical Lab",
            "type":"Services"
        }
    ],
    "sg:phone":"+1 250 248 3362",
    "sg:postcode":"V9P 1H2",
    "sg:province":"BC",
    "sg:tags":[
        "x"
    ],
    "wof:name":"Parksville X-Ray Ltd",
    "wof:placetype":"venue"
},
  "geometry": {"coordinates":[-124.32962000000001,49.324974],"type":"Point"}
}