{
  "type": "Feature",
  "properties": {
    "addr:full":"58 King St E Brockville ON K6V 1B1",
    "addr:housenumber":"58",
    "addr:postcode":"k6v 1b1",
    "addr:street":"King St",
    "iso:country":"CA",
    "sg:address":"58 King St E",
    "sg:city":"Brockville",
    "sg:classifiers":[
        {
            "category":"Professional",
            "subcategory":"Lawyer & Legal Services",
            "type":"Services"
        }
    ],
    "sg:phone":"+1 613 342 5577",
    "sg:postcode":"K6V 1B1",
    "sg:province":"ON",
    "sg:tags":[
        "attorney"
    ],
    "wof:name":"Hain, David A",
    "wof:placetype":"venue"
},
  "geometry": {"coordinates":[-75.68142700200001,44.5915718079],"type":"Point"}
}