{
  "type": "Feature",
  "properties": {
    "addr:full":"10975 West Saanich Rd North Saanich BC V8L 5P6",
    "addr:housenumber":"10975",
    "addr:postcode":"v8l 5p6",
    "addr:street":"West Saanich Rd",
    "iso:country":"CA",
    "sg:address":"10975 West Saanich Rd",
    "sg:city":"North Saanich",
    "sg:classifiers":[
        {
            "category":"Education",
            "subcategory":"School",
            "type":"Public Place"
        }
    ],
    "sg:phone":"+1 250 656 7254",
    "sg:postcode":"V8L 5P6",
    "sg:province":"BC",
    "wof:name":"Deep Cove Elementary School",
    "wof:placetype":"venue"
},
  "geometry": {"coordinates":[-123.45757293699999,48.6800231934],"type":"Point"}
}