{
  "type": "Feature",
  "properties": {
    "addr:full":"1822 Portage Ave Winnipeg MB R3J 0G5",
    "addr:housenumber":"1822",
    "addr:postcode":"r3j 0g5",
    "addr:street":"Portage Ave",
    "iso:country":"CA",
    "sg:address":"1822 Portage Ave",
    "sg:city":"Winnipeg",
    "sg:classifiers":[
        {
            "category":"Banks & Credit Unions",
            "subcategory":"Bank",
            "type":"Services"
        }
    ],
    "sg:phone":"+1 204 837 3892",
    "sg:postcode":"R3J 0G5",
    "sg:province":"MB",
    "sg:tags":[
        "financing"
    ],
    "wof:name":"Agrifinance",
    "wof:placetype":"venue"
},
  "geometry": {"coordinates":[-97.21440887449999,49.8785362244],"type":"Point"}
}