{
  "type": "Feature",
  "properties": {
    "iso:country":"CA",
    "sg:address":"33 Av Argyle",
    "sg:city":"Saint-Lambert",
    "sg:classifiers":[
        {
            "category":"Health Services",
            "subcategory":"Nursing And Care Facility",
            "type":"Services"
        }
    ],
    "sg:phone":"+1 450 465 1401",
    "sg:postcode":"J4P 3P5",
    "sg:province":"QC",
    "sg:tags":[
        "home",
        "retirement",
        "community"
    ],
    "wof:name":"Residence Du Parc",
    "wof:placetype":"venue"
},
  "geometry": {"coordinates":[-73.514832,45.501675],"type":"Point"}
}