{
  "type": "Feature",
  "properties": {
    "addr:full":"5015 49th Ave Edgerton AB T0B 1K0",
    "addr:housenumber":"5015",
    "addr:postcode":"t0b 1k0",
    "addr:street":"49Th Ave",
    "iso:country":"CA",
    "sg:address":"5015 49th Ave",
    "sg:city":"Edgerton",
    "sg:classifiers":[
        {
            "category":"Autos & Motor Vehicles",
            "subcategory":"Auto Supplies",
            "type":"Retail Goods"
        }
    ],
    "sg:phone":"+1 780 755 3838",
    "sg:postcode":"T0B 1K0",
    "sg:province":"AB",
    "sg:tags":[
        "automobile",
        "parts"
    ],
    "wof:name":"Agri Auto Svc",
    "wof:placetype":"venue"
},
  "geometry": {"coordinates":[-110.46096799999999,52.758469],"type":"Point"}
}