{
  "type": "Feature",
  "properties": {
    "iso:country":"CA",
    "sg:city":"Penticton",
    "sg:classifiers":[
        {
            "category":"Professional",
            "subcategory":"Lawyer & Legal Services",
            "type":"Services"
        }
    ],
    "sg:phone":"+1 250 492 6100",
    "sg:postcode":"V2A 1H1",
    "sg:province":"BC",
    "sg:tags":[
        "attorney"
    ],
    "wof:name":"Duerr, Tyrone A",
    "wof:placetype":"venue"
},
  "geometry": {"coordinates":[-119.59191131599999,49.5014953613],"type":"Point"}
}