{
  "type": "Feature",
  "properties": {
    "addr:full":"611 Ch Des Patriotes Saint-Denis-Sur-Richelieu QC J0H 1K0",
    "addr:housenumber":"611",
    "addr:postcode":"j0h 1k0",
    "addr:street":"Ch Des Patriotes",
    "iso:country":"CA",
    "sg:address":"611 Ch Des Patriotes",
    "sg:city":"Saint-Denis-Sur-Richelieu",
    "sg:classifiers":[
        {
            "category":"Restaurant",
            "type":"Food & Drink"
        }
    ],
    "sg:phone":"+1 450 787 1167",
    "sg:postcode":"J0H 1K0",
    "sg:province":"QC",
    "wof:name":"Restaurant Les Chanterelles",
    "wof:placetype":"venue"
},
  "geometry": {"coordinates":[-73.160034,45.785175],"type":"Point"}
}