{
  "type": "Feature",
  "properties": {
    "addr:full":"59 Scarlett Rd York ON M6N 4J8",
    "addr:housenumber":"59",
    "addr:postcode":"m6n 4j8",
    "addr:street":"Scarlett Rd",
    "iso:country":"CA",
    "sg:address":"59 Scarlett Rd",
    "sg:city":"York",
    "sg:classifiers":[
        {
            "category":"Personal",
            "subcategory":"Beauty Salon",
            "type":"Services"
        }
    ],
    "sg:phone":"+1 416 769 2829",
    "sg:postcode":"M6N 4J8",
    "sg:province":"ON",
    "wof:name":"Nadia Beauty Boutique",
    "wof:placetype":"venue"
},
  "geometry": {"coordinates":[-79.500092,43.667889],"type":"Point"}
}