{
  "type": "Feature",
  "properties": {
    "iso:country":"CA",
    "sg:address":"181 Boul Hymus",
    "sg:city":"Pointe-Claire",
    "sg:classifiers":[
        {
            "category":"Government",
            "subcategory":"Office",
            "type":"Public Place"
        }
    ],
    "sg:phone":"+1 514 695 9311",
    "sg:postcode":"H9R 5P4",
    "sg:province":"QC",
    "wof:name":"Canada Emploi & Immigration",
    "wof:placetype":"venue"
},
  "geometry": {"coordinates":[-73.8172912598,45.4616546631],"type":"Point"}
}