{
  "type": "Feature",
  "properties": {
    "iso:country":"CA",
    "sg:address":"5110 3 St",
    "sg:city":"Boyle",
    "sg:classifiers":[
        {
            "category":"Manufacturing",
            "subcategory":"Motor Vehicles & Parts",
            "type":"Manufacturing & Wholesale Goods"
        }
    ],
    "sg:phone":"+1 780 689 3605",
    "sg:postcode":"T0A 0M0",
    "sg:province":"AB",
    "sg:tags":[
        "equipment",
        "truck",
        "automobile",
        "supply"
    ],
    "wof:name":"Boyle Automotive & Industrial",
    "wof:placetype":"venue"
},
  "geometry": {"coordinates":[-112.807571411,54.5887145996],"type":"Point"}
}