{
  "type": "Feature",
  "properties": {
    "iso:country":"CA",
    "sg:address":"32497 South Fraser Way",
    "sg:city":"Abbotsford",
    "sg:classifiers":[
        {
            "category":"Shopping",
            "type":"Retail Goods"
        }
    ],
    "sg:phone":"+1 604 854 1238",
    "sg:postcode":"V2T 1X4",
    "sg:province":"BC",
    "sg:tags":[
        "pet",
        "food",
        "supply"
    ],
    "wof:name":"Canadian Petcetera Ltd",
    "wof:placetype":"venue"
},
  "geometry": {"coordinates":[-122.315055847,49.0510597229],"type":"Point"}
}