{
  "type": "Feature",
  "properties": {
    "addr:full":"Richmond BC V6Y 3T8",
    "addr:postcode":"v6y 3t8",
    "iso:country":"CA",
    "sg:city":"Richmond",
    "sg:classifiers":[
        {
            "category":"Professional",
            "subcategory":"Lawyer & Legal Services",
            "type":"Services"
        }
    ],
    "sg:phone":"+1 604 273 7575",
    "sg:postcode":"V6Y 3T8",
    "sg:province":"BC",
    "sg:tags":[
        "attorney"
    ],
    "wof:name":"Forbes & Boyle",
    "wof:placetype":"venue"
},
  "geometry": {"coordinates":[-123.134292602,49.1666717529],"type":"Point"}
}