{
  "type": "Feature",
  "properties": {
    "addr:full":"390 Laclie St Orillia ON L3V 4P5",
    "addr:housenumber":"390",
    "addr:postcode":"l3v 4p5",
    "addr:street":"Laclie St",
    "iso:country":"CA",
    "sg:address":"390 Laclie St",
    "sg:city":"Orillia",
    "sg:classifiers":[
        {
            "category":"Insurance",
            "subcategory":"Insurance Agent",
            "type":"Services"
        }
    ],
    "sg:phone":"+1 705 725 7077",
    "sg:postcode":"L3V 4P5",
    "sg:province":"ON",
    "wof:name":"Mc Lean & Dickey Ltd",
    "wof:placetype":"venue"
},
  "geometry": {"coordinates":[-79.422371,44.623363],"type":"Point"}
}