{
  "type": "Feature",
  "properties": {
    "addr:full":"921 Sheppard Ave W North York ON M3H 2T7",
    "addr:housenumber":"921",
    "addr:postcode":"m3h 2t7",
    "addr:street":"Sheppard Ave W",
    "iso:country":"CA",
    "sg:address":"921 Sheppard Ave W",
    "sg:city":"North York",
    "sg:classifiers":[
        {
            "category":"Personal",
            "subcategory":"Beauty Salon",
            "type":"Services"
        }
    ],
    "sg:phone":"+1 416 636 5302",
    "sg:postcode":"M3H 2T7",
    "sg:province":"ON",
    "wof:name":"Roy's Hair",
    "wof:placetype":"venue"
},
  "geometry": {"coordinates":[-79.45742799999999,43.751369],"type":"Point"}
}