{
  "type": "Feature",
  "properties": {
    "addr:full":"1570 Second Ave Trail BC V1R 1M4",
    "addr:housenumber":"1570",
    "addr:postcode":"bc v1r 1m4",
    "addr:street":"Second Ave Trail",
    "iso:country":"CA",
    "sg:address":"1570 Second Ave",
    "sg:city":"Trail",
    "sg:classifiers":[
        {
            "category":"Personal",
            "subcategory":"Shoe Repair & Shine",
            "type":"Services"
        }
    ],
    "sg:phone":"+1 250 364 2339",
    "sg:postcode":"V1R 1M4",
    "sg:province":"BC",
    "sg:tags":[
        "repairing",
        "boot"
    ],
    "wof:name":"Victoria Shoe Repair",
    "wof:placetype":"venue"
},
  "geometry": {"coordinates":[-117.701889038,49.0978164673],"type":"Point"}
}