{
  "type": "Feature",
  "properties": {
    "addr:full":"10431 142 St NW Edmonton AB T5N 2P4",
    "addr:housenumber":"10431",
    "addr:postcode":"t5n 2p4",
    "addr:street":"142 St Nw",
    "iso:country":"CA",
    "sg:address":"10431 142 St NW",
    "sg:city":"Edmonton",
    "sg:classifiers":[
        {
            "category":"Home & Garden",
            "subcategory":"Household Appliances",
            "type":"Retail Goods"
        }
    ],
    "sg:phone":"+1 780 454 2085",
    "sg:postcode":"T5N 2P4",
    "sg:province":"AB",
    "sg:tags":[
        "cleaners",
        "parts",
        "vacuum"
    ],
    "wof:name":"Alberta Vacuum Svc",
    "wof:placetype":"venue"
},
  "geometry": {"coordinates":[-113.565521,53.547192],"type":"Point"}
}