{
  "type": "Feature",
  "properties": {
    "addr:full":"9233 Niagara Pky Niagara Falls ON L2E 6S6",
    "addr:housenumber":"9233",
    "addr:postcode":"l2e 6s6",
    "addr:street":"Niagara Pky",
    "iso:country":"CA",
    "sg:address":"9233 Niagara Pky",
    "sg:city":"Niagara Falls",
    "sg:classifiers":[
        {
            "category":"Sports & Exercise",
            "subcategory":"Golf",
            "type":"Entertainment"
        }
    ],
    "sg:phone":"+1 905 295 9595",
    "sg:postcode":"L2E 6S6",
    "sg:province":"ON",
    "sg:tags":[
        "course"
    ],
    "wof:name":"Niagara Parks Legends",
    "wof:placetype":"venue"
},
  "geometry": {"coordinates":[-79.01834869379999,43.0451316833],"type":"Point"}
}