{
  "type": "Feature",
  "properties": {
    "addr:full":"1595 Bedford Hwy # 154 Bedford NS B4A 3Y4",
    "addr:housenumber":"1595",
    "addr:postcode":"b4a 3y4",
    "addr:street":"Bedford Hwy # 154",
    "iso:country":"CA",
    "sg:address":"1595 Bedford Hwy # 154",
    "sg:city":"Bedford",
    "sg:classifiers":[
        {
            "category":"Shopping",
            "subcategory":"Computers & Home Electronics",
            "type":"Retail Goods"
        }
    ],
    "sg:phone":"+1 902 835 6176",
    "sg:postcode":"B4A 3Y4",
    "sg:province":"NS",
    "sg:tags":[
        "television",
        "radio"
    ],
    "wof:name":"Sony Store",
    "wof:placetype":"venue"
},
  "geometry": {"coordinates":[-63.655972,44.73278],"type":"Point"}
}