{
  "type": "Feature",
  "properties": {
    "addr:full":"139 Lawrence St Liverpool NS B0T 1K0",
    "addr:housenumber":"139",
    "addr:postcode":"b0t 1k0",
    "addr:street":"Lawrence St",
    "iso:country":"CA",
    "sg:address":"139 Lawrence St",
    "sg:city":"Liverpool",
    "sg:classifiers":[
        {
            "category":"Building & Trades",
            "subcategory":"Plumbing",
            "type":"Services"
        }
    ],
    "sg:phone":"+1 902 354 3806",
    "sg:postcode":"B0T 1K0",
    "sg:province":"NS",
    "sg:tags":[
        "contractor"
    ],
    "wof:name":"John Whynot Plumbing Mntnc",
    "wof:placetype":"venue"
},
  "geometry": {"coordinates":[-64.726479,44.037781],"type":"Point"}
}