{
  "type": "Feature",
  "properties": {
    "iso:country":"CA",
    "sg:address":"192 Spadina Ave",
    "sg:city":"Toronto",
    "sg:classifiers":[
        {
            "category":"Professional",
            "subcategory":"Art Services",
            "type":"Services"
        }
    ],
    "sg:phone":"+1 416 364 3573",
    "sg:postcode":"M5T 2C2",
    "sg:province":"ON",
    "sg:tags":[
        "graphic",
        "designer"
    ],
    "wof:name":"Cactus Designs Workshop",
    "wof:placetype":"venue"
},
  "geometry": {"coordinates":[-79.397247,43.650139],"type":"Point"}
}