{
  "type": "Feature",
  "properties": {
    "addr:full":"Cobble Hill BC V0R 1L0",
    "addr:postcode":"bc v0r 1l0",
    "iso:country":"CA",
    "sg:city":"Cobble Hill",
    "sg:classifiers":[
        {
            "category":"Restaurant",
            "type":"Food & Drink"
        }
    ],
    "sg:phone":"+1 250 743 5533",
    "sg:postcode":"V0R 1L0",
    "sg:province":"BC",
    "wof:name":"Friday's",
    "wof:placetype":"venue"
},
  "geometry": {"coordinates":[-123.60353088399999,48.686378479],"type":"Point"}
}