{
  "type": "Feature",
  "properties": {
    "addr:full":"Penticton BC V2A 5E9",
    "addr:postcode":"v2a 5e9",
    "iso:country":"CA",
    "sg:city":"Penticton",
    "sg:classifiers":[
        {
            "category":"Banks & Credit Unions",
            "subcategory":"Investment Brokerage",
            "type":"Services"
        }
    ],
    "sg:phone":"+1 250 492 8806",
    "sg:postcode":"V2A 5E9",
    "sg:province":"BC",
    "sg:tags":[
        "advisory",
        "financial"
    ],
    "wof:name":"Investors Group Financial Svc",
    "wof:placetype":"venue"
},
  "geometry": {"coordinates":[-119.586494,49.484982],"type":"Point"}
}