{
  "type": "Feature",
  "properties": {
    "addr:full":"2294 32E Av Lachine QC H8T 3H4",
    "addr:housenumber":"2294",
    "addr:postcode":"h8t 3h4",
    "addr:street":"32E Av",
    "iso:country":"CA",
    "sg:address":"2294 32E Av",
    "sg:city":"Lachine",
    "sg:classifiers":[
        {
            "category":"Shopping",
            "subcategory":"Computers & Home Electronics",
            "type":"Retail Goods"
        }
    ],
    "sg:phone":"+1 514 631 1891",
    "sg:postcode":"H8T 3H4",
    "sg:province":"QC",
    "sg:tags":[
        "software"
    ],
    "wof:name":"Digi Dyne Inc",
    "wof:placetype":"venue"
},
  "geometry": {"coordinates":[-73.71268463129999,45.4655189514],"type":"Point"}
}