{
  "type": "Feature",
  "properties": {
    "addr:full":"Ottawa ON K1G 3V4",
    "addr:postcode":"k1g 3v4",
    "iso:country":"CA",
    "sg:city":"Ottawa",
    "sg:classifiers":[
        {
            "category":"Insurance",
            "subcategory":"Insurance Agent",
            "type":"Services"
        }
    ],
    "sg:phone":"+1 613 260 5084",
    "sg:postcode":"K1G 3V4",
    "sg:province":"ON",
    "sg:tags":[
        "consultant"
    ],
    "wof:name":"Primerica Financial Svc",
    "wof:placetype":"venue"
},
  "geometry": {"coordinates":[-75.626633,45.405602],"type":"Point"}
}