{
  "type": "Feature",
  "properties": {
    "addr:full":"33 Cada Rd Margaree Forks NS B0E 2A0",
    "addr:housenumber":"33",
    "addr:postcode":"b0e 2a0",
    "addr:street":"Cada Rd",
    "iso:country":"CA",
    "sg:address":"33 Cada Rd",
    "sg:city":"Margaree Forks",
    "sg:classifiers":[
        {
            "category":"Farming",
            "subcategory":"Dairy Farm",
            "type":"Manufacturing & Wholesale Goods"
        }
    ],
    "sg:phone":"+1 902 248 2699",
    "sg:postcode":"B0E 2A0",
    "sg:province":"NS",
    "wof:name":"Farmers Dairy",
    "wof:placetype":"venue"
},
  "geometry": {"coordinates":[-61.096832,46.333508],"type":"Point"}
}