{
  "type": "Feature",
  "properties": {
    "addr:full":"Aylesford NS B0P 1C0",
    "addr:postcode":"b0p 1c0",
    "iso:country":"CA",
    "sg:city":"Aylesford",
    "sg:classifiers":[
        {
            "category":"Government",
            "subcategory":"Office",
            "type":"Public Place"
        }
    ],
    "sg:phone":"+1 902 847 1041",
    "sg:postcode":"B0P 1C0",
    "sg:province":"NS",
    "sg:tags":[
        "village"
    ],
    "wof:name":"Nova Scotia Natural Resources",
    "wof:placetype":"venue"
},
  "geometry": {"coordinates":[-64.8375244141,45.0277938843],"type":"Point"}
}