{
  "type": "Feature",
  "properties": {
    "iso:country":"CA",
    "sg:address":"1490 Ch DE Chambly",
    "sg:city":"Longueuil",
    "sg:classifiers":[
        {
            "category":"Shopping",
            "type":"Retail Goods"
        }
    ],
    "sg:phone":"+1 450 442 1566",
    "sg:postcode":"J4J 3X3",
    "sg:province":"QC",
    "sg:tags":[
        "telephone",
        "cellular"
    ],
    "wof:name":"Tel Expert Rogers At & T",
    "wof:placetype":"venue"
},
  "geometry": {"coordinates":[-73.485710144,45.5309333801],"type":"Point"}
}