{
  "type": "Feature",
  "properties": {
    "addr:full":"Nanaimo BC V9R 5B1",
    "addr:postcode":"v9r 5b1",
    "iso:country":"CA",
    "sg:city":"Nanaimo",
    "sg:classifiers":[
        {
            "category":"Health Services",
            "subcategory":"Doctor",
            "type":"Services"
        }
    ],
    "sg:phone":"+1 250 754 6522",
    "sg:postcode":"V9R 5B1",
    "sg:province":"BC",
    "sg:tags":[
        "dentist"
    ],
    "wof:name":"A L Pastro Inc",
    "wof:placetype":"venue"
},
  "geometry": {"coordinates":[-123.94149,49.1679],"type":"Point"}
}