{
  "type": "Feature",
  "properties": {
    "addr:full":"623 1st Rue O Barraute QC J0Y 1A0",
    "addr:housenumber":"623",
    "addr:postcode":"j0y 1a0",
    "addr:street":"1St Rue O",
    "iso:country":"CA",
    "sg:address":"623 1st Rue O",
    "sg:city":"Barraute",
    "sg:classifiers":[
        {
            "category":"Home & Garden",
            "subcategory":"Hardware",
            "type":"Retail Goods"
        }
    ],
    "sg:phone":"+1 819 734 6425",
    "sg:postcode":"J0Y 1A0",
    "sg:province":"QC",
    "sg:tags":[
        "building",
        "material"
    ],
    "wof:name":"Centre DE Renovation Barraute",
    "wof:placetype":"venue"
},
  "geometry": {"coordinates":[-77.63735200000001,48.439377],"type":"Point"}
}