{
  "type": "Feature",
  "properties": {
    "addr:full":"586 Metcalfe St E Strathroy ON N7G 1R7",
    "addr:housenumber":"586",
    "addr:postcode":"n7g 1r7",
    "addr:street":"Metcalfe St E",
    "iso:country":"CA",
    "sg:address":"586 Metcalfe St E",
    "sg:city":"Strathroy",
    "sg:classifiers":[
        {
            "category":"Building & Trades",
            "subcategory":"Construction",
            "type":"Services"
        }
    ],
    "sg:phone":"+1 519 245 2422",
    "sg:postcode":"N7G 1R7",
    "sg:province":"ON",
    "sg:tags":[
        "general",
        "contractor"
    ],
    "wof:name":"Glen Robson General Cnstrctn",
    "wof:placetype":"venue"
},
  "geometry": {"coordinates":[-81.60573599999999,42.966751],"type":"Point"}
}