{
  "type": "Feature",
  "properties": {
    "addr:full":"401 Queensway W Simcoe ON N3Y 2N4",
    "addr:housenumber":"401",
    "addr:postcode":"n3y 2n4",
    "addr:street":"Queensway W",
    "iso:country":"CA",
    "sg:address":"401 Queensway W",
    "sg:city":"Simcoe",
    "sg:classifiers":[
        {
            "category":"Retail",
            "subcategory":"Auto Repair",
            "type":"Services"
        }
    ],
    "sg:phone":"+1 519 428 0501",
    "sg:postcode":"N3Y 2N4",
    "sg:province":"ON",
    "sg:tags":[
        "truck"
    ],
    "wof:name":"Wilson Truck & Trailer",
    "wof:placetype":"venue"
},
  "geometry": {"coordinates":[-80.32055699999999,42.843815],"type":"Point"}
}