{
  "type": "Feature",
  "properties": {
    "addr:full":"23352 Mckay Ave Maple Ridge BC V2W 1B9",
    "addr:housenumber":"23352",
    "addr:postcode":"v2w 1b9",
    "addr:street":"Mckay Ave",
    "iso:country":"CA",
    "sg:address":"23352 Mckay Ave",
    "sg:city":"Maple Ridge",
    "sg:classifiers":[
        {
            "category":"Manufacturing",
            "subcategory":"Lumber",
            "type":"Manufacturing & Wholesale Goods"
        }
    ],
    "sg:phone":"+1 604 467 2544",
    "sg:postcode":"V2W 1B9",
    "sg:province":"BC",
    "wof:name":"Haney Cedar Products Ltd",
    "wof:placetype":"venue"
},
  "geometry": {"coordinates":[-122.574127,49.191216],"type":"Point"}
}