{
  "type": "Feature",
  "properties": {
    "iso:country":"CA",
    "sg:address":"1273 London Rd",
    "sg:city":"Sarnia",
    "sg:classifiers":[
        {
            "category":"Restaurant",
            "type":"Food & Drink"
        }
    ],
    "sg:phone":"+1 519 383 8000",
    "sg:postcode":"N7S 1P3",
    "sg:province":"ON",
    "wof:name":"Dragon Palace",
    "wof:placetype":"venue"
},
  "geometry": {"coordinates":[-82.3591766357,42.9796295166],"type":"Point"}
}