{
  "type": "Feature",
  "properties": {
    "iso:country":"CA",
    "sg:address":"53 Mallory Cres",
    "sg:city":"East York",
    "sg:classifiers":[
        {
            "category":"Organizations",
            "subcategory":"Professional Association",
            "type":"Services"
        }
    ],
    "sg:phone":"+1 416 696 7621",
    "sg:postcode":"M4G 3L6",
    "sg:province":"ON",
    "wof:name":"Women Like me",
    "wof:placetype":"venue"
},
  "geometry": {"coordinates":[-79.3667297363,43.695400238],"type":"Point"}
}