{
  "type": "Feature",
  "properties": {
    "addr:full":"430 Queen St Charlottetown PE C1A 4E7",
    "addr:housenumber":"430",
    "addr:postcode":"c1a 4e7",
    "addr:street":"Queen St",
    "iso:country":"CA",
    "sg:address":"430 Queen St",
    "sg:city":"Charlottetown",
    "sg:classifiers":[
        {
            "category":"Wholesale",
            "subcategory":"Electrical",
            "type":"Manufacturing & Wholesale Goods"
        }
    ],
    "sg:phone":"+1 902 368 8433",
    "sg:postcode":"C1A 4E7",
    "sg:province":"PE",
    "sg:tags":[
        "burglar",
        "supply",
        "alarm",
        "telephone",
        "system",
        "equipment"
    ],
    "wof:name":"Dpt Communications",
    "wof:placetype":"venue"
},
  "geometry": {"coordinates":[-63.136185,46.242401],"type":"Point"}
}