{
  "type": "Feature",
  "properties": {
    "addr:full":"2495 Coho Rd Campbell River BC V9W 4W3",
    "addr:housenumber":"2495",
    "addr:postcode":"v9w 4w3",
    "addr:street":"Coho Rd",
    "iso:country":"CA",
    "sg:address":"2495 Coho Rd",
    "sg:city":"Campbell River",
    "sg:classifiers":[
        {
            "category":"Freight",
            "type":"Transportation"
        }
    ],
    "sg:phone":"+1 250 286 6557",
    "sg:postcode":"V9W 4W3",
    "sg:province":"BC",
    "sg:tags":[
        "hauling",
        "log",
        "trucking"
    ],
    "wof:name":"Brian Thompson Trucking Ltd",
    "wof:placetype":"venue"
},
  "geometry": {"coordinates":[-125.282394,50.040562],"type":"Point"}
}