{
  "type": "Feature",
  "properties": {
    "iso:country":"CA",
    "sg:address":"15 Robinson St N",
    "sg:city":"Grimsby",
    "sg:classifiers":[
        {
            "category":"Building & Trades",
            "subcategory":"Construction",
            "type":"Services"
        }
    ],
    "sg:phone":"+1 905 309 1315",
    "sg:postcode":"L3M 3C8",
    "sg:province":"ON",
    "sg:tags":[
        "repairing",
        "lane",
        "refinishing",
        "bowling"
    ],
    "wof:name":"Capiset Consulting",
    "wof:placetype":"venue"
},
  "geometry": {"coordinates":[-79.556961,43.19268],"type":"Point"}
}