{
  "type": "Feature",
  "properties": {
    "addr:full":"10725 King George Hwy Surrey BC V3T 2X6",
    "addr:housenumber":"10725",
    "addr:postcode":"v3t 2x6",
    "addr:street":"King George Hwy",
    "iso:country":"CA",
    "sg:address":"10725 King George Hwy",
    "sg:city":"Surrey",
    "sg:classifiers":[
        {
            "category":"Food & Beverages",
            "subcategory":"Specialty",
            "type":"Retail Goods"
        }
    ],
    "sg:phone":"+1 604 583 0466",
    "sg:postcode":"V3T 2X6",
    "sg:province":"BC",
    "sg:tags":[
        "delicatessen",
        "ukrainian"
    ],
    "wof:name":"Krakus Deli Store",
    "wof:placetype":"venue"
},
  "geometry": {"coordinates":[-122.845466614,49.1916389465],"type":"Point"}
}