{
  "type": "Feature",
  "properties": {
    "iso:country":"CA",
    "sg:address":"245 Robie St",
    "sg:city":"Truro",
    "sg:classifiers":[
        {
            "category":"Professional",
            "subcategory":"Accounting & Tax Preparation",
            "type":"Services"
        }
    ],
    "sg:phone":"+1 902 893 7575",
    "sg:postcode":"B2N 5N6",
    "sg:province":"NS",
    "sg:tags":[
        "return",
        "filing"
    ],
    "wof:name":"Tax 2000",
    "wof:placetype":"venue"
},
  "geometry": {"coordinates":[-63.303237915,45.3695487976],"type":"Point"}
}