{
  "type": "Feature",
  "properties": {
    "addr:full":"Sainte-Anne-Des-Monts QC G4V 1P5",
    "addr:postcode":"g4v 1p5",
    "iso:country":"CA",
    "sg:city":"Sainte-Anne-Des-Monts",
    "sg:classifiers":[
        {
            "category":"Shopping",
            "subcategory":"Books",
            "type":"Retail Goods"
        }
    ],
    "sg:phone":"+1 418 763 5052",
    "sg:postcode":"G4V 1P5",
    "sg:province":"QC",
    "sg:tags":[
        "dealer"
    ],
    "wof:name":"Librairie L'Expression",
    "wof:placetype":"venue"
},
  "geometry": {"coordinates":[-66.48638916020001,49.1292114258],"type":"Point"}
}