{
  "type": "Feature",
  "properties": {
    "iso:country":"CA",
    "sg:address":"307 Birch St",
    "sg:city":"Kelvington",
    "sg:classifiers":[
        {
            "category":"Food & Beverages",
            "subcategory":"Specialty",
            "type":"Retail Goods"
        }
    ],
    "sg:phone":"+1 306 327 4651",
    "sg:postcode":"S0A 1W0",
    "sg:province":"SK",
    "sg:tags":[
        "water",
        "bulk",
        "company"
    ],
    "wof:name":"B & D Enterprises",
    "wof:placetype":"venue"
},
  "geometry": {"coordinates":[-103.53113555900001,52.1644210815],"type":"Point"}
}