{
  "type": "Feature",
  "properties": {
    "addr:full":"711 Leola St Winnipeg MB R2C 3R3",
    "addr:housenumber":"711",
    "addr:postcode":"r2c 3r3",
    "addr:street":"Leola St",
    "iso:country":"CA",
    "sg:address":"711 Leola St",
    "sg:city":"Winnipeg",
    "sg:classifiers":[
        {
            "category":"Recreation",
            "type":"Entertainment"
        }
    ],
    "sg:phone":"+1 204 222 0889",
    "sg:postcode":"R2C 3R3",
    "sg:province":"MB",
    "sg:tags":[
        "hall",
        "auditorium"
    ],
    "wof:name":"Assumption Parish Hall",
    "wof:placetype":"venue"
},
  "geometry": {"coordinates":[-96.9936752319,49.8984718323],"type":"Point"}
}