{
  "type": "Feature",
  "properties": {
    "addr:full":"14993 Rue Jean-Simon Mirabel QC J7N 1Z1",
    "addr:housenumber":"14993",
    "addr:postcode":"j7n 1z1",
    "addr:street":"Rue Jean-Simon",
    "iso:country":"CA",
    "sg:address":"14993 Rue Jean-Simon",
    "sg:city":"Mirabel",
    "sg:classifiers":[
        {
            "category":"Professional",
            "subcategory":"Detective & Security Services",
            "type":"Services"
        }
    ],
    "sg:phone":"+1 450 475 7586",
    "sg:postcode":"J7N 1Z1",
    "sg:province":"QC",
    "sg:tags":[
        "burglary",
        "protective",
        "robbery"
    ],
    "wof:name":"Alarme Mirabel Inc",
    "wof:placetype":"venue"
},
  "geometry": {"coordinates":[-73.984306,45.628773],"type":"Point"}
}