{
  "type": "Feature",
  "properties": {
    "addr:full":"Concord ON L4K 2Z5",
    "addr:postcode":"l4k 2z5",
    "iso:country":"CA",
    "sg:city":"Concord",
    "sg:classifiers":[
        {
            "category":"Professional",
            "subcategory":"Accounting & Tax Preparation",
            "type":"Services"
        }
    ],
    "sg:phone":"+1 905 738 0047",
    "sg:postcode":"L4K 2Z5",
    "sg:province":"ON",
    "sg:tags":[
        "accountant",
        "attorney"
    ],
    "wof:name":"Finstein, Jeffrey CA",
    "wof:placetype":"venue"
},
  "geometry": {"coordinates":[-79.49314117430001,43.7820014954],"type":"Point"}
}