{
  "type": "Feature",
  "properties": {
    "addr:full":"210 Church St Belleville ON K8N 3C3",
    "addr:housenumber":"210",
    "addr:postcode":"k8n 3c3",
    "addr:street":"Church St",
    "iso:country":"CA",
    "sg:address":"210 Church St",
    "sg:city":"Belleville",
    "sg:classifiers":[
        {
            "category":"Professional",
            "subcategory":"Lawyer & Legal Services",
            "type":"Services"
        }
    ],
    "sg:phone":"+1 613 969 8346",
    "sg:postcode":"K8N 3C3",
    "sg:province":"ON",
    "sg:tags":[
        "attorney"
    ],
    "wof:name":"Black, Michael A",
    "wof:placetype":"venue"
},
  "geometry": {"coordinates":[-77.3814620972,44.1647605896],"type":"Point"}
}