{
  "type": "Feature",
  "properties": {
    "addr:full":"112 Kent St # P4 Ottawa ON K1P 5P2",
    "addr:housenumber":"112",
    "addr:postcode":"k1p 5p2",
    "addr:street":"Kent St # P4",
    "iso:country":"CA",
    "sg:address":"112 Kent St # P4",
    "sg:city":"Ottawa",
    "sg:classifiers":[
        {
            "category":"Building & Trades",
            "subcategory":"Cleaning & Sanitation",
            "type":"Services"
        }
    ],
    "sg:phone":"+1 613 567 6555",
    "sg:postcode":"K1P 5P2",
    "sg:province":"ON",
    "sg:tags":[
        "janitor"
    ],
    "wof:name":"Hallmark Housekeeping Svc",
    "wof:placetype":"venue"
},
  "geometry": {"coordinates":[-75.702957,45.41954],"type":"Point"}
}