{
  "type": "Feature",
  "properties": {
    "iso:country":"CA",
    "sg:address":"52 Abelard Ave",
    "sg:city":"Brampton",
    "sg:classifiers":[
        {
            "category":"Building & Trades",
            "subcategory":"Electrical",
            "type":"Services"
        }
    ],
    "sg:phone":"+1 905 450 5703",
    "sg:postcode":"L6Y 2K8",
    "sg:province":"ON",
    "sg:tags":[
        "system",
        "home",
        "automation",
        "insurance",
        "consultant"
    ],
    "wof:name":"Intrusion Technologies Corp",
    "wof:placetype":"venue"
},
  "geometry": {"coordinates":[-79.754868,43.658115],"type":"Point"}
}