{
  "type": "Feature",
  "properties": {
    "iso:country":"CA",
    "sg:address":"979 Wellington Rd",
    "sg:city":"London",
    "sg:classifiers":[
        {
            "category":"Health Services",
            "subcategory":"Optometrist",
            "type":"Services"
        }
    ],
    "sg:phone":"+1 519 649 7415",
    "sg:postcode":"N6E 3A9",
    "sg:province":"ON",
    "wof:name":"Cook, Greg K OD",
    "wof:placetype":"venue"
},
  "geometry": {"coordinates":[-81.225037,42.939636],"type":"Point"}
}