{
  "type": "Feature",
  "properties": {
    "addr:full":"651 Sandhurst Ave Winnipeg MB R2L 1B1",
    "addr:housenumber":"651",
    "addr:postcode":"r2l 1b1",
    "addr:street":"Sandhurst Ave",
    "iso:country":"CA",
    "sg:address":"651 Sandhurst Ave",
    "sg:city":"Winnipeg",
    "sg:classifiers":[
        {
            "category":"Organizations",
            "subcategory":"Religious Organization",
            "type":"Services"
        }
    ],
    "sg:phone":"+1 204 667 9413",
    "sg:postcode":"R2L 1B1",
    "sg:province":"MB",
    "sg:tags":[
        "church"
    ],
    "wof:name":"Grey St United Church",
    "wof:placetype":"venue"
},
  "geometry": {"coordinates":[-97.091476,49.90694],"type":"Point"}
}