{
  "type": "Feature",
  "properties": {
    "addr:full":"1599 Quinn St S Prince George BC V2N 4W6",
    "addr:housenumber":"1599",
    "addr:postcode":"v2n 4w6",
    "addr:street":"Quinn St S",
    "iso:country":"CA",
    "sg:address":"1599 Quinn St S",
    "sg:city":"Prince George",
    "sg:classifiers":[
        {
            "category":"Retail",
            "subcategory":"Auto Repair",
            "type":"Services"
        }
    ],
    "sg:phone":"+1 250 562 7116",
    "sg:postcode":"V2N 4W6",
    "sg:province":"BC",
    "sg:tags":[
        "body",
        "automobile",
        "painting"
    ],
    "wof:name":"Klassic Auto Body",
    "wof:placetype":"venue"
},
  "geometry": {"coordinates":[-122.792007446,53.909362793],"type":"Point"}
}