{
  "type": "Feature",
  "properties": {
    "addr:full":"103414 Hwy 7 Marmora ON K0K 2M0",
    "addr:housenumber":"103414",
    "addr:postcode":"k0k 2m0",
    "addr:street":"Hwy 7",
    "iso:country":"CA",
    "sg:address":"103414 Hwy 7",
    "sg:city":"Marmora",
    "sg:classifiers":[
        {
            "category":"Shopping",
            "subcategory":"Books",
            "type":"Retail Goods"
        }
    ],
    "sg:phone":"+1 613 472 0081",
    "sg:postcode":"K0K 2M0",
    "sg:province":"ON",
    "sg:tags":[
        "religious"
    ],
    "wof:name":"Saint Joseph's Cabin",
    "wof:placetype":"venue"
},
  "geometry": {"coordinates":[-77.688019,44.480358],"type":"Point"}
}