{
  "type": "Feature",
  "properties": {
    "addr:full":"605 James St N Hamilton ON L8L 1J9",
    "addr:housenumber":"605",
    "addr:postcode":"l8l 1j9",
    "addr:street":"James St N",
    "iso:country":"CA",
    "sg:address":"605 James St N",
    "sg:city":"Hamilton",
    "sg:classifiers":[
        {
            "category":"Recreation",
            "subcategory":"Marina",
            "type":"Entertainment"
        }
    ],
    "sg:phone":"+1 905 525 4330",
    "sg:postcode":"L8L 1J9",
    "sg:province":"ON",
    "wof:name":"Hamilton Port Authorities",
    "wof:placetype":"venue"
},
  "geometry": {"coordinates":[-79.862106,43.272892],"type":"Point"}
}