{
  "type": "Feature",
  "properties": {
    "iso:country":"CA",
    "sg:city":"Markham",
    "sg:classifiers":[
        {
            "category":"Autos & Motor Vehicles",
            "subcategory":"Auto Supplies",
            "type":"Retail Goods"
        }
    ],
    "sg:phone":"+1 905 415 2622",
    "sg:postcode":"L3R 2Z6",
    "sg:province":"ON",
    "sg:tags":[
        "glass",
        "sunroof",
        "automobile"
    ],
    "wof:name":"A Apple Auto Glass",
    "wof:placetype":"venue"
},
  "geometry": {"coordinates":[-79.329575,43.826626],"type":"Point"}
}