{
  "type": "Feature",
  "properties": {
    "addr:full":"1485 Star Top Rd Gloucester ON K1B 3W5",
    "addr:housenumber":"1485",
    "addr:postcode":"k1b 3w5",
    "addr:street":"Star Top Rd",
    "iso:country":"CA",
    "sg:address":"1485 Star Top Rd",
    "sg:city":"Gloucester",
    "sg:classifiers":[
        {
            "category":"Wholesale",
            "subcategory":"Auto Parts",
            "type":"Manufacturing & Wholesale Goods"
        }
    ],
    "sg:phone":"+1 613 746 9797",
    "sg:postcode":"K1B 3W5",
    "sg:province":"ON",
    "sg:tags":[
        "equipment",
        "towing"
    ],
    "wof:name":"Gervais Equipment Sales & Svc",
    "wof:placetype":"venue"
},
  "geometry": {"coordinates":[-75.616272,45.417004],"type":"Point"}
}