{
  "type": "Feature",
  "properties": {
    "addr:full":"5148 Metral Dr # 1 Nanaimo BC V9T 2K8",
    "addr:housenumber":"5148",
    "addr:postcode":"v9t 2k8",
    "addr:street":"Metral Dr # 1",
    "iso:country":"CA",
    "sg:address":"5148 Metral Dr # 1",
    "sg:city":"Nanaimo",
    "sg:classifiers":[
        {
            "category":"Insurance",
            "subcategory":"Insurance Agent",
            "type":"Services"
        }
    ],
    "sg:phone":"+1 250 729 7918",
    "sg:postcode":"V9T 2K8",
    "sg:province":"BC",
    "wof:name":"Pfsl Investments Canada Ltd",
    "wof:placetype":"venue"
},
  "geometry": {"coordinates":[-124.031860352,49.2158889771],"type":"Point"}
}