{
  "type": "Feature",
  "properties": {
    "addr:full":"Calgary AB T2H 1G5",
    "addr:postcode":"t2h 1g5",
    "iso:country":"CA",
    "sg:city":"Calgary",
    "sg:classifiers":[
        {
            "category":"Real Estate",
            "subcategory":"Real Estate Operator",
            "type":"Services"
        }
    ],
    "sg:phone":"+1 403 253 9679",
    "sg:postcode":"T2H 1G5",
    "sg:province":"AB",
    "sg:tags":[
        "apartment"
    ],
    "wof:name":"Hillsboro Place Apartments",
    "wof:placetype":"venue"
},
  "geometry": {"coordinates":[-114.062774658,50.9799003601],"type":"Point"}
}