{
  "type": "Feature",
  "properties": {
    "addr:full":"791 Tapscott Rd Scarborough ON M1X 1A2",
    "addr:housenumber":"791",
    "addr:postcode":"m1x 1a2",
    "addr:street":"Tapscott Rd",
    "iso:country":"CA",
    "sg:address":"791 Tapscott Rd",
    "sg:city":"Scarborough",
    "sg:classifiers":[
        {
            "category":"Wholesale",
            "subcategory":"Sporting Goods",
            "type":"Manufacturing & Wholesale Goods"
        }
    ],
    "sg:phone":"+1 416 412 3665",
    "sg:postcode":"M1X 1A2",
    "sg:province":"ON",
    "wof:name":"Match Sports Intl Inc",
    "wof:placetype":"venue"
},
  "geometry": {"coordinates":[-79.239440918,43.8179626465],"type":"Point"}
}