{
  "type": "Feature",
  "properties": {
    "addr:full":"3088 Boul Cartier O Laval QC H7V 1J5",
    "addr:housenumber":"3088",
    "addr:postcode":"h7v 1j5",
    "addr:street":"Boul Cartier O",
    "iso:country":"CA",
    "sg:address":"3088 Boul Cartier O",
    "sg:city":"Laval",
    "sg:classifiers":[
        {
            "category":"Personal",
            "subcategory":"Beauty Salon",
            "type":"Services"
        }
    ],
    "sg:phone":"+1 450 680 1058",
    "sg:postcode":"H7V 1J5",
    "sg:province":"QC",
    "wof:name":"Coiffure/Paulina Pour Elle",
    "wof:placetype":"venue"
},
  "geometry": {"coordinates":[-73.728165,45.541649],"type":"Point"}
}