{
  "type": "Feature",
  "properties": {
    "addr:full":"Coquitlam BC V3C 4E4",
    "addr:postcode":"bc v3c 4e4",
    "iso:country":"CA",
    "sg:city":"Coquitlam",
    "sg:classifiers":[
        {
            "category":"Cinema",
            "subcategory":"Movie Rental",
            "type":"Entertainment"
        }
    ],
    "sg:phone":"+1 604 942 0113",
    "sg:postcode":"V3C 4E4",
    "sg:province":"BC",
    "sg:tags":[
        "leasing",
        "video",
        "disc",
        "tape"
    ],
    "wof:name":"Seoul Video",
    "wof:placetype":"venue"
},
  "geometry": {"coordinates":[-122.790748596,49.2719612122],"type":"Point"}
}