{
  "type": "Feature",
  "properties": {
    "addr:full":"22091 40 Ave Langley BC V2Z 1N8",
    "addr:housenumber":"22091",
    "addr:postcode":"v2z 1n8",
    "addr:street":"40 Ave",
    "iso:country":"CA",
    "sg:address":"22091 40 Ave",
    "sg:city":"Langley",
    "sg:classifiers":[
        {
            "category":"Food & Beverages",
            "subcategory":"Specialty",
            "type":"Retail Goods"
        }
    ],
    "sg:phone":"+1 604 534 7785",
    "sg:postcode":"V2Z 1N8",
    "sg:province":"BC",
    "sg:tags":[
        "vitamin"
    ],
    "wof:name":"Shaklee Independent Distr",
    "wof:placetype":"venue"
},
  "geometry": {"coordinates":[-122.61238899999999,49.074947],"type":"Point"}
}