{
  "type": "Feature",
  "properties": {
    "addr:full":"2121 Paramount Cres Abbotsford BC V2T 6A5",
    "addr:housenumber":"2121",
    "addr:postcode":"v2t 6a5",
    "addr:street":"Paramount Cres",
    "iso:country":"CA",
    "sg:address":"2121 Paramount Cres",
    "sg:city":"Abbotsford",
    "sg:classifiers":[
        {
            "category":"Manufacturing",
            "subcategory":"Metals",
            "type":"Manufacturing & Wholesale Goods"
        }
    ],
    "sg:phone":"+1 604 850 2464",
    "sg:postcode":"V2T 6A5",
    "sg:province":"BC",
    "sg:tags":[
        "finisher"
    ],
    "wof:name":"Valley Powdercoat Ltd",
    "wof:placetype":"venue"
},
  "geometry": {"coordinates":[-122.34594,49.040703],"type":"Point"}
}