{
  "type": "Feature",
  "properties": {
    "addr:full":"26 Fittons Rd E Orillia ON L3V 7T3",
    "addr:housenumber":"26",
    "addr:postcode":"l3v 7t3",
    "addr:street":"Fittons Rd E",
    "iso:country":"CA",
    "sg:address":"26 Fittons Rd E",
    "sg:city":"Orillia",
    "sg:classifiers":[
        {
            "category":"Real Estate",
            "subcategory":"Real Estate Operator",
            "type":"Services"
        }
    ],
    "sg:phone":"+1 705 329 1000",
    "sg:postcode":"L3V 7T3",
    "sg:province":"ON",
    "sg:tags":[
        "apartment"
    ],
    "wof:name":"Overend Place",
    "wof:placetype":"venue"
},
  "geometry": {"coordinates":[-79.428917,44.623775],"type":"Point"}
}