{
  "type": "Feature",
  "properties": {
    "addr:full":"7260 St. Albans Rd Richmond BC V6Y 2K3",
    "addr:housenumber":"7260",
    "addr:postcode":"v6y 2k3",
    "addr:street":"St. Albans Rd",
    "iso:country":"CA",
    "sg:address":"7260 St. Albans Rd",
    "sg:city":"Richmond",
    "sg:classifiers":[
        {
            "category":"Organizations",
            "subcategory":"Religious Organization",
            "type":"Services"
        }
    ],
    "sg:phone":"+1 604 278 2770",
    "sg:postcode":"V6Y 2K3",
    "sg:province":"BC",
    "sg:tags":[
        "church"
    ],
    "wof:name":"St Albans Anglican Church",
    "wof:placetype":"venue"
},
  "geometry": {"coordinates":[-123.13078299999999,49.160366],"type":"Point"}
}