{
  "type": "Feature",
  "properties": {
    "addr:full":"525 High St Carleton Place ON K7C 3P1",
    "addr:housenumber":"525",
    "addr:postcode":"k7c 3p1",
    "addr:street":"High St",
    "iso:country":"CA",
    "sg:address":"525 High St",
    "sg:city":"Carleton Place",
    "sg:classifiers":[
        {
            "category":"Home & Garden",
            "subcategory":"Furniture",
            "type":"Retail Goods"
        }
    ],
    "sg:phone":"+1 613 253 6300",
    "sg:postcode":"K7C 3P1",
    "sg:province":"ON",
    "wof:name":"Old Oak Tree",
    "wof:placetype":"venue"
},
  "geometry": {"coordinates":[-76.1584472656,45.1329917908],"type":"Point"}
}