{
  "type": "Feature",
  "properties": {
    "addr:full":"4715 Gertrude St Port Alberni BC V9Y 6K4",
    "addr:housenumber":"4715",
    "addr:postcode":"v9y 6k4",
    "addr:street":"Gertrude St",
    "iso:country":"CA",
    "sg:address":"4715 Gertrude St",
    "sg:city":"Port Alberni",
    "sg:classifiers":[
        {
            "category":"Building & Trades",
            "subcategory":"Construction",
            "type":"Services"
        }
    ],
    "sg:phone":"+1 250 723 1900",
    "sg:postcode":"V9Y 6K4",
    "sg:province":"BC",
    "sg:tags":[
        "insulation",
        "heat",
        "contractor"
    ],
    "wof:name":"Hygienic Insulations Ltd",
    "wof:placetype":"venue"
},
  "geometry": {"coordinates":[-124.81234000000001,49.260303],"type":"Point"}
}