{
  "type": "Feature",
  "properties": {
    "iso:country":"CA",
    "sg:address":"1148 Broadway Ave S",
    "sg:city":"Williams Lake",
    "sg:classifiers":[
        {
            "category":"Organizations",
            "subcategory":"Professional Association",
            "type":"Services"
        }
    ],
    "sg:phone":"+1 250 392 5025",
    "sg:postcode":"V2G 1A2",
    "sg:province":"BC",
    "sg:tags":[
        "information",
        "tourist"
    ],
    "wof:name":"Visitor Information Ctr",
    "wof:placetype":"venue"
},
  "geometry": {"coordinates":[-122.12339782700001,52.1263923645],"type":"Point"}
}