{
  "type": "Feature",
  "properties": {
    "addr:full":"950 Barton St E Hamilton ON L8L 3C5",
    "addr:housenumber":"950",
    "addr:postcode":"l8l 3c5",
    "addr:street":"Barton St E",
    "iso:country":"CA",
    "sg:address":"950 Barton St E",
    "sg:city":"Hamilton",
    "sg:classifiers":[
        {
            "category":"Shopping",
            "subcategory":"Discount & Variety Stores",
            "type":"Retail Goods"
        }
    ],
    "sg:phone":"+1 905 545 8725",
    "sg:postcode":"L8L 3C5",
    "sg:province":"ON",
    "wof:name":"David's Variety Store",
    "wof:placetype":"venue"
},
  "geometry": {"coordinates":[-79.823097229,43.2530708313],"type":"Point"}
}