{
  "type": "Feature",
  "properties": {
    "addr:full":"9 Boul Bourque Omerville QC J1X 4E5",
    "addr:housenumber":"9",
    "addr:postcode":"j1x 4e5",
    "addr:street":"Boul Bourque",
    "iso:country":"CA",
    "sg:address":"9 Boul Bourque",
    "sg:city":"Omerville",
    "sg:classifiers":[
        {
            "category":"Autos & Motor Vehicles",
            "subcategory":"Automobile Sales",
            "type":"Retail Goods"
        }
    ],
    "sg:phone":"+1 819 868 2919",
    "sg:postcode":"J1X 4E5",
    "sg:province":"QC",
    "sg:tags":[
        "repairing",
        "snowmobile"
    ],
    "wof:name":"Centre Mecanique Magog Enr",
    "wof:placetype":"venue"
},
  "geometry": {"coordinates":[-72.122726,45.283077],"type":"Point"}
}