{
  "type": "Feature",
  "properties": {
    "addr:full":"405 Main St S Alexandria ON K0C 1A0",
    "addr:housenumber":"405",
    "addr:postcode":"k0c 1a0",
    "addr:street":"Main St S",
    "iso:country":"CA",
    "sg:address":"405 Main St S",
    "sg:city":"Alexandria",
    "sg:classifiers":[
        {
            "category":"Real Estate",
            "subcategory":"Real Estate Agent",
            "type":"Services"
        }
    ],
    "sg:phone":"+1 613 525 3419",
    "sg:postcode":"K0C 1A0",
    "sg:province":"ON",
    "wof:name":"Richard Vaillancourt Real Est",
    "wof:placetype":"venue"
},
  "geometry": {"coordinates":[-74.6277313232,45.3004989624],"type":"Point"}
}