{
  "type": "Feature",
  "properties": {
    "addr:full":"Hwy 215 Centre Burlington NS B0N 1E0",
    "addr:postcode":"b0n 1e0",
    "addr:street":"Hwy 215",
    "iso:country":"CA",
    "sg:address":"Hwy 215",
    "sg:city":"Centre Burlington",
    "sg:classifiers":[
        {
            "category":"Personal",
            "subcategory":"Beauty Salon",
            "type":"Services"
        }
    ],
    "sg:phone":"+1 902 757 2876",
    "sg:postcode":"B0N 1E0",
    "sg:province":"NS",
    "wof:name":"Sanford's Family Hairstyling",
    "wof:placetype":"venue"
},
  "geometry": {"coordinates":[-64.099571,45.066681],"type":"Point"}
}