{
  "type": "Feature",
  "properties": {
    "addr:full":"Toronto ON M5V 1T6",
    "addr:postcode":"m5v 1t6",
    "iso:country":"CA",
    "sg:city":"Toronto",
    "sg:classifiers":[
        {
            "category":"Personal",
            "subcategory":"Beauty Salon",
            "type":"Services"
        }
    ],
    "sg:phone":"+1 416 504 1605",
    "sg:postcode":"M5V 1T6",
    "sg:province":"ON",
    "wof:name":"Plutino Group",
    "wof:placetype":"venue"
},
  "geometry": {"coordinates":[-79.402008,43.645298],"type":"Point"}
}