{
  "type": "Feature",
  "properties": {
    "addr:full":"718 7th Ave Hanover ON N4N 2K1",
    "addr:housenumber":"718",
    "addr:postcode":"n4n 2k1",
    "addr:street":"7Th Ave",
    "iso:country":"CA",
    "sg:address":"718 7th Ave",
    "sg:city":"Hanover",
    "sg:classifiers":[
        {
            "category":"Government",
            "subcategory":"Office",
            "type":"Public Place"
        }
    ],
    "sg:phone":"+1 519 364 1481",
    "sg:postcode":"N4N 2K1",
    "sg:province":"ON",
    "sg:tags":[
        "village"
    ],
    "wof:name":"Hanover Sewage Treatment",
    "wof:placetype":"venue"
},
  "geometry": {"coordinates":[-81.03299,44.158348],"type":"Point"}
}