{
  "type": "Feature",
  "properties": {
    "addr:full":"North Rustico PE C0A 1X0",
    "addr:postcode":"c0a 1x0",
    "iso:country":"CA",
    "sg:city":"North Rustico",
    "sg:phone":"+1 902 963 2443",
    "sg:postcode":"C0A 1X0",
    "sg:province":"PE",
    "sg:tags":[
        "oil"
    ],
    "wof:name":"Pineau's Fuels",
    "wof:placetype":"venue"
},
  "geometry": {"coordinates":[-63.3185577393,46.4587287903],"type":"Point"}
}