{
  "type": "Feature",
  "properties": {
    "addr:full":"159 College St W Belleville ON K8P 2G7",
    "addr:housenumber":"159",
    "addr:postcode":"k8p 2g7",
    "addr:street":"College St W",
    "iso:country":"CA",
    "sg:address":"159 College St W",
    "sg:city":"Belleville",
    "sg:classifiers":[
        {
            "category":"Shopping",
            "subcategory":"Bicycles & Sporting Goods",
            "type":"Retail Goods"
        }
    ],
    "sg:phone":"+1 613 966 9161",
    "sg:postcode":"K8P 2G7",
    "sg:province":"ON",
    "wof:name":"Doug's Bicycle Sales & Svc",
    "wof:placetype":"venue"
},
  "geometry": {"coordinates":[-77.4007949829,44.1742515564],"type":"Point"}
}