{
  "type": "Feature",
  "properties": {
    "addr:full":"79 Victoria Rd Lunenburg NS B0J 2C0",
    "addr:housenumber":"79",
    "addr:postcode":"b0j 2c0",
    "addr:street":"Victoria Rd",
    "iso:country":"CA",
    "sg:address":"79 Victoria Rd",
    "sg:city":"Lunenburg",
    "sg:classifiers":[
        {
            "category":"Sports & Exercise",
            "subcategory":"Bowling",
            "type":"Entertainment"
        }
    ],
    "sg:phone":"+1 902 634 8344",
    "sg:postcode":"B0J 2C0",
    "sg:province":"NS",
    "sg:tags":[
        "center"
    ],
    "wof:name":"Bluenose Bowlerama",
    "wof:placetype":"venue"
},
  "geometry": {"coordinates":[-64.321495,44.376987],"type":"Point"}
}