{
  "type": "Feature",
  "properties": {
    "iso:country":"CA",
    "sg:address":"2370 Rue Becancour",
    "sg:city":"Lyster",
    "sg:classifiers":[
        {
            "category":"Freight",
            "type":"Transportation"
        }
    ],
    "sg:phone":"+1 819 389 5891",
    "sg:postcode":"G0S 1V0",
    "sg:province":"QC",
    "sg:tags":[
        "trucking"
    ],
    "wof:name":"Bo Duc Transport Inc",
    "wof:placetype":"venue"
},
  "geometry": {"coordinates":[-71.615593,46.371243],"type":"Point"}
}