{
  "type": "Feature",
  "properties": {
    "addr:full":"306 Rue Heriot Drummondville QC J2B 1A7",
    "addr:housenumber":"306",
    "addr:postcode":"j2b 1a7",
    "addr:street":"Rue Heriot",
    "iso:country":"CA",
    "sg:address":"306 Rue Heriot",
    "sg:city":"Drummondville",
    "sg:classifiers":[
        {
            "category":"Building & Trades",
            "subcategory":"Construction",
            "type":"Services"
        }
    ],
    "sg:phone":"+1 819 471 2219",
    "sg:postcode":"J2B 1A7",
    "sg:province":"QC",
    "sg:tags":[
        "general",
        "contractor"
    ],
    "wof:name":"Construction Serge Brouillette",
    "wof:placetype":"venue"
},
  "geometry": {"coordinates":[-72.486107,45.883842],"type":"Point"}
}