{
  "type": "Feature",
  "properties": {
    "addr:full":"3200 Ch DE LA Visitation Saint-Ambroise-DE-Kildare QC J0K 1C0",
    "addr:postcode":"3200;j0k 1c0",
    "addr:street":"Ch De La Visitation",
    "iso:country":"CA",
    "sg:address":"3200 Ch DE LA Visitation",
    "sg:city":"Saint-Ambroise-DE-Kildare",
    "sg:classifiers":[
        {
            "category":"Building & Trades",
            "subcategory":"Construction",
            "type":"Services"
        }
    ],
    "sg:phone":"+1 450 756 6695",
    "sg:postcode":"J0K 1C0",
    "sg:province":"QC",
    "sg:tags":[
        "excavating",
        "contractor"
    ],
    "wof:name":"Champagne J-P Excavation",
    "wof:placetype":"venue"
},
  "geometry": {"coordinates":[-73.509438,46.074566],"type":"Point"}
}