{
  "type": "Feature",
  "properties": {
    "addr:full":"Winnipeg MB R3H 1C1",
    "addr:postcode":"r3h 1c1",
    "iso:country":"CA",
    "sg:city":"Winnipeg",
    "sg:classifiers":[
        {
            "category":"Airport",
            "type":"Transportation"
        }
    ],
    "sg:phone":"+1 204 983 8408",
    "sg:postcode":"R3H 1C1",
    "sg:province":"MB",
    "sg:tags":[
        "support",
        "establishment",
        "airline"
    ],
    "wof:name":"Nav Canada",
    "wof:placetype":"venue"
},
  "geometry": {"coordinates":[-97.226585,49.903229],"type":"Point"}
}