{
  "type": "Feature",
  "properties": {
    "addr:full":"2427 Av Du Pont S Alma QC G8B 5V2",
    "addr:housenumber":"2427",
    "addr:postcode":"g8b 5v2",
    "addr:street":"Av Du Pont S",
    "iso:country":"CA",
    "sg:address":"2427 Av Du Pont S",
    "sg:city":"Alma",
    "sg:classifiers":[
        {
            "category":"Retail",
            "subcategory":"Repair Shop",
            "type":"Services"
        }
    ],
    "sg:phone":"+1 418 668 3607",
    "sg:postcode":"G8B 5V2",
    "sg:province":"QC",
    "sg:tags":[
        "tool",
        "parts"
    ],
    "wof:name":"Clinique D'Outillage Serge",
    "wof:placetype":"venue"
},
  "geometry": {"coordinates":[-71.656136,48.516537],"type":"Point"}
}