{
  "type": "Feature",
  "properties": {
    "iso:country":"CA",
    "sg:city":"Nepean",
    "sg:classifiers":[
        {
            "category":"Wholesale",
            "subcategory":"Electrical",
            "type":"Manufacturing & Wholesale Goods"
        }
    ],
    "sg:phone":"+1 613 228 7171",
    "sg:postcode":"K2E 6T7",
    "sg:province":"ON",
    "sg:tags":[
        "equipment",
        "television",
        "station"
    ],
    "wof:name":"R F Wireless Systems Inc",
    "wof:placetype":"venue"
},
  "geometry": {"coordinates":[-75.71174621580001,45.3363609314],"type":"Point"}
}