{
  "type": "Feature",
  "properties": {
    "addr:full":"110 Rue Augusta Sorel-Tracy QC J3P 1A7",
    "addr:housenumber":"110",
    "addr:postcode":"j3p 1a7",
    "addr:street":"Rue Augusta",
    "iso:country":"CA",
    "sg:address":"110 Rue Augusta",
    "sg:city":"Sorel-Tracy",
    "sg:classifiers":[
        {
            "category":"Personal",
            "subcategory":"Beauty Salon",
            "type":"Services"
        }
    ],
    "sg:phone":"+1 450 742 0235",
    "sg:postcode":"J3P 1A7",
    "sg:province":"QC",
    "wof:name":"Salon Vadnais Frances Enr",
    "wof:placetype":"venue"
},
  "geometry": {"coordinates":[-73.11204499999999,46.04623],"type":"Point"}
}