{
  "type": "Feature",
  "properties": {
    "addr:full":"555 Rue Laviolette Saint-Jerome QC J7Y 3Y5",
    "addr:housenumber":"555",
    "addr:postcode":"j7y 3y5",
    "addr:street":"Rue Laviolette",
    "iso:country":"CA",
    "sg:address":"555 Rue Laviolette",
    "sg:city":"Saint-Jerome",
    "sg:classifiers":[
        {
            "category":"Health Services",
            "subcategory":"Nursing And Care Facility",
            "type":"Services"
        }
    ],
    "sg:phone":"+1 450 432 5151",
    "sg:postcode":"J7Y 3Y5",
    "sg:province":"QC",
    "sg:tags":[
        "home",
        "retirement",
        "community"
    ],
    "wof:name":"Residence LA Jeromienne Inc",
    "wof:placetype":"venue"
},
  "geometry": {"coordinates":[-74.0066604614,45.7836151123],"type":"Point"}
}