{
  "type": "Feature",
  "properties": {
    "iso:country":"CA",
    "sg:address":"46 Front St N",
    "sg:city":"Thorold",
    "sg:classifiers":[
        {
            "category":"Restaurant",
            "type":"Food & Drink"
        }
    ],
    "sg:phone":"+1 905 680 2318",
    "sg:postcode":"L2V 1X5",
    "sg:province":"ON",
    "wof:name":"Solitude's Cafe",
    "wof:placetype":"venue"
},
  "geometry": {"coordinates":[-79.200638,43.126507],"type":"Point"}
}