{
  "type": "Feature",
  "properties": {
    "addr:full":"86 Joseph St Parry Sound ON P2A 2G5",
    "addr:housenumber":"86",
    "addr:postcode":"p2a 2g5",
    "addr:street":"Joseph St",
    "iso:country":"CA",
    "sg:address":"86 Joseph St",
    "sg:city":"Parry Sound",
    "sg:classifiers":[
        {
            "category":"Building & Trades",
            "subcategory":"Electrical",
            "type":"Services"
        }
    ],
    "sg:phone":"+1 705 746 5877",
    "sg:postcode":"P2A 2G5",
    "sg:province":"ON",
    "sg:tags":[
        "electric",
        "contractor"
    ],
    "wof:name":"Bay Area Electrical CO Ltd",
    "wof:placetype":"venue"
},
  "geometry": {"coordinates":[-80.04047393800001,45.3597602844],"type":"Point"}
}