{
  "type": "Feature",
  "properties": {
    "addr:full":"Trail BC V1R 4T2",
    "addr:postcode":"bc v1r 4t2",
    "addr:street":"Trail",
    "iso:country":"CA",
    "sg:city":"Trail",
    "sg:classifiers":[
        {
            "category":"Professional",
            "subcategory":"Advertising",
            "type":"Services"
        }
    ],
    "sg:phone":"+1 250 364 1667",
    "sg:postcode":"V1R 4T2",
    "sg:province":"BC",
    "sg:tags":[
        "counselor"
    ],
    "wof:name":"Reeves Steele Corp Comms",
    "wof:placetype":"venue"
},
  "geometry": {"coordinates":[-117.707267761,49.0967140198],"type":"Point"}
}