{
  "type": "Feature",
  "properties": {
    "addr:full":"261 Restigouche Rd # 13 Oromocto NB E2V 2H1",
    "addr:housenumber":"261",
    "addr:postcode":"e2v 2h1",
    "addr:street":"Restigouche Rd # 13",
    "iso:country":"CA",
    "sg:address":"261 Restigouche Rd # 13",
    "sg:city":"Oromocto",
    "sg:classifiers":[
        {
            "category":"Freight",
            "type":"Transportation"
        }
    ],
    "sg:phone":"+1 506 357 8888",
    "sg:postcode":"E2V 2H1",
    "sg:province":"NB",
    "sg:tags":[
        "commercial",
        "storage"
    ],
    "wof:name":"Swift Current Enterprises",
    "wof:placetype":"venue"
},
  "geometry": {"coordinates":[-66.49978637700001,45.8411178589],"type":"Point"}
}