{
  "type": "Feature",
  "properties": {
    "iso:country":"CA",
    "sg:city":"Red Deer",
    "sg:classifiers":[
        {
            "category":"Real Estate",
            "subcategory":"Surveying",
            "type":"Services"
        }
    ],
    "sg:phone":"+1 403 342 1255",
    "sg:postcode":"T4N 6Y4",
    "sg:province":"AB",
    "sg:tags":[
        "surveyor"
    ],
    "wof:name":"Snell & Oslund Surveys",
    "wof:placetype":"venue"
},
  "geometry": {"coordinates":[-113.816436768,52.2711486816],"type":"Point"}
}