{
  "type": "Feature",
  "properties": {
    "addr:full":"8400 Boul Saint-Laurent Montreal QC H2P 2M4",
    "addr:housenumber":"8400",
    "addr:postcode":"h2p 2m4",
    "addr:street":"Boul Saint-Laurent",
    "iso:country":"CA",
    "sg:address":"8400 Boul Saint-Laurent",
    "sg:city":"Montreal",
    "sg:classifiers":[
        {
            "category":"Shopping",
            "subcategory":"Clothing, Apparel, & Fashions",
            "type":"Retail Goods"
        }
    ],
    "sg:phone":"+1 514 381 1991",
    "sg:postcode":"H2P 2M4",
    "sg:province":"QC",
    "sg:tags":[
        "dressmaker"
    ],
    "wof:name":"Thana",
    "wof:placetype":"venue"
},
  "geometry": {"coordinates":[-73.6361236572,45.5401077271],"type":"Point"}
}