{
  "type": "Feature",
  "properties": {
    "addr:full":"1285 Williams Pky Brampton ON L6S 3J8",
    "addr:housenumber":"1285",
    "addr:postcode":"l6s 3j8",
    "addr:street":"Williams Pky",
    "iso:country":"CA",
    "sg:address":"1285 Williams Pky",
    "sg:city":"Brampton",
    "sg:classifiers":[
        {
            "category":"Education",
            "subcategory":"School",
            "type":"Public Place"
        }
    ],
    "sg:phone":"+1 905 791 4324",
    "sg:postcode":"L6S 3J8",
    "sg:province":"ON",
    "wof:name":"Williams Parkway Sr Public",
    "wof:placetype":"venue"
},
  "geometry": {"coordinates":[-79.699180603,43.7618713379],"type":"Point"}
}