{
  "type": "Feature",
  "properties": {
    "addr:full":"525 Windmill Rd Dartmouth NS B3B 1B4",
    "addr:housenumber":"525",
    "addr:postcode":"b3b 1b4",
    "addr:street":"Windmill Rd",
    "iso:country":"CA",
    "sg:address":"525 Windmill Rd",
    "sg:city":"Dartmouth",
    "sg:classifiers":[
        {
            "category":"Building & Trades",
            "subcategory":"Equipment Rental",
            "type":"Services"
        }
    ],
    "sg:phone":"+1 902 468 6620",
    "sg:postcode":"B3B 1B4",
    "sg:province":"NS",
    "sg:tags":[
        "steel",
        "crane",
        "erectors"
    ],
    "wof:name":"Sagadore Cranes & Equipment",
    "wof:placetype":"venue"
},
  "geometry": {"coordinates":[-63.6006088257,44.6928939819],"type":"Point"}
}