{
  "type": "Feature",
  "properties": {
    "addr:full":"1426 Dundas St W Toronto ON M6J 1Y5",
    "addr:housenumber":"1426",
    "addr:postcode":"m6j 1y5",
    "addr:street":"Dundas St W",
    "iso:country":"CA",
    "sg:address":"1426 Dundas St W",
    "sg:city":"Toronto",
    "sg:classifiers":[
        {
            "category":"Personal",
            "subcategory":"Shoe Repair & Shine",
            "type":"Services"
        }
    ],
    "sg:phone":"+1 416 533 1551",
    "sg:postcode":"M6J 1Y5",
    "sg:province":"ON",
    "sg:tags":[
        "repairing",
        "boot"
    ],
    "wof:name":"Tony's Shoe Repair",
    "wof:placetype":"venue"
},
  "geometry": {"coordinates":[-79.429489,43.649708],"type":"Point"}
}