{
  "type": "Feature",
  "properties": {
    "iso:country":"CA",
    "sg:address":"2990 Church St",
    "sg:city":"South Mountain",
    "sg:classifiers":[
        {
            "category":"Retail",
            "subcategory":"Funeral Services",
            "type":"Services"
        }
    ],
    "sg:phone":"+1 613 989 3836",
    "sg:postcode":"K0E 1W0",
    "sg:province":"ON",
    "sg:tags":[
        "director",
        "plan"
    ],
    "wof:name":"Byers Funeral Home Inc",
    "wof:placetype":"venue"
},
  "geometry": {"coordinates":[-75.45156860349999,44.9903564453],"type":"Point"}
}