{
  "type": "Feature",
  "properties": {
    "addr:full":"317 116 Rte Cleveland QC J0B 2H0",
    "addr:housenumber":"116",
    "addr:postcode":"j0b 2h0",
    "addr:street":"Rte Cleveland",
    "iso:country":"CA",
    "sg:address":"317 116 Rte",
    "sg:city":"Cleveland",
    "sg:classifiers":[
        {
            "category":"Autos & Motor Vehicles",
            "subcategory":"Automobile Sales",
            "type":"Retail Goods"
        }
    ],
    "sg:phone":"+1 819 826 3084",
    "sg:postcode":"J0B 2H0",
    "sg:province":"QC",
    "sg:tags":[
        "car",
        "dealer"
    ],
    "wof:name":"J N Auto Roadside Inc",
    "wof:placetype":"venue"
},
  "geometry": {"coordinates":[-72.121399,45.676392],"type":"Point"}
}