{
  "type": "Feature",
  "properties": {
    "addr:full":"Chicoutimi QC G7H 5G4",
    "addr:postcode":"g7h 5g4",
    "iso:country":"CA",
    "sg:city":"Chicoutimi",
    "sg:classifiers":[
        {
            "category":"Manufacturing",
            "subcategory":"Petroleum Products",
            "type":"Manufacturing & Wholesale Goods"
        }
    ],
    "sg:phone":"+1 418 545 1411",
    "sg:postcode":"G7H 5G4",
    "sg:province":"QC",
    "wof:name":"Ultramar",
    "wof:placetype":"venue"
},
  "geometry": {"coordinates":[-70.99612399999999,48.443207],"type":"Point"}
}