{
  "type": "Feature",
  "properties": {
    "addr:full":"St Albert AB T8N 1E4",
    "addr:postcode":"t8n 1e4",
    "iso:country":"CA",
    "sg:city":"St Albert",
    "sg:classifiers":[
        {
            "category":"Health Services",
            "subcategory":"Chiropractor",
            "type":"Services"
        }
    ],
    "sg:phone":"+1 780 419 3833",
    "sg:postcode":"T8N 1E4",
    "sg:province":"AB",
    "wof:name":"Kisic, Wendi DC",
    "wof:placetype":"venue"
},
  "geometry": {"coordinates":[-113.62532043500001,53.633480072],"type":"Point"}
}