{
  "type": "Feature",
  "properties": {
    "iso:country":"CA",
    "sg:city":"Mississauga",
    "sg:classifiers":[
        {
            "category":"Manufacturing",
            "subcategory":"Apparel",
            "type":"Manufacturing & Wholesale Goods"
        }
    ],
    "sg:phone":"+1 905 625 5991",
    "sg:postcode":"L4X 1M2",
    "sg:province":"ON",
    "sg:tags":[
        "clothing"
    ],
    "wof:name":"Nfg Ltd",
    "wof:placetype":"venue"
},
  "geometry": {"coordinates":[-79.569366,43.623077],"type":"Point"}
}