{
  "type": "Feature",
  "properties": {
    "addr:full":"51 Macintosh Rd Middle Sackville NS B4E 3B3",
    "addr:housenumber":"51",
    "addr:postcode":"b4e 3b3",
    "addr:street":"Macintosh Rd",
    "iso:country":"CA",
    "sg:address":"51 Macintosh Rd",
    "sg:city":"Middle Sackville",
    "sg:classifiers":[
        {
            "category":"Shopping",
            "subcategory":"Computers & Home Electronics",
            "type":"Retail Goods"
        }
    ],
    "sg:phone":"+1 902 865 7401",
    "sg:postcode":"B4E 3B3",
    "sg:province":"NS",
    "sg:tags":[
        "television",
        "radio"
    ],
    "wof:name":"Universal Electronics Parts",
    "wof:placetype":"venue"
},
  "geometry": {"coordinates":[-63.735134,44.790287],"type":"Point"}
}