{
  "type": "Feature",
  "properties": {
    "addr:full":"119 Sapphire Dr Thunder Bay ON P7G 1A8",
    "addr:housenumber":"119",
    "addr:postcode":"p7g 1a8",
    "addr:street":"Sapphire Dr",
    "iso:country":"CA",
    "sg:address":"119 Sapphire Dr",
    "sg:city":"Thunder Bay",
    "sg:classifiers":[
        {
            "category":"Building & Trades",
            "subcategory":"Landscaping Services",
            "type":"Services"
        }
    ],
    "sg:phone":"+1 807 768 8669",
    "sg:postcode":"P7G 1A8",
    "sg:province":"ON",
    "sg:tags":[
        "landscape",
        "contractor"
    ],
    "wof:name":"P M Landscaping",
    "wof:placetype":"venue"
},
  "geometry": {"coordinates":[-89.2593917847,48.4638748169],"type":"Point"}
}