{
  "type": "Feature",
  "properties": {
    "addr:full":"Yellowknife NT X1A 3T5",
    "addr:postcode":"x1a 3t5",
    "iso:country":"CA",
    "sg:city":"Yellowknife",
    "sg:classifiers":[
        {
            "category":"Travel",
            "subcategory":"Travel Agent",
            "type":"Entertainment"
        }
    ],
    "sg:phone":"+1 867 873 4262",
    "sg:postcode":"X1A 3T5",
    "sg:province":"NT",
    "sg:tags":[
        "information",
        "tourist"
    ],
    "wof:name":"Northern Frontier Reg Visitor",
    "wof:placetype":"venue"
},
  "geometry": {"coordinates":[-114.374229,62.456333],"type":"Point"}
}