{
  "type": "Feature",
  "properties": {
    "addr:full":"166 Braemar Dr Dartmouth NS B2X 2T3",
    "addr:housenumber":"166",
    "addr:postcode":"b2x 2t3",
    "addr:street":"Braemar Dr",
    "iso:country":"CA",
    "sg:address":"166 Braemar Dr",
    "sg:city":"Dartmouth",
    "sg:classifiers":[
        {
            "category":"Professional",
            "subcategory":"Management & Consulting",
            "type":"Services"
        }
    ],
    "sg:phone":"+1 902 434 4647",
    "sg:postcode":"B2X 2T3",
    "sg:province":"NS",
    "sg:tags":[
        "consultant",
        "architectural"
    ],
    "wof:name":"Loomis Management Svc Ltd",
    "wof:placetype":"venue"
},
  "geometry": {"coordinates":[-63.547580719,44.6813583374],"type":"Point"}
}