{
  "type": "Feature",
  "properties": {
    "iso:country":"CA",
    "sg:address":"666 Elgin Ave",
    "sg:city":"Winnipeg",
    "sg:classifiers":[
        {
            "category":"Wholesale",
            "subcategory":"Groceries",
            "type":"Manufacturing & Wholesale Goods"
        }
    ],
    "sg:phone":"+1 204 774 7431",
    "sg:postcode":"R3E 1B2",
    "sg:province":"MB",
    "sg:tags":[
        "grocer"
    ],
    "wof:name":"Weston Bakeries Ltd",
    "wof:placetype":"venue"
},
  "geometry": {"coordinates":[-97.15581512449999,49.9051513672],"type":"Point"}
}