{
  "type": "Feature",
  "properties": {
    "addr:full":"Irish Town Rd Brigus NL A0A 1K0",
    "addr:postcode":"a0a 1k0",
    "addr:street":"Irish Town Rd",
    "iso:country":"CA",
    "sg:address":"Irish Town Rd",
    "sg:city":"Brigus",
    "sg:classifiers":[
        {
            "category":"Museum",
            "type":"Entertainment"
        }
    ],
    "sg:phone":"+1 709 528 4004",
    "sg:postcode":"A0A 1K0",
    "sg:province":"NL",
    "wof:name":"Hawthorne Cottage",
    "wof:placetype":"venue"
},
  "geometry": {"coordinates":[-53.232132,47.530632],"type":"Point"}
}