{
  "type": "Feature",
  "properties": {
    "addr:full":"59 Church St St Catharines ON L2R 3C3",
    "addr:housenumber":"59",
    "addr:postcode":"l2r 3c3",
    "addr:street":"Church St",
    "iso:country":"CA",
    "sg:address":"59 Church St",
    "sg:city":"St Catharines",
    "sg:classifiers":[
        {
            "category":"Government",
            "subcategory":"Office",
            "type":"Public Place"
        }
    ],
    "sg:phone":"+1 905 704 4090",
    "sg:postcode":"L2R 3C3",
    "sg:province":"ON",
    "wof:name":"Ontario Health Insurance",
    "wof:placetype":"venue"
},
  "geometry": {"coordinates":[-79.247185,43.159908],"type":"Point"}
}