{
  "type": "Feature",
  "properties": {
    "addr:full":"336 Av Noel Sept-Iles QC G4R 1L7",
    "addr:housenumber":"336",
    "addr:postcode":"g4r 1l7",
    "addr:street":"Av Noel Sept-Iles",
    "iso:country":"CA",
    "sg:address":"336 Av Noel",
    "sg:city":"Sept-Iles",
    "sg:classifiers":[
        {
            "category":"Retail",
            "subcategory":"Auto Repair",
            "type":"Services"
        }
    ],
    "sg:phone":"+1 418 962 4057",
    "sg:postcode":"G4R 1L7",
    "sg:province":"QC",
    "sg:tags":[
        "repairing",
        "automobile",
        "truck"
    ],
    "wof:name":"Centre DE Mecanique Du Golfe",
    "wof:placetype":"venue"
},
  "geometry": {"coordinates":[-66.3681564331,50.2103843689],"type":"Point"}
}