{
  "type": "Feature",
  "properties": {
    "addr:full":"460 Pim St # 1 Sault Ste Marie ON P6B 2V2",
    "addr:housenumber":"460",
    "addr:postcode":"p6b 2v2",
    "addr:street":"Pim St # 1",
    "iso:country":"CA",
    "sg:address":"460 Pim St # 1",
    "sg:city":"Sault Ste Marie",
    "sg:classifiers":[
        {
            "category":"Autos & Motor Vehicles",
            "subcategory":"Automobile Sales",
            "type":"Retail Goods"
        }
    ],
    "sg:phone":"+1 705 759 0043",
    "sg:postcode":"P6B 2V2",
    "sg:province":"ON",
    "sg:tags":[
        "car",
        "dealer"
    ],
    "wof:name":"Cambrian Nissan",
    "wof:placetype":"venue"
},
  "geometry": {"coordinates":[-84.319275,46.520157],"type":"Point"}
}