{
  "type": "Feature",
  "properties": {
    "addr:full":"220 Milner Ave #1 Scarborough ON M1S 4M8",
    "addr:housenumber":"220",
    "addr:postcode":"m1s 4m8",
    "addr:street":"Milner Ave # 1",
    "iso:country":"CA",
    "sg:address":"220 Milner Ave #1",
    "sg:city":"Scarborough",
    "sg:classifiers":[
        {
            "category":"Manufacturing",
            "subcategory":"Printing",
            "type":"Manufacturing & Wholesale Goods"
        }
    ],
    "sg:phone":"+1 416 298 7166",
    "sg:postcode":"M1S 4M8",
    "sg:province":"ON",
    "sg:tags":[
        "printer"
    ],
    "wof:name":"Pine Press",
    "wof:placetype":"venue"
},
  "geometry": {"coordinates":[-79.240883,43.788483],"type":"Point"}
}