{
  "type": "Feature",
  "properties": {
    "iso:country":"CA",
    "sg:address":"153 Boul Saint-Luc",
    "sg:city":"Saint-Luc",
    "sg:classifiers":[
        {
            "category":"Retail",
            "subcategory":"Auto Repair",
            "type":"Services"
        }
    ],
    "sg:phone":"+1 450 348 4503",
    "sg:postcode":"J2W 2M5",
    "sg:province":"QC",
    "sg:tags":[
        "body",
        "automobile",
        "painting"
    ],
    "wof:name":"Carossiers Rd Loignon Inc",
    "wof:placetype":"venue"
},
  "geometry": {"coordinates":[-73.279373,45.341068],"type":"Point"}
}