{
  "type": "Feature",
  "properties": {
    "addr:full":"415 28E Av Pointe-Calumet QC J0N 1G1",
    "addr:housenumber":"415",
    "addr:postcode":"j0n 1g1",
    "addr:street":"28E Av Pointe-Calumet",
    "iso:country":"CA",
    "sg:address":"415 28E Av",
    "sg:city":"Pointe-Calumet",
    "sg:classifiers":[
        {
            "category":"Building & Trades",
            "subcategory":"Landscaping Services",
            "type":"Services"
        }
    ],
    "sg:phone":"+1 450 623 8452",
    "sg:postcode":"J0N 1G1",
    "sg:province":"QC",
    "sg:tags":[
        "landscape",
        "contractor"
    ],
    "wof:name":"Paysagiste Jacques Dery Enr",
    "wof:placetype":"venue"
},
  "geometry": {"coordinates":[-73.9649887085,45.5046424866],"type":"Point"}
}