{
  "type": "Feature",
  "properties": {
    "addr:full":"81 St Clair Ave E Toronto ON M4T 1M7",
    "addr:housenumber":"81",
    "addr:postcode":"m4t 1m7",
    "addr:street":"St Clair Ave E",
    "iso:country":"CA",
    "sg:address":"81 St Clair Ave E",
    "sg:city":"Toronto",
    "sg:classifiers":[
        {
            "category":"Restaurant",
            "type":"Food & Drink"
        }
    ],
    "sg:phone":"+1 416 975 0999",
    "sg:postcode":"M4T 1M7",
    "sg:province":"ON",
    "wof:name":"Simply Thai",
    "wof:placetype":"venue"
},
  "geometry": {"coordinates":[-79.3902359009,43.6887550354],"type":"Point"}
}