{
  "type": "Feature",
  "properties": {
    "addr:full":"2034 Ch Du Bord-Du-Lac L'Ile-Bizard QC H9C 1A4",
    "addr:postcode":"2034;h9c 1a4",
    "addr:street":"Ch Du Bord-Du-Lac",
    "iso:country":"CA",
    "sg:address":"2034 Ch Du Bord-Du-Lac",
    "sg:city":"L'Ile-Bizard",
    "sg:classifiers":[
        {
            "category":"Manufacturing",
            "subcategory":"Tools & Machinery",
            "type":"Manufacturing & Wholesale Goods"
        }
    ],
    "sg:phone":"+1 514 620 3113",
    "sg:postcode":"H9C 1A4",
    "sg:province":"QC",
    "sg:tags":[
        "equipment",
        "hydraulic",
        "supply"
    ],
    "wof:name":"Abacus Hydraulics Ltd",
    "wof:placetype":"venue"
},
  "geometry": {"coordinates":[-73.902916,45.507305],"type":"Point"}
}