{
  "type": "Feature",
  "properties": {
    "addr:full":"110 Elgin St Port Elgin ON N0H 2C0",
    "addr:housenumber":"110",
    "addr:postcode":"n0h 2c0",
    "addr:street":"Elgin St",
    "iso:country":"CA",
    "sg:address":"110 Elgin St",
    "sg:city":"Port Elgin",
    "sg:classifiers":[
        {
            "category":"Restaurant",
            "type":"Food & Drink"
        }
    ],
    "sg:phone":"+1 519 832 6262",
    "sg:postcode":"N0H 2C0",
    "sg:province":"ON",
    "wof:name":"Harbourlite Restaurant",
    "wof:placetype":"venue"
},
  "geometry": {"coordinates":[-81.402794,44.444061],"type":"Point"}
}