{
  "type": "Feature",
  "properties": {
    "iso:country":"CA",
    "sg:address":"4403 56 Ave # 5",
    "sg:city":"Leduc",
    "sg:classifiers":[
        {
            "category":"Mining & Drilling",
            "type":"Manufacturing & Wholesale Goods"
        }
    ],
    "sg:phone":"+1 780 980 2409",
    "sg:postcode":"T9E 6T7",
    "sg:province":"AB",
    "sg:tags":[
        "field",
        "oil"
    ],
    "wof:name":"M & T Tong Repair Ltd",
    "wof:placetype":"venue"
},
  "geometry": {"coordinates":[-113.54153442400001,53.2705993652],"type":"Point"}
}