{
  "type": "Feature",
  "properties": {
    "addr:full":"281 Ch Du Ruisseau-Saint-Louis Marieville QC J3M 1P1",
    "addr:housenumber":"281",
    "addr:postcode":"j3m 1p1",
    "addr:street":"Ch Du Ruisseau-Saint-Louis",
    "iso:country":"CA",
    "sg:address":"281 Ch Du Ruisseau-Saint-Louis",
    "sg:city":"Marieville",
    "sg:classifiers":[
        {
            "category":"Manufacturing",
            "subcategory":"Tools & Machinery",
            "type":"Manufacturing & Wholesale Goods"
        }
    ],
    "sg:phone":"+1 450 460 2661",
    "sg:postcode":"J3M 1P1",
    "sg:province":"QC",
    "sg:tags":[
        "contractor"
    ],
    "wof:name":"Atelier Tetrault Theberge",
    "wof:placetype":"venue"
},
  "geometry": {"coordinates":[-73.176346,45.450996],"type":"Point"}
}