{
  "type": "Feature",
  "properties": {
    "addr:full":"713 15E Rue Saint-Zacharie QC G0M 2C0",
    "addr:housenumber":"713",
    "addr:postcode":"g0m 2c0",
    "addr:street":"15E Rue",
    "iso:country":"CA",
    "sg:address":"713 15E Rue",
    "sg:city":"Saint-Zacharie",
    "sg:classifiers":[
        {
            "category":"Shopping",
            "subcategory":"Gifts & Souvenirs",
            "type":"Retail Goods"
        }
    ],
    "sg:phone":"+1 418 593 3045",
    "sg:postcode":"G0M 2C0",
    "sg:province":"QC",
    "sg:tags":[
        "shop"
    ],
    "wof:name":"Paradis Du Cadeau",
    "wof:placetype":"venue"
},
  "geometry": {"coordinates":[-70.36302947999999,46.1264381409],"type":"Point"}
}