{
  "type": "Feature",
  "properties": {
    "addr:full":"Hwy 2 E Shubenacadie NS B0N 2H0",
    "addr:postcode":"b0n 2h0",
    "addr:street":"Hwy 2 E",
    "iso:country":"CA",
    "sg:address":"Hwy 2 E",
    "sg:city":"Shubenacadie",
    "sg:classifiers":[
        {
            "category":"Organizations",
            "subcategory":"Religious Organization",
            "type":"Services"
        }
    ],
    "sg:phone":"+1 902 758 3953",
    "sg:postcode":"B0N 2H0",
    "sg:province":"NS",
    "sg:tags":[
        "church"
    ],
    "wof:name":"Kingdom Hall Jehovah's Wtnss",
    "wof:placetype":"venue"
},
  "geometry": {"coordinates":[-63.399857,45.080906],"type":"Point"}
}