{
  "type": "Feature",
  "properties": {
    "addr:full":"259 Catharine St Port Colborne ON L3K 4L1",
    "addr:housenumber":"259",
    "addr:postcode":"l3k 4l1",
    "addr:street":"Catharine St",
    "iso:country":"CA",
    "sg:address":"259 Catharine St",
    "sg:city":"Port Colborne",
    "sg:classifiers":[
        {
            "category":"Professional",
            "subcategory":"Management & Consulting",
            "type":"Services"
        }
    ],
    "sg:phone":"+1 905 834 7117",
    "sg:postcode":"L3K 4L1",
    "sg:province":"ON",
    "sg:tags":[
        "consultant",
        "business"
    ],
    "wof:name":"Diri Management",
    "wof:placetype":"venue"
},
  "geometry": {"coordinates":[-79.25272369379999,42.8862609863],"type":"Point"}
}