{
  "type": "Feature",
  "properties": {
    "iso:country":"CA",
    "sg:city":"Winchester",
    "sg:classifiers":[
        {
            "category":"Restaurant",
            "type":"Food & Drink"
        }
    ],
    "sg:phone":"+1 613 774 3733",
    "sg:postcode":"K0C 2K0",
    "sg:province":"ON",
    "wof:name":"Mary's Restaurant",
    "wof:placetype":"venue"
},
  "geometry": {"coordinates":[-75.35317230219999,45.0924491882],"type":"Point"}
}