{
  "type": "Feature",
  "properties": {
    "addr:full":"3521 Finch Ave E Scarborough ON M1W 2S2",
    "addr:housenumber":"3521",
    "addr:postcode":"m1w 2s2",
    "addr:street":"Finch Ave E",
    "iso:country":"CA",
    "sg:address":"3521 Finch Ave E",
    "sg:city":"Scarborough",
    "sg:classifiers":[
        {
            "category":"Education",
            "subcategory":"School",
            "type":"Public Place"
        }
    ],
    "sg:phone":"+1 416 393 5350",
    "sg:postcode":"M1W 2S2",
    "sg:province":"ON",
    "wof:name":"Saint Aidan Catholic School",
    "wof:placetype":"venue"
},
  "geometry": {"coordinates":[-79.31127166749999,43.7976264954],"type":"Point"}
}