{
  "type": "Feature",
  "properties": {
    "addr:full":"1044 Benchlands Trail Canmore AB T1W 3B6",
    "addr:housenumber":"1044",
    "addr:postcode":"t1w 3b6",
    "addr:street":"Benchlands Trail",
    "iso:country":"CA",
    "sg:address":"1044 Benchlands Trail",
    "sg:city":"Canmore",
    "sg:classifiers":[
        {
            "category":"Professional",
            "subcategory":"Business Services",
            "type":"Services"
        }
    ],
    "sg:phone":"+1 403 609 2159",
    "sg:postcode":"T1W 3B6",
    "sg:province":"AB",
    "sg:tags":[
        "water",
        "company",
        "treatment"
    ],
    "wof:name":"Aquasource",
    "wof:placetype":"venue"
},
  "geometry": {"coordinates":[-115.330124,51.091064],"type":"Point"}
}