{
  "type": "Feature",
  "properties": {
    "iso:country":"CA",
    "sg:address":"4813 49 Ave",
    "sg:city":"Leduc",
    "sg:classifiers":[
        {
            "category":"Health Services",
            "subcategory":"Doctor",
            "type":"Services"
        }
    ],
    "sg:phone":"+1 780 986 6255",
    "sg:postcode":"T9E 7H8",
    "sg:province":"AB",
    "sg:tags":[
        "dentist"
    ],
    "wof:name":"Prairie Dental Ctr",
    "wof:placetype":"venue"
},
  "geometry": {"coordinates":[-113.548461914,53.2636871338],"type":"Point"}
}