{
  "type": "Feature",
  "properties": {
    "iso:country":"CA",
    "sg:address":"109 Gerrish St",
    "sg:city":"Windsor",
    "sg:classifiers":[
        {
            "category":"Health Services",
            "subcategory":"Nursing And Care Facility",
            "type":"Services"
        }
    ],
    "sg:phone":"+1 902 798 4375",
    "sg:postcode":"B0N 2T0",
    "sg:province":"NS",
    "sg:tags":[
        "home",
        "rest"
    ],
    "wof:name":"Hants Community Homes",
    "wof:placetype":"venue"
},
  "geometry": {"coordinates":[-64.1326751709,44.9923667908],"type":"Point"}
}