{
  "type": "Feature",
  "properties": {
    "addr:full":"Carleton NS B0W 1L0",
    "addr:postcode":"b0w 1l0",
    "iso:country":"CA",
    "sg:city":"Carleton",
    "sg:classifiers":[
        {
            "category":"Food & Beverages",
            "subcategory":"Groceries & Convenience Stores",
            "type":"Retail Goods"
        }
    ],
    "sg:phone":"+1 902 761 3000",
    "sg:postcode":"B0W 1L0",
    "sg:province":"NS",
    "wof:name":"Carleton Country Outfitters",
    "wof:placetype":"venue"
},
  "geometry": {"coordinates":[-65.928398,44.005779],"type":"Point"}
}