{
  "type": "Feature",
  "properties": {
    "iso:country":"CA",
    "sg:address":"PO Box 43115 Rpo Cascade",
    "sg:city":"Burnaby",
    "sg:classifiers":[
        {
            "category":"Local Transit",
            "type":"Transportation"
        }
    ],
    "sg:phone":"+1 604 329 6559",
    "sg:postcode":"V5G 4S2",
    "sg:province":"BC",
    "sg:tags":[
        "limousine"
    ],
    "wof:name":"Exclusive Limousine Svc",
    "wof:placetype":"venue"
},
  "geometry": {"coordinates":[-122.972763062,49.2444343567],"type":"Point"}
}