{
  "type": "Feature",
  "properties": {
    "addr:full":"323 Rue Jean-Talon E Montreal QC H2R 1T2",
    "addr:housenumber":"323",
    "addr:postcode":"h2r 1t2",
    "addr:street":"Rue Jean-Talon E",
    "iso:country":"CA",
    "sg:address":"323 Rue Jean-Talon E",
    "sg:city":"Montreal",
    "sg:classifiers":[
        {
            "category":"Food & Beverages",
            "subcategory":"Bakery",
            "type":"Retail Goods"
        }
    ],
    "sg:phone":"+1 514 271 7446",
    "sg:postcode":"H2R 1T2",
    "sg:province":"QC",
    "sg:tags":[
        "doughnut"
    ],
    "wof:name":"Tim Hortons",
    "wof:placetype":"venue"
},
  "geometry": {"coordinates":[-73.615486,45.53743],"type":"Point"}
}