{
  "type": "Feature",
  "properties": {
    "addr:full":"237 4 Ave SW # 3000 Calgary AB T2P 4X7",
    "addr:housenumber":"237",
    "addr:postcode":"t2p 4x7",
    "addr:street":"4 Ave Sw # 3000",
    "iso:country":"CA",
    "sg:address":"237 4 Ave SW # 3000",
    "sg:city":"Calgary",
    "sg:classifiers":[
        {
            "category":"Professional",
            "subcategory":"Lawyer & Legal Services",
            "type":"Services"
        }
    ],
    "sg:phone":"+1 403 268 7000",
    "sg:postcode":"T2P 4X7",
    "sg:province":"AB",
    "sg:tags":[
        "attorney"
    ],
    "wof:name":"Maxwell, Robert D",
    "wof:placetype":"venue"
},
  "geometry": {"coordinates":[-114.066108704,51.0492286682],"type":"Point"}
}