{
  "type": "Feature",
  "properties": {
    "addr:full":"7015 Boul Wilfrid-Hamel Sainte-Foy QC G2G 1B6",
    "addr:housenumber":"7015",
    "addr:postcode":"g2g 1b6",
    "addr:street":"Boul Wilfrid-Hamel",
    "iso:country":"CA",
    "sg:address":"7015 Boul Wilfrid-Hamel",
    "sg:city":"Sainte-Foy",
    "sg:classifiers":[
        {
            "category":"Restaurant",
            "type":"Food & Drink"
        }
    ],
    "sg:phone":"+1 418 874 0207",
    "sg:postcode":"G2G 1B6",
    "sg:province":"QC",
    "wof:name":"Restaurant LA Belle Province",
    "wof:placetype":"venue"
},
  "geometry": {"coordinates":[-71.35559082029999,46.7880973816],"type":"Point"}
}