{
  "type": "Feature",
  "properties": {
    "addr:full":"1135 Ch Saint-Louis Sillery QC G1S 1E7",
    "addr:housenumber":"1135",
    "addr:postcode":"g1s 1e7",
    "addr:street":"Ch Saint-Louis",
    "iso:country":"CA",
    "sg:address":"1135 Ch Saint-Louis",
    "sg:city":"Sillery",
    "sg:classifiers":[
        {
            "category":"Restaurant",
            "type":"Food & Drink"
        }
    ],
    "sg:phone":"+1 418 527 0595",
    "sg:postcode":"G1S 1E7",
    "sg:province":"QC",
    "wof:name":"Buffet Leguy",
    "wof:placetype":"venue"
},
  "geometry": {"coordinates":[-71.2471008301,46.7886428833],"type":"Point"}
}