{
  "type": "Feature",
  "properties": {
    "iso:country":"CA",
    "sg:city":"Whitby",
    "sg:classifiers":[
        {
            "category":"Professional",
            "subcategory":"Engineering",
            "type":"Services"
        }
    ],
    "sg:phone":"+1 905 666 7527",
    "sg:postcode":"L1N 9E7",
    "sg:province":"ON",
    "sg:tags":[
        "environmental",
        "ecological",
        "engineer"
    ],
    "wof:name":"Gaea Technologies Ltd",
    "wof:placetype":"venue"
},
  "geometry": {"coordinates":[-78.931343,43.88015],"type":"Point"}
}