{
  "type": "Feature",
  "properties": {
    "iso:country":"CA",
    "sg:address":"3005 Boul Levesque E",
    "sg:city":"Laval",
    "sg:classifiers":[
        {
            "category":"Health Services",
            "subcategory":"Doctor",
            "type":"Services"
        }
    ],
    "sg:phone":"+1 450 661 7404",
    "sg:postcode":"H7E 2P2",
    "sg:province":"QC",
    "sg:tags":[
        "clinic"
    ],
    "wof:name":"Daniel Brunet Denturologist",
    "wof:placetype":"venue"
},
  "geometry": {"coordinates":[-73.662262,45.587383],"type":"Point"}
}