{
  "type": "Feature",
  "properties": {
    "addr:full":"34 Av DE Gaspe O Saint-Jean-Port-Joli QC G0R 3G0",
    "addr:postcode":"g0r 3g0",
    "addr:street":"34 Av De Gaspe O",
    "iso:country":"CA",
    "sg:address":"34 Av DE Gaspe O",
    "sg:city":"Saint-Jean-Port-Joli",
    "sg:classifiers":[
        {
            "category":"Travel",
            "subcategory":"Hotels & Motels",
            "type":"Entertainment"
        }
    ],
    "sg:phone":"+1 418 598 3311",
    "sg:postcode":"G0R 3G0",
    "sg:province":"QC",
    "wof:name":"Auberge-Motel Blanche Tibervil",
    "wof:placetype":"venue"
},
  "geometry": {"coordinates":[-70.26873000000001,47.215996],"type":"Point"}
}