{
  "type": "Feature",
  "properties": {
    "addr:full":"71 Government St Duncan BC V9L 1A3",
    "addr:housenumber":"71",
    "addr:postcode":"v9l 1a3",
    "addr:street":"Government St",
    "iso:country":"CA",
    "sg:address":"71 Government St",
    "sg:city":"Duncan",
    "sg:classifiers":[
        {
            "category":"Government",
            "subcategory":"Office",
            "type":"Public Place"
        }
    ],
    "sg:phone":"+1 250 715 2737",
    "sg:postcode":"V9L 1A3",
    "sg:province":"BC",
    "wof:name":"B C Youth Svc Team",
    "wof:placetype":"venue"
},
  "geometry": {"coordinates":[-123.707687378,48.77709198],"type":"Point"}
}