{
  "type": "Feature",
  "properties": {
    "addr:full":"573 Rue Lafleur Lachute QC J8H 1R5",
    "addr:housenumber":"573",
    "addr:postcode":"j8h 1r5",
    "addr:street":"Rue Lafleur",
    "iso:country":"CA",
    "sg:address":"573 Rue Lafleur",
    "sg:city":"Lachute",
    "sg:classifiers":[
        {
            "category":"Real Estate",
            "subcategory":"Real Estate Agent",
            "type":"Services"
        }
    ],
    "sg:phone":"+1 450 562 9142",
    "sg:postcode":"J8H 1R5",
    "sg:province":"QC",
    "sg:tags":[
        "tool",
        "agency",
        "rental"
    ],
    "wof:name":"Location Madden Inc",
    "wof:placetype":"venue"
},
  "geometry": {"coordinates":[-74.33206199999999,45.656124],"type":"Point"}
}