{
  "type": "Feature",
  "properties": {
    "addr:full":"1291 Rue Johnson Thetford Mines QC G6G 5W7",
    "addr:housenumber":"1291",
    "addr:postcode":"g6g 5w7",
    "addr:street":"Rue Johnson",
    "iso:country":"CA",
    "sg:address":"1291 Rue Johnson",
    "sg:city":"Thetford Mines",
    "sg:classifiers":[
        {
            "category":"Personal",
            "subcategory":"Beauty Salon",
            "type":"Services"
        }
    ],
    "sg:phone":"+1 418 338 5683",
    "sg:postcode":"G6G 5W7",
    "sg:province":"QC",
    "wof:name":"Salon Beaute Pil Enr",
    "wof:placetype":"venue"
},
  "geometry": {"coordinates":[-71.339279,46.093357],"type":"Point"}
}