{
  "type": "Feature",
  "properties": {
    "addr:full":"371 Berkeley St Toronto ON M5A 2X8",
    "addr:housenumber":"371",
    "addr:postcode":"m5a 2x8",
    "addr:street":"Berkeley St",
    "iso:country":"CA",
    "sg:address":"371 Berkeley St",
    "sg:city":"Toronto",
    "sg:classifiers":[
        {
            "category":"Health Services",
            "subcategory":"Health Practitioner",
            "type":"Services"
        }
    ],
    "sg:phone":"+1 416 975 9388",
    "sg:postcode":"M5A 2X8",
    "sg:province":"ON",
    "sg:tags":[
        "psychotherapist"
    ],
    "wof:name":"Bustard, B R MD",
    "wof:placetype":"venue"
},
  "geometry": {"coordinates":[-79.368431,43.662346],"type":"Point"}
}