{
  "type": "Feature",
  "properties": {
    "addr:full":"500 Rennie St Hamilton ON L8H 3P5",
    "addr:housenumber":"500",
    "addr:postcode":"l8h 3p5",
    "addr:street":"Rennie St",
    "iso:country":"CA",
    "sg:address":"500 Rennie St",
    "sg:city":"Hamilton",
    "sg:classifiers":[
        {
            "category":"Freight",
            "type":"Transportation"
        }
    ],
    "sg:phone":"+1 905 548 0979",
    "sg:postcode":"L8H 3P5",
    "sg:province":"ON",
    "sg:tags":[
        "trucking"
    ],
    "wof:name":"Cole Carriers Corp",
    "wof:placetype":"venue"
},
  "geometry": {"coordinates":[-79.7806854248,43.2483291626],"type":"Point"}
}