{
  "type": "Feature",
  "properties": {
    "addr:full":"Centre St Alida SK S0C 0B0",
    "addr:postcode":"s0c 0b0",
    "addr:street":"Centre St",
    "iso:country":"CA",
    "sg:address":"Centre St",
    "sg:city":"Alida",
    "sg:classifiers":[
        {
            "category":"Insurance",
            "subcategory":"Insurance Agent",
            "type":"Services"
        }
    ],
    "sg:phone":"+1 306 443 2263",
    "sg:postcode":"S0C 0B0",
    "sg:province":"SK",
    "wof:name":"Carnduff Agencies Inc",
    "wof:placetype":"venue"
},
  "geometry": {"coordinates":[-101.874641419,49.3897895813],"type":"Point"}
}