{
  "type": "Feature",
  "properties": {
    "addr:full":"361 Alliford Bay Rd Sandspit BC V0T 1T0",
    "addr:housenumber":"361",
    "addr:postcode":"v0t 1t0",
    "addr:street":"Alliford Bay Rd",
    "iso:country":"CA",
    "sg:address":"361 Alliford Bay Rd",
    "sg:city":"Sandspit",
    "sg:classifiers":[
        {
            "category":"Building & Trades",
            "subcategory":"Construction",
            "type":"Services"
        }
    ],
    "sg:phone":"+1 250 637 5615",
    "sg:postcode":"V0T 1T0",
    "sg:province":"BC",
    "sg:tags":[
        "general",
        "contractor"
    ],
    "wof:name":"Shiels Contracting Ltd",
    "wof:placetype":"venue"
},
  "geometry": {"coordinates":[-131.838348,53.238579],"type":"Point"}
}