{
  "type": "Feature",
  "properties": {
    "addr:full":"Dartmouth NS B3B 1T6",
    "addr:postcode":"b3b 1t6",
    "iso:country":"CA",
    "sg:city":"Dartmouth",
    "sg:classifiers":[
        {
            "category":"Manufacturing",
            "subcategory":"Tools & Machinery",
            "type":"Manufacturing & Wholesale Goods"
        }
    ],
    "sg:phone":"+1 902 481 9000",
    "sg:postcode":"B3B 1T6",
    "sg:province":"NS",
    "sg:tags":[
        "equipment",
        "safety",
        "dealer",
        "boat",
        "sales"
    ],
    "wof:name":"Atlantic Aero Marine Supply",
    "wof:placetype":"venue"
},
  "geometry": {"coordinates":[-63.5887260437,44.703502655],"type":"Point"}
}