{
  "type": "Feature",
  "properties": {
    "iso:country":"CA",
    "sg:city":"Girouxville",
    "sg:classifiers":[
        {
            "category":"Retail",
            "subcategory":"Auto Repair",
            "type":"Services"
        }
    ],
    "sg:phone":"+1 780 323 4617",
    "sg:postcode":"T0H 1S0",
    "sg:province":"AB",
    "sg:tags":[
        "repairing",
        "automobile"
    ],
    "wof:name":"Boisvert Service Garage Ltd",
    "wof:placetype":"venue"
},
  "geometry": {"coordinates":[-117.338394165,55.7521324158],"type":"Point"}
}