{
  "type": "Feature",
  "properties": {
    "addr:full":"1 Henderson Dr Aurora ON L4G 4J7",
    "addr:housenumber":"1",
    "addr:postcode":"l4g 4j7",
    "addr:street":"Henderson Dr",
    "iso:country":"CA",
    "sg:address":"1 Henderson Dr",
    "sg:city":"Aurora",
    "sg:classifiers":[
        {
            "category":"Restaurant",
            "type":"Food & Drink"
        }
    ],
    "sg:phone":"+1 905 727 7918",
    "sg:postcode":"L4G 4J7",
    "sg:province":"ON",
    "sg:tags":[
        "chicken",
        "dinner"
    ],
    "wof:name":"Harvey's",
    "wof:placetype":"venue"
},
  "geometry": {"coordinates":[-79.4639129639,43.9836006165],"type":"Point"}
}