{
  "type": "Feature",
  "properties": {
    "addr:full":"98 Ch DE LA Baie Sainte-Barbe QC J0S 1P0",
    "addr:housenumber":"98",
    "addr:postcode":"j0s 1p0",
    "addr:street":"Ch De La Baie",
    "iso:country":"CA",
    "sg:address":"98 Ch DE LA Baie",
    "sg:city":"Sainte-Barbe",
    "sg:classifiers":[
        {
            "category":"Building & Trades",
            "subcategory":"Construction",
            "type":"Services"
        }
    ],
    "sg:phone":"+1 450 373 8259",
    "sg:postcode":"J0S 1P0",
    "sg:province":"QC",
    "sg:tags":[
        "excavating",
        "contractor"
    ],
    "wof:name":"Loiselle, Henri",
    "wof:placetype":"venue"
},
  "geometry": {"coordinates":[-74.18965911870001,45.1809043884],"type":"Point"}
}