{
  "type": "Feature",
  "properties": {
    "addr:full":"76 St Clair Ave W Toronto ON M4V 1M7",
    "addr:housenumber":"76",
    "addr:postcode":"m4v 1m7",
    "addr:street":"St Clair Ave W",
    "iso:country":"CA",
    "sg:address":"76 St Clair Ave W",
    "sg:city":"Toronto",
    "sg:classifiers":[
        {
            "category":"Cinema",
            "subcategory":"Movie Rental",
            "type":"Entertainment"
        }
    ],
    "sg:phone":"+1 416 963 0555",
    "sg:postcode":"M4V 1M7",
    "sg:province":"ON",
    "sg:tags":[
        "leasing",
        "video",
        "disc",
        "tape"
    ],
    "wof:name":"Deer Park Video",
    "wof:placetype":"venue"
},
  "geometry": {"coordinates":[-79.39752197270001,43.6875495911],"type":"Point"}
}