{
  "type": "Feature",
  "properties": {
    "addr:full":"1117 Rue Des Martins-Pecheurs Degelis QC G5T 2H7",
    "addr:housenumber":"1117",
    "addr:postcode":"g5t 2h7",
    "addr:street":"Rue Des Martins-Pecheurs Degelis",
    "iso:country":"CA",
    "sg:address":"1117 Rue Des Martins-Pecheurs",
    "sg:city":"Degelis",
    "sg:classifiers":[
        {
            "category":"Wholesale",
            "subcategory":"Construction Materials",
            "type":"Manufacturing & Wholesale Goods"
        }
    ],
    "sg:phone":"+1 418 853 5488",
    "sg:postcode":"G5T 2H7",
    "sg:province":"QC",
    "sg:tags":[
        "importer",
        "logging",
        "company"
    ],
    "wof:name":"Lemay Victorien Ltee",
    "wof:placetype":"venue"
},
  "geometry": {"coordinates":[-68.630821228,47.5474815369],"type":"Point"}
}