{
  "type": "Feature",
  "properties": {
    "addr:full":"110 Country Rd Corner Brook NL A2H 4M4",
    "addr:housenumber":"110",
    "addr:postcode":"a2h 4m4",
    "addr:street":"Country Rd",
    "iso:country":"CA",
    "sg:address":"110 Country Rd",
    "sg:city":"Corner Brook",
    "sg:classifiers":[
        {
            "category":"Personal",
            "subcategory":"Beauty Salon",
            "type":"Services"
        }
    ],
    "sg:phone":"+1 709 634 2721",
    "sg:postcode":"A2H 4M4",
    "sg:province":"NL",
    "wof:name":"Re-Style Hair Ctr",
    "wof:placetype":"venue"
},
  "geometry": {"coordinates":[-57.970627,48.943165],"type":"Point"}
}