{
  "type": "Feature",
  "properties": {
    "addr:full":"985 Rue Royale Trois-Rivieres QC G9A 4H7",
    "addr:housenumber":"985",
    "addr:postcode":"g9a 4h7",
    "addr:street":"Rue Royale",
    "iso:country":"CA",
    "sg:address":"985 Rue Royale",
    "sg:city":"Trois-Rivieres",
    "sg:classifiers":[
        {
            "category":"Social Services",
            "subcategory":"Job Training",
            "type":"Services"
        }
    ],
    "sg:phone":"+1 819 693 6777",
    "sg:postcode":"G9A 4H7",
    "sg:province":"QC",
    "sg:tags":[
        "employment"
    ],
    "wof:name":"Service D'Integration A L'Empl",
    "wof:placetype":"venue"
},
  "geometry": {"coordinates":[-72.542641,46.345154],"type":"Point"}
}