{
  "type": "Feature",
  "properties": {
    "addr:full":"8900 Boul Newman Lasalle QC H8R 1Y8",
    "addr:housenumber":"8900",
    "addr:postcode":"h8r 1y8",
    "addr:street":"Boul Newman",
    "iso:country":"CA",
    "sg:address":"8900 Boul Newman",
    "sg:city":"Lasalle",
    "sg:classifiers":[
        {
            "category":"Building & Trades",
            "subcategory":"Equipment Rental",
            "type":"Services"
        }
    ],
    "sg:phone":"+1 514 365 5000",
    "sg:postcode":"H8R 1Y8",
    "sg:province":"QC",
    "sg:tags":[
        "tool"
    ],
    "wof:name":"Centre DE Location Pyramide",
    "wof:placetype":"venue"
},
  "geometry": {"coordinates":[-73.63678,45.429646],"type":"Point"}
}