{
  "type": "Feature",
  "properties": {
    "addr:full":"3935 Route 115 Notre-Dame NB E4V 2G1",
    "addr:housenumber":"3935",
    "addr:postcode":"e4v 2g1",
    "addr:street":"Route 115",
    "iso:country":"CA",
    "sg:address":"3935 Route 115",
    "sg:city":"Notre-Dame",
    "sg:classifiers":[
        {
            "category":"Manufacturing",
            "subcategory":"Food",
            "type":"Manufacturing & Wholesale Goods"
        }
    ],
    "sg:phone":"+1 506 576 9292",
    "sg:postcode":"E4V 2G1",
    "sg:province":"NB",
    "sg:tags":[
        "tea",
        "coffee"
    ],
    "wof:name":"Down East Coffee Roasters Ltd",
    "wof:placetype":"venue"
},
  "geometry": {"coordinates":[-64.72901899999999,46.312519],"type":"Point"}
}