{
  "type": "Feature",
  "properties": {
    "iso:country":"CA",
    "sg:address":"250 Trowers Rd # 5",
    "sg:city":"Woodbridge",
    "sg:classifiers":[
        {
            "category":"Recreation",
            "type":"Entertainment"
        }
    ],
    "sg:phone":"+1 905 850 5151",
    "sg:postcode":"L4L 5Z6",
    "sg:province":"ON",
    "sg:tags":[
        "instruction",
        "gymnastic"
    ],
    "wof:name":"Academy of Gymnastics",
    "wof:placetype":"venue"
},
  "geometry": {"coordinates":[-79.561081,43.785583],"type":"Point"}
}