{
  "type": "Feature",
  "properties": {
    "addr:full":"Brampton ON L6W 4K6",
    "addr:postcode":"l6w 4k6",
    "iso:country":"CA",
    "sg:city":"Brampton",
    "sg:classifiers":[
        {
            "category":"Food & Beverages",
            "subcategory":"Bakery",
            "type":"Retail Goods"
        }
    ],
    "sg:phone":"+1 905 454 4220",
    "sg:postcode":"L6W 4K6",
    "sg:province":"ON",
    "sg:tags":[
        "doughnut"
    ],
    "wof:name":"Country Style Donuts",
    "wof:placetype":"venue"
},
  "geometry": {"coordinates":[-79.7429275513,43.7012290955],"type":"Point"}
}