{
  "type": "Feature",
  "properties": {
    "addr:full":"Brighton ON K0K 1H0",
    "addr:postcode":"k0k 1h0",
    "iso:country":"CA",
    "sg:city":"Brighton",
    "sg:classifiers":[
        {
            "category":"Building & Trades",
            "subcategory":"Construction",
            "type":"Services"
        }
    ],
    "sg:phone":"+1 613 475 3364",
    "sg:postcode":"K0K 1H0",
    "sg:province":"ON",
    "sg:tags":[
        "insulation",
        "home",
        "contractor",
        "improvement"
    ],
    "wof:name":"Cooper Insulation",
    "wof:placetype":"venue"
},
  "geometry": {"coordinates":[-77.7183,44.022205],"type":"Point"}
}