{
  "type": "Feature",
  "properties": {
    "addr:full":"100 Du Beau-Mont Beaupre QC G0A 1E0",
    "addr:housenumber":"100",
    "addr:postcode":"g0a 1e0",
    "addr:street":"Du Beau-Mont Beaupre",
    "iso:country":"CA",
    "sg:address":"100 Du Beau-Mont",
    "sg:city":"Beaupre",
    "sg:classifiers":[
        {
            "category":"Sports & Exercise",
            "subcategory":"Golf",
            "type":"Entertainment"
        }
    ],
    "sg:phone":"+1 418 827 4653",
    "sg:postcode":"G0A 1E0",
    "sg:province":"QC",
    "sg:tags":[
        "resort"
    ],
    "wof:name":"Golf Le Grand Vallon Mont",
    "wof:placetype":"venue"
},
  "geometry": {"coordinates":[-70.9082946777,47.0735855103],"type":"Point"}
}