{
  "type": "Feature",
  "properties": {
    "addr:full":"5504 50 Ave Bonnyville AB T9N 2K8",
    "addr:housenumber":"5504",
    "addr:postcode":"t9n 2k8",
    "addr:street":"50 Ave",
    "iso:country":"CA",
    "sg:address":"5504 50 Ave",
    "sg:city":"Bonnyville",
    "sg:classifiers":[
        {
            "category":"Autos & Motor Vehicles",
            "subcategory":"Auto Supplies",
            "type":"Retail Goods"
        }
    ],
    "sg:phone":"+1 780 826 3005",
    "sg:postcode":"T9N 2K8",
    "sg:province":"AB",
    "sg:tags":[
        "automobile",
        "parts"
    ],
    "wof:name":"Radford's Auto Supply Ctr Ltd",
    "wof:placetype":"venue"
},
  "geometry": {"coordinates":[-110.75559199999999,54.267815],"type":"Point"}
}