{
  "type": "Feature",
  "properties": {
    "addr:full":"4064 Rang Haut-St-Francois Laval QC H7E 4P2",
    "addr:housenumber":"4064",
    "addr:postcode":"h7e 4p2",
    "addr:street":"Rang Haut-St-Francois",
    "iso:country":"CA",
    "sg:address":"4064 Rang Haut-St-Francois",
    "sg:city":"Laval",
    "sg:classifiers":[
        {
            "category":"Wholesale",
            "subcategory":"Auto Parts",
            "type":"Manufacturing & Wholesale Goods"
        }
    ],
    "sg:phone":"+1 514 324 5366",
    "sg:postcode":"H7E 4P2",
    "sg:province":"QC",
    "sg:tags":[
        "automobile",
        "rebuilt"
    ],
    "wof:name":"Recycleur Duvernay",
    "wof:placetype":"venue"
},
  "geometry": {"coordinates":[-73.67990112299999,45.6291313171],"type":"Point"}
}