{
  "type": "Feature",
  "properties": {
    "addr:full":"7798 16 St NW Edmonton AB T6P 1L9",
    "addr:housenumber":"7798",
    "addr:postcode":"t6p 1l9",
    "addr:street":"16 St Nw",
    "iso:country":"CA",
    "sg:address":"7798 16 St NW",
    "sg:city":"Edmonton",
    "sg:classifiers":[
        {
            "category":"Manufacturing",
            "subcategory":"Signs",
            "type":"Manufacturing & Wholesale Goods"
        }
    ],
    "sg:phone":"+1 780 440 4114",
    "sg:postcode":"T6P 1L9",
    "sg:province":"AB",
    "wof:name":"Alberta Traffic Supply Ltd",
    "wof:placetype":"venue"
},
  "geometry": {"coordinates":[-113.367577,53.514816],"type":"Point"}
}