{
  "type": "Feature",
  "properties": {
    "addr:full":"125 Boul Saint-Joseph Lachine QC H8S 2K9",
    "addr:housenumber":"125",
    "addr:postcode":"h8s 2k9",
    "addr:street":"Boul Saint-Joseph",
    "iso:country":"CA",
    "sg:address":"125 Boul Saint-Joseph",
    "sg:city":"Lachine",
    "sg:classifiers":[
        {
            "category":"Manufacturing",
            "subcategory":"Tools & Machinery",
            "type":"Manufacturing & Wholesale Goods"
        }
    ],
    "sg:phone":"+1 514 637 9711",
    "sg:postcode":"H8S 2K9",
    "sg:province":"QC",
    "sg:tags":[
        "die",
        "maker"
    ],
    "wof:name":"Outillage Industriel Marino",
    "wof:placetype":"venue"
},
  "geometry": {"coordinates":[-73.6578903198,45.4376068115],"type":"Point"}
}