{
  "type": "Feature",
  "properties": {
    "iso:country":"CA",
    "sg:city":"Toronto",
    "sg:classifiers":[
        {
            "category":"Banks & Credit Unions",
            "subcategory":"Investment Brokerage",
            "type":"Services"
        }
    ],
    "sg:phone":"+1 416 515 2922",
    "sg:postcode":"M4V 1N6",
    "sg:province":"ON",
    "wof:name":"Equigenesis Corp",
    "wof:placetype":"venue"
},
  "geometry": {"coordinates":[-79.4000549316,43.6867408752],"type":"Point"}
}