{
  "type": "Feature",
  "properties": {
    "addr:full":"Nelson BC V1L 6L6",
    "addr:postcode":"bc v1l 6l6",
    "iso:country":"CA",
    "sg:city":"Nelson",
    "sg:classifiers":[
        {
            "category":"Education",
            "subcategory":"School",
            "type":"Public Place"
        }
    ],
    "sg:phone":"+1 250 825 4428",
    "sg:postcode":"V1L 6L6",
    "sg:province":"BC",
    "wof:name":"A I Collinson School",
    "wof:placetype":"venue"
},
  "geometry": {"coordinates":[-117.304832,49.486244],"type":"Point"}
}