{
  "type": "Feature",
  "properties": {
    "addr:full":"964 Laurier Ave Kelowna BC V1Y 6B1",
    "addr:housenumber":"964",
    "addr:postcode":"v1y 6b1",
    "addr:street":"Laurier Ave",
    "iso:country":"CA",
    "sg:address":"964 Laurier Ave",
    "sg:city":"Kelowna",
    "sg:classifiers":[
        {
            "category":"Health Services",
            "subcategory":"Nursing And Care Facility",
            "type":"Services"
        }
    ],
    "sg:phone":"+1 250 861 3991",
    "sg:postcode":"V1Y 6B1",
    "sg:province":"BC",
    "sg:tags":[
        "home",
        "senior",
        "convalescent",
        "citizen"
    ],
    "wof:name":"Comfort Living For Seniors Inc",
    "wof:placetype":"venue"
},
  "geometry": {"coordinates":[-119.48099499999999,49.882359],"type":"Point"}
}