{
  "type": "Feature",
  "properties": {
    "addr:full":"Terrace BC V8G 1V5",
    "addr:postcode":"v8g 1v5",
    "iso:country":"CA",
    "sg:city":"Terrace",
    "sg:classifiers":[
        {
            "category":"Government",
            "subcategory":"Office",
            "type":"Public Place"
        }
    ],
    "sg:phone":"+1 250 615 4828",
    "sg:postcode":"V8G 1V5",
    "sg:province":"BC",
    "wof:name":"B C Members of the Legislative",
    "wof:placetype":"venue"
},
  "geometry": {"coordinates":[-128.588684,54.518085],"type":"Point"}
}