{
  "type": "Feature",
  "properties": {
    "addr:full":"4200 Hobby Dr Prince George BC V2K 5V1",
    "addr:housenumber":"4200",
    "addr:postcode":"v2k 5v1",
    "addr:street":"Hobby Dr",
    "iso:country":"CA",
    "sg:address":"4200 Hobby Dr",
    "sg:city":"Prince George",
    "sg:classifiers":[
        {
            "category":"Freight",
            "type":"Transportation"
        }
    ],
    "sg:phone":"+1 250 962 5149",
    "sg:postcode":"V2K 5V1",
    "sg:province":"BC",
    "sg:tags":[
        "trucking"
    ],
    "wof:name":"Shane Perison Contracting",
    "wof:placetype":"venue"
},
  "geometry": {"coordinates":[-122.745087,53.91235],"type":"Point"}
}