{
  "type": "Feature",
  "properties": {
    "addr:full":"223 Ontario St Grand Bend ON N0M 1T0",
    "addr:housenumber":"223",
    "addr:postcode":"n0m 1t0",
    "addr:street":"Ontario St",
    "iso:country":"CA",
    "sg:address":"223 Ontario St",
    "sg:city":"Grand Bend",
    "sg:classifiers":[
        {
            "category":"Building & Trades",
            "subcategory":"Pest Control",
            "type":"Services"
        }
    ],
    "sg:phone":"+1 519 238 3648",
    "sg:postcode":"N0M 1T0",
    "sg:province":"ON",
    "wof:name":"Around the Bend Home Svc",
    "wof:placetype":"venue"
},
  "geometry": {"coordinates":[-81.764145,43.303612],"type":"Point"}
}