{
  "type": "Feature",
  "properties": {
    "addr:full":"123 Rue Saint-Paul Quebec QC G1K 3V8",
    "addr:housenumber":"123",
    "addr:postcode":"g1k 3v8",
    "addr:street":"Rue Saint-Paul",
    "iso:country":"CA",
    "sg:address":"123 Rue Saint-Paul",
    "sg:city":"Quebec",
    "sg:classifiers":[
        {
            "category":"Shopping",
            "subcategory":"Used Merchandise",
            "type":"Retail Goods"
        }
    ],
    "sg:phone":"+1 418 692 3099",
    "sg:postcode":"G1K 3V8",
    "sg:province":"QC",
    "sg:tags":[
        "antique"
    ],
    "wof:name":"Rendez-Vous Du Collectionneur",
    "wof:placetype":"venue"
},
  "geometry": {"coordinates":[-71.20534499999999,46.816372],"type":"Point"}
}