{
  "type": "Feature",
  "properties": {
    "addr:full":"LA Plaine QC J7M 1C3",
    "addr:postcode":"j7m 1c3",
    "iso:country":"CA",
    "sg:city":"LA Plaine",
    "sg:classifiers":[
        {
            "category":"Personal",
            "subcategory":"Beauty Salon",
            "type":"Services"
        }
    ],
    "sg:phone":"+1 450 968 2035",
    "sg:postcode":"J7M 1C3",
    "sg:province":"QC",
    "wof:name":"Salon L'Ambiance",
    "wof:placetype":"venue"
},
  "geometry": {"coordinates":[-73.711777,45.755436],"type":"Point"}
}