{
  "type": "Feature",
  "properties": {
    "addr:full":"60 DE L'Eglise Sayabec QC G0J 3K0",
    "addr:postcode":"g0j 3k0",
    "addr:street":"60 De L'Eglise",
    "iso:country":"CA",
    "sg:address":"60 DE L'Eglise",
    "sg:city":"Sayabec",
    "sg:classifiers":[
        {
            "category":"Personal",
            "subcategory":"Beauty Salon",
            "type":"Services"
        }
    ],
    "sg:phone":"+1 418 536 5051",
    "sg:postcode":"G0J 3K0",
    "sg:province":"QC",
    "wof:name":"Coiffure Maryse",
    "wof:placetype":"venue"
},
  "geometry": {"coordinates":[-67.688087,48.56646],"type":"Point"}
}