{
  "type": "Feature",
  "properties": {
    "addr:full":"Moonstone ON L0K 1N0",
    "addr:postcode":"l0k 1n0",
    "iso:country":"CA",
    "sg:city":"Moonstone",
    "sg:classifiers":[
        {
            "category":"Education",
            "subcategory":"School",
            "type":"Public Place"
        }
    ],
    "sg:phone":"+1 705 326 7476",
    "sg:postcode":"L0K 1N0",
    "sg:province":"ON",
    "wof:name":"Orillia Dance Academy",
    "wof:placetype":"venue"
},
  "geometry": {"coordinates":[-79.66194915769999,44.6561050415],"type":"Point"}
}