{
  "type": "Feature",
  "properties": {
    "addr:full":"1 Bond Rd Whitbourne NL A0B 3K0",
    "addr:housenumber":"1",
    "addr:postcode":"a0b 3k0",
    "addr:street":"Bond Rd",
    "iso:country":"CA",
    "sg:address":"1 Bond Rd",
    "sg:city":"Whitbourne",
    "sg:classifiers":[
        {
            "category":"Manufacturing",
            "subcategory":"Food",
            "type":"Manufacturing & Wholesale Goods"
        }
    ],
    "sg:phone":"+1 709 759 3003",
    "sg:postcode":"A0B 3K0",
    "sg:province":"NL",
    "sg:tags":[
        "winery"
    ],
    "wof:name":"Markland Cottage Winery",
    "wof:placetype":"venue"
},
  "geometry": {"coordinates":[-53.5358047485,47.4200057983],"type":"Point"}
}