{
  "type": "Feature",
  "properties": {
    "addr:full":"Scarborough ON M1T 1A3",
    "addr:postcode":"m1t 1a3",
    "iso:country":"CA",
    "sg:city":"Scarborough",
    "sg:classifiers":[
        {
            "category":"Food & Beverages",
            "subcategory":"Groceries & Convenience Stores",
            "type":"Retail Goods"
        }
    ],
    "sg:phone":"+1 416 502 9006",
    "sg:postcode":"M1T 1A3",
    "sg:province":"ON",
    "wof:name":"Convenient Plus",
    "wof:placetype":"venue"
},
  "geometry": {"coordinates":[-79.321915,43.773342],"type":"Point"}
}