{
  "type": "Feature",
  "properties": {
    "addr:full":"Uxbridge ON L9P 1Y2",
    "addr:postcode":"l9p 1y2",
    "iso:country":"CA",
    "sg:city":"Uxbridge",
    "sg:classifiers":[
        {
            "category":"Food & Beverages",
            "subcategory":"Groceries & Convenience Stores",
            "type":"Retail Goods"
        }
    ],
    "sg:phone":"+1 905 862 0351",
    "sg:postcode":"L9P 1Y2",
    "sg:province":"ON",
    "sg:tags":[
        "grocer"
    ],
    "wof:name":"M & M Meat Shops",
    "wof:placetype":"venue"
},
  "geometry": {"coordinates":[-79.1328582764,44.0913963318],"type":"Point"}
}