{
  "type": "Feature",
  "properties": {
    "addr:full":"8806 92 St NW Edmonton AB T6C 3R1",
    "addr:housenumber":"8806",
    "addr:postcode":"t6c 3r1",
    "addr:street":"92 St Nw",
    "iso:country":"CA",
    "sg:address":"8806 92 St NW",
    "sg:city":"Edmonton",
    "sg:classifiers":[
        {
            "category":"Health Services",
            "subcategory":"Chiropractor",
            "type":"Services"
        }
    ],
    "sg:phone":"+1 780 448 1020",
    "sg:postcode":"T6C 3R1",
    "sg:province":"AB",
    "wof:name":"Bonnie Doon Chiropractic",
    "wof:placetype":"venue"
},
  "geometry": {"coordinates":[-113.46854399999999,53.523766],"type":"Point"}
}