{
  "type": "Feature",
  "properties": {
    "addr:full":"781 Rte 139 Roxton Pond QC J0E 1Z0",
    "addr:housenumber":"781",
    "addr:postcode":"j0e 1z0",
    "addr:street":"Rte 139",
    "iso:country":"CA",
    "sg:address":"781 Rte 139",
    "sg:city":"Roxton Pond",
    "sg:phone":"+1 450 777 7734",
    "sg:postcode":"J0E 1Z0",
    "sg:province":"QC",
    "sg:tags":[
        "farm",
        "scale",
        "supply"
    ],
    "wof:name":"Weightronics Inc",
    "wof:placetype":"venue"
},
  "geometry": {"coordinates":[-72.66529083250001,45.4704627991],"type":"Point"}
}