{
  "type": "Feature",
  "properties": {
    "addr:full":"1219 Pembroke St E Pembroke ON K8A 7R8",
    "addr:housenumber":"1219",
    "addr:postcode":"k8a 7r8",
    "addr:street":"Pembroke St E",
    "iso:country":"CA",
    "sg:address":"1219 Pembroke St E",
    "sg:city":"Pembroke",
    "sg:classifiers":[
        {
            "category":"Shopping",
            "subcategory":"Computers & Home Electronics",
            "type":"Retail Goods"
        }
    ],
    "sg:phone":"+1 613 735 5544",
    "sg:postcode":"K8A 7R8",
    "sg:province":"ON",
    "sg:tags":[
        "equipment",
        "dealer"
    ],
    "wof:name":"Talco Computer Systems",
    "wof:placetype":"venue"
},
  "geometry": {"coordinates":[-77.0855255127,45.8240318298],"type":"Point"}
}