{
  "type": "Feature",
  "properties": {
    "addr:full":"751 Victoria Sq Montreal QC H2Y 2J3",
    "addr:housenumber":"751",
    "addr:postcode":"h2y 2j3",
    "addr:street":"Victoria Sq",
    "iso:country":"CA",
    "sg:address":"751 Victoria Sq",
    "sg:city":"Montreal",
    "sg:classifiers":[
        {
            "category":"Insurance",
            "subcategory":"Insurance Agent",
            "type":"Services"
        }
    ],
    "sg:phone":"+1 514 286 7400",
    "sg:postcode":"H2Y 2J3",
    "sg:province":"QC",
    "sg:tags":[
        "company",
        "holding"
    ],
    "wof:name":"Power Corp of Canada",
    "wof:placetype":"venue"
},
  "geometry": {"coordinates":[-73.560585,45.501518],"type":"Point"}
}