{
  "type": "Feature",
  "properties": {
    "addr:full":"7 Pine St Sudbury ON P3C 4W4",
    "addr:housenumber":"7",
    "addr:postcode":"p3c 4w4",
    "addr:street":"Pine St",
    "iso:country":"CA",
    "sg:address":"7 Pine St",
    "sg:city":"Sudbury",
    "sg:classifiers":[
        {
            "category":"Real Estate",
            "subcategory":"Real Estate Operator",
            "type":"Services"
        }
    ],
    "sg:phone":"+1 705 675 8019",
    "sg:postcode":"P3C 4W4",
    "sg:province":"ON",
    "sg:tags":[
        "boarding",
        "house"
    ],
    "wof:name":"Royal Apartments",
    "wof:placetype":"venue"
},
  "geometry": {"coordinates":[-80.999275,46.493271],"type":"Point"}
}