{
  "type": "Feature",
  "properties": {
    "iso:country":"CA",
    "sg:address":"5335 47 Ave",
    "sg:city":"Taber",
    "sg:classifiers":[
        {
            "category":"Food & Beverages",
            "subcategory":"Liquor & Beverages",
            "type":"Retail Goods"
        }
    ],
    "sg:phone":"+1 403 223 2241",
    "sg:postcode":"T1G 1R4",
    "sg:province":"AB",
    "sg:tags":[
        "store"
    ],
    "wof:name":"Taber Cold Beer & Liquor Store",
    "wof:placetype":"venue"
},
  "geometry": {"coordinates":[-112.14376799999999,49.784],"type":"Point"}
}