{
  "type": "Feature",
  "properties": {
    "iso:country":"CA",
    "sg:city":"London",
    "sg:classifiers":[
        {
            "category":"Shopping",
            "type":"Retail Goods"
        }
    ],
    "sg:phone":"+1 519 473 3700",
    "sg:postcode":"N6C 2R5",
    "sg:province":"ON",
    "sg:tags":[
        "hearing",
        "equipment",
        "supply",
        "impaired"
    ],
    "wof:name":"Carr Hearing Svc",
    "wof:placetype":"venue"
},
  "geometry": {"coordinates":[-81.227409,42.962193],"type":"Point"}
}