{
  "type": "Feature",
  "properties": {
    "iso:country":"CA",
    "sg:city":"Saskatoon",
    "sg:classifiers":[
        {
            "category":"Wholesale",
            "subcategory":"Hardware",
            "type":"Manufacturing & Wholesale Goods"
        }
    ],
    "sg:phone":"+1 306 931 7111",
    "sg:postcode":"S7K 4L1",
    "sg:province":"SK",
    "sg:tags":[
        "water",
        "cooler",
        "fountain",
        "filter"
    ],
    "wof:name":"Saskatoon Bottled Water CO",
    "wof:placetype":"venue"
},
  "geometry": {"coordinates":[-106.64901,52.160347],"type":"Point"}
}