{
  "type": "Feature",
  "properties": {
    "addr:full":"52065 Range Road 204 Sherwood Park AB T8G 1G3",
    "addr:housenumber":"52065",
    "addr:postcode":"t8g 1g3",
    "addr:street":"Range Road 204;Park",
    "iso:country":"CA",
    "sg:address":"52065 Range Road 204",
    "sg:city":"Sherwood Park",
    "sg:classifiers":[
        {
            "category":"Building & Trades",
            "subcategory":"Cleaning & Sanitation",
            "type":"Services"
        }
    ],
    "sg:phone":"+1 780 922 2133",
    "sg:postcode":"T8G 1G3",
    "sg:province":"AB",
    "sg:tags":[
        "cleaners",
        "janitor",
        "rug",
        "carpet"
    ],
    "wof:name":"R & K Carpet Cleaners",
    "wof:placetype":"venue"
},
  "geometry": {"coordinates":[-113.295738,53.526402],"type":"Point"}
}