{
  "type": "Feature",
  "properties": {
    "addr:full":"2000 Boul Firestone E Notre-Dame-Des-Prairies QC J6E 8Z6",
    "addr:housenumber":"2000",
    "addr:postcode":"j6e 8z6",
    "addr:street":"Boul Firestone E",
    "iso:country":"CA",
    "sg:address":"2000 Boul Firestone E",
    "sg:city":"Notre-Dame-Des-Prairies",
    "sg:classifiers":[
        {
            "category":"Home & Garden",
            "subcategory":"Hardware",
            "type":"Retail Goods"
        }
    ],
    "sg:phone":"+1 450 756 1616",
    "sg:postcode":"J6E 8Z6",
    "sg:province":"QC",
    "sg:tags":[
        "building",
        "material"
    ],
    "wof:name":"Rona Le Renovateur Regional",
    "wof:placetype":"venue"
},
  "geometry": {"coordinates":[-73.4146194458,46.0396270752],"type":"Point"}
}