{
  "type": "Feature",
  "properties": {
    "addr:full":"235 15th St West Vancouver BC V7T 2X1",
    "addr:housenumber":"235",
    "addr:postcode":"v7t 2x1",
    "addr:street":"15Th St",
    "iso:country":"CA",
    "sg:address":"235 15th St",
    "sg:city":"West Vancouver",
    "sg:classifiers":[
        {
            "category":"Restaurant",
            "type":"Food & Drink"
        }
    ],
    "sg:phone":"+1 604 913 8439",
    "sg:postcode":"V7T 2X1",
    "sg:province":"BC",
    "wof:name":"Saltaire Restaurant & Terrace",
    "wof:placetype":"venue"
},
  "geometry": {"coordinates":[-123.15682983400001,49.3275299072],"type":"Point"}
}