{
  "type": "Feature",
  "properties": {
    "addr:full":"48 Peter St S Orillia ON L3V 5B1",
    "addr:housenumber":"48",
    "addr:postcode":"l3v 5b1",
    "addr:street":"Peter St S",
    "iso:country":"CA",
    "sg:address":"48 Peter St S",
    "sg:city":"Orillia",
    "sg:classifiers":[
        {
            "category":"Social Services",
            "type":"Services"
        }
    ],
    "sg:phone":"+1 705 329 2265",
    "sg:postcode":"L3V 5B1",
    "sg:province":"ON",
    "sg:tags":[
        "organization",
        "welfare"
    ],
    "wof:name":"Lighthouse Christian Ministrie",
    "wof:placetype":"venue"
},
  "geometry": {"coordinates":[-79.4164733887,44.6079330444],"type":"Point"}
}