{
  "type": "Feature",
  "properties": {
    "addr:full":"22 Coldstream Cres Richmond Hill ON L4S 1E6",
    "addr:housenumber":"22",
    "addr:postcode":"l4s 1e6",
    "addr:street":"Coldstream Cres",
    "iso:country":"CA",
    "sg:address":"22 Coldstream Cres",
    "sg:city":"Richmond Hill",
    "sg:classifiers":[
        {
            "category":"Wholesale",
            "subcategory":"Chemicals & Plastics",
            "type":"Manufacturing & Wholesale Goods"
        }
    ],
    "sg:phone":"+1 905 416 0026",
    "sg:postcode":"L4S 1E6",
    "sg:province":"ON",
    "wof:name":"Clean Chem",
    "wof:placetype":"venue"
},
  "geometry": {"coordinates":[-79.4351882935,43.8970069885],"type":"Point"}
}