{
  "type": "Feature",
  "properties": {
    "addr:full":"1052 Hubrey Rd London ON N6N 1B6",
    "addr:housenumber":"1052",
    "addr:postcode":"n6n 1b6",
    "addr:street":"Hubrey Rd",
    "iso:country":"CA",
    "sg:address":"1052 Hubrey Rd",
    "sg:city":"London",
    "sg:classifiers":[
        {
            "category":"Manufacturing",
            "subcategory":"Metals",
            "type":"Manufacturing & Wholesale Goods"
        }
    ],
    "sg:phone":"+1 519 686 0803",
    "sg:postcode":"N6N 1B6",
    "sg:province":"ON",
    "sg:tags":[
        "plating"
    ],
    "wof:name":"Superior Metal Finishing Ltd",
    "wof:placetype":"venue"
},
  "geometry": {"coordinates":[-81.18330400000001,42.930157],"type":"Point"}
}