{
  "type": "Feature",
  "properties": {
    "iso:country":"CA",
    "sg:address":"1052 Hubrey Rd",
    "sg:city":"London",
    "sg:classifiers":[
        {
            "category":"Manufacturing",
            "subcategory":"Metals",
            "type":"Manufacturing & Wholesale Goods"
        }
    ],
    "sg:phone":"+1 519 686 0803",
    "sg:postcode":"N6N 1B6",
    "sg:province":"ON",
    "sg:tags":[
        "plating"
    ],
    "wof:name":"Superior Metal Finishing Ltd",
    "wof:placetype":"venue"
},
  "geometry": {"coordinates":[-81.183304,42.930157],"type":"Point"}
}