{
  "type": "Feature",
  "properties": {
    "iso:country":"CA",
    "sg:address":"101 King St # 17",
    "sg:city":"St Catharines",
    "sg:classifiers":[
        {
            "category":"Personal",
            "type":"Services"
        }
    ],
    "sg:phone":"+1 905 687 3559",
    "sg:postcode":"L2R 3H6",
    "sg:province":"ON",
    "sg:tags":[
        "electrolysis"
    ],
    "wof:name":"Beauty Spa",
    "wof:placetype":"venue"
},
  "geometry": {"coordinates":[-79.24588775629999,43.1589355469],"type":"Point"}
}