{
  "type": "Feature",
  "properties": {
    "addr:full":"119 Wasagaming Dr Wasagaming MB R0J 2H0",
    "addr:housenumber":"119",
    "addr:postcode":"r0j 2h0",
    "addr:street":"Wasagaming Dr",
    "iso:country":"CA",
    "sg:address":"119 Wasagaming Dr",
    "sg:city":"Wasagaming",
    "sg:classifiers":[
        {
            "category":"Recreation",
            "type":"Entertainment"
        }
    ],
    "sg:phone":"+1 204 848 7500",
    "sg:postcode":"R0J 2H0",
    "sg:province":"MB",
    "sg:tags":[
        "hall",
        "auditorium"
    ],
    "wof:name":"Danceland",
    "wof:placetype":"venue"
},
  "geometry": {"coordinates":[-99.972076,50.651073],"type":"Point"}
}