{
  "type": "Feature",
  "properties": {
    "addr:full":"17475 59 Ave Surrey BC V3S 1P3",
    "addr:housenumber":"17475",
    "addr:postcode":"v3s 1p3",
    "addr:street":"59 Ave",
    "iso:country":"CA",
    "sg:address":"17475 59 Ave",
    "sg:city":"Surrey",
    "sg:classifiers":[
        {
            "category":"Organizations",
            "subcategory":"Religious Organization",
            "type":"Services"
        }
    ],
    "sg:phone":"+1 604 574 4363",
    "sg:postcode":"V3S 1P3",
    "sg:province":"BC",
    "sg:tags":[
        "church"
    ],
    "wof:name":"Precious Blood Parish",
    "wof:placetype":"venue"
},
  "geometry": {"coordinates":[-122.739074707,49.1098060608],"type":"Point"}
}