{
  "type": "Feature",
  "properties": {
    "addr:full":"75 Mary St #10 Aurora ON L4G 1G3",
    "addr:housenumber":"75",
    "addr:postcode":"l4g 1g3",
    "addr:street":"Mary St # 10",
    "iso:country":"CA",
    "sg:address":"75 Mary St #10",
    "sg:city":"Aurora",
    "sg:classifiers":[
        {
            "category":"Autos & Motor Vehicles",
            "subcategory":"Auto Supplies",
            "type":"Retail Goods"
        }
    ],
    "sg:phone":"+1 905 841 7750",
    "sg:postcode":"L4G 1G3",
    "sg:province":"ON",
    "sg:tags":[
        "automobile",
        "parts"
    ],
    "wof:name":"B & B Dixon Automotive Inc",
    "wof:placetype":"venue"
},
  "geometry": {"coordinates":[-79.452866,43.999729],"type":"Point"}
}