{
  "type": "Feature",
  "properties": {
    "addr:full":"1192 Rue DE LA Poterie Cap-Rouge QC G1Y 2E5",
    "addr:housenumber":"1192",
    "addr:postcode":"g1y 2e5",
    "addr:street":"Rue De La Poterie",
    "iso:country":"CA",
    "sg:address":"1192 Rue DE LA Poterie",
    "sg:city":"Cap-Rouge",
    "sg:classifiers":[
        {
            "category":"Professional",
            "subcategory":"Secretarial Services",
            "type":"Services"
        }
    ],
    "sg:phone":"+1 418 652 1998",
    "sg:postcode":"G1Y 2E5",
    "sg:province":"QC",
    "sg:tags":[
        "processing",
        "word"
    ],
    "wof:name":"Traitement DE Textes Cap-Rouge",
    "wof:placetype":"venue"
},
  "geometry": {"coordinates":[-71.354218,46.753716],"type":"Point"}
}