{
  "type": "Feature",
  "properties": {
    "iso:country":"CA",
    "sg:address":"5761 Rue Jean-Talon E",
    "sg:city":"Saint-Leonard",
    "sg:classifiers":[
        {
            "category":"Restaurant",
            "type":"Food & Drink"
        }
    ],
    "sg:phone":"+1 514 255 2000",
    "sg:postcode":"H1S 1M3",
    "sg:province":"QC",
    "wof:name":"Chero Restaurant",
    "wof:placetype":"venue"
},
  "geometry": {"coordinates":[-73.580933,45.58424],"type":"Point"}
}