{
  "type": "Feature",
  "properties": {
    "addr:full":"2760 Yonge St Toronto ON M4N 2J2",
    "addr:housenumber":"2760",
    "addr:postcode":"m4n 2j2",
    "addr:street":"Yonge St",
    "iso:country":"CA",
    "sg:address":"2760 Yonge St",
    "sg:city":"Toronto",
    "sg:classifiers":[
        {
            "category":"Shopping",
            "subcategory":"Bicycles & Sporting Goods",
            "type":"Retail Goods"
        }
    ],
    "sg:phone":"+1 416 440 0244",
    "sg:postcode":"M4N 2J2",
    "sg:province":"ON",
    "sg:tags":[
        "equipment",
        "exercise"
    ],
    "wof:name":"Fitness Source",
    "wof:placetype":"venue"
},
  "geometry": {"coordinates":[-79.401009,43.718624],"type":"Point"}
}