{
  "type": "Feature",
  "properties": {
    "addr:full":"4331 Highgate Cres Mississauga ON L4W 3G9",
    "addr:housenumber":"4331",
    "addr:postcode":"l4w 3g9",
    "addr:street":"Highgate Cres",
    "iso:country":"CA",
    "sg:address":"4331 Highgate Cres",
    "sg:city":"Mississauga",
    "sg:classifiers":[
        {
            "category":"Building & Trades",
            "subcategory":"Construction",
            "type":"Services"
        }
    ],
    "sg:phone":"+1 905 624 9730",
    "sg:postcode":"L4W 3G9",
    "sg:province":"ON",
    "sg:tags":[
        "home",
        "improvement"
    ],
    "wof:name":"Four Seasons Bldg Renovations",
    "wof:placetype":"venue"
},
  "geometry": {"coordinates":[-79.61499000000001,43.625175],"type":"Point"}
}