{
  "type": "Feature",
  "properties": {
    "addr:full":"Vancouver BC V5P 3V2",
    "addr:postcode":"v5p 3v2",
    "iso:country":"CA",
    "sg:city":"Vancouver",
    "sg:classifiers":[
        {
            "category":"Professional",
            "subcategory":"Accounting & Tax Preparation",
            "type":"Services"
        }
    ],
    "sg:phone":"+1 604 322 7576",
    "sg:postcode":"V5P 3V2",
    "sg:province":"BC",
    "sg:tags":[
        "accountant"
    ],
    "wof:name":"Sandhu & CO",
    "wof:placetype":"venue"
},
  "geometry": {"coordinates":[-123.065147,49.237934],"type":"Point"}
}