{
  "type": "Feature",
  "properties": {
    "addr:full":"1501 Sieveright Rd Gloucester ON K1T 1M5",
    "addr:housenumber":"1501",
    "addr:postcode":"k1t 1m5",
    "addr:street":"Sieveright Rd",
    "iso:country":"CA",
    "sg:address":"1501 Sieveright Rd",
    "sg:city":"Gloucester",
    "sg:classifiers":[
        {
            "category":"Retail",
            "subcategory":"Repair Shop",
            "type":"Services"
        }
    ],
    "sg:phone":"+1 613 564 7707",
    "sg:postcode":"K1T 1M5",
    "sg:province":"ON",
    "sg:tags":[
        "welding"
    ],
    "wof:name":"Rock Welding",
    "wof:placetype":"venue"
},
  "geometry": {"coordinates":[-75.6372833252,45.3554039001],"type":"Point"}
}