{
  "type": "Feature",
  "properties": {
    "addr:full":"2425 Clemenceau Blvd Windsor ON N8T 2P4",
    "addr:housenumber":"2425",
    "addr:postcode":"n8t 2p4",
    "addr:street":"Clemenceau Blvd",
    "iso:country":"CA",
    "sg:address":"2425 Clemenceau Blvd",
    "sg:city":"Windsor",
    "sg:classifiers":[
        {
            "category":"Organizations",
            "subcategory":"Religious Organization",
            "type":"Services"
        }
    ],
    "sg:phone":"+1 519 974 8439",
    "sg:postcode":"N8T 2P4",
    "sg:province":"ON",
    "sg:tags":[
        "church"
    ],
    "wof:name":"Full Gospel Opendoor Assemblie",
    "wof:placetype":"venue"
},
  "geometry": {"coordinates":[-82.9540863037,42.3090362549],"type":"Point"}
}