{
  "type": "Feature",
  "properties": {
    "addr:full":"10388 Nordel Crt Delta BC V4G 1J7",
    "addr:housenumber":"10388",
    "addr:postcode":"v4g 1j7",
    "addr:street":"Nordel Crt",
    "iso:country":"CA",
    "sg:address":"10388 Nordel Crt",
    "sg:city":"Delta",
    "sg:classifiers":[
        {
            "category":"Recreation",
            "type":"Entertainment"
        }
    ],
    "sg:phone":"+1 604 584 6274",
    "sg:postcode":"V4G 1J7",
    "sg:province":"BC",
    "sg:tags":[
        "club",
        "hockey"
    ],
    "wof:name":"Nash",
    "wof:placetype":"venue"
},
  "geometry": {"coordinates":[-122.938316,49.149311],"type":"Point"}
}