{
  "type": "Feature",
  "properties": {
    "addr:full":"89 Scott St St Catharines ON L2N 1G8",
    "addr:housenumber":"89",
    "addr:postcode":"l2n 1g8",
    "addr:street":"Scott St",
    "iso:country":"CA",
    "sg:address":"89 Scott St",
    "sg:city":"St Catharines",
    "sg:classifiers":[
        {
            "category":"Education",
            "subcategory":"School",
            "type":"Public Place"
        }
    ],
    "sg:phone":"+1 905 935 3854",
    "sg:postcode":"L2N 1G8",
    "sg:province":"ON",
    "wof:name":"Calvary Christian School",
    "wof:placetype":"venue"
},
  "geometry": {"coordinates":[-79.25679,43.179123],"type":"Point"}
}