{
  "type": "Feature",
  "properties": {
    "iso:country":"CA",
    "sg:address":"110 Crawford Ave W",
    "sg:city":"Melfort",
    "sg:classifiers":[
        {
            "category":"Recreation",
            "type":"Entertainment"
        }
    ],
    "sg:phone":"+1 306 752 2779",
    "sg:postcode":"S0E 1A0",
    "sg:province":"SK",
    "sg:tags":[
        "club",
        "curling"
    ],
    "wof:name":"Melfort Curling Club",
    "wof:placetype":"venue"
},
  "geometry": {"coordinates":[-104.615364075,52.8637237549],"type":"Point"}
}