{
  "type": "Feature",
  "properties": {
    "addr:full":"303 12 St Cold Lake AB T9M 1B9",
    "addr:housenumber":"12",
    "addr:postcode":"t9m 1b9",
    "addr:street":"303",
    "iso:country":"CA",
    "sg:address":"303 12 St",
    "sg:city":"Cold Lake",
    "sg:classifiers":[
        {
            "category":"Social Services",
            "subcategory":"Adult Care",
            "type":"Services"
        }
    ],
    "sg:phone":"+1 780 639 3495",
    "sg:postcode":"T9M 1B9",
    "sg:province":"AB",
    "sg:tags":[
        "senior",
        "housing",
        "citizen"
    ],
    "wof:name":"Cold Lake Senior Citizens Ldge",
    "wof:placetype":"venue"
},
  "geometry": {"coordinates":[-110.180122376,54.4684066772],"type":"Point"}
}