{
  "type": "Feature",
  "properties": {
    "addr:full":"190 1E Av Portneuf QC G0A 2Y0",
    "addr:housenumber":"190",
    "addr:postcode":"g0a 2y0",
    "addr:street":"1E Av",
    "iso:country":"CA",
    "sg:address":"190 1E Av",
    "sg:city":"Portneuf",
    "sg:classifiers":[
        {
            "category":"Health Services",
            "subcategory":"Doctor",
            "type":"Services"
        }
    ],
    "sg:phone":"+1 418 286 3506",
    "sg:postcode":"G0A 2Y0",
    "sg:province":"QC",
    "sg:tags":[
        "clinic"
    ],
    "wof:name":"Pelletier, Fernand",
    "wof:placetype":"venue"
},
  "geometry": {"coordinates":[-71.884941,46.694111],"type":"Point"}
}