{
  "type": "Feature",
  "properties": {
    "addr:full":"3630 Brentwood Rd NW Calgary AB T2L 1K8",
    "addr:housenumber":"3630",
    "addr:postcode":"t2l 1k8",
    "addr:street":"Brentwood Rd Nw",
    "iso:country":"CA",
    "sg:address":"3630 Brentwood Rd NW",
    "sg:city":"Calgary",
    "sg:classifiers":[
        {
            "category":"Health Services",
            "subcategory":"Optometrist",
            "type":"Services"
        }
    ],
    "sg:phone":"+1 403 301 5333",
    "sg:postcode":"T2L 1K8",
    "sg:province":"AB",
    "wof:name":"Alliance Eye Ctr",
    "wof:placetype":"venue"
},
  "geometry": {"coordinates":[-114.126960754,51.0849838257],"type":"Point"}
}