{
  "type": "Feature",
  "properties": {
    "addr:full":"Rimbey AB T0C 2J0",
    "addr:postcode":"t0c 2j0",
    "iso:country":"CA",
    "sg:city":"Rimbey",
    "sg:classifiers":[
        {
            "category":"Organizations",
            "subcategory":"Religious Organization",
            "type":"Services"
        }
    ],
    "sg:phone":"+1 403 843 2126",
    "sg:postcode":"T0C 2J0",
    "sg:province":"AB",
    "sg:tags":[
        "church"
    ],
    "wof:name":"St Margaret Catholic Church",
    "wof:placetype":"venue"
},
  "geometry": {"coordinates":[-114.23828125,52.6396903992],"type":"Point"}
}