{
  "type": "Feature",
  "properties": {
    "addr:full":"1100 Central Pky W Mississauga ON L5C 4E5",
    "addr:housenumber":"1100",
    "addr:postcode":"l5c 4e5",
    "addr:street":"Central Pky W",
    "iso:country":"CA",
    "sg:address":"1100 Central Pky W",
    "sg:city":"Mississauga",
    "sg:classifiers":[
        {
            "category":"Health Services",
            "subcategory":"Health Practitioner",
            "type":"Services"
        }
    ],
    "sg:phone":"+1 905 272 1386",
    "sg:postcode":"L5C 4E5",
    "sg:province":"ON",
    "sg:tags":[
        "nurse",
        "registry"
    ],
    "wof:name":"Care Partners",
    "wof:placetype":"venue"
},
  "geometry": {"coordinates":[-79.657043,43.566608],"type":"Point"}
}