{
  "type": "Feature",
  "properties": {
    "addr:full":"Edmonton AB T6E 5Y6",
    "addr:postcode":"t6e 5y6",
    "iso:country":"CA",
    "sg:city":"Edmonton",
    "sg:classifiers":[
        {
            "category":"Organizations",
            "subcategory":"Labor Organization",
            "type":"Services"
        }
    ],
    "sg:phone":"+1 780 430 0422",
    "sg:postcode":"T6E 5Y6",
    "sg:province":"AB",
    "wof:name":"Beverage Workers",
    "wof:placetype":"venue"
},
  "geometry": {"coordinates":[-113.479652,53.476788],"type":"Point"}
}