{
  "type": "Feature",
  "properties": {
    "addr:full":"Stettler AB T0C 2L2",
    "addr:postcode":"t0c 2l2",
    "iso:country":"CA",
    "sg:city":"Stettler",
    "sg:classifiers":[
        {
            "category":"Shopping",
            "subcategory":"Stationery & Office Supplies",
            "type":"Retail Goods"
        }
    ],
    "sg:phone":"+1 403 742 2685",
    "sg:postcode":"T0C 2L2",
    "sg:province":"AB",
    "sg:tags":[
        "furniture"
    ],
    "wof:name":"Heartland Stationers Ltd",
    "wof:placetype":"venue"
},
  "geometry": {"coordinates":[-112.705406,52.325024],"type":"Point"}
}