{
  "type": "Feature",
  "properties": {
    "addr:full":"2415 Rue King E Fleurimont QC J1G 5G7",
    "addr:housenumber":"2415",
    "addr:postcode":"j1g 5g7",
    "addr:street":"Rue King E Fleurimont",
    "iso:country":"CA",
    "sg:address":"2415 Rue King E",
    "sg:city":"Fleurimont",
    "sg:classifiers":[
        {
            "category":"Building & Trades",
            "subcategory":"Construction",
            "type":"Services"
        }
    ],
    "sg:phone":"+1 819 821 0471",
    "sg:postcode":"J1G 5G7",
    "sg:province":"QC",
    "sg:tags":[
        "excavating",
        "contractor"
    ],
    "wof:name":"Excavation Henri Jette & Fils",
    "wof:placetype":"venue"
},
  "geometry": {"coordinates":[-71.8371124268,45.4126205444],"type":"Point"}
}