{
  "type": "Feature",
  "properties": {
    "iso:country":"CA",
    "sg:city":"Etobicoke",
    "sg:classifiers":[
        {
            "category":"Ferry",
            "type":"Transportation"
        }
    ],
    "sg:phone":"+1 416 620 7790",
    "sg:postcode":"M9C 5L5",
    "sg:province":"ON",
    "sg:tags":[
        "company",
        "steamship"
    ],
    "wof:name":"Apl Canada",
    "wof:placetype":"venue"
},
  "geometry": {"coordinates":[-79.5590438843,43.6254577637],"type":"Point"}
}