{
  "type": "Feature",
  "properties": {
    "addr:full":"Vancouver BC V6C 1T2",
    "addr:postcode":"v6c 1t2",
    "iso:country":"CA",
    "sg:city":"Vancouver",
    "sg:classifiers":[
        {
            "category":"Wholesale",
            "subcategory":"Jewelry",
            "type":"Manufacturing & Wholesale Goods"
        }
    ],
    "sg:phone":"+1 604 684 9388",
    "sg:postcode":"V6C 1T2",
    "sg:province":"BC",
    "sg:tags":[
        "jeweler",
        "supply"
    ],
    "wof:name":"Watier Findings Inc",
    "wof:placetype":"venue"
},
  "geometry": {"coordinates":[-123.114082336,49.285282135],"type":"Point"}
}