{
  "type": "Feature",
  "properties": {
    "addr:full":"5835 Coopers Ave Mississauga ON L4Z 1Y2",
    "addr:housenumber":"5835",
    "addr:postcode":"l4z 1y2",
    "addr:street":"Coopers Ave",
    "iso:country":"CA",
    "sg:address":"5835 Coopers Ave",
    "sg:city":"Mississauga",
    "sg:classifiers":[
        {
            "category":"Utilities",
            "subcategory":"Telephone",
            "type":"Services"
        }
    ],
    "sg:phone":"+1 905 890 2010",
    "sg:postcode":"L4Z 1Y2",
    "sg:province":"ON",
    "sg:tags":[
        "communications",
        "datum",
        "communication"
    ],
    "wof:name":"Allan Crawford Assoc Ltd",
    "wof:placetype":"venue"
},
  "geometry": {"coordinates":[-79.661171,43.631706],"type":"Point"}
}