{
  "type": "Feature",
  "properties": {
    "addr:full":"Main St Burin NL A0E 1E0",
    "addr:postcode":"a0e 1e0",
    "addr:street":"Main St",
    "iso:country":"CA",
    "sg:address":"Main St",
    "sg:city":"Burin",
    "sg:classifiers":[
        {
            "category":"Food & Beverages",
            "subcategory":"Groceries & Convenience Stores",
            "type":"Retail Goods"
        }
    ],
    "sg:phone":"+1 709 891 2900",
    "sg:postcode":"A0E 1E0",
    "sg:province":"NL",
    "sg:tags":[
        "grocer"
    ],
    "wof:name":"Brown's Store",
    "wof:placetype":"venue"
},
  "geometry": {"coordinates":[-55.1813087463,47.0724372864],"type":"Point"}
}