{
  "type": "Feature",
  "properties": {
    "addr:full":"48 First Ave Lowe Farm MB R0G 1E0",
    "addr:housenumber":"48",
    "addr:postcode":"r0g 1e0",
    "addr:street":"First Ave Lowe",
    "iso:country":"CA",
    "sg:address":"48 First Ave",
    "sg:city":"Lowe Farm",
    "sg:classifiers":[
        {
            "category":"Building & Trades",
            "subcategory":"Plumbing",
            "type":"Services"
        }
    ],
    "sg:phone":"+1 204 746 8284",
    "sg:postcode":"R0G 1E0",
    "sg:province":"MB",
    "sg:tags":[
        "tank",
        "septic"
    ],
    "wof:name":"Brown Septic Svc & Port-A-Pot",
    "wof:placetype":"venue"
},
  "geometry": {"coordinates":[-97.594909668,49.3556861877],"type":"Point"}
}