{
  "type": "Feature",
  "properties": {
    "addr:full":"15 Rue DE L'Anse Sainte-Anne-DE-Sorel QC J3P 5N3",
    "addr:housenumber":"15",
    "addr:postcode":"j3p 5n3",
    "addr:street":"Rue De L'Anse",
    "iso:country":"CA",
    "sg:address":"15 Rue DE L'Anse",
    "sg:city":"Sainte-Anne-DE-Sorel",
    "sg:classifiers":[
        {
            "category":"Building & Trades",
            "subcategory":"Construction",
            "type":"Services"
        }
    ],
    "sg:phone":"+1 450 743 6040",
    "sg:postcode":"J3P 5N3",
    "sg:province":"QC",
    "sg:tags":[
        "roofing",
        "contractor"
    ],
    "wof:name":"Patrick Bibeau Toitures",
    "wof:placetype":"venue"
},
  "geometry": {"coordinates":[-73.03117399999999,46.062271],"type":"Point"}
}