{
  "type": "Feature",
  "properties": {
    "addr:full":"Leduc AB T9E 2X2",
    "addr:postcode":"t9e 2x2",
    "iso:country":"CA",
    "sg:city":"Leduc",
    "sg:classifiers":[
        {
            "category":"Retail",
            "subcategory":"Animal Services",
            "type":"Services"
        }
    ],
    "sg:phone":"+1 780 986 6652",
    "sg:postcode":"T9E 2X2",
    "sg:province":"AB",
    "sg:tags":[
        "horse",
        "training"
    ],
    "wof:name":"Dawnville Farms",
    "wof:placetype":"venue"
},
  "geometry": {"coordinates":[-113.512916565,53.2215309143],"type":"Point"}
}