{
  "type": "Feature",
  "properties": {
    "addr:full":"Saint-Hyacinthe QC J2S 3H1",
    "addr:postcode":"j2s 3h1",
    "iso:country":"CA",
    "sg:city":"Saint-Hyacinthe",
    "sg:classifiers":[
        {
            "category":"Professional",
            "subcategory":"Management & Consulting",
            "type":"Services"
        }
    ],
    "sg:phone":"+1 450 261 1046",
    "sg:postcode":"J2S 3H1",
    "sg:province":"QC",
    "sg:tags":[
        "consultant",
        "instructional"
    ],
    "wof:name":"Rcr Premiers Soins Diane",
    "wof:placetype":"venue"
},
  "geometry": {"coordinates":[-72.944389,45.625694],"type":"Point"}
}