{
  "type": "Feature",
  "properties": {
    "addr:full":"130 Dawson Dr Faro YT Y0B 1K0",
    "addr:housenumber":"130",
    "addr:postcode":"y0b 1k0",
    "addr:street":"Dawson Dr",
    "iso:country":"CA",
    "sg:address":"130 Dawson Dr",
    "sg:city":"Faro",
    "sg:classifiers":[
        {
            "category":"Travel",
            "subcategory":"Hotels & Motels",
            "type":"Entertainment"
        }
    ],
    "sg:phone":"+1 867 994 3434",
    "sg:postcode":"Y0B 1K0",
    "sg:province":"YT",
    "sg:tags":[
        "breakfast",
        "accommodation",
        "bed"
    ],
    "wof:name":"Northstar Bed & Breakfast",
    "wof:placetype":"venue"
},
  "geometry": {"coordinates":[-133.35481300000001,62.229156],"type":"Point"}
}