{
  "type": "Feature",
  "properties": {
    "addr:full":"779 Boul Vachon S Sainte-Marie QC G6E 1Y4",
    "addr:housenumber":"779",
    "addr:postcode":"g6e 1y4",
    "addr:street":"Boul Vachon S",
    "iso:country":"CA",
    "sg:address":"779 Boul Vachon S",
    "sg:city":"Sainte-Marie",
    "sg:classifiers":[
        {
            "category":"Autos & Motor Vehicles",
            "subcategory":"Automobile Sales",
            "type":"Retail Goods"
        }
    ],
    "sg:phone":"+1 418 386 1523",
    "sg:postcode":"G6E 1Y4",
    "sg:province":"QC",
    "sg:tags":[
        "car",
        "dealer"
    ],
    "wof:name":"Guy Drouin Autos",
    "wof:placetype":"venue"
},
  "geometry": {"coordinates":[-71.00992599999999,46.432125],"type":"Point"}
}