{
  "type": "Feature",
  "properties": {
    "addr:full":"St Laurent MB R0C 2S0",
    "addr:postcode":"r0c 2s0",
    "iso:country":"CA",
    "sg:city":"St Laurent",
    "sg:classifiers":[
        {
            "category":"Retail",
            "subcategory":"Auto Repair",
            "type":"Services"
        }
    ],
    "sg:phone":"+1 204 646 2647",
    "sg:postcode":"R0C 2S0",
    "sg:province":"MB",
    "sg:tags":[
        "repairing",
        "automobile",
        "parts"
    ],
    "wof:name":"Alvins Muffler & General Rprs",
    "wof:placetype":"venue"
},
  "geometry": {"coordinates":[-97.936798,50.41819],"type":"Point"}
}