{
  "type": "Feature",
  "properties": {
    "addr:full":"297 Saint Marie St Collingwood ON L9Y 3K6",
    "addr:housenumber":"297",
    "addr:postcode":"l9y 3k6",
    "addr:street":"Saint Marie St",
    "iso:country":"CA",
    "sg:address":"297 Saint Marie St",
    "sg:city":"Collingwood",
    "sg:classifiers":[
        {
            "category":"Health Services",
            "subcategory":"Optometrist",
            "type":"Services"
        }
    ],
    "sg:phone":"+1 705 445 2970",
    "sg:postcode":"L9Y 3K6",
    "sg:province":"ON",
    "wof:name":"Hammond, R J OD",
    "wof:placetype":"venue"
},
  "geometry": {"coordinates":[-80.2138290405,44.4960517883],"type":"Point"}
}