{
  "type": "Feature",
  "properties": {
    "addr:full":"2418 Hwy 20 Anahim Lake BC V0L 1C0",
    "addr:housenumber":"2418",
    "addr:postcode":"v0l 1c0",
    "addr:street":"Hwy 20 Anahim",
    "iso:country":"CA",
    "sg:address":"2418 Hwy 20",
    "sg:city":"Anahim Lake",
    "sg:classifiers":[
        {
            "category":"Restaurant",
            "type":"Food & Drink"
        }
    ],
    "sg:phone":"+1 250 742 3268",
    "sg:postcode":"V0L 1C0",
    "sg:province":"BC",
    "wof:name":"Dutchman Restaurant",
    "wof:placetype":"venue"
},
  "geometry": {"coordinates":[-125.30693100000001,52.461704],"type":"Point"}
}