{
  "type": "Feature",
  "properties": {
    "addr:full":"18 Six Point Rd Etobicoke ON M8Z 2W9",
    "addr:housenumber":"18",
    "addr:postcode":"m8z 2w9",
    "addr:street":"Six Point Rd",
    "iso:country":"CA",
    "sg:address":"18 Six Point Rd",
    "sg:city":"Etobicoke",
    "sg:classifiers":[
        {
            "category":"Wholesale",
            "subcategory":"Groceries",
            "type":"Manufacturing & Wholesale Goods"
        }
    ],
    "sg:phone":"+1 416 236 7585",
    "sg:postcode":"M8Z 2W9",
    "sg:province":"ON",
    "sg:tags":[
        "baker"
    ],
    "wof:name":"Wanda's Pie in the Sky",
    "wof:placetype":"venue"
},
  "geometry": {"coordinates":[-79.53067016599999,43.6349830627],"type":"Point"}
}