{
  "type": "Feature",
  "properties": {
    "addr:full":"79 Elgin St N Cambridge ON N1R 5H4",
    "addr:housenumber":"79",
    "addr:postcode":"n1r 5h4",
    "addr:street":"Elgin St N",
    "iso:country":"CA",
    "sg:address":"79 Elgin St N",
    "sg:city":"Cambridge",
    "sg:classifiers":[
        {
            "category":"Restaurant",
            "type":"Food & Drink"
        }
    ],
    "sg:phone":"+1 519 621 1311",
    "sg:postcode":"N1R 5H4",
    "sg:province":"ON",
    "wof:name":"Silver China Rstrnt & Tavern",
    "wof:placetype":"venue"
},
  "geometry": {"coordinates":[-80.2985076904,43.3620605469],"type":"Point"}
}