{
  "type": "Feature",
  "properties": {
    "addr:full":"112 1st St W Kelvington SK S0A 1W0",
    "addr:housenumber":"112",
    "addr:postcode":"s0a 1w0",
    "addr:street":"1St St W Kelvington",
    "iso:country":"CA",
    "sg:address":"112 1st St W",
    "sg:city":"Kelvington",
    "sg:classifiers":[
        {
            "category":"Retail",
            "subcategory":"Auto Repair",
            "type":"Services"
        }
    ],
    "sg:phone":"+1 306 327 4992",
    "sg:postcode":"S0A 1W0",
    "sg:province":"SK",
    "sg:tags":[
        "body",
        "automobile",
        "painting"
    ],
    "wof:name":"Whiteline Auto Body",
    "wof:placetype":"venue"
},
  "geometry": {"coordinates":[-103.52950300000001,52.164566],"type":"Point"}
}