{
  "type": "Feature",
  "properties": {
    "iso:country":"CA",
    "sg:address":"PO Box 46",
    "sg:city":"Belle Plaine",
    "sg:classifiers":[
        {
            "category":"Retail",
            "subcategory":"Repair Shop",
            "type":"Services"
        }
    ],
    "sg:phone":"+1 306 345 2533",
    "sg:postcode":"S0G 0G0",
    "sg:province":"SK",
    "sg:tags":[
        "welding"
    ],
    "wof:name":"Gds Mfg",
    "wof:placetype":"venue"
},
  "geometry": {"coordinates":[-105.152450562,50.3932495117],"type":"Point"}
}