{
  "type": "Feature",
  "properties": {
    "addr:full":"Montreal QC H3B 4W8",
    "addr:postcode":"h3b 4w8",
    "iso:country":"CA",
    "sg:city":"Montreal",
    "sg:classifiers":[
        {
            "category":"Banks & Credit Unions",
            "subcategory":"Investment Brokerage",
            "type":"Services"
        }
    ],
    "sg:phone":"+1 514 933 8774",
    "sg:postcode":"H3B 4W8",
    "sg:province":"QC",
    "sg:tags":[
        "advisory",
        "financial"
    ],
    "wof:name":"Credit Suisse First Boston Can",
    "wof:placetype":"venue"
},
  "geometry": {"coordinates":[-73.55313099999999,45.517662],"type":"Point"}
}