{
  "type": "Feature",
  "properties": {
    "addr:full":"30 Marvin St New Hamburg ON N3A 4H8",
    "addr:housenumber":"30",
    "addr:postcode":"n3a 4h8",
    "addr:street":"Marvin St",
    "iso:country":"CA",
    "sg:address":"30 Marvin St",
    "sg:city":"New Hamburg",
    "sg:classifiers":[
        {
            "category":"Manufacturing",
            "subcategory":"Metals",
            "type":"Manufacturing & Wholesale Goods"
        }
    ],
    "sg:phone":"+1 519 662 1010",
    "sg:postcode":"N3A 4H8",
    "sg:province":"ON",
    "sg:tags":[
        "hardware"
    ],
    "wof:name":"Klassen Bronze Ltd",
    "wof:placetype":"venue"
},
  "geometry": {"coordinates":[-80.695297,43.379986],"type":"Point"}
}