{
  "type": "Feature",
  "properties": {
    "addr:full":"2645 Rue Maricourt Sherbrooke QC J1K 1R6",
    "addr:housenumber":"2645",
    "addr:postcode":"j1k 1r6",
    "addr:street":"Rue Maricourt",
    "iso:country":"CA",
    "sg:address":"2645 Rue Maricourt",
    "sg:city":"Sherbrooke",
    "sg:classifiers":[
        {
            "category":"Professional",
            "subcategory":"Management & Consulting",
            "type":"Services"
        }
    ],
    "sg:phone":"+1 819 565 3971",
    "sg:postcode":"J1K 1R6",
    "sg:province":"QC",
    "sg:tags":[
        "technical",
        "expertise",
        "analysis"
    ],
    "wof:name":"Levesque, Andre",
    "wof:placetype":"venue"
},
  "geometry": {"coordinates":[-71.937866,45.385715],"type":"Point"}
}