{
  "type": "Feature",
  "properties": {
    "addr:full":"1186 Middlegate Rd Oakville ON L6M 1M6",
    "addr:housenumber":"1186",
    "addr:postcode":"l6m 1m6",
    "addr:street":"Middlegate Rd",
    "iso:country":"CA",
    "sg:address":"1186 Middlegate Rd",
    "sg:city":"Oakville",
    "sg:classifiers":[
        {
            "category":"Local Transit",
            "type":"Transportation"
        }
    ],
    "sg:phone":"+1 905 847 1387",
    "sg:postcode":"L6M 1M6",
    "sg:province":"ON",
    "sg:tags":[
        "limousine"
    ],
    "wof:name":"Airport M & M Limo & Cab Svc",
    "wof:placetype":"venue"
},
  "geometry": {"coordinates":[-79.711769104,43.4475975037],"type":"Point"}
}