{
  "type": "Feature",
  "properties": {
    "addr:full":"210 Main St Vibank SK S0G 4Y0",
    "addr:housenumber":"210",
    "addr:postcode":"s0g 4y0",
    "addr:street":"Main St",
    "iso:country":"CA",
    "sg:address":"210 Main St",
    "sg:city":"Vibank",
    "sg:classifiers":[
        {
            "category":"Banks & Credit Unions",
            "subcategory":"Bank",
            "type":"Services"
        }
    ],
    "sg:phone":"+1 306 762 2166",
    "sg:postcode":"S0G 4Y0",
    "sg:province":"SK",
    "wof:name":"Plainsview Credit Union",
    "wof:placetype":"venue"
},
  "geometry": {"coordinates":[-103.94892900000001,50.333534],"type":"Point"}
}