{
  "type": "Feature",
  "properties": {
    "addr:full":"2355 Tedlo St Mississauga ON L5A 3W7",
    "addr:housenumber":"2355",
    "addr:postcode":"l5a 3w7",
    "addr:street":"Tedlo St",
    "iso:country":"CA",
    "sg:address":"2355 Tedlo St",
    "sg:city":"Mississauga",
    "sg:classifiers":[
        {
            "category":"Manufacturing",
            "subcategory":"Food",
            "type":"Manufacturing & Wholesale Goods"
        }
    ],
    "sg:phone":"+1 905 279 8330",
    "sg:postcode":"L5A 3W7",
    "sg:province":"ON",
    "sg:tags":[
        "juice"
    ],
    "wof:name":"Private Label Juices Ltd",
    "wof:placetype":"venue"
},
  "geometry": {"coordinates":[-79.5961685181,43.5869216919],"type":"Point"}
}