{
  "type": "Feature",
  "properties": {
    "addr:full":"357 Baig Blvd Moncton NB E1E 1E1",
    "addr:housenumber":"357",
    "addr:postcode":"e1e 1e1",
    "addr:street":"Baig Blvd",
    "iso:country":"CA",
    "sg:address":"357 Baig Blvd",
    "sg:city":"Moncton",
    "sg:classifiers":[
        {
            "category":"Freight",
            "type":"Transportation"
        }
    ],
    "sg:phone":"+1 506 855 3090",
    "sg:postcode":"E1E 1E1",
    "sg:province":"NB",
    "sg:tags":[
        "warehouse",
        "self",
        "storage"
    ],
    "wof:name":"Rjb Warehousing",
    "wof:placetype":"venue"
},
  "geometry": {"coordinates":[-64.830353,46.074383],"type":"Point"}
}