{
  "type": "Feature",
  "properties": {
    "addr:full":"4812 14 Ave SE Calgary AB T2A 0K9",
    "addr:housenumber":"4812",
    "addr:postcode":"t2a 0k9",
    "addr:street":"14 Ave Se",
    "iso:country":"CA",
    "sg:address":"4812 14 Ave SE",
    "sg:city":"Calgary",
    "sg:classifiers":[
        {
            "category":"Recreation",
            "type":"Entertainment"
        }
    ],
    "sg:phone":"+1 403 273 2944",
    "sg:postcode":"T2A 0K9",
    "sg:province":"AB",
    "sg:tags":[
        "pool",
        "swimming"
    ],
    "wof:name":"Bob Bahan Pool & Fitness Ctr",
    "wof:placetype":"venue"
},
  "geometry": {"coordinates":[-113.963546753,51.0410232544],"type":"Point"}
}