{
  "type": "Feature",
  "properties": {
    "addr:full":"4120A Sladeview Cres #1 Mississauga ON L5L 5Z3",
    "addr:housenumber":"4120a",
    "addr:postcode":"l5l 5z3",
    "addr:street":"Sladeview Cres # 1",
    "iso:country":"CA",
    "sg:address":"4120A Sladeview Cres #1",
    "sg:city":"Mississauga",
    "sg:classifiers":[
        {
            "category":"Manufacturing",
            "subcategory":"Tools & Machinery",
            "type":"Manufacturing & Wholesale Goods"
        }
    ],
    "sg:phone":"+1 905 820 4788",
    "sg:postcode":"L5L 5Z3",
    "sg:province":"ON",
    "sg:tags":[
        "physician",
        "surgeon",
        "manufacturer"
    ],
    "wof:name":"Rapid Aid Ltd",
    "wof:placetype":"venue"
},
  "geometry": {"coordinates":[-79.719444,43.528175],"type":"Point"}
}