{
  "type": "Feature",
  "properties": {
    "addr:full":"2255 Acadie Ch Cap-Pele NB E4N 1B2",
    "addr:housenumber":"2255",
    "addr:postcode":"e4n 1b2",
    "addr:street":"Acadie Ch Cap-Pele",
    "iso:country":"CA",
    "sg:address":"2255 Acadie Ch",
    "sg:city":"Cap-Pele",
    "sg:classifiers":[
        {
            "category":"Travel",
            "subcategory":"Hotels & Motels",
            "type":"Entertainment"
        }
    ],
    "sg:phone":"+1 506 577 2775",
    "sg:postcode":"E4N 1B2",
    "sg:province":"NB",
    "wof:name":"Aboiteau Restaurant & Motel",
    "wof:placetype":"venue"
},
  "geometry": {"coordinates":[-64.272102356,46.2154197693],"type":"Point"}
}