{
  "type": "Feature",
  "properties": {
    "addr:full":"Esterhazy SK S0A 0X0",
    "addr:postcode":"s0a 0x0",
    "addr:street":"Esterhazy",
    "iso:country":"CA",
    "sg:city":"Esterhazy",
    "sg:classifiers":[
        {
            "category":"Shopping",
            "subcategory":"Computers & Home Electronics",
            "type":"Retail Goods"
        }
    ],
    "sg:phone":"+1 306 745 6169",
    "sg:postcode":"S0A 0X0",
    "sg:province":"SK",
    "sg:tags":[
        "equipment",
        "dealer"
    ],
    "wof:name":"Better Build",
    "wof:placetype":"venue"
},
  "geometry": {"coordinates":[-102.078483581,50.6558380127],"type":"Point"}
}