{
  "type": "Feature",
  "properties": {
    "addr:full":"6021 Young St # 4A Halifax NS B3K 2A1",
    "addr:housenumber":"6021",
    "addr:postcode":"b3k 2a1",
    "addr:street":"Young St # 4A",
    "iso:country":"CA",
    "sg:address":"6021 Young St # 4A",
    "sg:city":"Halifax",
    "sg:classifiers":[
        {
            "category":"Manufacturing",
            "subcategory":"Electronics",
            "type":"Manufacturing & Wholesale Goods"
        }
    ],
    "sg:phone":"+1 902 455 4510",
    "sg:postcode":"B3K 2A1",
    "sg:province":"NS",
    "sg:tags":[
        "control",
        "automobile",
        "security",
        "radio",
        "stereo"
    ],
    "wof:name":"Halifax Car Audio",
    "wof:placetype":"venue"
},
  "geometry": {"coordinates":[-63.602463,44.659645],"type":"Point"}
}