{
  "type": "Feature",
  "properties": {
    "addr:full":"408 Rue DE Broqueville Beauport QC G1C 7R9",
    "addr:housenumber":"408",
    "addr:postcode":"qc g1c 7r9",
    "addr:street":"Rue De Broqueville",
    "iso:country":"CA",
    "sg:address":"408 Rue DE Broqueville",
    "sg:city":"Beauport",
    "sg:classifiers":[
        {
            "category":"Building & Trades",
            "subcategory":"Electrical",
            "type":"Services"
        }
    ],
    "sg:phone":"+1 418 660 9995",
    "sg:postcode":"G1C 7R9",
    "sg:province":"QC",
    "sg:tags":[
        "electric",
        "contractor"
    ],
    "wof:name":"Edi Electrique",
    "wof:placetype":"venue"
},
  "geometry": {"coordinates":[-71.214432,46.884991],"type":"Point"}
}