{
  "type": "Feature",
  "properties": {
    "addr:full":"6010 Edwards Blvd Mississauga ON L5T 2W3",
    "addr:housenumber":"6010",
    "addr:postcode":"l5t 2w3",
    "addr:street":"Edwards Blvd",
    "iso:country":"CA",
    "sg:address":"6010 Edwards Blvd",
    "sg:city":"Mississauga",
    "sg:classifiers":[
        {
            "category":"Manufacturing",
            "subcategory":"Furniture",
            "type":"Manufacturing & Wholesale Goods"
        }
    ],
    "sg:phone":"+1 905 564 2395",
    "sg:postcode":"L5T 2W3",
    "sg:province":"ON",
    "sg:tags":[
        "venetian",
        "blind"
    ],
    "wof:name":"D H Intl Ltd",
    "wof:placetype":"venue"
},
  "geometry": {"coordinates":[-79.67775726319999,43.6383666992],"type":"Point"}
}