{
  "type": "Feature",
  "properties": {
    "iso:country":"CA",
    "sg:address":"380 Wellington St",
    "sg:city":"London",
    "sg:classifiers":[
        {
            "category":"Professional",
            "subcategory":"Employment Agencies",
            "type":"Services"
        }
    ],
    "sg:phone":"+1 519 673 0345",
    "sg:postcode":"N6A 5B5",
    "sg:province":"ON",
    "sg:tags":[
        "opportunity",
        "contractor"
    ],
    "wof:name":"Kelly Services Inc",
    "wof:placetype":"venue"
},
  "geometry": {"coordinates":[-81.24462127690001,42.9841003418],"type":"Point"}
}