{
  "type": "Feature",
  "properties": {
    "addr:full":"4 Industrial Rd Bolton ON L7E 1K6",
    "addr:housenumber":"4",
    "addr:postcode":"l7e 1k6",
    "addr:street":"Industrial Rd",
    "iso:country":"CA",
    "sg:address":"4 Industrial Rd",
    "sg:city":"Bolton",
    "sg:classifiers":[
        {
            "category":"Personal",
            "type":"Services"
        }
    ],
    "sg:phone":"+1 905 857 2226",
    "sg:postcode":"L7E 1K6",
    "sg:province":"ON",
    "sg:tags":[
        "program",
        "physical",
        "exercise",
        "fitness"
    ],
    "wof:name":"Reflex Fitness Ctr",
    "wof:placetype":"venue"
},
  "geometry": {"coordinates":[-79.708359,43.858788],"type":"Point"}
}