{
  "type": "Feature",
  "properties": {
    "addr:full":"142 Parliament St Toronto ON M5A 2Z1",
    "addr:housenumber":"142",
    "addr:postcode":"m5a 2z1",
    "addr:street":"Parliament St",
    "iso:country":"CA",
    "sg:address":"142 Parliament St",
    "sg:city":"Toronto",
    "sg:classifiers":[
        {
            "category":"Food & Beverages",
            "subcategory":"Bakery",
            "type":"Retail Goods"
        }
    ],
    "sg:phone":"+1 416 363 0444",
    "sg:postcode":"M5A 2Z1",
    "sg:province":"ON",
    "sg:tags":[
        "doughnut"
    ],
    "wof:name":"Coffee Time Donuts",
    "wof:placetype":"venue"
},
  "geometry": {"coordinates":[-79.3642578125,43.6546897888],"type":"Point"}
}