{
  "type": "Feature",
  "properties": {
    "iso:country":"CA",
    "sg:address":"55 Northfield Dr E",
    "sg:city":"Waterloo",
    "sg:classifiers":[
        {
            "category":"Food & Beverages",
            "subcategory":"Bakery",
            "type":"Retail Goods"
        }
    ],
    "sg:phone":"+1 519 884 7226",
    "sg:postcode":"N2K 3T6",
    "sg:province":"ON",
    "sg:tags":[
        "shop",
        "doughnut",
        "coffee"
    ],
    "wof:name":"Tim Hortons",
    "wof:placetype":"venue"
},
  "geometry": {"coordinates":[-80.527885,43.503475],"type":"Point"}
}