{
  "type": "Feature",
  "properties": {
    "addr:full":"42231 Yarrow Central Rd Chilliwack BC V2R 5E3",
    "addr:postcode":"42231;v2r 5e3",
    "addr:street":"Central Rd",
    "iso:country":"CA",
    "sg:address":"42231 Yarrow Central Rd",
    "sg:city":"Chilliwack",
    "sg:classifiers":[
        {
            "category":"Food & Beverages",
            "subcategory":"Groceries & Convenience Stores",
            "type":"Retail Goods"
        }
    ],
    "sg:phone":"+1 604 823 6279",
    "sg:postcode":"V2R 5E3",
    "sg:province":"BC",
    "sg:tags":[
        "grocer"
    ],
    "wof:name":"Yarrow Supermarket",
    "wof:placetype":"venue"
},
  "geometry": {"coordinates":[-122.055717,49.082294],"type":"Point"}
}