{
  "type": "Feature",
  "properties": {
    "addr:full":"3575 Broadway St Hawkesville ON N0B 1X0",
    "addr:housenumber":"3575",
    "addr:postcode":"n0b 1x0",
    "addr:street":"Broadway St",
    "iso:country":"CA",
    "sg:address":"3575 Broadway St",
    "sg:city":"Hawkesville",
    "sg:classifiers":[
        {
            "category":"Building & Trades",
            "subcategory":"Construction",
            "type":"Services"
        }
    ],
    "sg:phone":"+1 519 699 4388",
    "sg:postcode":"N0B 1X0",
    "sg:province":"ON",
    "sg:tags":[
        "contractor"
    ],
    "wof:name":"Country Lane Builders Inc",
    "wof:placetype":"venue"
},
  "geometry": {"coordinates":[-80.6432189941,43.5643424988],"type":"Point"}
}