{
  "type": "Feature",
  "properties": {
    "addr:full":"561 Stephen St S Boissevain MB R0K 0E0",
    "addr:housenumber":"561",
    "addr:postcode":"r0k 0e0",
    "addr:street":"Stephen St S Boissevain",
    "iso:country":"CA",
    "sg:address":"561 Stephen St S",
    "sg:city":"Boissevain",
    "sg:classifiers":[
        {
            "category":"Manufacturing",
            "subcategory":"Printing",
            "type":"Manufacturing & Wholesale Goods"
        }
    ],
    "sg:phone":"+1 204 534 6479",
    "sg:postcode":"R0K 0E0",
    "sg:province":"MB",
    "sg:tags":[
        "newspaper"
    ],
    "wof:name":"Boissevain Recorder",
    "wof:placetype":"venue"
},
  "geometry": {"coordinates":[-100.059455872,49.2296257019],"type":"Point"}
}