{
  "type": "Feature",
  "properties": {
    "addr:full":"220 Bagot St Kingston ON K7L 3G2",
    "addr:housenumber":"220",
    "addr:postcode":"k7l 3g2",
    "addr:street":"Bagot St",
    "iso:country":"CA",
    "sg:address":"220 Bagot St",
    "sg:city":"Kingston",
    "sg:classifiers":[
        {
            "category":"Health Services",
            "subcategory":"Doctor",
            "type":"Services"
        }
    ],
    "sg:phone":"+1 613 549 4480",
    "sg:postcode":"K7L 3G2",
    "sg:province":"ON",
    "sg:tags":[
        "physician",
        "surgeon"
    ],
    "wof:name":"Griffiths, J MD",
    "wof:placetype":"venue"
},
  "geometry": {"coordinates":[-76.48523712159999,44.2303009033],"type":"Point"}
}