{
  "type": "Feature",
  "properties": {
    "addr:full":"66 Water St Vancouver BC V6B 1A4",
    "addr:housenumber":"66",
    "addr:postcode":"v6b 1a4",
    "addr:street":"Water St",
    "iso:country":"CA",
    "sg:address":"66 Water St",
    "sg:city":"Vancouver",
    "sg:classifiers":[
        {
            "category":"Bars & Pubs",
            "type":"Food & Drink"
        }
    ],
    "sg:phone":"+1 604 683 6695",
    "sg:postcode":"V6B 1A4",
    "sg:province":"BC",
    "sg:tags":[
        "club",
        "night"
    ],
    "wof:name":"Sonar Cabaret Ltd",
    "wof:placetype":"venue"
},
  "geometry": {"coordinates":[-123.10569,49.283623],"type":"Point"}
}