{
  "type": "Feature",
  "properties": {
    "addr:full":"1201 Egerter Rd Port Robinson ON L0S 1K0",
    "addr:housenumber":"1201",
    "addr:postcode":"l0s 1k0",
    "addr:street":"Egerter Rd",
    "iso:country":"CA",
    "sg:address":"1201 Egerter Rd",
    "sg:city":"Port Robinson",
    "sg:classifiers":[
        {
            "category":"Building & Trades",
            "subcategory":"Construction",
            "type":"Services"
        }
    ],
    "sg:phone":"+1 905 384 2761",
    "sg:postcode":"L0S 1K0",
    "sg:province":"ON",
    "sg:tags":[
        "steel",
        "electric",
        "contractor",
        "fabrication",
        "welding"
    ],
    "wof:name":"E S Fox Ltd",
    "wof:placetype":"venue"
},
  "geometry": {"coordinates":[-79.218628,43.032051],"type":"Point"}
}