{
  "type": "Feature",
  "properties": {
    "addr:full":"80 Bloor St E Toronto ON M4W 3G8",
    "addr:housenumber":"80",
    "addr:postcode":"m4w 3g8",
    "addr:street":"Bloor St E",
    "iso:country":"CA",
    "sg:address":"80 Bloor St E",
    "sg:city":"Toronto",
    "sg:classifiers":[
        {
            "category":"Retail",
            "subcategory":"Auto Rental",
            "type":"Services"
        }
    ],
    "sg:phone":"+1 416 964 2051",
    "sg:postcode":"M4W 3G8",
    "sg:province":"ON",
    "sg:tags":[
        "renting",
        "automobile"
    ],
    "wof:name":"Avis Rent A Car",
    "wof:placetype":"venue"
},
  "geometry": {"coordinates":[-79.38475,43.670792],"type":"Point"}
}