{
  "type": "Feature",
  "properties": {
    "addr:full":"1565 Joanisse Rd Clarence Creek ON K0A 1N0",
    "addr:housenumber":"1565",
    "addr:postcode":"k0a 1n0",
    "addr:street":"Joanisse Rd",
    "iso:country":"CA",
    "sg:address":"1565 Joanisse Rd",
    "sg:city":"Clarence Creek",
    "sg:classifiers":[
        {
            "category":"Manufacturing",
            "subcategory":"Printing",
            "type":"Manufacturing & Wholesale Goods"
        }
    ],
    "sg:phone":"+1 613 488 2822",
    "sg:postcode":"K0A 1N0",
    "sg:province":"ON",
    "sg:tags":[
        "equipment",
        "screen"
    ],
    "wof:name":"Teknecal Screen Print Supplies",
    "wof:placetype":"venue"
},
  "geometry": {"coordinates":[-75.21684999999999,45.507191],"type":"Point"}
}