{
  "type": "Feature",
  "properties": {
    "iso:country":"CA",
    "sg:address":"6061 Highway 7 # C",
    "sg:city":"Markham",
    "sg:classifiers":[
        {
            "category":"Home & Garden",
            "subcategory":"Furniture",
            "type":"Retail Goods"
        }
    ],
    "sg:phone":"+1 905 471 3500",
    "sg:postcode":"L3P 3B2",
    "sg:province":"ON",
    "sg:tags":[
        "equipment",
        "kitchen",
        "cabinet"
    ],
    "wof:name":"Creative Kitchen Gallery",
    "wof:placetype":"venue"
},
  "geometry": {"coordinates":[-79.339943,43.856033],"type":"Point"}
}