{
  "type": "Feature",
  "properties": {
    "addr:full":"1371 Rue Sainte-Catherine E Montreal QC H2L 2H7",
    "addr:housenumber":"1371",
    "addr:postcode":"h2l 2h7",
    "addr:street":"Rue Sainte-Catherine E",
    "iso:country":"CA",
    "sg:address":"1371 Rue Sainte-Catherine E",
    "sg:city":"Montreal",
    "sg:classifiers":[
        {
            "category":"Food & Beverages",
            "subcategory":"Bakery",
            "type":"Retail Goods"
        }
    ],
    "sg:phone":"+1 514 529 5656",
    "sg:postcode":"H2L 2H7",
    "sg:province":"QC",
    "sg:tags":[
        "baker"
    ],
    "wof:name":"Mie Matinale Inc",
    "wof:placetype":"venue"
},
  "geometry": {"coordinates":[-73.554695,45.520271],"type":"Point"}
}