{
  "type": "Feature",
  "properties": {
    "addr:full":"5217 Av King-Edward Montreal QC H4V 2J8",
    "addr:housenumber":"5217",
    "addr:postcode":"h4v 2j8",
    "addr:street":"Av King-Edward",
    "iso:country":"CA",
    "sg:address":"5217 Av King-Edward",
    "sg:city":"Montreal",
    "sg:classifiers":[
        {
            "category":"Health Services",
            "subcategory":"Doctor",
            "type":"Services"
        }
    ],
    "sg:phone":"+1 514 489 3781",
    "sg:postcode":"H4V 2J8",
    "sg:province":"QC",
    "sg:tags":[
        "physician",
        "surgeon"
    ],
    "wof:name":"Mazzella-Maiolo, L MD",
    "wof:placetype":"venue"
},
  "geometry": {"coordinates":[-73.64636993409999,45.4669418335],"type":"Point"}
}