{
  "type": "Feature",
  "properties": {
    "addr:full":"976 Boul Saint-Laurent Montreal QC H2Z 1J3",
    "addr:housenumber":"976",
    "addr:postcode":"h2z 1j3",
    "addr:street":"Boul Saint-Laurent",
    "iso:country":"CA",
    "sg:address":"976 Boul Saint-Laurent",
    "sg:city":"Montreal",
    "sg:classifiers":[
        {
            "category":"Wholesale",
            "subcategory":"Durable Goods & Equipment",
            "type":"Manufacturing & Wholesale Goods"
        }
    ],
    "sg:phone":"+1 514 861 5958",
    "sg:postcode":"H2Z 1J3",
    "sg:province":"QC",
    "sg:tags":[
        "importer"
    ],
    "wof:name":"Marie-Anne Novelties Inc",
    "wof:placetype":"venue"
},
  "geometry": {"coordinates":[-73.55901299999999,45.507504],"type":"Point"}
}