{
  "type": "Feature",
  "properties": {
    "addr:full":"SW 9 6 1E Hwy 205 Rosenort MB R0G 1W0",
    "addr:housenumber":"6 1e",
    "addr:postcode":"r0g 1w0",
    "addr:street":"Sw 9;Hwy 205 Rosenort",
    "iso:country":"CA",
    "sg:address":"SW 9 6 1E Hwy 205",
    "sg:city":"Rosenort",
    "sg:classifiers":[
        {
            "category":"Building & Trades",
            "subcategory":"Construction",
            "type":"Services"
        }
    ],
    "sg:phone":"+1 204 746 6564",
    "sg:postcode":"R0G 1W0",
    "sg:province":"MB",
    "wof:name":"Dueck Laminated Rafters",
    "wof:placetype":"venue"
},
  "geometry": {"coordinates":[-97.43461600000001,49.464806],"type":"Point"}
}