{
  "type": "Feature",
  "properties": {
    "addr:full":"220 Bay St #4 Toronto ON M5J 2W4",
    "addr:housenumber":"220",
    "addr:postcode":"m5j 2w4",
    "addr:street":"Bay St # 4",
    "iso:country":"CA",
    "sg:address":"220 Bay St #4",
    "sg:city":"Toronto",
    "sg:classifiers":[
        {
            "category":"Professional",
            "subcategory":"Printing & Photocopies",
            "type":"Services"
        }
    ],
    "sg:phone":"+1 416 306 9905",
    "sg:postcode":"M5J 2W4",
    "sg:province":"ON",
    "sg:tags":[
        "duplicating",
        "copying"
    ],
    "wof:name":"Tph the Printing House",
    "wof:placetype":"venue"
},
  "geometry": {"coordinates":[-79.380089,43.647743],"type":"Point"}
}