{
  "type": "Feature",
  "properties": {
    "iso:country":"CA",
    "sg:address":"237 Barton St E",
    "sg:city":"Hamilton",
    "sg:classifiers":[
        {
            "category":"Health Services",
            "subcategory":"Hospital",
            "type":"Services"
        }
    ],
    "sg:phone":"+1 905 527 0271",
    "sg:postcode":"L8L 2X2",
    "sg:province":"ON",
    "wof:name":"Hamilton General Hospital",
    "wof:placetype":"venue"
},
  "geometry": {"coordinates":[-79.85437011720001,43.2613868713],"type":"Point"}
}