{
  "type": "Feature",
  "properties": {
    "iso:country":"CA",
    "sg:address":"3465 Golden Orchard Dr",
    "sg:city":"Mississauga",
    "sg:classifiers":[
        {
            "category":"Education",
            "subcategory":"School",
            "type":"Public Place"
        }
    ],
    "sg:phone":"+1 905 625 0140",
    "sg:postcode":"L4Y 3H7",
    "sg:province":"ON",
    "wof:name":"Burnhamthorpe School",
    "wof:placetype":"venue"
},
  "geometry": {"coordinates":[-79.598251,43.615959],"type":"Point"}
}