{
  "type": "Feature",
  "properties": {
    "addr:full":"249 Notre Dame Ave Winnipeg MB R3B 1N8",
    "addr:housenumber":"249",
    "addr:postcode":"r3b 1n8",
    "addr:street":"Notre Dame Ave",
    "iso:country":"CA",
    "sg:address":"249 Notre Dame Ave",
    "sg:city":"Winnipeg",
    "sg:classifiers":[
        {
            "category":"Wholesale",
            "subcategory":"Electrical",
            "type":"Manufacturing & Wholesale Goods"
        }
    ],
    "sg:phone":"+1 204 943 5070",
    "sg:postcode":"R3B 1N8",
    "sg:province":"MB",
    "sg:tags":[
        "control",
        "security",
        "system"
    ],
    "wof:name":"Western Safe & Lock CO",
    "wof:placetype":"venue"
},
  "geometry": {"coordinates":[-97.141441,49.895866],"type":"Point"}
}