{
  "type": "Feature",
  "properties": {
    "addr:full":"11 Morrow Rd Barrie ON L4N 3V7",
    "addr:housenumber":"11",
    "addr:postcode":"l4n 3v7",
    "addr:street":"Morrow Rd",
    "iso:country":"CA",
    "sg:address":"11 Morrow Rd",
    "sg:city":"Barrie",
    "sg:classifiers":[
        {
            "category":"Manufacturing",
            "subcategory":"Metals",
            "type":"Manufacturing & Wholesale Goods"
        }
    ],
    "sg:phone":"+1 705 733 0066",
    "sg:postcode":"L4N 3V7",
    "sg:province":"ON",
    "sg:tags":[
        "die",
        "nonferrous",
        "casting",
        "alum"
    ],
    "wof:name":"Odc Manufacturing Ltd",
    "wof:placetype":"venue"
},
  "geometry": {"coordinates":[-79.699928,44.359737],"type":"Point"}
}