{
  "type": "Feature",
  "properties": {
    "addr:full":"11969 224 St Maple Ridge BC V2X 6B4",
    "addr:housenumber":"11969",
    "addr:postcode":"v2x 6b4",
    "addr:street":"224 St",
    "iso:country":"CA",
    "sg:address":"11969 224 St",
    "sg:city":"Maple Ridge",
    "sg:classifiers":[
        {
            "category":"Restaurant",
            "type":"Food & Drink"
        }
    ],
    "sg:phone":"+1 604 463 3663",
    "sg:postcode":"V2X 6B4",
    "sg:province":"BC",
    "wof:name":"Subway Sandwiches & Salads",
    "wof:placetype":"venue"
},
  "geometry": {"coordinates":[-122.601868,49.219788],"type":"Point"}
}