{
  "type": "Feature",
  "properties": {
    "iso:country":"CA",
    "sg:address":"10123 101st Ave",
    "sg:city":"Lac LA Biche",
    "sg:classifiers":[
        {
            "category":"Health Services",
            "subcategory":"Doctor",
            "type":"Services"
        }
    ],
    "sg:phone":"+1 780 623 4910",
    "sg:postcode":"T0A 2C0",
    "sg:province":"AB",
    "sg:tags":[
        "dentist"
    ],
    "wof:name":"Gee, Ronald DDS",
    "wof:placetype":"venue"
},
  "geometry": {"coordinates":[-111.976387024,54.7702255249],"type":"Point"}
}