{
  "type": "Feature",
  "properties": {
    "addr:full":"2531 Nanoose Beach Rd Nanoose Bay BC V9P 9E5",
    "addr:housenumber":"2531",
    "addr:postcode":"v9p 9e5",
    "addr:street":"Nanoose Beach Rd",
    "iso:country":"CA",
    "sg:address":"2531 Nanoose Beach Rd",
    "sg:city":"Nanoose Bay",
    "sg:classifiers":[
        {
            "category":"Organizations",
            "subcategory":"Religious Organization",
            "type":"Services"
        }
    ],
    "sg:phone":"+1 250 468 7644",
    "sg:postcode":"V9P 9E5",
    "sg:province":"BC",
    "sg:tags":[
        "church"
    ],
    "wof:name":"Nanoose Bay Pentecostal Camp",
    "wof:placetype":"venue"
},
  "geometry": {"coordinates":[-124.192703247,49.2626914978],"type":"Point"}
}