{
  "type": "Feature",
  "properties": {
    "addr:full":"104 Rue Saint-Jean-Baptiste L'Anse-Saint-Jean QC G0V 1J0",
    "addr:housenumber":"104",
    "addr:postcode":"g0v 1j0",
    "addr:street":"Rue Saint-Jean-Baptiste",
    "iso:country":"CA",
    "sg:address":"104 Rue Saint-Jean-Baptiste",
    "sg:city":"L'Anse-Saint-Jean",
    "sg:classifiers":[
        {
            "category":"Freight",
            "type":"Transportation"
        }
    ],
    "sg:phone":"+1 418 272 3031",
    "sg:postcode":"G0V 1J0",
    "sg:province":"QC",
    "sg:tags":[
        "trucking"
    ],
    "wof:name":"Laureat Gagne Inc",
    "wof:placetype":"venue"
},
  "geometry": {"coordinates":[-70.2281570435,48.2094535828],"type":"Point"}
}