{
  "type": "Feature",
  "properties": {
    "addr:full":"1850 1st St N Brandon MB R7C 1A9",
    "addr:housenumber":"1850",
    "addr:postcode":"r7c 1a9",
    "addr:street":"1St St N",
    "iso:country":"CA",
    "sg:address":"1850 1st St N",
    "sg:city":"Brandon",
    "sg:classifiers":[
        {
            "category":"Wholesale",
            "subcategory":"Groceries",
            "type":"Manufacturing & Wholesale Goods"
        }
    ],
    "sg:phone":"+1 204 728 7829",
    "sg:postcode":"R7C 1A9",
    "sg:province":"MB",
    "sg:tags":[
        "food",
        "baker",
        "product"
    ],
    "wof:name":"Weston Bakeries Ltd",
    "wof:placetype":"venue"
},
  "geometry": {"coordinates":[-99.939255,49.880802],"type":"Point"}
}