{
  "type": "Feature",
  "properties": {
    "iso:country":"CA",
    "sg:city":"Jerseyville",
    "sg:classifiers":[
        {
            "category":"Wholesale",
            "subcategory":"Machinery & Supplies",
            "type":"Manufacturing & Wholesale Goods"
        }
    ],
    "sg:phone":"+1 905 648 8001",
    "sg:postcode":"L0R 1R0",
    "sg:province":"ON",
    "sg:tags":[
        "lawn",
        "garden"
    ],
    "wof:name":"Crossroads Equipment",
    "wof:placetype":"venue"
},
  "geometry": {"coordinates":[-80.0511398315,43.2243270874],"type":"Point"}
}