{
  "type": "Feature",
  "properties": {
    "addr:full":"1245 Brookdale Ave Cornwall ON K6J 4P7",
    "addr:housenumber":"1245",
    "addr:postcode":"k6j 4p7",
    "addr:street":"Brookdale Ave",
    "iso:country":"CA",
    "sg:address":"1245 Brookdale Ave",
    "sg:city":"Cornwall",
    "sg:classifiers":[
        {
            "category":"Restaurant",
            "type":"Food & Drink"
        }
    ],
    "sg:phone":"+1 613 933 6330",
    "sg:postcode":"K6J 4P7",
    "sg:province":"ON",
    "wof:name":"Kfc",
    "wof:placetype":"venue"
},
  "geometry": {"coordinates":[-74.75235000000001,45.028107],"type":"Point"}
}