{
  "type": "Feature",
  "properties": {
    "addr:full":"1054 Boul Dr Albiny-Paquette Mont-Laurier QC J9L 1M1",
    "addr:housenumber":"1054",
    "addr:postcode":"j9l 1m1",
    "addr:street":"Boul Dr Albiny-Paquette",
    "iso:country":"CA",
    "sg:address":"1054 Boul Dr Albiny-Paquette",
    "sg:city":"Mont-Laurier",
    "sg:classifiers":[
        {
            "category":"Wholesale",
            "subcategory":"Groceries",
            "type":"Manufacturing & Wholesale Goods"
        }
    ],
    "sg:phone":"+1 819 623 6666",
    "sg:postcode":"J9L 1M1",
    "sg:province":"QC",
    "sg:tags":[
        "beverage"
    ],
    "wof:name":"Jules St-Pierre Ltee",
    "wof:placetype":"venue"
},
  "geometry": {"coordinates":[-75.48384900000001,46.550968],"type":"Point"}
}