{
  "type": "Feature",
  "properties": {
    "addr:full":"250 May St N Thunder Bay ON P7C 3P8",
    "addr:housenumber":"250",
    "addr:postcode":"p7c 3p8",
    "addr:street":"May St N",
    "iso:country":"CA",
    "sg:address":"250 May St N",
    "sg:city":"Thunder Bay",
    "sg:classifiers":[
        {
            "category":"Retail",
            "subcategory":"Auto Repair",
            "type":"Services"
        }
    ],
    "sg:phone":"+1 807 628 8875",
    "sg:postcode":"P7C 3P8",
    "sg:province":"ON",
    "sg:tags":[
        "repairing",
        "automobile"
    ],
    "wof:name":"Tech 1 Auto Repair",
    "wof:placetype":"venue"
},
  "geometry": {"coordinates":[-89.2453918457,48.3875999451],"type":"Point"}
}