{
  "type": "Feature",
  "properties": {
    "addr:full":"3020 52 St NE Calgary AB T1Y 5P4",
    "addr:housenumber":"3020",
    "addr:postcode":"t1y 5p4",
    "addr:street":"52 St Ne",
    "iso:country":"CA",
    "sg:address":"3020 52 St NE",
    "sg:city":"Calgary",
    "sg:classifiers":[
        {
            "category":"Education",
            "subcategory":"School",
            "type":"Public Place"
        }
    ],
    "sg:phone":"+1 403 280 6565",
    "sg:postcode":"T1Y 5P4",
    "sg:province":"AB",
    "wof:name":"Lester B Pearson High School",
    "wof:placetype":"venue"
},
  "geometry": {"coordinates":[-113.958191,51.077194],"type":"Point"}
}