{
  "type": "Feature",
  "properties": {
    "addr:full":"12 Hares Rd Nobel ON P0G 1G0",
    "addr:housenumber":"12",
    "addr:postcode":"p0g 1g0",
    "addr:street":"Hares Rd",
    "iso:country":"CA",
    "sg:address":"12 Hares Rd",
    "sg:city":"Nobel",
    "sg:classifiers":[
        {
            "category":"Manufacturing",
            "subcategory":"Signs",
            "type":"Manufacturing & Wholesale Goods"
        }
    ],
    "sg:phone":"+1 705 342 9306",
    "sg:postcode":"P0G 1G0",
    "sg:province":"ON",
    "wof:name":"Lou Balicki Signs",
    "wof:placetype":"venue"
},
  "geometry": {"coordinates":[-80.09229999999999,45.414669],"type":"Point"}
}