{
  "type": "Feature",
  "properties": {
    "addr:full":"9406 Rue Main Richibucto NB E4W 4E1",
    "addr:housenumber":"9406",
    "addr:postcode":"e4w 4e1",
    "addr:street":"Rue Main",
    "iso:country":"CA",
    "sg:address":"9406 Rue Main",
    "sg:city":"Richibucto",
    "sg:classifiers":[
        {
            "category":"Manufacturing",
            "subcategory":"Printing",
            "type":"Manufacturing & Wholesale Goods"
        }
    ],
    "sg:phone":"+1 506 523 6231",
    "sg:postcode":"E4W 4E1",
    "sg:province":"NB",
    "sg:tags":[
        "newspaper"
    ],
    "wof:name":"L'Etoile",
    "wof:placetype":"venue"
},
  "geometry": {"coordinates":[-64.86209869379999,46.6840782166],"type":"Point"}
}