{
  "type": "Feature",
  "properties": {
    "addr:full":"124 Broadview Ave Whitby ON L1N 2G5",
    "addr:housenumber":"124",
    "addr:postcode":"l1n 2g5",
    "addr:street":"Broadview Ave",
    "iso:country":"CA",
    "sg:address":"124 Broadview Ave",
    "sg:city":"Whitby",
    "sg:classifiers":[
        {
            "category":"Building & Trades",
            "subcategory":"Landscaping Services",
            "type":"Services"
        }
    ],
    "sg:phone":"+1 905 436 7833",
    "sg:postcode":"L1N 2G5",
    "sg:province":"ON",
    "sg:tags":[
        "lawn",
        "maintenance",
        "grounds"
    ],
    "wof:name":"L & D Mowing",
    "wof:placetype":"venue"
},
  "geometry": {"coordinates":[-78.899384,43.882481],"type":"Point"}
}