{
  "type": "Feature",
  "properties": {
    "addr:full":"701 108E Ave Saint-Georges-DE-Champlain QC G9T 5K4",
    "addr:housenumber":"701",
    "addr:postcode":"g9t 5k4",
    "addr:street":"108E Ave",
    "iso:country":"CA",
    "sg:address":"701 108E Ave",
    "sg:city":"Saint-Georges-DE-Champlain",
    "sg:classifiers":[
        {
            "category":"Food & Beverages",
            "subcategory":"Groceries & Convenience Stores",
            "type":"Retail Goods"
        }
    ],
    "sg:phone":"+1 819 533 5445",
    "sg:postcode":"G9T 5K4",
    "sg:province":"QC",
    "sg:tags":[
        "grocer"
    ],
    "wof:name":"Marche St-Georges Metro Enr",
    "wof:placetype":"venue"
},
  "geometry": {"coordinates":[-72.34311700000001,46.44104],"type":"Point"}
}