{
  "type": "Feature",
  "properties": {
    "iso:country":"CA",
    "sg:address":"163 Commercial St",
    "sg:city":"Nanaimo",
    "sg:classifiers":[
        {
            "category":"Travel",
            "subcategory":"Travel Agent",
            "type":"Entertainment"
        }
    ],
    "sg:phone":"+1 250 753 2282",
    "sg:postcode":"V9R 5G5",
    "sg:province":"BC",
    "sg:tags":[
        "agency",
        "bureau"
    ],
    "wof:name":"Around the World Travel Svc",
    "wof:placetype":"venue"
},
  "geometry": {"coordinates":[-123.937057495,49.1662101746],"type":"Point"}
}