{
  "type": "Feature",
  "properties": {
    "addr:full":"Three Hills AB T0M 2A0",
    "addr:postcode":"t0m 2a0",
    "iso:country":"CA",
    "sg:city":"Three Hills",
    "sg:classifiers":[
        {
            "category":"Organizations",
            "subcategory":"Professional Association",
            "type":"Services"
        }
    ],
    "sg:phone":"+1 403 443 5577",
    "sg:postcode":"T0M 2A0",
    "sg:province":"AB",
    "wof:name":"Mission Aviation Fellowship",
    "wof:placetype":"venue"
},
  "geometry": {"coordinates":[-113.25511932400001,51.7081985474],"type":"Point"}
}