{
  "type": "Feature",
  "properties": {
    "addr:full":"8160 120 St Surrey BC V3W 3N3",
    "addr:housenumber":"8160",
    "addr:postcode":"v3w 3n3",
    "addr:street":"120 St",
    "iso:country":"CA",
    "sg:address":"8160 120 St",
    "sg:city":"Surrey",
    "sg:classifiers":[
        {
            "category":"Home & Garden",
            "subcategory":"Building Materials",
            "type":"Retail Goods"
        }
    ],
    "sg:phone":"+1 604 543 8005",
    "sg:postcode":"V3W 3N3",
    "sg:province":"BC",
    "sg:tags":[
        "door"
    ],
    "wof:name":"Doors Galore",
    "wof:placetype":"venue"
},
  "geometry": {"coordinates":[-122.890167236,49.1516304016],"type":"Point"}
}