{
  "type": "Feature",
  "properties": {
    "addr:full":"401 Boul Labelle Rosemere QC J7A 3T2",
    "addr:housenumber":"401",
    "addr:postcode":"j7a 3t2",
    "addr:street":"Boul Labelle",
    "iso:country":"CA",
    "sg:address":"401 Boul Labelle",
    "sg:city":"Rosemere",
    "sg:classifiers":[
        {
            "category":"Food & Beverages",
            "subcategory":"Candy",
            "type":"Retail Goods"
        }
    ],
    "sg:phone":"+1 450 971 4224",
    "sg:postcode":"J7A 3T2",
    "sg:province":"QC",
    "sg:tags":[
        "confectionery"
    ],
    "wof:name":"Bonbonniere Sweet Factory",
    "wof:placetype":"venue"
},
  "geometry": {"coordinates":[-73.8170547485,45.6329040527],"type":"Point"}
}