{
  "type": "Feature",
  "properties": {
    "addr:full":"141 Bell Ave Essex ON N8M 3G8",
    "addr:housenumber":"141",
    "addr:postcode":"n8m 3g8",
    "addr:street":"Bell Ave",
    "iso:country":"CA",
    "sg:address":"141 Bell Ave",
    "sg:city":"Essex",
    "sg:classifiers":[
        {
            "category":"Manufacturing",
            "subcategory":"Tools & Machinery",
            "type":"Manufacturing & Wholesale Goods"
        }
    ],
    "sg:phone":"+1 519 776 6695",
    "sg:postcode":"N8M 3G8",
    "sg:province":"ON",
    "sg:tags":[
        "machine",
        "shop"
    ],
    "wof:name":"Glen Ross Tool Ltd",
    "wof:placetype":"venue"
},
  "geometry": {"coordinates":[-82.831924,42.175991],"type":"Point"}
}