{
  "type": "Feature",
  "properties": {
    "addr:full":"1691 Matheson Blvd Mississauga ON L4W 1S1",
    "addr:housenumber":"1691",
    "addr:postcode":"l4w 1s1",
    "addr:street":"Matheson Blvd",
    "iso:country":"CA",
    "sg:address":"1691 Matheson Blvd",
    "sg:city":"Mississauga",
    "sg:classifiers":[
        {
            "category":"Professional",
            "subcategory":"Business Services",
            "type":"Services"
        }
    ],
    "sg:phone":"+1 905 625 6301",
    "sg:postcode":"L4W 1S1",
    "sg:province":"ON",
    "sg:tags":[
        "packaging",
        "material"
    ],
    "wof:name":"Sonoco Flexible Packaging",
    "wof:placetype":"venue"
},
  "geometry": {"coordinates":[-79.62370300000001,43.640507],"type":"Point"}
}