{
  "type": "Feature",
  "properties": {
    "iso:country":"CA",
    "sg:address":"6799 Pacific Cir",
    "sg:city":"Mississauga",
    "sg:classifiers":[
        {
            "category":"Wholesale",
            "subcategory":"Plants",
            "type":"Manufacturing & Wholesale Goods"
        }
    ],
    "sg:phone":"+1 905 670 3111",
    "sg:postcode":"L5T 1S6",
    "sg:province":"ON",
    "sg:tags":[
        "florist"
    ],
    "wof:name":"Florimex Inc",
    "wof:placetype":"venue"
},
  "geometry": {"coordinates":[-79.68082427980001,43.6606178284],"type":"Point"}
}