{
  "type": "Feature",
  "properties": {
    "addr:full":"1862 Eglinton Ave W York ON M6E 2J4",
    "addr:housenumber":"1862",
    "addr:postcode":"m6e 2j4",
    "addr:street":"Eglinton Ave W",
    "iso:country":"CA",
    "sg:address":"1862 Eglinton Ave W",
    "sg:city":"York",
    "sg:classifiers":[
        {
            "category":"Professional",
            "subcategory":"Secretarial Services",
            "type":"Services"
        }
    ],
    "sg:phone":"+1 416 789 2485",
    "sg:postcode":"M6E 2J4",
    "sg:province":"ON",
    "sg:tags":[
        "proofreading",
        "reporting",
        "court"
    ],
    "wof:name":"Juanne Hemsol Communications",
    "wof:placetype":"venue"
},
  "geometry": {"coordinates":[-79.4513549805,43.6955223083],"type":"Point"}
}