{
  "type": "Feature",
  "properties": {
    "addr:full":"7333 Arkona Rd Arkona ON N0M 1B0",
    "addr:housenumber":"7333",
    "addr:postcode":"n0m 1b0",
    "addr:street":"Arkona Rd",
    "iso:country":"CA",
    "sg:address":"7333 Arkona Rd",
    "sg:city":"Arkona",
    "sg:classifiers":[
        {
            "category":"Home & Garden",
            "subcategory":"Household Appliances",
            "type":"Retail Goods"
        }
    ],
    "sg:phone":"+1 519 828 3274",
    "sg:postcode":"N0M 1B0",
    "sg:province":"ON",
    "wof:name":"Arkona Appliances Inc",
    "wof:placetype":"venue"
},
  "geometry": {"coordinates":[-81.83428192140001,43.0730552673],"type":"Point"}
}