{
  "type": "Feature",
  "properties": {
    "addr:full":"5 Third Ave N Yorkton SK S3N 1C1",
    "addr:housenumber":"5",
    "addr:postcode":"s3n 1c1",
    "addr:street":"Third Ave N",
    "iso:country":"CA",
    "sg:address":"5 Third Ave N",
    "sg:city":"Yorkton",
    "sg:classifiers":[
        {
            "category":"Restaurant",
            "type":"Food & Drink"
        }
    ],
    "sg:phone":"+1 306 783 3118",
    "sg:postcode":"S3N 1C1",
    "sg:province":"SK",
    "wof:name":"Mediterranean Restaurant",
    "wof:placetype":"venue"
},
  "geometry": {"coordinates":[-102.459755,51.21051],"type":"Point"}
}