{
  "type": "Feature",
  "properties": {
    "addr:full":"84 James St W Guelph ON N1G 1E6",
    "addr:housenumber":"84",
    "addr:postcode":"n1g 1e6",
    "addr:street":"James St W",
    "iso:country":"CA",
    "sg:address":"84 James St W",
    "sg:city":"Guelph",
    "sg:classifiers":[
        {
            "category":"Professional",
            "subcategory":"Management & Consulting",
            "type":"Services"
        }
    ],
    "sg:phone":"+1 519 836 0155",
    "sg:postcode":"N1G 1E6",
    "sg:province":"ON",
    "sg:tags":[
        "communications",
        "consultant"
    ],
    "wof:name":"Sandra Arthurs & Assoc Inc",
    "wof:placetype":"venue"
},
  "geometry": {"coordinates":[-80.243301,43.535202],"type":"Point"}
}