{
  "type": "Feature",
  "properties": {
    "addr:full":"Viking AB T0B 4N0",
    "addr:postcode":"t0b 4n0",
    "iso:country":"CA",
    "sg:city":"Viking",
    "sg:classifiers":[
        {
            "category":"Professional",
            "subcategory":"Accounting & Tax Preparation",
            "type":"Services"
        }
    ],
    "sg:phone":"+1 780 336 3540",
    "sg:postcode":"T0B 4N0",
    "sg:province":"AB",
    "sg:tags":[
        "accountant"
    ],
    "wof:name":"Wilde & CO",
    "wof:placetype":"venue"
},
  "geometry": {"coordinates":[-111.77862500000001,53.093552],"type":"Point"}
}