{
  "type": "Feature",
  "properties": {
    "addr:full":"19 3rd Ave E Vancouver BC V5T 1C5",
    "addr:housenumber":"19",
    "addr:postcode":"v5t 1c5",
    "addr:street":"3Rd Ave E",
    "iso:country":"CA",
    "sg:address":"19 3rd Ave E",
    "sg:city":"Vancouver",
    "sg:classifiers":[
        {
            "category":"Autos & Motor Vehicles",
            "subcategory":"Auto Supplies",
            "type":"Retail Goods"
        }
    ],
    "sg:phone":"+1 604 873 1903",
    "sg:postcode":"V5T 1C5",
    "sg:province":"BC",
    "sg:tags":[
        "automobile",
        "stereo",
        "radio",
        "system"
    ],
    "wof:name":"Comtect Industries Intl Ltd",
    "wof:placetype":"venue"
},
  "geometry": {"coordinates":[-123.104202,49.268433],"type":"Point"}
}