{
  "type": "Feature",
  "properties": {
    "iso:country":"CA",
    "sg:address":"436 Av Victoria",
    "sg:city":"Saint-Lambert",
    "sg:classifiers":[
        {
            "category":"Home & Garden",
            "subcategory":"Furniture",
            "type":"Retail Goods"
        }
    ],
    "sg:phone":"+1 450 465 8647",
    "sg:postcode":"J4P 2J4",
    "sg:province":"QC",
    "wof:name":"Basilieres Micheline Meubles",
    "wof:placetype":"venue"
},
  "geometry": {"coordinates":[-73.51221466059999,45.5019264221],"type":"Point"}
}