{
  "type": "Feature",
  "properties": {
    "addr:full":"Middle Arm Gb NL A0K 3R0",
    "addr:postcode":"a0k 3r0",
    "addr:street":"Middle Arm",
    "iso:country":"CA",
    "sg:city":"Middle Arm Gb",
    "sg:classifiers":[
        {
            "category":"Health Services",
            "subcategory":"Doctor",
            "type":"Services"
        }
    ],
    "sg:phone":"+1 709 252 2032",
    "sg:postcode":"A0K 3R0",
    "sg:province":"NL",
    "sg:tags":[
        "clinic"
    ],
    "wof:name":"Public Health Clinic",
    "wof:placetype":"venue"
},
  "geometry": {"coordinates":[-56.0895309448,49.7042312622],"type":"Point"}
}