{
  "type": "Feature",
  "properties": {
    "addr:full":"8 Pinefalls Dr Sheet Harbour NS B0J 3B0",
    "addr:housenumber":"8",
    "addr:postcode":"b0j 3b0",
    "addr:street":"Pinefalls Dr",
    "iso:country":"CA",
    "sg:address":"8 Pinefalls Dr",
    "sg:city":"Sheet Harbour",
    "sg:classifiers":[
        {
            "category":"Organizations",
            "subcategory":"Non-profit Organization",
            "type":"Services"
        }
    ],
    "sg:phone":"+1 902 885 2300",
    "sg:postcode":"B0J 3B0",
    "sg:province":"NS",
    "sg:tags":[
        "charitable",
        "institution"
    ],
    "wof:name":"Gerald Hardy Memorial Society",
    "wof:placetype":"venue"
},
  "geometry": {"coordinates":[-62.534767,44.925289],"type":"Point"}
}