{
  "type": "Feature",
  "properties": {
    "addr:full":"820 James Mckevitt Rd SW Calgary AB T2Y 2E7",
    "addr:housenumber":"820",
    "addr:postcode":"t2y 2e7",
    "addr:street":"James Mckevitt Rd Sw",
    "iso:country":"CA",
    "sg:address":"820 James Mckevitt Rd SW",
    "sg:city":"Calgary",
    "sg:classifiers":[
        {
            "category":"Recreation",
            "type":"Entertainment"
        }
    ],
    "sg:phone":"+1 403 256 1444",
    "sg:postcode":"T2Y 2E7",
    "sg:province":"AB",
    "sg:tags":[
        "course",
        "golf"
    ],
    "wof:name":"Shaw-Nee Slopes Golf Course",
    "wof:placetype":"venue"
},
  "geometry": {"coordinates":[-114.084602356,50.9215698242],"type":"Point"}
}