{
  "type": "Feature",
  "properties": {
    "addr:full":"31 Joseph Duggan Rd Toronto ON M4L 3X5",
    "addr:housenumber":"31",
    "addr:postcode":"m4l 3x5",
    "addr:street":"Joseph Duggan Rd",
    "iso:country":"CA",
    "sg:address":"31 Joseph Duggan Rd",
    "sg:city":"Toronto",
    "sg:classifiers":[
        {
            "category":"Professional",
            "subcategory":"Management & Consulting",
            "type":"Services"
        }
    ],
    "sg:phone":"+1 416 699 6494",
    "sg:postcode":"M4L 3X5",
    "sg:province":"ON",
    "sg:tags":[
        "consultant",
        "business"
    ],
    "wof:name":"Smith Knox & Assoc Inc",
    "wof:placetype":"venue"
},
  "geometry": {"coordinates":[-79.306755,43.665543],"type":"Point"}
}