{
  "type": "Feature",
  "properties": {
    "iso:country":"CA",
    "sg:city":"Mississauga",
    "sg:classifiers":[
        {
            "category":"Freight",
            "type":"Transportation"
        }
    ],
    "sg:phone":"+1 905 673 8798",
    "sg:postcode":"L5P 1C3",
    "sg:province":"ON",
    "sg:tags":[
        "broker",
        "customs"
    ],
    "wof:name":"Orbit Brokers & Forwarders Inc",
    "wof:placetype":"venue"
},
  "geometry": {"coordinates":[-79.629913,43.692299],"type":"Point"}
}