{
  "type": "Feature",
  "properties": {
    "addr:full":"2871 Dundas St W Toronto ON M6P 1Y9",
    "addr:housenumber":"2871",
    "addr:postcode":"m6p 1y9",
    "addr:street":"Dundas St W",
    "iso:country":"CA",
    "sg:address":"2871 Dundas St W",
    "sg:city":"Toronto",
    "sg:classifiers":[
        {
            "category":"Building & Trades",
            "subcategory":"Equipment Rental",
            "type":"Services"
        }
    ],
    "sg:phone":"+1 416 763 5631",
    "sg:postcode":"M6P 1Y9",
    "sg:province":"ON",
    "sg:tags":[
        "television",
        "radio"
    ],
    "wof:name":"Mister Television & Audio",
    "wof:placetype":"venue"
},
  "geometry": {"coordinates":[-79.465103,43.665272],"type":"Point"}
}