{
  "type": "Feature",
  "properties": {
    "addr:full":"6133 97 St NW Edmonton AB T6E 3J3",
    "addr:housenumber":"6133",
    "addr:postcode":"t6e 3j3",
    "addr:street":"97 St Nw",
    "iso:country":"CA",
    "sg:address":"6133 97 St NW",
    "sg:city":"Edmonton",
    "sg:classifiers":[
        {
            "category":"Manufacturing",
            "subcategory":"Metals",
            "type":"Manufacturing & Wholesale Goods"
        }
    ],
    "sg:phone":"+1 780 436 5353",
    "sg:postcode":"T6E 3J3",
    "sg:province":"AB",
    "sg:tags":[
        "valve"
    ],
    "wof:name":"D Valves Ltd",
    "wof:placetype":"venue"
},
  "geometry": {"coordinates":[-113.47914900000001,53.497543],"type":"Point"}
}