{
  "type": "Feature",
  "properties": {
    "iso:country":"CA",
    "sg:address":"3518 4th Ave W",
    "sg:city":"Vancouver",
    "sg:classifiers":[
        {
            "category":"Shopping",
            "subcategory":"Clothing, Apparel, & Fashions",
            "type":"Retail Goods"
        }
    ],
    "sg:phone":"+1 604 738 9798",
    "sg:postcode":"V6R 1N8",
    "sg:province":"BC",
    "wof:name":"Fun in the Sun",
    "wof:placetype":"venue"
},
  "geometry": {"coordinates":[-123.182098389,49.2684135437],"type":"Point"}
}