{
  "type": "Feature",
  "properties": {
    "addr:full":"193 Church St Toronto ON M5B 1Y7",
    "addr:housenumber":"193",
    "addr:postcode":"m5b 1y7",
    "addr:street":"Church St",
    "iso:country":"CA",
    "sg:address":"193 Church St",
    "sg:city":"Toronto",
    "sg:classifiers":[
        {
            "category":"Shopping",
            "subcategory":"Clothing, Apparel, & Fashions",
            "type":"Retail Goods"
        }
    ],
    "sg:phone":"+1 416 363 4868",
    "sg:postcode":"M5B 1Y7",
    "sg:province":"ON",
    "sg:tags":[
        "made",
        "shirt"
    ],
    "wof:name":"George Bouridis Custom Made",
    "wof:placetype":"venue"
},
  "geometry": {"coordinates":[-79.3764343262,43.6553115845],"type":"Point"}
}