{
  "type": "Feature",
  "properties": {
    "addr:full":"149 Rangoon Rd Etobicoke ON M9C 4P4",
    "addr:housenumber":"149",
    "addr:postcode":"m9c 4p4",
    "addr:street":"Rangoon Rd",
    "iso:country":"CA",
    "sg:address":"149 Rangoon Rd",
    "sg:city":"Etobicoke",
    "sg:classifiers":[
        {
            "category":"Building & Trades",
            "subcategory":"Electrical",
            "type":"Services"
        }
    ],
    "sg:phone":"+1 416 621 3920",
    "sg:postcode":"M9C 4P4",
    "sg:province":"ON",
    "sg:tags":[
        "electric",
        "contractor"
    ],
    "wof:name":"B & H Electric",
    "wof:placetype":"venue"
},
  "geometry": {"coordinates":[-79.577614,43.670132],"type":"Point"}
}