{
  "type": "Feature",
  "properties": {
    "addr:full":"Ponoka AB T4J 1R6",
    "addr:postcode":"t4j 1r6",
    "iso:country":"CA",
    "sg:city":"Ponoka",
    "sg:classifiers":[
        {
            "category":"Shopping",
            "subcategory":"Florist",
            "type":"Retail Goods"
        }
    ],
    "sg:phone":"+1 403 783 8190",
    "sg:postcode":"T4J 1R6",
    "sg:province":"AB",
    "wof:name":"Flowers For You",
    "wof:placetype":"venue"
},
  "geometry": {"coordinates":[-113.57590500000001,52.677132],"type":"Point"}
}