{
  "type": "Feature",
  "properties": {
    "addr:full":"290 3E Rang O Sainte-Louise QC G0R 3K0",
    "addr:housenumber":"290",
    "addr:postcode":"g0r 3k0",
    "addr:street":"3E Rang O",
    "iso:country":"CA",
    "sg:address":"290 3E Rang O",
    "sg:city":"Sainte-Louise",
    "sg:classifiers":[
        {
            "category":"Farming",
            "subcategory":"Livestock Farm",
            "type":"Manufacturing & Wholesale Goods"
        }
    ],
    "sg:phone":"+1 418 354 7731",
    "sg:postcode":"G0R 3K0",
    "sg:province":"QC",
    "sg:tags":[
        "circus",
        "broker",
        "animal",
        "dealer"
    ],
    "wof:name":"Claude Belanger Inc",
    "wof:placetype":"venue"
},
  "geometry": {"coordinates":[-72.9473724365,46.2556343079],"type":"Point"}
}