{
  "type": "Feature",
  "properties": {
    "addr:full":"Vars ON K0A 3H0",
    "addr:postcode":"k0a 3h0",
    "iso:country":"CA",
    "sg:city":"Vars",
    "sg:classifiers":[
        {
            "category":"Autos & Motor Vehicles",
            "subcategory":"Auto Supplies",
            "type":"Retail Goods"
        }
    ],
    "sg:phone":"+1 613 835 9884",
    "sg:postcode":"K0A 3H0",
    "sg:province":"ON",
    "sg:tags":[
        "equipment",
        "racing",
        "car",
        "automobile"
    ],
    "wof:name":"E Z Parts Trader",
    "wof:placetype":"venue"
},
  "geometry": {"coordinates":[-75.31117999999999,45.347103],"type":"Point"}
}