{
  "type": "Feature",
  "properties": {
    "addr:full":"1020 102nd Ave Hines Creek AB T0H 2A0",
    "addr:housenumber":"1020",
    "addr:postcode":"t0h 2a0",
    "addr:street":"102Nd Ave",
    "iso:country":"CA",
    "sg:address":"1020 102nd Ave",
    "sg:city":"Hines Creek",
    "sg:classifiers":[
        {
            "category":"Autos & Motor Vehicles",
            "subcategory":"Auto Supplies",
            "type":"Retail Goods"
        }
    ],
    "sg:phone":"+1 780 494 2545",
    "sg:postcode":"T0H 2A0",
    "sg:province":"AB",
    "sg:tags":[
        "automobile",
        "parts"
    ],
    "wof:name":"Hines Creek Part Mart",
    "wof:placetype":"venue"
},
  "geometry": {"coordinates":[-118.60226400000001,56.247372],"type":"Point"}
}