{
  "type": "Feature",
  "properties": {
    "iso:country":"CA",
    "sg:city":"Uxbridge",
    "sg:classifiers":[
        {
            "category":"Personal",
            "subcategory":"Beauty Salon",
            "type":"Services"
        }
    ],
    "sg:phone":"+1 905 852 7077",
    "sg:postcode":"L9P 1E5",
    "sg:province":"ON",
    "wof:name":"Moira's Hair Waves",
    "wof:placetype":"venue"
},
  "geometry": {"coordinates":[-79.1232452393,44.1095657349],"type":"Point"}
}