{
  "type": "Feature",
  "properties": {
    "addr:full":"4023 97 St NW Edmonton AB T6E 5Y5",
    "addr:housenumber":"4023",
    "addr:postcode":"t6e 5y5",
    "addr:street":"97 St Nw",
    "iso:country":"CA",
    "sg:address":"4023 97 St NW",
    "sg:city":"Edmonton",
    "sg:classifiers":[
        {
            "category":"Wholesale",
            "subcategory":"Machinery & Supplies",
            "type":"Manufacturing & Wholesale Goods"
        }
    ],
    "sg:phone":"+1 780 437 5518",
    "sg:postcode":"T6E 5Y5",
    "sg:province":"AB",
    "sg:tags":[
        "salon",
        "beauty"
    ],
    "wof:name":"Monarch Beauty Supply CO",
    "wof:placetype":"venue"
},
  "geometry": {"coordinates":[-113.47920227,53.4755020142],"type":"Point"}
}