{
  "type": "Feature",
  "properties": {
    "addr:full":"3833 Nashua Dr Mississauga ON L4V 1R3",
    "addr:housenumber":"3833",
    "addr:postcode":"l4v 1r3",
    "addr:street":"Nashua Dr",
    "iso:country":"CA",
    "sg:address":"3833 Nashua Dr",
    "sg:city":"Mississauga",
    "sg:classifiers":[
        {
            "category":"Wholesale",
            "subcategory":"Auto Parts",
            "type":"Manufacturing & Wholesale Goods"
        }
    ],
    "sg:phone":"+1 905 677 3522",
    "sg:postcode":"L4V 1R3",
    "sg:province":"ON",
    "sg:tags":[
        "equipment",
        "truck"
    ],
    "wof:name":"Canada Powertrain",
    "wof:placetype":"venue"
},
  "geometry": {"coordinates":[-79.62061309809999,43.7149353027],"type":"Point"}
}