{
  "type": "Feature",
  "properties": {
    "addr:full":"767 Rue Notre Dame Embrun ON K0A 1W1",
    "addr:housenumber":"767",
    "addr:postcode":"k0a 1w1",
    "addr:street":"Rue Notre Dame",
    "iso:country":"CA",
    "sg:address":"767 Rue Notre Dame",
    "sg:city":"Embrun",
    "sg:classifiers":[
        {
            "category":"Wholesale",
            "subcategory":"Meat",
            "type":"Manufacturing & Wholesale Goods"
        }
    ],
    "sg:phone":"+1 613 443 2755",
    "sg:postcode":"K0A 1W1",
    "sg:province":"ON",
    "sg:tags":[
        "butchering"
    ],
    "wof:name":"Denis' Gourmet Meats",
    "wof:placetype":"venue"
},
  "geometry": {"coordinates":[-75.3016738892,45.267578125],"type":"Point"}
}