{
  "type": "Feature",
  "properties": {
    "iso:country":"CA",
    "sg:address":"2756 16th Ave W",
    "sg:city":"Vancouver",
    "sg:classifiers":[
        {
            "category":"Organizations",
            "subcategory":"Religious Organization",
            "type":"Services"
        }
    ],
    "sg:phone":"+1 604 733 0915",
    "sg:postcode":"V6K 3C4",
    "sg:province":"BC",
    "sg:tags":[
        "church"
    ],
    "wof:name":"Sixteenth Avenue Gospel Chapel",
    "wof:placetype":"venue"
},
  "geometry": {"coordinates":[-123.166908264,49.257434845],"type":"Point"}
}