{
  "type": "Feature",
  "properties": {
    "addr:full":"890 Mckeown Ave North Bay ON P1B 8M1",
    "addr:housenumber":"890",
    "addr:postcode":"p1b 8m1",
    "addr:street":"Mckeown Ave",
    "iso:country":"CA",
    "sg:address":"890 Mckeown Ave",
    "sg:city":"North Bay",
    "sg:classifiers":[
        {
            "category":"Autos & Motor Vehicles",
            "subcategory":"Auto Supplies",
            "type":"Retail Goods"
        }
    ],
    "sg:phone":"+1 705 472 3000",
    "sg:postcode":"P1B 8M1",
    "sg:province":"ON",
    "sg:tags":[
        "hardware",
        "automobile",
        "parts"
    ],
    "wof:name":"Canadian Tire",
    "wof:placetype":"venue"
},
  "geometry": {"coordinates":[-79.471954,46.332775],"type":"Point"}
}