{
  "type": "Feature",
  "properties": {
    "addr:full":"1945 Labonte Clarence Creek ON K0A 1N0",
    "addr:housenumber":"1945",
    "addr:postcode":"k0a 1n0",
    "addr:street":"Labonte Clarence",
    "iso:country":"CA",
    "sg:address":"1945 Labonte",
    "sg:city":"Clarence Creek",
    "sg:classifiers":[
        {
            "category":"Health Services",
            "subcategory":"Health Practitioner",
            "type":"Services"
        }
    ],
    "sg:phone":"+1 613 488 3753",
    "sg:postcode":"K0A 1N0",
    "sg:province":"ON",
    "sg:tags":[
        "physiotherapist"
    ],
    "wof:name":"Physiotherapie Clarence Creek",
    "wof:placetype":"venue"
},
  "geometry": {"coordinates":[-75.214432,45.508026],"type":"Point"}
}