{
  "type": "Feature",
  "properties": {
    "addr:full":"Grenville QC J0V 1J0",
    "addr:postcode":"j0v 1j0",
    "iso:country":"CA",
    "sg:city":"Grenville",
    "sg:classifiers":[
        {
            "category":"Manufacturing",
            "subcategory":"Apparel",
            "type":"Manufacturing & Wholesale Goods"
        }
    ],
    "sg:phone":"+1 819 242 9703",
    "sg:postcode":"J0V 1J0",
    "sg:province":"QC",
    "sg:tags":[
        "sewing",
        "contractor"
    ],
    "wof:name":"Confections R-M Enrg",
    "wof:placetype":"venue"
},
  "geometry": {"coordinates":[-74.59279600000001,45.624218],"type":"Point"}
}