{
  "type": "Feature",
  "properties": {
    "addr:full":"6740 Boul Joseph-Renaud Anjou QC H1K 3V4",
    "addr:housenumber":"6740",
    "addr:postcode":"h1k 3v4",
    "addr:street":"Boul Joseph-Renaud",
    "iso:country":"CA",
    "sg:address":"6740 Boul Joseph-Renaud",
    "sg:city":"Anjou",
    "sg:classifiers":[
        {
            "category":"Restaurant",
            "type":"Food & Drink"
        }
    ],
    "sg:phone":"+1 514 352 6440",
    "sg:postcode":"H1K 3V4",
    "sg:province":"QC",
    "wof:name":"Restaurant Memphis",
    "wof:placetype":"venue"
},
  "geometry": {"coordinates":[-73.552368,45.605087],"type":"Point"}
}