{
  "type": "Feature",
  "properties": {
    "addr:full":"468 Rue Des Sarcelles Rimouski QC G5N 1E1",
    "addr:housenumber":"468",
    "addr:postcode":"g5n 1e1",
    "addr:street":"Rue Des Sarcelles",
    "iso:country":"CA",
    "sg:address":"468 Rue Des Sarcelles",
    "sg:city":"Rimouski",
    "sg:classifiers":[
        {
            "category":"Professional",
            "subcategory":"Accounting & Tax Preparation",
            "type":"Services"
        }
    ],
    "sg:phone":"+1 418 722 6166",
    "sg:postcode":"G5N 1E1",
    "sg:province":"QC",
    "sg:tags":[
        "accountant",
        "return",
        "filing"
    ],
    "wof:name":"Admico Enr",
    "wof:placetype":"venue"
},
  "geometry": {"coordinates":[-68.5301742554,48.4276161194],"type":"Point"}
}