{
  "type": "Feature",
  "properties": {
    "addr:full":"5 Terry Fox Dr Kingston ON K7K 6Y7",
    "addr:housenumber":"5",
    "addr:postcode":"k7k 6y7",
    "addr:street":"Terry Fox Dr",
    "iso:country":"CA",
    "sg:address":"5 Terry Fox Dr",
    "sg:city":"Kingston",
    "sg:classifiers":[
        {
            "category":"Building & Trades",
            "subcategory":"Construction",
            "type":"Services"
        }
    ],
    "sg:phone":"+1 613 546 2075",
    "sg:postcode":"K7K 6Y7",
    "sg:province":"ON",
    "sg:tags":[
        "insulation",
        "heat",
        "contractor"
    ],
    "wof:name":"Top Value Insulation Inc",
    "wof:placetype":"venue"
},
  "geometry": {"coordinates":[-76.5172576904,44.2615356445],"type":"Point"}
}