{
  "type": "Feature",
  "properties": {
    "addr:full":"249 Mcintyre St Thunder Bay ON P7A 3B3",
    "addr:housenumber":"249",
    "addr:postcode":"p7a 3b3",
    "addr:street":"Mcintyre St",
    "iso:country":"CA",
    "sg:address":"249 Mcintyre St",
    "sg:city":"Thunder Bay",
    "sg:classifiers":[
        {
            "category":"Building & Trades",
            "subcategory":"Construction",
            "type":"Services"
        }
    ],
    "sg:phone":"+1 807 345 3067",
    "sg:postcode":"P7A 3B3",
    "sg:province":"ON",
    "sg:tags":[
        "general",
        "contractor"
    ],
    "wof:name":"Sam Construction",
    "wof:placetype":"venue"
},
  "geometry": {"coordinates":[-89.210297,48.444103],"type":"Point"}
}