{
  "type": "Feature",
  "properties": {
    "addr:full":"Jasper AB T0E 1E0",
    "addr:postcode":"t0e 1e0",
    "iso:country":"CA",
    "sg:city":"Jasper",
    "sg:classifiers":[
        {
            "category":"Travel",
            "subcategory":"Hotels & Motels",
            "type":"Entertainment"
        }
    ],
    "sg:phone":"+1 780 852 3285",
    "sg:postcode":"T0E 1E0",
    "sg:province":"AB",
    "wof:name":"Alpine Village",
    "wof:placetype":"venue"
},
  "geometry": {"coordinates":[-118.091079712,52.8644256592],"type":"Point"}
}