{
  "type": "Feature",
  "properties": {
    "addr:full":"801 Progress Ave Scarborough ON M1H 2X4",
    "addr:housenumber":"801",
    "addr:postcode":"m1h 2x4",
    "addr:street":"Progress Ave",
    "iso:country":"CA",
    "sg:address":"801 Progress Ave",
    "sg:city":"Scarborough",
    "sg:classifiers":[
        {
            "category":"Organizations",
            "subcategory":"Religious Organization",
            "type":"Services"
        }
    ],
    "sg:phone":"+1 416 289 1463",
    "sg:postcode":"M1H 2X4",
    "sg:province":"ON",
    "sg:tags":[
        "church"
    ],
    "wof:name":"Grace Apostolic Church",
    "wof:placetype":"venue"
},
  "geometry": {"coordinates":[-79.2432479858,43.7801704407],"type":"Point"}
}