{
  "type": "Feature",
  "properties": {
    "iso:country":"CA",
    "sg:address":"300 Rue DE LA Berge-Du-Canal",
    "sg:city":"Lachine",
    "sg:classifiers":[
        {
            "category":"Manufacturing",
            "subcategory":"Furniture",
            "type":"Manufacturing & Wholesale Goods"
        }
    ],
    "sg:phone":"+1 514 363 1573",
    "sg:postcode":"H8R 1H3",
    "sg:province":"QC",
    "wof:name":"Bedros Furniture Inc",
    "wof:placetype":"venue"
},
  "geometry": {"coordinates":[-73.644913,45.442432],"type":"Point"}
}