{
  "type": "Feature",
  "properties": {
    "iso:country":"CA",
    "sg:address":"729 Erbsville Rd",
    "sg:city":"Waterloo",
    "sg:classifiers":[
        {
            "category":"Building & Trades",
            "subcategory":"Electrical",
            "type":"Services"
        }
    ],
    "sg:phone":"+1 519 746 2022",
    "sg:postcode":"N2J 3Z4",
    "sg:province":"ON",
    "sg:tags":[
        "electric",
        "contractor"
    ],
    "wof:name":"Erbsville Electrical Contrs",
    "wof:placetype":"venue"
},
  "geometry": {"coordinates":[-80.6041564941,43.4802780151],"type":"Point"}
}