{
  "type": "Feature",
  "properties": {
    "addr:full":"7950 Boul Saint-Michel Montreal QC H1Z 3E1",
    "addr:housenumber":"7950",
    "addr:postcode":"h1z 3e1",
    "addr:street":"Boul Saint-Michel",
    "iso:country":"CA",
    "sg:address":"7950 Boul Saint-Michel",
    "sg:city":"Montreal",
    "sg:classifiers":[
        {
            "category":"Social Services",
            "type":"Services"
        }
    ],
    "sg:phone":"+1 514 374 8223",
    "sg:postcode":"H1Z 3E1",
    "sg:province":"QC",
    "sg:tags":[
        "organization",
        "welfare"
    ],
    "wof:name":"Clsc St-Michel",
    "wof:placetype":"venue"
},
  "geometry": {"coordinates":[-73.6080856323,45.5628662109],"type":"Point"}
}