{
  "type": "Feature",
  "properties": {
    "iso:country":"CA",
    "sg:address":"53251 Range Road 232",
    "sg:city":"Sherwood Park",
    "sg:classifiers":[
        {
            "category":"Building & Trades",
            "subcategory":"Plumbing",
            "type":"Services"
        }
    ],
    "sg:phone":"+1 780 449 5111",
    "sg:postcode":"T8A 4V2",
    "sg:province":"AB",
    "sg:tags":[
        "fabricator",
        "mechanical",
        "metal",
        "contractor"
    ],
    "wof:name":"Aecon Industrial",
    "wof:placetype":"venue"
},
  "geometry": {"coordinates":[-113.29557,53.510151],"type":"Point"}
}