{
  "type": "Feature",
  "properties": {
    "addr:full":"10 2nd Ave NW Dauphin MB R7N 1H2",
    "addr:housenumber":"10",
    "addr:postcode":"dauphin;r7n 1h2",
    "addr:street":"2Nd Ave Nw",
    "iso:country":"CA",
    "sg:address":"10 2nd Ave NW",
    "sg:city":"Dauphin",
    "sg:classifiers":[
        {
            "category":"Health Services",
            "subcategory":"Doctor",
            "type":"Services"
        }
    ],
    "sg:phone":"+1 204 638 9312",
    "sg:postcode":"R7N 1H2",
    "sg:province":"MB",
    "sg:tags":[
        "dentist"
    ],
    "wof:name":"Dauphin Dental Clinic",
    "wof:placetype":"venue"
},
  "geometry": {"coordinates":[-100.049187,51.150715],"type":"Point"}
}