{
  "type": "Feature",
  "properties": {
    "addr:full":"Bamfield BC V0R 1B0",
    "addr:postcode":"v0r 1b0",
    "iso:country":"CA",
    "sg:city":"Bamfield",
    "sg:classifiers":[
        {
            "category":"Travel",
            "subcategory":"Hotels & Motels",
            "type":"Entertainment"
        }
    ],
    "sg:phone":"+1 250 728 3500",
    "sg:postcode":"V0R 1B0",
    "sg:province":"BC",
    "sg:tags":[
        "resort"
    ],
    "wof:name":"Broken Island Adventures Ltd",
    "wof:placetype":"venue"
},
  "geometry": {"coordinates":[-125.134743,48.819839],"type":"Point"}
}