{
  "type": "Feature",
  "properties": {
    "addr:full":"156 Pender St E Vancouver BC V6A 1T3",
    "addr:housenumber":"156",
    "addr:postcode":"v6a 1t3",
    "addr:street":"Pender St E",
    "iso:country":"CA",
    "sg:address":"156 Pender St E",
    "sg:city":"Vancouver",
    "sg:classifiers":[
        {
            "category":"Shopping",
            "subcategory":"Gifts & Souvenirs",
            "type":"Retail Goods"
        }
    ],
    "sg:phone":"+1 604 893 8628",
    "sg:postcode":"V6A 1T3",
    "sg:province":"BC",
    "sg:tags":[
        "shop"
    ],
    "wof:name":"Easy Time Import Export Inc",
    "wof:placetype":"venue"
},
  "geometry": {"coordinates":[-123.100845337,49.2802696228],"type":"Point"}
}