{
  "type": "Feature",
  "properties": {
    "addr:full":"15 Riverside Dr Kapuskasing ON P5N 1A4",
    "addr:housenumber":"15",
    "addr:postcode":"p5n 1a4",
    "addr:street":"Riverside Dr",
    "iso:country":"CA",
    "sg:address":"15 Riverside Dr",
    "sg:city":"Kapuskasing",
    "sg:classifiers":[
        {
            "category":"Wholesale",
            "subcategory":"Auto Parts",
            "type":"Manufacturing & Wholesale Goods"
        }
    ],
    "sg:phone":"+1 705 335 6076",
    "sg:postcode":"P5N 1A4",
    "sg:province":"ON",
    "sg:tags":[
        "automobile",
        "supply"
    ],
    "wof:name":"Timmins Automotive CO Ltd",
    "wof:placetype":"venue"
},
  "geometry": {"coordinates":[-82.42102050779999,49.4140472412],"type":"Point"}
}