{
  "type": "Feature",
  "properties": {
    "addr:full":"26899 Old Yale Rd Aldergrove BC V4W 3E4",
    "addr:housenumber":"26899",
    "addr:postcode":"v4w 3e4",
    "addr:street":"Old Yale Rd",
    "iso:country":"CA",
    "sg:address":"26899 Old Yale Rd",
    "sg:city":"Aldergrove",
    "sg:classifiers":[
        {
            "category":"Wholesale",
            "subcategory":"Machinery & Supplies",
            "type":"Manufacturing & Wholesale Goods"
        }
    ],
    "sg:phone":"+1 604 856 4010",
    "sg:postcode":"V4W 3E4",
    "sg:province":"BC",
    "sg:tags":[
        "farm",
        "equipment"
    ],
    "wof:name":"Rowterra Distributors Ltd",
    "wof:placetype":"venue"
},
  "geometry": {"coordinates":[-122.47914900000001,49.059277],"type":"Point"}
}