{
  "type": "Feature",
  "properties": {
    "iso:country":"CA",
    "sg:city":"Barrie",
    "sg:classifiers":[
        {
            "category":"Education",
            "subcategory":"Dance Studio",
            "type":"Public Place"
        }
    ],
    "sg:phone":"+1 705 721 1330",
    "sg:postcode":"L4M 5J1",
    "sg:province":"ON",
    "sg:tags":[
        "instruction",
        "dancing"
    ],
    "wof:name":"LA Ronde Dance Academy",
    "wof:placetype":"venue"
},
  "geometry": {"coordinates":[-79.684822,44.408131],"type":"Point"}
}