{
  "type": "Feature",
  "properties": {
    "iso:country":"CA",
    "sg:address":"4237 Blenkinsop Rd",
    "sg:city":"Victoria",
    "sg:classifiers":[
        {
            "category":"Sports & Exercise",
            "subcategory":"Golf",
            "type":"Entertainment"
        }
    ],
    "sg:phone":"+1 250 721 2001",
    "sg:postcode":"V8X 2C3",
    "sg:province":"BC",
    "sg:tags":[
        "range",
        "practice"
    ],
    "wof:name":"Blenkinsop Valley Golf Ctr",
    "wof:placetype":"venue"
},
  "geometry": {"coordinates":[-123.364517212,48.428314209],"type":"Point"}
}