{
  "type": "Feature",
  "properties": {
    "addr:full":"Montreal QC H3B 1P5",
    "addr:postcode":"h3b 1p5",
    "iso:country":"CA",
    "sg:city":"Montreal",
    "sg:classifiers":[
        {
            "category":"Banks & Credit Unions",
            "subcategory":"Investment Brokerage",
            "type":"Services"
        }
    ],
    "sg:phone":"+1 514 879 1702",
    "sg:postcode":"H3B 1P5",
    "sg:province":"QC",
    "wof:name":"Demers Conseil Inc",
    "wof:placetype":"venue"
},
  "geometry": {"coordinates":[-73.56697800000001,45.502811],"type":"Point"}
}