{
  "type": "Feature",
  "properties": {
    "addr:full":"114 Broad St Cut Knife SK S0M 0N0",
    "addr:housenumber":"114",
    "addr:postcode":"s0m 0n0",
    "addr:street":"Broad St",
    "iso:country":"CA",
    "sg:address":"114 Broad St",
    "sg:city":"Cut Knife",
    "sg:classifiers":[
        {
            "category":"Banks & Credit Unions",
            "subcategory":"Bank",
            "type":"Services"
        }
    ],
    "sg:phone":"+1 306 398 4983",
    "sg:postcode":"S0M 0N0",
    "sg:province":"SK",
    "wof:name":"Royal Bank Financial Group",
    "wof:placetype":"venue"
},
  "geometry": {"coordinates":[-109.02076700000001,52.74321],"type":"Point"}
}