{
  "type": "Feature",
  "properties": {
    "addr:full":"12246 Rue Grenet Montreal QC H4J 2J8",
    "addr:housenumber":"12246",
    "addr:postcode":"h4j 2j8",
    "addr:street":"Rue Grenet",
    "iso:country":"CA",
    "sg:address":"12246 Rue Grenet",
    "sg:city":"Montreal",
    "sg:classifiers":[
        {
            "category":"Retail",
            "subcategory":"Portrait Studio",
            "type":"Services"
        }
    ],
    "sg:phone":"+1 514 844 5464",
    "sg:postcode":"H4J 2J8",
    "sg:province":"QC",
    "sg:tags":[
        "photographer"
    ],
    "wof:name":"Service DE Photographie",
    "wof:placetype":"venue"
},
  "geometry": {"coordinates":[-73.71928405760001,45.5315132141],"type":"Point"}
}