{
  "type": "Feature",
  "properties": {
    "addr:full":"2139 Kensington Rd NW Calgary AB T2N 3R8",
    "addr:housenumber":"2139",
    "addr:postcode":"t2n 3r8",
    "addr:street":"Kensington Rd Nw",
    "iso:country":"CA",
    "sg:address":"2139 Kensington Rd NW",
    "sg:city":"Calgary",
    "sg:classifiers":[
        {
            "category":"Food & Beverages",
            "subcategory":"Groceries & Convenience Stores",
            "type":"Retail Goods"
        }
    ],
    "sg:phone":"+1 403 270 0889",
    "sg:postcode":"T2N 3R8",
    "sg:province":"AB",
    "wof:name":"Daylight Grocery",
    "wof:placetype":"venue"
},
  "geometry": {"coordinates":[-114.10900100000001,51.052357],"type":"Point"}
}