{
  "type": "Feature",
  "properties": {
    "addr:full":"2345 Island Hwy E Nanoose Bay BC V9P 9E2",
    "addr:housenumber":"2345",
    "addr:postcode":"v9p 9e2",
    "addr:street":"Island Hwy E",
    "iso:country":"CA",
    "sg:address":"2345 Island Hwy E",
    "sg:city":"Nanoose Bay",
    "sg:classifiers":[
        {
            "category":"Autos & Motor Vehicles",
            "subcategory":"Fuel & Gas Station",
            "type":"Retail Goods"
        }
    ],
    "sg:phone":"+1 250 468 7441",
    "sg:postcode":"V9P 9E2",
    "sg:province":"BC",
    "sg:tags":[
        "oil"
    ],
    "wof:name":"Nanoose Petro-Canada",
    "wof:placetype":"venue"
},
  "geometry": {"coordinates":[-124.197715759,49.2629241943],"type":"Point"}
}