{
  "type": "Feature",
  "properties": {
    "addr:full":"6250 Boul Wilfrid-Hamel L'Ancienne-Lorette QC G2E 2H8",
    "addr:housenumber":"6250",
    "addr:postcode":"g2e 2h8",
    "addr:street":"Boul Wilfrid-Hamel",
    "iso:country":"CA",
    "sg:address":"6250 Boul Wilfrid-Hamel",
    "sg:city":"L'Ancienne-Lorette",
    "sg:classifiers":[
        {
            "category":"Retail",
            "subcategory":"Auto Repair",
            "type":"Services"
        }
    ],
    "sg:phone":"+1 418 871 1471",
    "sg:postcode":"G2E 2H8",
    "sg:province":"QC",
    "sg:tags":[
        "repairing",
        "tire"
    ],
    "wof:name":"Capitale Bandag Inc",
    "wof:placetype":"venue"
},
  "geometry": {"coordinates":[-71.346397,46.797295],"type":"Point"}
}