{
  "type": "Feature",
  "properties": {
    "addr:full":"271 Rosetown Ave Penticton BC V2A 3J3",
    "addr:housenumber":"271",
    "addr:postcode":"v2a 3j3",
    "addr:street":"Rosetown Ave",
    "iso:country":"CA",
    "sg:address":"271 Rosetown Ave",
    "sg:city":"Penticton",
    "sg:classifiers":[
        {
            "category":"Autos & Motor Vehicles",
            "subcategory":"Auto Supplies",
            "type":"Retail Goods"
        }
    ],
    "sg:phone":"+1 250 492 6000",
    "sg:postcode":"V2A 3J3",
    "sg:province":"BC",
    "sg:tags":[
        "repairing",
        "automobile"
    ],
    "wof:name":"Big O Tires",
    "wof:placetype":"venue"
},
  "geometry": {"coordinates":[-119.579262,49.479473],"type":"Point"}
}