{
  "type": "Feature",
  "properties": {
    "addr:full":"38 Scott St W St Catharines ON L2R 1C9",
    "addr:housenumber":"38",
    "addr:postcode":"l2r 1c9",
    "addr:street":"Scott St W",
    "iso:country":"CA",
    "sg:address":"38 Scott St W",
    "sg:city":"St Catharines",
    "sg:classifiers":[
        {
            "category":"Education",
            "subcategory":"Special Training",
            "type":"Public Place"
        }
    ],
    "sg:phone":"+1 905 685 3141",
    "sg:postcode":"L2R 1C9",
    "sg:province":"ON",
    "sg:tags":[
        "instruction",
        "music"
    ],
    "wof:name":"John Lummen School of Music",
    "wof:placetype":"venue"
},
  "geometry": {"coordinates":[-79.26346588129999,43.1764450073],"type":"Point"}
}