{
  "type": "Feature",
  "properties": {
    "addr:full":"600 Hargrave St Thunder Bay ON P7C 2X7",
    "addr:housenumber":"600",
    "addr:postcode":"p7c 2x7",
    "addr:street":"Hargrave St",
    "iso:country":"CA",
    "sg:address":"600 Hargrave St",
    "sg:city":"Thunder Bay",
    "sg:classifiers":[
        {
            "category":"Retail",
            "subcategory":"Repair Shop",
            "type":"Services"
        }
    ],
    "sg:phone":"+1 807 622 9313",
    "sg:postcode":"P7C 2X7",
    "sg:province":"ON",
    "sg:tags":[
        "upholsterer"
    ],
    "wof:name":"East End Upholstery",
    "wof:placetype":"venue"
},
  "geometry": {"coordinates":[-89.226067,48.394306],"type":"Point"}
}