{
  "type": "Feature",
  "properties": {
    "addr:full":"Estevan SK S4A 2B4",
    "addr:postcode":"s4a 2b4",
    "iso:country":"CA",
    "sg:city":"Estevan",
    "sg:classifiers":[
        {
            "category":"Shopping",
            "type":"Retail Goods"
        }
    ],
    "sg:phone":"+1 306 636 1555",
    "sg:postcode":"S4A 2B4",
    "sg:province":"SK",
    "sg:tags":[
        "cosmetic",
        "perfume"
    ],
    "wof:name":"Merle Norman Cosmetics",
    "wof:placetype":"venue"
},
  "geometry": {"coordinates":[-102.976677,49.146629],"type":"Point"}
}