{
  "type": "Feature",
  "properties": {
    "addr:full":"2868 Place Davis Jonquiere QC G7S 2C5",
    "addr:housenumber":"2868",
    "addr:postcode":"g7s 2c5",
    "addr:street":"Place Davis",
    "iso:country":"CA",
    "sg:address":"2868 Place Davis",
    "sg:city":"Jonquiere",
    "sg:classifiers":[
        {
            "category":"Personal",
            "subcategory":"Beauty Salon",
            "type":"Services"
        }
    ],
    "sg:phone":"+1 418 548 2202",
    "sg:postcode":"G7S 2C5",
    "sg:province":"QC",
    "wof:name":"Salon Au Carre",
    "wof:placetype":"venue"
},
  "geometry": {"coordinates":[-71.182472,48.426083],"type":"Point"}
}