{
  "type": "Feature",
  "properties": {
    "addr:full":"4950 Yonge St North York ON M2N 6K1",
    "addr:housenumber":"4950",
    "addr:postcode":"m2n 6k1",
    "addr:street":"Yonge St",
    "iso:country":"CA",
    "sg:address":"4950 Yonge St",
    "sg:city":"North York",
    "sg:classifiers":[
        {
            "category":"Retail",
            "subcategory":"Car Wash",
            "type":"Services"
        }
    ],
    "sg:phone":"+1 416 733 4694",
    "sg:postcode":"M2N 6K1",
    "sg:province":"ON",
    "sg:tags":[
        "polishing",
        "washing"
    ],
    "wof:name":"Madison Auto Groom",
    "wof:placetype":"venue"
},
  "geometry": {"coordinates":[-79.4120025635,43.7649803162],"type":"Point"}
}