{
  "type": "Feature",
  "properties": {
    "addr:full":"303 York St Sudbury ON P3E 2A5",
    "addr:housenumber":"303",
    "addr:postcode":"p3e 2a5",
    "addr:street":"York St",
    "iso:country":"CA",
    "sg:address":"303 York St",
    "sg:city":"Sudbury",
    "sg:classifiers":[
        {
            "category":"Social Services",
            "type":"Services"
        }
    ],
    "sg:phone":"+1 705 671 9888",
    "sg:postcode":"P3E 2A5",
    "sg:province":"ON",
    "sg:tags":[
        "organization",
        "welfare"
    ],
    "wof:name":"Child Find Ontario",
    "wof:placetype":"venue"
},
  "geometry": {"coordinates":[-81.00619500000001,46.475395],"type":"Point"}
}