{
  "type": "Feature",
  "properties": {
    "addr:full":"397 Ch Larocque Salaberry-DE-Valleyfield QC J6T 4C4",
    "addr:housenumber":"397",
    "addr:postcode":"j6t 4c4",
    "addr:street":"Ch Larocque",
    "iso:country":"CA",
    "sg:address":"397 Ch Larocque",
    "sg:city":"Salaberry-DE-Valleyfield",
    "sg:classifiers":[
        {
            "category":"Retail",
            "subcategory":"Auto Repair",
            "type":"Services"
        }
    ],
    "sg:phone":"+1 450 373 0772",
    "sg:postcode":"J6T 4C4",
    "sg:province":"QC",
    "sg:tags":[
        "repairing",
        "automobile",
        "radiator"
    ],
    "wof:name":"L Martel Radiateur",
    "wof:placetype":"venue"
},
  "geometry": {"coordinates":[-74.1263580322,45.2425956726],"type":"Point"}
}