{
  "type": "Feature",
  "properties": {
    "iso:country":"CA",
    "sg:address":"1529 Ch DE LA Riviere-Croche",
    "sg:city":"LA Tuque",
    "sg:classifiers":[
        {
            "category":"Bars & Pubs",
            "type":"Food & Drink"
        }
    ],
    "sg:phone":"+1 819 523 3663",
    "sg:postcode":"G9X 3N7",
    "sg:province":"QC",
    "sg:tags":[
        "lounge",
        "cocktail"
    ],
    "wof:name":"Club LA Tuquois Inc",
    "wof:placetype":"venue"
},
  "geometry": {"coordinates":[-72.7631454468,47.5111885071],"type":"Point"}
}