{
  "type": "Feature",
  "properties": {
    "addr:full":"400 Skeena Dr Mackenzie BC V0J 2C0",
    "addr:housenumber":"400",
    "addr:postcode":"v0j 2c0",
    "addr:street":"Skeena Dr",
    "iso:country":"CA",
    "sg:address":"400 Skeena Dr",
    "sg:city":"Mackenzie",
    "sg:classifiers":[
        {
            "category":"Recreation",
            "type":"Entertainment"
        }
    ],
    "sg:phone":"+1 250 997 5283",
    "sg:postcode":"V0J 2C0",
    "sg:province":"BC",
    "sg:tags":[
        "center"
    ],
    "wof:name":"Mac Kenzie Recreation Complex",
    "wof:placetype":"venue"
},
  "geometry": {"coordinates":[-123.09098053,55.3384437561],"type":"Point"}
}