{
  "type": "Feature",
  "properties": {
    "addr:full":"221 Phillip St Tignish PE C0B 2B0",
    "addr:housenumber":"221",
    "addr:postcode":"c0b 2b0",
    "addr:street":"Phillip St",
    "iso:country":"CA",
    "sg:address":"221 Phillip St",
    "sg:city":"Tignish",
    "sg:classifiers":[
        {
            "category":"Bars & Pubs",
            "type":"Food & Drink"
        }
    ],
    "sg:phone":"+1 902 882 2011",
    "sg:postcode":"C0B 2B0",
    "sg:province":"PE",
    "sg:tags":[
        "lounge",
        "association",
        "cocktail"
    ],
    "wof:name":"Royal Canadian Legion Br 6",
    "wof:placetype":"venue"
},
  "geometry": {"coordinates":[-64.03583500000001,46.949287],"type":"Point"}
}