{
  "type": "Feature",
  "properties": {
    "addr:full":"North York ON M6A 2C1",
    "addr:postcode":"m6a 2c1",
    "iso:country":"CA",
    "sg:city":"North York",
    "sg:classifiers":[
        {
            "category":"Personal",
            "subcategory":"Beauty Salon",
            "type":"Services"
        }
    ],
    "sg:phone":"+1 416 787 6900",
    "sg:postcode":"M6A 2C1",
    "sg:province":"ON",
    "wof:name":"Heart of Nails",
    "wof:placetype":"venue"
},
  "geometry": {"coordinates":[-79.4313201904,43.7267341614],"type":"Point"}
}