{
  "type": "Feature",
  "properties": {
    "iso:country":"CA",
    "sg:address":"121 Avenue Rd",
    "sg:city":"Cambridge",
    "sg:classifiers":[
        {
            "category":"Manufacturing",
            "subcategory":"Tools & Machinery",
            "type":"Manufacturing & Wholesale Goods"
        }
    ],
    "sg:phone":"+1 519 740 3201",
    "sg:postcode":"N1R 1C2",
    "sg:province":"ON",
    "sg:tags":[
        "equipment",
        "conveyor",
        "material",
        "handling",
        "conveying"
    ],
    "wof:name":"Rolmaster Conveyors Inc",
    "wof:placetype":"venue"
},
  "geometry": {"coordinates":[-80.30894470210001,43.3788642883],"type":"Point"}
}