{
  "type": "Feature",
  "properties": {
    "addr:full":"8A Church Rd Grand Falls-Windsor NL A2A 2J3",
    "addr:housenumber":"8a",
    "addr:postcode":"a2a 2j3",
    "addr:street":"Church Rd",
    "iso:country":"CA",
    "sg:address":"8A Church Rd",
    "sg:city":"Grand Falls-Windsor",
    "sg:classifiers":[
        {
            "category":"Organizations",
            "subcategory":"Religious Organization",
            "type":"Services"
        }
    ],
    "sg:phone":"+1 709 489 6587",
    "sg:postcode":"A2A 2J3",
    "sg:province":"NL",
    "sg:tags":[
        "church"
    ],
    "wof:name":"R C Parish",
    "wof:placetype":"venue"
},
  "geometry": {"coordinates":[-55.659218,48.928905],"type":"Point"}
}