{
  "type": "Feature",
  "properties": {
    "addr:full":"2030 Barclay St Vancouver BC V6G 1L5",
    "addr:housenumber":"2030",
    "addr:postcode":"v6g 1l5",
    "addr:street":"Barclay St",
    "iso:country":"CA",
    "sg:address":"2030 Barclay St",
    "sg:city":"Vancouver",
    "sg:classifiers":[
        {
            "category":"Travel",
            "subcategory":"Hotels & Motels",
            "type":"Entertainment"
        }
    ],
    "sg:phone":"+1 604 689 4807",
    "sg:postcode":"V6G 1L5",
    "sg:province":"BC",
    "sg:tags":[
        "apartment"
    ],
    "wof:name":"Rosellen Suites",
    "wof:placetype":"venue"
},
  "geometry": {"coordinates":[-123.141159,49.292217],"type":"Point"}
}