{
  "type": "Feature",
  "properties": {
    "addr:full":"50 Wickware Gate Scarborough ON M1P 2B6",
    "addr:housenumber":"50",
    "addr:postcode":"m1p 2b6",
    "addr:street":"Wickware Gate",
    "iso:country":"CA",
    "sg:address":"50 Wickware Gate",
    "sg:city":"Scarborough",
    "sg:classifiers":[
        {
            "category":"Autos & Motor Vehicles",
            "subcategory":"Automobile Sales",
            "type":"Retail Goods"
        }
    ],
    "sg:phone":"+1 416 267 4641",
    "sg:postcode":"M1P 2B6",
    "sg:province":"ON",
    "sg:tags":[
        "repairing",
        "car"
    ],
    "wof:name":"Lakeside Motors",
    "wof:placetype":"venue"
},
  "geometry": {"coordinates":[-79.274658,43.753689],"type":"Point"}
}