{
  "type": "Feature",
  "properties": {
    "addr:full":"1993 Av Du Viaduc Charny QC G6X 2T4",
    "addr:housenumber":"1993",
    "addr:postcode":"g6x 2t4",
    "addr:street":"Av Du Viaduc",
    "iso:country":"CA",
    "sg:address":"1993 Av Du Viaduc",
    "sg:city":"Charny",
    "sg:classifiers":[
        {
            "category":"Retail",
            "subcategory":"Auto Repair",
            "type":"Services"
        }
    ],
    "sg:phone":"+1 418 832 2055",
    "sg:postcode":"G6X 2T4",
    "sg:province":"QC",
    "sg:tags":[
        "repairing",
        "automobile"
    ],
    "wof:name":"Garage Conrad Lacasse",
    "wof:placetype":"venue"
},
  "geometry": {"coordinates":[-71.26235198969999,46.7046394348],"type":"Point"}
}