{
  "type": "Feature",
  "properties": {
    "addr:full":"570 Av DE Grande-Ile Grande-Ile QC J6S 3N6",
    "addr:housenumber":"570",
    "addr:postcode":"j6s 3n6",
    "addr:street":"Av De Grande-Ile Grande-Ile",
    "iso:country":"CA",
    "sg:address":"570 Av DE Grande-Ile",
    "sg:city":"Grande-Ile",
    "sg:classifiers":[
        {
            "category":"Building & Trades",
            "subcategory":"Construction",
            "type":"Services"
        }
    ],
    "sg:phone":"+1 450 373 9900",
    "sg:postcode":"J6S 3N6",
    "sg:province":"QC",
    "sg:tags":[
        "repairing",
        "remodeling",
        "door",
        "contractor"
    ],
    "wof:name":"Portes & Fenetres Valleyfield",
    "wof:placetype":"venue"
},
  "geometry": {"coordinates":[-74.1388244629,45.2720832825],"type":"Point"}
}