{
  "type": "Feature",
  "properties": {
    "addr:full":"1230 Main St Smithers BC V0J 2N0",
    "addr:housenumber":"1230",
    "addr:postcode":"v0j 2n0",
    "addr:street":"Main St",
    "iso:country":"CA",
    "sg:address":"1230 Main St",
    "sg:city":"Smithers",
    "sg:classifiers":[
        {
            "category":"Shopping",
            "subcategory":"Florist",
            "type":"Retail Goods"
        }
    ],
    "sg:phone":"+1 250 847 9166",
    "sg:postcode":"V0J 2N0",
    "sg:province":"BC",
    "wof:name":"Appreciations Flowers & Gifts",
    "wof:placetype":"venue"
},
  "geometry": {"coordinates":[-127.169945,54.780338],"type":"Point"}
}