{
  "type": "Feature",
  "properties": {
    "addr:full":"Wawa ON P0S 1K0",
    "addr:postcode":"p0s 1k0",
    "iso:country":"CA",
    "sg:city":"Wawa",
    "sg:classifiers":[
        {
            "category":"Travel",
            "subcategory":"Hotels & Motels",
            "type":"Entertainment"
        }
    ],
    "sg:phone":"+1 705 856 2774",
    "sg:postcode":"P0S 1K0",
    "sg:province":"ON",
    "wof:name":"Lakewood Motel",
    "wof:placetype":"venue"
},
  "geometry": {"coordinates":[-84.772667,47.990986],"type":"Point"}
}