{
  "type": "Feature",
  "properties": {
    "addr:full":"236 Boul Cliche Vallee-Jonction QC G0S 3J0",
    "addr:housenumber":"236",
    "addr:postcode":"g0s 3j0",
    "addr:street":"Boul Cliche Vallee-Jonction",
    "iso:country":"CA",
    "sg:address":"236 Boul Cliche",
    "sg:city":"Vallee-Jonction",
    "sg:classifiers":[
        {
            "category":"Personal",
            "subcategory":"Beauty Salon",
            "type":"Services"
        }
    ],
    "sg:phone":"+1 418 253 5755",
    "sg:postcode":"G0S 3J0",
    "sg:province":"QC",
    "wof:name":"Salon Image Coiffure",
    "wof:placetype":"venue"
},
  "geometry": {"coordinates":[-70.917755,46.372028],"type":"Point"}
}