{
  "type": "Feature",
  "properties": {
    "addr:full":"6555 Rue Saint-Hubert Montreal QC H2S 2M5",
    "addr:housenumber":"6555",
    "addr:postcode":"h2s 2m5",
    "addr:street":"Rue Saint-Hubert",
    "iso:country":"CA",
    "sg:address":"6555 Rue Saint-Hubert",
    "sg:city":"Montreal",
    "sg:classifiers":[
        {
            "category":"Retail",
            "subcategory":"Portrait Studio",
            "type":"Services"
        }
    ],
    "sg:phone":"+1 514 277 0246",
    "sg:postcode":"H2S 2M5",
    "sg:province":"QC",
    "sg:tags":[
        "photographer"
    ],
    "wof:name":"Cinq Mars Photographes",
    "wof:placetype":"venue"
},
  "geometry": {"coordinates":[-73.604027,45.536762],"type":"Point"}
}