{
  "type": "Feature",
  "properties": {
    "addr:full":"183 Montee Du Moulin Laval QC H7N 3Y8",
    "addr:housenumber":"183",
    "addr:postcode":"h7n 3y8",
    "addr:street":"Montee Du Moulin",
    "iso:country":"CA",
    "sg:address":"183 Montee Du Moulin",
    "sg:city":"Laval",
    "sg:classifiers":[
        {
            "category":"Autos & Motor Vehicles",
            "subcategory":"Auto Supplies",
            "type":"Retail Goods"
        }
    ],
    "sg:phone":"+1 450 668 8619",
    "sg:postcode":"H7N 3Y8",
    "sg:province":"QC",
    "sg:tags":[
        "automobile",
        "parts",
        "brakes"
    ],
    "wof:name":"Distributions Pca Inc",
    "wof:placetype":"venue"
},
  "geometry": {"coordinates":[-73.706535,45.556767],"type":"Point"}
}