{
  "type": "Feature",
  "properties": {
    "iso:country":"CA",
    "sg:city":"Newmarket",
    "sg:classifiers":[
        {
            "category":"Banks & Credit Unions",
            "subcategory":"Financial Services",
            "type":"Services"
        }
    ],
    "sg:phone":"+1 905 830 0441",
    "sg:postcode":"L3Y 7T8",
    "sg:province":"ON",
    "sg:tags":[
        "bankruptcy",
        "trustee"
    ],
    "wof:name":"Perry Kreiger & Assoc Inc",
    "wof:placetype":"venue"
},
  "geometry": {"coordinates":[-79.462845,44.058624],"type":"Point"}
}