{
  "type": "Feature",
  "properties": {
    "addr:full":"29 Arena Lane Vermilion Bay ON P0V 2V0",
    "addr:housenumber":"29",
    "addr:postcode":"p0v 2v0",
    "addr:street":"Arena Lane",
    "iso:country":"CA",
    "sg:address":"29 Arena Lane",
    "sg:city":"Vermilion Bay",
    "sg:classifiers":[
        {
            "category":"Arena",
            "subcategory":"Sports Club",
            "type":"Entertainment"
        }
    ],
    "sg:phone":"+1 807 227 2833",
    "sg:postcode":"P0V 2V0",
    "sg:province":"ON",
    "sg:tags":[
        "athletic",
        "fields",
        "stadium",
        "government"
    ],
    "wof:name":"Woodland Arena",
    "wof:placetype":"venue"
},
  "geometry": {"coordinates":[-93.383743,49.858482],"type":"Point"}
}