{
  "type": "Feature",
  "properties": {
    "addr:full":"Margaree Centre NS B0E 1Z0",
    "addr:postcode":"b0e 1z0",
    "iso:country":"CA",
    "sg:city":"Margaree Centre",
    "sg:classifiers":[
        {
            "category":"Organizations",
            "subcategory":"Religious Organization",
            "type":"Services"
        }
    ],
    "sg:phone":"+1 902 248 2730",
    "sg:postcode":"B0E 1Z0",
    "sg:province":"NS",
    "sg:tags":[
        "church"
    ],
    "wof:name":"United Church Manse",
    "wof:placetype":"venue"
},
  "geometry": {"coordinates":[-61.000885,46.346378],"type":"Point"}
}