{
  "type": "Feature",
  "properties": {
    "addr:full":"4300 Rue Vachon Drummondville QC J2B 6V4",
    "addr:housenumber":"4300",
    "addr:postcode":"j2b 6v4",
    "addr:street":"Rue Vachon",
    "iso:country":"CA",
    "sg:address":"4300 Rue Vachon",
    "sg:city":"Drummondville",
    "sg:classifiers":[
        {
            "category":"Manufacturing",
            "subcategory":"Tools & Machinery",
            "type":"Manufacturing & Wholesale Goods"
        }
    ],
    "sg:phone":"+1 819 474 1910",
    "sg:postcode":"J2B 6V4",
    "sg:province":"QC",
    "sg:tags":[
        "pump",
        "steam",
        "cleaning"
    ],
    "wof:name":"Pulverisateur M-S Inc",
    "wof:placetype":"venue"
},
  "geometry": {"coordinates":[-72.51939400000001,45.908016],"type":"Point"}
}