{
  "type": "Feature",
  "properties": {
    "addr:full":"616 137 Rte Saint-Denis-Sur-Richelieu QC J0H 1K0",
    "addr:housenumber":"137",
    "addr:postcode":"j0h 1k0",
    "addr:street":"Rte Saint-Denis-Sur-Richelieu",
    "iso:country":"CA",
    "sg:address":"616 137 Rte",
    "sg:city":"Saint-Denis-Sur-Richelieu",
    "sg:classifiers":[
        {
            "category":"Retail",
            "subcategory":"Auto Repair",
            "type":"Services"
        }
    ],
    "sg:phone":"+1 450 787 2337",
    "sg:postcode":"J0H 1K0",
    "sg:province":"QC",
    "sg:tags":[
        "body",
        "automobile",
        "painting"
    ],
    "wof:name":"Bousquet Debosselage Enr",
    "wof:placetype":"venue"
},
  "geometry": {"coordinates":[-73.259552,45.316151],"type":"Point"}
}