{
  "type": "Feature",
  "properties": {
    "addr:full":"10 Bay St # 1000 Toronto ON M5J 2S3",
    "addr:housenumber":"10",
    "addr:postcode":"m5j 2s3",
    "addr:street":"Bay St # 1000",
    "iso:country":"CA",
    "sg:address":"10 Bay St # 1000",
    "sg:city":"Toronto",
    "sg:classifiers":[
        {
            "category":"Professional",
            "subcategory":"Advertising",
            "type":"Services"
        }
    ],
    "sg:phone":"+1 416 594 6000",
    "sg:postcode":"M5J 2S3",
    "sg:province":"ON",
    "sg:tags":[
        "counselor"
    ],
    "wof:name":"Mac Laren Mc Cann Canada Inc",
    "wof:placetype":"venue"
},
  "geometry": {"coordinates":[-79.377281189,43.6414833069],"type":"Point"}
}