{
  "type": "Feature",
  "properties": {
    "iso:country":"CA",
    "sg:address":"9845 Boul Saint-Michel",
    "sg:city":"Montreal-Nord",
    "sg:classifiers":[
        {
            "category":"Shopping",
            "subcategory":"Gifts & Souvenirs",
            "type":"Retail Goods"
        }
    ],
    "sg:phone":"+1 514 321 3600",
    "sg:postcode":"H1H 5G7",
    "sg:province":"QC",
    "sg:tags":[
        "shop"
    ],
    "wof:name":"Unik Centre Du Cadeau",
    "wof:placetype":"venue"
},
  "geometry": {"coordinates":[-73.6379623413,45.5768013],"type":"Point"}
}