{
  "type": "Feature",
  "properties": {
    "iso:country":"CA",
    "sg:address":"10801 Boul Ray-Lawson",
    "sg:city":"Anjou",
    "sg:classifiers":[
        {
            "category":"Manufacturing",
            "subcategory":"Printing",
            "type":"Manufacturing & Wholesale Goods"
        }
    ],
    "sg:phone":"+1 514 493 9937",
    "sg:postcode":"H1J 1M5",
    "sg:province":"QC",
    "sg:tags":[
        "printer"
    ],
    "wof:name":"Manere Inc",
    "wof:placetype":"venue"
},
  "geometry": {"coordinates":[-73.57660675050001,45.6232147217],"type":"Point"}
}