{
  "type": "Feature",
  "properties": {
    "addr:full":"1400 Robson St Vancouver BC V6G 1B9",
    "addr:housenumber":"1400",
    "addr:postcode":"v6g 1b9",
    "addr:street":"Robson St",
    "iso:country":"CA",
    "sg:address":"1400 Robson St",
    "sg:city":"Vancouver",
    "sg:classifiers":[
        {
            "category":"Retail",
            "subcategory":"Auto Rental",
            "type":"Services"
        }
    ],
    "sg:phone":"+1 604 681 4869",
    "sg:postcode":"V6G 1B9",
    "sg:province":"BC",
    "sg:tags":[
        "renting",
        "automobile"
    ],
    "wof:name":"Thrifty Car Rental",
    "wof:placetype":"venue"
},
  "geometry": {"coordinates":[-123.130157,49.287933],"type":"Point"}
}