{
  "type": "Feature",
  "properties": {
    "addr:full":"775 Seymour St Kamloops BC V2C 2H4",
    "addr:housenumber":"775",
    "addr:postcode":"bc v2c 2h4",
    "addr:street":"Seymour St",
    "iso:country":"CA",
    "sg:address":"775 Seymour St",
    "sg:city":"Kamloops",
    "sg:classifiers":[
        {
            "category":"Personal",
            "type":"Services"
        }
    ],
    "sg:phone":"+1 250 372 3863",
    "sg:postcode":"V2C 2H4",
    "sg:province":"BC",
    "sg:tags":[
        "therapist",
        "massage"
    ],
    "wof:name":"Downtown Massage Therapy Clnc",
    "wof:placetype":"venue"
},
  "geometry": {"coordinates":[-120.32229599999999,50.674789],"type":"Point"}
}