{
  "type": "Feature",
  "properties": {
    "addr:full":"Surrey BC V3W 0A6",
    "addr:postcode":"v3w 0a6",
    "iso:country":"CA",
    "sg:city":"Surrey",
    "sg:classifiers":[
        {
            "category":"Shopping",
            "subcategory":"Crafts & Fabrics",
            "type":"Retail Goods"
        }
    ],
    "sg:phone":"+1 604 788 1407",
    "sg:postcode":"V3W 0A6",
    "sg:province":"BC",
    "sg:tags":[
        "shop",
        "machine",
        "sewing"
    ],
    "wof:name":"Tom's Sewing Machine",
    "wof:placetype":"venue"
},
  "geometry": {"coordinates":[-122.865562,49.153854],"type":"Point"}
}