{
  "type": "Feature",
  "properties": {
    "addr:full":"338 Dundas St E Oakville ON L6H 6Z9",
    "addr:housenumber":"338",
    "addr:postcode":"l6h 6z9",
    "addr:street":"Dundas St E",
    "iso:country":"CA",
    "sg:address":"338 Dundas St E",
    "sg:city":"Oakville",
    "sg:classifiers":[
        {
            "category":"Food & Beverages",
            "subcategory":"Fruits & Vegetables",
            "type":"Retail Goods"
        }
    ],
    "sg:phone":"+1 905 257 5633",
    "sg:postcode":"L6H 6Z9",
    "sg:province":"ON",
    "sg:tags":[
        "grocer"
    ],
    "wof:name":"Longo's Fruit Market",
    "wof:placetype":"venue"
},
  "geometry": {"coordinates":[-79.71863555909999,43.4885063171],"type":"Point"}
}