{
  "type": "Feature",
  "properties": {
    "addr:full":"788 Centre St Burns Lake BC V0J 1E0",
    "addr:housenumber":"788",
    "addr:postcode":"v0j 1e0",
    "addr:street":"Centre St",
    "iso:country":"CA",
    "sg:address":"788 Centre St",
    "sg:city":"Burns Lake",
    "sg:classifiers":[
        {
            "category":"Social Services",
            "subcategory":"Child Care",
            "type":"Services"
        }
    ],
    "sg:phone":"+1 250 692 3575",
    "sg:postcode":"V0J 1E0",
    "sg:province":"BC",
    "wof:name":"Burns Lake Playschool",
    "wof:placetype":"venue"
},
  "geometry": {"coordinates":[-125.75988006599999,54.2361068726],"type":"Point"}
}