{
  "type": "Feature",
  "properties": {
    "addr:full":"General Delivery Kingfisher Lake ON P0V 1Z0",
    "addr:postcode":"p0v 1z0",
    "addr:street":"Lake",
    "iso:country":"CA",
    "sg:address":"General Delivery",
    "sg:city":"Kingfisher Lake",
    "sg:classifiers":[
        {
            "category":"Communications",
            "subcategory":"Radio Station",
            "type":"Services"
        }
    ],
    "sg:phone":"+1 807 532 2078",
    "sg:postcode":"P0V 1Z0",
    "sg:province":"ON",
    "sg:tags":[
        "company",
        "broadcasting"
    ],
    "wof:name":"Kingfisher Lake Radio Station",
    "wof:placetype":"venue"
},
  "geometry": {"coordinates":[-89.8333282471,53.03332901],"type":"Point"}
}