{
  "type": "Feature",
  "properties": {
    "addr:full":"8134 Rue Saint-Denis Montreal QC H2P 2G6",
    "addr:housenumber":"8134",
    "addr:postcode":"h2p 2g6",
    "addr:street":"Rue Saint-Denis",
    "iso:country":"CA",
    "sg:address":"8134 Rue Saint-Denis",
    "sg:city":"Montreal",
    "sg:classifiers":[
        {
            "category":"Health Services",
            "subcategory":"Health Practitioner",
            "type":"Services"
        }
    ],
    "sg:phone":"+1 514 382 6363",
    "sg:postcode":"H2P 2G6",
    "sg:province":"QC",
    "sg:tags":[
        "speech",
        "therapy",
        "hearing"
    ],
    "wof:name":"Clinique D'Orthophonie",
    "wof:placetype":"venue"
},
  "geometry": {"coordinates":[-73.6300125122,45.5426826477],"type":"Point"}
}