{
  "type": "Feature",
  "properties": {
    "addr:full":"91 Rue Felix-Leclerc Aylmer QC J9H 6Y4",
    "addr:housenumber":"91",
    "addr:postcode":"j9h 6y4",
    "addr:street":"Rue Felix-Leclerc",
    "iso:country":"CA",
    "sg:address":"91 Rue Felix-Leclerc",
    "sg:city":"Aylmer",
    "sg:classifiers":[
        {
            "category":"Building & Trades",
            "subcategory":"Construction",
            "type":"Services"
        }
    ],
    "sg:phone":"+1 819 772 1800",
    "sg:postcode":"J9H 6Y4",
    "sg:province":"QC",
    "sg:tags":[
        "contractor"
    ],
    "wof:name":"Dls Construction Inc",
    "wof:placetype":"venue"
},
  "geometry": {"coordinates":[-75.7976989746,45.3921165466],"type":"Point"}
}