{
  "type": "Feature",
  "properties": {
    "iso:country":"CA",
    "sg:city":"Brampton",
    "sg:classifiers":[
        {
            "category":"Manufacturing",
            "subcategory":"Tools & Machinery",
            "type":"Manufacturing & Wholesale Goods"
        }
    ],
    "sg:phone":"+1 905 451 3109",
    "sg:postcode":"L6W 3M5",
    "sg:province":"ON",
    "sg:tags":[
        "die",
        "maker"
    ],
    "wof:name":"Hita Tool & Die Ltd",
    "wof:placetype":"venue"
},
  "geometry": {"coordinates":[-79.716934,43.685585],"type":"Point"}
}