{
  "type": "Feature",
  "properties": {
    "addr:full":"Elk Point AB T0A 1A0",
    "addr:postcode":"t0a 1a0",
    "iso:country":"CA",
    "sg:city":"Elk Point",
    "sg:classifiers":[
        {
            "category":"Wholesale",
            "subcategory":"Construction Materials",
            "type":"Manufacturing & Wholesale Goods"
        }
    ],
    "sg:phone":"+1 780 724 4144",
    "sg:postcode":"T0A 1A0",
    "sg:province":"AB",
    "sg:tags":[
        "sand",
        "gravel"
    ],
    "wof:name":"Elk Point Sand & Gravel",
    "wof:placetype":"venue"
},
  "geometry": {"coordinates":[-110.89630099999999,53.897507],"type":"Point"}
}