{
  "type": "Feature",
  "properties": {
    "iso:country":"CA",
    "sg:address":"3431 Dundas St W",
    "sg:city":"York",
    "sg:classifiers":[
        {
            "category":"Building & Trades",
            "subcategory":"Electrical",
            "type":"Services"
        }
    ],
    "sg:phone":"+1 416 760 8194",
    "sg:postcode":"M6S 2S4",
    "sg:province":"ON",
    "sg:tags":[
        "equipment",
        "telecommunication"
    ],
    "wof:name":"Voxx Corp",
    "wof:placetype":"venue"
},
  "geometry": {"coordinates":[-79.5056610107,43.6627502441],"type":"Point"}
}