{
  "type": "Feature",
  "properties": {
    "addr:full":"Nanaimo BC V9T 1E5",
    "addr:postcode":"v9t 1e5",
    "iso:country":"CA",
    "sg:city":"Nanaimo",
    "sg:classifiers":[
        {
            "category":"Personal",
            "subcategory":"Barber",
            "type":"Services"
        }
    ],
    "sg:phone":"+1 250 758 9513",
    "sg:postcode":"V9T 1E5",
    "sg:province":"BC",
    "sg:tags":[
        "salon",
        "beauty"
    ],
    "wof:name":"Hair Haven Stylists",
    "wof:placetype":"venue"
},
  "geometry": {"coordinates":[-123.95622299999999,49.213787],"type":"Point"}
}