{
  "type": "Feature",
  "properties": {
    "iso:country":"CA",
    "sg:address":"72 Strathlorne Cres SW",
    "sg:city":"Calgary",
    "sg:classifiers":[
        {
            "category":"Professional",
            "subcategory":"Engineering",
            "type":"Services"
        }
    ],
    "sg:phone":"+1 403 242 7745",
    "sg:postcode":"T3H 1M8",
    "sg:province":"AB",
    "sg:tags":[
        "engineer"
    ],
    "wof:name":"Paul A Hawkins & Assoc Ltd",
    "wof:placetype":"venue"
},
  "geometry": {"coordinates":[-114.171577454,51.0427398682],"type":"Point"}
}