{
  "type": "Feature",
  "properties": {
    "addr:full":"190 Spokane St Kimberley BC V1A 2E4",
    "addr:housenumber":"190",
    "addr:postcode":"v1a 2e4",
    "addr:street":"Spokane St",
    "iso:country":"CA",
    "sg:address":"190 Spokane St",
    "sg:city":"Kimberley",
    "sg:classifiers":[
        {
            "category":"Restaurant",
            "type":"Food & Drink"
        }
    ],
    "sg:phone":"+1 250 427 3311",
    "sg:postcode":"V1A 2E4",
    "sg:province":"BC",
    "wof:name":"Golden Inn Restaurant",
    "wof:placetype":"venue"
},
  "geometry": {"coordinates":[-115.983665,49.685715],"type":"Point"}
}