{
  "type": "Feature",
  "properties": {
    "addr:full":"2599 Carling Ave Ottawa ON K2B 7H7",
    "addr:housenumber":"2599",
    "addr:postcode":"k2b 7h7",
    "addr:street":"Carling Ave",
    "iso:country":"CA",
    "sg:address":"2599 Carling Ave",
    "sg:city":"Ottawa",
    "sg:classifiers":[
        {
            "category":"Autos & Motor Vehicles",
            "subcategory":"Automobile Sales",
            "type":"Retail Goods"
        }
    ],
    "sg:phone":"+1 613 721 6244",
    "sg:postcode":"K2B 7H7",
    "sg:province":"ON",
    "sg:tags":[
        "repairing",
        "car"
    ],
    "wof:name":"Jim Dickinson Auto Tech",
    "wof:placetype":"venue"
},
  "geometry": {"coordinates":[-75.788414,45.36261],"type":"Point"}
}