{
  "type": "Feature",
  "properties": {
    "iso:country":"CA",
    "sg:city":"Dubreuilville",
    "sg:classifiers":[
        {
            "category":"Education",
            "subcategory":"School",
            "type":"Public Place"
        }
    ],
    "sg:phone":"+1 705 884 2309",
    "sg:postcode":"P0S 1B0",
    "sg:province":"ON",
    "wof:name":"Dubreuilville Rcss Board",
    "wof:placetype":"venue"
},
  "geometry": {"coordinates":[-84.5530166626,48.3505363464],"type":"Point"}
}