{
  "type": "Feature",
  "properties": {
    "addr:full":"Surrey BC V4N 4E6",
    "addr:postcode":"v4n 4e6",
    "iso:country":"CA",
    "sg:city":"Surrey",
    "sg:classifiers":[
        {
            "category":"Manufacturing",
            "subcategory":"Glass & Minerals",
            "type":"Manufacturing & Wholesale Goods"
        }
    ],
    "sg:phone":"+1 604 888 1919",
    "sg:postcode":"V4N 4E6",
    "sg:province":"BC",
    "sg:tags":[
        "fabricator",
        "fiber"
    ],
    "wof:name":"Versatile Fibreglass",
    "wof:placetype":"venue"
},
  "geometry": {"coordinates":[-122.68536400000001,49.173756],"type":"Point"}
}