{
  "type": "Feature",
  "properties": {
    "addr:full":"71 5th Ave W Battleford SK S0M 0E0",
    "addr:housenumber":"71",
    "addr:postcode":"s0m 0e0",
    "addr:street":"5Th Ave W",
    "iso:country":"CA",
    "sg:address":"71 5th Ave W",
    "sg:city":"Battleford",
    "sg:classifiers":[
        {
            "category":"Government",
            "subcategory":"Office",
            "type":"Public Place"
        }
    ],
    "sg:phone":"+1 306 445 6660",
    "sg:postcode":"S0M 0E0",
    "sg:province":"SK",
    "sg:tags":[
        "bus",
        "village"
    ],
    "wof:name":"First Bus Canada Ltd",
    "wof:placetype":"venue"
},
  "geometry": {"coordinates":[-108.318901,52.743553],"type":"Point"}
}