{
  "type": "Feature",
  "properties": {
    "addr:full":"552 Gordon Baker Rd North York ON M2H 3B4",
    "addr:housenumber":"552",
    "addr:postcode":"m2h 3b4",
    "addr:street":"Gordon Baker Rd",
    "iso:country":"CA",
    "sg:address":"552 Gordon Baker Rd",
    "sg:city":"North York",
    "sg:classifiers":[
        {
            "category":"Wholesale",
            "subcategory":"Non-durable Goods",
            "type":"Manufacturing & Wholesale Goods"
        }
    ],
    "sg:phone":"+1 416 496 2183",
    "sg:postcode":"M2H 3B4",
    "sg:province":"ON",
    "sg:tags":[
        "advertising"
    ],
    "wof:name":"Matsuda Canada CO Ltd",
    "wof:placetype":"venue"
},
  "geometry": {"coordinates":[-79.3459320068,43.8081016541],"type":"Point"}
}