{
  "type": "Feature",
  "properties": {
    "addr:full":"5 Race St St Catharines ON L2R 3M1",
    "addr:housenumber":"5",
    "addr:postcode":"l2r 3m1",
    "addr:street":"Race St",
    "iso:country":"CA",
    "sg:address":"5 Race St",
    "sg:city":"St Catharines",
    "sg:classifiers":[
        {
            "category":"Banks & Credit Unions",
            "subcategory":"Investment Brokerage",
            "type":"Services"
        }
    ],
    "sg:phone":"+1 905 684 3332",
    "sg:postcode":"L2R 3M1",
    "sg:province":"ON",
    "sg:tags":[
        "consultant",
        "planning",
        "financial"
    ],
    "wof:name":"Money Concepts",
    "wof:placetype":"venue"
},
  "geometry": {"coordinates":[-79.240852,43.158672],"type":"Point"}
}