{
  "type": "Feature",
  "properties": {
    "addr:full":"377 Conception Bay Hwy Holyrood NL A0A 2R0",
    "addr:housenumber":"377",
    "addr:postcode":"a0a 2r0",
    "addr:street":"Conception Bay Hwy",
    "iso:country":"CA",
    "sg:address":"377 Conception Bay Hwy",
    "sg:city":"Holyrood",
    "sg:classifiers":[
        {
            "category":"Autos & Motor Vehicles",
            "subcategory":"Fuel & Gas Station",
            "type":"Retail Goods"
        }
    ],
    "sg:phone":"+1 709 229 7518",
    "sg:postcode":"A0A 2R0",
    "sg:province":"NL",
    "sg:tags":[
        "oil"
    ],
    "wof:name":"Holyrood Irving Convenience",
    "wof:placetype":"venue"
},
  "geometry": {"coordinates":[-53.121651,47.389938],"type":"Point"}
}