{
  "type": "Feature",
  "properties": {
    "addr:full":"1711 19th Ave Campbell River BC V9W 4M4",
    "addr:housenumber":"1711",
    "addr:postcode":"v9w 4m4",
    "addr:street":"19Th Ave",
    "iso:country":"CA",
    "sg:address":"1711 19th Ave",
    "sg:city":"Campbell River",
    "sg:classifiers":[
        {
            "category":"Manufacturing",
            "subcategory":"Signs",
            "type":"Manufacturing & Wholesale Goods"
        }
    ],
    "sg:phone":"+1 250 287 8558",
    "sg:postcode":"V9W 4M4",
    "sg:province":"BC",
    "wof:name":"Grant Illuminated Signs Ltd",
    "wof:placetype":"venue"
},
  "geometry": {"coordinates":[-125.266823,50.033234],"type":"Point"}
}