{
  "type": "Feature",
  "properties": {
    "addr:full":"2555 Boul Mercure Saint-Nicephore QC J2A 1H3",
    "addr:housenumber":"2555",
    "addr:postcode":"j2a 1h3",
    "addr:street":"Boul Mercure Saint-Nicephore",
    "iso:country":"CA",
    "sg:address":"2555 Boul Mercure",
    "sg:city":"Saint-Nicephore",
    "sg:classifiers":[
        {
            "category":"Shopping",
            "subcategory":"Bicycles & Sporting Goods",
            "type":"Retail Goods"
        }
    ],
    "sg:phone":"+1 819 477 7470",
    "sg:postcode":"J2A 1H3",
    "sg:province":"QC",
    "wof:name":"Bicycles Excel Enr",
    "wof:placetype":"venue"
},
  "geometry": {"coordinates":[-72.4398117065,45.8338813782],"type":"Point"}
}