{
  "type": "Feature",
  "properties": {
    "iso:country":"CA",
    "sg:city":"Delta",
    "sg:classifiers":[
        {
            "category":"Insurance",
            "subcategory":"Insurance Agent",
            "type":"Services"
        }
    ],
    "sg:phone":"+1 604 943 0333",
    "sg:postcode":"V4L 2A6",
    "sg:province":"BC",
    "wof:name":"Westland Insurance Group Ltd",
    "wof:placetype":"venue"
},
  "geometry": {"coordinates":[-123.068893433,49.0269241333],"type":"Point"}
}