{
  "type": "Feature",
  "properties": {
    "addr:full":"208 Rue Dubuc Chicoutimi QC G7J 1W3",
    "addr:housenumber":"208",
    "addr:postcode":"g7j 1w3",
    "addr:street":"Rue Dubuc",
    "iso:country":"CA",
    "sg:address":"208 Rue Dubuc",
    "sg:city":"Chicoutimi",
    "sg:classifiers":[
        {
            "category":"Restaurant",
            "type":"Food & Drink"
        }
    ],
    "sg:phone":"+1 418 549 7939",
    "sg:postcode":"G7J 1W3",
    "sg:province":"QC",
    "sg:tags":[
        "party",
        "planning",
        "caterer"
    ],
    "wof:name":"Roger Levesque Maitre Traiteur",
    "wof:placetype":"venue"
},
  "geometry": {"coordinates":[-71.0756225586,48.4218025208],"type":"Point"}
}