{
  "type": "Feature",
  "properties": {
    "addr:full":"300 Holland St W Bradford ON L3Z 1J2",
    "addr:housenumber":"300",
    "addr:postcode":"l3z 1j2",
    "addr:street":"Holland St W",
    "iso:country":"CA",
    "sg:address":"300 Holland St W",
    "sg:city":"Bradford",
    "sg:classifiers":[
        {
            "category":"Restaurant",
            "type":"Food & Drink"
        }
    ],
    "sg:phone":"+1 905 778 1988",
    "sg:postcode":"L3Z 1J2",
    "sg:province":"ON",
    "wof:name":"Gino's Panini Inc",
    "wof:placetype":"venue"
},
  "geometry": {"coordinates":[-79.57576,44.111679],"type":"Point"}
}