{
  "type": "Feature",
  "properties": {
    "iso:country":"CA",
    "sg:address":"343 Grenfell Hts",
    "sg:city":"Grand Falls-Windsor",
    "sg:classifiers":[
        {
            "category":"Building & Trades",
            "subcategory":"Cleaning & Sanitation",
            "type":"Services"
        }
    ],
    "sg:phone":"+1 709 489 6500",
    "sg:postcode":"A2A 2J2",
    "sg:province":"NL",
    "sg:tags":[
        "cleaners",
        "janitor",
        "rug",
        "carpet"
    ],
    "wof:name":"Pitcher Perfect Cleaners",
    "wof:placetype":"venue"
},
  "geometry": {"coordinates":[-55.6243743896,48.9488601685],"type":"Point"}
}