{
  "type": "Feature",
  "properties": {
    "addr:full":"656 Tennent Ave London ON N5X 1L8",
    "addr:housenumber":"656",
    "addr:postcode":"n5x 1l8",
    "addr:street":"Tennent Ave",
    "iso:country":"CA",
    "sg:address":"656 Tennent Ave",
    "sg:city":"London",
    "sg:classifiers":[
        {
            "category":"Education",
            "subcategory":"School",
            "type":"Public Place"
        }
    ],
    "sg:phone":"+1 519 452 2600",
    "sg:postcode":"N5X 1L8",
    "sg:province":"ON",
    "wof:name":"Lucas School",
    "wof:placetype":"venue"
},
  "geometry": {"coordinates":[-81.2485961914,43.0317726135],"type":"Point"}
}