{
  "type": "Feature",
  "properties": {
    "iso:country":"CA",
    "sg:address":"25 Wilson Ave",
    "sg:city":"St Thomas",
    "sg:classifiers":[
        {
            "category":"Retail",
            "subcategory":"Animal Services",
            "type":"Services"
        }
    ],
    "sg:phone":"+1 519 633 3150",
    "sg:postcode":"N5R 3P9",
    "sg:province":"ON",
    "sg:tags":[
        "pet",
        "grooming",
        "washing"
    ],
    "wof:name":"St Thomas Pet Salon",
    "wof:placetype":"venue"
},
  "geometry": {"coordinates":[-81.196449,42.769615],"type":"Point"}
}