{
  "type": "Feature",
  "properties": {
    "addr:full":"1554 Danforth Ave Toronto ON M4J 1N4",
    "addr:housenumber":"1554",
    "addr:postcode":"m4j 1n4",
    "addr:street":"Danforth Ave",
    "iso:country":"CA",
    "sg:address":"1554 Danforth Ave",
    "sg:city":"Toronto",
    "sg:classifiers":[
        {
            "category":"Sports & Exercise",
            "subcategory":"Bowling",
            "type":"Entertainment"
        }
    ],
    "sg:phone":"+1 416 463 3000",
    "sg:postcode":"M4J 1N4",
    "sg:province":"ON",
    "sg:tags":[
        "center"
    ],
    "wof:name":"Danforth Bowl",
    "wof:placetype":"venue"
},
  "geometry": {"coordinates":[-79.32410430909999,43.6833877563],"type":"Point"}
}