{
  "type": "Feature",
  "properties": {
    "addr:full":"3562 Ch DE Sainte-Lucie Sainte-Agathe-Nord QC J8C 2Z8",
    "addr:housenumber":"3562",
    "addr:postcode":"j8c 2z8",
    "addr:street":"Ch De Sainte-Lucie Sainte-Agathe-Nord",
    "iso:country":"CA",
    "sg:address":"3562 Ch DE Sainte-Lucie",
    "sg:city":"Sainte-Agathe-Nord",
    "sg:classifiers":[
        {
            "category":"Building & Trades",
            "subcategory":"Electrical",
            "type":"Services"
        }
    ],
    "sg:phone":"+1 819 324 1018",
    "sg:postcode":"J8C 2Z8",
    "sg:province":"QC",
    "sg:tags":[
        "electric",
        "contractor"
    ],
    "wof:name":"Lanthier Electrique",
    "wof:placetype":"venue"
},
  "geometry": {"coordinates":[-74.2539596558,46.0971679688],"type":"Point"}
}