{
  "type": "Feature",
  "properties": {
    "iso:country":"CA",
    "sg:address":"8185 Barnett St",
    "sg:city":"Mission",
    "sg:classifiers":[
        {
            "category":"Building & Trades",
            "subcategory":"Construction",
            "type":"Services"
        }
    ],
    "sg:phone":"+1 604 826 3489",
    "sg:postcode":"V2V 7C7",
    "sg:province":"BC",
    "sg:tags":[
        "repairing",
        "remodeling",
        "contractor"
    ],
    "wof:name":"Swaine Home Finishing",
    "wof:placetype":"venue"
},
  "geometry": {"coordinates":[-122.289955139,49.15026474],"type":"Point"}
}