{
  "type": "Feature",
  "properties": {
    "iso:country":"CA",
    "sg:address":"786 Queen St",
    "sg:city":"Kincardine",
    "sg:classifiers":[
        {
            "category":"Shopping",
            "subcategory":"Used Merchandise",
            "type":"Retail Goods"
        }
    ],
    "sg:phone":"+1 519 396 3323",
    "sg:postcode":"N2Z 2Y2",
    "sg:province":"ON",
    "sg:tags":[
        "book",
        "rare",
        "dealer"
    ],
    "wof:name":"Condor Fine Books",
    "wof:placetype":"venue"
},
  "geometry": {"coordinates":[-81.6352920532,44.1772232056],"type":"Point"}
}