{
  "type": "Feature",
  "properties": {
    "addr:full":"Yellowknife NT X1A 3S5",
    "addr:postcode":"x1a 3s5",
    "iso:country":"CA",
    "sg:city":"Yellowknife",
    "sg:classifiers":[
        {
            "category":"Shopping",
            "type":"Retail Goods"
        }
    ],
    "sg:phone":"+1 867 873 4050",
    "sg:postcode":"X1A 3S5",
    "sg:province":"NT",
    "sg:tags":[
        "art",
        "gallery",
        "dealer"
    ],
    "wof:name":"Birchwood Gallery",
    "wof:placetype":"venue"
},
  "geometry": {"coordinates":[-114.37107849100001,62.4545593262],"type":"Point"}
}