{
  "type": "Feature",
  "properties": {
    "addr:full":"306 Rte Marie-Victorin Sorel-Tracy QC J3R 1K4",
    "addr:housenumber":"306",
    "addr:postcode":"j3r 1k4",
    "addr:street":"Rte Marie-Victorin",
    "iso:country":"CA",
    "sg:address":"306 Rte Marie-Victorin",
    "sg:city":"Sorel-Tracy",
    "sg:classifiers":[
        {
            "category":"Restaurant",
            "type":"Food & Drink"
        }
    ],
    "sg:phone":"+1 450 743 3366",
    "sg:postcode":"J3R 1K4",
    "sg:province":"QC",
    "wof:name":"Sorel-Tracy Bar-B-Q Inc",
    "wof:placetype":"venue"
},
  "geometry": {"coordinates":[-73.122612,46.040054],"type":"Point"}
}