{
  "type": "Feature",
  "properties": {
    "addr:full":"588 Scotland Rd Odessa ON K0H 2H0",
    "addr:housenumber":"588",
    "addr:postcode":"k0h 2h0",
    "addr:street":"Scotland Rd",
    "iso:country":"CA",
    "sg:address":"588 Scotland Rd",
    "sg:city":"Odessa",
    "sg:classifiers":[
        {
            "category":"Building & Trades",
            "subcategory":"Construction",
            "type":"Services"
        }
    ],
    "sg:phone":"+1 613 386 3033",
    "sg:postcode":"K0H 2H0",
    "sg:province":"ON",
    "sg:tags":[
        "general",
        "contractor"
    ],
    "wof:name":"Doornekamp Construction Ltd",
    "wof:placetype":"venue"
},
  "geometry": {"coordinates":[-76.71891784669999,44.2769737244],"type":"Point"}
}