{
  "type": "Feature",
  "properties": {
    "addr:full":"2095 Sinclair St Winnipeg MB R2V 3K2",
    "addr:housenumber":"2095",
    "addr:postcode":"r2v 3k2",
    "addr:street":"Sinclair St",
    "iso:country":"CA",
    "sg:address":"2095 Sinclair St",
    "sg:city":"Winnipeg",
    "sg:classifiers":[
        {
            "category":"Organizations",
            "subcategory":"Religious Organization",
            "type":"Services"
        }
    ],
    "sg:phone":"+1 204 339 8737",
    "sg:postcode":"R2V 3K2",
    "sg:province":"MB",
    "sg:tags":[
        "synagogue"
    ],
    "wof:name":"Lubavitch Centre",
    "wof:placetype":"venue"
},
  "geometry": {"coordinates":[-97.13381200000001,49.951824],"type":"Point"}
}