{
  "type": "Feature",
  "properties": {
    "addr:full":"268 Rue Saint-Patrice O Magog QC J1X 1W3",
    "addr:housenumber":"268",
    "addr:postcode":"j1x 1w3",
    "addr:street":"Rue Saint-Patrice O",
    "iso:country":"CA",
    "sg:address":"268 Rue Saint-Patrice O",
    "sg:city":"Magog",
    "sg:classifiers":[
        {
            "category":"Social Services",
            "type":"Services"
        }
    ],
    "sg:phone":"+1 819 847 2545",
    "sg:postcode":"J1X 1W3",
    "sg:province":"QC",
    "sg:tags":[
        "organization",
        "welfare"
    ],
    "wof:name":"Zone Libre Memphremagog",
    "wof:placetype":"venue"
},
  "geometry": {"coordinates":[-72.140106,45.264427],"type":"Point"}
}