{
  "type": "Feature",
  "properties": {
    "addr:full":"279 Ave Principale Degelis QC G5T 1K8",
    "addr:housenumber":"279",
    "addr:postcode":"g5t 1k8",
    "addr:street":"Ave Principale",
    "iso:country":"CA",
    "sg:address":"279 Ave Principale",
    "sg:city":"Degelis",
    "sg:classifiers":[
        {
            "category":"Bars & Pubs",
            "type":"Food & Drink"
        }
    ],
    "sg:phone":"+1 418 853 3720",
    "sg:postcode":"G5T 1K8",
    "sg:province":"QC",
    "sg:tags":[
        "lounge",
        "cocktail"
    ],
    "wof:name":"Bar Le Castel Enr",
    "wof:placetype":"venue"
},
  "geometry": {"coordinates":[-68.650757,47.548515],"type":"Point"}
}