{
  "type": "Feature",
  "properties": {
    "addr:full":"11970 224 St Maple Ridge BC V2X 6B3",
    "addr:housenumber":"11970",
    "addr:postcode":"v2x 6b3",
    "addr:street":"224 St",
    "iso:country":"CA",
    "sg:address":"11970 224 St",
    "sg:city":"Maple Ridge",
    "sg:classifiers":[
        {
            "category":"Shopping",
            "subcategory":"Gifts & Souvenirs",
            "type":"Retail Goods"
        }
    ],
    "sg:phone":"+1 604 463 3772",
    "sg:postcode":"V2X 6B3",
    "sg:province":"BC",
    "sg:tags":[
        "shop"
    ],
    "wof:name":"Midnite Fairy Party Products",
    "wof:placetype":"venue"
},
  "geometry": {"coordinates":[-122.601531982,49.220287323],"type":"Point"}
}