{
  "type": "Feature",
  "properties": {
    "addr:full":"337 Regal Dr London ON N5Y 1J3",
    "addr:housenumber":"337",
    "addr:postcode":"n5y 1j3",
    "addr:street":"Regal Dr",
    "iso:country":"CA",
    "sg:address":"337 Regal Dr",
    "sg:city":"London",
    "sg:classifiers":[
        {
            "category":"Professional",
            "subcategory":"Accounting & Tax Preparation",
            "type":"Services"
        }
    ],
    "sg:phone":"+1 519 659 2659",
    "sg:postcode":"N5Y 1J3",
    "sg:province":"ON",
    "sg:tags":[
        "bookkeeping",
        "general"
    ],
    "wof:name":"Taking Care of Business",
    "wof:placetype":"venue"
},
  "geometry": {"coordinates":[-81.22483099999999,43.020664],"type":"Point"}
}