{
  "type": "Feature",
  "properties": {
    "addr:full":"80 Sheridan St Brantford ON N3T 2R4",
    "addr:housenumber":"80",
    "addr:postcode":"n3t 2r4",
    "addr:street":"Sheridan St",
    "iso:country":"CA",
    "sg:address":"80 Sheridan St",
    "sg:city":"Brantford",
    "sg:classifiers":[
        {
            "category":"Health Services",
            "subcategory":"Hospital",
            "type":"Services"
        }
    ],
    "sg:phone":"+1 519 756 5077",
    "sg:postcode":"N3T 2R4",
    "sg:province":"ON",
    "sg:tags":[
        "mental"
    ],
    "wof:name":"Sheridan Villa",
    "wof:placetype":"venue"
},
  "geometry": {"coordinates":[-80.260925,43.144318],"type":"Point"}
}