{
  "type": "Feature",
  "properties": {
    "addr:full":"408 Selkirk Ave Winnipeg MB R2W 2M2",
    "addr:housenumber":"408",
    "addr:postcode":"r2w 2m2",
    "addr:street":"Selkirk Ave",
    "iso:country":"CA",
    "sg:address":"408 Selkirk Ave",
    "sg:city":"Winnipeg",
    "sg:classifiers":[
        {
            "category":"Restaurant",
            "type":"Food & Drink"
        }
    ],
    "sg:phone":"+1 204 586 3400",
    "sg:postcode":"R2W 2M2",
    "sg:province":"MB",
    "wof:name":"George's Burgers & Submarines",
    "wof:placetype":"venue"
},
  "geometry": {"coordinates":[-97.14089199999999,49.914215],"type":"Point"}
}