{
  "type": "Feature",
  "properties": {
    "addr:full":"121 Rue Saint-Laurent Val-D'Or QC J9P 2N2",
    "addr:housenumber":"121",
    "addr:postcode":"j9p 2n2",
    "addr:street":"Rue Saint-Laurent",
    "iso:country":"CA",
    "sg:address":"121 Rue Saint-Laurent",
    "sg:city":"Val-D'Or",
    "sg:classifiers":[
        {
            "category":"Personal",
            "subcategory":"Beauty Salon",
            "type":"Services"
        }
    ],
    "sg:phone":"+1 819 825 5959",
    "sg:postcode":"J9P 2N2",
    "sg:province":"QC",
    "wof:name":"Salon Le Peigne D'Art",
    "wof:placetype":"venue"
},
  "geometry": {"coordinates":[-68.25741577150001,48.4975128174],"type":"Point"}
}