{
  "type": "Feature",
  "properties": {
    "iso:country":"CA",
    "sg:address":"156 Jozo Weider Blvd",
    "sg:city":"Collingwood",
    "sg:classifiers":[
        {
            "category":"Shopping",
            "subcategory":"Tobacco",
            "type":"Retail Goods"
        }
    ],
    "sg:phone":"+1 705 444 0230",
    "sg:postcode":"L9Y 3Z2",
    "sg:province":"ON",
    "sg:tags":[
        "cigarette",
        "cigar",
        "dealer"
    ],
    "wof:name":"Up in Smoke",
    "wof:placetype":"venue"
},
  "geometry": {"coordinates":[-80.2168273926,44.4998893738],"type":"Point"}
}