{
  "type": "Feature",
  "properties": {
    "addr:full":"3921 Phillips Ave Burnaby BC V5A 3K4",
    "addr:housenumber":"3921",
    "addr:postcode":"v5a 3k4",
    "addr:street":"Phillips Ave",
    "iso:country":"CA",
    "sg:address":"3921 Phillips Ave",
    "sg:city":"Burnaby",
    "sg:classifiers":[
        {
            "category":"Wholesale",
            "subcategory":"Non-durable Goods",
            "type":"Manufacturing & Wholesale Goods"
        }
    ],
    "sg:phone":"+1 604 422 8848",
    "sg:postcode":"V5A 3K4",
    "sg:province":"BC",
    "wof:name":"Peter Wright Assoc Ltd",
    "wof:placetype":"venue"
},
  "geometry": {"coordinates":[-122.948883,49.248825],"type":"Point"}
}