{
  "type": "Feature",
  "properties": {
    "addr:full":"6619 86 Ave SE Calgary AB T2C 2S4",
    "addr:housenumber":"6619",
    "addr:postcode":"t2c 2s4",
    "addr:street":"86 Ave Se",
    "iso:country":"CA",
    "sg:address":"6619 86 Ave SE",
    "sg:city":"Calgary",
    "sg:classifiers":[
        {
            "category":"Manufacturing",
            "subcategory":"Metals",
            "type":"Manufacturing & Wholesale Goods"
        }
    ],
    "sg:phone":"+1 403 279 4950",
    "sg:postcode":"T2C 2S4",
    "sg:province":"AB",
    "sg:tags":[
        "steel"
    ],
    "wof:name":"Moss Fabrication Ltd",
    "wof:placetype":"venue"
},
  "geometry": {"coordinates":[-113.93911,50.975826],"type":"Point"}
}