{
  "type": "Feature",
  "properties": {
    "iso:country":"CA",
    "sg:address":"9515 104 Ave NW",
    "sg:city":"Edmonton",
    "sg:classifiers":[
        {
            "category":"Organizations",
            "subcategory":"Professional Association",
            "type":"Services"
        }
    ],
    "sg:phone":"+1 780 422 5857",
    "sg:postcode":"T5H 4H3",
    "sg:province":"AB",
    "wof:name":"Boyle St Community League",
    "wof:placetype":"venue"
},
  "geometry": {"coordinates":[-113.481437683,53.5484733582],"type":"Point"}
}