{
  "type": "Feature",
  "properties": {
    "addr:full":"3790 Rue Beethoven Brossard QC J4Z 2W3",
    "addr:housenumber":"3790",
    "addr:postcode":"j4z 2w3",
    "addr:street":"Rue Beethoven",
    "iso:country":"CA",
    "sg:address":"3790 Rue Beethoven",
    "sg:city":"Brossard",
    "sg:classifiers":[
        {
            "category":"Building & Trades",
            "subcategory":"Cleaning & Sanitation",
            "type":"Services"
        }
    ],
    "sg:phone":"+1 450 676 5341",
    "sg:postcode":"J4Z 2W3",
    "sg:province":"QC",
    "sg:tags":[
        "janitor"
    ],
    "wof:name":"Entretiens Bureau-Net Inc",
    "wof:placetype":"venue"
},
  "geometry": {"coordinates":[-73.4429016113,45.4646148682],"type":"Point"}
}