{
  "type": "Feature",
  "properties": {
    "addr:full":"528 Meloche Rd Amherstburg ON N9V 2Y8",
    "addr:housenumber":"528",
    "addr:postcode":"n9v 2y8",
    "addr:street":"Meloche Rd",
    "iso:country":"CA",
    "sg:address":"528 Meloche Rd",
    "sg:city":"Amherstburg",
    "sg:classifiers":[
        {
            "category":"Manufacturing",
            "subcategory":"Apparel",
            "type":"Manufacturing & Wholesale Goods"
        }
    ],
    "sg:phone":"+1 519 736 6335",
    "sg:postcode":"N9V 2Y8",
    "sg:province":"ON",
    "sg:tags":[
        "emblem"
    ],
    "wof:name":"Eastern Seas Trading CO Ltd",
    "wof:placetype":"venue"
},
  "geometry": {"coordinates":[-83.08292400000001,42.095383],"type":"Point"}
}