{
  "type": "Feature",
  "properties": {
    "addr:full":"Montreal QC H4P 1T7",
    "addr:postcode":"h4p 1t7",
    "iso:country":"CA",
    "sg:city":"Montreal",
    "sg:classifiers":[
        {
            "category":"Professional",
            "subcategory":"Engineering",
            "type":"Services"
        }
    ],
    "sg:phone":"+1 514 731 6951",
    "sg:postcode":"H4P 1T7",
    "sg:province":"QC",
    "sg:tags":[
        "engineer"
    ],
    "wof:name":"Stru-Des Inc",
    "wof:placetype":"venue"
},
  "geometry": {"coordinates":[-73.65063499999999,45.500538],"type":"Point"}
}