{
  "type": "Feature",
  "properties": {
    "addr:full":"27 Beech St Kingsville ON N9Y 1A9",
    "addr:housenumber":"27",
    "addr:postcode":"n9y 1a9",
    "addr:street":"Beech St",
    "iso:country":"CA",
    "sg:address":"27 Beech St",
    "sg:city":"Kingsville",
    "sg:classifiers":[
        {
            "category":"Personal",
            "subcategory":"Beauty Salon",
            "type":"Services"
        }
    ],
    "sg:phone":"+1 519 733 6126",
    "sg:postcode":"N9Y 1A9",
    "sg:province":"ON",
    "wof:name":"His & Hers Hairstyles",
    "wof:placetype":"venue"
},
  "geometry": {"coordinates":[-82.73841899999999,42.038841],"type":"Point"}
}