{
  "type": "Feature",
  "properties": {
    "addr:full":"5900 Rue Saint-Jacques Montreal QC H4A 2E9",
    "addr:housenumber":"5900",
    "addr:postcode":"h4a 2e9",
    "addr:street":"Rue Saint-Jacques",
    "iso:country":"CA",
    "sg:address":"5900 Rue Saint-Jacques",
    "sg:city":"Montreal",
    "sg:classifiers":[
        {
            "category":"Building & Trades",
            "subcategory":"Landscaping Services",
            "type":"Services"
        }
    ],
    "sg:phone":"+1 514 488 6883",
    "sg:postcode":"H4A 2E9",
    "sg:province":"QC",
    "sg:tags":[
        "landscape",
        "contractor"
    ],
    "wof:name":"Excavations Super",
    "wof:placetype":"venue"
},
  "geometry": {"coordinates":[-73.6158218384,45.4642601013],"type":"Point"}
}