{
  "type": "Feature",
  "properties": {
    "addr:full":"536 Rue Gingras Thetford Mines QC G6G 6G4",
    "addr:housenumber":"536",
    "addr:postcode":"g6g 6g4",
    "addr:street":"Rue Gingras",
    "iso:country":"CA",
    "sg:address":"536 Rue Gingras",
    "sg:city":"Thetford Mines",
    "sg:classifiers":[
        {
            "category":"Health Services",
            "subcategory":"Health Practitioner",
            "type":"Services"
        }
    ],
    "sg:phone":"+1 418 338 4295",
    "sg:postcode":"G6G 6G4",
    "sg:province":"QC",
    "sg:tags":[
        "psychologist"
    ],
    "wof:name":"Lessard, Marc Andre",
    "wof:placetype":"venue"
},
  "geometry": {"coordinates":[-71.323128,46.101254],"type":"Point"}
}