{
  "type": "Feature",
  "properties": {
    "addr:full":"3456 Principale Sainte-Helene-DE-Chester QC G0P 1H0",
    "addr:housenumber":"3456",
    "addr:postcode":"g0p 1h0",
    "addr:street":"Principale Sainte-Helene-De-Chester",
    "iso:country":"CA",
    "sg:address":"3456 Principale",
    "sg:city":"Sainte-Helene-DE-Chester",
    "sg:classifiers":[
        {
            "category":"Government",
            "subcategory":"Office",
            "type":"Public Place"
        }
    ],
    "sg:phone":"+1 819 382 2650",
    "sg:postcode":"G0P 1H0",
    "sg:province":"QC",
    "sg:tags":[
        "city",
        "hall",
        "village"
    ],
    "wof:name":"Chester Est Bureau Municpal",
    "wof:placetype":"venue"
},
  "geometry": {"coordinates":[-71.6759109497,46.0333404541],"type":"Point"}
}