{
  "type": "Feature",
  "properties": {
    "addr:full":"141 Av Kindersley Mont-Royal QC H3R 1R3",
    "addr:postcode":"h3r 1r3",
    "addr:street":"141 Av Kindersley",
    "iso:country":"CA",
    "sg:address":"141 Av Kindersley",
    "sg:city":"Mont-Royal",
    "sg:classifiers":[
        {
            "category":"Personal",
            "subcategory":"Beauty Salon",
            "type":"Services"
        }
    ],
    "sg:phone":"+1 514 738 1720",
    "sg:postcode":"H3R 1R3",
    "sg:province":"QC",
    "wof:name":"Karen Electrolyse Esthetique",
    "wof:placetype":"venue"
},
  "geometry": {"coordinates":[-73.64724,45.51379],"type":"Point"}
}