{
  "type": "Feature",
  "properties": {
    "addr:full":"117 Rue Dumont Vaudreuil-Dorion QC J7V 1W9",
    "addr:housenumber":"117",
    "addr:postcode":"j7v 1w9",
    "addr:street":"Rue Dumont",
    "iso:country":"CA",
    "sg:address":"117 Rue Dumont",
    "sg:city":"Vaudreuil-Dorion",
    "sg:classifiers":[
        {
            "category":"Personal",
            "subcategory":"Beauty Salon",
            "type":"Services"
        }
    ],
    "sg:phone":"+1 450 455 7986",
    "sg:postcode":"J7V 1W9",
    "sg:province":"QC",
    "wof:name":"Bellini Coiffure",
    "wof:placetype":"venue"
},
  "geometry": {"coordinates":[-74.010468,45.38448],"type":"Point"}
}