{
  "type": "Feature",
  "properties": {
    "addr:full":"601 Rue Du Sud Cowansville QC J2K 2X9",
    "addr:housenumber":"601",
    "addr:postcode":"j2k 2x9",
    "addr:street":"Rue Du Sud",
    "iso:country":"CA",
    "sg:address":"601 Rue Du Sud",
    "sg:city":"Cowansville",
    "sg:classifiers":[
        {
            "category":"Restaurant",
            "type":"Food & Drink"
        }
    ],
    "sg:phone":"+1 450 266 7166",
    "sg:postcode":"J2K 2X9",
    "sg:province":"QC",
    "wof:name":"O Patio",
    "wof:placetype":"venue"
},
  "geometry": {"coordinates":[-72.74722300000001,45.202744],"type":"Point"}
}