{
  "type": "Feature",
  "properties": {
    "iso:country":"CA",
    "sg:address":"22425 Jefferies Rd",
    "sg:city":"Komoka",
    "sg:classifiers":[
        {
            "category":"Health Services",
            "subcategory":"Doctor",
            "type":"Services"
        }
    ],
    "sg:phone":"+1 519 473 2600",
    "sg:postcode":"N0L 1R0",
    "sg:province":"ON",
    "sg:tags":[
        "physician",
        "surgeon"
    ],
    "wof:name":"Wolder, Thomas MD",
    "wof:placetype":"venue"
},
  "geometry": {"coordinates":[-81.40827941889999,42.9589958191],"type":"Point"}
}