{
  "type": "Feature",
  "properties": {
    "addr:full":"251 Scarlett Rd York ON M6N 4K9",
    "addr:housenumber":"251",
    "addr:postcode":"m6n 4k9",
    "addr:street":"Scarlett Rd",
    "iso:country":"CA",
    "sg:address":"251 Scarlett Rd",
    "sg:city":"York",
    "sg:classifiers":[
        {
            "category":"Professional",
            "subcategory":"Business Services",
            "type":"Services"
        }
    ],
    "sg:phone":"+1 416 763 4114",
    "sg:postcode":"M6N 4K9",
    "sg:province":"ON",
    "sg:tags":[
        "broker"
    ],
    "wof:name":"Sadowy Services Ltd",
    "wof:placetype":"venue"
},
  "geometry": {"coordinates":[-79.5060424805,43.6773452759],"type":"Point"}
}