{
  "type": "Feature",
  "properties": {
    "addr:full":"5104 50th St Hardisty AB T0B 1V0",
    "addr:housenumber":"5104",
    "addr:postcode":"t0b 1v0",
    "addr:street":"50Th St",
    "iso:country":"CA",
    "sg:address":"5104 50th St",
    "sg:city":"Hardisty",
    "sg:classifiers":[
        {
            "category":"Shopping",
            "subcategory":"Stationery & Office Supplies",
            "type":"Retail Goods"
        }
    ],
    "sg:phone":"+1 780 888 0008",
    "sg:postcode":"T0B 1V0",
    "sg:province":"AB",
    "wof:name":"Crocus Hill Distributors",
    "wof:placetype":"venue"
},
  "geometry": {"coordinates":[-111.30377960200001,52.6761245728],"type":"Point"}
}