{
  "type": "Feature",
  "properties": {
    "addr:full":"1480 Boul Le Corbusier Laval QC H7S 1Y8",
    "addr:housenumber":"1480",
    "addr:postcode":"h7s 1y8",
    "addr:street":"Boul Le Corbusier",
    "iso:country":"CA",
    "sg:address":"1480 Boul Le Corbusier",
    "sg:city":"Laval",
    "sg:classifiers":[
        {
            "category":"Shopping",
            "subcategory":"Clothing, Apparel, & Fashions",
            "type":"Retail Goods"
        }
    ],
    "sg:phone":"+1 450 680 1420",
    "sg:postcode":"H7S 1Y8",
    "sg:province":"QC",
    "sg:tags":[
        "tailor"
    ],
    "wof:name":"Allaire Paul Inc",
    "wof:placetype":"venue"
},
  "geometry": {"coordinates":[-73.7287368774,45.5616073608],"type":"Point"}
}