{
  "type": "Feature",
  "properties": {
    "addr:full":"PO Box 4211 STN Main Barrhead AB T7N 1A2",
    "addr:housenumber":"po",
    "addr:postcode":"t7n 1a2",
    "addr:street":"Box 4211 Stn Main",
    "iso:country":"CA",
    "sg:address":"PO Box 4211 STN Main",
    "sg:city":"Barrhead",
    "sg:classifiers":[
        {
            "category":"Building & Trades",
            "subcategory":"Construction",
            "type":"Services"
        }
    ],
    "sg:phone":"+1 780 674 6232",
    "sg:postcode":"T7N 1A2",
    "sg:province":"AB",
    "sg:tags":[
        "field",
        "oil",
        "general",
        "contractor"
    ],
    "wof:name":"Hillman Brothers Construction",
    "wof:placetype":"venue"
},
  "geometry": {"coordinates":[-114.406005859,54.1209907532],"type":"Point"}
}