{
  "type": "Feature",
  "properties": {
    "addr:full":"Calgary AB T3E 0A2",
    "addr:postcode":"t3e 0a2",
    "iso:country":"CA",
    "sg:city":"Calgary",
    "sg:classifiers":[
        {
            "category":"Shopping",
            "subcategory":"Books",
            "type":"Retail Goods"
        }
    ],
    "sg:phone":"+1 403 246 1706",
    "sg:postcode":"T3E 0A2",
    "sg:province":"AB",
    "sg:tags":[
        "comic"
    ],
    "wof:name":"Phoenix Comic Books",
    "wof:placetype":"venue"
},
  "geometry": {"coordinates":[-114.11949199999999,51.037704],"type":"Point"}
}