{
  "type": "Feature",
  "properties": {
    "addr:full":"Carstairs AB T0M 0N0",
    "addr:postcode":"t0m 0n0",
    "iso:country":"CA",
    "sg:city":"Carstairs",
    "sg:classifiers":[
        {
            "category":"Farming",
            "subcategory":"Nursery",
            "type":"Manufacturing & Wholesale Goods"
        }
    ],
    "sg:phone":"+1 403 337 2447",
    "sg:postcode":"T0M 0N0",
    "sg:province":"AB",
    "sg:tags":[
        "chemical",
        "agricultural",
        "greenhouse"
    ],
    "wof:name":"Agricore United",
    "wof:placetype":"venue"
},
  "geometry": {"coordinates":[-114.101311,51.572472],"type":"Point"}
}