{
  "type": "Feature",
  "properties": {
    "addr:full":"Stettler AB T0C 2L2",
    "addr:postcode":"t0c 2l2",
    "iso:country":"CA",
    "sg:city":"Stettler",
    "sg:classifiers":[
        {
            "category":"Shopping",
            "subcategory":"Discount & Variety Stores",
            "type":"Retail Goods"
        }
    ],
    "sg:phone":"+1 403 742 3460",
    "sg:postcode":"T0C 2L2",
    "sg:province":"AB",
    "wof:name":"Dan D Variety Ltd",
    "wof:placetype":"venue"
},
  "geometry": {"coordinates":[-112.70549774200001,52.3263587952],"type":"Point"}
}