{
  "type": "Feature",
  "properties": {
    "addr:full":"6774 Dufferin Ave West Vancouver BC V7W 2K2",
    "addr:housenumber":"6774",
    "addr:postcode":"v7w 2k2",
    "addr:street":"Dufferin Ave",
    "iso:country":"CA",
    "sg:address":"6774 Dufferin Ave",
    "sg:city":"West Vancouver",
    "sg:classifiers":[
        {
            "category":"Real Estate",
            "subcategory":"Architect",
            "type":"Services"
        }
    ],
    "sg:phone":"+1 604 921 6396",
    "sg:postcode":"V7W 2K2",
    "sg:province":"BC",
    "wof:name":"Legate Fiss Architects",
    "wof:placetype":"venue"
},
  "geometry": {"coordinates":[-123.282447815,49.3745994568],"type":"Point"}
}