{
  "type": "Feature",
  "properties": {
    "addr:full":"38 Meadow Park Dr Huntsville ON P1H 1E7",
    "addr:housenumber":"38",
    "addr:postcode":"p1h 1e7",
    "addr:street":"Meadow Park Dr",
    "iso:country":"CA",
    "sg:address":"38 Meadow Park Dr",
    "sg:city":"Huntsville",
    "sg:classifiers":[
        {
            "category":"Professional",
            "subcategory":"Art Services",
            "type":"Services"
        }
    ],
    "sg:phone":"+1 705 789 4947",
    "sg:postcode":"P1H 1E7",
    "sg:province":"ON",
    "sg:tags":[
        "photographer"
    ],
    "wof:name":"Jenny Kirkpatrick Photography",
    "wof:placetype":"venue"
},
  "geometry": {"coordinates":[-79.204376,45.332211],"type":"Point"}
}