{
  "type": "Feature",
  "properties": {
    "addr:full":"1805 Av Charland Montreal QC H1Z 1A1",
    "addr:housenumber":"1805",
    "addr:postcode":"h1z 1a1",
    "addr:street":"Av Charland",
    "iso:country":"CA",
    "sg:address":"1805 Av Charland",
    "sg:city":"Montreal",
    "sg:classifiers":[
        {
            "category":"Manufacturing",
            "subcategory":"Furniture",
            "type":"Manufacturing & Wholesale Goods"
        }
    ],
    "sg:phone":"+1 514 383 2229",
    "sg:postcode":"H1Z 1A1",
    "sg:province":"QC",
    "wof:name":"Galeries Napoleon",
    "wof:placetype":"venue"
},
  "geometry": {"coordinates":[-73.644806,45.564758],"type":"Point"}
}