{
  "type": "Feature",
  "properties": {
    "addr:full":"Consort AB T0C 1B0",
    "addr:postcode":"t0c 1b0",
    "iso:country":"CA",
    "sg:city":"Consort",
    "sg:classifiers":[
        {
            "category":"Manufacturing",
            "subcategory":"Tools & Machinery",
            "type":"Manufacturing & Wholesale Goods"
        }
    ],
    "sg:phone":"+1 403 577 3535",
    "sg:postcode":"T0C 1B0",
    "sg:province":"AB",
    "sg:tags":[
        "farm",
        "equipment"
    ],
    "wof:name":"United Farmers of Alberta",
    "wof:placetype":"venue"
},
  "geometry": {"coordinates":[-110.76608299999999,52.00716],"type":"Point"}
}