{
  "type": "Feature",
  "properties": {
    "addr:full":"10 Rue DE LA Cour Riviere-Du-Loup QC G5R 1J2",
    "addr:housenumber":"10",
    "addr:postcode":"g5r 1j2",
    "addr:street":"Rue De La Cour Riviere-Du-Loup",
    "iso:country":"CA",
    "sg:address":"10 Rue DE LA Cour",
    "sg:city":"Riviere-Du-Loup",
    "sg:classifiers":[
        {
            "category":"Personal",
            "subcategory":"Beauty Salon",
            "type":"Services"
        }
    ],
    "sg:phone":"+1 418 867 1268",
    "sg:postcode":"G5R 1J2",
    "sg:province":"QC",
    "wof:name":"Salon Jeanne",
    "wof:placetype":"venue"
},
  "geometry": {"coordinates":[-69.5394668579,47.8371696472],"type":"Point"}
}