{
  "type": "Feature",
  "properties": {
    "addr:full":"27 Rue Beauchemin Gatineau QC J8T 5S8",
    "addr:housenumber":"27",
    "addr:postcode":"j8t 5s8",
    "addr:street":"Rue Beauchemin",
    "iso:country":"CA",
    "sg:address":"27 Rue Beauchemin",
    "sg:city":"Gatineau",
    "sg:classifiers":[
        {
            "category":"Professional",
            "subcategory":"Business Services",
            "type":"Services"
        }
    ],
    "sg:phone":"+1 819 243 3980",
    "sg:postcode":"J8T 5S8",
    "sg:province":"QC",
    "sg:tags":[
        "translator",
        "interpreter"
    ],
    "wof:name":"Traduction G Ouellet Inc",
    "wof:placetype":"venue"
},
  "geometry": {"coordinates":[-75.698257,45.483032],"type":"Point"}
}