{
  "type": "Feature",
  "properties": {
    "addr:full":"379 Rue Pichette E Chateau-Richer QC G0A 1N0",
    "addr:housenumber":"379",
    "addr:postcode":"g0a 1n0",
    "addr:street":"Rue Pichette E Chateau-Richer",
    "iso:country":"CA",
    "sg:address":"379 Rue Pichette E",
    "sg:city":"Chateau-Richer",
    "sg:classifiers":[
        {
            "category":"Building & Trades",
            "subcategory":"Construction",
            "type":"Services"
        }
    ],
    "sg:phone":"+1 418 824 3590",
    "sg:postcode":"G0A 1N0",
    "sg:province":"QC",
    "sg:tags":[
        "general",
        "contractor"
    ],
    "wof:name":"Trottoirs & Chaines Picard",
    "wof:placetype":"venue"
},
  "geometry": {"coordinates":[-71.02016448969999,46.9712104797],"type":"Point"}
}