{
  "type": "Feature",
  "properties": {
    "addr:full":"6 Lansing Sq North York ON M2J 1T5",
    "addr:housenumber":"6",
    "addr:postcode":"m2j 1t5",
    "addr:street":"Lansing Sq",
    "iso:country":"CA",
    "sg:address":"6 Lansing Sq",
    "sg:city":"North York",
    "sg:classifiers":[
        {
            "category":"Shopping",
            "subcategory":"Computers & Home Electronics",
            "type":"Retail Goods"
        }
    ],
    "sg:phone":"+1 416 493 6440",
    "sg:postcode":"M2J 1T5",
    "sg:province":"ON",
    "sg:tags":[
        "consultant",
        "software"
    ],
    "wof:name":"Decision Software Inc",
    "wof:placetype":"venue"
},
  "geometry": {"coordinates":[-79.32567596440001,43.773601532],"type":"Point"}
}