{
  "type": "Feature",
  "properties": {
    "iso:country":"CA",
    "sg:address":"54 Central St",
    "sg:city":"Weldon",
    "sg:classifiers":[
        {
            "category":"Health Services",
            "subcategory":"Nursing And Care Facility",
            "type":"Services"
        }
    ],
    "sg:phone":"+1 306 887 2888",
    "sg:postcode":"S0J 3A0",
    "sg:province":"SK",
    "sg:tags":[
        "personal",
        "home"
    ],
    "wof:name":"Weldon Country Villa",
    "wof:placetype":"venue"
},
  "geometry": {"coordinates":[-105.140563965,53.0050888062],"type":"Point"}
}