{
  "type": "Feature",
  "properties": {
    "addr:full":"3840 Old Almonte Rd Almonte ON K0A 1A0",
    "addr:housenumber":"3840",
    "addr:postcode":"k0a 1a0",
    "addr:street":"Old Almonte Rd",
    "iso:country":"CA",
    "sg:address":"3840 Old Almonte Rd",
    "sg:city":"Almonte",
    "sg:classifiers":[
        {
            "category":"Home & Garden",
            "subcategory":"Garden Supply",
            "type":"Retail Goods"
        }
    ],
    "sg:phone":"+1 613 256 0228",
    "sg:postcode":"K0A 1A0",
    "sg:province":"ON",
    "sg:tags":[
        "nurseryman",
        "center"
    ],
    "wof:name":"Herb Garden",
    "wof:placetype":"venue"
},
  "geometry": {"coordinates":[-76.181,45.229328],"type":"Point"}
}