{
  "type": "Feature",
  "properties": {
    "addr:full":"413 Rue Saint-Jacques Montreal QC H2Y 1N9",
    "addr:housenumber":"413",
    "addr:postcode":"h2y 1n9",
    "addr:street":"Rue Saint-Jacques",
    "iso:country":"CA",
    "sg:address":"413 Rue Saint-Jacques",
    "sg:city":"Montreal",
    "sg:classifiers":[
        {
            "category":"Wholesale",
            "subcategory":"Apparel",
            "type":"Manufacturing & Wholesale Goods"
        }
    ],
    "sg:phone":"+1 514 844 9125",
    "sg:postcode":"H2Y 1N9",
    "sg:province":"QC",
    "sg:tags":[
        "clothing"
    ],
    "wof:name":"Dolce Donna",
    "wof:placetype":"venue"
},
  "geometry": {"coordinates":[-73.560028,45.502003],"type":"Point"}
}