{
  "type": "Feature",
  "properties": {
    "addr:full":"551 Shiloh Ave Kingston ON K7M 8W1",
    "addr:housenumber":"551",
    "addr:postcode":"k7m 8w1",
    "addr:street":"Shiloh Ave",
    "iso:country":"CA",
    "sg:address":"551 Shiloh Ave",
    "sg:city":"Kingston",
    "sg:classifiers":[
        {
            "category":"Health Services",
            "subcategory":"Doctor",
            "type":"Services"
        }
    ],
    "sg:phone":"+1 613 384 9829",
    "sg:postcode":"K7M 8W1",
    "sg:province":"ON",
    "sg:tags":[
        "clinic"
    ],
    "wof:name":"Bioenergy Health Clinic",
    "wof:placetype":"venue"
},
  "geometry": {"coordinates":[-76.59991455079999,44.2350120544],"type":"Point"}
}