{
  "type": "Feature",
  "properties": {
    "addr:full":"1187 Rue Labadie Longueuil QC J4N 1E2",
    "addr:housenumber":"1187",
    "addr:postcode":"j4n 1e2",
    "addr:street":"Rue Labadie",
    "iso:country":"CA",
    "sg:address":"1187 Rue Labadie",
    "sg:city":"Longueuil",
    "sg:classifiers":[
        {
            "category":"Wholesale",
            "subcategory":"Machinery & Supplies",
            "type":"Manufacturing & Wholesale Goods"
        }
    ],
    "sg:phone":"+1 450 442 4779",
    "sg:postcode":"J4N 1E2",
    "sg:province":"QC",
    "sg:tags":[
        "equipment",
        "printing"
    ],
    "wof:name":"Equipement D'Imprimerie D & D",
    "wof:placetype":"venue"
},
  "geometry": {"coordinates":[-73.455406,45.564075],"type":"Point"}
}