{
  "type": "Feature",
  "properties": {
    "iso:country":"CA",
    "sg:address":"10530 138 St NW",
    "sg:city":"Edmonton",
    "sg:classifiers":[
        {
            "category":"Education",
            "subcategory":"School",
            "type":"Public Place"
        }
    ],
    "sg:phone":"+1 780 452 1991",
    "sg:postcode":"T5N 2J6",
    "sg:province":"AB",
    "sg:tags":[
        "kindergarten"
    ],
    "wof:name":"Glenora Child Care",
    "wof:placetype":"venue"
},
  "geometry": {"coordinates":[-113.55990600600001,53.5483169556],"type":"Point"}
}