{
  "type": "Feature",
  "properties": {
    "addr:full":"2665 Rue King O Sherbrooke QC J1L 2G5",
    "addr:housenumber":"2665",
    "addr:postcode":"j1l 2g5",
    "addr:street":"Rue King O",
    "iso:country":"CA",
    "sg:address":"2665 Rue King O",
    "sg:city":"Sherbrooke",
    "sg:classifiers":[
        {
            "category":"Banks & Credit Unions",
            "subcategory":"Bank",
            "type":"Services"
        }
    ],
    "sg:phone":"+1 819 823 4200",
    "sg:postcode":"J1L 2G5",
    "sg:province":"QC",
    "wof:name":"Banque Royale",
    "wof:placetype":"venue"
},
  "geometry": {"coordinates":[-71.938187,45.398384],"type":"Point"}
}