{
  "type": "Feature",
  "properties": {
    "addr:full":"342 Rang Du Haut Corbin Saint-Damase QC J0H 1J0",
    "addr:housenumber":"342",
    "addr:postcode":"j0h 1j0",
    "addr:street":"Rang Du Haut Corbin",
    "iso:country":"CA",
    "sg:address":"342 Rang Du Haut Corbin",
    "sg:city":"Saint-Damase",
    "sg:classifiers":[
        {
            "category":"Wholesale",
            "subcategory":"Fruits & Vegetables",
            "type":"Manufacturing & Wholesale Goods"
        }
    ],
    "sg:phone":"+1 450 797 3637",
    "sg:postcode":"J0H 1J0",
    "sg:province":"QC",
    "sg:tags":[
        "shipper"
    ],
    "wof:name":"Vergers Mado Inc",
    "wof:placetype":"venue"
},
  "geometry": {"coordinates":[-73.03119700000001,45.497833],"type":"Point"}
}