{
  "type": "Feature",
  "properties": {
    "addr:full":"1220 Boul Lemire O Drummondville QC J2B 8A9",
    "addr:housenumber":"1220",
    "addr:postcode":"j2b 8a9",
    "addr:street":"Boul Lemire O",
    "iso:country":"CA",
    "sg:address":"1220 Boul Lemire O",
    "sg:city":"Drummondville",
    "sg:classifiers":[
        {
            "category":"Retail",
            "subcategory":"Auto Repair",
            "type":"Services"
        }
    ],
    "sg:phone":"+1 819 472 7922",
    "sg:postcode":"J2B 8A9",
    "sg:province":"QC",
    "sg:tags":[
        "body",
        "automobile",
        "painting"
    ],
    "wof:name":"Garage Marcel Lambert Enr",
    "wof:placetype":"venue"
},
  "geometry": {"coordinates":[-72.517715,45.874592],"type":"Point"}
}