{
  "type": "Feature",
  "properties": {
    "addr:full":"375 Doran St Pembroke ON K8A 4N3",
    "addr:housenumber":"375",
    "addr:postcode":"k8a 4n3",
    "addr:street":"Doran St",
    "iso:country":"CA",
    "sg:address":"375 Doran St",
    "sg:city":"Pembroke",
    "sg:classifiers":[
        {
            "category":"Social Services",
            "subcategory":"Child Care",
            "type":"Services"
        }
    ],
    "sg:phone":"+1 613 735 2259",
    "sg:postcode":"K8A 4N3",
    "sg:province":"ON",
    "sg:tags":[
        "kindergarten",
        "academic",
        "school"
    ],
    "wof:name":"Children's Garden Nursery Schl",
    "wof:placetype":"venue"
},
  "geometry": {"coordinates":[-77.119865,45.820065],"type":"Point"}
}