{
  "type": "Feature",
  "properties": {
    "iso:country":"CA",
    "sg:address":"515 Legget Drive Suite 700",
    "sg:city":"Ottawa",
    "sg:classifiers":[
        {
            "category":"Professional",
            "subcategory":"Computer Services",
            "type":"Services"
        }
    ],
    "sg:postcode":"K2K 3G4",
    "sg:tags":[
        "open-source",
        "intellectual-property",
        "ip-management",
        "plug-in",
        "software-development",
        "external-content",
        "ip-policies",
        "licenses",
        "developers",
        "eclipse",
        "cc",
        "java"
    ],
    "sg:website":"http://www.protecode.com/",
    "wof:name":"Protecode",
    "wof:placetype":"venue"
},
  "geometry": {"coordinates":[-75.83415100000001,45.352255],"type":"Point"}
}