{
  "type": "Feature",
  "properties": {
    "addr:full":"7 Hydro Rd St Thomas ON N5P 2N5",
    "addr:housenumber":"7",
    "addr:postcode":"n5p 2n5",
    "addr:street":"Hydro Rd",
    "iso:country":"CA",
    "sg:address":"7 Hydro Rd",
    "sg:city":"St Thomas",
    "sg:classifiers":[
        {
            "category":"Home & Garden",
            "subcategory":"Household Appliances",
            "type":"Retail Goods"
        }
    ],
    "sg:phone":"+1 519 633 0107",
    "sg:postcode":"N5P 2N5",
    "sg:province":"ON",
    "wof:name":"Mudge's Appliances",
    "wof:placetype":"venue"
},
  "geometry": {"coordinates":[-81.19314575200001,42.7789382935],"type":"Point"}
}