{
  "type": "Feature",
  "properties": {
    "addr:full":"229 Russell Hill Rd Toronto ON M4V 2T3",
    "addr:housenumber":"229",
    "addr:postcode":"m4v 2t3",
    "addr:street":"Russell Hill Rd",
    "iso:country":"CA",
    "sg:address":"229 Russell Hill Rd",
    "sg:city":"Toronto",
    "sg:classifiers":[
        {
            "category":"Professional",
            "subcategory":"Lawyer & Legal Services",
            "type":"Services"
        }
    ],
    "sg:phone":"+1 416 929 2919",
    "sg:postcode":"M4V 2T3",
    "sg:province":"ON",
    "sg:tags":[
        "attorney"
    ],
    "wof:name":"Benjamin Rubin & Assoc",
    "wof:placetype":"venue"
},
  "geometry": {"coordinates":[-79.407127,43.683933],"type":"Point"}
}