{
  "type": "Feature",
  "properties": {
    "addr:full":"10149 34 Ave NW Edmonton AB T6E 6J8",
    "addr:housenumber":"10149",
    "addr:postcode":"t6e 6j8",
    "addr:street":"34 Ave Nw",
    "iso:country":"CA",
    "sg:address":"10149 34 Ave NW",
    "sg:city":"Edmonton",
    "sg:classifiers":[
        {
            "category":"Building & Trades",
            "subcategory":"Equipment Rental",
            "type":"Services"
        }
    ],
    "sg:phone":"+1 780 944 1411",
    "sg:postcode":"T6E 6J8",
    "sg:province":"AB",
    "sg:tags":[
        "party",
        "supply"
    ],
    "wof:name":"Party Land",
    "wof:placetype":"venue"
},
  "geometry": {"coordinates":[-113.490257,53.467522],"type":"Point"}
}