{
  "type": "Feature",
  "properties": {
    "addr:full":"Frasers Mills Goshen NS B0H 1M0",
    "addr:postcode":"b0h 1m0",
    "iso:country":"CA",
    "sg:address":"Frasers Mills",
    "sg:city":"Goshen",
    "sg:classifiers":[
        {
            "category":"Government",
            "subcategory":"Office",
            "type":"Public Place"
        }
    ],
    "sg:phone":"+1 902 783 2926",
    "sg:postcode":"B0H 1M0",
    "sg:province":"NS",
    "wof:name":"Nova Scotia Fisheries",
    "wof:placetype":"venue"
},
  "geometry": {"coordinates":[-61.9736824036,45.3764686584],"type":"Point"}
}