{
  "type": "Feature",
  "properties": {
    "addr:full":"3052 Jaguar Valley Dr Mississauga ON L5A 2J3",
    "addr:housenumber":"3052",
    "addr:postcode":"l5a 2j3",
    "addr:street":"Jaguar Valley Dr",
    "iso:country":"CA",
    "sg:address":"3052 Jaguar Valley Dr",
    "sg:city":"Mississauga",
    "sg:classifiers":[
        {
            "category":"Retail",
            "subcategory":"Auto Repair",
            "type":"Services"
        }
    ],
    "sg:phone":"+1 416 667 8468",
    "sg:postcode":"L5A 2J3",
    "sg:province":"ON",
    "sg:tags":[
        "glass",
        "coating",
        "tinting"
    ],
    "wof:name":"Armorshield Window Films",
    "wof:placetype":"venue"
},
  "geometry": {"coordinates":[-79.61676,43.582355],"type":"Point"}
}