{
  "type": "Feature",
  "properties": {
    "addr:full":"4999 Rue Sainte-Catherine O Westmount QC H3Z 1T3",
    "addr:housenumber":"4999",
    "addr:postcode":"h3z 1t3",
    "addr:street":"Rue Sainte-Catherine O",
    "iso:country":"CA",
    "sg:address":"4999 Rue Sainte-Catherine O",
    "sg:city":"Westmount",
    "sg:classifiers":[
        {
            "category":"Health Services",
            "subcategory":"Health Practitioner",
            "type":"Services"
        }
    ],
    "sg:phone":"+1 514 482 6996",
    "sg:postcode":"H3Z 1T3",
    "sg:province":"QC",
    "sg:tags":[
        "psychologist"
    ],
    "wof:name":"Spector, Esther",
    "wof:placetype":"venue"
},
  "geometry": {"coordinates":[-73.601997,45.47588],"type":"Point"}
}