{
  "type": "Feature",
  "properties": {
    "iso:country":"CA",
    "sg:address":"1797 Pine Grove Rd",
    "sg:city":"Marlbank",
    "sg:classifiers":[
        {
            "category":"Manufacturing",
            "subcategory":"Furniture",
            "type":"Manufacturing & Wholesale Goods"
        }
    ],
    "sg:phone":"+1 613 478 2920",
    "sg:postcode":"K0K 2L0",
    "sg:province":"ON",
    "wof:name":"Hawley Brothers Ltd",
    "wof:placetype":"venue"
},
  "geometry": {"coordinates":[-77.092926,44.434944],"type":"Point"}
}