{
  "type": "Feature",
  "properties": {
    "addr:full":"1797 Pine Grove Rd Marlbank ON K0K 2L0",
    "addr:housenumber":"1797",
    "addr:postcode":"k0k 2l0",
    "addr:street":"Pine Grove Rd",
    "iso:country":"CA",
    "sg:address":"1797 Pine Grove Rd",
    "sg:city":"Marlbank",
    "sg:classifiers":[
        {
            "category":"Manufacturing",
            "subcategory":"Furniture",
            "type":"Manufacturing & Wholesale Goods"
        }
    ],
    "sg:phone":"+1 613 478 2920",
    "sg:postcode":"K0K 2L0",
    "sg:province":"ON",
    "wof:name":"Hawley Brothers Ltd",
    "wof:placetype":"venue"
},
  "geometry": {"coordinates":[-77.09292600000001,44.434944],"type":"Point"}
}