{
  "type": "Feature",
  "properties": {
    "addr:full":"155 Rue Marguerite-Bourgeoys L'Assomption QC J5W 3H3",
    "addr:housenumber":"155",
    "addr:postcode":"j5w 3h3",
    "addr:street":"Rue Marguerite-Bourgeoys",
    "iso:country":"CA",
    "sg:address":"155 Rue Marguerite-Bourgeoys",
    "sg:city":"L'Assomption",
    "sg:classifiers":[
        {
            "category":"Retail",
            "subcategory":"Veterinary Services",
            "type":"Services"
        }
    ],
    "sg:phone":"+1 450 589 3533",
    "sg:postcode":"J5W 3H3",
    "sg:province":"QC",
    "sg:tags":[
        "clinic",
        "veterinarian"
    ],
    "wof:name":"Clinique Veterinaire Enrg",
    "wof:placetype":"venue"
},
  "geometry": {"coordinates":[-73.4263839722,45.8227043152],"type":"Point"}
}