{
  "type": "Feature",
  "properties": {
    "addr:full":"7060 Rue Sherbrooke O Montreal QC H4B 1R2",
    "addr:housenumber":"7060",
    "addr:postcode":"h4b 1r2",
    "addr:street":"Rue Sherbrooke O",
    "iso:country":"CA",
    "sg:address":"7060 Rue Sherbrooke O",
    "sg:city":"Montreal",
    "sg:classifiers":[
        {
            "category":"Restaurant",
            "type":"Food & Drink"
        }
    ],
    "sg:phone":"+1 514 253 9991",
    "sg:postcode":"H4B 1R2",
    "sg:province":"QC",
    "wof:name":"Ronda Sushi",
    "wof:placetype":"venue"
},
  "geometry": {"coordinates":[-73.54001617430001,45.5875663757],"type":"Point"}
}