{
  "type": "Feature",
  "properties": {
    "addr:full":"4481 County Rd 36 Burleigh Falls ON K0L 1K0",
    "addr:housenumber":"4481;36",
    "addr:postcode":"k0l 1k0",
    "addr:street":"County Rd;Falls",
    "iso:country":"CA",
    "sg:address":"4481 County Rd 36",
    "sg:city":"Burleigh Falls",
    "sg:classifiers":[
        {
            "category":"Travel",
            "subcategory":"Hotels & Motels",
            "type":"Entertainment"
        }
    ],
    "sg:phone":"+1 705 654 3421",
    "sg:postcode":"K0L 1K0",
    "sg:province":"ON",
    "sg:tags":[
        "cottage",
        "resort",
        "cabin"
    ],
    "wof:name":"Marrick's Landing",
    "wof:placetype":"venue"
},
  "geometry": {"coordinates":[-78.21017456049999,44.5616798401],"type":"Point"}
}