{
  "type": "Feature",
  "properties": {
    "addr:full":"2050 Boul Monseigneur-Langlois Salaberry-DE-Valleyfield QC J6S 5R1",
    "addr:housenumber":"2050",
    "addr:postcode":"j6s 5r1",
    "addr:street":"Boul Monseigneur-Langlois",
    "iso:country":"CA",
    "sg:address":"2050 Boul Monseigneur-Langlois",
    "sg:city":"Salaberry-DE-Valleyfield",
    "sg:classifiers":[
        {
            "category":"Shopping",
            "subcategory":"Department Store",
            "type":"Retail Goods"
        }
    ],
    "sg:phone":"+1 450 371 9026",
    "sg:postcode":"J6S 5R1",
    "sg:province":"QC",
    "sg:tags":[
        "pharmacy"
    ],
    "wof:name":"Wal-Mart",
    "wof:placetype":"venue"
},
  "geometry": {"coordinates":[-74.117165,45.271732],"type":"Point"}
}