{
  "type": "Feature",
  "properties": {
    "addr:full":"5683 Rue Pare Mont-Royal QC H4P 1S1",
    "addr:housenumber":"5683",
    "addr:postcode":"h4p 1s1",
    "addr:street":"Rue Pare",
    "iso:country":"CA",
    "sg:address":"5683 Rue Pare",
    "sg:city":"Mont-Royal",
    "sg:classifiers":[
        {
            "category":"Building & Trades",
            "subcategory":"Construction",
            "type":"Services"
        }
    ],
    "sg:phone":"+1 514 731 6661",
    "sg:postcode":"H4P 1S1",
    "sg:province":"QC",
    "sg:tags":[
        "detection",
        "splicing",
        "installation",
        "cable",
        "internet"
    ],
    "wof:name":"Francois Pilon Enr",
    "wof:placetype":"venue"
},
  "geometry": {"coordinates":[-73.66471900000001,45.489059],"type":"Point"}
}