{
  "type": "Feature",
  "properties": {
    "iso:country":"CA",
    "sg:address":"8985 Rue DE L'Amazone",
    "sg:city":"Quebec",
    "sg:classifiers":[
        {
            "category":"Food & Beverages",
            "subcategory":"Groceries & Convenience Stores",
            "type":"Retail Goods"
        }
    ],
    "sg:phone":"+1 418 842 8132",
    "sg:postcode":"G2C 1E3",
    "sg:province":"QC",
    "wof:name":"Accommodation LA Chaumiere Enr",
    "wof:placetype":"venue"
},
  "geometry": {"coordinates":[-71.351921,46.827251],"type":"Point"}
}