{
  "type": "Feature",
  "properties": {
    "addr:full":"20 Orwell St North Vancouver BC V7J 2G1",
    "addr:housenumber":"20",
    "addr:postcode":"v7j 2g1",
    "addr:street":"Orwell St",
    "iso:country":"CA",
    "sg:address":"20 Orwell St",
    "sg:city":"North Vancouver",
    "sg:classifiers":[
        {
            "category":"Manufacturing",
            "subcategory":"Food",
            "type":"Manufacturing & Wholesale Goods"
        }
    ],
    "sg:phone":"+1 604 980 6536",
    "sg:postcode":"V7J 2G1",
    "sg:province":"BC",
    "sg:tags":[
        "packer",
        "fish"
    ],
    "wof:name":"Great Northern Packing Ltd",
    "wof:placetype":"venue"
},
  "geometry": {"coordinates":[-123.029594421,49.3002967834],"type":"Point"}
}