{
  "type": "Feature",
  "properties": {
    "iso:country":"CA",
    "sg:address":"1070 Roosevelt Cres",
    "sg:city":"North Vancouver",
    "sg:classifiers":[
        {
            "category":"Professional",
            "subcategory":"Business Services",
            "type":"Services"
        }
    ],
    "sg:phone":"+1 604 985 7491",
    "sg:postcode":"V7P 1M3",
    "sg:province":"BC",
    "sg:tags":[
        "packaging"
    ],
    "wof:name":"Amity-Cooinda Packaging Svc",
    "wof:placetype":"venue"
},
  "geometry": {"coordinates":[-123.103439331,49.3220291138],"type":"Point"}
}