{
  "type": "Feature",
  "properties": {
    "addr:full":"29 116 Rte E Princeville QC G6L 4K6",
    "addr:housenumber":"116",
    "addr:postcode":"g6l 4k6",
    "addr:street":"29;Rte E",
    "iso:country":"CA",
    "sg:address":"29 116 Rte E",
    "sg:city":"Princeville",
    "sg:classifiers":[
        {
            "category":"Wholesale",
            "subcategory":"Machinery & Supplies",
            "type":"Manufacturing & Wholesale Goods"
        }
    ],
    "sg:phone":"+1 819 364 7041",
    "sg:postcode":"G6L 4K6",
    "sg:province":"QC",
    "sg:tags":[
        "contractor"
    ],
    "wof:name":"Equipements Benoit Beauchesne",
    "wof:placetype":"venue"
},
  "geometry": {"coordinates":[-71.87023162840001,46.1691131592],"type":"Point"}
}