{
  "type": "Feature",
  "properties": {
    "addr:full":"2012 Arlington Ave Saskatoon SK S7J 2H5",
    "addr:housenumber":"2012",
    "addr:postcode":"s7j 2h5",
    "addr:street":"Arlington Ave",
    "iso:country":"CA",
    "sg:address":"2012 Arlington Ave",
    "sg:city":"Saskatoon",
    "sg:classifiers":[
        {
            "category":"Social Services",
            "subcategory":"Adult Care",
            "type":"Services"
        }
    ],
    "sg:phone":"+1 306 374 5151",
    "sg:postcode":"S7J 2H5",
    "sg:province":"SK",
    "sg:tags":[
        "home",
        "residential"
    ],
    "wof:name":"Elmwood Residences Inc",
    "wof:placetype":"venue"
},
  "geometry": {"coordinates":[-106.610153,52.104366],"type":"Point"}
}