{
  "type": "Feature",
  "properties": {
    "addr:full":"Chambord QC G0W 1G0",
    "addr:postcode":"g0w 1g0",
    "iso:country":"CA",
    "sg:city":"Chambord",
    "sg:classifiers":[
        {
            "category":"Professional",
            "subcategory":"Business Services",
            "type":"Services"
        }
    ],
    "sg:phone":"+1 418 342 8337",
    "sg:postcode":"G0W 1G0",
    "sg:province":"QC",
    "sg:tags":[
        "information",
        "referral"
    ],
    "wof:name":"Poste D'Accueil Regional",
    "wof:placetype":"venue"
},
  "geometry": {"coordinates":[-72.04846999999999,48.427769],"type":"Point"}
}