{
  "type": "Feature",
  "properties": {
    "iso:country":"CA",
    "sg:address":"2531 Av Walkley",
    "sg:city":"Montreal",
    "sg:classifiers":[
        {
            "category":"Building & Trades",
            "subcategory":"Electrical",
            "type":"Services"
        }
    ],
    "sg:phone":"+1 514 482 0800",
    "sg:postcode":"H4B 2J9",
    "sg:province":"QC",
    "sg:tags":[
        "electric",
        "contractor"
    ],
    "wof:name":"Sako Electric Ltd",
    "wof:placetype":"venue"
},
  "geometry": {"coordinates":[-73.629883,45.462547],"type":"Point"}
}