{
  "type": "Feature",
  "properties": {
    "addr:full":"2531 Av Walkley Montreal QC H4B 2J9",
    "addr:housenumber":"2531",
    "addr:postcode":"h4b 2j9",
    "addr:street":"Av Walkley",
    "iso:country":"CA",
    "sg:address":"2531 Av Walkley",
    "sg:city":"Montreal",
    "sg:classifiers":[
        {
            "category":"Building & Trades",
            "subcategory":"Electrical",
            "type":"Services"
        }
    ],
    "sg:phone":"+1 514 482 0800",
    "sg:postcode":"H4B 2J9",
    "sg:province":"QC",
    "sg:tags":[
        "electric",
        "contractor"
    ],
    "wof:name":"Sako Electric Ltd",
    "wof:placetype":"venue"
},
  "geometry": {"coordinates":[-73.62988300000001,45.462547],"type":"Point"}
}