{
  "type": "Feature",
  "properties": {
    "addr:full":"145 Rue Saint-Eustache Saint-Eustache QC J7R 2L5",
    "addr:housenumber":"145",
    "addr:postcode":"j7r 2l5",
    "addr:street":"Rue Saint-Eustache",
    "iso:country":"CA",
    "sg:address":"145 Rue Saint-Eustache",
    "sg:city":"Saint-Eustache",
    "sg:classifiers":[
        {
            "category":"Restaurant",
            "type":"Food & Drink"
        }
    ],
    "sg:phone":"+1 450 623 4446",
    "sg:postcode":"J7R 2L5",
    "sg:province":"QC",
    "wof:name":"Cafe Cle DE Sol",
    "wof:placetype":"venue"
},
  "geometry": {"coordinates":[-73.892921,45.558701],"type":"Point"}
}