{
  "type": "Feature",
  "properties": {
    "addr:full":"2199 Squilax-Anglmont Rd Chase BC V0E 1M0",
    "addr:housenumber":"2199",
    "addr:postcode":"v0e 1m0",
    "addr:street":"Squilax-Anglmont Rd",
    "iso:country":"CA",
    "sg:address":"2199 Squilax-Anglmont Rd",
    "sg:city":"Chase",
    "sg:classifiers":[
        {
            "category":"Home & Garden",
            "subcategory":"Building Materials",
            "type":"Retail Goods"
        }
    ],
    "sg:phone":"+1 250 679 3292",
    "sg:postcode":"V0E 1M0",
    "sg:province":"BC",
    "sg:tags":[
        "mixed",
        "concrete"
    ],
    "wof:name":"Tri-Lake Ready Mix Ltd",
    "wof:placetype":"venue"
},
  "geometry": {"coordinates":[-119.684303,50.816067],"type":"Point"}
}