{
  "type": "Feature",
  "properties": {
    "iso:country":"CA",
    "sg:city":"Coquitlam",
    "sg:classifiers":[
        {
            "category":"Health Services",
            "subcategory":"Doctor",
            "type":"Services"
        }
    ],
    "sg:phone":"+1 604 945 0032",
    "sg:postcode":"V3E 1J7",
    "sg:province":"BC",
    "sg:tags":[
        "clinic"
    ],
    "wof:name":"Eagle Ridge Medical Clinic",
    "wof:placetype":"venue"
},
  "geometry": {"coordinates":[-122.809547,49.283817],"type":"Point"}
}