{
  "type": "Feature",
  "properties": {
    "addr:full":"11280 Guelph Line Campbellville ON L0P 1B0",
    "addr:housenumber":"11280",
    "addr:postcode":"l0p 1b0",
    "addr:street":"Guelph Line",
    "iso:country":"CA",
    "sg:address":"11280 Guelph Line",
    "sg:city":"Campbellville",
    "sg:classifiers":[
        {
            "category":"Retail",
            "subcategory":"Veterinary Services",
            "type":"Services"
        }
    ],
    "sg:phone":"+1 905 854 2216",
    "sg:postcode":"L0P 1B0",
    "sg:province":"ON",
    "sg:tags":[
        "veterinarian"
    ],
    "wof:name":"Druif, Jacob DVM",
    "wof:placetype":"venue"
},
  "geometry": {"coordinates":[-80.008682251,43.5056304932],"type":"Point"}
}