{
  "type": "Feature",
  "properties": {
    "iso:country":"CA",
    "sg:city":"Montreal",
    "sg:classifiers":[
        {
            "category":"Personal",
            "subcategory":"Beauty Salon",
            "type":"Services"
        }
    ],
    "sg:phone":"+1 514 342 5124",
    "sg:postcode":"H3W 1X2",
    "sg:province":"QC",
    "wof:name":"Coiffure Unisexe Sandro",
    "wof:placetype":"venue"
},
  "geometry": {"coordinates":[-73.6265716553,45.4863853455],"type":"Point"}
}