{
  "type": "Feature",
  "properties": {
    "addr:full":"1470 18th St N Brandon MB R7C 1A5",
    "addr:housenumber":"1470",
    "addr:postcode":"r7c 1a5",
    "addr:street":"18Th St N",
    "iso:country":"CA",
    "sg:address":"1470 18th St N",
    "sg:city":"Brandon",
    "sg:classifiers":[
        {
            "category":"Shopping",
            "subcategory":"Gifts & Souvenirs",
            "type":"Retail Goods"
        }
    ],
    "sg:phone":"+1 204 727 4050",
    "sg:postcode":"R7C 1A5",
    "sg:province":"MB",
    "sg:tags":[
        "cards",
        "greeting"
    ],
    "wof:name":"Carlton Cards",
    "wof:placetype":"venue"
},
  "geometry": {"coordinates":[-99.962158,49.874947],"type":"Point"}
}