{
  "type": "Feature",
  "properties": {
    "addr:full":"11311 Bridgeport Rd Richmond BC V6X 1T4",
    "addr:housenumber":"11311",
    "addr:postcode":"v6x 1t4",
    "addr:street":"Bridgeport Rd",
    "iso:country":"CA",
    "sg:address":"11311 Bridgeport Rd",
    "sg:city":"Richmond",
    "sg:classifiers":[
        {
            "category":"Retail",
            "subcategory":"Auto Repair",
            "type":"Services"
        }
    ],
    "sg:phone":"+1 604 273 0751",
    "sg:postcode":"V6X 1T4",
    "sg:province":"BC",
    "sg:tags":[
        "body",
        "automobile",
        "painting"
    ],
    "wof:name":"Taurus Auto Care Ltd",
    "wof:placetype":"venue"
},
  "geometry": {"coordinates":[-123.098243713,49.1921310425],"type":"Point"}
}