{
  "type": "Feature",
  "properties": {
    "addr:full":"6887 Boul Saint-Laurent Montreal QC H2S 3C9",
    "addr:housenumber":"6887",
    "addr:postcode":"h2s 3c9",
    "addr:street":"Boul Saint-Laurent",
    "iso:country":"CA",
    "sg:address":"6887 Boul Saint-Laurent",
    "sg:city":"Montreal",
    "sg:classifiers":[
        {
            "category":"Shopping",
            "subcategory":"Luggage & Leather Goods",
            "type":"Retail Goods"
        }
    ],
    "sg:phone":"+1 514 274 1633",
    "sg:postcode":"H2S 3C9",
    "sg:province":"QC",
    "wof:name":"Carman Luggage CO",
    "wof:placetype":"venue"
},
  "geometry": {"coordinates":[-73.614243,45.533001],"type":"Point"}
}