{
  "type": "Feature",
  "properties": {
    "addr:full":"8240 Boul Langelier Saint-Leonard QC H1P 3G9",
    "addr:housenumber":"8240",
    "addr:postcode":"h1p 3g9",
    "addr:street":"Boul Langelier",
    "iso:country":"CA",
    "sg:address":"8240 Boul Langelier",
    "sg:city":"Saint-Leonard",
    "sg:classifiers":[
        {
            "category":"Retail",
            "subcategory":"Laundry & Dry Cleaning",
            "type":"Services"
        }
    ],
    "sg:phone":"+1 514 523 5197",
    "sg:postcode":"H1P 3G9",
    "sg:province":"QC",
    "sg:tags":[
        "cleaners"
    ],
    "wof:name":"Nettoyeurs Daoust",
    "wof:placetype":"venue"
},
  "geometry": {"coordinates":[-73.585312,45.596027],"type":"Point"}
}