{
  "type": "Feature",
  "properties": {
    "addr:full":"5192 Av Gatineau Montreal QC H3T 1W9",
    "addr:housenumber":"5192",
    "addr:postcode":"h3t 1w9",
    "addr:street":"Av Gatineau",
    "iso:country":"CA",
    "sg:address":"5192 Av Gatineau",
    "sg:city":"Montreal",
    "sg:classifiers":[
        {
            "category":"Restaurant",
            "type":"Food & Drink"
        }
    ],
    "sg:phone":"+1 514 340 9664",
    "sg:postcode":"H3T 1W9",
    "sg:province":"QC",
    "wof:name":"Rotisserie Mavi",
    "wof:placetype":"venue"
},
  "geometry": {"coordinates":[-73.61837768549999,45.4956512451],"type":"Point"}
}