{
  "type": "Feature",
  "properties": {
    "addr:full":"1474 Highway 7A Bethany ON L0A 1A0",
    "addr:housenumber":"1474",
    "addr:postcode":"l0a 1a0",
    "addr:street":"Highway 7A",
    "iso:country":"CA",
    "sg:address":"1474 Highway 7A",
    "sg:city":"Bethany",
    "sg:classifiers":[
        {
            "category":"Government",
            "subcategory":"Office",
            "type":"Public Place"
        }
    ],
    "sg:phone":"+1 705 277 2321",
    "sg:postcode":"L0A 1A0",
    "sg:province":"ON",
    "sg:tags":[
        "village"
    ],
    "wof:name":"Kawartha Lakes Svc Ctr",
    "wof:placetype":"venue"
},
  "geometry": {"coordinates":[-78.566734314,44.1828651428],"type":"Point"}
}