{
  "type": "Feature",
  "properties": {
    "addr:full":"2770 Kennedy Rd Scarborough ON M1T 3J2",
    "addr:housenumber":"2770",
    "addr:postcode":"m1t 3j2",
    "addr:street":"Kennedy Rd",
    "iso:country":"CA",
    "sg:address":"2770 Kennedy Rd",
    "sg:city":"Scarborough",
    "sg:classifiers":[
        {
            "category":"Retail",
            "subcategory":"Veterinary Services",
            "type":"Services"
        }
    ],
    "sg:phone":"+1 416 292 7804",
    "sg:postcode":"M1T 3J2",
    "sg:province":"ON",
    "sg:tags":[
        "veterinarian"
    ],
    "wof:name":"Milliken Veterinary Clinic",
    "wof:placetype":"venue"
},
  "geometry": {"coordinates":[-79.295761,43.799999],"type":"Point"}
}