{
  "type": "Feature",
  "properties": {
    "iso:country":"CA",
    "sg:address":"255 Boul Cremazie E",
    "sg:city":"Montreal",
    "sg:classifiers":[
        {
            "category":"Restaurant",
            "type":"Food & Drink"
        }
    ],
    "sg:phone":"+1 514 858 9936",
    "sg:postcode":"H2M 1M2",
    "sg:province":"QC",
    "sg:tags":[
        "shop",
        "coffee"
    ],
    "wof:name":"Cafe Supreme",
    "wof:placetype":"venue"
},
  "geometry": {"coordinates":[-73.640244,45.544228],"type":"Point"}
}