{
  "type": "Feature",
  "properties": {
    "addr:full":"204 295 Rte # 2260 Degelis QC G5T 1R3",
    "addr:housenumber":"295",
    "addr:postcode":"g5t 1r3",
    "addr:street":"Rte # 2260 Degelis",
    "iso:country":"CA",
    "sg:address":"204 295 Rte # 2260",
    "sg:city":"Degelis",
    "sg:classifiers":[
        {
            "category":"Food & Beverages",
            "subcategory":"Groceries & Convenience Stores",
            "type":"Retail Goods"
        }
    ],
    "sg:phone":"+1 418 853 2260",
    "sg:postcode":"G5T 1R3",
    "sg:province":"QC",
    "sg:tags":[
        "grocer"
    ],
    "wof:name":"Epicerie-Depanneur Morneault",
    "wof:placetype":"venue"
},
  "geometry": {"coordinates":[-68.642517,47.546989],"type":"Point"}
}