{
  "type": "Feature",
  "properties": {
    "addr:full":"95 2E Rue E LA Sarre QC J9Z 3J9",
    "addr:housenumber":"95",
    "addr:postcode":"j9z 3j9",
    "addr:street":"2E Rue E La Sarre",
    "iso:country":"CA",
    "sg:address":"95 2E Rue E",
    "sg:city":"LA Sarre",
    "sg:classifiers":[
        {
            "category":"Autos & Motor Vehicles",
            "subcategory":"Auto Supplies",
            "type":"Retail Goods"
        }
    ],
    "sg:phone":"+1 819 333 4975",
    "sg:postcode":"J9Z 3J9",
    "sg:province":"QC",
    "sg:tags":[
        "automobile",
        "parts"
    ],
    "wof:name":"Canadian Tire Gas Bar",
    "wof:placetype":"venue"
},
  "geometry": {"coordinates":[-79.200485,48.815582],"type":"Point"}
}