{
  "type": "Feature",
  "properties": {
    "addr:full":"1185 Pachendale Rd Sorrento BC V0E 2W0",
    "addr:housenumber":"1185",
    "addr:postcode":"bc v0e 2w0",
    "addr:street":"Pachendale Rd",
    "iso:country":"CA",
    "sg:address":"1185 Pachendale Rd",
    "sg:city":"Sorrento",
    "sg:classifiers":[
        {
            "category":"Travel",
            "subcategory":"Hotels & Motels",
            "type":"Entertainment"
        }
    ],
    "sg:phone":"+1 250 675 2420",
    "sg:postcode":"V0E 2W0",
    "sg:province":"BC",
    "wof:name":"Shuswap Lake Motel & Resort",
    "wof:placetype":"venue"
},
  "geometry": {"coordinates":[-119.47389200000001,50.87809],"type":"Point"}
}