{
  "type": "Feature",
  "properties": {
    "addr:full":"655 Boul Cremazie E Montreal QC H2M 2K9",
    "addr:housenumber":"655",
    "addr:postcode":"h2m 2k9",
    "addr:street":"Boul Cremazie E",
    "iso:country":"CA",
    "sg:address":"655 Boul Cremazie E",
    "sg:city":"Montreal",
    "sg:classifiers":[
        {
            "category":"Professional",
            "subcategory":"Accounting & Tax Preparation",
            "type":"Services"
        }
    ],
    "sg:phone":"+1 514 384 3620",
    "sg:postcode":"H2M 2K9",
    "sg:province":"QC",
    "sg:tags":[
        "accountant"
    ],
    "wof:name":"Belzile Tremblay",
    "wof:placetype":"venue"
},
  "geometry": {"coordinates":[-73.637276,45.547668],"type":"Point"}
}