{
  "type": "Feature",
  "properties": {
    "addr:full":"4 Vickers Rd Hamilton ON L9A 1Y1",
    "addr:housenumber":"4",
    "addr:postcode":"l9a 1y1",
    "addr:street":"Vickers Rd",
    "iso:country":"CA",
    "sg:address":"4 Vickers Rd",
    "sg:city":"Hamilton",
    "sg:classifiers":[
        {
            "category":"Education",
            "subcategory":"School",
            "type":"Public Place"
        }
    ],
    "sg:phone":"+1 905 385 5365",
    "sg:postcode":"L9A 1Y1",
    "sg:province":"ON",
    "wof:name":"Linden Park School",
    "wof:placetype":"venue"
},
  "geometry": {"coordinates":[-79.8638687134,43.2298927307],"type":"Point"}
}