{
  "type": "Feature",
  "properties": {
    "iso:country":"CA",
    "sg:address":"45 West Side Dr",
    "sg:city":"Bowmanville",
    "sg:classifiers":[
        {
            "category":"Social Services",
            "subcategory":"Child Care",
            "type":"Services"
        }
    ],
    "sg:phone":"+1 905 697 3171",
    "sg:postcode":"L1C 4Y8",
    "sg:province":"ON",
    "wof:name":"Ymca of Durham Region",
    "wof:placetype":"venue"
},
  "geometry": {"coordinates":[-78.70153000000001,43.898262],"type":"Point"}
}