{
  "type": "Feature",
  "properties": {
    "addr:full":"15 Elizabeth St E # 2 Creemore ON L0M 1G0",
    "addr:housenumber":"15",
    "addr:postcode":"l0m 1g0",
    "addr:street":"Elizabeth St E # 2 Creemore",
    "iso:country":"CA",
    "sg:address":"15 Elizabeth St E # 2",
    "sg:city":"Creemore",
    "sg:classifiers":[
        {
            "category":"Health Services",
            "subcategory":"Doctor",
            "type":"Services"
        }
    ],
    "sg:phone":"+1 705 466 3344",
    "sg:postcode":"L0M 1G0",
    "sg:province":"ON",
    "sg:tags":[
        "dentist"
    ],
    "wof:name":"Hawthorne, W DDS",
    "wof:placetype":"venue"
},
  "geometry": {"coordinates":[-80.1035003662,44.3253555298],"type":"Point"}
}