{
  "type": "Feature",
  "properties": {
    "iso:country":"CA",
    "sg:address":"330 Principale E",
    "sg:city":"Mont-Louis",
    "sg:classifiers":[
        {
            "category":"Education",
            "subcategory":"Dance Studio",
            "type":"Public Place"
        }
    ],
    "sg:phone":"+1 418 797 2775",
    "sg:postcode":"G0E 1T0",
    "sg:province":"QC",
    "sg:tags":[
        "instruction",
        "dancing"
    ],
    "wof:name":"Centre DE Loisirs-Riviere",
    "wof:placetype":"venue"
},
  "geometry": {"coordinates":[-65.7301025391,49.229434967],"type":"Point"}
}