{
  "type": "Feature",
  "properties": {
    "addr:full":"2800 Rue Masson Montreal QC H1Y 1W7",
    "addr:housenumber":"2800",
    "addr:postcode":"h1y 1w7",
    "addr:street":"Rue Masson",
    "iso:country":"CA",
    "sg:address":"2800 Rue Masson",
    "sg:city":"Montreal",
    "sg:classifiers":[
        {
            "category":"Shopping",
            "subcategory":"Florist",
            "type":"Retail Goods"
        }
    ],
    "sg:phone":"+1 514 527 1218",
    "sg:postcode":"H1Y 1W7",
    "sg:province":"QC",
    "wof:name":"Fleuriste Raymond Inc",
    "wof:placetype":"venue"
},
  "geometry": {"coordinates":[-73.575394,45.547035],"type":"Point"}
}