{
  "type": "Feature",
  "properties": {
    "addr:full":"Vancouver BC V6Z 1R9",
    "addr:postcode":"v6z 1r9",
    "iso:country":"CA",
    "sg:city":"Vancouver",
    "sg:classifiers":[
        {
            "category":"Health Services",
            "subcategory":"Doctor",
            "type":"Services"
        }
    ],
    "sg:phone":"+1 604 689 9474",
    "sg:postcode":"V6Z 1R9",
    "sg:province":"BC",
    "sg:tags":[
        "physician",
        "surgeon"
    ],
    "wof:name":"Doherty, M MD",
    "wof:placetype":"venue"
},
  "geometry": {"coordinates":[-123.130905,49.27549],"type":"Point"}
}