{
  "type": "Feature",
  "properties": {
    "addr:full":"Winnipeg MB R2J 1M2",
    "addr:postcode":"r2j 1m2",
    "iso:country":"CA",
    "sg:city":"Winnipeg",
    "sg:classifiers":[
        {
            "category":"Building & Trades",
            "subcategory":"Plumbing",
            "type":"Services"
        }
    ],
    "sg:phone":"+1 204 233 7456",
    "sg:postcode":"R2J 1M2",
    "sg:province":"MB",
    "sg:tags":[
        "balancing",
        "air"
    ],
    "wof:name":"Air Movement Svc",
    "wof:placetype":"venue"
},
  "geometry": {"coordinates":[-97.0733795166,49.8725013733],"type":"Point"}
}