{
  "type": "Feature",
  "properties": {
    "addr:full":"Saint-Cesaire QC J0L 1T0",
    "addr:postcode":"j0l 1t0",
    "iso:country":"CA",
    "sg:city":"Saint-Cesaire",
    "sg:classifiers":[
        {
            "category":"Local Transit",
            "type":"Transportation"
        }
    ],
    "sg:phone":"+1 450 469 4155",
    "sg:postcode":"J0L 1T0",
    "sg:province":"QC",
    "sg:tags":[
        "bus",
        "line"
    ],
    "wof:name":"Autobus St-Cesaire Ltee",
    "wof:placetype":"venue"
},
  "geometry": {"coordinates":[-73.0106124878,45.4108848572],"type":"Point"}
}