{
  "type": "Feature",
  "properties": {
    "addr:full":"45 Renfrew Ave E Renfrew ON K7V 2W7",
    "addr:housenumber":"45",
    "addr:postcode":"k7v 2w7",
    "addr:street":"Renfrew Ave E",
    "iso:country":"CA",
    "sg:address":"45 Renfrew Ave E",
    "sg:city":"Renfrew",
    "sg:classifiers":[
        {
            "category":"Banks & Credit Unions",
            "subcategory":"Financial Services",
            "type":"Services"
        }
    ],
    "sg:phone":"+1 613 432 2223",
    "sg:postcode":"K7V 2W7",
    "sg:province":"ON",
    "sg:tags":[
        "bankruptcy",
        "trustee"
    ],
    "wof:name":"Doyle Salewski Inc",
    "wof:placetype":"venue"
},
  "geometry": {"coordinates":[-76.682518,45.47208],"type":"Point"}
}