{
  "type": "Feature",
  "properties": {
    "iso:country":"CA",
    "sg:city":"Leamington",
    "sg:classifiers":[
        {
            "category":"Health Services",
            "subcategory":"Doctor",
            "type":"Services"
        }
    ],
    "sg:phone":"+1 519 322 4933",
    "sg:postcode":"N8H 5C5",
    "sg:province":"ON",
    "sg:tags":[
        "physician",
        "surgeon"
    ],
    "wof:name":"Klassen, Gerhard MD",
    "wof:placetype":"venue"
},
  "geometry": {"coordinates":[-82.5985412598,42.0517463684],"type":"Point"}
}