{
  "type": "Feature",
  "properties": {
    "iso:country":"CA",
    "sg:address":"274 County Rd 42",
    "sg:city":"Windsor",
    "sg:classifiers":[
        {
            "category":"Autos & Motor Vehicles",
            "subcategory":"Fuel & Gas Station",
            "type":"Retail Goods"
        }
    ],
    "sg:phone":"+1 519 727 3500",
    "sg:postcode":"N8N 2L9",
    "sg:province":"ON",
    "sg:tags":[
        "oil"
    ],
    "wof:name":"M & R Country Store",
    "wof:placetype":"venue"
},
  "geometry": {"coordinates":[-83.0339126587,42.3178215027],"type":"Point"}
}