{
  "type": "Feature",
  "properties": {
    "addr:full":"Richmond BC V6V 2H9",
    "addr:postcode":"v6v 2h9",
    "iso:country":"CA",
    "sg:city":"Richmond",
    "sg:classifiers":[
        {
            "category":"Organizations",
            "subcategory":"Non-profit Organization",
            "type":"Services"
        }
    ],
    "sg:phone":"+1 604 270 9437",
    "sg:postcode":"V6V 2H9",
    "sg:province":"BC",
    "sg:tags":[
        "disability"
    ],
    "wof:name":"Bridgeport Enterprises",
    "wof:placetype":"venue"
},
  "geometry": {"coordinates":[-123.081757,49.185856],"type":"Point"}
}