{
  "type": "Feature",
  "properties": {
    "iso:country":"CA",
    "sg:address":"26 Main St #7",
    "sg:city":"Callander",
    "sg:classifiers":[
        {
            "category":"Restaurant",
            "type":"Food & Drink"
        }
    ],
    "sg:phone":"+1 705 752 3011",
    "sg:postcode":"P0H 1H0",
    "sg:province":"ON",
    "wof:name":"Phoenix Restaurant",
    "wof:placetype":"venue"
},
  "geometry": {"coordinates":[-79.3648300171,46.2229003906],"type":"Point"}
}