{
  "type": "Feature",
  "properties": {
    "addr:full":"368 Rue Sherbrooke O Montreal QC H3A 1B2",
    "addr:housenumber":"368",
    "addr:postcode":"h3a 1b2",
    "addr:street":"Rue Sherbrooke O",
    "iso:country":"CA",
    "sg:address":"368 Rue Sherbrooke O",
    "sg:city":"Montreal",
    "sg:classifiers":[
        {
            "category":"Shopping",
            "type":"Retail Goods"
        }
    ],
    "sg:phone":"+1 514 842 4411",
    "sg:postcode":"H3A 1B2",
    "sg:province":"QC",
    "sg:tags":[
        "supply",
        "exchange",
        "broker",
        "foreign",
        "coin",
        "dealer"
    ],
    "wof:name":"Maison D'Argent Inc",
    "wof:placetype":"venue"
},
  "geometry": {"coordinates":[-73.5674362183,45.5165138245],"type":"Point"}
}