{
  "type": "Feature",
  "properties": {
    "iso:country":"CA",
    "sg:address":"1564 Marine Dr",
    "sg:city":"West Vancouver",
    "sg:classifiers":[
        {
            "category":"Shopping",
            "subcategory":"Photographic Equipment",
            "type":"Retail Goods"
        }
    ],
    "sg:phone":"+1 604 926 5451",
    "sg:postcode":"V7V 1H8",
    "sg:province":"BC",
    "sg:tags":[
        "supply"
    ],
    "wof:name":"Kerrisdale Cameras Ltd",
    "wof:placetype":"venue"
},
  "geometry": {"coordinates":[-123.158126831,49.3283653259],"type":"Point"}
}