{
  "type": "Feature",
  "properties": {
    "addr:full":"Lake Newell Rd Brooks AB T1R 1C1",
    "addr:postcode":"t1r 1c1",
    "addr:street":"Lake Newell Rd",
    "iso:country":"CA",
    "sg:address":"Lake Newell Rd",
    "sg:city":"Brooks",
    "sg:classifiers":[
        {
            "category":"Wholesale",
            "subcategory":"Farm Supplies",
            "type":"Manufacturing & Wholesale Goods"
        }
    ],
    "sg:phone":"+1 403 362 2626",
    "sg:postcode":"T1R 1C1",
    "sg:province":"AB",
    "sg:tags":[
        "chemical",
        "agricultural",
        "grain",
        "elevator"
    ],
    "wof:name":"Agricore United",
    "wof:placetype":"venue"
},
  "geometry": {"coordinates":[-111.881057739,50.5742645264],"type":"Point"}
}