{
  "type": "Feature",
  "properties": {
    "addr:full":"1983 Sterling Pl Burlington ON L7P 2Y6",
    "addr:housenumber":"1983",
    "addr:postcode":"l7p 2y6",
    "addr:street":"Sterling Pl",
    "iso:country":"CA",
    "sg:address":"1983 Sterling Pl",
    "sg:city":"Burlington",
    "sg:classifiers":[
        {
            "category":"Wholesale",
            "subcategory":"Metals & Minerals",
            "type":"Manufacturing & Wholesale Goods"
        }
    ],
    "sg:phone":"+1 905 319 0443",
    "sg:postcode":"L7P 2Y6",
    "sg:province":"ON",
    "sg:tags":[
        "steel",
        "warehouse"
    ],
    "wof:name":"Bfa Enterprises Ltd",
    "wof:placetype":"venue"
},
  "geometry": {"coordinates":[-79.84625200000001,43.343475],"type":"Point"}
}