{
  "type": "Feature",
  "properties": {
    "iso:country":"CA",
    "sg:address":"50801 O'Byrne Rd",
    "sg:city":"Chilliwack",
    "sg:classifiers":[
        {
            "category":"Travel",
            "subcategory":"Campground",
            "type":"Entertainment"
        }
    ],
    "sg:phone":"+1 604 858 4443",
    "sg:postcode":"V4Z 1J3",
    "sg:province":"BC",
    "sg:tags":[
        "mobile",
        "home"
    ],
    "wof:name":"Chilliwack River Campground",
    "wof:placetype":"venue"
},
  "geometry": {"coordinates":[-121.951469421,49.1563110352],"type":"Point"}
}