{
  "type": "Feature",
  "properties": {
    "addr:full":"2318 Dufferin St York ON M6E 3S3",
    "addr:housenumber":"2318",
    "addr:postcode":"m6e 3s3",
    "addr:street":"Dufferin St",
    "iso:country":"CA",
    "sg:address":"2318 Dufferin St",
    "sg:city":"York",
    "sg:classifiers":[
        {
            "category":"Building & Trades",
            "subcategory":"Construction",
            "type":"Services"
        }
    ],
    "sg:phone":"+1 416 781 2866",
    "sg:postcode":"M6E 3S3",
    "sg:province":"ON",
    "sg:tags":[
        "general",
        "contractor"
    ],
    "wof:name":"Calitir Brothers Construction",
    "wof:placetype":"venue"
},
  "geometry": {"coordinates":[-79.44976043699999,43.6940498352],"type":"Point"}
}