{
  "type": "Feature",
  "properties": {
    "iso:country":"CA",
    "sg:address":"65 Pitt St",
    "sg:city":"Sydney",
    "sg:classifiers":[
        {
            "category":"Recreation",
            "type":"Entertainment"
        }
    ],
    "sg:phone":"+1 902 539 8665",
    "sg:postcode":"B1P 5X6",
    "sg:province":"NS",
    "sg:tags":[
        "parlor",
        "billiard"
    ],
    "wof:name":"Dooly's Billiard Room",
    "wof:placetype":"venue"
},
  "geometry": {"coordinates":[-60.1937484741,46.1394844055],"type":"Point"}
}