{
  "type": "Feature",
  "properties": {
    "addr:full":"Calgary AB T1Y 6M6",
    "addr:postcode":"t1y 6m6",
    "iso:country":"CA",
    "sg:city":"Calgary",
    "sg:classifiers":[
        {
            "category":"Restaurant",
            "type":"Food & Drink"
        }
    ],
    "sg:phone":"+1 403 291 6611",
    "sg:postcode":"T1Y 6M6",
    "sg:province":"AB",
    "wof:name":"Willy's Old Style Hamburgers",
    "wof:placetype":"venue"
},
  "geometry": {"coordinates":[-113.98468,51.081306],"type":"Point"}
}