{
  "type": "Feature",
  "properties": {
    "addr:full":"1081 Ironwood St Campbell River BC V9W 5L6",
    "addr:housenumber":"1081",
    "addr:postcode":"v9w 5l6",
    "addr:street":"Ironwood St",
    "iso:country":"CA",
    "sg:address":"1081 Ironwood St",
    "sg:city":"Campbell River",
    "sg:classifiers":[
        {
            "category":"Manufacturing",
            "subcategory":"Rubber & Plastics",
            "type":"Manufacturing & Wholesale Goods"
        }
    ],
    "sg:phone":"+1 250 286 1533",
    "sg:postcode":"V9W 5L6",
    "sg:province":"BC",
    "sg:tags":[
        "product"
    ],
    "wof:name":"Campbell River Glass Ltd",
    "wof:placetype":"venue"
},
  "geometry": {"coordinates":[-125.25479900000001,50.025848],"type":"Point"}
}