{
  "type": "Feature",
  "properties": {
    "addr:full":"192 Rue Saint-Jean-Baptiste Baie-Saint-Paul QC G3Z 1N3",
    "addr:housenumber":"192",
    "addr:postcode":"g3z 1n3",
    "addr:street":"Rue Saint-Jean-Baptiste",
    "iso:country":"CA",
    "sg:address":"192 Rue Saint-Jean-Baptiste",
    "sg:city":"Baie-Saint-Paul",
    "sg:classifiers":[
        {
            "category":"Health Services",
            "subcategory":"Chiropractor",
            "type":"Services"
        }
    ],
    "sg:phone":"+1 418 435 3783",
    "sg:postcode":"G3Z 1N3",
    "sg:province":"QC",
    "wof:name":"Centre Chiro-Sante Lepage",
    "wof:placetype":"venue"
},
  "geometry": {"coordinates":[-70.511719,47.446316],"type":"Point"}
}