{
  "type": "Feature",
  "properties": {
    "iso:country":"CA",
    "sg:address":"2505 43 Hwy",
    "sg:city":"Kemptville",
    "sg:classifiers":[
        {
            "category":"Health Services",
            "subcategory":"Health Practitioner",
            "type":"Services"
        }
    ],
    "sg:phone":"+1 613 258 6271",
    "sg:postcode":"K0G 1J0",
    "sg:province":"ON",
    "sg:tags":[
        "correction",
        "laser",
        "vision"
    ],
    "wof:name":"Metris Canada",
    "wof:placetype":"venue"
},
  "geometry": {"coordinates":[-75.666519165,45.0144767761],"type":"Point"}
}