{
  "type": "Feature",
  "properties": {
    "addr:full":"195 Rexleigh Dr East York ON M4B 2N8",
    "addr:housenumber":"195",
    "addr:postcode":"m4b 2n8",
    "addr:street":"Rexleigh Dr",
    "iso:country":"CA",
    "sg:address":"195 Rexleigh Dr",
    "sg:city":"East York",
    "sg:classifiers":[
        {
            "category":"Real Estate",
            "subcategory":"Real Estate Operator",
            "type":"Services"
        }
    ],
    "sg:phone":"+1 416 759 2731",
    "sg:postcode":"M4B 2N8",
    "sg:province":"ON",
    "sg:tags":[
        "apartment"
    ],
    "wof:name":"Rexleigh Gardens Ltd",
    "wof:placetype":"venue"
},
  "geometry": {"coordinates":[-79.305573,43.704796],"type":"Point"}
}