{
  "type": "Feature",
  "properties": {
    "iso:country":"CA",
    "sg:city":"Hobbema",
    "sg:classifiers":[
        {
            "category":"Food & Beverages",
            "subcategory":"Groceries & Convenience Stores",
            "type":"Retail Goods"
        }
    ],
    "sg:phone":"+1 780 585 4200",
    "sg:postcode":"T0C 1N0",
    "sg:province":"AB",
    "sg:tags":[
        "grocer"
    ],
    "wof:name":"Bow N Arrow Convenience Store",
    "wof:placetype":"venue"
},
  "geometry": {"coordinates":[-113.446144104,52.8340835571],"type":"Point"}
}