{
  "type": "Feature",
  "properties": {
    "addr:full":"396 Broadway Winnipeg MB R3C 0V6",
    "addr:housenumber":"396",
    "addr:postcode":"r3c 0v6",
    "addr:street":"Broadway",
    "iso:country":"CA",
    "sg:address":"396 Broadway",
    "sg:city":"Winnipeg",
    "sg:classifiers":[
        {
            "category":"Organizations",
            "subcategory":"Religious Organization",
            "type":"Services"
        }
    ],
    "sg:phone":"+1 204 943 2658",
    "sg:postcode":"R3C 0V6",
    "sg:province":"MB",
    "sg:tags":[
        "church"
    ],
    "wof:name":"Broadway Disciples United Chr",
    "wof:placetype":"venue"
},
  "geometry": {"coordinates":[-97.1446,49.886425],"type":"Point"}
}