{
  "type": "Feature",
  "properties": {
    "addr:full":"71 Rue D'Auteuil Quebec QC G1R 4C3",
    "addr:housenumber":"71",
    "addr:postcode":"g1r 4c3",
    "addr:street":"Rue D'Auteuil",
    "iso:country":"CA",
    "sg:address":"71 Rue D'Auteuil",
    "sg:city":"Quebec",
    "sg:classifiers":[
        {
            "category":"Restaurant",
            "type":"Food & Drink"
        }
    ],
    "sg:phone":"+1 418 694 0232",
    "sg:postcode":"G1R 4C3",
    "sg:province":"QC",
    "sg:tags":[
        "inn"
    ],
    "wof:name":"Auberge DE LA Chouette",
    "wof:placetype":"venue"
},
  "geometry": {"coordinates":[-71.2119674683,46.8119697571],"type":"Point"}
}