{
  "type": "Feature",
  "properties": {
    "addr:full":"630 Dinner Bay Rd Mayne BC V0N 2J0",
    "addr:housenumber":"630",
    "addr:postcode":"v0n 2j0",
    "addr:street":"Dinner Bay Rd",
    "iso:country":"CA",
    "sg:address":"630 Dinner Bay Rd",
    "sg:city":"Mayne",
    "sg:classifiers":[
        {
            "category":"Professional",
            "subcategory":"Business Services",
            "type":"Services"
        }
    ],
    "sg:phone":"+1 250 539 5074",
    "sg:postcode":"V0N 2J0",
    "sg:province":"BC",
    "sg:tags":[
        "reservation",
        "motel",
        "hotel"
    ],
    "wof:name":"Oceanwood Country Inn",
    "wof:placetype":"venue"
},
  "geometry": {"coordinates":[-123.315574646,48.8335418701],"type":"Point"}
}