{
  "type": "Feature",
  "properties": {
    "addr:full":"1250 Brant St Burlington ON L7P 1X8",
    "addr:housenumber":"1250",
    "addr:postcode":"l7p 1x8",
    "addr:street":"Brant St",
    "iso:country":"CA",
    "sg:address":"1250 Brant St",
    "sg:city":"Burlington",
    "sg:classifiers":[
        {
            "category":"Shopping",
            "subcategory":"Stationery & Office Supplies",
            "type":"Retail Goods"
        }
    ],
    "sg:phone":"+1 905 319 8449",
    "sg:postcode":"L7P 1X8",
    "sg:province":"ON",
    "sg:tags":[
        "equipment",
        "computer",
        "dealer"
    ],
    "wof:name":"Office Depot",
    "wof:placetype":"venue"
},
  "geometry": {"coordinates":[-79.8267211914,43.3448066711],"type":"Point"}
}