{
  "type": "Feature",
  "properties": {
    "addr:full":"162 132 Rte W Saint-Omer QC G0C 2Z0",
    "addr:housenumber":"132",
    "addr:postcode":"g0c 2z0",
    "addr:street":"Rte W Saint-Omer",
    "iso:country":"CA",
    "sg:address":"162 132 Rte W",
    "sg:city":"Saint-Omer",
    "sg:classifiers":[
        {
            "category":"Shopping",
            "type":"Retail Goods"
        }
    ],
    "sg:phone":"+1 418 364 7787",
    "sg:postcode":"G0C 2Z0",
    "sg:province":"QC",
    "sg:tags":[
        "pet",
        "food",
        "supply"
    ],
    "wof:name":"Sir-Ali Inc",
    "wof:placetype":"venue"
},
  "geometry": {"coordinates":[-66.20742799999999,48.108437],"type":"Point"}
}