{
  "type": "Feature",
  "properties": {
    "addr:full":"36 Arbor Dr Brantford ON N3P 1Z4",
    "addr:housenumber":"36",
    "addr:postcode":"n3p 1z4",
    "addr:street":"Arbor Dr",
    "iso:country":"CA",
    "sg:address":"36 Arbor Dr",
    "sg:city":"Brantford",
    "sg:classifiers":[
        {
            "category":"Personal",
            "subcategory":"Beauty Salon",
            "type":"Services"
        }
    ],
    "sg:phone":"+1 519 759 4440",
    "sg:postcode":"N3P 1Z4",
    "sg:province":"ON",
    "wof:name":"Flair Hair Fashions",
    "wof:placetype":"venue"
},
  "geometry": {"coordinates":[-80.236664,43.192413],"type":"Point"}
}