{
  "type": "Feature",
  "properties": {
    "iso:country":"CA",
    "sg:address":"1240 Old Sackville Rd",
    "sg:city":"Middle Sackville",
    "sg:classifiers":[
        {
            "category":"Organizations",
            "subcategory":"Religious Organization",
            "type":"Services"
        }
    ],
    "sg:phone":"+1 902 865 3681",
    "sg:postcode":"B4E 3A6",
    "sg:province":"NS",
    "sg:tags":[
        "church"
    ],
    "wof:name":"Sackville United Baptist Chr",
    "wof:placetype":"venue"
},
  "geometry": {"coordinates":[-63.7152862549,44.7830581665],"type":"Point"}
}