{
  "type": "Feature",
  "properties": {
    "addr:full":"5920 Boul Industriel Montreal-Nord QC H1G 3J2",
    "addr:housenumber":"5920",
    "addr:postcode":"3j2",
    "addr:street":"Boul Industriel;H1G",
    "iso:country":"CA",
    "sg:address":"5920 Boul Industriel",
    "sg:city":"Montreal-Nord",
    "sg:classifiers":[
        {
            "category":"Retail",
            "subcategory":"Auto Repair",
            "type":"Services"
        }
    ],
    "sg:phone":"+1 514 325 2160",
    "sg:postcode":"H1G 3J2",
    "sg:province":"QC",
    "sg:tags":[
        "body",
        "automobile",
        "painting"
    ],
    "wof:name":"Garage Mj Contach",
    "wof:placetype":"venue"
},
  "geometry": {"coordinates":[-73.614105,45.603188],"type":"Point"}
}