{
  "type": "Feature",
  "properties": {
    "addr:full":"390 Boul Bourque Omerville QC J1X 4G1",
    "addr:housenumber":"390",
    "addr:postcode":"j1x 4g1",
    "addr:street":"Boul Bourque",
    "iso:country":"CA",
    "sg:address":"390 Boul Bourque",
    "sg:city":"Omerville",
    "sg:classifiers":[
        {
            "category":"Home & Garden",
            "subcategory":"Building Materials",
            "type":"Retail Goods"
        }
    ],
    "sg:phone":"+1 819 868 4022",
    "sg:postcode":"J1X 4G1",
    "sg:province":"QC",
    "sg:tags":[
        "glass",
        "window",
        "plate"
    ],
    "wof:name":"Pare-Brise Orford",
    "wof:placetype":"venue"
},
  "geometry": {"coordinates":[-72.1117553711,45.2903060913],"type":"Point"}
}