{
  "type": "Feature",
  "properties": {
    "addr:full":"Montreal QC H3A 2Z2",
    "addr:postcode":"h3a 2z2",
    "iso:country":"CA",
    "sg:city":"Montreal",
    "sg:classifiers":[
        {
            "category":"Professional",
            "subcategory":"Lawyer & Legal Services",
            "type":"Services"
        }
    ],
    "sg:phone":"+1 514 284 0426",
    "sg:postcode":"H3A 2Z2",
    "sg:province":"QC",
    "sg:tags":[
        "attorney"
    ],
    "wof:name":"Lacoste Langevin",
    "wof:placetype":"venue"
},
  "geometry": {"coordinates":[-73.5735244751,45.5022354126],"type":"Point"}
}