{
  "type": "Feature",
  "properties": {
    "addr:full":"803 Switzer Dr Hinton AB T7V 1V1",
    "addr:housenumber":"803",
    "addr:postcode":"t7v 1v1",
    "addr:street":"Switzer Dr",
    "iso:country":"CA",
    "sg:address":"803 Switzer Dr",
    "sg:city":"Hinton",
    "sg:classifiers":[
        {
            "category":"Government",
            "subcategory":"Office",
            "type":"Public Place"
        }
    ],
    "sg:phone":"+1 780 865 6055",
    "sg:postcode":"T7V 1V1",
    "sg:province":"AB",
    "sg:tags":[
        "village"
    ],
    "wof:name":"Hinton Arts & Culture",
    "wof:placetype":"venue"
},
  "geometry": {"coordinates":[-117.564125061,53.4121704102],"type":"Point"}
}