{
  "type": "Feature",
  "properties": {
    "iso:country":"CA",
    "sg:address":"9165 Rue Airlie",
    "sg:city":"Lasalle",
    "sg:classifiers":[
        {
            "category":"Food & Beverages",
            "subcategory":"Bakery",
            "type":"Retail Goods"
        }
    ],
    "sg:phone":"+1 514 364 2442",
    "sg:postcode":"H8R 2A7",
    "sg:province":"QC",
    "sg:tags":[
        "baker"
    ],
    "wof:name":"Boulangerie & Patisserie Bruno",
    "wof:placetype":"venue"
},
  "geometry": {"coordinates":[-73.6363601685,45.4220237732],"type":"Point"}
}