{
  "type": "Feature",
  "properties": {
    "addr:full":"Nouvelle QC G0C 2E0",
    "addr:postcode":"g0c 2e0",
    "iso:country":"CA",
    "sg:city":"Nouvelle",
    "sg:classifiers":[
        {
            "category":"Arena",
            "subcategory":"Sports Club",
            "type":"Entertainment"
        }
    ],
    "sg:phone":"+1 418 794 2763",
    "sg:postcode":"G0C 2E0",
    "sg:province":"QC",
    "sg:tags":[
        "athletic",
        "fields",
        "stadium"
    ],
    "wof:name":"Associations Sportive Nouvelle",
    "wof:placetype":"venue"
},
  "geometry": {"coordinates":[-66.311333,48.139019],"type":"Point"}
}