{
  "type": "Feature",
  "properties": {
    "iso:country":"CA",
    "sg:city":"Woodbridge",
    "sg:classifiers":[
        {
            "category":"Professional",
            "subcategory":"Lawyer & Legal Services",
            "type":"Services"
        }
    ],
    "sg:phone":"+1 416 213 7450",
    "sg:postcode":"L4L 4V9",
    "sg:province":"ON",
    "sg:tags":[
        "attorney"
    ],
    "wof:name":"Pascuzzi, Aurelio",
    "wof:placetype":"venue"
},
  "geometry": {"coordinates":[-79.55104064939999,43.7694854736],"type":"Point"}
}