{
  "type": "Feature",
  "properties": {
    "addr:full":"Saint-Constant QC J5A 2J5",
    "addr:postcode":"j5a 2j5",
    "iso:country":"CA",
    "sg:city":"Saint-Constant",
    "sg:classifiers":[
        {
            "category":"Shopping",
            "subcategory":"Pharmacy",
            "type":"Retail Goods"
        }
    ],
    "sg:phone":"+1 450 635 8383",
    "sg:postcode":"J5A 2J5",
    "sg:province":"QC",
    "wof:name":"Pharmacie Luc Dube",
    "wof:placetype":"venue"
},
  "geometry": {"coordinates":[-73.595978,45.386765],"type":"Point"}
}