{
  "type": "Feature",
  "properties": {
    "addr:full":"927 Ch Knowlton West Brome QC J0E 2P0",
    "addr:housenumber":"927",
    "addr:postcode":"j0e 2p0",
    "addr:street":"Ch Knowlton West Brome",
    "iso:country":"CA",
    "sg:address":"927 Ch Knowlton",
    "sg:city":"West Brome",
    "sg:classifiers":[
        {
            "category":"Real Estate",
            "subcategory":"Real Estate Agent",
            "type":"Services"
        }
    ],
    "sg:phone":"+1 450 263 1550",
    "sg:postcode":"J0E 2P0",
    "sg:province":"QC",
    "wof:name":"Maitre Mireille",
    "wof:placetype":"venue"
},
  "geometry": {"coordinates":[-72.62799835209999,45.2046661377],"type":"Point"}
}