{
  "type": "Feature",
  "properties": {
    "addr:full":"763 Carrier St Kamloops BC V2H 1G1",
    "addr:housenumber":"763",
    "addr:postcode":"bc v2h 1g1",
    "addr:street":"Carrier St",
    "iso:country":"CA",
    "sg:address":"763 Carrier St",
    "sg:city":"Kamloops",
    "sg:classifiers":[
        {
            "category":"Building & Trades",
            "subcategory":"Construction",
            "type":"Services"
        }
    ],
    "sg:phone":"+1 250 828 2999",
    "sg:postcode":"V2H 1G1",
    "sg:province":"BC",
    "sg:tags":[
        "masonry",
        "contractor"
    ],
    "wof:name":"Nicola Valley Masonry Ltd",
    "wof:placetype":"venue"
},
  "geometry": {"coordinates":[-120.317268372,50.6850204468],"type":"Point"}
}