{
  "type": "Feature",
  "properties": {
    "addr:full":"12 Clifton Downs Rd Hamilton ON L9C 2P2",
    "addr:housenumber":"12",
    "addr:postcode":"l9c 2p2",
    "addr:street":"Clifton Downs Rd",
    "iso:country":"CA",
    "sg:address":"12 Clifton Downs Rd",
    "sg:city":"Hamilton",
    "sg:classifiers":[
        {
            "category":"Building & Trades",
            "subcategory":"Construction",
            "type":"Services"
        }
    ],
    "sg:phone":"+1 905 574 4918",
    "sg:postcode":"L9C 2P2",
    "sg:province":"ON",
    "sg:tags":[
        "painter"
    ],
    "wof:name":"Artisan 2000 Inc",
    "wof:placetype":"venue"
},
  "geometry": {"coordinates":[-79.9044036865,43.230140686],"type":"Point"}
}