{
  "type": "Feature",
  "properties": {
    "iso:country":"CA",
    "sg:address":"160 Courtland Ave E",
    "sg:city":"Kitchener",
    "sg:classifiers":[
        {
            "category":"Education",
            "subcategory":"School",
            "type":"Public Place"
        }
    ],
    "sg:phone":"+1 519 743 3005",
    "sg:postcode":"N2G 2V3",
    "sg:province":"ON",
    "wof:name":"St Louis Adult Learning Ctr",
    "wof:placetype":"venue"
},
  "geometry": {"coordinates":[-80.486847,43.442757],"type":"Point"}
}