{
  "type": "Feature",
  "properties": {
    "addr:full":"3292 Broadway E Vancouver BC V5M 1Z8",
    "addr:housenumber":"3292",
    "addr:postcode":"v5m 1z8",
    "addr:street":"Broadway E",
    "iso:country":"CA",
    "sg:address":"3292 Broadway E",
    "sg:city":"Vancouver",
    "sg:classifiers":[
        {
            "category":"Social Services",
            "type":"Services"
        }
    ],
    "sg:phone":"+1 604 873 8139",
    "sg:postcode":"V5M 1Z8",
    "sg:province":"BC",
    "sg:tags":[
        "organization",
        "welfare"
    ],
    "wof:name":"Learning Disabilities Assn",
    "wof:placetype":"venue"
},
  "geometry": {"coordinates":[-123.03402699999999,49.261707],"type":"Point"}
}