{
  "type": "Feature",
  "properties": {
    "addr:full":"Toronto ON M5V 1A1",
    "addr:postcode":"m5v 1a1",
    "iso:country":"CA",
    "sg:city":"Toronto",
    "sg:classifiers":[
        {
            "category":"Building & Trades",
            "subcategory":"Equipment Rental",
            "type":"Services"
        }
    ],
    "sg:phone":"+1 416 203 6242",
    "sg:postcode":"M5V 1A1",
    "sg:province":"ON",
    "sg:tags":[
        "aircraft",
        "leasing",
        "charter",
        "school"
    ],
    "wof:name":"Island Air Flight School Inc",
    "wof:placetype":"venue"
},
  "geometry": {"coordinates":[-79.481888,43.669525],"type":"Point"}
}