{
  "type": "Feature",
  "properties": {
    "addr:full":"424 1st Ave Regina SK S4N 4Z2",
    "addr:housenumber":"424",
    "addr:postcode":"s4n 4z2",
    "addr:street":"1St Ave",
    "iso:country":"CA",
    "sg:address":"424 1st Ave",
    "sg:city":"Regina",
    "sg:classifiers":[
        {
            "category":"Real Estate",
            "subcategory":"Real Estate Agent",
            "type":"Services"
        }
    ],
    "sg:phone":"+1 306 721 5161",
    "sg:postcode":"S4N 4Z2",
    "sg:province":"SK",
    "sg:tags":[
        "propane",
        "management",
        "gas"
    ],
    "wof:name":"Mobile Propane Svc Inc",
    "wof:placetype":"venue"
},
  "geometry": {"coordinates":[-104.585906982,50.4678115845],"type":"Point"}
}