{
  "type": "Feature",
  "properties": {
    "addr:full":"100 Eglinton Sq Scarborough ON M1L 2K1",
    "addr:housenumber":"100",
    "addr:postcode":"m1l 2k1",
    "addr:street":"Eglinton Sq",
    "iso:country":"CA",
    "sg:address":"100 Eglinton Sq",
    "sg:city":"Scarborough",
    "sg:classifiers":[
        {
            "category":"Shopping",
            "subcategory":"Jewelry",
            "type":"Retail Goods"
        }
    ],
    "sg:phone":"+1 416 752 0808",
    "sg:postcode":"M1L 2K1",
    "sg:province":"ON",
    "sg:tags":[
        "jeweler"
    ],
    "wof:name":"Ardene",
    "wof:placetype":"venue"
},
  "geometry": {"coordinates":[-79.300957,43.723927],"type":"Point"}
}