{
  "type": "Feature",
  "properties": {
    "addr:full":"1290 Av Van Horne Outremont QC H2V 4S2",
    "addr:housenumber":"1290",
    "addr:postcode":"h2v 4s2",
    "addr:street":"Av Van Horne",
    "iso:country":"CA",
    "sg:address":"1290 Av Van Horne",
    "sg:city":"Outremont",
    "sg:classifiers":[
        {
            "category":"Health Services",
            "subcategory":"Health Practitioner",
            "type":"Services"
        }
    ],
    "sg:phone":"+1 514 278 1528",
    "sg:postcode":"H2V 4S2",
    "sg:province":"QC",
    "sg:tags":[
        "psychologist"
    ],
    "wof:name":"Desjardins, Danielle",
    "wof:placetype":"venue"
},
  "geometry": {"coordinates":[-73.613838,45.52142],"type":"Point"}
}