{
  "type": "Feature",
  "properties": {
    "addr:full":"3131 Rue Hochelaga Montreal QC H1W 1G3",
    "addr:housenumber":"3131",
    "addr:postcode":"h1w 1g3",
    "addr:street":"Rue Hochelaga",
    "iso:country":"CA",
    "sg:address":"3131 Rue Hochelaga",
    "sg:city":"Montreal",
    "sg:classifiers":[
        {
            "category":"Food & Beverages",
            "subcategory":"Groceries & Convenience Stores",
            "type":"Retail Goods"
        }
    ],
    "sg:phone":"+1 514 598 1391",
    "sg:postcode":"H1W 1G3",
    "sg:province":"QC",
    "wof:name":"Depanneur Sopia",
    "wof:placetype":"venue"
},
  "geometry": {"coordinates":[-73.554581,45.541992],"type":"Point"}
}