{
  "type": "Feature",
  "properties": {
    "addr:full":"770 Browns Line Etobicoke ON M8W 3W2",
    "addr:housenumber":"770",
    "addr:postcode":"m8w 3w2",
    "addr:street":"Browns Line",
    "iso:country":"CA",
    "sg:address":"770 Browns Line",
    "sg:city":"Etobicoke",
    "sg:classifiers":[
        {
            "category":"Real Estate",
            "subcategory":"Architect",
            "type":"Services"
        }
    ],
    "sg:phone":"+1 416 252 5679",
    "sg:postcode":"M8W 3W2",
    "sg:province":"ON",
    "wof:name":"Guthrie Muscovitch Architects",
    "wof:placetype":"venue"
},
  "geometry": {"coordinates":[-79.548225,43.608372],"type":"Point"}
}