{
  "type": "Feature",
  "properties": {
    "addr:full":"20 Mayfield Crt St Catharines ON L2S 3X7",
    "addr:housenumber":"20",
    "addr:postcode":"l2s 3x7",
    "addr:street":"Mayfield Crt",
    "iso:country":"CA",
    "sg:address":"20 Mayfield Crt",
    "sg:city":"St Catharines",
    "sg:classifiers":[
        {
            "category":"Building & Trades",
            "subcategory":"Construction",
            "type":"Services"
        }
    ],
    "sg:phone":"+1 905 688 6340",
    "sg:postcode":"L2S 3X7",
    "sg:province":"ON",
    "sg:tags":[
        "home",
        "contractor",
        "improvement"
    ],
    "wof:name":"Lakewood Homes",
    "wof:placetype":"venue"
},
  "geometry": {"coordinates":[-79.273743,43.161068],"type":"Point"}
}