{
  "type": "Feature",
  "properties": {
    "addr:full":"4208 50 St Cold Lake AB T9M 1S6",
    "addr:housenumber":"4208",
    "addr:postcode":"t9m 1s6",
    "addr:street":"50 St",
    "iso:country":"CA",
    "sg:address":"4208 50 St",
    "sg:city":"Cold Lake",
    "sg:classifiers":[
        {
            "category":"Restaurant",
            "type":"Food & Drink"
        }
    ],
    "sg:phone":"+1 780 594 2222",
    "sg:postcode":"T9M 1S6",
    "sg:province":"AB",
    "wof:name":"Mc Donald's",
    "wof:placetype":"venue"
},
  "geometry": {"coordinates":[-110.20562,54.406094],"type":"Point"}
}