{
  "type": "Feature",
  "properties": {
    "addr:full":"109 Chain Lake Dr Halifax NS B3S 1B3",
    "addr:housenumber":"109",
    "addr:postcode":"b3s 1b3",
    "addr:street":"Chain Lake Dr",
    "iso:country":"CA",
    "sg:address":"109 Chain Lake Dr",
    "sg:city":"Halifax",
    "sg:classifiers":[
        {
            "category":"Organizations",
            "subcategory":"Professional Association",
            "type":"Services"
        }
    ],
    "sg:phone":"+1 902 450 1433",
    "sg:postcode":"B3S 1B3",
    "sg:province":"NS",
    "wof:name":"Nova Scotia Roadbuilders Assn",
    "wof:placetype":"venue"
},
  "geometry": {"coordinates":[-63.66338,44.638138],"type":"Point"}
}