{
  "type": "Feature",
  "properties": {
    "iso:country":"CA",
    "sg:address":"18 Albert St E",
    "sg:city":"Thorold",
    "sg:classifiers":[
        {
            "category":"Professional",
            "subcategory":"Lawyer & Legal Services",
            "type":"Services"
        }
    ],
    "sg:phone":"+1 905 227 3777",
    "sg:postcode":"L2V 1P1",
    "sg:province":"ON",
    "sg:tags":[
        "attorney"
    ],
    "wof:name":"Young Mc Namara",
    "wof:placetype":"venue"
},
  "geometry": {"coordinates":[-79.1976013184,43.1250801086],"type":"Point"}
}