{
  "type": "Feature",
  "properties": {
    "addr:full":"1003 Gough Rd Carstairs AB T0M 0N0",
    "addr:housenumber":"1003",
    "addr:postcode":"t0m 0n0",
    "addr:street":"Gough Rd",
    "iso:country":"CA",
    "sg:address":"1003 Gough Rd",
    "sg:city":"Carstairs",
    "sg:classifiers":[
        {
            "category":"Real Estate",
            "subcategory":"Developer",
            "type":"Services"
        }
    ],
    "sg:phone":"+1 403 337 2290",
    "sg:postcode":"T0M 0N0",
    "sg:province":"AB",
    "sg:tags":[
        "company",
        "land"
    ],
    "wof:name":"Parkview Estates Ltd",
    "wof:placetype":"venue"
},
  "geometry": {"coordinates":[-114.099250794,51.5619888306],"type":"Point"}
}