{
  "type": "Feature",
  "properties": {
    "addr:full":"545 Mount Pleasant Rd Toronto ON M4S 2M5",
    "addr:housenumber":"545",
    "addr:postcode":"m4s 2m5",
    "addr:street":"Mount Pleasant Rd",
    "iso:country":"CA",
    "sg:address":"545 Mount Pleasant Rd",
    "sg:city":"Toronto",
    "sg:classifiers":[
        {
            "category":"Shopping",
            "subcategory":"Computers & Home Electronics",
            "type":"Retail Goods"
        }
    ],
    "sg:phone":"+1 416 482 2922",
    "sg:postcode":"M4S 2M5",
    "sg:province":"ON",
    "sg:tags":[
        "television",
        "radio",
        "system"
    ],
    "wof:name":"Mount Pleasant Stereo",
    "wof:placetype":"venue"
},
  "geometry": {"coordinates":[-79.387711,43.70277],"type":"Point"}
}