{
  "type": "Feature",
  "properties": {
    "addr:full":"General Delivery Cadotte Lake AB T0H 0N0",
    "addr:postcode":"t0h 0n0",
    "iso:country":"CA",
    "sg:address":"General Delivery",
    "sg:city":"Cadotte Lake",
    "sg:classifiers":[
        {
            "category":"Education",
            "subcategory":"Special Training",
            "type":"Public Place"
        }
    ],
    "sg:phone":"+1 780 629 3934",
    "sg:postcode":"T0H 0N0",
    "sg:province":"AB",
    "sg:tags":[
        "reading",
        "instruction",
        "improvement"
    ],
    "wof:name":"Northern Lakes College",
    "wof:placetype":"venue"
},
  "geometry": {"coordinates":[-116.37188,56.468094],"type":"Point"}
}