{
  "type": "Feature",
  "properties": {
    "addr:full":"Langley BC V1M 2G5",
    "addr:postcode":"v1m 2g5",
    "iso:country":"CA",
    "sg:city":"Langley",
    "sg:classifiers":[
        {
            "category":"Personal",
            "subcategory":"Beauty Salon",
            "type":"Services"
        }
    ],
    "sg:phone":"+1 604 882 5116",
    "sg:postcode":"V1M 2G5",
    "sg:province":"BC",
    "wof:name":"Fancy Cuts",
    "wof:placetype":"venue"
},
  "geometry": {"coordinates":[-122.633492,49.162449],"type":"Point"}
}