{
  "type": "Feature",
  "properties": {
    "addr:full":"112 Boulder Cres Canmore AB T1W 1L2",
    "addr:housenumber":"112",
    "addr:postcode":"t1w 1l2",
    "addr:street":"Boulder Cres",
    "iso:country":"CA",
    "sg:address":"112 Boulder Cres",
    "sg:city":"Canmore",
    "sg:classifiers":[
        {
            "category":"Retail",
            "subcategory":"Auto Repair",
            "type":"Services"
        }
    ],
    "sg:phone":"+1 403 678 5699",
    "sg:postcode":"T1W 1L2",
    "sg:province":"AB",
    "sg:tags":[
        "repairing",
        "automobile"
    ],
    "wof:name":"Triple NC Auto Ltd",
    "wof:placetype":"venue"
},
  "geometry": {"coordinates":[-115.324135,51.076744],"type":"Point"}
}