{
  "type": "Feature",
  "properties": {
    "addr:full":"14 Rue Principale N Windsor QC J1S 2C2",
    "addr:housenumber":"14",
    "addr:postcode":"j1s 2c2",
    "addr:street":"Rue Principale N",
    "iso:country":"CA",
    "sg:address":"14 Rue Principale N",
    "sg:city":"Windsor",
    "sg:classifiers":[
        {
            "category":"Food & Beverages",
            "subcategory":"Groceries & Convenience Stores",
            "type":"Retail Goods"
        }
    ],
    "sg:phone":"+1 819 845 4555",
    "sg:postcode":"J1S 2C2",
    "sg:province":"QC",
    "sg:tags":[
        "grocer"
    ],
    "wof:name":"Metro Couture",
    "wof:placetype":"venue"
},
  "geometry": {"coordinates":[-72.0051651001,45.5661277771],"type":"Point"}
}