{
  "type": "Feature",
  "properties": {
    "iso:country":"CA",
    "sg:address":"94 Hastings St N",
    "sg:city":"Bancroft",
    "sg:classifiers":[
        {
            "category":"Autos & Motor Vehicles",
            "subcategory":"Automobile Sales",
            "type":"Retail Goods"
        }
    ],
    "sg:phone":"+1 613 332 1410",
    "sg:postcode":"K0L 1C0",
    "sg:province":"ON",
    "sg:tags":[
        "car",
        "dealer"
    ],
    "wof:name":"Vance Motors Ltd",
    "wof:placetype":"venue"
},
  "geometry": {"coordinates":[-77.8550567627,45.0594673157],"type":"Point"}
}