{
  "type": "Feature",
  "properties": {
    "addr:full":"Edmonton AB T6J 2W4",
    "addr:postcode":"t6j 2w4",
    "iso:country":"CA",
    "sg:city":"Edmonton",
    "sg:classifiers":[
        {
            "category":"Health Services",
            "subcategory":"Medical Lab",
            "type":"Services"
        }
    ],
    "sg:phone":"+1 780 435 3246",
    "sg:postcode":"T6J 2W4",
    "sg:province":"AB",
    "sg:tags":[
        "laboratory"
    ],
    "wof:name":"Brown & Hone Orthodontic Lab",
    "wof:placetype":"venue"
},
  "geometry": {"coordinates":[-113.54067999999999,53.472546],"type":"Point"}
}