{
  "type": "Feature",
  "properties": {
    "addr:full":"4913 50 St Killam AB T0B 2L0",
    "addr:housenumber":"4913",
    "addr:postcode":"t0b 2l0",
    "addr:street":"50 St",
    "iso:country":"CA",
    "sg:address":"4913 50 St",
    "sg:city":"Killam",
    "sg:classifiers":[
        {
            "category":"Health Services",
            "subcategory":"Optometrist",
            "type":"Services"
        }
    ],
    "sg:phone":"+1 780 385 3133",
    "sg:postcode":"T0B 2L0",
    "sg:province":"AB",
    "wof:name":"Family Eyecare Clinic",
    "wof:placetype":"venue"
},
  "geometry": {"coordinates":[-111.855362,52.79015],"type":"Point"}
}