{
  "type": "Feature",
  "properties": {
    "iso:country":"CA",
    "sg:address":"395 Boul Labbe N",
    "sg:city":"Victoriaville",
    "sg:classifiers":[
        {
            "category":"Manufacturing",
            "subcategory":"Food",
            "type":"Manufacturing & Wholesale Goods"
        }
    ],
    "sg:phone":"+1 819 752 5050",
    "sg:postcode":"G6P 1B1",
    "sg:province":"QC",
    "sg:tags":[
        "brewer"
    ],
    "wof:name":"Brasserie Labatt Ltee",
    "wof:placetype":"venue"
},
  "geometry": {"coordinates":[-71.9572677612,46.0725135803],"type":"Point"}
}