{
  "type": "Feature",
  "properties": {
    "addr:full":"2957 Rue Belanger Montreal QC H1Y 3G4",
    "addr:housenumber":"2957",
    "addr:postcode":"h1y 3g4",
    "addr:street":"Rue Belanger",
    "iso:country":"CA",
    "sg:address":"2957 Rue Belanger",
    "sg:city":"Montreal",
    "sg:classifiers":[
        {
            "category":"Real Estate",
            "subcategory":"Real Estate Agent",
            "type":"Services"
        }
    ],
    "sg:phone":"+1 514 727 7575",
    "sg:postcode":"H1Y 3G4",
    "sg:province":"QC",
    "wof:name":"Groupe Sutton Acces",
    "wof:placetype":"venue"
},
  "geometry": {"coordinates":[-73.59619903559999,45.5550193787],"type":"Point"}
}