{
  "type": "Feature",
  "properties": {
    "addr:full":"550 Ch Principal Saint-Joseph-Du-Lac QC J0N 1M0",
    "addr:housenumber":"550",
    "addr:postcode":"j0n 1m0",
    "addr:street":"Ch Principal",
    "iso:country":"CA",
    "sg:address":"550 Ch Principal",
    "sg:city":"Saint-Joseph-Du-Lac",
    "sg:classifiers":[
        {
            "category":"Manufacturing",
            "subcategory":"Tools & Machinery",
            "type":"Manufacturing & Wholesale Goods"
        }
    ],
    "sg:phone":"+1 450 491 1739",
    "sg:postcode":"J0N 1M0",
    "sg:province":"QC",
    "sg:tags":[
        "irrigation",
        "system",
        "nurseryman"
    ],
    "wof:name":"Bouchard Fils & Fille Inc",
    "wof:placetype":"venue"
},
  "geometry": {"coordinates":[-73.9917831421,45.5231056213],"type":"Point"}
}