{
  "type": "Feature",
  "properties": {
    "addr:full":"1931 Chainsaw Ave Gray Creek BC V0B 1S0",
    "addr:housenumber":"1931",
    "addr:postcode":"bc v0b 1s0",
    "addr:street":"Chainsaw Ave Gray",
    "iso:country":"CA",
    "sg:address":"1931 Chainsaw Ave",
    "sg:city":"Gray Creek",
    "sg:classifiers":[
        {
            "category":"Travel",
            "subcategory":"Campground",
            "type":"Entertainment"
        }
    ],
    "sg:phone":"+1 250 227 9330",
    "sg:postcode":"V0B 1S0",
    "sg:province":"BC",
    "wof:name":"Gray Creek Auto Camp",
    "wof:placetype":"venue"
},
  "geometry": {"coordinates":[-116.788567,49.621647],"type":"Point"}
}