{
  "type": "Feature",
  "properties": {
    "addr:full":"546 Boul Laure Sept-Iles QC G4R 1X7",
    "addr:housenumber":"546",
    "addr:postcode":"g4r 1x7",
    "addr:street":"Boul Laure Sept-Iles",
    "iso:country":"CA",
    "sg:address":"546 Boul Laure",
    "sg:city":"Sept-Iles",
    "sg:classifiers":[
        {
            "category":"Communications",
            "subcategory":"Film & Video Production",
            "type":"Services"
        }
    ],
    "sg:phone":"+1 418 962 0100",
    "sg:postcode":"G4R 1X7",
    "sg:province":"QC",
    "sg:tags":[
        "picture",
        "producer",
        "entertainment",
        "motion",
        "bureau",
        "studio"
    ],
    "wof:name":"Salle DE Spectacle DE Sept-Ile",
    "wof:placetype":"venue"
},
  "geometry": {"coordinates":[-66.376846,50.214451],"type":"Point"}
}