{
  "type": "Feature",
  "properties": {
    "addr:full":"110 Woodycrest Ave East York ON M4J 3B2",
    "addr:housenumber":"110",
    "addr:postcode":"m4j 3b2",
    "addr:street":"Woodycrest Ave",
    "iso:country":"CA",
    "sg:address":"110 Woodycrest Ave",
    "sg:city":"East York",
    "sg:classifiers":[
        {
            "category":"Professional",
            "subcategory":"Management & Consulting",
            "type":"Services"
        }
    ],
    "sg:phone":"+1 416 463 1341",
    "sg:postcode":"M4J 3B2",
    "sg:province":"ON",
    "sg:tags":[
        "communications",
        "consultant"
    ],
    "wof:name":"Array Video & New Media Comms",
    "wof:placetype":"venue"
},
  "geometry": {"coordinates":[-79.3435211182,43.6837768555],"type":"Point"}
}