{
  "type": "Feature",
  "properties": {
    "addr:full":"4478 Montrose Rd Niagara Falls ON L2H 1K2",
    "addr:housenumber":"4478",
    "addr:postcode":"l2h 1k2",
    "addr:street":"Montrose Rd",
    "iso:country":"CA",
    "sg:address":"4478 Montrose Rd",
    "sg:city":"Niagara Falls",
    "sg:classifiers":[
        {
            "category":"Wholesale",
            "subcategory":"Electrical",
            "type":"Manufacturing & Wholesale Goods"
        }
    ],
    "sg:phone":"+1 905 356 6672",
    "sg:postcode":"L2H 1K2",
    "sg:province":"ON",
    "sg:tags":[
        "equipment",
        "electric",
        "supply"
    ],
    "wof:name":"Nedco",
    "wof:placetype":"venue"
},
  "geometry": {"coordinates":[-79.124084,43.107994],"type":"Point"}
}