{
  "type": "Feature",
  "properties": {
    "addr:full":"9 Alice St Thamesville ON N0P 2K0",
    "addr:housenumber":"9",
    "addr:postcode":"n0p 2k0",
    "addr:street":"Alice St",
    "iso:country":"CA",
    "sg:address":"9 Alice St",
    "sg:city":"Thamesville",
    "sg:classifiers":[
        {
            "category":"Organizations",
            "subcategory":"Religious Organization",
            "type":"Services"
        }
    ],
    "sg:phone":"+1 519 692 3874",
    "sg:postcode":"N0P 2K0",
    "sg:province":"ON",
    "sg:tags":[
        "church"
    ],
    "wof:name":"St Pauls Church",
    "wof:placetype":"venue"
},
  "geometry": {"coordinates":[-81.97732499999999,42.550301],"type":"Point"}
}