{
  "type": "Feature",
  "properties": {
    "addr:full":"Laurierville QC G0S 1P0",
    "addr:postcode":"g0s 1p0",
    "iso:country":"CA",
    "sg:city":"Laurierville",
    "sg:classifiers":[
        {
            "category":"Food & Beverages",
            "subcategory":"Groceries & Convenience Stores",
            "type":"Retail Goods"
        }
    ],
    "sg:phone":"+1 819 365 4443",
    "sg:postcode":"G0S 1P0",
    "sg:province":"QC",
    "wof:name":"Depanneur Mika",
    "wof:placetype":"venue"
},
  "geometry": {"coordinates":[-71.654037,46.293591],"type":"Point"}
}