{
  "type": "Feature",
  "properties": {
    "addr:full":"501 Ellis Dr Spruce Grove AB T7X 3G7",
    "addr:housenumber":"501",
    "addr:postcode":"t7x 3g7",
    "addr:street":"Ellis Dr",
    "iso:country":"CA",
    "sg:address":"501 Ellis Dr",
    "sg:city":"Spruce Grove",
    "sg:classifiers":[
        {
            "category":"Wholesale",
            "subcategory":"Machinery & Supplies",
            "type":"Manufacturing & Wholesale Goods"
        }
    ],
    "sg:phone":"+1 780 962 0846",
    "sg:postcode":"T7X 3G7",
    "sg:province":"AB",
    "sg:tags":[
        "equipment",
        "safety",
        "clothing"
    ],
    "wof:name":"Dalmatian Fire & Safety Inc",
    "wof:placetype":"venue"
},
  "geometry": {"coordinates":[-113.901855,53.544636],"type":"Point"}
}