{
  "type": "Feature",
  "properties": {
    "addr:full":"8 Davenport Crt Sudbury ON P3A 5V1",
    "addr:housenumber":"8",
    "addr:postcode":"p3a 5v1",
    "addr:street":"Davenport Crt",
    "iso:country":"CA",
    "sg:address":"8 Davenport Crt",
    "sg:city":"Sudbury",
    "sg:classifiers":[
        {
            "category":"Building & Trades",
            "subcategory":"Construction",
            "type":"Services"
        }
    ],
    "sg:phone":"+1 705 566 5072",
    "sg:postcode":"P3A 5V1",
    "sg:province":"ON",
    "sg:tags":[
        "excavating",
        "paving",
        "contractor"
    ],
    "wof:name":"B T Paving & Snowplowing",
    "wof:placetype":"venue"
},
  "geometry": {"coordinates":[-80.953934,46.527298],"type":"Point"}
}