{
  "type": "Feature",
  "properties": {
    "addr:full":"2203 110 St NW Edmonton AB T6J 6P4",
    "addr:housenumber":"2203",
    "addr:postcode":"t6j 6p4",
    "addr:street":"110 St Nw",
    "iso:country":"CA",
    "sg:address":"2203 110 St NW",
    "sg:city":"Edmonton",
    "sg:classifiers":[
        {
            "category":"Autos & Motor Vehicles",
            "subcategory":"Fuel & Gas Station",
            "type":"Retail Goods"
        }
    ],
    "sg:phone":"+1 780 437 2819",
    "sg:postcode":"T6J 6P4",
    "sg:province":"AB",
    "sg:tags":[
        "oil"
    ],
    "wof:name":"Heritage Shell",
    "wof:placetype":"venue"
},
  "geometry": {"coordinates":[-113.51288599999999,53.453274],"type":"Point"}
}