{
  "type": "Feature",
  "properties": {
    "addr:full":"100 Ch Morgan Coaticook QC J1A 1V7",
    "addr:housenumber":"100",
    "addr:postcode":"j1a 1v7",
    "addr:street":"Ch Morgan",
    "iso:country":"CA",
    "sg:address":"100 Ch Morgan",
    "sg:city":"Coaticook",
    "sg:classifiers":[
        {
            "category":"Real Estate",
            "subcategory":"Real Estate Agent",
            "type":"Services"
        }
    ],
    "sg:phone":"+1 819 849 9484",
    "sg:postcode":"J1A 1V7",
    "sg:province":"QC",
    "sg:tags":[
        "cooperative"
    ],
    "wof:name":"Cooperative D'Habitation Place",
    "wof:placetype":"venue"
},
  "geometry": {"coordinates":[-71.82019042970001,45.1391296387],"type":"Point"}
}