{
  "type": "Feature",
  "properties": {
    "addr:full":"5675 38 Ave NW Edmonton AB T6L 2Z1",
    "addr:housenumber":"5675",
    "addr:postcode":"t6l 2z1",
    "addr:street":"38 Ave Nw",
    "iso:country":"CA",
    "sg:address":"5675 38 Ave NW",
    "sg:city":"Edmonton",
    "sg:classifiers":[
        {
            "category":"Education",
            "subcategory":"School",
            "type":"Public Place"
        }
    ],
    "sg:phone":"+1 780 462 6448",
    "sg:postcode":"T6L 2Z1",
    "sg:province":"AB",
    "wof:name":"John Paul I Elementary School",
    "wof:placetype":"venue"
},
  "geometry": {"coordinates":[-113.425559998,53.4721755981],"type":"Point"}
}