{
  "type": "Feature",
  "properties": {
    "addr:full":"2073 Rue Saint-Louis Saint-Laurent QC H4M 1P1",
    "addr:housenumber":"2073",
    "addr:postcode":"h4m 1p1",
    "addr:street":"Rue Saint-Louis",
    "iso:country":"CA",
    "sg:address":"2073 Rue Saint-Louis",
    "sg:city":"Saint-Laurent",
    "sg:classifiers":[
        {
            "category":"Restaurant",
            "type":"Food & Drink"
        }
    ],
    "sg:phone":"+1 514 744 4113",
    "sg:postcode":"H4M 1P1",
    "sg:province":"QC",
    "sg:tags":[
        "delicatessen"
    ],
    "wof:name":"St Laurent Delicatessen Inc",
    "wof:placetype":"venue"
},
  "geometry": {"coordinates":[-73.680847,45.501751],"type":"Point"}
}