{
  "type": "Feature",
  "properties": {
    "addr:full":"834 Mountain Rd Moncton NB E1C 2R8",
    "addr:housenumber":"834",
    "addr:postcode":"e1c 2r8",
    "addr:street":"Mountain Rd",
    "iso:country":"CA",
    "sg:address":"834 Mountain Rd",
    "sg:city":"Moncton",
    "sg:classifiers":[
        {
            "category":"Organizations",
            "subcategory":"Community Association",
            "type":"Services"
        }
    ],
    "sg:phone":"+1 506 860 7771",
    "sg:postcode":"E1C 2R8",
    "sg:province":"NB",
    "sg:tags":[
        "club",
        "pub"
    ],
    "wof:name":"End Zone Sports Pub",
    "wof:placetype":"venue"
},
  "geometry": {"coordinates":[-64.80935700000001,46.100338],"type":"Point"}
}