{
  "type": "Feature",
  "properties": {
    "addr:full":"910 Rue DE LA Gauchetiere E Montreal QC H2L 2N4",
    "addr:housenumber":"910",
    "addr:postcode":"h2l 2n4",
    "addr:street":"Rue De La Gauchetiere E",
    "iso:country":"CA",
    "sg:address":"910 Rue DE LA Gauchetiere E",
    "sg:city":"Montreal",
    "sg:classifiers":[
        {
            "category":"Professional",
            "type":"Services"
        }
    ],
    "sg:phone":"+1 514 849 2420",
    "sg:postcode":"H2L 2N4",
    "sg:province":"QC",
    "sg:tags":[
        "arranger",
        "music",
        "composer"
    ],
    "wof:name":"Productions DE L'Encrier Ltee",
    "wof:placetype":"venue"
},
  "geometry": {"coordinates":[-73.5541152954,45.5149841309],"type":"Point"}
}