{
  "type": "Feature",
  "properties": {
    "iso:country":"CA",
    "sg:city":"Tilley",
    "sg:classifiers":[
        {
            "category":"Farming",
            "subcategory":"Nursery",
            "type":"Manufacturing & Wholesale Goods"
        }
    ],
    "sg:phone":"+1 403 377 2000",
    "sg:postcode":"T0J 3K0",
    "sg:province":"AB",
    "sg:tags":[
        "greenhouse"
    ],
    "wof:name":"Fabian Seed Farms",
    "wof:placetype":"venue"
},
  "geometry": {"coordinates":[-111.652793884,50.4507102966],"type":"Point"}
}