{
  "type": "Feature",
  "properties": {
    "addr:full":"1257 Eglinton Ave E Mississauga ON L4W 1K7",
    "addr:housenumber":"1257",
    "addr:postcode":"l4w 1k7",
    "addr:street":"Eglinton Ave E",
    "iso:country":"CA",
    "sg:address":"1257 Eglinton Ave E",
    "sg:city":"Mississauga",
    "sg:classifiers":[
        {
            "category":"Wholesale",
            "subcategory":"Motor Vehicles",
            "type":"Manufacturing & Wholesale Goods"
        }
    ],
    "sg:phone":"+1 905 624 1600",
    "sg:postcode":"L4W 1K7",
    "sg:province":"ON",
    "sg:tags":[
        "trailer"
    ],
    "wof:name":"Intrans Corp",
    "wof:placetype":"venue"
},
  "geometry": {"coordinates":[-79.62329864500001,43.6335868835],"type":"Point"}
}