{
  "type": "Feature",
  "properties": {
    "addr:full":"6450 Young St Halifax NS B3L 2A3",
    "addr:housenumber":"6450",
    "addr:postcode":"b3l 2a3",
    "addr:street":"Young St",
    "iso:country":"CA",
    "sg:address":"6450 Young St",
    "sg:city":"Halifax",
    "sg:classifiers":[
        {
            "category":"Freight",
            "type":"Transportation"
        }
    ],
    "sg:phone":"+1 902 455 8040",
    "sg:postcode":"B3L 2A3",
    "sg:province":"NS",
    "sg:tags":[
        "commercial",
        "storage"
    ],
    "wof:name":"Young Street Mini Storage",
    "wof:placetype":"venue"
},
  "geometry": {"coordinates":[-63.610413,44.65353],"type":"Point"}
}