{
  "type": "Feature",
  "properties": {
    "addr:full":"1520 Av Kennedy Chambly QC J3L 4P2",
    "addr:housenumber":"1520",
    "addr:postcode":"j3l 4p2",
    "addr:street":"Av Kennedy",
    "iso:country":"CA",
    "sg:address":"1520 Av Kennedy",
    "sg:city":"Chambly",
    "sg:classifiers":[
        {
            "category":"Food & Beverages",
            "subcategory":"Groceries & Convenience Stores",
            "type":"Retail Goods"
        }
    ],
    "sg:phone":"+1 450 658 9588",
    "sg:postcode":"J3L 4P2",
    "sg:province":"QC",
    "wof:name":"Depanneur Proprio",
    "wof:placetype":"venue"
},
  "geometry": {"coordinates":[-73.291718,45.434559],"type":"Point"}
}