{
  "type": "Feature",
  "properties": {
    "iso:country":"CA",
    "sg:city":"Laval",
    "sg:classifiers":[
        {
            "category":"Food & Beverages",
            "subcategory":"Groceries & Convenience Stores",
            "type":"Retail Goods"
        }
    ],
    "sg:phone":"+1 450 665 4367",
    "sg:postcode":"H7A 4C5",
    "sg:province":"QC",
    "wof:name":"Couche-Tard",
    "wof:placetype":"venue"
},
  "geometry": {"coordinates":[-73.736252,45.585442],"type":"Point"}
}