{
  "type": "Feature",
  "properties": {
    "iso:country":"CA",
    "sg:address":"500 Groves Ave",
    "sg:city":"Kelowna",
    "sg:classifiers":[
        {
            "category":"Shopping",
            "subcategory":"Used Merchandise",
            "type":"Retail Goods"
        }
    ],
    "sg:phone":"+1 250 763 7748",
    "sg:postcode":"V1Y 4Y7",
    "sg:province":"BC",
    "sg:tags":[
        "book",
        "rare",
        "dealer"
    ],
    "wof:name":"Book Bin",
    "wof:placetype":"venue"
},
  "geometry": {"coordinates":[-119.49108123800001,49.8634033203],"type":"Point"}
}