{
  "type": "Feature",
  "properties": {
    "addr:full":"21 Canal St E Bobcaygeon ON K0M 1A0",
    "addr:housenumber":"21",
    "addr:postcode":"k0m 1a0",
    "addr:street":"Canal St;Bobcaygeon",
    "iso:country":"CA",
    "sg:address":"21 Canal St E",
    "sg:city":"Bobcaygeon",
    "sg:classifiers":[
        {
            "category":"Travel",
            "subcategory":"Travel Agent",
            "type":"Entertainment"
        }
    ],
    "sg:phone":"+1 705 738 2202",
    "sg:postcode":"K0M 1A0",
    "sg:province":"ON",
    "sg:tags":[
        "information",
        "tourist"
    ],
    "wof:name":"Chamber of Commerce",
    "wof:placetype":"venue"
},
  "geometry": {"coordinates":[-78.542931,44.538292],"type":"Point"}
}