{
  "type": "Feature",
  "properties": {
    "addr:full":"385 Waterloo St New Hamburg ON N3A 1S6",
    "addr:housenumber":"385",
    "addr:postcode":"n3a 1s6",
    "addr:street":"Waterloo St",
    "iso:country":"CA",
    "sg:address":"385 Waterloo St",
    "sg:city":"New Hamburg",
    "sg:classifiers":[
        {
            "category":"Restaurant",
            "type":"Food & Drink"
        }
    ],
    "sg:phone":"+1 519 662 2211",
    "sg:postcode":"N3A 1S6",
    "sg:province":"ON",
    "sg:tags":[
        "out"
    ],
    "wof:name":"New Orleans Pizza",
    "wof:placetype":"venue"
},
  "geometry": {"coordinates":[-80.7114562988,43.3868026733],"type":"Point"}
}