{
  "type": "Feature",
  "properties": {
    "addr:full":"17 Wilson St E Perth ON K7H 1L3",
    "addr:housenumber":"17",
    "addr:postcode":"k7h 1l3",
    "addr:street":"Wilson St E",
    "iso:country":"CA",
    "sg:address":"17 Wilson St E",
    "sg:city":"Perth",
    "sg:classifiers":[
        {
            "category":"Home & Garden",
            "subcategory":"Home Furnishings",
            "type":"Retail Goods"
        }
    ],
    "sg:phone":"+1 613 267 9682",
    "sg:postcode":"K7H 1L3",
    "sg:province":"ON",
    "sg:tags":[
        "linen"
    ],
    "wof:name":"Oxford Linens",
    "wof:placetype":"venue"
},
  "geometry": {"coordinates":[-76.2513504028,44.8996353149],"type":"Point"}
}