{
  "type": "Feature",
  "properties": {
    "addr:full":"4805 King St Coronation AB T0C 1C0",
    "addr:housenumber":"4805",
    "addr:postcode":"t0c 1c0",
    "addr:street":"King St",
    "iso:country":"CA",
    "sg:address":"4805 King St",
    "sg:city":"Coronation",
    "sg:classifiers":[
        {
            "category":"Food & Beverages",
            "subcategory":"Groceries & Convenience Stores",
            "type":"Retail Goods"
        }
    ],
    "sg:phone":"+1 403 578 3596",
    "sg:postcode":"T0C 1C0",
    "sg:province":"AB",
    "sg:tags":[
        "grocer"
    ],
    "wof:name":"Korner Kash & Karry",
    "wof:placetype":"venue"
},
  "geometry": {"coordinates":[-111.446877,52.091728],"type":"Point"}
}