{
  "type": "Feature",
  "properties": {
    "addr:full":"4075 Macdonald St Vancouver BC V6L 2N8",
    "addr:housenumber":"4075",
    "addr:postcode":"v6l 2n8",
    "addr:street":"Macdonald St",
    "iso:country":"CA",
    "sg:address":"4075 Macdonald St",
    "sg:city":"Vancouver",
    "sg:classifiers":[
        {
            "category":"Food & Beverages",
            "subcategory":"Groceries & Convenience Stores",
            "type":"Retail Goods"
        }
    ],
    "sg:phone":"+1 604 738 6118",
    "sg:postcode":"V6L 2N8",
    "sg:province":"BC",
    "sg:tags":[
        "grocer"
    ],
    "wof:name":"Jimmy's Market",
    "wof:placetype":"venue"
},
  "geometry": {"coordinates":[-123.167946,49.25045],"type":"Point"}
}