{
  "type": "Feature",
  "properties": {
    "iso:country":"CA",
    "sg:address":"688 Elm St",
    "sg:city":"Port Colborne",
    "sg:classifiers":[
        {
            "category":"Organizations",
            "subcategory":"Religious Organization",
            "type":"Services"
        }
    ],
    "sg:phone":"+1 905 835 8111",
    "sg:postcode":"L3K 4R1",
    "sg:province":"ON",
    "sg:tags":[
        "church"
    ],
    "wof:name":"First Lutheran Church",
    "wof:placetype":"venue"
},
  "geometry": {"coordinates":[-79.25505065919999,42.8969917297],"type":"Point"}
}