{
  "type": "Feature",
  "properties": {
    "addr:full":"43 Cooper Cres Breslau ON N0B 1M0",
    "addr:housenumber":"43",
    "addr:postcode":"n0b 1m0",
    "addr:street":"Cooper Cres",
    "iso:country":"CA",
    "sg:address":"43 Cooper Cres",
    "sg:city":"Breslau",
    "sg:classifiers":[
        {
            "category":"Building & Trades",
            "subcategory":"Construction",
            "type":"Services"
        }
    ],
    "sg:phone":"+1 519 648 2843",
    "sg:postcode":"N0B 1M0",
    "sg:province":"ON",
    "sg:tags":[
        "sandblasting"
    ],
    "wof:name":"Stamar Enterprises Inc",
    "wof:placetype":"venue"
},
  "geometry": {"coordinates":[-80.412346,43.476749],"type":"Point"}
}