{
  "type": "Feature",
  "properties": {
    "addr:full":"2933 Granville St Vancouver BC V6H 3J6",
    "addr:housenumber":"2933",
    "addr:postcode":"v6h 3j6",
    "addr:street":"Granville St",
    "iso:country":"CA",
    "sg:address":"2933 Granville St",
    "sg:city":"Vancouver",
    "sg:classifiers":[
        {
            "category":"Shopping",
            "subcategory":"Shoes",
            "type":"Retail Goods"
        }
    ],
    "sg:phone":"+1 604 736 2933",
    "sg:postcode":"V6H 3J6",
    "sg:province":"BC",
    "wof:name":"Shoe Warehouse",
    "wof:placetype":"venue"
},
  "geometry": {"coordinates":[-123.13892364500001,49.2595329285],"type":"Point"}
}