{
  "type": "Feature",
  "properties": {
    "addr:full":"2265 Headon Rd Burlington ON L7M 4E2",
    "addr:housenumber":"2265",
    "addr:postcode":"l7m 4e2",
    "addr:street":"Headon Rd",
    "iso:country":"CA",
    "sg:address":"2265 Headon Rd",
    "sg:city":"Burlington",
    "sg:classifiers":[
        {
            "category":"Organizations",
            "subcategory":"Religious Organization",
            "type":"Services"
        }
    ],
    "sg:phone":"+1 905 332 5115",
    "sg:postcode":"L7M 4E2",
    "sg:province":"ON",
    "sg:tags":[
        "church"
    ],
    "wof:name":"St Paul the Apostle Parish",
    "wof:placetype":"venue"
},
  "geometry": {"coordinates":[-79.819389,43.381157],"type":"Point"}
}