{
  "type": "Feature",
  "properties": {
    "addr:full":"Corner of Hwy 1 & 257 Virden MB R0M 2C0",
    "addr:postcode":"r0m 2c0",
    "addr:street":"Corner Of Hwy 1 & 257 Virden",
    "iso:country":"CA",
    "sg:address":"Corner of Hwy 1 & 257",
    "sg:city":"Virden",
    "sg:classifiers":[
        {
            "category":"Manufacturing",
            "subcategory":"Glass & Minerals",
            "type":"Manufacturing & Wholesale Goods"
        }
    ],
    "sg:phone":"+1 204 748 1592",
    "sg:postcode":"R0M 2C0",
    "sg:province":"MB",
    "sg:tags":[
        "concrete",
        "brick",
        "block"
    ],
    "wof:name":"Midwestern Redi-Mix Concrete",
    "wof:placetype":"venue"
},
  "geometry": {"coordinates":[-100.919715881,49.8560256958],"type":"Point"}
}