{
  "type": "Feature",
  "properties": {
    "addr:full":"Scarborough ON M1V 2W7",
    "addr:postcode":"m1v 2w7",
    "iso:country":"CA",
    "sg:city":"Scarborough",
    "sg:classifiers":[
        {
            "category":"Shopping",
            "subcategory":"Pharmacy",
            "type":"Retail Goods"
        }
    ],
    "sg:phone":"+1 416 335 7373",
    "sg:postcode":"M1V 2W7",
    "sg:province":"ON",
    "wof:name":"Ivy Medical Pharmacy",
    "wof:placetype":"venue"
},
  "geometry": {"coordinates":[-79.31159973139999,43.8107299805],"type":"Point"}
}