{
  "type": "Feature",
  "properties": {
    "addr:full":"12600 Av Paul-Dufault Montreal QC H1E 2B6",
    "addr:housenumber":"12600",
    "addr:postcode":"h1e 2b6",
    "addr:street":"Av Paul-Dufault",
    "iso:country":"CA",
    "sg:address":"12600 Av Paul-Dufault",
    "sg:city":"Montreal",
    "sg:classifiers":[
        {
            "category":"Education",
            "subcategory":"School",
            "type":"Public Place"
        }
    ],
    "sg:phone":"+1 514 881 7140",
    "sg:postcode":"H1E 2B6",
    "sg:province":"QC",
    "wof:name":"Ecole Fernand-Gauthier",
    "wof:placetype":"venue"
},
  "geometry": {"coordinates":[-73.5916671753,45.643245697],"type":"Point"}
}