{
  "type": "Feature",
  "properties": {
    "addr:full":"724 Vine St Cambridge ON N3H 2Z3",
    "addr:housenumber":"724",
    "addr:postcode":"n3h 2z3",
    "addr:street":"Vine St",
    "iso:country":"CA",
    "sg:address":"724 Vine St",
    "sg:city":"Cambridge",
    "sg:classifiers":[
        {
            "category":"Building & Trades",
            "subcategory":"Electrical",
            "type":"Services"
        }
    ],
    "sg:phone":"+1 519 653 7959",
    "sg:postcode":"N3H 2Z3",
    "sg:province":"ON",
    "sg:tags":[
        "electric",
        "contractor"
    ],
    "wof:name":"Black Electric Inc",
    "wof:placetype":"venue"
},
  "geometry": {"coordinates":[-80.36144299999999,43.392082],"type":"Point"}
}