{
  "type": "Feature",
  "properties": {
    "addr:full":"1 Greensboro Dr Etobicoke ON M9W 1C8",
    "addr:housenumber":"1",
    "addr:postcode":"m9w 1c8",
    "addr:street":"Greensboro Dr",
    "iso:country":"CA",
    "sg:address":"1 Greensboro Dr",
    "sg:city":"Etobicoke",
    "sg:classifiers":[
        {
            "category":"Restaurant",
            "type":"Food & Drink"
        }
    ],
    "sg:phone":"+1 416 241 0088",
    "sg:postcode":"M9W 1C8",
    "sg:province":"ON",
    "wof:name":"Double Double Pizza Chicken",
    "wof:placetype":"venue"
},
  "geometry": {"coordinates":[-79.5617523193,43.702583313],"type":"Point"}
}