{
  "type": "Feature",
  "properties": {
    "addr:full":"1556 4E Rang Saint-Gabriel-DE-Brandon QC J0K 2N0",
    "addr:housenumber":"1556",
    "addr:postcode":"j0k 2n0",
    "addr:street":"4E Rang",
    "iso:country":"CA",
    "sg:address":"1556 4E Rang",
    "sg:city":"Saint-Gabriel-DE-Brandon",
    "sg:classifiers":[
        {
            "category":"Retail",
            "subcategory":"Auto Repair",
            "type":"Services"
        }
    ],
    "sg:phone":"+1 450 835 4881",
    "sg:postcode":"J0K 2N0",
    "sg:province":"QC",
    "sg:tags":[
        "body",
        "automobile",
        "painting"
    ],
    "wof:name":"Garage Brandon Enrg",
    "wof:placetype":"venue"
},
  "geometry": {"coordinates":[-73.3816070557,46.2912597656],"type":"Point"}
}