{
  "type": "Feature",
  "properties": {
    "addr:full":"Saint-Jean-Sur-Richelieu QC J3B 7X4",
    "addr:postcode":"j3b 7x4",
    "iso:country":"CA",
    "sg:city":"Saint-Jean-Sur-Richelieu",
    "sg:classifiers":[
        {
            "category":"Wholesale",
            "subcategory":"Groceries",
            "type":"Manufacturing & Wholesale Goods"
        }
    ],
    "sg:phone":"+1 450 359 7622",
    "sg:postcode":"J3B 7X4",
    "sg:province":"QC",
    "sg:tags":[
        "frozen",
        "food"
    ],
    "wof:name":"Nutrifrance Limitee",
    "wof:placetype":"venue"
},
  "geometry": {"coordinates":[-73.284836,45.320766],"type":"Point"}
}