{
  "type": "Feature",
  "properties": {
    "addr:full":"880 Lakeshore Rd Niagara on the Lake ON L0S 1J0",
    "addr:housenumber":"880",
    "addr:postcode":"l0s 1j0",
    "addr:street":"Lakeshore Rd;On",
    "iso:country":"CA",
    "sg:address":"880 Lakeshore Rd",
    "sg:city":"Niagara on the Lake",
    "sg:classifiers":[
        {
            "category":"Wholesale",
            "subcategory":"Plants",
            "type":"Manufacturing & Wholesale Goods"
        }
    ],
    "sg:phone":"+1 905 934 3986",
    "sg:postcode":"L0S 1J0",
    "sg:province":"ON",
    "sg:tags":[
        "florist"
    ],
    "wof:name":"Niagara Greenhouses Ltd",
    "wof:placetype":"venue"
},
  "geometry": {"coordinates":[-79.153824,43.244766],"type":"Point"}
}