{
  "type": "Feature",
  "properties": {
    "addr:full":"607 Ch Benoit St Pons NB E1X 1Z3",
    "addr:housenumber":"607",
    "addr:postcode":"e1x 1z3",
    "addr:street":"Ch Benoit St",
    "iso:country":"CA",
    "sg:address":"607 Ch Benoit",
    "sg:city":"St Pons",
    "sg:classifiers":[
        {
            "category":"Recreation",
            "type":"Entertainment"
        }
    ],
    "sg:phone":"+1 506 395 0903",
    "sg:postcode":"E1X 1Z3",
    "sg:province":"NB",
    "sg:tags":[
        "center",
        "hall",
        "auditorium"
    ],
    "wof:name":"Centre Communautaire DE St Pon",
    "wof:placetype":"venue"
},
  "geometry": {"coordinates":[-64.962509,47.475441],"type":"Point"}
}