{
  "type": "Feature",
  "properties": {
    "iso:country":"CA",
    "sg:address":"335 Rte Saint-Leon",
    "sg:city":"Amqui",
    "sg:classifiers":[
        {
            "category":"Building & Trades",
            "subcategory":"Construction",
            "type":"Services"
        }
    ],
    "sg:phone":"+1 418 629 4101",
    "sg:postcode":"G5J 2M8",
    "sg:province":"QC",
    "sg:tags":[
        "contractor"
    ],
    "wof:name":"Constructions Morneau Enr",
    "wof:placetype":"venue"
},
  "geometry": {"coordinates":[-67.4421081543,48.4451446533],"type":"Point"}
}