{
  "type": "Feature",
  "properties": {
    "addr:full":"210 Carnegie Dr St Albert AB T8N 5A7",
    "addr:housenumber":"210",
    "addr:postcode":"t8n 5a7",
    "addr:street":"Carnegie Dr",
    "iso:country":"CA",
    "sg:address":"210 Carnegie Dr",
    "sg:city":"St Albert",
    "sg:classifiers":[
        {
            "category":"Retail",
            "subcategory":"Car Wash",
            "type":"Services"
        }
    ],
    "sg:phone":"+1 780 460 5388",
    "sg:postcode":"T8N 5A7",
    "sg:province":"AB",
    "sg:tags":[
        "polishing",
        "washing"
    ],
    "wof:name":"Big Toy Wash CO Ltd",
    "wof:placetype":"venue"
},
  "geometry": {"coordinates":[-113.574485779,53.6378860474],"type":"Point"}
}