{
  "type": "Feature",
  "properties": {
    "addr:full":"Langley BC V1M 3A4",
    "addr:postcode":"v1m 3a4",
    "iso:country":"CA",
    "sg:city":"Langley",
    "sg:classifiers":[
        {
            "category":"Retail",
            "subcategory":"Auto Repair",
            "type":"Services"
        }
    ],
    "sg:phone":"+1 604 882 1301",
    "sg:postcode":"V1M 3A4",
    "sg:province":"BC",
    "sg:tags":[
        "body",
        "automobile",
        "painting"
    ],
    "wof:name":"Able Autobody",
    "wof:placetype":"venue"
},
  "geometry": {"coordinates":[-122.65657043500001,49.1041221619],"type":"Point"}
}