{
  "type": "Feature",
  "properties": {
    "addr:full":"388 Viewcrest Crt Kelowna BC V1W 4J9",
    "addr:housenumber":"388",
    "addr:postcode":"v1w 4j9",
    "addr:street":"Viewcrest Crt",
    "iso:country":"CA",
    "sg:address":"388 Viewcrest Crt",
    "sg:city":"Kelowna",
    "sg:classifiers":[
        {
            "category":"Building & Trades",
            "subcategory":"Construction",
            "type":"Services"
        }
    ],
    "sg:phone":"+1 250 764 0900",
    "sg:postcode":"V1W 4J9",
    "sg:province":"BC",
    "sg:tags":[
        "contractor"
    ],
    "wof:name":"Hill Valley Homes Ltd",
    "wof:placetype":"venue"
},
  "geometry": {"coordinates":[-119.51902771,49.7990684509],"type":"Point"}
}