{
  "type": "Feature",
  "properties": {
    "addr:full":"470 Glencairn Ave North York ON M5N 1V8",
    "addr:housenumber":"470",
    "addr:postcode":"m5n 1v8",
    "addr:street":"Glencairn Ave",
    "iso:country":"CA",
    "sg:address":"470 Glencairn Ave",
    "sg:city":"North York",
    "sg:classifiers":[
        {
            "category":"Restaurant",
            "type":"Food & Drink"
        }
    ],
    "sg:phone":"+1 416 782 8022",
    "sg:postcode":"M5N 1V8",
    "sg:province":"ON",
    "sg:tags":[
        "caterer"
    ],
    "wof:name":"Sam Firestone Caterers",
    "wof:placetype":"venue"
},
  "geometry": {"coordinates":[-79.4264221191,43.7128257751],"type":"Point"}
}