{
  "type": "Feature",
  "properties": {
    "iso:country":"CA",
    "sg:address":"828 Boul Taschereau",
    "sg:city":"Longueuil",
    "sg:classifiers":[
        {
            "category":"Autos & Motor Vehicles",
            "subcategory":"Automobile Sales",
            "type":"Retail Goods"
        }
    ],
    "sg:phone":"+1 450 674 9393",
    "sg:postcode":"J4K 5B6",
    "sg:province":"QC",
    "sg:tags":[
        "car",
        "dealer"
    ],
    "wof:name":"Diva Auto Inc",
    "wof:placetype":"venue"
},
  "geometry": {"coordinates":[-73.511566,45.516144],"type":"Point"}
}