{
  "type": "Feature",
  "properties": {
    "iso:country":"CA",
    "sg:address":"8677 Anchor Dr",
    "sg:city":"Windsor",
    "sg:classifiers":[
        {
            "category":"Insurance",
            "subcategory":"Health Insurance",
            "type":"Services"
        }
    ],
    "sg:phone":"+1 519 739 1133",
    "sg:postcode":"N8N 5G1",
    "sg:province":"ON",
    "sg:tags":[
        "surgical",
        "hospitalization",
        "plan"
    ],
    "wof:name":"Green Shield Canada",
    "wof:placetype":"venue"
},
  "geometry": {"coordinates":[-82.9175109863,42.2947921753],"type":"Point"}
}