{
  "type": "Feature",
  "properties": {
    "iso:country":"CA",
    "sg:address":"202 Rue Principale",
    "sg:city":"Lambton",
    "sg:classifiers":[
        {
            "category":"Sports & Exercise",
            "subcategory":"Bowling",
            "type":"Entertainment"
        }
    ],
    "sg:phone":"+1 418 486 2600",
    "sg:postcode":"G0M 1H0",
    "sg:province":"QC",
    "sg:tags":[
        "center"
    ],
    "wof:name":"Salon Du Quilleur",
    "wof:placetype":"venue"
},
  "geometry": {"coordinates":[-71.09061431879999,45.8386688232],"type":"Point"}
}