{
  "type": "Feature",
  "properties": {
    "addr:full":"7207 Main St Rte 6 North Rustico PE C0A 1X0",
    "addr:housenumber":"7207",
    "addr:postcode":"c0a 1x0",
    "addr:street":"Main St Rte 6",
    "iso:country":"CA",
    "sg:address":"7207 Main St Rte 6",
    "sg:city":"North Rustico",
    "sg:classifiers":[
        {
            "category":"Restaurant",
            "type":"Food & Drink"
        }
    ],
    "sg:phone":"+1 902 963 2290",
    "sg:postcode":"C0A 1X0",
    "sg:province":"PE",
    "wof:name":"By the Bay Family Restaurant",
    "wof:placetype":"venue"
},
  "geometry": {"coordinates":[-63.318687,46.452389],"type":"Point"}
}