{
  "type": "Feature",
  "properties": {
    "addr:full":"Mississauga ON L5G 1H1",
    "addr:postcode":"l5g 1h1",
    "iso:country":"CA",
    "sg:city":"Mississauga",
    "sg:classifiers":[
        {
            "category":"Shopping",
            "subcategory":"Used Merchandise",
            "type":"Retail Goods"
        }
    ],
    "sg:phone":"+1 905 274 0556",
    "sg:postcode":"L5G 1H1",
    "sg:province":"ON",
    "sg:tags":[
        "pawnbroker"
    ],
    "wof:name":"Sunny Jewellery & Pawnshop",
    "wof:placetype":"venue"
},
  "geometry": {"coordinates":[-79.5764389038,43.5604286194],"type":"Point"}
}