{
  "type": "Feature",
  "properties": {
    "addr:full":"600 Rue Victoria Lachine QC H8S 1Y7",
    "addr:housenumber":"600",
    "addr:postcode":"h8s 1y7",
    "addr:street":"Rue Victoria",
    "iso:country":"CA",
    "sg:address":"600 Rue Victoria",
    "sg:city":"Lachine",
    "sg:classifiers":[
        {
            "category":"Shopping",
            "subcategory":"Bicycles & Sporting Goods",
            "type":"Retail Goods"
        }
    ],
    "sg:phone":"+1 514 637 9217",
    "sg:postcode":"H8S 1Y7",
    "sg:province":"QC",
    "wof:name":"D'Amour Bicycles & Sports",
    "wof:placetype":"venue"
},
  "geometry": {"coordinates":[-73.66948699949999,45.4379768372],"type":"Point"}
}