{
  "type": "Feature",
  "properties": {
    "addr:full":"4510 47 St Wetaskiwin AB T9A 1B8",
    "addr:housenumber":"4510",
    "addr:postcode":"t9a 1b8",
    "addr:street":"47 St",
    "iso:country":"CA",
    "sg:address":"4510 47 St",
    "sg:city":"Wetaskiwin",
    "sg:classifiers":[
        {
            "category":"Education",
            "subcategory":"School",
            "type":"Public Place"
        }
    ],
    "sg:phone":"+1 780 352 6616",
    "sg:postcode":"T9A 1B8",
    "sg:province":"AB",
    "wof:name":"Clear Vista School",
    "wof:placetype":"venue"
},
  "geometry": {"coordinates":[-113.366158,52.964504],"type":"Point"}
}