{
  "type": "Feature",
  "properties": {
    "iso:country":"CA",
    "sg:address":"1500 Dundas St",
    "sg:city":"London",
    "sg:classifiers":[
        {
            "category":"Shopping",
            "subcategory":"Department Store",
            "type":"Retail Goods"
        }
    ],
    "sg:phone":"+1 519 659 0605",
    "sg:postcode":"N5W 3B9",
    "sg:province":"ON",
    "sg:tags":[
        "shop",
        "second",
        "hand"
    ],
    "wof:name":"Value Village Stores Ltd",
    "wof:placetype":"venue"
},
  "geometry": {"coordinates":[-81.196281,42.999119],"type":"Point"}
}