{
  "type": "Feature",
  "properties": {
    "addr:full":"5641 Boul Laurier LA Plaine QC J7M 1T7",
    "addr:housenumber":"5641",
    "addr:postcode":"j7m 1t7",
    "addr:street":"Boul Laurier",
    "iso:country":"CA",
    "sg:address":"5641 Boul Laurier",
    "sg:city":"LA Plaine",
    "sg:classifiers":[
        {
            "category":"Building & Trades",
            "subcategory":"Construction",
            "type":"Services"
        }
    ],
    "sg:phone":"+1 450 477 8102",
    "sg:postcode":"J7M 1T7",
    "sg:province":"QC",
    "sg:tags":[
        "designer",
        "dealer",
        "pool",
        "swimming"
    ],
    "wof:name":"Piscines Gravel",
    "wof:placetype":"venue"
},
  "geometry": {"coordinates":[-73.71219600000001,45.755718],"type":"Point"}
}