{
  "type": "Feature",
  "properties": {
    "addr:full":"685 Rue Olivier Joliette QC J6E 5M2",
    "addr:housenumber":"685",
    "addr:postcode":"j6e 5m2",
    "addr:street":"Rue Olivier",
    "iso:country":"CA",
    "sg:address":"685 Rue Olivier",
    "sg:city":"Joliette",
    "sg:classifiers":[
        {
            "category":"Manufacturing",
            "subcategory":"Metals",
            "type":"Manufacturing & Wholesale Goods"
        }
    ],
    "sg:phone":"+1 450 755 1422",
    "sg:postcode":"J6E 5M2",
    "sg:province":"QC",
    "sg:tags":[
        "steel"
    ],
    "wof:name":"Fabrication Ll",
    "wof:placetype":"venue"
},
  "geometry": {"coordinates":[-73.42944300000001,46.015392],"type":"Point"}
}