{
  "type": "Feature",
  "properties": {
    "addr:full":"34 Hawthorne Ave Ottawa ON K1S 0B1",
    "addr:housenumber":"34",
    "addr:postcode":"k1s 0b1",
    "addr:street":"Hawthorne Ave",
    "iso:country":"CA",
    "sg:address":"34 Hawthorne Ave",
    "sg:city":"Ottawa",
    "sg:classifiers":[
        {
            "category":"Professional",
            "subcategory":"Lawyer & Legal Services",
            "type":"Services"
        }
    ],
    "sg:phone":"+1 613 238 8006",
    "sg:postcode":"K1S 0B1",
    "sg:province":"ON",
    "sg:tags":[
        "attorney"
    ],
    "wof:name":"Farrell, Michael J",
    "wof:placetype":"venue"
},
  "geometry": {"coordinates":[-75.68174,45.411972],"type":"Point"}
}