{
  "type": "Feature",
  "properties": {
    "iso:country":"CA",
    "sg:city":"Sainte-Foy",
    "sg:classifiers":[
        {
            "category":"Professional",
            "subcategory":"Management & Consulting",
            "type":"Services"
        }
    ],
    "sg:phone":"+1 418 266 9473",
    "sg:postcode":"G1X 3V2",
    "sg:province":"QC",
    "sg:tags":[
        "employee",
        "consultant",
        "benefit",
        "insurance"
    ],
    "wof:name":"Centre DE Traitement D'Assrnce",
    "wof:placetype":"venue"
},
  "geometry": {"coordinates":[-71.2917633057,46.7692108154],"type":"Point"}
}