{
  "type": "Feature",
  "properties": {
    "iso:country":"CA",
    "sg:address":"824 Horace St",
    "sg:city":"Regina",
    "sg:classifiers":[
        {
            "category":"Building & Trades",
            "subcategory":"Construction",
            "type":"Services"
        }
    ],
    "sg:phone":"+1 306 545 8532",
    "sg:postcode":"S4T 5K8",
    "sg:province":"SK",
    "sg:tags":[
        "general",
        "contractor"
    ],
    "wof:name":"Jim Pomfrey Construction Ltd",
    "wof:placetype":"venue"
},
  "geometry": {"coordinates":[-104.659912,50.464954],"type":"Point"}
}