{
  "type": "Feature",
  "properties": {
    "addr:full":"Saint-Hyacinthe QC J2S 5C6",
    "addr:postcode":"j2s 5c6",
    "iso:country":"CA",
    "sg:city":"Saint-Hyacinthe",
    "sg:classifiers":[
        {
            "category":"Banks & Credit Unions",
            "subcategory":"Financial Services",
            "type":"Services"
        }
    ],
    "sg:phone":"+1 450 771 0100",
    "sg:postcode":"J2S 5C6",
    "sg:province":"QC",
    "sg:tags":[
        "bankruptcy",
        "trustee"
    ],
    "wof:name":"Jean Fortin & Assoc",
    "wof:placetype":"venue"
},
  "geometry": {"coordinates":[-72.947937,45.625839],"type":"Point"}
}