{
  "type": "Feature",
  "properties": {
    "addr:full":"221 Main St Cowan MB R0L 0L0",
    "addr:housenumber":"221",
    "addr:postcode":"r0l 0l0",
    "addr:street":"Main St",
    "iso:country":"CA",
    "sg:address":"221 Main St",
    "sg:city":"Cowan",
    "sg:classifiers":[
        {
            "category":"Manufacturing",
            "subcategory":"Glass & Minerals",
            "type":"Manufacturing & Wholesale Goods"
        }
    ],
    "sg:phone":"+1 204 569 4836",
    "sg:postcode":"R0L 0L0",
    "sg:province":"MB",
    "sg:tags":[
        "engraver"
    ],
    "wof:name":"Kolisnyk's General Store",
    "wof:placetype":"venue"
},
  "geometry": {"coordinates":[-100.645149,52.034386],"type":"Point"}
}