{
  "type": "Feature",
  "properties": {
    "addr:full":"4120 Route 114 Hopewell Cape NB E4H 3K2",
    "addr:housenumber":"4120",
    "addr:postcode":"e4h 3k2",
    "addr:street":"Route 114",
    "iso:country":"CA",
    "sg:address":"4120 Route 114",
    "sg:city":"Hopewell Cape",
    "sg:classifiers":[
        {
            "category":"Shopping",
            "subcategory":"Discount & Variety Stores",
            "type":"Retail Goods"
        }
    ],
    "sg:phone":"+1 506 734 2151",
    "sg:postcode":"E4H 3K2",
    "sg:province":"NB",
    "wof:name":"Rocks View Variety",
    "wof:placetype":"venue"
},
  "geometry": {"coordinates":[-64.576218,45.845879],"type":"Point"}
}