{
  "type": "Feature",
  "properties": {
    "addr:full":"1831 Ord Rd Kamloops BC V2B 7V5",
    "addr:housenumber":"1831",
    "addr:postcode":"bc v2b 7v5",
    "addr:street":"Ord Rd",
    "iso:country":"CA",
    "sg:address":"1831 Ord Rd",
    "sg:city":"Kamloops",
    "sg:classifiers":[
        {
            "category":"Retail",
            "subcategory":"Repair Shop",
            "type":"Services"
        }
    ],
    "sg:phone":"+1 250 554 1922",
    "sg:postcode":"V2B 7V5",
    "sg:province":"BC",
    "sg:tags":[
        "machine",
        "welding"
    ],
    "wof:name":"Donahue Industries Ltd",
    "wof:placetype":"venue"
},
  "geometry": {"coordinates":[-120.396072,50.711052],"type":"Point"}
}