{
  "type": "Feature",
  "properties": {
    "addr:full":"Hartney MB R0M 0X0",
    "addr:postcode":"r0m 0x0",
    "iso:country":"CA",
    "sg:city":"Hartney",
    "sg:classifiers":[
        {
            "category":"Wholesale",
            "subcategory":"Machinery & Supplies",
            "type":"Manufacturing & Wholesale Goods"
        }
    ],
    "sg:phone":"+1 204 858 2000",
    "sg:postcode":"R0M 0X0",
    "sg:province":"MB",
    "sg:tags":[
        "farm",
        "equipment"
    ],
    "wof:name":"Atkinson Implements",
    "wof:placetype":"venue"
},
  "geometry": {"coordinates":[-100.528015137,49.4774780273],"type":"Point"}
}