{
  "type": "Feature",
  "properties": {
    "addr:full":"1191 Av Bourgogne Chambly QC J3L 1X3",
    "addr:housenumber":"1191",
    "addr:postcode":"j3l 1x3",
    "addr:street":"Av Bourgogne",
    "iso:country":"CA",
    "sg:address":"1191 Av Bourgogne",
    "sg:city":"Chambly",
    "sg:classifiers":[
        {
            "category":"Social Services",
            "subcategory":"Child Care",
            "type":"Services"
        }
    ],
    "sg:phone":"+1 450 447 3614",
    "sg:postcode":"J3L 1X3",
    "sg:province":"QC",
    "sg:tags":[
        "kindergarten",
        "academic",
        "school"
    ],
    "wof:name":"Aux Petits Copains",
    "wof:placetype":"venue"
},
  "geometry": {"coordinates":[-73.301292,45.456005],"type":"Point"}
}