{
  "type": "Feature",
  "properties": {
    "addr:full":"Morris MB R0G 1K0",
    "addr:postcode":"r0g 1k0",
    "iso:country":"CA",
    "sg:city":"Morris",
    "sg:classifiers":[
        {
            "category":"Government",
            "subcategory":"Office",
            "type":"Public Place"
        }
    ],
    "sg:phone":"+1 204 746 8748",
    "sg:postcode":"R0G 1K0",
    "sg:province":"MB",
    "wof:name":"Manitoba Maintenance Yard",
    "wof:placetype":"venue"
},
  "geometry": {"coordinates":[-97.21593475340001,49.5097160339],"type":"Point"}
}