{
  "type": "Feature",
  "properties": {
    "addr:full":"425 2E Ave Sainte-Marie QC G6E 3H2",
    "addr:housenumber":"425",
    "addr:postcode":"g6e 3h2",
    "addr:street":"2E Ave",
    "iso:country":"CA",
    "sg:address":"425 2E Ave",
    "sg:city":"Sainte-Marie",
    "sg:classifiers":[
        {
            "category":"Utilities",
            "subcategory":"Fuel Oil & Lpg",
            "type":"Services"
        }
    ],
    "sg:phone":"+1 418 387 7699",
    "sg:postcode":"G6E 3H2",
    "sg:province":"QC",
    "sg:tags":[
        "propane",
        "gas"
    ],
    "wof:name":"Propane Grg Inc",
    "wof:placetype":"venue"
},
  "geometry": {"coordinates":[-65.98382599999999,48.172626],"type":"Point"}
}