{
  "type": "Feature",
  "properties": {
    "addr:full":"2509 Camden Rd Camden East ON K0K 1J0",
    "addr:housenumber":"2509",
    "addr:postcode":"k0k 1j0",
    "addr:street":"Camden Rd",
    "iso:country":"CA",
    "sg:address":"2509 Camden Rd",
    "sg:city":"Camden East",
    "sg:classifiers":[
        {
            "category":"Professional",
            "subcategory":"Business Services",
            "type":"Services"
        }
    ],
    "sg:phone":"+1 613 378 6441",
    "sg:postcode":"K0K 1J0",
    "sg:province":"ON",
    "sg:tags":[
        "appraiser"
    ],
    "wof:name":"Camden Motor & Sports",
    "wof:placetype":"venue"
},
  "geometry": {"coordinates":[-76.83354199999999,44.335602],"type":"Point"}
}