{
  "type": "Feature",
  "properties": {
    "iso:country":"CA",
    "sg:city":"Hamilton",
    "sg:classifiers":[
        {
            "category":"Personal",
            "type":"Services"
        }
    ],
    "sg:phone":"+1 905 389 8662",
    "sg:postcode":"L9C 5R9",
    "sg:province":"ON",
    "sg:tags":[
        "electrolysis"
    ],
    "wof:name":"Mountain Electrolysis",
    "wof:placetype":"venue"
},
  "geometry": {"coordinates":[-79.8786392212,43.2353591919],"type":"Point"}
}