{
  "type": "Feature",
  "properties": {
    "iso:country":"CA",
    "sg:address":"3753 Rue Sainte-Catherine E",
    "sg:city":"Montreal",
    "sg:classifiers":[
        {
            "category":"Shopping",
            "subcategory":"Clothing, Apparel, & Fashions",
            "type":"Retail Goods"
        }
    ],
    "sg:phone":"+1 514 521 9913",
    "sg:postcode":"H1W 2E9",
    "sg:province":"QC",
    "sg:tags":[
        "fur",
        "business"
    ],
    "wof:name":"Charles Rivet Fils Inc",
    "wof:placetype":"venue"
},
  "geometry": {"coordinates":[-73.53787994379999,45.5447273254],"type":"Point"}
}