{
  "type": "Feature",
  "properties": {
    "addr:full":"3970 Astral Ave Quesnel BC V2J 6W2",
    "addr:housenumber":"3970",
    "addr:postcode":"v2j 6w2",
    "addr:street":"Astral Ave",
    "iso:country":"CA",
    "sg:address":"3970 Astral Ave",
    "sg:city":"Quesnel",
    "sg:classifiers":[
        {
            "category":"Recreation",
            "type":"Entertainment"
        }
    ],
    "sg:phone":"+1 250 992 9484",
    "sg:postcode":"V2J 6W2",
    "sg:province":"BC",
    "sg:tags":[
        "archery",
        "instruction"
    ],
    "wof:name":"North Country Archery",
    "wof:placetype":"venue"
},
  "geometry": {"coordinates":[-122.498245,52.978119],"type":"Point"}
}