{
  "type": "Feature",
  "properties": {
    "addr:full":"367 Rue DE Castelnau E Montreal QC H2R 1R1",
    "addr:housenumber":"367",
    "addr:postcode":"h2r 1r1",
    "addr:street":"Rue De Castelnau E",
    "iso:country":"CA",
    "sg:address":"367 Rue DE Castelnau E",
    "sg:city":"Montreal",
    "sg:classifiers":[
        {
            "category":"Food & Beverages",
            "subcategory":"Bakery",
            "type":"Retail Goods"
        }
    ],
    "sg:phone":"+1 514 278 7047",
    "sg:postcode":"H2R 1R1",
    "sg:province":"QC",
    "sg:tags":[
        "baker"
    ],
    "wof:name":"Boulangerie Populaire",
    "wof:placetype":"venue"
},
  "geometry": {"coordinates":[-73.61772918699999,45.538772583],"type":"Point"}
}