{
  "type": "Feature",
  "properties": {
    "addr:full":"193 Strange St Kitchener ON N2G 1R7",
    "addr:housenumber":"193",
    "addr:postcode":"n2g 1r7",
    "addr:street":"Strange St",
    "iso:country":"CA",
    "sg:address":"193 Strange St",
    "sg:city":"Kitchener",
    "sg:classifiers":[
        {
            "category":"Personal",
            "subcategory":"Beauty Salon",
            "type":"Services"
        }
    ],
    "sg:phone":"+1 519 570 1951",
    "sg:postcode":"N2G 1R7",
    "sg:province":"ON",
    "wof:name":"Accent on Aesthetics",
    "wof:placetype":"venue"
},
  "geometry": {"coordinates":[-80.5099563599,43.4530677795],"type":"Point"}
}