{
  "type": "Feature",
  "properties": {
    "addr:full":"66 Woodland Dr Hay River NT X0E 1G1",
    "addr:housenumber":"66",
    "addr:postcode":"x0e 1g1",
    "addr:street":"Woodland Dr",
    "iso:country":"CA",
    "sg:address":"66 Woodland Dr",
    "sg:city":"Hay River",
    "sg:classifiers":[
        {
            "category":"Sports & Exercise",
            "subcategory":"Bowling",
            "type":"Entertainment"
        }
    ],
    "sg:phone":"+1 867 874 6664",
    "sg:postcode":"X0E 1G1",
    "sg:province":"NT",
    "sg:tags":[
        "center"
    ],
    "wof:name":"Hay River Bowling Lanes",
    "wof:placetype":"venue"
},
  "geometry": {"coordinates":[-115.788917541,60.809135437],"type":"Point"}
}