{
  "type": "Feature",
  "properties": {
    "addr:full":"10830 127 St NW Edmonton AB T5M 0S5",
    "addr:housenumber":"10830",
    "addr:postcode":"t5m 0s5",
    "addr:street":"127 St Nw",
    "iso:country":"CA",
    "sg:address":"10830 127 St NW",
    "sg:city":"Edmonton",
    "sg:classifiers":[
        {
            "category":"Health Services",
            "subcategory":"Clinic",
            "type":"Services"
        }
    ],
    "sg:phone":"+1 780 488 6683",
    "sg:postcode":"T5M 0S5",
    "sg:province":"AB",
    "sg:tags":[
        "home"
    ],
    "wof:name":"Home Health Care Svc",
    "wof:placetype":"venue"
},
  "geometry": {"coordinates":[-113.541382,53.553036],"type":"Point"}
}