{
  "type": "Feature",
  "properties": {
    "iso:country":"CA",
    "sg:address":"24 Peet St",
    "sg:city":"St. John's",
    "sg:classifiers":[
        {
            "category":"Wholesale",
            "subcategory":"Auto Parts",
            "type":"Manufacturing & Wholesale Goods"
        }
    ],
    "sg:phone":"+1 709 726 2750",
    "sg:postcode":"A1B 4S6",
    "sg:province":"NL",
    "sg:tags":[
        "equipment",
        "truck"
    ],
    "wof:name":"Hickman Motors Truck Ctr",
    "wof:placetype":"venue"
},
  "geometry": {"coordinates":[-52.75959,47.558109],"type":"Point"}
}