{
  "type": "Feature",
  "properties": {
    "addr:full":"4609 Hwy 49 Almonte ON K0A 1A0",
    "addr:housenumber":"4609",
    "addr:postcode":"k0a 1a0",
    "addr:street":"Hwy 49",
    "iso:country":"CA",
    "sg:address":"4609 Hwy 49",
    "sg:city":"Almonte",
    "sg:classifiers":[
        {
            "category":"Manufacturing",
            "subcategory":"Building Materials",
            "type":"Manufacturing & Wholesale Goods"
        }
    ],
    "sg:phone":"+1 613 256 9000",
    "sg:postcode":"K0A 1A0",
    "sg:province":"ON",
    "sg:tags":[
        "truss"
    ],
    "wof:name":"Almonte Lumber & Truss Ltd",
    "wof:placetype":"venue"
},
  "geometry": {"coordinates":[-76.19420599999999,45.228741],"type":"Point"}
}