{
  "type": "Feature",
  "properties": {
    "iso:country":"CA",
    "sg:address":"429 Lampson St",
    "sg:city":"Victoria",
    "sg:classifiers":[
        {
            "category":"Travel",
            "subcategory":"Hotels & Motels",
            "type":"Entertainment"
        }
    ],
    "sg:phone":"+1 250 388 4353",
    "sg:postcode":"V9A 5Y9",
    "sg:province":"BC",
    "wof:name":"English Inn & Resort",
    "wof:placetype":"venue"
},
  "geometry": {"coordinates":[-123.364517212,48.428314209],"type":"Point"}
}