{
  "type": "Feature",
  "properties": {
    "addr:full":"1831 15 St SW Calgary AB T2T 3Y7",
    "addr:housenumber":"1831",
    "addr:postcode":"t2t 3y7",
    "addr:street":"15 St Sw",
    "iso:country":"CA",
    "sg:address":"1831 15 St SW",
    "sg:city":"Calgary",
    "sg:classifiers":[
        {
            "category":"Manufacturing",
            "subcategory":"Metals",
            "type":"Manufacturing & Wholesale Goods"
        }
    ],
    "sg:phone":"+1 403 630 7316",
    "sg:postcode":"T2T 3Y7",
    "sg:province":"AB",
    "sg:tags":[
        "landscape",
        "contractor"
    ],
    "wof:name":"Cavro Limited",
    "wof:placetype":"venue"
},
  "geometry": {"coordinates":[-114.09777832,51.0375175476],"type":"Point"}
}