{
  "type": "Feature",
  "properties": {
    "addr:full":"223 Dunlop Pl # N Regina SK S4X 2R9",
    "addr:housenumber":"223;#",
    "addr:postcode":"s4x 2r9",
    "addr:street":"Dunlop Pl;N Regina",
    "iso:country":"CA",
    "sg:address":"223 Dunlop Pl # N",
    "sg:city":"Regina",
    "sg:classifiers":[
        {
            "category":"Wholesale",
            "subcategory":"Groceries",
            "type":"Manufacturing & Wholesale Goods"
        }
    ],
    "sg:phone":"+1 306 545 4142",
    "sg:postcode":"S4X 2R9",
    "sg:province":"SK",
    "sg:tags":[
        "food",
        "broker"
    ],
    "wof:name":"Maxima Sales",
    "wof:placetype":"venue"
},
  "geometry": {"coordinates":[-104.68306699999999,50.479061],"type":"Point"}
}