{
  "type": "Feature",
  "properties": {
    "addr:full":"1525 Centennial Dr Kingston ON K7L 4V2",
    "addr:housenumber":"1525",
    "addr:postcode":"k7l 4v2",
    "addr:street":"Centennial Dr",
    "iso:country":"CA",
    "sg:address":"1525 Centennial Dr",
    "sg:city":"Kingston",
    "sg:classifiers":[
        {
            "category":"Education",
            "subcategory":"Special Training",
            "type":"Public Place"
        }
    ],
    "sg:phone":"+1 613 389 6000",
    "sg:postcode":"K7L 4V2",
    "sg:province":"ON",
    "sg:tags":[
        "school",
        "instruction",
        "driving"
    ],
    "wof:name":"Crossroads Training Academy",
    "wof:placetype":"venue"
},
  "geometry": {"coordinates":[-76.5683670044,44.2796554565],"type":"Point"}
}