{
  "type": "Feature",
  "properties": {
    "addr:full":"5361 Rue Jean-Talon E Saint-Leonard QC H1S 1L7",
    "addr:housenumber":"5361",
    "addr:postcode":"h1s 1l7",
    "addr:street":"Rue Jean-Talon E",
    "iso:country":"CA",
    "sg:address":"5361 Rue Jean-Talon E",
    "sg:city":"Saint-Leonard",
    "sg:classifiers":[
        {
            "category":"Banks & Credit Unions",
            "subcategory":"Bank",
            "type":"Services"
        }
    ],
    "sg:phone":"+1 514 593 6060",
    "sg:postcode":"H1S 1L7",
    "sg:province":"QC",
    "wof:name":"Td Canada Trust",
    "wof:placetype":"venue"
},
  "geometry": {"coordinates":[-73.5819320679,45.5795249939],"type":"Point"}
}