{
  "type": "Feature",
  "properties": {
    "iso:country":"CA",
    "sg:city":"Paisley",
    "sg:classifiers":[
        {
            "category":"Government",
            "subcategory":"Fire Station",
            "type":"Public Place"
        }
    ],
    "sg:phone":"+1 519 353 5744",
    "sg:postcode":"N0G 2N0",
    "sg:province":"ON",
    "sg:tags":[
        "department"
    ],
    "wof:name":"Paisley Fire Department",
    "wof:placetype":"venue"
},
  "geometry": {"coordinates":[-81.2720565796,44.3065376282],"type":"Point"}
}