{
  "type": "Feature",
  "properties": {
    "addr:full":"11011 51 Ave NW Edmonton AB T6H 5T1",
    "addr:housenumber":"11011",
    "addr:postcode":"t6h 5t1",
    "addr:street":"51 Ave Nw",
    "iso:country":"CA",
    "sg:address":"11011 51 Ave NW",
    "sg:city":"Edmonton",
    "sg:classifiers":[
        {
            "category":"Food & Beverages",
            "subcategory":"Liquor & Beverages",
            "type":"Retail Goods"
        }
    ],
    "sg:phone":"+1 780 438 4071",
    "sg:postcode":"T6H 5T1",
    "sg:province":"AB",
    "sg:tags":[
        "store"
    ],
    "wof:name":"Liquor World",
    "wof:placetype":"venue"
},
  "geometry": {"coordinates":[-113.51431274399999,53.4879341125],"type":"Point"}
}