{
  "type": "Feature",
  "properties": {
    "addr:full":"1341 27th St E North Vancouver BC V7J 1S6",
    "addr:housenumber":"1341",
    "addr:postcode":"v7j 1s6",
    "addr:street":"27Th St E",
    "iso:country":"CA",
    "sg:address":"1341 27th St E",
    "sg:city":"North Vancouver",
    "sg:classifiers":[
        {
            "category":"Organizations",
            "subcategory":"Religious Organization",
            "type":"Services"
        }
    ],
    "sg:phone":"+1 604 986 4516",
    "sg:postcode":"V7J 1S6",
    "sg:province":"BC",
    "sg:tags":[
        "church"
    ],
    "wof:name":"Westlynn Baptist Church",
    "wof:placetype":"venue"
},
  "geometry": {"coordinates":[-123.036674499,49.3331794739],"type":"Point"}
}