{
  "type": "Feature",
  "properties": {
    "addr:full":"715 Harvey Ave Kelowna BC V1Y 6E2",
    "addr:housenumber":"715",
    "addr:postcode":"v1y 6e2",
    "addr:street":"Harvey Ave",
    "iso:country":"CA",
    "sg:address":"715 Harvey Ave",
    "sg:city":"Kelowna",
    "sg:classifiers":[
        {
            "category":"Autos & Motor Vehicles",
            "subcategory":"Fuel & Gas Station",
            "type":"Retail Goods"
        }
    ],
    "sg:phone":"+1 250 860 8311",
    "sg:postcode":"V1Y 6E2",
    "sg:province":"BC",
    "sg:tags":[
        "oil"
    ],
    "wof:name":"Richter Self Serve",
    "wof:placetype":"venue"
},
  "geometry": {"coordinates":[-119.486656,49.883461],"type":"Point"}
}