{
  "type": "Feature",
  "properties": {
    "addr:full":"1377 22 St SE Medicine Hat AB T1A 7V3",
    "addr:housenumber":"1377",
    "addr:postcode":"t1a 7v3",
    "addr:street":"22 St Se",
    "iso:country":"CA",
    "sg:address":"1377 22 St SE",
    "sg:city":"Medicine Hat",
    "sg:classifiers":[
        {
            "category":"Health Services",
            "subcategory":"Chiropractor",
            "type":"Services"
        }
    ],
    "sg:phone":"+1 403 526 8300",
    "sg:postcode":"T1A 7V3",
    "sg:province":"AB",
    "wof:name":"Jackle, Chad L DC",
    "wof:placetype":"venue"
},
  "geometry": {"coordinates":[-110.663459778,50.0190391541],"type":"Point"}
}