{
  "type": "Feature",
  "properties": {
    "addr:full":"North York ON M2N 3B3",
    "addr:postcode":"m2n 3b3",
    "iso:country":"CA",
    "sg:city":"North York",
    "sg:classifiers":[
        {
            "category":"Insurance",
            "subcategory":"Insurance Agent",
            "type":"Services"
        }
    ],
    "sg:phone":"+1 416 733 0006",
    "sg:postcode":"M2N 3B3",
    "sg:province":"ON",
    "wof:name":"E Paul Abbott Financial Group",
    "wof:placetype":"venue"
},
  "geometry": {"coordinates":[-79.390259,43.765961],"type":"Point"}
}