{
  "type": "Feature",
  "properties": {
    "addr:full":"3543 Ch D'Oka Saint-Joseph-Du-Lac QC J0N 1M0",
    "addr:housenumber":"3543",
    "addr:postcode":"j0n 1m0",
    "addr:street":"Ch D'Oka",
    "iso:country":"CA",
    "sg:address":"3543 Ch D'Oka",
    "sg:city":"Saint-Joseph-Du-Lac",
    "sg:classifiers":[
        {
            "category":"Restaurant",
            "type":"Food & Drink"
        }
    ],
    "sg:phone":"+1 450 472 6612",
    "sg:postcode":"J0N 1M0",
    "sg:province":"QC",
    "wof:name":"Restaurant L'Oasis",
    "wof:placetype":"venue"
},
  "geometry": {"coordinates":[-73.99696400000001,45.501682],"type":"Point"}
}