{
  "type": "Feature",
  "properties": {
    "iso:country":"CA",
    "sg:city":"Richmond",
    "sg:classifiers":[
        {
            "category":"Professional",
            "subcategory":"Lawyer & Legal Services",
            "type":"Services"
        }
    ],
    "sg:phone":"+1 604 273 8481",
    "sg:postcode":"V6X 3J6",
    "sg:province":"BC",
    "sg:tags":[
        "attorney"
    ],
    "wof:name":"Montague, Edward L",
    "wof:placetype":"venue"
},
  "geometry": {"coordinates":[-123.131660461,49.173084259],"type":"Point"}
}