{
  "type": "Feature",
  "properties": {
    "addr:full":"9535 Av Souligny Montreal QC H1L 2V4",
    "addr:housenumber":"9535",
    "addr:postcode":"h1l 2v4",
    "addr:street":"Av Souligny",
    "iso:country":"CA",
    "sg:address":"9535 Av Souligny",
    "sg:city":"Montreal",
    "sg:classifiers":[
        {
            "category":"Building & Trades",
            "subcategory":"Plumbing",
            "type":"Services"
        }
    ],
    "sg:phone":"+1 514 355 4929",
    "sg:postcode":"H1L 2V4",
    "sg:province":"QC",
    "sg:tags":[
        "contractor"
    ],
    "wof:name":"Plomberie Daniel Benoit Inc",
    "wof:placetype":"venue"
},
  "geometry": {"coordinates":[-73.513779,45.609558],"type":"Point"}
}