{
  "type": "Feature",
  "properties": {
    "addr:full":"1238 11 Ave SW Calgary AB T3C 0M4",
    "addr:housenumber":"1238",
    "addr:postcode":"t3c 0m4",
    "addr:street":"11 Ave Sw",
    "iso:country":"CA",
    "sg:address":"1238 11 Ave SW",
    "sg:city":"Calgary",
    "sg:classifiers":[
        {
            "category":"Shopping",
            "subcategory":"Florist",
            "type":"Retail Goods"
        }
    ],
    "sg:phone":"+1 403 245 3449",
    "sg:postcode":"T3C 0M4",
    "sg:province":"AB",
    "sg:tags":[
        "interior",
        "consultant",
        "design",
        "decorator"
    ],
    "wof:name":"Chintz & CO",
    "wof:placetype":"venue"
},
  "geometry": {"coordinates":[-114.089836121,51.0432548523],"type":"Point"}
}