{
  "type": "Feature",
  "properties": {
    "addr:full":"315 Second St W Brooks AB T1R 0E8",
    "addr:housenumber":"315",
    "addr:postcode":"ab t1r 0e8",
    "addr:street":"Second St W Brooks",
    "iso:country":"CA",
    "sg:address":"315 Second St W",
    "sg:city":"Brooks",
    "sg:classifiers":[
        {
            "category":"Insurance",
            "subcategory":"Insurance Agent",
            "type":"Services"
        }
    ],
    "sg:phone":"+1 403 362 3301",
    "sg:postcode":"T1R 0E8",
    "sg:province":"AB",
    "wof:name":"Wkb Newell Agencies",
    "wof:placetype":"venue"
},
  "geometry": {"coordinates":[-111.89849090600001,50.5678138733],"type":"Point"}
}