{
  "type": "Feature",
  "properties": {
    "addr:full":"2313 Main St Vancouver BC V5T 3C9",
    "addr:housenumber":"2313",
    "addr:postcode":"v5t 3c9",
    "addr:street":"Main St",
    "iso:country":"CA",
    "sg:address":"2313 Main St",
    "sg:city":"Vancouver",
    "sg:classifiers":[
        {
            "category":"Restaurant",
            "type":"Food & Drink"
        }
    ],
    "sg:phone":"+1 604 872 8779",
    "sg:postcode":"V5T 3C9",
    "sg:province":"BC",
    "wof:name":"Nirvana Restaurant",
    "wof:placetype":"venue"
},
  "geometry": {"coordinates":[-123.101067,49.264313],"type":"Point"}
}