{
  "type": "Feature",
  "properties": {
    "addr:full":"3122 Westsyde Rd Kamloops BC V2B 7G4",
    "addr:housenumber":"3122",
    "addr:postcode":"bc v2b 7g4",
    "addr:street":"Westsyde Rd",
    "iso:country":"CA",
    "sg:address":"3122 Westsyde Rd",
    "sg:city":"Kamloops",
    "sg:classifiers":[
        {
            "category":"Health Services",
            "subcategory":"Doctor",
            "type":"Services"
        }
    ],
    "sg:phone":"+1 250 579 8104",
    "sg:postcode":"V2B 7G4",
    "sg:province":"BC",
    "sg:tags":[
        "dentist"
    ],
    "wof:name":"Mehta, Rick DDS",
    "wof:placetype":"venue"
},
  "geometry": {"coordinates":[-120.34843444800001,50.7630233765],"type":"Point"}
}