{
  "type": "Feature",
  "properties": {
    "addr:full":"133 3rd Ave E Carberry MB R0K 0H0",
    "addr:housenumber":"133",
    "addr:postcode":"r0k 0h0",
    "addr:street":"3Rd Ave E",
    "iso:country":"CA",
    "sg:address":"133 3rd Ave E",
    "sg:city":"Carberry",
    "sg:classifiers":[
        {
            "category":"Restaurant",
            "type":"Food & Drink"
        }
    ],
    "sg:phone":"+1 204 834 2909",
    "sg:postcode":"R0K 0H0",
    "sg:province":"MB",
    "wof:name":"Summer Shack Drive Inn Rstrnt",
    "wof:placetype":"venue"
},
  "geometry": {"coordinates":[-99.3652038574,49.8680267334],"type":"Point"}
}