{
  "type": "Feature",
  "properties": {
    "addr:full":"Lac-Cayamant QC J0X 1Y0",
    "addr:postcode":"j0x 1y0",
    "iso:country":"CA",
    "sg:city":"Lac-Cayamant",
    "sg:classifiers":[
        {
            "category":"Shopping",
            "subcategory":"Bicycles & Sporting Goods",
            "type":"Retail Goods"
        }
    ],
    "sg:phone":"+1 819 463 0650",
    "sg:postcode":"J0X 1Y0",
    "sg:province":"QC",
    "sg:tags":[
        "hardware"
    ],
    "wof:name":"Gravel Quincaillerie",
    "wof:placetype":"venue"
},
  "geometry": {"coordinates":[-76.2474594116,46.1356391907],"type":"Point"}
}