{
  "type": "Feature",
  "properties": {
    "addr:full":"351 Wilson St E Ancaster ON L9G 2C1",
    "addr:housenumber":"351",
    "addr:postcode":"l9g 2c1",
    "addr:street":"Wilson St E",
    "iso:country":"CA",
    "sg:address":"351 Wilson St E",
    "sg:city":"Ancaster",
    "sg:classifiers":[
        {
            "category":"Personal",
            "subcategory":"Beauty Salon",
            "type":"Services"
        }
    ],
    "sg:phone":"+1 905 648 0733",
    "sg:postcode":"L9G 2C1",
    "sg:province":"ON",
    "wof:name":"Village Hair Design",
    "wof:placetype":"venue"
},
  "geometry": {"coordinates":[-79.9763336182,43.227180481],"type":"Point"}
}