{
  "type": "Feature",
  "properties": {
    "addr:full":"1080 Tristar Dr Mississauga ON L5T 1P1",
    "addr:housenumber":"1080",
    "addr:postcode":"l5t 1p1",
    "addr:street":"Tristar Dr",
    "iso:country":"CA",
    "sg:address":"1080 Tristar Dr",
    "sg:city":"Mississauga",
    "sg:classifiers":[
        {
            "category":"Wholesale",
            "subcategory":"Machinery & Supplies",
            "type":"Manufacturing & Wholesale Goods"
        }
    ],
    "sg:phone":"+1 905 670 2870",
    "sg:postcode":"L5T 1P1",
    "sg:province":"ON",
    "sg:tags":[
        "equipment",
        "printing"
    ],
    "wof:name":"Philips Graphic Svc Ltd",
    "wof:placetype":"venue"
},
  "geometry": {"coordinates":[-79.6657943726,43.6541061401],"type":"Point"}
}