{
  "type": "Feature",
  "properties": {
    "addr:full":"403 33rd St W Saskatoon SK S7L 0V5",
    "addr:housenumber":"403",
    "addr:postcode":"s7l 0v5",
    "addr:street":"33Rd St W",
    "iso:country":"CA",
    "sg:address":"403 33rd St W",
    "sg:city":"Saskatoon",
    "sg:classifiers":[
        {
            "category":"Restaurant",
            "type":"Food & Drink"
        }
    ],
    "sg:phone":"+1 306 242 3322",
    "sg:postcode":"S7L 0V5",
    "sg:province":"SK",
    "wof:name":"China Inn",
    "wof:placetype":"venue"
},
  "geometry": {"coordinates":[-106.67542299999999,52.143631],"type":"Point"}
}