{
  "type": "Feature",
  "properties": {
    "addr:full":"467 Newbold St London ON N6E 1V5",
    "addr:housenumber":"467",
    "addr:postcode":"n6e 1v5",
    "addr:street":"Newbold St",
    "iso:country":"CA",
    "sg:address":"467 Newbold St",
    "sg:city":"London",
    "sg:classifiers":[
        {
            "category":"Wholesale",
            "subcategory":"Scrap",
            "type":"Manufacturing & Wholesale Goods"
        }
    ],
    "sg:phone":"+1 519 681 4040",
    "sg:postcode":"N6E 1V5",
    "sg:province":"ON",
    "sg:tags":[
        "recycling",
        "center"
    ],
    "wof:name":"Bfi Canada",
    "wof:placetype":"venue"
},
  "geometry": {"coordinates":[-81.2111663818,42.9339141846],"type":"Point"}
}