{
  "type": "Feature",
  "properties": {
    "addr:full":"670 Woolwich St Guelph ON N1H 3Z1",
    "addr:housenumber":"670",
    "addr:postcode":"n1h 3z1",
    "addr:street":"Woolwich St",
    "iso:country":"CA",
    "sg:address":"670 Woolwich St",
    "sg:city":"Guelph",
    "sg:classifiers":[
        {
            "category":"Restaurant",
            "type":"Food & Drink"
        }
    ],
    "sg:phone":"+1 519 836 8806",
    "sg:postcode":"N1H 3Z1",
    "sg:province":"ON",
    "wof:name":"Arby's",
    "wof:placetype":"venue"
},
  "geometry": {"coordinates":[-80.2699127197,43.5593833923],"type":"Point"}
}