{
  "type": "Feature",
  "properties": {
    "addr:full":"117 Industrial Rd 2 Invermere BC V0A 1K5",
    "addr:housenumber":"117",
    "addr:postcode":"v0a 1k5",
    "addr:street":"Industrial Rd 2",
    "iso:country":"CA",
    "sg:address":"117 Industrial Rd 2",
    "sg:city":"Invermere",
    "sg:classifiers":[
        {
            "category":"Building & Trades",
            "subcategory":"Construction",
            "type":"Services"
        }
    ],
    "sg:phone":"+1 250 342 0313",
    "sg:postcode":"V0A 1K5",
    "sg:province":"BC",
    "sg:tags":[
        "boring",
        "drilling",
        "contractor"
    ],
    "wof:name":"Thompson Drilling",
    "wof:placetype":"venue"
},
  "geometry": {"coordinates":[-116.04216,50.509224],"type":"Point"}
}