{
  "type": "Feature",
  "properties": {
    "addr:full":"5488 Cape Rd Janeville NB E2A 5K2",
    "addr:housenumber":"5488",
    "addr:postcode":"e2a 5k2",
    "addr:street":"Cape Rd",
    "iso:country":"CA",
    "sg:address":"5488 Cape Rd",
    "sg:city":"Janeville",
    "sg:classifiers":[
        {
            "category":"Wholesale",
            "subcategory":"Seafood",
            "type":"Manufacturing & Wholesale Goods"
        }
    ],
    "sg:phone":"+1 506 546 4417",
    "sg:postcode":"E2A 5K2",
    "sg:province":"NB",
    "wof:name":"Coastal Harvesters Ltd",
    "wof:placetype":"venue"
},
  "geometry": {"coordinates":[-65.43699599999999,47.68837],"type":"Point"}
}