{
  "type": "Feature",
  "properties": {
    "iso:country":"CA",
    "sg:address":"6743 216th St",
    "sg:city":"Milner",
    "sg:classifiers":[
        {
            "category":"Shopping",
            "subcategory":"Used Merchandise",
            "type":"Retail Goods"
        }
    ],
    "sg:phone":"+1 604 534 7222",
    "sg:postcode":"V0X 1T0",
    "sg:province":"BC",
    "sg:tags":[
        "antique"
    ],
    "wof:name":"Napier's Country Antiques",
    "wof:placetype":"venue"
},
  "geometry": {"coordinates":[-122.61482238799999,49.13331604],"type":"Point"}
}