{
  "type": "Feature",
  "properties": {
    "addr:full":"Beausejour MB R0E 0C0",
    "addr:postcode":"r0e 0c0",
    "iso:country":"CA",
    "sg:city":"Beausejour",
    "sg:classifiers":[
        {
            "category":"Government",
            "subcategory":"Fire Station",
            "type":"Public Place"
        }
    ],
    "sg:phone":"+1 204 268 6043",
    "sg:postcode":"R0E 0C0",
    "sg:province":"MB",
    "sg:tags":[
        "department"
    ],
    "wof:name":"Manitoba Regional Office",
    "wof:placetype":"venue"
},
  "geometry": {"coordinates":[-96.51429748539999,50.0617866516],"type":"Point"}
}