{
  "type": "Feature",
  "properties": {
    "addr:full":"5409 206 St Langley BC V3A 2C5",
    "addr:housenumber":"5409",
    "addr:postcode":"v3a 2c5",
    "addr:street":"206 St",
    "iso:country":"CA",
    "sg:address":"5409 206 St",
    "sg:city":"Langley",
    "sg:classifiers":[
        {
            "category":"Education",
            "subcategory":"School",
            "type":"Public Place"
        }
    ],
    "sg:phone":"+1 604 533 4491",
    "sg:postcode":"V3A 2C5",
    "sg:province":"BC",
    "wof:name":"Douglas Park Community School",
    "wof:placetype":"venue"
},
  "geometry": {"coordinates":[-122.65203099999999,49.100643],"type":"Point"}
}