{
  "type": "Feature",
  "properties": {
    "addr:full":"275 Church Ave Winnipeg MB R2W 1B9",
    "addr:housenumber":"275",
    "addr:postcode":"r2w 1b9",
    "addr:street":"Church Ave",
    "iso:country":"CA",
    "sg:address":"275 Church Ave",
    "sg:city":"Winnipeg",
    "sg:classifiers":[
        {
            "category":"Education",
            "subcategory":"School",
            "type":"Public Place"
        }
    ],
    "sg:phone":"+1 204 586 5139",
    "sg:postcode":"R2W 1B9",
    "sg:province":"MB",
    "wof:name":"Champlain School",
    "wof:placetype":"venue"
},
  "geometry": {"coordinates":[-97.12962341310001,49.9230575562],"type":"Point"}
}