{
  "type": "Feature",
  "properties": {
    "addr:full":"Mississauga ON L4Y 4H9",
    "addr:postcode":"l4y 4h9",
    "iso:country":"CA",
    "sg:city":"Mississauga",
    "sg:classifiers":[
        {
            "category":"Restaurant",
            "type":"Food & Drink"
        }
    ],
    "sg:phone":"+1 905 281 8980",
    "sg:postcode":"L4Y 4H9",
    "sg:province":"ON",
    "sg:tags":[
        "delicatessen"
    ],
    "wof:name":"Croatia Meats & Deli",
    "wof:placetype":"venue"
},
  "geometry": {"coordinates":[-79.5943603516,43.5995330811],"type":"Point"}
}