{
  "type": "Feature",
  "properties": {
    "iso:country":"CA",
    "sg:address":"609 York St",
    "sg:city":"Fredericton",
    "sg:classifiers":[
        {
            "category":"Building & Trades",
            "subcategory":"Equipment Rental",
            "type":"Services"
        }
    ],
    "sg:phone":"+1 506 453 0819",
    "sg:postcode":"E3B 3R4",
    "sg:province":"NB",
    "sg:tags":[
        "yard"
    ],
    "wof:name":"Jumping Jack Inflatable Play",
    "wof:placetype":"venue"
},
  "geometry": {"coordinates":[-66.652641,45.952244],"type":"Point"}
}