{
  "type": "Feature",
  "properties": {
    "iso:country":"CA",
    "sg:address":"760 Rue Deligny",
    "sg:city":"Quebec",
    "sg:classifiers":[
        {
            "category":"Arts & Performance",
            "subcategory":"Theater",
            "type":"Entertainment"
        }
    ],
    "sg:phone":"+1 418 522 7426",
    "sg:postcode":"G1R 3A4",
    "sg:province":"QC",
    "sg:tags":[
        "clown"
    ],
    "wof:name":"Pico Le Clown",
    "wof:placetype":"venue"
},
  "geometry": {"coordinates":[-71.22315979,46.8096504211],"type":"Point"}
}