{
  "type": "Feature",
  "properties": {
    "addr:full":"Alfred ON K0B 1A0",
    "addr:postcode":"k0b 1a0",
    "iso:country":"CA",
    "sg:city":"Alfred",
    "sg:classifiers":[
        {
            "category":"Manufacturing",
            "subcategory":"Buildings",
            "type":"Manufacturing & Wholesale Goods"
        }
    ],
    "sg:phone":"+1 613 679 1204",
    "sg:postcode":"K0B 1A0",
    "sg:province":"ON",
    "sg:tags":[
        "home",
        "log",
        "cabin"
    ],
    "wof:name":"Renomarc Construction Ltd",
    "wof:placetype":"venue"
},
  "geometry": {"coordinates":[-74.88402600000001,45.557522],"type":"Point"}
}