{
  "type": "Feature",
  "properties": {
    "iso:country":"CA",
    "sg:city":"Red Deer",
    "sg:classifiers":[
        {
            "category":"Real Estate",
            "subcategory":"Real Estate Operator",
            "type":"Services"
        }
    ],
    "sg:phone":"+1 403 347 7731",
    "sg:postcode":"T4P 1C9",
    "sg:province":"AB",
    "sg:tags":[
        "mobile",
        "home",
        "community"
    ],
    "wof:name":"Mustang Acres",
    "wof:placetype":"venue"
},
  "geometry": {"coordinates":[-113.83026123,52.2919998169],"type":"Point"}
}