{
  "type": "Feature",
  "properties": {
    "addr:full":"10820 100 St Westlock AB T7P 2C3",
    "addr:housenumber":"10820",
    "addr:postcode":"t7p 2c3",
    "addr:street":"100 St",
    "iso:country":"CA",
    "sg:address":"10820 100 St",
    "sg:city":"Westlock",
    "sg:classifiers":[
        {
            "category":"Wholesale",
            "subcategory":"Machinery & Supplies",
            "type":"Manufacturing & Wholesale Goods"
        }
    ],
    "sg:phone":"+1 780 349 4055",
    "sg:postcode":"T7P 2C3",
    "sg:province":"AB",
    "sg:tags":[
        "farm",
        "equipment"
    ],
    "wof:name":"Ufa",
    "wof:placetype":"venue"
},
  "geometry": {"coordinates":[-113.836662,54.152275],"type":"Point"}
}