{
  "type": "Feature",
  "properties": {
    "addr:full":"4300 Steeles Ave W Woodbridge ON L4L 4C2",
    "addr:housenumber":"4300",
    "addr:postcode":"l4l 4c2",
    "addr:street":"Steeles Ave W",
    "iso:country":"CA",
    "sg:address":"4300 Steeles Ave W",
    "sg:city":"Woodbridge",
    "sg:classifiers":[
        {
            "category":"Organizations",
            "subcategory":"Professional Association",
            "type":"Services"
        }
    ],
    "sg:phone":"+1 905 856 5775",
    "sg:postcode":"L4L 4C2",
    "sg:province":"ON",
    "wof:name":"Associazione Trapanesi",
    "wof:placetype":"venue"
},
  "geometry": {"coordinates":[-79.561134,43.767429],"type":"Point"}
}