{
  "type": "Feature",
  "properties": {
    "addr:full":"3219 New St Burlington ON L7N 1M9",
    "addr:housenumber":"3219",
    "addr:postcode":"l7n 1m9",
    "addr:street":"New St",
    "iso:country":"CA",
    "sg:address":"3219 New St",
    "sg:city":"Burlington",
    "sg:classifiers":[
        {
            "category":"Shopping",
            "subcategory":"Clothing, Apparel, & Fashions",
            "type":"Retail Goods"
        }
    ],
    "sg:phone":"+1 905 637 2763",
    "sg:postcode":"L7N 1M9",
    "sg:province":"ON",
    "sg:tags":[
        "tailor"
    ],
    "wof:name":"Burlington Tailors",
    "wof:placetype":"venue"
},
  "geometry": {"coordinates":[-79.77924299999999,43.344105],"type":"Point"}
}