{
  "type": "Feature",
  "properties": {
    "iso:country":"CA",
    "sg:address":"3219 New St",
    "sg:city":"Burlington",
    "sg:classifiers":[
        {
            "category":"Shopping",
            "subcategory":"Clothing, Apparel, & Fashions",
            "type":"Retail Goods"
        }
    ],
    "sg:phone":"+1 905 637 2763",
    "sg:postcode":"L7N 1M9",
    "sg:province":"ON",
    "sg:tags":[
        "tailor"
    ],
    "wof:name":"Burlington Tailors",
    "wof:placetype":"venue"
},
  "geometry": {"coordinates":[-79.779243,43.344105],"type":"Point"}
}