{
  "type": "Feature",
  "properties": {
    "addr:full":"8 Vine Cres Barrie ON L4N 2B3",
    "addr:housenumber":"8",
    "addr:postcode":"l4n 2b3",
    "addr:street":"Vine Cres",
    "iso:country":"CA",
    "sg:address":"8 Vine Cres",
    "sg:city":"Barrie",
    "sg:classifiers":[
        {
            "category":"Manufacturing",
            "subcategory":"Tools & Machinery",
            "type":"Manufacturing & Wholesale Goods"
        }
    ],
    "sg:phone":"+1 705 739 7155",
    "sg:postcode":"L4N 2B3",
    "sg:province":"ON",
    "sg:tags":[
        "equipment",
        "system",
        "automation"
    ],
    "wof:name":"Programmable Controller Supprt",
    "wof:placetype":"venue"
},
  "geometry": {"coordinates":[-79.70938099999999,44.390228],"type":"Point"}
}