{
  "type": "Feature",
  "properties": {
    "iso:country":"CA",
    "sg:city":"Mississauga",
    "sg:classifiers":[
        {
            "category":"Arts & Performance",
            "subcategory":"Theater",
            "type":"Entertainment"
        }
    ],
    "sg:phone":"+1 905 828 5779",
    "sg:postcode":"L5L 1X2",
    "sg:province":"ON",
    "sg:tags":[
        "equipment",
        "theatrical",
        "supply"
    ],
    "wof:name":"Niscon Inc",
    "wof:placetype":"venue"
},
  "geometry": {"coordinates":[-79.672684,43.534798],"type":"Point"}
}