{
  "type": "Feature",
  "properties": {
    "addr:full":"430 Steelcase Rd E Markham ON L3R 1G2",
    "addr:housenumber":"430",
    "addr:postcode":"l3r 1g2",
    "addr:street":"Steelcase Rd E",
    "iso:country":"CA",
    "sg:address":"430 Steelcase Rd E",
    "sg:city":"Markham",
    "sg:classifiers":[
        {
            "category":"Wholesale",
            "subcategory":"Apparel",
            "type":"Manufacturing & Wholesale Goods"
        }
    ],
    "sg:phone":"+1 905 475 8922",
    "sg:postcode":"L3R 1G2",
    "sg:province":"ON",
    "sg:tags":[
        "clothing"
    ],
    "wof:name":"Intimelle Inc",
    "wof:placetype":"venue"
},
  "geometry": {"coordinates":[-79.33873699999999,43.822701],"type":"Point"}
}