{
  "type": "Feature",
  "properties": {
    "addr:full":"1374 Kingston Rd Scarborough ON M1N 1R2",
    "addr:housenumber":"1374",
    "addr:postcode":"m1n 1r2",
    "addr:street":"Kingston Rd",
    "iso:country":"CA",
    "sg:address":"1374 Kingston Rd",
    "sg:city":"Scarborough",
    "sg:classifiers":[
        {
            "category":"Personal",
            "subcategory":"Beauty Salon",
            "type":"Services"
        }
    ],
    "sg:phone":"+1 416 690 9655",
    "sg:postcode":"M1N 1R2",
    "sg:province":"ON",
    "wof:name":"Cut Hut Unisex Hairstyling",
    "wof:placetype":"venue"
},
  "geometry": {"coordinates":[-79.273438,43.686256],"type":"Point"}
}