{
  "type": "Feature",
  "properties": {
    "addr:full":"Mississauga ON L4Z 1H8",
    "addr:postcode":"l4z 1h8",
    "iso:country":"CA",
    "sg:city":"Mississauga",
    "sg:classifiers":[
        {
            "category":"Wholesale",
            "subcategory":"Durable Goods & Equipment",
            "type":"Manufacturing & Wholesale Goods"
        }
    ],
    "sg:phone":"+1 905 272 4883",
    "sg:postcode":"L4Z 1H8",
    "sg:province":"ON",
    "sg:tags":[
        "representative",
        "manufacturer"
    ],
    "wof:name":"Maxim Toastmaster",
    "wof:placetype":"venue"
},
  "geometry": {"coordinates":[-79.637939,43.596294],"type":"Point"}
}