{
  "type": "Feature",
  "properties": {
    "iso:country":"CA",
    "sg:address":"PO Box 911",
    "sg:city":"Qikiqtarjuaq",
    "sg:classifiers":[
        {
            "category":"Health Services",
            "subcategory":"Clinic",
            "type":"Services"
        }
    ],
    "sg:phone":"+1 867 927 8916",
    "sg:postcode":"X0A 0B0",
    "sg:province":"NU",
    "wof:name":"Health Centre",
    "wof:placetype":"venue"
},
  "geometry": {"coordinates":[-64.02360534669999,67.5586090088],"type":"Point"}
}