{
  "type": "Feature",
  "properties": {
    "addr:full":"255 Sixth St New Westminster BC V3L 3A5",
    "addr:housenumber":"255",
    "addr:postcode":"v3l 3a5",
    "addr:street":"Sixth St",
    "iso:country":"CA",
    "sg:address":"255 Sixth St",
    "sg:city":"New Westminster",
    "sg:classifiers":[
        {
            "category":"Insurance",
            "subcategory":"Insurance Agent",
            "type":"Services"
        }
    ],
    "sg:phone":"+1 604 525 4676",
    "sg:postcode":"V3L 3A5",
    "sg:province":"BC",
    "wof:name":"Atkinson & Terry Insurance Ltd",
    "wof:placetype":"venue"
},
  "geometry": {"coordinates":[-122.914161682,49.2084732056],"type":"Point"}
}