{
  "type": "Feature",
  "properties": {
    "addr:full":"210 1st St W Delisle SK S0L 0P0",
    "addr:housenumber":"210",
    "addr:postcode":"s0l 0p0",
    "addr:street":"1St St W Delisle",
    "iso:country":"CA",
    "sg:address":"210 1st St W",
    "sg:city":"Delisle",
    "sg:classifiers":[
        {
            "category":"Banks & Credit Unions",
            "subcategory":"Bank",
            "type":"Services"
        }
    ],
    "sg:phone":"+1 306 493 2414",
    "sg:postcode":"S0L 0P0",
    "sg:province":"SK",
    "wof:name":"Delisle Credit Union Ltd",
    "wof:placetype":"venue"
},
  "geometry": {"coordinates":[-107.134941101,51.9238395691],"type":"Point"}
}