{
  "type": "Feature",
  "properties": {
    "addr:full":"1242 Davie St Vancouver BC V6E 1N3",
    "addr:housenumber":"1242",
    "addr:postcode":"v6e 1n3",
    "addr:street":"Davie St",
    "iso:country":"CA",
    "sg:address":"1242 Davie St",
    "sg:city":"Vancouver",
    "sg:classifiers":[
        {
            "category":"Shopping",
            "type":"Retail Goods"
        }
    ],
    "sg:phone":"+1 604 683 3415",
    "sg:postcode":"V6E 1N3",
    "sg:province":"BC",
    "sg:tags":[
        "picture",
        "frame"
    ],
    "wof:name":"Davie Art Shop",
    "wof:placetype":"venue"
},
  "geometry": {"coordinates":[-123.134231567,49.2821617126],"type":"Point"}
}