{
  "type": "Feature",
  "properties": {
    "iso:country":"CA",
    "sg:address":"9 Jackman Dr",
    "sg:city":"Mount Pearl",
    "sg:classifiers":[
        {
            "category":"Building & Trades",
            "subcategory":"Construction",
            "type":"Services"
        }
    ],
    "sg:phone":"+1 709 364 1450",
    "sg:postcode":"A1N 2J8",
    "sg:province":"NL",
    "sg:tags":[
        "general",
        "contractor"
    ],
    "wof:name":"Rjf Contracting Ltd",
    "wof:placetype":"venue"
},
  "geometry": {"coordinates":[-52.8078460693,47.5060501099],"type":"Point"}
}