{
  "type": "Feature",
  "properties": {
    "iso:country":"CA",
    "sg:address":"294 Rue Gladstone",
    "sg:city":"Greenfield Park",
    "sg:classifiers":[
        {
            "category":"Restaurant",
            "type":"Food & Drink"
        }
    ],
    "sg:phone":"+1 450 671 1122",
    "sg:postcode":"J4V 2P7",
    "sg:province":"QC",
    "wof:name":"Restaurant Le Quai D'Or",
    "wof:placetype":"venue"
},
  "geometry": {"coordinates":[-73.480736,45.492638],"type":"Point"}
}