{
  "type": "Feature",
  "properties": {
    "addr:full":"191 South Mccarthy St Campbell River BC V9W 5P8",
    "addr:housenumber":"191",
    "addr:postcode":"v9w 5p8",
    "addr:street":"South Mccarthy St",
    "iso:country":"CA",
    "sg:address":"191 South Mccarthy St",
    "sg:city":"Campbell River",
    "sg:classifiers":[
        {
            "category":"Building & Trades",
            "subcategory":"Construction",
            "type":"Services"
        }
    ],
    "sg:phone":"+1 250 286 3512",
    "sg:postcode":"V9W 5P8",
    "sg:province":"BC",
    "sg:tags":[
        "general",
        "contractor"
    ],
    "wof:name":"Tnt Contracting",
    "wof:placetype":"venue"
},
  "geometry": {"coordinates":[-125.240455627,50.0042190552],"type":"Point"}
}