{
  "type": "Feature",
  "properties": {
    "addr:full":"6533 Rue Saint-Jacques Montreal QC H4B 1V3",
    "addr:housenumber":"6533",
    "addr:postcode":"h4b 1v3",
    "addr:street":"Rue Saint-Jacques",
    "iso:country":"CA",
    "sg:address":"6533 Rue Saint-Jacques",
    "sg:city":"Montreal",
    "sg:classifiers":[
        {
            "category":"Autos & Motor Vehicles",
            "subcategory":"Auto Supplies",
            "type":"Retail Goods"
        }
    ],
    "sg:phone":"+1 514 487 5545",
    "sg:postcode":"H4B 1V3",
    "sg:province":"QC",
    "sg:tags":[
        "tire"
    ],
    "wof:name":"Merson Automotive Inc",
    "wof:placetype":"venue"
},
  "geometry": {"coordinates":[-73.6260223389,45.4606781006],"type":"Point"}
}