{
  "type": "Feature",
  "properties": {
    "addr:full":"871 Rang DE L'Eglise Saint-Eugene-DE-Grantham QC J0C 1J0",
    "addr:housenumber":"871",
    "addr:postcode":"j0c 1j0",
    "addr:street":"Rang De L'Eglise Saint-Eugene-De-Grantham",
    "iso:country":"CA",
    "sg:address":"871 Rang DE L'Eglise",
    "sg:city":"Saint-Eugene-DE-Grantham",
    "sg:classifiers":[
        {
            "category":"Wholesale",
            "subcategory":"Farm Supplies",
            "type":"Manufacturing & Wholesale Goods"
        }
    ],
    "sg:phone":"+1 819 396 3279",
    "sg:postcode":"J0C 1J0",
    "sg:province":"QC",
    "sg:tags":[
        "feed"
    ],
    "wof:name":"Distribution Michel Jette Inc",
    "wof:placetype":"venue"
},
  "geometry": {"coordinates":[-72.774513,45.877846],"type":"Point"}
}