{
  "type": "Feature",
  "properties": {
    "addr:full":"171 7E Ave E Macamic QC J0Z 2S0",
    "addr:housenumber":"171",
    "addr:postcode":"j0z 2s0",
    "addr:street":"7E Ave E Macamic",
    "iso:country":"CA",
    "sg:address":"171 7E Ave E",
    "sg:city":"Macamic",
    "sg:classifiers":[
        {
            "category":"Health Services",
            "subcategory":"Nursing And Care Facility",
            "type":"Services"
        }
    ],
    "sg:phone":"+1 819 782 2522",
    "sg:postcode":"J0Z 2S0",
    "sg:province":"QC",
    "sg:tags":[
        "home",
        "rest",
        "site",
        "reception",
        "wedding"
    ],
    "wof:name":"Pavillon Royal Roussillon",
    "wof:placetype":"venue"
},
  "geometry": {"coordinates":[-78.98477172849999,48.7538566589],"type":"Point"}
}