{
  "type": "Feature",
  "properties": {
    "addr:full":"830 Main St Canmore AB T1W 2B7",
    "addr:housenumber":"830",
    "addr:postcode":"t1w 2b7",
    "addr:street":"Main St",
    "iso:country":"CA",
    "sg:address":"830 Main St",
    "sg:city":"Canmore",
    "sg:classifiers":[
        {
            "category":"Shopping",
            "subcategory":"Clothing, Apparel, & Fashions",
            "type":"Retail Goods"
        }
    ],
    "sg:phone":"+1 403 678 8853",
    "sg:postcode":"T1W 2B7",
    "sg:province":"AB",
    "sg:tags":[
        "snowboard"
    ],
    "wof:name":"Frozen Ocean",
    "wof:placetype":"venue"
},
  "geometry": {"coordinates":[-115.36170959499999,51.0893135071],"type":"Point"}
}