{
  "type": "Feature",
  "properties": {
    "iso:country":"CA",
    "sg:address":"587 Rue Notre-Dame",
    "sg:city":"Repentigny",
    "sg:classifiers":[
        {
            "category":"Manufacturing",
            "subcategory":"Tools & Machinery",
            "type":"Manufacturing & Wholesale Goods"
        }
    ],
    "sg:phone":"+1 450 585 0800",
    "sg:postcode":"J6A 2V2",
    "sg:province":"QC",
    "sg:tags":[
        "water",
        "equipment",
        "works",
        "supply"
    ],
    "wof:name":"Boutique D'Animaux Donald Inc",
    "wof:placetype":"venue"
},
  "geometry": {"coordinates":[-73.436264,45.747604],"type":"Point"}
}