{
  "type": "Feature",
  "properties": {
    "addr:full":"3429 Normandy St Saskatoon SK S7M 3R1",
    "addr:housenumber":"3429",
    "addr:postcode":"s7m 3r1",
    "addr:street":"Normandy St",
    "iso:country":"CA",
    "sg:address":"3429 Normandy St",
    "sg:city":"Saskatoon",
    "sg:classifiers":[
        {
            "category":"Building & Trades",
            "subcategory":"Electrical",
            "type":"Services"
        }
    ],
    "sg:phone":"+1 306 384 3228",
    "sg:postcode":"S7M 3R1",
    "sg:province":"SK",
    "sg:tags":[
        "electric",
        "contractor"
    ],
    "wof:name":"Double D Electrical Svc",
    "wof:placetype":"venue"
},
  "geometry": {"coordinates":[-106.738167,52.110687],"type":"Point"}
}