{
  "type": "Feature",
  "properties": {
    "addr:full":"1360 Av Galilee Quebec QC G1P 4E3",
    "addr:housenumber":"1360",
    "addr:postcode":"g1p 4e3",
    "addr:street":"Av Galilee",
    "iso:country":"CA",
    "sg:address":"1360 Av Galilee",
    "sg:city":"Quebec",
    "sg:classifiers":[
        {
            "category":"Wholesale",
            "subcategory":"Stationery",
            "type":"Manufacturing & Wholesale Goods"
        }
    ],
    "sg:phone":"+1 418 681 2320",
    "sg:postcode":"G1P 4E3",
    "sg:province":"QC",
    "sg:tags":[
        "packaging",
        "equipment",
        "supply"
    ],
    "wof:name":"L Boucher Inc",
    "wof:placetype":"venue"
},
  "geometry": {"coordinates":[-71.30107879640001,46.8051795959],"type":"Point"}
}