{
  "type": "Feature",
  "properties": {
    "iso:country":"CA",
    "sg:address":"313 Old Airport Rd",
    "sg:city":"Yellowknife",
    "sg:classifiers":[
        {
            "category":"Restaurant",
            "type":"Food & Drink"
        }
    ],
    "sg:phone":"+1 867 873 9556",
    "sg:postcode":"X1A 3T3",
    "sg:province":"NT",
    "wof:name":"Mc Donald's",
    "wof:placetype":"venue"
},
  "geometry": {"coordinates":[-114.413734436,62.4627304077],"type":"Point"}
}