{
  "type": "Feature",
  "properties": {
    "addr:full":"2963 Southern Cres Abbotsford BC V2T 5H8",
    "addr:housenumber":"2963",
    "addr:postcode":"v2t 5h8",
    "addr:street":"Southern Cres",
    "iso:country":"CA",
    "sg:address":"2963 Southern Cres",
    "sg:city":"Abbotsford",
    "sg:classifiers":[
        {
            "category":"Home & Garden",
            "subcategory":"Building Materials",
            "type":"Retail Goods"
        }
    ],
    "sg:phone":"+1 604 855 4346",
    "sg:postcode":"V2T 5H8",
    "sg:province":"BC",
    "sg:tags":[
        "type",
        "door"
    ],
    "wof:name":"W K Garage Doors",
    "wof:placetype":"venue"
},
  "geometry": {"coordinates":[-122.357338,49.055492],"type":"Point"}
}