{
  "type": "Feature",
  "properties": {
    "addr:full":"546 Seeleys Cove Rd Seeleys Cove NB E5H 2E8",
    "addr:housenumber":"546",
    "addr:postcode":"e5h 2e8",
    "addr:street":"Seeleys Cove Rd",
    "iso:country":"CA",
    "sg:address":"546 Seeleys Cove Rd",
    "sg:city":"Seeleys Cove",
    "sg:classifiers":[
        {
            "category":"Manufacturing",
            "subcategory":"Electronics",
            "type":"Manufacturing & Wholesale Goods"
        }
    ],
    "sg:phone":"+1 506 755 2573",
    "sg:postcode":"E5H 2E8",
    "sg:province":"NB",
    "sg:tags":[
        "electric",
        "alarm",
        "burglar",
        "system",
        "contractor"
    ],
    "wof:name":"Spear T Electric",
    "wof:placetype":"venue"
},
  "geometry": {"coordinates":[-66.662766,45.090797],"type":"Point"}
}