{
  "type": "Feature",
  "properties": {
    "addr:full":"Trail BC V1R 4N7",
    "addr:postcode":"bc v1r 4n7",
    "addr:street":"Trail",
    "iso:country":"CA",
    "sg:city":"Trail",
    "sg:classifiers":[
        {
            "category":"Shopping",
            "subcategory":"Music",
            "type":"Retail Goods"
        }
    ],
    "sg:phone":"+1 250 364 0330",
    "sg:postcode":"V1R 4N7",
    "sg:province":"BC",
    "sg:tags":[
        "compact",
        "record",
        "disc",
        "tape"
    ],
    "wof:name":"Cd Plus.com",
    "wof:placetype":"venue"
},
  "geometry": {"coordinates":[-117.71221199999999,49.096451],"type":"Point"}
}