{
  "type": "Feature",
  "properties": {
    "addr:full":"453 Laurier Ave E Ottawa ON K1N 6R4",
    "addr:housenumber":"453",
    "addr:postcode":"k1n 6r4",
    "addr:street":"Laurier Ave E",
    "iso:country":"CA",
    "sg:address":"453 Laurier Ave E",
    "sg:city":"Ottawa",
    "sg:classifiers":[
        {
            "category":"Education",
            "subcategory":"Special Training",
            "type":"Public Place"
        }
    ],
    "sg:phone":"+1 613 236 2433",
    "sg:postcode":"K1N 6R4",
    "sg:province":"ON",
    "sg:tags":[
        "school"
    ],
    "wof:name":"Cordon Bleu Ottawa Culinary",
    "wof:placetype":"venue"
},
  "geometry": {"coordinates":[-75.674469,45.428978],"type":"Point"}
}