{
  "type": "Feature",
  "properties": {
    "addr:full":"10110 107 Ave NW Edmonton AB T5H 0V5",
    "addr:housenumber":"10110",
    "addr:postcode":"t5h 0v5",
    "addr:street":"107 Ave Nw",
    "iso:country":"CA",
    "sg:address":"10110 107 Ave NW",
    "sg:city":"Edmonton",
    "sg:classifiers":[
        {
            "category":"Social Services",
            "subcategory":"Child Care",
            "type":"Services"
        }
    ],
    "sg:phone":"+1 780 425 8373",
    "sg:postcode":"T5H 0V5",
    "sg:province":"AB",
    "wof:name":"Mikey's Day Care",
    "wof:placetype":"venue"
},
  "geometry": {"coordinates":[-113.49406399999999,53.551647],"type":"Point"}
}