{
  "type": "Feature",
  "properties": {
    "iso:country":"CA",
    "sg:city":"Repentigny",
    "sg:classifiers":[
        {
            "category":"Personal",
            "subcategory":"Beauty Salon",
            "type":"Services"
        }
    ],
    "sg:phone":"+1 450 585 4885",
    "sg:postcode":"J6A 2S5",
    "sg:province":"QC",
    "wof:name":"Salon Momo IV",
    "wof:placetype":"venue"
},
  "geometry": {"coordinates":[-73.4514160156,45.7340927124],"type":"Point"}
}