{
  "type": "Feature",
  "properties": {
    "addr:full":"108 Hotel DE Ville Grande-Riviere QC G0C 1V0",
    "addr:housenumber":"108",
    "addr:postcode":"g0c 1v0",
    "addr:street":"Hotel De Ville",
    "iso:country":"CA",
    "sg:address":"108 Hotel DE Ville",
    "sg:city":"Grande-Riviere",
    "sg:classifiers":[
        {
            "category":"Government",
            "subcategory":"Office",
            "type":"Public Place"
        }
    ],
    "sg:phone":"+1 418 385 2282",
    "sg:postcode":"G0C 1V0",
    "sg:province":"QC",
    "sg:tags":[
        "village"
    ],
    "wof:name":"Grande Riviere Administration",
    "wof:placetype":"venue"
},
  "geometry": {"coordinates":[-64.4967346191,48.4000473022],"type":"Point"}
}