{
  "type": "Feature",
  "properties": {
    "iso:country":"CA",
    "sg:address":"8790 Av Royale",
    "sg:city":"Chateau-Richer",
    "sg:classifiers":[
        {
            "category":"Recreation",
            "type":"Entertainment"
        }
    ],
    "sg:phone":"+1 418 824 4478",
    "sg:postcode":"G0A 1N0",
    "sg:province":"QC",
    "sg:tags":[
        "hall",
        "auditorium"
    ],
    "wof:name":"Baker's Inn Auberge",
    "wof:placetype":"venue"
},
  "geometry": {"coordinates":[-70.98169708250001,47.0009803772],"type":"Point"}
}