{
  "type": "Feature",
  "properties": {
    "iso:country":"CA",
    "sg:address":"1321 94 Ave",
    "sg:city":"Dawson Creek",
    "sg:classifiers":[
        {
            "category":"Home & Garden",
            "subcategory":"Building Materials",
            "type":"Retail Goods"
        }
    ],
    "sg:phone":"+1 250 782 8053",
    "sg:postcode":"V1G 1G7",
    "sg:province":"BC",
    "sg:tags":[
        "glass",
        "window",
        "plate"
    ],
    "wof:name":"Rss Auto Glass",
    "wof:placetype":"venue"
},
  "geometry": {"coordinates":[-120.238716126,55.7686042786],"type":"Point"}
}