{
  "type": "Feature",
  "properties": {
    "iso:country":"CA",
    "sg:address":"RR 6 STN Main",
    "sg:city":"Goderich",
    "sg:classifiers":[
        {
            "category":"Real Estate",
            "subcategory":"Real Estate Operator",
            "type":"Services"
        }
    ],
    "sg:phone":"+1 519 524 5534",
    "sg:postcode":"N7A 3Y3",
    "sg:province":"ON",
    "sg:tags":[
        "mobile",
        "home",
        "community"
    ],
    "wof:name":"Huron Haven Village",
    "wof:placetype":"venue"
},
  "geometry": {"coordinates":[-81.7077636719,43.742641449],"type":"Point"}
}