{
  "type": "Feature",
  "properties": {
    "iso:country":"CA",
    "sg:address":"350 Cheadle St W",
    "sg:city":"Swift Current",
    "sg:classifiers":[
        {
            "category":"Government",
            "subcategory":"Office",
            "type":"Public Place"
        }
    ],
    "sg:phone":"+1 306 778 8200",
    "sg:postcode":"S9H 4G3",
    "sg:province":"SK",
    "wof:name":"Saskatchewan Land Titles Ofc",
    "wof:placetype":"venue"
},
  "geometry": {"coordinates":[-107.8046875,50.2832450867],"type":"Point"}
}