{
  "type": "Feature",
  "properties": {
    "addr:full":"9331 39 Ave NW Edmonton AB T6E 5T3",
    "addr:housenumber":"9331",
    "addr:postcode":"t6e 5t3",
    "addr:street":"39 Ave Nw",
    "iso:country":"CA",
    "sg:address":"9331 39 Ave NW",
    "sg:city":"Edmonton",
    "sg:classifiers":[
        {
            "category":"Manufacturing",
            "subcategory":"Tools & Machinery",
            "type":"Manufacturing & Wholesale Goods"
        }
    ],
    "sg:phone":"+1 780 469 2346",
    "sg:postcode":"T6E 5T3",
    "sg:province":"AB",
    "sg:tags":[
        "machine",
        "shop"
    ],
    "wof:name":"Cnc Industries Ltd",
    "wof:placetype":"venue"
},
  "geometry": {"coordinates":[-113.474335,53.473972],"type":"Point"}
}