{
  "type": "Feature",
  "properties": {
    "addr:full":"1533 Broadway W Vancouver BC V6J 1W6",
    "addr:housenumber":"1533",
    "addr:postcode":"v6j 1w6",
    "addr:street":"Broadway W",
    "iso:country":"CA",
    "sg:address":"1533 Broadway W",
    "sg:city":"Vancouver",
    "sg:classifiers":[
        {
            "category":"Shopping",
            "subcategory":"Books",
            "type":"Retail Goods"
        }
    ],
    "sg:phone":"+1 604 731 0553",
    "sg:postcode":"V6J 1W6",
    "sg:province":"BC",
    "sg:tags":[
        "dealer"
    ],
    "wof:name":"Oscar's Art Books",
    "wof:placetype":"venue"
},
  "geometry": {"coordinates":[-123.139427185,49.2637786865],"type":"Point"}
}