{
  "type": "Feature",
  "properties": {
    "addr:full":"405 Sackville Dr Lower Sackville NS B4C 2R9",
    "addr:housenumber":"405",
    "addr:postcode":"b4c 2r9",
    "addr:street":"Sackville Dr",
    "iso:country":"CA",
    "sg:address":"405 Sackville Dr",
    "sg:city":"Lower Sackville",
    "sg:classifiers":[
        {
            "category":"Insurance",
            "subcategory":"Insurance Agent",
            "type":"Services"
        }
    ],
    "sg:phone":"+1 902 865 3689",
    "sg:postcode":"B4C 2R9",
    "sg:province":"NS",
    "wof:name":"Hed Insurance Brokerage Grp",
    "wof:placetype":"venue"
},
  "geometry": {"coordinates":[-63.67627,44.764191],"type":"Point"}
}