{
  "type": "Feature",
  "properties": {
    "addr:full":"2832 Queensway Prince George BC V2L 4M5",
    "addr:housenumber":"2832",
    "addr:postcode":"v2l 4m5",
    "addr:street":"Queensway",
    "iso:country":"CA",
    "sg:address":"2832 Queensway",
    "sg:city":"Prince George",
    "sg:classifiers":[
        {
            "category":"Local Transit",
            "type":"Transportation"
        }
    ],
    "sg:phone":"+1 250 562 1394",
    "sg:postcode":"V2L 4M5",
    "sg:province":"BC",
    "sg:tags":[
        "organization",
        "line",
        "social",
        "bus",
        "welfare"
    ],
    "wof:name":"Carefree Society",
    "wof:placetype":"venue"
},
  "geometry": {"coordinates":[-122.743911743,53.8942298889],"type":"Point"}
}