{
  "type": "Feature",
  "properties": {
    "addr:full":"25 155E Rue Saint-Georges QC G5Y 2J5",
    "addr:housenumber":"25",
    "addr:postcode":"g5y 2j5",
    "addr:street":"155E Rue",
    "iso:country":"CA",
    "sg:address":"25 155E Rue",
    "sg:city":"Saint-Georges",
    "sg:classifiers":[
        {
            "category":"Cinema",
            "subcategory":"Movie Theater",
            "type":"Entertainment"
        }
    ],
    "sg:phone":"+1 418 228 8383",
    "sg:postcode":"G5Y 2J5",
    "sg:province":"QC",
    "wof:name":"Cine-Parc St-Georges",
    "wof:placetype":"venue"
},
  "geometry": {"coordinates":[-70.6590423584,46.1024169922],"type":"Point"}
}