{
  "type": "Feature",
  "properties": {
    "iso:country":"CA",
    "sg:city":"Victoria",
    "sg:classifiers":[
        {
            "category":"Professional",
            "subcategory":"Lawyer & Legal Services",
            "type":"Services"
        }
    ],
    "sg:phone":"+1 250 388 4457",
    "sg:postcode":"V8W 1H9",
    "sg:province":"BC",
    "sg:tags":[
        "attorney"
    ],
    "wof:name":"Cox Taylor",
    "wof:placetype":"venue"
},
  "geometry": {"coordinates":[-123.36937,48.426075],"type":"Point"}
}