{
  "type": "Feature",
  "properties": {
    "iso:country":"CA",
    "sg:address":"8780 Boul Saint-Michel",
    "sg:city":"Montreal",
    "sg:classifiers":[
        {
            "category":"Personal",
            "subcategory":"Beauty Salon",
            "type":"Services"
        }
    ],
    "sg:phone":"+1 514 728 5132",
    "sg:postcode":"H1Z 3G2",
    "sg:province":"QC",
    "wof:name":"Salon Richard Gelin",
    "wof:placetype":"venue"
},
  "geometry": {"coordinates":[-73.622849,45.569443],"type":"Point"}
}