{
  "type": "Feature",
  "properties": {
    "addr:full":"Fort Mcmurray AB T9H 3R5",
    "addr:postcode":"t9h 3r5",
    "iso:country":"CA",
    "sg:city":"Fort Mcmurray",
    "sg:classifiers":[
        {
            "category":"Building & Trades",
            "subcategory":"Construction",
            "type":"Services"
        }
    ],
    "sg:phone":"+1 780 743 3230",
    "sg:postcode":"T9H 3R5",
    "sg:province":"AB",
    "sg:tags":[
        "repairing",
        "cabinet",
        "remodeling",
        "maker",
        "contractor"
    ],
    "wof:name":"Woodshop",
    "wof:placetype":"venue"
},
  "geometry": {"coordinates":[-111.356499,56.692215],"type":"Point"}
}