{
  "type": "Feature",
  "properties": {
    "addr:full":"Maryhill ON N0B 2B0",
    "addr:postcode":"n0b 2b0",
    "iso:country":"CA",
    "sg:city":"Maryhill",
    "sg:classifiers":[
        {
            "category":"Health Services",
            "subcategory":"Nursing And Care Facility",
            "type":"Services"
        }
    ],
    "sg:phone":"+1 519 648 2117",
    "sg:postcode":"N0B 2B0",
    "sg:province":"ON",
    "sg:tags":[
        "home",
        "convalescent"
    ],
    "wof:name":"Twin Oaks of Maryhill Inc",
    "wof:placetype":"venue"
},
  "geometry": {"coordinates":[-80.394463,43.538441],"type":"Point"}
}