{
  "type": "Feature",
  "properties": {
    "addr:full":"53 Rue Gaston Saint-Bernard-DE-Lacolle QC J0J 1V0",
    "addr:housenumber":"53",
    "addr:postcode":"j0j 1v0",
    "addr:street":"Rue Gaston",
    "iso:country":"CA",
    "sg:address":"53 Rue Gaston",
    "sg:city":"Saint-Bernard-DE-Lacolle",
    "sg:classifiers":[
        {
            "category":"Freight",
            "type":"Transportation"
        }
    ],
    "sg:phone":"+1 450 246 3452",
    "sg:postcode":"J0J 1V0",
    "sg:province":"QC",
    "sg:tags":[
        "trucking"
    ],
    "wof:name":"Dubois Transport",
    "wof:placetype":"venue"
},
  "geometry": {"coordinates":[-73.46981,45.104519],"type":"Point"}
}