{
  "type": "Feature",
  "properties": {
    "iso:country":"CA",
    "sg:address":"17122 Ch Sainte-Marie",
    "sg:city":"Kirkland",
    "sg:classifiers":[
        {
            "category":"Health Services",
            "subcategory":"Doctor",
            "type":"Services"
        }
    ],
    "sg:phone":"+1 514 697 3033",
    "sg:postcode":"H9J 2K9",
    "sg:province":"QC",
    "sg:tags":[
        "dentist"
    ],
    "wof:name":"Taylor, Donald DDS",
    "wof:placetype":"venue"
},
  "geometry": {"coordinates":[-73.86138916020001,45.4481391907],"type":"Point"}
}