{
  "type": "Feature",
  "properties": {
    "addr:full":"3530 5E Av Shawinigan-Sud QC G9P 1S1",
    "addr:housenumber":"3530",
    "addr:postcode":"g9p 1s1",
    "addr:street":"5E Av Shawinigan-Sud",
    "iso:country":"CA",
    "sg:address":"3530 5E Av",
    "sg:city":"Shawinigan-Sud",
    "sg:classifiers":[
        {
            "category":"Building & Trades",
            "subcategory":"Landscaping Services",
            "type":"Services"
        }
    ],
    "sg:phone":"+1 819 537 3424",
    "sg:postcode":"G9P 1S1",
    "sg:province":"QC",
    "sg:tags":[
        "landscape",
        "contractor"
    ],
    "wof:name":"Pepiniere Jardin Bo Decor",
    "wof:placetype":"venue"
},
  "geometry": {"coordinates":[-72.735252,46.512856],"type":"Point"}
}