{
  "type": "Feature",
  "properties": {
    "addr:full":"1656 Barrington St Halifax NS B3J 2A2",
    "addr:housenumber":"1656",
    "addr:postcode":"ns b3j 2a2",
    "addr:street":"Barrington St",
    "iso:country":"CA",
    "sg:address":"1656 Barrington St",
    "sg:city":"Halifax",
    "sg:classifiers":[
        {
            "category":"Shopping",
            "subcategory":"Music",
            "type":"Retail Goods"
        }
    ],
    "sg:phone":"+1 902 423 6441",
    "sg:postcode":"B3J 2A2",
    "sg:province":"NS",
    "sg:tags":[
        "compact",
        "record",
        "disc",
        "tape"
    ],
    "wof:name":"Sam the Record Man",
    "wof:placetype":"venue"
},
  "geometry": {"coordinates":[-63.5738716125,44.6464767456],"type":"Point"}
}