{
  "type": "Feature",
  "properties": {
    "iso:country":"CA",
    "sg:city":"Sechelt",
    "sg:classifiers":[
        {
            "category":"Real Estate",
            "subcategory":"Real Estate Agent",
            "type":"Services"
        }
    ],
    "sg:phone":"+1 604 885 2122",
    "sg:postcode":"V0N 3A0",
    "sg:province":"BC",
    "sg:tags":[
        "notary"
    ],
    "wof:name":"Conroy, Jody",
    "wof:placetype":"venue"
},
  "geometry": {"coordinates":[-123.75440979,49.4733505249],"type":"Point"}
}