{
  "type": "Feature",
  "properties": {
    "iso:country":"CA",
    "sg:address":"2385 4th Ave W",
    "sg:city":"Vancouver",
    "sg:classifiers":[
        {
            "category":"Health Services",
            "subcategory":"Doctor",
            "type":"Services"
        }
    ],
    "sg:phone":"+1 604 731 3800",
    "sg:postcode":"V6K 1P2",
    "sg:province":"BC",
    "sg:tags":[
        "dentist"
    ],
    "wof:name":"Accord Dental Clinic",
    "wof:placetype":"venue"
},
  "geometry": {"coordinates":[-123.159263611,49.2684326172],"type":"Point"}
}