{
  "type": "Feature",
  "properties": {
    "addr:full":"Calgary AB T2R 1L3",
    "addr:postcode":"t2r 1l3",
    "iso:country":"CA",
    "sg:city":"Calgary",
    "sg:classifiers":[
        {
            "category":"Personal",
            "subcategory":"Hair Removal",
            "type":"Services"
        }
    ],
    "sg:phone":"+1 403 818 9054",
    "sg:postcode":"T2R 1L3",
    "sg:province":"AB",
    "sg:tags":[
        "removing"
    ],
    "wof:name":"Sugar Fix",
    "wof:placetype":"venue"
},
  "geometry": {"coordinates":[-114.08132171600001,51.0417480469],"type":"Point"}
}