{
  "type": "Feature",
  "properties": {
    "addr:full":"Burnaby BC V5C 3Y6",
    "addr:postcode":"v5c 3y6",
    "iso:country":"CA",
    "sg:city":"Burnaby",
    "sg:classifiers":[
        {
            "category":"Restaurant",
            "type":"Food & Drink"
        }
    ],
    "sg:phone":"+1 604 299 7600",
    "sg:postcode":"V5C 3Y6",
    "sg:province":"BC",
    "wof:name":"Boston Pizza",
    "wof:placetype":"venue"
},
  "geometry": {"coordinates":[-123.01033,49.266563],"type":"Point"}
}