{
  "type": "Feature",
  "properties": {
    "addr:full":"3 Broad St Sussex NB E4E 2J7",
    "addr:housenumber":"3",
    "addr:postcode":"e4e 2j7",
    "addr:street":"Broad St",
    "iso:country":"CA",
    "sg:address":"3 Broad St",
    "sg:city":"Sussex",
    "sg:classifiers":[
        {
            "category":"Shopping",
            "subcategory":"Pharmacy",
            "type":"Retail Goods"
        }
    ],
    "sg:phone":"+1 506 433 1186",
    "sg:postcode":"E4E 2J7",
    "sg:province":"NB",
    "wof:name":"Sharp's Corner Drug Store Ltd",
    "wof:placetype":"venue"
},
  "geometry": {"coordinates":[-65.51348900000001,45.722687],"type":"Point"}
}