{
  "type": "Feature",
  "properties": {
    "iso:country":"CA",
    "sg:address":"14 Av Garon",
    "sg:city":"Le Bic",
    "sg:classifiers":[
        {
            "category":"Building & Trades",
            "subcategory":"Construction",
            "type":"Services"
        }
    ],
    "sg:phone":"+1 418 736 4384",
    "sg:postcode":"G0L 1B0",
    "sg:province":"QC",
    "sg:tags":[
        "excavating",
        "contractor"
    ],
    "wof:name":"Excavation Garon Inc",
    "wof:placetype":"venue"
},
  "geometry": {"coordinates":[-68.6918334961,48.3731956482],"type":"Point"}
}