{
  "type": "Feature",
  "properties": {
    "addr:full":"568 Sutherland Dr Brooks AB T1R 1C7",
    "addr:housenumber":"568",
    "addr:postcode":"t1r 1c7",
    "addr:street":"Sutherland Dr",
    "iso:country":"CA",
    "sg:address":"568 Sutherland Dr",
    "sg:city":"Brooks",
    "sg:classifiers":[
        {
            "category":"Museum",
            "type":"Entertainment"
        }
    ],
    "sg:phone":"+1 403 362 5073",
    "sg:postcode":"T1R 1C7",
    "sg:province":"AB",
    "wof:name":"Brooks & District Museum",
    "wof:placetype":"venue"
},
  "geometry": {"coordinates":[-111.889717,50.565163],"type":"Point"}
}