{
  "type": "Feature",
  "properties": {
    "addr:full":"Vancouver BC V6E 2Y3",
    "addr:postcode":"v6e 2y3",
    "iso:country":"CA",
    "sg:city":"Vancouver",
    "sg:classifiers":[
        {
            "category":"Professional",
            "subcategory":"Lawyer & Legal Services",
            "type":"Services"
        }
    ],
    "sg:phone":"+1 604 682 2292",
    "sg:postcode":"V6E 2Y3",
    "sg:province":"BC",
    "sg:tags":[
        "attorney"
    ],
    "wof:name":"Cole, Allen",
    "wof:placetype":"venue"
},
  "geometry": {"coordinates":[-123.12184906,49.2847557068],"type":"Point"}
}