{
  "type": "Feature",
  "properties": {
    "addr:full":"8264 Ontario St Vancouver BC V5X 3E4",
    "addr:housenumber":"8264",
    "addr:postcode":"v5x 3e4",
    "addr:street":"Ontario St",
    "iso:country":"CA",
    "sg:address":"8264 Ontario St",
    "sg:city":"Vancouver",
    "sg:classifiers":[
        {
            "category":"Wholesale",
            "subcategory":"Machinery & Supplies",
            "type":"Manufacturing & Wholesale Goods"
        }
    ],
    "sg:phone":"+1 604 514 4787",
    "sg:postcode":"V5X 3E4",
    "sg:province":"BC",
    "sg:tags":[
        "car",
        "station",
        "equipment"
    ],
    "wof:name":"Western Oil Svc Ltd",
    "wof:placetype":"venue"
},
  "geometry": {"coordinates":[-123.10643,49.209984],"type":"Point"}
}