{
  "type": "Feature",
  "properties": {
    "addr:full":"1899 Columbia Rossland BC V0G 1Y0",
    "addr:housenumber":"1899",
    "addr:postcode":"v0g 1y0",
    "addr:street":"Columbia",
    "iso:country":"CA",
    "sg:address":"1899 Columbia",
    "sg:city":"Rossland",
    "sg:classifiers":[
        {
            "category":"Recreation",
            "type":"Entertainment"
        }
    ],
    "sg:phone":"+1 250 362 7191",
    "sg:postcode":"V0G 1Y0",
    "sg:province":"BC",
    "sg:tags":[
        "center"
    ],
    "wof:name":"Rossland Recreation Dept",
    "wof:placetype":"venue"
},
  "geometry": {"coordinates":[-117.802269,49.076908],"type":"Point"}
}