{
  "type": "Feature",
  "properties": {
    "iso:country":"CA",
    "sg:address":"25 Victoria Rd N",
    "sg:city":"Guelph",
    "sg:classifiers":[
        {
            "category":"Banks & Credit Unions",
            "subcategory":"Bank",
            "type":"Services"
        }
    ],
    "sg:phone":"+1 519 823 1550",
    "sg:postcode":"N1E 5G6",
    "sg:province":"ON",
    "wof:name":"Cibc",
    "wof:placetype":"venue"
},
  "geometry": {"coordinates":[-80.2314605713,43.5575675964],"type":"Point"}
}