{
  "type": "Feature",
  "properties": {
    "addr:full":"Swift Current SK S9H 2B4",
    "addr:postcode":"s9h 2b4",
    "iso:country":"CA",
    "sg:city":"Swift Current",
    "sg:classifiers":[
        {
            "category":"Shopping",
            "subcategory":"Jewelry",
            "type":"Retail Goods"
        }
    ],
    "sg:phone":"+1 306 773 8035",
    "sg:postcode":"S9H 2B4",
    "sg:province":"SK",
    "sg:tags":[
        "shop",
        "gift"
    ],
    "wof:name":"Kokopelli Gifts",
    "wof:placetype":"venue"
},
  "geometry": {"coordinates":[-107.79892,50.285931],"type":"Point"}
}