{
  "type": "Feature",
  "properties": {
    "addr:full":"109 Valley Rd Robb AB T0E 1X0",
    "addr:housenumber":"109",
    "addr:postcode":"t0e 1x0",
    "addr:street":"Valley Rd",
    "iso:country":"CA",
    "sg:address":"109 Valley Rd",
    "sg:city":"Robb",
    "sg:classifiers":[
        {
            "category":"Travel",
            "subcategory":"Hotels & Motels",
            "type":"Entertainment"
        }
    ],
    "sg:phone":"+1 780 794 3761",
    "sg:postcode":"T0E 1X0",
    "sg:province":"AB",
    "wof:name":"Bryan Hotel",
    "wof:placetype":"venue"
},
  "geometry": {"coordinates":[-116.98551178,53.2397727966],"type":"Point"}
}