{
  "type": "Feature",
  "properties": {
    "addr:full":"7001 Savona Access Rd Savona BC V0K 2J0",
    "addr:housenumber":"7001",
    "addr:postcode":"v0k 2j0",
    "addr:street":"Savona Access Rd",
    "iso:country":"CA",
    "sg:address":"7001 Savona Access Rd",
    "sg:city":"Savona",
    "sg:classifiers":[
        {
            "category":"Travel",
            "subcategory":"Hotels & Motels",
            "type":"Entertainment"
        }
    ],
    "sg:phone":"+1 250 373 2528",
    "sg:postcode":"V0K 2J0",
    "sg:province":"BC",
    "wof:name":"Lakeside Country Inn",
    "wof:placetype":"venue"
},
  "geometry": {"coordinates":[-120.827286,50.756454],"type":"Point"}
}