{
  "type": "Feature",
  "properties": {
    "addr:full":"8488 Main St Vancouver BC V5X 4W8",
    "addr:housenumber":"8488",
    "addr:postcode":"v5x 4w8",
    "addr:street":"Main St",
    "iso:country":"CA",
    "sg:address":"8488 Main St",
    "sg:city":"Vancouver",
    "sg:classifiers":[
        {
            "category":"Home & Garden",
            "subcategory":"Household Appliances",
            "type":"Retail Goods"
        }
    ],
    "sg:phone":"+1 604 321 5655",
    "sg:postcode":"V5X 4W8",
    "sg:province":"BC",
    "sg:tags":[
        "gas"
    ],
    "wof:name":"Tri-Way Distributors Ltd",
    "wof:placetype":"venue"
},
  "geometry": {"coordinates":[-123.10214999999999,49.208233],"type":"Point"}
}