{
  "type": "Feature",
  "properties": {
    "addr:full":"Revelstoke BC V0E 2S0",
    "addr:postcode":"v0e 2s0",
    "iso:country":"CA",
    "sg:city":"Revelstoke",
    "sg:classifiers":[
        {
            "category":"Recreation",
            "type":"Entertainment"
        }
    ],
    "sg:phone":"+1 250 837 6376",
    "sg:postcode":"V0E 2S0",
    "sg:province":"BC",
    "sg:tags":[
        "raft",
        "trip"
    ],
    "wof:name":"Apex Raft CO",
    "wof:placetype":"venue"
},
  "geometry": {"coordinates":[-118.194534,50.997433],"type":"Point"}
}