{
  "type": "Feature",
  "properties": {
    "addr:full":"420 Station Rd Shoal Lake MB R0J 1Z0",
    "addr:housenumber":"420",
    "addr:postcode":"r0j 1z0",
    "addr:street":"Station Rd",
    "iso:country":"CA",
    "sg:address":"420 Station Rd",
    "sg:city":"Shoal Lake",
    "sg:classifiers":[
        {
            "category":"Shopping",
            "subcategory":"Clothing, Apparel, & Fashions",
            "type":"Retail Goods"
        }
    ],
    "sg:phone":"+1 204 759 2215",
    "sg:postcode":"R0J 1Z0",
    "sg:province":"MB",
    "wof:name":"Prestons Place",
    "wof:placetype":"venue"
},
  "geometry": {"coordinates":[-100.590721,50.43692],"type":"Point"}
}