{
  "type": "Feature",
  "properties": {
    "iso:country":"CA",
    "sg:address":"415 West Hunt Club Rd",
    "sg:city":"Nepean",
    "sg:classifiers":[
        {
            "category":"Shopping",
            "subcategory":"Department Store",
            "type":"Retail Goods"
        }
    ],
    "sg:phone":"+1 613 221 2000",
    "sg:postcode":"K2E 1C5",
    "sg:province":"ON",
    "sg:tags":[
        "grocer"
    ],
    "wof:name":"Costco Wholesale Canada",
    "wof:placetype":"venue"
},
  "geometry": {"coordinates":[-75.7202529907,45.3366546631],"type":"Point"}
}