{
  "type": "Feature",
  "properties": {
    "addr:full":"411 Av Sirois Rimouski QC G5L 8B2",
    "addr:postcode":"g5l 8b2",
    "addr:street":"411 Av Sirois",
    "iso:country":"CA",
    "sg:address":"411 Av Sirois",
    "sg:city":"Rimouski",
    "sg:classifiers":[
        {
            "category":"Real Estate",
            "subcategory":"Real Estate Operator",
            "type":"Services"
        }
    ],
    "sg:phone":"+1 418 722 8122",
    "sg:postcode":"G5L 8B2",
    "sg:province":"QC",
    "sg:tags":[
        "mall",
        "shopping",
        "center"
    ],
    "wof:name":"Plaza Arthur-Buies Enr",
    "wof:placetype":"venue"
},
  "geometry": {"coordinates":[-68.52299499999999,48.435257],"type":"Point"}
}