{
  "type": "Feature",
  "properties": {
    "addr:full":"Haines Junction YT Y0B 1L0",
    "addr:postcode":"y0b 1l0",
    "iso:country":"CA",
    "sg:city":"Haines Junction",
    "sg:classifiers":[
        {
            "category":"Travel",
            "subcategory":"Campground",
            "type":"Entertainment"
        }
    ],
    "sg:phone":"+1 867 634 2709",
    "sg:postcode":"Y0B 1L0",
    "sg:province":"YT",
    "wof:name":"Kluane Rv Kampground Ltd",
    "wof:placetype":"venue"
},
  "geometry": {"coordinates":[-137.51068115199999,60.7533988953],"type":"Point"}
}