{
  "type": "Feature",
  "properties": {
    "addr:full":"1899 Portage Ave Winnipeg MB R3J 0H9",
    "addr:housenumber":"1899",
    "addr:postcode":"r3j 0h9",
    "addr:street":"Portage Ave",
    "iso:country":"CA",
    "sg:address":"1899 Portage Ave",
    "sg:city":"Winnipeg",
    "sg:classifiers":[
        {
            "category":"Health Services",
            "subcategory":"Medical Lab",
            "type":"Services"
        }
    ],
    "sg:phone":"+1 204 888 8954",
    "sg:postcode":"R3J 0H9",
    "sg:province":"MB",
    "sg:tags":[
        "laboratory"
    ],
    "wof:name":"Quality Dental Ceramics Lab",
    "wof:placetype":"venue"
},
  "geometry": {"coordinates":[-97.22068023680001,49.878780365],"type":"Point"}
}