{
  "type": "Feature",
  "properties": {
    "addr:full":"2015 Warren Ave Kimberley BC V1A 1S5",
    "addr:housenumber":"2015",
    "addr:postcode":"v1a 1s5",
    "addr:street":"Warren Ave",
    "iso:country":"CA",
    "sg:address":"2015 Warren Ave",
    "sg:city":"Kimberley",
    "sg:classifiers":[
        {
            "category":"Recreation",
            "type":"Entertainment"
        }
    ],
    "sg:phone":"+1 250 427 4874",
    "sg:postcode":"V1A 1S5",
    "sg:province":"BC",
    "sg:tags":[
        "instruction",
        "gymnastic"
    ],
    "wof:name":"Kimberley Gymnastics Club",
    "wof:placetype":"venue"
},
  "geometry": {"coordinates":[-115.978516,49.6702],"type":"Point"}
}