{
  "type": "Feature",
  "properties": {
    "addr:full":"527 Boul Sainte-Foy Longueuil QC J4J 1Y5",
    "addr:housenumber":"527",
    "addr:postcode":"j4j 1y5",
    "addr:street":"Boul Sainte-Foy",
    "iso:country":"CA",
    "sg:address":"527 Boul Sainte-Foy",
    "sg:city":"Longueuil",
    "sg:classifiers":[
        {
            "category":"Professional",
            "subcategory":"Accounting & Tax Preparation",
            "type":"Services"
        }
    ],
    "sg:phone":"+1 450 646 9246",
    "sg:postcode":"J4J 1Y5",
    "sg:province":"QC",
    "sg:tags":[
        "return",
        "filing"
    ],
    "wof:name":"Latour, Jean-Pierre",
    "wof:placetype":"venue"
},
  "geometry": {"coordinates":[-73.4924316406,45.5261039734],"type":"Point"}
}