{
  "type": "Feature",
  "properties": {
    "iso:country":"CA",
    "sg:address":"184 45E Rue E",
    "sg:city":"Charlesbourg",
    "sg:classifiers":[
        {
            "category":"Building & Trades",
            "subcategory":"Construction",
            "type":"Services"
        }
    ],
    "sg:phone":"+1 418 628 9180",
    "sg:postcode":"G1H 2P9",
    "sg:province":"QC",
    "sg:tags":[
        "repairing",
        "remodeling",
        "contractor"
    ],
    "wof:name":"Constructions Roger Fortin Inc",
    "wof:placetype":"venue"
},
  "geometry": {"coordinates":[-71.2516708374,46.8458213806],"type":"Point"}
}