{
  "type": "Feature",
  "properties": {
    "addr:full":"645 Rue Champlain Joliette QC J6E 2S4",
    "addr:housenumber":"645",
    "addr:postcode":"j6e 2s4",
    "addr:street":"Rue Champlain",
    "iso:country":"CA",
    "sg:address":"645 Rue Champlain",
    "sg:city":"Joliette",
    "sg:classifiers":[
        {
            "category":"Wholesale",
            "subcategory":"Machinery & Supplies",
            "type":"Manufacturing & Wholesale Goods"
        }
    ],
    "sg:phone":"+1 450 753 5835",
    "sg:postcode":"J6E 2S4",
    "sg:province":"QC",
    "sg:tags":[
        "farm",
        "bearing",
        "equipment"
    ],
    "wof:name":"Allen Roulements & Technologie",
    "wof:placetype":"venue"
},
  "geometry": {"coordinates":[-73.4480514526,46.0261955261],"type":"Point"}
}