{
  "type": "Feature",
  "properties": {
    "iso:country":"CA",
    "sg:address":"1867 Merivale Rd",
    "sg:city":"Nepean",
    "sg:classifiers":[
        {
            "category":"Home & Garden",
            "subcategory":"Home Furnishings",
            "type":"Retail Goods"
        }
    ],
    "sg:phone":"+1 613 727 4760",
    "sg:postcode":"K2G 1E3",
    "sg:province":"ON",
    "sg:tags":[
        "curtain",
        "made",
        "drapery"
    ],
    "wof:name":"Custom Blinds Plus",
    "wof:placetype":"venue"
},
  "geometry": {"coordinates":[-75.7233657837,45.3340263367],"type":"Point"}
}