{
  "type": "Feature",
  "properties": {
    "addr:full":"PO Box 24 Zurich ON N0M 2T0",
    "addr:housenumber":"po box 24",
    "addr:postcode":"n0m 2t0",
    "iso:country":"CA",
    "sg:address":"PO Box 24",
    "sg:city":"Zurich",
    "sg:classifiers":[
        {
            "category":"Organizations",
            "subcategory":"Religious Organization",
            "type":"Services"
        }
    ],
    "sg:phone":"+1 519 236 4697",
    "sg:postcode":"N0M 2T0",
    "sg:province":"ON",
    "sg:tags":[
        "church"
    ],
    "wof:name":"St Peter's Lutheran Church",
    "wof:placetype":"venue"
},
  "geometry": {"coordinates":[-81.625153,43.421135],"type":"Point"}
}