{
  "type": "Feature",
  "properties": {
    "addr:full":"147 Massey Rd Guelph ON N1K 1B2",
    "addr:housenumber":"147",
    "addr:postcode":"n1k 1b2",
    "addr:street":"Massey Rd",
    "iso:country":"CA",
    "sg:address":"147 Massey Rd",
    "sg:city":"Guelph",
    "sg:classifiers":[
        {
            "category":"Freight",
            "type":"Transportation"
        }
    ],
    "sg:phone":"+1 519 837 4953",
    "sg:postcode":"N1K 1B2",
    "sg:province":"ON",
    "sg:tags":[
        "courier"
    ],
    "wof:name":"Purolator",
    "wof:placetype":"venue"
},
  "geometry": {"coordinates":[-80.30027,43.542099],"type":"Point"}
}