{
  "type": "Feature",
  "properties": {
    "iso:country":"CA",
    "sg:address":"168 Fraser Ln # 1",
    "sg:city":"Ucluelet",
    "sg:classifiers":[
        {
            "category":"Ferry",
            "type":"Transportation"
        }
    ],
    "sg:phone":"+1 250 726 7444",
    "sg:postcode":"V0R 3A0",
    "sg:province":"BC",
    "sg:tags":[
        "whale",
        "watching"
    ],
    "wof:name":"Jamies Whaling Station",
    "wof:placetype":"venue"
},
  "geometry": {"coordinates":[-125.54530334499999,48.9424285889],"type":"Point"}
}