{
  "type": "Feature",
  "properties": {
    "addr:full":"Humboldt SK S0K 2A0",
    "addr:postcode":"s0k 2a0",
    "addr:street":"Humboldt",
    "iso:country":"CA",
    "sg:city":"Humboldt",
    "sg:classifiers":[
        {
            "category":"Government",
            "subcategory":"Office",
            "type":"Public Place"
        }
    ],
    "sg:phone":"+1 306 682 6726",
    "sg:postcode":"S0K 2A0",
    "sg:province":"SK",
    "wof:name":"S K Conservation Officers",
    "wof:placetype":"venue"
},
  "geometry": {"coordinates":[-105.12226867699999,52.2018966675],"type":"Point"}
}