{
  "type": "Feature",
  "properties": {
    "addr:full":"2090 Sumas Way Abbotsford BC V2S 2C7",
    "addr:housenumber":"2090",
    "addr:postcode":"v2s 2c7",
    "addr:street":"Sumas Way",
    "iso:country":"CA",
    "sg:address":"2090 Sumas Way",
    "sg:city":"Abbotsford",
    "sg:classifiers":[
        {
            "category":"Banks & Credit Unions",
            "subcategory":"Investment Brokerage",
            "type":"Services"
        }
    ],
    "sg:phone":"+1 604 557 7470",
    "sg:postcode":"V2S 2C7",
    "sg:province":"BC",
    "sg:tags":[
        "consultant",
        "planning",
        "financial",
        "insurance"
    ],
    "wof:name":"Envision Investment Svc Ltd",
    "wof:placetype":"venue"
},
  "geometry": {"coordinates":[-122.26805877699999,49.0376091003],"type":"Point"}
}