{
  "type": "Feature",
  "properties": {
    "addr:full":"225 Dundas St E Mississauga ON L5A 1W8",
    "addr:housenumber":"225",
    "addr:postcode":"l5a 1w8",
    "addr:street":"Dundas St E",
    "iso:country":"CA",
    "sg:address":"225 Dundas St E",
    "sg:city":"Mississauga",
    "sg:classifiers":[
        {
            "category":"Autos & Motor Vehicles",
            "subcategory":"Automobile Sales",
            "type":"Retail Goods"
        }
    ],
    "sg:phone":"+1 905 275 1500",
    "sg:postcode":"L5A 1W8",
    "sg:province":"ON",
    "sg:tags":[
        "car",
        "dealer"
    ],
    "wof:name":"Hawley Pontiac",
    "wof:placetype":"venue"
},
  "geometry": {"coordinates":[-79.61159499999999,43.584675],"type":"Point"}
}