{
  "type": "Feature",
  "properties": {
    "addr:full":"Salmon Arm BC V1E 1V7",
    "addr:postcode":"v1e 1v7",
    "iso:country":"CA",
    "sg:city":"Salmon Arm",
    "sg:classifiers":[
        {
            "category":"Retail",
            "subcategory":"Auto Repair",
            "type":"Services"
        }
    ],
    "sg:phone":"+1 250 832 1123",
    "sg:postcode":"V1E 1V7",
    "sg:province":"BC",
    "sg:tags":[
        "repairing",
        "automobile",
        "tire"
    ],
    "wof:name":"Fountain Tire",
    "wof:placetype":"venue"
},
  "geometry": {"coordinates":[-119.27188099999999,50.702221],"type":"Point"}
}