{
  "type": "Feature",
  "properties": {
    "iso:country":"CA",
    "sg:address":"4035 Rue Du Vieux-Pont",
    "sg:city":"Jonquiere",
    "sg:classifiers":[
        {
            "category":"Restaurant",
            "type":"Food & Drink"
        }
    ],
    "sg:phone":"+1 418 547 7448",
    "sg:postcode":"G8A 1N4",
    "sg:province":"QC",
    "wof:name":"Restaurant Le Tournesol Enr",
    "wof:placetype":"venue"
},
  "geometry": {"coordinates":[-71.26165771479999,48.410900116],"type":"Point"}
}