{
  "type": "Feature",
  "properties": {
    "addr:full":"623 Kennedy Rd Scarborough ON M1K 2B2",
    "addr:housenumber":"623",
    "addr:postcode":"m1k 2b2",
    "addr:street":"Kennedy Rd",
    "iso:country":"CA",
    "sg:address":"623 Kennedy Rd",
    "sg:city":"Scarborough",
    "sg:classifiers":[
        {
            "category":"Restaurant",
            "type":"Food & Drink"
        }
    ],
    "sg:phone":"+1 416 267 2721",
    "sg:postcode":"M1K 2B2",
    "sg:province":"ON",
    "wof:name":"Corvette Fish & Chips",
    "wof:placetype":"venue"
},
  "geometry": {"coordinates":[-79.264526,43.724659],"type":"Point"}
}