{
  "type": "Feature",
  "properties": {
    "addr:full":"3988 Boulter Rd Boulter ON K0L 1G0",
    "addr:housenumber":"3988",
    "addr:postcode":"k0l 1g0",
    "addr:street":"Boulter Rd",
    "iso:country":"CA",
    "sg:address":"3988 Boulter Rd",
    "sg:city":"Boulter",
    "sg:classifiers":[
        {
            "category":"Government",
            "subcategory":"Office",
            "type":"Public Place"
        }
    ],
    "sg:phone":"+1 613 332 4587",
    "sg:postcode":"K0L 1G0",
    "sg:province":"ON",
    "sg:tags":[
        "village"
    ],
    "wof:name":"Carlow Garage",
    "wof:placetype":"venue"
},
  "geometry": {"coordinates":[-77.63753509519999,45.2129936218],"type":"Point"}
}