{
  "type": "Feature",
  "properties": {
    "addr:full":"2215 Queen St E Toronto ON M4E 1E8",
    "addr:housenumber":"2215",
    "addr:postcode":"m4e 1e8",
    "addr:street":"Queen St E",
    "iso:country":"CA",
    "sg:address":"2215 Queen St E",
    "sg:city":"Toronto",
    "sg:classifiers":[
        {
            "category":"Professional",
            "subcategory":"Employment Agencies",
            "type":"Services"
        }
    ],
    "sg:phone":"+1 416 694 6604",
    "sg:postcode":"M4E 1E8",
    "sg:province":"ON",
    "sg:tags":[
        "opportunity"
    ],
    "wof:name":"Traditional Nannies",
    "wof:placetype":"venue"
},
  "geometry": {"coordinates":[-79.2960739136,43.6707496643],"type":"Point"}
}