{
  "type": "Feature",
  "properties": {
    "addr:full":"Richmond Hill ON L4C 3B3",
    "addr:postcode":"l4c 3b3",
    "iso:country":"CA",
    "sg:city":"Richmond Hill",
    "sg:classifiers":[
        {
            "category":"Professional",
            "subcategory":"Lawyer & Legal Services",
            "type":"Services"
        }
    ],
    "sg:phone":"+1 905 884 9133",
    "sg:postcode":"L4C 3B3",
    "sg:province":"ON",
    "sg:tags":[
        "attorney"
    ],
    "wof:name":"Lawlor, John QC",
    "wof:placetype":"venue"
},
  "geometry": {"coordinates":[-79.438225,43.876442],"type":"Point"}
}