{
  "type": "Feature",
  "properties": {
    "addr:full":"2931 4th Ave W Vancouver BC V6K 1R3",
    "addr:housenumber":"2931",
    "addr:postcode":"v6k 1r3",
    "addr:street":"4Th Ave W",
    "iso:country":"CA",
    "sg:address":"2931 4th Ave W",
    "sg:city":"Vancouver",
    "sg:classifiers":[
        {
            "category":"Shopping",
            "type":"Retail Goods"
        }
    ],
    "sg:phone":"+1 604 736 1321",
    "sg:postcode":"V6K 1R3",
    "sg:province":"BC",
    "sg:tags":[
        "picture",
        "frame",
        "art",
        "gallery",
        "dealer"
    ],
    "wof:name":"Mido Framers",
    "wof:placetype":"venue"
},
  "geometry": {"coordinates":[-123.170318603,49.2685241699],"type":"Point"}
}