{
  "type": "Feature",
  "properties": {
    "addr:full":"40 Main St Brownlee SK S0H 0M0",
    "addr:housenumber":"40",
    "addr:postcode":"s0h 0m0",
    "addr:street":"Main St",
    "iso:country":"CA",
    "sg:address":"40 Main St",
    "sg:city":"Brownlee",
    "sg:classifiers":[
        {
            "category":"Wholesale",
            "subcategory":"Machinery & Supplies",
            "type":"Manufacturing & Wholesale Goods"
        }
    ],
    "sg:phone":"+1 306 759 2002",
    "sg:postcode":"S0H 0M0",
    "sg:province":"SK",
    "sg:tags":[
        "farm",
        "equipment"
    ],
    "wof:name":"Brownlee Farm Equipment",
    "wof:placetype":"venue"
},
  "geometry": {"coordinates":[-106.02301,50.735443],"type":"Point"}
}