{
  "type": "Feature",
  "properties": {
    "addr:full":"672 Rue Du Parc Lac-Drolet QC G0Y 1C0",
    "addr:housenumber":"672",
    "addr:postcode":"g0y 1c0",
    "addr:street":"Rue Du Parc",
    "iso:country":"CA",
    "sg:address":"672 Rue Du Parc",
    "sg:city":"Lac-Drolet",
    "sg:classifiers":[
        {
            "category":"Professional",
            "subcategory":"Advertising",
            "type":"Services"
        }
    ],
    "sg:phone":"+1 819 549 2477",
    "sg:postcode":"G0Y 1C0",
    "sg:province":"QC",
    "wof:name":"Attraction",
    "wof:placetype":"venue"
},
  "geometry": {"coordinates":[-70.843262,45.722305],"type":"Point"}
}