{
  "type": "Feature",
  "properties": {
    "addr:full":"Hull QC J8Y 1S7",
    "addr:postcode":"j8y 1s7",
    "iso:country":"CA",
    "sg:city":"Hull",
    "sg:classifiers":[
        {
            "category":"Professional",
            "subcategory":"Management & Consulting",
            "type":"Services"
        }
    ],
    "sg:phone":"+1 819 777 5550",
    "sg:postcode":"J8Y 1S7",
    "sg:province":"QC",
    "sg:tags":[
        "employee",
        "consultant",
        "benefit"
    ],
    "wof:name":"Cowan Wright Beauchamp",
    "wof:placetype":"venue"
},
  "geometry": {"coordinates":[-75.742165,45.447105],"type":"Point"}
}