{
  "type": "Feature",
  "properties": {
    "iso:country":"CA",
    "sg:address":"419 Manitoba Rd",
    "sg:city":"Winkler",
    "sg:classifiers":[
        {
            "category":"Building & Trades",
            "subcategory":"Construction",
            "type":"Services"
        }
    ],
    "sg:phone":"+1 204 325 6489",
    "sg:postcode":"R6W 4A5",
    "sg:province":"MB",
    "sg:tags":[
        "steel",
        "erectors"
    ],
    "wof:name":"Diamond Steel Erectors",
    "wof:placetype":"venue"
},
  "geometry": {"coordinates":[-97.930305481,49.1660575867],"type":"Point"}
}