{
  "type": "Feature",
  "properties": {
    "addr:full":"31 Rue Pare Granby QC J2G 5C7",
    "addr:housenumber":"31",
    "addr:postcode":"j2g 5c7",
    "addr:street":"Rue Pare",
    "iso:country":"CA",
    "sg:address":"31 Rue Pare",
    "sg:city":"Granby",
    "sg:classifiers":[
        {
            "category":"Personal",
            "subcategory":"Beauty Salon",
            "type":"Services"
        }
    ],
    "sg:phone":"+1 450 372 2555",
    "sg:postcode":"J2G 5C7",
    "sg:province":"QC",
    "wof:name":"Salon Dyane",
    "wof:placetype":"venue"
},
  "geometry": {"coordinates":[-72.7282028198,45.4016227722],"type":"Point"}
}