{
  "type": "Feature",
  "properties": {
    "addr:full":"101 University Ave Miramichi NB E1N 2V6",
    "addr:housenumber":"101",
    "addr:postcode":"e1n 2v6",
    "addr:street":"University Ave",
    "iso:country":"CA",
    "sg:address":"101 University Ave",
    "sg:city":"Miramichi",
    "sg:classifiers":[
        {
            "category":"Arena",
            "subcategory":"Sports Club",
            "type":"Entertainment"
        }
    ],
    "sg:phone":"+1 506 778 1211",
    "sg:postcode":"E1N 2V6",
    "sg:province":"NB",
    "sg:tags":[
        "athletic",
        "fields",
        "stadium"
    ],
    "wof:name":"Lord Beaverbrook Arena",
    "wof:placetype":"venue"
},
  "geometry": {"coordinates":[-65.4656448364,47.0250091553],"type":"Point"}
}