{
  "type": "Feature",
  "properties": {
    "addr:full":"1950 Turner St Vancouver BC V5L 2A1",
    "addr:housenumber":"1950",
    "addr:postcode":"v5l 2a1",
    "addr:street":"Turner St",
    "iso:country":"CA",
    "sg:address":"1950 Turner St",
    "sg:city":"Vancouver",
    "sg:classifiers":[
        {
            "category":"Professional",
            "type":"Services"
        }
    ],
    "sg:phone":"+1 604 253 1962",
    "sg:postcode":"V5L 2A1",
    "sg:province":"BC",
    "sg:tags":[
        "writer"
    ],
    "wof:name":"Arbutus Communications",
    "wof:placetype":"venue"
},
  "geometry": {"coordinates":[-123.064629,49.279015],"type":"Point"}
}