{
  "type": "Feature",
  "properties": {
    "iso:country":"CA",
    "sg:address":"446 Ontario St",
    "sg:city":"Toronto",
    "sg:classifiers":[
        {
            "category":"Education",
            "subcategory":"Special Training",
            "type":"Public Place"
        }
    ],
    "sg:phone":"+1 416 967 0780",
    "sg:postcode":"M5A 2W1",
    "sg:province":"ON",
    "sg:tags":[
        "school",
        "instruction",
        "art"
    ],
    "wof:name":"Satok School of the Arts",
    "wof:placetype":"venue"
},
  "geometry": {"coordinates":[-79.3703613281,43.6629219055],"type":"Point"}
}