{
  "type": "Feature",
  "properties": {
    "addr:full":"137 2nd Ave N Saskatoon SK S7K 2A9",
    "addr:housenumber":"137",
    "addr:postcode":"s7k 2a9",
    "addr:street":"2Nd Ave N",
    "iso:country":"CA",
    "sg:address":"137 2nd Ave N",
    "sg:city":"Saskatoon",
    "sg:classifiers":[
        {
            "category":"Shopping",
            "subcategory":"Gifts & Souvenirs",
            "type":"Retail Goods"
        }
    ],
    "sg:phone":"+1 306 652 4499",
    "sg:postcode":"S7K 2A9",
    "sg:province":"SK",
    "sg:tags":[
        "shop"
    ],
    "wof:name":"Fran's Gifts & Souvenirs",
    "wof:placetype":"venue"
},
  "geometry": {"coordinates":[-106.663742,52.129429],"type":"Point"}
}