{
  "type": "Feature",
  "properties": {
    "addr:full":"42 Nash Rd S Hamilton ON L8K 4J6",
    "addr:housenumber":"42",
    "addr:postcode":"l8k 4j6",
    "addr:street":"Nash Rd S",
    "iso:country":"CA",
    "sg:address":"42 Nash Rd S",
    "sg:city":"Hamilton",
    "sg:classifiers":[
        {
            "category":"Real Estate",
            "subcategory":"Real Estate Operator",
            "type":"Services"
        }
    ],
    "sg:phone":"+1 905 560 0217",
    "sg:postcode":"L8K 4J6",
    "sg:province":"ON",
    "sg:tags":[
        "apartment"
    ],
    "wof:name":"Nashville Manor",
    "wof:placetype":"venue"
},
  "geometry": {"coordinates":[-79.774765,43.228416],"type":"Point"}
}