{
  "type": "Feature",
  "properties": {
    "addr:full":"189 Water St Guelph ON N1G 1B3",
    "addr:housenumber":"189",
    "addr:postcode":"n1g 1b3",
    "addr:street":"Water St",
    "iso:country":"CA",
    "sg:address":"189 Water St",
    "sg:city":"Guelph",
    "sg:classifiers":[
        {
            "category":"Education",
            "subcategory":"School",
            "type":"Public Place"
        }
    ],
    "sg:phone":"+1 519 824 0028",
    "sg:postcode":"N1G 1B3",
    "sg:province":"ON",
    "wof:name":"John Mc Crae Public School",
    "wof:placetype":"venue"
},
  "geometry": {"coordinates":[-80.247231,43.534676],"type":"Point"}
}