{
  "type": "Feature",
  "properties": {
    "addr:full":"1745 Nanaimo St Vancouver BC V5N 5C1",
    "addr:housenumber":"1745",
    "addr:postcode":"v5n 5c1",
    "addr:street":"Nanaimo St",
    "iso:country":"CA",
    "sg:address":"1745 Nanaimo St",
    "sg:city":"Vancouver",
    "sg:classifiers":[
        {
            "category":"Shopping",
            "subcategory":"Computers & Home Electronics",
            "type":"Retail Goods"
        }
    ],
    "sg:phone":"+1 604 253 1588",
    "sg:postcode":"V5N 5C1",
    "sg:province":"BC",
    "sg:tags":[
        "equipment",
        "dealer"
    ],
    "wof:name":"Nantron Systems",
    "wof:placetype":"venue"
},
  "geometry": {"coordinates":[-123.05672454800001,49.2691307068],"type":"Point"}
}