{
  "type": "Feature",
  "properties": {
    "addr:full":"609 Kingston Rd Toronto ON M4E 1R3",
    "addr:housenumber":"609",
    "addr:postcode":"m4e 1r3",
    "addr:street":"Kingston Rd",
    "iso:country":"CA",
    "sg:address":"609 Kingston Rd",
    "sg:city":"Toronto",
    "sg:classifiers":[
        {
            "category":"Food & Beverages",
            "subcategory":"Groceries & Convenience Stores",
            "type":"Retail Goods"
        }
    ],
    "sg:phone":"+1 416 699 0165",
    "sg:postcode":"M4E 1R3",
    "sg:province":"ON",
    "sg:tags":[
        "grocer"
    ],
    "wof:name":"Azzarello Brothers Ltd",
    "wof:placetype":"venue"
},
  "geometry": {"coordinates":[-79.29890399999999,43.67857],"type":"Point"}
}