{
  "type": "Feature",
  "properties": {
    "addr:full":"Winnipeg MB R2K 2M5",
    "addr:postcode":"r2k 2m5",
    "iso:country":"CA",
    "sg:city":"Winnipeg",
    "sg:classifiers":[
        {
            "category":"Restaurant",
            "type":"Food & Drink"
        }
    ],
    "sg:phone":"+1 204 334 3737",
    "sg:postcode":"R2K 2M5",
    "sg:province":"MB",
    "wof:name":"Mr Sub",
    "wof:placetype":"venue"
},
  "geometry": {"coordinates":[-97.0950088501,49.9361724854],"type":"Point"}
}