{
  "type": "Feature",
  "properties": {
    "addr:full":"Mississauga ON L5M 5P5",
    "addr:postcode":"l5m 5p5",
    "iso:country":"CA",
    "sg:city":"Mississauga",
    "sg:classifiers":[
        {
            "category":"Personal",
            "subcategory":"Beauty Salon",
            "type":"Services"
        }
    ],
    "sg:phone":"+1 905 820 4144",
    "sg:postcode":"L5M 5P5",
    "sg:province":"ON",
    "wof:name":"Virtu Hair Imaging",
    "wof:placetype":"venue"
},
  "geometry": {"coordinates":[-79.7167129517,43.5581970215],"type":"Point"}
}