{
  "type": "Feature",
  "properties": {
    "addr:full":"Gloucester ON K1J 6M5",
    "addr:postcode":"k1j 6m5",
    "iso:country":"CA",
    "sg:city":"Gloucester",
    "sg:classifiers":[
        {
            "category":"Health Services",
            "subcategory":"Chiropractor",
            "type":"Services"
        }
    ],
    "sg:phone":"+1 613 747 0444",
    "sg:postcode":"K1J 6M5",
    "sg:province":"ON",
    "wof:name":"Vandervoort, Daniel K DC",
    "wof:placetype":"venue"
},
  "geometry": {"coordinates":[-75.587982,45.449825],"type":"Point"}
}