{
  "type": "Feature",
  "properties": {
    "addr:full":"222 Queenston Rd Hamilton ON L8K 1G6",
    "addr:housenumber":"222",
    "addr:postcode":"l8k 1g6",
    "addr:street":"Queenston Rd",
    "iso:country":"CA",
    "sg:address":"222 Queenston Rd",
    "sg:city":"Hamilton",
    "sg:classifiers":[
        {
            "category":"Organizations",
            "subcategory":"Professional Association",
            "type":"Services"
        }
    ],
    "sg:phone":"+1 905 549 8636",
    "sg:postcode":"L8K 1G6",
    "sg:province":"ON",
    "sg:tags":[
        "club"
    ],
    "wof:name":"Knights of Columbus Club",
    "wof:placetype":"venue"
},
  "geometry": {"coordinates":[-79.794258,43.23465],"type":"Point"}
}