{
  "type": "Feature",
  "properties": {
    "addr:full":"Red Bay NL A0K 4K0",
    "addr:postcode":"a0k 4k0",
    "addr:street":"Red Bay",
    "iso:country":"CA",
    "sg:city":"Red Bay",
    "sg:classifiers":[
        {
            "category":"Government",
            "subcategory":"Office",
            "type":"Public Place"
        }
    ],
    "sg:phone":"+1 709 920 2197",
    "sg:postcode":"A0K 4K0",
    "sg:province":"NL",
    "sg:tags":[
        "village"
    ],
    "wof:name":"Red Bay Community Council",
    "wof:placetype":"venue"
},
  "geometry": {"coordinates":[-56.4258308411,51.730796814],"type":"Point"}
}