{
  "type": "Feature",
  "properties": {
    "addr:full":"746 Colborne St London ON N6A 3Z7",
    "addr:housenumber":"746",
    "addr:postcode":"n6a 3z7",
    "addr:street":"Colborne St",
    "iso:country":"CA",
    "sg:address":"746 Colborne St",
    "sg:city":"London",
    "sg:classifiers":[
        {
            "category":"Organizations",
            "subcategory":"Religious Organization",
            "type":"Services"
        }
    ],
    "sg:phone":"+1 519 432 4832",
    "sg:postcode":"N6A 3Z7",
    "sg:province":"ON",
    "sg:tags":[
        "church"
    ],
    "wof:name":"Trinity Lutheran Church",
    "wof:placetype":"venue"
},
  "geometry": {"coordinates":[-81.245186,42.997612],"type":"Point"}
}