{
  "type": "Feature",
  "properties": {
    "addr:full":"1383 Wellington St King City ON L7B 1K5",
    "addr:housenumber":"1383",
    "addr:postcode":"l7b 1k5",
    "addr:street":"Wellington St",
    "iso:country":"CA",
    "sg:address":"1383 Wellington St",
    "sg:city":"King City",
    "sg:classifiers":[
        {
            "category":"Home & Garden",
            "subcategory":"Garden Supply",
            "type":"Retail Goods"
        }
    ],
    "sg:phone":"+1 905 727 5851",
    "sg:postcode":"L7B 1K5",
    "sg:province":"ON",
    "sg:tags":[
        "equipment",
        "snow",
        "removal"
    ],
    "wof:name":"Snowball Equipment Sales Inc",
    "wof:placetype":"venue"
},
  "geometry": {"coordinates":[-79.512558,43.99017],"type":"Point"}
}