{
  "type": "Feature",
  "properties": {
    "addr:full":"108 Charing Cross St Brantford ON N3R 2H9",
    "addr:housenumber":"108",
    "addr:postcode":"n3r 2h9",
    "addr:street":"Charing Cross St",
    "iso:country":"CA",
    "sg:address":"108 Charing Cross St",
    "sg:city":"Brantford",
    "sg:classifiers":[
        {
            "category":"Health Services",
            "subcategory":"Medical Lab",
            "type":"Services"
        }
    ],
    "sg:phone":"+1 519 754 4746",
    "sg:postcode":"N3R 2H9",
    "sg:province":"ON",
    "wof:name":"Charing Cross Denture Clinic",
    "wof:placetype":"venue"
},
  "geometry": {"coordinates":[-80.2653884888,43.159362793],"type":"Point"}
}