{
  "type": "Feature",
  "properties": {
    "addr:full":"1557 Bella Vista Dr Cumberland ON K4C 1A7",
    "addr:housenumber":"1557",
    "addr:postcode":"k4c 1a7",
    "addr:street":"Bella Vista Dr",
    "iso:country":"CA",
    "sg:address":"1557 Bella Vista Dr",
    "sg:city":"Cumberland",
    "sg:classifiers":[
        {
            "category":"Professional",
            "subcategory":"Management & Consulting",
            "type":"Services"
        }
    ],
    "sg:phone":"+1 613 833 2494",
    "sg:postcode":"K4C 1A7",
    "sg:province":"ON",
    "sg:tags":[
        "consultant",
        "business"
    ],
    "wof:name":"Capra International",
    "wof:placetype":"venue"
},
  "geometry": {"coordinates":[-75.458878,45.51284],"type":"Point"}
}