{
  "type": "Feature",
  "properties": {
    "addr:full":"495 Rang DE L'Achigan L'Assomption QC J5W 3N3",
    "addr:housenumber":"495",
    "addr:postcode":"j5w 3n3",
    "addr:street":"Rang De L'Achigan",
    "iso:country":"CA",
    "sg:address":"495 Rang DE L'Achigan",
    "sg:city":"L'Assomption",
    "sg:classifiers":[
        {
            "category":"Manufacturing",
            "subcategory":"Metals",
            "type":"Manufacturing & Wholesale Goods"
        }
    ],
    "sg:phone":"+1 450 589 9342",
    "sg:postcode":"J5W 3N3",
    "sg:province":"QC",
    "sg:tags":[
        "steel"
    ],
    "wof:name":"Kadriform",
    "wof:placetype":"venue"
},
  "geometry": {"coordinates":[-73.44199399999999,45.903042],"type":"Point"}
}