{
  "type": "Feature",
  "properties": {
    "addr:full":"1760 Baker Rd E Casa Rio SK S7T 1B5",
    "addr:housenumber":"1760",
    "addr:postcode":"s7t 1b5",
    "addr:street":"Baker Rd E;Rio",
    "iso:country":"CA",
    "sg:address":"1760 Baker Rd E",
    "sg:city":"Casa Rio",
    "sg:classifiers":[
        {
            "category":"Education",
            "subcategory":"School",
            "type":"Public Place"
        }
    ],
    "sg:phone":"+1 306 477 0001",
    "sg:postcode":"S7T 1B5",
    "sg:province":"SK",
    "wof:name":"South Corman Park School",
    "wof:placetype":"venue"
},
  "geometry": {"coordinates":[-106.657051,52.027229],"type":"Point"}
}