{
  "type": "Feature",
  "properties": {
    "addr:full":"10256 Derham St Pugwash NS B0K 1L0",
    "addr:postcode":"10256;b0k 1l0",
    "addr:street":"Derham St",
    "iso:country":"CA",
    "sg:address":"10256 Derham St",
    "sg:city":"Pugwash",
    "sg:classifiers":[
        {
            "category":"Home & Garden",
            "subcategory":"Building Materials",
            "type":"Retail Goods"
        }
    ],
    "sg:phone":"+1 902 243 3306",
    "sg:postcode":"B0K 1L0",
    "sg:province":"NS",
    "wof:name":"Harrison's Home Building Ctr",
    "wof:placetype":"venue"
},
  "geometry": {"coordinates":[-63.661335,45.849506],"type":"Point"}
}