{
  "type": "Feature",
  "properties": {
    "addr:full":"739 20 Ave NW Calgary AB T2M 1E2",
    "addr:postcode":"t2m 1e2",
    "addr:street":"739 20 Ave Nw",
    "iso:country":"CA",
    "sg:address":"739 20 Ave NW",
    "sg:city":"Calgary",
    "sg:classifiers":[
        {
            "category":"Organizations",
            "subcategory":"Professional Association",
            "type":"Services"
        }
    ],
    "sg:phone":"+1 403 284 2610",
    "sg:postcode":"T2M 1E2",
    "sg:province":"AB",
    "wof:name":"Scandinavian Centre CO-OP Ltd",
    "wof:placetype":"venue"
},
  "geometry": {"coordinates":[-114.07740800000001,51.070278],"type":"Point"}
}