{
  "type": "Feature",
  "properties": {
    "addr:full":"970 4th Ave Prince George BC V2L 3H8",
    "addr:housenumber":"970",
    "addr:postcode":"v2l 3h8",
    "addr:street":"4Th Ave",
    "iso:country":"CA",
    "sg:address":"970 4th Ave",
    "sg:city":"Prince George",
    "sg:classifiers":[
        {
            "category":"Government",
            "subcategory":"Office",
            "type":"Public Place"
        }
    ],
    "sg:phone":"+1 250 962 8972",
    "sg:postcode":"V2L 3H8",
    "sg:province":"BC",
    "wof:name":"Fraser Regional Dist Landfill",
    "wof:placetype":"venue"
},
  "geometry": {"coordinates":[-122.740951538,53.9147949219],"type":"Point"}
}