{
  "type": "Feature",
  "properties": {
    "addr:full":"Abbotsford BC V2T 3L2",
    "addr:postcode":"v2t 3l2",
    "iso:country":"CA",
    "sg:city":"Abbotsford",
    "sg:classifiers":[
        {
            "category":"Manufacturing",
            "subcategory":"Printing",
            "type":"Manufacturing & Wholesale Goods"
        }
    ],
    "sg:phone":"+1 604 854 6303",
    "sg:postcode":"V2T 3L2",
    "sg:province":"BC",
    "sg:tags":[
        "printer",
        "duplicating",
        "copying"
    ],
    "wof:name":"Fraser Valley Reprographics",
    "wof:placetype":"venue"
},
  "geometry": {"coordinates":[-122.330543518,49.0511512756],"type":"Point"}
}