{
  "type": "Feature",
  "properties": {
    "addr:full":"550 Main St Winnipeg MB R3B 1C4",
    "addr:housenumber":"550",
    "addr:postcode":"r3b 1c4",
    "addr:street":"Main St",
    "iso:country":"CA",
    "sg:address":"550 Main St",
    "sg:city":"Winnipeg",
    "sg:classifiers":[
        {
            "category":"Personal",
            "subcategory":"Barber",
            "type":"Services"
        }
    ],
    "sg:phone":"+1 204 943 5348",
    "sg:postcode":"R3B 1C4",
    "sg:province":"MB",
    "wof:name":"Italia Barber Shop",
    "wof:placetype":"venue"
},
  "geometry": {"coordinates":[-97.137856,49.900581],"type":"Point"}
}