{
  "type": "Feature",
  "properties": {
    "addr:full":"706 Old Weston Rd York ON M6N 3B8",
    "addr:housenumber":"706",
    "addr:postcode":"m6n 3b8",
    "addr:street":"Old Weston Rd",
    "iso:country":"CA",
    "sg:address":"706 Old Weston Rd",
    "sg:city":"York",
    "sg:classifiers":[
        {
            "category":"Organizations",
            "subcategory":"Religious Organization",
            "type":"Services"
        }
    ],
    "sg:phone":"+1 416 653 7191",
    "sg:postcode":"M6N 3B8",
    "sg:province":"ON",
    "sg:tags":[
        "church"
    ],
    "wof:name":"St Matthew",
    "wof:placetype":"venue"
},
  "geometry": {"coordinates":[-79.46756000000001,43.681473],"type":"Point"}
}