{
  "type": "Feature",
  "properties": {
    "addr:full":"46 Meredith St Gore Bay ON P0P 1H0",
    "addr:housenumber":"46",
    "addr:postcode":"p0p 1h0",
    "addr:street":"Meredith St",
    "iso:country":"CA",
    "sg:address":"46 Meredith St",
    "sg:city":"Gore Bay",
    "sg:classifiers":[
        {
            "category":"Organizations",
            "subcategory":"Professional Association",
            "type":"Services"
        }
    ],
    "sg:phone":"+1 705 282 2237",
    "sg:postcode":"P0P 1H0",
    "sg:province":"ON",
    "wof:name":"Manitoulin Planning Board",
    "wof:placetype":"venue"
},
  "geometry": {"coordinates":[-82.46416473390001,45.9168052673],"type":"Point"}
}