{
  "type": "Feature",
  "properties": {
    "addr:full":"33889 Essendene Ave Abbotsford BC V2S 2H6",
    "addr:housenumber":"33889",
    "addr:postcode":"v2s 2h6",
    "addr:street":"Essendene Ave",
    "iso:country":"CA",
    "sg:address":"33889 Essendene Ave",
    "sg:city":"Abbotsford",
    "sg:classifiers":[
        {
            "category":"Social Services",
            "type":"Services"
        }
    ],
    "sg:phone":"+1 604 853 5151",
    "sg:postcode":"V2S 2H6",
    "sg:province":"BC",
    "sg:tags":[
        "senior",
        "citizen"
    ],
    "wof:name":"Abbotsford Seniors Assn Dance",
    "wof:placetype":"venue"
},
  "geometry": {"coordinates":[-122.286613464,49.0491065979],"type":"Point"}
}