{
  "type": "Feature",
  "properties": {
    "addr:full":"225 Henry St Brantford ON N3S 7R4",
    "addr:housenumber":"225",
    "addr:postcode":"n3s 7r4",
    "addr:street":"Henry St",
    "iso:country":"CA",
    "sg:address":"225 Henry St",
    "sg:city":"Brantford",
    "sg:classifiers":[
        {
            "category":"Wholesale",
            "subcategory":"Auto Parts",
            "type":"Manufacturing & Wholesale Goods"
        }
    ],
    "sg:phone":"+1 519 720 0425",
    "sg:postcode":"N3S 7R4",
    "sg:province":"ON",
    "sg:tags":[
        "automobile",
        "supply"
    ],
    "wof:name":"Meridian Automotive Systems",
    "wof:placetype":"venue"
},
  "geometry": {"coordinates":[-80.236412,43.155727],"type":"Point"}
}