{
  "type": "Feature",
  "properties": {
    "addr:full":"724 Park Ave Beausejour MB R0E 0C0",
    "addr:housenumber":"724",
    "addr:postcode":"r0e 0c0",
    "addr:street":"Park Ave",
    "iso:country":"CA",
    "sg:address":"724 Park Ave",
    "sg:city":"Beausejour",
    "sg:classifiers":[
        {
            "category":"Restaurant",
            "type":"Food & Drink"
        }
    ],
    "sg:phone":"+1 204 268 3888",
    "sg:postcode":"R0E 0C0",
    "sg:province":"MB",
    "wof:name":"Copper Pot Restaurant",
    "wof:placetype":"venue"
},
  "geometry": {"coordinates":[-96.514297,50.061787],"type":"Point"}
}