{
  "type": "Feature",
  "properties": {
    "addr:full":"120 Donald St Barrie ON L4N 5G7",
    "addr:housenumber":"120",
    "addr:postcode":"l4n 5g7",
    "addr:street":"Donald St",
    "iso:country":"CA",
    "sg:address":"120 Donald St",
    "sg:city":"Barrie",
    "sg:classifiers":[
        {
            "category":"Travel",
            "subcategory":"Hotels & Motels",
            "type":"Entertainment"
        }
    ],
    "sg:phone":"+1 705 726 0208",
    "sg:postcode":"L4N 5G7",
    "sg:province":"ON",
    "wof:name":"White Towers Motel",
    "wof:placetype":"venue"
},
  "geometry": {"coordinates":[-79.70626799999999,44.384937],"type":"Point"}
}