{
  "type": "Feature",
  "properties": {
    "iso:country":"CA",
    "sg:city":"Mississauga",
    "sg:classifiers":[
        {
            "category":"Manufacturing",
            "subcategory":"Printing",
            "type":"Manufacturing & Wholesale Goods"
        }
    ],
    "sg:phone":"+1 905 897 8858",
    "sg:postcode":"L5C 1V8",
    "sg:province":"ON",
    "sg:tags":[
        "screen"
    ],
    "wof:name":"Csm Enterprises Inc",
    "wof:placetype":"venue"
},
  "geometry": {"coordinates":[-79.6408,43.566486],"type":"Point"}
}