{
  "type": "Feature",
  "properties": {
    "iso:country":"CA",
    "sg:city":"Bolton",
    "sg:classifiers":[
        {
            "category":"Autos & Motor Vehicles",
            "subcategory":"Auto Supplies",
            "type":"Retail Goods"
        }
    ],
    "sg:phone":"+1 905 857 8100",
    "sg:postcode":"L7E 5A9",
    "sg:province":"ON",
    "sg:tags":[
        "automobile",
        "parts"
    ],
    "wof:name":"Albatross Automotive Ltd",
    "wof:placetype":"venue"
},
  "geometry": {"coordinates":[-79.722366333,43.8650741577],"type":"Point"}
}