{
  "type": "Feature",
  "properties": {
    "iso:country":"CA",
    "sg:city":"Hamilton",
    "sg:classifiers":[
        {
            "category":"Real Estate",
            "subcategory":"Real Estate Operator",
            "type":"Services"
        }
    ],
    "sg:phone":"+1 905 523 1277",
    "sg:postcode":"L8N 3X2",
    "sg:province":"ON",
    "sg:tags":[
        "apartment"
    ],
    "wof:name":"Oakland Square Tower",
    "wof:placetype":"venue"
},
  "geometry": {"coordinates":[-79.8677825928,43.2493209839],"type":"Point"}
}