{
  "type": "Feature",
  "properties": {
    "addr:full":"919C Albert St # 230 Regina SK S4R 2P6",
    "addr:housenumber":"919c",
    "addr:postcode":"s4r 2p6",
    "addr:street":"Albert St # 230",
    "iso:country":"CA",
    "sg:address":"919C Albert St # 230",
    "sg:city":"Regina",
    "sg:classifiers":[
        {
            "category":"Building & Trades",
            "subcategory":"Construction",
            "type":"Services"
        }
    ],
    "sg:phone":"+1 306 781 9401",
    "sg:postcode":"S4R 2P6",
    "sg:province":"SK",
    "sg:tags":[
        "millwright"
    ],
    "wof:name":"Allied Millwright Group",
    "wof:placetype":"venue"
},
  "geometry": {"coordinates":[-104.61786651600001,50.4641151428],"type":"Point"}
}