{
  "type": "Feature",
  "properties": {
    "iso:country":"CA",
    "sg:address":"581 Boler Rd",
    "sg:city":"London",
    "sg:classifiers":[
        {
            "category":"Building & Trades",
            "subcategory":"Construction",
            "type":"Services"
        }
    ],
    "sg:phone":"+1 519 672 5236",
    "sg:postcode":"N6K 3R8",
    "sg:province":"ON",
    "sg:tags":[
        "roofing",
        "contractor"
    ],
    "wof:name":"Howarth Roofing & Renovations",
    "wof:placetype":"venue"
},
  "geometry": {"coordinates":[-81.329414,42.945175],"type":"Point"}
}