{
  "type": "Feature",
  "properties": {
    "iso:country":"CA",
    "sg:address":"76 Brock St W",
    "sg:city":"Uxbridge",
    "sg:classifiers":[
        {
            "category":"Home & Garden",
            "subcategory":"Carpets & Floor Coverings",
            "type":"Retail Goods"
        }
    ],
    "sg:phone":"+1 905 852 3073",
    "sg:postcode":"L9P 1P4",
    "sg:province":"ON",
    "sg:tags":[
        "dealer",
        "rug"
    ],
    "wof:name":"Low's Carpet Shop",
    "wof:placetype":"venue"
},
  "geometry": {"coordinates":[-79.123664856,44.108455658],"type":"Point"}
}