{
  "type": "Feature",
  "properties": {
    "addr:full":"17 Av DE Gaspe O Saint-Jean-Port-Joli QC G0R 3G0",
    "addr:postcode":"g0r 3g0",
    "addr:street":"17 Av De Gaspe O",
    "iso:country":"CA",
    "sg:address":"17 Av DE Gaspe O",
    "sg:city":"Saint-Jean-Port-Joli",
    "sg:classifiers":[
        {
            "category":"Restaurant",
            "type":"Food & Drink"
        }
    ],
    "sg:phone":"+1 418 598 9644",
    "sg:postcode":"G0R 3G0",
    "sg:province":"QC",
    "wof:name":"Restaurant Libellule Enr",
    "wof:placetype":"venue"
},
  "geometry": {"coordinates":[-70.26973700000001,47.215122],"type":"Point"}
}