{
  "type": "Feature",
  "properties": {
    "iso:country":"CA",
    "sg:city":"Montreal",
    "sg:classifiers":[
        {
            "category":"Manufacturing",
            "subcategory":"Tools & Machinery",
            "type":"Manufacturing & Wholesale Goods"
        }
    ],
    "sg:phone":"+1 514 494 9286",
    "sg:postcode":"H1E 1P9",
    "sg:province":"QC",
    "sg:tags":[
        "equipment",
        "hydraulic",
        "supply"
    ],
    "wof:name":"Hydro-Mac Inc",
    "wof:placetype":"venue"
},
  "geometry": {"coordinates":[-73.59777832029999,45.6198043823],"type":"Point"}
}