{
  "type": "Feature",
  "properties": {
    "iso:country":"CA",
    "sg:address":"257 Hamilton Cres",
    "sg:city":"Dorchester",
    "sg:classifiers":[
        {
            "category":"Wholesale",
            "subcategory":"Auto Parts",
            "type":"Manufacturing & Wholesale Goods"
        }
    ],
    "sg:phone":"+1 519 268 7070",
    "sg:postcode":"N0L 1G4",
    "sg:province":"ON",
    "sg:tags":[
        "automobile",
        "supply"
    ],
    "wof:name":"Canusa Automotive Warehousing",
    "wof:placetype":"venue"
},
  "geometry": {"coordinates":[-81.0835342407,42.9929656982],"type":"Point"}
}