{
  "type": "Feature",
  "properties": {
    "iso:country":"CA",
    "sg:city":"Surrey",
    "sg:classifiers":[
        {
            "category":"Shopping",
            "subcategory":"Gifts & Souvenirs",
            "type":"Retail Goods"
        }
    ],
    "sg:phone":"+1 604 541 2673",
    "sg:postcode":"V4A 2H9",
    "sg:province":"BC",
    "sg:tags":[
        "novelty"
    ],
    "wof:name":"A Buck or Two",
    "wof:placetype":"venue"
},
  "geometry": {"coordinates":[-122.797424,49.045792],"type":"Point"}
}