{
  "type": "Feature",
  "properties": {
    "addr:full":"344 Bulyea Rd NW Edmonton AB T6R 2B3",
    "addr:housenumber":"344",
    "addr:postcode":"t6r 2b3",
    "addr:street":"Bulyea Rd Nw",
    "iso:country":"CA",
    "sg:address":"344 Bulyea Rd NW",
    "sg:city":"Edmonton",
    "sg:classifiers":[
        {
            "category":"Retail",
            "subcategory":"Auto Repair",
            "type":"Services"
        }
    ],
    "sg:phone":"+1 780 430 9045",
    "sg:postcode":"T6R 2B3",
    "sg:province":"AB",
    "sg:tags":[
        "repairing",
        "automobile"
    ],
    "wof:name":"Brookview Husky Automotive",
    "wof:placetype":"venue"
},
  "geometry": {"coordinates":[-113.572487,53.475483],"type":"Point"}
}