{
  "type": "Feature",
  "properties": {
    "addr:full":"75 Rue Castonguay Cookshire QC J0B 1M0",
    "addr:housenumber":"75",
    "addr:postcode":"j0b 1m0",
    "addr:street":"Rue Castonguay Cookshire",
    "iso:country":"CA",
    "sg:address":"75 Rue Castonguay",
    "sg:city":"Cookshire",
    "sg:classifiers":[
        {
            "category":"Recreation",
            "type":"Entertainment"
        }
    ],
    "sg:phone":"+1 819 875 5681",
    "sg:postcode":"J0B 1M0",
    "sg:province":"QC",
    "sg:tags":[
        "hall",
        "auditorium"
    ],
    "wof:name":"Loisirs Cookshire Inc",
    "wof:placetype":"venue"
},
  "geometry": {"coordinates":[-71.62009399999999,45.414799],"type":"Point"}
}