{
  "type": "Feature",
  "properties": {
    "iso:country":"CA",
    "sg:address":"132 Lakeshore Rd",
    "sg:city":"St Catharines",
    "sg:classifiers":[
        {
            "category":"Shopping",
            "subcategory":"Music",
            "type":"Retail Goods"
        }
    ],
    "sg:phone":"+1 905 646 9870",
    "sg:postcode":"L2N 2T5",
    "sg:province":"ON",
    "sg:tags":[
        "compact",
        "record",
        "disc",
        "tape"
    ],
    "wof:name":"Niagara Entertainment Exchange",
    "wof:placetype":"venue"
},
  "geometry": {"coordinates":[-79.24398040769999,43.2035903931],"type":"Point"}
}