{
  "type": "Feature",
  "properties": {
    "addr:full":"391 Tollendal Mill Rd Barrie ON L4N 7T1",
    "addr:housenumber":"391",
    "addr:postcode":"l4n 7t1",
    "addr:street":"Tollendal Mill Rd",
    "iso:country":"CA",
    "sg:address":"391 Tollendal Mill Rd",
    "sg:city":"Barrie",
    "sg:classifiers":[
        {
            "category":"Building & Trades",
            "subcategory":"Construction",
            "type":"Services"
        }
    ],
    "sg:phone":"+1 705 721 1717",
    "sg:postcode":"L4N 7T1",
    "sg:province":"ON",
    "sg:tags":[
        "downspouts",
        "gutter"
    ],
    "wof:name":"Cook's Home Improvements",
    "wof:placetype":"venue"
},
  "geometry": {"coordinates":[-79.64717899999999,44.372456],"type":"Point"}
}