{
  "type": "Feature",
  "properties": {
    "iso:country":"CA",
    "sg:address":"340 Byron St S",
    "sg:city":"Whitby",
    "sg:classifiers":[
        {
            "category":"Professional",
            "subcategory":"Management & Consulting",
            "type":"Services"
        }
    ],
    "sg:phone":"+1 905 666 9735",
    "sg:postcode":"L1N 4P8",
    "sg:province":"ON",
    "sg:tags":[
        "town",
        "city",
        "regional",
        "planner"
    ],
    "wof:name":"Tunney Planning",
    "wof:placetype":"venue"
},
  "geometry": {"coordinates":[-78.942566,43.876991],"type":"Point"}
}