{
  "type": "Feature",
  "properties": {
    "addr:full":"522 Rte 132 O Nouvelle-Ouest QC G0C 2G0",
    "addr:housenumber":"522",
    "addr:postcode":"g0c 2g0",
    "addr:street":"Rte 132 O Nouvelle-Ouest",
    "iso:country":"CA",
    "sg:address":"522 Rte 132 O",
    "sg:city":"Nouvelle-Ouest",
    "sg:classifiers":[
        {
            "category":"Autos & Motor Vehicles",
            "subcategory":"Fuel & Gas Station",
            "type":"Retail Goods"
        }
    ],
    "sg:phone":"+1 418 794 2411",
    "sg:postcode":"G0C 2G0",
    "sg:province":"QC",
    "sg:tags":[
        "oil"
    ],
    "wof:name":"Garage Maxwell Wafer & Fils",
    "wof:placetype":"venue"
},
  "geometry": {"coordinates":[-66.360039,48.154003],"type":"Point"}
}