{
  "type": "Feature",
  "properties": {
    "addr:full":"905 Don Mills Rd North York ON M3C 1W4",
    "addr:housenumber":"905",
    "addr:postcode":"m3c 1w4",
    "addr:street":"Don Mills Rd",
    "iso:country":"CA",
    "sg:address":"905 Don Mills Rd",
    "sg:city":"North York",
    "sg:classifiers":[
        {
            "category":"Retail",
            "subcategory":"Auto Repair",
            "type":"Services"
        }
    ],
    "sg:phone":"+1 416 447 8900",
    "sg:postcode":"M3C 1W4",
    "sg:province":"ON",
    "sg:tags":[
        "repairing",
        "automobile"
    ],
    "wof:name":"A 1 Autotech",
    "wof:placetype":"venue"
},
  "geometry": {"coordinates":[-79.340767,43.728317],"type":"Point"}
}