{
  "type": "Feature",
  "properties": {
    "addr:full":"Hughenden AB T0B 2E0",
    "addr:postcode":"t0b 2e0",
    "iso:country":"CA",
    "sg:city":"Hughenden",
    "sg:classifiers":[
        {
            "category":"Wholesale",
            "subcategory":"Chemicals & Plastics",
            "type":"Manufacturing & Wholesale Goods"
        }
    ],
    "sg:phone":"+1 780 856 2526",
    "sg:postcode":"T0B 2E0",
    "sg:province":"AB",
    "sg:tags":[
        "treating",
        "oil",
        "compound"
    ],
    "wof:name":"Newalta Corp",
    "wof:placetype":"venue"
},
  "geometry": {"coordinates":[-110.975334167,52.5094833374],"type":"Point"}
}