{
  "type": "Feature",
  "properties": {
    "iso:country":"CA",
    "sg:address":"4348 Rue Rivard",
    "sg:city":"Montreal",
    "sg:classifiers":[
        {
            "category":"Food & Beverages",
            "subcategory":"Groceries & Convenience Stores",
            "type":"Retail Goods"
        }
    ],
    "sg:phone":"+1 514 844 3001",
    "sg:postcode":"H2J 2M8",
    "sg:province":"QC",
    "sg:tags":[
        "grocer"
    ],
    "wof:name":"Marche Des Patriotes",
    "wof:placetype":"venue"
},
  "geometry": {"coordinates":[-73.57987213129999,45.5232429504],"type":"Point"}
}