{
  "type": "Feature",
  "properties": {
    "addr:full":"912 Dundas St Woodstock ON N4S 1H1",
    "addr:housenumber":"912",
    "addr:postcode":"n4s 1h1",
    "addr:street":"Dundas St",
    "iso:country":"CA",
    "sg:address":"912 Dundas St",
    "sg:city":"Woodstock",
    "sg:classifiers":[
        {
            "category":"Social Services",
            "type":"Services"
        }
    ],
    "sg:phone":"+1 519 539 0463",
    "sg:postcode":"N4S 1H1",
    "sg:province":"ON",
    "sg:tags":[
        "organization",
        "welfare"
    ],
    "wof:name":"Oxford Child & Youth Ctr",
    "wof:placetype":"venue"
},
  "geometry": {"coordinates":[-80.73737335209999,43.1327476501],"type":"Point"}
}