{
  "type": "Feature",
  "properties": {
    "addr:full":"Woodbridge ON L4L 8H2",
    "addr:postcode":"l4l 8h2",
    "iso:country":"CA",
    "sg:city":"Woodbridge",
    "sg:classifiers":[
        {
            "category":"Shopping",
            "subcategory":"Computers & Home Electronics",
            "type":"Retail Goods"
        }
    ],
    "sg:phone":"+1 905 264 9000",
    "sg:postcode":"L4L 8H2",
    "sg:province":"ON",
    "sg:tags":[
        "equipment",
        "dealer"
    ],
    "wof:name":"Stealth Computer Corp",
    "wof:placetype":"venue"
},
  "geometry": {"coordinates":[-79.561852,43.779411],"type":"Point"}
}