{
  "type": "Feature",
  "properties": {
    "addr:full":"8808 92 St NW Edmonton AB T6C 3R1",
    "addr:housenumber":"8808",
    "addr:postcode":"t6c 3r1",
    "addr:street":"92 St Nw",
    "iso:country":"CA",
    "sg:address":"8808 92 St NW",
    "sg:city":"Edmonton",
    "sg:classifiers":[
        {
            "category":"Health Services",
            "subcategory":"Doctor",
            "type":"Services"
        }
    ],
    "sg:phone":"+1 780 469 2118",
    "sg:postcode":"T6C 3R1",
    "sg:province":"AB",
    "sg:tags":[
        "physician",
        "surgeon"
    ],
    "wof:name":"Young, Janice MD",
    "wof:placetype":"venue"
},
  "geometry": {"coordinates":[-113.46854399999999,53.523796],"type":"Point"}
}