{
  "type": "Feature",
  "properties": {
    "addr:full":"315 Boul Labelle Sainte-Therese QC J7E 2Y2",
    "addr:housenumber":"315",
    "addr:postcode":"j7e 2y2",
    "addr:street":"Boul Labelle Sainte-Therese",
    "iso:country":"CA",
    "sg:address":"315 Boul Labelle",
    "sg:city":"Sainte-Therese",
    "sg:classifiers":[
        {
            "category":"Restaurant",
            "type":"Food & Drink"
        }
    ],
    "sg:phone":"+1 450 434 2552",
    "sg:postcode":"J7E 2Y2",
    "sg:province":"QC",
    "wof:name":"Restaurant Makisu Inc",
    "wof:placetype":"venue"
},
  "geometry": {"coordinates":[-73.8410949707,45.648059845],"type":"Point"}
}