{
  "type": "Feature",
  "properties": {
    "addr:full":"2177 Fourth Ave St Catharines ON L2R 6P9",
    "addr:housenumber":"2177",
    "addr:postcode":"l2r 6p9",
    "addr:street":"Fourth Ave",
    "iso:country":"CA",
    "sg:address":"2177 Fourth Ave",
    "sg:city":"St Catharines",
    "sg:classifiers":[
        {
            "category":"Freight",
            "type":"Transportation"
        }
    ],
    "sg:phone":"+1 905 562 4211",
    "sg:postcode":"L2R 6P9",
    "sg:province":"ON",
    "sg:tags":[
        "trucking"
    ],
    "wof:name":"Mac Laurin Trucking",
    "wof:placetype":"venue"
},
  "geometry": {"coordinates":[-79.31466674799999,43.1538505554],"type":"Point"}
}