{
  "type": "Feature",
  "properties": {
    "addr:full":"Delta BC V3M 6M1",
    "addr:postcode":"v3m 6m1",
    "iso:country":"CA",
    "sg:city":"Delta",
    "sg:classifiers":[
        {
            "category":"Retail",
            "subcategory":"Repair Shop",
            "type":"Services"
        }
    ],
    "sg:phone":"+1 604 540 8620",
    "sg:postcode":"V3M 6M1",
    "sg:province":"BC",
    "sg:tags":[
        "conditioning",
        "air",
        "system",
        "contractor"
    ],
    "wof:name":"Comstock Canada Ltd",
    "wof:placetype":"venue"
},
  "geometry": {"coordinates":[-122.96985626199999,49.1644325256],"type":"Point"}
}