{
  "type": "Feature",
  "properties": {
    "addr:full":"1673 Richmond St London ON N6G 2N3",
    "addr:housenumber":"1673",
    "addr:postcode":"n6g 2n3",
    "addr:street":"Richmond St",
    "iso:country":"CA",
    "sg:address":"1673 Richmond St",
    "sg:city":"London",
    "sg:classifiers":[
        {
            "category":"Personal",
            "subcategory":"Beauty Salon",
            "type":"Services"
        }
    ],
    "sg:phone":"+1 519 850 0702",
    "sg:postcode":"N6G 2N3",
    "sg:province":"ON",
    "wof:name":"Hair Evolution & Spa Inc",
    "wof:placetype":"venue"
},
  "geometry": {"coordinates":[-81.28222700000001,43.025509],"type":"Point"}
}