{
  "type": "Feature",
  "properties": {
    "iso:country":"CA",
    "sg:city":"Nepean",
    "sg:classifiers":[
        {
            "category":"Wholesale",
            "subcategory":"Photographic Equipment",
            "type":"Manufacturing & Wholesale Goods"
        }
    ],
    "sg:phone":"+1 613 224 4840",
    "sg:postcode":"K2E 7S4",
    "sg:province":"ON",
    "sg:tags":[
        "audio"
    ],
    "wof:name":"Nova Visual Products",
    "wof:placetype":"venue"
},
  "geometry": {"coordinates":[-75.705498,45.3437],"type":"Point"}
}