{
  "type": "Feature",
  "properties": {
    "addr:full":"1035 Vanier Blvd Bathurst NB E2A 3N4",
    "addr:housenumber":"1035",
    "addr:postcode":"e2a 3n4",
    "addr:street":"Vanier Blvd",
    "iso:country":"CA",
    "sg:address":"1035 Vanier Blvd",
    "sg:city":"Bathurst",
    "sg:classifiers":[
        {
            "category":"Retail",
            "subcategory":"Auto Repair",
            "type":"Services"
        }
    ],
    "sg:phone":"+1 506 548 2159",
    "sg:postcode":"E2A 3N4",
    "sg:province":"NB",
    "sg:tags":[
        "wrecker"
    ],
    "wof:name":"Bathurst Towing",
    "wof:placetype":"venue"
},
  "geometry": {"coordinates":[-65.6934432983,47.6393547058],"type":"Point"}
}