{
  "type": "Feature",
  "properties": {
    "addr:full":"1525 45 St SE Calgary AB T2A 1N3",
    "addr:housenumber":"1525",
    "addr:postcode":"t2a 1n3",
    "addr:street":"45 St Se",
    "iso:country":"CA",
    "sg:address":"1525 45 St SE",
    "sg:city":"Calgary",
    "sg:classifiers":[
        {
            "category":"Organizations",
            "subcategory":"Religious Organization",
            "type":"Services"
        }
    ],
    "sg:phone":"+1 403 272 1258",
    "sg:postcode":"T2A 1N3",
    "sg:province":"AB",
    "sg:tags":[
        "church"
    ],
    "wof:name":"Holy Trinity Church",
    "wof:placetype":"venue"
},
  "geometry": {"coordinates":[-113.968765,51.04063],"type":"Point"}
}