{
  "type": "Feature",
  "properties": {
    "addr:full":"PO Box 288 Bay Bulls NL A0A 1C0",
    "addr:housenumber":"po;288",
    "addr:postcode":"a0a 1c0",
    "addr:street":"Box;Bay Bulls",
    "iso:country":"CA",
    "sg:address":"PO Box 288",
    "sg:city":"Bay Bulls",
    "sg:classifiers":[
        {
            "category":"Education",
            "subcategory":"School",
            "type":"Public Place"
        }
    ],
    "sg:phone":"+1 709 334 2808",
    "sg:postcode":"A0A 1C0",
    "sg:province":"NL",
    "wof:name":"St Patrick's Elementary",
    "wof:placetype":"venue"
},
  "geometry": {"coordinates":[-52.8186035156,47.3170166016],"type":"Point"}
}