{
  "type": "Feature",
  "properties": {
    "addr:full":"11211 100 St Grande Prairie AB T8V 6P7",
    "addr:housenumber":"11211",
    "addr:postcode":"t8v 6p7",
    "addr:street":"100 St",
    "iso:country":"CA",
    "sg:address":"11211 100 St",
    "sg:city":"Grande Prairie",
    "sg:classifiers":[
        {
            "category":"Retail",
            "subcategory":"Auto Repair",
            "type":"Services"
        }
    ],
    "sg:phone":"+1 780 538 4242",
    "sg:postcode":"T8V 6P7",
    "sg:province":"AB",
    "sg:tags":[
        "repairing",
        "automobile"
    ],
    "wof:name":"Midas Auto Svc Experts",
    "wof:placetype":"venue"
},
  "geometry": {"coordinates":[-118.79460899999999,55.181992],"type":"Point"}
}