{
  "type": "Feature",
  "properties": {
    "iso:country":"CA",
    "sg:address":"3420 the Collegeway #308",
    "sg:city":"Mississauga",
    "sg:classifiers":[
        {
            "category":"Wholesale",
            "subcategory":"Stationery",
            "type":"Manufacturing & Wholesale Goods"
        }
    ],
    "sg:phone":"+1 905 607 2448",
    "sg:postcode":"L5L 5T2",
    "sg:province":"ON",
    "sg:tags":[
        "product",
        "paper"
    ],
    "wof:name":"J & S Distribution",
    "wof:placetype":"venue"
},
  "geometry": {"coordinates":[-79.7045516968,43.5232200623],"type":"Point"}
}