{
  "type": "Feature",
  "properties": {
    "addr:full":"Victoria BC V8V 4Z3",
    "addr:postcode":"v8v 4z3",
    "iso:country":"CA",
    "sg:city":"Victoria",
    "sg:classifiers":[
        {
            "category":"Education",
            "subcategory":"School",
            "type":"Public Place"
        }
    ],
    "sg:phone":"+1 250 381 3755",
    "sg:postcode":"V8V 4Z3",
    "sg:province":"BC",
    "sg:tags":[
        "academic",
        "special"
    ],
    "wof:name":"Project Literacy Victoria",
    "wof:placetype":"venue"
},
  "geometry": {"coordinates":[-123.358337402,48.4258155823],"type":"Point"}
}