{
  "type": "Feature",
  "properties": {
    "addr:full":"31278 Hwy 17 Chalk River ON K0J 1J0",
    "addr:housenumber":"31278",
    "addr:postcode":"k0j 1j0",
    "addr:street":"Hwy 17",
    "iso:country":"CA",
    "sg:address":"31278 Hwy 17",
    "sg:city":"Chalk River",
    "sg:classifiers":[
        {
            "category":"Manufacturing",
            "subcategory":"Tools & Machinery",
            "type":"Manufacturing & Wholesale Goods"
        }
    ],
    "sg:phone":"+1 613 589 2456",
    "sg:postcode":"K0J 1J0",
    "sg:province":"ON",
    "sg:tags":[
        "instrument",
        "radioactivity",
        "scientific",
        "apparatus"
    ],
    "wof:name":"Bubble Technology Industries",
    "wof:placetype":"venue"
},
  "geometry": {"coordinates":[-77.449631,46.019112],"type":"Point"}
}