{
  "type": "Feature",
  "properties": {
    "addr:full":"345 Main St Tofino BC V0R 2Z0",
    "addr:housenumber":"345",
    "addr:postcode":"v0r 2z0",
    "addr:street":"Main St",
    "iso:country":"CA",
    "sg:address":"345 Main St",
    "sg:city":"Tofino",
    "sg:classifiers":[
        {
            "category":"Professional",
            "type":"Services"
        }
    ],
    "sg:phone":"+1 250 725 3120",
    "sg:postcode":"V0R 2Z0",
    "sg:province":"BC",
    "sg:tags":[
        "arts",
        "artist"
    ],
    "wof:name":"Coastline Art",
    "wof:placetype":"venue"
},
  "geometry": {"coordinates":[-125.906631,49.153717],"type":"Point"}
}