{
  "type": "Feature",
  "properties": {
    "addr:full":"8665 Boul DE L'Ormiere Quebec QC G2C 1C2",
    "addr:housenumber":"8665",
    "addr:postcode":"qc g2c 1c2",
    "addr:street":"Boul De L'Ormiere",
    "iso:country":"CA",
    "sg:address":"8665 Boul DE L'Ormiere",
    "sg:city":"Quebec",
    "sg:classifiers":[
        {
            "category":"Shopping",
            "subcategory":"Computers & Home Electronics",
            "type":"Retail Goods"
        }
    ],
    "sg:phone":"+1 418 847 1581",
    "sg:postcode":"G2C 1C2",
    "sg:province":"QC",
    "sg:tags":[
        "equipment",
        "dealer"
    ],
    "wof:name":"Centre-L'Ordinateur L'Ormiere",
    "wof:placetype":"venue"
},
  "geometry": {"coordinates":[-71.3399353027,46.8249206543],"type":"Point"}
}