{
  "type": "Feature",
  "properties": {
    "iso:country":"CA",
    "sg:address":"4261 Highway 7 # 3B",
    "sg:city":"Markham",
    "sg:classifiers":[
        {
            "category":"Building & Trades",
            "subcategory":"Construction",
            "type":"Services"
        }
    ],
    "sg:phone":"+1 905 479 7665",
    "sg:postcode":"L3R 9W6",
    "sg:province":"ON",
    "sg:tags":[
        "designer",
        "dealer",
        "pool",
        "swimming"
    ],
    "wof:name":"Mayfair Pools & Supplies Inc",
    "wof:placetype":"venue"
},
  "geometry": {"coordinates":[-79.339943,43.856033],"type":"Point"}
}