{
  "type": "Feature",
  "properties": {
    "addr:full":"5140 Hubalta Rd SE Calgary AB T2B 2P1",
    "addr:housenumber":"5140",
    "addr:postcode":"t2b 2p1",
    "addr:street":"Hubalta Rd Se",
    "iso:country":"CA",
    "sg:address":"5140 Hubalta Rd SE",
    "sg:city":"Calgary",
    "sg:classifiers":[
        {
            "category":"Autos & Motor Vehicles",
            "subcategory":"Auto Supplies",
            "type":"Retail Goods"
        }
    ],
    "sg:phone":"+1 403 272 3391",
    "sg:postcode":"T2B 2P1",
    "sg:province":"AB",
    "sg:tags":[
        "automobile",
        "parts"
    ],
    "wof:name":"Auto Value Parts",
    "wof:placetype":"venue"
},
  "geometry": {"coordinates":[-113.960335,51.032974],"type":"Point"}
}