{
  "type": "Feature",
  "properties": {
    "addr:full":"3455 Fairview St Burlington ON L7N 2R4",
    "addr:housenumber":"3455",
    "addr:postcode":"l7n 2r4",
    "addr:street":"Fairview St",
    "iso:country":"CA",
    "sg:address":"3455 Fairview St",
    "sg:city":"Burlington",
    "sg:classifiers":[
        {
            "category":"Restaurant",
            "type":"Food & Drink"
        }
    ],
    "sg:phone":"+1 905 637 7171",
    "sg:postcode":"L7N 2R4",
    "sg:province":"ON",
    "wof:name":"Napoleon's Steak & Seafood Hse",
    "wof:placetype":"venue"
},
  "geometry": {"coordinates":[-79.78209699999999,43.357525],"type":"Point"}
}