{
  "type": "Feature",
  "properties": {
    "addr:full":"1939 Sheppard Ave W North York ON M3L 1Y8",
    "addr:housenumber":"1939",
    "addr:postcode":"m3l 1y8",
    "addr:street":"Sheppard Ave W",
    "iso:country":"CA",
    "sg:address":"1939 Sheppard Ave W",
    "sg:city":"North York",
    "sg:classifiers":[
        {
            "category":"Shopping",
            "subcategory":"Florist",
            "type":"Retail Goods"
        }
    ],
    "sg:phone":"+1 416 747 9525",
    "sg:postcode":"M3L 1Y8",
    "sg:province":"ON",
    "wof:name":"Cattolica Flowers",
    "wof:placetype":"venue"
},
  "geometry": {"coordinates":[-79.5118713379,43.739364624],"type":"Point"}
}