{
  "type": "Feature",
  "properties": {
    "addr:full":"1560 Falls St Allanburg ON L0S 1A0",
    "addr:housenumber":"1560",
    "addr:postcode":"l0s 1a0",
    "addr:street":"Falls St",
    "iso:country":"CA",
    "sg:address":"1560 Falls St",
    "sg:city":"Allanburg",
    "sg:classifiers":[
        {
            "category":"Recreation",
            "type":"Entertainment"
        }
    ],
    "sg:phone":"+1 905 227 2042",
    "sg:postcode":"L0S 1A0",
    "sg:province":"ON",
    "sg:tags":[
        "hall",
        "auditorium"
    ],
    "wof:name":"Allanburg Community Ctr",
    "wof:placetype":"venue"
},
  "geometry": {"coordinates":[-79.2080383301,43.0776519775],"type":"Point"}
}