{
  "type": "Feature",
  "properties": {
    "addr:full":"235 Boul Marcotte Roberval QC G8H 1Z3",
    "addr:housenumber":"235",
    "addr:postcode":"g8h 1z3",
    "addr:street":"Boul Marcotte",
    "iso:country":"CA",
    "sg:address":"235 Boul Marcotte",
    "sg:city":"Roberval",
    "sg:classifiers":[
        {
            "category":"Building & Trades",
            "subcategory":"Construction",
            "type":"Services"
        }
    ],
    "sg:phone":"+1 418 275 0222",
    "sg:postcode":"G8H 1Z3",
    "sg:province":"QC",
    "sg:tags":[
        "general",
        "contractor"
    ],
    "wof:name":"Construction Martin Tanguay",
    "wof:placetype":"venue"
},
  "geometry": {"coordinates":[-72.22217559809999,48.5001983643],"type":"Point"}
}