{
  "type": "Feature",
  "properties": {
    "addr:full":"Victoria BC V8W 2E1",
    "addr:postcode":"v8w 2e1",
    "iso:country":"CA",
    "sg:city":"Victoria",
    "sg:classifiers":[
        {
            "category":"Real Estate",
            "subcategory":"Real Estate Agent",
            "type":"Services"
        }
    ],
    "sg:phone":"+1 250 388 6454",
    "sg:postcode":"V8W 2E1",
    "sg:province":"BC",
    "wof:name":"Colliers Mac Aulay Nicolls Inc",
    "wof:placetype":"venue"
},
  "geometry": {"coordinates":[-123.365074158,48.4251785278],"type":"Point"}
}