{
  "type": "Feature",
  "properties": {
    "addr:full":"222 3 St SW Calgary AB T2P 1P9",
    "addr:housenumber":"222 3",
    "addr:postcode":"t2p 1p9",
    "addr:street":"St Sw",
    "iso:country":"CA",
    "sg:address":"222 3 St SW",
    "sg:city":"Calgary",
    "sg:classifiers":[
        {
            "category":"Restaurant",
            "type":"Food & Drink"
        }
    ],
    "sg:phone":"+1 403 263 7223",
    "sg:postcode":"T2P 1P9",
    "sg:province":"AB",
    "wof:name":"Old Spaghetti Factory",
    "wof:placetype":"venue"
},
  "geometry": {"coordinates":[-114.06978599999999,51.051125],"type":"Point"}
}