{
  "type": "Feature",
  "properties": {
    "addr:full":"930 15 Ave SW Calgary AB T2R 0S4",
    "addr:housenumber":"930",
    "addr:postcode":"t2r 0s4",
    "addr:street":"15 Ave Sw",
    "iso:country":"CA",
    "sg:address":"930 15 Ave SW",
    "sg:city":"Calgary",
    "sg:classifiers":[
        {
            "category":"Real Estate",
            "subcategory":"Real Estate Operator",
            "type":"Services"
        }
    ],
    "sg:phone":"+1 403 245 0375",
    "sg:postcode":"T2R 0S4",
    "sg:province":"AB",
    "sg:tags":[
        "apartment"
    ],
    "wof:name":"Centennial House",
    "wof:placetype":"venue"
},
  "geometry": {"coordinates":[-114.08254241900001,51.0392341614],"type":"Point"}
}