{
  "type": "Feature",
  "properties": {
    "addr:full":"280 Spadina Rd Toronto ON M5R 2V4",
    "addr:housenumber":"280",
    "addr:postcode":"m5r 2v4",
    "addr:street":"Spadina Rd",
    "iso:country":"CA",
    "sg:address":"280 Spadina Rd",
    "sg:city":"Toronto",
    "sg:classifiers":[
        {
            "category":"Shopping",
            "subcategory":"Clothing, Apparel, & Fashions",
            "type":"Retail Goods"
        }
    ],
    "sg:phone":"+1 416 341 9669",
    "sg:postcode":"M5R 2V4",
    "sg:province":"ON",
    "wof:name":"My Heart Lingerie",
    "wof:placetype":"venue"
},
  "geometry": {"coordinates":[-79.40906524659999,43.679233551],"type":"Point"}
}