{
  "type": "Feature",
  "properties": {
    "addr:full":"10321 85 St NW Calgary AB T3G 5H5",
    "addr:housenumber":"10321",
    "addr:postcode":"t3g 5h5",
    "addr:street":"85 St Nw",
    "iso:country":"CA",
    "sg:address":"10321 85 St NW",
    "sg:city":"Calgary",
    "sg:classifiers":[
        {
            "category":"Retail",
            "subcategory":"Animal Services",
            "type":"Services"
        }
    ],
    "sg:phone":"+1 403 239 0598",
    "sg:postcode":"T3G 5H5",
    "sg:province":"AB",
    "sg:tags":[
        "pet",
        "boarding",
        "sitting"
    ],
    "wof:name":"Rocky Glen Kennels Ltd",
    "wof:placetype":"venue"
},
  "geometry": {"coordinates":[-114.212608,51.15015],"type":"Point"}
}