{
  "type": "Feature",
  "properties": {
    "addr:full":"Melville SK S0A 2P0",
    "addr:postcode":"s0a 2p0",
    "iso:country":"CA",
    "sg:city":"Melville",
    "sg:classifiers":[
        {
            "category":"Organizations",
            "subcategory":"Religious Organization",
            "type":"Services"
        }
    ],
    "sg:phone":"+1 306 728 5057",
    "sg:postcode":"S0A 2P0",
    "sg:province":"SK",
    "sg:tags":[
        "church"
    ],
    "wof:name":"United Church Office",
    "wof:placetype":"venue"
},
  "geometry": {"coordinates":[-102.803466797,50.9300231934],"type":"Point"}
}