{
  "type": "Feature",
  "properties": {
    "iso:country":"CA",
    "sg:address":"519 Main St E",
    "sg:city":"Leader",
    "sg:classifiers":[
        {
            "category":"Health Services",
            "subcategory":"Doctor",
            "type":"Services"
        }
    ],
    "sg:phone":"+1 306 628 4584",
    "sg:postcode":"S0N 1H0",
    "sg:province":"SK",
    "sg:tags":[
        "physician",
        "surgeon"
    ],
    "wof:name":"Leader Medical Clinic",
    "wof:placetype":"venue"
},
  "geometry": {"coordinates":[-109.536506653,50.8870353699],"type":"Point"}
}