{
  "type": "Feature",
  "properties": {
    "iso:country":"CA",
    "sg:city":"Barrie",
    "sg:classifiers":[
        {
            "category":"Health Services",
            "subcategory":"Doctor",
            "type":"Services"
        }
    ],
    "sg:phone":"+1 705 737 2582",
    "sg:postcode":"L4N 4Y5",
    "sg:province":"ON",
    "sg:tags":[
        "dentist"
    ],
    "wof:name":"Staples, David A DDS",
    "wof:placetype":"venue"
},
  "geometry": {"coordinates":[-79.682167,44.357983],"type":"Point"}
}