{
  "type": "Feature",
  "properties": {
    "addr:full":"2205 Av Charland Montreal QC H1Z 1B3",
    "addr:housenumber":"2205",
    "addr:postcode":"h1z 1b3",
    "addr:street":"Av Charland",
    "iso:country":"CA",
    "sg:address":"2205 Av Charland",
    "sg:city":"Montreal",
    "sg:classifiers":[
        {
            "category":"Retail",
            "subcategory":"Auto Repair",
            "type":"Services"
        }
    ],
    "sg:phone":"+1 514 389 8118",
    "sg:postcode":"H1Z 1B3",
    "sg:province":"QC",
    "sg:tags":[
        "automobile",
        "electric"
    ],
    "wof:name":"Messore Centre D'Auto",
    "wof:placetype":"venue"
},
  "geometry": {"coordinates":[-73.6412277222,45.5689964294],"type":"Point"}
}