{
  "type": "Feature",
  "properties": {
    "addr:full":"Peace River AB T8S 1S2",
    "addr:postcode":"t8s 1s2",
    "iso:country":"CA",
    "sg:city":"Peace River",
    "sg:classifiers":[
        {
            "category":"Building & Trades",
            "subcategory":"Landscaping Services",
            "type":"Services"
        }
    ],
    "sg:phone":"+1 780 624 4746",
    "sg:postcode":"T8S 1S2",
    "sg:province":"AB",
    "sg:tags":[
        "lawn",
        "maintenance",
        "grounds"
    ],
    "wof:name":"Waterworks Irrigation & Lawn",
    "wof:placetype":"venue"
},
  "geometry": {"coordinates":[-117.293854,56.243088],"type":"Point"}
}