{
  "type": "Feature",
  "properties": {
    "addr:full":"1991 Main St Vancouver BC V5T 3C1",
    "addr:housenumber":"1991",
    "addr:postcode":"v5t 3c1",
    "addr:street":"Main St",
    "iso:country":"CA",
    "sg:address":"1991 Main St",
    "sg:city":"Vancouver",
    "sg:classifiers":[
        {
            "category":"Wholesale",
            "subcategory":"Motor Vehicles",
            "type":"Manufacturing & Wholesale Goods"
        }
    ],
    "sg:phone":"+1 604 732 7833",
    "sg:postcode":"V5T 3C1",
    "sg:province":"BC",
    "sg:tags":[
        "renting",
        "automobile",
        "truck",
        "broker"
    ],
    "wof:name":"Triad Leasing CO Ltd",
    "wof:placetype":"venue"
},
  "geometry": {"coordinates":[-123.10099,49.267498],"type":"Point"}
}