{
  "type": "Feature",
  "properties": {
    "addr:full":"41035 Front St Clinton ON N0M 1L0",
    "addr:housenumber":"41035",
    "addr:postcode":"n0m 1l0",
    "addr:street":"Front St",
    "iso:country":"CA",
    "sg:address":"41035 Front St",
    "sg:city":"Clinton",
    "sg:classifiers":[
        {
            "category":"Wholesale",
            "subcategory":"Non-durable Goods",
            "type":"Manufacturing & Wholesale Goods"
        }
    ],
    "sg:phone":"+1 519 233 7080",
    "sg:postcode":"N0M 1L0",
    "sg:province":"ON",
    "sg:tags":[
        "advertising"
    ],
    "wof:name":"Y2K Promotional Products",
    "wof:placetype":"venue"
},
  "geometry": {"coordinates":[-81.53969573969999,43.6176681519],"type":"Point"}
}