{
  "type": "Feature",
  "properties": {
    "addr:full":"4134 Rue Principale Tracadie-Sheila NB E1X 1B8",
    "addr:housenumber":"4134",
    "addr:postcode":"e1x 1b8",
    "addr:street":"Rue Principale",
    "iso:country":"CA",
    "sg:address":"4134 Rue Principale",
    "sg:city":"Tracadie-Sheila",
    "sg:classifiers":[
        {
            "category":"Health Services",
            "subcategory":"Doctor",
            "type":"Services"
        }
    ],
    "sg:phone":"+1 506 395 3300",
    "sg:postcode":"E1X 1B8",
    "sg:province":"NB",
    "sg:tags":[
        "dentist"
    ],
    "wof:name":"Antuna, Silvia DDS",
    "wof:placetype":"venue"
},
  "geometry": {"coordinates":[-64.91925048829999,47.4861907959],"type":"Point"}
}