{
  "type": "Feature",
  "properties": {
    "addr:full":"133 Hwy 60 Huntsville ON P1H 2K8",
    "addr:housenumber":"133",
    "addr:postcode":"p1h 2k8",
    "addr:street":"Hwy 60",
    "iso:country":"CA",
    "sg:address":"133 Hwy 60",
    "sg:city":"Huntsville",
    "sg:classifiers":[
        {
            "category":"Professional",
            "subcategory":"Lawyer & Legal Services",
            "type":"Services"
        }
    ],
    "sg:phone":"+1 705 789 9659",
    "sg:postcode":"P1H 2K8",
    "sg:province":"ON",
    "sg:tags":[
        "attorney"
    ],
    "wof:name":"Bagshaw, J Ross QC",
    "wof:placetype":"venue"
},
  "geometry": {"coordinates":[-79.1978759766,45.3378181458],"type":"Point"}
}