{
  "type": "Feature",
  "properties": {
    "addr:full":"Weagamow Lake ON P0V 2Y0",
    "addr:postcode":"p0v 2y0",
    "iso:country":"CA",
    "sg:city":"Weagamow Lake",
    "sg:classifiers":[
        {
            "category":"Food & Beverages",
            "subcategory":"Groceries & Convenience Stores",
            "type":"Retail Goods"
        }
    ],
    "sg:phone":"+1 807 469 1452",
    "sg:postcode":"P0V 2Y0",
    "sg:province":"ON",
    "sg:tags":[
        "grocer"
    ],
    "wof:name":"Indian Store",
    "wof:placetype":"venue"
},
  "geometry": {"coordinates":[-91.3333282471,52.9500007629],"type":"Point"}
}