{
  "type": "Feature",
  "properties": {
    "addr:full":"4225 Fraser St Vancouver BC V5V 4G1",
    "addr:housenumber":"4225",
    "addr:postcode":"v5v 4g1",
    "addr:street":"Fraser St",
    "iso:country":"CA",
    "sg:address":"4225 Fraser St",
    "sg:city":"Vancouver",
    "sg:classifiers":[
        {
            "category":"Cinema",
            "subcategory":"Movie Rental",
            "type":"Entertainment"
        }
    ],
    "sg:phone":"+1 604 876 0030",
    "sg:postcode":"V5V 4G1",
    "sg:province":"BC",
    "sg:tags":[
        "leasing",
        "video",
        "disc",
        "tape"
    ],
    "wof:name":"Aling Pining Video Rental",
    "wof:placetype":"venue"
},
  "geometry": {"coordinates":[-123.090301514,49.2473449707],"type":"Point"}
}