{
  "type": "Feature",
  "properties": {
    "addr:full":"238 Highland St Haliburton ON K0M 1S0",
    "addr:housenumber":"238",
    "addr:postcode":"k0m 1s0",
    "addr:street":"Highland St",
    "iso:country":"CA",
    "sg:address":"238 Highland St",
    "sg:city":"Haliburton",
    "sg:classifiers":[
        {
            "category":"Professional",
            "subcategory":"Lawyer & Legal Services",
            "type":"Services"
        }
    ],
    "sg:phone":"+1 705 457 1440",
    "sg:postcode":"K0M 1S0",
    "sg:province":"ON",
    "sg:tags":[
        "attorney"
    ],
    "wof:name":"Bishop & Rogers",
    "wof:placetype":"venue"
},
  "geometry": {"coordinates":[-78.508842,45.04631],"type":"Point"}
}