{
  "type": "Feature",
  "properties": {
    "addr:full":"Nepean ON K2G 4V3",
    "addr:postcode":"k2g 4v3",
    "iso:country":"CA",
    "sg:city":"Nepean",
    "sg:classifiers":[
        {
            "category":"Restaurant",
            "type":"Food & Drink"
        }
    ],
    "sg:phone":"+1 613 228 0840",
    "sg:postcode":"K2G 4V3",
    "sg:province":"ON",
    "wof:name":"Yangming Buffet",
    "wof:placetype":"venue"
},
  "geometry": {"coordinates":[-75.7352600098,45.3544311523],"type":"Point"}
}