{
  "type": "Feature",
  "properties": {
    "addr:full":"2950 Bremner Ave Red Deer AB T4R 1M9",
    "addr:housenumber":"2950",
    "addr:postcode":"t4r 1m9",
    "addr:street":"Bremner Ave",
    "iso:country":"CA",
    "sg:address":"2950 Bremner Ave",
    "sg:city":"Red Deer",
    "sg:classifiers":[
        {
            "category":"Manufacturing",
            "subcategory":"Printing",
            "type":"Manufacturing & Wholesale Goods"
        }
    ],
    "sg:phone":"+1 403 343 2400",
    "sg:postcode":"T4R 1M9",
    "sg:province":"AB",
    "sg:tags":[
        "newspaper",
        "printer"
    ],
    "wof:name":"Red Deer Advocate",
    "wof:placetype":"venue"
},
  "geometry": {"coordinates":[-113.810349,52.247639],"type":"Point"}
}