{
  "type": "Feature",
  "properties": {
    "addr:full":"40 Coburg St Saint John NB E2L 3J5",
    "addr:housenumber":"40",
    "addr:postcode":"nb e2l 3j5",
    "addr:street":"Coburg St",
    "iso:country":"CA",
    "sg:address":"40 Coburg St",
    "sg:city":"Saint John",
    "sg:classifiers":[
        {
            "category":"Real Estate",
            "subcategory":"Architect",
            "type":"Services"
        }
    ],
    "sg:phone":"+1 506 634 8860",
    "sg:postcode":"E2L 3J5",
    "sg:province":"NB",
    "wof:name":"Steen Knorr Architecture Inc",
    "wof:placetype":"venue"
},
  "geometry": {"coordinates":[-66.05948600000001,45.275948],"type":"Point"}
}