{
  "type": "Feature",
  "properties": {
    "addr:full":"Burnaby BC V5C 6G9",
    "addr:postcode":"v5c 6g9",
    "iso:country":"CA",
    "sg:city":"Burnaby",
    "sg:classifiers":[
        {
            "category":"Education",
            "subcategory":"College",
            "type":"Public Place"
        }
    ],
    "sg:phone":"+1 604 205 6999",
    "sg:postcode":"V5C 6G9",
    "sg:province":"BC",
    "sg:tags":[
        "academic",
        "school"
    ],
    "wof:name":"University of Phoenix",
    "wof:placetype":"venue"
},
  "geometry": {"coordinates":[-123.007118225,49.2601013184],"type":"Point"}
}