{
  "type": "Feature",
  "properties": {
    "addr:full":"80 Bolton St Bobcaygeon ON K0M 1A0",
    "addr:housenumber":"80",
    "addr:postcode":"k0m 1a0",
    "addr:street":"Bolton St",
    "iso:country":"CA",
    "sg:address":"80 Bolton St",
    "sg:city":"Bobcaygeon",
    "sg:classifiers":[
        {
            "category":"Restaurant",
            "type":"Food & Drink"
        }
    ],
    "sg:phone":"+1 705 738 6608",
    "sg:postcode":"K0M 1A0",
    "sg:province":"ON",
    "wof:name":"Mac Doo's",
    "wof:placetype":"venue"
},
  "geometry": {"coordinates":[-78.5437698364,44.5361709595],"type":"Point"}
}