{
  "type": "Feature",
  "properties": {
    "iso:country":"CA",
    "sg:address":"3530 Kempt Rd",
    "sg:city":"Halifax",
    "sg:classifiers":[
        {
            "category":"Retail",
            "subcategory":"Auto Repair",
            "type":"Services"
        }
    ],
    "sg:phone":"+1 902 404 0404",
    "sg:postcode":"B3K 4X8",
    "sg:province":"NS",
    "sg:tags":[
        "alternator",
        "automobile",
        "electric",
        "starter"
    ],
    "wof:name":"Rand Auto Electric Ltd",
    "wof:placetype":"venue"
},
  "geometry": {"coordinates":[-63.61581,44.661537],"type":"Point"}
}