{
  "type": "Feature",
  "properties": {
    "addr:full":"365 Oakdale Rd North York ON M3N 1W7",
    "addr:housenumber":"365",
    "addr:postcode":"m3n 1w7",
    "addr:street":"Oakdale Rd",
    "iso:country":"CA",
    "sg:address":"365 Oakdale Rd",
    "sg:city":"North York",
    "sg:classifiers":[
        {
            "category":"Wholesale",
            "subcategory":"Home Furnishings",
            "type":"Manufacturing & Wholesale Goods"
        }
    ],
    "sg:phone":"+1 416 213 8882",
    "sg:postcode":"M3N 1W7",
    "sg:province":"ON",
    "sg:tags":[
        "venetian",
        "blind"
    ],
    "wof:name":"Progressive Distribution Inc",
    "wof:placetype":"venue"
},
  "geometry": {"coordinates":[-79.526466,43.747799],"type":"Point"}
}