{
  "type": "Feature",
  "properties": {
    "iso:country":"CA",
    "sg:address":"31 11th Ave S",
    "sg:city":"Cranbrook",
    "sg:classifiers":[
        {
            "category":"Government",
            "subcategory":"Fire Station",
            "type":"Public Place"
        }
    ],
    "sg:phone":"+1 250 426 2325",
    "sg:postcode":"V1C 2N9",
    "sg:province":"BC",
    "sg:tags":[
        "department"
    ],
    "wof:name":"Cranbrook Fire Hall",
    "wof:placetype":"venue"
},
  "geometry": {"coordinates":[-115.76638794,49.5114936829],"type":"Point"}
}