{
  "type": "Feature",
  "properties": {
    "addr:full":"424 West St N Orillia ON L3V 5E8",
    "addr:housenumber":"424",
    "addr:postcode":"l3v 5e8",
    "addr:street":"West St N",
    "iso:country":"CA",
    "sg:address":"424 West St N",
    "sg:city":"Orillia",
    "sg:classifiers":[
        {
            "category":"Restaurant",
            "type":"Food & Drink"
        }
    ],
    "sg:phone":"+1 705 325 1022",
    "sg:postcode":"L3V 5E8",
    "sg:province":"ON",
    "wof:name":"Kfc",
    "wof:placetype":"venue"
},
  "geometry": {"coordinates":[-79.431595,44.622925],"type":"Point"}
}