{
  "type": "Feature",
  "properties": {
    "addr:full":"Joliette QC J6E 8C6",
    "addr:postcode":"j6e 8c6",
    "iso:country":"CA",
    "sg:city":"Joliette",
    "sg:classifiers":[
        {
            "category":"Shopping",
            "subcategory":"Computers & Home Electronics",
            "type":"Retail Goods"
        }
    ],
    "sg:phone":"+1 450 759 8696",
    "sg:postcode":"J6E 8C6",
    "sg:province":"QC",
    "sg:tags":[
        "equipment",
        "dealer"
    ],
    "wof:name":"Infotech Sl",
    "wof:placetype":"venue"
},
  "geometry": {"coordinates":[-73.464294,46.022655],"type":"Point"}
}