{
  "type": "Feature",
  "properties": {
    "addr:full":"200 Bridge St Saint John NB E2K 1S7",
    "addr:housenumber":"200",
    "addr:postcode":"e2k 1s7",
    "addr:street":"Bridge St",
    "iso:country":"CA",
    "sg:address":"200 Bridge St",
    "sg:city":"Saint John",
    "sg:classifiers":[
        {
            "category":"Travel",
            "subcategory":"Travel Agent",
            "type":"Entertainment"
        }
    ],
    "sg:phone":"+1 506 658 2937",
    "sg:postcode":"E2K 1S7",
    "sg:province":"NB",
    "sg:tags":[
        "information",
        "tourist",
        "government"
    ],
    "wof:name":"Tourist Information",
    "wof:placetype":"venue"
},
  "geometry": {"coordinates":[-66.088180542,45.2766342163],"type":"Point"}
}