{
  "type": "Feature",
  "properties": {
    "addr:full":"7960 132 St Surrey BC V3W 4N1",
    "addr:housenumber":"7960",
    "addr:postcode":"v3w 4n1",
    "addr:street":"132 St",
    "iso:country":"CA",
    "sg:address":"7960 132 St",
    "sg:city":"Surrey",
    "sg:classifiers":[
        {
            "category":"Wholesale",
            "subcategory":"Construction Materials",
            "type":"Manufacturing & Wholesale Goods"
        }
    ],
    "sg:phone":"+1 604 502 8900",
    "sg:postcode":"V3W 4N1",
    "sg:province":"BC",
    "sg:tags":[
        "sand",
        "gravel"
    ],
    "wof:name":"Raider Stone Slinger Svc Inc",
    "wof:placetype":"venue"
},
  "geometry": {"coordinates":[-122.85667419400001,49.1473693848],"type":"Point"}
}