{
  "type": "Feature",
  "properties": {
    "addr:full":"2661 Av Tour Du Lac Lac-A-LA-Tortue QC G0X 1L0",
    "addr:housenumber":"2661",
    "addr:postcode":"g0x 1l0",
    "addr:street":"Av Tour Du Lac Lac-A-La-Tortue",
    "iso:country":"CA",
    "sg:address":"2661 Av Tour Du Lac",
    "sg:city":"Lac-A-LA-Tortue",
    "sg:classifiers":[
        {
            "category":"Retail",
            "subcategory":"Repair Shop",
            "type":"Services"
        }
    ],
    "sg:phone":"+1 819 538 7297",
    "sg:postcode":"G0X 1L0",
    "sg:province":"QC",
    "sg:tags":[
        "solder",
        "welding"
    ],
    "wof:name":"Z Lahaie Inc",
    "wof:placetype":"venue"
},
  "geometry": {"coordinates":[-72.618332,46.62735],"type":"Point"}
}