{
  "type": "Feature",
  "properties": {
    "addr:full":"2703 79 St NW #159 Edmonton AB T6K 3Z6",
    "addr:housenumber":"2703",
    "addr:postcode":"t6k 3z6",
    "addr:street":"79 St Nw # 159",
    "iso:country":"CA",
    "sg:address":"2703 79 St NW #159",
    "sg:city":"Edmonton",
    "sg:classifiers":[
        {
            "category":"Real Estate",
            "subcategory":"Real Estate Operator",
            "type":"Services"
        }
    ],
    "sg:phone":"+1 780 440 4053",
    "sg:postcode":"T6K 3Z6",
    "sg:province":"AB",
    "sg:tags":[
        "condominium"
    ],
    "wof:name":"Emerald Place Phase 1 Condo",
    "wof:placetype":"venue"
},
  "geometry": {"coordinates":[-113.45344543500001,53.4578437805],"type":"Point"}
}