{
  "type": "Feature",
  "properties": {
    "addr:full":"669 Wilson St Saint John NB E2M 3V1",
    "addr:housenumber":"669",
    "addr:postcode":"e2m 3v1",
    "addr:street":"Wilson St",
    "iso:country":"CA",
    "sg:address":"669 Wilson St",
    "sg:city":"Saint John",
    "sg:classifiers":[
        {
            "category":"Banks & Credit Unions",
            "subcategory":"Investment Brokerage",
            "type":"Services"
        }
    ],
    "sg:phone":"+1 506 658 0156",
    "sg:postcode":"E2M 3V1",
    "sg:province":"NB",
    "wof:name":"Armstrong Financial Svc Inc",
    "wof:placetype":"venue"
},
  "geometry": {"coordinates":[-66.09917449949999,45.2540931702],"type":"Point"}
}