{
  "type": "Feature",
  "properties": {
    "addr:full":"770 Boul Guimond Longueuil QC J4G 1V6",
    "addr:housenumber":"770",
    "addr:postcode":"j4g 1v6",
    "addr:street":"Boul Guimond",
    "iso:country":"CA",
    "sg:address":"770 Boul Guimond",
    "sg:city":"Longueuil",
    "sg:classifiers":[
        {
            "category":"Professional",
            "subcategory":"Advertising",
            "type":"Services"
        }
    ],
    "sg:phone":"+1 514 871 1671",
    "sg:postcode":"J4G 1V6",
    "sg:province":"QC",
    "sg:tags":[
        "counselor"
    ],
    "wof:name":"Quad Communications Marketing",
    "wof:placetype":"venue"
},
  "geometry": {"coordinates":[-73.465385,45.564693],"type":"Point"}
}