{
  "type": "Feature",
  "properties": {
    "addr:full":"901 Rue Des Sorbiers Amos QC J9T 3G7",
    "addr:housenumber":"901",
    "addr:postcode":"j9t 3g7",
    "addr:street":"Rue Des Sorbiers Amos",
    "iso:country":"CA",
    "sg:address":"901 Rue Des Sorbiers",
    "sg:city":"Amos",
    "sg:classifiers":[
        {
            "category":"Building & Trades",
            "subcategory":"Cleaning & Sanitation",
            "type":"Services"
        }
    ],
    "sg:phone":"+1 819 732 4020",
    "sg:postcode":"J9T 3G7",
    "sg:province":"QC",
    "sg:tags":[
        "window"
    ],
    "wof:name":"Clair & Net",
    "wof:placetype":"venue"
},
  "geometry": {"coordinates":[-78.103256,48.580082],"type":"Point"}
}