{
  "type": "Feature",
  "properties": {
    "addr:full":"538 Rue Saint-Roch Montreal QC H3N 1K6",
    "addr:housenumber":"538",
    "addr:postcode":"h3n 1k6",
    "addr:street":"Rue Saint-Roch",
    "iso:country":"CA",
    "sg:address":"538 Rue Saint-Roch",
    "sg:city":"Montreal",
    "sg:classifiers":[
        {
            "category":"Professional",
            "subcategory":"Accounting & Tax Preparation",
            "type":"Services"
        }
    ],
    "sg:phone":"+1 514 273 4512",
    "sg:postcode":"H3N 1K6",
    "sg:province":"QC",
    "sg:tags":[
        "bookkeeping",
        "general"
    ],
    "wof:name":"G K Bookkeeping Svc Reg",
    "wof:placetype":"venue"
},
  "geometry": {"coordinates":[-73.62898254389999,45.5298995972],"type":"Point"}
}