{
  "type": "Feature",
  "properties": {
    "addr:full":"459 Queen Charlotte Dr SE Calgary AB T2J 4H2",
    "addr:housenumber":"459",
    "addr:postcode":"t2j 4h2",
    "addr:street":"Queen Charlotte Dr Se",
    "iso:country":"CA",
    "sg:address":"459 Queen Charlotte Dr SE",
    "sg:city":"Calgary",
    "sg:classifiers":[
        {
            "category":"Building & Trades",
            "subcategory":"Construction",
            "type":"Services"
        }
    ],
    "sg:phone":"+1 403 278 1552",
    "sg:postcode":"T2J 4H2",
    "sg:province":"AB",
    "sg:tags":[
        "masonry",
        "contractor"
    ],
    "wof:name":"Kurt Fackelmayer Stone Mason",
    "wof:placetype":"venue"
},
  "geometry": {"coordinates":[-114.02504,50.93644],"type":"Point"}
}