{
  "type": "Feature",
  "properties": {
    "addr:full":"3421 Kingsway Vancouver BC V5R 5L3",
    "addr:housenumber":"3421",
    "addr:postcode":"v5r 5l3",
    "addr:street":"Kingsway",
    "iso:country":"CA",
    "sg:address":"3421 Kingsway",
    "sg:city":"Vancouver",
    "sg:classifiers":[
        {
            "category":"Banks & Credit Unions",
            "subcategory":"Bank",
            "type":"Services"
        }
    ],
    "sg:phone":"+1 604 435 2274",
    "sg:postcode":"V5R 5L3",
    "sg:province":"BC",
    "sg:tags":[
        "cashing",
        "loan",
        "check"
    ],
    "wof:name":"Mr Payday Easy Loans Inc",
    "wof:placetype":"venue"
},
  "geometry": {"coordinates":[-123.03196,49.232357],"type":"Point"}
}