{
  "type": "Feature",
  "properties": {
    "addr:full":"1201 Mountain Rd Moncton NB E1C 2T4",
    "addr:housenumber":"1201",
    "addr:postcode":"e1c 2t4",
    "addr:street":"Mountain Rd",
    "iso:country":"CA",
    "sg:address":"1201 Mountain Rd",
    "sg:city":"Moncton",
    "sg:classifiers":[
        {
            "category":"Personal",
            "subcategory":"Beauty Salon",
            "type":"Services"
        }
    ],
    "sg:phone":"+1 506 382 3223",
    "sg:postcode":"E1C 2T4",
    "sg:province":"NB",
    "wof:name":"Fingers Faces & Feet",
    "wof:placetype":"venue"
},
  "geometry": {"coordinates":[-64.825462,46.107689],"type":"Point"}
}