{
  "type": "Feature",
  "properties": {
    "addr:full":"Scarborough ON M1S 4A7",
    "addr:postcode":"m1s 4a7",
    "iso:country":"CA",
    "sg:city":"Scarborough",
    "sg:classifiers":[
        {
            "category":"Retail",
            "subcategory":"Auto Repair",
            "type":"Services"
        }
    ],
    "sg:phone":"+1 416 298 1353",
    "sg:postcode":"M1S 4A7",
    "sg:province":"ON",
    "sg:tags":[
        "transmission"
    ],
    "wof:name":"Mister Transmission",
    "wof:placetype":"venue"
},
  "geometry": {"coordinates":[-79.2486038208,43.7918701172],"type":"Point"}
}