{
  "type": "Feature",
  "properties": {
    "addr:full":"209 Chain Lake Dr Halifax NS B3S 1C9",
    "addr:housenumber":"209",
    "addr:postcode":"b3s 1c9",
    "addr:street":"Chain Lake Dr",
    "iso:country":"CA",
    "sg:address":"209 Chain Lake Dr",
    "sg:city":"Halifax",
    "sg:classifiers":[
        {
            "category":"Restaurant",
            "type":"Food & Drink"
        }
    ],
    "sg:phone":"+1 902 450 1169",
    "sg:postcode":"B3S 1C9",
    "sg:province":"NS",
    "wof:name":"Burger King",
    "wof:placetype":"venue"
},
  "geometry": {"coordinates":[-63.675617,44.649841],"type":"Point"}
}