{
  "type": "Feature",
  "properties": {
    "addr:full":"Owen Sound ON N4K 6N7",
    "addr:postcode":"n4k 6n7",
    "iso:country":"CA",
    "sg:city":"Owen Sound",
    "sg:classifiers":[
        {
            "category":"Shopping",
            "subcategory":"Shoes",
            "type":"Retail Goods"
        }
    ],
    "sg:phone":"+1 519 371 5529",
    "sg:postcode":"N4K 6N7",
    "sg:province":"ON",
    "sg:tags":[
        "sportswear"
    ],
    "wof:name":"Foot Locker",
    "wof:placetype":"venue"
},
  "geometry": {"coordinates":[-80.921661,44.574303],"type":"Point"}
}