{
  "type": "Feature",
  "properties": {
    "addr:full":"1165 5th Ave Prince George BC V2L 3L1",
    "addr:housenumber":"1165",
    "addr:postcode":"v2l 3l1",
    "addr:street":"5Th Ave",
    "iso:country":"CA",
    "sg:address":"1165 5th Ave",
    "sg:city":"Prince George",
    "sg:classifiers":[
        {
            "category":"Restaurant",
            "type":"Food & Drink"
        }
    ],
    "sg:phone":"+1 250 564 1220",
    "sg:postcode":"V2L 3L1",
    "sg:province":"BC",
    "wof:name":"Cariboo Steak & Seafood Rstrnt",
    "wof:placetype":"venue"
},
  "geometry": {"coordinates":[-122.745201111,53.9147186279],"type":"Point"}
}