{
  "type": "Feature",
  "properties": {
    "iso:country":"CA",
    "sg:address":"3009 Grande Allee",
    "sg:city":"Saint-Hubert",
    "sg:classifiers":[
        {
            "category":"Food & Beverages",
            "subcategory":"Groceries & Convenience Stores",
            "type":"Retail Goods"
        }
    ],
    "sg:phone":"+1 450 672 5875",
    "sg:postcode":"J4T 2R8",
    "sg:province":"QC",
    "sg:tags":[
        "grocer"
    ],
    "wof:name":"Epicerie Cayer",
    "wof:placetype":"venue"
},
  "geometry": {"coordinates":[-73.4816741943,45.5004653931],"type":"Point"}
}