{
  "type": "Feature",
  "properties": {
    "iso:country":"CA",
    "sg:address":"1165 Rang Saint-Michel",
    "sg:city":"Saint-Ignace-DE-Loyola",
    "sg:classifiers":[
        {
            "category":"Wholesale",
            "subcategory":"Construction Materials",
            "type":"Manufacturing & Wholesale Goods"
        }
    ],
    "sg:phone":"+1 450 836 7915",
    "sg:postcode":"J0K 2P0",
    "sg:province":"QC",
    "sg:tags":[
        "concrete",
        "form"
    ],
    "wof:name":"Coffrage M Fafard Inc",
    "wof:placetype":"venue"
},
  "geometry": {"coordinates":[-73.1154251099,46.0645027161],"type":"Point"}
}