{
  "type": "Feature",
  "properties": {
    "iso:country":"CA",
    "sg:address":"5424 97 St NW",
    "sg:city":"Edmonton",
    "sg:classifiers":[
        {
            "category":"Manufacturing",
            "subcategory":"Building Materials",
            "type":"Manufacturing & Wholesale Goods"
        }
    ],
    "sg:phone":"+1 780 438 2896",
    "sg:postcode":"T6E 5C1",
    "sg:province":"AB",
    "wof:name":"Prospec Custom Woodwork Ltd",
    "wof:placetype":"venue"
},
  "geometry": {"coordinates":[-113.479614258,53.4900932312],"type":"Point"}
}