{
  "type": "Feature",
  "properties": {
    "addr:full":"64 Guided Crt Etobicoke ON M9V 4K6",
    "addr:housenumber":"64",
    "addr:postcode":"m9v 4k6",
    "addr:street":"Guided Crt",
    "iso:country":"CA",
    "sg:address":"64 Guided Crt",
    "sg:city":"Etobicoke",
    "sg:classifiers":[
        {
            "category":"Freight",
            "type":"Transportation"
        }
    ],
    "sg:phone":"+1 416 740 5660",
    "sg:postcode":"M9V 4K6",
    "sg:province":"ON",
    "sg:tags":[
        "trucking"
    ],
    "wof:name":"Lansing Transport Svc Inc",
    "wof:placetype":"venue"
},
  "geometry": {"coordinates":[-79.60887908940001,43.7539291382],"type":"Point"}
}