{
  "type": "Feature",
  "properties": {
    "iso:country":"CA",
    "sg:address":"70 Homan St",
    "sg:city":"London",
    "sg:classifiers":[
        {
            "category":"Building & Trades",
            "subcategory":"Plumbing",
            "type":"Services"
        }
    ],
    "sg:phone":"+1 519 432 9449",
    "sg:postcode":"N5Z 1A8",
    "sg:province":"ON",
    "sg:tags":[
        "furnace",
        "cleaning"
    ],
    "wof:name":"Action Clean Air Svc Inc",
    "wof:placetype":"venue"
},
  "geometry": {"coordinates":[-81.207359314,42.977394104],"type":"Point"}
}