{
  "type": "Feature",
  "properties": {
    "addr:full":"379 Somerset St Saint John NB E2K 2Y5",
    "addr:housenumber":"379",
    "addr:postcode":"e2k 2y5",
    "addr:street":"Somerset St",
    "iso:country":"CA",
    "sg:address":"379 Somerset St",
    "sg:city":"Saint John",
    "sg:classifiers":[
        {
            "category":"Health Services",
            "subcategory":"Clinic",
            "type":"Services"
        }
    ],
    "sg:phone":"+1 506 693 3330",
    "sg:postcode":"E2K 2Y5",
    "sg:province":"NB",
    "sg:tags":[
        "wheel",
        "home",
        "chair",
        "lift",
        "ramp"
    ],
    "wof:name":"Medichair/Aml",
    "wof:placetype":"venue"
},
  "geometry": {"coordinates":[-66.07795,45.286415],"type":"Point"}
}