{
  "type": "Feature",
  "properties": {
    "addr:full":"40 Jubilee Ave E Timmins ON P4N 5W3",
    "addr:housenumber":"40",
    "addr:postcode":"p4n 5w3",
    "addr:street":"Jubilee Ave E",
    "iso:country":"CA",
    "sg:address":"40 Jubilee Ave E",
    "sg:city":"Timmins",
    "sg:classifiers":[
        {
            "category":"Real Estate",
            "subcategory":"Real Estate Operator",
            "type":"Services"
        }
    ],
    "sg:phone":"+1 705 267 4000",
    "sg:postcode":"P4N 5W3",
    "sg:province":"ON",
    "sg:tags":[
        "apartment"
    ],
    "wof:name":"Jubilee Apartments",
    "wof:placetype":"venue"
},
  "geometry": {"coordinates":[-81.33427399999999,48.487064],"type":"Point"}
}