{
  "type": "Feature",
  "properties": {
    "addr:full":"37 Woodyatt Dr Brantford ON N3R 7K3",
    "addr:housenumber":"37",
    "addr:postcode":"n3r 7k3",
    "addr:street":"Woodyatt Dr",
    "iso:country":"CA",
    "sg:address":"37 Woodyatt Dr",
    "sg:city":"Brantford",
    "sg:classifiers":[
        {
            "category":"Manufacturing",
            "subcategory":"Toys & Sporting Goods",
            "type":"Manufacturing & Wholesale Goods"
        }
    ],
    "sg:phone":"+1 519 770 4621",
    "sg:postcode":"N3R 7K3",
    "sg:province":"ON",
    "sg:tags":[
        "bingo",
        "game",
        "supply"
    ],
    "wof:name":"Arrow Games Inc",
    "wof:placetype":"venue"
},
  "geometry": {"coordinates":[-80.2375411987,43.1723747253],"type":"Point"}
}