{
  "type": "Feature",
  "properties": {
    "addr:full":"8508 Boul Lacordaire Saint-Leonard QC H1R 2A5",
    "addr:housenumber":"8508",
    "addr:postcode":"h1r 2a5",
    "addr:street":"Boul Lacordaire",
    "iso:country":"CA",
    "sg:address":"8508 Boul Lacordaire",
    "sg:city":"Saint-Leonard",
    "sg:classifiers":[
        {
            "category":"Retail",
            "subcategory":"Laundry & Dry Cleaning",
            "type":"Services"
        }
    ],
    "sg:phone":"+1 514 323 6841",
    "sg:postcode":"H1R 2A5",
    "sg:province":"QC",
    "sg:tags":[
        "cleaners"
    ],
    "wof:name":"Nettoyeur St-Leonard Ltee",
    "wof:placetype":"venue"
},
  "geometry": {"coordinates":[-73.59794599999999,45.588264],"type":"Point"}
}