{
  "type": "Feature",
  "properties": {
    "addr:full":"Beaupre QC G0A 1E0",
    "addr:postcode":"g0a 1e0",
    "addr:street":"Beaupre",
    "iso:country":"CA",
    "sg:city":"Beaupre",
    "sg:classifiers":[
        {
            "category":"Restaurant",
            "type":"Food & Drink"
        }
    ],
    "sg:phone":"+1 418 827 6668",
    "sg:postcode":"G0A 1E0",
    "sg:province":"QC",
    "wof:name":"Resto-Bar Le St-Bernard",
    "wof:placetype":"venue"
},
  "geometry": {"coordinates":[-70.894447,47.047989],"type":"Point"}
}