{
  "type": "Feature",
  "properties": {
    "iso:country":"CA",
    "sg:address":"3302 Ch Des Chutes",
    "sg:city":"LA Baie",
    "sg:classifiers":[
        {
            "category":"Building & Trades",
            "subcategory":"Construction",
            "type":"Services"
        }
    ],
    "sg:phone":"+1 418 544 7725",
    "sg:postcode":"G7B 2Z6",
    "sg:province":"QC",
    "sg:tags":[
        "repairing",
        "remodeling",
        "contractor"
    ],
    "wof:name":"Renovations Gilles Inc",
    "wof:placetype":"venue"
},
  "geometry": {"coordinates":[-70.9085235596,48.3307952881],"type":"Point"}
}