{
  "type": "Feature",
  "properties": {
    "addr:full":"Brampton ON L6T 5A8",
    "addr:postcode":"l6t 5a8",
    "iso:country":"CA",
    "sg:city":"Brampton",
    "sg:classifiers":[
        {
            "category":"Education",
            "subcategory":"School",
            "type":"Public Place"
        }
    ],
    "sg:phone":"+1 905 799 9231",
    "sg:postcode":"L6T 5A8",
    "sg:province":"ON",
    "wof:name":"Islamic Private Board of Ed",
    "wof:placetype":"venue"
},
  "geometry": {"coordinates":[-79.6999969482,43.7349395752],"type":"Point"}
}