{
  "type": "Feature",
  "properties": {
    "addr:full":"1600 Railway St E North Vancouver BC V7J 1B5",
    "addr:housenumber":"1600",
    "addr:postcode":"v7j 1b5",
    "addr:street":"Railway St E",
    "iso:country":"CA",
    "sg:address":"1600 Railway St E",
    "sg:city":"North Vancouver",
    "sg:classifiers":[
        {
            "category":"Communications",
            "subcategory":"Film & Video Production",
            "type":"Services"
        }
    ],
    "sg:phone":"+1 604 980 8363",
    "sg:postcode":"V7J 1B5",
    "sg:province":"BC",
    "sg:tags":[
        "motion",
        "picture",
        "studio",
        "producer"
    ],
    "wof:name":"Aja Tan Enterprises Ltd",
    "wof:placetype":"venue"
},
  "geometry": {"coordinates":[-123.031265,49.303867],"type":"Point"}
}