{
  "type": "Feature",
  "properties": {
    "addr:full":"955 Av DE Bourgogne # 207 Sainte-Foy QC G1X 3E5",
    "addr:postcode":"g1x 3e5",
    "addr:street":"955 Av De Bourgogne # 207",
    "iso:country":"CA",
    "sg:address":"955 Av DE Bourgogne # 207",
    "sg:city":"Sainte-Foy",
    "sg:classifiers":[
        {
            "category":"Health Services",
            "subcategory":"Health Practitioner",
            "type":"Services"
        }
    ],
    "sg:phone":"+1 418 652 2383",
    "sg:postcode":"G1X 3E5",
    "sg:province":"QC",
    "sg:tags":[
        "speech",
        "therapy",
        "hearing"
    ],
    "wof:name":"Clinique D'Orthophonie Monique",
    "wof:placetype":"venue"
},
  "geometry": {"coordinates":[-71.3120727539,46.7671585083],"type":"Point"}
}