{
  "type": "Feature",
  "properties": {
    "addr:full":"26 Tangiers Rd North York ON M3J 2B2",
    "addr:housenumber":"26",
    "addr:postcode":"m3j 2b2",
    "addr:street":"Tangiers Rd",
    "iso:country":"CA",
    "sg:address":"26 Tangiers Rd",
    "sg:city":"North York",
    "sg:classifiers":[
        {
            "category":"Real Estate",
            "subcategory":"Real Estate Agent",
            "type":"Services"
        }
    ],
    "sg:phone":"+1 416 636 7265",
    "sg:postcode":"M3J 2B2",
    "sg:province":"ON",
    "sg:tags":[
        "management"
    ],
    "wof:name":"Gammond Investments Ltd",
    "wof:placetype":"venue"
},
  "geometry": {"coordinates":[-79.488091,43.762684],"type":"Point"}
}