{
  "type": "Feature",
  "properties": {
    "addr:full":"9483 152A St Surrey BC V3R 9B8",
    "addr:housenumber":"9483",
    "addr:postcode":"v3r 9b8",
    "addr:street":"152A St",
    "iso:country":"CA",
    "sg:address":"9483 152A St",
    "sg:city":"Surrey",
    "sg:classifiers":[
        {
            "category":"Professional",
            "subcategory":"Employment Agencies",
            "type":"Services"
        }
    ],
    "sg:phone":"+1 604 930 9386",
    "sg:postcode":"V3R 9B8",
    "sg:province":"BC",
    "sg:tags":[
        "opportunity",
        "help"
    ],
    "wof:name":"Jacobsen Secretarial Svc",
    "wof:placetype":"venue"
},
  "geometry": {"coordinates":[-122.830215454,49.105178833],"type":"Point"}
}