{
  "type": "Feature",
  "properties": {
    "addr:full":"1650 Rue Sir-Louis-Jette Quebec QC G1S 2W3",
    "addr:housenumber":"1650",
    "addr:postcode":"g1s 2w3",
    "addr:street":"Rue Sir-Louis-Jette",
    "iso:country":"CA",
    "sg:address":"1650 Rue Sir-Louis-Jette",
    "sg:city":"Quebec",
    "sg:classifiers":[
        {
            "category":"Government",
            "subcategory":"Office",
            "type":"Public Place"
        }
    ],
    "sg:phone":"+1 418 643 5430",
    "sg:postcode":"G1S 2W3",
    "sg:province":"QC",
    "wof:name":"Quebec Transports",
    "wof:placetype":"venue"
},
  "geometry": {"coordinates":[-71.266541,46.794388],"type":"Point"}
}