{
  "type": "Feature",
  "properties": {
    "addr:full":"Campbell River BC V9W 2E4",
    "addr:postcode":"v9w 2e4",
    "iso:country":"CA",
    "sg:city":"Campbell River",
    "sg:classifiers":[
        {
            "category":"Farming",
            "subcategory":"Fish & Marine Products",
            "type":"Manufacturing & Wholesale Goods"
        }
    ],
    "sg:phone":"+1 250 286 1549",
    "sg:postcode":"V9W 2E4",
    "sg:province":"BC",
    "sg:tags":[
        "fisherman"
    ],
    "wof:name":"Laichkwiltach Enterprises",
    "wof:placetype":"venue"
},
  "geometry": {"coordinates":[-125.257751,50.033524],"type":"Point"}
}