{
  "type": "Feature",
  "properties": {
    "addr:full":"521 Victoria Park Ave Scarborough ON M4C 5H1",
    "addr:housenumber":"521",
    "addr:postcode":"m4c 5h1",
    "addr:street":"Victoria Park Ave",
    "iso:country":"CA",
    "sg:address":"521 Victoria Park Ave",
    "sg:city":"Scarborough",
    "sg:classifiers":[
        {
            "category":"Health Services",
            "subcategory":"Doctor",
            "type":"Services"
        }
    ],
    "sg:phone":"+1 416 690 8043",
    "sg:postcode":"M4C 5H1",
    "sg:province":"ON",
    "sg:tags":[
        "physician",
        "surgeon"
    ],
    "wof:name":"Lombardi, L P MD",
    "wof:placetype":"venue"
},
  "geometry": {"coordinates":[-79.287659,43.690029],"type":"Point"}
}