{
  "type": "Feature",
  "properties": {
    "addr:full":"Port Coquitlam BC V3C 2A1",
    "addr:postcode":"v3c 2a1",
    "iso:country":"CA",
    "sg:city":"Port Coquitlam",
    "sg:classifiers":[
        {
            "category":"Insurance",
            "subcategory":"Hazard Insurance",
            "type":"Services"
        }
    ],
    "sg:phone":"+1 604 945 7607",
    "sg:postcode":"V3C 2A1",
    "sg:province":"BC",
    "sg:tags":[
        "profit",
        "sharing",
        "pension",
        "plan"
    ],
    "wof:name":"Prudent Benefits Admin Society",
    "wof:placetype":"venue"
},
  "geometry": {"coordinates":[-122.783348084,49.261680603],"type":"Point"}
}