{
  "type": "Feature",
  "properties": {
    "addr:full":"4455 Juneau St Burnaby BC V5C 4C4",
    "addr:housenumber":"4455",
    "addr:postcode":"v5c 4c4",
    "addr:street":"Juneau St",
    "iso:country":"CA",
    "sg:address":"4455 Juneau St",
    "sg:city":"Burnaby",
    "sg:classifiers":[
        {
            "category":"Manufacturing",
            "subcategory":"Tools & Machinery",
            "type":"Manufacturing & Wholesale Goods"
        }
    ],
    "sg:phone":"+1 604 677 8979",
    "sg:postcode":"V5C 4C4",
    "sg:province":"BC",
    "sg:tags":[
        "equipment",
        "electric"
    ],
    "wof:name":"F D Bolton Ltd",
    "wof:placetype":"venue"
},
  "geometry": {"coordinates":[-123.00451700000001,49.263763],"type":"Point"}
}