{
  "type": "Feature",
  "properties": {
    "addr:full":"PO Box 371 STN Ganges Salt Spring Island BC V8K 2W1",
    "addr:housenumber":"po",
    "addr:postcode":"v8k 2w1",
    "addr:street":"Box 371 Stn Ganges",
    "iso:country":"CA",
    "sg:address":"PO Box 371 STN Ganges",
    "sg:city":"Salt Spring Island",
    "sg:classifiers":[
        {
            "category":"Building & Trades",
            "subcategory":"Construction",
            "type":"Services"
        }
    ],
    "sg:phone":"+1 250 537 1056",
    "sg:postcode":"V8K 2W1",
    "sg:province":"BC",
    "sg:tags":[
        "excavating",
        "contractor"
    ],
    "wof:name":"Gulf Islands Trucking & Excvt",
    "wof:placetype":"venue"
},
  "geometry": {"coordinates":[-123.445702,48.781757],"type":"Point"}
}