{
  "type": "Feature",
  "properties": {
    "addr:full":"Melfort SK S0E 1A0",
    "addr:postcode":"s0e 1a0",
    "addr:street":"Melfort",
    "iso:country":"CA",
    "sg:city":"Melfort",
    "sg:classifiers":[
        {
            "category":"Shopping",
            "subcategory":"Books",
            "type":"Retail Goods"
        }
    ],
    "sg:phone":"+1 306 752 3114",
    "sg:postcode":"S0E 1A0",
    "sg:province":"SK",
    "sg:tags":[
        "dealer"
    ],
    "wof:name":"Bookstop",
    "wof:placetype":"venue"
},
  "geometry": {"coordinates":[-104.608940124,52.8630905151],"type":"Point"}
}