{
  "type": "Feature",
  "properties": {
    "addr:full":"406 Steele St Whitehorse YT Y1A 2C8",
    "addr:housenumber":"406",
    "addr:postcode":"y1a 2c8",
    "addr:street":"Steele St",
    "iso:country":"CA",
    "sg:address":"406 Steele St",
    "sg:city":"Whitehorse",
    "sg:classifiers":[
        {
            "category":"Organizations",
            "subcategory":"Religious Organization",
            "type":"Services"
        }
    ],
    "sg:phone":"+1 867 667 2437",
    "sg:postcode":"Y1A 2C8",
    "sg:province":"YT",
    "sg:tags":[
        "church"
    ],
    "wof:name":"Sacred Heart Cathedral",
    "wof:placetype":"venue"
},
  "geometry": {"coordinates":[-135.05722,60.719807],"type":"Point"}
}