{
  "type": "Feature",
  "properties": {
    "addr:full":"1355 3E Ave Quebec QC G1L 2Y1",
    "addr:housenumber":"1355",
    "addr:postcode":"g1l 2y1",
    "addr:street":"3E Ave",
    "iso:country":"CA",
    "sg:address":"1355 3E Ave",
    "sg:city":"Quebec",
    "sg:classifiers":[
        {
            "category":"Recreation",
            "type":"Entertainment"
        }
    ],
    "sg:phone":"+1 418 525 9642",
    "sg:postcode":"G1L 2Y1",
    "sg:province":"QC",
    "sg:tags":[
        "instruction",
        "yoga"
    ],
    "wof:name":"Centre DE Yoga Quebec",
    "wof:placetype":"venue"
},
  "geometry": {"coordinates":[-71.232094,46.828701],"type":"Point"}
}