{
  "type": "Feature",
  "properties": {
    "addr:full":"771 2E Av Louiseville QC J5V 2L4",
    "addr:housenumber":"771",
    "addr:postcode":"j5v 2l4",
    "addr:street":"2E Av",
    "iso:country":"CA",
    "sg:address":"771 2E Av",
    "sg:city":"Louiseville",
    "sg:classifiers":[
        {
            "category":"Farming",
            "subcategory":"Farm",
            "type":"Manufacturing & Wholesale Goods"
        }
    ],
    "sg:phone":"+1 819 228 5393",
    "sg:postcode":"J5V 2L4",
    "sg:province":"QC",
    "wof:name":"Jardins Ricard Inc",
    "wof:placetype":"venue"
},
  "geometry": {"coordinates":[-72.922325,46.242565],"type":"Point"}
}