{
  "type": "Feature",
  "properties": {
    "iso:country":"CA",
    "sg:city":"Hillsburgh",
    "sg:classifiers":[
        {
            "category":"Retail",
            "subcategory":"Veterinary Services",
            "type":"Services"
        }
    ],
    "sg:phone":"+1 519 855 6439",
    "sg:postcode":"N0B 1Z0",
    "sg:province":"ON",
    "sg:tags":[
        "veterinarian"
    ],
    "wof:name":"Graham Animal Hospital",
    "wof:placetype":"venue"
},
  "geometry": {"coordinates":[-80.1437911987,43.7900009155],"type":"Point"}
}