{
  "type": "Feature",
  "properties": {
    "iso:country":"CA",
    "sg:address":"1310 St James St",
    "sg:city":"Winnipeg",
    "sg:classifiers":[
        {
            "category":"Retail",
            "subcategory":"Auto Repair",
            "type":"Services"
        }
    ],
    "sg:phone":"+1 204 783 5407",
    "sg:postcode":"R3H 0L1",
    "sg:province":"MB",
    "sg:tags":[
        "body",
        "automobile",
        "painting"
    ],
    "wof:name":"Mac Donald Auto Body Ltd",
    "wof:placetype":"venue"
},
  "geometry": {"coordinates":[-97.200088501,49.9030303955],"type":"Point"}
}