{
  "type": "Feature",
  "properties": {
    "iso:country":"CA",
    "sg:address":"1050 Foundry St SE",
    "sg:city":"Medicine Hat",
    "sg:classifiers":[
        {
            "category":"Building & Trades",
            "subcategory":"Construction",
            "type":"Services"
        }
    ],
    "sg:phone":"+1 403 526 4649",
    "sg:postcode":"T1A 1X5",
    "sg:province":"AB",
    "sg:tags":[
        "painter"
    ],
    "wof:name":"Martin's Painting & Decorating",
    "wof:placetype":"venue"
},
  "geometry": {"coordinates":[-110.660842895,50.029750824],"type":"Point"}
}