{
  "type": "Feature",
  "properties": {
    "addr:full":"Toronto ON M5J 2R8",
    "addr:postcode":"m5j 2r8",
    "iso:country":"CA",
    "sg:city":"Toronto",
    "sg:classifiers":[
        {
            "category":"Professional",
            "subcategory":"Testing Lab",
            "type":"Services"
        }
    ],
    "sg:phone":"+1 416 362 8743",
    "sg:postcode":"M5J 2R8",
    "sg:province":"ON",
    "sg:tags":[
        "consultant",
        "forensic"
    ],
    "wof:name":"M G Forensic Accounting",
    "wof:placetype":"venue"
},
  "geometry": {"coordinates":[-79.377281189,43.6414833069],"type":"Point"}
}