{
  "type": "Feature",
  "properties": {
    "addr:full":"10581 Hermosa Dr Delta BC V4C 6S8",
    "addr:housenumber":"10581",
    "addr:postcode":"v4c 6s8",
    "addr:street":"Hermosa Dr",
    "iso:country":"CA",
    "sg:address":"10581 Hermosa Dr",
    "sg:city":"Delta",
    "sg:classifiers":[
        {
            "category":"Building & Trades",
            "subcategory":"Construction",
            "type":"Services"
        }
    ],
    "sg:phone":"+1 604 591 5590",
    "sg:postcode":"V4C 6S8",
    "sg:province":"BC",
    "sg:tags":[
        "resurfacing",
        "refinishing",
        "floor"
    ],
    "wof:name":"Mc Master Hardwood Floors Ltd",
    "wof:placetype":"venue"
},
  "geometry": {"coordinates":[-122.92855072,49.1514625549],"type":"Point"}
}