{
  "type": "Feature",
  "properties": {
    "addr:full":"1831 Shawson Dr Mississauga ON L4W 1T9",
    "addr:housenumber":"1831",
    "addr:postcode":"l4w 1t9",
    "addr:street":"Shawson Dr",
    "iso:country":"CA",
    "sg:address":"1831 Shawson Dr",
    "sg:city":"Mississauga",
    "sg:classifiers":[
        {
            "category":"Wholesale",
            "subcategory":"Machinery & Supplies",
            "type":"Manufacturing & Wholesale Goods"
        }
    ],
    "sg:phone":"+1 905 670 8822",
    "sg:postcode":"L4W 1T9",
    "sg:province":"ON",
    "sg:tags":[
        "crane"
    ],
    "wof:name":"Cooper's Crane Rental Ltd",
    "wof:placetype":"venue"
},
  "geometry": {"coordinates":[-79.63679504389999,43.6585769653],"type":"Point"}
}