{
  "type": "Feature",
  "properties": {
    "addr:full":"Richmond BC V6X 2R4",
    "addr:postcode":"v6x 2r4",
    "iso:country":"CA",
    "sg:city":"Richmond",
    "sg:classifiers":[
        {
            "category":"Education",
            "subcategory":"Dance Studio",
            "type":"Public Place"
        }
    ],
    "sg:phone":"+1 604 270 9272",
    "sg:postcode":"V6X 2R4",
    "sg:province":"BC",
    "sg:tags":[
        "instruction",
        "dancing"
    ],
    "wof:name":"Danceability",
    "wof:placetype":"venue"
},
  "geometry": {"coordinates":[-123.096024,49.192684],"type":"Point"}
}