{
  "type": "Feature",
  "properties": {
    "addr:full":"2691 Hastings St E Vancouver BC V5K 1Z5",
    "addr:housenumber":"2691",
    "addr:postcode":"v5k 1z5",
    "addr:street":"Hastings St E",
    "iso:country":"CA",
    "sg:address":"2691 Hastings St E",
    "sg:city":"Vancouver",
    "sg:classifiers":[
        {
            "category":"Retail",
            "subcategory":"Laundry & Dry Cleaning",
            "type":"Services"
        }
    ],
    "sg:phone":"+1 604 255 9366",
    "sg:postcode":"V5K 1Z5",
    "sg:province":"BC",
    "sg:tags":[
        "cleaners"
    ],
    "wof:name":"Five Star Laundry & Dryclng",
    "wof:placetype":"venue"
},
  "geometry": {"coordinates":[-123.049706,49.281269],"type":"Point"}
}