{
  "type": "Feature",
  "properties": {
    "addr:full":"PO Box 5738 STN L Edmonton AB T6C 4G2",
    "addr:housenumber":"po",
    "addr:postcode":"t6c 4g2",
    "addr:street":"Box 5738 Stn L Edmonton",
    "iso:country":"CA",
    "sg:address":"PO Box 5738 STN L",
    "sg:city":"Edmonton",
    "sg:classifiers":[
        {
            "category":"Organizations",
            "subcategory":"Professional Association",
            "type":"Services"
        }
    ],
    "sg:phone":"+1 780 455 3319",
    "sg:postcode":"T6C 4G2",
    "sg:province":"AB",
    "wof:name":"Crohn's & Colitis Foundation",
    "wof:placetype":"venue"
},
  "geometry": {"coordinates":[-113.490371704,53.5462188721],"type":"Point"}
}