{
  "type": "Feature",
  "properties": {
    "addr:full":"Sainte-Therese QC J7E 2A6",
    "addr:postcode":"j7e 2a6",
    "addr:street":"Sainte-Therese",
    "iso:country":"CA",
    "sg:city":"Sainte-Therese",
    "sg:classifiers":[
        {
            "category":"Restaurant",
            "type":"Food & Drink"
        }
    ],
    "sg:phone":"+1 450 430 4111",
    "sg:postcode":"J7E 2A6",
    "sg:province":"QC",
    "wof:name":"Anna Pizzeria Restaurant",
    "wof:placetype":"venue"
},
  "geometry": {"coordinates":[-73.8498306274,45.6416625977],"type":"Point"}
}