{
  "type": "Feature",
  "properties": {
    "addr:full":"60 Caledon Ave Hamilton ON L9C 3C8",
    "addr:housenumber":"60",
    "addr:postcode":"l9c 3c8",
    "addr:street":"Caledon Ave",
    "iso:country":"CA",
    "sg:address":"60 Caledon Ave",
    "sg:city":"Hamilton",
    "sg:classifiers":[
        {
            "category":"Education",
            "subcategory":"School",
            "type":"Public Place"
        }
    ],
    "sg:phone":"+1 905 388 2521",
    "sg:postcode":"L9C 3C8",
    "sg:province":"ON",
    "wof:name":"Mountain Secondary School",
    "wof:placetype":"venue"
},
  "geometry": {"coordinates":[-79.884468,43.226669],"type":"Point"}
}