{
  "type": "Feature",
  "properties": {
    "iso:country":"CA",
    "sg:address":"27 Kilmarnock Bay",
    "sg:city":"Winnipeg",
    "sg:classifiers":[
        {
            "category":"Wholesale",
            "subcategory":"Durable Goods & Equipment",
            "type":"Manufacturing & Wholesale Goods"
        }
    ],
    "sg:phone":"+1 204 956 0148",
    "sg:postcode":"R2M 4R7",
    "sg:province":"MB",
    "sg:tags":[
        "representative",
        "manufacturer"
    ],
    "wof:name":"Mack Smith Agencies Ltd",
    "wof:placetype":"venue"
},
  "geometry": {"coordinates":[-97.132843,49.828541],"type":"Point"}
}