{
  "type": "Feature",
  "properties": {
    "addr:full":"347 Hargrave St Winnipeg MB R3B 2J7",
    "addr:housenumber":"347",
    "addr:postcode":"r3b 2j7",
    "addr:street":"Hargrave St",
    "iso:country":"CA",
    "sg:address":"347 Hargrave St",
    "sg:city":"Winnipeg",
    "sg:classifiers":[
        {
            "category":"Personal",
            "subcategory":"Beauty Salon",
            "type":"Services"
        }
    ],
    "sg:phone":"+1 204 949 1775",
    "sg:postcode":"R3B 2J7",
    "sg:province":"MB",
    "wof:name":"Coiffure 2000 Hair Design",
    "wof:placetype":"venue"
},
  "geometry": {"coordinates":[-97.1452255249,49.8945999146],"type":"Point"}
}