{
  "type": "Feature",
  "properties": {
    "addr:full":"1020 Laut Ave Crossfield AB T0M 0S0",
    "addr:housenumber":"1020",
    "addr:postcode":"t0m 0s0",
    "addr:street":"Laut Ave",
    "iso:country":"CA",
    "sg:address":"1020 Laut Ave",
    "sg:city":"Crossfield",
    "sg:classifiers":[
        {
            "category":"Wholesale",
            "subcategory":"Chemicals & Plastics",
            "type":"Manufacturing & Wholesale Goods"
        }
    ],
    "sg:phone":"+1 403 946 4808",
    "sg:postcode":"T0M 0S0",
    "sg:province":"AB",
    "sg:tags":[
        "mold",
        "maker"
    ],
    "wof:name":"Sms Plastics",
    "wof:placetype":"venue"
},
  "geometry": {"coordinates":[-114.03304300000001,51.422623],"type":"Point"}
}