{
  "type": "Feature",
  "properties": {
    "addr:full":"60 Ch DE LA Traverse Saint-Paul NB E4T 3H7",
    "addr:housenumber":"60",
    "addr:postcode":"e4t 3h7",
    "addr:street":"Ch De La Traverse",
    "iso:country":"CA",
    "sg:address":"60 Ch DE LA Traverse",
    "sg:city":"Saint-Paul",
    "sg:classifiers":[
        {
            "category":"Food & Beverages",
            "subcategory":"Groceries & Convenience Stores",
            "type":"Retail Goods"
        }
    ],
    "sg:phone":"+1 506 955 3300",
    "sg:postcode":"E4T 3H7",
    "sg:province":"NB",
    "sg:tags":[
        "grocer"
    ],
    "wof:name":"CO-Operative DE St Paul DE",
    "wof:placetype":"venue"
},
  "geometry": {"coordinates":[-64.98497,46.351055],"type":"Point"}
}