{
  "type": "Feature",
  "properties": {
    "addr:full":"Victoria BC V8Z 1B5",
    "addr:postcode":"v8z 1b5",
    "iso:country":"CA",
    "sg:city":"Victoria",
    "sg:classifiers":[
        {
            "category":"Building & Trades",
            "subcategory":"Construction",
            "type":"Services"
        }
    ],
    "sg:phone":"+1 250 475 3569",
    "sg:postcode":"V8Z 1B5",
    "sg:province":"BC",
    "sg:tags":[
        "repairing",
        "bathroom",
        "remodeling",
        "contractor"
    ],
    "wof:name":"Island Builders Ltd",
    "wof:placetype":"venue"
},
  "geometry": {"coordinates":[-123.37492399999999,48.446857],"type":"Point"}
}