{
  "type": "Feature",
  "properties": {
    "iso:country":"CA",
    "sg:address":"134 Welton St",
    "sg:city":"Sydney",
    "sg:classifiers":[
        {
            "category":"Professional",
            "subcategory":"Computer Services",
            "type":"Services"
        }
    ],
    "sg:phone":"+1 902 564 8700",
    "sg:postcode":"B1P 5R8",
    "sg:province":"NS",
    "sg:tags":[
        "repair",
        "dealer",
        "equipment"
    ],
    "wof:name":"Alliance Computer Systems",
    "wof:placetype":"venue"
},
  "geometry": {"coordinates":[-60.1700935364,46.1424064636],"type":"Point"}
}