{
  "type": "Feature",
  "properties": {
    "addr:full":"4605 Rue Dickson Montreal QC H1M 2R5",
    "addr:housenumber":"4605",
    "addr:postcode":"h1m 2r5",
    "addr:street":"Rue Dickson",
    "iso:country":"CA",
    "sg:address":"4605 Rue Dickson",
    "sg:city":"Montreal",
    "sg:classifiers":[
        {
            "category":"Health Services",
            "subcategory":"Chiropractor",
            "type":"Services"
        }
    ],
    "sg:phone":"+1 514 254 3975",
    "sg:postcode":"H1M 2R5",
    "sg:province":"QC",
    "wof:name":"Centre Chiro-Sante D Gagnon",
    "wof:placetype":"venue"
},
  "geometry": {"coordinates":[-73.551071167,45.5743713379],"type":"Point"}
}