{
  "type": "Feature",
  "properties": {
    "addr:full":"24 Rue Pied-Des-Pentes Lac-Delage QC G0A 4P0",
    "addr:housenumber":"24",
    "addr:postcode":"g0a 4p0",
    "addr:street":"Rue Pied-Des-Pentes",
    "iso:country":"CA",
    "sg:address":"24 Rue Pied-Des-Pentes",
    "sg:city":"Lac-Delage",
    "sg:classifiers":[
        {
            "category":"Government",
            "subcategory":"Office",
            "type":"Public Place"
        }
    ],
    "sg:phone":"+1 418 848 2417",
    "sg:postcode":"G0A 4P0",
    "sg:province":"QC",
    "sg:tags":[
        "village"
    ],
    "wof:name":"Lac Delage Secretariat",
    "wof:placetype":"venue"
},
  "geometry": {"coordinates":[-71.4046783447,46.9710083008],"type":"Point"}
}