{
  "type": "Feature",
  "properties": {
    "addr:full":"807 Arrow Rd North York ON M9M 2L4",
    "addr:housenumber":"807",
    "addr:postcode":"m9m 2l4",
    "addr:street":"Arrow Rd",
    "iso:country":"CA",
    "sg:address":"807 Arrow Rd",
    "sg:city":"North York",
    "sg:classifiers":[
        {
            "category":"Wholesale",
            "subcategory":"Chemicals & Plastics",
            "type":"Manufacturing & Wholesale Goods"
        }
    ],
    "sg:phone":"+1 416 746 3143",
    "sg:postcode":"M9M 2L4",
    "sg:province":"ON",
    "wof:name":"Superchem Industries",
    "wof:placetype":"venue"
},
  "geometry": {"coordinates":[-79.5310745239,43.7483558655],"type":"Point"}
}