{
  "type": "Feature",
  "properties": {
    "addr:full":"Montreal-Nord QC H1G 2T3",
    "addr:postcode":"h1g 2t3",
    "iso:country":"CA",
    "sg:city":"Montreal-Nord",
    "sg:classifiers":[
        {
            "category":"Retail",
            "subcategory":"Laundry & Dry Cleaning",
            "type":"Services"
        }
    ],
    "sg:phone":"+1 514 326 0303",
    "sg:postcode":"H1G 2T3",
    "sg:province":"QC",
    "sg:tags":[
        "cleaners"
    ],
    "wof:name":"Nettoyeur Savoy 2",
    "wof:placetype":"venue"
},
  "geometry": {"coordinates":[-73.621376,45.605965],"type":"Point"}
}