{
  "type": "Feature",
  "properties": {
    "iso:country":"CA",
    "sg:address":"111 Ontario St",
    "sg:city":"Port Hope",
    "sg:classifiers":[
        {
            "category":"Professional",
            "subcategory":"Lawyer & Legal Services",
            "type":"Services"
        }
    ],
    "sg:phone":"+1 905 885 8118",
    "sg:postcode":"L1A 3V9",
    "sg:province":"ON",
    "sg:tags":[
        "attorney"
    ],
    "wof:name":"Day, Wilfred A",
    "wof:placetype":"venue"
},
  "geometry": {"coordinates":[-78.29246521,43.9567718506],"type":"Point"}
}