{
  "type": "Feature",
  "properties": {
    "addr:full":"1088 Alberni St Vancouver BC V6E 1A3",
    "addr:housenumber":"1088",
    "addr:postcode":"v6e 1a3",
    "addr:street":"Alberni St",
    "iso:country":"CA",
    "sg:address":"1088 Alberni St",
    "sg:city":"Vancouver",
    "sg:classifiers":[
        {
            "category":"Personal",
            "subcategory":"Beauty Salon",
            "type":"Services"
        }
    ],
    "sg:phone":"+1 604 608 4247",
    "sg:postcode":"V6E 1A3",
    "sg:province":"BC",
    "wof:name":"Toni & Guy Robson Street",
    "wof:placetype":"venue"
},
  "geometry": {"coordinates":[-123.123634,49.284973],"type":"Point"}
}