{
  "type": "Feature",
  "properties": {
    "addr:full":"1545 Route 525 Sainte-Marie-DE-Kent NB E4S 2H2",
    "addr:housenumber":"1545",
    "addr:postcode":"e4s 2h2",
    "addr:street":"Route 525",
    "iso:country":"CA",
    "sg:address":"1545 Route 525",
    "sg:city":"Sainte-Marie-DE-Kent",
    "sg:classifiers":[
        {
            "category":"Education",
            "subcategory":"School",
            "type":"Public Place"
        }
    ],
    "sg:phone":"+1 506 955 6000",
    "sg:postcode":"E4S 2H2",
    "sg:province":"NB",
    "wof:name":"Mont-Carmel Ecole",
    "wof:placetype":"venue"
},
  "geometry": {"coordinates":[-67.6262435913,46.530418396],"type":"Point"}
}