{
  "type": "Feature",
  "properties": {
    "addr:full":"Brampton ON L6T 5A1",
    "addr:postcode":"l6t 5a1",
    "iso:country":"CA",
    "sg:city":"Brampton",
    "sg:classifiers":[
        {
            "category":"Manufacturing",
            "subcategory":"Tools & Machinery",
            "type":"Manufacturing & Wholesale Goods"
        }
    ],
    "sg:phone":"+1 905 458 4003",
    "sg:postcode":"L6T 5A1",
    "sg:province":"ON",
    "sg:tags":[
        "machine",
        "shop"
    ],
    "wof:name":"Canadian Precix",
    "wof:placetype":"venue"
},
  "geometry": {"coordinates":[-79.67971799999999,43.714378],"type":"Point"}
}