{
  "type": "Feature",
  "properties": {
    "addr:full":"Saskatoon SK S7M 0S2",
    "addr:postcode":"s7m 0s2",
    "iso:country":"CA",
    "sg:city":"Saskatoon",
    "sg:classifiers":[
        {
            "category":"Education",
            "subcategory":"School",
            "type":"Public Place"
        }
    ],
    "sg:phone":"+1 306 477 4929",
    "sg:postcode":"S7M 0S2",
    "sg:province":"SK",
    "sg:tags":[
        "salon",
        "beauty"
    ],
    "wof:name":"Bellissima Esthetiques",
    "wof:placetype":"venue"
},
  "geometry": {"coordinates":[-106.684524536,52.1291427612],"type":"Point"}
}