{
  "type": "Feature",
  "properties": {
    "iso:country":"CA",
    "sg:city":"Saint-Gabriel-DE-Valcartier",
    "sg:classifiers":[
        {
            "category":"Travel",
            "subcategory":"Campground",
            "type":"Entertainment"
        }
    ],
    "sg:phone":"+1 418 844 2713",
    "sg:postcode":"G0A 4S0",
    "sg:province":"QC",
    "sg:tags":[
        "riding",
        "camp",
        "academy"
    ],
    "wof:name":"Club Equestre DE Quebec",
    "wof:placetype":"venue"
},
  "geometry": {"coordinates":[-71.4897232056,46.9613494873],"type":"Point"}
}