{
  "type": "Feature",
  "properties": {
    "iso:country":"CA",
    "sg:address":"1420 Av Laurier E",
    "sg:city":"Montreal",
    "sg:classifiers":[
        {
            "category":"Food & Beverages",
            "subcategory":"Groceries & Convenience Stores",
            "type":"Retail Goods"
        }
    ],
    "sg:phone":"+1 514 523 6496",
    "sg:postcode":"H2J 1H5",
    "sg:province":"QC",
    "sg:tags":[
        "grocer"
    ],
    "wof:name":"Depanneur Laurier",
    "wof:placetype":"venue"
},
  "geometry": {"coordinates":[-73.583275,45.533733],"type":"Point"}
}