{
  "type": "Feature",
  "properties": {
    "addr:full":"363 Rideau St Ottawa ON K1N 5Y6",
    "addr:housenumber":"363",
    "addr:postcode":"k1n 5y6",
    "addr:street":"Rideau St",
    "iso:country":"CA",
    "sg:address":"363 Rideau St",
    "sg:city":"Ottawa",
    "sg:classifiers":[
        {
            "category":"Shopping",
            "subcategory":"Pharmacy",
            "type":"Retail Goods"
        }
    ],
    "sg:phone":"+1 613 789 3346",
    "sg:postcode":"K1N 5Y6",
    "sg:province":"ON",
    "wof:name":"Drug Store Pharmacy",
    "wof:placetype":"venue"
},
  "geometry": {"coordinates":[-75.683418,45.429913],"type":"Point"}
}