{
  "type": "Feature",
  "properties": {
    "iso:country":"CA",
    "sg:address":"1029 Mountain Rd",
    "sg:city":"Moncton",
    "sg:classifiers":[
        {
            "category":"Restaurant",
            "type":"Food & Drink"
        }
    ],
    "sg:phone":"+1 506 384 1202",
    "sg:postcode":"E1C 2S7",
    "sg:province":"NB",
    "wof:name":"Arby's",
    "wof:placetype":"venue"
},
  "geometry": {"coordinates":[-64.81809997560001,46.1039581299],"type":"Point"}
}