{
  "type": "Feature",
  "properties": {
    "addr:full":"175 Rue Du Progres Masson-Angers QC J8M 1T2",
    "addr:housenumber":"175",
    "addr:postcode":"j8m 1t2",
    "addr:street":"Rue Du Progres",
    "iso:country":"CA",
    "sg:address":"175 Rue Du Progres",
    "sg:city":"Masson-Angers",
    "sg:classifiers":[
        {
            "category":"Bars & Pubs",
            "type":"Food & Drink"
        }
    ],
    "sg:phone":"+1 819 986 2010",
    "sg:postcode":"J8M 1T2",
    "sg:province":"QC",
    "sg:tags":[
        "lounge",
        "cocktail"
    ],
    "wof:name":"Bar Salon Chez Tom",
    "wof:placetype":"venue"
},
  "geometry": {"coordinates":[-75.4928817749,45.5239143372],"type":"Point"}
}