{
  "type": "Feature",
  "properties": {
    "addr:full":"Sainte-Claire QC G0R 2V0",
    "addr:postcode":"g0r 2v0",
    "iso:country":"CA",
    "sg:city":"Sainte-Claire",
    "sg:classifiers":[
        {
            "category":"Wholesale",
            "subcategory":"Machinery & Supplies",
            "type":"Manufacturing & Wholesale Goods"
        }
    ],
    "sg:phone":"+1 418 883 4115",
    "sg:postcode":"G0R 2V0",
    "sg:province":"QC",
    "sg:tags":[
        "equipment",
        "mill"
    ],
    "wof:name":"Services Agricoles Aube Inc",
    "wof:placetype":"venue"
},
  "geometry": {"coordinates":[-73.81731414790001,45.4480247498],"type":"Point"}
}