{
  "type": "Feature",
  "properties": {
    "addr:full":"Spruce Grove AB T7Y 1G2",
    "addr:postcode":"t7y 1g2",
    "iso:country":"CA",
    "sg:city":"Spruce Grove",
    "sg:classifiers":[
        {
            "category":"Wholesale",
            "subcategory":"Machinery & Supplies",
            "type":"Manufacturing & Wholesale Goods"
        }
    ],
    "sg:phone":"+1 780 987 5319",
    "sg:postcode":"T7Y 1G2",
    "sg:province":"AB",
    "sg:tags":[
        "field",
        "oil",
        "equipment"
    ],
    "wof:name":"R K Supply",
    "wof:placetype":"venue"
},
  "geometry": {"coordinates":[-113.901855,53.544636],"type":"Point"}
}