{
  "type": "Feature",
  "properties": {
    "addr:full":"PO Box 150 Arviat NU X0C 0E0",
    "addr:housenumber":"po",
    "addr:postcode":"x0c 0e0",
    "addr:street":"Box 150",
    "iso:country":"CA",
    "sg:address":"PO Box 150",
    "sg:city":"Arviat",
    "sg:classifiers":[
        {
            "category":"Government",
            "subcategory":"Office",
            "type":"Public Place"
        }
    ],
    "sg:phone":"+1 867 857 2811",
    "sg:postcode":"X0C 0E0",
    "sg:province":"NU",
    "sg:tags":[
        "village"
    ],
    "wof:name":"N T Community Liaison Officer",
    "wof:placetype":"venue"
},
  "geometry": {"coordinates":[-94.0589981079,61.1097068787],"type":"Point"}
}