{
  "type": "Feature",
  "properties": {
    "addr:full":"1815 10 Ave SW Calgary AB T3C 0K2",
    "addr:housenumber":"1815",
    "addr:postcode":"t3c 0k2",
    "addr:street":"10 Ave Sw",
    "iso:country":"CA",
    "sg:address":"1815 10 Ave SW",
    "sg:city":"Calgary",
    "sg:classifiers":[
        {
            "category":"Wholesale",
            "subcategory":"Durable Goods & Equipment",
            "type":"Manufacturing & Wholesale Goods"
        }
    ],
    "sg:phone":"+1 403 262 7224",
    "sg:postcode":"T3C 0K2",
    "sg:province":"AB",
    "sg:tags":[
        "blueprinting",
        "architect",
        "supply"
    ],
    "wof:name":"Continental Imaging Products",
    "wof:placetype":"venue"
},
  "geometry": {"coordinates":[-114.10218,51.044281],"type":"Point"}
}