{
  "type": "Feature",
  "properties": {
    "addr:full":"31 Coleridge Cres NW Calgary AB T2K 1X8",
    "addr:housenumber":"31",
    "addr:postcode":"t2k 1x8",
    "addr:street":"Coleridge Cres Nw",
    "iso:country":"CA",
    "sg:address":"31 Coleridge Cres NW",
    "sg:city":"Calgary",
    "sg:classifiers":[
        {
            "category":"Real Estate",
            "subcategory":"Real Estate Agent",
            "type":"Services"
        }
    ],
    "sg:phone":"+1 403 220 0090",
    "sg:postcode":"T2K 1X8",
    "sg:province":"AB",
    "sg:tags":[
        "management"
    ],
    "wof:name":"Contempo Developments Ltd",
    "wof:placetype":"venue"
},
  "geometry": {"coordinates":[-114.093597,51.088509],"type":"Point"}
}