{
  "type": "Feature",
  "properties": {
    "addr:full":"164 Oxford St W London ON N6H 1S1",
    "addr:housenumber":"164",
    "addr:postcode":"n6h 1s1",
    "addr:street":"Oxford St W",
    "iso:country":"CA",
    "sg:address":"164 Oxford St W",
    "sg:city":"London",
    "sg:classifiers":[
        {
            "category":"Building & Trades",
            "subcategory":"Plumbing",
            "type":"Services"
        }
    ],
    "sg:phone":"+1 519 439 6671",
    "sg:postcode":"N6H 1S1",
    "sg:province":"ON",
    "sg:tags":[
        "contractor",
        "mechanical"
    ],
    "wof:name":"B B & H Mechanical London Ltd",
    "wof:placetype":"venue"
},
  "geometry": {"coordinates":[-81.27027099999999,42.990265],"type":"Point"}
}