{
  "type": "Feature",
  "properties": {
    "iso:country":"CA",
    "sg:address":"164 Oxford St W",
    "sg:city":"London",
    "sg:classifiers":[
        {
            "category":"Building & Trades",
            "subcategory":"Plumbing",
            "type":"Services"
        }
    ],
    "sg:phone":"+1 519 439 6671",
    "sg:postcode":"N6H 1S1",
    "sg:province":"ON",
    "sg:tags":[
        "contractor",
        "mechanical"
    ],
    "wof:name":"B B & H Mechanical London Ltd",
    "wof:placetype":"venue"
},
  "geometry": {"coordinates":[-81.270271,42.990265],"type":"Point"}
}