{
  "type": "Feature",
  "properties": {
    "iso:country":"CA",
    "sg:address":"18 Alterra Crt",
    "sg:city":"Woodbridge",
    "sg:classifiers":[
        {
            "category":"Travel",
            "subcategory":"Travel Agent",
            "type":"Entertainment"
        }
    ],
    "sg:phone":"+1 905 856 2900",
    "sg:postcode":"L4L 9E2",
    "sg:province":"ON",
    "sg:tags":[
        "agency",
        "bureau"
    ],
    "wof:name":"Travel Only",
    "wof:placetype":"venue"
},
  "geometry": {"coordinates":[-79.598457,43.814796],"type":"Point"}
}