{
  "type": "Feature",
  "properties": {
    "addr:full":"58 Riverside Dr Lower Sackville NS B4C 1B9",
    "addr:housenumber":"58",
    "addr:postcode":"b4c 1b9",
    "addr:street":"Riverside Dr",
    "iso:country":"CA",
    "sg:address":"58 Riverside Dr",
    "sg:city":"Lower Sackville",
    "sg:classifiers":[
        {
            "category":"Cinema",
            "subcategory":"Movie Rental",
            "type":"Entertainment"
        }
    ],
    "sg:phone":"+1 902 865 7744",
    "sg:postcode":"B4C 1B9",
    "sg:province":"NS",
    "sg:tags":[
        "leasing",
        "video",
        "disc",
        "tape"
    ],
    "wof:name":"Jason's Video & Convenience",
    "wof:placetype":"venue"
},
  "geometry": {"coordinates":[-63.684162,44.776077],"type":"Point"}
}