{
  "type": "Feature",
  "properties": {
    "addr:full":"301 1st Ave Young SK S0K 4Y0",
    "addr:housenumber":"301",
    "addr:postcode":"s0k 4y0",
    "addr:street":"1St Ave",
    "iso:country":"CA",
    "sg:address":"301 1st Ave",
    "sg:city":"Young",
    "sg:classifiers":[
        {
            "category":"Autos & Motor Vehicles",
            "subcategory":"Fuel & Gas Station",
            "type":"Retail Goods"
        }
    ],
    "sg:phone":"+1 306 259 2114",
    "sg:postcode":"S0K 4Y0",
    "sg:province":"SK",
    "sg:tags":[
        "oil"
    ],
    "wof:name":"Young CO-OP Assn Ltd",
    "wof:placetype":"venue"
},
  "geometry": {"coordinates":[-105.746826172,51.7667007446],"type":"Point"}
}