{
  "type": "Feature",
  "properties": {
    "addr:full":"1067 Av Lapierre Saint-Emile QC G3E 1H8",
    "addr:housenumber":"1067",
    "addr:postcode":"g3e 1h8",
    "addr:street":"Av Lapierre Saint-Emile",
    "iso:country":"CA",
    "sg:address":"1067 Av Lapierre",
    "sg:city":"Saint-Emile",
    "sg:classifiers":[
        {
            "category":"Autos & Motor Vehicles",
            "subcategory":"Motorcycle Sales",
            "type":"Retail Goods"
        }
    ],
    "sg:phone":"+1 418 842 1171",
    "sg:postcode":"G3E 1H8",
    "sg:province":"QC",
    "sg:tags":[
        "car",
        "golf",
        "cart"
    ],
    "wof:name":"Entreprises Louis Beaulieu Inc",
    "wof:placetype":"venue"
},
  "geometry": {"coordinates":[-71.33029174799999,46.8631973267],"type":"Point"}
}