{
  "type": "Feature",
  "properties": {
    "addr:full":"1293 Main St Glace Bay NS B1A 5A5",
    "addr:housenumber":"1293",
    "addr:postcode":"b1a 5a5",
    "addr:street":"Main St",
    "iso:country":"CA",
    "sg:address":"1293 Main St",
    "sg:city":"Glace Bay",
    "sg:classifiers":[
        {
            "category":"Wholesale",
            "subcategory":"Groceries",
            "type":"Manufacturing & Wholesale Goods"
        }
    ],
    "sg:phone":"+1 902 849 1112",
    "sg:postcode":"B1A 5A5",
    "sg:province":"NS",
    "sg:tags":[
        "food",
        "product"
    ],
    "wof:name":"M & B Wholesale Ltd",
    "wof:placetype":"venue"
},
  "geometry": {"coordinates":[-59.995403,46.208267],"type":"Point"}
}