{
  "type": "Feature",
  "properties": {
    "addr:full":"Ottawa ON K2C 0C7",
    "addr:postcode":"k2c 0c7",
    "iso:country":"CA",
    "sg:city":"Ottawa",
    "sg:classifiers":[
        {
            "category":"Health Services",
            "subcategory":"Doctor",
            "type":"Services"
        }
    ],
    "sg:phone":"+1 613 224 7381",
    "sg:postcode":"K2C 0C7",
    "sg:province":"ON",
    "sg:tags":[
        "physician",
        "surgeon"
    ],
    "wof:name":"Malik, A MD",
    "wof:placetype":"venue"
},
  "geometry": {"coordinates":[-75.7591705322,45.3533096313],"type":"Point"}
}