{
  "type": "Feature",
  "properties": {
    "addr:full":"Bolton ON L7E 1E2",
    "addr:postcode":"l7e 1e2",
    "iso:country":"CA",
    "sg:city":"Bolton",
    "sg:classifiers":[
        {
            "category":"Retail",
            "subcategory":"Auto Repair",
            "type":"Services"
        }
    ],
    "sg:phone":"+1 905 951 2690",
    "sg:postcode":"L7E 1E2",
    "sg:province":"ON",
    "sg:tags":[
        "repairing",
        "automobile"
    ],
    "wof:name":"Killam Auto Ctr",
    "wof:placetype":"venue"
},
  "geometry": {"coordinates":[-79.726562,43.860851],"type":"Point"}
}