{
  "type": "Feature",
  "properties": {
    "addr:full":"321 St Clair St Chatham ON N7L 3J8",
    "addr:housenumber":"321",
    "addr:postcode":"n7l 3j8",
    "addr:street":"St Clair St",
    "iso:country":"CA",
    "sg:address":"321 St Clair St",
    "sg:city":"Chatham",
    "sg:classifiers":[
        {
            "category":"Retail",
            "subcategory":"Laundry & Dry Cleaning",
            "type":"Services"
        }
    ],
    "sg:phone":"+1 519 354 5432",
    "sg:postcode":"N7L 3J8",
    "sg:province":"ON",
    "sg:tags":[
        "cleaners"
    ],
    "wof:name":"Highlander Laundry & Dry Clean",
    "wof:placetype":"venue"
},
  "geometry": {"coordinates":[-82.1974105835,42.4131774902],"type":"Point"}
}