{
  "type": "Feature",
  "properties": {
    "addr:full":"1941 Ontario Ave Saskatoon SK S7K 1T5",
    "addr:housenumber":"1941",
    "addr:postcode":"s7k 1t5",
    "addr:street":"Ontario Ave",
    "iso:country":"CA",
    "sg:address":"1941 Ontario Ave",
    "sg:city":"Saskatoon",
    "sg:classifiers":[
        {
            "category":"Retail",
            "subcategory":"Auto Repair",
            "type":"Services"
        }
    ],
    "sg:phone":"+1 306 652 3337",
    "sg:postcode":"S7K 1T5",
    "sg:province":"SK",
    "sg:tags":[
        "transmission"
    ],
    "wof:name":"Trevor's Transmission Repair",
    "wof:placetype":"venue"
},
  "geometry": {"coordinates":[-106.666275,52.15556],"type":"Point"}
}