{
  "type": "Feature",
  "properties": {
    "addr:full":"156 Oakchurch Pl SW Calgary AB T2V 4B5",
    "addr:housenumber":"156",
    "addr:postcode":"t2v 4b5",
    "addr:street":"Oakchurch Pl Sw",
    "iso:country":"CA",
    "sg:address":"156 Oakchurch Pl SW",
    "sg:city":"Calgary",
    "sg:classifiers":[
        {
            "category":"Professional",
            "subcategory":"Art Services",
            "type":"Services"
        }
    ],
    "sg:phone":"+1 403 251 7519",
    "sg:postcode":"T2V 4B5",
    "sg:province":"AB",
    "sg:tags":[
        "graphic",
        "publishing",
        "designer"
    ],
    "wof:name":"Reproductions Etc",
    "wof:placetype":"venue"
},
  "geometry": {"coordinates":[-114.128632,50.96767],"type":"Point"}
}