{
  "type": "Feature",
  "properties": {
    "addr:full":"5015 Boul Levesque O Laval QC H7W 2S1",
    "addr:housenumber":"5015",
    "addr:postcode":"h7w 2s1",
    "addr:street":"Boul Levesque O",
    "iso:country":"CA",
    "sg:address":"5015 Boul Levesque O",
    "sg:city":"Laval",
    "sg:classifiers":[
        {
            "category":"Wholesale",
            "subcategory":"Machinery & Supplies",
            "type":"Manufacturing & Wholesale Goods"
        }
    ],
    "sg:phone":"+1 514 336 4723",
    "sg:postcode":"H7W 2S1",
    "sg:province":"QC",
    "sg:tags":[
        "equipment",
        "irrigation",
        "system",
        "sprinkler"
    ],
    "wof:name":"Holmes Irrigation Inc",
    "wof:placetype":"venue"
},
  "geometry": {"coordinates":[-73.7649612427,45.5236701965],"type":"Point"}
}