{
  "type": "Feature",
  "properties": {
    "addr:full":"549 Massey Rd # 4 Guelph ON N1K 1B3",
    "addr:housenumber":"549",
    "addr:postcode":"n1k 1b3",
    "addr:street":"Massey Rd # 4",
    "iso:country":"CA",
    "sg:address":"549 Massey Rd # 4",
    "sg:city":"Guelph",
    "sg:classifiers":[
        {
            "category":"Retail",
            "subcategory":"Auto Repair",
            "type":"Services"
        }
    ],
    "sg:phone":"+1 519 824 7770",
    "sg:postcode":"N1K 1B3",
    "sg:province":"ON",
    "sg:tags":[
        "washing",
        "undercoating",
        "automobile",
        "rustproofing",
        "car",
        "polishing"
    ],
    "wof:name":"Krown Rust Control",
    "wof:placetype":"venue"
},
  "geometry": {"coordinates":[-80.313866,43.532246],"type":"Point"}
}