{
  "type": "Feature",
  "properties": {
    "addr:full":"Rockwood ON N0B 2K0",
    "addr:postcode":"n0b 2k0",
    "iso:country":"CA",
    "sg:city":"Rockwood",
    "sg:classifiers":[
        {
            "category":"Building & Trades",
            "subcategory":"Construction",
            "type":"Services"
        }
    ],
    "sg:phone":"+1 519 856 9222",
    "sg:postcode":"N0B 2K0",
    "sg:province":"ON",
    "sg:tags":[
        "cabinet",
        "maker",
        "woodworker"
    ],
    "wof:name":"Daniel's Dovetails",
    "wof:placetype":"venue"
},
  "geometry": {"coordinates":[-80.154579,43.626362],"type":"Point"}
}