{
  "type": "Feature",
  "properties": {
    "iso:country":"CA",
    "sg:address":"312 Saddleback Rd NW",
    "sg:city":"Edmonton",
    "sg:classifiers":[
        {
            "category":"Real Estate",
            "subcategory":"Real Estate Agent",
            "type":"Services"
        }
    ],
    "sg:phone":"+1 780 434 4700",
    "sg:postcode":"T6J 4R7",
    "sg:province":"AB",
    "wof:name":"Century 21 All Stars",
    "wof:placetype":"venue"
},
  "geometry": {"coordinates":[-113.528358,53.461205],"type":"Point"}
}