{
  "type": "Feature",
  "properties": {
    "addr:full":"Hwy 6 & 39 Wabowden MB R0B 1S0",
    "addr:postcode":"r0b 1s0",
    "addr:street":"Hwy 6 & 39",
    "iso:country":"CA",
    "sg:address":"Hwy 6 & 39",
    "sg:city":"Wabowden",
    "sg:classifiers":[
        {
            "category":"Travel",
            "subcategory":"Hotels & Motels",
            "type":"Entertainment"
        }
    ],
    "sg:phone":"+1 204 689 9900",
    "sg:postcode":"R0B 1S0",
    "sg:province":"MB",
    "wof:name":"Ponton Service Station",
    "wof:placetype":"venue"
},
  "geometry": {"coordinates":[-98.626701,54.95779],"type":"Point"}
}