{
  "type": "Feature",
  "properties": {
    "iso:country":"CA",
    "sg:address":"27 Milliken Blvd",
    "sg:city":"Scarborough",
    "sg:classifiers":[
        {
            "category":"Professional",
            "type":"Services"
        }
    ],
    "sg:phone":"+1 416 321 8866",
    "sg:postcode":"M1V 5H9",
    "sg:province":"ON",
    "sg:tags":[
        "establishment",
        "meat"
    ],
    "wof:name":"Hing Man Meat Inc",
    "wof:placetype":"venue"
},
  "geometry": {"coordinates":[-79.294883728,43.803527832],"type":"Point"}
}