{
  "type": "Feature",
  "properties": {
    "addr:full":"8134 Boul Decarie # 145 Montreal QC H4P 2S8",
    "addr:housenumber":"8134",
    "addr:postcode":"h4p 2s8",
    "addr:street":"Boul Decarie # 145",
    "iso:country":"CA",
    "sg:address":"8134 Boul Decarie # 145",
    "sg:city":"Montreal",
    "sg:classifiers":[
        {
            "category":"Professional",
            "subcategory":"Business Services",
            "type":"Services"
        }
    ],
    "sg:phone":"+1 514 343 4993",
    "sg:postcode":"H4P 2S8",
    "sg:province":"QC",
    "sg:tags":[
        "interior",
        "consultant",
        "design",
        "decorator"
    ],
    "wof:name":"Desrosiers, Andree",
    "wof:placetype":"venue"
},
  "geometry": {"coordinates":[-73.65991200000001,45.498131],"type":"Point"}
}