{
  "type": "Feature",
  "properties": {
    "addr:full":"4505 101 St NW Edmonton AB T6E 5C6",
    "addr:housenumber":"4505",
    "addr:postcode":"t6e 5c6",
    "addr:street":"101 St Nw",
    "iso:country":"CA",
    "sg:address":"4505 101 St NW",
    "sg:city":"Edmonton",
    "sg:classifiers":[
        {
            "category":"Retail",
            "subcategory":"Laundry & Dry Cleaning",
            "type":"Services"
        }
    ],
    "sg:phone":"+1 780 439 5151",
    "sg:postcode":"T6E 5C6",
    "sg:province":"AB",
    "sg:tags":[
        "cleaners",
        "rug",
        "carpet"
    ],
    "wof:name":"Royal Steam-Vue Cleaners",
    "wof:placetype":"venue"
},
  "geometry": {"coordinates":[-113.488945007,53.4834671021],"type":"Point"}
}