{
  "type": "Feature",
  "properties": {
    "iso:country":"CA",
    "sg:address":"865 Rue Rachel E",
    "sg:city":"Montreal",
    "sg:classifiers":[
        {
            "category":"Manufacturing",
            "subcategory":"Food",
            "type":"Manufacturing & Wholesale Goods"
        }
    ],
    "sg:phone":"+1 514 527 5487",
    "sg:postcode":"H2J 2H9",
    "sg:province":"QC",
    "sg:tags":[
        "pasta",
        "noodle"
    ],
    "wof:name":"Maison Des Pates Fraiches",
    "wof:placetype":"venue"
},
  "geometry": {"coordinates":[-73.576141,45.52417],"type":"Point"}
}