{
  "type": "Feature",
  "properties": {
    "iso:country":"CA",
    "sg:address":"285 Rue DE L'Eglise",
    "sg:city":"Saint-Romuald",
    "sg:classifiers":[
        {
            "category":"Organizations",
            "subcategory":"Non-profit Organization",
            "type":"Services"
        }
    ],
    "sg:phone":"+1 418 839 5588",
    "sg:postcode":"G6W 3H6",
    "sg:province":"QC",
    "sg:tags":[
        "charitable",
        "institution",
        "association"
    ],
    "wof:name":"Service D'Entraide St-Romuald",
    "wof:placetype":"venue"
},
  "geometry": {"coordinates":[-71.239159,46.758049],"type":"Point"}
}