{
  "type": "Feature",
  "properties": {
    "addr:full":"Toronto ON M5B 1B7",
    "addr:postcode":"m5b 1b7",
    "iso:country":"CA",
    "sg:city":"Toronto",
    "sg:classifiers":[
        {
            "category":"Wholesale",
            "subcategory":"Jewelry",
            "type":"Manufacturing & Wholesale Goods"
        }
    ],
    "sg:phone":"+1 416 367 0707",
    "sg:postcode":"M5B 1B7",
    "sg:province":"ON",
    "sg:tags":[
        "jeweler"
    ],
    "wof:name":"Shiny Jewelers",
    "wof:placetype":"venue"
},
  "geometry": {"coordinates":[-79.37989,43.655834],"type":"Point"}
}