{
  "type": "Feature",
  "properties": {
    "addr:full":"2925 Av Kepler Sainte-Foy QC G1X 3V4",
    "addr:housenumber":"2925",
    "addr:postcode":"g1x 3v4",
    "addr:street":"Av Kepler",
    "iso:country":"CA",
    "sg:address":"2925 Av Kepler",
    "sg:city":"Sainte-Foy",
    "sg:classifiers":[
        {
            "category":"Freight",
            "type":"Transportation"
        }
    ],
    "sg:phone":"+1 418 654 3615",
    "sg:postcode":"G1X 3V4",
    "sg:province":"QC",
    "sg:tags":[
        "courier"
    ],
    "wof:name":"Ics Courrier",
    "wof:placetype":"venue"
},
  "geometry": {"coordinates":[-71.31729900000001,46.787598],"type":"Point"}
}