{
  "type": "Feature",
  "properties": {
    "addr:full":"Saint-Pascal QC G0L 3Y0",
    "addr:postcode":"g0l 3y0",
    "iso:country":"CA",
    "sg:city":"Saint-Pascal",
    "sg:classifiers":[
        {
            "category":"Government",
            "subcategory":"Office",
            "type":"Public Place"
        }
    ],
    "sg:phone":"+1 418 492 7314",
    "sg:postcode":"G0L 3Y0",
    "sg:province":"QC",
    "wof:name":"Quebec Mandataires",
    "wof:placetype":"venue"
},
  "geometry": {"coordinates":[-69.801857,47.52396],"type":"Point"}
}