{
  "type": "Feature",
  "properties": {
    "addr:full":"300 Laplanche St # 20898 Amherst NS B4H 4A1",
    "addr:housenumber":"300",
    "addr:postcode":"b4h 4a1",
    "addr:street":"Laplanche St # 20898",
    "iso:country":"CA",
    "sg:address":"300 Laplanche St # 20898",
    "sg:city":"Amherst",
    "sg:classifiers":[
        {
            "category":"Home & Garden",
            "subcategory":"Building Materials",
            "type":"Retail Goods"
        }
    ],
    "sg:phone":"+1 902 667 5676",
    "sg:postcode":"B4H 4A1",
    "sg:province":"NS",
    "wof:name":"Amherst Millwork Ltd",
    "wof:placetype":"venue"
},
  "geometry": {"coordinates":[-64.21367600000001,45.834839],"type":"Point"}
}