{
  "type": "Feature",
  "properties": {
    "addr:full":"258 Charlotte St Sydney NS B1P 1C5",
    "addr:housenumber":"258",
    "addr:postcode":"b1p 1c5",
    "addr:street":"Charlotte St",
    "iso:country":"CA",
    "sg:address":"258 Charlotte St",
    "sg:city":"Sydney",
    "sg:classifiers":[
        {
            "category":"Banks & Credit Unions",
            "subcategory":"Bank",
            "type":"Services"
        }
    ],
    "sg:phone":"+1 902 539 2110",
    "sg:postcode":"B1P 1C5",
    "sg:province":"NS",
    "wof:name":"Scotiabank",
    "wof:placetype":"venue"
},
  "geometry": {"coordinates":[-60.1953277588,46.1394920349],"type":"Point"}
}