{
  "type": "Feature",
  "properties": {
    "addr:full":"2397 Lakeshore Dr Brechin ON L0K 1B0",
    "addr:housenumber":"2397",
    "addr:postcode":"l0k 1b0",
    "addr:street":"Lakeshore Dr",
    "iso:country":"CA",
    "sg:address":"2397 Lakeshore Dr",
    "sg:city":"Brechin",
    "sg:classifiers":[
        {
            "category":"Building & Trades",
            "subcategory":"Plumbing",
            "type":"Services"
        }
    ],
    "sg:phone":"+1 705 484 5054",
    "sg:postcode":"L0K 1B0",
    "sg:province":"ON",
    "sg:tags":[
        "conditioning",
        "air",
        "refrigeration",
        "system",
        "contractor"
    ],
    "wof:name":"Arctic Air Refrigeration",
    "wof:placetype":"venue"
},
  "geometry": {"coordinates":[-79.201279,44.521938],"type":"Point"}
}