{
  "type": "Feature",
  "properties": {
    "addr:full":"273 Boul Gerard-D.-Levesque O Paspebiac QC G0C 2K0",
    "addr:housenumber":"273",
    "addr:postcode":"g0c 2k0",
    "addr:street":"Boul Gerard-D.-Levesque O Paspebiac",
    "iso:country":"CA",
    "sg:address":"273 Boul Gerard-D.-Levesque O",
    "sg:city":"Paspebiac",
    "sg:classifiers":[
        {
            "category":"Social Services",
            "type":"Services"
        }
    ],
    "sg:phone":"+1 418 752 2572",
    "sg:postcode":"G0C 2K0",
    "sg:province":"QC",
    "sg:tags":[
        "organization",
        "welfare"
    ],
    "wof:name":"Clsc Chaleurs",
    "wof:placetype":"venue"
},
  "geometry": {"coordinates":[-65.228493,48.033573],"type":"Point"}
}