{
  "type": "Feature",
  "properties": {
    "addr:full":"Surrey BC V3R 8X2",
    "addr:postcode":"v3r 8x2",
    "iso:country":"CA",
    "sg:city":"Surrey",
    "sg:classifiers":[
        {
            "category":"Food & Beverages",
            "subcategory":"Specialty",
            "type":"Retail Goods"
        }
    ],
    "sg:phone":"+1 604 588 3866",
    "sg:postcode":"V3R 8X2",
    "sg:province":"BC",
    "sg:tags":[
        "health",
        "diet"
    ],
    "wof:name":"Justin's Natural Foods",
    "wof:placetype":"venue"
},
  "geometry": {"coordinates":[-122.798973084,49.1844406128],"type":"Point"}
}