{
  "type": "Feature",
  "properties": {
    "addr:full":"15167 108 Ave Surrey BC V3R 1W5",
    "addr:housenumber":"15167",
    "addr:postcode":"v3r 1w5",
    "addr:street":"108 Ave",
    "iso:country":"CA",
    "sg:address":"15167 108 Ave",
    "sg:city":"Surrey",
    "sg:classifiers":[
        {
            "category":"Communications",
            "subcategory":"Film & Video Production",
            "type":"Services"
        }
    ],
    "sg:phone":"+1 604 581 7809",
    "sg:postcode":"V3R 1W5",
    "sg:province":"BC",
    "sg:tags":[
        "motion",
        "picture"
    ],
    "wof:name":"Maier Motion Productions",
    "wof:placetype":"venue"
},
  "geometry": {"coordinates":[-122.80178832999999,49.1989173889],"type":"Point"}
}