{
  "type": "Feature",
  "properties": {
    "addr:full":"460 7th St W Cornwall ON K6J 2Y7",
    "addr:housenumber":"460",
    "addr:postcode":"k6j 2y7",
    "addr:street":"7Th St W",
    "iso:country":"CA",
    "sg:address":"460 7th St W",
    "sg:city":"Cornwall",
    "sg:classifiers":[
        {
            "category":"Manufacturing",
            "subcategory":"Glass & Minerals",
            "type":"Manufacturing & Wholesale Goods"
        }
    ],
    "sg:phone":"+1 613 933 2290",
    "sg:postcode":"K6J 2Y7",
    "sg:province":"ON",
    "sg:tags":[
        "concrete",
        "shape",
        "common",
        "block"
    ],
    "wof:name":"Cornwall Concrete Products Ltd",
    "wof:placetype":"venue"
},
  "geometry": {"coordinates":[-74.745026,45.022114],"type":"Point"}
}