{
  "type": "Feature",
  "properties": {
    "addr:full":"925 Dundas St Woodstock ON N4S 1H2",
    "addr:housenumber":"925",
    "addr:postcode":"n4s 1h2",
    "addr:street":"Dundas St",
    "iso:country":"CA",
    "sg:address":"925 Dundas St",
    "sg:city":"Woodstock",
    "sg:classifiers":[
        {
            "category":"Cinema",
            "subcategory":"Movie Rental",
            "type":"Entertainment"
        }
    ],
    "sg:phone":"+1 519 537 6217",
    "sg:postcode":"N4S 1H2",
    "sg:province":"ON",
    "sg:tags":[
        "leasing",
        "video",
        "disc",
        "tape"
    ],
    "wof:name":"Blockbuster Video",
    "wof:placetype":"venue"
},
  "geometry": {"coordinates":[-80.733688,43.133553],"type":"Point"}
}