{
  "type": "Feature",
  "properties": {
    "addr:full":"Scarborough ON M1B 5J7",
    "addr:postcode":"m1b 5j7",
    "iso:country":"CA",
    "sg:city":"Scarborough",
    "sg:classifiers":[
        {
            "category":"Organizations",
            "subcategory":"Religious Organization",
            "type":"Services"
        }
    ],
    "sg:phone":"+1 416 299 5234",
    "sg:postcode":"M1B 5J7",
    "sg:province":"ON",
    "sg:tags":[
        "church"
    ],
    "wof:name":"Malvern Chinese Free Methodist",
    "wof:placetype":"venue"
},
  "geometry": {"coordinates":[-79.230835,43.795612],"type":"Point"}
}