{
  "type": "Feature",
  "properties": {
    "addr:full":"Plessisville QC G6L 2Y2",
    "addr:postcode":"g6l 2y2",
    "iso:country":"CA",
    "sg:city":"Plessisville",
    "sg:classifiers":[
        {
            "category":"Real Estate",
            "subcategory":"Real Estate Agent",
            "type":"Services"
        }
    ],
    "sg:phone":"+1 819 362 1614",
    "sg:postcode":"G6L 2Y2",
    "sg:province":"QC",
    "sg:tags":[
        "tool",
        "agency",
        "rental"
    ],
    "wof:name":"Location D'Outils F Luneau",
    "wof:placetype":"venue"
},
  "geometry": {"coordinates":[-71.76544199999999,46.21489],"type":"Point"}
}