{
  "type": "Feature",
  "properties": {
    "addr:full":"5798 Route 127 Bocabec NB E5B 3J8",
    "addr:housenumber":"5798",
    "addr:postcode":"e5b 3j8",
    "addr:street":"Route 127",
    "iso:country":"CA",
    "sg:address":"5798 Route 127",
    "sg:city":"Bocabec",
    "sg:classifiers":[
        {
            "category":"Home & Garden",
            "subcategory":"Garden Supply",
            "type":"Retail Goods"
        }
    ],
    "sg:phone":"+1 506 529 3762",
    "sg:postcode":"E5B 3J8",
    "sg:province":"NB",
    "sg:tags":[
        "engine",
        "lawn",
        "mower"
    ],
    "wof:name":"Norm Small Engine Repair",
    "wof:placetype":"venue"
},
  "geometry": {"coordinates":[-66.98857099999999,45.177689],"type":"Point"}
}