{
  "type": "Feature",
  "properties": {
    "addr:full":"252 Rue Principale Granby QC J2G 2V8",
    "addr:housenumber":"252",
    "addr:postcode":"j2g 2v8",
    "addr:street":"Rue Principale",
    "iso:country":"CA",
    "sg:address":"252 Rue Principale",
    "sg:city":"Granby",
    "sg:classifiers":[
        {
            "category":"Organizations",
            "subcategory":"Religious Organization",
            "type":"Services"
        }
    ],
    "sg:phone":"+1 450 372 7303",
    "sg:postcode":"J2G 2V8",
    "sg:province":"QC",
    "sg:tags":[
        "church"
    ],
    "wof:name":"Presbytere Notre Dame",
    "wof:placetype":"venue"
},
  "geometry": {"coordinates":[-72.7289047241,45.4007835388],"type":"Point"}
}