{
  "type": "Feature",
  "properties": {
    "iso:country":"CA",
    "sg:city":"Vancouver",
    "sg:classifiers":[
        {
            "category":"Restaurant",
            "type":"Food & Drink"
        }
    ],
    "sg:phone":"+1 604 683 2337",
    "sg:postcode":"V6E 1C6",
    "sg:province":"BC",
    "wof:name":"Fogg 'N' Suds Restaurants",
    "wof:placetype":"venue"
},
  "geometry": {"coordinates":[-123.128799438,49.2873878479],"type":"Point"}
}