{
  "type": "Feature",
  "properties": {
    "iso:country":"CA",
    "sg:address":"24 Rue DE Courcelette",
    "sg:city":"Quebec",
    "sg:classifiers":[
        {
            "category":"Retail",
            "subcategory":"Repair Shop",
            "type":"Services"
        }
    ],
    "sg:phone":"+1 418 687 9574",
    "sg:postcode":"G1N 4T3",
    "sg:province":"QC",
    "sg:tags":[
        "welding"
    ],
    "wof:name":"Soudure Dtg",
    "wof:placetype":"venue"
},
  "geometry": {"coordinates":[-71.2475357056,46.8109893799],"type":"Point"}
}