{
  "type": "Feature",
  "properties": {
    "addr:full":"Quesnel BC V2J 1G2",
    "addr:postcode":"v2j 1g2",
    "iso:country":"CA",
    "sg:city":"Quesnel",
    "sg:classifiers":[
        {
            "category":"Restaurant",
            "type":"Food & Drink"
        }
    ],
    "sg:phone":"+1 250 992 2220",
    "sg:postcode":"V2J 1G2",
    "sg:province":"BC",
    "wof:name":"Come Joy Restaurant",
    "wof:placetype":"venue"
},
  "geometry": {"coordinates":[-122.515533447,52.9710083008],"type":"Point"}
}