{
  "type": "Feature",
  "properties": {
    "addr:full":"Edson AB T7E 1R8",
    "addr:postcode":"t7e 1r8",
    "iso:country":"CA",
    "sg:city":"Edson",
    "sg:classifiers":[
        {
            "category":"Building & Trades",
            "subcategory":"Equipment Rental",
            "type":"Services"
        }
    ],
    "sg:phone":"+1 780 723 3535",
    "sg:postcode":"T7E 1R8",
    "sg:province":"AB",
    "sg:tags":[
        "yard",
        "contractor"
    ],
    "wof:name":"Castle Rentals & Welding Supls",
    "wof:placetype":"venue"
},
  "geometry": {"coordinates":[-116.44996643099999,53.5770339966],"type":"Point"}
}