{
  "type": "Feature",
  "properties": {
    "addr:full":"96 Sumbler Rd Fenwick ON L0S 1C0",
    "addr:housenumber":"96",
    "addr:postcode":"l0s 1c0",
    "addr:street":"Sumbler Rd",
    "iso:country":"CA",
    "sg:address":"96 Sumbler Rd",
    "sg:city":"Fenwick",
    "sg:classifiers":[
        {
            "category":"Wholesale",
            "subcategory":"Construction Materials",
            "type":"Manufacturing & Wholesale Goods"
        }
    ],
    "sg:phone":"+1 905 735 8654",
    "sg:postcode":"L0S 1C0",
    "sg:province":"ON",
    "sg:tags":[
        "home",
        "fence",
        "improvement"
    ],
    "wof:name":"Alfa Project",
    "wof:placetype":"venue"
},
  "geometry": {"coordinates":[-79.3574523926,43.0261611938],"type":"Point"}
}