{
  "type": "Feature",
  "properties": {
    "addr:full":"798 Av Outremont Outremont QC H2V 3N4",
    "addr:housenumber":"798",
    "addr:postcode":"h2v 3n4",
    "addr:street":"Av Outremont",
    "iso:country":"CA",
    "sg:address":"798 Av Outremont",
    "sg:city":"Outremont",
    "sg:classifiers":[
        {
            "category":"Home & Garden",
            "subcategory":"Building Materials",
            "type":"Retail Goods"
        }
    ],
    "sg:phone":"+1 514 272 5222",
    "sg:postcode":"H2V 3N4",
    "sg:province":"QC",
    "sg:tags":[
        "door",
        "gate",
        "operating",
        "devices"
    ],
    "wof:name":"Electronic Garage Door Svc",
    "wof:placetype":"venue"
},
  "geometry": {"coordinates":[-73.6140823364,45.5211868286],"type":"Point"}
}