{
  "type": "Feature",
  "properties": {
    "addr:full":"Hawkesbury ON K6A 3B2",
    "addr:postcode":"k6a 3b2",
    "iso:country":"CA",
    "sg:city":"Hawkesbury",
    "sg:classifiers":[
        {
            "category":"Health Services",
            "subcategory":"Doctor",
            "type":"Services"
        }
    ],
    "sg:phone":"+1 613 632 0118",
    "sg:postcode":"K6A 3B2",
    "sg:province":"ON",
    "sg:tags":[
        "physician",
        "surgeon"
    ],
    "wof:name":"Fairfield, John A MD",
    "wof:placetype":"venue"
},
  "geometry": {"coordinates":[-74.609207,45.5989],"type":"Point"}
}