{
  "type": "Feature",
  "properties": {
    "addr:full":"164187 Brownsville Rd Tillsonburg ON N4G 4G8",
    "addr:housenumber":"164187",
    "addr:postcode":"n4g 4g8",
    "addr:street":"Brownsville Rd",
    "iso:country":"CA",
    "sg:address":"164187 Brownsville Rd",
    "sg:city":"Tillsonburg",
    "sg:classifiers":[
        {
            "category":"Building & Trades",
            "subcategory":"Construction",
            "type":"Services"
        }
    ],
    "sg:phone":"+1 519 842 6695",
    "sg:postcode":"N4G 4G8",
    "sg:province":"ON",
    "sg:tags":[
        "designer",
        "hot",
        "spa",
        "tub",
        "dealer",
        "pool",
        "swimming"
    ],
    "wof:name":"Backyard Watercreations Inc",
    "wof:placetype":"venue"
},
  "geometry": {"coordinates":[-80.761047,42.876347],"type":"Point"}
}