{
  "type": "Feature",
  "properties": {
    "addr:full":"2024 Rue Schulz Saint-Jerome QC J7Y 4L3",
    "addr:housenumber":"2024",
    "addr:postcode":"j7y 4l3",
    "addr:street":"Rue Schulz Saint-Jerome",
    "iso:country":"CA",
    "sg:address":"2024 Rue Schulz",
    "sg:city":"Saint-Jerome",
    "sg:classifiers":[
        {
            "category":"Personal",
            "subcategory":"Beauty Salon",
            "type":"Services"
        }
    ],
    "sg:phone":"+1 450 565 5500",
    "sg:postcode":"J7Y 4L3",
    "sg:province":"QC",
    "wof:name":"Coiffure Entete Enr",
    "wof:placetype":"venue"
},
  "geometry": {"coordinates":[-73.996117,45.798336],"type":"Point"}
}