{
  "type": "Feature",
  "properties": {
    "addr:full":"60 Rue Renaud Saint-Jacques-Le-Mineur QC J0J 1Z0",
    "addr:housenumber":"60",
    "addr:postcode":"qc j0j 1z0",
    "addr:street":"Rue Renaud",
    "iso:country":"CA",
    "sg:address":"60 Rue Renaud",
    "sg:city":"Saint-Jacques-Le-Mineur",
    "sg:classifiers":[
        {
            "category":"Retail",
            "subcategory":"Auto Repair",
            "type":"Services"
        }
    ],
    "sg:phone":"+1 450 347 5024",
    "sg:postcode":"J0J 1Z0",
    "sg:province":"QC",
    "sg:tags":[
        "repairing",
        "automobile",
        "body"
    ],
    "wof:name":"Garage C & N Clermont Inc",
    "wof:placetype":"venue"
},
  "geometry": {"coordinates":[-73.4186782837,45.2771148682],"type":"Point"}
}