{
  "type": "Feature",
  "properties": {
    "addr:full":"701 Boul Manseau Joliette QC J6E 3E8",
    "addr:housenumber":"701",
    "addr:postcode":"j6e 3e8",
    "addr:street":"Boul Manseau",
    "iso:country":"CA",
    "sg:address":"701 Boul Manseau",
    "sg:city":"Joliette",
    "sg:classifiers":[
        {
            "category":"Health Services",
            "subcategory":"Doctor",
            "type":"Services"
        }
    ],
    "sg:phone":"+1 450 753 5730",
    "sg:postcode":"J6E 3E8",
    "sg:province":"QC",
    "sg:tags":[
        "dentist"
    ],
    "wof:name":"Goyette, Normand DDS",
    "wof:placetype":"venue"
},
  "geometry": {"coordinates":[-73.44380200000001,46.022171],"type":"Point"}
}