{
  "type": "Feature",
  "properties": {
    "iso:country":"CA",
    "sg:address":"3100 12th Ave",
    "sg:city":"Regina",
    "sg:classifiers":[
        {
            "category":"Wholesale",
            "subcategory":"Hardware",
            "type":"Manufacturing & Wholesale Goods"
        }
    ],
    "sg:phone":"+1 306 352 1756",
    "sg:postcode":"S4T 1J7",
    "sg:province":"SK",
    "sg:tags":[
        "tool"
    ],
    "wof:name":"Cooper Tools & Equip Wrhse Ltd",
    "wof:placetype":"venue"
},
  "geometry": {"coordinates":[-104.625549316,50.4489173889],"type":"Point"}
}