{
  "type": "Feature",
  "properties": {
    "addr:full":"1923 Mclean Ave Port Coquitlam BC V3C 1N1",
    "addr:housenumber":"1923",
    "addr:postcode":"v3c 1n1",
    "addr:street":"Mclean Ave",
    "iso:country":"CA",
    "sg:address":"1923 Mclean Ave",
    "sg:city":"Port Coquitlam",
    "sg:classifiers":[
        {
            "category":"Wholesale",
            "subcategory":"Electrical",
            "type":"Manufacturing & Wholesale Goods"
        }
    ],
    "sg:phone":"+1 604 941 6611",
    "sg:postcode":"V3C 1N1",
    "sg:province":"BC",
    "sg:tags":[
        "electric",
        "motor"
    ],
    "wof:name":"Trans West Mining Systems Inc",
    "wof:placetype":"venue"
},
  "geometry": {"coordinates":[-122.770713806,49.2534255981],"type":"Point"}
}