{
  "type": "Feature",
  "properties": {
    "iso:country":"CA",
    "sg:address":"568 Boul Renault",
    "sg:city":"Beauceville",
    "sg:classifiers":[
        {
            "category":"Retail",
            "subcategory":"Auto Repair",
            "type":"Services"
        }
    ],
    "sg:phone":"+1 418 774 6301",
    "sg:postcode":"G5X 1N2",
    "sg:province":"QC",
    "sg:tags":[
        "repairing",
        "automobile"
    ],
    "wof:name":"Cloutier Valere Garage Enr",
    "wof:placetype":"venue"
},
  "geometry": {"coordinates":[-70.774719,46.212303],"type":"Point"}
}