{
  "type": "Feature",
  "properties": {
    "iso:country":"CA",
    "sg:address":"225 Main St S",
    "sg:city":"Kenora",
    "sg:classifiers":[
        {
            "category":"Professional",
            "subcategory":"Lawyer & Legal Services",
            "type":"Services"
        }
    ],
    "sg:phone":"+1 807 468 3355",
    "sg:postcode":"P9N 1T3",
    "sg:province":"ON",
    "sg:tags":[
        "attorney"
    ],
    "wof:name":"David James Elliot Law Office",
    "wof:placetype":"venue"
},
  "geometry": {"coordinates":[-94.49090576170001,49.7660865784],"type":"Point"}
}