{
  "type": "Feature",
  "properties": {
    "addr:full":"185 Vansittart Ave Woodstock ON N4S 6E7",
    "addr:housenumber":"185",
    "addr:postcode":"n4s 6e7",
    "addr:street":"Vansittart Ave",
    "iso:country":"CA",
    "sg:address":"185 Vansittart Ave",
    "sg:city":"Woodstock",
    "sg:classifiers":[
        {
            "category":"Building & Trades",
            "subcategory":"Construction",
            "type":"Services"
        }
    ],
    "sg:phone":"+1 519 539 9452",
    "sg:postcode":"N4S 6E7",
    "sg:province":"ON",
    "sg:tags":[
        "painter"
    ],
    "wof:name":"Paul Roberts Paint & Decor",
    "wof:placetype":"venue"
},
  "geometry": {"coordinates":[-80.7638931274,43.1354408264],"type":"Point"}
}