{
  "type": "Feature",
  "properties": {
    "addr:full":"36 Fourth St Charlottetown PE C1E 2B3",
    "addr:housenumber":"36",
    "addr:postcode":"c1e 2b3",
    "addr:street":"Fourth St",
    "iso:country":"CA",
    "sg:address":"36 Fourth St",
    "sg:city":"Charlottetown",
    "sg:classifiers":[
        {
            "category":"Social Services",
            "type":"Services"
        }
    ],
    "sg:phone":"+1 902 628 6771",
    "sg:postcode":"C1E 2B3",
    "sg:province":"PE",
    "sg:tags":[
        "information",
        "center",
        "diabetes"
    ],
    "wof:name":"Activa Brand Products",
    "wof:placetype":"venue"
},
  "geometry": {"coordinates":[-63.1707611084,46.2693405151],"type":"Point"}
}