{
  "type": "Feature",
  "properties": {
    "iso:country":"CA",
    "sg:address":"3590 Skaha Lake Rd",
    "sg:city":"Penticton",
    "sg:classifiers":[
        {
            "category":"Travel",
            "subcategory":"Hotels & Motels",
            "type":"Entertainment"
        }
    ],
    "sg:phone":"+1 250 493 1520",
    "sg:postcode":"V2A 6G7",
    "sg:province":"BC",
    "wof:name":"Traveler's Motel",
    "wof:placetype":"venue"
},
  "geometry": {"coordinates":[-119.58706665,49.4555892944],"type":"Point"}
}