{
  "type": "Feature",
  "properties": {
    "addr:full":"Glencoe ON N0L 1M0",
    "addr:postcode":"n0l 1m0",
    "iso:country":"CA",
    "sg:city":"Glencoe",
    "sg:classifiers":[
        {
            "category":"Building & Trades",
            "subcategory":"Electrical",
            "type":"Services"
        }
    ],
    "sg:phone":"+1 519 287 2981",
    "sg:postcode":"N0L 1M0",
    "sg:province":"ON",
    "sg:tags":[
        "pole",
        "line",
        "electric",
        "contractor"
    ],
    "wof:name":"Southwest Power Corp",
    "wof:placetype":"venue"
},
  "geometry": {"coordinates":[-81.7108078003,42.7485580444],"type":"Point"}
}