{
  "type": "Feature",
  "properties": {
    "addr:full":"Vancouver BC V5L 5E4",
    "addr:postcode":"v5l 5e4",
    "iso:country":"CA",
    "sg:city":"Vancouver",
    "sg:classifiers":[
        {
            "category":"Wholesale",
            "subcategory":"Photographic Equipment",
            "type":"Manufacturing & Wholesale Goods"
        }
    ],
    "sg:phone":"+1 604 437 8650",
    "sg:postcode":"V5L 5E4",
    "sg:province":"BC",
    "sg:tags":[
        "motion",
        "picture",
        "supply"
    ],
    "wof:name":"Ace of Spades Productions Inc",
    "wof:placetype":"venue"
},
  "geometry": {"coordinates":[-123.063385,49.285271],"type":"Point"}
}