{
  "type": "Feature",
  "properties": {
    "addr:full":"26188 126 Ave Maple Ridge BC V2W 1C4",
    "addr:housenumber":"26188",
    "addr:postcode":"v2w 1c4",
    "addr:street":"126 Ave",
    "iso:country":"CA",
    "sg:address":"26188 126 Ave",
    "sg:city":"Maple Ridge",
    "sg:classifiers":[
        {
            "category":"Building & Trades",
            "subcategory":"Construction",
            "type":"Services"
        }
    ],
    "sg:phone":"+1 604 462 0807",
    "sg:postcode":"V2W 1C4",
    "sg:province":"BC",
    "sg:tags":[
        "excavating",
        "contractor"
    ],
    "wof:name":"Unique Loading Svc",
    "wof:placetype":"venue"
},
  "geometry": {"coordinates":[-122.496925,49.229008],"type":"Point"}
}