{
  "type": "Feature",
  "properties": {
    "addr:full":"Delta BC V4G 1M6",
    "addr:postcode":"v4g 1m6",
    "iso:country":"CA",
    "sg:city":"Delta",
    "sg:classifiers":[
        {
            "category":"Manufacturing",
            "subcategory":"Electronics",
            "type":"Manufacturing & Wholesale Goods"
        }
    ],
    "sg:phone":"+1 604 946 8276",
    "sg:postcode":"V4G 1M6",
    "sg:province":"BC",
    "wof:name":"Talkie Tooter Ltd",
    "wof:placetype":"venue"
},
  "geometry": {"coordinates":[-123.02439099999999,49.133102],"type":"Point"}
}