{
  "type": "Feature",
  "properties": {
    "addr:full":"4 Crescent Ave W Souris MB R0K 2C0",
    "addr:housenumber":"4",
    "addr:postcode":"r0k 2c0",
    "addr:street":"Crescent Ave W",
    "iso:country":"CA",
    "sg:address":"4 Crescent Ave W",
    "sg:city":"Souris",
    "sg:classifiers":[
        {
            "category":"Professional",
            "subcategory":"Lawyer & Legal Services",
            "type":"Services"
        }
    ],
    "sg:phone":"+1 204 483 2171",
    "sg:postcode":"R0K 2C0",
    "sg:province":"MB",
    "sg:tags":[
        "attorney"
    ],
    "wof:name":"Forrest & Forrest",
    "wof:placetype":"venue"
},
  "geometry": {"coordinates":[-100.258865,49.620834],"type":"Point"}
}