{
  "type": "Feature",
  "properties": {
    "addr:full":"487 Av Du Quebec Sept-Iles QC G4R 1J8",
    "addr:postcode":"g4r 1j8",
    "addr:street":"487 Av Du Quebec Sept-Iles",
    "iso:country":"CA",
    "sg:address":"487 Av Du Quebec",
    "sg:city":"Sept-Iles",
    "sg:classifiers":[
        {
            "category":"Autos & Motor Vehicles",
            "subcategory":"Motorcycle Sales",
            "type":"Retail Goods"
        }
    ],
    "sg:phone":"+1 418 961 2111",
    "sg:postcode":"G4R 1J8",
    "sg:province":"QC",
    "sg:tags":[
        "scooter"
    ],
    "wof:name":"Sept-Iles Motorsports Inc",
    "wof:placetype":"venue"
},
  "geometry": {"coordinates":[-66.36988100000001,50.215603],"type":"Point"}
}