{
  "type": "Feature",
  "properties": {
    "iso:country":"CA",
    "sg:address":"2131 Deer Park Rd",
    "sg:city":"Oakville",
    "sg:classifiers":[
        {
            "category":"Building & Trades",
            "subcategory":"Construction",
            "type":"Services"
        }
    ],
    "sg:phone":"+1 905 827 7921",
    "sg:postcode":"L6M 3X4",
    "sg:province":"ON",
    "sg:tags":[
        "home",
        "improvement"
    ],
    "wof:name":"Palton Construction Inc",
    "wof:placetype":"venue"
},
  "geometry": {"coordinates":[-79.73983764650001,43.4461631775],"type":"Point"}
}