{
  "type": "Feature",
  "properties": {
    "addr:full":"2465 1E Av Quebec QC G1L 3M9",
    "addr:housenumber":"2465",
    "addr:postcode":"g1l 3m9",
    "addr:street":"1E Av",
    "iso:country":"CA",
    "sg:address":"2465 1E Av",
    "sg:city":"Quebec",
    "sg:classifiers":[
        {
            "category":"Farming",
            "subcategory":"Dairy Farm",
            "type":"Manufacturing & Wholesale Goods"
        }
    ],
    "sg:phone":"+1 418 641 0857",
    "sg:postcode":"G1L 3M9",
    "sg:province":"QC",
    "wof:name":"Natrel Inc",
    "wof:placetype":"venue"
},
  "geometry": {"coordinates":[-71.2421035767,46.834072113],"type":"Point"}
}