{
  "type": "Feature",
  "properties": {
    "addr:full":"764 7 St SE Medicine Hat AB T1A 1K6",
    "addr:housenumber":"764 7",
    "addr:postcode":"t1a 1k6",
    "addr:street":"St Se",
    "iso:country":"CA",
    "sg:address":"764 7 St SE",
    "sg:city":"Medicine Hat",
    "sg:classifiers":[
        {
            "category":"Organizations",
            "subcategory":"Non-profit Organization",
            "type":"Services"
        }
    ],
    "sg:phone":"+1 403 526 0791",
    "sg:postcode":"T1A 1K6",
    "sg:province":"AB",
    "sg:tags":[
        "vegetable",
        "fund",
        "counselor",
        "fruit",
        "raising"
    ],
    "wof:name":"Brewmaster Wholesale Foods",
    "wof:placetype":"venue"
},
  "geometry": {"coordinates":[-110.667625,50.03223],"type":"Point"}
}