{
  "type": "Feature",
  "properties": {
    "iso:country":"CA",
    "sg:address":"145 West St",
    "sg:city":"Mitchell",
    "sg:classifiers":[
        {
            "category":"Manufacturing",
            "subcategory":"Tools & Machinery",
            "type":"Manufacturing & Wholesale Goods"
        }
    ],
    "sg:phone":"+1 519 348 8020",
    "sg:postcode":"N0K 1N0",
    "sg:province":"ON",
    "sg:tags":[
        "machine",
        "shop"
    ],
    "wof:name":"Reynolds Fabricating Ltd",
    "wof:placetype":"venue"
},
  "geometry": {"coordinates":[-81.21175384519999,43.4792785645],"type":"Point"}
}