{
  "type": "Feature",
  "properties": {
    "addr:full":"Mississauga ON L5M 4Z5",
    "addr:postcode":"l5m 4z5",
    "iso:country":"CA",
    "sg:city":"Mississauga",
    "sg:classifiers":[
        {
            "category":"Health Services",
            "subcategory":"Optometrist",
            "type":"Services"
        }
    ],
    "sg:phone":"+1 905 828 0138",
    "sg:postcode":"L5M 4Z5",
    "sg:province":"ON",
    "wof:name":"Hum, Jerry J OD",
    "wof:placetype":"venue"
},
  "geometry": {"coordinates":[-79.7068099976,43.5587882996],"type":"Point"}
}