{
  "type": "Feature",
  "properties": {
    "addr:full":"North York ON M3C 3S2",
    "addr:postcode":"m3c 3s2",
    "iso:country":"CA",
    "sg:city":"North York",
    "sg:classifiers":[
        {
            "category":"Health Services",
            "subcategory":"Doctor",
            "type":"Services"
        }
    ],
    "sg:phone":"+1 416 443 0811",
    "sg:postcode":"M3C 3S2",
    "sg:province":"ON",
    "sg:tags":[
        "physician",
        "surgeon"
    ],
    "wof:name":"Don Valley Chelation Ctr",
    "wof:placetype":"venue"
},
  "geometry": {"coordinates":[-79.336975,43.723591],"type":"Point"}
}