{
  "type": "Feature",
  "properties": {
    "iso:country":"CA",
    "sg:address":"4637 Bute St",
    "sg:city":"Port Alberni",
    "sg:classifiers":[
        {
            "category":"Retail",
            "subcategory":"Animal Services",
            "type":"Services"
        }
    ],
    "sg:phone":"+1 250 724 7954",
    "sg:postcode":"V9Y 3M8",
    "sg:province":"BC",
    "sg:tags":[
        "pet"
    ],
    "wof:name":"Precious Paws Petsitting",
    "wof:placetype":"venue"
},
  "geometry": {"coordinates":[-124.802513123,49.2437057495],"type":"Point"}
}