{
  "type": "Feature",
  "properties": {
    "iso:country":"CA",
    "sg:address":"19950 Av Clark-Graham",
    "sg:city":"Baie-D'Urfe",
    "sg:classifiers":[
        {
            "category":"Real Estate",
            "subcategory":"Real Estate Agent",
            "type":"Services"
        }
    ],
    "sg:phone":"+1 514 457 9371",
    "sg:postcode":"H9X 3R8",
    "sg:province":"QC",
    "sg:tags":[
        "cooperative"
    ],
    "wof:name":"Federation Des Cooperatives",
    "wof:placetype":"venue"
},
  "geometry": {"coordinates":[-71.49565887449999,46.9807128906],"type":"Point"}
}