{
  "type": "Feature",
  "properties": {
    "addr:full":"1701 Michigan Line Sarnia ON N7T 7H4",
    "addr:housenumber":"1701",
    "addr:postcode":"n7t 7h4",
    "addr:street":"Michigan Line",
    "iso:country":"CA",
    "sg:address":"1701 Michigan Line",
    "sg:city":"Sarnia",
    "sg:classifiers":[
        {
            "category":"Building & Trades",
            "subcategory":"Landscaping Services",
            "type":"Services"
        }
    ],
    "sg:phone":"+1 519 542 5728",
    "sg:postcode":"N7T 7H4",
    "sg:province":"ON",
    "sg:tags":[
        "landscape",
        "contractor"
    ],
    "wof:name":"Hindmarch Landscape Ltd",
    "wof:placetype":"venue"
},
  "geometry": {"coordinates":[-82.328712,43.007065],"type":"Point"}
}