{
  "type": "Feature",
  "properties": {
    "addr:full":"1090 Cummings Ave Gloucester ON K1J 7R8",
    "addr:housenumber":"1090",
    "addr:postcode":"k1j 7r8",
    "addr:street":"Cummings Ave",
    "iso:country":"CA",
    "sg:address":"1090 Cummings Ave",
    "sg:city":"Gloucester",
    "sg:classifiers":[
        {
            "category":"Retail",
            "subcategory":"Auto Repair",
            "type":"Services"
        }
    ],
    "sg:phone":"+1 613 745 7448",
    "sg:postcode":"K1J 7R8",
    "sg:province":"ON",
    "sg:tags":[
        "body",
        "automobile",
        "painting"
    ],
    "wof:name":"Belko Auto Body Ltd",
    "wof:placetype":"venue"
},
  "geometry": {"coordinates":[-75.63394927980001,45.4299812317],"type":"Point"}
}