{
  "type": "Feature",
  "properties": {
    "addr:full":"906 Bloor St W Toronto ON M6H 1L1",
    "addr:housenumber":"906",
    "addr:postcode":"m6h 1l1",
    "addr:street":"Bloor St W",
    "iso:country":"CA",
    "sg:address":"906 Bloor St W",
    "sg:city":"Toronto",
    "sg:classifiers":[
        {
            "category":"Wholesale",
            "subcategory":"Meat",
            "type":"Manufacturing & Wholesale Goods"
        }
    ],
    "sg:phone":"+1 416 531 2522",
    "sg:postcode":"M6H 1L1",
    "sg:province":"ON",
    "sg:tags":[
        "butchering"
    ],
    "wof:name":"Macelleria Venezia Butcher Shp",
    "wof:placetype":"venue"
},
  "geometry": {"coordinates":[-79.426292,43.66198],"type":"Point"}
}