{
  "type": "Feature",
  "properties": {
    "addr:full":"321 Rawdon St Brantford ON N3S 6H7",
    "addr:housenumber":"321",
    "addr:postcode":"n3s 6h7",
    "addr:street":"Rawdon St",
    "iso:country":"CA",
    "sg:address":"321 Rawdon St",
    "sg:city":"Brantford",
    "sg:classifiers":[
        {
            "category":"Organizations",
            "subcategory":"Non-profit Organization",
            "type":"Services"
        }
    ],
    "sg:phone":"+1 519 752 2000",
    "sg:postcode":"N3S 6H7",
    "sg:province":"ON",
    "sg:tags":[
        "disability"
    ],
    "wof:name":"Tara L Hooper & Assoc",
    "wof:placetype":"venue"
},
  "geometry": {"coordinates":[-80.2487487793,43.1487236023],"type":"Point"}
}