{
  "type": "Feature",
  "properties": {
    "addr:full":"185 Adesso Dr Concord ON L4K 3C4",
    "addr:housenumber":"185",
    "addr:postcode":"l4k 3c4",
    "addr:street":"Adesso Dr",
    "iso:country":"CA",
    "sg:address":"185 Adesso Dr",
    "sg:city":"Concord",
    "sg:classifiers":[
        {
            "category":"Building & Trades",
            "subcategory":"Construction",
            "type":"Services"
        }
    ],
    "sg:phone":"+1 905 669 9481",
    "sg:postcode":"L4K 3C4",
    "sg:province":"ON",
    "sg:tags":[
        "contractor"
    ],
    "wof:name":"Belrock Construction Ltd",
    "wof:placetype":"venue"
},
  "geometry": {"coordinates":[-79.5311050415,43.7765426636],"type":"Point"}
}