{
  "type": "Feature",
  "properties": {
    "addr:full":"255 Indian Rd S Sarnia ON N7T 3W5",
    "addr:housenumber":"255",
    "addr:postcode":"n7t 3w5",
    "addr:street":"Indian Rd S",
    "iso:country":"CA",
    "sg:address":"255 Indian Rd S",
    "sg:city":"Sarnia",
    "sg:classifiers":[
        {
            "category":"Autos & Motor Vehicles",
            "subcategory":"Automobile Sales",
            "type":"Retail Goods"
        }
    ],
    "sg:phone":"+1 519 337 7561",
    "sg:postcode":"N7T 3W5",
    "sg:province":"ON",
    "sg:tags":[
        "car",
        "dealer"
    ],
    "wof:name":"Bayview Chrysler Dodge Ltd",
    "wof:placetype":"venue"
},
  "geometry": {"coordinates":[-82.376465,42.963345],"type":"Point"}
}