{
  "type": "Feature",
  "properties": {
    "iso:country":"CA",
    "sg:address":"20 Rue Viger",
    "sg:city":"Kirkland",
    "sg:classifiers":[
        {
            "category":"Parking",
            "type":"Transportation"
        }
    ],
    "sg:phone":"+1 514 866 1971",
    "sg:postcode":"H9J 2E5",
    "sg:province":"QC",
    "sg:tags":[
        "garage",
        "traffic",
        "consultant"
    ],
    "wof:name":"Stationnement Metropolitain",
    "wof:placetype":"venue"
},
  "geometry": {"coordinates":[-73.857178,45.445385],"type":"Point"}
}