{
  "type": "Feature",
  "properties": {
    "addr:full":"116 Prescott Kemptville ON K0G 1J0",
    "addr:housenumber":"116",
    "addr:postcode":"k0g 1j0",
    "addr:street":"Prescott",
    "iso:country":"CA",
    "sg:address":"116 Prescott",
    "sg:city":"Kemptville",
    "sg:classifiers":[
        {
            "category":"Banks & Credit Unions",
            "subcategory":"Bank",
            "type":"Services"
        }
    ],
    "sg:phone":"+1 613 258 3491",
    "sg:postcode":"K0G 1J0",
    "sg:province":"ON",
    "wof:name":"Cibc",
    "wof:placetype":"venue"
},
  "geometry": {"coordinates":[-75.64534759519999,45.0156021118],"type":"Point"}
}