{
  "type": "Feature",
  "properties": {
    "addr:full":"Milton ON L9T 1Y8",
    "addr:postcode":"l9t 1y8",
    "iso:country":"CA",
    "sg:city":"Milton",
    "sg:classifiers":[
        {
            "category":"Real Estate",
            "subcategory":"Real Estate Operator",
            "type":"Services"
        }
    ],
    "sg:phone":"+1 905 878 5375",
    "sg:postcode":"L9T 1Y8",
    "sg:province":"ON",
    "sg:tags":[
        "apartment"
    ],
    "wof:name":"Glen Eden Court Apartments",
    "wof:placetype":"venue"
},
  "geometry": {"coordinates":[-79.88488769529999,43.5059776306],"type":"Point"}
}