{
  "type": "Feature",
  "properties": {
    "addr:full":"454 Poonamalie Rd N Smiths Falls ON K7A 4S4",
    "addr:housenumber":"454",
    "addr:postcode":"k7a 4s4",
    "addr:street":"Poonamalie Rd N",
    "iso:country":"CA",
    "sg:address":"454 Poonamalie Rd N",
    "sg:city":"Smiths Falls",
    "sg:classifiers":[
        {
            "category":"Wholesale",
            "subcategory":"Electrical",
            "type":"Manufacturing & Wholesale Goods"
        }
    ],
    "sg:phone":"+1 613 283 6022",
    "sg:postcode":"K7A 4S4",
    "sg:province":"ON",
    "sg:tags":[
        "electric",
        "motor"
    ],
    "wof:name":"B W Storey Electric Motor Rprs",
    "wof:placetype":"venue"
},
  "geometry": {"coordinates":[-76.02151499999999,44.902584],"type":"Point"}
}