{
  "type": "Feature",
  "properties": {
    "addr:full":"339 Rue Roy N Weedon QC J0B 3J0",
    "addr:housenumber":"339",
    "addr:postcode":"j0b 3j0",
    "addr:street":"Rue Roy N",
    "iso:country":"CA",
    "sg:address":"339 Rue Roy N",
    "sg:city":"Weedon",
    "sg:classifiers":[
        {
            "category":"Health Services",
            "subcategory":"Nursing And Care Facility",
            "type":"Services"
        }
    ],
    "sg:phone":"+1 819 877 2032",
    "sg:postcode":"J0B 3J0",
    "sg:province":"QC",
    "sg:tags":[
        "home",
        "retirement",
        "community",
        "rest"
    ],
    "wof:name":"Pavillion St-Gerard Inc",
    "wof:placetype":"venue"
},
  "geometry": {"coordinates":[-71.415352,45.760433],"type":"Point"}
}