{
  "type": "Feature",
  "properties": {
    "addr:full":"290 Glendale Ave St Catharines ON L2T 2L3",
    "addr:housenumber":"290",
    "addr:postcode":"l2t 2l3",
    "addr:street":"Glendale Ave",
    "iso:country":"CA",
    "sg:address":"290 Glendale Ave",
    "sg:city":"St Catharines",
    "sg:classifiers":[
        {
            "category":"Health Services",
            "subcategory":"Chiropractor",
            "type":"Services"
        }
    ],
    "sg:phone":"+1 905 227 4411",
    "sg:postcode":"L2T 2L3",
    "sg:province":"ON",
    "wof:name":"Glendale Chiropractic Clinic",
    "wof:placetype":"venue"
},
  "geometry": {"coordinates":[-79.2174453735,43.1356086731],"type":"Point"}
}