{
  "type": "Feature",
  "properties": {
    "addr:full":"1488 Main St Stittsville ON K2S 1A7",
    "addr:housenumber":"1488",
    "addr:postcode":"k2s 1a7",
    "addr:street":"Main St",
    "iso:country":"CA",
    "sg:address":"1488 Main St",
    "sg:city":"Stittsville",
    "sg:classifiers":[
        {
            "category":"Manufacturing",
            "subcategory":"Printing",
            "type":"Manufacturing & Wholesale Goods"
        }
    ],
    "sg:phone":"+1 613 836 1357",
    "sg:postcode":"K2S 1A7",
    "sg:province":"ON",
    "sg:tags":[
        "newspaper"
    ],
    "wof:name":"Stittsville News",
    "wof:placetype":"venue"
},
  "geometry": {"coordinates":[-75.927216,45.263855],"type":"Point"}
}