{
  "type": "Feature",
  "properties": {
    "iso:country":"CA",
    "sg:address":"904 King St E",
    "sg:city":"Hamilton",
    "sg:classifiers":[
        {
            "category":"Health Services",
            "subcategory":"Nursing And Care Facility",
            "type":"Services"
        }
    ],
    "sg:phone":"+1 905 549 2536",
    "sg:postcode":"L8M 1B7",
    "sg:province":"ON",
    "sg:tags":[
        "home",
        "retirement",
        "community"
    ],
    "wof:name":"Maplecrest Manor",
    "wof:placetype":"venue"
},
  "geometry": {"coordinates":[-79.8392791748,43.2511711121],"type":"Point"}
}