{
  "type": "Feature",
  "properties": {
    "addr:full":"29 Walker St Truro NS B2N 4A5",
    "addr:housenumber":"29",
    "addr:postcode":"b2n 4a5",
    "addr:street":"Walker St",
    "iso:country":"CA",
    "sg:address":"29 Walker St",
    "sg:city":"Truro",
    "sg:classifiers":[
        {
            "category":"Restaurant",
            "type":"Food & Drink"
        }
    ],
    "sg:phone":"+1 902 897 1214",
    "sg:postcode":"B2N 4A5",
    "sg:province":"NS",
    "wof:name":"Mc Donald's",
    "wof:placetype":"venue"
},
  "geometry": {"coordinates":[-63.272556,45.366741],"type":"Point"}
}