{
  "type": "Feature",
  "properties": {
    "addr:full":"Dartmouth NS B3B 1T7",
    "addr:postcode":"b3b 1t7",
    "iso:country":"CA",
    "sg:city":"Dartmouth",
    "sg:classifiers":[
        {
            "category":"Freight",
            "type":"Transportation"
        }
    ],
    "sg:phone":"+1 902 468 1820",
    "sg:postcode":"B3B 1T7",
    "sg:province":"NS",
    "sg:tags":[
        "delivery",
        "courier"
    ],
    "wof:name":"New Century Courier",
    "wof:placetype":"venue"
},
  "geometry": {"coordinates":[-63.5897064209,44.703704834],"type":"Point"}
}