{
  "type": "Feature",
  "properties": {
    "addr:full":"29 Centre St W Richmond Hill ON L4C 3P3",
    "addr:housenumber":"29",
    "addr:postcode":"l4c 3p3",
    "addr:street":"Centre St W",
    "iso:country":"CA",
    "sg:address":"29 Centre St W",
    "sg:city":"Richmond Hill",
    "sg:classifiers":[
        {
            "category":"Health Services",
            "subcategory":"Doctor",
            "type":"Services"
        }
    ],
    "sg:phone":"+1 905 883 9054",
    "sg:postcode":"L4C 3P3",
    "sg:province":"ON",
    "sg:tags":[
        "physician",
        "surgeon"
    ],
    "wof:name":"Zelina, P I MD",
    "wof:placetype":"venue"
},
  "geometry": {"coordinates":[-79.43955200000001,43.875744],"type":"Point"}
}