{
  "type": "Feature",
  "properties": {
    "addr:full":"Winnipeg MB R3Y 1V8",
    "addr:postcode":"r3y 1v8",
    "iso:country":"CA",
    "sg:city":"Winnipeg",
    "sg:classifiers":[
        {
            "category":"Food & Beverages",
            "subcategory":"Specialty",
            "type":"Retail Goods"
        }
    ],
    "sg:phone":"+1 204 984 9558",
    "sg:postcode":"R3Y 1V8",
    "sg:province":"MB",
    "sg:tags":[
        "health",
        "diet"
    ],
    "wof:name":"Vita Health Natural Food Store",
    "wof:placetype":"venue"
},
  "geometry": {"coordinates":[-97.1982498169,49.8181686401],"type":"Point"}
}