{
  "type": "Feature",
  "properties": {
    "addr:full":"391 Boul Des Prairies Laval QC H7N 2W4",
    "addr:housenumber":"391",
    "addr:postcode":"h7n 2w4",
    "addr:street":"Boul Des Prairies",
    "iso:country":"CA",
    "sg:address":"391 Boul Des Prairies",
    "sg:city":"Laval",
    "sg:classifiers":[
        {
            "category":"Shopping",
            "subcategory":"Pharmacy",
            "type":"Retail Goods"
        }
    ],
    "sg:phone":"+1 450 975 9667",
    "sg:postcode":"H7N 2W4",
    "sg:province":"QC",
    "wof:name":"Pharmacie Shefteshy Francis",
    "wof:placetype":"venue"
},
  "geometry": {"coordinates":[-73.7086486816,45.5462875366],"type":"Point"}
}