{
  "type": "Feature",
  "properties": {
    "addr:full":"55 Church Elora ON N0B 1S0",
    "addr:housenumber":"55",
    "addr:postcode":"n0b 1s0",
    "addr:street":"Church Elora",
    "iso:country":"CA",
    "sg:address":"55 Church",
    "sg:city":"Elora",
    "sg:classifiers":[
        {
            "category":"Organizations",
            "subcategory":"Religious Organization",
            "type":"Services"
        }
    ],
    "sg:phone":"+1 519 846 0680",
    "sg:postcode":"N0B 1S0",
    "sg:province":"ON",
    "sg:tags":[
        "church"
    ],
    "wof:name":"Knox Presbyterian Church",
    "wof:placetype":"venue"
},
  "geometry": {"coordinates":[-80.42821499999999,43.683292],"type":"Point"}
}