{
  "type": "Feature",
  "properties": {
    "addr:full":"351 Rue Visitation Upton QC J0H 2E0",
    "addr:housenumber":"351",
    "addr:postcode":"j0h 2e0",
    "addr:street":"Rue Visitation",
    "iso:country":"CA",
    "sg:address":"351 Rue Visitation",
    "sg:city":"Upton",
    "sg:classifiers":[
        {
            "category":"Personal",
            "subcategory":"Beauty Salon",
            "type":"Services"
        }
    ],
    "sg:phone":"+1 450 549 5395",
    "sg:postcode":"J0H 2E0",
    "sg:province":"QC",
    "wof:name":"Salon LA Bellacoiffure Enr",
    "wof:placetype":"venue"
},
  "geometry": {"coordinates":[-72.693207,45.650249],"type":"Point"}
}