{
  "type": "Feature",
  "properties": {
    "addr:full":"Winnipeg MB R3C 1C7",
    "addr:postcode":"r3c 1c7",
    "iso:country":"CA",
    "sg:city":"Winnipeg",
    "sg:classifiers":[
        {
            "category":"Professional",
            "subcategory":"Engineering",
            "type":"Services"
        }
    ],
    "sg:phone":"+1 204 943 6142",
    "sg:postcode":"R3C 1C7",
    "sg:province":"MB",
    "sg:tags":[
        "engineer"
    ],
    "wof:name":"Nova 3 Consulting Engineers",
    "wof:placetype":"venue"
},
  "geometry": {"coordinates":[-97.136848,49.889141],"type":"Point"}
}