{
  "type": "Feature",
  "properties": {
    "addr:full":"528 Oakpark Dr Windsor ON N8N 4P2",
    "addr:housenumber":"528",
    "addr:postcode":"n8n 4p2",
    "addr:street":"Oakpark Dr",
    "iso:country":"CA",
    "sg:address":"528 Oakpark Dr",
    "sg:city":"Windsor",
    "sg:classifiers":[
        {
            "category":"Organizations",
            "subcategory":"Membership Organization",
            "type":"Services"
        }
    ],
    "sg:phone":"+1 519 739 1061",
    "sg:postcode":"N8N 4P2",
    "sg:province":"ON",
    "wof:name":"Windsor Fc National Soccer",
    "wof:placetype":"venue"
},
  "geometry": {"coordinates":[-83.033913,42.317822],"type":"Point"}
}