{
  "type": "Feature",
  "properties": {
    "iso:country":"CA",
    "sg:address":"674 Athabasca St W",
    "sg:city":"Moose Jaw",
    "sg:classifiers":[
        {
            "category":"Food & Beverages",
            "subcategory":"Meat & Fish",
            "type":"Retail Goods"
        }
    ],
    "sg:phone":"+1 306 692 3823",
    "sg:postcode":"S6H 2C8",
    "sg:province":"SK",
    "sg:tags":[
        "grocer"
    ],
    "wof:name":"Maple Leaf Grocery",
    "wof:placetype":"venue"
},
  "geometry": {"coordinates":[-105.551208496,50.3954696655],"type":"Point"}
}