{
  "type": "Feature",
  "properties": {
    "iso:country":"CA",
    "sg:address":"235 Montee Lesage",
    "sg:city":"Rosemere",
    "sg:classifiers":[
        {
            "category":"Education",
            "subcategory":"School",
            "type":"Public Place"
        }
    ],
    "sg:phone":"+1 450 621 5600",
    "sg:postcode":"J7A 4Y6",
    "sg:province":"QC",
    "wof:name":"Commission Scolaire Sir",
    "wof:placetype":"venue"
},
  "geometry": {"coordinates":[-73.783173,45.647411],"type":"Point"}
}