{
  "type": "Feature",
  "properties": {
    "addr:full":"1721 University Ave W Windsor ON N9B 1C5",
    "addr:housenumber":"1721",
    "addr:postcode":"n9b 1c5",
    "addr:street":"University Ave W",
    "iso:country":"CA",
    "sg:address":"1721 University Ave W",
    "sg:city":"Windsor",
    "sg:classifiers":[
        {
            "category":"Shopping",
            "subcategory":"Discount & Variety Stores",
            "type":"Retail Goods"
        }
    ],
    "sg:phone":"+1 519 258 4133",
    "sg:postcode":"N9B 1C5",
    "sg:province":"ON",
    "sg:tags":[
        "grocer"
    ],
    "wof:name":"Select Express Mart",
    "wof:placetype":"venue"
},
  "geometry": {"coordinates":[-83.059181,42.311516],"type":"Point"}
}