{
  "type": "Feature",
  "properties": {
    "addr:full":"152 Sparkhall Ave Toronto ON M4K 1G8",
    "addr:housenumber":"152",
    "addr:postcode":"m4k 1g8",
    "addr:street":"Sparkhall Ave",
    "iso:country":"CA",
    "sg:address":"152 Sparkhall Ave",
    "sg:city":"Toronto",
    "sg:classifiers":[
        {
            "category":"Building & Trades",
            "subcategory":"Construction",
            "type":"Services"
        }
    ],
    "sg:phone":"+1 416 466 5172",
    "sg:postcode":"M4K 1G8",
    "sg:province":"ON",
    "sg:tags":[
        "contractor"
    ],
    "wof:name":"Creative Communities",
    "wof:placetype":"venue"
},
  "geometry": {"coordinates":[-79.34880099999999,43.672504],"type":"Point"}
}