{
  "type": "Feature",
  "properties": {
    "iso:country":"CA",
    "sg:address":"152 Sparkhall Ave",
    "sg:city":"Toronto",
    "sg:classifiers":[
        {
            "category":"Building & Trades",
            "subcategory":"Construction",
            "type":"Services"
        }
    ],
    "sg:phone":"+1 416 466 5172",
    "sg:postcode":"M4K 1G8",
    "sg:province":"ON",
    "sg:tags":[
        "contractor"
    ],
    "wof:name":"Creative Communities",
    "wof:placetype":"venue"
},
  "geometry": {"coordinates":[-79.348801,43.672504],"type":"Point"}
}