{
  "type": "Feature",
  "properties": {
    "addr:full":"8 Main St E Hamilton ON L8N 1E8",
    "addr:housenumber":"8",
    "addr:postcode":"l8n 1e8",
    "addr:street":"Main St E",
    "iso:country":"CA",
    "sg:address":"8 Main St E",
    "sg:city":"Hamilton",
    "sg:classifiers":[
        {
            "category":"Building & Trades",
            "subcategory":"Electrical",
            "type":"Services"
        }
    ],
    "sg:phone":"+1 905 526 9021",
    "sg:postcode":"L8N 1E8",
    "sg:province":"ON",
    "sg:tags":[
        "electric",
        "contractor"
    ],
    "wof:name":"Victor Electric & Equipment",
    "wof:placetype":"venue"
},
  "geometry": {"coordinates":[-79.8693695068,43.2551574707],"type":"Point"}
}