{
  "type": "Feature",
  "properties": {
    "addr:full":"RR 1 Palmerston ON N0G 2P0",
    "addr:postcode":"n0g 2p0",
    "addr:street":"Rr 1",
    "iso:country":"CA",
    "sg:address":"RR 1",
    "sg:city":"Palmerston",
    "sg:classifiers":[
        {
            "category":"Wholesale",
            "subcategory":"Machinery & Supplies",
            "type":"Manufacturing & Wholesale Goods"
        }
    ],
    "sg:phone":"+1 519 343 5477",
    "sg:postcode":"N0G 2P0",
    "sg:province":"ON",
    "sg:tags":[
        "farm",
        "equipment"
    ],
    "wof:name":"Tevoitdale Farm Supplies",
    "wof:placetype":"venue"
},
  "geometry": {"coordinates":[-80.8475570679,43.8344345093],"type":"Point"}
}