{
  "type": "Feature",
  "properties": {
    "addr:full":"418 Alpha Terr Victoria BC V8Z 1B6",
    "addr:housenumber":"418",
    "addr:postcode":"v8z 1b6",
    "addr:street":"Alpha Terr",
    "iso:country":"CA",
    "sg:address":"418 Alpha Terr",
    "sg:city":"Victoria",
    "sg:classifiers":[
        {
            "category":"Building & Trades",
            "subcategory":"Plumbing",
            "type":"Services"
        }
    ],
    "sg:phone":"+1 250 383 6484",
    "sg:postcode":"V8Z 1B6",
    "sg:province":"BC",
    "sg:tags":[
        "heating",
        "refrigerating",
        "contractor"
    ],
    "wof:name":"Victoria Refrigeration Ltd",
    "wof:placetype":"venue"
},
  "geometry": {"coordinates":[-123.37849426299999,48.4467468262],"type":"Point"}
}