{
  "type": "Feature",
  "properties": {
    "addr:full":"128 Erith Dr Hinton AB T7V 1P4",
    "addr:housenumber":"128",
    "addr:postcode":"t7v 1p4",
    "addr:street":"Erith Dr",
    "iso:country":"CA",
    "sg:address":"128 Erith Dr",
    "sg:city":"Hinton",
    "sg:classifiers":[
        {
            "category":"Building & Trades",
            "subcategory":"Plumbing",
            "type":"Services"
        }
    ],
    "sg:phone":"+1 780 865 2100",
    "sg:postcode":"T7V 1P4",
    "sg:province":"AB",
    "sg:tags":[
        "fitter",
        "gas"
    ],
    "wof:name":"Cardinal River Plbg & Heat Ltd",
    "wof:placetype":"venue"
},
  "geometry": {"coordinates":[-117.597672,53.395767],"type":"Point"}
}