{
  "type": "Feature",
  "properties": {
    "addr:full":"209 Bowen Rd Fort Erie ON L2A 2Y6",
    "addr:housenumber":"209",
    "addr:postcode":"l2a 2y6",
    "addr:street":"Bowen Rd",
    "iso:country":"CA",
    "sg:address":"209 Bowen Rd",
    "sg:city":"Fort Erie",
    "sg:classifiers":[
        {
            "category":"Real Estate",
            "subcategory":"Real Estate Agent",
            "type":"Services"
        }
    ],
    "sg:phone":"+1 905 871 5325",
    "sg:postcode":"L2A 2Y6",
    "sg:province":"ON",
    "sg:tags":[
        "management"
    ],
    "wof:name":"Consolidated Property Mgmt",
    "wof:placetype":"venue"
},
  "geometry": {"coordinates":[-78.9199142456,42.9350204468],"type":"Point"}
}