{
  "type": "Feature",
  "properties": {
    "addr:full":"15 Mcchesney Ave Kirkland Lake ON P2N 3R9",
    "addr:housenumber":"15",
    "addr:postcode":"p2n 3r9",
    "addr:street":"Mcchesney Ave",
    "iso:country":"CA",
    "sg:address":"15 Mcchesney Ave",
    "sg:city":"Kirkland Lake",
    "sg:classifiers":[
        {
            "category":"Shopping",
            "subcategory":"Pharmacy",
            "type":"Retail Goods"
        }
    ],
    "sg:phone":"+1 705 567 4941",
    "sg:postcode":"P2N 3R9",
    "sg:province":"ON",
    "wof:name":"Drug Store Pharmacy",
    "wof:placetype":"venue"
},
  "geometry": {"coordinates":[-80.0430984497,48.1469154358],"type":"Point"}
}