{
  "type": "Feature",
  "properties": {
    "addr:full":"Sunset House AB T0H 3H0",
    "addr:postcode":"t0h 3h0",
    "iso:country":"CA",
    "sg:city":"Sunset House",
    "sg:classifiers":[
        {
            "category":"Education",
            "subcategory":"School",
            "type":"Public Place"
        }
    ],
    "sg:phone":"+1 780 524 2425",
    "sg:postcode":"T0H 3H0",
    "sg:province":"AB",
    "wof:name":"Sunset House School",
    "wof:placetype":"venue"
},
  "geometry": {"coordinates":[-116.899406,55.09787],"type":"Point"}
}