{
  "type": "Feature",
  "properties": {
    "addr:full":"118 Route 935 Westcock NB E4L 2G9",
    "addr:housenumber":"118",
    "addr:postcode":"e4l 2g9",
    "addr:street":"Route 935",
    "iso:country":"CA",
    "sg:address":"118 Route 935",
    "sg:city":"Westcock",
    "sg:classifiers":[
        {
            "category":"Retail",
            "subcategory":"Auto Repair",
            "type":"Services"
        }
    ],
    "sg:phone":"+1 506 536 0532",
    "sg:postcode":"E4L 2G9",
    "sg:province":"NB",
    "sg:tags":[
        "wrecker"
    ],
    "wof:name":"Atlantic Towing & Radiator Wrk",
    "wof:placetype":"venue"
},
  "geometry": {"coordinates":[-64.36982,45.869663],"type":"Point"}
}