{
  "type": "Feature",
  "properties": {
    "addr:full":"Westmount QC H3Z 2M6",
    "addr:postcode":"h3z 2m6",
    "iso:country":"CA",
    "sg:city":"Westmount",
    "sg:classifiers":[
        {
            "category":"Health Services",
            "subcategory":"Health Practitioner",
            "type":"Services"
        }
    ],
    "sg:phone":"+1 514 933 9781",
    "sg:postcode":"H3Z 2M6",
    "sg:province":"QC",
    "sg:tags":[
        "psychologist"
    ],
    "wof:name":"Rothenberg, Pearl",
    "wof:placetype":"venue"
},
  "geometry": {"coordinates":[-73.59940338129999,45.4772224426],"type":"Point"}
}