{
  "type": "Feature",
  "properties": {
    "addr:full":"1989 St Joseph Blvd Orleans ON K1C 1E5",
    "addr:housenumber":"1989",
    "addr:postcode":"k1c 1e5",
    "addr:street":"St Joseph Blvd",
    "iso:country":"CA",
    "sg:address":"1989 St Joseph Blvd",
    "sg:city":"Orleans",
    "sg:classifiers":[
        {
            "category":"Professional",
            "subcategory":"Advertising",
            "type":"Services"
        }
    ],
    "sg:phone":"+1 613 824 8441",
    "sg:postcode":"K1C 1E5",
    "sg:province":"ON",
    "sg:tags":[
        "guide"
    ],
    "wof:name":"Magnetouch Media Inc",
    "wof:placetype":"venue"
},
  "geometry": {"coordinates":[-75.539146,45.464756],"type":"Point"}
}