{
  "type": "Feature",
  "properties": {
    "iso:country":"CA",
    "sg:address":"5 Wall St",
    "sg:city":"Brockville",
    "sg:classifiers":[
        {
            "category":"Organizations",
            "subcategory":"Religious Organization",
            "type":"Services"
        }
    ],
    "sg:phone":"+1 613 342 5401",
    "sg:postcode":"K6V 4R8",
    "sg:province":"ON",
    "sg:tags":[
        "church"
    ],
    "wof:name":"Wall Street United Church",
    "wof:placetype":"venue"
},
  "geometry": {"coordinates":[-75.6848373413,44.5907821655],"type":"Point"}
}