{
  "type": "Feature",
  "properties": {
    "addr:full":"8692 Highway 9 Tottenham ON L0G 1W0",
    "addr:housenumber":"8692",
    "addr:postcode":"l0g 1w0",
    "addr:street":"Highway 9 Tottenham",
    "iso:country":"CA",
    "sg:address":"8692 Highway 9",
    "sg:city":"Tottenham",
    "sg:classifiers":[
        {
            "category":"Wholesale",
            "subcategory":"Auto Parts",
            "type":"Manufacturing & Wholesale Goods"
        }
    ],
    "sg:phone":"+1 905 936 4943",
    "sg:postcode":"L0G 1W0",
    "sg:province":"ON",
    "sg:tags":[
        "automobile",
        "rebuilt",
        "wrecking"
    ],
    "wof:name":"Number 9 Auto & Truck Wreckers",
    "wof:placetype":"venue"
},
  "geometry": {"coordinates":[-79.805786,44.022877],"type":"Point"}
}