{
  "type": "Feature",
  "properties": {
    "addr:full":"668 101 Rte S Saint-Bruno-DE-Guigues QC J0Z 2G0",
    "addr:housenumber":"101",
    "addr:postcode":"j0z 2g0",
    "addr:street":"Rte S Saint-Bruno-De-Guigues",
    "iso:country":"CA",
    "sg:address":"668 101 Rte S",
    "sg:city":"Saint-Bruno-DE-Guigues",
    "sg:classifiers":[
        {
            "category":"Wholesale",
            "subcategory":"Machinery & Supplies",
            "type":"Manufacturing & Wholesale Goods"
        }
    ],
    "sg:phone":"+1 819 728 2323",
    "sg:postcode":"J0Z 2G0",
    "sg:province":"QC",
    "sg:tags":[
        "farm",
        "equipment"
    ],
    "wof:name":"Machineries M Larose Ltee",
    "wof:placetype":"venue"
},
  "geometry": {"coordinates":[-79.4377670288,47.4538383484],"type":"Point"}
}