{
  "type": "Feature",
  "properties": {
    "addr:full":"5400 Boul Couture Saint-Leonard QC H1R 1C7",
    "addr:housenumber":"5400",
    "addr:postcode":"h1r 1c7",
    "addr:street":"Boul Couture",
    "iso:country":"CA",
    "sg:address":"5400 Boul Couture",
    "sg:city":"Saint-Leonard",
    "sg:classifiers":[
        {
            "category":"Education",
            "subcategory":"School",
            "type":"Public Place"
        }
    ],
    "sg:phone":"+1 514 321 9234",
    "sg:postcode":"H1R 1C7",
    "sg:province":"QC",
    "wof:name":"Victor Lavigne Ecoles",
    "wof:placetype":"venue"
},
  "geometry": {"coordinates":[-73.6107635498,45.5929641724],"type":"Point"}
}