{
  "type": "Feature",
  "properties": {
    "addr:full":"409 Rue Montcalm Saint-Joseph-DE-Sorel QC J3R 1C5",
    "addr:housenumber":"409",
    "addr:postcode":"j3r 1c5",
    "addr:street":"Rue Montcalm",
    "iso:country":"CA",
    "sg:address":"409 Rue Montcalm",
    "sg:city":"Saint-Joseph-DE-Sorel",
    "sg:classifiers":[
        {
            "category":"Personal",
            "subcategory":"Beauty Salon",
            "type":"Services"
        }
    ],
    "sg:phone":"+1 450 743 4564",
    "sg:postcode":"J3R 1C5",
    "sg:province":"QC",
    "wof:name":"Salon Diane",
    "wof:placetype":"venue"
},
  "geometry": {"coordinates":[-73.123856,46.042717],"type":"Point"}
}