{
  "type": "Feature",
  "properties": {
    "addr:full":"Sainte-Henedine QC G0S 2R0",
    "addr:postcode":"g0s 2r0",
    "iso:country":"CA",
    "sg:city":"Sainte-Henedine",
    "sg:classifiers":[
        {
            "category":"Autos & Motor Vehicles",
            "subcategory":"Automobile Sales",
            "type":"Retail Goods"
        }
    ],
    "sg:phone":"+1 418 935 7219",
    "sg:postcode":"G0S 2R0",
    "sg:province":"QC",
    "sg:tags":[
        "parts",
        "snowmobile",
        "accessory"
    ],
    "wof:name":"Roy, Marius",
    "wof:placetype":"venue"
},
  "geometry": {"coordinates":[-70.980408,46.559746],"type":"Point"}
}