{
  "type": "Feature",
  "properties": {
    "addr:full":"896 Riverside Dr Timmins ON P4N 3W2",
    "addr:housenumber":"896",
    "addr:postcode":"p4n 3w2",
    "addr:street":"Riverside Dr",
    "iso:country":"CA",
    "sg:address":"896 Riverside Dr",
    "sg:city":"Timmins",
    "sg:classifiers":[
        {
            "category":"Education",
            "subcategory":"School",
            "type":"Public Place"
        }
    ],
    "sg:phone":"+1 705 267 1421",
    "sg:postcode":"P4N 3W2",
    "sg:province":"ON",
    "wof:name":"Conseil Scolaire Catholique",
    "wof:placetype":"venue"
},
  "geometry": {"coordinates":[-81.36275500000001,48.476582],"type":"Point"}
}