{
  "type": "Feature",
  "properties": {
    "iso:country":"CA",
    "sg:address":"295 Rue Chicoine",
    "sg:city":"Vaudreuil-Dorion",
    "sg:classifiers":[
        {
            "category":"Retail",
            "subcategory":"Auto Repair",
            "type":"Services"
        }
    ],
    "sg:phone":"+1 450 424 5767",
    "sg:postcode":"J7V 1Z2",
    "sg:province":"QC",
    "sg:tags":[
        "repairing",
        "automobile"
    ],
    "wof:name":"Garage Michel Bouffard",
    "wof:placetype":"venue"
},
  "geometry": {"coordinates":[-74.014275,45.380619],"type":"Point"}
}