{
  "type": "Feature",
  "properties": {
    "addr:full":"7282 Kingsway Burnaby BC V5E 1G3",
    "addr:housenumber":"7282",
    "addr:postcode":"v5e 1g3",
    "addr:street":"Kingsway",
    "iso:country":"CA",
    "sg:address":"7282 Kingsway",
    "sg:city":"Burnaby",
    "sg:classifiers":[
        {
            "category":"Recreation",
            "type":"Entertainment"
        }
    ],
    "sg:phone":"+1 604 525 1671",
    "sg:postcode":"V5E 1G3",
    "sg:province":"BC",
    "sg:tags":[
        "government",
        "hall",
        "auditorium"
    ],
    "wof:name":"Edmonds Community Ctr",
    "wof:placetype":"venue"
},
  "geometry": {"coordinates":[-122.95324707,49.21824646],"type":"Point"}
}