{
  "type": "Feature",
  "properties": {
    "addr:full":"6225 Av Godfrey Montreal QC H4B 1K3",
    "addr:housenumber":"6225",
    "addr:postcode":"h4b 1k3",
    "addr:street":"Av Godfrey",
    "iso:country":"CA",
    "sg:address":"6225 Av Godfrey",
    "sg:city":"Montreal",
    "sg:classifiers":[
        {
            "category":"Organizations",
            "subcategory":"Religious Organization",
            "type":"Services"
        }
    ],
    "sg:phone":"+1 514 486 4559",
    "sg:postcode":"H4B 1K3",
    "sg:province":"QC",
    "sg:tags":[
        "church"
    ],
    "wof:name":"Knox Crescent Kensington",
    "wof:placetype":"venue"
},
  "geometry": {"coordinates":[-73.62700700000001,45.468006],"type":"Point"}
}