{
  "type": "Feature",
  "properties": {
    "iso:country":"CA",
    "sg:address":"2632 Liruma Rd",
    "sg:city":"Mississauga",
    "sg:classifiers":[
        {
            "category":"Retail",
            "subcategory":"Veterinary Services",
            "type":"Services"
        }
    ],
    "sg:phone":"+1 905 822 9974",
    "sg:postcode":"L5K 1Z1",
    "sg:province":"ON",
    "sg:tags":[
        "veterinarian"
    ],
    "wof:name":"Glen Erin Animal Hospital",
    "wof:placetype":"venue"
},
  "geometry": {"coordinates":[-79.6716384888,43.5301055908],"type":"Point"}
}