{
  "type": "Feature",
  "properties": {
    "addr:full":"Ste-Catherine-DE-LA-J-Cartier QC G0A 3M0",
    "addr:postcode":"g0a 3m0",
    "iso:country":"CA",
    "sg:city":"Ste-Catherine-DE-LA-J-Cartier",
    "sg:classifiers":[
        {
            "category":"Travel",
            "subcategory":"Travel Agent",
            "type":"Entertainment"
        }
    ],
    "sg:phone":"+1 418 875 2555",
    "sg:postcode":"G0A 3M0",
    "sg:province":"QC",
    "sg:tags":[
        "bureau",
        "agency",
        "tours"
    ],
    "wof:name":"Agence DE Voyages Jacques",
    "wof:placetype":"venue"
},
  "geometry": {"coordinates":[-70.8497543335,48.3168296814],"type":"Point"}
}