{
  "type": "Feature",
  "properties": {
    "iso:country":"CA",
    "sg:address":"3415 Boul Dagenais O",
    "sg:city":"Laval",
    "sg:classifiers":[
        {
            "category":"Personal",
            "subcategory":"Beauty Salon",
            "type":"Services"
        }
    ],
    "sg:phone":"+1 450 625 4000",
    "sg:postcode":"H7P 4V9",
    "sg:province":"QC",
    "wof:name":"Metamorphose",
    "wof:placetype":"venue"
},
  "geometry": {"coordinates":[-73.808098,45.578411],"type":"Point"}
}