{
  "type": "Feature",
  "properties": {
    "addr:full":"18505 Forest Nursery Rd Prince George BC V2N 5Y7",
    "addr:housenumber":"18505",
    "addr:postcode":"v2n 5y7",
    "addr:street":"Forest Nursery Rd",
    "iso:country":"CA",
    "sg:address":"18505 Forest Nursery Rd",
    "sg:city":"Prince George",
    "sg:classifiers":[
        {
            "category":"Home & Garden",
            "subcategory":"Garden Supply",
            "type":"Retail Goods"
        }
    ],
    "sg:phone":"+1 250 963 9199",
    "sg:postcode":"V2N 5Y7",
    "sg:province":"BC",
    "sg:tags":[
        "nurseryman"
    ],
    "wof:name":"Prt-Red Rock Nursery",
    "wof:placetype":"venue"
},
  "geometry": {"coordinates":[-122.74508667000001,53.9123497009],"type":"Point"}
}