{
  "type": "Feature",
  "properties": {
    "addr:full":"624 Rue Shefford Bromont QC J2L 1C1",
    "addr:housenumber":"624",
    "addr:postcode":"j2l 1c1",
    "addr:street":"Rue Shefford",
    "iso:country":"CA",
    "sg:address":"624 Rue Shefford",
    "sg:city":"Bromont",
    "sg:classifiers":[
        {
            "category":"Food & Beverages",
            "subcategory":"Groceries & Convenience Stores",
            "type":"Retail Goods"
        }
    ],
    "sg:phone":"+1 450 534 2116",
    "sg:postcode":"J2L 1C1",
    "sg:province":"QC",
    "wof:name":"Depanneur Shefford Inc",
    "wof:placetype":"venue"
},
  "geometry": {"coordinates":[-72.6532363892,45.3190422058],"type":"Point"}
}