{
  "type": "Feature",
  "properties": {
    "addr:full":"Edmonton AB T5J 3N4",
    "addr:postcode":"t5j 3n4",
    "iso:country":"CA",
    "sg:city":"Edmonton",
    "sg:classifiers":[
        {
            "category":"Health Services",
            "subcategory":"Doctor",
            "type":"Services"
        }
    ],
    "sg:phone":"+1 780 425 1646",
    "sg:postcode":"T5J 3N4",
    "sg:province":"AB",
    "sg:tags":[
        "dentist"
    ],
    "wof:name":"Eguren, Juan C DDS",
    "wof:placetype":"venue"
},
  "geometry": {"coordinates":[-113.49949646,53.5408096313],"type":"Point"}
}