{
  "type": "Feature",
  "properties": {
    "iso:country":"CA",
    "sg:address":"1805 Rue Fleury E",
    "sg:city":"Montreal",
    "sg:classifiers":[
        {
            "category":"Government",
            "subcategory":"Police Station",
            "type":"Public Place"
        }
    ],
    "sg:phone":"+1 514 280 0128",
    "sg:postcode":"H2B 1H7",
    "sg:province":"QC",
    "sg:tags":[
        "department"
    ],
    "wof:name":"Montreal Police Dept",
    "wof:placetype":"venue"
},
  "geometry": {"coordinates":[-73.653465,45.568371],"type":"Point"}
}