{
  "type": "Feature",
  "properties": {
    "iso:country":"CA",
    "sg:address":"PO Box 8",
    "sg:city":"Richardson",
    "sg:classifiers":[
        {
            "category":"Wholesale",
            "subcategory":"Petroleum",
            "type":"Manufacturing & Wholesale Goods"
        }
    ],
    "sg:phone":"+1 306 352 2813",
    "sg:postcode":"S0G 4G0",
    "sg:province":"SK",
    "sg:tags":[
        "pipe",
        "line",
        "company"
    ],
    "wof:name":"Trans Canada Pipe Lines Ltd",
    "wof:placetype":"venue"
},
  "geometry": {"coordinates":[-104.457389831,50.3847541809],"type":"Point"}
}