{
  "type": "Feature",
  "properties": {
    "addr:full":"Oromocto NB E2V 1B8",
    "addr:postcode":"e2v 1b8",
    "iso:country":"CA",
    "sg:city":"Oromocto",
    "sg:classifiers":[
        {
            "category":"Shopping",
            "subcategory":"Clothing, Apparel, & Fashions",
            "type":"Retail Goods"
        }
    ],
    "sg:phone":"+1 506 357 8221",
    "sg:postcode":"E2V 1B8",
    "sg:province":"NB",
    "wof:name":"Reitmans",
    "wof:placetype":"venue"
},
  "geometry": {"coordinates":[-66.4770202637,45.8520011902],"type":"Point"}
}