{
  "type": "Feature",
  "properties": {
    "addr:full":"1401 Ernest Ave # 5 London ON N6E 2P6",
    "addr:housenumber":"1401",
    "addr:postcode":"n6e 2p6",
    "addr:street":"Ernest Ave # 5",
    "iso:country":"CA",
    "sg:address":"1401 Ernest Ave # 5",
    "sg:city":"London",
    "sg:classifiers":[
        {
            "category":"Personal",
            "subcategory":"Beauty Salon",
            "type":"Services"
        }
    ],
    "sg:phone":"+1 519 690 1331",
    "sg:postcode":"N6E 2P6",
    "sg:province":"ON",
    "wof:name":"Bradley Hair Express",
    "wof:placetype":"venue"
},
  "geometry": {"coordinates":[-81.236679,42.932636],"type":"Point"}
}