{
  "type": "Feature",
  "properties": {
    "addr:full":"1180 DE L'Eglise Ch Saint-Polycarpe QC J0P 1X0",
    "addr:housenumber":"1180",
    "addr:postcode":"j0p 1x0",
    "addr:street":"De L'Eglise Ch Saint-Polycarpe",
    "iso:country":"CA",
    "sg:address":"1180 DE L'Eglise Ch",
    "sg:city":"Saint-Polycarpe",
    "sg:classifiers":[
        {
            "category":"Wholesale",
            "subcategory":"Construction Materials",
            "type":"Manufacturing & Wholesale Goods"
        }
    ],
    "sg:phone":"+1 450 265 3447",
    "sg:postcode":"J0P 1X0",
    "sg:province":"QC",
    "sg:tags":[
        "sand",
        "gravel"
    ],
    "wof:name":"Chevrier Aurele",
    "wof:placetype":"venue"
},
  "geometry": {"coordinates":[-74.30639600000001,45.300701],"type":"Point"}
}