{
  "type": "Feature",
  "properties": {
    "addr:full":"3576 Novalea Dr Halifax NS B3K 3E8",
    "addr:housenumber":"3576",
    "addr:postcode":"b3k 3e8",
    "addr:street":"Novalea Dr",
    "iso:country":"CA",
    "sg:address":"3576 Novalea Dr",
    "sg:city":"Halifax",
    "sg:classifiers":[
        {
            "category":"Food & Beverages",
            "subcategory":"Groceries & Convenience Stores",
            "type":"Retail Goods"
        }
    ],
    "sg:phone":"+1 902 455 7245",
    "sg:postcode":"B3K 3E8",
    "sg:province":"NS",
    "sg:tags":[
        "grocer"
    ],
    "wof:name":"Freshmart",
    "wof:placetype":"venue"
},
  "geometry": {"coordinates":[-63.6077156067,44.668384552],"type":"Point"}
}