{
  "type": "Feature",
  "properties": {
    "addr:full":"3119 Rue Monsabre Montreal QC H1N 2L3",
    "addr:housenumber":"3119",
    "addr:postcode":"h1n 2l3",
    "addr:street":"Rue Monsabre",
    "iso:country":"CA",
    "sg:address":"3119 Rue Monsabre",
    "sg:city":"Montreal",
    "sg:classifiers":[
        {
            "category":"Organizations",
            "subcategory":"Professional Association",
            "type":"Services"
        }
    ],
    "sg:phone":"+1 514 256 7374",
    "sg:postcode":"H1N 2L3",
    "sg:province":"QC",
    "wof:name":"Jeunesse Ouvriere Chretienne",
    "wof:placetype":"venue"
},
  "geometry": {"coordinates":[-73.5447769165,45.5730361938],"type":"Point"}
}