{
  "type": "Feature",
  "properties": {
    "addr:full":"71 John St Napanee ON K7R 1P9",
    "addr:housenumber":"71",
    "addr:postcode":"k7r 1p9",
    "addr:street":"John St",
    "iso:country":"CA",
    "sg:address":"71 John St",
    "sg:city":"Napanee",
    "sg:classifiers":[
        {
            "category":"Food & Beverages",
            "subcategory":"Specialty",
            "type":"Retail Goods"
        }
    ],
    "sg:phone":"+1 613 354 4769",
    "sg:postcode":"K7R 1P9",
    "sg:province":"ON",
    "sg:tags":[
        "health",
        "diet"
    ],
    "wof:name":"Mainstay Natural Foods",
    "wof:placetype":"venue"
},
  "geometry": {"coordinates":[-76.94892120359999,44.2477989197],"type":"Point"}
}