{
  "type": "Feature",
  "properties": {
    "addr:full":"Harrison Hot Springs BC V0M 1K0",
    "addr:postcode":"v0m 1k0",
    "iso:country":"CA",
    "sg:city":"Harrison Hot Springs",
    "sg:classifiers":[
        {
            "category":"Shopping",
            "subcategory":"Gifts & Souvenirs",
            "type":"Retail Goods"
        }
    ],
    "sg:phone":"+1 604 796 5531",
    "sg:postcode":"V0M 1K0",
    "sg:province":"BC",
    "sg:tags":[
        "shop"
    ],
    "wof:name":"Serenity Now Gifts",
    "wof:placetype":"venue"
},
  "geometry": {"coordinates":[-121.786125,49.303322],"type":"Point"}
}