{
  "type": "Feature",
  "properties": {
    "iso:country":"CA",
    "sg:city":"Vancouver",
    "sg:classifiers":[
        {
            "category":"Education",
            "subcategory":"Vocational School",
            "type":"Public Place"
        }
    ],
    "sg:phone":"+1 604 683 7400",
    "sg:postcode":"V6C 1N5",
    "sg:province":"BC",
    "sg:tags":[
        "technical",
        "trade"
    ],
    "wof:name":"Sprott-Shaw Community Colleges",
    "wof:placetype":"venue"
},
  "geometry": {"coordinates":[-123.117881775,49.2848320007],"type":"Point"}
}