{
  "type": "Feature",
  "properties": {
    "addr:full":"505 Consumers Rd #401 North York ON M2J 4V8",
    "addr:housenumber":"505",
    "addr:postcode":"m2j 4v8",
    "addr:street":"Consumers Rd # 401",
    "iso:country":"CA",
    "sg:address":"505 Consumers Rd #401",
    "sg:city":"North York",
    "sg:classifiers":[
        {
            "category":"Manufacturing",
            "subcategory":"Printing",
            "type":"Manufacturing & Wholesale Goods"
        }
    ],
    "sg:phone":"+1 416 492 2711",
    "sg:postcode":"M2J 4V8",
    "sg:province":"ON",
    "sg:tags":[
        "printer"
    ],
    "wof:name":"Transcontinental Printing Inc",
    "wof:placetype":"venue"
},
  "geometry": {"coordinates":[-79.3242340088,43.7711410522],"type":"Point"}
}