{
  "type": "Feature",
  "properties": {
    "addr:full":"Sechelt BC V0N 3A0",
    "addr:postcode":"v0n 3a0",
    "iso:country":"CA",
    "sg:city":"Sechelt",
    "sg:classifiers":[
        {
            "category":"Retail",
            "subcategory":"Auto Rental",
            "type":"Services"
        }
    ],
    "sg:phone":"+1 604 885 6422",
    "sg:postcode":"V0N 3A0",
    "sg:province":"BC",
    "sg:tags":[
        "renting",
        "automobile"
    ],
    "wof:name":"Prime Time Rentals",
    "wof:placetype":"venue"
},
  "geometry": {"coordinates":[-123.75453949,49.4741516113],"type":"Point"}
}