{
  "type": "Feature",
  "properties": {
    "addr:full":"RR 3 STN Main Perth ON K7H 3C5",
    "addr:postcode":"k7h 3c5",
    "addr:street":"Rr 3 Stn",
    "iso:country":"CA",
    "sg:address":"RR 3 STN Main",
    "sg:city":"Perth",
    "sg:classifiers":[
        {
            "category":"Building & Trades",
            "subcategory":"Construction",
            "type":"Services"
        }
    ],
    "sg:phone":"+1 613 264 0124",
    "sg:postcode":"K7H 3C5",
    "sg:province":"ON",
    "sg:tags":[
        "excavating",
        "contractor"
    ],
    "wof:name":"Norris Sand & Gravel",
    "wof:placetype":"venue"
},
  "geometry": {"coordinates":[-76.248329,44.898945],"type":"Point"}
}