{
  "type": "Feature",
  "properties": {
    "addr:full":"Rigaud QC J0P 1P0",
    "addr:postcode":"j0p 1p0",
    "iso:country":"CA",
    "sg:city":"Rigaud",
    "sg:classifiers":[
        {
            "category":"Restaurant",
            "type":"Food & Drink"
        }
    ],
    "sg:phone":"+1 450 458 2066",
    "sg:postcode":"J0P 1P0",
    "sg:province":"QC",
    "wof:name":"Resto Express",
    "wof:placetype":"venue"
},
  "geometry": {"coordinates":[-74.22727999999999,45.461201],"type":"Point"}
}