{
  "type": "Feature",
  "properties": {
    "addr:full":"1339 Danforth Ave Toronto ON M4J 1N1",
    "addr:housenumber":"1339",
    "addr:postcode":"m4j 1n1",
    "addr:street":"Danforth Ave",
    "iso:country":"CA",
    "sg:address":"1339 Danforth Ave",
    "sg:city":"Toronto",
    "sg:classifiers":[
        {
            "category":"Retail",
            "subcategory":"Auto Repair",
            "type":"Services"
        }
    ],
    "sg:phone":"+1 416 778 0372",
    "sg:postcode":"M4J 1N1",
    "sg:province":"ON",
    "sg:tags":[
        "repairing",
        "automobile"
    ],
    "wof:name":"Pinpoint Auto Ctr",
    "wof:placetype":"venue"
},
  "geometry": {"coordinates":[-79.329033,43.682049],"type":"Point"}
}