{
  "type": "Feature",
  "properties": {
    "addr:full":"1489 Rue Sainte-Catherine E Montreal QC H2L 2H9",
    "addr:housenumber":"1489",
    "addr:postcode":"h2l 2h9",
    "addr:street":"Rue Sainte-Catherine E",
    "iso:country":"CA",
    "sg:address":"1489 Rue Sainte-Catherine E",
    "sg:city":"Montreal",
    "sg:classifiers":[
        {
            "category":"Shopping",
            "subcategory":"Shoes",
            "type":"Retail Goods"
        }
    ],
    "sg:phone":"+1 514 521 5050",
    "sg:postcode":"H2L 2H9",
    "sg:province":"QC",
    "wof:name":"Bunker Canada",
    "wof:placetype":"venue"
},
  "geometry": {"coordinates":[-73.55394699999999,45.52108],"type":"Point"}
}