{
  "type": "Feature",
  "properties": {
    "addr:full":"505 North Railway St SE Medicine Hat AB T1A 2Z4",
    "addr:housenumber":"505",
    "addr:postcode":"t1a 2z4",
    "addr:street":"North Railway St Se",
    "iso:country":"CA",
    "sg:address":"505 North Railway St SE",
    "sg:city":"Medicine Hat",
    "sg:classifiers":[
        {
            "category":"Bars & Pubs",
            "type":"Food & Drink"
        }
    ],
    "sg:phone":"+1 403 529 1995",
    "sg:postcode":"T1A 2Z4",
    "sg:province":"AB",
    "wof:name":"Mainliner Pub",
    "wof:placetype":"venue"
},
  "geometry": {"coordinates":[-110.670471191,50.0392227173],"type":"Point"}
}