{
  "type": "Feature",
  "properties": {
    "addr:full":"Winnipeg MB R3L 0H4",
    "addr:postcode":"r3l 0h4",
    "iso:country":"CA",
    "sg:city":"Winnipeg",
    "sg:classifiers":[
        {
            "category":"Real Estate",
            "subcategory":"Real Estate Operator",
            "type":"Services"
        }
    ],
    "sg:phone":"+1 204 284 5011",
    "sg:postcode":"R3L 0H4",
    "sg:province":"MB",
    "sg:tags":[
        "condominium"
    ],
    "wof:name":"Fountain House",
    "wof:placetype":"venue"
},
  "geometry": {"coordinates":[-97.15204620359999,49.8792533875],"type":"Point"}
}