{
  "type": "Feature",
  "properties": {
    "addr:full":"17409 South Branch Rd Cornwall ON K6H 5R6",
    "addr:housenumber":"17409",
    "addr:postcode":"k6h 5r6",
    "addr:street":"South Branch Rd",
    "iso:country":"CA",
    "sg:address":"17409 South Branch Rd",
    "sg:city":"Cornwall",
    "sg:classifiers":[
        {
            "category":"Building & Trades",
            "subcategory":"Electrical",
            "type":"Services"
        }
    ],
    "sg:phone":"+1 613 933 0370",
    "sg:postcode":"K6H 5R6",
    "sg:province":"ON",
    "sg:tags":[
        "electric",
        "contractor"
    ],
    "wof:name":"Elco Electric Ltd",
    "wof:placetype":"venue"
},
  "geometry": {"coordinates":[-74.761100769,45.064453125],"type":"Point"}
}