{
  "type": "Feature",
  "properties": {
    "addr:full":"34 Stone Church Rd Ancaster ON L9K 1P4",
    "addr:housenumber":"34",
    "addr:postcode":"l9k 1p4",
    "addr:street":"Stone Church Rd",
    "iso:country":"CA",
    "sg:address":"34 Stone Church Rd",
    "sg:city":"Ancaster",
    "sg:classifiers":[
        {
            "category":"Health Services",
            "subcategory":"Doctor",
            "type":"Services"
        }
    ],
    "sg:phone":"+1 905 304 1122",
    "sg:postcode":"L9K 1P4",
    "sg:province":"ON",
    "sg:tags":[
        "physician",
        "surgeon"
    ],
    "wof:name":"O'Malley, M MD",
    "wof:placetype":"venue"
},
  "geometry": {"coordinates":[-79.9368515015,43.2277107239],"type":"Point"}
}