{
  "type": "Feature",
  "properties": {
    "addr:full":"42 Church St E Elora ON N0B 1S0",
    "addr:housenumber":"42",
    "addr:postcode":"n0b 1s0",
    "addr:street":"Church St E",
    "iso:country":"CA",
    "sg:address":"42 Church St E",
    "sg:city":"Elora",
    "sg:classifiers":[
        {
            "category":"Health Services",
            "subcategory":"Chiropractor",
            "type":"Services"
        }
    ],
    "sg:phone":"+1 519 846 0100",
    "sg:postcode":"N0B 1S0",
    "sg:province":"ON",
    "wof:name":"Brak, Sarah DC",
    "wof:placetype":"venue"
},
  "geometry": {"coordinates":[-80.429283,43.682861],"type":"Point"}
}