{
  "type": "Feature",
  "properties": {
    "addr:full":"31 King St E Cobourg ON K9A 1K6",
    "addr:housenumber":"31",
    "addr:postcode":"k9a 1k6",
    "addr:street":"King St E",
    "iso:country":"CA",
    "sg:address":"31 King St E",
    "sg:city":"Cobourg",
    "sg:classifiers":[
        {
            "category":"Restaurant",
            "type":"Food & Drink"
        }
    ],
    "sg:phone":"+1 905 372 6634",
    "sg:postcode":"K9A 1K6",
    "sg:province":"ON",
    "wof:name":"Oasis Bar & Grill",
    "wof:placetype":"venue"
},
  "geometry": {"coordinates":[-78.16431427000001,43.9600028992],"type":"Point"}
}