{
  "type": "Feature",
  "properties": {
    "iso:country":"CA",
    "sg:address":"416 Tamarack Dr",
    "sg:city":"Waterloo",
    "sg:classifiers":[
        {
            "category":"Building & Trades",
            "subcategory":"Construction",
            "type":"Services"
        }
    ],
    "sg:phone":"+1 519 886 3284",
    "sg:postcode":"N2L 4G6",
    "sg:province":"ON",
    "sg:tags":[
        "dry wall",
        "contractor"
    ],
    "wof:name":"Tri County Construction",
    "wof:placetype":"venue"
},
  "geometry": {"coordinates":[-80.533638,43.4841],"type":"Point"}
}