{
  "type": "Feature",
  "properties": {
    "addr:full":"4841 Yonge St North York ON M2N 5X2",
    "addr:housenumber":"4841",
    "addr:postcode":"m2n 5x2",
    "addr:street":"Yonge St",
    "iso:country":"CA",
    "sg:address":"4841 Yonge St",
    "sg:city":"North York",
    "sg:classifiers":[
        {
            "category":"Shopping",
            "subcategory":"Clothing, Apparel, & Fashions",
            "type":"Retail Goods"
        }
    ],
    "sg:phone":"+1 416 250 0553",
    "sg:postcode":"M2N 5X2",
    "sg:province":"ON",
    "wof:name":"Winners",
    "wof:placetype":"venue"
},
  "geometry": {"coordinates":[-79.4108428955,43.7619781494],"type":"Point"}
}