{
  "type": "Feature",
  "properties": {
    "iso:country":"CA",
    "sg:address":"276 Victoria St E",
    "sg:city":"Alliston",
    "sg:classifiers":[
        {
            "category":"Autos & Motor Vehicles",
            "subcategory":"Fuel & Gas Station",
            "type":"Retail Goods"
        }
    ],
    "sg:phone":"+1 705 435 1273",
    "sg:postcode":"L9R 1K4",
    "sg:province":"ON",
    "sg:tags":[
        "oil"
    ],
    "wof:name":"Cango Gas Bar",
    "wof:placetype":"venue"
},
  "geometry": {"coordinates":[-79.85714,44.156715],"type":"Point"}
}