{
  "type": "Feature",
  "properties": {
    "addr:full":"2921 Boul Wallberg Dolbeau-Mistassini QC G8L 1L6",
    "addr:housenumber":"2921",
    "addr:postcode":"g8l 1l6",
    "addr:street":"Boul Wallberg",
    "iso:country":"CA",
    "sg:address":"2921 Boul Wallberg",
    "sg:city":"Dolbeau-Mistassini",
    "sg:classifiers":[
        {
            "category":"Wholesale",
            "subcategory":"Machinery & Supplies",
            "type":"Manufacturing & Wholesale Goods"
        }
    ],
    "sg:phone":"+1 418 276 5831",
    "sg:postcode":"G8L 1L6",
    "sg:province":"QC",
    "sg:tags":[
        "equipment",
        "fitting",
        "hose",
        "coupling",
        "hydraulic"
    ],
    "wof:name":"Hydromec Inc",
    "wof:placetype":"venue"
},
  "geometry": {"coordinates":[-72.27836600000001,48.886921],"type":"Point"}
}