{
  "type": "Feature",
  "properties": {
    "addr:full":"45 Overlea Blvd # A8 Toronto ON M4H 1C3",
    "addr:housenumber":"45",
    "addr:postcode":"m4h 1c3",
    "addr:street":"Overlea Blvd # A8",
    "iso:country":"CA",
    "sg:address":"45 Overlea Blvd # A8",
    "sg:city":"Toronto",
    "sg:classifiers":[
        {
            "category":"Health Services",
            "subcategory":"Doctor",
            "type":"Services"
        }
    ],
    "sg:phone":"+1 416 421 5065",
    "sg:postcode":"M4H 1C3",
    "sg:province":"ON",
    "sg:tags":[
        "laboratory",
        "clinic"
    ],
    "wof:name":"East York Diagnostic Ultrasnd",
    "wof:placetype":"venue"
},
  "geometry": {"coordinates":[-79.349304,43.705124],"type":"Point"}
}