{
  "type": "Feature",
  "properties": {
    "addr:full":"31 Sparks St Magnetawan ON P0A 1P0",
    "addr:housenumber":"31",
    "addr:postcode":"p0a 1p0",
    "addr:street":"Sparks St",
    "iso:country":"CA",
    "sg:address":"31 Sparks St",
    "sg:city":"Magnetawan",
    "sg:classifiers":[
        {
            "category":"Education",
            "subcategory":"School",
            "type":"Public Place"
        }
    ],
    "sg:phone":"+1 705 387 3939",
    "sg:postcode":"P0A 1P0",
    "sg:province":"ON",
    "wof:name":"Magnetawan Public School",
    "wof:placetype":"venue"
},
  "geometry": {"coordinates":[-79.64044199999999,45.66008],"type":"Point"}
}