{
  "type": "Feature",
  "properties": {
    "iso:country":"CA",
    "sg:address":"325 Woodville Rd",
    "sg:city":"Saint John",
    "sg:classifiers":[
        {
            "category":"Food & Beverages",
            "subcategory":"Specialty",
            "type":"Retail Goods"
        }
    ],
    "sg:phone":"+1 506 635 1842",
    "sg:postcode":"E2M 2H9",
    "sg:province":"NB",
    "sg:tags":[
        "health",
        "diet"
    ],
    "wof:name":"Health Is Wealth",
    "wof:placetype":"venue"
},
  "geometry": {"coordinates":[-66.06996917719999,45.2520065308],"type":"Point"}
}