{
  "type": "Feature",
  "properties": {
    "addr:full":"2033 Eglinton Ave W York ON M6E 2K4",
    "addr:housenumber":"2033",
    "addr:postcode":"m6e 2k4",
    "addr:street":"Eglinton Ave W",
    "iso:country":"CA",
    "sg:address":"2033 Eglinton Ave W",
    "sg:city":"York",
    "sg:classifiers":[
        {
            "category":"Personal",
            "subcategory":"Beauty Salon",
            "type":"Services"
        }
    ],
    "sg:phone":"+1 416 781 3141",
    "sg:postcode":"M6E 2K4",
    "sg:province":"ON",
    "wof:name":"Glamourama Stylist",
    "wof:placetype":"venue"
},
  "geometry": {"coordinates":[-79.456024,43.694313],"type":"Point"}
}