{
  "type": "Feature",
  "properties": {
    "addr:full":"395 Wellington Rd London ON N6C 5Z6",
    "addr:housenumber":"395",
    "addr:postcode":"n6c 5z6",
    "addr:street":"Wellington Rd",
    "iso:country":"CA",
    "sg:address":"395 Wellington Rd",
    "sg:city":"London",
    "sg:classifiers":[
        {
            "category":"Shopping",
            "type":"Retail Goods"
        }
    ],
    "sg:phone":"+1 519 680 5131",
    "sg:postcode":"N6C 5Z6",
    "sg:province":"ON",
    "sg:tags":[
        "pet",
        "food",
        "supply"
    ],
    "wof:name":"Paws & Claws",
    "wof:placetype":"venue"
},
  "geometry": {"coordinates":[-81.23090362550001,42.9603614807],"type":"Point"}
}