{
  "type": "Feature",
  "properties": {
    "addr:full":"271 Old Kingston Rd Scarborough ON M1C 1B4",
    "addr:housenumber":"271",
    "addr:postcode":"m1c 1b4",
    "addr:street":"Old Kingston Rd",
    "iso:country":"CA",
    "sg:address":"271 Old Kingston Rd",
    "sg:city":"Scarborough",
    "sg:classifiers":[
        {
            "category":"Cinema",
            "subcategory":"Movie Rental",
            "type":"Entertainment"
        }
    ],
    "sg:phone":"+1 416 282 5412",
    "sg:postcode":"M1C 1B4",
    "sg:province":"ON",
    "sg:tags":[
        "leasing",
        "video",
        "disc",
        "tape"
    ],
    "wof:name":"High Times Video",
    "wof:placetype":"venue"
},
  "geometry": {"coordinates":[-79.172492981,43.7820091248],"type":"Point"}
}