{
  "type": "Feature",
  "properties": {
    "addr:full":"Calgary AB T2C 1Z4",
    "addr:postcode":"t2c 1z4",
    "iso:country":"CA",
    "sg:city":"Calgary",
    "sg:classifiers":[
        {
            "category":"Professional",
            "subcategory":"Lawyer & Legal Services",
            "type":"Services"
        }
    ],
    "sg:phone":"+1 403 236 2110",
    "sg:postcode":"T2C 1Z4",
    "sg:province":"AB",
    "sg:tags":[
        "attorney"
    ],
    "wof:name":"White & CO",
    "wof:placetype":"venue"
},
  "geometry": {"coordinates":[-113.980194,50.999172],"type":"Point"}
}