{
  "type": "Feature",
  "properties": {
    "iso:country":"CA",
    "sg:address":"1883 Logan Ave",
    "sg:city":"Winnipeg",
    "sg:classifiers":[
        {
            "category":"Wholesale",
            "subcategory":"Groceries",
            "type":"Manufacturing & Wholesale Goods"
        }
    ],
    "sg:phone":"+1 204 632 7692",
    "sg:postcode":"R2R 0H6",
    "sg:province":"MB",
    "sg:tags":[
        "food",
        "grocer",
        "product"
    ],
    "wof:name":"Best Choice Food Products",
    "wof:placetype":"venue"
},
  "geometry": {"coordinates":[-97.1995925903,49.9231491089],"type":"Point"}
}