{
  "type": "Feature",
  "properties": {
    "iso:country":"CA",
    "sg:address":"510 Memorial Ave S",
    "sg:city":"Russell",
    "sg:classifiers":[
        {
            "category":"Restaurant",
            "type":"Food & Drink"
        }
    ],
    "sg:phone":"+1 204 773 3839",
    "sg:postcode":"R0J 1W0",
    "sg:province":"MB",
    "wof:name":"Gabel's Homesyle Restaurant",
    "wof:placetype":"venue"
},
  "geometry": {"coordinates":[-101.288269043,50.7731285095],"type":"Point"}
}