{
  "type": "Feature",
  "properties": {
    "iso:country":"CA",
    "sg:address":"14320 Highway 27",
    "sg:city":"Nobleton",
    "sg:classifiers":[
        {
            "category":"Building & Trades",
            "subcategory":"Construction",
            "type":"Services"
        }
    ],
    "sg:phone":"+1 905 859 3082",
    "sg:postcode":"L0G 1N0",
    "sg:province":"ON",
    "sg:tags":[
        "masonry",
        "contractor"
    ],
    "wof:name":"Columbia Masonry Ltd",
    "wof:placetype":"venue"
},
  "geometry": {"coordinates":[-79.65287780760001,43.902885437],"type":"Point"}
}