{
  "type": "Feature",
  "properties": {
    "addr:full":"Maple St Clinton ON N0M 1L0",
    "addr:postcode":"n0m 1l0",
    "addr:street":"Maple St",
    "iso:country":"CA",
    "sg:address":"Maple St",
    "sg:city":"Clinton",
    "sg:classifiers":[
        {
            "category":"Organizations",
            "subcategory":"Religious Organization",
            "type":"Services"
        }
    ],
    "sg:phone":"+1 705 625 3125",
    "sg:postcode":"N0M 1L0",
    "sg:province":"ON",
    "sg:tags":[
        "church"
    ],
    "wof:name":"Fellowship Bible Chapel",
    "wof:placetype":"venue"
},
  "geometry": {"coordinates":[-81.538284,43.623295],"type":"Point"}
}