{
  "type": "Feature",
  "properties": {
    "addr:full":"Kamloops BC V2C 1T4",
    "addr:postcode":"bc v2c 1t4",
    "iso:country":"CA",
    "sg:city":"Kamloops",
    "sg:classifiers":[
        {
            "category":"Retail",
            "subcategory":"Laundry & Dry Cleaning",
            "type":"Services"
        }
    ],
    "sg:phone":"+1 250 372 8884",
    "sg:postcode":"V2C 1T4",
    "sg:province":"BC",
    "sg:tags":[
        "cleaners",
        "rug",
        "carpet"
    ],
    "wof:name":"Lemon Fresh Carpet-Upholstery",
    "wof:placetype":"venue"
},
  "geometry": {"coordinates":[-120.347984,50.672497],"type":"Point"}
}