{
  "type": "Feature",
  "properties": {
    "iso:country":"CA",
    "sg:city":"Calgary",
    "sg:classifiers":[
        {
            "category":"Insurance",
            "subcategory":"Insurance Agent",
            "type":"Services"
        }
    ],
    "sg:phone":"+1 403 264 3094",
    "sg:postcode":"T2R 0G5",
    "sg:province":"AB",
    "wof:name":"Vega Insurance Svc Inc",
    "wof:placetype":"venue"
},
  "geometry": {"coordinates":[-114.08684539799999,51.0429000854],"type":"Point"}
}