{
  "type": "Feature",
  "properties": {
    "addr:full":"1075 Boul Industriel Granby QC J2J 2B8",
    "addr:housenumber":"1075",
    "addr:postcode":"j2j 2b8",
    "addr:street":"Boul Industriel",
    "iso:country":"CA",
    "sg:address":"1075 Boul Industriel",
    "sg:city":"Granby",
    "sg:classifiers":[
        {
            "category":"Manufacturing",
            "subcategory":"Printing",
            "type":"Manufacturing & Wholesale Goods"
        }
    ],
    "sg:phone":"+1 450 372 1116",
    "sg:postcode":"J2J 2B8",
    "sg:province":"QC",
    "sg:tags":[
        "printer"
    ],
    "wof:name":"Imprimerie NJ Inc",
    "wof:placetype":"venue"
},
  "geometry": {"coordinates":[-72.774506,45.377693],"type":"Point"}
}