{
  "type": "Feature",
  "properties": {
    "addr:full":"100 1st Ave S Middle Lake SK S0K 2X0",
    "addr:housenumber":"100",
    "addr:postcode":"s0k 2x0",
    "addr:street":"1St Ave S Middle Lake",
    "iso:country":"CA",
    "sg:address":"100 1st Ave S",
    "sg:city":"Middle Lake",
    "sg:classifiers":[
        {
            "category":"Autos & Motor Vehicles",
            "subcategory":"Fuel & Gas Station",
            "type":"Retail Goods"
        }
    ],
    "sg:phone":"+1 306 367 4244",
    "sg:postcode":"S0K 2X0",
    "sg:province":"SK",
    "sg:tags":[
        "oil"
    ],
    "wof:name":"Zimmer's Service",
    "wof:placetype":"venue"
},
  "geometry": {"coordinates":[-105.301537,52.482044],"type":"Point"}
}