{
  "type": "Feature",
  "properties": {
    "iso:country":"CA",
    "sg:address":"359 Horton St E",
    "sg:city":"London",
    "sg:classifiers":[
        {
            "category":"Food & Beverages",
            "subcategory":"Groceries & Convenience Stores",
            "type":"Retail Goods"
        }
    ],
    "sg:phone":"+1 519 438 7696",
    "sg:postcode":"N6B 1L6",
    "sg:province":"ON",
    "sg:tags":[
        "grocer"
    ],
    "wof:name":"European Groceries Ltd",
    "wof:placetype":"venue"
},
  "geometry": {"coordinates":[-81.2388687134,42.9811248779],"type":"Point"}
}