{
  "type": "Feature",
  "properties": {
    "iso:country":"CA",
    "sg:address":"325 Rue Saint-Pierre",
    "sg:city":"Riviere-Du-Loup",
    "sg:classifiers":[
        {
            "category":"Education",
            "subcategory":"College",
            "type":"Public Place"
        }
    ],
    "sg:phone":"+1 418 862 6903",
    "sg:postcode":"G5R 3T6",
    "sg:province":"QC",
    "sg:tags":[
        "academic",
        "school"
    ],
    "wof:name":"Cegep DE Riviere-Du-Loup",
    "wof:placetype":"venue"
},
  "geometry": {"coordinates":[-69.54536437989999,47.8297042847],"type":"Point"}
}