{
  "type": "Feature",
  "properties": {
    "iso:country":"CA",
    "sg:address":"PO Box 157 STN B",
    "sg:city":"Ottawa",
    "sg:classifiers":[
        {
            "category":"Social Services",
            "type":"Services"
        }
    ],
    "sg:phone":"+1 613 820 5669",
    "sg:postcode":"K1P 6C4",
    "sg:province":"ON",
    "sg:tags":[
        "control",
        "organization",
        "weight",
        "welfare"
    ],
    "wof:name":"Outre Mangeur Anonyme",
    "wof:placetype":"venue"
},
  "geometry": {"coordinates":[-75.69189453120001,45.4215011597],"type":"Point"}
}