{
  "type": "Feature",
  "properties": {
    "addr:full":"901 Rang Du Bas-DE-L'Assomptio L'Assomption QC J5W 2A3",
    "addr:housenumber":"901",
    "addr:postcode":"j5w 2a3",
    "addr:street":"Rang Du Bas-De-L'Assomptio",
    "iso:country":"CA",
    "sg:address":"901 Rang Du Bas-DE-L'Assomptio",
    "sg:city":"L'Assomption",
    "sg:classifiers":[
        {
            "category":"Home & Garden",
            "subcategory":"Furniture",
            "type":"Retail Goods"
        }
    ],
    "sg:phone":"+1 450 589 2255",
    "sg:postcode":"J5W 2A3",
    "sg:province":"QC",
    "sg:tags":[
        "equipment",
        "kitchen",
        "cabinet"
    ],
    "wof:name":"Cuisirama Inc",
    "wof:placetype":"venue"
},
  "geometry": {"coordinates":[-73.434792,45.807964],"type":"Point"}
}