{
  "type": "Feature",
  "properties": {
    "addr:full":"329 Main St N Sauble Beach ON N0H 2G0",
    "addr:housenumber":"329",
    "addr:postcode":"n0h 2g0",
    "addr:street":"Main St N",
    "iso:country":"CA",
    "sg:address":"329 Main St N",
    "sg:city":"Sauble Beach",
    "sg:classifiers":[
        {
            "category":"Restaurant",
            "type":"Food & Drink"
        }
    ],
    "sg:phone":"+1 519 422 1175",
    "sg:postcode":"N0H 2G0",
    "sg:province":"ON",
    "sg:tags":[
        "pizza"
    ],
    "wof:name":"Pizza Delight",
    "wof:placetype":"venue"
},
  "geometry": {"coordinates":[-81.2672958374,44.6296730042],"type":"Point"}
}