{
  "type": "Feature",
  "properties": {
    "addr:full":"135 Av DE LA Citadelle Hull QC J8Z 3L8",
    "addr:postcode":"j8z 3l8",
    "addr:street":"135 Av De La Citadelle",
    "iso:country":"CA",
    "sg:address":"135 Av DE LA Citadelle",
    "sg:city":"Hull",
    "sg:classifiers":[
        {
            "category":"Professional",
            "subcategory":"Art Services",
            "type":"Services"
        }
    ],
    "sg:phone":"+1 819 771 4816",
    "sg:postcode":"J8Z 3L8",
    "sg:province":"QC",
    "sg:tags":[
        "graphic",
        "designer"
    ],
    "wof:name":"Design or & Art",
    "wof:placetype":"venue"
},
  "geometry": {"coordinates":[-75.763054,45.475536],"type":"Point"}
}