{
  "type": "Feature",
  "properties": {
    "addr:full":"Simcoe ON N3Y 4J9",
    "addr:postcode":"n3y 4j9",
    "iso:country":"CA",
    "sg:city":"Simcoe",
    "sg:classifiers":[
        {
            "category":"Wholesale",
            "subcategory":"Machinery & Supplies",
            "type":"Manufacturing & Wholesale Goods"
        }
    ],
    "sg:phone":"+1 519 429 2937",
    "sg:postcode":"N3Y 4J9",
    "sg:province":"ON",
    "sg:tags":[
        "bearing"
    ],
    "wof:name":"Simcoe Bearing Supply",
    "wof:placetype":"venue"
},
  "geometry": {"coordinates":[-80.328232,42.844864],"type":"Point"}
}