{
  "type": "Feature",
  "properties": {
    "addr:full":"268 Rutherford Rd S Brampton ON L6W 3N3",
    "addr:housenumber":"268",
    "addr:postcode":"l6w 3n3",
    "addr:street":"Rutherford Rd S",
    "iso:country":"CA",
    "sg:address":"268 Rutherford Rd S",
    "sg:city":"Brampton",
    "sg:classifiers":[
        {
            "category":"Home & Garden",
            "subcategory":"Carpets & Floor Coverings",
            "type":"Retail Goods"
        }
    ],
    "sg:phone":"+1 905 456 1600",
    "sg:postcode":"L6W 3N3",
    "sg:province":"ON",
    "sg:tags":[
        "material"
    ],
    "wof:name":"Sears Floor Covering Ctr",
    "wof:placetype":"venue"
},
  "geometry": {"coordinates":[-79.725883,43.686798],"type":"Point"}
}