{
  "type": "Feature",
  "properties": {
    "addr:full":"101 Scarlet Ridge Rd # 201 Carbonear NL A1Y 1A2",
    "addr:housenumber":"101",
    "addr:postcode":"a1y 1a2",
    "addr:street":"Scarlet Ridge Rd # 201",
    "iso:country":"CA",
    "sg:address":"101 Scarlet Ridge Rd # 201",
    "sg:city":"Carbonear",
    "sg:classifiers":[
        {
            "category":"Travel",
            "subcategory":"Hotels & Motels",
            "type":"Entertainment"
        }
    ],
    "sg:phone":"+1 709 596 2159",
    "sg:postcode":"A1Y 1A2",
    "sg:province":"NL",
    "sg:tags":[
        "apartment"
    ],
    "wof:name":"Belleview Residence",
    "wof:placetype":"venue"
},
  "geometry": {"coordinates":[-53.2295,47.736382],"type":"Point"}
}