{
  "type": "Feature",
  "properties": {
    "addr:full":"549 Island Hwy W Parksville BC V9P 1C7",
    "addr:housenumber":"549",
    "addr:postcode":"v9p 1c7",
    "addr:street":"Island Hwy W",
    "iso:country":"CA",
    "sg:address":"549 Island Hwy W",
    "sg:city":"Parksville",
    "sg:classifiers":[
        {
            "category":"Wholesale",
            "subcategory":"Groceries",
            "type":"Manufacturing & Wholesale Goods"
        }
    ],
    "sg:phone":"+1 250 248 9284",
    "sg:postcode":"V9P 1C7",
    "sg:province":"BC",
    "sg:tags":[
        "food",
        "grocer",
        "product"
    ],
    "wof:name":"Temple Food Store",
    "wof:placetype":"venue"
},
  "geometry": {"coordinates":[-124.330276489,49.3254623413],"type":"Point"}
}