{
  "type": "Feature",
  "properties": {
    "iso:country":"CA",
    "sg:address":"216 Main St",
    "sg:city":"Biggar",
    "sg:classifiers":[
        {
            "category":"Shopping",
            "subcategory":"Computers & Home Electronics",
            "type":"Retail Goods"
        }
    ],
    "sg:phone":"+1 306 948 2266",
    "sg:postcode":"S0K 0M0",
    "sg:province":"SK",
    "sg:tags":[
        "equipment",
        "electronic",
        "telephone",
        "cellular"
    ],
    "wof:name":"Biggar Leisure Ctr",
    "wof:placetype":"venue"
},
  "geometry": {"coordinates":[-107.98548126199999,52.0550842285],"type":"Point"}
}