{
  "type": "Feature",
  "properties": {
    "addr:full":"30 Baldwin St Toronto ON M5T 1L3",
    "addr:housenumber":"30",
    "addr:postcode":"m5t 1l3",
    "addr:street":"Baldwin St",
    "iso:country":"CA",
    "sg:address":"30 Baldwin St",
    "sg:city":"Toronto",
    "sg:classifiers":[
        {
            "category":"Restaurant",
            "type":"Food & Drink"
        }
    ],
    "sg:phone":"+1 416 977 1287",
    "sg:postcode":"M5T 1L3",
    "sg:province":"ON",
    "wof:name":"Bodega Restaurant",
    "wof:placetype":"venue"
},
  "geometry": {"coordinates":[-79.3936920166,43.6560707092],"type":"Point"}
}