{
  "type": "Feature",
  "properties": {
    "addr:full":"1652 Mcrae Ave Victoria BC V8P 1H3",
    "addr:housenumber":"1652",
    "addr:postcode":"v8p 1h3",
    "addr:street":"Mcrae Ave",
    "iso:country":"CA",
    "sg:address":"1652 Mcrae Ave",
    "sg:city":"Victoria",
    "sg:classifiers":[
        {
            "category":"Food & Beverages",
            "subcategory":"Groceries & Convenience Stores",
            "type":"Retail Goods"
        }
    ],
    "sg:phone":"+1 250 592 1731",
    "sg:postcode":"V8P 1H3",
    "sg:province":"BC",
    "sg:tags":[
        "grocer"
    ],
    "wof:name":"Mc Rae Food Market",
    "wof:placetype":"venue"
},
  "geometry": {"coordinates":[-123.364517212,48.428314209],"type":"Point"}
}