{
  "type": "Feature",
  "properties": {
    "addr:full":"1901 Boul DE Portland Sherbrooke QC J1J 1T7",
    "addr:housenumber":"1901",
    "addr:postcode":"j1j 1t7",
    "addr:street":"Boul De Portland",
    "iso:country":"CA",
    "sg:address":"1901 Boul DE Portland",
    "sg:city":"Sherbrooke",
    "sg:classifiers":[
        {
            "category":"Health Services",
            "subcategory":"Medical Lab",
            "type":"Services"
        }
    ],
    "sg:phone":"+1 819 562 2453",
    "sg:postcode":"J1J 1T7",
    "sg:province":"QC",
    "wof:name":"Clinique DE Denturologie",
    "wof:placetype":"venue"
},
  "geometry": {"coordinates":[-71.920799,45.403881],"type":"Point"}
}