{
  "type": "Feature",
  "properties": {
    "iso:country":"CA",
    "sg:address":"777 Dundas St W # 2",
    "sg:city":"Mississauga",
    "sg:classifiers":[
        {
            "category":"Retail",
            "subcategory":"Car Wash",
            "type":"Services"
        }
    ],
    "sg:phone":"+1 905 566 7878",
    "sg:postcode":"L5C 4P6",
    "sg:province":"ON",
    "sg:tags":[
        "polishing",
        "automobile",
        "rustproofing",
        "washing",
        "undercoating"
    ],
    "wof:name":"Rust Check Centre Inc",
    "wof:placetype":"venue"
},
  "geometry": {"coordinates":[-79.63539886469999,43.564037323],"type":"Point"}
}