{
  "type": "Feature",
  "properties": {
    "iso:country":"CA",
    "sg:address":"345 Wallace Ave N",
    "sg:city":"Listowel",
    "sg:classifiers":[
        {
            "category":"Shopping",
            "type":"Retail Goods"
        }
    ],
    "sg:phone":"+1 519 291 1930",
    "sg:postcode":"N4W 1L2",
    "sg:province":"ON",
    "sg:tags":[
        "cosmetic",
        "pharmacy"
    ],
    "wof:name":"Shoppers Drug Mart",
    "wof:placetype":"venue"
},
  "geometry": {"coordinates":[-80.951461792,43.7339782715],"type":"Point"}
}