{
  "type": "Feature",
  "properties": {
    "iso:country":"CA",
    "sg:city":"Edmonton",
    "sg:classifiers":[
        {
            "category":"Health Services",
            "subcategory":"Doctor",
            "type":"Services"
        }
    ],
    "sg:phone":"+1 780 990 1898",
    "sg:postcode":"T5H 0W2",
    "sg:province":"AB",
    "sg:tags":[
        "dentist"
    ],
    "wof:name":"Jamie Denture Clinic",
    "wof:placetype":"venue"
},
  "geometry": {"coordinates":[-113.501296997,53.5515213013],"type":"Point"}
}