{
  "type": "Feature",
  "properties": {
    "addr:full":"67 Doncaster Ave Thornhill ON L3T 1L6",
    "addr:housenumber":"67",
    "addr:postcode":"l3t 1l6",
    "addr:street":"Doncaster Ave",
    "iso:country":"CA",
    "sg:address":"67 Doncaster Ave",
    "sg:city":"Thornhill",
    "sg:classifiers":[
        {
            "category":"Shopping",
            "subcategory":"Shoes",
            "type":"Retail Goods"
        }
    ],
    "sg:phone":"+1 905 731 8520",
    "sg:postcode":"L3T 1L6",
    "sg:province":"ON",
    "wof:name":"Little Shoe Palace Ltd",
    "wof:placetype":"venue"
},
  "geometry": {"coordinates":[-79.4159851074,43.8039054871],"type":"Point"}
}