{
  "type": "Feature",
  "properties": {
    "iso:country":"CA",
    "sg:address":"154 30E Av",
    "sg:city":"Sainte-Marthe-Sur-Le-Lac",
    "sg:classifiers":[
        {
            "category":"Retail",
            "subcategory":"Auto Repair",
            "type":"Services"
        }
    ],
    "sg:phone":"+1 450 473 1451",
    "sg:postcode":"J0N 1P0",
    "sg:province":"QC",
    "sg:tags":[
        "body",
        "automobile",
        "painting"
    ],
    "wof:name":"Debosselage SC Enrg",
    "wof:placetype":"venue"
},
  "geometry": {"coordinates":[-73.93236541749999,45.5292510986],"type":"Point"}
}