{
  "type": "Feature",
  "properties": {
    "addr:full":"201 Main St N Mount Forest ON N0G 2L0",
    "addr:housenumber":"201",
    "addr:postcode":"n0g 2l0",
    "addr:street":"Main St N",
    "iso:country":"CA",
    "sg:address":"201 Main St N",
    "sg:city":"Mount Forest",
    "sg:classifiers":[
        {
            "category":"Banks & Credit Unions",
            "subcategory":"Bank",
            "type":"Services"
        }
    ],
    "sg:phone":"+1 519 323 2130",
    "sg:postcode":"N0G 2L0",
    "sg:province":"ON",
    "wof:name":"Bank of Montreal",
    "wof:placetype":"venue"
},
  "geometry": {"coordinates":[-80.7375793457,43.9829940796],"type":"Point"}
}