{
  "type": "Feature",
  "properties": {
    "iso:country":"CA",
    "sg:address":"340 8 Rang",
    "sg:city":"Lyster",
    "sg:classifiers":[
        {
            "category":"Farming",
            "subcategory":"Farm",
            "type":"Manufacturing & Wholesale Goods"
        }
    ],
    "sg:phone":"+1 819 389 1212",
    "sg:postcode":"G0S 1V0",
    "sg:province":"QC",
    "wof:name":"Ferme Arion",
    "wof:placetype":"venue"
},
  "geometry": {"coordinates":[-71.57982635499999,46.3484764099],"type":"Point"}
}