{
  "type": "Feature",
  "properties": {
    "addr:full":"2861 Kingston Rd Scarborough ON M1M 1N3",
    "addr:housenumber":"2861",
    "addr:postcode":"m1m 1n3",
    "addr:street":"Kingston Rd",
    "iso:country":"CA",
    "sg:address":"2861 Kingston Rd",
    "sg:city":"Scarborough",
    "sg:classifiers":[
        {
            "category":"Personal",
            "subcategory":"Tanning Parlor",
            "type":"Services"
        }
    ],
    "sg:phone":"+1 416 266 3825",
    "sg:postcode":"M1M 1N3",
    "sg:province":"ON",
    "sg:tags":[
        "salon"
    ],
    "wof:name":"Tanning Duck",
    "wof:placetype":"venue"
},
  "geometry": {"coordinates":[-79.23575599999999,43.721992],"type":"Point"}
}