{
  "type": "Feature",
  "properties": {
    "addr:full":"2288 Skipper Pl Vancouver BC V5P 4T5",
    "addr:housenumber":"2288",
    "addr:postcode":"v5p 4t5",
    "addr:street":"Skipper Pl",
    "iso:country":"CA",
    "sg:address":"2288 Skipper Pl",
    "sg:city":"Vancouver",
    "sg:classifiers":[
        {
            "category":"Real Estate",
            "subcategory":"Real Estate Agent",
            "type":"Services"
        }
    ],
    "sg:phone":"+1 604 327 3588",
    "sg:postcode":"V5P 4T5",
    "sg:province":"BC",
    "sg:tags":[
        "cooperative"
    ],
    "wof:name":"Riverside Landing Hsng CO-OP",
    "wof:placetype":"venue"
},
  "geometry": {"coordinates":[-123.060562,49.206886],"type":"Point"}
}