{
  "type": "Feature",
  "properties": {
    "addr:full":"51 Adair Ave S Hamilton ON L8H 1B5",
    "addr:housenumber":"51",
    "addr:postcode":"l8h 1b5",
    "addr:street":"Adair Ave S",
    "iso:country":"CA",
    "sg:address":"51 Adair Ave S",
    "sg:city":"Hamilton",
    "sg:classifiers":[
        {
            "category":"Restaurant",
            "type":"Food & Drink"
        }
    ],
    "sg:phone":"+1 905 548 9360",
    "sg:postcode":"L8H 1B5",
    "sg:province":"ON",
    "sg:tags":[
        "caterer"
    ],
    "wof:name":"Jocic Catering",
    "wof:placetype":"venue"
},
  "geometry": {"coordinates":[-79.79048899999999,43.234524],"type":"Point"}
}