{
  "type": "Feature",
  "properties": {
    "addr:full":"277 Mcphillips St Winnipeg MB R3E 2K7",
    "addr:housenumber":"277",
    "addr:postcode":"r3e 2k7",
    "addr:street":"Mcphillips St",
    "iso:country":"CA",
    "sg:address":"277 Mcphillips St",
    "sg:city":"Winnipeg",
    "sg:classifiers":[
        {
            "category":"Freight",
            "type":"Transportation"
        }
    ],
    "sg:phone":"+1 204 783 7979",
    "sg:postcode":"R3E 2K7",
    "sg:province":"MB",
    "sg:tags":[
        "crane",
        "trucking"
    ],
    "wof:name":"Litz Crane Rentals",
    "wof:placetype":"venue"
},
  "geometry": {"coordinates":[-97.17041015620001,49.9129867554],"type":"Point"}
}