{
  "type": "Feature",
  "properties": {
    "iso:country":"CA",
    "sg:address":"3707 Massey Dr",
    "sg:city":"Prince George",
    "sg:classifiers":[
        {
            "category":"Wholesale",
            "subcategory":"Sporting Goods",
            "type":"Manufacturing & Wholesale Goods"
        }
    ],
    "sg:phone":"+1 250 561 2671",
    "sg:postcode":"V2N 4E6",
    "sg:province":"BC",
    "wof:name":"Short Game Systems CO",
    "wof:placetype":"venue"
},
  "geometry": {"coordinates":[-122.791161,53.898537],"type":"Point"}
}