{
  "type": "Feature",
  "properties": {
    "addr:full":"5975 Mavis Rd Mississauga ON L5R 3T7",
    "addr:housenumber":"5975",
    "addr:postcode":"l5r 3t7",
    "addr:street":"Mavis Rd",
    "iso:country":"CA",
    "sg:address":"5975 Mavis Rd",
    "sg:city":"Mississauga",
    "sg:classifiers":[
        {
            "category":"Restaurant",
            "type":"Food & Drink"
        }
    ],
    "sg:phone":"+1 905 502 8555",
    "sg:postcode":"L5R 3T7",
    "sg:province":"ON",
    "wof:name":"Tucker's Marketplace Rstrnts",
    "wof:placetype":"venue"
},
  "geometry": {"coordinates":[-79.6943664551,43.6113624573],"type":"Point"}
}