{
  "type": "Feature",
  "properties": {
    "addr:full":"Calgary AB T3G 2A7",
    "addr:postcode":"t3g 2a7",
    "iso:country":"CA",
    "sg:city":"Calgary",
    "sg:classifiers":[
        {
            "category":"Banks & Credit Unions",
            "subcategory":"Bank",
            "type":"Services"
        }
    ],
    "sg:phone":"+1 403 221 6810",
    "sg:postcode":"T3G 2A7",
    "sg:province":"AB",
    "wof:name":"Scotiabank",
    "wof:placetype":"venue"
},
  "geometry": {"coordinates":[-114.196426,51.123127],"type":"Point"}
}