{
  "type": "Feature",
  "properties": {
    "addr:full":"9102 108 St Grande Prairie AB T8V 4C8",
    "addr:housenumber":"9102",
    "addr:postcode":"t8v 4c8",
    "addr:street":"108 St",
    "iso:country":"CA",
    "sg:address":"9102 108 St",
    "sg:city":"Grande Prairie",
    "sg:classifiers":[
        {
            "category":"Wholesale",
            "subcategory":"Auto Parts",
            "type":"Manufacturing & Wholesale Goods"
        }
    ],
    "sg:phone":"+1 780 538 3038",
    "sg:postcode":"T8V 4C8",
    "sg:province":"AB",
    "sg:tags":[
        "equipment",
        "truck",
        "trailer"
    ],
    "wof:name":"Traction",
    "wof:placetype":"venue"
},
  "geometry": {"coordinates":[-118.820747376,55.1624946594],"type":"Point"}
}