{
  "type": "Feature",
  "properties": {
    "addr:full":"Montreal QC H1E 3J9",
    "addr:postcode":"h1e 3j9",
    "iso:country":"CA",
    "sg:city":"Montreal",
    "sg:classifiers":[
        {
            "category":"Professional",
            "subcategory":"Employment Agencies",
            "type":"Services"
        }
    ],
    "sg:phone":"+1 514 643 4484",
    "sg:postcode":"H1E 3J9",
    "sg:province":"QC",
    "sg:tags":[
        "opportunity"
    ],
    "wof:name":"Adamo Soins",
    "wof:placetype":"venue"
},
  "geometry": {"coordinates":[-73.59136199949999,45.6357727051],"type":"Point"}
}