{
  "type": "Feature",
  "properties": {
    "addr:full":"6502 50 Ave Bonnyville AB T9N 2M6",
    "addr:housenumber":"6502",
    "addr:postcode":"t9n 2m6",
    "addr:street":"50 Ave",
    "iso:country":"CA",
    "sg:address":"6502 50 Ave",
    "sg:city":"Bonnyville",
    "sg:classifiers":[
        {
            "category":"Utilities",
            "subcategory":"Fuel Oil & Lpg",
            "type":"Services"
        }
    ],
    "sg:phone":"+1 780 812 2644",
    "sg:postcode":"T9N 2M6",
    "sg:province":"AB",
    "sg:tags":[
        "propane",
        "gas"
    ],
    "wof:name":"Canwest Propane Inc",
    "wof:placetype":"venue"
},
  "geometry": {"coordinates":[-110.777992248,54.2674446106],"type":"Point"}
}