{
  "type": "Feature",
  "properties": {
    "addr:full":"5412 44 Ave Wetaskiwin AB T9A 0C7",
    "addr:housenumber":"5412",
    "addr:postcode":"t9a 0c7",
    "addr:street":"44 Ave",
    "iso:country":"CA",
    "sg:address":"5412 44 Ave",
    "sg:city":"Wetaskiwin",
    "sg:classifiers":[
        {
            "category":"Wholesale",
            "subcategory":"Electrical",
            "type":"Manufacturing & Wholesale Goods"
        }
    ],
    "sg:phone":"+1 780 352 0708",
    "sg:postcode":"T9A 0C7",
    "sg:province":"AB",
    "sg:tags":[
        "communications",
        "equipment"
    ],
    "wof:name":"Fon-Tel Communications Svc",
    "wof:placetype":"venue"
},
  "geometry": {"coordinates":[-113.384674072,52.9645042419],"type":"Point"}
}