{
  "type": "Feature",
  "properties": {
    "addr:full":"6452 Flewellyn Rd Stittsville ON K2S 1B6",
    "addr:housenumber":"6452",
    "addr:postcode":"k2s 1b6",
    "addr:street":"Flewellyn Rd",
    "iso:country":"CA",
    "sg:address":"6452 Flewellyn Rd",
    "sg:city":"Stittsville",
    "sg:classifiers":[
        {
            "category":"Shopping",
            "type":"Retail Goods"
        }
    ],
    "sg:phone":"+1 613 831 2570",
    "sg:postcode":"K2S 1B6",
    "sg:province":"ON",
    "sg:tags":[
        "spa",
        "hot",
        "tub"
    ],
    "wof:name":"Stittsville Pool & Spa",
    "wof:placetype":"venue"
},
  "geometry": {"coordinates":[-75.9114227295,45.2318000793],"type":"Point"}
}