{
  "type": "Feature",
  "properties": {
    "addr:full":"RR 5 Spencerville ON K0E 1X0",
    "addr:postcode":"k0e 1x0",
    "addr:street":"Rr 5",
    "iso:country":"CA",
    "sg:address":"RR 5",
    "sg:city":"Spencerville",
    "sg:classifiers":[
        {
            "category":"Utilities",
            "subcategory":"Refuse",
            "type":"Services"
        }
    ],
    "sg:phone":"+1 613 925 3755",
    "sg:postcode":"K0E 1X0",
    "sg:province":"ON",
    "sg:tags":[
        "garbage",
        "collection"
    ],
    "wof:name":"Cameron's Cartage",
    "wof:placetype":"venue"
},
  "geometry": {"coordinates":[-75.546684,44.84306],"type":"Point"}
}