{
  "type": "Feature",
  "properties": {
    "iso:country":"CA",
    "sg:address":"603 Grand Ave",
    "sg:city":"Luseland",
    "sg:classifiers":[
        {
            "category":"Personal",
            "subcategory":"Beauty Salon",
            "type":"Services"
        }
    ],
    "sg:phone":"+1 306 372 4433",
    "sg:postcode":"S0L 2A0",
    "sg:province":"SK",
    "wof:name":"Carol's Beauty Palace",
    "wof:placetype":"venue"
},
  "geometry": {"coordinates":[-109.39264679,52.0801506042],"type":"Point"}
}