{
  "type": "Feature",
  "properties": {
    "iso:country":"CA",
    "sg:address":"6855 Adair St",
    "sg:city":"Burnaby",
    "sg:classifiers":[
        {
            "category":"Building & Trades",
            "subcategory":"Landscaping Services",
            "type":"Services"
        }
    ],
    "sg:phone":"+1 604 420 9088",
    "sg:postcode":"V5B 2W8",
    "sg:province":"BC",
    "sg:tags":[
        "landscape",
        "contractor"
    ],
    "wof:name":"Taku Landscaping",
    "wof:placetype":"venue"
},
  "geometry": {"coordinates":[-122.961555481,49.2644767761],"type":"Point"}
}