{
  "type": "Feature",
  "properties": {
    "addr:full":"5127 49 St # 7 Rocky Mountain House AB T4T 1B8",
    "addr:housenumber":"5127",
    "addr:postcode":"t4t 1b8",
    "addr:street":"49 St # 7",
    "iso:country":"CA",
    "sg:address":"5127 49 St # 7",
    "sg:city":"Rocky Mountain House",
    "sg:classifiers":[
        {
            "category":"Health Services",
            "subcategory":"Optometrist",
            "type":"Services"
        }
    ],
    "sg:phone":"+1 403 845 2780",
    "sg:postcode":"T4T 1B8",
    "sg:province":"AB",
    "wof:name":"Rudyk, Roger OD",
    "wof:placetype":"venue"
},
  "geometry": {"coordinates":[-114.917518616,52.3764953613],"type":"Point"}
}