{
  "type": "Feature",
  "properties": {
    "addr:full":"1580 Avenue Rd North York ON M5M 3X6",
    "addr:housenumber":"1580",
    "addr:postcode":"m5m 3x6",
    "addr:street":"Avenue Rd",
    "iso:country":"CA",
    "sg:address":"1580 Avenue Rd",
    "sg:city":"North York",
    "sg:classifiers":[
        {
            "category":"Food & Beverages",
            "subcategory":"Liquor & Beverages",
            "type":"Retail Goods"
        }
    ],
    "sg:phone":"+1 416 781 0651",
    "sg:postcode":"M5M 3X6",
    "sg:province":"ON",
    "sg:tags":[
        "beer",
        "ale"
    ],
    "wof:name":"Beer Store",
    "wof:placetype":"venue"
},
  "geometry": {"coordinates":[-79.4165725708,43.7242012024],"type":"Point"}
}