{
  "type": "Feature",
  "properties": {
    "addr:full":"175 Pine St S Thorold ON L2V 3M5",
    "addr:housenumber":"175",
    "addr:postcode":"l2v 3m5",
    "addr:street":"Pine St S",
    "iso:country":"CA",
    "sg:address":"175 Pine St S",
    "sg:city":"Thorold",
    "sg:classifiers":[
        {
            "category":"Social Services",
            "type":"Services"
        }
    ],
    "sg:phone":"+1 905 227 1113",
    "sg:postcode":"L2V 3M5",
    "sg:province":"ON",
    "sg:tags":[
        "organization",
        "welfare"
    ],
    "wof:name":"Arid Group Home Inc",
    "wof:placetype":"venue"
},
  "geometry": {"coordinates":[-79.202507019,43.1139144897],"type":"Point"}
}