{
  "type": "Feature",
  "properties": {
    "addr:full":"53 Brunswick St Truro NS B2N 2G8",
    "addr:housenumber":"53",
    "addr:postcode":"b2n 2g8",
    "addr:street":"Brunswick St",
    "iso:country":"CA",
    "sg:address":"53 Brunswick St",
    "sg:city":"Truro",
    "sg:classifiers":[
        {
            "category":"Wholesale",
            "subcategory":"Farm Supplies",
            "type":"Manufacturing & Wholesale Goods"
        }
    ],
    "sg:phone":"+1 902 895 9201",
    "sg:postcode":"B2N 2G8",
    "sg:province":"NS",
    "sg:tags":[
        "feed"
    ],
    "wof:name":"Clarence Farm Svc",
    "wof:placetype":"venue"
},
  "geometry": {"coordinates":[-63.275364,45.361591],"type":"Point"}
}