{
  "type": "Feature",
  "properties": {
    "addr:full":"6125 1E Av Charlesbourg QC G1H 2V9",
    "addr:housenumber":"6125",
    "addr:postcode":"g1h 2v9",
    "addr:street":"1E Av",
    "iso:country":"CA",
    "sg:address":"6125 1E Av",
    "sg:city":"Charlesbourg",
    "sg:classifiers":[
        {
            "category":"Organizations",
            "subcategory":"Religious Organization",
            "type":"Services"
        }
    ],
    "sg:phone":"+1 418 623 5497",
    "sg:postcode":"G1H 2V9",
    "sg:province":"QC",
    "wof:name":"Peres Eudistes",
    "wof:placetype":"venue"
},
  "geometry": {"coordinates":[-71.25793457029999,46.8517341614],"type":"Point"}
}