{
  "type": "Feature",
  "properties": {
    "iso:country":"CA",
    "sg:address":"411 Main St",
    "sg:city":"Wesleyville",
    "sg:classifiers":[
        {
            "category":"Retail",
            "subcategory":"Portrait Studio",
            "type":"Services"
        }
    ],
    "sg:phone":"+1 709 536 3382",
    "sg:postcode":"A0G 4R0",
    "sg:province":"NL",
    "sg:tags":[
        "photographer"
    ],
    "wof:name":"Blackwood's Photography",
    "wof:placetype":"venue"
},
  "geometry": {"coordinates":[-53.556416,49.17218],"type":"Point"}
}