{
  "type": "Feature",
  "properties": {
    "addr:full":"212 Louth St St Catharines ON L2S 2R6",
    "addr:housenumber":"212",
    "addr:postcode":"l2s 2r6",
    "addr:street":"Louth St",
    "iso:country":"CA",
    "sg:address":"212 Louth St",
    "sg:city":"St Catharines",
    "sg:classifiers":[
        {
            "category":"Retail",
            "subcategory":"Auto Repair",
            "type":"Services"
        }
    ],
    "sg:phone":"+1 905 685 5757",
    "sg:postcode":"L2S 2R6",
    "sg:province":"ON",
    "sg:tags":[
        "repairing",
        "automobile"
    ],
    "wof:name":"Ray James Auto Repair",
    "wof:placetype":"venue"
},
  "geometry": {"coordinates":[-79.25970458979999,43.144744873],"type":"Point"}
}