{
  "type": "Feature",
  "properties": {
    "iso:country":"CA",
    "sg:address":"5625 4th Ave",
    "sg:city":"Regina",
    "sg:classifiers":[
        {
            "category":"Building & Trades",
            "subcategory":"Construction",
            "type":"Services"
        }
    ],
    "sg:phone":"+1 306 543 0009",
    "sg:postcode":"S4T 0K2",
    "sg:province":"SK",
    "sg:tags":[
        "general",
        "contractor"
    ],
    "wof:name":"Patren Construction Inc",
    "wof:placetype":"venue"
},
  "geometry": {"coordinates":[-104.661712647,50.4627914429],"type":"Point"}
}