{
  "type": "Feature",
  "properties": {
    "addr:full":"80 Sheppard Ave E North York ON M2N 6E8",
    "addr:housenumber":"80",
    "addr:postcode":"m2n 6e8",
    "addr:street":"Sheppard Ave E",
    "iso:country":"CA",
    "sg:address":"80 Sheppard Ave E",
    "sg:city":"North York",
    "sg:classifiers":[
        {
            "category":"Education",
            "subcategory":"School",
            "type":"Public Place"
        }
    ],
    "sg:phone":"+1 416 222 8282",
    "sg:postcode":"M2N 6E8",
    "sg:province":"ON",
    "wof:name":"Toronto Catholic District Schl",
    "wof:placetype":"venue"
},
  "geometry": {"coordinates":[-79.407448,43.762447],"type":"Point"}
}