{
  "type": "Feature",
  "properties": {
    "iso:country":"CA",
    "sg:address":"75 Akins Dr",
    "sg:city":"St Albert",
    "sg:classifiers":[
        {
            "category":"Social Services",
            "subcategory":"Child Care",
            "type":"Services"
        }
    ],
    "sg:phone":"+1 780 419 7466",
    "sg:postcode":"T8N 3A5",
    "sg:province":"AB",
    "wof:name":"Sigis Child Care Society",
    "wof:placetype":"venue"
},
  "geometry": {"coordinates":[-113.586471558,53.6310844421],"type":"Point"}
}