{
  "type": "Feature",
  "properties": {
    "iso:country":"CA",
    "sg:city":"Orillia",
    "sg:classifiers":[
        {
            "category":"Personal",
            "subcategory":"Beauty Salon",
            "type":"Services"
        }
    ],
    "sg:phone":"+1 705 325 2122",
    "sg:postcode":"L3V 5E8",
    "sg:province":"ON",
    "wof:name":"C J's Hair Care",
    "wof:placetype":"venue"
},
  "geometry": {"coordinates":[-79.4322052002,44.6236495972],"type":"Point"}
}