{
  "type": "Feature",
  "properties": {
    "iso:country":"CA",
    "sg:address":"988 Boul Saint-Laurent",
    "sg:city":"Montreal",
    "sg:classifiers":[
        {
            "category":"Wholesale",
            "subcategory":"Durable Goods & Equipment",
            "type":"Manufacturing & Wholesale Goods"
        }
    ],
    "sg:phone":"+1 514 871 0993",
    "sg:postcode":"H2Z 1J3",
    "sg:province":"QC",
    "sg:tags":[
        "importer",
        "exporter"
    ],
    "wof:name":"Swatow Import-Export Inc",
    "wof:placetype":"venue"
},
  "geometry": {"coordinates":[-73.5591659546,45.5075798035],"type":"Point"}
}