{
  "type": "Feature",
  "properties": {
    "addr:full":"Innisfail AB T4G 1S7",
    "addr:postcode":"t4g 1s7",
    "iso:country":"CA",
    "sg:city":"Innisfail",
    "sg:classifiers":[
        {
            "category":"Organizations",
            "subcategory":"Professional Association",
            "type":"Services"
        }
    ],
    "sg:phone":"+1 403 227 6766",
    "sg:postcode":"T4G 1S7",
    "sg:province":"AB",
    "wof:name":"Big Brothers & Big Sisters",
    "wof:placetype":"venue"
},
  "geometry": {"coordinates":[-113.95059967,52.0272903442],"type":"Point"}
}