{
  "type": "Feature",
  "properties": {
    "addr:full":"525 Welland Ave St Catharines ON L2M 6P3",
    "addr:housenumber":"525",
    "addr:postcode":"l2m 6p3",
    "addr:street":"Welland Ave",
    "iso:country":"CA",
    "sg:address":"525 Welland Ave",
    "sg:city":"St Catharines",
    "sg:classifiers":[
        {
            "category":"Home & Garden",
            "subcategory":"Furniture",
            "type":"Retail Goods"
        }
    ],
    "sg:phone":"+1 905 641 0779",
    "sg:postcode":"L2M 6P3",
    "sg:province":"ON",
    "wof:name":"United Furniture Warehouse",
    "wof:placetype":"venue"
},
  "geometry": {"coordinates":[-79.211922,43.176102],"type":"Point"}
}