{
  "type": "Feature",
  "properties": {
    "iso:country":"CA",
    "sg:address":"525 Welland Ave",
    "sg:city":"St Catharines",
    "sg:classifiers":[
        {
            "category":"Home & Garden",
            "subcategory":"Furniture",
            "type":"Retail Goods"
        }
    ],
    "sg:phone":"+1 905 641 0779",
    "sg:postcode":"L2M 6P3",
    "sg:province":"ON",
    "wof:name":"United Furniture Warehouse",
    "wof:placetype":"venue"
},
  "geometry": {"coordinates":[-79.211922,43.176102],"type":"Point"}
}