{
  "type": "Feature",
  "properties": {
    "addr:full":"3320 Boul Dagenais O Laval QC H7P 1V4",
    "addr:housenumber":"3320",
    "addr:postcode":"h7p 1v4",
    "addr:street":"Boul Dagenais O",
    "iso:country":"CA",
    "sg:address":"3320 Boul Dagenais O",
    "sg:city":"Laval",
    "sg:classifiers":[
        {
            "category":"Personal",
            "subcategory":"Beauty Salon",
            "type":"Services"
        }
    ],
    "sg:phone":"+1 450 622 5182",
    "sg:postcode":"H7P 1V4",
    "sg:province":"QC",
    "wof:name":"Salon DE Coiffure G Fleury",
    "wof:placetype":"venue"
},
  "geometry": {"coordinates":[-73.803535,45.579018],"type":"Point"}
}