{
  "type": "Feature",
  "properties": {
    "addr:full":"4813 47 St Red Deer AB T4N 1R3",
    "addr:housenumber":"4813",
    "addr:postcode":"t4n 1r3",
    "addr:street":"47 St",
    "iso:country":"CA",
    "sg:address":"4813 47 St",
    "sg:city":"Red Deer",
    "sg:classifiers":[
        {
            "category":"Social Services",
            "subcategory":"Child Care",
            "type":"Services"
        }
    ],
    "sg:phone":"+1 403 340 3660",
    "sg:postcode":"T4N 1R3",
    "sg:province":"AB",
    "wof:name":"Town Centre Day Care",
    "wof:placetype":"venue"
},
  "geometry": {"coordinates":[-113.80953979500001,52.2659492493],"type":"Point"}
}