{
  "type": "Feature",
  "properties": {
    "addr:full":"Coquitlam BC V3E 1S3",
    "addr:postcode":"v3e 1s3",
    "iso:country":"CA",
    "sg:city":"Coquitlam",
    "sg:classifiers":[
        {
            "category":"Retail",
            "subcategory":"Animal Services",
            "type":"Services"
        }
    ],
    "sg:phone":"+1 604 464 6966",
    "sg:postcode":"V3E 1S3",
    "sg:province":"BC",
    "sg:tags":[
        "pet",
        "grooming",
        "washing"
    ],
    "wof:name":"All Animal Grooming",
    "wof:placetype":"venue"
},
  "geometry": {"coordinates":[-122.816406,49.278961],"type":"Point"}
}