{
  "type": "Feature",
  "properties": {
    "addr:full":"2639 Boul Pitfield Saint-Laurent QC H4S 1T2",
    "addr:housenumber":"2639",
    "addr:postcode":"h4s 1t2",
    "addr:street":"Boul Pitfield",
    "iso:country":"CA",
    "sg:address":"2639 Boul Pitfield",
    "sg:city":"Saint-Laurent",
    "sg:classifiers":[
        {
            "category":"Manufacturing",
            "subcategory":"Tools & Machinery",
            "type":"Manufacturing & Wholesale Goods"
        }
    ],
    "sg:phone":"+1 514 335 6486",
    "sg:postcode":"H4S 1T2",
    "sg:province":"QC",
    "sg:tags":[
        "built",
        "designed"
    ],
    "wof:name":"Citco",
    "wof:placetype":"venue"
},
  "geometry": {"coordinates":[-73.74389600000001,45.495502],"type":"Point"}
}