{
  "type": "Feature",
  "properties": {
    "addr:full":"431 Av Otis Sept-Iles QC G4R 1L2",
    "addr:postcode":"g4r 1l2",
    "addr:street":"431 Av Otis Sept-Iles",
    "iso:country":"CA",
    "sg:address":"431 Av Otis",
    "sg:city":"Sept-Iles",
    "sg:classifiers":[
        {
            "category":"Manufacturing",
            "subcategory":"Tools & Machinery",
            "type":"Manufacturing & Wholesale Goods"
        }
    ],
    "sg:phone":"+1 418 962 6948",
    "sg:postcode":"G4R 1L2",
    "sg:province":"QC",
    "sg:tags":[
        "machine",
        "shop",
        "welding"
    ],
    "wof:name":"Fabnor Inc",
    "wof:placetype":"venue"
},
  "geometry": {"coordinates":[-66.370758,50.213455],"type":"Point"}
}