{
  "type": "Feature",
  "properties": {
    "addr:full":"530 36 St N Lethbridge AB T1H 5H6",
    "addr:postcode":"530 36;t1h 5h6",
    "addr:street":"St N",
    "iso:country":"CA",
    "sg:address":"530 36 St N",
    "sg:city":"Lethbridge",
    "sg:classifiers":[
        {
            "category":"Wholesale",
            "subcategory":"Machinery & Supplies",
            "type":"Manufacturing & Wholesale Goods"
        }
    ],
    "sg:phone":"+1 403 327 7566",
    "sg:postcode":"T1H 5H6",
    "sg:province":"AB",
    "sg:tags":[
        "building",
        "material"
    ],
    "wof:name":"Winroc Corp",
    "wof:placetype":"venue"
},
  "geometry": {"coordinates":[-112.788528442,49.7062911987],"type":"Point"}
}