{
  "type": "Feature",
  "properties": {
    "iso:country":"CA",
    "sg:city":"Mississauga",
    "sg:classifiers":[
        {
            "category":"Freight",
            "type":"Transportation"
        }
    ],
    "sg:phone":"+1 905 677 8334",
    "sg:postcode":"L5S 1W1",
    "sg:province":"ON",
    "wof:name":"Ecu Line Canada",
    "wof:placetype":"venue"
},
  "geometry": {"coordinates":[-79.66575622560001,43.6803131104],"type":"Point"}
}