{
  "type": "Feature",
  "properties": {
    "addr:full":"1475 Bedford Hwy Bedford NS B4A 3Z5",
    "addr:housenumber":"1475",
    "addr:postcode":"b4a 3z5",
    "addr:street":"Bedford Hwy",
    "iso:country":"CA",
    "sg:address":"1475 Bedford Hwy",
    "sg:city":"Bedford",
    "sg:classifiers":[
        {
            "category":"Restaurant",
            "type":"Food & Drink"
        }
    ],
    "sg:phone":"+1 902 832 2226",
    "sg:postcode":"B4A 3Z5",
    "sg:province":"NS",
    "wof:name":"May Garden Chinese Food",
    "wof:placetype":"venue"
},
  "geometry": {"coordinates":[-63.661503,44.730644],"type":"Point"}
}