{
  "type": "Feature",
  "properties": {
    "addr:full":"245 Keefer St Vancouver BC V6A 1X6",
    "addr:housenumber":"245",
    "addr:postcode":"v6a 1x6",
    "addr:street":"Keefer St",
    "iso:country":"CA",
    "sg:address":"245 Keefer St",
    "sg:city":"Vancouver",
    "sg:classifiers":[
        {
            "category":"Health Services",
            "subcategory":"Clinic",
            "type":"Services"
        }
    ],
    "sg:phone":"+1 604 331 0992",
    "sg:postcode":"V6A 1X6",
    "sg:province":"BC",
    "sg:tags":[
        "herbalist"
    ],
    "wof:name":"Cheng Fung Herbs Ltd",
    "wof:placetype":"venue"
},
  "geometry": {"coordinates":[-123.098518372,49.2795829773],"type":"Point"}
}