{
  "type": "Feature",
  "properties": {
    "addr:full":"1198 River Rd St Andrews MB R1A 2E1",
    "addr:housenumber":"1198",
    "addr:postcode":"r1a 2e1",
    "addr:street":"River Rd",
    "iso:country":"CA",
    "sg:address":"1198 River Rd",
    "sg:city":"St Andrews",
    "sg:classifiers":[
        {
            "category":"Organizations",
            "subcategory":"Religious Organization",
            "type":"Services"
        }
    ],
    "sg:phone":"+1 204 482 9486",
    "sg:postcode":"R1A 2E1",
    "sg:province":"MB",
    "sg:tags":[
        "church"
    ],
    "wof:name":"St Clements Church",
    "wof:placetype":"venue"
},
  "geometry": {"coordinates":[-97.0265960693,50.0369606018],"type":"Point"}
}