{
  "type": "Feature",
  "properties": {
    "addr:full":"2 Glenabbey Dr Courtice ON L1E 1C1",
    "addr:housenumber":"2",
    "addr:postcode":"l1e 1c1",
    "addr:street":"Glenabbey Dr",
    "iso:country":"CA",
    "sg:address":"2 Glenabbey Dr",
    "sg:city":"Courtice",
    "sg:classifiers":[
        {
            "category":"Cinema",
            "subcategory":"Movie Rental",
            "type":"Entertainment"
        }
    ],
    "sg:phone":"+1 905 432 3011",
    "sg:postcode":"L1E 1C1",
    "sg:province":"ON",
    "sg:tags":[
        "leasing",
        "video",
        "disc",
        "tape"
    ],
    "wof:name":"Fans Convenience Store",
    "wof:placetype":"venue"
},
  "geometry": {"coordinates":[-78.8074188232,43.8936538696],"type":"Point"}
}