{
  "type": "Feature",
  "properties": {
    "iso:country":"CA",
    "sg:address":"50 Church St",
    "sg:city":"St Catharines",
    "sg:classifiers":[
        {
            "category":"Professional",
            "subcategory":"Management & Consulting",
            "type":"Services"
        }
    ],
    "sg:phone":"+1 905 688 5600",
    "sg:postcode":"L2R 7C2",
    "sg:province":"ON",
    "sg:tags":[
        "consultant",
        "business"
    ],
    "wof:name":"St Catharines Business Dev Ofc",
    "wof:placetype":"venue"
},
  "geometry": {"coordinates":[-79.247292,43.159359],"type":"Point"}
}