{
  "type": "Feature",
  "properties": {
    "addr:full":"Mississauga ON L4Y 2C1",
    "addr:postcode":"l4y 2c1",
    "iso:country":"CA",
    "sg:city":"Mississauga",
    "sg:classifiers":[
        {
            "category":"Food & Beverages",
            "subcategory":"Bakery",
            "type":"Retail Goods"
        }
    ],
    "sg:phone":"+1 905 276 6398",
    "sg:postcode":"L4Y 2C1",
    "sg:province":"ON",
    "sg:tags":[
        "baker"
    ],
    "wof:name":"What A Bagel",
    "wof:placetype":"venue"
},
  "geometry": {"coordinates":[-79.5856170654,43.6075363159],"type":"Point"}
}