{
  "type": "Feature",
  "properties": {
    "addr:full":"6220 Boul Wilfrid-Hamel L'Ancienne-Lorette QC G2E 2H7",
    "addr:housenumber":"6220",
    "addr:postcode":"g2e 2h7",
    "addr:street":"Boul Wilfrid-Hamel",
    "iso:country":"CA",
    "sg:address":"6220 Boul Wilfrid-Hamel",
    "sg:city":"L'Ancienne-Lorette",
    "sg:classifiers":[
        {
            "category":"Retail",
            "subcategory":"Veterinary Services",
            "type":"Services"
        }
    ],
    "sg:phone":"+1 418 872 4942",
    "sg:postcode":"G2E 2H7",
    "sg:province":"QC",
    "sg:tags":[
        "veterinarian"
    ],
    "wof:name":"Clinique Veterinaire Hamel",
    "wof:placetype":"venue"
},
  "geometry": {"coordinates":[-71.34478759770001,46.7979125977],"type":"Point"}
}