{
  "type": "Feature",
  "properties": {
    "addr:full":"4078 Rue Alfred-Laliberte Boisbriand QC J7H 1P8",
    "addr:housenumber":"4078",
    "addr:postcode":"j7h 1p8",
    "addr:street":"Rue Alfred-Laliberte",
    "iso:country":"CA",
    "sg:address":"4078 Rue Alfred-Laliberte",
    "sg:city":"Boisbriand",
    "sg:classifiers":[
        {
            "category":"Freight",
            "type":"Transportation"
        }
    ],
    "sg:phone":"+1 450 437 2495",
    "sg:postcode":"J7H 1P8",
    "sg:province":"QC",
    "sg:tags":[
        "trucking"
    ],
    "wof:name":"Forbec Transport Ltee",
    "wof:placetype":"venue"
},
  "geometry": {"coordinates":[-73.868301,45.637913],"type":"Point"}
}