{
  "type": "Feature",
  "properties": {
    "addr:full":"867 N Copper St Greenwood BC V0H 1J0",
    "addr:housenumber":"867",
    "addr:postcode":"v0h 1j0",
    "addr:street":"N Copper St",
    "iso:country":"CA",
    "sg:address":"867 N Copper St",
    "sg:city":"Greenwood",
    "sg:classifiers":[
        {
            "category":"Autos & Motor Vehicles",
            "subcategory":"Automobile Sales",
            "type":"Retail Goods"
        }
    ],
    "sg:phone":"+1 250 445 6587",
    "sg:postcode":"V0H 1J0",
    "sg:province":"BC",
    "sg:tags":[
        "body",
        "car",
        "painting"
    ],
    "wof:name":"Heritage Autobody",
    "wof:placetype":"venue"
},
  "geometry": {"coordinates":[-118.67742200000001,49.091797],"type":"Point"}
}