{
  "type": "Feature",
  "properties": {
    "addr:full":"308 Wood St Whitehorse YT Y1A 2E6",
    "addr:housenumber":"308",
    "addr:postcode":"y1a 2e6",
    "addr:street":"Wood St",
    "iso:country":"CA",
    "sg:address":"308 Wood St",
    "sg:city":"Whitehorse",
    "sg:classifiers":[
        {
            "category":"Food & Beverages",
            "subcategory":"Specialty",
            "type":"Retail Goods"
        }
    ],
    "sg:phone":"+1 867 668 4908",
    "sg:postcode":"Y1A 2E6",
    "sg:province":"YT",
    "sg:tags":[
        "health",
        "diet"
    ],
    "wof:name":"Three Beans Natural Foods",
    "wof:placetype":"venue"
},
  "geometry": {"coordinates":[-135.05587800000001,60.720963],"type":"Point"}
}