{
  "type": "Feature",
  "properties": {
    "iso:country":"CA",
    "sg:address":"7333 Boul Newman",
    "sg:city":"Lasalle",
    "sg:classifiers":[
        {
            "category":"Restaurant",
            "type":"Food & Drink"
        }
    ],
    "sg:phone":"+1 514 366 0999",
    "sg:postcode":"H8N 2K3",
    "sg:province":"QC",
    "wof:name":"Boccacinos Restaurants",
    "wof:placetype":"venue"
},
  "geometry": {"coordinates":[-73.6196670532,45.4412612915],"type":"Point"}
}