{
  "type": "Feature",
  "properties": {
    "addr:full":"Bayfield ON N0M 1G0",
    "addr:postcode":"n0m 1g0",
    "iso:country":"CA",
    "sg:city":"Bayfield",
    "sg:classifiers":[
        {
            "category":"Shopping",
            "subcategory":"Jewelry",
            "type":"Retail Goods"
        }
    ],
    "sg:phone":"+1 519 565 5499",
    "sg:postcode":"N0M 1G0",
    "sg:province":"ON",
    "sg:tags":[
        "jeweler"
    ],
    "wof:name":"Micheline's Jewellery Boutique",
    "wof:placetype":"venue"
},
  "geometry": {"coordinates":[-81.856194,43.163338],"type":"Point"}
}