{
  "type": "Feature",
  "properties": {
    "addr:full":"5016 Hwy 62 Belleville ON K8N 4Z7",
    "addr:housenumber":"5016",
    "addr:postcode":"k8n 4z7",
    "addr:street":"Hwy 62",
    "iso:country":"CA",
    "sg:address":"5016 Hwy 62",
    "sg:city":"Belleville",
    "sg:classifiers":[
        {
            "category":"Building & Trades",
            "subcategory":"Electrical",
            "type":"Services"
        }
    ],
    "sg:phone":"+1 613 969 6197",
    "sg:postcode":"K8N 4Z7",
    "sg:province":"ON",
    "sg:tags":[
        "excavating",
        "electric",
        "contractor"
    ],
    "wof:name":"K G Reid Trenching & Constr",
    "wof:placetype":"venue"
},
  "geometry": {"coordinates":[-77.4022369385,44.2008209229],"type":"Point"}
}