{
  "type": "Feature",
  "properties": {
    "addr:full":"1805 Beaufort Ave Comox BC V9M 1R9",
    "addr:housenumber":"1805",
    "addr:postcode":"v9m 1r9",
    "addr:street":"Beaufort Ave",
    "iso:country":"CA",
    "sg:address":"1805 Beaufort Ave",
    "sg:city":"Comox",
    "sg:classifiers":[
        {
            "category":"Recreation",
            "subcategory":"Marina",
            "type":"Entertainment"
        }
    ],
    "sg:phone":"+1 250 339 2930",
    "sg:postcode":"V9M 1R9",
    "sg:province":"BC",
    "wof:name":"Comox Bay Marina",
    "wof:placetype":"venue"
},
  "geometry": {"coordinates":[-124.927086,49.67252],"type":"Point"}
}