{
  "type": "Feature",
  "properties": {
    "addr:full":"650 Portland St Dartmouth NS B2W 6A3",
    "addr:housenumber":"650",
    "addr:postcode":"b2w 6a3",
    "addr:street":"Portland St",
    "iso:country":"CA",
    "sg:address":"650 Portland St",
    "sg:city":"Dartmouth",
    "sg:classifiers":[
        {
            "category":"Cinema",
            "subcategory":"Movie Theater",
            "type":"Entertainment"
        }
    ],
    "sg:phone":"+1 902 434 4200",
    "sg:postcode":"B2W 6A3",
    "sg:province":"NS",
    "wof:name":"Empire 6 Cinemas",
    "wof:placetype":"venue"
},
  "geometry": {"coordinates":[-63.5266265869,44.6713829041],"type":"Point"}
}