{
  "type": "Feature",
  "properties": {
    "addr:full":"1908 Weston Rd York ON M9N 1W2",
    "addr:housenumber":"1908",
    "addr:postcode":"m9n 1w2",
    "addr:street":"Weston Rd",
    "iso:country":"CA",
    "sg:address":"1908 Weston Rd",
    "sg:city":"York",
    "sg:classifiers":[
        {
            "category":"Shopping",
            "subcategory":"Optical Goods",
            "type":"Retail Goods"
        }
    ],
    "sg:phone":"+1 416 249 7761",
    "sg:postcode":"M9N 1W2",
    "sg:province":"ON",
    "sg:tags":[
        "optician"
    ],
    "wof:name":"Future Optical",
    "wof:placetype":"venue"
},
  "geometry": {"coordinates":[-79.51657899999999,43.700108],"type":"Point"}
}