{
  "type": "Feature",
  "properties": {
    "addr:full":"391 Av Courtemanche Montreal-Est QC H1B 4X7",
    "addr:postcode":"h1b 4x7",
    "addr:street":"391 Av Courtemanche",
    "iso:country":"CA",
    "sg:address":"391 Av Courtemanche",
    "sg:city":"Montreal-Est",
    "sg:classifiers":[
        {
            "category":"Building & Trades",
            "subcategory":"Plumbing",
            "type":"Services"
        }
    ],
    "sg:phone":"+1 514 640 9446",
    "sg:postcode":"H1B 4X7",
    "sg:province":"QC",
    "sg:tags":[
        "mechanical",
        "welding",
        "contractor"
    ],
    "wof:name":"Soudure Lessard",
    "wof:placetype":"venue"
},
  "geometry": {"coordinates":[-73.510513,45.633904],"type":"Point"}
}