{
  "type": "Feature",
  "properties": {
    "addr:full":"Spruce Grove AB T7X 1R2",
    "addr:postcode":"t7x 1r2",
    "iso:country":"CA",
    "sg:city":"Spruce Grove",
    "sg:classifiers":[
        {
            "category":"Restaurant",
            "type":"Food & Drink"
        }
    ],
    "sg:phone":"+1 780 962 2211",
    "sg:postcode":"T7X 1R2",
    "sg:province":"AB",
    "sg:tags":[
        "pizza"
    ],
    "wof:name":"Little Caesars Pizza",
    "wof:placetype":"venue"
},
  "geometry": {"coordinates":[-113.910561,53.542179],"type":"Point"}
}