{
  "type": "Feature",
  "properties": {
    "addr:full":"54 Colborne St Fenelon Falls ON K0M 1N0",
    "addr:housenumber":"54",
    "addr:postcode":"k0m 1n0",
    "addr:street":"Colborne St",
    "iso:country":"CA",
    "sg:address":"54 Colborne St",
    "sg:city":"Fenelon Falls",
    "sg:classifiers":[
        {
            "category":"Home & Garden",
            "subcategory":"Household Appliances",
            "type":"Retail Goods"
        }
    ],
    "sg:phone":"+1 705 887 5436",
    "sg:postcode":"K0M 1N0",
    "sg:province":"ON",
    "wof:name":"Bert's Appliance Sales & Svc",
    "wof:placetype":"venue"
},
  "geometry": {"coordinates":[-78.7357330322,44.5374488831],"type":"Point"}
}