{
  "type": "Feature",
  "properties": {
    "iso:country":"CA",
    "sg:address":"2165 Gottingen St",
    "sg:city":"Halifax",
    "sg:classifiers":[
        {
            "category":"Health Services",
            "subcategory":"Doctor",
            "type":"Services"
        }
    ],
    "sg:phone":"+1 902 420 0303",
    "sg:postcode":"B3K 3B5",
    "sg:province":"NS",
    "sg:tags":[
        "physician",
        "surgeon"
    ],
    "wof:name":"Patriquin, Maria MD",
    "wof:placetype":"venue"
},
  "geometry": {"coordinates":[-63.584377,44.652893],"type":"Point"}
}