{
  "type": "Feature",
  "properties": {
    "addr:full":"884 Portage Ave Winnipeg MB R3G 0P1",
    "addr:housenumber":"884",
    "addr:postcode":"r3g 0p1",
    "addr:street":"Portage Ave",
    "iso:country":"CA",
    "sg:address":"884 Portage Ave",
    "sg:city":"Winnipeg",
    "sg:classifiers":[
        {
            "category":"Health Services",
            "subcategory":"Doctor",
            "type":"Services"
        }
    ],
    "sg:phone":"+1 204 783 1883",
    "sg:postcode":"R3G 0P1",
    "sg:province":"MB",
    "sg:tags":[
        "dentist"
    ],
    "wof:name":"Sedor, Karen DDS",
    "wof:placetype":"venue"
},
  "geometry": {"coordinates":[-97.16906,49.885506],"type":"Point"}
}