{
  "type": "Feature",
  "properties": {
    "addr:full":"8288 Granville St Vancouver BC V6P 4Z4",
    "addr:housenumber":"8288",
    "addr:postcode":"v6p 4z4",
    "addr:street":"Granville St",
    "iso:country":"CA",
    "sg:address":"8288 Granville St",
    "sg:city":"Vancouver",
    "sg:classifiers":[
        {
            "category":"Shopping",
            "subcategory":"Jewelry",
            "type":"Retail Goods"
        }
    ],
    "sg:phone":"+1 604 261 8870",
    "sg:postcode":"V6P 4Z4",
    "sg:province":"BC",
    "sg:tags":[
        "jeweler"
    ],
    "wof:name":"Unique Jewellery Ltd",
    "wof:placetype":"venue"
},
  "geometry": {"coordinates":[-123.14020538299999,49.211151123],"type":"Point"}
}