{
  "type": "Feature",
  "properties": {
    "addr:full":"3084 Binbrook Rd Binbrook ON L0R 1C0",
    "addr:housenumber":"3084",
    "addr:postcode":"l0r 1c0",
    "addr:street":"Binbrook Rd",
    "iso:country":"CA",
    "sg:address":"3084 Binbrook Rd",
    "sg:city":"Binbrook",
    "sg:classifiers":[
        {
            "category":"Organizations",
            "subcategory":"Religious Organization",
            "type":"Services"
        }
    ],
    "sg:phone":"+1 905 692 3904",
    "sg:postcode":"L0R 1C0",
    "sg:province":"ON",
    "sg:tags":[
        "church"
    ],
    "wof:name":"Binbrook Baptist Church",
    "wof:placetype":"venue"
},
  "geometry": {"coordinates":[-79.807693,43.121674],"type":"Point"}
}