{
  "type": "Feature",
  "properties": {
    "addr:full":"4600 Rue Hickmore Saint-Laurent QC H4T 1K2",
    "addr:housenumber":"4600",
    "addr:postcode":"h4t 1k2",
    "addr:street":"Rue Hickmore",
    "iso:country":"CA",
    "sg:address":"4600 Rue Hickmore",
    "sg:city":"Saint-Laurent",
    "sg:classifiers":[
        {
            "category":"Wholesale",
            "subcategory":"Apparel",
            "type":"Manufacturing & Wholesale Goods"
        }
    ],
    "sg:phone":"+1 514 344 1219",
    "sg:postcode":"H4T 1K2",
    "sg:province":"QC",
    "sg:tags":[
        "shoes"
    ],
    "wof:name":"Hush Puppies Canada",
    "wof:placetype":"venue"
},
  "geometry": {"coordinates":[-73.694992,45.471687],"type":"Point"}
}