{
  "type": "Feature",
  "properties": {
    "addr:full":"280 St Anne Ave St Agatha ON N0B 2L0",
    "addr:housenumber":"280",
    "addr:postcode":"n0b 2l0",
    "addr:street":"St Anne Ave",
    "iso:country":"CA",
    "sg:address":"280 St Anne Ave",
    "sg:city":"St Agatha",
    "sg:classifiers":[
        {
            "category":"Building & Trades",
            "subcategory":"Construction",
            "type":"Services"
        }
    ],
    "sg:phone":"+1 519 747 1411",
    "sg:postcode":"N0B 2L0",
    "sg:province":"ON",
    "sg:tags":[
        "concrete",
        "contractor"
    ],
    "wof:name":"Donny Haid Construction Ltd",
    "wof:placetype":"venue"
},
  "geometry": {"coordinates":[-80.6365661621,43.4380226135],"type":"Point"}
}