{
  "type": "Feature",
  "properties": {
    "addr:full":"3240 Douglas St Victoria BC V8Z 3K7",
    "addr:housenumber":"3240",
    "addr:postcode":"v8z 3k7",
    "addr:street":"Douglas St",
    "iso:country":"CA",
    "sg:address":"3240 Douglas St",
    "sg:city":"Victoria",
    "sg:classifiers":[
        {
            "category":"Autos & Motor Vehicles",
            "subcategory":"Automobile Sales",
            "type":"Retail Goods"
        }
    ],
    "sg:phone":"+1 250 475 2313",
    "sg:postcode":"V8Z 3K7",
    "sg:province":"BC",
    "sg:tags":[
        "car",
        "dealer"
    ],
    "wof:name":"Wille Dodge Chrysler Ltd",
    "wof:placetype":"venue"
},
  "geometry": {"coordinates":[-123.37233000000001,48.44767],"type":"Point"}
}