{
  "type": "Feature",
  "properties": {
    "addr:full":"238 Rte Du Centre-DE-Ski Matane QC G4W 3M7",
    "addr:housenumber":"238",
    "addr:postcode":"g4w 3m7",
    "addr:street":"Rte Du Centre-De-Ski",
    "iso:country":"CA",
    "sg:address":"238 Rte Du Centre-DE-Ski",
    "sg:city":"Matane",
    "sg:classifiers":[
        {
            "category":"Government",
            "subcategory":"Office",
            "type":"Public Place"
        }
    ],
    "sg:phone":"+1 418 562 1513",
    "sg:postcode":"G4W 3M7",
    "sg:province":"QC",
    "sg:tags":[
        "village"
    ],
    "wof:name":"Matane Centre DE Ski",
    "wof:placetype":"venue"
},
  "geometry": {"coordinates":[-67.5431137085,48.7627754211],"type":"Point"}
}