{
  "type": "Feature",
  "properties": {
    "addr:full":"Keewatin ON P0X 1C0",
    "addr:postcode":"p0x 1c0",
    "addr:street":"Keewatin",
    "iso:country":"CA",
    "sg:city":"Keewatin",
    "sg:classifiers":[
        {
            "category":"Retail",
            "subcategory":"Repair Shop",
            "type":"Services"
        }
    ],
    "sg:phone":"+1 807 543 2127",
    "sg:postcode":"P0X 1C0",
    "sg:province":"ON",
    "sg:tags":[
        "welding"
    ],
    "wof:name":"John's Mobile Welding",
    "wof:placetype":"venue"
},
  "geometry": {"coordinates":[-94.55727386469999,49.7577133179],"type":"Point"}
}