{
  "type": "Feature",
  "properties": {
    "addr:full":"588 Arthur St W Thunder Bay ON P7E 5R7",
    "addr:housenumber":"588",
    "addr:postcode":"p7e 5r7",
    "addr:street":"Arthur St W",
    "iso:country":"CA",
    "sg:address":"588 Arthur St W",
    "sg:city":"Thunder Bay",
    "sg:classifiers":[
        {
            "category":"Restaurant",
            "type":"Food & Drink"
        }
    ],
    "sg:phone":"+1 807 475 5930",
    "sg:postcode":"P7E 5R7",
    "sg:province":"ON",
    "wof:name":"A & W Family Restaurant",
    "wof:placetype":"venue"
},
  "geometry": {"coordinates":[-89.234268,48.380665],"type":"Point"}
}