{
  "type": "Feature",
  "properties": {
    "addr:full":"Bradford ON L3Z 3G3",
    "addr:postcode":"l3z 3g3",
    "iso:country":"CA",
    "sg:city":"Bradford",
    "sg:classifiers":[
        {
            "category":"Autos & Motor Vehicles",
            "subcategory":"Motorcycle Sales",
            "type":"Retail Goods"
        }
    ],
    "sg:phone":"+1 905 775 5838",
    "sg:postcode":"L3Z 3G3",
    "sg:province":"ON",
    "sg:tags":[
        "scooter"
    ],
    "wof:name":"Northern Motorsports",
    "wof:placetype":"venue"
},
  "geometry": {"coordinates":[-79.555786,44.135517],"type":"Point"}
}