{
  "type": "Feature",
  "properties": {
    "addr:full":"538 Rue Roussin #D Lac-Saint-Charles QC G3G 2C9",
    "addr:housenumber":"538;# d",
    "addr:postcode":"g3g 2c9",
    "addr:street":"Rue Roussin;Lac-Saint-Charles",
    "iso:country":"CA",
    "sg:address":"538 Rue Roussin #D",
    "sg:city":"Lac-Saint-Charles",
    "sg:classifiers":[
        {
            "category":"Building & Trades",
            "subcategory":"Construction",
            "type":"Services"
        }
    ],
    "sg:phone":"+1 418 849 7503",
    "sg:postcode":"G3G 2C9",
    "sg:province":"QC",
    "sg:tags":[
        "concrete",
        "contractor"
    ],
    "wof:name":"Construction Injection Edm Inc",
    "wof:placetype":"venue"
},
  "geometry": {"coordinates":[-71.3622055054,46.8923225403],"type":"Point"}
}