{
  "type": "Feature",
  "properties": {
    "addr:full":"Abbotsford BC V2T 5T5",
    "addr:postcode":"v2t 5t5",
    "iso:country":"CA",
    "sg:city":"Abbotsford",
    "sg:classifiers":[
        {
            "category":"Personal",
            "subcategory":"Beauty Salon",
            "type":"Services"
        }
    ],
    "sg:phone":"+1 604 854 6304",
    "sg:postcode":"V2T 5T5",
    "sg:province":"BC",
    "wof:name":"Hair By Design",
    "wof:placetype":"venue"
},
  "geometry": {"coordinates":[-122.315758,49.059566],"type":"Point"}
}