{
  "type": "Feature",
  "properties": {
    "addr:full":"1180 Kingdale Rd Newmarket ON L3Y 4W1",
    "addr:housenumber":"1180",
    "addr:postcode":"l3y 4w1",
    "addr:street":"Kingdale Rd",
    "iso:country":"CA",
    "sg:address":"1180 Kingdale Rd",
    "sg:city":"Newmarket",
    "sg:classifiers":[
        {
            "category":"Manufacturing",
            "subcategory":"Printing",
            "type":"Manufacturing & Wholesale Goods"
        }
    ],
    "sg:phone":"+1 905 513 3999",
    "sg:postcode":"L3Y 4W1",
    "sg:province":"ON",
    "sg:tags":[
        "publisher"
    ],
    "wof:name":"Graphic Arts Magazine",
    "wof:placetype":"venue"
},
  "geometry": {"coordinates":[-79.41938018800001,44.0448112488],"type":"Point"}
}