{
  "type": "Feature",
  "properties": {
    "addr:full":"2251 Lee Valley Rd Espanola ON P5E 1P7",
    "addr:housenumber":"2251",
    "addr:postcode":"p5e 1p7",
    "addr:street":"Lee Valley Rd",
    "iso:country":"CA",
    "sg:address":"2251 Lee Valley Rd",
    "sg:city":"Espanola",
    "sg:classifiers":[
        {
            "category":"Building & Trades",
            "subcategory":"Electrical",
            "type":"Services"
        }
    ],
    "sg:phone":"+1 705 869 3858",
    "sg:postcode":"P5E 1P7",
    "sg:province":"ON",
    "sg:tags":[
        "electric",
        "contractor"
    ],
    "wof:name":"Dan's Electric",
    "wof:placetype":"venue"
},
  "geometry": {"coordinates":[-81.798676,46.25013],"type":"Point"}
}