{
  "type": "Feature",
  "properties": {
    "addr:full":"1059 Ridgeway Ave Coquitlam BC V3J 1S6",
    "addr:housenumber":"1059",
    "addr:postcode":"v3j 1s6",
    "addr:street":"Ridgeway Ave",
    "iso:country":"CA",
    "sg:address":"1059 Ridgeway Ave",
    "sg:city":"Coquitlam",
    "sg:classifiers":[
        {
            "category":"Government",
            "subcategory":"Police Station",
            "type":"Public Place"
        }
    ],
    "sg:phone":"+1 604 933 6888",
    "sg:postcode":"V3J 1S6",
    "sg:province":"BC",
    "sg:tags":[
        "department"
    ],
    "wof:name":"Port Coquitlam Cmnty Police",
    "wof:placetype":"venue"
},
  "geometry": {"coordinates":[-122.86406700000001,49.249882],"type":"Point"}
}