{
  "type": "Feature",
  "properties": {
    "iso:country":"CA",
    "sg:address":"350 Viewmount Dr",
    "sg:city":"Nepean",
    "sg:classifiers":[
        {
            "category":"Health Services",
            "subcategory":"Doctor",
            "type":"Services"
        }
    ],
    "sg:phone":"+1 613 727 9346",
    "sg:postcode":"K2E 7T5",
    "sg:province":"ON",
    "sg:tags":[
        "dentist"
    ],
    "wof:name":"Malhotra, Rina DDS",
    "wof:placetype":"venue"
},
  "geometry": {"coordinates":[-75.71467590330001,45.3494796753],"type":"Point"}
}