{
  "type": "Feature",
  "properties": {
    "addr:full":"605 Boul Saint-Luc O Alma QC G8B 2K8",
    "addr:housenumber":"605",
    "addr:postcode":"g8b 2k8",
    "addr:street":"Boul Saint-Luc O",
    "iso:country":"CA",
    "sg:address":"605 Boul Saint-Luc O",
    "sg:city":"Alma",
    "sg:classifiers":[
        {
            "category":"Restaurant",
            "type":"Food & Drink"
        }
    ],
    "sg:phone":"+1 418 480 1888",
    "sg:postcode":"G8B 2K8",
    "sg:province":"QC",
    "wof:name":"Estrade",
    "wof:placetype":"venue"
},
  "geometry": {"coordinates":[-71.657898,48.538052],"type":"Point"}
}