{
  "type": "Feature",
  "properties": {
    "iso:country":"CA",
    "sg:address":"35 Laurel St",
    "sg:city":"Ottawa",
    "sg:classifiers":[
        {
            "category":"Manufacturing",
            "subcategory":"Tools & Machinery",
            "type":"Manufacturing & Wholesale Goods"
        }
    ],
    "sg:phone":"+1 613 761 7777",
    "sg:postcode":"K1Y 4M4",
    "sg:province":"ON",
    "sg:tags":[
        "disk",
        "supply",
        "equipment",
        "optical",
        "tape",
        "video",
        "duplication"
    ],
    "wof:name":"Ids Intl Duplication Svc Inc",
    "wof:placetype":"venue"
},
  "geometry": {"coordinates":[-75.7176742554,45.4051628113],"type":"Point"}
}