{
  "type": "Feature",
  "properties": {
    "addr:full":"1 Rice St Rosseau ON P0C 1J0",
    "addr:housenumber":"1",
    "addr:postcode":"p0c 1j0",
    "addr:street":"Rice St",
    "iso:country":"CA",
    "sg:address":"1 Rice St",
    "sg:city":"Rosseau",
    "sg:classifiers":[
        {
            "category":"Shopping",
            "subcategory":"Discount & Variety Stores",
            "type":"Retail Goods"
        }
    ],
    "sg:phone":"+1 705 732 4479",
    "sg:postcode":"P0C 1J0",
    "sg:province":"ON",
    "sg:tags":[
        "merchandise",
        "general"
    ],
    "wof:name":"Rosseau General Store",
    "wof:placetype":"venue"
},
  "geometry": {"coordinates":[-79.639709,45.256317],"type":"Point"}
}