{
  "type": "Feature",
  "properties": {
    "addr:full":"12321 97 St NW Edmonton AB T5G 1Z5",
    "addr:housenumber":"12321",
    "addr:postcode":"t5g 1z5",
    "addr:street":"97 St Nw",
    "iso:country":"CA",
    "sg:address":"12321 97 St NW",
    "sg:city":"Edmonton",
    "sg:classifiers":[
        {
            "category":"Government",
            "subcategory":"Office",
            "type":"Public Place"
        }
    ],
    "sg:phone":"+1 780 471 3405",
    "sg:postcode":"T5G 1Z5",
    "sg:province":"AB",
    "sg:tags":[
        "federal",
        "affairs"
    ],
    "wof:name":"Consulate of Nicaragua",
    "wof:placetype":"venue"
},
  "geometry": {"coordinates":[-113.491776,53.578606],"type":"Point"}
}