{
  "type": "Feature",
  "properties": {
    "iso:country":"CA",
    "sg:address":"8123 Wiltshire Pl",
    "sg:city":"Delta",
    "sg:classifiers":[
        {
            "category":"Professional",
            "subcategory":"Management & Consulting",
            "type":"Services"
        }
    ],
    "sg:phone":"+1 604 507 0600",
    "sg:postcode":"V4C 6T1",
    "sg:province":"BC",
    "sg:tags":[
        "consultant",
        "business"
    ],
    "wof:name":"Mhs Consulting Corp",
    "wof:placetype":"venue"
},
  "geometry": {"coordinates":[-122.930404663,49.1505851746],"type":"Point"}
}