{
  "type": "Feature",
  "properties": {
    "addr:full":"North York ON M2J 1W8",
    "addr:postcode":"m2j 1w8",
    "iso:country":"CA",
    "sg:city":"North York",
    "sg:classifiers":[
        {
            "category":"Insurance",
            "subcategory":"Insurance Agent",
            "type":"Services"
        }
    ],
    "sg:phone":"+1 416 499 2227",
    "sg:postcode":"M2J 1W8",
    "sg:province":"ON",
    "wof:name":"Medi Fast Inc",
    "wof:placetype":"venue"
},
  "geometry": {"coordinates":[-79.3304443359,43.7748718262],"type":"Point"}
}