{
  "type": "Feature",
  "properties": {
    "addr:full":"PO Box 2173 STN B Prince George BC V2N 2J6",
    "addr:housenumber":"po",
    "addr:postcode":"v2n 2j6",
    "addr:street":"Box 2173 Stn B",
    "iso:country":"CA",
    "sg:address":"PO Box 2173 STN B",
    "sg:city":"Prince George",
    "sg:classifiers":[
        {
            "category":"Building & Trades",
            "subcategory":"Plumbing",
            "type":"Services"
        }
    ],
    "sg:phone":"+1 250 563 6845",
    "sg:postcode":"V2N 2J6",
    "sg:province":"BC",
    "sg:tags":[
        "heating",
        "contractor"
    ],
    "wof:name":"Malcolm Heating Svc Ltd",
    "wof:placetype":"venue"
},
  "geometry": {"coordinates":[-122.74508667000001,53.9123497009],"type":"Point"}
}