{
  "type": "Feature",
  "properties": {
    "addr:full":"463 King St E Toronto ON M5A 1L6",
    "addr:housenumber":"463",
    "addr:postcode":"m5a 1l6",
    "addr:street":"King St E",
    "iso:country":"CA",
    "sg:address":"463 King St E",
    "sg:city":"Toronto",
    "sg:classifiers":[
        {
            "category":"Shopping",
            "type":"Retail Goods"
        }
    ],
    "sg:phone":"+1 416 364 3730",
    "sg:postcode":"M5A 1L6",
    "sg:province":"ON",
    "sg:tags":[
        "art",
        "gallery",
        "dealer"
    ],
    "wof:name":"John A Libby Fine Art",
    "wof:placetype":"venue"
},
  "geometry": {"coordinates":[-79.361,43.653954],"type":"Point"}
}