{
  "type": "Feature",
  "properties": {
    "addr:full":"2545 Lynburn Cres Nanaimo BC V9S 3T5",
    "addr:housenumber":"2545",
    "addr:postcode":"v9s 3t5",
    "addr:street":"Lynburn Cres",
    "iso:country":"CA",
    "sg:address":"2545 Lynburn Cres",
    "sg:city":"Nanaimo",
    "sg:classifiers":[
        {
            "category":"Social Services",
            "subcategory":"Job Training",
            "type":"Services"
        }
    ],
    "sg:phone":"+1 250 751 7872",
    "sg:postcode":"V9S 3T5",
    "sg:province":"BC",
    "sg:tags":[
        "rehabilitation"
    ],
    "wof:name":"Mid Island Occupational Thrpy",
    "wof:placetype":"venue"
},
  "geometry": {"coordinates":[-123.9729,49.200306],"type":"Point"}
}