{
  "type": "Feature",
  "properties": {
    "addr:full":"2402 10 Ave SW Calgary AB T3C 0K6",
    "addr:housenumber":"2402",
    "addr:postcode":"t3c 0k6",
    "addr:street":"10 Ave Sw",
    "iso:country":"CA",
    "sg:address":"2402 10 Ave SW",
    "sg:city":"Calgary",
    "sg:classifiers":[
        {
            "category":"Shopping",
            "subcategory":"Florist",
            "type":"Retail Goods"
        }
    ],
    "sg:phone":"+1 403 240 1115",
    "sg:postcode":"T3C 0K6",
    "sg:province":"AB",
    "sg:tags":[
        "plant"
    ],
    "wof:name":"Greenery Office Interiors Ltd",
    "wof:placetype":"venue"
},
  "geometry": {"coordinates":[-114.115898132,51.0453910828],"type":"Point"}
}