{
  "type": "Feature",
  "properties": {
    "addr:full":"Edmonton AB T5K 1C5",
    "addr:postcode":"t5k 1c5",
    "iso:country":"CA",
    "sg:city":"Edmonton",
    "sg:classifiers":[
        {
            "category":"Professional",
            "subcategory":"Management & Consulting",
            "type":"Services"
        }
    ],
    "sg:phone":"+1 780 436 2518",
    "sg:postcode":"T5K 1C5",
    "sg:province":"AB",
    "sg:tags":[
        "consultant",
        "business"
    ],
    "wof:name":"Acton Consulting Ltd",
    "wof:placetype":"venue"
},
  "geometry": {"coordinates":[-113.50316599999999,53.537567],"type":"Point"}
}