{
  "type": "Feature",
  "properties": {
    "addr:full":"375 Island Hwy W Parksville BC V9P 1A1",
    "addr:housenumber":"375",
    "addr:postcode":"v9p 1a1",
    "addr:street":"Island Hwy W",
    "iso:country":"CA",
    "sg:address":"375 Island Hwy W",
    "sg:city":"Parksville",
    "sg:classifiers":[
        {
            "category":"Travel",
            "subcategory":"Campground",
            "type":"Entertainment"
        }
    ],
    "sg:phone":"+1 250 248 6612",
    "sg:postcode":"V9P 1A1",
    "sg:province":"BC",
    "wof:name":"Paradise Sea-Side Resort Ltd",
    "wof:placetype":"venue"
},
  "geometry": {"coordinates":[-124.322655,49.32325],"type":"Point"}
}