{
  "type": "Feature",
  "properties": {
    "addr:full":"Beaucanton QC J0Z 1H0",
    "addr:postcode":"j0z 1h0",
    "iso:country":"CA",
    "sg:city":"Beaucanton",
    "sg:classifiers":[
        {
            "category":"Freight",
            "type":"Transportation"
        }
    ],
    "sg:phone":"+1 819 941 2307",
    "sg:postcode":"J0Z 1H0",
    "sg:province":"QC",
    "sg:tags":[
        "trucking"
    ],
    "wof:name":"Duchesne, Romeo",
    "wof:placetype":"venue"
},
  "geometry": {"coordinates":[-79.23960113530001,49.0392456055],"type":"Point"}
}