{
  "type": "Feature",
  "properties": {
    "addr:full":"1441 29 St NW Calgary AB T2N 4J8",
    "addr:housenumber":"1441",
    "addr:postcode":"t2n 4j8",
    "addr:street":"29 St Nw",
    "iso:country":"CA",
    "sg:address":"1441 29 St NW",
    "sg:city":"Calgary",
    "sg:classifiers":[
        {
            "category":"Health Services",
            "subcategory":"Doctor",
            "type":"Services"
        }
    ],
    "sg:phone":"+1 403 944 8475",
    "sg:postcode":"T2N 4J8",
    "sg:province":"AB",
    "sg:tags":[
        "physician",
        "surgeon"
    ],
    "wof:name":"Dline, Gregory MD",
    "wof:placetype":"venue"
},
  "geometry": {"coordinates":[-114.13067599999999,51.065044],"type":"Point"}
}