{
  "type": "Feature",
  "properties": {
    "iso:country":"CA",
    "sg:address":"8650 Boul Parent",
    "sg:city":"Trois-Rivieres",
    "sg:classifiers":[
        {
            "category":"Manufacturing",
            "subcategory":"Tools & Machinery",
            "type":"Manufacturing & Wholesale Goods"
        }
    ],
    "sg:phone":"+1 819 374 1000",
    "sg:postcode":"G9A 5E1",
    "sg:province":"QC",
    "sg:tags":[
        "fitting",
        "hose",
        "coupling",
        "hydraulic"
    ],
    "wof:name":"Hydraufab Enr",
    "wof:placetype":"venue"
},
  "geometry": {"coordinates":[-72.6444778442,46.3745384216],"type":"Point"}
}