{
  "type": "Feature",
  "properties": {
    "addr:full":"924 Rathburn Rd E Mississauga ON L4W 4H5",
    "addr:housenumber":"924",
    "addr:postcode":"l4w 4h5",
    "addr:street":"Rathburn Rd E",
    "iso:country":"CA",
    "sg:address":"924 Rathburn Rd E",
    "sg:city":"Mississauga",
    "sg:classifiers":[
        {
            "category":"Real Estate",
            "subcategory":"Real Estate Operator",
            "type":"Services"
        }
    ],
    "sg:phone":"+1 905 273 9508",
    "sg:postcode":"L4W 4H5",
    "sg:province":"ON",
    "sg:tags":[
        "apartment"
    ],
    "wof:name":"Samuel Property Management",
    "wof:placetype":"venue"
},
  "geometry": {"coordinates":[-79.6166610718,43.6155128479],"type":"Point"}
}