{
  "type": "Feature",
  "properties": {
    "addr:full":"55 Kearney Lake Rd Halifax NS B3M 2S6",
    "addr:housenumber":"55",
    "addr:postcode":"b3m 2s6",
    "addr:street":"Kearney Lake Rd",
    "iso:country":"CA",
    "sg:address":"55 Kearney Lake Rd",
    "sg:city":"Halifax",
    "sg:classifiers":[
        {
            "category":"Social Services",
            "subcategory":"Child Care",
            "type":"Services"
        }
    ],
    "sg:phone":"+1 902 443 2273",
    "sg:postcode":"B3M 2S6",
    "sg:province":"NS",
    "wof:name":"Wedgewoods Little School",
    "wof:placetype":"venue"
},
  "geometry": {"coordinates":[-63.666683197,44.6813011169],"type":"Point"}
}