{
  "type": "Feature",
  "properties": {
    "addr:full":"35 Mill St W Leamington ON N8H 1S7",
    "addr:housenumber":"35",
    "addr:postcode":"n8h 1s7",
    "addr:street":"Mill St W",
    "iso:country":"CA",
    "sg:address":"35 Mill St W",
    "sg:city":"Leamington",
    "sg:classifiers":[
        {
            "category":"Shopping",
            "subcategory":"Clothing, Apparel, & Fashions",
            "type":"Retail Goods"
        }
    ],
    "sg:phone":"+1 519 322 2442",
    "sg:postcode":"N8H 1S7",
    "sg:province":"ON",
    "sg:tags":[
        "dressmaker"
    ],
    "wof:name":"Beny's Custom Sewing Shoppe",
    "wof:placetype":"venue"
},
  "geometry": {"coordinates":[-82.6002960205,42.0523757935],"type":"Point"}
}