{
  "type": "Feature",
  "properties": {
    "addr:full":"110 1st Ave E Nipawin SK S0E 1E0",
    "addr:housenumber":"110",
    "addr:postcode":"s0e 1e0",
    "addr:street":"1St Ave E Nipawin",
    "iso:country":"CA",
    "sg:address":"110 1st Ave E",
    "sg:city":"Nipawin",
    "sg:classifiers":[
        {
            "category":"Shopping",
            "subcategory":"Jewelry",
            "type":"Retail Goods"
        }
    ],
    "sg:phone":"+1 306 862 3055",
    "sg:postcode":"S0E 1E0",
    "sg:province":"SK",
    "sg:tags":[
        "jeweler"
    ],
    "wof:name":"E Butt Watch & Clock Repair",
    "wof:placetype":"venue"
},
  "geometry": {"coordinates":[-104.016701,53.362408],"type":"Point"}
}