{
  "type": "Feature",
  "properties": {
    "addr:full":"38 Pine St N Timmins ON P4N 6K6",
    "addr:housenumber":"38",
    "addr:postcode":"p4n 6k6",
    "addr:street":"Pine St N",
    "iso:country":"CA",
    "sg:address":"38 Pine St N",
    "sg:city":"Timmins",
    "sg:classifiers":[
        {
            "category":"Professional",
            "subcategory":"Management & Consulting",
            "type":"Services"
        }
    ],
    "sg:phone":"+1 705 360 5800",
    "sg:postcode":"P4N 6K6",
    "sg:province":"ON",
    "sg:tags":[
        "development",
        "economic",
        "agency"
    ],
    "wof:name":"Venture Centre",
    "wof:placetype":"venue"
},
  "geometry": {"coordinates":[-81.3281326294,48.4770469666],"type":"Point"}
}