{
  "type": "Feature",
  "properties": {
    "addr:full":"531 Park St N Peterborough ON K9H 4R6",
    "addr:housenumber":"531",
    "addr:postcode":"k9h 4r6",
    "addr:street":"Park St N",
    "iso:country":"CA",
    "sg:address":"531 Park St N",
    "sg:city":"Peterborough",
    "sg:classifiers":[
        {
            "category":"Shopping",
            "subcategory":"Musical Instruments",
            "type":"Retail Goods"
        }
    ],
    "sg:phone":"+1 705 743 2641",
    "sg:postcode":"K9H 4R6",
    "sg:province":"ON",
    "wof:name":"Ed's Music Workshop",
    "wof:placetype":"venue"
},
  "geometry": {"coordinates":[-78.3326416016,44.3092765808],"type":"Point"}
}