{
  "type": "Feature",
  "properties": {
    "addr:full":"1000 Elgin St W Cobourg ON K9A 5S1",
    "addr:housenumber":"1000",
    "addr:postcode":"k9a 5s1",
    "addr:street":"Elgin St W",
    "iso:country":"CA",
    "sg:address":"1000 Elgin St W",
    "sg:city":"Cobourg",
    "sg:classifiers":[
        {
            "category":"Cinema",
            "subcategory":"Movie Rental",
            "type":"Entertainment"
        }
    ],
    "sg:phone":"+1 905 373 4904",
    "sg:postcode":"K9A 5S1",
    "sg:province":"ON",
    "sg:tags":[
        "leasing",
        "video",
        "disc",
        "tape"
    ],
    "wof:name":"Blockbuster",
    "wof:placetype":"venue"
},
  "geometry": {"coordinates":[-78.19699900000001,43.972012],"type":"Point"}
}