{
  "type": "Feature",
  "properties": {
    "addr:full":"275 Brockville St Smiths Falls ON K7A 4Z6",
    "addr:housenumber":"275",
    "addr:postcode":"k7a 4z6",
    "addr:street":"Brockville St",
    "iso:country":"CA",
    "sg:address":"275 Brockville St",
    "sg:city":"Smiths Falls",
    "sg:classifiers":[
        {
            "category":"Shopping",
            "subcategory":"Pharmacy",
            "type":"Retail Goods"
        }
    ],
    "sg:phone":"+1 613 283 9363",
    "sg:postcode":"K7A 4Z6",
    "sg:province":"ON",
    "wof:name":"Zellers Pharmacy",
    "wof:placetype":"venue"
},
  "geometry": {"coordinates":[-76.01778411870001,44.8832740784],"type":"Point"}
}