{
  "type": "Feature",
  "properties": {
    "iso:country":"CA",
    "sg:address":"215 Houston St",
    "sg:city":"Nelson",
    "sg:classifiers":[
        {
            "category":"Travel",
            "subcategory":"Hotels & Motels",
            "type":"Entertainment"
        }
    ],
    "sg:phone":"+1 250 505 3663",
    "sg:postcode":"V1L 5H1",
    "sg:province":"BC",
    "sg:tags":[
        "breakfast",
        "accommodation",
        "bed"
    ],
    "wof:name":"Kiwi Vine Family Guesthouse",
    "wof:placetype":"venue"
},
  "geometry": {"coordinates":[-117.290458679,49.4822731018],"type":"Point"}
}