{
  "type": "Feature",
  "properties": {
    "iso:country":"CA",
    "sg:address":"1260 Ch Filteau",
    "sg:city":"Saint-Nicolas",
    "sg:classifiers":[
        {
            "category":"Wholesale",
            "subcategory":"Durable Goods & Equipment",
            "type":"Manufacturing & Wholesale Goods"
        }
    ],
    "sg:phone":"+1 418 831 1085",
    "sg:postcode":"G7A 2M1",
    "sg:province":"QC",
    "sg:tags":[
        "representative",
        "manufacturer"
    ],
    "wof:name":"Fertilec Limitee",
    "wof:placetype":"venue"
},
  "geometry": {"coordinates":[-71.35814666749999,46.6732215881],"type":"Point"}
}