{
  "type": "Feature",
  "properties": {
    "addr:full":"Sainte-Marthe-Sur-Le-Lac QC J0N 1P0",
    "addr:postcode":"j0n 1p0",
    "iso:country":"CA",
    "sg:city":"Sainte-Marthe-Sur-Le-Lac",
    "sg:classifiers":[
        {
            "category":"Social Services",
            "type":"Services"
        }
    ],
    "sg:phone":"+1 450 623 2112",
    "sg:postcode":"J0N 1P0",
    "sg:province":"QC",
    "sg:tags":[
        "organization",
        "welfare"
    ],
    "wof:name":"Fondation Emile-Z-Laviolette",
    "wof:placetype":"venue"
},
  "geometry": {"coordinates":[-73.99458312989999,45.5016860962],"type":"Point"}
}