{
  "type": "Feature",
  "properties": {
    "iso:country":"CA",
    "sg:address":"398 Ferrier St",
    "sg:city":"Markham",
    "sg:classifiers":[
        {
            "category":"Personal",
            "subcategory":"Beauty Salon",
            "type":"Services"
        }
    ],
    "sg:phone":"+1 905 944 1555",
    "sg:postcode":"L3R 2Z5",
    "sg:province":"ON",
    "wof:name":"Meng Er Beautician & Hair Styl",
    "wof:placetype":"venue"
},
  "geometry": {"coordinates":[-79.331085,43.820442],"type":"Point"}
}