{
  "type": "Feature",
  "properties": {
    "addr:full":"1840 Meyerside Dr Mississauga ON L5T 1B4",
    "addr:housenumber":"1840",
    "addr:postcode":"l5t 1b4",
    "addr:street":"Meyerside Dr",
    "iso:country":"CA",
    "sg:address":"1840 Meyerside Dr",
    "sg:city":"Mississauga",
    "sg:classifiers":[
        {
            "category":"Manufacturing",
            "subcategory":"Wood Products",
            "type":"Manufacturing & Wholesale Goods"
        }
    ],
    "sg:phone":"+1 905 564 6826",
    "sg:postcode":"L5T 1B4",
    "sg:province":"ON",
    "sg:tags":[
        "rubber",
        "metal",
        "roller"
    ],
    "wof:name":"Rotadyne Inc",
    "wof:placetype":"venue"
},
  "geometry": {"coordinates":[-79.6462860107,43.6668891907],"type":"Point"}
}