{
  "type": "Feature",
  "properties": {
    "addr:full":"342 Av Dorval #18 Dorval QC H9S 3H7",
    "addr:postcode":"h9s 3h7",
    "addr:street":"342 Av Dorval # 18",
    "iso:country":"CA",
    "sg:address":"342 Av Dorval #18",
    "sg:city":"Dorval",
    "sg:classifiers":[
        {
            "category":"Health Services",
            "subcategory":"Doctor",
            "type":"Services"
        }
    ],
    "sg:phone":"+1 514 636 5760",
    "sg:postcode":"H9S 3H7",
    "sg:province":"QC",
    "sg:tags":[
        "dentist"
    ],
    "wof:name":"Baskin, Leonard DDS",
    "wof:placetype":"venue"
},
  "geometry": {"coordinates":[-73.741096,45.444084],"type":"Point"}
}