{
  "type": "Feature",
  "properties": {
    "addr:full":"120 Winges Rd Woodbridge ON L4L 6C2",
    "addr:housenumber":"120",
    "addr:postcode":"l4l 6c2",
    "addr:street":"Winges Rd",
    "iso:country":"CA",
    "sg:address":"120 Winges Rd",
    "sg:city":"Woodbridge",
    "sg:classifiers":[
        {
            "category":"Organizations",
            "subcategory":"Community Association",
            "type":"Services"
        }
    ],
    "sg:phone":"+1 905 850 8095",
    "sg:postcode":"L4L 6C2",
    "sg:province":"ON",
    "sg:tags":[
        "club"
    ],
    "wof:name":"Due Torri Social Club",
    "wof:placetype":"venue"
},
  "geometry": {"coordinates":[-79.55252075200001,43.7872200012],"type":"Point"}
}