{
  "type": "Feature",
  "properties": {
    "addr:full":"7 Victoria St W Alliston ON L9R 1S9",
    "addr:housenumber":"7",
    "addr:postcode":"l9r 1s9",
    "addr:street":"Victoria St W Alliston",
    "iso:country":"CA",
    "sg:address":"7 Victoria St W",
    "sg:city":"Alliston",
    "sg:classifiers":[
        {
            "category":"Real Estate",
            "subcategory":"Real Estate Agent",
            "type":"Services"
        }
    ],
    "sg:phone":"+1 705 435 3000",
    "sg:postcode":"L9R 1S9",
    "sg:province":"ON",
    "wof:name":"Complete Realty Inc",
    "wof:placetype":"venue"
},
  "geometry": {"coordinates":[-79.86949157710001,44.1537780762],"type":"Point"}
}