{
  "type": "Feature",
  "properties": {
    "addr:full":"559 131 Rte Joliette QC J6E 7Y8",
    "addr:housenumber":"131",
    "addr:postcode":"j6e 7y8",
    "addr:street":"Rte Joliette",
    "iso:country":"CA",
    "sg:address":"559 131 Rte",
    "sg:city":"Joliette",
    "sg:classifiers":[
        {
            "category":"Building & Trades",
            "subcategory":"Construction",
            "type":"Services"
        }
    ],
    "sg:phone":"+1 450 753 7236",
    "sg:postcode":"J6E 7Y8",
    "sg:province":"QC",
    "sg:tags":[
        "roof",
        "structure"
    ],
    "wof:name":"Toiture Mauricienne Inc",
    "wof:placetype":"venue"
},
  "geometry": {"coordinates":[-73.441956,46.023571],"type":"Point"}
}