{
  "type": "Feature",
  "properties": {
    "addr:full":"Granby QC J2J 1E9",
    "addr:postcode":"j2j 1e9",
    "iso:country":"CA",
    "sg:city":"Granby",
    "sg:classifiers":[
        {
            "category":"Professional",
            "subcategory":"Management & Consulting",
            "type":"Services"
        }
    ],
    "sg:phone":"+1 450 776 3600",
    "sg:postcode":"J2J 1E9",
    "sg:province":"QC",
    "sg:tags":[
        "marketing",
        "all",
        "program",
        "terrain",
        "vehicle"
    ],
    "wof:name":"Bombardier Inc Utility Vhcls",
    "wof:placetype":"venue"
},
  "geometry": {"coordinates":[-72.775345,45.387569],"type":"Point"}
}