{
  "type": "Feature",
  "properties": {
    "addr:full":"18 Ganley St Wawa ON P0S 1K0",
    "addr:housenumber":"18",
    "addr:postcode":"p0s 1k0",
    "addr:street":"Ganley St",
    "iso:country":"CA",
    "sg:address":"18 Ganley St",
    "sg:city":"Wawa",
    "sg:classifiers":[
        {
            "category":"Social Services",
            "type":"Services"
        }
    ],
    "sg:phone":"+1 705 856 7208",
    "sg:postcode":"P0S 1K0",
    "sg:province":"ON",
    "sg:tags":[
        "pregnancy",
        "counseling",
        "information"
    ],
    "wof:name":"Algoma Health Unit",
    "wof:placetype":"venue"
},
  "geometry": {"coordinates":[-84.77159881590001,47.9958496094],"type":"Point"}
}