{
  "type": "Feature",
  "properties": {
    "addr:full":"8874 116 St Delta BC V4C 5W5",
    "addr:housenumber":"8874",
    "addr:postcode":"v4c 5w5",
    "addr:street":"116 St",
    "iso:country":"CA",
    "sg:address":"8874 116 St",
    "sg:city":"Delta",
    "sg:classifiers":[
        {
            "category":"Building & Trades",
            "subcategory":"Cleaning & Sanitation",
            "type":"Services"
        }
    ],
    "sg:phone":"+1 604 592 0985",
    "sg:postcode":"V4C 5W5",
    "sg:province":"BC",
    "sg:tags":[
        "janitor"
    ],
    "wof:name":"Image Building Maintenance",
    "wof:placetype":"venue"
},
  "geometry": {"coordinates":[-122.901916504,49.1647949219],"type":"Point"}
}