{
  "type": "Feature",
  "properties": {
    "addr:full":"108 Montee Du Moulin Laval QC H7N 3Y6",
    "addr:housenumber":"108",
    "addr:postcode":"h7n 3y6",
    "addr:street":"Montee Du Moulin",
    "iso:country":"CA",
    "sg:address":"108 Montee Du Moulin",
    "sg:city":"Laval",
    "sg:classifiers":[
        {
            "category":"Food & Beverages",
            "subcategory":"Specialty",
            "type":"Retail Goods"
        }
    ],
    "sg:phone":"+1 450 663 7117",
    "sg:postcode":"H7N 3Y6",
    "sg:province":"QC",
    "sg:tags":[
        "game",
        "venison",
        "bird"
    ],
    "wof:name":"Cunico Ltee",
    "wof:placetype":"venue"
},
  "geometry": {"coordinates":[-73.70478799999999,45.554558],"type":"Point"}
}