{
  "type": "Feature",
  "properties": {
    "addr:full":"44 Parkside St Minden ON K0M 2K0",
    "addr:housenumber":"44",
    "addr:postcode":"k0m 2k0",
    "addr:street":"Parkside St",
    "iso:country":"CA",
    "sg:address":"44 Parkside St",
    "sg:city":"Minden",
    "sg:classifiers":[
        {
            "category":"Social Services",
            "type":"Services"
        }
    ],
    "sg:phone":"+1 705 286 3444",
    "sg:postcode":"K0M 2K0",
    "sg:province":"ON",
    "sg:tags":[
        "housing",
        "assistance"
    ],
    "wof:name":"Staanworth Non Profit Housing",
    "wof:placetype":"venue"
},
  "geometry": {"coordinates":[-78.726868,44.930393],"type":"Point"}
}