{
  "type": "Feature",
  "properties": {
    "addr:full":"Deer Lake NL A8A 2H2",
    "addr:postcode":"a8a 2h2",
    "iso:country":"CA",
    "sg:city":"Deer Lake",
    "sg:classifiers":[
        {
            "category":"Retail",
            "subcategory":"Auto Repair",
            "type":"Services"
        }
    ],
    "sg:phone":"+1 709 635 3737",
    "sg:postcode":"A8A 2H2",
    "sg:province":"NL",
    "sg:tags":[
        "alternator",
        "automobile",
        "electric",
        "starter"
    ],
    "wof:name":"Adams Alternators & Starters",
    "wof:placetype":"venue"
},
  "geometry": {"coordinates":[-57.4236602783,49.1753387451],"type":"Point"}
}