{
  "type": "Feature",
  "properties": {
    "addr:full":"48 Rue Sylvio Dieppe NB E1A 7W6",
    "addr:housenumber":"48",
    "addr:postcode":"e1a 7w6",
    "addr:street":"Rue Sylvio",
    "iso:country":"CA",
    "sg:address":"48 Rue Sylvio",
    "sg:city":"Dieppe",
    "sg:classifiers":[
        {
            "category":"Freight",
            "type":"Transportation"
        }
    ],
    "sg:phone":"+1 506 386 8270",
    "sg:postcode":"E1A 7W6",
    "sg:province":"NB",
    "sg:tags":[
        "trucking"
    ],
    "wof:name":"Andlauer Transportation Svc",
    "wof:placetype":"venue"
},
  "geometry": {"coordinates":[-64.70117999999999,46.109543],"type":"Point"}
}