{
  "type": "Feature",
  "properties": {
    "addr:full":"140 Aberdeen Ave Saint John NB E2P 1E4",
    "addr:housenumber":"140",
    "addr:postcode":"e2p 1e4",
    "addr:street":"Aberdeen Ave",
    "iso:country":"CA",
    "sg:address":"140 Aberdeen Ave",
    "sg:city":"Saint John",
    "sg:classifiers":[
        {
            "category":"Retail",
            "subcategory":"Animal Services",
            "type":"Services"
        }
    ],
    "sg:phone":"+1 506 636 6966",
    "sg:postcode":"E2P 1E4",
    "sg:province":"NB",
    "sg:tags":[
        "pet",
        "grooming",
        "washing"
    ],
    "wof:name":"Dogspa",
    "wof:placetype":"venue"
},
  "geometry": {"coordinates":[-65.9952926636,45.2489395142],"type":"Point"}
}