{
  "type": "Feature",
  "properties": {
    "addr:full":"408 Boul Jessop Rimouski QC G5L 1N2",
    "addr:housenumber":"408",
    "addr:postcode":"g5l 1n2",
    "addr:street":"Boul Jessop",
    "iso:country":"CA",
    "sg:address":"408 Boul Jessop",
    "sg:city":"Rimouski",
    "sg:classifiers":[
        {
            "category":"Manufacturing",
            "subcategory":"Petroleum Products",
            "type":"Manufacturing & Wholesale Goods"
        }
    ],
    "sg:phone":"+1 418 723 2356",
    "sg:postcode":"G5L 1N2",
    "sg:province":"QC",
    "sg:tags":[
        "lubricant"
    ],
    "wof:name":"Sinto Racing",
    "wof:placetype":"venue"
},
  "geometry": {"coordinates":[-68.5161819458,48.4673538208],"type":"Point"}
}