{
  "type": "Feature",
  "properties": {
    "addr:full":"1005 William St Cobourg ON K9A 5J4",
    "addr:housenumber":"1005",
    "addr:postcode":"k9a 5j4",
    "addr:street":"William St",
    "iso:country":"CA",
    "sg:address":"1005 William St",
    "sg:city":"Cobourg",
    "sg:classifiers":[
        {
            "category":"Education",
            "subcategory":"College",
            "type":"Public Place"
        }
    ],
    "sg:phone":"+1 905 372 6865",
    "sg:postcode":"K9A 5J4",
    "sg:province":"ON",
    "sg:tags":[
        "academic",
        "school"
    ],
    "wof:name":"Sir Sandford Fleming College",
    "wof:placetype":"venue"
},
  "geometry": {"coordinates":[-78.192947,43.972389],"type":"Point"}
}