{
  "type": "Feature",
  "properties": {
    "iso:country":"CA",
    "sg:address":"3600 Kempt Rd",
    "sg:city":"Halifax",
    "sg:classifiers":[
        {
            "category":"Real Estate",
            "subcategory":"Real Estate Agent",
            "type":"Services"
        }
    ],
    "sg:phone":"+1 902 453 5051",
    "sg:postcode":"B3K 4X8",
    "sg:province":"NS",
    "sg:tags":[
        "appraiser"
    ],
    "wof:name":"Fennell & Assoc Appraisers Ltd",
    "wof:placetype":"venue"
},
  "geometry": {"coordinates":[-63.616726,44.66188],"type":"Point"}
}