{
  "type": "Feature",
  "properties": {
    "addr:full":"4497 Drummond Rd Niagara Falls ON L2E 6C5",
    "addr:housenumber":"4497",
    "addr:postcode":"l2e 6c5",
    "addr:street":"Drummond Rd",
    "iso:country":"CA",
    "sg:address":"4497 Drummond Rd",
    "sg:city":"Niagara Falls",
    "sg:classifiers":[
        {
            "category":"Food & Beverages",
            "subcategory":"Groceries & Convenience Stores",
            "type":"Retail Goods"
        }
    ],
    "sg:phone":"+1 905 356 8090",
    "sg:postcode":"L2E 6C5",
    "sg:province":"ON",
    "wof:name":"Avondale Stores Ltd",
    "wof:placetype":"venue"
},
  "geometry": {"coordinates":[-79.098778,43.107525],"type":"Point"}
}