{
  "type": "Feature",
  "properties": {
    "addr:full":"545 249 Rte Windsor QC J1S 2L5",
    "addr:housenumber":"545 249",
    "addr:postcode":"j1s 2l5",
    "addr:street":"Rte Windsor",
    "iso:country":"CA",
    "sg:address":"545 249 Rte",
    "sg:city":"Windsor",
    "sg:classifiers":[
        {
            "category":"Building & Trades",
            "subcategory":"Construction",
            "type":"Services"
        }
    ],
    "sg:phone":"+1 819 845 5436",
    "sg:postcode":"J1S 2L5",
    "sg:province":"QC",
    "sg:tags":[
        "general",
        "contractor"
    ],
    "wof:name":"Constructions Edb",
    "wof:placetype":"venue"
},
  "geometry": {"coordinates":[-72.0065,45.569019],"type":"Point"}
}