{
  "type": "Feature",
  "properties": {
    "addr:full":"5105 51 Ave Drayton Valley AB T7A 1R5",
    "addr:housenumber":"5105",
    "addr:postcode":"t7a 1r5",
    "addr:street":"51 Ave",
    "iso:country":"CA",
    "sg:address":"5105 51 Ave",
    "sg:city":"Drayton Valley",
    "sg:classifiers":[
        {
            "category":"Personal",
            "subcategory":"Beauty Salon",
            "type":"Services"
        }
    ],
    "sg:phone":"+1 780 542 5334",
    "sg:postcode":"T7A 1R5",
    "sg:province":"AB",
    "wof:name":"Health Connection",
    "wof:placetype":"venue"
},
  "geometry": {"coordinates":[-114.97859954800001,53.2222557068],"type":"Point"}
}