{
  "type": "Feature",
  "properties": {
    "addr:full":"2 Guelph St Georgetown ON L7G 3Y9",
    "addr:housenumber":"2",
    "addr:postcode":"l7g 3y9",
    "addr:street":"Guelph St",
    "iso:country":"CA",
    "sg:address":"2 Guelph St",
    "sg:city":"Georgetown",
    "sg:classifiers":[
        {
            "category":"Health Services",
            "subcategory":"Chiropractor",
            "type":"Services"
        }
    ],
    "sg:phone":"+1 905 873 3113",
    "sg:postcode":"L7G 3Y9",
    "sg:province":"ON",
    "wof:name":"Lifestyle Family Chiropractic",
    "wof:placetype":"venue"
},
  "geometry": {"coordinates":[-79.9284667969,43.6514129639],"type":"Point"}
}