{
  "type": "Feature",
  "properties": {
    "addr:full":"251 Bridge St Eganville ON K0J 1T0",
    "addr:housenumber":"251",
    "addr:postcode":"k0j 1t0",
    "addr:street":"Bridge St",
    "iso:country":"CA",
    "sg:address":"251 Bridge St",
    "sg:city":"Eganville",
    "sg:classifiers":[
        {
            "category":"Shopping",
            "subcategory":"Pharmacy",
            "type":"Retail Goods"
        }
    ],
    "sg:phone":"+1 613 628 2808",
    "sg:postcode":"K0J 1T0",
    "sg:province":"ON",
    "wof:name":"Conway's Pharmacy",
    "wof:placetype":"venue"
},
  "geometry": {"coordinates":[-77.10086099999999,45.539253],"type":"Point"}
}