{
  "type": "Feature",
  "properties": {
    "addr:full":"7179 Rue Waverly Montreal QC H2S 3J1",
    "addr:housenumber":"7179",
    "addr:postcode":"h2s 3j1",
    "addr:street":"Rue Waverly",
    "iso:country":"CA",
    "sg:address":"7179 Rue Waverly",
    "sg:city":"Montreal",
    "sg:classifiers":[
        {
            "category":"Building & Trades",
            "subcategory":"Landscaping Services",
            "type":"Services"
        }
    ],
    "sg:phone":"+1 514 279 1130",
    "sg:postcode":"H2S 3J1",
    "sg:province":"QC",
    "sg:tags":[
        "plant",
        "landscape",
        "contractor"
    ],
    "wof:name":"Aralia",
    "wof:placetype":"venue"
},
  "geometry": {"coordinates":[-73.61926269529999,45.5329093933],"type":"Point"}
}