{
  "type": "Feature",
  "properties": {
    "addr:full":"445 Rue DE L'Hotel-Dieu Chicoutimi QC G7H 1V6",
    "addr:housenumber":"445",
    "addr:postcode":"g7h 1v6",
    "addr:street":"Rue De L'Hotel-Dieu",
    "iso:country":"CA",
    "sg:address":"445 Rue DE L'Hotel-Dieu",
    "sg:city":"Chicoutimi",
    "sg:classifiers":[
        {
            "category":"Personal",
            "subcategory":"Beauty Salon",
            "type":"Services"
        }
    ],
    "sg:phone":"+1 418 549 5722",
    "sg:postcode":"G7H 1V6",
    "sg:province":"QC",
    "wof:name":"Salon DE Coiffure Amadeus",
    "wof:placetype":"venue"
},
  "geometry": {"coordinates":[-71.05658699999999,48.427261],"type":"Point"}
}