{
  "type": "Feature",
  "properties": {
    "addr:full":"967 Rue Labelle Saint-Jerome QC J7Z 5N3",
    "addr:housenumber":"967",
    "addr:postcode":"j7z 5n3",
    "addr:street":"Rue Labelle Saint-Jerome",
    "iso:country":"CA",
    "sg:address":"967 Rue Labelle",
    "sg:city":"Saint-Jerome",
    "sg:classifiers":[
        {
            "category":"Professional",
            "subcategory":"Accounting & Tax Preparation",
            "type":"Services"
        }
    ],
    "sg:phone":"+1 450 432 5478",
    "sg:postcode":"J7Z 5N3",
    "sg:province":"QC",
    "sg:tags":[
        "accountant"
    ],
    "wof:name":"Nelson Nadeau",
    "wof:placetype":"venue"
},
  "geometry": {"coordinates":[-74.00727844239999,45.7911224365],"type":"Point"}
}