{
  "type": "Feature",
  "properties": {
    "addr:full":"75 King St W Brockville ON K6V 3R1",
    "addr:housenumber":"75",
    "addr:postcode":"k6v 3r1",
    "addr:street":"King St W",
    "iso:country":"CA",
    "sg:address":"75 King St W",
    "sg:city":"Brockville",
    "sg:classifiers":[
        {
            "category":"Shopping",
            "subcategory":"Clothing, Apparel, & Fashions",
            "type":"Retail Goods"
        }
    ],
    "sg:phone":"+1 613 345 1310",
    "sg:postcode":"K6V 3R1",
    "sg:province":"ON",
    "sg:tags":[
        "jean"
    ],
    "wof:name":"Biba",
    "wof:placetype":"venue"
},
  "geometry": {"coordinates":[-75.68506622309999,44.5889854431],"type":"Point"}
}