{
  "type": "Feature",
  "properties": {
    "addr:full":"2100 Rue King O Sherbrooke QC J1J 2E8",
    "addr:housenumber":"2100",
    "addr:postcode":"j1j 2e8",
    "addr:street":"Rue King O",
    "iso:country":"CA",
    "sg:address":"2100 Rue King O",
    "sg:city":"Sherbrooke",
    "sg:classifiers":[
        {
            "category":"Organizations",
            "subcategory":"Labor Organization",
            "type":"Services"
        }
    ],
    "sg:phone":"+1 819 562 3922",
    "sg:postcode":"J1J 2E8",
    "sg:province":"QC",
    "wof:name":"Ftq Conseil Des Travailleurs",
    "wof:placetype":"venue"
},
  "geometry": {"coordinates":[-71.924538,45.398006],"type":"Point"}
}