{
  "type": "Feature",
  "properties": {
    "addr:full":"7 Deekshill Dr Scarborough ON M1E 3R5",
    "addr:housenumber":"7",
    "addr:postcode":"m1e 3r5",
    "addr:street":"Deekshill Dr",
    "iso:country":"CA",
    "sg:address":"7 Deekshill Dr",
    "sg:city":"Scarborough",
    "sg:classifiers":[
        {
            "category":"Home & Garden",
            "subcategory":"Household Appliances",
            "type":"Retail Goods"
        }
    ],
    "sg:phone":"+1 416 284 9774",
    "sg:postcode":"M1E 3R5",
    "sg:province":"ON",
    "wof:name":"Commonwealth Appliance Svc",
    "wof:placetype":"venue"
},
  "geometry": {"coordinates":[-79.17892500000001,43.763844],"type":"Point"}
}