{
  "type": "Feature",
  "properties": {
    "iso:country":"CA",
    "sg:address":"97 King St E",
    "sg:city":"Oshawa",
    "sg:classifiers":[
        {
            "category":"Shopping",
            "subcategory":"Pharmacy",
            "type":"Retail Goods"
        }
    ],
    "sg:phone":"+1 905 433 1566",
    "sg:postcode":"L1H 1B8",
    "sg:province":"ON",
    "wof:name":"Guardian Savers Drug Mart",
    "wof:placetype":"venue"
},
  "geometry": {"coordinates":[-78.86000823969999,43.898273468],"type":"Point"}
}