{
  "type": "Feature",
  "properties": {
    "iso:country":"CA",
    "sg:address":"265 Edward St",
    "sg:city":"Aurora",
    "sg:classifiers":[
        {
            "category":"Restaurant",
            "type":"Food & Drink"
        }
    ],
    "sg:phone":"+1 905 713 0719",
    "sg:postcode":"L4G 3M7",
    "sg:province":"ON",
    "sg:tags":[
        "parlor",
        "ice",
        "cream"
    ],
    "wof:name":"Dairy Queen",
    "wof:placetype":"venue"
},
  "geometry": {"coordinates":[-79.462097,43.987064],"type":"Point"}
}