{
  "type": "Feature",
  "properties": {
    "addr:full":"301 Webster Ave Winnipeg MB R2C 3E2",
    "addr:housenumber":"301",
    "addr:postcode":"r2c 3e2",
    "addr:street":"Webster Ave",
    "iso:country":"CA",
    "sg:address":"301 Webster Ave",
    "sg:city":"Winnipeg",
    "sg:classifiers":[
        {
            "category":"Building & Trades",
            "subcategory":"Electrical",
            "type":"Services"
        }
    ],
    "sg:phone":"+1 204 224 1533",
    "sg:postcode":"R2C 3E2",
    "sg:province":"MB",
    "sg:tags":[
        "electric",
        "contractor"
    ],
    "wof:name":"Southside Electric",
    "wof:placetype":"venue"
},
  "geometry": {"coordinates":[-97.0004272461,49.8819046021],"type":"Point"}
}