{
  "type": "Feature",
  "properties": {
    "addr:full":"7220 Pioneer Ave Agassiz BC V0M 1A0",
    "addr:housenumber":"7220",
    "addr:postcode":"v0m 1a0",
    "addr:street":"Pioneer Ave",
    "iso:country":"CA",
    "sg:address":"7220 Pioneer Ave",
    "sg:city":"Agassiz",
    "sg:classifiers":[
        {
            "category":"Shopping",
            "subcategory":"Florist",
            "type":"Retail Goods"
        }
    ],
    "sg:phone":"+1 604 796 2596",
    "sg:postcode":"V0M 1A0",
    "sg:province":"BC",
    "wof:name":"Holly Tree Florist & Gifts",
    "wof:placetype":"venue"
},
  "geometry": {"coordinates":[-121.759659,49.238514],"type":"Point"}
}