{
  "type": "Feature",
  "properties": {
    "addr:full":"Komoka ON N0L 1R0",
    "addr:postcode":"n0l 1r0",
    "iso:country":"CA",
    "sg:city":"Komoka",
    "sg:classifiers":[
        {
            "category":"Autos & Motor Vehicles",
            "subcategory":"Automobile Sales",
            "type":"Retail Goods"
        }
    ],
    "sg:phone":"+1 519 666 0220",
    "sg:postcode":"N0L 1R0",
    "sg:province":"ON",
    "sg:tags":[
        "car",
        "dealer"
    ],
    "wof:name":"George's Auto Sales & Wreckers",
    "wof:placetype":"venue"
},
  "geometry": {"coordinates":[-81.42542299999999,43.000408],"type":"Point"}
}