{
  "type": "Feature",
  "properties": {
    "addr:full":"1730 Broadway Ave S Williams Lake BC V2G 2W4",
    "addr:housenumber":"1730",
    "addr:postcode":"v2g 2w4",
    "addr:street":"Broadway Ave S Williams",
    "iso:country":"CA",
    "sg:address":"1730 Broadway Ave S",
    "sg:city":"Williams Lake",
    "sg:classifiers":[
        {
            "category":"Restaurant",
            "type":"Food & Drink"
        }
    ],
    "sg:phone":"+1 250 398 5666",
    "sg:postcode":"V2G 2W4",
    "sg:province":"BC",
    "wof:name":"Laughing Loon Neighbourhood",
    "wof:placetype":"venue"
},
  "geometry": {"coordinates":[-122.09429900000001,52.122631],"type":"Point"}
}