{
  "type": "Feature",
  "properties": {
    "addr:full":"6915 St-Hubert Montreal H2S 2M7",
    "addr:housenumber":"6915",
    "addr:postcode":"h2s 2m7",
    "addr:street":"St-Hubert",
    "iso:country":"CA",
    "sg:address":"6915 St-Hubert",
    "sg:city":"Montreal",
    "sg:classifiers":[
        {
            "category":"Professional",
            "subcategory":"Advertising",
            "type":"Services"
        }
    ],
    "sg:postcode":"H2S 2M7",
    "sg:tags":[
        "advertising",
        "digital-advertising",
        "interactive",
        "marketing",
        "digital-marketing",
        "new-media",
        "emerging-media"
    ],
    "sg:website":"http://www.phenomblue.com",
    "wof:name":"Phenomblue",
    "wof:placetype":"venue"
},
  "geometry": {"coordinates":[-73.60953689999999,45.5390677],"type":"Point"}
}