{
  "type": "Feature",
  "properties": {
    "addr:full":"111 Plymouth St Winnipeg MB R2X 2V5",
    "addr:housenumber":"111",
    "addr:postcode":"r2x 2v5",
    "addr:street":"Plymouth St",
    "iso:country":"CA",
    "sg:address":"111 Plymouth St",
    "sg:city":"Winnipeg",
    "sg:classifiers":[
        {
            "category":"Manufacturing",
            "subcategory":"Printing",
            "type":"Manufacturing & Wholesale Goods"
        }
    ],
    "sg:phone":"+1 204 632 1483",
    "sg:postcode":"R2X 2V5",
    "sg:province":"MB",
    "sg:tags":[
        "printer"
    ],
    "wof:name":"L Rasmussen CO Ltd",
    "wof:placetype":"venue"
},
  "geometry": {"coordinates":[-97.1884460449,49.9406394958],"type":"Point"}
}