{
  "type": "Feature",
  "properties": {
    "addr:full":"188 Westmount Blvd Moncton NB E1E 1V3",
    "addr:housenumber":"188",
    "addr:postcode":"e1e 1v3",
    "addr:street":"Westmount Blvd",
    "iso:country":"CA",
    "sg:address":"188 Westmount Blvd",
    "sg:city":"Moncton",
    "sg:classifiers":[
        {
            "category":"Wholesale",
            "subcategory":"Office Equipment",
            "type":"Manufacturing & Wholesale Goods"
        }
    ],
    "sg:phone":"+1 506 857 0053",
    "sg:postcode":"E1E 1V3",
    "sg:province":"NB",
    "sg:tags":[
        "register",
        "cash",
        "supply"
    ],
    "wof:name":"Atlantic Data",
    "wof:placetype":"venue"
},
  "geometry": {"coordinates":[-64.80120100000001,46.081291],"type":"Point"}
}