{
  "type": "Feature",
  "properties": {
    "addr:full":"2605 Ch Saint-Roch Sorel-Tracy QC J3R 3L5",
    "addr:postcode":"2605;j3r 3l5",
    "addr:street":"Ch Saint-Roch",
    "iso:country":"CA",
    "sg:address":"2605 Ch Saint-Roch",
    "sg:city":"Sorel-Tracy",
    "sg:classifiers":[
        {
            "category":"Autos & Motor Vehicles",
            "subcategory":"Auto Supplies",
            "type":"Retail Goods"
        }
    ],
    "sg:phone":"+1 450 742 1111",
    "sg:postcode":"J3R 3L5",
    "sg:province":"QC",
    "sg:tags":[
        "automobile",
        "stereo",
        "radio"
    ],
    "wof:name":"Audio-Expert",
    "wof:placetype":"venue"
},
  "geometry": {"coordinates":[-73.1323928833,46.031993866],"type":"Point"}
}