{
  "type": "Feature",
  "properties": {
    "addr:full":"Chambly QC J3L 1W7",
    "addr:postcode":"j3l 1w7",
    "iso:country":"CA",
    "sg:city":"Chambly",
    "sg:classifiers":[
        {
            "category":"Restaurant",
            "type":"Food & Drink"
        }
    ],
    "sg:phone":"+1 450 447 5928",
    "sg:postcode":"J3L 1W7",
    "sg:province":"QC",
    "wof:name":"C'Est Un Peche Bistro Traiteur",
    "wof:placetype":"venue"
},
  "geometry": {"coordinates":[-73.2892608643,45.4467506409],"type":"Point"}
}