{
  "type": "Feature",
  "properties": {
    "addr:full":"1371 Spring Garden Crt Mississauga ON L5N 8K6",
    "addr:housenumber":"1371",
    "addr:postcode":"l5n 8k6",
    "addr:street":"Spring Garden Crt",
    "iso:country":"CA",
    "sg:address":"1371 Spring Garden Crt",
    "sg:city":"Mississauga",
    "sg:classifiers":[
        {
            "category":"Freight",
            "type":"Transportation"
        }
    ],
    "sg:phone":"+1 905 812 3894",
    "sg:postcode":"L5N 8K6",
    "sg:province":"ON",
    "sg:tags":[
        "delivery"
    ],
    "wof:name":"Reliant Courier",
    "wof:placetype":"venue"
},
  "geometry": {"coordinates":[-79.73653400000001,43.614136],"type":"Point"}
}