{
  "type": "Feature",
  "properties": {
    "addr:full":"21 Arthur St W Thornbury ON N0H 2P0",
    "addr:housenumber":"21",
    "addr:postcode":"n0h 2p0",
    "addr:street":"Arthur St W",
    "iso:country":"CA",
    "sg:address":"21 Arthur St W",
    "sg:city":"Thornbury",
    "sg:classifiers":[
        {
            "category":"Restaurant",
            "type":"Food & Drink"
        }
    ],
    "sg:phone":"+1 519 599 6466",
    "sg:postcode":"N0H 2P0",
    "sg:province":"ON",
    "wof:name":"Itty Bitty Diner",
    "wof:placetype":"venue"
},
  "geometry": {"coordinates":[-80.45426940919999,44.5623855591],"type":"Point"}
}