{
  "type": "Feature",
  "properties": {
    "addr:full":"Montreal QC H1T 1V1",
    "addr:postcode":"h1t 1v1",
    "iso:country":"CA",
    "sg:city":"Montreal",
    "sg:classifiers":[
        {
            "category":"Health Services",
            "subcategory":"Doctor",
            "type":"Services"
        }
    ],
    "sg:phone":"+1 514 721 8000",
    "sg:postcode":"H1T 1V1",
    "sg:province":"QC",
    "sg:tags":[
        "dentist"
    ],
    "wof:name":"Clinique Dentaire Dr Luu",
    "wof:placetype":"venue"
},
  "geometry": {"coordinates":[-73.57252502439999,45.5710067749],"type":"Point"}
}