{
  "type": "Feature",
  "properties": {
    "iso:country":"CA",
    "sg:address":"1959 Fraser Ave",
    "sg:city":"Port Coquitlam",
    "sg:classifiers":[
        {
            "category":"Home & Garden",
            "subcategory":"Building Materials",
            "type":"Retail Goods"
        }
    ],
    "sg:phone":"+1 604 351 8704",
    "sg:postcode":"V3B 1N4",
    "sg:province":"BC",
    "sg:tags":[
        "door"
    ],
    "wof:name":"Top Notch Garage Doors",
    "wof:placetype":"venue"
},
  "geometry": {"coordinates":[-122.76889,49.269287],"type":"Point"}
}