{
  "type": "Feature",
  "properties": {
    "addr:full":"151 Rue St Jean Sainte-Monique-Lac-Saint-Jean QC G0W 2T0",
    "addr:housenumber":"151",
    "addr:postcode":"g0w 2t0",
    "addr:street":"Rue St Jean Sainte-Monique-Lac-Saint-Jean",
    "iso:country":"CA",
    "sg:address":"151 Rue St Jean",
    "sg:city":"Sainte-Monique-Lac-Saint-Jean",
    "sg:classifiers":[
        {
            "category":"Food & Beverages",
            "subcategory":"Groceries & Convenience Stores",
            "type":"Retail Goods"
        }
    ],
    "sg:phone":"+1 418 347 3532",
    "sg:postcode":"G0W 2T0",
    "sg:province":"QC",
    "sg:tags":[
        "grocer"
    ],
    "wof:name":"Paul-Armand Larouche Inc",
    "wof:placetype":"venue"
},
  "geometry": {"coordinates":[-71.847916,48.742558],"type":"Point"}
}