{
  "type": "Feature",
  "properties": {
    "addr:full":"96 Rue Murray Pointe-Lebel QC G0H 1N0",
    "addr:housenumber":"96",
    "addr:postcode":"g0h 1n0",
    "addr:street":"Rue Murray",
    "iso:country":"CA",
    "sg:address":"96 Rue Murray",
    "sg:city":"Pointe-Lebel",
    "sg:classifiers":[
        {
            "category":"Building & Trades",
            "subcategory":"Construction",
            "type":"Services"
        }
    ],
    "sg:phone":"+1 418 589 5294",
    "sg:postcode":"G0H 1N0",
    "sg:province":"QC",
    "sg:tags":[
        "excavating",
        "contractor",
        "general"
    ],
    "wof:name":"Excavation Mc Intyre Inc",
    "wof:placetype":"venue"
},
  "geometry": {"coordinates":[-68.322303772,49.1722679138],"type":"Point"}
}