{
  "type": "Feature",
  "properties": {
    "addr:full":"184 Rue Du Quai Sainte-Rose-Du-Nord QC G0V 1T0",
    "addr:housenumber":"184",
    "addr:postcode":"g0v 1t0",
    "addr:street":"Rue Du Quai",
    "iso:country":"CA",
    "sg:address":"184 Rue Du Quai",
    "sg:city":"Sainte-Rose-Du-Nord",
    "sg:classifiers":[
        {
            "category":"Manufacturing",
            "subcategory":"Lumber",
            "type":"Manufacturing & Wholesale Goods"
        }
    ],
    "sg:phone":"+1 418 675 2266",
    "sg:postcode":"G0V 1T0",
    "sg:province":"QC",
    "sg:tags":[
        "forester"
    ],
    "wof:name":"Coop Forestiere DE Ste-Rose",
    "wof:placetype":"venue"
},
  "geometry": {"coordinates":[-70.6208267212,48.4157791138],"type":"Point"}
}