{
  "type": "Feature",
  "properties": {
    "addr:full":"Gardiner St Holdfast SK S0G 2H0",
    "addr:postcode":"s0g 2h0",
    "addr:street":"Gardiner St",
    "iso:country":"CA",
    "sg:address":"Gardiner St",
    "sg:city":"Holdfast",
    "sg:classifiers":[
        {
            "category":"Retail",
            "subcategory":"Auto Repair",
            "type":"Services"
        }
    ],
    "sg:phone":"+1 306 488 2101",
    "sg:postcode":"S0G 2H0",
    "sg:province":"SK",
    "sg:tags":[
        "repairing",
        "automobile"
    ],
    "wof:name":"Ted's Auto",
    "wof:placetype":"venue"
},
  "geometry": {"coordinates":[-105.422065735,50.9585647583],"type":"Point"}
}