{
  "type": "Feature",
  "properties": {
    "addr:full":"809 Av Du Mont-Royal E Montreal QC H2J 1W9",
    "addr:postcode":"h2j 1w9",
    "addr:street":"809 Av Du Mont-Royal E",
    "iso:country":"CA",
    "sg:address":"809 Av Du Mont-Royal E",
    "sg:city":"Montreal",
    "sg:classifiers":[
        {
            "category":"Shopping",
            "subcategory":"Jewelry",
            "type":"Retail Goods"
        }
    ],
    "sg:phone":"+1 514 528 1567",
    "sg:postcode":"H2J 1W9",
    "sg:province":"QC",
    "sg:tags":[
        "jeweler"
    ],
    "wof:name":"Bagus",
    "wof:placetype":"venue"
},
  "geometry": {"coordinates":[-73.58107757569999,45.526134491],"type":"Point"}
}