{
  "type": "Feature",
  "properties": {
    "addr:full":"813 Coronation Ave Kelowna BC V1Y 7A4",
    "addr:housenumber":"813",
    "addr:postcode":"v1y 7a4",
    "addr:street":"Coronation Ave",
    "iso:country":"CA",
    "sg:address":"813 Coronation Ave",
    "sg:city":"Kelowna",
    "sg:classifiers":[
        {
            "category":"Building & Trades",
            "subcategory":"Plumbing",
            "type":"Services"
        }
    ],
    "sg:phone":"+1 250 860 9977",
    "sg:postcode":"V1Y 7A4",
    "sg:province":"BC",
    "sg:tags":[
        "air",
        "conditioning",
        "contractor",
        "system",
        "heating"
    ],
    "wof:name":"All Rite Heating & Cooling",
    "wof:placetype":"venue"
},
  "geometry": {"coordinates":[-119.485336304,49.8925018311],"type":"Point"}
}