{
  "type": "Feature",
  "properties": {
    "addr:full":"124 Main St Carlyle SK S0C 0R0",
    "addr:housenumber":"124",
    "addr:postcode":"s0c 0r0",
    "addr:street":"Main St",
    "iso:country":"CA",
    "sg:address":"124 Main St",
    "sg:city":"Carlyle",
    "sg:classifiers":[
        {
            "category":"Shopping",
            "subcategory":"Department Store",
            "type":"Retail Goods"
        }
    ],
    "sg:phone":"+1 306 453 6337",
    "sg:postcode":"S0C 0R0",
    "sg:province":"SK",
    "wof:name":"King's Department Store",
    "wof:placetype":"venue"
},
  "geometry": {"coordinates":[-102.26749420199999,49.633846283],"type":"Point"}
}