{
  "type": "Feature",
  "properties": {
    "addr:full":"4172 Starlight Cres Mississauga ON L4W 4R1",
    "addr:housenumber":"4172",
    "addr:postcode":"l4w 4r1",
    "addr:street":"Starlight Cres",
    "iso:country":"CA",
    "sg:address":"4172 Starlight Cres",
    "sg:city":"Mississauga",
    "sg:classifiers":[
        {
            "category":"Building & Trades",
            "subcategory":"Landscaping Services",
            "type":"Services"
        }
    ],
    "sg:phone":"+1 905 276 2138",
    "sg:postcode":"L4W 4R1",
    "sg:province":"ON",
    "sg:tags":[
        "lawn",
        "maintenance",
        "grounds"
    ],
    "wof:name":"Garden Spray & Landscaping",
    "wof:placetype":"venue"
},
  "geometry": {"coordinates":[-79.6161956787,43.6175079346],"type":"Point"}
}