{
  "type": "Feature",
  "properties": {
    "addr:full":"1039 Devonshire Dr Regina SK S4X 2X4",
    "addr:housenumber":"1039",
    "addr:postcode":"s4x 2x4",
    "addr:street":"Devonshire Dr",
    "iso:country":"CA",
    "sg:address":"1039 Devonshire Dr",
    "sg:city":"Regina",
    "sg:classifiers":[
        {
            "category":"Health Services",
            "subcategory":"Doctor",
            "type":"Services"
        }
    ],
    "sg:phone":"+1 306 924 2220",
    "sg:postcode":"S4X 2X4",
    "sg:province":"SK",
    "sg:tags":[
        "physician",
        "surgeon"
    ],
    "wof:name":"Mc Carthy Park Medical Clinic",
    "wof:placetype":"venue"
},
  "geometry": {"coordinates":[-104.671646,50.494423],"type":"Point"}
}