{
  "type": "Feature",
  "properties": {
    "iso:country":"CA",
    "sg:city":"Montreal",
    "sg:classifiers":[
        {
            "category":"Education",
            "subcategory":"Special Training",
            "type":"Public Place"
        }
    ],
    "sg:phone":"+1 514 847 0841",
    "sg:postcode":"H3G 1J1",
    "sg:province":"QC",
    "sg:tags":[
        "school",
        "language"
    ],
    "wof:name":"Corporation DE Langues Geos",
    "wof:placetype":"venue"
},
  "geometry": {"coordinates":[-73.564857,45.524738],"type":"Point"}
}