{
  "type": "Feature",
  "properties": {
    "addr:full":"1825 Hwy 11 W Hearst ON P0L 1N0",
    "addr:housenumber":"1825",
    "addr:postcode":"p0l 1n0",
    "addr:street":"Hwy 11 W",
    "iso:country":"CA",
    "sg:address":"1825 Hwy 11 W",
    "sg:city":"Hearst",
    "sg:classifiers":[
        {
            "category":"Freight",
            "type":"Transportation"
        }
    ],
    "sg:phone":"+1 705 372 0015",
    "sg:postcode":"P0L 1N0",
    "sg:province":"ON",
    "sg:tags":[
        "log",
        "hauling"
    ],
    "wof:name":"Lachance Trucking",
    "wof:placetype":"venue"
},
  "geometry": {"coordinates":[-83.73017120359999,49.6981582642],"type":"Point"}
}