{
  "type": "Feature",
  "properties": {
    "addr:full":"1100 Burloak Dr Burlington ON L7L 6B2",
    "addr:housenumber":"1100",
    "addr:postcode":"l7l 6b2",
    "addr:street":"Burloak Dr",
    "iso:country":"CA",
    "sg:address":"1100 Burloak Dr",
    "sg:city":"Burlington",
    "sg:classifiers":[
        {
            "category":"Real Estate",
            "subcategory":"Developer",
            "type":"Services"
        }
    ],
    "sg:phone":"+1 905 827 1263",
    "sg:postcode":"L7L 6B2",
    "sg:province":"ON",
    "wof:name":"Port Charlotte Home Builders",
    "wof:placetype":"venue"
},
  "geometry": {"coordinates":[-79.75975,43.397469],"type":"Point"}
}