{
  "type": "Feature",
  "properties": {
    "addr:full":"2060 Queen St E Toronto ON M4E 1C9",
    "addr:housenumber":"2060",
    "addr:postcode":"m4e 1c9",
    "addr:street":"Queen St E",
    "iso:country":"CA",
    "sg:address":"2060 Queen St E",
    "sg:city":"Toronto",
    "sg:classifiers":[
        {
            "category":"Travel",
            "subcategory":"Travel Agent",
            "type":"Entertainment"
        }
    ],
    "sg:phone":"+1 416 694 2121",
    "sg:postcode":"M4E 1C9",
    "sg:province":"ON",
    "sg:tags":[
        "agency",
        "bureau"
    ],
    "wof:name":"Carlson Wagonlit Travel",
    "wof:placetype":"venue"
},
  "geometry": {"coordinates":[-79.297394,43.67075],"type":"Point"}
}