{
  "type": "Feature",
  "properties": {
    "addr:full":"442 Front St Trenton ON K8V 4P9",
    "addr:housenumber":"442",
    "addr:postcode":"k8v 4p9",
    "addr:street":"Front St",
    "iso:country":"CA",
    "sg:address":"442 Front St",
    "sg:city":"Trenton",
    "sg:classifiers":[
        {
            "category":"Shopping",
            "subcategory":"Discount & Variety Stores",
            "type":"Retail Goods"
        }
    ],
    "sg:phone":"+1 613 394 6149",
    "sg:postcode":"K8V 4P9",
    "sg:province":"ON",
    "wof:name":"Front Street Variety",
    "wof:placetype":"venue"
},
  "geometry": {"coordinates":[-77.59036999999999,44.108082],"type":"Point"}
}