{
  "type": "Feature",
  "properties": {
    "addr:full":"103 College St W Belleville ON K8P 2G3",
    "addr:housenumber":"103",
    "addr:postcode":"k8p 2g3",
    "addr:street":"College St W",
    "iso:country":"CA",
    "sg:address":"103 College St W",
    "sg:city":"Belleville",
    "sg:classifiers":[
        {
            "category":"Food & Beverages",
            "subcategory":"Groceries & Convenience Stores",
            "type":"Retail Goods"
        }
    ],
    "sg:phone":"+1 613 962 1604",
    "sg:postcode":"K8P 2G3",
    "sg:province":"ON",
    "wof:name":"Super Duper 2",
    "wof:placetype":"venue"
},
  "geometry": {"coordinates":[-77.3971252441,44.1751060486],"type":"Point"}
}