{
  "type": "Feature",
  "properties": {
    "addr:full":"Port Hawkesbury NS B9A 2M5",
    "addr:postcode":"b9a 2m5",
    "iso:country":"CA",
    "sg:city":"Port Hawkesbury",
    "sg:classifiers":[
        {
            "category":"Shopping",
            "subcategory":"Musical Instruments",
            "type":"Retail Goods"
        }
    ],
    "sg:phone":"+1 902 625 5135",
    "sg:postcode":"B9A 2M5",
    "sg:province":"NS",
    "wof:name":"Cameron Music Sales",
    "wof:placetype":"venue"
},
  "geometry": {"coordinates":[-61.363895,45.615005],"type":"Point"}
}