{
  "type": "Feature",
  "properties": {
    "iso:country":"CA",
    "sg:city":"Chateauguay",
    "sg:classifiers":[
        {
            "category":"Health Services",
            "subcategory":"Optometrist",
            "type":"Services"
        }
    ],
    "sg:phone":"+1 450 691 5060",
    "sg:postcode":"J6J 2R3",
    "sg:province":"QC",
    "wof:name":"Cote, Annie",
    "wof:placetype":"venue"
},
  "geometry": {"coordinates":[-73.718971,45.358818],"type":"Point"}
}