{
  "type": "Feature",
  "properties": {
    "addr:full":"7728 Edmonds St Burnaby BC V3N 1B8",
    "addr:housenumber":"7728",
    "addr:postcode":"v3n 1b8",
    "addr:street":"Edmonds St",
    "iso:country":"CA",
    "sg:address":"7728 Edmonds St",
    "sg:city":"Burnaby",
    "sg:classifiers":[
        {
            "category":"Organizations",
            "subcategory":"Community Association",
            "type":"Services"
        }
    ],
    "sg:phone":"+1 604 521 0114",
    "sg:postcode":"V3N 1B8",
    "sg:province":"BC",
    "sg:tags":[
        "fraternal"
    ],
    "wof:name":"Independent Order-Odd Fellows",
    "wof:placetype":"venue"
},
  "geometry": {"coordinates":[-122.940048,49.224434],"type":"Point"}
}