{
  "type": "Feature",
  "properties": {
    "addr:full":"172 South Service Rd Stoney Creek ON L8E 3H6",
    "addr:housenumber":"172",
    "addr:postcode":"l8e 3h6",
    "addr:street":"South Service Rd",
    "iso:country":"CA",
    "sg:address":"172 South Service Rd",
    "sg:city":"Stoney Creek",
    "sg:classifiers":[
        {
            "category":"Manufacturing",
            "subcategory":"Tools & Machinery",
            "type":"Manufacturing & Wholesale Goods"
        }
    ],
    "sg:phone":"+1 905 664 4040",
    "sg:postcode":"L8E 3H6",
    "sg:province":"ON",
    "sg:tags":[
        "crane",
        "derrick"
    ],
    "wof:name":"Motivation Industrial Equip",
    "wof:placetype":"venue"
},
  "geometry": {"coordinates":[-79.734444,43.240196],"type":"Point"}
}