{
  "type": "Feature",
  "properties": {
    "addr:full":"10045 156 St NW Edmonton AB T5P 2P7",
    "addr:housenumber":"10045",
    "addr:postcode":"t5p 2p7",
    "addr:street":"156 St Nw",
    "iso:country":"CA",
    "sg:address":"10045 156 St NW",
    "sg:city":"Edmonton",
    "sg:classifiers":[
        {
            "category":"Arts & Performance",
            "subcategory":"Theater",
            "type":"Entertainment"
        }
    ],
    "sg:phone":"+1 780 497 4470",
    "sg:postcode":"T5P 2P7",
    "sg:province":"AB",
    "wof:name":"John L Haar Theatre",
    "wof:placetype":"venue"
},
  "geometry": {"coordinates":[-113.590103149,53.5404930115],"type":"Point"}
}