{
  "type": "Feature",
  "properties": {
    "iso:country":"CA",
    "sg:address":"57 Trevor St",
    "sg:city":"Woodbridge",
    "sg:classifiers":[
        {
            "category":"Health Services",
            "subcategory":"Doctor",
            "type":"Services"
        }
    ],
    "sg:phone":"+1 905 264 8144",
    "sg:postcode":"L4L 7S6",
    "sg:province":"ON",
    "sg:tags":[
        "physician",
        "surgeon"
    ],
    "wof:name":"Mbs Therapy Svc",
    "wof:placetype":"venue"
},
  "geometry": {"coordinates":[-79.555367,43.799816],"type":"Point"}
}