{
  "type": "Feature",
  "properties": {
    "addr:full":"7 Ch Rochon Gracefield QC J0X 1W0",
    "addr:housenumber":"7",
    "addr:postcode":"j0x 1w0",
    "addr:street":"Ch Rochon",
    "iso:country":"CA",
    "sg:address":"7 Ch Rochon",
    "sg:city":"Gracefield",
    "sg:classifiers":[
        {
            "category":"Manufacturing",
            "subcategory":"Textiles",
            "type":"Manufacturing & Wholesale Goods"
        }
    ],
    "sg:phone":"+1 819 463 1739",
    "sg:postcode":"J0X 1W0",
    "sg:province":"QC",
    "sg:tags":[
        "rug",
        "carpet"
    ],
    "wof:name":"Multi-Couleurs",
    "wof:placetype":"venue"
},
  "geometry": {"coordinates":[-76.053314,46.091839],"type":"Point"}
}