{
  "type": "Feature",
  "properties": {
    "iso:country":"CA",
    "sg:address":"4812 50 Ave",
    "sg:city":"Red Deer",
    "sg:classifiers":[
        {
            "category":"Shopping",
            "subcategory":"Shoes",
            "type":"Retail Goods"
        }
    ],
    "sg:phone":"+1 403 342 7653",
    "sg:postcode":"T4N 4A3",
    "sg:province":"AB",
    "wof:name":"Comforts the Sole",
    "wof:placetype":"venue"
},
  "geometry": {"coordinates":[-113.814323425,52.2678985596],"type":"Point"}
}