{
  "type": "Feature",
  "properties": {
    "addr:full":"766038 Township Rd 5 Innerkip ON N0J 1M0",
    "addr:housenumber":"766038",
    "addr:postcode":"n0j 1m0",
    "addr:street":"Township Rd 5 Innerkip",
    "iso:country":"CA",
    "sg:address":"766038 Township Rd 5",
    "sg:city":"Innerkip",
    "sg:classifiers":[
        {
            "category":"Government",
            "subcategory":"Office",
            "type":"Public Place"
        }
    ],
    "sg:phone":"+1 519 469 3247",
    "sg:postcode":"N0J 1M0",
    "sg:province":"ON",
    "sg:tags":[
        "society",
        "humane",
        "village"
    ],
    "wof:name":"Hillside Kennels",
    "wof:placetype":"venue"
},
  "geometry": {"coordinates":[-80.66181899999999,43.194313],"type":"Point"}
}