{
  "type": "Feature",
  "properties": {
    "iso:country":"CA",
    "sg:address":"360 Rue Benjamin-Sulte",
    "sg:city":"Laval",
    "sg:classifiers":[
        {
            "category":"Food & Beverages",
            "subcategory":"Specialty",
            "type":"Retail Goods"
        }
    ],
    "sg:phone":"+1 450 669 2009",
    "sg:postcode":"H7M 1Y3",
    "sg:province":"QC",
    "sg:tags":[
        "vitamin"
    ],
    "wof:name":"Shaklee Distributeur",
    "wof:placetype":"venue"
},
  "geometry": {"coordinates":[-73.71394348139999,45.5812187195],"type":"Point"}
}