{
  "type": "Feature",
  "properties": {
    "addr:full":"300 Dufferin Ave London ON N6B 1Z2",
    "addr:housenumber":"300",
    "addr:postcode":"n6b 1z2",
    "addr:street":"Dufferin Ave",
    "iso:country":"CA",
    "sg:address":"300 Dufferin Ave",
    "sg:city":"London",
    "sg:classifiers":[
        {
            "category":"Government",
            "subcategory":"Office",
            "type":"Public Place"
        }
    ],
    "sg:phone":"+1 519 661 5140",
    "sg:postcode":"N6B 1Z2",
    "sg:province":"ON",
    "sg:tags":[
        "village"
    ],
    "wof:name":"Ontario Provincial Offences",
    "wof:placetype":"venue"
},
  "geometry": {"coordinates":[-81.24639892579999,42.9877319336],"type":"Point"}
}