{
  "type": "Feature",
  "properties": {
    "addr:full":"6011 Yonge St North York ON M2M 3W2",
    "addr:housenumber":"6011",
    "addr:postcode":"m2m 3w2",
    "addr:street":"Yonge St",
    "iso:country":"CA",
    "sg:address":"6011 Yonge St",
    "sg:city":"North York",
    "sg:classifiers":[
        {
            "category":"Travel",
            "subcategory":"Travel Agent",
            "type":"Entertainment"
        }
    ],
    "sg:phone":"+1 416 221 9199",
    "sg:postcode":"M2M 3W2",
    "sg:province":"ON",
    "sg:tags":[
        "agency",
        "bureau"
    ],
    "wof:name":"Worldlink Travel Inc",
    "wof:placetype":"venue"
},
  "geometry": {"coordinates":[-79.41766357420001,43.7891731262],"type":"Point"}
}