{
  "type": "Feature",
  "properties": {
    "addr:full":"1312 Britannia Rd E Mississauga ON L4W 1C8",
    "addr:housenumber":"1312",
    "addr:postcode":"l4w 1c8",
    "addr:street":"Britannia Rd E",
    "iso:country":"CA",
    "sg:address":"1312 Britannia Rd E",
    "sg:city":"Mississauga",
    "sg:classifiers":[
        {
            "category":"Manufacturing",
            "subcategory":"Tools & Machinery",
            "type":"Manufacturing & Wholesale Goods"
        }
    ],
    "sg:phone":"+1 905 670 2200",
    "sg:postcode":"L4W 1C8",
    "sg:province":"ON",
    "sg:tags":[
        "oven"
    ],
    "wof:name":"Applied Heat Equipment CO Ltd",
    "wof:placetype":"venue"
},
  "geometry": {"coordinates":[-79.65038300000001,43.652626],"type":"Point"}
}