{
  "type": "Feature",
  "properties": {
    "addr:full":"229 Brunswick St Prince George BC V2L 2B4",
    "addr:housenumber":"229",
    "addr:postcode":"v2l 2b4",
    "addr:street":"Brunswick St",
    "iso:country":"CA",
    "sg:address":"229 Brunswick St",
    "sg:city":"Prince George",
    "sg:classifiers":[
        {
            "category":"Restaurant",
            "type":"Food & Drink"
        }
    ],
    "sg:phone":"+1 250 562 8226",
    "sg:postcode":"V2L 2B4",
    "sg:province":"BC",
    "wof:name":"Amigo's Taco Shop",
    "wof:placetype":"venue"
},
  "geometry": {"coordinates":[-122.74739099999999,53.917919],"type":"Point"}
}