{
  "type": "Feature",
  "properties": {
    "addr:full":"50 Queen St E Brampton ON L6V 1A2",
    "addr:housenumber":"50",
    "addr:postcode":"l6v 1a2",
    "addr:street":"Queen St E",
    "iso:country":"CA",
    "sg:address":"50 Queen St E",
    "sg:city":"Brampton",
    "sg:classifiers":[
        {
            "category":"Shopping",
            "subcategory":"Clothing, Apparel, & Fashions",
            "type":"Retail Goods"
        }
    ],
    "sg:phone":"+1 905 459 9370",
    "sg:postcode":"L6V 1A2",
    "sg:province":"ON",
    "sg:tags":[
        "shop",
        "bridal"
    ],
    "wof:name":"L & J Bridal Boutique",
    "wof:placetype":"venue"
},
  "geometry": {"coordinates":[-79.7590332031,43.6869430542],"type":"Point"}
}