{
  "type": "Feature",
  "properties": {
    "addr:full":"661 111 Rte W Amos QC J9T 2Y1",
    "addr:housenumber":"111",
    "addr:postcode":"j9t 2y1",
    "addr:street":"Rte W Amos",
    "iso:country":"CA",
    "sg:address":"661 111 Rte W",
    "sg:city":"Amos",
    "sg:classifiers":[
        {
            "category":"Wholesale",
            "subcategory":"Machinery & Supplies",
            "type":"Manufacturing & Wholesale Goods"
        }
    ],
    "sg:phone":"+1 819 732 2345",
    "sg:postcode":"J9T 2Y1",
    "sg:province":"QC",
    "sg:tags":[
        "forestry",
        "timber"
    ],
    "wof:name":"Equipement Ontrac Quebec Inc",
    "wof:placetype":"venue"
},
  "geometry": {"coordinates":[-78.1064834595,48.5637702942],"type":"Point"}
}