{
  "type": "Feature",
  "properties": {
    "addr:full":"2960 Martin Rd Blezard Valley ON P0M 1E0",
    "addr:housenumber":"2960",
    "addr:postcode":"p0m 1e0",
    "addr:street":"Martin Rd",
    "iso:country":"CA",
    "sg:address":"2960 Martin Rd",
    "sg:city":"Blezard Valley",
    "sg:phone":"+1 705 897 4560",
    "sg:postcode":"P0M 1E0",
    "sg:province":"ON",
    "sg:tags":[
        "vegetable",
        "grower",
        "potato"
    ],
    "wof:name":"Valley Growers Inc",
    "wof:placetype":"venue"
},
  "geometry": {"coordinates":[-81.049858,46.608662],"type":"Point"}
}