{
  "type": "Feature",
  "properties": {
    "addr:full":"131 Woodbridge Ave #5 Woodbridge ON L4L 2S6",
    "addr:housenumber":"131",
    "addr:postcode":"l4l 2s6",
    "addr:street":"Woodbridge Ave # 5",
    "iso:country":"CA",
    "sg:address":"131 Woodbridge Ave #5",
    "sg:city":"Woodbridge",
    "sg:classifiers":[
        {
            "category":"Banks & Credit Unions",
            "subcategory":"Bank",
            "type":"Services"
        }
    ],
    "sg:phone":"+1 905 265 0016",
    "sg:postcode":"L4L 2S6",
    "sg:province":"ON",
    "sg:tags":[
        "loan",
        "real estate"
    ],
    "wof:name":"Royal Bank Mortgage Specialist",
    "wof:placetype":"venue"
},
  "geometry": {"coordinates":[-79.592697,43.784763],"type":"Point"}
}