{
  "type": "Feature",
  "properties": {
    "iso:country":"CA",
    "sg:address":"9333 Boul Saint-Laurent",
    "sg:city":"Montreal",
    "sg:classifiers":[
        {
            "category":"Manufacturing",
            "subcategory":"Apparel",
            "type":"Manufacturing & Wholesale Goods"
        }
    ],
    "sg:phone":"+1 514 385 3898",
    "sg:postcode":"H2N 1P6",
    "sg:province":"QC",
    "sg:tags":[
        "clothing"
    ],
    "wof:name":"D Jeremy Ltee",
    "wof:placetype":"venue"
},
  "geometry": {"coordinates":[-73.65171813960001,45.5447654724],"type":"Point"}
}