{
  "type": "Feature",
  "properties": {
    "addr:full":"9352 34 Ave NW Edmonton AB T6E 5X8",
    "addr:housenumber":"9352",
    "addr:postcode":"t6e 5x8",
    "addr:street":"34 Ave Nw",
    "iso:country":"CA",
    "sg:address":"9352 34 Ave NW",
    "sg:city":"Edmonton",
    "sg:classifiers":[
        {
            "category":"Shopping",
            "subcategory":"Jewelry",
            "type":"Retail Goods"
        }
    ],
    "sg:phone":"+1 780 465 3052",
    "sg:postcode":"T6E 5X8",
    "sg:province":"AB",
    "sg:tags":[
        "jeweler"
    ],
    "wof:name":"Punjab Jewellers Ltd",
    "wof:placetype":"venue"
},
  "geometry": {"coordinates":[-113.475708008,53.4663162231],"type":"Point"}
}