{
  "type": "Feature",
  "properties": {
    "addr:full":"426 Rue Dorimene-Desjardins Levis QC G6V 5V4",
    "addr:housenumber":"426",
    "addr:postcode":"g6v 5v4",
    "addr:street":"Rue Dorimene-Desjardins",
    "iso:country":"CA",
    "sg:address":"426 Rue Dorimene-Desjardins",
    "sg:city":"Levis",
    "sg:classifiers":[
        {
            "category":"Restaurant",
            "type":"Food & Drink"
        }
    ],
    "sg:phone":"+1 418 833 7106",
    "sg:postcode":"G6V 5V4",
    "sg:province":"QC",
    "wof:name":"Au P'Tit Coin Chinois",
    "wof:placetype":"venue"
},
  "geometry": {"coordinates":[-71.18273162840001,46.8046989441],"type":"Point"}
}