{
  "type": "Feature",
  "properties": {
    "addr:full":"C/O Narwhal Artic Svc Resolute NU X0A 0V0",
    "addr:housenumber":"/ o",
    "addr:postcode":"x0a 0v0",
    "addr:street":"C;Narwhal Artic Svc",
    "iso:country":"CA",
    "sg:address":"C/O Narwhal Artic Svc",
    "sg:city":"Resolute",
    "sg:classifiers":[
        {
            "category":"Professional",
            "subcategory":"Research",
            "type":"Services"
        }
    ],
    "sg:phone":"+1 867 252 3898",
    "sg:postcode":"X0A 0V0",
    "sg:province":"NU",
    "sg:tags":[
        "development",
        "laboratory"
    ],
    "wof:name":"Resolute Bay Observatory",
    "wof:placetype":"venue"
},
  "geometry": {"coordinates":[-94.839935,74.69452699999999],"type":"Point"}
}