{
  "type": "Feature",
  "properties": {
    "addr:full":"792 105th St North Battleford SK S9A 1R8",
    "addr:housenumber":"792",
    "addr:postcode":"s9a 1r8",
    "addr:street":"105Th St",
    "iso:country":"CA",
    "sg:address":"792 105th St",
    "sg:city":"North Battleford",
    "sg:classifiers":[
        {
            "category":"Autos & Motor Vehicles",
            "subcategory":"Fuel & Gas Station",
            "type":"Retail Goods"
        }
    ],
    "sg:phone":"+1 306 445 8000",
    "sg:postcode":"S9A 1R8",
    "sg:province":"SK",
    "sg:tags":[
        "polishing",
        "car",
        "oil",
        "washing"
    ],
    "wof:name":"Mohawk North Battleford",
    "wof:placetype":"venue"
},
  "geometry": {"coordinates":[-108.291634,52.768684],"type":"Point"}
}