{
  "type": "Feature",
  "properties": {
    "addr:full":"27 Hamilton Rd Barrie ON L4N 8Y6",
    "addr:housenumber":"27",
    "addr:postcode":"l4n 8y6",
    "addr:street":"Hamilton Rd",
    "iso:country":"CA",
    "sg:address":"27 Hamilton Rd",
    "sg:city":"Barrie",
    "sg:classifiers":[
        {
            "category":"Wholesale",
            "subcategory":"Machinery & Supplies",
            "type":"Manufacturing & Wholesale Goods"
        }
    ],
    "sg:phone":"+1 705 721 9500",
    "sg:postcode":"L4N 8Y6",
    "sg:province":"ON",
    "sg:tags":[
        "spraying",
        "gas",
        "equipment"
    ],
    "wof:name":"Paintline Products Inc",
    "wof:placetype":"venue"
},
  "geometry": {"coordinates":[-79.672264,44.357098],"type":"Point"}
}