{
  "type": "Feature",
  "properties": {
    "addr:full":"2400 343 Rte Saint-Come QC J0K 2B0",
    "addr:housenumber":"2400",
    "addr:postcode":"j0k 2b0",
    "addr:street":"343 Rte Saint-Come",
    "iso:country":"CA",
    "sg:address":"2400 343 Rte",
    "sg:city":"Saint-Come",
    "sg:classifiers":[
        {
            "category":"Retail",
            "subcategory":"Repair Shop",
            "type":"Services"
        }
    ],
    "sg:phone":"+1 450 883 6138",
    "sg:postcode":"J0K 2B0",
    "sg:province":"QC",
    "sg:tags":[
        "clocks",
        "parts"
    ],
    "wof:name":"Ateliers Lavoie Et Freres",
    "wof:placetype":"venue"
},
  "geometry": {"coordinates":[-73.72489899999999,46.247551],"type":"Point"}
}