{
  "type": "Feature",
  "properties": {
    "addr:full":"3440 Rue Chapais Sherbrooke QC J1L 2V5",
    "addr:housenumber":"3440",
    "addr:postcode":"j1l 2v5",
    "addr:street":"Rue Chapais",
    "iso:country":"CA",
    "sg:address":"3440 Rue Chapais",
    "sg:city":"Sherbrooke",
    "sg:classifiers":[
        {
            "category":"Food & Beverages",
            "subcategory":"Liquor & Beverages",
            "type":"Retail Goods"
        }
    ],
    "sg:phone":"+1 819 562 6947",
    "sg:postcode":"J1L 2V5",
    "sg:province":"QC",
    "sg:tags":[
        "grocer"
    ],
    "wof:name":"Depanneur Jc Enr",
    "wof:placetype":"venue"
},
  "geometry": {"coordinates":[-71.95565795900001,45.4109039307],"type":"Point"}
}