{
  "type": "Feature",
  "properties": {
    "iso:country":"CA",
    "sg:address":"379 Boul Des Bois-Francs S",
    "sg:city":"Victoriaville",
    "sg:classifiers":[
        {
            "category":"Cinema",
            "subcategory":"Movie Rental",
            "type":"Entertainment"
        }
    ],
    "sg:phone":"+1 819 758 1414",
    "sg:postcode":"G6P 4T2",
    "sg:province":"QC",
    "sg:tags":[
        "leasing",
        "video",
        "disc",
        "tape"
    ],
    "wof:name":"Superclub Videotron Ltee",
    "wof:placetype":"venue"
},
  "geometry": {"coordinates":[-71.9408950806,46.0530433655],"type":"Point"}
}