{
  "type": "Feature",
  "properties": {
    "addr:full":"516 9 Ave SW Calgary AB T2P 1L4",
    "addr:housenumber":"516",
    "addr:postcode":"t2p 1l4",
    "addr:street":"9 Ave Sw",
    "iso:country":"CA",
    "sg:address":"516 9 Ave SW",
    "sg:city":"Calgary",
    "sg:classifiers":[
        {
            "category":"Restaurant",
            "type":"Food & Drink"
        }
    ],
    "sg:phone":"+1 403 265 5071",
    "sg:postcode":"T2P 1L4",
    "sg:province":"AB",
    "wof:name":"Break the Fast Cafe",
    "wof:placetype":"venue"
},
  "geometry": {"coordinates":[-114.072411,51.044987],"type":"Point"}
}