{
  "type": "Feature",
  "properties": {
    "iso:country":"CA",
    "sg:address":"516 9 Ave SW",
    "sg:city":"Calgary",
    "sg:classifiers":[
        {
            "category":"Restaurant",
            "type":"Food & Drink"
        }
    ],
    "sg:phone":"+1 403 265 5071",
    "sg:postcode":"T2P 1L4",
    "sg:province":"AB",
    "wof:name":"Break the Fast Cafe",
    "wof:placetype":"venue"
},
  "geometry": {"coordinates":[-114.072411,51.044987],"type":"Point"}
}