{
  "type": "Feature",
  "properties": {
    "addr:full":"1625 Boul Quinn Longueuil QC J4J 3J2",
    "addr:housenumber":"1625",
    "addr:postcode":"j4j 3j2",
    "addr:street":"Boul Quinn",
    "iso:country":"CA",
    "sg:address":"1625 Boul Quinn",
    "sg:city":"Longueuil",
    "sg:classifiers":[
        {
            "category":"Retail",
            "subcategory":"Auto Repair",
            "type":"Services"
        }
    ],
    "sg:phone":"+1 450 677 2651",
    "sg:postcode":"J4J 3J2",
    "sg:province":"QC",
    "sg:tags":[
        "wheel",
        "alignment",
        "axle"
    ],
    "wof:name":"Roy Alignement Enrg",
    "wof:placetype":"venue"
},
  "geometry": {"coordinates":[-73.4892883301,45.5253448486],"type":"Point"}
}