{
  "type": "Feature",
  "properties": {
    "iso:country":"CA",
    "sg:address":"267 Rue Dubois",
    "sg:city":"Chateauguay",
    "sg:classifiers":[
        {
            "category":"Shopping",
            "subcategory":"Computers & Home Electronics",
            "type":"Retail Goods"
        }
    ],
    "sg:phone":"+1 450 691 6969",
    "sg:postcode":"J6K 1H3",
    "sg:province":"QC",
    "sg:tags":[
        "parts",
        "supply"
    ],
    "wof:name":"Data-Source Canada",
    "wof:placetype":"venue"
},
  "geometry": {"coordinates":[-73.720512,45.357311],"type":"Point"}
}