{
  "type": "Feature",
  "properties": {
    "addr:full":"33809 Airport Rd Goderich ON N7A 3Y2",
    "addr:housenumber":"33809",
    "addr:postcode":"n7a 3y2",
    "addr:street":"Airport Rd",
    "iso:country":"CA",
    "sg:address":"33809 Airport Rd",
    "sg:city":"Goderich",
    "sg:classifiers":[
        {
            "category":"Health Services",
            "subcategory":"Nursing And Care Facility",
            "type":"Services"
        }
    ],
    "sg:phone":"+1 519 524 9895",
    "sg:postcode":"N7A 3Y2",
    "sg:province":"ON",
    "sg:tags":[
        "home",
        "retirement",
        "community"
    ],
    "wof:name":"Meneset on the Lake",
    "wof:placetype":"venue"
},
  "geometry": {"coordinates":[-81.707764,43.742641],"type":"Point"}
}