{
  "type": "Feature",
  "properties": {
    "addr:full":"6373 Fraser St Vancouver BC V5W 3A3",
    "addr:housenumber":"6373",
    "addr:postcode":"v5w 3a3",
    "addr:street":"Fraser St",
    "iso:country":"CA",
    "sg:address":"6373 Fraser St",
    "sg:city":"Vancouver",
    "sg:classifiers":[
        {
            "category":"Banks & Credit Unions",
            "subcategory":"Bank",
            "type":"Services"
        }
    ],
    "sg:phone":"+1 604 324 2481",
    "sg:postcode":"V5W 3A3",
    "sg:province":"BC",
    "wof:name":"Hsbc Bank Canada",
    "wof:placetype":"venue"
},
  "geometry": {"coordinates":[-123.090881348,49.2268562317],"type":"Point"}
}