{
  "type": "Feature",
  "properties": {
    "addr:full":"26 33rd St E Saskatoon SK S7K 0R9",
    "addr:housenumber":"26",
    "addr:postcode":"s7k 0r9",
    "addr:street":"33Rd St E",
    "iso:country":"CA",
    "sg:address":"26 33rd St E",
    "sg:city":"Saskatoon",
    "sg:classifiers":[
        {
            "category":"Retail",
            "subcategory":"Auto Repair",
            "type":"Services"
        }
    ],
    "sg:phone":"+1 306 244 8669",
    "sg:postcode":"S7K 0R9",
    "sg:province":"SK",
    "sg:tags":[
        "repairing",
        "automobile"
    ],
    "wof:name":"Diamond Service",
    "wof:placetype":"venue"
},
  "geometry": {"coordinates":[-106.66798400899999,52.1439552307],"type":"Point"}
}