{
  "type": "Feature",
  "properties": {
    "addr:full":"47585 Trans Canada Hwy Boston Bar BC V0K 1C0",
    "addr:housenumber":"47585",
    "addr:postcode":"v0k 1c0",
    "addr:street":"Trans Canada Hwy",
    "iso:country":"CA",
    "sg:address":"47585 Trans Canada Hwy",
    "sg:city":"Boston Bar",
    "sg:classifiers":[
        {
            "category":"Sports & Exercise",
            "subcategory":"Bowling",
            "type":"Entertainment"
        }
    ],
    "sg:phone":"+1 604 867 8800",
    "sg:postcode":"V0K 1C0",
    "sg:province":"BC",
    "sg:tags":[
        "center"
    ],
    "wof:name":"Canyon Lanes",
    "wof:placetype":"venue"
},
  "geometry": {"coordinates":[-121.44194793699999,49.8657493591],"type":"Point"}
}