{
  "type": "Feature",
  "properties": {
    "addr:full":"941 24E Av S Saint-Jerome QC J7Z 3H7",
    "addr:housenumber":"941",
    "addr:postcode":"j7z 3h7",
    "addr:street":"24E Av S Saint-Jerome",
    "iso:country":"CA",
    "sg:address":"941 24E Av S",
    "sg:city":"Saint-Jerome",
    "sg:classifiers":[
        {
            "category":"Shopping",
            "subcategory":"Computers & Home Electronics",
            "type":"Retail Goods"
        }
    ],
    "sg:phone":"+1 450 438 9232",
    "sg:postcode":"J7Z 3H7",
    "sg:province":"QC",
    "sg:tags":[
        "cleaners",
        "television",
        "vacuum"
    ],
    "wof:name":"Beauchamp Tv Svc",
    "wof:placetype":"venue"
},
  "geometry": {"coordinates":[-74.00351000000001,45.775009],"type":"Point"}
}