{
  "type": "Feature",
  "properties": {
    "addr:full":"2044 Otter Point Rd Sooke BC V0S 1N0",
    "addr:housenumber":"2044",
    "addr:postcode":"v0s 1n0",
    "addr:street":"Otter Point Rd",
    "iso:country":"CA",
    "sg:address":"2044 Otter Point Rd",
    "sg:city":"Sooke",
    "sg:classifiers":[
        {
            "category":"Shopping",
            "type":"Retail Goods"
        }
    ],
    "sg:phone":"+1 250 642 7787",
    "sg:postcode":"V0S 1N0",
    "sg:province":"BC",
    "sg:tags":[
        "equipment",
        "beer",
        "supply"
    ],
    "wof:name":"Sooke U-Brew",
    "wof:placetype":"venue"
},
  "geometry": {"coordinates":[-123.72435,48.377846],"type":"Point"}
}