{
  "type": "Feature",
  "properties": {
    "addr:full":"Chester NS B0J 1J0",
    "addr:postcode":"b0j 1j0",
    "iso:country":"CA",
    "sg:city":"Chester",
    "sg:classifiers":[
        {
            "category":"Organizations",
            "subcategory":"Non-profit Organization",
            "type":"Services"
        }
    ],
    "sg:phone":"+1 902 275 2460",
    "sg:postcode":"B0J 1J0",
    "sg:province":"NS",
    "sg:tags":[
        "charitable",
        "institution"
    ],
    "wof:name":"Little Red School",
    "wof:placetype":"venue"
},
  "geometry": {"coordinates":[-64.2417831421,44.5462760925],"type":"Point"}
}