{
  "type": "Feature",
  "properties": {
    "addr:full":"89 Rue Principale Saint-Andre-DE-Kamouraska QC G0L 2H0",
    "addr:housenumber":"89",
    "addr:postcode":"g0l 2h0",
    "addr:street":"Rue Principale",
    "iso:country":"CA",
    "sg:address":"89 Rue Principale",
    "sg:city":"Saint-Andre-DE-Kamouraska",
    "sg:classifiers":[
        {
            "category":"Retail",
            "subcategory":"Auto Repair",
            "type":"Services"
        }
    ],
    "sg:phone":"+1 418 493 2244",
    "sg:postcode":"G0L 2H0",
    "sg:province":"QC",
    "sg:tags":[
        "body",
        "automobile",
        "painting"
    ],
    "wof:name":"Carrosseries Du Kamouraska Inc",
    "wof:placetype":"venue"
},
  "geometry": {"coordinates":[-69.73323822019999,47.6709518433],"type":"Point"}
}