{
  "type": "Feature",
  "properties": {
    "addr:full":"1851 Sandstone Manor Pickering ON L1W 3R9",
    "addr:housenumber":"1851",
    "addr:postcode":"l1w 3r9",
    "addr:street":"Sandstone Manor",
    "iso:country":"CA",
    "sg:address":"1851 Sandstone Manor",
    "sg:city":"Pickering",
    "sg:classifiers":[
        {
            "category":"Wholesale",
            "subcategory":"Office Equipment",
            "type":"Manufacturing & Wholesale Goods"
        }
    ],
    "sg:phone":"+1 905 839 7921",
    "sg:postcode":"L1W 3R9",
    "sg:province":"ON",
    "sg:tags":[
        "machine",
        "duplicating",
        "copying"
    ],
    "wof:name":"Konica Business Machines",
    "wof:placetype":"venue"
},
  "geometry": {"coordinates":[-79.117980957,43.8100776672],"type":"Point"}
}