{
  "type": "Feature",
  "properties": {
    "addr:full":"Morson ON P0W 1J0",
    "addr:postcode":"p0w 1j0",
    "iso:country":"CA",
    "sg:city":"Morson",
    "sg:classifiers":[
        {
            "category":"Social Services",
            "subcategory":"Child Care",
            "type":"Services"
        }
    ],
    "sg:phone":"+1 807 488 5917",
    "sg:postcode":"P0W 1J0",
    "sg:province":"ON",
    "sg:tags":[
        "government"
    ],
    "wof:name":"Big Grassy Child Care Morson",
    "wof:placetype":"venue"
},
  "geometry": {"coordinates":[-94.309372,49.107056],"type":"Point"}
}