{
  "type": "Feature",
  "properties": {
    "addr:full":"PO Box 252 Donnelly AB T0H 1G0",
    "addr:housenumber":"po",
    "addr:postcode":"t0h 1g0",
    "addr:street":"Box 252 Donnelly",
    "iso:country":"CA",
    "sg:address":"PO Box 252",
    "sg:city":"Donnelly",
    "sg:classifiers":[
        {
            "category":"Building & Trades",
            "subcategory":"Construction",
            "type":"Services"
        }
    ],
    "sg:phone":"+1 780 925 2387",
    "sg:postcode":"T0H 1G0",
    "sg:province":"AB",
    "sg:tags":[
        "carpenter"
    ],
    "wof:name":"Turcotte Construction",
    "wof:placetype":"venue"
},
  "geometry": {"coordinates":[-117.10546100000001,55.731026],"type":"Point"}
}