{
  "type": "Feature",
  "properties": {
    "addr:full":"621 Rue Principale E Sainte-Agathe-Des-Monts QC J8C 1L1",
    "addr:housenumber":"621",
    "addr:postcode":"j8c 1l1",
    "addr:street":"Rue Principale E Sainte-Agathe-Des-Monts",
    "iso:country":"CA",
    "sg:address":"621 Rue Principale E",
    "sg:city":"Sainte-Agathe-Des-Monts",
    "sg:classifiers":[
        {
            "category":"Restaurant",
            "type":"Food & Drink"
        }
    ],
    "sg:phone":"+1 819 326 5311",
    "sg:postcode":"J8C 1L1",
    "sg:province":"QC",
    "wof:name":"Mikes Restaurant",
    "wof:placetype":"venue"
},
  "geometry": {"coordinates":[-74.27316999999999,46.044327],"type":"Point"}
}