{
  "type": "Feature",
  "properties": {
    "addr:full":"857 May St N Thunder Bay ON P7C 3S2",
    "addr:housenumber":"857",
    "addr:postcode":"p7c 3s2",
    "addr:street":"May St N",
    "iso:country":"CA",
    "sg:address":"857 May St N",
    "sg:city":"Thunder Bay",
    "sg:classifiers":[
        {
            "category":"Building & Trades",
            "subcategory":"Plumbing",
            "type":"Services"
        }
    ],
    "sg:phone":"+1 807 624 2990",
    "sg:postcode":"P7C 3S2",
    "sg:province":"ON",
    "sg:tags":[
        "mechanical",
        "contractor"
    ],
    "wof:name":"Mechanical Contractors Assn",
    "wof:placetype":"venue"
},
  "geometry": {"coordinates":[-89.24574279789999,48.398147583],"type":"Point"}
}