{
  "type": "Feature",
  "properties": {
    "addr:full":"45 Rue Gauthier E Alma QC G8B 1G4",
    "addr:housenumber":"45",
    "addr:postcode":"g8b 1g4",
    "addr:street":"Rue Gauthier E",
    "iso:country":"CA",
    "sg:address":"45 Rue Gauthier E",
    "sg:city":"Alma",
    "sg:classifiers":[
        {
            "category":"Autos & Motor Vehicles",
            "subcategory":"Auto Supplies",
            "type":"Retail Goods"
        }
    ],
    "sg:phone":"+1 418 668 7991",
    "sg:postcode":"G8B 1G4",
    "sg:province":"QC",
    "sg:tags":[
        "automobile",
        "parts"
    ],
    "wof:name":"Uap Napa Pieces D'Auto",
    "wof:placetype":"venue"
},
  "geometry": {"coordinates":[-71.644279,48.540314],"type":"Point"}
}