{
  "type": "Feature",
  "properties": {
    "addr:full":"55 Brisbane Rd North York ON M3J 2K3",
    "addr:housenumber":"55",
    "addr:postcode":"m3j 2k3",
    "addr:street":"Brisbane Rd",
    "iso:country":"CA",
    "sg:address":"55 Brisbane Rd",
    "sg:city":"North York",
    "sg:classifiers":[
        {
            "category":"Manufacturing",
            "subcategory":"Electronics",
            "type":"Manufacturing & Wholesale Goods"
        }
    ],
    "sg:phone":"+1 416 665 8511",
    "sg:postcode":"M3J 2K3",
    "sg:province":"ON",
    "sg:tags":[
        "equipment",
        "electronic",
        "supply"
    ],
    "wof:name":"R L Components Ltd",
    "wof:placetype":"venue"
},
  "geometry": {"coordinates":[-79.47319,43.771904],"type":"Point"}
}