{
  "type": "Feature",
  "properties": {
    "addr:full":"2730 Ch DE LA Cote-Sainte-Cath Montreal QC H3T 1B7",
    "addr:postcode":"2730;h3t 1b7",
    "addr:street":"Ch De La Cote-Sainte-Cath",
    "iso:country":"CA",
    "sg:address":"2730 Ch DE LA Cote-Sainte-Cath",
    "sg:city":"Montreal",
    "sg:classifiers":[
        {
            "category":"Wholesale",
            "subcategory":"Durable Goods & Equipment",
            "type":"Manufacturing & Wholesale Goods"
        }
    ],
    "sg:phone":"+1 514 733 9787",
    "sg:postcode":"H3T 1B7",
    "sg:province":"QC",
    "sg:tags":[
        "exporter"
    ],
    "wof:name":"Agrimpex Inc",
    "wof:placetype":"venue"
},
  "geometry": {"coordinates":[-73.55439,45.512287],"type":"Point"}
}