{
  "type": "Feature",
  "properties": {
    "addr:full":"1500 Rue Du College # 410 Saint-Laurent QC H4L 5G6",
    "addr:housenumber":"1500;# 410",
    "addr:postcode":"h4l 5g6",
    "addr:street":"Rue Du College",
    "iso:country":"CA",
    "sg:address":"1500 Rue Du College # 410",
    "sg:city":"Saint-Laurent",
    "sg:classifiers":[
        {
            "category":"Professional",
            "subcategory":"Lawyer & Legal Services",
            "type":"Services"
        }
    ],
    "sg:phone":"+1 514 335 1122",
    "sg:postcode":"H4L 5G6",
    "sg:province":"QC",
    "sg:tags":[
        "attorney"
    ],
    "wof:name":"Srougi, Nabih",
    "wof:placetype":"venue"
},
  "geometry": {"coordinates":[-73.67506400000001,45.509228],"type":"Point"}
}