{
  "type": "Feature",
  "properties": {
    "iso:country":"CA",
    "sg:address":"1350 Rue Du Relais",
    "sg:city":"Laval",
    "sg:classifiers":[
        {
            "category":"Recreation",
            "type":"Entertainment"
        }
    ],
    "sg:phone":"+1 450 689 9601",
    "sg:postcode":"H7Y 1W2",
    "sg:province":"QC",
    "sg:tags":[
        "government",
        "hall",
        "auditorium"
    ],
    "wof:name":"Centre Jolibourg",
    "wof:placetype":"venue"
},
  "geometry": {"coordinates":[-73.856827,45.524963],"type":"Point"}
}