{
  "type": "Feature",
  "properties": {
    "addr:full":"3075 Ch D'Oka Sainte-Marthe-Sur-Le-Lac QC J0N 1P0",
    "addr:postcode":"3075;j0n 1p0",
    "addr:street":"Ch D'Oka",
    "iso:country":"CA",
    "sg:address":"3075 Ch D'Oka",
    "sg:city":"Sainte-Marthe-Sur-Le-Lac",
    "sg:classifiers":[
        {
            "category":"Shopping",
            "subcategory":"Florist",
            "type":"Retail Goods"
        }
    ],
    "sg:phone":"+1 450 473 5666",
    "sg:postcode":"J0N 1P0",
    "sg:province":"QC",
    "wof:name":"Boutique DE Fleurs Le Petit",
    "wof:placetype":"venue"
},
  "geometry": {"coordinates":[-73.99458312989999,45.5016860962],"type":"Point"}
}