{
  "type": "Feature",
  "properties": {
    "iso:country":"CA",
    "sg:address":"10300 Seacote Rd",
    "sg:city":"Richmond",
    "sg:classifiers":[
        {
            "category":"Education",
            "subcategory":"School",
            "type":"Public Place"
        }
    ],
    "sg:phone":"+1 604 668 6296",
    "sg:postcode":"V7A 4B2",
    "sg:province":"BC",
    "wof:name":"Daniel Woodward Elementary",
    "wof:placetype":"venue"
},
  "geometry": {"coordinates":[-123.098274,49.138046],"type":"Point"}
}