{
  "type": "Feature",
  "properties": {
    "iso:country":"CA",
    "sg:address":"269 Stadacona St W",
    "sg:city":"Moose Jaw",
    "sg:classifiers":[
        {
            "category":"Social Services",
            "subcategory":"Child Care",
            "type":"Services"
        }
    ],
    "sg:phone":"+1 306 693 0754",
    "sg:postcode":"S6H 1Z4",
    "sg:province":"SK",
    "sg:tags":[
        "kindergarten",
        "academic",
        "school"
    ],
    "wof:name":"Head Start Community Pre-Schl",
    "wof:placetype":"venue"
},
  "geometry": {"coordinates":[-105.54196167000001,50.3941993713],"type":"Point"}
}