{
  "type": "Feature",
  "properties": {
    "addr:full":"1209 Boul Sacre-Coeur Saint-Felicien QC G8K 2R1",
    "addr:housenumber":"1209",
    "addr:postcode":"g8k 2r1",
    "addr:street":"Boul Sacre-Coeur Saint-Felicien",
    "iso:country":"CA",
    "sg:address":"1209 Boul Sacre-Coeur",
    "sg:city":"Saint-Felicien",
    "sg:classifiers":[
        {
            "category":"Government",
            "subcategory":"Office",
            "type":"Public Place"
        }
    ],
    "sg:phone":"+1 418 679 0251",
    "sg:postcode":"G8K 2R1",
    "sg:province":"QC",
    "sg:tags":[
        "village"
    ],
    "wof:name":"St-Felicien Hotel DE Ville",
    "wof:placetype":"venue"
},
  "geometry": {"coordinates":[-72.4471206665,48.6532211304],"type":"Point"}
}