{
  "type": "Feature",
  "properties": {
    "addr:full":"850 Champlain Ave Oshawa ON L1J 8C3",
    "addr:housenumber":"850",
    "addr:postcode":"l1j 8c3",
    "addr:street":"Champlain Ave",
    "iso:country":"CA",
    "sg:address":"850 Champlain Ave",
    "sg:city":"Oshawa",
    "sg:classifiers":[
        {
            "category":"Retail",
            "subcategory":"Auto Rental",
            "type":"Services"
        }
    ],
    "sg:phone":"+1 905 436 0171",
    "sg:postcode":"L1J 8C3",
    "sg:province":"ON",
    "sg:tags":[
        "renting",
        "truck",
        "leasing"
    ],
    "wof:name":"Penske Truck Rental & Leasing",
    "wof:placetype":"venue"
},
  "geometry": {"coordinates":[-78.88716100000001,43.873859],"type":"Point"}
}