{
  "type": "Feature",
  "properties": {
    "addr:full":"Stratford ON N5A 6H5",
    "addr:postcode":"n5a 6h5",
    "iso:country":"CA",
    "sg:city":"Stratford",
    "sg:classifiers":[
        {
            "category":"Health Services",
            "subcategory":"Doctor",
            "type":"Services"
        }
    ],
    "sg:phone":"+1 519 272 0064",
    "sg:postcode":"N5A 6H5",
    "sg:province":"ON",
    "sg:tags":[
        "physician",
        "surgeon"
    ],
    "wof:name":"Bukala, B MD",
    "wof:placetype":"venue"
},
  "geometry": {"coordinates":[-80.98799099999999,43.374096],"type":"Point"}
}