{
  "type": "Feature",
  "properties": {
    "addr:full":"1799 Lasalle Blvd Sudbury ON P3A 2A3",
    "addr:housenumber":"1799",
    "addr:postcode":"p3a 2a3",
    "addr:street":"Lasalle Blvd",
    "iso:country":"CA",
    "sg:address":"1799 Lasalle Blvd",
    "sg:city":"Sudbury",
    "sg:classifiers":[
        {
            "category":"Professional",
            "subcategory":"Accounting & Tax Preparation",
            "type":"Services"
        }
    ],
    "sg:phone":"+1 705 524 9863",
    "sg:postcode":"P3A 2A3",
    "sg:province":"ON",
    "sg:tags":[
        "bookkeeping",
        "return",
        "filing",
        "general"
    ],
    "wof:name":"Keen Bookkeeping Svc",
    "wof:placetype":"venue"
},
  "geometry": {"coordinates":[-80.93278503419999,46.5220451355],"type":"Point"}
}