{
  "type": "Feature",
  "properties": {
    "iso:country":"CA",
    "sg:city":"North Vancouver",
    "sg:classifiers":[
        {
            "category":"Real Estate",
            "subcategory":"Real Estate Operator",
            "type":"Services"
        }
    ],
    "sg:phone":"+1 604 980 5467",
    "sg:postcode":"V7P 1R2",
    "sg:province":"BC",
    "sg:tags":[
        "apartment"
    ],
    "wof:name":"Cedar Crest",
    "wof:placetype":"venue"
},
  "geometry": {"coordinates":[-123.095672607,49.3231086731],"type":"Point"}
}