{
  "type": "Feature",
  "properties": {
    "addr:full":"Highway 17 Schreiber ON P0T 2S0",
    "addr:postcode":"p0t 2s0",
    "addr:street":"Highway 17",
    "iso:country":"CA",
    "sg:address":"Highway 17",
    "sg:city":"Schreiber",
    "sg:classifiers":[
        {
            "category":"Travel",
            "subcategory":"Hotels & Motels",
            "type":"Entertainment"
        }
    ],
    "sg:phone":"+1 807 887 1842",
    "sg:postcode":"P0T 2S0",
    "sg:province":"ON",
    "wof:name":"Gravel River Resort",
    "wof:placetype":"venue"
},
  "geometry": {"coordinates":[-87.2664718628,48.8138656616],"type":"Point"}
}