{
  "type": "Feature",
  "properties": {
    "addr:full":"430 Av Du Mont-Royal E Montreal QC H2J 1W1",
    "addr:housenumber":"430",
    "addr:postcode":"h2j 1w1",
    "addr:street":"Av Du Mont-Royal E",
    "iso:country":"CA",
    "sg:address":"430 Av Du Mont-Royal E",
    "sg:city":"Montreal",
    "sg:classifiers":[
        {
            "category":"Health Services",
            "subcategory":"Health Practitioner",
            "type":"Services"
        }
    ],
    "sg:phone":"+1 514 993 0210",
    "sg:postcode":"H2J 1W1",
    "sg:province":"QC",
    "sg:tags":[
        "psychotherapist"
    ],
    "wof:name":"Centre DE Psychotherapie",
    "wof:placetype":"venue"
},
  "geometry": {"coordinates":[-73.58242,45.524242],"type":"Point"}
}