{
  "type": "Feature",
  "properties": {
    "iso:country":"CA",
    "sg:address":"9520 119A St",
    "sg:city":"Delta",
    "sg:classifiers":[
        {
            "category":"Building & Trades",
            "subcategory":"Plumbing",
            "type":"Services"
        }
    ],
    "sg:phone":"+1 604 584 3438",
    "sg:postcode":"V4C 6P2",
    "sg:province":"BC",
    "sg:tags":[
        "sheet",
        "work",
        "metal",
        "contractor"
    ],
    "wof:name":"Aquarius Metal Fabricators",
    "wof:placetype":"venue"
},
  "geometry": {"coordinates":[-123.059616089,49.0848007202],"type":"Point"}
}