{
  "type": "Feature",
  "properties": {
    "addr:full":"Quebec QC G2K 1W6",
    "addr:postcode":"g2k 1w6",
    "iso:country":"CA",
    "sg:city":"Quebec",
    "sg:classifiers":[
        {
            "category":"Retail",
            "subcategory":"Repair Shop",
            "type":"Services"
        }
    ],
    "sg:phone":"+1 418 627 7272",
    "sg:postcode":"G2K 1W6",
    "sg:province":"QC",
    "sg:tags":[
        "tool",
        "parts"
    ],
    "wof:name":"Entreprises Kar-Bat Inc",
    "wof:placetype":"venue"
},
  "geometry": {"coordinates":[-71.28369903559999,46.8534698486],"type":"Point"}
}