{
  "type": "Feature",
  "properties": {
    "addr:full":"921 Twelfth St New Westminster BC V3M 4K7",
    "addr:housenumber":"921",
    "addr:postcode":"v3m 4k7",
    "addr:street":"Twelfth St",
    "iso:country":"CA",
    "sg:address":"921 Twelfth St",
    "sg:city":"New Westminster",
    "sg:classifiers":[
        {
            "category":"Cinema",
            "subcategory":"Movie Rental",
            "type":"Entertainment"
        }
    ],
    "sg:phone":"+1 604 521 6457",
    "sg:postcode":"V3M 4K7",
    "sg:province":"BC",
    "sg:tags":[
        "leasing",
        "video",
        "disc",
        "tape"
    ],
    "wof:name":"Video Stop",
    "wof:placetype":"venue"
},
  "geometry": {"coordinates":[-122.936813,49.212811],"type":"Point"}
}