{
  "type": "Feature",
  "properties": {
    "addr:full":"475 Boul Jutras E Victoriaville QC G6P 7H4",
    "addr:housenumber":"475",
    "addr:postcode":"g6p 7h4",
    "addr:street":"Boul Jutras E",
    "iso:country":"CA",
    "sg:address":"475 Boul Jutras E",
    "sg:city":"Victoriaville",
    "sg:classifiers":[
        {
            "category":"Personal",
            "subcategory":"Beauty Salon",
            "type":"Services"
        }
    ],
    "sg:phone":"+1 819 758 2525",
    "sg:postcode":"G6P 7H4",
    "sg:province":"QC",
    "wof:name":"Coiffure Liz",
    "wof:placetype":"venue"
},
  "geometry": {"coordinates":[-71.9385223389,46.0593261719],"type":"Point"}
}