{
  "type": "Feature",
  "properties": {
    "iso:country":"CA",
    "sg:city":"Edmonton",
    "sg:classifiers":[
        {
            "category":"Health Services",
            "subcategory":"Doctor",
            "type":"Services"
        }
    ],
    "sg:phone":"+1 780 462 9200",
    "sg:postcode":"T6K 3L6",
    "sg:province":"AB",
    "sg:tags":[
        "dentist"
    ],
    "wof:name":"Millbourne Mall Dental Clinic",
    "wof:placetype":"venue"
},
  "geometry": {"coordinates":[-113.453048706,53.4722328186],"type":"Point"}
}