{
  "type": "Feature",
  "properties": {
    "addr:full":"90 Albert St London ON N6A 1L8",
    "addr:housenumber":"90",
    "addr:postcode":"n6a 1l8",
    "addr:street":"Albert St",
    "iso:country":"CA",
    "sg:address":"90 Albert St",
    "sg:city":"London",
    "sg:classifiers":[
        {
            "category":"Professional",
            "subcategory":"Lawyer & Legal Services",
            "type":"Services"
        }
    ],
    "sg:phone":"+1 519 679 9250",
    "sg:postcode":"N6A 1L8",
    "sg:province":"ON",
    "sg:tags":[
        "attorney"
    ],
    "wof:name":"Trudell, Paul",
    "wof:placetype":"venue"
},
  "geometry": {"coordinates":[-81.25480651860001,42.988243103],"type":"Point"}
}