{
  "type": "Feature",
  "properties": {
    "addr:full":"145 Kingston Rd E Ajax ON L1S 7J4",
    "addr:housenumber":"145",
    "addr:postcode":"l1s 7j4",
    "addr:street":"Kingston Rd E",
    "iso:country":"CA",
    "sg:address":"145 Kingston Rd E",
    "sg:city":"Ajax",
    "sg:classifiers":[
        {
            "category":"Food & Beverages",
            "subcategory":"Groceries & Convenience Stores",
            "type":"Retail Goods"
        }
    ],
    "sg:phone":"+1 905 426 6179",
    "sg:postcode":"L1S 7J4",
    "sg:province":"ON",
    "wof:name":"Heritage Convenience Plus",
    "wof:placetype":"venue"
},
  "geometry": {"coordinates":[-79.0185546875,43.862651825],"type":"Point"}
}