{
  "type": "Feature",
  "properties": {
    "addr:full":"7593 Main St W Radium Hot Springs BC V0A 1M0",
    "addr:housenumber":"7593",
    "addr:postcode":"v0a 1m0",
    "addr:street":"Main St W",
    "iso:country":"CA",
    "sg:address":"7593 Main St W",
    "sg:city":"Radium Hot Springs",
    "sg:classifiers":[
        {
            "category":"Travel",
            "subcategory":"Hotels & Motels",
            "type":"Entertainment"
        }
    ],
    "sg:phone":"+1 250 347 9463",
    "sg:postcode":"V0A 1M0",
    "sg:province":"BC",
    "sg:tags":[
        "resort"
    ],
    "wof:name":"Cedar Motel",
    "wof:placetype":"venue"
},
  "geometry": {"coordinates":[-116.06963348399999,50.6175537109],"type":"Point"}
}