{
  "type": "Feature",
  "properties": {
    "addr:full":"130 Clergy St E Kingston ON K7K 3S3",
    "addr:housenumber":"130",
    "addr:postcode":"k7k 3s3",
    "addr:street":"Clergy St E",
    "iso:country":"CA",
    "sg:address":"130 Clergy St E",
    "sg:city":"Kingston",
    "sg:classifiers":[
        {
            "category":"Organizations",
            "subcategory":"Religious Organization",
            "type":"Services"
        }
    ],
    "sg:phone":"+1 613 546 6316",
    "sg:postcode":"K7K 3S3",
    "sg:province":"ON",
    "sg:tags":[
        "church"
    ],
    "wof:name":"St Andrew's Presbyterian Chr",
    "wof:placetype":"venue"
},
  "geometry": {"coordinates":[-76.4889450073,44.2336502075],"type":"Point"}
}