{
  "type": "Feature",
  "properties": {
    "addr:full":"Calgary AB T2Y 3H9",
    "addr:postcode":"t2y 3h9",
    "iso:country":"CA",
    "sg:city":"Calgary",
    "sg:classifiers":[
        {
            "category":"Restaurant",
            "type":"Food & Drink"
        }
    ],
    "sg:phone":"+1 403 543 7200",
    "sg:postcode":"T2Y 3H9",
    "sg:province":"AB",
    "wof:name":"Ricky's All Day Grill",
    "wof:placetype":"venue"
},
  "geometry": {"coordinates":[-114.064865,50.901508],"type":"Point"}
}