{
  "type": "Feature",
  "properties": {
    "addr:full":"Hubley NS B3Z 1B7",
    "addr:postcode":"b3z 1b7",
    "iso:country":"CA",
    "sg:city":"Hubley",
    "sg:classifiers":[
        {
            "category":"Health Services",
            "subcategory":"Nursing And Care Facility",
            "type":"Services"
        }
    ],
    "sg:phone":"+1 902 876 1205",
    "sg:postcode":"B3Z 1B7",
    "sg:province":"NS",
    "sg:tags":[
        "home",
        "convalescent"
    ],
    "wof:name":"Sheldrake Lake Guest Home",
    "wof:placetype":"venue"
},
  "geometry": {"coordinates":[-63.8017997742,44.6761169434],"type":"Point"}
}