{
  "type": "Feature",
  "properties": {
    "addr:full":"Winnipeg MB R3C 3Z3",
    "addr:postcode":"r3c 3z3",
    "iso:country":"CA",
    "sg:city":"Winnipeg",
    "sg:classifiers":[
        {
            "category":"Real Estate",
            "subcategory":"Real Estate Operator",
            "type":"Services"
        }
    ],
    "sg:phone":"+1 204 947 1200",
    "sg:postcode":"R3C 3Z3",
    "sg:province":"MB",
    "sg:tags":[
        "management",
        "apartment"
    ],
    "wof:name":"Marwest Management Canada Ltd",
    "wof:placetype":"venue"
},
  "geometry": {"coordinates":[-97.138206,49.894695],"type":"Point"}
}