{
  "type": "Feature",
  "properties": {
    "addr:full":"40 Byward Market Sq Ottawa ON K1N 7A2",
    "addr:housenumber":"40",
    "addr:postcode":"k1n 7a2",
    "addr:street":"Byward Market Sq",
    "iso:country":"CA",
    "sg:address":"40 Byward Market Sq",
    "sg:city":"Ottawa",
    "sg:classifiers":[
        {
            "category":"Food & Beverages",
            "subcategory":"Dairy",
            "type":"Retail Goods"
        }
    ],
    "sg:phone":"+1 613 241 5411",
    "sg:postcode":"K1N 7A2",
    "sg:province":"ON",
    "sg:tags":[
        "cheese",
        "product"
    ],
    "wof:name":"International Cheese & Deli",
    "wof:placetype":"venue"
},
  "geometry": {"coordinates":[-75.692978,45.427673],"type":"Point"}
}