{
  "type": "Feature",
  "properties": {
    "addr:full":"1204 56 St Delta BC V4L 2A4",
    "addr:housenumber":"1204",
    "addr:postcode":"v4l 2a4",
    "addr:street":"56 St",
    "iso:country":"CA",
    "sg:address":"1204 56 St",
    "sg:city":"Delta",
    "sg:classifiers":[
        {
            "category":"Autos & Motor Vehicles",
            "subcategory":"Fuel & Gas Station",
            "type":"Retail Goods"
        }
    ],
    "sg:phone":"+1 604 948 2073",
    "sg:postcode":"V4L 2A4",
    "sg:province":"BC",
    "sg:tags":[
        "oil"
    ],
    "wof:name":"Beach Grove Chevron",
    "wof:placetype":"venue"
},
  "geometry": {"coordinates":[-123.068466,49.024929],"type":"Point"}
}