{
  "type": "Feature",
  "properties": {
    "addr:full":"151 Rue Saint-Charles O Longueuil QC J4H 1C7",
    "addr:housenumber":"151",
    "addr:postcode":"j4h 1c7",
    "addr:street":"Rue Saint-Charles O",
    "iso:country":"CA",
    "sg:address":"151 Rue Saint-Charles O",
    "sg:city":"Longueuil",
    "sg:classifiers":[
        {
            "category":"Restaurant",
            "type":"Food & Drink"
        }
    ],
    "sg:phone":"+1 450 442 2111",
    "sg:postcode":"J4H 1C7",
    "sg:province":"QC",
    "wof:name":"Restaurant Pinocchio",
    "wof:placetype":"venue"
},
  "geometry": {"coordinates":[-73.5072402954,45.5424728394],"type":"Point"}
}