{
  "type": "Feature",
  "properties": {
    "addr:full":"101 Bonnechere St E Eganville ON K0J 1T0",
    "addr:housenumber":"101",
    "addr:postcode":"k0j 1t0",
    "addr:street":"Bonnechere St E",
    "iso:country":"CA",
    "sg:address":"101 Bonnechere St E",
    "sg:city":"Eganville",
    "sg:classifiers":[
        {
            "category":"Home & Garden",
            "subcategory":"Garden Supply",
            "type":"Retail Goods"
        }
    ],
    "sg:phone":"+1 613 628 1048",
    "sg:postcode":"K0J 1T0",
    "sg:province":"ON",
    "sg:tags":[
        "nurseryman",
        "center"
    ],
    "wof:name":"Temperate Garden",
    "wof:placetype":"venue"
},
  "geometry": {"coordinates":[-77.10066999999999,45.540913],"type":"Point"}
}