{
  "type": "Feature",
  "properties": {
    "addr:full":"706 Shaver Rd Ancaster ON L9G 3K9",
    "addr:housenumber":"706",
    "addr:postcode":"l9g 3k9",
    "addr:street":"Shaver Rd",
    "iso:country":"CA",
    "sg:address":"706 Shaver Rd",
    "sg:city":"Ancaster",
    "sg:classifiers":[
        {
            "category":"Wholesale",
            "subcategory":"Durable Goods & Equipment",
            "type":"Manufacturing & Wholesale Goods"
        }
    ],
    "sg:phone":"+1 905 648 5569",
    "sg:postcode":"L9G 3K9",
    "sg:province":"ON",
    "sg:tags":[
        "laboratory",
        "supply"
    ],
    "wof:name":"Ideal Instrument",
    "wof:placetype":"venue"
},
  "geometry": {"coordinates":[-80.010582,43.191467],"type":"Point"}
}