{
  "type": "Feature",
  "properties": {
    "addr:full":"6235 Stone Church Union ON N0L 2L0",
    "addr:housenumber":"6235",
    "addr:postcode":"n0l 2l0",
    "addr:street":"Stone;Union",
    "iso:country":"CA",
    "sg:address":"6235 Stone Church",
    "sg:city":"Union",
    "sg:classifiers":[
        {
            "category":"Building & Trades",
            "subcategory":"Construction",
            "type":"Services"
        }
    ],
    "sg:phone":"+1 519 631 3677",
    "sg:postcode":"N0L 2L0",
    "sg:province":"ON",
    "sg:tags":[
        "roofing",
        "contractor",
        "general"
    ],
    "wof:name":"Paul Thibodeau Contracting",
    "wof:placetype":"venue"
},
  "geometry": {"coordinates":[-81.19496917719999,42.6887397766],"type":"Point"}
}