{
  "type": "Feature",
  "properties": {
    "addr:full":"206 Indian Rd Toronto ON M6R 2W6",
    "addr:housenumber":"206",
    "addr:postcode":"m6r 2w6",
    "addr:street":"Indian Rd",
    "iso:country":"CA",
    "sg:address":"206 Indian Rd",
    "sg:city":"Toronto",
    "sg:classifiers":[
        {
            "category":"Professional",
            "subcategory":"Accounting & Tax Preparation",
            "type":"Services"
        }
    ],
    "sg:phone":"+1 416 621 8900",
    "sg:postcode":"M6R 2W6",
    "sg:province":"ON",
    "sg:tags":[
        "accountant"
    ],
    "wof:name":"Hlavacek & Sala Accountants",
    "wof:placetype":"venue"
},
  "geometry": {"coordinates":[-79.454643,43.648254],"type":"Point"}
}