{
  "type": "Feature",
  "properties": {
    "addr:full":"473 East 38th St Hamilton ON L8V 4G7",
    "addr:housenumber":"473",
    "addr:postcode":"l8v 4g7",
    "addr:street":"East 38Th St",
    "iso:country":"CA",
    "sg:address":"473 East 38th St",
    "sg:city":"Hamilton",
    "sg:classifiers":[
        {
            "category":"Building & Trades",
            "subcategory":"Construction",
            "type":"Services"
        }
    ],
    "sg:phone":"+1 905 575 5700",
    "sg:postcode":"L8V 4G7",
    "sg:province":"ON",
    "sg:tags":[
        "roofing",
        "contractor"
    ],
    "wof:name":"Larry's Roofing & Siding",
    "wof:placetype":"venue"
},
  "geometry": {"coordinates":[-79.84354399999999,43.220608],"type":"Point"}
}