{
  "type": "Feature",
  "properties": {
    "addr:full":"1100 Rue Craig N Cookshire QC J0B 1M0",
    "addr:housenumber":"1100",
    "addr:postcode":"j0b 1m0",
    "addr:street":"Rue Craig N Cookshire",
    "iso:country":"CA",
    "sg:address":"1100 Rue Craig N",
    "sg:city":"Cookshire",
    "sg:classifiers":[
        {
            "category":"Freight",
            "type":"Transportation"
        }
    ],
    "sg:phone":"+1 819 875 3862",
    "sg:postcode":"J0B 1M0",
    "sg:province":"QC",
    "sg:tags":[
        "trucking"
    ],
    "wof:name":"Transport Jean-Guy Rouleau",
    "wof:placetype":"venue"
},
  "geometry": {"coordinates":[-71.63761100000001,45.424995],"type":"Point"}
}