{
  "type": "Feature",
  "properties": {
    "addr:full":"6325 Boul Henri-Bourassa E Montreal-Nord QC H1G 2V4",
    "addr:housenumber":"6325",
    "addr:postcode":"h1g 2v4",
    "addr:street":"Boul Henri-Bourassa E",
    "iso:country":"CA",
    "sg:address":"6325 Boul Henri-Bourassa E",
    "sg:city":"Montreal-Nord",
    "sg:classifiers":[
        {
            "category":"Travel",
            "subcategory":"Hotels & Motels",
            "type":"Entertainment"
        }
    ],
    "sg:phone":"+1 514 321 6813",
    "sg:postcode":"H1G 2V4",
    "sg:province":"QC",
    "wof:name":"Motel Bourassa Enrg",
    "wof:placetype":"venue"
},
  "geometry": {"coordinates":[-73.61199951170001,45.609588623],"type":"Point"}
}