{
  "type": "Feature",
  "properties": {
    "addr:full":"Red Deer AB T4N 4H5",
    "addr:postcode":"t4n 4h5",
    "iso:country":"CA",
    "sg:city":"Red Deer",
    "sg:classifiers":[
        {
            "category":"Cinema",
            "subcategory":"Movie Rental",
            "type":"Entertainment"
        }
    ],
    "sg:phone":"+1 403 342 1166",
    "sg:postcode":"T4N 4H5",
    "sg:province":"AB",
    "sg:tags":[
        "player",
        "recorder",
        "video",
        "leasing",
        "tape"
    ],
    "wof:name":"Blockbuster Video",
    "wof:placetype":"venue"
},
  "geometry": {"coordinates":[-113.816772,52.26907],"type":"Point"}
}