{
  "type": "Feature",
  "properties": {
    "addr:full":"1380 Boul DE Portland Sherbrooke QC J1J 1S3",
    "addr:housenumber":"1380",
    "addr:postcode":"j1j 1s3",
    "addr:street":"Boul De Portland",
    "iso:country":"CA",
    "sg:address":"1380 Boul DE Portland",
    "sg:city":"Sherbrooke",
    "sg:classifiers":[
        {
            "category":"Recreation",
            "type":"Entertainment"
        }
    ],
    "sg:phone":"+1 819 821 5780",
    "sg:postcode":"J1J 1S3",
    "sg:province":"QC",
    "sg:tags":[
        "center",
        "government"
    ],
    "wof:name":"Sherbrooke Loisirs Nord",
    "wof:placetype":"venue"
},
  "geometry": {"coordinates":[-71.90896600000001,45.403465],"type":"Point"}
}