{
  "type": "Feature",
  "properties": {
    "addr:full":"1025 Ch Du Plan-Bouchard Blainville QC J7C 4K7",
    "addr:housenumber":"1025",
    "addr:postcode":"j7c 4k7",
    "addr:street":"Ch Du Plan-Bouchard",
    "iso:country":"CA",
    "sg:address":"1025 Ch Du Plan-Bouchard",
    "sg:city":"Blainville",
    "sg:classifiers":[
        {
            "category":"Recreation",
            "type":"Entertainment"
        }
    ],
    "sg:phone":"+1 450 433 3909",
    "sg:postcode":"J7C 4K7",
    "sg:province":"QC",
    "sg:tags":[
        "stable"
    ],
    "wof:name":"Poney-Club Blainville",
    "wof:placetype":"venue"
},
  "geometry": {"coordinates":[-73.8708267212,45.6825942993],"type":"Point"}
}