{
  "type": "Feature",
  "properties": {
    "addr:full":"493 Victoria Ave Chatham ON N7L 3B4",
    "addr:housenumber":"493",
    "addr:postcode":"n7l 3b4",
    "addr:street":"Victoria Ave",
    "iso:country":"CA",
    "sg:address":"493 Victoria Ave",
    "sg:city":"Chatham",
    "sg:classifiers":[
        {
            "category":"Organizations",
            "subcategory":"Religious Organization",
            "type":"Services"
        }
    ],
    "sg:phone":"+1 519 354 0060",
    "sg:postcode":"N7L 3B4",
    "sg:province":"ON",
    "sg:tags":[
        "church"
    ],
    "wof:name":"Sprucedale United Church",
    "wof:placetype":"venue"
},
  "geometry": {"coordinates":[-82.2024307251,42.4217567444],"type":"Point"}
}