{
  "type": "Feature",
  "properties": {
    "addr:full":"142 Rue Saint-Joseph Black Lake QC G6H 1W2",
    "addr:housenumber":"142",
    "addr:postcode":"g6h 1w2",
    "addr:street":"Rue Saint-Joseph;Lake",
    "iso:country":"CA",
    "sg:address":"142 Rue Saint-Joseph",
    "sg:city":"Black Lake",
    "sg:classifiers":[
        {
            "category":"Organizations",
            "subcategory":"Professional Association",
            "type":"Services"
        }
    ],
    "sg:phone":"+1 418 423 4147",
    "sg:postcode":"G6H 1W2",
    "sg:province":"QC",
    "wof:name":"Club DE L'Age D'Or Coleraine",
    "wof:placetype":"venue"
},
  "geometry": {"coordinates":[-71.355667,46.045986],"type":"Point"}
}