{
  "type": "Feature",
  "properties": {
    "iso:country":"CA",
    "sg:address":"63 Riverside Dr E",
    "sg:city":"Windsor",
    "sg:classifiers":[
        {
            "category":"Restaurant",
            "type":"Food & Drink"
        }
    ],
    "sg:phone":"+1 519 258 1334",
    "sg:postcode":"N9A 2S4",
    "sg:province":"ON",
    "wof:name":"Papa Cheney's Whiskey Well",
    "wof:placetype":"venue"
},
  "geometry": {"coordinates":[-83.039024,42.319733],"type":"Point"}
}