{
  "type": "Feature",
  "properties": {
    "addr:full":"809 Delmonte Lane Victoria BC V8Y 3H2",
    "addr:housenumber":"809",
    "addr:postcode":"v8y 3h2",
    "addr:street":"Delmonte Lane",
    "iso:country":"CA",
    "sg:address":"809 Delmonte Lane",
    "sg:city":"Victoria",
    "sg:classifiers":[
        {
            "category":"Health Services",
            "subcategory":"Clinic",
            "type":"Services"
        }
    ],
    "sg:phone":"+1 250 472 0141",
    "sg:postcode":"V8Y 3H2",
    "sg:province":"BC",
    "sg:tags":[
        "agency",
        "welfare"
    ],
    "wof:name":"Canadian Celiac Assn Victoria",
    "wof:placetype":"venue"
},
  "geometry": {"coordinates":[-123.36451700000001,48.428314],"type":"Point"}
}