{
  "type": "Feature",
  "properties": {
    "addr:full":"East Angus QC J0B 1R0",
    "addr:postcode":"j0b 1r0",
    "iso:country":"CA",
    "sg:city":"East Angus",
    "sg:classifiers":[
        {
            "category":"Organizations",
            "subcategory":"Professional Association",
            "type":"Services"
        }
    ],
    "sg:phone":"+1 819 832 2711",
    "sg:postcode":"J0B 1R0",
    "sg:province":"QC",
    "wof:name":"Transport Du Bonheur",
    "wof:placetype":"venue"
},
  "geometry": {"coordinates":[-71.66021000000001,45.487072],"type":"Point"}
}