{
  "type": "Feature",
  "properties": {
    "addr:full":"1202 Avenue X S Saskatoon SK S7M 3H9",
    "addr:housenumber":"1202",
    "addr:postcode":"s7m 3h9",
    "addr:street":"Avenue X S",
    "iso:country":"CA",
    "sg:address":"1202 Avenue X S",
    "sg:city":"Saskatoon",
    "sg:classifiers":[
        {
            "category":"Building & Trades",
            "subcategory":"Construction",
            "type":"Services"
        }
    ],
    "sg:phone":"+1 306 931 2344",
    "sg:postcode":"S7M 3H9",
    "sg:province":"SK",
    "sg:tags":[
        "general",
        "contractor"
    ],
    "wof:name":"Petrocare Construction Svc",
    "wof:placetype":"venue"
},
  "geometry": {"coordinates":[-106.704803,52.112988],"type":"Point"}
}