{
  "type": "Feature",
  "properties": {
    "addr:full":"70 Green Hedge Lane London ON N6H 5A6",
    "addr:housenumber":"70",
    "addr:postcode":"n6h 5a6",
    "addr:street":"Green Hedge Lane",
    "iso:country":"CA",
    "sg:address":"70 Green Hedge Lane",
    "sg:city":"London",
    "sg:classifiers":[
        {
            "category":"Professional",
            "subcategory":"Management & Consulting",
            "type":"Services"
        }
    ],
    "sg:phone":"+1 519 657 9980",
    "sg:postcode":"N6H 5A6",
    "sg:province":"ON",
    "sg:tags":[
        "consultant",
        "business"
    ],
    "wof:name":"David Williamson & CO",
    "wof:placetype":"venue"
},
  "geometry": {"coordinates":[-81.320419,42.964436],"type":"Point"}
}