{
  "type": "Feature",
  "properties": {
    "addr:full":"Brookfield NS B0N 1C0",
    "addr:postcode":"b0n 1c0",
    "iso:country":"CA",
    "sg:city":"Brookfield",
    "sg:classifiers":[
        {
            "category":"Health Services",
            "subcategory":"Doctor",
            "type":"Services"
        }
    ],
    "sg:phone":"+1 902 895 6525",
    "sg:postcode":"B0N 1C0",
    "sg:province":"NS",
    "sg:tags":[
        "physician",
        "surgeon"
    ],
    "wof:name":"Hilden Medical Ctr",
    "wof:placetype":"venue"
},
  "geometry": {"coordinates":[-63.279518,45.253689],"type":"Point"}
}