{
  "type": "Feature",
  "properties": {
    "addr:full":"1476 Marine Dr West Vancouver BC V7T 1B7",
    "addr:housenumber":"1476",
    "addr:postcode":"v7t 1b7",
    "addr:street":"Marine Dr",
    "iso:country":"CA",
    "sg:address":"1476 Marine Dr",
    "sg:city":"West Vancouver",
    "sg:classifiers":[
        {
            "category":"Food & Beverages",
            "subcategory":"Fruits & Vegetables",
            "type":"Retail Goods"
        }
    ],
    "sg:phone":"+1 604 922 8140",
    "sg:postcode":"V7T 1B7",
    "sg:province":"BC",
    "wof:name":"West Van Produce Ltd",
    "wof:placetype":"venue"
},
  "geometry": {"coordinates":[-123.15612793,49.3280715942],"type":"Point"}
}