{
  "type": "Feature",
  "properties": {
    "addr:full":"224 Pitt St Cornwall ON K6J 3P6",
    "addr:housenumber":"224",
    "addr:postcode":"k6j 3p6",
    "addr:street":"Pitt St",
    "iso:country":"CA",
    "sg:address":"224 Pitt St",
    "sg:city":"Cornwall",
    "sg:classifiers":[
        {
            "category":"Shopping",
            "subcategory":"Used Merchandise",
            "type":"Retail Goods"
        }
    ],
    "sg:phone":"+1 613 933 2333",
    "sg:postcode":"K6J 3P6",
    "sg:province":"ON",
    "sg:tags":[
        "pawnbroker"
    ],
    "wof:name":"Poppy's Pawns Plus",
    "wof:placetype":"venue"
},
  "geometry": {"coordinates":[-74.72914123539999,45.0186843872],"type":"Point"}
}