{
  "type": "Feature",
  "properties": {
    "iso:country":"CA",
    "sg:address":"174 Bayfield St",
    "sg:city":"Barrie",
    "sg:classifiers":[
        {
            "category":"Shopping",
            "subcategory":"Clothing, Apparel, & Fashions",
            "type":"Retail Goods"
        }
    ],
    "sg:phone":"+1 705 728 7537",
    "sg:postcode":"L4M 3B5",
    "sg:province":"ON",
    "sg:tags":[
        "shop",
        "bridal"
    ],
    "wof:name":"Bridal Wreath",
    "wof:placetype":"venue"
},
  "geometry": {"coordinates":[-79.694862,44.394508],"type":"Point"}
}