{
  "type": "Feature",
  "properties": {
    "addr:full":"16 Bimbrok Rd Scarborough ON M1K 4T7",
    "addr:housenumber":"16",
    "addr:postcode":"m1k 4t7",
    "addr:street":"Bimbrok Rd",
    "iso:country":"CA",
    "sg:address":"16 Bimbrok Rd",
    "sg:city":"Scarborough",
    "sg:classifiers":[
        {
            "category":"Health Services",
            "subcategory":"Health Practitioner",
            "type":"Services"
        }
    ],
    "sg:phone":"+1 416 269 8979",
    "sg:postcode":"M1K 4T7",
    "sg:province":"ON",
    "sg:tags":[
        "acupuncture"
    ],
    "wof:name":"East End Naturopathic Ctr",
    "wof:placetype":"venue"
},
  "geometry": {"coordinates":[-79.25256299999999,43.736687],"type":"Point"}
}