{
  "type": "Feature",
  "properties": {
    "addr:full":"2770 E Victoria Ave Regina SK S4N 6M5",
    "addr:housenumber":"2770",
    "addr:postcode":"s4n 6m5",
    "addr:street":"E Victoria Ave",
    "iso:country":"CA",
    "sg:address":"2770 E Victoria Ave",
    "sg:city":"Regina",
    "sg:classifiers":[
        {
            "category":"Wholesale",
            "subcategory":"Farm Supplies",
            "type":"Manufacturing & Wholesale Goods"
        }
    ],
    "sg:phone":"+1 306 721 5115",
    "sg:postcode":"S4N 6M5",
    "sg:province":"SK",
    "sg:tags":[
        "equipment",
        "hydraulic"
    ],
    "wof:name":"Princess Auto Ltd",
    "wof:placetype":"venue"
},
  "geometry": {"coordinates":[-104.54376999999999,50.447777],"type":"Point"}
}