{
  "type": "Feature",
  "properties": {
    "addr:full":"Valleyview AB T0H 3N0",
    "addr:postcode":"t0h 3n0",
    "iso:country":"CA",
    "sg:city":"Valleyview",
    "sg:classifiers":[
        {
            "category":"Travel",
            "subcategory":"Campground",
            "type":"Entertainment"
        }
    ],
    "sg:phone":"+1 780 524 4949",
    "sg:postcode":"T0H 3N0",
    "sg:province":"AB",
    "wof:name":"Sherk's Rv Park",
    "wof:placetype":"venue"
},
  "geometry": {"coordinates":[-117.27177399999999,55.068642],"type":"Point"}
}