{
  "type": "Feature",
  "properties": {
    "iso:country":"CA",
    "sg:address":"336 Pine St",
    "sg:city":"Sudbury",
    "sg:classifiers":[
        {
            "category":"Health Services",
            "subcategory":"Hospital",
            "type":"Services"
        }
    ],
    "sg:phone":"+1 705 675 7022",
    "sg:postcode":"P3C 1X8",
    "sg:province":"ON",
    "sg:tags":[
        "info",
        "mental",
        "drug",
        "abuse",
        "treatment",
        "addiction"
    ],
    "wof:name":"Pinegate Women's Withdrawal",
    "wof:placetype":"venue"
},
  "geometry": {"coordinates":[-81.0074920654,46.4939880371],"type":"Point"}
}