{
  "type": "Feature",
  "properties": {
    "addr:full":"Montreal QC H3T 1Y6",
    "addr:postcode":"h3t 1y6",
    "iso:country":"CA",
    "sg:city":"Montreal",
    "sg:classifiers":[
        {
            "category":"Health Services",
            "subcategory":"Doctor",
            "type":"Services"
        }
    ],
    "sg:phone":"+1 514 342 0551",
    "sg:postcode":"H3T 1Y6",
    "sg:province":"QC",
    "sg:tags":[
        "dentist"
    ],
    "wof:name":"Clinique Dentaire Nguyet Ngo",
    "wof:placetype":"venue"
},
  "geometry": {"coordinates":[-73.624016,45.496975],"type":"Point"}
}