{
  "type": "Feature",
  "properties": {
    "iso:country":"CA",
    "sg:address":"6024 87 St NW",
    "sg:city":"Edmonton",
    "sg:classifiers":[
        {
            "category":"Wholesale",
            "subcategory":"Machinery & Supplies",
            "type":"Manufacturing & Wholesale Goods"
        }
    ],
    "sg:phone":"+1 780 499 2690",
    "sg:postcode":"T6E 2Y4",
    "sg:province":"AB",
    "sg:tags":[
        "pump"
    ],
    "wof:name":"Brico Pumps",
    "wof:placetype":"venue"
},
  "geometry": {"coordinates":[-113.458381653,53.496006012],"type":"Point"}
}