{
  "type": "Feature",
  "properties": {
    "iso:country":"CA",
    "sg:address":"4230 12E Av",
    "sg:city":"Shawinigan-Sud",
    "sg:classifiers":[
        {
            "category":"Restaurant",
            "type":"Food & Drink"
        }
    ],
    "sg:phone":"+1 819 536 5648",
    "sg:postcode":"G9P 4G2",
    "sg:province":"QC",
    "wof:name":"Restaurant Olympia",
    "wof:placetype":"venue"
},
  "geometry": {"coordinates":[-72.7281036377,46.5030593872],"type":"Point"}
}