{
  "type": "Feature",
  "properties": {
    "addr:full":"2618 Commercial Dr Vancouver BC V5N 5R4",
    "addr:housenumber":"2618",
    "addr:postcode":"v5n 5r4",
    "addr:street":"Commercial Dr",
    "iso:country":"CA",
    "sg:address":"2618 Commercial Dr",
    "sg:city":"Vancouver",
    "sg:classifiers":[
        {
            "category":"Health Services",
            "subcategory":"Doctor",
            "type":"Services"
        }
    ],
    "sg:phone":"+1 604 874 4261",
    "sg:postcode":"V5N 5R4",
    "sg:province":"BC",
    "sg:tags":[
        "dentist"
    ],
    "wof:name":"Eddy Lam Inc",
    "wof:placetype":"venue"
},
  "geometry": {"coordinates":[-123.069656372,49.2611541748],"type":"Point"}
}