{
  "type": "Feature",
  "properties": {
    "addr:full":"1073 Boul Rene-Levesque O Sillery QC G1S 4R5",
    "addr:housenumber":"1073",
    "addr:postcode":"g1s 4r5",
    "addr:street":"Boul Rene-Levesque O",
    "iso:country":"CA",
    "sg:address":"1073 Boul Rene-Levesque O",
    "sg:city":"Sillery",
    "sg:classifiers":[
        {
            "category":"Organizations",
            "subcategory":"Professional Association",
            "type":"Services"
        }
    ],
    "sg:phone":"+1 418 688 0426",
    "sg:postcode":"G1S 4R5",
    "sg:province":"QC",
    "wof:name":"Respect DE LA Vie",
    "wof:placetype":"venue"
},
  "geometry": {"coordinates":[-71.243347,46.794674],"type":"Point"}
}