{
  "type": "Feature",
  "properties": {
    "iso:country":"CA",
    "sg:address":"2320 Rue Principale",
    "sg:city":"Saint-Cuthbert",
    "sg:classifiers":[
        {
            "category":"Farming",
            "subcategory":"Farm",
            "type":"Manufacturing & Wholesale Goods"
        }
    ],
    "sg:phone":"+1 450 836 3063",
    "sg:postcode":"J0K 2C0",
    "sg:province":"QC",
    "wof:name":"Volaille Giannone Inc",
    "wof:placetype":"venue"
},
  "geometry": {"coordinates":[-73.2266616821,46.1494064331],"type":"Point"}
}