{
  "type": "Feature",
  "properties": {
    "addr:full":"822 Lounsborough St Windsor ON N9G 1G3",
    "addr:housenumber":"822",
    "addr:postcode":"n9g 1g3",
    "addr:street":"Lounsborough St",
    "iso:country":"CA",
    "sg:address":"822 Lounsborough St",
    "sg:city":"Windsor",
    "sg:classifiers":[
        {
            "category":"Professional",
            "subcategory":"Engineering",
            "type":"Services"
        }
    ],
    "sg:phone":"+1 519 972 0677",
    "sg:postcode":"N9G 1G3",
    "sg:province":"ON",
    "sg:tags":[
        "engineer"
    ],
    "wof:name":"Spaarg Engineering Ltd",
    "wof:placetype":"venue"
},
  "geometry": {"coordinates":[-82.98638200000001,42.258896],"type":"Point"}
}