{
  "type": "Feature",
  "properties": {
    "addr:full":"1510 Hwy 27 Schomberg ON L0G 1T0",
    "addr:housenumber":"1510",
    "addr:postcode":"l0g 1t0",
    "addr:street":"Hwy 27",
    "iso:country":"CA",
    "sg:address":"1510 Hwy 27",
    "sg:city":"Schomberg",
    "sg:classifiers":[
        {
            "category":"Building & Trades",
            "subcategory":"Landscaping Services",
            "type":"Services"
        }
    ],
    "sg:phone":"+1 905 939 1230",
    "sg:postcode":"L0G 1T0",
    "sg:province":"ON",
    "sg:tags":[
        "landscape",
        "contractor"
    ],
    "wof:name":"Hermanns Contracting Ltd",
    "wof:placetype":"venue"
},
  "geometry": {"coordinates":[-79.665725708,43.9567604065],"type":"Point"}
}