{
  "type": "Feature",
  "properties": {
    "addr:full":"422 Richards St # 170 Vancouver BC V6B 2Z4",
    "addr:housenumber":"422",
    "addr:postcode":"v6b 2z4",
    "addr:street":"Richards St # 170",
    "iso:country":"CA",
    "sg:address":"422 Richards St # 170",
    "sg:city":"Vancouver",
    "sg:classifiers":[
        {
            "category":"Shopping",
            "subcategory":"Used Merchandise",
            "type":"Retail Goods"
        }
    ],
    "sg:phone":"+1 604 684 9822",
    "sg:postcode":"V6B 2Z4",
    "sg:province":"BC",
    "sg:tags":[
        "antique"
    ],
    "wof:name":"Harbour Hall Antiques",
    "wof:placetype":"venue"
},
  "geometry": {"coordinates":[-123.111953735,49.2837295532],"type":"Point"}
}