{
  "type": "Feature",
  "properties": {
    "addr:full":"250 Shirley Ave Kitchener ON N2B 2E1",
    "addr:housenumber":"250",
    "addr:postcode":"n2b 2e1",
    "addr:street":"Shirley Ave",
    "iso:country":"CA",
    "sg:address":"250 Shirley Ave",
    "sg:city":"Kitchener",
    "sg:classifiers":[
        {
            "category":"Building & Trades",
            "subcategory":"Construction",
            "type":"Services"
        }
    ],
    "sg:phone":"+1 519 743 4353",
    "sg:postcode":"N2B 2E1",
    "sg:province":"ON",
    "sg:tags":[
        "bridge",
        "builder"
    ],
    "wof:name":"Eagle Bridge",
    "wof:placetype":"venue"
},
  "geometry": {"coordinates":[-80.459366,43.468857],"type":"Point"}
}