{
  "type": "Feature",
  "properties": {
    "iso:country":"CA",
    "sg:address":"80 Rue Principale",
    "sg:city":"Saint-Michel-DE-Bellechasse",
    "sg:classifiers":[
        {
            "category":"Health Services",
            "subcategory":"Nursing And Care Facility",
            "type":"Services"
        }
    ],
    "sg:phone":"+1 418 884 2811",
    "sg:postcode":"G0R 3S0",
    "sg:province":"QC",
    "sg:tags":[
        "home",
        "hospital",
        "rest"
    ],
    "wof:name":"Chsld",
    "wof:placetype":"venue"
},
  "geometry": {"coordinates":[-70.9102478027,46.8750801086],"type":"Point"}
}