{
  "type": "Feature",
  "properties": {
    "addr:full":"1072 Aspen Dr Zama City AB T0H 4E0",
    "addr:housenumber":"1072",
    "addr:postcode":"t0h 4e0",
    "addr:street":"Aspen Dr Zama",
    "iso:country":"CA",
    "sg:address":"1072 Aspen Dr",
    "sg:city":"Zama City",
    "sg:classifiers":[
        {
            "category":"Mining & Drilling",
            "type":"Manufacturing & Wholesale Goods"
        }
    ],
    "sg:phone":"+1 780 683 2132",
    "sg:postcode":"T0H 4E0",
    "sg:province":"AB",
    "sg:tags":[
        "field",
        "oil"
    ],
    "wof:name":"Norm's Oilfield Svc Ltd",
    "wof:placetype":"venue"
},
  "geometry": {"coordinates":[-118.620079041,59.1942062378],"type":"Point"}
}