{
  "type": "Feature",
  "properties": {
    "addr:full":"811 Rte Du President-Kennedy Pintendre QC G6C 1C9",
    "addr:housenumber":"811",
    "addr:postcode":"g6c 1c9",
    "addr:street":"Rte Du President-Kennedy Pintendre",
    "iso:country":"CA",
    "sg:address":"811 Rte Du President-Kennedy",
    "sg:city":"Pintendre",
    "sg:classifiers":[
        {
            "category":"Retail",
            "subcategory":"Auto Repair",
            "type":"Services"
        }
    ],
    "sg:phone":"+1 418 837 3577",
    "sg:postcode":"G6C 1C9",
    "sg:province":"QC",
    "sg:tags":[
        "repairing",
        "automobile"
    ],
    "wof:name":"Martin Dube Atelier-Silencieux",
    "wof:placetype":"venue"
},
  "geometry": {"coordinates":[-71.120667,46.75391],"type":"Point"}
}