{
  "type": "Feature",
  "properties": {
    "addr:full":"84 Queen St Niagara on the Lake ON L0S 1J0",
    "addr:housenumber":"84",
    "addr:postcode":"l0s 1j0",
    "addr:street":"Queen St;On",
    "iso:country":"CA",
    "sg:address":"84 Queen St",
    "sg:city":"Niagara on the Lake",
    "sg:classifiers":[
        {
            "category":"Restaurant",
            "type":"Food & Drink"
        }
    ],
    "sg:phone":"+1 905 468 3408",
    "sg:postcode":"L0S 1J0",
    "sg:province":"ON",
    "wof:name":"Epicurean Fine Foods",
    "wof:placetype":"venue"
},
  "geometry": {"coordinates":[-79.07350158689999,43.2559318542],"type":"Point"}
}