{
  "type": "Feature",
  "properties": {
    "addr:full":"124 Rue Saint-Raphael LA Malbaie QC G5A 1X9",
    "addr:housenumber":"124",
    "addr:postcode":"g5a 1x9",
    "addr:street":"Rue Saint-Raphael",
    "iso:country":"CA",
    "sg:address":"124 Rue Saint-Raphael",
    "sg:city":"LA Malbaie",
    "sg:classifiers":[
        {
            "category":"Travel",
            "subcategory":"Hotels & Motels",
            "type":"Entertainment"
        }
    ],
    "sg:phone":"+1 418 665 4431",
    "sg:postcode":"G5A 1X9",
    "sg:province":"QC",
    "wof:name":"Auberge LA Pinsonniere Inc",
    "wof:placetype":"venue"
},
  "geometry": {"coordinates":[-70.115921,47.658012],"type":"Point"}
}