{
  "type": "Feature",
  "properties": {
    "addr:full":"116 Chartier Ave E St Lazare MB R0M 1Y0",
    "addr:housenumber":"116",
    "addr:postcode":"r0m 1y0",
    "addr:street":"Chartier Ave E St Lazare",
    "iso:country":"CA",
    "sg:address":"116 Chartier Ave E",
    "sg:city":"St Lazare",
    "sg:classifiers":[
        {
            "category":"Education",
            "subcategory":"School",
            "type":"Public Place"
        }
    ],
    "sg:phone":"+1 204 683 2251",
    "sg:postcode":"R0M 1Y0",
    "sg:province":"MB",
    "wof:name":"Ecole St Lazare",
    "wof:placetype":"venue"
},
  "geometry": {"coordinates":[-101.30325317400001,50.4489059448],"type":"Point"}
}