{
  "type": "Feature",
  "properties": {
    "addr:full":"Meaghers Grant NS B0N 1V0",
    "addr:postcode":"b0n 1v0",
    "iso:country":"CA",
    "sg:city":"Meaghers Grant",
    "sg:classifiers":[
        {
            "category":"Sports & Exercise",
            "subcategory":"Golf",
            "type":"Entertainment"
        }
    ],
    "sg:phone":"+1 902 384 2033",
    "sg:postcode":"B0N 1V0",
    "sg:province":"NS",
    "sg:tags":[
        "course"
    ],
    "wof:name":"River Oaks Golf Club",
    "wof:placetype":"venue"
},
  "geometry": {"coordinates":[-63.2294006348,44.9121322632],"type":"Point"}
}