{
  "type": "Feature",
  "properties": {
    "addr:full":"4941 49 St Camrose AB T4V 1N3",
    "addr:housenumber":"4941",
    "addr:postcode":"t4v 1n3",
    "addr:street":"49 St",
    "iso:country":"CA",
    "sg:address":"4941 49 St",
    "sg:city":"Camrose",
    "sg:classifiers":[
        {
            "category":"Shopping",
            "type":"Retail Goods"
        }
    ],
    "sg:phone":"+1 780 672 5848",
    "sg:postcode":"T4V 1N3",
    "sg:province":"AB",
    "sg:tags":[
        "picture",
        "frame"
    ],
    "wof:name":"Fine Framing & Such",
    "wof:placetype":"venue"
},
  "geometry": {"coordinates":[-112.823341,53.021145],"type":"Point"}
}