{
  "type": "Feature",
  "properties": {
    "addr:full":"10049 Yonge St Richmond Hill ON L4C 1T7",
    "addr:housenumber":"10049",
    "addr:postcode":"l4c 1t7",
    "addr:street":"Yonge St",
    "iso:country":"CA",
    "sg:address":"10049 Yonge St",
    "sg:city":"Richmond Hill",
    "sg:classifiers":[
        {
            "category":"Health Services",
            "subcategory":"Health Practitioner",
            "type":"Services"
        }
    ],
    "sg:phone":"+1 905 737 5195",
    "sg:postcode":"L4C 1T7",
    "sg:province":"ON",
    "sg:tags":[
        "acupuncture"
    ],
    "wof:name":"Mac Yonge Physiotherapy Clinic",
    "wof:placetype":"venue"
},
  "geometry": {"coordinates":[-79.4373016357,43.8725090027],"type":"Point"}
}