{
  "type": "Feature",
  "properties": {
    "iso:country":"CA",
    "sg:address":"3461 Rue DE L'Energie",
    "sg:city":"Jonquiere",
    "sg:classifiers":[
        {
            "category":"Building & Trades",
            "subcategory":"Construction",
            "type":"Services"
        }
    ],
    "sg:phone":"+1 418 542 3749",
    "sg:postcode":"G7X 0C1",
    "sg:province":"QC",
    "sg:tags":[
        "general",
        "contractor"
    ],
    "wof:name":"Terrassement St Louis Inc",
    "wof:placetype":"venue"
},
  "geometry": {"coordinates":[-71.21891021730001,48.4080810547],"type":"Point"}
}