{
  "type": "Feature",
  "properties": {
    "iso:country":"CA",
    "sg:address":"106 Pacific Trans Hwy 2",
    "sg:city":"Elm Creek",
    "sg:classifiers":[
        {
            "category":"Freight",
            "type":"Transportation"
        }
    ],
    "sg:phone":"+1 204 436 2010",
    "sg:postcode":"R0G 0N0",
    "sg:province":"MB",
    "sg:tags":[
        "grain",
        "elevator"
    ],
    "wof:name":"Cargill Limited",
    "wof:placetype":"venue"
},
  "geometry": {"coordinates":[-97.99304199220001,49.6755638123],"type":"Point"}
}