{
  "type": "Feature",
  "properties": {
    "addr:full":"120 Rte 153 Sainte-Thecle QC G0X 3G0",
    "addr:housenumber":"120",
    "addr:postcode":"g0x 3g0",
    "addr:street":"Rte 153 Sainte-Thecle",
    "iso:country":"CA",
    "sg:address":"120 Rte 153",
    "sg:city":"Sainte-Thecle",
    "sg:classifiers":[
        {
            "category":"Building & Trades",
            "subcategory":"Construction",
            "type":"Services"
        }
    ],
    "sg:phone":"+1 418 289 3093",
    "sg:postcode":"G0X 3G0",
    "sg:province":"QC",
    "sg:tags":[
        "water",
        "well",
        "drilling"
    ],
    "wof:name":"Marcel Beaupre Puits Artesiens",
    "wof:placetype":"venue"
},
  "geometry": {"coordinates":[-72.50424957280001,46.8118667603],"type":"Point"}
}