{
  "type": "Feature",
  "properties": {
    "iso:country":"CA",
    "sg:address":"102 Durham",
    "sg:city":"White River",
    "sg:classifiers":[
        {
            "category":"Government",
            "subcategory":"Office",
            "type":"Public Place"
        }
    ],
    "sg:phone":"+1 807 822 2450",
    "sg:postcode":"P0M 3G0",
    "sg:province":"ON",
    "sg:tags":[
        "village"
    ],
    "wof:name":"White River Municipal Ofc",
    "wof:placetype":"venue"
},
  "geometry": {"coordinates":[-85.27722199999999,48.589558],"type":"Point"}
}