{
  "type": "Feature",
  "properties": {
    "addr:full":"45 Spruce St Garson ON P3L 1P8",
    "addr:housenumber":"45",
    "addr:postcode":"p3l 1p8",
    "addr:street":"Spruce St",
    "iso:country":"CA",
    "sg:address":"45 Spruce St",
    "sg:city":"Garson",
    "sg:classifiers":[
        {
            "category":"Social Services",
            "subcategory":"Child Care",
            "type":"Services"
        }
    ],
    "sg:phone":"+1 705 693 3767",
    "sg:postcode":"P3L 1P8",
    "sg:province":"ON",
    "wof:name":"Northeastern Kids",
    "wof:placetype":"venue"
},
  "geometry": {"coordinates":[-80.857147,46.561131],"type":"Point"}
}