{
  "type": "Feature",
  "properties": {
    "addr:full":"18 Lola Rd Toronto ON M5P 1E4",
    "addr:housenumber":"18",
    "addr:postcode":"m5p 1e4",
    "addr:street":"Lola Rd",
    "iso:country":"CA",
    "sg:address":"18 Lola Rd",
    "sg:city":"Toronto",
    "sg:classifiers":[
        {
            "category":"Health Services",
            "subcategory":"Chiropractor",
            "type":"Services"
        }
    ],
    "sg:phone":"+1 416 489 0077",
    "sg:postcode":"M5P 1E4",
    "sg:province":"ON",
    "wof:name":"Urban Chiropractic",
    "wof:placetype":"venue"
},
  "geometry": {"coordinates":[-79.3978729248,43.7018203735],"type":"Point"}
}