{
  "type": "Feature",
  "properties": {
    "iso:country":"CA",
    "sg:address":"1510 16 Ave NW",
    "sg:city":"Calgary",
    "sg:classifiers":[
        {
            "category":"Travel",
            "subcategory":"Travel Agent",
            "type":"Entertainment"
        }
    ],
    "sg:phone":"+1 403 289 6656",
    "sg:postcode":"T2M 0L5",
    "sg:province":"AB",
    "sg:tags":[
        "agency",
        "bureau"
    ],
    "wof:name":"Airline Ticket Ctr",
    "wof:placetype":"venue"
},
  "geometry": {"coordinates":[-114.095809937,51.0670700073],"type":"Point"}
}