{
  "type": "Feature",
  "properties": {
    "addr:full":"1744 Kenneth Dr Val Therese ON P3P 1S4",
    "addr:housenumber":"1744",
    "addr:postcode":"p3p 1s4",
    "addr:street":"Kenneth Dr",
    "iso:country":"CA",
    "sg:address":"1744 Kenneth Dr",
    "sg:city":"Val Therese",
    "sg:classifiers":[
        {
            "category":"Wholesale",
            "subcategory":"Construction Materials",
            "type":"Manufacturing & Wholesale Goods"
        }
    ],
    "sg:phone":"+1 705 969 2732",
    "sg:postcode":"P3P 1S4",
    "sg:province":"ON",
    "sg:tags":[
        "pallet",
        "skid"
    ],
    "wof:name":"Ouellet Lumber",
    "wof:placetype":"venue"
},
  "geometry": {"coordinates":[-81.013611,46.652794],"type":"Point"}
}