{
  "type": "Feature",
  "properties": {
    "addr:full":"784 Gravel Dr Hanmer ON P3P 1R8",
    "addr:housenumber":"784",
    "addr:postcode":"p3p 1r8",
    "addr:street":"Gravel Dr",
    "iso:country":"CA",
    "sg:address":"784 Gravel Dr",
    "sg:city":"Hanmer",
    "sg:classifiers":[
        {
            "category":"Building & Trades",
            "subcategory":"Plumbing",
            "type":"Services"
        }
    ],
    "sg:phone":"+1 705 969 3583",
    "sg:postcode":"P3P 1R8",
    "sg:province":"ON",
    "sg:tags":[
        "heating",
        "contractor"
    ],
    "wof:name":"Regional Sheet Metal",
    "wof:placetype":"venue"
},
  "geometry": {"coordinates":[-80.97687500000001,46.667538],"type":"Point"}
}