{
  "type": "Feature",
  "properties": {
    "iso:country":"CA",
    "sg:city":"Prince Rupert",
    "sg:classifiers":[
        {
            "category":"Freight",
            "type":"Transportation"
        }
    ],
    "sg:phone":"+1 250 624 5233",
    "sg:postcode":"V8J 1L5",
    "sg:province":"BC",
    "sg:tags":[
        "shipping",
        "agent"
    ],
    "wof:name":"G W Nickerson CO",
    "wof:placetype":"venue"
},
  "geometry": {"coordinates":[-130.32421875,54.3132858276],"type":"Point"}
}