{
  "type": "Feature",
  "properties": {
    "addr:full":"8 Lessard Dr Yellowknife NT X1A 2G5",
    "addr:housenumber":"8",
    "addr:postcode":"x1a 2g5",
    "addr:street":"Lessard Dr",
    "iso:country":"CA",
    "sg:address":"8 Lessard Dr",
    "sg:city":"Yellowknife",
    "sg:classifiers":[
        {
            "category":"Travel",
            "subcategory":"Hotels & Motels",
            "type":"Entertainment"
        }
    ],
    "sg:phone":"+1 867 873 3746",
    "sg:postcode":"X1A 2G5",
    "sg:province":"NT",
    "sg:tags":[
        "breakfast",
        "accommodation",
        "bed"
    ],
    "wof:name":"Captain Ron's Bed & Breakfast",
    "wof:placetype":"venue"
},
  "geometry": {"coordinates":[-114.34681701700001,62.4679107666],"type":"Point"}
}