{
  "type": "Feature",
  "properties": {
    "addr:full":"199 Ontario St Burks Falls ON P0A 1C0",
    "addr:housenumber":"199",
    "addr:postcode":"p0a 1c0",
    "addr:street":"Ontario St",
    "iso:country":"CA",
    "sg:address":"199 Ontario St",
    "sg:city":"Burks Falls",
    "sg:classifiers":[
        {
            "category":"Restaurant",
            "type":"Food & Drink"
        }
    ],
    "sg:phone":"+1 705 382 3945",
    "sg:postcode":"P0A 1C0",
    "sg:province":"ON",
    "wof:name":"Mark's Village Restaurant",
    "wof:placetype":"venue"
},
  "geometry": {"coordinates":[-83.5641860962,46.2570953369],"type":"Point"}
}