{
  "type": "Feature",
  "properties": {
    "iso:country":"CA",
    "sg:city":"Norwich",
    "sg:classifiers":[
        {
            "category":"Government",
            "subcategory":"Office",
            "type":"Public Place"
        }
    ],
    "sg:phone":"+1 519 863 3430",
    "sg:postcode":"N0J 1P0",
    "sg:province":"ON",
    "wof:name":"Ontario Driver & Vehicle Lcnc",
    "wof:placetype":"venue"
},
  "geometry": {"coordinates":[-80.5986175537,42.9875679016],"type":"Point"}
}