{
  "type": "Feature",
  "properties": {
    "addr:full":"1063 Chemong Rd Peterborough ON K9H 7R8",
    "addr:housenumber":"1063",
    "addr:postcode":"k9h 7r8",
    "addr:street":"Chemong Rd",
    "iso:country":"CA",
    "sg:address":"1063 Chemong Rd",
    "sg:city":"Peterborough",
    "sg:classifiers":[
        {
            "category":"Restaurant",
            "type":"Food & Drink"
        }
    ],
    "sg:phone":"+1 705 745 0550",
    "sg:postcode":"K9H 7R8",
    "sg:province":"ON",
    "wof:name":"Arby's",
    "wof:placetype":"venue"
},
  "geometry": {"coordinates":[-78.337822,44.325336],"type":"Point"}
}