{
  "type": "Feature",
  "properties": {
    "addr:full":"5825 Rue Saint-Jacques #1800 Montreal QC H4A 2G1",
    "addr:housenumber":"5825",
    "addr:postcode":"h4a 2g1",
    "addr:street":"Rue Saint-Jacques # 1800",
    "iso:country":"CA",
    "sg:address":"5825 Rue Saint-Jacques #1800",
    "sg:city":"Montreal",
    "sg:classifiers":[
        {
            "category":"Wholesale",
            "subcategory":"Hardware",
            "type":"Manufacturing & Wholesale Goods"
        }
    ],
    "sg:phone":"+1 514 489 5361",
    "sg:postcode":"H4A 2G1",
    "sg:province":"QC",
    "sg:tags":[
        "system",
        "air",
        "equipment",
        "heating",
        "conditioning",
        "contractor"
    ],
    "wof:name":"Refac",
    "wof:placetype":"venue"
},
  "geometry": {"coordinates":[-73.6106643677,45.4664382935],"type":"Point"}
}