{
  "type": "Feature",
  "properties": {
    "addr:full":"1060 Leslie Dr Victoria BC V8X 2Y8",
    "addr:housenumber":"1060",
    "addr:postcode":"v8x 2y8",
    "addr:street":"Leslie Dr",
    "iso:country":"CA",
    "sg:address":"1060 Leslie Dr",
    "sg:city":"Victoria",
    "sg:classifiers":[
        {
            "category":"Retail",
            "subcategory":"Repair Shop",
            "type":"Services"
        }
    ],
    "sg:phone":"+1 250 383 6600",
    "sg:postcode":"V8X 2Y8",
    "sg:province":"BC",
    "sg:tags":[
        "beer",
        "related"
    ],
    "wof:name":"Royal Victoria Keg Tapper's",
    "wof:placetype":"venue"
},
  "geometry": {"coordinates":[-123.364517212,48.428314209],"type":"Point"}
}