{
  "type": "Feature",
  "properties": {
    "addr:full":"1538 Old Falconbridge Rd Sudbury ON P3A 4N8",
    "addr:housenumber":"1538",
    "addr:postcode":"p3a 4n8",
    "addr:street":"Old Falconbridge Rd",
    "iso:country":"CA",
    "sg:address":"1538 Old Falconbridge Rd",
    "sg:city":"Sudbury",
    "sg:classifiers":[
        {
            "category":"Building & Trades",
            "subcategory":"Plumbing",
            "type":"Services"
        }
    ],
    "sg:phone":"+1 705 566 0368",
    "sg:postcode":"P3A 4N8",
    "sg:province":"ON",
    "sg:tags":[
        "sheet",
        "work",
        "metal",
        "contractor"
    ],
    "wof:name":"Gauvreau Heating Ltd",
    "wof:placetype":"venue"
},
  "geometry": {"coordinates":[-80.912544,46.529083],"type":"Point"}
}