{
  "type": "Feature",
  "properties": {
    "addr:full":"60 4th Ave E Vancouver BC V5T 1E8",
    "addr:housenumber":"60",
    "addr:postcode":"v5t 1e8",
    "addr:street":"4Th Ave E",
    "iso:country":"CA",
    "sg:address":"60 4th Ave E",
    "sg:city":"Vancouver",
    "sg:classifiers":[
        {
            "category":"Manufacturing",
            "subcategory":"Apparel",
            "type":"Manufacturing & Wholesale Goods"
        }
    ],
    "sg:phone":"+1 604 687 3268",
    "sg:postcode":"V5T 1E8",
    "sg:province":"BC",
    "sg:tags":[
        "clothing"
    ],
    "wof:name":"NU-Fashion Garment Mfrs Ltd",
    "wof:placetype":"venue"
},
  "geometry": {"coordinates":[-123.103622,49.267254],"type":"Point"}
}