{
  "type": "Feature",
  "properties": {
    "addr:full":"Airport Rd Cobden ON K0J 1K0",
    "addr:postcode":"k0j 1k0",
    "addr:street":"Airport Rd",
    "iso:country":"CA",
    "sg:address":"Airport Rd",
    "sg:city":"Cobden",
    "sg:classifiers":[
        {
            "category":"Airport",
            "type":"Transportation"
        }
    ],
    "sg:phone":"+1 613 646 7922",
    "sg:postcode":"K0J 1K0",
    "sg:province":"ON",
    "wof:name":"Champlain Airport",
    "wof:placetype":"venue"
},
  "geometry": {"coordinates":[-76.879982,45.627075],"type":"Point"}
}