{
  "type": "Feature",
  "properties": {
    "addr:full":"3621 156A St Surrey BC V3S 0L4",
    "addr:housenumber":"3621",
    "addr:postcode":"v3s 0l4",
    "addr:street":"156A St",
    "iso:country":"CA",
    "sg:address":"3621 156A St",
    "sg:city":"Surrey",
    "sg:classifiers":[
        {
            "category":"Banks & Credit Unions",
            "subcategory":"Bank",
            "type":"Services"
        }
    ],
    "sg:phone":"+1 604 542 2705",
    "sg:postcode":"V3S 0L4",
    "sg:province":"BC",
    "sg:tags":[
        "financing"
    ],
    "wof:name":"Interface Financial Group",
    "wof:placetype":"venue"
},
  "geometry": {"coordinates":[-122.830215,49.105179],"type":"Point"}
}