{
  "type": "Feature",
  "properties": {
    "addr:full":"9 Haas Rd Etobicoke ON M9W 3A1",
    "addr:housenumber":"9",
    "addr:postcode":"m9w 3a1",
    "addr:street":"Haas Rd",
    "iso:country":"CA",
    "sg:address":"9 Haas Rd",
    "sg:city":"Etobicoke",
    "sg:classifiers":[
        {
            "category":"Building & Trades",
            "subcategory":"Construction",
            "type":"Services"
        }
    ],
    "sg:phone":"+1 416 743 8058",
    "sg:postcode":"M9W 3A1",
    "sg:province":"ON",
    "sg:tags":[
        "roofing",
        "contractor"
    ],
    "wof:name":"Cherry Roofing Ltd",
    "wof:placetype":"venue"
},
  "geometry": {"coordinates":[-79.57344818120001,43.7168045044],"type":"Point"}
}