{
  "type": "Feature",
  "properties": {
    "addr:full":"Mississauga ON L5M 3S8",
    "addr:postcode":"l5m 3s8",
    "iso:country":"CA",
    "sg:city":"Mississauga",
    "sg:classifiers":[
        {
            "category":"Retail",
            "subcategory":"Auto Repair",
            "type":"Services"
        }
    ],
    "sg:phone":"+1 905 826 3916",
    "sg:postcode":"L5M 3S8",
    "sg:province":"ON",
    "sg:tags":[
        "repairing",
        "automobile"
    ],
    "wof:name":"J Salema & Sons Auto Svc",
    "wof:placetype":"venue"
},
  "geometry": {"coordinates":[-79.715942,43.577919],"type":"Point"}
}