{
  "type": "Feature",
  "properties": {
    "iso:country":"CA",
    "sg:city":"Richmond",
    "sg:classifiers":[
        {
            "category":"Health Services",
            "subcategory":"Doctor",
            "type":"Services"
        }
    ],
    "sg:phone":"+1 604 821 9888",
    "sg:postcode":"V6X 3Y2",
    "sg:province":"BC",
    "sg:tags":[
        "dentist"
    ],
    "wof:name":"Yuen, John DDS",
    "wof:placetype":"venue"
},
  "geometry": {"coordinates":[-123.133034,49.170059],"type":"Point"}
}