{
  "type": "Feature",
  "properties": {
    "addr:full":"5151 Terminal Rd Halifax NS B3J 1A1",
    "addr:housenumber":"5151",
    "addr:postcode":"ns b3j 1a1",
    "addr:street":"Terminal Rd",
    "iso:country":"CA",
    "sg:address":"5151 Terminal Rd",
    "sg:city":"Halifax",
    "sg:classifiers":[
        {
            "category":"Restaurant",
            "type":"Food & Drink"
        }
    ],
    "sg:phone":"+1 902 422 5602",
    "sg:postcode":"B3J 1A1",
    "sg:province":"NS",
    "wof:name":"Costello Cafe",
    "wof:placetype":"venue"
},
  "geometry": {"coordinates":[-63.568211,44.640987],"type":"Point"}
}