{
  "type": "Feature",
  "properties": {
    "addr:full":"431 Rue Bergevin Lasalle QC H8R 3M6",
    "addr:housenumber":"431",
    "addr:postcode":"h8r 3m6",
    "addr:street":"Rue Bergevin",
    "iso:country":"CA",
    "sg:address":"431 Rue Bergevin",
    "sg:city":"Lasalle",
    "sg:classifiers":[
        {
            "category":"Personal",
            "type":"Services"
        }
    ],
    "sg:phone":"+1 514 365 5961",
    "sg:postcode":"H8R 3M6",
    "sg:province":"QC",
    "sg:tags":[
        "control",
        "weight"
    ],
    "wof:name":"Tops Club Inc",
    "wof:placetype":"venue"
},
  "geometry": {"coordinates":[-73.654533,45.433762],"type":"Point"}
}