{
  "type": "Feature",
  "properties": {
    "addr:full":"346 Boul St-Pierre O Caraquet NB E1W 1A3",
    "addr:housenumber":"346",
    "addr:postcode":"e1w 1a3",
    "addr:street":"Boul St-Pierre O",
    "iso:country":"CA",
    "sg:address":"346 Boul St-Pierre O",
    "sg:city":"Caraquet",
    "sg:classifiers":[
        {
            "category":"Building & Trades",
            "subcategory":"Plumbing",
            "type":"Services"
        }
    ],
    "sg:phone":"+1 506 727 7169",
    "sg:postcode":"E1W 1A3",
    "sg:province":"NB",
    "sg:tags":[
        "conditioning",
        "air",
        "system",
        "contractor"
    ],
    "wof:name":"Refrigeration Plus Inc",
    "wof:placetype":"venue"
},
  "geometry": {"coordinates":[-64.99816131590001,47.7735824585],"type":"Point"}
}