{
  "type": "Feature",
  "properties": {
    "addr:full":"1440 Rue Des Pionniers Saint-Nicolas QC G7A 4L6",
    "addr:housenumber":"1440",
    "addr:postcode":"g7a 4l6",
    "addr:street":"Rue Des Pionniers",
    "iso:country":"CA",
    "sg:address":"1440 Rue Des Pionniers",
    "sg:city":"Saint-Nicolas",
    "sg:classifiers":[
        {
            "category":"Organizations",
            "subcategory":"Religious Organization",
            "type":"Services"
        }
    ],
    "sg:phone":"+1 418 831 1859",
    "sg:postcode":"G7A 4L6",
    "sg:province":"QC",
    "sg:tags":[
        "house",
        "retreat"
    ],
    "wof:name":"Residences Des Pionniers",
    "wof:placetype":"venue"
},
  "geometry": {"coordinates":[-71.400352,46.702385],"type":"Point"}
}