{
  "type": "Feature",
  "properties": {
    "iso:country":"CA",
    "sg:city":"Mississauga",
    "sg:classifiers":[
        {
            "category":"Banks & Credit Unions",
            "subcategory":"Investment Brokerage",
            "type":"Services"
        }
    ],
    "sg:phone":"+1 905 542 3441",
    "sg:postcode":"L5N 1P7",
    "sg:province":"ON",
    "sg:tags":[
        "consultant",
        "planning",
        "financial"
    ],
    "wof:name":"DE Thomas Financial Corp",
    "wof:placetype":"venue"
},
  "geometry": {"coordinates":[-79.740486,43.600536],"type":"Point"}
}