{
  "type": "Feature",
  "properties": {
    "addr:full":"900 Boul Decarie Saint-Laurent QC H4L 3L9",
    "addr:housenumber":"900",
    "addr:postcode":"h4l 3l9",
    "addr:street":"Boul Decarie",
    "iso:country":"CA",
    "sg:address":"900 Boul Decarie",
    "sg:city":"Saint-Laurent",
    "sg:classifiers":[
        {
            "category":"Shopping",
            "subcategory":"Clothing, Apparel, & Fashions",
            "type":"Retail Goods"
        }
    ],
    "sg:phone":"+1 514 744 0985",
    "sg:postcode":"H4L 3L9",
    "sg:province":"QC",
    "sg:tags":[
        "furnishing"
    ],
    "wof:name":"Jaf Pret A Porter Inc",
    "wof:placetype":"venue"
},
  "geometry": {"coordinates":[-73.68047300000001,45.512676],"type":"Point"}
}