{
  "type": "Feature",
  "properties": {
    "iso:country":"CA",
    "sg:address":"77 Ferry Ave",
    "sg:city":"Fredericton",
    "sg:classifiers":[
        {
            "category":"Retail",
            "subcategory":"Laundry & Dry Cleaning",
            "type":"Services"
        }
    ],
    "sg:phone":"+1 506 451 7739",
    "sg:postcode":"E3A 1R7",
    "sg:province":"NB",
    "sg:tags":[
        "cleaners"
    ],
    "wof:name":"Dry Cleaner",
    "wof:placetype":"venue"
},
  "geometry": {"coordinates":[-66.6580963135,45.9791564941],"type":"Point"}
}