{
  "type": "Feature",
  "properties": {
    "iso:country":"CA",
    "sg:city":"Queen Charlotte",
    "sg:classifiers":[
        {
            "category":"Home & Garden",
            "subcategory":"Garden Supply",
            "type":"Retail Goods"
        }
    ],
    "sg:phone":"+1 250 559 4515",
    "sg:postcode":"V0T 1S0",
    "sg:province":"BC",
    "sg:tags":[
        "lawn",
        "mower"
    ],
    "wof:name":"Cowpar Equipment",
    "wof:placetype":"venue"
},
  "geometry": {"coordinates":[-132.08216857900001,53.2547454834],"type":"Point"}
}