{
  "type": "Feature",
  "properties": {
    "addr:full":"1140 Davenport Rd Toronto ON M6G 2C6",
    "addr:housenumber":"1140",
    "addr:postcode":"m6g 2c6",
    "addr:street":"Davenport Rd",
    "iso:country":"CA",
    "sg:address":"1140 Davenport Rd",
    "sg:city":"Toronto",
    "sg:classifiers":[
        {
            "category":"Shopping",
            "subcategory":"Pharmacy",
            "type":"Retail Goods"
        }
    ],
    "sg:phone":"+1 416 656 3351",
    "sg:postcode":"M6G 2C6",
    "sg:province":"ON",
    "wof:name":"Willer's Pharmacy",
    "wof:placetype":"venue"
},
  "geometry": {"coordinates":[-79.4310684204,43.6747550964],"type":"Point"}
}