{
  "type": "Feature",
  "properties": {
    "addr:full":"Blanc-Sablon QC G0G 1C0",
    "addr:postcode":"g0g 1c0",
    "iso:country":"CA",
    "sg:city":"Blanc-Sablon",
    "sg:classifiers":[
        {
            "category":"Government",
            "subcategory":"Office",
            "type":"Public Place"
        }
    ],
    "sg:phone":"+1 418 461 2707",
    "sg:postcode":"G0G 1C0",
    "sg:province":"QC",
    "sg:tags":[
        "village"
    ],
    "wof:name":"Municipalite DE Blanc-Sablon",
    "wof:placetype":"venue"
},
  "geometry": {"coordinates":[-57.135208,51.428616],"type":"Point"}
}