{
  "type": "Feature",
  "properties": {
    "iso:country":"CA",
    "sg:address":"5330 89 St NW",
    "sg:city":"Edmonton",
    "sg:classifiers":[
        {
            "category":"Recreation",
            "type":"Entertainment"
        }
    ],
    "sg:phone":"+1 780 413 4500",
    "sg:postcode":"T6E 5P9",
    "sg:province":"AB",
    "sg:tags":[
        "martial",
        "arts",
        "instruction"
    ],
    "wof:name":"Wilson Karate School",
    "wof:placetype":"venue"
},
  "geometry": {"coordinates":[-113.464226,53.490021],"type":"Point"}
}