{
  "type": "Feature",
  "properties": {
    "addr:full":"Gormley ON L0H 1G0",
    "addr:postcode":"l0h 1g0",
    "iso:country":"CA",
    "sg:city":"Gormley",
    "sg:classifiers":[
        {
            "category":"Manufacturing",
            "subcategory":"Tools & Machinery",
            "type":"Manufacturing & Wholesale Goods"
        }
    ],
    "sg:phone":"+1 905 888 9398",
    "sg:postcode":"L0H 1G0",
    "sg:province":"ON",
    "sg:tags":[
        "die",
        "maker"
    ],
    "wof:name":"Twin Tooling Inc",
    "wof:placetype":"venue"
},
  "geometry": {"coordinates":[-79.3830337524,43.9546928406],"type":"Point"}
}