{
  "type": "Feature",
  "properties": {
    "iso:country":"CA",
    "sg:city":"Brampton",
    "sg:classifiers":[
        {
            "category":"Food & Beverages",
            "subcategory":"Groceries & Convenience Stores",
            "type":"Retail Goods"
        }
    ],
    "sg:phone":"+1 905 452 7949",
    "sg:postcode":"L6W 3R1",
    "sg:province":"ON",
    "sg:tags":[
        "product"
    ],
    "wof:name":"Bulk Barn",
    "wof:placetype":"venue"
},
  "geometry": {"coordinates":[-79.741882,43.702206],"type":"Point"}
}