{
  "type": "Feature",
  "properties": {
    "addr:full":"20 College St Toronto ON M5G 1K2",
    "addr:housenumber":"20",
    "addr:postcode":"m5g 1k2",
    "addr:street":"College St",
    "iso:country":"CA",
    "sg:address":"20 College St",
    "sg:city":"Toronto",
    "sg:classifiers":[
        {
            "category":"Restaurant",
            "type":"Food & Drink"
        }
    ],
    "sg:phone":"+1 416 923 9867",
    "sg:postcode":"M5G 1K2",
    "sg:province":"ON",
    "wof:name":"Fran Restaurants Ltd",
    "wof:placetype":"venue"
},
  "geometry": {"coordinates":[-79.38426971440001,43.6612472534],"type":"Point"}
}