{
  "type": "Feature",
  "properties": {
    "iso:country":"CA",
    "sg:city":"North York",
    "sg:classifiers":[
        {
            "category":"Social Services",
            "type":"Services"
        }
    ],
    "sg:phone":"+1 416 222 6335",
    "sg:postcode":"M2N 6K8",
    "sg:province":"ON",
    "sg:tags":[
        "organization",
        "welfare"
    ],
    "wof:name":"Hope Air",
    "wof:placetype":"venue"
},
  "geometry": {"coordinates":[-79.41021,43.759468],"type":"Point"}
}