{
  "type": "Feature",
  "properties": {
    "addr:full":"243 High St Southampton ON N0H 2L0",
    "addr:housenumber":"243",
    "addr:postcode":"n0h 2l0",
    "addr:street":"High St",
    "iso:country":"CA",
    "sg:address":"243 High St",
    "sg:city":"Southampton",
    "sg:classifiers":[
        {
            "category":"Professional",
            "subcategory":"Lawyer & Legal Services",
            "type":"Services"
        }
    ],
    "sg:phone":"+1 519 797 3223",
    "sg:postcode":"N0H 2L0",
    "sg:province":"ON",
    "sg:tags":[
        "attorney"
    ],
    "wof:name":"Forsyth, Robert E QC",
    "wof:placetype":"venue"
},
  "geometry": {"coordinates":[-81.36998,44.494839],"type":"Point"}
}