{
  "type": "Feature",
  "properties": {
    "addr:full":"49 Rue Dalhousie Quebec QC G1K 4B6",
    "addr:housenumber":"49",
    "addr:postcode":"g1k 4b6",
    "addr:street":"Rue Dalhousie",
    "iso:country":"CA",
    "sg:address":"49 Rue Dalhousie",
    "sg:city":"Quebec",
    "sg:classifiers":[
        {
            "category":"Shopping",
            "subcategory":"Gifts & Souvenirs",
            "type":"Retail Goods"
        }
    ],
    "sg:phone":"+1 418 692 1142",
    "sg:postcode":"G1K 4B6",
    "sg:province":"QC",
    "sg:tags":[
        "shop"
    ],
    "wof:name":"Souvenirs DE LA Nouvelle",
    "wof:placetype":"venue"
},
  "geometry": {"coordinates":[-71.2016372681,46.8141822815],"type":"Point"}
}