{
  "type": "Feature",
  "properties": {
    "addr:full":"147 Colvin Cres Thornhill ON L4J 2N7",
    "addr:housenumber":"147",
    "addr:postcode":"l4j 2n7",
    "addr:street":"Colvin Cres",
    "iso:country":"CA",
    "sg:address":"147 Colvin Cres",
    "sg:city":"Thornhill",
    "sg:classifiers":[
        {
            "category":"Manufacturing",
            "subcategory":"Building Materials",
            "type":"Manufacturing & Wholesale Goods"
        }
    ],
    "sg:phone":"+1 905 762 0305",
    "sg:postcode":"L4J 2N7",
    "sg:province":"ON",
    "wof:name":"Pinnacle Millwork Inc",
    "wof:placetype":"venue"
},
  "geometry": {"coordinates":[-79.45565795900001,43.7978439331],"type":"Point"}
}