{
  "type": "Feature",
  "properties": {
    "addr:full":"222 Main St Picton ON K0K 2T0",
    "addr:housenumber":"222",
    "addr:postcode":"k0k 2t0",
    "addr:street":"Main St",
    "iso:country":"CA",
    "sg:address":"222 Main St",
    "sg:city":"Picton",
    "sg:classifiers":[
        {
            "category":"Restaurant",
            "type":"Food & Drink"
        }
    ],
    "sg:phone":"+1 613 476 9833",
    "sg:postcode":"K0K 2T0",
    "sg:province":"ON",
    "wof:name":"Regent Cafe",
    "wof:placetype":"venue"
},
  "geometry": {"coordinates":[-77.1412887573,44.007434845],"type":"Point"}
}