{
  "type": "Feature",
  "properties": {
    "addr:full":"190 Wallace Ave Toronto ON M6H 1V4",
    "addr:housenumber":"190",
    "addr:postcode":"m6h 1v4",
    "addr:street":"Wallace Ave",
    "iso:country":"CA",
    "sg:address":"190 Wallace Ave",
    "sg:city":"Toronto",
    "sg:classifiers":[
        {
            "category":"Professional",
            "subcategory":"Lawyer & Legal Services",
            "type":"Services"
        }
    ],
    "sg:phone":"+1 416 533 7702",
    "sg:postcode":"M6H 1V4",
    "sg:province":"ON",
    "sg:tags":[
        "naturalization",
        "immigration"
    ],
    "wof:name":"Ad All Counselling Svc",
    "wof:placetype":"venue"
},
  "geometry": {"coordinates":[-79.44422149659999,43.6625289917],"type":"Point"}
}