{
  "type": "Feature",
  "properties": {
    "addr:full":"4440 Craig Dr Prince George BC V2K 3P5",
    "addr:housenumber":"4440",
    "addr:postcode":"v2k 3p5",
    "addr:street":"Craig Dr",
    "iso:country":"CA",
    "sg:address":"4440 Craig Dr",
    "sg:city":"Prince George",
    "sg:classifiers":[
        {
            "category":"Education",
            "subcategory":"School",
            "type":"Public Place"
        }
    ],
    "sg:phone":"+1 250 562 5381",
    "sg:postcode":"V2K 3P5",
    "sg:province":"BC",
    "wof:name":"Edgewood Elementary School",
    "wof:placetype":"venue"
},
  "geometry": {"coordinates":[-122.800552,53.945801],"type":"Point"}
}