{
  "type": "Feature",
  "properties": {
    "addr:full":"1124 Great Northern Rd RR 2 Sault Ste Marie ON P6A 5K7",
    "addr:housenumber":"1124",
    "addr:postcode":"p6a 5k7",
    "addr:street":"Great Northern Rd;2",
    "iso:country":"CA",
    "sg:address":"1124 Great Northern Rd RR 2",
    "sg:city":"Sault Ste Marie",
    "sg:classifiers":[
        {
            "category":"Education",
            "subcategory":"Special Training",
            "type":"Public Place"
        }
    ],
    "sg:phone":"+1 705 759 4545",
    "sg:postcode":"P6A 5K7",
    "sg:province":"ON",
    "sg:tags":[
        "instruction",
        "driving"
    ],
    "wof:name":"Young Drivers of Canada",
    "wof:placetype":"venue"
},
  "geometry": {"coordinates":[-84.320122,46.561134],"type":"Point"}
}