{
  "type": "Feature",
  "properties": {
    "addr:full":"11321 82 Ave Delta BC V4C 2B8",
    "addr:housenumber":"11321",
    "addr:postcode":"v4c 2b8",
    "addr:street":"82 Ave",
    "iso:country":"CA",
    "sg:address":"11321 82 Ave",
    "sg:city":"Delta",
    "sg:classifiers":[
        {
            "category":"Building & Trades",
            "subcategory":"Landscaping Services",
            "type":"Services"
        }
    ],
    "sg:phone":"+1 604 596 1655",
    "sg:postcode":"V4C 2B8",
    "sg:province":"BC",
    "sg:tags":[
        "landscape",
        "contractor"
    ],
    "wof:name":"John's Landscaping & Mntnc",
    "wof:placetype":"venue"
},
  "geometry": {"coordinates":[-122.909195,49.152428],"type":"Point"}
}