{
  "type": "Feature",
  "properties": {
    "addr:full":"551 Boul Ferdinand Dieppe NB E1A 7G1",
    "addr:housenumber":"551",
    "addr:postcode":"e1a 7g1",
    "addr:street":"Boul Ferdinand Dieppe Nb",
    "iso:country":"CA",
    "sg:address":"551 Boul Ferdinand",
    "sg:city":"Dieppe",
    "sg:classifiers":[
        {
            "category":"Wholesale",
            "subcategory":"Machinery & Supplies",
            "type":"Manufacturing & Wholesale Goods"
        }
    ],
    "sg:phone":"+1 506 852 4310",
    "sg:postcode":"E1A 7G1",
    "sg:province":"NB",
    "sg:tags":[
        "equipment",
        "sawmill"
    ],
    "wof:name":"Cardinal Sawmill Equipment",
    "wof:placetype":"venue"
},
  "geometry": {"coordinates":[-64.70079800000001,46.111118],"type":"Point"}
}