{
  "type": "Feature",
  "properties": {
    "addr:full":"181 First Ave N Williams Lake BC V2G 1Y7",
    "addr:housenumber":"181",
    "addr:postcode":"v2g 1y7",
    "addr:street":"First Ave N",
    "iso:country":"CA",
    "sg:address":"181 First Ave N",
    "sg:city":"Williams Lake",
    "sg:classifiers":[
        {
            "category":"Government",
            "subcategory":"Office",
            "type":"Public Place"
        }
    ],
    "sg:phone":"+1 250 398 4414",
    "sg:postcode":"V2G 1Y7",
    "sg:province":"BC",
    "wof:name":"BC Parks",
    "wof:placetype":"venue"
},
  "geometry": {"coordinates":[-122.14613342299999,52.1308021545],"type":"Point"}
}