{
  "type": "Feature",
  "properties": {
    "addr:full":"Saint-Leonard QC H1R 2T6",
    "addr:postcode":"h1r 2t6",
    "iso:country":"CA",
    "sg:city":"Saint-Leonard",
    "sg:classifiers":[
        {
            "category":"Health Services",
            "subcategory":"Health Practitioner",
            "type":"Services"
        }
    ],
    "sg:phone":"+1 514 955 1020",
    "sg:postcode":"H1R 2T6",
    "sg:province":"QC",
    "sg:tags":[
        "physiotherapist"
    ],
    "wof:name":"Clinique-Physiotherapie Viau",
    "wof:placetype":"venue"
},
  "geometry": {"coordinates":[-73.6026916504,45.5815467834],"type":"Point"}
}