{
  "type": "Feature",
  "properties": {
    "addr:full":"4205 Highway 2A Ponoka AB T4J 1J8",
    "addr:housenumber":"4205",
    "addr:postcode":"t4j 1j8",
    "addr:street":"Highway 2A",
    "iso:country":"CA",
    "sg:address":"4205 Highway 2A",
    "sg:city":"Ponoka",
    "sg:classifiers":[
        {
            "category":"Mining & Drilling",
            "type":"Manufacturing & Wholesale Goods"
        }
    ],
    "sg:phone":"+1 403 783 4929",
    "sg:postcode":"T4J 1J8",
    "sg:province":"AB",
    "sg:tags":[
        "company",
        "oil"
    ],
    "wof:name":"Encana Corp",
    "wof:placetype":"venue"
},
  "geometry": {"coordinates":[-113.5909729,52.6760749817],"type":"Point"}
}