{
  "type": "Feature",
  "properties": {
    "iso:country":"CA",
    "sg:address":"9204 144 Ave NW #911",
    "sg:city":"Edmonton",
    "sg:classifiers":[
        {
            "category":"Restaurant",
            "type":"Food & Drink"
        }
    ],
    "sg:phone":"+1 780 473 2716",
    "sg:postcode":"T5E 6A3",
    "sg:province":"AB",
    "wof:name":"Capital Pizza & Steakhouse Ltd",
    "wof:placetype":"venue"
},
  "geometry": {"coordinates":[-113.48267364500001,53.6061210632],"type":"Point"}
}