{
  "type": "Feature",
  "properties": {
    "iso:country":"CA",
    "sg:address":"142 Main St W",
    "sg:city":"Dowling",
    "sg:classifiers":[
        {
            "category":"Shopping",
            "subcategory":"Catalog Store",
            "type":"Retail Goods"
        }
    ],
    "sg:phone":"+1 705 855 2267",
    "sg:postcode":"P0M 1R0",
    "sg:province":"ON",
    "sg:tags":[
        "mail",
        "order",
        "internet"
    ],
    "wof:name":"Sears Canada Inc",
    "wof:placetype":"venue"
},
  "geometry": {"coordinates":[-81.34618377690001,46.586025238],"type":"Point"}
}