{
  "type": "Feature",
  "properties": {
    "iso:country":"CA",
    "sg:city":"Etobicoke",
    "sg:classifiers":[
        {
            "category":"Personal",
            "subcategory":"Beauty Salon",
            "type":"Services"
        }
    ],
    "sg:phone":"+1 416 231 5854",
    "sg:postcode":"M9C 1E7",
    "sg:province":"ON",
    "wof:name":"Tony & Wendy's Hair Alive",
    "wof:placetype":"venue"
},
  "geometry": {"coordinates":[-79.56568908689999,43.6421012878],"type":"Point"}
}