{
  "type": "Feature",
  "properties": {
    "addr:full":"48 Smith Ave E Arnaud MB R0A 0B0",
    "addr:housenumber":"48",
    "addr:postcode":"r0a 0b0",
    "addr:street":"Smith Ave E Arnaud",
    "iso:country":"CA",
    "sg:address":"48 Smith Ave E",
    "sg:city":"Arnaud",
    "sg:phone":"+1 204 427 3144",
    "sg:postcode":"R0A 0B0",
    "sg:province":"MB",
    "sg:tags":[
        "oil"
    ],
    "wof:name":"Al Mc Vicar Farm Svc Ltd",
    "wof:placetype":"venue"
},
  "geometry": {"coordinates":[-97.118057251,49.2514648438],"type":"Point"}
}