{
  "type": "Feature",
  "properties": {
    "addr:full":"965 Bay St Toronto ON M5S 2A3",
    "addr:housenumber":"965",
    "addr:postcode":"m5s 2a3",
    "addr:street":"Bay St",
    "iso:country":"CA",
    "sg:address":"965 Bay St",
    "sg:city":"Toronto",
    "sg:classifiers":[
        {
            "category":"Banks & Credit Unions",
            "subcategory":"Investment Brokerage",
            "type":"Services"
        }
    ],
    "sg:phone":"+1 416 920 5114",
    "sg:postcode":"M5S 2A3",
    "sg:province":"ON",
    "sg:tags":[
        "consultant",
        "financing"
    ],
    "wof:name":"Lever Enterprises",
    "wof:placetype":"venue"
},
  "geometry": {"coordinates":[-79.38709299999999,43.664654],"type":"Point"}
}