{
  "type": "Feature",
  "properties": {
    "addr:full":"1633 Rue Saint-Denis Montreal QC H2X 3K3",
    "addr:housenumber":"1633",
    "addr:postcode":"h2x 3k3",
    "addr:street":"Rue Saint-Denis",
    "iso:country":"CA",
    "sg:address":"1633 Rue Saint-Denis",
    "sg:city":"Montreal",
    "sg:classifiers":[
        {
            "category":"Restaurant",
            "type":"Food & Drink"
        }
    ],
    "sg:phone":"+1 514 499 9213",
    "sg:postcode":"H2X 3K3",
    "sg:province":"QC",
    "wof:name":"Pita Pit",
    "wof:placetype":"venue"
},
  "geometry": {"coordinates":[-73.5629119873,45.5150260925],"type":"Point"}
}