{
  "type": "Feature",
  "properties": {
    "addr:full":"140 9th St SE Portage LA Prairie MB R1N 3V5",
    "addr:housenumber":"140",
    "addr:postcode":"r1n 3v5",
    "addr:street":"9Th St Se",
    "iso:country":"CA",
    "sg:address":"140 9th St SE",
    "sg:city":"Portage LA Prairie",
    "sg:classifiers":[
        {
            "category":"Health Services",
            "subcategory":"Doctor",
            "type":"Services"
        }
    ],
    "sg:phone":"+1 204 857 3445",
    "sg:postcode":"R1N 3V5",
    "sg:province":"MB",
    "sg:tags":[
        "physician",
        "surgeon"
    ],
    "wof:name":"Price, J B MD",
    "wof:placetype":"venue"
},
  "geometry": {"coordinates":[-98.27880096440001,49.969871521],"type":"Point"}
}