{
  "type": "Feature",
  "properties": {
    "addr:full":"11700 Boul Saint-Jean-Baptiste Montreal QC H1C 2J3",
    "addr:housenumber":"11700",
    "addr:postcode":"h1c 2j3",
    "addr:street":"Boul Saint-Jean-Baptiste",
    "iso:country":"CA",
    "sg:address":"11700 Boul Saint-Jean-Baptiste",
    "sg:city":"Montreal",
    "sg:classifiers":[
        {
            "category":"Building & Trades",
            "subcategory":"Construction",
            "type":"Services"
        }
    ],
    "sg:phone":"+1 514 494 0932",
    "sg:postcode":"H1C 2J3",
    "sg:province":"QC",
    "sg:tags":[
        "tank"
    ],
    "wof:name":"Girard Citernes & Coulombe",
    "wof:placetype":"venue"
},
  "geometry": {"coordinates":[-73.538811,45.655605],"type":"Point"}
}