{
  "type": "Feature",
  "properties": {
    "addr:full":"Trois-Rivieres QC G8Z 2C9",
    "addr:postcode":"g8z 2c9",
    "iso:country":"CA",
    "sg:city":"Trois-Rivieres",
    "sg:classifiers":[
        {
            "category":"Restaurant",
            "type":"Food & Drink"
        }
    ],
    "sg:phone":"+1 819 375 8888",
    "sg:postcode":"G8Z 2C9",
    "sg:province":"QC",
    "wof:name":"Palais DE Chine",
    "wof:placetype":"venue"
},
  "geometry": {"coordinates":[-72.5595169067,46.3413314819],"type":"Point"}
}