{
  "type": "Feature",
  "properties": {
    "addr:full":"500 Dupont St Toronto ON M6G 1Y7",
    "addr:housenumber":"500",
    "addr:postcode":"m6g 1y7",
    "addr:street":"Dupont St",
    "iso:country":"CA",
    "sg:address":"500 Dupont St",
    "sg:city":"Toronto",
    "sg:classifiers":[
        {
            "category":"Food & Beverages",
            "subcategory":"Liquor & Beverages",
            "type":"Retail Goods"
        }
    ],
    "sg:phone":"+1 416 537 4882",
    "sg:postcode":"M6G 1Y7",
    "sg:province":"ON",
    "sg:tags":[
        "beer",
        "ale"
    ],
    "wof:name":"Beer Store",
    "wof:placetype":"venue"
},
  "geometry": {"coordinates":[-79.415482,43.673065],"type":"Point"}
}