{
  "type": "Feature",
  "properties": {
    "addr:full":"178 Highway 8 Stoney Creek ON L8G 1C3",
    "addr:housenumber":"178",
    "addr:postcode":"l8g 1c3",
    "addr:street":"Highway 8",
    "iso:country":"CA",
    "sg:address":"178 Highway 8",
    "sg:city":"Stoney Creek",
    "sg:classifiers":[
        {
            "category":"Personal",
            "subcategory":"Beauty Salon",
            "type":"Services"
        }
    ],
    "sg:phone":"+1 905 662 1846",
    "sg:postcode":"L8G 1C3",
    "sg:province":"ON",
    "sg:tags":[
        "barber"
    ],
    "wof:name":"Pines Barbers & Hair Stylists",
    "wof:placetype":"venue"
},
  "geometry": {"coordinates":[-79.6898803711,43.2120666504],"type":"Point"}
}