{
  "type": "Feature",
  "properties": {
    "addr:full":"37 Michael Ave Hanwell NB E3C 2A5",
    "addr:housenumber":"37",
    "addr:postcode":"e3c 2a5",
    "addr:street":"Michael Ave",
    "iso:country":"CA",
    "sg:address":"37 Michael Ave",
    "sg:city":"Hanwell",
    "sg:classifiers":[
        {
            "category":"Social Services",
            "subcategory":"Child Care",
            "type":"Services"
        }
    ],
    "sg:phone":"+1 506 455 2231",
    "sg:postcode":"E3C 2A5",
    "sg:province":"NB",
    "wof:name":"Jilly Beans Childcare",
    "wof:placetype":"venue"
},
  "geometry": {"coordinates":[-66.795441,45.868484],"type":"Point"}
}