{
  "type": "Feature",
  "properties": {
    "addr:full":"6340 Ch Archambault Lourdes-DE-Joliette QC J0K 1K0",
    "addr:postcode":"6340;j0k 1k0",
    "addr:street":"Ch Archambault Lourdes-De-Joliette",
    "iso:country":"CA",
    "sg:address":"6340 Ch Archambault",
    "sg:city":"Lourdes-DE-Joliette",
    "sg:classifiers":[
        {
            "category":"Retail",
            "subcategory":"Repair Shop",
            "type":"Services"
        }
    ],
    "sg:phone":"+1 450 753 1127",
    "sg:postcode":"J0K 1K0",
    "sg:province":"QC",
    "sg:tags":[
        "upholsterer"
    ],
    "wof:name":"Rembourrage Plus",
    "wof:placetype":"venue"
},
  "geometry": {"coordinates":[-73.441956,46.023571],"type":"Point"}
}