{
  "type": "Feature",
  "properties": {
    "addr:full":"North Bay ON P1B 2Y8",
    "addr:postcode":"p1b 2y8",
    "iso:country":"CA",
    "sg:city":"North Bay",
    "sg:classifiers":[
        {
            "category":"Professional",
            "subcategory":"Employment Agencies",
            "type":"Services"
        }
    ],
    "sg:phone":"+1 705 472 7382",
    "sg:postcode":"P1B 2Y8",
    "sg:province":"ON",
    "sg:tags":[
        "training",
        "opportunity"
    ],
    "wof:name":"Wallace & Assoc Inc",
    "wof:placetype":"venue"
},
  "geometry": {"coordinates":[-79.4646072388,46.3130950928],"type":"Point"}
}