{
  "type": "Feature",
  "properties": {
    "addr:full":"111 Garafraxa St S Durham ON N0G 1R0",
    "addr:housenumber":"111",
    "addr:postcode":"n0g 1r0",
    "addr:street":"Garafraxa St S",
    "iso:country":"CA",
    "sg:address":"111 Garafraxa St S",
    "sg:city":"Durham",
    "sg:classifiers":[
        {
            "category":"Shopping",
            "subcategory":"Gifts & Souvenirs",
            "type":"Retail Goods"
        }
    ],
    "sg:phone":"+1 519 369 5943",
    "sg:postcode":"N0G 1R0",
    "sg:province":"ON",
    "sg:tags":[
        "shop"
    ],
    "wof:name":"Smart Buys",
    "wof:placetype":"venue"
},
  "geometry": {"coordinates":[-80.81819900000001,44.175991],"type":"Point"}
}