{
  "type": "Feature",
  "properties": {
    "addr:full":"1515 Richmond Ave E Brandon MB R7A 7A3",
    "addr:housenumber":"1515",
    "addr:postcode":"r7a 7a3",
    "addr:street":"Richmond Ave E",
    "iso:country":"CA",
    "sg:address":"1515 Richmond Ave E",
    "sg:city":"Brandon",
    "sg:classifiers":[
        {
            "category":"Freight",
            "type":"Transportation"
        }
    ],
    "sg:phone":"+1 204 728 5785",
    "sg:postcode":"R7A 7A3",
    "sg:province":"MB",
    "sg:tags":[
        "trucking"
    ],
    "wof:name":"Paul's Hauling Ltd",
    "wof:placetype":"venue"
},
  "geometry": {"coordinates":[-99.91826629640001,49.8274993896],"type":"Point"}
}