{
  "type": "Feature",
  "properties": {
    "iso:country":"CA",
    "sg:address":"5114 51 Ave",
    "sg:city":"Bonnyville",
    "sg:classifiers":[
        {
            "category":"Banks & Credit Unions",
            "subcategory":"Investment Brokerage",
            "type":"Services"
        }
    ],
    "sg:phone":"+1 780 826 7882",
    "sg:postcode":"T9N 2H4",
    "sg:province":"AB",
    "sg:tags":[
        "consultant",
        "planning",
        "financial"
    ],
    "wof:name":"Investors Group",
    "wof:placetype":"venue"
},
  "geometry": {"coordinates":[-110.74392700200001,54.2687416077],"type":"Point"}
}