{
  "type": "Feature",
  "properties": {
    "addr:full":"Winnipeg MB R3C 0C9",
    "addr:postcode":"r3c 0c9",
    "iso:country":"CA",
    "sg:city":"Winnipeg",
    "sg:classifiers":[
        {
            "category":"Shopping",
            "subcategory":"Clothing, Apparel, & Fashions",
            "type":"Retail Goods"
        }
    ],
    "sg:phone":"+1 204 942 3602",
    "sg:postcode":"R3C 0C9",
    "sg:province":"MB",
    "sg:tags":[
        "shop",
        "bridal"
    ],
    "wof:name":"Helene's Bridal Salon",
    "wof:placetype":"venue"
},
  "geometry": {"coordinates":[-97.14864349370001,49.8915367126],"type":"Point"}
}