{
  "type": "Feature",
  "properties": {
    "addr:full":"121 Wyndham Street North Unit 202 Guelph N1H 4E9",
    "addr:housenumber":"121;202",
    "addr:postcode":"n1h 4e9",
    "addr:street":"Wyndham Street North Unit",
    "iso:country":"CA",
    "sg:address":"121 Wyndham Street North Unit 202",
    "sg:city":"Guelph",
    "sg:classifiers":[
        {
            "category":"Professional",
            "subcategory":"Advertising",
            "type":"Services"
        }
    ],
    "sg:postcode":"N1H 4E9",
    "sg:tags":[
        "advertising",
        "banner",
        "video",
        "email",
        "pop",
        "interactive",
        "agency"
    ],
    "sg:website":"http://www.bootcampmedia.com",
    "wof:name":"Bootcamp Media",
    "wof:placetype":"venue"
},
  "geometry": {"coordinates":[-80.2499858,43.5468152],"type":"Point"}
}