{
  "type": "Feature",
  "properties": {
    "addr:full":"5252 Rue Ferrier Montreal QC H4P 1L3",
    "addr:housenumber":"5252",
    "addr:postcode":"h4p 1l3",
    "addr:street":"Rue Ferrier",
    "iso:country":"CA",
    "sg:address":"5252 Rue Ferrier",
    "sg:city":"Montreal",
    "sg:classifiers":[
        {
            "category":"Restaurant",
            "type":"Food & Drink"
        }
    ],
    "sg:phone":"+1 514 344 8686",
    "sg:postcode":"H4P 1L3",
    "sg:province":"QC",
    "wof:name":"Cafe Paninoteca",
    "wof:placetype":"venue"
},
  "geometry": {"coordinates":[-73.656792,45.498096],"type":"Point"}
}