{
  "type": "Feature",
  "properties": {
    "iso:country":"CA",
    "sg:address":"9189 National Pl",
    "sg:city":"Prince George",
    "sg:classifiers":[
        {
            "category":"Building & Trades",
            "subcategory":"Equipment Rental",
            "type":"Services"
        }
    ],
    "sg:phone":"+1 250 562 0600",
    "sg:postcode":"V2N 5T1",
    "sg:province":"BC",
    "sg:tags":[
        "scaffolding"
    ],
    "wof:name":"Chinook Scaffold Systems Ltd",
    "wof:placetype":"venue"
},
  "geometry": {"coordinates":[-122.735679627,53.8390960693],"type":"Point"}
}