{
  "type": "Feature",
  "properties": {
    "addr:full":"236 Centre St Assiniboia SK S0H 0B0",
    "addr:housenumber":"236",
    "addr:postcode":"s0h 0b0",
    "addr:street":"Centre St",
    "iso:country":"CA",
    "sg:address":"236 Centre St",
    "sg:city":"Assiniboia",
    "sg:classifiers":[
        {
            "category":"Shopping",
            "subcategory":"Bicycles & Sporting Goods",
            "type":"Retail Goods"
        }
    ],
    "sg:phone":"+1 306 642 3065",
    "sg:postcode":"S0H 0B0",
    "sg:province":"SK",
    "wof:name":"James Fong Sporting Goods",
    "wof:placetype":"venue"
},
  "geometry": {"coordinates":[-105.992355347,49.6324081421],"type":"Point"}
}