{
  "type": "Feature",
  "properties": {
    "iso:country":"CA",
    "sg:city":"London",
    "sg:classifiers":[
        {
            "category":"Professional",
            "subcategory":"Management & Consulting",
            "type":"Services"
        }
    ],
    "sg:phone":"+1 519 673 3100",
    "sg:postcode":"N6H 4S4",
    "sg:province":"ON",
    "sg:tags":[
        "consultant",
        "business"
    ],
    "wof:name":"Zarex Business Ctr",
    "wof:placetype":"venue"
},
  "geometry": {"coordinates":[-81.276299,42.988758],"type":"Point"}
}