{
  "type": "Feature",
  "properties": {
    "addr:full":"Surrey BC V3W 3V6",
    "addr:postcode":"v3w 3v6",
    "iso:country":"CA",
    "sg:city":"Surrey",
    "sg:classifiers":[
        {
            "category":"Building & Trades",
            "subcategory":"Construction",
            "type":"Services"
        }
    ],
    "sg:phone":"+1 604 596 2366",
    "sg:postcode":"V3W 3V6",
    "sg:province":"BC",
    "sg:tags":[
        "dry wall",
        "contractor"
    ],
    "wof:name":"Phoenix Lath & Plaster Ltd",
    "wof:placetype":"venue"
},
  "geometry": {"coordinates":[-122.882041931,49.1583328247],"type":"Point"}
}