{
  "type": "Feature",
  "properties": {
    "addr:full":"10 Rue Lois Hull QC J8Y 3R1",
    "addr:housenumber":"10",
    "addr:postcode":"j8y 3r1",
    "addr:street":"Rue Lois",
    "iso:country":"CA",
    "sg:address":"10 Rue Lois",
    "sg:city":"Hull",
    "sg:classifiers":[
        {
            "category":"Autos & Motor Vehicles",
            "subcategory":"Auto Supplies",
            "type":"Retail Goods"
        }
    ],
    "sg:phone":"+1 819 770 2340",
    "sg:postcode":"J8Y 3R1",
    "sg:province":"QC",
    "sg:tags":[
        "alternator",
        "automobile",
        "electric"
    ],
    "wof:name":"Auto Electrique Pl",
    "wof:placetype":"venue"
},
  "geometry": {"coordinates":[-75.732208,45.429344],"type":"Point"}
}