{
  "type": "Feature",
  "properties": {
    "addr:full":"55 Allen St Charlottetown PE C1A 2V6",
    "addr:housenumber":"55",
    "addr:postcode":"c1a 2v6",
    "addr:street":"Allen St",
    "iso:country":"CA",
    "sg:address":"55 Allen St",
    "sg:city":"Charlottetown",
    "sg:classifiers":[
        {
            "category":"Freight",
            "type":"Transportation"
        }
    ],
    "sg:phone":"+1 902 894 3817",
    "sg:postcode":"C1A 2V6",
    "sg:province":"PE",
    "sg:tags":[
        "trucking"
    ],
    "wof:name":"Austin Mc Quaid Inc",
    "wof:placetype":"venue"
},
  "geometry": {"coordinates":[-63.1310386658,46.2463378906],"type":"Point"}
}