{
  "type": "Feature",
  "properties": {
    "addr:full":"1696 Av Bourgogne Chambly QC J3L 1Z2",
    "addr:housenumber":"1696",
    "addr:postcode":"j3l 1z2",
    "addr:street":"Av Bourgogne",
    "iso:country":"CA",
    "sg:address":"1696 Av Bourgogne",
    "sg:city":"Chambly",
    "sg:classifiers":[
        {
            "category":"Restaurant",
            "type":"Food & Drink"
        }
    ],
    "sg:phone":"+1 450 658 6653",
    "sg:postcode":"J3L 1Z2",
    "sg:province":"QC",
    "wof:name":"Restaurant Tre Colori Inc",
    "wof:placetype":"venue"
},
  "geometry": {"coordinates":[-73.285454,45.447422],"type":"Point"}
}