{
  "type": "Feature",
  "properties": {
    "addr:full":"RR 1 Box 712420 Dundalk ON N0C 1B0",
    "addr:postcode":"n0c 1b0",
    "addr:street":"Rr 1 Box 712420",
    "iso:country":"CA",
    "sg:address":"RR 1 Box 712420",
    "sg:city":"Dundalk",
    "sg:classifiers":[
        {
            "category":"Building & Trades",
            "subcategory":"Construction",
            "type":"Services"
        }
    ],
    "sg:phone":"+1 519 923 2433",
    "sg:postcode":"N0C 1B0",
    "sg:province":"ON",
    "sg:tags":[
        "general",
        "contractor"
    ],
    "wof:name":"B & M Construction & Lumber",
    "wof:placetype":"venue"
},
  "geometry": {"coordinates":[-80.391327,44.16967],"type":"Point"}
}