{
  "type": "Feature",
  "properties": {
    "iso:country":"CA",
    "sg:city":"Toronto",
    "sg:classifiers":[
        {
            "category":"Professional",
            "subcategory":"Printing & Photocopies",
            "type":"Services"
        }
    ],
    "sg:phone":"+1 416 593 4303",
    "sg:postcode":"M5B 2J1",
    "sg:province":"ON",
    "sg:tags":[
        "duplicating",
        "copying"
    ],
    "wof:name":"Lapex Copy Ctr",
    "wof:placetype":"venue"
},
  "geometry": {"coordinates":[-79.377724,43.660133],"type":"Point"}
}