{
  "type": "Feature",
  "properties": {
    "addr:full":"5800 Boul Cavendish Cote Saint-Luc QC H4W 2T5",
    "addr:housenumber":"5800",
    "addr:postcode":"h4w 2t5",
    "addr:street":"Boul Cavendish Cote",
    "iso:country":"CA",
    "sg:address":"5800 Boul Cavendish",
    "sg:city":"Cote Saint-Luc",
    "sg:classifiers":[
        {
            "category":"Shopping",
            "subcategory":"Gifts & Souvenirs",
            "type":"Retail Goods"
        }
    ],
    "sg:phone":"+1 514 487 3050",
    "sg:postcode":"H4W 2T5",
    "sg:province":"QC",
    "sg:tags":[
        "cards",
        "greeting"
    ],
    "wof:name":"Hallmark Card Shop",
    "wof:placetype":"venue"
},
  "geometry": {"coordinates":[-73.66176605219999,45.4759483337],"type":"Point"}
}