{
  "type": "Feature",
  "properties": {
    "addr:full":"12344 Boul Laurentien Montreal QC H4K 1N6",
    "addr:housenumber":"12344",
    "addr:postcode":"h4k 1n6",
    "addr:street":"Boul Laurentien",
    "iso:country":"CA",
    "sg:address":"12344 Boul Laurentien",
    "sg:city":"Montreal",
    "sg:classifiers":[
        {
            "category":"Manufacturing",
            "subcategory":"Tools & Machinery",
            "type":"Manufacturing & Wholesale Goods"
        }
    ],
    "sg:phone":"+1 514 339 9909",
    "sg:postcode":"H4K 1N6",
    "sg:province":"QC",
    "sg:tags":[
        "lubricating",
        "system",
        "devices"
    ],
    "wof:name":"Axxitron Inc",
    "wof:placetype":"venue"
},
  "geometry": {"coordinates":[-73.723961,45.530014],"type":"Point"}
}