{
  "type": "Feature",
  "properties": {
    "addr:full":"4950 47 Ave Red Deer AB T4N 6P8",
    "addr:housenumber":"4950",
    "addr:postcode":"t4n 6p8",
    "addr:street":"47 Ave",
    "iso:country":"CA",
    "sg:address":"4950 47 Ave",
    "sg:city":"Red Deer",
    "sg:classifiers":[
        {
            "category":"Bars & Pubs",
            "type":"Food & Drink"
        }
    ],
    "sg:phone":"+1 403 342 4014",
    "sg:postcode":"T4N 6P8",
    "sg:province":"AB",
    "sg:tags":[
        "lounge",
        "cocktail"
    ],
    "wof:name":"Lucky's Lounge Ltd",
    "wof:placetype":"venue"
},
  "geometry": {"coordinates":[-113.805222,52.268543],"type":"Point"}
}