{
  "type": "Feature",
  "properties": {
    "iso:country":"CA",
    "sg:address":"12 Wettlaufer Rd",
    "sg:city":"Conception Bay South",
    "sg:classifiers":[
        {
            "category":"Health Services",
            "subcategory":"Nursing And Care Facility",
            "type":"Services"
        }
    ],
    "sg:phone":"+1 709 834 3047",
    "sg:postcode":"A1X 7P6",
    "sg:province":"NL",
    "sg:tags":[
        "home",
        "convalescent"
    ],
    "wof:name":"Greenslades Special Care Home",
    "wof:placetype":"venue"
},
  "geometry": {"coordinates":[-52.9972648621,47.4994697571],"type":"Point"}
}