{
  "type": "Feature",
  "properties": {
    "addr:full":"236 Mill St Kitchener ON N2M 3R5",
    "addr:housenumber":"236",
    "addr:postcode":"n2m 3r5",
    "addr:street":"Mill St",
    "iso:country":"CA",
    "sg:address":"236 Mill St",
    "sg:city":"Kitchener",
    "sg:classifiers":[
        {
            "category":"Retail",
            "subcategory":"Auto Repair",
            "type":"Services"
        }
    ],
    "sg:phone":"+1 519 578 0360",
    "sg:postcode":"N2M 3R5",
    "sg:province":"ON",
    "sg:tags":[
        "repairing",
        "automobile"
    ],
    "wof:name":"Jerry Zister's Sales & Svc",
    "wof:placetype":"venue"
},
  "geometry": {"coordinates":[-80.48703,43.437176],"type":"Point"}
}