{
  "type": "Feature",
  "properties": {
    "addr:full":"Black Lake QC G6H 2B4",
    "addr:postcode":"g6h 2b4",
    "addr:street":"Black Lake",
    "iso:country":"CA",
    "sg:city":"Black Lake",
    "sg:classifiers":[
        {
            "category":"Food & Beverages",
            "subcategory":"Groceries & Convenience Stores",
            "type":"Retail Goods"
        }
    ],
    "sg:phone":"+1 418 423 5727",
    "sg:postcode":"G6H 2B4",
    "sg:province":"QC",
    "sg:tags":[
        "grocer"
    ],
    "wof:name":"Alimentation Denis Inc",
    "wof:placetype":"venue"
},
  "geometry": {"coordinates":[-71.368469,46.05127],"type":"Point"}
}