{
  "type": "Feature",
  "properties": {
    "iso:country":"CA",
    "sg:address":"163 Rte DE Saint-Philippe",
    "sg:city":"Dubuisson",
    "sg:classifiers":[
        {
            "category":"Food & Beverages",
            "subcategory":"Groceries & Convenience Stores",
            "type":"Retail Goods"
        }
    ],
    "sg:phone":"+1 819 738 7049",
    "sg:postcode":"J9P 4N7",
    "sg:province":"QC",
    "wof:name":"Depanneur Resto Express",
    "wof:placetype":"venue"
},
  "geometry": {"coordinates":[-77.8930511475,48.0924072266],"type":"Point"}
}