{
  "type": "Feature",
  "properties": {
    "addr:full":"22 Trider Cres Dartmouth NS B3B 1R6",
    "addr:housenumber":"22",
    "addr:postcode":"b3b 1r6",
    "addr:street":"Trider Cres",
    "iso:country":"CA",
    "sg:address":"22 Trider Cres",
    "sg:city":"Dartmouth",
    "sg:classifiers":[
        {
            "category":"Wholesale",
            "subcategory":"Machinery & Supplies",
            "type":"Manufacturing & Wholesale Goods"
        }
    ],
    "sg:phone":"+1 902 468 2405",
    "sg:postcode":"B3B 1R6",
    "sg:province":"NS",
    "sg:tags":[
        "marine",
        "electronic"
    ],
    "wof:name":"R C Marine Electronics Ltd",
    "wof:placetype":"venue"
},
  "geometry": {"coordinates":[-63.5882797241,44.707359314],"type":"Point"}
}