{
  "type": "Feature",
  "properties": {
    "iso:country":"CA",
    "sg:address":"143 Wellington St W",
    "sg:city":"Chatham",
    "sg:classifiers":[
        {
            "category":"Wholesale",
            "subcategory":"Stationery",
            "type":"Manufacturing & Wholesale Goods"
        }
    ],
    "sg:phone":"+1 519 352 8636",
    "sg:postcode":"N7M 1J5",
    "sg:province":"ON",
    "sg:tags":[
        "business",
        "form",
        "system"
    ],
    "wof:name":"Relizon Canada",
    "wof:placetype":"venue"
},
  "geometry": {"coordinates":[-82.185951,42.404438],"type":"Point"}
}