{
  "type": "Feature",
  "properties": {
    "addr:full":"13780 Westminster Hwy Richmond BC V6V 1A2",
    "addr:housenumber":"13780",
    "addr:postcode":"v6v 1a2",
    "addr:street":"Westminster Hwy",
    "iso:country":"CA",
    "sg:address":"13780 Westminster Hwy",
    "sg:city":"Richmond",
    "sg:classifiers":[
        {
            "category":"Organizations",
            "subcategory":"Religious Organization",
            "type":"Services"
        }
    ],
    "sg:phone":"+1 604 276 9627",
    "sg:postcode":"V6V 1A2",
    "sg:province":"BC",
    "sg:tags":[
        "recreation",
        "center",
        "church"
    ],
    "wof:name":"Armenian Community Ctr",
    "wof:placetype":"venue"
},
  "geometry": {"coordinates":[-123.070518494,49.1698150635],"type":"Point"}
}