{
  "type": "Feature",
  "properties": {
    "addr:full":"814 Brock St N Whitby ON L1N 4J5",
    "addr:housenumber":"814",
    "addr:postcode":"l1n 4j5",
    "addr:street":"Brock St N",
    "iso:country":"CA",
    "sg:address":"814 Brock St N",
    "sg:city":"Whitby",
    "sg:classifiers":[
        {
            "category":"Professional",
            "subcategory":"Lawyer & Legal Services",
            "type":"Services"
        }
    ],
    "sg:phone":"+1 905 430 6699",
    "sg:postcode":"L1N 4J5",
    "sg:province":"ON",
    "sg:tags":[
        "attorney"
    ],
    "wof:name":"Seetner, Mark F",
    "wof:placetype":"venue"
},
  "geometry": {"coordinates":[-78.94682299999999,43.890442],"type":"Point"}
}