{
  "type": "Feature",
  "properties": {
    "iso:country":"CA",
    "sg:address":"1600 Byland Rd",
    "sg:city":"Kelowna",
    "sg:classifiers":[
        {
            "category":"Home & Garden",
            "subcategory":"Garden Supply",
            "type":"Retail Goods"
        }
    ],
    "sg:phone":"+1 250 769 7272",
    "sg:postcode":"V1Z 1H6",
    "sg:province":"BC",
    "sg:tags":[
        "center"
    ],
    "wof:name":"Byland's Garden Ctr Ltd",
    "wof:placetype":"venue"
},
  "geometry": {"coordinates":[-119.583320618,49.8629417419],"type":"Point"}
}