{
  "type": "Feature",
  "properties": {
    "addr:full":"Spences Bridge BC V0K 2L0",
    "addr:postcode":"v0k 2l0",
    "iso:country":"CA",
    "sg:city":"Spences Bridge",
    "sg:classifiers":[
        {
            "category":"Food & Beverages",
            "subcategory":"Fruits & Vegetables",
            "type":"Retail Goods"
        }
    ],
    "sg:phone":"+1 250 458 2284",
    "sg:postcode":"V0K 2L0",
    "sg:province":"BC",
    "sg:tags":[
        "produce"
    ],
    "wof:name":"Nine Mile Garden",
    "wof:placetype":"venue"
},
  "geometry": {"coordinates":[-121.342766,50.424522],"type":"Point"}
}