{
  "type": "Feature",
  "properties": {
    "addr:full":"Ajax ON L1S 7J5",
    "addr:postcode":"l1s 7j5",
    "iso:country":"CA",
    "sg:city":"Ajax",
    "sg:classifiers":[
        {
            "category":"Government",
            "subcategory":"Office",
            "type":"Public Place"
        }
    ],
    "sg:phone":"+1 905 427 5600",
    "sg:postcode":"L1S 7J5",
    "sg:province":"ON",
    "wof:name":"Ontario Environment & Energy",
    "wof:placetype":"venue"
},
  "geometry": {"coordinates":[-79.035973,43.842415],"type":"Point"}
}