{
  "type": "Feature",
  "properties": {
    "iso:country":"CA",
    "sg:address":"4225 Aut Des Laurentides",
    "sg:city":"Laval",
    "sg:classifiers":[
        {
            "category":"Manufacturing",
            "subcategory":"Metals",
            "type":"Manufacturing & Wholesale Goods"
        }
    ],
    "sg:phone":"+1 450 682 4141",
    "sg:postcode":"H7L 5W5",
    "sg:province":"QC",
    "sg:tags":[
        "cap",
        "bottle",
        "seal"
    ],
    "wof:name":"Ampak Distribution Inc",
    "wof:placetype":"venue"
},
  "geometry": {"coordinates":[-73.77039337159999,45.5804290771],"type":"Point"}
}