{
  "type": "Feature",
  "properties": {
    "addr:full":"91 Front St W Toronto ON M5J 1E5",
    "addr:housenumber":"91",
    "addr:postcode":"m5j 1e5",
    "addr:street":"Front St W",
    "iso:country":"CA",
    "sg:address":"91 Front St W",
    "sg:city":"Toronto",
    "sg:classifiers":[
        {
            "category":"Restaurant",
            "type":"Food & Drink"
        }
    ],
    "sg:phone":"+1 416 368 5241",
    "sg:postcode":"M5J 1E5",
    "sg:province":"ON",
    "sg:tags":[
        "delicatessen"
    ],
    "wof:name":"Mustachio Inc",
    "wof:placetype":"venue"
},
  "geometry": {"coordinates":[-79.38153839109999,43.6452445984],"type":"Point"}
}