{
  "type": "Feature",
  "properties": {
    "addr:full":"575 Markham Rd Scarborough ON M1H 2A3",
    "addr:housenumber":"575",
    "addr:postcode":"m1h 2a3",
    "addr:street":"Markham Rd",
    "iso:country":"CA",
    "sg:address":"575 Markham Rd",
    "sg:city":"Scarborough",
    "sg:classifiers":[
        {
            "category":"Restaurant",
            "type":"Food & Drink"
        }
    ],
    "sg:phone":"+1 416 431 3393",
    "sg:postcode":"M1H 2A3",
    "sg:province":"ON",
    "wof:name":"Tommy's Restaurant & Bar",
    "wof:placetype":"venue"
},
  "geometry": {"coordinates":[-79.22483099999999,43.758877],"type":"Point"}
}