{
  "type": "Feature",
  "properties": {
    "addr:full":"110 Carleton St Woodstock NB E7M 1E4",
    "addr:housenumber":"110",
    "addr:postcode":"e7m 1e4",
    "addr:street":"Carleton St",
    "iso:country":"CA",
    "sg:address":"110 Carleton St",
    "sg:city":"Woodstock",
    "sg:classifiers":[
        {
            "category":"Manufacturing",
            "subcategory":"Printing",
            "type":"Manufacturing & Wholesale Goods"
        }
    ],
    "sg:phone":"+1 506 328 8863",
    "sg:postcode":"E7M 1E4",
    "sg:province":"NB",
    "sg:tags":[
        "newspaper"
    ],
    "wof:name":"Bugle",
    "wof:placetype":"venue"
},
  "geometry": {"coordinates":[-67.5711975098,46.1501998901],"type":"Point"}
}