{
  "type": "Feature",
  "properties": {
    "addr:full":"791 Rue Des Cedres Dolbeau-Mistassini QC G8L 1N2",
    "addr:housenumber":"791",
    "addr:postcode":"g8l 1n2",
    "addr:street":"Rue Des Cedres",
    "iso:country":"CA",
    "sg:address":"791 Rue Des Cedres",
    "sg:city":"Dolbeau-Mistassini",
    "sg:classifiers":[
        {
            "category":"Building & Trades",
            "subcategory":"Construction",
            "type":"Services"
        }
    ],
    "sg:phone":"+1 418 276 2262",
    "sg:postcode":"G8L 1N2",
    "sg:province":"QC",
    "sg:tags":[
        "repairing",
        "remodeling",
        "contractor"
    ],
    "wof:name":"Produits Fenestra Inc",
    "wof:placetype":"venue"
},
  "geometry": {"coordinates":[-72.22792800000001,48.872761],"type":"Point"}
}