{
  "type": "Feature",
  "properties": {
    "iso:country":"CA",
    "sg:address":"626 Queen St W",
    "sg:city":"Toronto",
    "sg:classifiers":[
        {
            "category":"Food & Beverages",
            "subcategory":"Bakery",
            "type":"Retail Goods"
        }
    ],
    "sg:phone":"+1 416 703 7278",
    "sg:postcode":"M6J 1E4",
    "sg:province":"ON",
    "sg:tags":[
        "baker"
    ],
    "wof:name":"Vienna Home Bakery",
    "wof:placetype":"venue"
},
  "geometry": {"coordinates":[-79.405724,43.646988],"type":"Point"}
}