{
  "type": "Feature",
  "properties": {
    "addr:full":"22 Ospika Cres Mackenzie BC V0J 2C0",
    "addr:housenumber":"22",
    "addr:postcode":"v0j 2c0",
    "addr:street":"Ospika Cres",
    "iso:country":"CA",
    "sg:address":"22 Ospika Cres",
    "sg:city":"Mackenzie",
    "sg:classifiers":[
        {
            "category":"Professional",
            "subcategory":"Research",
            "type":"Services"
        }
    ],
    "sg:phone":"+1 250 997 4094",
    "sg:postcode":"V0J 2C0",
    "sg:province":"BC",
    "sg:tags":[
        "environmental",
        "ecological"
    ],
    "wof:name":"Beacon Environmental Consultin",
    "wof:placetype":"venue"
},
  "geometry": {"coordinates":[-123.081825256,55.3327560425],"type":"Point"}
}