{
  "type": "Feature",
  "properties": {
    "addr:full":"102 Argyle St N Alexander MB R0K 0A0",
    "addr:housenumber":"102",
    "addr:postcode":"r0k 0a0",
    "addr:street":"Argyle St N Alexander",
    "iso:country":"CA",
    "sg:address":"102 Argyle St N",
    "sg:city":"Alexander",
    "sg:classifiers":[
        {
            "category":"Education",
            "subcategory":"School",
            "type":"Public Place"
        }
    ],
    "sg:phone":"+1 204 752 2251",
    "sg:postcode":"R0K 0A0",
    "sg:province":"MB",
    "wof:name":"Alexander School",
    "wof:placetype":"venue"
},
  "geometry": {"coordinates":[-100.30331420900001,49.8305854797],"type":"Point"}
}