{
  "type": "Feature",
  "properties": {
    "addr:full":"2475 Bloor St W Toronto ON M6S 1P7",
    "addr:housenumber":"2475",
    "addr:postcode":"m6s 1p7",
    "addr:street":"Bloor St W",
    "iso:country":"CA",
    "sg:address":"2475 Bloor St W",
    "sg:city":"Toronto",
    "sg:classifiers":[
        {
            "category":"Health Services",
            "subcategory":"Doctor",
            "type":"Services"
        }
    ],
    "sg:phone":"+1 416 769 4220",
    "sg:postcode":"M6S 1P7",
    "sg:province":"ON",
    "sg:tags":[
        "dentist"
    ],
    "wof:name":"Zigan Lube Family Dentistry",
    "wof:placetype":"venue"
},
  "geometry": {"coordinates":[-79.484695,43.649185],"type":"Point"}
}