{
  "type": "Feature",
  "properties": {
    "addr:full":"12235 Lake Louise Way SE Calgary AB T2J 2M2",
    "addr:housenumber":"12235",
    "addr:postcode":"t2j 2m2",
    "addr:street":"Lake Louise Way Se",
    "iso:country":"CA",
    "sg:address":"12235 Lake Louise Way SE",
    "sg:city":"Calgary",
    "sg:classifiers":[
        {
            "category":"Mining & Drilling",
            "type":"Manufacturing & Wholesale Goods"
        }
    ],
    "sg:phone":"+1 403 278 8855",
    "sg:postcode":"T2J 2M2",
    "sg:province":"AB",
    "sg:tags":[
        "company",
        "oil"
    ],
    "wof:name":"Cuesta Energy Inc",
    "wof:placetype":"venue"
},
  "geometry": {"coordinates":[-114.049682617,50.9435997009],"type":"Point"}
}