{
  "type": "Feature",
  "properties": {
    "addr:full":"5804 Datsun Rd Mississauga ON L4W 1H2",
    "addr:housenumber":"5804",
    "addr:postcode":"l4w 1h2",
    "addr:street":"Datsun Rd",
    "iso:country":"CA",
    "sg:address":"5804 Datsun Rd",
    "sg:city":"Mississauga",
    "sg:classifiers":[
        {
            "category":"Wholesale",
            "subcategory":"Machinery & Supplies",
            "type":"Manufacturing & Wholesale Goods"
        }
    ],
    "sg:phone":"+1 905 670 3440",
    "sg:postcode":"L4W 1H2",
    "sg:province":"ON",
    "sg:tags":[
        "contractor"
    ],
    "wof:name":"Amaco Construction Equipment",
    "wof:placetype":"venue"
},
  "geometry": {"coordinates":[-79.645004,43.648888],"type":"Point"}
}