{
  "type": "Feature",
  "properties": {
    "addr:full":"849 Walker Rd Windsor ON N8Y 2N4",
    "addr:housenumber":"849",
    "addr:postcode":"n8y 2n4",
    "addr:street":"Walker Rd",
    "iso:country":"CA",
    "sg:address":"849 Walker Rd",
    "sg:city":"Windsor",
    "sg:classifiers":[
        {
            "category":"Manufacturing",
            "subcategory":"Tools & Machinery",
            "type":"Manufacturing & Wholesale Goods"
        }
    ],
    "sg:phone":"+1 519 256 7223",
    "sg:postcode":"N8Y 2N4",
    "sg:province":"ON",
    "sg:tags":[
        "machine",
        "shop"
    ],
    "wof:name":"Browning Engineering & Mfg",
    "wof:placetype":"venue"
},
  "geometry": {"coordinates":[-83.00732421879999,42.3219604492],"type":"Point"}
}