{
  "type": "Feature",
  "properties": {
    "iso:country":"CA",
    "sg:city":"St Catharines",
    "sg:classifiers":[
        {
            "category":"Wholesale",
            "subcategory":"Meat",
            "type":"Manufacturing & Wholesale Goods"
        }
    ],
    "sg:phone":"+1 905 646 2466",
    "sg:postcode":"L2N 7H8",
    "sg:province":"ON",
    "sg:tags":[
        "butchering"
    ],
    "wof:name":"King's Quality Meats & Deli",
    "wof:placetype":"venue"
},
  "geometry": {"coordinates":[-79.259804,43.195599],"type":"Point"}
}