{
  "type": "Feature",
  "properties": {
    "addr:full":"2121 Rue Leonard-DE Vinci Sainte-Julie QC J3E 1Z2",
    "addr:housenumber":"2121",
    "addr:postcode":"j3e 1z2",
    "addr:street":"Rue Leonard-De Vinci",
    "iso:country":"CA",
    "sg:address":"2121 Rue Leonard-DE Vinci",
    "sg:city":"Sainte-Julie",
    "sg:classifiers":[
        {
            "category":"Wholesale",
            "subcategory":"Groceries",
            "type":"Manufacturing & Wholesale Goods"
        }
    ],
    "sg:phone":"+1 450 922 2885",
    "sg:postcode":"J3E 1Z2",
    "sg:province":"QC",
    "sg:tags":[
        "food",
        "product",
        "natural"
    ],
    "wof:name":"Gourmet Nutrition Fb Inc",
    "wof:placetype":"venue"
},
  "geometry": {"coordinates":[-73.3371582031,45.577255249],"type":"Point"}
}