{
  "type": "Feature",
  "properties": {
    "addr:full":"210 Cowan Blvd Cambridge ON N1T 1V4",
    "addr:housenumber":"210",
    "addr:postcode":"n1t 1v4",
    "addr:street":"Cowan Blvd",
    "iso:country":"CA",
    "sg:address":"210 Cowan Blvd",
    "sg:city":"Cambridge",
    "sg:classifiers":[
        {
            "category":"Social Services",
            "subcategory":"Child Care",
            "type":"Services"
        }
    ],
    "sg:phone":"+1 519 622 6773",
    "sg:postcode":"N1T 1V4",
    "sg:province":"ON",
    "wof:name":"Ywca of Cambridge",
    "wof:placetype":"venue"
},
  "geometry": {"coordinates":[-80.29675292970001,43.388458252],"type":"Point"}
}