{
  "type": "Feature",
  "properties": {
    "iso:country":"CA",
    "sg:address":"3207 Boul Des Sources",
    "sg:city":"Dollard-Des-Ormeaux",
    "sg:classifiers":[
        {
            "category":"Shopping",
            "subcategory":"Clothing, Apparel, & Fashions",
            "type":"Retail Goods"
        }
    ],
    "sg:phone":"+1 514 683 6260",
    "sg:postcode":"H9B 1Z6",
    "sg:province":"QC",
    "wof:name":"Winners Apparel Ltd",
    "wof:placetype":"venue"
},
  "geometry": {"coordinates":[-73.795319,45.482861],"type":"Point"}
}