{
  "type": "Feature",
  "properties": {
    "addr:full":"Mississauga ON L4V 1X1",
    "addr:postcode":"l4v 1x1",
    "iso:country":"CA",
    "sg:city":"Mississauga",
    "sg:classifiers":[
        {
            "category":"Restaurant",
            "type":"Food & Drink"
        }
    ],
    "sg:phone":"+1 905 678 9375",
    "sg:postcode":"L4V 1X1",
    "sg:province":"ON",
    "wof:name":"Cumbar's Bar & Tavola Calda",
    "wof:placetype":"venue"
},
  "geometry": {"coordinates":[-79.61938499999999,43.701832],"type":"Point"}
}