{
  "type": "Feature",
  "properties": {
    "addr:full":"1936 Kent Rd Kelowna BC V1Y 7S1",
    "addr:housenumber":"1936",
    "addr:postcode":"v1y 7s1",
    "addr:street":"Kent Rd",
    "iso:country":"CA",
    "sg:address":"1936 Kent Rd",
    "sg:city":"Kelowna",
    "sg:classifiers":[
        {
            "category":"Wholesale",
            "subcategory":"Electrical",
            "type":"Manufacturing & Wholesale Goods"
        }
    ],
    "sg:phone":"+1 250 862 8200",
    "sg:postcode":"V1Y 7S1",
    "sg:province":"BC",
    "sg:tags":[
        "equipment",
        "electric",
        "supply"
    ],
    "wof:name":"Wesco Distribution-Canada Inc",
    "wof:placetype":"venue"
},
  "geometry": {"coordinates":[-119.453292847,49.8786773682],"type":"Point"}
}