{
  "type": "Feature",
  "properties": {
    "addr:full":"2780 Av Raymond Saint-Hyacinthe QC J2S 5W7",
    "addr:housenumber":"2780",
    "addr:postcode":"j2s 5w7",
    "addr:street":"Av Raymond",
    "iso:country":"CA",
    "sg:address":"2780 Av Raymond",
    "sg:city":"Saint-Hyacinthe",
    "sg:classifiers":[
        {
            "category":"Shopping",
            "subcategory":"Pharmacy",
            "type":"Retail Goods"
        }
    ],
    "sg:phone":"+1 450 774 0093",
    "sg:postcode":"J2S 5W7",
    "sg:province":"QC",
    "wof:name":"Malenfant & Legendre",
    "wof:placetype":"venue"
},
  "geometry": {"coordinates":[-72.9628753662,45.6318435669],"type":"Point"}
}