{
  "type": "Feature",
  "properties": {
    "addr:full":"5495 Rue Pare Mont-Royal QC H4P 1P7",
    "addr:housenumber":"5495",
    "addr:postcode":"h4p 1p7",
    "addr:street":"Rue Pare",
    "iso:country":"CA",
    "sg:address":"5495 Rue Pare",
    "sg:city":"Mont-Royal",
    "sg:classifiers":[
        {
            "category":"Manufacturing",
            "subcategory":"Food",
            "type":"Manufacturing & Wholesale Goods"
        }
    ],
    "sg:phone":"+1 514 738 3600",
    "sg:postcode":"H4P 1P7",
    "sg:province":"QC",
    "sg:tags":[
        "bakery",
        "prod",
        "cookie"
    ],
    "wof:name":"Montreal Kosher Bakery-Passovr",
    "wof:placetype":"venue"
},
  "geometry": {"coordinates":[-73.65989685060001,45.4928092957],"type":"Point"}
}