{
  "type": "Feature",
  "properties": {
    "addr:full":"56 Tache St Fisher Branch MB R0C 0Z0",
    "addr:housenumber":"56",
    "addr:postcode":"r0c 0z0",
    "addr:street":"Tache St",
    "iso:country":"CA",
    "sg:address":"56 Tache St",
    "sg:city":"Fisher Branch",
    "sg:classifiers":[
        {
            "category":"Retail",
            "subcategory":"Auto Repair",
            "type":"Services"
        }
    ],
    "sg:phone":"+1 204 372 6123",
    "sg:postcode":"R0C 0Z0",
    "sg:province":"MB",
    "sg:tags":[
        "repairing",
        "automobile"
    ],
    "wof:name":"Northern Garage",
    "wof:placetype":"venue"
},
  "geometry": {"coordinates":[-97.618454,51.082603],"type":"Point"}
}