{
  "type": "Feature",
  "properties": {
    "iso:country":"CA",
    "sg:city":"North York",
    "sg:classifiers":[
        {
            "category":"Personal",
            "type":"Services"
        }
    ],
    "sg:phone":"+1 416 385 0110",
    "sg:postcode":"M2L 2Y5",
    "sg:province":"ON",
    "sg:tags":[
        "therapist",
        "chiropractor",
        "massage"
    ],
    "wof:name":"Sports Specialist Rehab Ctr",
    "wof:placetype":"venue"
},
  "geometry": {"coordinates":[-79.385567,43.747864],"type":"Point"}
}