{
  "type": "Feature",
  "properties": {
    "addr:full":"Dryden ON P8N 1Z2",
    "addr:postcode":"p8n 1z2",
    "iso:country":"CA",
    "sg:city":"Dryden",
    "sg:classifiers":[
        {
            "category":"Home & Garden",
            "subcategory":"Household Appliances",
            "type":"Retail Goods"
        }
    ],
    "sg:phone":"+1 807 223 5334",
    "sg:postcode":"P8N 1Z2",
    "sg:province":"ON",
    "sg:tags":[
        "mail",
        "catalog",
        "shopping",
        "order"
    ],
    "wof:name":"Sears Canada Inc",
    "wof:placetype":"venue"
},
  "geometry": {"coordinates":[-92.83865356450001,49.7836952209],"type":"Point"}
}