{
  "type": "Feature",
  "properties": {
    "addr:full":"2323 Rue Cohen Saint-Laurent QC H4R 2N7",
    "addr:housenumber":"2323",
    "addr:postcode":"h4r 2n7",
    "addr:street":"Rue Cohen Saint-Laurent",
    "iso:country":"CA",
    "sg:address":"2323 Rue Cohen",
    "sg:city":"Saint-Laurent",
    "sg:classifiers":[
        {
            "category":"Wholesale",
            "subcategory":"Durable Goods & Equipment",
            "type":"Manufacturing & Wholesale Goods"
        }
    ],
    "sg:phone":"+1 514 832 1010",
    "sg:postcode":"H4R 2N7",
    "sg:province":"QC",
    "sg:tags":[
        "luggage"
    ],
    "wof:name":"Bugatti",
    "wof:placetype":"venue"
},
  "geometry": {"coordinates":[-73.7325744629,45.4955482483],"type":"Point"}
}