{
  "type": "Feature",
  "properties": {
    "addr:full":"352 Av Martineau Otter Lake QC J0X 2P0",
    "addr:postcode":"j0x 2p0",
    "addr:street":"352 Av Martineau",
    "iso:country":"CA",
    "sg:address":"352 Av Martineau",
    "sg:city":"Otter Lake",
    "sg:classifiers":[
        {
            "category":"Food & Beverages",
            "subcategory":"Groceries & Convenience Stores",
            "type":"Retail Goods"
        }
    ],
    "sg:phone":"+1 819 453 7600",
    "sg:postcode":"J0X 2P0",
    "sg:province":"QC",
    "wof:name":"Beauchamp Service",
    "wof:placetype":"venue"
},
  "geometry": {"coordinates":[-76.4313049316,45.8469200134],"type":"Point"}
}