{
  "type": "Feature",
  "properties": {
    "addr:full":"8191 Rue Saint-Denis Montreal QC H2P 2G7",
    "addr:housenumber":"8191",
    "addr:postcode":"h2p 2g7",
    "addr:street":"Rue Saint-Denis",
    "iso:country":"CA",
    "sg:address":"8191 Rue Saint-Denis",
    "sg:city":"Montreal",
    "sg:classifiers":[
        {
            "category":"Professional",
            "subcategory":"Business Services",
            "type":"Services"
        }
    ],
    "sg:phone":"+1 514 272 7395",
    "sg:postcode":"H2P 2G7",
    "sg:province":"QC",
    "sg:tags":[
        "notary"
    ],
    "wof:name":"Scotti & Magny",
    "wof:placetype":"venue"
},
  "geometry": {"coordinates":[-73.630569458,45.5431365967],"type":"Point"}
}