{
  "type": "Feature",
  "properties": {
    "iso:country":"CA",
    "sg:address":"2505 Brock Rd N RR 1",
    "sg:city":"Pickering",
    "sg:classifiers":[
        {
            "category":"Real Estate",
            "subcategory":"Developer",
            "type":"Services"
        }
    ],
    "sg:phone":"+1 905 427 3385",
    "sg:postcode":"L1V 2P8",
    "sg:province":"ON",
    "sg:tags":[
        "cemetery"
    ],
    "wof:name":"Duffin Meadows Cemetery",
    "wof:placetype":"venue"
},
  "geometry": {"coordinates":[-79.07762146,43.8549995422],"type":"Point"}
}