{
  "type": "Feature",
  "properties": {
    "iso:country":"CA",
    "sg:city":"Lloydminster",
    "sg:classifiers":[
        {
            "category":"Home & Garden",
            "subcategory":"Building Materials",
            "type":"Retail Goods"
        }
    ],
    "sg:phone":"+1 780 875 7557",
    "sg:postcode":"T9V 2V3",
    "sg:province":"AB",
    "sg:tags":[
        "glass",
        "window",
        "plate"
    ],
    "wof:name":"Apple Auto Glass",
    "wof:placetype":"venue"
},
  "geometry": {"coordinates":[-110.03073120099999,53.2770271301],"type":"Point"}
}