{
  "type": "Feature",
  "properties": {
    "addr:full":"620 Marine Dr SE Vancouver BC V5X 2T4",
    "addr:housenumber":"620",
    "addr:postcode":"v5x 2t4",
    "addr:street":"Marine Dr Se",
    "iso:country":"CA",
    "sg:address":"620 Marine Dr SE",
    "sg:city":"Vancouver",
    "sg:classifiers":[
        {
            "category":"Restaurant",
            "type":"Food & Drink"
        }
    ],
    "sg:phone":"+1 604 321 4433",
    "sg:postcode":"V5X 2T4",
    "sg:province":"BC",
    "wof:name":"Wonton King",
    "wof:placetype":"venue"
},
  "geometry": {"coordinates":[-123.092636,49.210835],"type":"Point"}
}