{
  "type": "Feature",
  "properties": {
    "addr:full":"690 Carlaw Ave Toronto ON M4K 3K9",
    "addr:housenumber":"690",
    "addr:postcode":"m4k 3k9",
    "addr:street":"Carlaw Ave",
    "iso:country":"CA",
    "sg:address":"690 Carlaw Ave",
    "sg:city":"Toronto",
    "sg:classifiers":[
        {
            "category":"Social Services",
            "subcategory":"Child Care",
            "type":"Services"
        }
    ],
    "sg:phone":"+1 416 469 0560",
    "sg:postcode":"M4K 3K9",
    "sg:province":"ON",
    "wof:name":"Childspace Day Care Corp",
    "wof:placetype":"venue"
},
  "geometry": {"coordinates":[-79.34671,43.676758],"type":"Point"}
}