{
  "type": "Feature",
  "properties": {
    "addr:full":"87 Wade Ave Toronto ON M6H 1P5",
    "addr:housenumber":"87",
    "addr:postcode":"m6h 1p5",
    "addr:street":"Wade Ave",
    "iso:country":"CA",
    "sg:address":"87 Wade Ave",
    "sg:city":"Toronto",
    "sg:classifiers":[
        {
            "category":"Museum",
            "type":"Entertainment"
        }
    ],
    "sg:phone":"+1 416 538 4003",
    "sg:postcode":"M6H 1P5",
    "sg:province":"ON",
    "sg:tags":[
        "organization",
        "arts",
        "information"
    ],
    "wof:name":"Territory Orphans",
    "wof:placetype":"venue"
},
  "geometry": {"coordinates":[-79.44560199999999,43.659985],"type":"Point"}
}