{
  "type": "Feature",
  "properties": {
    "addr:full":"1161 Sunshine Coast Hwy Gibsons BC V0N 1V4",
    "addr:housenumber":"1161",
    "addr:postcode":"v0n 1v4",
    "addr:street":"Sunshine Coast Hwy",
    "iso:country":"CA",
    "sg:address":"1161 Sunshine Coast Hwy",
    "sg:city":"Gibsons",
    "sg:classifiers":[
        {
            "category":"Education",
            "subcategory":"School",
            "type":"Public Place"
        }
    ],
    "sg:phone":"+1 604 886 7221",
    "sg:postcode":"V0N 1V4",
    "sg:province":"BC",
    "wof:name":"Alternate Education Program",
    "wof:placetype":"venue"
},
  "geometry": {"coordinates":[-123.526146,49.406639],"type":"Point"}
}