{
  "type": "Feature",
  "properties": {
    "iso:country":"CA",
    "sg:address":"PO Box 187",
    "sg:city":"Vauxhall",
    "sg:classifiers":[
        {
            "category":"Freight",
            "type":"Transportation"
        }
    ],
    "sg:phone":"+1 403 654 2045",
    "sg:postcode":"T0K 2K0",
    "sg:province":"AB",
    "sg:tags":[
        "field",
        "oil",
        "trucking"
    ],
    "wof:name":"Phillips Oilfield Svc",
    "wof:placetype":"venue"
},
  "geometry": {"coordinates":[-112.09733581499999,50.0708847046],"type":"Point"}
}