{
  "type": "Feature",
  "properties": {
    "addr:full":"Hwy 2 E High Prairie AB T0G 1E0",
    "addr:postcode":"t0g 1e0",
    "addr:street":"Hwy 2 E",
    "iso:country":"CA",
    "sg:address":"Hwy 2 E",
    "sg:city":"High Prairie",
    "sg:classifiers":[
        {
            "category":"Autos & Motor Vehicles",
            "subcategory":"Auto Supplies",
            "type":"Retail Goods"
        }
    ],
    "sg:phone":"+1 780 523 4740",
    "sg:postcode":"T0G 1E0",
    "sg:province":"AB",
    "sg:tags":[
        "tire"
    ],
    "wof:name":"Kal Tire",
    "wof:placetype":"venue"
},
  "geometry": {"coordinates":[-116.477051,55.432865],"type":"Point"}
}