{
  "type": "Feature",
  "properties": {
    "addr:full":"76 Stuart St Kingston ON K7L 2V7",
    "addr:housenumber":"76",
    "addr:postcode":"k7l 2v7",
    "addr:street":"Stuart St",
    "iso:country":"CA",
    "sg:address":"76 Stuart St",
    "sg:city":"Kingston",
    "sg:classifiers":[
        {
            "category":"Health Services",
            "subcategory":"Doctor",
            "type":"Services"
        }
    ],
    "sg:phone":"+1 613 546 4933",
    "sg:postcode":"K7L 2V7",
    "sg:province":"ON",
    "sg:tags":[
        "dentist"
    ],
    "wof:name":"Chan, Roy DDS",
    "wof:placetype":"venue"
},
  "geometry": {"coordinates":[-76.4932479858,44.2243843079],"type":"Point"}
}