{
  "type": "Feature",
  "properties": {
    "addr:full":"427 Rogers Rd York ON M6M 1A4",
    "addr:housenumber":"427",
    "addr:postcode":"m6m 1a4",
    "addr:street":"Rogers Rd",
    "iso:country":"CA",
    "sg:address":"427 Rogers Rd",
    "sg:city":"York",
    "sg:classifiers":[
        {
            "category":"Personal",
            "subcategory":"Beauty Salon",
            "type":"Services"
        }
    ],
    "sg:phone":"+1 416 652 6903",
    "sg:postcode":"M6M 1A4",
    "sg:province":"ON",
    "wof:name":"Family Nails",
    "wof:placetype":"venue"
},
  "geometry": {"coordinates":[-79.463508606,43.6825752258],"type":"Point"}
}