{
  "type": "Feature",
  "properties": {
    "iso:country":"CA",
    "sg:address":"Bldg 59",
    "sg:city":"Split Lake",
    "sg:classifiers":[
        {
            "category":"Communications",
            "subcategory":"Radio Station",
            "type":"Services"
        }
    ],
    "sg:phone":"+1 204 342 2568",
    "sg:postcode":"R0B 1P0",
    "sg:province":"MB",
    "sg:tags":[
        "company",
        "broadcasting"
    ],
    "wof:name":"Tataskweyak Radio Station",
    "wof:placetype":"venue"
},
  "geometry": {"coordinates":[-96.1045379639,56.2460594177],"type":"Point"}
}