{
  "type": "Feature",
  "properties": {
    "addr:full":"1136 Boul Jean Cartier Mont-Joli QC G5H 2S6",
    "addr:housenumber":"1136",
    "addr:postcode":"g5h 2s6",
    "addr:street":"Boul Jean Cartier",
    "iso:country":"CA",
    "sg:address":"1136 Boul Jean Cartier",
    "sg:city":"Mont-Joli",
    "sg:classifiers":[
        {
            "category":"Shopping",
            "type":"Retail Goods"
        }
    ],
    "sg:phone":"+1 418 775 9464",
    "sg:postcode":"G5H 2S6",
    "sg:province":"QC",
    "sg:tags":[
        "hearing",
        "equipment",
        "supply",
        "impaired"
    ],
    "wof:name":"Tremblay, Gilles",
    "wof:placetype":"venue"
},
  "geometry": {"coordinates":[-68.2025375366,48.5944480896],"type":"Point"}
}