{
  "type": "Feature",
  "properties": {
    "addr:full":"1200 Place Nobel Boucherville QC J4B 5L2",
    "addr:housenumber":"1200",
    "addr:postcode":"j4b 5l2",
    "addr:street":"Place Nobel",
    "iso:country":"CA",
    "sg:address":"1200 Place Nobel",
    "sg:city":"Boucherville",
    "sg:classifiers":[
        {
            "category":"Home & Garden",
            "subcategory":"Furniture",
            "type":"Retail Goods"
        }
    ],
    "sg:phone":"+1 450 641 3305",
    "sg:postcode":"J4B 5L2",
    "sg:province":"QC",
    "sg:tags":[
        "infant",
        "wear"
    ],
    "wof:name":"Clement Limitee",
    "wof:placetype":"venue"
},
  "geometry": {"coordinates":[-73.44686900000001,45.571564],"type":"Point"}
}