{
  "type": "Feature",
  "properties": {
    "addr:full":"3610 Rue Saint-Dominique Montreal QC H2X 2X7",
    "addr:housenumber":"3610",
    "addr:postcode":"h2x 2x7",
    "addr:street":"Rue Saint-Dominique",
    "iso:country":"CA",
    "sg:address":"3610 Rue Saint-Dominique",
    "sg:city":"Montreal",
    "sg:classifiers":[
        {
            "category":"Restaurant",
            "type":"Food & Drink"
        }
    ],
    "sg:phone":"+1 514 288 5577",
    "sg:postcode":"H2X 2X7",
    "sg:province":"QC",
    "wof:name":"Gourmet Thai Viet",
    "wof:placetype":"venue"
},
  "geometry": {"coordinates":[-73.57255600000001,45.514427],"type":"Point"}
}