{
  "type": "Feature",
  "properties": {
    "addr:full":"95 Metcalfe St Elora ON N0B 1S0",
    "addr:housenumber":"95",
    "addr:postcode":"n0b 1s0",
    "addr:street":"Metcalfe St",
    "iso:country":"CA",
    "sg:address":"95 Metcalfe St",
    "sg:city":"Elora",
    "sg:classifiers":[
        {
            "category":"Shopping",
            "subcategory":"Florist",
            "type":"Retail Goods"
        }
    ],
    "sg:phone":"+1 519 846 0021",
    "sg:postcode":"N0B 1S0",
    "sg:province":"ON",
    "wof:name":"David Drimmie Florist",
    "wof:placetype":"venue"
},
  "geometry": {"coordinates":[-80.429771,43.681965],"type":"Point"}
}