{
  "type": "Feature",
  "properties": {
    "addr:full":"55 Keith Rd Winnipeg MB R3H 0H7",
    "addr:housenumber":"55",
    "addr:postcode":"r3h 0h7",
    "addr:street":"Keith Rd",
    "iso:country":"CA",
    "sg:address":"55 Keith Rd",
    "sg:city":"Winnipeg",
    "sg:classifiers":[
        {
            "category":"Manufacturing",
            "subcategory":"Metals",
            "type":"Manufacturing & Wholesale Goods"
        }
    ],
    "sg:phone":"+1 204 694 7128",
    "sg:postcode":"R3H 0H7",
    "sg:province":"MB",
    "sg:tags":[
        "spring"
    ],
    "wof:name":"Western Spring & Wire Ltd",
    "wof:placetype":"venue"
},
  "geometry": {"coordinates":[-97.21403503419999,49.9132003784],"type":"Point"}
}