{
  "type": "Feature",
  "properties": {
    "addr:full":"Granby QC J2H 1K7",
    "addr:postcode":"j2h 1k7",
    "iso:country":"CA",
    "sg:city":"Granby",
    "sg:classifiers":[
        {
            "category":"Building & Trades",
            "subcategory":"Construction",
            "type":"Services"
        }
    ],
    "sg:phone":"+1 450 777 1378",
    "sg:postcode":"J2H 1K7",
    "sg:province":"QC",
    "sg:tags":[
        "general",
        "contractor"
    ],
    "wof:name":"Constructions Daniel Ducharme",
    "wof:placetype":"venue"
},
  "geometry": {"coordinates":[-72.716888,45.418709],"type":"Point"}
}