{
  "type": "Feature",
  "properties": {
    "iso:country":"CA",
    "sg:address":"10 Hutchings St",
    "sg:city":"Winnipeg",
    "sg:classifiers":[
        {
            "category":"Manufacturing",
            "subcategory":"Glass & Minerals",
            "type":"Manufacturing & Wholesale Goods"
        }
    ],
    "sg:phone":"+1 204 694 2691",
    "sg:postcode":"R2X 2X1",
    "sg:province":"MB",
    "sg:tags":[
        "refractory"
    ],
    "wof:name":"Inproheat Industries Ltd",
    "wof:placetype":"venue"
},
  "geometry": {"coordinates":[-97.182975769,49.9364318848],"type":"Point"}
}