{
  "type": "Feature",
  "properties": {
    "addr:full":"Saskatoon SK S7K 1K8",
    "addr:postcode":"s7k 1k8",
    "iso:country":"CA",
    "sg:city":"Saskatoon",
    "sg:classifiers":[
        {
            "category":"Shopping",
            "subcategory":"Clothing, Apparel, & Fashions",
            "type":"Retail Goods"
        }
    ],
    "sg:phone":"+1 306 651 1566",
    "sg:postcode":"S7K 1K8",
    "sg:province":"SK",
    "sg:tags":[
        "alteration"
    ],
    "wof:name":"Carmen's Dress Shop & Altrtn",
    "wof:placetype":"venue"
},
  "geometry": {"coordinates":[-106.66532100000001,52.126205],"type":"Point"}
}