{
  "type": "Feature",
  "properties": {
    "iso:country":"CA",
    "sg:city":"Calgary",
    "sg:classifiers":[
        {
            "category":"Wholesale",
            "subcategory":"Medical Equipment & Supplies",
            "type":"Manufacturing & Wholesale Goods"
        }
    ],
    "sg:phone":"+1 403 250 9557",
    "sg:postcode":"T2E 7T1",
    "sg:province":"AB",
    "sg:tags":[
        "optical"
    ],
    "wof:name":"Consolidated Optical Products",
    "wof:placetype":"venue"
},
  "geometry": {"coordinates":[-114.010490417,51.0646591187],"type":"Point"}
}