{
  "type": "Feature",
  "properties": {
    "addr:full":"Chester NS B0J 1J0",
    "addr:postcode":"b0j 1j0",
    "iso:country":"CA",
    "sg:city":"Chester",
    "sg:classifiers":[
        {
            "category":"Government",
            "subcategory":"Office",
            "type":"Public Place"
        }
    ],
    "sg:phone":"+1 902 275 3574",
    "sg:postcode":"B0J 1J0",
    "sg:province":"NS",
    "wof:name":"Nova Scotia Depots",
    "wof:placetype":"venue"
},
  "geometry": {"coordinates":[-64.241783,44.546276],"type":"Point"}
}