{
  "type": "Feature",
  "properties": {
    "addr:full":"1276 Rue Saint-Nicolas Laval QC H7E 4X3",
    "addr:housenumber":"1276",
    "addr:postcode":"h7e 4x3",
    "addr:street":"Rue Saint-Nicolas",
    "iso:country":"CA",
    "sg:address":"1276 Rue Saint-Nicolas",
    "sg:city":"Laval",
    "sg:classifiers":[
        {
            "category":"Wholesale",
            "subcategory":"Machinery & Supplies",
            "type":"Manufacturing & Wholesale Goods"
        }
    ],
    "sg:phone":"+1 450 661 0406",
    "sg:postcode":"H7E 4X3",
    "sg:province":"QC",
    "sg:tags":[
        "equipment",
        "irrigation",
        "system"
    ],
    "wof:name":"Systemes D'Irrigation Ideal",
    "wof:placetype":"venue"
},
  "geometry": {"coordinates":[-73.6705703735,45.6114501953],"type":"Point"}
}