{
  "type": "Feature",
  "properties": {
    "iso:country":"CA",
    "sg:city":"Montreal",
    "sg:classifiers":[
        {
            "category":"Social Services",
            "type":"Services"
        }
    ],
    "sg:phone":"+1 514 875 8882",
    "sg:postcode":"H2X 1N8",
    "sg:province":"QC",
    "sg:tags":[
        "employee",
        "assistance",
        "program"
    ],
    "wof:name":"Proact Pae Inc",
    "wof:placetype":"venue"
},
  "geometry": {"coordinates":[-73.5599441528,45.5110816956],"type":"Point"}
}