{
  "type": "Feature",
  "properties": {
    "addr:full":"165 Erie St Stratford ON N5A 2M6",
    "addr:housenumber":"165",
    "addr:postcode":"n5a 2m6",
    "addr:street":"Erie St",
    "iso:country":"CA",
    "sg:address":"165 Erie St",
    "sg:city":"Stratford",
    "sg:classifiers":[
        {
            "category":"Shopping",
            "type":"Retail Goods"
        }
    ],
    "sg:phone":"+1 519 271 9641",
    "sg:postcode":"N5A 2M6",
    "sg:province":"ON",
    "sg:tags":[
        "art",
        "gallery",
        "dealer"
    ],
    "wof:name":"Baynard & Nye Studio",
    "wof:placetype":"venue"
},
  "geometry": {"coordinates":[-80.9853210449,43.3682174683],"type":"Point"}
}