{
  "type": "Feature",
  "properties": {
    "iso:country":"CA",
    "sg:city":"Montreal",
    "sg:classifiers":[
        {
            "category":"Personal",
            "type":"Services"
        }
    ],
    "sg:phone":"+1 514 527 2666",
    "sg:postcode":"H2H 2S5",
    "sg:province":"QC",
    "sg:tags":[
        "school",
        "therapist",
        "massage"
    ],
    "wof:name":"Guijek Institut Quebecois",
    "wof:placetype":"venue"
},
  "geometry": {"coordinates":[-73.58223,45.539967],"type":"Point"}
}