{
  "type": "Feature",
  "properties": {
    "addr:full":"Richmond BC V6X 3Z9",
    "addr:postcode":"v6x 3z9",
    "iso:country":"CA",
    "sg:city":"Richmond",
    "sg:classifiers":[
        {
            "category":"Manufacturing",
            "subcategory":"Lumber",
            "type":"Manufacturing & Wholesale Goods"
        }
    ],
    "sg:phone":"+1 604 207 2138",
    "sg:postcode":"V6X 3Z9",
    "sg:province":"BC",
    "sg:tags":[
        "ginseng"
    ],
    "wof:name":"Nutra Ginseng Ltd",
    "wof:placetype":"venue"
},
  "geometry": {"coordinates":[-123.128304,49.185127],"type":"Point"}
}