{
  "type": "Feature",
  "properties": {
    "addr:full":"Vancouver BC V5K 1Z2",
    "addr:postcode":"v5k 1z2",
    "iso:country":"CA",
    "sg:city":"Vancouver",
    "sg:classifiers":[
        {
            "category":"Professional",
            "subcategory":"Lawyer & Legal Services",
            "type":"Services"
        }
    ],
    "sg:phone":"+1 604 257 3588",
    "sg:postcode":"V5K 1Z2",
    "sg:province":"BC",
    "sg:tags":[
        "attorney"
    ],
    "wof:name":"Lundrie's Law Office",
    "wof:placetype":"venue"
},
  "geometry": {"coordinates":[-123.052223,49.2813],"type":"Point"}
}