{
  "type": "Feature",
  "properties": {
    "addr:full":"150 Main St E Hamilton ON L8N 3W9",
    "addr:housenumber":"150",
    "addr:postcode":"l8n 3w9",
    "addr:street":"Main St E",
    "iso:country":"CA",
    "sg:address":"150 Main St E",
    "sg:city":"Hamilton",
    "sg:classifiers":[
        {
            "category":"Professional",
            "subcategory":"Advertising",
            "type":"Services"
        }
    ],
    "sg:phone":"+1 905 547 1675",
    "sg:postcode":"L8N 3W9",
    "sg:province":"ON",
    "sg:tags":[
        "equipment",
        "distribution",
        "supply"
    ],
    "wof:name":"P & A Plastics Inc",
    "wof:placetype":"venue"
},
  "geometry": {"coordinates":[-79.8639221191,43.2538070679],"type":"Point"}
}