{
  "type": "Feature",
  "properties": {
    "addr:full":"North Bay ON P1B 1B6",
    "addr:postcode":"p1b 1b6",
    "iso:country":"CA",
    "sg:city":"North Bay",
    "sg:classifiers":[
        {
            "category":"Travel",
            "subcategory":"Travel Agent",
            "type":"Entertainment"
        }
    ],
    "sg:phone":"+1 705 476 1211",
    "sg:postcode":"P1B 1B6",
    "sg:province":"ON",
    "sg:tags":[
        "agency",
        "bureau"
    ],
    "wof:name":"Goliger's Travel Svc",
    "wof:placetype":"venue"
},
  "geometry": {"coordinates":[-79.4596939087,46.3053588867],"type":"Point"}
}