{
  "type": "Feature",
  "properties": {
    "addr:full":"North York ON M2P 2B5",
    "addr:postcode":"m2p 2b5",
    "iso:country":"CA",
    "sg:city":"North York",
    "sg:classifiers":[
        {
            "category":"Shopping",
            "subcategory":"Discount & Variety Stores",
            "type":"Retail Goods"
        }
    ],
    "sg:phone":"+1 416 250 9711",
    "sg:postcode":"M2P 2B5",
    "sg:province":"ON",
    "wof:name":"Gateway Newstand",
    "wof:placetype":"venue"
},
  "geometry": {"coordinates":[-79.4079818726,43.7462501526],"type":"Point"}
}