{
  "type": "Feature",
  "properties": {
    "addr:full":"1134 Av Des Bouleaux Plessisville QC G6L 3B7",
    "addr:housenumber":"1134",
    "addr:postcode":"g6l 3b7",
    "addr:street":"Av Des Bouleaux",
    "iso:country":"CA",
    "sg:address":"1134 Av Des Bouleaux",
    "sg:city":"Plessisville",
    "sg:classifiers":[
        {
            "category":"Education",
            "subcategory":"Special Training",
            "type":"Public Place"
        }
    ],
    "sg:phone":"+1 819 362 2523",
    "sg:postcode":"G6L 3B7",
    "sg:province":"QC",
    "sg:tags":[
        "instruction",
        "driving"
    ],
    "wof:name":"Roubec Camions Ecole Pierre",
    "wof:placetype":"venue"
},
  "geometry": {"coordinates":[-71.764465,46.215694],"type":"Point"}
}