{
  "type": "Feature",
  "properties": {
    "addr:full":"876 Kingston Mills Rd Kingston ON K7L 4V3",
    "addr:housenumber":"876",
    "addr:postcode":"k7l 4v3",
    "addr:street":"Kingston Mills Rd",
    "iso:country":"CA",
    "sg:address":"876 Kingston Mills Rd",
    "sg:city":"Kingston",
    "sg:classifiers":[
        {
            "category":"Building & Trades",
            "subcategory":"Construction",
            "type":"Services"
        }
    ],
    "sg:phone":"+1 613 549 3345",
    "sg:postcode":"K7L 4V3",
    "sg:province":"ON",
    "sg:tags":[
        "excavating",
        "contractor"
    ],
    "wof:name":"Brian Cooper Excavating",
    "wof:placetype":"venue"
},
  "geometry": {"coordinates":[-76.461578,44.288422],"type":"Point"}
}