{
  "type": "Feature",
  "properties": {
    "addr:full":"5126 50 St St Paul AB T0A 3A1",
    "addr:housenumber":"5126",
    "addr:postcode":"t0a 3a1",
    "addr:street":"50 St",
    "iso:country":"CA",
    "sg:address":"5126 50 St",
    "sg:city":"St Paul",
    "sg:classifiers":[
        {
            "category":"Government",
            "subcategory":"Office",
            "type":"Public Place"
        }
    ],
    "sg:phone":"+1 780 645 6473",
    "sg:postcode":"T0A 3A1",
    "sg:province":"AB",
    "wof:name":"Alberta Service Ctr",
    "wof:placetype":"venue"
},
  "geometry": {"coordinates":[-111.297195,53.992619],"type":"Point"}
}