{
  "type": "Feature",
  "properties": {
    "addr:full":"Scarborough ON M1J 3N6",
    "addr:postcode":"m1j 3n6",
    "iso:country":"CA",
    "sg:city":"Scarborough",
    "sg:classifiers":[
        {
            "category":"Utilities",
            "subcategory":"Refuse",
            "type":"Services"
        }
    ],
    "sg:phone":"+1 416 261 0800",
    "sg:postcode":"M1J 3N6",
    "sg:province":"ON",
    "sg:tags":[
        "equipment",
        "recycling",
        "system"
    ],
    "wof:name":"Waste Warrior Products",
    "wof:placetype":"venue"
},
  "geometry": {"coordinates":[-79.213776,43.744251],"type":"Point"}
}