{
  "type": "Feature",
  "properties": {
    "addr:full":"198 New Toronto St Etobicoke ON M8V 2E8",
    "addr:housenumber":"198",
    "addr:postcode":"m8v 2e8",
    "addr:street":"New;St",
    "iso:country":"CA",
    "sg:address":"198 New Toronto St",
    "sg:city":"Etobicoke",
    "sg:classifiers":[
        {
            "category":"Manufacturing",
            "subcategory":"Food",
            "type":"Manufacturing & Wholesale Goods"
        }
    ],
    "sg:phone":"+1 416 252 9431",
    "sg:postcode":"M8V 2E8",
    "sg:province":"ON",
    "sg:tags":[
        "refiner",
        "sugar"
    ],
    "wof:name":"Lantic Sugar Ltd",
    "wof:placetype":"venue"
},
  "geometry": {"coordinates":[-79.50432600000001,43.607391],"type":"Point"}
}