{
  "type": "Feature",
  "properties": {
    "addr:full":"Highway 93 & 95 Windermere BC V0B 2L0",
    "addr:postcode":"bc v0b 2l0",
    "addr:street":"Highway 93 & 95",
    "iso:country":"CA",
    "sg:address":"Highway 93 & 95",
    "sg:city":"Windermere",
    "sg:classifiers":[
        {
            "category":"Sports & Exercise",
            "subcategory":"Bowling",
            "type":"Entertainment"
        }
    ],
    "sg:phone":"+1 250 342 2695",
    "sg:postcode":"V0B 2L0",
    "sg:province":"BC",
    "sg:tags":[
        "center"
    ],
    "wof:name":"Valley Alley Bowling Ctr",
    "wof:placetype":"venue"
},
  "geometry": {"coordinates":[-115.97554,50.465599],"type":"Point"}
}