{
  "type": "Feature",
  "properties": {
    "addr:full":"140 Freshwater Rd St. John's NL A1C 2N9",
    "addr:housenumber":"140",
    "addr:postcode":"a1c 2n9",
    "addr:street":"Freshwater Rd",
    "iso:country":"CA",
    "sg:address":"140 Freshwater Rd",
    "sg:city":"St. John's",
    "sg:classifiers":[
        {
            "category":"Restaurant",
            "type":"Food & Drink"
        }
    ],
    "sg:phone":"+1 709 579 1299",
    "sg:postcode":"A1C 2N9",
    "sg:province":"NL",
    "wof:name":"Mary Brown's Fried Chicken",
    "wof:placetype":"venue"
},
  "geometry": {"coordinates":[-52.725559,47.563351],"type":"Point"}
}