{
  "type": "Feature",
  "properties": {
    "addr:full":"4177 Boul Saint-Laurent Montreal QC H2W 1Y7",
    "addr:housenumber":4177,
    "addr:postcode":"h2w 1y7",
    "addr:street":"Boul Saint-Laurent",
    "iso:country":"CA",
    "sg:address":"4177 Boul Saint-Laurent",
    "sg:city":"Montreal",
    "sg:classifiers":[
        {
            "category":"Restaurant",
            "type":"Food & Drink"
        }
    ],
    "sg:phone":"+1 514 844 0216",
    "sg:postcode":"H2W 1Y7",
    "sg:province":"QC",
    "wof:name":"Patati Patata",
    "wof:placetype":"venue"
},
  "geometry": {"coordinates":[-73.58143699999999,45.51806],"type":"Point"}
}