{
  "type": "Feature",
  "properties": {
    "iso:country":"CA",
    "sg:address":"7835 Confederation Line",
    "sg:city":"Watford",
    "sg:classifiers":[
        {
            "category":"Health Services",
            "subcategory":"Nursing And Care Facility",
            "type":"Services"
        }
    ],
    "sg:phone":"+1 519 876 3452",
    "sg:postcode":"N0M 2S0",
    "sg:province":"ON",
    "sg:tags":[
        "home",
        "retirement",
        "community"
    ],
    "wof:name":"Brookside Retirement",
    "wof:placetype":"venue"
},
  "geometry": {"coordinates":[-81.8832702637,42.9554481506],"type":"Point"}
}