{
  "type": "Feature",
  "properties": {
    "addr:full":"1900 Boul Mellon Jonquiere QC G7S 3H4",
    "addr:housenumber":"1900",
    "addr:postcode":"g7s 3h4",
    "addr:street":"Boul Mellon",
    "iso:country":"CA",
    "sg:address":"1900 Boul Mellon",
    "sg:city":"Jonquiere",
    "sg:classifiers":[
        {
            "category":"Recreation",
            "type":"Entertainment"
        }
    ],
    "sg:phone":"+1 418 548 0130",
    "sg:postcode":"G7S 3H4",
    "sg:province":"QC",
    "sg:tags":[
        "ticket"
    ],
    "wof:name":"Quebes-Issime",
    "wof:placetype":"venue"
},
  "geometry": {"coordinates":[-71.182098,48.427338],"type":"Point"}
}