{
  "type": "Feature",
  "properties": {
    "addr:full":"5627 55 St SE Calgary AB T2C 4R4",
    "addr:housenumber":"5627",
    "addr:postcode":"t2c 4r4",
    "addr:street":"55 St Se",
    "iso:country":"CA",
    "sg:address":"5627 55 St SE",
    "sg:city":"Calgary",
    "sg:classifiers":[
        {
            "category":"Freight",
            "type":"Transportation"
        }
    ],
    "sg:phone":"+1 403 720 8233",
    "sg:postcode":"T2C 4R4",
    "sg:province":"AB",
    "sg:tags":[
        "trucking"
    ],
    "wof:name":"Ricardo Tractor Svc Ltd",
    "wof:placetype":"venue"
},
  "geometry": {"coordinates":[-113.951256,51.002724],"type":"Point"}
}