{
  "type": "Feature",
  "properties": {
    "addr:full":"12160 Horseshoe Way Richmond BC V7A 4V5",
    "addr:housenumber":"12160",
    "addr:postcode":"v7a 4v5",
    "addr:street":"Horseshoe Way",
    "iso:country":"CA",
    "sg:address":"12160 Horseshoe Way",
    "sg:city":"Richmond",
    "sg:classifiers":[
        {
            "category":"Food & Beverages",
            "subcategory":"Fruits & Vegetables",
            "type":"Retail Goods"
        }
    ],
    "sg:phone":"+1 604 271 9797",
    "sg:postcode":"V7A 4V5",
    "sg:province":"BC",
    "wof:name":"Central Foods CO Ltd",
    "wof:placetype":"venue"
},
  "geometry": {"coordinates":[-123.09925800000001,49.12495],"type":"Point"}
}