{
  "type": "Feature",
  "properties": {
    "addr:full":"810 Selkirk Ave Winnipeg MB R2X 0B7",
    "addr:housenumber":"810",
    "addr:postcode":"r2x 0b7",
    "addr:street":"Selkirk Ave",
    "iso:country":"CA",
    "sg:address":"810 Selkirk Ave",
    "sg:city":"Winnipeg",
    "sg:classifiers":[
        {
            "category":"Food & Beverages",
            "subcategory":"Groceries & Convenience Stores",
            "type":"Retail Goods"
        }
    ],
    "sg:phone":"+1 204 582 7355",
    "sg:postcode":"R2X 0B7",
    "sg:province":"MB",
    "wof:name":"Mac's Convenience Stores Ltd",
    "wof:placetype":"venue"
},
  "geometry": {"coordinates":[-97.1568527222,49.9193305969],"type":"Point"}
}