{
  "type": "Feature",
  "properties": {
    "iso:country":"CA",
    "sg:address":"98 Gerrish St",
    "sg:city":"Windsor",
    "sg:classifiers":[
        {
            "category":"Professional",
            "subcategory":"Lawyer & Legal Services",
            "type":"Services"
        }
    ],
    "sg:phone":"+1 902 798 5997",
    "sg:postcode":"B0N 2T0",
    "sg:province":"NS",
    "sg:tags":[
        "attorney"
    ],
    "wof:name":"Bowes, Debbie",
    "wof:placetype":"venue"
},
  "geometry": {"coordinates":[-64.1326751709,44.9923667908],"type":"Point"}
}