{
  "type": "Feature",
  "properties": {
    "iso:country":"CA",
    "sg:address":"205 Arena Ave",
    "sg:city":"Trochu",
    "sg:classifiers":[
        {
            "category":"Wholesale",
            "subcategory":"Scrap",
            "type":"Manufacturing & Wholesale Goods"
        }
    ],
    "sg:phone":"+1 403 442 2008",
    "sg:postcode":"T0M 2C0",
    "sg:province":"AB",
    "sg:tags":[
        "recycling",
        "can",
        "bottle",
        "depot"
    ],
    "wof:name":"Trochu Bottle Depot",
    "wof:placetype":"venue"
},
  "geometry": {"coordinates":[-113.22903442400001,51.8248252869],"type":"Point"}
}