{
  "type": "Feature",
  "properties": {
    "addr:full":"8440 112 St NW Edmonton AB T6G 2B7",
    "addr:housenumber":"8440",
    "addr:postcode":"t6g 2b7",
    "addr:street":"112 St Nw",
    "iso:country":"CA",
    "sg:address":"8440 112 St NW",
    "sg:city":"Edmonton",
    "sg:classifiers":[
        {
            "category":"Health Services",
            "subcategory":"Hospital",
            "type":"Services"
        }
    ],
    "sg:phone":"+1 780 407 1000",
    "sg:postcode":"T6G 2B7",
    "sg:province":"AB",
    "wof:name":"Capital Health Corporate Ofc",
    "wof:placetype":"venue"
},
  "geometry": {"coordinates":[-113.521072,53.520458],"type":"Point"}
}