{
  "type": "Feature",
  "properties": {
    "addr:full":"372 Midland Ave Midland ON L4R 3K7",
    "addr:housenumber":"372",
    "addr:postcode":"l4r 3k7",
    "addr:street":"Midland Ave",
    "iso:country":"CA",
    "sg:address":"372 Midland Ave",
    "sg:city":"Midland",
    "sg:classifiers":[
        {
            "category":"Health Services",
            "subcategory":"Doctor",
            "type":"Services"
        }
    ],
    "sg:phone":"+1 705 527 7744",
    "sg:postcode":"L4R 3K7",
    "sg:province":"ON",
    "sg:tags":[
        "ophthalmologist"
    ],
    "wof:name":"Scanlan, Daniel MD",
    "wof:placetype":"venue"
},
  "geometry": {"coordinates":[-79.881942749,44.7479057312],"type":"Point"}
}