{
  "type": "Feature",
  "properties": {
    "addr:full":"42 Ebert Ave Red Deer AB T4R 2H8",
    "addr:housenumber":"42",
    "addr:postcode":"t4r 2h8",
    "addr:street":"Ebert Ave",
    "iso:country":"CA",
    "sg:address":"42 Ebert Ave",
    "sg:city":"Red Deer",
    "sg:classifiers":[
        {
            "category":"Wholesale",
            "subcategory":"Machinery & Supplies",
            "type":"Manufacturing & Wholesale Goods"
        }
    ],
    "sg:phone":"+1 403 357 1228",
    "sg:postcode":"T4R 2H8",
    "sg:province":"AB",
    "sg:tags":[
        "crane",
        "derrick"
    ],
    "wof:name":"Direct Crane Svc Ltd",
    "wof:placetype":"venue"
},
  "geometry": {"coordinates":[-113.77796936,52.2643661499],"type":"Point"}
}