{
  "type": "Feature",
  "properties": {
    "addr:full":"Calgary AB T2C 2X3",
    "addr:postcode":"t2c 2x3",
    "iso:country":"CA",
    "sg:city":"Calgary",
    "sg:classifiers":[
        {
            "category":"Professional",
            "type":"Services"
        }
    ],
    "sg:phone":"+1 403 203 0606",
    "sg:postcode":"T2C 2X3",
    "sg:province":"AB",
    "sg:tags":[
        "geophysical"
    ],
    "wof:name":"Kozun Exploration Svc Ltd",
    "wof:placetype":"venue"
},
  "geometry": {"coordinates":[-113.960166931,50.9805603027],"type":"Point"}
}