{
  "type": "Feature",
  "properties": {
    "addr:full":"1050 Boul Du Seminaire N Saint-Jean-Sur-Richelieu QC J3A 1S7",
    "addr:housenumber":"1050",
    "addr:postcode":"j3a 1s7",
    "addr:street":"Boul Du Seminaire N",
    "iso:country":"CA",
    "sg:address":"1050 Boul Du Seminaire N",
    "sg:city":"Saint-Jean-Sur-Richelieu",
    "sg:classifiers":[
        {
            "category":"Home & Garden",
            "subcategory":"Home Furnishings",
            "type":"Retail Goods"
        }
    ],
    "sg:phone":"+1 450 348 0990",
    "sg:postcode":"J3A 1S7",
    "sg:province":"QC",
    "sg:tags":[
        "window",
        "covering"
    ],
    "wof:name":"Marche Du Store",
    "wof:placetype":"venue"
},
  "geometry": {"coordinates":[-73.268456,45.338783],"type":"Point"}
}