{
  "type": "Feature",
  "properties": {
    "addr:full":"Airbase Pl Botwood NL A0H 1E0",
    "addr:postcode":"a0h 1e0",
    "addr:street":"Airbase Pl",
    "iso:country":"CA",
    "sg:address":"Airbase Pl",
    "sg:city":"Botwood",
    "sg:classifiers":[
        {
            "category":"Museum",
            "type":"Entertainment"
        }
    ],
    "sg:phone":"+1 709 257 4612",
    "sg:postcode":"A0H 1E0",
    "sg:province":"NL",
    "wof:name":"Botwood Heritage Museum",
    "wof:placetype":"venue"
},
  "geometry": {"coordinates":[-55.366905,49.130859],"type":"Point"}
}