{
  "type": "Feature",
  "properties": {
    "addr:full":"3775 Bayridge Ave West Vancouver BC V7V 3J3",
    "addr:housenumber":"3775",
    "addr:postcode":"v7v 3j3",
    "addr:street":"Bayridge Ave",
    "iso:country":"CA",
    "sg:address":"3775 Bayridge Ave",
    "sg:city":"West Vancouver",
    "sg:classifiers":[
        {
            "category":"Professional",
            "subcategory":"Engineering",
            "type":"Services"
        }
    ],
    "sg:phone":"+1 604 926 5630",
    "sg:postcode":"V7V 3J3",
    "sg:province":"BC",
    "sg:tags":[
        "engineer"
    ],
    "wof:name":"Reg Davis & Assoc Ltd",
    "wof:placetype":"venue"
},
  "geometry": {"coordinates":[-123.22075700000001,49.343731],"type":"Point"}
}