{
  "type": "Feature",
  "properties": {
    "iso:country":"CA",
    "sg:address":"424 2E Av",
    "sg:city":"Iberville",
    "sg:classifiers":[
        {
            "category":"Shopping",
            "subcategory":"Clothing, Apparel, & Fashions",
            "type":"Retail Goods"
        }
    ],
    "sg:phone":"+1 450 346 1076",
    "sg:postcode":"J2X 2B8",
    "sg:province":"QC",
    "sg:tags":[
        "work",
        "uniform"
    ],
    "wof:name":"Vetements Mpd Inc",
    "wof:placetype":"venue"
},
  "geometry": {"coordinates":[-73.2291564941,45.3042602539],"type":"Point"}
}