{
  "type": "Feature",
  "properties": {
    "iso:country":"CA",
    "sg:address":"PO Box 10",
    "sg:city":"Repulse Bay",
    "sg:classifiers":[
        {
            "category":"Recreation",
            "type":"Entertainment"
        }
    ],
    "sg:phone":"+1 867 462 4097",
    "sg:postcode":"X0C 0H0",
    "sg:province":"NU",
    "sg:tags":[
        "skating",
        "arena",
        "rink",
        "athletic",
        "fields",
        "stadium"
    ],
    "wof:name":"Arena Maintainer",
    "wof:placetype":"venue"
},
  "geometry": {"coordinates":[-86.2357177734,66.5250701904],"type":"Point"}
}