{
  "type": "Feature",
  "properties": {
    "addr:full":"30 Church St Grand Bank NL A0E 1W0",
    "addr:housenumber":"30",
    "addr:postcode":"a0e 1w0",
    "addr:street":"Church St",
    "iso:country":"CA",
    "sg:address":"30 Church St",
    "sg:city":"Grand Bank",
    "sg:classifiers":[
        {
            "category":"Health Services",
            "subcategory":"Doctor",
            "type":"Services"
        }
    ],
    "sg:phone":"+1 709 832 0550",
    "sg:postcode":"A0E 1W0",
    "sg:province":"NL",
    "sg:tags":[
        "dentist"
    ],
    "wof:name":"Grand Bank Dental",
    "wof:placetype":"venue"
},
  "geometry": {"coordinates":[-55.754471,47.101349],"type":"Point"}
}