{
  "type": "Feature",
  "properties": {
    "addr:full":"140 Kent St W Lindsay ON K9V 2Y4",
    "addr:housenumber":"140",
    "addr:postcode":"k9v 2y4",
    "addr:street":"Kent St W",
    "iso:country":"CA",
    "sg:address":"140 Kent St W",
    "sg:city":"Lindsay",
    "sg:classifiers":[
        {
            "category":"Restaurant",
            "type":"Food & Drink"
        }
    ],
    "sg:phone":"+1 705 324 8117",
    "sg:postcode":"K9V 2Y4",
    "sg:province":"ON",
    "wof:name":"Pita Pantry",
    "wof:placetype":"venue"
},
  "geometry": {"coordinates":[-78.738495,44.354794],"type":"Point"}
}