{
  "type": "Feature",
  "properties": {
    "addr:full":"8627 91 St NW Edmonton AB T6C 3N1",
    "addr:housenumber":"8627",
    "addr:postcode":"t6c 3n1",
    "addr:street":"91 St Nw",
    "iso:country":"CA",
    "sg:address":"8627 91 St NW",
    "sg:city":"Edmonton",
    "sg:classifiers":[
        {
            "category":"Organizations",
            "subcategory":"Professional Association",
            "type":"Services"
        }
    ],
    "sg:phone":"+1 780 468 6934",
    "sg:postcode":"T6C 3N1",
    "sg:province":"AB",
    "wof:name":"Federation Des Parents",
    "wof:placetype":"venue"
},
  "geometry": {"coordinates":[-113.467201,53.522106],"type":"Point"}
}