{
  "type": "Feature",
  "properties": {
    "addr:full":"98 Regina St N Waterloo ON N2J 3A9",
    "addr:housenumber":"98",
    "addr:postcode":"n2j 3a9",
    "addr:street":"Regina St N",
    "iso:country":"CA",
    "sg:address":"98 Regina St N",
    "sg:city":"Waterloo",
    "sg:classifiers":[
        {
            "category":"Building & Trades",
            "subcategory":"Electrical",
            "type":"Services"
        }
    ],
    "sg:phone":"+1 519 885 5030",
    "sg:postcode":"N2J 3A9",
    "sg:province":"ON",
    "sg:tags":[
        "electric",
        "contractor"
    ],
    "wof:name":"B J Electric",
    "wof:placetype":"venue"
},
  "geometry": {"coordinates":[-80.52243,43.470768],"type":"Point"}
}