{
  "type": "Feature",
  "properties": {
    "addr:full":"5606 48 Ave Camrose AB T4V 0K1",
    "addr:housenumber":"5606",
    "addr:postcode":"t4v 0k1",
    "addr:street":"48 Ave",
    "iso:country":"CA",
    "sg:address":"5606 48 Ave",
    "sg:city":"Camrose",
    "sg:classifiers":[
        {
            "category":"Restaurant",
            "type":"Food & Drink"
        }
    ],
    "sg:phone":"+1 780 672 7252",
    "sg:postcode":"T4V 0K1",
    "sg:province":"AB",
    "wof:name":"Humpty's Family Restaurant",
    "wof:placetype":"venue"
},
  "geometry": {"coordinates":[-112.835983,53.018169],"type":"Point"}
}