{
  "type": "Feature",
  "properties": {
    "addr:full":"198 Fairbank Ave York ON M6B 4C5",
    "addr:housenumber":"198",
    "addr:postcode":"m6b 4c5",
    "addr:street":"Fairbank Ave",
    "iso:country":"CA",
    "sg:address":"198 Fairbank Ave",
    "sg:city":"York",
    "sg:classifiers":[
        {
            "category":"Home & Garden",
            "subcategory":"Furniture",
            "type":"Retail Goods"
        }
    ],
    "sg:phone":"+1 416 784 9777",
    "sg:postcode":"M6B 4C5",
    "sg:province":"ON",
    "sg:tags":[
        "rubber",
        "mattress"
    ],
    "wof:name":"Foamco Industries Corp",
    "wof:placetype":"venue"
},
  "geometry": {"coordinates":[-79.45491,43.699951],"type":"Point"}
}