{
  "type": "Feature",
  "properties": {
    "addr:full":"980 52A St Delta BC V4M 3A4",
    "addr:housenumber":"52a st",
    "addr:postcode":"v4m 3a4",
    "addr:street":"980",
    "iso:country":"CA",
    "sg:address":"980 52A St",
    "sg:city":"Delta",
    "sg:classifiers":[
        {
            "category":"Building & Trades",
            "subcategory":"Construction",
            "type":"Services"
        }
    ],
    "sg:phone":"+1 604 943 6113",
    "sg:postcode":"V4M 3A4",
    "sg:province":"BC",
    "sg:tags":[
        "roofing",
        "contractor"
    ],
    "wof:name":"Wolf's Roofing Ltd",
    "wof:placetype":"venue"
},
  "geometry": {"coordinates":[-123.05961600000001,49.084801],"type":"Point"}
}