{
  "type": "Feature",
  "properties": {
    "iso:country":"CA",
    "sg:address":"5315 Wilderness Trail",
    "sg:city":"Mississauga",
    "sg:classifiers":[
        {
            "category":"Professional",
            "subcategory":"Art Services",
            "type":"Services"
        }
    ],
    "sg:phone":"+1 905 568 7240",
    "sg:postcode":"L4Z 4E3",
    "sg:province":"ON",
    "sg:tags":[
        "graphic",
        "designer"
    ],
    "wof:name":"A M Graphics",
    "wof:placetype":"venue"
},
  "geometry": {"coordinates":[-79.65023040769999,43.6229629517],"type":"Point"}
}