{
  "type": "Feature",
  "properties": {
    "addr:full":"365 Hollywood Ave North York ON M2N 3L3",
    "addr:housenumber":"365",
    "addr:postcode":"m2n 3l3",
    "addr:street":"Hollywood Ave",
    "iso:country":"CA",
    "sg:address":"365 Hollywood Ave",
    "sg:city":"North York",
    "sg:classifiers":[
        {
            "category":"Professional",
            "subcategory":"Accounting & Tax Preparation",
            "type":"Services"
        }
    ],
    "sg:phone":"+1 416 225 2729",
    "sg:postcode":"M2N 3L3",
    "sg:province":"ON",
    "sg:tags":[
        "accountant"
    ],
    "wof:name":"Howes, Alan G CA",
    "wof:placetype":"venue"
},
  "geometry": {"coordinates":[-79.39152526860001,43.7700271606],"type":"Point"}
}