{
  "type": "Feature",
  "properties": {
    "addr:full":"32 Rockland Dr Mcadam NB E6J 1V4",
    "addr:housenumber":"32",
    "addr:postcode":"e6j 1v4",
    "addr:street":"Rockland Dr",
    "iso:country":"CA",
    "sg:address":"32 Rockland Dr",
    "sg:city":"Mcadam",
    "sg:classifiers":[
        {
            "category":"Organizations",
            "subcategory":"Religious Organization",
            "type":"Services"
        }
    ],
    "sg:phone":"+1 506 784 2446",
    "sg:postcode":"E6J 1V4",
    "sg:province":"NB",
    "sg:tags":[
        "church"
    ],
    "wof:name":"United Baptist Church",
    "wof:placetype":"venue"
},
  "geometry": {"coordinates":[-67.3296966553,45.5922927856],"type":"Point"}
}