{
  "type": "Feature",
  "properties": {
    "addr:full":"Toronto ON M5J 2R8",
    "addr:postcode":"m5j 2r8",
    "iso:country":"CA",
    "sg:city":"Toronto",
    "sg:classifiers":[
        {
            "category":"Shopping",
            "subcategory":"News",
            "type":"Retail Goods"
        }
    ],
    "sg:phone":"+1 416 368 8552",
    "sg:postcode":"M5J 2R8",
    "sg:province":"ON",
    "sg:tags":[
        "magazine"
    ],
    "wof:name":"International News Plus",
    "wof:placetype":"venue"
},
  "geometry": {"coordinates":[-79.377274,43.641499],"type":"Point"}
}