{
  "type": "Feature",
  "properties": {
    "iso:country":"CA",
    "sg:address":"184 Rue Paradis",
    "sg:city":"Rosemere",
    "sg:classifiers":[
        {
            "category":"Manufacturing",
            "subcategory":"Tools & Machinery",
            "type":"Manufacturing & Wholesale Goods"
        }
    ],
    "sg:phone":"+1 450 621 1422",
    "sg:postcode":"J7A 3N2",
    "sg:province":"QC",
    "sg:tags":[
        "system",
        "automation",
        "electric",
        "contractor"
    ],
    "wof:name":"Entrepreneur En Electricite",
    "wof:placetype":"venue"
},
  "geometry": {"coordinates":[-73.782097,45.643864],"type":"Point"}
}