{
  "type": "Feature",
  "properties": {
    "addr:full":"50 Front St N Thorold ON L2V 1X5",
    "addr:housenumber":"50",
    "addr:postcode":"l2v 1x5",
    "addr:street":"Front St N",
    "iso:country":"CA",
    "sg:address":"50 Front St N",
    "sg:city":"Thorold",
    "sg:classifiers":[
        {
            "category":"Shopping",
            "subcategory":"Florist",
            "type":"Retail Goods"
        }
    ],
    "sg:phone":"+1 905 227 4051",
    "sg:postcode":"L2V 1X5",
    "sg:province":"ON",
    "wof:name":"A Yellow Flower Basket",
    "wof:placetype":"venue"
},
  "geometry": {"coordinates":[-79.20064499999999,43.126625],"type":"Point"}
}