{
  "type": "Feature",
  "properties": {
    "addr:full":"Mississauga ON L5L 5V8",
    "addr:postcode":"l5l 5v8",
    "iso:country":"CA",
    "sg:city":"Mississauga",
    "sg:classifiers":[
        {
            "category":"Retail",
            "subcategory":"Repair Shop",
            "type":"Services"
        }
    ],
    "sg:phone":"+1 905 608 1373",
    "sg:postcode":"L5L 5V8",
    "sg:province":"ON",
    "sg:tags":[
        "leather",
        "cleaning"
    ],
    "wof:name":"Masters Garment Care",
    "wof:placetype":"venue"
},
  "geometry": {"coordinates":[-79.68495900000001,43.519867],"type":"Point"}
}