{
  "type": "Feature",
  "properties": {
    "iso:country":"CA",
    "sg:address":"1 1/2 Birchmount Rd",
    "sg:city":"Scarborough",
    "sg:classifiers":[
        {
            "category":"Building & Trades",
            "subcategory":"Pest Control",
            "type":"Services"
        }
    ],
    "sg:phone":"+1 416 690 0407",
    "sg:postcode":"M1N 3J3",
    "sg:province":"ON",
    "sg:tags":[
        "repellent",
        "bird",
        "barrier"
    ],
    "wof:name":"Pigeon Guard",
    "wof:placetype":"venue"
},
  "geometry": {"coordinates":[-79.261536,43.6912],"type":"Point"}
}