{
  "type": "Feature",
  "properties": {
    "iso:country":"CA",
    "sg:city":"North Vancouver",
    "sg:classifiers":[
        {
            "category":"Wholesale",
            "subcategory":"Stationery",
            "type":"Manufacturing & Wholesale Goods"
        }
    ],
    "sg:phone":"+1 604 980 5646",
    "sg:postcode":"V7M 1R9",
    "sg:province":"BC",
    "sg:tags":[
        "system",
        "business",
        "form",
        "furniture"
    ],
    "wof:name":"West-Can Office Furn & Supls",
    "wof:placetype":"venue"
},
  "geometry": {"coordinates":[-123.073753357,49.3219528198],"type":"Point"}
}