{
  "type": "Feature",
  "properties": {
    "addr:full":"Spencerville ON K0E 1X0",
    "addr:postcode":"k0e 1x0",
    "iso:country":"CA",
    "sg:city":"Spencerville",
    "sg:classifiers":[
        {
            "category":"Retail",
            "subcategory":"Repair Shop",
            "type":"Services"
        }
    ],
    "sg:phone":"+1 613 658 5625",
    "sg:postcode":"K0E 1X0",
    "sg:province":"ON",
    "sg:tags":[
        "lock",
        "locksmith"
    ],
    "wof:name":"D & B Lock & Key Svc",
    "wof:placetype":"venue"
},
  "geometry": {"coordinates":[-75.5466842651,44.8430595398],"type":"Point"}
}