{
  "type": "Feature",
  "properties": {
    "iso:country":"CA",
    "sg:city":"Prescott",
    "sg:classifiers":[
        {
            "category":"Building & Trades",
            "subcategory":"Construction",
            "type":"Services"
        }
    ],
    "sg:phone":"+1 613 925 2056",
    "sg:postcode":"K0E 1T0",
    "sg:province":"ON",
    "sg:tags":[
        "general",
        "contractor"
    ],
    "wof:name":"D C Snelling Ltd",
    "wof:placetype":"venue"
},
  "geometry": {"coordinates":[-75.5154037476,44.7158622742],"type":"Point"}
}