{
  "type": "Feature",
  "properties": {
    "addr:full":"274 Rue Boivin Granby QC J2G 2K4",
    "addr:housenumber":"274",
    "addr:postcode":"j2g 2k4",
    "addr:street":"Rue Boivin",
    "iso:country":"CA",
    "sg:address":"274 Rue Boivin",
    "sg:city":"Granby",
    "sg:classifiers":[
        {
            "category":"Restaurant",
            "type":"Food & Drink"
        }
    ],
    "sg:phone":"+1 450 372 9058",
    "sg:postcode":"J2G 2K4",
    "sg:province":"QC",
    "sg:tags":[
        "delicatessen",
        "caterer"
    ],
    "wof:name":"Charcuterie France Enrg",
    "wof:placetype":"venue"
},
  "geometry": {"coordinates":[-72.72695899999999,45.404259],"type":"Point"}
}