{
  "type": "Feature",
  "properties": {
    "iso:country":"CA",
    "sg:address":"1220 Northwest Blvd",
    "sg:city":"Creston",
    "sg:classifiers":[
        {
            "category":"Home & Garden",
            "subcategory":"Building Materials",
            "type":"Retail Goods"
        }
    ],
    "sg:phone":"+1 250 428 7114",
    "sg:postcode":"V0B 1G6",
    "sg:province":"BC",
    "wof:name":"Pyramid Building Supplies Ltd",
    "wof:placetype":"venue"
},
  "geometry": {"coordinates":[-116.52331543,49.1083068848],"type":"Point"}
}