{
  "type": "Feature",
  "properties": {
    "addr:full":"280 College St Toronto ON M5T 1R9",
    "addr:housenumber":"280",
    "addr:postcode":"m5t 1r9",
    "addr:street":"College St",
    "iso:country":"CA",
    "sg:address":"280 College St",
    "sg:city":"Toronto",
    "sg:classifiers":[
        {
            "category":"Shopping",
            "subcategory":"Computers & Home Electronics",
            "type":"Retail Goods"
        }
    ],
    "sg:phone":"+1 416 324 9426",
    "sg:postcode":"M5T 1R9",
    "sg:province":"ON",
    "sg:tags":[
        "equipment",
        "dealer"
    ],
    "wof:name":"Aplus Computers",
    "wof:placetype":"venue"
},
  "geometry": {"coordinates":[-79.400986,43.657921],"type":"Point"}
}