{
  "type": "Feature",
  "properties": {
    "addr:full":"PO Box 170 Fosston SK S0E 0V0",
    "addr:housenumber":"po",
    "addr:postcode":"s0e 0v0",
    "addr:street":"Box 170",
    "iso:country":"CA",
    "sg:address":"PO Box 170",
    "sg:city":"Fosston",
    "sg:classifiers":[
        {
            "category":"Organizations",
            "subcategory":"Religious Organization",
            "type":"Services"
        }
    ],
    "sg:phone":"+1 306 322 4417",
    "sg:postcode":"S0E 0V0",
    "sg:province":"SK",
    "sg:tags":[
        "church"
    ],
    "wof:name":"Elim Evangelical Free Church",
    "wof:placetype":"venue"
},
  "geometry": {"coordinates":[-103.812477,52.193432],"type":"Point"}
}