{
  "type": "Feature",
  "properties": {
    "addr:full":"582 Rte 201 Saint-Clet QC J0P 1S0",
    "addr:housenumber":"582",
    "addr:postcode":"j0p 1s0",
    "addr:street":"Rte 201",
    "iso:country":"CA",
    "sg:address":"582 Rte 201",
    "sg:city":"Saint-Clet",
    "sg:classifiers":[
        {
            "category":"Social Services",
            "subcategory":"Child Care",
            "type":"Services"
        }
    ],
    "sg:phone":"+1 450 456 3300",
    "sg:postcode":"J0P 1S0",
    "sg:province":"QC",
    "wof:name":"Service Garde Des Schtroumpfes",
    "wof:placetype":"venue"
},
  "geometry": {"coordinates":[-74.222458,45.351017],"type":"Point"}
}