{
  "type": "Feature",
  "properties": {
    "addr:full":"3410 Rue Peel Montreal QC H3A 1W8",
    "addr:housenumber":"3410",
    "addr:postcode":"h3a 1w8",
    "addr:street":"Rue Peel",
    "iso:country":"CA",
    "sg:address":"3410 Rue Peel",
    "sg:city":"Montreal",
    "sg:classifiers":[
        {
            "category":"Real Estate",
            "subcategory":"Real Estate Agent",
            "type":"Services"
        }
    ],
    "sg:phone":"+1 514 286 5006",
    "sg:postcode":"H3A 1W8",
    "sg:province":"QC",
    "sg:tags":[
        "management"
    ],
    "wof:name":"Courtiers Gl Inc",
    "wof:placetype":"venue"
},
  "geometry": {"coordinates":[-73.57698059080001,45.5020103455],"type":"Point"}
}