{
  "type": "Feature",
  "properties": {
    "addr:full":"109 Pembroke St W Pembroke ON K8A 5M7",
    "addr:housenumber":"109",
    "addr:postcode":"k8a 5m7",
    "addr:street":"Pembroke St W",
    "iso:country":"CA",
    "sg:address":"109 Pembroke St W",
    "sg:city":"Pembroke",
    "sg:classifiers":[
        {
            "category":"Shopping",
            "subcategory":"Jewelry",
            "type":"Retail Goods"
        }
    ],
    "sg:phone":"+1 613 732 3163",
    "sg:postcode":"K8A 5M7",
    "sg:province":"ON",
    "sg:tags":[
        "jeweler"
    ],
    "wof:name":"Valley Goldsmith Inc",
    "wof:placetype":"venue"
},
  "geometry": {"coordinates":[-77.115234,45.825607],"type":"Point"}
}