{
  "type": "Feature",
  "properties": {
    "iso:country":"CA",
    "sg:city":"St Catharines",
    "sg:classifiers":[
        {
            "category":"Education",
            "subcategory":"School",
            "type":"Public Place"
        }
    ],
    "sg:phone":"+1 905 685 8141",
    "sg:postcode":"L2S 3P1",
    "sg:province":"ON",
    "sg:tags":[
        "tutoring"
    ],
    "wof:name":"Oxford Learning Ctr",
    "wof:placetype":"venue"
},
  "geometry": {"coordinates":[-79.260895,43.15617],"type":"Point"}
}