{
  "type": "Feature",
  "properties": {
    "addr:full":"9521 41 Ave NW Edmonton AB T6E 5X7",
    "addr:housenumber":"9521",
    "addr:postcode":"t6e 5x7",
    "addr:street":"41 Ave Nw",
    "iso:country":"CA",
    "sg:address":"9521 41 Ave NW",
    "sg:city":"Edmonton",
    "sg:classifiers":[
        {
            "category":"Wholesale",
            "subcategory":"Chemicals & Plastics",
            "type":"Manufacturing & Wholesale Goods"
        }
    ],
    "sg:phone":"+1 780 435 7700",
    "sg:postcode":"T6E 5X7",
    "sg:province":"AB",
    "wof:name":"Redwood Plastics Corp",
    "wof:placetype":"venue"
},
  "geometry": {"coordinates":[-113.47605896,53.4762458801],"type":"Point"}
}