{
  "type": "Feature",
  "properties": {
    "addr:full":"55 Harbour Sq # 100 Toronto ON M5J 2L1",
    "addr:housenumber":"55",
    "addr:postcode":"m5j 2l1",
    "addr:street":"Harbour Sq # 100",
    "iso:country":"CA",
    "sg:address":"55 Harbour Sq # 100",
    "sg:city":"Toronto",
    "sg:classifiers":[
        {
            "category":"Retail",
            "subcategory":"Laundry & Dry Cleaning",
            "type":"Services"
        }
    ],
    "sg:phone":"+1 416 363 7348",
    "sg:postcode":"M5J 2L1",
    "sg:province":"ON",
    "sg:tags":[
        "cleaners"
    ],
    "wof:name":"Windsor Valet",
    "wof:placetype":"venue"
},
  "geometry": {"coordinates":[-79.37893699999999,43.641399],"type":"Point"}
}