{
  "type": "Feature",
  "properties": {
    "iso:country":"CA",
    "sg:address":"674 St. George Blvd",
    "sg:city":"Moncton",
    "sg:classifiers":[
        {
            "category":"Home & Garden",
            "subcategory":"Building Materials",
            "type":"Retail Goods"
        }
    ],
    "sg:phone":"+1 506 857 4113",
    "sg:postcode":"E1E 2C6",
    "sg:province":"NB",
    "sg:tags":[
        "paint"
    ],
    "wof:name":"Glidden Ici Paint Ctr",
    "wof:placetype":"venue"
},
  "geometry": {"coordinates":[-64.8083572388,46.0854530334],"type":"Point"}
}