{
  "type": "Feature",
  "properties": {
    "addr:full":"1736 10 Ave SW Calgary AB T3C 0J8",
    "addr:housenumber":"1736",
    "addr:postcode":"t3c 0j8",
    "addr:street":"10 Ave Sw",
    "iso:country":"CA",
    "sg:address":"1736 10 Ave SW",
    "sg:city":"Calgary",
    "sg:classifiers":[
        {
            "category":"Organizations",
            "subcategory":"Religious Organization",
            "type":"Services"
        }
    ],
    "sg:phone":"+1 403 244 8812",
    "sg:postcode":"T3C 0J8",
    "sg:province":"AB",
    "sg:tags":[
        "church"
    ],
    "wof:name":"Jehovah's Witnessess Kingdom",
    "wof:placetype":"venue"
},
  "geometry": {"coordinates":[-114.100135803,51.0444908142],"type":"Point"}
}