{
  "type": "Feature",
  "properties": {
    "addr:full":"3695 Boul Saint-Jean Dollard-Des-Ormeaux QC H9G 1X2",
    "addr:housenumber":"3695",
    "addr:postcode":"h9g 1x2",
    "addr:street":"Boul Saint-Jean",
    "iso:country":"CA",
    "sg:address":"3695 Boul Saint-Jean",
    "sg:city":"Dollard-Des-Ormeaux",
    "sg:classifiers":[
        {
            "category":"Retail",
            "subcategory":"Laundry & Dry Cleaning",
            "type":"Services"
        }
    ],
    "sg:phone":"+1 514 626 7732",
    "sg:postcode":"H9G 1X2",
    "sg:province":"QC",
    "sg:tags":[
        "cleaners"
    ],
    "wof:name":"Nettoyeur Blue Haven Cleaners",
    "wof:placetype":"venue"
},
  "geometry": {"coordinates":[-73.83344268800001,45.4721412659],"type":"Point"}
}