{
  "type": "Feature",
  "properties": {
    "addr:full":"Calgary AB T2P 3T9",
    "addr:postcode":"t2p 3t9",
    "iso:country":"CA",
    "sg:city":"Calgary",
    "sg:classifiers":[
        {
            "category":"Shopping",
            "subcategory":"Bicycles & Sporting Goods",
            "type":"Retail Goods"
        }
    ],
    "sg:phone":"+1 403 262 2915",
    "sg:postcode":"T2P 3T9",
    "sg:province":"AB",
    "sg:tags":[
        "car",
        "golf",
        "cart"
    ],
    "wof:name":"Riksha Golf Inc",
    "wof:placetype":"venue"
},
  "geometry": {"coordinates":[-114.086410523,51.046333313],"type":"Point"}
}