{
  "type": "Feature",
  "properties": {
    "addr:full":"450 Rue DE LA Gare-Du-Palais Quebec QC G1K 3X2",
    "addr:housenumber":"450",
    "addr:postcode":"g1k 3x2",
    "addr:street":"Rue De La Gare-Du-Palais",
    "iso:country":"CA",
    "sg:address":"450 Rue DE LA Gare-Du-Palais",
    "sg:city":"Quebec",
    "sg:classifiers":[
        {
            "category":"Restaurant",
            "type":"Food & Drink"
        }
    ],
    "sg:phone":"+1 418 648 9992",
    "sg:postcode":"G1K 3X2",
    "sg:province":"QC",
    "wof:name":"Sul Posto Gare Du Palais",
    "wof:placetype":"venue"
},
  "geometry": {"coordinates":[-71.21307400000001,46.817554],"type":"Point"}
}