{
  "type": "Feature",
  "properties": {
    "iso:country":"CA",
    "sg:address":"10 Ross St",
    "sg:city":"Barrie",
    "sg:classifiers":[
        {
            "category":"Food & Beverages",
            "subcategory":"Bakery",
            "type":"Retail Goods"
        }
    ],
    "sg:phone":"+1 705 726 0121",
    "sg:postcode":"L4N 1E7",
    "sg:province":"ON",
    "sg:tags":[
        "baker"
    ],
    "wof:name":"Sigrid's Cafe & Fine Bakery",
    "wof:placetype":"venue"
},
  "geometry": {"coordinates":[-79.692245,44.390881],"type":"Point"}
}