{
  "type": "Feature",
  "properties": {
    "addr:full":"34616 99th St Oliver BC V0H 1T0",
    "addr:housenumber":"34616",
    "addr:postcode":"bc v0h 1t0",
    "addr:street":"99Th St",
    "iso:country":"CA",
    "sg:address":"34616 99th St",
    "sg:city":"Oliver",
    "sg:classifiers":[
        {
            "category":"Retail",
            "subcategory":"Funeral Services",
            "type":"Services"
        }
    ],
    "sg:phone":"+1 250 498 3833",
    "sg:postcode":"V0H 1T0",
    "sg:province":"BC",
    "sg:tags":[
        "director"
    ],
    "wof:name":"Graham Funeral Home Ltd",
    "wof:placetype":"venue"
},
  "geometry": {"coordinates":[-119.55278778100001,49.1784477234],"type":"Point"}
}