{
  "type": "Feature",
  "properties": {
    "addr:full":"33 Main St N Rossburn MB R0J 1V0",
    "addr:housenumber":"33",
    "addr:postcode":"r0j 1v0",
    "addr:street":"Main St N Rossburn",
    "iso:country":"CA",
    "sg:address":"33 Main St N",
    "sg:city":"Rossburn",
    "sg:classifiers":[
        {
            "category":"Shopping",
            "subcategory":"Catalog Store",
            "type":"Retail Goods"
        }
    ],
    "sg:phone":"+1 204 859 2506",
    "sg:postcode":"R0J 1V0",
    "sg:province":"MB",
    "sg:tags":[
        "mail",
        "order",
        "internet"
    ],
    "wof:name":"Sears Canada Inc",
    "wof:placetype":"venue"
},
  "geometry": {"coordinates":[-100.81082916299999,50.6689682007],"type":"Point"}
}