{
  "type": "Feature",
  "properties": {
    "addr:full":"9643 186 St Surrey BC V4N 3N8",
    "addr:housenumber":"9643",
    "addr:postcode":"v4n 3n8",
    "addr:street":"186 St",
    "iso:country":"CA",
    "sg:address":"9643 186 St",
    "sg:city":"Surrey",
    "sg:classifiers":[
        {
            "category":"Manufacturing",
            "subcategory":"Rubber & Plastics",
            "type":"Manufacturing & Wholesale Goods"
        }
    ],
    "sg:phone":"+1 604 888 1739",
    "sg:postcode":"V4N 3N8",
    "sg:province":"BC",
    "wof:name":"Plastec",
    "wof:placetype":"venue"
},
  "geometry": {"coordinates":[-122.707626,49.177765],"type":"Point"}
}