{
  "type": "Feature",
  "properties": {
    "addr:full":"20711 Bristol Slough Rd Hope BC V0X 1L2",
    "addr:housenumber":"20711",
    "addr:postcode":"v0x 1l2",
    "addr:street":"Bristol Slough Rd",
    "iso:country":"CA",
    "sg:address":"20711 Bristol Slough Rd",
    "sg:city":"Hope",
    "sg:classifiers":[
        {
            "category":"Wholesale",
            "subcategory":"Durable Goods & Equipment",
            "type":"Manufacturing & Wholesale Goods"
        }
    ],
    "sg:phone":"+1 604 869 7111",
    "sg:postcode":"V0X 1L2",
    "sg:province":"BC",
    "sg:tags":[
        "log",
        "broker"
    ],
    "wof:name":"International Forest Products",
    "wof:placetype":"venue"
},
  "geometry": {"coordinates":[-121.486320496,49.3730316162],"type":"Point"}
}