{
  "type": "Feature",
  "properties": {
    "addr:full":"165 Rue Lomas Sherbrooke QC J1J 2R2",
    "addr:housenumber":"165",
    "addr:postcode":"j1j 2r2",
    "addr:street":"Rue Lomas",
    "iso:country":"CA",
    "sg:address":"165 Rue Lomas",
    "sg:city":"Sherbrooke",
    "sg:classifiers":[
        {
            "category":"Health Services",
            "subcategory":"Clinic",
            "type":"Services"
        }
    ],
    "sg:phone":"+1 819 569 5558",
    "sg:postcode":"J1J 2R2",
    "sg:province":"QC",
    "sg:tags":[
        "psychotherapist",
        "holistic",
        "practitioner"
    ],
    "wof:name":"Cema Enr Celine Roy & Mario",
    "wof:placetype":"venue"
},
  "geometry": {"coordinates":[-71.930542,45.401276],"type":"Point"}
}