{
  "type": "Feature",
  "properties": {
    "addr:full":"8561 132 St Surrey BC V3W 4N8",
    "addr:housenumber":"8561",
    "addr:postcode":"v3w 4n8",
    "addr:street":"132 St",
    "iso:country":"CA",
    "sg:address":"8561 132 St",
    "sg:city":"Surrey",
    "sg:classifiers":[
        {
            "category":"Professional",
            "subcategory":"Accounting & Tax Preparation",
            "type":"Services"
        }
    ],
    "sg:phone":"+1 604 596 1114",
    "sg:postcode":"V3W 4N8",
    "sg:province":"BC",
    "sg:tags":[
        "accountant"
    ],
    "wof:name":"Lang & CO",
    "wof:placetype":"venue"
},
  "geometry": {"coordinates":[-122.856994629,49.1585731506],"type":"Point"}
}