{
  "type": "Feature",
  "properties": {
    "addr:full":"North York ON M3H 5X2",
    "addr:postcode":"m3h 5x2",
    "iso:country":"CA",
    "sg:city":"North York",
    "sg:classifiers":[
        {
            "category":"Retail",
            "subcategory":"Auto Repair",
            "type":"Services"
        }
    ],
    "sg:phone":"+1 416 667 0636",
    "sg:postcode":"M3H 5X2",
    "sg:province":"ON",
    "sg:tags":[
        "repairing",
        "automobile"
    ],
    "wof:name":"Columbus Auto Repair Ltd",
    "wof:placetype":"venue"
},
  "geometry": {"coordinates":[-79.467018,43.768482],"type":"Point"}
}