{
  "type": "Feature",
  "properties": {
    "addr:full":"Burnaby BC V5J 3N3",
    "addr:postcode":"v5j 3n3",
    "iso:country":"CA",
    "sg:city":"Burnaby",
    "sg:classifiers":[
        {
            "category":"Wholesale",
            "subcategory":"Plants",
            "type":"Manufacturing & Wholesale Goods"
        }
    ],
    "sg:phone":"+1 604 430 1575",
    "sg:postcode":"V5J 3N3",
    "sg:province":"BC",
    "sg:tags":[
        "florist"
    ],
    "wof:name":"North West Wholesale Florist",
    "wof:placetype":"venue"
},
  "geometry": {"coordinates":[-123.014968872,49.2072219849],"type":"Point"}
}