{
  "type": "Feature",
  "properties": {
    "iso:country":"CA",
    "sg:address":"102 Metcalfe Ave W",
    "sg:city":"Dresden",
    "sg:classifiers":[
        {
            "category":"Home & Garden",
            "subcategory":"Hardware",
            "type":"Retail Goods"
        }
    ],
    "sg:phone":"+1 519 683 4363",
    "sg:postcode":"N0P 1M0",
    "sg:province":"ON",
    "wof:name":"Clark's Fuel & Supply",
    "wof:placetype":"venue"
},
  "geometry": {"coordinates":[-82.179573,42.59407],"type":"Point"}
}