{
  "type": "Feature",
  "properties": {
    "addr:full":"104 Rue Cliche Frampton QC G0R 1M0",
    "addr:housenumber":"104",
    "addr:postcode":"g0r 1m0",
    "addr:street":"Rue Cliche",
    "iso:country":"CA",
    "sg:address":"104 Rue Cliche",
    "sg:city":"Frampton",
    "sg:classifiers":[
        {
            "category":"Wholesale",
            "subcategory":"Construction Materials",
            "type":"Manufacturing & Wholesale Goods"
        }
    ],
    "sg:phone":"+1 418 479 2112",
    "sg:postcode":"G0R 1M0",
    "sg:province":"QC",
    "sg:tags":[
        "fence"
    ],
    "wof:name":"Clotures Jpn Inc",
    "wof:placetype":"venue"
},
  "geometry": {"coordinates":[-70.805031,46.462051],"type":"Point"}
}