{
  "type": "Feature",
  "properties": {
    "addr:full":"Westmount QC H3Z 2Y5",
    "addr:postcode":"h3z 2y5",
    "iso:country":"CA",
    "sg:city":"Westmount",
    "sg:classifiers":[
        {
            "category":"Health Services",
            "subcategory":"Doctor",
            "type":"Services"
        }
    ],
    "sg:phone":"+1 514 932 7239",
    "sg:postcode":"H3Z 2Y5",
    "sg:province":"QC",
    "sg:tags":[
        "dentist"
    ],
    "wof:name":"Gardner, Michael E DDS",
    "wof:placetype":"venue"
},
  "geometry": {"coordinates":[-73.587097,45.486717],"type":"Point"}
}