{
  "type": "Feature",
  "properties": {
    "addr:full":"10123 101st Ave Lac LA Biche AB T0A 2C0",
    "addr:housenumber":"10123",
    "addr:postcode":"t0a 2c0",
    "addr:street":"101St Ave",
    "iso:country":"CA",
    "sg:address":"10123 101st Ave",
    "sg:city":"Lac LA Biche",
    "sg:classifiers":[
        {
            "category":"Real Estate",
            "subcategory":"Real Estate Agent",
            "type":"Services"
        }
    ],
    "sg:phone":"+1 780 623 2634",
    "sg:postcode":"T0A 2C0",
    "sg:province":"AB",
    "wof:name":"Royal Lepage Tlc Realty",
    "wof:placetype":"venue"
},
  "geometry": {"coordinates":[-111.976387024,54.7702255249],"type":"Point"}
}