{
  "type": "Feature",
  "properties": {
    "iso:country":"CA",
    "sg:address":"460 Main St E #301",
    "sg:city":"Hamilton",
    "sg:classifiers":[
        {
            "category":"Banks & Credit Unions",
            "subcategory":"Investment Brokerage",
            "type":"Services"
        }
    ],
    "sg:phone":"+1 905 528 3388",
    "sg:postcode":"L8N 1K4",
    "sg:province":"ON",
    "sg:tags":[
        "funds",
        "mutual"
    ],
    "wof:name":"Pfsl Investments Canada Ltd",
    "wof:placetype":"venue"
},
  "geometry": {"coordinates":[-79.85177612299999,43.250667572],"type":"Point"}
}