{
  "type": "Feature",
  "properties": {
    "iso:country":"CA",
    "sg:address":"510 Rue Delage",
    "sg:city":"Lac-Saint-Charles",
    "sg:classifiers":[
        {
            "category":"Government",
            "subcategory":"Fire Station",
            "type":"Public Place"
        }
    ],
    "sg:phone":"+1 ",
    "sg:postcode":"G3G 1J1",
    "sg:province":"QC",
    "sg:tags":[
        "department"
    ],
    "wof:name":"Lac St-Charles Svc Incendie",
    "wof:placetype":"venue"
},
  "geometry": {"coordinates":[-71.375664,46.908157],"type":"Point"}
}