{
  "type": "Feature",
  "properties": {
    "addr:full":"6435 Erin Mills Pky Mississauga ON L5N 4H4",
    "addr:housenumber":"6435",
    "addr:postcode":"l5n 4h4",
    "addr:street":"Erin Mills Pky",
    "iso:country":"CA",
    "sg:address":"6435 Erin Mills Pky",
    "sg:city":"Mississauga",
    "sg:classifiers":[
        {
            "category":"Personal",
            "subcategory":"Beauty Salon",
            "type":"Services"
        }
    ],
    "sg:phone":"+1 905 858 4247",
    "sg:postcode":"L5N 4H4",
    "sg:province":"ON",
    "wof:name":"Hair",
    "wof:placetype":"venue"
},
  "geometry": {"coordinates":[-79.741928,43.587414],"type":"Point"}
}