{
  "type": "Feature",
  "properties": {
    "addr:full":"1940 Campbell Cres Quesnel BC V2J 5Z9",
    "addr:housenumber":"1940",
    "addr:postcode":"v2j 5z9",
    "addr:street":"Campbell Cres",
    "iso:country":"CA",
    "sg:address":"1940 Campbell Cres",
    "sg:city":"Quesnel",
    "sg:classifiers":[
        {
            "category":"Manufacturing",
            "subcategory":"Tools & Machinery",
            "type":"Manufacturing & Wholesale Goods"
        }
    ],
    "sg:phone":"+1 250 992 3308",
    "sg:postcode":"V2J 5Z9",
    "sg:province":"BC",
    "sg:tags":[
        "steel",
        "machine",
        "shop"
    ],
    "wof:name":"Riverview Steel & Machine CO",
    "wof:placetype":"venue"
},
  "geometry": {"coordinates":[-122.508178711,53.0156021118],"type":"Point"}
}