{
  "type": "Feature",
  "properties": {
    "addr:full":"2777 Rue Berthon Longueuil QC J4M 1Y4",
    "addr:housenumber":"2777",
    "addr:postcode":"j4m 1y4",
    "addr:street":"Rue Berthon",
    "iso:country":"CA",
    "sg:address":"2777 Rue Berthon",
    "sg:city":"Longueuil",
    "sg:classifiers":[
        {
            "category":"Home & Garden",
            "subcategory":"Home Furnishings",
            "type":"Retail Goods"
        }
    ],
    "sg:phone":"+1 450 468 2381",
    "sg:postcode":"J4M 1Y4",
    "sg:province":"QC",
    "sg:tags":[
        "curtain",
        "made",
        "drapery"
    ],
    "wof:name":"Confection Signee LA Fine",
    "wof:placetype":"venue"
},
  "geometry": {"coordinates":[-73.44966125489999,45.5379562378],"type":"Point"}
}