{
  "type": "Feature",
  "properties": {
    "addr:full":"84 Stewart Ave Cambridge ON N1R 2T9",
    "addr:housenumber":"84",
    "addr:postcode":"n1r 2t9",
    "addr:street":"Stewart Ave",
    "iso:country":"CA",
    "sg:address":"84 Stewart Ave",
    "sg:city":"Cambridge",
    "sg:classifiers":[
        {
            "category":"Wholesale",
            "subcategory":"Construction Materials",
            "type":"Manufacturing & Wholesale Goods"
        }
    ],
    "sg:phone":"+1 519 623 9700",
    "sg:postcode":"N1R 2T9",
    "sg:province":"ON",
    "sg:tags":[
        "fence"
    ],
    "wof:name":"Gilks Fence Ltd",
    "wof:placetype":"venue"
},
  "geometry": {"coordinates":[-80.308678,43.348385],"type":"Point"}
}