{
  "type": "Feature",
  "properties": {
    "iso:country":"CA",
    "sg:address":"25 10th Ave",
    "sg:city":"Shaunavon",
    "sg:classifiers":[
        {
            "category":"Building & Trades",
            "subcategory":"Construction",
            "type":"Services"
        }
    ],
    "sg:phone":"+1 306 297 2297",
    "sg:postcode":"S0N 2M0",
    "sg:province":"SK",
    "sg:tags":[
        "excavating",
        "contractor"
    ],
    "wof:name":"Kirkpatrick Enterprises",
    "wof:placetype":"venue"
},
  "geometry": {"coordinates":[-108.41545105,49.6547012329],"type":"Point"}
}