{
  "type": "Feature",
  "properties": {
    "iso:country":"CA",
    "sg:address":"1258 Michigan Ave",
    "sg:city":"Sarnia",
    "sg:classifiers":[
        {
            "category":"Social Services",
            "type":"Services"
        }
    ],
    "sg:phone":"+1 519 542 2481",
    "sg:postcode":"N7S 3Y2",
    "sg:province":"ON",
    "sg:tags":[
        "organization",
        "health",
        "mental",
        "welfare"
    ],
    "wof:name":"St Clair Child & Youth Svc",
    "wof:placetype":"venue"
},
  "geometry": {"coordinates":[-82.362526,43.000034],"type":"Point"}
}