{
  "type": "Feature",
  "properties": {
    "iso:country":"CA",
    "sg:address":"1690 Kingsway",
    "sg:city":"Vancouver",
    "sg:classifiers":[
        {
            "category":"Shopping",
            "subcategory":"Bicycles & Sporting Goods",
            "type":"Retail Goods"
        }
    ],
    "sg:phone":"+1 604 876 2738",
    "sg:postcode":"V5N 2S1",
    "sg:province":"BC",
    "wof:name":"Tepee Fitness Products",
    "wof:placetype":"venue"
},
  "geometry": {"coordinates":[-123.070205688,49.2473258972],"type":"Point"}
}