{
  "type": "Feature",
  "properties": {
    "addr:full":"1120 Av DE Salaberry Quebec QC G1R 2V8",
    "addr:housenumber":"1120",
    "addr:postcode":"g1r 2v8",
    "addr:street":"Av De Salaberry",
    "iso:country":"CA",
    "sg:address":"1120 Av DE Salaberry",
    "sg:city":"Quebec",
    "sg:classifiers":[
        {
            "category":"Professional",
            "subcategory":"Art Services",
            "type":"Services"
        }
    ],
    "sg:phone":"+1 418 529 0883",
    "sg:postcode":"G1R 2V8",
    "sg:province":"QC",
    "sg:tags":[
        "graphic",
        "designer"
    ],
    "wof:name":"R-Design Inc",
    "wof:placetype":"venue"
},
  "geometry": {"coordinates":[-71.22448730470001,46.8039665222],"type":"Point"}
}