{
  "type": "Feature",
  "properties": {
    "addr:full":"483 High St Mactier ON P0C 1H0",
    "addr:housenumber":"483",
    "addr:postcode":"p0c 1h0",
    "addr:street":"High St",
    "iso:country":"CA",
    "sg:address":"483 High St",
    "sg:city":"Mactier",
    "sg:classifiers":[
        {
            "category":"Education",
            "subcategory":"Library",
            "type":"Public Place"
        }
    ],
    "sg:phone":"+1 705 375 5430",
    "sg:postcode":"P0C 1H0",
    "sg:province":"ON",
    "wof:name":"Mac Tier Public Library",
    "wof:placetype":"venue"
},
  "geometry": {"coordinates":[-79.770126,45.136143],"type":"Point"}
}