{
  "type": "Feature",
  "properties": {
    "addr:full":"5004 49 St Drayton Valley AB T7A 1E2",
    "addr:housenumber":"5004",
    "addr:postcode":"t7a 1e2",
    "addr:street":"49 St",
    "iso:country":"CA",
    "sg:address":"5004 49 St",
    "sg:city":"Drayton Valley",
    "sg:classifiers":[
        {
            "category":"Organizations",
            "subcategory":"Religious Organization",
            "type":"Services"
        }
    ],
    "sg:phone":"+1 780 542 5091",
    "sg:postcode":"T7A 1E2",
    "sg:province":"AB",
    "sg:tags":[
        "church"
    ],
    "wof:name":"Church of God",
    "wof:placetype":"venue"
},
  "geometry": {"coordinates":[-114.97520400000001,53.221394],"type":"Point"}
}