{
  "type": "Feature",
  "properties": {
    "addr:full":"975 Queenston Rd Stoney Creek ON L8G 1B8",
    "addr:housenumber":"975",
    "addr:postcode":"l8g 1b8",
    "addr:street":"Queenston Rd",
    "iso:country":"CA",
    "sg:address":"975 Queenston Rd",
    "sg:city":"Stoney Creek",
    "sg:classifiers":[
        {
            "category":"Professional",
            "subcategory":"Lawyer & Legal Services",
            "type":"Services"
        }
    ],
    "sg:phone":"+1 905 662 7101",
    "sg:postcode":"L8G 1B8",
    "sg:province":"ON",
    "sg:tags":[
        "attorney"
    ],
    "wof:name":"Calcagni, Frank",
    "wof:placetype":"venue"
},
  "geometry": {"coordinates":[-79.75044250489999,43.2250137329],"type":"Point"}
}