{
  "type": "Feature",
  "properties": {
    "addr:full":"1247 Rue Adrien-Brien Chambly QC J3L 5W1",
    "addr:housenumber":"1247",
    "addr:postcode":"j3l 5w1",
    "addr:street":"Rue Adrien-Brien",
    "iso:country":"CA",
    "sg:address":"1247 Rue Adrien-Brien",
    "sg:city":"Chambly",
    "sg:classifiers":[
        {
            "category":"Building & Trades",
            "subcategory":"Plumbing",
            "type":"Services"
        }
    ],
    "sg:phone":"+1 450 447 9399",
    "sg:postcode":"J3L 5W1",
    "sg:province":"QC",
    "sg:tags":[
        "conditioning",
        "air",
        "system",
        "contractor"
    ],
    "wof:name":"Air Action Climatisation",
    "wof:placetype":"venue"
},
  "geometry": {"coordinates":[-73.298035,45.438614],"type":"Point"}
}