{
  "type": "Feature",
  "properties": {
    "iso:country":"CA",
    "sg:city":"Frenchman Butte",
    "sg:classifiers":[
        {
            "category":"Mining & Drilling",
            "type":"Manufacturing & Wholesale Goods"
        }
    ],
    "sg:phone":"+1 306 344 4822",
    "sg:postcode":"S0M 0W0",
    "sg:province":"SK",
    "sg:tags":[
        "consultant",
        "oil",
        "gas"
    ],
    "wof:name":"Norman Land Svc",
    "wof:placetype":"venue"
},
  "geometry": {"coordinates":[-109.63385772700001,53.5930404663],"type":"Point"}
}