{
  "type": "Feature",
  "properties": {
    "iso:country":"CA",
    "sg:address":"1550 United Blvd",
    "sg:city":"Coquitlam",
    "sg:classifiers":[
        {
            "category":"Manufacturing",
            "subcategory":"Food",
            "type":"Manufacturing & Wholesale Goods"
        }
    ],
    "sg:phone":"+1 604 777 1757",
    "sg:postcode":"V3K 6Y2",
    "sg:province":"BC",
    "sg:tags":[
        "product",
        "health"
    ],
    "wof:name":"Natural Factors Nutritional",
    "wof:placetype":"venue"
},
  "geometry": {"coordinates":[-122.84622192400001,49.2284965515],"type":"Point"}
}