{
  "type": "Feature",
  "properties": {
    "addr:full":"519 Rue Principale LA Sarre QC J9Z 2A4",
    "addr:housenumber":"519",
    "addr:postcode":"j9z 2a4",
    "addr:street":"Rue Principale La Sarre",
    "iso:country":"CA",
    "sg:address":"519 Rue Principale",
    "sg:city":"LA Sarre",
    "sg:classifiers":[
        {
            "category":"Organizations",
            "subcategory":"Religious Organization",
            "type":"Services"
        }
    ],
    "sg:phone":"+1 819 333 6315",
    "sg:postcode":"J9Z 2A4",
    "sg:province":"QC",
    "sg:tags":[
        "association"
    ],
    "wof:name":"Soeurs DE L'Assomption LA Sv",
    "wof:placetype":"venue"
},
  "geometry": {"coordinates":[-79.205185,48.795975],"type":"Point"}
}