{
  "type": "Feature",
  "properties": {
    "addr:full":"Vancouver BC V6Z 1X9",
    "addr:postcode":"v6z 1x9",
    "iso:country":"CA",
    "sg:city":"Vancouver",
    "sg:classifiers":[
        {
            "category":"Restaurant",
            "type":"Food & Drink"
        }
    ],
    "sg:phone":"+1 604 689 3127",
    "sg:postcode":"V6Z 1X9",
    "sg:province":"BC",
    "wof:name":"Denny's of Canada Ltd",
    "wof:placetype":"venue"
},
  "geometry": {"coordinates":[-123.12388610799999,49.2823562622],"type":"Point"}
}