{
  "type": "Feature",
  "properties": {
    "addr:full":"1610 East Heights Saskatoon SK S7J 3B7",
    "addr:housenumber":"1610",
    "addr:postcode":"s7j 3b7",
    "iso:country":"CA",
    "sg:address":"1610 East Heights",
    "sg:city":"Saskatoon",
    "sg:classifiers":[
        {
            "category":"Food & Beverages",
            "subcategory":"Specialty",
            "type":"Retail Goods"
        }
    ],
    "sg:phone":"+1 306 374 3236",
    "sg:postcode":"S7J 3B7",
    "sg:province":"SK",
    "sg:tags":[
        "health",
        "diet"
    ],
    "wof:name":"Shaklee Products Distributor",
    "wof:placetype":"venue"
},
  "geometry": {"coordinates":[-106.676040649,52.1511573792],"type":"Point"}
}