{
  "type": "Feature",
  "properties": {
    "iso:country":"CA",
    "sg:address":"2 Ch Du Canal",
    "sg:city":"Pointe-Des-Cascades",
    "sg:classifiers":[
        {
            "category":"Arts & Performance",
            "subcategory":"Theater",
            "type":"Entertainment"
        }
    ],
    "sg:phone":"+1 450 455 8855",
    "sg:postcode":"J0P 1M0",
    "sg:province":"QC",
    "wof:name":"Theatre Des Cascades",
    "wof:placetype":"venue"
},
  "geometry": {"coordinates":[-73.96143341059999,45.3338928223],"type":"Point"}
}