{
  "type": "Feature",
  "properties": {
    "addr:full":"755 Roger St Sarnia ON N7S 2S8",
    "addr:housenumber":"755",
    "addr:postcode":"n7s 2s8",
    "addr:street":"Roger St",
    "iso:country":"CA",
    "sg:address":"755 Roger St",
    "sg:city":"Sarnia",
    "sg:classifiers":[
        {
            "category":"Real Estate",
            "subcategory":"Real Estate Operator",
            "type":"Services"
        }
    ],
    "sg:phone":"+1 519 344 6124",
    "sg:postcode":"N7S 2S8",
    "sg:province":"ON",
    "sg:tags":[
        "apartment"
    ],
    "wof:name":"High Park Apartments",
    "wof:placetype":"venue"
},
  "geometry": {"coordinates":[-82.374802,42.982285],"type":"Point"}
}