{
  "type": "Feature",
  "properties": {
    "iso:country":"CA",
    "sg:address":"60 Fordhouse Blvd",
    "sg:city":"Etobicoke",
    "sg:classifiers":[
        {
            "category":"Building & Trades",
            "subcategory":"Cleaning & Sanitation",
            "type":"Services"
        }
    ],
    "sg:phone":"+1 416 503 8851",
    "sg:postcode":"M8Z 1M6",
    "sg:province":"ON",
    "sg:tags":[
        "janitor"
    ],
    "wof:name":"Janitor For Hire",
    "wof:placetype":"venue"
},
  "geometry": {"coordinates":[-79.5352630615,43.6166381836],"type":"Point"}
}