{
  "type": "Feature",
  "properties": {
    "addr:full":"Calgary AB T2H 2V2",
    "addr:postcode":"t2h 2v2",
    "iso:country":"CA",
    "sg:city":"Calgary",
    "sg:classifiers":[
        {
            "category":"Shopping",
            "subcategory":"Books",
            "type":"Retail Goods"
        }
    ],
    "sg:phone":"+1 403 252 9577",
    "sg:postcode":"T2H 2V2",
    "sg:province":"AB",
    "sg:tags":[
        "dealer"
    ],
    "wof:name":"G Books Inc",
    "wof:placetype":"venue"
},
  "geometry": {"coordinates":[-114.071236,50.978546],"type":"Point"}
}