{
  "type": "Feature",
  "properties": {
    "addr:full":"32 Seguin St Parry Sound ON P2A 1B1",
    "addr:housenumber":"32",
    "addr:postcode":"p2a 1b1",
    "addr:street":"Seguin St",
    "iso:country":"CA",
    "sg:address":"32 Seguin St",
    "sg:city":"Parry Sound",
    "sg:classifiers":[
        {
            "category":"Food & Beverages",
            "subcategory":"Candy",
            "type":"Retail Goods"
        }
    ],
    "sg:phone":"+1 705 746 5286",
    "sg:postcode":"P2A 1B1",
    "sg:province":"ON",
    "sg:tags":[
        "confectionery"
    ],
    "wof:name":"Somewhere in Time Candy & Gift",
    "wof:placetype":"venue"
},
  "geometry": {"coordinates":[-80.033051,45.343418],"type":"Point"}
}