{
  "type": "Feature",
  "properties": {
    "addr:full":"804 Waterloo St Winnipeg MB R3N 0T6",
    "addr:housenumber":"804",
    "addr:postcode":"r3n 0t6",
    "addr:street":"Waterloo St",
    "iso:country":"CA",
    "sg:address":"804 Waterloo St",
    "sg:city":"Winnipeg",
    "sg:classifiers":[
        {
            "category":"Real Estate",
            "subcategory":"Real Estate Agent",
            "type":"Services"
        }
    ],
    "sg:phone":"+1 204 488 8710",
    "sg:postcode":"R3N 0T6",
    "sg:province":"MB",
    "wof:name":"Property Lines Realty Inc",
    "wof:placetype":"venue"
},
  "geometry": {"coordinates":[-97.185211,49.855003],"type":"Point"}
}