{
  "type": "Feature",
  "properties": {
    "addr:full":"4105 Hwy 3 Rock Creek BC V0H 1Y0",
    "addr:housenumber":"4105",
    "addr:postcode":"v0h 1y0",
    "addr:street":"Hwy 3",
    "iso:country":"CA",
    "sg:address":"4105 Hwy 3",
    "sg:city":"Rock Creek",
    "sg:classifiers":[
        {
            "category":"Shopping",
            "subcategory":"Discount & Variety Stores",
            "type":"Retail Goods"
        }
    ],
    "sg:phone":"+1 250 446 2722",
    "sg:postcode":"V0H 1Y0",
    "sg:province":"BC",
    "sg:tags":[
        "grocer",
        "general"
    ],
    "wof:name":"Rock Creek General Store",
    "wof:placetype":"venue"
},
  "geometry": {"coordinates":[-118.996307,49.055534],"type":"Point"}
}