{
  "type": "Feature",
  "properties": {
    "addr:full":"1 Rue Forget Baie-Saint-Paul QC G3Z 1T3",
    "addr:housenumber":"1",
    "addr:postcode":"g3z 1t3",
    "addr:street":"Rue Forget",
    "iso:country":"CA",
    "sg:address":"1 Rue Forget",
    "sg:city":"Baie-Saint-Paul",
    "sg:classifiers":[
        {
            "category":"Shopping",
            "type":"Retail Goods"
        }
    ],
    "sg:phone":"+1 418 435 3429",
    "sg:postcode":"G3Z 1T3",
    "sg:province":"QC",
    "sg:tags":[
        "art",
        "gallery",
        "dealer"
    ],
    "wof:name":"Galerie D'Art Yvon Desgagnes",
    "wof:placetype":"venue"
},
  "geometry": {"coordinates":[-70.506851,47.43956],"type":"Point"}
}