{
  "type": "Feature",
  "properties": {
    "iso:country":"CA",
    "sg:address":"574 Artisan Lane",
    "sg:city":"Bowen Island",
    "sg:classifiers":[
        {
            "category":"Professional",
            "subcategory":"Secretarial Services",
            "type":"Services"
        }
    ],
    "sg:phone":"+1 604 947 9119",
    "sg:postcode":"V0N 1G0",
    "sg:province":"BC",
    "sg:tags":[
        "reporting",
        "court"
    ],
    "wof:name":"Office At Artisan Square",
    "wof:placetype":"venue"
},
  "geometry": {"coordinates":[-123.345054627,49.3804359436],"type":"Point"}
}