{
  "type": "Feature",
  "properties": {
    "addr:full":"35 3rd St Weyburn SK S4H 0W1",
    "addr:housenumber":"35",
    "addr:postcode":"s4h 0w1",
    "addr:street":"3Rd St",
    "iso:country":"CA",
    "sg:address":"35 3rd St",
    "sg:city":"Weyburn",
    "sg:classifiers":[
        {
            "category":"Shopping",
            "subcategory":"Clothing, Apparel, & Fashions",
            "type":"Retail Goods"
        }
    ],
    "sg:phone":"+1 306 842 3999",
    "sg:postcode":"S4H 0W1",
    "sg:province":"SK",
    "wof:name":"Snup'n Mo's Kids Clothing",
    "wof:placetype":"venue"
},
  "geometry": {"coordinates":[-103.854202,49.660873],"type":"Point"}
}