{
  "type": "Feature",
  "properties": {
    "addr:full":"44 Grafton St Charlottetown PE C1A 1K5",
    "addr:housenumber":"44",
    "addr:postcode":"c1a 1k5",
    "addr:street":"Grafton St",
    "iso:country":"CA",
    "sg:address":"44 Grafton St",
    "sg:city":"Charlottetown",
    "sg:classifiers":[
        {
            "category":"Health Services",
            "subcategory":"Health Practitioner",
            "type":"Services"
        }
    ],
    "sg:phone":"+1 902 393 3829",
    "sg:postcode":"C1A 1K5",
    "sg:province":"PE",
    "sg:tags":[
        "psychologist"
    ],
    "wof:name":"Le Blanc, Caroline PhD",
    "wof:placetype":"venue"
},
  "geometry": {"coordinates":[-63.1298370361,46.2331542969],"type":"Point"}
}