{
  "type": "Feature",
  "properties": {
    "addr:full":"7505 Boul Lacordaire Saint-Leonard QC H1S 2A6",
    "addr:housenumber":"7505",
    "addr:postcode":"h1s 2a6",
    "addr:street":"Boul Lacordaire",
    "iso:country":"CA",
    "sg:address":"7505 Boul Lacordaire",
    "sg:city":"Saint-Leonard",
    "sg:classifiers":[
        {
            "category":"Restaurant",
            "type":"Food & Drink"
        }
    ],
    "sg:phone":"+1 514 255 7844",
    "sg:postcode":"H1S 2A6",
    "sg:province":"QC",
    "wof:name":"Harvey's",
    "wof:placetype":"venue"
},
  "geometry": {"coordinates":[-73.58234400000001,45.582932],"type":"Point"}
}