{
  "type": "Feature",
  "properties": {
    "addr:full":"688 Selkirk Ave Winnipeg MB R2W 2N3",
    "addr:housenumber":"688",
    "addr:postcode":"r2w 2n3",
    "addr:street":"Selkirk Ave",
    "iso:country":"CA",
    "sg:address":"688 Selkirk Ave",
    "sg:city":"Winnipeg",
    "sg:classifiers":[
        {
            "category":"Wholesale",
            "subcategory":"Electrical",
            "type":"Manufacturing & Wholesale Goods"
        }
    ],
    "sg:phone":"+1 204 237 1868",
    "sg:postcode":"R2W 2N3",
    "sg:province":"MB",
    "sg:tags":[
        "refrigerator",
        "freezer"
    ],
    "wof:name":"Masson Appliance Svc",
    "wof:placetype":"venue"
},
  "geometry": {"coordinates":[-97.15236663819999,49.917881012],"type":"Point"}
}