{
  "type": "Feature",
  "properties": {
    "iso:country":"CA",
    "sg:address":"593 Glengrove Ave",
    "sg:city":"North York",
    "sg:classifiers":[
        {
            "category":"Manufacturing",
            "subcategory":"Printing",
            "type":"Manufacturing & Wholesale Goods"
        }
    ],
    "sg:phone":"+1 416 783 2465",
    "sg:postcode":"M6B 2H7",
    "sg:province":"ON",
    "sg:tags":[
        "printer"
    ],
    "wof:name":"More Printing",
    "wof:placetype":"venue"
},
  "geometry": {"coordinates":[-79.436699,43.712254],"type":"Point"}
}