{
  "type": "Feature",
  "properties": {
    "addr:full":"634199 30 Sideroad Feversham ON N0C 1C0",
    "addr:housenumber":"634199 30",
    "addr:postcode":"n0c 1c0",
    "addr:street":"Sideroad Feversham",
    "iso:country":"CA",
    "sg:address":"634199 30 Sideroad",
    "sg:city":"Feversham",
    "sg:classifiers":[
        {
            "category":"Organizations",
            "subcategory":"Religious Organization",
            "type":"Services"
        }
    ],
    "sg:phone":"+1 519 922 1159",
    "sg:postcode":"N0C 1C0",
    "sg:province":"ON",
    "sg:tags":[
        "church"
    ],
    "wof:name":"Mount Pleasant Church",
    "wof:placetype":"venue"
},
  "geometry": {"coordinates":[-80.377388,44.336353],"type":"Point"}
}