{
  "type": "Feature",
  "properties": {
    "addr:full":"Farm Leoville SK S0J 1N0",
    "addr:postcode":"s0j 1n0",
    "iso:country":"CA",
    "sg:address":"Farm",
    "sg:city":"Leoville",
    "sg:classifiers":[
        {
            "category":"Farming",
            "subcategory":"Farm",
            "type":"Manufacturing & Wholesale Goods"
        }
    ],
    "sg:phone":"+1 306 984 2429",
    "sg:postcode":"S0J 1N0",
    "sg:province":"SK",
    "wof:name":"Junor Farms Ltd",
    "wof:placetype":"venue"
},
  "geometry": {"coordinates":[-107.554047,53.632771],"type":"Point"}
}