{
  "type": "Feature",
  "properties": {
    "addr:full":"380 Rue Simonds S Granby QC J2J 1L4",
    "addr:housenumber":"380",
    "addr:postcode":"j2j 1l4",
    "addr:street":"Rue Simonds S Granby",
    "iso:country":"CA",
    "sg:address":"380 Rue Simonds S",
    "sg:city":"Granby",
    "sg:classifiers":[
        {
            "category":"Cinema",
            "subcategory":"Movie Rental",
            "type":"Entertainment"
        }
    ],
    "sg:phone":"+1 450 776 6666",
    "sg:postcode":"J2J 1L4",
    "sg:province":"QC",
    "sg:tags":[
        "leasing",
        "video",
        "disc",
        "tape"
    ],
    "wof:name":"Boulevard Hollywood Enr",
    "wof:placetype":"venue"
},
  "geometry": {"coordinates":[-72.760437,45.402401],"type":"Point"}
}