{
  "type": "Feature",
  "properties": {
    "addr:full":"11 William St E Arnprior ON K7S 1J6",
    "addr:housenumber":"11",
    "addr:postcode":"k7s 1j6",
    "addr:street":"William St E",
    "iso:country":"CA",
    "sg:address":"11 William St E",
    "sg:city":"Arnprior",
    "sg:classifiers":[
        {
            "category":"Autos & Motor Vehicles",
            "subcategory":"Automobile Sales",
            "type":"Retail Goods"
        }
    ],
    "sg:phone":"+1 613 623 6499",
    "sg:postcode":"K7S 1J6",
    "sg:province":"ON",
    "sg:tags":[
        "car",
        "dealer"
    ],
    "wof:name":"Jim's Used Autos",
    "wof:placetype":"venue"
},
  "geometry": {"coordinates":[-76.35693359379999,45.4298095703],"type":"Point"}
}