{
  "type": "Feature",
  "properties": {
    "addr:full":"365457 Evergreen St Burgessville ON N0J 1C0",
    "addr:housenumber":"365457",
    "addr:postcode":"n0j 1c0",
    "addr:street":"Evergreen St",
    "iso:country":"CA",
    "sg:address":"365457 Evergreen St",
    "sg:city":"Burgessville",
    "sg:classifiers":[
        {
            "category":"Manufacturing",
            "subcategory":"Tools & Machinery",
            "type":"Manufacturing & Wholesale Goods"
        }
    ],
    "sg:phone":"+1 519 424 3393",
    "sg:postcode":"N0J 1C0",
    "sg:province":"ON",
    "sg:tags":[
        "pattern",
        "maker"
    ],
    "wof:name":"Patterns 'N Things",
    "wof:placetype":"venue"
},
  "geometry": {"coordinates":[-80.638817,43.011055],"type":"Point"}
}