{
  "type": "Feature",
  "properties": {
    "addr:full":"160 Hemlock Ave Atikokan ON P0T 1C0",
    "addr:housenumber":"160",
    "addr:postcode":"p0t 1c0",
    "addr:street":"Hemlock Ave",
    "iso:country":"CA",
    "sg:address":"160 Hemlock Ave",
    "sg:city":"Atikokan",
    "sg:classifiers":[
        {
            "category":"Education",
            "subcategory":"School",
            "type":"Public Place"
        }
    ],
    "sg:phone":"+1 807 597 6748",
    "sg:postcode":"P0T 1C0",
    "sg:province":"ON",
    "wof:name":"Atikokan Roman Catholic Sep",
    "wof:placetype":"venue"
},
  "geometry": {"coordinates":[-91.604446,48.760094],"type":"Point"}
}