{
  "type": "Feature",
  "properties": {
    "iso:country":"CA",
    "sg:address":"190 Ch Brosseau",
    "sg:city":"Cowansville",
    "sg:classifiers":[
        {
            "category":"Wholesale",
            "subcategory":"Scrap",
            "type":"Manufacturing & Wholesale Goods"
        }
    ],
    "sg:phone":"+1 450 266 0333",
    "sg:postcode":"J2K 3G6",
    "sg:province":"QC",
    "sg:tags":[
        "recycling",
        "center"
    ],
    "wof:name":"Chemrec Inc",
    "wof:placetype":"venue"
},
  "geometry": {"coordinates":[-72.773445,45.223038],"type":"Point"}
}