{
  "type": "Feature",
  "properties": {
    "addr:full":"1454 Rue Fleury E Montreal QC H2C 1S1",
    "addr:housenumber":"1454",
    "addr:postcode":"h2c 1s1",
    "addr:street":"Rue Fleury E",
    "iso:country":"CA",
    "sg:address":"1454 Rue Fleury E",
    "sg:city":"Montreal",
    "sg:classifiers":[
        {
            "category":"Shopping",
            "subcategory":"Jewelry",
            "type":"Retail Goods"
        }
    ],
    "sg:phone":"+1 514 389 1914",
    "sg:postcode":"H2C 1S1",
    "sg:province":"QC",
    "sg:tags":[
        "jeweler"
    ],
    "wof:name":"Granada Bijouterie",
    "wof:placetype":"venue"
},
  "geometry": {"coordinates":[-73.656723,45.561977],"type":"Point"}
}