{
  "type": "Feature",
  "properties": {
    "addr:full":"Calgary AB T2H 2G2",
    "addr:postcode":"t2h 2g2",
    "iso:country":"CA",
    "sg:city":"Calgary",
    "sg:classifiers":[
        {
            "category":"Manufacturing",
            "subcategory":"Signs",
            "type":"Manufacturing & Wholesale Goods"
        }
    ],
    "sg:phone":"+1 403 258 3381",
    "sg:postcode":"T2H 2G2",
    "sg:province":"AB",
    "wof:name":"A-1 Signs Ltd",
    "wof:placetype":"venue"
},
  "geometry": {"coordinates":[-114.051041,50.992069],"type":"Point"}
}