{
  "type": "Feature",
  "properties": {
    "addr:full":"Smiths Falls ON K7A 2A8",
    "addr:postcode":"k7a 2a8",
    "iso:country":"CA",
    "sg:city":"Smiths Falls",
    "sg:classifiers":[
        {
            "category":"Government",
            "subcategory":"Office",
            "type":"Public Place"
        }
    ],
    "sg:phone":"+1 613 283 5170",
    "sg:postcode":"K7A 2A8",
    "sg:province":"ON",
    "wof:name":"Canada Canals",
    "wof:placetype":"venue"
},
  "geometry": {"coordinates":[-76.021278,44.899281],"type":"Point"}
}