{
  "type": "Feature",
  "properties": {
    "addr:full":"103 Rue Laurier O Victoriaville QC G6P 6S1",
    "addr:housenumber":"103",
    "addr:postcode":"g6p 6s1",
    "addr:street":"Rue Laurier O",
    "iso:country":"CA",
    "sg:address":"103 Rue Laurier O",
    "sg:city":"Victoriaville",
    "sg:classifiers":[
        {
            "category":"Autos & Motor Vehicles",
            "subcategory":"Fuel & Gas Station",
            "type":"Retail Goods"
        }
    ],
    "sg:phone":"+1 819 357 2006",
    "sg:postcode":"G6P 6S1",
    "sg:province":"QC",
    "sg:tags":[
        "oil"
    ],
    "wof:name":"Olco",
    "wof:placetype":"venue"
},
  "geometry": {"coordinates":[-71.911491,46.044472],"type":"Point"}
}