{
  "type": "Feature",
  "properties": {
    "addr:full":"46 Northcliffe Blvd Toronto ON M6H 3H2",
    "addr:housenumber":"46",
    "addr:postcode":"m6h 3h2",
    "addr:street":"Northcliffe Blvd",
    "iso:country":"CA",
    "sg:address":"46 Northcliffe Blvd",
    "sg:city":"Toronto",
    "sg:classifiers":[
        {
            "category":"Professional",
            "subcategory":"Lawyer & Legal Services",
            "type":"Services"
        }
    ],
    "sg:phone":"+1 416 656 6465",
    "sg:postcode":"M6H 3H2",
    "sg:province":"ON",
    "sg:tags":[
        "attorney"
    ],
    "wof:name":"Titherington, Michael K",
    "wof:placetype":"venue"
},
  "geometry": {"coordinates":[-79.440483,43.677078],"type":"Point"}
}