{
  "type": "Feature",
  "properties": {
    "addr:full":"4671 Ranger Ave North Vancouver BC V7R 3L9",
    "addr:housenumber":"4671",
    "addr:postcode":"v7r 3l9",
    "addr:street":"Ranger Ave",
    "iso:country":"CA",
    "sg:address":"4671 Ranger Ave",
    "sg:city":"North Vancouver",
    "sg:classifiers":[
        {
            "category":"Professional",
            "subcategory":"Engineering",
            "type":"Services"
        }
    ],
    "sg:phone":"+1 604 980 7766",
    "sg:postcode":"V7R 3L9",
    "sg:province":"BC",
    "sg:tags":[
        "engineer"
    ],
    "wof:name":"Meridian Technologies Ltd",
    "wof:placetype":"venue"
},
  "geometry": {"coordinates":[-123.09079,49.355003],"type":"Point"}
}