{
  "type": "Feature",
  "properties": {
    "addr:full":"Waterloo ON N2V 1A2",
    "addr:postcode":"n2v 1a2",
    "iso:country":"CA",
    "sg:city":"Waterloo",
    "sg:classifiers":[
        {
            "category":"Retail",
            "subcategory":"Auto Repair",
            "type":"Services"
        }
    ],
    "sg:phone":"+1 519 886 2641",
    "sg:postcode":"N2V 1A2",
    "sg:province":"ON",
    "sg:tags":[
        "repairing",
        "automobile"
    ],
    "wof:name":"Total Auto Svc",
    "wof:placetype":"venue"
},
  "geometry": {"coordinates":[-80.5419998169,43.5048675537],"type":"Point"}
}