{
  "type": "Feature",
  "properties": {
    "addr:full":"2995 Islington Ave North York ON M9L 2K9",
    "addr:housenumber":"2995",
    "addr:postcode":"m9l 2k9",
    "addr:street":"Islington Ave",
    "iso:country":"CA",
    "sg:address":"2995 Islington Ave",
    "sg:city":"North York",
    "sg:classifiers":[
        {
            "category":"Wholesale",
            "subcategory":"Meat",
            "type":"Manufacturing & Wholesale Goods"
        }
    ],
    "sg:phone":"+1 416 749 1633",
    "sg:postcode":"M9L 2K9",
    "sg:province":"ON",
    "sg:tags":[
        "product"
    ],
    "wof:name":"Cavallino Carne Equina",
    "wof:placetype":"venue"
},
  "geometry": {"coordinates":[-79.5708770752,43.7590789795],"type":"Point"}
}