{
  "type": "Feature",
  "properties": {
    "iso:country":"CA",
    "sg:city":"Surrey",
    "sg:classifiers":[
        {
            "category":"Building & Trades",
            "subcategory":"Construction",
            "type":"Services"
        }
    ],
    "sg:phone":"+1 604 882 0511",
    "sg:postcode":"V4N 4C7",
    "sg:province":"BC",
    "sg:tags":[
        "maker",
        "cabinet"
    ],
    "wof:name":"Signature Editions Millwork",
    "wof:placetype":"venue"
},
  "geometry": {"coordinates":[-122.690605164,49.1805419922],"type":"Point"}
}