{
  "type": "Feature",
  "properties": {
    "addr:full":"205 John St Watrous SK S0K 4T0",
    "addr:housenumber":"205",
    "addr:postcode":"s0k 4t0",
    "addr:street":"John St",
    "iso:country":"CA",
    "sg:address":"205 John St",
    "sg:city":"Watrous",
    "sg:classifiers":[
        {
            "category":"Travel",
            "subcategory":"Hotels & Motels",
            "type":"Entertainment"
        }
    ],
    "sg:phone":"+1 306 946 2707",
    "sg:postcode":"S0K 4T0",
    "sg:province":"SK",
    "sg:tags":[
        "breakfast",
        "accommodation",
        "bed"
    ],
    "wof:name":"Harmony House",
    "wof:placetype":"venue"
},
  "geometry": {"coordinates":[-105.46787999999999,51.671623],"type":"Point"}
}