{
  "type": "Feature",
  "properties": {
    "addr:full":"135 King St W Cobourg ON K9A 2M7",
    "addr:housenumber":"135",
    "addr:postcode":"k9a 2m7",
    "addr:street":"King St W",
    "iso:country":"CA",
    "sg:address":"135 King St W",
    "sg:city":"Cobourg",
    "sg:classifiers":[
        {
            "category":"Education",
            "subcategory":"School",
            "type":"Public Place"
        }
    ],
    "sg:phone":"+1 905 372 2191",
    "sg:postcode":"K9A 2M7",
    "sg:province":"ON",
    "wof:name":"Cobourg District Collegiate W",
    "wof:placetype":"venue"
},
  "geometry": {"coordinates":[-78.1711196899,43.9591560364],"type":"Point"}
}