{
  "type": "Feature",
  "properties": {
    "addr:full":"205 Simcoe St S Oshawa ON L1H 4H2",
    "addr:housenumber":"205",
    "addr:postcode":"l1h 4h2",
    "addr:street":"Simcoe St S",
    "iso:country":"CA",
    "sg:address":"205 Simcoe St S",
    "sg:city":"Oshawa",
    "sg:classifiers":[
        {
            "category":"Manufacturing",
            "subcategory":"Metals",
            "type":"Manufacturing & Wholesale Goods"
        }
    ],
    "sg:phone":"+1 905 433 2323",
    "sg:postcode":"L1H 4H2",
    "sg:province":"ON",
    "sg:tags":[
        "home",
        "improvement"
    ],
    "wof:name":"Acm Doors & Windows",
    "wof:placetype":"venue"
},
  "geometry": {"coordinates":[-78.8609695435,43.8921928406],"type":"Point"}
}