{
  "type": "Feature",
  "properties": {
    "addr:full":"132 Rang Montee Grande Ligne Saint-Urbain-Premier QC J0S 1Y0",
    "addr:housenumber":"132",
    "addr:postcode":"j0s 1y0",
    "addr:street":"Rang Montee Grande Ligne",
    "iso:country":"CA",
    "sg:address":"132 Rang Montee Grande Ligne",
    "sg:city":"Saint-Urbain-Premier",
    "sg:classifiers":[
        {
            "category":"Wholesale",
            "subcategory":"Machinery & Supplies",
            "type":"Manufacturing & Wholesale Goods"
        }
    ],
    "sg:phone":"+1 450 427 3057",
    "sg:postcode":"J0S 1Y0",
    "sg:province":"QC",
    "sg:tags":[
        "repairing",
        "automobile",
        "hydraulic",
        "equipment"
    ],
    "wof:name":"Reparation J Marcil",
    "wof:placetype":"venue"
},
  "geometry": {"coordinates":[-73.718193,45.232147],"type":"Point"}
}