{
  "type": "Feature",
  "properties": {
    "addr:full":"Toronto ON M5A 4K2",
    "addr:postcode":"m5a 4k2",
    "iso:country":"CA",
    "sg:city":"Toronto",
    "sg:classifiers":[
        {
            "category":"Wholesale",
            "subcategory":"Non-durable Goods",
            "type":"Manufacturing & Wholesale Goods"
        }
    ],
    "sg:phone":"+1 416 968 0508",
    "sg:postcode":"M5A 4K2",
    "sg:province":"ON",
    "sg:tags":[
        "advertising"
    ],
    "wof:name":"Raceinc International Inc",
    "wof:placetype":"venue"
},
  "geometry": {"coordinates":[-79.37660980219999,43.6625061035],"type":"Point"}
}