{
  "type": "Feature",
  "properties": {
    "addr:full":"25 Camilla Cres Scarborough ON M1L 1Y9",
    "addr:housenumber":"25",
    "addr:postcode":"m1l 1y9",
    "addr:street":"Camilla Cres",
    "iso:country":"CA",
    "sg:address":"25 Camilla Cres",
    "sg:city":"Scarborough",
    "sg:classifiers":[
        {
            "category":"Building & Trades",
            "subcategory":"Construction",
            "type":"Services"
        }
    ],
    "sg:phone":"+1 416 750 0973",
    "sg:postcode":"M1L 1Y9",
    "sg:province":"ON",
    "sg:tags":[
        "resurfacing",
        "laying",
        "refinishing",
        "floor"
    ],
    "wof:name":"Albany Flooring Inc",
    "wof:placetype":"venue"
},
  "geometry": {"coordinates":[-79.29164900000001,43.713551],"type":"Point"}
}