{
  "type": "Feature",
  "properties": {
    "addr:full":"189 Westcreek Dr Woodbridge ON L4L 9N6",
    "addr:housenumber":"189",
    "addr:postcode":"l4l 9n6",
    "addr:street":"Westcreek Dr",
    "iso:country":"CA",
    "sg:address":"189 Westcreek Dr",
    "sg:city":"Woodbridge",
    "sg:classifiers":[
        {
            "category":"Wholesale",
            "subcategory":"Groceries",
            "type":"Manufacturing & Wholesale Goods"
        }
    ],
    "sg:phone":"+1 905 265 0441",
    "sg:postcode":"L4L 9N6",
    "sg:province":"ON",
    "sg:tags":[
        "grocer"
    ],
    "wof:name":"Maximum Seafood",
    "wof:placetype":"venue"
},
  "geometry": {"coordinates":[-79.55127,43.813259],"type":"Point"}
}