{
  "type": "Feature",
  "properties": {
    "addr:full":"105 Harewood Cres Fredericton NB E3B 2P4",
    "addr:housenumber":"105",
    "addr:postcode":"e3b 2p4",
    "addr:street":"Harewood Cres",
    "iso:country":"CA",
    "sg:address":"105 Harewood Cres",
    "sg:city":"Fredericton",
    "sg:classifiers":[
        {
            "category":"Health Services",
            "subcategory":"Health Practitioner",
            "type":"Services"
        }
    ],
    "sg:phone":"+1 506 459 3274",
    "sg:postcode":"E3B 2P4",
    "sg:province":"NB",
    "sg:tags":[
        "psychologist"
    ],
    "wof:name":"Bate Boerop, J L D PhD",
    "wof:placetype":"venue"
},
  "geometry": {"coordinates":[-66.66575622560001,45.9611167908],"type":"Point"}
}