{
  "type": "Feature",
  "properties": {
    "addr:full":"RR 1 Coboconk ON K0M 1K0",
    "addr:postcode":"k0m 1k0",
    "addr:street":"Rr 1",
    "iso:country":"CA",
    "sg:address":"RR 1",
    "sg:city":"Coboconk",
    "sg:classifiers":[
        {
            "category":"Travel",
            "subcategory":"Campground",
            "type":"Entertainment"
        }
    ],
    "sg:phone":"+1 705 454 8176",
    "sg:postcode":"K0M 1K0",
    "sg:province":"ON",
    "wof:name":"Trailer Park on the Bay Inc",
    "wof:placetype":"venue"
},
  "geometry": {"coordinates":[-78.797676,44.658997],"type":"Point"}
}