{
  "type": "Feature",
  "properties": {
    "addr:full":"5834 Auburn Cres Duncan BC V9L 4X4",
    "addr:housenumber":"5834",
    "addr:postcode":"v9l 4x4",
    "addr:street":"Auburn Cres",
    "iso:country":"CA",
    "sg:address":"5834 Auburn Cres",
    "sg:city":"Duncan",
    "sg:classifiers":[
        {
            "category":"Health Services",
            "subcategory":"Health Practitioner",
            "type":"Services"
        }
    ],
    "sg:phone":"+1 250 746 1664",
    "sg:postcode":"V9L 4X4",
    "sg:province":"BC",
    "sg:tags":[
        "physiotherapist"
    ],
    "wof:name":"Go West Physiotherapy Clinic",
    "wof:placetype":"venue"
},
  "geometry": {"coordinates":[-123.707382,48.779095],"type":"Point"}
}