{
  "type": "Feature",
  "properties": {
    "iso:country":"CA",
    "sg:address":"5485 Ch DE LA Cote-Saint-Paul",
    "sg:city":"Montreal",
    "sg:classifiers":[
        {
            "category":"Sports & Exercise",
            "subcategory":"Gym",
            "type":"Entertainment"
        }
    ],
    "sg:phone":"+1 514 933 1634",
    "sg:postcode":"H4C 1X3",
    "sg:province":"QC",
    "sg:tags":[
        "club",
        "health",
        "studio",
        "gymnasium"
    ],
    "wof:name":"Geants DE Montreal",
    "wof:placetype":"venue"
},
  "geometry": {"coordinates":[-73.59526824949999,45.4660224915],"type":"Point"}
}