{
  "type": "Feature",
  "properties": {
    "iso:country":"CA",
    "sg:address":"4664 Yonge St",
    "sg:city":"North York",
    "sg:classifiers":[
        {
            "category":"Personal",
            "subcategory":"Beauty Salon",
            "type":"Services"
        }
    ],
    "sg:phone":"+1 416 225 4666",
    "sg:postcode":"M2N 5M1",
    "sg:province":"ON",
    "wof:name":"Salon Fifth Image",
    "wof:placetype":"venue"
},
  "geometry": {"coordinates":[-79.4102630615,43.7580108643],"type":"Point"}
}