{
  "type": "Feature",
  "properties": {
    "addr:full":"7810 Boul Henri-Bourassa O Saint-Laurent QC H4S 1P4",
    "addr:housenumber":"7810",
    "addr:postcode":"h4s 1p4",
    "addr:street":"Boul Henri-Bourassa O",
    "iso:country":"CA",
    "sg:address":"7810 Boul Henri-Bourassa O",
    "sg:city":"Saint-Laurent",
    "sg:classifiers":[
        {
            "category":"Professional",
            "subcategory":"Engineering",
            "type":"Services"
        }
    ],
    "sg:phone":"+1 514 335 7665",
    "sg:postcode":"H4S 1P4",
    "sg:province":"QC",
    "sg:tags":[
        "architectural"
    ],
    "wof:name":"Mds Aero Support Corp",
    "wof:placetype":"venue"
},
  "geometry": {"coordinates":[-73.741356,45.504509],"type":"Point"}
}