{
  "type": "Feature",
  "properties": {
    "addr:full":"332 Av DE Gaspe O Saint-Jean-Port-Joli QC G0R 3G0",
    "addr:postcode":"g0r 3g0",
    "addr:street":"332 Av De Gaspe O",
    "iso:country":"CA",
    "sg:address":"332 Av DE Gaspe O",
    "sg:city":"Saint-Jean-Port-Joli",
    "sg:classifiers":[
        {
            "category":"Shopping",
            "subcategory":"Hobbies, Toys, & Games",
            "type":"Retail Goods"
        }
    ],
    "sg:phone":"+1 418 598 3392",
    "sg:postcode":"G0R 3G0",
    "sg:province":"QC",
    "sg:tags":[
        "craft"
    ],
    "wof:name":"Musee Des Anciens Canadiens",
    "wof:placetype":"venue"
},
  "geometry": {"coordinates":[-70.24858856199999,47.2282180786],"type":"Point"}
}