{
  "type": "Feature",
  "properties": {
    "iso:country":"CA",
    "sg:address":"Copper Beach Ests Hwy 99",
    "sg:city":"Britannia Beach",
    "sg:classifiers":[
        {
            "category":"Restaurant",
            "type":"Food & Drink"
        }
    ],
    "sg:phone":"+1 604 896 2468",
    "sg:postcode":"V0N 1J0",
    "sg:province":"BC",
    "wof:name":"Mountain Woman Take-Out",
    "wof:placetype":"venue"
},
  "geometry": {"coordinates":[-123.20626831,49.6241493225],"type":"Point"}
}