{
  "type": "Feature",
  "properties": {
    "addr:full":"7449 West Saanich Rd Saanichton BC V8M 1R7",
    "addr:housenumber":"7449",
    "addr:postcode":"v8m 1r7",
    "addr:street":"West Saanich Rd",
    "iso:country":"CA",
    "sg:address":"7449 West Saanich Rd",
    "sg:city":"Saanichton",
    "sg:classifiers":[
        {
            "category":"Education",
            "subcategory":"School",
            "type":"Public Place"
        }
    ],
    "sg:phone":"+1 250 652 2313",
    "sg:postcode":"V8M 1R7",
    "sg:province":"BC",
    "wof:name":"Saanich Indian School Board",
    "wof:placetype":"venue"
},
  "geometry": {"coordinates":[-123.41689300500001,48.595199585],"type":"Point"}
}