{
  "type": "Feature",
  "properties": {
    "iso:country":"CA",
    "sg:address":"107 Manitou Dr",
    "sg:city":"Kitchener",
    "sg:classifiers":[
        {
            "category":"Wholesale",
            "subcategory":"Electrical",
            "type":"Manufacturing & Wholesale Goods"
        }
    ],
    "sg:phone":"+1 519 893 1932",
    "sg:postcode":"N2C 1L4",
    "sg:province":"ON",
    "sg:tags":[
        "equipment",
        "electric",
        "supply"
    ],
    "wof:name":"Gerrie Electric Wholesale Ltd",
    "wof:placetype":"venue"
},
  "geometry": {"coordinates":[-80.44956970210001,43.4123191833],"type":"Point"}
}