{
  "type": "Feature",
  "properties": {
    "iso:country":"CA",
    "sg:address":"348 Lyndock St",
    "sg:city":"Corunna",
    "sg:classifiers":[
        {
            "category":"Health Services",
            "subcategory":"Doctor",
            "type":"Services"
        }
    ],
    "sg:phone":"+1 519 862 1471",
    "sg:postcode":"N0N 1G0",
    "sg:province":"ON",
    "sg:tags":[
        "physician",
        "surgeon"
    ],
    "wof:name":"Corunna Medical Clinic",
    "wof:placetype":"venue"
},
  "geometry": {"coordinates":[-82.45305633540001,42.8913421631],"type":"Point"}
}