{
  "type": "Feature",
  "properties": {
    "addr:full":"1426 Lindsay St Regina SK S4N 3B6",
    "addr:housenumber":"1426",
    "addr:postcode":"s4n 3b6",
    "addr:street":"Lindsay St",
    "iso:country":"CA",
    "sg:address":"1426 Lindsay St",
    "sg:city":"Regina",
    "sg:classifiers":[
        {
            "category":"Farming",
            "subcategory":"Farm & Veterinary Services",
            "type":"Manufacturing & Wholesale Goods"
        }
    ],
    "sg:phone":"+1 306 757 8332",
    "sg:postcode":"S4N 3B6",
    "sg:province":"SK",
    "sg:tags":[
        "control",
        "weed"
    ],
    "wof:name":"AAA Weed Control Svc Ltd",
    "wof:placetype":"venue"
},
  "geometry": {"coordinates":[-104.585212708,50.4559898376],"type":"Point"}
}