{
  "type": "Feature",
  "properties": {
    "addr:full":"6767 Boul Newman Lasalle QC H8N 3E4",
    "addr:housenumber":"6767",
    "addr:postcode":"h8n 3e4",
    "addr:street":"Boul Newman",
    "iso:country":"CA",
    "sg:address":"6767 Boul Newman",
    "sg:city":"Lasalle",
    "sg:classifiers":[
        {
            "category":"Food & Beverages",
            "subcategory":"Groceries & Convenience Stores",
            "type":"Retail Goods"
        }
    ],
    "sg:phone":"+1 514 364 7168",
    "sg:postcode":"H8N 3E4",
    "sg:province":"QC",
    "sg:tags":[
        "grocer"
    ],
    "wof:name":"Loblaws",
    "wof:placetype":"venue"
},
  "geometry": {"coordinates":[-73.60805499999999,45.449535],"type":"Point"}
}