{
  "type": "Feature",
  "properties": {
    "iso:country":"CA",
    "sg:address":"1750 Rue Sauriol E",
    "sg:city":"Montreal",
    "sg:classifiers":[
        {
            "category":"Sports & Exercise",
            "subcategory":"Gym",
            "type":"Entertainment"
        }
    ],
    "sg:phone":"+1 514 382 4121",
    "sg:postcode":"H2C 1X4",
    "sg:province":"QC",
    "sg:tags":[
        "club",
        "health",
        "studio",
        "gymnasium"
    ],
    "wof:name":"Centre Culturel & Sportif Reg",
    "wof:placetype":"venue"
},
  "geometry": {"coordinates":[-73.651031,45.565651],"type":"Point"}
}