{
  "type": "Feature",
  "properties": {
    "iso:country":"CA",
    "sg:address":"8 Rue Jeannotte",
    "sg:city":"Vaudreuil-Dorion",
    "sg:classifiers":[
        {
            "category":"Education",
            "subcategory":"School",
            "type":"Public Place"
        }
    ],
    "sg:phone":"+1 514 477 7010",
    "sg:postcode":"J7V 1E4",
    "sg:province":"QC",
    "wof:name":"Ecole Saint-Michel",
    "wof:placetype":"venue"
},
  "geometry": {"coordinates":[-74.0281219482,45.3983612061],"type":"Point"}
}