{
  "type": "Feature",
  "properties": {
    "iso:country":"CA",
    "sg:address":"2215 Midland Ave",
    "sg:city":"Scarborough",
    "sg:classifiers":[
        {
            "category":"Autos & Motor Vehicles",
            "subcategory":"Auto Supplies",
            "type":"Retail Goods"
        }
    ],
    "sg:phone":"+1 416 297 9444",
    "sg:postcode":"M1P 3E7",
    "sg:province":"ON",
    "sg:tags":[
        "tire"
    ],
    "wof:name":"Triple A Tire Inc",
    "wof:placetype":"venue"
},
  "geometry": {"coordinates":[-79.273193,43.773888],"type":"Point"}
}