{
  "type": "Feature",
  "properties": {
    "addr:full":"Scarborough ON M1H 3G2",
    "addr:postcode":"m1h 3g2",
    "iso:country":"CA",
    "sg:city":"Scarborough",
    "sg:classifiers":[
        {
            "category":"Professional",
            "subcategory":"Employment Agencies",
            "type":"Services"
        }
    ],
    "sg:phone":"+1 416 290 6790",
    "sg:postcode":"M1H 3G2",
    "sg:province":"ON",
    "sg:tags":[
        "opportunity"
    ],
    "wof:name":"Kelly Services",
    "wof:placetype":"venue"
},
  "geometry": {"coordinates":[-79.25132000000001,43.779396],"type":"Point"}
}