{
  "type": "Feature",
  "properties": {
    "addr:full":"1069 Boul Dr Albiny-Paquette Mont-Laurier QC J9L 1M4",
    "addr:housenumber":"1069",
    "addr:postcode":"j9l 1m4",
    "addr:street":"Boul Dr Albiny-Paquette",
    "iso:country":"CA",
    "sg:address":"1069 Boul Dr Albiny-Paquette",
    "sg:city":"Mont-Laurier",
    "sg:classifiers":[
        {
            "category":"Personal",
            "subcategory":"Beauty Salon",
            "type":"Services"
        }
    ],
    "sg:phone":"+1 819 623 5092",
    "sg:postcode":"J9L 1M4",
    "sg:province":"QC",
    "wof:name":"Salon DE Coiffure Lili",
    "wof:placetype":"venue"
},
  "geometry": {"coordinates":[-75.4828872681,46.5511703491],"type":"Point"}
}