{
  "type": "Feature",
  "properties": {
    "addr:full":"616 Av Saint-Redempteur Matane QC G4W 1L1",
    "addr:postcode":"g4w 1l1",
    "addr:street":"616 Av Saint-Redempteur",
    "iso:country":"CA",
    "sg:address":"616 Av Saint-Redempteur",
    "sg:city":"Matane",
    "sg:classifiers":[
        {
            "category":"Government",
            "subcategory":"Office",
            "type":"Public Place"
        }
    ],
    "sg:phone":"+1 418 560 8244",
    "sg:postcode":"G4W 1L1",
    "sg:province":"QC",
    "wof:name":"Quebec Agriculture",
    "wof:placetype":"venue"
},
  "geometry": {"coordinates":[-67.50258599999999,48.840466],"type":"Point"}
}