{
  "type": "Feature",
  "properties": {
    "iso:country":"CA",
    "sg:address":"499 Oxford St E",
    "sg:city":"London",
    "sg:classifiers":[
        {
            "category":"Health Services",
            "subcategory":"Doctor",
            "type":"Services"
        }
    ],
    "sg:phone":"+1 519 672 1495",
    "sg:postcode":"N5Y 3H8",
    "sg:province":"ON",
    "sg:tags":[
        "physician",
        "surgeon"
    ],
    "wof:name":"London Doctors' Relief Svc",
    "wof:placetype":"venue"
},
  "geometry": {"coordinates":[-81.24201965330001,42.998664856],"type":"Point"}
}