{
  "type": "Feature",
  "properties": {
    "iso:country":"CA",
    "sg:address":"8 Old Rd",
    "sg:city":"Grand Bank",
    "sg:classifiers":[
        {
            "category":"Retail",
            "subcategory":"Repair Shop",
            "type":"Services"
        }
    ],
    "sg:phone":"+1 709 832 1971",
    "sg:postcode":"A0E 1W0",
    "sg:province":"NL",
    "sg:tags":[
        "upholsterer"
    ],
    "wof:name":"Herridge's Upholstery",
    "wof:placetype":"venue"
},
  "geometry": {"coordinates":[-55.7579421997,47.0944137573],"type":"Point"}
}