{
  "type": "Feature",
  "properties": {
    "addr:full":"13 Kinsman Crt Fonthill ON L0S 1E3",
    "addr:housenumber":"13",
    "addr:postcode":"l0s 1e3",
    "addr:street":"Kinsman Crt",
    "iso:country":"CA",
    "sg:address":"13 Kinsman Crt",
    "sg:city":"Fonthill",
    "sg:classifiers":[
        {
            "category":"Banks & Credit Unions",
            "subcategory":"Financial Services",
            "type":"Services"
        }
    ],
    "sg:phone":"+1 905 892 1314",
    "sg:postcode":"L0S 1E3",
    "sg:province":"ON",
    "sg:tags":[
        "annuity",
        "insurance"
    ],
    "wof:name":"Annuity Benefits",
    "wof:placetype":"venue"
},
  "geometry": {"coordinates":[-79.283981,43.047585],"type":"Point"}
}