{
  "type": "Feature",
  "properties": {
    "addr:full":"6062 Main St Niagara Falls ON L2G 5Z9",
    "addr:housenumber":"6062",
    "addr:postcode":"l2g 5z9",
    "addr:street":"Main St",
    "iso:country":"CA",
    "sg:address":"6062 Main St",
    "sg:city":"Niagara Falls",
    "sg:classifiers":[
        {
            "category":"Retail",
            "subcategory":"Funeral Services",
            "type":"Services"
        }
    ],
    "sg:phone":"+1 905 358 3513",
    "sg:postcode":"L2G 5Z9",
    "sg:province":"ON",
    "sg:tags":[
        "director"
    ],
    "wof:name":"Patterson Funeral Home",
    "wof:placetype":"venue"
},
  "geometry": {"coordinates":[-79.091492,43.08688],"type":"Point"}
}