{
  "type": "Feature",
  "properties": {
    "addr:full":"5779 Boul Des Grandes-Prairies Saint-Leonard QC H1R 1B3",
    "addr:housenumber":"5779",
    "addr:postcode":"h1r 1b3",
    "addr:street":"Boul Des Grandes-Prairies",
    "iso:country":"CA",
    "sg:address":"5779 Boul Des Grandes-Prairies",
    "sg:city":"Saint-Leonard",
    "sg:classifiers":[
        {
            "category":"Restaurant",
            "type":"Food & Drink"
        }
    ],
    "sg:phone":"+1 514 955 9359",
    "sg:postcode":"H1R 1B3",
    "sg:province":"QC",
    "wof:name":"Nickels",
    "wof:placetype":"venue"
},
  "geometry": {"coordinates":[-73.6128692627,45.5980758667],"type":"Point"}
}