{
  "type": "Feature",
  "properties": {
    "addr:full":"45701 Berkeley Ave Chilliwack BC V2P 3N1",
    "addr:housenumber":"45701",
    "addr:postcode":"v2p 3n1",
    "addr:street":"Berkeley Ave",
    "iso:country":"CA",
    "sg:address":"45701 Berkeley Ave",
    "sg:city":"Chilliwack",
    "sg:classifiers":[
        {
            "category":"Building & Trades",
            "subcategory":"Cleaning & Sanitation",
            "type":"Services"
        }
    ],
    "sg:phone":"+1 604 795 6546",
    "sg:postcode":"V2P 3N1",
    "sg:province":"BC",
    "sg:tags":[
        "house"
    ],
    "wof:name":"Sal's Cleaning Svc",
    "wof:placetype":"venue"
},
  "geometry": {"coordinates":[-121.959816,49.181023],"type":"Point"}
}