{
  "type": "Feature",
  "properties": {
    "addr:full":"2445 Canoe Ave Coquitlam BC V3K 6A9",
    "addr:housenumber":"2445",
    "addr:postcode":"v3k 6a9",
    "addr:street":"Canoe Ave",
    "iso:country":"CA",
    "sg:address":"2445 Canoe Ave",
    "sg:city":"Coquitlam",
    "sg:classifiers":[
        {
            "category":"Wholesale",
            "subcategory":"Auto Parts",
            "type":"Manufacturing & Wholesale Goods"
        }
    ],
    "sg:phone":"+1 604 464 6554",
    "sg:postcode":"V3K 6A9",
    "sg:province":"BC",
    "sg:tags":[
        "tire",
        "supply"
    ],
    "wof:name":"Yokohama Tire Canada Inc",
    "wof:placetype":"venue"
},
  "geometry": {"coordinates":[-122.821922,49.22982],"type":"Point"}
}