{
  "type": "Feature",
  "properties": {
    "iso:country":"CA",
    "sg:address":"153 First Ave W",
    "sg:city":"Qualicum Beach",
    "sg:classifiers":[
        {
            "category":"Building & Trades",
            "subcategory":"Construction",
            "type":"Services"
        }
    ],
    "sg:phone":"+1 250 752 0363",
    "sg:postcode":"V9K 1G9",
    "sg:province":"BC",
    "sg:tags":[
        "masonry",
        "fireplace",
        "cleaning",
        "chimney",
        "contractor"
    ],
    "wof:name":"Focal Point Masonry & Chimney",
    "wof:placetype":"venue"
},
  "geometry": {"coordinates":[-124.445777893,49.3484764099],"type":"Point"}
}