{
  "type": "Feature",
  "properties": {
    "addr:full":"Govan SK S0G 1Z0",
    "addr:postcode":"s0g 1z0",
    "addr:street":"Govan",
    "iso:country":"CA",
    "sg:city":"Govan",
    "sg:classifiers":[
        {
            "category":"Organizations",
            "subcategory":"Religious Organization",
            "type":"Services"
        }
    ],
    "sg:phone":"+1 306 484 2110",
    "sg:postcode":"S0G 1Z0",
    "sg:province":"SK",
    "sg:tags":[
        "church"
    ],
    "wof:name":"Prince of Peace Lutheran Chr",
    "wof:placetype":"venue"
},
  "geometry": {"coordinates":[-104.991844,51.311275],"type":"Point"}
}