{
  "type": "Feature",
  "properties": {
    "addr:full":"13 Union St Corner Brook NL A2H 5M7",
    "addr:housenumber":"13",
    "addr:postcode":"a2h 5m7",
    "addr:street":"Union St",
    "iso:country":"CA",
    "sg:address":"13 Union St",
    "sg:city":"Corner Brook",
    "sg:classifiers":[
        {
            "category":"Cinema",
            "subcategory":"Movie Rental",
            "type":"Entertainment"
        }
    ],
    "sg:phone":"+1 709 639 7790",
    "sg:postcode":"A2H 5M7",
    "sg:province":"NL",
    "sg:tags":[
        "leasing",
        "video",
        "disc",
        "tape"
    ],
    "wof:name":"Jumbo Video",
    "wof:placetype":"venue"
},
  "geometry": {"coordinates":[-57.9497146606,48.9428825378],"type":"Point"}
}