{
  "type": "Feature",
  "properties": {
    "addr:full":"807 25 Ave Nisku AB T9E 7Z4",
    "addr:postcode":"t9e 7z4",
    "addr:street":"807 25 Ave",
    "iso:country":"CA",
    "sg:address":"807 25 Ave",
    "sg:city":"Nisku",
    "sg:classifiers":[
        {
            "category":"Building & Trades",
            "subcategory":"Construction",
            "type":"Services"
        }
    ],
    "sg:phone":"+1 780 955 7011",
    "sg:postcode":"T9E 7Z4",
    "sg:province":"AB",
    "sg:tags":[
        "boring",
        "oil",
        "well",
        "drilling",
        "contractor"
    ],
    "wof:name":"Precision Drilling",
    "wof:placetype":"venue"
},
  "geometry": {"coordinates":[-113.515457,53.352287],"type":"Point"}
}