{
  "type": "Feature",
  "properties": {
    "addr:full":"Laval QC H7S 2K6",
    "addr:postcode":"h7s 2k6",
    "iso:country":"CA",
    "sg:city":"Laval",
    "sg:classifiers":[
        {
            "category":"Restaurant",
            "type":"Food & Drink"
        }
    ],
    "sg:phone":"+1 450 973 6252",
    "sg:postcode":"H7S 2K6",
    "sg:province":"QC",
    "wof:name":"Ben Buff",
    "wof:placetype":"venue"
},
  "geometry": {"coordinates":[-73.729378,45.56284],"type":"Point"}
}