{
  "type": "Feature",
  "properties": {
    "addr:full":"500 Av Du Mont-Cassin Montreal QC H3L 1W6",
    "addr:housenumber":"500",
    "addr:postcode":"h3l 1w6",
    "addr:street":"Av Du Mont-Cassin",
    "iso:country":"CA",
    "sg:address":"500 Av Du Mont-Cassin",
    "sg:city":"Montreal",
    "sg:classifiers":[
        {
            "category":"Education",
            "subcategory":"School",
            "type":"Public Place"
        }
    ],
    "sg:phone":"+1 514 596 5206",
    "sg:postcode":"H3L 1W6",
    "sg:province":"QC",
    "wof:name":"Ecole St-Benoit",
    "wof:placetype":"venue"
},
  "geometry": {"coordinates":[-73.66815200000001,45.540718],"type":"Point"}
}