{
  "type": "Feature",
  "properties": {
    "addr:full":"3K Morice River Rd Houston BC V0J 1Z0",
    "addr:postcode":"v0j 1z0",
    "addr:street":"River Rd",
    "iso:country":"CA",
    "sg:address":"3K Morice River Rd",
    "sg:city":"Houston",
    "sg:classifiers":[
        {
            "category":"Manufacturing",
            "subcategory":"Lumber",
            "type":"Manufacturing & Wholesale Goods"
        }
    ],
    "sg:phone":"+1 250 845 7585",
    "sg:postcode":"V0J 1Z0",
    "sg:province":"BC",
    "wof:name":"Pleasant Valley Remanufacturng",
    "wof:placetype":"venue"
},
  "geometry": {"coordinates":[-126.711936951,54.3898162842],"type":"Point"}
}