{
  "type": "Feature",
  "properties": {
    "iso:country":"CA",
    "sg:address":"10 Fincham Ave",
    "sg:city":"Markham",
    "sg:classifiers":[
        {
            "category":"Food & Beverages",
            "subcategory":"Groceries & Convenience Stores",
            "type":"Retail Goods"
        }
    ],
    "sg:phone":"+1 905 471 3198",
    "sg:postcode":"L3P 4C8",
    "sg:province":"ON",
    "wof:name":"Jaggar's Convenience Inc",
    "wof:placetype":"venue"
},
  "geometry": {"coordinates":[-79.2582855225,43.8929672241],"type":"Point"}
}