{
  "type": "Feature",
  "properties": {
    "iso:country":"CA",
    "sg:address":"459 Conception Bay Hwy",
    "sg:city":"Conception Bay South",
    "sg:classifiers":[
        {
            "category":"Autos & Motor Vehicles",
            "subcategory":"Auto Supplies",
            "type":"Retail Goods"
        }
    ],
    "sg:phone":"+1 709 834 8000",
    "sg:postcode":"A1X 2B4",
    "sg:province":"NL",
    "sg:tags":[
        "automobile",
        "parts"
    ],
    "wof:name":"Uap Napa Auto Parts",
    "wof:placetype":"venue"
},
  "geometry": {"coordinates":[-52.9874687195,47.5083503723],"type":"Point"}
}