{
  "type": "Feature",
  "properties": {
    "iso:country":"CA",
    "sg:address":"3415 Dixie Rd",
    "sg:city":"Mississauga",
    "sg:classifiers":[
        {
            "category":"Restaurant",
            "type":"Food & Drink"
        }
    ],
    "sg:phone":"+1 905 624 9099",
    "sg:postcode":"L4Y 2B1",
    "sg:province":"ON",
    "wof:name":"Banh MI Tan Vinh",
    "wof:placetype":"venue"
},
  "geometry": {"coordinates":[-79.5953292847,43.6174850464],"type":"Point"}
}