{
  "type": "Feature",
  "properties": {
    "addr:full":"Montreal QC H4P 1W9",
    "addr:postcode":"h4p 1w9",
    "iso:country":"CA",
    "sg:city":"Montreal",
    "sg:classifiers":[
        {
            "category":"Restaurant",
            "type":"Food & Drink"
        }
    ],
    "sg:phone":"+1 514 739 7939",
    "sg:postcode":"H4P 1W9",
    "sg:province":"QC",
    "wof:name":"Multi Restaurants Inc",
    "wof:placetype":"venue"
},
  "geometry": {"coordinates":[-73.6490097046,45.4975395203],"type":"Point"}
}