{
  "type": "Feature",
  "properties": {
    "iso:country":"CA",
    "sg:address":"7053 Arthur Rd 2 RR 5",
    "sg:city":"Mount Forest",
    "sg:classifiers":[
        {
            "category":"Building & Trades",
            "subcategory":"Plumbing",
            "type":"Services"
        }
    ],
    "sg:phone":"+1 519 323 2569",
    "sg:postcode":"N0G 2L0",
    "sg:province":"ON",
    "sg:tags":[
        "tank",
        "septic"
    ],
    "wof:name":"Wayne Weidemann Contracting",
    "wof:placetype":"venue"
},
  "geometry": {"coordinates":[-81.9993438721,43.0979690552],"type":"Point"}
}