{
  "type": "Feature",
  "properties": {
    "addr:full":"418 Queen St W Toronto ON M5V 2A7",
    "addr:housenumber":"418",
    "addr:postcode":"m5v 2a7",
    "addr:street":"Queen St W",
    "iso:country":"CA",
    "sg:address":"418 Queen St W",
    "sg:city":"Toronto",
    "sg:classifiers":[
        {
            "category":"Shopping",
            "subcategory":"Gifts & Souvenirs",
            "type":"Retail Goods"
        }
    ],
    "sg:phone":"+1 416 504 0475",
    "sg:postcode":"M5V 2A7",
    "sg:province":"ON",
    "sg:tags":[
        "shop"
    ],
    "wof:name":"Artzy Phartzy",
    "wof:placetype":"venue"
},
  "geometry": {"coordinates":[-79.3978347778,43.6485595703],"type":"Point"}
}