{
  "type": "Feature",
  "properties": {
    "addr:full":"Montreal QC H3C 1C7",
    "addr:postcode":"h3c 1c7",
    "iso:country":"CA",
    "sg:city":"Montreal",
    "sg:classifiers":[
        {
            "category":"Travel",
            "subcategory":"Travel Agent",
            "type":"Entertainment"
        }
    ],
    "sg:phone":"+1 514 861 2897",
    "sg:postcode":"H3C 1C7",
    "sg:province":"QC",
    "sg:tags":[
        "agency",
        "bureau"
    ],
    "wof:name":"Varaplaya Tours Inc",
    "wof:placetype":"venue"
},
  "geometry": {"coordinates":[-73.56066131590001,45.5008773804],"type":"Point"}
}