{
  "type": "Feature",
  "properties": {
    "addr:full":"215 Rue Celina Terrebonne QC J6Y 1M8",
    "addr:housenumber":"215",
    "addr:postcode":"j6y 1m8",
    "addr:street":"Rue Celina",
    "iso:country":"CA",
    "sg:address":"215 Rue Celina",
    "sg:city":"Terrebonne",
    "sg:classifiers":[
        {
            "category":"Building & Trades",
            "subcategory":"Plumbing",
            "type":"Services"
        }
    ],
    "sg:phone":"+1 450 621 8461",
    "sg:postcode":"J6Y 1M8",
    "sg:province":"QC",
    "sg:tags":[
        "refrigeration",
        "heating",
        "contractor"
    ],
    "wof:name":"Climatisation Profair Inc",
    "wof:placetype":"venue"
},
  "geometry": {"coordinates":[-73.74621582029999,45.6769142151],"type":"Point"}
}