{
  "type": "Feature",
  "properties": {
    "addr:full":"1037 Bev Mclachlin Dr Pincher Creek AB T0K 1W0",
    "addr:housenumber":"1037",
    "addr:postcode":"t0k 1w0",
    "addr:street":"Bev Mclachlin Dr Pincher",
    "iso:country":"CA",
    "sg:address":"1037 Bev Mclachlin Dr",
    "sg:city":"Pincher Creek",
    "sg:classifiers":[
        {
            "category":"Museum",
            "type":"Entertainment"
        }
    ],
    "sg:phone":"+1 403 627 3684",
    "sg:postcode":"T0K 1W0",
    "sg:province":"AB",
    "wof:name":"Kootenai Brown Pioneer Village",
    "wof:placetype":"venue"
},
  "geometry": {"coordinates":[-113.946235657,49.4865989685],"type":"Point"}
}