{
  "type": "Feature",
  "properties": {
    "addr:full":"Timmins ON P4N 7J5",
    "addr:postcode":"p4n 7j5",
    "iso:country":"CA",
    "sg:city":"Timmins",
    "sg:classifiers":[
        {
            "category":"Building & Trades",
            "subcategory":"Electrical",
            "type":"Services"
        }
    ],
    "sg:phone":"+1 705 268 2262",
    "sg:postcode":"P4N 7J5",
    "sg:province":"ON",
    "sg:tags":[
        "electric",
        "contractor"
    ],
    "wof:name":"Par Energy Electrical",
    "wof:placetype":"venue"
},
  "geometry": {"coordinates":[-81.318428,48.476658],"type":"Point"}
}