{
  "type": "Feature",
  "properties": {
    "addr:full":"Saint-Jean-Sur-Richelieu QC J3A 1M1",
    "addr:postcode":"j3a 1m1",
    "iso:country":"CA",
    "sg:city":"Saint-Jean-Sur-Richelieu",
    "sg:classifiers":[
        {
            "category":"Shopping",
            "subcategory":"Shoes",
            "type":"Retail Goods"
        }
    ],
    "sg:phone":"+1 450 348 8528",
    "sg:postcode":"J3A 1M1",
    "sg:province":"QC",
    "wof:name":"Chaussures Confort",
    "wof:placetype":"venue"
},
  "geometry": {"coordinates":[-73.281479,45.331577],"type":"Point"}
}