{
  "type": "Feature",
  "properties": {
    "iso:country":"CA",
    "sg:address":"5770 Boul Royal",
    "sg:city":"Shawinigan",
    "sg:classifiers":[
        {
            "category":"Home & Garden",
            "subcategory":"Building Materials",
            "type":"Retail Goods"
        }
    ],
    "sg:phone":"+1 819 539 8331",
    "sg:postcode":"G9N 4R8",
    "sg:province":"QC",
    "sg:tags":[
        "glass",
        "window",
        "plate"
    ],
    "wof:name":"Lebeau Vitres D'Autos",
    "wof:placetype":"venue"
},
  "geometry": {"coordinates":[-72.7224578857,46.5716972351],"type":"Point"}
}