{
  "type": "Feature",
  "properties": {
    "addr:full":"392 Kingsway Vancouver BC V5T 3J8",
    "addr:housenumber":"392",
    "addr:postcode":"v5t 3j8",
    "addr:street":"Kingsway",
    "iso:country":"CA",
    "sg:address":"392 Kingsway",
    "sg:city":"Vancouver",
    "sg:classifiers":[
        {
            "category":"Home & Garden",
            "subcategory":"Building Materials",
            "type":"Retail Goods"
        }
    ],
    "sg:phone":"+1 604 876 3331",
    "sg:postcode":"V5T 3J8",
    "sg:province":"BC",
    "sg:tags":[
        "glass",
        "window",
        "plate"
    ],
    "wof:name":"Speedy Auto & Window Glass",
    "wof:placetype":"venue"
},
  "geometry": {"coordinates":[-123.09672500000001,49.259808],"type":"Point"}
}