{
  "type": "Feature",
  "properties": {
    "addr:full":"4604 Penhallow Rd Mississauga ON L5V 1E8",
    "addr:housenumber":"4604",
    "addr:postcode":"l5v 1e8",
    "addr:street":"Penhallow Rd",
    "iso:country":"CA",
    "sg:address":"4604 Penhallow Rd",
    "sg:city":"Mississauga",
    "sg:classifiers":[
        {
            "category":"Professional",
            "subcategory":"Computer Services",
            "type":"Services"
        }
    ],
    "sg:phone":"+1 905 502 5705",
    "sg:postcode":"L5V 1E8",
    "sg:province":"ON",
    "sg:tags":[
        "consultant"
    ],
    "wof:name":"Terenzio, Daniel",
    "wof:placetype":"venue"
},
  "geometry": {"coordinates":[-79.675583,43.584805],"type":"Point"}
}