{
  "type": "Feature",
  "properties": {
    "addr:full":"211 Rte 132 E Saint-Fabien QC G0L 2Z0",
    "addr:housenumber":"211",
    "addr:postcode":"g0l 2z0",
    "addr:street":"Rte 132 E Saint-Fabien",
    "iso:country":"CA",
    "sg:address":"211 Rte 132 E",
    "sg:city":"Saint-Fabien",
    "sg:classifiers":[
        {
            "category":"Home & Garden",
            "subcategory":"Furniture",
            "type":"Retail Goods"
        }
    ],
    "sg:phone":"+1 418 869 2859",
    "sg:postcode":"G0L 2Z0",
    "sg:province":"QC",
    "wof:name":"Remises Du Bas St-Laurent Enr",
    "wof:placetype":"venue"
},
  "geometry": {"coordinates":[-68.928375,48.267315],"type":"Point"}
}