{
  "type": "Feature",
  "properties": {
    "addr:full":"4917 Pemberton Rd Port Alberni BC V9Y 5J8",
    "addr:housenumber":"4917",
    "addr:postcode":"v9y 5j8",
    "addr:street":"Pemberton Rd",
    "iso:country":"CA",
    "sg:address":"4917 Pemberton Rd",
    "sg:city":"Port Alberni",
    "sg:classifiers":[
        {
            "category":"Government",
            "subcategory":"Office",
            "type":"Public Place"
        }
    ],
    "sg:phone":"+1 250 724 9290",
    "sg:postcode":"V9Y 5J8",
    "sg:province":"BC",
    "wof:name":"BC Conservation Officer",
    "wof:placetype":"venue"
},
  "geometry": {"coordinates":[-124.80941,49.256081],"type":"Point"}
}