{
  "type": "Feature",
  "properties": {
    "iso:country":"CA",
    "sg:address":"224 Av Joseph-Casavant",
    "sg:city":"Beauport",
    "sg:classifiers":[
        {
            "category":"Shopping",
            "subcategory":"Department Store",
            "type":"Retail Goods"
        }
    ],
    "sg:phone":"+1 418 660 4943",
    "sg:postcode":"G1C 7Z3",
    "sg:province":"QC",
    "wof:name":"Wal-Mart",
    "wof:placetype":"venue"
},
  "geometry": {"coordinates":[-71.206604,46.868553],"type":"Point"}
}