{
  "type": "Feature",
  "properties": {
    "addr:full":"595 Rue Saint-Charles-Borromee Joliette QC J6E 4S7",
    "addr:housenumber":"595",
    "addr:postcode":"j6e 4s7",
    "addr:street":"Rue Saint-Charles-Borromee",
    "iso:country":"CA",
    "sg:address":"595 Rue Saint-Charles-Borromee",
    "sg:city":"Joliette",
    "sg:classifiers":[
        {
            "category":"Restaurant",
            "type":"Food & Drink"
        }
    ],
    "sg:phone":"+1 450 759 7490",
    "sg:postcode":"J6E 4S7",
    "sg:province":"QC",
    "wof:name":"Mc Donald's",
    "wof:placetype":"venue"
},
  "geometry": {"coordinates":[-73.443146,46.037323],"type":"Point"}
}