{
  "type": "Feature",
  "properties": {
    "addr:full":"910 Applecross Dr East St Paul MB R2E 0G5",
    "addr:housenumber":"910",
    "addr:postcode":"r2e 0g5",
    "addr:street":"Applecross Dr",
    "iso:country":"CA",
    "sg:address":"910 Applecross Dr",
    "sg:city":"East St Paul",
    "sg:classifiers":[
        {
            "category":"Professional",
            "subcategory":"Business Services",
            "type":"Services"
        }
    ],
    "sg:phone":"+1 204 661 8581",
    "sg:postcode":"R2E 0G5",
    "sg:province":"MB",
    "sg:tags":[
        "water",
        "alarm",
        "burglar",
        "system",
        "treatment"
    ],
    "wof:name":"All Seasons Home Furnishings",
    "wof:placetype":"venue"
},
  "geometry": {"coordinates":[-97.02048499999999,49.976517],"type":"Point"}
}