{
  "type": "Feature",
  "properties": {
    "iso:country":"CA",
    "sg:address":"910 Applecross Dr",
    "sg:city":"East St Paul",
    "sg:classifiers":[
        {
            "category":"Professional",
            "subcategory":"Business Services",
            "type":"Services"
        }
    ],
    "sg:phone":"+1 204 661 8581",
    "sg:postcode":"R2E 0G5",
    "sg:province":"MB",
    "sg:tags":[
        "water",
        "alarm",
        "burglar",
        "system",
        "treatment"
    ],
    "wof:name":"All Seasons Home Furnishings",
    "wof:placetype":"venue"
},
  "geometry": {"coordinates":[-97.020485,49.976517],"type":"Point"}
}