{
  "type": "Feature",
  "properties": {
    "addr:full":"Grand Valley ON L0N 1G0",
    "addr:postcode":"l0n 1g0",
    "iso:country":"CA",
    "sg:city":"Grand Valley",
    "sg:classifiers":[
        {
            "category":"Arts & Performance",
            "subcategory":"Theater",
            "type":"Entertainment"
        }
    ],
    "sg:phone":"+1 519 928 5929",
    "sg:postcode":"L0N 1G0",
    "sg:province":"ON",
    "sg:tags":[
        "equipment",
        "theatrical",
        "supply"
    ],
    "wof:name":"Shock Lighting",
    "wof:placetype":"venue"
},
  "geometry": {"coordinates":[-80.315613,43.90041],"type":"Point"}
}