{
  "type": "Feature",
  "properties": {
    "addr:full":"372 Hatfield Cres Orleans ON K1E 1M8",
    "addr:housenumber":"372",
    "addr:postcode":"k1e 1m8",
    "addr:street":"Hatfield Cres",
    "iso:country":"CA",
    "sg:address":"372 Hatfield Cres",
    "sg:city":"Orleans",
    "sg:classifiers":[
        {
            "category":"Health Services",
            "subcategory":"Doctor",
            "type":"Services"
        }
    ],
    "sg:phone":"+1 613 824 6221",
    "sg:postcode":"K1E 1M8",
    "sg:province":"ON",
    "sg:tags":[
        "dentist"
    ],
    "wof:name":"Outreach Dental Care Group",
    "wof:placetype":"venue"
},
  "geometry": {"coordinates":[-75.49915300000001,45.474087],"type":"Point"}
}