{
  "type": "Feature",
  "properties": {
    "addr:full":"329 Irwin St Prince George BC V2M 2X4",
    "addr:housenumber":"329",
    "addr:postcode":"v2m 2x4",
    "addr:street":"Irwin St",
    "iso:country":"CA",
    "sg:address":"329 Irwin St",
    "sg:city":"Prince George",
    "sg:classifiers":[
        {
            "category":"Building & Trades",
            "subcategory":"Plumbing",
            "type":"Services"
        }
    ],
    "sg:phone":"+1 250 563 5445",
    "sg:postcode":"V2M 2X4",
    "sg:province":"BC",
    "sg:tags":[
        "heating",
        "contractor"
    ],
    "wof:name":"Bruno's Heating",
    "wof:placetype":"venue"
},
  "geometry": {"coordinates":[-122.77847300000001,53.922203],"type":"Point"}
}