{
  "type": "Feature",
  "properties": {
    "iso:country":"CA",
    "sg:address":"36 Rutherford Ave",
    "sg:city":"Deep River",
    "sg:classifiers":[
        {
            "category":"Organizations",
            "subcategory":"Religious Organization",
            "type":"Services"
        }
    ],
    "sg:phone":"+1 613 584 2838",
    "sg:postcode":"K0J 1P0",
    "sg:province":"ON",
    "sg:tags":[
        "church"
    ],
    "wof:name":"Free Methodist Church",
    "wof:placetype":"venue"
},
  "geometry": {"coordinates":[-77.4967803955,46.0999031067],"type":"Point"}
}