{
  "type": "Feature",
  "properties": {
    "addr:full":"11865 Highway 1 Wolfville NS B4P 2R3",
    "addr:housenumber":"11865",
    "addr:postcode":"b4p 2r3",
    "addr:street":"Highway 1",
    "iso:country":"CA",
    "sg:address":"11865 Highway 1",
    "sg:city":"Wolfville",
    "sg:classifiers":[
        {
            "category":"Restaurant",
            "type":"Food & Drink"
        }
    ],
    "sg:phone":"+1 902 542 7474",
    "sg:postcode":"B4P 2R3",
    "sg:province":"NS",
    "sg:tags":[
        "shop",
        "coffee"
    ],
    "wof:name":"Just US Coffee",
    "wof:placetype":"venue"
},
  "geometry": {"coordinates":[-64.36320495610001,45.0913543701],"type":"Point"}
}