{
  "type": "Feature",
  "properties": {
    "iso:country":"CA",
    "sg:city":"Longueuil",
    "sg:classifiers":[
        {
            "category":"Real Estate",
            "subcategory":"Real Estate Operator",
            "type":"Services"
        }
    ],
    "sg:phone":"+1 450 679 1330",
    "sg:postcode":"J4H 2G5",
    "sg:province":"QC",
    "sg:tags":[
        "apartment"
    ],
    "wof:name":"Domaine D'Iberville Ltee",
    "wof:placetype":"venue"
},
  "geometry": {"coordinates":[-73.519577,45.531803],"type":"Point"}
}