{
  "type": "Feature",
  "properties": {
    "addr:full":"Vancouver BC V5X 3H3",
    "addr:postcode":"v5x 3h3",
    "iso:country":"CA",
    "sg:city":"Vancouver",
    "sg:classifiers":[
        {
            "category":"Building & Trades",
            "subcategory":"Construction",
            "type":"Services"
        }
    ],
    "sg:phone":"+1 604 327 5977",
    "sg:postcode":"V5X 3H3",
    "sg:province":"BC",
    "sg:tags":[
        "general",
        "contractor"
    ],
    "wof:name":"Altima Contracting Ltd",
    "wof:placetype":"venue"
},
  "geometry": {"coordinates":[-123.10180699999999,49.224449],"type":"Point"}
}