{
  "type": "Feature",
  "properties": {
    "iso:country":"CA",
    "sg:address":"333 Buchner Rd",
    "sg:city":"Welland",
    "sg:classifiers":[
        {
            "category":"Building & Trades",
            "subcategory":"Construction",
            "type":"Services"
        }
    ],
    "sg:phone":"+1 905 788 9892",
    "sg:postcode":"L3B 5N4",
    "sg:province":"ON",
    "sg:tags":[
        "excavating",
        "contractor"
    ],
    "wof:name":"Ray's Backhoe Svc",
    "wof:placetype":"venue"
},
  "geometry": {"coordinates":[-79.2032089233,42.9839439392],"type":"Point"}
}