{
  "type": "Feature",
  "properties": {
    "addr:full":"7 Aurora Heights Dr Aurora ON L4G 2W3",
    "addr:housenumber":"7",
    "addr:postcode":"l4g 2w3",
    "addr:street":"Aurora Heights Dr",
    "iso:country":"CA",
    "sg:address":"7 Aurora Heights Dr",
    "sg:city":"Aurora",
    "sg:classifiers":[
        {
            "category":"Retail",
            "subcategory":"Animal Services",
            "type":"Services"
        }
    ],
    "sg:phone":"+1 905 727 1008",
    "sg:postcode":"L4G 2W3",
    "sg:province":"ON",
    "sg:tags":[
        "pet",
        "grooming",
        "washing"
    ],
    "wof:name":"Margaret's Mobile Dog Grooming",
    "wof:placetype":"venue"
},
  "geometry": {"coordinates":[-79.472786,44.005013],"type":"Point"}
}