{
  "type": "Feature",
  "properties": {
    "iso:country":"CA",
    "sg:address":"4417 47 Ave",
    "sg:city":"Drayton Valley",
    "sg:classifiers":[
        {
            "category":"Education",
            "subcategory":"School",
            "type":"Public Place"
        }
    ],
    "sg:phone":"+1 780 542 5535",
    "sg:postcode":"T7A 1P2",
    "sg:province":"AB",
    "wof:name":"Evergreen Elementary",
    "wof:placetype":"venue"
},
  "geometry": {"coordinates":[-114.968933105,53.216835022],"type":"Point"}
}