{
  "type": "Feature",
  "properties": {
    "addr:full":"4857 Elliott St # 156 Delta BC V4K 2X7",
    "addr:housenumber":"4857",
    "addr:postcode":"v4k 2x7",
    "addr:street":"Elliott St # 156",
    "iso:country":"CA",
    "sg:address":"4857 Elliott St # 156",
    "sg:city":"Delta",
    "sg:classifiers":[
        {
            "category":"Shopping",
            "type":"Retail Goods"
        }
    ],
    "sg:phone":"+1 604 940 9246",
    "sg:postcode":"V4K 2X7",
    "sg:province":"BC",
    "sg:tags":[
        "picture",
        "frame"
    ],
    "wof:name":"Picture Framers",
    "wof:placetype":"venue"
},
  "geometry": {"coordinates":[-123.08367157000001,49.0912017822],"type":"Point"}
}