{
  "type": "Feature",
  "properties": {
    "addr:full":"647 Rue Radisson Trois-Rivieres QC G9A 2C8",
    "addr:housenumber":"647",
    "addr:postcode":"g9a 2c8",
    "addr:street":"Rue Radisson Trois-Rivieres",
    "iso:country":"CA",
    "sg:address":"647 Rue Radisson",
    "sg:city":"Trois-Rivieres",
    "sg:classifiers":[
        {
            "category":"Food & Beverages",
            "subcategory":"Groceries & Convenience Stores",
            "type":"Retail Goods"
        }
    ],
    "sg:phone":"+1 819 378 4621",
    "sg:postcode":"G9A 2C8",
    "sg:province":"QC",
    "wof:name":"Epicerie Heroux Enr",
    "wof:placetype":"venue"
},
  "geometry": {"coordinates":[-72.54624200000001,46.343773],"type":"Point"}
}