{
  "type": "Feature",
  "properties": {
    "addr:full":"973 Wellington St W Ottawa ON K1Y 2X7",
    "addr:housenumber":"973",
    "addr:postcode":"k1y 2x7",
    "addr:street":"Wellington St W",
    "iso:country":"CA",
    "sg:address":"973 Wellington St W",
    "sg:city":"Ottawa",
    "sg:classifiers":[
        {
            "category":"Retail",
            "subcategory":"Auto Repair",
            "type":"Services"
        }
    ],
    "sg:phone":"+1 613 761 9576",
    "sg:postcode":"K1Y 2X7",
    "sg:province":"ON",
    "sg:tags":[
        "repairing",
        "automobile"
    ],
    "wof:name":"Jensen Import Auto Svc Inc",
    "wof:placetype":"venue"
},
  "geometry": {"coordinates":[-75.722717,45.406071],"type":"Point"}
}