{
  "type": "Feature",
  "properties": {
    "iso:country":"CA",
    "sg:address":"3911 Don Mills Rd",
    "sg:city":"North York",
    "sg:classifiers":[
        {
            "category":"Personal",
            "subcategory":"Beauty Salon",
            "type":"Services"
        }
    ],
    "sg:phone":"+1 416 493 9832",
    "sg:postcode":"M2H 2S7",
    "sg:province":"ON",
    "wof:name":"Profiles Hair Styling",
    "wof:placetype":"venue"
},
  "geometry": {"coordinates":[-79.3574142456,43.8077468872],"type":"Point"}
}