{
  "type": "Feature",
  "properties": {
    "addr:full":"17 1st Ave SW Dauphin MB R7N 1R9",
    "addr:housenumber":"17",
    "addr:postcode":"r7n 1r9",
    "addr:street":"1St Ave Sw",
    "iso:country":"CA",
    "sg:address":"17 1st Ave SW",
    "sg:city":"Dauphin",
    "sg:classifiers":[
        {
            "category":"Wholesale",
            "subcategory":"Machinery & Supplies",
            "type":"Manufacturing & Wholesale Goods"
        }
    ],
    "sg:phone":"+1 204 638 8930",
    "sg:postcode":"R7N 1R9",
    "sg:province":"MB",
    "sg:tags":[
        "equipment",
        "welding"
    ],
    "wof:name":"Praxair Inc",
    "wof:placetype":"venue"
},
  "geometry": {"coordinates":[-100.05146000000001,51.148987],"type":"Point"}
}