{
  "type": "Feature",
  "properties": {
    "iso:country":"CA",
    "sg:address":"29 Duncan Ave S",
    "sg:city":"Kirkland Lake",
    "sg:classifiers":[
        {
            "category":"Government",
            "subcategory":"Office",
            "type":"Public Place"
        }
    ],
    "sg:phone":"+1 705 567 4650",
    "sg:postcode":"P2N 1X5",
    "sg:province":"ON",
    "wof:name":"M P P Constituency Office",
    "wof:placetype":"venue"
},
  "geometry": {"coordinates":[-80.03276824949999,48.1504211426],"type":"Point"}
}