{
  "type": "Feature",
  "properties": {
    "addr:full":"448 Spadina Ave Toronto ON M5T 2G8",
    "addr:housenumber":"448",
    "addr:postcode":"m5t 2g8",
    "addr:street":"Spadina Ave",
    "iso:country":"CA",
    "sg:address":"448 Spadina Ave",
    "sg:city":"Toronto",
    "sg:classifiers":[
        {
            "category":"Wholesale",
            "subcategory":"Non-durable Goods",
            "type":"Manufacturing & Wholesale Goods"
        }
    ],
    "sg:phone":"+1 416 922 5333",
    "sg:postcode":"M5T 2G8",
    "sg:province":"ON",
    "sg:tags":[
        "leaf",
        "gold",
        "artist"
    ],
    "wof:name":"Masters Inc",
    "wof:placetype":"venue"
},
  "geometry": {"coordinates":[-79.4000549316,43.6571350098],"type":"Point"}
}