{
  "type": "Feature",
  "properties": {
    "addr:full":"750 Gordon St Guelph ON N1G 1Y6",
    "addr:housenumber":"750",
    "addr:postcode":"n1g 1y6",
    "addr:street":"Gordon St",
    "iso:country":"CA",
    "sg:address":"750 Gordon St",
    "sg:city":"Guelph",
    "sg:classifiers":[
        {
            "category":"Health Services",
            "subcategory":"Doctor",
            "type":"Services"
        }
    ],
    "sg:phone":"+1 519 836 1717",
    "sg:postcode":"N1G 1Y6",
    "sg:province":"ON",
    "sg:tags":[
        "dentist"
    ],
    "wof:name":"Bader, Susan DDS",
    "wof:placetype":"venue"
},
  "geometry": {"coordinates":[-80.2216339111,43.5258178711],"type":"Point"}
}