{
  "type": "Feature",
  "properties": {
    "addr:full":"430 Franklin Blvd Cambridge ON N1R 8G6",
    "addr:housenumber":"430",
    "addr:postcode":"n1r 8g6",
    "addr:street":"Franklin Blvd",
    "iso:country":"CA",
    "sg:address":"430 Franklin Blvd",
    "sg:city":"Cambridge",
    "sg:classifiers":[
        {
            "category":"Wholesale",
            "subcategory":"Hardware",
            "type":"Manufacturing & Wholesale Goods"
        }
    ],
    "sg:phone":"+1 519 621 6210",
    "sg:postcode":"N1R 8G6",
    "sg:province":"ON",
    "sg:tags":[
        "dust",
        "collecting",
        "system"
    ],
    "wof:name":"N R Murphy Ltd",
    "wof:placetype":"venue"
},
  "geometry": {"coordinates":[-80.292007,43.364788],"type":"Point"}
}