{
  "type": "Feature",
  "properties": {
    "iso:country":"CA",
    "sg:address":"904 Service Rd NW",
    "sg:city":"Milk River",
    "sg:classifiers":[
        {
            "category":"Restaurant",
            "type":"Food & Drink"
        }
    ],
    "sg:phone":"+1 403 647 3883",
    "sg:postcode":"T0K 1M0",
    "sg:province":"AB",
    "wof:name":"D J's Diner & Drive Inn",
    "wof:placetype":"venue"
},
  "geometry": {"coordinates":[-112.091598511,49.1551971436],"type":"Point"}
}