{
  "type": "Feature",
  "properties": {
    "iso:country":"CA",
    "sg:address":"49 Vineyard Crt",
    "sg:city":"Woodbridge",
    "sg:classifiers":[
        {
            "category":"Real Estate",
            "subcategory":"Real Estate Agent",
            "type":"Services"
        }
    ],
    "sg:phone":"+1 905 851 4409",
    "sg:postcode":"L4L 5J8",
    "sg:province":"ON",
    "wof:name":"Jdm Realty Ltd",
    "wof:placetype":"venue"
},
  "geometry": {"coordinates":[-79.57038879389999,43.7905921936],"type":"Point"}
}