{
  "type": "Feature",
  "properties": {
    "addr:full":"1438 Kensington Rd NW Calgary AB T2N 3P9",
    "addr:housenumber":"1438",
    "addr:postcode":"t2n 3p9",
    "addr:street":"Kensington Rd Nw",
    "iso:country":"CA",
    "sg:address":"1438 Kensington Rd NW",
    "sg:city":"Calgary",
    "sg:classifiers":[
        {
            "category":"Autos & Motor Vehicles",
            "subcategory":"Fuel & Gas Station",
            "type":"Retail Goods"
        }
    ],
    "sg:phone":"+1 403 283 1503",
    "sg:postcode":"T2N 3P9",
    "sg:province":"AB",
    "sg:tags":[
        "oil"
    ],
    "wof:name":"Kensington Petro-Canada",
    "wof:placetype":"venue"
},
  "geometry": {"coordinates":[-114.09371899999999,51.052723],"type":"Point"}
}