{
  "type": "Feature",
  "properties": {
    "addr:full":"Toronto ON M6R 2H9",
    "addr:postcode":"m6r 2h9",
    "iso:country":"CA",
    "sg:city":"Toronto",
    "sg:classifiers":[
        {
            "category":"Professional",
            "subcategory":"Lawyer & Legal Services",
            "type":"Services"
        }
    ],
    "sg:phone":"+1 416 533 8826",
    "sg:postcode":"M6R 2H9",
    "sg:province":"ON",
    "sg:tags":[
        "attorney"
    ],
    "wof:name":"Manning, Glenn D",
    "wof:placetype":"venue"
},
  "geometry": {"coordinates":[-79.4468765259,43.6526222229],"type":"Point"}
}