{
  "type": "Feature",
  "properties": {
    "addr:full":"1405 Bewicke Ave North Vancouver BC V7M 3C7",
    "addr:housenumber":"1405",
    "addr:postcode":"v7m 3c7",
    "addr:street":"Bewicke Ave",
    "iso:country":"CA",
    "sg:address":"1405 Bewicke Ave",
    "sg:city":"North Vancouver",
    "sg:classifiers":[
        {
            "category":"Personal",
            "subcategory":"Massage",
            "type":"Services"
        }
    ],
    "sg:phone":"+1 604 985 4969",
    "sg:postcode":"V7M 3C7",
    "sg:province":"BC",
    "wof:name":"Meridien Spa Ltd",
    "wof:placetype":"venue"
},
  "geometry": {"coordinates":[-123.09147643999999,49.3213806152],"type":"Point"}
}