{
  "type": "Feature",
  "properties": {
    "iso:country":"CA",
    "sg:address":"6179 Perth St",
    "sg:city":"Richmond",
    "sg:classifiers":[
        {
            "category":"Banks & Credit Unions",
            "subcategory":"Bank",
            "type":"Services"
        }
    ],
    "sg:phone":"+1 613 838 3200",
    "sg:postcode":"K0A 2Z0",
    "sg:province":"ON",
    "wof:name":"Cibc",
    "wof:placetype":"venue"
},
  "geometry": {"coordinates":[-75.8413391113,45.1929931641],"type":"Point"}
}