{
  "type": "Feature",
  "properties": {
    "iso:country":"CA",
    "sg:address":"2004 Yellowhead Trail NE",
    "sg:city":"Edmonton",
    "sg:classifiers":[
        {
            "category":"Freight",
            "type":"Transportation"
        }
    ],
    "sg:phone":"+1 780 457 0242",
    "sg:postcode":"T6S 1B4",
    "sg:province":"AB",
    "sg:tags":[
        "field",
        "oil",
        "trucking"
    ],
    "wof:name":"Sparky's Trucking & Camp",
    "wof:placetype":"venue"
},
  "geometry": {"coordinates":[-113.316399,53.570827],"type":"Point"}
}