{
  "type": "Feature",
  "properties": {
    "addr:full":"122 Shanty Bay Rd Barrie ON L4M 1E2",
    "addr:housenumber":"122",
    "addr:postcode":"l4m 1e2",
    "addr:street":"Shanty Bay Rd",
    "iso:country":"CA",
    "sg:address":"122 Shanty Bay Rd",
    "sg:city":"Barrie",
    "sg:classifiers":[
        {
            "category":"Retail",
            "subcategory":"Repair Shop",
            "type":"Services"
        }
    ],
    "sg:phone":"+1 705 739 4730",
    "sg:postcode":"L4M 1E2",
    "sg:province":"ON",
    "sg:tags":[
        "lock",
        "locksmith"
    ],
    "wof:name":"Hallocks",
    "wof:placetype":"venue"
},
  "geometry": {"coordinates":[-79.65465500000001,44.394199],"type":"Point"}
}