{
  "type": "Feature",
  "properties": {
    "addr:full":"805 Park Royal N West Vancouver BC V7T 1H9",
    "addr:housenumber":"805",
    "addr:postcode":"v7t 1h9",
    "addr:street":"Park Royal N",
    "iso:country":"CA",
    "sg:address":"805 Park Royal N",
    "sg:city":"West Vancouver",
    "sg:classifiers":[
        {
            "category":"Wholesale",
            "subcategory":"Groceries",
            "type":"Manufacturing & Wholesale Goods"
        }
    ],
    "sg:phone":"+1 604 925 2213",
    "sg:postcode":"V7T 1H9",
    "sg:province":"BC",
    "sg:tags":[
        "cocoa",
        "confectionery",
        "candy",
        "chocolate"
    ],
    "wof:name":"Chocolat Daniel Belge Ltd",
    "wof:placetype":"venue"
},
  "geometry": {"coordinates":[-123.138038635,49.3273544312],"type":"Point"}
}