{
  "type": "Feature",
  "properties": {
    "addr:full":"5650 Aut Transcanadienne Pointe-Claire QC H9R 1B9",
    "addr:postcode":"5650;h9r 1b9",
    "addr:street":"Transcanadienne",
    "iso:country":"CA",
    "sg:address":"5650 Aut Transcanadienne",
    "sg:city":"Pointe-Claire",
    "sg:classifiers":[
        {
            "category":"Wholesale",
            "subcategory":"Home Furnishings",
            "type":"Manufacturing & Wholesale Goods"
        }
    ],
    "sg:phone":"+1 514 426 8556",
    "sg:postcode":"H9R 1B9",
    "sg:province":"QC",
    "sg:tags":[
        "housewares"
    ],
    "wof:name":"Coranco Corp",
    "wof:placetype":"venue"
},
  "geometry": {"coordinates":[-73.838218689,45.4578323364],"type":"Point"}
}