{
  "type": "Feature",
  "properties": {
    "addr:full":"20701 Fraser Hwy Langley BC V3A 4G4",
    "addr:housenumber":"20701",
    "addr:postcode":"v3a 4g4",
    "addr:street":"Fraser Hwy",
    "iso:country":"CA",
    "sg:address":"20701 Fraser Hwy",
    "sg:city":"Langley",
    "sg:classifiers":[
        {
            "category":"Organizations",
            "subcategory":"Community Association",
            "type":"Services"
        }
    ],
    "sg:phone":"+1 604 530 7626",
    "sg:postcode":"V3A 4G4",
    "sg:province":"BC",
    "sg:tags":[
        "fraternal"
    ],
    "wof:name":"Masonic Halls & Offices",
    "wof:placetype":"venue"
},
  "geometry": {"coordinates":[-122.64913900000001,49.103222],"type":"Point"}
}