{
  "type": "Feature",
  "properties": {
    "iso:country":"CA",
    "sg:address":"1062 Goldstream Ave",
    "sg:city":"Victoria",
    "sg:classifiers":[
        {
            "category":"Home & Garden",
            "subcategory":"Garden Supply",
            "type":"Retail Goods"
        }
    ],
    "sg:phone":"+1 250 478 4557",
    "sg:postcode":"V9B 2Y5",
    "sg:province":"BC",
    "sg:tags":[
        "center"
    ],
    "wof:name":"Lynne's Little Elf Garden Ctr",
    "wof:placetype":"venue"
},
  "geometry": {"coordinates":[-123.364517212,48.428314209],"type":"Point"}
}