{
  "type": "Feature",
  "properties": {
    "addr:full":"516 40 Ave NW Calgary AB T2K 0E6",
    "addr:postcode":"t2k 0e6",
    "addr:street":"516 40 Ave Nw",
    "iso:country":"CA",
    "sg:address":"516 40 Ave NW",
    "sg:city":"Calgary",
    "sg:classifiers":[
        {
            "category":"Professional",
            "subcategory":"Accounting & Tax Preparation",
            "type":"Services"
        }
    ],
    "sg:phone":"+1 403 283 8881",
    "sg:postcode":"T2K 0E6",
    "sg:province":"AB",
    "sg:tags":[
        "accountant",
        "real estate"
    ],
    "wof:name":"Crystal Realty & Property Mgmt",
    "wof:placetype":"venue"
},
  "geometry": {"coordinates":[-114.071907044,51.0874900818],"type":"Point"}
}