{
  "type": "Feature",
  "properties": {
    "addr:full":"279 Rue Principale Daveluyville QC G0Z 1C0",
    "addr:housenumber":"279",
    "addr:postcode":"g0z 1c0",
    "addr:street":"Rue Principale",
    "iso:country":"CA",
    "sg:address":"279 Rue Principale",
    "sg:city":"Daveluyville",
    "sg:classifiers":[
        {
            "category":"Retail",
            "subcategory":"Auto Repair",
            "type":"Services"
        }
    ],
    "sg:phone":"+1 819 367 2351",
    "sg:postcode":"G0Z 1C0",
    "sg:province":"QC",
    "sg:tags":[
        "repairing",
        "automobile"
    ],
    "wof:name":"Garage Rene Tourigny Inc",
    "wof:placetype":"venue"
},
  "geometry": {"coordinates":[-72.13855700000001,46.206966],"type":"Point"}
}