{
  "type": "Feature",
  "properties": {
    "addr:full":"Toronto ON M5H 3S6",
    "addr:postcode":"m5h 3s6",
    "iso:country":"CA",
    "sg:city":"Toronto",
    "sg:classifiers":[
        {
            "category":"Organizations",
            "subcategory":"Non-profit Organization",
            "type":"Services"
        }
    ],
    "sg:phone":"+1 416 340 9710",
    "sg:postcode":"M5H 3S6",
    "sg:province":"ON",
    "sg:tags":[
        "fund",
        "counselor",
        "raising"
    ],
    "wof:name":"Ketchum Canada Inc",
    "wof:placetype":"venue"
},
  "geometry": {"coordinates":[-79.386314,43.647449],"type":"Point"}
}