{
  "type": "Feature",
  "properties": {
    "addr:full":"693 Fuller Ave Penetanguishene ON L9M 2E8",
    "addr:housenumber":"693",
    "addr:postcode":"l9m 2e8",
    "addr:street":"Fuller Ave",
    "iso:country":"CA",
    "sg:address":"693 Fuller Ave",
    "sg:city":"Penetanguishene",
    "sg:classifiers":[
        {
            "category":"Building & Trades",
            "subcategory":"Construction",
            "type":"Services"
        }
    ],
    "sg:phone":"+1 705 526 7269",
    "sg:postcode":"L9M 2E8",
    "sg:province":"ON",
    "sg:tags":[
        "excavating",
        "contractor"
    ],
    "wof:name":"Tinney's Septic Svc & Constr",
    "wof:placetype":"venue"
},
  "geometry": {"coordinates":[-79.9080047607,44.7763252258],"type":"Point"}
}