{
  "type": "Feature",
  "properties": {
    "addr:full":"707 Mohawk Rd E Hamilton ON L8T 2P7",
    "addr:housenumber":"707",
    "addr:postcode":"l8t 2p7",
    "addr:street":"Mohawk Rd E",
    "iso:country":"CA",
    "sg:address":"707 Mohawk Rd E",
    "sg:city":"Hamilton",
    "sg:classifiers":[
        {
            "category":"Personal",
            "subcategory":"Beauty Salon",
            "type":"Services"
        }
    ],
    "sg:phone":"+1 905 389 3764",
    "sg:postcode":"L8T 2P7",
    "sg:province":"ON",
    "wof:name":"Skylock Hairstyling",
    "wof:placetype":"venue"
},
  "geometry": {"coordinates":[-79.842026,43.219044],"type":"Point"}
}