{
  "type": "Feature",
  "properties": {
    "iso:country":"CA",
    "sg:city":"Saint-Paul-DE-Montminy",
    "sg:classifiers":[
        {
            "category":"Personal",
            "subcategory":"Beauty Salon",
            "type":"Services"
        }
    ],
    "sg:phone":"+1 418 469 2393",
    "sg:postcode":"G0R 3Y0",
    "sg:province":"QC",
    "wof:name":"Salon DE Coiffure Marina",
    "wof:placetype":"venue"
},
  "geometry": {"coordinates":[-70.3604354858,46.7308654785],"type":"Point"}
}