{
  "type": "Feature",
  "properties": {
    "addr:full":"83 Boul Churchill Greenfield Park QC J4V 3L8",
    "addr:housenumber":"83",
    "addr:postcode":"j4v 3l8",
    "addr:street":"Boul Churchill;Park",
    "iso:country":"CA",
    "sg:address":"83 Boul Churchill",
    "sg:city":"Greenfield Park",
    "sg:classifiers":[
        {
            "category":"Cinema",
            "subcategory":"Movie Rental",
            "type":"Entertainment"
        }
    ],
    "sg:phone":"+1 450 465 9909",
    "sg:postcode":"J4V 3L8",
    "sg:province":"QC",
    "sg:tags":[
        "leasing",
        "video",
        "disc",
        "tape"
    ],
    "wof:name":"Video 2 Pour 1",
    "wof:placetype":"venue"
},
  "geometry": {"coordinates":[-73.4892196655,45.4903144836],"type":"Point"}
}