{
  "type": "Feature",
  "properties": {
    "addr:full":"263 Queenston Rd Hamilton ON L8K 1G9",
    "addr:housenumber":"263",
    "addr:postcode":"l8k 1g9",
    "addr:street":"Queenston Rd",
    "iso:country":"CA",
    "sg:address":"263 Queenston Rd",
    "sg:city":"Hamilton",
    "sg:classifiers":[
        {
            "category":"Wholesale",
            "subcategory":"Wine & Distilled Alcoholic Beverages",
            "type":"Manufacturing & Wholesale Goods"
        }
    ],
    "sg:phone":"+1 905 549 6954",
    "sg:postcode":"L8K 1G9",
    "sg:province":"ON",
    "sg:tags":[
        "equipment",
        "brewer",
        "supply"
    ],
    "wof:name":"Wine & Hop Shoppe",
    "wof:placetype":"venue"
},
  "geometry": {"coordinates":[-79.79261779789999,43.2345352173],"type":"Point"}
}