{
  "type": "Feature",
  "properties": {
    "addr:full":"41 Rue Des Pins Magog QC J1X 2H6",
    "addr:housenumber":"41",
    "addr:postcode":"j1x 2h6",
    "addr:street":"Rue Des Pins",
    "iso:country":"CA",
    "sg:address":"41 Rue Des Pins",
    "sg:city":"Magog",
    "sg:classifiers":[
        {
            "category":"Professional",
            "subcategory":"Accounting & Tax Preparation",
            "type":"Services"
        }
    ],
    "sg:phone":"+1 819 843 2070",
    "sg:postcode":"J1X 2H6",
    "sg:province":"QC",
    "sg:tags":[
        "accountant"
    ],
    "wof:name":"Langlois, Alain CA",
    "wof:placetype":"venue"
},
  "geometry": {"coordinates":[-72.1533203125,45.2667808533],"type":"Point"}
}