{
  "type": "Feature",
  "properties": {
    "addr:full":"Victoria BC V8V 3K8",
    "addr:postcode":"v8v 3k8",
    "iso:country":"CA",
    "sg:city":"Victoria",
    "sg:classifiers":[
        {
            "category":"Professional",
            "subcategory":"Accounting & Tax Preparation",
            "type":"Services"
        }
    ],
    "sg:phone":"+1 250 383 6109",
    "sg:postcode":"V8V 3K8",
    "sg:province":"BC",
    "sg:tags":[
        "consultant",
        "accountant"
    ],
    "wof:name":"Fastax Efile Svc",
    "wof:placetype":"venue"
},
  "geometry": {"coordinates":[-123.352783,48.423386],"type":"Point"}
}