{
  "type": "Feature",
  "properties": {
    "iso:country":"CA",
    "sg:address":"800 Niagara St",
    "sg:city":"Welland",
    "sg:classifiers":[
        {
            "category":"Shopping",
            "subcategory":"Department Store",
            "type":"Retail Goods"
        }
    ],
    "sg:phone":"+1 905 732 6100",
    "sg:postcode":"L3C 5Z4",
    "sg:province":"ON",
    "wof:name":"Sears Canada Inc",
    "wof:placetype":"venue"
},
  "geometry": {"coordinates":[-79.2498016357,43.0148506165],"type":"Point"}
}