{
  "type": "Feature",
  "properties": {
    "iso:country":"CA",
    "sg:address":"760 Latoria Rd",
    "sg:city":"Victoria",
    "sg:classifiers":[
        {
            "category":"Organizations",
            "subcategory":"Religious Organization",
            "type":"Services"
        }
    ],
    "sg:phone":"+1 250 474 0452",
    "sg:postcode":"V9C 3A4",
    "sg:province":"BC",
    "sg:tags":[
        "church"
    ],
    "wof:name":"West Shore Presbyterian Church",
    "wof:placetype":"venue"
},
  "geometry": {"coordinates":[-123.364517,48.428314],"type":"Point"}
}