{
  "type": "Feature",
  "properties": {
    "addr:full":"421 St Mary's Rd Winnipeg MB R2M 3K5",
    "addr:housenumber":"421",
    "addr:postcode":"r2m 3k5",
    "addr:street":"St Mary'S Rd",
    "iso:country":"CA",
    "sg:address":"421 St Mary's Rd",
    "sg:city":"Winnipeg",
    "sg:classifiers":[
        {
            "category":"Autos & Motor Vehicles",
            "subcategory":"Auto Supplies",
            "type":"Retail Goods"
        }
    ],
    "sg:phone":"+1 204 987 9557",
    "sg:postcode":"R2M 3K5",
    "sg:province":"MB",
    "sg:tags":[
        "tire"
    ],
    "wof:name":"Sturgeon Tire Ltd",
    "wof:placetype":"venue"
},
  "geometry": {"coordinates":[-97.148819,49.889183],"type":"Point"}
}