{
  "type": "Feature",
  "properties": {
    "iso:country":"CA",
    "sg:address":"5369 Headland Dr",
    "sg:city":"West Vancouver",
    "sg:classifiers":[
        {
            "category":"Restaurant",
            "type":"Food & Drink"
        }
    ],
    "sg:phone":"+1 604 922 9333",
    "sg:postcode":"V7W 3C7",
    "sg:province":"BC",
    "wof:name":"Pastameli of New York",
    "wof:placetype":"venue"
},
  "geometry": {"coordinates":[-123.252990723,49.3505973816],"type":"Point"}
}