{
  "type": "Feature",
  "properties": {
    "addr:full":"1637 Woodroffe Ave Nepean ON K2G 1W2",
    "addr:housenumber":"1637",
    "addr:postcode":"k2g 1w2",
    "addr:street":"Woodroffe Ave",
    "iso:country":"CA",
    "sg:address":"1637 Woodroffe Ave",
    "sg:city":"Nepean",
    "sg:classifiers":[
        {
            "category":"Shopping",
            "subcategory":"Pharmacy",
            "type":"Retail Goods"
        }
    ],
    "sg:phone":"+1 613 224 8342",
    "sg:postcode":"K2G 1W2",
    "sg:province":"ON",
    "wof:name":"Woodroffe Pharmacy",
    "wof:placetype":"venue"
},
  "geometry": {"coordinates":[-75.749611,45.330318],"type":"Point"}
}