{
  "type": "Feature",
  "properties": {
    "iso:country":"CA",
    "sg:address":"876 Rue Trans-Canada",
    "sg:city":"Longueuil",
    "sg:classifiers":[
        {
            "category":"Building & Trades",
            "subcategory":"Construction",
            "type":"Services"
        }
    ],
    "sg:phone":"+1 450 442 4442",
    "sg:postcode":"J4G 2M1",
    "sg:province":"QC",
    "sg:tags":[
        "general",
        "contractor"
    ],
    "wof:name":"Construction Tigre",
    "wof:placetype":"venue"
},
  "geometry": {"coordinates":[-73.4517669678,45.5700187683],"type":"Point"}
}