{
  "type": "Feature",
  "properties": {
    "iso:country":"CA",
    "sg:city":"Formosa",
    "sg:classifiers":[
        {
            "category":"Building & Trades",
            "subcategory":"Electrical",
            "type":"Services"
        }
    ],
    "sg:phone":"+1 519 881 2488",
    "sg:postcode":"N0G 1W0",
    "sg:province":"ON",
    "sg:tags":[
        "electric",
        "contractor"
    ],
    "wof:name":"Wally's Electric Ltd",
    "wof:placetype":"venue"
},
  "geometry": {"coordinates":[-81.2140960693,44.0670166016],"type":"Point"}
}