{
  "type": "Feature",
  "properties": {
    "addr:full":"112 Huron St Stratford ON N5A 5S6",
    "addr:housenumber":"112",
    "addr:postcode":"n5a 5s6",
    "addr:street":"Huron St",
    "iso:country":"CA",
    "sg:address":"112 Huron St",
    "sg:city":"Stratford",
    "sg:classifiers":[
        {
            "category":"Travel",
            "subcategory":"Hotels & Motels",
            "type":"Entertainment"
        }
    ],
    "sg:phone":"+1 519 271 2055",
    "sg:postcode":"N5A 5S6",
    "sg:province":"ON",
    "sg:tags":[
        "breakfast",
        "accommodation",
        "bed"
    ],
    "wof:name":"Alban Abbeys House",
    "wof:placetype":"venue"
},
  "geometry": {"coordinates":[-80.9874801636,43.3738174438],"type":"Point"}
}