{
  "type": "Feature",
  "properties": {
    "iso:country":"CA",
    "sg:address":"73 Bidwell St",
    "sg:city":"Tillsonburg",
    "sg:classifiers":[
        {
            "category":"Personal",
            "subcategory":"Beauty Salon",
            "type":"Services"
        }
    ],
    "sg:phone":"+1 519 688 9775",
    "sg:postcode":"N4G 3T8",
    "sg:province":"ON",
    "wof:name":"Giggles N Curls",
    "wof:placetype":"venue"
},
  "geometry": {"coordinates":[-80.7293014526,42.8598594666],"type":"Point"}
}