{
  "type": "Feature",
  "properties": {
    "addr:full":"1057 Parkinson Rd Woodstock ON N4S 7W3",
    "addr:housenumber":"1057",
    "addr:postcode":"n4s 7w3",
    "addr:street":"Parkinson Rd",
    "iso:country":"CA",
    "sg:address":"1057 Parkinson Rd",
    "sg:city":"Woodstock",
    "sg:classifiers":[
        {
            "category":"Wholesale",
            "subcategory":"Electrical",
            "type":"Manufacturing & Wholesale Goods"
        }
    ],
    "sg:phone":"+1 519 539 4789",
    "sg:postcode":"N4S 7W3",
    "sg:province":"ON",
    "sg:tags":[
        "equipment",
        "electric",
        "supply"
    ],
    "wof:name":"Tesco Electric Supply Ltd",
    "wof:placetype":"venue"
},
  "geometry": {"coordinates":[-80.718658,43.123329],"type":"Point"}
}