{
  "type": "Feature",
  "properties": {
    "addr:full":"91 Cumberland St S Thunder Bay ON P7B 6A7",
    "addr:housenumber":"91",
    "addr:postcode":"p7b 6a7",
    "addr:street":"Cumberland St S",
    "iso:country":"CA",
    "sg:address":"91 Cumberland St S",
    "sg:city":"Thunder Bay",
    "sg:classifiers":[
        {
            "category":"Health Services",
            "subcategory":"Doctor",
            "type":"Services"
        }
    ],
    "sg:phone":"+1 807 345 2211",
    "sg:postcode":"P7B 6A7",
    "sg:province":"ON",
    "sg:tags":[
        "dentist"
    ],
    "wof:name":"Jacobson, Ken A DDS",
    "wof:placetype":"venue"
},
  "geometry": {"coordinates":[-89.22248840330001,48.4315795898],"type":"Point"}
}