{
  "type": "Feature",
  "properties": {
    "addr:full":"Kelowna BC V1W 1X4",
    "addr:postcode":"v1w 1x4",
    "iso:country":"CA",
    "sg:city":"Kelowna",
    "sg:classifiers":[
        {
            "category":"Restaurant",
            "type":"Food & Drink"
        }
    ],
    "sg:phone":"+1 250 764 0674",
    "sg:postcode":"V1W 1X4",
    "sg:province":"BC",
    "wof:name":"Laughing Moon Gallery & Rstrnt",
    "wof:placetype":"venue"
},
  "geometry": {"coordinates":[-119.494034,49.818329],"type":"Point"}
}