{
  "type": "Feature",
  "properties": {
    "addr:full":"1520 3 Ave S Lethbridge AB T1J 0K8",
    "addr:housenumber":"1520",
    "addr:postcode":"t1j 0k8",
    "addr:street":"3 Ave S",
    "iso:country":"CA",
    "sg:address":"1520 3 Ave S",
    "sg:city":"Lethbridge",
    "sg:classifiers":[
        {
            "category":"Restaurant",
            "type":"Food & Drink"
        }
    ],
    "sg:phone":"+1 403 328 0676",
    "sg:postcode":"T1J 0K8",
    "sg:province":"AB",
    "wof:name":"Georgio's Contemporary Dining",
    "wof:placetype":"venue"
},
  "geometry": {"coordinates":[-112.82048,49.696293],"type":"Point"}
}