{
  "type": "Feature",
  "properties": {
    "iso:country":"CA",
    "sg:address":"2886 Stanley Ave",
    "sg:city":"Niagara Falls",
    "sg:classifiers":[
        {
            "category":"Freight",
            "type":"Transportation"
        }
    ],
    "sg:phone":"+1 905 374 7988",
    "sg:postcode":"L2E 6S4",
    "sg:province":"ON",
    "sg:tags":[
        "commercial",
        "storage"
    ],
    "wof:name":"Classic Self Storage",
    "wof:placetype":"venue"
},
  "geometry": {"coordinates":[-79.087020874,43.1330986023],"type":"Point"}
}