{
  "type": "Feature",
  "properties": {
    "addr:full":"192 Howey St Red Lake ON P0V 2M0",
    "addr:housenumber":"192",
    "addr:postcode":"p0v 2m0",
    "addr:street":"Howey St",
    "iso:country":"CA",
    "sg:address":"192 Howey St",
    "sg:city":"Red Lake",
    "sg:classifiers":[
        {
            "category":"Manufacturing",
            "subcategory":"Metals",
            "type":"Manufacturing & Wholesale Goods"
        }
    ],
    "sg:phone":"+1 807 727 2172",
    "sg:postcode":"P0V 2M0",
    "sg:province":"ON",
    "sg:tags":[
        "energy",
        "solar",
        "furniture"
    ],
    "wof:name":"Try Smith & Details",
    "wof:placetype":"venue"
},
  "geometry": {"coordinates":[-93.8256607056,51.0191993713],"type":"Point"}
}