{
  "type": "Feature",
  "properties": {
    "addr:full":"129 Rue DE Freville Gatineau QC J8P 8B7",
    "addr:housenumber":"129",
    "addr:postcode":"j8p 8b7",
    "addr:street":"Rue De Freville",
    "iso:country":"CA",
    "sg:address":"129 Rue DE Freville",
    "sg:city":"Gatineau",
    "sg:classifiers":[
        {
            "category":"Professional",
            "subcategory":"Business Services",
            "type":"Services"
        }
    ],
    "sg:phone":"+1 819 669 6766",
    "sg:postcode":"J8P 8B7",
    "sg:province":"QC",
    "sg:tags":[
        "interior",
        "consultant",
        "design",
        "decorator"
    ],
    "wof:name":"Decoration Interieure Denise",
    "wof:placetype":"venue"
},
  "geometry": {"coordinates":[-75.57205999999999,45.498783],"type":"Point"}
}