{
  "type": "Feature",
  "properties": {
    "addr:full":"7015 Boul Gouin E Montreal QC H1E 5N2",
    "addr:housenumber":"7015",
    "addr:postcode":"h1e 5n2",
    "addr:street":"Boul Gouin E",
    "iso:country":"CA",
    "sg:address":"7015 Boul Gouin E",
    "sg:city":"Montreal",
    "sg:classifiers":[
        {
            "category":"Health Services",
            "subcategory":"Nursing And Care Facility",
            "type":"Services"
        }
    ],
    "sg:phone":"+1 514 955 5229",
    "sg:postcode":"H1E 5N2",
    "sg:province":"QC",
    "sg:tags":[
        "home",
        "rest"
    ],
    "wof:name":"Centre Garant",
    "wof:placetype":"venue"
},
  "geometry": {"coordinates":[-73.618850708,45.629737854],"type":"Point"}
}