{
  "type": "Feature",
  "properties": {
    "addr:full":"7A Oceanview School Rd Eastern Passage NS B3G 1J3",
    "addr:housenumber":"7a",
    "addr:postcode":"b3g 1j3",
    "addr:street":"Oceanview School Rd",
    "iso:country":"CA",
    "sg:address":"7A Oceanview School Rd",
    "sg:city":"Eastern Passage",
    "sg:classifiers":[
        {
            "category":"Wholesale",
            "subcategory":"Machinery & Supplies",
            "type":"Manufacturing & Wholesale Goods"
        }
    ],
    "sg:phone":"+1 902 461 1045",
    "sg:postcode":"B3G 1J3",
    "sg:province":"NS",
    "sg:tags":[
        "hoist"
    ],
    "wof:name":"Mjs Holdings Ltd",
    "wof:placetype":"venue"
},
  "geometry": {"coordinates":[-63.4729881287,44.6102104187],"type":"Point"}
}