{
  "type": "Feature",
  "properties": {
    "addr:full":"860 Des Acadiens Ch Yamachiche QC G0X 3L0",
    "addr:housenumber":"860",
    "addr:postcode":"g0x 3l0",
    "addr:street":"Des Acadiens Ch",
    "iso:country":"CA",
    "sg:address":"860 Des Acadiens Ch",
    "sg:city":"Yamachiche",
    "sg:classifiers":[
        {
            "category":"Wholesale",
            "subcategory":"Meat",
            "type":"Manufacturing & Wholesale Goods"
        }
    ],
    "sg:phone":"+1 819 296 3791",
    "sg:postcode":"G0X 3L0",
    "sg:province":"QC",
    "sg:tags":[
        "packer"
    ],
    "wof:name":"Atrahan Transformation Inc",
    "wof:placetype":"venue"
},
  "geometry": {"coordinates":[-72.860435,46.321877],"type":"Point"}
}