{
  "type": "Feature",
  "properties": {
    "addr:full":"4595 8th Ave W Vancouver BC V6R 2A4",
    "addr:housenumber":"4595",
    "addr:postcode":"v6r 2a4",
    "addr:street":"8Th Ave W",
    "iso:country":"CA",
    "sg:address":"4595 8th Ave W",
    "sg:city":"Vancouver",
    "sg:classifiers":[
        {
            "category":"Social Services",
            "subcategory":"Child Care",
            "type":"Services"
        }
    ],
    "sg:phone":"+1 604 228 5885",
    "sg:postcode":"V6R 2A4",
    "sg:province":"BC",
    "wof:name":"Abc University Kindercare",
    "wof:placetype":"venue"
},
  "geometry": {"coordinates":[-123.211601257,49.2657432556],"type":"Point"}
}