{
  "type": "Feature",
  "properties": {
    "addr:full":"Pointe-Claire QC H9R 5K3",
    "addr:postcode":"h9r 5k3",
    "iso:country":"CA",
    "sg:city":"Pointe-Claire",
    "sg:classifiers":[
        {
            "category":"Health Services",
            "subcategory":"Doctor",
            "type":"Services"
        }
    ],
    "sg:phone":"+1 514 695 2292",
    "sg:postcode":"H9R 5K3",
    "sg:province":"QC",
    "sg:tags":[
        "dentist"
    ],
    "wof:name":"Lerner, Earl DDS",
    "wof:placetype":"venue"
},
  "geometry": {"coordinates":[-73.8305053711,45.4692420959],"type":"Point"}
}