{
  "type": "Feature",
  "properties": {
    "addr:full":"466 Wentworth St N Hamilton ON L8L 5W8",
    "addr:housenumber":"466",
    "addr:postcode":"l8l 5w8",
    "addr:street":"Wentworth St N",
    "iso:country":"CA",
    "sg:address":"466 Wentworth St N",
    "sg:city":"Hamilton",
    "sg:classifiers":[
        {
            "category":"Retail",
            "subcategory":"Auto Repair",
            "type":"Services"
        }
    ],
    "sg:phone":"+1 905 527 1504",
    "sg:postcode":"L8L 5W8",
    "sg:province":"ON",
    "sg:tags":[
        "repairing",
        "automobile",
        "truck"
    ],
    "wof:name":"Wentworth Truck Repair & Align",
    "wof:placetype":"venue"
},
  "geometry": {"coordinates":[-79.84304,43.265247],"type":"Point"}
}