{
  "type": "Feature",
  "properties": {
    "iso:country":"CA",
    "sg:address":"373 Strathmillan Rd",
    "sg:city":"Winnipeg",
    "sg:classifiers":[
        {
            "category":"Retail",
            "subcategory":"Animal Services",
            "type":"Services"
        }
    ],
    "sg:phone":"+1 204 889 6762",
    "sg:postcode":"R3J 2V8",
    "sg:province":"MB",
    "sg:tags":[
        "pet",
        "grooming",
        "washing"
    ],
    "wof:name":"Clippers Dog Grooming",
    "wof:placetype":"venue"
},
  "geometry": {"coordinates":[-97.250488,49.882763],"type":"Point"}
}