{
  "type": "Feature",
  "properties": {
    "addr:full":"Coquitlam BC V3K 7A8",
    "addr:postcode":"v3k 7a8",
    "iso:country":"CA",
    "sg:city":"Coquitlam",
    "sg:classifiers":[
        {
            "category":"Manufacturing",
            "subcategory":"Food",
            "type":"Manufacturing & Wholesale Goods"
        }
    ],
    "sg:phone":"+1 604 540 1411",
    "sg:postcode":"V3K 7A8",
    "sg:province":"BC",
    "sg:tags":[
        "product",
        "broker",
        "manufacturer"
    ],
    "wof:name":"Northleaf Foods Ltd",
    "wof:placetype":"venue"
},
  "geometry": {"coordinates":[-122.839683533,49.2274475098],"type":"Point"}
}