{
  "type": "Feature",
  "properties": {
    "addr:full":"494 Queenston Rd # 210 Hamilton ON L8K 1J5",
    "addr:housenumber":"494;210",
    "addr:postcode":"l8k 1j5",
    "addr:street":"Queenston Rd #",
    "iso:country":"CA",
    "sg:address":"494 Queenston Rd # 210",
    "sg:city":"Hamilton",
    "sg:classifiers":[
        {
            "category":"Building & Trades",
            "subcategory":"Cleaning & Sanitation",
            "type":"Services"
        }
    ],
    "sg:phone":"+1 905 573 6361",
    "sg:postcode":"L8K 1J5",
    "sg:province":"ON",
    "sg:tags":[
        "property",
        "maintenance"
    ],
    "wof:name":"Homestead Land Holdings Ltd",
    "wof:placetype":"venue"
},
  "geometry": {"coordinates":[-79.780914,43.231544],"type":"Point"}
}