{
  "type": "Feature",
  "properties": {
    "addr:full":"36312 Talbot Line Shedden ON N0L 2E0",
    "addr:housenumber":"36312",
    "addr:postcode":"n0l 2e0",
    "addr:street":"Talbot Line",
    "iso:country":"CA",
    "sg:address":"36312 Talbot Line",
    "sg:city":"Shedden",
    "sg:classifiers":[
        {
            "category":"Wholesale",
            "subcategory":"Machinery & Supplies",
            "type":"Manufacturing & Wholesale Goods"
        }
    ],
    "sg:phone":"+1 519 764 2040",
    "sg:postcode":"N0L 2E0",
    "sg:province":"ON",
    "sg:tags":[
        "farm",
        "equipment",
        "tractor"
    ],
    "wof:name":"Shedden Farm Equipment Ltd",
    "wof:placetype":"venue"
},
  "geometry": {"coordinates":[-81.337349,42.747948],"type":"Point"}
}