{
  "type": "Feature",
  "properties": {
    "iso:country":"CA",
    "sg:address":"56 Place D'Auvergne",
    "sg:city":"Candiac",
    "sg:classifiers":[
        {
            "category":"Wholesale",
            "subcategory":"Sporting Goods",
            "type":"Manufacturing & Wholesale Goods"
        }
    ],
    "sg:phone":"+1 450 619 1400",
    "sg:postcode":"J5R 5R1",
    "sg:province":"QC",
    "wof:name":"Gaetan Hudon Agences Ltee",
    "wof:placetype":"venue"
},
  "geometry": {"coordinates":[-73.504974,45.386745],"type":"Point"}
}