{
  "type": "Feature",
  "properties": {
    "addr:full":"299 Main St N Callander ON P0H 1H0",
    "addr:housenumber":"299",
    "addr:postcode":"p0h 1h0",
    "addr:street":"Main St N",
    "iso:country":"CA",
    "sg:address":"299 Main St N",
    "sg:city":"Callander",
    "sg:classifiers":[
        {
            "category":"Health Services",
            "subcategory":"Chiropractor",
            "type":"Services"
        }
    ],
    "sg:phone":"+1 705 752 4572",
    "sg:postcode":"P0H 1H0",
    "sg:province":"ON",
    "wof:name":"Callander Chiropractic Ctr",
    "wof:placetype":"venue"
},
  "geometry": {"coordinates":[-79.366997,46.225517],"type":"Point"}
}