{
  "type": "Feature",
  "properties": {
    "addr:full":"PO Box 100 Hudson ON P0V 1X0",
    "addr:housenumber":"po",
    "addr:postcode":"p0v 1x0",
    "addr:street":"Box 100",
    "iso:country":"CA",
    "sg:address":"PO Box 100",
    "sg:city":"Hudson",
    "sg:classifiers":[
        {
            "category":"Organizations",
            "subcategory":"Professional Association",
            "type":"Services"
        }
    ],
    "sg:phone":"+1 807 582 3459",
    "sg:postcode":"P0V 1X0",
    "sg:province":"ON",
    "wof:name":"Lac Seul Health Authority",
    "wof:placetype":"venue"
},
  "geometry": {"coordinates":[-92.169304,50.090839],"type":"Point"}
}