{
  "type": "Feature",
  "properties": {
    "addr:full":"433 Rue Principale St-Sauveur-Des-Monts QC J0R 1R4",
    "addr:housenumber":"433",
    "addr:postcode":"j0r 1r4",
    "addr:street":"Rue Principale",
    "iso:country":"CA",
    "sg:address":"433 Rue Principale",
    "sg:city":"St-Sauveur-Des-Monts",
    "sg:classifiers":[
        {
            "category":"Professional",
            "subcategory":"Advertising",
            "type":"Services"
        }
    ],
    "sg:phone":"+1 450 227 5353",
    "sg:postcode":"J0R 1R4",
    "sg:province":"QC",
    "sg:tags":[
        "mail",
        "accountant"
    ],
    "wof:name":"Gascon & Papillon Assoc",
    "wof:placetype":"venue"
},
  "geometry": {"coordinates":[-74.166298,45.889675],"type":"Point"}
}