{
  "type": "Feature",
  "properties": {
    "addr:full":"Notre-Dame-Du-Laus QC J0X 2M0",
    "addr:postcode":"j0x 2m0",
    "iso:country":"CA",
    "sg:city":"Notre-Dame-Du-Laus",
    "sg:classifiers":[
        {
            "category":"Shopping",
            "subcategory":"Clothing, Apparel, & Fashions",
            "type":"Retail Goods"
        }
    ],
    "sg:phone":"+1 819 767 2754",
    "sg:postcode":"J0X 2M0",
    "sg:province":"QC",
    "wof:name":"Lingerie Mado",
    "wof:placetype":"venue"
},
  "geometry": {"coordinates":[-75.6239318848,46.0887489319],"type":"Point"}
}