{
  "type": "Feature",
  "properties": {
    "iso:country":"CA",
    "sg:address":"2060 Brant St",
    "sg:city":"Burlington",
    "sg:classifiers":[
        {
            "category":"Wholesale",
            "subcategory":"Chemicals & Plastics",
            "type":"Manufacturing & Wholesale Goods"
        }
    ],
    "sg:phone":"+1 905 335 0755",
    "sg:postcode":"L7P 3A6",
    "sg:province":"ON",
    "wof:name":"David E Lowe CO",
    "wof:placetype":"venue"
},
  "geometry": {"coordinates":[-79.8379898071,43.3529014587],"type":"Point"}
}