{
  "type": "Feature",
  "properties": {
    "addr:full":"1200 Saskatchewan Ave W Portage LA Prairie MB R1N 0N2",
    "addr:housenumber":"1200",
    "addr:postcode":"r1n 0n2",
    "addr:street":"Saskatchewan Ave W",
    "iso:country":"CA",
    "sg:address":"1200 Saskatchewan Ave W",
    "sg:city":"Portage LA Prairie",
    "sg:classifiers":[
        {
            "category":"Health Services",
            "subcategory":"Chiropractor",
            "type":"Services"
        }
    ],
    "sg:phone":"+1 204 857 9452",
    "sg:postcode":"R1N 0N2",
    "sg:province":"MB",
    "wof:name":"Narvey, E Bruce DC",
    "wof:placetype":"venue"
},
  "geometry": {"coordinates":[-98.30611399999999,49.973],"type":"Point"}
}