{
  "type": "Feature",
  "properties": {
    "addr:full":"11935 65 St NW Edmonton AB T5W 4L5",
    "addr:housenumber":"11935",
    "addr:postcode":"t5w 4l5",
    "addr:street":"65 St Nw",
    "iso:country":"CA",
    "sg:address":"11935 65 St NW",
    "sg:city":"Edmonton",
    "sg:classifiers":[
        {
            "category":"Social Services",
            "subcategory":"Adult Care",
            "type":"Services"
        }
    ],
    "sg:phone":"+1 780 471 2443",
    "sg:postcode":"T5W 4L5",
    "sg:province":"AB",
    "sg:tags":[
        "senior",
        "housing",
        "citizen"
    ],
    "wof:name":"Holy Eucharist Sr Citizens Hm",
    "wof:placetype":"venue"
},
  "geometry": {"coordinates":[-113.441184998,53.5725479126],"type":"Point"}
}