{
  "type": "Feature",
  "properties": {
    "iso:country":"CA",
    "sg:city":"Edmonton",
    "sg:classifiers":[
        {
            "category":"Organizations",
            "subcategory":"Professional Association",
            "type":"Services"
        }
    ],
    "sg:phone":"+1 780 988 2713",
    "sg:postcode":"T6E 2B3",
    "sg:province":"AB",
    "wof:name":"Ecology Systems Information",
    "wof:placetype":"venue"
},
  "geometry": {"coordinates":[-113.510323,53.518375],"type":"Point"}
}