{
  "type": "Feature",
  "properties": {
    "addr:full":"142 Bay St Cobourg ON K9A 1P4",
    "addr:housenumber":"142",
    "addr:postcode":"k9a 1p4",
    "addr:street":"Bay St",
    "iso:country":"CA",
    "sg:address":"142 Bay St",
    "sg:city":"Cobourg",
    "sg:classifiers":[
        {
            "category":"Real Estate",
            "subcategory":"Real Estate Agent",
            "type":"Services"
        }
    ],
    "sg:phone":"+1 905 372 7900",
    "sg:postcode":"K9A 1P4",
    "sg:province":"ON",
    "wof:name":"Kirkup Realty Corp",
    "wof:placetype":"venue"
},
  "geometry": {"coordinates":[-78.159149,43.95808],"type":"Point"}
}