{
  "type": "Feature",
  "properties": {
    "iso:country":"CA",
    "sg:address":"256 Rue Duvernay",
    "sg:city":"Beloeil",
    "sg:classifiers":[
        {
            "category":"Shopping",
            "subcategory":"Catalog Store",
            "type":"Retail Goods"
        }
    ],
    "sg:phone":"+1 450 464 4000",
    "sg:postcode":"J3G 2M2",
    "sg:province":"QC",
    "sg:tags":[
        "mail",
        "order",
        "internet"
    ],
    "wof:name":"Sears Canada Inc",
    "wof:placetype":"venue"
},
  "geometry": {"coordinates":[-73.207375,45.563885],"type":"Point"}
}