{
  "type": "Feature",
  "properties": {
    "addr:full":"Cranbrook BC V1C 7G9",
    "addr:postcode":"v1c 7g9",
    "iso:country":"CA",
    "sg:city":"Cranbrook",
    "sg:classifiers":[
        {
            "category":"Shopping",
            "type":"Retail Goods"
        }
    ],
    "sg:phone":"+1 250 426 5995",
    "sg:postcode":"V1C 7G9",
    "sg:province":"BC",
    "sg:tags":[
        "cards",
        "sport",
        "baseball",
        "memorabilia"
    ],
    "wof:name":"Kootenay Sport Cards & Cllctbl",
    "wof:placetype":"venue"
},
  "geometry": {"coordinates":[-115.756531,49.513733],"type":"Point"}
}