{
  "type": "Feature",
  "properties": {
    "addr:full":"3030 Lawrence Ave E # 101 Scarborough ON M1P 2T7",
    "addr:housenumber":"3030",
    "addr:postcode":"m1p 2t7",
    "addr:street":"Lawrence Ave E # 101",
    "iso:country":"CA",
    "sg:address":"3030 Lawrence Ave E # 101",
    "sg:city":"Scarborough",
    "sg:classifiers":[
        {
            "category":"Shopping",
            "type":"Retail Goods"
        }
    ],
    "sg:phone":"+1 416 289 2021",
    "sg:postcode":"M1P 2T7",
    "sg:province":"ON",
    "sg:tags":[
        "hearing",
        "equipment",
        "supply",
        "impaired"
    ],
    "wof:name":"Hearing Clinic",
    "wof:placetype":"venue"
},
  "geometry": {"coordinates":[-79.247756958,43.7552146912],"type":"Point"}
}