{
  "type": "Feature",
  "properties": {
    "iso:country":"CA",
    "sg:address":"20 Jenkinson Grove",
    "sg:city":"King City",
    "sg:classifiers":[
        {
            "category":"Shopping",
            "type":"Retail Goods"
        }
    ],
    "sg:phone":"+1 905 833 8333",
    "sg:postcode":"L7B 1B5",
    "sg:province":"ON",
    "sg:tags":[
        "church",
        "religious",
        "supply"
    ],
    "wof:name":"Ramada Imports Ltd",
    "wof:placetype":"venue"
},
  "geometry": {"coordinates":[-79.528175354,43.9387588501],"type":"Point"}
}