{
  "type": "Feature",
  "properties": {
    "iso:country":"CA",
    "sg:address":"380 Ambassador Dr",
    "sg:city":"Mississauga",
    "sg:classifiers":[
        {
            "category":"Wholesale",
            "subcategory":"Machinery & Supplies",
            "type":"Manufacturing & Wholesale Goods"
        }
    ],
    "sg:phone":"+1 905 362 0509",
    "sg:postcode":"L5T 2J3",
    "sg:province":"ON",
    "sg:tags":[
        "pipe",
        "fitting"
    ],
    "wof:name":"H Paulin & CO",
    "wof:placetype":"venue"
},
  "geometry": {"coordinates":[-79.688782,43.647057],"type":"Point"}
}