{
  "type": "Feature",
  "properties": {
    "iso:country":"CA",
    "sg:address":"90 Ch Bois Franc",
    "sg:city":"Davidson",
    "sg:classifiers":[
        {
            "category":"Manufacturing",
            "subcategory":"Lumber",
            "type":"Manufacturing & Wholesale Goods"
        }
    ],
    "sg:phone":"+1 819 683 1313",
    "sg:postcode":"J0X 1R0",
    "sg:province":"QC",
    "sg:tags":[
        "sawmill"
    ],
    "wof:name":"Scierie Lefebvre & Pharand Inc",
    "wof:placetype":"venue"
},
  "geometry": {"coordinates":[-76.8017578125,45.8977661133],"type":"Point"}
}