{
  "type": "Feature",
  "properties": {
    "addr:full":"1422 Notre Dame Ave Winnipeg MB R3E 3G5",
    "addr:housenumber":"1422",
    "addr:postcode":"r3e 3g5",
    "addr:street":"Notre Dame Ave",
    "iso:country":"CA",
    "sg:address":"1422 Notre Dame Ave",
    "sg:city":"Winnipeg",
    "sg:classifiers":[
        {
            "category":"Building & Trades",
            "subcategory":"Plumbing",
            "type":"Services"
        }
    ],
    "sg:phone":"+1 204 774 5141",
    "sg:postcode":"R3E 3G5",
    "sg:province":"MB",
    "sg:tags":[
        "conditioning",
        "air",
        "system",
        "contractor"
    ],
    "wof:name":"Smart Manufacturing",
    "wof:placetype":"venue"
},
  "geometry": {"coordinates":[-97.18765999999999,49.910278],"type":"Point"}
}