{
  "type": "Feature",
  "properties": {
    "addr:full":"665 Mcdonald St Regina SK S4N 4X1",
    "addr:housenumber":"665",
    "addr:postcode":"s4n 4x1",
    "addr:street":"Mcdonald St",
    "iso:country":"CA",
    "sg:address":"665 Mcdonald St",
    "sg:city":"Regina",
    "sg:classifiers":[
        {
            "category":"Wholesale",
            "subcategory":"Machinery & Supplies",
            "type":"Manufacturing & Wholesale Goods"
        }
    ],
    "sg:phone":"+1 306 525 6176",
    "sg:postcode":"S4N 4X1",
    "sg:province":"SK",
    "sg:tags":[
        "equipment",
        "industrial",
        "welding"
    ],
    "wof:name":"Boc Gases",
    "wof:placetype":"venue"
},
  "geometry": {"coordinates":[-104.583366394,50.4685287476],"type":"Point"}
}