{
  "type": "Feature",
  "properties": {
    "addr:full":"1810 Broadway Ave Saskatoon SK S7H 2B7",
    "addr:housenumber":"1810",
    "addr:postcode":"s7h 2b7",
    "addr:street":"Broadway Ave",
    "iso:country":"CA",
    "sg:address":"1810 Broadway Ave",
    "sg:city":"Saskatoon",
    "sg:classifiers":[
        {
            "category":"Retail",
            "subcategory":"Laundry & Dry Cleaning",
            "type":"Services"
        }
    ],
    "sg:phone":"+1 306 653 2636",
    "sg:postcode":"S7H 2B7",
    "sg:province":"SK",
    "sg:tags":[
        "cleaners"
    ],
    "wof:name":"Tip Top Cleaners",
    "wof:placetype":"venue"
},
  "geometry": {"coordinates":[-106.65689086899999,52.1081123352],"type":"Point"}
}