{
  "type": "Feature",
  "properties": {
    "addr:full":"8011 Dickenson Rd Mount Hope ON L0R 1W0",
    "addr:housenumber":"8011",
    "addr:postcode":"l0r 1w0",
    "addr:street":"Dickenson Rd",
    "iso:country":"CA",
    "sg:address":"8011 Dickenson Rd",
    "sg:city":"Mount Hope",
    "sg:classifiers":[
        {
            "category":"Building & Trades",
            "subcategory":"Construction",
            "type":"Services"
        }
    ],
    "sg:phone":"+1 905 679 6565",
    "sg:postcode":"L0R 1W0",
    "sg:province":"ON",
    "sg:tags":[
        "masonry",
        "contractor"
    ],
    "wof:name":"Giacomelli Masonry Contracting",
    "wof:placetype":"venue"
},
  "geometry": {"coordinates":[-79.8887557983,43.1756706238],"type":"Point"}
}