{
  "type": "Feature",
  "properties": {
    "iso:country":"CA",
    "sg:address":"1264 Rue DE LA Durance",
    "sg:city":"Charlesbourg",
    "sg:classifiers":[
        {
            "category":"Restaurant",
            "type":"Food & Drink"
        }
    ],
    "sg:phone":"+1 418 849 4445",
    "sg:postcode":"G2N 1X2",
    "sg:province":"QC",
    "wof:name":"Restaurant LA Caverne",
    "wof:placetype":"venue"
},
  "geometry": {"coordinates":[-71.333,46.911636],"type":"Point"}
}