{
  "type": "Feature",
  "properties": {
    "addr:full":"Victoria BC V8V 3P9",
    "addr:postcode":"v8v 3p9",
    "iso:country":"CA",
    "sg:city":"Victoria",
    "sg:classifiers":[
        {
            "category":"Social Services",
            "type":"Services"
        }
    ],
    "sg:phone":"+1 250 384 1341",
    "sg:postcode":"V8V 3P9",
    "sg:province":"BC",
    "sg:tags":[
        "counselor",
        "marriage",
        "family"
    ],
    "wof:name":"Progressive Edge Plus Nlp",
    "wof:placetype":"venue"
},
  "geometry": {"coordinates":[-123.35283699999999,48.426678],"type":"Point"}
}