{
  "type": "Feature",
  "properties": {
    "iso:country":"CA",
    "sg:city":"Victoria",
    "sg:classifiers":[
        {
            "category":"Social Services",
            "type":"Services"
        }
    ],
    "sg:phone":"+1 250 384 1341",
    "sg:postcode":"V8V 3P9",
    "sg:province":"BC",
    "sg:tags":[
        "counselor",
        "marriage",
        "family"
    ],
    "wof:name":"Progressive Edge Plus Nlp",
    "wof:placetype":"venue"
},
  "geometry": {"coordinates":[-123.352837,48.426678],"type":"Point"}
}