{
  "type": "Feature",
  "properties": {
    "iso:country":"CA",
    "sg:city":"Vancouver",
    "sg:classifiers":[
        {
            "category":"Real Estate",
            "subcategory":"Architect",
            "type":"Services"
        }
    ],
    "sg:phone":"+1 604 685 9913",
    "sg:postcode":"V6B 1A7",
    "sg:province":"BC",
    "wof:name":"Bunting Coady Architects",
    "wof:placetype":"venue"
},
  "geometry": {"coordinates":[-123.107971191,49.2843170166],"type":"Point"}
}