{
  "type": "Feature",
  "properties": {
    "addr:full":"125 Gore St W Thunder Bay ON P7E 3R3",
    "addr:housenumber":"125",
    "addr:postcode":"p7e 3r3",
    "addr:street":"Gore St W",
    "iso:country":"CA",
    "sg:address":"125 Gore St W",
    "sg:city":"Thunder Bay",
    "sg:classifiers":[
        {
            "category":"Wholesale",
            "subcategory":"Machinery & Supplies",
            "type":"Manufacturing & Wholesale Goods"
        }
    ],
    "sg:phone":"+1 807 577 7795",
    "sg:postcode":"P7E 3R3",
    "sg:province":"ON",
    "sg:tags":[
        "water",
        "brush",
        "treatment"
    ],
    "wof:name":"Thunder Bay Broom & Chemicals",
    "wof:placetype":"venue"
},
  "geometry": {"coordinates":[-89.279404,48.364155],"type":"Point"}
}