{
  "type": "Feature",
  "properties": {
    "addr:full":"33542 Eighth Ave Mission BC V2V 4L5",
    "addr:housenumber":"33542",
    "addr:postcode":"v2v 4l5",
    "addr:street":"Eighth Ave",
    "iso:country":"CA",
    "sg:address":"33542 Eighth Ave",
    "sg:city":"Mission",
    "sg:classifiers":[
        {
            "category":"Home & Garden",
            "subcategory":"Building Materials",
            "type":"Retail Goods"
        }
    ],
    "sg:phone":"+1 604 826 0481",
    "sg:postcode":"V2V 4L5",
    "sg:province":"BC",
    "sg:tags":[
        "door",
        "railing"
    ],
    "wof:name":"Dew Specialties",
    "wof:placetype":"venue"
},
  "geometry": {"coordinates":[-122.29573059099999,49.1404876709],"type":"Point"}
}