{
  "type": "Feature",
  "properties": {
    "addr:full":"2302 52E Av Lachine QC H8T 2Y3",
    "addr:housenumber":"2302",
    "addr:postcode":"h8t 2y3",
    "addr:street":"52E Av",
    "iso:country":"CA",
    "sg:address":"2302 52E Av",
    "sg:city":"Lachine",
    "sg:classifiers":[
        {
            "category":"Retail",
            "subcategory":"Auto Repair",
            "type":"Services"
        }
    ],
    "sg:phone":"+1 514 631 1988",
    "sg:postcode":"H8T 2Y3",
    "sg:province":"QC",
    "sg:tags":[
        "muffler",
        "exhaust",
        "system"
    ],
    "wof:name":"Silencieux Federal Muffler",
    "wof:placetype":"venue"
},
  "geometry": {"coordinates":[-73.72144299999999,45.46101],"type":"Point"}
}