{
  "type": "Feature",
  "properties": {
    "addr:full":"3065 King St E Kitchener ON N2A 1B1",
    "addr:housenumber":"3065",
    "addr:postcode":"n2a 1b1",
    "addr:street":"King St E",
    "iso:country":"CA",
    "sg:address":"3065 King St E",
    "sg:city":"Kitchener",
    "sg:classifiers":[
        {
            "category":"Manufacturing",
            "subcategory":"Food",
            "type":"Manufacturing & Wholesale Goods"
        }
    ],
    "sg:phone":"+1 519 893 1460",
    "sg:postcode":"N2A 1B1",
    "sg:province":"ON",
    "sg:tags":[
        "corn",
        "chips",
        "potato"
    ],
    "wof:name":"Humpty Dumpty Snack Foods Inc",
    "wof:placetype":"venue"
},
  "geometry": {"coordinates":[-80.42804700000001,43.427017],"type":"Point"}
}