{
  "type": "Feature",
  "properties": {
    "iso:country":"CA",
    "sg:address":"304 Markland Dr",
    "sg:city":"Etobicoke",
    "sg:classifiers":[
        {
            "category":"Professional",
            "subcategory":"Business Services",
            "type":"Services"
        }
    ],
    "sg:phone":"+1 416 626 1234",
    "sg:postcode":"M9C 1R8",
    "sg:province":"ON",
    "wof:name":"Regazzi Wines & Spirits Slctns",
    "wof:placetype":"venue"
},
  "geometry": {"coordinates":[-79.571503,43.62878],"type":"Point"}
}