{
  "type": "Feature",
  "properties": {
    "iso:country":"CA",
    "sg:address":"445 Route 309",
    "sg:city":"Val-Des-Bois",
    "sg:classifiers":[
        {
            "category":"Government",
            "subcategory":"Office",
            "type":"Public Place"
        }
    ],
    "sg:phone":"+1 819 454 2250",
    "sg:postcode":"J0X 3C0",
    "sg:province":"QC",
    "wof:name":"Quebec Conservation-Le Faune",
    "wof:placetype":"venue"
},
  "geometry": {"coordinates":[-75.60656738279999,45.8948860168],"type":"Point"}
}