{
  "type": "Feature",
  "properties": {
    "addr:full":"Belleville ON K8N 4Z5",
    "addr:postcode":"k8n 4z5",
    "iso:country":"CA",
    "sg:city":"Belleville",
    "sg:classifiers":[
        {
            "category":"Retail",
            "subcategory":"Auto Repair",
            "type":"Services"
        }
    ],
    "sg:phone":"+1 613 967 0315",
    "sg:postcode":"K8N 4Z5",
    "sg:province":"ON",
    "sg:tags":[
        "repairing",
        "automobile"
    ],
    "wof:name":"Keytag Auto Ltd",
    "wof:placetype":"venue"
},
  "geometry": {"coordinates":[-77.38189697270001,44.1610412598],"type":"Point"}
}