{
  "type": "Feature",
  "properties": {
    "iso:country":"CA",
    "sg:address":"249 Simcoe St",
    "sg:city":"Peterborough",
    "sg:classifiers":[
        {
            "category":"Banks & Credit Unions",
            "subcategory":"Investment Brokerage",
            "type":"Services"
        }
    ],
    "sg:phone":"+1 705 743 7865",
    "sg:postcode":"K9H 2H9",
    "sg:province":"ON",
    "wof:name":"Money Managers",
    "wof:placetype":"venue"
},
  "geometry": {"coordinates":[-78.323662,44.304356],"type":"Point"}
}