{
  "type": "Feature",
  "properties": {
    "iso:country":"CA",
    "sg:address":"274 Restigouche Rd",
    "sg:city":"Oromocto",
    "sg:classifiers":[
        {
            "category":"Retail",
            "subcategory":"Auto Repair",
            "type":"Services"
        }
    ],
    "sg:phone":"+1 506 357 2229",
    "sg:postcode":"E2V 2G9",
    "sg:province":"NB",
    "sg:tags":[
        "repairing",
        "automobile"
    ],
    "wof:name":"J & P Auto Repair",
    "wof:placetype":"venue"
},
  "geometry": {"coordinates":[-66.5006103516,45.8417510986],"type":"Point"}
}