{
  "type": "Feature",
  "properties": {
    "addr:full":"211 Ch Girouardville Bouctouche NB E4S 3G6",
    "addr:housenumber":"211",
    "addr:postcode":"e4s 3g6",
    "addr:street":"Ch Girouardville",
    "iso:country":"CA",
    "sg:address":"211 Ch Girouardville",
    "sg:city":"Bouctouche",
    "sg:classifiers":[
        {
            "category":"Sports & Exercise",
            "subcategory":"Golf",
            "type":"Entertainment"
        }
    ],
    "sg:phone":"+1 506 743 5251",
    "sg:postcode":"E4S 3G6",
    "sg:province":"NB",
    "sg:tags":[
        "course"
    ],
    "wof:name":"Bouctouche Golf Course",
    "wof:placetype":"venue"
},
  "geometry": {"coordinates":[-64.763245,46.478989],"type":"Point"}
}