{
  "type": "Feature",
  "properties": {
    "addr:full":"427 Railway Ave Abbey SK S0N 0A0",
    "addr:housenumber":"427",
    "addr:postcode":"s0n 0a0",
    "addr:street":"Railway Ave Abbey",
    "iso:country":"CA",
    "sg:address":"427 Railway Ave",
    "sg:city":"Abbey",
    "sg:classifiers":[
        {
            "category":"Wholesale",
            "subcategory":"Machinery & Supplies",
            "type":"Manufacturing & Wholesale Goods"
        }
    ],
    "sg:phone":"+1 306 689 2666",
    "sg:postcode":"S0N 0A0",
    "sg:province":"SK",
    "sg:tags":[
        "agricultural",
        "implement"
    ],
    "wof:name":"Bono Holdings",
    "wof:placetype":"venue"
},
  "geometry": {"coordinates":[-108.756690979,50.7361412048],"type":"Point"}
}