{
  "type": "Feature",
  "properties": {
    "iso:country":"CA",
    "sg:address":"835 Supertest Rd #200",
    "sg:city":"North York",
    "sg:classifiers":[
        {
            "category":"Professional",
            "type":"Services"
        }
    ],
    "sg:phone":"+1 416 665 1412",
    "sg:postcode":"M3J 2M9",
    "sg:province":"ON",
    "sg:tags":[
        "establishment",
        "furniture"
    ],
    "wof:name":"Hollend Furnishings",
    "wof:placetype":"venue"
},
  "geometry": {"coordinates":[-79.479568,43.775551],"type":"Point"}
}