{
  "type": "Feature",
  "properties": {
    "addr:full":"1895 Rue Lavoie Laval QC H7M 2N4",
    "addr:housenumber":"1895",
    "addr:postcode":"h7m 2n4",
    "addr:street":"Rue Lavoie",
    "iso:country":"CA",
    "sg:address":"1895 Rue Lavoie",
    "sg:city":"Laval",
    "sg:classifiers":[
        {
            "category":"Food & Beverages",
            "subcategory":"Groceries & Convenience Stores",
            "type":"Retail Goods"
        }
    ],
    "sg:phone":"+1 450 669 7103",
    "sg:postcode":"H7M 2N4",
    "sg:province":"QC",
    "sg:tags":[
        "grocer"
    ],
    "wof:name":"Depanneur Lavoie 2000",
    "wof:placetype":"venue"
},
  "geometry": {"coordinates":[-73.72760009770001,45.6030158997],"type":"Point"}
}