{
  "type": "Feature",
  "properties": {
    "addr:full":"806 Victoria St London ON N5Y 4E1",
    "addr:housenumber":"806",
    "addr:postcode":"n5y 4e1",
    "addr:street":"Victoria St",
    "iso:country":"CA",
    "sg:address":"806 Victoria St",
    "sg:city":"London",
    "sg:classifiers":[
        {
            "category":"Real Estate",
            "subcategory":"Developer",
            "type":"Services"
        }
    ],
    "sg:phone":"+1 519 451 9120",
    "sg:postcode":"N5Y 4E1",
    "sg:province":"ON",
    "sg:tags":[
        "cemetery"
    ],
    "wof:name":"St Peter's Cemetery & Chapel",
    "wof:placetype":"venue"
},
  "geometry": {"coordinates":[-81.228928,43.011951],"type":"Point"}
}