{
  "type": "Feature",
  "properties": {
    "addr:full":"Coquitlam BC V3K 7A1",
    "addr:postcode":"v3k 7a1",
    "iso:country":"CA",
    "sg:city":"Coquitlam",
    "sg:classifiers":[
        {
            "category":"Retail",
            "subcategory":"Auto Repair",
            "type":"Services"
        }
    ],
    "sg:phone":"+1 604 523 1239",
    "sg:postcode":"V3K 7A1",
    "sg:province":"BC",
    "sg:tags":[
        "repairing",
        "automobile",
        "muffler",
        "exhaust"
    ],
    "wof:name":"Budget Brake & Muffler",
    "wof:placetype":"venue"
},
  "geometry": {"coordinates":[-122.844009,49.226383],"type":"Point"}
}