{
  "type": "Feature",
  "properties": {
    "iso:country":"CA",
    "sg:address":"90 Sykes St N",
    "sg:city":"Meaford",
    "sg:classifiers":[
        {
            "category":"Shopping",
            "subcategory":"Computers & Home Electronics",
            "type":"Retail Goods"
        }
    ],
    "sg:phone":"+1 519 538 4498",
    "sg:postcode":"N4L 1N8",
    "sg:province":"ON",
    "sg:tags":[
        "equipment",
        "dealer"
    ],
    "wof:name":"Harbour Micro Trends",
    "wof:placetype":"venue"
},
  "geometry": {"coordinates":[-80.5925979614,44.6086158752],"type":"Point"}
}