{
  "type": "Feature",
  "properties": {
    "addr:full":"189 Dallas Rd Victoria BC V8V 1A1",
    "addr:housenumber":"189",
    "addr:postcode":"v8v 1a1",
    "addr:street":"Dallas Rd",
    "iso:country":"CA",
    "sg:address":"189 Dallas Rd",
    "sg:city":"Victoria",
    "sg:classifiers":[
        {
            "category":"Organizations",
            "subcategory":"Professional Association",
            "type":"Services"
        }
    ],
    "sg:phone":"+1 250 381 1611",
    "sg:postcode":"V8V 1A1",
    "sg:province":"BC",
    "wof:name":"Victoria am Assn",
    "wof:placetype":"venue"
},
  "geometry": {"coordinates":[-123.38508606000001,48.4162330627],"type":"Point"}
}