{
  "type": "Feature",
  "properties": {
    "addr:full":"Toronto ON M4T 1M9",
    "addr:postcode":"m4t 1m9",
    "iso:country":"CA",
    "sg:city":"Toronto",
    "sg:classifiers":[
        {
            "category":"Education",
            "subcategory":"College",
            "type":"Public Place"
        }
    ],
    "sg:phone":"+1 416 963 1211",
    "sg:postcode":"M4T 1M9",
    "sg:province":"ON",
    "sg:tags":[
        "academic",
        "school"
    ],
    "wof:name":"Ibt College of Business",
    "wof:placetype":"venue"
},
  "geometry": {"coordinates":[-79.391937,43.688663],"type":"Point"}
}