{
  "type": "Feature",
  "properties": {
    "addr:full":"1710 Railway St NW Edmonton AB T6P 1X3",
    "addr:housenumber":"1710",
    "addr:postcode":"t6p 1x3",
    "addr:street":"Railway St Nw",
    "iso:country":"CA",
    "sg:address":"1710 Railway St NW",
    "sg:city":"Edmonton",
    "sg:classifiers":[
        {
            "category":"Wholesale",
            "subcategory":"Machinery & Supplies",
            "type":"Manufacturing & Wholesale Goods"
        }
    ],
    "sg:phone":"+1 780 467 4580",
    "sg:postcode":"T6P 1X3",
    "sg:province":"AB",
    "sg:tags":[
        "cargo",
        "container",
        "freight"
    ],
    "wof:name":"Container King",
    "wof:placetype":"venue"
},
  "geometry": {"coordinates":[-113.34828899999999,53.460701],"type":"Point"}
}