{
  "type": "Feature",
  "properties": {
    "addr:full":"Mississauga ON L5T 2G6",
    "addr:postcode":"l5t 2g6",
    "iso:country":"CA",
    "sg:city":"Mississauga",
    "sg:classifiers":[
        {
            "category":"Retail",
            "subcategory":"Auto Repair",
            "type":"Services"
        }
    ],
    "sg:phone":"+1 905 564 7147",
    "sg:postcode":"L5T 2G6",
    "sg:province":"ON",
    "sg:tags":[
        "body",
        "automobile",
        "painting"
    ],
    "wof:name":"Black Diamond Auto Collision",
    "wof:placetype":"venue"
},
  "geometry": {"coordinates":[-79.64404296879999,43.6650123596],"type":"Point"}
}