{
  "type": "Feature",
  "properties": {
    "iso:country":"CA",
    "sg:address":"3863 Rue Beaubien E",
    "sg:city":"Montreal",
    "sg:classifiers":[
        {
            "category":"Food & Beverages",
            "subcategory":"Groceries & Convenience Stores",
            "type":"Retail Goods"
        }
    ],
    "sg:phone":"+1 514 722 2243",
    "sg:postcode":"H1X 1H3",
    "sg:province":"QC",
    "sg:tags":[
        "grocer"
    ],
    "wof:name":"Depanneur Bien Beau",
    "wof:placetype":"venue"
},
  "geometry": {"coordinates":[-73.581772,45.56039],"type":"Point"}
}