{
  "type": "Feature",
  "properties": {
    "addr:full":"342 Riverside Pky Frankford ON K0K 2C0",
    "addr:housenumber":"342",
    "addr:postcode":"k0k 2c0",
    "addr:street":"Riverside Pky",
    "iso:country":"CA",
    "sg:address":"342 Riverside Pky",
    "sg:city":"Frankford",
    "sg:classifiers":[
        {
            "category":"Food & Beverages",
            "subcategory":"Groceries & Convenience Stores",
            "type":"Retail Goods"
        }
    ],
    "sg:phone":"+1 613 398 6535",
    "sg:postcode":"K0K 2C0",
    "sg:province":"ON",
    "sg:tags":[
        "grocer"
    ],
    "wof:name":"Oasis Grocery",
    "wof:placetype":"venue"
},
  "geometry": {"coordinates":[-77.5914840698,44.2039604187],"type":"Point"}
}