{
  "type": "Feature",
  "properties": {
    "iso:country":"CA",
    "sg:address":"2800 Aviation Way",
    "sg:city":"Kamloops",
    "sg:classifiers":[
        {
            "category":"Building & Trades",
            "subcategory":"Equipment Rental",
            "type":"Services"
        }
    ],
    "sg:phone":"+1 250 376 4727",
    "sg:postcode":"V2B 7W1",
    "sg:province":"BC",
    "sg:tags":[
        "helicopter",
        "aircraft",
        "leasing",
        "charter"
    ],
    "wof:name":"Highland Helicopters Ltd",
    "wof:placetype":"venue"
},
  "geometry": {"coordinates":[-120.42918396,50.699432373],"type":"Point"}
}