{
  "type": "Feature",
  "properties": {
    "addr:full":"95 Oak St Simcoe ON N3Y 3K1",
    "addr:housenumber":"95",
    "addr:postcode":"n3y 3k1",
    "addr:street":"Oak St",
    "iso:country":"CA",
    "sg:address":"95 Oak St",
    "sg:city":"Simcoe",
    "sg:classifiers":[
        {
            "category":"Organizations",
            "subcategory":"Religious Organization",
            "type":"Services"
        }
    ],
    "sg:phone":"+1 519 426 0440",
    "sg:postcode":"N3Y 3K1",
    "sg:province":"ON",
    "sg:tags":[
        "church"
    ],
    "wof:name":"Christian Reformed Church",
    "wof:placetype":"venue"
},
  "geometry": {"coordinates":[-80.314774,42.827129],"type":"Point"}
}