{
  "type": "Feature",
  "properties": {
    "addr:full":"212 Mcgivern St W Walkerton ON N0G 2V0",
    "addr:housenumber":"212",
    "addr:postcode":"n0g 2v0",
    "addr:street":"Mcgivern St W Walkerton",
    "iso:country":"CA",
    "sg:address":"212 Mcgivern St W",
    "sg:city":"Walkerton",
    "sg:classifiers":[
        {
            "category":"Building & Trades",
            "subcategory":"Construction",
            "type":"Services"
        }
    ],
    "sg:phone":"+1 519 881 2024",
    "sg:postcode":"N0G 2V0",
    "sg:province":"ON",
    "sg:tags":[
        "excavating",
        "contractor"
    ],
    "wof:name":"Al Reich Backhoeing & Haulage",
    "wof:placetype":"venue"
},
  "geometry": {"coordinates":[-81.158165,44.118145],"type":"Point"}
}