{
  "type": "Feature",
  "properties": {
    "addr:full":"195 Boul Des Pres-Verts LA Prairie QC J5R 4P3",
    "addr:housenumber":"195",
    "addr:postcode":"j5r 4p3",
    "addr:street":"Boul Des Pres-Verts",
    "iso:country":"CA",
    "sg:address":"195 Boul Des Pres-Verts",
    "sg:city":"LA Prairie",
    "sg:classifiers":[
        {
            "category":"Health Services",
            "subcategory":"Medical Lab",
            "type":"Services"
        }
    ],
    "sg:phone":"+1 450 659 2363",
    "sg:postcode":"J5R 4P3",
    "sg:province":"QC",
    "wof:name":"Contant, Paul",
    "wof:placetype":"venue"
},
  "geometry": {"coordinates":[-73.4697647095,45.4124526978],"type":"Point"}
}