{
  "type": "Feature",
  "properties": {
    "iso:country":"CA",
    "sg:address":"1723 Comox Ave # 203",
    "sg:city":"Comox",
    "sg:classifiers":[
        {
            "category":"Health Services",
            "subcategory":"Clinic",
            "type":"Services"
        }
    ],
    "sg:phone":"+1 250 339 2233",
    "sg:postcode":"V9M 3M1",
    "sg:province":"BC",
    "sg:tags":[
        "therapist",
        "massage"
    ],
    "wof:name":"Harbourview Therapeutic Clinic",
    "wof:placetype":"venue"
},
  "geometry": {"coordinates":[-124.92350768999999,49.6723709106],"type":"Point"}
}