{
  "type": "Feature",
  "properties": {
    "iso:country":"CA",
    "sg:city":"Georgetown",
    "sg:classifiers":[
        {
            "category":"Shopping",
            "type":"Retail Goods"
        }
    ],
    "sg:phone":"+1 905 873 6642",
    "sg:postcode":"L7G 5G1",
    "sg:province":"ON",
    "sg:tags":[
        "hearing",
        "equipment",
        "supply",
        "impaired"
    ],
    "wof:name":"Hearing Clinic",
    "wof:placetype":"venue"
},
  "geometry": {"coordinates":[-79.894333,43.648521],"type":"Point"}
}