{
  "type": "Feature",
  "properties": {
    "addr:full":"4421 Boul Bourque Rock Forest QC J1N 1S4",
    "addr:housenumber":"4421",
    "addr:postcode":"j1n 1s4",
    "addr:street":"Boul Bourque",
    "iso:country":"CA",
    "sg:address":"4421 Boul Bourque",
    "sg:city":"Rock Forest",
    "sg:classifiers":[
        {
            "category":"Autos & Motor Vehicles",
            "subcategory":"Automobile Sales",
            "type":"Retail Goods"
        }
    ],
    "sg:phone":"+1 819 564 2834",
    "sg:postcode":"J1N 1S4",
    "sg:province":"QC",
    "sg:tags":[
        "car",
        "dealer"
    ],
    "wof:name":"Audi Sherbrooke Autohaus",
    "wof:placetype":"venue"
},
  "geometry": {"coordinates":[-71.97644805909999,45.3782196045],"type":"Point"}
}