{
  "type": "Feature",
  "properties": {
    "addr:full":"136 Bloor St E Oshawa ON L1H 3M4",
    "addr:housenumber":"136",
    "addr:postcode":"l1h 3m4",
    "addr:street":"Bloor St E",
    "iso:country":"CA",
    "sg:address":"136 Bloor St E",
    "sg:city":"Oshawa",
    "sg:classifiers":[
        {
            "category":"Real Estate",
            "subcategory":"Real Estate Agent",
            "type":"Services"
        }
    ],
    "sg:phone":"+1 905 720 0228",
    "sg:postcode":"L1H 3M4",
    "sg:province":"ON",
    "wof:name":"Homelife Durham Real Estate",
    "wof:placetype":"venue"
},
  "geometry": {"coordinates":[-78.850769,43.881687],"type":"Point"}
}