{
  "type": "Feature",
  "properties": {
    "addr:full":"425 Esterhazy St Esterhazy SK S0A 0X0",
    "addr:housenumber":"425",
    "addr:postcode":"s0a 0x0",
    "addr:street":"Esterhazy St",
    "iso:country":"CA",
    "sg:address":"425 Esterhazy St",
    "sg:city":"Esterhazy",
    "sg:classifiers":[
        {
            "category":"Building & Trades",
            "subcategory":"Plumbing",
            "type":"Services"
        }
    ],
    "sg:phone":"+1 306 745 3966",
    "sg:postcode":"S0A 0X0",
    "sg:province":"SK",
    "sg:tags":[
        "contractor"
    ],
    "wof:name":"Harris Plumbing & Heating",
    "wof:placetype":"venue"
},
  "geometry": {"coordinates":[-102.076706,50.655849],"type":"Point"}
}