{
  "type": "Feature",
  "properties": {
    "iso:country":"CA",
    "sg:address":"510 1st St",
    "sg:city":"Sointula",
    "sg:classifiers":[
        {
            "category":"Recreation",
            "subcategory":"Marina",
            "type":"Entertainment"
        }
    ],
    "sg:phone":"+1 250 973 6710",
    "sg:postcode":"V0N 3E0",
    "sg:province":"BC",
    "sg:tags":[
        "ways",
        "repairing",
        "marine",
        "boat"
    ],
    "wof:name":"Tarkanen Marine Ways",
    "wof:placetype":"venue"
},
  "geometry": {"coordinates":[-127.017357,50.627266],"type":"Point"}
}