{
  "type": "Feature",
  "properties": {
    "addr:full":"4275 Boul DE LA Rive-Sud Levis QC G6W 6M9",
    "addr:housenumber":"4275",
    "addr:postcode":"g6w 6m9",
    "addr:street":"Boul De La Rive-Sud",
    "iso:country":"CA",
    "sg:address":"4275 Boul DE LA Rive-Sud",
    "sg:city":"Levis",
    "sg:classifiers":[
        {
            "category":"Manufacturing",
            "subcategory":"Printing",
            "type":"Manufacturing & Wholesale Goods"
        }
    ],
    "sg:phone":"+1 418 833 1234",
    "sg:postcode":"G6W 6M9",
    "sg:province":"QC",
    "sg:tags":[
        "website",
        "multimedia",
        "design"
    ],
    "wof:name":"Dorcas Multimedia",
    "wof:placetype":"venue"
},
  "geometry": {"coordinates":[-71.19425200000001,46.778858],"type":"Point"}
}