{
  "type": "Feature",
  "properties": {
    "addr:full":"212 Main St Maidstone SK S0M 1M0",
    "addr:housenumber":"212",
    "addr:postcode":"s0m 1m0",
    "addr:street":"Main St",
    "iso:country":"CA",
    "sg:address":"212 Main St",
    "sg:city":"Maidstone",
    "sg:classifiers":[
        {
            "category":"Professional",
            "subcategory":"Research",
            "type":"Services"
        }
    ],
    "sg:phone":"+1 306 893 4156",
    "sg:postcode":"S0M 1M0",
    "sg:province":"SK",
    "sg:tags":[
        "economic",
        "analysis"
    ],
    "wof:name":"Big Gully Reda Inc",
    "wof:placetype":"venue"
},
  "geometry": {"coordinates":[-109.28984832800001,53.0874786377],"type":"Point"}
}