{
  "type": "Feature",
  "properties": {
    "addr:full":"41 Metropolitan Rd Scarborough ON M1R 2T5",
    "addr:housenumber":"41",
    "addr:postcode":"m1r 2t5",
    "addr:street":"Metropolitan Rd",
    "iso:country":"CA",
    "sg:address":"41 Metropolitan Rd",
    "sg:city":"Scarborough",
    "sg:classifiers":[
        {
            "category":"Professional",
            "subcategory":"Research",
            "type":"Services"
        }
    ],
    "sg:phone":"+1 416 297 7359",
    "sg:postcode":"M1R 2T5",
    "sg:province":"ON",
    "sg:tags":[
        "market",
        "analysis"
    ],
    "wof:name":"Target Dimensions",
    "wof:placetype":"venue"
},
  "geometry": {"coordinates":[-79.30069,43.767525],"type":"Point"}
}