{
  "type": "Feature",
  "properties": {
    "addr:full":"35 Brennan Harbour Rd Spanish ON P0P 2A0",
    "addr:housenumber":"35",
    "addr:postcode":"p0p 2a0",
    "addr:street":"Brennan Harbour Rd",
    "iso:country":"CA",
    "sg:address":"35 Brennan Harbour Rd",
    "sg:city":"Spanish",
    "sg:classifiers":[
        {
            "category":"Government",
            "subcategory":"Office",
            "type":"Public Place"
        }
    ],
    "sg:phone":"+1 705 844 2349",
    "sg:postcode":"P0P 2A0",
    "sg:province":"ON",
    "sg:tags":[
        "village"
    ],
    "wof:name":"Shedden Public Works Bldg",
    "wof:placetype":"venue"
},
  "geometry": {"coordinates":[-82.364113,46.190872],"type":"Point"}
}