{
  "type": "Feature",
  "properties": {
    "addr:full":"3663 Opie Cres Prince George BC V2N 1B9",
    "addr:housenumber":"3663",
    "addr:postcode":"v2n 1b9",
    "addr:street":"Opie Cres",
    "iso:country":"CA",
    "sg:address":"3663 Opie Cres",
    "sg:city":"Prince George",
    "sg:classifiers":[
        {
            "category":"Utilities",
            "subcategory":"Mobile Phone",
            "type":"Services"
        }
    ],
    "sg:phone":"+1 250 564 5517",
    "sg:postcode":"V2N 1B9",
    "sg:province":"BC",
    "sg:tags":[
        "telephone",
        "cellular"
    ],
    "wof:name":"Central Interior Comms Ltd",
    "wof:placetype":"venue"
},
  "geometry": {"coordinates":[-122.790580749,53.9007415771],"type":"Point"}
}