{
  "type": "Feature",
  "properties": {
    "iso:country":"CA",
    "sg:address":"965 Boul D'Auteuil",
    "sg:city":"Laval",
    "sg:classifiers":[
        {
            "category":"Cinema",
            "subcategory":"Movie Rental",
            "type":"Entertainment"
        }
    ],
    "sg:phone":"+1 450 661 0676",
    "sg:postcode":"H7E 5J7",
    "sg:province":"QC",
    "sg:tags":[
        "leasing",
        "video",
        "disc",
        "tape"
    ],
    "wof:name":"Superclub Videotron Ltee",
    "wof:placetype":"venue"
},
  "geometry": {"coordinates":[-73.72524261469999,45.6506881714],"type":"Point"}
}