{
  "type": "Feature",
  "properties": {
    "addr:full":"Lillooet BC V0K 1V0",
    "addr:postcode":"v0k 1v0",
    "iso:country":"CA",
    "sg:city":"Lillooet",
    "sg:classifiers":[
        {
            "category":"Home & Garden",
            "subcategory":"Building Materials",
            "type":"Retail Goods"
        }
    ],
    "sg:phone":"+1 250 256 0433",
    "sg:postcode":"V0K 1V0",
    "sg:province":"BC",
    "sg:tags":[
        "equipment",
        "kitchen",
        "door",
        "cabinet"
    ],
    "wof:name":"Second Growth Woodcraft",
    "wof:placetype":"venue"
},
  "geometry": {"coordinates":[-121.920181,50.719921],"type":"Point"}
}