{
  "type": "Feature",
  "properties": {
    "iso:country":"CA",
    "sg:address":"45 Rue DE LA Fabrique",
    "sg:city":"Varennes",
    "sg:classifiers":[
        {
            "category":"Social Services",
            "subcategory":"Child Care",
            "type":"Services"
        }
    ],
    "sg:phone":"+1 450 652 3821",
    "sg:postcode":"J3X 1R1",
    "sg:province":"QC",
    "wof:name":"Garderie Matin Soleil",
    "wof:placetype":"venue"
},
  "geometry": {"coordinates":[-73.440804,45.682995],"type":"Point"}
}