{
  "type": "Feature",
  "properties": {
    "addr:full":"London ON N6A 5C7",
    "addr:postcode":"n6a 5c7",
    "iso:country":"CA",
    "sg:city":"London",
    "sg:classifiers":[
        {
            "category":"Bars & Pubs",
            "type":"Food & Drink"
        }
    ],
    "sg:phone":"+1 519 675 1212",
    "sg:postcode":"N6A 5C7",
    "sg:province":"ON",
    "wof:name":"Molly Bloom's Irish Pub",
    "wof:placetype":"venue"
},
  "geometry": {"coordinates":[-81.25225067140001,42.993976593],"type":"Point"}
}