{
  "type": "Feature",
  "properties": {
    "addr:full":"6 Colby Crt #21 Waterloo ON N2V 1Y9",
    "addr:housenumber":"6",
    "addr:postcode":"n2v 1y9",
    "addr:street":"Colby Crt # 21",
    "iso:country":"CA",
    "sg:address":"6 Colby Crt #21",
    "sg:city":"Waterloo",
    "sg:classifiers":[
        {
            "category":"Manufacturing",
            "subcategory":"Tools & Machinery",
            "type":"Manufacturing & Wholesale Goods"
        }
    ],
    "sg:phone":"+1 519 725 4965",
    "sg:postcode":"N2V 1Y9",
    "sg:province":"ON",
    "sg:tags":[
        "machine",
        "shop"
    ],
    "wof:name":"Reactive Custom Machining Ltd",
    "wof:placetype":"venue"
},
  "geometry": {"coordinates":[-80.543541,43.50753],"type":"Point"}
}