{
  "type": "Feature",
  "properties": {
    "addr:full":"1401 Highway 17 E Kenora ON P9N 1M1",
    "addr:housenumber":"1401",
    "addr:postcode":"p9n 1m1",
    "addr:street":"Highway 17 E",
    "iso:country":"CA",
    "sg:address":"1401 Highway 17 E",
    "sg:city":"Kenora",
    "sg:classifiers":[
        {
            "category":"Autos & Motor Vehicles",
            "subcategory":"Fuel & Gas Station",
            "type":"Retail Goods"
        }
    ],
    "sg:phone":"+1 807 468 4888",
    "sg:postcode":"P9N 1M1",
    "sg:province":"ON",
    "sg:tags":[
        "oil"
    ],
    "wof:name":"Sunset Strip Husky",
    "wof:placetype":"venue"
},
  "geometry": {"coordinates":[-94.489311,49.770626],"type":"Point"}
}