{
  "type": "Feature",
  "properties": {
    "addr:full":"129 1st Ave W Hussar AB T0J 1S0",
    "addr:housenumber":"129",
    "addr:postcode":"t0j 1s0",
    "addr:street":"1St Ave W Hussar",
    "iso:country":"CA",
    "sg:address":"129 1st Ave W",
    "sg:city":"Hussar",
    "sg:classifiers":[
        {
            "category":"Building & Trades",
            "subcategory":"Construction",
            "type":"Services"
        }
    ],
    "sg:phone":"+1 403 787 3741",
    "sg:postcode":"T0J 1S0",
    "sg:province":"AB",
    "sg:tags":[
        "excavating",
        "contractor"
    ],
    "wof:name":"Doug's Earthmoving",
    "wof:placetype":"venue"
},
  "geometry": {"coordinates":[-112.68113700000001,51.039608],"type":"Point"}
}