{
  "type": "Feature",
  "properties": {
    "addr:full":"Calgary AB T2J 5S1",
    "addr:postcode":"t2j 5s1",
    "iso:country":"CA",
    "sg:city":"Calgary",
    "sg:classifiers":[
        {
            "category":"Retail",
            "subcategory":"Veterinary Services",
            "type":"Services"
        }
    ],
    "sg:phone":"+1 403 278 3168",
    "sg:postcode":"T2J 5S1",
    "sg:province":"AB",
    "sg:tags":[
        "veterinarian"
    ],
    "wof:name":"Acadia Drive Animal Clinic",
    "wof:placetype":"venue"
},
  "geometry": {"coordinates":[-114.04530334499999,50.9597816467],"type":"Point"}
}