{
  "type": "Feature",
  "properties": {
    "iso:country":"CA",
    "sg:city":"Saint-Tite",
    "sg:classifiers":[
        {
            "category":"Wholesale",
            "subcategory":"Machinery & Supplies",
            "type":"Manufacturing & Wholesale Goods"
        }
    ],
    "sg:phone":"+1 418 365 6110",
    "sg:postcode":"G0X 3H0",
    "sg:province":"QC",
    "sg:tags":[
        "brush"
    ],
    "wof:name":"Balai Laviolette Enr",
    "wof:placetype":"venue"
},
  "geometry": {"coordinates":[-72.5635147095,46.7240715027],"type":"Point"}
}