{
  "type": "Feature",
  "properties": {
    "iso:country":"CA",
    "sg:address":"74 Bushford St",
    "sg:city":"Courtice",
    "sg:classifiers":[
        {
            "category":"Real Estate",
            "subcategory":"Real Estate Agent",
            "type":"Services"
        }
    ],
    "sg:phone":"+1 905 404 2335",
    "sg:postcode":"L1E 2X1",
    "sg:province":"ON",
    "wof:name":"Paul Mc Arthur Ltd",
    "wof:placetype":"venue"
},
  "geometry": {"coordinates":[-78.7884140015,43.907787323],"type":"Point"}
}