{
  "type": "Feature",
  "properties": {
    "addr:full":"2570 Rue Nicolet # 315 Montreal QC H1W 3L5",
    "addr:housenumber":"2570",
    "addr:postcode":"h1w 3l5",
    "addr:street":"Rue Nicolet # 315",
    "iso:country":"CA",
    "sg:address":"2570 Rue Nicolet # 315",
    "sg:city":"Montreal",
    "sg:classifiers":[
        {
            "category":"Professional",
            "subcategory":"Lawyer & Legal Services",
            "type":"Services"
        }
    ],
    "sg:phone":"+1 514 597 2681",
    "sg:postcode":"H1W 3L5",
    "sg:province":"QC",
    "sg:tags":[
        "attorney"
    ],
    "wof:name":"Guevremont, Suzanne",
    "wof:placetype":"venue"
},
  "geometry": {"coordinates":[-73.55215454099999,45.5487480164],"type":"Point"}
}