{
  "type": "Feature",
  "properties": {
    "addr:full":"1111 Regent St Fredericton NB E3B 3Z2",
    "addr:housenumber":"1111",
    "addr:postcode":"e3b 3z2",
    "addr:street":"Regent St",
    "iso:country":"CA",
    "sg:address":"1111 Regent St",
    "sg:city":"Fredericton",
    "sg:classifiers":[
        {
            "category":"Restaurant",
            "type":"Food & Drink"
        }
    ],
    "sg:phone":"+1 506 450 4393",
    "sg:postcode":"E3B 3Z2",
    "sg:province":"NB",
    "wof:name":"Subway Sandwiches & Salads",
    "wof:placetype":"venue"
},
  "geometry": {"coordinates":[-66.65692900000001,45.940243],"type":"Point"}
}