{
  "type": "Feature",
  "properties": {
    "addr:full":"1194 Benson St Innisfil ON L9S 1Y4",
    "addr:housenumber":"1194",
    "addr:postcode":"l9s 1y4",
    "addr:street":"Benson St",
    "iso:country":"CA",
    "sg:address":"1194 Benson St",
    "sg:city":"Innisfil",
    "sg:classifiers":[
        {
            "category":"Wholesale",
            "subcategory":"Office Equipment",
            "type":"Manufacturing & Wholesale Goods"
        }
    ],
    "sg:phone":"+1 705 431 2947",
    "sg:postcode":"L9S 1Y4",
    "sg:province":"ON",
    "sg:tags":[
        "vault",
        "safe"
    ],
    "wof:name":"Rowe Safe & Vault Svc",
    "wof:placetype":"venue"
},
  "geometry": {"coordinates":[-79.56173699999999,44.314732],"type":"Point"}
}