{
  "type": "Feature",
  "properties": {
    "addr:full":"10525 150 St # 218 Surrey BC V3R 4B4",
    "addr:housenumber":"10525",
    "addr:postcode":"v3r 4b4",
    "addr:street":"150 St # 218",
    "iso:country":"CA",
    "sg:address":"10525 150 St # 218",
    "sg:city":"Surrey",
    "sg:classifiers":[
        {
            "category":"Real Estate",
            "subcategory":"Real Estate Operator",
            "type":"Services"
        }
    ],
    "sg:phone":"+1 604 582 0465",
    "sg:postcode":"V3R 4B4",
    "sg:province":"BC",
    "sg:tags":[
        "apartment"
    ],
    "wof:name":"Evergreen Apartments",
    "wof:placetype":"venue"
},
  "geometry": {"coordinates":[-122.806557,49.193981],"type":"Point"}
}