{
  "type": "Feature",
  "properties": {
    "iso:country":"CA",
    "sg:address":"9845 Av Papineau",
    "sg:city":"Montreal",
    "sg:classifiers":[
        {
            "category":"Health Services",
            "subcategory":"Nursing And Care Facility",
            "type":"Services"
        }
    ],
    "sg:phone":"+1 514 850 5678",
    "sg:postcode":"H2B 1Z9",
    "sg:province":"QC",
    "sg:tags":[
        "home",
        "retirement",
        "community"
    ],
    "wof:name":"Residence-St-Joseph D'Auntsic",
    "wof:placetype":"venue"
},
  "geometry": {"coordinates":[-73.645309,45.564838],"type":"Point"}
}