{
  "type": "Feature",
  "properties": {
    "iso:country":"CA",
    "sg:address":"9590 Boul Levesque E",
    "sg:city":"Laval",
    "sg:classifiers":[
        {
            "category":"Wholesale",
            "subcategory":"Groceries",
            "type":"Manufacturing & Wholesale Goods"
        }
    ],
    "sg:phone":"+1 450 665 8444",
    "sg:postcode":"H7A 4C6",
    "sg:province":"QC",
    "sg:tags":[
        "beverage"
    ],
    "wof:name":"L A Fruits Inc",
    "wof:placetype":"venue"
},
  "geometry": {"coordinates":[-73.5498352051,45.679649353],"type":"Point"}
}