{
  "type": "Feature",
  "properties": {
    "addr:full":"91 Esna Park Dr # 10 Markham ON L3R 2S2",
    "addr:housenumber":"91",
    "addr:postcode":"l3r 2s2",
    "addr:street":"Esna Park Dr # 10",
    "iso:country":"CA",
    "sg:address":"91 Esna Park Dr # 10",
    "sg:city":"Markham",
    "sg:classifiers":[
        {
            "category":"Wholesale",
            "subcategory":"Furniture",
            "type":"Manufacturing & Wholesale Goods"
        }
    ],
    "sg:phone":"+1 905 513 7274",
    "sg:postcode":"L3R 2S2",
    "sg:province":"ON",
    "wof:name":"Nervana International",
    "wof:placetype":"venue"
},
  "geometry": {"coordinates":[-79.340508,43.827484],"type":"Point"}
}