{
  "type": "Feature",
  "properties": {
    "addr:full":"231 132 Rte W Saint-Omer QC G0C 2Z0",
    "addr:housenumber":"132",
    "addr:postcode":"g0c 2z0",
    "addr:street":"Rte W Saint-Omer",
    "iso:country":"CA",
    "sg:address":"231 132 Rte W",
    "sg:city":"Saint-Omer",
    "sg:classifiers":[
        {
            "category":"Retail",
            "subcategory":"Auto Repair",
            "type":"Services"
        }
    ],
    "sg:phone":"+1 418 364 7669",
    "sg:postcode":"G0C 2Z0",
    "sg:province":"QC",
    "sg:tags":[
        "repairing",
        "automobile",
        "exchanging"
    ],
    "wof:name":"Garage Raymond Richard",
    "wof:placetype":"venue"
},
  "geometry": {"coordinates":[-66.244362,48.109612],"type":"Point"}
}