{
  "type": "Feature",
  "properties": {
    "addr:full":"Yellowknife NT X1A 3T3",
    "addr:postcode":"x1a 3t3",
    "iso:country":"CA",
    "sg:city":"Yellowknife",
    "sg:classifiers":[
        {
            "category":"Health Services",
            "subcategory":"Doctor",
            "type":"Services"
        }
    ],
    "sg:phone":"+1 867 873 3512",
    "sg:postcode":"X1A 3T3",
    "sg:province":"NT",
    "sg:tags":[
        "physician",
        "surgeon"
    ],
    "wof:name":"Woodside, Margaret MD",
    "wof:placetype":"venue"
},
  "geometry": {"coordinates":[-114.413094,62.462643],"type":"Point"}
}