{
  "type": "Feature",
  "properties": {
    "iso:country":"CA",
    "sg:address":"961 Camosun Cres",
    "sg:city":"Kamloops",
    "sg:classifiers":[
        {
            "category":"Retail",
            "subcategory":"Auto Repair",
            "type":"Services"
        }
    ],
    "sg:phone":"+1 250 374 2398",
    "sg:postcode":"V2C 6G1",
    "sg:province":"BC",
    "sg:tags":[
        "repairing",
        "automobile",
        "brake"
    ],
    "wof:name":"Hewett Auto Svc",
    "wof:placetype":"venue"
},
  "geometry": {"coordinates":[-120.367416,50.665707],"type":"Point"}
}