{
  "type": "Feature",
  "properties": {
    "iso:country":"CA",
    "sg:address":"145 Deer Park Ave",
    "sg:city":"Kimberley",
    "sg:classifiers":[
        {
            "category":"Restaurant",
            "type":"Food & Drink"
        }
    ],
    "sg:phone":"+1 250 427 1771",
    "sg:postcode":"V1A 2J5",
    "sg:province":"BC",
    "sg:tags":[
        "caterer"
    ],
    "wof:name":"Downtown Deli & Catering",
    "wof:placetype":"venue"
},
  "geometry": {"coordinates":[-115.983192444,49.6866989136],"type":"Point"}
}