{
  "type": "Feature",
  "properties": {
    "addr:full":"41 Munroe Pl # 22 Regina SK S4S 6A7",
    "addr:housenumber":"41;22",
    "addr:postcode":"s4s 6a7",
    "addr:street":"Munroe Pl #",
    "iso:country":"CA",
    "sg:address":"41 Munroe Pl # 22",
    "sg:city":"Regina",
    "sg:classifiers":[
        {
            "category":"Real Estate",
            "subcategory":"Real Estate Operator",
            "type":"Services"
        }
    ],
    "sg:phone":"+1 306 751 2260",
    "sg:postcode":"S4S 6A7",
    "sg:province":"SK",
    "sg:tags":[
        "apartment"
    ],
    "wof:name":"Qu'Appelle Village",
    "wof:placetype":"venue"
},
  "geometry": {"coordinates":[-104.599373,50.4142],"type":"Point"}
}