{
  "type": "Feature",
  "properties": {
    "iso:country":"CA",
    "sg:address":"473 Windmill Rd",
    "sg:city":"Dartmouth",
    "sg:classifiers":[
        {
            "category":"Home & Garden",
            "subcategory":"Carpets & Floor Coverings",
            "type":"Retail Goods"
        }
    ],
    "sg:phone":"+1 902 468 5193",
    "sg:postcode":"B3B 1B2",
    "sg:province":"NS",
    "sg:tags":[
        "material",
        "rug"
    ],
    "wof:name":"T K's Carpet Factory Outlet",
    "wof:placetype":"venue"
},
  "geometry": {"coordinates":[-63.5995063782,44.6882553101],"type":"Point"}
}