{
  "type": "Feature",
  "properties": {
    "addr:full":"271 Seldom Seen Rd Massey ON P0P 1P0",
    "addr:housenumber":"271",
    "addr:postcode":"p0p 1p0",
    "addr:street":"Seldom Seen Rd",
    "iso:country":"CA",
    "sg:address":"271 Seldom Seen Rd",
    "sg:city":"Massey",
    "sg:classifiers":[
        {
            "category":"Retail",
            "subcategory":"Animal Services",
            "type":"Services"
        }
    ],
    "sg:phone":"+1 705 865 2813",
    "sg:postcode":"P0P 1P0",
    "sg:province":"ON",
    "sg:tags":[
        "pet",
        "boarding",
        "grooming",
        "washing",
        "sitting"
    ],
    "wof:name":"Braeview Kennels Reg'd",
    "wof:placetype":"venue"
},
  "geometry": {"coordinates":[-82.076218,46.212616],"type":"Point"}
}