{
  "type": "Feature",
  "properties": {
    "iso:country":"CA",
    "sg:address":"5236 54 St",
    "sg:city":"Rocky Mountain House",
    "sg:classifiers":[
        {
            "category":"Organizations",
            "subcategory":"Religious Organization",
            "type":"Services"
        }
    ],
    "sg:phone":"+1 403 845 2063",
    "sg:postcode":"T4T 1H2",
    "sg:province":"AB",
    "sg:tags":[
        "church"
    ],
    "wof:name":"Lutheran Church",
    "wof:placetype":"venue"
},
  "geometry": {"coordinates":[-114.925392151,52.3780899048],"type":"Point"}
}