{
  "type": "Feature",
  "properties": {
    "addr:full":"Newmarket ON L3Y 1T3",
    "addr:postcode":"l3y 1t3",
    "iso:country":"CA",
    "sg:city":"Newmarket",
    "sg:classifiers":[
        {
            "category":"Banks & Credit Unions",
            "subcategory":"Investment Brokerage",
            "type":"Services"
        }
    ],
    "sg:phone":"+1 905 830 1500",
    "sg:postcode":"L3Y 1T3",
    "sg:province":"ON",
    "sg:tags":[
        "consultant",
        "planning",
        "financial"
    ],
    "wof:name":"Investment Planning Counsel",
    "wof:placetype":"venue"
},
  "geometry": {"coordinates":[-79.45813,44.052803],"type":"Point"}
}