{
  "type": "Feature",
  "properties": {
    "addr:full":"239 4th Ave E Prince Rupert BC V8J 1N4",
    "addr:housenumber":"239",
    "addr:postcode":"v8j 1n4",
    "addr:street":"4Th Ave E",
    "iso:country":"CA",
    "sg:address":"239 4th Ave E",
    "sg:city":"Prince Rupert",
    "sg:classifiers":[
        {
            "category":"Freight",
            "type":"Transportation"
        }
    ],
    "sg:phone":"+1 250 624 5133",
    "sg:postcode":"V8J 1N4",
    "sg:province":"BC",
    "sg:tags":[
        "broker",
        "customs"
    ],
    "wof:name":"Ets Moore Customs Brokers",
    "wof:placetype":"venue"
},
  "geometry": {"coordinates":[-130.31838999999999,54.315456],"type":"Point"}
}