{
  "type": "Feature",
  "properties": {
    "iso:country":"CA",
    "sg:address":"401 Albert St",
    "sg:city":"Brussels",
    "sg:classifiers":[
        {
            "category":"Retail",
            "subcategory":"Funeral Services",
            "type":"Services"
        }
    ],
    "sg:phone":"+1 519 887 6336",
    "sg:postcode":"N0G 1H0",
    "sg:province":"ON",
    "sg:tags":[
        "director"
    ],
    "wof:name":"Schiamanski Family Funeral Hme",
    "wof:placetype":"venue"
},
  "geometry": {"coordinates":[-81.246887207,43.7432746887],"type":"Point"}
}