{
  "type": "Feature",
  "properties": {
    "addr:full":"2895 Highway 60 Dwight ON P0A 1H0",
    "addr:housenumber":"2895",
    "addr:postcode":"p0a 1h0",
    "addr:street":"Highway 60",
    "iso:country":"CA",
    "sg:address":"2895 Highway 60",
    "sg:city":"Dwight",
    "sg:classifiers":[
        {
            "category":"Utilities",
            "subcategory":"Fuel Oil & Lpg",
            "type":"Services"
        }
    ],
    "sg:phone":"+1 705 635 2481",
    "sg:postcode":"P0A 1H0",
    "sg:province":"ON",
    "sg:tags":[
        "propane",
        "gas"
    ],
    "wof:name":"Algonquin & Rideau Propane",
    "wof:placetype":"venue"
},
  "geometry": {"coordinates":[-79.005188,45.324905],"type":"Point"}
}