{
  "type": "Feature",
  "properties": {
    "addr:full":"Rankin Inlet NU X0C 0G0",
    "addr:postcode":"x0c 0g0",
    "iso:country":"CA",
    "sg:city":"Rankin Inlet",
    "sg:classifiers":[
        {
            "category":"Social Services",
            "subcategory":"Child Care",
            "type":"Services"
        }
    ],
    "sg:phone":"+1 867 645 2685",
    "sg:postcode":"X0C 0G0",
    "sg:province":"NU",
    "wof:name":"Kataujaq Day Care",
    "wof:placetype":"venue"
},
  "geometry": {"coordinates":[-92.08335099999999,62.807144],"type":"Point"}
}