{
  "type": "Feature",
  "properties": {
    "iso:country":"CA",
    "sg:city":"Swan River",
    "sg:classifiers":[
        {
            "category":"Education",
            "subcategory":"School",
            "type":"Public Place"
        }
    ],
    "sg:phone":"+1 204 734 2651",
    "sg:postcode":"R0L 1Z0",
    "sg:province":"MB",
    "wof:name":"Solid Rock Christian School",
    "wof:placetype":"venue"
},
  "geometry": {"coordinates":[-101.251495361,52.1132888794],"type":"Point"}
}