{
  "type": "Feature",
  "properties": {
    "addr:full":"58 Clegg St Ottawa ON K1S 0H8",
    "addr:housenumber":"58",
    "addr:postcode":"k1s 0h8",
    "addr:street":"Clegg St",
    "iso:country":"CA",
    "sg:address":"58 Clegg St",
    "sg:city":"Ottawa",
    "sg:classifiers":[
        {
            "category":"Professional",
            "subcategory":"Lawyer & Legal Services",
            "type":"Services"
        }
    ],
    "sg:phone":"+1 613 237 6874",
    "sg:postcode":"K1S 0H8",
    "sg:province":"ON",
    "sg:tags":[
        "attorney"
    ],
    "wof:name":"Minard, Richard",
    "wof:placetype":"venue"
},
  "geometry": {"coordinates":[-75.67757415769999,45.4056129456],"type":"Point"}
}