{
  "type": "Feature",
  "properties": {
    "iso:country":"CA",
    "sg:address":"159 King St E # 207",
    "sg:city":"Kitchener",
    "sg:classifiers":[
        {
            "category":"Professional",
            "subcategory":"Employment Agencies",
            "type":"Services"
        }
    ],
    "sg:phone":"+1 519 576 0225",
    "sg:postcode":"N2G 2K8",
    "sg:province":"ON",
    "sg:tags":[
        "opportunity"
    ],
    "wof:name":"Action Force Driver Svc",
    "wof:placetype":"venue"
},
  "geometry": {"coordinates":[-80.486824,43.448593],"type":"Point"}
}