{
  "type": "Feature",
  "properties": {
    "iso:country":"CA",
    "sg:address":"238 Hood Rd",
    "sg:city":"Markham",
    "sg:classifiers":[
        {
            "category":"Wholesale",
            "subcategory":"Durable Goods & Equipment",
            "type":"Manufacturing & Wholesale Goods"
        }
    ],
    "sg:phone":"+1 905 944 0939",
    "sg:postcode":"L3R 3K8",
    "sg:province":"ON",
    "sg:tags":[
        "importer"
    ],
    "wof:name":"Amillo Inc",
    "wof:placetype":"venue"
},
  "geometry": {"coordinates":[-79.327721,43.824764],"type":"Point"}
}