{
  "type": "Feature",
  "properties": {
    "addr:full":"331 Main St Stoughton SK S0G 4T0",
    "addr:housenumber":"331",
    "addr:postcode":"s0g 4t0",
    "addr:street":"Main St",
    "iso:country":"CA",
    "sg:address":"331 Main St",
    "sg:city":"Stoughton",
    "sg:classifiers":[
        {
            "category":"Banks & Credit Unions",
            "subcategory":"Bank",
            "type":"Services"
        }
    ],
    "sg:phone":"+1 306 457 2443",
    "sg:postcode":"S0G 4T0",
    "sg:province":"SK",
    "wof:name":"Stoughton Credit Union",
    "wof:placetype":"venue"
},
  "geometry": {"coordinates":[-103.02252960200001,49.6766395569],"type":"Point"}
}