{
  "type": "Feature",
  "properties": {
    "addr:full":"320 Second Ave Strathmore AB T1P 1B3",
    "addr:housenumber":"320",
    "addr:postcode":"t1p 1b3",
    "addr:street":"Second Ave",
    "iso:country":"CA",
    "sg:address":"320 Second Ave",
    "sg:city":"Strathmore",
    "sg:classifiers":[
        {
            "category":"Food & Beverages",
            "subcategory":"Groceries & Convenience Stores",
            "type":"Retail Goods"
        }
    ],
    "sg:phone":"+1 403 934 3121",
    "sg:postcode":"T1P 1B3",
    "sg:province":"AB",
    "sg:tags":[
        "grocer"
    ],
    "wof:name":"Calgary CO-Operative Assn Ltd",
    "wof:placetype":"venue"
},
  "geometry": {"coordinates":[-113.398827,51.042282],"type":"Point"}
}