{
  "type": "Feature",
  "properties": {
    "addr:full":"2200 Bromsgrove Rd Mississauga ON L5J 1L4",
    "addr:housenumber":"2200",
    "addr:postcode":"l5j 1l4",
    "addr:street":"Bromsgrove Rd",
    "iso:country":"CA",
    "sg:address":"2200 Bromsgrove Rd",
    "sg:city":"Mississauga",
    "sg:classifiers":[
        {
            "category":"Manufacturing",
            "subcategory":"Glass & Minerals",
            "type":"Manufacturing & Wholesale Goods"
        }
    ],
    "sg:phone":"+1 905 822 4287",
    "sg:postcode":"L5J 1L4",
    "sg:province":"ON",
    "sg:tags":[
        "blackboard"
    ],
    "wof:name":"Architectural School Prods Ltd",
    "wof:placetype":"venue"
},
  "geometry": {"coordinates":[-79.6384353638,43.5109024048],"type":"Point"}
}