{
  "type": "Feature",
  "properties": {
    "iso:country":"CA",
    "sg:address":"2940 Rue Remembrance",
    "sg:city":"Lachine",
    "sg:classifiers":[
        {
            "category":"Shopping",
            "subcategory":"Clothing, Apparel, & Fashions",
            "type":"Retail Goods"
        }
    ],
    "sg:phone":"+1 514 634 3752",
    "sg:postcode":"H8S 1X8",
    "sg:province":"QC",
    "wof:name":"Reitmans",
    "wof:placetype":"venue"
},
  "geometry": {"coordinates":[-73.690063,45.437782],"type":"Point"}
}