{
  "type": "Feature",
  "properties": {
    "addr:full":"3112 Beta Ave Burnaby BC V5G 4K4",
    "addr:housenumber":"3112",
    "addr:postcode":"v5g 4k4",
    "addr:street":"Beta Ave",
    "iso:country":"CA",
    "sg:address":"3112 Beta Ave",
    "sg:city":"Burnaby",
    "sg:classifiers":[
        {
            "category":"Wholesale",
            "subcategory":"Auto Parts",
            "type":"Manufacturing & Wholesale Goods"
        }
    ],
    "sg:phone":"+1 604 299 0929",
    "sg:postcode":"V5G 4K4",
    "sg:province":"BC",
    "sg:tags":[
        "body",
        "automobile",
        "shop"
    ],
    "wof:name":"Sherwin-Williams CO",
    "wof:placetype":"venue"
},
  "geometry": {"coordinates":[-122.997833,49.25576],"type":"Point"}
}