{
  "type": "Feature",
  "properties": {
    "addr:full":"947 Rue Sainte-Helene Longueuil QC J4K 3R7",
    "addr:housenumber":"947",
    "addr:postcode":"j4k 3r7",
    "addr:street":"Rue Sainte-Helene",
    "iso:country":"CA",
    "sg:address":"947 Rue Sainte-Helene",
    "sg:city":"Longueuil",
    "sg:classifiers":[
        {
            "category":"Retail",
            "subcategory":"Auto Repair",
            "type":"Services"
        }
    ],
    "sg:phone":"+1 450 677 3851",
    "sg:postcode":"J4K 3R7",
    "sg:province":"QC",
    "sg:tags":[
        "repairing",
        "automobile"
    ],
    "wof:name":"Garage G Levert Enr",
    "wof:placetype":"venue"
},
  "geometry": {"coordinates":[-73.5057525635,45.5202903748],"type":"Point"}
}