{
  "type": "Feature",
  "properties": {
    "iso:country":"CA",
    "sg:address":"4720 Capilano Rd",
    "sg:city":"North Vancouver",
    "sg:classifiers":[
        {
            "category":"Retail",
            "subcategory":"Laundry & Dry Cleaning",
            "type":"Services"
        }
    ],
    "sg:phone":"+1 604 988 2020",
    "sg:postcode":"V7R 4K3",
    "sg:province":"BC",
    "sg:tags":[
        "cleaners"
    ],
    "wof:name":"Jeffersons Drycleaners",
    "wof:placetype":"venue"
},
  "geometry": {"coordinates":[-123.106079102,49.3554229736],"type":"Point"}
}