{
  "type": "Feature",
  "properties": {
    "iso:country":"CA",
    "sg:address":"104 Rankin Rd",
    "sg:city":"Sault Ste Marie",
    "sg:classifiers":[
        {
            "category":"Education",
            "subcategory":"Special Training",
            "type":"Public Place"
        }
    ],
    "sg:phone":"+1 705 946 1565",
    "sg:postcode":"P6A 4R8",
    "sg:province":"ON",
    "sg:tags":[
        "reading",
        "instruction",
        "improvement"
    ],
    "wof:name":"Coin Des Mots",
    "wof:placetype":"venue"
},
  "geometry": {"coordinates":[-84.263229,46.52486],"type":"Point"}
}