{
  "type": "Feature",
  "properties": {
    "iso:country":"CA",
    "sg:city":"Surrey",
    "sg:classifiers":[
        {
            "category":"Wholesale",
            "subcategory":"Machinery & Supplies",
            "type":"Manufacturing & Wholesale Goods"
        }
    ],
    "sg:phone":"+1 604 513 1773",
    "sg:postcode":"V4N 4C1",
    "sg:province":"BC",
    "sg:tags":[
        "sheet",
        "metal",
        "working"
    ],
    "wof:name":"Active Machinery Sales Ltd",
    "wof:placetype":"venue"
},
  "geometry": {"coordinates":[-122.686271667,49.1768722534],"type":"Point"}
}