{
  "type": "Feature",
  "properties": {
    "addr:full":"Calgary AB T2V 1K2",
    "addr:postcode":"t2v 1k2",
    "iso:country":"CA",
    "sg:city":"Calgary",
    "sg:classifiers":[
        {
            "category":"Real Estate",
            "subcategory":"Developer",
            "type":"Services"
        }
    ],
    "sg:phone":"+1 403 230 9472",
    "sg:postcode":"T2V 1K2",
    "sg:province":"AB",
    "wof:name":"Britgary Properties Ltd",
    "wof:placetype":"venue"
},
  "geometry": {"coordinates":[-114.082932,50.984673],"type":"Point"}
}