{
  "type": "Feature",
  "properties": {
    "addr:full":"395 Ontario St St Catharines ON L2N 7N6",
    "addr:housenumber":"395",
    "addr:postcode":"l2n 7n6",
    "addr:street":"Ontario St",
    "iso:country":"CA",
    "sg:address":"395 Ontario St",
    "sg:city":"St Catharines",
    "sg:classifiers":[
        {
            "category":"Social Services",
            "subcategory":"Child Care",
            "type":"Services"
        }
    ],
    "sg:phone":"+1 905 646 7311",
    "sg:postcode":"L2N 7N6",
    "sg:province":"ON",
    "sg:tags":[
        "consultant",
        "educational"
    ],
    "wof:name":"Early Childhood Community Dev",
    "wof:placetype":"venue"
},
  "geometry": {"coordinates":[-79.267235,43.181862],"type":"Point"}
}