{
  "type": "Feature",
  "properties": {
    "addr:full":"Saint-Jean-Port-Joli QC G0R 3G0",
    "addr:postcode":"g0r 3g0",
    "iso:country":"CA",
    "sg:city":"Saint-Jean-Port-Joli",
    "sg:classifiers":[
        {
            "category":"Government",
            "subcategory":"Office",
            "type":"Public Place"
        }
    ],
    "sg:phone":"+1 418 598 9465",
    "sg:postcode":"G0R 3G0",
    "sg:province":"QC",
    "sg:tags":[
        "village"
    ],
    "wof:name":"St-Jean Port-Joli Bureau",
    "wof:placetype":"venue"
},
  "geometry": {"coordinates":[-70.266777,47.212105],"type":"Point"}
}