{
  "type": "Feature",
  "properties": {
    "addr:full":"850 Boul Pierre-Bertrand # 340 Vanier QC G1M 3K8",
    "addr:housenumber":"850",
    "addr:postcode":"g1m 3k8",
    "addr:street":"Boul Pierre-Bertrand # 340",
    "iso:country":"CA",
    "sg:address":"850 Boul Pierre-Bertrand # 340",
    "sg:city":"Vanier",
    "sg:classifiers":[
        {
            "category":"Building & Trades",
            "subcategory":"Construction",
            "type":"Services"
        }
    ],
    "sg:phone":"+1 418 687 4334",
    "sg:postcode":"G1M 3K8",
    "sg:province":"QC",
    "sg:tags":[
        "general",
        "contractor"
    ],
    "wof:name":"Questco Inc",
    "wof:placetype":"venue"
},
  "geometry": {"coordinates":[-71.2734527588,46.8259086609],"type":"Point"}
}