{
  "type": "Feature",
  "properties": {
    "addr:full":"10307 95 Ave Fort St John BC V1J 5J5",
    "addr:housenumber":"10307",
    "addr:postcode":"v1j 5j5",
    "addr:street":"95 Ave",
    "iso:country":"CA",
    "sg:address":"10307 95 Ave",
    "sg:city":"Fort St John",
    "sg:classifiers":[
        {
            "category":"Building & Trades",
            "subcategory":"Construction",
            "type":"Services"
        }
    ],
    "sg:phone":"+1 250 787 9445",
    "sg:postcode":"V1J 5J5",
    "sg:province":"BC",
    "sg:tags":[
        "excavating",
        "contractor",
        "general"
    ],
    "wof:name":"Gtx Cavating Ltd",
    "wof:placetype":"venue"
},
  "geometry": {"coordinates":[-120.852699,56.241207],"type":"Point"}
}