{
  "type": "Feature",
  "properties": {
    "addr:full":"114 8th St E Owen Sound ON N4K 1K8",
    "addr:housenumber":"114",
    "addr:postcode":"n4k 1k8",
    "addr:street":"8Th St E",
    "iso:country":"CA",
    "sg:address":"114 8th St E",
    "sg:city":"Owen Sound",
    "sg:classifiers":[
        {
            "category":"Manufacturing",
            "subcategory":"Food",
            "type":"Manufacturing & Wholesale Goods"
        }
    ],
    "sg:phone":"+1 519 371 4484",
    "sg:postcode":"N4K 1K8",
    "sg:province":"ON",
    "sg:tags":[
        "chips"
    ],
    "wof:name":"Market Chip Wagon",
    "wof:placetype":"venue"
},
  "geometry": {"coordinates":[-80.94352000000001,44.563896],"type":"Point"}
}