{
  "type": "Feature",
  "properties": {
    "addr:full":"Demorestville ON K0K 1W0",
    "addr:postcode":"k0k 1w0",
    "iso:country":"CA",
    "sg:city":"Demorestville",
    "sg:classifiers":[
        {
            "category":"Autos & Motor Vehicles",
            "subcategory":"Boat Sales",
            "type":"Retail Goods"
        }
    ],
    "sg:phone":"+1 613 476 5357",
    "sg:postcode":"K0K 1W0",
    "sg:province":"ON",
    "sg:tags":[
        "marina",
        "dealer"
    ],
    "wof:name":"Baycrest Lodge & Marina",
    "wof:placetype":"venue"
},
  "geometry": {"coordinates":[-77.208015,44.092529],"type":"Point"}
}