{
  "type": "Feature",
  "properties": {
    "addr:full":"318 Lakeshore S Sauble Beach ON N0H 2G0",
    "addr:housenumber":"318",
    "addr:postcode":"n0h 2g0",
    "addr:street":"Lakeshore S Sauble Beach",
    "iso:country":"CA",
    "sg:address":"318 Lakeshore S",
    "sg:city":"Sauble Beach",
    "sg:classifiers":[
        {
            "category":"Restaurant",
            "type":"Food & Drink"
        }
    ],
    "sg:phone":"+1 519 422 1332",
    "sg:postcode":"N0H 2G0",
    "sg:province":"ON",
    "wof:name":"Driftwood Restaurant",
    "wof:placetype":"venue"
},
  "geometry": {"coordinates":[-81.27066000000001,44.628086],"type":"Point"}
}