{
  "type": "Feature",
  "properties": {
    "iso:country":"CA",
    "sg:address":"714 Rue Des Erables",
    "sg:city":"Neuville",
    "sg:classifiers":[
        {
            "category":"Organizations",
            "subcategory":"Religious Organization",
            "type":"Services"
        }
    ],
    "sg:phone":"+1 418 876 2022",
    "sg:postcode":"G0A 2R0",
    "sg:province":"QC",
    "sg:tags":[
        "church"
    ],
    "wof:name":"Presbytere Neuville",
    "wof:placetype":"venue"
},
  "geometry": {"coordinates":[-71.5840301514,46.6979446411],"type":"Point"}
}