{
  "type": "Feature",
  "properties": {
    "addr:full":"1919 Riverside Dr # 303 Ottawa ON K1H 1A2",
    "addr:housenumber":"1919",
    "addr:postcode":"k1h 1a2",
    "addr:street":"Riverside Dr # 303",
    "iso:country":"CA",
    "sg:address":"1919 Riverside Dr # 303",
    "sg:city":"Ottawa",
    "sg:classifiers":[
        {
            "category":"Health Services",
            "subcategory":"Doctor",
            "type":"Services"
        }
    ],
    "sg:phone":"+1 613 731 2781",
    "sg:postcode":"K1H 1A2",
    "sg:province":"ON",
    "sg:tags":[
        "physician",
        "surgeon"
    ],
    "wof:name":"Taylor, Mary MD",
    "wof:placetype":"venue"
},
  "geometry": {"coordinates":[-75.6698379517,45.3970565796],"type":"Point"}
}