{
  "type": "Feature",
  "properties": {
    "addr:full":"23 Rue Grande Katevale QC J0B 1W0",
    "addr:housenumber":"23",
    "addr:postcode":"j0b 1w0",
    "addr:street":"Rue Grande Katevale",
    "iso:country":"CA",
    "sg:address":"23 Rue Grande",
    "sg:city":"Katevale",
    "sg:classifiers":[
        {
            "category":"Organizations",
            "subcategory":"Religious Organization",
            "type":"Services"
        }
    ],
    "sg:phone":"+1 819 843 5151",
    "sg:postcode":"J0B 1W0",
    "sg:province":"QC",
    "sg:tags":[
        "church"
    ],
    "wof:name":"Presbytere Ste-Catherine",
    "wof:placetype":"venue"
},
  "geometry": {"coordinates":[-72.052864,45.196171],"type":"Point"}
}