{
  "type": "Feature",
  "properties": {
    "addr:full":"7830 Ch Du Lac-Kaiagamac Saint-Michel-Des-Saints QC J0K 3B0",
    "addr:postcode":"7830;j0k 3b0",
    "addr:street":"Ch Du Lac-Kaiagamac",
    "iso:country":"CA",
    "sg:address":"7830 Ch Du Lac-Kaiagamac",
    "sg:city":"Saint-Michel-Des-Saints",
    "sg:classifiers":[
        {
            "category":"Travel",
            "subcategory":"Hotels & Motels",
            "type":"Entertainment"
        }
    ],
    "sg:phone":"+1 450 833 6714",
    "sg:postcode":"J0K 3B0",
    "sg:province":"QC",
    "sg:tags":[
        "cottage",
        "cabin"
    ],
    "wof:name":"Motel Au P'Tit Gibier",
    "wof:placetype":"venue"
},
  "geometry": {"coordinates":[-73.893097,46.649937],"type":"Point"}
}