{
  "type": "Feature",
  "properties": {
    "iso:country":"CA",
    "sg:city":"Calgary",
    "sg:classifiers":[
        {
            "category":"Wholesale",
            "subcategory":"Durable Goods & Equipment",
            "type":"Manufacturing & Wholesale Goods"
        }
    ],
    "sg:phone":"+1 403 291 6661",
    "sg:postcode":"T2E 6L1",
    "sg:province":"AB",
    "sg:tags":[
        "importer"
    ],
    "wof:name":"Classy Imports",
    "wof:placetype":"venue"
},
  "geometry": {"coordinates":[-114.030006,51.088856],"type":"Point"}
}