{
  "type": "Feature",
  "properties": {
    "addr:full":"239 3rd St Weyburn SK S4H 0W5",
    "addr:housenumber":"239",
    "addr:postcode":"s4h 0w5",
    "addr:street":"3Rd St",
    "iso:country":"CA",
    "sg:address":"239 3rd St",
    "sg:city":"Weyburn",
    "sg:classifiers":[
        {
            "category":"Organizations",
            "subcategory":"Religious Organization",
            "type":"Services"
        }
    ],
    "sg:phone":"+1 306 842 3125",
    "sg:postcode":"S4H 0W5",
    "sg:province":"SK",
    "sg:tags":[
        "church"
    ],
    "wof:name":"All Saints Anglican Church",
    "wof:placetype":"venue"
},
  "geometry": {"coordinates":[-103.85329400000001,49.663914],"type":"Point"}
}