{
  "type": "Feature",
  "properties": {
    "addr:full":"201 Ferguson Ave S Hamilton ON L8N 2N2",
    "addr:housenumber":"201",
    "addr:postcode":"l8n 2n2",
    "addr:street":"Ferguson Ave S",
    "iso:country":"CA",
    "sg:address":"201 Ferguson Ave S",
    "sg:city":"Hamilton",
    "sg:classifiers":[
        {
            "category":"Building & Trades",
            "subcategory":"Construction",
            "type":"Services"
        }
    ],
    "sg:phone":"+1 905 526 1314",
    "sg:postcode":"L8N 2N2",
    "sg:province":"ON",
    "sg:tags":[
        "painter"
    ],
    "wof:name":"Al's Residential Painting",
    "wof:placetype":"venue"
},
  "geometry": {"coordinates":[-79.8645706177,43.2482147217],"type":"Point"}
}