{
  "type": "Feature",
  "properties": {
    "iso:country":"CA",
    "sg:address":"679 Mount Pleasant Rd",
    "sg:city":"Toronto",
    "sg:classifiers":[
        {
            "category":"Restaurant",
            "type":"Food & Drink"
        }
    ],
    "sg:phone":"+1 416 486 1111",
    "sg:postcode":"M4S 2N2",
    "sg:province":"ON",
    "wof:name":"Across the Road Restaurant",
    "wof:placetype":"venue"
},
  "geometry": {"coordinates":[-79.3889465332,43.7058181763],"type":"Point"}
}