{
  "type": "Feature",
  "properties": {
    "addr:full":"1587 Highway 56 Hannon ON L0R 1P0",
    "addr:housenumber":"1587",
    "addr:postcode":"l0r 1p0",
    "addr:street":"Highway 56",
    "iso:country":"CA",
    "sg:address":"1587 Highway 56",
    "sg:city":"Hannon",
    "sg:classifiers":[
        {
            "category":"Wholesale",
            "subcategory":"Machinery & Supplies",
            "type":"Manufacturing & Wholesale Goods"
        }
    ],
    "sg:phone":"+1 905 692 5561",
    "sg:postcode":"L0R 1P0",
    "sg:province":"ON",
    "sg:tags":[
        "equipment",
        "industrial"
    ],
    "wof:name":"Advanced Control Concepts",
    "wof:placetype":"venue"
},
  "geometry": {"coordinates":[-79.837738,43.19854],"type":"Point"}
}