{
  "type": "Feature",
  "properties": {
    "addr:full":"Sainte-Madeleine QC J0H 1S0",
    "addr:postcode":"j0h 1s0",
    "iso:country":"CA",
    "sg:city":"Sainte-Madeleine",
    "sg:classifiers":[
        {
            "category":"Wholesale",
            "subcategory":"Durable Goods & Equipment",
            "type":"Manufacturing & Wholesale Goods"
        }
    ],
    "sg:phone":"+1 450 795 8733",
    "sg:postcode":"J0H 1S0",
    "sg:province":"QC",
    "sg:tags":[
        "fire",
        "extinguisher"
    ],
    "wof:name":"Securite Maska Enr",
    "wof:placetype":"venue"
},
  "geometry": {"coordinates":[-73.009109,45.585712],"type":"Point"}
}