{
  "type": "Feature",
  "properties": {
    "addr:full":"Coquitlam BC V3K 6R4",
    "addr:postcode":"v3k 6r4",
    "iso:country":"CA",
    "sg:city":"Coquitlam",
    "sg:classifiers":[
        {
            "category":"Wholesale",
            "subcategory":"Durable Goods & Equipment",
            "type":"Manufacturing & Wholesale Goods"
        }
    ],
    "sg:phone":"+1 604 931 4713",
    "sg:postcode":"V3K 6R4",
    "sg:province":"BC",
    "sg:tags":[
        "exporter"
    ],
    "wof:name":"Rhino Caps Industries Inc",
    "wof:placetype":"venue"
},
  "geometry": {"coordinates":[-122.88886261,49.2492256165],"type":"Point"}
}