{
  "type": "Feature",
  "properties": {
    "addr:full":"953 King L'Orignal ON K0B 1K0",
    "addr:housenumber":"953",
    "addr:postcode":"k0b 1k0",
    "addr:street":"King L'Orignal",
    "iso:country":"CA",
    "sg:address":"953 King",
    "sg:city":"L'Orignal",
    "sg:classifiers":[
        {
            "category":"Government",
            "subcategory":"Office",
            "type":"Public Place"
        }
    ],
    "sg:phone":"+1 613 675 2629",
    "sg:postcode":"K0B 1K0",
    "sg:province":"ON",
    "sg:tags":[
        "village"
    ],
    "wof:name":"L'Orignal Municipal Skating",
    "wof:placetype":"venue"
},
  "geometry": {"coordinates":[-74.6896820068,45.6210365295],"type":"Point"}
}