{
  "type": "Feature",
  "properties": {
    "addr:full":"2794 Lake Shore Blvd W Etobicoke ON M8V 1H5",
    "addr:housenumber":"2794",
    "addr:postcode":"m8v 1h5",
    "addr:street":"Lake Shore Blvd W",
    "iso:country":"CA",
    "sg:address":"2794 Lake Shore Blvd W",
    "sg:city":"Etobicoke",
    "sg:classifiers":[
        {
            "category":"Professional",
            "subcategory":"Lawyer & Legal Services",
            "type":"Services"
        }
    ],
    "sg:phone":"+1 416 252 3351",
    "sg:postcode":"M8V 1H5",
    "sg:province":"ON",
    "sg:tags":[
        "attorney"
    ],
    "wof:name":"Copeland Mc Kenna",
    "wof:placetype":"venue"
},
  "geometry": {"coordinates":[-79.500191,43.602016],"type":"Point"}
}