{
  "type": "Feature",
  "properties": {
    "addr:full":"574 Rue Saint-Ignace Quebec QC G1N 1N7",
    "addr:housenumber":"574",
    "addr:postcode":"g1n 1n7",
    "addr:street":"Rue Saint-Ignace",
    "iso:country":"CA",
    "sg:address":"574 Rue Saint-Ignace",
    "sg:city":"Quebec",
    "sg:classifiers":[
        {
            "category":"Wholesale",
            "subcategory":"Machinery & Supplies",
            "type":"Manufacturing & Wholesale Goods"
        }
    ],
    "sg:phone":"+1 418 647 9512",
    "sg:postcode":"G1N 1N7",
    "sg:province":"QC",
    "sg:tags":[
        "director",
        "funeral"
    ],
    "wof:name":"Maison DE L'Orfevre",
    "wof:placetype":"venue"
},
  "geometry": {"coordinates":[-71.24232499999999,46.809967],"type":"Point"}
}