{
  "type": "Feature",
  "properties": {
    "addr:full":"10 Rue Saint-Dominique Victoriaville QC G6P 5B6",
    "addr:housenumber":"10",
    "addr:postcode":"g6p 5b6",
    "addr:street":"Rue Saint-Dominique",
    "iso:country":"CA",
    "sg:address":"10 Rue Saint-Dominique",
    "sg:city":"Victoriaville",
    "sg:classifiers":[
        {
            "category":"Personal",
            "subcategory":"Beauty Salon",
            "type":"Services"
        }
    ],
    "sg:phone":"+1 819 751 1313",
    "sg:postcode":"G6P 5B6",
    "sg:province":"QC",
    "wof:name":"Maryse Concept Esthetique",
    "wof:placetype":"venue"
},
  "geometry": {"coordinates":[-71.95689400000001,46.056122],"type":"Point"}
}