{
  "type": "Feature",
  "properties": {
    "addr:full":"915 Rue Vercheres Longueuil QC J4K 2Y8",
    "addr:housenumber":"915",
    "addr:postcode":"j4k 2y8",
    "addr:street":"Rue Vercheres",
    "iso:country":"CA",
    "sg:address":"915 Rue Vercheres",
    "sg:city":"Longueuil",
    "sg:classifiers":[
        {
            "category":"Retail",
            "subcategory":"Auto Repair",
            "type":"Services"
        }
    ],
    "sg:phone":"+1 450 442 0474",
    "sg:postcode":"J4K 2Y8",
    "sg:province":"QC",
    "sg:tags":[
        "wrecker"
    ],
    "wof:name":"Entreprise-Remorquage Towbec",
    "wof:placetype":"venue"
},
  "geometry": {"coordinates":[-73.508842,45.516457],"type":"Point"}
}