{
  "type": "Feature",
  "properties": {
    "addr:full":"469 Lake Park Rd Carleton Place ON K7C 3P2",
    "addr:housenumber":"469",
    "addr:postcode":"k7c 3p2",
    "addr:street":"Lake Park Rd",
    "iso:country":"CA",
    "sg:address":"469 Lake Park Rd",
    "sg:city":"Carleton Place",
    "sg:classifiers":[
        {
            "category":"Sports & Exercise",
            "subcategory":"Golf",
            "type":"Entertainment"
        }
    ],
    "sg:phone":"+1 613 257 8623",
    "sg:postcode":"K7C 3P2",
    "sg:province":"ON",
    "sg:tags":[
        "course"
    ],
    "wof:name":"Carlbeck Golf & Country Club",
    "wof:placetype":"venue"
},
  "geometry": {"coordinates":[-76.146812439,45.1404495239],"type":"Point"}
}