{
  "type": "Feature",
  "properties": {
    "addr:full":"113 6th St Wawanesa MB R0K 2G0",
    "addr:housenumber":"113",
    "addr:postcode":"r0k 2g0",
    "addr:street":"6Th St",
    "iso:country":"CA",
    "sg:address":"113 6th St",
    "sg:city":"Wawanesa",
    "sg:classifiers":[
        {
            "category":"Building & Trades",
            "subcategory":"Plumbing",
            "type":"Services"
        }
    ],
    "sg:phone":"+1 204 824 2427",
    "sg:postcode":"R0K 2G0",
    "sg:province":"MB",
    "sg:tags":[
        "contractor"
    ],
    "wof:name":"Tom's Plumbing & Heating",
    "wof:placetype":"venue"
},
  "geometry": {"coordinates":[-99.68441799999999,49.595905],"type":"Point"}
}