{
  "type": "Feature",
  "properties": {
    "addr:full":"3530 91 St NW Edmonton AB T6E 6P1",
    "addr:housenumber":"3530",
    "addr:postcode":"t6e 6p1",
    "addr:street":"91 St Nw",
    "iso:country":"CA",
    "sg:address":"3530 91 St NW",
    "sg:city":"Edmonton",
    "sg:classifiers":[
        {
            "category":"Recreation",
            "type":"Entertainment"
        }
    ],
    "sg:phone":"+1 780 435 1252",
    "sg:postcode":"T6E 6P1",
    "sg:province":"AB",
    "sg:tags":[
        "hall",
        "auditorium"
    ],
    "wof:name":"Asian Christian Assn-Alberta",
    "wof:placetype":"venue"
},
  "geometry": {"coordinates":[-113.467468,53.469158],"type":"Point"}
}