{
  "type": "Feature",
  "properties": {
    "addr:full":"185 West River Rd Cambridge ON N1S 2Z9",
    "addr:housenumber":"185",
    "addr:postcode":"n1s 2z9",
    "addr:street":"West River Rd",
    "iso:country":"CA",
    "sg:address":"185 West River Rd",
    "sg:city":"Cambridge",
    "sg:classifiers":[
        {
            "category":"Real Estate",
            "subcategory":"Real Estate Agent",
            "type":"Services"
        }
    ],
    "sg:phone":"+1 519 740 8080",
    "sg:postcode":"N1S 2Z9",
    "sg:province":"ON",
    "wof:name":"Holmes Real Estate Svc Inc",
    "wof:placetype":"venue"
},
  "geometry": {"coordinates":[-80.321358,43.337631],"type":"Point"}
}