{
  "type": "Feature",
  "properties": {
    "addr:full":"PO Box 3321 STN B Calgary AB T2M 4L8",
    "addr:housenumber":"po",
    "addr:postcode":"t2m 4l8",
    "addr:street":"Box 3321 Stn B",
    "iso:country":"CA",
    "sg:address":"PO Box 3321 STN B",
    "sg:city":"Calgary",
    "sg:classifiers":[
        {
            "category":"Wholesale",
            "subcategory":"Electrical",
            "type":"Manufacturing & Wholesale Goods"
        }
    ],
    "sg:phone":"+1 403 286 2080",
    "sg:postcode":"T2M 4L8",
    "sg:province":"AB",
    "sg:tags":[
        "instrument"
    ],
    "wof:name":"R H Pyle & Assoc Ltd",
    "wof:placetype":"venue"
},
  "geometry": {"coordinates":[-114.063194,51.045074],"type":"Point"}
}