{
  "type": "Feature",
  "properties": {
    "iso:country":"CA",
    "sg:address":"16 Paint St",
    "sg:city":"Port Hawkesbury",
    "sg:classifiers":[
        {
            "category":"Wholesale",
            "subcategory":"Scrap",
            "type":"Manufacturing & Wholesale Goods"
        }
    ],
    "sg:phone":"+1 902 625 2448",
    "sg:postcode":"B9A 3J6",
    "sg:province":"NS",
    "sg:tags":[
        "recycling",
        "center"
    ],
    "wof:name":"Strait Bottle Exchange",
    "wof:placetype":"venue"
},
  "geometry": {"coordinates":[-61.3336334229,45.6178855896],"type":"Point"}
}