{
  "type": "Feature",
  "properties": {
    "addr:full":"234 Bay St Orillia ON L3V 3W8",
    "addr:housenumber":"234",
    "addr:postcode":"l3v 3w8",
    "addr:street":"Bay St",
    "iso:country":"CA",
    "sg:address":"234 Bay St",
    "sg:city":"Orillia",
    "sg:classifiers":[
        {
            "category":"Health Services",
            "subcategory":"Nursing And Care Facility",
            "type":"Services"
        }
    ],
    "sg:phone":"+1 705 326 8520",
    "sg:postcode":"L3V 3W8",
    "sg:province":"ON",
    "sg:tags":[
        "home",
        "retirement",
        "community"
    ],
    "wof:name":"Birchmere Retirement Residence",
    "wof:placetype":"venue"
},
  "geometry": {"coordinates":[-79.4142150879,44.6193618774],"type":"Point"}
}