{
  "type": "Feature",
  "properties": {
    "iso:country":"CA",
    "sg:address":"538 Rue Cherrier",
    "sg:city":"L'Ile-Bizard",
    "sg:classifiers":[
        {
            "category":"Health Services",
            "subcategory":"Hospital",
            "type":"Services"
        }
    ],
    "sg:phone":"+1 514 282 7753",
    "sg:postcode":"H9E 1B4",
    "sg:province":"QC",
    "sg:tags":[
        "mental"
    ],
    "wof:name":"Centre DE Crise Le Transit",
    "wof:placetype":"venue"
},
  "geometry": {"coordinates":[-73.8795547485,45.4859161377],"type":"Point"}
}