{
  "type": "Feature",
  "properties": {
    "iso:country":"CA",
    "sg:address":"5920 Malden Rd",
    "sg:city":"Windsor",
    "sg:classifiers":[
        {
            "category":"Health Services",
            "subcategory":"Doctor",
            "type":"Services"
        }
    ],
    "sg:phone":"+1 519 972 4874",
    "sg:postcode":"N9H 1S4",
    "sg:province":"ON",
    "sg:tags":[
        "dentist"
    ],
    "wof:name":"Evon, Bill DDS",
    "wof:placetype":"venue"
},
  "geometry": {"coordinates":[-83.060509,42.252739],"type":"Point"}
}