{
  "type": "Feature",
  "properties": {
    "addr:full":"150 Rue Lansdowne Granby QC J2G 4P4",
    "addr:housenumber":"150",
    "addr:postcode":"j2g 4p4",
    "addr:street":"Rue Lansdowne",
    "iso:country":"CA",
    "sg:address":"150 Rue Lansdowne",
    "sg:city":"Granby",
    "sg:classifiers":[
        {
            "category":"Education",
            "subcategory":"School",
            "type":"Public Place"
        }
    ],
    "sg:phone":"+1 450 372 5454",
    "sg:postcode":"J2G 4P4",
    "sg:province":"QC",
    "wof:name":"Polyvalente Sacre-Coeur",
    "wof:placetype":"venue"
},
  "geometry": {"coordinates":[-72.7156295776,45.4051132202],"type":"Point"}
}