{
  "type": "Feature",
  "properties": {
    "addr:full":"251 Vidal St N Sarnia ON N7T 5Y5",
    "addr:housenumber":"251",
    "addr:postcode":"n7t 5y5",
    "addr:street":"Vidal St N",
    "iso:country":"CA",
    "sg:address":"251 Vidal St N",
    "sg:city":"Sarnia",
    "sg:classifiers":[
        {
            "category":"Shopping",
            "type":"Retail Goods"
        }
    ],
    "sg:phone":"+1 519 332 8901",
    "sg:postcode":"N7T 5Y5",
    "sg:province":"ON",
    "sg:tags":[
        "art",
        "gallery",
        "dealer"
    ],
    "wof:name":"Kenneith Gallery",
    "wof:placetype":"venue"
},
  "geometry": {"coordinates":[-82.404488,42.975883],"type":"Point"}
}