{
  "type": "Feature",
  "properties": {
    "addr:full":"720 Midland Ave Scarborough ON M1K 4C9",
    "addr:housenumber":"720",
    "addr:postcode":"m1k 4c9",
    "addr:street":"Midland Ave",
    "iso:country":"CA",
    "sg:address":"720 Midland Ave",
    "sg:city":"Scarborough",
    "sg:classifiers":[
        {
            "category":"Social Services",
            "subcategory":"Child Care",
            "type":"Services"
        }
    ],
    "sg:phone":"+1 416 264 8050",
    "sg:postcode":"M1K 4C9",
    "sg:province":"ON",
    "wof:name":"Nyad Midland Campus",
    "wof:placetype":"venue"
},
  "geometry": {"coordinates":[-79.25561500000001,43.728245],"type":"Point"}
}