{
  "type": "Feature",
  "properties": {
    "addr:full":"Montreal QC H2J 2K7",
    "addr:postcode":"h2j 2k7",
    "iso:country":"CA",
    "sg:city":"Montreal",
    "sg:classifiers":[
        {
            "category":"Professional",
            "subcategory":"Business Services",
            "type":"Services"
        }
    ],
    "sg:phone":"+1 514 525 8852",
    "sg:postcode":"H2J 2K7",
    "sg:province":"QC",
    "sg:tags":[
        "notary"
    ],
    "wof:name":"Allard, Ginette",
    "wof:placetype":"venue"
},
  "geometry": {"coordinates":[-73.57004499999999,45.530197],"type":"Point"}
}