{
  "type": "Feature",
  "properties": {
    "addr:full":"63 Av Plante Vanier QC G1M 1R8",
    "addr:postcode":"g1m 1r8",
    "addr:street":"63 Av Plante",
    "iso:country":"CA",
    "sg:address":"63 Av Plante",
    "sg:city":"Vanier",
    "sg:classifiers":[
        {
            "category":"Retail",
            "subcategory":"Car Wash",
            "type":"Services"
        }
    ],
    "sg:phone":"+1 418 688 8936",
    "sg:postcode":"G1M 1R8",
    "sg:province":"QC",
    "sg:tags":[
        "polishing",
        "washing"
    ],
    "wof:name":"Lave-Auto CA Click",
    "wof:placetype":"venue"
},
  "geometry": {"coordinates":[-71.253845,46.81559],"type":"Point"}
}