{
  "type": "Feature",
  "properties": {
    "addr:full":"Airdrie AB T4A 2J2",
    "addr:postcode":"t4a 2j2",
    "iso:country":"CA",
    "sg:city":"Airdrie",
    "sg:classifiers":[
        {
            "category":"Building & Trades",
            "subcategory":"Construction",
            "type":"Services"
        }
    ],
    "sg:phone":"+1 403 948 4363",
    "sg:postcode":"T4A 2J2",
    "sg:province":"AB",
    "sg:tags":[
        "boring",
        "road"
    ],
    "wof:name":"Badger Coring Ltd",
    "wof:placetype":"venue"
},
  "geometry": {"coordinates":[-113.995498657,51.2911148071],"type":"Point"}
}