{
  "type": "Feature",
  "properties": {
    "iso:country":"CA",
    "sg:address":"272 Church St",
    "sg:city":"Pugwash",
    "sg:classifiers":[
        {
            "category":"Health Services",
            "subcategory":"Doctor",
            "type":"Services"
        }
    ],
    "sg:phone":"+1 902 243 3345",
    "sg:postcode":"B0K 1L0",
    "sg:province":"NS",
    "sg:tags":[
        "physician",
        "surgeon"
    ],
    "wof:name":"Northumberland Family Practice",
    "wof:placetype":"venue"
},
  "geometry": {"coordinates":[-63.659362793,45.8555831909],"type":"Point"}
}