{
  "type": "Feature",
  "properties": {
    "addr:full":"870 Av Dessane Quebec QC G1S 3J8",
    "addr:housenumber":"870",
    "addr:postcode":"g1s 3j8",
    "addr:street":"Av Dessane",
    "iso:country":"CA",
    "sg:address":"870 Av Dessane",
    "sg:city":"Quebec",
    "sg:classifiers":[
        {
            "category":"Health Services",
            "subcategory":"Health Practitioner",
            "type":"Services"
        }
    ],
    "sg:phone":"+1 418 688 4771",
    "sg:postcode":"G1S 3J8",
    "sg:province":"QC",
    "sg:tags":[
        "psychologist"
    ],
    "wof:name":"Ruelland, Gerard",
    "wof:placetype":"venue"
},
  "geometry": {"coordinates":[-71.243217,46.797119],"type":"Point"}
}