{
  "type": "Feature",
  "properties": {
    "iso:country":"CA",
    "sg:city":"Kelowna",
    "sg:classifiers":[
        {
            "category":"Retail",
            "subcategory":"Auto Repair",
            "type":"Services"
        }
    ],
    "sg:phone":"+1 250 765 6100",
    "sg:postcode":"V1X 2P9",
    "sg:province":"BC",
    "sg:tags":[
        "repairing",
        "automobile"
    ],
    "wof:name":"E-Z Way Auto",
    "wof:placetype":"venue"
},
  "geometry": {"coordinates":[-119.40583801299999,49.9010658264],"type":"Point"}
}