{
  "type": "Feature",
  "properties": {
    "addr:full":"5016 50th St Provost AB T0B 3S0",
    "addr:housenumber":"5016",
    "addr:postcode":"t0b 3s0",
    "addr:street":"50Th St",
    "iso:country":"CA",
    "sg:address":"5016 50th St",
    "sg:city":"Provost",
    "sg:classifiers":[
        {
            "category":"Wholesale",
            "subcategory":"Scrap",
            "type":"Manufacturing & Wholesale Goods"
        }
    ],
    "sg:phone":"+1 780 753 2030",
    "sg:postcode":"T0B 3S0",
    "sg:province":"AB",
    "sg:tags":[
        "recycling",
        "can",
        "bottle",
        "depot"
    ],
    "wof:name":"Provost Bottle Depot",
    "wof:placetype":"venue"
},
  "geometry": {"coordinates":[-110.264701843,52.3516426086],"type":"Point"}
}