{
  "type": "Feature",
  "properties": {
    "iso:country":"CA",
    "sg:address":"10980 132A St",
    "sg:city":"Surrey",
    "sg:classifiers":[
        {
            "category":"Social Services",
            "type":"Services"
        }
    ],
    "sg:phone":"+1 604 585 9067",
    "sg:postcode":"V3T 3Y4",
    "sg:province":"BC",
    "sg:tags":[
        "organization",
        "welfare"
    ],
    "wof:name":"Act II Society Child & Family",
    "wof:placetype":"venue"
},
  "geometry": {"coordinates":[-122.830215454,49.105178833],"type":"Point"}
}