{
  "type": "Feature",
  "properties": {
    "addr:full":"598 9E Av Beauceville QC G5X 1J1",
    "addr:housenumber":"598",
    "addr:postcode":"g5x 1j1",
    "addr:street":"9E Av",
    "iso:country":"CA",
    "sg:address":"598 9E Av",
    "sg:city":"Beauceville",
    "sg:classifiers":[
        {
            "category":"Building & Trades",
            "subcategory":"Electrical",
            "type":"Services"
        }
    ],
    "sg:phone":"+1 418 774 4105",
    "sg:postcode":"G5X 1J1",
    "sg:province":"QC",
    "sg:tags":[
        "electric",
        "contractor"
    ],
    "wof:name":"Centre Electrique DE Beauce",
    "wof:placetype":"venue"
},
  "geometry": {"coordinates":[-70.77300262449999,46.2092132568],"type":"Point"}
}