{
  "type": "Feature",
  "properties": {
    "iso:country":"CA",
    "sg:address":"2240 Rue Montpetit",
    "sg:city":"Jonquiere",
    "sg:classifiers":[
        {
            "category":"Professional",
            "subcategory":"Management & Consulting",
            "type":"Services"
        }
    ],
    "sg:phone":"+1 418 542 7777",
    "sg:postcode":"G7X 6A3",
    "sg:province":"QC",
    "sg:tags":[
        "development",
        "economic",
        "agency"
    ],
    "wof:name":"Societe D'Intervention Urbain",
    "wof:placetype":"venue"
},
  "geometry": {"coordinates":[-71.252129,48.412678],"type":"Point"}
}