{
  "type": "Feature",
  "properties": {
    "addr:full":"530 Seaview Dr North Sydney NS B2A 3N8",
    "addr:housenumber":"530",
    "addr:postcode":"b2a 3n8",
    "addr:street":"Seaview Dr",
    "iso:country":"CA",
    "sg:address":"530 Seaview Dr",
    "sg:city":"North Sydney",
    "sg:classifiers":[
        {
            "category":"Travel",
            "subcategory":"Hotels & Motels",
            "type":"Entertainment"
        }
    ],
    "sg:phone":"+1 902 794 4530",
    "sg:postcode":"B2A 3N8",
    "sg:province":"NS",
    "wof:name":"Highland Motel",
    "wof:placetype":"venue"
},
  "geometry": {"coordinates":[-60.2514343262,46.2071151733],"type":"Point"}
}