{
  "type": "Feature",
  "properties": {
    "addr:full":"38 Dalseg Dr Morson ON P0W 1J0",
    "addr:housenumber":"38",
    "addr:postcode":"p0w 1j0",
    "addr:street":"Dalseg Dr",
    "iso:country":"CA",
    "sg:address":"38 Dalseg Dr",
    "sg:city":"Morson",
    "sg:classifiers":[
        {
            "category":"Recreation",
            "subcategory":"Marina",
            "type":"Entertainment"
        }
    ],
    "sg:phone":"+1 807 488 5727",
    "sg:postcode":"P0W 1J0",
    "sg:province":"ON",
    "wof:name":"Morson Outboard & Automotive",
    "wof:placetype":"venue"
},
  "geometry": {"coordinates":[-94.32218899999999,49.096176],"type":"Point"}
}