{
  "type": "Feature",
  "properties": {
    "addr:full":"40 Beth Nealson Dr East York ON M4H 1M6",
    "addr:housenumber":"40",
    "addr:postcode":"m4h 1m6",
    "addr:street":"Beth Nealson Dr",
    "iso:country":"CA",
    "sg:address":"40 Beth Nealson Dr",
    "sg:city":"East York",
    "sg:classifiers":[
        {
            "category":"Freight",
            "type":"Transportation"
        }
    ],
    "sg:phone":"+1 416 421 6630",
    "sg:postcode":"M4H 1M6",
    "sg:province":"ON",
    "sg:tags":[
        "commercial",
        "storage"
    ],
    "wof:name":"Security Self Serve Storage",
    "wof:placetype":"venue"
},
  "geometry": {"coordinates":[-79.3456954956,43.7108917236],"type":"Point"}
}