{
  "type": "Feature",
  "properties": {
    "iso:country":"CA",
    "sg:address":"2404 Rue DE LA Province",
    "sg:city":"Longueuil",
    "sg:classifiers":[
        {
            "category":"Wholesale",
            "subcategory":"Electrical",
            "type":"Manufacturing & Wholesale Goods"
        }
    ],
    "sg:phone":"+1 450 928 9372",
    "sg:postcode":"J4G 1G1",
    "sg:province":"QC",
    "sg:tags":[
        "equipment",
        "electric",
        "supply"
    ],
    "wof:name":"Wesco",
    "wof:placetype":"venue"
},
  "geometry": {"coordinates":[-73.462852478,45.5724716187],"type":"Point"}
}