{
  "type": "Feature",
  "properties": {
    "iso:country":"CA",
    "sg:city":"Turner Valley",
    "sg:classifiers":[
        {
            "category":"Organizations",
            "subcategory":"Professional Association",
            "type":"Services"
        }
    ],
    "sg:phone":"+1 403 933 9514",
    "sg:postcode":"T0L 2A0",
    "sg:province":"AB",
    "wof:name":"Army Cadets",
    "wof:placetype":"venue"
},
  "geometry": {"coordinates":[-114.27887725799999,50.6748161316],"type":"Point"}
}