{
  "type": "Feature",
  "properties": {
    "addr:full":"264 High St Moncton NB E1C 6C2",
    "addr:housenumber":"264",
    "addr:postcode":"e1c 6c2",
    "addr:street":"High St",
    "iso:country":"CA",
    "sg:address":"264 High St",
    "sg:city":"Moncton",
    "sg:classifiers":[
        {
            "category":"Retail",
            "subcategory":"Laundry & Dry Cleaning",
            "type":"Services"
        }
    ],
    "sg:phone":"+1 506 857 3107",
    "sg:postcode":"E1C 6C2",
    "sg:province":"NB",
    "sg:tags":[
        "diaper"
    ],
    "wof:name":"N T Enterprises Inc",
    "wof:placetype":"venue"
},
  "geometry": {"coordinates":[-64.792328,46.092419],"type":"Point"}
}