{
  "type": "Feature",
  "properties": {
    "addr:full":"977 Maple St Pincher Creek AB T0K 1W0",
    "addr:housenumber":"977",
    "addr:postcode":"t0k 1w0",
    "addr:street":"Maple St",
    "iso:country":"CA",
    "sg:address":"977 Maple St",
    "sg:city":"Pincher Creek",
    "sg:classifiers":[
        {
            "category":"Organizations",
            "subcategory":"Religious Organization",
            "type":"Services"
        }
    ],
    "sg:phone":"+1 403 627 4755",
    "sg:postcode":"T0K 1W0",
    "sg:province":"AB",
    "sg:tags":[
        "church"
    ],
    "wof:name":"Jehovah's Witnesses Kngdm Hall",
    "wof:placetype":"venue"
},
  "geometry": {"coordinates":[-113.937881,49.48724],"type":"Point"}
}