{
  "type": "Feature",
  "properties": {
    "iso:country":"CA",
    "sg:city":"London",
    "sg:classifiers":[
        {
            "category":"Shopping",
            "subcategory":"Clothing, Apparel, & Fashions",
            "type":"Retail Goods"
        }
    ],
    "sg:phone":"+1 519 850 0379",
    "sg:postcode":"N6G 3Y9",
    "sg:province":"ON",
    "sg:tags":[
        "tailor"
    ],
    "wof:name":"Stitch It Canada's Tailor",
    "wof:placetype":"venue"
},
  "geometry": {"coordinates":[-81.281708,43.025272],"type":"Point"}
}