{
  "type": "Feature",
  "properties": {
    "addr:full":"Kirkton ON N0K 1K0",
    "addr:postcode":"n0k 1k0",
    "addr:street":"Kirkton",
    "iso:country":"CA",
    "sg:city":"Kirkton",
    "sg:classifiers":[
        {
            "category":"Food & Beverages",
            "subcategory":"Groceries & Convenience Stores",
            "type":"Retail Goods"
        }
    ],
    "sg:phone":"+1 519 229 8923",
    "sg:postcode":"N0K 1K0",
    "sg:province":"ON",
    "sg:tags":[
        "grocer"
    ],
    "wof:name":"Kirkton Market",
    "wof:placetype":"venue"
},
  "geometry": {"coordinates":[-81.313858,43.323673],"type":"Point"}
}