{
  "type": "Feature",
  "properties": {
    "addr:full":"Grande Prairie AB T8V 7Z4",
    "addr:postcode":"t8v 7z4",
    "iso:country":"CA",
    "sg:city":"Grande Prairie",
    "sg:classifiers":[
        {
            "category":"Airline",
            "type":"Transportation"
        }
    ],
    "sg:phone":"+1 780 539 3112",
    "sg:postcode":"T8V 7Z4",
    "sg:province":"AB",
    "sg:tags":[
        "helicopter",
        "rental"
    ],
    "wof:name":"Highland Helicopters Ltd",
    "wof:placetype":"venue"
},
  "geometry": {"coordinates":[-118.870918274,55.1814575195],"type":"Point"}
}