{
  "type": "Feature",
  "properties": {
    "addr:full":"423 Tranquille Rd Kamloops BC V2B 3G9",
    "addr:housenumber":"423",
    "addr:postcode":"bc v2b 3g9",
    "addr:street":"Tranquille Rd",
    "iso:country":"CA",
    "sg:address":"423 Tranquille Rd",
    "sg:city":"Kamloops",
    "sg:classifiers":[
        {
            "category":"Retail",
            "subcategory":"Portrait Studio",
            "type":"Services"
        }
    ],
    "sg:phone":"+1 250 376 4715",
    "sg:postcode":"V2B 3G9",
    "sg:province":"BC",
    "sg:tags":[
        "photographic",
        "supply"
    ],
    "wof:name":"Enman's Mr Camera",
    "wof:placetype":"venue"
},
  "geometry": {"coordinates":[-120.358810425,50.690574646],"type":"Point"}
}