{
  "type": "Feature",
  "properties": {
    "iso:country":"CA",
    "sg:address":"53 Parkside Dr",
    "sg:city":"Newmarket",
    "sg:classifiers":[
        {
            "category":"Health Services",
            "subcategory":"Doctor",
            "type":"Services"
        }
    ],
    "sg:phone":"+1 905 898 3819",
    "sg:postcode":"L3Y 4R7",
    "sg:province":"ON",
    "sg:tags":[
        "dentist"
    ],
    "wof:name":"Wong, R DDS",
    "wof:placetype":"venue"
},
  "geometry": {"coordinates":[-79.47229,44.054955],"type":"Point"}
}