{
  "type": "Feature",
  "properties": {
    "iso:country":"CA",
    "sg:address":"22 Pleasant Valley Pl",
    "sg:city":"Brampton",
    "sg:classifiers":[
        {
            "category":"Building & Trades",
            "subcategory":"Construction",
            "type":"Services"
        }
    ],
    "sg:phone":"+1 905 791 7071",
    "sg:postcode":"L6S 5S2",
    "sg:province":"ON",
    "sg:tags":[
        "insulation",
        "heat",
        "contractor"
    ],
    "wof:name":"Misco Insulation CO Ltd",
    "wof:placetype":"venue"
},
  "geometry": {"coordinates":[-79.736298,43.741447],"type":"Point"}
}