{
  "type": "Feature",
  "properties": {
    "addr:full":"158 Wharncliffe Rd S London ON N6J 2K6",
    "addr:housenumber":"158",
    "addr:postcode":"n6j 2k6",
    "addr:street":"Wharncliffe Rd",
    "iso:country":"CA",
    "sg:address":"158 Wharncliffe Rd S",
    "sg:city":"London",
    "sg:classifiers":[
        {
            "category":"Restaurant",
            "type":"Food & Drink"
        }
    ],
    "sg:phone":"+1 519 438 9641",
    "sg:postcode":"N6J 2K6",
    "sg:province":"ON",
    "wof:name":"Harvey's",
    "wof:placetype":"venue"
},
  "geometry": {"coordinates":[-81.26177199999999,42.972321],"type":"Point"}
}