{
  "type": "Feature",
  "properties": {
    "addr:full":"16 Ferry Wharf Rd Grand Manan NB E5G 3A2",
    "addr:housenumber":"16",
    "addr:postcode":"e5g 3a2",
    "addr:street":"Ferry Wharf Rd",
    "iso:country":"CA",
    "sg:address":"16 Ferry Wharf Rd",
    "sg:city":"Grand Manan",
    "sg:classifiers":[
        {
            "category":"Wholesale",
            "subcategory":"Seafood",
            "type":"Manufacturing & Wholesale Goods"
        }
    ],
    "sg:phone":"+1 506 662 8431",
    "sg:postcode":"E5G 3A2",
    "sg:province":"NB",
    "wof:name":"Special K Fisheries Ltd",
    "wof:placetype":"venue"
},
  "geometry": {"coordinates":[-66.79814910890001,44.675453186],"type":"Point"}
}