{
  "type": "Feature",
  "properties": {
    "iso:country":"CA",
    "sg:city":"Montreal",
    "sg:classifiers":[
        {
            "category":"Professional",
            "subcategory":"Research",
            "type":"Services"
        }
    ],
    "sg:phone":"+1 514 848 9640",
    "sg:postcode":"H2W 1Y5",
    "sg:province":"QC",
    "sg:tags":[
        "development",
        "laboratory"
    ],
    "wof:name":"Xiphos Technologies Inc",
    "wof:placetype":"venue"
},
  "geometry": {"coordinates":[-73.5784835815,45.5167045593],"type":"Point"}
}