{
  "type": "Feature",
  "properties": {
    "iso:country":"CA",
    "sg:address":"574 Brant St",
    "sg:city":"Burlington",
    "sg:classifiers":[
        {
            "category":"Insurance",
            "subcategory":"Insurance Agent",
            "type":"Services"
        }
    ],
    "sg:phone":"+1 905 632 2305",
    "sg:postcode":"L7R 2G8",
    "sg:province":"ON",
    "wof:name":"David H Coons Insurance Brkrs",
    "wof:placetype":"venue"
},
  "geometry": {"coordinates":[-79.802773,43.328938],"type":"Point"}
}