{
  "type": "Feature",
  "properties": {
    "iso:country":"CA",
    "sg:address":"1560 Regent Ave W",
    "sg:city":"Winnipeg",
    "sg:classifiers":[
        {
            "category":"Shopping",
            "subcategory":"Department Store",
            "type":"Retail Goods"
        }
    ],
    "sg:phone":"+1 204 661 9045",
    "sg:postcode":"R2C 3B4",
    "sg:province":"MB",
    "sg:tags":[
        "shop",
        "second",
        "hand"
    ],
    "wof:name":"Value Village Stores Ltd",
    "wof:placetype":"venue"
},
  "geometry": {"coordinates":[-97.061707,49.896824],"type":"Point"}
}