{
  "type": "Feature",
  "properties": {
    "addr:full":"2815 Yale St Vancouver BC V5K 1C5",
    "addr:housenumber":"2815",
    "addr:postcode":"v5k 1c5",
    "addr:street":"Yale St",
    "iso:country":"CA",
    "sg:address":"2815 Yale St",
    "sg:city":"Vancouver",
    "sg:classifiers":[
        {
            "category":"Professional",
            "subcategory":"Management & Consulting",
            "type":"Services"
        }
    ],
    "sg:phone":"+1 604 732 4010",
    "sg:postcode":"V5K 1C5",
    "sg:province":"BC",
    "sg:tags":[
        "consultant",
        "business"
    ],
    "wof:name":"Vanry & Assoc",
    "wof:placetype":"venue"
},
  "geometry": {"coordinates":[-123.04631000000001,49.290836],"type":"Point"}
}