{
  "type": "Feature",
  "properties": {
    "addr:full":"2165 Shetland Rd Campbell River BC V9W 3Y5",
    "addr:housenumber":"2165",
    "addr:postcode":"v9w 3y5",
    "addr:street":"Shetland Rd",
    "iso:country":"CA",
    "sg:address":"2165 Shetland Rd",
    "sg:city":"Campbell River",
    "sg:classifiers":[
        {
            "category":"Manufacturing",
            "subcategory":"Glass & Minerals",
            "type":"Manufacturing & Wholesale Goods"
        }
    ],
    "sg:phone":"+1 250 287 4006",
    "sg:postcode":"V9W 3Y5",
    "sg:province":"BC",
    "sg:tags":[
        "concrete",
        "brick",
        "prod",
        "block"
    ],
    "wof:name":"Campbell River Precast Inc",
    "wof:placetype":"venue"
},
  "geometry": {"coordinates":[-125.277519,50.017609],"type":"Point"}
}