{
  "type": "Feature",
  "properties": {
    "iso:country":"CA",
    "sg:address":"10885 Av Moisan",
    "sg:city":"Montreal-Nord",
    "sg:classifiers":[
        {
            "category":"Home & Garden",
            "subcategory":"Building Materials",
            "type":"Retail Goods"
        }
    ],
    "sg:phone":"+1 514 322 6784",
    "sg:postcode":"H1G 4N6",
    "sg:province":"QC",
    "sg:tags":[
        "glass",
        "window",
        "plate"
    ],
    "wof:name":"Opti-Teinte Plus Enr",
    "wof:placetype":"venue"
},
  "geometry": {"coordinates":[-73.61669921879999,45.602104187],"type":"Point"}
}