{
  "type": "Feature",
  "properties": {
    "addr:full":"101 Rue Maclaren E Buckingham QC J8L 1J9",
    "addr:housenumber":"101",
    "addr:postcode":"j8l 1j9",
    "addr:street":"Rue Maclaren E",
    "iso:country":"CA",
    "sg:address":"101 Rue Maclaren E",
    "sg:city":"Buckingham",
    "sg:classifiers":[
        {
            "category":"Government",
            "subcategory":"Office",
            "type":"Public Place"
        }
    ],
    "sg:phone":"+1 819 986 3383",
    "sg:postcode":"J8L 1J9",
    "sg:province":"QC",
    "wof:name":"Canada Centre DE Ressources",
    "wof:placetype":"venue"
},
  "geometry": {"coordinates":[-75.41669464109999,45.5866546631],"type":"Point"}
}