{
  "type": "Feature",
  "properties": {
    "iso:country":"CA",
    "sg:address":"277 City Centre",
    "sg:city":"Kitimat",
    "sg:classifiers":[
        {
            "category":"Professional",
            "subcategory":"Accounting & Tax Preparation",
            "type":"Services"
        }
    ],
    "sg:phone":"+1 250 632 6137",
    "sg:postcode":"V8C 1T6",
    "sg:province":"BC",
    "sg:tags":[
        "accountant"
    ],
    "wof:name":"Adp Computer Svc Ltd",
    "wof:placetype":"venue"
},
  "geometry": {"coordinates":[-128.65553283700001,54.0531158447],"type":"Point"}
}