{
  "type": "Feature",
  "properties": {
    "addr:full":"125 Stewart Blvd Brockville ON K6V 4W4",
    "addr:housenumber":"125",
    "addr:postcode":"k6v 4w4",
    "addr:street":"Stewart Blvd",
    "iso:country":"CA",
    "sg:address":"125 Stewart Blvd",
    "sg:city":"Brockville",
    "sg:classifiers":[
        {
            "category":"Cinema",
            "subcategory":"Movie Rental",
            "type":"Entertainment"
        }
    ],
    "sg:phone":"+1 613 345 8433",
    "sg:postcode":"K6V 4W4",
    "sg:province":"ON",
    "sg:tags":[
        "leasing",
        "video",
        "disc",
        "tape"
    ],
    "wof:name":"Jumbo Video",
    "wof:placetype":"venue"
},
  "geometry": {"coordinates":[-75.69795999999999,44.598503],"type":"Point"}
}