{
  "type": "Feature",
  "properties": {
    "addr:full":"330 Byron St S Whitby ON L1N 4P8",
    "addr:housenumber":"330",
    "addr:postcode":"l1n 4p8",
    "addr:street":"Byron St S",
    "iso:country":"CA",
    "sg:address":"330 Byron St S",
    "sg:city":"Whitby",
    "sg:classifiers":[
        {
            "category":"Professional",
            "subcategory":"Accounting & Tax Preparation",
            "type":"Services"
        }
    ],
    "sg:phone":"+1 905 666 4510",
    "sg:postcode":"L1N 4P8",
    "sg:province":"ON",
    "sg:tags":[
        "accountant"
    ],
    "wof:name":"Van Dusen & Van Dusen",
    "wof:placetype":"venue"
},
  "geometry": {"coordinates":[-78.94259643549999,43.8770713806],"type":"Point"}
}