{
  "type": "Feature",
  "properties": {
    "addr:full":"545 Irishtown Rd Kensington PE C0B 1M0",
    "addr:housenumber":"545",
    "addr:postcode":"c0b 1m0",
    "addr:street":"Irishtown Rd",
    "iso:country":"CA",
    "sg:address":"545 Irishtown Rd",
    "sg:city":"Kensington",
    "sg:classifiers":[
        {
            "category":"Freight",
            "type":"Transportation"
        }
    ],
    "sg:phone":"+1 902 836 3703",
    "sg:postcode":"C0B 1M0",
    "sg:province":"PE",
    "sg:tags":[
        "trucking"
    ],
    "wof:name":"Four Seasons Transport",
    "wof:placetype":"venue"
},
  "geometry": {"coordinates":[-63.636848,46.436882],"type":"Point"}
}