{
  "type": "Feature",
  "properties": {
    "addr:full":"121 Oakdale Ave St Catharines ON L2P 2L3",
    "addr:housenumber":"121",
    "addr:postcode":"l2p 2l3",
    "addr:street":"Oakdale Ave",
    "iso:country":"CA",
    "sg:address":"121 Oakdale Ave",
    "sg:city":"St Catharines",
    "sg:classifiers":[
        {
            "category":"Health Services",
            "subcategory":"Doctor",
            "type":"Services"
        }
    ],
    "sg:phone":"+1 905 685 8700",
    "sg:postcode":"L2P 2L3",
    "sg:province":"ON",
    "sg:tags":[
        "physician",
        "surgeon"
    ],
    "wof:name":"Harb, Raymond T MD",
    "wof:placetype":"venue"
},
  "geometry": {"coordinates":[-79.2201,43.146194],"type":"Point"}
}