{
  "type": "Feature",
  "properties": {
    "addr:full":"237 Parkdale Ave N Hamilton ON L8H 5X4",
    "addr:housenumber":"237",
    "addr:postcode":"l8h 5x4",
    "addr:street":"Parkdale Ave N",
    "iso:country":"CA",
    "sg:address":"237 Parkdale Ave N",
    "sg:city":"Hamilton",
    "sg:classifiers":[
        {
            "category":"Restaurant",
            "type":"Food & Drink"
        }
    ],
    "sg:phone":"+1 905 545 5531",
    "sg:postcode":"L8H 5X4",
    "sg:province":"ON",
    "sg:tags":[
        "sandwich"
    ],
    "wof:name":"Mr Sub",
    "wof:placetype":"venue"
},
  "geometry": {"coordinates":[-79.789253,43.243217],"type":"Point"}
}