{
  "type": "Feature",
  "properties": {
    "addr:full":"Edson AB T7E 1T7",
    "addr:postcode":"t7e 1t7",
    "iso:country":"CA",
    "sg:city":"Edson",
    "sg:classifiers":[
        {
            "category":"Shopping",
            "subcategory":"Clothing, Apparel, & Fashions",
            "type":"Retail Goods"
        }
    ],
    "sg:phone":"+1 780 723 6677",
    "sg:postcode":"T7E 1T7",
    "sg:province":"AB",
    "sg:tags":[
        "furnishing"
    ],
    "wof:name":"Jensen's Lifestyle Clothing",
    "wof:placetype":"venue"
},
  "geometry": {"coordinates":[-116.43167099999999,53.58247],"type":"Point"}
}