{
  "type": "Feature",
  "properties": {
    "addr:full":"96 Durham St Sudbury ON P3E 3M6",
    "addr:housenumber":"96",
    "addr:postcode":"p3e 3m6",
    "addr:street":"Durham St",
    "iso:country":"CA",
    "sg:address":"96 Durham St",
    "sg:city":"Sudbury",
    "sg:classifiers":[
        {
            "category":"Food & Beverages",
            "subcategory":"Groceries & Convenience Stores",
            "type":"Retail Goods"
        }
    ],
    "sg:phone":"+1 705 673 6717",
    "sg:postcode":"P3E 3M6",
    "sg:province":"ON",
    "wof:name":"Black Cat One",
    "wof:placetype":"venue"
},
  "geometry": {"coordinates":[-80.99490400000001,46.491516],"type":"Point"}
}