{
  "type": "Feature",
  "properties": {
    "addr:full":"20 Prince Arthur Ave Toronto ON M5R 1B1",
    "addr:housenumber":"20",
    "addr:postcode":"m5r 1b1",
    "addr:street":"Prince Arthur Ave",
    "iso:country":"CA",
    "sg:address":"20 Prince Arthur Ave",
    "sg:city":"Toronto",
    "sg:classifiers":[
        {
            "category":"Social Services",
            "type":"Services"
        }
    ],
    "sg:phone":"+1 416 515 2055",
    "sg:postcode":"M5R 1B1",
    "sg:province":"ON",
    "sg:tags":[
        "counselor",
        "marriage",
        "family"
    ],
    "wof:name":"Philipp, Eva",
    "wof:placetype":"venue"
},
  "geometry": {"coordinates":[-79.3960266113,43.6697616577],"type":"Point"}
}