{
  "type": "Feature",
  "properties": {
    "iso:country":"CA",
    "sg:address":"5103 51 St #101",
    "sg:city":"Yellowknife",
    "sg:classifiers":[
        {
            "category":"Autos & Motor Vehicles",
            "subcategory":"Boat Sales",
            "type":"Retail Goods"
        }
    ],
    "sg:phone":"+1 867 873 6443",
    "sg:postcode":"X1A 1S8",
    "sg:province":"NT",
    "sg:tags":[
        "dealer",
        "canoe"
    ],
    "wof:name":"Narwal Paddling Adventures",
    "wof:placetype":"venue"
},
  "geometry": {"coordinates":[-114.36962127699999,62.452129364],"type":"Point"}
}