{
  "type": "Feature",
  "properties": {
    "addr:full":"Cobourg ON K9A 4K8",
    "addr:postcode":"k9a 4k8",
    "iso:country":"CA",
    "sg:city":"Cobourg",
    "sg:classifiers":[
        {
            "category":"Manufacturing",
            "subcategory":"Tools & Machinery",
            "type":"Manufacturing & Wholesale Goods"
        }
    ],
    "sg:phone":"+1 905 372 4371",
    "sg:postcode":"K9A 4K8",
    "sg:province":"ON",
    "sg:tags":[
        "system",
        "automation"
    ],
    "wof:name":"Amara CO",
    "wof:placetype":"venue"
},
  "geometry": {"coordinates":[-78.13542200000001,43.965652],"type":"Point"}
}