{
  "type": "Feature",
  "properties": {
    "addr:full":"Sandy Lake ON P0V 1V0",
    "addr:postcode":"p0v 1v0",
    "iso:country":"CA",
    "sg:city":"Sandy Lake",
    "sg:classifiers":[
        {
            "category":"Organizations",
            "subcategory":"Professional Association",
            "type":"Services"
        }
    ],
    "sg:phone":"+1 807 771 1080",
    "sg:postcode":"P0V 1V0",
    "sg:province":"ON",
    "sg:tags":[
        "government"
    ],
    "wof:name":"Keewaywin Education Authority",
    "wof:placetype":"venue"
},
  "geometry": {"coordinates":[-93.3333282471,53.0502204895],"type":"Point"}
}