{
  "type": "Feature",
  "properties": {
    "addr:full":"390 Rue Saint-Jacques Montreal QC H2Y 1S1",
    "addr:housenumber":"390",
    "addr:postcode":"h2y 1s1",
    "addr:street":"Rue Saint-Jacques",
    "iso:country":"CA",
    "sg:address":"390 Rue Saint-Jacques",
    "sg:city":"Montreal",
    "sg:classifiers":[
        {
            "category":"Shopping",
            "subcategory":"Gifts & Souvenirs",
            "type":"Retail Goods"
        }
    ],
    "sg:phone":"+1 514 844 2549",
    "sg:postcode":"H2Y 1S1",
    "sg:province":"QC",
    "sg:tags":[
        "platinum",
        "collectible",
        "silver",
        "gold"
    ],
    "wof:name":"Mint Master Numismatiques Inc",
    "wof:placetype":"venue"
},
  "geometry": {"coordinates":[-73.559669,45.501961],"type":"Point"}
}