{
  "type": "Feature",
  "properties": {
    "addr:full":"Richmond BC V7C 4R9",
    "addr:postcode":"v7c 4r9",
    "iso:country":"CA",
    "sg:city":"Richmond",
    "sg:classifiers":[
        {
            "category":"Wholesale",
            "subcategory":"Furniture",
            "type":"Manufacturing & Wholesale Goods"
        }
    ],
    "sg:phone":"+1 604 273 2988",
    "sg:postcode":"V7C 4R9",
    "sg:province":"BC",
    "wof:name":"DE Stijl Furniture Ltd",
    "wof:placetype":"venue"
},
  "geometry": {"coordinates":[-123.158455,49.17049],"type":"Point"}
}