{
  "type": "Feature",
  "properties": {
    "addr:full":"1405 Rue Joliot-Curie Boucherville QC J4B 7M4",
    "addr:housenumber":"1405",
    "addr:postcode":"j4b 7m4",
    "addr:street":"Rue Joliot-Curie",
    "iso:country":"CA",
    "sg:address":"1405 Rue Joliot-Curie",
    "sg:city":"Boucherville",
    "sg:classifiers":[
        {
            "category":"Building & Trades",
            "subcategory":"Construction",
            "type":"Services"
        }
    ],
    "sg:phone":"+1 450 655 2002",
    "sg:postcode":"J4B 7M4",
    "sg:province":"QC",
    "sg:tags":[
        "general",
        "contractor"
    ],
    "wof:name":"Constructions Pier-Jal Inc",
    "wof:placetype":"venue"
},
  "geometry": {"coordinates":[-73.43444824220001,45.557849884],"type":"Point"}
}