{
  "type": "Feature",
  "properties": {
    "iso:country":"CA",
    "sg:address":"475 Rue Papineau",
    "sg:city":"Sherbrooke",
    "sg:classifiers":[
        {
            "category":"Retail",
            "subcategory":"Repair Shop",
            "type":"Services"
        }
    ],
    "sg:phone":"+1 819 346 6274",
    "sg:postcode":"J1E 1X7",
    "sg:province":"QC",
    "sg:tags":[
        "upholsterer"
    ],
    "wof:name":"Rembourreur Lacroix",
    "wof:placetype":"venue"
},
  "geometry": {"coordinates":[-71.878616333,45.4091262817],"type":"Point"}
}