{
  "type": "Feature",
  "properties": {
    "iso:country":"CA",
    "sg:address":"940 Boul Saint-Jean",
    "sg:city":"Pointe-Claire",
    "sg:classifiers":[
        {
            "category":"Restaurant",
            "type":"Food & Drink"
        }
    ],
    "sg:phone":"+1 514 630 0123",
    "sg:postcode":"H9R 5N8",
    "sg:province":"QC",
    "wof:name":"Soho Sushi Lounge Fine Cuisine",
    "wof:placetype":"venue"
},
  "geometry": {"coordinates":[-73.83037567140001,45.4683914185],"type":"Point"}
}