{
  "type": "Feature",
  "properties": {
    "iso:country":"CA",
    "sg:address":"737 Jones St",
    "sg:city":"Qualicum Beach",
    "sg:classifiers":[
        {
            "category":"Recreation",
            "type":"Entertainment"
        }
    ],
    "sg:phone":"+1 250 752 5014",
    "sg:postcode":"V9K 1S4",
    "sg:province":"BC",
    "sg:tags":[
        "pool",
        "swimming"
    ],
    "wof:name":"Ravensong Aquatic Ctr",
    "wof:placetype":"venue"
},
  "geometry": {"coordinates":[-124.449386597,49.3463821411],"type":"Point"}
}