{
  "type": "Feature",
  "properties": {
    "addr:full":"4837 51st Ave Chetwynd BC V0C 1J0",
    "addr:housenumber":"4837",
    "addr:postcode":"bc v0c 1j0",
    "addr:street":"51St Ave",
    "iso:country":"CA",
    "sg:address":"4837 51st Ave",
    "sg:city":"Chetwynd",
    "sg:classifiers":[
        {
            "category":"Utilities",
            "subcategory":"Mobile Phone",
            "type":"Services"
        }
    ],
    "sg:phone":"+1 250 788 3271",
    "sg:postcode":"V0C 1J0",
    "sg:province":"BC",
    "sg:tags":[
        "telephone",
        "cellular"
    ],
    "wof:name":"Cardinal Telecom Inc",
    "wof:placetype":"venue"
},
  "geometry": {"coordinates":[-121.622108,55.695812],"type":"Point"}
}