{
  "type": "Feature",
  "properties": {
    "addr:full":"350 Rue Dubois Grande-Ile QC J6S 1A2",
    "addr:housenumber":"350",
    "addr:postcode":"j6s 1a2",
    "addr:street":"Rue Dubois Grande-Ile",
    "iso:country":"CA",
    "sg:address":"350 Rue Dubois",
    "sg:city":"Grande-Ile",
    "sg:classifiers":[
        {
            "category":"Wholesale",
            "subcategory":"Auto Parts",
            "type":"Manufacturing & Wholesale Goods"
        }
    ],
    "sg:phone":"+1 450 373 9607",
    "sg:postcode":"J6S 1A2",
    "sg:province":"QC",
    "sg:tags":[
        "automobile",
        "rebuilt"
    ],
    "wof:name":"R Jodin & Fils Inc",
    "wof:placetype":"venue"
},
  "geometry": {"coordinates":[-74.145241,45.276981],"type":"Point"}
}