{
  "type": "Feature",
  "properties": {
    "addr:full":"Exeter ON N0M 1S3",
    "addr:postcode":"n0m 1s3",
    "iso:country":"CA",
    "sg:city":"Exeter",
    "sg:classifiers":[
        {
            "category":"Shopping",
            "subcategory":"Used Merchandise",
            "type":"Retail Goods"
        }
    ],
    "sg:phone":"+1 519 235 3744",
    "sg:postcode":"N0M 1S3",
    "sg:province":"ON",
    "sg:tags":[
        "second",
        "store",
        "hand"
    ],
    "wof:name":"Ept Noahs Ark",
    "wof:placetype":"venue"
},
  "geometry": {"coordinates":[-81.48369599999999,43.363518],"type":"Point"}
}