{
  "type": "Feature",
  "properties": {
    "addr:full":"120 Berkeley St Toronto ON M5A 2W9",
    "addr:housenumber":"120",
    "addr:postcode":"m5a 2w9",
    "addr:street":"Berkeley St",
    "iso:country":"CA",
    "sg:address":"120 Berkeley St",
    "sg:city":"Toronto",
    "sg:classifiers":[
        {
            "category":"Communications",
            "subcategory":"Film & Video Production",
            "type":"Services"
        }
    ],
    "sg:phone":"+1 416 861 0455",
    "sg:postcode":"M5A 2W9",
    "sg:province":"ON",
    "sg:tags":[
        "taping"
    ],
    "wof:name":"H 2 Media Inc",
    "wof:placetype":"venue"
},
  "geometry": {"coordinates":[-79.365585,43.65448],"type":"Point"}
}