{
  "type": "Feature",
  "properties": {
    "addr:full":"314 Main St Port Dover ON N0A 1N0",
    "addr:housenumber":"314",
    "addr:postcode":"n0a 1n0",
    "addr:street":"Main St",
    "iso:country":"CA",
    "sg:address":"314 Main St",
    "sg:city":"Port Dover",
    "sg:classifiers":[
        {
            "category":"Home & Garden",
            "subcategory":"Hardware",
            "type":"Retail Goods"
        }
    ],
    "sg:phone":"+1 519 583 0730",
    "sg:postcode":"N0A 1N0",
    "sg:province":"ON",
    "wof:name":"Stoney's Home Hardware Ltd",
    "wof:placetype":"venue"
},
  "geometry": {"coordinates":[-80.2038803101,42.7870941162],"type":"Point"}
}