{
  "type": "Feature",
  "properties": {
    "addr:full":"4372 Steeles Ave E Markham ON L3R 9V6",
    "addr:housenumber":"4372",
    "addr:postcode":"l3r 9v6",
    "addr:street":"Steeles Ave E",
    "iso:country":"CA",
    "sg:address":"4372 Steeles Ave E",
    "sg:city":"Markham",
    "sg:classifiers":[
        {
            "category":"Restaurant",
            "type":"Food & Drink"
        }
    ],
    "sg:phone":"+1 905 305 8877",
    "sg:postcode":"L3R 9V6",
    "sg:province":"ON",
    "wof:name":"City Hollywood Cafe",
    "wof:placetype":"venue"
},
  "geometry": {"coordinates":[-79.3046417236,43.8243637085],"type":"Point"}
}