{
  "type": "Feature",
  "properties": {
    "iso:country":"CA",
    "sg:address":"148 Niagara St",
    "sg:city":"St Catharines",
    "sg:classifiers":[
        {
            "category":"Banks & Credit Unions",
            "subcategory":"Investment Brokerage",
            "type":"Services"
        }
    ],
    "sg:phone":"+1 905 988 3562",
    "sg:postcode":"L2R 4L4",
    "sg:province":"ON",
    "wof:name":"Credential Securities",
    "wof:placetype":"venue"
},
  "geometry": {"coordinates":[-79.2338562012,43.1704216003],"type":"Point"}
}