{
  "type": "Feature",
  "properties": {
    "iso:country":"CA",
    "sg:address":"531 Boul Rosemont",
    "sg:city":"Montreal",
    "sg:classifiers":[
        {
            "category":"Personal",
            "type":"Services"
        }
    ],
    "sg:phone":"+1 514 279 7069",
    "sg:postcode":"H2S 1Z4",
    "sg:province":"QC",
    "sg:tags":[
        "salon",
        "treatment",
        "beauty",
        "scalp"
    ],
    "wof:name":"Salon Des Caraibes",
    "wof:placetype":"venue"
},
  "geometry": {"coordinates":[-73.597824,45.532013],"type":"Point"}
}