{
  "type": "Feature",
  "properties": {
    "addr:full":"3930 Rue Saint-Hubert Montreal QC H2L 4A5",
    "addr:housenumber":"3930",
    "addr:postcode":"h2l 4a5",
    "addr:street":"Rue Saint-Hubert",
    "iso:country":"CA",
    "sg:address":"3930 Rue Saint-Hubert",
    "sg:city":"Montreal",
    "sg:classifiers":[
        {
            "category":"Building & Trades",
            "subcategory":"Plumbing",
            "type":"Services"
        }
    ],
    "sg:phone":"+1 514 891 2848",
    "sg:postcode":"H2L 4A5",
    "sg:province":"QC",
    "sg:tags":[
        "heating",
        "contractor"
    ],
    "wof:name":"Gaz Naturel Region Ctr Inc",
    "wof:placetype":"venue"
},
  "geometry": {"coordinates":[-73.5728225708,45.5216941833],"type":"Point"}
}