{
  "type": "Feature",
  "properties": {
    "addr:full":"1960 Springfield Rd # 7 Kelowna BC V1Y 5V7",
    "addr:housenumber":"1960",
    "addr:postcode":"v1y 5v7",
    "addr:street":"Springfield Rd # 7",
    "iso:country":"CA",
    "sg:address":"1960 Springfield Rd # 7",
    "sg:city":"Kelowna",
    "sg:classifiers":[
        {
            "category":"Wholesale",
            "subcategory":"Medical Equipment & Supplies",
            "type":"Manufacturing & Wholesale Goods"
        }
    ],
    "sg:phone":"+1 250 860 7331",
    "sg:postcode":"V1Y 5V7",
    "sg:province":"BC",
    "sg:tags":[
        "physician",
        "surgeon"
    ],
    "wof:name":"Creative Mobility Products Inc",
    "wof:placetype":"venue"
},
  "geometry": {"coordinates":[-119.452141,49.877449],"type":"Point"}
}