{
  "type": "Feature",
  "properties": {
    "addr:full":"Mississauga ON L5C 4P4",
    "addr:postcode":"l5c 4p4",
    "iso:country":"CA",
    "sg:city":"Mississauga",
    "sg:classifiers":[
        {
            "category":"Insurance",
            "subcategory":"Insurance Agent",
            "type":"Services"
        }
    ],
    "sg:phone":"+1 905 615 8641",
    "sg:postcode":"L5C 4P4",
    "sg:province":"ON",
    "wof:name":"C G & B Group",
    "wof:placetype":"venue"
},
  "geometry": {"coordinates":[-79.660949707,43.5668182373],"type":"Point"}
}