{
  "type": "Feature",
  "properties": {
    "addr:full":"447 Rte LA Vallee Memramcook NB E4K 3C6",
    "addr:housenumber":"447",
    "addr:postcode":"e4k 3c6",
    "addr:street":"Rte La Vallee",
    "iso:country":"CA",
    "sg:address":"447 Rte LA Vallee",
    "sg:city":"Memramcook",
    "sg:classifiers":[
        {
            "category":"Retail",
            "subcategory":"Auto Repair",
            "type":"Services"
        }
    ],
    "sg:phone":"+1 506 758 9842",
    "sg:postcode":"E4K 3C6",
    "sg:province":"NB",
    "sg:tags":[
        "repairing",
        "automobile"
    ],
    "wof:name":"Irac",
    "wof:placetype":"venue"
},
  "geometry": {"coordinates":[-64.59858699999999,46.010422],"type":"Point"}
}