{
  "type": "Feature",
  "properties": {
    "addr:full":"6 Industry Ave Yarmouth NS B5A 4B2",
    "addr:housenumber":"6",
    "addr:postcode":"b5a 4b2",
    "addr:street":"Industry Ave",
    "iso:country":"CA",
    "sg:address":"6 Industry Ave",
    "sg:city":"Yarmouth",
    "sg:classifiers":[
        {
            "category":"Wholesale",
            "subcategory":"Electrical",
            "type":"Manufacturing & Wholesale Goods"
        }
    ],
    "sg:phone":"+1 902 742 6771",
    "sg:postcode":"B5A 4B2",
    "sg:province":"NS",
    "sg:tags":[
        "equipment",
        "electric",
        "supply"
    ],
    "wof:name":"Harris & Roome Supply Ltd",
    "wof:placetype":"venue"
},
  "geometry": {"coordinates":[-66.095917,43.831566],"type":"Point"}
}