{
  "type": "Feature",
  "properties": {
    "addr:full":"9916 72 Ave NW Edmonton AB T6E 0Z3",
    "addr:housenumber":"9916",
    "addr:postcode":"t6e 0z3",
    "addr:street":"72 Ave Nw",
    "iso:country":"CA",
    "sg:address":"9916 72 Ave NW",
    "sg:city":"Edmonton",
    "sg:classifiers":[
        {
            "category":"Autos & Motor Vehicles",
            "subcategory":"Auto Supplies",
            "type":"Retail Goods"
        }
    ],
    "sg:phone":"+1 780 438 7292",
    "sg:postcode":"T6E 0Z3",
    "sg:province":"AB",
    "sg:tags":[
        "repairing",
        "automobile",
        "parts"
    ],
    "wof:name":"Toytech Auto Ltd",
    "wof:placetype":"venue"
},
  "geometry": {"coordinates":[-113.48684692400001,53.5087547302],"type":"Point"}
}