{
  "type": "Feature",
  "properties": {
    "addr:full":"Vancouver BC V6H 1A6",
    "addr:postcode":"v6h 1a6",
    "iso:country":"CA",
    "sg:city":"Vancouver",
    "sg:classifiers":[
        {
            "category":"Manufacturing",
            "subcategory":"Printing",
            "type":"Manufacturing & Wholesale Goods"
        }
    ],
    "sg:phone":"+1 604 732 6397",
    "sg:postcode":"V6H 1A6",
    "sg:province":"BC",
    "sg:tags":[
        "newspaper"
    ],
    "wof:name":"Youthlink Publishing Inc",
    "wof:placetype":"venue"
},
  "geometry": {"coordinates":[-123.133056641,49.2663269043],"type":"Point"}
}