{
  "type": "Feature",
  "properties": {
    "addr:full":"2438 Glengarry Rd Mississauga ON L5C 1Y2",
    "addr:housenumber":"2438",
    "addr:postcode":"l5c 1y2",
    "addr:street":"Glengarry Rd",
    "iso:country":"CA",
    "sg:address":"2438 Glengarry Rd",
    "sg:city":"Mississauga",
    "sg:classifiers":[
        {
            "category":"Organizations",
            "subcategory":"Religious Organization",
            "type":"Services"
        }
    ],
    "sg:phone":"+1 905 277 1130",
    "sg:postcode":"L5C 1Y2",
    "sg:province":"ON",
    "sg:tags":[
        "church"
    ],
    "wof:name":"Ebenezer Reformed Church",
    "wof:placetype":"venue"
},
  "geometry": {"coordinates":[-79.6375045776,43.5534667969],"type":"Point"}
}