{
  "type": "Feature",
  "properties": {
    "addr:full":"2746 Camcrest Dr Nanaimo BC V9T 4W4",
    "addr:housenumber":"2746",
    "addr:postcode":"v9t 4w4",
    "addr:street":"Camcrest Dr",
    "iso:country":"CA",
    "sg:address":"2746 Camcrest Dr",
    "sg:city":"Nanaimo",
    "sg:classifiers":[
        {
            "category":"Wholesale",
            "subcategory":"Construction Materials",
            "type":"Manufacturing & Wholesale Goods"
        }
    ],
    "sg:phone":"+1 250 756 1134",
    "sg:postcode":"V9T 4W4",
    "sg:province":"BC",
    "sg:tags":[
        "concrete",
        "form"
    ],
    "wof:name":"Harbour West Steel Contractors",
    "wof:placetype":"venue"
},
  "geometry": {"coordinates":[-124.025245666,49.199634552],"type":"Point"}
}