{
  "type": "Feature",
  "properties": {
    "addr:full":"Trois-Rivieres-Ouest QC G8Y 4R9",
    "addr:postcode":"g8y 4r9",
    "iso:country":"CA",
    "sg:city":"Trois-Rivieres-Ouest",
    "sg:classifiers":[
        {
            "category":"Shopping",
            "subcategory":"Bicycles & Sporting Goods",
            "type":"Retail Goods"
        }
    ],
    "sg:phone":"+1 819 370 1537",
    "sg:postcode":"G8Y 4R9",
    "sg:province":"QC",
    "sg:tags":[
        "collectible"
    ],
    "wof:name":"Carte Etoile",
    "wof:placetype":"venue"
},
  "geometry": {"coordinates":[-72.59326934809999,46.3322525024],"type":"Point"}
}