{
  "type": "Feature",
  "properties": {
    "addr:full":"Mount Albert ON L0G 1M0",
    "addr:postcode":"l0g 1m0",
    "iso:country":"CA",
    "sg:city":"Mount Albert",
    "sg:classifiers":[
        {
            "category":"Personal",
            "subcategory":"Beauty Salon",
            "type":"Services"
        }
    ],
    "sg:phone":"+1 905 473 3912",
    "sg:postcode":"L0G 1M0",
    "sg:province":"ON",
    "wof:name":"Mainshop Salon",
    "wof:placetype":"venue"
},
  "geometry": {"coordinates":[-79.308525,44.136246],"type":"Point"}
}