{
  "type": "Feature",
  "properties": {
    "addr:full":"551 Clair Rd W Guelph ON N1L 1E9",
    "addr:housenumber":"551",
    "addr:postcode":"n1l 1e9",
    "addr:street":"Clair Rd W",
    "iso:country":"CA",
    "sg:address":"551 Clair Rd W",
    "sg:city":"Guelph",
    "sg:classifiers":[
        {
            "category":"Manufacturing",
            "subcategory":"Food",
            "type":"Manufacturing & Wholesale Goods"
        }
    ],
    "sg:phone":"+1 519 823 7903",
    "sg:postcode":"N1L 1E9",
    "sg:province":"ON",
    "sg:tags":[
        "liquor",
        "store",
        "brewer"
    ],
    "wof:name":"Sleeman Breweries Ltd",
    "wof:placetype":"venue"
},
  "geometry": {"coordinates":[-80.2053604126,43.4882354736],"type":"Point"}
}