{
  "type": "Feature",
  "properties": {
    "iso:country":"CA",
    "sg:address":"7750 Kennedy Rd # 2A",
    "sg:city":"Markham",
    "sg:classifiers":[
        {
            "category":"Food & Beverages",
            "subcategory":"Bakery",
            "type":"Retail Goods"
        }
    ],
    "sg:phone":"+1 905 513 1188",
    "sg:postcode":"L3R 0A7",
    "sg:province":"ON",
    "sg:tags":[
        "baker"
    ],
    "wof:name":"Lucullus Bakery",
    "wof:placetype":"venue"
},
  "geometry": {"coordinates":[-79.3050231934,43.8431816101],"type":"Point"}
}