{
  "type": "Feature",
  "properties": {
    "iso:country":"CA",
    "sg:address":"5042 48 Ave",
    "sg:city":"Delta",
    "sg:classifiers":[
        {
            "category":"Home & Garden",
            "subcategory":"Furniture",
            "type":"Retail Goods"
        }
    ],
    "sg:phone":"+1 604 946 2455",
    "sg:postcode":"V4K 1V8",
    "sg:province":"BC",
    "wof:name":"Heritage House Interiors",
    "wof:placetype":"venue"
},
  "geometry": {"coordinates":[-123.083854675,49.0900344849],"type":"Point"}
}