{
  "type": "Feature",
  "properties": {
    "addr:full":"PO Box 627 Kelvington SK S0A 1W0",
    "addr:housenumber":"po",
    "addr:postcode":"s0a 1w0",
    "addr:street":"Box 627",
    "iso:country":"CA",
    "sg:address":"PO Box 627",
    "sg:city":"Kelvington",
    "sg:classifiers":[
        {
            "category":"Organizations",
            "subcategory":"Religious Organization",
            "type":"Services"
        }
    ],
    "sg:phone":"+1 306 327 5327",
    "sg:postcode":"S0A 1W0",
    "sg:province":"SK",
    "sg:tags":[
        "church"
    ],
    "wof:name":"St Athanase Rectory",
    "wof:placetype":"venue"
},
  "geometry": {"coordinates":[-103.52950300000001,52.164566],"type":"Point"}
}