{
  "type": "Feature",
  "properties": {
    "addr:full":"44 Av Monseigneur-Deziel Beauport QC G1E 2T7",
    "addr:postcode":"qc g1e 2t7",
    "addr:street":"44 Av Monseigneur-Deziel",
    "iso:country":"CA",
    "sg:address":"44 Av Monseigneur-Deziel",
    "sg:city":"Beauport",
    "sg:classifiers":[
        {
            "category":"Building & Trades",
            "subcategory":"Electrical",
            "type":"Services"
        }
    ],
    "sg:phone":"+1 418 663 4218",
    "sg:postcode":"G1E 2T7",
    "sg:province":"QC",
    "sg:tags":[
        "electric",
        "contractor"
    ],
    "wof:name":"Yvon Laplante Enr",
    "wof:placetype":"venue"
},
  "geometry": {"coordinates":[-71.18699599999999,46.861713],"type":"Point"}
}