{
  "type": "Feature",
  "properties": {
    "iso:country":"CA",
    "sg:city":"Winnipeg",
    "sg:classifiers":[
        {
            "category":"Retail",
            "subcategory":"Auto Rental",
            "type":"Services"
        }
    ],
    "sg:phone":"+1 204 925 3532",
    "sg:postcode":"R2V 3C8",
    "sg:province":"MB",
    "sg:tags":[
        "renting",
        "automobile"
    ],
    "wof:name":"National Car Rental",
    "wof:placetype":"venue"
},
  "geometry": {"coordinates":[-97.1517562866,49.9490318298],"type":"Point"}
}