{
  "type": "Feature",
  "properties": {
    "iso:country":"CA",
    "sg:city":"Winnipeg",
    "sg:classifiers":[
        {
            "category":"Personal",
            "type":"Services"
        }
    ],
    "sg:phone":"+1 204 779 0909",
    "sg:postcode":"R3G 0V3",
    "sg:province":"MB",
    "sg:tags":[
        "electrolysis",
        "cosmetic",
        "perfume"
    ],
    "wof:name":"Genie Electrology",
    "wof:placetype":"venue"
},
  "geometry": {"coordinates":[-97.18826293950001,49.8828468323],"type":"Point"}
}