{
  "type": "Feature",
  "properties": {
    "addr:full":"5653 Boul Henri-Bourassa E Montreal-Nord QC H1G 2T4",
    "addr:housenumber":"5653",
    "addr:postcode":"h1g 2t4",
    "addr:street":"Boul Henri-Bourassa E",
    "iso:country":"CA",
    "sg:address":"5653 Boul Henri-Bourassa E",
    "sg:city":"Montreal-Nord",
    "sg:classifiers":[
        {
            "category":"Health Services",
            "subcategory":"Doctor",
            "type":"Services"
        }
    ],
    "sg:phone":"+1 514 329 2303",
    "sg:postcode":"H1G 2T4",
    "sg:province":"QC",
    "sg:tags":[
        "clinic",
        "dentist"
    ],
    "wof:name":"Centre Dentaire Paulo & Taheri",
    "wof:placetype":"venue"
},
  "geometry": {"coordinates":[-73.6208114624,45.6066169739],"type":"Point"}
}