{
  "type": "Feature",
  "properties": {
    "addr:full":"2428 Islington Ave Etobicoke ON M9W 3X8",
    "addr:housenumber":"2428",
    "addr:postcode":"m9w 3x8",
    "addr:street":"Islington Ave",
    "iso:country":"CA",
    "sg:address":"2428 Islington Ave",
    "sg:city":"Etobicoke",
    "sg:classifiers":[
        {
            "category":"Retail",
            "subcategory":"Laundry & Dry Cleaning",
            "type":"Services"
        }
    ],
    "sg:phone":"+1 416 741 1331",
    "sg:postcode":"M9W 3X8",
    "sg:province":"ON",
    "sg:tags":[
        "cleaners"
    ],
    "wof:name":"Moty's Custom Cleaners",
    "wof:placetype":"venue"
},
  "geometry": {"coordinates":[-79.55931099999999,43.723652],"type":"Point"}
}