{
  "type": "Feature",
  "properties": {
    "iso:country":"CA",
    "sg:address":"2428 Islington Ave",
    "sg:city":"Etobicoke",
    "sg:classifiers":[
        {
            "category":"Retail",
            "subcategory":"Laundry & Dry Cleaning",
            "type":"Services"
        }
    ],
    "sg:phone":"+1 416 741 1331",
    "sg:postcode":"M9W 3X8",
    "sg:province":"ON",
    "sg:tags":[
        "cleaners"
    ],
    "wof:name":"Moty's Custom Cleaners",
    "wof:placetype":"venue"
},
  "geometry": {"coordinates":[-79.559311,43.723652],"type":"Point"}
}