{
  "type": "Feature",
  "properties": {
    "addr:full":"707 Simcoe St S Oshawa ON L1H 4K5",
    "addr:housenumber":"707",
    "addr:postcode":"l1h 4k5",
    "addr:street":"Simcoe St S",
    "iso:country":"CA",
    "sg:address":"707 Simcoe St S",
    "sg:city":"Oshawa",
    "sg:classifiers":[
        {
            "category":"Organizations",
            "subcategory":"Professional Association",
            "type":"Services"
        }
    ],
    "sg:phone":"+1 905 725 4252",
    "sg:postcode":"L1H 4K5",
    "sg:province":"ON",
    "sg:tags":[
        "club"
    ],
    "wof:name":"Club Soleil",
    "wof:placetype":"venue"
},
  "geometry": {"coordinates":[-78.85442352290001,43.879535675],"type":"Point"}
}