{
  "type": "Feature",
  "properties": {
    "iso:country":"CA",
    "sg:city":"Sidney",
    "sg:classifiers":[
        {
            "category":"Health Services",
            "subcategory":"Health Practitioner",
            "type":"Services"
        }
    ],
    "sg:phone":"+1 250 656 5525",
    "sg:postcode":"V8L 3C4",
    "sg:province":"BC",
    "sg:tags":[
        "physiotherapist"
    ],
    "wof:name":"Sidney Physiotherapy Clinic",
    "wof:placetype":"venue"
},
  "geometry": {"coordinates":[-123.396789551,48.6469917297],"type":"Point"}
}