{
  "type": "Feature",
  "properties": {
    "addr:full":"632 Pembroke St Victoria BC V8T 1H6",
    "addr:housenumber":"632",
    "addr:postcode":"v8t 1h6",
    "addr:street":"Pembroke St",
    "iso:country":"CA",
    "sg:address":"632 Pembroke St",
    "sg:city":"Victoria",
    "sg:classifiers":[
        {
            "category":"Manufacturing",
            "subcategory":"Tools & Machinery",
            "type":"Manufacturing & Wholesale Goods"
        }
    ],
    "sg:phone":"+1 250 384 3022",
    "sg:postcode":"V8T 1H6",
    "sg:province":"BC",
    "sg:tags":[
        "machine",
        "shop"
    ],
    "wof:name":"Smith Brothers Foundry & Mach",
    "wof:placetype":"venue"
},
  "geometry": {"coordinates":[-123.366264343,48.4328536987],"type":"Point"}
}