{
  "type": "Feature",
  "properties": {
    "addr:full":"80 Little Dyke Rd Great Village NS B0M 1L0",
    "addr:housenumber":"80",
    "addr:postcode":"b0m 1l0",
    "addr:street":"Little Dyke Rd",
    "iso:country":"CA",
    "sg:address":"80 Little Dyke Rd",
    "sg:city":"Great Village",
    "sg:classifiers":[
        {
            "category":"Farming",
            "subcategory":"Farm",
            "type":"Manufacturing & Wholesale Goods"
        }
    ],
    "sg:phone":"+1 902 662 3848",
    "sg:postcode":"B0M 1L0",
    "sg:province":"NS",
    "wof:name":"Millen Farms U-Pick Ltd",
    "wof:placetype":"venue"
},
  "geometry": {"coordinates":[-63.5978889465,45.4154624939],"type":"Point"}
}