{
  "type": "Feature",
  "properties": {
    "addr:full":"6104 67A St Red Deer AB T4P 3E8",
    "addr:housenumber":"6104",
    "addr:postcode":"t4p 3e8",
    "addr:street":"67A St",
    "iso:country":"CA",
    "sg:address":"6104 67A St",
    "sg:city":"Red Deer",
    "sg:classifiers":[
        {
            "category":"Retail",
            "subcategory":"Car Wash",
            "type":"Services"
        }
    ],
    "sg:phone":"+1 403 347 7552",
    "sg:postcode":"T4P 3E8",
    "sg:province":"AB",
    "sg:tags":[
        "polishing",
        "automobile",
        "washing",
        "detail"
    ],
    "wof:name":"Lazer Wash",
    "wof:placetype":"venue"
},
  "geometry": {"coordinates":[-113.817436218,52.2623023987],"type":"Point"}
}