{
  "type": "Feature",
  "properties": {
    "iso:country":"CA",
    "sg:address":"4860 Rue Jacques-Cartier",
    "sg:city":"Saint-Hyacinthe",
    "sg:classifiers":[
        {
            "category":"Insurance",
            "subcategory":"Insurance Agent",
            "type":"Services"
        }
    ],
    "sg:phone":"+1 450 774 5751",
    "sg:postcode":"J2S 8A3",
    "sg:province":"QC",
    "wof:name":"Multi Courtage Inc",
    "wof:placetype":"venue"
},
  "geometry": {"coordinates":[-72.97211456300001,45.6046066284],"type":"Point"}
}