{
  "type": "Feature",
  "properties": {
    "addr:full":"4549 Av Pierre-DE Coubertin Montreal QC H1V 3N7",
    "addr:housenumber":"4549",
    "addr:postcode":"h1v 3n7",
    "addr:street":"Av Pierre-De Coubertin",
    "iso:country":"CA",
    "sg:address":"4549 Av Pierre-DE Coubertin",
    "sg:city":"Montreal",
    "sg:classifiers":[
        {
            "category":"Recreation",
            "type":"Entertainment"
        }
    ],
    "sg:phone":"+1 514 253 3434",
    "sg:postcode":"H1V 3N7",
    "sg:province":"QC",
    "sg:tags":[
        "club",
        "baseball"
    ],
    "wof:name":"Montreal Expos Ltd",
    "wof:placetype":"venue"
},
  "geometry": {"coordinates":[-73.5495681763,45.5574111938],"type":"Point"}
}