{
  "type": "Feature",
  "properties": {
    "addr:full":"136 Wallace Ave N Listowel ON N4W 1K7",
    "addr:housenumber":"136",
    "addr:postcode":"n4w 1k7",
    "addr:street":"Wallace Ave N",
    "iso:country":"CA",
    "sg:address":"136 Wallace Ave N",
    "sg:city":"Listowel",
    "sg:classifiers":[
        {
            "category":"Insurance",
            "subcategory":"Insurance Agent",
            "type":"Services"
        }
    ],
    "sg:phone":"+1 519 291 3920",
    "sg:postcode":"N4W 1K7",
    "sg:province":"ON",
    "wof:name":"Hemsworth Insurance",
    "wof:placetype":"venue"
},
  "geometry": {"coordinates":[-80.952721,43.73188],"type":"Point"}
}