{
  "type": "Feature",
  "properties": {
    "addr:full":"1233 Kane Rd Mississauga ON L5H 2M2",
    "addr:housenumber":"1233",
    "addr:postcode":"l5h 2m2",
    "addr:street":"Kane Rd",
    "iso:country":"CA",
    "sg:address":"1233 Kane Rd",
    "sg:city":"Mississauga",
    "sg:classifiers":[
        {
            "category":"Professional",
            "subcategory":"Computer Services",
            "type":"Services"
        }
    ],
    "sg:phone":"+1 905 891 2011",
    "sg:postcode":"L5H 2M2",
    "sg:province":"ON",
    "sg:tags":[
        "consultant"
    ],
    "wof:name":"Cansoft Consulting Inc",
    "wof:placetype":"venue"
},
  "geometry": {"coordinates":[-79.59832,43.549824],"type":"Point"}
}