{
  "type": "Feature",
  "properties": {
    "addr:full":"24 Hope St E Tavistock ON N0B 2R0",
    "addr:housenumber":"24",
    "addr:postcode":"n0b 2r0",
    "addr:street":"Hope St",
    "iso:country":"CA",
    "sg:address":"24 Hope St E",
    "sg:city":"Tavistock",
    "sg:classifiers":[
        {
            "category":"Insurance",
            "subcategory":"Insurance Agent",
            "type":"Services"
        }
    ],
    "sg:phone":"+1 519 655 2422",
    "sg:postcode":"N0B 2R0",
    "sg:province":"ON",
    "wof:name":"C J Kaufman Insurance Brokers",
    "wof:placetype":"venue"
},
  "geometry": {"coordinates":[-80.83442700000001,43.321346],"type":"Point"}
}