{
  "type": "Feature",
  "properties": {
    "addr:full":"320 12E Rue Grand-Mere QC G9T 4A5",
    "addr:housenumber":"320",
    "addr:postcode":"g9t 4a5",
    "addr:street":"12E Rue Grand-Mere",
    "iso:country":"CA",
    "sg:address":"320 12E Rue",
    "sg:city":"Grand-Mere",
    "sg:classifiers":[
        {
            "category":"Wholesale",
            "subcategory":"Machinery & Supplies",
            "type":"Manufacturing & Wholesale Goods"
        }
    ],
    "sg:phone":"+1 819 538 6383",
    "sg:postcode":"G9T 4A5",
    "sg:province":"QC",
    "sg:tags":[
        "machine",
        "tool"
    ],
    "wof:name":"General Surplus S Pepin Enr",
    "wof:placetype":"venue"
},
  "geometry": {"coordinates":[-72.69449615480001,46.6202697754],"type":"Point"}
}