{
  "type": "Feature",
  "properties": {
    "addr:full":"685 Runnymede Rd Toronto ON M6S 3A4",
    "addr:housenumber":"685",
    "addr:postcode":"m6s 3a4",
    "addr:street":"Runnymede Rd",
    "iso:country":"CA",
    "sg:address":"685 Runnymede Rd",
    "sg:city":"Toronto",
    "sg:classifiers":[
        {
            "category":"Restaurant",
            "type":"Food & Drink"
        }
    ],
    "sg:phone":"+1 416 763 6961",
    "sg:postcode":"M6S 3A4",
    "sg:province":"ON",
    "wof:name":"Jumbo Burgers",
    "wof:placetype":"venue"
},
  "geometry": {"coordinates":[-79.482353,43.666416],"type":"Point"}
}