{
  "type": "Feature",
  "properties": {
    "addr:full":"3 Rue Du Carillon Matapedia QC G0J 1V0",
    "addr:housenumber":"3",
    "addr:postcode":"g0j 1v0",
    "addr:street":"Rue Du Carillon Matapedia",
    "iso:country":"CA",
    "sg:address":"3 Rue Du Carillon",
    "sg:city":"Matapedia",
    "sg:classifiers":[
        {
            "category":"Organizations",
            "subcategory":"Professional Association",
            "type":"Services"
        }
    ],
    "sg:phone":"+1 418 865 2740",
    "sg:postcode":"G0J 1V0",
    "sg:province":"QC",
    "wof:name":"Centre D'Action Benevole",
    "wof:placetype":"venue"
},
  "geometry": {"coordinates":[-66.95333099370001,47.9747390747],"type":"Point"}
}