{
  "type": "Feature",
  "properties": {
    "iso:country":"CA",
    "sg:address":"405 Spadina Ave",
    "sg:city":"Toronto",
    "sg:classifiers":[
        {
            "category":"Wholesale",
            "subcategory":"Durable Goods & Equipment",
            "type":"Manufacturing & Wholesale Goods"
        }
    ],
    "sg:phone":"+1 416 596 6878",
    "sg:postcode":"M5T 2G6",
    "sg:province":"ON",
    "sg:tags":[
        "importer"
    ],
    "wof:name":"S D Intl Import",
    "wof:placetype":"venue"
},
  "geometry": {"coordinates":[-79.3992385864,43.6566314697],"type":"Point"}
}