{
  "type": "Feature",
  "properties": {
    "addr:full":"Sherwood Park AB T8A 4T6",
    "addr:postcode":"t8a 4t6",
    "iso:country":"CA",
    "sg:city":"Sherwood Park",
    "sg:classifiers":[
        {
            "category":"Professional",
            "subcategory":"Computer Services",
            "type":"Services"
        }
    ],
    "sg:phone":"+1 780 464 7579",
    "sg:postcode":"T8A 4T6",
    "sg:province":"AB",
    "sg:tags":[
        "processing",
        "datum"
    ],
    "wof:name":"Essex Data Svc Ltd",
    "wof:placetype":"venue"
},
  "geometry": {"coordinates":[-113.246955872,53.512260437],"type":"Point"}
}