{
  "type": "Feature",
  "properties": {
    "addr:full":"7594 Ch DE LA Cote-DE-Liesse Saint-Laurent QC H4T 1E7",
    "addr:housenumber":"7594",
    "addr:postcode":"h4t 1e7",
    "addr:street":"Ch De La Cote-De-Liesse",
    "iso:country":"CA",
    "sg:address":"7594 Ch DE LA Cote-DE-Liesse",
    "sg:city":"Saint-Laurent",
    "sg:classifiers":[
        {
            "category":"Retail",
            "subcategory":"Repair Shop",
            "type":"Services"
        }
    ],
    "sg:phone":"+1 514 735 9405",
    "sg:postcode":"H4T 1E7",
    "sg:province":"QC",
    "sg:tags":[
        "equipment",
        "electronic",
        "supply"
    ],
    "wof:name":"Avi Electronique",
    "wof:placetype":"venue"
},
  "geometry": {"coordinates":[-73.7006530762,45.4785270691],"type":"Point"}
}