{
  "type": "Feature",
  "properties": {
    "addr:full":"155 Wayne Gretzky Pky Brantford ON N3S 7P1",
    "addr:housenumber":"155",
    "addr:postcode":"n3s 7p1",
    "addr:street":"Wayne Gretzky Pky",
    "iso:country":"CA",
    "sg:address":"155 Wayne Gretzky Pky",
    "sg:city":"Brantford",
    "sg:classifiers":[
        {
            "category":"Shopping",
            "subcategory":"Stationery & Office Supplies",
            "type":"Retail Goods"
        }
    ],
    "sg:phone":"+1 519 759 6839",
    "sg:postcode":"N3S 7P1",
    "sg:province":"ON",
    "wof:name":"Amb Automation Inc",
    "wof:placetype":"venue"
},
  "geometry": {"coordinates":[-80.238304,43.152454],"type":"Point"}
}