{
  "type": "Feature",
  "properties": {
    "addr:full":"Thornhill ON L4J 7K5",
    "addr:postcode":"l4j 7k5",
    "iso:country":"CA",
    "sg:city":"Thornhill",
    "sg:classifiers":[
        {
            "category":"Professional",
            "subcategory":"Research",
            "type":"Services"
        }
    ],
    "sg:phone":"+1 905 882 7725",
    "sg:postcode":"L4J 7K5",
    "sg:province":"ON",
    "sg:tags":[
        "foundation",
        "philanthropic"
    ],
    "wof:name":"Dysautonomia Foundation Inc",
    "wof:placetype":"venue"
},
  "geometry": {"coordinates":[-79.43463134770001,43.8060188293],"type":"Point"}
}