{
  "type": "Feature",
  "properties": {
    "iso:country":"CA",
    "sg:address":"191 Strathcona Ave",
    "sg:city":"Ottawa",
    "sg:classifiers":[
        {
            "category":"Building & Trades",
            "subcategory":"Construction",
            "type":"Services"
        }
    ],
    "sg:phone":"+1 613 231 5857",
    "sg:postcode":"K1S 1X7",
    "sg:province":"ON",
    "sg:tags":[
        "masonry",
        "contractor"
    ],
    "wof:name":"Atkinson Stonecraft Masonry",
    "wof:placetype":"venue"
},
  "geometry": {"coordinates":[-75.68901824949999,45.4082565308],"type":"Point"}
}