{
  "type": "Feature",
  "properties": {
    "iso:country":"CA",
    "sg:address":"River Rd",
    "sg:city":"Kahnawake",
    "sg:classifiers":[
        {
            "category":"Food & Beverages",
            "subcategory":"Groceries & Convenience Stores",
            "type":"Retail Goods"
        }
    ],
    "sg:phone":"+1 450 635 6225",
    "sg:postcode":"J0L 1B0",
    "sg:province":"QC",
    "sg:tags":[
        "grocer"
    ],
    "wof:name":"Mc Comber Convenience",
    "wof:placetype":"venue"
},
  "geometry": {"coordinates":[-73.683357,45.415802],"type":"Point"}
}