{
  "type": "Feature",
  "properties": {
    "addr:full":"Quebec QC G1R 2H4",
    "addr:postcode":"g1r 2h4",
    "iso:country":"CA",
    "sg:city":"Quebec",
    "sg:classifiers":[
        {
            "category":"Insurance",
            "subcategory":"Insurance Agent",
            "type":"Services"
        }
    ],
    "sg:phone":"+1 418 522 4757",
    "sg:postcode":"G1R 2H4",
    "sg:province":"QC",
    "wof:name":"Optimum Societe D'Assurance",
    "wof:placetype":"venue"
},
  "geometry": {"coordinates":[-71.2263412476,46.8008499146],"type":"Point"}
}