{
  "type": "Feature",
  "properties": {
    "addr:full":"1331 Brenton St Halifax NS B3J 2K5",
    "addr:housenumber":"1331",
    "addr:postcode":"ns b3j 2k5",
    "addr:street":"Brenton St",
    "iso:country":"CA",
    "sg:address":"1331 Brenton St",
    "sg:city":"Halifax",
    "sg:classifiers":[
        {
            "category":"Professional",
            "subcategory":"Research",
            "type":"Services"
        }
    ],
    "sg:phone":"+1 902 421 1720",
    "sg:postcode":"B3J 2K5",
    "sg:province":"NS",
    "sg:tags":[
        "economic",
        "analysis"
    ],
    "wof:name":"Gardner Pinfold Consulting",
    "wof:placetype":"venue"
},
  "geometry": {"coordinates":[-63.577587,44.640602],"type":"Point"}
}