{
  "type": "Feature",
  "properties": {
    "addr:full":"1390 Av O'Neil Quebec QC G1P 2G9",
    "addr:housenumber":"1390",
    "addr:postcode":"g1p 2g9",
    "addr:street":"Av O'Neil",
    "iso:country":"CA",
    "sg:address":"1390 Av O'Neil",
    "sg:city":"Quebec",
    "sg:classifiers":[
        {
            "category":"Professional",
            "subcategory":"Accounting & Tax Preparation",
            "type":"Services"
        }
    ],
    "sg:phone":"+1 418 872 5115",
    "sg:postcode":"G1P 2G9",
    "sg:province":"QC",
    "sg:tags":[
        "accountant"
    ],
    "wof:name":"Bergeron Lavigne Senc",
    "wof:placetype":"venue"
},
  "geometry": {"coordinates":[-71.306549,46.805099],"type":"Point"}
}