{
  "type": "Feature",
  "properties": {
    "addr:full":"609 Rue Mccaffrey Saint-Laurent QC H4T 1N3",
    "addr:housenumber":"609",
    "addr:postcode":"h4t 1n3",
    "addr:street":"Rue Mccaffrey",
    "iso:country":"CA",
    "sg:address":"609 Rue Mccaffrey",
    "sg:city":"Saint-Laurent",
    "sg:classifiers":[
        {
            "category":"Professional",
            "subcategory":"Computer Services",
            "type":"Services"
        }
    ],
    "sg:phone":"+1 514 344 2447",
    "sg:postcode":"H4T 1N3",
    "sg:province":"QC",
    "sg:tags":[
        "information",
        "system",
        "consultant"
    ],
    "wof:name":"Dcs Destratek Computer Svc",
    "wof:placetype":"venue"
},
  "geometry": {"coordinates":[-73.7084121704,45.4862289429],"type":"Point"}
}