{
  "type": "Feature",
  "properties": {
    "addr:full":"155 Main St Lillooet BC V0K 1V0",
    "addr:housenumber":"155",
    "addr:postcode":"v0k 1v0",
    "addr:street":"Main St",
    "iso:country":"CA",
    "sg:address":"155 Main St",
    "sg:city":"Lillooet",
    "sg:classifiers":[
        {
            "category":"Food & Beverages",
            "subcategory":"Groceries & Convenience Stores",
            "type":"Retail Goods"
        }
    ],
    "sg:phone":"+1 250 256 7922",
    "sg:postcode":"V0K 1V0",
    "sg:province":"BC",
    "sg:tags":[
        "grocer"
    ],
    "wof:name":"Buy Low Foods",
    "wof:placetype":"venue"
},
  "geometry": {"coordinates":[-121.93284606900001,50.6827888489],"type":"Point"}
}