{
  "type": "Feature",
  "properties": {
    "addr:full":"5 Harold Allen Rd Timber River NB E4M 3B5",
    "addr:housenumber":"5",
    "addr:postcode":"e4m 3b5",
    "addr:street":"Harold Allen Rd",
    "iso:country":"CA",
    "sg:address":"5 Harold Allen Rd",
    "sg:city":"Timber River",
    "sg:classifiers":[
        {
            "category":"Food & Beverages",
            "subcategory":"Groceries & Convenience Stores",
            "type":"Retail Goods"
        }
    ],
    "sg:phone":"+1 506 538 7409",
    "sg:postcode":"E4M 3B5",
    "sg:province":"NB",
    "wof:name":"Timber River Country Market",
    "wof:placetype":"venue"
},
  "geometry": {"coordinates":[-64.050606,46.069679],"type":"Point"}
}