{
  "type": "Feature",
  "properties": {
    "addr:full":"Granby QC J2G 4W7",
    "addr:postcode":"j2g 4w7",
    "iso:country":"CA",
    "sg:city":"Granby",
    "sg:classifiers":[
        {
            "category":"Professional",
            "subcategory":"Research",
            "type":"Services"
        }
    ],
    "sg:phone":"+1 450 372 6607",
    "sg:postcode":"J2G 4W7",
    "sg:province":"QC",
    "sg:tags":[
        "environmental",
        "ecological",
        "engineer"
    ],
    "wof:name":"Bureau D'Etudes Estrie Conslnt",
    "wof:placetype":"venue"
},
  "geometry": {"coordinates":[-72.72244262700001,45.4002685547],"type":"Point"}
}