{
  "type": "Feature",
  "properties": {
    "addr:full":"Lewisporte NL A0G 3A0",
    "addr:postcode":"a0g 3a0",
    "iso:country":"CA",
    "sg:city":"Lewisporte",
    "sg:classifiers":[
        {
            "category":"Recreation",
            "type":"Entertainment"
        }
    ],
    "sg:phone":"+1 709 535 6903",
    "sg:postcode":"A0G 3A0",
    "sg:province":"NL",
    "sg:tags":[
        "center"
    ],
    "wof:name":"Newfoundland Recreation",
    "wof:placetype":"venue"
},
  "geometry": {"coordinates":[-55.0599365234,49.2417984009],"type":"Point"}
}