{
  "type": "Feature",
  "properties": {
    "addr:full":"363 Rue Saint-Francois-Xavier Montreal QC H2Y 3P9",
    "addr:housenumber":"363",
    "addr:postcode":"h2y 3p9",
    "addr:street":"Rue Saint-Francois-Xavier",
    "iso:country":"CA",
    "sg:address":"363 Rue Saint-Francois-Xavier",
    "sg:city":"Montreal",
    "sg:classifiers":[
        {
            "category":"Restaurant",
            "type":"Food & Drink"
        }
    ],
    "sg:phone":"+1 514 845 3646",
    "sg:postcode":"H2Y 3P9",
    "sg:province":"QC",
    "wof:name":"Restaurant Fr Le Bourlingueur",
    "wof:placetype":"venue"
},
  "geometry": {"coordinates":[-73.55502300000001,45.502705],"type":"Point"}
}