{
  "type": "Feature",
  "properties": {
    "addr:full":"4401 Railway Ave Elk Point AB T0A 1A0",
    "addr:housenumber":"4401",
    "addr:postcode":"t0a 1a0",
    "addr:street":"Railway Ave",
    "iso:country":"CA",
    "sg:address":"4401 Railway Ave",
    "sg:city":"Elk Point",
    "sg:classifiers":[
        {
            "category":"Mining & Drilling",
            "type":"Manufacturing & Wholesale Goods"
        }
    ],
    "sg:phone":"+1 780 724 2647",
    "sg:postcode":"T0A 1A0",
    "sg:province":"AB",
    "sg:tags":[
        "field",
        "oil"
    ],
    "wof:name":"A & J Oilfield Svc Ltd",
    "wof:placetype":"venue"
},
  "geometry": {"coordinates":[-110.890373,53.896538],"type":"Point"}
}