{
  "type": "Feature",
  "properties": {
    "addr:full":"London ON N6L 1E6",
    "addr:postcode":"n6l 1e6",
    "iso:country":"CA",
    "sg:city":"London",
    "sg:classifiers":[
        {
            "category":"Wholesale",
            "subcategory":"Photographic Equipment",
            "type":"Manufacturing & Wholesale Goods"
        }
    ],
    "sg:phone":"+1 519 652 3533",
    "sg:postcode":"N6L 1E6",
    "sg:province":"ON",
    "sg:tags":[
        "video"
    ],
    "wof:name":"Edcom Multimedia Products",
    "wof:placetype":"venue"
},
  "geometry": {"coordinates":[-81.26683800000001,42.92012],"type":"Point"}
}