{
  "type": "Feature",
  "properties": {
    "iso:country":"CA",
    "sg:address":"5205 County Road 17",
    "sg:city":"Alfred",
    "sg:classifiers":[
        {
            "category":"Building & Trades",
            "subcategory":"Equipment Rental",
            "type":"Services"
        }
    ],
    "sg:phone":"+1 613 679 4465",
    "sg:postcode":"K0B 1A0",
    "sg:province":"ON",
    "sg:tags":[
        "crane",
        "yard"
    ],
    "wof:name":"Carriere Equipment Rental",
    "wof:placetype":"venue"
},
  "geometry": {"coordinates":[-74.8840255737,45.5575218201],"type":"Point"}
}