{
  "type": "Feature",
  "properties": {
    "addr:full":"1990 Rue DE Foucault Terrebonne QC J6X 2P7",
    "addr:housenumber":"1990",
    "addr:postcode":"j6x 2p7",
    "addr:street":"Rue De Foucault",
    "iso:country":"CA",
    "sg:address":"1990 Rue DE Foucault",
    "sg:city":"Terrebonne",
    "sg:classifiers":[
        {
            "category":"Wholesale",
            "subcategory":"Machinery & Supplies",
            "type":"Manufacturing & Wholesale Goods"
        }
    ],
    "sg:phone":"+1 514 944 6581",
    "sg:postcode":"J6X 2P7",
    "sg:province":"QC",
    "sg:tags":[
        "platform",
        "mezzanine",
        "partition"
    ],
    "wof:name":"Amenagement Manu-Nord Enr",
    "wof:placetype":"venue"
},
  "geometry": {"coordinates":[-73.672096,45.722485],"type":"Point"}
}