{
  "type": "Feature",
  "properties": {
    "addr:full":"3780 Fallowfield Rd Nepean ON K2J 1A1",
    "addr:housenumber":"3780",
    "addr:postcode":"k2j 1a1",
    "addr:street":"Fallowfield Rd",
    "iso:country":"CA",
    "sg:address":"3780 Fallowfield Rd",
    "sg:city":"Nepean",
    "sg:classifiers":[
        {
            "category":"Education",
            "subcategory":"School",
            "type":"Public Place"
        }
    ],
    "sg:phone":"+1 613 823 1300",
    "sg:postcode":"K2J 1A1",
    "sg:province":"ON",
    "wof:name":"Oxford Learning Ctr",
    "wof:placetype":"venue"
},
  "geometry": {"coordinates":[-75.75746154789999,45.2876625061],"type":"Point"}
}