{
  "type": "Feature",
  "properties": {
    "iso:country":"CA",
    "sg:address":"3077 Mainway",
    "sg:city":"Burlington",
    "sg:classifiers":[
        {
            "category":"Manufacturing",
            "subcategory":"Furniture",
            "type":"Manufacturing & Wholesale Goods"
        }
    ],
    "sg:phone":"+1 905 319 9955",
    "sg:postcode":"L7M 1A1",
    "sg:province":"ON",
    "sg:tags":[
        "fixture",
        "store"
    ],
    "wof:name":"Whips Carpentry",
    "wof:placetype":"venue"
},
  "geometry": {"coordinates":[-79.808662,43.359142],"type":"Point"}
}