{
  "type": "Feature",
  "properties": {
    "addr:full":"22 Hazelwood Cres Brandon MB R7A 2J9",
    "addr:housenumber":"22",
    "addr:postcode":"r7a 2j9",
    "addr:street":"Hazelwood Cres",
    "iso:country":"CA",
    "sg:address":"22 Hazelwood Cres",
    "sg:city":"Brandon",
    "sg:classifiers":[
        {
            "category":"Railroad",
            "type":"Transportation"
        }
    ],
    "sg:phone":"+1 204 725 2119",
    "sg:postcode":"R7A 2J9",
    "sg:province":"MB",
    "wof:name":"Hudson Bay Route Assn",
    "wof:placetype":"venue"
},
  "geometry": {"coordinates":[-99.926018,49.828041],"type":"Point"}
}