{
  "type": "Feature",
  "properties": {
    "addr:full":"Orleans ON K1C 4R1",
    "addr:postcode":"k1c 4r1",
    "iso:country":"CA",
    "sg:city":"Orleans",
    "sg:classifiers":[
        {
            "category":"Professional",
            "subcategory":"Lawyer & Legal Services",
            "type":"Services"
        }
    ],
    "sg:phone":"+1 613 590 7991",
    "sg:postcode":"K1C 4R1",
    "sg:province":"ON",
    "sg:tags":[
        "attorney"
    ],
    "wof:name":"Gauthier Law Office",
    "wof:placetype":"venue"
},
  "geometry": {"coordinates":[-75.54980500000001,45.464672],"type":"Point"}
}