{
  "type": "Feature",
  "properties": {
    "iso:country":"CA",
    "sg:address":"40 Place Du Commerce",
    "sg:city":"Verdun",
    "sg:classifiers":[
        {
            "category":"Manufacturing",
            "subcategory":"Chemicals & Compounds",
            "type":"Manufacturing & Wholesale Goods"
        }
    ],
    "sg:phone":"+1 450 638 8979",
    "sg:postcode":"H3E 1J6",
    "sg:province":"QC",
    "wof:name":"Multhi-Bio",
    "wof:placetype":"venue"
},
  "geometry": {"coordinates":[-73.571762085,45.4590187073],"type":"Point"}
}