{
  "type": "Feature",
  "properties": {
    "addr:full":"Quebec QC G1K 4A4",
    "addr:postcode":"g1k 4a4",
    "iso:country":"CA",
    "sg:city":"Quebec",
    "sg:classifiers":[
        {
            "category":"Shopping",
            "type":"Retail Goods"
        }
    ],
    "sg:phone":"+1 418 692 9996",
    "sg:postcode":"G1K 4A4",
    "sg:province":"QC",
    "sg:tags":[
        "art",
        "gallery",
        "dealer"
    ],
    "wof:name":"Galerie D'Art Ars Vivesco",
    "wof:placetype":"venue"
},
  "geometry": {"coordinates":[-71.202957,46.814606],"type":"Point"}
}