{
  "type": "Feature",
  "properties": {
    "addr:full":"Waswanipi QC J0Y 3C0",
    "addr:postcode":"j0y 3c0",
    "iso:country":"CA",
    "sg:city":"Waswanipi",
    "sg:classifiers":[
        {
            "category":"Social Services",
            "subcategory":"Child Care",
            "type":"Services"
        }
    ],
    "sg:phone":"+1 819 753 2623",
    "sg:postcode":"J0Y 3C0",
    "sg:province":"QC",
    "sg:tags":[
        "recreation",
        "center"
    ],
    "wof:name":"Waswanipi Awaash Shiishikunkam",
    "wof:placetype":"venue"
},
  "geometry": {"coordinates":[-75.8924331665,49.7433013916],"type":"Point"}
}