{
  "type": "Feature",
  "properties": {
    "addr:full":"30 Riviera Dr Markham ON L3R 5M1",
    "addr:housenumber":"30",
    "addr:postcode":"l3r 5m1",
    "addr:street":"Riviera Dr",
    "iso:country":"CA",
    "sg:address":"30 Riviera Dr",
    "sg:city":"Markham",
    "sg:classifiers":[
        {
            "category":"Manufacturing",
            "subcategory":"Metals",
            "type":"Manufacturing & Wholesale Goods"
        }
    ],
    "sg:phone":"+1 905 479 9339",
    "sg:postcode":"L3R 5M1",
    "sg:province":"ON",
    "sg:tags":[
        "steel"
    ],
    "wof:name":"Vebcam Metal Products Ltd",
    "wof:placetype":"venue"
},
  "geometry": {"coordinates":[-79.34777099999999,43.831608],"type":"Point"}
}