{
  "type": "Feature",
  "properties": {
    "addr:full":"136 Rue Saint-Paul E Montreal QC H2Y 1G6",
    "addr:housenumber":"136",
    "addr:postcode":"h2y 1g6",
    "addr:street":"Rue Saint-Paul E",
    "iso:country":"CA",
    "sg:address":"136 Rue Saint-Paul E",
    "sg:city":"Montreal",
    "sg:classifiers":[
        {
            "category":"Shopping",
            "subcategory":"Bicycles & Sporting Goods",
            "type":"Retail Goods"
        }
    ],
    "sg:phone":"+1 514 866 1457",
    "sg:postcode":"H2Y 1G6",
    "sg:province":"QC",
    "wof:name":"Galeries Du Sport",
    "wof:placetype":"venue"
},
  "geometry": {"coordinates":[-73.552696,45.506954],"type":"Point"}
}