{
  "type": "Feature",
  "properties": {
    "addr:full":"1328 Marine Dr SE Vancouver BC V5X 4K4",
    "addr:housenumber":"1328",
    "addr:postcode":"v5x 4k4",
    "addr:street":"Marine Dr Se",
    "iso:country":"CA",
    "sg:address":"1328 Marine Dr SE",
    "sg:city":"Vancouver",
    "sg:classifiers":[
        {
            "category":"Wholesale",
            "subcategory":"Furniture",
            "type":"Manufacturing & Wholesale Goods"
        }
    ],
    "sg:phone":"+1 604 321 7658",
    "sg:postcode":"V5X 4K4",
    "sg:province":"BC",
    "wof:name":"Janssen International",
    "wof:placetype":"venue"
},
  "geometry": {"coordinates":[-123.08026886,49.2109184265],"type":"Point"}
}