{
  "type": "Feature",
  "properties": {
    "addr:full":"615 Boul Des Promenades Saint-Bruno QC J3V 6L9",
    "addr:housenumber":"615",
    "addr:postcode":"j3v 6l9",
    "addr:street":"Boul Des Promenades",
    "iso:country":"CA",
    "sg:address":"615 Boul Des Promenades",
    "sg:city":"Saint-Bruno",
    "sg:classifiers":[
        {
            "category":"Shopping",
            "subcategory":"Bicycles & Sporting Goods",
            "type":"Retail Goods"
        }
    ],
    "sg:phone":"+1 450 653 1364",
    "sg:postcode":"J3V 6L9",
    "sg:province":"QC",
    "sg:tags":[
        "skiing"
    ],
    "wof:name":"Sports Experts",
    "wof:placetype":"venue"
},
  "geometry": {"coordinates":[-71.675522,48.471771],"type":"Point"}
}