{
  "type": "Feature",
  "properties": {
    "addr:full":"701 Millidge Ave Saint John NB E2K 2N7",
    "addr:housenumber":"701",
    "addr:postcode":"e2k 2n7",
    "addr:street":"Millidge Ave",
    "iso:country":"CA",
    "sg:address":"701 Millidge Ave",
    "sg:city":"Saint John",
    "sg:classifiers":[
        {
            "category":"Food & Beverages",
            "subcategory":"Groceries & Convenience Stores",
            "type":"Retail Goods"
        }
    ],
    "sg:phone":"+1 506 634 8389",
    "sg:postcode":"E2K 2N7",
    "sg:province":"NB",
    "wof:name":"Millidgeville Convenience Str",
    "wof:placetype":"venue"
},
  "geometry": {"coordinates":[-66.09684,45.294521],"type":"Point"}
}