{
  "type": "Feature",
  "properties": {
    "iso:country":"CA",
    "sg:city":"Brantford",
    "sg:classifiers":[
        {
            "category":"Real Estate",
            "subcategory":"Real Estate Operator",
            "type":"Services"
        }
    ],
    "sg:phone":"+1 519 770 4998",
    "sg:postcode":"N3T 6A7",
    "sg:province":"ON",
    "sg:tags":[
        "apartment"
    ],
    "wof:name":"Centennial Towers",
    "wof:placetype":"venue"
},
  "geometry": {"coordinates":[-80.2593994141,43.1407737732],"type":"Point"}
}