{
  "type": "Feature",
  "properties": {
    "addr:full":"Toronto ON M5H 2G4",
    "addr:postcode":"m5h 2g4",
    "iso:country":"CA",
    "sg:city":"Toronto",
    "sg:classifiers":[
        {
            "category":"Professional",
            "subcategory":"Employment Agencies",
            "type":"Services"
        }
    ],
    "sg:phone":"+1 416 867 9295",
    "sg:postcode":"M5H 2G4",
    "sg:province":"ON",
    "sg:tags":[
        "consultant",
        "search",
        "executive",
        "opportunity"
    ],
    "wof:name":"Bryan Jason & Assoc",
    "wof:placetype":"venue"
},
  "geometry": {"coordinates":[-79.3838348389,43.6504745483],"type":"Point"}
}