{
  "type": "Feature",
  "properties": {
    "addr:full":"4435 Boul Saint-Martin O Laval QC H7T 1C6",
    "addr:housenumber":"4435",
    "addr:postcode":"h7t 1c6",
    "addr:street":"Boul Saint-Martin O",
    "iso:country":"CA",
    "sg:address":"4435 Boul Saint-Martin O",
    "sg:city":"Laval",
    "sg:classifiers":[
        {
            "category":"Shopping",
            "type":"Retail Goods"
        }
    ],
    "sg:phone":"+1 450 681 6113",
    "sg:postcode":"H7T 1C6",
    "sg:province":"QC",
    "sg:tags":[
        "cosmetic",
        "perfume"
    ],
    "wof:name":"Parfumerie Eternelle",
    "wof:placetype":"venue"
},
  "geometry": {"coordinates":[-73.77048499999999,45.548252],"type":"Point"}
}