{
  "type": "Feature",
  "properties": {
    "iso:country":"CA",
    "sg:address":"583 Rue Principale",
    "sg:city":"Saint-Thomas",
    "sg:classifiers":[
        {
            "category":"Manufacturing",
            "subcategory":"Food",
            "type":"Manufacturing & Wholesale Goods"
        }
    ],
    "sg:phone":"+1 450 753 4281",
    "sg:postcode":"J0K 3L0",
    "sg:province":"QC",
    "sg:tags":[
        "grocer",
        "cookie",
        "bakery"
    ],
    "wof:name":"Boulangerie Gadoua Ltee",
    "wof:placetype":"venue"
},
  "geometry": {"coordinates":[-73.35945129389999,46.013923645],"type":"Point"}
}