{
  "type": "Feature",
  "properties": {
    "addr:full":"Richmond BC V6V 2L4",
    "addr:postcode":"v6v 2l4",
    "iso:country":"CA",
    "sg:city":"Richmond",
    "sg:classifiers":[
        {
            "category":"Building & Trades",
            "subcategory":"Construction",
            "type":"Services"
        }
    ],
    "sg:phone":"+1 604 273 3301",
    "sg:postcode":"V6V 2L4",
    "sg:province":"BC",
    "sg:tags":[
        "contractor"
    ],
    "wof:name":"Vanbots Construction Inc",
    "wof:placetype":"venue"
},
  "geometry": {"coordinates":[-123.07308999999999,49.184063],"type":"Point"}
}