{
  "type": "Feature",
  "properties": {
    "addr:full":"Magrath AB T0K 1J0",
    "addr:postcode":"t0k 1j0",
    "iso:country":"CA",
    "sg:city":"Magrath",
    "sg:classifiers":[
        {
            "category":"Building & Trades",
            "subcategory":"Construction",
            "type":"Services"
        }
    ],
    "sg:phone":"+1 403 758 3569",
    "sg:postcode":"T0K 1J0",
    "sg:province":"AB",
    "sg:tags":[
        "excavating",
        "contractor"
    ],
    "wof:name":"Freds Excavating",
    "wof:placetype":"venue"
},
  "geometry": {"coordinates":[-112.861862,49.420944],"type":"Point"}
}