{
  "type": "Feature",
  "properties": {
    "addr:full":"Pickle Lake ON P0V 3A0",
    "addr:postcode":"p0v 3a0",
    "iso:country":"CA",
    "sg:city":"Pickle Lake",
    "sg:classifiers":[
        {
            "category":"Education",
            "subcategory":"School",
            "type":"Public Place"
        }
    ],
    "sg:phone":"+1 807 928 2284",
    "sg:postcode":"P0V 3A0",
    "sg:province":"ON",
    "wof:name":"Missabay Local Education",
    "wof:placetype":"venue"
},
  "geometry": {"coordinates":[-90.160538,51.481373],"type":"Point"}
}