{
  "type": "Feature",
  "properties": {
    "addr:full":"38 Unsworth Ave Toronto ON M5M 3C5",
    "addr:housenumber":"38",
    "addr:postcode":"m5m 3c5",
    "addr:street":"Unsworth Ave",
    "iso:country":"CA",
    "sg:address":"38 Unsworth Ave",
    "sg:city":"Toronto",
    "sg:classifiers":[
        {
            "category":"Professional",
            "subcategory":"Employment Agencies",
            "type":"Services"
        }
    ],
    "sg:phone":"+1 416 482 0744",
    "sg:postcode":"M5M 3C5",
    "sg:province":"ON",
    "sg:tags":[
        "opportunity"
    ],
    "wof:name":"Bongard & Assoc",
    "wof:placetype":"venue"
},
  "geometry": {"coordinates":[-79.404999,43.725281],"type":"Point"}
}