{
  "type": "Feature",
  "properties": {
    "addr:full":"111 1st Ave W Nipawin SK S0E 1E0",
    "addr:housenumber":"111",
    "addr:postcode":"s0e 1e0",
    "addr:street":"1St Ave W Nipawin",
    "iso:country":"CA",
    "sg:address":"111 1st Ave W",
    "sg:city":"Nipawin",
    "sg:classifiers":[
        {
            "category":"Home & Garden",
            "subcategory":"Hardware",
            "type":"Retail Goods"
        }
    ],
    "sg:phone":"+1 306 862 3119",
    "sg:postcode":"S0E 1E0",
    "sg:province":"SK",
    "wof:name":"Home Hardware",
    "wof:placetype":"venue"
},
  "geometry": {"coordinates":[-104.017944336,53.3620681763],"type":"Point"}
}