{
  "type": "Feature",
  "properties": {
    "addr:full":"6071 Oldfield Rd Victoria BC V9E 2J4",
    "addr:housenumber":"6071",
    "addr:postcode":"v9e 2j4",
    "addr:street":"Oldfield Rd",
    "iso:country":"CA",
    "sg:address":"6071 Oldfield Rd",
    "sg:city":"Victoria",
    "sg:classifiers":[
        {
            "category":"Recreation",
            "type":"Entertainment"
        }
    ],
    "sg:phone":"+1 250 652 8390",
    "sg:postcode":"V9E 2J4",
    "sg:province":"BC",
    "sg:tags":[
        "stable"
    ],
    "wof:name":"Tudor Rose Farm",
    "wof:placetype":"venue"
},
  "geometry": {"coordinates":[-123.36451700000001,48.428314],"type":"Point"}
}