{
  "type": "Feature",
  "properties": {
    "addr:full":"1202 Rue Bishop Montreal QC H3G 2E3",
    "addr:housenumber":"1202",
    "addr:postcode":"h3g 2e3",
    "addr:street":"Rue Bishop",
    "iso:country":"CA",
    "sg:address":"1202 Rue Bishop",
    "sg:city":"Montreal",
    "sg:classifiers":[
        {
            "category":"Restaurant",
            "type":"Food & Drink"
        }
    ],
    "sg:phone":"+1 514 875 7082",
    "sg:postcode":"H3G 2E3",
    "sg:province":"QC",
    "wof:name":"Mango Bay",
    "wof:placetype":"venue"
},
  "geometry": {"coordinates":[-73.57511100000001,45.495819],"type":"Point"}
}