{
  "type": "Feature",
  "properties": {
    "iso:country":"CA",
    "sg:address":"1202 Rue Bishop",
    "sg:city":"Montreal",
    "sg:classifiers":[
        {
            "category":"Restaurant",
            "type":"Food & Drink"
        }
    ],
    "sg:phone":"+1 514 875 7082",
    "sg:postcode":"H3G 2E3",
    "sg:province":"QC",
    "wof:name":"Mango Bay",
    "wof:placetype":"venue"
},
  "geometry": {"coordinates":[-73.575111,45.495819],"type":"Point"}
}