{
  "type": "Feature",
  "properties": {
    "addr:full":"202 Percy St Smiths Falls ON K7A 4W8",
    "addr:housenumber":"202",
    "addr:postcode":"k7a 4w8",
    "addr:street":"Percy St",
    "iso:country":"CA",
    "sg:address":"202 Percy St",
    "sg:city":"Smiths Falls",
    "sg:classifiers":[
        {
            "category":"Retail",
            "subcategory":"Laundry & Dry Cleaning",
            "type":"Services"
        }
    ],
    "sg:phone":"+1 613 283 0444",
    "sg:postcode":"K7A 4W8",
    "sg:province":"ON",
    "sg:tags":[
        "cleaners"
    ],
    "wof:name":"Rideau Cleaners",
    "wof:placetype":"venue"
},
  "geometry": {"coordinates":[-76.01927947999999,44.8891181946],"type":"Point"}
}