{
  "type": "Feature",
  "properties": {
    "addr:full":"8609 Rue DE Grosbois Montreal QC H1K 2G4",
    "addr:housenumber":"8609",
    "addr:postcode":"h1k 2g4",
    "addr:street":"Rue De Grosbois",
    "iso:country":"CA",
    "sg:address":"8609 Rue DE Grosbois",
    "sg:city":"Montreal",
    "sg:classifiers":[
        {
            "category":"Personal",
            "subcategory":"Beauty Salon",
            "type":"Services"
        }
    ],
    "sg:phone":"+1 514 352 7690",
    "sg:postcode":"H1K 2G4",
    "sg:province":"QC",
    "wof:name":"Salon DE Coiffure St Justin",
    "wof:placetype":"venue"
},
  "geometry": {"coordinates":[-73.53507995610001,45.6046791077],"type":"Point"}
}