{
  "type": "Feature",
  "properties": {
    "addr:full":"Nanaimo BC V9S 5L6",
    "addr:postcode":"v9s 5l6",
    "iso:country":"CA",
    "sg:city":"Nanaimo",
    "sg:classifiers":[
        {
            "category":"Banks & Credit Unions",
            "subcategory":"Bank",
            "type":"Services"
        }
    ],
    "sg:phone":"+1 250 754 7731",
    "sg:postcode":"V9S 5L6",
    "sg:province":"BC",
    "wof:name":"Td Canada Trust",
    "wof:placetype":"venue"
},
  "geometry": {"coordinates":[-123.953994751,49.1828117371],"type":"Point"}
}