{
  "type": "Feature",
  "properties": {
    "addr:full":"340 Rue Seigneuriale Beauport QC G1C 3P9",
    "addr:housenumber":"340",
    "addr:postcode":"qc g1c 3p9",
    "addr:street":"Rue Seigneuriale",
    "iso:country":"CA",
    "sg:address":"340 Rue Seigneuriale",
    "sg:city":"Beauport",
    "sg:classifiers":[
        {
            "category":"Real Estate",
            "subcategory":"Real Estate Agent",
            "type":"Services"
        }
    ],
    "sg:phone":"+1 418 661 8000",
    "sg:postcode":"G1C 3P9",
    "sg:province":"QC",
    "wof:name":"Capitale Cite Inc",
    "wof:placetype":"venue"
},
  "geometry": {"coordinates":[-71.2029495239,46.8815689087],"type":"Point"}
}