{
  "type": "Feature",
  "properties": {
    "addr:full":"403 Rue Du Pont Mont-Laurier QC J9L 2R6",
    "addr:housenumber":"403",
    "addr:postcode":"j9l 2r6",
    "addr:street":"Rue Du Pont",
    "iso:country":"CA",
    "sg:address":"403 Rue Du Pont",
    "sg:city":"Mont-Laurier",
    "sg:classifiers":[
        {
            "category":"Personal",
            "subcategory":"Beauty Salon",
            "type":"Services"
        }
    ],
    "sg:phone":"+1 819 623 3244",
    "sg:postcode":"J9L 2R6",
    "sg:province":"QC",
    "wof:name":"Escale Beaute",
    "wof:placetype":"venue"
},
  "geometry": {"coordinates":[-75.498901,46.550674],"type":"Point"}
}