{
  "type": "Feature",
  "properties": {
    "addr:full":"1708 Av Laurier E Montreal QC H2J 1J2",
    "addr:housenumber":"1708",
    "addr:postcode":"h2j 1j2",
    "addr:street":"Av Laurier E",
    "iso:country":"CA",
    "sg:address":"1708 Av Laurier E",
    "sg:city":"Montreal",
    "sg:classifiers":[
        {
            "category":"Restaurant",
            "type":"Food & Drink"
        }
    ],
    "sg:phone":"+1 514 598 1292",
    "sg:postcode":"H2J 1J2",
    "sg:province":"QC",
    "wof:name":"Restaurant Chez Mai Lan Enr",
    "wof:placetype":"venue"
},
  "geometry": {"coordinates":[-73.58158899999999,45.535557],"type":"Point"}
}