{
  "type": "Feature",
  "properties": {
    "addr:full":"525 Bernard Ave Kelowna BC V1Y 6N9",
    "addr:housenumber":"525",
    "addr:postcode":"v1y 6n9",
    "addr:street":"Bernard Ave",
    "iso:country":"CA",
    "sg:address":"525 Bernard Ave",
    "sg:city":"Kelowna",
    "sg:classifiers":[
        {
            "category":"Shopping",
            "subcategory":"Books",
            "type":"Retail Goods"
        }
    ],
    "sg:phone":"+1 250 762 3153",
    "sg:postcode":"V1Y 6N9",
    "sg:province":"BC",
    "sg:tags":[
        "food",
        "health",
        "diet"
    ],
    "wof:name":"Natural Rezources",
    "wof:placetype":"venue"
},
  "geometry": {"coordinates":[-119.49271400000001,49.886101],"type":"Point"}
}