{
  "type": "Feature",
  "properties": {
    "addr:full":"Penticton BC V2A 8N9",
    "addr:postcode":"v2a 8n9",
    "iso:country":"CA",
    "sg:city":"Penticton",
    "sg:classifiers":[
        {
            "category":"Manufacturing",
            "subcategory":"Tools & Machinery",
            "type":"Manufacturing & Wholesale Goods"
        }
    ],
    "sg:phone":"+1 250 492 7551",
    "sg:postcode":"V2A 8N9",
    "sg:province":"BC",
    "sg:tags":[
        "concrete",
        "cutting",
        "rental",
        "breaking"
    ],
    "wof:name":"Westminster Equipment Rentals",
    "wof:placetype":"venue"
},
  "geometry": {"coordinates":[-119.575378418,49.4790496826],"type":"Point"}
}