{
  "type": "Feature",
  "properties": {
    "iso:country":"CA",
    "sg:city":"Markham",
    "sg:classifiers":[
        {
            "category":"Taxi",
            "type":"Transportation"
        }
    ],
    "sg:phone":"+1 905 471 0101",
    "sg:postcode":"L3P 1Y7",
    "sg:province":"ON",
    "sg:tags":[
        "taxicab"
    ],
    "wof:name":"Welcome Taxi",
    "wof:placetype":"venue"
},
  "geometry": {"coordinates":[-79.280525,43.963902],"type":"Point"}
}