{
  "type": "Feature",
  "properties": {
    "addr:full":"5410 39 St Camrose AB T4V 4P4",
    "addr:housenumber":"5410",
    "addr:postcode":"t4v 4p4",
    "addr:street":"39 St",
    "iso:country":"CA",
    "sg:address":"5410 39 St",
    "sg:city":"Camrose",
    "sg:classifiers":[
        {
            "category":"Manufacturing",
            "subcategory":"Metals",
            "type":"Manufacturing & Wholesale Goods"
        }
    ],
    "sg:phone":"+1 780 679 6400",
    "sg:postcode":"T4V 4P4",
    "sg:province":"AB",
    "sg:tags":[
        "coating"
    ],
    "wof:name":"Shaw Pipe Protection",
    "wof:placetype":"venue"
},
  "geometry": {"coordinates":[-112.80643499999999,53.030434],"type":"Point"}
}