{
  "type": "Feature",
  "properties": {
    "iso:country":"CA",
    "sg:city":"Winnipeg",
    "sg:classifiers":[
        {
            "category":"Real Estate",
            "subcategory":"Real Estate Agent",
            "type":"Services"
        }
    ],
    "sg:phone":"+1 204 947 3477",
    "sg:postcode":"R3B 0S9",
    "sg:province":"MB",
    "wof:name":"Re Max",
    "wof:placetype":"venue"
},
  "geometry": {"coordinates":[-97.141785,49.897697],"type":"Point"}
}