{
  "type": "Feature",
  "properties": {
    "addr:full":"Hwy 16 & Hwy 34 Gladstone MB R0J 0T0",
    "addr:postcode":"r0j 0t0",
    "addr:street":"Hwy 16 & Hwy 34",
    "iso:country":"CA",
    "sg:address":"Hwy 16 & Hwy 34",
    "sg:city":"Gladstone",
    "sg:classifiers":[
        {
            "category":"Travel",
            "subcategory":"Hotels & Motels",
            "type":"Entertainment"
        }
    ],
    "sg:phone":"+1 204 385 2921",
    "sg:postcode":"R0J 0T0",
    "sg:province":"MB",
    "wof:name":"Welcomestop Motel",
    "wof:placetype":"venue"
},
  "geometry": {"coordinates":[-98.9507522583,50.2254219055],"type":"Point"}
}