{
  "type": "Feature",
  "properties": {
    "addr:full":"1040 Walker Lake Rd Lake of Bays ON P1H 2J6",
    "addr:housenumber":"1040",
    "addr:postcode":"p1h 2j6",
    "addr:street":"Walker Lake Rd",
    "iso:country":"CA",
    "sg:address":"1040 Walker Lake Rd",
    "sg:city":"Lake of Bays",
    "sg:classifiers":[
        {
            "category":"Travel",
            "subcategory":"Hotels & Motels",
            "type":"Entertainment"
        }
    ],
    "sg:phone":"+1 705 635 2473",
    "sg:postcode":"P1H 2J6",
    "sg:province":"ON",
    "sg:tags":[
        "resort"
    ],
    "wof:name":"Walker Lake Resort",
    "wof:placetype":"venue"
},
  "geometry": {"coordinates":[-79.079353,45.381283],"type":"Point"}
}