{
  "type": "Feature",
  "properties": {
    "iso:country":"CA",
    "sg:address":"Bella Bella Rd",
    "sg:city":"Bella Bella",
    "sg:classifiers":[
        {
            "category":"Organizations",
            "subcategory":"Professional Association",
            "type":"Services"
        }
    ],
    "sg:phone":"+1 250 957 2288",
    "sg:postcode":"V0T 1B0",
    "sg:province":"BC",
    "wof:name":"Heiltsuk Communication Channel",
    "wof:placetype":"venue"
},
  "geometry": {"coordinates":[-128.145141602,52.1656990051],"type":"Point"}
}