{
  "type": "Feature",
  "properties": {
    "addr:full":"Tofield AB T0B 4J0",
    "addr:postcode":"t0b 4j0",
    "iso:country":"CA",
    "sg:city":"Tofield",
    "sg:classifiers":[
        {
            "category":"Recreation",
            "type":"Entertainment"
        }
    ],
    "sg:phone":"+1 780 662 4011",
    "sg:postcode":"T0B 4J0",
    "sg:province":"AB",
    "sg:tags":[
        "club",
        "curling"
    ],
    "wof:name":"Tofield Curling Rink",
    "wof:placetype":"venue"
},
  "geometry": {"coordinates":[-112.66252899200001,53.3693008423],"type":"Point"}
}