{
  "type": "Feature",
  "properties": {
    "addr:full":"167 Brock St S Sarnia ON N7T 2W3",
    "addr:housenumber":"167",
    "addr:postcode":"n7t 2w3",
    "addr:street":"Brock St S",
    "iso:country":"CA",
    "sg:address":"167 Brock St S",
    "sg:city":"Sarnia",
    "sg:classifiers":[
        {
            "category":"Professional",
            "subcategory":"Art Services",
            "type":"Services"
        }
    ],
    "sg:phone":"+1 519 337 8189",
    "sg:postcode":"N7T 2W3",
    "sg:province":"ON",
    "sg:tags":[
        "graphic",
        "designer"
    ],
    "wof:name":"Formosa Graphics",
    "wof:placetype":"venue"
},
  "geometry": {"coordinates":[-82.4041900635,42.9695205688],"type":"Point"}
}