{
  "type": "Feature",
  "properties": {
    "iso:country":"CA",
    "sg:address":"237 Main St",
    "sg:city":"Delhi",
    "sg:classifiers":[
        {
            "category":"Insurance",
            "subcategory":"Insurance Agent",
            "type":"Services"
        }
    ],
    "sg:phone":"+1 519 582 1401",
    "sg:postcode":"N4B 2M4",
    "sg:province":"ON",
    "wof:name":"Mc Kay Financial Svc",
    "wof:placetype":"venue"
},
  "geometry": {"coordinates":[-80.49913787840001,42.8531913757],"type":"Point"}
}