{
  "type": "Feature",
  "properties": {
    "iso:country":"CA",
    "sg:address":"275 Rue Paradis",
    "sg:city":"Repentigny",
    "sg:classifiers":[
        {
            "category":"Personal",
            "type":"Services"
        }
    ],
    "sg:phone":"+1 450 582 0050",
    "sg:postcode":"J6A 8H2",
    "sg:province":"QC",
    "sg:tags":[
        "electrolysis"
    ],
    "wof:name":"Esthetique Louise Goyette",
    "wof:placetype":"venue"
},
  "geometry": {"coordinates":[-73.460236,45.753414],"type":"Point"}
}