{
  "type": "Feature",
  "properties": {
    "addr:full":"275 Rue Paradis Repentigny QC J6A 8H2",
    "addr:housenumber":"275",
    "addr:postcode":"j6a 8h2",
    "addr:street":"Rue Paradis",
    "iso:country":"CA",
    "sg:address":"275 Rue Paradis",
    "sg:city":"Repentigny",
    "sg:classifiers":[
        {
            "category":"Personal",
            "type":"Services"
        }
    ],
    "sg:phone":"+1 450 582 0050",
    "sg:postcode":"J6A 8H2",
    "sg:province":"QC",
    "sg:tags":[
        "electrolysis"
    ],
    "wof:name":"Esthetique Louise Goyette",
    "wof:placetype":"venue"
},
  "geometry": {"coordinates":[-73.46023599999999,45.753414],"type":"Point"}
}