{
  "type": "Feature",
  "properties": {
    "iso:country":"CA",
    "sg:address":"334 1st Ave",
    "sg:city":"Arborg",
    "sg:classifiers":[
        {
            "category":"Personal",
            "subcategory":"Beauty Salon",
            "type":"Services"
        }
    ],
    "sg:phone":"+1 204 376 2014",
    "sg:postcode":"R0C 0A0",
    "sg:province":"MB",
    "wof:name":"First Avenue Salon",
    "wof:placetype":"venue"
},
  "geometry": {"coordinates":[-97.2208099365,50.9080467224],"type":"Point"}
}