{
  "type": "Feature",
  "properties": {
    "addr:full":"Delta BC V4G 1A6",
    "addr:postcode":"v4g 1a6",
    "iso:country":"CA",
    "sg:city":"Delta",
    "sg:classifiers":[
        {
            "category":"Restaurant",
            "type":"Food & Drink"
        }
    ],
    "sg:phone":"+1 604 946 5144",
    "sg:postcode":"V4G 1A6",
    "sg:province":"BC",
    "wof:name":"Hadi's Restaurant",
    "wof:placetype":"venue"
},
  "geometry": {"coordinates":[-123.011566,49.139046],"type":"Point"}
}