{
  "type": "Feature",
  "properties": {
    "addr:full":"197 Bruce N Durham ON N0G 1R0",
    "addr:housenumber":"197",
    "addr:postcode":"n0g 1r0",
    "addr:street":"Bruce N",
    "iso:country":"CA",
    "sg:address":"197 Bruce N",
    "sg:city":"Durham",
    "sg:classifiers":[
        {
            "category":"Local Transit",
            "type":"Transportation"
        }
    ],
    "sg:phone":"+1 519 369 5230",
    "sg:postcode":"N0G 1R0",
    "sg:province":"ON",
    "sg:tags":[
        "taxicab",
        "airport"
    ],
    "wof:name":"Phil's Taxi",
    "wof:placetype":"venue"
},
  "geometry": {"coordinates":[-80.823296,44.177605],"type":"Point"}
}