{
  "type": "Feature",
  "properties": {
    "addr:full":"4505 Boul Industriel Sherbrooke QC J1L 2S9",
    "addr:housenumber":"4505",
    "addr:postcode":"j1l 2s9",
    "addr:street":"Boul Industriel",
    "iso:country":"CA",
    "sg:address":"4505 Boul Industriel",
    "sg:city":"Sherbrooke",
    "sg:classifiers":[
        {
            "category":"Utilities",
            "subcategory":"Mobile Phone",
            "type":"Services"
        }
    ],
    "sg:phone":"+1 819 563 0406",
    "sg:postcode":"J1L 2S9",
    "sg:province":"QC",
    "sg:tags":[
        "telephone",
        "cellular"
    ],
    "wof:name":"Gobeil & Filles",
    "wof:placetype":"venue"
},
  "geometry": {"coordinates":[-71.974602,45.395798],"type":"Point"}
}