{
  "type": "Feature",
  "properties": {
    "addr:full":"78 Thomas Windsor NS B0N 2T0",
    "addr:housenumber":"78",
    "addr:postcode":"b0n 2t0",
    "addr:street":"Thomas",
    "iso:country":"CA",
    "sg:address":"78 Thomas",
    "sg:city":"Windsor",
    "sg:classifiers":[
        {
            "category":"Recreation",
            "type":"Entertainment"
        }
    ],
    "sg:phone":"+1 902 798 2536",
    "sg:postcode":"B0N 2T0",
    "sg:province":"NS",
    "sg:tags":[
        "government",
        "hall",
        "auditorium"
    ],
    "wof:name":"Windsor Community Ctr",
    "wof:placetype":"venue"
},
  "geometry": {"coordinates":[-64.133064,44.992134],"type":"Point"}
}