{
  "type": "Feature",
  "properties": {
    "addr:full":"386 Division St Cobourg ON K9A 3R6",
    "addr:housenumber":"386",
    "addr:postcode":"k9a 3r6",
    "addr:street":"Division St",
    "iso:country":"CA",
    "sg:address":"386 Division St",
    "sg:city":"Cobourg",
    "sg:classifiers":[
        {
            "category":"Health Services",
            "subcategory":"Chiropractor",
            "type":"Services"
        }
    ],
    "sg:phone":"+1 905 372 2946",
    "sg:postcode":"K9A 3R6",
    "sg:province":"ON",
    "wof:name":"Bradford Chiropractic Clinic",
    "wof:placetype":"venue"
},
  "geometry": {"coordinates":[-78.16706848139999,43.9637870789],"type":"Point"}
}