{
  "type": "Feature",
  "properties": {
    "addr:full":"1853 Lawrence Ave E Scarborough ON M1R 2Y3",
    "addr:housenumber":"1853",
    "addr:postcode":"m1r 2y3",
    "addr:street":"Lawrence Ave E",
    "iso:country":"CA",
    "sg:address":"1853 Lawrence Ave E",
    "sg:city":"Scarborough",
    "sg:classifiers":[
        {
            "category":"Personal",
            "subcategory":"Beauty Salon",
            "type":"Services"
        }
    ],
    "sg:phone":"+1 416 750 1098",
    "sg:postcode":"M1R 2Y3",
    "sg:province":"ON",
    "sg:tags":[
        "manicuring"
    ],
    "wof:name":"Universal Nails",
    "wof:placetype":"venue"
},
  "geometry": {"coordinates":[-79.302933,43.74345],"type":"Point"}
}