{
  "type": "Feature",
  "properties": {
    "addr:full":"3700 Kempt Rd Halifax NS B3K 4X8",
    "addr:housenumber":"3700",
    "addr:postcode":"b3k 4x8",
    "addr:street":"Kempt Rd",
    "iso:country":"CA",
    "sg:address":"3700 Kempt Rd",
    "sg:city":"Halifax",
    "sg:classifiers":[
        {
            "category":"Organizations",
            "subcategory":"Labor Organization",
            "type":"Services"
        }
    ],
    "sg:phone":"+1 902 455 1095",
    "sg:postcode":"B3K 4X8",
    "sg:province":"NS",
    "wof:name":"Service Employees Intl Union",
    "wof:placetype":"venue"
},
  "geometry": {"coordinates":[-63.6179847717,44.6623725891],"type":"Point"}
}