{
  "type": "Feature",
  "properties": {
    "iso:country":"CA",
    "sg:city":"Baie-Comeau",
    "sg:classifiers":[
        {
            "category":"Personal",
            "subcategory":"Beauty Salon",
            "type":"Services"
        }
    ],
    "sg:phone":"+1 418 296 2388",
    "sg:postcode":"G4Z 1J8",
    "sg:province":"QC",
    "sg:tags":[
        "barber"
    ],
    "wof:name":"Salon Figaro",
    "wof:placetype":"venue"
},
  "geometry": {"coordinates":[-68.1514663696,49.2211761475],"type":"Point"}
}