{
  "type": "Feature",
  "properties": {
    "addr:full":"245 Coxwell Ave Toronto ON M4L 3B4",
    "addr:housenumber":"245",
    "addr:postcode":"m4l 3b4",
    "addr:street":"Coxwell Ave",
    "iso:country":"CA",
    "sg:address":"245 Coxwell Ave",
    "sg:city":"Toronto",
    "sg:classifiers":[
        {
            "category":"Professional",
            "subcategory":"Lawyer & Legal Services",
            "type":"Services"
        }
    ],
    "sg:phone":"+1 416 465 3561",
    "sg:postcode":"M4L 3B4",
    "sg:province":"ON",
    "sg:tags":[
        "attorney"
    ],
    "wof:name":"Peters & Kestelman",
    "wof:placetype":"venue"
},
  "geometry": {"coordinates":[-79.318962,43.672577],"type":"Point"}
}