{
  "type": "Feature",
  "properties": {
    "addr:full":"Paul Band Health Ctr Wabamun AB T0E 2K0",
    "addr:postcode":"t0e 2k0",
    "iso:country":"CA",
    "sg:address":"Paul Band Health Ctr",
    "sg:city":"Wabamun",
    "sg:classifiers":[
        {
            "category":"Government",
            "subcategory":"Office",
            "type":"Public Place"
        }
    ],
    "sg:phone":"+1 780 892 2141",
    "sg:postcode":"T0E 2K0",
    "sg:province":"AB",
    "wof:name":"Health Canada",
    "wof:placetype":"venue"
},
  "geometry": {"coordinates":[-114.468407,53.559334],"type":"Point"}
}