{
  "type": "Feature",
  "properties": {
    "addr:full":"St George MB R0E 1V0",
    "addr:postcode":"r0e 1v0",
    "iso:country":"CA",
    "sg:city":"St George",
    "sg:classifiers":[
        {
            "category":"Professional",
            "subcategory":"Management & Consulting",
            "type":"Services"
        }
    ],
    "sg:phone":"+1 204 367 8392",
    "sg:postcode":"R0E 1V0",
    "sg:province":"MB",
    "sg:tags":[
        "planner"
    ],
    "wof:name":"Winnipeg River Planning Dist",
    "wof:placetype":"venue"
},
  "geometry": {"coordinates":[-96.14991000000001,50.540016],"type":"Point"}
}