{
  "type": "Feature",
  "properties": {
    "addr:full":"Brooks AB T1R 0G9",
    "addr:postcode":"t1r 0g9",
    "iso:country":"CA",
    "sg:city":"Brooks",
    "sg:classifiers":[
        {
            "category":"Personal",
            "subcategory":"Beauty Salon",
            "type":"Services"
        }
    ],
    "sg:phone":"+1 403 362 5286",
    "sg:postcode":"T1R 0G9",
    "sg:province":"AB",
    "wof:name":"New World of Beauty Ltd",
    "wof:placetype":"venue"
},
  "geometry": {"coordinates":[-111.89447,50.563965],"type":"Point"}
}