{
  "type": "Feature",
  "properties": {
    "addr:full":"456 St Clair St Chatham ON N7L 3K7",
    "addr:housenumber":"456",
    "addr:postcode":"n7l 3k7",
    "addr:street":"St Clair St",
    "iso:country":"CA",
    "sg:address":"456 St Clair St",
    "sg:city":"Chatham",
    "sg:classifiers":[
        {
            "category":"Shopping",
            "subcategory":"Used Merchandise",
            "type":"Retail Goods"
        }
    ],
    "sg:phone":"+1 519 358 7299",
    "sg:postcode":"N7L 3K7",
    "sg:province":"ON",
    "sg:tags":[
        "second",
        "store",
        "hand"
    ],
    "wof:name":"Salvation Army Thrift Store",
    "wof:placetype":"venue"
},
  "geometry": {"coordinates":[-82.2037353516,42.4178695679],"type":"Point"}
}