{
  "type": "Feature",
  "properties": {
    "addr:full":"250 Laurier Blvd Brockville ON K6V 5V5",
    "addr:housenumber":"250",
    "addr:postcode":"k6v 5v5",
    "addr:street":"Laurier Blvd",
    "iso:country":"CA",
    "sg:address":"250 Laurier Blvd",
    "sg:city":"Brockville",
    "sg:classifiers":[
        {
            "category":"Freight",
            "type":"Transportation"
        }
    ],
    "sg:phone":"+1 613 498 5744",
    "sg:postcode":"K6V 5V5",
    "sg:province":"ON",
    "sg:tags":[
        "trucking"
    ],
    "wof:name":"Ryder Integrated Logistics",
    "wof:placetype":"venue"
},
  "geometry": {"coordinates":[-75.691261,44.620628],"type":"Point"}
}