{
  "type": "Feature",
  "properties": {
    "addr:full":"44 Mcarthur Ave Lac Du Bonnet MB R0E 1A0",
    "addr:housenumber":"44",
    "addr:postcode":"r0e 1a0",
    "addr:street":"Mcarthur Ave",
    "iso:country":"CA",
    "sg:address":"44 Mcarthur Ave",
    "sg:city":"Lac Du Bonnet",
    "sg:classifiers":[
        {
            "category":"Restaurant",
            "type":"Food & Drink"
        }
    ],
    "sg:phone":"+1 204 345 2433",
    "sg:postcode":"R0E 1A0",
    "sg:province":"MB",
    "wof:name":"Chicken Chef",
    "wof:placetype":"venue"
},
  "geometry": {"coordinates":[-96.06196594239999,50.2510490417],"type":"Point"}
}