{
  "type": "Feature",
  "properties": {
    "addr:full":"930 Bay Ave Kelowna BC V1Y 7K4",
    "addr:housenumber":"930",
    "addr:postcode":"v1y 7k4",
    "addr:street":"Bay Ave",
    "iso:country":"CA",
    "sg:address":"930 Bay Ave",
    "sg:city":"Kelowna",
    "sg:classifiers":[
        {
            "category":"Wholesale",
            "subcategory":"Scrap",
            "type":"Manufacturing & Wholesale Goods"
        }
    ],
    "sg:phone":"+1 250 763 6502",
    "sg:postcode":"V1Y 7K4",
    "sg:province":"BC",
    "sg:tags":[
        "metal",
        "iron"
    ],
    "wof:name":"Knox Mountain Metals Inc",
    "wof:placetype":"venue"
},
  "geometry": {"coordinates":[-119.482719,49.899189],"type":"Point"}
}