{
  "type": "Feature",
  "properties": {
    "iso:country":"CA",
    "sg:address":"7195 Torbram Rd # 1",
    "sg:city":"Mississauga",
    "sg:classifiers":[
        {
            "category":"Food & Beverages",
            "subcategory":"Specialty",
            "type":"Retail Goods"
        }
    ],
    "sg:phone":"+1 905 673 5465",
    "sg:postcode":"L4T 4G3",
    "sg:province":"ON",
    "sg:tags":[
        "tea",
        "coffee"
    ],
    "wof:name":"Coffee & Lunch",
    "wof:placetype":"venue"
},
  "geometry": {"coordinates":[-79.65850830079999,43.6986541748],"type":"Point"}
}