{
  "type": "Feature",
  "properties": {
    "addr:full":"2449 Cross Rd Nanoose Bay BC V9P 9E6",
    "addr:housenumber":"2449",
    "addr:postcode":"v9p 9e6",
    "addr:street":"Cross Rd",
    "iso:country":"CA",
    "sg:address":"2449 Cross Rd",
    "sg:city":"Nanoose Bay",
    "sg:classifiers":[
        {
            "category":"Building & Trades",
            "subcategory":"Construction",
            "type":"Services"
        }
    ],
    "sg:phone":"+1 250 468 1443",
    "sg:postcode":"V9P 9E6",
    "sg:province":"BC",
    "sg:tags":[
        "general",
        "contractor"
    ],
    "wof:name":"Smitty Construction Ltd",
    "wof:placetype":"venue"
},
  "geometry": {"coordinates":[-124.19425200000001,49.277493],"type":"Point"}
}