{
  "type": "Feature",
  "properties": {
    "addr:full":"100 Mile House BC V0K 2E0",
    "addr:postcode":"v0k 2e0",
    "iso:country":"CA",
    "sg:city":"100 Mile House",
    "sg:classifiers":[
        {
            "category":"Travel",
            "subcategory":"Hotels & Motels",
            "type":"Entertainment"
        }
    ],
    "sg:phone":"+1 250 395 2211",
    "sg:postcode":"V0K 2E0",
    "sg:province":"BC",
    "wof:name":"Lakewood Inn",
    "wof:placetype":"venue"
},
  "geometry": {"coordinates":[-121.391159058,51.3140258789],"type":"Point"}
}