{
  "type": "Feature",
  "properties": {
    "iso:country":"CA",
    "sg:address":"310 Rue DE L'Anse",
    "sg:city":"Saint-Victor",
    "sg:classifiers":[
        {
            "category":"Personal",
            "subcategory":"Beauty Salon",
            "type":"Services"
        }
    ],
    "sg:phone":"+1 418 588 6598",
    "sg:postcode":"G0M 2B0",
    "sg:province":"QC",
    "wof:name":"Salon Primeur Elle & Lui",
    "wof:placetype":"venue"
},
  "geometry": {"coordinates":[-70.9002151489,46.1463317871],"type":"Point"}
}