{
  "type": "Feature",
  "properties": {
    "addr:full":"3621 Dufferin St North York ON M3K 1N5",
    "addr:housenumber":"3621",
    "addr:postcode":"m3k 1n5",
    "addr:street":"Dufferin St",
    "iso:country":"CA",
    "sg:address":"3621 Dufferin St",
    "sg:city":"North York",
    "sg:classifiers":[
        {
            "category":"Government",
            "subcategory":"Office",
            "type":"Public Place"
        }
    ],
    "sg:phone":"+1 416 373 6477",
    "sg:postcode":"M3K 1N5",
    "sg:province":"ON",
    "wof:name":"Canada Militia Denison Armory",
    "wof:placetype":"venue"
},
  "geometry": {"coordinates":[-79.458527,43.731346],"type":"Point"}
}