{
  "type": "Feature",
  "properties": {
    "addr:full":"100 Rue Caouette O Thetford Mines QC G6G 7M7",
    "addr:housenumber":"100",
    "addr:postcode":"g6g 7m7",
    "addr:street":"Rue Caouette O",
    "iso:country":"CA",
    "sg:address":"100 Rue Caouette O",
    "sg:city":"Thetford Mines",
    "sg:classifiers":[
        {
            "category":"Social Services",
            "type":"Services"
        }
    ],
    "sg:phone":"+1 418 335 3529",
    "sg:postcode":"G6G 7M7",
    "sg:province":"QC",
    "sg:tags":[
        "organization",
        "welfare"
    ],
    "wof:name":"Domremy",
    "wof:placetype":"venue"
},
  "geometry": {"coordinates":[-71.3068313599,46.0924415588],"type":"Point"}
}