{
  "type": "Feature",
  "properties": {
    "addr:full":"200 Rue Paul Aime Hudon Saint-Honore-DE-Chicoutimi QC G0V 1L0",
    "addr:housenumber":"200",
    "addr:postcode":"g0v 1l0",
    "addr:street":"Rue Paul Aime Hudon Saint-Honore-De-Chicoutimi",
    "iso:country":"CA",
    "sg:address":"200 Rue Paul Aime Hudon",
    "sg:city":"Saint-Honore-DE-Chicoutimi",
    "sg:classifiers":[
        {
            "category":"Education",
            "subcategory":"School",
            "type":"Public Place"
        }
    ],
    "sg:phone":"+1 418 673 3383",
    "sg:postcode":"G0V 1L0",
    "sg:province":"QC",
    "wof:name":"Ecole LA Source",
    "wof:placetype":"venue"
},
  "geometry": {"coordinates":[-71.0613937378,48.428943634],"type":"Point"}
}