{
  "type": "Feature",
  "properties": {
    "addr:full":"1273 129A St Surrey BC V4A 3Y3",
    "addr:housenumber":"1273",
    "addr:postcode":"v4a 3y3",
    "addr:street":"129A St",
    "iso:country":"CA",
    "sg:address":"1273 129A St",
    "sg:city":"Surrey",
    "sg:classifiers":[
        {
            "category":"Professional",
            "subcategory":"Management & Consulting",
            "type":"Services"
        }
    ],
    "sg:phone":"+1 604 536 0281",
    "sg:postcode":"V4A 3Y3",
    "sg:province":"BC",
    "sg:tags":[
        "consultant",
        "relation",
        "business",
        "labor"
    ],
    "wof:name":"Thorne Industrial Relations",
    "wof:placetype":"venue"
},
  "geometry": {"coordinates":[-122.830215,49.105179],"type":"Point"}
}