{
  "type": "Feature",
  "properties": {
    "iso:country":"CA",
    "sg:address":"50 Dexter Dr",
    "sg:city":"Saint John",
    "sg:classifiers":[
        {
            "category":"Organizations",
            "subcategory":"Religious Organization",
            "type":"Services"
        }
    ],
    "sg:phone":"+1 506 672 3320",
    "sg:postcode":"E2M 4M4",
    "sg:province":"NB",
    "sg:tags":[
        "church"
    ],
    "wof:name":"St Mark's United Church",
    "wof:placetype":"venue"
},
  "geometry": {"coordinates":[-66.1056213379,45.2534790039],"type":"Point"}
}