{
  "type": "Feature",
  "properties": {
    "addr:full":"121 East Dr Summerside PE C1N 4E3",
    "addr:housenumber":"121",
    "addr:postcode":"c1n 4e3",
    "addr:street":"East Dr",
    "iso:country":"CA",
    "sg:address":"121 East Dr",
    "sg:city":"Summerside",
    "sg:classifiers":[
        {
            "category":"Social Services",
            "type":"Services"
        }
    ],
    "sg:phone":"+1 902 436 9380",
    "sg:postcode":"C1N 4E3",
    "sg:province":"PE",
    "sg:tags":[
        "organization",
        "welfare"
    ],
    "wof:name":"St Eleanors Lion Club",
    "wof:placetype":"venue"
},
  "geometry": {"coordinates":[-63.8066940308,46.4222106934],"type":"Point"}
}