{
  "type": "Feature",
  "properties": {
    "addr:full":"5055 Boul Des Gradins Quebec QC G2J 1E5",
    "addr:housenumber":"5055",
    "addr:postcode":"g2j 1e5",
    "addr:street":"Boul Des Gradins",
    "iso:country":"CA",
    "sg:address":"5055 Boul Des Gradins",
    "sg:city":"Quebec",
    "sg:classifiers":[
        {
            "category":"Autos & Motor Vehicles",
            "subcategory":"Automobile Sales",
            "type":"Retail Goods"
        }
    ],
    "sg:phone":"+1 418 626 8600",
    "sg:postcode":"G2J 1E5",
    "sg:province":"QC",
    "sg:tags":[
        "car",
        "dealer"
    ],
    "wof:name":"Kia Quebec",
    "wof:placetype":"venue"
},
  "geometry": {"coordinates":[-71.27196499999999,46.836708],"type":"Point"}
}