{
  "type": "Feature",
  "properties": {
    "iso:country":"CA",
    "sg:address":"5017 Boul Des Sources",
    "sg:city":"Pierrefonds",
    "sg:classifiers":[
        {
            "category":"Recreation",
            "subcategory":"Amusement Park",
            "type":"Entertainment"
        }
    ],
    "sg:phone":"+1 514 685 0704",
    "sg:postcode":"H8Y 3E3",
    "sg:province":"QC",
    "wof:name":"Billiard Shooters",
    "wof:placetype":"venue"
},
  "geometry": {"coordinates":[-73.82102966310001,45.5083045959],"type":"Point"}
}