{
  "type": "Feature",
  "properties": {
    "addr:full":"Vancouver BC V5L 2A8",
    "addr:postcode":"v5l 2a8",
    "iso:country":"CA",
    "sg:city":"Vancouver",
    "sg:classifiers":[
        {
            "category":"Wholesale",
            "subcategory":"Hardware",
            "type":"Manufacturing & Wholesale Goods"
        }
    ],
    "sg:phone":"+1 604 252 9600",
    "sg:postcode":"V5L 2A8",
    "sg:province":"BC",
    "sg:tags":[
        "water",
        "cooler",
        "fountain",
        "filter"
    ],
    "wof:name":"Canadian Mist Water",
    "wof:placetype":"venue"
},
  "geometry": {"coordinates":[-123.056557,49.27837],"type":"Point"}
}