{
  "type": "Feature",
  "properties": {
    "addr:full":"PO Box 86 Perryvale AB T0G 1T0",
    "addr:housenumber":"po box 86",
    "addr:postcode":"t0g 1t0",
    "addr:street":"Perryvale Ab",
    "iso:country":"CA",
    "sg:address":"PO Box 86",
    "sg:city":"Perryvale",
    "sg:classifiers":[
        {
            "category":"Freight",
            "type":"Transportation"
        }
    ],
    "sg:phone":"+1 780 698 2461",
    "sg:postcode":"T0G 1T0",
    "sg:province":"AB",
    "sg:tags":[
        "water",
        "hauling",
        "trucking"
    ],
    "wof:name":"White Thunder Trucking Ltd",
    "wof:placetype":"venue"
},
  "geometry": {"coordinates":[-113.38951110799999,54.4708709717],"type":"Point"}
}