{
  "type": "Feature",
  "properties": {
    "iso:country":"CA",
    "sg:address":"1095 Keith Rd W",
    "sg:city":"North Vancouver",
    "sg:classifiers":[
        {
            "category":"Travel",
            "subcategory":"Hotels & Motels",
            "type":"Entertainment"
        }
    ],
    "sg:phone":"+1 604 988 9629",
    "sg:postcode":"V7P 1Y6",
    "sg:province":"BC",
    "sg:tags":[
        "breakfast",
        "accommodation",
        "bed"
    ],
    "wof:name":"Cedar Hill Bed & Breakfast",
    "wof:placetype":"venue"
},
  "geometry": {"coordinates":[-123.091461182,49.3200912476],"type":"Point"}
}