{
  "type": "Feature",
  "properties": {
    "addr:full":"4228 Rue Boyer Montreal QC H2J 3C7",
    "addr:housenumber":"4228",
    "addr:postcode":"h2j 3c7",
    "addr:street":"Rue Boyer",
    "iso:country":"CA",
    "sg:address":"4228 Rue Boyer",
    "sg:city":"Montreal",
    "sg:classifiers":[
        {
            "category":"Professional",
            "subcategory":"Art Services",
            "type":"Services"
        }
    ],
    "sg:phone":"+1 514 598 9600",
    "sg:postcode":"H2J 3C7",
    "sg:province":"QC",
    "sg:tags":[
        "graphic",
        "designer"
    ],
    "wof:name":"Mj Changnon Design Inc",
    "wof:placetype":"venue"
},
  "geometry": {"coordinates":[-73.575729,45.525417],"type":"Point"}
}