{
  "type": "Feature",
  "properties": {
    "iso:country":"CA",
    "sg:address":"37 Pine",
    "sg:city":"Tatamagouche",
    "sg:classifiers":[
        {
            "category":"Organizations",
            "subcategory":"Religious Organization",
            "type":"Services"
        }
    ],
    "sg:phone":"+1 902 657 2748",
    "sg:postcode":"B0K 1V0",
    "sg:province":"NS",
    "sg:tags":[
        "church"
    ],
    "wof:name":"Sedgewick Mem Presbyterian Ch",
    "wof:placetype":"venue"
},
  "geometry": {"coordinates":[-63.290397644,45.7080497742],"type":"Point"}
}