{
  "type": "Feature",
  "properties": {
    "addr:full":"1710 Rue Beaudry # 30 Montreal QC H2L 3E7",
    "addr:housenumber":"1710",
    "addr:postcode":"h2l 3e7",
    "addr:street":"Rue Beaudry # 30",
    "iso:country":"CA",
    "sg:address":"1710 Rue Beaudry # 30",
    "sg:city":"Montreal",
    "sg:classifiers":[
        {
            "category":"Social Services",
            "type":"Services"
        }
    ],
    "sg:phone":"+1 514 528 9000",
    "sg:postcode":"H2L 3E7",
    "sg:province":"QC",
    "sg:tags":[
        "organization",
        "welfare"
    ],
    "wof:name":"Meta D'Ame",
    "wof:placetype":"venue"
},
  "geometry": {"coordinates":[-73.55909699999999,45.520187],"type":"Point"}
}