{
  "type": "Feature",
  "properties": {
    "addr:full":"2210 Rue Andre Brossard QC J4Z 2Z8",
    "addr:housenumber":"2210",
    "addr:postcode":"j4z 2z8",
    "addr:street":"Rue Andre",
    "iso:country":"CA",
    "sg:address":"2210 Rue Andre",
    "sg:city":"Brossard",
    "sg:classifiers":[
        {
            "category":"Organizations",
            "subcategory":"Non-profit Organization",
            "type":"Services"
        }
    ],
    "sg:phone":"+1 450 462 3330",
    "sg:postcode":"J4Z 2Z8",
    "sg:province":"QC",
    "sg:tags":[
        "charitable",
        "institution",
        "association"
    ],
    "wof:name":"Union Des Haitiens Du Quebec",
    "wof:placetype":"venue"
},
  "geometry": {"coordinates":[-73.46225699999999,45.4785],"type":"Point"}
}