{
  "type": "Feature",
  "properties": {
    "addr:full":"311 4 St S Lethbridge AB T1J 1Z9",
    "addr:housenumber":"311 4",
    "addr:postcode":"t1j 1z9",
    "addr:street":"St S",
    "iso:country":"CA",
    "sg:address":"311 4 St S",
    "sg:city":"Lethbridge",
    "sg:classifiers":[
        {
            "category":"Restaurant",
            "type":"Food & Drink"
        }
    ],
    "sg:phone":"+1 403 327 8382",
    "sg:postcode":"T1J 1Z9",
    "sg:province":"AB",
    "wof:name":"O-Sho Japanese Restaurant",
    "wof:placetype":"venue"
},
  "geometry": {"coordinates":[-112.841697693,49.6955070496],"type":"Point"}
}