{
  "type": "Feature",
  "properties": {
    "addr:full":"Chatsworth ON N0H 1G0",
    "addr:postcode":"n0h 1g0",
    "iso:country":"CA",
    "sg:city":"Chatsworth",
    "sg:classifiers":[
        {
            "category":"Retail",
            "subcategory":"Repair Shop",
            "type":"Services"
        }
    ],
    "sg:phone":"+1 519 374 1025",
    "sg:postcode":"N0H 1G0",
    "sg:province":"ON",
    "sg:tags":[
        "refrigerator",
        "refrigerating"
    ],
    "wof:name":"Arctic Refrigeration & Ac",
    "wof:placetype":"venue"
},
  "geometry": {"coordinates":[-80.8974075317,44.4536552429],"type":"Point"}
}