{
  "type": "Feature",
  "properties": {
    "addr:full":"127 Kingston Rd Toronto ON M4L 1T3",
    "addr:housenumber":"127",
    "addr:postcode":"m4l 1t3",
    "addr:street":"Kingston Rd",
    "iso:country":"CA",
    "sg:address":"127 Kingston Rd",
    "sg:city":"Toronto",
    "sg:classifiers":[
        {
            "category":"Professional",
            "subcategory":"Business Services",
            "type":"Services"
        }
    ],
    "sg:phone":"+1 416 698 8827",
    "sg:postcode":"M4L 1T3",
    "sg:province":"ON",
    "sg:tags":[
        "information",
        "referral"
    ],
    "wof:name":"Act Research",
    "wof:placetype":"venue"
},
  "geometry": {"coordinates":[-79.31092099999999,43.670101],"type":"Point"}
}