{
  "type": "Feature",
  "properties": {
    "addr:full":"5055 Rue DE Verdun Verdun QC H4G 1N5",
    "addr:housenumber":"5055",
    "addr:postcode":"h4g 1n5",
    "addr:street":"Rue De Verdun",
    "iso:country":"CA",
    "sg:address":"5055 Rue DE Verdun",
    "sg:city":"Verdun",
    "sg:classifiers":[
        {
            "category":"Restaurant",
            "type":"Food & Drink"
        }
    ],
    "sg:phone":"+1 514 767 3135",
    "sg:postcode":"H4G 1N5",
    "sg:province":"QC",
    "wof:name":"Milan Restaurant",
    "wof:placetype":"venue"
},
  "geometry": {"coordinates":[-73.572159,45.455898],"type":"Point"}
}