{
  "type": "Feature",
  "properties": {
    "addr:full":"614 First Ave Bassano AB T0J 0B0",
    "addr:housenumber":"614",
    "addr:postcode":"t0j 0b0",
    "addr:street":"First Ave",
    "iso:country":"CA",
    "sg:address":"614 First Ave",
    "sg:city":"Bassano",
    "sg:classifiers":[
        {
            "category":"Retail",
            "subcategory":"Repair Shop",
            "type":"Services"
        }
    ],
    "sg:phone":"+1 403 641 4472",
    "sg:postcode":"T0J 0B0",
    "sg:province":"AB",
    "sg:tags":[
        "welding"
    ],
    "wof:name":"Don's Welding",
    "wof:placetype":"venue"
},
  "geometry": {"coordinates":[-112.46472168,50.7856864929],"type":"Point"}
}