{
  "type": "Feature",
  "properties": {
    "addr:full":"430 Maclaren St Ottawa ON K2P 0M8",
    "addr:housenumber":"430",
    "addr:postcode":"k2p 0m8",
    "addr:street":"Maclaren St",
    "iso:country":"CA",
    "sg:address":"430 Maclaren St",
    "sg:city":"Ottawa",
    "sg:classifiers":[
        {
            "category":"Health Services",
            "subcategory":"Chiropractor",
            "type":"Services"
        }
    ],
    "sg:phone":"+1 613 235 6449",
    "sg:postcode":"K2P 0M8",
    "sg:province":"ON",
    "wof:name":"Mac Laren Street Chiropractic",
    "wof:placetype":"venue"
},
  "geometry": {"coordinates":[-75.697227,45.413982],"type":"Point"}
}