{
  "type": "Feature",
  "properties": {
    "addr:full":"224 Pembroke St W Pembroke ON K8A 5N2",
    "addr:housenumber":"224",
    "addr:postcode":"k8a 5n2",
    "addr:street":"Pembroke St W",
    "iso:country":"CA",
    "sg:address":"224 Pembroke St W",
    "sg:city":"Pembroke",
    "sg:classifiers":[
        {
            "category":"Government",
            "subcategory":"Office",
            "type":"Public Place"
        }
    ],
    "sg:phone":"+1 613 732 4903",
    "sg:postcode":"K8A 5N2",
    "sg:province":"ON",
    "wof:name":"Aide Juridique",
    "wof:placetype":"venue"
},
  "geometry": {"coordinates":[-77.1179885864,45.8246307373],"type":"Point"}
}