{
  "type": "Feature",
  "properties": {
    "addr:full":"RR 3 STN Main Ingersoll ON N5C 3J6",
    "addr:postcode":"n5c 3j6",
    "addr:street":"Rr 3 Stn Main",
    "iso:country":"CA",
    "sg:address":"RR 3 STN Main",
    "sg:city":"Ingersoll",
    "sg:classifiers":[
        {
            "category":"Building & Trades",
            "subcategory":"Construction",
            "type":"Services"
        }
    ],
    "sg:phone":"+1 519 425 0342",
    "sg:postcode":"N5C 3J6",
    "sg:province":"ON",
    "sg:tags":[
        "control",
        "erosion"
    ],
    "wof:name":"Mulchit",
    "wof:placetype":"venue"
},
  "geometry": {"coordinates":[-80.88385009770001,43.0381164551],"type":"Point"}
}