{
  "type": "Feature",
  "properties": {
    "addr:full":"Edmonton AB T6E 1X5",
    "addr:postcode":"t6e 1x5",
    "iso:country":"CA",
    "sg:city":"Edmonton",
    "sg:classifiers":[
        {
            "category":"Professional",
            "subcategory":"Lawyer & Legal Services",
            "type":"Services"
        }
    ],
    "sg:phone":"+1 780 439 3611",
    "sg:postcode":"T6E 1X5",
    "sg:province":"AB",
    "sg:tags":[
        "attorney"
    ],
    "wof:name":"Khullar, Ritu",
    "wof:placetype":"venue"
},
  "geometry": {"coordinates":[-113.498504639,53.5172080994],"type":"Point"}
}