{
  "type": "Feature",
  "properties": {
    "addr:full":"7555 51 St SE Calgary AB T2C 4A6",
    "addr:housenumber":"7555",
    "addr:postcode":"t2c 4a6",
    "addr:street":"51 St Se",
    "iso:country":"CA",
    "sg:address":"7555 51 St SE",
    "sg:city":"Calgary",
    "sg:classifiers":[
        {
            "category":"Manufacturing",
            "subcategory":"Metals",
            "type":"Manufacturing & Wholesale Goods"
        }
    ],
    "sg:phone":"+1 403 236 8022",
    "sg:postcode":"T2C 4A6",
    "sg:province":"AB",
    "sg:tags":[
        "steel"
    ],
    "wof:name":"Acropolis Steel Industries Ltd",
    "wof:placetype":"venue"
},
  "geometry": {"coordinates":[-113.960350037,50.9868354797],"type":"Point"}
}