{
  "type": "Feature",
  "properties": {
    "iso:country":"CA",
    "sg:address":"250 Taunton Rd E",
    "sg:city":"Oshawa",
    "sg:classifiers":[
        {
            "category":"Manufacturing",
            "subcategory":"Jewelry",
            "type":"Manufacturing & Wholesale Goods"
        }
    ],
    "sg:phone":"+1 905 579 3697",
    "sg:postcode":"L1G 7T1",
    "sg:province":"ON",
    "sg:tags":[
        "craftsman"
    ],
    "wof:name":"Mjeas Jewellers",
    "wof:placetype":"venue"
},
  "geometry": {"coordinates":[-78.8703918457,43.9350013733],"type":"Point"}
}