{
  "type": "Feature",
  "properties": {
    "iso:country":"CA",
    "sg:address":"465 Davis Dr",
    "sg:city":"Newmarket",
    "sg:classifiers":[
        {
            "category":"Government",
            "subcategory":"Office",
            "type":"Public Place"
        }
    ],
    "sg:phone":"+1 905 954 4700",
    "sg:postcode":"L3Y 7T9",
    "sg:province":"ON",
    "wof:name":"Central East Regeion Health",
    "wof:placetype":"venue"
},
  "geometry": {"coordinates":[-79.45945,44.059628],"type":"Point"}
}