{
  "type": "Feature",
  "properties": {
    "addr:full":"2850 Rue King E Fleurimont QC J1G 5H3",
    "addr:housenumber":"2850",
    "addr:postcode":"j1g 5h3",
    "addr:street":"Rue King E Fleurimont",
    "iso:country":"CA",
    "sg:address":"2850 Rue King E",
    "sg:city":"Fleurimont",
    "sg:classifiers":[
        {
            "category":"Wholesale",
            "subcategory":"Machinery & Supplies",
            "type":"Manufacturing & Wholesale Goods"
        }
    ],
    "sg:phone":"+1 819 821 3721",
    "sg:postcode":"J1G 5H3",
    "sg:province":"QC",
    "sg:tags":[
        "pulverizing",
        "crushing"
    ],
    "wof:name":"Construction A Boisvert Inc",
    "wof:placetype":"venue"
},
  "geometry": {"coordinates":[-71.830826,45.416058],"type":"Point"}
}