{
  "type": "Feature",
  "properties": {
    "addr:full":"2500 University Dr NW #48 Calgary AB T2N 1N4",
    "addr:housenumber":"2500",
    "addr:postcode":"t2n 1n4",
    "addr:street":"University Dr Nw # 48",
    "iso:country":"CA",
    "sg:address":"2500 University Dr NW #48",
    "sg:city":"Calgary",
    "sg:classifiers":[
        {
            "category":"Banks & Credit Unions",
            "subcategory":"Bank",
            "type":"Services"
        }
    ],
    "sg:phone":"+1 403 220 7335",
    "sg:postcode":"T2N 1N4",
    "sg:province":"AB",
    "wof:name":"Apex Credit Union",
    "wof:placetype":"venue"
},
  "geometry": {"coordinates":[-114.128471,51.074982],"type":"Point"}
}