{
  "type": "Feature",
  "properties": {
    "iso:country":"CA",
    "sg:address":"516 Lawrence Ave",
    "sg:city":"Kelowna",
    "sg:classifiers":[
        {
            "category":"Travel",
            "subcategory":"Hotels & Motels",
            "type":"Entertainment"
        }
    ],
    "sg:phone":"+1 250 860 5858",
    "sg:postcode":"V1Y 6L7",
    "sg:province":"BC",
    "wof:name":"Prestige Inns-Hotels & Resorts",
    "wof:placetype":"venue"
},
  "geometry": {"coordinates":[-119.492683411,49.8854827881],"type":"Point"}
}