{
  "type": "Feature",
  "properties": {
    "addr:full":"518 Main St N Dauphin MB R7N 1C9",
    "addr:housenumber":"518",
    "addr:postcode":"r7n 1c9",
    "addr:street":"Main St N Dauphin",
    "iso:country":"CA",
    "sg:address":"518 Main St N",
    "sg:city":"Dauphin",
    "sg:classifiers":[
        {
            "category":"Building & Trades",
            "subcategory":"Construction",
            "type":"Services"
        }
    ],
    "sg:phone":"+1 204 638 4237",
    "sg:postcode":"R7N 1C9",
    "sg:province":"MB",
    "sg:tags":[
        "home",
        "builder",
        "maker",
        "cabinet"
    ],
    "wof:name":"Korzenowsky Custom Carpentry",
    "wof:placetype":"venue"
},
  "geometry": {"coordinates":[-100.04586,51.152802],"type":"Point"}
}