{
  "type": "Feature",
  "properties": {
    "addr:full":"1250 Terwillegar Ave Oshawa ON L1J 7A5",
    "addr:housenumber":"1250",
    "addr:postcode":"l1j 7a5",
    "addr:street":"Terwillegar Ave",
    "iso:country":"CA",
    "sg:address":"1250 Terwillegar Ave",
    "sg:city":"Oshawa",
    "sg:classifiers":[
        {
            "category":"Manufacturing",
            "subcategory":"Rubber & Plastics",
            "type":"Manufacturing & Wholesale Goods"
        }
    ],
    "sg:phone":"+1 905 433 2550",
    "sg:postcode":"L1J 7A5",
    "sg:province":"ON",
    "wof:name":"Polymer Extrusions Inc",
    "wof:placetype":"venue"
},
  "geometry": {"coordinates":[-78.876183,43.856392],"type":"Point"}
}