{
  "type": "Feature",
  "properties": {
    "iso:country":"CA",
    "sg:address":"7820 Rue Marquette",
    "sg:city":"Montreal",
    "sg:classifiers":[
        {
            "category":"Health Services",
            "subcategory":"Doctor",
            "type":"Services"
        }
    ],
    "sg:phone":"+1 514 722 3506",
    "sg:postcode":"H2E 2E7",
    "sg:province":"QC",
    "sg:tags":[
        "clinic"
    ],
    "wof:name":"Clinique Dentaire Jeanne Mance",
    "wof:placetype":"venue"
},
  "geometry": {"coordinates":[-73.616165,45.55098],"type":"Point"}
}