{
  "type": "Feature",
  "properties": {
    "iso:country":"CA",
    "sg:address":"4 Cataraqui St",
    "sg:city":"Kingston",
    "sg:classifiers":[
        {
            "category":"Organizations",
            "subcategory":"Professional Association",
            "type":"Services"
        }
    ],
    "sg:phone":"+1 613 531 8292",
    "sg:postcode":"K7K 1Z7",
    "sg:province":"ON",
    "wof:name":"International Fiscal Assoc",
    "wof:placetype":"venue"
},
  "geometry": {"coordinates":[-76.48086547849999,44.2420082092],"type":"Point"}
}