{
  "type": "Feature",
  "properties": {
    "addr:full":"1304 Finlayson St LA Ronge SK S0J 1L0",
    "addr:housenumber":"1304",
    "addr:postcode":"s0j 1l0",
    "addr:street":"Finlayson St",
    "iso:country":"CA",
    "sg:address":"1304 Finlayson St",
    "sg:city":"LA Ronge",
    "sg:classifiers":[
        {
            "category":"Retail",
            "subcategory":"Auto Rental",
            "type":"Services"
        }
    ],
    "sg:phone":"+1 306 425 5218",
    "sg:postcode":"S0J 1L0",
    "sg:province":"SK",
    "sg:tags":[
        "renting",
        "leasing",
        "truck",
        "trailer"
    ],
    "wof:name":"U-Haul CO Ltd",
    "wof:placetype":"venue"
},
  "geometry": {"coordinates":[-105.295326,55.112495],"type":"Point"}
}