{
  "type": "Feature",
  "properties": {
    "addr:full":"212 Main Rd Marius MB R0H 0T0",
    "addr:housenumber":"212",
    "addr:postcode":"r0h 0t0",
    "addr:street":"Main Rd Marius",
    "iso:country":"CA",
    "sg:address":"212 Main Rd",
    "sg:city":"Marius",
    "sg:classifiers":[
        {
            "category":"Organizations",
            "subcategory":"Professional Association",
            "type":"Services"
        }
    ],
    "sg:phone":"+1 204 843 3276",
    "sg:postcode":"R0H 0T0",
    "sg:province":"MB",
    "sg:tags":[
        "information",
        "alcoholism",
        "treatment"
    ],
    "wof:name":"Addictions Preventions Program",
    "wof:placetype":"venue"
},
  "geometry": {"coordinates":[-98.6529846191,50.5493049622],"type":"Point"}
}