{
  "type": "Feature",
  "properties": {
    "addr:full":"96 Glendower Circt Scarborough ON M1T 2Z4",
    "addr:housenumber":"96",
    "addr:postcode":"m1t 2z4",
    "addr:street":"Glendower Circt",
    "iso:country":"CA",
    "sg:address":"96 Glendower Circt",
    "sg:city":"Scarborough",
    "sg:classifiers":[
        {
            "category":"Home & Garden",
            "subcategory":"Household Appliances",
            "type":"Retail Goods"
        }
    ],
    "sg:phone":"+1 416 292 9063",
    "sg:postcode":"M1T 2Z4",
    "sg:province":"ON",
    "wof:name":"Dragon Appliance Svc",
    "wof:placetype":"venue"
},
  "geometry": {"coordinates":[-79.3037185669,43.7972984314],"type":"Point"}
}