{
  "type": "Feature",
  "properties": {
    "addr:full":"721 9 Ave SE High River AB T1V 1K5",
    "addr:housenumber":"721",
    "addr:postcode":"t1v 1k5",
    "addr:street":"9 Ave Se",
    "iso:country":"CA",
    "sg:address":"721 9 Ave SE",
    "sg:city":"High River",
    "sg:classifiers":[
        {
            "category":"Building & Trades",
            "subcategory":"Electrical",
            "type":"Services"
        }
    ],
    "sg:phone":"+1 403 652 1849",
    "sg:postcode":"T1V 1K5",
    "sg:province":"AB",
    "sg:tags":[
        "electric",
        "contractor"
    ],
    "wof:name":"Ace Electric Svc",
    "wof:placetype":"venue"
},
  "geometry": {"coordinates":[-113.856239,50.575001],"type":"Point"}
}