{
  "type": "Feature",
  "properties": {
    "addr:full":"Edmonton AB T5J 3Y2",
    "addr:postcode":"t5j 3y2",
    "iso:country":"CA",
    "sg:city":"Edmonton",
    "sg:classifiers":[
        {
            "category":"Professional",
            "subcategory":"Lawyer & Legal Services",
            "type":"Services"
        }
    ],
    "sg:phone":"+1 780 423 5730",
    "sg:postcode":"T5J 3Y2",
    "sg:province":"AB",
    "sg:tags":[
        "attorney"
    ],
    "wof:name":"Romanko, Bogumil F QC",
    "wof:placetype":"venue"
},
  "geometry": {"coordinates":[-113.49393499999999,53.542587],"type":"Point"}
}