{
  "type": "Feature",
  "properties": {
    "addr:full":"Kelowna BC V1Y 9N1",
    "addr:postcode":"v1y 9n1",
    "iso:country":"CA",
    "sg:city":"Kelowna",
    "sg:classifiers":[
        {
            "category":"Government",
            "subcategory":"Office",
            "type":"Public Place"
        }
    ],
    "sg:phone":"+1 250 868 7788",
    "sg:postcode":"V1Y 9N1",
    "sg:province":"BC",
    "sg:tags":[
        "health"
    ],
    "wof:name":"BC Mental Health",
    "wof:placetype":"venue"
},
  "geometry": {"coordinates":[-119.49374400000001,49.890549],"type":"Point"}
}