{
  "type": "Feature",
  "properties": {
    "addr:full":"545 Av Delmar Pointe-Claire QC H9R 4A7",
    "addr:housenumber":"545",
    "addr:postcode":"h9r 4a7",
    "addr:street":"Av Delmar",
    "iso:country":"CA",
    "sg:address":"545 Av Delmar",
    "sg:city":"Pointe-Claire",
    "sg:classifiers":[
        {
            "category":"Professional",
            "subcategory":"Advertising",
            "type":"Services"
        }
    ],
    "sg:phone":"+1 514 426 4468",
    "sg:postcode":"H9R 4A7",
    "sg:province":"QC",
    "sg:tags":[
        "mail"
    ],
    "wof:name":"Econo Plus",
    "wof:placetype":"venue"
},
  "geometry": {"coordinates":[-73.804337,45.469021],"type":"Point"}
}