{
  "type": "Feature",
  "properties": {
    "addr:full":"386 Rogers St Peterborough ON K9H 1W7",
    "addr:housenumber":"386",
    "addr:postcode":"k9h 1w7",
    "addr:street":"Rogers St",
    "iso:country":"CA",
    "sg:address":"386 Rogers St",
    "sg:city":"Peterborough",
    "sg:classifiers":[
        {
            "category":"Organizations",
            "subcategory":"Religious Organization",
            "type":"Services"
        }
    ],
    "sg:phone":"+1 705 742 5466",
    "sg:postcode":"K9H 1W7",
    "sg:province":"ON",
    "sg:tags":[
        "church"
    ],
    "wof:name":"Immaculate Conception",
    "wof:placetype":"venue"
},
  "geometry": {"coordinates":[-78.306839,44.306313],"type":"Point"}
}