{
  "type": "Feature",
  "properties": {
    "addr:full":"6161 Thorold Stone Rd Niagara Falls ON L2J 1A4",
    "addr:housenumber":"6161",
    "addr:postcode":"l2j 1a4",
    "addr:street":"Thorold Stone Rd",
    "iso:country":"CA",
    "sg:address":"6161 Thorold Stone Rd",
    "sg:city":"Niagara Falls",
    "sg:classifiers":[
        {
            "category":"Shopping",
            "subcategory":"Gifts & Souvenirs",
            "type":"Retail Goods"
        }
    ],
    "sg:phone":"+1 905 374 2641",
    "sg:postcode":"L2J 1A4",
    "sg:province":"ON",
    "sg:tags":[
        "party",
        "supply"
    ],
    "wof:name":"Party Connection",
    "wof:placetype":"venue"
},
  "geometry": {"coordinates":[-79.0978546143,43.1154022217],"type":"Point"}
}