{
  "type": "Feature",
  "properties": {
    "addr:full":"2409 139 Rte Saint-Nicephore QC J2A 1Z1",
    "addr:housenumber":"2409",
    "addr:postcode":"j2a 1z1",
    "addr:street":"139 Rte Saint-Nicephore",
    "iso:country":"CA",
    "sg:address":"2409 139 Rte",
    "sg:city":"Saint-Nicephore",
    "sg:classifiers":[
        {
            "category":"Retail",
            "subcategory":"Repair Shop",
            "type":"Services"
        }
    ],
    "sg:phone":"+1 819 478 5467",
    "sg:postcode":"J2A 1Z1",
    "sg:province":"QC",
    "sg:tags":[
        "welding"
    ],
    "wof:name":"Ateliers Gagne Enr",
    "wof:placetype":"venue"
},
  "geometry": {"coordinates":[-72.4245605469,45.8255004883],"type":"Point"}
}