{
  "type": "Feature",
  "properties": {
    "addr:full":"8867 Glover Rd Langley BC V1M 2S1",
    "addr:housenumber":"8867",
    "addr:postcode":"v1m 2s1",
    "addr:street":"Glover Rd",
    "iso:country":"CA",
    "sg:address":"8867 Glover Rd",
    "sg:city":"Langley",
    "sg:classifiers":[
        {
            "category":"Professional",
            "subcategory":"Management & Consulting",
            "type":"Services"
        }
    ],
    "sg:phone":"+1 604 888 7663",
    "sg:postcode":"V1M 2S1",
    "sg:province":"BC",
    "sg:tags":[
        "roofing",
        "consultant"
    ],
    "wof:name":"Roof Tech 2000 Consultants",
    "wof:placetype":"venue"
},
  "geometry": {"coordinates":[-122.584778,49.164085],"type":"Point"}
}