{
  "type": "Feature",
  "properties": {
    "addr:full":"2338 Hurontario St # 201 Mississauga ON L5B 1N1",
    "addr:housenumber":"2338",
    "addr:postcode":"l5b 1n1",
    "addr:street":"Hurontario St # 201",
    "iso:country":"CA",
    "sg:address":"2338 Hurontario St # 201",
    "sg:city":"Mississauga",
    "sg:classifiers":[
        {
            "category":"Health Services",
            "subcategory":"Doctor",
            "type":"Services"
        }
    ],
    "sg:phone":"+1 905 281 9100",
    "sg:postcode":"L5B 1N1",
    "sg:province":"ON",
    "sg:tags":[
        "physician",
        "surgeon"
    ],
    "wof:name":"Hurontario Medical Clinic",
    "wof:placetype":"venue"
},
  "geometry": {"coordinates":[-79.6091766357,43.5750045776],"type":"Point"}
}