{
  "type": "Feature",
  "properties": {
    "addr:full":"4353 Rue Sainte-Catherine E Montreal QC H1V 1Y2",
    "addr:housenumber":"4353",
    "addr:postcode":"h1v 1y2",
    "addr:street":"Rue Sainte-Catherine E",
    "iso:country":"CA",
    "sg:address":"4353 Rue Sainte-Catherine E",
    "sg:city":"Montreal",
    "sg:classifiers":[
        {
            "category":"Cinema",
            "subcategory":"Movie Theater",
            "type":"Entertainment"
        }
    ],
    "sg:phone":"+1 514 253 8974",
    "sg:postcode":"H1V 1Y2",
    "sg:province":"QC",
    "wof:name":"Salle Fred-Barry",
    "wof:placetype":"venue"
},
  "geometry": {"coordinates":[-73.53374481199999,45.5514526367],"type":"Point"}
}