{
  "type": "Feature",
  "properties": {
    "addr:full":"2106 Rue Jean-Talon E Montreal QC H2E 1V3",
    "addr:housenumber":"2106",
    "addr:postcode":"h2e 1v3",
    "addr:street":"Rue Jean-Talon E",
    "iso:country":"CA",
    "sg:address":"2106 Rue Jean-Talon E",
    "sg:city":"Montreal",
    "sg:classifiers":[
        {
            "category":"Restaurant",
            "type":"Food & Drink"
        }
    ],
    "sg:phone":"+1 514 721 2846",
    "sg:postcode":"H2E 1V3",
    "sg:province":"QC",
    "sg:tags":[
        "parlor",
        "ice",
        "cream"
    ],
    "wof:name":"Restaurant Deli Delicieux",
    "wof:placetype":"venue"
},
  "geometry": {"coordinates":[-73.60481299999999,45.550304],"type":"Point"}
}