{
  "type": "Feature",
  "properties": {
    "addr:full":"Delta BC V4C 6R2",
    "addr:postcode":"v4c 6r2",
    "iso:country":"CA",
    "sg:city":"Delta",
    "sg:classifiers":[
        {
            "category":"Manufacturing",
            "subcategory":"Tools & Machinery",
            "type":"Manufacturing & Wholesale Goods"
        }
    ],
    "sg:phone":"+1 604 594 4499",
    "sg:postcode":"V4C 6R2",
    "sg:province":"BC",
    "sg:tags":[
        "equipment",
        "hospital",
        "pharmacy"
    ],
    "wof:name":"Delta Prescription Clinic",
    "wof:placetype":"venue"
},
  "geometry": {"coordinates":[-122.890511,49.156517],"type":"Point"}
}