{
  "type": "Feature",
  "properties": {
    "addr:full":"549 Boul Samson Laval QC H7X 1J5",
    "addr:housenumber":"549",
    "addr:postcode":"h7x 1j5",
    "addr:street":"Boul Samson",
    "iso:country":"CA",
    "sg:address":"549 Boul Samson",
    "sg:city":"Laval",
    "sg:classifiers":[
        {
            "category":"Cinema",
            "subcategory":"Movie Rental",
            "type":"Entertainment"
        }
    ],
    "sg:phone":"+1 450 969 3493",
    "sg:postcode":"H7X 1J5",
    "sg:province":"QC",
    "sg:tags":[
        "leasing",
        "video",
        "disc",
        "tape"
    ],
    "wof:name":"Video Boulevard Enr",
    "wof:placetype":"venue"
},
  "geometry": {"coordinates":[-73.81144714360001,45.526725769],"type":"Point"}
}