{
  "type": "Feature",
  "properties": {
    "addr:full":"351 Peel St Collingwood ON L9Y 3W5",
    "addr:housenumber":"351",
    "addr:postcode":"l9y 3w5",
    "addr:street":"Peel St",
    "iso:country":"CA",
    "sg:address":"351 Peel St",
    "sg:city":"Collingwood",
    "sg:classifiers":[
        {
            "category":"Building & Trades",
            "subcategory":"Construction",
            "type":"Services"
        }
    ],
    "sg:phone":"+1 705 445 9879",
    "sg:postcode":"L9Y 3W5",
    "sg:province":"ON",
    "sg:tags":[
        "general",
        "contractor"
    ],
    "wof:name":"Ken Wilson Roofing",
    "wof:placetype":"venue"
},
  "geometry": {"coordinates":[-80.204514,44.497471],"type":"Point"}
}