{
  "type": "Feature",
  "properties": {
    "addr:full":"Montreal QC H3A 3A2",
    "addr:postcode":"h3a 3a2",
    "iso:country":"CA",
    "sg:city":"Montreal",
    "sg:classifiers":[
        {
            "category":"Professional",
            "subcategory":"Lawyer & Legal Services",
            "type":"Services"
        }
    ],
    "sg:phone":"+1 514 868 9595",
    "sg:postcode":"H3A 3A2",
    "sg:province":"QC",
    "sg:tags":[
        "attorney"
    ],
    "wof:name":"Drolet-Savoie, Madelaine",
    "wof:placetype":"venue"
},
  "geometry": {"coordinates":[-73.57352400000001,45.502235],"type":"Point"}
}