{
  "type": "Feature",
  "properties": {
    "addr:full":"140 Hespeler Rd Cambridge ON N1R 3H2",
    "addr:housenumber":"140",
    "addr:postcode":"n1r 3h2",
    "addr:street":"Hespeler Rd",
    "iso:country":"CA",
    "sg:address":"140 Hespeler Rd",
    "sg:city":"Cambridge",
    "sg:classifiers":[
        {
            "category":"Shopping",
            "subcategory":"Clothing, Apparel, & Fashions",
            "type":"Retail Goods"
        }
    ],
    "sg:phone":"+1 519 624 2076",
    "sg:postcode":"N1R 3H2",
    "sg:province":"ON",
    "wof:name":"Caesar's Closet",
    "wof:placetype":"venue"
},
  "geometry": {"coordinates":[-80.31945,43.379128],"type":"Point"}
}