{
  "type": "Feature",
  "properties": {
    "iso:country":"CA",
    "sg:address":"1219 Rue Marie-Anne E",
    "sg:city":"Montreal",
    "sg:classifiers":[
        {
            "category":"Retail",
            "subcategory":"Auto Repair",
            "type":"Services"
        }
    ],
    "sg:phone":"+1 514 524 9570",
    "sg:postcode":"H2J 2B9",
    "sg:province":"QC",
    "sg:tags":[
        "repairing",
        "automobile"
    ],
    "wof:name":"Garage Michel Gauthier Enr",
    "wof:placetype":"venue"
},
  "geometry": {"coordinates":[-73.576126,45.527985],"type":"Point"}
}