{
  "type": "Feature",
  "properties": {
    "addr:full":"69 Boul DE LA Seigneurie E Blainville QC J7C 4M9",
    "addr:housenumber":"69",
    "addr:postcode":"j7c 4m9",
    "addr:street":"Boul De La Seigneurie E",
    "iso:country":"CA",
    "sg:address":"69 Boul DE LA Seigneurie E",
    "sg:city":"Blainville",
    "sg:classifiers":[
        {
            "category":"Real Estate",
            "subcategory":"Surveying",
            "type":"Services"
        }
    ],
    "sg:phone":"+1 450 434 7887",
    "sg:postcode":"J7C 4M9",
    "sg:province":"QC",
    "sg:tags":[
        "surveyor"
    ],
    "wof:name":"Audet Daigle Daoust & Assoc",
    "wof:placetype":"venue"
},
  "geometry": {"coordinates":[-73.861763,45.673176],"type":"Point"}
}