{
  "type": "Feature",
  "properties": {
    "addr:full":"433 Av DE Las Pointe Jameson Venise-En-Quebec QC J0J 2K0",
    "addr:postcode":"j0j 2k0",
    "addr:street":"433 Av De Las Pointe Jameson Venise-En-Quebec",
    "iso:country":"CA",
    "sg:address":"433 Av DE Las Pointe Jameson",
    "sg:city":"Venise-En-Quebec",
    "sg:classifiers":[
        {
            "category":"Health Services",
            "subcategory":"Doctor",
            "type":"Services"
        }
    ],
    "sg:phone":"+1 450 244 5638",
    "sg:postcode":"J0J 2K0",
    "sg:province":"QC",
    "sg:tags":[
        "dentist"
    ],
    "wof:name":"Guta, Mihaela DDS",
    "wof:placetype":"venue"
},
  "geometry": {"coordinates":[-73.131638,45.073086],"type":"Point"}
}