{
  "type": "Feature",
  "properties": {
    "addr:full":"342 Powell St Vancouver BC V6A 1G4",
    "addr:housenumber":"342",
    "addr:postcode":"v6a 1g4",
    "addr:street":"Powell St",
    "iso:country":"CA",
    "sg:address":"342 Powell St",
    "sg:city":"Vancouver",
    "sg:classifiers":[
        {
            "category":"Restaurant",
            "type":"Food & Drink"
        }
    ],
    "sg:phone":"+1 604 608 1188",
    "sg:postcode":"V6A 1G4",
    "sg:province":"BC",
    "wof:name":"Aristocrat Restaurant",
    "wof:placetype":"venue"
},
  "geometry": {"coordinates":[-123.09661102299999,49.2830085754],"type":"Point"}
}