{
  "type": "Feature",
  "properties": {
    "addr:full":"223 Cranbrook St N Cranbrook BC V1C 3R1",
    "addr:housenumber":"223",
    "addr:postcode":"v1c 3r1",
    "addr:street":"Cranbrook St N",
    "iso:country":"CA",
    "sg:address":"223 Cranbrook St N",
    "sg:city":"Cranbrook",
    "sg:classifiers":[
        {
            "category":"Shopping",
            "subcategory":"Musical Instruments",
            "type":"Retail Goods"
        }
    ],
    "sg:phone":"+1 250 426 2999",
    "sg:postcode":"V1C 3R1",
    "sg:province":"BC",
    "wof:name":"Just Music",
    "wof:placetype":"venue"
},
  "geometry": {"coordinates":[-115.765830994,49.5146713257],"type":"Point"}
}