{
  "type": "Feature",
  "properties": {
    "addr:full":"2612 Hastings St E Vancouver BC V5K 1Z6",
    "addr:housenumber":"2612",
    "addr:postcode":"v5k 1z6",
    "addr:street":"Hastings St E",
    "iso:country":"CA",
    "sg:address":"2612 Hastings St E",
    "sg:city":"Vancouver",
    "sg:classifiers":[
        {
            "category":"Professional",
            "subcategory":"Accounting & Tax Preparation",
            "type":"Services"
        }
    ],
    "sg:phone":"+1 604 713 1050",
    "sg:postcode":"V5K 1Z6",
    "sg:province":"BC",
    "sg:tags":[
        "return",
        "filing"
    ],
    "wof:name":"H & R Block Canada Inc",
    "wof:placetype":"venue"
},
  "geometry": {"coordinates":[-123.05136108400001,49.2810173035],"type":"Point"}
}