{
  "type": "Feature",
  "properties": {
    "addr:full":"3085 Boul Lemire Drummondville QC J2B 6Y8",
    "addr:housenumber":"3085",
    "addr:postcode":"j2b 6y8",
    "addr:street":"Boul Lemire",
    "iso:country":"CA",
    "sg:address":"3085 Boul Lemire",
    "sg:city":"Drummondville",
    "sg:classifiers":[
        {
            "category":"Retail",
            "subcategory":"Veterinary Services",
            "type":"Services"
        }
    ],
    "sg:phone":"+1 819 477 0125",
    "sg:postcode":"J2B 6Y8",
    "sg:province":"QC",
    "sg:tags":[
        "veterinarian"
    ],
    "wof:name":"Hopital Veterinaire Drummond",
    "wof:placetype":"venue"
},
  "geometry": {"coordinates":[-72.4840393066,45.8555908203],"type":"Point"}
}