{
  "type": "Feature",
  "properties": {
    "addr:full":"523 Grand Ave Indian Head SK S0G 2K0",
    "addr:housenumber":"523",
    "addr:postcode":"s0g 2k0",
    "addr:street":"Grand Ave",
    "iso:country":"CA",
    "sg:address":"523 Grand Ave",
    "sg:city":"Indian Head",
    "sg:classifiers":[
        {
            "category":"Insurance",
            "subcategory":"Insurance Agent",
            "type":"Services"
        }
    ],
    "sg:phone":"+1 306 695 3533",
    "sg:postcode":"S0G 2K0",
    "sg:province":"SK",
    "wof:name":"Indian Head Agencies Ltd",
    "wof:placetype":"venue"
},
  "geometry": {"coordinates":[-103.66886100000001,50.53257],"type":"Point"}
}