{
  "type": "Feature",
  "properties": {
    "iso:country":"CA",
    "sg:address":"413 Albany St",
    "sg:city":"Petrolia",
    "sg:classifiers":[
        {
            "category":"Restaurant",
            "type":"Food & Drink"
        }
    ],
    "sg:phone":"+1 519 882 1366",
    "sg:postcode":"N0N 1R0",
    "sg:province":"ON",
    "sg:tags":[
        "pizza"
    ],
    "wof:name":"Pumphouse Pizza & Sub",
    "wof:placetype":"venue"
},
  "geometry": {"coordinates":[-82.1485748291,42.8811340332],"type":"Point"}
}