{
  "type": "Feature",
  "properties": {
    "addr:full":"298 Mountain St Boissevain MB R0K 0E0",
    "addr:housenumber":"298",
    "addr:postcode":"r0k 0e0",
    "addr:street":"Mountain St",
    "iso:country":"CA",
    "sg:address":"298 Mountain St",
    "sg:city":"Boissevain",
    "sg:classifiers":[
        {
            "category":"Museum",
            "type":"Entertainment"
        }
    ],
    "sg:phone":"+1 204 534 6662",
    "sg:postcode":"R0K 0E0",
    "sg:province":"MB",
    "wof:name":"Irvin Goodon Intl Wildlife",
    "wof:placetype":"venue"
},
  "geometry": {"coordinates":[-100.058769226,49.2252311707],"type":"Point"}
}