{
  "type": "Feature",
  "properties": {
    "addr:full":"120 Longworth Lane #A Woodstock ON N4V 1C4",
    "addr:housenumber":"120",
    "addr:postcode":"n4v 1c4",
    "addr:street":"Longworth Lane # A",
    "iso:country":"CA",
    "sg:address":"120 Longworth Lane #A",
    "sg:city":"Woodstock",
    "sg:phone":"+1 519 539 9877",
    "sg:postcode":"N4V 1C4",
    "sg:province":"ON",
    "sg:tags":[
        "scale"
    ],
    "wof:name":"Interweight Systems Inc",
    "wof:placetype":"venue"
},
  "geometry": {"coordinates":[-80.730225,43.118294],"type":"Point"}
}