{
  "type": "Feature",
  "properties": {
    "addr:full":"Vancouver BC V5T 1W9",
    "addr:postcode":"v5t 1w9",
    "iso:country":"CA",
    "sg:city":"Vancouver",
    "sg:classifiers":[
        {
            "category":"Professional",
            "subcategory":"Credit Reporting & Collection",
            "type":"Services"
        }
    ],
    "sg:phone":"+1 604 877 2380",
    "sg:postcode":"V5T 1W9",
    "sg:province":"BC",
    "sg:tags":[
        "agency"
    ],
    "wof:name":"Cmc Credit Management",
    "wof:placetype":"venue"
},
  "geometry": {"coordinates":[-123.09378100000001,49.262657],"type":"Point"}
}