{
  "type": "Feature",
  "properties": {
    "addr:full":"Farm Eatonia SK S0L 0Y0",
    "addr:postcode":"s0l 0y0",
    "iso:country":"CA",
    "sg:address":"Farm",
    "sg:city":"Eatonia",
    "sg:classifiers":[
        {
            "category":"Farming",
            "subcategory":"Nursery",
            "type":"Manufacturing & Wholesale Goods"
        }
    ],
    "sg:phone":"+1 306 967 2440",
    "sg:postcode":"S0L 0Y0",
    "sg:province":"SK",
    "sg:tags":[
        "seed"
    ],
    "wof:name":"Bews Agrow Ltd",
    "wof:placetype":"venue"
},
  "geometry": {"coordinates":[-109.389266968,51.2211494446],"type":"Point"}
}