{
  "type": "Feature",
  "properties": {
    "addr:full":"Lloydminster AB T9V 0X4",
    "addr:postcode":"t9v 0x4",
    "iso:country":"CA",
    "sg:city":"Lloydminster",
    "sg:classifiers":[
        {
            "category":"Recreation",
            "type":"Entertainment"
        }
    ],
    "sg:phone":"+1 780 875 3601",
    "sg:postcode":"T9V 0X4",
    "sg:province":"AB",
    "sg:tags":[
        "hall",
        "auditorium"
    ],
    "wof:name":"Elk's Hall",
    "wof:placetype":"venue"
},
  "geometry": {"coordinates":[-110.005737305,53.2918167114],"type":"Point"}
}