{
  "type": "Feature",
  "properties": {
    "iso:country":"CA",
    "sg:address":"6603 48 Ave",
    "sg:city":"Camrose",
    "sg:classifiers":[
        {
            "category":"Restaurant",
            "type":"Food & Drink"
        }
    ],
    "sg:phone":"+1 780 672 9453",
    "sg:postcode":"T4V 3K3",
    "sg:province":"AB",
    "wof:name":"Mc Donald's",
    "wof:placetype":"venue"
},
  "geometry": {"coordinates":[-112.855735779,53.0177841187],"type":"Point"}
}