{
  "type": "Feature",
  "properties": {
    "addr:full":"RR 2 Kennetcook NS B0N 1P0",
    "addr:postcode":"b0n 1p0",
    "addr:street":"Rr 2",
    "iso:country":"CA",
    "sg:address":"RR 2",
    "sg:city":"Kennetcook",
    "sg:classifiers":[
        {
            "category":"Freight",
            "type":"Transportation"
        }
    ],
    "sg:phone":"+1 902 362 2465",
    "sg:postcode":"B0N 1P0",
    "sg:province":"NS",
    "sg:tags":[
        "trucking"
    ],
    "wof:name":"Kennetcook Trucking",
    "wof:placetype":"venue"
},
  "geometry": {"coordinates":[-63.721973,45.17746],"type":"Point"}
}