{
  "type": "Feature",
  "properties": {
    "addr:full":"143 Huggard Rd Calgary AB T3Z 2C2",
    "addr:housenumber":"143",
    "addr:postcode":"t3z 2c2",
    "addr:street":"Huggard Rd",
    "iso:country":"CA",
    "sg:address":"143 Huggard Rd",
    "sg:city":"Calgary",
    "sg:classifiers":[
        {
            "category":"Manufacturing",
            "subcategory":"Retail Goods",
            "type":"Manufacturing & Wholesale Goods"
        }
    ],
    "sg:phone":"+1 403 266 4363",
    "sg:postcode":"T3Z 2C2",
    "sg:province":"AB",
    "sg:tags":[
        "marking",
        "devices"
    ],
    "wof:name":"Genpack Industries Ltd",
    "wof:placetype":"venue"
},
  "geometry": {"coordinates":[-114.063194,51.045074],"type":"Point"}
}