{
  "type": "Feature",
  "properties": {
    "addr:full":"5580 Ch DE Chambly Saint-Hubert QC J3Y 3P5",
    "addr:postcode":"5580;j3y 3p5",
    "addr:street":"Ch De Chambly",
    "iso:country":"CA",
    "sg:address":"5580 Ch DE Chambly",
    "sg:city":"Saint-Hubert",
    "sg:classifiers":[
        {
            "category":"Health Services",
            "subcategory":"Doctor",
            "type":"Services"
        }
    ],
    "sg:phone":"+1 450 926 2236",
    "sg:postcode":"J3Y 3P5",
    "sg:province":"QC",
    "sg:tags":[
        "clinic"
    ],
    "wof:name":"Clinique Medicale Chambley",
    "wof:placetype":"venue"
},
  "geometry": {"coordinates":[-73.4163284302,45.5021438599],"type":"Point"}
}