{
  "type": "Feature",
  "properties": {
    "addr:full":"355 Howe St Vancouver BC V6C 3N2",
    "addr:housenumber":"355",
    "addr:postcode":"bc v6c 3n2",
    "addr:street":"Howe St",
    "iso:country":"CA",
    "sg:address":"355 Howe St",
    "sg:city":"Vancouver",
    "sg:classifiers":[
        {
            "category":"Shopping",
            "subcategory":"Clothing, Apparel, & Fashions",
            "type":"Retail Goods"
        }
    ],
    "sg:phone":"+1 604 685 4225",
    "sg:postcode":"V6C 3N2",
    "sg:province":"BC",
    "wof:name":"Dyanna Fine Clothing For Women",
    "wof:placetype":"venue"
},
  "geometry": {"coordinates":[-123.114570618,49.2862625122],"type":"Point"}
}