{
  "type": "Feature",
  "properties": {
    "addr:full":"1683 158 Rte Saint-Jerome QC J7Z 7M1",
    "addr:housenumber":"1683",
    "addr:postcode":"j7z 7m1",
    "addr:street":"158 Rte Saint-Jerome",
    "iso:country":"CA",
    "sg:address":"1683 158 Rte",
    "sg:city":"Saint-Jerome",
    "sg:classifiers":[
        {
            "category":"Retail",
            "subcategory":"Auto Repair",
            "type":"Services"
        }
    ],
    "sg:phone":"+1 450 436 4707",
    "sg:postcode":"J7Z 7M1",
    "sg:province":"QC",
    "sg:tags":[
        "body",
        "automobile",
        "rustproofing",
        "painting",
        "undercoating"
    ],
    "wof:name":"Garage Sylvain Lauzon",
    "wof:placetype":"venue"
},
  "geometry": {"coordinates":[-74.00350952150001,45.7750091553],"type":"Point"}
}