{
  "type": "Feature",
  "properties": {
    "addr:full":"4044 Bridlepath Trail Mississauga ON L5L 3E9",
    "addr:housenumber":"4044",
    "addr:postcode":"l5l 3e9",
    "addr:street":"Bridlepath Trail",
    "iso:country":"CA",
    "sg:address":"4044 Bridlepath Trail",
    "sg:city":"Mississauga",
    "sg:classifiers":[
        {
            "category":"Professional",
            "subcategory":"Research",
            "type":"Services"
        }
    ],
    "sg:phone":"+1 905 569 3340",
    "sg:postcode":"L5L 3E9",
    "sg:province":"ON",
    "sg:tags":[
        "environmental",
        "ecological"
    ],
    "wof:name":"Building Survey Consultants",
    "wof:placetype":"venue"
},
  "geometry": {"coordinates":[-79.6789855957,43.5578460693],"type":"Point"}
}