{
  "type": "Feature",
  "properties": {
    "iso:country":"CA",
    "sg:address":"117 Rue Saint-Andre",
    "sg:city":"Cap-DE-LA-Madeleine",
    "sg:classifiers":[
        {
            "category":"Freight",
            "type":"Transportation"
        }
    ],
    "sg:phone":"+1 819 371 9963",
    "sg:postcode":"G8T 1R6",
    "sg:province":"QC",
    "sg:tags":[
        "courier"
    ],
    "wof:name":"May-D Colis",
    "wof:placetype":"venue"
},
  "geometry": {"coordinates":[-72.552376,46.383442],"type":"Point"}
}