{
  "type": "Feature",
  "properties": {
    "addr:full":"Vancouver BC V6A 2S9",
    "addr:postcode":"v6a 2s9",
    "iso:country":"CA",
    "sg:city":"Vancouver",
    "sg:classifiers":[
        {
            "category":"Health Services",
            "subcategory":"Doctor",
            "type":"Services"
        }
    ],
    "sg:phone":"+1 604 688 5822",
    "sg:postcode":"V6A 2S9",
    "sg:province":"BC",
    "sg:tags":[
        "physician",
        "surgeon"
    ],
    "wof:name":"Ma, Gilbert MD",
    "wof:placetype":"venue"
},
  "geometry": {"coordinates":[-123.099846,49.28199],"type":"Point"}
}