{
  "type": "Feature",
  "properties": {
    "iso:country":"CA",
    "sg:address":"10345 Av Papineau # 300",
    "sg:city":"Montreal",
    "sg:classifiers":[
        {
            "category":"Health Services",
            "subcategory":"Hospital",
            "type":"Services"
        }
    ],
    "sg:phone":"+1 514 383 5080",
    "sg:postcode":"H2B 2A3",
    "sg:province":"QC",
    "wof:name":"Centre Hospitalier Fluery Inc",
    "wof:placetype":"venue"
},
  "geometry": {"coordinates":[-73.653954,45.568596],"type":"Point"}
}