{
  "type": "Feature",
  "properties": {
    "addr:full":"4166 Catherine St Dorchester ON N0L 1G0",
    "addr:housenumber":"4166",
    "addr:postcode":"n0l 1g0",
    "addr:street":"Catherine St",
    "iso:country":"CA",
    "sg:address":"4166 Catherine St",
    "sg:city":"Dorchester",
    "sg:classifiers":[
        {
            "category":"Manufacturing",
            "subcategory":"Tools & Machinery",
            "type":"Manufacturing & Wholesale Goods"
        }
    ],
    "sg:phone":"+1 519 268 3148",
    "sg:postcode":"N0L 1G0",
    "sg:province":"ON",
    "sg:tags":[
        "conditioning",
        "air",
        "system",
        "contractor"
    ],
    "wof:name":"Marco Heating Ltd",
    "wof:placetype":"venue"
},
  "geometry": {"coordinates":[-81.06390399999999,42.990185],"type":"Point"}
}