{
  "type": "Feature",
  "properties": {
    "addr:full":"75 Bolton St Bobcaygeon ON K0M 1A0",
    "addr:housenumber":"75",
    "addr:postcode":"k0m 1a0",
    "addr:street":"Bolton St",
    "iso:country":"CA",
    "sg:address":"75 Bolton St",
    "sg:city":"Bobcaygeon",
    "sg:classifiers":[
        {
            "category":"Banks & Credit Unions",
            "subcategory":"Bank",
            "type":"Services"
        }
    ],
    "sg:phone":"+1 705 738 2354",
    "sg:postcode":"K0M 1A0",
    "sg:province":"ON",
    "wof:name":"Bank of Montreal",
    "wof:placetype":"venue"
},
  "geometry": {"coordinates":[-78.5441741943,44.5361862183],"type":"Point"}
}