{
  "type": "Feature",
  "properties": {
    "addr:full":"Scarborough ON M1E 2S2",
    "addr:postcode":"m1e 2s2",
    "iso:country":"CA",
    "sg:city":"Scarborough",
    "sg:classifiers":[
        {
            "category":"Health Services",
            "subcategory":"Doctor",
            "type":"Services"
        }
    ],
    "sg:phone":"+1 416 281 5522",
    "sg:postcode":"M1E 2S2",
    "sg:province":"ON",
    "sg:tags":[
        "physician",
        "surgeon"
    ],
    "wof:name":"Jeu, Joan P MD",
    "wof:placetype":"venue"
},
  "geometry": {"coordinates":[-79.1926574707,43.7668914795],"type":"Point"}
}