{
  "type": "Feature",
  "properties": {
    "addr:full":"10442 82 Ave NW Edmonton AB T6E 2A2",
    "addr:housenumber":"10442",
    "addr:postcode":"t6e 2a2",
    "addr:street":"82 Ave Nw",
    "iso:country":"CA",
    "sg:address":"10442 82 Ave NW",
    "sg:city":"Edmonton",
    "sg:classifiers":[
        {
            "category":"Shopping",
            "subcategory":"Used Merchandise",
            "type":"Retail Goods"
        }
    ],
    "sg:phone":"+1 780 433 9963",
    "sg:postcode":"T6E 2A2",
    "sg:province":"AB",
    "sg:tags":[
        "antique"
    ],
    "wof:name":"Junque Cellar",
    "wof:placetype":"venue"
},
  "geometry": {"coordinates":[-113.49888610799999,53.5182685852],"type":"Point"}
}