{
  "type": "Feature",
  "properties": {
    "addr:full":"2155 Rue Beaubien E Montreal QC H2G 1M5",
    "addr:housenumber":"2155",
    "addr:postcode":"h2g 1m5",
    "addr:street":"Rue Beaubien E",
    "iso:country":"CA",
    "sg:address":"2155 Rue Beaubien E",
    "sg:city":"Montreal",
    "sg:classifiers":[
        {
            "category":"Shopping",
            "subcategory":"Pharmacy",
            "type":"Retail Goods"
        }
    ],
    "sg:phone":"+1 514 721 4913",
    "sg:postcode":"H2G 1M5",
    "sg:province":"QC",
    "wof:name":"Uniprix",
    "wof:placetype":"venue"
},
  "geometry": {"coordinates":[-73.59438323969999,45.5459671021],"type":"Point"}
}