{
  "type": "Feature",
  "properties": {
    "addr:full":"Dorval QC H4Y 1J6",
    "addr:postcode":"h4y 1j6",
    "iso:country":"CA",
    "sg:city":"Dorval",
    "sg:classifiers":[
        {
            "category":"Airline",
            "type":"Transportation"
        }
    ],
    "sg:phone":"+1 514 631 1532",
    "sg:postcode":"H4Y 1J6",
    "sg:province":"QC",
    "sg:tags":[
        "company"
    ],
    "wof:name":"Scandinavian Airlines Sas",
    "wof:placetype":"venue"
},
  "geometry": {"coordinates":[-73.7611312866,45.4574317932],"type":"Point"}
}