{
  "type": "Feature",
  "properties": {
    "iso:country":"CA",
    "sg:city":"Hobbema",
    "sg:classifiers":[
        {
            "category":"Restaurant",
            "type":"Food & Drink"
        }
    ],
    "sg:phone":"+1 780 585 2495",
    "sg:postcode":"T0C 1N0",
    "sg:province":"AB",
    "sg:tags":[
        "caterer"
    ],
    "wof:name":"Ermineskin Cafeteria",
    "wof:placetype":"venue"
},
  "geometry": {"coordinates":[-113.446144104,52.8340835571],"type":"Point"}
}