{
  "type": "Feature",
  "properties": {
    "addr:full":"8468 Adera St Vancouver BC V6P 5E7",
    "addr:housenumber":"8468",
    "addr:postcode":"v6p 5e7",
    "addr:street":"Adera St",
    "iso:country":"CA",
    "sg:address":"8468 Adera St",
    "sg:city":"Vancouver",
    "sg:classifiers":[
        {
            "category":"Professional",
            "subcategory":"Engineering",
            "type":"Services"
        }
    ],
    "sg:phone":"+1 604 263 0338",
    "sg:postcode":"V6P 5E7",
    "sg:province":"BC",
    "sg:tags":[
        "engineer"
    ],
    "wof:name":"A-Min-Tech Research Ltd",
    "wof:placetype":"venue"
},
  "geometry": {"coordinates":[-123.14339447,49.2098579407],"type":"Point"}
}