{
  "type": "Feature",
  "properties": {
    "addr:full":"10240 Boul Lacroix Saint-Georges QC G5Y 1K1",
    "addr:housenumber":"10240",
    "addr:postcode":"g5y 1k1",
    "addr:street":"Boul Lacroix",
    "iso:country":"CA",
    "sg:address":"10240 Boul Lacroix",
    "sg:city":"Saint-Georges",
    "sg:classifiers":[
        {
            "category":"Autos & Motor Vehicles",
            "subcategory":"Automobile Sales",
            "type":"Retail Goods"
        }
    ],
    "sg:phone":"+1 418 228 5575",
    "sg:postcode":"G5Y 1K1",
    "sg:province":"QC",
    "sg:tags":[
        "car",
        "dealer"
    ],
    "wof:name":"Kennebec Dodge Chrysler Inc",
    "wof:placetype":"venue"
},
  "geometry": {"coordinates":[-70.687027,46.128368],"type":"Point"}
}