{
  "type": "Feature",
  "properties": {
    "addr:full":"231 Brock St W Uxbridge ON L9P 1B1",
    "addr:housenumber":"231",
    "addr:postcode":"l9p 1b1",
    "addr:street":"Brock St W",
    "iso:country":"CA",
    "sg:address":"231 Brock St W",
    "sg:city":"Uxbridge",
    "sg:classifiers":[
        {
            "category":"Organizations",
            "subcategory":"Religious Organization",
            "type":"Services"
        }
    ],
    "sg:phone":"+1 905 852 3662",
    "sg:postcode":"L9P 1B1",
    "sg:province":"ON",
    "sg:tags":[
        "church"
    ],
    "wof:name":"Uxbridge Baptist Church",
    "wof:placetype":"venue"
},
  "geometry": {"coordinates":[-79.1307144165,44.1071472168],"type":"Point"}
}