{
  "type": "Feature",
  "properties": {
    "iso:country":"CA",
    "sg:city":"Repentigny",
    "sg:classifiers":[
        {
            "category":"Personal",
            "subcategory":"Beauty Salon",
            "type":"Services"
        }
    ],
    "sg:phone":"+1 450 585 2492",
    "sg:postcode":"J6A 5N4",
    "sg:province":"QC",
    "wof:name":"Carisme Coiffure",
    "wof:placetype":"venue"
},
  "geometry": {"coordinates":[-73.455147,45.744362],"type":"Point"}
}