{
  "type": "Feature",
  "properties": {
    "addr:full":"48 High St SE Calgary AB T2Z 3T8",
    "addr:housenumber":"48",
    "addr:postcode":"t2z 3t8",
    "addr:street":"High St Se",
    "iso:country":"CA",
    "sg:address":"48 High St SE",
    "sg:city":"Calgary",
    "sg:classifiers":[
        {
            "category":"Insurance",
            "subcategory":"Insurance Agent",
            "type":"Services"
        }
    ],
    "sg:phone":"+1 403 257 0790",
    "sg:postcode":"T2Z 3T8",
    "sg:province":"AB",
    "wof:name":"Mc Kenzie Insurance Svc Ltd",
    "wof:placetype":"venue"
},
  "geometry": {"coordinates":[-113.96032,50.915493],"type":"Point"}
}