{
  "type": "Feature",
  "properties": {
    "addr:full":"327 Chemainus Rd Ladysmith BC V9G 1X9",
    "addr:housenumber":"327",
    "addr:postcode":"v9g 1x9",
    "addr:street":"Chemainus Rd",
    "iso:country":"CA",
    "sg:address":"327 Chemainus Rd",
    "sg:city":"Ladysmith",
    "sg:classifiers":[
        {
            "category":"Building & Trades",
            "subcategory":"Plumbing",
            "type":"Services"
        }
    ],
    "sg:phone":"+1 250 245 7814",
    "sg:postcode":"V9G 1X9",
    "sg:province":"BC",
    "sg:tags":[
        "contractor"
    ],
    "wof:name":"Al's Plumbing & Heating",
    "wof:placetype":"venue"
},
  "geometry": {"coordinates":[-123.802528,48.97897],"type":"Point"}
}