{
  "type": "Feature",
  "properties": {
    "addr:full":"1311 Rue Des Pins E L'Ancienne-Lorette QC G2E 1G3",
    "addr:housenumber":"1311",
    "addr:postcode":"g2e 1g3",
    "addr:street":"Rue Des Pins E L'Ancienne-Lorette",
    "iso:country":"CA",
    "sg:address":"1311 Rue Des Pins E",
    "sg:city":"L'Ancienne-Lorette",
    "sg:classifiers":[
        {
            "category":"Building & Trades",
            "subcategory":"Construction",
            "type":"Services"
        }
    ],
    "sg:phone":"+1 418 872 2231",
    "sg:postcode":"G2E 1G3",
    "sg:province":"QC",
    "sg:tags":[
        "excavating",
        "contractor"
    ],
    "wof:name":"Michel Dube Excavation",
    "wof:placetype":"venue"
},
  "geometry": {"coordinates":[-71.361526,46.798977],"type":"Point"}
}