{
  "type": "Feature",
  "properties": {
    "addr:full":"Calgary AB T2H 0K5",
    "addr:postcode":"t2h 0k5",
    "iso:country":"CA",
    "sg:city":"Calgary",
    "sg:classifiers":[
        {
            "category":"Health Services",
            "subcategory":"Doctor",
            "type":"Services"
        }
    ],
    "sg:phone":"+1 403 253 7003",
    "sg:postcode":"T2H 0K5",
    "sg:province":"AB",
    "sg:tags":[
        "dentist"
    ],
    "wof:name":"Chinook Plaza Dental Ctr",
    "wof:placetype":"venue"
},
  "geometry": {"coordinates":[-114.071266174,50.9988441467],"type":"Point"}
}