{
  "type": "Feature",
  "properties": {
    "addr:full":"4504 52nd Ave Provost AB T0B 3S0",
    "addr:housenumber":"4504",
    "addr:postcode":"t0b 3s0",
    "addr:street":"52Nd Ave",
    "iso:country":"CA",
    "sg:address":"4504 52nd Ave",
    "sg:city":"Provost",
    "sg:classifiers":[
        {
            "category":"Education",
            "subcategory":"School",
            "type":"Public Place"
        }
    ],
    "sg:phone":"+1 780 753 6824",
    "sg:postcode":"T0B 3S0",
    "sg:province":"AB",
    "wof:name":"Provost Public School",
    "wof:placetype":"venue"
},
  "geometry": {"coordinates":[-110.25904800000001,52.354305],"type":"Point"}
}