{
  "type": "Feature",
  "properties": {
    "addr:full":"Abbotsford BC V2T 4W1",
    "addr:postcode":"v2t 4w1",
    "iso:country":"CA",
    "sg:city":"Abbotsford",
    "sg:classifiers":[
        {
            "category":"Insurance",
            "subcategory":"Insurance Agent",
            "type":"Services"
        }
    ],
    "sg:phone":"+1 604 504 5460",
    "sg:postcode":"V2T 4W1",
    "sg:province":"BC",
    "wof:name":"Westland Insurance Group Ltd",
    "wof:placetype":"venue"
},
  "geometry": {"coordinates":[-122.315056,49.05106],"type":"Point"}
}