{
  "type": "Feature",
  "properties": {
    "addr:full":"5 Rue Chabanel O Montreal QC H2N 1C2",
    "addr:housenumber":"5",
    "addr:postcode":"h2n 1c2",
    "addr:street":"Rue Chabanel O",
    "iso:country":"CA",
    "sg:address":"5 Rue Chabanel O",
    "sg:city":"Montreal",
    "sg:classifiers":[
        {
            "category":"Restaurant",
            "type":"Food & Drink"
        }
    ],
    "sg:phone":"+1 514 384 2671",
    "sg:postcode":"H2N 1C2",
    "sg:province":"QC",
    "wof:name":"Restaurant Lavaria",
    "wof:placetype":"venue"
},
  "geometry": {"coordinates":[-73.6511688232,45.5446052551],"type":"Point"}
}