{
  "type": "Feature",
  "properties": {
    "addr:full":"North York ON M3J 2X4",
    "addr:postcode":"m3j 2x4",
    "iso:country":"CA",
    "sg:city":"North York",
    "sg:classifiers":[
        {
            "category":"Wholesale",
            "subcategory":"Jewelry",
            "type":"Manufacturing & Wholesale Goods"
        }
    ],
    "sg:phone":"+1 416 661 0606",
    "sg:postcode":"M3J 2X4",
    "sg:province":"ON",
    "sg:tags":[
        "watch"
    ],
    "wof:name":"Watches Direct CO",
    "wof:placetype":"venue"
},
  "geometry": {"coordinates":[-79.475296,43.779285],"type":"Point"}
}