{
  "type": "Feature",
  "properties": {
    "addr:full":"838 15th St W North Vancouver BC V7P 1M6",
    "addr:housenumber":"838",
    "addr:postcode":"v7p 1m6",
    "addr:street":"15Th St W",
    "iso:country":"CA",
    "sg:address":"838 15th St W",
    "sg:city":"North Vancouver",
    "sg:classifiers":[
        {
            "category":"Personal",
            "subcategory":"Beauty Salon",
            "type":"Services"
        }
    ],
    "sg:phone":"+1 604 904 4700",
    "sg:postcode":"V7P 1M6",
    "sg:province":"BC",
    "wof:name":"Kathleen & CO Hair Studio Ltd",
    "wof:placetype":"venue"
},
  "geometry": {"coordinates":[-123.09567300000001,49.322418],"type":"Point"}
}