{
  "type": "Feature",
  "properties": {
    "addr:full":"980 Dundas St London ON N5W 3A2",
    "addr:housenumber":"980",
    "addr:postcode":"n5w 3a2",
    "addr:street":"Dundas St",
    "iso:country":"CA",
    "sg:address":"980 Dundas St",
    "sg:city":"London",
    "sg:classifiers":[
        {
            "category":"Restaurant",
            "type":"Food & Drink"
        }
    ],
    "sg:phone":"+1 519 455 4520",
    "sg:postcode":"N5W 3A2",
    "sg:province":"ON",
    "wof:name":"Tony's Pizza Place & Tavern",
    "wof:placetype":"venue"
},
  "geometry": {"coordinates":[-81.21863555909999,42.9927406311],"type":"Point"}
}