{
  "type": "Feature",
  "properties": {
    "iso:country":"CA",
    "sg:address":"400 Lansdowne St E",
    "sg:city":"Peterborough",
    "sg:classifiers":[
        {
            "category":"Shopping",
            "subcategory":"Used Merchandise",
            "type":"Retail Goods"
        }
    ],
    "sg:phone":"+1 705 749 9070",
    "sg:postcode":"K9J 6X9",
    "sg:province":"ON",
    "sg:tags":[
        "shop",
        "consignment"
    ],
    "wof:name":"Recycled Kids",
    "wof:placetype":"venue"
},
  "geometry": {"coordinates":[-78.28889465330001,44.2925300598],"type":"Point"}
}