{
  "type": "Feature",
  "properties": {
    "addr:full":"Scarborough ON M1X 1B2",
    "addr:postcode":"m1x 1b2",
    "iso:country":"CA",
    "sg:city":"Scarborough",
    "sg:classifiers":[
        {
            "category":"Retail",
            "subcategory":"Repair Shop",
            "type":"Services"
        }
    ],
    "sg:phone":"+1 416 299 4900",
    "sg:postcode":"M1X 1B2",
    "sg:province":"ON",
    "sg:tags":[
        "upholsterer"
    ],
    "wof:name":"Designer's Choice Upholstery",
    "wof:placetype":"venue"
},
  "geometry": {"coordinates":[-79.233276,43.819302],"type":"Point"}
}