{
  "type": "Feature",
  "properties": {
    "addr:full":"35 Rakely Crt Etobicoke ON M9C 5A5",
    "addr:housenumber":"35",
    "addr:postcode":"m9c 5a5",
    "addr:street":"Rakely Crt",
    "iso:country":"CA",
    "sg:address":"35 Rakely Crt",
    "sg:city":"Etobicoke",
    "sg:classifiers":[
        {
            "category":"Manufacturing",
            "subcategory":"Food",
            "type":"Manufacturing & Wholesale Goods"
        }
    ],
    "sg:phone":"+1 416 622 1830",
    "sg:postcode":"M9C 5A5",
    "sg:province":"ON",
    "sg:tags":[
        "grocer",
        "product",
        "manufacturer"
    ],
    "wof:name":"Dempster's Bread",
    "wof:placetype":"venue"
},
  "geometry": {"coordinates":[-79.60451507569999,43.6474227905],"type":"Point"}
}