{
  "type": "Feature",
  "properties": {
    "addr:full":"St Albert AB T8N 1C7",
    "addr:postcode":"t8n 1c7",
    "iso:country":"CA",
    "sg:city":"St Albert",
    "sg:classifiers":[
        {
            "category":"Education",
            "subcategory":"School",
            "type":"Public Place"
        }
    ],
    "sg:phone":"+1 780 460 1168",
    "sg:postcode":"T8N 1C7",
    "sg:province":"AB",
    "sg:tags":[
        "tutoring"
    ],
    "wof:name":"Success 2000 Study Ctr",
    "wof:placetype":"venue"
},
  "geometry": {"coordinates":[-113.625252,53.633915],"type":"Point"}
}