{
  "type": "Feature",
  "properties": {
    "addr:full":"Oshawa ON L1H 8A7",
    "addr:postcode":"l1h 8a7",
    "iso:country":"CA",
    "sg:city":"Oshawa",
    "sg:classifiers":[
        {
            "category":"Retail",
            "subcategory":"Auto Repair",
            "type":"Services"
        }
    ],
    "sg:phone":"+1 905 571 3438",
    "sg:postcode":"L1H 8A7",
    "sg:province":"ON",
    "sg:tags":[
        "transmission",
        "automobile",
        "repairing"
    ],
    "wof:name":"Universal Transmission",
    "wof:placetype":"venue"
},
  "geometry": {"coordinates":[-78.83879852290001,43.8741340637],"type":"Point"}
}