{
  "type": "Feature",
  "properties": {
    "iso:country":"CA",
    "sg:address":"82 Letete Rd",
    "sg:city":"St George",
    "sg:classifiers":[
        {
            "category":"Food & Beverages",
            "subcategory":"Groceries & Convenience Stores",
            "type":"Retail Goods"
        }
    ],
    "sg:phone":"+1 506 755 1006",
    "sg:postcode":"E5C 3H6",
    "sg:province":"NB",
    "sg:tags":[
        "grocer"
    ],
    "wof:name":"St George Mainway",
    "wof:placetype":"venue"
},
  "geometry": {"coordinates":[-66.818634,45.127224],"type":"Point"}
}