{
  "type": "Feature",
  "properties": {
    "addr:full":"6533 Roszell Rd Cambridge ON N3C 2V3",
    "addr:housenumber":"6533",
    "addr:postcode":"n3c 2v3",
    "addr:street":"Roszell Rd",
    "iso:country":"CA",
    "sg:address":"6533 Roszell Rd",
    "sg:city":"Cambridge",
    "sg:classifiers":[
        {
            "category":"Building & Trades",
            "subcategory":"Plumbing",
            "type":"Services"
        }
    ],
    "sg:phone":"+1 519 651 0278",
    "sg:postcode":"N3C 2V3",
    "sg:province":"ON",
    "sg:tags":[
        "refrigeration",
        "contractor"
    ],
    "wof:name":"Total Refrigeration Ltd",
    "wof:placetype":"venue"
},
  "geometry": {"coordinates":[-80.3153305054,43.3614082336],"type":"Point"}
}