{
  "type": "Feature",
  "properties": {
    "addr:full":"650 Cataraqui Woods Dr Kingston ON K7P 2Y4",
    "addr:housenumber":"650",
    "addr:postcode":"k7p 2y4",
    "addr:street":"Cataraqui Woods Dr",
    "iso:country":"CA",
    "sg:address":"650 Cataraqui Woods Dr",
    "sg:city":"Kingston",
    "sg:classifiers":[
        {
            "category":"Wholesale",
            "subcategory":"Groceries",
            "type":"Manufacturing & Wholesale Goods"
        }
    ],
    "sg:phone":"+1 613 384 6666",
    "sg:postcode":"K7P 2Y4",
    "sg:province":"ON",
    "sg:tags":[
        "grocer"
    ],
    "wof:name":"Sysco Serca Foodservice Inc",
    "wof:placetype":"venue"
},
  "geometry": {"coordinates":[-76.56925200000001,44.267231],"type":"Point"}
}