{
  "type": "Feature",
  "properties": {
    "addr:full":"755 Lake Bonavista Dr SE Calgary AB T2J 0N3",
    "addr:housenumber":"755",
    "addr:postcode":"t2j 0n3",
    "addr:street":"Lake Bonavista Dr Se",
    "iso:country":"CA",
    "sg:address":"755 Lake Bonavista Dr SE",
    "sg:city":"Calgary",
    "sg:classifiers":[
        {
            "category":"Professional",
            "subcategory":"Management & Consulting",
            "type":"Services"
        }
    ],
    "sg:phone":"+1 403 278 5828",
    "sg:postcode":"T2J 0N3",
    "sg:province":"AB",
    "sg:tags":[
        "consultant",
        "relation",
        "business",
        "labor"
    ],
    "wof:name":"D Bobiy & Assoc Inc",
    "wof:placetype":"venue"
},
  "geometry": {"coordinates":[-114.048141,50.943687],"type":"Point"}
}