{
  "type": "Feature",
  "properties": {
    "addr:full":"145 Scott Rd Sarnia ON N7T 7W1",
    "addr:housenumber":"145",
    "addr:postcode":"n7t 7w1",
    "addr:street":"Scott Rd",
    "iso:country":"CA",
    "sg:address":"145 Scott Rd",
    "sg:city":"Sarnia",
    "sg:classifiers":[
        {
            "category":"Wholesale",
            "subcategory":"Machinery & Supplies",
            "type":"Manufacturing & Wholesale Goods"
        }
    ],
    "sg:phone":"+1 519 332 8460",
    "sg:postcode":"N7T 7W1",
    "sg:province":"ON",
    "sg:tags":[
        "contractor"
    ],
    "wof:name":"Cooper's Crane Rental Ltd",
    "wof:placetype":"venue"
},
  "geometry": {"coordinates":[-82.39636993409999,42.9555587769],"type":"Point"}
}