{
  "type": "Feature",
  "properties": {
    "addr:full":"Richmond BC V7C 4V4",
    "addr:postcode":"v7c 4v4",
    "iso:country":"CA",
    "sg:city":"Richmond",
    "sg:classifiers":[
        {
            "category":"Manufacturing",
            "subcategory":"Furniture",
            "type":"Manufacturing & Wholesale Goods"
        }
    ],
    "sg:phone":"+1 604 273 8158",
    "sg:postcode":"V7C 4V4",
    "sg:province":"BC",
    "wof:name":"Imperial Furniture Mfg Ltd",
    "wof:placetype":"venue"
},
  "geometry": {"coordinates":[-123.15707399999999,49.170376],"type":"Point"}
}