{
  "type": "Feature",
  "properties": {
    "addr:full":"150 Palmer Rd NE Calgary AB T2E 7R3",
    "addr:housenumber":"150",
    "addr:postcode":"t2e 7r3",
    "addr:street":"Palmer Rd Ne",
    "iso:country":"CA",
    "sg:address":"150 Palmer Rd NE",
    "sg:city":"Calgary",
    "sg:classifiers":[
        {
            "category":"Manufacturing",
            "subcategory":"Tools & Machinery",
            "type":"Manufacturing & Wholesale Goods"
        }
    ],
    "sg:phone":"+1 403 219 6600",
    "sg:postcode":"T2E 7R3",
    "sg:province":"AB",
    "sg:tags":[
        "turbine"
    ],
    "wof:name":"Transcanada Turbines Ltd",
    "wof:placetype":"venue"
},
  "geometry": {"coordinates":[-114.007149,51.096771],"type":"Point"}
}