{
  "type": "Feature",
  "properties": {
    "iso:country":"CA",
    "sg:city":"Montreal",
    "sg:classifiers":[
        {
            "category":"Real Estate",
            "subcategory":"Real Estate Agent",
            "type":"Services"
        }
    ],
    "sg:phone":"+1 514 523 1521",
    "sg:postcode":"H2L 1L4",
    "sg:province":"QC",
    "sg:tags":[
        "authorities",
        "housing"
    ],
    "wof:name":"Tour Lafontaine",
    "wof:placetype":"venue"
},
  "geometry": {"coordinates":[-73.565842,45.520988],"type":"Point"}
}