{
  "type": "Feature",
  "properties": {
    "addr:full":"76 Water St Pictou NS B0K 1H0",
    "addr:housenumber":"76",
    "addr:postcode":"b0k 1h0",
    "addr:street":"Water St",
    "iso:country":"CA",
    "sg:address":"76 Water St",
    "sg:city":"Pictou",
    "sg:classifiers":[
        {
            "category":"Manufacturing",
            "subcategory":"Tools & Machinery",
            "type":"Manufacturing & Wholesale Goods"
        }
    ],
    "sg:phone":"+1 902 485 8057",
    "sg:postcode":"B0K 1H0",
    "sg:province":"NS",
    "sg:tags":[
        "automobile",
        "parts",
        "supply"
    ],
    "wof:name":"Shiretown Home & Auto Ltd",
    "wof:placetype":"venue"
},
  "geometry": {"coordinates":[-62.711399,45.676189],"type":"Point"}
}