{
  "type": "Feature",
  "properties": {
    "addr:full":"4 Jubilee Ave Winnipegosis MB R0L 2G0",
    "addr:housenumber":"4",
    "addr:postcode":"r0l 2g0",
    "addr:street":"Jubilee Ave",
    "iso:country":"CA",
    "sg:address":"4 Jubilee Ave",
    "sg:city":"Winnipegosis",
    "sg:classifiers":[
        {
            "category":"Autos & Motor Vehicles",
            "subcategory":"Fuel & Gas Station",
            "type":"Retail Goods"
        }
    ],
    "sg:phone":"+1 204 656 4824",
    "sg:postcode":"R0L 2G0",
    "sg:province":"MB",
    "sg:tags":[
        "oil"
    ],
    "wof:name":"Foxy's Gas Bar",
    "wof:placetype":"venue"
},
  "geometry": {"coordinates":[-99.9255065918,51.6529006958],"type":"Point"}
}