{
  "type": "Feature",
  "properties": {
    "addr:full":"10 Cite Des Jeunes Blvd Kapuskasing ON P5N 2K2",
    "addr:housenumber":"10",
    "addr:postcode":"p5n 2k2",
    "addr:street":"Cite Des Jeunes Blvd",
    "iso:country":"CA",
    "sg:address":"10 Cite Des Jeunes Blvd",
    "sg:city":"Kapuskasing",
    "sg:classifiers":[
        {
            "category":"Education",
            "subcategory":"School",
            "type":"Public Place"
        }
    ],
    "sg:phone":"+1 705 335 6057",
    "sg:postcode":"P5N 2K2",
    "sg:province":"ON",
    "wof:name":"Cite Des Jeunes Secondary",
    "wof:placetype":"venue"
},
  "geometry": {"coordinates":[-82.425194,49.417809],"type":"Point"}
}