{
  "type": "Feature",
  "properties": {
    "addr:full":"10 1st Ave S Sioux Lookout ON P8T 1A1",
    "addr:housenumber":"10",
    "addr:postcode":"p8t 1a1",
    "addr:street":"1St Ave S Sioux Lookout",
    "iso:country":"CA",
    "sg:address":"10 1st Ave S",
    "sg:city":"Sioux Lookout",
    "sg:classifiers":[
        {
            "category":"Travel",
            "subcategory":"Hotels & Motels",
            "type":"Entertainment"
        }
    ],
    "sg:phone":"+1 807 737 1113",
    "sg:postcode":"P8T 1A1",
    "sg:province":"ON",
    "wof:name":"Sunset Inn",
    "wof:placetype":"venue"
},
  "geometry": {"coordinates":[-91.908478,50.101254],"type":"Point"}
}