{
  "type": "Feature",
  "properties": {
    "iso:country":"CA",
    "sg:address":"73 Route 105 # 200",
    "sg:city":"Chelsea",
    "sg:classifiers":[
        {
            "category":"Professional",
            "subcategory":"Engineering",
            "type":"Services"
        }
    ],
    "sg:phone":"+1 819 246 8249",
    "sg:postcode":"J9B 1L3",
    "sg:province":"QC",
    "sg:tags":[
        "engineer"
    ],
    "wof:name":"Jean-Claude Blais Consultant",
    "wof:placetype":"venue"
},
  "geometry": {"coordinates":[-75.74876403810001,45.4817619324],"type":"Point"}
}