{
  "type": "Feature",
  "properties": {
    "addr:full":"Prince Albert SK S6V 1E9",
    "addr:postcode":"s6v 1e9",
    "iso:country":"CA",
    "sg:city":"Prince Albert",
    "sg:classifiers":[
        {
            "category":"Professional",
            "subcategory":"Accounting & Tax Preparation",
            "type":"Services"
        }
    ],
    "sg:phone":"+1 306 763 7411",
    "sg:postcode":"S6V 1E9",
    "sg:province":"SK",
    "sg:tags":[
        "accountant"
    ],
    "wof:name":"Hogeweide, Barb CA",
    "wof:placetype":"venue"
},
  "geometry": {"coordinates":[-105.75226600000001,53.199215],"type":"Point"}
}