{
  "type": "Feature",
  "properties": {
    "addr:full":"Ottawa ON K1K 3X9",
    "addr:postcode":"k1k 3x9",
    "iso:country":"CA",
    "sg:city":"Ottawa",
    "sg:classifiers":[
        {
            "category":"Real Estate",
            "subcategory":"Real Estate Operator",
            "type":"Services"
        }
    ],
    "sg:phone":"+1 613 745 2145",
    "sg:postcode":"K1K 3X9",
    "sg:province":"ON",
    "sg:tags":[
        "apartment"
    ],
    "wof:name":"Concorde Apartments",
    "wof:placetype":"venue"
},
  "geometry": {"coordinates":[-75.62593099999999,45.446465],"type":"Point"}
}