{
  "type": "Feature",
  "properties": {
    "addr:full":"Burnaby BC V5J 3J3",
    "addr:postcode":"v5j 3j3",
    "iso:country":"CA",
    "sg:city":"Burnaby",
    "sg:classifiers":[
        {
            "category":"Building & Trades",
            "subcategory":"Electrical",
            "type":"Services"
        }
    ],
    "sg:phone":"+1 604 431 7433",
    "sg:postcode":"V5J 3J3",
    "sg:province":"BC",
    "sg:tags":[
        "electric",
        "contractor"
    ],
    "wof:name":"Marlatt Industrial Elec Ltd",
    "wof:placetype":"venue"
},
  "geometry": {"coordinates":[-122.97895800000001,49.20343],"type":"Point"}
}