{
  "type": "Feature",
  "properties": {
    "addr:full":"131 Rue Saint-Georges Matane QC G4W 2B3",
    "addr:housenumber":"131",
    "addr:postcode":"g4w 2b3",
    "addr:street":"Rue Saint-Georges",
    "iso:country":"CA",
    "sg:address":"131 Rue Saint-Georges",
    "sg:city":"Matane",
    "sg:classifiers":[
        {
            "category":"Organizations",
            "subcategory":"Religious Organization",
            "type":"Services"
        }
    ],
    "sg:phone":"+1 418 562 4766",
    "sg:postcode":"G4W 2B3",
    "sg:province":"QC",
    "sg:tags":[
        "church"
    ],
    "wof:name":"Eglise Evangelique-Pentecote",
    "wof:placetype":"venue"
},
  "geometry": {"coordinates":[-67.53125799999999,48.846859],"type":"Point"}
}