{
  "type": "Feature",
  "properties": {
    "addr:full":"241 Queen St Burks Falls ON P0A 1C0",
    "addr:housenumber":"241",
    "addr:postcode":"p0a 1c0",
    "addr:street":"Queen St",
    "iso:country":"CA",
    "sg:address":"241 Queen St",
    "sg:city":"Burks Falls",
    "sg:classifiers":[
        {
            "category":"Professional",
            "subcategory":"Accounting & Tax Preparation",
            "type":"Services"
        }
    ],
    "sg:phone":"+1 705 382 2418",
    "sg:postcode":"P0A 1C0",
    "sg:province":"ON",
    "sg:tags":[
        "return",
        "filing"
    ],
    "wof:name":"Ian Smith Accounting",
    "wof:placetype":"venue"
},
  "geometry": {"coordinates":[-81.16905975340001,48.4948921204],"type":"Point"}
}