{
  "type": "Feature",
  "properties": {
    "addr:full":"1038 Elisabella St Sudbury ON P3A 5K2",
    "addr:housenumber":"1038",
    "addr:postcode":"p3a 5k2",
    "addr:street":"Elisabella St",
    "iso:country":"CA",
    "sg:address":"1038 Elisabella St",
    "sg:city":"Sudbury",
    "sg:classifiers":[
        {
            "category":"Manufacturing",
            "subcategory":"Tools & Machinery",
            "type":"Manufacturing & Wholesale Goods"
        }
    ],
    "sg:phone":"+1 705 521 1616",
    "sg:postcode":"P3A 5K2",
    "sg:province":"ON",
    "sg:tags":[
        "equipment",
        "mining",
        "trencher",
        "supply"
    ],
    "wof:name":"Hardrock Mining Products Ltd",
    "wof:placetype":"venue"
},
  "geometry": {"coordinates":[-80.90934799999999,46.520386],"type":"Point"}
}