{
  "type": "Feature",
  "properties": {
    "addr:full":"706 Norway Rd S Canora SK S0A 0L0",
    "addr:housenumber":"706",
    "addr:postcode":"s0a 0l0",
    "addr:street":"Norway Rd",
    "iso:country":"CA",
    "sg:address":"706 Norway Rd S",
    "sg:city":"Canora",
    "sg:classifiers":[
        {
            "category":"Travel",
            "subcategory":"Travel Agent",
            "type":"Entertainment"
        }
    ],
    "sg:phone":"+1 306 563 6046",
    "sg:postcode":"S0A 0L0",
    "sg:province":"SK",
    "sg:tags":[
        "information",
        "tourist"
    ],
    "wof:name":"Tourist Information Booth",
    "wof:placetype":"venue"
},
  "geometry": {"coordinates":[-102.432434,51.635456],"type":"Point"}
}