{
  "type": "Feature",
  "properties": {
    "addr:full":"Logan Lake BC V0K 1W0",
    "addr:postcode":"v0k 1w0",
    "addr:street":"Logan",
    "iso:country":"CA",
    "sg:city":"Logan Lake",
    "sg:classifiers":[
        {
            "category":"Recreation",
            "type":"Entertainment"
        }
    ],
    "sg:phone":"+1 250 523 6229",
    "sg:postcode":"V0K 1W0",
    "sg:province":"BC",
    "sg:tags":[
        "center"
    ],
    "wof:name":"Logan Lake Y",
    "wof:placetype":"venue"
},
  "geometry": {"coordinates":[-120.819328308,50.4946517944],"type":"Point"}
}