{
  "type": "Feature",
  "properties": {
    "addr:full":"Glace Bay NS B1A 2P4",
    "addr:postcode":"b1a 2p4",
    "iso:country":"CA",
    "sg:city":"Glace Bay",
    "sg:classifiers":[
        {
            "category":"Manufacturing",
            "subcategory":"Signs",
            "type":"Manufacturing & Wholesale Goods"
        }
    ],
    "sg:phone":"+1 902 849 5455",
    "sg:postcode":"B1A 2P4",
    "sg:province":"NS",
    "wof:name":"Bay Signs",
    "wof:placetype":"venue"
},
  "geometry": {"coordinates":[-59.9563064575,46.1954536438],"type":"Point"}
}