{
  "type": "Feature",
  "properties": {
    "addr:full":"1491 Rue Verreault Saint-Felicien QC G8K 1W2",
    "addr:housenumber":"1491",
    "addr:postcode":"g8k 1w2",
    "addr:street":"Rue Verreault Saint-Felicien",
    "iso:country":"CA",
    "sg:address":"1491 Rue Verreault",
    "sg:city":"Saint-Felicien",
    "sg:classifiers":[
        {
            "category":"Freight",
            "type":"Transportation"
        }
    ],
    "sg:phone":"+1 418 679 2711",
    "sg:postcode":"G8K 1W2",
    "sg:province":"QC",
    "sg:tags":[
        "trucking"
    ],
    "wof:name":"Transport Roger Boivin & Fils",
    "wof:placetype":"venue"
},
  "geometry": {"coordinates":[-72.45311700000001,48.639214],"type":"Point"}
}