{
  "type": "Feature",
  "properties": {
    "addr:full":"979 Av DE Bourgogne # 430 Sainte-Foy QC G1W 2L4",
    "addr:postcode":"g1w 2l4",
    "addr:street":"979 Av De Bourgogne # 430",
    "iso:country":"CA",
    "sg:address":"979 Av DE Bourgogne # 430",
    "sg:city":"Sainte-Foy",
    "sg:classifiers":[
        {
            "category":"Professional",
            "subcategory":"Business Services",
            "type":"Services"
        }
    ],
    "sg:phone":"+1 418 656 1240",
    "sg:postcode":"G1W 2L4",
    "sg:province":"QC",
    "sg:tags":[
        "translator",
        "interpreter"
    ],
    "wof:name":"Compositon Ste-Foy Inc",
    "wof:placetype":"venue"
},
  "geometry": {"coordinates":[-71.310417,46.765804],"type":"Point"}
}