{
  "type": "Feature",
  "properties": {
    "iso:country":"CA",
    "sg:city":"Sidney",
    "sg:classifiers":[
        {
            "category":"Wholesale",
            "subcategory":"Machinery & Supplies",
            "type":"Manufacturing & Wholesale Goods"
        }
    ],
    "sg:phone":"+1 250 656 3928",
    "sg:postcode":"V8L 5X6",
    "sg:province":"BC",
    "wof:name":"Stanbuilt Manufacturing",
    "wof:placetype":"venue"
},
  "geometry": {"coordinates":[-123.415672302,48.6568145752],"type":"Point"}
}