{
  "type": "Feature",
  "properties": {
    "addr:full":"St Catharines ON L2N 1L1",
    "addr:postcode":"l2n 1l1",
    "iso:country":"CA",
    "sg:city":"St Catharines",
    "sg:classifiers":[
        {
            "category":"Retail",
            "subcategory":"Repair Shop",
            "type":"Services"
        }
    ],
    "sg:phone":"+1 905 646 4881",
    "sg:postcode":"L2N 1L1",
    "sg:province":"ON",
    "sg:tags":[
        "tool",
        "parts"
    ],
    "wof:name":"A & A Power Tool Repair",
    "wof:placetype":"venue"
},
  "geometry": {"coordinates":[-79.2482757568,43.1828231812],"type":"Point"}
}