{
  "type": "Feature",
  "properties": {
    "iso:country":"CA",
    "sg:address":"3248 Victoria St",
    "sg:city":"Oakville",
    "sg:classifiers":[
        {
            "category":"Retail",
            "subcategory":"Portrait Studio",
            "type":"Services"
        }
    ],
    "sg:phone":"+1 905 847 6354",
    "sg:postcode":"L6L 5R3",
    "sg:province":"ON",
    "sg:tags":[
        "photographer"
    ],
    "wof:name":"A Woman's Touch",
    "wof:placetype":"venue"
},
  "geometry": {"coordinates":[-79.71802520750001,43.3837509155],"type":"Point"}
}