{
  "type": "Feature",
  "properties": {
    "addr:full":"6855 Boul Couture Saint-Leonard QC H1P 3M6",
    "addr:housenumber":"6855",
    "addr:postcode":"h1p 3m6",
    "addr:street":"Boul Couture",
    "iso:country":"CA",
    "sg:address":"6855 Boul Couture",
    "sg:city":"Saint-Leonard",
    "sg:classifiers":[
        {
            "category":"Manufacturing",
            "subcategory":"Rubber & Plastics",
            "type":"Manufacturing & Wholesale Goods"
        }
    ],
    "sg:phone":"+1 514 321 9840",
    "sg:postcode":"H1P 3M6",
    "sg:province":"QC",
    "sg:tags":[
        "mold",
        "maker"
    ],
    "wof:name":"Plastipro Canada Ltd",
    "wof:placetype":"venue"
},
  "geometry": {"coordinates":[-73.59520721440001,45.6063194275],"type":"Point"}
}