{
  "type": "Feature",
  "properties": {
    "addr:full":"Red Deer AB T4N 1C8",
    "addr:postcode":"t4n 1c8",
    "iso:country":"CA",
    "sg:city":"Red Deer",
    "sg:classifiers":[
        {
            "category":"Utilities",
            "subcategory":"Mobile Phone",
            "type":"Services"
        }
    ],
    "sg:phone":"+1 403 346 3667",
    "sg:postcode":"T4N 1C8",
    "sg:province":"AB",
    "sg:tags":[
        "equipment",
        "telephone",
        "cellular",
        "supply"
    ],
    "wof:name":"Phone Experts Communications",
    "wof:placetype":"venue"
},
  "geometry": {"coordinates":[-113.822288513,52.2622871399],"type":"Point"}
}