{
  "type": "Feature",
  "properties": {
    "iso:country":"CA",
    "sg:city":"Chicoutimi",
    "sg:classifiers":[
        {
            "category":"Building & Trades",
            "subcategory":"Construction",
            "type":"Services"
        }
    ],
    "sg:phone":"+1 418 549 7705",
    "sg:postcode":"G7H 7Y1",
    "sg:province":"QC",
    "sg:tags":[
        "general",
        "contractor"
    ],
    "wof:name":"Gilbert Fernand Ltee",
    "wof:placetype":"venue"
},
  "geometry": {"coordinates":[-71.064491272,48.398765564],"type":"Point"}
}