{
  "type": "Feature",
  "properties": {
    "addr:full":"3569 Rue Laval Lac-Megantic QC G6B 1A5",
    "addr:housenumber":"3569",
    "addr:postcode":"g6b 1a5",
    "addr:street":"Rue Laval Lac-Megantic",
    "iso:country":"CA",
    "sg:address":"3569 Rue Laval",
    "sg:city":"Lac-Megantic",
    "sg:classifiers":[
        {
            "category":"Health Services",
            "subcategory":"Hospital",
            "type":"Services"
        }
    ],
    "sg:phone":"+1 819 583 0330",
    "sg:postcode":"G6B 1A5",
    "sg:province":"QC",
    "wof:name":"Carrefour Sante Du Granit",
    "wof:placetype":"venue"
},
  "geometry": {"coordinates":[-70.90483856199999,45.5890274048],"type":"Point"}
}