{
  "type": "Feature",
  "properties": {
    "iso:country":"CA",
    "sg:address":"100 Rue Des Dalles",
    "sg:city":"St-Barnabe-Nord",
    "sg:classifiers":[
        {
            "category":"Shopping",
            "subcategory":"Bicycles & Sporting Goods",
            "type":"Retail Goods"
        }
    ],
    "sg:phone":"+1 819 264 2051",
    "sg:postcode":"G0X 2K0",
    "sg:province":"QC",
    "wof:name":"Centre Du Bicycle",
    "wof:placetype":"venue"
},
  "geometry": {"coordinates":[-72.8800201416,46.393901825],"type":"Point"}
}