{
  "type": "Feature",
  "properties": {
    "addr:full":"52nd St & Hwy 13 Lougheed AB T0B 2V0",
    "addr:postcode":"t0b 2v0",
    "addr:street":"52Nd St & Hwy 13 Lougheed",
    "iso:country":"CA",
    "sg:address":"52nd St & Hwy 13",
    "sg:city":"Lougheed",
    "sg:classifiers":[
        {
            "category":"Manufacturing",
            "subcategory":"Tools & Machinery",
            "type":"Manufacturing & Wholesale Goods"
        }
    ],
    "sg:phone":"+1 780 386 3755",
    "sg:postcode":"T0B 2V0",
    "sg:province":"AB",
    "sg:tags":[
        "farm",
        "equipment"
    ],
    "wof:name":"Smith's Service Lougheed Ltd",
    "wof:placetype":"venue"
},
  "geometry": {"coordinates":[-111.531685,52.741039],"type":"Point"}
}