{
  "type": "Feature",
  "properties": {
    "iso:country":"CA",
    "sg:address":"5259 Tecumseh Rd E",
    "sg:city":"Windsor",
    "sg:classifiers":[
        {
            "category":"Recreation",
            "type":"Entertainment"
        }
    ],
    "sg:phone":"+1 519 948 5322",
    "sg:postcode":"N8T 1C5",
    "sg:province":"ON",
    "sg:tags":[
        "caterer",
        "hall",
        "auditorium"
    ],
    "wof:name":"Croatian Centre",
    "wof:placetype":"venue"
},
  "geometry": {"coordinates":[-82.961182,42.30851],"type":"Point"}
}