{
  "type": "Feature",
  "properties": {
    "addr:full":"8 Weldrick Rd W Richmond Hill ON L4C 3T8",
    "addr:housenumber":"8",
    "addr:postcode":"l4c 3t8",
    "addr:street":"Weldrick Rd W",
    "iso:country":"CA",
    "sg:address":"8 Weldrick Rd W",
    "sg:city":"Richmond Hill",
    "sg:classifiers":[
        {
            "category":"Real Estate",
            "subcategory":"Real Estate Agent",
            "type":"Services"
        }
    ],
    "sg:phone":"+1 905 883 4922",
    "sg:postcode":"L4C 3T8",
    "sg:province":"ON",
    "wof:name":"Re Max Executive Realty Inc",
    "wof:placetype":"venue"
},
  "geometry": {"coordinates":[-79.4356918335,43.8601531982],"type":"Point"}
}