{
  "type": "Feature",
  "properties": {
    "addr:full":"192 Tunnel St Sarnia ON N7T 2K2",
    "addr:housenumber":"192",
    "addr:postcode":"n7t 2k2",
    "addr:street":"Tunnel St",
    "iso:country":"CA",
    "sg:address":"192 Tunnel St",
    "sg:city":"Sarnia",
    "sg:classifiers":[
        {
            "category":"Manufacturing",
            "subcategory":"Tools & Machinery",
            "type":"Manufacturing & Wholesale Goods"
        }
    ],
    "sg:phone":"+1 519 339 0871",
    "sg:postcode":"N7T 2K2",
    "sg:province":"ON",
    "sg:tags":[
        "testing",
        "apparatus"
    ],
    "wof:name":"Dufort Testing Svc Ltd",
    "wof:placetype":"venue"
},
  "geometry": {"coordinates":[-82.402618,42.958366],"type":"Point"}
}