{
  "type": "Feature",
  "properties": {
    "addr:full":"16 Sandhurst Crt Brantford ON N3R 7G4",
    "addr:housenumber":"16",
    "addr:postcode":"n3r 7g4",
    "addr:street":"Sandhurst Crt",
    "iso:country":"CA",
    "sg:address":"16 Sandhurst Crt",
    "sg:city":"Brantford",
    "sg:classifiers":[
        {
            "category":"Manufacturing",
            "subcategory":"Signs",
            "type":"Manufacturing & Wholesale Goods"
        }
    ],
    "sg:phone":"+1 519 758 8230",
    "sg:postcode":"N3R 7G4",
    "sg:province":"ON",
    "wof:name":"Brant Specialties",
    "wof:placetype":"venue"
},
  "geometry": {"coordinates":[-80.2544937134,43.1879501343],"type":"Point"}
}