{
  "type": "Feature",
  "properties": {
    "addr:full":"99 Rue Notre-Dame O Victoriaville QC G6P 1R8",
    "addr:housenumber":"99",
    "addr:postcode":"g6p 1r8",
    "addr:street":"Rue Notre-Dame O",
    "iso:country":"CA",
    "sg:address":"99 Rue Notre-Dame O",
    "sg:city":"Victoriaville",
    "sg:classifiers":[
        {
            "category":"Real Estate",
            "subcategory":"Developer",
            "type":"Services"
        }
    ],
    "sg:phone":"+1 819 752 4525",
    "sg:postcode":"G6P 1R8",
    "sg:province":"QC",
    "sg:tags":[
        "cemetery"
    ],
    "wof:name":"Cimetieres St-Joseph St-Martyr",
    "wof:placetype":"venue"
},
  "geometry": {"coordinates":[-71.956322,46.056423],"type":"Point"}
}