{
  "type": "Feature",
  "properties": {
    "addr:full":"Essex ON N8M 2X7",
    "addr:postcode":"n8m 2x7",
    "iso:country":"CA",
    "sg:city":"Essex",
    "sg:classifiers":[
        {
            "category":"Building & Trades",
            "subcategory":"Construction",
            "type":"Services"
        }
    ],
    "sg:phone":"+1 519 723 4496",
    "sg:postcode":"N8M 2X7",
    "sg:province":"ON",
    "wof:name":"Louis Byrne & Sons Ltd",
    "wof:placetype":"venue"
},
  "geometry": {"coordinates":[-82.819672,42.172825],"type":"Point"}
}