{
  "type": "Feature",
  "properties": {
    "iso:country":"CA",
    "sg:address":"3983 Rue Wellington",
    "sg:city":"Verdun",
    "sg:classifiers":[
        {
            "category":"Shopping",
            "subcategory":"Stationery & Office Supplies",
            "type":"Retail Goods"
        }
    ],
    "sg:phone":"+1 514 768 9561",
    "sg:postcode":"H4G 1V6",
    "sg:province":"QC",
    "sg:tags":[
        "personal",
        "organizer",
        "planner",
        "miscellaneous",
        "store"
    ],
    "wof:name":"Aupel Inc",
    "wof:placetype":"venue"
},
  "geometry": {"coordinates":[-73.5671081543,45.4640083313],"type":"Point"}
}