{
  "type": "Feature",
  "properties": {
    "addr:full":"2475 Bayswater St Vancouver BC V6K 4N3",
    "addr:housenumber":"2475",
    "addr:postcode":"v6k 4n3",
    "addr:street":"Bayswater St",
    "iso:country":"CA",
    "sg:address":"2475 Bayswater St",
    "sg:city":"Vancouver",
    "sg:classifiers":[
        {
            "category":"Health Services",
            "subcategory":"Doctor",
            "type":"Services"
        }
    ],
    "sg:phone":"+1 604 733 5722",
    "sg:postcode":"V6K 4N3",
    "sg:province":"BC",
    "sg:tags":[
        "physician",
        "surgeon"
    ],
    "wof:name":"Marcus, Harvey MD",
    "wof:placetype":"venue"
},
  "geometry": {"coordinates":[-123.171272278,49.2643585205],"type":"Point"}
}