{
  "type": "Feature",
  "properties": {
    "iso:country":"CA",
    "sg:city":"Stoney Creek",
    "sg:classifiers":[
        {
            "category":"Manufacturing",
            "subcategory":"Tools & Machinery",
            "type":"Manufacturing & Wholesale Goods"
        }
    ],
    "sg:phone":"+1 905 662 7188",
    "sg:postcode":"L8E 2N3",
    "sg:province":"ON",
    "sg:tags":[
        "cleaning",
        "system"
    ],
    "wof:name":"Indcomm Power Products",
    "wof:placetype":"venue"
},
  "geometry": {"coordinates":[-79.7250671387,43.2295303345],"type":"Point"}
}