{
  "type": "Feature",
  "properties": {
    "addr:full":"Maxwell ON N0C 1J0",
    "addr:postcode":"n0c 1j0",
    "iso:country":"CA",
    "sg:city":"Maxwell",
    "sg:classifiers":[
        {
            "category":"Education",
            "subcategory":"School",
            "type":"Public Place"
        }
    ],
    "sg:phone":"+1 519 922 2341",
    "sg:postcode":"N0C 1J0",
    "sg:province":"ON",
    "wof:name":"Osprey Central School",
    "wof:placetype":"venue"
},
  "geometry": {"coordinates":[-80.38323200000001,44.312309],"type":"Point"}
}