{
  "type": "Feature",
  "properties": {
    "addr:full":"Saskatoon SK S7L 5Z5",
    "addr:postcode":"s7l 5z5",
    "iso:country":"CA",
    "sg:city":"Saskatoon",
    "sg:classifiers":[
        {
            "category":"Retail",
            "subcategory":"Auto Rental",
            "type":"Services"
        }
    ],
    "sg:phone":"+1 306 652 3434",
    "sg:postcode":"S7L 5Z5",
    "sg:province":"SK",
    "sg:tags":[
        "renting",
        "automobile"
    ],
    "wof:name":"Avis Car & Truck Rentals",
    "wof:placetype":"venue"
},
  "geometry": {"coordinates":[-106.674423218,52.1617240906],"type":"Point"}
}