{
  "type": "Feature",
  "properties": {
    "addr:full":"330 Portugal Cove Pl St. John's NL A1A 4Y5",
    "addr:housenumber":"330",
    "addr:postcode":"a1a 4y5",
    "addr:street":"Portugal Cove Pl",
    "iso:country":"CA",
    "sg:address":"330 Portugal Cove Pl",
    "sg:city":"St. John's",
    "sg:classifiers":[
        {
            "category":"Organizations",
            "subcategory":"Labor Organization",
            "type":"Services"
        }
    ],
    "sg:phone":"+1 709 726 5667",
    "sg:postcode":"A1A 4Y5",
    "sg:province":"NL",
    "wof:name":"Communication Energy-Paperwork",
    "wof:placetype":"venue"
},
  "geometry": {"coordinates":[-52.8507385254,47.6272201538],"type":"Point"}
}