{
  "type": "Feature",
  "properties": {
    "addr:full":"91 Elgin St Port Colborne ON L3K 3K1",
    "addr:housenumber":"91",
    "addr:postcode":"l3k 3k1",
    "addr:street":"Elgin St",
    "iso:country":"CA",
    "sg:address":"91 Elgin St",
    "sg:city":"Port Colborne",
    "sg:classifiers":[
        {
            "category":"Professional",
            "subcategory":"Management & Consulting",
            "type":"Services"
        }
    ],
    "sg:phone":"+1 905 834 6238",
    "sg:postcode":"L3K 3K1",
    "sg:province":"ON",
    "sg:tags":[
        "consultant",
        "business"
    ],
    "wof:name":"Porter & Porter",
    "wof:placetype":"venue"
},
  "geometry": {"coordinates":[-79.25507399999999,42.888416],"type":"Point"}
}