{
  "type": "Feature",
  "properties": {
    "addr:full":"3590 Dufferin Ave Prince George BC V2N 1E9",
    "addr:housenumber":"3590",
    "addr:postcode":"v2n 1e9",
    "addr:street":"Dufferin Ave",
    "iso:country":"CA",
    "sg:address":"3590 Dufferin Ave",
    "sg:city":"Prince George",
    "sg:classifiers":[
        {
            "category":"Organizations",
            "subcategory":"Religious Organization",
            "type":"Services"
        }
    ],
    "sg:phone":"+1 250 564 4336",
    "sg:postcode":"V2N 1E9",
    "sg:province":"BC",
    "sg:tags":[
        "church"
    ],
    "wof:name":"Lutheran Our Savior's Church",
    "wof:placetype":"venue"
},
  "geometry": {"coordinates":[-122.788132,53.895874],"type":"Point"}
}