{
  "type": "Feature",
  "properties": {
    "addr:full":"6195 Quick Ave Windsor ON N9J 3C7",
    "addr:housenumber":"6195",
    "addr:postcode":"n9j 3c7",
    "addr:street":"Quick Ave",
    "iso:country":"CA",
    "sg:address":"6195 Quick Ave",
    "sg:city":"Windsor",
    "sg:classifiers":[
        {
            "category":"Home & Garden",
            "subcategory":"Household Appliances",
            "type":"Retail Goods"
        }
    ],
    "sg:phone":"+1 519 734 1742",
    "sg:postcode":"N9J 3C7",
    "sg:province":"ON",
    "wof:name":"Thomsen's Appliance Svc",
    "wof:placetype":"venue"
},
  "geometry": {"coordinates":[-83.033913,42.317822],"type":"Point"}
}