{
  "type": "Feature",
  "properties": {
    "addr:full":"2492 Turton Crt Kelowna BC V1W 4B3",
    "addr:housenumber":"2492",
    "addr:postcode":"v1w 4b3",
    "addr:street":"Turton Crt",
    "iso:country":"CA",
    "sg:address":"2492 Turton Crt",
    "sg:city":"Kelowna",
    "sg:classifiers":[
        {
            "category":"Building & Trades",
            "subcategory":"Construction",
            "type":"Services"
        }
    ],
    "sg:phone":"+1 250 860 8318",
    "sg:postcode":"V1W 4B3",
    "sg:province":"BC",
    "sg:tags":[
        "concrete",
        "contractor",
        "general"
    ],
    "wof:name":"Lou's Concrete Finishing Ltd",
    "wof:placetype":"venue"
},
  "geometry": {"coordinates":[-119.431968689,49.8396606445],"type":"Point"}
}