{
  "type": "Feature",
  "properties": {
    "addr:full":"Liverpool NS B0T 1K0",
    "addr:postcode":"b0t 1k0",
    "iso:country":"CA",
    "sg:city":"Liverpool",
    "sg:classifiers":[
        {
            "category":"Wholesale",
            "subcategory":"Electrical",
            "type":"Manufacturing & Wholesale Goods"
        }
    ],
    "sg:phone":"+1 902 354 2886",
    "sg:postcode":"B0T 1K0",
    "sg:province":"NS",
    "sg:tags":[
        "equipment",
        "electric",
        "supply"
    ],
    "wof:name":"Guillevin International CO",
    "wof:placetype":"venue"
},
  "geometry": {"coordinates":[-64.720474,44.030567],"type":"Point"}
}