{
  "type": "Feature",
  "properties": {
    "iso:country":"CA",
    "sg:address":"78 Rue Grande-Ile",
    "sg:city":"Salaberry-DE-Valleyfield",
    "sg:classifiers":[
        {
            "category":"Retail",
            "subcategory":"Laundry & Dry Cleaning",
            "type":"Services"
        }
    ],
    "sg:phone":"+1 450 371 0225",
    "sg:postcode":"J6S 3M2",
    "sg:province":"QC",
    "sg:tags":[
        "cleaners"
    ],
    "wof:name":"Nettoyeur Unic",
    "wof:placetype":"venue"
},
  "geometry": {"coordinates":[-74.13287353520001,45.263885498],"type":"Point"}
}