{
  "type": "Feature",
  "properties": {
    "addr:full":"139 Prom Du Portage Hull QC J8X 2K2",
    "addr:housenumber":"139",
    "addr:postcode":"j8x 2k2",
    "addr:street":"Prom Du Portage",
    "iso:country":"CA",
    "sg:address":"139 Prom Du Portage",
    "sg:city":"Hull",
    "sg:classifiers":[
        {
            "category":"Shopping",
            "subcategory":"Bicycles & Sporting Goods",
            "type":"Retail Goods"
        }
    ],
    "sg:phone":"+1 819 770 7447",
    "sg:postcode":"J8X 2K2",
    "sg:province":"QC",
    "wof:name":"Foulee Sportive Inc",
    "wof:placetype":"venue"
},
  "geometry": {"coordinates":[-75.716919,45.425598],"type":"Point"}
}