{
  "type": "Feature",
  "properties": {
    "addr:full":"Welland ON L3C 3W6",
    "addr:postcode":"l3c 3w6",
    "iso:country":"CA",
    "sg:city":"Welland",
    "sg:classifiers":[
        {
            "category":"Health Services",
            "subcategory":"Chiropractor",
            "type":"Services"
        }
    ],
    "sg:phone":"+1 905 735 8422",
    "sg:postcode":"L3C 3W6",
    "sg:province":"ON",
    "wof:name":"Zavitz Chiropractic",
    "wof:placetype":"venue"
},
  "geometry": {"coordinates":[-79.268463,43.003876],"type":"Point"}
}