{
  "type": "Feature",
  "properties": {
    "addr:full":"420 Winnipeg Ave Thunder Bay ON P7B 6B7",
    "addr:housenumber":"420",
    "addr:postcode":"p7b 6b7",
    "addr:street":"Winnipeg Ave",
    "iso:country":"CA",
    "sg:address":"420 Winnipeg Ave",
    "sg:city":"Thunder Bay",
    "sg:classifiers":[
        {
            "category":"Government",
            "subcategory":"Office",
            "type":"Public Place"
        }
    ],
    "sg:phone":"+1 807 684 3311",
    "sg:postcode":"P7B 6B7",
    "sg:province":"ON",
    "sg:tags":[
        "village"
    ],
    "wof:name":"Canada Games Complex",
    "wof:placetype":"venue"
},
  "geometry": {"coordinates":[-89.241035,48.423546],"type":"Point"}
}