{
  "type": "Feature",
  "properties": {
    "addr:full":"Portland ON K0G 1V0",
    "addr:postcode":"k0g 1v0",
    "iso:country":"CA",
    "sg:city":"Portland",
    "sg:classifiers":[
        {
            "category":"Health Services",
            "subcategory":"Nursing And Care Facility",
            "type":"Services"
        }
    ],
    "sg:phone":"+1 613 272 3303",
    "sg:postcode":"K0G 1V0",
    "sg:province":"ON",
    "sg:tags":[
        "home",
        "retirement",
        "community"
    ],
    "wof:name":"Mill Bay Court",
    "wof:placetype":"venue"
},
  "geometry": {"coordinates":[-76.18821,44.698425],"type":"Point"}
}