{
  "type": "Feature",
  "properties": {
    "addr:full":"349 Waterloo St Winnipeg MB R3N 0S7",
    "addr:housenumber":"349",
    "addr:postcode":"r3n 0s7",
    "addr:street":"Waterloo St",
    "iso:country":"CA",
    "sg:address":"349 Waterloo St",
    "sg:city":"Winnipeg",
    "sg:classifiers":[
        {
            "category":"Shopping",
            "subcategory":"Stationery & Office Supplies",
            "type":"Retail Goods"
        }
    ],
    "sg:phone":"+1 204 488 0091",
    "sg:postcode":"R3N 0S7",
    "sg:province":"MB",
    "sg:tags":[
        "rubber",
        "stamp",
        "marking",
        "devices",
        "plastic"
    ],
    "wof:name":"St James Rubber Stamp Shop",
    "wof:placetype":"venue"
},
  "geometry": {"coordinates":[-97.184425354,49.8684539795],"type":"Point"}
}