{
  "type": "Feature",
  "properties": {
    "iso:country":"CA",
    "sg:address":"107 Marshall St",
    "sg:city":"Barrie",
    "sg:classifiers":[
        {
            "category":"Building & Trades",
            "subcategory":"Plumbing",
            "type":"Services"
        }
    ],
    "sg:phone":"+1 705 728 6495",
    "sg:postcode":"L4N 4K7",
    "sg:province":"ON",
    "sg:tags":[
        "contractor"
    ],
    "wof:name":"M A Waddell Plumbing",
    "wof:placetype":"venue"
},
  "geometry": {"coordinates":[-79.6899108887,44.3599281311],"type":"Point"}
}