{
  "type": "Feature",
  "properties": {
    "addr:full":"5548 Sebastian Pl Halifax NS B3K 2K6",
    "addr:housenumber":"5548",
    "addr:postcode":"b3k 2k6",
    "addr:street":"Sebastian Pl",
    "iso:country":"CA",
    "sg:address":"5548 Sebastian Pl",
    "sg:city":"Halifax",
    "sg:classifiers":[
        {
            "category":"Professional",
            "subcategory":"Research",
            "type":"Services"
        }
    ],
    "sg:phone":"+1 902 431 6356",
    "sg:postcode":"B3K 2K6",
    "sg:province":"NS",
    "sg:tags":[
        "ergonomics"
    ],
    "wof:name":"Ergonomics Systems Assoc",
    "wof:placetype":"venue"
},
  "geometry": {"coordinates":[-63.6057281494,44.6663017273],"type":"Point"}
}