{
  "type": "Feature",
  "properties": {
    "iso:country":"CA",
    "sg:address":"133 Saunders Rd",
    "sg:city":"Mcadam",
    "sg:classifiers":[
        {
            "category":"Banks & Credit Unions",
            "subcategory":"Bank",
            "type":"Services"
        }
    ],
    "sg:phone":"+1 506 784 2234",
    "sg:postcode":"E6J 1L7",
    "sg:province":"NB",
    "wof:name":"Scotiabank",
    "wof:placetype":"venue"
},
  "geometry": {"coordinates":[-67.3277130127,45.5931243896],"type":"Point"}
}