{
  "type": "Feature",
  "properties": {
    "addr:full":"132 Rue Eddy Hull QC J8X 2W8",
    "addr:housenumber":"132",
    "addr:postcode":"j8x 2w8",
    "addr:street":"Rue Eddy",
    "iso:country":"CA",
    "sg:address":"132 Rue Eddy",
    "sg:city":"Hull",
    "sg:classifiers":[
        {
            "category":"Personal",
            "subcategory":"Beauty Salon",
            "type":"Services"
        }
    ],
    "sg:phone":"+1 819 777 4445",
    "sg:postcode":"J8X 2W8",
    "sg:province":"QC",
    "wof:name":"Salon Le Regard Elle & Lui",
    "wof:placetype":"venue"
},
  "geometry": {"coordinates":[-75.71997833250001,45.4294052124],"type":"Point"}
}