{
  "type": "Feature",
  "properties": {
    "addr:full":"Azilda ON P0M 1B0",
    "addr:postcode":"p0m 1b0",
    "iso:country":"CA",
    "sg:city":"Azilda",
    "sg:classifiers":[
        {
            "category":"Shopping",
            "subcategory":"Department Store",
            "type":"Retail Goods"
        }
    ],
    "sg:phone":"+1 705 983 4132",
    "sg:postcode":"P0M 1B0",
    "sg:province":"ON",
    "sg:tags":[
        "shop"
    ],
    "wof:name":"Dollar Stop",
    "wof:placetype":"venue"
},
  "geometry": {"coordinates":[-81.1189422607,46.5532035828],"type":"Point"}
}