{
  "type": "Feature",
  "properties": {
    "addr:full":"Vancouver BC V5L 2G8",
    "addr:postcode":"v5l 2g8",
    "iso:country":"CA",
    "sg:city":"Vancouver",
    "sg:classifiers":[
        {
            "category":"Communications",
            "subcategory":"Radio Station",
            "type":"Services"
        }
    ],
    "sg:phone":"+1 604 255 2200",
    "sg:postcode":"V5L 2G8",
    "sg:province":"BC",
    "sg:tags":[
        "company",
        "broadcasting"
    ],
    "wof:name":"S W Davis Broadcast Technical",
    "wof:placetype":"venue"
},
  "geometry": {"coordinates":[-123.07328800000001,49.276794],"type":"Point"}
}