{
  "type": "Feature",
  "properties": {
    "addr:full":"49 Davis St Dryden ON P8N 1R7",
    "addr:housenumber":"49",
    "addr:postcode":"p8n 1r7",
    "addr:street":"Davis St",
    "iso:country":"CA",
    "sg:address":"49 Davis St",
    "sg:city":"Dryden",
    "sg:classifiers":[
        {
            "category":"Manufacturing",
            "subcategory":"Lumber",
            "type":"Manufacturing & Wholesale Goods"
        }
    ],
    "sg:phone":"+1 807 223 8458",
    "sg:postcode":"P8N 1R7",
    "sg:province":"ON",
    "sg:tags":[
        "forester"
    ],
    "wof:name":"Signal Weather Svc",
    "wof:placetype":"venue"
},
  "geometry": {"coordinates":[-92.83854700000001,49.774376],"type":"Point"}
}