{
  "type": "Feature",
  "properties": {
    "addr:full":"615 20E Av Deux-Montagnes QC J7R 6B2",
    "addr:housenumber":"615",
    "addr:postcode":"j7r 6b2",
    "addr:street":"20E Av Deux-Montagnes",
    "iso:country":"CA",
    "sg:address":"615 20E Av",
    "sg:city":"Deux-Montagnes",
    "sg:classifiers":[
        {
            "category":"Government",
            "subcategory":"Fire Station",
            "type":"Public Place"
        }
    ],
    "sg:phone":"+1 ",
    "sg:postcode":"J7R 6B2",
    "sg:province":"QC",
    "sg:tags":[
        "department"
    ],
    "wof:name":"Deux-Montagnes Fire-Incendies",
    "wof:placetype":"venue"
},
  "geometry": {"coordinates":[-73.9154586792,45.543132782],"type":"Point"}
}