{
  "type": "Feature",
  "properties": {
    "addr:full":"Weyburn SK S4H 2K1",
    "addr:postcode":"s4h 2k1",
    "iso:country":"CA",
    "sg:city":"Weyburn",
    "sg:classifiers":[
        {
            "category":"Government",
            "subcategory":"Office",
            "type":"Public Place"
        }
    ],
    "sg:phone":"+1 306 456 2566",
    "sg:postcode":"S4H 2K1",
    "sg:province":"SK",
    "sg:tags":[
        "municipality"
    ],
    "wof:name":"Rural Municipality of Lomond",
    "wof:placetype":"venue"
},
  "geometry": {"coordinates":[-103.858192,49.66803],"type":"Point"}
}