{
  "type": "Feature",
  "properties": {
    "addr:full":"92 Arlington Dr Moncton NB E1E 3J1",
    "addr:housenumber":"92",
    "addr:postcode":"e1e 3j1",
    "addr:street":"Arlington Dr",
    "iso:country":"CA",
    "sg:address":"92 Arlington Dr",
    "sg:city":"Moncton",
    "sg:classifiers":[
        {
            "category":"Personal",
            "subcategory":"Beauty Salon",
            "type":"Services"
        }
    ],
    "sg:phone":"+1 506 384 4247",
    "sg:postcode":"E1E 3J1",
    "sg:province":"NB",
    "wof:name":"Arlington Place",
    "wof:placetype":"venue"
},
  "geometry": {"coordinates":[-64.80061340330001,46.0856781006],"type":"Point"}
}