{
  "type": "Feature",
  "properties": {
    "addr:full":"465 Victoria Ave Windsor ON N9A 4N1",
    "addr:housenumber":"465",
    "addr:postcode":"n9a 4n1",
    "addr:street":"Victoria Ave",
    "iso:country":"CA",
    "sg:address":"465 Victoria Ave",
    "sg:city":"Windsor",
    "sg:classifiers":[
        {
            "category":"Education",
            "subcategory":"School",
            "type":"Public Place"
        }
    ],
    "sg:phone":"+1 519 977 6161",
    "sg:postcode":"N9A 4N1",
    "sg:province":"ON",
    "wof:name":"St Michael's Alternate Program",
    "wof:placetype":"venue"
},
  "geometry": {"coordinates":[-83.039963,42.314945],"type":"Point"}
}