{
  "type": "Feature",
  "properties": {
    "iso:country":"CA",
    "sg:address":"3703 Rue Monselet",
    "sg:city":"Montreal-Nord",
    "sg:classifiers":[
        {
            "category":"Shopping",
            "subcategory":"Computers & Home Electronics",
            "type":"Retail Goods"
        }
    ],
    "sg:phone":"+1 514 321 3642",
    "sg:postcode":"H1H 2B3",
    "sg:province":"QC",
    "sg:tags":[
        "equipment",
        "dealer"
    ],
    "wof:name":"Mc Microtech",
    "wof:placetype":"venue"
},
  "geometry": {"coordinates":[-73.64209747309999,45.587387085],"type":"Point"}
}