{
  "type": "Feature",
  "properties": {
    "iso:country":"CA",
    "sg:city":"Calgary",
    "sg:classifiers":[
        {
            "category":"Wholesale",
            "subcategory":"Hardware",
            "type":"Manufacturing & Wholesale Goods"
        }
    ],
    "sg:phone":"+1 403 248 8000",
    "sg:postcode":"T2A 5P1",
    "sg:province":"AB",
    "sg:tags":[
        "closer",
        "door",
        "devices",
        "operating",
        "gate",
        "check"
    ],
    "wof:name":"Auto Magic Entrance Sys Ltd",
    "wof:placetype":"venue"
},
  "geometry": {"coordinates":[-113.986198425,51.0635375977],"type":"Point"}
}