{
  "type": "Feature",
  "properties": {
    "addr:full":"660 28th St Fort Macleod AB T0L 0Z0",
    "addr:housenumber":"660",
    "addr:postcode":"t0l 0z0",
    "addr:street":"28Th St",
    "iso:country":"CA",
    "sg:address":"660 28th St",
    "sg:city":"Fort Macleod",
    "sg:classifiers":[
        {
            "category":"Real Estate",
            "subcategory":"Real Estate Operator",
            "type":"Services"
        }
    ],
    "sg:phone":"+1 403 553 3663",
    "sg:postcode":"T0L 0Z0",
    "sg:province":"AB",
    "sg:tags":[
        "apartment"
    ],
    "wof:name":"Mac Leod Pioneer Lodge",
    "wof:placetype":"venue"
},
  "geometry": {"coordinates":[-113.39598100000001,49.728451],"type":"Point"}
}