{
  "type": "Feature",
  "properties": {
    "addr:full":"Annapolis Royal NS B0S 1A0",
    "addr:postcode":"b0s 1a0",
    "iso:country":"CA",
    "sg:city":"Annapolis Royal",
    "sg:classifiers":[
        {
            "category":"Organizations",
            "subcategory":"Non-profit Organization",
            "type":"Services"
        }
    ],
    "sg:phone":"+1 902 532 7069",
    "sg:postcode":"B0S 1A0",
    "sg:province":"NS",
    "sg:tags":[
        "charitable",
        "institution"
    ],
    "wof:name":"Annapolis Region Community Art",
    "wof:placetype":"venue"
},
  "geometry": {"coordinates":[-65.51486199999999,44.741615],"type":"Point"}
}