{
  "type": "Feature",
  "properties": {
    "addr:full":"284 Smythe St Fredericton NB E3B 3C9",
    "addr:housenumber":"284",
    "addr:postcode":"e3b 3c9",
    "addr:street":"Smythe St",
    "iso:country":"CA",
    "sg:address":"284 Smythe St",
    "sg:city":"Fredericton",
    "sg:classifiers":[
        {
            "category":"Education",
            "subcategory":"College",
            "type":"Public Place"
        }
    ],
    "sg:phone":"+1 506 453 3641",
    "sg:postcode":"E3B 3C9",
    "sg:province":"NB",
    "sg:tags":[
        "academic",
        "school"
    ],
    "wof:name":"College Communautaire-NB",
    "wof:placetype":"venue"
},
  "geometry": {"coordinates":[-66.653206,45.961971],"type":"Point"}
}