{
  "type": "Feature",
  "properties": {
    "addr:full":"10814 106 Ave NW Edmonton AB T5H 4E1",
    "addr:housenumber":"10814",
    "addr:postcode":"t5h 4e1",
    "addr:street":"106 Ave Nw",
    "iso:country":"CA",
    "sg:address":"10814 106 Ave NW",
    "sg:city":"Edmonton",
    "sg:classifiers":[
        {
            "category":"Organizations",
            "subcategory":"Professional Association",
            "type":"Services"
        }
    ],
    "sg:phone":"+1 780 455 2601",
    "sg:postcode":"T5H 4E1",
    "sg:province":"AB",
    "sg:tags":[
        "school"
    ],
    "wof:name":"Excel Society",
    "wof:placetype":"venue"
},
  "geometry": {"coordinates":[-113.506989,53.549942],"type":"Point"}
}