{
  "type": "Feature",
  "properties": {
    "iso:country":"CA",
    "sg:address":"3320 Kalum St",
    "sg:city":"Terrace",
    "sg:classifiers":[
        {
            "category":"Government",
            "subcategory":"Office",
            "type":"Public Place"
        }
    ],
    "sg:phone":"+1 250 638 4750",
    "sg:postcode":"V8G 2N6",
    "sg:province":"BC",
    "sg:tags":[
        "provincial",
        "parks",
        "village"
    ],
    "wof:name":"Terrace Parks & Recreation Ofc",
    "wof:placetype":"venue"
},
  "geometry": {"coordinates":[-128.586334228,54.5186157227],"type":"Point"}
}