{
  "type": "Feature",
  "properties": {
    "iso:country":"CA",
    "sg:address":"1095 Rue Legendre E",
    "sg:city":"Montreal",
    "sg:classifiers":[
        {
            "category":"Health Services",
            "subcategory":"Doctor",
            "type":"Services"
        }
    ],
    "sg:phone":"+1 514 385 3368",
    "sg:postcode":"H2M 2N2",
    "sg:province":"QC",
    "sg:tags":[
        "dentist"
    ],
    "wof:name":"Grilo, Carla DDS",
    "wof:placetype":"venue"
},
  "geometry": {"coordinates":[-73.6406707764,45.5559463501],"type":"Point"}
}