{
  "type": "Feature",
  "properties": {
    "addr:full":"55 Elora St S Harriston ON N0G 1Z0",
    "addr:housenumber":"55",
    "addr:postcode":"n0g 1z0",
    "addr:street":"Elora St S",
    "iso:country":"CA",
    "sg:address":"55 Elora St S",
    "sg:city":"Harriston",
    "sg:classifiers":[
        {
            "category":"Building & Trades",
            "subcategory":"Plumbing",
            "type":"Services"
        }
    ],
    "sg:phone":"+1 519 338 3823",
    "sg:postcode":"N0G 1Z0",
    "sg:province":"ON",
    "sg:tags":[
        "contractor"
    ],
    "wof:name":"Don Wallace & Son Plbg & Htg",
    "wof:placetype":"venue"
},
  "geometry": {"coordinates":[-80.8692932129,43.9123001099],"type":"Point"}
}