{
  "type": "Feature",
  "properties": {
    "iso:country":"CA",
    "sg:city":"Montague",
    "sg:classifiers":[
        {
            "category":"Autos & Motor Vehicles",
            "subcategory":"Automobile Sales",
            "type":"Retail Goods"
        }
    ],
    "sg:phone":"+1 902 838 4775",
    "sg:postcode":"C0A 1R0",
    "sg:province":"PE",
    "sg:tags":[
        "car",
        "dealer"
    ],
    "wof:name":"Fair Isle Ford Sales Ltd",
    "wof:placetype":"venue"
},
  "geometry": {"coordinates":[-62.6400184631,46.1575088501],"type":"Point"}
}