{
  "type": "Feature",
  "properties": {
    "addr:full":"125 King St London ON N6A 1C3",
    "addr:housenumber":"125",
    "addr:postcode":"n6a 1c3",
    "addr:street":"King St",
    "iso:country":"CA",
    "sg:address":"125 King St",
    "sg:city":"London",
    "sg:classifiers":[
        {
            "category":"Food & Beverages",
            "subcategory":"Bakery",
            "type":"Retail Goods"
        }
    ],
    "sg:phone":"+1 519 433 2759",
    "sg:postcode":"N6A 1C3",
    "sg:province":"ON",
    "sg:tags":[
        "baker"
    ],
    "wof:name":"Cakewalkers Inc",
    "wof:placetype":"venue"
},
  "geometry": {"coordinates":[-81.2506637573,42.9819259644],"type":"Point"}
}