{
  "type": "Feature",
  "properties": {
    "addr:full":"Stella Rd Fraser Lake BC V0J 1S0",
    "addr:postcode":"v0j 1s0",
    "addr:street":"Stella Rd",
    "iso:country":"CA",
    "sg:address":"Stella Rd",
    "sg:city":"Fraser Lake",
    "sg:classifiers":[
        {
            "category":"Manufacturing",
            "subcategory":"Lumber",
            "type":"Manufacturing & Wholesale Goods"
        }
    ],
    "sg:phone":"+1 250 699 6554",
    "sg:postcode":"V0J 1S0",
    "sg:province":"BC",
    "sg:tags":[
        "company",
        "logging"
    ],
    "wof:name":"Selkin Logging Ltd",
    "wof:placetype":"venue"
},
  "geometry": {"coordinates":[-124.845947,54.057343],"type":"Point"}
}