{
  "type": "Feature",
  "properties": {
    "addr:full":"1515 10E Rue Saint-Come-Liniere QC G0M 1J0",
    "addr:housenumber":"1515",
    "addr:postcode":"g0m 1j0",
    "addr:street":"10E Rue Saint-Come-Liniere",
    "iso:country":"CA",
    "sg:address":"1515 10E Rue",
    "sg:city":"Saint-Come-Liniere",
    "sg:classifiers":[
        {
            "category":"Manufacturing",
            "subcategory":"Apparel",
            "type":"Manufacturing & Wholesale Goods"
        }
    ],
    "sg:phone":"+1 418 685 3840",
    "sg:postcode":"G0M 1J0",
    "sg:province":"QC",
    "sg:tags":[
        "clothing"
    ],
    "wof:name":"Confections DE Beauce Inc",
    "wof:placetype":"venue"
},
  "geometry": {"coordinates":[-70.524734,46.062267],"type":"Point"}
}