{
  "type": "Feature",
  "properties": {
    "addr:full":"Mississauga ON L5S 1T7",
    "addr:postcode":"l5s 1t7",
    "iso:country":"CA",
    "sg:city":"Mississauga",
    "sg:classifiers":[
        {
            "category":"Organizations",
            "subcategory":"Labor Organization",
            "type":"Services"
        }
    ],
    "sg:phone":"+1 905 678 1550",
    "sg:postcode":"L5S 1T7",
    "sg:province":"ON",
    "wof:name":"Caw",
    "wof:placetype":"venue"
},
  "geometry": {"coordinates":[-79.66776275629999,43.6831855774],"type":"Point"}
}