{
  "type": "Feature",
  "properties": {
    "addr:full":"900 11th Ave Regina SK S4N 0K7",
    "addr:housenumber":"900",
    "addr:postcode":"s4n 0k7",
    "addr:street":"11Th Ave",
    "iso:country":"CA",
    "sg:address":"900 11th Ave",
    "sg:city":"Regina",
    "sg:classifiers":[
        {
            "category":"Social Services",
            "type":"Services"
        }
    ],
    "sg:phone":"+1 306 352 0016",
    "sg:postcode":"S4N 0K7",
    "sg:province":"SK",
    "sg:tags":[
        "organization",
        "welfare"
    ],
    "wof:name":"Visitation House",
    "wof:placetype":"venue"
},
  "geometry": {"coordinates":[-104.593887,50.450485],"type":"Point"}
}