{
  "type": "Feature",
  "properties": {
    "addr:full":"86 Avenue Rd Toronto ON M5R 2H2",
    "addr:housenumber":"86",
    "addr:postcode":"m5r 2h2",
    "addr:street":"Avenue Rd",
    "iso:country":"CA",
    "sg:address":"86 Avenue Rd",
    "sg:city":"Toronto",
    "sg:classifiers":[
        {
            "category":"Banks & Credit Unions",
            "subcategory":"Investment Brokerage",
            "type":"Services"
        }
    ],
    "sg:phone":"+1 416 927 7740",
    "sg:postcode":"M5R 2H2",
    "sg:province":"ON",
    "sg:tags":[
        "advisory",
        "financial"
    ],
    "wof:name":"Kingwest & CO",
    "wof:placetype":"venue"
},
  "geometry": {"coordinates":[-79.395775,43.672272],"type":"Point"}
}