{
  "type": "Feature",
  "properties": {
    "addr:full":"12211 Bridgeport Rd Richmond BC V6V 1J4",
    "addr:housenumber":"12211",
    "addr:postcode":"v6v 1j4",
    "addr:street":"Bridgeport Rd",
    "iso:country":"CA",
    "sg:address":"12211 Bridgeport Rd",
    "sg:city":"Richmond",
    "sg:classifiers":[
        {
            "category":"Retail",
            "subcategory":"Auto Repair",
            "type":"Services"
        }
    ],
    "sg:phone":"+1 604 273 7670",
    "sg:postcode":"V6V 1J4",
    "sg:province":"BC",
    "sg:tags":[
        "body",
        "automobile",
        "painting"
    ],
    "wof:name":"Mastercraft Autobody Ltd",
    "wof:placetype":"venue"
},
  "geometry": {"coordinates":[-123.088104,49.192196],"type":"Point"}
}