{
  "type": "Feature",
  "properties": {
    "addr:full":"224 2nd Ave Cromer MB R0M 0J0",
    "addr:housenumber":"224",
    "addr:postcode":"r0m 0j0",
    "addr:street":"2Nd Ave",
    "iso:country":"CA",
    "sg:address":"224 2nd Ave",
    "sg:city":"Cromer",
    "sg:classifiers":[
        {
            "category":"Building & Trades",
            "subcategory":"Construction",
            "type":"Services"
        }
    ],
    "sg:phone":"+1 204 748 5560",
    "sg:postcode":"R0M 0J0",
    "sg:province":"MB",
    "sg:tags":[
        "home",
        "builder"
    ],
    "wof:name":"Cromer Valley Construction",
    "wof:placetype":"venue"
},
  "geometry": {"coordinates":[-101.23584,49.730865],"type":"Point"}
}