{
  "type": "Feature",
  "properties": {
    "addr:full":"53730 Bridal Falls Rd Rosedale BC V0X 1X0",
    "addr:postcode":"53730;v0x 1x0",
    "addr:street":"Bridal Falls Rd",
    "iso:country":"CA",
    "sg:address":"53730 Bridal Falls Rd",
    "sg:city":"Rosedale",
    "sg:classifiers":[
        {
            "category":"Travel",
            "subcategory":"Hotels & Motels",
            "type":"Entertainment"
        }
    ],
    "sg:phone":"+1 604 794 7876",
    "sg:postcode":"V0X 1X0",
    "sg:province":"BC",
    "sg:tags":[
        "resort"
    ],
    "wof:name":"Holiday Trails Resorts Inc",
    "wof:placetype":"venue"
},
  "geometry": {"coordinates":[-121.805626,49.18211],"type":"Point"}
}