{
  "type": "Feature",
  "properties": {
    "iso:country":"CA",
    "sg:address":"5070 Fairwind Dr",
    "sg:city":"Mississauga",
    "sg:classifiers":[
        {
            "category":"Education",
            "subcategory":"School",
            "type":"Public Place"
        }
    ],
    "sg:phone":"+1 905 568 0056",
    "sg:postcode":"L5R 2N4",
    "sg:province":"ON",
    "wof:name":"St Hilary School",
    "wof:placetype":"venue"
},
  "geometry": {"coordinates":[-79.660919,43.604431],"type":"Point"}
}