{
  "type": "Feature",
  "properties": {
    "addr:full":"PO Box 330 Big Trout Lake ON P0V 1G0",
    "addr:housenumber":"po",
    "addr:postcode":"p0v 1g0",
    "addr:street":"Box 330;Trout",
    "iso:country":"CA",
    "sg:address":"PO Box 330",
    "sg:city":"Big Trout Lake",
    "sg:classifiers":[
        {
            "category":"Utilities",
            "subcategory":"Cable",
            "type":"Services"
        }
    ],
    "sg:phone":"+1 807 537 2270",
    "sg:postcode":"P0V 1G0",
    "sg:province":"ON",
    "sg:tags":[
        "internet"
    ],
    "wof:name":"K I Telecom Ctr",
    "wof:placetype":"venue"
},
  "geometry": {"coordinates":[-89.83509100000001,53.81876],"type":"Point"}
}