{
  "type": "Feature",
  "properties": {
    "addr:full":"869 Rue Mccrea Sherbrooke QC J1L 2N3",
    "addr:housenumber":"869",
    "addr:postcode":"j1l 2n3",
    "addr:street":"Rue Mccrea",
    "iso:country":"CA",
    "sg:address":"869 Rue Mccrea",
    "sg:city":"Sherbrooke",
    "sg:classifiers":[
        {
            "category":"Personal",
            "type":"Services"
        }
    ],
    "sg:phone":"+1 819 348 0945",
    "sg:postcode":"J1L 2N3",
    "sg:province":"QC",
    "sg:tags":[
        "therapist",
        "massage"
    ],
    "wof:name":"Elie, Diane",
    "wof:placetype":"venue"
},
  "geometry": {"coordinates":[-71.9564819336,45.411315918],"type":"Point"}
}