{
  "type": "Feature",
  "properties": {
    "addr:full":"Lac-Frontiere QC G0R 1T0",
    "addr:postcode":"g0r 1t0",
    "iso:country":"CA",
    "sg:city":"Lac-Frontiere",
    "sg:classifiers":[
        {
            "category":"Travel",
            "subcategory":"Campground",
            "type":"Entertainment"
        }
    ],
    "sg:phone":"+1 418 245 3459",
    "sg:postcode":"G0R 1T0",
    "sg:province":"QC",
    "sg:tags":[
        "camp",
        "fishing"
    ],
    "wof:name":"Pourvoirie Le Reve Du Chasseur",
    "wof:placetype":"venue"
},
  "geometry": {"coordinates":[-69.9848251343,46.7179260254],"type":"Point"}
}