{
  "type": "Feature",
  "properties": {
    "addr:full":"Sainte-Foy QC G1V 4N3",
    "addr:postcode":"g1v 4n3",
    "iso:country":"CA",
    "sg:city":"Sainte-Foy",
    "sg:classifiers":[
        {
            "category":"Professional",
            "subcategory":"Accounting & Tax Preparation",
            "type":"Services"
        }
    ],
    "sg:phone":"+1 418 656 1163",
    "sg:postcode":"G1V 4N3",
    "sg:province":"QC",
    "sg:tags":[
        "consultant"
    ],
    "wof:name":"Fiscalite Plus Sec",
    "wof:placetype":"venue"
},
  "geometry": {"coordinates":[-71.293999,46.764862],"type":"Point"}
}