{
  "type": "Feature",
  "properties": {
    "iso:country":"CA",
    "sg:address":"10181 Boul Pie-Ix",
    "sg:city":"Montreal-Nord",
    "sg:classifiers":[
        {
            "category":"Bars & Pubs",
            "type":"Food & Drink"
        }
    ],
    "sg:phone":"+1 514 325 0940",
    "sg:postcode":"H1H 3Z4",
    "sg:province":"QC",
    "sg:tags":[
        "lounge",
        "cocktail"
    ],
    "wof:name":"Cabaret Chez Mado",
    "wof:placetype":"venue"
},
  "geometry": {"coordinates":[-73.631279,45.585484],"type":"Point"}
}