{
  "type": "Feature",
  "properties": {
    "addr:full":"Scarborough ON M1S 5B3",
    "addr:postcode":"m1s 5b3",
    "iso:country":"CA",
    "sg:city":"Scarborough",
    "sg:classifiers":[
        {
            "category":"Shopping",
            "subcategory":"Stationery & Office Supplies",
            "type":"Retail Goods"
        }
    ],
    "sg:phone":"+1 416 297 6476",
    "sg:postcode":"M1S 5B3",
    "sg:province":"ON",
    "wof:name":"Harding Friden Business Mach",
    "wof:placetype":"venue"
},
  "geometry": {"coordinates":[-79.2535858154,43.7905960083],"type":"Point"}
}