{
  "type": "Feature",
  "properties": {
    "addr:full":"30 Penn Dr North York ON M9L 2A9",
    "addr:housenumber":"30",
    "addr:postcode":"m9l 2a9",
    "addr:street":"Penn Dr",
    "iso:country":"CA",
    "sg:address":"30 Penn Dr",
    "sg:city":"North York",
    "sg:classifiers":[
        {
            "category":"Manufacturing",
            "subcategory":"Lumber",
            "type":"Manufacturing & Wholesale Goods"
        }
    ],
    "sg:phone":"+1 416 744 2488",
    "sg:postcode":"M9L 2A9",
    "sg:province":"ON",
    "sg:tags":[
        "frame",
        "furniture"
    ],
    "wof:name":"Contour Frames Ltd",
    "wof:placetype":"venue"
},
  "geometry": {"coordinates":[-79.555611,43.751591],"type":"Point"}
}