{
  "type": "Feature",
  "properties": {
    "addr:full":"North York ON M3N 1W8",
    "addr:postcode":"m3n 1w8",
    "iso:country":"CA",
    "sg:city":"North York",
    "sg:classifiers":[
        {
            "category":"Manufacturing",
            "subcategory":"Retail Goods",
            "type":"Manufacturing & Wholesale Goods"
        }
    ],
    "sg:phone":"+1 416 663 1950",
    "sg:postcode":"M3N 1W8",
    "sg:province":"ON",
    "sg:tags":[
        "salon",
        "beauty"
    ],
    "wof:name":"Charlston International",
    "wof:placetype":"venue"
},
  "geometry": {"coordinates":[-79.5287017822,43.7592010498],"type":"Point"}
}