{
  "type": "Feature",
  "properties": {
    "iso:country":"CA",
    "sg:address":"440 Macdonnell St",
    "sg:city":"Kingston",
    "sg:classifiers":[
        {
            "category":"Autos & Motor Vehicles",
            "subcategory":"Auto Supplies",
            "type":"Retail Goods"
        }
    ],
    "sg:phone":"+1 613 544 1171",
    "sg:postcode":"K7L 4E4",
    "sg:province":"ON",
    "sg:tags":[
        "automobile",
        "stereo",
        "parts",
        "radio"
    ],
    "wof:name":"Norton Electronics",
    "wof:placetype":"venue"
},
  "geometry": {"coordinates":[-76.505875,44.238091],"type":"Point"}
}