{
  "type": "Feature",
  "properties": {
    "iso:country":"CA",
    "sg:address":"300 Rue DE L'Hotel-DE-Ville",
    "sg:city":"Brownsburg-Chatham",
    "sg:classifiers":[
        {
            "category":"Government",
            "subcategory":"Office",
            "type":"Public Place"
        }
    ],
    "sg:phone":"+1 450 533 6687",
    "sg:postcode":"J8G 3B4",
    "sg:province":"QC",
    "sg:tags":[
        "village"
    ],
    "wof:name":"Brownsburg Hotel DE Ville",
    "wof:placetype":"venue"
},
  "geometry": {"coordinates":[-74.4068374634,45.6757698059],"type":"Point"}
}