{
  "type": "Feature",
  "properties": {
    "addr:full":"Olds AB T4H 1V1",
    "addr:postcode":"t4h 1v1",
    "iso:country":"CA",
    "sg:city":"Olds",
    "sg:classifiers":[
        {
            "category":"Home & Garden",
            "subcategory":"Garden Supply",
            "type":"Retail Goods"
        }
    ],
    "sg:phone":"+1 403 556 7328",
    "sg:postcode":"T4H 1V1",
    "sg:province":"AB",
    "sg:tags":[
        "peat",
        "moss"
    ],
    "wof:name":"Premier Horticulture Ltd",
    "wof:placetype":"venue"
},
  "geometry": {"coordinates":[-114.101677,51.781261],"type":"Point"}
}