{
  "type": "Feature",
  "properties": {
    "addr:full":"1570 Highland Ave Brandon MB R7C 1A7",
    "addr:housenumber":"1570",
    "addr:postcode":"r7c 1a7",
    "addr:street":"Highland Ave",
    "iso:country":"CA",
    "sg:address":"1570 Highland Ave",
    "sg:city":"Brandon",
    "sg:classifiers":[
        {
            "category":"Travel",
            "subcategory":"Hotels & Motels",
            "type":"Entertainment"
        }
    ],
    "sg:phone":"+1 204 729 8024",
    "sg:postcode":"R7C 1A7",
    "sg:province":"MB",
    "wof:name":"Super 8 Motel",
    "wof:placetype":"venue"
},
  "geometry": {"coordinates":[-99.95481100000001,49.886372],"type":"Point"}
}