{
  "type": "Feature",
  "properties": {
    "addr:full":"180 Rue Sainte-Catherine O Montreal QC H2X 3Y2",
    "addr:housenumber":"180",
    "addr:postcode":"h2x 3y2",
    "addr:street":"Rue Sainte-Catherine O",
    "iso:country":"CA",
    "sg:address":"180 Rue Sainte-Catherine O",
    "sg:city":"Montreal",
    "sg:classifiers":[
        {
            "category":"Restaurant",
            "type":"Food & Drink"
        }
    ],
    "sg:phone":"+1 514 282 7444",
    "sg:postcode":"H2X 3Y2",
    "sg:province":"QC",
    "wof:name":"Restaurant Baton Rouge",
    "wof:placetype":"venue"
},
  "geometry": {"coordinates":[-73.56223300000001,45.511398],"type":"Point"}
}