{
  "type": "Feature",
  "properties": {
    "addr:full":"Surrey BC V3S 8E5",
    "addr:postcode":"v3s 8e5",
    "iso:country":"CA",
    "sg:city":"Surrey",
    "sg:classifiers":[
        {
            "category":"Manufacturing",
            "subcategory":"Lumber",
            "type":"Manufacturing & Wholesale Goods"
        }
    ],
    "sg:phone":"+1 604 574 0444",
    "sg:postcode":"V3S 8E5",
    "sg:province":"BC",
    "wof:name":"Raintree Lumber Specialties",
    "wof:placetype":"venue"
},
  "geometry": {"coordinates":[-122.69089508099999,49.1005172729],"type":"Point"}
}