{
  "type": "Feature",
  "properties": {
    "addr:full":"488 Lavoie Ave St Pierre Jolys MB R0A 1V0",
    "addr:housenumber":"488",
    "addr:postcode":"r0a 1v0",
    "addr:street":"Lavoie Ave St",
    "iso:country":"CA",
    "sg:address":"488 Lavoie Ave",
    "sg:city":"St Pierre Jolys",
    "sg:classifiers":[
        {
            "category":"Organizations",
            "subcategory":"Religious Organization",
            "type":"Services"
        }
    ],
    "sg:phone":"+1 204 433 7546",
    "sg:postcode":"R0A 1V0",
    "sg:province":"MB",
    "sg:tags":[
        "church"
    ],
    "wof:name":"St Pierre Bible Fellowship",
    "wof:placetype":"venue"
},
  "geometry": {"coordinates":[-96.985123,49.440708],"type":"Point"}
}