{
  "type": "Feature",
  "properties": {
    "addr:full":"242 Fielden Ave Port Colborne ON L3K 4T3",
    "addr:housenumber":"242",
    "addr:postcode":"l3k 4t3",
    "addr:street":"Fielden Ave",
    "iso:country":"CA",
    "sg:address":"242 Fielden Ave",
    "sg:city":"Port Colborne",
    "sg:classifiers":[
        {
            "category":"Building & Trades",
            "subcategory":"Plumbing",
            "type":"Services"
        }
    ],
    "sg:phone":"+1 905 834 4484",
    "sg:postcode":"L3K 4T3",
    "sg:province":"ON",
    "sg:tags":[
        "contractor"
    ],
    "wof:name":"Winn's Plumbing & Heating",
    "wof:placetype":"venue"
},
  "geometry": {"coordinates":[-79.2574234009,42.8863792419],"type":"Point"}
}