{
  "type": "Feature",
  "properties": {
    "addr:full":"8401 115 St Grande Prairie AB T8V 6Y6",
    "addr:housenumber":"8401",
    "addr:postcode":"t8v 6y6",
    "addr:street":"115 St",
    "iso:country":"CA",
    "sg:address":"8401 115 St",
    "sg:city":"Grande Prairie",
    "sg:classifiers":[
        {
            "category":"Mining & Drilling",
            "type":"Manufacturing & Wholesale Goods"
        }
    ],
    "sg:phone":"+1 780 538 4900",
    "sg:postcode":"T8V 6Y6",
    "sg:province":"AB",
    "sg:tags":[
        "field",
        "oil"
    ],
    "wof:name":"Weatherford-CA Drilling & Inte",
    "wof:placetype":"venue"
},
  "geometry": {"coordinates":[-118.843086,55.156487],"type":"Point"}
}