{
  "type": "Feature",
  "properties": {
    "iso:country":"CA",
    "sg:address":"903 Rte Principale",
    "sg:city":"Val-Des-Monts",
    "sg:classifiers":[
        {
            "category":"Food & Beverages",
            "subcategory":"Groceries & Convenience Stores",
            "type":"Retail Goods"
        }
    ],
    "sg:phone":"+1 819 457 4076",
    "sg:postcode":"J8N 4H7",
    "sg:province":"QC",
    "sg:tags":[
        "grocer"
    ],
    "wof:name":"Depanneur Le 27",
    "wof:placetype":"venue"
},
  "geometry": {"coordinates":[-75.7295913696,45.6750335693],"type":"Point"}
}