{
  "type": "Feature",
  "properties": {
    "iso:country":"CA",
    "sg:city":"Nepean",
    "sg:classifiers":[
        {
            "category":"Building & Trades",
            "subcategory":"Construction",
            "type":"Services"
        }
    ],
    "sg:phone":"+1 613 226 1867",
    "sg:postcode":"K2E 6T7",
    "sg:province":"ON",
    "sg:tags":[
        "general",
        "contractor"
    ],
    "wof:name":"G R Brune Construction Inc",
    "wof:placetype":"venue"
},
  "geometry": {"coordinates":[-75.7119064331,45.3363075256],"type":"Point"}
}