{
  "type": "Feature",
  "properties": {
    "addr:full":"88 Ardelt Ave Kitchener ON N2C 2C9",
    "addr:housenumber":"88",
    "addr:postcode":"n2c 2c9",
    "addr:street":"Ardelt Ave",
    "iso:country":"CA",
    "sg:address":"88 Ardelt Ave",
    "sg:city":"Kitchener",
    "sg:classifiers":[
        {
            "category":"Manufacturing",
            "subcategory":"Tools & Machinery",
            "type":"Manufacturing & Wholesale Goods"
        }
    ],
    "sg:phone":"+1 519 571 1522",
    "sg:postcode":"N2C 2C9",
    "sg:province":"ON",
    "sg:tags":[
        "equipment",
        "system",
        "automation"
    ],
    "wof:name":"Brock Solutions",
    "wof:placetype":"venue"
},
  "geometry": {"coordinates":[-80.477272,43.426899],"type":"Point"}
}