{
  "type": "Feature",
  "properties": {
    "addr:full":"155 Stadacona St W Moose Jaw SK S6H 1Z3",
    "addr:housenumber":"155",
    "addr:postcode":"s6h 1z3",
    "addr:street":"Stadacona St W",
    "iso:country":"CA",
    "sg:address":"155 Stadacona St W",
    "sg:city":"Moose Jaw",
    "sg:classifiers":[
        {
            "category":"Professional",
            "subcategory":"Accounting & Tax Preparation",
            "type":"Services"
        }
    ],
    "sg:phone":"+1 306 693 0733",
    "sg:postcode":"S6H 1Z3",
    "sg:province":"SK",
    "sg:tags":[
        "accountant"
    ],
    "wof:name":"Hanson, Donald A",
    "wof:placetype":"venue"
},
  "geometry": {"coordinates":[-105.53866600000001,50.394199],"type":"Point"}
}