{
  "type": "Feature",
  "properties": {
    "addr:full":"245 Guelph St Georgetown ON L7G 4A8",
    "addr:housenumber":"245",
    "addr:postcode":"l7g 4a8",
    "addr:street":"Guelph St",
    "iso:country":"CA",
    "sg:address":"245 Guelph St",
    "sg:city":"Georgetown",
    "sg:classifiers":[
        {
            "category":"Home & Garden",
            "subcategory":"Home Furnishings",
            "type":"Retail Goods"
        }
    ],
    "sg:phone":"+1 905 873 2996",
    "sg:postcode":"L7G 4A8",
    "sg:province":"ON",
    "sg:tags":[
        "lighting",
        "fixture"
    ],
    "wof:name":"Georgetown Living Lighting",
    "wof:placetype":"venue"
},
  "geometry": {"coordinates":[-79.894569397,43.6499061584],"type":"Point"}
}