{
  "type": "Feature",
  "properties": {
    "addr:full":"64 Dufour O Sacre-Coeur-Saguenay QC G0T 1Y0",
    "addr:housenumber":"64",
    "addr:postcode":"g0t 1y0",
    "addr:street":"Dufour O Sacre-Coeur-Saguenay",
    "iso:country":"CA",
    "sg:address":"64 Dufour O",
    "sg:city":"Sacre-Coeur-Saguenay",
    "sg:classifiers":[
        {
            "category":"Social Services",
            "subcategory":"Child Care",
            "type":"Services"
        }
    ],
    "sg:phone":"+1 418 236 1509",
    "sg:postcode":"G0T 1Y0",
    "sg:province":"QC",
    "wof:name":"Grain DE Soleil",
    "wof:placetype":"venue"
},
  "geometry": {"coordinates":[-69.80349,48.230759],"type":"Point"}
}