{
  "type": "Feature",
  "properties": {
    "addr:full":"875 Rue Bernard-Pilon Beloeil QC J3G 1V6",
    "addr:housenumber":"875",
    "addr:postcode":"j3g 1v6",
    "addr:street":"Rue Bernard-Pilon",
    "iso:country":"CA",
    "sg:address":"875 Rue Bernard-Pilon",
    "sg:city":"Beloeil",
    "sg:classifiers":[
        {
            "category":"Building & Trades",
            "subcategory":"Construction",
            "type":"Services"
        }
    ],
    "sg:phone":"+1 450 446 2904",
    "sg:postcode":"J3G 1V6",
    "sg:province":"QC",
    "sg:tags":[
        "designer",
        "dealer",
        "pool",
        "swimming"
    ],
    "wof:name":"Piscine Belle Etoile",
    "wof:placetype":"venue"
},
  "geometry": {"coordinates":[-73.22727966310001,45.5547981262],"type":"Point"}
}