{
  "type": "Feature",
  "properties": {
    "addr:full":"718 Rue Technologie Beresford NB E8K 2C4",
    "addr:housenumber":"718",
    "addr:postcode":"e8k 2c4",
    "addr:street":"Rue Technologie",
    "iso:country":"CA",
    "sg:address":"718 Rue Technologie",
    "sg:city":"Beresford",
    "sg:classifiers":[
        {
            "category":"Manufacturing",
            "subcategory":"Tools & Machinery",
            "type":"Manufacturing & Wholesale Goods"
        }
    ],
    "sg:phone":"+1 506 542 1050",
    "sg:postcode":"E8K 2C4",
    "sg:province":"NB",
    "sg:tags":[
        "machine",
        "shop"
    ],
    "wof:name":"All-Tech Hydraulic & Mech Inc",
    "wof:placetype":"venue"
},
  "geometry": {"coordinates":[-65.72255699999999,47.706661],"type":"Point"}
}