{
  "type": "Feature",
  "properties": {
    "addr:full":"104 4th St S Langenburg SK S0A 2A0",
    "addr:housenumber":"104",
    "addr:postcode":"s0a 2a0",
    "addr:street":"4Th St S",
    "iso:country":"CA",
    "sg:address":"104 4th St S",
    "sg:city":"Langenburg",
    "sg:classifiers":[
        {
            "category":"Shopping",
            "type":"Retail Goods"
        }
    ],
    "sg:phone":"+1 306 743 5188",
    "sg:postcode":"S0A 2A0",
    "sg:province":"SK",
    "sg:tags":[
        "storage",
        "monument"
    ],
    "wof:name":"Wallace Enterprises",
    "wof:placetype":"venue"
},
  "geometry": {"coordinates":[-101.70108795199999,50.8385314941],"type":"Point"}
}