{
  "type": "Feature",
  "properties": {
    "addr:full":"1490 Jackson Dr Comox BC V9M 4E5",
    "addr:housenumber":"1490",
    "addr:postcode":"v9m 4e5",
    "addr:street":"Jackson Dr",
    "iso:country":"CA",
    "sg:address":"1490 Jackson Dr",
    "sg:city":"Comox",
    "sg:classifiers":[
        {
            "category":"Professional",
            "subcategory":"Management & Consulting",
            "type":"Services"
        }
    ],
    "sg:phone":"+1 250 339 0288",
    "sg:postcode":"V9M 4E5",
    "sg:province":"BC",
    "sg:tags":[
        "marketing",
        "consultant"
    ],
    "wof:name":"Ryan-Aylward Marketing",
    "wof:placetype":"venue"
},
  "geometry": {"coordinates":[-124.926818848,49.673538208],"type":"Point"}
}