{
  "type": "Feature",
  "properties": {
    "addr:full":"Mississauga ON L4W 1J3",
    "addr:postcode":"l4w 1j3",
    "iso:country":"CA",
    "sg:city":"Mississauga",
    "sg:classifiers":[
        {
            "category":"Retail",
            "subcategory":"Auto Rental",
            "type":"Services"
        }
    ],
    "sg:phone":"+1 905 670 4410",
    "sg:postcode":"L4W 1J3",
    "sg:province":"ON",
    "sg:tags":[
        "renting",
        "leasing",
        "trailer"
    ],
    "wof:name":"Xtra Canada",
    "wof:placetype":"venue"
},
  "geometry": {"coordinates":[-79.638443,43.663231],"type":"Point"}
}