{
  "type": "Feature",
  "properties": {
    "addr:full":"76 King St Saint John NB E2L 1G4",
    "addr:housenumber":"76",
    "addr:postcode":"nb e2l 1g4",
    "addr:street":"King St",
    "iso:country":"CA",
    "sg:address":"76 King St",
    "sg:city":"Saint John",
    "sg:classifiers":[
        {
            "category":"Personal",
            "subcategory":"Beauty Salon",
            "type":"Services"
        }
    ],
    "sg:phone":"+1 506 642 6314",
    "sg:postcode":"E2L 1G4",
    "sg:province":"NB",
    "sg:tags":[
        "barber"
    ],
    "wof:name":"Vic's Barber Shop",
    "wof:placetype":"venue"
},
  "geometry": {"coordinates":[-66.060074,45.273106],"type":"Point"}
}