{
  "type": "Feature",
  "properties": {
    "iso:country":"CA",
    "sg:address":"4360 Ch Des Bouvreuils",
    "sg:city":"Becancour",
    "sg:classifiers":[
        {
            "category":"Farming",
            "subcategory":"Farm & Veterinary Services",
            "type":"Manufacturing & Wholesale Goods"
        }
    ],
    "sg:phone":"+1 819 298 2330",
    "sg:postcode":"G9H 4E3",
    "sg:province":"QC",
    "sg:tags":[
        "management"
    ],
    "wof:name":"Lavigne, Wilfrid",
    "wof:placetype":"venue"
},
  "geometry": {"coordinates":[-72.2891082764,46.3705863953],"type":"Point"}
}