{
  "type": "Feature",
  "properties": {
    "iso:country":"CA",
    "sg:address":"655 Champlain St",
    "sg:city":"Dieppe",
    "sg:classifiers":[
        {
            "category":"Farming",
            "subcategory":"Dairy Farm",
            "type":"Manufacturing & Wholesale Goods"
        }
    ],
    "sg:phone":"+1 506 383 6455",
    "sg:postcode":"E1A 1P6",
    "sg:province":"NB",
    "sg:tags":[
        "product"
    ],
    "wof:name":"Saputo Milk Div",
    "wof:placetype":"venue"
},
  "geometry": {"coordinates":[-64.7265167236,46.100025177],"type":"Point"}
}