{
  "type": "Feature",
  "properties": {
    "addr:full":"Spanish ON P0P 2A0",
    "addr:postcode":"p0p 2a0",
    "iso:country":"CA",
    "sg:city":"Spanish",
    "sg:classifiers":[
        {
            "category":"Travel",
            "subcategory":"Hotels & Motels",
            "type":"Entertainment"
        }
    ],
    "sg:phone":"+1 705 844 2000",
    "sg:postcode":"P0P 2A0",
    "sg:province":"ON",
    "wof:name":"Vance's Motor Inn",
    "wof:placetype":"venue"
},
  "geometry": {"coordinates":[-82.3380737305,46.1930999756],"type":"Point"}
}