{
  "type": "Feature",
  "properties": {
    "addr:full":"29 Caithness St E Caledonia ON N3W 1B7",
    "addr:housenumber":"29",
    "addr:postcode":"n3w 1b7",
    "addr:street":"Caithness St E",
    "iso:country":"CA",
    "sg:address":"29 Caithness St E",
    "sg:city":"Caledonia",
    "sg:classifiers":[
        {
            "category":"Organizations",
            "subcategory":"Professional Association",
            "type":"Services"
        }
    ],
    "sg:phone":"+1 905 765 2642",
    "sg:postcode":"N3W 1B7",
    "sg:province":"ON",
    "wof:name":"Royal Canadian Legion",
    "wof:placetype":"venue"
},
  "geometry": {"coordinates":[-79.9508132935,43.0734405518],"type":"Point"}
}