{
  "type": "Feature",
  "properties": {
    "addr:full":"Waterloo ON N2T 2L6",
    "addr:postcode":"n2t 2l6",
    "iso:country":"CA",
    "sg:city":"Waterloo",
    "sg:classifiers":[
        {
            "category":"Social Services",
            "type":"Services"
        }
    ],
    "sg:phone":"+1 519 747 9479",
    "sg:postcode":"N2T 2L6",
    "sg:province":"ON",
    "sg:tags":[
        "counselor",
        "marriage",
        "family"
    ],
    "wof:name":"N Rose Art Therapist",
    "wof:placetype":"venue"
},
  "geometry": {"coordinates":[-80.568359375,43.4473953247],"type":"Point"}
}