{
  "type": "Feature",
  "properties": {
    "addr:full":"Mississauga ON L5H 3A5",
    "addr:postcode":"l5h 3a5",
    "iso:country":"CA",
    "sg:city":"Mississauga",
    "sg:classifiers":[
        {
            "category":"Shopping",
            "type":"Retail Goods"
        }
    ],
    "sg:phone":"+1 905 274 7011",
    "sg:postcode":"L5H 3A5",
    "sg:province":"ON",
    "sg:tags":[
        "picture",
        "frame"
    ],
    "wof:name":"Artists Friend",
    "wof:placetype":"venue"
},
  "geometry": {"coordinates":[-79.61560799999999,43.531147],"type":"Point"}
}