{
  "type": "Feature",
  "properties": {
    "addr:full":"3975 Rue Notre-Dame O Montreal QC H4C 1R2",
    "addr:housenumber":"3975",
    "addr:postcode":"h4c 1r2",
    "addr:street":"Rue Notre-Dame O",
    "iso:country":"CA",
    "sg:address":"3975 Rue Notre-Dame O",
    "sg:city":"Montreal",
    "sg:classifiers":[
        {
            "category":"Organizations",
            "subcategory":"Religious Organization",
            "type":"Services"
        }
    ],
    "sg:phone":"+1 514 933 4876",
    "sg:postcode":"H4C 1R2",
    "sg:province":"QC",
    "sg:tags":[
        "church"
    ],
    "wof:name":"St Henri Free Methodist Church",
    "wof:placetype":"venue"
},
  "geometry": {"coordinates":[-73.534302,45.546623],"type":"Point"}
}