{
  "type": "Feature",
  "properties": {
    "addr:full":"1030 Islington Ave Etobicoke ON M8Z 6A4",
    "addr:housenumber":"1030",
    "addr:postcode":"m8z 6a4",
    "addr:street":"Islington Ave",
    "iso:country":"CA",
    "sg:address":"1030 Islington Ave",
    "sg:city":"Etobicoke",
    "sg:classifiers":[
        {
            "category":"Communications",
            "subcategory":"Film & Video Production",
            "type":"Services"
        }
    ],
    "sg:phone":"+1 416 234 5557",
    "sg:postcode":"M8Z 6A4",
    "sg:province":"ON",
    "sg:tags":[
        "television",
        "producer"
    ],
    "wof:name":"Tellavision",
    "wof:placetype":"venue"
},
  "geometry": {"coordinates":[-79.5185089111,43.6323165894],"type":"Point"}
}