{
  "type": "Feature",
  "properties": {
    "addr:full":"PO Box 70012 Rpo Londonderry Edmonton AB T5C 3R6",
    "addr:housenumber":"po box",
    "addr:postcode":"70012;t5c 3r6",
    "iso:country":"CA",
    "sg:address":"PO Box 70012 Rpo Londonderry",
    "sg:city":"Edmonton",
    "sg:classifiers":[
        {
            "category":"Retail",
            "subcategory":"Repair Shop",
            "type":"Services"
        }
    ],
    "sg:phone":"+1 780 478 1570",
    "sg:postcode":"T5C 3R6",
    "sg:province":"AB",
    "sg:tags":[
        "lock",
        "locksmith"
    ],
    "wof:name":"Ever Ready Locksmiths Ltd",
    "wof:placetype":"venue"
},
  "geometry": {"coordinates":[-113.49037199999999,53.546219],"type":"Point"}
}