{
  "type": "Feature",
  "properties": {
    "addr:full":"Vancouver BC V6E 1P2",
    "addr:postcode":"v6e 1p2",
    "iso:country":"CA",
    "sg:city":"Vancouver",
    "sg:classifiers":[
        {
            "category":"Wholesale",
            "subcategory":"Durable Goods & Equipment",
            "type":"Manufacturing & Wholesale Goods"
        }
    ],
    "sg:phone":"+1 604 683 3716",
    "sg:postcode":"V6E 1P2",
    "sg:province":"BC",
    "sg:tags":[
        "importer"
    ],
    "wof:name":"General Imports Ltd",
    "wof:placetype":"venue"
},
  "geometry": {"coordinates":[-123.133537,49.280308],"type":"Point"}
}