{
  "type": "Feature",
  "properties": {
    "addr:full":"1145 St Andrews Way Kamloops BC V1S 1S7",
    "addr:housenumber":"1145",
    "addr:postcode":"bc v1s 1s7",
    "addr:street":"St Andrews Way",
    "iso:country":"CA",
    "sg:address":"1145 St Andrews Way",
    "sg:city":"Kamloops",
    "sg:classifiers":[
        {
            "category":"Building & Trades",
            "subcategory":"Construction",
            "type":"Services"
        }
    ],
    "sg:phone":"+1 250 828 2870",
    "sg:postcode":"V1S 1S7",
    "sg:province":"BC",
    "sg:tags":[
        "masonry",
        "contractor"
    ],
    "wof:name":"Dave Robinson Masonry",
    "wof:placetype":"venue"
},
  "geometry": {"coordinates":[-120.370949,50.643063],"type":"Point"}
}