{
  "type": "Feature",
  "properties": {
    "iso:country":"CA",
    "sg:address":"2361 Rue DE LA Metallurgie",
    "sg:city":"Jonquiere",
    "sg:classifiers":[
        {
            "category":"Wholesale",
            "subcategory":"Hardware",
            "type":"Manufacturing & Wholesale Goods"
        }
    ],
    "sg:phone":"+1 418 547 3322",
    "sg:postcode":"G7X 9V8",
    "sg:province":"QC",
    "sg:tags":[
        "ventilating",
        "equipment",
        "heating",
        "system"
    ],
    "wof:name":"Cometal Sl Inc",
    "wof:placetype":"venue"
},
  "geometry": {"coordinates":[-71.22988891599999,48.4067306519],"type":"Point"}
}