{
  "type": "Feature",
  "properties": {
    "addr:full":"2317 Arlington Ave Saskatoon SK S7J 2H8",
    "addr:housenumber":"2317",
    "addr:postcode":"s7j 2h8",
    "addr:street":"Arlington Ave",
    "iso:country":"CA",
    "sg:address":"2317 Arlington Ave",
    "sg:city":"Saskatoon",
    "sg:classifiers":[
        {
            "category":"Organizations",
            "subcategory":"Professional Association",
            "type":"Services"
        }
    ],
    "sg:phone":"+1 306 373 3879",
    "sg:postcode":"S7J 2H8",
    "sg:province":"SK",
    "wof:name":"Superannuated Teachers",
    "wof:placetype":"venue"
},
  "geometry": {"coordinates":[-106.610664368,52.1019172668],"type":"Point"}
}