{
  "type": "Feature",
  "properties": {
    "addr:full":"Sainte-Anne-Des-Plaines QC J0N 1H0",
    "addr:postcode":"j0n 1h0",
    "iso:country":"CA",
    "sg:city":"Sainte-Anne-Des-Plaines",
    "sg:classifiers":[
        {
            "category":"Organizations",
            "subcategory":"Non-profit Organization",
            "type":"Services"
        }
    ],
    "sg:phone":"+1 450 478 5346",
    "sg:postcode":"J0N 1H0",
    "sg:province":"QC",
    "sg:tags":[
        "fund",
        "counselor",
        "raising"
    ],
    "wof:name":"Distribution Pl Rive-Nord Enr",
    "wof:placetype":"venue"
},
  "geometry": {"coordinates":[-73.822006,45.760834],"type":"Point"}
}