{
  "type": "Feature",
  "properties": {
    "iso:country":"CA",
    "sg:address":"615 Rue Bernard-Pilon",
    "sg:city":"Beloeil",
    "sg:classifiers":[
        {
            "category":"Building & Trades",
            "subcategory":"Construction",
            "type":"Services"
        }
    ],
    "sg:phone":"+1 450 446 2827",
    "sg:postcode":"J3G 1V5",
    "sg:province":"QC",
    "sg:tags":[
        "roofing",
        "contractor"
    ],
    "wof:name":"Couvreur Thr",
    "wof:placetype":"venue"
},
  "geometry": {"coordinates":[-73.223343,45.551819],"type":"Point"}
}