{
  "type": "Feature",
  "properties": {
    "addr:full":"175 Ashgrove Ave Brantford ON N3R 7C6",
    "addr:housenumber":"175",
    "addr:postcode":"n3r 7c6",
    "addr:street":"Ashgrove Ave",
    "iso:country":"CA",
    "sg:address":"175 Ashgrove Ave",
    "sg:city":"Brantford",
    "sg:classifiers":[
        {
            "category":"Shopping",
            "subcategory":"Computers & Home Electronics",
            "type":"Retail Goods"
        }
    ],
    "sg:phone":"+1 519 752 7866",
    "sg:postcode":"N3R 7C6",
    "sg:province":"ON",
    "sg:tags":[
        "parts",
        "supply"
    ],
    "wof:name":"Brant Laser Products & Svc",
    "wof:placetype":"venue"
},
  "geometry": {"coordinates":[-80.255661,43.186672],"type":"Point"}
}