{
  "type": "Feature",
  "properties": {
    "addr:full":"18 Norwood Pl Brampton ON L6S 4W9",
    "addr:housenumber":"18",
    "addr:postcode":"l6s 4w9",
    "addr:street":"Norwood Pl",
    "iso:country":"CA",
    "sg:address":"18 Norwood Pl",
    "sg:city":"Brampton",
    "sg:classifiers":[
        {
            "category":"Building & Trades",
            "subcategory":"Plumbing",
            "type":"Services"
        }
    ],
    "sg:phone":"+1 905 460 1932",
    "sg:postcode":"L6S 4W9",
    "sg:province":"ON",
    "sg:tags":[
        "conditioning",
        "air",
        "system",
        "contractor"
    ],
    "wof:name":"Dolden Mechanical",
    "wof:placetype":"venue"
},
  "geometry": {"coordinates":[-79.75527954099999,43.7250862122],"type":"Point"}
}