{
  "type": "Feature",
  "properties": {
    "addr:full":"113 Av Manfred Pointe-Claire QC H9R 4Y4",
    "addr:postcode":"h9r 4y4",
    "addr:street":"113 Av Manfred",
    "iso:country":"CA",
    "sg:address":"113 Av Manfred",
    "sg:city":"Pointe-Claire",
    "sg:classifiers":[
        {
            "category":"Freight",
            "type":"Transportation"
        }
    ],
    "sg:phone":"+1 514 426 5062",
    "sg:postcode":"H9R 4Y4",
    "sg:province":"QC",
    "sg:tags":[
        "trucking"
    ],
    "wof:name":"Ant-Pass Transport Ltd",
    "wof:placetype":"venue"
},
  "geometry": {"coordinates":[-73.8166046143,45.4622001648],"type":"Point"}
}