{
  "type": "Feature",
  "properties": {
    "iso:country":"CA",
    "sg:city":"Sudbury",
    "sg:classifiers":[
        {
            "category":"Personal",
            "subcategory":"Beauty Salon",
            "type":"Services"
        }
    ],
    "sg:phone":"+1 705 675 1002",
    "sg:postcode":"P3C 5M9",
    "sg:province":"ON",
    "wof:name":"Variance Hair Care",
    "wof:placetype":"venue"
},
  "geometry": {"coordinates":[-81.0353393555,46.4708480835],"type":"Point"}
}