{
  "type": "Feature",
  "properties": {
    "addr:full":"1253 Pacific Blvd Vancouver BC V6Z 2R6",
    "addr:housenumber":"1253",
    "addr:postcode":"v6z 2r6",
    "addr:street":"Pacific Blvd",
    "iso:country":"CA",
    "sg:address":"1253 Pacific Blvd",
    "sg:city":"Vancouver",
    "sg:classifiers":[
        {
            "category":"Shopping",
            "subcategory":"Clothing, Apparel, & Fashions",
            "type":"Retail Goods"
        }
    ],
    "sg:phone":"+1 604 899 6018",
    "sg:postcode":"V6Z 2R6",
    "sg:province":"BC",
    "sg:tags":[
        "item",
        "boutique"
    ],
    "wof:name":"Cotton Tree CO",
    "wof:placetype":"venue"
},
  "geometry": {"coordinates":[-123.122825623,49.2738037109],"type":"Point"}
}