{
  "type": "Feature",
  "properties": {
    "iso:country":"CA",
    "sg:city":"Vancouver",
    "sg:classifiers":[
        {
            "category":"Professional",
            "subcategory":"Business Services",
            "type":"Services"
        }
    ],
    "sg:phone":"+1 604 876 9955",
    "sg:postcode":"V5N 1X6",
    "sg:province":"BC",
    "sg:tags":[
        "translator",
        "interpreter"
    ],
    "wof:name":"Koening German Translation Svc",
    "wof:placetype":"venue"
},
  "geometry": {"coordinates":[-123.139572144,49.2628822327],"type":"Point"}
}