{
  "type": "Feature",
  "properties": {
    "addr:full":"2121 Mccowan Rd Scarborough ON M1S 3Y6",
    "addr:housenumber":"2121",
    "addr:postcode":"m1s 3y6",
    "addr:street":"Mccowan Rd",
    "iso:country":"CA",
    "sg:address":"2121 Mccowan Rd",
    "sg:city":"Scarborough",
    "sg:classifiers":[
        {
            "category":"Wholesale",
            "subcategory":"Drugs",
            "type":"Manufacturing & Wholesale Goods"
        }
    ],
    "sg:phone":"+1 416 298 1234",
    "sg:postcode":"M1S 3Y6",
    "sg:province":"ON",
    "sg:tags":[
        "pharmaceutical",
        "product"
    ],
    "wof:name":"Usf Processors Canada Inc",
    "wof:placetype":"venue"
},
  "geometry": {"coordinates":[-79.26160400000001,43.796833],"type":"Point"}
}