{
  "type": "Feature",
  "properties": {
    "addr:full":"540 8th Ave S Virden MB R0M 2C0",
    "addr:housenumber":"540",
    "addr:postcode":"r0m 2c0",
    "addr:street":"8Th Ave S Virden",
    "iso:country":"CA",
    "sg:address":"540 8th Ave S",
    "sg:city":"Virden",
    "sg:classifiers":[
        {
            "category":"Organizations",
            "subcategory":"Community Association",
            "type":"Services"
        }
    ],
    "sg:phone":"+1 204 748 1668",
    "sg:postcode":"R0M 2C0",
    "sg:province":"MB",
    "sg:tags":[
        "club"
    ],
    "wof:name":"Royal Canadian Legion",
    "wof:placetype":"venue"
},
  "geometry": {"coordinates":[-100.91971599999999,49.856026],"type":"Point"}
}