{
  "type": "Feature",
  "properties": {
    "addr:full":"143 Sheppard Ave E North York ON M2N 3A6",
    "addr:housenumber":"143",
    "addr:postcode":"m2n 3a6",
    "addr:street":"Sheppard Ave E",
    "iso:country":"CA",
    "sg:address":"143 Sheppard Ave E",
    "sg:city":"North York",
    "sg:classifiers":[
        {
            "category":"Health Services",
            "subcategory":"Doctor",
            "type":"Services"
        }
    ],
    "sg:phone":"+1 416 223 7292",
    "sg:postcode":"M2N 3A6",
    "sg:province":"ON",
    "sg:tags":[
        "dentist"
    ],
    "wof:name":"Phillips Moncarz Farber",
    "wof:placetype":"venue"
},
  "geometry": {"coordinates":[-79.4016571045,43.763420105],"type":"Point"}
}