{
  "type": "Feature",
  "properties": {
    "addr:full":"103 Hearst Cir North York ON M6M 2V4",
    "addr:housenumber":"103",
    "addr:postcode":"m6m 2v4",
    "addr:street":"Hearst Cir",
    "iso:country":"CA",
    "sg:address":"103 Hearst Cir",
    "sg:city":"North York",
    "sg:classifiers":[
        {
            "category":"Home & Garden",
            "subcategory":"Garden Supply",
            "type":"Retail Goods"
        }
    ],
    "sg:phone":"+1 416 804 5922",
    "sg:postcode":"M6M 2V4",
    "sg:province":"ON",
    "sg:tags":[
        "lawn",
        "mower"
    ],
    "wof:name":"Mobiletec Small Engines",
    "wof:placetype":"venue"
},
  "geometry": {"coordinates":[-79.495232,43.698978],"type":"Point"}
}