{
  "type": "Feature",
  "properties": {
    "addr:full":"Burnaby BC V5A 4J8",
    "addr:postcode":"v5a 4j8",
    "iso:country":"CA",
    "sg:city":"Burnaby",
    "sg:classifiers":[
        {
            "category":"Recreation",
            "type":"Entertainment"
        }
    ],
    "sg:phone":"+1 604 421 9755",
    "sg:postcode":"V5A 4J8",
    "sg:province":"BC",
    "sg:tags":[
        "club",
        "sport"
    ],
    "wof:name":"B C Lacrosse Assn",
    "wof:placetype":"venue"
},
  "geometry": {"coordinates":[-122.945679,49.248322],"type":"Point"}
}