{
  "type": "Feature",
  "properties": {
    "addr:full":"3298 Broadway W Vancouver BC V6K 2H4",
    "addr:housenumber":"3298",
    "addr:postcode":"v6k 2h4",
    "addr:street":"Broadway W",
    "iso:country":"CA",
    "sg:address":"3298 Broadway W",
    "sg:city":"Vancouver",
    "sg:classifiers":[
        {
            "category":"Cinema",
            "subcategory":"Movie Rental",
            "type":"Entertainment"
        }
    ],
    "sg:phone":"+1 604 732 4734",
    "sg:postcode":"V6K 2H4",
    "sg:province":"BC",
    "sg:tags":[
        "leasing",
        "video",
        "disc",
        "tape"
    ],
    "wof:name":"Blockbuster Video",
    "wof:placetype":"venue"
},
  "geometry": {"coordinates":[-123.177498,49.264099],"type":"Point"}
}