{
  "type": "Feature",
  "properties": {
    "addr:full":"8606 39B Ave NW Edmonton AB T6K 3S2",
    "addr:housenumber":"8606",
    "addr:postcode":"t6k 3s2",
    "addr:street":"39B Ave Nw",
    "iso:country":"CA",
    "sg:address":"8606 39B Ave NW",
    "sg:city":"Edmonton",
    "sg:classifiers":[
        {
            "category":"Building & Trades",
            "subcategory":"Cleaning & Sanitation",
            "type":"Services"
        }
    ],
    "sg:phone":"+1 780 461 2134",
    "sg:postcode":"T6K 3S2",
    "sg:province":"AB",
    "sg:tags":[
        "janitor"
    ],
    "wof:name":"Zona North Janitorial",
    "wof:placetype":"venue"
},
  "geometry": {"coordinates":[-113.45957900000001,53.475491],"type":"Point"}
}