{
  "type": "Feature",
  "properties": {
    "addr:full":"1899 Dunmore Rd SE # 109 Medicine Hat AB T1A 1Z8",
    "addr:housenumber":"1899",
    "addr:postcode":"t1a 1z8",
    "addr:street":"Dunmore Rd Se # 109",
    "iso:country":"CA",
    "sg:address":"1899 Dunmore Rd SE # 109",
    "sg:city":"Medicine Hat",
    "sg:classifiers":[
        {
            "category":"Professional",
            "subcategory":"Lawyer & Legal Services",
            "type":"Services"
        }
    ],
    "sg:phone":"+1 403 529 1888",
    "sg:postcode":"T1A 1Z8",
    "sg:province":"AB",
    "sg:tags":[
        "attorney"
    ],
    "wof:name":"Stuart M Smith Law Office",
    "wof:placetype":"venue"
},
  "geometry": {"coordinates":[-110.65664700000001,50.015781],"type":"Point"}
}