{
  "type": "Feature",
  "properties": {
    "addr:full":"L'Ascension QC J0T 1W0",
    "addr:postcode":"j0t 1w0",
    "iso:country":"CA",
    "sg:city":"L'Ascension",
    "sg:classifiers":[
        {
            "category":"Government",
            "subcategory":"Fire Station",
            "type":"Public Place"
        }
    ],
    "sg:phone":"+1 819 275 3636",
    "sg:postcode":"J0T 1W0",
    "sg:province":"QC",
    "sg:tags":[
        "department"
    ],
    "wof:name":"Feu-Appels D'Urgence",
    "wof:placetype":"venue"
},
  "geometry": {"coordinates":[-74.830581665,46.5512962341],"type":"Point"}
}