{
  "type": "Feature",
  "properties": {
    "addr:full":"7850 Weston Rd # B Woodbridge ON L4L 9N8",
    "addr:housenumber":"7850",
    "addr:postcode":"l4l 9n8",
    "addr:street":"Weston Rd # B",
    "iso:country":"CA",
    "sg:address":"7850 Weston Rd # B",
    "sg:city":"Woodbridge",
    "sg:classifiers":[
        {
            "category":"Shopping",
            "subcategory":"Bicycles & Sporting Goods",
            "type":"Retail Goods"
        }
    ],
    "sg:phone":"+1 905 264 2848",
    "sg:postcode":"L4L 9N8",
    "sg:province":"ON",
    "wof:name":"Sport Chek",
    "wof:placetype":"venue"
},
  "geometry": {"coordinates":[-79.548324585,43.7920608521],"type":"Point"}
}