{
  "type": "Feature",
  "properties": {
    "iso:country":"CA",
    "sg:address":"General Delivery",
    "sg:city":"Little Dover",
    "sg:classifiers":[
        {
            "category":"Retail",
            "subcategory":"Auto Repair",
            "type":"Services"
        }
    ],
    "sg:phone":"+1 902 366 3015",
    "sg:postcode":"B0H 1V0",
    "sg:province":"NS",
    "sg:tags":[
        "repairing",
        "automobile"
    ],
    "wof:name":"Avery's Auto Repair",
    "wof:placetype":"venue"
},
  "geometry": {"coordinates":[-61.0474205017,45.2869987488],"type":"Point"}
}