{
  "type": "Feature",
  "properties": {
    "iso:country":"CA",
    "sg:address":"100 Rue Berlioz # 214",
    "sg:city":"Verdun",
    "sg:classifiers":[
        {
            "category":"Wholesale",
            "subcategory":"Groceries",
            "type":"Manufacturing & Wholesale Goods"
        }
    ],
    "sg:phone":"+1 514 762 9990",
    "sg:postcode":"H3E 1N4",
    "sg:province":"QC",
    "sg:tags":[
        "food",
        "natural"
    ],
    "wof:name":"Ginseng Enterprise Canada Inc",
    "wof:placetype":"venue"
},
  "geometry": {"coordinates":[-73.571762085,45.4590187073],"type":"Point"}
}