{
  "type": "Feature",
  "properties": {
    "addr:full":"10512 110 St Fairview AB T0H 1L0",
    "addr:housenumber":"10512",
    "addr:postcode":"t0h 1l0",
    "addr:street":"110 St",
    "iso:country":"CA",
    "sg:address":"10512 110 St",
    "sg:city":"Fairview",
    "sg:classifiers":[
        {
            "category":"Professional",
            "subcategory":"Accounting & Tax Preparation",
            "type":"Services"
        }
    ],
    "sg:phone":"+1 780 835 3544",
    "sg:postcode":"T0H 1L0",
    "sg:province":"AB",
    "sg:tags":[
        "accountant"
    ],
    "wof:name":"Lancaster-Monner & CO",
    "wof:placetype":"venue"
},
  "geometry": {"coordinates":[-118.38455200200001,56.069770813],"type":"Point"}
}