{
  "type": "Feature",
  "properties": {
    "addr:full":"1692 Ch Darcy #D Bromont QC J2L 2X3",
    "addr:housenumber":"# d",
    "addr:postcode":"1692;j2l 2x3",
    "addr:street":"Ch Darcy",
    "iso:country":"CA",
    "sg:address":"1692 Ch Darcy #D",
    "sg:city":"Bromont",
    "sg:classifiers":[
        {
            "category":"Retail",
            "subcategory":"Repair Shop",
            "type":"Services"
        }
    ],
    "sg:phone":"+1 450 534 3608",
    "sg:postcode":"J2L 2X3",
    "sg:province":"QC",
    "sg:tags":[
        "upholsterer"
    ],
    "wof:name":"Rembourrage Bromont",
    "wof:placetype":"venue"
},
  "geometry": {"coordinates":[-72.70360565190001,45.3241844177],"type":"Point"}
}