{
  "type": "Feature",
  "properties": {
    "addr:full":"Vancouver BC V5T 2C4",
    "addr:postcode":"v5t 2c4",
    "iso:country":"CA",
    "sg:city":"Vancouver",
    "sg:classifiers":[
        {
            "category":"Social Services",
            "type":"Services"
        }
    ],
    "sg:phone":"+1 604 438 3755",
    "sg:postcode":"V5T 2C4",
    "sg:province":"BC",
    "sg:tags":[
        "organization",
        "welfare"
    ],
    "wof:name":"Watari Youth Day Program",
    "wof:placetype":"venue"
},
  "geometry": {"coordinates":[-123.110153,49.261513],"type":"Point"}
}