{
  "type": "Feature",
  "properties": {
    "iso:country":"CA",
    "sg:address":"1615 Rue Trudel",
    "sg:city":"Shawinigan",
    "sg:classifiers":[
        {
            "category":"Restaurant",
            "type":"Food & Drink"
        }
    ],
    "sg:phone":"+1 819 537 7243",
    "sg:postcode":"G9N 8K8",
    "sg:province":"QC",
    "wof:name":"Restaurant Jan Hing",
    "wof:placetype":"venue"
},
  "geometry": {"coordinates":[-72.7491226196,46.5558052063],"type":"Point"}
}