{
  "type": "Feature",
  "properties": {
    "addr:full":"2760 Derry Rd W Mississauga ON L5N 3N5",
    "addr:housenumber":"2760",
    "addr:postcode":"l5n 3n5",
    "addr:street":"Derry Rd W",
    "iso:country":"CA",
    "sg:address":"2760 Derry Rd W",
    "sg:city":"Mississauga",
    "sg:classifiers":[
        {
            "category":"Food & Beverages",
            "subcategory":"Groceries & Convenience Stores",
            "type":"Retail Goods"
        }
    ],
    "sg:phone":"+1 905 858 9500",
    "sg:postcode":"L5N 3N5",
    "sg:province":"ON",
    "sg:tags":[
        "grocer"
    ],
    "wof:name":"Rabba Fine Foods",
    "wof:placetype":"venue"
},
  "geometry": {"coordinates":[-79.76535,43.593185],"type":"Point"}
}