{
  "type": "Feature",
  "properties": {
    "iso:country":"CA",
    "sg:address":"2575 Ouellette Pl",
    "sg:city":"Windsor",
    "sg:classifiers":[
        {
            "category":"Real Estate",
            "subcategory":"Developer",
            "type":"Services"
        }
    ],
    "sg:phone":"+1 519 966 5608",
    "sg:postcode":"N8X 1L9",
    "sg:province":"ON",
    "wof:name":"Prime Rose Inc",
    "wof:placetype":"venue"
},
  "geometry": {"coordinates":[-83.0196380615,42.283203125],"type":"Point"}
}