{
  "type": "Feature",
  "properties": {
    "iso:country":"CA",
    "sg:address":"78 Av Stirling",
    "sg:city":"Lasalle",
    "sg:classifiers":[
        {
            "category":"Building & Trades",
            "subcategory":"Electrical",
            "type":"Services"
        }
    ],
    "sg:phone":"+1 514 367 0044",
    "sg:postcode":"H8R 3P1",
    "sg:province":"QC",
    "sg:tags":[
        "electric",
        "contractor"
    ],
    "wof:name":"R Gelineau & Fils Electrique",
    "wof:placetype":"venue"
},
  "geometry": {"coordinates":[-73.658669,45.428253],"type":"Point"}
}