{
  "type": "Feature",
  "properties": {
    "addr:full":"105 Rochford St Charlottetown PE C1A 3T6",
    "addr:housenumber":"105",
    "addr:postcode":"c1a 3t6",
    "addr:street":"Rochford St",
    "iso:country":"CA",
    "sg:address":"105 Rochford St",
    "sg:city":"Charlottetown",
    "sg:classifiers":[
        {
            "category":"Government",
            "subcategory":"Office",
            "type":"Public Place"
        }
    ],
    "sg:phone":"+1 902 368 4040",
    "sg:postcode":"C1A 3T6",
    "sg:province":"PE",
    "wof:name":"Pei Procurement Svc",
    "wof:placetype":"venue"
},
  "geometry": {"coordinates":[-63.1330184937,46.2337532043],"type":"Point"}
}