{
  "type": "Feature",
  "properties": {
    "iso:country":"CA",
    "sg:city":"Ottawa",
    "sg:classifiers":[
        {
            "category":"Wholesale",
            "subcategory":"Hardware",
            "type":"Manufacturing & Wholesale Goods"
        }
    ],
    "sg:phone":"+1 613 728 2412",
    "sg:postcode":"K1Z 5A2",
    "sg:province":"ON",
    "sg:tags":[
        "windmill",
        "energy",
        "solar"
    ],
    "wof:name":"Ottawa Solar & Wind Power",
    "wof:placetype":"venue"
},
  "geometry": {"coordinates":[-75.7492523193,45.3771514893],"type":"Point"}
}