{
  "type": "Feature",
  "properties": {
    "addr:full":"2410 200 St Langley BC V2Z 1X1",
    "addr:housenumber":"2410",
    "addr:postcode":"v2z 1x1",
    "addr:street":"200 St",
    "iso:country":"CA",
    "sg:address":"2410 200 St",
    "sg:city":"Langley",
    "sg:classifiers":[
        {
            "category":"Restaurant",
            "type":"Food & Drink"
        }
    ],
    "sg:phone":"+1 604 532 6995",
    "sg:postcode":"V2Z 1X1",
    "sg:province":"BC",
    "sg:tags":[
        "shop",
        "coffee"
    ],
    "wof:name":"Cappuccino Cottage",
    "wof:placetype":"venue"
},
  "geometry": {"coordinates":[-122.66918182400001,49.046459198],"type":"Point"}
}