{
  "type": "Feature",
  "properties": {
    "iso:country":"CA",
    "sg:address":"31 Rue J.-F.-Kennedy",
    "sg:city":"Saint-Jerome",
    "sg:classifiers":[
        {
            "category":"Manufacturing",
            "subcategory":"Metals",
            "type":"Manufacturing & Wholesale Goods"
        }
    ],
    "sg:phone":"+1 450 436 5355",
    "sg:postcode":"J7Y 4B4",
    "sg:province":"QC",
    "sg:tags":[
        "stamping"
    ],
    "wof:name":"Produits DE Metal Vulcain Inc",
    "wof:placetype":"venue"
},
  "geometry": {"coordinates":[-74.022644043,45.7675552368],"type":"Point"}
}