{
  "type": "Feature",
  "properties": {
    "addr:full":"Dorval QC H9S 1B7",
    "addr:postcode":"h9s 1b7",
    "iso:country":"CA",
    "sg:city":"Dorval",
    "sg:classifiers":[
        {
            "category":"Wholesale",
            "subcategory":"Stationery",
            "type":"Manufacturing & Wholesale Goods"
        }
    ],
    "sg:phone":"+1 514 631 3700",
    "sg:postcode":"H9S 1B7",
    "sg:province":"QC",
    "sg:tags":[
        "business",
        "form",
        "system"
    ],
    "wof:name":"Raymur Services",
    "wof:placetype":"venue"
},
  "geometry": {"coordinates":[-73.762985,45.448605],"type":"Point"}
}