{
  "type": "Feature",
  "properties": {
    "addr:full":"7154 Adams Ave Niagara Falls ON L2G 5H1",
    "addr:housenumber":"7154",
    "addr:postcode":"l2g 5h1",
    "addr:street":"Adams Ave",
    "iso:country":"CA",
    "sg:address":"7154 Adams Ave",
    "sg:city":"Niagara Falls",
    "sg:classifiers":[
        {
            "category":"Organizations",
            "subcategory":"Religious Organization",
            "type":"Services"
        }
    ],
    "sg:phone":"+1 905 358 0377",
    "sg:postcode":"L2G 5H1",
    "sg:province":"ON",
    "sg:tags":[
        "church"
    ],
    "wof:name":"Oakwood Gospel Hall",
    "wof:placetype":"venue"
},
  "geometry": {"coordinates":[-79.106461,43.071774],"type":"Point"}
}