{
  "type": "Feature",
  "properties": {
    "addr:full":"20 Anne St S # 4 Barrie ON L4N 2C6",
    "addr:housenumber":"20",
    "addr:postcode":"l4n 2c6",
    "addr:street":"Anne St S # 4",
    "iso:country":"CA",
    "sg:address":"20 Anne St S # 4",
    "sg:city":"Barrie",
    "sg:classifiers":[
        {
            "category":"Banks & Credit Unions",
            "subcategory":"Bank",
            "type":"Services"
        }
    ],
    "sg:phone":"+1 705 721 4509",
    "sg:postcode":"L4N 2C6",
    "sg:province":"ON",
    "sg:tags":[
        "loan",
        "real estate"
    ],
    "wof:name":"Annteam Mortgage Svc",
    "wof:placetype":"venue"
},
  "geometry": {"coordinates":[-79.70449829099999,44.3813591003],"type":"Point"}
}