{
  "type": "Feature",
  "properties": {
    "iso:country":"CA",
    "sg:address":"12600 66 Ave",
    "sg:city":"Surrey",
    "sg:classifiers":[
        {
            "category":"Education",
            "subcategory":"School",
            "type":"Public Place"
        }
    ],
    "sg:phone":"+1 604 597 5234",
    "sg:postcode":"V3W 2A8",
    "sg:province":"BC",
    "wof:name":"Tamanawis School",
    "wof:placetype":"venue"
},
  "geometry": {"coordinates":[-122.872077942,49.1227645874],"type":"Point"}
}