{
  "type": "Feature",
  "properties": {
    "addr:full":"125 Rang Tache O # A Sainte-Perpetue-DE-L'Islet QC G0R 3Z0",
    "addr:housenumber":"125",
    "addr:postcode":"g0r 3z0",
    "addr:street":"Rang Tache O # A Sainte-Perpetue-De-L'Islet",
    "iso:country":"CA",
    "sg:address":"125 Rang Tache O # A",
    "sg:city":"Sainte-Perpetue-DE-L'Islet",
    "sg:classifiers":[
        {
            "category":"Retail",
            "subcategory":"Auto Repair",
            "type":"Services"
        }
    ],
    "sg:phone":"+1 418 359 3163",
    "sg:postcode":"G0R 3Z0",
    "sg:province":"QC",
    "sg:tags":[
        "repairing",
        "automobile"
    ],
    "wof:name":"Garage Bruno Bourgault",
    "wof:placetype":"venue"
},
  "geometry": {"coordinates":[-70.33153533940001,47.0898017883],"type":"Point"}
}