{
  "type": "Feature",
  "properties": {
    "addr:full":"68 Millwick Dr North York ON M9L 1Y3",
    "addr:housenumber":"68",
    "addr:postcode":"m9l 1y3",
    "addr:street":"Millwick Dr",
    "iso:country":"CA",
    "sg:address":"68 Millwick Dr",
    "sg:city":"North York",
    "sg:classifiers":[
        {
            "category":"Building & Trades",
            "subcategory":"Electrical",
            "type":"Services"
        }
    ],
    "sg:phone":"+1 416 741 4020",
    "sg:postcode":"M9L 1Y3",
    "sg:province":"ON",
    "sg:tags":[
        "electric",
        "contractor"
    ],
    "wof:name":"United Electric",
    "wof:placetype":"venue"
},
  "geometry": {"coordinates":[-79.562157,43.759262],"type":"Point"}
}