{
  "type": "Feature",
  "properties": {
    "addr:full":"4407 Blenheim St Vancouver BC V6L 2Z8",
    "addr:housenumber":"4407",
    "addr:postcode":"v6l 2z8",
    "addr:street":"Blenheim St",
    "iso:country":"CA",
    "sg:address":"4407 Blenheim St",
    "sg:city":"Vancouver",
    "sg:classifiers":[
        {
            "category":"Professional",
            "subcategory":"Lawyer & Legal Services",
            "type":"Services"
        }
    ],
    "sg:phone":"+1 604 739 2988",
    "sg:postcode":"V6L 2Z8",
    "sg:province":"BC",
    "sg:tags":[
        "consultant",
        "planning",
        "financial",
        "estate"
    ],
    "wof:name":"Vlaovich, Vera",
    "wof:placetype":"venue"
},
  "geometry": {"coordinates":[-123.17868042000001,49.2469520569],"type":"Point"}
}