{
  "type": "Feature",
  "properties": {
    "addr:full":"53 Aitkman Rd Malahat BC V0R 2L0",
    "addr:housenumber":"53",
    "addr:postcode":"v0r 2l0",
    "addr:street":"Aitkman Rd",
    "iso:country":"CA",
    "sg:address":"53 Aitkman Rd",
    "sg:city":"Malahat",
    "sg:classifiers":[
        {
            "category":"Building & Trades",
            "subcategory":"Construction",
            "type":"Services"
        }
    ],
    "sg:phone":"+1 250 743 7331",
    "sg:postcode":"V0R 2L0",
    "sg:province":"BC",
    "sg:tags":[
        "maker",
        "cabinet"
    ],
    "wof:name":"Mountain Woodworking",
    "wof:placetype":"venue"
},
  "geometry": {"coordinates":[-123.57191467299999,48.5546913147],"type":"Point"}
}