{
  "type": "Feature",
  "properties": {
    "addr:full":"484 Boul Laure Sept-Iles QC G4R 1X5",
    "addr:housenumber":"484",
    "addr:postcode":"g4r 1x5",
    "addr:street":"Boul Laure Sept-Iles",
    "iso:country":"CA",
    "sg:address":"484 Boul Laure",
    "sg:city":"Sept-Iles",
    "sg:classifiers":[
        {
            "category":"Health Services",
            "subcategory":"Doctor",
            "type":"Services"
        }
    ],
    "sg:phone":"+1 418 968 3368",
    "sg:postcode":"G4R 1X5",
    "sg:province":"QC",
    "sg:tags":[
        "dentist"
    ],
    "wof:name":"Grimard, Chantal DDS",
    "wof:placetype":"venue"
},
  "geometry": {"coordinates":[-66.374886,50.21291],"type":"Point"}
}