{
  "type": "Feature",
  "properties": {
    "iso:country":"CA",
    "sg:address":"RR 1",
    "sg:city":"Arva",
    "sg:classifiers":[
        {
            "category":"Retail",
            "subcategory":"Auto Repair",
            "type":"Services"
        }
    ],
    "sg:phone":"+1 519 659 9991",
    "sg:postcode":"N0M 1C0",
    "sg:province":"ON",
    "sg:tags":[
        "repairing",
        "automobile"
    ],
    "wof:name":"Dan Newstead's Travellin' Auto",
    "wof:placetype":"venue"
},
  "geometry": {"coordinates":[-81.295242,43.05117],"type":"Point"}
}