{
  "type": "Feature",
  "properties": {
    "addr:full":"14307 106A Ave NW Edmonton AB T5N 1E3",
    "addr:housenumber":"14307",
    "addr:postcode":"t5n 1e3",
    "addr:street":"106A Ave Nw",
    "iso:country":"CA",
    "sg:address":"14307 106A Ave NW",
    "sg:city":"Edmonton",
    "sg:classifiers":[
        {
            "category":"Building & Trades",
            "subcategory":"Landscaping Services",
            "type":"Services"
        }
    ],
    "sg:phone":"+1 780 903 5332",
    "sg:postcode":"T5N 1E3",
    "sg:province":"AB",
    "sg:tags":[
        "tree"
    ],
    "wof:name":"Timberland Maintenance & Tree",
    "wof:placetype":"venue"
},
  "geometry": {"coordinates":[-113.56733699999999,53.549397],"type":"Point"}
}