{
  "type": "Feature",
  "properties": {
    "addr:full":"631 Rue Des Ursulines Roberval QC G8H 3H4",
    "addr:housenumber":"631",
    "addr:postcode":"g8h 3h4",
    "addr:street":"Rue Des Ursulines",
    "iso:country":"CA",
    "sg:address":"631 Rue Des Ursulines",
    "sg:city":"Roberval",
    "sg:classifiers":[
        {
            "category":"Personal",
            "subcategory":"Beauty Salon",
            "type":"Services"
        }
    ],
    "sg:phone":"+1 418 275 3347",
    "sg:postcode":"G8H 3H4",
    "sg:province":"QC",
    "wof:name":"Salon Flash Coiffure Enr",
    "wof:placetype":"venue"
},
  "geometry": {"coordinates":[-72.23255899999999,48.508808],"type":"Point"}
}