{
  "type": "Feature",
  "properties": {
    "addr:full":"Toronto ON M4P 1E4",
    "addr:postcode":"m4p 1e4",
    "iso:country":"CA",
    "sg:city":"Toronto",
    "sg:classifiers":[
        {
            "category":"Shopping",
            "subcategory":"Jewelry",
            "type":"Retail Goods"
        }
    ],
    "sg:phone":"+1 416 487 0467",
    "sg:postcode":"M4P 1E4",
    "sg:province":"ON",
    "sg:tags":[
        "jeweler"
    ],
    "wof:name":"Ardene",
    "wof:placetype":"venue"
},
  "geometry": {"coordinates":[-79.3986663818,43.7072372437],"type":"Point"}
}