{
  "type": "Feature",
  "properties": {
    "iso:country":"CA",
    "sg:city":"Toronto",
    "sg:classifiers":[
        {
            "category":"Health Services",
            "subcategory":"Doctor",
            "type":"Services"
        }
    ],
    "sg:phone":"+1 416 766 7616",
    "sg:postcode":"M6S 1M8",
    "sg:province":"ON",
    "sg:tags":[
        "dentist"
    ],
    "wof:name":"Cuff, T W DDS",
    "wof:placetype":"venue"
},
  "geometry": {"coordinates":[-79.4730606079,43.6519355774],"type":"Point"}
}