{
  "type": "Feature",
  "properties": {
    "addr:full":"110 Boul Perrot L'Ile-Perrot QC J7V 3G1",
    "addr:housenumber":"110",
    "addr:postcode":"j7v 3g1",
    "addr:street":"Boul Perrot L'Ile-Perrot",
    "iso:country":"CA",
    "sg:address":"110 Boul Perrot",
    "sg:city":"L'Ile-Perrot",
    "sg:classifiers":[
        {
            "category":"Government",
            "subcategory":"Fire Station",
            "type":"Public Place"
        }
    ],
    "sg:phone":"+1 ",
    "sg:postcode":"J7V 3G1",
    "sg:province":"QC",
    "sg:tags":[
        "department"
    ],
    "wof:name":"Ile-Perrot Feu Dept",
    "wof:placetype":"venue"
},
  "geometry": {"coordinates":[-73.95546,45.393646],"type":"Point"}
}