{
  "type": "Feature",
  "properties": {
    "iso:country":"CA",
    "sg:city":"New Westminster",
    "sg:classifiers":[
        {
            "category":"Real Estate",
            "subcategory":"Real Estate Operator",
            "type":"Services"
        }
    ],
    "sg:phone":"+1 604 520 3881",
    "sg:postcode":"V3M 6B9",
    "sg:province":"BC",
    "sg:tags":[
        "food",
        "mall",
        "shopping",
        "center",
        "market"
    ],
    "wof:name":"Westminster Quay Public Market",
    "wof:placetype":"venue"
},
  "geometry": {"coordinates":[-122.91182708700001,49.2002487183],"type":"Point"}
}