{
  "type": "Feature",
  "properties": {
    "addr:full":"Prince George BC V2K 4L1",
    "addr:postcode":"v2k 4l1",
    "iso:country":"CA",
    "sg:city":"Prince George",
    "sg:classifiers":[
        {
            "category":"Building & Trades",
            "subcategory":"Plumbing",
            "type":"Services"
        }
    ],
    "sg:phone":"+1 250 563 4107",
    "sg:postcode":"V2K 4L1",
    "sg:province":"BC",
    "sg:tags":[
        "contractor"
    ],
    "wof:name":"Yellowhead Installations Ltd",
    "wof:placetype":"venue"
},
  "geometry": {"coordinates":[-122.773773193,53.9294548035],"type":"Point"}
}