{
  "type": "Feature",
  "properties": {
    "addr:full":"117 Marbury Cres North York ON M3A 2G3",
    "addr:housenumber":"117",
    "addr:postcode":"m3a 2g3",
    "addr:street":"Marbury Cres",
    "iso:country":"CA",
    "sg:address":"117 Marbury Cres",
    "sg:city":"North York",
    "sg:classifiers":[
        {
            "category":"Shopping",
            "subcategory":"Hobbies, Toys, & Games",
            "type":"Retail Goods"
        }
    ],
    "sg:phone":"+1 416 445 0890",
    "sg:postcode":"M3A 2G3",
    "sg:province":"ON",
    "sg:tags":[
        "product",
        "ceramic"
    ],
    "wof:name":"Margon Imports",
    "wof:placetype":"venue"
},
  "geometry": {"coordinates":[-79.334373,43.765102],"type":"Point"}
}