{
  "type": "Feature",
  "properties": {
    "iso:country":"CA",
    "sg:address":"305 Acacia Dr",
    "sg:city":"Airdrie",
    "sg:classifiers":[
        {
            "category":"Education",
            "subcategory":"School",
            "type":"Public Place"
        }
    ],
    "sg:phone":"+1 403 948 2445",
    "sg:postcode":"T4B 1G2",
    "sg:province":"AB",
    "wof:name":"Muriel Clayton Middle School",
    "wof:placetype":"venue"
},
  "geometry": {"coordinates":[-114.008300781,51.2862930298],"type":"Point"}
}