{
  "type": "Feature",
  "properties": {
    "addr:full":"324 Carrington St # 5 Milestone SK S0G 3L0",
    "addr:housenumber":"324",
    "addr:postcode":"s0g 3l0",
    "addr:street":"Carrington St # 5 Milestone",
    "iso:country":"CA",
    "sg:address":"324 Carrington St # 5",
    "sg:city":"Milestone",
    "sg:classifiers":[
        {
            "category":"Shopping",
            "type":"Retail Goods"
        }
    ],
    "sg:phone":"+1 306 436 2055",
    "sg:postcode":"S0G 3L0",
    "sg:province":"SK",
    "sg:tags":[
        "equipment",
        "care",
        "health",
        "home"
    ],
    "wof:name":"Assisted Living Support",
    "wof:placetype":"venue"
},
  "geometry": {"coordinates":[-104.517501831,49.9923248291],"type":"Point"}
}