{
  "type": "Feature",
  "properties": {
    "addr:full":"6110 Temple Dr NE Calgary AB T1Y 5V4",
    "addr:housenumber":"6110",
    "addr:postcode":"t1y 5v4",
    "addr:street":"Temple Dr Ne",
    "iso:country":"CA",
    "sg:address":"6110 Temple Dr NE",
    "sg:city":"Calgary",
    "sg:classifiers":[
        {
            "category":"Education",
            "subcategory":"School",
            "type":"Public Place"
        }
    ],
    "sg:phone":"+1 403 280 9005",
    "sg:postcode":"T1Y 5V4",
    "sg:province":"AB",
    "wof:name":"St Thomas More Elem School",
    "wof:placetype":"venue"
},
  "geometry": {"coordinates":[-113.945992,51.08503],"type":"Point"}
}