{
  "type": "Feature",
  "properties": {
    "addr:full":"25 John St Yarmouth NS B5A 3H3",
    "addr:housenumber":"25",
    "addr:postcode":"b5a 3h3",
    "addr:street":"John St",
    "iso:country":"CA",
    "sg:address":"25 John St",
    "sg:city":"Yarmouth",
    "sg:classifiers":[
        {
            "category":"Retail",
            "subcategory":"Car Wash",
            "type":"Services"
        }
    ],
    "sg:phone":"+1 902 742 8813",
    "sg:postcode":"B5A 3H3",
    "sg:province":"NS",
    "sg:tags":[
        "polishing",
        "automobile",
        "rustproofing",
        "washing",
        "undercoating"
    ],
    "wof:name":"Shine Factory",
    "wof:placetype":"venue"
},
  "geometry": {"coordinates":[-66.1192779541,43.8354644775],"type":"Point"}
}