{
  "type": "Feature",
  "properties": {
    "addr:full":"Surrey BC V3W 2M9",
    "addr:postcode":"v3w 2m9",
    "iso:country":"CA",
    "sg:city":"Surrey",
    "sg:classifiers":[
        {
            "category":"Shopping",
            "subcategory":"Pharmacy",
            "type":"Retail Goods"
        }
    ],
    "sg:phone":"+1 604 599 4588",
    "sg:postcode":"V3W 2M9",
    "sg:province":"BC",
    "wof:name":"Bus Stop Pharmacy",
    "wof:placetype":"venue"
},
  "geometry": {"coordinates":[-122.86792,49.133961],"type":"Point"}
}