{
  "type": "Feature",
  "properties": {
    "iso:country":"CA",
    "sg:address":"4109 Boul Saint-Laurent",
    "sg:city":"Montreal",
    "sg:classifiers":[
        {
            "category":"Shopping",
            "subcategory":"Gifts & Souvenirs",
            "type":"Retail Goods"
        }
    ],
    "sg:phone":"+1 514 286 9236",
    "sg:postcode":"H2W 1Y7",
    "sg:province":"QC",
    "sg:tags":[
        "shop"
    ],
    "wof:name":"Cadeaux Suki",
    "wof:placetype":"venue"
},
  "geometry": {"coordinates":[-73.580582,45.517708],"type":"Point"}
}