{
  "type": "Feature",
  "properties": {
    "addr:full":"Ottawa ON K1G 3W3",
    "addr:postcode":"k1g 3w3",
    "iso:country":"CA",
    "sg:city":"Ottawa",
    "sg:classifiers":[
        {
            "category":"Building & Trades",
            "subcategory":"Construction",
            "type":"Services"
        }
    ],
    "sg:phone":"+1 613 737 7776",
    "sg:postcode":"K1G 3W3",
    "sg:province":"ON",
    "sg:tags":[
        "fire",
        "restoration",
        "damage"
    ],
    "wof:name":"Dfb Assoc",
    "wof:placetype":"venue"
},
  "geometry": {"coordinates":[-75.6087646484,45.3799476624],"type":"Point"}
}