{
  "type": "Feature",
  "properties": {
    "addr:full":"Avonlea Village Hunter River PE C0A 1N0",
    "addr:postcode":"c0a 1n0",
    "iso:country":"CA",
    "sg:address":"Avonlea Village",
    "sg:city":"Hunter River",
    "sg:classifiers":[
        {
            "category":"Shopping",
            "subcategory":"Department Store",
            "type":"Retail Goods"
        }
    ],
    "sg:phone":"+1 902 963 2856",
    "sg:postcode":"C0A 1N0",
    "sg:province":"PE",
    "wof:name":"Dollar Warehouse",
    "wof:placetype":"venue"
},
  "geometry": {"coordinates":[-63.343147,46.351761],"type":"Point"}
}