{
  "type": "Feature",
  "properties": {
    "addr:full":"9573 60 Ave NW Edmonton AB T6E 0C2",
    "addr:housenumber":"9573",
    "addr:postcode":"t6e 0c2",
    "addr:street":"60 Ave Nw",
    "iso:country":"CA",
    "sg:address":"9573 60 Ave NW",
    "sg:city":"Edmonton",
    "sg:classifiers":[
        {
            "category":"Building & Trades",
            "subcategory":"Construction",
            "type":"Services"
        }
    ],
    "sg:phone":"+1 780 413 9799",
    "sg:postcode":"T6E 0C2",
    "sg:province":"AB",
    "sg:tags":[
        "sewer",
        "tank",
        "septic",
        "contractor"
    ],
    "wof:name":"Lavenders Contracting Ltd",
    "wof:placetype":"venue"
},
  "geometry": {"coordinates":[-113.47576100000001,53.495636],"type":"Point"}
}