{
  "type": "Feature",
  "properties": {
    "addr:full":"NE 33-58-3 W 5 Barrhead AB T7N 1N4",
    "addr:housenumber":"33-58-3;5",
    "addr:postcode":"t7n 1n4",
    "addr:street":"W",
    "iso:country":"CA",
    "sg:address":"NE 33-58-3 W 5",
    "sg:city":"Barrhead",
    "sg:classifiers":[
        {
            "category":"Building & Trades",
            "subcategory":"Construction",
            "type":"Services"
        }
    ],
    "sg:phone":"+1 780 674 3162",
    "sg:postcode":"T7N 1N4",
    "sg:province":"AB",
    "sg:tags":[
        "painter"
    ],
    "wof:name":"Handel Painting & Decorating",
    "wof:placetype":"venue"
},
  "geometry": {"coordinates":[-114.406005859,54.1209907532],"type":"Point"}
}