{
  "type": "Feature",
  "properties": {
    "addr:full":"445 Monk St Cobourg ON K9A 2S9",
    "addr:housenumber":"445",
    "addr:postcode":"k9a 2s9",
    "addr:street":"Monk St",
    "iso:country":"CA",
    "sg:address":"445 Monk St",
    "sg:city":"Cobourg",
    "sg:classifiers":[
        {
            "category":"Organizations",
            "subcategory":"Religious Organization",
            "type":"Services"
        }
    ],
    "sg:phone":"+1 905 372 2741",
    "sg:postcode":"K9A 2S9",
    "sg:province":"ON",
    "sg:tags":[
        "house",
        "retreat"
    ],
    "wof:name":"Villa St Joseph Retreat Centre",
    "wof:placetype":"venue"
},
  "geometry": {"coordinates":[-78.182816,43.955654],"type":"Point"}
}