{
  "type": "Feature",
  "properties": {
    "addr:full":"175 Plains Rd East York ON M4J 2R2",
    "addr:housenumber":"175",
    "addr:postcode":"m4j 2r2",
    "addr:street":"Plains Rd",
    "iso:country":"CA",
    "sg:address":"175 Plains Rd",
    "sg:city":"East York",
    "sg:classifiers":[
        {
            "category":"Education",
            "subcategory":"School",
            "type":"Public Place"
        }
    ],
    "sg:phone":"+1 416 396 2350",
    "sg:postcode":"M4J 2R2",
    "sg:province":"ON",
    "wof:name":"Diefenbaker Elementary School",
    "wof:placetype":"venue"
},
  "geometry": {"coordinates":[-79.3327713013,43.6949195862],"type":"Point"}
}