{
  "type": "Feature",
  "properties": {
    "addr:full":"Saint-Charles-DE-Bellechasse QC G0R 2T0",
    "addr:postcode":"g0r 2t0",
    "iso:country":"CA",
    "sg:city":"Saint-Charles-DE-Bellechasse",
    "sg:classifiers":[
        {
            "category":"Manufacturing",
            "subcategory":"Furniture",
            "type":"Manufacturing & Wholesale Goods"
        }
    ],
    "sg:phone":"+1 418 887 3331",
    "sg:postcode":"G0R 2T0",
    "sg:province":"QC",
    "sg:tags":[
        "upholsterer"
    ],
    "wof:name":"Meuble Ideal Ltee",
    "wof:placetype":"venue"
},
  "geometry": {"coordinates":[-70.9394454956,46.7763023376],"type":"Point"}
}