{
  "type": "Feature",
  "properties": {
    "addr:full":"469 Richmond St E Toronto ON M5A 1R1",
    "addr:housenumber":"469",
    "addr:postcode":"m5a 1r1",
    "addr:street":"Richmond St E",
    "iso:country":"CA",
    "sg:address":"469 Richmond St E",
    "sg:city":"Toronto",
    "sg:classifiers":[
        {
            "category":"Professional",
            "subcategory":"Detective & Security Services",
            "type":"Services"
        }
    ],
    "sg:phone":"+1 416 367 2933",
    "sg:postcode":"M5A 1R1",
    "sg:province":"ON",
    "sg:tags":[
        "investigator"
    ],
    "wof:name":"Mantis Investigation Agency",
    "wof:placetype":"venue"
},
  "geometry": {"coordinates":[-79.36576100000001,43.653992],"type":"Point"}
}