{
  "type": "Feature",
  "properties": {
    "iso:country":"CA",
    "sg:address":"12418 111 Ave NW",
    "sg:city":"Edmonton",
    "sg:classifiers":[
        {
            "category":"Personal",
            "subcategory":"Beauty Salon",
            "type":"Services"
        }
    ],
    "sg:phone":"+1 780 454 0114",
    "sg:postcode":"T5M 2N6",
    "sg:province":"AB",
    "wof:name":"Rick's Hair Design",
    "wof:placetype":"venue"
},
  "geometry": {"coordinates":[-113.536338806,53.5590286255],"type":"Point"}
}