{
  "type": "Feature",
  "properties": {
    "addr:full":"Kenora ON P9N 1L9",
    "addr:postcode":"p9n 1l9",
    "iso:country":"CA",
    "sg:city":"Kenora",
    "sg:classifiers":[
        {
            "category":"Home & Garden",
            "subcategory":"Building Materials",
            "type":"Retail Goods"
        }
    ],
    "sg:phone":"+1 807 468 1644",
    "sg:postcode":"P9N 1L9",
    "sg:province":"ON",
    "sg:tags":[
        "paint"
    ],
    "wof:name":"Tim's Paint & Trim",
    "wof:placetype":"venue"
},
  "geometry": {"coordinates":[-94.4774017334,49.7618637085],"type":"Point"}
}