{
  "type": "Feature",
  "properties": {
    "addr:full":"Tilbury ON N0P 2L0",
    "addr:postcode":"n0p 2l0",
    "addr:street":"Tilbury",
    "iso:country":"CA",
    "sg:city":"Tilbury",
    "sg:classifiers":[
        {
            "category":"Personal",
            "subcategory":"Beauty Salon",
            "type":"Services"
        }
    ],
    "sg:phone":"+1 519 682 3468",
    "sg:postcode":"N0P 2L0",
    "sg:province":"ON",
    "wof:name":"Shear Perfection",
    "wof:placetype":"venue"
},
  "geometry": {"coordinates":[-82.4319229126,42.2602005005],"type":"Point"}
}