{
  "type": "Feature",
  "properties": {
    "addr:full":"6220 64 St Taber AB T1G 1Z3",
    "addr:housenumber":"6220",
    "addr:postcode":"t1g 1z3",
    "addr:street":"64 St",
    "iso:country":"CA",
    "sg:address":"6220 64 St",
    "sg:city":"Taber",
    "sg:classifiers":[
        {
            "category":"Manufacturing",
            "subcategory":"Tools & Machinery",
            "type":"Manufacturing & Wholesale Goods"
        }
    ],
    "sg:phone":"+1 403 223 2210",
    "sg:postcode":"T1G 1Z3",
    "sg:province":"AB",
    "sg:tags":[
        "equipment",
        "sandblasting"
    ],
    "wof:name":"Superior Sand",
    "wof:placetype":"venue"
},
  "geometry": {"coordinates":[-112.127663,49.798641],"type":"Point"}
}