{
  "type": "Feature",
  "properties": {
    "addr:full":"1004 Manotick Rd Manotick ON K4M 1B2",
    "addr:housenumber":"1004",
    "addr:postcode":"k4m 1b2",
    "addr:street":"Manotick Rd",
    "iso:country":"CA",
    "sg:address":"1004 Manotick Rd",
    "sg:city":"Manotick",
    "sg:classifiers":[
        {
            "category":"Shopping",
            "subcategory":"Discount & Variety Stores",
            "type":"Retail Goods"
        }
    ],
    "sg:phone":"+1 613 822 1659",
    "sg:postcode":"K4M 1B2",
    "sg:province":"ON",
    "sg:tags":[
        "merchandise",
        "general"
    ],
    "wof:name":"Bakker General Store",
    "wof:placetype":"venue"
},
  "geometry": {"coordinates":[-75.685936,45.226265],"type":"Point"}
}