{
  "type": "Feature",
  "properties": {
    "addr:full":"Toronto ON M5T 1S6",
    "addr:postcode":"m5t 1s6",
    "iso:country":"CA",
    "sg:city":"Toronto",
    "sg:classifiers":[
        {
            "category":"Health Services",
            "subcategory":"Medical Lab",
            "type":"Services"
        }
    ],
    "sg:phone":"+1 416 926 8088",
    "sg:postcode":"M5T 1S6",
    "sg:province":"ON",
    "sg:tags":[
        "clinic"
    ],
    "wof:name":"Emel Solva Denture Clinic",
    "wof:placetype":"venue"
},
  "geometry": {"coordinates":[-79.40483093260001,43.6571998596],"type":"Point"}
}