{
  "type": "Feature",
  "properties": {
    "iso:country":"CA",
    "sg:address":"981 Main St # 201",
    "sg:city":"Moncton",
    "sg:classifiers":[
        {
            "category":"Taxi",
            "type":"Transportation"
        }
    ],
    "sg:phone":"+1 506 857 3000",
    "sg:postcode":"E1C 1G9",
    "sg:province":"NB",
    "sg:tags":[
        "taxicab"
    ],
    "wof:name":"White Cab CO Ltd",
    "wof:placetype":"venue"
},
  "geometry": {"coordinates":[-64.78301999999999,46.087147],"type":"Point"}
}