{
  "type": "Feature",
  "properties": {
    "addr:full":"2255 Av West Hill Montreal QC H4B 2S3",
    "addr:housenumber":"2255",
    "addr:postcode":"h4b 2s3",
    "addr:street":"Av West",
    "iso:country":"CA",
    "sg:address":"2255 Av West Hill",
    "sg:city":"Montreal",
    "sg:classifiers":[
        {
            "category":"Wholesale",
            "subcategory":"Fruits & Vegetables",
            "type":"Manufacturing & Wholesale Goods"
        }
    ],
    "sg:phone":"+1 514 489 7164",
    "sg:postcode":"H4B 2S3",
    "sg:province":"QC",
    "wof:name":"Bethehem United Church Inc",
    "wof:placetype":"venue"
},
  "geometry": {"coordinates":[-73.623283,45.464348],"type":"Point"}
}