{
  "type": "Feature",
  "properties": {
    "addr:full":"207 Du Parc Prevert Saint-Ubalde QC G0A 4L0",
    "addr:housenumber":"207",
    "addr:postcode":"g0a 4l0",
    "addr:street":"Du Parc Prevert",
    "iso:country":"CA",
    "sg:address":"207 Du Parc Prevert",
    "sg:city":"Saint-Ubalde",
    "sg:classifiers":[
        {
            "category":"Building & Trades",
            "subcategory":"Construction",
            "type":"Services"
        }
    ],
    "sg:phone":"+1 418 277 2688",
    "sg:postcode":"G0A 4L0",
    "sg:province":"QC",
    "sg:tags":[
        "contractor"
    ],
    "wof:name":"Cym Construction Ltee",
    "wof:placetype":"venue"
},
  "geometry": {"coordinates":[-72.27549,46.753269],"type":"Point"}
}