{
  "type": "Feature",
  "properties": {
    "addr:full":"86 Lennon Cres Saskatoon SK S7L 6K2",
    "addr:housenumber":"86",
    "addr:postcode":"s7l 6k2",
    "addr:street":"Lennon Cres",
    "iso:country":"CA",
    "sg:address":"86 Lennon Cres",
    "sg:city":"Saskatoon",
    "sg:classifiers":[
        {
            "category":"Food & Beverages",
            "subcategory":"Specialty",
            "type":"Retail Goods"
        }
    ],
    "sg:phone":"+1 306 384 6410",
    "sg:postcode":"S7L 6K2",
    "sg:province":"SK",
    "sg:tags":[
        "health",
        "diet"
    ],
    "wof:name":"Reflexology & Kinesiology",
    "wof:placetype":"venue"
},
  "geometry": {"coordinates":[-106.740470886,52.1470489502],"type":"Point"}
}