{
  "type": "Feature",
  "properties": {
    "addr:full":"22233 4 Ave Langley BC V2Z 1R9",
    "addr:housenumber":"22233",
    "addr:postcode":"v2z 1r9",
    "addr:street":"4 Ave",
    "iso:country":"CA",
    "sg:address":"22233 4 Ave",
    "sg:city":"Langley",
    "sg:classifiers":[
        {
            "category":"Wholesale",
            "subcategory":"Non-durable Goods",
            "type":"Manufacturing & Wholesale Goods"
        }
    ],
    "sg:phone":"+1 604 533 9818",
    "sg:postcode":"V2Z 1R9",
    "sg:province":"BC",
    "sg:tags":[
        "advertising"
    ],
    "wof:name":"North Pacific Promotions Inc",
    "wof:placetype":"venue"
},
  "geometry": {"coordinates":[-122.606133,49.009556],"type":"Point"}
}