{
  "type": "Feature",
  "properties": {
    "addr:full":"139 Green Rd Stoney Creek ON L8G 3X2",
    "addr:housenumber":"139",
    "addr:postcode":"l8g 3x2",
    "addr:street":"Green Rd",
    "iso:country":"CA",
    "sg:address":"139 Green Rd",
    "sg:city":"Stoney Creek",
    "sg:classifiers":[
        {
            "category":"Shopping",
            "subcategory":"Florist",
            "type":"Retail Goods"
        }
    ],
    "sg:phone":"+1 905 662 8860",
    "sg:postcode":"L8G 3X2",
    "sg:province":"ON",
    "wof:name":"Yates Florist",
    "wof:placetype":"venue"
},
  "geometry": {"coordinates":[-79.734596,43.219353],"type":"Point"}
}