{
  "type": "Feature",
  "properties": {
    "iso:country":"CA",
    "sg:address":"240 Main St",
    "sg:city":"Melville",
    "sg:classifiers":[
        {
            "category":"Travel",
            "subcategory":"Hotels & Motels",
            "type":"Entertainment"
        }
    ],
    "sg:phone":"+1 306 728 4486",
    "sg:postcode":"S0A 2P0",
    "sg:province":"SK",
    "wof:name":"King George Hotel",
    "wof:placetype":"venue"
},
  "geometry": {"coordinates":[-102.80573272700001,50.9283065796],"type":"Point"}
}