{
  "type": "Feature",
  "properties": {
    "iso:country":"CA",
    "sg:city":"Cobden",
    "sg:classifiers":[
        {
            "category":"Insurance",
            "subcategory":"Insurance Agent",
            "type":"Services"
        }
    ],
    "sg:phone":"+1 613 646 7498",
    "sg:postcode":"K0J 1K0",
    "sg:province":"ON",
    "wof:name":"Keith Peever Insurance",
    "wof:placetype":"venue"
},
  "geometry": {"coordinates":[-76.8799819946,45.6270751953],"type":"Point"}
}