{
  "type": "Feature",
  "properties": {
    "addr:full":"2900 Steeles Ave E Thornhill ON L3T 4X1",
    "addr:housenumber":"2900",
    "addr:postcode":"l3t 4x1",
    "addr:street":"Steeles Ave E",
    "iso:country":"CA",
    "sg:address":"2900 Steeles Ave E",
    "sg:city":"Thornhill",
    "sg:classifiers":[
        {
            "category":"Insurance",
            "subcategory":"Insurance Agent",
            "type":"Services"
        }
    ],
    "sg:phone":"+1 416 733 2600",
    "sg:postcode":"L3T 4X1",
    "sg:province":"ON",
    "wof:name":"Paul S Karda Insurance",
    "wof:placetype":"venue"
},
  "geometry": {"coordinates":[-79.35920715330001,43.8117523193],"type":"Point"}
}