{
  "type": "Feature",
  "properties": {
    "iso:country":"CA",
    "sg:address":"620 Cedar St",
    "sg:city":"Okanagan Falls",
    "sg:classifiers":[
        {
            "category":"Travel",
            "subcategory":"Hotels & Motels",
            "type":"Entertainment"
        }
    ],
    "sg:phone":"+1 250 497 5460",
    "sg:postcode":"V0H 1R0",
    "sg:province":"BC",
    "wof:name":"South Shore Motel",
    "wof:placetype":"venue"
},
  "geometry": {"coordinates":[-119.57533264200001,49.3467636108],"type":"Point"}
}