{
  "type": "Feature",
  "properties": {
    "addr:full":"226 Queen St S Mississauga ON L5M 1L5",
    "addr:housenumber":"226",
    "addr:postcode":"l5m 1l5",
    "addr:street":"Queen St S",
    "iso:country":"CA",
    "sg:address":"226 Queen St S",
    "sg:city":"Mississauga",
    "sg:classifiers":[
        {
            "category":"Wholesale",
            "subcategory":"Non-durable Goods",
            "type":"Manufacturing & Wholesale Goods"
        }
    ],
    "sg:phone":"+1 905 567 9795",
    "sg:postcode":"L5M 1L5",
    "sg:province":"ON",
    "sg:tags":[
        "interior",
        "shop",
        "gift"
    ],
    "wof:name":"Crafted Decor",
    "wof:placetype":"venue"
},
  "geometry": {"coordinates":[-79.600357,43.543072],"type":"Point"}
}