{
  "type": "Feature",
  "properties": {
    "addr:full":"3701 Chesswood Dr North York ON M3J 2P6",
    "addr:housenumber":"3701",
    "addr:postcode":"m3j 2p6",
    "addr:street":"Chesswood Dr",
    "iso:country":"CA",
    "sg:address":"3701 Chesswood Dr",
    "sg:city":"North York",
    "sg:classifiers":[
        {
            "category":"Banks & Credit Unions",
            "subcategory":"Investment Brokerage",
            "type":"Services"
        }
    ],
    "sg:phone":"+1 416 398 5443",
    "sg:postcode":"M3J 2P6",
    "sg:province":"ON",
    "sg:tags":[
        "consultant",
        "planning",
        "financial"
    ],
    "wof:name":"Primerica Financial Svc",
    "wof:placetype":"venue"
},
  "geometry": {"coordinates":[-79.474075,43.755787],"type":"Point"}
}