{
  "type": "Feature",
  "properties": {
    "iso:country":"CA",
    "sg:address":"558 Keenleyside St",
    "sg:city":"Winnipeg",
    "sg:classifiers":[
        {
            "category":"Education",
            "subcategory":"Dance Studio",
            "type":"Public Place"
        }
    ],
    "sg:phone":"+1 204 669 2369",
    "sg:postcode":"R2K 3H2",
    "sg:province":"MB",
    "sg:tags":[
        "instruction",
        "dancing"
    ],
    "wof:name":"Rising Star Dance Academy",
    "wof:placetype":"venue"
},
  "geometry": {"coordinates":[-97.06931304930001,49.9054107666],"type":"Point"}
}