{
  "type": "Feature",
  "properties": {
    "iso:country":"CA",
    "sg:address":"154 Boul Sir-Wilfrid-Laurier",
    "sg:city":"Beloeil",
    "sg:classifiers":[
        {
            "category":"Restaurant",
            "type":"Food & Drink"
        }
    ],
    "sg:phone":"+1 450 464 5166",
    "sg:postcode":"J3G 4G7",
    "sg:province":"QC",
    "wof:name":"Restaurant Danvito",
    "wof:placetype":"venue"
},
  "geometry": {"coordinates":[-73.21533203120001,45.552116394],"type":"Point"}
}