{
  "type": "Feature",
  "properties": {
    "iso:country":"CA",
    "sg:address":"647 Whiteswan Dr",
    "sg:city":"Saskatoon",
    "sg:classifiers":[
        {
            "category":"Building & Trades",
            "subcategory":"Construction",
            "type":"Services"
        }
    ],
    "sg:phone":"+1 306 931 7797",
    "sg:postcode":"S7K 8A2",
    "sg:province":"SK",
    "sg:tags":[
        "contractor"
    ],
    "wof:name":"Springwood Homes Ltd",
    "wof:placetype":"venue"
},
  "geometry": {"coordinates":[-106.616844177,52.1805305481],"type":"Point"}
}