{
  "type": "Feature",
  "properties": {
    "addr:full":"312 Ch Des Patriotes Saint-Mathias-Sur-Richelieu QC J3L 6A4",
    "addr:housenumber":"312",
    "addr:postcode":"j3l 6a4",
    "addr:street":"Ch Des Patriotes",
    "iso:country":"CA",
    "sg:address":"312 Ch Des Patriotes",
    "sg:city":"Saint-Mathias-Sur-Richelieu",
    "sg:classifiers":[
        {
            "category":"Retail",
            "subcategory":"Auto Repair",
            "type":"Services"
        }
    ],
    "sg:phone":"+1 450 658 5215",
    "sg:postcode":"J3L 6A4",
    "sg:province":"QC",
    "sg:tags":[
        "repairing",
        "automobile",
        "painting"
    ],
    "wof:name":"Garage Fd Viens Inc",
    "wof:placetype":"venue"
},
  "geometry": {"coordinates":[-73.26796,45.47691],"type":"Point"}
}