{
  "type": "Feature",
  "properties": {
    "iso:country":"CA",
    "sg:city":"Conception Bay South",
    "sg:classifiers":[
        {
            "category":"Professional",
            "subcategory":"Management & Consulting",
            "type":"Services"
        }
    ],
    "sg:phone":"+1 709 834 7518",
    "sg:postcode":"A1X 1H6",
    "sg:province":"NL",
    "sg:tags":[
        "consultant",
        "safety",
        "business"
    ],
    "wof:name":"Nosci Intl",
    "wof:placetype":"venue"
},
  "geometry": {"coordinates":[-52.968875885,47.5126190186],"type":"Point"}
}