{
  "type": "Feature",
  "properties": {
    "addr:full":"450 Nanaimo St Vancouver BC V5L 4W3",
    "addr:housenumber":"450",
    "addr:postcode":"v5l 4w3",
    "addr:street":"Nanaimo St",
    "iso:country":"CA",
    "sg:address":"450 Nanaimo St",
    "sg:city":"Vancouver",
    "sg:classifiers":[
        {
            "category":"Professional",
            "subcategory":"Business Services",
            "type":"Services"
        }
    ],
    "sg:phone":"+1 604 251 4610",
    "sg:postcode":"V5L 4W3",
    "sg:province":"BC",
    "sg:tags":[
        "consultant",
        "planning",
        "design",
        "interior",
        "home",
        "decorator"
    ],
    "wof:name":"Raffaele & Assoc Designs",
    "wof:placetype":"venue"
},
  "geometry": {"coordinates":[-123.05642700200001,49.2807388306],"type":"Point"}
}