{
  "type": "Feature",
  "properties": {
    "addr:full":"9913 98 Ave Peace River AB T8S 1J5",
    "addr:housenumber":"9913",
    "addr:postcode":"t8s 1j5",
    "addr:street":"98 Ave",
    "iso:country":"CA",
    "sg:address":"9913 98 Ave",
    "sg:city":"Peace River",
    "sg:classifiers":[
        {
            "category":"Professional",
            "subcategory":"Accounting & Tax Preparation",
            "type":"Services"
        }
    ],
    "sg:phone":"+1 780 624 5146",
    "sg:postcode":"T8S 1J5",
    "sg:province":"AB",
    "sg:tags":[
        "accountant"
    ],
    "wof:name":"Cote, Emilien H CA",
    "wof:placetype":"venue"
},
  "geometry": {"coordinates":[-117.290665,56.235256],"type":"Point"}
}