{
  "type": "Feature",
  "properties": {
    "addr:full":"Hwy 1 Rugby Rd Brandon MB R7A 5Y2",
    "addr:postcode":"r7a 5y2",
    "addr:street":"Hwy 1 Rugby Rd",
    "iso:country":"CA",
    "sg:address":"Hwy 1 Rugby Rd",
    "sg:city":"Brandon",
    "sg:classifiers":[
        {
            "category":"Autos & Motor Vehicles",
            "subcategory":"Auto Supplies",
            "type":"Retail Goods"
        }
    ],
    "sg:phone":"+1 204 727 3323",
    "sg:postcode":"R7A 5Y2",
    "sg:province":"MB",
    "sg:tags":[
        "tire"
    ],
    "wof:name":"K K Penner & Sons",
    "wof:placetype":"venue"
},
  "geometry": {"coordinates":[-99.961952,49.847698],"type":"Point"}
}