{
  "type": "Feature",
  "properties": {
    "iso:country":"CA",
    "sg:address":"285 Old Margaree Rd",
    "sg:city":"Baddeck",
    "sg:classifiers":[
        {
            "category":"Building & Trades",
            "subcategory":"Construction",
            "type":"Services"
        }
    ],
    "sg:phone":"+1 902 295 1555",
    "sg:postcode":"B0E 1B0",
    "sg:province":"NS",
    "sg:tags":[
        "excavating",
        "contractor",
        "general"
    ],
    "wof:name":"Barra Construction Ltd",
    "wof:placetype":"venue"
},
  "geometry": {"coordinates":[-60.7614402771,46.1021308899],"type":"Point"}
}