{
  "type": "Feature",
  "properties": {
    "iso:country":"CA",
    "sg:address":"250 Boul Cure-Labelle",
    "sg:city":"Sainte-Rose",
    "sg:classifiers":[
        {
            "category":"Autos & Motor Vehicles",
            "subcategory":"Automobile Sales",
            "type":"Retail Goods"
        }
    ],
    "sg:phone":"+1 450 625 1114",
    "sg:postcode":"H7L 3A2",
    "sg:province":"QC",
    "sg:tags":[
        "car",
        "dealer"
    ],
    "wof:name":"Carrefour Subaru Inc",
    "wof:placetype":"venue"
},
  "geometry": {"coordinates":[-73.788795,45.600159],"type":"Point"}
}