{
  "type": "Feature",
  "properties": {
    "iso:country":"CA",
    "sg:address":"1619 Eglinton Ave W",
    "sg:city":"York",
    "sg:classifiers":[
        {
            "category":"Shopping",
            "subcategory":"Jewelry",
            "type":"Retail Goods"
        }
    ],
    "sg:phone":"+1 416 781 3998",
    "sg:postcode":"M6E 2H1",
    "sg:province":"ON",
    "sg:tags":[
        "jeweler"
    ],
    "wof:name":"West York Jewellers & Engraver",
    "wof:placetype":"venue"
},
  "geometry": {"coordinates":[-79.443695,43.696957],"type":"Point"}
}