{
  "type": "Feature",
  "properties": {
    "addr:full":"1619 Eglinton Ave W York ON M6E 2H1",
    "addr:housenumber":"1619",
    "addr:postcode":"m6e 2h1",
    "addr:street":"Eglinton Ave W",
    "iso:country":"CA",
    "sg:address":"1619 Eglinton Ave W",
    "sg:city":"York",
    "sg:classifiers":[
        {
            "category":"Shopping",
            "subcategory":"Jewelry",
            "type":"Retail Goods"
        }
    ],
    "sg:phone":"+1 416 781 3998",
    "sg:postcode":"M6E 2H1",
    "sg:province":"ON",
    "sg:tags":[
        "jeweler"
    ],
    "wof:name":"West York Jewellers & Engraver",
    "wof:placetype":"venue"
},
  "geometry": {"coordinates":[-79.44369500000001,43.696957],"type":"Point"}
}