{
  "type": "Feature",
  "properties": {
    "addr:full":"27 Empey St Brantford ON N3S 7P9",
    "addr:housenumber":"27",
    "addr:postcode":"n3s 7p9",
    "addr:street":"Empey St",
    "iso:country":"CA",
    "sg:address":"27 Empey St",
    "sg:city":"Brantford",
    "sg:classifiers":[
        {
            "category":"Home & Garden",
            "subcategory":"Building Materials",
            "type":"Retail Goods"
        }
    ],
    "sg:phone":"+1 519 751 0440",
    "sg:postcode":"N3S 7P9",
    "sg:province":"ON",
    "sg:tags":[
        "mixed",
        "concrete"
    ],
    "wof:name":"Brant County Concrete Ltd",
    "wof:placetype":"venue"
},
  "geometry": {"coordinates":[-80.2214508057,43.1561584473],"type":"Point"}
}