{
  "type": "Feature",
  "properties": {
    "addr:full":"101 Pinhey St Ottawa ON K1Y 1T7",
    "addr:housenumber":"101",
    "addr:postcode":"k1y 1t7",
    "addr:street":"Pinhey St",
    "iso:country":"CA",
    "sg:address":"101 Pinhey St",
    "sg:city":"Ottawa",
    "sg:classifiers":[
        {
            "category":"Home & Garden",
            "subcategory":"Home Furnishings",
            "type":"Retail Goods"
        }
    ],
    "sg:phone":"+1 613 728 3786",
    "sg:postcode":"K1Y 1T7",
    "sg:province":"ON",
    "sg:tags":[
        "fireplace"
    ],
    "wof:name":"Hubert Heating",
    "wof:placetype":"venue"
},
  "geometry": {"coordinates":[-75.7257385254,45.4037322998],"type":"Point"}
}