{
  "type": "Feature",
  "properties": {
    "iso:country":"CA",
    "sg:address":"10303 Jasper Ave NW",
    "sg:city":"Edmonton",
    "sg:classifiers":[
        {
            "category":"Government",
            "subcategory":"Office",
            "type":"Public Place"
        }
    ],
    "sg:phone":"+1 780 495 4660",
    "sg:postcode":"T5J 3N6",
    "sg:province":"AB",
    "wof:name":"Canada Customs Border Svc",
    "wof:placetype":"venue"
},
  "geometry": {"coordinates":[-113.49763488799999,53.5407485962],"type":"Point"}
}