{
  "type": "Feature",
  "properties": {
    "iso:country":"CA",
    "sg:address":"2479 Highway 97 N",
    "sg:city":"Kelowna",
    "sg:classifiers":[
        {
            "category":"Professional",
            "subcategory":"Advertising",
            "type":"Services"
        }
    ],
    "sg:phone":"+1 250 868 8386",
    "sg:postcode":"V1X 4J2",
    "sg:province":"BC",
    "sg:tags":[
        "demonstration"
    ],
    "wof:name":"Professional Warehouse Demo",
    "wof:placetype":"venue"
},
  "geometry": {"coordinates":[-119.49659699999999,49.886814],"type":"Point"}
}