{
  "type": "Feature",
  "properties": {
    "addr:full":"40 Topple Dr Dartmouth NS B3B 1L6",
    "addr:housenumber":"40",
    "addr:postcode":"b3b 1l6",
    "addr:street":"Topple Dr",
    "iso:country":"CA",
    "sg:address":"40 Topple Dr",
    "sg:city":"Dartmouth",
    "sg:classifiers":[
        {
            "category":"Wholesale",
            "subcategory":"Machinery & Supplies",
            "type":"Manufacturing & Wholesale Goods"
        }
    ],
    "sg:phone":"+1 902 468 4900",
    "sg:postcode":"B3B 1L6",
    "sg:province":"NS",
    "sg:tags":[
        "ship",
        "chandler"
    ],
    "wof:name":"Blue Water Agencies Ltd",
    "wof:placetype":"venue"
},
  "geometry": {"coordinates":[-63.606571,44.7132],"type":"Point"}
}