{
  "type": "Feature",
  "properties": {
    "addr:full":"1500 125 Rte Notre-Dame-DE-LA-Merci QC J0T 2A0",
    "addr:housenumber":"1500",
    "addr:postcode":"j0t 2a0",
    "addr:street":"125 Rte",
    "iso:country":"CA",
    "sg:address":"1500 125 Rte",
    "sg:city":"Notre-Dame-DE-LA-Merci",
    "sg:classifiers":[
        {
            "category":"Recreation",
            "type":"Entertainment"
        }
    ],
    "sg:phone":"+1 819 424 1865",
    "sg:postcode":"J0T 2A0",
    "sg:province":"QC",
    "sg:tags":[
        "center"
    ],
    "wof:name":"Foret Quareau",
    "wof:placetype":"venue"
},
  "geometry": {"coordinates":[-73.74482,45.311584],"type":"Point"}
}