{
  "type": "Feature",
  "properties": {
    "addr:full":"1200 24th St W Prince Albert SK S6V 4N9",
    "addr:housenumber":"1200",
    "addr:postcode":"s6v 4n9",
    "addr:street":"24Th St",
    "iso:country":"CA",
    "sg:address":"1200 24th St W",
    "sg:city":"Prince Albert",
    "sg:classifiers":[
        {
            "category":"Retail",
            "subcategory":"Laundry & Dry Cleaning",
            "type":"Services"
        }
    ],
    "sg:phone":"+1 306 764 5264",
    "sg:postcode":"S6V 4N9",
    "sg:province":"SK",
    "wof:name":"North Sask Laundry Svc Ltd",
    "wof:placetype":"venue"
},
  "geometry": {"coordinates":[-105.772942,53.191559],"type":"Point"}
}