{
  "type": "Feature",
  "properties": {
    "addr:full":"Victoria BC V8T 4M1",
    "addr:postcode":"v8t 4m1",
    "iso:country":"CA",
    "sg:city":"Victoria",
    "sg:classifiers":[
        {
            "category":"Organizations",
            "subcategory":"Labor Organization",
            "type":"Services"
        }
    ],
    "sg:phone":"+1 250 388 7328",
    "sg:postcode":"V8T 4M1",
    "sg:province":"BC",
    "wof:name":"Victoria Vancouver Island",
    "wof:placetype":"venue"
},
  "geometry": {"coordinates":[-123.366119385,48.4366226196],"type":"Point"}
}