{
  "type": "Feature",
  "properties": {
    "addr:full":"426 Rue Anna Quebec QC G1N 3L4",
    "addr:housenumber":"426",
    "addr:postcode":"g1n 3l4",
    "addr:street":"Rue Anna",
    "iso:country":"CA",
    "sg:address":"426 Rue Anna",
    "sg:city":"Quebec",
    "sg:classifiers":[
        {
            "category":"Shopping",
            "subcategory":"Clothing, Apparel, & Fashions",
            "type":"Retail Goods"
        }
    ],
    "sg:phone":"+1 418 683 5503",
    "sg:postcode":"G1N 3L4",
    "sg:province":"QC",
    "sg:tags":[
        "tailor"
    ],
    "wof:name":"Boutique Kat-Lyn Enr",
    "wof:placetype":"venue"
},
  "geometry": {"coordinates":[-71.244461,46.804607],"type":"Point"}
}