{
  "type": "Feature",
  "properties": {
    "iso:country":"CA",
    "sg:address":"49 Niagara St",
    "sg:city":"Toronto",
    "sg:classifiers":[
        {
            "category":"Manufacturing",
            "subcategory":"Tools & Machinery",
            "type":"Manufacturing & Wholesale Goods"
        }
    ],
    "sg:phone":"+1 416 703 0326",
    "sg:postcode":"M5V 1C2",
    "sg:province":"ON",
    "sg:tags":[
        "model",
        "maker"
    ],
    "wof:name":"Peter Mc Cann Architectural",
    "wof:placetype":"venue"
},
  "geometry": {"coordinates":[-79.40218353269999,43.641708374],"type":"Point"}
}