{
  "type": "Feature",
  "properties": {
    "addr:full":"2571 Smith St Richmond BC V6X 2J1",
    "addr:housenumber":"2571",
    "addr:postcode":"v6x 2j1",
    "addr:street":"Smith St",
    "iso:country":"CA",
    "sg:address":"2571 Smith St",
    "sg:city":"Richmond",
    "sg:classifiers":[
        {
            "category":"Wholesale",
            "subcategory":"Medical Equipment & Supplies",
            "type":"Manufacturing & Wholesale Goods"
        }
    ],
    "sg:phone":"+1 604 276 8662",
    "sg:postcode":"V6X 2J1",
    "sg:province":"BC",
    "sg:tags":[
        "dental"
    ],
    "wof:name":"Bisco Dental Products Canada",
    "wof:placetype":"venue"
},
  "geometry": {"coordinates":[-123.125457764,49.1943397522],"type":"Point"}
}