{
  "type": "Feature",
  "properties": {
    "addr:full":"11 Crowfoot Terr NW Calgary AB T3G 4J8",
    "addr:housenumber":"11",
    "addr:postcode":"t3g 4j8",
    "addr:street":"Crowfoot Terr Nw",
    "iso:country":"CA",
    "sg:address":"11 Crowfoot Terr NW",
    "sg:city":"Calgary",
    "sg:classifiers":[
        {
            "category":"Restaurant",
            "type":"Food & Drink"
        }
    ],
    "sg:phone":"+1 403 215 1008",
    "sg:postcode":"T3G 4J8",
    "sg:province":"AB",
    "wof:name":"Burger King",
    "wof:placetype":"venue"
},
  "geometry": {"coordinates":[-114.198898,51.126713],"type":"Point"}
}