{
  "type": "Feature",
  "properties": {
    "addr:full":"132 Boul Leon-Vachon Saint-Lambert-DE-Lauzon QC G0S 2W0",
    "addr:housenumber":"132",
    "addr:postcode":"g0s 2w0",
    "addr:street":"Boul Leon-Vachon",
    "iso:country":"CA",
    "sg:address":"132 Boul Leon-Vachon",
    "sg:city":"Saint-Lambert-DE-Lauzon",
    "sg:classifiers":[
        {
            "category":"Home & Garden",
            "subcategory":"Building Materials",
            "type":"Retail Goods"
        }
    ],
    "sg:phone":"+1 418 889 9032",
    "sg:postcode":"G0S 2W0",
    "sg:province":"QC",
    "sg:tags":[
        "windows"
    ],
    "wof:name":"Industries Radisson",
    "wof:placetype":"venue"
},
  "geometry": {"coordinates":[-71.1914978027,46.5992088318],"type":"Point"}
}