{
  "type": "Feature",
  "properties": {
    "addr:full":"831 1E Rue O Barraute QC J0Y 1A0",
    "addr:housenumber":"831",
    "addr:postcode":"j0y 1a0",
    "addr:street":"1E Rue O",
    "iso:country":"CA",
    "sg:address":"831 1E Rue O",
    "sg:city":"Barraute",
    "sg:classifiers":[
        {
            "category":"Shopping",
            "subcategory":"Florist",
            "type":"Retail Goods"
        }
    ],
    "sg:phone":"+1 819 734 5143",
    "sg:postcode":"J0Y 1A0",
    "sg:province":"QC",
    "wof:name":"Fleuriste Anne-Marie",
    "wof:placetype":"venue"
},
  "geometry": {"coordinates":[-77.6374206543,48.4432067871],"type":"Point"}
}