{
  "type": "Feature",
  "properties": {
    "iso:country":"CA",
    "sg:address":"5 Lonsdale Ave",
    "sg:city":"North Vancouver",
    "sg:classifiers":[
        {
            "category":"Restaurant",
            "type":"Food & Drink"
        }
    ],
    "sg:phone":"+1 604 985 9853",
    "sg:postcode":"V7M 2E4",
    "sg:province":"BC",
    "wof:name":"Anatoli Souvlaki",
    "wof:placetype":"venue"
},
  "geometry": {"coordinates":[-123.080223,49.310562],"type":"Point"}
}