{
  "type": "Feature",
  "properties": {
    "addr:full":"1181 Highbury Ave N London ON N5Y 1A6",
    "addr:housenumber":"1181",
    "addr:postcode":"n5y 1a6",
    "addr:street":"Highbury Ave N",
    "iso:country":"CA",
    "sg:address":"1181 Highbury Ave N",
    "sg:city":"London",
    "sg:classifiers":[
        {
            "category":"Food & Beverages",
            "subcategory":"Bakery",
            "type":"Retail Goods"
        }
    ],
    "sg:phone":"+1 519 452 4822",
    "sg:postcode":"N5Y 1A6",
    "sg:province":"ON",
    "sg:tags":[
        "doughnut"
    ],
    "wof:name":"Tim Hortons",
    "wof:placetype":"venue"
},
  "geometry": {"coordinates":[-81.213402,43.01572],"type":"Point"}
}