{
  "type": "Feature",
  "properties": {
    "addr:full":"5198 Av Gatineau Montreal QC H3T 1W9",
    "addr:housenumber":"5198",
    "addr:postcode":"h3t 1w9",
    "addr:street":"Av Gatineau",
    "iso:country":"CA",
    "sg:address":"5198 Av Gatineau",
    "sg:city":"Montreal",
    "sg:classifiers":[
        {
            "category":"Manufacturing",
            "subcategory":"Metals",
            "type":"Manufacturing & Wholesale Goods"
        }
    ],
    "sg:phone":"+1 514 737 0042",
    "sg:postcode":"H3T 1W9",
    "sg:province":"QC",
    "sg:tags":[
        "lock",
        "safe",
        "locksmith"
    ],
    "wof:name":"Serrurier Montreal Enrg",
    "wof:placetype":"venue"
},
  "geometry": {"coordinates":[-73.61837768549999,45.4956512451],"type":"Point"}
}