{
  "type": "Feature",
  "properties": {
    "addr:full":"Toronto ON M5A 1J2",
    "addr:postcode":"m5a 1j2",
    "iso:country":"CA",
    "sg:city":"Toronto",
    "sg:classifiers":[
        {
            "category":"Arts & Performance",
            "subcategory":"Theater",
            "type":"Entertainment"
        }
    ],
    "sg:phone":"+1 416 364 8941",
    "sg:postcode":"M5A 1J2",
    "sg:province":"ON",
    "sg:tags":[
        "television",
        "program",
        "producer"
    ],
    "wof:name":"David Langer Productions",
    "wof:placetype":"venue"
},
  "geometry": {"coordinates":[-79.3648986816,43.6497306824],"type":"Point"}
}