{
  "type": "Feature",
  "properties": {
    "addr:full":"10049 Galaran Rd Sidney BC V8L 5X3",
    "addr:housenumber":"10049",
    "addr:postcode":"v8l 5x3",
    "addr:street":"Galaran Rd",
    "iso:country":"CA",
    "sg:address":"10049 Galaran Rd",
    "sg:city":"Sidney",
    "sg:classifiers":[
        {
            "category":"Autos & Motor Vehicles",
            "subcategory":"Recreational Vehicle Sales",
            "type":"Retail Goods"
        }
    ],
    "sg:phone":"+1 250 656 3464",
    "sg:postcode":"V8L 5X3",
    "sg:province":"BC",
    "wof:name":"Peden Recreation Vehicle Ltd",
    "wof:placetype":"venue"
},
  "geometry": {"coordinates":[-123.41219329800001,48.6542358398],"type":"Point"}
}