{
  "type": "Feature",
  "properties": {
    "addr:full":"4415 12 St NE Calgary AB T2E 4R1",
    "addr:housenumber":"4415",
    "addr:postcode":"t2e 4r1",
    "addr:street":"12 St Ne",
    "iso:country":"CA",
    "sg:address":"4415 12 St NE",
    "sg:city":"Calgary",
    "sg:classifiers":[
        {
            "category":"Utilities",
            "subcategory":"Natural Gas",
            "type":"Services"
        }
    ],
    "sg:phone":"+1 403 245 7444",
    "sg:postcode":"T2E 4R1",
    "sg:province":"AB",
    "sg:tags":[
        "company"
    ],
    "wof:name":"Atco Gas",
    "wof:placetype":"venue"
},
  "geometry": {"coordinates":[-114.033112,51.090889],"type":"Point"}
}