{
  "type": "Feature",
  "properties": {
    "addr:full":"517 Boul Sainte-Anne Joliette QC J6E 5A3",
    "addr:housenumber":"517",
    "addr:postcode":"j6e 5a3",
    "addr:street":"Boul Sainte-Anne",
    "iso:country":"CA",
    "sg:address":"517 Boul Sainte-Anne",
    "sg:city":"Joliette",
    "sg:classifiers":[
        {
            "category":"Local Transit",
            "type":"Transportation"
        }
    ],
    "sg:phone":"+1 450 759 1312",
    "sg:postcode":"J6E 5A3",
    "sg:province":"QC",
    "sg:tags":[
        "ambulance"
    ],
    "wof:name":"Ambulance DE Joliette Inc",
    "wof:placetype":"venue"
},
  "geometry": {"coordinates":[-73.4471817017,46.0319290161],"type":"Point"}
}