{
  "type": "Feature",
  "properties": {
    "iso:country":"CA",
    "sg:address":"1922 Park St",
    "sg:city":"Regina",
    "sg:classifiers":[
        {
            "category":"Travel",
            "subcategory":"Hotels & Motels",
            "type":"Entertainment"
        }
    ],
    "sg:phone":"+1 306 787 2300",
    "sg:postcode":"S4N 7M4",
    "sg:province":"SK",
    "sg:tags":[
        "resort",
        "tourist",
        "information"
    ],
    "wof:name":"Saskatchewan Tourism",
    "wof:placetype":"venue"
},
  "geometry": {"coordinates":[-104.572563171,50.448348999],"type":"Point"}
}