{
  "type": "Feature",
  "properties": {
    "addr:full":"3 1st Ave S Ashern MB R0C 0E0",
    "addr:housenumber":"3",
    "addr:postcode":"r0c 0e0",
    "addr:street":"1St Ave S Ashern",
    "iso:country":"CA",
    "sg:address":"3 1st Ave S",
    "sg:city":"Ashern",
    "sg:classifiers":[
        {
            "category":"Retail",
            "subcategory":"Auto Repair",
            "type":"Services"
        }
    ],
    "sg:phone":"+1 204 768 3566",
    "sg:postcode":"R0C 0E0",
    "sg:province":"MB",
    "sg:tags":[
        "repairing",
        "automobile",
        "radiator"
    ],
    "wof:name":"Cal's Radiator Repair",
    "wof:placetype":"venue"
},
  "geometry": {"coordinates":[-98.34837341310001,51.1793136597],"type":"Point"}
}