{
  "type": "Feature",
  "properties": {
    "addr:full":"Welland ON L3B 3K4",
    "addr:postcode":"l3b 3k4",
    "iso:country":"CA",
    "sg:city":"Welland",
    "sg:classifiers":[
        {
            "category":"Health Services",
            "subcategory":"Doctor",
            "type":"Services"
        }
    ],
    "sg:phone":"+1 905 714 1747",
    "sg:postcode":"L3B 3K4",
    "sg:province":"ON",
    "sg:tags":[
        "physician",
        "surgeon"
    ],
    "wof:name":"Chaudhry, Naheed MD",
    "wof:placetype":"venue"
},
  "geometry": {"coordinates":[-79.25135,42.981964],"type":"Point"}
}