{
  "type": "Feature",
  "properties": {
    "addr:full":"2694 Eglinton Ave W York ON M6M 1T9",
    "addr:housenumber":"2694",
    "addr:postcode":"m6m 1t9",
    "addr:street":"Eglinton Ave W",
    "iso:country":"CA",
    "sg:address":"2694 Eglinton Ave W",
    "sg:city":"York",
    "sg:classifiers":[
        {
            "category":"Recreation",
            "type":"Entertainment"
        }
    ],
    "sg:phone":"+1 416 394 2469",
    "sg:postcode":"M6M 1T9",
    "sg:province":"ON",
    "sg:tags":[
        "center",
        "hall",
        "auditorium"
    ],
    "wof:name":"Centennial Recreation Ctr",
    "wof:placetype":"venue"
},
  "geometry": {"coordinates":[-79.4777755737,43.6902046204],"type":"Point"}
}