{
  "type": "Feature",
  "properties": {
    "addr:full":"81 Wellesley St E Toronto ON M4Y 1H6",
    "addr:housenumber":"81",
    "addr:postcode":"m4y 1h6",
    "addr:street":"Wellesley St E",
    "iso:country":"CA",
    "sg:address":"81 Wellesley St E",
    "sg:city":"Toronto",
    "sg:classifiers":[
        {
            "category":"Social Services",
            "type":"Services"
        }
    ],
    "sg:phone":"+1 416 961 1928",
    "sg:postcode":"M4Y 1H6",
    "sg:province":"ON",
    "sg:tags":[
        "organization",
        "welfare"
    ],
    "wof:name":"Wellspring",
    "wof:placetype":"venue"
},
  "geometry": {"coordinates":[-79.3800811768,43.665763855],"type":"Point"}
}