{
  "type": "Feature",
  "properties": {
    "addr:full":"489 Abercrombie Rd New Glasgow NS B2H 1L3",
    "addr:housenumber":"489",
    "addr:postcode":"b2h 1l3",
    "addr:street":"Abercrombie Rd",
    "iso:country":"CA",
    "sg:address":"489 Abercrombie Rd",
    "sg:city":"New Glasgow",
    "sg:classifiers":[
        {
            "category":"Organizations",
            "subcategory":"Religious Organization",
            "type":"Services"
        }
    ],
    "sg:phone":"+1 902 755 1500",
    "sg:postcode":"B2H 1L3",
    "sg:province":"NS",
    "sg:tags":[
        "church"
    ],
    "wof:name":"Christian Fellowship Church",
    "wof:placetype":"venue"
},
  "geometry": {"coordinates":[-62.652218,45.601078],"type":"Point"}
}