{
  "type": "Feature",
  "properties": {
    "addr:full":"Surrey BC V3W 7T8",
    "addr:postcode":"v3w 7t8",
    "iso:country":"CA",
    "sg:city":"Surrey",
    "sg:classifiers":[
        {
            "category":"Retail",
            "subcategory":"Auto Repair",
            "type":"Services"
        }
    ],
    "sg:phone":"+1 604 590 0086",
    "sg:postcode":"V3W 7T8",
    "sg:province":"BC",
    "sg:tags":[
        "body",
        "automobile",
        "painting"
    ],
    "wof:name":"A Canadian Autobody & Paint",
    "wof:placetype":"venue"
},
  "geometry": {"coordinates":[-122.850967,49.142307],"type":"Point"}
}