{
  "type": "Feature",
  "properties": {
    "iso:country":"CA",
    "sg:address":"92 King St N",
    "sg:city":"Waterloo",
    "sg:classifiers":[
        {
            "category":"Personal",
            "type":"Services"
        }
    ],
    "sg:phone":"+1 519 884 8801",
    "sg:postcode":"N2J 2X4",
    "sg:province":"ON",
    "sg:tags":[
        "program",
        "physical",
        "exercise",
        "fitness"
    ],
    "wof:name":"Taoist Tai Chi Society",
    "wof:placetype":"venue"
},
  "geometry": {"coordinates":[-80.52300262449999,43.4681930542],"type":"Point"}
}