{
  "type": "Feature",
  "properties": {
    "addr:full":"1261 Glenmore Trail SW Calgary AB T2V 4Y8",
    "addr:housenumber":"1261",
    "addr:postcode":"t2v 4y8",
    "addr:street":"Glenmore Trail Sw",
    "iso:country":"CA",
    "sg:address":"1261 Glenmore Trail SW",
    "sg:city":"Calgary",
    "sg:classifiers":[
        {
            "category":"Health Services",
            "subcategory":"Nursing And Care Facility",
            "type":"Services"
        }
    ],
    "sg:phone":"+1 403 252 0141",
    "sg:postcode":"T2V 4Y8",
    "sg:province":"AB",
    "sg:tags":[
        "home",
        "convalescent"
    ],
    "wof:name":"Chinook Care Ctr",
    "wof:placetype":"venue"
},
  "geometry": {"coordinates":[-114.089584351,50.9938049316],"type":"Point"}
}