{
  "type": "Feature",
  "properties": {
    "iso:country":"CA",
    "sg:address":"160 Rue Du Frere-Dominique",
    "sg:city":"Nicolet",
    "sg:classifiers":[
        {
            "category":"Social Services",
            "type":"Services"
        }
    ],
    "sg:phone":"+1 819 293 5900",
    "sg:postcode":"J3T 1K6",
    "sg:province":"QC",
    "sg:tags":[
        "handicapped",
        "organization",
        "welfare"
    ],
    "wof:name":"Roph Centre Du Quebec",
    "wof:placetype":"venue"
},
  "geometry": {"coordinates":[-72.6067810059,46.2343826294],"type":"Point"}
}