{
  "type": "Feature",
  "properties": {
    "addr:full":"41 Mojave Cres Richmond Hill ON L4S 1R7",
    "addr:housenumber":"41",
    "addr:postcode":"l4s 1r7",
    "addr:street":"Mojave Cres",
    "iso:country":"CA",
    "sg:address":"41 Mojave Cres",
    "sg:city":"Richmond Hill",
    "sg:classifiers":[
        {
            "category":"Building & Trades",
            "subcategory":"Construction",
            "type":"Services"
        }
    ],
    "sg:phone":"+1 905 883 5890",
    "sg:postcode":"L4S 1R7",
    "sg:province":"ON",
    "sg:tags":[
        "painter"
    ],
    "wof:name":"Northern Painting",
    "wof:placetype":"venue"
},
  "geometry": {"coordinates":[-79.46955871580001,43.8966293335],"type":"Point"}
}