{
  "type": "Feature",
  "properties": {
    "addr:full":"150 Boul Notre-Dame Clermont QC G4A 1G2",
    "addr:housenumber":"150",
    "addr:postcode":"g4a 1g2",
    "addr:street":"Boul Notre-Dame",
    "iso:country":"CA",
    "sg:address":"150 Boul Notre-Dame",
    "sg:city":"Clermont",
    "sg:classifiers":[
        {
            "category":"Retail",
            "subcategory":"Auto Repair",
            "type":"Services"
        }
    ],
    "sg:phone":"+1 418 439 3581",
    "sg:postcode":"G4A 1G2",
    "sg:province":"QC",
    "sg:tags":[
        "repairing",
        "automobile"
    ],
    "wof:name":"Garage Atelier Mecanique Dr",
    "wof:placetype":"venue"
},
  "geometry": {"coordinates":[-70.229141,47.691082],"type":"Point"}
}