{
  "type": "Feature",
  "properties": {
    "addr:full":"Calgary AB T1Y 6G7",
    "addr:postcode":"t1y 6g7",
    "iso:country":"CA",
    "sg:city":"Calgary",
    "sg:classifiers":[
        {
            "category":"Home & Garden",
            "subcategory":"Building Materials",
            "type":"Retail Goods"
        }
    ],
    "sg:phone":"+1 403 219 0822",
    "sg:postcode":"T1Y 6G7",
    "sg:province":"AB",
    "sg:tags":[
        "glass",
        "window",
        "plate"
    ],
    "wof:name":"Heritage Glass & Aluminum",
    "wof:placetype":"venue"
},
  "geometry": {"coordinates":[-113.98839599999999,51.084839],"type":"Point"}
}