{
  "type": "Feature",
  "properties": {
    "iso:country":"CA",
    "sg:address":"4143 97 St NW",
    "sg:city":"Edmonton",
    "sg:classifiers":[
        {
            "category":"Wholesale",
            "subcategory":"Electrical",
            "type":"Manufacturing & Wholesale Goods"
        }
    ],
    "sg:phone":"+1 780 461 2334",
    "sg:postcode":"T6E 6E9",
    "sg:province":"AB",
    "sg:tags":[
        "equipment",
        "electric",
        "supply"
    ],
    "wof:name":"B J Electric Supplies Ltd",
    "wof:placetype":"venue"
},
  "geometry": {"coordinates":[-113.47921,53.477478],"type":"Point"}
}