{
  "type": "Feature",
  "properties": {
    "addr:full":"78 Rue DE L'Assomption Granby QC J2G 3S1",
    "addr:housenumber":"78",
    "addr:postcode":"j2g 3s1",
    "addr:street":"Rue De L'Assomption",
    "iso:country":"CA",
    "sg:address":"78 Rue DE L'Assomption",
    "sg:city":"Granby",
    "sg:classifiers":[
        {
            "category":"Shopping",
            "subcategory":"Computers & Home Electronics",
            "type":"Retail Goods"
        }
    ],
    "sg:phone":"+1 450 375 2323",
    "sg:postcode":"J2G 3S1",
    "sg:province":"QC",
    "sg:tags":[
        "radio",
        "television",
        "video",
        "equipment"
    ],
    "wof:name":"Clinique Du Son Inc",
    "wof:placetype":"venue"
},
  "geometry": {"coordinates":[-72.731300354,45.397819519],"type":"Point"}
}