{
  "type": "Feature",
  "properties": {
    "iso:country":"CA",
    "sg:address":"1061 Granville St # 102",
    "sg:city":"Vancouver",
    "sg:classifiers":[
        {
            "category":"Food & Beverages",
            "subcategory":"Groceries & Convenience Stores",
            "type":"Retail Goods"
        }
    ],
    "sg:phone":"+1 604 683 7864",
    "sg:postcode":"V6Z 1L4",
    "sg:province":"BC",
    "sg:tags":[
        "grocer"
    ],
    "wof:name":"Sunny Grocery",
    "wof:placetype":"venue"
},
  "geometry": {"coordinates":[-123.124084473,49.2787742615],"type":"Point"}
}