{
  "type": "Feature",
  "properties": {
    "iso:country":"CA",
    "sg:city":"Port Coquitlam",
    "sg:classifiers":[
        {
            "category":"Building & Trades",
            "subcategory":"Construction",
            "type":"Services"
        }
    ],
    "sg:phone":"+1 604 878 0880",
    "sg:postcode":"V3C 4K9",
    "sg:province":"BC",
    "sg:tags":[
        "water",
        "control",
        "pollution"
    ],
    "wof:name":"Nbs Environmental",
    "wof:placetype":"venue"
},
  "geometry": {"coordinates":[-122.765693665,49.2531585693],"type":"Point"}
}