{
  "type": "Feature",
  "properties": {
    "iso:country":"CA",
    "sg:address":"36 Bentley Ave",
    "sg:city":"Nepean",
    "sg:classifiers":[
        {
            "category":"Utilities",
            "subcategory":"Fuel Oil & Lpg",
            "type":"Services"
        }
    ],
    "sg:phone":"+1 613 727 5200",
    "sg:postcode":"K2E 6T8",
    "sg:province":"ON",
    "wof:name":"Ultramar",
    "wof:placetype":"venue"
},
  "geometry": {"coordinates":[-75.7191314697,45.3328285217],"type":"Point"}
}