{
  "type": "Feature",
  "properties": {
    "addr:full":"Saint-Paul QC J0K 3E0",
    "addr:postcode":"j0k 3e0",
    "iso:country":"CA",
    "sg:city":"Saint-Paul",
    "sg:classifiers":[
        {
            "category":"Personal",
            "subcategory":"Beauty Salon",
            "type":"Services"
        }
    ],
    "sg:phone":"+1 450 755 2816",
    "sg:postcode":"J0K 3E0",
    "sg:province":"QC",
    "wof:name":"Salon DE Coiffure L'Entregent",
    "wof:placetype":"venue"
},
  "geometry": {"coordinates":[-73.4438858032,45.9805908203],"type":"Point"}
}