{
  "type": "Feature",
  "properties": {
    "addr:full":"Summerside PE C1N 4J9",
    "addr:postcode":"c1n 4j9",
    "iso:country":"CA",
    "sg:city":"Summerside",
    "sg:classifiers":[
        {
            "category":"Professional",
            "subcategory":"Management & Consulting",
            "type":"Services"
        }
    ],
    "sg:phone":"+1 902 436 8400",
    "sg:postcode":"C1N 4J9",
    "sg:province":"PE",
    "sg:tags":[
        "project"
    ],
    "wof:name":"Design Tech Svc Ltd",
    "wof:placetype":"venue"
},
  "geometry": {"coordinates":[-63.787434,46.401356],"type":"Point"}
}