{
  "type": "Feature",
  "properties": {
    "addr:full":"Mississauga ON L5T 1E4",
    "addr:postcode":"l5t 1e4",
    "iso:country":"CA",
    "sg:city":"Mississauga",
    "sg:classifiers":[
        {
            "category":"Wholesale",
            "subcategory":"Auto Parts",
            "type":"Manufacturing & Wholesale Goods"
        }
    ],
    "sg:phone":"+1 905 564 8020",
    "sg:postcode":"L5T 1E4",
    "sg:province":"ON",
    "sg:tags":[
        "equipment",
        "truck"
    ],
    "wof:name":"Fleet Tec",
    "wof:placetype":"venue"
},
  "geometry": {"coordinates":[-79.65788999999999,43.651894],"type":"Point"}
}