{
  "type": "Feature",
  "properties": {
    "iso:country":"CA",
    "sg:city":"Saint-Eustache",
    "sg:classifiers":[
        {
            "category":"Autos & Motor Vehicles",
            "subcategory":"Auto Supplies",
            "type":"Retail Goods"
        }
    ],
    "sg:phone":"+1 450 472 6006",
    "sg:postcode":"J7P 1J1",
    "sg:province":"QC",
    "sg:tags":[
        "automobile",
        "parts"
    ],
    "wof:name":"Pieces D'Auto Grande Cote Inc",
    "wof:placetype":"venue"
},
  "geometry": {"coordinates":[-73.887253,45.560379],"type":"Point"}
}