{
  "type": "Feature",
  "properties": {
    "addr:full":"133 Road To the Isles Summerford NL A0G 4E0",
    "addr:postcode":"a0g 4e0",
    "addr:street":"133 Road To The",
    "iso:country":"CA",
    "sg:address":"133 Road To the Isles",
    "sg:city":"Summerford",
    "sg:classifiers":[
        {
            "category":"Building & Trades",
            "subcategory":"Construction",
            "type":"Services"
        }
    ],
    "sg:phone":"+1 709 629 3609",
    "sg:postcode":"A0G 4E0",
    "sg:province":"NL",
    "sg:tags":[
        "general",
        "contractor"
    ],
    "wof:name":"Bulgin Enterprises",
    "wof:placetype":"venue"
},
  "geometry": {"coordinates":[-54.8064231873,49.4896697998],"type":"Point"}
}