{
  "type": "Feature",
  "properties": {
    "iso:country":"CA",
    "sg:address":"60 Baker St",
    "sg:city":"Guelph",
    "sg:classifiers":[
        {
            "category":"Food & Beverages",
            "subcategory":"Bakery",
            "type":"Retail Goods"
        }
    ],
    "sg:phone":"+1 519 362 1967",
    "sg:postcode":"N1H 4G1",
    "sg:province":"ON",
    "sg:tags":[
        "caterer"
    ],
    "wof:name":"Blackbird Catering CO",
    "wof:placetype":"venue"
},
  "geometry": {"coordinates":[-80.25211334230001,43.5469360352],"type":"Point"}
}