{
  "type": "Feature",
  "properties": {
    "iso:country":"CA",
    "sg:address":"390 North Front St",
    "sg:city":"Belleville",
    "sg:classifiers":[
        {
            "category":"Personal",
            "subcategory":"Beauty Salon",
            "type":"Services"
        }
    ],
    "sg:phone":"+1 613 962 1222",
    "sg:postcode":"K8P 3E1",
    "sg:province":"ON",
    "wof:name":"Regis",
    "wof:placetype":"venue"
},
  "geometry": {"coordinates":[-77.396591,44.1884],"type":"Point"}
}