{
  "type": "Feature",
  "properties": {
    "addr:full":"300 Merritt Ave Chatham ON N7M 3G1",
    "addr:housenumber":"300",
    "addr:postcode":"n7m 3g1",
    "addr:street":"Merritt Ave",
    "iso:country":"CA",
    "sg:address":"300 Merritt Ave",
    "sg:city":"Chatham",
    "sg:classifiers":[
        {
            "category":"Insurance",
            "subcategory":"Insurance Agent",
            "type":"Services"
        }
    ],
    "sg:phone":"+1 519 352 9550",
    "sg:postcode":"N7M 3G1",
    "sg:province":"ON",
    "wof:name":"Gary Dick Insurance",
    "wof:placetype":"venue"
},
  "geometry": {"coordinates":[-82.1997756958,42.3944664001],"type":"Point"}
}