{
  "type": "Feature",
  "properties": {
    "addr:full":"2705 Haddington Cres Port Mcneill BC V0N 2R0",
    "addr:housenumber":"2705",
    "addr:postcode":"v0n 2r0",
    "addr:street":"Haddington Cres",
    "iso:country":"CA",
    "sg:address":"2705 Haddington Cres",
    "sg:city":"Port Mcneill",
    "sg:classifiers":[
        {
            "category":"Government",
            "subcategory":"Fire Station",
            "type":"Public Place"
        }
    ],
    "sg:phone":"+1 250 956 4513",
    "sg:postcode":"V0N 2R0",
    "sg:province":"BC",
    "sg:tags":[
        "department"
    ],
    "wof:name":"Port Mc Neill Fire Chief",
    "wof:placetype":"venue"
},
  "geometry": {"coordinates":[-127.072639,50.582409],"type":"Point"}
}