{
  "type": "Feature",
  "properties": {
    "addr:full":"Abbotsford BC V2S 2A6",
    "addr:postcode":"v2s 2a6",
    "iso:country":"CA",
    "sg:city":"Abbotsford",
    "sg:classifiers":[
        {
            "category":"Restaurant",
            "type":"Food & Drink"
        }
    ],
    "sg:phone":"+1 604 853 8185",
    "sg:postcode":"V2S 2A6",
    "sg:province":"BC",
    "wof:name":"Red Robin Restaurant Ltd",
    "wof:placetype":"venue"
},
  "geometry": {"coordinates":[-122.308921814,49.0509300232],"type":"Point"}
}