{
  "type": "Feature",
  "properties": {
    "addr:full":"645 Gardiners Rd Kingston ON K7M 8K2",
    "addr:housenumber":"645",
    "addr:postcode":"k7m 8k2",
    "addr:street":"Gardiners Rd",
    "iso:country":"CA",
    "sg:address":"645 Gardiners Rd",
    "sg:city":"Kingston",
    "sg:classifiers":[
        {
            "category":"Personal",
            "type":"Services"
        }
    ],
    "sg:phone":"+1 613 389 1919",
    "sg:postcode":"K7M 8K2",
    "sg:province":"ON",
    "sg:tags":[
        "control",
        "weight"
    ],
    "wof:name":"Bernstein, S K",
    "wof:placetype":"venue"
},
  "geometry": {"coordinates":[-76.5680847168,44.2440795898],"type":"Point"}
}