{
  "type": "Feature",
  "properties": {
    "addr:full":"Vancouver BC V6G 2T3",
    "addr:postcode":"v6g 2t3",
    "iso:country":"CA",
    "sg:city":"Vancouver",
    "sg:classifiers":[
        {
            "category":"Real Estate",
            "subcategory":"Real Estate Agent",
            "type":"Services"
        }
    ],
    "sg:phone":"+1 604 662 8099",
    "sg:postcode":"V6G 2T3",
    "sg:province":"BC",
    "sg:tags":[
        "consultant"
    ],
    "wof:name":"Development Consulting Group",
    "wof:placetype":"venue"
},
  "geometry": {"coordinates":[-123.129394531,49.2899856567],"type":"Point"}
}