{
  "type": "Feature",
  "properties": {
    "iso:country":"CA",
    "sg:city":"Mississauga",
    "sg:classifiers":[
        {
            "category":"Real Estate",
            "subcategory":"Real Estate Agent",
            "type":"Services"
        }
    ],
    "sg:phone":"+1 905 670 0501",
    "sg:postcode":"L5T 1K4",
    "sg:province":"ON",
    "sg:tags":[
        "management"
    ],
    "wof:name":"Orion Management",
    "wof:placetype":"venue"
},
  "geometry": {"coordinates":[-79.64962005620001,43.6597557068],"type":"Point"}
}