{
  "type": "Feature",
  "properties": {
    "addr:full":"361 Stevens Rd Kapuskasing ON P5N 2X7",
    "addr:housenumber":"361",
    "addr:postcode":"p5n 2x7",
    "addr:street":"Stevens Rd",
    "iso:country":"CA",
    "sg:address":"361 Stevens Rd",
    "sg:city":"Kapuskasing",
    "sg:classifiers":[
        {
            "category":"Manufacturing",
            "subcategory":"Lumber",
            "type":"Manufacturing & Wholesale Goods"
        }
    ],
    "sg:phone":"+1 705 337 5010",
    "sg:postcode":"P5N 2X7",
    "sg:province":"ON",
    "sg:tags":[
        "company",
        "logging"
    ],
    "wof:name":"Dumais Logging Ltd",
    "wof:placetype":"venue"
},
  "geometry": {"coordinates":[-82.37878417970001,49.3770027161],"type":"Point"}
}