{
  "type": "Feature",
  "properties": {
    "addr:full":"8371 Boul Newman # A Lasalle QC H8N 1Y4",
    "addr:housenumber":"8371;# a",
    "addr:postcode":"h8n 1y4",
    "addr:street":"Boul Newman",
    "iso:country":"CA",
    "sg:address":"8371 Boul Newman # A",
    "sg:city":"Lasalle",
    "sg:classifiers":[
        {
            "category":"Health Services",
            "subcategory":"Doctor",
            "type":"Services"
        }
    ],
    "sg:phone":"+1 514 366 4280",
    "sg:postcode":"H8N 1Y4",
    "sg:province":"QC",
    "sg:tags":[
        "physician",
        "surgeon"
    ],
    "wof:name":"Castonguay, Gilles MD",
    "wof:placetype":"venue"
},
  "geometry": {"coordinates":[-73.6295700073,45.4329910278],"type":"Point"}
}