{
  "type": "Feature",
  "properties": {
    "addr:full":"2938 Ch Royal Notre-Dame-Des-Pins QC G0M 1K0",
    "addr:housenumber":"2938",
    "addr:postcode":"g0m 1k0",
    "addr:street":"Ch Royal",
    "iso:country":"CA",
    "sg:address":"2938 Ch Royal",
    "sg:city":"Notre-Dame-Des-Pins",
    "sg:classifiers":[
        {
            "category":"Autos & Motor Vehicles",
            "subcategory":"Automobile Sales",
            "type":"Retail Goods"
        }
    ],
    "sg:phone":"+1 418 774 3846",
    "sg:postcode":"G0M 1K0",
    "sg:province":"QC",
    "sg:tags":[
        "snowmobile"
    ],
    "wof:name":"Securitour Location Moto-Neige",
    "wof:placetype":"venue"
},
  "geometry": {"coordinates":[-70.72109985349999,46.1770362854],"type":"Point"}
}