{
  "type": "Feature",
  "properties": {
    "addr:full":"462 Ch Saint-Louis Saint-Etienne-DE-Beauharnois QC J0S 1S0",
    "addr:housenumber":"462",
    "addr:postcode":"j0s 1s0",
    "addr:street":"Ch Saint-Louis",
    "iso:country":"CA",
    "sg:address":"462 Ch Saint-Louis",
    "sg:city":"Saint-Etienne-DE-Beauharnois",
    "sg:classifiers":[
        {
            "category":"Restaurant",
            "type":"Food & Drink"
        }
    ],
    "sg:phone":"+1 450 429 7412",
    "sg:postcode":"J0S 1S0",
    "sg:province":"QC",
    "sg:tags":[
        "caterer"
    ],
    "wof:name":"Buffet Marie-Chantal Enr",
    "wof:placetype":"venue"
},
  "geometry": {"coordinates":[-73.9175109863,45.2441062927],"type":"Point"}
}