{
  "type": "Feature",
  "properties": {
    "addr:full":"Langley BC V2Y 1G9",
    "addr:postcode":"v2y 1g9",
    "iso:country":"CA",
    "sg:city":"Langley",
    "sg:classifiers":[
        {
            "category":"Recreation",
            "type":"Entertainment"
        }
    ],
    "sg:phone":"+1 604 532 4822",
    "sg:postcode":"V2Y 1G9",
    "sg:province":"BC",
    "sg:tags":[
        "yoga",
        "club",
        "instruction",
        "gymnasium",
        "studio",
        "health"
    ],
    "wof:name":"Evolution Pilates & Yoga Std",
    "wof:placetype":"venue"
},
  "geometry": {"coordinates":[-122.671829,49.119171],"type":"Point"}
}