{
  "type": "Feature",
  "properties": {
    "addr:full":"1865 Lakeshore Rd W Mississauga ON L5J 4P1",
    "addr:housenumber":"1865",
    "addr:postcode":"l5j 4p1",
    "addr:street":"Lakeshore Rd W",
    "iso:country":"CA",
    "sg:address":"1865 Lakeshore Rd W",
    "sg:city":"Mississauga",
    "sg:classifiers":[
        {
            "category":"Shopping",
            "subcategory":"Pharmacy",
            "type":"Retail Goods"
        }
    ],
    "sg:phone":"+1 905 823 0490",
    "sg:postcode":"L5J 4P1",
    "sg:province":"ON",
    "wof:name":"Shoppers Drug Mart",
    "wof:placetype":"venue"
},
  "geometry": {"coordinates":[-79.6259765625,43.5148696899],"type":"Point"}
}