{
  "type": "Feature",
  "properties": {
    "addr:full":"2488 Graham St Pakenham ON K0A 2X0",
    "addr:housenumber":"2488",
    "addr:postcode":"k0a 2x0",
    "addr:street":"Graham St",
    "iso:country":"CA",
    "sg:address":"2488 Graham St",
    "sg:city":"Pakenham",
    "sg:classifiers":[
        {
            "category":"Wholesale",
            "subcategory":"Farm Supplies",
            "type":"Manufacturing & Wholesale Goods"
        }
    ],
    "sg:phone":"+1 613 624 5569",
    "sg:postcode":"K0A 2X0",
    "sg:province":"ON",
    "sg:tags":[
        "feed"
    ],
    "wof:name":"5 Span Feed & Seed Inc",
    "wof:placetype":"venue"
},
  "geometry": {"coordinates":[-76.29052734379999,45.3325119019],"type":"Point"}
}