{
  "type": "Feature",
  "properties": {
    "iso:country":"CA",
    "sg:address":"50 Rue Dufferin",
    "sg:city":"Salaberry-DE-Valleyfield",
    "sg:classifiers":[
        {
            "category":"Shopping",
            "subcategory":"Clothing, Apparel, & Fashions",
            "type":"Retail Goods"
        }
    ],
    "sg:phone":"+1 450 371 5837",
    "sg:postcode":"J6S 4W4",
    "sg:province":"QC",
    "sg:tags":[
        "item",
        "boutique"
    ],
    "wof:name":"Boutique Le Pentagone Inc",
    "wof:placetype":"venue"
},
  "geometry": {"coordinates":[-74.128937,45.262398],"type":"Point"}
}