{
  "type": "Feature",
  "properties": {
    "addr:full":"3199 Walker Rd Windsor ON N8W 3R6",
    "addr:housenumber":"3199",
    "addr:postcode":"n8w 3r6",
    "addr:street":"Walker Rd",
    "iso:country":"CA",
    "sg:address":"3199 Walker Rd",
    "sg:city":"Windsor",
    "sg:classifiers":[
        {
            "category":"Retail",
            "subcategory":"Auto Repair",
            "type":"Services"
        }
    ],
    "sg:phone":"+1 519 966 1390",
    "sg:postcode":"N8W 3R6",
    "sg:province":"ON",
    "sg:tags":[
        "repairing",
        "automobile"
    ],
    "wof:name":"Kavanaugh Garnet Svc",
    "wof:placetype":"venue"
},
  "geometry": {"coordinates":[-82.98062896730001,42.2806587219],"type":"Point"}
}