{
  "type": "Feature",
  "properties": {
    "addr:full":"3690 Walker Rd Windsor ON N8W 3S7",
    "addr:housenumber":"3690",
    "addr:postcode":"n8w 3s7",
    "addr:street":"Walker Rd",
    "iso:country":"CA",
    "sg:address":"3690 Walker Rd",
    "sg:city":"Windsor",
    "sg:classifiers":[
        {
            "category":"Personal",
            "subcategory":"Beauty Salon",
            "type":"Services"
        }
    ],
    "sg:phone":"+1 519 969 6908",
    "sg:postcode":"N8W 3S7",
    "sg:province":"ON",
    "wof:name":"Classic Cuts",
    "wof:placetype":"venue"
},
  "geometry": {"coordinates":[-82.973671,42.270245],"type":"Point"}
}