{
  "type": "Feature",
  "properties": {
    "addr:full":"336 Armour Rd Peterborough ON K9H 1Y6",
    "addr:housenumber":"336",
    "addr:postcode":"k9h 1y6",
    "addr:street":"Armour Rd",
    "iso:country":"CA",
    "sg:address":"336 Armour Rd",
    "sg:city":"Peterborough",
    "sg:classifiers":[
        {
            "category":"Health Services",
            "subcategory":"Doctor",
            "type":"Services"
        }
    ],
    "sg:phone":"+1 705 743 8085",
    "sg:postcode":"K9H 1Y6",
    "sg:province":"ON",
    "sg:tags":[
        "dentist"
    ],
    "wof:name":"Kaller, K DDS",
    "wof:placetype":"venue"
},
  "geometry": {"coordinates":[-78.3045883179,44.3059844971],"type":"Point"}
}