{
  "type": "Feature",
  "properties": {
    "addr:full":"2031 Rue Principale Saint-Faustin-Lac-Carre QC J0T 1J1",
    "addr:housenumber":"2031",
    "addr:postcode":"j0t 1j1",
    "addr:street":"Rue Principale",
    "iso:country":"CA",
    "sg:address":"2031 Rue Principale",
    "sg:city":"Saint-Faustin-Lac-Carre",
    "sg:classifiers":[
        {
            "category":"Building & Trades",
            "subcategory":"Construction",
            "type":"Services"
        }
    ],
    "sg:phone":"+1 819 688 2958",
    "sg:postcode":"J0T 1J1",
    "sg:province":"QC",
    "sg:tags":[
        "paint",
        "painter"
    ],
    "wof:name":"Peintures Du Lac Carre Enr",
    "wof:placetype":"venue"
},
  "geometry": {"coordinates":[-74.47271000000001,46.132233],"type":"Point"}
}