{
  "type": "Feature",
  "properties": {
    "addr:full":"Mississauga ON L5J 4B3",
    "addr:postcode":"l5j 4b3",
    "iso:country":"CA",
    "sg:city":"Mississauga",
    "sg:classifiers":[
        {
            "category":"Real Estate",
            "subcategory":"Real Estate Operator",
            "type":"Services"
        }
    ],
    "sg:phone":"+1 905 822 6009",
    "sg:postcode":"L5J 4B3",
    "sg:province":"ON",
    "sg:tags":[
        "apartment"
    ],
    "wof:name":"Bromsgate Apartments",
    "wof:placetype":"venue"
},
  "geometry": {"coordinates":[-79.63786315919999,43.511806488],"type":"Point"}
}