{
  "type": "Feature",
  "properties": {
    "iso:country":"CA",
    "sg:address":"3075 Ridgeway Dr",
    "sg:city":"Mississauga",
    "sg:classifiers":[
        {
            "category":"Organizations",
            "subcategory":"Religious Organization",
            "type":"Services"
        }
    ],
    "sg:phone":"+1 905 828 5951",
    "sg:postcode":"L5L 5M6",
    "sg:province":"ON",
    "sg:tags":[
        "publishing"
    ],
    "wof:name":"T & M Publishing",
    "wof:placetype":"venue"
},
  "geometry": {"coordinates":[-79.68938446040001,43.5186347961],"type":"Point"}
}