{
  "type": "Feature",
  "properties": {
    "addr:full":"210 Rue Principale Granby QC J2G 2V8",
    "addr:housenumber":"210",
    "addr:postcode":"j2g 2v8",
    "addr:street":"Rue Principale",
    "iso:country":"CA",
    "sg:address":"210 Rue Principale",
    "sg:city":"Granby",
    "sg:classifiers":[
        {
            "category":"Shopping",
            "subcategory":"Bicycles & Sporting Goods",
            "type":"Retail Goods"
        }
    ],
    "sg:phone":"+1 450 777 7949",
    "sg:postcode":"J2G 2V8",
    "sg:province":"QC",
    "sg:tags":[
        "equipment",
        "camping"
    ],
    "wof:name":"Bivouac",
    "wof:placetype":"venue"
},
  "geometry": {"coordinates":[-72.727783,45.400215],"type":"Point"}
}