{
  "type": "Feature",
  "properties": {
    "addr:full":"PO Box 3 Coalhurst AB T0L 0V0",
    "addr:housenumber":"po;3",
    "addr:postcode":"t0l 0v0",
    "addr:street":"Box",
    "iso:country":"CA",
    "sg:address":"PO Box 3",
    "sg:city":"Coalhurst",
    "sg:classifiers":[
        {
            "category":"Wholesale",
            "subcategory":"Construction Materials",
            "type":"Manufacturing & Wholesale Goods"
        }
    ],
    "sg:phone":"+1 403 381 3744",
    "sg:postcode":"T0L 0V0",
    "sg:province":"AB",
    "sg:tags":[
        "sand",
        "gravel"
    ],
    "wof:name":"M P Crushing Ltd",
    "wof:placetype":"venue"
},
  "geometry": {"coordinates":[-112.933685303,49.7454185486],"type":"Point"}
}