{
  "type": "Feature",
  "properties": {
    "addr:full":"23 Strathearn Ave Brampton ON L6T 4P1",
    "addr:housenumber":"23",
    "addr:postcode":"l6t 4p1",
    "addr:street":"Strathearn Ave",
    "iso:country":"CA",
    "sg:address":"23 Strathearn Ave",
    "sg:city":"Brampton",
    "sg:classifiers":[
        {
            "category":"Wholesale",
            "subcategory":"Electrical",
            "type":"Manufacturing & Wholesale Goods"
        }
    ],
    "sg:phone":"+1 905 792 1111",
    "sg:postcode":"L6T 4P1",
    "sg:province":"ON",
    "sg:tags":[
        "equipment",
        "electric",
        "supply"
    ],
    "wof:name":"Bramtor Electric Supply CO Ltd",
    "wof:placetype":"venue"
},
  "geometry": {"coordinates":[-79.695892,43.69371],"type":"Point"}
}