{
  "type": "Feature",
  "properties": {
    "addr:full":"529 Lisgar Ave Renfrew ON K7V 3N6",
    "addr:housenumber":"529",
    "addr:postcode":"k7v 3n6",
    "addr:street":"Lisgar Ave",
    "iso:country":"CA",
    "sg:address":"529 Lisgar Ave",
    "sg:city":"Renfrew",
    "sg:classifiers":[
        {
            "category":"Government",
            "subcategory":"Office",
            "type":"Public Place"
        }
    ],
    "sg:phone":"+1 613 432 4147",
    "sg:postcode":"K7V 3N6",
    "sg:province":"ON",
    "sg:tags":[
        "village"
    ],
    "wof:name":"Renfrew Public Works Garage",
    "wof:placetype":"venue"
},
  "geometry": {"coordinates":[-76.700439,45.470348],"type":"Point"}
}