{
  "type": "Feature",
  "properties": {
    "iso:country":"CA",
    "sg:address":"104 Boul DE LA Marine",
    "sg:city":"Varennes",
    "sg:classifiers":[
        {
            "category":"Education",
            "subcategory":"School",
            "type":"Public Place"
        }
    ],
    "sg:phone":"+1 450 652 6869",
    "sg:postcode":"J3X 1Z5",
    "sg:province":"QC",
    "wof:name":"Ecole Primaire Ctr Educatif",
    "wof:placetype":"venue"
},
  "geometry": {"coordinates":[-73.432579,45.664238],"type":"Point"}
}