{
  "type": "Feature",
  "properties": {
    "addr:full":"1677 St. Jean St Val Caron ON P3N 1N1",
    "addr:housenumber":"1677",
    "addr:postcode":"p3n 1n1",
    "addr:street":"St. Jean St",
    "iso:country":"CA",
    "sg:address":"1677 St. Jean St",
    "sg:city":"Val Caron",
    "sg:classifiers":[
        {
            "category":"Health Services",
            "subcategory":"Nursing And Care Facility",
            "type":"Services"
        }
    ],
    "sg:phone":"+1 705 897 3142",
    "sg:postcode":"P3N 1N1",
    "sg:province":"ON",
    "sg:tags":[
        "home",
        "retirement",
        "community"
    ],
    "wof:name":"Golden Years Retirement Home",
    "wof:placetype":"venue"
},
  "geometry": {"coordinates":[-81.00907100000001,46.609306],"type":"Point"}
}