{
  "type": "Feature",
  "properties": {
    "addr:full":"Buckingham QC J8L 1K1",
    "addr:postcode":"j8l 1k1",
    "iso:country":"CA",
    "sg:city":"Buckingham",
    "sg:classifiers":[
        {
            "category":"Cinema",
            "subcategory":"Movie Rental",
            "type":"Entertainment"
        }
    ],
    "sg:phone":"+1 819 986 6111",
    "sg:postcode":"J8L 1K1",
    "sg:province":"QC",
    "sg:tags":[
        "video",
        "game",
        "tape",
        "leasing"
    ],
    "wof:name":"Super Club Videotron",
    "wof:placetype":"venue"
},
  "geometry": {"coordinates":[-75.415848,45.586674],"type":"Point"}
}