{
  "type": "Feature",
  "properties": {
    "addr:full":"4639 Rue Ontario E Montreal QC H1V 1L1",
    "addr:housenumber":"4639",
    "addr:postcode":"h1v 1l1",
    "addr:street":"Rue Ontario E",
    "iso:country":"CA",
    "sg:address":"4639 Rue Ontario E",
    "sg:city":"Montreal",
    "sg:classifiers":[
        {
            "category":"Health Services",
            "subcategory":"Doctor",
            "type":"Services"
        }
    ],
    "sg:phone":"+1 514 252 8778",
    "sg:postcode":"H1V 1L1",
    "sg:province":"QC",
    "sg:tags":[
        "clinic"
    ],
    "wof:name":"Clinique Medicale Viauville",
    "wof:placetype":"venue"
},
  "geometry": {"coordinates":[-73.53774300000001,45.556026],"type":"Point"}
}