{
  "type": "Feature",
  "properties": {
    "addr:full":"3126 Broadway W Vancouver BC V6K 2H3",
    "addr:housenumber":"3126",
    "addr:postcode":"v6k 2h3",
    "addr:street":"Broadway W",
    "iso:country":"CA",
    "sg:address":"3126 Broadway W",
    "sg:city":"Vancouver",
    "sg:classifiers":[
        {
            "category":"Health Services",
            "subcategory":"Doctor",
            "type":"Services"
        }
    ],
    "sg:phone":"+1 604 732 3930",
    "sg:postcode":"V6K 2H3",
    "sg:province":"BC",
    "sg:tags":[
        "clinic"
    ],
    "wof:name":"Anxiety & Stress Reduction Cln",
    "wof:placetype":"venue"
},
  "geometry": {"coordinates":[-123.174453735,49.2640190125],"type":"Point"}
}