{
  "type": "Feature",
  "properties": {
    "addr:full":"2 Kalium Rd Belle Plaine SK S0G 0G0",
    "addr:housenumber":"2",
    "addr:postcode":"s0g 0g0",
    "addr:street":"Kalium Rd;Plaine",
    "iso:country":"CA",
    "sg:address":"2 Kalium Rd",
    "sg:city":"Belle Plaine",
    "sg:classifiers":[
        {
            "category":"Manufacturing",
            "subcategory":"Chemicals & Compounds",
            "type":"Manufacturing & Wholesale Goods"
        }
    ],
    "sg:phone":"+1 306 345 4200",
    "sg:postcode":"S0G 0G0",
    "sg:province":"SK",
    "sg:tags":[
        "fertilizer"
    ],
    "wof:name":"Saskferco Products Inc",
    "wof:placetype":"venue"
},
  "geometry": {"coordinates":[-105.152450562,50.3932495117],"type":"Point"}
}