{
  "type": "Feature",
  "properties": {
    "iso:country":"CA",
    "sg:address":"444 7 Ave SW",
    "sg:city":"Calgary",
    "sg:classifiers":[
        {
            "category":"Government",
            "subcategory":"Office",
            "type":"Public Place"
        }
    ],
    "sg:phone":"+1 403 292 4800",
    "sg:postcode":"T2P 0X8",
    "sg:province":"AB",
    "wof:name":"Canada National Energy Board",
    "wof:placetype":"venue"
},
  "geometry": {"coordinates":[-114.070847,51.046806],"type":"Point"}
}