{
  "type": "Feature",
  "properties": {
    "addr:full":"26 Rue Notre-Dame E Montreal QC H2Y 1B9",
    "addr:housenumber":"26",
    "addr:postcode":"h2y 1b9",
    "addr:street":"Rue Notre-Dame E",
    "iso:country":"CA",
    "sg:address":"26 Rue Notre-Dame E",
    "sg:city":"Montreal",
    "sg:classifiers":[
        {
            "category":"Shopping",
            "subcategory":"Photographic Equipment",
            "type":"Retail Goods"
        }
    ],
    "sg:phone":"+1 514 875 5110",
    "sg:postcode":"H2Y 1B9",
    "sg:province":"QC",
    "sg:tags":[
        "supply"
    ],
    "wof:name":"Camtec Photo",
    "wof:placetype":"venue"
},
  "geometry": {"coordinates":[-73.5552444458,45.5065612793],"type":"Point"}
}