{
  "type": "Feature",
  "properties": {
    "addr:full":"2260 Philip Ave North Vancouver BC V7P 2W8",
    "addr:housenumber":"2260",
    "addr:postcode":"v7p 2w8",
    "addr:street":"Philip Ave",
    "iso:country":"CA",
    "sg:address":"2260 Philip Ave",
    "sg:city":"North Vancouver",
    "sg:classifiers":[
        {
            "category":"Social Services",
            "subcategory":"Child Care",
            "type":"Services"
        }
    ],
    "sg:phone":"+1 604 985 9622",
    "sg:postcode":"V7P 2W8",
    "sg:province":"BC",
    "wof:name":"Sunflower Preschool",
    "wof:placetype":"venue"
},
  "geometry": {"coordinates":[-123.112884522,49.3306541443],"type":"Point"}
}