{
  "type": "Feature",
  "properties": {
    "addr:full":"346 Queen St # 201 Fredericton NB E3B 1B2",
    "addr:housenumber":"346",
    "addr:postcode":"e3b 1b2",
    "addr:street":"Queen St # 201",
    "iso:country":"CA",
    "sg:address":"346 Queen St # 201",
    "sg:city":"Fredericton",
    "sg:classifiers":[
        {
            "category":"Professional",
            "subcategory":"Lawyer & Legal Services",
            "type":"Services"
        }
    ],
    "sg:phone":"+1 506 450 2848",
    "sg:postcode":"E3B 1B2",
    "sg:province":"NB",
    "sg:tags":[
        "attorney"
    ],
    "wof:name":"Davidson, Norah J",
    "wof:placetype":"venue"
},
  "geometry": {"coordinates":[-66.64437100000001,45.963398],"type":"Point"}
}