{
  "type": "Feature",
  "properties": {
    "iso:country":"CA",
    "sg:address":"20810 Dalton Rd",
    "sg:city":"Sutton West",
    "sg:classifiers":[
        {
            "category":"Restaurant",
            "type":"Food & Drink"
        }
    ],
    "sg:phone":"+1 905 722 3762",
    "sg:postcode":"L0E 1R0",
    "sg:province":"ON",
    "wof:name":"South Shore Restaurant",
    "wof:placetype":"venue"
},
  "geometry": {"coordinates":[-79.362686,44.303631],"type":"Point"}
}