{
  "type": "Feature",
  "properties": {
    "addr:full":"Bragg Creek AB T0L 0K0",
    "addr:postcode":"t0l 0k0",
    "iso:country":"CA",
    "sg:city":"Bragg Creek",
    "sg:classifiers":[
        {
            "category":"Mining & Drilling",
            "type":"Manufacturing & Wholesale Goods"
        }
    ],
    "sg:phone":"+1 403 949 2022",
    "sg:postcode":"T0L 0K0",
    "sg:province":"AB",
    "sg:tags":[
        "company",
        "oil"
    ],
    "wof:name":"Shell Canada Ltd",
    "wof:placetype":"venue"
},
  "geometry": {"coordinates":[-114.56076,50.951038],"type":"Point"}
}