{
  "type": "Feature",
  "properties": {
    "addr:full":"76 Main St W Grimsby ON L3M 1R6",
    "addr:housenumber":"76",
    "addr:postcode":"l3m 1r6",
    "addr:street":"Main St W",
    "iso:country":"CA",
    "sg:address":"76 Main St W",
    "sg:city":"Grimsby",
    "sg:classifiers":[
        {
            "category":"Professional",
            "subcategory":"Management & Consulting",
            "type":"Services"
        }
    ],
    "sg:phone":"+1 905 945 6791",
    "sg:postcode":"L3M 1R6",
    "sg:province":"ON",
    "sg:tags":[
        "consultant",
        "business"
    ],
    "wof:name":"Jayeff Partners",
    "wof:placetype":"venue"
},
  "geometry": {"coordinates":[-79.563377,43.194836],"type":"Point"}
}