{
  "type": "Feature",
  "properties": {
    "addr:full":"75 Perkell Pl Kitchener ON N2B 1J3",
    "addr:housenumber":"75",
    "addr:postcode":"n2b 1j3",
    "addr:street":"Perkell Pl",
    "iso:country":"CA",
    "sg:address":"75 Perkell Pl",
    "sg:city":"Kitchener",
    "sg:classifiers":[
        {
            "category":"Professional",
            "subcategory":"Management & Consulting",
            "type":"Services"
        }
    ],
    "sg:phone":"+1 519 744 6263",
    "sg:postcode":"N2B 1J3",
    "sg:province":"ON",
    "sg:tags":[
        "consultant",
        "business"
    ],
    "wof:name":"Enhanced Performance Systems",
    "wof:placetype":"venue"
},
  "geometry": {"coordinates":[-80.45734400000001,43.457493],"type":"Point"}
}