{
  "type": "Feature",
  "properties": {
    "addr:full":"PO Box 5846 STN L Edmonton AB T6C 4G3",
    "addr:housenumber":"po",
    "addr:postcode":"t6c 4g3",
    "addr:street":"Box 5846 Stn L Edmonton",
    "iso:country":"CA",
    "sg:address":"PO Box 5846 STN L",
    "sg:city":"Edmonton",
    "sg:classifiers":[
        {
            "category":"Travel",
            "subcategory":"Campground",
            "type":"Entertainment"
        }
    ],
    "sg:phone":"+1 780 464 7537",
    "sg:postcode":"T6C 4G3",
    "sg:province":"AB",
    "sg:tags":[
        "camp",
        "fishing"
    ],
    "wof:name":"Andrew Lake Lodge",
    "wof:placetype":"venue"
},
  "geometry": {"coordinates":[-113.49037199999999,53.546219],"type":"Point"}
}