{
  "type": "Feature",
  "properties": {
    "addr:full":"Hobbema AB T0C 1N0",
    "addr:postcode":"t0c 1n0",
    "iso:country":"CA",
    "sg:city":"Hobbema",
    "sg:classifiers":[
        {
            "category":"Food & Beverages",
            "subcategory":"Groceries & Convenience Stores",
            "type":"Retail Goods"
        }
    ],
    "sg:phone":"+1 780 585 3306",
    "sg:postcode":"T0C 1N0",
    "sg:province":"AB",
    "sg:tags":[
        "grocer"
    ],
    "wof:name":"Akamihk Gas Bar & Convenience",
    "wof:placetype":"venue"
},
  "geometry": {"coordinates":[-113.446144,52.834084],"type":"Point"}
}