{
  "type": "Feature",
  "properties": {
    "iso:country":"CA",
    "sg:address":"620 Twelfth St",
    "sg:city":"New Westminster",
    "sg:classifiers":[
        {
            "category":"Restaurant",
            "type":"Food & Drink"
        }
    ],
    "sg:phone":"+1 604 516 6031",
    "sg:postcode":"V3M 4J4",
    "sg:province":"BC",
    "sg:tags":[
        "shop",
        "coffee"
    ],
    "wof:name":"Lety's Cantina Coffee Bar",
    "wof:placetype":"venue"
},
  "geometry": {"coordinates":[-122.931503296,49.2082633972],"type":"Point"}
}