{
  "type": "Feature",
  "properties": {
    "addr:full":"13585 King George Hwy Surrey BC V3T 2V1",
    "addr:housenumber":"13585",
    "addr:postcode":"v3t 2v1",
    "addr:street":"King George Hwy",
    "iso:country":"CA",
    "sg:address":"13585 King George Hwy",
    "sg:city":"Surrey",
    "sg:classifiers":[
        {
            "category":"Health Services",
            "subcategory":"Clinic",
            "type":"Services"
        }
    ],
    "sg:phone":"+1 604 588 3828",
    "sg:postcode":"V3T 2V1",
    "sg:province":"BC",
    "sg:tags":[
        "food",
        "herbalist",
        "diet"
    ],
    "wof:name":"Surrey Natural Foods",
    "wof:placetype":"venue"
},
  "geometry": {"coordinates":[-122.845581,49.199345],"type":"Point"}
}