{
  "type": "Feature",
  "properties": {
    "addr:full":"155 Av Saint-Rene Saint-Rene-DE-Matane QC G0J 3E0",
    "addr:postcode":"g0j 3e0",
    "addr:street":"155 Av Saint-Rene Saint-Rene-De-Matane",
    "iso:country":"CA",
    "sg:address":"155 Av Saint-Rene",
    "sg:city":"Saint-Rene-DE-Matane",
    "sg:classifiers":[
        {
            "category":"Organizations",
            "subcategory":"Religious Organization",
            "type":"Services"
        }
    ],
    "sg:phone":"+1 418 224 3744",
    "sg:postcode":"G0J 3E0",
    "sg:province":"QC",
    "sg:tags":[
        "church"
    ],
    "wof:name":"St-Rene DE Matane Presbytere",
    "wof:placetype":"venue"
},
  "geometry": {"coordinates":[-67.38883209230001,48.7077445984],"type":"Point"}
}