{
  "type": "Feature",
  "properties": {
    "addr:full":"118 West River Rd Hinton AB T7V 1Z1",
    "addr:housenumber":"118",
    "addr:postcode":"t7v 1z1",
    "addr:street":"West River Rd",
    "iso:country":"CA",
    "sg:address":"118 West River Rd",
    "sg:city":"Hinton",
    "sg:classifiers":[
        {
            "category":"Professional",
            "subcategory":"Business Services",
            "type":"Services"
        }
    ],
    "sg:phone":"+1 780 865 7889",
    "sg:postcode":"T7V 1Z1",
    "sg:province":"AB",
    "sg:tags":[
        "steam",
        "cleaning"
    ],
    "wof:name":"Blue Canyon Ltd",
    "wof:placetype":"venue"
},
  "geometry": {"coordinates":[-117.602654,53.400513],"type":"Point"}
}