{
  "type": "Feature",
  "properties": {
    "addr:full":"402 22 Ave Nisku AB T9E 7W8",
    "addr:postcode":"t9e 7w8",
    "addr:street":"402 22 Ave",
    "iso:country":"CA",
    "sg:address":"402 22 Ave",
    "sg:city":"Nisku",
    "sg:classifiers":[
        {
            "category":"Mining & Drilling",
            "type":"Manufacturing & Wholesale Goods"
        }
    ],
    "sg:phone":"+1 780 955 3033",
    "sg:postcode":"T9E 7W8",
    "sg:province":"AB",
    "sg:tags":[
        "field",
        "oil"
    ],
    "wof:name":"Baker Atlas",
    "wof:placetype":"venue"
},
  "geometry": {"coordinates":[-113.53666699999999,53.343155],"type":"Point"}
}