{
  "type": "Feature",
  "properties": {
    "addr:full":"Vernon BC V1T 2E2",
    "addr:postcode":"v1t 2e2",
    "iso:country":"CA",
    "sg:city":"Vernon",
    "sg:classifiers":[
        {
            "category":"Education",
            "subcategory":"College",
            "type":"Public Place"
        }
    ],
    "sg:phone":"+1 250 558 3718",
    "sg:postcode":"V1T 2E2",
    "sg:province":"BC",
    "sg:tags":[
        "academic",
        "school"
    ],
    "wof:name":"Okanagan Valley College-Mass",
    "wof:placetype":"venue"
},
  "geometry": {"coordinates":[-119.277725,50.263638],"type":"Point"}
}