{
  "type": "Feature",
  "properties": {
    "addr:full":"2390 Argentia Rd Mississauga ON L5N 5Z7",
    "addr:housenumber":"2390",
    "addr:postcode":"l5n 5z7",
    "addr:street":"Argentia Rd",
    "iso:country":"CA",
    "sg:address":"2390 Argentia Rd",
    "sg:city":"Mississauga",
    "sg:classifiers":[
        {
            "category":"Professional",
            "type":"Services"
        }
    ],
    "sg:phone":"+1 905 567 4444",
    "sg:postcode":"L5N 5Z7",
    "sg:province":"ON",
    "sg:tags":[
        "establishment",
        "engineer"
    ],
    "wof:name":"Golder Associates",
    "wof:placetype":"venue"
},
  "geometry": {"coordinates":[-79.751991,43.599827],"type":"Point"}
}