{
  "type": "Feature",
  "properties": {
    "addr:full":"104 3rd Ave W Neilburg SK S0M 2C0",
    "addr:housenumber":"104",
    "addr:postcode":"s0m 2c0",
    "addr:street":"3Rd Ave W Neilburg",
    "iso:country":"CA",
    "sg:address":"104 3rd Ave W",
    "sg:city":"Neilburg",
    "sg:classifiers":[
        {
            "category":"Recreation",
            "type":"Entertainment"
        }
    ],
    "sg:phone":"+1 306 823 4224",
    "sg:postcode":"S0M 2C0",
    "sg:province":"SK",
    "sg:tags":[
        "club",
        "curling"
    ],
    "wof:name":"Neilburg Curling Club",
    "wof:placetype":"venue"
},
  "geometry": {"coordinates":[-109.62306213399999,52.8420448303],"type":"Point"}
}