{
  "type": "Feature",
  "properties": {
    "addr:full":"4718 1 St SW Calgary AB T2G 0A2",
    "addr:housenumber":"4718 1",
    "addr:postcode":"t2g 0a2",
    "addr:street":"St Sw",
    "iso:country":"CA",
    "sg:address":"4718 1 St SW",
    "sg:city":"Calgary",
    "sg:classifiers":[
        {
            "category":"Organizations",
            "subcategory":"Non-profit Organization",
            "type":"Services"
        }
    ],
    "sg:phone":"+1 403 287 3397",
    "sg:postcode":"T2G 0A2",
    "sg:province":"AB",
    "sg:tags":[
        "information",
        "alcoholism",
        "treatment"
    ],
    "wof:name":"Al-Anon Literature Distr Ctr",
    "wof:placetype":"venue"
},
  "geometry": {"coordinates":[-114.065117,51.010681],"type":"Point"}
}