{
  "type": "Feature",
  "properties": {
    "iso:country":"CA",
    "sg:city":"Ottawa",
    "sg:classifiers":[
        {
            "category":"Professional",
            "subcategory":"Lawyer & Legal Services",
            "type":"Services"
        }
    ],
    "sg:phone":"+1 613 235 6650",
    "sg:postcode":"K1P 5B5",
    "sg:province":"ON",
    "sg:tags":[
        "attorney"
    ],
    "wof:name":"Champagne, Paul M",
    "wof:placetype":"venue"
},
  "geometry": {"coordinates":[-75.69812774659999,45.4227142334],"type":"Point"}
}