{
  "type": "Feature",
  "properties": {
    "addr:full":"240 Starwood Lane Windsor ON N8N 4X3",
    "addr:housenumber":"240",
    "addr:postcode":"n8n 4x3",
    "addr:street":"Starwood Lane",
    "iso:country":"CA",
    "sg:address":"240 Starwood Lane",
    "sg:city":"Windsor",
    "sg:classifiers":[
        {
            "category":"Professional",
            "subcategory":"Engineering",
            "type":"Services"
        }
    ],
    "sg:phone":"+1 519 979 7759",
    "sg:postcode":"N8N 4X3",
    "sg:province":"ON",
    "sg:tags":[
        "health",
        "occupational",
        "safety",
        "engineer"
    ],
    "wof:name":"M Naqvi & Assoc Inc",
    "wof:placetype":"venue"
},
  "geometry": {"coordinates":[-83.033913,42.317822],"type":"Point"}
}