{
  "type": "Feature",
  "properties": {
    "addr:full":"NW 1-6-22W Elgin MB R0K 0T0",
    "addr:postcode":"1-6-22w;r0k 0t0",
    "addr:street":"Nw",
    "iso:country":"CA",
    "sg:address":"NW 1-6-22W",
    "sg:city":"Elgin",
    "sg:classifiers":[
        {
            "category":"Wholesale",
            "subcategory":"Farm Supplies",
            "type":"Manufacturing & Wholesale Goods"
        }
    ],
    "sg:phone":"+1 204 769 2378",
    "sg:postcode":"R0K 0T0",
    "sg:province":"MB",
    "sg:tags":[
        "livestock"
    ],
    "wof:name":"Cloverleaf Cattle CO",
    "wof:placetype":"venue"
},
  "geometry": {"coordinates":[-100.27074399999999,49.444141],"type":"Point"}
}