{
  "type": "Feature",
  "properties": {
    "addr:full":"8307 Coronet Rd NW Edmonton AB T6E 4N7",
    "addr:housenumber":"8307",
    "addr:postcode":"t6e 4n7",
    "addr:street":"Coronet Rd Nw",
    "iso:country":"CA",
    "sg:address":"8307 Coronet Rd NW",
    "sg:city":"Edmonton",
    "sg:classifiers":[
        {
            "category":"Manufacturing",
            "subcategory":"Metals",
            "type":"Manufacturing & Wholesale Goods"
        }
    ],
    "sg:phone":"+1 780 465 3484",
    "sg:postcode":"T6E 4N7",
    "sg:province":"AB",
    "sg:tags":[
        "steel",
        "stainless"
    ],
    "wof:name":"National Metal Products Ltd",
    "wof:placetype":"venue"
},
  "geometry": {"coordinates":[-113.45287322999999,53.5018157959],"type":"Point"}
}