{
  "type": "Feature",
  "properties": {
    "addr:full":"282 Rue Radisson Trois-Rivieres QC G9A 2C3",
    "addr:housenumber":"282",
    "addr:postcode":"g9a 2c3",
    "addr:street":"Rue Radisson Trois-Rivieres",
    "iso:country":"CA",
    "sg:address":"282 Rue Radisson",
    "sg:city":"Trois-Rivieres",
    "sg:classifiers":[
        {
            "category":"Professional",
            "subcategory":"Lawyer & Legal Services",
            "type":"Services"
        }
    ],
    "sg:phone":"+1 819 376 6811",
    "sg:postcode":"G9A 2C3",
    "sg:province":"QC",
    "sg:tags":[
        "attorney"
    ],
    "wof:name":"Lacoursiere, Jean F",
    "wof:placetype":"venue"
},
  "geometry": {"coordinates":[-72.5411148071,46.3429336548],"type":"Point"}
}