{
  "type": "Feature",
  "properties": {
    "addr:full":"82 Mill St Georgetown ON L7G 2C9",
    "addr:housenumber":"82",
    "addr:postcode":"l7g 2c9",
    "addr:street":"Mill St",
    "iso:country":"CA",
    "sg:address":"82 Mill St",
    "sg:city":"Georgetown",
    "sg:classifiers":[
        {
            "category":"Shopping",
            "subcategory":"Used Merchandise",
            "type":"Retail Goods"
        }
    ],
    "sg:phone":"+1 905 877 8522",
    "sg:postcode":"L7G 2C9",
    "sg:province":"ON",
    "sg:tags":[
        "second",
        "salvage",
        "surplus",
        "store",
        "hand"
    ],
    "wof:name":"Salvation Army Family Thrift",
    "wof:placetype":"venue"
},
  "geometry": {"coordinates":[-79.92543029789999,43.6500473022],"type":"Point"}
}