{
  "type": "Feature",
  "properties": {
    "addr:full":"102 Av Leacock Pointe-Claire QC H9R 1H1",
    "addr:postcode":"h9r 1h1",
    "addr:street":"102 Av Leacock",
    "iso:country":"CA",
    "sg:address":"102 Av Leacock",
    "sg:city":"Pointe-Claire",
    "sg:classifiers":[
        {
            "category":"Wholesale",
            "subcategory":"Machinery & Supplies",
            "type":"Manufacturing & Wholesale Goods"
        }
    ],
    "sg:phone":"+1 514 695 6787",
    "sg:postcode":"H9R 1H1",
    "sg:province":"QC",
    "sg:tags":[
        "equipment",
        "irrigation",
        "system",
        "landscape",
        "contractor"
    ],
    "wof:name":"Landcare Independent Inc",
    "wof:placetype":"venue"
},
  "geometry": {"coordinates":[-73.798034668,45.4707145691],"type":"Point"}
}