{
  "type": "Feature",
  "properties": {
    "addr:full":"223 Branchflower Rd Salmon Arm BC V1E 3C6",
    "addr:housenumber":"223",
    "addr:postcode":"v1e 3c6",
    "addr:street":"Branchflower Rd",
    "iso:country":"CA",
    "sg:address":"223 Branchflower Rd",
    "sg:city":"Salmon Arm",
    "sg:classifiers":[
        {
            "category":"Manufacturing",
            "subcategory":"Lumber",
            "type":"Manufacturing & Wholesale Goods"
        }
    ],
    "sg:phone":"+1 250 832 3282",
    "sg:postcode":"V1E 3C6",
    "sg:province":"BC",
    "sg:tags":[
        "company",
        "logging"
    ],
    "wof:name":"Jackson Contracting Ltd",
    "wof:placetype":"venue"
},
  "geometry": {"coordinates":[-119.271888733,50.7022285461],"type":"Point"}
}