{
  "type": "Feature",
  "properties": {
    "addr:full":"3667 Strawberry Hill St Halifax NS B3K 5A8",
    "addr:housenumber":"3667",
    "addr:postcode":"b3k 5a8",
    "addr:street":"Strawberry Hill St",
    "iso:country":"CA",
    "sg:address":"3667 Strawberry Hill St",
    "sg:city":"Halifax",
    "sg:classifiers":[
        {
            "category":"Home & Garden",
            "subcategory":"Building Materials",
            "type":"Retail Goods"
        }
    ],
    "sg:phone":"+1 902 455 1335",
    "sg:postcode":"B3K 5A8",
    "sg:province":"NS",
    "sg:tags":[
        "paint"
    ],
    "wof:name":"Colorworks Decorating Ctr",
    "wof:placetype":"venue"
},
  "geometry": {"coordinates":[-63.620354,44.662132],"type":"Point"}
}