{
  "type": "Feature",
  "properties": {
    "addr:full":"13 Erie St St Thomas ON N5R 2M4",
    "addr:housenumber":"13",
    "addr:postcode":"n5r 2m4",
    "addr:street":"Erie St",
    "iso:country":"CA",
    "sg:address":"13 Erie St",
    "sg:city":"St Thomas",
    "sg:classifiers":[
        {
            "category":"Building & Trades",
            "subcategory":"Cleaning & Sanitation",
            "type":"Services"
        }
    ],
    "sg:phone":"+1 519 631 0484",
    "sg:postcode":"N5R 2M4",
    "sg:province":"ON",
    "sg:tags":[
        "janitor"
    ],
    "wof:name":"Woolley Maintenance Svc",
    "wof:placetype":"venue"
},
  "geometry": {"coordinates":[-81.187828,42.774204],"type":"Point"}
}