{
  "type": "Feature",
  "properties": {
    "addr:full":"143 Ontario St N Milton ON L9T 2T2",
    "addr:housenumber":"143",
    "addr:postcode":"l9t 2t2",
    "addr:street":"Ontario St N",
    "iso:country":"CA",
    "sg:address":"143 Ontario St N",
    "sg:city":"Milton",
    "sg:classifiers":[
        {
            "category":"Professional",
            "subcategory":"Engineering",
            "type":"Services"
        }
    ],
    "sg:phone":"+1 905 878 1455",
    "sg:postcode":"L9T 2T2",
    "sg:province":"ON",
    "sg:tags":[
        "engineer"
    ],
    "wof:name":"Maitland Spencer Engineering",
    "wof:placetype":"venue"
},
  "geometry": {"coordinates":[-79.881058,43.521255],"type":"Point"}
}