{
  "type": "Feature",
  "properties": {
    "addr:full":"1109 Clarkson Rd Mississauga ON L5J 2W1",
    "addr:housenumber":"1109",
    "addr:postcode":"l5j 2w1",
    "addr:street":"Clarkson Rd",
    "iso:country":"CA",
    "sg:address":"1109 Clarkson Rd",
    "sg:city":"Mississauga",
    "sg:classifiers":[
        {
            "category":"Wholesale",
            "subcategory":"Meat",
            "type":"Manufacturing & Wholesale Goods"
        }
    ],
    "sg:phone":"+1 905 822 1551",
    "sg:postcode":"L5J 2W1",
    "sg:province":"ON",
    "sg:tags":[
        "butchering"
    ],
    "wof:name":"Doug Auld & Son Butchers",
    "wof:placetype":"venue"
},
  "geometry": {"coordinates":[-79.6263122559,43.5195045471],"type":"Point"}
}