{
  "type": "Feature",
  "properties": {
    "addr:full":"401 Rue Racine E Chicoutimi QC G7H 1S8",
    "addr:housenumber":"401",
    "addr:postcode":"g7h 1s8",
    "addr:street":"Rue Racine E",
    "iso:country":"CA",
    "sg:address":"401 Rue Racine E",
    "sg:city":"Chicoutimi",
    "sg:classifiers":[
        {
            "category":"Shopping",
            "subcategory":"Gifts & Souvenirs",
            "type":"Retail Goods"
        }
    ],
    "sg:phone":"+1 418 693 0627",
    "sg:postcode":"G7H 1S8",
    "sg:province":"QC",
    "sg:tags":[
        "shop"
    ],
    "wof:name":"Boutique Maya & Inca",
    "wof:placetype":"venue"
},
  "geometry": {"coordinates":[-71.056168,48.42815],"type":"Point"}
}