{
  "type": "Feature",
  "properties": {
    "addr:full":"Etobicoke ON M9B 6J1",
    "addr:postcode":"m9b 6j1",
    "iso:country":"CA",
    "sg:city":"Etobicoke",
    "sg:classifiers":[
        {
            "category":"Restaurant",
            "type":"Food & Drink"
        }
    ],
    "sg:phone":"+1 416 234 8778",
    "sg:postcode":"M9B 6J1",
    "sg:province":"ON",
    "wof:name":"Subway Sandwiches & Salads",
    "wof:placetype":"venue"
},
  "geometry": {"coordinates":[-79.552605,43.631866],"type":"Point"}
}