{
  "type": "Feature",
  "properties": {
    "addr:full":"195 Douglas Ave Red Deer AB T4R 2G2",
    "addr:housenumber":"195",
    "addr:postcode":"t4r 2g2",
    "addr:street":"Douglas Ave",
    "iso:country":"CA",
    "sg:address":"195 Douglas Ave",
    "sg:city":"Red Deer",
    "sg:classifiers":[
        {
            "category":"Organizations",
            "subcategory":"Religious Organization",
            "type":"Services"
        }
    ],
    "sg:phone":"+1 403 342 5383",
    "sg:postcode":"T4R 2G2",
    "sg:province":"AB",
    "sg:tags":[
        "church"
    ],
    "wof:name":"Red Deer Islamic Ctr",
    "wof:placetype":"venue"
},
  "geometry": {"coordinates":[-113.761635,52.259171],"type":"Point"}
}