{
  "type": "Feature",
  "properties": {
    "addr:full":"2 Walnut St Pine Falls MB R0E 1M0",
    "addr:housenumber":"2",
    "addr:postcode":"r0e 1m0",
    "addr:street":"Walnut St",
    "iso:country":"CA",
    "sg:address":"2 Walnut St",
    "sg:city":"Pine Falls",
    "sg:classifiers":[
        {
            "category":"Education",
            "subcategory":"School",
            "type":"Public Place"
        }
    ],
    "sg:phone":"+1 204 367 2254",
    "sg:postcode":"R0E 1M0",
    "sg:province":"MB",
    "wof:name":"Pine Falls School",
    "wof:placetype":"venue"
},
  "geometry": {"coordinates":[-96.217575,50.567356],"type":"Point"}
}