{
  "type": "Feature",
  "properties": {
    "addr:full":"10 William St #2 Parry Sound ON P2A 1V1",
    "addr:housenumber":"10",
    "addr:postcode":"p2a 1v1",
    "addr:street":"William St # 2",
    "iso:country":"CA",
    "sg:address":"10 William St #2",
    "sg:city":"Parry Sound",
    "sg:classifiers":[
        {
            "category":"Professional",
            "subcategory":"Lawyer & Legal Services",
            "type":"Services"
        }
    ],
    "sg:phone":"+1 705 746 5838",
    "sg:postcode":"P2A 1V1",
    "sg:province":"ON",
    "sg:tags":[
        "attorney"
    ],
    "wof:name":"Thomson, D Andrew",
    "wof:placetype":"venue"
},
  "geometry": {"coordinates":[-80.032669,45.348785],"type":"Point"}
}