{
  "type": "Feature",
  "properties": {
    "iso:country":"CA",
    "sg:address":"Duck Bay Rd",
    "sg:city":"Camperville",
    "sg:classifiers":[
        {
            "category":"Social Services",
            "type":"Services"
        }
    ],
    "sg:phone":"+1 204 524 2128",
    "sg:postcode":"R0L 0J0",
    "sg:province":"MB",
    "sg:tags":[
        "organization",
        "welfare"
    ],
    "wof:name":"West Region Child & Family Svc",
    "wof:placetype":"venue"
},
  "geometry": {"coordinates":[-100.145202637,51.9859199524],"type":"Point"}
}