{
  "type": "Feature",
  "properties": {
    "addr:full":"22 Madison Ave Toronto ON M5R 2S1",
    "addr:housenumber":"22",
    "addr:postcode":"m5r 2s1",
    "addr:street":"Madison Ave",
    "iso:country":"CA",
    "sg:address":"22 Madison Ave",
    "sg:city":"Toronto",
    "sg:classifiers":[
        {
            "category":"Social Services",
            "type":"Services"
        }
    ],
    "sg:phone":"+1 416 923 8450",
    "sg:postcode":"M5R 2S1",
    "sg:province":"ON",
    "sg:tags":[
        "organization",
        "welfare"
    ],
    "wof:name":"Theta Delta Chi",
    "wof:placetype":"venue"
},
  "geometry": {"coordinates":[-79.403267,43.667892],"type":"Point"}
}