{
  "type": "Feature",
  "properties": {
    "addr:full":"Richmond Hill ON L4C 0B1",
    "addr:postcode":"l4c 0b1",
    "iso:country":"CA",
    "sg:city":"Richmond Hill",
    "sg:classifiers":[
        {
            "category":"Social Services",
            "type":"Services"
        }
    ],
    "sg:phone":"+1 905 770 8377",
    "sg:postcode":"L4C 0B1",
    "sg:province":"ON",
    "sg:tags":[
        "housing",
        "assistance"
    ],
    "wof:name":"Genesis Place Support Svc",
    "wof:placetype":"venue"
},
  "geometry": {"coordinates":[-79.437538,43.880608],"type":"Point"}
}