{
  "type": "Feature",
  "properties": {
    "addr:full":"48 Ellen St Barrie ON L4N 3A4",
    "addr:housenumber":"48",
    "addr:postcode":"l4n 3a4",
    "addr:street":"Ellen St",
    "iso:country":"CA",
    "sg:address":"48 Ellen St",
    "sg:city":"Barrie",
    "sg:classifiers":[
        {
            "category":"Manufacturing",
            "subcategory":"Signs",
            "type":"Manufacturing & Wholesale Goods"
        }
    ],
    "sg:phone":"+1 705 728 6666",
    "sg:postcode":"L4N 3A4",
    "sg:province":"ON",
    "wof:name":"Owen Signcraft Ltd",
    "wof:placetype":"venue"
},
  "geometry": {"coordinates":[-79.6923828125,44.3809738159],"type":"Point"}
}