{
  "type": "Feature",
  "properties": {
    "addr:full":"215 Wellington St London ON N6B 2L2",
    "addr:housenumber":"215",
    "addr:postcode":"n6b 2l2",
    "addr:street":"Wellington St",
    "iso:country":"CA",
    "sg:address":"215 Wellington St",
    "sg:city":"London",
    "sg:classifiers":[
        {
            "category":"Education",
            "subcategory":"Special Training",
            "type":"Public Place"
        }
    ],
    "sg:phone":"+1 519 673 4360",
    "sg:postcode":"N6B 2L2",
    "sg:province":"ON",
    "sg:tags":[
        "instruction",
        "driving"
    ],
    "wof:name":"Ontario Driving School",
    "wof:placetype":"venue"
},
  "geometry": {"coordinates":[-81.242546,42.979206],"type":"Point"}
}