{
  "type": "Feature",
  "properties": {
    "addr:full":"206 Rue Heriot Drummondville QC J2C 1J8",
    "addr:housenumber":"206",
    "addr:postcode":"j2c 1j8",
    "addr:street":"Rue Heriot",
    "iso:country":"CA",
    "sg:address":"206 Rue Heriot",
    "sg:city":"Drummondville",
    "sg:classifiers":[
        {
            "category":"Health Services",
            "subcategory":"Optometrist",
            "type":"Services"
        }
    ],
    "sg:phone":"+1 819 472 6921",
    "sg:postcode":"J2C 1J8",
    "sg:province":"QC",
    "wof:name":"Greiche & Scaff",
    "wof:placetype":"venue"
},
  "geometry": {"coordinates":[-72.48931884770001,45.8856086731],"type":"Point"}
}