{
  "type": "Feature",
  "properties": {
    "addr:full":"Uxbridge ON L9P 1R4",
    "addr:postcode":"l9p 1r4",
    "iso:country":"CA",
    "sg:city":"Uxbridge",
    "sg:classifiers":[
        {
            "category":"Building & Trades",
            "subcategory":"Construction",
            "type":"Services"
        }
    ],
    "sg:phone":"+1 905 852 9724",
    "sg:postcode":"L9P 1R4",
    "sg:province":"ON",
    "sg:tags":[
        "product",
        "asphalt"
    ],
    "wof:name":"Miller Paving Ltd",
    "wof:placetype":"venue"
},
  "geometry": {"coordinates":[-79.114906,44.096741],"type":"Point"}
}