{
  "type": "Feature",
  "properties": {
    "addr:full":"315 Kleinsteuber Parks Rd Bloomfield ON K0K 1G0",
    "addr:housenumber":"315",
    "addr:postcode":"k0k 1g0",
    "addr:street":"Kleinsteuber Parks Rd",
    "iso:country":"CA",
    "sg:address":"315 Kleinsteuber Parks Rd",
    "sg:city":"Bloomfield",
    "sg:classifiers":[
        {
            "category":"Professional",
            "subcategory":"Accounting & Tax Preparation",
            "type":"Services"
        }
    ],
    "sg:phone":"+1 613 393 2300",
    "sg:postcode":"K0K 1G0",
    "sg:province":"ON",
    "sg:tags":[
        "accountant"
    ],
    "wof:name":"Moore, Jack",
    "wof:placetype":"venue"
},
  "geometry": {"coordinates":[-77.2341842651,43.985496521],"type":"Point"}
}