{
  "type": "Feature",
  "properties": {
    "addr:full":"785 Ch Fresniere Saint-Eustache QC J7R 4K3",
    "addr:housenumber":"785",
    "addr:postcode":"j7r 4k3",
    "addr:street":"Ch Fresniere",
    "iso:country":"CA",
    "sg:address":"785 Ch Fresniere",
    "sg:city":"Saint-Eustache",
    "sg:classifiers":[
        {
            "category":"Wholesale",
            "subcategory":"Machinery & Supplies",
            "type":"Manufacturing & Wholesale Goods"
        }
    ],
    "sg:phone":"+1 450 473 1470",
    "sg:postcode":"J7R 4K3",
    "sg:province":"QC",
    "sg:tags":[
        "farm",
        "equipment"
    ],
    "wof:name":"Garage Bigras Tracteur Inc",
    "wof:placetype":"venue"
},
  "geometry": {"coordinates":[-73.982178,45.56345],"type":"Point"}
}