{
  "type": "Feature",
  "properties": {
    "addr:full":"1760 Albion Rd Etobicoke ON M9V 1C1",
    "addr:housenumber":"1760",
    "addr:postcode":"m9v 1c1",
    "addr:street":"Albion Rd",
    "iso:country":"CA",
    "sg:address":"1760 Albion Rd",
    "sg:city":"Etobicoke",
    "sg:classifiers":[
        {
            "category":"Retail",
            "subcategory":"Car Wash",
            "type":"Services"
        }
    ],
    "sg:phone":"+1 416 745 0487",
    "sg:postcode":"M9V 1C1",
    "sg:province":"ON",
    "sg:tags":[
        "polishing",
        "washing"
    ],
    "wof:name":"Looney Twooney Coin Car Wash",
    "wof:placetype":"venue"
},
  "geometry": {"coordinates":[-79.603027,43.743626],"type":"Point"}
}