{
  "type": "Feature",
  "properties": {
    "addr:full":"1391 Boul Wallberg Dolbeau-Mistassini QC G8L 1H3",
    "addr:housenumber":"1391",
    "addr:postcode":"g8l 1h3",
    "addr:street":"Boul Wallberg",
    "iso:country":"CA",
    "sg:address":"1391 Boul Wallberg",
    "sg:city":"Dolbeau-Mistassini",
    "sg:classifiers":[
        {
            "category":"Manufacturing",
            "subcategory":"Tools & Machinery",
            "type":"Manufacturing & Wholesale Goods"
        }
    ],
    "sg:phone":"+1 418 276 0531",
    "sg:postcode":"G8L 1H3",
    "sg:province":"QC",
    "sg:tags":[
        "optometrist",
        "optical"
    ],
    "wof:name":"Clinique Visuelle Gaston Rives",
    "wof:placetype":"venue"
},
  "geometry": {"coordinates":[-72.228668,48.87822],"type":"Point"}
}