{
  "type": "Feature",
  "properties": {
    "addr:full":"Rimouski QC G5L 8B3",
    "addr:postcode":"g5l 8b3",
    "iso:country":"CA",
    "sg:city":"Rimouski",
    "sg:classifiers":[
        {
            "category":"Real Estate",
            "subcategory":"Real Estate Operator",
            "type":"Services"
        }
    ],
    "sg:phone":"+1 418 722 7511",
    "sg:postcode":"G5L 8B3",
    "sg:province":"QC",
    "sg:tags":[
        "mall",
        "shopping",
        "center"
    ],
    "wof:name":"Galeries Gp",
    "wof:placetype":"venue"
},
  "geometry": {"coordinates":[-68.51572400000001,48.446293],"type":"Point"}
}