{
  "type": "Feature",
  "properties": {
    "iso:country":"CA",
    "sg:address":"504 Talbot St W",
    "sg:city":"Aylmer",
    "sg:classifiers":[
        {
            "category":"Shopping",
            "subcategory":"Discount & Variety Stores",
            "type":"Retail Goods"
        }
    ],
    "sg:phone":"+1 519 765 1073",
    "sg:postcode":"N5H 2T8",
    "sg:province":"ON",
    "wof:name":"Family Mart 1",
    "wof:placetype":"venue"
},
  "geometry": {"coordinates":[-80.9954452515,42.7731704712],"type":"Point"}
}