{
  "type": "Feature",
  "properties": {
    "addr:full":"2705 County Road 43 Kemptville ON K0G 1J0",
    "addr:housenumber":"2705",
    "addr:postcode":"k0g 1j0",
    "addr:street":"County Road 43",
    "iso:country":"CA",
    "sg:address":"2705 County Road 43",
    "sg:city":"Kemptville",
    "sg:classifiers":[
        {
            "category":"Real Estate",
            "subcategory":"Real Estate Agent",
            "type":"Services"
        }
    ],
    "sg:phone":"+1 613 258 1990",
    "sg:postcode":"K0G 1J0",
    "sg:province":"ON",
    "wof:name":"Royal Le Page Gale Real Estate",
    "wof:placetype":"venue"
},
  "geometry": {"coordinates":[-75.645614624,45.0159187317],"type":"Point"}
}