{
  "type": "Feature",
  "properties": {
    "iso:country":"CA",
    "sg:address":"3598 Av Barclay",
    "sg:city":"Montreal",
    "sg:classifiers":[
        {
            "category":"Personal",
            "subcategory":"Barber",
            "type":"Services"
        }
    ],
    "sg:phone":"+1 514 731 8783",
    "sg:postcode":"H3S 1K4",
    "sg:province":"QC",
    "wof:name":"Barclay Barber Shop",
    "wof:placetype":"venue"
},
  "geometry": {"coordinates":[-73.635033,45.502979],"type":"Point"}
}