{
  "type": "Feature",
  "properties": {
    "addr:full":"3598 Av Barclay Montreal QC H3S 1K4",
    "addr:housenumber":"3598",
    "addr:postcode":"h3s 1k4",
    "addr:street":"Av Barclay",
    "iso:country":"CA",
    "sg:address":"3598 Av Barclay",
    "sg:city":"Montreal",
    "sg:classifiers":[
        {
            "category":"Personal",
            "subcategory":"Barber",
            "type":"Services"
        }
    ],
    "sg:phone":"+1 514 731 8783",
    "sg:postcode":"H3S 1K4",
    "sg:province":"QC",
    "wof:name":"Barclay Barber Shop",
    "wof:placetype":"venue"
},
  "geometry": {"coordinates":[-73.63503300000001,45.502979],"type":"Point"}
}