{
  "type": "Feature",
  "properties": {
    "addr:full":"3425 Boul Dagenais O Laval QC H7P 4V9",
    "addr:housenumber":"3425",
    "addr:postcode":"h7p 4v9",
    "addr:street":"Boul Dagenais O",
    "iso:country":"CA",
    "sg:address":"3425 Boul Dagenais O",
    "sg:city":"Laval",
    "sg:classifiers":[
        {
            "category":"Shopping",
            "subcategory":"Crafts & Fabrics",
            "type":"Retail Goods"
        }
    ],
    "sg:phone":"+1 450 628 0019",
    "sg:postcode":"H7P 4V9",
    "sg:province":"QC",
    "sg:tags":[
        "shop"
    ],
    "wof:name":"Textiles Hajaly Inc",
    "wof:placetype":"venue"
},
  "geometry": {"coordinates":[-73.8082809448,45.578338623],"type":"Point"}
}