{
  "type": "Feature",
  "properties": {
    "addr:full":"Westlock AB T7P 2P4",
    "addr:postcode":"t7p 2p4",
    "iso:country":"CA",
    "sg:city":"Westlock",
    "sg:classifiers":[
        {
            "category":"Building & Trades",
            "subcategory":"Landscaping Services",
            "type":"Services"
        }
    ],
    "sg:phone":"+1 780 349 2525",
    "sg:postcode":"T7P 2P4",
    "sg:province":"AB",
    "sg:tags":[
        "landscape",
        "contractor"
    ],
    "wof:name":"Pro Hort Svc",
    "wof:placetype":"venue"
},
  "geometry": {"coordinates":[-113.860031128,54.1554450989],"type":"Point"}
}