{
  "type": "Feature",
  "properties": {
    "addr:full":"12720 111 Ave NW Edmonton AB T5M 3X3",
    "addr:housenumber":"12720",
    "addr:postcode":"t5m 3x3",
    "addr:street":"111 Ave Nw",
    "iso:country":"CA",
    "sg:address":"12720 111 Ave NW",
    "sg:city":"Edmonton",
    "sg:classifiers":[
        {
            "category":"Real Estate",
            "subcategory":"Real Estate Operator",
            "type":"Services"
        }
    ],
    "sg:phone":"+1 780 452 4444",
    "sg:postcode":"T5M 3X3",
    "sg:province":"AB",
    "sg:tags":[
        "senior",
        "apartment",
        "housing",
        "citizen"
    ],
    "wof:name":"St Andrew's Ctr",
    "wof:placetype":"venue"
},
  "geometry": {"coordinates":[-113.542198181,53.5590057373],"type":"Point"}
}