{
  "type": "Feature",
  "properties": {
    "addr:full":"Nipawin SK S0E 1E0",
    "addr:postcode":"s0e 1e0",
    "iso:country":"CA",
    "sg:city":"Nipawin",
    "sg:classifiers":[
        {
            "category":"Banks & Credit Unions",
            "subcategory":"Investment Brokerage",
            "type":"Services"
        }
    ],
    "sg:phone":"+1 306 862 8162",
    "sg:postcode":"S0E 1E0",
    "sg:province":"SK",
    "wof:name":"Credential Securities Inc",
    "wof:placetype":"venue"
},
  "geometry": {"coordinates":[-104.026283264,53.3567390442],"type":"Point"}
}