{
  "type": "Feature",
  "properties": {
    "addr:full":"Edmonton AB T5E 6C2",
    "addr:postcode":"t5e 6c2",
    "iso:country":"CA",
    "sg:city":"Edmonton",
    "sg:classifiers":[
        {
            "category":"Government",
            "subcategory":"Post Office",
            "type":"Public Place"
        }
    ],
    "sg:phone":"+1 780 476 0422",
    "sg:postcode":"T5E 6C2",
    "sg:province":"AB",
    "sg:tags":[
        "confectionery",
        "candy"
    ],
    "wof:name":"Candy Inc",
    "wof:placetype":"venue"
},
  "geometry": {"coordinates":[-113.485596,53.599724],"type":"Point"}
}