{
  "type": "Feature",
  "properties": {
    "addr:full":"3611 Roblin Blvd Winnipeg MB R3R 0C6",
    "addr:housenumber":"3611",
    "addr:postcode":"r3r 0c6",
    "addr:street":"Roblin Blvd",
    "iso:country":"CA",
    "sg:address":"3611 Roblin Blvd",
    "sg:city":"Winnipeg",
    "sg:classifiers":[
        {
            "category":"Building & Trades",
            "subcategory":"Construction",
            "type":"Services"
        }
    ],
    "sg:phone":"+1 204 889 0674",
    "sg:postcode":"R3R 0C6",
    "sg:province":"MB",
    "sg:tags":[
        "home",
        "builder"
    ],
    "wof:name":"Southport Construction",
    "wof:placetype":"venue"
},
  "geometry": {"coordinates":[-97.259567,49.868565],"type":"Point"}
}