{
  "type": "Feature",
  "properties": {
    "addr:full":"5960 Fraser St Vancouver BC V5W 2Z7",
    "addr:housenumber":"5960",
    "addr:postcode":"v5w 2z7",
    "addr:street":"Fraser St",
    "iso:country":"CA",
    "sg:address":"5960 Fraser St",
    "sg:city":"Vancouver",
    "sg:classifiers":[
        {
            "category":"Shopping",
            "subcategory":"Pharmacy",
            "type":"Retail Goods"
        }
    ],
    "sg:phone":"+1 604 323 1268",
    "sg:postcode":"V5W 2Z7",
    "sg:province":"BC",
    "wof:name":"Vicon Medic Pharmacy",
    "wof:placetype":"venue"
},
  "geometry": {"coordinates":[-123.09036254900001,49.2303390503],"type":"Point"}
}