{
  "type": "Feature",
  "properties": {
    "iso:country":"CA",
    "sg:address":"25 Maywood Ave",
    "sg:city":"St Catharines",
    "sg:classifiers":[
        {
            "category":"Shopping",
            "subcategory":"Bicycles & Sporting Goods",
            "type":"Retail Goods"
        }
    ],
    "sg:phone":"+1 905 685 7775",
    "sg:postcode":"L2R 1C5",
    "sg:province":"ON",
    "sg:tags":[
        "equipment",
        "exercise"
    ],
    "wof:name":"Niagara Fitness",
    "wof:placetype":"venue"
},
  "geometry": {"coordinates":[-79.262634,43.178871],"type":"Point"}
}