{
  "type": "Feature",
  "properties": {
    "addr:full":"25 Maywood Ave St Catharines ON L2R 1C5",
    "addr:housenumber":"25",
    "addr:postcode":"l2r 1c5",
    "addr:street":"Maywood Ave",
    "iso:country":"CA",
    "sg:address":"25 Maywood Ave",
    "sg:city":"St Catharines",
    "sg:classifiers":[
        {
            "category":"Shopping",
            "subcategory":"Bicycles & Sporting Goods",
            "type":"Retail Goods"
        }
    ],
    "sg:phone":"+1 905 685 7775",
    "sg:postcode":"L2R 1C5",
    "sg:province":"ON",
    "sg:tags":[
        "equipment",
        "exercise"
    ],
    "wof:name":"Niagara Fitness",
    "wof:placetype":"venue"
},
  "geometry": {"coordinates":[-79.26263400000001,43.178871],"type":"Point"}
}