{
  "type": "Feature",
  "properties": {
    "addr:full":"Port Coquitlam BC V3C 6P6",
    "addr:postcode":"v3c 6p6",
    "iso:country":"CA",
    "sg:city":"Port Coquitlam",
    "sg:classifiers":[
        {
            "category":"Wholesale",
            "subcategory":"Hardware",
            "type":"Manufacturing & Wholesale Goods"
        }
    ],
    "sg:phone":"+1 604 941 4411",
    "sg:postcode":"V3C 6P6",
    "sg:province":"BC",
    "sg:tags":[
        "plumbing",
        "fixture",
        "supply"
    ],
    "wof:name":"Aquabrass West Inc",
    "wof:placetype":"venue"
},
  "geometry": {"coordinates":[-122.76252700000001,49.242783],"type":"Point"}
}