{
  "type": "Feature",
  "properties": {
    "iso:country":"CA",
    "sg:address":"329 Centennial Dr S",
    "sg:city":"Martensville",
    "sg:classifiers":[
        {
            "category":"Autos & Motor Vehicles",
            "subcategory":"Fuel & Gas Station",
            "type":"Retail Goods"
        }
    ],
    "sg:phone":"+1 306 242 4020",
    "sg:postcode":"S0K 2T0",
    "sg:province":"SK",
    "sg:tags":[
        "oil"
    ],
    "wof:name":"Martensville Shell",
    "wof:placetype":"venue"
},
  "geometry": {"coordinates":[-106.67024231000001,52.2814712524],"type":"Point"}
}