{
  "type": "Feature",
  "properties": {
    "iso:country":"CA",
    "sg:address":"4100 Rue Jarry E",
    "sg:city":"Montreal",
    "sg:classifiers":[
        {
            "category":"Home & Garden",
            "subcategory":"Building Materials",
            "type":"Retail Goods"
        }
    ],
    "sg:phone":"+1 514 376 2666",
    "sg:postcode":"H1Z 2H3",
    "sg:province":"QC",
    "sg:tags":[
        "glass",
        "window",
        "plate"
    ],
    "wof:name":"Vitro Plus Pie-Ix",
    "wof:placetype":"venue"
},
  "geometry": {"coordinates":[-73.60247039790001,45.5716018677],"type":"Point"}
}