{
  "type": "Feature",
  "properties": {
    "addr:full":"131 Rte 235 Ange-Gardien QC J0E 1E0",
    "addr:housenumber":"131",
    "addr:postcode":"j0e 1e0",
    "addr:street":"Rte 235 Ange-Gardien",
    "iso:country":"CA",
    "sg:address":"131 Rte 235",
    "sg:city":"Ange-Gardien",
    "sg:classifiers":[
        {
            "category":"Wholesale",
            "subcategory":"Farm Supplies",
            "type":"Manufacturing & Wholesale Goods"
        }
    ],
    "sg:phone":"+1 450 293 8161",
    "sg:postcode":"J0E 1E0",
    "sg:province":"QC",
    "sg:tags":[
        "grain"
    ],
    "wof:name":"Meunerie Cote-Paquette Inc",
    "wof:placetype":"venue"
},
  "geometry": {"coordinates":[-72.9358825684,45.3596801758],"type":"Point"}
}