{
  "type": "Feature",
  "properties": {
    "addr:full":"116 Timberlane Dr Brampton ON L6Y 4V7",
    "addr:housenumber":"116",
    "addr:postcode":"l6y 4v7",
    "addr:street":"Timberlane Dr",
    "iso:country":"CA",
    "sg:address":"116 Timberlane Dr",
    "sg:city":"Brampton",
    "sg:classifiers":[
        {
            "category":"Building & Trades",
            "subcategory":"Construction",
            "type":"Services"
        }
    ],
    "sg:phone":"+1 905 796 0707",
    "sg:postcode":"L6Y 4V7",
    "sg:province":"ON",
    "sg:tags":[
        "tile",
        "dealer"
    ],
    "wof:name":"Virsa Tile Installation",
    "wof:placetype":"venue"
},
  "geometry": {"coordinates":[-79.7296295166,43.6468734741],"type":"Point"}
}