{
  "type": "Feature",
  "properties": {
    "addr:full":"2880 Boul Saint-Charles Kirkland QC H9H 3B6",
    "addr:housenumber":"2880",
    "addr:postcode":"h9h 3b6",
    "addr:street":"Boul Saint-Charles",
    "iso:country":"CA",
    "sg:address":"2880 Boul Saint-Charles",
    "sg:city":"Kirkland",
    "sg:classifiers":[
        {
            "category":"Cinema",
            "subcategory":"Movie Rental",
            "type":"Entertainment"
        }
    ],
    "sg:phone":"+1 514 426 4282",
    "sg:postcode":"H9H 3B6",
    "sg:province":"QC",
    "sg:tags":[
        "leasing",
        "video",
        "disc",
        "tape"
    ],
    "wof:name":"Blockbuster Video",
    "wof:placetype":"venue"
},
  "geometry": {"coordinates":[-73.853775,45.447105],"type":"Point"}
}