{
  "type": "Feature",
  "properties": {
    "addr:full":"2530 Ouellette Ave Windsor ON N8X 1L7",
    "addr:housenumber":"2530",
    "addr:postcode":"n8x 1l7",
    "addr:street":"Ouellette Ave",
    "iso:country":"CA",
    "sg:address":"2530 Ouellette Ave",
    "sg:city":"Windsor",
    "sg:classifiers":[
        {
            "category":"Travel",
            "subcategory":"Hotels & Motels",
            "type":"Entertainment"
        }
    ],
    "sg:phone":"+1 519 966 1860",
    "sg:postcode":"N8X 1L7",
    "sg:province":"ON",
    "wof:name":"Marquis Plaza Hotel",
    "wof:placetype":"venue"
},
  "geometry": {"coordinates":[-83.0197067261,42.2878417969],"type":"Point"}
}