{
  "type": "Feature",
  "properties": {
    "addr:full":"398 Daly St N Winnipeg MB R3L 2K6",
    "addr:housenumber":"398",
    "addr:postcode":"r3l 2k6",
    "addr:street":"Daly St N",
    "iso:country":"CA",
    "sg:address":"398 Daly St N",
    "sg:city":"Winnipeg",
    "sg:classifiers":[
        {
            "category":"Manufacturing",
            "subcategory":"Signs",
            "type":"Manufacturing & Wholesale Goods"
        }
    ],
    "sg:phone":"+1 204 452 6168",
    "sg:postcode":"R3L 2K6",
    "sg:province":"MB",
    "wof:name":"Electra Sign",
    "wof:placetype":"venue"
},
  "geometry": {"coordinates":[-97.14490499999999,49.868053],"type":"Point"}
}