{
  "type": "Feature",
  "properties": {
    "addr:full":"286 Harbour St Kincardine ON N2Z 2X9",
    "addr:housenumber":"286",
    "addr:postcode":"n2z 2x9",
    "addr:street":"Harbour St",
    "iso:country":"CA",
    "sg:address":"286 Harbour St",
    "sg:city":"Kincardine",
    "sg:classifiers":[
        {
            "category":"Food & Beverages",
            "subcategory":"Groceries & Convenience Stores",
            "type":"Retail Goods"
        }
    ],
    "sg:phone":"+1 519 396 8442",
    "sg:postcode":"N2Z 2X9",
    "sg:province":"ON",
    "sg:tags":[
        "grocer"
    ],
    "wof:name":"Scoop & Save",
    "wof:placetype":"venue"
},
  "geometry": {"coordinates":[-81.636253,44.176685],"type":"Point"}
}