{
  "type": "Feature",
  "properties": {
    "addr:full":"Vanier QC G1M 3K8",
    "addr:postcode":"g1m 3k8",
    "iso:country":"CA",
    "sg:city":"Vanier",
    "sg:classifiers":[
        {
            "category":"Wholesale",
            "subcategory":"Machinery & Supplies",
            "type":"Manufacturing & Wholesale Goods"
        }
    ],
    "sg:phone":"+1 418 686 3082",
    "sg:postcode":"G1M 3K8",
    "sg:province":"QC",
    "sg:tags":[
        "bearing"
    ],
    "wof:name":"Reseau Cb Groupe Gestion Info",
    "wof:placetype":"venue"
},
  "geometry": {"coordinates":[-71.273453,46.825909],"type":"Point"}
}