{
  "type": "Feature",
  "properties": {
    "addr:full":"Burns Lake BC V0J 1E0",
    "addr:postcode":"bc v0j 1e0",
    "addr:street":"Burns Lake",
    "iso:country":"CA",
    "sg:city":"Burns Lake",
    "sg:classifiers":[
        {
            "category":"Bars & Pubs",
            "type":"Food & Drink"
        }
    ],
    "sg:phone":"+1 250 692 3078",
    "sg:postcode":"V0J 1E0",
    "sg:province":"BC",
    "wof:name":"Mulvaney's Pub",
    "wof:placetype":"venue"
},
  "geometry": {"coordinates":[-125.758537292,54.2266998291],"type":"Point"}
}