{
  "type": "Feature",
  "properties": {
    "addr:full":"108 King St Shelburne NS B0T 1W0",
    "addr:housenumber":"108",
    "addr:postcode":"b0t 1w0",
    "addr:street":"King St",
    "iso:country":"CA",
    "sg:address":"108 King St",
    "sg:city":"Shelburne",
    "sg:classifiers":[
        {
            "category":"Building & Trades",
            "subcategory":"Construction",
            "type":"Services"
        }
    ],
    "sg:phone":"+1 902 875 2758",
    "sg:postcode":"B0T 1W0",
    "sg:province":"NS",
    "sg:tags":[
        "excavating",
        "contractor",
        "general"
    ],
    "wof:name":"Harlow Construction Ltd",
    "wof:placetype":"venue"
},
  "geometry": {"coordinates":[-65.31564299999999,43.765659],"type":"Point"}
}