{
  "type": "Feature",
  "properties": {
    "iso:country":"CA",
    "sg:address":"4290 Padgett Rd",
    "sg:city":"Powell River",
    "sg:classifiers":[
        {
            "category":"Home & Garden",
            "subcategory":"Hardware",
            "type":"Retail Goods"
        }
    ],
    "sg:phone":"+1 604 485 9744",
    "sg:postcode":"V8A 4Z2",
    "sg:province":"BC",
    "wof:name":"Valley Building Supplies",
    "wof:placetype":"venue"
},
  "geometry": {"coordinates":[-124.491096497,49.8338623047],"type":"Point"}
}