{
  "type": "Feature",
  "properties": {
    "iso:country":"CA",
    "sg:address":"11277 Boul Lacordaire",
    "sg:city":"Montreal-Nord",
    "sg:classifiers":[
        {
            "category":"Shopping",
            "subcategory":"Gifts & Souvenirs",
            "type":"Retail Goods"
        }
    ],
    "sg:phone":"+1 514 327 1113",
    "sg:postcode":"H1G 4J7",
    "sg:province":"QC",
    "sg:tags":[
        "party",
        "supply",
        "drapery",
        "curtain"
    ],
    "wof:name":"Bou Clair Inc",
    "wof:placetype":"venue"
},
  "geometry": {"coordinates":[-73.618812561,45.6059761047],"type":"Point"}
}