{
  "type": "Feature",
  "properties": {
    "addr:full":"760 Carrier St Kamloops BC V2H 1G2",
    "addr:housenumber":"760",
    "addr:postcode":"bc v2h 1g2",
    "addr:street":"Carrier St",
    "iso:country":"CA",
    "sg:address":"760 Carrier St",
    "sg:city":"Kamloops",
    "sg:classifiers":[
        {
            "category":"Freight",
            "type":"Transportation"
        }
    ],
    "sg:phone":"+1 250 374 0084",
    "sg:postcode":"V2H 1G2",
    "sg:province":"BC",
    "sg:tags":[
        "trucking"
    ],
    "wof:name":"Robo Transport BC Ltd",
    "wof:placetype":"venue"
},
  "geometry": {"coordinates":[-120.317215,50.685303],"type":"Point"}
}