{
  "type": "Feature",
  "properties": {
    "iso:country":"CA",
    "sg:address":"1656 St Clair Ave W",
    "sg:city":"Toronto",
    "sg:classifiers":[
        {
            "category":"Food & Beverages",
            "subcategory":"Bakery",
            "type":"Retail Goods"
        }
    ],
    "sg:phone":"+1 416 656 2444",
    "sg:postcode":"M6N 1H8",
    "sg:province":"ON",
    "sg:tags":[
        "baker"
    ],
    "wof:name":"St Clair Bakery",
    "wof:placetype":"venue"
},
  "geometry": {"coordinates":[-79.4576034546,43.6748008728],"type":"Point"}
}