{
  "type": "Feature",
  "properties": {
    "addr:full":"Vancouver BC V6B 2L3",
    "addr:postcode":"v6b 2l3",
    "iso:country":"CA",
    "sg:city":"Vancouver",
    "sg:classifiers":[
        {
            "category":"Professional",
            "subcategory":"Management & Consulting",
            "type":"Services"
        }
    ],
    "sg:phone":"+1 604 669 4310",
    "sg:postcode":"V6B 2L3",
    "sg:province":"BC",
    "sg:tags":[
        "communications",
        "consultant",
        "computer",
        "software"
    ],
    "wof:name":"S-Matrix Enterprises Inc",
    "wof:placetype":"venue"
},
  "geometry": {"coordinates":[-123.109397888,49.280544281],"type":"Point"}
}