{
  "type": "Feature",
  "properties": {
    "addr:full":"221 Tundra Dr Fort Mcmurray AB T9H 4Z7",
    "addr:housenumber":"221",
    "addr:postcode":"t9h 4z7",
    "addr:street":"Tundra Dr",
    "iso:country":"CA",
    "sg:address":"221 Tundra Dr",
    "sg:city":"Fort Mcmurray",
    "sg:classifiers":[
        {
            "category":"Social Services",
            "subcategory":"Child Care",
            "type":"Services"
        }
    ],
    "sg:phone":"+1 780 790 9622",
    "sg:postcode":"T9H 4Z7",
    "sg:province":"AB",
    "sg:tags":[
        "association"
    ],
    "wof:name":"Ymca",
    "wof:placetype":"venue"
},
  "geometry": {"coordinates":[-111.455932617,56.7292060852],"type":"Point"}
}