{
  "type": "Feature",
  "properties": {
    "iso:country":"CA",
    "sg:address":"2555 Av Du Havre-Des-Iles",
    "sg:city":"Laval",
    "sg:classifiers":[
        {
            "category":"Food & Beverages",
            "subcategory":"Groceries & Convenience Stores",
            "type":"Retail Goods"
        }
    ],
    "sg:phone":"+1 450 681 9042",
    "sg:postcode":"H7W 4R4",
    "sg:province":"QC",
    "sg:tags":[
        "grocer"
    ],
    "wof:name":"Depanneur Gm Enr",
    "wof:placetype":"venue"
},
  "geometry": {"coordinates":[-73.755463,45.522945],"type":"Point"}
}