{
  "type": "Feature",
  "properties": {
    "addr:full":"2555 Av Du Havre-Des-Iles Laval QC H7W 4R4",
    "addr:housenumber":"2555",
    "addr:postcode":"h7w 4r4",
    "addr:street":"Av Du Havre-Des-Iles",
    "iso:country":"CA",
    "sg:address":"2555 Av Du Havre-Des-Iles",
    "sg:city":"Laval",
    "sg:classifiers":[
        {
            "category":"Food & Beverages",
            "subcategory":"Groceries & Convenience Stores",
            "type":"Retail Goods"
        }
    ],
    "sg:phone":"+1 450 681 9042",
    "sg:postcode":"H7W 4R4",
    "sg:province":"QC",
    "sg:tags":[
        "grocer"
    ],
    "wof:name":"Depanneur Gm Enr",
    "wof:placetype":"venue"
},
  "geometry": {"coordinates":[-73.75546300000001,45.522945],"type":"Point"}
}