{
  "type": "Feature",
  "properties": {
    "iso:country":"CA",
    "sg:city":"Cambridge",
    "sg:classifiers":[
        {
            "category":"Freight",
            "type":"Transportation"
        }
    ],
    "sg:phone":"+1 519 620 4440",
    "sg:postcode":"N1R 6J9",
    "sg:province":"ON",
    "sg:tags":[
        "consultant"
    ],
    "wof:name":"Triangle Traffic Svc",
    "wof:placetype":"venue"
},
  "geometry": {"coordinates":[-80.3210678101,43.3959350586],"type":"Point"}
}