{
  "type": "Feature",
  "properties": {
    "addr:full":"5962 Main St Niagara Falls ON L2G 5Z8",
    "addr:housenumber":"5962",
    "addr:postcode":"l2g 5z8",
    "addr:street":"Main St",
    "iso:country":"CA",
    "sg:address":"5962 Main St",
    "sg:city":"Niagara Falls",
    "sg:classifiers":[
        {
            "category":"Shopping",
            "subcategory":"Clothing, Apparel, & Fashions",
            "type":"Retail Goods"
        }
    ],
    "sg:phone":"+1 905 354 5226",
    "sg:postcode":"L2G 5Z8",
    "sg:province":"ON",
    "sg:tags":[
        "tailor"
    ],
    "wof:name":"Betty's Dressmaking & Altrtns",
    "wof:placetype":"venue"
},
  "geometry": {"coordinates":[-79.092125,43.088352],"type":"Point"}
}