{
  "type": "Feature",
  "properties": {
    "addr:full":"252 1E Av Portneuf QC G0A 2Y0",
    "addr:housenumber":"252",
    "addr:postcode":"g0a 2y0",
    "addr:street":"1E Av",
    "iso:country":"CA",
    "sg:address":"252 1E Av",
    "sg:city":"Portneuf",
    "sg:classifiers":[
        {
            "category":"Health Services",
            "subcategory":"Doctor",
            "type":"Services"
        }
    ],
    "sg:phone":"+1 418 286 4433",
    "sg:postcode":"G0A 2Y0",
    "sg:province":"QC",
    "sg:tags":[
        "dentist"
    ],
    "wof:name":"Clinique Dentaire Gagnon",
    "wof:placetype":"venue"
},
  "geometry": {"coordinates":[-71.8873596191,46.6920051575],"type":"Point"}
}