{
  "type": "Feature",
  "properties": {
    "addr:full":"5132 50th St Chetwynd BC V0C 1J0",
    "addr:housenumber":"5132",
    "addr:postcode":"bc v0c 1j0",
    "addr:street":"50Th St",
    "iso:country":"CA",
    "sg:address":"5132 50th St",
    "sg:city":"Chetwynd",
    "sg:classifiers":[
        {
            "category":"Education",
            "subcategory":"College",
            "type":"Public Place"
        }
    ],
    "sg:phone":"+1 250 788 2248",
    "sg:postcode":"V0C 1J0",
    "sg:province":"BC",
    "sg:tags":[
        "academic",
        "school"
    ],
    "wof:name":"Northern Lights College",
    "wof:placetype":"venue"
},
  "geometry": {"coordinates":[-121.629859924,55.6987075806],"type":"Point"}
}