{
  "type": "Feature",
  "properties": {
    "addr:full":"Mont-Saint-Hilaire QC J3H 4X9",
    "addr:postcode":"j3h 4x9",
    "iso:country":"CA",
    "sg:city":"Mont-Saint-Hilaire",
    "sg:classifiers":[
        {
            "category":"Restaurant",
            "type":"Food & Drink"
        }
    ],
    "sg:phone":"+1 450 467 0457",
    "sg:postcode":"J3H 4X9",
    "sg:province":"QC",
    "wof:name":"Restaurant L'Etoile-MT-St-Hlre",
    "wof:placetype":"venue"
},
  "geometry": {"coordinates":[-73.176041,45.572197],"type":"Point"}
}