{
  "type": "Feature",
  "properties": {
    "addr:full":"1 Paget Rd Scarborough ON M1R 4G6",
    "addr:housenumber":"1",
    "addr:postcode":"m1r 4g6",
    "addr:street":"Paget Rd",
    "iso:country":"CA",
    "sg:address":"1 Paget Rd",
    "sg:city":"Scarborough",
    "sg:classifiers":[
        {
            "category":"Manufacturing",
            "subcategory":"Tools & Machinery",
            "type":"Manufacturing & Wholesale Goods"
        }
    ],
    "sg:phone":"+1 416 289 6653",
    "sg:postcode":"M1R 4G6",
    "sg:province":"ON",
    "sg:tags":[
        "mold"
    ],
    "wof:name":"Unique Mould Makers Ltd",
    "wof:placetype":"venue"
},
  "geometry": {"coordinates":[-79.315826,43.759888],"type":"Point"}
}