{
  "type": "Feature",
  "properties": {
    "addr:full":"15 Rue Du Moulin Saint-Basile-Le-Grand QC J3N 1A1",
    "addr:housenumber":"15",
    "addr:postcode":"j3n 1a1",
    "addr:street":"Rue Du Moulin",
    "iso:country":"CA",
    "sg:address":"15 Rue Du Moulin",
    "sg:city":"Saint-Basile-Le-Grand",
    "sg:classifiers":[
        {
            "category":"Building & Trades",
            "subcategory":"Construction",
            "type":"Services"
        }
    ],
    "sg:phone":"+1 450 441 1162",
    "sg:postcode":"J3N 1A1",
    "sg:province":"QC",
    "sg:tags":[
        "contractor"
    ],
    "wof:name":"Mithoteck Enr",
    "wof:placetype":"venue"
},
  "geometry": {"coordinates":[-73.270782,45.534962],"type":"Point"}
}