{
  "type": "Feature",
  "properties": {
    "addr:full":"242 Rue Ouimet Saint-Jerome QC J7Z 1R7",
    "addr:housenumber":"242",
    "addr:postcode":"j7z 1r7",
    "addr:street":"Rue Ouimet Saint-Jerome",
    "iso:country":"CA",
    "sg:address":"242 Rue Ouimet",
    "sg:city":"Saint-Jerome",
    "sg:classifiers":[
        {
            "category":"Home & Garden",
            "subcategory":"Garden Supply",
            "type":"Retail Goods"
        }
    ],
    "sg:phone":"+1 450 438 6347",
    "sg:postcode":"J7Z 1R7",
    "sg:province":"QC",
    "sg:tags":[
        "lawn",
        "mower"
    ],
    "wof:name":"Gaby Deslauriers Inc",
    "wof:placetype":"venue"
},
  "geometry": {"coordinates":[-74.00198399999999,45.782139],"type":"Point"}
}