{
  "type": "Feature",
  "properties": {
    "addr:full":"1002 Victoria Ave Saskatoon SK S7N 0Z8",
    "addr:housenumber":"1002",
    "addr:postcode":"s7n 0z8",
    "addr:street":"Victoria Ave",
    "iso:country":"CA",
    "sg:address":"1002 Victoria Ave",
    "sg:city":"Saskatoon",
    "sg:classifiers":[
        {
            "category":"Organizations",
            "subcategory":"Religious Organization",
            "type":"Services"
        }
    ],
    "sg:phone":"+1 306 653 0661",
    "sg:postcode":"S7N 0Z8",
    "sg:province":"SK",
    "sg:tags":[
        "church"
    ],
    "wof:name":"Seventh-Day Adventist Church",
    "wof:placetype":"venue"
},
  "geometry": {"coordinates":[-106.66246032700001,52.1155662537],"type":"Point"}
}