{
  "type": "Feature",
  "properties": {
    "iso:country":"CA",
    "sg:address":"6400 Beausejour Dr",
    "sg:city":"Orleans",
    "sg:classifiers":[
        {
            "category":"Education",
            "subcategory":"School",
            "type":"Public Place"
        }
    ],
    "sg:phone":"+1 613 830 2454",
    "sg:postcode":"K1C 4W2",
    "sg:province":"ON",
    "wof:name":"Blessed Kateri Tekakwitha",
    "wof:placetype":"venue"
},
  "geometry": {"coordinates":[-75.524475,45.458778],"type":"Point"}
}