{
  "type": "Feature",
  "properties": {
    "iso:country":"CA",
    "sg:address":"4058 Edgevalley Landng NW",
    "sg:city":"Calgary",
    "sg:classifiers":[
        {
            "category":"Shopping",
            "type":"Retail Goods"
        }
    ],
    "sg:phone":"+1 403 239 1955",
    "sg:postcode":"T3A 5H5",
    "sg:province":"AB",
    "sg:tags":[
        "picture",
        "frame"
    ],
    "wof:name":"Time Frames Custom Picture",
    "wof:placetype":"venue"
},
  "geometry": {"coordinates":[-114.146492,51.133053],"type":"Point"}
}