{
  "type": "Feature",
  "properties": {
    "addr:full":"4058 Edgevalley Landng NW Calgary AB T3A 5H5",
    "addr:postcode":"4058;t3a 5h5",
    "addr:street":"Landng Nw",
    "iso:country":"CA",
    "sg:address":"4058 Edgevalley Landng NW",
    "sg:city":"Calgary",
    "sg:classifiers":[
        {
            "category":"Shopping",
            "type":"Retail Goods"
        }
    ],
    "sg:phone":"+1 403 239 1955",
    "sg:postcode":"T3A 5H5",
    "sg:province":"AB",
    "sg:tags":[
        "picture",
        "frame"
    ],
    "wof:name":"Time Frames Custom Picture",
    "wof:placetype":"venue"
},
  "geometry": {"coordinates":[-114.14649199999999,51.133053],"type":"Point"}
}