{
  "type": "Feature",
  "properties": {
    "addr:full":"171 St. Peters Rd Charlottetown PE C1A 5P6",
    "addr:housenumber":"171",
    "addr:postcode":"c1a 5p6",
    "addr:street":"St. Peters Rd",
    "iso:country":"CA",
    "sg:address":"171 St. Peters Rd",
    "sg:city":"Charlottetown",
    "sg:classifiers":[
        {
            "category":"Shopping",
            "subcategory":"Stationery & Office Supplies",
            "type":"Retail Goods"
        }
    ],
    "sg:phone":"+1 902 628 8640",
    "sg:postcode":"C1A 5P6",
    "sg:province":"PE",
    "sg:tags":[
        "album",
        "scrapbook",
        "shop"
    ],
    "wof:name":"Buy Rite",
    "wof:placetype":"venue"
},
  "geometry": {"coordinates":[-63.118568,46.261711],"type":"Point"}
}