{
  "type": "Feature",
  "properties": {
    "iso:country":"CA",
    "sg:address":"1237 Mccreary Rd",
    "sg:city":"Winnipeg",
    "sg:classifiers":[
        {
            "category":"Recreation",
            "type":"Entertainment"
        }
    ],
    "sg:phone":"+1 204 895 0805",
    "sg:postcode":"R3P 0M6",
    "sg:province":"MB",
    "sg:tags":[
        "riding",
        "academy"
    ],
    "wof:name":"Teske's Equestrian Ctr",
    "wof:placetype":"venue"
},
  "geometry": {"coordinates":[-97.2317199707,49.8415336609],"type":"Point"}
}