{
  "type": "Feature",
  "properties": {
    "addr:full":"1575 Clarkson Rd Mississauga ON L5J 2X1",
    "addr:housenumber":"1575",
    "addr:postcode":"l5j 2x1",
    "addr:street":"Clarkson Rd",
    "iso:country":"CA",
    "sg:address":"1575 Clarkson Rd",
    "sg:city":"Mississauga",
    "sg:classifiers":[
        {
            "category":"Retail",
            "subcategory":"Laundry & Dry Cleaning",
            "type":"Services"
        }
    ],
    "sg:phone":"+1 905 822 2528",
    "sg:postcode":"L5J 2X1",
    "sg:province":"ON",
    "sg:tags":[
        "cleaners"
    ],
    "wof:name":"Utone Cleaners",
    "wof:placetype":"venue"
},
  "geometry": {"coordinates":[-79.63887800000001,43.528366],"type":"Point"}
}