{
  "type": "Feature",
  "properties": {
    "addr:full":"Fort Mcmurray AB T9H 4G8",
    "addr:postcode":"t9h 4g8",
    "iso:country":"CA",
    "sg:city":"Fort Mcmurray",
    "sg:classifiers":[
        {
            "category":"Shopping",
            "subcategory":"Pharmacy",
            "type":"Retail Goods"
        }
    ],
    "sg:phone":"+1 780 743 1251",
    "sg:postcode":"T9H 4G8",
    "sg:province":"AB",
    "wof:name":"Shoppers Drug Mart",
    "wof:placetype":"venue"
},
  "geometry": {"coordinates":[-111.36032104500001,56.7196655273],"type":"Point"}
}