{
  "type": "Feature",
  "properties": {
    "addr:full":"914 Av Des Erables Quebec QC G1R 2M5",
    "addr:postcode":"g1r 2m5",
    "addr:street":"914 Av Des Erables",
    "iso:country":"CA",
    "sg:address":"914 Av Des Erables",
    "sg:city":"Quebec",
    "sg:classifiers":[
        {
            "category":"Health Services",
            "subcategory":"Doctor",
            "type":"Services"
        }
    ],
    "sg:phone":"+1 418 681 5255",
    "sg:postcode":"G1R 2M5",
    "sg:province":"QC",
    "sg:tags":[
        "dentist"
    ],
    "wof:name":"Demers, Simard DDS",
    "wof:placetype":"venue"
},
  "geometry": {"coordinates":[-71.231003,46.803364],"type":"Point"}
}