{
  "type": "Feature",
  "properties": {
    "addr:full":"108 Mile Ranch BC V0K 2Z0",
    "addr:housenumber":"108",
    "addr:postcode":"v0k 2z0",
    "addr:street":"Mile Ranch",
    "iso:country":"CA",
    "sg:city":"108 Mile Ranch",
    "sg:classifiers":[
        {
            "category":"Wholesale",
            "subcategory":"Machinery & Supplies",
            "type":"Manufacturing & Wholesale Goods"
        }
    ],
    "sg:phone":"+1 250 791 7270",
    "sg:postcode":"V0K 2Z0",
    "sg:province":"BC",
    "sg:tags":[
        "valve"
    ],
    "wof:name":"Cariboo House of Hose & Beltin",
    "wof:placetype":"venue"
},
  "geometry": {"coordinates":[-121.38067627,51.7408370972],"type":"Point"}
}