{
  "type": "Feature",
  "properties": {
    "addr:full":"96 Picola Crt North York ON M2H 2N4",
    "addr:housenumber":"96",
    "addr:postcode":"m2h 2n4",
    "addr:street":"Picola Crt",
    "iso:country":"CA",
    "sg:address":"96 Picola Crt",
    "sg:city":"North York",
    "sg:classifiers":[
        {
            "category":"Professional",
            "subcategory":"Business Services",
            "type":"Services"
        }
    ],
    "sg:phone":"+1 416 494 3335",
    "sg:postcode":"M2H 2N4",
    "sg:province":"ON",
    "sg:tags":[
        "convention",
        "meeting",
        "facility"
    ],
    "wof:name":"Katz Consulting & Event Coordn",
    "wof:placetype":"venue"
},
  "geometry": {"coordinates":[-79.34774,43.803753],"type":"Point"}
}