{
  "type": "Feature",
  "properties": {
    "addr:full":"419 Rue Sainte-Marie Marieville QC J3M 1H7",
    "addr:housenumber":"419",
    "addr:postcode":"j3m 1h7",
    "addr:street":"Rue Sainte-Marie",
    "iso:country":"CA",
    "sg:address":"419 Rue Sainte-Marie",
    "sg:city":"Marieville",
    "sg:classifiers":[
        {
            "category":"Insurance",
            "subcategory":"Insurance Agent",
            "type":"Services"
        }
    ],
    "sg:phone":"+1 450 460 4921",
    "sg:postcode":"J3M 1H7",
    "sg:province":"QC",
    "wof:name":"Assurance Denis Beauregard",
    "wof:placetype":"venue"
},
  "geometry": {"coordinates":[-73.16345200000001,45.43399],"type":"Point"}
}