{
  "type": "Feature",
  "properties": {
    "addr:full":"2175 Rue Saint-Jean Plessisville QC G6L 2Y4",
    "addr:housenumber":"2175",
    "addr:postcode":"g6l 2y4",
    "addr:street":"Rue Saint-Jean",
    "iso:country":"CA",
    "sg:address":"2175 Rue Saint-Jean",
    "sg:city":"Plessisville",
    "sg:classifiers":[
        {
            "category":"Wholesale",
            "subcategory":"Machinery & Supplies",
            "type":"Manufacturing & Wholesale Goods"
        }
    ],
    "sg:phone":"+1 819 362 2417",
    "sg:postcode":"G6L 2Y4",
    "sg:province":"QC",
    "sg:tags":[
        "equipment",
        "dairy"
    ],
    "wof:name":"A Provencher Equipements Inc",
    "wof:placetype":"venue"
},
  "geometry": {"coordinates":[-71.77063800000001,46.228207],"type":"Point"}
}