{
  "type": "Feature",
  "properties": {
    "addr:full":"Waterloo ON N2V 1Z7",
    "addr:postcode":"n2v 1z7",
    "iso:country":"CA",
    "sg:city":"Waterloo",
    "sg:classifiers":[
        {
            "category":"Professional",
            "subcategory":"Research",
            "type":"Services"
        }
    ],
    "sg:phone":"+1 519 886 0978",
    "sg:postcode":"N2V 1Z7",
    "sg:province":"ON",
    "sg:tags":[
        "development",
        "electronic"
    ],
    "wof:name":"Moreltronics",
    "wof:placetype":"venue"
},
  "geometry": {"coordinates":[-80.53012099999999,43.506912],"type":"Point"}
}