{
  "type": "Feature",
  "properties": {
    "addr:full":"212 Watline Ave Mississauga ON L4Z 1P4",
    "addr:housenumber":"212",
    "addr:postcode":"l4z 1p4",
    "addr:street":"Watline Ave",
    "iso:country":"CA",
    "sg:address":"212 Watline Ave",
    "sg:city":"Mississauga",
    "sg:classifiers":[
        {
            "category":"Professional",
            "subcategory":"Advertising",
            "type":"Services"
        }
    ],
    "sg:phone":"+1 905 568 3100",
    "sg:postcode":"L4Z 1P4",
    "sg:province":"ON",
    "sg:tags":[
        "equipment",
        "distribution",
        "electric",
        "heating"
    ],
    "wof:name":"Zesta Engineering Ltd",
    "wof:placetype":"venue"
},
  "geometry": {"coordinates":[-79.666702,43.626095],"type":"Point"}
}