{
  "type": "Feature",
  "properties": {
    "addr:full":"314 Pine Ave Winnipeg Beach MB R0C 3G0",
    "addr:housenumber":"314",
    "addr:postcode":"r0c 3g0",
    "addr:street":"Pine Ave",
    "iso:country":"CA",
    "sg:address":"314 Pine Ave",
    "sg:city":"Winnipeg Beach",
    "sg:classifiers":[
        {
            "category":"Professional",
            "subcategory":"Management & Consulting",
            "type":"Services"
        }
    ],
    "sg:phone":"+1 204 389 2784",
    "sg:postcode":"R0C 3G0",
    "sg:province":"MB",
    "sg:tags":[
        "consultant",
        "business"
    ],
    "wof:name":"Paskanake Project Management",
    "wof:placetype":"venue"
},
  "geometry": {"coordinates":[-96.9754867554,50.5131111145],"type":"Point"}
}