{
  "type": "Feature",
  "properties": {
    "addr:full":"1180 Rue Des Genevriers Saint-Felicien QC G8K 2Z8",
    "addr:housenumber":"1180",
    "addr:postcode":"g8k 2z8",
    "addr:street":"Rue Des Genevriers Saint-Felicien",
    "iso:country":"CA",
    "sg:address":"1180 Rue Des Genevriers",
    "sg:city":"Saint-Felicien",
    "sg:classifiers":[
        {
            "category":"Organizations",
            "subcategory":"Religious Organization",
            "type":"Services"
        }
    ],
    "sg:phone":"+1 418 679 0079",
    "sg:postcode":"G8K 2Z8",
    "sg:province":"QC",
    "sg:tags":[
        "house",
        "retreat"
    ],
    "wof:name":"Habitations Du Carrefour",
    "wof:placetype":"venue"
},
  "geometry": {"coordinates":[-72.4506607056,48.6575508118],"type":"Point"}
}