{
  "type": "Feature",
  "properties": {
    "addr:full":"51 Rosenfeld Dr Barrie ON L4M 5X5",
    "addr:housenumber":"51",
    "addr:postcode":"l4m 5x5",
    "addr:street":"Rosenfeld Dr",
    "iso:country":"CA",
    "sg:address":"51 Rosenfeld Dr",
    "sg:city":"Barrie",
    "sg:classifiers":[
        {
            "category":"Building & Trades",
            "subcategory":"Construction",
            "type":"Services"
        }
    ],
    "sg:phone":"+1 705 737 9433",
    "sg:postcode":"L4M 5X5",
    "sg:province":"ON",
    "sg:tags":[
        "painter"
    ],
    "wof:name":"Kempenfelt Painting",
    "wof:placetype":"venue"
},
  "geometry": {"coordinates":[-79.648613,44.406311],"type":"Point"}
}