{
  "type": "Feature",
  "properties": {
    "addr:full":"Amqui QC G5J 3G2",
    "addr:postcode":"g5j 3g2",
    "iso:country":"CA",
    "sg:city":"Amqui",
    "sg:classifiers":[
        {
            "category":"Health Services",
            "subcategory":"Optometrist",
            "type":"Services"
        }
    ],
    "sg:phone":"+1 418 629 5873",
    "sg:postcode":"G5J 3G2",
    "sg:province":"QC",
    "wof:name":"Clinique Visuelle D'Amqui",
    "wof:placetype":"venue"
},
  "geometry": {"coordinates":[-67.433807,48.464195],"type":"Point"}
}