{
  "type": "Feature",
  "properties": {
    "addr:full":"4255 Sherwoodtowne Blvd Mississauga ON L4Z 1Y5",
    "addr:housenumber":"4255",
    "addr:postcode":"l4z 1y5",
    "addr:street":"Sherwoodtowne Blvd",
    "iso:country":"CA",
    "sg:address":"4255 Sherwoodtowne Blvd",
    "sg:city":"Mississauga",
    "sg:classifiers":[
        {
            "category":"Real Estate",
            "subcategory":"Real Estate Agent",
            "type":"Services"
        }
    ],
    "sg:phone":"+1 905 279 2714",
    "sg:postcode":"L4Z 1Y5",
    "sg:province":"ON",
    "sg:tags":[
        "desk",
        "space"
    ],
    "wof:name":"Bdo Professional Ctr",
    "wof:placetype":"venue"
},
  "geometry": {"coordinates":[-79.64025100000001,43.600628],"type":"Point"}
}