{
  "type": "Feature",
  "properties": {
    "iso:country":"CA",
    "sg:city":"Langley",
    "sg:classifiers":[
        {
            "category":"Professional",
            "type":"Services"
        }
    ],
    "sg:phone":"+1 604 888 8311",
    "sg:postcode":"V1M 3J9",
    "sg:province":"BC",
    "sg:tags":[
        "sporting",
        "good",
        "establishment"
    ],
    "wof:name":"Fore Star Enterprises Ltd",
    "wof:placetype":"venue"
},
  "geometry": {"coordinates":[-122.674118042,49.1723251343],"type":"Point"}
}