{
  "type": "Feature",
  "properties": {
    "iso:country":"CA",
    "sg:address":"47 Pine Glen Rd",
    "sg:city":"Riverview",
    "sg:classifiers":[
        {
            "category":"Health Services",
            "subcategory":"Chiropractor",
            "type":"Services"
        }
    ],
    "sg:phone":"+1 506 386 2225",
    "sg:postcode":"E1B 1V3",
    "sg:province":"NB",
    "wof:name":"Maillet, Marie-Josee DC",
    "wof:placetype":"venue"
},
  "geometry": {"coordinates":[-64.79388427729999,46.0664291382],"type":"Point"}
}