{
  "type": "Feature",
  "properties": {
    "addr:full":"Warwick QC J0A 1M0",
    "addr:postcode":"j0a 1m0",
    "iso:country":"CA",
    "sg:city":"Warwick",
    "sg:classifiers":[
        {
            "category":"Banks & Credit Unions",
            "subcategory":"Bank",
            "type":"Services"
        }
    ],
    "sg:phone":"+1 819 358 2001",
    "sg:postcode":"J0A 1M0",
    "sg:province":"QC",
    "wof:name":"Banque Nationale Du Canada",
    "wof:placetype":"venue"
},
  "geometry": {"coordinates":[-71.9925003052,45.9468803406],"type":"Point"}
}