{
  "type": "Feature",
  "properties": {
    "iso:country":"CA",
    "sg:address":"954 Rue DE L'Eglise",
    "sg:city":"Saint-Antoine-DE-Tilly",
    "sg:classifiers":[
        {
            "category":"Recreation",
            "type":"Entertainment"
        }
    ],
    "sg:phone":"+1 418 886 2585",
    "sg:postcode":"G0S 2C0",
    "sg:province":"QC",
    "sg:tags":[
        "hall",
        "auditorium"
    ],
    "wof:name":"Carrefour DE Tilly",
    "wof:placetype":"venue"
},
  "geometry": {"coordinates":[-71.5090637207,46.6148490906],"type":"Point"}
}