{
  "type": "Feature",
  "properties": {
    "addr:full":"530 Walden Blvd Fort Erie ON L2A 1S3",
    "addr:housenumber":"530",
    "addr:postcode":"l2a 1s3",
    "addr:street":"Walden Blvd",
    "iso:country":"CA",
    "sg:address":"530 Walden Blvd",
    "sg:city":"Fort Erie",
    "sg:classifiers":[
        {
            "category":"Organizations",
            "subcategory":"Religious Organization",
            "type":"Services"
        }
    ],
    "sg:phone":"+1 905 871 5262",
    "sg:postcode":"L2A 1S3",
    "sg:province":"ON",
    "sg:tags":[
        "church"
    ],
    "wof:name":"Jehovah's Witnesses Kingdom Hl",
    "wof:placetype":"venue"
},
  "geometry": {"coordinates":[-78.933899,42.906471],"type":"Point"}
}