{
  "type": "Feature",
  "properties": {
    "addr:full":"248 Rue Notre-Dame E Victoriaville QC G6P 4A1",
    "addr:housenumber":"248",
    "addr:postcode":"g6p 4a1",
    "addr:street":"Rue Notre-Dame E",
    "iso:country":"CA",
    "sg:address":"248 Rue Notre-Dame E",
    "sg:city":"Victoriaville",
    "sg:classifiers":[
        {
            "category":"Professional",
            "subcategory":"Management & Consulting",
            "type":"Services"
        }
    ],
    "sg:phone":"+1 819 758 6275",
    "sg:postcode":"G6P 4A1",
    "sg:province":"QC",
    "sg:tags":[
        "consultant",
        "telecommunication"
    ],
    "wof:name":"Somum Inc",
    "wof:placetype":"venue"
},
  "geometry": {"coordinates":[-71.952888,46.057751],"type":"Point"}
}