{
  "type": "Feature",
  "properties": {
    "addr:full":"673 Boul Renault Beauceville QC G5X 1L9",
    "addr:housenumber":"673",
    "addr:postcode":"g5x 1l9",
    "addr:street":"Boul Renault",
    "iso:country":"CA",
    "sg:address":"673 Boul Renault",
    "sg:city":"Beauceville",
    "sg:classifiers":[
        {
            "category":"Organizations",
            "subcategory":"Professional Association",
            "type":"Services"
        }
    ],
    "sg:phone":"+1 418 774 2444",
    "sg:postcode":"G5X 1L9",
    "sg:province":"QC",
    "wof:name":"Murmure Groupe DE Personnes",
    "wof:placetype":"venue"
},
  "geometry": {"coordinates":[-70.770218,46.201561],"type":"Point"}
}