{
  "type": "Feature",
  "properties": {
    "addr:full":"Sunderland ON L0C 1H0",
    "addr:postcode":"l0c 1h0",
    "iso:country":"CA",
    "sg:city":"Sunderland",
    "sg:classifiers":[
        {
            "category":"Organizations",
            "subcategory":"Non-profit Organization",
            "type":"Services"
        }
    ],
    "sg:phone":"+1 705 357 2984",
    "sg:postcode":"L0C 1H0",
    "sg:province":"ON",
    "sg:tags":[
        "addiction",
        "treatment",
        "center"
    ],
    "wof:name":"Doing Life Intl Inc",
    "wof:placetype":"venue"
},
  "geometry": {"coordinates":[-79.0679397583,44.2614860535],"type":"Point"}
}