{
  "type": "Feature",
  "properties": {
    "addr:full":"Saint-Felicien QC G8K 1R4",
    "addr:postcode":"g8k 1r4",
    "iso:country":"CA",
    "sg:city":"Saint-Felicien",
    "sg:classifiers":[
        {
            "category":"Restaurant",
            "type":"Food & Drink"
        }
    ],
    "sg:phone":"+1 418 679 3339",
    "sg:postcode":"G8K 1R4",
    "sg:province":"QC",
    "wof:name":"Restaurants O Mets Chinois Enr",
    "wof:placetype":"venue"
},
  "geometry": {"coordinates":[-72.440613,48.648643],"type":"Point"}
}