{
  "type": "Feature",
  "properties": {
    "addr:full":"143 Joseph St Clinton ON N0M 1L0",
    "addr:housenumber":"143",
    "addr:postcode":"n0m 1l0",
    "addr:street":"Joseph St",
    "iso:country":"CA",
    "sg:address":"143 Joseph St",
    "sg:city":"Clinton",
    "sg:classifiers":[
        {
            "category":"Organizations",
            "subcategory":"Religious Organization",
            "type":"Services"
        }
    ],
    "sg:phone":"+1 519 482 8687",
    "sg:postcode":"N0M 1L0",
    "sg:province":"ON",
    "sg:tags":[
        "church"
    ],
    "wof:name":"Joseph Street Gospel Hall",
    "wof:placetype":"venue"
},
  "geometry": {"coordinates":[-81.54422,43.616459],"type":"Point"}
}