{
  "type": "Feature",
  "properties": {
    "addr:full":"Edmonton AB T6H 5P9",
    "addr:postcode":"t6h 5p9",
    "iso:country":"CA",
    "sg:city":"Edmonton",
    "sg:classifiers":[
        {
            "category":"Health Services",
            "subcategory":"Doctor",
            "type":"Services"
        }
    ],
    "sg:phone":"+1 780 439 6662",
    "sg:postcode":"T6H 5P9",
    "sg:province":"AB",
    "sg:tags":[
        "dentist"
    ],
    "wof:name":"Mac Donald, J W C DDS",
    "wof:placetype":"venue"
},
  "geometry": {"coordinates":[-113.496262,53.492722],"type":"Point"}
}