{
  "type": "Feature",
  "properties": {
    "iso:country":"CA",
    "sg:address":"9863 Av Du Parc-Georges",
    "sg:city":"Montreal-Nord",
    "sg:classifiers":[
        {
            "category":"Manufacturing",
            "subcategory":"Apparel",
            "type":"Manufacturing & Wholesale Goods"
        }
    ],
    "sg:phone":"+1 514 323 6715",
    "sg:postcode":"H1H 4X6",
    "sg:province":"QC",
    "sg:tags":[
        "clothes",
        "accessory"
    ],
    "wof:name":"Anjou Knitwear Inc",
    "wof:placetype":"venue"
},
  "geometry": {"coordinates":[-73.6364364624,45.5780448914],"type":"Point"}
}