{
  "type": "Feature",
  "properties": {
    "addr:full":"655 Mountain Rd Moncton NB E1C 2P4",
    "addr:housenumber":"655",
    "addr:postcode":"e1c 2p4",
    "addr:street":"Mountain Rd",
    "iso:country":"CA",
    "sg:address":"655 Mountain Rd",
    "sg:city":"Moncton",
    "sg:classifiers":[
        {
            "category":"Banks & Credit Unions",
            "subcategory":"Bank",
            "type":"Services"
        }
    ],
    "sg:phone":"+1 506 859 3710",
    "sg:postcode":"E1C 2P4",
    "sg:province":"NB",
    "wof:name":"Cibc",
    "wof:placetype":"venue"
},
  "geometry": {"coordinates":[-64.80168151860001,46.0988502502],"type":"Point"}
}