{
  "type": "Feature",
  "properties": {
    "addr:full":"2185 8E Rue Saint-Prosper-DE-Dorchester QC G0M 1Y0",
    "addr:housenumber":"2185",
    "addr:postcode":"g0m 1y0",
    "addr:street":"8E Rue Saint-Prosper-De-Dorchester",
    "iso:country":"CA",
    "sg:address":"2185 8E Rue",
    "sg:city":"Saint-Prosper-DE-Dorchester",
    "sg:classifiers":[
        {
            "category":"Shopping",
            "subcategory":"Crafts & Fabrics",
            "type":"Retail Goods"
        }
    ],
    "sg:phone":"+1 418 594 5258",
    "sg:postcode":"G0M 1Y0",
    "sg:province":"QC",
    "sg:tags":[
        "shop"
    ],
    "wof:name":"Chez Martine Enr",
    "wof:placetype":"venue"
},
  "geometry": {"coordinates":[-70.49774932859999,46.2215538025],"type":"Point"}
}