{
  "type": "Feature",
  "properties": {
    "addr:full":"RR 4 Frankford ON K0K 2C0",
    "addr:postcode":"k0k 2c0",
    "addr:street":"Rr 4",
    "iso:country":"CA",
    "sg:address":"RR 4",
    "sg:city":"Frankford",
    "sg:classifiers":[
        {
            "category":"Recreation",
            "type":"Entertainment"
        }
    ],
    "sg:phone":"+1 613 398 8946",
    "sg:postcode":"K0K 2C0",
    "sg:province":"ON",
    "sg:tags":[
        "hall",
        "auditorium"
    ],
    "wof:name":"Lower Trent Valley Fish Club",
    "wof:placetype":"venue"
},
  "geometry": {"coordinates":[-77.596352,44.201118],"type":"Point"}
}