{
  "type": "Feature",
  "properties": {
    "addr:full":"Toronto ON M5G 1Z3",
    "addr:postcode":"m5g 1z3",
    "iso:country":"CA",
    "sg:city":"Toronto",
    "sg:classifiers":[
        {
            "category":"Food & Beverages",
            "subcategory":"Bakery",
            "type":"Retail Goods"
        }
    ],
    "sg:phone":"+1 416 598 1177",
    "sg:postcode":"M5G 1Z3",
    "sg:province":"ON",
    "sg:tags":[
        "baker"
    ],
    "wof:name":"Sweet Rosie's Cookies Ltd",
    "wof:placetype":"venue"
},
  "geometry": {"coordinates":[-79.381096,43.656155],"type":"Point"}
}