{
  "type": "Feature",
  "properties": {
    "iso:country":"CA",
    "sg:address":"194 City Centre",
    "sg:city":"Kitimat",
    "sg:classifiers":[
        {
            "category":"Food & Beverages",
            "subcategory":"Groceries & Convenience Stores",
            "type":"Retail Goods"
        }
    ],
    "sg:phone":"+1 250 632 2626",
    "sg:postcode":"V8C 1T6",
    "sg:province":"BC",
    "sg:tags":[
        "grocer"
    ],
    "wof:name":"Super Valu",
    "wof:placetype":"venue"
},
  "geometry": {"coordinates":[-128.65573120100001,54.0533065796],"type":"Point"}
}