{
  "type": "Feature",
  "properties": {
    "addr:full":"53 Van Horne Cres North Bay ON P1A 1G2",
    "addr:housenumber":"53",
    "addr:postcode":"p1a 1g2",
    "addr:street":"Van Horne Cres",
    "iso:country":"CA",
    "sg:address":"53 Van Horne Cres",
    "sg:city":"North Bay",
    "sg:classifiers":[
        {
            "category":"Building & Trades",
            "subcategory":"Landscaping Services",
            "type":"Services"
        }
    ],
    "sg:phone":"+1 705 497 0002",
    "sg:postcode":"P1A 1G2",
    "sg:province":"ON",
    "sg:tags":[
        "landscape",
        "contractor"
    ],
    "wof:name":"Lawn Guard Irrigation",
    "wof:placetype":"venue"
},
  "geometry": {"coordinates":[-79.447304,46.293407],"type":"Point"}
}