{
  "type": "Feature",
  "properties": {
    "addr:full":"15 Rte Tache Saint-Fulgence QC G0V 1S0",
    "addr:housenumber":"15",
    "addr:postcode":"g0v 1s0",
    "addr:street":"Rte Tache",
    "iso:country":"CA",
    "sg:address":"15 Rte Tache",
    "sg:city":"Saint-Fulgence",
    "sg:classifiers":[
        {
            "category":"Building & Trades",
            "subcategory":"Construction",
            "type":"Services"
        }
    ],
    "sg:phone":"+1 418 674 2375",
    "sg:postcode":"G0V 1S0",
    "sg:province":"QC",
    "sg:tags":[
        "roofing",
        "contractor"
    ],
    "wof:name":"Couvertures Du Saguenay Inc",
    "wof:placetype":"venue"
},
  "geometry": {"coordinates":[-70.962425,48.498573],"type":"Point"}
}