{
  "type": "Feature",
  "properties": {
    "addr:full":"1126 Davie St Vancouver BC V6E 1N1",
    "addr:housenumber":"1126",
    "addr:postcode":"v6e 1n1",
    "addr:street":"Davie St",
    "iso:country":"CA",
    "sg:address":"1126 Davie St",
    "sg:city":"Vancouver",
    "sg:classifiers":[
        {
            "category":"Shopping",
            "subcategory":"Tobacco",
            "type":"Retail Goods"
        }
    ],
    "sg:phone":"+1 604 687 4541",
    "sg:postcode":"V6E 1N1",
    "sg:province":"BC",
    "sg:tags":[
        "cigarette",
        "cigar",
        "dealer"
    ],
    "wof:name":"S Mart",
    "wof:placetype":"venue"
},
  "geometry": {"coordinates":[-123.13208,49.280769],"type":"Point"}
}