{
  "type": "Feature",
  "properties": {
    "addr:full":"45846 Wellington Ave Chilliwack BC V2P 2C9",
    "addr:housenumber":"45846",
    "addr:postcode":"v2p 2c9",
    "addr:street":"Wellington Ave",
    "iso:country":"CA",
    "sg:address":"45846 Wellington Ave",
    "sg:city":"Chilliwack",
    "sg:classifiers":[
        {
            "category":"Restaurant",
            "type":"Food & Drink"
        }
    ],
    "sg:phone":"+1 604 793 6675",
    "sg:postcode":"V2P 2C9",
    "sg:province":"BC",
    "sg:tags":[
        "shop",
        "coffee"
    ],
    "wof:name":"Decades Coffee",
    "wof:placetype":"venue"
},
  "geometry": {"coordinates":[-121.95603199999999,49.172012],"type":"Point"}
}