{
  "type": "Feature",
  "properties": {
    "addr:full":"116 Main St Young SK S0K 4Y0",
    "addr:housenumber":"116",
    "addr:postcode":"s0k 4y0",
    "addr:street":"Main St",
    "iso:country":"CA",
    "sg:address":"116 Main St",
    "sg:city":"Young",
    "sg:classifiers":[
        {
            "category":"Government",
            "subcategory":"Office",
            "type":"Public Place"
        }
    ],
    "sg:phone":"+1 306 259 2242",
    "sg:postcode":"S0K 4Y0",
    "sg:province":"SK",
    "sg:tags":[
        "village"
    ],
    "wof:name":"Village of Young",
    "wof:placetype":"venue"
},
  "geometry": {"coordinates":[-105.746826,51.766701],"type":"Point"}
}