{
  "type": "Feature",
  "properties": {
    "addr:full":"Toronto ON M4W 1A9",
    "addr:postcode":"m4w 1a9",
    "iso:country":"CA",
    "sg:city":"Toronto",
    "sg:classifiers":[
        {
            "category":"Professional",
            "subcategory":"Lawyer & Legal Services",
            "type":"Services"
        }
    ],
    "sg:phone":"+1 416 515 9686",
    "sg:postcode":"M4W 1A9",
    "sg:province":"ON",
    "sg:tags":[
        "attorney"
    ],
    "wof:name":"Scher & DE Angelis",
    "wof:placetype":"venue"
},
  "geometry": {"coordinates":[-79.38465118409999,43.6705322266],"type":"Point"}
}