{
  "type": "Feature",
  "properties": {
    "addr:full":"230 Victoria St Kamloops BC V2C 2A2",
    "addr:housenumber":"230",
    "addr:postcode":"bc v2c 2a2",
    "addr:street":"Victoria St",
    "iso:country":"CA",
    "sg:address":"230 Victoria St",
    "sg:city":"Kamloops",
    "sg:classifiers":[
        {
            "category":"Personal",
            "subcategory":"Beauty Salon",
            "type":"Services"
        }
    ],
    "sg:phone":"+1 250 828 2799",
    "sg:postcode":"V2C 2A2",
    "sg:province":"BC",
    "wof:name":"Total Ten Studios Ltd",
    "wof:placetype":"venue"
},
  "geometry": {"coordinates":[-120.335906982,50.6760139465],"type":"Point"}
}