{
  "type": "Feature",
  "properties": {
    "addr:full":"100 Boul Jutras E Victoriaville QC G6P 4L5",
    "addr:housenumber":"100",
    "addr:postcode":"g6p 4l5",
    "addr:street":"Boul Jutras E",
    "iso:country":"CA",
    "sg:address":"100 Boul Jutras E",
    "sg:city":"Victoriaville",
    "sg:classifiers":[
        {
            "category":"Shopping",
            "subcategory":"Florist",
            "type":"Retail Goods"
        }
    ],
    "sg:phone":"+1 819 752 9716",
    "sg:postcode":"G6P 4L5",
    "sg:province":"QC",
    "wof:name":"Fleuriste Beauchesne & Frere",
    "wof:placetype":"venue"
},
  "geometry": {"coordinates":[-71.94834899999999,46.054298],"type":"Point"}
}