{
  "type": "Feature",
  "properties": {
    "addr:full":"3081 Rue Principale Saint-Zotique QC J0P 1Z0",
    "addr:housenumber":"3081",
    "addr:postcode":"j0p 1z0",
    "addr:street":"Rue Principale",
    "iso:country":"CA",
    "sg:address":"3081 Rue Principale",
    "sg:city":"Saint-Zotique",
    "sg:classifiers":[
        {
            "category":"Food & Beverages",
            "subcategory":"Groceries & Convenience Stores",
            "type":"Retail Goods"
        }
    ],
    "sg:phone":"+1 450 267 9477",
    "sg:postcode":"J0P 1Z0",
    "sg:province":"QC",
    "wof:name":"Depanneur LA Pointe",
    "wof:placetype":"venue"
},
  "geometry": {"coordinates":[-74.286957,45.229134],"type":"Point"}
}