{
  "type": "Feature",
  "properties": {
    "addr:full":"2080 Fasan Dr Oldcastle ON N0R 1L0",
    "addr:housenumber":"2080",
    "addr:postcode":"n0r 1l0",
    "addr:street":"Fasan Dr",
    "iso:country":"CA",
    "sg:address":"2080 Fasan Dr",
    "sg:city":"Oldcastle",
    "sg:classifiers":[
        {
            "category":"Manufacturing",
            "subcategory":"Tools & Machinery",
            "type":"Manufacturing & Wholesale Goods"
        }
    ],
    "sg:phone":"+1 519 737 6499",
    "sg:postcode":"N0R 1L0",
    "sg:province":"ON",
    "sg:tags":[
        "machine",
        "shop"
    ],
    "wof:name":"Rova Machine Inc",
    "wof:placetype":"venue"
},
  "geometry": {"coordinates":[-82.970879,42.23074],"type":"Point"}
}