{
  "type": "Feature",
  "properties": {
    "addr:full":"10210 108 Ave NW Edmonton AB T5H 1A8",
    "addr:housenumber":"10210",
    "addr:postcode":"t5h 1a8",
    "addr:street":"108 Ave Nw",
    "iso:country":"CA",
    "sg:address":"10210 108 Ave NW",
    "sg:city":"Edmonton",
    "sg:classifiers":[
        {
            "category":"Education",
            "subcategory":"School",
            "type":"Public Place"
        }
    ],
    "sg:phone":"+1 780 426 3010",
    "sg:postcode":"T5H 1A8",
    "sg:province":"AB",
    "wof:name":"Victoria School-Performing Art",
    "wof:placetype":"venue"
},
  "geometry": {"coordinates":[-113.495895,53.553238],"type":"Point"}
}