{
  "type": "Feature",
  "properties": {
    "iso:country":"CA",
    "sg:address":"12712 Cathy Cres",
    "sg:city":"Mission",
    "sg:classifiers":[
        {
            "category":"Banks & Credit Unions",
            "subcategory":"Investment Brokerage",
            "type":"Services"
        }
    ],
    "sg:phone":"+1 604 462 8200",
    "sg:postcode":"V4S 1C8",
    "sg:province":"BC",
    "sg:tags":[
        "consultant",
        "planning",
        "financial"
    ],
    "wof:name":"Daignault, D",
    "wof:placetype":"venue"
},
  "geometry": {"coordinates":[-122.394508362,49.2321624756],"type":"Point"}
}