{
  "type": "Feature",
  "properties": {
    "iso:country":"CA",
    "sg:city":"Kingston",
    "sg:classifiers":[
        {
            "category":"Manufacturing",
            "subcategory":"Printing",
            "type":"Manufacturing & Wholesale Goods"
        }
    ],
    "sg:phone":"+1 613 546 5977",
    "sg:postcode":"K7K 6C7",
    "sg:province":"ON",
    "sg:tags":[
        "printer"
    ],
    "wof:name":"Superior Printing Ctr",
    "wof:placetype":"venue"
},
  "geometry": {"coordinates":[-76.531288,44.225327],"type":"Point"}
}