{
  "type": "Feature",
  "properties": {
    "iso:country":"CA",
    "sg:address":"6920 29 Ave NW",
    "sg:city":"Calgary",
    "sg:classifiers":[
        {
            "category":"Wholesale",
            "subcategory":"Construction Materials",
            "type":"Manufacturing & Wholesale Goods"
        }
    ],
    "sg:phone":"+1 403 247 5599",
    "sg:postcode":"T3B 0J4",
    "sg:province":"AB",
    "sg:tags":[
        "fence"
    ],
    "wof:name":"Totem Building Supplies Ltd",
    "wof:placetype":"venue"
},
  "geometry": {"coordinates":[-114.185265,51.079777],"type":"Point"}
}