{
  "type": "Feature",
  "properties": {
    "iso:country":"CA",
    "sg:address":"9936 153 Ave NW",
    "sg:city":"Edmonton",
    "sg:classifiers":[
        {
            "category":"Health Services",
            "subcategory":"Doctor",
            "type":"Services"
        }
    ],
    "sg:phone":"+1 780 456 7578",
    "sg:postcode":"T5X 6A4",
    "sg:province":"AB",
    "sg:tags":[
        "dentist"
    ],
    "wof:name":"Beaumaris Dental Ctr",
    "wof:placetype":"venue"
},
  "geometry": {"coordinates":[-113.496025,53.614368],"type":"Point"}
}