{
  "type": "Feature",
  "properties": {
    "addr:full":"110 Meyers Ave Kinistino SK S0J 1H0",
    "addr:housenumber":"110",
    "addr:postcode":"s0j 1h0",
    "addr:street":"Meyers Ave",
    "iso:country":"CA",
    "sg:address":"110 Meyers Ave",
    "sg:city":"Kinistino",
    "sg:classifiers":[
        {
            "category":"Organizations",
            "subcategory":"Professional Association",
            "type":"Services"
        }
    ],
    "sg:phone":"+1 306 864 2807",
    "sg:postcode":"S0J 1H0",
    "sg:province":"SK",
    "wof:name":"Haven of Hope Home",
    "wof:placetype":"venue"
},
  "geometry": {"coordinates":[-105.034217834,52.9511146545],"type":"Point"}
}