{
  "type": "Feature",
  "properties": {
    "addr:full":"Kensington PE C0B 1M0",
    "addr:postcode":"c0b 1m0",
    "iso:country":"CA",
    "sg:city":"Kensington",
    "sg:classifiers":[
        {
            "category":"Home & Garden",
            "subcategory":"Building Materials",
            "type":"Retail Goods"
        }
    ],
    "sg:phone":"+1 902 836 4289",
    "sg:postcode":"C0B 1M0",
    "sg:province":"PE",
    "wof:name":"Spring Valley Building Ctr",
    "wof:placetype":"venue"
},
  "geometry": {"coordinates":[-63.627304,46.432545],"type":"Point"}
}