{
  "type": "Feature",
  "properties": {
    "addr:full":"Saint-Jacques QC J0K 2R0",
    "addr:postcode":"j0k 2r0",
    "iso:country":"CA",
    "sg:city":"Saint-Jacques",
    "sg:classifiers":[
        {
            "category":"Restaurant",
            "type":"Food & Drink"
        }
    ],
    "sg:phone":"+1 450 839 7253",
    "sg:postcode":"J0K 2R0",
    "sg:province":"QC",
    "wof:name":"Resto-Pub St Jacques Inc",
    "wof:placetype":"venue"
},
  "geometry": {"coordinates":[-73.57678199999999,45.952187],"type":"Point"}
}