{
  "type": "Feature",
  "properties": {
    "addr:full":"55 Macdonald Ave Dartmouth NS B3B 1T9",
    "addr:housenumber":"55",
    "addr:postcode":"b3b 1t9",
    "addr:street":"Macdonald Ave",
    "iso:country":"CA",
    "sg:address":"55 Macdonald Ave",
    "sg:city":"Dartmouth",
    "sg:classifiers":[
        {
            "category":"Manufacturing",
            "subcategory":"Electronics",
            "type":"Manufacturing & Wholesale Goods"
        }
    ],
    "sg:phone":"+1 902 468 2226",
    "sg:postcode":"B3B 1T9",
    "sg:province":"NS",
    "sg:tags":[
        "control",
        "security",
        "audio"
    ],
    "wof:name":"Instructor Aids Ltd",
    "wof:placetype":"venue"
},
  "geometry": {"coordinates":[-63.591137,44.697132],"type":"Point"}
}