{
  "type": "Feature",
  "properties": {
    "addr:full":"1964 Notion Rd Pickering ON L1V 2G3",
    "addr:housenumber":"1964",
    "addr:postcode":"l1v 2g3",
    "addr:street":"Notion Rd",
    "iso:country":"CA",
    "sg:address":"1964 Notion Rd",
    "sg:city":"Pickering",
    "sg:classifiers":[
        {
            "category":"Building & Trades",
            "subcategory":"Plumbing",
            "type":"Services"
        }
    ],
    "sg:phone":"+1 905 683 0380",
    "sg:postcode":"L1V 2G3",
    "sg:province":"ON",
    "sg:tags":[
        "air",
        "conditioning",
        "contractor",
        "system",
        "heating"
    ],
    "wof:name":"Service Experts",
    "wof:placetype":"venue"
},
  "geometry": {"coordinates":[-79.06526184080001,43.8512954712],"type":"Point"}
}