{
  "type": "Feature",
  "properties": {
    "addr:full":"4523 50 St # 1 Stony Plain AB T7Z 1L5",
    "addr:housenumber":"4523",
    "addr:postcode":"t7z 1l5",
    "addr:street":"50 St # 1",
    "iso:country":"CA",
    "sg:address":"4523 50 St # 1",
    "sg:city":"Stony Plain",
    "sg:classifiers":[
        {
            "category":"Retail",
            "subcategory":"Auto Repair",
            "type":"Services"
        }
    ],
    "sg:phone":"+1 780 968 8833",
    "sg:postcode":"T7Z 1L5",
    "sg:province":"AB",
    "sg:tags":[
        "repairing",
        "automobile"
    ],
    "wof:name":"A Tech Automotive Repair Ltd",
    "wof:placetype":"venue"
},
  "geometry": {"coordinates":[-114.007553,53.533649],"type":"Point"}
}