{
  "type": "Feature",
  "properties": {
    "iso:country":"CA",
    "sg:address":"2269 Kingston Rd",
    "sg:city":"Scarborough",
    "sg:classifiers":[
        {
            "category":"Restaurant",
            "type":"Food & Drink"
        }
    ],
    "sg:phone":"+1 416 265 5444",
    "sg:postcode":"M1N 1T8",
    "sg:province":"ON",
    "wof:name":"Domino's Pizza",
    "wof:placetype":"venue"
},
  "geometry": {"coordinates":[-79.2516708374,43.7052726746],"type":"Point"}
}