{
  "type": "Feature",
  "properties": {
    "addr:full":"9206 Dickenson Rd Mount Hope ON L0R 1W0",
    "addr:housenumber":"9206",
    "addr:postcode":"l0r 1w0",
    "addr:street":"Dickenson Rd",
    "iso:country":"CA",
    "sg:address":"9206 Dickenson Rd",
    "sg:city":"Mount Hope",
    "sg:classifiers":[
        {
            "category":"Wholesale",
            "subcategory":"Plants",
            "type":"Manufacturing & Wholesale Goods"
        }
    ],
    "sg:phone":"+1 905 679 4169",
    "sg:postcode":"L0R 1W0",
    "sg:province":"ON",
    "sg:tags":[
        "florist"
    ],
    "wof:name":"Sheldrick's Decor Inc",
    "wof:placetype":"venue"
},
  "geometry": {"coordinates":[-79.908722,43.180641],"type":"Point"}
}