{
  "type": "Feature",
  "properties": {
    "addr:full":"Mont-Royal QC H4P 1P7",
    "addr:postcode":"h4p 1p7",
    "iso:country":"CA",
    "sg:city":"Mont-Royal",
    "sg:classifiers":[
        {
            "category":"Building & Trades",
            "subcategory":"Construction",
            "type":"Services"
        }
    ],
    "sg:phone":"+1 514 733 7402",
    "sg:postcode":"H4P 1P7",
    "sg:province":"QC",
    "sg:tags":[
        "general",
        "contractor"
    ],
    "wof:name":"Construction Canalex Inc",
    "wof:placetype":"venue"
},
  "geometry": {"coordinates":[-73.659531,45.493107],"type":"Point"}
}