{
  "type": "Feature",
  "properties": {
    "addr:full":"1575 the Queensway Etobicoke ON M8Z 1T9",
    "addr:housenumber":"1575",
    "addr:postcode":"m8z 1t9",
    "addr:street":"The Queensway",
    "iso:country":"CA",
    "sg:address":"1575 the Queensway",
    "sg:city":"Etobicoke",
    "sg:classifiers":[
        {
            "category":"Retail",
            "subcategory":"Auto Repair",
            "type":"Services"
        }
    ],
    "sg:phone":"+1 416 521 7010",
    "sg:postcode":"M8Z 1T9",
    "sg:province":"ON",
    "sg:tags":[
        "truck"
    ],
    "wof:name":"Sherway Ford Truck Sales",
    "wof:placetype":"venue"
},
  "geometry": {"coordinates":[-79.540085,43.617786],"type":"Point"}
}