{
  "type": "Feature",
  "properties": {
    "addr:full":"163 Rue Principale RR 1 Girardville QC G0W 1R0",
    "addr:housenumber":"163",
    "addr:postcode":"g0w 1r0",
    "addr:street":"Rue Principale Rr 1",
    "iso:country":"CA",
    "sg:address":"163 Rue Principale RR 1",
    "sg:city":"Girardville",
    "sg:classifiers":[
        {
            "category":"Organizations",
            "subcategory":"Religious Organization",
            "type":"Services"
        }
    ],
    "sg:phone":"+1 418 258 3234",
    "sg:postcode":"G0W 1R0",
    "sg:province":"QC",
    "sg:tags":[
        "church"
    ],
    "wof:name":"Presbytere DE Girardville",
    "wof:placetype":"venue"
},
  "geometry": {"coordinates":[-72.547127,49.003242],"type":"Point"}
}