{
  "type": "Feature",
  "properties": {
    "addr:full":"5701 47 St Leduc AB T9E 7A1",
    "addr:housenumber":"5701",
    "addr:postcode":"t9e 7a1",
    "addr:street":"47 St",
    "iso:country":"CA",
    "sg:address":"5701 47 St",
    "sg:city":"Leduc",
    "sg:classifiers":[
        {
            "category":"Retail",
            "subcategory":"Auto Repair",
            "type":"Services"
        }
    ],
    "sg:phone":"+1 780 986 2211",
    "sg:postcode":"T9E 7A1",
    "sg:province":"AB",
    "sg:tags":[
        "repairing",
        "automobile"
    ],
    "wof:name":"Tischer Automotive Svc Ltd",
    "wof:placetype":"venue"
},
  "geometry": {"coordinates":[-113.547325134,53.270324707],"type":"Point"}
}