{
  "type": "Feature",
  "properties": {
    "addr:full":"1010 Degurse Rd Sarnia ON N7T 7H5",
    "addr:housenumber":"1010",
    "addr:postcode":"n7t 7h5",
    "addr:street":"Degurse Rd",
    "iso:country":"CA",
    "sg:address":"1010 Degurse Rd",
    "sg:city":"Sarnia",
    "sg:classifiers":[
        {
            "category":"Autos & Motor Vehicles",
            "subcategory":"Fuel & Gas Station",
            "type":"Retail Goods"
        }
    ],
    "sg:phone":"+1 519 344 7166",
    "sg:postcode":"N7T 7H5",
    "sg:province":"ON",
    "sg:tags":[
        "oil"
    ],
    "wof:name":"Chippewa Sunoco",
    "wof:placetype":"venue"
},
  "geometry": {"coordinates":[-82.40979,42.934547],"type":"Point"}
}