{
  "type": "Feature",
  "properties": {
    "iso:country":"CA",
    "sg:address":"4262 Rue Beaubien E",
    "sg:city":"Montreal",
    "sg:classifiers":[
        {
            "category":"Restaurant",
            "type":"Food & Drink"
        }
    ],
    "sg:phone":"+1 514 374 2332",
    "sg:postcode":"H1T 1S6",
    "sg:province":"QC",
    "wof:name":"Restaurant Resto Frederique",
    "wof:placetype":"venue"
},
  "geometry": {"coordinates":[-73.578316,45.563923],"type":"Point"}
}