{
  "type": "Feature",
  "properties": {
    "addr:full":"Edmonton AB T5J 2Z2",
    "addr:postcode":"t5j 2z2",
    "iso:country":"CA",
    "sg:city":"Edmonton",
    "sg:classifiers":[
        {
            "category":"Wholesale",
            "subcategory":"Non-durable Goods",
            "type":"Manufacturing & Wholesale Goods"
        }
    ],
    "sg:phone":"+1 780 422 7241",
    "sg:postcode":"T5J 2Z2",
    "sg:province":"AB",
    "sg:tags":[
        "advertising"
    ],
    "wof:name":"Morie Promotional Group",
    "wof:placetype":"venue"
},
  "geometry": {"coordinates":[-113.493431,53.543591],"type":"Point"}
}