{
  "type": "Feature",
  "properties": {
    "addr:full":"17 Cranston Ave Dartmouth NS B2Y 3G1",
    "addr:housenumber":"17",
    "addr:postcode":"b2y 3g1",
    "addr:street":"Cranston Ave",
    "iso:country":"CA",
    "sg:address":"17 Cranston Ave",
    "sg:city":"Dartmouth",
    "sg:classifiers":[
        {
            "category":"Professional",
            "subcategory":"Engineering",
            "type":"Services"
        }
    ],
    "sg:phone":"+1 902 461 9855",
    "sg:postcode":"B2Y 3G1",
    "sg:province":"NS",
    "sg:tags":[
        "town",
        "city",
        "regional",
        "planner",
        "engineer"
    ],
    "wof:name":"Atlanplan Ltd",
    "wof:placetype":"venue"
},
  "geometry": {"coordinates":[-63.552319,44.676922],"type":"Point"}
}