{
  "type": "Feature",
  "properties": {
    "addr:full":"105 Church St E Brampton ON L6V 1G7",
    "addr:housenumber":"105",
    "addr:postcode":"l6v 1g7",
    "addr:street":"Church St E",
    "iso:country":"CA",
    "sg:address":"105 Church St E",
    "sg:city":"Brampton",
    "sg:classifiers":[
        {
            "category":"Retail",
            "subcategory":"Animal Services",
            "type":"Services"
        }
    ],
    "sg:phone":"+1 905 796 7387",
    "sg:postcode":"L6V 1G7",
    "sg:province":"ON",
    "sg:tags":[
        "pet",
        "grooming",
        "washing"
    ],
    "wof:name":"Pet Spa",
    "wof:placetype":"venue"
},
  "geometry": {"coordinates":[-79.757317,43.692959],"type":"Point"}
}