{
  "type": "Feature",
  "properties": {
    "addr:full":"59 Main St N Markham ON L3P 1X7",
    "addr:housenumber":"59",
    "addr:postcode":"l3p 1x7",
    "addr:street":"Main St N",
    "iso:country":"CA",
    "sg:address":"59 Main St N",
    "sg:city":"Markham",
    "sg:classifiers":[
        {
            "category":"Insurance",
            "subcategory":"Insurance Agent",
            "type":"Services"
        }
    ],
    "sg:phone":"+1 905 294 0722",
    "sg:postcode":"L3P 1X7",
    "sg:province":"ON",
    "wof:name":"Carson & Weeks Insurance Brkrs",
    "wof:placetype":"venue"
},
  "geometry": {"coordinates":[-79.260239,43.876274],"type":"Point"}
}