{
  "type": "Feature",
  "properties": {
    "addr:full":"52 Stadacona St Winnipeg MB R2L 2C8",
    "addr:housenumber":"52",
    "addr:postcode":"r2l 2c8",
    "addr:street":"Stadacona St",
    "iso:country":"CA",
    "sg:address":"52 Stadacona St",
    "sg:city":"Winnipeg",
    "sg:classifiers":[
        {
            "category":"Food & Beverages",
            "subcategory":"Groceries & Convenience Stores",
            "type":"Retail Goods"
        }
    ],
    "sg:phone":"+1 204 663 3062",
    "sg:postcode":"R2L 2C8",
    "sg:province":"MB",
    "sg:tags":[
        "grocer"
    ],
    "wof:name":"Zip Thru Food Store",
    "wof:placetype":"venue"
},
  "geometry": {"coordinates":[-97.11174,49.907616],"type":"Point"}
}