{
  "type": "Feature",
  "properties": {
    "iso:country":"CA",
    "sg:address":"689 65th Ave E",
    "sg:city":"Vancouver",
    "sg:classifiers":[
        {
            "category":"Restaurant",
            "type":"Food & Drink"
        }
    ],
    "sg:phone":"+1 604 327 8900",
    "sg:postcode":"V5X 2P7",
    "sg:province":"BC",
    "wof:name":"Original Tandoori Kitchen King",
    "wof:placetype":"venue"
},
  "geometry": {"coordinates":[-123.091438294,49.2120857239],"type":"Point"}
}