{
  "type": "Feature",
  "properties": {
    "iso:country":"CA",
    "sg:address":"1315 Hwy 97 S",
    "sg:city":"Quesnel",
    "sg:classifiers":[
        {
            "category":"Building & Trades",
            "subcategory":"Construction",
            "type":"Services"
        }
    ],
    "sg:phone":"+1 250 992 2216",
    "sg:postcode":"V2J 4E2",
    "sg:province":"BC",
    "sg:tags":[
        "general",
        "contractor"
    ],
    "wof:name":"Forbes Construction CO Ltd",
    "wof:placetype":"venue"
},
  "geometry": {"coordinates":[-122.506774902,52.9939498901],"type":"Point"}
}