{
  "type": "Feature",
  "properties": {
    "addr:full":"8803 Rue Hochelaga Montreal, QC H1L 2N1",
    "iso:country":"CA",
    "name:eng_x_preferred":[
        "Le Coq de l'Est"
    ],
    "wof:name":"Le Coq de l'Est",
    "wof:placetype":"venue"
},
  "geometry": {"coordinates":[-73.519317,45.602539],"type":"Point"}
}