{
  "type": "Feature",
  "properties": {
    "addr:full":"688 Emily St Hanmer ON P3P 1E4",
    "addr:housenumber":"688",
    "addr:postcode":"p3p 1e4",
    "addr:street":"Emily St",
    "iso:country":"CA",
    "sg:address":"688 Emily St",
    "sg:city":"Hanmer",
    "sg:classifiers":[
        {
            "category":"Organizations",
            "subcategory":"Professional Association",
            "type":"Services"
        }
    ],
    "sg:phone":"+1 705 969 8895",
    "sg:postcode":"P3P 1E4",
    "sg:province":"ON",
    "sg:tags":[
        "club",
        "hall",
        "auditorium"
    ],
    "wof:name":"Knights of Columbus Hall",
    "wof:placetype":"venue"
},
  "geometry": {"coordinates":[-80.97159600000001,46.65435],"type":"Point"}
}