{
  "type": "Feature",
  "properties": {
    "addr:full":"Rosemere QC J7A 4K3",
    "addr:postcode":"j7a 4k3",
    "iso:country":"CA",
    "sg:city":"Rosemere",
    "sg:classifiers":[
        {
            "category":"Building & Trades",
            "subcategory":"Construction",
            "type":"Services"
        }
    ],
    "sg:phone":"+1 450 621 8557",
    "sg:postcode":"J7A 4K3",
    "sg:province":"QC",
    "sg:tags":[
        "caulking",
        "contractor"
    ],
    "wof:name":"Calfeutrage-Pro Inc",
    "wof:placetype":"venue"
},
  "geometry": {"coordinates":[-73.784187,45.651955],"type":"Point"}
}