{
  "type": "Feature",
  "properties": {
    "addr:full":"Vancouver BC V5N 5P4",
    "addr:postcode":"v5n 5p4",
    "iso:country":"CA",
    "sg:city":"Vancouver",
    "sg:classifiers":[
        {
            "category":"Education",
            "subcategory":"Special Training",
            "type":"Public Place"
        }
    ],
    "sg:phone":"+1 604 684 8825",
    "sg:postcode":"V5N 5P4",
    "sg:province":"BC",
    "sg:tags":[
        "organization",
        "school",
        "social",
        "language",
        "welfare"
    ],
    "wof:name":"Mosaic Language Ctr",
    "wof:placetype":"venue"
},
  "geometry": {"coordinates":[-123.069588,49.260162],"type":"Point"}
}