{
  "type": "Feature",
  "properties": {
    "addr:full":"6161 St. Georges Cres West Vancouver BC V7W 1Y9",
    "addr:housenumber":"6161",
    "addr:postcode":"v7w 1y9",
    "addr:street":"St. Georges Cres",
    "iso:country":"CA",
    "sg:address":"6161 St. Georges Cres",
    "sg:city":"West Vancouver",
    "sg:classifiers":[
        {
            "category":"Real Estate",
            "subcategory":"Architect",
            "type":"Services"
        }
    ],
    "sg:phone":"+1 604 921 1030",
    "sg:postcode":"V7W 1Y9",
    "sg:province":"BC",
    "wof:name":"Bentall, Charles",
    "wof:placetype":"venue"
},
  "geometry": {"coordinates":[-123.28643035899999,49.3647842407],"type":"Point"}
}