{
  "type": "Feature",
  "properties": {
    "addr:full":"7195 Cariboo Rd Burnaby BC V3N 4A6",
    "addr:housenumber":"7195",
    "addr:postcode":"v3n 4a6",
    "addr:street":"Cariboo Rd",
    "iso:country":"CA",
    "sg:address":"7195 Cariboo Rd",
    "sg:city":"Burnaby",
    "sg:classifiers":[
        {
            "category":"Social Services",
            "subcategory":"Child Care",
            "type":"Services"
        }
    ],
    "sg:phone":"+1 604 525 7311",
    "sg:postcode":"V3N 4A6",
    "sg:province":"BC",
    "sg:tags":[
        "church"
    ],
    "wof:name":"Salvation Army",
    "wof:placetype":"venue"
},
  "geometry": {"coordinates":[-122.910065,49.243732],"type":"Point"}
}