{
  "type": "Feature",
  "properties": {
    "addr:full":"Sudbury ON P3C 5M6",
    "addr:postcode":"p3c 5m6",
    "iso:country":"CA",
    "sg:city":"Sudbury",
    "sg:classifiers":[
        {
            "category":"Manufacturing",
            "subcategory":"Tools & Machinery",
            "type":"Manufacturing & Wholesale Goods"
        }
    ],
    "sg:phone":"+1 705 521 1115",
    "sg:postcode":"P3C 5M6",
    "sg:province":"ON",
    "sg:tags":[
        "equipment",
        "safety",
        "clothing"
    ],
    "wof:name":"Norguard Industries Inc",
    "wof:placetype":"venue"
},
  "geometry": {"coordinates":[-80.9885559082,46.5141563416],"type":"Point"}
}