{
  "type": "Feature",
  "properties": {
    "addr:full":"Brockville ON K6V 4V5",
    "addr:postcode":"k6v 4v5",
    "iso:country":"CA",
    "sg:city":"Brockville",
    "sg:classifiers":[
        {
            "category":"Insurance",
            "subcategory":"Insurance Agent",
            "type":"Services"
        }
    ],
    "sg:phone":"+1 613 345 5880",
    "sg:postcode":"K6V 4V5",
    "sg:province":"ON",
    "wof:name":"State Farm Insurance CO",
    "wof:placetype":"venue"
},
  "geometry": {"coordinates":[-75.6888046265,44.5926246643],"type":"Point"}
}