{
  "type": "Feature",
  "properties": {
    "addr:full":"1266 Victoria Park Ave East York ON M4B 2L1",
    "addr:housenumber":"1266",
    "addr:postcode":"m4b 2l1",
    "addr:street":"Victoria Park Ave",
    "iso:country":"CA",
    "sg:address":"1266 Victoria Park Ave",
    "sg:city":"East York",
    "sg:classifiers":[
        {
            "category":"Organizations",
            "subcategory":"Religious Organization",
            "type":"Services"
        }
    ],
    "sg:phone":"+1 416 757 7441",
    "sg:postcode":"M4B 2L1",
    "sg:province":"ON",
    "sg:tags":[
        "church"
    ],
    "wof:name":"Faith Gospel Chapel",
    "wof:placetype":"venue"
},
  "geometry": {"coordinates":[-79.2974472046,43.7121162415],"type":"Point"}
}