{
  "type": "Feature",
  "properties": {
    "addr:full":"122 Rue Saint-Emile Chicoutimi QC G7G 2K6",
    "addr:housenumber":"122",
    "addr:postcode":"g7g 2k6",
    "addr:street":"Rue Saint-Emile",
    "iso:country":"CA",
    "sg:address":"122 Rue Saint-Emile",
    "sg:city":"Chicoutimi",
    "sg:classifiers":[
        {
            "category":"Government",
            "subcategory":"Office",
            "type":"Public Place"
        }
    ],
    "sg:phone":"+1 418 698 3246",
    "sg:postcode":"G7G 2K6",
    "sg:province":"QC",
    "sg:tags":[
        "village"
    ],
    "wof:name":"Chicoutimi Maurice-Gauthier",
    "wof:placetype":"venue"
},
  "geometry": {"coordinates":[-71.04832500000001,48.438812],"type":"Point"}
}