{
  "type": "Feature",
  "properties": {
    "addr:full":"256 Lake Promenade Etobicoke ON M8W 1B3",
    "addr:housenumber":"256",
    "addr:postcode":"m8w 1b3",
    "addr:street":"Lake Promenade",
    "iso:country":"CA",
    "sg:address":"256 Lake Promenade",
    "sg:city":"Etobicoke",
    "sg:classifiers":[
        {
            "category":"Communications",
            "subcategory":"Film & Video Production",
            "type":"Services"
        }
    ],
    "sg:phone":"+1 416 777 1171",
    "sg:postcode":"M8W 1B3",
    "sg:province":"ON",
    "sg:tags":[
        "motion",
        "picture"
    ],
    "wof:name":"943463 Ontario Ltd",
    "wof:placetype":"venue"
},
  "geometry": {"coordinates":[-79.53230285639999,43.5888786316],"type":"Point"}
}