{
  "type": "Feature",
  "properties": {
    "addr:full":"1069 Boul Maloney E Gatineau QC J8P 1H8",
    "addr:housenumber":"1069",
    "addr:postcode":"j8p 1h8",
    "addr:street":"Boul Maloney E",
    "iso:country":"CA",
    "sg:address":"1069 Boul Maloney E",
    "sg:city":"Gatineau",
    "sg:classifiers":[
        {
            "category":"Utilities",
            "subcategory":"Fuel Oil & Lpg",
            "type":"Services"
        }
    ],
    "sg:phone":"+1 819 643 4033",
    "sg:postcode":"J8P 1H8",
    "sg:province":"QC",
    "sg:tags":[
        "propane",
        "gas"
    ],
    "wof:name":"Propane Outaouais Inc",
    "wof:placetype":"venue"
},
  "geometry": {"coordinates":[-75.5894622803,45.4919967651],"type":"Point"}
}