{
  "type": "Feature",
  "properties": {
    "addr:full":"5403 36 Ave Wetaskiwin AB T9A 3C7",
    "addr:housenumber":"5403",
    "addr:postcode":"t9a 3c7",
    "addr:street":"36 Ave",
    "iso:country":"CA",
    "sg:address":"5403 36 Ave",
    "sg:city":"Wetaskiwin",
    "sg:classifiers":[
        {
            "category":"Insurance",
            "subcategory":"Insurance Agent",
            "type":"Services"
        }
    ],
    "sg:phone":"+1 780 352 2420",
    "sg:postcode":"T9A 3C7",
    "sg:province":"AB",
    "wof:name":"Canada Brokerlink",
    "wof:placetype":"venue"
},
  "geometry": {"coordinates":[-113.387024,52.952446],"type":"Point"}
}