{
  "type": "Feature",
  "properties": {
    "addr:full":"Calgary AB T2A 0S6",
    "addr:postcode":"t2a 0s6",
    "iso:country":"CA",
    "sg:city":"Calgary",
    "sg:classifiers":[
        {
            "category":"Retail",
            "subcategory":"Self-service Laundry",
            "type":"Services"
        }
    ],
    "sg:phone":"+1 403 273 8224",
    "sg:postcode":"T2A 0S6",
    "sg:province":"AB",
    "wof:name":"Belle's Coin Laundry",
    "wof:placetype":"venue"
},
  "geometry": {"coordinates":[-113.97843899999999,51.037987],"type":"Point"}
}