{
  "type": "Feature",
  "properties": {
    "addr:full":"131 Queen St Killaloe ON K0J 2A0",
    "addr:housenumber":"131",
    "addr:postcode":"k0j 2a0",
    "addr:street":"Queen St",
    "iso:country":"CA",
    "sg:address":"131 Queen St",
    "sg:city":"Killaloe",
    "sg:classifiers":[
        {
            "category":"Education",
            "subcategory":"School",
            "type":"Public Place"
        }
    ],
    "sg:phone":"+1 613 757 2330",
    "sg:postcode":"K0J 2A0",
    "sg:province":"ON",
    "wof:name":"St Andrew's School",
    "wof:placetype":"venue"
},
  "geometry": {"coordinates":[-77.417412,45.557621],"type":"Point"}
}