{
  "type": "Feature",
  "properties": {
    "addr:full":"505 King George Hwy Miramichi NB E1V 1M6",
    "addr:housenumber":"505",
    "addr:postcode":"e1v 1m6",
    "addr:street":"King George Hwy",
    "iso:country":"CA",
    "sg:address":"505 King George Hwy",
    "sg:city":"Miramichi",
    "sg:classifiers":[
        {
            "category":"Insurance",
            "subcategory":"Insurance Agent",
            "type":"Services"
        }
    ],
    "sg:phone":"+1 506 622 0717",
    "sg:postcode":"E1V 1M6",
    "sg:province":"NB",
    "wof:name":"Mc Crae, Edith",
    "wof:placetype":"venue"
},
  "geometry": {"coordinates":[-65.56899300000001,47.000847],"type":"Point"}
}