{
  "type": "Feature",
  "properties": {
    "addr:full":"300 King Ave E Newcastle ON L1B 1J8",
    "addr:housenumber":"300",
    "addr:postcode":"l1b 1j8",
    "addr:street":"King Ave E",
    "iso:country":"CA",
    "sg:address":"300 King Ave E",
    "sg:city":"Newcastle",
    "sg:classifiers":[
        {
            "category":"Food & Beverages",
            "subcategory":"Bakery",
            "type":"Retail Goods"
        }
    ],
    "sg:phone":"+1 905 987 3060",
    "sg:postcode":"L1B 1J8",
    "sg:province":"ON",
    "sg:tags":[
        "doughnut"
    ],
    "wof:name":"Coffee Time Donuts",
    "wof:placetype":"venue"
},
  "geometry": {"coordinates":[-78.5830154419,43.9190292358],"type":"Point"}
}