{
  "type": "Feature",
  "properties": {
    "addr:full":"48 Erie St S Leamington ON N8H 3A9",
    "addr:housenumber":"48",
    "addr:postcode":"n8h 3a9",
    "addr:street":"Erie St S",
    "iso:country":"CA",
    "sg:address":"48 Erie St S",
    "sg:city":"Leamington",
    "sg:classifiers":[
        {
            "category":"Wholesale",
            "subcategory":"Seafood",
            "type":"Manufacturing & Wholesale Goods"
        }
    ],
    "sg:phone":"+1 519 326 0086",
    "sg:postcode":"N8H 3A9",
    "sg:province":"ON",
    "wof:name":"Mediterranean Seafood",
    "wof:placetype":"venue"
},
  "geometry": {"coordinates":[-82.599693,42.051895],"type":"Point"}
}