{
  "type": "Feature",
  "properties": {
    "addr:full":"10837 Ilderton Rd Ilderton ON N0M 2A0",
    "addr:housenumber":"10837",
    "addr:postcode":"n0m 2a0",
    "addr:street":"Ilderton Rd",
    "iso:country":"CA",
    "sg:address":"10837 Ilderton Rd",
    "sg:city":"Ilderton",
    "sg:classifiers":[
        {
            "category":"Building & Trades",
            "subcategory":"Landscaping Services",
            "type":"Services"
        }
    ],
    "sg:phone":"+1 519 666 0135",
    "sg:postcode":"N0M 2A0",
    "sg:province":"ON",
    "sg:tags":[
        "landscape",
        "contractor"
    ],
    "wof:name":"Heritage Landscaping Ltd",
    "wof:placetype":"venue"
},
  "geometry": {"coordinates":[-81.47622699999999,43.033882],"type":"Point"}
}