{
  "type": "Feature",
  "properties": {
    "addr:full":"340 Ch Des Erables Saint-Gerard-Des-Laurentides QC G9R 1G8",
    "addr:housenumber":"340",
    "addr:postcode":"g9r 1g8",
    "addr:street":"Ch Des Erables Saint-Gerard-Des-Laurentides",
    "iso:country":"CA",
    "sg:address":"340 Ch Des Erables",
    "sg:city":"Saint-Gerard-Des-Laurentides",
    "sg:classifiers":[
        {
            "category":"Retail",
            "subcategory":"Auto Repair",
            "type":"Services"
        }
    ],
    "sg:phone":"+1 819 539 5665",
    "sg:postcode":"G9R 1G8",
    "sg:province":"QC",
    "sg:tags":[
        "repairing",
        "automobile",
        "painting"
    ],
    "wof:name":"Garage N Massicotte",
    "wof:placetype":"venue"
},
  "geometry": {"coordinates":[-72.78280599999999,46.587761],"type":"Point"}
}