{
  "type": "Feature",
  "properties": {
    "addr:full":"York ON M6E 4V8",
    "addr:postcode":"m6e 4v8",
    "iso:country":"CA",
    "sg:city":"York",
    "sg:classifiers":[
        {
            "category":"Retail",
            "subcategory":"Auto Rental",
            "type":"Services"
        }
    ],
    "sg:phone":"+1 416 322 3911",
    "sg:postcode":"M6E 4V8",
    "sg:province":"ON",
    "sg:tags":[
        "renting",
        "automobile",
        "leasing"
    ],
    "wof:name":"Cardel Leasing",
    "wof:placetype":"venue"
},
  "geometry": {"coordinates":[-79.463005,43.696072],"type":"Point"}
}