{
  "type": "Feature",
  "properties": {
    "addr:full":"665 Columbia St New Westminster BC V3M 1A8",
    "addr:housenumber":"665",
    "addr:postcode":"v3m 1a8",
    "addr:street":"Columbia",
    "iso:country":"CA",
    "sg:address":"665 Columbia St",
    "sg:city":"New Westminster",
    "sg:classifiers":[
        {
            "category":"Shopping",
            "subcategory":"Stationery & Office Supplies",
            "type":"Retail Goods"
        }
    ],
    "sg:phone":"+1 604 517 1700",
    "sg:postcode":"V3M 1A8",
    "sg:province":"BC",
    "sg:tags":[
        "craft"
    ],
    "wof:name":"Paper Poet",
    "wof:placetype":"venue"
},
  "geometry": {"coordinates":[-122.909378,49.202541],"type":"Point"}
}