{
  "type": "Feature",
  "properties": {
    "addr:full":"6 Maplewood Pky Orillia ON L3V 6H1",
    "addr:housenumber":"6",
    "addr:postcode":"l3v 6h1",
    "addr:street":"Maplewood Pky",
    "iso:country":"CA",
    "sg:address":"6 Maplewood Pky",
    "sg:city":"Orillia",
    "sg:classifiers":[
        {
            "category":"Retail",
            "subcategory":"Portrait Studio",
            "type":"Services"
        }
    ],
    "sg:phone":"+1 705 327 8981",
    "sg:postcode":"L3V 6H1",
    "sg:province":"ON",
    "sg:tags":[
        "photographer"
    ],
    "wof:name":"Maplewood Studio",
    "wof:placetype":"venue"
},
  "geometry": {"coordinates":[-79.41822814939999,44.606590271],"type":"Point"}
}