{
  "type": "Feature",
  "properties": {
    "addr:full":"482 Beaconsfield Blvd Beaconsfield QC H9W 4C4",
    "addr:housenumber":"482",
    "addr:postcode":"h9w 4c4",
    "addr:street":"Beaconsfield Blvd",
    "iso:country":"CA",
    "sg:address":"482 Beaconsfield Blvd",
    "sg:city":"Beaconsfield",
    "sg:classifiers":[
        {
            "category":"Personal",
            "subcategory":"Beauty Salon",
            "type":"Services"
        }
    ],
    "sg:phone":"+1 514 695 7400",
    "sg:postcode":"H9W 4C4",
    "sg:province":"QC",
    "wof:name":"Salon Le Marly Maison-Beaute",
    "wof:placetype":"venue"
},
  "geometry": {"coordinates":[-73.8826599121,45.4193649292],"type":"Point"}
}