{
  "type": "Feature",
  "properties": {
    "addr:full":"2670 Fifth St Victoria BC V8T 5A8",
    "addr:housenumber":"2670",
    "addr:postcode":"v8t 5a8",
    "addr:street":"Fifth St",
    "iso:country":"CA",
    "sg:address":"2670 Fifth St",
    "sg:city":"Victoria",
    "sg:classifiers":[
        {
            "category":"Professional",
            "subcategory":"Computer Services",
            "type":"Services"
        }
    ],
    "sg:phone":"+1 250 389 0077",
    "sg:postcode":"V8T 5A8",
    "sg:province":"BC",
    "sg:tags":[
        "repair"
    ],
    "wof:name":"O E Systems Inc",
    "wof:placetype":"venue"
},
  "geometry": {"coordinates":[-123.357849121,48.4389343262],"type":"Point"}
}