{
  "type": "Feature",
  "properties": {
    "iso:country":"CA",
    "sg:address":"645 65E Rue E",
    "sg:city":"Charlesbourg",
    "sg:classifiers":[
        {
            "category":"Professional",
            "subcategory":"Accounting & Tax Preparation",
            "type":"Services"
        }
    ],
    "sg:phone":"+1 418 622 3207",
    "sg:postcode":"G1H 1W9",
    "sg:province":"QC",
    "sg:tags":[
        "bookkeeping",
        "return",
        "system",
        "filing"
    ],
    "wof:name":"Martin & Parent Enr",
    "wof:placetype":"venue"
},
  "geometry": {"coordinates":[-71.251518,46.845882],"type":"Point"}
}