{
  "type": "Feature",
  "properties": {
    "addr:full":"515 Rue Jacques-Cartier E Chicoutimi QC G7H 2A1",
    "addr:housenumber":"515",
    "addr:postcode":"g7h 2a1",
    "addr:street":"Rue Jacques-Cartier E",
    "iso:country":"CA",
    "sg:address":"515 Rue Jacques-Cartier E",
    "sg:city":"Chicoutimi",
    "sg:classifiers":[
        {
            "category":"Health Services",
            "subcategory":"Doctor",
            "type":"Services"
        }
    ],
    "sg:phone":"+1 418 549 8412",
    "sg:postcode":"G7H 2A1",
    "sg:province":"QC",
    "sg:tags":[
        "clinic",
        "chiropractor"
    ],
    "wof:name":"Centre Chiropratique Thibault",
    "wof:placetype":"venue"
},
  "geometry": {"coordinates":[-71.05285600000001,48.425667],"type":"Point"}
}