{
  "type": "Feature",
  "properties": {
    "addr:full":"5785 Boul Des Laurentides Laval QC H7K 2K5",
    "addr:housenumber":"5785",
    "addr:postcode":"qc h7k 2k5",
    "addr:street":"Boul Des Laurentides",
    "iso:country":"CA",
    "sg:address":"5785 Boul Des Laurentides",
    "sg:city":"Laval",
    "sg:classifiers":[
        {
            "category":"Health Services",
            "subcategory":"Doctor",
            "type":"Services"
        }
    ],
    "sg:phone":"+1 450 625 0543",
    "sg:postcode":"H7K 2K5",
    "sg:province":"QC",
    "sg:tags":[
        "clinic",
        "dentist"
    ],
    "wof:name":"Centre Dentaire P Beauparlant",
    "wof:placetype":"venue"
},
  "geometry": {"coordinates":[-73.75215911870001,45.6301307678],"type":"Point"}
}