{
  "type": "Feature",
  "properties": {
    "addr:full":"6801 83rd St Osoyoos BC V0H 1V0",
    "addr:housenumber":"6801",
    "addr:postcode":"v0h 1v0",
    "addr:street":"83Rd St",
    "iso:country":"CA",
    "sg:address":"6801 83rd St",
    "sg:city":"Osoyoos",
    "sg:classifiers":[
        {
            "category":"Food & Beverages",
            "subcategory":"Liquor & Beverages",
            "type":"Retail Goods"
        }
    ],
    "sg:phone":"+1 250 495 7321",
    "sg:postcode":"V0H 1V0",
    "sg:province":"BC",
    "sg:tags":[
        "store"
    ],
    "wof:name":"Liquor Stores-Government",
    "wof:placetype":"venue"
},
  "geometry": {"coordinates":[-119.463111877,49.0301589966],"type":"Point"}
}