{
  "type": "Feature",
  "properties": {
    "addr:full":"Milton ON L9T 5A3",
    "addr:postcode":"l9t 5a3",
    "iso:country":"CA",
    "sg:city":"Milton",
    "sg:classifiers":[
        {
            "category":"Home & Garden",
            "subcategory":"Home Furnishings",
            "type":"Retail Goods"
        }
    ],
    "sg:phone":"+1 905 878 7333",
    "sg:postcode":"L9T 5A3",
    "sg:province":"ON",
    "sg:tags":[
        "quilting",
        "quilt"
    ],
    "wof:name":"Quilter's Basket",
    "wof:placetype":"venue"
},
  "geometry": {"coordinates":[-79.8811340332,43.5031661987],"type":"Point"}
}