{
  "type": "Feature",
  "properties": {
    "iso:country":"CA",
    "sg:address":"2600 Rue Monty",
    "sg:city":"Val-David",
    "sg:classifiers":[
        {
            "category":"Manufacturing",
            "subcategory":"Printing",
            "type":"Manufacturing & Wholesale Goods"
        }
    ],
    "sg:phone":"+1 819 322 7969",
    "sg:postcode":"J0T 2N0",
    "sg:province":"QC",
    "sg:tags":[
        "newspaper",
        "association"
    ],
    "wof:name":"Ski-SE-Dit Val David Inc",
    "wof:placetype":"venue"
},
  "geometry": {"coordinates":[-74.2049331665,46.0316238403],"type":"Point"}
}