{
  "type": "Feature",
  "properties": {
    "addr:full":"455 Queen Charlotte Dr SE Calgary AB T2J 4H2",
    "addr:housenumber":"455",
    "addr:postcode":"t2j 4h2",
    "addr:street":"Queen Charlotte Dr Se",
    "iso:country":"CA",
    "sg:address":"455 Queen Charlotte Dr SE",
    "sg:city":"Calgary",
    "sg:classifiers":[
        {
            "category":"Building & Trades",
            "subcategory":"Landscaping Services",
            "type":"Services"
        }
    ],
    "sg:phone":"+1 403 278 0441",
    "sg:postcode":"T2J 4H2",
    "sg:province":"AB",
    "sg:tags":[
        "landscape",
        "contractor"
    ],
    "wof:name":"Gino's Landscaping & Constr",
    "wof:placetype":"venue"
},
  "geometry": {"coordinates":[-114.025024414,50.9363594055],"type":"Point"}
}