{
  "type": "Feature",
  "properties": {
    "addr:full":"Saint-Laurent QC H4L 1Y2",
    "addr:postcode":"h4l 1y2",
    "iso:country":"CA",
    "sg:city":"Saint-Laurent",
    "sg:classifiers":[
        {
            "category":"Health Services",
            "subcategory":"Doctor",
            "type":"Services"
        }
    ],
    "sg:phone":"+1 514 748 8702",
    "sg:postcode":"H4L 1Y2",
    "sg:province":"QC",
    "sg:tags":[
        "dentist"
    ],
    "wof:name":"Clinique Dentaire Tawfik",
    "wof:placetype":"venue"
},
  "geometry": {"coordinates":[-73.673965,45.521355],"type":"Point"}
}