{
  "type": "Feature",
  "properties": {
    "addr:full":"Saskatoon SK S7K 4Z6",
    "addr:postcode":"s7k 4z6",
    "iso:country":"CA",
    "sg:city":"Saskatoon",
    "sg:classifiers":[
        {
            "category":"Wholesale",
            "subcategory":"Auto Parts",
            "type":"Manufacturing & Wholesale Goods"
        }
    ],
    "sg:phone":"+1 306 934 5838",
    "sg:postcode":"S7K 4Z6",
    "sg:province":"SK",
    "sg:tags":[
        "repairing",
        "automobile",
        "rebuilt"
    ],
    "wof:name":"Adam's Active Auto Wrecking",
    "wof:placetype":"venue"
},
  "geometry": {"coordinates":[-106.657402039,52.1751670837],"type":"Point"}
}