{
  "type": "Feature",
  "properties": {
    "addr:full":"403 Dufferin Row Saint John NB E2M 2J9",
    "addr:housenumber":"403",
    "addr:postcode":"e2m 2j9",
    "addr:street":"Dufferin Row",
    "iso:country":"CA",
    "sg:address":"403 Dufferin Row",
    "sg:city":"Saint John",
    "sg:classifiers":[
        {
            "category":"Food & Beverages",
            "subcategory":"Groceries & Convenience Stores",
            "type":"Retail Goods"
        }
    ],
    "sg:phone":"+1 506 634 0827",
    "sg:postcode":"E2M 2J9",
    "sg:province":"NB",
    "wof:name":"Martello Convenience",
    "wof:placetype":"venue"
},
  "geometry": {"coordinates":[-66.073982,45.252186],"type":"Point"}
}