{
  "type": "Feature",
  "properties": {
    "addr:full":"620 Alden Rd Markham ON L3R 9R7",
    "addr:housenumber":"620",
    "addr:postcode":"l3r 9r7",
    "addr:street":"Alden Rd",
    "iso:country":"CA",
    "sg:address":"620 Alden Rd",
    "sg:city":"Markham",
    "sg:classifiers":[
        {
            "category":"Professional",
            "subcategory":"Advertising",
            "type":"Services"
        }
    ],
    "sg:phone":"+1 905 946 1122",
    "sg:postcode":"L3R 9R7",
    "sg:province":"ON",
    "wof:name":"Capital Networks Ltd",
    "wof:placetype":"venue"
},
  "geometry": {"coordinates":[-79.331024,43.837372],"type":"Point"}
}