{
  "type": "Feature",
  "properties": {
    "addr:full":"1150 Richter St Kelowna BC V1Y 2K7",
    "addr:housenumber":"1150",
    "addr:postcode":"v1y 2k7",
    "addr:street":"Richter St",
    "iso:country":"CA",
    "sg:address":"1150 Richter St",
    "sg:city":"Kelowna",
    "sg:classifiers":[
        {
            "category":"Shopping",
            "subcategory":"Used Merchandise",
            "type":"Retail Goods"
        }
    ],
    "sg:phone":"+1 250 763 6540",
    "sg:postcode":"V1Y 2K7",
    "sg:province":"BC",
    "sg:tags":[
        "pawnbroker"
    ],
    "wof:name":"Money Mikes",
    "wof:placetype":"venue"
},
  "geometry": {"coordinates":[-119.488617,49.894371],"type":"Point"}
}