{
  "type": "Feature",
  "properties": {
    "addr:full":"Ottawa ON K1P 6L2",
    "addr:postcode":"k1p 6l2",
    "iso:country":"CA",
    "sg:city":"Ottawa",
    "sg:classifiers":[
        {
            "category":"Government",
            "subcategory":"Office",
            "type":"Public Place"
        }
    ],
    "sg:phone":"+1 613 563 8206",
    "sg:postcode":"K1P 6L2",
    "sg:province":"ON",
    "sg:tags":[
        "federal",
        "affairs"
    ],
    "wof:name":"Embassy of Ecuador",
    "wof:placetype":"venue"
},
  "geometry": {"coordinates":[-75.691879,45.421478],"type":"Point"}
}