{
  "type": "Feature",
  "properties": {
    "iso:country":"CA",
    "sg:address":"460 Rue Eveline",
    "sg:city":"Laval",
    "sg:classifiers":[
        {
            "category":"Building & Trades",
            "subcategory":"Construction",
            "type":"Services"
        }
    ],
    "sg:phone":"+1 450 625 8403",
    "sg:postcode":"H7P 2V5",
    "sg:province":"QC",
    "sg:tags":[
        "roofing",
        "contractor"
    ],
    "wof:name":"Couvreur Vimont & Fils",
    "wof:placetype":"venue"
},
  "geometry": {"coordinates":[-73.79136657710001,45.5767555237],"type":"Point"}
}