{
  "type": "Feature",
  "properties": {
    "addr:full":"8795 Keele St Concord ON L4K 2N1",
    "addr:housenumber":"8795",
    "addr:postcode":"l4k 2n1",
    "addr:street":"Keele St",
    "iso:country":"CA",
    "sg:address":"8795 Keele St",
    "sg:city":"Concord",
    "sg:classifiers":[
        {
            "category":"Organizations",
            "subcategory":"Religious Organization",
            "type":"Services"
        }
    ],
    "sg:phone":"+1 905 669 9842",
    "sg:postcode":"L4K 2N1",
    "sg:province":"ON",
    "sg:tags":[
        "church"
    ],
    "wof:name":"Zion Lutheran Church",
    "wof:placetype":"venue"
},
  "geometry": {"coordinates":[-79.50561500000001,43.825905],"type":"Point"}
}