{
  "type": "Feature",
  "properties": {
    "iso:country":"CA",
    "sg:address":"5417 Burnett Rd",
    "sg:city":"Sechelt",
    "sg:classifiers":[
        {
            "category":"Wholesale",
            "subcategory":"Construction Materials",
            "type":"Manufacturing & Wholesale Goods"
        }
    ],
    "sg:phone":"+1 604 885 9666",
    "sg:postcode":"V0N 3A4",
    "sg:province":"BC",
    "sg:tags":[
        "concrete",
        "product"
    ],
    "wof:name":"Swanson's Ready Mix",
    "wof:placetype":"venue"
},
  "geometry": {"coordinates":[-123.73878479,49.5007286072],"type":"Point"}
}