{
  "type": "Feature",
  "properties": {
    "iso:country":"CA",
    "sg:address":"2750 Boul Laframboise",
    "sg:city":"Saint-Hyacinthe",
    "sg:classifiers":[
        {
            "category":"Organizations",
            "subcategory":"Labor Organization",
            "type":"Services"
        }
    ],
    "sg:phone":"+1 450 778 2007",
    "sg:postcode":"J2S 4Y8",
    "sg:province":"QC",
    "wof:name":"Syndicat Des Employes Generaux",
    "wof:placetype":"venue"
},
  "geometry": {"coordinates":[-72.95951100000001,45.633362],"type":"Point"}
}