{
  "type": "Feature",
  "properties": {
    "addr:full":"113 2nd Ave E Eatonia SK S0L 0Y0",
    "addr:housenumber":"113",
    "addr:postcode":"s0l 0y0",
    "addr:street":"2Nd Ave E Eatonia",
    "iso:country":"CA",
    "sg:address":"113 2nd Ave E",
    "sg:city":"Eatonia",
    "sg:classifiers":[
        {
            "category":"Organizations",
            "subcategory":"Religious Organization",
            "type":"Services"
        }
    ],
    "sg:phone":"+1 306 967 2210",
    "sg:postcode":"S0L 0Y0",
    "sg:province":"SK",
    "sg:tags":[
        "church"
    ],
    "wof:name":"St Pauls Lutheran Church",
    "wof:placetype":"venue"
},
  "geometry": {"coordinates":[-109.389266968,51.2211494446],"type":"Point"}
}