{
  "type": "Feature",
  "properties": {
    "addr:full":"4812 50 Ave Camrose AB T4V 0R9",
    "addr:housenumber":"4812",
    "addr:postcode":"t4v 0r9",
    "addr:street":"50 Ave",
    "iso:country":"CA",
    "sg:address":"4812 50 Ave",
    "sg:city":"Camrose",
    "sg:classifiers":[
        {
            "category":"Professional",
            "subcategory":"Accounting & Tax Preparation",
            "type":"Services"
        }
    ],
    "sg:phone":"+1 780 672 0796",
    "sg:postcode":"T4V 0R9",
    "sg:province":"AB",
    "sg:tags":[
        "accountant"
    ],
    "wof:name":"Lewsaw, Larry CA",
    "wof:placetype":"venue"
},
  "geometry": {"coordinates":[-112.82210499999999,53.022152],"type":"Point"}
}