{
  "type": "Feature",
  "properties": {
    "addr:full":"19400 Av Cruickshank Baie-D'Urfe QC H9X 3P1",
    "addr:housenumber":"19400",
    "addr:postcode":"h9x 3p1",
    "addr:street":"Av Cruickshank Baie-D'Urfe",
    "iso:country":"CA",
    "sg:address":"19400 Av Cruickshank",
    "sg:city":"Baie-D'Urfe",
    "sg:classifiers":[
        {
            "category":"Manufacturing",
            "subcategory":"Tools & Machinery",
            "type":"Manufacturing & Wholesale Goods"
        }
    ],
    "sg:phone":"+1 514 457 6485",
    "sg:postcode":"H9X 3P1",
    "sg:province":"QC",
    "sg:tags":[
        "machine",
        "shop"
    ],
    "wof:name":"Atelier D'Usinage Fj Ltee",
    "wof:placetype":"venue"
},
  "geometry": {"coordinates":[-73.90473900000001,45.42878],"type":"Point"}
}