{
  "type": "Feature",
  "properties": {
    "iso:country":"CA",
    "sg:address":"32 DE L Arena",
    "sg:city":"Chute-Aux-Outardes",
    "sg:classifiers":[
        {
            "category":"Arena",
            "subcategory":"Sports Club",
            "type":"Entertainment"
        }
    ],
    "sg:phone":"+1 418 567 2624",
    "sg:postcode":"G0H 1C0",
    "sg:province":"QC",
    "sg:tags":[
        "athletic",
        "fields",
        "stadium",
        "government"
    ],
    "wof:name":"Chute Aux Outardes Arena",
    "wof:placetype":"venue"
},
  "geometry": {"coordinates":[-68.3963012695,49.1254653931],"type":"Point"}
}