{
  "type": "Feature",
  "properties": {
    "addr:full":"4794 Bank St Gloucester ON K1T 3W7",
    "addr:housenumber":"4794",
    "addr:postcode":"k1t 3w7",
    "addr:street":"Bank St",
    "iso:country":"CA",
    "sg:address":"4794 Bank St",
    "sg:city":"Gloucester",
    "sg:classifiers":[
        {
            "category":"Manufacturing",
            "subcategory":"Building Materials",
            "type":"Manufacturing & Wholesale Goods"
        }
    ],
    "sg:phone":"+1 613 822 8787",
    "sg:postcode":"K1T 3W7",
    "sg:province":"ON",
    "sg:tags":[
        "truss"
    ],
    "wof:name":"Superior Roof Truss",
    "wof:placetype":"venue"
},
  "geometry": {"coordinates":[-75.591309,45.315891],"type":"Point"}
}