{
  "type": "Feature",
  "properties": {
    "addr:full":"103 High St Vankleek Hill ON K0B 1R0",
    "addr:housenumber":"103",
    "addr:postcode":"k0b 1r0",
    "addr:street":"High St",
    "iso:country":"CA",
    "sg:address":"103 High St",
    "sg:city":"Vankleek Hill",
    "sg:classifiers":[
        {
            "category":"Retail",
            "subcategory":"Funeral Services",
            "type":"Services"
        }
    ],
    "sg:phone":"+1 613 678 3000",
    "sg:postcode":"K0B 1R0",
    "sg:province":"ON",
    "sg:tags":[
        "director"
    ],
    "wof:name":"Salon Funeraire Berthiaume",
    "wof:placetype":"venue"
},
  "geometry": {"coordinates":[-74.654701,45.515793],"type":"Point"}
}