{
  "type": "Feature",
  "properties": {
    "addr:full":"10211 Boul Saint-Laurent Montreal QC H3L 2N5",
    "addr:housenumber":"10211",
    "addr:postcode":"h3l 2n5",
    "addr:street":"Boul Saint-Laurent",
    "iso:country":"CA",
    "sg:address":"10211 Boul Saint-Laurent",
    "sg:city":"Montreal",
    "sg:classifiers":[
        {
            "category":"Professional",
            "subcategory":"Art Services",
            "type":"Services"
        }
    ],
    "sg:phone":"+1 514 383 2989",
    "sg:postcode":"H3L 2N5",
    "sg:province":"QC",
    "sg:tags":[
        "artist"
    ],
    "wof:name":"Emmanuel Claudais Enr",
    "wof:placetype":"venue"
},
  "geometry": {"coordinates":[-73.663589,45.54826],"type":"Point"}
}