{
  "type": "Feature",
  "properties": {
    "addr:full":"1114 Central Ave Prince Albert SK S6V 4V6",
    "addr:housenumber":"1114",
    "addr:postcode":"s6v 4v6",
    "addr:street":"Central Ave",
    "iso:country":"CA",
    "sg:address":"1114 Central Ave",
    "sg:city":"Prince Albert",
    "sg:classifiers":[
        {
            "category":"Shopping",
            "type":"Retail Goods"
        }
    ],
    "sg:phone":"+1 306 763 8350",
    "sg:postcode":"S6V 4V6",
    "sg:province":"SK",
    "sg:tags":[
        "wedding",
        "supply"
    ],
    "wof:name":"Celebrations By Design",
    "wof:placetype":"venue"
},
  "geometry": {"coordinates":[-105.75404399999999,53.202873],"type":"Point"}
}