{
  "type": "Feature",
  "properties": {
    "addr:full":"3655 3rd Ave W Vancouver BC V6R 1M1",
    "addr:housenumber":"3655",
    "addr:postcode":"v6r 1m1",
    "addr:street":"3Rd Ave W",
    "iso:country":"CA",
    "sg:address":"3655 3rd Ave W",
    "sg:city":"Vancouver",
    "sg:classifiers":[
        {
            "category":"Real Estate",
            "subcategory":"Real Estate Agent",
            "type":"Services"
        }
    ],
    "sg:phone":"+1 604 681 2929",
    "sg:postcode":"V6R 1M1",
    "sg:province":"BC",
    "sg:tags":[
        "appraiser"
    ],
    "wof:name":"Watson Clee & Assoc",
    "wof:placetype":"venue"
},
  "geometry": {"coordinates":[-123.18466949499999,49.2696304321],"type":"Point"}
}