{
  "type": "Feature",
  "properties": {
    "iso:country":"CA",
    "sg:address":"3160 Norland Ave",
    "sg:city":"Burnaby",
    "sg:classifiers":[
        {
            "category":"Retail",
            "subcategory":"Laundry & Dry Cleaning",
            "type":"Services"
        }
    ],
    "sg:phone":"+1 604 473 9190",
    "sg:postcode":"V5B 3A6",
    "sg:province":"BC",
    "sg:tags":[
        "cleaners",
        "rug",
        "carpet"
    ],
    "wof:name":"B C Wide Carpet & Furnace",
    "wof:placetype":"venue"
},
  "geometry": {"coordinates":[-122.97544860799999,49.2554931641],"type":"Point"}
}