{
  "type": "Feature",
  "properties": {
    "iso:country":"CA",
    "sg:address":"RR 4 STN Main",
    "sg:city":"Lindsay",
    "sg:classifiers":[
        {
            "category":"Wholesale",
            "subcategory":"Farm Supplies",
            "type":"Manufacturing & Wholesale Goods"
        }
    ],
    "sg:phone":"+1 705 324 3085",
    "sg:postcode":"K9V 4R4",
    "sg:province":"ON",
    "sg:tags":[
        "livestock"
    ],
    "wof:name":"DE Mc Morrow Livestock Ex",
    "wof:placetype":"venue"
},
  "geometry": {"coordinates":[-78.74006652830001,44.3542861938],"type":"Point"}
}