{
  "type": "Feature",
  "properties": {
    "addr:full":"Calgary AB T2N 2T8",
    "addr:postcode":"t2n 2t8",
    "iso:country":"CA",
    "sg:city":"Calgary",
    "sg:classifiers":[
        {
            "category":"Health Services",
            "subcategory":"Doctor",
            "type":"Services"
        }
    ],
    "sg:phone":"+1 403 283 1241",
    "sg:postcode":"T2N 2T8",
    "sg:province":"AB",
    "sg:tags":[
        "physician",
        "surgeon"
    ],
    "wof:name":"Farnells, R B MD",
    "wof:placetype":"venue"
},
  "geometry": {"coordinates":[-114.133514404,51.0625534058],"type":"Point"}
}