{
  "type": "Feature",
  "properties": {
    "iso:country":"CA",
    "sg:city":"Vancouver",
    "sg:classifiers":[
        {
            "category":"Travel",
            "subcategory":"Travel Agent",
            "type":"Entertainment"
        }
    ],
    "sg:phone":"+1 604 681 9747",
    "sg:postcode":"V6B 1L8",
    "sg:province":"BC",
    "sg:tags":[
        "agency",
        "bureau"
    ],
    "wof:name":"Canada Tour Systems Inc",
    "wof:placetype":"venue"
},
  "geometry": {"coordinates":[-123.1121521,49.284034729],"type":"Point"}
}