{
  "type": "Feature",
  "properties": {
    "iso:country":"CA",
    "sg:city":"Montreal",
    "sg:classifiers":[
        {
            "category":"Personal",
            "subcategory":"Beauty Salon",
            "type":"Services"
        }
    ],
    "sg:phone":"+1 514 845 4454",
    "sg:postcode":"H3B 1H9",
    "sg:province":"QC",
    "wof:name":"O Bleu Coiffure Esthetique",
    "wof:placetype":"venue"
},
  "geometry": {"coordinates":[-73.5570449829,45.5177192688],"type":"Point"}
}