{
  "type": "Feature",
  "properties": {
    "addr:full":"129 Hampton Rd Rothesay NB E2E 2N7",
    "addr:housenumber":"129",
    "addr:postcode":"e2e 2n7",
    "addr:street":"Hampton Rd",
    "iso:country":"CA",
    "sg:address":"129 Hampton Rd",
    "sg:city":"Rothesay",
    "sg:classifiers":[
        {
            "category":"Insurance",
            "subcategory":"Insurance Agent",
            "type":"Services"
        }
    ],
    "sg:phone":"+1 506 847 7505",
    "sg:postcode":"E2E 2N7",
    "sg:province":"NB",
    "wof:name":"C S Branch Insurance Ltd",
    "wof:placetype":"venue"
},
  "geometry": {"coordinates":[-65.979095,45.399193],"type":"Point"}
}