{
  "type": "Feature",
  "properties": {
    "addr:full":"1648 1/2 Queen St W Toronto ON M6R 1B2",
    "addr:housenumber":"1648 1 / 2",
    "addr:postcode":"m6r 1b2",
    "addr:street":"Queen St W",
    "iso:country":"CA",
    "sg:address":"1648 1/2 Queen St W",
    "sg:city":"Toronto",
    "sg:classifiers":[
        {
            "category":"Restaurant",
            "type":"Food & Drink"
        }
    ],
    "sg:phone":"+1 416 537 2222",
    "sg:postcode":"M6R 1B2",
    "sg:province":"ON",
    "sg:tags":[
        "out"
    ],
    "wof:name":"Amico's Pizza",
    "wof:placetype":"venue"
},
  "geometry": {"coordinates":[-79.443192,43.639435],"type":"Point"}
}