{
  "type": "Feature",
  "properties": {
    "addr:full":"650 Flora Ave Winnipeg MB R2W 2S5",
    "addr:housenumber":"650",
    "addr:postcode":"r2w 2s5",
    "addr:street":"Flora Ave",
    "iso:country":"CA",
    "sg:address":"650 Flora Ave",
    "sg:city":"Winnipeg",
    "sg:classifiers":[
        {
            "category":"Education",
            "subcategory":"School",
            "type":"Public Place"
        }
    ],
    "sg:phone":"+1 204 582 5698",
    "sg:postcode":"R2W 2S5",
    "sg:province":"MB",
    "wof:name":"Immaculate Heart-Mary School",
    "wof:placetype":"venue"
},
  "geometry": {"coordinates":[-97.15134429930001,49.9166412354],"type":"Point"}
}