{
  "type": "Feature",
  "properties": {
    "iso:country":"CA",
    "sg:address":"95 Wharncliffe Rd S",
    "sg:city":"London",
    "sg:classifiers":[
        {
            "category":"Retail",
            "subcategory":"Veterinary Services",
            "type":"Services"
        }
    ],
    "sg:phone":"+1 519 434 4882",
    "sg:postcode":"N6J 2K2",
    "sg:province":"ON",
    "sg:tags":[
        "veterinarian"
    ],
    "wof:name":"Blue Cross Animal Hospital",
    "wof:placetype":"venue"
},
  "geometry": {"coordinates":[-81.262352,42.975216],"type":"Point"}
}