{
  "type": "Feature",
  "properties": {
    "iso:country":"CA",
    "sg:address":"8828 95 St NW",
    "sg:city":"Edmonton",
    "sg:classifiers":[
        {
            "category":"Education",
            "subcategory":"Special Training",
            "type":"Public Place"
        }
    ],
    "sg:phone":"+1 780 440 9373",
    "sg:postcode":"T6C 4H9",
    "sg:province":"AB",
    "sg:tags":[
        "instruction",
        "music"
    ],
    "wof:name":"Centre DE Devloppement",
    "wof:placetype":"venue"
},
  "geometry": {"coordinates":[-113.473312378,53.5240936279],"type":"Point"}
}