{
  "type": "Feature",
  "properties": {
    "addr:full":"6204 2 St SE Calgary AB T2H 1J4",
    "addr:housenumber":"6204 2",
    "addr:postcode":"t2h 1j4",
    "addr:street":"St Se",
    "iso:country":"CA",
    "sg:address":"6204 2 St SE",
    "sg:city":"Calgary",
    "sg:classifiers":[
        {
            "category":"Wholesale",
            "subcategory":"Construction Materials",
            "type":"Manufacturing & Wholesale Goods"
        }
    ],
    "sg:phone":"+1 403 259 5155",
    "sg:postcode":"T2H 1J4",
    "sg:province":"AB",
    "sg:tags":[
        "fence"
    ],
    "wof:name":"Phoenix Fence Ltd",
    "wof:placetype":"venue"
},
  "geometry": {"coordinates":[-114.059875488,50.996295929],"type":"Point"}
}