{
  "type": "Feature",
  "properties": {
    "addr:full":"534 Sargent Ave Winnipeg MB R3B 1W2",
    "addr:housenumber":"534",
    "addr:postcode":"r3b 1w2",
    "addr:street":"Sargent Ave",
    "iso:country":"CA",
    "sg:address":"534 Sargent Ave",
    "sg:city":"Winnipeg",
    "sg:classifiers":[
        {
            "category":"Restaurant",
            "type":"Food & Drink"
        }
    ],
    "sg:phone":"+1 204 774 8888",
    "sg:postcode":"R3B 1W2",
    "sg:province":"MB",
    "wof:name":"Thanh Huong Restaurant",
    "wof:placetype":"venue"
},
  "geometry": {"coordinates":[-97.15543365480001,49.8963012695],"type":"Point"}
}