{
  "type": "Feature",
  "properties": {
    "addr:full":"11 Rue Notre Dame Oka QC J0N 1E0",
    "addr:housenumber":"11",
    "addr:postcode":"j0n 1e0",
    "addr:street":"Rue Notre Dame",
    "iso:country":"CA",
    "sg:address":"11 Rue Notre Dame",
    "sg:city":"Oka",
    "sg:classifiers":[
        {
            "category":"Food & Beverages",
            "subcategory":"Groceries & Convenience Stores",
            "type":"Retail Goods"
        }
    ],
    "sg:phone":"+1 450 479 1797",
    "sg:postcode":"J0N 1E0",
    "sg:province":"QC",
    "wof:name":"Depanneur A L'Entree Du Vllge",
    "wof:placetype":"venue"
},
  "geometry": {"coordinates":[-74.07770499999999,45.466667],"type":"Point"}
}