{
  "type": "Feature",
  "properties": {
    "addr:full":"8415 Rue Lafrenaie Saint-Leonard QC H1P 2B3",
    "addr:housenumber":"8415",
    "addr:postcode":"h1p 2b3",
    "addr:street":"Rue Lafrenaie",
    "iso:country":"CA",
    "sg:address":"8415 Rue Lafrenaie",
    "sg:city":"Saint-Leonard",
    "sg:classifiers":[
        {
            "category":"Wholesale",
            "subcategory":"Groceries",
            "type":"Manufacturing & Wholesale Goods"
        }
    ],
    "sg:phone":"+1 514 324 8039",
    "sg:postcode":"H1P 2B3",
    "sg:province":"QC",
    "sg:tags":[
        "baker"
    ],
    "wof:name":"Patisserie Lafrenaie Inc",
    "wof:placetype":"venue"
},
  "geometry": {"coordinates":[-73.586929,45.598721],"type":"Point"}
}