{
  "type": "Feature",
  "properties": {
    "addr:full":"338 Church St Oakville ON L6J 1P1",
    "addr:housenumber":"338",
    "addr:postcode":"l6j 1p1",
    "addr:street":"Church St",
    "iso:country":"CA",
    "sg:address":"338 Church St",
    "sg:city":"Oakville",
    "sg:classifiers":[
        {
            "category":"Personal",
            "subcategory":"Beauty Salon",
            "type":"Services"
        }
    ],
    "sg:phone":"+1 905 337 1713",
    "sg:postcode":"L6J 1P1",
    "sg:province":"ON",
    "wof:name":"Paul Anthony Salon",
    "wof:placetype":"venue"
},
  "geometry": {"coordinates":[-79.6660690308,43.4488296509],"type":"Point"}
}