{
  "type": "Feature",
  "properties": {
    "iso:country":"CA",
    "sg:address":"Sparks St S",
    "sg:city":"Magnetawan",
    "sg:classifiers":[
        {
            "category":"Organizations",
            "subcategory":"Religious Organization",
            "type":"Services"
        }
    ],
    "sg:phone":"+1 705 387 4882",
    "sg:postcode":"P0A 1P0",
    "sg:province":"ON",
    "sg:tags":[
        "church"
    ],
    "wof:name":"Knox Presbyterian Church",
    "wof:placetype":"venue"
},
  "geometry": {"coordinates":[-79.6412887573,45.6609992981],"type":"Point"}
}