{
  "type": "Feature",
  "properties": {
    "addr:full":"1394 Erin St Winnipeg MB R3E 2S8",
    "addr:housenumber":"1394",
    "addr:postcode":"r3e 2s8",
    "addr:street":"Erin St",
    "iso:country":"CA",
    "sg:address":"1394 Erin St",
    "sg:city":"Winnipeg",
    "sg:classifiers":[
        {
            "category":"Building & Trades",
            "subcategory":"Plumbing",
            "type":"Services"
        }
    ],
    "sg:phone":"+1 204 786 1776",
    "sg:postcode":"R3E 2S8",
    "sg:province":"MB",
    "sg:tags":[
        "conditioning",
        "air",
        "system",
        "refrigerating",
        "contractor"
    ],
    "wof:name":"K-Mar Refrigeration Ltd",
    "wof:placetype":"venue"
},
  "geometry": {"coordinates":[-97.184029,49.901218],"type":"Point"}
}