{
  "type": "Feature",
  "properties": {
    "addr:full":"1752 Island Hwy Victoria BC V9B 1H8",
    "addr:housenumber":"1752",
    "addr:postcode":"v9b 1h8",
    "addr:street":"Island Hwy",
    "iso:country":"CA",
    "sg:address":"1752 Island Hwy",
    "sg:city":"Victoria",
    "sg:classifiers":[
        {
            "category":"Restaurant",
            "type":"Food & Drink"
        }
    ],
    "sg:phone":"+1 250 391 8648",
    "sg:postcode":"V9B 1H8",
    "sg:province":"BC",
    "wof:name":"Jasmine's Restaurant",
    "wof:placetype":"venue"
},
  "geometry": {"coordinates":[-123.364517212,48.428314209],"type":"Point"}
}