{
  "type": "Feature",
  "properties": {
    "iso:country":"CA",
    "sg:address":"1491 Richmond Rd",
    "sg:city":"Ottawa",
    "sg:classifiers":[
        {
            "category":"Manufacturing",
            "subcategory":"Metals",
            "type":"Manufacturing & Wholesale Goods"
        }
    ],
    "sg:phone":"+1 613 596 3802",
    "sg:postcode":"K2B 6R9",
    "sg:province":"ON",
    "sg:tags":[
        "cashing",
        "mail",
        "check"
    ],
    "wof:name":"Money Mart Cheque Cashing Ctr",
    "wof:placetype":"venue"
},
  "geometry": {"coordinates":[-75.79099273680001,45.3623161316],"type":"Point"}
}