{
  "type": "Feature",
  "properties": {
    "iso:country":"CA",
    "sg:address":"5991 Alderbridge Way",
    "sg:city":"Richmond",
    "sg:classifiers":[
        {
            "category":"Restaurant",
            "type":"Food & Drink"
        }
    ],
    "sg:phone":"+1 604 270 2266",
    "sg:postcode":"V6X 4C5",
    "sg:province":"BC",
    "wof:name":"Foggy Dew Irish Pub",
    "wof:placetype":"venue"
},
  "geometry": {"coordinates":[-123.144699097,49.172039032],"type":"Point"}
}