{
  "type": "Feature",
  "properties": {
    "addr:full":"17 Whelan Ave Mount Pearl NL A1N 2S7",
    "addr:housenumber":"17",
    "addr:postcode":"a1n 2s7",
    "addr:street":"Whelan Ave",
    "iso:country":"CA",
    "sg:address":"17 Whelan Ave",
    "sg:city":"Mount Pearl",
    "sg:classifiers":[
        {
            "category":"Building & Trades",
            "subcategory":"Construction",
            "type":"Services"
        }
    ],
    "sg:phone":"+1 709 368 3412",
    "sg:postcode":"A1N 2S7",
    "sg:province":"NL",
    "sg:tags":[
        "masonry",
        "contractor"
    ],
    "wof:name":"Hunt's Masonry Ltd",
    "wof:placetype":"venue"
},
  "geometry": {"coordinates":[-52.8093986511,47.5098838806],"type":"Point"}
}