{
  "type": "Feature",
  "properties": {
    "addr:full":"33 Capilano Way New Westminster BC V3L 5G3",
    "addr:housenumber":"33",
    "addr:postcode":"v3l 5g3",
    "addr:street":"Capilano Way",
    "iso:country":"CA",
    "sg:address":"33 Capilano Way",
    "sg:city":"New Westminster",
    "sg:classifiers":[
        {
            "category":"Restaurant",
            "type":"Food & Drink"
        }
    ],
    "sg:phone":"+1 604 522 3078",
    "sg:postcode":"V3L 5G3",
    "sg:province":"BC",
    "sg:tags":[
        "sandwich"
    ],
    "wof:name":"Deli-Fresh",
    "wof:placetype":"venue"
},
  "geometry": {"coordinates":[-122.884438,49.225159],"type":"Point"}
}