{
  "type": "Feature",
  "properties": {
    "addr:full":"Armstrong BC V0E 1B2",
    "addr:postcode":"v0e 1b2",
    "iso:country":"CA",
    "sg:city":"Armstrong",
    "sg:classifiers":[
        {
            "category":"Shopping",
            "subcategory":"Computers & Home Electronics",
            "type":"Retail Goods"
        }
    ],
    "sg:phone":"+1 250 546 8544",
    "sg:postcode":"V0E 1B2",
    "sg:province":"BC",
    "sg:tags":[
        "equipment",
        "dealer"
    ],
    "wof:name":"Computer Solutions",
    "wof:placetype":"venue"
},
  "geometry": {"coordinates":[-119.216179,50.40086],"type":"Point"}
}