{
  "type": "Feature",
  "properties": {
    "iso:country":"CA",
    "sg:address":"243 St. James St",
    "sg:city":"Thunder Bay",
    "sg:classifiers":[
        {
            "category":"Social Services",
            "subcategory":"Child Care",
            "type":"Services"
        }
    ],
    "sg:phone":"+1 807 344 8719",
    "sg:postcode":"P7A 3P1",
    "sg:province":"ON",
    "wof:name":"Schoolhouse Playcare Ctr",
    "wof:placetype":"venue"
},
  "geometry": {"coordinates":[-89.213516,48.441734],"type":"Point"}
}