{
  "type": "Feature",
  "properties": {
    "addr:full":"51 Metropolitan Ave Lower Sackville NS B4C 3Z6",
    "addr:housenumber":"51",
    "addr:postcode":"b4c 3z6",
    "addr:street":"Metropolitan Ave",
    "iso:country":"CA",
    "sg:address":"51 Metropolitan Ave",
    "sg:city":"Lower Sackville",
    "sg:classifiers":[
        {
            "category":"Organizations",
            "subcategory":"Religious Organization",
            "type":"Services"
        }
    ],
    "sg:phone":"+1 902 865 8010",
    "sg:postcode":"B4C 3Z6",
    "sg:province":"NS",
    "sg:tags":[
        "church"
    ],
    "wof:name":"Salvation Army",
    "wof:placetype":"venue"
},
  "geometry": {"coordinates":[-63.6748809814,44.7772827148],"type":"Point"}
}