{
  "type": "Feature",
  "properties": {
    "addr:full":"467 Boul Sainte-Anne Sainte-Anne-Des-Plaines QC J0N 1H0",
    "addr:housenumber":"467",
    "addr:postcode":"j0n 1h0",
    "addr:street":"Boul Sainte-Anne",
    "iso:country":"CA",
    "sg:address":"467 Boul Sainte-Anne",
    "sg:city":"Sainte-Anne-Des-Plaines",
    "sg:classifiers":[
        {
            "category":"Wholesale",
            "subcategory":"Non-durable Goods",
            "type":"Manufacturing & Wholesale Goods"
        }
    ],
    "sg:phone":"+1 450 478 3043",
    "sg:postcode":"J0N 1H0",
    "sg:province":"QC",
    "sg:tags":[
        "water"
    ],
    "wof:name":"Cyr Eau-Sante Inc",
    "wof:placetype":"venue"
},
  "geometry": {"coordinates":[-73.81444500000001,45.760204],"type":"Point"}
}