{
  "type": "Feature",
  "properties": {
    "addr:full":"4780 Roger St Port Alberni BC V9Y 3Z2",
    "addr:housenumber":"4780",
    "addr:postcode":"v9y 3z2",
    "addr:street":"Roger St",
    "iso:country":"CA",
    "sg:address":"4780 Roger St",
    "sg:city":"Port Alberni",
    "sg:classifiers":[
        {
            "category":"Government",
            "subcategory":"Office",
            "type":"Public Place"
        }
    ],
    "sg:phone":"+1 250 724 3554",
    "sg:postcode":"V9Y 3Z2",
    "sg:province":"BC",
    "wof:name":"BC Mental Health Ctr",
    "wof:placetype":"venue"
},
  "geometry": {"coordinates":[-124.806442,49.254398],"type":"Point"}
}