{
  "type": "Feature",
  "properties": {
    "addr:full":"Logan Lake BC V0K 1W0",
    "addr:postcode":"v0k 1w0",
    "addr:street":"Logan",
    "iso:country":"CA",
    "sg:city":"Logan Lake",
    "sg:classifiers":[
        {
            "category":"Professional",
            "type":"Services"
        }
    ],
    "sg:phone":"+1 250 523 2349",
    "sg:postcode":"V0K 1W0",
    "sg:province":"BC",
    "sg:tags":[
        "environmental",
        "ecological",
        "establishment"
    ],
    "wof:name":"C E Jones & Assoc Ltd",
    "wof:placetype":"venue"
},
  "geometry": {"coordinates":[-120.812439,50.493656],"type":"Point"}
}