{
  "type": "Feature",
  "properties": {
    "addr:full":"Richmond BC V7C 5S7",
    "addr:postcode":"v7c 5s7",
    "iso:country":"CA",
    "sg:city":"Richmond",
    "sg:classifiers":[
        {
            "category":"Personal",
            "subcategory":"Beauty Salon",
            "type":"Services"
        }
    ],
    "sg:phone":"+1 604 270 8879",
    "sg:postcode":"V7C 5S7",
    "sg:province":"BC",
    "wof:name":"Brandee's Hair & Nail Design",
    "wof:placetype":"venue"
},
  "geometry": {"coordinates":[-123.167404175,49.1699333191],"type":"Point"}
}