{
  "type": "Feature",
  "properties": {
    "addr:full":"100 Av Principale Rouyn-Noranda QC J9X 4P2",
    "addr:postcode":"j9x 4p2",
    "addr:street":"100 Av Principale",
    "iso:country":"CA",
    "sg:address":"100 Av Principale",
    "sg:city":"Rouyn-Noranda",
    "sg:classifiers":[
        {
            "category":"Travel",
            "subcategory":"Travel Agent",
            "type":"Entertainment"
        }
    ],
    "sg:phone":"+1 819 762 0922",
    "sg:postcode":"J9X 4P2",
    "sg:province":"QC",
    "sg:tags":[
        "agency",
        "bureau"
    ],
    "wof:name":"Voyages Ricard Inc",
    "wof:placetype":"venue"
},
  "geometry": {"coordinates":[-79.020218,48.240608],"type":"Point"}
}