{
  "type": "Feature",
  "properties": {
    "addr:full":"1032 Fort St Victoria BC V8V 3K4",
    "addr:housenumber":"1032",
    "addr:postcode":"v8v 3k4",
    "addr:street":"Fort St",
    "iso:country":"CA",
    "sg:address":"1032 Fort St",
    "sg:city":"Victoria",
    "sg:classifiers":[
        {
            "category":"Shopping",
            "subcategory":"Used Merchandise",
            "type":"Retail Goods"
        }
    ],
    "sg:phone":"+1 250 386 1850",
    "sg:postcode":"V8V 3K4",
    "sg:province":"BC",
    "sg:tags":[
        "antique",
        "book",
        "rare"
    ],
    "wof:name":"Voss Art & Antiques Ltd",
    "wof:placetype":"venue"
},
  "geometry": {"coordinates":[-123.355858,48.423717],"type":"Point"}
}