{
  "type": "Feature",
  "properties": {
    "addr:full":"25 Hemlock Blvd E Strathroy ON N7G 4B9",
    "addr:housenumber":"25",
    "addr:postcode":"n7g 4b9",
    "addr:street":"Hemlock Blvd E",
    "iso:country":"CA",
    "sg:address":"25 Hemlock Blvd E",
    "sg:city":"Strathroy",
    "sg:classifiers":[
        {
            "category":"Wholesale",
            "subcategory":"Chemicals & Plastics",
            "type":"Manufacturing & Wholesale Goods"
        }
    ],
    "sg:phone":"+1 519 245 2080",
    "sg:postcode":"N7G 4B9",
    "sg:province":"ON",
    "wof:name":"Ondeo Nalco Energy Svc",
    "wof:placetype":"venue"
},
  "geometry": {"coordinates":[-81.59791564939999,42.9624862671],"type":"Point"}
}