{
  "type": "Feature",
  "properties": {
    "addr:full":"107 Rue Saint-Laurent Beauharnois QC J6N 1V8",
    "addr:housenumber":"107",
    "addr:postcode":"j6n 1v8",
    "addr:street":"Rue Saint-Laurent",
    "iso:country":"CA",
    "sg:address":"107 Rue Saint-Laurent",
    "sg:city":"Beauharnois",
    "sg:classifiers":[
        {
            "category":"Government",
            "subcategory":"Office",
            "type":"Public Place"
        }
    ],
    "sg:phone":"+1 450 429 3959",
    "sg:postcode":"J6N 1V8",
    "sg:province":"QC",
    "sg:tags":[
        "village"
    ],
    "wof:name":"Beauharnois Usines-Traitement",
    "wof:placetype":"venue"
},
  "geometry": {"coordinates":[-73.87743399999999,45.315136],"type":"Point"}
}