{
  "type": "Feature",
  "properties": {
    "addr:full":"449 Legion Dr Quesnel BC V2J 2A5",
    "addr:housenumber":"449",
    "addr:postcode":"v2j 2a5",
    "addr:street":"Legion Dr",
    "iso:country":"CA",
    "sg:address":"449 Legion Dr",
    "sg:city":"Quesnel",
    "sg:classifiers":[
        {
            "category":"Manufacturing",
            "subcategory":"Tools & Machinery",
            "type":"Manufacturing & Wholesale Goods"
        }
    ],
    "sg:phone":"+1 250 992 7259",
    "sg:postcode":"V2J 2A5",
    "sg:province":"BC",
    "sg:tags":[
        "automobile",
        "parts",
        "supply"
    ],
    "wof:name":"Taylor Automotive Supplies",
    "wof:placetype":"venue"
},
  "geometry": {"coordinates":[-122.492614746,52.9744644165],"type":"Point"}
}