{
  "type": "Feature",
  "properties": {
    "addr:full":"Whitemouth MB R0E 2G0",
    "addr:postcode":"r0e 2g0",
    "iso:country":"CA",
    "sg:city":"Whitemouth",
    "sg:classifiers":[
        {
            "category":"Health Services",
            "subcategory":"Nursing And Care Facility",
            "type":"Services"
        }
    ],
    "sg:phone":"+1 204 348 7191",
    "sg:postcode":"R0E 2G0",
    "sg:province":"MB",
    "sg:tags":[
        "personal",
        "home"
    ],
    "wof:name":"Whitemouth District Health Ctr",
    "wof:placetype":"venue"
},
  "geometry": {"coordinates":[-96.68147999999999,49.53083],"type":"Point"}
}