{
  "type": "Feature",
  "properties": {
    "addr:full":"1391 Abercrombie Rd New Glasgow NS B2H 5C6",
    "addr:housenumber":"1391",
    "addr:postcode":"b2h 5c6",
    "addr:street":"Abercrombie Rd",
    "iso:country":"CA",
    "sg:address":"1391 Abercrombie Rd",
    "sg:city":"New Glasgow",
    "sg:classifiers":[
        {
            "category":"Manufacturing",
            "subcategory":"Metals",
            "type":"Manufacturing & Wholesale Goods"
        }
    ],
    "sg:phone":"+1 902 759 6776",
    "sg:postcode":"B2H 5C6",
    "sg:province":"NS",
    "sg:tags":[
        "steel"
    ],
    "wof:name":"K & M Creative Metals",
    "wof:placetype":"venue"
},
  "geometry": {"coordinates":[-62.643414,45.591839],"type":"Point"}
}