{
  "type": "Feature",
  "properties": {
    "addr:full":"3858 Rue Principale Dunham QC J0E 1M0",
    "addr:housenumber":"3858",
    "addr:postcode":"j0e 1m0",
    "addr:street":"Rue Principale",
    "iso:country":"CA",
    "sg:address":"3858 Rue Principale",
    "sg:city":"Dunham",
    "sg:classifiers":[
        {
            "category":"Education",
            "subcategory":"School",
            "type":"Public Place"
        }
    ],
    "sg:phone":"+1 450 295 2722",
    "sg:postcode":"J0E 1M0",
    "sg:province":"QC",
    "wof:name":"Ecole DE LA Cle-Des-Champs",
    "wof:placetype":"venue"
},
  "geometry": {"coordinates":[-72.80090332029999,45.1288719177],"type":"Point"}
}