{
  "type": "Feature",
  "properties": {
    "iso:country":"CA",
    "sg:address":"140 Merton St",
    "sg:city":"Toronto",
    "sg:classifiers":[
        {
            "category":"Organizations",
            "subcategory":"Professional Association",
            "type":"Services"
        }
    ],
    "sg:phone":"+1 416 489 0146",
    "sg:postcode":"M4S 1A1",
    "sg:province":"ON",
    "wof:name":"Concerned Friends of Ontario",
    "wof:placetype":"venue"
},
  "geometry": {"coordinates":[-79.391396,43.697243],"type":"Point"}
}