{
  "type": "Feature",
  "properties": {
    "addr:full":"6957 Eighth Line W Elora ON N0B 1S0",
    "addr:housenumber":"6957",
    "addr:postcode":"n0b 1s0",
    "addr:street":"Eighth Line W",
    "iso:country":"CA",
    "sg:address":"6957 Eighth Line W",
    "sg:city":"Elora",
    "sg:classifiers":[
        {
            "category":"Farming",
            "subcategory":"Farm",
            "type":"Manufacturing & Wholesale Goods"
        }
    ],
    "sg:phone":"+1 519 669 5411",
    "sg:postcode":"N0B 1S0",
    "sg:province":"ON",
    "wof:name":"Alma Research Station",
    "wof:placetype":"venue"
},
  "geometry": {"coordinates":[-80.42974853520001,43.6815795898],"type":"Point"}
}