{
  "type": "Feature",
  "properties": {
    "addr:full":"Shippagan NB E8S 1A4",
    "addr:postcode":"e8s 1a4",
    "iso:country":"CA",
    "sg:city":"Shippagan",
    "sg:classifiers":[
        {
            "category":"Restaurant",
            "type":"Food & Drink"
        }
    ],
    "sg:phone":"+1 506 336 9704",
    "sg:postcode":"E8S 1A4",
    "sg:province":"NB",
    "wof:name":"Saigon Maxim Restaurant",
    "wof:placetype":"venue"
},
  "geometry": {"coordinates":[-64.721146,47.740349],"type":"Point"}
}