{
  "type": "Feature",
  "properties": {
    "addr:full":"2550 Goldenridge Rd # 68 Mississauga ON L4X 2S3",
    "addr:housenumber":"2550",
    "addr:postcode":"l4x 2s3",
    "addr:street":"Goldenridge Rd # 68",
    "iso:country":"CA",
    "sg:address":"2550 Goldenridge Rd # 68",
    "sg:city":"Mississauga",
    "sg:classifiers":[
        {
            "category":"Home & Garden",
            "subcategory":"Furniture",
            "type":"Retail Goods"
        }
    ],
    "sg:phone":"+1 905 281 2534",
    "sg:postcode":"L4X 2S3",
    "sg:province":"ON",
    "sg:tags":[
        "equipment",
        "kitchen",
        "cabinet"
    ],
    "wof:name":"Classic Kitchen Designs",
    "wof:placetype":"venue"
},
  "geometry": {"coordinates":[-79.572472,43.618217],"type":"Point"}
}