{
  "type": "Feature",
  "properties": {
    "addr:full":"2900 Eglinton Ave E Scarborough ON M1J 2E4",
    "addr:housenumber":"2900",
    "addr:postcode":"m1j 2e4",
    "addr:street":"Eglinton Ave E",
    "iso:country":"CA",
    "sg:address":"2900 Eglinton Ave E",
    "sg:city":"Scarborough",
    "sg:classifiers":[
        {
            "category":"Health Services",
            "subcategory":"Doctor",
            "type":"Services"
        }
    ],
    "sg:phone":"+1 416 289 6777",
    "sg:postcode":"M1J 2E4",
    "sg:province":"ON",
    "sg:tags":[
        "physician",
        "surgeon"
    ],
    "wof:name":"Hirsch, Andrei MD",
    "wof:placetype":"venue"
},
  "geometry": {"coordinates":[-79.23616027830001,43.7395095825],"type":"Point"}
}