{
  "type": "Feature",
  "properties": {
    "addr:full":"8171 Ackroyd Rd #1910 Richmond BC V6X 3K1",
    "addr:housenumber":"8171",
    "addr:postcode":"v6x 3k1",
    "addr:street":"Ackroyd Rd # 1910",
    "iso:country":"CA",
    "sg:address":"8171 Ackroyd Rd #1910",
    "sg:city":"Richmond",
    "sg:classifiers":[
        {
            "category":"Health Services",
            "subcategory":"Health Practitioner",
            "type":"Services"
        }
    ],
    "sg:phone":"+1 604 278 5628",
    "sg:postcode":"V6X 3K1",
    "sg:province":"BC",
    "sg:tags":[
        "physiotherapist"
    ],
    "wof:name":"Ackroyd Physiotherapy Ctr",
    "wof:placetype":"venue"
},
  "geometry": {"coordinates":[-123.134308,49.17218],"type":"Point"}
}