{
  "type": "Feature",
  "properties": {
    "addr:full":"200 Main St Plaster Rock NB E7G 2E2",
    "addr:housenumber":"200",
    "addr:postcode":"e7g 2e2",
    "addr:street":"Main St",
    "iso:country":"CA",
    "sg:address":"200 Main St",
    "sg:city":"Plaster Rock",
    "sg:classifiers":[
        {
            "category":"Insurance",
            "subcategory":"Insurance Agent",
            "type":"Services"
        }
    ],
    "sg:phone":"+1 506 356 8833",
    "sg:postcode":"E7G 2E2",
    "sg:province":"NB",
    "wof:name":"Shaw Insurance",
    "wof:placetype":"venue"
},
  "geometry": {"coordinates":[-67.396072,46.903271],"type":"Point"}
}