{
  "type": "Feature",
  "properties": {
    "iso:country":"CA",
    "sg:city":"Peterborough",
    "sg:classifiers":[
        {
            "category":"Real Estate",
            "subcategory":"Developer",
            "type":"Services"
        }
    ],
    "sg:phone":"+1 705 741 1422",
    "sg:postcode":"K9H 7L7",
    "sg:province":"ON",
    "wof:name":"Charter Development Group",
    "wof:placetype":"venue"
},
  "geometry": {"coordinates":[-78.30503845210001,44.306854248],"type":"Point"}
}