{
  "type": "Feature",
  "properties": {
    "addr:full":"1 Hazen Ave Saint John NB E2L 3G6",
    "addr:housenumber":"1",
    "addr:postcode":"e2l 3g6",
    "addr:street":"Hazen Ave",
    "iso:country":"CA",
    "sg:address":"1 Hazen Ave",
    "sg:city":"Saint John",
    "sg:classifiers":[
        {
            "category":"Restaurant",
            "type":"Food & Drink"
        }
    ],
    "sg:phone":"+1 506 634 3900",
    "sg:postcode":"E2L 3G6",
    "sg:province":"NB",
    "wof:name":"Vito's Dining Room & Lounge",
    "wof:placetype":"venue"
},
  "geometry": {"coordinates":[-66.063202,45.275051],"type":"Point"}
}