{
  "type": "Feature",
  "properties": {
    "addr:full":"2900 Warden Ave Scarborough ON M1W 2S8",
    "addr:housenumber":"2900",
    "addr:postcode":"m1w 2s8",
    "addr:street":"Warden Ave",
    "iso:country":"CA",
    "sg:address":"2900 Warden Ave",
    "sg:city":"Scarborough",
    "sg:classifiers":[
        {
            "category":"Professional",
            "subcategory":"Business Services",
            "type":"Services"
        }
    ],
    "sg:phone":"+1 416 497 1761",
    "sg:postcode":"M1W 2S8",
    "sg:province":"ON",
    "sg:tags":[
        "wine"
    ],
    "wof:name":"Wine Rack",
    "wof:placetype":"venue"
},
  "geometry": {"coordinates":[-79.31596374510001,43.7968978882],"type":"Point"}
}