{
  "type": "Feature",
  "properties": {
    "addr:full":"2220 Boul Hymus Dorval QC H9P 1J7",
    "addr:housenumber":"2220",
    "addr:postcode":"h9p 1j7",
    "addr:street":"Boul Hymus",
    "iso:country":"CA",
    "sg:address":"2220 Boul Hymus",
    "sg:city":"Dorval",
    "sg:classifiers":[
        {
            "category":"Wholesale",
            "subcategory":"Machinery & Supplies",
            "type":"Manufacturing & Wholesale Goods"
        }
    ],
    "sg:phone":"+1 514 875 1990",
    "sg:postcode":"H9P 1J7",
    "sg:province":"QC",
    "sg:tags":[
        "machine",
        "tool",
        "saw"
    ],
    "wof:name":"Acme Saw Ltee",
    "wof:placetype":"venue"
},
  "geometry": {"coordinates":[-73.78549957280001,45.4782867432],"type":"Point"}
}