{
  "type": "Feature",
  "properties": {
    "iso:country":"CA",
    "sg:address":"32995 South Fraser Way",
    "sg:city":"Abbotsford",
    "sg:classifiers":[
        {
            "category":"Autos & Motor Vehicles",
            "subcategory":"Auto Supplies",
            "type":"Retail Goods"
        }
    ],
    "sg:phone":"+1 604 853 6961",
    "sg:postcode":"V2S 2A6",
    "sg:province":"BC",
    "sg:tags":[
        "tire"
    ],
    "wof:name":"Braconnier's Csc Tirecraft",
    "wof:placetype":"venue"
},
  "geometry": {"coordinates":[-122.30934906,49.0509529114],"type":"Point"}
}