{
  "type": "Feature",
  "properties": {
    "iso:country":"CA",
    "sg:address":"56 Grand Ave N",
    "sg:city":"Cambridge",
    "sg:classifiers":[
        {
            "category":"Health Services",
            "subcategory":"Doctor",
            "type":"Services"
        }
    ],
    "sg:phone":"+1 519 622 1577",
    "sg:postcode":"N1S 2K9",
    "sg:province":"ON",
    "sg:tags":[
        "physician",
        "surgeon"
    ],
    "wof:name":"Wong, William H MD",
    "wof:placetype":"venue"
},
  "geometry": {"coordinates":[-80.31772613530001,43.3612251282],"type":"Point"}
}