{
  "type": "Feature",
  "properties": {
    "addr:full":"140 3rd St E Bengough SK S0C 0K0",
    "addr:housenumber":"140",
    "addr:postcode":"s0c 0k0",
    "addr:street":"3Rd St;Bengough",
    "iso:country":"CA",
    "sg:address":"140 3rd St E",
    "sg:city":"Bengough",
    "sg:classifiers":[
        {
            "category":"Wholesale",
            "subcategory":"Petroleum",
            "type":"Manufacturing & Wholesale Goods"
        }
    ],
    "sg:phone":"+1 306 268 2040",
    "sg:postcode":"S0C 0K0",
    "sg:province":"SK",
    "sg:tags":[
        "oil"
    ],
    "wof:name":"Bengough CO-Operative Ltd",
    "wof:placetype":"venue"
},
  "geometry": {"coordinates":[-105.12273399999999,49.397285],"type":"Point"}
}