{
  "type": "Feature",
  "properties": {
    "addr:full":"11 Racine Rd Etobicoke ON M9W 2Z2",
    "addr:housenumber":"11",
    "addr:postcode":"m9w 2z2",
    "addr:street":"Racine Rd",
    "iso:country":"CA",
    "sg:address":"11 Racine Rd",
    "sg:city":"Etobicoke",
    "sg:classifiers":[
        {
            "category":"Retail",
            "subcategory":"Auto Repair",
            "type":"Services"
        }
    ],
    "sg:phone":"+1 416 248 1166",
    "sg:postcode":"M9W 2Z2",
    "sg:province":"ON",
    "sg:tags":[
        "repairing",
        "automobile"
    ],
    "wof:name":"Loveleen Auto Sales & Svc Ltd",
    "wof:placetype":"venue"
},
  "geometry": {"coordinates":[-79.57089233400001,43.7152519226],"type":"Point"}
}