{
  "type": "Feature",
  "properties": {
    "addr:full":"543 St Mary's Rd Winnipeg MB R2M 3L4",
    "addr:housenumber":"543",
    "addr:postcode":"r2m 3l4",
    "addr:street":"St Mary'S Rd",
    "iso:country":"CA",
    "sg:address":"543 St Mary's Rd",
    "sg:city":"Winnipeg",
    "sg:classifiers":[
        {
            "category":"Wholesale",
            "subcategory":"Plants",
            "type":"Manufacturing & Wholesale Goods"
        }
    ],
    "sg:phone":"+1 204 233 1139",
    "sg:postcode":"R2M 3L4",
    "sg:province":"MB",
    "wof:name":"Euphorbia Plants & Flowers Ltd",
    "wof:placetype":"venue"
},
  "geometry": {"coordinates":[-97.152725,49.88932],"type":"Point"}
}