{
  "type": "Feature",
  "properties": {
    "addr:full":"Mississauga ON L4V 1R9",
    "addr:postcode":"l4v 1r9",
    "iso:country":"CA",
    "sg:city":"Mississauga",
    "sg:classifiers":[
        {
            "category":"Freight",
            "type":"Transportation"
        }
    ],
    "sg:phone":"+1 905 673 9300",
    "sg:postcode":"L4V 1R9",
    "sg:province":"ON",
    "wof:name":"Triumph Express Svc Canada Inc",
    "wof:placetype":"venue"
},
  "geometry": {"coordinates":[-79.6083984375,43.6860847473],"type":"Point"}
}