{
  "type": "Feature",
  "properties": {
    "addr:full":"259 Boul DE LA Cote-Vertu Saint-Laurent QC H4N 1C8",
    "addr:housenumber":"259",
    "addr:postcode":"h4n 1c8",
    "addr:street":"Boul De La Cote-Vertu",
    "iso:country":"CA",
    "sg:address":"259 Boul DE LA Cote-Vertu",
    "sg:city":"Saint-Laurent",
    "sg:classifiers":[
        {
            "category":"Retail",
            "subcategory":"Laundry & Dry Cleaning",
            "type":"Services"
        }
    ],
    "sg:phone":"+1 514 334 8838",
    "sg:postcode":"H4N 1C8",
    "sg:province":"QC",
    "sg:tags":[
        "cleaners"
    ],
    "wof:name":"Nettoyeurs Daoust",
    "wof:placetype":"venue"
},
  "geometry": {"coordinates":[-73.6696853638,45.528087616],"type":"Point"}
}