{
  "type": "Feature",
  "properties": {
    "iso:country":"CA",
    "sg:address":"10128 104 Ave NW",
    "sg:city":"Edmonton",
    "sg:classifiers":[
        {
            "category":"Recreation",
            "subcategory":"Arcade",
            "type":"Entertainment"
        }
    ],
    "sg:phone":"+1 780 413 3178",
    "sg:postcode":"T5J 4Y8",
    "sg:province":"AB",
    "sg:tags":[
        "casino"
    ],
    "wof:name":"Baccarat Casino",
    "wof:placetype":"venue"
},
  "geometry": {"coordinates":[-113.494293,53.546387],"type":"Point"}
}