{
  "type": "Feature",
  "properties": {
    "addr:full":"3445 180 St Surrey BC V3S 0L5",
    "addr:housenumber":"3445",
    "addr:postcode":"v3s 0l5",
    "addr:street":"180 St",
    "iso:country":"CA",
    "sg:address":"3445 180 St",
    "sg:city":"Surrey",
    "sg:classifiers":[
        {
            "category":"Wholesale",
            "subcategory":"Construction Materials",
            "type":"Manufacturing & Wholesale Goods"
        }
    ],
    "sg:phone":"+1 604 541 1950",
    "sg:postcode":"V3S 0L5",
    "sg:province":"BC",
    "sg:tags":[
        "pole"
    ],
    "wof:name":"Bos Pole Sales & Installations",
    "wof:placetype":"venue"
},
  "geometry": {"coordinates":[-122.724601746,49.0643806458],"type":"Point"}
}