{
  "type": "Feature",
  "properties": {
    "addr:full":"1801 Dundas St London ON N5W 3E6",
    "addr:housenumber":"1801",
    "addr:postcode":"n5w 3e6",
    "addr:street":"Dundas St",
    "iso:country":"CA",
    "sg:address":"1801 Dundas St",
    "sg:city":"London",
    "sg:classifiers":[
        {
            "category":"Home & Garden",
            "subcategory":"Furniture",
            "type":"Retail Goods"
        }
    ],
    "sg:phone":"+1 519 452 0638",
    "sg:postcode":"N5W 3E6",
    "sg:province":"ON",
    "wof:name":"Sutherland's Furniture Plus",
    "wof:placetype":"venue"
},
  "geometry": {"coordinates":[-81.18157958979999,43.0030021667],"type":"Point"}
}