{
  "type": "Feature",
  "properties": {
    "iso:country":"CA",
    "sg:address":"320 Main St #2B",
    "sg:city":"Antigonish",
    "sg:classifiers":[
        {
            "category":"Professional",
            "subcategory":"Accounting & Tax Preparation",
            "type":"Services"
        }
    ],
    "sg:phone":"+1 902 863 2299",
    "sg:postcode":"B2G 2C4",
    "sg:province":"NS",
    "sg:tags":[
        "accountant"
    ],
    "wof:name":"J Mark Sears Inc",
    "wof:placetype":"venue"
},
  "geometry": {"coordinates":[-61.9933280945,45.6226348877],"type":"Point"}
}