{
  "type": "Feature",
  "properties": {
    "iso:country":"CA",
    "sg:address":"425 Av Du Quebec",
    "sg:city":"Sept-Iles",
    "sg:classifiers":[
        {
            "category":"Wholesale",
            "subcategory":"Electrical",
            "type":"Manufacturing & Wholesale Goods"
        }
    ],
    "sg:phone":"+1 418 962 5538",
    "sg:postcode":"G4R 1J8",
    "sg:province":"QC",
    "sg:tags":[
        "electric",
        "motor"
    ],
    "wof:name":"Ge Canada",
    "wof:placetype":"venue"
},
  "geometry": {"coordinates":[-66.3684387207,50.2145004272],"type":"Point"}
}