{
  "type": "Feature",
  "properties": {
    "addr:full":"1341 Main St Winnipeg MB R2W 3T7",
    "addr:housenumber":"1341",
    "addr:postcode":"r2w 3t7",
    "addr:street":"Main St",
    "iso:country":"CA",
    "sg:address":"1341 Main St",
    "sg:city":"Winnipeg",
    "sg:classifiers":[
        {
            "category":"Shopping",
            "subcategory":"Clothing, Apparel, & Fashions",
            "type":"Retail Goods"
        }
    ],
    "sg:phone":"+1 204 589 4141",
    "sg:postcode":"R2W 3T7",
    "sg:province":"MB",
    "sg:tags":[
        "lingerie"
    ],
    "wof:name":"Love Nest",
    "wof:placetype":"venue"
},
  "geometry": {"coordinates":[-97.126121521,49.9232406616],"type":"Point"}
}