{
  "type": "Feature",
  "properties": {
    "addr:full":"16951 12 Ave Surrey BC V3S 9M3",
    "addr:housenumber":"16951",
    "addr:postcode":"v3s 9m3",
    "addr:street":"12 Ave",
    "iso:country":"CA",
    "sg:address":"16951 12 Ave",
    "sg:city":"Surrey",
    "sg:classifiers":[
        {
            "category":"Building & Trades",
            "subcategory":"Construction",
            "type":"Services"
        }
    ],
    "sg:phone":"+1 604 538 5546",
    "sg:postcode":"V3S 9M3",
    "sg:province":"BC",
    "sg:tags":[
        "general",
        "contractor"
    ],
    "wof:name":"Wood Projects Ltd",
    "wof:placetype":"venue"
},
  "geometry": {"coordinates":[-122.75415802000001,49.0240058899],"type":"Point"}
}