{
  "type": "Feature",
  "properties": {
    "addr:full":"17 Rue Ontario E Montreal QC H2X 1G8",
    "addr:housenumber":"17",
    "addr:postcode":"h2x 1g8",
    "addr:street":"Rue Ontario E",
    "iso:country":"CA",
    "sg:address":"17 Rue Ontario E",
    "sg:city":"Montreal",
    "sg:classifiers":[
        {
            "category":"Food & Beverages",
            "subcategory":"Groceries & Convenience Stores",
            "type":"Retail Goods"
        }
    ],
    "sg:phone":"+1 514 849 0546",
    "sg:postcode":"H2X 1G8",
    "sg:province":"QC",
    "sg:tags":[
        "grocer"
    ],
    "wof:name":"New Madina Super Market Inc",
    "wof:placetype":"venue"
},
  "geometry": {"coordinates":[-73.5668563843,45.5114784241],"type":"Point"}
}