{
  "type": "Feature",
  "properties": {
    "addr:full":"4504 Boul Dagenais O Laval QC H7R 1L5",
    "addr:housenumber":"4504",
    "addr:postcode":"h7r 1l5",
    "addr:street":"Boul Dagenais O",
    "iso:country":"CA",
    "sg:address":"4504 Boul Dagenais O",
    "sg:city":"Laval",
    "sg:classifiers":[
        {
            "category":"Wholesale",
            "subcategory":"Construction Materials",
            "type":"Manufacturing & Wholesale Goods"
        }
    ],
    "sg:phone":"+1 450 627 5613",
    "sg:postcode":"H7R 1L5",
    "sg:province":"QC",
    "sg:tags":[
        "sand",
        "gravel"
    ],
    "wof:name":"Pierre-Paul Lavoie Les Serres",
    "wof:placetype":"venue"
},
  "geometry": {"coordinates":[-73.84699999999999,45.555645],"type":"Point"}
}