{
  "type": "Feature",
  "properties": {
    "addr:full":"952 Commercial Dr Vancouver BC V5L 3W7",
    "addr:housenumber":"952",
    "addr:postcode":"v5l 3w7",
    "addr:street":"Commercial Dr",
    "iso:country":"CA",
    "sg:address":"952 Commercial Dr",
    "sg:city":"Vancouver",
    "sg:classifiers":[
        {
            "category":"Home & Garden",
            "subcategory":"Home Furnishings",
            "type":"Retail Goods"
        }
    ],
    "sg:phone":"+1 604 255 5464",
    "sg:postcode":"V5L 3W7",
    "sg:province":"BC",
    "sg:tags":[
        "lighting",
        "fixture"
    ],
    "wof:name":"Babic Electric Ltd",
    "wof:placetype":"venue"
},
  "geometry": {"coordinates":[-123.06933600000001,49.276207],"type":"Point"}
}