{
  "type": "Feature",
  "properties": {
    "addr:full":"45 Grenfell St Happy Valley-Goose Bay NL A0P 1E0",
    "addr:housenumber":"45",
    "addr:postcode":"a0p 1e0",
    "addr:street":"Grenfell St",
    "iso:country":"CA",
    "sg:address":"45 Grenfell St",
    "sg:city":"Happy Valley-Goose Bay",
    "sg:classifiers":[
        {
            "category":"Banks & Credit Unions",
            "subcategory":"Bank",
            "type":"Services"
        }
    ],
    "sg:phone":"+1 709 897 3000",
    "sg:postcode":"A0P 1E0",
    "sg:province":"NL",
    "wof:name":"Scotiabank",
    "wof:placetype":"venue"
},
  "geometry": {"coordinates":[-60.3103523254,53.2966918945],"type":"Point"}
}