{
  "type": "Feature",
  "properties": {
    "addr:full":"9964 Nipigon St Port Franks ON N0M 2L0",
    "addr:housenumber":"9964",
    "addr:postcode":"n0m 2l0",
    "addr:street":"Nipigon St",
    "iso:country":"CA",
    "sg:address":"9964 Nipigon St",
    "sg:city":"Port Franks",
    "sg:classifiers":[
        {
            "category":"Wholesale",
            "subcategory":"Electrical",
            "type":"Manufacturing & Wholesale Goods"
        }
    ],
    "sg:phone":"+1 519 243 2544",
    "sg:postcode":"N0M 2L0",
    "sg:province":"ON",
    "sg:tags":[
        "alarm",
        "burglar",
        "system"
    ],
    "wof:name":"Tnt Security Systems",
    "wof:placetype":"venue"
},
  "geometry": {"coordinates":[-81.885201,43.226849],"type":"Point"}
}