{
  "type": "Feature",
  "properties": {
    "addr:full":"420 Rue Des Adirondacks Beauport QC G1C 7E8",
    "addr:housenumber":"420",
    "addr:postcode":"qc g1c 7e8",
    "addr:street":"Rue Des Adirondacks",
    "iso:country":"CA",
    "sg:address":"420 Rue Des Adirondacks",
    "sg:city":"Beauport",
    "sg:classifiers":[
        {
            "category":"Building & Trades",
            "subcategory":"Plumbing",
            "type":"Services"
        }
    ],
    "sg:phone":"+1 418 660 6262",
    "sg:postcode":"G1C 7E8",
    "sg:province":"QC",
    "sg:tags":[
        "ventilating",
        "contractor"
    ],
    "wof:name":"Ventilation Orleans Inc",
    "wof:placetype":"venue"
},
  "geometry": {"coordinates":[-71.190468,46.880383],"type":"Point"}
}