{
  "type": "Feature",
  "properties": {
    "addr:full":"Wetaskiwin AB T9A 0T9",
    "addr:postcode":"t9a 0t9",
    "iso:country":"CA",
    "sg:city":"Wetaskiwin",
    "sg:classifiers":[
        {
            "category":"Health Services",
            "subcategory":"Chiropractor",
            "type":"Services"
        }
    ],
    "sg:phone":"+1 780 352 2101",
    "sg:postcode":"T9A 0T9",
    "sg:province":"AB",
    "wof:name":"Wetaskiwin Family Chiropractic",
    "wof:placetype":"venue"
},
  "geometry": {"coordinates":[-113.37402299999999,52.970402],"type":"Point"}
}