{
  "type": "Feature",
  "properties": {
    "addr:full":"Windsor QC J1S 1J7",
    "addr:postcode":"j1s 1j7",
    "iso:country":"CA",
    "sg:city":"Windsor",
    "sg:classifiers":[
        {
            "category":"Shopping",
            "subcategory":"Florist",
            "type":"Retail Goods"
        }
    ],
    "sg:phone":"+1 819 845 5365",
    "sg:postcode":"J1S 1J7",
    "sg:province":"QC",
    "wof:name":"Decor Dame Plume Ltee",
    "wof:placetype":"venue"
},
  "geometry": {"coordinates":[-71.9998092651,45.5726661682],"type":"Point"}
}