{
  "type": "Feature",
  "properties": {
    "iso:country":"CA",
    "sg:address":"847 Agnew Lake Rd",
    "sg:city":"Webbwood",
    "sg:classifiers":[
        {
            "category":"Travel",
            "subcategory":"Campground",
            "type":"Entertainment"
        }
    ],
    "sg:phone":"+1 705 869 2239",
    "sg:postcode":"P0P 2G0",
    "sg:province":"ON",
    "sg:tags":[
        "accommodation",
        "camp",
        "fishing",
        "tourist"
    ],
    "wof:name":"Agnew Lake Lodge Ltd",
    "wof:placetype":"venue"
},
  "geometry": {"coordinates":[-81.8982086182,46.2667388916],"type":"Point"}
}