{
  "type": "Feature",
  "properties": {
    "addr:full":"PO Box 27004 Rpo Downtown Red Deer AB T4N 6X8",
    "addr:housenumber":"po box",
    "addr:postcode":"27004;t4n 6x8",
    "addr:street":"Rpo",
    "iso:country":"CA",
    "sg:address":"PO Box 27004 Rpo Downtown",
    "sg:city":"Red Deer",
    "sg:classifiers":[
        {
            "category":"Recreation",
            "type":"Entertainment"
        }
    ],
    "sg:phone":"+1 403 886 4952",
    "sg:postcode":"T4N 6X8",
    "sg:province":"AB",
    "sg:tags":[
        "stable"
    ],
    "wof:name":"Lazy A Stables",
    "wof:placetype":"venue"
},
  "geometry": {"coordinates":[-113.817436,52.262302],"type":"Point"}
}