{
  "type": "Feature",
  "properties": {
    "iso:country":"CA",
    "sg:city":"Port Coquitlam",
    "sg:classifiers":[
        {
            "category":"Shopping",
            "type":"Retail Goods"
        }
    ],
    "sg:phone":"+1 604 941 1179",
    "sg:postcode":"V3C 2M8",
    "sg:province":"BC",
    "sg:tags":[
        "art",
        "gallery",
        "dealer"
    ],
    "wof:name":"Coastal Art Publishing",
    "wof:placetype":"venue"
},
  "geometry": {"coordinates":[-122.762077,49.248615],"type":"Point"}
}