{
  "type": "Feature",
  "properties": {
    "iso:country":"CA",
    "sg:city":"Toronto",
    "sg:classifiers":[
        {
            "category":"Professional",
            "subcategory":"Business Services",
            "type":"Services"
        }
    ],
    "sg:phone":"+1 416 593 6118",
    "sg:postcode":"M5V 3B1",
    "sg:province":"ON",
    "sg:tags":[
        "translator",
        "interpreter"
    ],
    "wof:name":"Japan Communications Inc",
    "wof:placetype":"venue"
},
  "geometry": {"coordinates":[-79.40184783940001,43.6466789246],"type":"Point"}
}