{
  "type": "Feature",
  "properties": {
    "iso:country":"CA",
    "sg:address":"57 Jessica Gdns",
    "sg:city":"Thornhill",
    "sg:phone":"+1 905 889 1859",
    "sg:postcode":"L4J 3G1",
    "sg:province":"ON",
    "sg:tags":[
        "shelving"
    ],
    "wof:name":"Shelf Baron",
    "wof:placetype":"venue"
},
  "geometry": {"coordinates":[-79.43528747560001,43.8071746826],"type":"Point"}
}