{
  "type": "Feature",
  "properties": {
    "addr:full":"302 St George St Annapolis Royal NS B0S 1A0",
    "addr:housenumber":"302",
    "addr:postcode":"b0s 1a0",
    "addr:street":"St George St",
    "iso:country":"CA",
    "sg:address":"302 St George St",
    "sg:city":"Annapolis Royal",
    "sg:classifiers":[
        {
            "category":"Professional",
            "subcategory":"Computer Services",
            "type":"Services"
        }
    ],
    "sg:phone":"+1 902 532 2546",
    "sg:postcode":"B0S 1A0",
    "sg:province":"NS",
    "sg:tags":[
        "website",
        "design"
    ],
    "wof:name":"Design Fort Desktop Publishing",
    "wof:placetype":"venue"
},
  "geometry": {"coordinates":[-65.518883,44.742756],"type":"Point"}
}