{
  "type": "Feature",
  "properties": {
    "addr:full":"39 Dundas St W Trenton ON K8V 3N9",
    "addr:housenumber":"39",
    "addr:postcode":"k8v 3n9",
    "addr:street":"Dundas St W",
    "iso:country":"CA",
    "sg:address":"39 Dundas St W",
    "sg:city":"Trenton",
    "sg:classifiers":[
        {
            "category":"Food & Beverages",
            "subcategory":"Specialty",
            "type":"Retail Goods"
        }
    ],
    "sg:phone":"+1 613 394 2882",
    "sg:postcode":"K8V 3N9",
    "sg:province":"ON",
    "sg:tags":[
        "health",
        "diet"
    ],
    "wof:name":"Natural Sequence",
    "wof:placetype":"venue"
},
  "geometry": {"coordinates":[-77.575729,44.101379],"type":"Point"}
}