{
  "type": "Feature",
  "properties": {
    "iso:country":"CA",
    "sg:address":"387 Rue Des Erables",
    "sg:city":"Saint-Elzear",
    "sg:classifiers":[
        {
            "category":"Manufacturing",
            "subcategory":"Tools & Machinery",
            "type":"Manufacturing & Wholesale Goods"
        }
    ],
    "sg:phone":"+1 418 387 7072",
    "sg:postcode":"G0S 2J0",
    "sg:province":"QC",
    "sg:tags":[
        "machine",
        "shop"
    ],
    "wof:name":"Centre D'Usinage St-Elzear",
    "wof:placetype":"venue"
},
  "geometry": {"coordinates":[-71.0531387329,46.4138298035],"type":"Point"}
}