{
  "type": "Feature",
  "properties": {
    "iso:country":"CA",
    "sg:address":"4811 Ontario Ave",
    "sg:city":"Powell River",
    "sg:classifiers":[
        {
            "category":"Organizations",
            "subcategory":"Religious Organization",
            "type":"Services"
        }
    ],
    "sg:phone":"+1 604 485 2000",
    "sg:postcode":"V8A 5B9",
    "sg:province":"BC",
    "sg:tags":[
        "church"
    ],
    "wof:name":"Faith Lutheran Church",
    "wof:placetype":"venue"
},
  "geometry": {"coordinates":[-124.515068,49.845829],"type":"Point"}
}