{
  "type": "Feature",
  "properties": {
    "iso:country":"CA",
    "sg:address":"1568 Hollis St",
    "sg:city":"Halifax",
    "sg:classifiers":[
        {
            "category":"Social Services",
            "type":"Services"
        }
    ],
    "sg:phone":"+1 902 422 3681",
    "sg:postcode":"B3J 1V3",
    "sg:province":"NS",
    "sg:tags":[
        "arbitration",
        "counselor",
        "marriage",
        "family"
    ],
    "wof:name":"Ams Mediation Assoc",
    "wof:placetype":"venue"
},
  "geometry": {"coordinates":[-63.5720672607,44.6456756592],"type":"Point"}
}