{
  "type": "Feature",
  "properties": {
    "iso:country":"CA",
    "sg:city":"Toronto",
    "sg:classifiers":[
        {
            "category":"Wholesale",
            "subcategory":"Home Furnishings",
            "type":"Manufacturing & Wholesale Goods"
        }
    ],
    "sg:phone":"+1 416 591 7640",
    "sg:postcode":"M5V 3A8",
    "sg:province":"ON",
    "sg:tags":[
        "curtain",
        "drapery"
    ],
    "wof:name":"Drapery Design Studio",
    "wof:placetype":"venue"
},
  "geometry": {"coordinates":[-79.3950881958,43.6478500366],"type":"Point"}
}