{
  "type": "Feature",
  "properties": {
    "addr:full":"1496 Lower Water St Halifax NS B3J 3R5",
    "addr:housenumber":"1496",
    "addr:postcode":"ns b3j 3r5",
    "addr:street":"Lower Water St",
    "iso:country":"CA",
    "sg:address":"1496 Lower Water St",
    "sg:city":"Halifax",
    "sg:classifiers":[
        {
            "category":"Professional",
            "subcategory":"Printing & Photocopies",
            "type":"Services"
        }
    ],
    "sg:phone":"+1 902 453 4429",
    "sg:postcode":"B3J 3R5",
    "sg:province":"NS",
    "sg:tags":[
        "multimedia",
        "duplicating",
        "copying"
    ],
    "wof:name":"Blue Sky Entertainment Svc",
    "wof:placetype":"venue"
},
  "geometry": {"coordinates":[-63.5704994202,44.6450080872],"type":"Point"}
}