{
  "type": "Feature",
  "properties": {
    "addr:full":"41 Dundas St E Napanee ON K7R 1H7",
    "addr:housenumber":"41",
    "addr:postcode":"k7r 1h7",
    "addr:street":"Dundas St",
    "iso:country":"CA",
    "sg:address":"41 Dundas St E",
    "sg:city":"Napanee",
    "sg:classifiers":[
        {
            "category":"Shopping",
            "type":"Retail Goods"
        }
    ],
    "sg:phone":"+1 613 354 1992",
    "sg:postcode":"K7R 1H7",
    "sg:province":"ON",
    "sg:tags":[
        "equipment",
        "supply",
        "wine",
        "wedding"
    ],
    "wof:name":"Wine Store",
    "wof:placetype":"venue"
},
  "geometry": {"coordinates":[-76.94910430909999,44.2482452393],"type":"Point"}
}