{
  "type": "Feature",
  "properties": {
    "addr:full":"100 Taunton Rd E #61 Oshawa ON L1G 7N1",
    "addr:housenumber":"100",
    "addr:postcode":"l1g 7n1",
    "addr:street":"Taunton Rd E # 61",
    "iso:country":"CA",
    "sg:address":"100 Taunton Rd E #61",
    "sg:city":"Oshawa",
    "sg:classifiers":[
        {
            "category":"Real Estate",
            "subcategory":"Real Estate Operator",
            "type":"Services"
        }
    ],
    "sg:phone":"+1 905 436 3346",
    "sg:postcode":"L1G 7N1",
    "sg:province":"ON",
    "sg:tags":[
        "apartment"
    ],
    "wof:name":"Taunton Terrace",
    "wof:placetype":"venue"
},
  "geometry": {"coordinates":[-78.874916,43.93396],"type":"Point"}
}