{
  "type": "Feature",
  "properties": {
    "addr:full":"500 Grandview St W Moose Jaw SK S6H 5W3",
    "addr:housenumber":"500",
    "addr:postcode":"s6h 5w3",
    "addr:street":"Grandview St W",
    "iso:country":"CA",
    "sg:address":"500 Grandview St W",
    "sg:city":"Moose Jaw",
    "sg:classifiers":[
        {
            "category":"Education",
            "subcategory":"School",
            "type":"Public Place"
        }
    ],
    "sg:phone":"+1 306 694 0066",
    "sg:postcode":"S6H 5W3",
    "sg:province":"SK",
    "wof:name":"St Mary School",
    "wof:placetype":"venue"
},
  "geometry": {"coordinates":[-105.54587600000001,50.380699],"type":"Point"}
}