{
  "type": "Feature",
  "properties": {
    "iso:country":"CA",
    "sg:city":"Vanderhoof",
    "sg:classifiers":[
        {
            "category":"Organizations",
            "subcategory":"Non-profit Organization",
            "type":"Services"
        }
    ],
    "sg:phone":"+1 250 567 2107",
    "sg:postcode":"V0J 3A0",
    "sg:province":"BC",
    "sg:tags":[
        "info",
        "information",
        "drug",
        "abuse",
        "treatment",
        "addiction",
        "alcoholism"
    ],
    "wof:name":"Vanderhoof Alcohol & Drug Svc",
    "wof:placetype":"venue"
},
  "geometry": {"coordinates":[-124.012901306,54.0139770508],"type":"Point"}
}