{
  "type": "Feature",
  "properties": {
    "addr:full":"127 Linden Dr Winkler MB R6W 1X8",
    "addr:housenumber":"127",
    "addr:postcode":"r6w 1x8",
    "addr:street":"Linden Dr",
    "iso:country":"CA",
    "sg:address":"127 Linden Dr",
    "sg:city":"Winkler",
    "sg:classifiers":[
        {
            "category":"Building & Trades",
            "subcategory":"Electrical",
            "type":"Services"
        }
    ],
    "sg:phone":"+1 204 325 7377",
    "sg:postcode":"R6W 1X8",
    "sg:province":"MB",
    "sg:tags":[
        "electric",
        "contractor"
    ],
    "wof:name":"R P Wiebe Electric",
    "wof:placetype":"venue"
},
  "geometry": {"coordinates":[-97.9472122192,49.1764526367],"type":"Point"}
}