{
  "type": "Feature",
  "properties": {
    "addr:full":"259 Elm St Sudbury ON P3C 1V5",
    "addr:housenumber":"259",
    "addr:postcode":"p3c 1v5",
    "addr:street":"Elm St",
    "iso:country":"CA",
    "sg:address":"259 Elm St",
    "sg:city":"Sudbury",
    "sg:classifiers":[
        {
            "category":"Travel",
            "subcategory":"Hotels & Motels",
            "type":"Entertainment"
        }
    ],
    "sg:phone":"+1 705 674 2442",
    "sg:postcode":"P3C 1V5",
    "sg:province":"ON",
    "wof:name":"Parker House Roastery & Inn",
    "wof:placetype":"venue"
},
  "geometry": {"coordinates":[-81.0050201416,46.4929924011],"type":"Point"}
}