{
  "type": "Feature",
  "properties": {
    "addr:full":"76 Princess St Saint John NB E2L 1K4",
    "addr:housenumber":"76",
    "addr:postcode":"e2l 1k4",
    "addr:street":"Princess St",
    "iso:country":"CA",
    "sg:address":"76 Princess St",
    "sg:city":"Saint John",
    "sg:classifiers":[
        {
            "category":"Health Services",
            "subcategory":"Doctor",
            "type":"Services"
        }
    ],
    "sg:phone":"+1 506 634 8717",
    "sg:postcode":"E2L 1K4",
    "sg:province":"NB",
    "sg:tags":[
        "dentist"
    ],
    "wof:name":"Wowchuk, Jerry A DDS",
    "wof:placetype":"venue"
},
  "geometry": {"coordinates":[-66.0598602295,45.2715263367],"type":"Point"}
}