{
  "type": "Feature",
  "properties": {
    "addr:full":"400 Burrard St # 810 Vancouver BC V6C 3A6",
    "addr:housenumber":"400",
    "addr:postcode":"v6c 3a6",
    "addr:street":"Burrard St # 810",
    "iso:country":"CA",
    "sg:address":"400 Burrard St # 810",
    "sg:city":"Vancouver",
    "sg:classifiers":[
        {
            "category":"Insurance",
            "subcategory":"Insurance Agent",
            "type":"Services"
        }
    ],
    "sg:phone":"+1 604 687 7688",
    "sg:postcode":"V6C 3A6",
    "sg:province":"BC",
    "wof:name":"Guarantee CO of North America",
    "wof:placetype":"venue"
},
  "geometry": {"coordinates":[-123.116936,49.287106],"type":"Point"}
}