{
  "type": "Feature",
  "properties": {
    "iso:country":"CA",
    "sg:address":"630 Rivard St",
    "sg:city":"Ile Des Chenes",
    "sg:classifiers":[
        {
            "category":"Arena",
            "subcategory":"Sports Club",
            "type":"Entertainment"
        }
    ],
    "sg:phone":"+1 204 878 3104",
    "sg:postcode":"R0A 0T0",
    "sg:province":"MB",
    "sg:tags":[
        "athletic",
        "fields",
        "stadium"
    ],
    "wof:name":"Ile Des Chenes Club Inc Arena",
    "wof:placetype":"venue"
},
  "geometry": {"coordinates":[-96.9940109253,49.7110710144],"type":"Point"}
}