{
  "type": "Feature",
  "properties": {
    "addr:full":"51 Notre-Dame W Azilda ON P0M 1B0",
    "addr:housenumber":"51",
    "addr:postcode":"p0m 1b0",
    "addr:street":"Notre-Dame W",
    "iso:country":"CA",
    "sg:address":"51 Notre-Dame W",
    "sg:city":"Azilda",
    "sg:classifiers":[
        {
            "category":"Retail",
            "subcategory":"Car Wash",
            "type":"Services"
        }
    ],
    "sg:phone":"+1 705 983 0602",
    "sg:postcode":"P0M 1B0",
    "sg:province":"ON",
    "sg:tags":[
        "polishing",
        "washing"
    ],
    "wof:name":"Mike's Gas Bar",
    "wof:placetype":"venue"
},
  "geometry": {"coordinates":[-81.116394,46.552139],"type":"Point"}
}