{
  "type": "Feature",
  "properties": {
    "addr:full":"512 Kingston Rd Pickering ON L1V 1A6",
    "addr:housenumber":"512",
    "addr:postcode":"l1v 1a6",
    "addr:street":"Kingston Rd",
    "iso:country":"CA",
    "sg:address":"512 Kingston Rd",
    "sg:city":"Pickering",
    "sg:classifiers":[
        {
            "category":"Professional",
            "type":"Services"
        }
    ],
    "sg:phone":"+1 905 831 5539",
    "sg:postcode":"L1V 1A6",
    "sg:province":"ON",
    "sg:tags":[
        "compact",
        "record",
        "disc",
        "establishment",
        "tape"
    ],
    "wof:name":"Swel",
    "wof:placetype":"venue"
},
  "geometry": {"coordinates":[-79.1227722168,43.8138504028],"type":"Point"}
}