{
  "type": "Feature",
  "properties": {
    "iso:country":"CA",
    "sg:address":"1156 137 Ave SE",
    "sg:city":"Calgary",
    "sg:classifiers":[
        {
            "category":"Personal",
            "subcategory":"Beauty Salon",
            "type":"Services"
        }
    ],
    "sg:phone":"+1 403 271 8080",
    "sg:postcode":"T2J 6T6",
    "sg:province":"AB",
    "wof:name":"Ultracuts",
    "wof:placetype":"venue"
},
  "geometry": {"coordinates":[-114.027702331,50.9279060364],"type":"Point"}
}