{
  "type": "Feature",
  "properties": {
    "addr:full":"579 Third Rd E Stoney Creek ON L8J 2Y1",
    "addr:housenumber":"579",
    "addr:postcode":"l8j 2y1",
    "addr:street":"Third Rd E",
    "iso:country":"CA",
    "sg:address":"579 Third Rd E",
    "sg:city":"Stoney Creek",
    "sg:classifiers":[
        {
            "category":"Freight",
            "type":"Transportation"
        }
    ],
    "sg:phone":"+1 905 662 1444",
    "sg:postcode":"L8J 2Y1",
    "sg:province":"ON",
    "sg:tags":[
        "consultant"
    ],
    "wof:name":"Sts Starliner",
    "wof:placetype":"venue"
},
  "geometry": {"coordinates":[-79.72927856450001,43.205329895],"type":"Point"}
}