{
  "type": "Feature",
  "properties": {
    "addr:full":"1 Lancaster St Hamilton ON L8L 6X1",
    "addr:housenumber":"1",
    "addr:postcode":"l8l 6x1",
    "addr:street":"Lancaster St",
    "iso:country":"CA",
    "sg:address":"1 Lancaster St",
    "sg:city":"Hamilton",
    "sg:classifiers":[
        {
            "category":"Manufacturing",
            "subcategory":"Metals",
            "type":"Manufacturing & Wholesale Goods"
        }
    ],
    "sg:phone":"+1 905 544 0250",
    "sg:postcode":"L8L 6X1",
    "sg:province":"ON",
    "sg:tags":[
        "stamping"
    ],
    "wof:name":"Homer & Wilson Ltd",
    "wof:placetype":"venue"
},
  "geometry": {"coordinates":[-79.823311,43.263424],"type":"Point"}
}