{
  "type": "Feature",
  "properties": {
    "addr:full":"Ottawa ON K2H 9N6",
    "addr:postcode":"k2h 9n6",
    "iso:country":"CA",
    "sg:city":"Ottawa",
    "sg:classifiers":[
        {
            "category":"Manufacturing",
            "subcategory":"Electronics",
            "type":"Manufacturing & Wholesale Goods"
        }
    ],
    "sg:phone":"+1 613 828 5626",
    "sg:postcode":"K2H 9N6",
    "sg:province":"ON",
    "sg:tags":[
        "semiconductor",
        "devices"
    ],
    "wof:name":"Silicon Perspective Corp",
    "wof:placetype":"venue"
},
  "geometry": {"coordinates":[-75.79631000000001,45.345142],"type":"Point"}
}