{
  "type": "Feature",
  "properties": {
    "addr:full":"397 Russell St Midland ON L4R 3A7",
    "addr:housenumber":"397",
    "addr:postcode":"l4r 3a7",
    "addr:street":"Russell St",
    "iso:country":"CA",
    "sg:address":"397 Russell St",
    "sg:city":"Midland",
    "sg:classifiers":[
        {
            "category":"Food & Beverages",
            "subcategory":"Groceries & Convenience Stores",
            "type":"Retail Goods"
        }
    ],
    "sg:phone":"+1 705 527 6032",
    "sg:postcode":"L4R 3A7",
    "sg:province":"ON",
    "sg:tags":[
        "grocer"
    ],
    "wof:name":"Midland Food Town",
    "wof:placetype":"venue"
},
  "geometry": {"coordinates":[-79.877396,44.74892],"type":"Point"}
}