{
  "type": "Feature",
  "properties": {
    "addr:full":"3121 Country Lane Whitby ON L1P 1N3",
    "addr:housenumber":"3121",
    "addr:postcode":"l1p 1n3",
    "addr:street":"Country Lane",
    "iso:country":"CA",
    "sg:address":"3121 Country Lane",
    "sg:city":"Whitby",
    "sg:classifiers":[
        {
            "category":"Education",
            "subcategory":"School",
            "type":"Public Place"
        }
    ],
    "sg:phone":"+1 905 665 2001",
    "sg:postcode":"L1P 1N3",
    "sg:province":"ON",
    "wof:name":"Captain Michael Vandenbois Ps",
    "wof:placetype":"venue"
},
  "geometry": {"coordinates":[-78.970192,43.899849],"type":"Point"}
}