{
  "type": "Feature",
  "properties": {
    "addr:full":"412 Rue Du Bateau Passeur Tadoussac QC G0T 2A0",
    "addr:housenumber":"412",
    "addr:postcode":"g0t 2a0",
    "addr:street":"Rue Du Bateau Passeur",
    "iso:country":"CA",
    "sg:address":"412 Rue Du Bateau Passeur",
    "sg:city":"Tadoussac",
    "sg:classifiers":[
        {
            "category":"Travel",
            "subcategory":"Hotels & Motels",
            "type":"Entertainment"
        }
    ],
    "sg:phone":"+1 418 235 4733",
    "sg:postcode":"G0T 2A0",
    "sg:province":"QC",
    "wof:name":"Restaurant Motel Chantmartin",
    "wof:placetype":"venue"
},
  "geometry": {"coordinates":[-69.7154998779,48.1495094299],"type":"Point"}
}