{
  "type": "Feature",
  "properties": {
    "addr:full":"2083 Rue Saint-Denis Montreal QC H2X 3K8",
    "addr:housenumber":"2083",
    "addr:postcode":"h2x 3k8",
    "addr:street":"Rue Saint-Denis",
    "iso:country":"CA",
    "sg:address":"2083 Rue Saint-Denis",
    "sg:city":"Montreal",
    "sg:classifiers":[
        {
            "category":"Food & Beverages",
            "subcategory":"Groceries & Convenience Stores",
            "type":"Retail Goods"
        }
    ],
    "sg:phone":"+1 514 847 0099",
    "sg:postcode":"H2X 3K8",
    "sg:province":"QC",
    "wof:name":"Depanneur Aline",
    "wof:placetype":"venue"
},
  "geometry": {"coordinates":[-73.56638336180001,45.5166053772],"type":"Point"}
}