{
  "type": "Feature",
  "properties": {
    "addr:full":"3127 30 Ave Vernon BC V1T 2C4",
    "addr:housenumber":"3127",
    "addr:postcode":"v1t 2c4",
    "addr:street":"30 Ave",
    "iso:country":"CA",
    "sg:address":"3127 30 Ave",
    "sg:city":"Vernon",
    "sg:classifiers":[
        {
            "category":"Restaurant",
            "type":"Food & Drink"
        }
    ],
    "sg:phone":"+1 250 545 3228",
    "sg:postcode":"V1T 2C4",
    "sg:province":"BC",
    "wof:name":"K T's Family Restaurant",
    "wof:placetype":"venue"
},
  "geometry": {"coordinates":[-119.27273599999999,50.263889],"type":"Point"}
}