{
  "type": "Feature",
  "properties": {
    "addr:full":"206 Harwood Ave S Ajax ON L1S 2H6",
    "addr:housenumber":"206",
    "addr:postcode":"l1s 2h6",
    "addr:street":"Harwood Ave S",
    "iso:country":"CA",
    "sg:address":"206 Harwood Ave S",
    "sg:city":"Ajax",
    "sg:classifiers":[
        {
            "category":"Personal",
            "subcategory":"Beauty Salon",
            "type":"Services"
        }
    ],
    "sg:phone":"+1 905 683 1846",
    "sg:postcode":"L1S 2H6",
    "sg:province":"ON",
    "wof:name":"Hair We Are",
    "wof:placetype":"venue"
},
  "geometry": {"coordinates":[-79.02069899999999,43.848858],"type":"Point"}
}