{
  "type": "Feature",
  "properties": {
    "iso:country":"CA",
    "sg:address":"206 Harwood Ave S",
    "sg:city":"Ajax",
    "sg:classifiers":[
        {
            "category":"Personal",
            "subcategory":"Beauty Salon",
            "type":"Services"
        }
    ],
    "sg:phone":"+1 905 683 1846",
    "sg:postcode":"L1S 2H6",
    "sg:province":"ON",
    "wof:name":"Hair We Are",
    "wof:placetype":"venue"
},
  "geometry": {"coordinates":[-79.020699,43.848858],"type":"Point"}
}