{
  "type": "Feature",
  "properties": {
    "addr:full":"NW 9-2-29W Pierson MB R0M 1S0",
    "addr:postcode":"9-2-29w;r0m 1s0",
    "addr:street":"Nw",
    "iso:country":"CA",
    "sg:address":"NW 9-2-29W",
    "sg:city":"Pierson",
    "sg:classifiers":[
        {
            "category":"Mining & Drilling",
            "type":"Manufacturing & Wholesale Goods"
        }
    ],
    "sg:phone":"+1 204 634 2361",
    "sg:postcode":"R0M 1S0",
    "sg:province":"MB",
    "sg:tags":[
        "company",
        "oil"
    ],
    "wof:name":"Canadian Natural Resources Ltd",
    "wof:placetype":"venue"
},
  "geometry": {"coordinates":[-101.256683,49.17939],"type":"Point"}
}