{
  "type": "Feature",
  "properties": {
    "addr:full":"36 Victoria Rd Dartmouth NS B2Y 2V9",
    "addr:housenumber":"36",
    "addr:postcode":"b2y 2v9",
    "addr:street":"Victoria Rd",
    "iso:country":"CA",
    "sg:address":"36 Victoria Rd",
    "sg:city":"Dartmouth",
    "sg:classifiers":[
        {
            "category":"Organizations",
            "subcategory":"Religious Organization",
            "type":"Services"
        }
    ],
    "sg:phone":"+1 902 469 8576",
    "sg:postcode":"B2Y 2V9",
    "sg:province":"NS",
    "sg:tags":[
        "church"
    ],
    "wof:name":"Victoria Rd United Bapt Church",
    "wof:placetype":"venue"
},
  "geometry": {"coordinates":[-63.566895,44.669022],"type":"Point"}
}