{
  "type": "Feature",
  "properties": {
    "addr:full":"526 Deloraine Ave North York ON M5M 2C3",
    "addr:housenumber":"526",
    "addr:postcode":"m5m 2c3",
    "addr:street":"Deloraine Ave",
    "iso:country":"CA",
    "sg:address":"526 Deloraine Ave",
    "sg:city":"North York",
    "sg:classifiers":[
        {
            "category":"Professional",
            "type":"Services"
        }
    ],
    "sg:phone":"+1 416 340 2626",
    "sg:postcode":"M5M 2C3",
    "sg:province":"ON",
    "sg:tags":[
        "interior",
        "consultant",
        "design",
        "establishment",
        "decorator"
    ],
    "wof:name":"Radcliffe Design Assoc",
    "wof:placetype":"venue"
},
  "geometry": {"coordinates":[-79.4258880615,43.7295799255],"type":"Point"}
}