{
  "type": "Feature",
  "properties": {
    "addr:full":"16 Edgehill Rd Etobicoke ON M9A 4N3",
    "addr:housenumber":"16",
    "addr:postcode":"m9a 4n3",
    "addr:street":"Edgehill Rd",
    "iso:country":"CA",
    "sg:address":"16 Edgehill Rd",
    "sg:city":"Etobicoke",
    "sg:classifiers":[
        {
            "category":"Real Estate",
            "subcategory":"Real Estate Agent",
            "type":"Services"
        }
    ],
    "sg:phone":"+1 416 231 1377",
    "sg:postcode":"M9A 4N3",
    "sg:province":"ON",
    "wof:name":"Jaclon Realty",
    "wof:placetype":"venue"
},
  "geometry": {"coordinates":[-79.517235,43.666126],"type":"Point"}
}