{
  "type": "Feature",
  "properties": {
    "iso:country":"CA",
    "sg:address":"2118 Dublin St",
    "sg:city":"New Westminster",
    "sg:classifiers":[
        {
            "category":"Retail",
            "subcategory":"Auto Repair",
            "type":"Services"
        }
    ],
    "sg:phone":"+1 604 520 1147",
    "sg:postcode":"V3M 3A9",
    "sg:province":"BC",
    "sg:tags":[
        "automobile",
        "co",
        "drive",
        "transporter"
    ],
    "wof:name":"Sweet Auto Transportation Ltd",
    "wof:placetype":"venue"
},
  "geometry": {"coordinates":[-122.95223999,49.2028312683],"type":"Point"}
}