{
  "type": "Feature",
  "properties": {
    "addr:full":"Mildmay ON N0G 2J0",
    "addr:postcode":"n0g 2j0",
    "iso:country":"CA",
    "sg:city":"Mildmay",
    "sg:classifiers":[
        {
            "category":"Shopping",
            "subcategory":"Pharmacy",
            "type":"Retail Goods"
        }
    ],
    "sg:phone":"+1 519 367 5521",
    "sg:postcode":"N0G 2J0",
    "sg:province":"ON",
    "wof:name":"Stewart's Pharmacy",
    "wof:placetype":"venue"
},
  "geometry": {"coordinates":[-81.110855,44.038059],"type":"Point"}
}