{
  "type": "Feature",
  "properties": {
    "addr:full":"200 Broadway St #B8 Tillsonburg ON N4G 5A7",
    "addr:housenumber":"200",
    "addr:postcode":"n4g 5a7",
    "addr:street":"Broadway St # B8",
    "iso:country":"CA",
    "sg:address":"200 Broadway St #B8",
    "sg:city":"Tillsonburg",
    "sg:classifiers":[
        {
            "category":"Shopping",
            "subcategory":"Clothing, Apparel, & Fashions",
            "type":"Retail Goods"
        }
    ],
    "sg:phone":"+1 519 842 9594",
    "sg:postcode":"N4G 5A7",
    "sg:province":"ON",
    "wof:name":"Reitmans",
    "wof:placetype":"venue"
},
  "geometry": {"coordinates":[-80.7260360718,42.8589515686],"type":"Point"}
}