{
  "type": "Feature",
  "properties": {
    "addr:full":"925 Rte Kennedy N Saint-Come-Liniere QC G0M 1J0",
    "addr:housenumber":"925",
    "addr:postcode":"g0m 1j0",
    "addr:street":"Rte Kennedy N",
    "iso:country":"CA",
    "sg:address":"925 Rte Kennedy N",
    "sg:city":"Saint-Come-Liniere",
    "sg:classifiers":[
        {
            "category":"Retail",
            "subcategory":"Auto Repair",
            "type":"Services"
        }
    ],
    "sg:phone":"+1 418 685 2444",
    "sg:postcode":"G0M 1J0",
    "sg:province":"QC",
    "sg:tags":[
        "repairing",
        "automobile"
    ],
    "wof:name":"D C Mecanique Enr",
    "wof:placetype":"venue"
},
  "geometry": {"coordinates":[-70.55712890620001,46.0625801086],"type":"Point"}
}