{
  "type": "Feature",
  "properties": {
    "addr:full":"3121 Sheppard Ave E Scarborough ON M1T 3J7",
    "addr:housenumber":"3121",
    "addr:postcode":"m1t 3j7",
    "addr:street":"Sheppard Ave E",
    "iso:country":"CA",
    "sg:address":"3121 Sheppard Ave E",
    "sg:city":"Scarborough",
    "sg:classifiers":[
        {
            "category":"Food & Beverages",
            "subcategory":"Groceries & Convenience Stores",
            "type":"Retail Goods"
        }
    ],
    "sg:phone":"+1 416 495 7531",
    "sg:postcode":"M1T 3J7",
    "sg:province":"ON",
    "sg:tags":[
        "grocer"
    ],
    "wof:name":"Aprozar Fresh Fruits & Vgtbls",
    "wof:placetype":"venue"
},
  "geometry": {"coordinates":[-79.31690979,43.776550293],"type":"Point"}
}