{
  "type": "Feature",
  "properties": {
    "addr:full":"Niagara Falls ON L2H 1K2",
    "addr:postcode":"l2h 1k2",
    "iso:country":"CA",
    "sg:city":"Niagara Falls",
    "sg:classifiers":[
        {
            "category":"Retail",
            "subcategory":"Auto Repair",
            "type":"Services"
        }
    ],
    "sg:phone":"+1 905 356 8324",
    "sg:postcode":"L2H 1K2",
    "sg:province":"ON",
    "sg:tags":[
        "repairing",
        "automobile"
    ],
    "wof:name":"Alltech Automotive",
    "wof:placetype":"venue"
},
  "geometry": {"coordinates":[-79.12412999999999,43.109261],"type":"Point"}
}