{
  "type": "Feature",
  "properties": {
    "addr:full":"6900 Airport Rd Mississauga ON L4V 1E8",
    "addr:housenumber":"6900",
    "addr:postcode":"l4v 1e8",
    "addr:street":"Airport Rd",
    "iso:country":"CA",
    "sg:address":"6900 Airport Rd",
    "sg:city":"Mississauga",
    "sg:classifiers":[
        {
            "category":"Manufacturing",
            "subcategory":"Furniture",
            "type":"Manufacturing & Wholesale Goods"
        }
    ],
    "sg:phone":"+1 905 673 6570",
    "sg:postcode":"L4V 1E8",
    "sg:province":"ON",
    "wof:name":"Magnussen Presidential Inc",
    "wof:placetype":"venue"
},
  "geometry": {"coordinates":[-79.63806200000001,43.700108],"type":"Point"}
}