{
  "type": "Feature",
  "properties": {
    "iso:country":"CA",
    "sg:address":"6900 Airport Rd",
    "sg:city":"Mississauga",
    "sg:classifiers":[
        {
            "category":"Manufacturing",
            "subcategory":"Furniture",
            "type":"Manufacturing & Wholesale Goods"
        }
    ],
    "sg:phone":"+1 905 673 6570",
    "sg:postcode":"L4V 1E8",
    "sg:province":"ON",
    "wof:name":"Magnussen Presidential Inc",
    "wof:placetype":"venue"
},
  "geometry": {"coordinates":[-79.638062,43.700108],"type":"Point"}
}