{
  "type": "Feature",
  "properties": {
    "addr:full":"2170 Danforth Ave Toronto ON M4C 1K3",
    "addr:housenumber":"2170",
    "addr:postcode":"m4c 1k3",
    "addr:street":"Danforth Ave",
    "iso:country":"CA",
    "sg:address":"2170 Danforth Ave",
    "sg:city":"Toronto",
    "sg:classifiers":[
        {
            "category":"Shopping",
            "subcategory":"Crafts & Fabrics",
            "type":"Retail Goods"
        }
    ],
    "sg:phone":"+1 416 696 2670",
    "sg:postcode":"M4C 1K3",
    "sg:province":"ON",
    "sg:tags":[
        "yarn"
    ],
    "wof:name":"Wool Mill",
    "wof:placetype":"venue"
},
  "geometry": {"coordinates":[-79.31034088129999,43.686378479],"type":"Point"}
}