{
  "type": "Feature",
  "properties": {
    "addr:full":"3030 Granville St Vancouver BC V6H 3J8",
    "addr:housenumber":"3030",
    "addr:postcode":"v6h 3j8",
    "addr:street":"Granville St",
    "iso:country":"CA",
    "sg:address":"3030 Granville St",
    "sg:city":"Vancouver",
    "sg:classifiers":[
        {
            "category":"Home & Garden",
            "subcategory":"Carpets & Floor Coverings",
            "type":"Retail Goods"
        }
    ],
    "sg:phone":"+1 604 730 2566",
    "sg:postcode":"V6H 3J8",
    "sg:province":"BC",
    "sg:tags":[
        "rug",
        "furniture"
    ],
    "wof:name":"Spiral Living Decor",
    "wof:placetype":"venue"
},
  "geometry": {"coordinates":[-123.138542175,49.2586174011],"type":"Point"}
}