{
  "type": "Feature",
  "properties": {
    "addr:full":"721 Rue Du Cap LA Baie QC G7B 2X2",
    "addr:housenumber":"721",
    "addr:postcode":"g7b 2x2",
    "addr:street":"Rue Du Cap",
    "iso:country":"CA",
    "sg:address":"721 Rue Du Cap",
    "sg:city":"LA Baie",
    "sg:classifiers":[
        {
            "category":"Travel",
            "subcategory":"Travel Agent",
            "type":"Entertainment"
        }
    ],
    "sg:phone":"+1 418 697 7630",
    "sg:postcode":"G7B 2X2",
    "sg:province":"QC",
    "sg:tags":[
        "boat",
        "cruise"
    ],
    "wof:name":"Croisiere DE LA Baie",
    "wof:placetype":"venue"
},
  "geometry": {"coordinates":[-70.88030999999999,48.343479],"type":"Point"}
}