{
  "type": "Feature",
  "properties": {
    "addr:full":"423 Sidney St Trenton ON K8V 6N6",
    "addr:housenumber":"423",
    "addr:postcode":"k8v 6n6",
    "addr:street":"Sidney St",
    "iso:country":"CA",
    "sg:address":"423 Sidney St",
    "sg:city":"Trenton",
    "sg:classifiers":[
        {
            "category":"Food & Beverages",
            "subcategory":"Groceries & Convenience Stores",
            "type":"Retail Goods"
        }
    ],
    "sg:phone":"+1 613 394 6454",
    "sg:postcode":"K8V 6N6",
    "sg:province":"ON",
    "wof:name":"Sidney Market",
    "wof:placetype":"venue"
},
  "geometry": {"coordinates":[-77.58062,44.128269],"type":"Point"}
}