{
  "type": "Feature",
  "properties": {
    "addr:full":"5424 Rue Jean-Talon E Saint-Leonard QC H1S 1L6",
    "addr:housenumber":"5424",
    "addr:postcode":"h1s 1l6",
    "addr:street":"Rue Jean-Talon E",
    "iso:country":"CA",
    "sg:address":"5424 Rue Jean-Talon E",
    "sg:city":"Saint-Leonard",
    "sg:classifiers":[
        {
            "category":"Retail",
            "subcategory":"Laundry & Dry Cleaning",
            "type":"Services"
        }
    ],
    "sg:phone":"+1 514 725 7860",
    "sg:postcode":"H1S 1L6",
    "sg:province":"QC",
    "sg:tags":[
        "cleaners"
    ],
    "wof:name":"Nettoyeur David",
    "wof:placetype":"venue"
},
  "geometry": {"coordinates":[-73.58120700000001,45.580246],"type":"Point"}
}