{
  "type": "Feature",
  "properties": {
    "iso:country":"CA",
    "sg:address":"1593 Boul Saint-Paul",
    "sg:city":"Chicoutimi",
    "sg:classifiers":[
        {
            "category":"Wholesale",
            "subcategory":"Apparel",
            "type":"Manufacturing & Wholesale Goods"
        }
    ],
    "sg:phone":"+1 418 696 2593",
    "sg:postcode":"G7J 3Y3",
    "sg:province":"QC",
    "sg:tags":[
        "textile"
    ],
    "wof:name":"Catphiltex Inc",
    "wof:placetype":"venue"
},
  "geometry": {"coordinates":[-71.098816,48.402267],"type":"Point"}
}