{
  "type": "Feature",
  "properties": {
    "addr:full":"78 Queenston St St Catharines ON L2R 2Z2",
    "addr:housenumber":"78",
    "addr:postcode":"l2r 2z2",
    "addr:street":"Queenston St",
    "iso:country":"CA",
    "sg:address":"78 Queenston St",
    "sg:city":"St Catharines",
    "sg:classifiers":[
        {
            "category":"Manufacturing",
            "subcategory":"Paper Products",
            "type":"Manufacturing & Wholesale Goods"
        }
    ],
    "sg:phone":"+1 905 682 2458",
    "sg:postcode":"L2R 2Z2",
    "sg:province":"ON",
    "sg:tags":[
        "printer"
    ],
    "wof:name":"Burtnik Printing Inc",
    "wof:placetype":"venue"
},
  "geometry": {"coordinates":[-79.23569500000001,43.163177],"type":"Point"}
}