{
  "type": "Feature",
  "properties": {
    "addr:full":"3960 Boul Des Forges Trois-Rivieres QC G8Y 1V7",
    "addr:housenumber":"3960",
    "addr:postcode":"g8y 1v7",
    "addr:street":"Boul Des Forges Trois-Rivieres",
    "iso:country":"CA",
    "sg:address":"3960 Boul Des Forges",
    "sg:city":"Trois-Rivieres",
    "sg:classifiers":[
        {
            "category":"Wholesale",
            "subcategory":"Meat",
            "type":"Manufacturing & Wholesale Goods"
        }
    ],
    "sg:phone":"+1 819 373 3337",
    "sg:postcode":"G8Y 1V7",
    "sg:province":"QC",
    "sg:tags":[
        "butchering"
    ],
    "wof:name":"Boucherie Du Gourmet Enr",
    "wof:placetype":"venue"
},
  "geometry": {"coordinates":[-72.584526,46.355499],"type":"Point"}
}