{
  "type": "Feature",
  "properties": {
    "addr:full":"1700 Manawagonish Rd Saint John NB E2M 3Y5",
    "addr:housenumber":"1700",
    "addr:postcode":"e2m 3y5",
    "addr:street":"Manawagonish Rd",
    "iso:country":"CA",
    "sg:address":"1700 Manawagonish Rd",
    "sg:city":"Saint John",
    "sg:classifiers":[
        {
            "category":"Retail",
            "subcategory":"Veterinary Services",
            "type":"Services"
        }
    ],
    "sg:phone":"+1 506 635 8100",
    "sg:postcode":"E2M 3Y5",
    "sg:province":"NB",
    "sg:tags":[
        "veterinarian"
    ],
    "wof:name":"Wait, John E H DVM",
    "wof:placetype":"venue"
},
  "geometry": {"coordinates":[-66.127106,45.233524],"type":"Point"}
}