{
  "type": "Feature",
  "properties": {
    "addr:full":"Burnaby BC V5C 5Z4",
    "addr:postcode":"v5c 5z4",
    "iso:country":"CA",
    "sg:city":"Burnaby",
    "sg:classifiers":[
        {
            "category":"Organizations",
            "subcategory":"Religious Organization",
            "type":"Services"
        }
    ],
    "sg:phone":"+1 604 291 2635",
    "sg:postcode":"V5C 5Z4",
    "sg:province":"BC",
    "sg:tags":[
        "church"
    ],
    "wof:name":"Chr in the Lord of Vancouver",
    "wof:placetype":"venue"
},
  "geometry": {"coordinates":[-123.00717926,49.2682113647],"type":"Point"}
}