{
  "type": "Feature",
  "properties": {
    "addr:full":"2002 Quilchena Ave Merritt BC V1K 1B8",
    "addr:housenumber":"2002",
    "addr:postcode":"v1k 1b8",
    "addr:street":"Quilchena Ave",
    "iso:country":"CA",
    "sg:address":"2002 Quilchena Ave",
    "sg:city":"Merritt",
    "sg:classifiers":[
        {
            "category":"Banks & Credit Unions",
            "subcategory":"Bank",
            "type":"Services"
        }
    ],
    "sg:phone":"+1 250 378 2296",
    "sg:postcode":"V1K 1B8",
    "sg:province":"BC",
    "wof:name":"Cibc",
    "wof:placetype":"venue"
},
  "geometry": {"coordinates":[-120.78930699999999,50.110008],"type":"Point"}
}