{
  "type": "Feature",
  "properties": {
    "iso:country":"CA",
    "sg:address":"99 Rue Emile-Des Pins",
    "sg:city":"Charlemagne",
    "sg:classifiers":[
        {
            "category":"Restaurant",
            "type":"Food & Drink"
        }
    ],
    "sg:phone":"+1 450 581 0645",
    "sg:postcode":"J5Z 3L6",
    "sg:province":"QC",
    "wof:name":"Rotisserie St-Hubert",
    "wof:placetype":"venue"
},
  "geometry": {"coordinates":[-73.49081420900001,45.7217254639],"type":"Point"}
}