{
  "type": "Feature",
  "properties": {
    "addr:full":"6411 Liverpool St Halifax NS B3L 1Y3",
    "addr:housenumber":"6411",
    "addr:postcode":"b3l 1y3",
    "addr:street":"Liverpool St",
    "iso:country":"CA",
    "sg:address":"6411 Liverpool St",
    "sg:city":"Halifax",
    "sg:classifiers":[
        {
            "category":"Restaurant",
            "type":"Food & Drink"
        }
    ],
    "sg:phone":"+1 902 455 5119",
    "sg:postcode":"B3L 1Y3",
    "sg:province":"NS",
    "wof:name":"Cozy Snack Bar",
    "wof:placetype":"venue"
},
  "geometry": {"coordinates":[-63.608864,44.653088],"type":"Point"}
}