{
  "type": "Feature",
  "properties": {
    "addr:full":"3505 Golden Orchard Dr Mississauga ON L4Y 3H7",
    "addr:housenumber":"3505",
    "addr:postcode":"l4y 3h7",
    "addr:street":"Golden Orchard Dr",
    "iso:country":"CA",
    "sg:address":"3505 Golden Orchard Dr",
    "sg:city":"Mississauga",
    "sg:classifiers":[
        {
            "category":"Recreation",
            "type":"Entertainment"
        }
    ],
    "sg:phone":"+1 905 238 9901",
    "sg:postcode":"L4Y 3H7",
    "sg:province":"ON",
    "sg:tags":[
        "tennis",
        "court"
    ],
    "wof:name":"Applewood Tennis Club",
    "wof:placetype":"venue"
},
  "geometry": {"coordinates":[-79.5996170044,43.6168746948],"type":"Point"}
}