{
  "type": "Feature",
  "properties": {
    "addr:full":"Osoyoos BC V0H 1V0",
    "addr:postcode":"v0h 1v0",
    "iso:country":"CA",
    "sg:city":"Osoyoos",
    "sg:classifiers":[
        {
            "category":"Travel",
            "subcategory":"Travel Agent",
            "type":"Entertainment"
        }
    ],
    "sg:phone":"+1 250 495 3225",
    "sg:postcode":"V0H 1V0",
    "sg:province":"BC",
    "sg:tags":[
        "agency",
        "bureau"
    ],
    "wof:name":"Osoyoos Travel Ltd",
    "wof:placetype":"venue"
},
  "geometry": {"coordinates":[-119.462593,49.029911],"type":"Point"}
}