{
  "type": "Feature",
  "properties": {
    "addr:full":"114 6th Ave Thorhild AB T0A 3J0",
    "addr:housenumber":"114",
    "addr:postcode":"t0a 3j0",
    "addr:street":"6Th Ave",
    "iso:country":"CA",
    "sg:address":"114 6th Ave",
    "sg:city":"Thorhild",
    "sg:classifiers":[
        {
            "category":"Restaurant",
            "type":"Food & Drink"
        }
    ],
    "sg:phone":"+1 780 398 3650",
    "sg:postcode":"T0A 3J0",
    "sg:province":"AB",
    "wof:name":"Parkview Restaurant",
    "wof:placetype":"venue"
},
  "geometry": {"coordinates":[-113.124481,54.158604],"type":"Point"}
}