{
  "type": "Feature",
  "properties": {
    "addr:full":"75 Nugget Ave Scarborough ON M1S 3B1",
    "addr:housenumber":"75",
    "addr:postcode":"m1s 3b1",
    "addr:street":"Nugget Ave",
    "iso:country":"CA",
    "sg:address":"75 Nugget Ave",
    "sg:city":"Scarborough",
    "sg:classifiers":[
        {
            "category":"Manufacturing",
            "subcategory":"Tools & Machinery",
            "type":"Manufacturing & Wholesale Goods"
        }
    ],
    "sg:phone":"+1 416 291 8451",
    "sg:postcode":"M1S 3B1",
    "sg:province":"ON",
    "sg:tags":[
        "machine",
        "shop"
    ],
    "wof:name":"Romax Tool Corp",
    "wof:placetype":"venue"
},
  "geometry": {"coordinates":[-79.2567062378,43.7927932739],"type":"Point"}
}