{
  "type": "Feature",
  "properties": {
    "addr:full":"Woodbridge ON L4L 4C2",
    "addr:postcode":"l4l 4c2",
    "iso:country":"CA",
    "sg:city":"Woodbridge",
    "sg:classifiers":[
        {
            "category":"Manufacturing",
            "subcategory":"Tools & Machinery",
            "type":"Manufacturing & Wholesale Goods"
        }
    ],
    "sg:phone":"+1 905 851 8413",
    "sg:postcode":"L4L 4C2",
    "sg:province":"ON",
    "sg:tags":[
        "electric",
        "motor"
    ],
    "wof:name":"Arco Electric Motors",
    "wof:placetype":"venue"
},
  "geometry": {"coordinates":[-79.5611343384,43.7674293518],"type":"Point"}
}