{
  "type": "Feature",
  "properties": {
    "addr:full":"8736 149 St NW Edmonton AB T5R 1B6",
    "addr:housenumber":"8736",
    "addr:postcode":"t5r 1b6",
    "addr:street":"149 St Nw",
    "iso:country":"CA",
    "sg:address":"8736 149 St NW",
    "sg:city":"Edmonton",
    "sg:classifiers":[
        {
            "category":"Shopping",
            "subcategory":"Florist",
            "type":"Retail Goods"
        }
    ],
    "sg:phone":"+1 780 448 9387",
    "sg:postcode":"T5R 1B6",
    "sg:province":"AB",
    "wof:name":"Grower Direct Fresh Cut Flwrs",
    "wof:placetype":"venue"
},
  "geometry": {"coordinates":[-113.578239,53.520027],"type":"Point"}
}