{
  "type": "Feature",
  "properties": {
    "addr:full":"2626 48 St SE Calgary AB T2B 1M4",
    "addr:housenumber":"2626",
    "addr:postcode":"t2b 1m4",
    "addr:street":"48 St Se",
    "iso:country":"CA",
    "sg:address":"2626 48 St SE",
    "sg:city":"Calgary",
    "sg:classifiers":[
        {
            "category":"Wholesale",
            "subcategory":"Plants",
            "type":"Manufacturing & Wholesale Goods"
        }
    ],
    "sg:phone":"+1 403 203 3338",
    "sg:postcode":"T2B 1M4",
    "sg:province":"AB",
    "sg:tags":[
        "nursery",
        "tree"
    ],
    "wof:name":"Foothills Nurseries",
    "wof:placetype":"venue"
},
  "geometry": {"coordinates":[-113.964119,51.03067],"type":"Point"}
}