{
  "type": "Feature",
  "properties": {
    "addr:full":"1183 Finch Ave W North York ON M3J 2G2",
    "addr:housenumber":"1183",
    "addr:postcode":"m3j 2g2",
    "addr:street":"Finch Ave W",
    "iso:country":"CA",
    "sg:address":"1183 Finch Ave W",
    "sg:city":"North York",
    "sg:classifiers":[
        {
            "category":"Professional",
            "subcategory":"Accounting & Tax Preparation",
            "type":"Services"
        }
    ],
    "sg:phone":"+1 416 636 0201",
    "sg:postcode":"M3J 2G2",
    "sg:province":"ON",
    "sg:tags":[
        "accountant"
    ],
    "wof:name":"Birenbaum, Michael J",
    "wof:placetype":"venue"
},
  "geometry": {"coordinates":[-79.48181200000001,43.765377],"type":"Point"}
}