{
  "type": "Feature",
  "properties": {
    "addr:full":"2277 Queen St E Toronto ON M4E 1G5",
    "addr:housenumber":"2277",
    "addr:postcode":"m4e 1g5",
    "addr:street":"Queen St E",
    "iso:country":"CA",
    "sg:address":"2277 Queen St E",
    "sg:city":"Toronto",
    "sg:classifiers":[
        {
            "category":"Health Services",
            "subcategory":"Chiropractor",
            "type":"Services"
        }
    ],
    "sg:phone":"+1 416 691 2289",
    "sg:postcode":"M4E 1G5",
    "sg:province":"ON",
    "wof:name":"Garbutt, Mark T DC",
    "wof:placetype":"venue"
},
  "geometry": {"coordinates":[-79.29289199999999,43.671429],"type":"Point"}
}