{
  "type": "Feature",
  "properties": {
    "iso:country":"CA",
    "sg:address":"5690 Rosemont Blvd",
    "sg:city":"Montreal",
    "sg:classifiers":[
        {
            "category":"Organizations",
            "subcategory":"Religious Organization",
            "type":"Services"
        }
    ],
    "sg:phone":"+1 514 255 1441",
    "sg:postcode":"H1T 2H2",
    "sg:province":"QC",
    "sg:tags":[
        "school"
    ],
    "wof:name":"Soeurs Franciscaines Missres",
    "wof:placetype":"venue"
},
  "geometry": {"coordinates":[-73.5609664917,45.5768623352],"type":"Point"}
}