{
  "type": "Feature",
  "properties": {
    "addr:full":"565 Shepherd St E Windsor ON N8X 2K8",
    "addr:housenumber":"565",
    "addr:postcode":"n8x 2k8",
    "addr:street":"Shepherd St E",
    "iso:country":"CA",
    "sg:address":"565 Shepherd St E",
    "sg:city":"Windsor",
    "sg:classifiers":[
        {
            "category":"Building & Trades",
            "subcategory":"Construction",
            "type":"Services"
        }
    ],
    "sg:phone":"+1 519 253 1165",
    "sg:postcode":"N8X 2K8",
    "sg:province":"ON",
    "sg:tags":[
        "resurfacing",
        "material",
        "laying",
        "refinishing",
        "floor"
    ],
    "wof:name":"Oak Tree",
    "wof:placetype":"venue"
},
  "geometry": {"coordinates":[-83.01976000000001,42.303238],"type":"Point"}
}