{
  "type": "Feature",
  "properties": {
    "addr:full":"RR 2 Kerwood ON N0M 2B0",
    "addr:postcode":"n0m 2b0",
    "addr:street":"Rr 2",
    "iso:country":"CA",
    "sg:address":"RR 2",
    "sg:city":"Kerwood",
    "sg:phone":"+1 519 247 3314",
    "sg:postcode":"N0M 2B0",
    "sg:province":"ON",
    "sg:tags":[
        "equipment",
        "station"
    ],
    "wof:name":"New Horizon Steel Ltd",
    "wof:placetype":"venue"
},
  "geometry": {"coordinates":[-81.74376700000001,42.943893],"type":"Point"}
}