{
  "type": "Feature",
  "properties": {
    "addr:full":"526 Grays Rd # B Hamilton ON L8E 2Z4",
    "addr:housenumber":"526",
    "addr:postcode":"l8e 2z4",
    "addr:street":"Grays Rd # B",
    "iso:country":"CA",
    "sg:address":"526 Grays Rd # B",
    "sg:city":"Hamilton",
    "sg:classifiers":[
        {
            "category":"Insurance",
            "subcategory":"Insurance Agent",
            "type":"Services"
        }
    ],
    "sg:phone":"+1 905 561 0100",
    "sg:postcode":"L8E 2Z4",
    "sg:province":"ON",
    "wof:name":"Burrowes Insurance Brokers",
    "wof:placetype":"venue"
},
  "geometry": {"coordinates":[-79.737121582,43.2393722534],"type":"Point"}
}