{
  "type": "Feature",
  "properties": {
    "addr:full":"1820 Hastings St E Vancouver BC V5L 1T2",
    "addr:housenumber":"1820",
    "addr:postcode":"v5l 1t2",
    "addr:street":"Hastings St E",
    "iso:country":"CA",
    "sg:address":"1820 Hastings St E",
    "sg:city":"Vancouver",
    "sg:classifiers":[
        {
            "category":"Shopping",
            "subcategory":"Used Merchandise",
            "type":"Retail Goods"
        }
    ],
    "sg:phone":"+1 604 254 4282",
    "sg:postcode":"V5L 1T2",
    "sg:province":"BC",
    "sg:tags":[
        "second",
        "store",
        "hand"
    ],
    "wof:name":"Value Village Stores Ltd",
    "wof:placetype":"venue"
},
  "geometry": {"coordinates":[-123.067528,49.281094],"type":"Point"}
}