{
  "type": "Feature",
  "properties": {
    "addr:full":"359 Water St Miramichi NB E1V 3G4",
    "addr:housenumber":"359",
    "addr:postcode":"e1v 3g4",
    "addr:street":"Water St",
    "iso:country":"CA",
    "sg:address":"359 Water St",
    "sg:city":"Miramichi",
    "sg:classifiers":[
        {
            "category":"Personal",
            "subcategory":"Barber",
            "type":"Services"
        }
    ],
    "sg:phone":"+1 506 624 7779",
    "sg:postcode":"E1V 3G4",
    "sg:province":"NB",
    "wof:name":"Morrison's Barber Shop",
    "wof:placetype":"venue"
},
  "geometry": {"coordinates":[-65.546936,47.001194],"type":"Point"}
}