{
  "type": "Feature",
  "properties": {
    "addr:full":"348 Main St Port Dover ON N0A 1N0",
    "addr:housenumber":"348",
    "addr:postcode":"n0a 1n0",
    "addr:street":"Main St",
    "iso:country":"CA",
    "sg:address":"348 Main St",
    "sg:city":"Port Dover",
    "sg:classifiers":[
        {
            "category":"Travel",
            "subcategory":"Hotels & Motels",
            "type":"Entertainment"
        }
    ],
    "sg:phone":"+1 519 583 0416",
    "sg:postcode":"N0A 1N0",
    "sg:province":"ON",
    "wof:name":"Angelo's of Dover",
    "wof:placetype":"venue"
},
  "geometry": {"coordinates":[-80.2041854858,42.787311554],"type":"Point"}
}