{
  "type": "Feature",
  "properties": {
    "addr:full":"Saskatoon SK S7N 1Y7",
    "addr:postcode":"s7n 1y7",
    "iso:country":"CA",
    "sg:city":"Saskatoon",
    "sg:classifiers":[
        {
            "category":"Wholesale",
            "subcategory":"Durable Goods & Equipment",
            "type":"Manufacturing & Wholesale Goods"
        }
    ],
    "sg:phone":"+1 306 373 3777",
    "sg:postcode":"S7N 1Y7",
    "sg:province":"SK",
    "sg:tags":[
        "fire",
        "extinguisher",
        "protection"
    ],
    "wof:name":"Abc Fire Extinguisher CO",
    "wof:placetype":"venue"
},
  "geometry": {"coordinates":[-106.597213745,52.1301651001],"type":"Point"}
}