{
  "type": "Feature",
  "properties": {
    "addr:full":"Grande Prairie AB T8V 7Z5",
    "addr:postcode":"t8v 7z5",
    "iso:country":"CA",
    "sg:city":"Grande Prairie",
    "sg:classifiers":[
        {
            "category":"Building & Trades",
            "subcategory":"Equipment Rental",
            "type":"Services"
        }
    ],
    "sg:phone":"+1 780 532 2047",
    "sg:postcode":"T8V 7Z5",
    "sg:province":"AB",
    "sg:tags":[
        "helicopter",
        "aircraft",
        "leasing",
        "charter"
    ],
    "wof:name":"Canadian Helicopters Ltd",
    "wof:placetype":"venue"
},
  "geometry": {"coordinates":[-118.876198,55.179447],"type":"Point"}
}