{
  "type": "Feature",
  "properties": {
    "addr:full":"30 Kennedy Rd S # A Brampton ON L6W 3E2",
    "addr:housenumber":"30",
    "addr:postcode":"l6w 3e2",
    "addr:street":"Kennedy Rd S # A",
    "iso:country":"CA",
    "sg:address":"30 Kennedy Rd S # A",
    "sg:city":"Brampton",
    "sg:classifiers":[
        {
            "category":"Restaurant",
            "type":"Food & Drink"
        }
    ],
    "sg:phone":"+1 905 456 7647",
    "sg:postcode":"L6W 3E2",
    "sg:province":"ON",
    "wof:name":"Jack's Backyard",
    "wof:placetype":"venue"
},
  "geometry": {"coordinates":[-79.7451705933,43.692653656],"type":"Point"}
}