{
  "type": "Feature",
  "properties": {
    "iso:country":"CA",
    "sg:address":"45 Riviera Dr",
    "sg:city":"Markham",
    "sg:classifiers":[
        {
            "category":"Building & Trades",
            "subcategory":"Construction",
            "type":"Services"
        }
    ],
    "sg:phone":"+1 416 391 4635",
    "sg:postcode":"L3R 5J6",
    "sg:province":"ON",
    "sg:tags":[
        "ramp"
    ],
    "wof:name":"Aerdon Dock Levellers",
    "wof:placetype":"venue"
},
  "geometry": {"coordinates":[-79.3442993164,43.8320503235],"type":"Point"}
}