{
  "type": "Feature",
  "properties": {
    "addr:full":"Orillia ON L3V 1V7",
    "addr:postcode":"l3v 1v7",
    "iso:country":"CA",
    "sg:city":"Orillia",
    "sg:classifiers":[
        {
            "category":"Personal",
            "subcategory":"Tattoo Parlor",
            "type":"Services"
        }
    ],
    "sg:phone":"+1 705 326 4380",
    "sg:postcode":"L3V 1V7",
    "sg:province":"ON",
    "sg:tags":[
        "tattooing"
    ],
    "wof:name":"Bodyco",
    "wof:placetype":"venue"
},
  "geometry": {"coordinates":[-79.41615299999999,44.609901],"type":"Point"}
}