{
  "type": "Feature",
  "properties": {
    "addr:full":"3282 Oakglade Cres Mississauga ON L5C 1X3",
    "addr:housenumber":"3282",
    "addr:postcode":"l5c 1x3",
    "addr:street":"Oakglade Cres",
    "iso:country":"CA",
    "sg:address":"3282 Oakglade Cres",
    "sg:city":"Mississauga",
    "sg:classifiers":[
        {
            "category":"Shopping",
            "subcategory":"Luggage & Leather Goods",
            "type":"Retail Goods"
        }
    ],
    "sg:phone":"+1 905 282 9394",
    "sg:postcode":"L5C 1X3",
    "sg:province":"ON",
    "wof:name":"Chokwanger Leather CO Ltd",
    "wof:placetype":"venue"
},
  "geometry": {"coordinates":[-79.64965100000001,43.565323],"type":"Point"}
}