{
  "type": "Feature",
  "properties": {
    "addr:full":"PO Box 157 Didsbury AB T0M 0W0",
    "addr:housenumber":"po",
    "addr:postcode":"t0m 0w0",
    "addr:street":"Box 157",
    "iso:country":"CA",
    "sg:address":"PO Box 157",
    "sg:city":"Didsbury",
    "sg:classifiers":[
        {
            "category":"Building & Trades",
            "subcategory":"Electrical",
            "type":"Services"
        }
    ],
    "sg:phone":"+1 403 335 8831",
    "sg:postcode":"T0M 0W0",
    "sg:province":"AB",
    "sg:tags":[
        "electric",
        "contractor"
    ],
    "wof:name":"Eagle Electric",
    "wof:placetype":"venue"
},
  "geometry": {"coordinates":[-114.14054107699999,51.6662712097],"type":"Point"}
}