{
  "type": "Feature",
  "properties": {
    "addr:full":"204 Rue Gastineau Saint-Eustache QC J7P 3T7",
    "addr:housenumber":"204",
    "addr:postcode":"j7p 3t7",
    "addr:street":"Rue Gastineau",
    "iso:country":"CA",
    "sg:address":"204 Rue Gastineau",
    "sg:city":"Saint-Eustache",
    "sg:classifiers":[
        {
            "category":"Home & Garden",
            "subcategory":"Carpets & Floor Coverings",
            "type":"Retail Goods"
        }
    ],
    "sg:phone":"+1 514 382 2048",
    "sg:postcode":"J7P 3T7",
    "sg:province":"QC",
    "sg:tags":[
        "dealer",
        "rug"
    ],
    "wof:name":"Paul Boisclair Tapis Enrg",
    "wof:placetype":"venue"
},
  "geometry": {"coordinates":[-73.8838272095,45.5674858093],"type":"Point"}
}