{
  "type": "Feature",
  "properties": {
    "iso:country":"CA",
    "sg:address":"7 Druken Cres",
    "sg:city":"Shea Heights",
    "sg:classifiers":[
        {
            "category":"Building & Trades",
            "subcategory":"Construction",
            "type":"Services"
        }
    ],
    "sg:phone":"+1 709 579 3962",
    "sg:postcode":"A0A 1J0",
    "sg:province":"NL",
    "sg:tags":[
        "painter"
    ],
    "wof:name":"Triple E Painters",
    "wof:placetype":"venue"
},
  "geometry": {"coordinates":[-52.7088012695,47.5488739014],"type":"Point"}
}