{
  "type": "Feature",
  "properties": {
    "addr:full":"125 John St W Exeter ON N0M 1S2",
    "addr:housenumber":"125",
    "addr:postcode":"n0m 1s2",
    "addr:street":"John St W",
    "iso:country":"CA",
    "sg:address":"125 John St W",
    "sg:city":"Exeter",
    "sg:classifiers":[
        {
            "category":"Organizations",
            "subcategory":"Professional Association",
            "type":"Services"
        }
    ],
    "sg:phone":"+1 519 235 3307",
    "sg:postcode":"N0M 1S2",
    "sg:province":"ON",
    "wof:name":"Big Brothers & Big Sisters",
    "wof:placetype":"venue"
},
  "geometry": {"coordinates":[-81.48500061039999,43.3452796936],"type":"Point"}
}