{
  "type": "Feature",
  "properties": {
    "iso:country":"CA",
    "sg:address":"380 Boul Harwood",
    "sg:city":"Vaudreuil-Dorion",
    "sg:classifiers":[
        {
            "category":"Shopping",
            "subcategory":"Pharmacy",
            "type":"Retail Goods"
        }
    ],
    "sg:phone":"+1 450 455 6141",
    "sg:postcode":"J7V 7L6",
    "sg:province":"QC",
    "wof:name":"Jean Coutu",
    "wof:placetype":"venue"
},
  "geometry": {"coordinates":[-74.0194015503,45.3790664673],"type":"Point"}
}