{
  "type": "Feature",
  "properties": {
    "addr:full":"16405 Av Bourdages S Saint-Hyacinthe QC J2T 4G9",
    "addr:housenumber":"16405",
    "addr:postcode":"j2t 4g9",
    "addr:street":"Av Bourdages S",
    "iso:country":"CA",
    "sg:address":"16405 Av Bourdages S",
    "sg:city":"Saint-Hyacinthe",
    "sg:classifiers":[
        {
            "category":"Health Services",
            "subcategory":"Doctor",
            "type":"Services"
        }
    ],
    "sg:phone":"+1 450 773 6734",
    "sg:postcode":"J2T 4G9",
    "sg:province":"QC",
    "sg:tags":[
        "physician",
        "surgeon"
    ],
    "wof:name":"Labelle, Robert MD",
    "wof:placetype":"venue"
},
  "geometry": {"coordinates":[-72.943611,45.616661],"type":"Point"}
}