{
  "type": "Feature",
  "properties": {
    "addr:full":"1710 Bonhill Rd Mississauga ON L5T 1C8",
    "addr:housenumber":"1710",
    "addr:postcode":"l5t 1c8",
    "addr:street":"Bonhill Rd",
    "iso:country":"CA",
    "sg:address":"1710 Bonhill Rd",
    "sg:city":"Mississauga",
    "sg:classifiers":[
        {
            "category":"Wholesale",
            "subcategory":"Stationery",
            "type":"Manufacturing & Wholesale Goods"
        }
    ],
    "sg:phone":"+1 905 670 3090",
    "sg:postcode":"L5T 1C8",
    "sg:province":"ON",
    "sg:tags":[
        "cards",
        "greeting"
    ],
    "wof:name":"Beaucraft Greeting Cards",
    "wof:placetype":"venue"
},
  "geometry": {"coordinates":[-79.6512756348,43.666847229],"type":"Point"}
}