{
  "type": "Feature",
  "properties": {
    "addr:full":"537 Cruice Lane Gibsons BC V0N 1V0",
    "addr:housenumber":"537",
    "addr:postcode":"v0n 1v0",
    "addr:street":"Cruice Lane",
    "iso:country":"CA",
    "sg:address":"537 Cruice Lane",
    "sg:city":"Gibsons",
    "sg:classifiers":[
        {
            "category":"Retail",
            "subcategory":"Repair Shop",
            "type":"Services"
        }
    ],
    "sg:phone":"+1 604 886 9959",
    "sg:postcode":"V0N 1V0",
    "sg:province":"BC",
    "sg:tags":[
        "appliance"
    ],
    "wof:name":"Metz Appliance Sales & Svc",
    "wof:placetype":"venue"
},
  "geometry": {"coordinates":[-123.504768,49.402805],"type":"Point"}
}