{
  "type": "Feature",
  "properties": {
    "iso:country":"CA",
    "sg:city":"Cheneville",
    "sg:classifiers":[
        {
            "category":"Building & Trades",
            "subcategory":"Construction",
            "type":"Services"
        }
    ],
    "sg:phone":"+1 819 428 7008",
    "sg:postcode":"J0V 1E0",
    "sg:province":"QC",
    "sg:tags":[
        "maker",
        "cabinet"
    ],
    "wof:name":"Boiseries 3 Dimensions",
    "wof:placetype":"venue"
},
  "geometry": {"coordinates":[-75.05462646479999,45.8749809265],"type":"Point"}
}