{
  "type": "Feature",
  "properties": {
    "addr:full":"22 Yonge St N Elmvale ON L0L 1P0",
    "addr:housenumber":"22",
    "addr:postcode":"l0l 1p0",
    "addr:street":"Yonge St N",
    "iso:country":"CA",
    "sg:address":"22 Yonge St N",
    "sg:city":"Elmvale",
    "sg:classifiers":[
        {
            "category":"Organizations",
            "subcategory":"Religious Organization",
            "type":"Services"
        }
    ],
    "sg:phone":"+1 705 322 4556",
    "sg:postcode":"L0L 1P0",
    "sg:province":"ON",
    "sg:tags":[
        "church"
    ],
    "wof:name":"Wycliffe Anglican Church",
    "wof:placetype":"venue"
},
  "geometry": {"coordinates":[-79.86779,44.585224],"type":"Point"}
}