{
  "type": "Feature",
  "properties": {
    "addr:full":"90 Mcmurray St Bracebridge ON P1L 2G1",
    "addr:housenumber":"90",
    "addr:postcode":"p1l 2g1",
    "addr:street":"Mcmurray St",
    "iso:country":"CA",
    "sg:address":"90 Mcmurray St",
    "sg:city":"Bracebridge",
    "sg:classifiers":[
        {
            "category":"Social Services",
            "subcategory":"Child Care",
            "type":"Services"
        }
    ],
    "sg:phone":"+1 705 645 2229",
    "sg:postcode":"P1L 2G1",
    "sg:province":"ON",
    "sg:tags":[
        "school"
    ],
    "wof:name":"Bracebridge Public School",
    "wof:placetype":"venue"
},
  "geometry": {"coordinates":[-79.31564299999999,45.042053],"type":"Point"}
}