{
  "type": "Feature",
  "properties": {
    "addr:full":"Edmonton AB T6H 5R7",
    "addr:postcode":"t6h 5r7",
    "iso:country":"CA",
    "sg:city":"Edmonton",
    "sg:classifiers":[
        {
            "category":"Banks & Credit Unions",
            "subcategory":"Investment Brokerage",
            "type":"Services"
        }
    ],
    "sg:phone":"+1 780 436 7777",
    "sg:postcode":"T6H 5R7",
    "sg:province":"AB",
    "sg:tags":[
        "consultant",
        "planning",
        "financial",
        "advisory"
    ],
    "wof:name":"Kofin Financial Group",
    "wof:placetype":"venue"
},
  "geometry": {"coordinates":[-113.49490400000001,53.482243],"type":"Point"}
}