{
  "type": "Feature",
  "properties": {
    "addr:full":"387 40E Av Lachine QC H8T 2E7",
    "addr:housenumber":"387",
    "addr:postcode":"h8t 2e7",
    "addr:street":"40E Av",
    "iso:country":"CA",
    "sg:address":"387 40E Av",
    "sg:city":"Lachine",
    "sg:classifiers":[
        {
            "category":"Social Services",
            "type":"Services"
        }
    ],
    "sg:phone":"+1 514 634 8944",
    "sg:postcode":"H8T 2E7",
    "sg:province":"QC",
    "sg:tags":[
        "organization",
        "welfare"
    ],
    "wof:name":"Avatil Inc",
    "wof:placetype":"venue"
},
  "geometry": {"coordinates":[-73.701126,45.439281],"type":"Point"}
}