{
  "type": "Feature",
  "properties": {
    "addr:full":"192 Lyons Branch Rd Centreville NS B0P 1J0",
    "addr:housenumber":"192",
    "addr:postcode":"b0p 1j0",
    "addr:street":"Lyons Branch Rd",
    "iso:country":"CA",
    "sg:address":"192 Lyons Branch Rd",
    "sg:city":"Centreville",
    "sg:classifiers":[
        {
            "category":"Building & Trades",
            "subcategory":"Construction",
            "type":"Services"
        }
    ],
    "sg:phone":"+1 902 582 3865",
    "sg:postcode":"B0P 1J0",
    "sg:province":"NS",
    "sg:tags":[
        "excavating",
        "contractor"
    ],
    "wof:name":"Reg Kane's Excavating",
    "wof:placetype":"venue"
},
  "geometry": {"coordinates":[-64.528542,45.133881],"type":"Point"}
}