{
  "type": "Feature",
  "properties": {
    "addr:full":"30 Mckay Cres Markham ON L3R 3M6",
    "addr:housenumber":"30",
    "addr:postcode":"l3r 3m6",
    "addr:street":"Mckay Cres",
    "iso:country":"CA",
    "sg:address":"30 Mckay Cres",
    "sg:city":"Markham",
    "sg:classifiers":[
        {
            "category":"Real Estate",
            "subcategory":"Real Estate Agent",
            "type":"Services"
        }
    ],
    "sg:phone":"+1 905 513 1298",
    "sg:postcode":"L3R 3M6",
    "sg:province":"ON",
    "wof:name":"Amek Realty Inc",
    "wof:placetype":"venue"
},
  "geometry": {"coordinates":[-79.3197937012,43.8712692261],"type":"Point"}
}