{
  "type": "Feature",
  "properties": {
    "addr:full":"380 Eagleson Rd Kanata ON K2M 1G8",
    "addr:housenumber":"380",
    "addr:postcode":"k2m 1g8",
    "addr:street":"Eagleson Rd",
    "iso:country":"CA",
    "sg:address":"380 Eagleson Rd",
    "sg:city":"Kanata",
    "sg:classifiers":[
        {
            "category":"Government",
            "subcategory":"Fire Station",
            "type":"Public Place"
        }
    ],
    "sg:phone":"+1 ",
    "sg:postcode":"K2M 1G8",
    "sg:province":"ON",
    "sg:tags":[
        "department"
    ],
    "wof:name":"Kanata Fire Prevention",
    "wof:placetype":"venue"
},
  "geometry": {"coordinates":[-75.8723526001,45.2953872681],"type":"Point"}
}