{
  "type": "Feature",
  "properties": {
    "iso:country":"CA",
    "sg:address":"53 Division St",
    "sg:city":"Oshawa",
    "sg:classifiers":[
        {
            "category":"Personal",
            "subcategory":"Beauty Salon",
            "type":"Services"
        }
    ],
    "sg:phone":"+1 905 721 2838",
    "sg:postcode":"L1G 5L8",
    "sg:province":"ON",
    "wof:name":"Marg's Hair Design",
    "wof:placetype":"venue"
},
  "geometry": {"coordinates":[-78.85762786870001,43.9006309509],"type":"Point"}
}