{
  "type": "Feature",
  "properties": {
    "iso:country":"CA",
    "sg:address":"264 Broadway E",
    "sg:city":"Vancouver",
    "sg:classifiers":[
        {
            "category":"Food & Beverages",
            "subcategory":"Specialty",
            "type":"Retail Goods"
        }
    ],
    "sg:phone":"+1 604 879 2800",
    "sg:postcode":"V5T 1W3",
    "sg:province":"BC",
    "sg:tags":[
        "health",
        "diet"
    ],
    "wof:name":"Genesis Nutrition",
    "wof:placetype":"venue"
},
  "geometry": {"coordinates":[-123.099601746,49.2628097534],"type":"Point"}
}