{
  "type": "Feature",
  "properties": {
    "addr:full":"280 1st Ave E Avonlea SK S0H 0C0",
    "addr:housenumber":"280",
    "addr:postcode":"s0h 0c0",
    "addr:street":"1St Ave E Avonlea",
    "iso:country":"CA",
    "sg:address":"280 1st Ave E",
    "sg:city":"Avonlea",
    "sg:classifiers":[
        {
            "category":"Wholesale",
            "subcategory":"Machinery & Supplies",
            "type":"Manufacturing & Wholesale Goods"
        }
    ],
    "sg:phone":"+1 306 868 2022",
    "sg:postcode":"S0H 0C0",
    "sg:province":"SK",
    "sg:tags":[
        "automobile",
        "dealer"
    ],
    "wof:name":"Nelson Motors & Equipment Ltd",
    "wof:placetype":"venue"
},
  "geometry": {"coordinates":[-105.055336,50.015781],"type":"Point"}
}