{
  "type": "Feature",
  "properties": {
    "addr:full":"7126 Av Royale Chateau-Richer QC G0A 1N0",
    "addr:housenumber":"7126",
    "addr:postcode":"g0a 1n0",
    "addr:street":"Av Royale",
    "iso:country":"CA",
    "sg:address":"7126 Av Royale",
    "sg:city":"Chateau-Richer",
    "sg:classifiers":[
        {
            "category":"Travel",
            "subcategory":"Hotels & Motels",
            "type":"Entertainment"
        }
    ],
    "sg:phone":"+1 418 824 3852",
    "sg:postcode":"G0A 1N0",
    "sg:province":"QC",
    "sg:tags":[
        "inn"
    ],
    "wof:name":"Auberge Du Petit Pre",
    "wof:placetype":"venue"
},
  "geometry": {"coordinates":[-71.05719000000001,46.940853],"type":"Point"}
}