{
  "type": "Feature",
  "properties": {
    "addr:full":"45 4E Rue Montmagny QC G5V 3K8",
    "addr:housenumber":"45",
    "addr:postcode":"g5v 3k8",
    "addr:street":"4E Rue Montmagny",
    "iso:country":"CA",
    "sg:address":"45 4E Rue",
    "sg:city":"Montmagny",
    "sg:classifiers":[
        {
            "category":"Home & Garden",
            "subcategory":"Furniture",
            "type":"Retail Goods"
        }
    ],
    "sg:phone":"+1 418 248 0255",
    "sg:postcode":"G5V 3K8",
    "sg:province":"QC",
    "sg:tags":[
        "equipment",
        "kitchen",
        "cabinet"
    ],
    "wof:name":"Industrie Caron Meubles Inc",
    "wof:placetype":"venue"
},
  "geometry": {"coordinates":[-70.56321,46.974716],"type":"Point"}
}