{
  "type": "Feature",
  "properties": {
    "addr:full":"1318 Line 2 Rd Niagara on the Lake ON L0S 1J0",
    "addr:housenumber":"1318",
    "addr:postcode":"l0s 1j0",
    "addr:street":"Line 2 Rd;On",
    "iso:country":"CA",
    "sg:address":"1318 Line 2 Rd",
    "sg:city":"Niagara on the Lake",
    "sg:classifiers":[
        {
            "category":"Travel",
            "subcategory":"Hotels & Motels",
            "type":"Entertainment"
        }
    ],
    "sg:phone":"+1 905 468 6685",
    "sg:postcode":"L0S 1J0",
    "sg:province":"ON",
    "sg:tags":[
        "breakfast",
        "accommodation",
        "bed"
    ],
    "wof:name":"Whispering Pines Bed & Brkfst",
    "wof:placetype":"venue"
},
  "geometry": {"coordinates":[-79.077156,43.219101],"type":"Point"}
}