{
  "type": "Feature",
  "properties": {
    "iso:country":"CA",
    "sg:address":"242 Place DE Noirmoutier",
    "sg:city":"Laval",
    "sg:classifiers":[
        {
            "category":"Home & Garden",
            "subcategory":"Household Appliances",
            "type":"Retail Goods"
        }
    ],
    "sg:phone":"+1 450 669 4033",
    "sg:postcode":"H7N 5M2",
    "sg:province":"QC",
    "wof:name":"M J Morin Enrg",
    "wof:placetype":"venue"
},
  "geometry": {"coordinates":[-73.7024307251,45.5603981018],"type":"Point"}
}