{
  "type": "Feature",
  "properties": {
    "addr:full":"11031 124 St NW Edmonton AB T5M 0J5",
    "addr:housenumber":"11031",
    "addr:postcode":"t5m 0j5",
    "addr:street":"124 St Nw",
    "iso:country":"CA",
    "sg:address":"11031 124 St NW",
    "sg:city":"Edmonton",
    "sg:classifiers":[
        {
            "category":"Organizations",
            "subcategory":"Non-profit Organization",
            "type":"Services"
        }
    ],
    "sg:phone":"+1 780 452 5791",
    "sg:postcode":"T5M 0J5",
    "sg:province":"AB",
    "sg:tags":[
        "charitable",
        "institution"
    ],
    "wof:name":"Uncles & Aunts At Large",
    "wof:placetype":"venue"
},
  "geometry": {"coordinates":[-113.535751343,53.5578536987],"type":"Point"}
}