{
  "type": "Feature",
  "properties": {
    "addr:full":"39 Delaware Ave Toronto ON M6H 2S8",
    "addr:housenumber":"39",
    "addr:postcode":"m6h 2s8",
    "addr:street":"Delaware Ave",
    "iso:country":"CA",
    "sg:address":"39 Delaware Ave",
    "sg:city":"Toronto",
    "sg:classifiers":[
        {
            "category":"Professional",
            "subcategory":"Management & Consulting",
            "type":"Services"
        }
    ],
    "sg:phone":"+1 416 534 7115",
    "sg:postcode":"M6H 2S8",
    "sg:province":"ON",
    "sg:tags":[
        "consultant",
        "government"
    ],
    "wof:name":"Leonard Domino & Assoc",
    "wof:placetype":"venue"
},
  "geometry": {"coordinates":[-79.42561340330001,43.6554527283],"type":"Point"}
}