{
  "type": "Feature",
  "properties": {
    "addr:full":"2571 Av Royale Beauport QC G1C 1S3",
    "addr:housenumber":"2571",
    "addr:postcode":"qc g1c 1s3",
    "addr:street":"Av Royale",
    "iso:country":"CA",
    "sg:address":"2571 Av Royale",
    "sg:city":"Beauport",
    "sg:classifiers":[
        {
            "category":"Food & Beverages",
            "subcategory":"Meat & Fish",
            "type":"Retail Goods"
        }
    ],
    "sg:phone":"+1 418 660 5227",
    "sg:postcode":"G1C 1S3",
    "sg:province":"QC",
    "sg:tags":[
        "seafood"
    ],
    "wof:name":"Poissonnerie Des Chutes",
    "wof:placetype":"venue"
},
  "geometry": {"coordinates":[-71.1505203247,46.8906936646],"type":"Point"}
}