{
  "type": "Feature",
  "properties": {
    "addr:full":"Victoria BC V8S 1G1",
    "addr:postcode":"v8s 1g1",
    "iso:country":"CA",
    "sg:city":"Victoria",
    "sg:classifiers":[
        {
            "category":"Shopping",
            "subcategory":"Pharmacy",
            "type":"Retail Goods"
        }
    ],
    "sg:phone":"+1 250 598 9232",
    "sg:postcode":"V8S 1G1",
    "sg:province":"BC",
    "wof:name":"Peoples Drug Mart",
    "wof:placetype":"venue"
},
  "geometry": {"coordinates":[-123.337287903,48.4122962952],"type":"Point"}
}