{
  "type": "Feature",
  "properties": {
    "addr:full":"1240 Bay St Toronto ON M5R 2A7",
    "addr:housenumber":"1240",
    "addr:postcode":"m5r 2a7",
    "addr:street":"Bay St",
    "iso:country":"CA",
    "sg:address":"1240 Bay St",
    "sg:city":"Toronto",
    "sg:classifiers":[
        {
            "category":"Professional",
            "subcategory":"Lawyer & Legal Services",
            "type":"Services"
        }
    ],
    "sg:phone":"+1 416 961 1981",
    "sg:postcode":"M5R 2A7",
    "sg:province":"ON",
    "sg:tags":[
        "attorney"
    ],
    "wof:name":"Jane Harvey Assoc Lawyers",
    "wof:placetype":"venue"
},
  "geometry": {"coordinates":[-79.3898925781,43.6704025269],"type":"Point"}
}