{
  "type": "Feature",
  "properties": {
    "addr:full":"24 Main St W Saint John NB E2M 3N1",
    "addr:housenumber":"24",
    "addr:postcode":"e2m 3n1",
    "addr:street":"Main St W",
    "iso:country":"CA",
    "sg:address":"24 Main St W",
    "sg:city":"Saint John",
    "sg:classifiers":[
        {
            "category":"Restaurant",
            "type":"Food & Drink"
        }
    ],
    "sg:phone":"+1 506 635 1886",
    "sg:postcode":"E2M 3N1",
    "sg:province":"NB",
    "wof:name":"Buccaneer's Pub & Eatery",
    "wof:placetype":"venue"
},
  "geometry": {"coordinates":[-66.09921300000001,45.256924],"type":"Point"}
}