{
  "type": "Feature",
  "properties": {
    "addr:full":"244 Rue DE Cherbourg Saint-Nicolas QC G7A 1P6",
    "addr:housenumber":"244",
    "addr:postcode":"g7a 1p6",
    "addr:street":"Rue De Cherbourg",
    "iso:country":"CA",
    "sg:address":"244 Rue DE Cherbourg",
    "sg:city":"Saint-Nicolas",
    "sg:classifiers":[
        {
            "category":"Insurance",
            "subcategory":"Insurance Agent",
            "type":"Services"
        }
    ],
    "sg:phone":"+1 418 831 6875",
    "sg:postcode":"G7A 1P6",
    "sg:province":"QC",
    "wof:name":"Jacques Gingras Agent General",
    "wof:placetype":"venue"
},
  "geometry": {"coordinates":[-71.30027,46.709618],"type":"Point"}
}