{
  "type": "Feature",
  "properties": {
    "addr:full":"Calgary AB T2R 1A7",
    "addr:postcode":"t2r 1a7",
    "iso:country":"CA",
    "sg:city":"Calgary",
    "sg:classifiers":[
        {
            "category":"Professional",
            "subcategory":"Engineering",
            "type":"Services"
        }
    ],
    "sg:phone":"+1 403 802 1090",
    "sg:postcode":"T2R 1A7",
    "sg:province":"AB",
    "sg:tags":[
        "engineer"
    ],
    "wof:name":"Mech Wave Engineering Ltd",
    "wof:placetype":"venue"
},
  "geometry": {"coordinates":[-114.079063,51.038754],"type":"Point"}
}