{
  "type": "Feature",
  "properties": {
    "addr:full":"Vermilion Bay ON P0V 2V0",
    "addr:postcode":"p0v 2v0",
    "addr:street":"Vermilion Bay",
    "iso:country":"CA",
    "sg:city":"Vermilion Bay",
    "sg:classifiers":[
        {
            "category":"Manufacturing",
            "subcategory":"Watercraft",
            "type":"Manufacturing & Wholesale Goods"
        }
    ],
    "sg:phone":"+1 807 227 2080",
    "sg:postcode":"P0V 2V0",
    "sg:province":"ON",
    "sg:tags":[
        "boat"
    ],
    "wof:name":"Naden Boats Ltd",
    "wof:placetype":"venue"
},
  "geometry": {"coordinates":[-93.383743,49.858482],"type":"Point"}
}