{
  "type": "Feature",
  "properties": {
    "addr:full":"1960 Chaplin St W Swift Current SK S9H 5G6",
    "addr:housenumber":"1960",
    "addr:postcode":"s9h 5g6",
    "addr:street":"Chaplin St W",
    "iso:country":"CA",
    "sg:address":"1960 Chaplin St W",
    "sg:city":"Swift Current",
    "sg:classifiers":[
        {
            "category":"Freight",
            "type":"Transportation"
        }
    ],
    "sg:phone":"+1 306 773 1437",
    "sg:postcode":"S9H 5G6",
    "sg:province":"SK",
    "sg:tags":[
        "warehouse",
        "commercial"
    ],
    "wof:name":"Swift Mini Storage",
    "wof:placetype":"venue"
},
  "geometry": {"coordinates":[-107.826408,50.28471],"type":"Point"}
}