{
  "type": "Feature",
  "properties": {
    "addr:full":"6032 Boul Monk Montreal QC H4E 3H6",
    "addr:housenumber":"6032",
    "addr:postcode":"h4e 3h6",
    "addr:street":"Boul Monk",
    "iso:country":"CA",
    "sg:address":"6032 Boul Monk",
    "sg:city":"Montreal",
    "sg:classifiers":[
        {
            "category":"Health Services",
            "subcategory":"Chiropractor",
            "type":"Services"
        }
    ],
    "sg:phone":"+1 514 766 1577",
    "sg:postcode":"H4E 3H6",
    "sg:province":"QC",
    "wof:name":"Centre Chiropratique Ville",
    "wof:placetype":"venue"
},
  "geometry": {"coordinates":[-73.59569500000001,45.458183],"type":"Point"}
}