{
  "type": "Feature",
  "properties": {
    "addr:full":"RR 2 Warsaw ON K0L 3A0",
    "addr:postcode":"k0l 3a0",
    "addr:street":"Rr 2",
    "iso:country":"CA",
    "sg:address":"RR 2",
    "sg:city":"Warsaw",
    "sg:classifiers":[
        {
            "category":"Recreation",
            "subcategory":"Marina",
            "type":"Entertainment"
        }
    ],
    "sg:phone":"+1 705 652 7566",
    "sg:postcode":"K0L 3A0",
    "sg:province":"ON",
    "sg:tags":[
        "repairing",
        "antique",
        "boat"
    ],
    "wof:name":"Ken Simmonds Antiques",
    "wof:placetype":"venue"
},
  "geometry": {"coordinates":[-78.13716125489999,44.4280853271],"type":"Point"}
}