{
  "type": "Feature",
  "properties": {
    "addr:full":"8525 Cambie St Vancouver BC V6P 3J9",
    "addr:housenumber":"8525",
    "addr:postcode":"v6p 3j9",
    "addr:street":"Cambie St",
    "iso:country":"CA",
    "sg:address":"8525 Cambie St",
    "sg:city":"Vancouver",
    "sg:classifiers":[
        {
            "category":"Retail",
            "subcategory":"Auto Repair",
            "type":"Services"
        }
    ],
    "sg:phone":"+1 604 324 1124",
    "sg:postcode":"V6P 3J9",
    "sg:province":"BC",
    "sg:tags":[
        "body",
        "automobile",
        "painting"
    ],
    "wof:name":"Craftsman Collision Ltd",
    "wof:placetype":"venue"
},
  "geometry": {"coordinates":[-123.117355,49.208725],"type":"Point"}
}