{
  "type": "Feature",
  "properties": {
    "addr:full":"368 Lacewood Dr Halifax NS B3S 1L8",
    "addr:housenumber":"368",
    "addr:postcode":"b3s 1l8",
    "addr:street":"Lacewood Dr",
    "iso:country":"CA",
    "sg:address":"368 Lacewood Dr",
    "sg:city":"Halifax",
    "sg:classifiers":[
        {
            "category":"Building & Trades",
            "subcategory":"Construction",
            "type":"Services"
        }
    ],
    "sg:phone":"+1 902 457 3481",
    "sg:postcode":"B3S 1L8",
    "sg:province":"NS",
    "sg:tags":[
        "home",
        "material",
        "floor",
        "improvement"
    ],
    "wof:name":"Home Depot",
    "wof:placetype":"venue"
},
  "geometry": {"coordinates":[-63.669975,44.658642],"type":"Point"}
}