{
  "type": "Feature",
  "properties": {
    "addr:full":"432 College St Toronto ON M5T 1T3",
    "addr:housenumber":"432",
    "addr:postcode":"m5t 1t3",
    "addr:street":"College St",
    "iso:country":"CA",
    "sg:address":"432 College St",
    "sg:city":"Toronto",
    "sg:classifiers":[
        {
            "category":"Restaurant",
            "type":"Food & Drink"
        }
    ],
    "sg:phone":"+1 416 921 6332",
    "sg:postcode":"M5T 1T3",
    "sg:province":"ON",
    "wof:name":"Mars Restaurant",
    "wof:placetype":"venue"
},
  "geometry": {"coordinates":[-79.407211,43.656689],"type":"Point"}
}