{
  "type": "Feature",
  "properties": {
    "iso:country":"CA",
    "sg:address":"6880 Line 86",
    "sg:city":"Elmira",
    "sg:classifiers":[
        {
            "category":"Wholesale",
            "subcategory":"Poultry",
            "type":"Manufacturing & Wholesale Goods"
        }
    ],
    "sg:phone":"+1 519 669 2225",
    "sg:postcode":"N3B 2Z3",
    "sg:province":"ON",
    "wof:name":"Pullets Plus Ltd",
    "wof:placetype":"venue"
},
  "geometry": {"coordinates":[-80.55871582029999,43.598651886],"type":"Point"}
}