{
  "type": "Feature",
  "properties": {
    "addr:full":"1234 Dupont St Toronto ON M6H 2A4",
    "addr:housenumber":"1234",
    "addr:postcode":"m6h 2a4",
    "addr:street":"Dupont St",
    "iso:country":"CA",
    "sg:address":"1234 Dupont St",
    "sg:city":"Toronto",
    "sg:classifiers":[
        {
            "category":"Retail",
            "subcategory":"Auto Repair",
            "type":"Services"
        }
    ],
    "sg:phone":"+1 416 537 1234",
    "sg:postcode":"M6H 2A4",
    "sg:province":"ON",
    "sg:tags":[
        "repairing",
        "automobile",
        "parts",
        "supply"
    ],
    "wof:name":"Public Auto Parts Plus",
    "wof:placetype":"venue"
},
  "geometry": {"coordinates":[-79.44194,43.668289],"type":"Point"}
}