{
  "type": "Feature",
  "properties": {
    "addr:full":"Kelowna BC V1Z 3P3",
    "addr:postcode":"v1z 3p3",
    "iso:country":"CA",
    "sg:city":"Kelowna",
    "sg:classifiers":[
        {
            "category":"Freight",
            "type":"Transportation"
        }
    ],
    "sg:phone":"+1 250 769 7974",
    "sg:postcode":"V1Z 3P3",
    "sg:province":"BC",
    "sg:tags":[
        "mover"
    ],
    "wof:name":"Amj Campbell Van Lines",
    "wof:placetype":"venue"
},
  "geometry": {"coordinates":[-119.58972168,49.861328125],"type":"Point"}
}