{
  "type": "Feature",
  "properties": {
    "addr:full":"299 Ranee Ave North York ON M6A 1N9",
    "addr:housenumber":"299",
    "addr:postcode":"m6a 1n9",
    "addr:street":"Ranee Ave",
    "iso:country":"CA",
    "sg:address":"299 Ranee Ave",
    "sg:city":"North York",
    "sg:classifiers":[
        {
            "category":"Building & Trades",
            "subcategory":"Construction",
            "type":"Services"
        }
    ],
    "sg:phone":"+1 416 784 5556",
    "sg:postcode":"M6A 1N9",
    "sg:province":"ON",
    "sg:tags":[
        "concrete",
        "contractor"
    ],
    "wof:name":"Primo Concrete Cutting Ltd",
    "wof:placetype":"venue"
},
  "geometry": {"coordinates":[-79.45151519780001,43.7225036621],"type":"Point"}
}