{
  "type": "Feature",
  "properties": {
    "addr:full":"546 Plains Rd E Burlington ON L7T 2E3",
    "addr:housenumber":"546",
    "addr:postcode":"l7t 2e3",
    "addr:street":"Plains Rd E",
    "iso:country":"CA",
    "sg:address":"546 Plains Rd E",
    "sg:city":"Burlington",
    "sg:classifiers":[
        {
            "category":"Autos & Motor Vehicles",
            "subcategory":"Automobile Sales",
            "type":"Retail Goods"
        }
    ],
    "sg:phone":"+1 905 333 1220",
    "sg:postcode":"L7T 2E3",
    "sg:province":"ON",
    "sg:tags":[
        "car",
        "dealer"
    ],
    "wof:name":"Alternative Auto Inc",
    "wof:placetype":"venue"
},
  "geometry": {"coordinates":[-79.8345565796,43.3202819824],"type":"Point"}
}