{
  "type": "Feature",
  "properties": {
    "addr:full":"5240 11E Av Shawinigan QC G9N 8K3",
    "addr:housenumber":"5240",
    "addr:postcode":"g9n 8k3",
    "addr:street":"11E Av",
    "iso:country":"CA",
    "sg:address":"5240 11E Av",
    "sg:city":"Shawinigan",
    "sg:classifiers":[
        {
            "category":"Manufacturing",
            "subcategory":"Tools & Machinery",
            "type":"Manufacturing & Wholesale Goods"
        }
    ],
    "sg:phone":"+1 819 539 4377",
    "sg:postcode":"G9N 8K3",
    "sg:province":"QC",
    "sg:tags":[
        "machine",
        "shop"
    ],
    "wof:name":"Ateliers Jpc Enr",
    "wof:placetype":"venue"
},
  "geometry": {"coordinates":[-72.7245101929,46.5675506592],"type":"Point"}
}