{
  "type": "Feature",
  "properties": {
    "iso:country":"CA",
    "sg:address":"1440 Rue Mackay",
    "sg:city":"Montreal",
    "sg:classifiers":[
        {
            "category":"Professional",
            "subcategory":"Printing & Photocopies",
            "type":"Services"
        }
    ],
    "sg:phone":"+1 514 937 7720",
    "sg:postcode":"H3G 2H7",
    "sg:province":"QC",
    "sg:tags":[
        "duplicating",
        "copying"
    ],
    "wof:name":"Jolie Copie",
    "wof:placetype":"venue"
},
  "geometry": {"coordinates":[-73.5779342651,45.4961776733],"type":"Point"}
}