{
  "type": "Feature",
  "properties": {
    "addr:full":"Ridgetown ON N0P 2C0",
    "addr:postcode":"n0p 2c0",
    "iso:country":"CA",
    "sg:city":"Ridgetown",
    "sg:classifiers":[
        {
            "category":"Building & Trades",
            "subcategory":"Construction",
            "type":"Services"
        }
    ],
    "sg:phone":"+1 519 674 0705",
    "sg:postcode":"N0P 2C0",
    "sg:province":"ON",
    "sg:tags":[
        "general",
        "contractor"
    ],
    "wof:name":"Comstock Stechleyhall Location",
    "wof:placetype":"venue"
},
  "geometry": {"coordinates":[-81.8793258667,42.4446716309],"type":"Point"}
}