{
  "type": "Feature",
  "properties": {
    "iso:country":"CA",
    "sg:address":"2229 Rue Guenette",
    "sg:city":"Saint-Laurent",
    "sg:classifiers":[
        {
            "category":"Building & Trades",
            "subcategory":"Electrical",
            "type":"Services"
        }
    ],
    "sg:phone":"+1 514 337 8502",
    "sg:postcode":"H4R 2E9",
    "sg:province":"QC",
    "sg:tags":[
        "equipment",
        "telecommunication",
        "radio",
        "system",
        "communication"
    ],
    "wof:name":"Microprecision",
    "wof:placetype":"venue"
},
  "geometry": {"coordinates":[-73.72528839109999,45.4983100891],"type":"Point"}
}