{
  "type": "Feature",
  "properties": {
    "addr:full":"508 Riverside Dr London ON N6H 2R7",
    "addr:housenumber":"508",
    "addr:postcode":"n6h 2r7",
    "addr:street":"Riverside Dr",
    "iso:country":"CA",
    "sg:address":"508 Riverside Dr",
    "sg:city":"London",
    "sg:classifiers":[
        {
            "category":"Recreation",
            "type":"Entertainment"
        }
    ],
    "sg:phone":"+1 519 657 7979",
    "sg:postcode":"N6H 2R7",
    "sg:province":"ON",
    "sg:tags":[
        "hall",
        "auditorium"
    ],
    "wof:name":"Civitan Club London Middlesex",
    "wof:placetype":"venue"
},
  "geometry": {"coordinates":[-81.28922271730001,42.976360321],"type":"Point"}
}