{
  "type": "Feature",
  "properties": {
    "addr:full":"14807 134 Ave NW Edmonton AB T5L 4V5",
    "addr:housenumber":"14807",
    "addr:postcode":"t5l 4v5",
    "addr:street":"134 Ave Nw",
    "iso:country":"CA",
    "sg:address":"14807 134 Ave NW",
    "sg:city":"Edmonton",
    "sg:classifiers":[
        {
            "category":"Shopping",
            "subcategory":"Computers & Home Electronics",
            "type":"Retail Goods"
        }
    ],
    "sg:phone":"+1 780 413 9474",
    "sg:postcode":"T5L 4V5",
    "sg:province":"AB",
    "sg:tags":[
        "parts",
        "supply"
    ],
    "wof:name":"Visual Data Systems Inc",
    "wof:placetype":"venue"
},
  "geometry": {"coordinates":[-113.576293945,53.5934486389],"type":"Point"}
}