{
  "type": "Feature",
  "properties": {
    "addr:full":"130 York Blvd Hamilton ON L8R 1Y5",
    "addr:housenumber":"130",
    "addr:postcode":"l8r 1y5",
    "addr:street":"York Blvd",
    "iso:country":"CA",
    "sg:address":"130 York Blvd",
    "sg:city":"Hamilton",
    "sg:classifiers":[
        {
            "category":"Education",
            "subcategory":"School",
            "type":"Public Place"
        }
    ],
    "sg:phone":"+1 905 528 8363",
    "sg:postcode":"L8R 1Y5",
    "sg:province":"ON",
    "wof:name":"Sir John A Mac Donald School",
    "wof:placetype":"venue"
},
  "geometry": {"coordinates":[-79.8733215332,43.2604446411],"type":"Point"}
}