{
  "type": "Feature",
  "properties": {
    "addr:full":"1437 Boul Ducharme LA Tuque QC G9X 4R7",
    "addr:housenumber":"1437",
    "addr:postcode":"g9x 4r7",
    "addr:street":"Boul Ducharme",
    "iso:country":"CA",
    "sg:address":"1437 Boul Ducharme",
    "sg:city":"LA Tuque",
    "sg:classifiers":[
        {
            "category":"Building & Trades",
            "subcategory":"Electrical",
            "type":"Services"
        }
    ],
    "sg:phone":"+1 819 523 7927",
    "sg:postcode":"G9X 4R7",
    "sg:province":"QC",
    "sg:tags":[
        "electric",
        "contractor"
    ],
    "wof:name":"H & R Electrique Luminaires",
    "wof:placetype":"venue"
},
  "geometry": {"coordinates":[-72.785484,47.410873],"type":"Point"}
}