{
  "type": "Feature",
  "properties": {
    "addr:full":"80 Queen St Charlottetown PE C1A 4A7",
    "addr:housenumber":"80",
    "addr:postcode":"c1a 4a7",
    "addr:street":"Queen St",
    "iso:country":"CA",
    "sg:address":"80 Queen St",
    "sg:city":"Charlottetown",
    "sg:classifiers":[
        {
            "category":"Food & Beverages",
            "subcategory":"Liquor & Beverages",
            "type":"Retail Goods"
        }
    ],
    "sg:phone":"+1 902 368 5099",
    "sg:postcode":"C1A 4A7",
    "sg:province":"PE",
    "sg:tags":[
        "store"
    ],
    "wof:name":"Queen St Liquor Store",
    "wof:placetype":"venue"
},
  "geometry": {"coordinates":[-63.12606,46.233086],"type":"Point"}
}