{
  "type": "Feature",
  "properties": {
    "addr:full":"6815 1st Ave N Regina SK S4X 1C7",
    "addr:housenumber":"6815",
    "addr:postcode":"s4x 1c7",
    "addr:street":"1St Ave N",
    "iso:country":"CA",
    "sg:address":"6815 1st Ave N",
    "sg:city":"Regina",
    "sg:classifiers":[
        {
            "category":"Building & Trades",
            "subcategory":"Construction",
            "type":"Services"
        }
    ],
    "sg:phone":"+1 306 545 5166",
    "sg:postcode":"S4X 1C7",
    "sg:province":"SK",
    "sg:tags":[
        "general",
        "contractor"
    ],
    "wof:name":"Fenk Construction Ltd",
    "wof:placetype":"venue"
},
  "geometry": {"coordinates":[-104.678848,50.47493],"type":"Point"}
}