{
  "type": "Feature",
  "properties": {
    "addr:full":"1566 Northmount Dr NW Calgary AB T2L 0G6",
    "addr:housenumber":"1566",
    "addr:postcode":"t2l 0g6",
    "addr:street":"Northmount Dr Nw",
    "iso:country":"CA",
    "sg:address":"1566 Northmount Dr NW",
    "sg:city":"Calgary",
    "sg:classifiers":[
        {
            "category":"Organizations",
            "subcategory":"Religious Organization",
            "type":"Services"
        }
    ],
    "sg:phone":"+1 403 282 9488",
    "sg:postcode":"T2L 0G6",
    "sg:province":"AB",
    "sg:tags":[
        "church"
    ],
    "wof:name":"St Lukes Catholic Church",
    "wof:placetype":"venue"
},
  "geometry": {"coordinates":[-114.14035,51.096169],"type":"Point"}
}