{
  "type": "Feature",
  "properties": {
    "addr:full":"51299 Yale Rd E Rosedale BC V0X 1X0",
    "addr:housenumber":"51299",
    "addr:postcode":"v0x 1x0",
    "addr:street":"Yale Rd E",
    "iso:country":"CA",
    "sg:address":"51299 Yale Rd E",
    "sg:city":"Rosedale",
    "sg:classifiers":[
        {
            "category":"Restaurant",
            "type":"Food & Drink"
        }
    ],
    "sg:phone":"+1 604 794 7977",
    "sg:postcode":"V0X 1X0",
    "sg:province":"BC",
    "wof:name":"Lee's Restaurant",
    "wof:placetype":"venue"
},
  "geometry": {"coordinates":[-121.80523700000001,49.1824],"type":"Point"}
}