{
  "type": "Feature",
  "properties": {
    "addr:full":"3557 Boul Dagenais O Laval QC H7P 1V8",
    "addr:housenumber":"3557",
    "addr:postcode":"h7p 1v8",
    "addr:street":"Boul Dagenais O",
    "iso:country":"CA",
    "sg:address":"3557 Boul Dagenais O",
    "sg:city":"Laval",
    "sg:classifiers":[
        {
            "category":"Food & Beverages",
            "subcategory":"Groceries & Convenience Stores",
            "type":"Retail Goods"
        }
    ],
    "sg:phone":"+1 450 628 2420",
    "sg:postcode":"H7P 1V8",
    "sg:province":"QC",
    "sg:tags":[
        "grocer"
    ],
    "wof:name":"Iga Extra Rene Laliberte",
    "wof:placetype":"venue"
},
  "geometry": {"coordinates":[-73.81266021730001,45.5761299133],"type":"Point"}
}