{
  "type": "Feature",
  "properties": {
    "addr:full":"545 Silvercreek Pky N Guelph ON N1K 1S7",
    "addr:housenumber":"545",
    "addr:postcode":"n1k 1s7",
    "addr:street":"Silvercreek Pky N",
    "iso:country":"CA",
    "sg:address":"545 Silvercreek Pky N",
    "sg:city":"Guelph",
    "sg:classifiers":[
        {
            "category":"Home & Garden",
            "subcategory":"Hardware",
            "type":"Retail Goods"
        }
    ],
    "sg:phone":"+1 519 766 1566",
    "sg:postcode":"N1K 1S7",
    "sg:province":"ON",
    "wof:name":"Tsc Stores Ltd",
    "wof:placetype":"venue"
},
  "geometry": {"coordinates":[-80.297234,43.552303],"type":"Point"}
}