{
  "type": "Feature",
  "properties": {
    "addr:full":"12047 Harris Rd Pitt Meadows BC V3Y 2B5",
    "addr:housenumber":"12047",
    "addr:postcode":"v3y 2b5",
    "addr:street":"Harris Rd",
    "iso:country":"CA",
    "sg:address":"12047 Harris Rd",
    "sg:city":"Pitt Meadows",
    "sg:classifiers":[
        {
            "category":"Education",
            "subcategory":"Library",
            "type":"Public Place"
        }
    ],
    "sg:phone":"+1 604 465 4113",
    "sg:postcode":"V3Y 2B5",
    "sg:province":"BC",
    "wof:name":"Pitt Meadows Library",
    "wof:placetype":"venue"
},
  "geometry": {"coordinates":[-122.68982696499999,49.2213630676],"type":"Point"}
}