{
  "type": "Feature",
  "properties": {
    "addr:full":"5431 Doyle St Halifax NS B3J 1H9",
    "addr:housenumber":"5431",
    "addr:postcode":"ns b3j 1h9",
    "addr:street":"Doyle St",
    "iso:country":"CA",
    "sg:address":"5431 Doyle St",
    "sg:city":"Halifax",
    "sg:classifiers":[
        {
            "category":"Food & Beverages",
            "subcategory":"Liquor & Beverages",
            "type":"Retail Goods"
        }
    ],
    "sg:phone":"+1 902 422 0580",
    "sg:postcode":"B3J 1H9",
    "sg:province":"NS",
    "sg:tags":[
        "store"
    ],
    "wof:name":"Nova Scotia Liquor Store",
    "wof:placetype":"venue"
},
  "geometry": {"coordinates":[-63.575611,44.644028],"type":"Point"}
}