{
  "type": "Feature",
  "properties": {
    "addr:full":"22 Foster St Perth ON K7H 1R6",
    "addr:housenumber":"22",
    "addr:postcode":"k7h 1r6",
    "addr:street":"Foster St",
    "iso:country":"CA",
    "sg:address":"22 Foster St",
    "sg:city":"Perth",
    "sg:classifiers":[
        {
            "category":"Insurance",
            "subcategory":"Insurance Agent",
            "type":"Services"
        }
    ],
    "sg:phone":"+1 613 267 1345",
    "sg:postcode":"K7H 1R6",
    "sg:province":"ON",
    "sg:tags":[
        "profit",
        "sharing",
        "pension",
        "plan"
    ],
    "wof:name":"Maritime Life Assurance CO",
    "wof:placetype":"venue"
},
  "geometry": {"coordinates":[-76.2486343384,44.9025688171],"type":"Point"}
}