{
  "type": "Feature",
  "properties": {
    "addr:full":"150 Joseph Zatzman Dr Dartmouth NS B3B 1P1",
    "addr:housenumber":"150",
    "addr:postcode":"b3b 1p1",
    "addr:street":"Joseph Zatzman Dr",
    "iso:country":"CA",
    "sg:address":"150 Joseph Zatzman Dr",
    "sg:city":"Dartmouth",
    "sg:classifiers":[
        {
            "category":"Manufacturing",
            "subcategory":"Metals",
            "type":"Manufacturing & Wholesale Goods"
        }
    ],
    "sg:phone":"+1 902 468 2526",
    "sg:postcode":"B3B 1P1",
    "sg:province":"NS",
    "sg:tags":[
        "steel"
    ],
    "wof:name":"Harris Rebar",
    "wof:placetype":"venue"
},
  "geometry": {"coordinates":[-63.5979576111,44.7099075317],"type":"Point"}
}