{
  "type": "Feature",
  "properties": {
    "iso:country":"CA",
    "sg:address":"6 Alice St",
    "sg:city":"Flesherton",
    "sg:classifiers":[
        {
            "category":"Health Services",
            "subcategory":"Doctor",
            "type":"Services"
        }
    ],
    "sg:phone":"+1 519 924 2012",
    "sg:postcode":"N0C 1E0",
    "sg:province":"ON",
    "sg:tags":[
        "physician",
        "surgeon"
    ],
    "wof:name":"Power, Brian MD",
    "wof:placetype":"venue"
},
  "geometry": {"coordinates":[-80.5518417358,44.2598266602],"type":"Point"}
}