{
  "type": "Feature",
  "properties": {
    "addr:full":"52 Rue Sous-Le-Fort Quebec QC G1K 4G8",
    "addr:housenumber":"52",
    "addr:postcode":"g1k 4g8",
    "addr:street":"Rue Sous-Le-Fort",
    "iso:country":"CA",
    "sg:address":"52 Rue Sous-Le-Fort",
    "sg:city":"Quebec",
    "sg:classifiers":[
        {
            "category":"Shopping",
            "subcategory":"Gifts & Souvenirs",
            "type":"Retail Goods"
        }
    ],
    "sg:phone":"+1 418 692 2861",
    "sg:postcode":"G1K 4G8",
    "sg:province":"QC",
    "sg:tags":[
        "shop"
    ],
    "wof:name":"Boutique Feejos",
    "wof:placetype":"venue"
},
  "geometry": {"coordinates":[-71.2030792236,46.8127098083],"type":"Point"}
}