{
  "type": "Feature",
  "properties": {
    "addr:full":"4190 10 Ave SE Salmon Arm BC V1E 1W7",
    "addr:housenumber":"4190",
    "addr:postcode":"v1e 1w7",
    "addr:street":"10 Ave Se",
    "iso:country":"CA",
    "sg:address":"4190 10 Ave SE",
    "sg:city":"Salmon Arm",
    "sg:classifiers":[
        {
            "category":"Building & Trades",
            "subcategory":"Electrical",
            "type":"Services"
        }
    ],
    "sg:phone":"+1 250 832 0205",
    "sg:postcode":"V1E 1W7",
    "sg:province":"BC",
    "sg:tags":[
        "electric",
        "contractor"
    ],
    "wof:name":"Shuswap Electrical & Alarms",
    "wof:placetype":"venue"
},
  "geometry": {"coordinates":[-119.235107422,50.6924552917],"type":"Point"}
}