{
  "type": "Feature",
  "properties": {
    "iso:country":"CA",
    "sg:address":"3380 Rue Jean-Talon E",
    "sg:city":"Montreal",
    "sg:classifiers":[
        {
            "category":"Bars & Pubs",
            "type":"Food & Drink"
        }
    ],
    "sg:phone":"+1 514 722 3771",
    "sg:postcode":"H2A 1W8",
    "sg:province":"QC",
    "wof:name":"Taverne Apollo",
    "wof:placetype":"venue"
},
  "geometry": {"coordinates":[-73.59674072270001,45.5603675842],"type":"Point"}
}