{
  "type": "Feature",
  "properties": {
    "addr:full":"746 Boul Cure-Labelle Laval QC H7V 2T9",
    "addr:housenumber":"746",
    "addr:postcode":"h7v 2t9",
    "addr:street":"Boul Cure-Labelle",
    "iso:country":"CA",
    "sg:address":"746 Boul Cure-Labelle",
    "sg:city":"Laval",
    "sg:classifiers":[
        {
            "category":"Retail",
            "subcategory":"Car Wash",
            "type":"Services"
        }
    ],
    "sg:phone":"+1 450 682 1982",
    "sg:postcode":"H7V 2T9",
    "sg:province":"QC",
    "sg:tags":[
        "polishing",
        "washing"
    ],
    "wof:name":"Jobin Lave-Auto Enr",
    "wof:placetype":"venue"
},
  "geometry": {"coordinates":[-73.74614699999999,45.538593],"type":"Point"}
}