{
  "type": "Feature",
  "properties": {
    "addr:full":"47 Main St E Smiths Falls ON K7A 1A5",
    "addr:housenumber":"47",
    "addr:postcode":"k7a 1a5",
    "addr:street":"Main St E",
    "iso:country":"CA",
    "sg:address":"47 Main St E",
    "sg:city":"Smiths Falls",
    "sg:classifiers":[
        {
            "category":"Personal",
            "subcategory":"Beauty Salon",
            "type":"Services"
        }
    ],
    "sg:phone":"+1 613 283 3945",
    "sg:postcode":"K7A 1A5",
    "sg:province":"ON",
    "wof:name":"Geno's Hairstyling Salon",
    "wof:placetype":"venue"
},
  "geometry": {"coordinates":[-76.017639,44.899773],"type":"Point"}
}