{
  "type": "Feature",
  "properties": {
    "addr:full":"1275 Av Maguire Sillery QC G1T 1Z2",
    "addr:housenumber":"1275",
    "addr:postcode":"g1t 1z2",
    "addr:street":"Av Maguire",
    "iso:country":"CA",
    "sg:address":"1275 Av Maguire",
    "sg:city":"Sillery",
    "sg:classifiers":[
        {
            "category":"Wholesale",
            "subcategory":"Groceries",
            "type":"Manufacturing & Wholesale Goods"
        }
    ],
    "sg:phone":"+1 418 682 3878",
    "sg:postcode":"G1T 1Z2",
    "sg:province":"QC",
    "sg:tags":[
        "coffee",
        "brewing",
        "devices"
    ],
    "wof:name":"Importations MI-Ra",
    "wof:placetype":"venue"
},
  "geometry": {"coordinates":[-71.25257873539999,46.7816581726],"type":"Point"}
}