{
  "type": "Feature",
  "properties": {
    "addr:full":"67 Rue Desbiens Amqui QC G5J 3P5",
    "addr:housenumber":"67",
    "addr:postcode":"g5j 3p5",
    "addr:street":"Rue Desbiens",
    "iso:country":"CA",
    "sg:address":"67 Rue Desbiens",
    "sg:city":"Amqui",
    "sg:classifiers":[
        {
            "category":"Organizations",
            "subcategory":"Professional Association",
            "type":"Services"
        }
    ],
    "sg:phone":"+1 418 629 5197",
    "sg:postcode":"G5J 3P5",
    "sg:province":"QC",
    "wof:name":"Rayon DE Partage-Sante Mentale",
    "wof:placetype":"venue"
},
  "geometry": {"coordinates":[-67.42887899999999,48.465633],"type":"Point"}
}