{
  "type": "Feature",
  "properties": {
    "addr:full":"248 Jane St Toronto ON M6S 3Z1",
    "addr:housenumber":"248",
    "addr:postcode":"m6s 3z1",
    "addr:street":"Jane St",
    "iso:country":"CA",
    "sg:address":"248 Jane St",
    "sg:city":"Toronto",
    "sg:classifiers":[
        {
            "category":"Retail",
            "subcategory":"Repair Shop",
            "type":"Services"
        }
    ],
    "sg:phone":"+1 416 769 5821",
    "sg:postcode":"M6S 3Z1",
    "sg:province":"ON",
    "sg:tags":[
        "upholsterer"
    ],
    "wof:name":"Luso Upholstery",
    "wof:placetype":"venue"
},
  "geometry": {"coordinates":[-79.48703,43.655102],"type":"Point"}
}