{
  "type": "Feature",
  "properties": {
    "addr:full":"6982 Financial Dr Mississauga ON L5N 8J4",
    "addr:housenumber":"6982",
    "addr:postcode":"l5n 8j4",
    "addr:street":"Financial Dr",
    "iso:country":"CA",
    "sg:address":"6982 Financial Dr",
    "sg:city":"Mississauga",
    "sg:classifiers":[
        {
            "category":"Restaurant",
            "type":"Food & Drink"
        }
    ],
    "sg:phone":"+1 905 567 9173",
    "sg:postcode":"L5N 8J4",
    "sg:province":"ON",
    "wof:name":"Drake & Firkin",
    "wof:placetype":"venue"
},
  "geometry": {"coordinates":[-79.748916626,43.6110534668],"type":"Point"}
}