{
  "type": "Feature",
  "properties": {
    "iso:country":"CA",
    "sg:address":"5596 Morris St",
    "sg:city":"Halifax",
    "sg:classifiers":[
        {
            "category":"Social Services",
            "type":"Services"
        }
    ],
    "sg:phone":"+1 902 421 6131",
    "sg:postcode":"B3J 1C2",
    "sg:province":"NS",
    "sg:tags":[
        "senior",
        "citizen"
    ],
    "wof:name":"Spencer House Senior Ctr",
    "wof:placetype":"venue"
},
  "geometry": {"coordinates":[-63.5757598877,44.6405181885],"type":"Point"}
}