{
  "type": "Feature",
  "properties": {
    "addr:full":"Change Islands NL A0G 1R0",
    "addr:postcode":"a0g 1r0",
    "iso:country":"CA",
    "sg:city":"Change Islands",
    "sg:classifiers":[
        {
            "category":"Food & Beverages",
            "subcategory":"Groceries & Convenience Stores",
            "type":"Retail Goods"
        }
    ],
    "sg:phone":"+1 709 621 4561",
    "sg:postcode":"A0G 1R0",
    "sg:province":"NL",
    "sg:tags":[
        "grocer"
    ],
    "wof:name":"Dms Enterprises Ltd",
    "wof:placetype":"venue"
},
  "geometry": {"coordinates":[-54.407276,49.67144],"type":"Point"}
}