{
  "type": "Feature",
  "properties": {
    "iso:country":"CA",
    "sg:address":"302 Lakeshore Rd E",
    "sg:city":"Oakville",
    "sg:classifiers":[
        {
            "category":"Personal",
            "subcategory":"Beauty Salon",
            "type":"Services"
        }
    ],
    "sg:phone":"+1 905 845 7671",
    "sg:postcode":"L6J 1J2",
    "sg:province":"ON",
    "wof:name":"Haircraft",
    "wof:placetype":"venue"
},
  "geometry": {"coordinates":[-79.665863,43.447731],"type":"Point"}
}