{
  "type": "Feature",
  "properties": {
    "iso:country":"CA",
    "sg:address":"2275 Ch DE Saint-Jean",
    "sg:city":"LA Prairie",
    "sg:classifiers":[
        {
            "category":"Retail",
            "subcategory":"Auto Repair",
            "type":"Services"
        }
    ],
    "sg:phone":"+1 450 659 3045",
    "sg:postcode":"J5R 3X8",
    "sg:province":"QC",
    "sg:tags":[
        "truck"
    ],
    "wof:name":"Unite Mobile SD Inc",
    "wof:placetype":"venue"
},
  "geometry": {"coordinates":[-73.4615478516,45.4039573669],"type":"Point"}
}