{
  "type": "Feature",
  "properties": {
    "iso:country":"CA",
    "sg:address":"700 Hamilton St",
    "sg:city":"Vancouver",
    "sg:classifiers":[
        {
            "category":"Communications",
            "subcategory":"Radio Station",
            "type":"Services"
        }
    ],
    "sg:phone":"+1 604 662 6000",
    "sg:postcode":"V6B 2R5",
    "sg:province":"BC",
    "sg:tags":[
        "company",
        "broadcasting"
    ],
    "wof:name":"Canadian Broadcasting Corp",
    "wof:placetype":"venue"
},
  "geometry": {"coordinates":[-123.114196777,49.2797813416],"type":"Point"}
}