{
  "type": "Feature",
  "properties": {
    "addr:full":"541 St Mary's Rd Winnipeg MB R2M 3L4",
    "addr:housenumber":"541",
    "addr:postcode":"r2m 3l4",
    "addr:street":"St Mary'S Rd",
    "iso:country":"CA",
    "sg:address":"541 St Mary's Rd",
    "sg:city":"Winnipeg",
    "sg:classifiers":[
        {
            "category":"Health Services",
            "subcategory":"Doctor",
            "type":"Services"
        }
    ],
    "sg:phone":"+1 204 237 8896",
    "sg:postcode":"R2M 3L4",
    "sg:province":"MB",
    "sg:tags":[
        "medicine",
        "injury",
        "sport"
    ],
    "wof:name":"Sport-Tec Athletic Therapy Ctr",
    "wof:placetype":"venue"
},
  "geometry": {"coordinates":[-97.15267900000001,49.889317],"type":"Point"}
}