{
  "type": "Feature",
  "properties": {
    "addr:full":"10010 99 Ave LA Glace AB T0H 2J0",
    "addr:housenumber":"10010",
    "addr:postcode":"t0h 2j0",
    "addr:street":"99 Ave La",
    "iso:country":"CA",
    "sg:address":"10010 99 Ave",
    "sg:city":"LA Glace",
    "sg:classifiers":[
        {
            "category":"Building & Trades",
            "subcategory":"Construction",
            "type":"Services"
        }
    ],
    "sg:phone":"+1 780 568 2540",
    "sg:postcode":"T0H 2J0",
    "sg:province":"AB",
    "sg:tags":[
        "well",
        "drilling"
    ],
    "wof:name":"Petersen Aqua-Tech Drilling",
    "wof:placetype":"venue"
},
  "geometry": {"coordinates":[-119.153931,55.402802],"type":"Point"}
}