{
  "type": "Feature",
  "properties": {
    "addr:full":"34 Castille Cres Keswick ON L4P 3L4",
    "addr:housenumber":"34",
    "addr:postcode":"l4p 3l4",
    "addr:street":"Castille Cres",
    "iso:country":"CA",
    "sg:address":"34 Castille Cres",
    "sg:city":"Keswick",
    "sg:classifiers":[
        {
            "category":"Wholesale",
            "subcategory":"Electrical",
            "type":"Manufacturing & Wholesale Goods"
        }
    ],
    "sg:phone":"+1 905 476 8776",
    "sg:postcode":"L4P 3L4",
    "sg:province":"ON",
    "sg:tags":[
        "television",
        "radio"
    ],
    "wof:name":"Divide Research",
    "wof:placetype":"venue"
},
  "geometry": {"coordinates":[-79.45295,44.225677],"type":"Point"}
}