{
  "type": "Feature",
  "properties": {
    "addr:full":"39 Selkirk Ave Hughenden AB T0B 2E0",
    "addr:housenumber":"39",
    "addr:postcode":"t0b 2e0",
    "addr:street":"Selkirk Ave",
    "iso:country":"CA",
    "sg:address":"39 Selkirk Ave",
    "sg:city":"Hughenden",
    "sg:classifiers":[
        {
            "category":"Retail",
            "subcategory":"Repair Shop",
            "type":"Services"
        }
    ],
    "sg:phone":"+1 780 856 3970",
    "sg:postcode":"T0B 2E0",
    "sg:province":"AB",
    "sg:tags":[
        "welding"
    ],
    "wof:name":"Vern's Welding",
    "wof:placetype":"venue"
},
  "geometry": {"coordinates":[-110.965515,52.512833],"type":"Point"}
}