{
  "type": "Feature",
  "properties": {
    "addr:full":"1094 Queen St W Toronto ON M6J 1H9",
    "addr:housenumber":"1094",
    "addr:postcode":"m6j 1h9",
    "addr:street":"Queen St W",
    "iso:country":"CA",
    "sg:address":"1094 Queen St W",
    "sg:city":"Toronto",
    "sg:classifiers":[
        {
            "category":"Shopping",
            "subcategory":"Florist",
            "type":"Retail Goods"
        }
    ],
    "sg:phone":"+1 416 538 2497",
    "sg:postcode":"M6J 1H9",
    "sg:province":"ON",
    "wof:name":"Poppies",
    "wof:placetype":"venue"
},
  "geometry": {"coordinates":[-79.422653,43.64357],"type":"Point"}
}