{
  "type": "Feature",
  "properties": {
    "addr:full":"309 Cedar St Port Mcneill BC V0N 2R0",
    "addr:housenumber":"309",
    "addr:postcode":"v0n 2r0",
    "addr:street":"Cedar St",
    "iso:country":"CA",
    "sg:address":"309 Cedar St",
    "sg:city":"Port Mcneill",
    "sg:classifiers":[
        {
            "category":"Manufacturing",
            "subcategory":"Tools & Machinery",
            "type":"Manufacturing & Wholesale Goods"
        }
    ],
    "sg:phone":"+1 250 956 2200",
    "sg:postcode":"V0N 2R0",
    "sg:province":"BC",
    "sg:tags":[
        "machine",
        "shop"
    ],
    "wof:name":"Cln Machining & Fabricating",
    "wof:placetype":"venue"
},
  "geometry": {"coordinates":[-127.078781128,50.5890884399],"type":"Point"}
}