{
  "type": "Feature",
  "properties": {
    "addr:full":"5055 Eagle Bay Rd Eagle Bay BC V0E 1T0",
    "addr:housenumber":"5055",
    "addr:postcode":"v0e 1t0",
    "addr:street":"Eagle Bay Rd",
    "iso:country":"CA",
    "sg:address":"5055 Eagle Bay Rd",
    "sg:city":"Eagle Bay",
    "sg:classifiers":[
        {
            "category":"Organizations",
            "subcategory":"Religious Organization",
            "type":"Services"
        }
    ],
    "sg:phone":"+1 250 675 2122",
    "sg:postcode":"V0E 1T0",
    "sg:province":"BC",
    "sg:tags":[
        "church"
    ],
    "wof:name":"Eagle Bay Camp",
    "wof:placetype":"venue"
},
  "geometry": {"coordinates":[-119.12246704099999,50.9565391541],"type":"Point"}
}