{
  "type": "Feature",
  "properties": {
    "addr:full":"Barrie ON L4M 6E5",
    "addr:postcode":"l4m 6e5",
    "iso:country":"CA",
    "sg:city":"Barrie",
    "sg:classifiers":[
        {
            "category":"Shopping",
            "subcategory":"Computers & Home Electronics",
            "type":"Retail Goods"
        }
    ],
    "sg:phone":"+1 705 737 1195",
    "sg:postcode":"L4M 6E5",
    "sg:province":"ON",
    "sg:tags":[
        "television",
        "radio"
    ],
    "wof:name":"Sony Store",
    "wof:placetype":"venue"
},
  "geometry": {"coordinates":[-79.7065200806,44.4084625244],"type":"Point"}
}