{
  "type": "Feature",
  "properties": {
    "iso:country":"CA",
    "sg:address":"100 Rue DE Rotterdam",
    "sg:city":"Saint-Augustin-DE-Desmaures",
    "sg:classifiers":[
        {
            "category":"Wholesale",
            "subcategory":"Machinery & Supplies",
            "type":"Manufacturing & Wholesale Goods"
        }
    ],
    "sg:phone":"+1 418 878 3000",
    "sg:postcode":"G3A 1T2",
    "sg:province":"QC",
    "sg:tags":[
        "heavy",
        "equipment"
    ],
    "wof:name":"Hewitt Equipement Ltee",
    "wof:placetype":"venue"
},
  "geometry": {"coordinates":[-71.4421920776,46.7568969727],"type":"Point"}
}