{
  "type": "Feature",
  "properties": {
    "addr:full":"5235 Av Du Parc Montreal QC H2V 4G9",
    "addr:housenumber":"5235",
    "addr:postcode":"h2v 4g9",
    "addr:street":"Av Du Parc",
    "iso:country":"CA",
    "sg:address":"5235 Av Du Parc",
    "sg:city":"Montreal",
    "sg:classifiers":[
        {
            "category":"Shopping",
            "subcategory":"Florist",
            "type":"Retail Goods"
        }
    ],
    "sg:phone":"+1 514 274 8237",
    "sg:postcode":"H2V 4G9",
    "sg:province":"QC",
    "wof:name":"Au Fleuriste Y Florist Ltee",
    "wof:placetype":"venue"
},
  "geometry": {"coordinates":[-73.5985488892,45.5208206177],"type":"Point"}
}