{
  "type": "Feature",
  "properties": {
    "addr:full":"PO Box 350 Guy AB T0H 1Y0",
    "addr:housenumber":"po;350",
    "addr:postcode":"t0h 1y0",
    "addr:street":"Box",
    "iso:country":"CA",
    "sg:address":"PO Box 350",
    "sg:city":"Guy",
    "sg:classifiers":[
        {
            "category":"Manufacturing",
            "subcategory":"Lumber",
            "type":"Manufacturing & Wholesale Goods"
        }
    ],
    "sg:phone":"+1 780 837 8172",
    "sg:postcode":"T0H 1Y0",
    "sg:province":"AB",
    "sg:tags":[
        "company",
        "logging"
    ],
    "wof:name":"Mgn Logging & Excavating",
    "wof:placetype":"venue"
},
  "geometry": {"coordinates":[-117.13133999999999,55.563206],"type":"Point"}
}