{
  "type": "Feature",
  "properties": {
    "addr:full":"515 Boul Sir-Wilfrid-Laurier Beloeil QC J3G 4H8",
    "addr:housenumber":"515",
    "addr:postcode":"j3g 4h8",
    "addr:street":"Boul Sir-Wilfrid-Laurier",
    "iso:country":"CA",
    "sg:address":"515 Boul Sir-Wilfrid-Laurier",
    "sg:city":"Beloeil",
    "sg:classifiers":[
        {
            "category":"Government",
            "subcategory":"Office",
            "type":"Public Place"
        }
    ],
    "sg:phone":"+1 450 467 9400",
    "sg:postcode":"J3G 4H8",
    "sg:province":"QC",
    "wof:name":"Quebec Solidarite Sociale",
    "wof:placetype":"venue"
},
  "geometry": {"coordinates":[-73.207649,45.560719],"type":"Point"}
}