{
  "type": "Feature",
  "properties": {
    "addr:full":"Vancouver BC V5Z 1K7",
    "addr:postcode":"v5z 1k7",
    "iso:country":"CA",
    "sg:city":"Vancouver",
    "sg:classifiers":[
        {
            "category":"Professional",
            "subcategory":"Detective & Security Services",
            "type":"Services"
        }
    ],
    "sg:phone":"+1 604 738 1568",
    "sg:postcode":"V5Z 1K7",
    "sg:province":"BC",
    "sg:tags":[
        "pet",
        "training",
        "guard",
        "dog"
    ],
    "wof:name":"Hollywood North Canine Trainin",
    "wof:placetype":"venue"
},
  "geometry": {"coordinates":[-123.12478637700001,49.2632522583],"type":"Point"}
}