{
  "type": "Feature",
  "properties": {
    "iso:country":"CA",
    "sg:address":"1900 Rue Sherbrooke",
    "sg:city":"Magog",
    "sg:classifiers":[
        {
            "category":"Restaurant",
            "type":"Food & Drink"
        }
    ],
    "sg:phone":"+1 819 868 6704",
    "sg:postcode":"J1X 2T3",
    "sg:province":"QC",
    "wof:name":"Burger King",
    "wof:placetype":"venue"
},
  "geometry": {"coordinates":[-72.1271286011,45.2795066833],"type":"Point"}
}