{
  "type": "Feature",
  "properties": {
    "addr:full":"Peterborough ON K9H 7E7",
    "addr:postcode":"k9h 7e7",
    "iso:country":"CA",
    "sg:city":"Peterborough",
    "sg:classifiers":[
        {
            "category":"Shopping",
            "subcategory":"Clothing, Apparel, & Fashions",
            "type":"Retail Goods"
        }
    ],
    "sg:phone":"+1 705 743 9242",
    "sg:postcode":"K9H 7E7",
    "sg:province":"ON",
    "sg:tags":[
        "furnishing"
    ],
    "wof:name":"Gentry Apparel Inc",
    "wof:placetype":"venue"
},
  "geometry": {"coordinates":[-78.31976299999999,44.304508],"type":"Point"}
}