{
  "type": "Feature",
  "properties": {
    "addr:full":"Edmonton AB T5K 0J7",
    "addr:postcode":"t5k 0j7",
    "iso:country":"CA",
    "sg:city":"Edmonton",
    "sg:classifiers":[
        {
            "category":"Personal",
            "subcategory":"Beauty Salon",
            "type":"Services"
        }
    ],
    "sg:phone":"+1 780 482 6163",
    "sg:postcode":"T5K 0J7",
    "sg:province":"AB",
    "wof:name":"Mary's Place",
    "wof:placetype":"venue"
},
  "geometry": {"coordinates":[-113.51995100000001,53.538979],"type":"Point"}
}