{
  "type": "Feature",
  "properties": {
    "iso:country":"CA",
    "sg:city":"Concord",
    "sg:classifiers":[
        {
            "category":"Retail",
            "subcategory":"Auto Repair",
            "type":"Services"
        }
    ],
    "sg:phone":"+1 905 660 6082",
    "sg:postcode":"L4K 1S4",
    "sg:province":"ON",
    "sg:tags":[
        "repairing",
        "automobile"
    ],
    "wof:name":"A's & C's Auto Repair",
    "wof:placetype":"venue"
},
  "geometry": {"coordinates":[-79.51284,43.792843],"type":"Point"}
}