{
  "type": "Feature",
  "properties": {
    "addr:full":"629 Buck Rd Kelowna BC V1W 1N6",
    "addr:housenumber":"629",
    "addr:postcode":"v1w 1n6",
    "addr:street":"Buck Rd",
    "iso:country":"CA",
    "sg:address":"629 Buck Rd",
    "sg:city":"Kelowna",
    "sg:classifiers":[
        {
            "category":"Retail",
            "subcategory":"Repair Shop",
            "type":"Services"
        }
    ],
    "sg:phone":"+1 250 869 9529",
    "sg:postcode":"V1W 1N6",
    "sg:province":"BC",
    "sg:tags":[
        "ironwork"
    ],
    "wof:name":"Anderson Ironworks",
    "wof:placetype":"venue"
},
  "geometry": {"coordinates":[-119.48611450200001,49.8144836426],"type":"Point"}
}