{
  "type": "Feature",
  "properties": {
    "addr:full":"669 Ch Du Grand-Bernier N Saint-Jean-Sur-Richelieu QC J3B 8K1",
    "addr:housenumber":"669",
    "addr:postcode":"j3b 8k1",
    "addr:street":"Ch Du Grand-Bernier N",
    "iso:country":"CA",
    "sg:address":"669 Ch Du Grand-Bernier N",
    "sg:city":"Saint-Jean-Sur-Richelieu",
    "sg:classifiers":[
        {
            "category":"Freight",
            "type":"Transportation"
        }
    ],
    "sg:phone":"+1 450 358 1684",
    "sg:postcode":"J3B 8K1",
    "sg:province":"QC",
    "sg:tags":[
        "delivery"
    ],
    "wof:name":"Monsieur Livre Tout",
    "wof:placetype":"venue"
},
  "geometry": {"coordinates":[-73.295799,45.321697],"type":"Point"}
}