{
  "type": "Feature",
  "properties": {
    "addr:full":"8419 24 St NW Edmonton AB T6P 1L3",
    "addr:housenumber":"8419",
    "addr:postcode":"t6p 1l3",
    "addr:street":"24 St Nw",
    "iso:country":"CA",
    "sg:address":"8419 24 St NW",
    "sg:city":"Edmonton",
    "sg:classifiers":[
        {
            "category":"Manufacturing",
            "subcategory":"Metals",
            "type":"Manufacturing & Wholesale Goods"
        }
    ],
    "sg:phone":"+1 780 449 4450",
    "sg:postcode":"T6P 1L3",
    "sg:province":"AB",
    "sg:tags":[
        "treating",
        "heat"
    ],
    "wof:name":"Goodwin Heat Treating Ltd",
    "wof:placetype":"venue"
},
  "geometry": {"coordinates":[-113.37953899999999,53.5965],"type":"Point"}
}