{
  "type": "Feature",
  "properties": {
    "addr:full":"61 Radford Ave Cambridge ON N1R 5L8",
    "addr:housenumber":"61",
    "addr:postcode":"n1r 5l8",
    "addr:street":"Radford Ave",
    "iso:country":"CA",
    "sg:address":"61 Radford Ave",
    "sg:city":"Cambridge",
    "sg:classifiers":[
        {
            "category":"Autos & Motor Vehicles",
            "subcategory":"Auto Supplies",
            "type":"Retail Goods"
        }
    ],
    "sg:phone":"+1 519 623 8040",
    "sg:postcode":"N1R 5L8",
    "sg:province":"ON",
    "sg:tags":[
        "automobile",
        "parts"
    ],
    "wof:name":"Eastec Marketing",
    "wof:placetype":"venue"
},
  "geometry": {"coordinates":[-80.296959,43.366905],"type":"Point"}
}