{
  "type": "Feature",
  "properties": {
    "iso:country":"CA",
    "sg:address":"1265 Carling Ave",
    "sg:city":"Ottawa",
    "sg:classifiers":[
        {
            "category":"Restaurant",
            "type":"Food & Drink"
        }
    ],
    "sg:phone":"+1 613 725 2992",
    "sg:postcode":"K1Z 8S9",
    "sg:province":"ON",
    "wof:name":"Monkey Joe's Bar & Grill",
    "wof:placetype":"venue"
},
  "geometry": {"coordinates":[-75.733421,45.386623],"type":"Point"}
}