{
  "type": "Feature",
  "properties": {
    "addr:full":"4917 Epsom Crt Niagara Falls ON L2H 1V8",
    "addr:housenumber":"4917",
    "addr:postcode":"l2h 1v8",
    "addr:street":"Epsom Crt",
    "iso:country":"CA",
    "sg:address":"4917 Epsom Crt",
    "sg:city":"Niagara Falls",
    "sg:classifiers":[
        {
            "category":"Building & Trades",
            "subcategory":"Construction",
            "type":"Services"
        }
    ],
    "sg:phone":"+1 905 356 4155",
    "sg:postcode":"L2H 1V8",
    "sg:province":"ON",
    "sg:tags":[
        "home",
        "improvement"
    ],
    "wof:name":"Finishing Touch Home Improvmt",
    "wof:placetype":"venue"
},
  "geometry": {"coordinates":[-79.1338195801,43.1016654968],"type":"Point"}
}