{
  "type": "Feature",
  "properties": {
    "addr:full":"Calgary AB T2G 5B6",
    "addr:postcode":"t2g 5b6",
    "iso:country":"CA",
    "sg:city":"Calgary",
    "sg:classifiers":[
        {
            "category":"Organizations",
            "subcategory":"Community Association",
            "type":"Services"
        }
    ],
    "sg:phone":"+1 403 264 3483",
    "sg:postcode":"T2G 5B6",
    "sg:province":"AB",
    "sg:tags":[
        "club"
    ],
    "wof:name":"Dive Calgary",
    "wof:placetype":"venue"
},
  "geometry": {"coordinates":[-114.060379,51.034328],"type":"Point"}
}