{
  "type": "Feature",
  "properties": {
    "iso:country":"CA",
    "sg:address":"9590 Boul Gouin O",
    "sg:city":"Pierrefonds",
    "sg:classifiers":[
        {
            "category":"Restaurant",
            "type":"Food & Drink"
        }
    ],
    "sg:phone":"+1 514 648 4428",
    "sg:postcode":"H8Y 1R3",
    "sg:province":"QC",
    "wof:name":"Restaurant Vincent Inc",
    "wof:placetype":"venue"
},
  "geometry": {"coordinates":[-73.7811965942,45.5038490295],"type":"Point"}
}