{
  "type": "Feature",
  "properties": {
    "addr:full":"432 King Ave Bathurst NB E2A 1P5",
    "addr:housenumber":"432",
    "addr:postcode":"e2a 1p5",
    "addr:street":"King Ave",
    "iso:country":"CA",
    "sg:address":"432 King Ave",
    "sg:city":"Bathurst",
    "sg:classifiers":[
        {
            "category":"Organizations",
            "subcategory":"Religious Organization",
            "type":"Services"
        }
    ],
    "sg:phone":"+1 506 546 3225",
    "sg:postcode":"E2A 1P5",
    "sg:province":"NB",
    "sg:tags":[
        "church"
    ],
    "wof:name":"St George's Anglican Church",
    "wof:placetype":"venue"
},
  "geometry": {"coordinates":[-65.65271,47.617599],"type":"Point"}
}