{
  "type": "Feature",
  "properties": {
    "addr:full":"North York ON M3A 1B2",
    "addr:postcode":"m3a 1b2",
    "iso:country":"CA",
    "sg:city":"North York",
    "sg:classifiers":[
        {
            "category":"Organizations",
            "subcategory":"Professional Association",
            "type":"Services"
        }
    ],
    "sg:phone":"+1 416 446 5980",
    "sg:postcode":"M3A 1B2",
    "sg:province":"ON",
    "wof:name":"North York Cosmos Soccer Club",
    "wof:placetype":"venue"
},
  "geometry": {"coordinates":[-79.319984436,43.7396621704],"type":"Point"}
}