{
  "type": "Feature",
  "properties": {
    "iso:country":"CA",
    "sg:address":"3960 Rue Saint-Denis",
    "sg:city":"Montreal",
    "sg:classifiers":[
        {
            "category":"Home & Garden",
            "subcategory":"Home Furnishings",
            "type":"Retail Goods"
        }
    ],
    "sg:phone":"+1 514 843 7513",
    "sg:postcode":"H2W 2M2",
    "sg:province":"QC",
    "sg:tags":[
        "glassware",
        "chinaware"
    ],
    "wof:name":"Arthur Quentin",
    "wof:placetype":"venue"
},
  "geometry": {"coordinates":[-73.574707,45.520088],"type":"Point"}
}