{
  "type": "Feature",
  "properties": {
    "iso:country":"CA",
    "sg:address":"4351 Ontario Ave",
    "sg:city":"Powell River",
    "sg:classifiers":[
        {
            "category":"Education",
            "subcategory":"School",
            "type":"Public Place"
        }
    ],
    "sg:phone":"+1 604 485 6271",
    "sg:postcode":"V8A 1V3",
    "sg:province":"BC",
    "wof:name":"School District 47",
    "wof:placetype":"venue"
},
  "geometry": {"coordinates":[-124.515282,49.833706],"type":"Point"}
}