{
  "type": "Feature",
  "properties": {
    "addr:full":"369 Main St Lawrencetown. NS B0S 1M0",
    "addr:housenumber":"369",
    "addr:postcode":"b0s 1m0",
    "addr:street":"Main St",
    "iso:country":"CA",
    "sg:address":"369 Main St",
    "sg:city":"Lawrencetown.",
    "sg:classifiers":[
        {
            "category":"Personal",
            "subcategory":"Beauty Salon",
            "type":"Services"
        }
    ],
    "sg:phone":"+1 902 584 3553",
    "sg:postcode":"B0S 1M0",
    "sg:province":"NS",
    "wof:name":"Tami's Hair Shoppe",
    "wof:placetype":"venue"
},
  "geometry": {"coordinates":[-63.338531,44.645439],"type":"Point"}
}