{
  "type": "Feature",
  "properties": {
    "addr:full":"Winnipeg MB R2G 0Y4",
    "addr:postcode":"r2g 0y4",
    "iso:country":"CA",
    "sg:city":"Winnipeg",
    "sg:classifiers":[
        {
            "category":"Professional",
            "subcategory":"Accounting & Tax Preparation",
            "type":"Services"
        }
    ],
    "sg:phone":"+1 204 661 2112",
    "sg:postcode":"R2G 0Y4",
    "sg:province":"MB",
    "sg:tags":[
        "accountant"
    ],
    "wof:name":"Harris, Ward CA",
    "wof:placetype":"venue"
},
  "geometry": {"coordinates":[-97.0631637573,49.9269561768],"type":"Point"}
}