{
  "type": "Feature",
  "properties": {
    "addr:full":"185 Wyandotte St E Windsor ON N9A 3H3",
    "addr:housenumber":"185",
    "addr:postcode":"n9a 3h3",
    "addr:street":"Wyandotte St E",
    "iso:country":"CA",
    "sg:address":"185 Wyandotte St E",
    "sg:city":"Windsor",
    "sg:classifiers":[
        {
            "category":"Government",
            "subcategory":"Office",
            "type":"Public Place"
        }
    ],
    "sg:phone":"+1 519 255 6298",
    "sg:postcode":"N9A 3H3",
    "sg:province":"ON",
    "sg:tags":[
        "village"
    ],
    "wof:name":"Windsor Parking Violations",
    "wof:placetype":"venue"
},
  "geometry": {"coordinates":[-83.033997,42.314926],"type":"Point"}
}