{
  "type": "Feature",
  "properties": {
    "addr:full":"2074 Rte Marie-Victorin Saint-Nicolas QC G7A 4H5",
    "addr:housenumber":"2074",
    "addr:postcode":"g7a 4h5",
    "addr:street":"Rte Marie-Victorin",
    "iso:country":"CA",
    "sg:address":"2074 Rte Marie-Victorin",
    "sg:city":"Saint-Nicolas",
    "sg:classifiers":[
        {
            "category":"Wholesale",
            "subcategory":"Fruits & Vegetables",
            "type":"Manufacturing & Wholesale Goods"
        }
    ],
    "sg:phone":"+1 418 836 5505",
    "sg:postcode":"G7A 4H5",
    "sg:province":"QC",
    "sg:tags":[
        "cider",
        "shipper"
    ],
    "wof:name":"Cidrerie & Vergers St-Nicolas",
    "wof:placetype":"venue"
},
  "geometry": {"coordinates":[-71.4560928345,46.692276001],"type":"Point"}
}