{
  "type": "Feature",
  "properties": {
    "addr:full":"2411 Vauxhall Pl Richmond BC V6V 1Z5",
    "addr:housenumber":"2411",
    "addr:postcode":"v6v 1z5",
    "addr:street":"Vauxhall Pl",
    "iso:country":"CA",
    "sg:address":"2411 Vauxhall Pl",
    "sg:city":"Richmond",
    "sg:classifiers":[
        {
            "category":"Professional",
            "subcategory":"Management & Consulting",
            "type":"Services"
        }
    ],
    "sg:phone":"+1 604 276 8989",
    "sg:postcode":"V6V 1Z5",
    "sg:province":"BC",
    "sg:tags":[
        "consultant",
        "industrial"
    ],
    "wof:name":"Advanced Equipment Inc",
    "wof:placetype":"venue"
},
  "geometry": {"coordinates":[-123.08585357699999,49.1966934204],"type":"Point"}
}