{
  "type": "Feature",
  "properties": {
    "addr:full":"221 Centre Ave Meadow Lake SK S9X 1H2",
    "addr:housenumber":"221",
    "addr:postcode":"s9x 1h2",
    "addr:street":"Centre Ave",
    "iso:country":"CA",
    "sg:address":"221 Centre Ave",
    "sg:city":"Meadow Lake",
    "sg:classifiers":[
        {
            "category":"Home & Garden",
            "subcategory":"Building Materials",
            "type":"Retail Goods"
        }
    ],
    "sg:phone":"+1 306 236 5551",
    "sg:postcode":"S9X 1H2",
    "sg:province":"SK",
    "sg:tags":[
        "carpet",
        "dealer",
        "rug"
    ],
    "wof:name":"Mac's Decorating Ctr Ltd",
    "wof:placetype":"venue"
},
  "geometry": {"coordinates":[-108.432197571,54.1199455261],"type":"Point"}
}