{
  "type": "Feature",
  "properties": {
    "addr:full":"Thunder Bay ON P7C 1C8",
    "addr:postcode":"p7c 1c8",
    "iso:country":"CA",
    "sg:city":"Thunder Bay",
    "sg:classifiers":[
        {
            "category":"Social Services",
            "type":"Services"
        }
    ],
    "sg:phone":"+1 807 623 2353",
    "sg:postcode":"P7C 1C8",
    "sg:province":"ON",
    "sg:tags":[
        "organization",
        "welfare"
    ],
    "wof:name":"Wesway Family Support Program",
    "wof:placetype":"venue"
},
  "geometry": {"coordinates":[-89.25960499999999,48.384377],"type":"Point"}
}