{
  "type": "Feature",
  "properties": {
    "addr:full":"681 Rue Des Ateliers Boucherville QC J4B 8H3",
    "addr:housenumber":"681",
    "addr:postcode":"j4b 8h3",
    "addr:street":"Rue Des Ateliers",
    "iso:country":"CA",
    "sg:address":"681 Rue Des Ateliers",
    "sg:city":"Boucherville",
    "sg:classifiers":[
        {
            "category":"Wholesale",
            "subcategory":"Machinery & Supplies",
            "type":"Manufacturing & Wholesale Goods"
        }
    ],
    "sg:phone":"+1 450 655 2252",
    "sg:postcode":"J4B 8H3",
    "sg:province":"QC",
    "sg:tags":[
        "farm",
        "equipment"
    ],
    "wof:name":"Entretien Mecanique Langlois",
    "wof:placetype":"venue"
},
  "geometry": {"coordinates":[-73.44055899999999,45.610142],"type":"Point"}
}