{
  "type": "Feature",
  "properties": {
    "addr:full":"2175 Rue DE LA Montagne Montreal QC H3G 1Z8",
    "addr:housenumber":"2175",
    "addr:postcode":"h3g 1z8",
    "addr:street":"Rue De La Montagne",
    "iso:country":"CA",
    "sg:address":"2175 Rue DE LA Montagne",
    "sg:city":"Montreal",
    "sg:classifiers":[
        {
            "category":"Shopping",
            "subcategory":"Clothing, Apparel, & Fashions",
            "type":"Retail Goods"
        }
    ],
    "sg:phone":"+1 514 844 8874",
    "sg:postcode":"H3G 1Z8",
    "sg:province":"QC",
    "sg:tags":[
        "tailor",
        "furnishing"
    ],
    "wof:name":"Russell Chemises Sur Mesure",
    "wof:placetype":"venue"
},
  "geometry": {"coordinates":[-73.577789,45.499405],"type":"Point"}
}