{
  "type": "Feature",
  "properties": {
    "addr:full":"Bearn QC J0Z 1G0",
    "addr:postcode":"j0z 1g0",
    "iso:country":"CA",
    "sg:city":"Bearn",
    "sg:classifiers":[
        {
            "category":"Freight",
            "type":"Transportation"
        }
    ],
    "sg:phone":"+1 819 726 2433",
    "sg:postcode":"J0Z 1G0",
    "sg:province":"QC",
    "sg:tags":[
        "trucking"
    ],
    "wof:name":"Transport Rc Gingras",
    "wof:placetype":"venue"
},
  "geometry": {"coordinates":[-79.350815,47.284931],"type":"Point"}
}