{
  "type": "Feature",
  "properties": {
    "addr:full":"398 Danforth Ave Toronto ON M4K 1P3",
    "addr:housenumber":"398",
    "addr:postcode":"m4k 1p3",
    "addr:street":"Danforth Ave",
    "iso:country":"CA",
    "sg:address":"398 Danforth Ave",
    "sg:city":"Toronto",
    "sg:classifiers":[
        {
            "category":"Real Estate",
            "subcategory":"Real Estate Agent",
            "type":"Services"
        }
    ],
    "sg:phone":"+1 416 778 7750",
    "sg:postcode":"M4K 1P3",
    "sg:province":"ON",
    "sg:tags":[
        "management"
    ],
    "wof:name":"Astoria Holdings Ltd",
    "wof:placetype":"venue"
},
  "geometry": {"coordinates":[-79.351669,43.677719],"type":"Point"}
}