{
  "type": "Feature",
  "properties": {
    "addr:full":"1640 Ch Kipawa Temiscaming QC J0Z 3R0",
    "addr:postcode":"1640;j0z 3r0",
    "addr:street":"Ch Kipawa Temiscaming",
    "iso:country":"CA",
    "sg:address":"1640 Ch Kipawa",
    "sg:city":"Temiscaming",
    "sg:classifiers":[
        {
            "category":"Travel",
            "subcategory":"Hotels & Motels",
            "type":"Entertainment"
        }
    ],
    "sg:phone":"+1 819 627 9151",
    "sg:postcode":"J0Z 3R0",
    "sg:province":"QC",
    "wof:name":"Auberge Canadienne",
    "wof:placetype":"venue"
},
  "geometry": {"coordinates":[-79.06603200000001,46.737823],"type":"Point"}
}