{
  "type": "Feature",
  "properties": {
    "addr:full":"26th South St Nipigon ON P0T 2J0",
    "addr:postcode":"p0t 2j0",
    "addr:street":"South St",
    "iso:country":"CA",
    "sg:address":"26th South St",
    "sg:city":"Nipigon",
    "sg:classifiers":[
        {
            "category":"Organizations",
            "subcategory":"Religious Organization",
            "type":"Services"
        }
    ],
    "sg:phone":"+1 807 887 3038",
    "sg:postcode":"P0T 2J0",
    "sg:province":"ON",
    "sg:tags":[
        "church"
    ],
    "wof:name":"Catholic Church",
    "wof:placetype":"venue"
},
  "geometry": {"coordinates":[-88.262489,49.013752],"type":"Point"}
}