{
  "type": "Feature",
  "properties": {
    "addr:full":"720 Rue Gilles Laval QC H7P 2W4",
    "addr:housenumber":"720",
    "addr:postcode":"h7p 2w4",
    "addr:street":"Rue Gilles",
    "iso:country":"CA",
    "sg:address":"720 Rue Gilles",
    "sg:city":"Laval",
    "sg:classifiers":[
        {
            "category":"Health Services",
            "subcategory":"Medical Lab",
            "type":"Services"
        }
    ],
    "sg:phone":"+1 450 622 1440",
    "sg:postcode":"H7P 2W4",
    "sg:province":"QC",
    "wof:name":"Clinique DE Denturologie Varin",
    "wof:placetype":"venue"
},
  "geometry": {"coordinates":[-73.7962265015,45.5874977112],"type":"Point"}
}