{
  "type": "Feature",
  "properties": {
    "addr:full":"124 Rue Pinoteau Mont-Tremblant QC J8E 1G2",
    "addr:housenumber":"124",
    "addr:postcode":"j8e 1g2",
    "addr:street":"Rue Pinoteau",
    "iso:country":"CA",
    "sg:address":"124 Rue Pinoteau",
    "sg:city":"Mont-Tremblant",
    "sg:classifiers":[
        {
            "category":"Farming",
            "subcategory":"Aquatic Farm",
            "type":"Manufacturing & Wholesale Goods"
        }
    ],
    "sg:phone":"+1 819 425 2412",
    "sg:postcode":"J8E 1G2",
    "sg:province":"QC",
    "sg:tags":[
        "hatchery",
        "fish"
    ],
    "wof:name":"Pisciculture Mont-Tremblant",
    "wof:placetype":"venue"
},
  "geometry": {"coordinates":[-74.59898376460001,46.2064819336],"type":"Point"}
}