{
  "type": "Feature",
  "properties": {
    "addr:full":"1011 Ch Des Anglais Mascouche QC J7L 3R8",
    "addr:housenumber":"1011",
    "addr:postcode":"j7l 3r8",
    "addr:street":"Ch Des Anglais",
    "iso:country":"CA",
    "sg:address":"1011 Ch Des Anglais",
    "sg:city":"Mascouche",
    "sg:classifiers":[
        {
            "category":"Recreation",
            "type":"Entertainment"
        }
    ],
    "sg:phone":"+1 450 477 7021",
    "sg:postcode":"J7L 3R8",
    "sg:province":"QC",
    "sg:tags":[
        "range",
        "practice",
        "golf"
    ],
    "wof:name":"Arizona Golf DE Pratique",
    "wof:placetype":"venue"
},
  "geometry": {"coordinates":[-73.643135,45.745811],"type":"Point"}
}