{
  "type": "Feature",
  "properties": {
    "addr:full":"1287 Meadowood Way Qualicum Beach BC V9K 2S4",
    "addr:housenumber":"1287",
    "addr:postcode":"v9k 2s4",
    "addr:street":"Meadowood Way",
    "iso:country":"CA",
    "sg:address":"1287 Meadowood Way",
    "sg:city":"Qualicum Beach",
    "sg:classifiers":[
        {
            "category":"Building & Trades",
            "subcategory":"Construction",
            "type":"Services"
        }
    ],
    "sg:phone":"+1 250 752 3026",
    "sg:postcode":"V9K 2S4",
    "sg:province":"BC",
    "sg:tags":[
        "contractor"
    ],
    "wof:name":"Home Sweet Homes",
    "wof:placetype":"venue"
},
  "geometry": {"coordinates":[-124.441704,49.346706],"type":"Point"}
}