{
  "type": "Feature",
  "properties": {
    "addr:full":"85 Rue Lavigueur Quebec QC G1R 1A8",
    "addr:housenumber":"85",
    "addr:postcode":"g1r 1a8",
    "addr:street":"Rue Lavigueur",
    "iso:country":"CA",
    "sg:address":"85 Rue Lavigueur",
    "sg:city":"Quebec",
    "sg:classifiers":[
        {
            "category":"Shopping",
            "subcategory":"Bicycles & Sporting Goods",
            "type":"Retail Goods"
        }
    ],
    "sg:phone":"+1 418 525 8893",
    "sg:postcode":"G1R 1A8",
    "sg:province":"QC",
    "sg:tags":[
        "equipment",
        "diver",
        "supply"
    ],
    "wof:name":"Bolan Enr",
    "wof:placetype":"venue"
},
  "geometry": {"coordinates":[-71.22827100000001,46.808517],"type":"Point"}
}