{
  "type": "Feature",
  "properties": {
    "addr:full":"606 Sand Cove Rd Saint John NB E2M 3C4",
    "addr:housenumber":"606",
    "addr:postcode":"e2m 3c4",
    "addr:street":"Sand Cove Rd",
    "iso:country":"CA",
    "sg:address":"606 Sand Cove Rd",
    "sg:city":"Saint John",
    "sg:classifiers":[
        {
            "category":"Personal",
            "subcategory":"Beauty Salon",
            "type":"Services"
        }
    ],
    "sg:phone":"+1 506 672 1605",
    "sg:postcode":"E2M 3C4",
    "sg:province":"NB",
    "wof:name":"Catherine Scissorhands",
    "wof:placetype":"venue"
},
  "geometry": {"coordinates":[-66.08895099999999,45.251644],"type":"Point"}
}