{
  "type": "Feature",
  "properties": {
    "iso:country":"CA",
    "sg:city":"Yellowknife",
    "sg:classifiers":[
        {
            "category":"Government",
            "subcategory":"Office",
            "type":"Public Place"
        }
    ],
    "sg:phone":"+1 867 669 4900",
    "sg:postcode":"X1A 1E2",
    "sg:province":"NT",
    "wof:name":"Canada Fisheries Management",
    "wof:placetype":"venue"
},
  "geometry": {"coordinates":[-114.375328064,62.452583313],"type":"Point"}
}