{
  "type": "Feature",
  "properties": {
    "addr:full":"1420 Rue Legendre E Montreal QC H2M 1H5",
    "addr:housenumber":"1420",
    "addr:postcode":"h2m 1h5",
    "addr:street":"Rue Legendre E",
    "iso:country":"CA",
    "sg:address":"1420 Rue Legendre E",
    "sg:city":"Montreal",
    "sg:classifiers":[
        {
            "category":"Restaurant",
            "type":"Food & Drink"
        }
    ],
    "sg:phone":"+1 514 389 1990",
    "sg:postcode":"H2M 1H5",
    "sg:province":"QC",
    "wof:name":"Restaurant Casa Nassau",
    "wof:placetype":"venue"
},
  "geometry": {"coordinates":[-73.6379318237,45.55859375],"type":"Point"}
}