{
  "type": "Feature",
  "properties": {
    "iso:country":"CA",
    "sg:address":"7035 Fir Tree Dr",
    "sg:city":"Mississauga",
    "sg:classifiers":[
        {
            "category":"Freight",
            "type":"Transportation"
        }
    ],
    "sg:phone":"+1 905 673 1995",
    "sg:postcode":"L5S 1J7",
    "sg:province":"ON",
    "sg:tags":[
        "courier"
    ],
    "wof:name":"Al's Quality Express Ltd",
    "wof:placetype":"venue"
},
  "geometry": {"coordinates":[-79.65855407710001,43.6915817261],"type":"Point"}
}