{
  "type": "Feature",
  "properties": {
    "addr:full":"3930 Montrose Rd Niagara Falls ON L2H 3C9",
    "addr:housenumber":"3930",
    "addr:postcode":"l2h 3c9",
    "addr:street":"Montrose Rd",
    "iso:country":"CA",
    "sg:address":"3930 Montrose Rd",
    "sg:city":"Niagara Falls",
    "sg:classifiers":[
        {
            "category":"Restaurant",
            "type":"Food & Drink"
        }
    ],
    "sg:phone":"+1 905 371 3918",
    "sg:postcode":"L2H 3C9",
    "sg:province":"ON",
    "wof:name":"Jasmine Chinese Cuisine",
    "wof:placetype":"venue"
},
  "geometry": {"coordinates":[-79.124504,43.115608],"type":"Point"}
}