{
  "type": "Feature",
  "properties": {
    "iso:country":"CA",
    "sg:address":"6 Railway Ave",
    "sg:city":"Brunkild",
    "sg:phone":"+1 204 736 4331",
    "sg:postcode":"R0G 0E0",
    "sg:province":"MB",
    "sg:tags":[
        "oil"
    ],
    "wof:name":"Shell Canada Bulk Agent",
    "wof:placetype":"venue"
},
  "geometry": {"coordinates":[-97.5743103027,49.5927886963],"type":"Point"}
}