{
  "type": "Feature",
  "properties": {
    "iso:country":"CA",
    "sg:address":"1150 Wellington Rd",
    "sg:city":"London",
    "sg:classifiers":[
        {
            "category":"Travel",
            "subcategory":"Hotels & Motels",
            "type":"Entertainment"
        }
    ],
    "sg:phone":"+1 519 681 0600",
    "sg:postcode":"N6E 1M3",
    "sg:province":"ON",
    "wof:name":"Four Points Hotel Sheraton",
    "wof:placetype":"venue"
},
  "geometry": {"coordinates":[-81.21946,42.929504],"type":"Point"}
}