{
  "type": "Feature",
  "properties": {
    "addr:full":"299 Cedar St Simcoe ON N3Y 2J2",
    "addr:housenumber":"299",
    "addr:postcode":"n3y 2j2",
    "addr:street":"Cedar St",
    "iso:country":"CA",
    "sg:address":"299 Cedar St",
    "sg:city":"Simcoe",
    "sg:classifiers":[
        {
            "category":"Food & Beverages",
            "subcategory":"Groceries & Convenience Stores",
            "type":"Retail Goods"
        }
    ],
    "sg:phone":"+1 519 426 8944",
    "sg:postcode":"N3Y 2J2",
    "sg:province":"ON",
    "wof:name":"Cedar Street Food Market",
    "wof:placetype":"venue"
},
  "geometry": {"coordinates":[-80.3199081421,42.8416938782],"type":"Point"}
}