{
  "type": "Feature",
  "properties": {
    "addr:full":"232 Dundas St Waterdown ON L0R 2H4",
    "addr:housenumber":"232",
    "addr:postcode":"l0r 2h4",
    "addr:street":"Dundas St",
    "iso:country":"CA",
    "sg:address":"232 Dundas St",
    "sg:city":"Waterdown",
    "sg:classifiers":[
        {
            "category":"Autos & Motor Vehicles",
            "subcategory":"Fuel & Gas Station",
            "type":"Retail Goods"
        }
    ],
    "sg:phone":"+1 905 690 6087",
    "sg:postcode":"L0R 2H4",
    "sg:province":"ON",
    "sg:tags":[
        "oil"
    ],
    "wof:name":"Suny's Gas Bar",
    "wof:placetype":"venue"
},
  "geometry": {"coordinates":[-79.89904,43.327888],"type":"Point"}
}