{
  "type": "Feature",
  "properties": {
    "addr:full":"85 Cedar Dr Turkey Point ON N0E 1T0",
    "addr:housenumber":"85",
    "addr:postcode":"n0e 1t0",
    "addr:street":"Cedar Dr Turkey Point",
    "iso:country":"CA",
    "sg:address":"85 Cedar Dr",
    "sg:city":"Turkey Point",
    "sg:classifiers":[
        {
            "category":"Restaurant",
            "type":"Food & Drink"
        }
    ],
    "sg:phone":"+1 519 426 6606",
    "sg:postcode":"N0E 1T0",
    "sg:province":"ON",
    "wof:name":"Sun Tan Restaurant & Motel",
    "wof:placetype":"venue"
},
  "geometry": {"coordinates":[-80.3274383545,42.6915359497],"type":"Point"}
}