{
  "type": "Feature",
  "properties": {
    "addr:full":"Parry Sound ON P2A 2W7",
    "addr:postcode":"p2a 2w7",
    "iso:country":"CA",
    "sg:city":"Parry Sound",
    "sg:classifiers":[
        {
            "category":"Building & Trades",
            "subcategory":"Electrical",
            "type":"Services"
        }
    ],
    "sg:phone":"+1 705 389 9987",
    "sg:postcode":"P2A 2W7",
    "sg:province":"ON",
    "sg:tags":[
        "electric",
        "contractor"
    ],
    "wof:name":"Weatherill Electric Ltd",
    "wof:placetype":"venue"
},
  "geometry": {"coordinates":[-80.0363616943,45.3447685242],"type":"Point"}
}