{
  "type": "Feature",
  "properties": {
    "addr:full":"4305 Redford St Port Alberni BC V9Y 3R2",
    "addr:housenumber":"4305",
    "addr:postcode":"v9y 3r2",
    "addr:street":"Redford St",
    "iso:country":"CA",
    "sg:address":"4305 Redford St",
    "sg:city":"Port Alberni",
    "sg:classifiers":[
        {
            "category":"Autos & Motor Vehicles",
            "subcategory":"Fuel & Gas Station",
            "type":"Retail Goods"
        }
    ],
    "sg:phone":"+1 250 724 2241",
    "sg:postcode":"V9Y 3R2",
    "sg:province":"BC",
    "sg:tags":[
        "oil"
    ],
    "wof:name":"Redford Shell Food Store",
    "wof:placetype":"venue"
},
  "geometry": {"coordinates":[-124.798065185,49.2454299927],"type":"Point"}
}