{
  "type": "Feature",
  "properties": {
    "addr:full":"6910 Rue Saint-Jacques Montreal QC H4B 1V8",
    "addr:housenumber":"6910",
    "addr:postcode":"h4b 1v8",
    "addr:street":"Rue Saint-Jacques",
    "iso:country":"CA",
    "sg:address":"6910 Rue Saint-Jacques",
    "sg:city":"Montreal",
    "sg:classifiers":[
        {
            "category":"Bars & Pubs",
            "type":"Food & Drink"
        }
    ],
    "sg:phone":"+1 514 489 6356",
    "sg:postcode":"H4B 1V8",
    "sg:province":"QC",
    "wof:name":"Pub Pj",
    "wof:placetype":"venue"
},
  "geometry": {"coordinates":[-73.6291351318,45.4572792053],"type":"Point"}
}