{
  "type": "Feature",
  "properties": {
    "addr:full":"Calgary AB T2R 0G5",
    "addr:postcode":"t2r 0g5",
    "iso:country":"CA",
    "sg:city":"Calgary",
    "sg:classifiers":[
        {
            "category":"Professional",
            "subcategory":"Lawyer & Legal Services",
            "type":"Services"
        }
    ],
    "sg:phone":"+1 403 229 1111",
    "sg:postcode":"T2R 0G5",
    "sg:province":"AB",
    "sg:tags":[
        "attorney"
    ],
    "wof:name":"Szabo & CO",
    "wof:placetype":"venue"
},
  "geometry": {"coordinates":[-114.08684539799999,51.0429000854],"type":"Point"}
}