{
  "type": "Feature",
  "properties": {
    "addr:full":"5380 Av Du Marechal-Joffre Charny QC G6X 3C7",
    "addr:housenumber":"5380",
    "addr:postcode":"g6x 3c7",
    "addr:street":"Av Du Marechal-Joffre",
    "iso:country":"CA",
    "sg:address":"5380 Av Du Marechal-Joffre",
    "sg:city":"Charny",
    "sg:classifiers":[
        {
            "category":"Retail",
            "subcategory":"Car Wash",
            "type":"Services"
        }
    ],
    "sg:phone":"+1 418 832 9911",
    "sg:postcode":"G6X 3C7",
    "sg:province":"QC",
    "sg:tags":[
        "polishing",
        "washing"
    ],
    "wof:name":"Perma-Shine Antirouille",
    "wof:placetype":"venue"
},
  "geometry": {"coordinates":[-71.260605,46.716702],"type":"Point"}
}