{
  "type": "Feature",
  "properties": {
    "iso:country":"CA",
    "sg:city":"Wellington Station",
    "sg:classifiers":[
        {
            "category":"Building & Trades",
            "subcategory":"Construction",
            "type":"Services"
        }
    ],
    "sg:phone":"+1 902 854 2294",
    "sg:postcode":"C0B 2E0",
    "sg:province":"PE",
    "sg:tags":[
        "concrete",
        "contractor"
    ],
    "wof:name":"Egmont Bay Construction Ltd",
    "wof:placetype":"venue"
},
  "geometry": {"coordinates":[-64.0004501343,46.4499511719],"type":"Point"}
}