{
  "type": "Feature",
  "properties": {
    "iso:country":"CA",
    "sg:city":"New Westminster",
    "sg:classifiers":[
        {
            "category":"Recreation",
            "type":"Entertainment"
        }
    ],
    "sg:phone":"+1 604 520 7000",
    "sg:postcode":"V3L 3K1",
    "sg:province":"BC",
    "sg:tags":[
        "boating",
        "instruction"
    ],
    "wof:name":"Captain Mac's School-Seamanshp",
    "wof:placetype":"venue"
},
  "geometry": {"coordinates":[-122.893981934,49.224773407],"type":"Point"}
}