{
  "type": "Feature",
  "properties": {
    "addr:full":"Quebec QC G1R 2J1",
    "addr:postcode":"g1r 2j1",
    "iso:country":"CA",
    "sg:city":"Quebec",
    "sg:classifiers":[
        {
            "category":"Real Estate",
            "subcategory":"Real Estate Operator",
            "type":"Services"
        }
    ],
    "sg:phone":"+1 418 529 5458",
    "sg:postcode":"G1R 2J1",
    "sg:province":"QC",
    "sg:tags":[
        "apartment"
    ],
    "wof:name":"Claridge Apartments",
    "wof:placetype":"venue"
},
  "geometry": {"coordinates":[-71.2212219238,46.8037986755],"type":"Point"}
}