{
  "type": "Feature",
  "properties": {
    "addr:full":"120 Railway Ave LA Riviere MB R0G 1A0",
    "addr:housenumber":"120",
    "addr:postcode":"r0g 1a0",
    "addr:street":"Railway Ave",
    "iso:country":"CA",
    "sg:address":"120 Railway Ave",
    "sg:city":"LA Riviere",
    "sg:classifiers":[
        {
            "category":"Travel",
            "subcategory":"Hotels & Motels",
            "type":"Entertainment"
        }
    ],
    "sg:phone":"+1 204 242 3023",
    "sg:postcode":"R0G 1A0",
    "sg:province":"MB",
    "wof:name":"Riviere Hotel",
    "wof:placetype":"venue"
},
  "geometry": {"coordinates":[-98.68032100000001,49.238739],"type":"Point"}
}