{
  "type": "Feature",
  "properties": {
    "addr:full":"20 Burnett Ave Winnipeg MB R2G 1C1",
    "addr:housenumber":"20",
    "addr:postcode":"r2g 1c1",
    "addr:street":"Burnett Ave",
    "iso:country":"CA",
    "sg:address":"20 Burnett Ave",
    "sg:city":"Winnipeg",
    "sg:classifiers":[
        {
            "category":"Manufacturing",
            "subcategory":"Glass & Minerals",
            "type":"Manufacturing & Wholesale Goods"
        }
    ],
    "sg:phone":"+1 204 668 9320",
    "sg:postcode":"R2G 1C1",
    "sg:province":"MB",
    "sg:tags":[
        "fabricator",
        "fiber"
    ],
    "wof:name":"Structural Glass Ltd",
    "wof:placetype":"venue"
},
  "geometry": {"coordinates":[-97.065201,49.932076],"type":"Point"}
}