{
  "type": "Feature",
  "properties": {
    "addr:full":"3524 Rue Ashby Saint-Laurent QC H4R 2C1",
    "addr:housenumber":"3524",
    "addr:postcode":"h4r 2c1",
    "addr:street":"Rue Ashby",
    "iso:country":"CA",
    "sg:address":"3524 Rue Ashby",
    "sg:city":"Saint-Laurent",
    "sg:classifiers":[
        {
            "category":"Freight",
            "type":"Transportation"
        }
    ],
    "sg:phone":"+1 514 331 3437",
    "sg:postcode":"H4R 2C1",
    "sg:province":"QC",
    "sg:tags":[
        "shipping",
        "agent"
    ],
    "wof:name":"Venus Transport",
    "wof:placetype":"venue"
},
  "geometry": {"coordinates":[-73.716492,45.498386],"type":"Point"}
}