{
  "type": "Feature",
  "properties": {
    "iso:country":"CA",
    "sg:address":"751 Boul Saint-Joseph E",
    "sg:city":"Montreal",
    "sg:classifiers":[
        {
            "category":"Professional",
            "subcategory":"Lawyer & Legal Services",
            "type":"Services"
        }
    ],
    "sg:phone":"+1 514 844 0129",
    "sg:postcode":"H2J 1K3",
    "sg:province":"QC",
    "sg:tags":[
        "accountant",
        "attorney"
    ],
    "wof:name":"Boisvert DE Niverville & Assoc",
    "wof:placetype":"venue"
},
  "geometry": {"coordinates":[-73.5864028931,45.528213501],"type":"Point"}
}