{
  "type": "Feature",
  "properties": {
    "addr:full":"26 Albert St Welland ON L3B 4L2",
    "addr:housenumber":"26",
    "addr:postcode":"l3b 4l2",
    "addr:street":"Albert St",
    "iso:country":"CA",
    "sg:address":"26 Albert St",
    "sg:city":"Welland",
    "sg:classifiers":[
        {
            "category":"Building & Trades",
            "subcategory":"Construction",
            "type":"Services"
        }
    ],
    "sg:phone":"+1 905 735 8943",
    "sg:postcode":"L3B 4L2",
    "sg:province":"ON",
    "sg:tags":[
        "windows",
        "solarium"
    ],
    "wof:name":"Greg Berry Renovations",
    "wof:placetype":"venue"
},
  "geometry": {"coordinates":[-79.250289917,42.98595047],"type":"Point"}
}