{
  "type": "Feature",
  "properties": {
    "addr:full":"100 Rue Wolfe Levis QC G6V 3Y6",
    "addr:housenumber":"100",
    "addr:postcode":"g6v 3y6",
    "addr:street":"Rue Wolfe",
    "iso:country":"CA",
    "sg:address":"100 Rue Wolfe",
    "sg:city":"Levis",
    "sg:classifiers":[
        {
            "category":"Personal",
            "subcategory":"Beauty Salon",
            "type":"Services"
        }
    ],
    "sg:phone":"+1 418 837 1204",
    "sg:postcode":"G6V 3Y6",
    "sg:province":"QC",
    "wof:name":"Coiffure Kevin-Pier",
    "wof:placetype":"venue"
},
  "geometry": {"coordinates":[-71.18222045900001,46.8127708435],"type":"Point"}
}