{
  "type": "Feature",
  "properties": {
    "addr:full":"114 Walton St Port Hope ON L1A 1N5",
    "addr:housenumber":"114",
    "addr:postcode":"l1a 1n5",
    "addr:street":"Walton St",
    "iso:country":"CA",
    "sg:address":"114 Walton St",
    "sg:city":"Port Hope",
    "sg:classifiers":[
        {
            "category":"Professional",
            "subcategory":"Lawyer & Legal Services",
            "type":"Services"
        }
    ],
    "sg:phone":"+1 905 885 2451",
    "sg:postcode":"L1A 1N5",
    "sg:province":"ON",
    "sg:tags":[
        "attorney"
    ],
    "wof:name":"Mc Cracken, Allan",
    "wof:placetype":"venue"
},
  "geometry": {"coordinates":[-78.29542499999999,43.951988],"type":"Point"}
}