{
  "type": "Feature",
  "properties": {
    "addr:full":"Calgary AB T2P 0G7",
    "addr:postcode":"t2p 0g7",
    "iso:country":"CA",
    "sg:city":"Calgary",
    "sg:classifiers":[
        {
            "category":"Education",
            "subcategory":"School",
            "type":"Public Place"
        }
    ],
    "sg:phone":"+1 403 265 5718",
    "sg:postcode":"T2P 0G7",
    "sg:province":"AB",
    "sg:tags":[
        "kindergarten",
        "child",
        "care"
    ],
    "wof:name":"Tiny Tykes Creative Child Care",
    "wof:placetype":"venue"
},
  "geometry": {"coordinates":[-114.076958,51.050766],"type":"Point"}
}