{
  "type": "Feature",
  "properties": {
    "iso:country":"CA",
    "sg:address":"2055 Winston Park Dr",
    "sg:city":"Oakville",
    "sg:classifiers":[
        {
            "category":"Restaurant",
            "type":"Food & Drink"
        }
    ],
    "sg:phone":"+1 905 829 9592",
    "sg:postcode":"L6H 6P5",
    "sg:province":"ON",
    "sg:tags":[
        "shop",
        "coffee"
    ],
    "wof:name":"Timothy's World Coffee",
    "wof:placetype":"venue"
},
  "geometry": {"coordinates":[-79.668999,43.508492],"type":"Point"}
}