{
  "type": "Feature",
  "properties": {
    "iso:country":"CA",
    "sg:address":"4333 46 Ave SE",
    "sg:city":"Calgary",
    "sg:classifiers":[
        {
            "category":"Mining & Drilling",
            "type":"Manufacturing & Wholesale Goods"
        }
    ],
    "sg:phone":"+1 403 279 8545",
    "sg:postcode":"T2B 3N5",
    "sg:province":"AB",
    "sg:tags":[
        "mud",
        "oil",
        "well",
        "additive"
    ],
    "wof:name":"Brine-Add Fluids Ltd",
    "wof:placetype":"venue"
},
  "geometry": {"coordinates":[-113.97114563,51.0131263733],"type":"Point"}
}