{
  "type": "Feature",
  "properties": {
    "iso:country":"CA",
    "sg:address":"60 Lancing Dr",
    "sg:city":"Hamilton",
    "sg:classifiers":[
        {
            "category":"Manufacturing",
            "subcategory":"Glass & Minerals",
            "type":"Manufacturing & Wholesale Goods"
        }
    ],
    "sg:phone":"+1 905 387 8613",
    "sg:postcode":"L8W 3A1",
    "sg:province":"ON",
    "sg:tags":[
        "granite"
    ],
    "wof:name":"Take US For Granite",
    "wof:placetype":"venue"
},
  "geometry": {"coordinates":[-79.84056854249999,43.1928520203],"type":"Point"}
}