{
  "type": "Feature",
  "properties": {
    "addr:full":"11451 Bridgeport Rd # 140 Richmond BC V6X 1T4",
    "addr:housenumber":"11451;140",
    "addr:postcode":"v6x 1t4",
    "addr:street":"Bridgeport Rd #",
    "iso:country":"CA",
    "sg:address":"11451 Bridgeport Rd # 140",
    "sg:city":"Richmond",
    "sg:classifiers":[
        {
            "category":"Building & Trades",
            "subcategory":"Construction",
            "type":"Services"
        }
    ],
    "sg:phone":"+1 604 207 0027",
    "sg:postcode":"V6X 1T4",
    "sg:province":"BC",
    "sg:tags":[
        "railing"
    ],
    "wof:name":"Sunning Trading CO",
    "wof:placetype":"venue"
},
  "geometry": {"coordinates":[-123.09710699999999,49.192127],"type":"Point"}
}