{
  "type": "Feature",
  "properties": {
    "addr:full":"6890 Pleasant Valley Rd Vernon BC V1B 3R5",
    "addr:housenumber":"6890",
    "addr:postcode":"bc v1b 3r5",
    "addr:street":"Pleasant Valley Rd",
    "iso:country":"CA",
    "sg:address":"6890 Pleasant Valley Rd",
    "sg:city":"Vernon",
    "sg:classifiers":[
        {
            "category":"Education",
            "subcategory":"School",
            "type":"Public Place"
        }
    ],
    "sg:phone":"+1 250 545 7345",
    "sg:postcode":"V1B 3R5",
    "sg:province":"BC",
    "wof:name":"Vernon Christian School",
    "wof:placetype":"venue"
},
  "geometry": {"coordinates":[-119.25355500000001,50.282928],"type":"Point"}
}