{
  "type": "Feature",
  "properties": {
    "iso:country":"CA",
    "sg:address":"6951 Rue Saint-Jacques",
    "sg:city":"Montreal",
    "sg:classifiers":[
        {
            "category":"Travel",
            "subcategory":"Hotels & Motels",
            "type":"Entertainment"
        }
    ],
    "sg:phone":"+1 514 488 9561",
    "sg:postcode":"H4B 1V3",
    "sg:province":"QC",
    "wof:name":"Hotel Chablis",
    "wof:placetype":"venue"
},
  "geometry": {"coordinates":[-73.629807,45.457134],"type":"Point"}
}