{
  "type": "Feature",
  "properties": {
    "addr:full":"6951 Rue Saint-Jacques Montreal QC H4B 1V3",
    "addr:housenumber":"6951",
    "addr:postcode":"h4b 1v3",
    "addr:street":"Rue Saint-Jacques",
    "iso:country":"CA",
    "sg:address":"6951 Rue Saint-Jacques",
    "sg:city":"Montreal",
    "sg:classifiers":[
        {
            "category":"Travel",
            "subcategory":"Hotels & Motels",
            "type":"Entertainment"
        }
    ],
    "sg:phone":"+1 514 488 9561",
    "sg:postcode":"H4B 1V3",
    "sg:province":"QC",
    "wof:name":"Hotel Chablis",
    "wof:placetype":"venue"
},
  "geometry": {"coordinates":[-73.629807,45.457134],"type":"Point"}
}