{
  "type": "Feature",
  "properties": {
    "iso:country":"CA",
    "sg:address":"805 Kildare St",
    "sg:city":"New Denver",
    "sg:classifiers":[
        {
            "category":"Shopping",
            "subcategory":"Catalog Store",
            "type":"Retail Goods"
        }
    ],
    "sg:phone":"+1 250 358 7926",
    "sg:postcode":"V0G 1S0",
    "sg:province":"BC",
    "sg:tags":[
        "mail",
        "order",
        "internet"
    ],
    "wof:name":"Sears Canada Inc",
    "wof:placetype":"venue"
},
  "geometry": {"coordinates":[-117.37397,49.985352],"type":"Point"}
}