{
  "type": "Feature",
  "properties": {
    "addr:full":"832 Charles St Bridgenorth ON K0L 1H0",
    "addr:housenumber":"832",
    "addr:postcode":"k0l 1h0",
    "addr:street":"Charles St",
    "iso:country":"CA",
    "sg:address":"832 Charles St",
    "sg:city":"Bridgenorth",
    "sg:classifiers":[
        {
            "category":"Organizations",
            "subcategory":"Religious Organization",
            "type":"Services"
        }
    ],
    "sg:phone":"+1 705 292 9601",
    "sg:postcode":"K0L 1H0",
    "sg:province":"ON",
    "sg:tags":[
        "church"
    ],
    "wof:name":"Bridgenorth United Church",
    "wof:placetype":"venue"
},
  "geometry": {"coordinates":[-78.382561,44.379025],"type":"Point"}
}