{
  "type": "Feature",
  "properties": {
    "addr:full":"192 Rue Benjamin-Hudon Saint-Laurent QC H4N 1H8",
    "addr:housenumber":"192",
    "addr:postcode":"h4n 1h8",
    "addr:street":"Rue Benjamin-Hudon",
    "iso:country":"CA",
    "sg:address":"192 Rue Benjamin-Hudon",
    "sg:city":"Saint-Laurent",
    "sg:classifiers":[
        {
            "category":"Wholesale",
            "subcategory":"Apparel",
            "type":"Manufacturing & Wholesale Goods"
        }
    ],
    "sg:phone":"+1 514 332 5023",
    "sg:postcode":"H4N 1H8",
    "sg:province":"QC",
    "sg:tags":[
        "importer"
    ],
    "wof:name":"Ducale Importing Inc",
    "wof:placetype":"venue"
},
  "geometry": {"coordinates":[-73.6562805176,45.5275878906],"type":"Point"}
}