{
  "type": "Feature",
  "properties": {
    "iso:country":"CA",
    "sg:address":"430 Boul Alexandre-Tache",
    "sg:city":"Hull",
    "sg:classifiers":[
        {
            "category":"Government",
            "subcategory":"Office",
            "type":"Public Place"
        }
    ],
    "sg:phone":"+1 819 772 3283",
    "sg:postcode":"J9A 1M7",
    "sg:province":"QC",
    "sg:tags":[
        "instruction",
        "music"
    ],
    "wof:name":"Conservatoire DE Musique",
    "wof:placetype":"venue"
},
  "geometry": {"coordinates":[-75.74848937989999,45.4213027954],"type":"Point"}
}