{
  "type": "Feature",
  "properties": {
    "iso:country":"CA",
    "sg:address":"2651 Islington Ave",
    "sg:city":"Etobicoke",
    "sg:classifiers":[
        {
            "category":"Shopping",
            "subcategory":"Gifts & Souvenirs",
            "type":"Retail Goods"
        }
    ],
    "sg:phone":"+1 416 740 5311",
    "sg:postcode":"M9V 2X6",
    "sg:province":"ON",
    "sg:tags":[
        "shop"
    ],
    "wof:name":"Bears & Stuff",
    "wof:placetype":"venue"
},
  "geometry": {"coordinates":[-79.56572723390001,43.7385559082],"type":"Point"}
}