{
  "type": "Feature",
  "properties": {
    "addr:full":"1684 Victoria Park Ave North York ON M1R 1R1",
    "addr:housenumber":"1684",
    "addr:postcode":"m1r 1r1",
    "addr:street":"Victoria Park Ave",
    "iso:country":"CA",
    "sg:address":"1684 Victoria Park Ave",
    "sg:city":"North York",
    "sg:classifiers":[
        {
            "category":"Organizations",
            "subcategory":"Religious Organization",
            "type":"Services"
        }
    ],
    "sg:phone":"+1 416 757 1593",
    "sg:postcode":"M1R 1R1",
    "sg:province":"ON",
    "sg:tags":[
        "church"
    ],
    "wof:name":"Emmanuel Lutheran Church",
    "wof:placetype":"venue"
},
  "geometry": {"coordinates":[-79.306183,43.732803],"type":"Point"}
}