{
  "type": "Feature",
  "properties": {
    "iso:country":"CA",
    "sg:address":"140 Silas Blvd",
    "sg:city":"Keswick",
    "sg:classifiers":[
        {
            "category":"Building & Trades",
            "subcategory":"Construction",
            "type":"Services"
        }
    ],
    "sg:phone":"+1 905 476 7496",
    "sg:postcode":"L4P 2K3",
    "sg:province":"ON",
    "sg:tags":[
        "maker",
        "cabinet"
    ],
    "wof:name":"Rudy's Pools & Carpentry Shop",
    "wof:placetype":"venue"
},
  "geometry": {"coordinates":[-79.4663391113,44.2379951477],"type":"Point"}
}