{
  "type": "Feature",
  "properties": {
    "addr:full":"1405 Bloor St W Toronto ON M6P 3L4",
    "addr:housenumber":"1405",
    "addr:postcode":"m6p 3l4",
    "addr:street":"Bloor St W",
    "iso:country":"CA",
    "sg:address":"1405 Bloor St W",
    "sg:city":"Toronto",
    "sg:classifiers":[
        {
            "category":"Retail",
            "subcategory":"Auto Repair",
            "type":"Services"
        }
    ],
    "sg:phone":"+1 416 516 6650",
    "sg:postcode":"M6P 3L4",
    "sg:province":"ON",
    "sg:tags":[
        "body",
        "automobile",
        "painting"
    ],
    "wof:name":"Cool 1 Autobody",
    "wof:placetype":"venue"
},
  "geometry": {"coordinates":[-79.4472961426,43.6572418213],"type":"Point"}
}