{
  "type": "Feature",
  "properties": {
    "addr:full":"3661 Boul Mountainview Saint-Hubert QC J3Y 5N7",
    "addr:housenumber":"3661",
    "addr:postcode":"j3y 5n7",
    "addr:street":"Boul Mountainview",
    "iso:country":"CA",
    "sg:address":"3661 Boul Mountainview",
    "sg:city":"Saint-Hubert",
    "sg:classifiers":[
        {
            "category":"Home & Garden",
            "subcategory":"Furniture",
            "type":"Retail Goods"
        }
    ],
    "sg:phone":"+1 450 462 8647",
    "sg:postcode":"J3Y 5N7",
    "sg:province":"QC",
    "sg:tags":[
        "equipment",
        "kitchen",
        "cabinet"
    ],
    "wof:name":"Cuisine Qualibel Inc",
    "wof:placetype":"venue"
},
  "geometry": {"coordinates":[-73.3795471191,45.4656257629],"type":"Point"}
}