{
  "type": "Feature",
  "properties": {
    "iso:country":"CA",
    "sg:address":"185 Shade St",
    "sg:city":"New Hamburg",
    "sg:classifiers":[
        {
            "category":"Building & Trades",
            "subcategory":"Construction",
            "type":"Services"
        }
    ],
    "sg:phone":"+1 519 662 2098",
    "sg:postcode":"N3A 4J2",
    "sg:province":"ON",
    "sg:tags":[
        "builder",
        "repairer",
        "masonry",
        "chimney",
        "contractor"
    ],
    "wof:name":"Wayne Bender Construction Ltd",
    "wof:placetype":"venue"
},
  "geometry": {"coordinates":[-80.718704,43.377411],"type":"Point"}
}