{
  "type": "Feature",
  "properties": {
    "addr:full":"175 Rue Scott Mcmasterville QC J3G 1K9",
    "addr:housenumber":"175",
    "addr:postcode":"j3g 1k9",
    "addr:street":"Rue Scott",
    "iso:country":"CA",
    "sg:address":"175 Rue Scott",
    "sg:city":"Mcmasterville",
    "sg:classifiers":[
        {
            "category":"Building & Trades",
            "subcategory":"Construction",
            "type":"Services"
        }
    ],
    "sg:phone":"+1 450 464 7320",
    "sg:postcode":"J3G 1K9",
    "sg:province":"QC",
    "sg:tags":[
        "painter"
    ],
    "wof:name":"Rolland Moreau & Fils Inc",
    "wof:placetype":"venue"
},
  "geometry": {"coordinates":[-73.23616790769999,45.5555953979],"type":"Point"}
}