{
  "type": "Feature",
  "properties": {
    "addr:full":"811 Robinson Dr Sudbury ON P3E 2J2",
    "addr:housenumber":"811",
    "addr:postcode":"p3e 2j2",
    "addr:street":"Robinson Dr",
    "iso:country":"CA",
    "sg:address":"811 Robinson Dr",
    "sg:city":"Sudbury",
    "sg:classifiers":[
        {
            "category":"Education",
            "subcategory":"School",
            "type":"Public Place"
        }
    ],
    "sg:phone":"+1 705 522 8810",
    "sg:postcode":"P3E 2J2",
    "sg:province":"ON",
    "wof:name":"Corpus Christi School",
    "wof:placetype":"venue"
},
  "geometry": {"coordinates":[-81.022141,46.462082],"type":"Point"}
}