{
  "type": "Feature",
  "properties": {
    "addr:full":"2001 Rue Davis Jonquiere QC G7S 3B5",
    "addr:housenumber":"2001",
    "addr:postcode":"g7s 3b5",
    "addr:street":"Rue Davis",
    "iso:country":"CA",
    "sg:address":"2001 Rue Davis",
    "sg:city":"Jonquiere",
    "sg:classifiers":[
        {
            "category":"Personal",
            "subcategory":"Beauty Salon",
            "type":"Services"
        }
    ],
    "sg:phone":"+1 418 548 6193",
    "sg:postcode":"G7S 3B5",
    "sg:province":"QC",
    "wof:name":"Coiffure Internationale",
    "wof:placetype":"venue"
},
  "geometry": {"coordinates":[-71.18199157710001,48.4242134094],"type":"Point"}
}