{
  "type": "Feature",
  "properties": {
    "addr:full":"1175 Davie St Vancouver BC V6E 1N2",
    "addr:housenumber":"1175",
    "addr:postcode":"v6e 1n2",
    "addr:street":"Davie St",
    "iso:country":"CA",
    "sg:address":"1175 Davie St",
    "sg:city":"Vancouver",
    "sg:classifiers":[
        {
            "category":"Restaurant",
            "type":"Food & Drink"
        }
    ],
    "sg:phone":"+1 604 682 8820",
    "sg:postcode":"V6E 1N2",
    "sg:province":"BC",
    "wof:name":"Andale's Mexican Restaurant",
    "wof:placetype":"venue"
},
  "geometry": {"coordinates":[-123.13259100000001,49.281475],"type":"Point"}
}