{
  "type": "Feature",
  "properties": {
    "addr:full":"Abbotsford BC V2S 1L4",
    "addr:postcode":"v2s 1l4",
    "iso:country":"CA",
    "sg:city":"Abbotsford",
    "sg:classifiers":[
        {
            "category":"Food & Beverages",
            "subcategory":"Groceries & Convenience Stores",
            "type":"Retail Goods"
        }
    ],
    "sg:phone":"+1 604 859 8811",
    "sg:postcode":"V2S 1L4",
    "sg:province":"BC",
    "sg:tags":[
        "grocer"
    ],
    "wof:name":"Marshall Road Mini Mart",
    "wof:placetype":"venue"
},
  "geometry": {"coordinates":[-122.291976929,49.0391273499],"type":"Point"}
}