{
  "type": "Feature",
  "properties": {
    "addr:full":"1650 Boul Industriel Magog QC J1X 4V9",
    "addr:housenumber":"1650",
    "addr:postcode":"j1x 4v9",
    "addr:street":"Boul Industriel",
    "iso:country":"CA",
    "sg:address":"1650 Boul Industriel",
    "sg:city":"Magog",
    "sg:classifiers":[
        {
            "category":"Wholesale",
            "subcategory":"Chemicals & Plastics",
            "type":"Manufacturing & Wholesale Goods"
        }
    ],
    "sg:phone":"+1 819 847 2269",
    "sg:postcode":"J1X 4V9",
    "sg:province":"QC",
    "sg:tags":[
        "adhesive",
        "glue"
    ],
    "wof:name":"Adhesifs Adhpro Inc",
    "wof:placetype":"venue"
},
  "geometry": {"coordinates":[-72.126137,45.273506],"type":"Point"}
}