{
  "type": "Feature",
  "properties": {
    "addr:full":"Winnipeg MB R3T 5J3",
    "addr:postcode":"r3t 5j3",
    "iso:country":"CA",
    "sg:city":"Winnipeg",
    "sg:classifiers":[
        {
            "category":"Professional",
            "subcategory":"Business Services",
            "type":"Services"
        }
    ],
    "sg:phone":"+1 204 942 4408",
    "sg:postcode":"R3T 5J3",
    "sg:province":"MB",
    "sg:tags":[
        "arbitration"
    ],
    "wof:name":"Resolution Processes Inc",
    "wof:placetype":"venue"
},
  "geometry": {"coordinates":[-97.15376281739999,49.8096847534],"type":"Point"}
}