{
  "type": "Feature",
  "properties": {
    "addr:full":"43 Morrow Rd Barrie ON L4N 3V7",
    "addr:housenumber":"43",
    "addr:postcode":"l4n 3v7",
    "addr:street":"Morrow Rd",
    "iso:country":"CA",
    "sg:address":"43 Morrow Rd",
    "sg:city":"Barrie",
    "sg:classifiers":[
        {
            "category":"Wholesale",
            "subcategory":"Electrical",
            "type":"Manufacturing & Wholesale Goods"
        }
    ],
    "sg:phone":"+1 705 734 0304",
    "sg:postcode":"L4N 3V7",
    "sg:province":"ON",
    "sg:tags":[
        "parts",
        "electric",
        "motor"
    ],
    "wof:name":"Thistle Industries",
    "wof:placetype":"venue"
},
  "geometry": {"coordinates":[-79.70180499999999,44.361027],"type":"Point"}
}