{
  "type": "Feature",
  "properties": {
    "addr:full":"Garson ON P3L 1P5",
    "addr:postcode":"p3l 1p5",
    "iso:country":"CA",
    "sg:city":"Garson",
    "sg:classifiers":[
        {
            "category":"Health Services",
            "subcategory":"Doctor",
            "type":"Services"
        }
    ],
    "sg:phone":"+1 705 693 4200",
    "sg:postcode":"P3L 1P5",
    "sg:province":"ON",
    "sg:tags":[
        "physician",
        "surgeon"
    ],
    "wof:name":"Abdulhusein, Abbas MD",
    "wof:placetype":"venue"
},
  "geometry": {"coordinates":[-80.8753890991,46.5496826172],"type":"Point"}
}