{
  "type": "Feature",
  "properties": {
    "addr:full":"939 45 St SW Calgary AB T3C 2B9",
    "addr:housenumber":"45",
    "addr:postcode":"t3c 2b9",
    "addr:street":"939;St Sw",
    "iso:country":"CA",
    "sg:address":"939 45 St SW",
    "sg:city":"Calgary",
    "sg:classifiers":[
        {
            "category":"Education",
            "subcategory":"School",
            "type":"Public Place"
        }
    ],
    "sg:phone":"+1 403 777 7870",
    "sg:postcode":"T3C 2B9",
    "sg:province":"AB",
    "wof:name":"Vincent Massey Jr High Schl",
    "wof:placetype":"venue"
},
  "geometry": {"coordinates":[-114.152832,51.044563],"type":"Point"}
}