{
  "type": "Feature",
  "properties": {
    "addr:full":"8615 Ch Dalton Mont-Royal QC H4T 1V5",
    "addr:housenumber":"ch",
    "addr:postcode":"8615;h4t 1v5",
    "addr:street":"Dalton",
    "iso:country":"CA",
    "sg:address":"8615 Ch Dalton",
    "sg:city":"Mont-Royal",
    "sg:classifiers":[
        {
            "category":"Manufacturing",
            "subcategory":"Printing",
            "type":"Manufacturing & Wholesale Goods"
        }
    ],
    "sg:phone":"+1 514 343 9999",
    "sg:postcode":"H4T 1V5",
    "sg:province":"QC",
    "sg:tags":[
        "printer"
    ],
    "wof:name":"B B Color",
    "wof:placetype":"venue"
},
  "geometry": {"coordinates":[-73.68351699999999,45.48856],"type":"Point"}
}