{
  "type": "Feature",
  "properties": {
    "addr:full":"360 Albert St # 1110 Ottawa ON K1R 7X7",
    "addr:housenumber":"360",
    "addr:postcode":"k1r 7x7",
    "addr:street":"Albert St # 1110",
    "iso:country":"CA",
    "sg:address":"360 Albert St # 1110",
    "sg:city":"Ottawa",
    "sg:classifiers":[
        {
            "category":"Wholesale",
            "subcategory":"Drugs",
            "type":"Manufacturing & Wholesale Goods"
        }
    ],
    "sg:phone":"+1 613 569 6619",
    "sg:postcode":"K1R 7X7",
    "sg:province":"ON",
    "sg:tags":[
        "pharmaceutical",
        "product"
    ],
    "wof:name":"Glaxo Smith Kline Inc",
    "wof:placetype":"venue"
},
  "geometry": {"coordinates":[-75.70417,45.41811],"type":"Point"}
}