{
  "type": "Feature",
  "properties": {
    "iso:country":"CA",
    "sg:address":"163 Eric Cres",
    "sg:city":"South Porcupine",
    "sg:classifiers":[
        {
            "category":"Retail",
            "subcategory":"Animal Services",
            "type":"Services"
        }
    ],
    "sg:phone":"+1 705 235 4036",
    "sg:postcode":"P0N 1K0",
    "sg:province":"ON",
    "sg:tags":[
        "pet",
        "grooming",
        "washing"
    ],
    "wof:name":"Lora's Pet Grooming",
    "wof:placetype":"venue"
},
  "geometry": {"coordinates":[-81.160393,48.494278],"type":"Point"}
}