{
  "type": "Feature",
  "properties": {
    "addr:full":"4911 Boul Des Sources Pierrefonds QC H8Y 3C8",
    "addr:housenumber":"4911",
    "addr:postcode":"h8y 3c8",
    "addr:street":"Boul Des Sources",
    "iso:country":"CA",
    "sg:address":"4911 Boul Des Sources",
    "sg:city":"Pierrefonds",
    "sg:classifiers":[
        {
            "category":"Cinema",
            "subcategory":"Movie Rental",
            "type":"Entertainment"
        }
    ],
    "sg:phone":"+1 514 683 4100",
    "sg:postcode":"H8Y 3C8",
    "sg:province":"QC",
    "sg:tags":[
        "leasing",
        "video",
        "disc",
        "tape"
    ],
    "wof:name":"Blockbuster Video",
    "wof:placetype":"venue"
},
  "geometry": {"coordinates":[-73.8186035156,45.5058517456],"type":"Point"}
}