{
  "type": "Feature",
  "properties": {
    "iso:country":"CA",
    "sg:address":"18 Spencer St E",
    "sg:city":"Cobourg",
    "sg:classifiers":[
        {
            "category":"Professional",
            "subcategory":"Employment Agencies",
            "type":"Services"
        }
    ],
    "sg:phone":"+1 905 372 1901",
    "sg:postcode":"K9A 1C2",
    "sg:province":"ON",
    "sg:tags":[
        "training",
        "opportunity"
    ],
    "wof:name":"Watton Employment Svc",
    "wof:placetype":"venue"
},
  "geometry": {"coordinates":[-78.16709899999999,43.96563],"type":"Point"}
}