{
  "type": "Feature",
  "properties": {
    "addr:full":"5319 Boul Cleroux Laval QC H7T 2E5",
    "addr:housenumber":"5319",
    "addr:postcode":"h7t 2e5",
    "addr:street":"Boul Cleroux",
    "iso:country":"CA",
    "sg:address":"5319 Boul Cleroux",
    "sg:city":"Laval",
    "sg:classifiers":[
        {
            "category":"Manufacturing",
            "subcategory":"Paper Products",
            "type":"Manufacturing & Wholesale Goods"
        }
    ],
    "sg:phone":"+1 450 680 1365",
    "sg:postcode":"H7T 2E5",
    "sg:province":"QC",
    "sg:tags":[
        "packaging",
        "material"
    ],
    "wof:name":"Styropak Inc",
    "wof:placetype":"venue"
},
  "geometry": {"coordinates":[-73.800201,45.551079],"type":"Point"}
}