{
  "type": "Feature",
  "properties": {
    "addr:full":"7717 Wyandotte St E Windsor ON N8S 1S6",
    "addr:housenumber":"7717",
    "addr:postcode":"n8s 1s6",
    "addr:street":"Wyandotte St E",
    "iso:country":"CA",
    "sg:address":"7717 Wyandotte St E",
    "sg:city":"Windsor",
    "sg:classifiers":[
        {
            "category":"Health Services",
            "subcategory":"Doctor",
            "type":"Services"
        }
    ],
    "sg:phone":"+1 519 948 3961",
    "sg:postcode":"N8S 1S6",
    "sg:province":"ON",
    "sg:tags":[
        "physician",
        "surgeon"
    ],
    "wof:name":"Children's Health Care Network",
    "wof:placetype":"venue"
},
  "geometry": {"coordinates":[-82.946175,42.332935],"type":"Point"}
}