{
  "type": "Feature",
  "properties": {
    "addr:full":"401 Rue Thomas Lachute QC J8H 4M8",
    "addr:housenumber":"401",
    "addr:postcode":"j8h 4m8",
    "addr:street":"Rue Thomas",
    "iso:country":"CA",
    "sg:address":"401 Rue Thomas",
    "sg:city":"Lachute",
    "sg:classifiers":[
        {
            "category":"Shopping",
            "subcategory":"Pharmacy",
            "type":"Retail Goods"
        }
    ],
    "sg:phone":"+1 450 562 1604",
    "sg:postcode":"J8H 4M8",
    "sg:province":"QC",
    "wof:name":"Pharmacie Mario Caron & Assoc",
    "wof:placetype":"venue"
},
  "geometry": {"coordinates":[-74.34008799999999,45.658585],"type":"Point"}
}