{
  "type": "Feature",
  "properties": {
    "addr:full":"2515 Hemlock St Vancouver BC V6H 2V2",
    "addr:housenumber":"2515",
    "addr:postcode":"v6h 2v2",
    "addr:street":"Hemlock St",
    "iso:country":"CA",
    "sg:address":"2515 Hemlock St",
    "sg:city":"Vancouver",
    "sg:classifiers":[
        {
            "category":"Food & Beverages",
            "subcategory":"Groceries & Convenience Stores",
            "type":"Retail Goods"
        }
    ],
    "sg:phone":"+1 604 736 5115",
    "sg:postcode":"V6H 2V2",
    "sg:province":"BC",
    "sg:tags":[
        "grocer"
    ],
    "wof:name":"Mac's Convenience Stores Ltd",
    "wof:placetype":"venue"
},
  "geometry": {"coordinates":[-123.136314,49.263367],"type":"Point"}
}