{
  "type": "Feature",
  "properties": {
    "addr:full":"40 Ontario St Stratford ON N5A 3G8",
    "addr:housenumber":"40",
    "addr:postcode":"n5a 3g8",
    "addr:street":"Ontario St",
    "iso:country":"CA",
    "sg:address":"40 Ontario St",
    "sg:city":"Stratford",
    "sg:classifiers":[
        {
            "category":"Shopping",
            "subcategory":"Clothing, Apparel, & Fashions",
            "type":"Retail Goods"
        }
    ],
    "sg:phone":"+1 519 271 3240",
    "sg:postcode":"N5A 3G8",
    "sg:province":"ON",
    "sg:tags":[
        "item",
        "boutique"
    ],
    "wof:name":"Green Room",
    "wof:placetype":"venue"
},
  "geometry": {"coordinates":[-80.983208,43.371605],"type":"Point"}
}