{
  "type": "Feature",
  "properties": {
    "addr:full":"Neepawa MB R0J 1H0",
    "addr:postcode":"r0j 1h0",
    "iso:country":"CA",
    "sg:city":"Neepawa",
    "sg:classifiers":[
        {
            "category":"Home & Garden",
            "subcategory":"Hardware",
            "type":"Retail Goods"
        }
    ],
    "sg:phone":"+1 204 476 5858",
    "sg:postcode":"R0J 1H0",
    "sg:province":"MB",
    "wof:name":"Home Hardware Store",
    "wof:placetype":"venue"
},
  "geometry": {"coordinates":[-99.46654510499999,50.2304763794],"type":"Point"}
}