{
  "type": "Feature",
  "properties": {
    "addr:full":"1795 Versatile Dr Kamloops BC V1S 1C5",
    "addr:housenumber":"1795",
    "addr:postcode":"bc v1s 1c5",
    "addr:street":"Versatile Dr",
    "iso:country":"CA",
    "sg:address":"1795 Versatile Dr",
    "sg:city":"Kamloops",
    "sg:classifiers":[
        {
            "category":"Wholesale",
            "subcategory":"Auto Parts",
            "type":"Manufacturing & Wholesale Goods"
        }
    ],
    "sg:phone":"+1 250 372 1414",
    "sg:postcode":"V1S 1C5",
    "sg:province":"BC",
    "sg:tags":[
        "equipment",
        "truck"
    ],
    "wof:name":"K V Truck Parts",
    "wof:placetype":"venue"
},
  "geometry": {"coordinates":[-120.393822,50.657501],"type":"Point"}
}