{
  "type": "Feature",
  "properties": {
    "addr:full":"1165 Division St Cobourg ON K9A 4J9",
    "addr:housenumber":"1165",
    "addr:postcode":"k9a 4j9",
    "addr:street":"Division St",
    "iso:country":"CA",
    "sg:address":"1165 Division St",
    "sg:city":"Cobourg",
    "sg:classifiers":[
        {
            "category":"Government",
            "subcategory":"Police Station",
            "type":"Public Place"
        }
    ],
    "sg:phone":"+1 905 372 5421",
    "sg:postcode":"K9A 4J9",
    "sg:province":"ON",
    "sg:tags":[
        "department"
    ],
    "wof:name":"Ontario Provincial Police",
    "wof:placetype":"venue"
},
  "geometry": {"coordinates":[-78.17562103269999,43.9819717407],"type":"Point"}
}