{
  "type": "Feature",
  "properties": {
    "addr:full":"North Vancouver BC V7M 2J2",
    "addr:postcode":"v7m 2j2",
    "iso:country":"CA",
    "sg:city":"North Vancouver",
    "sg:classifiers":[
        {
            "category":"Manufacturing",
            "subcategory":"Food",
            "type":"Manufacturing & Wholesale Goods"
        }
    ],
    "sg:phone":"+1 604 987 8070",
    "sg:postcode":"V7M 2J2",
    "sg:province":"BC",
    "sg:tags":[
        "equipment",
        "wine",
        "winery",
        "supply"
    ],
    "wof:name":"My Wine Cellar Winemaking CO",
    "wof:placetype":"venue"
},
  "geometry": {"coordinates":[-123.07242599999999,49.322182],"type":"Point"}
}