{
  "type": "Feature",
  "properties": {
    "addr:full":"Winnipeg MB R3G 0R6",
    "addr:postcode":"r3g 0r6",
    "iso:country":"CA",
    "sg:city":"Winnipeg",
    "sg:classifiers":[
        {
            "category":"Restaurant",
            "type":"Food & Drink"
        }
    ],
    "sg:phone":"+1 204 987 5550",
    "sg:postcode":"R3G 0R6",
    "sg:province":"MB",
    "sg:tags":[
        "pizza"
    ],
    "wof:name":"Domino's Pizza",
    "wof:placetype":"venue"
},
  "geometry": {"coordinates":[-97.17501068120001,49.884437561],"type":"Point"}
}