{
  "type": "Feature",
  "properties": {
    "iso:country":"CA",
    "sg:address":"1963 Finch Ave W",
    "sg:city":"North York",
    "sg:classifiers":[
        {
            "category":"Banks & Credit Unions",
            "subcategory":"Bank",
            "type":"Services"
        }
    ],
    "sg:phone":"+1 416 749 2274",
    "sg:postcode":"M3N 2V3",
    "sg:province":"ON",
    "sg:tags":[
        "cashing",
        "check"
    ],
    "wof:name":"Money Mart",
    "wof:placetype":"venue"
},
  "geometry": {"coordinates":[-79.518776,43.757008],"type":"Point"}
}