{
  "type": "Feature",
  "properties": {
    "addr:full":"Quebec QC G1K 8Z8",
    "addr:postcode":"g1k 8z8",
    "iso:country":"CA",
    "sg:city":"Quebec",
    "sg:classifiers":[
        {
            "category":"Ferry",
            "type":"Transportation"
        }
    ],
    "sg:phone":"+1 418 692 1000",
    "sg:postcode":"G1K 8Z8",
    "sg:province":"QC",
    "sg:tags":[
        "company",
        "steamship"
    ],
    "wof:name":"Groupe Desgagnes Inc",
    "wof:placetype":"venue"
},
  "geometry": {"coordinates":[-71.2017822266,46.8121871948],"type":"Point"}
}