{
  "type": "Feature",
  "properties": {
    "addr:full":"226 132 Rte Pabos Mills QC G0C 2J0",
    "addr:housenumber":"132",
    "addr:postcode":"g0c 2j0",
    "addr:street":"Rte Pabos Mills",
    "iso:country":"CA",
    "sg:address":"226 132 Rte",
    "sg:city":"Pabos Mills",
    "sg:classifiers":[
        {
            "category":"Retail",
            "subcategory":"Auto Repair",
            "type":"Services"
        }
    ],
    "sg:phone":"+1 418 689 2487",
    "sg:postcode":"G0C 2J0",
    "sg:province":"QC",
    "sg:tags":[
        "repairing",
        "automobile"
    ],
    "wof:name":"Garage Laurier Gionest",
    "wof:placetype":"venue"
},
  "geometry": {"coordinates":[-64.7396240234,48.3374977112],"type":"Point"}
}