{
  "type": "Feature",
  "properties": {
    "addr:full":"Port Carling ON P0B 1J0",
    "addr:postcode":"p0b 1j0",
    "iso:country":"CA",
    "sg:city":"Port Carling",
    "sg:classifiers":[
        {
            "category":"Building & Trades",
            "subcategory":"Construction",
            "type":"Services"
        }
    ],
    "sg:phone":"+1 705 765 3675",
    "sg:postcode":"P0B 1J0",
    "sg:province":"ON",
    "sg:tags":[
        "general",
        "contractor"
    ],
    "wof:name":"Cottage Country Builders",
    "wof:placetype":"venue"
},
  "geometry": {"coordinates":[-80.1802520752,45.4786262512],"type":"Point"}
}