{
  "type": "Feature",
  "properties": {
    "addr:full":"Victoria BC V9A 3M4",
    "addr:postcode":"v9a 3m4",
    "iso:country":"CA",
    "sg:city":"Victoria",
    "sg:classifiers":[
        {
            "category":"Retail",
            "subcategory":"Self-service Laundry",
            "type":"Services"
        }
    ],
    "sg:phone":"+1 250 388 4434",
    "sg:postcode":"V9A 3M4",
    "sg:province":"BC",
    "sg:tags":[
        "cleaners"
    ],
    "wof:name":"Tumbles Laundromat",
    "wof:placetype":"venue"
},
  "geometry": {"coordinates":[-123.372276,48.427959],"type":"Point"}
}