{
  "type": "Feature",
  "properties": {
    "addr:full":"Williams Lake BC V2G 2P1",
    "addr:postcode":"bc v2g 2p1",
    "iso:country":"CA",
    "sg:city":"Williams Lake",
    "sg:classifiers":[
        {
            "category":"Shopping",
            "subcategory":"Luggage & Leather Goods",
            "type":"Retail Goods"
        }
    ],
    "sg:phone":"+1 250 392 6331",
    "sg:postcode":"V2G 2P1",
    "sg:province":"BC",
    "wof:name":"Wyatt Stock Saddles",
    "wof:placetype":"venue"
},
  "geometry": {"coordinates":[-122.139427185,52.1078643799],"type":"Point"}
}