{
  "type": "Feature",
  "properties": {
    "addr:full":"Pond Road Rocky Harbour NL A0K 4N0",
    "addr:postcode":"a0k 4n0",
    "addr:street":"Pond Road",
    "iso:country":"CA",
    "sg:address":"Pond Road",
    "sg:city":"Rocky Harbour",
    "sg:classifiers":[
        {
            "category":"Government",
            "subcategory":"Office",
            "type":"Public Place"
        }
    ],
    "sg:phone":"+1 709 458 2102",
    "sg:postcode":"A0K 4N0",
    "sg:province":"NL",
    "wof:name":"Hrcc Rocky Harbour",
    "wof:placetype":"venue"
},
  "geometry": {"coordinates":[-57.912781,49.593906],"type":"Point"}
}