{
  "type": "Feature",
  "properties": {
    "addr:full":"9229 58 Ave NW Edmonton AB T6E 0B7",
    "addr:housenumber":"9229",
    "addr:postcode":"t6e 0b7",
    "addr:street":"58 Ave Nw",
    "iso:country":"CA",
    "sg:address":"9229 58 Ave NW",
    "sg:city":"Edmonton",
    "sg:classifiers":[
        {
            "category":"Freight",
            "type":"Transportation"
        }
    ],
    "sg:phone":"+1 780 435 4110",
    "sg:postcode":"T6E 0B7",
    "sg:province":"AB",
    "sg:tags":[
        "trucking"
    ],
    "wof:name":"Dynamic Transport Ltd",
    "wof:placetype":"venue"
},
  "geometry": {"coordinates":[-113.46940600000001,53.493683],"type":"Point"}
}