{
  "type": "Feature",
  "properties": {
    "iso:country":"CA",
    "sg:city":"Courtenay",
    "sg:classifiers":[
        {
            "category":"Restaurant",
            "type":"Food & Drink"
        }
    ],
    "sg:phone":"+1 250 334 1644",
    "sg:postcode":"V9N 2L5",
    "sg:province":"BC",
    "sg:tags":[
        "pizza"
    ],
    "wof:name":"Cosmos Pizza & Fried Chicken",
    "wof:placetype":"venue"
},
  "geometry": {"coordinates":[-124.983680725,49.6772651672],"type":"Point"}
}