{
  "type": "Feature",
  "properties": {
    "addr:full":"164 Pleasant St Stellarton NS B0K 1S0",
    "addr:housenumber":"164",
    "addr:postcode":"b0k 1s0",
    "addr:street":"Pleasant St",
    "iso:country":"CA",
    "sg:address":"164 Pleasant St",
    "sg:city":"Stellarton",
    "sg:classifiers":[
        {
            "category":"Real Estate",
            "subcategory":"Surveying",
            "type":"Services"
        }
    ],
    "sg:phone":"+1 902 752 5617",
    "sg:postcode":"B0K 1S0",
    "sg:province":"NS",
    "sg:tags":[
        "surveyor"
    ],
    "wof:name":"Mac Callum, Albert",
    "wof:placetype":"venue"
},
  "geometry": {"coordinates":[-62.666954,45.560032],"type":"Point"}
}