{
  "type": "Feature",
  "properties": {
    "addr:full":"324 Packham Ave Saskatoon SK S7N 2T1",
    "addr:housenumber":"324",
    "addr:postcode":"s7n 2t1",
    "addr:street":"Packham Ave",
    "iso:country":"CA",
    "sg:address":"324 Packham Ave",
    "sg:city":"Saskatoon",
    "sg:classifiers":[
        {
            "category":"Building & Trades",
            "subcategory":"Construction",
            "type":"Services"
        }
    ],
    "sg:phone":"+1 306 653 4046",
    "sg:postcode":"S7N 2T1",
    "sg:province":"SK",
    "sg:tags":[
        "general",
        "contractor"
    ],
    "wof:name":"Con-Tech General Contractors",
    "wof:placetype":"venue"
},
  "geometry": {"coordinates":[-106.58824157700001,52.1298484802],"type":"Point"}
}