{
  "type": "Feature",
  "properties": {
    "addr:full":"6794 Rue Saint-Hubert Montreal QC H2S 2M6",
    "addr:housenumber":"6794",
    "addr:postcode":"h2s 2m6",
    "addr:street":"Rue Saint-Hubert",
    "iso:country":"CA",
    "sg:address":"6794 Rue Saint-Hubert",
    "sg:city":"Montreal",
    "sg:classifiers":[
        {
            "category":"Restaurant",
            "type":"Food & Drink"
        }
    ],
    "sg:phone":"+1 514 270 9102",
    "sg:postcode":"H2S 2M6",
    "sg:province":"QC",
    "wof:name":"Tropical",
    "wof:placetype":"venue"
},
  "geometry": {"coordinates":[-73.608002,45.538223],"type":"Point"}
}