{
  "type": "Feature",
  "properties": {
    "addr:full":"Calgary AB T3K 2A8",
    "addr:postcode":"t3k 2a8",
    "iso:country":"CA",
    "sg:city":"Calgary",
    "sg:classifiers":[
        {
            "category":"Building & Trades",
            "subcategory":"Construction",
            "type":"Services"
        }
    ],
    "sg:phone":"+1 403 283 2938",
    "sg:postcode":"T3K 2A8",
    "sg:province":"AB",
    "sg:tags":[
        "concrete",
        "restoration",
        "repair",
        "cleaning",
        "contractor"
    ],
    "wof:name":"Crackmaster Concrete Inc",
    "wof:placetype":"venue"
},
  "geometry": {"coordinates":[-114.07295227,51.1254081726],"type":"Point"}
}