{
  "type": "Feature",
  "properties": {
    "addr:full":"524 Sharpe St New Westminster BC V3M 4R2",
    "addr:housenumber":"524",
    "addr:postcode":"v3m 4r2",
    "addr:street":"Sharpe St",
    "iso:country":"CA",
    "sg:address":"524 Sharpe St",
    "sg:city":"New Westminster",
    "sg:classifiers":[
        {
            "category":"Building & Trades",
            "subcategory":"Construction",
            "type":"Services"
        }
    ],
    "sg:phone":"+1 604 540 7670",
    "sg:postcode":"V3M 4R2",
    "sg:province":"BC",
    "sg:tags":[
        "tile",
        "dealer"
    ],
    "wof:name":"Bridgewater Tile Ltd",
    "wof:placetype":"venue"
},
  "geometry": {"coordinates":[-122.933578,49.204212],"type":"Point"}
}