{
  "type": "Feature",
  "properties": {
    "addr:full":"Kemble ON N0H 1S0",
    "addr:postcode":"n0h 1s0",
    "iso:country":"CA",
    "sg:city":"Kemble",
    "sg:classifiers":[
        {
            "category":"Arena",
            "subcategory":"Sports Club",
            "type":"Entertainment"
        }
    ],
    "sg:phone":"+1 519 376 2856",
    "sg:postcode":"N0H 1S0",
    "sg:province":"ON",
    "sg:tags":[
        "athletic",
        "fields",
        "stadium"
    ],
    "wof:name":"Kemble Arena",
    "wof:placetype":"venue"
},
  "geometry": {"coordinates":[-80.9312515259,44.7153396606],"type":"Point"}
}