{
  "type": "Feature",
  "properties": {
    "addr:full":"193 Rue Fusey Cap-DE-LA-Madeleine QC G8T 2W1",
    "addr:housenumber":"193",
    "addr:postcode":"g8t 2w1",
    "addr:street":"Rue Fusey",
    "iso:country":"CA",
    "sg:address":"193 Rue Fusey",
    "sg:city":"Cap-DE-LA-Madeleine",
    "sg:classifiers":[
        {
            "category":"Restaurant",
            "type":"Food & Drink"
        }
    ],
    "sg:phone":"+1 819 373 8200",
    "sg:postcode":"G8T 2W1",
    "sg:province":"QC",
    "wof:name":"Mc Donald's",
    "wof:placetype":"venue"
},
  "geometry": {"coordinates":[-72.52413900000001,46.367599],"type":"Point"}
}