{
  "type": "Feature",
  "properties": {
    "addr:full":"97 Old Chicopee Dr Kitchener ON N2A 3R7",
    "addr:housenumber":"97",
    "addr:postcode":"n2a 3r7",
    "addr:street":"Old Chicopee Dr",
    "iso:country":"CA",
    "sg:address":"97 Old Chicopee Dr",
    "sg:city":"Kitchener",
    "sg:classifiers":[
        {
            "category":"Real Estate",
            "subcategory":"Real Estate Agent",
            "type":"Services"
        }
    ],
    "sg:phone":"+1 519 894 6320",
    "sg:postcode":"N2A 3R7",
    "sg:province":"ON",
    "sg:tags":[
        "management"
    ],
    "wof:name":"Orense Enterprises",
    "wof:placetype":"venue"
},
  "geometry": {"coordinates":[-80.43762207029999,43.4490203857],"type":"Point"}
}