{
  "type": "Feature",
  "properties": {
    "iso:country":"CA",
    "sg:address":"41 James Lewis Ave",
    "sg:city":"Stittsville",
    "sg:classifiers":[
        {
            "category":"Building & Trades",
            "subcategory":"Landscaping Services",
            "type":"Services"
        }
    ],
    "sg:phone":"+1 613 761 0467",
    "sg:postcode":"K2S 1K4",
    "sg:province":"ON",
    "sg:tags":[
        "landscape",
        "contractor"
    ],
    "wof:name":"Evergreen Landscape",
    "wof:placetype":"venue"
},
  "geometry": {"coordinates":[-75.907722,45.249729],"type":"Point"}
}