{
  "type": "Feature",
  "properties": {
    "addr:full":"Victoria BC V8V 3N7",
    "addr:postcode":"v8v 3n7",
    "iso:country":"CA",
    "sg:city":"Victoria",
    "sg:classifiers":[
        {
            "category":"Real Estate",
            "subcategory":"Architect",
            "type":"Services"
        }
    ],
    "sg:phone":"+1 250 360 9009",
    "sg:postcode":"V8V 3N7",
    "sg:province":"BC",
    "wof:name":"Jensen Group Architects Inc",
    "wof:placetype":"venue"
},
  "geometry": {"coordinates":[-123.355164,48.426266],"type":"Point"}
}