{
  "type": "Feature",
  "properties": {
    "addr:full":"10 Main St Roberts Arm NL A0J 1R0",
    "addr:housenumber":"10",
    "addr:postcode":"a0j 1r0",
    "addr:street":"Main St",
    "iso:country":"CA",
    "sg:address":"10 Main St",
    "sg:city":"Roberts Arm",
    "sg:classifiers":[
        {
            "category":"Restaurant",
            "type":"Food & Drink"
        }
    ],
    "sg:phone":"+1 709 652 3478",
    "sg:postcode":"A0J 1R0",
    "sg:province":"NL",
    "sg:tags":[
        "motel",
        "hotel"
    ],
    "wof:name":"Robert's Arm Motel",
    "wof:placetype":"venue"
},
  "geometry": {"coordinates":[-57.9447822571,48.9540901184],"type":"Point"}
}