{
  "type": "Feature",
  "properties": {
    "addr:full":"40 Rue Albert-Ferland Cheneville QC J0V 1E0",
    "addr:housenumber":"40",
    "addr:postcode":"j0v 1e0",
    "addr:street":"Rue Albert-Ferland Cheneville",
    "iso:country":"CA",
    "sg:address":"40 Rue Albert-Ferland",
    "sg:city":"Cheneville",
    "sg:classifiers":[
        {
            "category":"Restaurant",
            "type":"Food & Drink"
        }
    ],
    "sg:phone":"+1 819 428 3805",
    "sg:postcode":"J0V 1E0",
    "sg:province":"QC",
    "wof:name":"Restaurant Du Village",
    "wof:placetype":"venue"
},
  "geometry": {"coordinates":[-75.06385,45.88649],"type":"Point"}
}