{
  "type": "Feature",
  "properties": {
    "iso:country":"CA",
    "sg:address":"486 Weber St N",
    "sg:city":"Waterloo",
    "sg:classifiers":[
        {
            "category":"Manufacturing",
            "subcategory":"Metals",
            "type":"Manufacturing & Wholesale Goods"
        }
    ],
    "sg:phone":"+1 519 884 2590",
    "sg:postcode":"N2L 4E7",
    "sg:province":"ON",
    "sg:tags":[
        "machine",
        "screw",
        "product"
    ],
    "wof:name":"Wheeler Metal Products",
    "wof:placetype":"venue"
},
  "geometry": {"coordinates":[-80.5345535278,43.4904022217],"type":"Point"}
}