{
  "type": "Feature",
  "properties": {
    "addr:full":"Niagara Falls ON L2G 5X7",
    "addr:postcode":"l2g 5x7",
    "iso:country":"CA",
    "sg:city":"Niagara Falls",
    "sg:classifiers":[
        {
            "category":"Health Services",
            "subcategory":"Doctor",
            "type":"Services"
        }
    ],
    "sg:phone":"+1 905 354 2323",
    "sg:postcode":"L2G 5X7",
    "sg:province":"ON",
    "sg:tags":[
        "physician",
        "surgeon"
    ],
    "wof:name":"Mac Tavish, A MD",
    "wof:placetype":"venue"
},
  "geometry": {"coordinates":[-79.090805,43.095966],"type":"Point"}
}