{
  "type": "Feature",
  "properties": {
    "addr:full":"Kelowna BC V1X 7R8",
    "addr:postcode":"v1x 7r8",
    "iso:country":"CA",
    "sg:city":"Kelowna",
    "sg:classifiers":[
        {
            "category":"Wholesale",
            "subcategory":"Groceries",
            "type":"Manufacturing & Wholesale Goods"
        }
    ],
    "sg:phone":"+1 250 765 0300",
    "sg:postcode":"V1X 7R8",
    "sg:province":"BC",
    "sg:tags":[
        "food",
        "product"
    ],
    "wof:name":"Direct Plus Food Group",
    "wof:placetype":"venue"
},
  "geometry": {"coordinates":[-119.389976502,49.9238815308],"type":"Point"}
}