{
  "type": "Feature",
  "properties": {
    "addr:full":"10655 Southport Rd SW # 790 Calgary AB T2W 4Y1",
    "addr:housenumber":"10655",
    "addr:postcode":"t2w 4y1",
    "addr:street":"Southport Rd Sw # 790",
    "iso:country":"CA",
    "sg:address":"10655 Southport Rd SW # 790",
    "sg:city":"Calgary",
    "sg:classifiers":[
        {
            "category":"Banks & Credit Unions",
            "subcategory":"Bank",
            "type":"Services"
        }
    ],
    "sg:phone":"+1 403 236 4445",
    "sg:postcode":"T2W 4Y1",
    "sg:province":"AB",
    "sg:tags":[
        "financing"
    ],
    "wof:name":"Paccar Financial Svc Ltd",
    "wof:placetype":"venue"
},
  "geometry": {"coordinates":[-114.072631836,50.9584274292],"type":"Point"}
}