{
  "type": "Feature",
  "properties": {
    "addr:full":"835 Vickers St N Thunder Bay ON P7C 4B9",
    "addr:housenumber":"835",
    "addr:postcode":"p7c 4b9",
    "addr:street":"Vickers St N",
    "iso:country":"CA",
    "sg:address":"835 Vickers St N",
    "sg:city":"Thunder Bay",
    "sg:classifiers":[
        {
            "category":"Manufacturing",
            "subcategory":"Metals",
            "type":"Manufacturing & Wholesale Goods"
        }
    ],
    "sg:phone":"+1 807 622 0658",
    "sg:postcode":"P7C 4B9",
    "sg:province":"ON",
    "sg:tags":[
        "steel"
    ],
    "wof:name":"Lakehead Ironworks Inc",
    "wof:placetype":"venue"
},
  "geometry": {"coordinates":[-89.251396,48.397327],"type":"Point"}
}