{
  "type": "Feature",
  "properties": {
    "iso:country":"CA",
    "sg:city":"Burnaby",
    "sg:classifiers":[
        {
            "category":"Health Services",
            "subcategory":"Doctor",
            "type":"Services"
        }
    ],
    "sg:phone":"+1 604 421 2555",
    "sg:postcode":"V3J 1N4",
    "sg:province":"BC",
    "sg:tags":[
        "physician",
        "clinic",
        "surgeon"
    ],
    "wof:name":"Lougheed Medical Clinic Ltd",
    "wof:placetype":"venue"
},
  "geometry": {"coordinates":[-122.895767,49.249142],"type":"Point"}
}