{
  "type": "Feature",
  "properties": {
    "addr:full":"180 170 Rte L'Anse-Saint-Jean QC G0V 1J0",
    "addr:housenumber":"170",
    "addr:postcode":"g0v 1j0",
    "addr:street":"Rte L'Anse-Saint-Jean",
    "iso:country":"CA",
    "sg:address":"180 170 Rte",
    "sg:city":"L'Anse-Saint-Jean",
    "sg:classifiers":[
        {
            "category":"Health Services",
            "subcategory":"Doctor",
            "type":"Services"
        }
    ],
    "sg:phone":"+1 418 272 2114",
    "sg:postcode":"G0V 1J0",
    "sg:province":"QC",
    "sg:tags":[
        "dentist"
    ],
    "wof:name":"Clinique Dentaire Anse St-Jean",
    "wof:placetype":"venue"
},
  "geometry": {"coordinates":[-70.236031,48.197517],"type":"Point"}
}