{
  "type": "Feature",
  "properties": {
    "addr:full":"North Hatley QC J0B 2C0",
    "addr:postcode":"j0b 2c0",
    "iso:country":"CA",
    "sg:city":"North Hatley",
    "sg:classifiers":[
        {
            "category":"Recreation",
            "type":"Entertainment"
        }
    ],
    "sg:phone":"+1 819 842 4491",
    "sg:postcode":"J0B 2C0",
    "sg:province":"QC",
    "sg:tags":[
        "center",
        "amusement"
    ],
    "wof:name":"North Hatley Recreation",
    "wof:placetype":"venue"
},
  "geometry": {"coordinates":[-71.9779663086,45.2686424255],"type":"Point"}
}