{
  "type": "Feature",
  "properties": {
    "addr:full":"Abbotsford BC V2T 2X8",
    "addr:postcode":"v2t 2x8",
    "iso:country":"CA",
    "sg:city":"Abbotsford",
    "sg:classifiers":[
        {
            "category":"Personal",
            "subcategory":"Beauty Salon",
            "type":"Services"
        }
    ],
    "sg:phone":"+1 604 854 3380",
    "sg:postcode":"V2T 2X8",
    "sg:province":"BC",
    "sg:tags":[
        "consultant",
        "health"
    ],
    "wof:name":"Arvi's Hair Design",
    "wof:placetype":"venue"
},
  "geometry": {"coordinates":[-122.336868286,49.0468597412],"type":"Point"}
}