{
  "type": "Feature",
  "properties": {
    "addr:full":"110 8 St S Lethbridge AB T1J 2J3",
    "addr:housenumber":"110 8",
    "addr:postcode":"t1j 2j3",
    "iso:country":"CA",
    "sg:address":"110 8 St S",
    "sg:city":"Lethbridge",
    "sg:classifiers":[
        {
            "category":"Personal",
            "subcategory":"Beauty Salon",
            "type":"Services"
        }
    ],
    "sg:phone":"+1 403 320 4444",
    "sg:postcode":"T1J 2J3",
    "sg:province":"AB",
    "wof:name":"Salon Quattro Inc",
    "wof:placetype":"venue"
},
  "geometry": {"coordinates":[-112.835929871,49.6975364685],"type":"Point"}
}