{
  "type": "Feature",
  "properties": {
    "addr:full":"Niagara Falls ON L2E 4C6",
    "addr:postcode":"l2e 4c6",
    "iso:country":"CA",
    "sg:city":"Niagara Falls",
    "sg:classifiers":[
        {
            "category":"Shopping",
            "subcategory":"Jewelry",
            "type":"Retail Goods"
        }
    ],
    "sg:phone":"+1 905 374 6991",
    "sg:postcode":"L2E 4C6",
    "sg:province":"ON",
    "sg:tags":[
        "jeweler"
    ],
    "wof:name":"Olindo Jewellers",
    "wof:placetype":"venue"
},
  "geometry": {"coordinates":[-79.395248,43.191383],"type":"Point"}
}