{
  "type": "Feature",
  "properties": {
    "iso:country":"CA",
    "sg:city":"Vancouver",
    "sg:classifiers":[
        {
            "category":"Professional",
            "subcategory":"Computer Services",
            "type":"Services"
        }
    ],
    "sg:phone":"+1 604 638 8900",
    "sg:postcode":"V6B 2M9",
    "sg:province":"BC",
    "sg:tags":[
        "internet"
    ],
    "wof:name":"Projux Online Inc",
    "wof:placetype":"venue"
},
  "geometry": {"coordinates":[-123.108696,49.284122],"type":"Point"}
}