{
  "type": "Feature",
  "properties": {
    "addr:full":"2520 Binder Cres Oldcastle ON N0R 1L0",
    "addr:housenumber":"2520",
    "addr:postcode":"n0r 1l0",
    "addr:street":"Binder Cres",
    "iso:country":"CA",
    "sg:address":"2520 Binder Cres",
    "sg:city":"Oldcastle",
    "sg:classifiers":[
        {
            "category":"Manufacturing",
            "subcategory":"Tools & Machinery",
            "type":"Manufacturing & Wholesale Goods"
        }
    ],
    "sg:phone":"+1 519 737 1331",
    "sg:postcode":"N0R 1L0",
    "sg:province":"ON",
    "sg:tags":[
        "die",
        "maker"
    ],
    "wof:name":"Ellis Tool & Die",
    "wof:placetype":"venue"
},
  "geometry": {"coordinates":[-82.962051,42.236576],"type":"Point"}
}