{
  "type": "Feature",
  "properties": {
    "iso:country":"CA",
    "sg:city":"Yellowknife",
    "sg:classifiers":[
        {
            "category":"Manufacturing",
            "subcategory":"Signs",
            "type":"Manufacturing & Wholesale Goods"
        }
    ],
    "sg:phone":"+1 867 873 8161",
    "sg:postcode":"X1A 3S3",
    "sg:province":"NT",
    "sg:tags":[
        "advertising"
    ],
    "wof:name":"Jofran Advertising Specialties",
    "wof:placetype":"venue"
},
  "geometry": {"coordinates":[-114.371704102,62.4563980103],"type":"Point"}
}