{
  "type": "Feature",
  "properties": {
    "addr:full":"Winnipeg MB R2K 2T8",
    "addr:postcode":"r2k 2t8",
    "iso:country":"CA",
    "sg:city":"Winnipeg",
    "sg:classifiers":[
        {
            "category":"Building & Trades",
            "subcategory":"Landscaping Services",
            "type":"Services"
        }
    ],
    "sg:phone":"+1 204 663 1200",
    "sg:postcode":"R2K 2T8",
    "sg:province":"MB",
    "sg:tags":[
        "control",
        "lawn",
        "weed",
        "maintenance",
        "grounds"
    ],
    "wof:name":"Eco Green For Lawns & Trees",
    "wof:placetype":"venue"
},
  "geometry": {"coordinates":[-97.0948791504,49.917804718],"type":"Point"}
}