{
  "type": "Feature",
  "properties": {
    "addr:full":"100 Fifth Ave Orangeville ON L9W 5E8",
    "addr:housenumber":"100",
    "addr:postcode":"l9w 5e8",
    "addr:street":"Fifth Ave",
    "iso:country":"CA",
    "sg:address":"100 Fifth Ave",
    "sg:city":"Orangeville",
    "sg:classifiers":[
        {
            "category":"Food & Beverages",
            "subcategory":"Bakery",
            "type":"Retail Goods"
        }
    ],
    "sg:phone":"+1 519 941 4494",
    "sg:postcode":"L9W 5E8",
    "sg:province":"ON",
    "sg:tags":[
        "doughnut"
    ],
    "wof:name":"Tim Hortons",
    "wof:placetype":"venue"
},
  "geometry": {"coordinates":[-80.094498,43.928902],"type":"Point"}
}