{
  "type": "Feature",
  "properties": {
    "addr:full":"1230 Rue Saint-Denis Montreal QC H2X 3J6",
    "addr:housenumber":"1230",
    "addr:postcode":"h2x 3j6",
    "addr:street":"Rue Saint-Denis",
    "iso:country":"CA",
    "sg:address":"1230 Rue Saint-Denis",
    "sg:city":"Montreal",
    "sg:classifiers":[
        {
            "category":"Personal",
            "subcategory":"Beauty Salon",
            "type":"Services"
        }
    ],
    "sg:phone":"+1 514 288 0127",
    "sg:postcode":"H2X 3J6",
    "sg:province":"QC",
    "sg:tags":[
        "barber"
    ],
    "wof:name":"Coiffure Style Toi",
    "wof:placetype":"venue"
},
  "geometry": {"coordinates":[-73.5596084595,45.5131835938],"type":"Point"}
}