{
  "type": "Feature",
  "properties": {
    "addr:full":"1401 Mill Rd Mackenzie BC V0J 2C0",
    "addr:housenumber":"1401",
    "addr:postcode":"v0j 2c0",
    "addr:street":"Mill Rd",
    "iso:country":"CA",
    "sg:address":"1401 Mill Rd",
    "sg:city":"Mackenzie",
    "sg:classifiers":[
        {
            "category":"Freight",
            "type":"Transportation"
        }
    ],
    "sg:phone":"+1 250 997 3355",
    "sg:postcode":"V0J 2C0",
    "sg:province":"BC",
    "sg:tags":[
        "trucking"
    ],
    "wof:name":"Lomak Bulk Carriers Corp",
    "wof:placetype":"venue"
},
  "geometry": {"coordinates":[-123.12597656200001,55.3116531372],"type":"Point"}
}