{
  "type": "Feature",
  "properties": {
    "addr:full":"PO Box 2 Pangnirtung NU X0A 0R0",
    "addr:housenumber":"po;2",
    "addr:postcode":"x0a 0r0",
    "addr:street":"Box",
    "iso:country":"CA",
    "sg:address":"PO Box 2",
    "sg:city":"Pangnirtung",
    "sg:classifiers":[
        {
            "category":"Organizations",
            "subcategory":"Professional Association",
            "type":"Services"
        }
    ],
    "sg:phone":"+1 867 473 8751",
    "sg:postcode":"X0A 0R0",
    "sg:province":"NU",
    "wof:name":"Pangnirtung Hunters & Trappers",
    "wof:placetype":"venue"
},
  "geometry": {"coordinates":[-65.69454193120001,66.1486816406],"type":"Point"}
}