{
  "type": "Feature",
  "properties": {
    "addr:full":"977 Boul Saint-Luc Saint-Luc QC J2W 2G6",
    "addr:housenumber":"977",
    "addr:postcode":"j2w 2g6",
    "addr:street":"Boul Saint-Luc",
    "iso:country":"CA",
    "sg:address":"977 Boul Saint-Luc",
    "sg:city":"Saint-Luc",
    "sg:classifiers":[
        {
            "category":"Travel",
            "subcategory":"Campground",
            "type":"Entertainment"
        }
    ],
    "sg:phone":"+1 450 348 9383",
    "sg:postcode":"J2W 2G6",
    "sg:province":"QC",
    "wof:name":"Camping Joie DE Vivre",
    "wof:placetype":"venue"
},
  "geometry": {"coordinates":[-73.35787999999999,45.376034],"type":"Point"}
}