{
  "type": "Feature",
  "properties": {
    "addr:full":"11 Cobb Crt Nepean ON K2J 2K2",
    "addr:housenumber":"11",
    "addr:postcode":"k2j 2k2",
    "addr:street":"Cobb Crt",
    "iso:country":"CA",
    "sg:address":"11 Cobb Crt",
    "sg:city":"Nepean",
    "sg:classifiers":[
        {
            "category":"Wholesale",
            "subcategory":"Durable Goods & Equipment",
            "type":"Manufacturing & Wholesale Goods"
        }
    ],
    "sg:phone":"+1 613 825 1544",
    "sg:postcode":"K2J 2K2",
    "sg:province":"ON",
    "sg:tags":[
        "representative",
        "manufacturer"
    ],
    "wof:name":"J H Mc Cusker Assoc",
    "wof:placetype":"venue"
},
  "geometry": {"coordinates":[-75.745766,45.289738],"type":"Point"}
}