{
  "type": "Feature",
  "properties": {
    "addr:full":"4863 Boul Saint-Charles Pierrefonds QC H9H 3E4",
    "addr:housenumber":"4863",
    "addr:postcode":"h9h 3e4",
    "addr:street":"Boul Saint-Charles",
    "iso:country":"CA",
    "sg:address":"4863 Boul Saint-Charles",
    "sg:city":"Pierrefonds",
    "sg:classifiers":[
        {
            "category":"Personal",
            "subcategory":"Beauty Salon",
            "type":"Services"
        }
    ],
    "sg:phone":"+1 514 620 7415",
    "sg:postcode":"H9H 3E4",
    "sg:province":"QC",
    "wof:name":"Zig-Zag Coiffure",
    "wof:placetype":"venue"
},
  "geometry": {"coordinates":[-73.8734512329,45.4663276672],"type":"Point"}
}