{
  "type": "Feature",
  "properties": {
    "addr:full":"25 Morrow Ave #100 Toronto ON M6R 2H9",
    "addr:housenumber":"25",
    "addr:postcode":"m6r 2h9",
    "addr:street":"Morrow Ave # 100",
    "iso:country":"CA",
    "sg:address":"25 Morrow Ave #100",
    "sg:city":"Toronto",
    "sg:classifiers":[
        {
            "category":"Professional",
            "subcategory":"Lawyer & Legal Services",
            "type":"Services"
        }
    ],
    "sg:phone":"+1 416 533 1025",
    "sg:postcode":"M6R 2H9",
    "sg:province":"ON",
    "sg:tags":[
        "attorney"
    ],
    "wof:name":"Halkiw, William",
    "wof:placetype":"venue"
},
  "geometry": {"coordinates":[-79.446877,43.652622],"type":"Point"}
}