{
  "type": "Feature",
  "properties": {
    "iso:country":"CA",
    "sg:address":"677 Hwy 3A",
    "sg:city":"Nelson",
    "sg:classifiers":[
        {
            "category":"Retail",
            "subcategory":"Auto Repair",
            "type":"Services"
        }
    ],
    "sg:phone":"+1 250 354 4929",
    "sg:postcode":"V1L 6M6",
    "sg:province":"BC",
    "sg:tags":[
        "repairing",
        "automobile"
    ],
    "wof:name":"Able Transmission",
    "wof:placetype":"venue"
},
  "geometry": {"coordinates":[-117.292503357,49.4938468933],"type":"Point"}
}