{
  "type": "Feature",
  "properties": {
    "iso:country":"CA",
    "sg:city":"Vancouver",
    "sg:classifiers":[
        {
            "category":"Health Services",
            "subcategory":"Doctor",
            "type":"Services"
        }
    ],
    "sg:phone":"+1 604 875 9996",
    "sg:postcode":"V5Z 3N8",
    "sg:province":"BC",
    "sg:tags":[
        "physician",
        "surgeon"
    ],
    "wof:name":"Maberley, A L MD",
    "wof:placetype":"venue"
},
  "geometry": {"coordinates":[-123.122062683,49.2630653381],"type":"Point"}
}