{
  "type": "Feature",
  "properties": {
    "addr:full":"Surrey BC V3T 5T3",
    "addr:postcode":"v3t 5t3",
    "iso:country":"CA",
    "sg:city":"Surrey",
    "sg:classifiers":[
        {
            "category":"Banks & Credit Unions",
            "subcategory":"Investment Brokerage",
            "type":"Services"
        }
    ],
    "sg:phone":"+1 604 930 9995",
    "sg:postcode":"V3T 5T3",
    "sg:province":"BC",
    "sg:tags":[
        "consultant",
        "planning",
        "financial"
    ],
    "wof:name":"Smcc Management Inc",
    "wof:placetype":"venue"
},
  "geometry": {"coordinates":[-122.834121704,49.198841095],"type":"Point"}
}