{
  "type": "Feature",
  "properties": {
    "addr:full":"51 Front St S Thorold ON L2V 1W8",
    "addr:housenumber":"51",
    "addr:postcode":"l2v 1w8",
    "addr:street":"Front St S",
    "iso:country":"CA",
    "sg:address":"51 Front St S",
    "sg:city":"Thorold",
    "sg:classifiers":[
        {
            "category":"Retail",
            "subcategory":"Animal Services",
            "type":"Services"
        }
    ],
    "sg:phone":"+1 905 680 2389",
    "sg:postcode":"L2V 1W8",
    "sg:province":"ON",
    "sg:tags":[
        "pet",
        "grooming",
        "washing"
    ],
    "wof:name":"Lynn's Grooming Salon",
    "wof:placetype":"venue"
},
  "geometry": {"coordinates":[-79.200706,43.123425],"type":"Point"}
}