{
  "type": "Feature",
  "properties": {
    "addr:full":"Edmonton AB T5B 1G2",
    "addr:postcode":"t5b 1g2",
    "iso:country":"CA",
    "sg:city":"Edmonton",
    "sg:classifiers":[
        {
            "category":"Wholesale",
            "subcategory":"Machinery & Supplies",
            "type":"Manufacturing & Wholesale Goods"
        }
    ],
    "sg:phone":"+1 780 413 1740",
    "sg:postcode":"T5B 1G2",
    "sg:province":"AB",
    "sg:tags":[
        "contractor"
    ],
    "wof:name":"Yellow Tractor Works Inc",
    "wof:placetype":"venue"
},
  "geometry": {"coordinates":[-113.479843,53.581619],"type":"Point"}
}