{
  "type": "Feature",
  "properties": {
    "addr:full":"229 Adelaide St N London ON N6B 3H3",
    "addr:housenumber":"229",
    "addr:postcode":"n6b 3h3",
    "addr:street":"Adelaide St N",
    "iso:country":"CA",
    "sg:address":"229 Adelaide St N",
    "sg:city":"London",
    "sg:classifiers":[
        {
            "category":"Wholesale",
            "subcategory":"Electrical",
            "type":"Manufacturing & Wholesale Goods"
        }
    ],
    "sg:phone":"+1 519 673 1800",
    "sg:postcode":"N6B 3H3",
    "sg:province":"ON",
    "sg:tags":[
        "equipment",
        "electric",
        "supply"
    ],
    "wof:name":"Guillevin International Inc",
    "wof:placetype":"venue"
},
  "geometry": {"coordinates":[-81.22919464109999,42.9829216003],"type":"Point"}
}