{
  "type": "Feature",
  "properties": {
    "addr:full":"1941 Route 450 Lagaceville NB E9G 2M6",
    "addr:housenumber":"1941",
    "addr:postcode":"e9g 2m6",
    "addr:street":"Route 450",
    "iso:country":"CA",
    "sg:address":"1941 Route 450",
    "sg:city":"Lagaceville",
    "sg:classifiers":[
        {
            "category":"Organizations",
            "subcategory":"Religious Organization",
            "type":"Services"
        }
    ],
    "sg:phone":"+1 506 776 3279",
    "sg:postcode":"E9G 2M6",
    "sg:province":"NB",
    "wof:name":"Filles DE Marie Auxillatrice",
    "wof:placetype":"venue"
},
  "geometry": {"coordinates":[-65.1796417236,47.2290534973],"type":"Point"}
}