{
  "type": "Feature",
  "properties": {
    "iso:country":"CA",
    "sg:address":"1100 Rue Sherbrooke O",
    "sg:city":"Montreal",
    "sg:classifiers":[
        {
            "category":"Banks & Credit Unions",
            "subcategory":"Bank",
            "type":"Services"
        }
    ],
    "sg:phone":"+1 514 874 8730",
    "sg:postcode":"H3A 1G7",
    "sg:province":"QC",
    "wof:name":"Banque Royale",
    "wof:placetype":"venue"
},
  "geometry": {"coordinates":[-73.565491,45.521454],"type":"Point"}
}