{
  "type": "Feature",
  "properties": {
    "addr:full":"Rosetown SK S0L 2V0",
    "addr:postcode":"s0l 2v0",
    "addr:street":"Rosetown",
    "iso:country":"CA",
    "sg:city":"Rosetown",
    "sg:classifiers":[
        {
            "category":"Farming",
            "subcategory":"Farm & Veterinary Services",
            "type":"Manufacturing & Wholesale Goods"
        }
    ],
    "sg:phone":"+1 306 882 3830",
    "sg:postcode":"S0L 2V0",
    "sg:province":"SK",
    "sg:tags":[
        "aerial",
        "applicator"
    ],
    "wof:name":"West Central Air",
    "wof:placetype":"venue"
},
  "geometry": {"coordinates":[-107.986946106,51.5502853394],"type":"Point"}
}