{
  "type": "Feature",
  "properties": {
    "addr:full":"Meaford ON N4L 1Y1",
    "addr:postcode":"n4l 1y1",
    "iso:country":"CA",
    "sg:city":"Meaford",
    "sg:classifiers":[
        {
            "category":"Restaurant",
            "type":"Food & Drink"
        }
    ],
    "sg:phone":"+1 519 538 5969",
    "sg:postcode":"N4L 1Y1",
    "sg:province":"ON",
    "wof:name":"Dixie Lee Fried Chicken",
    "wof:placetype":"venue"
},
  "geometry": {"coordinates":[-80.592651,44.606834],"type":"Point"}
}