{
  "type": "Feature",
  "properties": {
    "addr:full":"12 Churchill St Chatham ON N7L 3T1",
    "addr:housenumber":"12",
    "addr:postcode":"n7l 3t1",
    "addr:street":"Churchill St",
    "iso:country":"CA",
    "sg:address":"12 Churchill St",
    "sg:city":"Chatham",
    "sg:classifiers":[
        {
            "category":"Home & Garden",
            "subcategory":"Building Materials",
            "type":"Retail Goods"
        }
    ],
    "sg:phone":"+1 519 436 1333",
    "sg:postcode":"N7L 3T1",
    "sg:province":"ON",
    "sg:tags":[
        "wallpaper"
    ],
    "wof:name":"Wallpaper Station",
    "wof:placetype":"venue"
},
  "geometry": {"coordinates":[-82.20233899999999,42.402752],"type":"Point"}
}