{
  "type": "Feature",
  "properties": {
    "addr:full":"1207 Rue Rachel E Montreal QC H2J 2J8",
    "addr:housenumber":"1207",
    "addr:postcode":"h2j 2j8",
    "addr:street":"Rue Rachel E",
    "iso:country":"CA",
    "sg:address":"1207 Rue Rachel E",
    "sg:city":"Montreal",
    "sg:classifiers":[
        {
            "category":"Health Services",
            "subcategory":"Doctor",
            "type":"Services"
        }
    ],
    "sg:phone":"+1 450 464 4999",
    "sg:postcode":"H2J 2J8",
    "sg:province":"QC",
    "sg:tags":[
        "physician",
        "surgeon"
    ],
    "wof:name":"Ouellette, Catherine MD",
    "wof:placetype":"venue"
},
  "geometry": {"coordinates":[-73.573448,45.526596],"type":"Point"}
}