{
  "type": "Feature",
  "properties": {
    "addr:full":"93 Front St E Toronto ON M5E 1C3",
    "addr:housenumber":"93",
    "addr:postcode":"m5e 1c3",
    "addr:street":"Front St E",
    "iso:country":"CA",
    "sg:address":"93 Front St E",
    "sg:city":"Toronto",
    "sg:classifiers":[
        {
            "category":"Food & Beverages",
            "subcategory":"Dairy",
            "type":"Retail Goods"
        }
    ],
    "sg:phone":"+1 416 368 2415",
    "sg:postcode":"M5E 1C3",
    "sg:province":"ON",
    "sg:tags":[
        "cheese"
    ],
    "wof:name":"Alex Farm Products",
    "wof:placetype":"venue"
},
  "geometry": {"coordinates":[-79.3718338013,43.6491127014],"type":"Point"}
}