{
  "type": "Feature",
  "properties": {
    "addr:full":"109 Maple St Port Carling ON P0B 1J0",
    "addr:housenumber":"109",
    "addr:postcode":"p0b 1j0",
    "addr:street":"Maple St",
    "iso:country":"CA",
    "sg:address":"109 Maple St",
    "sg:city":"Port Carling",
    "sg:classifiers":[
        {
            "category":"Banks & Credit Unions",
            "subcategory":"Bank",
            "type":"Services"
        }
    ],
    "sg:phone":"+1 705 765 6881",
    "sg:postcode":"P0B 1J0",
    "sg:province":"ON",
    "wof:name":"Scotiabank",
    "wof:placetype":"venue"
},
  "geometry": {"coordinates":[-79.577721,45.120773],"type":"Point"}
}