{
  "type": "Feature",
  "properties": {
    "iso:country":"CA",
    "sg:address":"12 Tanbark Cres",
    "sg:city":"North York",
    "sg:classifiers":[
        {
            "category":"Professional",
            "subcategory":"Advertising",
            "type":"Services"
        }
    ],
    "sg:phone":"+1 416 449 0878",
    "sg:postcode":"M3B 1N6",
    "sg:province":"ON",
    "wof:name":"Wmb Publishing Inc",
    "wof:placetype":"venue"
},
  "geometry": {"coordinates":[-79.365211,43.743832],"type":"Point"}
}