{
  "type": "Feature",
  "properties": {
    "addr:full":"Burnaby BC V5E 1E1",
    "addr:postcode":"v5e 1e1",
    "iso:country":"CA",
    "sg:city":"Burnaby",
    "sg:classifiers":[
        {
            "category":"Restaurant",
            "type":"Food & Drink"
        }
    ],
    "sg:phone":"+1 604 438 0186",
    "sg:postcode":"V5E 1E1",
    "sg:province":"BC",
    "sg:tags":[
        "shop",
        "coffee"
    ],
    "wof:name":"Estea Beverage Club",
    "wof:placetype":"venue"
},
  "geometry": {"coordinates":[-122.970367,49.21973],"type":"Point"}
}