{
  "type": "Feature",
  "properties": {
    "addr:full":"Wakefield QC J0X 3G0",
    "addr:postcode":"j0x 3g0",
    "iso:country":"CA",
    "sg:city":"Wakefield",
    "sg:classifiers":[
        {
            "category":"Government",
            "subcategory":"Office",
            "type":"Public Place"
        }
    ],
    "sg:phone":"+1 819 456 2161",
    "sg:postcode":"J0X 3G0",
    "sg:province":"QC",
    "sg:tags":[
        "village"
    ],
    "wof:name":"LA Peche Municipality",
    "wof:placetype":"venue"
},
  "geometry": {"coordinates":[-75.9288101196,45.6344909668],"type":"Point"}
}