{
  "type": "Feature",
  "properties": {
    "iso:country":"CA",
    "sg:address":"15 Boul Bouchard",
    "sg:city":"Dorval",
    "sg:classifiers":[
        {
            "category":"Restaurant",
            "type":"Food & Drink"
        }
    ],
    "sg:phone":"+1 514 631 2233",
    "sg:postcode":"H9S 5X2",
    "sg:province":"QC",
    "wof:name":"Barbie's",
    "wof:placetype":"venue"
},
  "geometry": {"coordinates":[-73.7214584351,45.4446144104],"type":"Point"}
}