{
  "type": "Feature",
  "properties": {
    "addr:full":"580 Bissett St Mattawa ON P0H 1V0",
    "addr:housenumber":"580",
    "addr:postcode":"p0h 1v0",
    "addr:street":"Bissett St",
    "iso:country":"CA",
    "sg:address":"580 Bissett St",
    "sg:city":"Mattawa",
    "sg:classifiers":[
        {
            "category":"Wholesale",
            "subcategory":"Office Equipment",
            "type":"Manufacturing & Wholesale Goods"
        }
    ],
    "sg:phone":"+1 705 744 2755",
    "sg:postcode":"P0H 1V0",
    "sg:province":"ON",
    "sg:tags":[
        "accounting",
        "bookkeeping",
        "system"
    ],
    "wof:name":"Burke's Bookkeeping Svc",
    "wof:placetype":"venue"
},
  "geometry": {"coordinates":[-78.7127532959,46.3146743774],"type":"Point"}
}