{
  "type": "Feature",
  "properties": {
    "iso:country":"CA",
    "sg:city":"Kitchener",
    "sg:classifiers":[
        {
            "category":"Manufacturing",
            "subcategory":"Tools & Machinery",
            "type":"Manufacturing & Wholesale Goods"
        }
    ],
    "sg:phone":"+1 519 895 0076",
    "sg:postcode":"N2R 1J4",
    "sg:province":"ON",
    "sg:tags":[
        "equipment",
        "system",
        "automation"
    ],
    "wof:name":"Linear Transfer Systems Ltd",
    "wof:placetype":"venue"
},
  "geometry": {"coordinates":[-80.472801,43.39991],"type":"Point"}
}