{
  "type": "Feature",
  "properties": {
    "addr:full":"Vancouver BC V6B 3B4",
    "addr:postcode":"v6b 3b4",
    "iso:country":"CA",
    "sg:city":"Vancouver",
    "sg:classifiers":[
        {
            "category":"Mining & Drilling",
            "type":"Manufacturing & Wholesale Goods"
        }
    ],
    "sg:phone":"+1 604 647 2227",
    "sg:postcode":"V6B 3B4",
    "sg:province":"BC",
    "sg:tags":[
        "company"
    ],
    "wof:name":"Electra Gold Ltd",
    "wof:placetype":"venue"
},
  "geometry": {"coordinates":[-123.11882,49.279621],"type":"Point"}
}