{
  "type": "Feature",
  "properties": {
    "iso:country":"CA",
    "sg:address":"186 Boul Saint-Michel",
    "sg:city":"Dolbeau-Mistassini",
    "sg:classifiers":[
        {
            "category":"Home & Garden",
            "subcategory":"Furniture",
            "type":"Retail Goods"
        }
    ],
    "sg:phone":"+1 418 276 1463",
    "sg:postcode":"G8L 4P4",
    "sg:province":"QC",
    "wof:name":"E Sasseville Ltee",
    "wof:placetype":"venue"
},
  "geometry": {"coordinates":[-72.20346832280001,48.8931732178],"type":"Point"}
}