{
  "type": "Feature",
  "properties": {
    "addr:full":"2311 Mcnicoll Ave Scarborough ON M1V 5L3",
    "addr:housenumber":"2311",
    "addr:postcode":"m1v 5l3",
    "addr:street":"Mcnicoll Ave",
    "iso:country":"CA",
    "sg:address":"2311 Mcnicoll Ave",
    "sg:city":"Scarborough",
    "sg:classifiers":[
        {
            "category":"Health Services",
            "subcategory":"Doctor",
            "type":"Services"
        }
    ],
    "sg:phone":"+1 416 321 6679",
    "sg:postcode":"M1V 5L3",
    "sg:province":"ON",
    "sg:tags":[
        "physician",
        "surgeon"
    ],
    "wof:name":"Lee, Simon MD",
    "wof:placetype":"venue"
},
  "geometry": {"coordinates":[-79.29155731199999,43.8145523071],"type":"Point"}
}