{
  "type": "Feature",
  "properties": {
    "iso:country":"CA",
    "sg:address":"155 Rang 3 & 4",
    "sg:city":"Lejeune",
    "sg:classifiers":[
        {
            "category":"Manufacturing",
            "subcategory":"Lumber",
            "type":"Manufacturing & Wholesale Goods"
        }
    ],
    "sg:phone":"+1 418 855 2568",
    "sg:postcode":"G0L 1S0",
    "sg:province":"QC",
    "sg:tags":[
        "syrup",
        "maple",
        "sugar"
    ],
    "wof:name":"Erabliere LA Grande Coulee Inc",
    "wof:placetype":"venue"
},
  "geometry": {"coordinates":[-69.778854,47.452312],"type":"Point"}
}