{
  "type": "Feature",
  "properties": {
    "addr:full":"721 Fraser St Prince Rupert BC V8J 1R1",
    "addr:housenumber":"721",
    "addr:postcode":"v8j 1r1",
    "addr:street":"Fraser St",
    "iso:country":"CA",
    "sg:address":"721 Fraser St",
    "sg:city":"Prince Rupert",
    "sg:classifiers":[
        {
            "category":"Organizations",
            "subcategory":"Religious Organization",
            "type":"Services"
        }
    ],
    "sg:phone":"+1 250 624 4403",
    "sg:postcode":"V8J 1R1",
    "sg:province":"BC",
    "sg:tags":[
        "church"
    ],
    "wof:name":"Prince Rupert Ntv Revival Ctr",
    "wof:placetype":"venue"
},
  "geometry": {"coordinates":[-130.32676699999999,54.310329],"type":"Point"}
}