{
  "type": "Feature",
  "properties": {
    "addr:full":"32 Ch Caron Dsl DE Drummond NB E3Y 1M7",
    "addr:housenumber":"32",
    "addr:postcode":"e3y 1m7",
    "addr:street":"Ch Caron Dsl De Drummond",
    "iso:country":"CA",
    "sg:address":"32 Ch Caron",
    "sg:city":"Dsl DE Drummond",
    "sg:classifiers":[
        {
            "category":"Manufacturing",
            "subcategory":"Signs",
            "type":"Manufacturing & Wholesale Goods"
        }
    ],
    "sg:phone":"+1 506 473 2191",
    "sg:postcode":"E3Y 1M7",
    "sg:province":"NB",
    "wof:name":"Georges' Sign Shop",
    "wof:placetype":"venue"
},
  "geometry": {"coordinates":[-67.6851806641,47.0367889404],"type":"Point"}
}