{
  "type": "Feature",
  "properties": {
    "addr:full":"3360 Rue Joseph Verdun QC H4G 1H9",
    "addr:housenumber":"3360",
    "addr:postcode":"h4g 1h9",
    "addr:street":"Rue Joseph Verdun",
    "iso:country":"CA",
    "sg:address":"3360 Rue Joseph",
    "sg:city":"Verdun",
    "sg:classifiers":[
        {
            "category":"Wholesale",
            "subcategory":"Furniture",
            "type":"Manufacturing & Wholesale Goods"
        }
    ],
    "sg:phone":"+1 514 769 0646",
    "sg:postcode":"H4G 1H9",
    "sg:province":"QC",
    "wof:name":"Imagine Solutions DE Bureau",
    "wof:placetype":"venue"
},
  "geometry": {"coordinates":[-73.571625,45.4701],"type":"Point"}
}