{
  "type": "Feature",
  "properties": {
    "addr:full":"Otter Lake Rd Parry Sound ON P2A 2W8",
    "addr:postcode":"p2a 2w8",
    "addr:street":"Otter Lake Rd",
    "iso:country":"CA",
    "sg:address":"Otter Lake Rd",
    "sg:city":"Parry Sound",
    "sg:classifiers":[
        {
            "category":"Recreation",
            "type":"Entertainment"
        }
    ],
    "sg:phone":"+1 705 378 2401",
    "sg:postcode":"P2A 2W8",
    "sg:province":"ON",
    "sg:tags":[
        "provincial",
        "parks"
    ],
    "wof:name":"Ontario Oastler Lake Prov Park",
    "wof:placetype":"venue"
},
  "geometry": {"coordinates":[-80.0363616943,45.3447685242],"type":"Point"}
}