{
  "type": "Feature",
  "properties": {
    "addr:full":"602 Silica St Nelson BC V1L 4N1",
    "addr:housenumber":"602",
    "addr:postcode":"bc v1l 4n1",
    "addr:street":"Silica St",
    "iso:country":"CA",
    "sg:address":"602 Silica St",
    "sg:city":"Nelson",
    "sg:classifiers":[
        {
            "category":"Organizations",
            "subcategory":"Religious Organization",
            "type":"Services"
        }
    ],
    "sg:phone":"+1 250 352 2822",
    "sg:postcode":"V1L 4N1",
    "sg:province":"BC",
    "sg:tags":[
        "church"
    ],
    "wof:name":"Nelson United Church",
    "wof:placetype":"venue"
},
  "geometry": {"coordinates":[-117.291023,49.490955],"type":"Point"}
}