{
  "type": "Feature",
  "properties": {
    "iso:country":"CA",
    "sg:address":"516 the Kingsway",
    "sg:city":"Etobicoke",
    "sg:classifiers":[
        {
            "category":"Social Services",
            "subcategory":"Child Care",
            "type":"Services"
        }
    ],
    "sg:phone":"+1 416 239 6816",
    "sg:postcode":"M9A 3W6",
    "sg:province":"ON",
    "wof:name":"Prestige Day Care",
    "wof:placetype":"venue"
},
  "geometry": {"coordinates":[-79.546738,43.673618],"type":"Point"}
}