{
  "type": "Feature",
  "properties": {
    "addr:full":"49 the Links Rd North York ON M2P 1T7",
    "addr:housenumber":"49",
    "addr:postcode":"m2p 1t7",
    "addr:street":"The Links Rd",
    "iso:country":"CA",
    "sg:address":"49 the Links Rd",
    "sg:city":"North York",
    "sg:classifiers":[
        {
            "category":"Retail",
            "subcategory":"Laundry & Dry Cleaning",
            "type":"Services"
        }
    ],
    "sg:phone":"+1 416 222 1289",
    "sg:postcode":"M2P 1T7",
    "sg:province":"ON",
    "sg:tags":[
        "cleaners"
    ],
    "wof:name":"Sketchley Cleaners",
    "wof:placetype":"venue"
},
  "geometry": {"coordinates":[-79.402046,43.751511],"type":"Point"}
}