{
  "type": "Feature",
  "properties": {
    "iso:country":"CA",
    "sg:city":"Grande Prairie",
    "sg:classifiers":[
        {
            "category":"Freight",
            "type":"Transportation"
        }
    ],
    "sg:phone":"+1 780 539 6085",
    "sg:postcode":"T8V 4W4",
    "sg:province":"AB",
    "sg:tags":[
        "field",
        "oil"
    ],
    "wof:name":"Thatchuk's Oil & Water Trnsprt",
    "wof:placetype":"venue"
},
  "geometry": {"coordinates":[-118.827575684,55.1611251831],"type":"Point"}
}