{
  "type": "Feature",
  "properties": {
    "addr:full":"1 Harbour St Thornbury ON N0H 2P0",
    "addr:housenumber":"1",
    "addr:postcode":"n0h 2p0",
    "addr:street":"Harbour St",
    "iso:country":"CA",
    "sg:address":"1 Harbour St",
    "sg:city":"Thornbury",
    "sg:classifiers":[
        {
            "category":"Travel",
            "subcategory":"Hotels & Motels",
            "type":"Entertainment"
        }
    ],
    "sg:phone":"+1 519 599 5591",
    "sg:postcode":"N0H 2P0",
    "sg:province":"ON",
    "sg:tags":[
        "resort"
    ],
    "wof:name":"Royal Harbour Resort",
    "wof:placetype":"venue"
},
  "geometry": {"coordinates":[-80.450874,44.563824],"type":"Point"}
}