{
  "type": "Feature",
  "properties": {
    "addr:full":"Winnipeg MB R2J 3T4",
    "addr:postcode":"r2j 3t4",
    "iso:country":"CA",
    "sg:city":"Winnipeg",
    "sg:classifiers":[
        {
            "category":"Shopping",
            "type":"Retail Goods"
        }
    ],
    "sg:phone":"+1 204 253 7499",
    "sg:postcode":"R2J 3T4",
    "sg:province":"MB",
    "sg:tags":[
        "spa",
        "hot",
        "tub"
    ],
    "wof:name":"Aqua Spa Pak",
    "wof:placetype":"venue"
},
  "geometry": {"coordinates":[-97.04613500000001,49.856609],"type":"Point"}
}