{
  "type": "Feature",
  "properties": {
    "addr:full":"145 Government Rd W Kirkland Lake ON P2N 2E8",
    "addr:housenumber":"145",
    "addr:postcode":"p2n 2e8",
    "addr:street":"Government Rd W",
    "iso:country":"CA",
    "sg:address":"145 Government Rd W",
    "sg:city":"Kirkland Lake",
    "sg:classifiers":[
        {
            "category":"Restaurant",
            "type":"Food & Drink"
        }
    ],
    "sg:phone":"+1 705 567 6363",
    "sg:postcode":"P2N 2E8",
    "sg:province":"ON",
    "sg:tags":[
        "shop",
        "coffee"
    ],
    "wof:name":"Coffee Time Deli",
    "wof:placetype":"venue"
},
  "geometry": {"coordinates":[-80.046257,48.147072],"type":"Point"}
}