{
  "type": "Feature",
  "properties": {
    "addr:full":"559 Boul Perron Carleton QC G0C 1J0",
    "addr:housenumber":"559",
    "addr:postcode":"g0c 1j0",
    "addr:street":"Boul Perron",
    "iso:country":"CA",
    "sg:address":"559 Boul Perron",
    "sg:city":"Carleton",
    "sg:classifiers":[
        {
            "category":"Restaurant",
            "type":"Food & Drink"
        }
    ],
    "sg:phone":"+1 418 364 3113",
    "sg:postcode":"G0C 1J0",
    "sg:province":"QC",
    "wof:name":"Cantine Enr",
    "wof:placetype":"venue"
},
  "geometry": {"coordinates":[-66.127411,48.104645],"type":"Point"}
}