{
  "type": "Feature",
  "properties": {
    "addr:full":"1006 Route 124 Norton NB E5T 1X3",
    "addr:housenumber":"1006",
    "addr:postcode":"e5t 1x3",
    "addr:street":"Route 124",
    "iso:country":"CA",
    "sg:address":"1006 Route 124",
    "sg:city":"Norton",
    "sg:classifiers":[
        {
            "category":"Manufacturing",
            "subcategory":"Building Materials",
            "type":"Manufacturing & Wholesale Goods"
        }
    ],
    "sg:phone":"+1 506 839 2946",
    "sg:postcode":"E5T 1X3",
    "sg:province":"NB",
    "sg:tags":[
        "truss"
    ],
    "wof:name":"Gable Enterprises Ltd",
    "wof:placetype":"venue"
},
  "geometry": {"coordinates":[-65.7462234497,45.6603431702],"type":"Point"}
}