{
  "type": "Feature",
  "properties": {
    "addr:full":"Kedgwick NB E8B 1G3",
    "addr:postcode":"e8b 1g3",
    "iso:country":"CA",
    "sg:city":"Kedgwick",
    "sg:classifiers":[
        {
            "category":"Health Services",
            "subcategory":"Doctor",
            "type":"Services"
        }
    ],
    "sg:phone":"+1 506 284 2032",
    "sg:postcode":"E8B 1G3",
    "sg:province":"NB",
    "sg:tags":[
        "physician",
        "surgeon"
    ],
    "wof:name":"Bouchard, Jean-Guy MD",
    "wof:placetype":"venue"
},
  "geometry": {"coordinates":[-67.352203,47.645359],"type":"Point"}
}