{
  "type": "Feature",
  "properties": {
    "addr:full":"567 Christie St Toronto ON M6G 3E4",
    "addr:housenumber":"567",
    "addr:postcode":"m6g 3e4",
    "addr:street":"Christie St",
    "iso:country":"CA",
    "sg:address":"567 Christie St",
    "sg:city":"Toronto",
    "sg:classifiers":[
        {
            "category":"Health Services",
            "subcategory":"Doctor",
            "type":"Services"
        }
    ],
    "sg:phone":"+1 416 656 4230",
    "sg:postcode":"M6G 3E4",
    "sg:province":"ON",
    "sg:tags":[
        "physician",
        "surgeon"
    ],
    "wof:name":"Da Costa, G A MD",
    "wof:placetype":"venue"
},
  "geometry": {"coordinates":[-79.424446106,43.6791343689],"type":"Point"}
}