{
  "type": "Feature",
  "properties": {
    "addr:full":"Saint-Laurent QC H4L 5A6",
    "addr:postcode":"h4l 5a6",
    "iso:country":"CA",
    "sg:city":"Saint-Laurent",
    "sg:classifiers":[
        {
            "category":"Real Estate",
            "subcategory":"Real Estate Agent",
            "type":"Services"
        }
    ],
    "sg:phone":"+1 514 331 9059",
    "sg:postcode":"H4L 5A6",
    "sg:province":"QC",
    "wof:name":"Gfl Immobilier Inc",
    "wof:placetype":"venue"
},
  "geometry": {"coordinates":[-73.6701126099,45.5209541321],"type":"Point"}
}