{
  "type": "Feature",
  "properties": {
    "addr:full":"Toronto ON M4V 1R1",
    "addr:postcode":"m4v 1r1",
    "iso:country":"CA",
    "sg:city":"Toronto",
    "sg:classifiers":[
        {
            "category":"Health Services",
            "subcategory":"Doctor",
            "type":"Services"
        }
    ],
    "sg:phone":"+1 416 961 9740",
    "sg:postcode":"M4V 1R1",
    "sg:province":"ON",
    "sg:tags":[
        "physician",
        "surgeon"
    ],
    "wof:name":"Preston, Helen A MD",
    "wof:placetype":"venue"
},
  "geometry": {"coordinates":[-79.402672,43.686531],"type":"Point"}
}