{
  "type": "Feature",
  "properties": {
    "addr:full":"360 Mcmillan Ave Winnipeg MB R3L 0N2",
    "addr:housenumber":"360",
    "addr:postcode":"r3l 0n2",
    "addr:street":"Mcmillan Ave",
    "iso:country":"CA",
    "sg:address":"360 Mcmillan Ave",
    "sg:city":"Winnipeg",
    "sg:classifiers":[
        {
            "category":"Real Estate",
            "subcategory":"Real Estate Agent",
            "type":"Services"
        }
    ],
    "sg:phone":"+1 204 453 1981",
    "sg:postcode":"R3L 0N2",
    "sg:province":"MB",
    "sg:tags":[
        "management"
    ],
    "wof:name":"Bachman Property Management",
    "wof:placetype":"venue"
},
  "geometry": {"coordinates":[-97.141243,49.875729],"type":"Point"}
}