{
  "type": "Feature",
  "properties": {
    "addr:full":"Iqaluit NU X0A 0H0",
    "addr:postcode":"x0a 0h0",
    "iso:country":"CA",
    "sg:city":"Iqaluit",
    "sg:classifiers":[
        {
            "category":"Wholesale",
            "subcategory":"Seafood",
            "type":"Manufacturing & Wholesale Goods"
        }
    ],
    "sg:phone":"+1 867 979 4458",
    "sg:postcode":"X0A 0H0",
    "sg:province":"NU",
    "wof:name":"Iqaluit Enterprises",
    "wof:placetype":"venue"
},
  "geometry": {"coordinates":[-68.5190200806,63.7514686584],"type":"Point"}
}