{
  "type": "Feature",
  "properties": {
    "addr:full":"95 Arbour Dr Oakville ON L6J 4Y6",
    "addr:housenumber":"95",
    "addr:postcode":"l6j 4y6",
    "addr:street":"Arbour Dr",
    "iso:country":"CA",
    "sg:address":"95 Arbour Dr",
    "sg:city":"Oakville",
    "sg:classifiers":[
        {
            "category":"Building & Trades",
            "subcategory":"Construction",
            "type":"Services"
        }
    ],
    "sg:phone":"+1 905 842 9451",
    "sg:postcode":"L6J 4Y6",
    "sg:province":"ON",
    "sg:tags":[
        "water",
        "control",
        "pollution"
    ],
    "wof:name":"Biothane Corp",
    "wof:placetype":"venue"
},
  "geometry": {"coordinates":[-79.637199,43.473984],"type":"Point"}
}