{
  "type": "Feature",
  "properties": {
    "addr:full":"1443 Bathurst St Toronto ON M5R 3J2",
    "addr:housenumber":"1443",
    "addr:postcode":"m5r 3j2",
    "addr:street":"Bathurst St",
    "iso:country":"CA",
    "sg:address":"1443 Bathurst St",
    "sg:city":"Toronto",
    "sg:classifiers":[
        {
            "category":"Organizations",
            "subcategory":"Religious Organization",
            "type":"Services"
        }
    ],
    "sg:phone":"+1 416 533 5750",
    "sg:postcode":"M5R 3J2",
    "sg:province":"ON",
    "sg:tags":[
        "church"
    ],
    "wof:name":"Community of Christ",
    "wof:placetype":"venue"
},
  "geometry": {"coordinates":[-79.41784667970001,43.6825370789],"type":"Point"}
}