{
  "type": "Feature",
  "properties": {
    "addr:full":"241 Edgeley Blvd Concord ON L4K 3Y6",
    "addr:housenumber":"241",
    "addr:postcode":"l4k 3y6",
    "addr:street":"Edgeley Blvd",
    "iso:country":"CA",
    "sg:address":"241 Edgeley Blvd",
    "sg:city":"Concord",
    "sg:classifiers":[
        {
            "category":"Building & Trades",
            "subcategory":"Construction",
            "type":"Services"
        }
    ],
    "sg:phone":"+1 905 738 8905",
    "sg:postcode":"L4K 3Y6",
    "sg:province":"ON",
    "sg:tags":[
        "tile",
        "dealer"
    ],
    "wof:name":"B J Tiles & Marble",
    "wof:placetype":"venue"
},
  "geometry": {"coordinates":[-79.533241272,43.7985153198],"type":"Point"}
}