{
  "type": "Feature",
  "properties": {
    "addr:full":"7677 134 St Surrey BC V3W 9E9",
    "addr:housenumber":"7677",
    "addr:postcode":"v3w 9e9",
    "addr:street":"134 St",
    "iso:country":"CA",
    "sg:address":"7677 134 St",
    "sg:city":"Surrey",
    "sg:classifiers":[
        {
            "category":"Sports & Exercise",
            "subcategory":"Gym",
            "type":"Entertainment"
        }
    ],
    "sg:phone":"+1 604 591 9944",
    "sg:postcode":"V3W 9E9",
    "sg:province":"BC",
    "sg:tags":[
        "club",
        "health",
        "studio",
        "gymnasium"
    ],
    "wof:name":"California Club & Fitness Ctr",
    "wof:placetype":"venue"
},
  "geometry": {"coordinates":[-122.85137899999999,49.142246],"type":"Point"}
}