{
  "type": "Feature",
  "properties": {
    "addr:full":"20 Rue Principale E Cacouna QC G0L 1G0",
    "addr:housenumber":"20",
    "addr:postcode":"g0l 1g0",
    "addr:street":"Rue Principale E",
    "iso:country":"CA",
    "sg:address":"20 Rue Principale E",
    "sg:city":"Cacouna",
    "sg:classifiers":[
        {
            "category":"Personal",
            "subcategory":"Beauty Salon",
            "type":"Services"
        }
    ],
    "sg:phone":"+1 418 860 2431",
    "sg:postcode":"G0L 1G0",
    "sg:province":"QC",
    "wof:name":"Salon DE Coiffure Discretion",
    "wof:placetype":"venue"
},
  "geometry": {"coordinates":[-69.506462,47.910439],"type":"Point"}
}