{
  "type": "Feature",
  "properties": {
    "addr:full":"601 Rue Saint-Georges LA Prairie QC J5R 2N6",
    "addr:housenumber":"601",
    "addr:postcode":"j5r 2n6",
    "addr:street":"Rue Saint-Georges",
    "iso:country":"CA",
    "sg:address":"601 Rue Saint-Georges",
    "sg:city":"LA Prairie",
    "sg:classifiers":[
        {
            "category":"Personal",
            "subcategory":"Beauty Salon",
            "type":"Services"
        }
    ],
    "sg:phone":"+1 450 659 5292",
    "sg:postcode":"J5R 2N6",
    "sg:province":"QC",
    "wof:name":"Salon Ginette Riendeau",
    "wof:placetype":"venue"
},
  "geometry": {"coordinates":[-73.487159729,45.414981842],"type":"Point"}
}