{
  "type": "Feature",
  "properties": {
    "iso:country":"CA",
    "sg:address":"4190 Finch Ave E",
    "sg:city":"Scarborough",
    "sg:classifiers":[
        {
            "category":"Shopping",
            "subcategory":"Pharmacy",
            "type":"Retail Goods"
        }
    ],
    "sg:phone":"+1 416 297 8008",
    "sg:postcode":"M1S 4T7",
    "sg:province":"ON",
    "sg:tags":[
        "post"
    ],
    "wof:name":"Finch Midland Pharmacy",
    "wof:placetype":"venue"
},
  "geometry": {"coordinates":[-79.287064,43.803734],"type":"Point"}
}