{
  "type": "Feature",
  "properties": {
    "addr:full":"64 Nelson St W Brampton ON L6X 1C5",
    "addr:housenumber":"64",
    "addr:postcode":"l6x 1c5",
    "addr:street":"Nelson St W",
    "iso:country":"CA",
    "sg:address":"64 Nelson St W",
    "sg:city":"Brampton",
    "sg:phone":"+1 905 451 6275",
    "sg:postcode":"L6X 1C5",
    "sg:province":"ON",
    "sg:tags":[
        "oil"
    ],
    "wof:name":"Peel Ice & Fuel",
    "wof:placetype":"venue"
},
  "geometry": {"coordinates":[-79.7650985718,43.6841659546],"type":"Point"}
}