{
  "type": "Feature",
  "properties": {
    "iso:country":"CA",
    "sg:address":"4911 Boul Notre-Dame",
    "sg:city":"Laval",
    "sg:classifiers":[
        {
            "category":"Personal",
            "subcategory":"Beauty Salon",
            "type":"Services"
        }
    ],
    "sg:phone":"+1 450 688 2181",
    "sg:postcode":"H7W 1V3",
    "sg:province":"QC",
    "wof:name":"Salon Sonny",
    "wof:placetype":"venue"
},
  "geometry": {"coordinates":[-73.7710723877,45.5341644287],"type":"Point"}
}