{
  "type": "Feature",
  "properties": {
    "addr:full":"4411 59 St Stettler AB T0C 2L1",
    "addr:housenumber":"4411",
    "addr:postcode":"t0c 2l1",
    "addr:street":"59 St",
    "iso:country":"CA",
    "sg:address":"4411 59 St",
    "sg:city":"Stettler",
    "sg:classifiers":[
        {
            "category":"Food & Beverages",
            "subcategory":"Groceries & Convenience Stores",
            "type":"Retail Goods"
        }
    ],
    "sg:phone":"+1 403 742 5747",
    "sg:postcode":"T0C 2L1",
    "sg:province":"AB",
    "sg:tags":[
        "grocer"
    ],
    "wof:name":"Grandview Grocery",
    "wof:placetype":"venue"
},
  "geometry": {"coordinates":[-112.71888,52.319801],"type":"Point"}
}