{
  "type": "Feature",
  "properties": {
    "addr:full":"4819 48 Ave Sedgewick AB T0B 4C0",
    "addr:housenumber":"4819",
    "addr:postcode":"t0b 4c0",
    "addr:street":"48 Ave Sedgewick",
    "iso:country":"CA",
    "sg:address":"4819 48 Ave",
    "sg:city":"Sedgewick",
    "sg:classifiers":[
        {
            "category":"Shopping",
            "subcategory":"Florist",
            "type":"Retail Goods"
        }
    ],
    "sg:phone":"+1 780 384 2727",
    "sg:postcode":"T0B 4C0",
    "sg:province":"AB",
    "wof:name":"Flowers By the Trax & Sears",
    "wof:placetype":"venue"
},
  "geometry": {"coordinates":[-111.694282532,52.7738494873],"type":"Point"}
}