{
  "type": "Feature",
  "properties": {
    "iso:country":"CA",
    "sg:address":"1198 Rue Bishop",
    "sg:city":"Montreal",
    "sg:classifiers":[
        {
            "category":"Personal",
            "subcategory":"Tanning Parlor",
            "type":"Services"
        }
    ],
    "sg:phone":"+1 514 861 9786",
    "sg:postcode":"H3G 2E3",
    "sg:province":"QC",
    "sg:tags":[
        "salon"
    ],
    "wof:name":"Bronzage Bishop",
    "wof:placetype":"venue"
},
  "geometry": {"coordinates":[-73.575066,45.4958],"type":"Point"}
}