{
  "type": "Feature",
  "properties": {
    "addr:full":"19 Law Cres Richmond Hill ON L4C 5K7",
    "addr:housenumber":"19",
    "addr:postcode":"l4c 5k7",
    "addr:street":"Law Cres",
    "iso:country":"CA",
    "sg:address":"19 Law Cres",
    "sg:city":"Richmond Hill",
    "sg:classifiers":[
        {
            "category":"Building & Trades",
            "subcategory":"Construction",
            "type":"Services"
        }
    ],
    "sg:phone":"+1 416 385 7200",
    "sg:postcode":"L4C 5K7",
    "sg:province":"ON",
    "sg:tags":[
        "ceiling"
    ],
    "wof:name":"Camspec Contractors Inc",
    "wof:placetype":"venue"
},
  "geometry": {"coordinates":[-79.4548568726,43.8532218933],"type":"Point"}
}