{
  "type": "Feature",
  "properties": {
    "addr:full":"375 William St Delhi ON N4B 2X6",
    "addr:housenumber":"375",
    "addr:postcode":"n4b 2x6",
    "addr:street":"William St",
    "iso:country":"CA",
    "sg:address":"375 William St",
    "sg:city":"Delhi",
    "sg:classifiers":[
        {
            "category":"Building & Trades",
            "subcategory":"Cleaning & Sanitation",
            "type":"Services"
        }
    ],
    "sg:phone":"+1 519 582 8233",
    "sg:postcode":"N4B 2X6",
    "sg:province":"ON",
    "sg:tags":[
        "filter"
    ],
    "wof:name":"Mullin Industries M & P Filter",
    "wof:placetype":"venue"
},
  "geometry": {"coordinates":[-80.50820899999999,42.850304],"type":"Point"}
}