{
  "type": "Feature",
  "properties": {
    "iso:country":"CA",
    "sg:address":"120 Whitmore Rd #19",
    "sg:city":"Woodbridge",
    "sg:classifiers":[
        {
            "category":"Restaurant",
            "type":"Food & Drink"
        }
    ],
    "sg:phone":"+1 905 265 9229",
    "sg:postcode":"L4L 6A5",
    "sg:province":"ON",
    "sg:tags":[
        "caterer"
    ],
    "wof:name":"Cater me Please Ltd",
    "wof:placetype":"venue"
},
  "geometry": {"coordinates":[-79.555786,43.78532],"type":"Point"}
}