{
  "type": "Feature",
  "properties": {
    "iso:country":"CA",
    "sg:address":"Bridge St",
    "sg:city":"Kitwanga",
    "sg:classifiers":[
        {
            "category":"Organizations",
            "subcategory":"Community Association",
            "type":"Services"
        }
    ],
    "sg:phone":"+1 250 849 5591",
    "sg:postcode":"V0J 2A0",
    "sg:province":"BC",
    "sg:tags":[
        "native"
    ],
    "wof:name":"Gitwangak Band Council",
    "wof:placetype":"venue"
},
  "geometry": {"coordinates":[-128.076660156,55.100440979],"type":"Point"}
}