{
  "type": "Feature",
  "properties": {
    "addr:full":"12408 Kalamalka Rd Coldstream BC V1B 1M7",
    "addr:housenumber":"12408",
    "addr:postcode":"bc v1b 1m7",
    "addr:street":"Kalamalka Rd",
    "iso:country":"CA",
    "sg:address":"12408 Kalamalka Rd",
    "sg:city":"Coldstream",
    "sg:classifiers":[
        {
            "category":"Bars & Pubs",
            "type":"Food & Drink"
        }
    ],
    "sg:phone":"+1 250 545 3131",
    "sg:postcode":"V1B 1M7",
    "sg:province":"BC",
    "wof:name":"Alexander's Pub on the Beach",
    "wof:placetype":"venue"
},
  "geometry": {"coordinates":[-119.263442993,50.230266571],"type":"Point"}
}