{
  "type": "Feature",
  "properties": {
    "addr:full":"Concord ON L4K 2G1",
    "addr:postcode":"l4k 2g1",
    "iso:country":"CA",
    "sg:city":"Concord",
    "sg:classifiers":[
        {
            "category":"Manufacturing",
            "subcategory":"Rubber & Plastics",
            "type":"Manufacturing & Wholesale Goods"
        }
    ],
    "sg:phone":"+1 905 761 2828",
    "sg:postcode":"L4K 2G1",
    "sg:province":"ON",
    "wof:name":"Bulldog Tool & Extrusions Ltd",
    "wof:placetype":"venue"
},
  "geometry": {"coordinates":[-79.49793243409999,43.8105354309],"type":"Point"}
}