{
  "type": "Feature",
  "properties": {
    "addr:full":"5970 16th Ave Markham ON L3P 7R1",
    "addr:housenumber":"5970",
    "addr:postcode":"l3p 7r1",
    "addr:street":"16Th Ave",
    "iso:country":"CA",
    "sg:address":"5970 16th Ave",
    "sg:city":"Markham",
    "sg:classifiers":[
        {
            "category":"Banks & Credit Unions",
            "subcategory":"Bank",
            "type":"Services"
        }
    ],
    "sg:phone":"+1 905 472 4890",
    "sg:postcode":"L3P 7R1",
    "sg:province":"ON",
    "wof:name":"Bank of Montreal",
    "wof:placetype":"venue"
},
  "geometry": {"coordinates":[-79.266242981,43.8912277222],"type":"Point"}
}