{
  "type": "Feature",
  "properties": {
    "addr:full":"Swan River MB R0L 1Z0",
    "addr:postcode":"r0l 1z0",
    "iso:country":"CA",
    "sg:city":"Swan River",
    "sg:classifiers":[
        {
            "category":"Travel",
            "subcategory":"Hotels & Motels",
            "type":"Entertainment"
        }
    ],
    "sg:phone":"+1 204 734 3471",
    "sg:postcode":"R0L 1Z0",
    "sg:province":"MB",
    "wof:name":"Skyline Motel & Restaurant",
    "wof:placetype":"venue"
},
  "geometry": {"coordinates":[-101.255028,52.114143],"type":"Point"}
}