{
  "type": "Feature",
  "properties": {
    "addr:full":"2266 Lasalle Blvd Sudbury ON P3A 2B1",
    "addr:housenumber":"2266",
    "addr:postcode":"p3a 2b1",
    "addr:street":"Lasalle Blvd",
    "iso:country":"CA",
    "sg:address":"2266 Lasalle Blvd",
    "sg:city":"Sudbury",
    "sg:classifiers":[
        {
            "category":"Home & Garden",
            "subcategory":"Carpets & Floor Coverings",
            "type":"Retail Goods"
        }
    ],
    "sg:phone":"+1 705 560 1313",
    "sg:postcode":"P3A 2B1",
    "sg:province":"ON",
    "sg:tags":[
        "dealer",
        "rug"
    ],
    "wof:name":"Sudbury Carpetland & Home Int",
    "wof:placetype":"venue"
},
  "geometry": {"coordinates":[-80.917191,46.522247],"type":"Point"}
}