{
  "type": "Feature",
  "properties": {
    "addr:full":"600 Princess St Woodstock ON N4S 4H4",
    "addr:housenumber":"600",
    "addr:postcode":"n4s 4h4",
    "addr:street":"Princess St",
    "iso:country":"CA",
    "sg:address":"600 Princess St",
    "sg:city":"Woodstock",
    "sg:classifiers":[
        {
            "category":"Health Services",
            "subcategory":"Doctor",
            "type":"Services"
        }
    ],
    "sg:phone":"+1 519 421 7252",
    "sg:postcode":"N4S 4H4",
    "sg:province":"ON",
    "sg:tags":[
        "physician",
        "surgeon"
    ],
    "wof:name":"Brioux, Joseph MD",
    "wof:placetype":"venue"
},
  "geometry": {"coordinates":[-80.7525253296,43.1322479248],"type":"Point"}
}