{
  "type": "Feature",
  "properties": {
    "iso:country":"CA",
    "sg:address":"11819 106 St NW # 1",
    "sg:city":"Edmonton",
    "sg:classifiers":[
        {
            "category":"Real Estate",
            "subcategory":"Real Estate Operator",
            "type":"Services"
        }
    ],
    "sg:phone":"+1 780 477 8230",
    "sg:postcode":"T5G 2R3",
    "sg:province":"AB",
    "sg:tags":[
        "apartment"
    ],
    "wof:name":"Hartford Apartments",
    "wof:placetype":"venue"
},
  "geometry": {"coordinates":[-113.50273132300001,53.571056366],"type":"Point"}
}