{
  "type": "Feature",
  "properties": {
    "addr:full":"505 Rue Principale Buckingham QC J8L 2G8",
    "addr:housenumber":"505",
    "addr:postcode":"j8l 2g8",
    "addr:street":"Rue Principale",
    "iso:country":"CA",
    "sg:address":"505 Rue Principale",
    "sg:city":"Buckingham",
    "sg:classifiers":[
        {
            "category":"Shopping",
            "subcategory":"Clothing, Apparel, & Fashions",
            "type":"Retail Goods"
        }
    ],
    "sg:phone":"+1 819 986 3371",
    "sg:postcode":"J8L 2G8",
    "sg:province":"QC",
    "wof:name":"David Assad Mag Entrepot",
    "wof:placetype":"venue"
},
  "geometry": {"coordinates":[-75.4155426025,45.5876731873],"type":"Point"}
}