{
  "type": "Feature",
  "properties": {
    "addr:full":"PO Box 75 Plum Point NL A0K 4A0",
    "addr:housenumber":"po box 75",
    "addr:postcode":"a0k 4a0",
    "addr:street":"Plum Point",
    "iso:country":"CA",
    "sg:address":"PO Box 75",
    "sg:city":"Plum Point",
    "sg:classifiers":[
        {
            "category":"Organizations",
            "subcategory":"Religious Organization",
            "type":"Services"
        }
    ],
    "sg:phone":"+1 709 247 2003",
    "sg:postcode":"A0K 4A0",
    "sg:province":"NL",
    "sg:tags":[
        "church"
    ],
    "wof:name":"Anglican Church of the Advent",
    "wof:placetype":"venue"
},
  "geometry": {"coordinates":[-56.877193,51.07777],"type":"Point"}
}