{
  "type": "Feature",
  "properties": {
    "addr:full":"410 Rue St-Francois Edmundston NB E3V 1G6",
    "addr:housenumber":"410",
    "addr:postcode":"e3v 1g6",
    "addr:street":"Rue St-Francois",
    "iso:country":"CA",
    "sg:address":"410 Rue St-Francois",
    "sg:city":"Edmundston",
    "sg:classifiers":[
        {
            "category":"Autos & Motor Vehicles",
            "subcategory":"Auto Supplies",
            "type":"Retail Goods"
        }
    ],
    "sg:phone":"+1 506 735 6136",
    "sg:postcode":"E3V 1G6",
    "sg:province":"NB",
    "sg:tags":[
        "tire"
    ],
    "wof:name":"Provincial Bandag Tires Ltd",
    "wof:placetype":"venue"
},
  "geometry": {"coordinates":[-68.346367,47.359608],"type":"Point"}
}