{
  "type": "Feature",
  "properties": {
    "addr:full":"Stratford ON N5A 6S6",
    "addr:postcode":"n5a 6s6",
    "iso:country":"CA",
    "sg:city":"Stratford",
    "sg:classifiers":[
        {
            "category":"Building & Trades",
            "subcategory":"Plumbing",
            "type":"Services"
        }
    ],
    "sg:phone":"+1 519 271 1511",
    "sg:postcode":"N5A 6S6",
    "sg:province":"ON",
    "sg:tags":[
        "sheet",
        "work",
        "metal",
        "contractor"
    ],
    "wof:name":"Avon Heating",
    "wof:placetype":"venue"
},
  "geometry": {"coordinates":[-80.995178,43.387981],"type":"Point"}
}