{
  "type": "Feature",
  "properties": {
    "iso:country":"CA",
    "sg:address":"2900 Rue Masson",
    "sg:city":"Montreal",
    "sg:classifiers":[
        {
            "category":"Utilities",
            "subcategory":"Mobile Phone",
            "type":"Services"
        }
    ],
    "sg:phone":"+1 514 723 6306",
    "sg:postcode":"H1Y 1X2",
    "sg:province":"QC",
    "sg:tags":[
        "telephone",
        "cellular"
    ],
    "wof:name":"Multi-Cell Communications",
    "wof:placetype":"venue"
},
  "geometry": {"coordinates":[-73.574768,45.548161],"type":"Point"}
}