{
  "type": "Feature",
  "properties": {
    "addr:full":"New Westminster BC V3L 3W2",
    "addr:postcode":"v3l 3w2",
    "iso:country":"CA",
    "sg:city":"New Westminster",
    "sg:classifiers":[
        {
            "category":"Health Services",
            "subcategory":"Doctor",
            "type":"Services"
        }
    ],
    "sg:phone":"+1 604 521 5986",
    "sg:postcode":"V3L 3W2",
    "sg:province":"BC",
    "sg:tags":[
        "physician",
        "surgeon"
    ],
    "wof:name":"Bojm, Morris A MD",
    "wof:placetype":"venue"
},
  "geometry": {"coordinates":[-122.89312700000001,49.222923],"type":"Point"}
}