{
  "type": "Feature",
  "properties": {
    "addr:full":"400 Fines Dr Regina SK S4N 5L9",
    "addr:housenumber":"400",
    "addr:postcode":"s4n 5l9",
    "addr:street":"Fines Dr",
    "iso:country":"CA",
    "sg:address":"400 Fines Dr",
    "sg:city":"Regina",
    "sg:classifiers":[
        {
            "category":"Education",
            "subcategory":"School",
            "type":"Public Place"
        }
    ],
    "sg:phone":"+1 306 791 8370",
    "sg:postcode":"S4N 5L9",
    "sg:province":"SK",
    "wof:name":"F W Johnson Collegiate",
    "wof:placetype":"venue"
},
  "geometry": {"coordinates":[-104.547424316,50.449382782],"type":"Point"}
}