{
  "type": "Feature",
  "properties": {
    "addr:full":"31476 Crossley Crt Abbotsford BC V2T 5G8",
    "addr:housenumber":"31476",
    "addr:postcode":"v2t 5g8",
    "addr:street":"Crossley Crt",
    "iso:country":"CA",
    "sg:address":"31476 Crossley Crt",
    "sg:city":"Abbotsford",
    "sg:classifiers":[
        {
            "category":"Wholesale",
            "subcategory":"Non-durable Goods",
            "type":"Manufacturing & Wholesale Goods"
        }
    ],
    "sg:phone":"+1 604 504 7080",
    "sg:postcode":"V2T 5G8",
    "sg:province":"BC",
    "sg:tags":[
        "advertising"
    ],
    "wof:name":"T & S Specialty Imprinting",
    "wof:placetype":"venue"
},
  "geometry": {"coordinates":[-122.35219574,49.0562095642],"type":"Point"}
}