{
  "type": "Feature",
  "properties": {
    "addr:full":"706 Boul Perron Maria QC G0C 1Y0",
    "addr:housenumber":"706",
    "addr:postcode":"g0c 1y0",
    "addr:street":"Boul Perron",
    "iso:country":"CA",
    "sg:address":"706 Boul Perron",
    "sg:city":"Maria",
    "sg:classifiers":[
        {
            "category":"Organizations",
            "subcategory":"Professional Association",
            "type":"Services"
        }
    ],
    "sg:phone":"+1 418 759 8000",
    "sg:postcode":"G0C 1Y0",
    "sg:province":"QC",
    "wof:name":"Source Alimentaire Bonavignon",
    "wof:placetype":"venue"
},
  "geometry": {"coordinates":[-65.967026,48.191418],"type":"Point"}
}