{
  "type": "Feature",
  "properties": {
    "addr:full":"5619 Ch DE LA Cote-Des-Neiges Montreal QC H3T 1Y8",
    "addr:housenumber":"5619",
    "addr:postcode":"h3t 1y8",
    "addr:street":"Ch De La Cote-Des-Neiges",
    "iso:country":"CA",
    "sg:address":"5619 Ch DE LA Cote-Des-Neiges",
    "sg:city":"Montreal",
    "sg:classifiers":[
        {
            "category":"Personal",
            "subcategory":"Beauty Salon",
            "type":"Services"
        }
    ],
    "sg:phone":"+1 514 731 0495",
    "sg:postcode":"H3T 1Y8",
    "sg:province":"QC",
    "wof:name":"Salon DE Coiffure Venus",
    "wof:placetype":"venue"
},
  "geometry": {"coordinates":[-73.626411,45.498333],"type":"Point"}
}