{
  "type": "Feature",
  "properties": {
    "addr:full":"251 Union St Simcoe ON N3Y 2B4",
    "addr:housenumber":"251",
    "addr:postcode":"n3y 2b4",
    "addr:street":"Union St",
    "iso:country":"CA",
    "sg:address":"251 Union St",
    "sg:city":"Simcoe",
    "sg:classifiers":[
        {
            "category":"Social Services",
            "type":"Services"
        }
    ],
    "sg:phone":"+1 519 426 7604",
    "sg:postcode":"N3Y 2B4",
    "sg:province":"ON",
    "sg:tags":[
        "organization",
        "welfare"
    ],
    "wof:name":"Union House Residence",
    "wof:placetype":"venue"
},
  "geometry": {"coordinates":[-80.31322479249999,42.8386039734],"type":"Point"}
}