{
  "type": "Feature",
  "properties": {
    "addr:full":"510 Eastern Ave Toronto ON M4M 1C7",
    "addr:housenumber":"510",
    "addr:postcode":"m4m 1c7",
    "addr:street":"Eastern Ave",
    "iso:country":"CA",
    "sg:address":"510 Eastern Ave",
    "sg:city":"Toronto",
    "sg:classifiers":[
        {
            "category":"Building & Trades",
            "subcategory":"Electrical",
            "type":"Services"
        }
    ],
    "sg:phone":"+1 416 461 9664",
    "sg:postcode":"M4M 1C7",
    "sg:province":"ON",
    "sg:tags":[
        "electric",
        "contractor"
    ],
    "wof:name":"Synchro Tech Electric Inc",
    "wof:placetype":"venue"
},
  "geometry": {"coordinates":[-79.340042,43.658253],"type":"Point"}
}