{
  "type": "Feature",
  "properties": {
    "iso:country":"CA",
    "sg:address":"3240 Jefferson Blvd",
    "sg:city":"Windsor",
    "sg:classifiers":[
        {
            "category":"Manufacturing",
            "subcategory":"Signs",
            "type":"Manufacturing & Wholesale Goods"
        }
    ],
    "sg:phone":"+1 519 944 6446",
    "sg:postcode":"N8T 2W8",
    "sg:province":"ON",
    "wof:name":"Roland's Neon Signs",
    "wof:placetype":"venue"
},
  "geometry": {"coordinates":[-82.9408416748,42.2932434082],"type":"Point"}
}