{
  "type": "Feature",
  "properties": {
    "addr:full":"97 Tobique Ch Grand Falls NB E3Y 1B9",
    "addr:housenumber":"97",
    "addr:postcode":"e3y 1b9",
    "iso:country":"CA",
    "sg:address":"97 Tobique Ch",
    "sg:city":"Grand Falls",
    "sg:classifiers":[
        {
            "category":"Shopping",
            "subcategory":"Florist",
            "type":"Retail Goods"
        }
    ],
    "sg:phone":"+1 506 473 1877",
    "sg:postcode":"E3Y 1B9",
    "sg:province":"NB",
    "wof:name":"Fleuriste Centre Floral-Grand",
    "wof:placetype":"venue"
},
  "geometry": {"coordinates":[-67.734283,47.051365],"type":"Point"}
}