{
  "type": "Feature",
  "properties": {
    "addr:full":"634 Colby Dr Waterloo ON N2V 1A2",
    "addr:housenumber":"634",
    "addr:postcode":"n2v 1a2",
    "addr:street":"Colby Dr",
    "iso:country":"CA",
    "sg:address":"634 Colby Dr",
    "sg:city":"Waterloo",
    "sg:classifiers":[
        {
            "category":"Manufacturing",
            "subcategory":"Tools & Machinery",
            "type":"Manufacturing & Wholesale Goods"
        }
    ],
    "sg:phone":"+1 519 746 2101",
    "sg:postcode":"N2V 1A2",
    "sg:province":"ON",
    "sg:tags":[
        "alternator",
        "starter"
    ],
    "wof:name":"Royal Electric Alternator",
    "wof:placetype":"venue"
},
  "geometry": {"coordinates":[-80.54070299999999,43.506184],"type":"Point"}
}