{
  "type": "Feature",
  "properties": {
    "addr:full":"Mount Pearl NL A1N 4V6",
    "addr:postcode":"a1n 4v6",
    "iso:country":"CA",
    "sg:city":"Mount Pearl",
    "sg:classifiers":[
        {
            "category":"Freight",
            "type":"Transportation"
        }
    ],
    "sg:phone":"+1 709 368 1914",
    "sg:postcode":"A1N 4V6",
    "sg:province":"NL",
    "sg:tags":[
        "courier"
    ],
    "wof:name":"Ace Courier Svc",
    "wof:placetype":"venue"
},
  "geometry": {"coordinates":[-52.811474,47.527073],"type":"Point"}
}