{
  "type": "Feature",
  "properties": {
    "addr:full":"154 Av Atwater Montreal QC H4C 2G3",
    "addr:postcode":"h4c 2g3",
    "addr:street":"154 Av Atwater",
    "iso:country":"CA",
    "sg:address":"154 Av Atwater",
    "sg:city":"Montreal",
    "sg:classifiers":[
        {
            "category":"Food & Beverages",
            "subcategory":"Meat & Fish",
            "type":"Retail Goods"
        }
    ],
    "sg:phone":"+1 514 937 2863",
    "sg:postcode":"H4C 2G3",
    "sg:province":"QC",
    "sg:tags":[
        "seafood"
    ],
    "wof:name":"Poissonnerie Du Marche Atwater",
    "wof:placetype":"venue"
},
  "geometry": {"coordinates":[-73.576454,45.479759],"type":"Point"}
}