{
  "type": "Feature",
  "properties": {
    "addr:full":"Little Harbour St New Glasgow NS B2H 5C4",
    "addr:postcode":"b2h 5c4",
    "addr:street":"Little Harbour St",
    "iso:country":"CA",
    "sg:address":"Little Harbour St",
    "sg:city":"New Glasgow",
    "sg:classifiers":[
        {
            "category":"Wholesale",
            "subcategory":"Machinery & Supplies",
            "type":"Manufacturing & Wholesale Goods"
        }
    ],
    "sg:phone":"+1 902 752 4377",
    "sg:postcode":"B2H 5C4",
    "sg:province":"NS",
    "sg:tags":[
        "machine",
        "automobile",
        "shop"
    ],
    "wof:name":"Hemphill Mechanical Svc",
    "wof:placetype":"venue"
},
  "geometry": {"coordinates":[-62.637348,45.593407],"type":"Point"}
}