{
  "type": "Feature",
  "properties": {
    "addr:full":"Princeton ON N0J 1V0",
    "addr:postcode":"n0j 1v0",
    "iso:country":"CA",
    "sg:city":"Princeton",
    "sg:classifiers":[
        {
            "category":"Wholesale",
            "subcategory":"Farm Supplies",
            "type":"Manufacturing & Wholesale Goods"
        }
    ],
    "sg:phone":"+1 519 458 4777",
    "sg:postcode":"N0J 1V0",
    "sg:province":"ON",
    "sg:tags":[
        "livestock"
    ],
    "wof:name":"Ann Govier Livestock Trucking",
    "wof:placetype":"venue"
},
  "geometry": {"coordinates":[-80.5275268555,43.1720085144],"type":"Point"}
}