{
  "type": "Feature",
  "properties": {
    "addr:full":"Highway 1 & 6 Regina SK S4P 3A8",
    "addr:postcode":"s4p 3a8",
    "addr:street":"Highway 1 & 6",
    "iso:country":"CA",
    "sg:address":"Highway 1 & 6",
    "sg:city":"Regina",
    "sg:classifiers":[
        {
            "category":"Autos & Motor Vehicles",
            "subcategory":"Automobile Sales",
            "type":"Retail Goods"
        }
    ],
    "sg:phone":"+1 306 585 1770",
    "sg:postcode":"S4P 3A8",
    "sg:province":"SK",
    "sg:tags":[
        "car",
        "dealer"
    ],
    "wof:name":"Regina Motor Products Ltd",
    "wof:placetype":"venue"
},
  "geometry": {"coordinates":[-104.618149,50.4408],"type":"Point"}
}