{
  "type": "Feature",
  "properties": {
    "addr:full":"1204 Rue King O Sherbrooke QC J1H 1S2",
    "addr:housenumber":"1204",
    "addr:postcode":"j1h 1s2",
    "addr:street":"Rue King O",
    "iso:country":"CA",
    "sg:address":"1204 Rue King O",
    "sg:city":"Sherbrooke",
    "sg:classifiers":[
        {
            "category":"Local Transit",
            "type":"Transportation"
        }
    ],
    "sg:phone":"+1 819 821 3637",
    "sg:postcode":"J1H 1S2",
    "sg:province":"QC",
    "wof:name":"Allo-Stop",
    "wof:placetype":"venue"
},
  "geometry": {"coordinates":[-71.86211400000001,45.408401],"type":"Point"}
}