{
  "type": "Feature",
  "properties": {
    "addr:full":"4948 Ch Queen-Mary Montreal QC H3W 1X2",
    "addr:housenumber":"4948",
    "addr:postcode":"h3w 1x2",
    "addr:street":"Ch Queen-Mary",
    "iso:country":"CA",
    "sg:address":"4948 Ch Queen-Mary",
    "sg:city":"Montreal",
    "sg:classifiers":[
        {
            "category":"Shopping",
            "subcategory":"Department Store",
            "type":"Retail Goods"
        }
    ],
    "sg:phone":"+1 514 342 6966",
    "sg:postcode":"H3W 1X2",
    "sg:province":"QC",
    "sg:tags":[
        "shop",
        "variety"
    ],
    "wof:name":"Dollartisanat Inc",
    "wof:placetype":"venue"
},
  "geometry": {"coordinates":[-73.62647247309999,45.4864959717],"type":"Point"}
}