{
  "type": "Feature",
  "properties": {
    "addr:full":"688 Rue Du Conseil Sherbrooke QC J1G 1K6",
    "addr:housenumber":"688",
    "addr:postcode":"j1g 1k6",
    "addr:street":"Rue Du Conseil",
    "iso:country":"CA",
    "sg:address":"688 Rue Du Conseil",
    "sg:city":"Sherbrooke",
    "sg:classifiers":[
        {
            "category":"Shopping",
            "subcategory":"Clothing, Apparel, & Fashions",
            "type":"Retail Goods"
        }
    ],
    "sg:phone":"+1 819 563 4577",
    "sg:postcode":"J1G 1K6",
    "sg:province":"QC",
    "sg:tags":[
        "boutique",
        "furnishing"
    ],
    "wof:name":"Boutique Skaro",
    "wof:placetype":"venue"
},
  "geometry": {"coordinates":[-71.873901,45.403564],"type":"Point"}
}