{
  "type": "Feature",
  "properties": {
    "addr:full":"2190 Rue Dessaulles Saint-Hyacinthe QC J2S 2T6",
    "addr:housenumber":"2190",
    "addr:postcode":"j2s 2t6",
    "addr:street":"Rue Dessaulles",
    "iso:country":"CA",
    "sg:address":"2190 Rue Dessaulles",
    "sg:city":"Saint-Hyacinthe",
    "sg:classifiers":[
        {
            "category":"Food & Beverages",
            "subcategory":"Groceries & Convenience Stores",
            "type":"Retail Goods"
        }
    ],
    "sg:phone":"+1 450 778 5558",
    "sg:postcode":"J2S 2T6",
    "sg:province":"QC",
    "sg:tags":[
        "grocer"
    ],
    "wof:name":"Marche Dessaules",
    "wof:placetype":"venue"
},
  "geometry": {"coordinates":[-72.952431,45.624531],"type":"Point"}
}