{
  "type": "Feature",
  "properties": {
    "addr:full":"Vancouver BC V5W 2S8",
    "addr:postcode":"v5w 2s8",
    "iso:country":"CA",
    "sg:city":"Vancouver",
    "sg:classifiers":[
        {
            "category":"Autos & Motor Vehicles",
            "subcategory":"Fuel & Gas Station",
            "type":"Retail Goods"
        }
    ],
    "sg:phone":"+1 604 321 7140",
    "sg:postcode":"V5W 2S8",
    "sg:province":"BC",
    "sg:tags":[
        "oil"
    ],
    "wof:name":"Main & 41st Chevron Town",
    "wof:placetype":"venue"
},
  "geometry": {"coordinates":[-123.099975586,49.2850914001],"type":"Point"}
}