{
  "type": "Feature",
  "properties": {
    "iso:country":"CA",
    "sg:address":"852 Rue Bosse",
    "sg:city":"Baie-Comeau",
    "sg:classifiers":[
        {
            "category":"Manufacturing",
            "subcategory":"Tools & Machinery",
            "type":"Manufacturing & Wholesale Goods"
        }
    ],
    "sg:phone":"+1 418 589 6666",
    "sg:postcode":"G5C 1L6",
    "sg:province":"QC",
    "sg:tags":[
        "machine",
        "equipment",
        "computer",
        "dealer",
        "copying"
    ],
    "wof:name":"Pci",
    "wof:placetype":"venue"
},
  "geometry": {"coordinates":[-68.2580490112,49.1929969788],"type":"Point"}
}