{
  "type": "Feature",
  "properties": {
    "iso:country":"CA",
    "sg:address":"252 Adelaide St E",
    "sg:city":"Toronto",
    "sg:classifiers":[
        {
            "category":"Parking",
            "type":"Transportation"
        }
    ],
    "sg:phone":"+1 416 364 1351",
    "sg:postcode":"M5A 1N1",
    "sg:province":"ON",
    "sg:tags":[
        "garage"
    ],
    "wof:name":"Frank Valet Parking",
    "wof:placetype":"venue"
},
  "geometry": {"coordinates":[-79.370949,43.651726],"type":"Point"}
}