{
  "type": "Feature",
  "properties": {
    "addr:full":"61 Highland Ave Newmarket ON L3Y 3H9",
    "addr:housenumber":"61",
    "addr:postcode":"l3y 3h9",
    "addr:street":"Highland Ave",
    "iso:country":"CA",
    "sg:address":"61 Highland Ave",
    "sg:city":"Newmarket",
    "sg:classifiers":[
        {
            "category":"Building & Trades",
            "subcategory":"Construction",
            "type":"Services"
        }
    ],
    "sg:phone":"+1 905 836 2611",
    "sg:postcode":"L3Y 3H9",
    "sg:province":"ON",
    "sg:tags":[
        "layer",
        "carpet"
    ],
    "wof:name":"George Rollings Carpet Install",
    "wof:placetype":"venue"
},
  "geometry": {"coordinates":[-79.44278,44.060452],"type":"Point"}
}