{
  "type": "Feature",
  "properties": {
    "iso:country":"CA",
    "sg:address":"21 Brackley Point Rd",
    "sg:city":"Charlottetown",
    "sg:classifiers":[
        {
            "category":"Restaurant",
            "type":"Food & Drink"
        }
    ],
    "sg:phone":"+1 902 566 4641",
    "sg:postcode":"C1A 6Y1",
    "sg:province":"PE",
    "sg:tags":[
        "shop",
        "coffee"
    ],
    "wof:name":"Maid Marians Coffee Shop",
    "wof:placetype":"venue"
},
  "geometry": {"coordinates":[-63.1205329895,46.2598152161],"type":"Point"}
}