{
  "type": "Feature",
  "properties": {
    "addr:full":"538 Rang Notre-Dame Saint-Chrysostome QC J0S 1R0",
    "addr:housenumber":"538",
    "addr:postcode":"j0s 1r0",
    "addr:street":"Rang Notre-Dame",
    "iso:country":"CA",
    "sg:address":"538 Rang Notre-Dame",
    "sg:city":"Saint-Chrysostome",
    "sg:classifiers":[
        {
            "category":"Restaurant",
            "type":"Food & Drink"
        }
    ],
    "sg:phone":"+1 450 826 3821",
    "sg:postcode":"J0S 1R0",
    "sg:province":"QC",
    "sg:tags":[
        "caterer"
    ],
    "wof:name":"Buffet Johanne Dupras",
    "wof:placetype":"venue"
},
  "geometry": {"coordinates":[-73.7607498169,45.1025009155],"type":"Point"}
}