{
  "type": "Feature",
  "properties": {
    "addr:full":"743 Rue Principale Granby QC J2G 2Y6",
    "addr:housenumber":"743",
    "addr:postcode":"j2g 2y6",
    "addr:street":"Rue Principale",
    "iso:country":"CA",
    "sg:address":"743 Rue Principale",
    "sg:city":"Granby",
    "sg:classifiers":[
        {
            "category":"Health Services",
            "subcategory":"Doctor",
            "type":"Services"
        }
    ],
    "sg:phone":"+1 450 375 0903",
    "sg:postcode":"J2G 2Y6",
    "sg:province":"QC",
    "sg:tags":[
        "clinic",
        "dentist"
    ],
    "wof:name":"Centre Dentaire Martin Hogue",
    "wof:placetype":"venue"
},
  "geometry": {"coordinates":[-72.747299,45.41098],"type":"Point"}
}