{
  "type": "Feature",
  "properties": {
    "iso:country":"CA",
    "sg:address":"5805 Whittle Rd #105",
    "sg:city":"Mississauga",
    "sg:classifiers":[
        {
            "category":"Professional",
            "subcategory":"Computer Services",
            "type":"Services"
        }
    ],
    "sg:phone":"+1 905 755 1104",
    "sg:postcode":"L4Z 2J1",
    "sg:province":"ON",
    "sg:tags":[
        "consultant"
    ],
    "wof:name":"Ved Software Svc Inc",
    "wof:placetype":"venue"
},
  "geometry": {"coordinates":[-79.672668457,43.6251525879],"type":"Point"}
}