{
  "type": "Feature",
  "properties": {
    "addr:full":"70 Charterhouse Cres London ON N5W 5V5",
    "addr:housenumber":"70",
    "addr:postcode":"n5w 5v5",
    "addr:street":"Charterhouse Cres",
    "iso:country":"CA",
    "sg:address":"70 Charterhouse Cres",
    "sg:city":"London",
    "sg:classifiers":[
        {
            "category":"Restaurant",
            "type":"Food & Drink"
        }
    ],
    "sg:phone":"+1 519 451 8563",
    "sg:postcode":"N5W 5V5",
    "sg:province":"ON",
    "sg:tags":[
        "club",
        "banquet",
        "rooms"
    ],
    "wof:name":"Maltese Canadian Club",
    "wof:placetype":"venue"
},
  "geometry": {"coordinates":[-81.170692,42.989201],"type":"Point"}
}