{
  "type": "Feature",
  "properties": {
    "addr:full":"5223 Industrial Rd Drayton Valley AB T7A 1R5",
    "addr:housenumber":"5223",
    "addr:postcode":"t7a 1r5",
    "addr:street":"Industrial Rd",
    "iso:country":"CA",
    "sg:address":"5223 Industrial Rd",
    "sg:city":"Drayton Valley",
    "sg:classifiers":[
        {
            "category":"Retail",
            "subcategory":"Auto Repair",
            "type":"Services"
        }
    ],
    "sg:phone":"+1 780 542 4170",
    "sg:postcode":"T7A 1R5",
    "sg:province":"AB",
    "sg:tags":[
        "body",
        "automobile",
        "painting"
    ],
    "wof:name":"Gemini Auto Solutions Inc",
    "wof:placetype":"venue"
},
  "geometry": {"coordinates":[-114.983764648,53.2259254456],"type":"Point"}
}