{
  "type": "Feature",
  "properties": {
    "addr:full":"442 Main St Creighton SK S0P 0A0",
    "addr:housenumber":"442",
    "addr:postcode":"s0p 0a0",
    "addr:street":"Main St",
    "iso:country":"CA",
    "sg:address":"442 Main St",
    "sg:city":"Creighton",
    "sg:classifiers":[
        {
            "category":"Food & Beverages",
            "subcategory":"Liquor & Beverages",
            "type":"Retail Goods"
        }
    ],
    "sg:phone":"+1 306 688 8870",
    "sg:postcode":"S0P 0A0",
    "sg:province":"SK",
    "sg:tags":[
        "store"
    ],
    "wof:name":"Saskatchewan Liquor Stores",
    "wof:placetype":"venue"
},
  "geometry": {"coordinates":[-101.899666,54.757206],"type":"Point"}
}