{
  "type": "Feature",
  "properties": {
    "addr:full":"561 King George Hwy Miramichi NB E1V 1N2",
    "addr:housenumber":"561",
    "addr:postcode":"e1v 1n2",
    "addr:street":"King George Hwy",
    "iso:country":"CA",
    "sg:address":"561 King George Hwy",
    "sg:city":"Miramichi",
    "sg:classifiers":[
        {
            "category":"Real Estate",
            "subcategory":"Real Estate Operator",
            "type":"Services"
        }
    ],
    "sg:phone":"+1 506 622 8064",
    "sg:postcode":"E1V 1N2",
    "sg:province":"NB",
    "sg:tags":[
        "apartment"
    ],
    "wof:name":"Johnson Management",
    "wof:placetype":"venue"
},
  "geometry": {"coordinates":[-65.56804700000001,47.002659],"type":"Point"}
}