{
  "type": "Feature",
  "properties": {
    "iso:country":"CA",
    "sg:address":"340 Spedding Crt",
    "sg:city":"Kelowna",
    "sg:classifiers":[
        {
            "category":"Banks & Credit Unions",
            "subcategory":"Investment Brokerage",
            "type":"Services"
        }
    ],
    "sg:phone":"+1 250 717 8750",
    "sg:postcode":"V1X 7K9",
    "sg:province":"BC",
    "sg:tags":[
        "consultant",
        "planning",
        "financial"
    ],
    "wof:name":"Mc Intyre Investments",
    "wof:placetype":"venue"
},
  "geometry": {"coordinates":[-119.422111511,49.8856010437],"type":"Point"}
}