{
  "type": "Feature",
  "properties": {
    "iso:country":"CA",
    "sg:address":"4911 Northland Dr NW",
    "sg:city":"Calgary",
    "sg:classifiers":[
        {
            "category":"Autos & Motor Vehicles",
            "subcategory":"Auto Supplies",
            "type":"Retail Goods"
        }
    ],
    "sg:phone":"+1 403 286 3386",
    "sg:postcode":"T2L 2K3",
    "sg:province":"AB",
    "sg:tags":[
        "repairing",
        "automobile"
    ],
    "wof:name":"Fountain Tire",
    "wof:placetype":"venue"
},
  "geometry": {"coordinates":[-114.141555786,51.0961837769],"type":"Point"}
}