{
  "type": "Feature",
  "properties": {
    "addr:full":"98 Boul Des Bois-Francs N Victoriaville QC G6P 1E7",
    "addr:housenumber":"98",
    "addr:postcode":"g6p 1e7",
    "addr:street":"Boul Des Bois-Francs N",
    "iso:country":"CA",
    "sg:address":"98 Boul Des Bois-Francs N",
    "sg:city":"Victoriaville",
    "sg:classifiers":[
        {
            "category":"Personal",
            "subcategory":"Tanning Parlor",
            "type":"Services"
        }
    ],
    "sg:phone":"+1 819 751 1222",
    "sg:postcode":"G6P 1E7",
    "sg:province":"QC",
    "sg:tags":[
        "salon"
    ],
    "wof:name":"Punch Eau Soleil",
    "wof:placetype":"venue"
},
  "geometry": {"coordinates":[-71.9532241821,46.0597801208],"type":"Point"}
}