{
  "type": "Feature",
  "properties": {
    "addr:full":"750 Av Thorncrest Dorval QC H9P 2R5",
    "addr:housenumber":"750",
    "addr:postcode":"h9p 2r5",
    "addr:street":"Av Thorncrest",
    "iso:country":"CA",
    "sg:address":"750 Av Thorncrest",
    "sg:city":"Dorval",
    "sg:classifiers":[
        {
            "category":"Government",
            "subcategory":"Office",
            "type":"Public Place"
        }
    ],
    "sg:phone":"+1 514 633 4002",
    "sg:postcode":"H9P 2R5",
    "sg:province":"QC",
    "sg:tags":[
        "village"
    ],
    "wof:name":"Dorval Centre Sportif Westwood",
    "wof:placetype":"venue"
},
  "geometry": {"coordinates":[-73.76417499999999,45.456573],"type":"Point"}
}