{
  "type": "Feature",
  "properties": {
    "addr:full":"689 Topsail Rd St. John's NL A1E 2E3",
    "addr:housenumber":"689",
    "addr:postcode":"a1e 2e3",
    "addr:street":"Topsail Rd",
    "iso:country":"CA",
    "sg:address":"689 Topsail Rd",
    "sg:city":"St. John's",
    "sg:classifiers":[
        {
            "category":"Government",
            "subcategory":"Office",
            "type":"Public Place"
        }
    ],
    "sg:phone":"+1 709 772 5322",
    "sg:postcode":"A1E 2E3",
    "sg:province":"NL",
    "wof:name":"Canada Labour",
    "wof:placetype":"venue"
},
  "geometry": {"coordinates":[-52.776386,47.523136],"type":"Point"}
}