{
  "type": "Feature",
  "properties": {
    "iso:country":"CA",
    "sg:address":"715 Wellington Rd # B",
    "sg:city":"London",
    "sg:classifiers":[
        {
            "category":"Restaurant",
            "type":"Food & Drink"
        }
    ],
    "sg:phone":"+1 519 668 7407",
    "sg:postcode":"N6C 4R4",
    "sg:province":"ON",
    "wof:name":"Shiki Japanese Restaurants",
    "wof:placetype":"venue"
},
  "geometry": {"coordinates":[-81.228065,42.948219],"type":"Point"}
}