{
  "type": "Feature",
  "properties": {
    "addr:full":"1639 Rosser Ave Brandon MB R7A 0M9",
    "addr:housenumber":"1639",
    "addr:postcode":"r7a 0m9",
    "addr:street":"Rosser Ave",
    "iso:country":"CA",
    "sg:address":"1639 Rosser Ave",
    "sg:city":"Brandon",
    "sg:classifiers":[
        {
            "category":"Shopping",
            "subcategory":"Computers & Home Electronics",
            "type":"Retail Goods"
        }
    ],
    "sg:phone":"+1 204 728 1232",
    "sg:postcode":"R7A 0M9",
    "sg:province":"MB",
    "sg:tags":[
        "equipment",
        "television",
        "satellite",
        "system"
    ],
    "wof:name":"Television City",
    "wof:placetype":"venue"
},
  "geometry": {"coordinates":[-99.9601898193,49.8486785889],"type":"Point"}
}