{
  "type": "Feature",
  "properties": {
    "addr:full":"80 King St Moncton NB E1C 4M6",
    "addr:housenumber":"80",
    "addr:postcode":"e1c 4m6",
    "addr:street":"King St",
    "iso:country":"CA",
    "sg:address":"80 King St",
    "sg:city":"Moncton",
    "sg:classifiers":[
        {
            "category":"Autos & Motor Vehicles",
            "subcategory":"Motorcycle Sales",
            "type":"Retail Goods"
        }
    ],
    "sg:phone":"+1 506 382 0262",
    "sg:postcode":"E1C 4M6",
    "sg:province":"NB",
    "sg:tags":[
        "scooter"
    ],
    "wof:name":"Adriaan's Cycle Svc",
    "wof:placetype":"venue"
},
  "geometry": {"coordinates":[-64.7709197998,46.0923690796],"type":"Point"}
}