{
  "type": "Feature",
  "properties": {
    "iso:country":"CA",
    "sg:address":"652 Queen St W",
    "sg:city":"Toronto",
    "sg:classifiers":[
        {
            "category":"Restaurant",
            "type":"Food & Drink"
        }
    ],
    "sg:phone":"+1 416 504 0433",
    "sg:postcode":"M6J 1E5",
    "sg:province":"ON",
    "sg:tags":[
        "shop",
        "coffee"
    ],
    "wof:name":"Second Cup",
    "wof:placetype":"venue"
},
  "geometry": {"coordinates":[-79.4067230225,43.6467247009],"type":"Point"}
}