{
  "type": "Feature",
  "properties": {
    "addr:full":"2251 Ridgemount Stevensville ON L0S 1S0",
    "addr:housenumber":"2251",
    "addr:postcode":"l0s 1s0",
    "addr:street":"Ridgemount",
    "iso:country":"CA",
    "sg:address":"2251 Ridgemount",
    "sg:city":"Stevensville",
    "sg:classifiers":[
        {
            "category":"Organizations",
            "subcategory":"Religious Organization",
            "type":"Services"
        }
    ],
    "sg:phone":"+1 905 382 2608",
    "sg:postcode":"L0S 1S0",
    "sg:province":"ON",
    "sg:tags":[
        "church"
    ],
    "wof:name":"St John's Anglican Church",
    "wof:placetype":"venue"
},
  "geometry": {"coordinates":[-79.0546722412,42.9437065125],"type":"Point"}
}