{
  "type": "Feature",
  "properties": {
    "addr:full":"10084 164 St NW Edmonton AB T5P 4Y3",
    "addr:housenumber":"10084",
    "addr:postcode":"t5p 4y3",
    "addr:street":"164 St Nw",
    "iso:country":"CA",
    "sg:address":"10084 164 St NW",
    "sg:city":"Edmonton",
    "sg:classifiers":[
        {
            "category":"Health Services",
            "subcategory":"Clinic",
            "type":"Services"
        }
    ],
    "sg:phone":"+1 780 487 7995",
    "sg:postcode":"T5P 4Y3",
    "sg:province":"AB",
    "sg:tags":[
        "herbalist"
    ],
    "wof:name":"Kieler's Health & Herbal",
    "wof:placetype":"venue"
},
  "geometry": {"coordinates":[-113.604759,53.540859],"type":"Point"}
}