{
  "type": "Feature",
  "properties": {
    "addr:full":"Trois-Rivieres-Ouest QC G8Y 6S6",
    "addr:postcode":"g8y 6s6",
    "iso:country":"CA",
    "sg:city":"Trois-Rivieres-Ouest",
    "sg:classifiers":[
        {
            "category":"Health Services",
            "subcategory":"Health Practitioner",
            "type":"Services"
        }
    ],
    "sg:phone":"+1 819 372 5199",
    "sg:postcode":"G8Y 6S6",
    "sg:province":"QC",
    "sg:tags":[
        "psychologist"
    ],
    "wof:name":"Marcoux, Lucie PhD",
    "wof:placetype":"venue"
},
  "geometry": {"coordinates":[-72.6082992554,46.3384094238],"type":"Point"}
}