{
  "type": "Feature",
  "properties": {
    "iso:country":"CA",
    "sg:address":"9 Rue DE L'Artisan",
    "sg:city":"Victoriaville",
    "sg:classifiers":[
        {
            "category":"Wholesale",
            "subcategory":"Photographic Equipment",
            "type":"Manufacturing & Wholesale Goods"
        }
    ],
    "sg:phone":"+1 819 758 3532",
    "sg:postcode":"G6P 9S9",
    "sg:province":"QC",
    "sg:tags":[
        "motion",
        "picture",
        "supply"
    ],
    "wof:name":"Entreprises Michel Prince",
    "wof:placetype":"venue"
},
  "geometry": {"coordinates":[-71.9602508545,46.0712738037],"type":"Point"}
}