{
  "type": "Feature",
  "properties": {
    "iso:country":"CA",
    "sg:city":"New Westminster",
    "sg:classifiers":[
        {
            "category":"Government",
            "subcategory":"Office",
            "type":"Public Place"
        }
    ],
    "sg:phone":"+1 604 660 6222",
    "sg:postcode":"V3L 5B3",
    "sg:province":"BC",
    "wof:name":"B C Electrical Safety Program",
    "wof:placetype":"venue"
},
  "geometry": {"coordinates":[-122.910332,49.205006],"type":"Point"}
}