{
  "type": "Feature",
  "properties": {
    "iso:country":"CA",
    "sg:city":"Calgary",
    "sg:classifiers":[
        {
            "category":"Government",
            "subcategory":"Office",
            "type":"Public Place"
        }
    ],
    "sg:phone":"+1 403 297 8511",
    "sg:postcode":"T2R 1H5",
    "sg:province":"AB",
    "wof:name":"Assured Income For Severly",
    "wof:placetype":"venue"
},
  "geometry": {"coordinates":[-114.071281433,51.0386123657],"type":"Point"}
}