{
  "type": "Feature",
  "properties": {
    "addr:full":"553 Niagara St Welland ON L3C 1L7",
    "addr:housenumber":"553",
    "addr:postcode":"l3c 1l7",
    "addr:street":"Niagara St",
    "iso:country":"CA",
    "sg:address":"553 Niagara St",
    "sg:city":"Welland",
    "sg:classifiers":[
        {
            "category":"Banks & Credit Unions",
            "subcategory":"Investment Brokerage",
            "type":"Services"
        }
    ],
    "sg:phone":"+1 905 732 7555",
    "sg:postcode":"L3C 1L7",
    "sg:province":"ON",
    "wof:name":"Dundee Wealth Mgmt",
    "wof:placetype":"venue"
},
  "geometry": {"coordinates":[-79.252647,43.005878],"type":"Point"}
}