{
  "type": "Feature",
  "properties": {
    "addr:full":"100 Castlefrank Rd Kanata ON K2L 2V6",
    "addr:housenumber":"100",
    "addr:postcode":"k2l 2v6",
    "addr:street":"Castlefrank Rd",
    "iso:country":"CA",
    "sg:address":"100 Castlefrank Rd",
    "sg:city":"Kanata",
    "sg:classifiers":[
        {
            "category":"Recreation",
            "type":"Entertainment"
        }
    ],
    "sg:phone":"+1 613 862 2101",
    "sg:postcode":"K2L 2V6",
    "sg:province":"ON",
    "sg:tags":[
        "martial",
        "arts",
        "instruction"
    ],
    "wof:name":"Kou's Tae Kwon DO & Martial",
    "wof:placetype":"venue"
},
  "geometry": {"coordinates":[-75.881989,45.293484],"type":"Point"}
}