{
  "type": "Feature",
  "properties": {
    "iso:country":"CA",
    "sg:address":"2131 Kingsway Dr",
    "sg:city":"Kitchener",
    "sg:classifiers":[
        {
            "category":"Autos & Motor Vehicles",
            "subcategory":"Automobile Sales",
            "type":"Retail Goods"
        }
    ],
    "sg:phone":"+1 519 893 6580",
    "sg:postcode":"N2C 1A1",
    "sg:province":"ON",
    "sg:tags":[
        "car",
        "dealer"
    ],
    "wof:name":"Durnin Motors",
    "wof:placetype":"venue"
},
  "geometry": {"coordinates":[-80.4536819458,43.4348068237],"type":"Point"}
}