{
  "type": "Feature",
  "properties": {
    "iso:country":"CA",
    "sg:address":"544 Simcoe St",
    "sg:city":"Collingwood",
    "sg:classifiers":[
        {
            "category":"Building & Trades",
            "subcategory":"Construction",
            "type":"Services"
        }
    ],
    "sg:phone":"+1 705 445 5031",
    "sg:postcode":"L9Y 1K1",
    "sg:province":"ON",
    "sg:tags":[
        "painter"
    ],
    "wof:name":"Glenn Parr Painting",
    "wof:placetype":"venue"
},
  "geometry": {"coordinates":[-80.20431518549999,44.5055809021],"type":"Point"}
}