{
  "type": "Feature",
  "properties": {
    "addr:full":"Campbell's Bay QC J0X 1K0",
    "addr:postcode":"j0x 1k0",
    "addr:street":"Bay",
    "iso:country":"CA",
    "sg:city":"Campbell's Bay",
    "sg:classifiers":[
        {
            "category":"Retail",
            "subcategory":"Portrait Studio",
            "type":"Services"
        }
    ],
    "sg:phone":"+1 819 648 5537",
    "sg:postcode":"J0X 1K0",
    "sg:province":"QC",
    "sg:tags":[
        "photographer"
    ],
    "wof:name":"Studio Andree",
    "wof:placetype":"venue"
},
  "geometry": {"coordinates":[-76.5992279053,45.740322113],"type":"Point"}
}