{
  "type": "Feature",
  "properties": {
    "addr:full":"924 King St Midland ON L4R 4L3",
    "addr:housenumber":"924",
    "addr:postcode":"l4r 4l3",
    "addr:street":"King St",
    "iso:country":"CA",
    "sg:address":"924 King St",
    "sg:city":"Midland",
    "sg:classifiers":[
        {
            "category":"Travel",
            "subcategory":"Hotels & Motels",
            "type":"Entertainment"
        }
    ],
    "sg:phone":"+1 705 526 9307",
    "sg:postcode":"L4R 4L3",
    "sg:province":"ON",
    "wof:name":"Best Western Highland Inn",
    "wof:placetype":"venue"
},
  "geometry": {"coordinates":[-79.869675,44.731323],"type":"Point"}
}