{
  "type": "Feature",
  "properties": {
    "addr:full":"484 Rue DE Frontenac Berthierville QC J0K 1A0",
    "addr:housenumber":"484",
    "addr:postcode":"j0k 1a0",
    "addr:street":"Rue De Frontenac",
    "iso:country":"CA",
    "sg:address":"484 Rue DE Frontenac",
    "sg:city":"Berthierville",
    "sg:classifiers":[
        {
            "category":"Shopping",
            "subcategory":"Computers & Home Electronics",
            "type":"Retail Goods"
        }
    ],
    "sg:phone":"+1 450 836 6132",
    "sg:postcode":"J0K 1A0",
    "sg:province":"QC",
    "sg:tags":[
        "equipment",
        "dealer"
    ],
    "wof:name":"Jmc Informatique",
    "wof:placetype":"venue"
},
  "geometry": {"coordinates":[-73.17181396479999,46.0841598511],"type":"Point"}
}