{
  "type": "Feature",
  "properties": {
    "iso:country":"CA",
    "sg:city":"Mississauga",
    "sg:classifiers":[
        {
            "category":"Home & Garden",
            "subcategory":"Home Furnishings",
            "type":"Retail Goods"
        }
    ],
    "sg:phone":"+1 905 507 9782",
    "sg:postcode":"L5R 4B8",
    "sg:province":"ON",
    "sg:tags":[
        "curtain",
        "made",
        "drapery"
    ],
    "wof:name":"Covers Window & Bed",
    "wof:placetype":"venue"
},
  "geometry": {"coordinates":[-79.686752,43.611389],"type":"Point"}
}