{
  "type": "Feature",
  "properties": {
    "addr:full":"11585 Av Philippe-Panneton Montreal QC H1E 4M1",
    "addr:postcode":"h1e 4m1",
    "addr:street":"Av Philippe-Panneton",
    "iso:country":"CA",
    "sg:address":"11585 Av Philippe-Panneton",
    "sg:city":"Montreal",
    "sg:classifiers":[
        {
            "category":"Manufacturing",
            "subcategory":"Printing",
            "type":"Manufacturing & Wholesale Goods"
        }
    ],
    "sg:phone":"+1 514 648 0202",
    "sg:postcode":"H1E 4M1",
    "sg:province":"QC",
    "sg:tags":[
        "printer"
    ],
    "wof:name":"Imprimerie Dimar Printing",
    "wof:placetype":"venue"
},
  "geometry": {"coordinates":[-73.59607699999999,45.62191],"type":"Point"}
}