{
  "type": "Feature",
  "properties": {
    "addr:full":"421 Grand Ave E Chatham ON N7L 1X4",
    "addr:housenumber":"421",
    "addr:postcode":"n7l 1x4",
    "addr:street":"Grand Ave E",
    "iso:country":"CA",
    "sg:address":"421 Grand Ave E",
    "sg:city":"Chatham",
    "sg:classifiers":[
        {
            "category":"Travel",
            "subcategory":"Hotels & Motels",
            "type":"Entertainment"
        }
    ],
    "sg:phone":"+1 519 354 5130",
    "sg:postcode":"N7L 1X4",
    "sg:province":"ON",
    "wof:name":"Flamingo Motel",
    "wof:placetype":"venue"
},
  "geometry": {"coordinates":[-82.17557499999999,42.417988],"type":"Point"}
}