{
  "type": "Feature",
  "properties": {
    "addr:full":"Hwy 621 Morson ON P0W 1J0",
    "addr:postcode":"p0w 1j0",
    "addr:street":"Hwy 621",
    "iso:country":"CA",
    "sg:address":"Hwy 621",
    "sg:city":"Morson",
    "sg:classifiers":[
        {
            "category":"Food & Beverages",
            "subcategory":"Groceries & Convenience Stores",
            "type":"Retail Goods"
        }
    ],
    "sg:phone":"+1 807 488 9637",
    "sg:postcode":"P0W 1J0",
    "sg:province":"ON",
    "wof:name":"Zig's Place",
    "wof:placetype":"venue"
},
  "geometry": {"coordinates":[-94.2881317139,49.1262054443],"type":"Point"}
}