{
  "type": "Feature",
  "properties": {
    "addr:full":"2636 Innes Rd Gloucester ON K1B 4Z5",
    "addr:housenumber":"2636",
    "addr:postcode":"k1b 4z5",
    "addr:street":"Innes Rd",
    "iso:country":"CA",
    "sg:address":"2636 Innes Rd",
    "sg:city":"Gloucester",
    "sg:classifiers":[
        {
            "category":"Food & Beverages",
            "subcategory":"Groceries & Convenience Stores",
            "type":"Retail Goods"
        }
    ],
    "sg:phone":"+1 613 837 1845",
    "sg:postcode":"K1B 4Z5",
    "sg:province":"ON",
    "sg:tags":[
        "grocer"
    ],
    "wof:name":"Loeb Blackburn Hamlet",
    "wof:placetype":"venue"
},
  "geometry": {"coordinates":[-75.5638122559,45.4318351746],"type":"Point"}
}