{
  "type": "Feature",
  "properties": {
    "addr:full":"390 Av Bethany Lachute QC J8H 4G8",
    "addr:postcode":"j8h 4g8",
    "addr:street":"390 Av Bethany",
    "iso:country":"CA",
    "sg:address":"390 Av Bethany",
    "sg:city":"Lachute",
    "sg:classifiers":[
        {
            "category":"Social Services",
            "subcategory":"Job Training",
            "type":"Services"
        }
    ],
    "sg:phone":"+1 450 562 8563",
    "sg:postcode":"J8H 4G8",
    "sg:province":"QC",
    "sg:tags":[
        "rehabilitation"
    ],
    "wof:name":"Centre Du Flores",
    "wof:placetype":"venue"
},
  "geometry": {"coordinates":[-74.328789,45.642914],"type":"Point"}
}