{
  "type": "Feature",
  "properties": {
    "addr:full":"9595 Rue Ignace Brossard QC J4Y 2P3",
    "addr:housenumber":"9595",
    "addr:postcode":"j4y 2p3",
    "addr:street":"Rue Ignace",
    "iso:country":"CA",
    "sg:address":"9595 Rue Ignace",
    "sg:city":"Brossard",
    "sg:classifiers":[
        {
            "category":"Building & Trades",
            "subcategory":"Electrical",
            "type":"Services"
        }
    ],
    "sg:phone":"+1 450 659 9641",
    "sg:postcode":"J4Y 2P3",
    "sg:province":"QC",
    "sg:tags":[
        "electric",
        "contractor"
    ],
    "wof:name":"Pierre Brossard Ltee",
    "wof:placetype":"venue"
},
  "geometry": {"coordinates":[-73.4755859375,45.4316101074],"type":"Point"}
}