{
  "type": "Feature",
  "properties": {
    "iso:country":"CA",
    "sg:city":"Paspebiac",
    "sg:classifiers":[
        {
            "category":"Professional",
            "subcategory":"Business Services",
            "type":"Services"
        }
    ],
    "sg:phone":"+1 418 393 3344",
    "sg:postcode":"G0C 2K0",
    "sg:province":"QC",
    "sg:tags":[
        "notary"
    ],
    "wof:name":"Moulin & Moulin",
    "wof:placetype":"venue"
},
  "geometry": {"coordinates":[-65.24885559080001,48.0643539429],"type":"Point"}
}