{
  "type": "Feature",
  "properties": {
    "addr:full":"5014 50 St Beaumont AB T4X 1E5",
    "addr:housenumber":"5014",
    "addr:postcode":"t4x 1e5",
    "addr:street":"50 St",
    "iso:country":"CA",
    "sg:address":"5014 50 St",
    "sg:city":"Beaumont",
    "sg:classifiers":[
        {
            "category":"Restaurant",
            "type":"Food & Drink"
        }
    ],
    "sg:phone":"+1 780 929 2499",
    "sg:postcode":"T4X 1E5",
    "sg:province":"AB",
    "wof:name":"Basile's 2 For 1 Pizza & Pasta",
    "wof:placetype":"venue"
},
  "geometry": {"coordinates":[-113.41543579099999,53.3527793884],"type":"Point"}
}