{
  "type": "Feature",
  "properties": {
    "addr:full":"Vancouver BC V6K 3J3",
    "addr:postcode":"v6k 3j3",
    "iso:country":"CA",
    "sg:city":"Vancouver",
    "sg:classifiers":[
        {
            "category":"Professional",
            "subcategory":"Management & Consulting",
            "type":"Services"
        }
    ],
    "sg:phone":"+1 604 730 8866",
    "sg:postcode":"V6K 3J3",
    "sg:province":"BC",
    "sg:tags":[
        "consultant",
        "business"
    ],
    "wof:name":"Equus Consulting",
    "wof:placetype":"venue"
},
  "geometry": {"coordinates":[-123.157524,49.271454],"type":"Point"}
}