{
  "type": "Feature",
  "properties": {
    "addr:full":"75 Av Marcoux Beauport QC G1E 3B3",
    "addr:postcode":"qc g1e 3b3",
    "addr:street":"75 Av Marcoux",
    "iso:country":"CA",
    "sg:address":"75 Av Marcoux",
    "sg:city":"Beauport",
    "sg:classifiers":[
        {
            "category":"Shopping",
            "subcategory":"Stationery & Office Supplies",
            "type":"Retail Goods"
        }
    ],
    "sg:phone":"+1 418 667 6094",
    "sg:postcode":"G1E 3B3",
    "sg:province":"QC",
    "sg:tags":[
        "stationer"
    ],
    "wof:name":"Centre Du Classeur Enr",
    "wof:placetype":"venue"
},
  "geometry": {"coordinates":[-71.18407440190001,46.8589515686],"type":"Point"}
}