{
  "type": "Feature",
  "properties": {
    "addr:full":"210 Boul DE Montarville Boucherville QC J4B 6T3",
    "addr:housenumber":"210",
    "addr:postcode":"j4b 6t3",
    "addr:street":"Boul De Montarville",
    "iso:country":"CA",
    "sg:address":"210 Boul DE Montarville",
    "sg:city":"Boucherville",
    "sg:classifiers":[
        {
            "category":"Organizations",
            "subcategory":"Labor Organization",
            "type":"Services"
        }
    ],
    "sg:phone":"+1 450 449 9630",
    "sg:postcode":"J4B 6T3",
    "sg:province":"QC",
    "wof:name":"Syndicat Professionel Des",
    "wof:placetype":"venue"
},
  "geometry": {"coordinates":[-73.45101200000001,45.602074],"type":"Point"}
}