{
  "type": "Feature",
  "properties": {
    "addr:full":"1860 Rue Commerciale Saint-Francois-DE-Madawaska NB E7A 1A7",
    "addr:housenumber":"1860",
    "addr:postcode":"e7a 1a7",
    "addr:street":"Rue Commerciale;Nb",
    "iso:country":"CA",
    "sg:address":"1860 Rue Commerciale",
    "sg:city":"Saint-Francois-DE-Madawaska",
    "sg:classifiers":[
        {
            "category":"Insurance",
            "subcategory":"Insurance Agent",
            "type":"Services"
        }
    ],
    "sg:phone":"+1 506 992 2914",
    "sg:postcode":"E7A 1A7",
    "sg:province":"NB",
    "wof:name":"Beaupre Laurent Inc",
    "wof:placetype":"venue"
},
  "geometry": {"coordinates":[-68.7097625732,47.2437973022],"type":"Point"}
}