{
  "type": "Feature",
  "properties": {
    "addr:full":"1609 Connrose Ave Halifax NS B3H 4C4",
    "addr:housenumber":"1609",
    "addr:postcode":"b3h 4c4",
    "addr:street":"Connrose Ave",
    "iso:country":"CA",
    "sg:address":"1609 Connrose Ave",
    "sg:city":"Halifax",
    "sg:classifiers":[
        {
            "category":"Professional",
            "subcategory":"Business Services",
            "type":"Services"
        }
    ],
    "sg:phone":"+1 902 491 1778",
    "sg:postcode":"B3H 4C4",
    "sg:province":"NS",
    "sg:tags":[
        "arbitration"
    ],
    "wof:name":"Arbitrator & Mediator",
    "wof:placetype":"venue"
},
  "geometry": {"coordinates":[-63.599976,44.638397],"type":"Point"}
}