{
  "type": "Feature",
  "properties": {
    "addr:full":"1 Viewmount Ave North York ON M6B 1T2",
    "addr:housenumber":"1",
    "addr:postcode":"m6b 1t2",
    "addr:street":"Viewmount Ave",
    "iso:country":"CA",
    "sg:address":"1 Viewmount Ave",
    "sg:city":"North York",
    "sg:classifiers":[
        {
            "category":"Restaurant",
            "type":"Food & Drink"
        }
    ],
    "sg:phone":"+1 416 781 3062",
    "sg:postcode":"M6B 1T2",
    "sg:province":"ON",
    "sg:tags":[
        "caterer"
    ],
    "wof:name":"Jacobs Caterers",
    "wof:placetype":"venue"
},
  "geometry": {"coordinates":[-79.42787199999999,43.710281],"type":"Point"}
}