{
  "type": "Feature",
  "properties": {
    "addr:full":"7015 90 Ave NW Edmonton AB T6B 0P3",
    "addr:housenumber":"7015",
    "addr:postcode":"t6b 0p3",
    "addr:street":"90 Ave Nw",
    "iso:country":"CA",
    "sg:address":"7015 90 Ave NW",
    "sg:city":"Edmonton",
    "sg:classifiers":[
        {
            "category":"Retail",
            "subcategory":"Auto Repair",
            "type":"Services"
        }
    ],
    "sg:phone":"+1 780 466 5497",
    "sg:postcode":"T6B 0P3",
    "sg:province":"AB",
    "sg:tags":[
        "repairing",
        "automobile"
    ],
    "wof:name":"Brandsma Auto Svc Ltd",
    "wof:placetype":"venue"
},
  "geometry": {"coordinates":[-113.434532,53.524963],"type":"Point"}
}