{
  "type": "Feature",
  "properties": {
    "addr:full":"22 Pinebush Rd Cambridge ON N1R 8K5",
    "addr:housenumber":"22",
    "addr:postcode":"n1r 8k5",
    "addr:street":"Pinebush Rd",
    "iso:country":"CA",
    "sg:address":"22 Pinebush Rd",
    "sg:city":"Cambridge",
    "sg:classifiers":[
        {
            "category":"Travel",
            "subcategory":"Travel Agent",
            "type":"Entertainment"
        }
    ],
    "sg:phone":"+1 519 622 6599",
    "sg:postcode":"N1R 8K5",
    "sg:province":"ON",
    "sg:tags":[
        "agency",
        "bureau"
    ],
    "wof:name":"Marlin Travel",
    "wof:placetype":"venue"
},
  "geometry": {"coordinates":[-80.32652299999999,43.408405],"type":"Point"}
}