{
  "type": "Feature",
  "properties": {
    "addr:full":"8655 Boul Perras Montreal QC H1E 4M7",
    "addr:housenumber":"8655",
    "addr:postcode":"h1e 4m7",
    "addr:street":"Boul Perras",
    "iso:country":"CA",
    "sg:address":"8655 Boul Perras",
    "sg:city":"Montreal",
    "sg:classifiers":[
        {
            "category":"Social Services",
            "type":"Services"
        }
    ],
    "sg:phone":"+1 514 494 4924",
    "sg:postcode":"H1E 4M7",
    "sg:province":"QC",
    "sg:tags":[
        "organization",
        "welfare"
    ],
    "wof:name":"Clsc Riviere Des Prairies",
    "wof:placetype":"venue"
},
  "geometry": {"coordinates":[-73.585793,45.644493],"type":"Point"}
}