{
  "type": "Feature",
  "properties": {
    "addr:full":"12810 111 Ave NW Edmonton AB T5M 2N7",
    "addr:housenumber":"12810",
    "addr:postcode":"t5m 2n7",
    "addr:street":"111 Ave Nw",
    "iso:country":"CA",
    "sg:address":"12810 111 Ave NW",
    "sg:city":"Edmonton",
    "sg:classifiers":[
        {
            "category":"Organizations",
            "subcategory":"Religious Organization",
            "type":"Services"
        }
    ],
    "sg:phone":"+1 780 451 6601",
    "sg:postcode":"T5M 2N7",
    "sg:province":"AB",
    "sg:tags":[
        "church"
    ],
    "wof:name":"St Andrew Roman Catholic Chr",
    "wof:placetype":"venue"
},
  "geometry": {"coordinates":[-113.54317500000001,53.559128],"type":"Point"}
}