{
  "type": "Feature",
  "properties": {
    "addr:full":"4185 Conc 7 Windsor ON N9A 6J3",
    "addr:housenumber":"4185;7",
    "addr:postcode":"n9a 6j3",
    "addr:street":"Conc",
    "iso:country":"CA",
    "sg:address":"4185 Conc 7",
    "sg:city":"Windsor",
    "sg:classifiers":[
        {
            "category":"Building & Trades",
            "subcategory":"Plumbing",
            "type":"Services"
        }
    ],
    "sg:phone":"+1 519 969 7822",
    "sg:postcode":"N9A 6J3",
    "sg:province":"ON",
    "sg:tags":[
        "electric",
        "contractor"
    ],
    "wof:name":"Fahrhall Mechanical Contrs Ltd",
    "wof:placetype":"venue"
},
  "geometry": {"coordinates":[-82.962341,42.258072],"type":"Point"}
}