{
  "type": "Feature",
  "properties": {
    "addr:full":"115 Main St Hazlet SK S0N 1E0",
    "addr:housenumber":"115",
    "addr:postcode":"s0n 1e0",
    "addr:street":"Main St",
    "iso:country":"CA",
    "sg:address":"115 Main St",
    "sg:city":"Hazlet",
    "sg:classifiers":[
        {
            "category":"Government",
            "subcategory":"Post Office",
            "type":"Public Place"
        }
    ],
    "sg:phone":"+1 306 678 2202",
    "sg:postcode":"S0N 1E0",
    "sg:province":"SK",
    "wof:name":"Canada Post-Hazlet",
    "wof:placetype":"venue"
},
  "geometry": {"coordinates":[-108.595268249,50.3979949951],"type":"Point"}
}