{
  "type": "Feature",
  "properties": {
    "iso:country":"CA",
    "sg:address":"3330 Henderson Rd",
    "sg:city":"Pinantan Lake",
    "sg:classifiers":[
        {
            "category":"Building & Trades",
            "subcategory":"Electrical",
            "type":"Services"
        }
    ],
    "sg:phone":"+1 250 573 3607",
    "sg:postcode":"V0E 3E1",
    "sg:province":"BC",
    "sg:tags":[
        "electric",
        "contractor"
    ],
    "wof:name":"Terry's Electric",
    "wof:placetype":"venue"
},
  "geometry": {"coordinates":[-120.01438140899999,50.7159805298],"type":"Point"}
}