{
  "type": "Feature",
  "properties": {
    "addr:full":"48 Centrepointe Dr Nepean ON K2G 6J5",
    "addr:housenumber":"48",
    "addr:postcode":"k2g 6j5",
    "addr:street":"Centrepointe Dr",
    "iso:country":"CA",
    "sg:address":"48 Centrepointe Dr",
    "sg:city":"Nepean",
    "sg:classifiers":[
        {
            "category":"Health Services",
            "subcategory":"Health Practitioner",
            "type":"Services"
        }
    ],
    "sg:phone":"+1 613 224 3300",
    "sg:postcode":"K2G 6J5",
    "sg:province":"ON",
    "sg:tags":[
        "acupuncture"
    ],
    "wof:name":"O C Massage & Acupuncture Ctr",
    "wof:placetype":"venue"
},
  "geometry": {"coordinates":[-75.767319,45.347073],"type":"Point"}
}