{
  "type": "Feature",
  "properties": {
    "addr:full":"611 Wellington Ave Windsor ON N9A 5J5",
    "addr:housenumber":"611",
    "addr:postcode":"n9a 5j5",
    "addr:street":"Wellington Ave",
    "iso:country":"CA",
    "sg:address":"611 Wellington Ave",
    "sg:city":"Windsor",
    "sg:classifiers":[
        {
            "category":"Food & Beverages",
            "subcategory":"Groceries & Convenience Stores",
            "type":"Retail Goods"
        }
    ],
    "sg:phone":"+1 519 254 6333",
    "sg:postcode":"N9A 5J5",
    "sg:province":"ON",
    "sg:tags":[
        "grocer"
    ],
    "wof:name":"J P Fish & Seafoods",
    "wof:placetype":"venue"
},
  "geometry": {"coordinates":[-83.0498352051,42.3091011047],"type":"Point"}
}