{
  "type": "Feature",
  "properties": {
    "addr:full":"732 Queenston Rd Hamilton ON L8G 1A4",
    "addr:housenumber":"732",
    "addr:postcode":"l8g 1a4",
    "addr:street":"Queenston Rd",
    "iso:country":"CA",
    "sg:address":"732 Queenston Rd",
    "sg:city":"Hamilton",
    "sg:classifiers":[
        {
            "category":"Restaurant",
            "type":"Food & Drink"
        }
    ],
    "sg:phone":"+1 905 578 2278",
    "sg:postcode":"L8G 1A4",
    "sg:province":"ON",
    "wof:name":"Mr Sub",
    "wof:placetype":"venue"
},
  "geometry": {"coordinates":[-79.769722,43.229042],"type":"Point"}
}