{
  "type": "Feature",
  "properties": {
    "iso:country":"CA",
    "sg:city":"Mattawa",
    "sg:classifiers":[
        {
            "category":"Local Transit",
            "type":"Transportation"
        }
    ],
    "sg:phone":"+1 705 744 2685",
    "sg:postcode":"P0H 1V0",
    "sg:province":"ON",
    "sg:tags":[
        "bus",
        "line"
    ],
    "wof:name":"Belanger Brownway Bus Lines",
    "wof:placetype":"venue"
},
  "geometry": {"coordinates":[-78.7031555176,46.3177490234],"type":"Point"}
}