{
  "type": "Feature",
  "properties": {
    "addr:full":"82 Boul Cartier Riviere-Du-Loup QC G5R 2M9",
    "addr:housenumber":"82",
    "addr:postcode":"g5r 2m9",
    "addr:street":"Boul Cartier Riviere-Du-Loup",
    "iso:country":"CA",
    "sg:address":"82 Boul Cartier",
    "sg:city":"Riviere-Du-Loup",
    "sg:classifiers":[
        {
            "category":"Professional",
            "subcategory":"Business Services",
            "type":"Services"
        }
    ],
    "sg:phone":"+1 418 862 7587",
    "sg:postcode":"G5R 2M9",
    "sg:province":"QC",
    "sg:tags":[
        "appraiser"
    ],
    "wof:name":"Turmo Estimations Inc",
    "wof:placetype":"venue"
},
  "geometry": {"coordinates":[-69.541168,47.850758],"type":"Point"}
}