{
  "type": "Feature",
  "properties": {
    "addr:full":"313 3rd St W Meadow Lake SK S9X 1C8",
    "addr:housenumber":"313",
    "addr:postcode":"s9x 1c8",
    "addr:street":"3Rd St W Meadow",
    "iso:country":"CA",
    "sg:address":"313 3rd St W",
    "sg:city":"Meadow Lake",
    "sg:classifiers":[
        {
            "category":"Insurance",
            "subcategory":"Insurance Agent",
            "type":"Services"
        }
    ],
    "sg:phone":"+1 306 236 2500",
    "sg:postcode":"S9X 1C8",
    "sg:province":"SK",
    "sg:tags":[
        "government"
    ],
    "wof:name":"Saskatchewan Government Ins",
    "wof:placetype":"venue"
},
  "geometry": {"coordinates":[-108.428116,54.130043],"type":"Point"}
}