{
  "type": "Feature",
  "properties": {
    "addr:full":"2466 Summerset Rd Nanoose Bay BC V9P 9E4",
    "addr:housenumber":"2466",
    "addr:postcode":"v9p 9e4",
    "addr:street":"Summerset Rd",
    "iso:country":"CA",
    "sg:address":"2466 Summerset Rd",
    "sg:city":"Nanoose Bay",
    "sg:classifiers":[
        {
            "category":"Home & Garden",
            "subcategory":"Furniture",
            "type":"Retail Goods"
        }
    ],
    "sg:phone":"+1 250 468 9613",
    "sg:postcode":"V9P 9E4",
    "sg:province":"BC",
    "sg:tags":[
        "equipment",
        "kitchen",
        "cabinet"
    ],
    "wof:name":"Rolmar Manufacturing",
    "wof:placetype":"venue"
},
  "geometry": {"coordinates":[-124.195663,49.259811],"type":"Point"}
}