{
  "type": "Feature",
  "properties": {
    "addr:full":"325 Scott St Fort Frances ON P9A 1H1",
    "addr:housenumber":"325",
    "addr:postcode":"p9a 1h1",
    "addr:street":"Scott St",
    "iso:country":"CA",
    "sg:address":"325 Scott St",
    "sg:city":"Fort Frances",
    "sg:classifiers":[
        {
            "category":"Travel",
            "subcategory":"Hotels & Motels",
            "type":"Entertainment"
        }
    ],
    "sg:phone":"+1 807 274 9874",
    "sg:postcode":"P9A 1H1",
    "sg:province":"ON",
    "wof:name":"Makabi Inn Motel",
    "wof:placetype":"venue"
},
  "geometry": {"coordinates":[-93.3947067261,48.6097946167],"type":"Point"}
}