{
  "type": "Feature",
  "properties": {
    "addr:full":"1050 12E Av N Fleurimont QC J1E 2X3",
    "addr:housenumber":"1050",
    "addr:postcode":"j1e 2x3",
    "addr:street":"12E Av N",
    "iso:country":"CA",
    "sg:address":"1050 12E Av N",
    "sg:city":"Fleurimont",
    "sg:classifiers":[
        {
            "category":"Personal",
            "subcategory":"Beauty Salon",
            "type":"Services"
        }
    ],
    "sg:phone":"+1 819 821 2022",
    "sg:postcode":"J1E 2X3",
    "sg:province":"QC",
    "wof:name":"Salon-Coiffure Clin D'Oeil Enr",
    "wof:placetype":"venue"
},
  "geometry": {"coordinates":[-71.8736877441,45.4229545593],"type":"Point"}
}