{
  "type": "Feature",
  "properties": {
    "addr:full":"32420 Seventh Ave Mission BC V2V 2B5",
    "addr:housenumber":"32420",
    "addr:postcode":"v2v 2b5",
    "addr:street":"Seventh Ave",
    "iso:country":"CA",
    "sg:address":"32420 Seventh Ave",
    "sg:city":"Mission",
    "sg:classifiers":[
        {
            "category":"Organizations",
            "subcategory":"Religious Organization",
            "type":"Services"
        }
    ],
    "sg:phone":"+1 604 826 8587",
    "sg:postcode":"V2V 2B5",
    "sg:province":"BC",
    "sg:tags":[
        "church"
    ],
    "wof:name":"Lutheran Church Mount Calvary",
    "wof:placetype":"venue"
},
  "geometry": {"coordinates":[-122.32710299999999,49.140106],"type":"Point"}
}