{
  "type": "Feature",
  "properties": {
    "addr:full":"15848 106A Ave Surrey BC V4N 1K7",
    "addr:housenumber":"15848",
    "addr:postcode":"v4n 1k7",
    "addr:street":"106A Ave",
    "iso:country":"CA",
    "sg:address":"15848 106A Ave",
    "sg:city":"Surrey",
    "sg:classifiers":[
        {
            "category":"Home & Garden",
            "subcategory":"Building Materials",
            "type":"Retail Goods"
        }
    ],
    "sg:phone":"+1 604 581 7227",
    "sg:postcode":"V4N 1K7",
    "sg:province":"BC",
    "sg:tags":[
        "glass",
        "window",
        "plate"
    ],
    "wof:name":"Dependable Glass",
    "wof:placetype":"venue"
},
  "geometry": {"coordinates":[-122.830215,49.105179],"type":"Point"}
}