{
  "type": "Feature",
  "properties": {
    "addr:full":"1111 Elgin St W # C3 Cobourg ON K9A 5H7",
    "addr:housenumber":"1111",
    "addr:postcode":"k9a 5h7",
    "addr:street":"Elgin St W # C3",
    "iso:country":"CA",
    "sg:address":"1111 Elgin St W # C3",
    "sg:city":"Cobourg",
    "sg:classifiers":[
        {
            "category":"Shopping",
            "subcategory":"Clothing, Apparel, & Fashions",
            "type":"Retail Goods"
        }
    ],
    "sg:phone":"+1 905 372 8349",
    "sg:postcode":"K9A 5H7",
    "sg:province":"ON",
    "wof:name":"Cotton Ginny",
    "wof:placetype":"venue"
},
  "geometry": {"coordinates":[-78.200096,43.97105],"type":"Point"}
}