{
  "type": "Feature",
  "properties": {
    "addr:full":"2401 Boul Jean-Jacques Cossett Val-D'Or QC J9P 6Y3",
    "addr:housenumber":"2401",
    "addr:postcode":"j9p 6y3",
    "addr:street":"Boul Jean-Jacques Cossett",
    "iso:country":"CA",
    "sg:address":"2401 Boul Jean-Jacques Cossett",
    "sg:city":"Val-D'Or",
    "sg:classifiers":[
        {
            "category":"Autos & Motor Vehicles",
            "subcategory":"Fuel & Gas Station",
            "type":"Retail Goods"
        }
    ],
    "sg:phone":"+1 819 825 2850",
    "sg:postcode":"J9P 6Y3",
    "sg:province":"QC",
    "sg:tags":[
        "oil"
    ],
    "wof:name":"Petro-Pass",
    "wof:placetype":"venue"
},
  "geometry": {"coordinates":[-71.003319,45.383507],"type":"Point"}
}