{
  "type": "Feature",
  "properties": {
    "addr:full":"1716 Jane St York ON M9N 2S4",
    "addr:housenumber":"1716",
    "addr:postcode":"m9n 2s4",
    "addr:street":"Jane St",
    "iso:country":"CA",
    "sg:address":"1716 Jane St",
    "sg:city":"York",
    "sg:classifiers":[
        {
            "category":"Shopping",
            "type":"Retail Goods"
        }
    ],
    "sg:phone":"+1 416 241 0998",
    "sg:postcode":"M9N 2S4",
    "sg:province":"ON",
    "sg:tags":[
        "cosmetic",
        "perfume"
    ],
    "wof:name":"Ratina's Beauty Supplies",
    "wof:placetype":"venue"
},
  "geometry": {"coordinates":[-79.504211,43.703751],"type":"Point"}
}