{
  "type": "Feature",
  "properties": {
    "addr:full":"Edmonton AB T5E 4E1",
    "addr:postcode":"t5e 4e1",
    "iso:country":"CA",
    "sg:city":"Edmonton",
    "sg:classifiers":[
        {
            "category":"Restaurant",
            "type":"Food & Drink"
        }
    ],
    "sg:phone":"+1 780 476 8686",
    "sg:postcode":"T5E 4E1",
    "sg:province":"AB",
    "wof:name":"A & W Family Restaurant",
    "wof:placetype":"venue"
},
  "geometry": {"coordinates":[-113.492165,53.59549],"type":"Point"}
}