{
  "type": "Feature",
  "properties": {
    "addr:full":"2724 Barnet Hwy Coquitlam BC V3B 1B8",
    "addr:housenumber":"2724",
    "addr:postcode":"v3b 1b8",
    "addr:street":"Barnet Hwy",
    "iso:country":"CA",
    "sg:address":"2724 Barnet Hwy",
    "sg:city":"Coquitlam",
    "sg:classifiers":[
        {
            "category":"Retail",
            "subcategory":"Auto Repair",
            "type":"Services"
        }
    ],
    "sg:phone":"+1 604 461 4494",
    "sg:postcode":"V3B 1B8",
    "sg:province":"BC",
    "sg:tags":[
        "body",
        "automobile",
        "painting"
    ],
    "wof:name":"Kirmac Collision Svc",
    "wof:placetype":"venue"
},
  "geometry": {"coordinates":[-122.810188,49.277683],"type":"Point"}
}