{
  "type": "Feature",
  "properties": {
    "addr:full":"1770 Rue Notre-Dame Est Sainte-Marthe-Du-Cap QC G8T 4J3",
    "addr:housenumber":"1770",
    "addr:postcode":"g8t 4j3",
    "addr:street":"Rue Notre-Dame Est",
    "iso:country":"CA",
    "sg:address":"1770 Rue Notre-Dame Est",
    "sg:city":"Sainte-Marthe-Du-Cap",
    "sg:classifiers":[
        {
            "category":"Professional",
            "subcategory":"Lawyer & Legal Services",
            "type":"Services"
        }
    ],
    "sg:phone":"+1 819 375 5531",
    "sg:postcode":"G8T 4J3",
    "sg:province":"QC",
    "sg:tags":[
        "attorney"
    ],
    "wof:name":"Page, Louise",
    "wof:placetype":"venue"
},
  "geometry": {"coordinates":[-72.478813,46.385445],"type":"Point"}
}