{
  "type": "Feature",
  "properties": {
    "addr:full":"10 Fasken Dr Etobicoke ON M9W 1K5",
    "addr:housenumber":"10",
    "addr:postcode":"m9w 1k5",
    "addr:street":"Fasken Dr",
    "iso:country":"CA",
    "sg:address":"10 Fasken Dr",
    "sg:city":"Etobicoke",
    "sg:classifiers":[
        {
            "category":"Retail",
            "subcategory":"Auto Repair",
            "type":"Services"
        }
    ],
    "sg:phone":"+1 416 675 7257",
    "sg:postcode":"M9W 1K5",
    "sg:province":"ON",
    "sg:tags":[
        "body",
        "automobile",
        "painting"
    ],
    "wof:name":"Premium Auto Collision Inc",
    "wof:placetype":"venue"
},
  "geometry": {"coordinates":[-79.5990066528,43.6912345886],"type":"Point"}
}