{
  "type": "Feature",
  "properties": {
    "addr:full":"26 St Anne St St Albert AB T8N 1E9",
    "addr:housenumber":"26",
    "addr:postcode":"t8n 1e9",
    "addr:street":"St Anne St",
    "iso:country":"CA",
    "sg:address":"26 St Anne St",
    "sg:city":"St Albert",
    "sg:classifiers":[
        {
            "category":"Education",
            "subcategory":"School",
            "type":"Public Place"
        }
    ],
    "sg:phone":"+1 780 460 8528",
    "sg:postcode":"T8N 1E9",
    "sg:province":"AB",
    "sg:tags":[
        "tutoring"
    ],
    "wof:name":"Sylvan Learning Ctr",
    "wof:placetype":"venue"
},
  "geometry": {"coordinates":[-113.625046,53.635059],"type":"Point"}
}