{
  "type": "Feature",
  "properties": {
    "addr:full":"5804 87 St NW Edmonton AB T6E 2Y4",
    "addr:housenumber":"5804",
    "addr:postcode":"t6e 2y4",
    "addr:street":"87 St Nw",
    "iso:country":"CA",
    "sg:address":"5804 87 St NW",
    "sg:city":"Edmonton",
    "sg:classifiers":[
        {
            "category":"Retail",
            "subcategory":"Repair Shop",
            "type":"Services"
        }
    ],
    "sg:phone":"+1 780 469 6924",
    "sg:postcode":"T6E 2Y4",
    "sg:province":"AB",
    "sg:tags":[
        "welding"
    ],
    "wof:name":"Tempo Industrial Machine Ltd",
    "wof:placetype":"venue"
},
  "geometry": {"coordinates":[-113.458382,53.494259],"type":"Point"}
}