{
  "type": "Feature",
  "properties": {
    "iso:country":"CA",
    "sg:address":"1321 Scarth St",
    "sg:city":"Regina",
    "sg:classifiers":[
        {
            "category":"Wholesale",
            "subcategory":"Machinery & Supplies",
            "type":"Manufacturing & Wholesale Goods"
        }
    ],
    "sg:phone":"+1 306 525 2844",
    "sg:postcode":"S4R 2E7",
    "sg:province":"SK",
    "sg:tags":[
        "equipment",
        "barber"
    ],
    "wof:name":"Peddies Distributors Ltd",
    "wof:placetype":"venue"
},
  "geometry": {"coordinates":[-104.610694885,50.4578704834],"type":"Point"}
}