{
  "type": "Feature",
  "properties": {
    "addr:full":"Goderich ON N7A 3X8",
    "addr:postcode":"n7a 3x8",
    "iso:country":"CA",
    "sg:city":"Goderich",
    "sg:classifiers":[
        {
            "category":"Restaurant",
            "type":"Food & Drink"
        }
    ],
    "sg:phone":"+1 519 524 5135",
    "sg:postcode":"N7A 3X8",
    "sg:province":"ON",
    "wof:name":"Harvey's Plus",
    "wof:placetype":"venue"
},
  "geometry": {"coordinates":[-81.6876525879,43.7292366028],"type":"Point"}
}