{
  "type": "Feature",
  "properties": {
    "addr:full":"9620 Rue Meilleur Montreal QC H2N 2E6",
    "addr:housenumber":"9620",
    "addr:postcode":"h2n 2e6",
    "addr:street":"Rue Meilleur",
    "iso:country":"CA",
    "sg:address":"9620 Rue Meilleur",
    "sg:city":"Montreal",
    "sg:classifiers":[
        {
            "category":"Home & Garden",
            "subcategory":"Furniture",
            "type":"Retail Goods"
        }
    ],
    "sg:phone":"+1 514 382 0180",
    "sg:postcode":"H2N 2E6",
    "sg:province":"QC",
    "sg:tags":[
        "material",
        "fixture",
        "display",
        "store"
    ],
    "wof:name":"Adco Ameublement & Accessories",
    "wof:placetype":"venue"
},
  "geometry": {"coordinates":[-73.660301,45.539051],"type":"Point"}
}