{
  "type": "Feature",
  "properties": {
    "iso:country":"CA",
    "sg:city":"LA Sarre",
    "sg:classifiers":[
        {
            "category":"Manufacturing",
            "subcategory":"Tools & Machinery",
            "type":"Manufacturing & Wholesale Goods"
        }
    ],
    "sg:phone":"+1 819 333 6262",
    "sg:postcode":"J9Z 2X4",
    "sg:province":"QC",
    "sg:tags":[
        "machine",
        "shop"
    ],
    "wof:name":"Prbf Technologies",
    "wof:placetype":"venue"
},
  "geometry": {"coordinates":[-79.20031738279999,48.7975616455],"type":"Point"}
}