{
  "type": "Feature",
  "properties": {
    "addr:full":"1211 Sutherland Ave Kelowna BC V1Y 5Y2",
    "addr:housenumber":"1211",
    "addr:postcode":"v1y 5y2",
    "addr:street":"Sutherland Ave",
    "iso:country":"CA",
    "sg:address":"1211 Sutherland Ave",
    "sg:city":"Kelowna",
    "sg:classifiers":[
        {
            "category":"Retail",
            "subcategory":"Funeral Services",
            "type":"Services"
        }
    ],
    "sg:phone":"+1 250 762 2299",
    "sg:postcode":"V1Y 5Y2",
    "sg:province":"BC",
    "sg:tags":[
        "director"
    ],
    "wof:name":"First Memorial Funeral Svc",
    "wof:placetype":"venue"
},
  "geometry": {"coordinates":[-119.473259,49.880074],"type":"Point"}
}