{
  "type": "Feature",
  "properties": {
    "addr:full":"Yorkton SK S3N 1G1",
    "addr:postcode":"s3n 1g1",
    "iso:country":"CA",
    "sg:city":"Yorkton",
    "sg:classifiers":[
        {
            "category":"Shopping",
            "subcategory":"Clothing, Apparel, & Fashions",
            "type":"Retail Goods"
        }
    ],
    "sg:phone":"+1 306 786 7191",
    "sg:postcode":"S3N 1G1",
    "sg:province":"SK",
    "sg:tags":[
        "alteration"
    ],
    "wof:name":"Hemlines By Linda",
    "wof:placetype":"venue"
},
  "geometry": {"coordinates":[-102.461235,51.210667],"type":"Point"}
}