{
  "type": "Feature",
  "properties": {
    "addr:full":"6615 34 St NW Edmonton AB T6B 2V8",
    "addr:housenumber":"6615",
    "addr:postcode":"t6b 2v8",
    "addr:street":"34 St Nw",
    "iso:country":"CA",
    "sg:address":"6615 34 St NW",
    "sg:city":"Edmonton",
    "sg:classifiers":[
        {
            "category":"Building & Trades",
            "subcategory":"Construction",
            "type":"Services"
        }
    ],
    "sg:phone":"+1 780 466 0397",
    "sg:postcode":"T6B 2V8",
    "sg:province":"AB",
    "sg:tags":[
        "sandblasting",
        "painter"
    ],
    "wof:name":"Scona Enterprises Ltd",
    "wof:placetype":"venue"
},
  "geometry": {"coordinates":[-113.393600464,53.5030860901],"type":"Point"}
}