{
  "type": "Feature",
  "properties": {
    "addr:full":"3 Rue Ste-Marie Saint-Jean-DE-Dieu QC G0L 3M0",
    "addr:housenumber":"3",
    "addr:postcode":"g0l 3m0",
    "addr:street":"Rue Ste-Marie",
    "iso:country":"CA",
    "sg:address":"3 Rue Ste-Marie",
    "sg:city":"Saint-Jean-DE-Dieu",
    "sg:classifiers":[
        {
            "category":"Education",
            "subcategory":"School",
            "type":"Public Place"
        }
    ],
    "sg:phone":"+1 418 963 3225",
    "sg:postcode":"G0L 3M0",
    "sg:province":"QC",
    "wof:name":"Ecole Sainte-Marie",
    "wof:placetype":"venue"
},
  "geometry": {"coordinates":[-69.045799,48.008392],"type":"Point"}
}