{
  "type": "Feature",
  "properties": {
    "addr:full":"Surrey BC V3W 4G2",
    "addr:postcode":"v3w 4g2",
    "iso:country":"CA",
    "sg:city":"Surrey",
    "sg:classifiers":[
        {
            "category":"Banks & Credit Unions",
            "subcategory":"Investment Brokerage",
            "type":"Services"
        }
    ],
    "sg:phone":"+1 604 543 9109",
    "sg:postcode":"V3W 4G2",
    "sg:province":"BC",
    "sg:tags":[
        "consultant",
        "planning",
        "financial"
    ],
    "wof:name":"Chahal, Balwinder S",
    "wof:placetype":"venue"
},
  "geometry": {"coordinates":[-122.86782074,49.1541099548],"type":"Point"}
}