{
  "type": "Feature",
  "properties": {
    "addr:full":"68 Main St Guysborough NS B0H 1N0",
    "addr:housenumber":"68",
    "addr:postcode":"b0h 1n0",
    "addr:street":"Main St",
    "iso:country":"CA",
    "sg:address":"68 Main St",
    "sg:city":"Guysborough",
    "sg:classifiers":[
        {
            "category":"Cinema",
            "subcategory":"Movie Theater",
            "type":"Entertainment"
        }
    ],
    "sg:phone":"+1 902 533 2092",
    "sg:postcode":"B0H 1N0",
    "sg:province":"NS",
    "sg:tags":[
        "charitable",
        "institution"
    ],
    "wof:name":"Mulgrave Road Theatre",
    "wof:placetype":"venue"
},
  "geometry": {"coordinates":[-61.497978,45.391369],"type":"Point"}
}