{
  "type": "Feature",
  "properties": {
    "addr:full":"Chicoutimi QC G7H 6B9",
    "addr:postcode":"g7h 6b9",
    "iso:country":"CA",
    "sg:city":"Chicoutimi",
    "sg:classifiers":[
        {
            "category":"Health Services",
            "subcategory":"Doctor",
            "type":"Services"
        }
    ],
    "sg:phone":"+1 418 545 3505",
    "sg:postcode":"G7H 6B9",
    "sg:province":"QC",
    "sg:tags":[
        "clinic"
    ],
    "wof:name":"Clinique DE Radiologie",
    "wof:placetype":"venue"
},
  "geometry": {"coordinates":[-71.1117095947,48.3061218262],"type":"Point"}
}