{
  "type": "Feature",
  "properties": {
    "addr:full":"1612 17 Ave SW Calgary AB T2T 0E3",
    "addr:housenumber":"1612",
    "addr:postcode":"t2t 0e3",
    "addr:street":"17 Ave Sw",
    "iso:country":"CA",
    "sg:address":"1612 17 Ave SW",
    "sg:city":"Calgary",
    "sg:classifiers":[
        {
            "category":"Real Estate",
            "subcategory":"Real Estate Agent",
            "type":"Services"
        }
    ],
    "sg:phone":"+1 403 245 0773",
    "sg:postcode":"T2T 0E3",
    "sg:province":"AB",
    "wof:name":"Century 21 Bamber Realty Ltd",
    "wof:placetype":"venue"
},
  "geometry": {"coordinates":[-114.09790802000001,51.037940979],"type":"Point"}
}