{
  "type": "Feature",
  "properties": {
    "addr:full":"2254 Newton Rd Hwy 3 Cawston BC V0X 1C0",
    "addr:housenumber":"2254",
    "addr:postcode":"v0x 1c0",
    "addr:street":"Newton Rd Hwy 3",
    "iso:country":"CA",
    "sg:address":"2254 Newton Rd Hwy 3",
    "sg:city":"Cawston",
    "sg:classifiers":[
        {
            "category":"Manufacturing",
            "subcategory":"Lumber",
            "type":"Manufacturing & Wholesale Goods"
        }
    ],
    "sg:phone":"+1 250 499 0142",
    "sg:postcode":"V0X 1C0",
    "sg:province":"BC",
    "sg:tags":[
        "sawmill"
    ],
    "wof:name":"T L Timber",
    "wof:placetype":"venue"
},
  "geometry": {"coordinates":[-119.751328,49.173508],"type":"Point"}
}