{
  "type": "Feature",
  "properties": {
    "addr:full":"584 Wallace St Hope BC V0X 1L0",
    "addr:housenumber":"584",
    "addr:postcode":"v0x 1l0",
    "addr:street":"Wallace St",
    "iso:country":"CA",
    "sg:address":"584 Wallace St",
    "sg:city":"Hope",
    "sg:classifiers":[
        {
            "category":"Sports & Exercise",
            "subcategory":"Bowling",
            "type":"Entertainment"
        }
    ],
    "sg:phone":"+1 604 869 7027",
    "sg:postcode":"V0X 1L0",
    "sg:province":"BC",
    "sg:tags":[
        "center"
    ],
    "wof:name":"Fraser Bowl & Racquetball",
    "wof:placetype":"venue"
},
  "geometry": {"coordinates":[-121.435585022,49.3816184998],"type":"Point"}
}