{
  "type": "Feature",
  "properties": {
    "addr:full":"155 Market St Hamilton ON L8R 3H5",
    "addr:housenumber":"155",
    "addr:postcode":"l8r 3h5",
    "addr:street":"Market St",
    "iso:country":"CA",
    "sg:address":"155 Market St",
    "sg:city":"Hamilton",
    "sg:classifiers":[
        {
            "category":"Building & Trades",
            "subcategory":"Construction",
            "type":"Services"
        }
    ],
    "sg:phone":"+1 905 529 1123",
    "sg:postcode":"L8R 3H5",
    "sg:province":"ON",
    "sg:tags":[
        "contractor"
    ],
    "wof:name":"Matterhorn Construction Ltd",
    "wof:placetype":"venue"
},
  "geometry": {"coordinates":[-79.876526,43.25956],"type":"Point"}
}