{
  "type": "Feature",
  "properties": {
    "iso:country":"CA",
    "sg:address":"108 Ontario St",
    "sg:city":"Stratford",
    "sg:classifiers":[
        {
            "category":"Travel",
            "subcategory":"Hotels & Motels",
            "type":"Entertainment"
        }
    ],
    "sg:phone":"+1 519 271 1888",
    "sg:postcode":"N5A 3H2",
    "sg:province":"ON",
    "sg:tags":[
        "inn"
    ],
    "wof:name":"Mercer Hall Inn",
    "wof:placetype":"venue"
},
  "geometry": {"coordinates":[-80.98123200000001,43.371544],"type":"Point"}
}