{
  "type": "Feature",
  "properties": {
    "addr:full":"4631 Richardson Way SW Calgary AB T3E 7B7",
    "addr:housenumber":"4631",
    "addr:postcode":"t3e 7b7",
    "addr:street":"Richardson Way Sw",
    "iso:country":"CA",
    "sg:address":"4631 Richardson Way SW",
    "sg:city":"Calgary",
    "sg:classifiers":[
        {
            "category":"Health Services",
            "subcategory":"Clinic",
            "type":"Services"
        }
    ],
    "sg:phone":"+1 403 240 7327",
    "sg:postcode":"T3E 7B7",
    "sg:province":"AB",
    "sg:tags":[
        "home"
    ],
    "wof:name":"In-Home Support Svc",
    "wof:placetype":"venue"
},
  "geometry": {"coordinates":[-114.14067840600001,51.0124015808],"type":"Point"}
}