{
  "type": "Feature",
  "properties": {
    "addr:full":"522 Church Shubenacadie NS B0N 2H0",
    "addr:housenumber":"522",
    "addr:postcode":"b0n 2h0",
    "addr:street":"Church",
    "iso:country":"CA",
    "sg:address":"522 Church",
    "sg:city":"Shubenacadie",
    "sg:classifiers":[
        {
            "category":"Organizations",
            "subcategory":"Professional Association",
            "type":"Services"
        }
    ],
    "sg:phone":"+1 902 758 2335",
    "sg:postcode":"B0N 2H0",
    "sg:province":"NS",
    "sg:tags":[
        "club"
    ],
    "wof:name":"Indian Brook Minor Hockey",
    "wof:placetype":"venue"
},
  "geometry": {"coordinates":[-63.4035148621,45.0885658264],"type":"Point"}
}