{
  "type": "Feature",
  "properties": {
    "addr:full":"Calgary AB T2H 2L9",
    "addr:postcode":"t2h 2l9",
    "iso:country":"CA",
    "sg:city":"Calgary",
    "sg:classifiers":[
        {
            "category":"Manufacturing",
            "subcategory":"Food",
            "type":"Manufacturing & Wholesale Goods"
        }
    ],
    "sg:phone":"+1 403 253 1505",
    "sg:postcode":"T2H 2L9",
    "sg:province":"AB",
    "sg:tags":[
        "baker",
        "supply"
    ],
    "wof:name":"Dawn Food Products Ltd",
    "wof:placetype":"venue"
},
  "geometry": {"coordinates":[-114.063186645,51.0450706482],"type":"Point"}
}