{
  "type": "Feature",
  "properties": {
    "addr:full":"11945 Hwy 1 Lawrencetown. NS B0S 1M0",
    "addr:housenumber":"11945",
    "addr:postcode":"b0s 1m0",
    "addr:street":"Hwy 1",
    "iso:country":"CA",
    "sg:address":"11945 Hwy 1",
    "sg:city":"Lawrencetown.",
    "sg:classifiers":[
        {
            "category":"Retail",
            "subcategory":"Auto Repair",
            "type":"Services"
        }
    ],
    "sg:phone":"+1 902 584 7165",
    "sg:postcode":"B0S 1M0",
    "sg:province":"NS",
    "sg:tags":[
        "repairing",
        "automobile",
        "wheel",
        "axle"
    ],
    "wof:name":"Roberts Mechanical",
    "wof:placetype":"venue"
},
  "geometry": {"coordinates":[-63.3385314941,44.6454391479],"type":"Point"}
}