{
  "type": "Feature",
  "properties": {
    "addr:full":"1522 10th Ave Fernie BC V0B 1M0",
    "addr:housenumber":"1522",
    "addr:postcode":"bc v0b 1m0",
    "addr:street":"10Th Ave",
    "iso:country":"CA",
    "sg:address":"1522 10th Ave",
    "sg:city":"Fernie",
    "sg:classifiers":[
        {
            "category":"Manufacturing",
            "subcategory":"Lumber",
            "type":"Manufacturing & Wholesale Goods"
        }
    ],
    "sg:phone":"+1 250 423 6449",
    "sg:postcode":"V0B 1M0",
    "sg:province":"BC",
    "sg:tags":[
        "company",
        "logging"
    ],
    "wof:name":"Morrissey Aggregates Ltd",
    "wof:placetype":"venue"
},
  "geometry": {"coordinates":[-115.06201900000001,49.515327],"type":"Point"}
}