{
  "type": "Feature",
  "properties": {
    "addr:full":"35 Lakecrest Dr Dartmouth NS B2X 1T9",
    "addr:housenumber":"35",
    "addr:postcode":"b2x 1t9",
    "addr:street":"Lakecrest Dr",
    "iso:country":"CA",
    "sg:address":"35 Lakecrest Dr",
    "sg:city":"Dartmouth",
    "sg:classifiers":[
        {
            "category":"Organizations",
            "subcategory":"Religious Organization",
            "type":"Services"
        }
    ],
    "sg:phone":"+1 902 434 1562",
    "sg:postcode":"B2X 1T9",
    "sg:province":"NS",
    "sg:tags":[
        "church"
    ],
    "wof:name":"Seventh-Day Adventist Church",
    "wof:placetype":"venue"
},
  "geometry": {"coordinates":[-63.57534,44.674011],"type":"Point"}
}