{
  "type": "Feature",
  "properties": {
    "addr:full":"713 Douglas Fir Rd Sparwood BC V0B 2G0",
    "addr:housenumber":"713",
    "addr:postcode":"bc v0b 2g0",
    "addr:street":"Douglas Fir Rd",
    "iso:country":"CA",
    "sg:address":"713 Douglas Fir Rd",
    "sg:city":"Sparwood",
    "sg:classifiers":[
        {
            "category":"Freight",
            "type":"Transportation"
        }
    ],
    "sg:phone":"+1 250 425 7066",
    "sg:postcode":"V0B 2G0",
    "sg:province":"BC",
    "sg:tags":[
        "trucking"
    ],
    "wof:name":"James Czeh Trucking",
    "wof:placetype":"venue"
},
  "geometry": {"coordinates":[-114.894363403,49.712146759],"type":"Point"}
}