{
  "type": "Feature",
  "properties": {
    "addr:full":"45 Rue Des Entreprises Sainte-Anne-Des-Plaines QC J0N 1H0",
    "addr:housenumber":"45",
    "addr:postcode":"j0n 1h0",
    "addr:street":"Rue Des Entreprises",
    "iso:country":"CA",
    "sg:address":"45 Rue Des Entreprises",
    "sg:city":"Sainte-Anne-Des-Plaines",
    "sg:classifiers":[
        {
            "category":"Manufacturing",
            "subcategory":"Tools & Machinery",
            "type":"Manufacturing & Wholesale Goods"
        }
    ],
    "sg:phone":"+1 450 478 3456",
    "sg:postcode":"J0N 1H0",
    "sg:province":"QC",
    "sg:tags":[
        "farm",
        "equipment"
    ],
    "wof:name":"Comptoir Agricole Ste-Anne Inc",
    "wof:placetype":"venue"
},
  "geometry": {"coordinates":[-73.822487,45.748276],"type":"Point"}
}