{
  "type": "Feature",
  "properties": {
    "addr:full":"Prince George BC V2M 3B7",
    "addr:postcode":"v2m 3b7",
    "iso:country":"CA",
    "sg:city":"Prince George",
    "sg:classifiers":[
        {
            "category":"Food & Beverages",
            "subcategory":"Bakery",
            "type":"Retail Goods"
        }
    ],
    "sg:phone":"+1 250 614 1044",
    "sg:postcode":"V2M 3B7",
    "sg:province":"BC",
    "sg:tags":[
        "baker"
    ],
    "wof:name":"Surgardaddy's Bakery Ltd",
    "wof:placetype":"venue"
},
  "geometry": {"coordinates":[-122.781013489,53.9182777405],"type":"Point"}
}