{
  "type": "Feature",
  "properties": {
    "addr:full":"700 Chiefswood Ohsweken ON N0A 1M0",
    "addr:housenumber":"700",
    "addr:postcode":"n0a 1m0",
    "addr:street":"Chiefswood",
    "iso:country":"CA",
    "sg:address":"700 Chiefswood",
    "sg:city":"Ohsweken",
    "sg:classifiers":[
        {
            "category":"Restaurant",
            "type":"Food & Drink"
        }
    ],
    "sg:phone":"+1 519 445 2951",
    "sg:postcode":"N0A 1M0",
    "sg:province":"ON",
    "wof:name":"Two Arrows Restaurant",
    "wof:placetype":"venue"
},
  "geometry": {"coordinates":[-80.12715900000001,43.05468],"type":"Point"}
}