{
  "type": "Feature",
  "properties": {
    "addr:full":"2430 Don Reid Dr Ottawa ON K1H 1E1",
    "addr:housenumber":"2430",
    "addr:postcode":"k1h 1e1",
    "addr:street":"Don Reid Dr",
    "iso:country":"CA",
    "sg:address":"2430 Don Reid Dr",
    "sg:city":"Ottawa",
    "sg:classifiers":[
        {
            "category":"Restaurant",
            "type":"Food & Drink"
        }
    ],
    "sg:phone":"+1 613 247 0765",
    "sg:postcode":"K1H 1E1",
    "sg:province":"ON",
    "wof:name":"Marcie's Cafeteria",
    "wof:placetype":"venue"
},
  "geometry": {"coordinates":[-75.63395690919999,45.3790473938],"type":"Point"}
}