{
  "type": "Feature",
  "properties": {
    "addr:full":"Scarborough ON M1J 2H6",
    "addr:postcode":"m1j 2h6",
    "iso:country":"CA",
    "sg:city":"Scarborough",
    "sg:classifiers":[
        {
            "category":"Personal",
            "subcategory":"Beauty Salon",
            "type":"Services"
        }
    ],
    "sg:phone":"+1 416 261 8881",
    "sg:postcode":"M1J 2H6",
    "sg:province":"ON",
    "wof:name":"Excell Hair Studio",
    "wof:placetype":"venue"
},
  "geometry": {"coordinates":[-79.21807861329999,43.7435493469],"type":"Point"}
}