{
  "type": "Feature",
  "properties": {
    "addr:full":"PO Box 635 Melfort SK S0E 1A0",
    "addr:housenumber":"po",
    "addr:postcode":"s0e 1a0",
    "addr:street":"Box 635 Melfort",
    "iso:country":"CA",
    "sg:address":"PO Box 635",
    "sg:city":"Melfort",
    "sg:classifiers":[
        {
            "category":"Building & Trades",
            "subcategory":"Plumbing",
            "type":"Services"
        }
    ],
    "sg:phone":"+1 306 921 7710",
    "sg:postcode":"S0E 1A0",
    "sg:province":"SK",
    "sg:tags":[
        "conditioning",
        "air",
        "system",
        "contractor"
    ],
    "wof:name":"Rick's Plumbing & Heating",
    "wof:placetype":"venue"
},
  "geometry": {"coordinates":[-104.61794999999999,52.861366],"type":"Point"}
}