{
  "type": "Feature",
  "properties": {
    "iso:country":"CA",
    "sg:address":"95 Av Des Tilleuls",
    "sg:city":"Drummondville",
    "sg:classifiers":[
        {
            "category":"Sports & Exercise",
            "subcategory":"Gym",
            "type":"Entertainment"
        }
    ],
    "sg:phone":"+1 819 471 4881",
    "sg:postcode":"J2C 3S1",
    "sg:province":"QC",
    "sg:tags":[
        "club",
        "health",
        "studio",
        "gymnasium"
    ],
    "wof:name":"Mon Gym",
    "wof:placetype":"venue"
},
  "geometry": {"coordinates":[-72.5023803711,45.8867950439],"type":"Point"}
}