{
  "type": "Feature",
  "properties": {
    "iso:country":"CA",
    "sg:address":"62 Av Hillcrest",
    "sg:city":"Lachine",
    "sg:classifiers":[
        {
            "category":"Building & Trades",
            "subcategory":"Cleaning & Sanitation",
            "type":"Services"
        }
    ],
    "sg:phone":"+1 514 486 3566",
    "sg:postcode":"H8R 1J2",
    "sg:province":"QC",
    "sg:tags":[
        "ventilating",
        "janitor",
        "system"
    ],
    "wof:name":"Briault Nettoyeurs Du Quebec",
    "wof:placetype":"venue"
},
  "geometry": {"coordinates":[-73.649803,45.449097],"type":"Point"}
}