{
  "type": "Feature",
  "properties": {
    "addr:full":"17 Munroe Ave Port Elgin NB E4M 1B5",
    "addr:housenumber":"17",
    "addr:postcode":"e4m 1b5",
    "addr:street":"Munroe Ave",
    "iso:country":"CA",
    "sg:address":"17 Munroe Ave",
    "sg:city":"Port Elgin",
    "sg:classifiers":[
        {
            "category":"Organizations",
            "subcategory":"Religious Organization",
            "type":"Services"
        }
    ],
    "sg:phone":"+1 506 538 7330",
    "sg:postcode":"E4M 1B5",
    "sg:province":"NB",
    "sg:tags":[
        "church"
    ],
    "wof:name":"Anglican Parish of Westmorland",
    "wof:placetype":"venue"
},
  "geometry": {"coordinates":[-64.08878300000001,46.046043],"type":"Point"}
}