{
  "type": "Feature",
  "properties": {
    "iso:country":"CA",
    "sg:address":"50 Rue DE LA Barre",
    "sg:city":"Longueuil",
    "sg:classifiers":[
        {
            "category":"Professional",
            "subcategory":"Management & Consulting",
            "type":"Services"
        }
    ],
    "sg:phone":"+1 450 646 5507",
    "sg:postcode":"J4K 5G2",
    "sg:province":"QC",
    "sg:tags":[
        "consultant",
        "business"
    ],
    "wof:name":"Fdo Inc",
    "wof:placetype":"venue"
},
  "geometry": {"coordinates":[-73.5232391357,45.5272369385],"type":"Point"}
}