{
  "type": "Feature",
  "properties": {
    "addr:full":"1818 Victoria Ave Regina SK S4P 0R1",
    "addr:housenumber":"1818",
    "addr:postcode":"s4p 0r1",
    "addr:street":"Victoria Ave",
    "iso:country":"CA",
    "sg:address":"1818 Victoria Ave",
    "sg:city":"Regina",
    "sg:classifiers":[
        {
            "category":"Travel",
            "subcategory":"Hotels & Motels",
            "type":"Entertainment"
        }
    ],
    "sg:phone":"+1 306 569 1666",
    "sg:postcode":"S4P 0R1",
    "sg:province":"SK",
    "wof:name":"Ramada Hotel & Convention Ctr",
    "wof:placetype":"venue"
},
  "geometry": {"coordinates":[-104.60688018800001,50.4473609924],"type":"Point"}
}