{
  "type": "Feature",
  "properties": {
    "addr:full":"878 Rang Saint-Francois Lotbiniere QC G0S 1S0",
    "addr:housenumber":"878",
    "addr:postcode":"g0s 1s0",
    "addr:street":"Rang Saint-Francois Lotbiniere",
    "iso:country":"CA",
    "sg:address":"878 Rang Saint-Francois",
    "sg:city":"Lotbiniere",
    "sg:classifiers":[
        {
            "category":"Organizations",
            "subcategory":"Non-profit Organization",
            "type":"Services"
        }
    ],
    "sg:phone":"+1 418 796 2137",
    "sg:postcode":"G0S 1S0",
    "sg:province":"QC",
    "sg:tags":[
        "info",
        "addiction",
        "abuse",
        "treatment",
        "drug"
    ],
    "wof:name":"Defi Jeunesse Quebec Inc",
    "wof:placetype":"venue"
},
  "geometry": {"coordinates":[-71.9338607788,46.5826683044],"type":"Point"}
}