{
  "type": "Feature",
  "properties": {
    "addr:full":"269 South Service Rd Grimsby ON L3M 1Y6",
    "addr:housenumber":"269",
    "addr:postcode":"l3m 1y6",
    "addr:street":"South Service Rd",
    "iso:country":"CA",
    "sg:address":"269 South Service Rd",
    "sg:city":"Grimsby",
    "sg:classifiers":[
        {
            "category":"Wholesale",
            "subcategory":"Machinery & Supplies",
            "type":"Manufacturing & Wholesale Goods"
        }
    ],
    "sg:phone":"+1 905 945 2131",
    "sg:postcode":"L3M 1Y6",
    "sg:province":"ON",
    "sg:tags":[
        "printer",
        "printing",
        "cartridge"
    ],
    "wof:name":"Williamson Printing Materials",
    "wof:placetype":"venue"
},
  "geometry": {"coordinates":[-79.514755249,43.18907547],"type":"Point"}
}