{
  "type": "Feature",
  "properties": {
    "iso:country":"CA",
    "sg:city":"Chateauguay",
    "sg:classifiers":[
        {
            "category":"Shopping",
            "type":"Retail Goods"
        }
    ],
    "sg:phone":"+1 450 692 8000",
    "sg:postcode":"J6K 3A9",
    "sg:province":"QC",
    "sg:tags":[
        "hearing",
        "equipment",
        "supply",
        "impaired"
    ],
    "wof:name":"Groupe Forget-Parent",
    "wof:placetype":"venue"
},
  "geometry": {"coordinates":[-73.7163772583,45.3574256897],"type":"Point"}
}