{
  "type": "Feature",
  "properties": {
    "addr:full":"7710 Boul Wilfrid-Hamel Sainte-Foy QC G2G 2J5",
    "addr:housenumber":"7710",
    "addr:postcode":"g2g 2j5",
    "addr:street":"Boul Wilfrid-Hamel",
    "iso:country":"CA",
    "sg:address":"7710 Boul Wilfrid-Hamel",
    "sg:city":"Sainte-Foy",
    "sg:classifiers":[
        {
            "category":"Wholesale",
            "subcategory":"Electrical",
            "type":"Manufacturing & Wholesale Goods"
        }
    ],
    "sg:phone":"+1 418 877 1069",
    "sg:postcode":"G2G 2J5",
    "sg:province":"QC",
    "sg:tags":[
        "sound",
        "equipment",
        "system"
    ],
    "wof:name":"Sonorisation DE Roo & Filles",
    "wof:placetype":"venue"
},
  "geometry": {"coordinates":[-71.381241,46.771965],"type":"Point"}
}