{
  "type": "Feature",
  "properties": {
    "addr:full":"Upton QC J0H 2E0",
    "addr:postcode":"j0h 2e0",
    "iso:country":"CA",
    "sg:city":"Upton",
    "sg:classifiers":[
        {
            "category":"Professional",
            "type":"Services"
        }
    ],
    "sg:phone":"+1 450 549 5868",
    "sg:postcode":"J0H 2E0",
    "sg:province":"QC",
    "sg:tags":[
        "feed",
        "establishment"
    ],
    "wof:name":"Produits Agricoles Neralco Inc",
    "wof:placetype":"venue"
},
  "geometry": {"coordinates":[-72.69330600000001,45.649158],"type":"Point"}
}