{
  "type": "Feature",
  "properties": {
    "iso:country":"CA",
    "sg:address":"265 Annette St",
    "sg:city":"Toronto",
    "sg:classifiers":[
        {
            "category":"Education",
            "subcategory":"School",
            "type":"Public Place"
        }
    ],
    "sg:phone":"+1 416 393 9040",
    "sg:postcode":"M6P 1R3",
    "sg:province":"ON",
    "wof:name":"Annette Street Jr & Sr Ps",
    "wof:placetype":"venue"
},
  "geometry": {"coordinates":[-79.47384643549999,43.6616249084],"type":"Point"}
}