{
  "type": "Feature",
  "properties": {
    "addr:full":"114 Weisner Rd Lakeville-Westmorland NB E1H 1L6",
    "addr:housenumber":"114",
    "addr:postcode":"e1h 1l6",
    "addr:street":"Weisner Rd",
    "iso:country":"CA",
    "sg:address":"114 Weisner Rd",
    "sg:city":"Lakeville-Westmorland",
    "sg:classifiers":[
        {
            "category":"Shopping",
            "subcategory":"Clothing, Apparel, & Fashions",
            "type":"Retail Goods"
        }
    ],
    "sg:phone":"+1 506 383 1141",
    "sg:postcode":"E1H 1L6",
    "sg:province":"NB",
    "sg:tags":[
        "dressmaker"
    ],
    "wof:name":"A 1 Sewing Repairs",
    "wof:placetype":"venue"
},
  "geometry": {"coordinates":[-64.678421,46.157047],"type":"Point"}
}