{
  "type": "Feature",
  "properties": {
    "addr:full":"518 Sixth St New Westminster BC V3L 1V3",
    "addr:housenumber":"518",
    "addr:postcode":"v3l 1v3",
    "addr:street":"Sixth St",
    "iso:country":"CA",
    "sg:address":"518 Sixth St",
    "sg:city":"New Westminster",
    "sg:classifiers":[
        {
            "category":"Restaurant",
            "type":"Food & Drink"
        }
    ],
    "sg:phone":"+1 604 522 1288",
    "sg:postcode":"V3L 1V3",
    "sg:province":"BC",
    "wof:name":"Jim's Cafe",
    "wof:placetype":"venue"
},
  "geometry": {"coordinates":[-122.919365,49.212128],"type":"Point"}
}