{
  "type": "Feature",
  "properties": {
    "addr:full":"500 Cook Rd Kelowna BC V1W 3G9",
    "addr:housenumber":"500",
    "addr:postcode":"v1w 3g9",
    "addr:street":"Cook Rd",
    "iso:country":"CA",
    "sg:address":"500 Cook Rd",
    "sg:city":"Kelowna",
    "sg:classifiers":[
        {
            "category":"Food & Beverages",
            "subcategory":"Liquor & Beverages",
            "type":"Retail Goods"
        }
    ],
    "sg:phone":"+1 250 763 7500",
    "sg:postcode":"V1W 3G9",
    "sg:province":"BC",
    "wof:name":"Eldorado Dining Room & Bar",
    "wof:placetype":"venue"
},
  "geometry": {"coordinates":[-119.489265,49.845261],"type":"Point"}
}