{
  "type": "Feature",
  "properties": {
    "iso:country":"CA",
    "sg:address":"115 62 Ave SE",
    "sg:city":"Calgary",
    "sg:classifiers":[
        {
            "category":"Building & Trades",
            "subcategory":"Electrical",
            "type":"Services"
        }
    ],
    "sg:phone":"+1 403 253 8793",
    "sg:postcode":"T2H 0R5",
    "sg:province":"AB",
    "sg:tags":[
        "electric",
        "contractor"
    ],
    "wof:name":"Anderson Controls & Elec Contr",
    "wof:placetype":"venue"
},
  "geometry": {"coordinates":[-114.063186645,50.9963645935],"type":"Point"}
}