{
  "type": "Feature",
  "properties": {
    "addr:full":"4916 46 St Red Deer AB T4N 1N3",
    "addr:housenumber":"4916",
    "addr:postcode":"t4n 1n3",
    "addr:street":"46 St",
    "iso:country":"CA",
    "sg:address":"4916 46 St",
    "sg:city":"Red Deer",
    "sg:classifiers":[
        {
            "category":"Restaurant",
            "type":"Food & Drink"
        }
    ],
    "sg:phone":"+1 403 346 1883",
    "sg:postcode":"T4N 1N3",
    "sg:province":"AB",
    "wof:name":"Golden Dragon Restaurant",
    "wof:placetype":"venue"
},
  "geometry": {"coordinates":[-113.813416,52.265461],"type":"Point"}
}