{
  "type": "Feature",
  "properties": {
    "addr:full":"1925 Steeles Ave E North York ON M2H 2H3",
    "addr:housenumber":"1925",
    "addr:postcode":"m2h 2h3",
    "addr:street":"Steeles Ave E",
    "iso:country":"CA",
    "sg:address":"1925 Steeles Ave E",
    "sg:city":"North York",
    "sg:classifiers":[
        {
            "category":"Shopping",
            "subcategory":"Pharmacy",
            "type":"Retail Goods"
        }
    ],
    "sg:phone":"+1 416 491 0167",
    "sg:postcode":"M2H 2H3",
    "sg:province":"ON",
    "wof:name":"Medisystems Technologies",
    "wof:placetype":"venue"
},
  "geometry": {"coordinates":[-79.3756408691,43.8076629639],"type":"Point"}
}