{
  "type": "Feature",
  "properties": {
    "addr:full":"2000 Division Ave N Medicine Hat AB T1C 1X9",
    "addr:housenumber":"2000",
    "addr:postcode":"t1c 1x9",
    "addr:street":"Division Ave N",
    "iso:country":"CA",
    "sg:address":"2000 Division Ave N",
    "sg:city":"Medicine Hat",
    "sg:classifiers":[
        {
            "category":"Government",
            "subcategory":"Office",
            "type":"Public Place"
        }
    ],
    "sg:phone":"+1 403 502 8560",
    "sg:postcode":"T1C 1X9",
    "sg:province":"AB",
    "sg:tags":[
        "village"
    ],
    "wof:name":"Medicine Hat Family Leisure",
    "wof:placetype":"venue"
},
  "geometry": {"coordinates":[-110.687202,50.060066],"type":"Point"}
}