{
  "type": "Feature",
  "properties": {
    "addr:full":"Glen Huron ON L0M 1L0",
    "addr:postcode":"l0m 1l0",
    "addr:street":"Glen",
    "iso:country":"CA",
    "sg:city":"Glen Huron",
    "sg:classifiers":[
        {
            "category":"Home & Garden",
            "subcategory":"Building Materials",
            "type":"Retail Goods"
        }
    ],
    "sg:phone":"+1 705 466 2244",
    "sg:postcode":"L0M 1L0",
    "sg:province":"ON",
    "sg:tags":[
        "truss"
    ],
    "wof:name":"Hamilton Brothers Farm & Bldg",
    "wof:placetype":"venue"
},
  "geometry": {"coordinates":[-80.16879299999999,44.3531],"type":"Point"}
}