{
  "type": "Feature",
  "properties": {
    "addr:full":"560 Rue Saint-Alphonse E Thetford Mines QC G6G 3V8",
    "addr:housenumber":"560",
    "addr:postcode":"g6g 3v8",
    "addr:street":"Rue Saint-Alphonse E",
    "iso:country":"CA",
    "sg:address":"560 Rue Saint-Alphonse E",
    "sg:city":"Thetford Mines",
    "sg:classifiers":[
        {
            "category":"Wholesale",
            "subcategory":"Hardware",
            "type":"Manufacturing & Wholesale Goods"
        }
    ],
    "sg:phone":"+1 418 338 5157",
    "sg:postcode":"G6G 3V8",
    "sg:province":"QC",
    "sg:tags":[
        "system",
        "equipment",
        "heating",
        "lubricant"
    ],
    "wof:name":"Huiles Lamontagne Inc",
    "wof:placetype":"venue"
},
  "geometry": {"coordinates":[-71.292603,46.084579],"type":"Point"}
}