{
  "type": "Feature",
  "properties": {
    "addr:full":"Shawville QC J0X 2Y0",
    "addr:postcode":"j0x 2y0",
    "iso:country":"CA",
    "sg:city":"Shawville",
    "sg:classifiers":[
        {
            "category":"Food & Beverages",
            "subcategory":"Bakery",
            "type":"Retail Goods"
        }
    ],
    "sg:phone":"+1 819 647 2575",
    "sg:postcode":"J0X 2Y0",
    "sg:province":"QC",
    "sg:tags":[
        "baker"
    ],
    "wof:name":"Pontiac Home Bakery",
    "wof:placetype":"venue"
},
  "geometry": {"coordinates":[-76.491355896,45.6021995544],"type":"Point"}
}