{
  "type": "Feature",
  "properties": {
    "iso:country":"CA",
    "sg:address":"563 Commercial Cres",
    "sg:city":"London",
    "sg:classifiers":[
        {
            "category":"Freight",
            "type":"Transportation"
        }
    ],
    "sg:phone":"+1 519 453 8250",
    "sg:postcode":"N5V 1Z2",
    "sg:province":"ON",
    "sg:tags":[
        "trucking"
    ],
    "wof:name":"Apex Motor Express Ltd",
    "wof:placetype":"venue"
},
  "geometry": {"coordinates":[-81.19863891599999,43.0055046082],"type":"Point"}
}