{
  "type": "Feature",
  "properties": {
    "addr:full":"Big Trout Lake ON P0V 1G0",
    "addr:postcode":"p0v 1g0",
    "addr:street":"Lake",
    "iso:country":"CA",
    "sg:city":"Big Trout Lake",
    "sg:classifiers":[
        {
            "category":"Organizations",
            "subcategory":"Professional Association",
            "type":"Services"
        }
    ],
    "sg:phone":"+1 807 537 2320",
    "sg:postcode":"P0V 1G0",
    "sg:province":"ON",
    "sg:tags":[
        "government"
    ],
    "wof:name":"Wapekeka Judas & Emily Winter",
    "wof:placetype":"venue"
},
  "geometry": {"coordinates":[-89.83509100000001,53.81876],"type":"Point"}
}