{
  "type": "Feature",
  "properties": {
    "iso:country":"CA",
    "sg:address":"4536 Montrose Rd",
    "sg:city":"Niagara Falls",
    "sg:classifiers":[
        {
            "category":"Manufacturing",
            "subcategory":"Printing",
            "type":"Manufacturing & Wholesale Goods"
        }
    ],
    "sg:phone":"+1 905 357 7468",
    "sg:postcode":"L2H 1K2",
    "sg:province":"ON",
    "sg:tags":[
        "printer"
    ],
    "wof:name":"Artista Design & Print Inc",
    "wof:placetype":"venue"
},
  "geometry": {"coordinates":[-79.1240615845,43.1073989868],"type":"Point"}
}