{
  "type": "Feature",
  "properties": {
    "iso:country":"CA",
    "sg:address":"25 Ch Hodge",
    "sg:city":"Sawyerville",
    "sg:classifiers":[
        {
            "category":"Wholesale",
            "subcategory":"Machinery & Supplies",
            "type":"Manufacturing & Wholesale Goods"
        }
    ],
    "sg:phone":"+1 819 820 4160",
    "sg:postcode":"J0B 3A0",
    "sg:province":"QC",
    "sg:tags":[
        "janitor"
    ],
    "wof:name":"Distribution Royal Net Enr",
    "wof:placetype":"venue"
},
  "geometry": {"coordinates":[-71.5654754639,45.3369483948],"type":"Point"}
}