{
  "type": "Feature",
  "properties": {
    "addr:full":"10515 117 Ave Grande Prairie AB T8V 7N6",
    "addr:housenumber":"10515",
    "addr:postcode":"t8v 7n6",
    "addr:street":"117 Ave",
    "iso:country":"CA",
    "sg:address":"10515 117 Ave",
    "sg:city":"Grande Prairie",
    "sg:classifiers":[
        {
            "category":"Home & Garden",
            "subcategory":"Furniture",
            "type":"Retail Goods"
        }
    ],
    "sg:phone":"+1 780 539 3313",
    "sg:postcode":"T8V 7N6",
    "sg:province":"AB",
    "wof:name":"City Furniture & Appliances",
    "wof:placetype":"venue"
},
  "geometry": {"coordinates":[-118.812157,55.186245],"type":"Point"}
}