{
  "type": "Feature",
  "properties": {
    "addr:full":"Claresholm AB T0L 0T0",
    "addr:postcode":"t0l 0t0",
    "iso:country":"CA",
    "sg:city":"Claresholm",
    "sg:classifiers":[
        {
            "category":"Shopping",
            "type":"Retail Goods"
        }
    ],
    "sg:phone":"+1 403 625 2263",
    "sg:postcode":"T0L 0T0",
    "sg:province":"AB",
    "sg:tags":[
        "picture",
        "frame"
    ],
    "wof:name":"Judy Dahl Photography Gallery",
    "wof:placetype":"venue"
},
  "geometry": {"coordinates":[-113.582893372,50.0263137817],"type":"Point"}
}