{
  "type": "Feature",
  "properties": {
    "addr:full":"Scarborough ON M1S 2K9",
    "addr:postcode":"m1s 2k9",
    "iso:country":"CA",
    "sg:city":"Scarborough",
    "sg:classifiers":[
        {
            "category":"Wholesale",
            "subcategory":"Durable Goods & Equipment",
            "type":"Manufacturing & Wholesale Goods"
        }
    ],
    "sg:phone":"+1 416 609 8288",
    "sg:postcode":"M1S 2K9",
    "sg:province":"ON",
    "sg:tags":[
        "importer"
    ],
    "wof:name":"Ka Wing Hong CO",
    "wof:placetype":"venue"
},
  "geometry": {"coordinates":[-79.28247833250001,43.7991752625],"type":"Point"}
}