{
  "type": "Feature",
  "properties": {
    "iso:country":"CA",
    "sg:address":"32032 Lougheed Hwy",
    "sg:city":"Mission",
    "sg:classifiers":[
        {
            "category":"Food & Beverages",
            "subcategory":"Groceries & Convenience Stores",
            "type":"Retail Goods"
        }
    ],
    "sg:phone":"+1 604 820 1591",
    "sg:postcode":"V2V 1A4",
    "sg:province":"BC",
    "sg:tags":[
        "grocer"
    ],
    "wof:name":"Mission Mini Mart",
    "wof:placetype":"venue"
},
  "geometry": {"coordinates":[-122.33705139200001,49.1326446533],"type":"Point"}
}