{
  "type": "Feature",
  "properties": {
    "addr:full":"5321 1A St SW Calgary AB T2H 0E5",
    "addr:housenumber":"5321",
    "addr:postcode":"t2h 0e5",
    "addr:street":"1A St Sw",
    "iso:country":"CA",
    "sg:address":"5321 1A St SW",
    "sg:city":"Calgary",
    "sg:classifiers":[
        {
            "category":"Building & Trades",
            "subcategory":"Electrical",
            "type":"Services"
        }
    ],
    "sg:phone":"+1 403 253 7724",
    "sg:postcode":"T2H 0E5",
    "sg:province":"AB",
    "sg:tags":[
        "electric",
        "contractor"
    ],
    "wof:name":"Johnson Brothers Electric Ltd",
    "wof:placetype":"venue"
},
  "geometry": {"coordinates":[-114.067345,51.006733],"type":"Point"}
}