{
  "type": "Feature",
  "properties": {
    "addr:full":"Abbotsford BC V2T 6H2",
    "addr:postcode":"v2t 6h2",
    "iso:country":"CA",
    "sg:city":"Abbotsford",
    "sg:classifiers":[
        {
            "category":"Building & Trades",
            "subcategory":"Construction",
            "type":"Services"
        }
    ],
    "sg:phone":"+1 604 855 1676",
    "sg:postcode":"V2T 6H2",
    "sg:province":"BC",
    "sg:tags":[
        "dry wall",
        "contractor"
    ],
    "wof:name":"Regency Drywall II Ltd",
    "wof:placetype":"venue"
},
  "geometry": {"coordinates":[-122.358123779,49.0438842773],"type":"Point"}
}