{
  "type": "Feature",
  "properties": {
    "addr:full":"16 Sillers Ave Trenton ON K8V 1X6",
    "addr:housenumber":"16",
    "addr:postcode":"k8v 1x6",
    "addr:street":"Sillers Ave",
    "iso:country":"CA",
    "sg:address":"16 Sillers Ave",
    "sg:city":"Trenton",
    "sg:classifiers":[
        {
            "category":"Education",
            "subcategory":"School",
            "type":"Public Place"
        }
    ],
    "sg:phone":"+1 613 392 5004",
    "sg:postcode":"K8V 1X6",
    "sg:province":"ON",
    "wof:name":"Queen Elizabeth Elementary",
    "wof:placetype":"venue"
},
  "geometry": {"coordinates":[-77.5771865845,44.1093254089],"type":"Point"}
}