{
  "type": "Feature",
  "properties": {
    "iso:country":"CA",
    "sg:city":"Salmon Arm",
    "sg:classifiers":[
        {
            "category":"Health Services",
            "subcategory":"Doctor",
            "type":"Services"
        }
    ],
    "sg:phone":"+1 250 832 6558",
    "sg:postcode":"V1E 1R6",
    "sg:province":"BC",
    "sg:tags":[
        "dentist"
    ],
    "wof:name":"Charles C Smith Inc",
    "wof:placetype":"venue"
},
  "geometry": {"coordinates":[-119.2784729,50.7035827637],"type":"Point"}
}