{
  "type": "Feature",
  "properties": {
    "addr:full":"4125 Main St Vancouver BC V5V 3P6",
    "addr:housenumber":"4125",
    "addr:postcode":"v5v 3p6",
    "addr:street":"Main St",
    "iso:country":"CA",
    "sg:address":"4125 Main St",
    "sg:city":"Vancouver",
    "sg:classifiers":[
        {
            "category":"Restaurant",
            "type":"Food & Drink"
        }
    ],
    "sg:phone":"+1 604 874 8610",
    "sg:postcode":"V5V 3P6",
    "sg:province":"BC",
    "sg:tags":[
        "delicatessen"
    ],
    "wof:name":"Tonina Deli & Cafe",
    "wof:placetype":"venue"
},
  "geometry": {"coordinates":[-123.101234436,49.2485275269],"type":"Point"}
}