{
  "type": "Feature",
  "properties": {
    "addr:full":"7 Mill St W Milverton ON N0K 1M0",
    "addr:housenumber":"7",
    "addr:postcode":"n0k 1m0",
    "addr:street":"Mill St W Milverton",
    "iso:country":"CA",
    "sg:address":"7 Mill St W",
    "sg:city":"Milverton",
    "sg:classifiers":[
        {
            "category":"Health Services",
            "subcategory":"Health Practitioner",
            "type":"Services"
        }
    ],
    "sg:phone":"+1 519 595 4815",
    "sg:postcode":"N0K 1M0",
    "sg:province":"ON",
    "sg:tags":[
        "midwife"
    ],
    "wof:name":"Countryside Midwifery Svc",
    "wof:placetype":"venue"
},
  "geometry": {"coordinates":[-80.9230728149,43.5660514832],"type":"Point"}
}