{
  "type": "Feature",
  "properties": {
    "addr:full":"8916 19th Ave North Battleford SK S9A 2V9",
    "addr:housenumber":"8916",
    "addr:postcode":"s9a 2v9",
    "addr:street":"19Th Ave",
    "iso:country":"CA",
    "sg:address":"8916 19th Ave",
    "sg:city":"North Battleford",
    "sg:classifiers":[
        {
            "category":"Real Estate",
            "subcategory":"Real Estate Agent",
            "type":"Services"
        }
    ],
    "sg:phone":"+1 306 445 6300",
    "sg:postcode":"S9A 2V9",
    "sg:province":"SK",
    "wof:name":"Battlefords Realtors Assn",
    "wof:placetype":"venue"
},
  "geometry": {"coordinates":[-108.315651,52.786125],"type":"Point"}
}