{
  "type": "Feature",
  "properties": {
    "addr:full":"Prince George BC V2L 3G3",
    "addr:postcode":"v2l 3g3",
    "iso:country":"CA",
    "sg:city":"Prince George",
    "sg:classifiers":[
        {
            "category":"Organizations",
            "subcategory":"Labor Organization",
            "type":"Services"
        }
    ],
    "sg:phone":"+1 250 564 7270",
    "sg:postcode":"V2L 3G3",
    "sg:province":"BC",
    "wof:name":"Prince George Fire Fighters",
    "wof:placetype":"venue"
},
  "geometry": {"coordinates":[-122.749825,53.917953],"type":"Point"}
}