{
  "type": "Feature",
  "properties": {
    "addr:full":"25 Elgin St Springhill NS B0M 1X0",
    "addr:housenumber":"25",
    "addr:postcode":"b0m 1x0",
    "addr:street":"Elgin St",
    "iso:country":"CA",
    "sg:address":"25 Elgin St",
    "sg:city":"Springhill",
    "sg:classifiers":[
        {
            "category":"Shopping",
            "subcategory":"Discount & Variety Stores",
            "type":"Retail Goods"
        }
    ],
    "sg:phone":"+1 902 597 2738",
    "sg:postcode":"B0M 1X0",
    "sg:province":"NS",
    "sg:tags":[
        "merchandise",
        "general"
    ],
    "wof:name":"Alick Grocery",
    "wof:placetype":"venue"
},
  "geometry": {"coordinates":[-64.05735,45.650555],"type":"Point"}
}