{
  "type": "Feature",
  "properties": {
    "addr:full":"Calgary AB T2G 4M8",
    "addr:postcode":"t2g 4m8",
    "iso:country":"CA",
    "sg:city":"Calgary",
    "sg:classifiers":[
        {
            "category":"Freight",
            "type":"Transportation"
        }
    ],
    "sg:phone":"+1 403 269 5313",
    "sg:postcode":"T2G 4M8",
    "sg:province":"AB",
    "sg:tags":[
        "trucking"
    ],
    "wof:name":"Cwt Carriers",
    "wof:placetype":"venue"
},
  "geometry": {"coordinates":[-114.033432007,51.0312995911],"type":"Point"}
}