{
  "type": "Feature",
  "properties": {
    "addr:full":"4101 1st Ave W Carrot River SK S0E 0L0",
    "addr:housenumber":"4101",
    "addr:postcode":"s0e 0l0",
    "addr:street":"1St Ave W Carrot",
    "iso:country":"CA",
    "sg:address":"4101 1st Ave W",
    "sg:city":"Carrot River",
    "sg:classifiers":[
        {
            "category":"Health Services",
            "subcategory":"Doctor",
            "type":"Services"
        }
    ],
    "sg:phone":"+1 306 768 2725",
    "sg:postcode":"S0E 0L0",
    "sg:province":"SK",
    "sg:tags":[
        "home",
        "clinic",
        "convalescent",
        "nursing"
    ],
    "wof:name":"Carrot River & District Health",
    "wof:placetype":"venue"
},
  "geometry": {"coordinates":[-103.587532,53.28336],"type":"Point"}
}