{
  "type": "Feature",
  "properties": {
    "iso:country":"CA",
    "sg:address":"2756 Swaine St",
    "sg:city":"Halifax",
    "sg:classifiers":[
        {
            "category":"Organizations",
            "subcategory":"Religious Organization",
            "type":"Services"
        }
    ],
    "sg:phone":"+1 902 454 4237",
    "sg:postcode":"B3L 3R5",
    "sg:province":"NS",
    "sg:tags":[
        "church"
    ],
    "wof:name":"Gospel Hall",
    "wof:placetype":"venue"
},
  "geometry": {"coordinates":[-63.6084594727,44.6485519409],"type":"Point"}
}