{
  "type": "Feature",
  "properties": {
    "addr:full":"6208 6th Ave Whitehorse YT Y1A 1P2",
    "addr:housenumber":"6208",
    "addr:postcode":"y1a 1p2",
    "addr:street":"6Th Ave",
    "iso:country":"CA",
    "sg:address":"6208 6th Ave",
    "sg:city":"Whitehorse",
    "sg:classifiers":[
        {
            "category":"Real Estate",
            "subcategory":"Real Estate Agent",
            "type":"Services"
        }
    ],
    "sg:phone":"+1 867 667 4288",
    "sg:postcode":"Y1A 1P2",
    "sg:province":"YT",
    "sg:tags":[
        "management"
    ],
    "wof:name":"Rampart Development Group",
    "wof:placetype":"venue"
},
  "geometry": {"coordinates":[-135.06553649899999,60.7250785828],"type":"Point"}
}