{
  "type": "Feature",
  "properties": {
    "addr:full":"Kingston ON K7L 1A1",
    "addr:postcode":"k7l 1a1",
    "iso:country":"CA",
    "sg:city":"Kingston",
    "sg:classifiers":[
        {
            "category":"Professional",
            "subcategory":"Lawyer & Legal Services",
            "type":"Services"
        }
    ],
    "sg:phone":"+1 613 546 6411",
    "sg:postcode":"K7L 1A1",
    "sg:province":"ON",
    "sg:tags":[
        "attorney"
    ],
    "wof:name":"Casey, Philip",
    "wof:placetype":"venue"
},
  "geometry": {"coordinates":[-76.479202,44.231174],"type":"Point"}
}