{
  "type": "Feature",
  "properties": {
    "iso:country":"CA",
    "sg:address":"27 Rue Elgin # 1",
    "sg:city":"Granby",
    "sg:classifiers":[
        {
            "category":"Health Services",
            "subcategory":"Medical Lab",
            "type":"Services"
        }
    ],
    "sg:phone":"+1 450 372 5928",
    "sg:postcode":"J2G 4T8",
    "sg:province":"QC",
    "wof:name":"Bourgault, Jean",
    "wof:placetype":"venue"
},
  "geometry": {"coordinates":[-72.717628479,45.399181366],"type":"Point"}
}