{
  "type": "Feature",
  "properties": {
    "iso:country":"CA",
    "sg:address":"2634 Douglas St",
    "sg:city":"Victoria",
    "sg:classifiers":[
        {
            "category":"Retail",
            "subcategory":"Auto Rental",
            "type":"Services"
        }
    ],
    "sg:phone":"+1 250 385 4440",
    "sg:postcode":"V8T 4M1",
    "sg:province":"BC",
    "sg:tags":[
        "renting",
        "automobile"
    ],
    "wof:name":"Hertz Rent A Car",
    "wof:placetype":"venue"
},
  "geometry": {"coordinates":[-123.366355896,48.4370231628],"type":"Point"}
}