{
  "type": "Feature",
  "properties": {
    "iso:country":"CA",
    "sg:address":"2698 Rue Beaubien E",
    "sg:city":"Montreal",
    "sg:classifiers":[
        {
            "category":"Professional",
            "subcategory":"Business Services",
            "type":"Services"
        }
    ],
    "sg:phone":"+1 514 728 0101",
    "sg:postcode":"H1Y 1G7",
    "sg:province":"QC",
    "sg:tags":[
        "notary"
    ],
    "wof:name":"Reilly Simon Notaires",
    "wof:placetype":"venue"
},
  "geometry": {"coordinates":[-73.589119,45.551609],"type":"Point"}
}