{
  "type": "Feature",
  "properties": {
    "addr:full":"3584 Collinson Rd Cranbrook BC V1C 7B8",
    "addr:housenumber":"3584",
    "addr:postcode":"bc v1c 7b8",
    "addr:street":"Collinson Rd",
    "iso:country":"CA",
    "sg:address":"3584 Collinson Rd",
    "sg:city":"Cranbrook",
    "sg:classifiers":[
        {
            "category":"Utilities",
            "subcategory":"Fuel Oil & Lpg",
            "type":"Services"
        }
    ],
    "sg:phone":"+1 250 489 2238",
    "sg:postcode":"V1C 7B8",
    "sg:province":"BC",
    "sg:tags":[
        "propane",
        "gas"
    ],
    "wof:name":"Duthie's First Choice Auto",
    "wof:placetype":"venue"
},
  "geometry": {"coordinates":[-115.7687,49.5135],"type":"Point"}
}