{
  "type": "Feature",
  "properties": {
    "addr:full":"374 Commonwealth Cir Mississauga ON L5B 3V2",
    "addr:housenumber":"374",
    "addr:postcode":"l5b 3v2",
    "addr:street":"Commonwealth Cir",
    "iso:country":"CA",
    "sg:address":"374 Commonwealth Cir",
    "sg:city":"Mississauga",
    "sg:classifiers":[
        {
            "category":"Building & Trades",
            "subcategory":"Construction",
            "type":"Services"
        }
    ],
    "sg:phone":"+1 905 275 1231",
    "sg:postcode":"L5B 3V2",
    "sg:province":"ON",
    "sg:tags":[
        "paving",
        "contractor"
    ],
    "wof:name":"Di Natale Paving CO",
    "wof:placetype":"venue"
},
  "geometry": {"coordinates":[-79.6411743164,43.5815315247],"type":"Point"}
}