{
  "type": "Feature",
  "properties": {
    "iso:country":"CA",
    "sg:address":"377 Dalhousie St Suite 210",
    "sg:city":"Ottawa",
    "sg:classifiers":[
        {
            "category":"Professional",
            "subcategory":"Advertising",
            "type":"Services"
        }
    ],
    "sg:postcode":"K1N 9N8",
    "sg:tags":[
        "home-server",
        "digital",
        "software",
        "nas",
        "video",
        "music",
        "pictures",
        "digital-home",
        "remote-sharing",
        "hipserv"
    ],
    "sg:website":"http://www.axentra.com",
    "wof:name":"Axentra Corporation",
    "wof:placetype":"venue"
},
  "geometry": {"coordinates":[-75.6898711,45.4273982],"type":"Point"}
}