{
  "type": "Feature",
  "properties": {
    "iso:country":"CA",
    "sg:city":"Winnipeg",
    "sg:classifiers":[
        {
            "category":"Freight",
            "type":"Transportation"
        }
    ],
    "sg:phone":"+1 204 694 2566",
    "sg:postcode":"R2X 2Y3",
    "sg:province":"MB",
    "sg:tags":[
        "consultant"
    ],
    "wof:name":"Compliance Solutions Inc",
    "wof:placetype":"venue"
},
  "geometry": {"coordinates":[-97.1953659058,49.9270362854],"type":"Point"}
}