{
  "type": "Feature",
  "properties": {
    "iso:country":"CA",
    "sg:address":"1865 Hollis St",
    "sg:city":"Halifax",
    "sg:classifiers":[
        {
            "category":"Restaurant",
            "type":"Food & Drink"
        }
    ],
    "sg:phone":"+1 902 425 6738",
    "sg:postcode":"B3J 1W5",
    "sg:province":"NS",
    "wof:name":"Nemo's Restaurant",
    "wof:placetype":"venue"
},
  "geometry": {"coordinates":[-63.5737533569,44.649810791],"type":"Point"}
}