{
  "type": "Feature",
  "properties": {
    "addr:full":"Highway 105 N Ear Falls ON P0V 1T0",
    "addr:postcode":"p0v 1t0",
    "addr:street":"Highway 105 N",
    "iso:country":"CA",
    "sg:address":"Highway 105 N",
    "sg:city":"Ear Falls",
    "sg:classifiers":[
        {
            "category":"Professional",
            "subcategory":"Business Services",
            "type":"Services"
        }
    ],
    "sg:phone":"+1 807 222 2394",
    "sg:postcode":"P0V 1T0",
    "sg:province":"ON",
    "sg:tags":[
        "screen",
        "printing",
        "embroidery"
    ],
    "wof:name":"North Silk Screening",
    "wof:placetype":"venue"
},
  "geometry": {"coordinates":[-93.421791,50.800728],"type":"Point"}
}