{
  "type": "Feature",
  "properties": {
    "addr:full":"59 Millpark Way SW Calgary AB T2Y 2N1",
    "addr:housenumber":"59",
    "addr:postcode":"t2y 2n1",
    "addr:street":"Millpark Way Sw",
    "iso:country":"CA",
    "sg:address":"59 Millpark Way SW",
    "sg:city":"Calgary",
    "sg:classifiers":[
        {
            "category":"Manufacturing",
            "subcategory":"Printing",
            "type":"Manufacturing & Wholesale Goods"
        }
    ],
    "sg:phone":"+1 403 201 3678",
    "sg:postcode":"T2Y 2N1",
    "sg:province":"AB",
    "sg:tags":[
        "printer"
    ],
    "wof:name":"Cdp Creative Design & Print",
    "wof:placetype":"venue"
},
  "geometry": {"coordinates":[-114.083808899,50.9188919067],"type":"Point"}
}