{
  "type": "Feature",
  "properties": {
    "addr:full":"Peterborough ON K9J 8J9",
    "addr:postcode":"k9j 8j9",
    "iso:country":"CA",
    "sg:city":"Peterborough",
    "sg:classifiers":[
        {
            "category":"Restaurant",
            "type":"Food & Drink"
        }
    ],
    "sg:phone":"+1 705 741 0629",
    "sg:postcode":"K9J 8J9",
    "sg:province":"ON",
    "sg:tags":[
        "sandwich"
    ],
    "wof:name":"Subway Sandwiches & Salads",
    "wof:placetype":"venue"
},
  "geometry": {"coordinates":[-78.33371699999999,44.283394],"type":"Point"}
}