{
  "type": "Feature",
  "properties": {
    "addr:full":"743 Galt St North Bay ON P1B 5M9",
    "addr:housenumber":"743",
    "addr:postcode":"p1b 5m9",
    "addr:street":"Galt St",
    "iso:country":"CA",
    "sg:address":"743 Galt St",
    "sg:city":"North Bay",
    "sg:classifiers":[
        {
            "category":"Building & Trades",
            "subcategory":"Plumbing",
            "type":"Services"
        }
    ],
    "sg:phone":"+1 705 472 6725",
    "sg:postcode":"P1B 5M9",
    "sg:province":"ON",
    "sg:tags":[
        "conditioning",
        "air",
        "system",
        "contractor"
    ],
    "wof:name":"Burnie's Heating & Air Cond",
    "wof:placetype":"venue"
},
  "geometry": {"coordinates":[-79.46399700000001,46.321884],"type":"Point"}
}