{
  "type": "Feature",
  "properties": {
    "addr:full":"840 Coxwell Ave # 204 East York ON M4C 5T2",
    "addr:housenumber":"840",
    "addr:postcode":"m4c 5t2",
    "addr:street":"Coxwell Ave # 204",
    "iso:country":"CA",
    "sg:address":"840 Coxwell Ave # 204",
    "sg:city":"East York",
    "sg:classifiers":[
        {
            "category":"Health Services",
            "subcategory":"Doctor",
            "type":"Services"
        }
    ],
    "sg:phone":"+1 416 461 0123",
    "sg:postcode":"M4C 5T2",
    "sg:province":"ON",
    "sg:tags":[
        "physician",
        "surgeon"
    ],
    "wof:name":"Morrow, Gary MD",
    "wof:placetype":"venue"
},
  "geometry": {"coordinates":[-79.326645,43.690292],"type":"Point"}
}