{
  "type": "Feature",
  "properties": {
    "addr:full":"Burlington ON L7L 6B5",
    "addr:postcode":"l7l 6b5",
    "iso:country":"CA",
    "sg:city":"Burlington",
    "sg:classifiers":[
        {
            "category":"Manufacturing",
            "subcategory":"Tools & Machinery",
            "type":"Manufacturing & Wholesale Goods"
        }
    ],
    "sg:phone":"+1 905 632 5411",
    "sg:postcode":"L7L 6B5",
    "sg:province":"ON",
    "sg:tags":[
        "machine",
        "shop"
    ],
    "wof:name":"Londrome Industries Inc",
    "wof:placetype":"venue"
},
  "geometry": {"coordinates":[-79.7623062134,43.3826408386],"type":"Point"}
}