{
  "type": "Feature",
  "properties": {
    "addr:full":"Repentigny QC J6A 8B4",
    "addr:postcode":"j6a 8b4",
    "iso:country":"CA",
    "sg:city":"Repentigny",
    "sg:classifiers":[
        {
            "category":"Manufacturing",
            "subcategory":"Textiles",
            "type":"Manufacturing & Wholesale Goods"
        }
    ],
    "sg:phone":"+1 450 582 1753",
    "sg:postcode":"J6A 8B4",
    "sg:province":"QC",
    "sg:tags":[
        "screen",
        "printing"
    ],
    "wof:name":"Serigraphies Contraste",
    "wof:placetype":"venue"
},
  "geometry": {"coordinates":[-73.4496307373,45.7485466003],"type":"Point"}
}