{
  "type": "Feature",
  "properties": {
    "addr:full":"5643 Rue Clark Montreal QC H2T 2V5",
    "addr:housenumber":"5643",
    "addr:postcode":"h2t 2v5",
    "addr:street":"Rue Clark",
    "iso:country":"CA",
    "sg:address":"5643 Rue Clark",
    "sg:city":"Montreal",
    "sg:classifiers":[
        {
            "category":"Communications",
            "subcategory":"Film & Video Production",
            "type":"Services"
        }
    ],
    "sg:phone":"+1 514 273 4252",
    "sg:postcode":"H2T 2V5",
    "sg:province":"QC",
    "sg:tags":[
        "motion",
        "picture",
        "studio",
        "producer"
    ],
    "wof:name":"Galafilm Inc",
    "wof:placetype":"venue"
},
  "geometry": {"coordinates":[-73.60086800000001,45.526142],"type":"Point"}
}