{
  "type": "Feature",
  "properties": {
    "addr:full":"11818 Route 11 Village Blanchard NB E8P 1R5",
    "addr:housenumber":"11818",
    "addr:postcode":"e8p 1r5",
    "addr:street":"Route 11",
    "iso:country":"CA",
    "sg:address":"11818 Route 11",
    "sg:city":"Village Blanchard",
    "sg:classifiers":[
        {
            "category":"Food & Beverages",
            "subcategory":"Groceries & Convenience Stores",
            "type":"Retail Goods"
        }
    ],
    "sg:phone":"+1 506 727 7858",
    "sg:postcode":"E8P 1R5",
    "sg:province":"NB",
    "sg:tags":[
        "grocer"
    ],
    "wof:name":"Marche Freshmart",
    "wof:placetype":"venue"
},
  "geometry": {"coordinates":[-66.3815002441,48.0558013916],"type":"Point"}
}