{
  "type": "Feature",
  "properties": {
    "addr:full":"420 Rue Des Forges Trois-Rivieres QC G9A 2H5",
    "addr:housenumber":"420",
    "addr:postcode":"g9a 2h5",
    "addr:street":"Rue Des Forges Trois-Rivieres",
    "iso:country":"CA",
    "sg:address":"420 Rue Des Forges",
    "sg:city":"Trois-Rivieres",
    "sg:classifiers":[
        {
            "category":"Restaurant",
            "type":"Food & Drink"
        }
    ],
    "sg:phone":"+1 819 373 3838",
    "sg:postcode":"G9A 2H5",
    "sg:province":"QC",
    "wof:name":"Buffet Chinois Palais Royal",
    "wof:placetype":"venue"
},
  "geometry": {"coordinates":[-72.5444107056,46.3424758911],"type":"Point"}
}