{
  "type": "Feature",
  "properties": {
    "addr:full":"274 Place Des Cedres Dollard-Des-Ormeaux QC H9G 1W1",
    "addr:housenumber":"274",
    "addr:postcode":"h9g 1w1",
    "addr:street":"Place Des Cedres",
    "iso:country":"CA",
    "sg:address":"274 Place Des Cedres",
    "sg:city":"Dollard-Des-Ormeaux",
    "sg:classifiers":[
        {
            "category":"Home & Garden",
            "subcategory":"Building Materials",
            "type":"Retail Goods"
        }
    ],
    "sg:phone":"+1 514 620 5614",
    "sg:postcode":"H9G 1W1",
    "sg:province":"QC",
    "sg:tags":[
        "door"
    ],
    "wof:name":"Aluminium Cosmopolitain Inc",
    "wof:placetype":"venue"
},
  "geometry": {"coordinates":[-73.8306732178,45.4714164734],"type":"Point"}
}