{
  "type": "Feature",
  "properties": {
    "addr:full":"5635 Petrolia Line Petrolia ON N0N 1R0",
    "addr:housenumber":"5635",
    "addr:postcode":"n0n 1r0",
    "addr:street":"Petrolia Line",
    "iso:country":"CA",
    "sg:address":"5635 Petrolia Line",
    "sg:city":"Petrolia",
    "sg:classifiers":[
        {
            "category":"Building & Trades",
            "subcategory":"Construction",
            "type":"Services"
        }
    ],
    "sg:phone":"+1 519 882 1622",
    "sg:postcode":"N0N 1R0",
    "sg:province":"ON",
    "sg:tags":[
        "drainage",
        "contractor"
    ],
    "wof:name":"Jaques Farm Drainage",
    "wof:placetype":"venue"
},
  "geometry": {"coordinates":[-82.1165771484,42.8812484741],"type":"Point"}
}