{
  "type": "Feature",
  "properties": {
    "addr:full":"270 Av Michaud Rimouski QC G5L 6A1",
    "addr:housenumber":"270",
    "addr:postcode":"g5l 6a1",
    "addr:street":"Av Michaud",
    "iso:country":"CA",
    "sg:address":"270 Av Michaud",
    "sg:city":"Rimouski",
    "sg:classifiers":[
        {
            "category":"Retail",
            "subcategory":"Repair Shop",
            "type":"Services"
        }
    ],
    "sg:phone":"+1 418 724 2421",
    "sg:postcode":"G5L 6A1",
    "sg:province":"QC",
    "sg:tags":[
        "repairing",
        "piano",
        "refinishing"
    ],
    "wof:name":"Pianopro",
    "wof:placetype":"venue"
},
  "geometry": {"coordinates":[-68.5300750732,48.4422607422],"type":"Point"}
}