{
  "type": "Feature",
  "properties": {
    "iso:country":"CA",
    "sg:address":"259 Lewis Estates Blvd NW",
    "sg:city":"Edmonton",
    "sg:classifiers":[
        {
            "category":"Sports & Exercise",
            "subcategory":"Golf",
            "type":"Entertainment"
        }
    ],
    "sg:phone":"+1 780 489 4653",
    "sg:postcode":"T5T 6A4",
    "sg:province":"AB",
    "sg:tags":[
        "course"
    ],
    "wof:name":"Lewis Estates Golf Course",
    "wof:placetype":"venue"
},
  "geometry": {"coordinates":[-113.677612305,53.5122909546],"type":"Point"}
}