{
  "type": "Feature",
  "properties": {
    "iso:country":"CA",
    "sg:address":"17309 106 Ave NW",
    "sg:city":"Edmonton",
    "sg:classifiers":[
        {
            "category":"Manufacturing",
            "subcategory":"Tools & Machinery",
            "type":"Manufacturing & Wholesale Goods"
        }
    ],
    "sg:phone":"+1 780 483 0361",
    "sg:postcode":"T5S 1E7",
    "sg:province":"AB",
    "sg:tags":[
        "machine",
        "shop"
    ],
    "wof:name":"Mayfield Machine & Welding",
    "wof:placetype":"venue"
},
  "geometry": {"coordinates":[-113.61992645300001,53.5503425598],"type":"Point"}
}