{
  "type": "Feature",
  "properties": {
    "addr:full":"Dolbeau-Mistassini QC G8L 1M9",
    "addr:postcode":"g8l 1m9",
    "iso:country":"CA",
    "sg:city":"Dolbeau-Mistassini",
    "sg:classifiers":[
        {
            "category":"Manufacturing",
            "subcategory":"Printing",
            "type":"Manufacturing & Wholesale Goods"
        }
    ],
    "sg:phone":"+1 418 276 6211",
    "sg:postcode":"G8L 1M9",
    "sg:province":"QC",
    "sg:tags":[
        "newspaper"
    ],
    "wof:name":"Journal Nouvelles Hebdo",
    "wof:placetype":"venue"
},
  "geometry": {"coordinates":[-72.231567,48.881958],"type":"Point"}
}