{
  "type": "Feature",
  "properties": {
    "addr:full":"605 Chipmunk Janetville ON L0B 1K0",
    "addr:housenumber":"605",
    "addr:postcode":"l0b 1k0",
    "addr:street":"Chipmunk Janetville",
    "iso:country":"CA",
    "sg:address":"605 Chipmunk",
    "sg:city":"Janetville",
    "sg:classifiers":[
        {
            "category":"Building & Trades",
            "subcategory":"Plumbing",
            "type":"Services"
        }
    ],
    "sg:phone":"+1 705 878 0380",
    "sg:postcode":"L0B 1K0",
    "sg:province":"ON",
    "sg:tags":[
        "conditioning",
        "air",
        "system",
        "contractor"
    ],
    "wof:name":"Thermotech Heating & Cooling",
    "wof:placetype":"venue"
},
  "geometry": {"coordinates":[-78.69435882569999,44.2339286804],"type":"Point"}
}