{
  "type": "Feature",
  "properties": {
    "addr:full":"75 33rd St E Saskatoon SK S7K 0R8",
    "addr:housenumber":"75",
    "addr:postcode":"s7k 0r8",
    "addr:street":"33Rd St E",
    "iso:country":"CA",
    "sg:address":"75 33rd St E",
    "sg:city":"Saskatoon",
    "sg:classifiers":[
        {
            "category":"Manufacturing",
            "subcategory":"Pet Food",
            "type":"Manufacturing & Wholesale Goods"
        }
    ],
    "sg:phone":"+1 306 934 3200",
    "sg:postcode":"S7K 0R8",
    "sg:province":"SK",
    "sg:tags":[
        "flour",
        "mills"
    ],
    "wof:name":"Dawn Food Products Ltd",
    "wof:placetype":"venue"
},
  "geometry": {"coordinates":[-106.666816711,52.1437797546],"type":"Point"}
}