{
  "type": "Feature",
  "properties": {
    "iso:country":"CA",
    "sg:address":"105 Rue DE Montbrun",
    "sg:city":"Boucherville",
    "sg:classifiers":[
        {
            "category":"Manufacturing",
            "subcategory":"Tools & Machinery",
            "type":"Manufacturing & Wholesale Goods"
        }
    ],
    "sg:phone":"+1 450 655 1803",
    "sg:postcode":"J4B 4V1",
    "sg:province":"QC",
    "sg:tags":[
        "equipment",
        "electric"
    ],
    "wof:name":"Distrobution Atis Inc",
    "wof:placetype":"venue"
},
  "geometry": {"coordinates":[-73.449379,45.614662],"type":"Point"}
}