{
  "type": "Feature",
  "properties": {
    "addr:full":"364 Second Ave Sault Ste Marie ON P6C 4N3",
    "addr:housenumber":"364",
    "addr:postcode":"p6c 4n3",
    "addr:street":"Second Ave",
    "iso:country":"CA",
    "sg:address":"364 Second Ave",
    "sg:city":"Sault Ste Marie",
    "sg:classifiers":[
        {
            "category":"Shopping",
            "subcategory":"Pharmacy",
            "type":"Retail Goods"
        }
    ],
    "sg:phone":"+1 705 945 1215",
    "sg:postcode":"P6C 4N3",
    "sg:province":"ON",
    "wof:name":"Shoppers Drug Mart",
    "wof:placetype":"venue"
},
  "geometry": {"coordinates":[-84.368515,46.533115],"type":"Point"}
}