{
  "type": "Feature",
  "properties": {
    "addr:full":"27 Colborne St S Simcoe ON N3Y 4H2",
    "addr:housenumber":"27",
    "addr:postcode":"n3y 4h2",
    "addr:street":"Colborne St S",
    "iso:country":"CA",
    "sg:address":"27 Colborne St S",
    "sg:city":"Simcoe",
    "sg:classifiers":[
        {
            "category":"Cinema",
            "subcategory":"Movie Rental",
            "type":"Entertainment"
        }
    ],
    "sg:phone":"+1 519 426 6464",
    "sg:postcode":"N3Y 4H2",
    "sg:province":"ON",
    "sg:tags":[
        "leasing",
        "video",
        "disc",
        "tape"
    ],
    "wof:name":"Video 27",
    "wof:placetype":"venue"
},
  "geometry": {"coordinates":[-80.3059387207,42.8363494873],"type":"Point"}
}