{
  "type": "Feature",
  "properties": {
    "iso:country":"CA",
    "sg:address":"1138 Maybank St",
    "sg:city":"Ottawa",
    "sg:classifiers":[
        {
            "category":"Building & Trades",
            "subcategory":"Landscaping Services",
            "type":"Services"
        }
    ],
    "sg:phone":"+1 613 596 0467",
    "sg:postcode":"K2C 2W6",
    "sg:province":"ON",
    "sg:tags":[
        "landscape",
        "contractor"
    ],
    "wof:name":"Trillium Paysagement Landscpng",
    "wof:placetype":"venue"
},
  "geometry": {"coordinates":[-75.773308,45.35648],"type":"Point"}
}