{
  "type": "Feature",
  "properties": {
    "addr:full":"50 Commonwealth Ave Mount Pearl NL A1N 1W8",
    "addr:housenumber":"50",
    "addr:postcode":"a1n 1w8",
    "addr:street":"Commonwealth Ave",
    "iso:country":"CA",
    "sg:address":"50 Commonwealth Ave",
    "sg:city":"Mount Pearl",
    "sg:classifiers":[
        {
            "category":"Recreation",
            "type":"Entertainment"
        }
    ],
    "sg:phone":"+1 709 368 2500",
    "sg:postcode":"A1N 1W8",
    "sg:province":"NL",
    "sg:tags":[
        "parlor",
        "billiard"
    ],
    "wof:name":"Player's Cue Corp",
    "wof:placetype":"venue"
},
  "geometry": {"coordinates":[-52.806335,47.516594],"type":"Point"}
}