{
  "type": "Feature",
  "properties": {
    "addr:full":"3503 Boul Laurier Sainte-Madeleine QC J0H 1S0",
    "addr:housenumber":"3503",
    "addr:postcode":"j0h 1s0",
    "addr:street":"Boul Laurier",
    "iso:country":"CA",
    "sg:address":"3503 Boul Laurier",
    "sg:city":"Sainte-Madeleine",
    "sg:classifiers":[
        {
            "category":"Shopping",
            "subcategory":"Gifts & Souvenirs",
            "type":"Retail Goods"
        }
    ],
    "sg:phone":"+1 450 795 0095",
    "sg:postcode":"J0H 1S0",
    "sg:province":"QC",
    "sg:tags":[
        "material",
        "wrapping"
    ],
    "wof:name":"Via Samson",
    "wof:placetype":"venue"
},
  "geometry": {"coordinates":[-73.1206893921,45.5893669128],"type":"Point"}
}