{
  "type": "Feature",
  "properties": {
    "addr:full":"Saskatoon SK S7H 0W5",
    "addr:postcode":"s7h 0w5",
    "iso:country":"CA",
    "sg:city":"Saskatoon",
    "sg:classifiers":[
        {
            "category":"Banks & Credit Unions",
            "subcategory":"Financial Services",
            "type":"Services"
        }
    ],
    "sg:phone":"+1 306 653 1100",
    "sg:postcode":"S7H 0W5",
    "sg:province":"SK",
    "sg:tags":[
        "bankruptcy",
        "trustee"
    ],
    "wof:name":"Jeffrey Pinder & Assoc",
    "wof:placetype":"venue"
},
  "geometry": {"coordinates":[-106.59680938699999,52.1149101257],"type":"Point"}
}