{
  "type": "Feature",
  "properties": {
    "addr:full":"8040 Westminster Hwy Richmond BC V6X 1A6",
    "addr:housenumber":"8040",
    "addr:postcode":"v6x 1a6",
    "addr:street":"Westminster Hwy",
    "iso:country":"CA",
    "sg:address":"8040 Westminster Hwy",
    "sg:city":"Richmond",
    "sg:classifiers":[
        {
            "category":"Education",
            "subcategory":"Special Training",
            "type":"Public Place"
        }
    ],
    "sg:phone":"+1 604 276 8672",
    "sg:postcode":"V6X 1A6",
    "sg:province":"BC",
    "sg:tags":[
        "instruction",
        "music"
    ],
    "wof:name":"Piano Place Music Ctr Inc",
    "wof:placetype":"venue"
},
  "geometry": {"coordinates":[-123.135757,49.169994],"type":"Point"}
}