{
  "type": "Feature",
  "properties": {
    "iso:country":"CA",
    "sg:address":"55 St. Paul St W",
    "sg:city":"St Catharines",
    "sg:classifiers":[
        {
            "category":"Restaurant",
            "type":"Food & Drink"
        }
    ],
    "sg:phone":"+1 905 685 0888",
    "sg:postcode":"L2S 2C4",
    "sg:province":"ON",
    "wof:name":"Stop 55 Pizzeria Bar & Grill",
    "wof:placetype":"venue"
},
  "geometry": {"coordinates":[-79.250084,43.148884],"type":"Point"}
}