{
  "type": "Feature",
  "properties": {
    "addr:full":"Saint-Jacques-Le-Mineur QC J0J 1Z0",
    "addr:postcode":"qc j0j 1z0",
    "iso:country":"CA",
    "sg:city":"Saint-Jacques-Le-Mineur",
    "sg:classifiers":[
        {
            "category":"Building & Trades",
            "subcategory":"Construction",
            "type":"Services"
        }
    ],
    "sg:phone":"+1 450 347 8697",
    "sg:postcode":"J0J 1Z0",
    "sg:province":"QC",
    "sg:tags":[
        "excavating",
        "contractor"
    ],
    "wof:name":"Entreprises Gm Bouchard Inc",
    "wof:placetype":"venue"
},
  "geometry": {"coordinates":[-73.402961731,45.2927513123],"type":"Point"}
}