{
  "type": "Feature",
  "properties": {
    "addr:full":"300 Painted Post Dr Scarborough ON M1G 2M3",
    "addr:housenumber":"300",
    "addr:postcode":"m1g 2m3",
    "addr:street":"Painted Post Dr",
    "iso:country":"CA",
    "sg:address":"300 Painted Post Dr",
    "sg:city":"Scarborough",
    "sg:classifiers":[
        {
            "category":"Retail",
            "subcategory":"Auto Repair",
            "type":"Services"
        }
    ],
    "sg:phone":"+1 416 439 0818",
    "sg:postcode":"M1G 2M3",
    "sg:province":"ON",
    "sg:tags":[
        "repairing",
        "automobile"
    ],
    "wof:name":"Bertrand Tire & Auto Ctr",
    "wof:placetype":"venue"
},
  "geometry": {"coordinates":[-79.22827100000001,43.767651],"type":"Point"}
}