{
  "type": "Feature",
  "properties": {
    "addr:full":"215 River St Bedford QC J0J 1A0",
    "addr:housenumber":"215",
    "addr:postcode":"j0j 1a0",
    "addr:street":"River St",
    "iso:country":"CA",
    "sg:address":"215 River St",
    "sg:city":"Bedford",
    "sg:classifiers":[
        {
            "category":"Retail",
            "subcategory":"Funeral Services",
            "type":"Services"
        }
    ],
    "sg:phone":"+1 450 248 2911",
    "sg:postcode":"J0J 1A0",
    "sg:province":"QC",
    "sg:tags":[
        "director"
    ],
    "wof:name":"Joseph Dion & Fils Ltee",
    "wof:placetype":"venue"
},
  "geometry": {"coordinates":[-72.97101600000001,45.119949],"type":"Point"}
}