{
  "type": "Feature",
  "properties": {
    "addr:full":"Saskatoon SK S7K 0M8",
    "addr:postcode":"s7k 0m8",
    "iso:country":"CA",
    "sg:city":"Saskatoon",
    "sg:classifiers":[
        {
            "category":"Health Services",
            "subcategory":"Doctor",
            "type":"Services"
        }
    ],
    "sg:phone":"+1 306 244 6818",
    "sg:postcode":"S7K 0M8",
    "sg:province":"SK",
    "sg:tags":[
        "physician",
        "surgeon"
    ],
    "wof:name":"Hayes, Paul MD",
    "wof:placetype":"venue"
},
  "geometry": {"coordinates":[-106.653358459,52.1367797852],"type":"Point"}
}