{
  "type": "Feature",
  "properties": {
    "addr:full":"1270 Cedar Ave Trail BC V1R 4C1",
    "addr:housenumber":"1270",
    "addr:postcode":"bc v1r 4c1",
    "addr:street":"Cedar Ave Trail",
    "iso:country":"CA",
    "sg:address":"1270 Cedar Ave",
    "sg:city":"Trail",
    "sg:classifiers":[
        {
            "category":"Restaurant",
            "type":"Food & Drink"
        }
    ],
    "sg:phone":"+1 250 364 9800",
    "sg:postcode":"V1R 4C1",
    "sg:province":"BC",
    "sg:tags":[
        "pizza"
    ],
    "wof:name":"Ferraro's Pizza",
    "wof:placetype":"venue"
},
  "geometry": {"coordinates":[-117.709472656,49.0958824158],"type":"Point"}
}