{
  "type": "Feature",
  "properties": {
    "addr:full":"Toronto ON M5A 1T7",
    "addr:postcode":"m5a 1t7",
    "iso:country":"CA",
    "sg:city":"Toronto",
    "sg:classifiers":[
        {
            "category":"Professional",
            "subcategory":"Management & Consulting",
            "type":"Services"
        }
    ],
    "sg:phone":"+1 416 861 9850",
    "sg:postcode":"M5A 1T7",
    "sg:province":"ON",
    "sg:tags":[
        "marketing",
        "consultant"
    ],
    "wof:name":"Marketing Solutions Ltd",
    "wof:placetype":"venue"
},
  "geometry": {"coordinates":[-79.360405,43.656559],"type":"Point"}
}