{
  "type": "Feature",
  "properties": {
    "iso:country":"CA",
    "sg:address":"3652 Rue Queen",
    "sg:city":"Rawdon",
    "sg:classifiers":[
        {
            "category":"Shopping",
            "subcategory":"Gifts & Souvenirs",
            "type":"Retail Goods"
        }
    ],
    "sg:phone":"+1 450 834 1919",
    "sg:postcode":"J0K 1S0",
    "sg:province":"QC",
    "sg:tags":[
        "shop",
        "clothing"
    ],
    "wof:name":"Trouvailles DE Marie Pop'In",
    "wof:placetype":"venue"
},
  "geometry": {"coordinates":[-73.70765686039999,46.0426177979],"type":"Point"}
}