{
  "type": "Feature",
  "properties": {
    "addr:full":"110 Mcelmon Rd Debert NS B0M 1G0",
    "addr:housenumber":"110",
    "addr:postcode":"b0m 1g0",
    "addr:street":"Mcelmon Rd",
    "iso:country":"CA",
    "sg:address":"110 Mcelmon Rd",
    "sg:city":"Debert",
    "sg:classifiers":[
        {
            "category":"Home & Garden",
            "subcategory":"Building Materials",
            "type":"Retail Goods"
        }
    ],
    "sg:phone":"+1 902 662 3100",
    "sg:postcode":"B0M 1G0",
    "sg:province":"NS",
    "sg:tags":[
        "windows"
    ],
    "wof:name":"Kohler International Window",
    "wof:placetype":"venue"
},
  "geometry": {"coordinates":[-63.4477386475,45.430480957],"type":"Point"}
}