{
  "type": "Feature",
  "properties": {
    "addr:full":"4113 Route 126 Indian Mountain NB E1G 2Z4",
    "addr:housenumber":"4113",
    "addr:postcode":"e1g 2z4",
    "addr:street":"Route 126",
    "iso:country":"CA",
    "sg:address":"4113 Route 126",
    "sg:city":"Indian Mountain",
    "sg:classifiers":[
        {
            "category":"Travel",
            "subcategory":"Hotels & Motels",
            "type":"Entertainment"
        }
    ],
    "sg:phone":"+1 506 861 9091",
    "sg:postcode":"E1G 2Z4",
    "sg:province":"NB",
    "sg:tags":[
        "inn"
    ],
    "wof:name":"Saunders Country Inn & Estate",
    "wof:placetype":"venue"
},
  "geometry": {"coordinates":[-64.93963599999999,46.16571],"type":"Point"}
}