{
  "type": "Feature",
  "properties": {
    "addr:full":"224 Merton St Toronto ON M4S 1A1",
    "addr:housenumber":"224",
    "addr:postcode":"m4s 1a1",
    "addr:street":"Merton St",
    "iso:country":"CA",
    "sg:address":"224 Merton St",
    "sg:city":"Toronto",
    "sg:classifiers":[
        {
            "category":"Professional",
            "subcategory":"Management & Consulting",
            "type":"Services"
        }
    ],
    "sg:phone":"+1 416 440 0071",
    "sg:postcode":"M4S 1A1",
    "sg:province":"ON",
    "sg:tags":[
        "marketing",
        "consultant"
    ],
    "wof:name":"Macaulay Marketing Assoc",
    "wof:placetype":"venue"
},
  "geometry": {"coordinates":[-79.39008331300001,43.697517395],"type":"Point"}
}