{
  "type": "Feature",
  "properties": {
    "addr:full":"730 Danforth Ave Toronto ON M4J 1L5",
    "addr:housenumber":"730",
    "addr:postcode":"m4j 1l5",
    "addr:street":"Danforth Ave",
    "iso:country":"CA",
    "sg:address":"730 Danforth Ave",
    "sg:city":"Toronto",
    "sg:classifiers":[
        {
            "category":"Cinema",
            "subcategory":"Movie Rental",
            "type":"Entertainment"
        }
    ],
    "sg:phone":"+1 416 406 3441",
    "sg:postcode":"M4J 1L5",
    "sg:province":"ON",
    "sg:tags":[
        "leasing",
        "video",
        "disc",
        "tape"
    ],
    "wof:name":"Rogers Video",
    "wof:placetype":"venue"
},
  "geometry": {"coordinates":[-79.342743,43.679493],"type":"Point"}
}