{
  "type": "Feature",
  "properties": {
    "addr:full":"211 Mcdonald St N Regina SK S4N 5W2",
    "addr:housenumber":"211",
    "addr:postcode":"s4n 5w2",
    "addr:street":"Mcdonald St N",
    "iso:country":"CA",
    "sg:address":"211 Mcdonald St N",
    "sg:city":"Regina",
    "sg:classifiers":[
        {
            "category":"Building & Trades",
            "subcategory":"Plumbing",
            "type":"Services"
        }
    ],
    "sg:phone":"+1 306 721 7448",
    "sg:postcode":"S4N 5W2",
    "sg:province":"SK",
    "sg:tags":[
        "mechanical",
        "contractor"
    ],
    "wof:name":"Conley Management Ltd",
    "wof:placetype":"venue"
},
  "geometry": {"coordinates":[-104.57487500000001,50.478481],"type":"Point"}
}