{
  "type": "Feature",
  "properties": {
    "addr:full":"Winlaw BC V0G 2J0",
    "addr:postcode":"v0g 2j0",
    "iso:country":"CA",
    "sg:city":"Winlaw",
    "sg:classifiers":[
        {
            "category":"Wholesale",
            "subcategory":"Farm Supplies",
            "type":"Manufacturing & Wholesale Goods"
        }
    ],
    "sg:phone":"+1 250 226 7034",
    "sg:postcode":"V0G 2J0",
    "sg:province":"BC",
    "sg:tags":[
        "feed"
    ],
    "wof:name":"Egg-Cetera Feed & Supplies",
    "wof:placetype":"venue"
},
  "geometry": {"coordinates":[-117.498512268,49.6750488281],"type":"Point"}
}