{
  "type": "Feature",
  "properties": {
    "addr:full":"655 Main St Winnipeg MB R3B 1E3",
    "addr:housenumber":"655",
    "addr:postcode":"r3b 1e3",
    "addr:street":"Main St",
    "iso:country":"CA",
    "sg:address":"655 Main St",
    "sg:city":"Winnipeg",
    "sg:classifiers":[
        {
            "category":"Travel",
            "subcategory":"Hotels & Motels",
            "type":"Entertainment"
        }
    ],
    "sg:phone":"+1 204 942 6925",
    "sg:postcode":"R3B 1E3",
    "sg:province":"MB",
    "wof:name":"Manwin Hotel",
    "wof:placetype":"venue"
},
  "geometry": {"coordinates":[-97.1350479126,49.9030799866],"type":"Point"}
}