{
  "type": "Feature",
  "properties": {
    "iso:country":"CA",
    "sg:address":"2468 Sherbrooke St",
    "sg:city":"Peterborough",
    "sg:classifiers":[
        {
            "category":"Recreation",
            "subcategory":"Marina",
            "type":"Entertainment"
        }
    ],
    "sg:phone":"+1 705 745 0186",
    "sg:postcode":"K9J 6X4",
    "sg:province":"ON",
    "sg:tags":[
        "outboard",
        "motor"
    ],
    "wof:name":"Harrison Power Sports",
    "wof:placetype":"venue"
},
  "geometry": {"coordinates":[-78.37828063960001,44.2881393433],"type":"Point"}
}