{
  "type": "Feature",
  "properties": {
    "addr:full":"485 133 Rte Sabrevois QC J0J 2G0",
    "addr:housenumber":"485 133",
    "addr:postcode":"j0j 2g0",
    "addr:street":"Rte Sabrevois",
    "iso:country":"CA",
    "sg:address":"485 133 Rte",
    "sg:city":"Sabrevois",
    "sg:classifiers":[
        {
            "category":"Food & Beverages",
            "subcategory":"Fruits & Vegetables",
            "type":"Retail Goods"
        }
    ],
    "sg:phone":"+1 450 346 6867",
    "sg:postcode":"J0J 2G0",
    "sg:province":"QC",
    "wof:name":"Ferme M Reid",
    "wof:placetype":"venue"
},
  "geometry": {"coordinates":[-73.2304992676,45.2063903809],"type":"Point"}
}