{
  "type": "Feature",
  "properties": {
    "iso:country":"CA",
    "sg:city":"Montreal",
    "sg:classifiers":[
        {
            "category":"Professional",
            "subcategory":"Lawyer & Legal Services",
            "type":"Services"
        }
    ],
    "sg:phone":"+1 514 844 8804",
    "sg:postcode":"H2X 3P3",
    "sg:province":"QC",
    "sg:tags":[
        "attorney"
    ],
    "wof:name":"Papillon Guilbault",
    "wof:placetype":"venue"
},
  "geometry": {"coordinates":[-73.559151,45.512012],"type":"Point"}
}