{
  "type": "Feature",
  "properties": {
    "iso:country":"CA",
    "sg:address":"57 Rue Prince-Arthur E",
    "sg:city":"Montreal",
    "sg:classifiers":[
        {
            "category":"Bars & Pubs",
            "type":"Food & Drink"
        }
    ],
    "sg:phone":"+1 514 844 1010",
    "sg:postcode":"H2X 1B4",
    "sg:province":"QC",
    "sg:tags":[
        "discotheque"
    ],
    "wof:name":"Cafe Campus",
    "wof:placetype":"venue"
},
  "geometry": {"coordinates":[-73.572166,45.514545],"type":"Point"}
}