{
  "type": "Feature",
  "properties": {
    "addr:full":"27 Rue Principale N Amos QC J9T 2K7",
    "addr:housenumber":"27",
    "addr:postcode":"j9t 2k7",
    "addr:street":"Rue Principale N Amos",
    "iso:country":"CA",
    "sg:address":"27 Rue Principale N",
    "sg:city":"Amos",
    "sg:classifiers":[
        {
            "category":"Utilities",
            "subcategory":"Cable",
            "type":"Services"
        }
    ],
    "sg:phone":"+1 819 732 5570",
    "sg:postcode":"J9T 2K7",
    "sg:province":"QC",
    "sg:tags":[
        "television"
    ],
    "wof:name":"Teledistribution",
    "wof:placetype":"venue"
},
  "geometry": {"coordinates":[-78.1161804199,48.5724143982],"type":"Point"}
}