{
  "type": "Feature",
  "properties": {
    "iso:country":"CA",
    "sg:address":"115 Rte Du President-Kennedy",
    "sg:city":"Levis",
    "sg:classifiers":[
        {
            "category":"Travel",
            "subcategory":"Travel Agent",
            "type":"Entertainment"
        }
    ],
    "sg:phone":"+1 418 833 6823",
    "sg:postcode":"G6V 6C8",
    "sg:province":"QC",
    "sg:tags":[
        "agency",
        "bureau"
    ],
    "wof:name":"Agence DE Voyages Paradis Inc",
    "wof:placetype":"venue"
},
  "geometry": {"coordinates":[-71.166924,46.788883],"type":"Point"}
}