{
  "type": "Feature",
  "properties": {
    "iso:country":"CA",
    "sg:address":"2538 Main St",
    "sg:city":"Westbank",
    "sg:classifiers":[
        {
            "category":"Shopping",
            "subcategory":"Computers & Home Electronics",
            "type":"Retail Goods"
        }
    ],
    "sg:phone":"+1 250 707 0622",
    "sg:postcode":"V4T 2E3",
    "sg:province":"BC",
    "sg:tags":[
        "software"
    ],
    "wof:name":"Quantech Software.com Inc",
    "wof:placetype":"venue"
},
  "geometry": {"coordinates":[-119.633148193,49.8294219971],"type":"Point"}
}