{
  "type": "Feature",
  "properties": {
    "addr:full":"665 Garson Coniston Rd Garson ON P3L 1V9",
    "addr:housenumber":"665",
    "addr:postcode":"p3l 1v9",
    "addr:street":"Garson Coniston Rd",
    "iso:country":"CA",
    "sg:address":"665 Garson Coniston Rd",
    "sg:city":"Garson",
    "sg:classifiers":[
        {
            "category":"Building & Trades",
            "subcategory":"Construction",
            "type":"Services"
        }
    ],
    "sg:phone":"+1 705 693 3867",
    "sg:postcode":"P3L 1V9",
    "sg:province":"ON",
    "sg:tags":[
        "masonry",
        "contractor"
    ],
    "wof:name":"Can Masonry Inc",
    "wof:placetype":"venue"
},
  "geometry": {"coordinates":[-80.83944700000001,46.51511],"type":"Point"}
}