{
  "type": "Feature",
  "properties": {
    "iso:country":"CA",
    "sg:address":"385 Rue Saint-Eustache # E",
    "sg:city":"Saint-Eustache",
    "sg:classifiers":[
        {
            "category":"Personal",
            "type":"Services"
        }
    ],
    "sg:phone":"+1 450 473 7627",
    "sg:postcode":"J7R 2M4",
    "sg:province":"QC",
    "sg:tags":[
        "electrolysis"
    ],
    "wof:name":"Esthetique Nany",
    "wof:placetype":"venue"
},
  "geometry": {"coordinates":[-73.9035186768,45.5594787598],"type":"Point"}
}