{
  "type": "Feature",
  "properties": {
    "addr:full":"North York ON M2J 2K9",
    "addr:postcode":"m2j 2k9",
    "iso:country":"CA",
    "sg:city":"North York",
    "sg:classifiers":[
        {
            "category":"Health Services",
            "subcategory":"Doctor",
            "type":"Services"
        }
    ],
    "sg:phone":"+1 416 225 9299",
    "sg:postcode":"M2J 2K9",
    "sg:province":"ON",
    "sg:tags":[
        "physician",
        "surgeon"
    ],
    "wof:name":"Born, Abraham MD",
    "wof:placetype":"venue"
},
  "geometry": {"coordinates":[-79.365746,43.779411],"type":"Point"}
}