{
  "type": "Feature",
  "properties": {
    "addr:full":"395 Cochrane Crt Port Perry ON L9L 1N1",
    "addr:housenumber":"395",
    "addr:postcode":"l9l 1n1",
    "addr:street":"Cochrane Crt",
    "iso:country":"CA",
    "sg:address":"395 Cochrane Crt",
    "sg:city":"Port Perry",
    "sg:classifiers":[
        {
            "category":"Personal",
            "type":"Services"
        }
    ],
    "sg:phone":"+1 905 985 0031",
    "sg:postcode":"L9L 1N1",
    "sg:province":"ON",
    "sg:tags":[
        "wedding",
        "chapel"
    ],
    "wof:name":"Durham Marriage Svc",
    "wof:placetype":"venue"
},
  "geometry": {"coordinates":[-78.95254516599999,44.109413147],"type":"Point"}
}