{
  "type": "Feature",
  "properties": {
    "addr:full":"5420 53 Ave SE Calgary AB T2C 4R3",
    "addr:housenumber":"5420",
    "addr:postcode":"t2c 4r3",
    "addr:street":"53 Ave Se",
    "iso:country":"CA",
    "sg:address":"5420 53 Ave SE",
    "sg:city":"Calgary",
    "sg:classifiers":[
        {
            "category":"Retail",
            "subcategory":"Auto Repair",
            "type":"Services"
        }
    ],
    "sg:phone":"+1 403 279 8487",
    "sg:postcode":"T2C 4R3",
    "sg:province":"AB",
    "sg:tags":[
        "trailer"
    ],
    "wof:name":"Rpm Trailer Repair Svc",
    "wof:placetype":"venue"
},
  "geometry": {"coordinates":[-113.955665588,51.0052223206],"type":"Point"}
}