{
  "type": "Feature",
  "properties": {
    "iso:country":"CA",
    "sg:address":"119 Rue Saint-Pierre",
    "sg:city":"Matane",
    "sg:classifiers":[
        {
            "category":"Real Estate",
            "subcategory":"Real Estate Agent",
            "type":"Services"
        }
    ],
    "sg:phone":"+1 418 562 5555",
    "sg:postcode":"G4W 2B6",
    "sg:province":"QC",
    "sg:tags":[
        "authorities",
        "housing",
        "apartment"
    ],
    "wof:name":"Immeubles Rioux",
    "wof:placetype":"venue"
},
  "geometry": {"coordinates":[-67.5303268433,48.8465156555],"type":"Point"}
}