{
  "type": "Feature",
  "properties": {
    "addr:full":"67 Glenbrook Pl SW Calgary AB T3E 6W4",
    "addr:housenumber":"67",
    "addr:postcode":"t3e 6w4",
    "addr:street":"Glenbrook Pl Sw",
    "iso:country":"CA",
    "sg:address":"67 Glenbrook Pl SW",
    "sg:city":"Calgary",
    "sg:classifiers":[
        {
            "category":"Professional",
            "subcategory":"Business Services",
            "type":"Services"
        }
    ],
    "sg:phone":"+1 403 246 6266",
    "sg:postcode":"T3E 6W4",
    "sg:province":"AB",
    "sg:tags":[
        "interior",
        "consultant",
        "design",
        "decorator",
        "furniture"
    ],
    "wof:name":"Mc Arthur Fine Furniture",
    "wof:placetype":"venue"
},
  "geometry": {"coordinates":[-114.162003,51.02187],"type":"Point"}
}