{
  "type": "Feature",
  "properties": {
    "addr:full":"2114 Boul Du Cure-Labelle Saint-Jerome QC J7Y 1S8",
    "addr:housenumber":"2114",
    "addr:postcode":"j7y 1s8",
    "addr:street":"Boul Du Cure-Labelle Saint-Jerome",
    "iso:country":"CA",
    "sg:address":"2114 Boul Du Cure-Labelle",
    "sg:city":"Saint-Jerome",
    "sg:classifiers":[
        {
            "category":"Health Services",
            "subcategory":"Doctor",
            "type":"Services"
        }
    ],
    "sg:phone":"+1 450 432 4424",
    "sg:postcode":"J7Y 1S8",
    "sg:province":"QC",
    "sg:tags":[
        "physician",
        "surgeon"
    ],
    "wof:name":"Osteopathie Pierre Lafleur",
    "wof:placetype":"venue"
},
  "geometry": {"coordinates":[-74.0107955933,45.7993736267],"type":"Point"}
}