{
  "type": "Feature",
  "properties": {
    "addr:full":"17 Dundee Ave Mount Pearl NL A1N 4R6",
    "addr:housenumber":"17",
    "addr:postcode":"a1n 4r6",
    "addr:street":"Dundee Ave",
    "iso:country":"CA",
    "sg:address":"17 Dundee Ave",
    "sg:city":"Mount Pearl",
    "sg:classifiers":[
        {
            "category":"Government",
            "subcategory":"Office",
            "type":"Public Place"
        }
    ],
    "sg:phone":"+1 709 368 6790",
    "sg:postcode":"A1N 4R6",
    "sg:province":"NL",
    "sg:tags":[
        "federal",
        "affairs"
    ],
    "wof:name":"Italian Consulate",
    "wof:placetype":"venue"
},
  "geometry": {"coordinates":[-52.83926,47.518646],"type":"Point"}
}