{
  "type": "Feature",
  "properties": {
    "addr:full":"14073 18 Ave Surrey BC V4A 6S9",
    "addr:housenumber":"14073",
    "addr:postcode":"v4a 6s9",
    "addr:street":"18 Ave",
    "iso:country":"CA",
    "sg:address":"14073 18 Ave",
    "sg:city":"Surrey",
    "sg:classifiers":[
        {
            "category":"Retail",
            "subcategory":"Repair Shop",
            "type":"Services"
        }
    ],
    "sg:phone":"+1 604 531 0715",
    "sg:postcode":"V4A 6S9",
    "sg:province":"BC",
    "sg:tags":[
        "lock",
        "locksmith"
    ],
    "wof:name":"White Rock Lock & Key",
    "wof:placetype":"venue"
},
  "geometry": {"coordinates":[-122.832291,49.034805],"type":"Point"}
}