{
  "type": "Feature",
  "properties": {
    "addr:full":"Torbay NL A1K 1K1",
    "addr:postcode":"a1k 1k1",
    "iso:country":"CA",
    "sg:city":"Torbay",
    "sg:classifiers":[
        {
            "category":"Building & Trades",
            "subcategory":"Construction",
            "type":"Services"
        }
    ],
    "sg:phone":"+1 709 437 2777",
    "sg:postcode":"A1K 1K1",
    "sg:province":"NL",
    "sg:tags":[
        "tile",
        "concrete",
        "contractor"
    ],
    "wof:name":"Terra Nova Tile Ltd",
    "wof:placetype":"venue"
},
  "geometry": {"coordinates":[-52.7331695557,47.6571998596],"type":"Point"}
}