{
  "type": "Feature",
  "properties": {
    "addr:full":"13008 115 St NW Edmonton AB T5E 5G3",
    "addr:housenumber":"13008",
    "addr:postcode":"t5e 5g3",
    "addr:street":"115 St Nw",
    "iso:country":"CA",
    "sg:address":"13008 115 St NW",
    "sg:city":"Edmonton",
    "sg:classifiers":[
        {
            "category":"Manufacturing",
            "subcategory":"Signs",
            "type":"Manufacturing & Wholesale Goods"
        }
    ],
    "sg:phone":"+1 780 451 2829",
    "sg:postcode":"T5E 5G3",
    "sg:province":"AB",
    "wof:name":"Attractive Signs",
    "wof:placetype":"venue"
},
  "geometry": {"coordinates":[-113.520095825,53.5901908875],"type":"Point"}
}