{
  "type": "Feature",
  "properties": {
    "addr:full":"2300 Dixie Rd Mississauga ON L4Y 1Z4",
    "addr:housenumber":"2300",
    "addr:postcode":"l4y 1z4",
    "addr:street":"Dixie Rd",
    "iso:country":"CA",
    "sg:address":"2300 Dixie Rd",
    "sg:city":"Mississauga",
    "sg:classifiers":[
        {
            "category":"Manufacturing",
            "subcategory":"Apparel",
            "type":"Manufacturing & Wholesale Goods"
        }
    ],
    "sg:phone":"+1 905 276 3399",
    "sg:postcode":"L4Y 1Z4",
    "sg:province":"ON",
    "sg:tags":[
        "bridal",
        "supply"
    ],
    "wof:name":"Gordon Dress",
    "wof:placetype":"venue"
},
  "geometry": {"coordinates":[-79.57629394529999,43.6037826538],"type":"Point"}
}