{
  "type": "Feature",
  "properties": {
    "addr:full":"Port Coquitlam BC V3C 6P3",
    "addr:postcode":"v3c 6p3",
    "iso:country":"CA",
    "sg:city":"Port Coquitlam",
    "sg:classifiers":[
        {
            "category":"Manufacturing",
            "subcategory":"Building Materials",
            "type":"Manufacturing & Wholesale Goods"
        }
    ],
    "sg:phone":"+1 604 468 7749",
    "sg:postcode":"V3C 6P3",
    "sg:province":"BC",
    "wof:name":"Wildwood Custom Millwork",
    "wof:placetype":"venue"
},
  "geometry": {"coordinates":[-122.76252746599999,49.242931366],"type":"Point"}
}