{
  "type": "Feature",
  "properties": {
    "addr:full":"Halifax NS B3M 4L4",
    "addr:postcode":"b3m 4l4",
    "iso:country":"CA",
    "sg:city":"Halifax",
    "sg:classifiers":[
        {
            "category":"Real Estate",
            "subcategory":"Real Estate Operator",
            "type":"Services"
        }
    ],
    "sg:phone":"+1 902 457 3600",
    "sg:postcode":"B3M 4L4",
    "sg:province":"NS",
    "sg:tags":[
        "apartment"
    ],
    "wof:name":"Stonecrest Village",
    "wof:placetype":"venue"
},
  "geometry": {"coordinates":[-63.662891,44.668827],"type":"Point"}
}