{
  "type": "Feature",
  "properties": {
    "addr:full":"Gold River BC V0P 1G0",
    "addr:postcode":"v0p 1g0",
    "iso:country":"CA",
    "sg:city":"Gold River",
    "sg:classifiers":[
        {
            "category":"Building & Trades",
            "subcategory":"Construction",
            "type":"Services"
        }
    ],
    "sg:phone":"+1 250 283 7315",
    "sg:postcode":"V0P 1G0",
    "sg:province":"BC",
    "sg:tags":[
        "excavating",
        "contractor"
    ],
    "wof:name":"Conuma Excavating & Trucking",
    "wof:placetype":"venue"
},
  "geometry": {"coordinates":[-126.054450989,49.772693634],"type":"Point"}
}