{
  "type": "Feature",
  "properties": {
    "addr:full":"205 Rue Fraserville Riviere-Du-Loup QC G5R 5M3",
    "addr:housenumber":"205",
    "addr:postcode":"g5r 5m3",
    "addr:street":"Rue Fraserville Riviere-Du-Loup",
    "iso:country":"CA",
    "sg:address":"205 Rue Fraserville",
    "sg:city":"Riviere-Du-Loup",
    "sg:classifiers":[
        {
            "category":"Home & Garden",
            "subcategory":"Building Materials",
            "type":"Retail Goods"
        }
    ],
    "sg:phone":"+1 418 867 3222",
    "sg:postcode":"G5R 5M3",
    "sg:province":"QC",
    "sg:tags":[
        "door"
    ],
    "wof:name":"Martin Portes & Fenetres",
    "wof:placetype":"venue"
},
  "geometry": {"coordinates":[-69.539772,47.811848],"type":"Point"}
}