{
  "type": "Feature",
  "properties": {
    "addr:full":"480 Garyray Dr North York ON M9L 1P8",
    "addr:housenumber":"480",
    "addr:postcode":"m9l 1p8",
    "addr:street":"Garyray Dr",
    "iso:country":"CA",
    "sg:address":"480 Garyray Dr",
    "sg:city":"North York",
    "sg:classifiers":[
        {
            "category":"Wholesale",
            "subcategory":"Metals & Minerals",
            "type":"Manufacturing & Wholesale Goods"
        }
    ],
    "sg:phone":"+1 416 749 8822",
    "sg:postcode":"M9L 1P8",
    "sg:province":"ON",
    "sg:tags":[
        "rope",
        "wire"
    ],
    "wof:name":"Cable Craft Ltd",
    "wof:placetype":"venue"
},
  "geometry": {"coordinates":[-79.5498886108,43.7669525146],"type":"Point"}
}