{
  "type": "Feature",
  "properties": {
    "addr:full":"North York ON M9L 1X9",
    "addr:postcode":"m9l 1x9",
    "iso:country":"CA",
    "sg:city":"North York",
    "sg:classifiers":[
        {
            "category":"Building & Trades",
            "subcategory":"Construction",
            "type":"Services"
        }
    ],
    "sg:phone":"+1 416 740 3876",
    "sg:postcode":"M9L 1X9",
    "sg:province":"ON",
    "sg:tags":[
        "paving",
        "contractor"
    ],
    "wof:name":"Roadside Paving Ltd",
    "wof:placetype":"venue"
},
  "geometry": {"coordinates":[-79.5533447266,43.7572975159],"type":"Point"}
}