{
  "type": "Feature",
  "properties": {
    "addr:full":"257 Huntingdon Ave Stratford ON N5A 6P7",
    "addr:housenumber":"257",
    "addr:postcode":"n5a 6p7",
    "addr:street":"Huntingdon Ave",
    "iso:country":"CA",
    "sg:address":"257 Huntingdon Ave",
    "sg:city":"Stratford",
    "sg:classifiers":[
        {
            "category":"Professional",
            "subcategory":"Advertising",
            "type":"Services"
        }
    ],
    "sg:phone":"+1 519 273 9369",
    "sg:postcode":"N5A 6P7",
    "sg:province":"ON",
    "sg:tags":[
        "counselor"
    ],
    "wof:name":"James Fitzgerald & Assoc",
    "wof:placetype":"venue"
},
  "geometry": {"coordinates":[-80.99372099999999,43.379147],"type":"Point"}
}