{
  "type": "Feature",
  "properties": {
    "addr:full":"116 Deer Run Close SE Calgary AB T2J 5P6",
    "addr:housenumber":"116",
    "addr:postcode":"t2j 5p6",
    "addr:street":"Deer Run Close Se",
    "iso:country":"CA",
    "sg:address":"116 Deer Run Close SE",
    "sg:city":"Calgary",
    "sg:classifiers":[
        {
            "category":"Professional",
            "subcategory":"Art Services",
            "type":"Services"
        }
    ],
    "sg:phone":"+1 403 225 0092",
    "sg:postcode":"T2J 5P6",
    "sg:province":"AB",
    "sg:tags":[
        "graphic",
        "designer"
    ],
    "wof:name":"Stater Communications Inc",
    "wof:placetype":"venue"
},
  "geometry": {"coordinates":[-114.010391,50.918621],"type":"Point"}
}