{
  "type": "Feature",
  "properties": {
    "addr:full":"223 Waterloo St Exeter ON N0M 1S2",
    "addr:housenumber":"223",
    "addr:postcode":"n0m 1s2",
    "addr:street":"Waterloo St",
    "iso:country":"CA",
    "sg:address":"223 Waterloo St",
    "sg:city":"Exeter",
    "sg:classifiers":[
        {
            "category":"Building & Trades",
            "subcategory":"Construction",
            "type":"Services"
        }
    ],
    "sg:phone":"+1 519 235 1701",
    "sg:postcode":"N0M 1S2",
    "sg:province":"ON",
    "sg:tags":[
        "painter"
    ],
    "wof:name":"M & M Painting & Decorating",
    "wof:placetype":"venue"
},
  "geometry": {"coordinates":[-81.4873352051,43.3406524658],"type":"Point"}
}