{
  "type": "Feature",
  "properties": {
    "iso:country":"CA",
    "sg:address":"1270 Av Van Horne",
    "sg:city":"Outremont",
    "sg:classifiers":[
        {
            "category":"Retail",
            "subcategory":"Laundry & Dry Cleaning",
            "type":"Services"
        }
    ],
    "sg:phone":"+1 514 274 4964",
    "sg:postcode":"H2V 1K6",
    "sg:province":"QC",
    "wof:name":"Yvonne's Laundry",
    "wof:placetype":"venue"
},
  "geometry": {"coordinates":[-73.61364,45.521637],"type":"Point"}
}