{
  "type": "Feature",
  "properties": {
    "iso:country":"CA",
    "sg:city":"Boucherville",
    "sg:classifiers":[
        {
            "category":"Shopping",
            "subcategory":"Clothing, Apparel, & Fashions",
            "type":"Retail Goods"
        }
    ],
    "sg:phone":"+1 450 641 9930",
    "sg:postcode":"J4B 6P5",
    "sg:province":"QC",
    "sg:tags":[
        "furnishing"
    ],
    "wof:name":"L'Elegance Pour Lui",
    "wof:placetype":"venue"
},
  "geometry": {"coordinates":[-73.43412,45.589848],"type":"Point"}
}