{
  "type": "Feature",
  "properties": {
    "addr:full":"1520 39 St SE Calgary AB T2A 1H9",
    "addr:housenumber":"1520",
    "addr:postcode":"t2a 1h9",
    "addr:street":"39 St Se",
    "iso:country":"CA",
    "sg:address":"1520 39 St SE",
    "sg:city":"Calgary",
    "sg:classifiers":[
        {
            "category":"Education",
            "subcategory":"School",
            "type":"Public Place"
        }
    ],
    "sg:phone":"+1 403 777 8220",
    "sg:postcode":"T2A 1H9",
    "sg:province":"AB",
    "wof:name":"Patrick Airlie Elementary Schl",
    "wof:placetype":"venue"
},
  "geometry": {"coordinates":[-113.97693599999999,51.040657],"type":"Point"}
}