{
  "type": "Feature",
  "properties": {
    "addr:full":"North York ON M5M 4A4",
    "addr:postcode":"m5m 4a4",
    "iso:country":"CA",
    "sg:city":"North York",
    "sg:classifiers":[
        {
            "category":"Personal",
            "subcategory":"Beauty Salon",
            "type":"Services"
        }
    ],
    "sg:phone":"+1 416 485 3444",
    "sg:postcode":"M5M 4A4",
    "sg:province":"ON",
    "wof:name":"Amys Art Coiffure",
    "wof:placetype":"venue"
},
  "geometry": {"coordinates":[-79.42021942140001,43.7356758118],"type":"Point"}
}