{
  "type": "Feature",
  "properties": {
    "addr:full":"42 Norlorne Dr Winnipeg MB R3R 2Y6",
    "addr:housenumber":"42",
    "addr:postcode":"r3r 2y6",
    "addr:street":"Norlorne Dr",
    "iso:country":"CA",
    "sg:address":"42 Norlorne Dr",
    "sg:city":"Winnipeg",
    "sg:classifiers":[
        {
            "category":"Real Estate",
            "subcategory":"Surveying",
            "type":"Services"
        }
    ],
    "sg:phone":"+1 204 284 9530",
    "sg:postcode":"R3R 2Y6",
    "sg:province":"MB",
    "sg:tags":[
        "surveyor"
    ],
    "wof:name":"Smt Survey & Design",
    "wof:placetype":"venue"
},
  "geometry": {"coordinates":[-97.308487,49.853779],"type":"Point"}
}