{
  "type": "Feature",
  "properties": {
    "addr:full":"8259 Walkers Line Campbellville ON L0P 1B0",
    "addr:housenumber":"8259",
    "addr:postcode":"l0p 1b0",
    "addr:street":"Walkers Line",
    "iso:country":"CA",
    "sg:address":"8259 Walkers Line",
    "sg:city":"Campbellville",
    "sg:classifiers":[
        {
            "category":"Recreation",
            "type":"Entertainment"
        }
    ],
    "sg:phone":"+1 905 854 0762",
    "sg:postcode":"L0P 1B0",
    "sg:province":"ON",
    "sg:tags":[
        "stable"
    ],
    "wof:name":"Milestone Stables",
    "wof:placetype":"venue"
},
  "geometry": {"coordinates":[-79.983047,43.48774],"type":"Point"}
}