{
  "type": "Feature",
  "properties": {
    "addr:full":"Armstrong BC V0E 1B5",
    "addr:postcode":"v0e 1b5",
    "iso:country":"CA",
    "sg:city":"Armstrong",
    "sg:classifiers":[
        {
            "category":"Organizations",
            "subcategory":"Religious Organization",
            "type":"Services"
        }
    ],
    "sg:phone":"+1 250 546 6970",
    "sg:postcode":"V0E 1B5",
    "sg:province":"BC",
    "sg:tags":[
        "church"
    ],
    "wof:name":"Seventh Day Adventist Church",
    "wof:placetype":"venue"
},
  "geometry": {"coordinates":[-119.183701,50.441818],"type":"Point"}
}