{
  "type": "Feature",
  "properties": {
    "addr:full":"23 Sunbury St Fredericton NB E3B 3S9",
    "addr:housenumber":"23",
    "addr:postcode":"e3b 3s9",
    "addr:street":"Sunbury St",
    "iso:country":"CA",
    "sg:address":"23 Sunbury St",
    "sg:city":"Fredericton",
    "sg:classifiers":[
        {
            "category":"Personal",
            "subcategory":"Beauty Salon",
            "type":"Services"
        }
    ],
    "sg:phone":"+1 506 453 9196",
    "sg:postcode":"E3B 3S9",
    "sg:province":"NB",
    "sg:tags":[
        "school"
    ],
    "wof:name":"Atlantic Hair Styling Academy",
    "wof:placetype":"venue"
},
  "geometry": {"coordinates":[-66.64408874510001,45.9604530334],"type":"Point"}
}