{
  "type": "Feature",
  "properties": {
    "addr:full":"2442 Rue Frontenac Montreal QC H2K 2Z9",
    "addr:housenumber":"2442",
    "addr:postcode":"h2k 2z9",
    "addr:street":"Rue Frontenac",
    "iso:country":"CA",
    "sg:address":"2442 Rue Frontenac",
    "sg:city":"Montreal",
    "sg:classifiers":[
        {
            "category":"Retail",
            "subcategory":"Laundry & Dry Cleaning",
            "type":"Services"
        }
    ],
    "sg:phone":"+1 514 526 2828",
    "sg:postcode":"H2K 2Z9",
    "sg:province":"QC",
    "sg:tags":[
        "cleaners"
    ],
    "wof:name":"Nettoyeurs Chatel Inc",
    "wof:placetype":"venue"
},
  "geometry": {"coordinates":[-73.55800600000001,45.535118],"type":"Point"}
}