{
  "type": "Feature",
  "properties": {
    "addr:full":"174 Arvin Ave Stoney Creek ON L8E 3P9",
    "addr:housenumber":"174",
    "addr:postcode":"l8e 3p9",
    "addr:street":"Arvin Ave",
    "iso:country":"CA",
    "sg:address":"174 Arvin Ave",
    "sg:city":"Stoney Creek",
    "sg:classifiers":[
        {
            "category":"Wholesale",
            "subcategory":"Machinery & Supplies",
            "type":"Manufacturing & Wholesale Goods"
        }
    ],
    "sg:phone":"+1 905 560 3811",
    "sg:postcode":"L8E 3P9",
    "sg:province":"ON",
    "sg:tags":[
        "equipment",
        "safety",
        "clothing",
        "glove"
    ],
    "wof:name":"Glove Reconditioners",
    "wof:placetype":"venue"
},
  "geometry": {"coordinates":[-79.734291,43.233185],"type":"Point"}
}