{
  "type": "Feature",
  "properties": {
    "addr:full":"489 Pelissier St Windsor ON N9A 4L2",
    "addr:housenumber":"489",
    "addr:postcode":"n9a 4l2",
    "addr:street":"Pelissier St",
    "iso:country":"CA",
    "sg:address":"489 Pelissier St",
    "sg:city":"Windsor",
    "sg:classifiers":[
        {
            "category":"Bars & Pubs",
            "type":"Food & Drink"
        }
    ],
    "sg:phone":"+1 519 255 7772",
    "sg:postcode":"N9A 4L2",
    "sg:province":"ON",
    "sg:tags":[
        "club",
        "night"
    ],
    "wof:name":"Zebra Room",
    "wof:placetype":"venue"
},
  "geometry": {"coordinates":[-83.0387496948,42.3150253296],"type":"Point"}
}