{
  "type": "Feature",
  "properties": {
    "addr:full":"3030 Commercial Dr Vancouver BC V5N 4E2",
    "addr:housenumber":"3030",
    "addr:postcode":"v5n 4e2",
    "addr:street":"Commercial Dr",
    "iso:country":"CA",
    "sg:address":"3030 Commercial Dr",
    "sg:city":"Vancouver",
    "sg:classifiers":[
        {
            "category":"Restaurant",
            "type":"Food & Drink"
        }
    ],
    "sg:phone":"+1 604 875 0879",
    "sg:postcode":"V5N 4E2",
    "sg:province":"BC",
    "wof:name":"Ben's Bar & Grill",
    "wof:placetype":"venue"
},
  "geometry": {"coordinates":[-123.06979370099999,49.2574653625],"type":"Point"}
}