{
  "type": "Feature",
  "properties": {
    "addr:full":"800 Rue South Cowansville QC J2K 2Y3",
    "addr:housenumber":"800",
    "addr:postcode":"j2k 2y3",
    "addr:street":"Rue South",
    "iso:country":"CA",
    "sg:address":"800 Rue South",
    "sg:city":"Cowansville",
    "sg:classifiers":[
        {
            "category":"Wholesale",
            "subcategory":"Sporting Goods",
            "type":"Manufacturing & Wholesale Goods"
        }
    ],
    "sg:phone":"+1 450 263 4747",
    "sg:postcode":"J2K 2Y3",
    "sg:province":"QC",
    "wof:name":"Garmont Canada",
    "wof:placetype":"venue"
},
  "geometry": {"coordinates":[-72.74597199999999,45.207802],"type":"Point"}
}