{
  "type": "Feature",
  "properties": {
    "addr:full":"1426 Queen St W Toronto ON M6K 1L9",
    "addr:housenumber":"1426",
    "addr:postcode":"m6k 1l9",
    "addr:street":"Queen St W",
    "iso:country":"CA",
    "sg:address":"1426 Queen St W",
    "sg:city":"Toronto",
    "sg:classifiers":[
        {
            "category":"Restaurant",
            "type":"Food & Drink"
        }
    ],
    "sg:phone":"+1 416 536 3682",
    "sg:postcode":"M6K 1L9",
    "sg:province":"ON",
    "wof:name":"Skyline Restaurant",
    "wof:placetype":"venue"
},
  "geometry": {"coordinates":[-79.4351882935,43.6410446167],"type":"Point"}
}