{
  "type": "Feature",
  "properties": {
    "addr:full":"351 S Birch Ave 100 Mile House BC V0K 2E0",
    "addr:housenumber":"351",
    "addr:postcode":"v0k 2e0",
    "addr:street":"S Birch Ave",
    "iso:country":"CA",
    "sg:address":"351 S Birch Ave",
    "sg:city":"100 Mile House",
    "sg:classifiers":[
        {
            "category":"Retail",
            "subcategory":"Repair Shop",
            "type":"Services"
        }
    ],
    "sg:phone":"+1 250 395 2922",
    "sg:postcode":"V0K 2E0",
    "sg:province":"BC",
    "sg:tags":[
        "television",
        "telephone",
        "cellular"
    ],
    "wof:name":"Tip-Top Radio Tv & Video",
    "wof:placetype":"venue"
},
  "geometry": {"coordinates":[-121.391159,51.314026],"type":"Point"}
}