{
  "type": "Feature",
  "properties": {
    "addr:full":"Nanaimo BC V9T 1W1",
    "addr:postcode":"v9t 1w1",
    "iso:country":"CA",
    "sg:city":"Nanaimo",
    "sg:classifiers":[
        {
            "category":"Shopping",
            "subcategory":"Bicycles & Sporting Goods",
            "type":"Retail Goods"
        }
    ],
    "sg:phone":"+1 250 751 2878",
    "sg:postcode":"V9T 1W1",
    "sg:province":"BC",
    "wof:name":"Sport Mart",
    "wof:placetype":"venue"
},
  "geometry": {"coordinates":[-124.002250671,49.2047576904],"type":"Point"}
}