{
  "type": "Feature",
  "properties": {
    "iso:country":"CA",
    "sg:city":"Kingston",
    "sg:classifiers":[
        {
            "category":"Professional",
            "subcategory":"Engineering",
            "type":"Services"
        }
    ],
    "sg:phone":"+1 613 546 2227",
    "sg:postcode":"K7L 1H1",
    "sg:province":"ON",
    "sg:tags":[
        "engineer"
    ],
    "wof:name":"Mc Cormick Rankin Corp",
    "wof:placetype":"venue"
},
  "geometry": {"coordinates":[-76.510513,44.240566],"type":"Point"}
}