{
  "type": "Feature",
  "properties": {
    "addr:full":"18 Alcie W Thornbury ON N0H 2P0",
    "addr:housenumber":"18",
    "addr:postcode":"n0h 2p0",
    "addr:street":"W",
    "iso:country":"CA",
    "sg:address":"18 Alcie W",
    "sg:city":"Thornbury",
    "sg:classifiers":[
        {
            "category":"Building & Trades",
            "subcategory":"Landscaping Services",
            "type":"Services"
        }
    ],
    "sg:phone":"+1 519 599 7743",
    "sg:postcode":"N0H 2P0",
    "sg:province":"ON",
    "sg:tags":[
        "designer",
        "contractor",
        "landscape",
        "dealer",
        "pool",
        "swimming"
    ],
    "wof:name":"Stonescapes",
    "wof:placetype":"venue"
},
  "geometry": {"coordinates":[-80.450699,44.561565],"type":"Point"}
}