{
  "type": "Feature",
  "properties": {
    "addr:full":"524 5 St S Lethbridge AB T1J 2B8",
    "addr:housenumber":"524 5",
    "addr:postcode":"t1j 2b8",
    "addr:street":"St S",
    "iso:country":"CA",
    "sg:address":"524 5 St S",
    "sg:city":"Lethbridge",
    "sg:classifiers":[
        {
            "category":"Shopping",
            "subcategory":"Computers & Home Electronics",
            "type":"Retail Goods"
        }
    ],
    "sg:phone":"+1 403 327 3737",
    "sg:postcode":"T1J 2B8",
    "sg:province":"AB",
    "sg:tags":[
        "equipment",
        "dealer"
    ],
    "wof:name":"Computing Excellence Ltd",
    "wof:placetype":"venue"
},
  "geometry": {"coordinates":[-112.840149,49.692223],"type":"Point"}
}