{
  "type": "Feature",
  "properties": {
    "addr:full":"147 Mitton St N Sarnia ON N7T 6G9",
    "addr:housenumber":"147",
    "addr:postcode":"n7t 6g9",
    "addr:street":"Mitton St N",
    "iso:country":"CA",
    "sg:address":"147 Mitton St N",
    "sg:city":"Sarnia",
    "sg:classifiers":[
        {
            "category":"Shopping",
            "subcategory":"Optical Goods",
            "type":"Retail Goods"
        }
    ],
    "sg:phone":"+1 519 337 4060",
    "sg:postcode":"N7T 6G9",
    "sg:province":"ON",
    "sg:tags":[
        "optician"
    ],
    "wof:name":"Eye Guy",
    "wof:placetype":"venue"
},
  "geometry": {"coordinates":[-82.3984222412,42.972240448],"type":"Point"}
}