{
  "type": "Feature",
  "properties": {
    "addr:full":"Delta BC V4E 2A9",
    "addr:postcode":"v4e 2a9",
    "iso:country":"CA",
    "sg:city":"Delta",
    "sg:classifiers":[
        {
            "category":"Food & Beverages",
            "subcategory":"Specialty",
            "type":"Retail Goods"
        }
    ],
    "sg:phone":"+1 604 597 1176",
    "sg:postcode":"V4E 2A9",
    "sg:province":"BC",
    "sg:tags":[
        "vitamin"
    ],
    "wof:name":"Canadian Sun Vitamin Ctr",
    "wof:placetype":"venue"
},
  "geometry": {"coordinates":[-122.890556,49.131989],"type":"Point"}
}