{
  "type": "Feature",
  "properties": {
    "addr:full":"105 Garafraxa St N Durham ON N0G 1R0",
    "addr:housenumber":"105",
    "addr:postcode":"n0g 1r0",
    "addr:street":"Garafraxa St N",
    "iso:country":"CA",
    "sg:address":"105 Garafraxa St N",
    "sg:city":"Durham",
    "sg:classifiers":[
        {
            "category":"Real Estate",
            "subcategory":"Real Estate Agent",
            "type":"Services"
        }
    ],
    "sg:phone":"+1 519 369 2128",
    "sg:postcode":"N0G 1R0",
    "sg:province":"ON",
    "wof:name":"Wilfred Mc Intee & CO Ltd",
    "wof:placetype":"venue"
},
  "geometry": {"coordinates":[-80.818405,44.176456],"type":"Point"}
}