{
  "type": "Feature",
  "properties": {
    "addr:full":"140 Rue Degrace Shippagan NB E8S 1H5",
    "addr:housenumber":"140",
    "addr:postcode":"e8s 1h5",
    "addr:street":"Rue Degrace Shippagan",
    "iso:country":"CA",
    "sg:address":"140 Rue Degrace",
    "sg:city":"Shippagan",
    "sg:classifiers":[
        {
            "category":"Restaurant",
            "type":"Food & Drink"
        }
    ],
    "sg:phone":"+1 506 336 2354",
    "sg:postcode":"E8S 1H5",
    "sg:province":"NB",
    "wof:name":"Dixie Lee Shippagan",
    "wof:placetype":"venue"
},
  "geometry": {"coordinates":[-64.71272277830001,47.7457427979],"type":"Point"}
}