{
  "type": "Feature",
  "properties": {
    "addr:full":"10207 96 St High Level AB T0H 1Z0",
    "addr:housenumber":"10207",
    "addr:postcode":"t0h 1z0",
    "addr:street":"96 St",
    "iso:country":"CA",
    "sg:address":"10207 96 St",
    "sg:city":"High Level",
    "sg:classifiers":[
        {
            "category":"Wholesale",
            "subcategory":"Machinery & Supplies",
            "type":"Manufacturing & Wholesale Goods"
        }
    ],
    "sg:phone":"+1 780 926 2521",
    "sg:postcode":"T0H 1Z0",
    "sg:province":"AB",
    "sg:tags":[
        "industrial",
        "equipment",
        "parts",
        "automobile"
    ],
    "wof:name":"Gregg Distributors CO",
    "wof:placetype":"venue"
},
  "geometry": {"coordinates":[-117.129112244,58.5138244629],"type":"Point"}
}