{
  "type": "Feature",
  "properties": {
    "addr:full":"6352 Rue Pascal Montreal-Nord QC H1G 1T6",
    "addr:housenumber":"6352",
    "addr:postcode":"h1g 1t6",
    "addr:street":"Rue Pascal",
    "iso:country":"CA",
    "sg:address":"6352 Rue Pascal",
    "sg:city":"Montreal-Nord",
    "sg:classifiers":[
        {
            "category":"Restaurant",
            "type":"Food & Drink"
        }
    ],
    "sg:phone":"+1 514 852 1010",
    "sg:postcode":"H1G 1T6",
    "sg:province":"QC",
    "wof:name":"Pizza New York",
    "wof:placetype":"venue"
},
  "geometry": {"coordinates":[-73.620010376,45.617729187],"type":"Point"}
}