{
  "type": "Feature",
  "properties": {
    "addr:full":"925 15th Sideroad King City ON L7B 1K5",
    "addr:housenumber":"925",
    "addr:postcode":"l7b 1k5",
    "addr:street":"15Th Sideroad",
    "iso:country":"CA",
    "sg:address":"925 15th Sideroad",
    "sg:city":"King City",
    "sg:classifiers":[
        {
            "category":"Building & Trades",
            "subcategory":"Construction",
            "type":"Services"
        }
    ],
    "sg:phone":"+1 905 773 8531",
    "sg:postcode":"L7B 1K5",
    "sg:province":"ON",
    "sg:tags":[
        "masonry",
        "contractor"
    ],
    "wof:name":"Orland Masonry Construction",
    "wof:placetype":"venue"
},
  "geometry": {"coordinates":[-79.527512,43.926113],"type":"Point"}
}