{
  "type": "Feature",
  "properties": {
    "iso:country":"CA",
    "sg:city":"Patuanak",
    "sg:classifiers":[
        {
            "category":"Recreation",
            "type":"Entertainment"
        }
    ],
    "sg:phone":"+1 306 396 2221",
    "sg:postcode":"S0M 2H0",
    "sg:province":"SK",
    "sg:tags":[
        "hall",
        "auditorium"
    ],
    "wof:name":"William Apesis Memorial Band",
    "wof:placetype":"venue"
},
  "geometry": {"coordinates":[-107.707290649,55.8982658386],"type":"Point"}
}