{
  "type": "Feature",
  "properties": {
    "addr:full":"915 Boul DE L'Anse-A-Valleau Gaspe QC G4X 4A1",
    "addr:housenumber":"915",
    "addr:postcode":"g4x 4a1",
    "addr:street":"Boul De L'Anse-A-Valleau Gaspe",
    "iso:country":"CA",
    "sg:address":"915 Boul DE L'Anse-A-Valleau",
    "sg:city":"Gaspe",
    "sg:classifiers":[
        {
            "category":"Retail",
            "subcategory":"Auto Repair",
            "type":"Services"
        }
    ],
    "sg:phone":"+1 418 269 5103",
    "sg:postcode":"G4X 4A1",
    "sg:province":"QC",
    "sg:tags":[
        "body",
        "automobile",
        "painting"
    ],
    "wof:name":"Atelier DE Debosselage",
    "wof:placetype":"venue"
},
  "geometry": {"coordinates":[-64.5786437988,49.0871238708],"type":"Point"}
}