{
  "type": "Feature",
  "properties": {
    "addr:full":"150 Mile House BC V0K 2G0",
    "addr:postcode":"v0k 2g0",
    "iso:country":"CA",
    "sg:city":"150 Mile House",
    "sg:classifiers":[
        {
            "category":"Retail",
            "subcategory":"Auto Repair",
            "type":"Services"
        }
    ],
    "sg:phone":"+1 250 296 0006",
    "sg:postcode":"V0K 2G0",
    "sg:province":"BC",
    "sg:tags":[
        "repairing",
        "automobile"
    ],
    "wof:name":"C & T Repairs",
    "wof:placetype":"venue"
},
  "geometry": {"coordinates":[-122.147003,52.136719],"type":"Point"}
}