{
  "type": "Feature",
  "properties": {
    "addr:full":"3 Court Terr Brockville ON K6V 4T4",
    "addr:housenumber":"3",
    "addr:postcode":"k6v 4t4",
    "addr:street":"Court Terr",
    "iso:country":"CA",
    "sg:address":"3 Court Terr",
    "sg:city":"Brockville",
    "sg:classifiers":[
        {
            "category":"Professional",
            "subcategory":"Lawyer & Legal Services",
            "type":"Services"
        }
    ],
    "sg:phone":"+1 613 345 1907",
    "sg:postcode":"K6V 4T4",
    "sg:province":"ON",
    "sg:tags":[
        "attorney"
    ],
    "wof:name":"Evely, Brian G",
    "wof:placetype":"venue"
},
  "geometry": {"coordinates":[-75.684303,44.589672],"type":"Point"}
}