{
  "type": "Feature",
  "properties": {
    "addr:full":"118 Brock St Sault Ste Marie ON P6A 3B5",
    "addr:housenumber":"118",
    "addr:postcode":"p6a 3b5",
    "addr:street":"Brock St",
    "iso:country":"CA",
    "sg:address":"118 Brock St",
    "sg:city":"Sault Ste Marie",
    "sg:classifiers":[
        {
            "category":"Health Services",
            "subcategory":"Optometrist",
            "type":"Services"
        }
    ],
    "sg:phone":"+1 705 946 4498",
    "sg:postcode":"P6A 3B5",
    "sg:province":"ON",
    "wof:name":"Myles, Lynda A OD",
    "wof:placetype":"venue"
},
  "geometry": {"coordinates":[-84.32923099999999,46.50943],"type":"Point"}
}