{
  "type": "Feature",
  "properties": {
    "addr:full":"Burnaby BC V5C 5B7",
    "addr:postcode":"v5c 5b7",
    "iso:country":"CA",
    "sg:city":"Burnaby",
    "sg:classifiers":[
        {
            "category":"Travel",
            "subcategory":"Travel Agent",
            "type":"Entertainment"
        }
    ],
    "sg:phone":"+1 604 294 3251",
    "sg:postcode":"V5C 5B7",
    "sg:province":"BC",
    "sg:tags":[
        "agency",
        "bureau"
    ],
    "wof:name":"Jackie's Travel Place Ltd",
    "wof:placetype":"venue"
},
  "geometry": {"coordinates":[-122.982948303,49.2593078613],"type":"Point"}
}