{
  "type": "Feature",
  "properties": {
    "addr:full":"Taber AB T1G 1V2",
    "addr:postcode":"t1g 1v2",
    "iso:country":"CA",
    "sg:city":"Taber",
    "sg:classifiers":[
        {
            "category":"Organizations",
            "subcategory":"Professional Association",
            "type":"Services"
        }
    ],
    "sg:phone":"+1 403 223 9008",
    "sg:postcode":"T1G 1V2",
    "sg:province":"AB",
    "wof:name":"Alberta Association For Safety",
    "wof:placetype":"venue"
},
  "geometry": {"coordinates":[-112.142899,49.786133],"type":"Point"}
}