{
  "type": "Feature",
  "properties": {
    "addr:full":"1353 Balfour St Fenwick ON L0S 1C0",
    "addr:housenumber":"1353",
    "addr:postcode":"l0s 1c0",
    "addr:street":"Balfour St",
    "iso:country":"CA",
    "sg:address":"1353 Balfour St",
    "sg:city":"Fenwick",
    "sg:classifiers":[
        {
            "category":"Building & Trades",
            "subcategory":"Landscaping Services",
            "type":"Services"
        }
    ],
    "sg:phone":"+1 905 892 5668",
    "sg:postcode":"L0S 1C0",
    "sg:province":"ON",
    "sg:tags":[
        "control",
        "lawn",
        "weed",
        "maintenance",
        "grounds"
    ],
    "wof:name":"Lawrences's Lawn Care Ltd",
    "wof:placetype":"venue"
},
  "geometry": {"coordinates":[-79.35153961180001,43.0365982056],"type":"Point"}
}