{
  "type": "Feature",
  "properties": {
    "iso:country":"CA",
    "sg:city":"Burnaby",
    "sg:classifiers":[
        {
            "category":"Sports & Exercise",
            "subcategory":"Gym",
            "type":"Entertainment"
        }
    ],
    "sg:phone":"+1 604 293 0001",
    "sg:postcode":"V5C 5T5",
    "sg:province":"BC",
    "sg:tags":[
        "club",
        "health",
        "studio",
        "gymnasium"
    ],
    "wof:name":"Fitcity For Women",
    "wof:placetype":"venue"
},
  "geometry": {"coordinates":[-122.998657227,49.2660942078],"type":"Point"}
}