{
  "type": "Feature",
  "properties": {
    "addr:full":"241 Main St Sturgeon Falls ON P2B 1P5",
    "addr:housenumber":"241",
    "addr:postcode":"p2b 1p5",
    "addr:street":"Main St",
    "iso:country":"CA",
    "sg:address":"241 Main St",
    "sg:city":"Sturgeon Falls",
    "sg:classifiers":[
        {
            "category":"Organizations",
            "subcategory":"Professional Association",
            "type":"Services"
        }
    ],
    "sg:phone":"+1 705 753 3310",
    "sg:postcode":"P2B 1P5",
    "sg:province":"ON",
    "sg:tags":[
        "club"
    ],
    "wof:name":"Club Calumet",
    "wof:placetype":"venue"
},
  "geometry": {"coordinates":[-79.9284896851,46.366268158],"type":"Point"}
}