{
  "type": "Feature",
  "properties": {
    "addr:full":"Burnaby BC V5E 1H8",
    "addr:postcode":"v5e 1h8",
    "iso:country":"CA",
    "sg:city":"Burnaby",
    "sg:classifiers":[
        {
            "category":"Social Services",
            "type":"Services"
        }
    ],
    "sg:phone":"+1 604 517 1034",
    "sg:postcode":"V5E 1H8",
    "sg:province":"BC",
    "sg:tags":[
        "organization",
        "welfare"
    ],
    "wof:name":"Actss Community Svc",
    "wof:placetype":"venue"
},
  "geometry": {"coordinates":[-122.953582764,49.2191047668],"type":"Point"}
}