{
  "type": "Feature",
  "properties": {
    "addr:full":"16815 117 Ave NW Edmonton AB T5M 3V6",
    "addr:housenumber":"16815",
    "addr:postcode":"t5m 3v6",
    "addr:street":"117 Ave Nw",
    "iso:country":"CA",
    "sg:address":"16815 117 Ave NW",
    "sg:city":"Edmonton",
    "sg:classifiers":[
        {
            "category":"Real Estate",
            "subcategory":"Real Estate Agent",
            "type":"Services"
        }
    ],
    "sg:phone":"+1 780 455 4111",
    "sg:postcode":"T5M 3V6",
    "sg:province":"AB",
    "sg:tags":[
        "management"
    ],
    "wof:name":"Rayland Properties Inc",
    "wof:placetype":"venue"
},
  "geometry": {"coordinates":[-113.611236572,53.5672836304],"type":"Point"}
}