{
  "type": "Feature",
  "properties": {
    "addr:full":"97 Woodlawn Ave Winnipeg MB R2M 2P3",
    "addr:housenumber":"97",
    "addr:postcode":"r2m 2p3",
    "addr:street":"Woodlawn Ave",
    "iso:country":"CA",
    "sg:address":"97 Woodlawn Ave",
    "sg:city":"Winnipeg",
    "sg:classifiers":[
        {
            "category":"Wholesale",
            "subcategory":"Farm Supplies",
            "type":"Manufacturing & Wholesale Goods"
        }
    ],
    "sg:phone":"+1 204 257 8900",
    "sg:postcode":"R2M 2P3",
    "sg:province":"MB",
    "sg:tags":[
        "grain",
        "broker"
    ],
    "wof:name":"Gamcar International Trade Ltd",
    "wof:placetype":"venue"
},
  "geometry": {"coordinates":[-97.122406,49.820866],"type":"Point"}
}