{
  "type": "Feature",
  "properties": {
    "addr:full":"8517 Rue Hochelaga Montreal QC H1L 2M1",
    "addr:housenumber":"8517",
    "addr:postcode":"h1l 2m1",
    "addr:street":"Rue Hochelaga",
    "iso:country":"CA",
    "sg:address":"8517 Rue Hochelaga",
    "sg:city":"Montreal",
    "sg:classifiers":[
        {
            "category":"Restaurant",
            "type":"Food & Drink"
        }
    ],
    "sg:phone":"+1 514 351 0527",
    "sg:postcode":"H1L 2M1",
    "sg:province":"QC",
    "wof:name":"Restaurant Le Carpediem",
    "wof:placetype":"venue"
},
  "geometry": {"coordinates":[-73.5212478638,45.5993461609],"type":"Point"}
}