{
  "type": "Feature",
  "properties": {
    "iso:country":"CA",
    "sg:address":"2030 32E Av",
    "sg:city":"Pointe-Aux-Trembles",
    "sg:classifiers":[
        {
            "category":"Retail",
            "subcategory":"Car Wash",
            "type":"Services"
        }
    ],
    "sg:phone":"+1 514 642 8550",
    "sg:postcode":"H1A 3X4",
    "sg:province":"QC",
    "sg:tags":[
        "polishing",
        "washing"
    ],
    "wof:name":"Lave 32",
    "wof:placetype":"venue"
},
  "geometry": {"coordinates":[-73.507347,45.658081],"type":"Point"}
}