{
  "type": "Feature",
  "properties": {
    "addr:full":"2212 13 St NW Calgary AB T2M 4P7",
    "addr:housenumber":"2212",
    "addr:postcode":"t2m 4p7",
    "addr:street":"13 St Nw",
    "iso:country":"CA",
    "sg:address":"2212 13 St NW",
    "sg:city":"Calgary",
    "sg:classifiers":[
        {
            "category":"Social Services",
            "subcategory":"Adult Care",
            "type":"Services"
        }
    ],
    "sg:phone":"+1 403 289 4780",
    "sg:postcode":"T2M 4P7",
    "sg:province":"AB",
    "sg:tags":[
        "organization",
        "senior",
        "citizen"
    ],
    "wof:name":"Confederation Park Sr Citizens",
    "wof:placetype":"venue"
},
  "geometry": {"coordinates":[-114.092072,51.071503],"type":"Point"}
}