{
  "type": "Feature",
  "properties": {
    "addr:full":"Abbotsford BC V2S 4A7",
    "addr:postcode":"v2s 4a7",
    "iso:country":"CA",
    "sg:city":"Abbotsford",
    "sg:classifiers":[
        {
            "category":"Building & Trades",
            "subcategory":"Plumbing",
            "type":"Services"
        }
    ],
    "sg:phone":"+1 604 859 3959",
    "sg:postcode":"V2S 4A7",
    "sg:province":"BC",
    "sg:tags":[
        "conditioning",
        "air",
        "system",
        "contractor"
    ],
    "wof:name":"Comfort Valley Ventilation",
    "wof:placetype":"venue"
},
  "geometry": {"coordinates":[-122.282623,49.053101],"type":"Point"}
}