{
  "type": "Feature",
  "properties": {
    "iso:country":"CA",
    "sg:city":"Coteau-Du-Lac",
    "sg:classifiers":[
        {
            "category":"Retail",
            "subcategory":"Auto Repair",
            "type":"Services"
        }
    ],
    "sg:phone":"+1 450 763 0635",
    "sg:postcode":"J0P 1B0",
    "sg:province":"QC",
    "sg:tags":[
        "repairing",
        "automobile"
    ],
    "wof:name":"Garage Roger Campeau Enr",
    "wof:placetype":"venue"
},
  "geometry": {"coordinates":[-74.173523,45.295147],"type":"Point"}
}