{
  "type": "Feature",
  "properties": {
    "addr:full":"1654 Queen St W Toronto ON M6R 1B2",
    "addr:housenumber":"1654",
    "addr:postcode":"m6r 1b2",
    "addr:street":"Queen St W",
    "iso:country":"CA",
    "sg:address":"1654 Queen St W",
    "sg:city":"Toronto",
    "sg:classifiers":[
        {
            "category":"Retail",
            "subcategory":"Veterinary Services",
            "type":"Services"
        }
    ],
    "sg:phone":"+1 416 532 1169",
    "sg:postcode":"M6R 1B2",
    "sg:province":"ON",
    "sg:tags":[
        "veterinarian"
    ],
    "wof:name":"Parkdale Animal Hospital",
    "wof:placetype":"venue"
},
  "geometry": {"coordinates":[-79.4433670044,43.6394042969],"type":"Point"}
}