{
  "type": "Feature",
  "properties": {
    "addr:full":"Perrault Falls ON P0V 2K0",
    "addr:postcode":"p0v 2k0",
    "addr:street":"Perrault Falls",
    "iso:country":"CA",
    "sg:city":"Perrault Falls",
    "sg:classifiers":[
        {
            "category":"Travel",
            "subcategory":"Campground",
            "type":"Entertainment"
        }
    ],
    "sg:phone":"+1 807 529 6211",
    "sg:postcode":"P0V 2K0",
    "sg:province":"ON",
    "sg:tags":[
        "camp"
    ],
    "wof:name":"Cedar Lake Camp",
    "wof:placetype":"venue"
},
  "geometry": {"coordinates":[-93.11996499999999,50.364014],"type":"Point"}
}