{
  "type": "Feature",
  "properties": {
    "iso:country":"CA",
    "sg:address":"71 King St W",
    "sg:city":"Mississauga",
    "sg:classifiers":[
        {
            "category":"Health Services",
            "subcategory":"Optometrist",
            "type":"Services"
        }
    ],
    "sg:phone":"+1 905 279 1708",
    "sg:postcode":"L5B 4A2",
    "sg:province":"ON",
    "wof:name":"Zoberi, K OD",
    "wof:placetype":"venue"
},
  "geometry": {"coordinates":[-79.615509,43.577759],"type":"Point"}
}