{
  "type": "Feature",
  "properties": {
    "addr:full":"2040 Vernon St Lumby BC V0E 2G0",
    "addr:housenumber":"2040",
    "addr:postcode":"v0e 2g0",
    "addr:street":"Vernon St",
    "iso:country":"CA",
    "sg:address":"2040 Vernon St",
    "sg:city":"Lumby",
    "sg:classifiers":[
        {
            "category":"Food & Beverages",
            "subcategory":"Groceries & Convenience Stores",
            "type":"Retail Goods"
        }
    ],
    "sg:phone":"+1 250 547 2236",
    "sg:postcode":"V0E 2G0",
    "sg:province":"BC",
    "sg:tags":[
        "grocer"
    ],
    "wof:name":"Sheardown's Foodliner Ltd",
    "wof:placetype":"venue"
},
  "geometry": {"coordinates":[-118.966888,50.247269],"type":"Point"}
}