{
  "type": "Feature",
  "properties": {
    "addr:full":"78 Lincoln Ave Yorkton SK S3N 2H2",
    "addr:housenumber":"78",
    "addr:postcode":"s3n 2h2",
    "addr:street":"Lincoln Ave",
    "iso:country":"CA",
    "sg:address":"78 Lincoln Ave",
    "sg:city":"Yorkton",
    "sg:classifiers":[
        {
            "category":"Building & Trades",
            "subcategory":"Electrical",
            "type":"Services"
        }
    ],
    "sg:phone":"+1 306 783 7008",
    "sg:postcode":"S3N 2H2",
    "sg:province":"SK",
    "sg:tags":[
        "electric",
        "contractor"
    ],
    "wof:name":"Action Zaharia Electric Ltd",
    "wof:placetype":"venue"
},
  "geometry": {"coordinates":[-102.48168200000001,51.212894],"type":"Point"}
}