{
  "type": "Feature",
  "properties": {
    "addr:full":"441 Baldoon Rd Chatham ON N7L 5B8",
    "addr:housenumber":"441",
    "addr:postcode":"n7l 5b8",
    "addr:street":"Baldoon Rd",
    "iso:country":"CA",
    "sg:address":"441 Baldoon Rd",
    "sg:city":"Chatham",
    "sg:classifiers":[
        {
            "category":"Real Estate",
            "subcategory":"Real Estate Agent",
            "type":"Services"
        }
    ],
    "sg:phone":"+1 519 351 6695",
    "sg:postcode":"N7L 5B8",
    "sg:province":"ON",
    "wof:name":"Precision Point Realty Inc",
    "wof:placetype":"venue"
},
  "geometry": {"coordinates":[-82.2170410156,42.4080276489],"type":"Point"}
}