{
  "type": "Feature",
  "properties": {
    "iso:country":"CA",
    "sg:address":"286 Rue Langlais",
    "sg:city":"Trois-Pistoles",
    "sg:classifiers":[
        {
            "category":"Education",
            "subcategory":"School",
            "type":"Public Place"
        }
    ],
    "sg:phone":"+1 418 851 2346",
    "sg:postcode":"G0L 4K0",
    "sg:province":"QC",
    "wof:name":"Ecole Litalien",
    "wof:placetype":"venue"
},
  "geometry": {"coordinates":[-69.17287445069999,48.1256866455],"type":"Point"}
}