{
  "type": "Feature",
  "properties": {
    "iso:country":"CA",
    "sg:city":"Calgary",
    "sg:classifiers":[
        {
            "category":"Manufacturing",
            "subcategory":"Metals",
            "type":"Manufacturing & Wholesale Goods"
        }
    ],
    "sg:phone":"+1 403 640 9400",
    "sg:postcode":"T2H 2J7",
    "sg:province":"AB",
    "sg:tags":[
        "spring"
    ],
    "wof:name":"Western Spring & Wire",
    "wof:placetype":"venue"
},
  "geometry": {"coordinates":[-114.039932251,50.9952354431],"type":"Point"}
}