{
  "type": "Feature",
  "properties": {
    "iso:country":"CA",
    "sg:city":"Saint-Louis-DE-France",
    "sg:classifiers":[
        {
            "category":"Health Services",
            "subcategory":"Health Practitioner",
            "type":"Services"
        }
    ],
    "sg:phone":"+1 819 370 8692",
    "sg:postcode":"G8T 1E8",
    "sg:province":"QC",
    "sg:tags":[
        "food",
        "natural"
    ],
    "wof:name":"Demers Naturopathe",
    "wof:placetype":"venue"
},
  "geometry": {"coordinates":[-72.57563,46.407864],"type":"Point"}
}