{
  "type": "Feature",
  "properties": {
    "addr:full":"10555 Boul Pie-Ix Montreal-Nord QC H1H 4A3",
    "addr:housenumber":"10555",
    "addr:postcode":"h1h 4a3",
    "addr:street":"Boul Pie-Ix",
    "iso:country":"CA",
    "sg:address":"10555 Boul Pie-Ix",
    "sg:city":"Montreal-Nord",
    "sg:classifiers":[
        {
            "category":"Shopping",
            "subcategory":"Clothing, Apparel, & Fashions",
            "type":"Retail Goods"
        }
    ],
    "sg:phone":"+1 514 321 4880",
    "sg:postcode":"H1H 4A3",
    "sg:province":"QC",
    "wof:name":"Reitmans",
    "wof:placetype":"venue"
},
  "geometry": {"coordinates":[-73.6340637207,45.5881195068],"type":"Point"}
}