{
  "type": "Feature",
  "properties": {
    "addr:full":"4807 47 Ave Stettler AB T0C 2L1",
    "addr:housenumber":"4807",
    "addr:postcode":"t0c 2l1",
    "addr:street":"47 Ave",
    "iso:country":"CA",
    "sg:address":"4807 47 Ave",
    "sg:city":"Stettler",
    "sg:classifiers":[
        {
            "category":"Government",
            "subcategory":"Fire Station",
            "type":"Public Place"
        }
    ],
    "sg:phone":"+1 ",
    "sg:postcode":"T0C 2L1",
    "sg:province":"AB",
    "sg:tags":[
        "department"
    ],
    "wof:name":"Stettler Fire Hall",
    "wof:placetype":"venue"
},
  "geometry": {"coordinates":[-112.70217100000001,52.321301],"type":"Point"}
}