{
  "type": "Feature",
  "properties": {
    "iso:country":"CA",
    "sg:address":"24 Nashville Ave",
    "sg:city":"York",
    "sg:classifiers":[
        {
            "category":"Wholesale",
            "subcategory":"Scrap",
            "type":"Manufacturing & Wholesale Goods"
        }
    ],
    "sg:phone":"+1 416 653 6045",
    "sg:postcode":"M6M 1J1",
    "sg:province":"ON",
    "sg:tags":[
        "metal",
        "iron"
    ],
    "wof:name":"Lewis Iron & Metal CO",
    "wof:placetype":"venue"
},
  "geometry": {"coordinates":[-79.475730896,43.6829147339],"type":"Point"}
}