{
  "type": "Feature",
  "properties": {
    "addr:full":"Pointe-Aux-Trembles QC H1B 5L7",
    "addr:postcode":"h1b 5l7",
    "iso:country":"CA",
    "sg:city":"Pointe-Aux-Trembles",
    "sg:classifiers":[
        {
            "category":"Health Services",
            "subcategory":"Doctor",
            "type":"Services"
        }
    ],
    "sg:phone":"+1 514 645 9229",
    "sg:postcode":"H1B 5L7",
    "sg:province":"QC",
    "sg:tags":[
        "dentist"
    ],
    "wof:name":"Clinique Dentaire Pierre Caty",
    "wof:placetype":"venue"
},
  "geometry": {"coordinates":[-73.5002822876,45.6422462463],"type":"Point"}
}