{
  "type": "Feature",
  "properties": {
    "addr:full":"37 Boul Brunswick Dollard-Des-Ormeaux QC H9B 1P6",
    "addr:housenumber":"37",
    "addr:postcode":"h9b 1p6",
    "addr:street":"Boul Brunswick",
    "iso:country":"CA",
    "sg:address":"37 Boul Brunswick",
    "sg:city":"Dollard-Des-Ormeaux",
    "sg:classifiers":[
        {
            "category":"Real Estate",
            "subcategory":"Real Estate Operator",
            "type":"Services"
        }
    ],
    "sg:phone":"+1 514 684 1828",
    "sg:postcode":"H9B 1P6",
    "sg:province":"QC",
    "sg:tags":[
        "apartment"
    ],
    "wof:name":"Westwood House",
    "wof:placetype":"venue"
},
  "geometry": {"coordinates":[-73.79085499999999,45.485867],"type":"Point"}
}