{
  "type": "Feature",
  "properties": {
    "iso:country":"CA",
    "sg:address":"47 Quebec St",
    "sg:city":"Bracebridge",
    "sg:classifiers":[
        {
            "category":"Professional",
            "subcategory":"Lawyer & Legal Services",
            "type":"Services"
        }
    ],
    "sg:phone":"+1 705 645 1338",
    "sg:postcode":"P1L 1W6",
    "sg:province":"ON",
    "sg:tags":[
        "attorney"
    ],
    "wof:name":"Ward, Peter N",
    "wof:placetype":"venue"
},
  "geometry": {"coordinates":[-79.312263,45.040588],"type":"Point"}
}