{
  "type": "Feature",
  "properties": {
    "addr:full":"235 Boul Charest O Quebec QC G1K 1X5",
    "addr:housenumber":"235",
    "addr:postcode":"g1k 1x5",
    "addr:street":"Boul Charest O",
    "iso:country":"CA",
    "sg:address":"235 Boul Charest O",
    "sg:city":"Quebec",
    "sg:classifiers":[
        {
            "category":"Manufacturing",
            "subcategory":"Printing",
            "type":"Manufacturing & Wholesale Goods"
        }
    ],
    "sg:phone":"+1 418 648 1911",
    "sg:postcode":"G1K 1X5",
    "sg:province":"QC",
    "sg:tags":[
        "printer",
        "duplicating",
        "copying"
    ],
    "wof:name":"Copies DE Capitale Inc",
    "wof:placetype":"venue"
},
  "geometry": {"coordinates":[-71.227013,46.812401],"type":"Point"}
}