{
  "type": "Feature",
  "properties": {
    "addr:full":"960 117 Rte Val-David QC J0T 2N0",
    "addr:housenumber":"960 117",
    "addr:postcode":"j0t 2n0",
    "addr:street":"Rte Val-David",
    "iso:country":"CA",
    "sg:address":"960 117 Rte",
    "sg:city":"Val-David",
    "sg:classifiers":[
        {
            "category":"Cinema",
            "subcategory":"Movie Rental",
            "type":"Entertainment"
        }
    ],
    "sg:phone":"+1 819 322 3423",
    "sg:postcode":"J0T 2N0",
    "sg:province":"QC",
    "sg:tags":[
        "leasing",
        "video",
        "disc",
        "tape"
    ],
    "wof:name":"Niko's Video Enr",
    "wof:placetype":"venue"
},
  "geometry": {"coordinates":[-74.2124404907,46.0123176575],"type":"Point"}
}