{
  "type": "Feature",
  "properties": {
    "addr:full":"266 Rue Principale Issoudun QC G0S 1L0",
    "addr:housenumber":"266",
    "addr:postcode":"g0s 1l0",
    "addr:street":"Rue Principale",
    "iso:country":"CA",
    "sg:address":"266 Rue Principale",
    "sg:city":"Issoudun",
    "sg:classifiers":[
        {
            "category":"Organizations",
            "subcategory":"Professional Association",
            "type":"Services"
        }
    ],
    "sg:phone":"+1 418 728 4608",
    "sg:postcode":"G0S 1L0",
    "sg:province":"QC",
    "wof:name":"Club DE L'Age D'Or D'Issoudun",
    "wof:placetype":"venue"
},
  "geometry": {"coordinates":[-71.624756,46.578018],"type":"Point"}
}