{
  "type": "Feature",
  "properties": {
    "iso:country":"CA",
    "sg:address":"4819 50 St",
    "sg:city":"Athabasca",
    "sg:classifiers":[
        {
            "category":"Banks & Credit Unions",
            "subcategory":"Bank",
            "type":"Services"
        }
    ],
    "sg:phone":"+1 780 675 2247",
    "sg:postcode":"T9S 1C8",
    "sg:province":"AB",
    "wof:name":"Cibc",
    "wof:placetype":"venue"
},
  "geometry": {"coordinates":[-113.286117554,54.7182579041],"type":"Point"}
}