{
  "type": "Feature",
  "properties": {
    "addr:full":"9 Roscoe Dr Kentville NS B4N 3V7",
    "addr:housenumber":"9",
    "addr:postcode":"b4n 3v7",
    "addr:street":"Roscoe Dr",
    "iso:country":"CA",
    "sg:address":"9 Roscoe Dr",
    "sg:city":"Kentville",
    "sg:classifiers":[
        {
            "category":"Wholesale",
            "subcategory":"Electrical",
            "type":"Manufacturing & Wholesale Goods"
        }
    ],
    "sg:phone":"+1 902 678 2800",
    "sg:postcode":"B4N 3V7",
    "sg:province":"NS",
    "sg:tags":[
        "equipment",
        "electric",
        "supply"
    ],
    "wof:name":"Harris & Roome Supply Ltd",
    "wof:placetype":"venue"
},
  "geometry": {"coordinates":[-64.5517959595,45.0696144104],"type":"Point"}
}