{
  "type": "Feature",
  "properties": {
    "addr:full":"1680 Lakeshore Rd W Mississauga ON L5J 1J5",
    "addr:housenumber":"1680",
    "addr:postcode":"l5j 1j5",
    "addr:street":"Lakeshore Rd W",
    "iso:country":"CA",
    "sg:address":"1680 Lakeshore Rd W",
    "sg:city":"Mississauga",
    "sg:classifiers":[
        {
            "category":"Banks & Credit Unions",
            "subcategory":"Bank",
            "type":"Services"
        }
    ],
    "sg:phone":"+1 905 823 1411",
    "sg:postcode":"L5J 1J5",
    "sg:province":"ON",
    "sg:tags":[
        "loan",
        "real estate"
    ],
    "wof:name":"Mortgage Broker Inc",
    "wof:placetype":"venue"
},
  "geometry": {"coordinates":[-79.62158203120001,43.518497467],"type":"Point"}
}