{
  "type": "Feature",
  "properties": {
    "iso:country":"CA",
    "sg:address":"3875 Rue Masson",
    "sg:city":"Montreal",
    "sg:classifiers":[
        {
            "category":"Food & Beverages",
            "subcategory":"Groceries & Convenience Stores",
            "type":"Retail Goods"
        }
    ],
    "sg:phone":"+1 514 727 8171",
    "sg:postcode":"H1X 1T2",
    "sg:province":"QC",
    "sg:tags":[
        "grocer"
    ],
    "wof:name":"Provi-Soir Couche-Tard",
    "wof:placetype":"venue"
},
  "geometry": {"coordinates":[-73.5700683594,45.5568847656],"type":"Point"}
}