{
  "type": "Feature",
  "properties": {
    "addr:full":"100 Haist Ave Woodbridge ON L4L 5V4",
    "addr:housenumber":"100",
    "addr:postcode":"l4l 5v4",
    "addr:street":"Haist Ave",
    "iso:country":"CA",
    "sg:address":"100 Haist Ave",
    "sg:city":"Woodbridge",
    "sg:classifiers":[
        {
            "category":"Wholesale",
            "subcategory":"Apparel",
            "type":"Manufacturing & Wholesale Goods"
        }
    ],
    "sg:phone":"+1 905 851 7375",
    "sg:postcode":"L4L 5V4",
    "sg:province":"ON",
    "sg:tags":[
        "textile"
    ],
    "wof:name":"Viana Canada Inc",
    "wof:placetype":"venue"
},
  "geometry": {"coordinates":[-79.567314,43.77964],"type":"Point"}
}