{
  "type": "Feature",
  "properties": {
    "addr:full":"559 Queen St W Toronto ON M5V 2B6",
    "addr:housenumber":"559",
    "addr:postcode":"m5v 2b6",
    "addr:street":"Queen St W",
    "iso:country":"CA",
    "sg:address":"559 Queen St W",
    "sg:city":"Toronto",
    "sg:classifiers":[
        {
            "category":"Professional",
            "type":"Services"
        }
    ],
    "sg:phone":"+1 416 703 5275",
    "sg:postcode":"M5V 2B6",
    "sg:province":"ON",
    "sg:tags":[
        "shop",
        "coffee",
        "establishment"
    ],
    "wof:name":"Caffeine Bean Bar",
    "wof:placetype":"venue"
},
  "geometry": {"coordinates":[-79.400299,43.647781],"type":"Point"}
}