{
  "type": "Feature",
  "properties": {
    "addr:full":"6552 Bayers Rd Halifax NS B3L 2B3",
    "addr:postcode":"6552;b3l 2b3",
    "addr:street":"Bayers Rd",
    "iso:country":"CA",
    "sg:address":"6552 Bayers Rd",
    "sg:city":"Halifax",
    "sg:classifiers":[
        {
            "category":"Retail",
            "subcategory":"Funeral Services",
            "type":"Services"
        }
    ],
    "sg:phone":"+1 902 453 1434",
    "sg:postcode":"B3L 2B3",
    "sg:province":"NS",
    "sg:tags":[
        "director"
    ],
    "wof:name":"Atlantic Funeral Home",
    "wof:placetype":"venue"
},
  "geometry": {"coordinates":[-63.6136283875,44.6527900696],"type":"Point"}
}