{
  "type": "Feature",
  "properties": {
    "addr:full":"195 Janefield Ave Guelph ON N1G 2L5",
    "addr:housenumber":"195",
    "addr:postcode":"n1g 2l5",
    "addr:street":"Janefield Ave",
    "iso:country":"CA",
    "sg:address":"195 Janefield Ave",
    "sg:city":"Guelph",
    "sg:classifiers":[
        {
            "category":"Education",
            "subcategory":"Special Training",
            "type":"Public Place"
        }
    ],
    "sg:phone":"+1 519 766 9033",
    "sg:postcode":"N1G 2L5",
    "sg:province":"ON",
    "sg:tags":[
        "management"
    ],
    "wof:name":"Strive",
    "wof:placetype":"venue"
},
  "geometry": {"coordinates":[-80.2437286377,43.516494751],"type":"Point"}
}