{
  "type": "Feature",
  "properties": {
    "addr:full":"Port Blandford NL A0C 2G0",
    "addr:postcode":"a0c 2g0",
    "addr:street":"Port",
    "iso:country":"CA",
    "sg:city":"Port Blandford",
    "sg:classifiers":[
        {
            "category":"Travel",
            "subcategory":"Hotels & Motels",
            "type":"Entertainment"
        }
    ],
    "sg:phone":"+1 709 543 2288",
    "sg:postcode":"A0C 2G0",
    "sg:province":"NL",
    "sg:tags":[
        "tourist",
        "accommodation"
    ],
    "wof:name":"Silver Maple Housekeeping Unit",
    "wof:placetype":"venue"
},
  "geometry": {"coordinates":[-54.1719970703,48.3571205139],"type":"Point"}
}