{
  "type": "Feature",
  "properties": {
    "iso:country":"CA",
    "sg:city":"Charlesbourg",
    "sg:classifiers":[
        {
            "category":"Health Services",
            "subcategory":"Health Practitioner",
            "type":"Services"
        }
    ],
    "sg:phone":"+1 418 624 9779",
    "sg:postcode":"G1H 6Y8",
    "sg:province":"QC",
    "sg:tags":[
        "physician"
    ],
    "wof:name":"Lessard, Pierre",
    "wof:placetype":"venue"
},
  "geometry": {"coordinates":[-71.2483825684,46.8507995605],"type":"Point"}
}