{
  "type": "Feature",
  "properties": {
    "addr:full":"4707 49th Ave Calmar AB T0C 0V0",
    "addr:housenumber":"4707",
    "addr:postcode":"t0c 0v0",
    "addr:street":"49Th Ave",
    "iso:country":"CA",
    "sg:address":"4707 49th Ave",
    "sg:city":"Calmar",
    "sg:classifiers":[
        {
            "category":"Freight",
            "type":"Transportation"
        }
    ],
    "sg:phone":"+1 780 985 3828",
    "sg:postcode":"T0C 0V0",
    "sg:province":"AB",
    "sg:tags":[
        "field",
        "oil"
    ],
    "wof:name":"Cameron Brothers Oil & Water",
    "wof:placetype":"venue"
},
  "geometry": {"coordinates":[-113.80090300000001,53.263947],"type":"Point"}
}