{
  "type": "Feature",
  "properties": {
    "iso:country":"CA",
    "sg:address":"27 Place Demers",
    "sg:city":"Victoriaville",
    "sg:classifiers":[
        {
            "category":"Personal",
            "subcategory":"Beauty Salon",
            "type":"Services"
        }
    ],
    "sg:phone":"+1 819 758 6660",
    "sg:postcode":"G6P 9G6",
    "sg:province":"QC",
    "wof:name":"Salon Figaro Elle",
    "wof:placetype":"venue"
},
  "geometry": {"coordinates":[-71.9779663086,46.0586624146],"type":"Point"}
}