{
  "type": "Feature",
  "properties": {
    "addr:full":"70 Regina Rd Woodbridge ON L4L 8L6",
    "addr:housenumber":"70",
    "addr:postcode":"l4l 8l6",
    "addr:street":"Regina Rd",
    "iso:country":"CA",
    "sg:address":"70 Regina Rd",
    "sg:city":"Woodbridge",
    "sg:classifiers":[
        {
            "category":"Home & Garden",
            "subcategory":"Furniture",
            "type":"Retail Goods"
        }
    ],
    "sg:phone":"+1 416 622 1613",
    "sg:postcode":"L4L 8L6",
    "sg:province":"ON",
    "sg:tags":[
        "equipment",
        "kitchen",
        "cabinet"
    ],
    "wof:name":"Cortina Kitchens Inc",
    "wof:placetype":"venue"
},
  "geometry": {"coordinates":[-79.6117095947,43.7726287842],"type":"Point"}
}