{
  "type": "Feature",
  "properties": {
    "addr:full":"4233 Spiers Rd Kelowna BC V1W 4E3",
    "addr:housenumber":"4233",
    "addr:postcode":"v1w 4e3",
    "addr:street":"Spiers Rd",
    "iso:country":"CA",
    "sg:address":"4233 Spiers Rd",
    "sg:city":"Kelowna",
    "sg:classifiers":[
        {
            "category":"Building & Trades",
            "subcategory":"Plumbing",
            "type":"Services"
        }
    ],
    "sg:phone":"+1 250 868 8912",
    "sg:postcode":"V1W 4E3",
    "sg:province":"BC",
    "sg:tags":[
        "heating",
        "contractor"
    ],
    "wof:name":"Henderson's Heating",
    "wof:placetype":"venue"
},
  "geometry": {"coordinates":[-119.416588,49.837006],"type":"Point"}
}