{
  "type": "Feature",
  "properties": {
    "addr:full":"Sainte-Foy QC G1V 4M6",
    "addr:postcode":"g1v 4m6",
    "iso:country":"CA",
    "sg:city":"Sainte-Foy",
    "sg:classifiers":[
        {
            "category":"Professional",
            "subcategory":"Accounting & Tax Preparation",
            "type":"Services"
        }
    ],
    "sg:phone":"+1 418 659 7265",
    "sg:postcode":"G1V 4M6",
    "sg:province":"QC",
    "sg:tags":[
        "accountant"
    ],
    "wof:name":"Laberge Lafleur & Assoc Inc",
    "wof:placetype":"venue"
},
  "geometry": {"coordinates":[-71.281059,46.771248],"type":"Point"}
}