{
  "type": "Feature",
  "properties": {
    "addr:full":"33723 Essendene Ave Abbotsford BC V2S 2G7",
    "addr:housenumber":"33723",
    "addr:postcode":"v2s 2g7",
    "addr:street":"Essendene Ave",
    "iso:country":"CA",
    "sg:address":"33723 Essendene Ave",
    "sg:city":"Abbotsford",
    "sg:classifiers":[
        {
            "category":"Restaurant",
            "type":"Food & Drink"
        }
    ],
    "sg:phone":"+1 604 852 6775",
    "sg:postcode":"V2S 2G7",
    "sg:province":"BC",
    "wof:name":"Cosy Cottage Tea Room",
    "wof:placetype":"venue"
},
  "geometry": {"coordinates":[-122.290993,49.049213],"type":"Point"}
}