{
  "type": "Feature",
  "properties": {
    "addr:full":"95 First Ave S Williams Lake BC V2G 1H4",
    "addr:housenumber":"95",
    "addr:postcode":"v2g 1h4",
    "addr:street":"First Ave S Williams",
    "iso:country":"CA",
    "sg:address":"95 First Ave S",
    "sg:city":"Williams Lake",
    "sg:classifiers":[
        {
            "category":"Shopping",
            "subcategory":"Bicycles & Sporting Goods",
            "type":"Retail Goods"
        }
    ],
    "sg:phone":"+1 250 398 7873",
    "sg:postcode":"V2G 1H4",
    "sg:province":"BC",
    "wof:name":"Red Shred's Bike & Board Shed",
    "wof:placetype":"venue"
},
  "geometry": {"coordinates":[-122.145713806,52.1272850037],"type":"Point"}
}