{
  "type": "Feature",
  "properties": {
    "addr:full":"9694 Boul Sainte-Anne Sainte-Anne-DE-Beaupre QC G0A 3C0",
    "addr:housenumber":"9694",
    "addr:postcode":"g0a 3c0",
    "addr:street":"Boul Sainte-Anne Sainte-Anne-De-Beaupre",
    "iso:country":"CA",
    "sg:address":"9694 Boul Sainte-Anne",
    "sg:city":"Sainte-Anne-DE-Beaupre",
    "sg:classifiers":[
        {
            "category":"Health Services",
            "subcategory":"Hospital",
            "type":"Services"
        }
    ],
    "sg:phone":"+1 418 827 1551",
    "sg:postcode":"G0A 3C0",
    "sg:province":"QC",
    "sg:tags":[
        "mental"
    ],
    "wof:name":"Libre Espace Orleans Inc",
    "wof:placetype":"venue"
},
  "geometry": {"coordinates":[-70.8884963989,47.0488700867],"type":"Point"}
}