{
  "type": "Feature",
  "properties": {
    "addr:full":"135 Mark St Sault Ste Marie ON P6A 3M4",
    "addr:housenumber":"135",
    "addr:postcode":"p6a 3m4",
    "addr:street":"Mark St",
    "iso:country":"CA",
    "sg:address":"135 Mark St",
    "sg:city":"Sault Ste Marie",
    "sg:classifiers":[
        {
            "category":"Professional",
            "subcategory":"Business Services",
            "type":"Services"
        }
    ],
    "sg:phone":"+1 705 949 8151",
    "sg:postcode":"P6A 3M4",
    "sg:province":"ON",
    "sg:tags":[
        "interior",
        "consultant",
        "design",
        "decorator"
    ],
    "wof:name":"Interiors By Nancy",
    "wof:placetype":"venue"
},
  "geometry": {"coordinates":[-84.2940826416,46.5051612854],"type":"Point"}
}