{
  "type": "Feature",
  "properties": {
    "addr:full":"10 Railway Ave Eriksdale MB R0C 0W0",
    "addr:housenumber":"10",
    "addr:postcode":"r0c 0w0",
    "addr:street":"Railway Ave",
    "iso:country":"CA",
    "sg:address":"10 Railway Ave",
    "sg:city":"Eriksdale",
    "sg:classifiers":[
        {
            "category":"Food & Beverages",
            "subcategory":"Groceries & Convenience Stores",
            "type":"Retail Goods"
        }
    ],
    "sg:phone":"+1 204 739 2118",
    "sg:postcode":"R0C 0W0",
    "sg:province":"MB",
    "sg:tags":[
        "merchandise",
        "general"
    ],
    "wof:name":"Eriksdale Shop Easy",
    "wof:placetype":"venue"
},
  "geometry": {"coordinates":[-98.122299,50.860088],"type":"Point"}
}