{
  "type": "Feature",
  "properties": {
    "addr:full":"63 North St Perth ON K7H 2T1",
    "addr:housenumber":"63",
    "addr:postcode":"k7h 2t1",
    "addr:street":"North St",
    "iso:country":"CA",
    "sg:address":"63 North St",
    "sg:city":"Perth",
    "sg:classifiers":[
        {
            "category":"Home & Garden",
            "subcategory":"Home Furnishings",
            "type":"Retail Goods"
        }
    ],
    "sg:phone":"+1 613 264 0878",
    "sg:postcode":"K7H 2T1",
    "sg:province":"ON",
    "sg:tags":[
        "stove",
        "wood",
        "burning"
    ],
    "wof:name":"Embers",
    "wof:placetype":"venue"
},
  "geometry": {"coordinates":[-76.253777,44.900555],"type":"Point"}
}