{
  "type": "Feature",
  "properties": {
    "iso:country":"CA",
    "sg:address":"582 George St",
    "sg:city":"Sydney",
    "sg:classifiers":[
        {
            "category":"Organizations",
            "subcategory":"Community Association",
            "type":"Services"
        }
    ],
    "sg:phone":"+1 902 567 1628",
    "sg:postcode":"B1P 1K9",
    "sg:province":"NS",
    "sg:tags":[
        "environmental",
        "org"
    ],
    "wof:name":"Acap Cape Breton",
    "wof:placetype":"venue"
},
  "geometry": {"coordinates":[-60.191608429,46.1347312927],"type":"Point"}
}