{
  "type": "Feature",
  "properties": {
    "addr:full":"601 2nd Ave N Saskatoon SK S7K 2C7",
    "addr:housenumber":"601",
    "addr:postcode":"s7k 2c7",
    "addr:street":"2Nd Ave N",
    "iso:country":"CA",
    "sg:address":"601 2nd Ave N",
    "sg:city":"Saskatoon",
    "sg:classifiers":[
        {
            "category":"Professional",
            "subcategory":"Computer Services",
            "type":"Services"
        }
    ],
    "sg:phone":"+1 306 664 2686",
    "sg:postcode":"S7K 2C7",
    "sg:province":"SK",
    "sg:tags":[
        "equipment",
        "dealer",
        "internet"
    ],
    "wof:name":"Western Business Machines",
    "wof:placetype":"venue"
},
  "geometry": {"coordinates":[-106.660179,52.136803],"type":"Point"}
}