{
  "type": "Feature",
  "properties": {
    "addr:full":"3350 Cote DE Terrebonne Terrebonne QC J6Y 1J2",
    "addr:housenumber":"3350",
    "addr:postcode":"j6y 1j2",
    "addr:street":"Cote De Terrebonne",
    "iso:country":"CA",
    "sg:address":"3350 Cote DE Terrebonne",
    "sg:city":"Terrebonne",
    "sg:classifiers":[
        {
            "category":"Organizations",
            "subcategory":"Religious Organization",
            "type":"Services"
        }
    ],
    "sg:phone":"+1 450 492 9561",
    "sg:postcode":"J6Y 1J2",
    "sg:province":"QC",
    "sg:tags":[
        "home",
        "retirement",
        "community",
        "retreat",
        "house"
    ],
    "wof:name":"Villa Victoire DE L'Age",
    "wof:placetype":"venue"
},
  "geometry": {"coordinates":[-73.684928894,45.6948928833],"type":"Point"}
}