{
  "type": "Feature",
  "properties": {
    "addr:full":"9281 50 St NW Edmonton AB T6B 3B6",
    "addr:housenumber":"9281",
    "addr:postcode":"t6b 3b6",
    "addr:street":"50 St Nw",
    "iso:country":"CA",
    "sg:address":"9281 50 St NW",
    "sg:city":"Edmonton",
    "sg:classifiers":[
        {
            "category":"Wholesale",
            "subcategory":"Hardware",
            "type":"Manufacturing & Wholesale Goods"
        }
    ],
    "sg:phone":"+1 780 465 9719",
    "sg:postcode":"T6B 3B6",
    "sg:province":"AB",
    "sg:tags":[
        "sheet",
        "metal",
        "fabricator"
    ],
    "wof:name":"Gemco Fireplaces & Heating Ltd",
    "wof:placetype":"venue"
},
  "geometry": {"coordinates":[-113.41791499999999,53.529446],"type":"Point"}
}