{
  "type": "Feature",
  "properties": {
    "addr:full":"2013 Harvey Ave Kelowna BC V1Y 6G6",
    "addr:housenumber":"2013",
    "addr:postcode":"v1y 6g6",
    "addr:street":"Harvey Ave",
    "iso:country":"CA",
    "sg:address":"2013 Harvey Ave",
    "sg:city":"Kelowna",
    "sg:classifiers":[
        {
            "category":"Restaurant",
            "type":"Food & Drink"
        }
    ],
    "sg:phone":"+1 250 861 3383",
    "sg:postcode":"V1Y 6G6",
    "sg:province":"BC",
    "sg:tags":[
        "pizza"
    ],
    "wof:name":"2 For 1 Family Pizza",
    "wof:placetype":"venue"
},
  "geometry": {"coordinates":[-119.44931,49.881802],"type":"Point"}
}