{
  "type": "Feature",
  "properties": {
    "iso:country":"CA",
    "sg:address":"2349 Fairview St",
    "sg:city":"Burlington",
    "sg:classifiers":[
        {
            "category":"Wholesale",
            "subcategory":"Machinery & Supplies",
            "type":"Manufacturing & Wholesale Goods"
        }
    ],
    "sg:phone":"+1 905 637 6002",
    "sg:postcode":"L7R 2E3",
    "sg:province":"ON",
    "sg:tags":[
        "pump",
        "heat",
        "exchanger"
    ],
    "wof:name":"S A Armstrong Ltd",
    "wof:placetype":"venue"
},
  "geometry": {"coordinates":[-79.801826,43.344078],"type":"Point"}
}