{
  "type": "Feature",
  "properties": {
    "addr:full":"174 Yamaska Ch Saint-Germain-DE-Grantham QC J0C 1K0",
    "addr:housenumber":"174",
    "addr:postcode":"j0c 1k0",
    "iso:country":"CA",
    "sg:address":"174 Yamaska Ch",
    "sg:city":"Saint-Germain-DE-Grantham",
    "sg:classifiers":[
        {
            "category":"Autos & Motor Vehicles",
            "subcategory":"Automobile Sales",
            "type":"Retail Goods"
        }
    ],
    "sg:phone":"+1 819 395 4665",
    "sg:postcode":"J0C 1K0",
    "sg:province":"QC",
    "sg:tags":[
        "repairing",
        "car",
        "dealer"
    ],
    "wof:name":"Centre DE L'Auto F Marcoux Inc",
    "wof:placetype":"venue"
},
  "geometry": {"coordinates":[-72.565071,45.845036],"type":"Point"}
}