{
  "type": "Feature",
  "properties": {
    "addr:full":"Saint-Marc-Sur-Richelieu QC J0L 2E0",
    "addr:postcode":"j0l 2e0",
    "iso:country":"CA",
    "sg:city":"Saint-Marc-Sur-Richelieu",
    "sg:classifiers":[
        {
            "category":"Shopping",
            "subcategory":"Computers & Home Electronics",
            "type":"Retail Goods"
        }
    ],
    "sg:phone":"+1 450 584 2248",
    "sg:postcode":"J0L 2E0",
    "sg:province":"QC",
    "sg:tags":[
        "parts",
        "supply"
    ],
    "wof:name":"Rubans Dube Inc",
    "wof:placetype":"venue"
},
  "geometry": {"coordinates":[-73.203056,45.680481],"type":"Point"}
}