{
  "type": "Feature",
  "properties": {
    "addr:full":"Manotick ON K4M 1A2",
    "addr:postcode":"k4m 1a2",
    "iso:country":"CA",
    "sg:city":"Manotick",
    "sg:classifiers":[
        {
            "category":"Recreation",
            "subcategory":"Marina",
            "type":"Entertainment"
        }
    ],
    "sg:phone":"+1 613 692 3455",
    "sg:postcode":"K4M 1A2",
    "sg:province":"ON",
    "sg:tags":[
        "repairing",
        "boat"
    ],
    "wof:name":"Millar Potter Boat Restoration",
    "wof:placetype":"venue"
},
  "geometry": {"coordinates":[-75.6859359741,45.2262649536],"type":"Point"}
}