{
  "type": "Feature",
  "properties": {
    "addr:full":"79 Av Principale Rouyn-Noranda QC J9X 4P1",
    "addr:postcode":"j9x 4p1",
    "addr:street":"79 Av Principale",
    "iso:country":"CA",
    "sg:address":"79 Av Principale",
    "sg:city":"Rouyn-Noranda",
    "sg:classifiers":[
        {
            "category":"Personal",
            "subcategory":"Beauty Salon",
            "type":"Services"
        }
    ],
    "sg:phone":"+1 819 797 6040",
    "sg:postcode":"J9X 4P1",
    "sg:province":"QC",
    "sg:tags":[
        "school"
    ],
    "wof:name":"Salons Hom-Fam Inc",
    "wof:placetype":"venue"
},
  "geometry": {"coordinates":[-79.0198135376,48.2409553528],"type":"Point"}
}