{
  "type": "Feature",
  "properties": {
    "iso:country":"CA",
    "sg:address":"9816 128 St",
    "sg:city":"Surrey",
    "sg:classifiers":[
        {
            "category":"Freight",
            "type":"Transportation"
        }
    ],
    "sg:phone":"+1 604 583 9696",
    "sg:postcode":"V3T 2Y6",
    "sg:province":"BC",
    "sg:tags":[
        "delivery"
    ],
    "wof:name":"City Wide Liquor Couriers",
    "wof:placetype":"venue"
},
  "geometry": {"coordinates":[-122.867576599,49.1812553406],"type":"Point"}
}