{
  "type": "Feature",
  "properties": {
    "addr:full":"425 Monarch Crt Kamloops BC V2E 1Y3",
    "addr:housenumber":"425",
    "addr:postcode":"bc v2e 1y3",
    "addr:street":"Monarch Crt",
    "iso:country":"CA",
    "sg:address":"425 Monarch Crt",
    "sg:city":"Kamloops",
    "sg:classifiers":[
        {
            "category":"Education",
            "subcategory":"School",
            "type":"Public Place"
        }
    ],
    "sg:phone":"+1 250 372 1224",
    "sg:postcode":"V2E 1Y3",
    "sg:province":"BC",
    "wof:name":"Summit Elementary School",
    "wof:placetype":"venue"
},
  "geometry": {"coordinates":[-120.349060059,50.6529045105],"type":"Point"}
}