{
  "type": "Feature",
  "properties": {
    "addr:full":"8736 216 St Langley BC V1M 2X9",
    "addr:housenumber":"8736",
    "addr:postcode":"v1m 2x9",
    "addr:street":"216 St",
    "iso:country":"CA",
    "sg:address":"8736 216 St",
    "sg:city":"Langley",
    "sg:classifiers":[
        {
            "category":"Education",
            "subcategory":"School",
            "type":"Public Place"
        }
    ],
    "sg:phone":"+1 604 881 0222",
    "sg:postcode":"V1M 2X9",
    "sg:province":"BC",
    "wof:name":"School District No 93",
    "wof:placetype":"venue"
},
  "geometry": {"coordinates":[-122.62384,49.160725],"type":"Point"}
}