{
  "type": "Feature",
  "properties": {
    "addr:full":"88 Rue Saint-Germain O Rimouski QC G5L 4B5",
    "addr:housenumber":"88",
    "addr:postcode":"g5l 4b5",
    "addr:street":"Rue Saint-Germain O",
    "iso:country":"CA",
    "sg:address":"88 Rue Saint-Germain O",
    "sg:city":"Rimouski",
    "sg:classifiers":[
        {
            "category":"Professional",
            "subcategory":"Testing Lab",
            "type":"Services"
        }
    ],
    "sg:phone":"+1 418 721 5711",
    "sg:postcode":"G5L 4B5",
    "sg:province":"QC",
    "sg:tags":[
        "laboratory"
    ],
    "wof:name":"Conseil Regionale DE L'Envir",
    "wof:placetype":"venue"
},
  "geometry": {"coordinates":[-68.52406311039999,48.4528961182],"type":"Point"}
}