{
  "type": "Feature",
  "properties": {
    "addr:full":"Montreal QC H3X 3Z6",
    "addr:postcode":"h3x 3z6",
    "iso:country":"CA",
    "sg:city":"Montreal",
    "sg:classifiers":[
        {
            "category":"Professional",
            "subcategory":"Accounting & Tax Preparation",
            "type":"Services"
        }
    ],
    "sg:phone":"+1 514 487 1566",
    "sg:postcode":"H3X 3Z6",
    "sg:province":"QC",
    "sg:tags":[
        "accountant"
    ],
    "wof:name":"Levy Pilotte",
    "wof:placetype":"venue"
},
  "geometry": {"coordinates":[-73.63166809080001,45.4843940735],"type":"Point"}
}