{
  "type": "Feature",
  "properties": {
    "iso:country":"CA",
    "sg:city":"LA Presentation",
    "sg:classifiers":[
        {
            "category":"Restaurant",
            "type":"Food & Drink"
        }
    ],
    "sg:phone":"+1 450 796 4271",
    "sg:postcode":"J0H 1B0",
    "sg:province":"QC",
    "wof:name":"Cantine LA Presentation",
    "wof:placetype":"venue"
},
  "geometry": {"coordinates":[-73.0547866821,45.6677093506],"type":"Point"}
}