{
  "type": "Feature",
  "properties": {
    "addr:full":"864 Markham Rd Scarborough ON M1H 2Y2",
    "addr:housenumber":"864",
    "addr:postcode":"m1h 2y2",
    "addr:street":"Markham Rd",
    "iso:country":"CA",
    "sg:address":"864 Markham Rd",
    "sg:city":"Scarborough",
    "sg:classifiers":[
        {
            "category":"Personal",
            "subcategory":"Beauty Salon",
            "type":"Services"
        }
    ],
    "sg:phone":"+1 416 289 7865",
    "sg:postcode":"M1H 2Y2",
    "sg:province":"ON",
    "sg:tags":[
        "manicuring"
    ],
    "wof:name":"Hot Nails",
    "wof:placetype":"venue"
},
  "geometry": {"coordinates":[-79.22881317140001,43.7683258057],"type":"Point"}
}