{
  "type": "Feature",
  "properties": {
    "iso:country":"CA",
    "sg:address":"1165 Black River Rd",
    "sg:city":"Wolfville",
    "sg:classifiers":[
        {
            "category":"Farming",
            "subcategory":"Aquatic Farm",
            "type":"Manufacturing & Wholesale Goods"
        }
    ],
    "sg:phone":"+1 902 542 3336",
    "sg:postcode":"B4P 2R1",
    "sg:province":"NS",
    "sg:tags":[
        "hatchery",
        "fish"
    ],
    "wof:name":"Big Falls Fish Growers Ltd",
    "wof:placetype":"venue"
},
  "geometry": {"coordinates":[-64.36320495610001,45.0913543701],"type":"Point"}
}