{
  "type": "Feature",
  "properties": {
    "addr:full":"5588 Rue Jean-Talon E Saint-Leonard QC H1S 1L9",
    "addr:housenumber":"5588",
    "addr:postcode":"h1s 1l9",
    "addr:street":"Rue Jean-Talon E",
    "iso:country":"CA",
    "sg:address":"5588 Rue Jean-Talon E",
    "sg:city":"Saint-Leonard",
    "sg:classifiers":[
        {
            "category":"Wholesale",
            "subcategory":"Meat",
            "type":"Manufacturing & Wholesale Goods"
        }
    ],
    "sg:phone":"+1 514 253 0071",
    "sg:postcode":"H1S 1L9",
    "sg:province":"QC",
    "sg:tags":[
        "butchering"
    ],
    "wof:name":"Boucherie Charcuterie A-1",
    "wof:placetype":"venue"
},
  "geometry": {"coordinates":[-73.5803146362,45.5821418762],"type":"Point"}
}