{
  "type": "Feature",
  "properties": {
    "addr:full":"Scarborough ON M1E 4X9",
    "addr:postcode":"m1e 4x9",
    "iso:country":"CA",
    "sg:city":"Scarborough",
    "sg:classifiers":[
        {
            "category":"Health Services",
            "subcategory":"Chiropractor",
            "type":"Services"
        }
    ],
    "sg:phone":"+1 416 282 7937",
    "sg:postcode":"M1E 4X9",
    "sg:province":"ON",
    "wof:name":"Kura, Martin DC",
    "wof:placetype":"venue"
},
  "geometry": {"coordinates":[-79.184433,43.768951],"type":"Point"}
}