{
  "type": "Feature",
  "properties": {
    "iso:country":"CA",
    "sg:address":"331 Rue Principale",
    "sg:city":"Saint-Honore-DE-Shenley",
    "sg:classifiers":[
        {
            "category":"Manufacturing",
            "subcategory":"Lumber",
            "type":"Manufacturing & Wholesale Goods"
        }
    ],
    "sg:phone":"+1 418 485 7777",
    "sg:postcode":"G0M 1V0",
    "sg:province":"QC",
    "sg:tags":[
        "syrup",
        "maple",
        "sugar"
    ],
    "wof:name":"Produits DE L'Erable Du Grand",
    "wof:placetype":"venue"
},
  "geometry": {"coordinates":[-70.8400268555,45.9605178833],"type":"Point"}
}