{
  "type": "Feature",
  "properties": {
    "addr:full":"Saint-Georges QC G5Y 5L6",
    "addr:postcode":"g5y 5l6",
    "iso:country":"CA",
    "sg:city":"Saint-Georges",
    "sg:classifiers":[
        {
            "category":"Shopping",
            "subcategory":"Clothing, Apparel, & Fashions",
            "type":"Retail Goods"
        }
    ],
    "sg:phone":"+1 418 228 2820",
    "sg:postcode":"G5Y 5L6",
    "sg:province":"QC",
    "wof:name":"Boutique Colori Inc",
    "wof:placetype":"venue"
},
  "geometry": {"coordinates":[-70.6993026733,46.1324539185],"type":"Point"}
}