{
  "type": "Feature",
  "properties": {
    "addr:full":"58 Blyth St Richmond Hill ON L4E 2W6",
    "addr:housenumber":"58",
    "addr:postcode":"l4e 2w6",
    "addr:street":"Blyth St",
    "iso:country":"CA",
    "sg:address":"58 Blyth St",
    "sg:city":"Richmond Hill",
    "sg:classifiers":[
        {
            "category":"Wholesale",
            "subcategory":"Non-durable Goods",
            "type":"Manufacturing & Wholesale Goods"
        }
    ],
    "sg:phone":"+1 905 773 1256",
    "sg:postcode":"L4E 2W6",
    "sg:province":"ON",
    "sg:tags":[
        "advertising"
    ],
    "wof:name":"Markcona Promotions Inc",
    "wof:placetype":"venue"
},
  "geometry": {"coordinates":[-79.469116,43.948284],"type":"Point"}
}