{
  "type": "Feature",
  "properties": {
    "iso:country":"CA",
    "sg:address":"2391 Av DE LA Ronde",
    "sg:city":"Quebec",
    "sg:classifiers":[
        {
            "category":"Manufacturing",
            "subcategory":"Printing",
            "type":"Manufacturing & Wholesale Goods"
        }
    ],
    "sg:phone":"+1 418 523 8931",
    "sg:postcode":"G1J 4E9",
    "sg:province":"QC",
    "sg:tags":[
        "printer"
    ],
    "wof:name":"Imprimerie Laliberte Inc",
    "wof:placetype":"venue"
},
  "geometry": {"coordinates":[-71.2294006348,46.8417243958],"type":"Point"}
}