{
  "type": "Feature",
  "properties": {
    "addr:full":"Kamloops BC V2C 5P3",
    "addr:postcode":"bc v2c 5p3",
    "iso:country":"CA",
    "sg:city":"Kamloops",
    "sg:classifiers":[
        {
            "category":"Shopping",
            "subcategory":"Computers & Home Electronics",
            "type":"Retail Goods"
        }
    ],
    "sg:phone":"+1 250 372 0799",
    "sg:postcode":"V2C 5P3",
    "sg:province":"BC",
    "sg:tags":[
        "equipment",
        "dealer"
    ],
    "wof:name":"Business World Computer Ctr",
    "wof:placetype":"venue"
},
  "geometry": {"coordinates":[-120.356964,50.662643],"type":"Point"}
}