{
  "type": "Feature",
  "properties": {
    "addr:full":"1015 Rue Galt E Sherbrooke QC J1G 1Y7",
    "addr:housenumber":"1015",
    "addr:postcode":"j1g 1y7",
    "addr:street":"Rue Galt E",
    "iso:country":"CA",
    "sg:address":"1015 Rue Galt E",
    "sg:city":"Sherbrooke",
    "sg:classifiers":[
        {
            "category":"Building & Trades",
            "subcategory":"Cleaning & Sanitation",
            "type":"Services"
        }
    ],
    "sg:phone":"+1 819 562 5622",
    "sg:postcode":"J1G 1Y7",
    "sg:province":"QC",
    "sg:tags":[
        "maintenance"
    ],
    "wof:name":"G C Specialties Inc",
    "wof:placetype":"venue"
},
  "geometry": {"coordinates":[-71.8661956787,45.3964080811],"type":"Point"}
}