{
  "type": "Feature",
  "properties": {
    "iso:country":"CA",
    "sg:address":"General Delivery",
    "sg:city":"New Harbour Tb",
    "sg:classifiers":[
        {
            "category":"Shopping",
            "subcategory":"Catalog Store",
            "type":"Retail Goods"
        }
    ],
    "sg:phone":"+1 709 582 3200",
    "sg:postcode":"A0B 2P0",
    "sg:province":"NL",
    "sg:tags":[
        "mail",
        "order",
        "internet"
    ],
    "wof:name":"Sears Canada Inc",
    "wof:placetype":"venue"
},
  "geometry": {"coordinates":[-53.5431785583,47.5848426819],"type":"Point"}
}