{
  "type": "Feature",
  "properties": {
    "addr:full":"28 Grande Allee O Grande-Riviere-Ouest QC G0C 1W0",
    "addr:housenumber":"28",
    "addr:postcode":"g0c 1w0",
    "addr:street":"Grande Allee O Grande-Riviere-Ouest",
    "iso:country":"CA",
    "sg:address":"28 Grande Allee O",
    "sg:city":"Grande-Riviere-Ouest",
    "sg:classifiers":[
        {
            "category":"Shopping",
            "subcategory":"Department Store",
            "type":"Retail Goods"
        }
    ],
    "sg:phone":"+1 418 385 2822",
    "sg:postcode":"G0C 1W0",
    "sg:province":"QC",
    "wof:name":"J Gerard Methot Magasin A Ryns",
    "wof:placetype":"venue"
},
  "geometry": {"coordinates":[-64.5155410767,48.3909034729],"type":"Point"}
}