{
  "type": "Feature",
  "properties": {
    "iso:country":"CA",
    "sg:address":"6610 176 St",
    "sg:city":"Surrey",
    "sg:classifiers":[
        {
            "category":"Manufacturing",
            "subcategory":"Tools & Machinery",
            "type":"Manufacturing & Wholesale Goods"
        }
    ],
    "sg:phone":"+1 604 576 9441",
    "sg:postcode":"V3S 4G5",
    "sg:province":"BC",
    "sg:tags":[
        "lubricating",
        "system",
        "devices",
        "compressor"
    ],
    "wof:name":"Wiseworth Canada Industries",
    "wof:placetype":"venue"
},
  "geometry": {"coordinates":[-122.73469543500001,49.1222991943],"type":"Point"}
}