{
  "type": "Feature",
  "properties": {
    "addr:full":"7225 Duncan St Powell River BC V8A 1W4",
    "addr:housenumber":"7225",
    "addr:postcode":"v8a 1w4",
    "addr:street":"Duncan St",
    "iso:country":"CA",
    "sg:address":"7225 Duncan St",
    "sg:city":"Powell River",
    "sg:classifiers":[
        {
            "category":"Home & Garden",
            "subcategory":"Building Materials",
            "type":"Retail Goods"
        }
    ],
    "sg:phone":"+1 604 485 9761",
    "sg:postcode":"V8A 1W4",
    "sg:province":"BC",
    "sg:tags":[
        "plumbing",
        "fixture",
        "supply"
    ],
    "wof:name":"Pete's Plumbing & Heating",
    "wof:placetype":"venue"
},
  "geometry": {"coordinates":[-124.511246,49.837177],"type":"Point"}
}