{
  "type": "Feature",
  "properties": {
    "iso:country":"CA",
    "sg:address":"4150 Boul Thimens",
    "sg:city":"Saint-Laurent",
    "sg:classifiers":[
        {
            "category":"Manufacturing",
            "subcategory":"Motor Vehicles & Parts",
            "type":"Manufacturing & Wholesale Goods"
        }
    ],
    "sg:phone":"+1 514 333 4991",
    "sg:postcode":"H4R 2B9",
    "sg:province":"QC",
    "sg:tags":[
        "equipment",
        "truck"
    ],
    "wof:name":"Yad Heavy Duty Parts Inc",
    "wof:placetype":"venue"
},
  "geometry": {"coordinates":[-73.7169265747,45.493850708],"type":"Point"}
}