{
  "type": "Feature",
  "properties": {
    "addr:full":"4289 Rue Majeau Montreal-Nord QC H1H 2V7",
    "addr:housenumber":"4289",
    "addr:postcode":"h1h 2v7",
    "addr:street":"Rue Majeau",
    "iso:country":"CA",
    "sg:address":"4289 Rue Majeau",
    "sg:city":"Montreal-Nord",
    "sg:classifiers":[
        {
            "category":"Manufacturing",
            "subcategory":"Furniture",
            "type":"Manufacturing & Wholesale Goods"
        }
    ],
    "sg:phone":"+1 514 327 7201",
    "sg:postcode":"H1H 2V7",
    "sg:province":"QC",
    "sg:tags":[
        "material",
        "fixture",
        "display"
    ],
    "wof:name":"Fermos Inc",
    "wof:placetype":"venue"
},
  "geometry": {"coordinates":[-73.6293182373,45.5869293213],"type":"Point"}
}