{
  "type": "Feature",
  "properties": {
    "iso:country":"CA",
    "sg:address":"2458 Dundas St W",
    "sg:city":"Mississauga",
    "sg:classifiers":[
        {
            "category":"Real Estate",
            "subcategory":"Real Estate Operator",
            "type":"Services"
        }
    ],
    "sg:phone":"+1 905 822 2615",
    "sg:postcode":"L5K 1R8",
    "sg:province":"ON",
    "sg:tags":[
        "mall",
        "shopping",
        "center"
    ],
    "wof:name":"Woodchester Mall Shopping Ctr",
    "wof:placetype":"venue"
},
  "geometry": {"coordinates":[-79.6756973267,43.5280380249],"type":"Point"}
}