{
  "type": "Feature",
  "properties": {
    "addr:full":"26 Whytes Rd Bancroft ON K0L 1C0",
    "addr:housenumber":"26",
    "addr:postcode":"k0l 1c0",
    "addr:street":"Whytes Rd",
    "iso:country":"CA",
    "sg:address":"26 Whytes Rd",
    "sg:city":"Bancroft",
    "sg:classifiers":[
        {
            "category":"Retail",
            "subcategory":"Repair Shop",
            "type":"Services"
        }
    ],
    "sg:phone":"+1 613 332 2313",
    "sg:postcode":"K0L 1C0",
    "sg:province":"ON",
    "sg:tags":[
        "welding"
    ],
    "wof:name":"Valley View Garage",
    "wof:placetype":"venue"
},
  "geometry": {"coordinates":[-77.853348,45.056541],"type":"Point"}
}