{
  "type": "Feature",
  "properties": {
    "iso:country":"CA",
    "sg:address":"2 Charles Walk",
    "sg:city":"Elliot Lake",
    "sg:classifiers":[
        {
            "category":"Freight",
            "type":"Transportation"
        }
    ],
    "sg:phone":"+1 705 848 3013",
    "sg:postcode":"P5A 2A3",
    "sg:province":"ON",
    "sg:tags":[
        "bus",
        "line",
        "courier"
    ],
    "wof:name":"Greyhound Lines of Canada Ltd",
    "wof:placetype":"venue"
},
  "geometry": {"coordinates":[-82.64813995359999,46.3861961365],"type":"Point"}
}