{
  "type": "Feature",
  "properties": {
    "addr:full":"62 Nassau St Toronto ON M5T 1M2",
    "addr:housenumber":"62",
    "addr:postcode":"m5t 1m2",
    "addr:street":"Nassau St",
    "iso:country":"CA",
    "sg:address":"62 Nassau St",
    "sg:city":"Toronto",
    "sg:classifiers":[
        {
            "category":"Communications",
            "subcategory":"Radio Station",
            "type":"Services"
        }
    ],
    "sg:phone":"+1 416 596 1566",
    "sg:postcode":"M5T 1M2",
    "sg:province":"ON",
    "sg:tags":[
        "company",
        "broadcasting"
    ],
    "wof:name":"Asas DO Atlantico",
    "wof:placetype":"venue"
},
  "geometry": {"coordinates":[-79.4019393921,43.6554412842],"type":"Point"}
}