{
  "type": "Feature",
  "properties": {
    "addr:full":"1688 4th Ave W Vancouver BC V6J 1L9",
    "addr:housenumber":"1688",
    "addr:postcode":"v6j 1l9",
    "addr:street":"4Th Ave W",
    "iso:country":"CA",
    "sg:address":"1688 4th Ave W",
    "sg:city":"Vancouver",
    "sg:classifiers":[
        {
            "category":"Restaurant",
            "type":"Food & Drink"
        }
    ],
    "sg:phone":"+1 604 742 8386",
    "sg:postcode":"V6J 1L9",
    "sg:province":"BC",
    "wof:name":"Ordinary Cafe",
    "wof:placetype":"venue"
},
  "geometry": {"coordinates":[-123.143089,49.267918],"type":"Point"}
}