{
  "type": "Feature",
  "properties": {
    "addr:full":"Montreal QC H3B 4R7",
    "addr:postcode":"h3b 4r7",
    "iso:country":"CA",
    "sg:city":"Montreal",
    "sg:classifiers":[
        {
            "category":"Professional",
            "subcategory":"Business Services",
            "type":"Services"
        }
    ],
    "sg:phone":"+1 514 875 8100",
    "sg:postcode":"H3B 4R7",
    "sg:province":"QC",
    "wof:name":"Wise Blackman",
    "wof:placetype":"venue"
},
  "geometry": {"coordinates":[-73.56797,45.50182],"type":"Point"}
}