{
  "type": "Feature",
  "properties": {
    "addr:full":"10 Boul Pabos Pabos QC G0C 2H0",
    "addr:housenumber":"10",
    "addr:postcode":"g0c 2h0",
    "addr:street":"Boul Pabos Pabos",
    "iso:country":"CA",
    "sg:address":"10 Boul Pabos",
    "sg:city":"Pabos",
    "sg:classifiers":[
        {
            "category":"Organizations",
            "subcategory":"Professional Association",
            "type":"Services"
        }
    ],
    "sg:phone":"+1 418 689 4912",
    "sg:postcode":"G0C 2H0",
    "sg:province":"QC",
    "wof:name":"Regroupement Pour LA Rstrntn",
    "wof:placetype":"venue"
},
  "geometry": {"coordinates":[-64.65419799999999,48.352089],"type":"Point"}
}