{
  "type": "Feature",
  "properties": {
    "addr:full":"Edmonton AB T6H 2J5",
    "addr:postcode":"t6h 2j5",
    "iso:country":"CA",
    "sg:city":"Edmonton",
    "sg:classifiers":[
        {
            "category":"Manufacturing",
            "subcategory":"Tools & Machinery",
            "type":"Manufacturing & Wholesale Goods"
        }
    ],
    "sg:phone":"+1 780 434 8537",
    "sg:postcode":"T6H 2J5",
    "sg:province":"AB",
    "sg:tags":[
        "lubricating",
        "system",
        "devices"
    ],
    "wof:name":"Husco Industrial Ltd",
    "wof:placetype":"venue"
},
  "geometry": {"coordinates":[-113.492210388,53.4923324585],"type":"Point"}
}