{
  "type": "Feature",
  "properties": {
    "addr:full":"Farm Yarbo SK S0A 4V0",
    "addr:postcode":"s0a 4v0",
    "iso:country":"CA",
    "sg:address":"Farm",
    "sg:city":"Yarbo",
    "sg:classifiers":[
        {
            "category":"Farming",
            "subcategory":"Nursery",
            "type":"Manufacturing & Wholesale Goods"
        }
    ],
    "sg:phone":"+1 306 745 3830",
    "sg:postcode":"S0A 4V0",
    "sg:province":"SK",
    "sg:tags":[
        "seed"
    ],
    "wof:name":"Fraser Seed",
    "wof:placetype":"venue"
},
  "geometry": {"coordinates":[-101.93182400000001,50.695152],"type":"Point"}
}