{
  "type": "Feature",
  "properties": {
    "addr:full":"2900 Cedarbrae Dr SW Calgary AB T2W 3S9",
    "addr:housenumber":"2900",
    "addr:postcode":"t2w 3s9",
    "addr:street":"Cedarbrae Dr Sw",
    "iso:country":"CA",
    "sg:address":"2900 Cedarbrae Dr SW",
    "sg:city":"Calgary",
    "sg:classifiers":[
        {
            "category":"Organizations",
            "subcategory":"Religious Organization",
            "type":"Services"
        }
    ],
    "sg:phone":"+1 403 281 6755",
    "sg:postcode":"T2W 3S9",
    "sg:province":"AB",
    "sg:tags":[
        "church"
    ],
    "wof:name":"South Calgary Community Church",
    "wof:placetype":"venue"
},
  "geometry": {"coordinates":[-114.129455566,50.9572639465],"type":"Point"}
}