{
  "type": "Feature",
  "properties": {
    "iso:country":"CA",
    "sg:address":"2193 Rue DE LA Province",
    "sg:city":"Longueuil",
    "sg:classifiers":[
        {
            "category":"Real Estate",
            "subcategory":"Real Estate Agent",
            "type":"Services"
        }
    ],
    "sg:phone":"+1 450 442 4283",
    "sg:postcode":"J4G 1R2",
    "sg:province":"QC",
    "sg:tags":[
        "agency",
        "rental"
    ],
    "wof:name":"Locaparty Enr",
    "wof:placetype":"venue"
},
  "geometry": {"coordinates":[-73.469246,45.566509],"type":"Point"}
}