{
  "type": "Feature",
  "properties": {
    "iso:country":"CA",
    "sg:city":"Burlington",
    "sg:classifiers":[
        {
            "category":"Real Estate",
            "subcategory":"Real Estate Operator",
            "type":"Services"
        }
    ],
    "sg:phone":"+1 905 632 5339",
    "sg:postcode":"L7R 4A9",
    "sg:province":"ON",
    "sg:tags":[
        "apartment"
    ],
    "wof:name":"Martha Terrace Apartments",
    "wof:placetype":"venue"
},
  "geometry": {"coordinates":[-79.79326629640001,43.3272094727],"type":"Point"}
}