{
  "type": "Feature",
  "properties": {
    "addr:full":"Hwy 20 Hanceville BC V0L 1K0",
    "addr:postcode":"v0l 1k0",
    "addr:street":"Hwy 20",
    "iso:country":"CA",
    "sg:address":"Hwy 20",
    "sg:city":"Hanceville",
    "sg:classifiers":[
        {
            "category":"Education",
            "subcategory":"School",
            "type":"Public Place"
        }
    ],
    "sg:phone":"+1 250 394 4217",
    "sg:postcode":"V0L 1K0",
    "sg:province":"BC",
    "wof:name":"Stone Band School",
    "wof:placetype":"venue"
},
  "geometry": {"coordinates":[-123.089546,51.93745],"type":"Point"}
}