{
  "type": "Feature",
  "properties": {
    "addr:full":"115 Arnold Ave Thornhill ON L4J 1B6",
    "addr:housenumber":"115",
    "addr:postcode":"l4j 1b6",
    "addr:street":"Arnold Ave",
    "iso:country":"CA",
    "sg:address":"115 Arnold Ave",
    "sg:city":"Thornhill",
    "sg:classifiers":[
        {
            "category":"Manufacturing",
            "subcategory":"Paper Products",
            "type":"Manufacturing & Wholesale Goods"
        }
    ],
    "sg:phone":"+1 905 707 7720",
    "sg:postcode":"L4J 1B6",
    "sg:province":"ON",
    "sg:tags":[
        "bag"
    ],
    "wof:name":"Supreme Marketing",
    "wof:placetype":"venue"
},
  "geometry": {"coordinates":[-79.43380000000001,43.809315],"type":"Point"}
}