{
  "type": "Feature",
  "properties": {
    "addr:full":"866 Walker Rd Windsor ON N8Y 2N5",
    "addr:housenumber":"866",
    "addr:postcode":"n8y 2n5",
    "addr:street":"Walker Rd",
    "iso:country":"CA",
    "sg:address":"866 Walker Rd",
    "sg:city":"Windsor",
    "sg:classifiers":[
        {
            "category":"Manufacturing",
            "subcategory":"Printing",
            "type":"Manufacturing & Wholesale Goods"
        }
    ],
    "sg:phone":"+1 519 258 8300",
    "sg:postcode":"N8Y 2N5",
    "sg:province":"ON",
    "sg:tags":[
        "printer"
    ],
    "wof:name":"Border Press Inc",
    "wof:placetype":"venue"
},
  "geometry": {"coordinates":[-83.006721,42.321644],"type":"Point"}
}