{
  "type": "Feature",
  "properties": {
    "addr:full":"Red Deer AB T4N 6C9",
    "addr:postcode":"t4n 6c9",
    "iso:country":"CA",
    "sg:city":"Red Deer",
    "sg:classifiers":[
        {
            "category":"Health Services",
            "subcategory":"Doctor",
            "type":"Services"
        }
    ],
    "sg:phone":"+1 403 343 7277",
    "sg:postcode":"T4N 6C9",
    "sg:province":"AB",
    "sg:tags":[
        "dentist"
    ],
    "wof:name":"Dawes, Tracy DDS",
    "wof:placetype":"venue"
},
  "geometry": {"coordinates":[-113.81281280499999,52.2782173157],"type":"Point"}
}