{
  "type": "Feature",
  "properties": {
    "addr:full":"2694 St Clair Ave Windsor ON N9E 4L6",
    "addr:housenumber":"2694",
    "addr:postcode":"n9e 4l6",
    "addr:street":"St Clair Ave",
    "iso:country":"CA",
    "sg:address":"2694 St Clair Ave",
    "sg:city":"Windsor",
    "sg:classifiers":[
        {
            "category":"Building & Trades",
            "subcategory":"Construction",
            "type":"Services"
        }
    ],
    "sg:phone":"+1 519 966 3081",
    "sg:postcode":"N9E 4L6",
    "sg:province":"ON",
    "sg:tags":[
        "general",
        "contractor"
    ],
    "wof:name":"Vinpico Construction Ltd",
    "wof:placetype":"venue"
},
  "geometry": {"coordinates":[-83.0411682129,42.2688522339],"type":"Point"}
}