{
  "type": "Feature",
  "properties": {
    "iso:country":"CA",
    "sg:address":"6835 Merritt Ave",
    "sg:city":"Burnaby",
    "sg:classifiers":[
        {
            "category":"Autos & Motor Vehicles",
            "subcategory":"Auto Supplies",
            "type":"Retail Goods"
        }
    ],
    "sg:phone":"+1 604 430 4622",
    "sg:postcode":"V5J 4R5",
    "sg:province":"BC",
    "sg:tags":[
        "repairing",
        "radiator",
        "automobile",
        "air",
        "equipment",
        "conditioning"
    ],
    "wof:name":"Cool-It Radiators Ltd",
    "wof:placetype":"venue"
},
  "geometry": {"coordinates":[-122.980445862,49.2215003967],"type":"Point"}
}