{
  "type": "Feature",
  "properties": {
    "iso:country":"CA",
    "sg:address":"930 Talbot St",
    "sg:city":"St Thomas",
    "sg:classifiers":[
        {
            "category":"Restaurant",
            "type":"Food & Drink"
        }
    ],
    "sg:phone":"+1 519 633 5404",
    "sg:postcode":"N5P 1E7",
    "sg:province":"ON",
    "sg:tags":[
        "high",
        "fidelity",
        "stereophonic"
    ],
    "wof:name":"Century Sound",
    "wof:placetype":"venue"
},
  "geometry": {"coordinates":[-81.18133544920001,42.7787017822],"type":"Point"}
}