{
  "type": "Feature",
  "properties": {
    "iso:country":"CA",
    "sg:address":"320 Rue Du Saguenay",
    "sg:city":"Victoriaville",
    "sg:classifiers":[
        {
            "category":"Wholesale",
            "subcategory":"Auto Parts",
            "type":"Manufacturing & Wholesale Goods"
        }
    ],
    "sg:phone":"+1 819 758 6878",
    "sg:postcode":"G6T 1T6",
    "sg:province":"QC",
    "sg:tags":[
        "equipment",
        "truck"
    ],
    "wof:name":"Diesel & Gaz Victo",
    "wof:placetype":"venue"
},
  "geometry": {"coordinates":[-71.95156900000001,46.072411],"type":"Point"}
}