{
  "type": "Feature",
  "properties": {
    "addr:full":"2 Maitland St Toronto ON M4Y 1C5",
    "addr:housenumber":"2",
    "addr:postcode":"m4y 1c5",
    "addr:street":"Maitland St",
    "iso:country":"CA",
    "sg:address":"2 Maitland St",
    "sg:city":"Toronto",
    "sg:classifiers":[
        {
            "category":"Shopping",
            "subcategory":"Discount & Variety Stores",
            "type":"Retail Goods"
        }
    ],
    "sg:phone":"+1 416 324 9929",
    "sg:postcode":"M4Y 1C5",
    "sg:province":"ON",
    "wof:name":"Maitland Variety",
    "wof:placetype":"venue"
},
  "geometry": {"coordinates":[-79.38402600000001,43.66394],"type":"Point"}
}