{
  "type": "Feature",
  "properties": {
    "addr:full":"5006 50 St Stony Plain AB T7Z 1T2",
    "addr:housenumber":"5006",
    "addr:postcode":"t7z 1t2",
    "addr:street":"50 St",
    "iso:country":"CA",
    "sg:address":"5006 50 St",
    "sg:city":"Stony Plain",
    "sg:classifiers":[
        {
            "category":"Manufacturing",
            "subcategory":"Printing",
            "type":"Manufacturing & Wholesale Goods"
        }
    ],
    "sg:phone":"+1 780 963 2291",
    "sg:postcode":"T7Z 1T2",
    "sg:province":"AB",
    "sg:tags":[
        "newspaper"
    ],
    "wof:name":"Stony Plain Reporter",
    "wof:placetype":"venue"
},
  "geometry": {"coordinates":[-114.007377624,53.5294647217],"type":"Point"}
}