{
  "type": "Feature",
  "properties": {
    "addr:full":"Surrey BC V3W 0J5",
    "addr:postcode":"v3w 0j5",
    "iso:country":"CA",
    "sg:city":"Surrey",
    "sg:classifiers":[
        {
            "category":"Education",
            "subcategory":"Dance Studio",
            "type":"Public Place"
        }
    ],
    "sg:phone":"+1 604 591 5753",
    "sg:postcode":"V3W 0J5",
    "sg:province":"BC",
    "sg:tags":[
        "instruction",
        "dancing"
    ],
    "wof:name":"Dance West",
    "wof:placetype":"venue"
},
  "geometry": {"coordinates":[-122.880096435,49.1556930542],"type":"Point"}
}