{
  "type": "Feature",
  "properties": {
    "addr:full":"1777 Brookside Blvd Winnipeg MB R3C 2E6",
    "addr:housenumber":"1777",
    "addr:postcode":"r3c 2e6",
    "addr:street":"Brookside Blvd",
    "iso:country":"CA",
    "sg:address":"1777 Brookside Blvd",
    "sg:city":"Winnipeg",
    "sg:classifiers":[
        {
            "category":"Autos & Motor Vehicles",
            "subcategory":"Auto Supplies",
            "type":"Retail Goods"
        }
    ],
    "sg:phone":"+1 204 694 8560",
    "sg:postcode":"R3C 2E6",
    "sg:province":"MB",
    "sg:tags":[
        "tire"
    ],
    "wof:name":"Kal Tire",
    "wof:placetype":"venue"
},
  "geometry": {"coordinates":[-97.229294,49.943043],"type":"Point"}
}