{
  "type": "Feature",
  "properties": {
    "addr:full":"270 Ch Du Tremblay Boucherville QC J4B 5X9",
    "addr:housenumber":"270",
    "addr:postcode":"j4b 5x9",
    "addr:street":"Ch Du Tremblay",
    "iso:country":"CA",
    "sg:address":"270 Ch Du Tremblay",
    "sg:city":"Boucherville",
    "sg:classifiers":[
        {
            "category":"Building & Trades",
            "subcategory":"Construction",
            "type":"Services"
        }
    ],
    "sg:phone":"+1 450 641 4000",
    "sg:postcode":"J4B 5X9",
    "sg:province":"QC",
    "wof:name":"Murox",
    "wof:placetype":"venue"
},
  "geometry": {"coordinates":[-73.41735799999999,45.566036],"type":"Point"}
}