{
  "type": "Feature",
  "properties": {
    "addr:full":"5851 Yonge St North York ON M2M 3T9",
    "addr:housenumber":"5851",
    "addr:postcode":"m2m 3t9",
    "addr:street":"Yonge St",
    "iso:country":"CA",
    "sg:address":"5851 Yonge St",
    "sg:city":"North York",
    "sg:classifiers":[
        {
            "category":"Shopping",
            "subcategory":"Stationery & Office Supplies",
            "type":"Retail Goods"
        }
    ],
    "sg:phone":"+1 416 223 8898",
    "sg:postcode":"M2M 3T9",
    "sg:province":"ON",
    "sg:tags":[
        "educational",
        "material"
    ],
    "wof:name":"Scholar's Choice Retail Store",
    "wof:placetype":"venue"
},
  "geometry": {"coordinates":[-79.416718,43.78532],"type":"Point"}
}