{
  "type": "Feature",
  "properties": {
    "addr:full":"211 2nd Ave Medstead SK S0M 1W0",
    "addr:housenumber":"211",
    "addr:postcode":"s0m 1w0",
    "addr:street":"2Nd Ave",
    "iso:country":"CA",
    "sg:address":"211 2nd Ave",
    "sg:city":"Medstead",
    "sg:classifiers":[
        {
            "category":"Wholesale",
            "subcategory":"Farm Supplies",
            "type":"Manufacturing & Wholesale Goods"
        }
    ],
    "sg:phone":"+1 306 342 2027",
    "sg:postcode":"S0M 1W0",
    "sg:province":"SK",
    "wof:name":"Medstead Farm Supply",
    "wof:placetype":"venue"
},
  "geometry": {"coordinates":[-108.076668,53.297176],"type":"Point"}
}