{
  "type": "Feature",
  "properties": {
    "iso:country":"CA",
    "sg:address":"1775 Boul Trudel E",
    "sg:city":"Saint-Boniface-DE-Shawinigan",
    "sg:classifiers":[
        {
            "category":"Building & Trades",
            "subcategory":"Construction",
            "type":"Services"
        }
    ],
    "sg:phone":"+1 819 535 3944",
    "sg:postcode":"G0X 2L0",
    "sg:province":"QC",
    "sg:tags":[
        "builder",
        "stair"
    ],
    "wof:name":"Escaliers Pierre Houle Inc",
    "wof:placetype":"venue"
},
  "geometry": {"coordinates":[-72.80824279789999,46.5245666504],"type":"Point"}
}