{
  "type": "Feature",
  "properties": {
    "addr:full":"Brossard QC J4W 3H3",
    "addr:postcode":"j4w 3h3",
    "iso:country":"CA",
    "sg:city":"Brossard",
    "sg:classifiers":[
        {
            "category":"Travel",
            "subcategory":"Travel Agent",
            "type":"Entertainment"
        }
    ],
    "sg:phone":"+1 450 466 0444",
    "sg:postcode":"J4W 3H3",
    "sg:province":"QC",
    "sg:tags":[
        "agency",
        "bureau"
    ],
    "wof:name":"Voyage En Direct Brossard",
    "wof:placetype":"venue"
},
  "geometry": {"coordinates":[-73.4652938843,45.4552536011],"type":"Point"}
}