{
  "type": "Feature",
  "properties": {
    "iso:country":"CA",
    "sg:address":"2221 Yonge St #Ll10",
    "sg:city":"Toronto",
    "sg:classifiers":[
        {
            "category":"Real Estate",
            "subcategory":"Real Estate Agent",
            "type":"Services"
        }
    ],
    "sg:phone":"+1 416 440 0858",
    "sg:postcode":"M4S 2B4",
    "sg:province":"ON",
    "wof:name":"Venture Point Realty Ltd",
    "wof:placetype":"venue"
},
  "geometry": {"coordinates":[-79.3979797363,43.7058601379],"type":"Point"}
}