{
  "type": "Feature",
  "properties": {
    "iso:country":"CA",
    "sg:city":"Toronto",
    "sg:classifiers":[
        {
            "category":"Professional",
            "subcategory":"Employment Agencies",
            "type":"Services"
        }
    ],
    "sg:phone":"+1 416 515 2073",
    "sg:postcode":"M5R 1B9",
    "sg:province":"ON",
    "sg:tags":[
        "opportunity"
    ],
    "wof:name":"Personnel Opportunities Ltd",
    "wof:placetype":"venue"
},
  "geometry": {"coordinates":[-79.3908691406,43.6712646484],"type":"Point"}
}