{
  "type": "Feature",
  "properties": {
    "iso:country":"CA",
    "sg:address":"260 Rue Faillon O",
    "sg:city":"Montreal",
    "sg:classifiers":[
        {
            "category":"Manufacturing",
            "subcategory":"Apparel",
            "type":"Manufacturing & Wholesale Goods"
        }
    ],
    "sg:phone":"+1 514 384 7691",
    "sg:postcode":"H2R 2V7",
    "sg:province":"QC",
    "sg:tags":[
        "clothing"
    ],
    "wof:name":"Lilianne Lingerie",
    "wof:placetype":"venue"
},
  "geometry": {"coordinates":[-73.620865,45.538452],"type":"Point"}
}