{
  "type": "Feature",
  "properties": {
    "addr:full":"2060 Sumas Way Abbotsford BC V2S 2C7",
    "addr:housenumber":"2060",
    "addr:postcode":"v2s 2c7",
    "addr:street":"Sumas Way",
    "iso:country":"CA",
    "sg:address":"2060 Sumas Way",
    "sg:city":"Abbotsford",
    "sg:classifiers":[
        {
            "category":"Restaurant",
            "type":"Food & Drink"
        }
    ],
    "sg:phone":"+1 604 504 5900",
    "sg:postcode":"V2S 2C7",
    "sg:province":"BC",
    "wof:name":"Boston Pizza Restaurants",
    "wof:placetype":"venue"
},
  "geometry": {"coordinates":[-122.26797500000001,49.037479],"type":"Point"}
}