{
  "type": "Feature",
  "properties": {
    "iso:country":"CA",
    "sg:address":"10938 124 St NW",
    "sg:city":"Edmonton",
    "sg:classifiers":[
        {
            "category":"Professional",
            "subcategory":"Lawyer & Legal Services",
            "type":"Services"
        }
    ],
    "sg:phone":"+1 780 451 2769",
    "sg:postcode":"T5M 0H5",
    "sg:province":"AB",
    "sg:tags":[
        "attorney"
    ],
    "wof:name":"Hamish Henderson Law Offices",
    "wof:placetype":"venue"
},
  "geometry": {"coordinates":[-113.536216736,53.5551185608],"type":"Point"}
}