{
  "type": "Feature",
  "properties": {
    "addr:full":"Sudbury ON P3C 1L8",
    "addr:postcode":"p3c 1l8",
    "iso:country":"CA",
    "sg:city":"Sudbury",
    "sg:classifiers":[
        {
            "category":"Home & Garden",
            "subcategory":"Household Appliances",
            "type":"Retail Goods"
        }
    ],
    "sg:phone":"+1 705 522 0729",
    "sg:postcode":"P3C 1L8",
    "sg:province":"ON",
    "wof:name":"Cambrian Appliance Svc",
    "wof:placetype":"venue"
},
  "geometry": {"coordinates":[-81.00659899999999,46.490284],"type":"Point"}
}