{
  "type": "Feature",
  "properties": {
    "iso:country":"CA",
    "sg:city":"Kingston",
    "sg:classifiers":[
        {
            "category":"Health Services",
            "subcategory":"Doctor",
            "type":"Services"
        }
    ],
    "sg:phone":"+1 613 389 1099",
    "sg:postcode":"K7P 1T5",
    "sg:province":"ON",
    "sg:tags":[
        "dentist"
    ],
    "wof:name":"Proud, G V DDS",
    "wof:placetype":"venue"
},
  "geometry": {"coordinates":[-76.589058,44.252136],"type":"Point"}
}