{
  "type": "Feature",
  "properties": {
    "iso:country":"CA",
    "sg:address":"1973 Rue Leclair",
    "sg:city":"Waterloo",
    "sg:classifiers":[
        {
            "category":"Health Services",
            "subcategory":"Nursing And Care Facility",
            "type":"Services"
        }
    ],
    "sg:phone":"+1 450 539 4897",
    "sg:postcode":"J0E 2N0",
    "sg:province":"QC",
    "sg:tags":[
        "home",
        "retirement",
        "community",
        "rest"
    ],
    "wof:name":"Place Primevere",
    "wof:placetype":"venue"
},
  "geometry": {"coordinates":[-72.51277160639999,45.3400192261],"type":"Point"}
}