{
  "type": "Feature",
  "properties": {
    "addr:full":"3062 Silverthorn Dr Oakville ON L6L 5N7",
    "addr:housenumber":"3062",
    "addr:postcode":"l6l 5n7",
    "addr:street":"Silverthorn Dr",
    "iso:country":"CA",
    "sg:address":"3062 Silverthorn Dr",
    "sg:city":"Oakville",
    "sg:classifiers":[
        {
            "category":"Professional",
            "subcategory":"Art Services",
            "type":"Services"
        }
    ],
    "sg:phone":"+1 905 469 0525",
    "sg:postcode":"L6L 5N7",
    "sg:province":"ON",
    "sg:tags":[
        "artist"
    ],
    "wof:name":"Stephen Quinlan Illustration",
    "wof:placetype":"venue"
},
  "geometry": {"coordinates":[-79.71909332280001,43.3911247253],"type":"Point"}
}