{
  "type": "Feature",
  "properties": {
    "addr:full":"119 George St Enderby BC V0E 1V0",
    "addr:housenumber":"119",
    "addr:postcode":"v0e 1v0",
    "addr:street":"George St",
    "iso:country":"CA",
    "sg:address":"119 George St",
    "sg:city":"Enderby",
    "sg:classifiers":[
        {
            "category":"Food & Beverages",
            "subcategory":"Liquor & Beverages",
            "type":"Retail Goods"
        }
    ],
    "sg:phone":"+1 250 838 7308",
    "sg:postcode":"V0E 1V0",
    "sg:province":"BC",
    "sg:tags":[
        "store"
    ],
    "wof:name":"Enderby Liquor Stores",
    "wof:placetype":"venue"
},
  "geometry": {"coordinates":[-119.140091,50.543587],"type":"Point"}
}