{
  "type": "Feature",
  "properties": {
    "addr:full":"Brampton ON L6W 3R7",
    "addr:postcode":"l6w 3r7",
    "iso:country":"CA",
    "sg:city":"Brampton",
    "sg:classifiers":[
        {
            "category":"Restaurant",
            "type":"Food & Drink"
        }
    ],
    "sg:phone":"+1 905 451 1910",
    "sg:postcode":"L6W 3R7",
    "sg:province":"ON",
    "wof:name":"Our Place Restaurant",
    "wof:placetype":"venue"
},
  "geometry": {"coordinates":[-79.7411727905,43.689617157],"type":"Point"}
}