{
  "type": "Feature",
  "properties": {
    "addr:full":"42 Rue Principale Sud L'Annonciation QC J0T 1T0",
    "addr:housenumber":"42",
    "addr:postcode":"j0t 1t0",
    "addr:street":"Rue Principale Sud",
    "iso:country":"CA",
    "sg:address":"42 Rue Principale Sud",
    "sg:city":"L'Annonciation",
    "sg:classifiers":[
        {
            "category":"Shopping",
            "subcategory":"Department Store",
            "type":"Retail Goods"
        }
    ],
    "sg:phone":"+1 819 275 9038",
    "sg:postcode":"J0T 1T0",
    "sg:province":"QC",
    "sg:tags":[
        "shop"
    ],
    "wof:name":"Dollar Des Monts",
    "wof:placetype":"venue"
},
  "geometry": {"coordinates":[-74.8690109253,46.4084358215],"type":"Point"}
}