{
  "type": "Feature",
  "properties": {
    "addr:full":"Montreal QC H3J 1N5",
    "addr:postcode":"h3j 1n5",
    "iso:country":"CA",
    "sg:city":"Montreal",
    "sg:classifiers":[
        {
            "category":"Professional",
            "subcategory":"Business Services",
            "type":"Services"
        }
    ],
    "sg:phone":"+1 514 931 8998",
    "sg:postcode":"H3J 1N5",
    "sg:province":"QC",
    "sg:tags":[
        "interior",
        "consultant",
        "design",
        "decorator"
    ],
    "wof:name":"Shadow Design",
    "wof:placetype":"venue"
},
  "geometry": {"coordinates":[-73.544296,45.528233],"type":"Point"}
}