{
  "type": "Feature",
  "properties": {
    "addr:full":"11 Main St Lafleche SK S0H 2K0",
    "addr:housenumber":"11",
    "addr:postcode":"s0h 2k0",
    "addr:street":"Main St",
    "iso:country":"CA",
    "sg:address":"11 Main St",
    "sg:city":"Lafleche",
    "sg:classifiers":[
        {
            "category":"Autos & Motor Vehicles",
            "subcategory":"Auto Supplies",
            "type":"Retail Goods"
        }
    ],
    "sg:phone":"+1 306 472 5245",
    "sg:postcode":"S0H 2K0",
    "sg:province":"SK",
    "sg:tags":[
        "repairing",
        "automobile"
    ],
    "wof:name":"LA Fleche Tire & Svc",
    "wof:placetype":"venue"
},
  "geometry": {"coordinates":[-106.57157100000001,49.698975],"type":"Point"}
}