{
  "type": "Feature",
  "properties": {
    "addr:full":"14 Ottawa St S Kitchener ON N2G 3S5",
    "addr:housenumber":"14",
    "addr:postcode":"n2g 3s5",
    "addr:street":"Ottawa St S",
    "iso:country":"CA",
    "sg:address":"14 Ottawa St S",
    "sg:city":"Kitchener",
    "sg:classifiers":[
        {
            "category":"Building & Trades",
            "subcategory":"Construction",
            "type":"Services"
        }
    ],
    "sg:phone":"+1 519 743 4811",
    "sg:postcode":"N2G 3S5",
    "sg:province":"ON",
    "sg:tags":[
        "maker",
        "cabinet"
    ],
    "wof:name":"Henry Haiser Carpentry & Cabnt",
    "wof:placetype":"venue"
},
  "geometry": {"coordinates":[-80.4720916748,43.4417152405],"type":"Point"}
}