{
  "type": "Feature",
  "properties": {
    "addr:full":"62 Bridge St Saint John NB E2K 1S3",
    "addr:housenumber":"62",
    "addr:postcode":"e2k 1s3",
    "addr:street":"Bridge St",
    "iso:country":"CA",
    "sg:address":"62 Bridge St",
    "sg:city":"Saint John",
    "sg:classifiers":[
        {
            "category":"Building & Trades",
            "subcategory":"Construction",
            "type":"Services"
        }
    ],
    "sg:phone":"+1 506 633 0060",
    "sg:postcode":"E2K 1S3",
    "sg:province":"NB",
    "sg:tags":[
        "painter"
    ],
    "wof:name":"A J Mallette & Sons",
    "wof:placetype":"venue"
},
  "geometry": {"coordinates":[-66.087822,45.2743],"type":"Point"}
}