{
  "type": "Feature",
  "properties": {
    "addr:full":"601 3E Rue Chibougamau QC G8P 3A2",
    "addr:housenumber":"601",
    "addr:postcode":"g8p 3a2",
    "addr:street":"3E Rue",
    "iso:country":"CA",
    "sg:address":"601 3E Rue",
    "sg:city":"Chibougamau",
    "sg:classifiers":[
        {
            "category":"Education",
            "subcategory":"Library",
            "type":"Public Place"
        }
    ],
    "sg:phone":"+1 418 748 2497",
    "sg:postcode":"G8P 3A2",
    "sg:province":"QC",
    "wof:name":"Bibliotheque Municipale-Chibou",
    "wof:placetype":"venue"
},
  "geometry": {"coordinates":[-74.366226,49.913734],"type":"Point"}
}