{
  "type": "Feature",
  "properties": {
    "addr:full":"553 Baker St Nelson BC V1L 4J1",
    "addr:housenumber":"553",
    "addr:postcode":"bc v1l 4j1",
    "addr:street":"Baker St",
    "iso:country":"CA",
    "sg:address":"553 Baker St",
    "sg:city":"Nelson",
    "sg:classifiers":[
        {
            "category":"Shopping",
            "subcategory":"Shoes",
            "type":"Retail Goods"
        }
    ],
    "sg:phone":"+1 250 352 3034",
    "sg:postcode":"V1L 4J1",
    "sg:province":"BC",
    "wof:name":"Lyons Shoe Store Ltd",
    "wof:placetype":"venue"
},
  "geometry": {"coordinates":[-117.29336499999999,49.492374],"type":"Point"}
}