{
  "type": "Feature",
  "properties": {
    "iso:country":"CA",
    "sg:address":"307 Richmond Rd #A",
    "sg:city":"Ottawa",
    "sg:classifiers":[
        {
            "category":"Travel",
            "subcategory":"Travel Agent",
            "type":"Entertainment"
        }
    ],
    "sg:phone":"+1 613 789 1900",
    "sg:postcode":"K1Z 6X3",
    "sg:province":"ON",
    "sg:tags":[
        "agency",
        "bureau"
    ],
    "wof:name":"Trailfinders",
    "wof:placetype":"venue"
},
  "geometry": {"coordinates":[-75.7524108887,45.3929023743],"type":"Point"}
}