{
  "type": "Feature",
  "properties": {
    "addr:full":"7500 Ch DE LA Cote-DE-Liesse Saint-Laurent QC H4T 1E7",
    "addr:postcode":"7500;h4t 1e7",
    "addr:street":"Ch De La Cote-De-Liesse",
    "iso:country":"CA",
    "sg:address":"7500 Ch DE LA Cote-DE-Liesse",
    "sg:city":"Saint-Laurent",
    "sg:classifiers":[
        {
            "category":"Manufacturing",
            "subcategory":"Food",
            "type":"Manufacturing & Wholesale Goods"
        }
    ],
    "sg:phone":"+1 514 738 9999",
    "sg:postcode":"H4T 1E7",
    "sg:province":"QC",
    "sg:tags":[
        "brewer"
    ],
    "wof:name":"Canacermex",
    "wof:placetype":"venue"
},
  "geometry": {"coordinates":[-73.70034,45.478764],"type":"Point"}
}