{
  "type": "Feature",
  "properties": {
    "iso:country":"CA",
    "sg:address":"15 Boul Levesque E",
    "sg:city":"Laval",
    "sg:classifiers":[
        {
            "category":"Health Services",
            "subcategory":"Hospital",
            "type":"Services"
        }
    ],
    "sg:phone":"+1 450 668 1771",
    "sg:postcode":"H7G 1B3",
    "sg:province":"QC",
    "sg:tags":[
        "mental"
    ],
    "wof:name":"Centre D'Implication Libre",
    "wof:placetype":"venue"
},
  "geometry": {"coordinates":[-73.6819610596,45.5617828369],"type":"Point"}
}