{
  "type": "Feature",
  "properties": {
    "iso:country":"CA",
    "sg:address":"9820 93 Ave NW",
    "sg:city":"Edmonton",
    "sg:classifiers":[
        {
            "category":"Real Estate",
            "subcategory":"Architect",
            "type":"Services"
        }
    ],
    "sg:phone":"+1 780 413 1892",
    "sg:postcode":"T6E 2W1",
    "sg:province":"AB",
    "wof:name":"Faling, David",
    "wof:placetype":"venue"
},
  "geometry": {"coordinates":[-113.483627,53.528381],"type":"Point"}
}