{
  "type": "Feature",
  "properties": {
    "addr:full":"42 Av Lindsay Dorval QC H9P 2T8",
    "addr:postcode":"h9p 2t8",
    "addr:street":"42 Av Lindsay",
    "iso:country":"CA",
    "sg:address":"42 Av Lindsay",
    "sg:city":"Dorval",
    "sg:classifiers":[
        {
            "category":"Wholesale",
            "subcategory":"Electrical",
            "type":"Manufacturing & Wholesale Goods"
        }
    ],
    "sg:phone":"+1 514 633 1966",
    "sg:postcode":"H9P 2T8",
    "sg:province":"QC",
    "sg:tags":[
        "equipment",
        "electronic",
        "supply"
    ],
    "wof:name":"East Cliff Supply CO Ltd",
    "wof:placetype":"venue"
},
  "geometry": {"coordinates":[-73.7240447998,45.4554328918],"type":"Point"}
}