{
  "type": "Feature",
  "properties": {
    "addr:full":"120 Delvecchio Rd Campbell River BC V9W 2T5",
    "addr:housenumber":"120",
    "addr:postcode":"v9w 2t5",
    "addr:street":"Delvecchio Rd",
    "iso:country":"CA",
    "sg:address":"120 Delvecchio Rd",
    "sg:city":"Campbell River",
    "sg:classifiers":[
        {
            "category":"Personal",
            "subcategory":"Beauty Salon",
            "type":"Services"
        }
    ],
    "sg:phone":"+1 250 286 1986",
    "sg:postcode":"V9W 2T5",
    "sg:province":"BC",
    "wof:name":"Shane's Hair Studio",
    "wof:placetype":"venue"
},
  "geometry": {"coordinates":[-125.24331665,50.0053710938],"type":"Point"}
}