{
  "type": "Feature",
  "properties": {
    "addr:full":"45 Boul Pie-Xii Saint-Timothee QC J6S 6P5",
    "addr:housenumber":"45",
    "addr:postcode":"j6s 6p5",
    "addr:street":"Boul Pie-Xii Saint-Timothee",
    "iso:country":"CA",
    "sg:address":"45 Boul Pie-Xii",
    "sg:city":"Saint-Timothee",
    "sg:classifiers":[
        {
            "category":"Professional",
            "subcategory":"Business Services",
            "type":"Services"
        }
    ],
    "sg:phone":"+1 450 373 8818",
    "sg:postcode":"J6S 6P5",
    "sg:province":"QC",
    "sg:tags":[
        "arbitration",
        "notary"
    ],
    "wof:name":"Brunet, Normand",
    "wof:placetype":"venue"
},
  "geometry": {"coordinates":[-74.040604,45.289349],"type":"Point"}
}