{
  "type": "Feature",
  "properties": {
    "addr:full":"Baddeck NS B0E 1B0",
    "addr:postcode":"b0e 1b0",
    "iso:country":"CA",
    "sg:city":"Baddeck",
    "sg:classifiers":[
        {
            "category":"Sports & Exercise",
            "subcategory":"Golf",
            "type":"Entertainment"
        }
    ],
    "sg:phone":"+1 902 295 2174",
    "sg:postcode":"B0E 1B0",
    "sg:province":"NS",
    "sg:tags":[
        "course"
    ],
    "wof:name":"Baddeck Forks Golf Club",
    "wof:placetype":"venue"
},
  "geometry": {"coordinates":[-60.7521743774,46.1020812988],"type":"Point"}
}