{
  "type": "Feature",
  "properties": {
    "addr:full":"12550 72 St NW Edmonton AB T5B 1Y6",
    "addr:housenumber":"12550",
    "addr:postcode":"t5b 1y6",
    "addr:street":"72 St Nw",
    "iso:country":"CA",
    "sg:address":"12550 72 St NW",
    "sg:city":"Edmonton",
    "sg:classifiers":[
        {
            "category":"Organizations",
            "subcategory":"Religious Organization",
            "type":"Services"
        }
    ],
    "sg:phone":"+1 780 477 5048",
    "sg:postcode":"T5B 1Y6",
    "sg:province":"AB",
    "sg:tags":[
        "church"
    ],
    "wof:name":"Getsemani Christian Church",
    "wof:placetype":"venue"
},
  "geometry": {"coordinates":[-113.452323914,53.5823020935],"type":"Point"}
}