{
  "type": "Feature",
  "properties": {
    "addr:full":"797 County Rd 10 Omemee ON K0L 2W0",
    "addr:housenumber":"797;10",
    "addr:postcode":"k0l 2w0",
    "addr:street":"County Rd",
    "iso:country":"CA",
    "sg:address":"797 County Rd 10",
    "sg:city":"Omemee",
    "sg:classifiers":[
        {
            "category":"Travel",
            "subcategory":"Campground",
            "type":"Entertainment"
        }
    ],
    "sg:phone":"+1 705 799 5170",
    "sg:postcode":"K0L 2W0",
    "sg:province":"ON",
    "wof:name":"Ontario Emily Provincial Park",
    "wof:placetype":"venue"
},
  "geometry": {"coordinates":[-78.559074,44.299061],"type":"Point"}
}