{
  "type": "Feature",
  "properties": {
    "iso:country":"CA",
    "sg:city":"Winnipeg",
    "sg:classifiers":[
        {
            "category":"Social Services",
            "subcategory":"Child Care",
            "type":"Services"
        }
    ],
    "sg:phone":"+1 204 832 4707",
    "sg:postcode":"R2Y 0H7",
    "sg:province":"MB",
    "wof:name":"Voyageur in-School Program Inc",
    "wof:placetype":"venue"
},
  "geometry": {"coordinates":[-97.3005447388,49.8960609436],"type":"Point"}
}