{
  "type": "Feature",
  "properties": {
    "iso:country":"CA",
    "sg:address":"30 Titan Rd # 15",
    "sg:city":"Etobicoke",
    "sg:classifiers":[
        {
            "category":"Building & Trades",
            "subcategory":"Electrical",
            "type":"Services"
        }
    ],
    "sg:phone":"+1 416 252 4762",
    "sg:postcode":"M8Z 5Y2",
    "sg:province":"ON",
    "sg:tags":[
        "electric",
        "contractor"
    ],
    "wof:name":"Delta B Electric",
    "wof:placetype":"venue"
},
  "geometry": {"coordinates":[-79.52043151860001,43.6304397583],"type":"Point"}
}