{
  "type": "Feature",
  "properties": {
    "addr:full":"990 59th Ave W Vancouver BC V6P 1X9",
    "addr:housenumber":"990",
    "addr:postcode":"v6p 1x9",
    "addr:street":"59Th Ave W",
    "iso:country":"CA",
    "sg:address":"990 59th Ave W",
    "sg:city":"Vancouver",
    "sg:classifiers":[
        {
            "category":"Sports & Exercise",
            "subcategory":"Gym",
            "type":"Entertainment"
        }
    ],
    "sg:phone":"+1 604 257 8174",
    "sg:postcode":"V6P 1X9",
    "sg:province":"BC",
    "sg:tags":[
        "club",
        "health",
        "studio",
        "gymnasium",
        "government"
    ],
    "wof:name":"Marpole-Oakridge Fitness Ctr",
    "wof:placetype":"venue"
},
  "geometry": {"coordinates":[-123.128883,49.217014],"type":"Point"}
}