{
  "type": "Feature",
  "properties": {
    "iso:country":"CA",
    "sg:address":"2100 Boul Marcel-Laurin",
    "sg:city":"Saint-Laurent",
    "sg:classifiers":[
        {
            "category":"Shopping",
            "type":"Retail Goods"
        }
    ],
    "sg:phone":"+1 514 856 1884",
    "sg:postcode":"H4R 1J9",
    "sg:province":"QC",
    "sg:tags":[
        "telephone",
        "cellular"
    ],
    "wof:name":"Planete Mobile",
    "wof:placetype":"venue"
},
  "geometry": {"coordinates":[-73.702354,45.518814],"type":"Point"}
}