{
  "type": "Feature",
  "properties": {
    "addr:full":"Huntingdon QC J0S 1H0",
    "addr:postcode":"j0s 1h0",
    "iso:country":"CA",
    "sg:city":"Huntingdon",
    "sg:classifiers":[
        {
            "category":"Home & Garden",
            "subcategory":"Garden Supply",
            "type":"Retail Goods"
        }
    ],
    "sg:phone":"+1 450 264 3539",
    "sg:postcode":"J0S 1H0",
    "sg:province":"QC",
    "sg:tags":[
        "engine"
    ],
    "wof:name":"Mac's Chainsaw & Garden Equip",
    "wof:placetype":"venue"
},
  "geometry": {"coordinates":[-74.1692123413,45.0914611816],"type":"Point"}
}