{
  "type": "Feature",
  "properties": {
    "addr:full":"240 16 Ave NE Calgary AB T2E 1J8",
    "addr:postcode":"240;t2e 1j8",
    "addr:street":"16 Ave Ne",
    "iso:country":"CA",
    "sg:address":"240 16 Ave NE",
    "sg:city":"Calgary",
    "sg:classifiers":[
        {
            "category":"Restaurant",
            "type":"Food & Drink"
        }
    ],
    "sg:phone":"+1 403 230 8910",
    "sg:postcode":"T2E 1J8",
    "sg:province":"AB",
    "wof:name":"Mc Donald's",
    "wof:placetype":"venue"
},
  "geometry": {"coordinates":[-114.05843400000001,51.067101],"type":"Point"}
}