{
  "type": "Feature",
  "properties": {
    "iso:country":"CA",
    "sg:address":"4633 Lakelse Ave",
    "sg:city":"Terrace",
    "sg:classifiers":[
        {
            "category":"Banks & Credit Unions",
            "subcategory":"Bank",
            "type":"Services"
        }
    ],
    "sg:phone":"+1 250 635 8900",
    "sg:postcode":"V8G 1R3",
    "sg:province":"BC",
    "wof:name":"T D Bank Financial Group",
    "wof:placetype":"venue"
},
  "geometry": {"coordinates":[-128.589645386,54.5165672302],"type":"Point"}
}