{
  "type": "Feature",
  "properties": {
    "addr:full":"270 Rue Renaud O Laval QC H7M 3M1",
    "addr:housenumber":"270",
    "addr:postcode":"h7m 3m1",
    "addr:street":"Rue Renaud O",
    "iso:country":"CA",
    "sg:address":"270 Rue Renaud O",
    "sg:city":"Laval",
    "sg:classifiers":[
        {
            "category":"Recreation",
            "type":"Entertainment"
        }
    ],
    "sg:phone":"+1 450 668 3368",
    "sg:postcode":"H7M 3M1",
    "sg:province":"QC",
    "sg:tags":[
        "club",
        "bridge"
    ],
    "wof:name":"Ecole DE Bridge G Thibault",
    "wof:placetype":"venue"
},
  "geometry": {"coordinates":[-73.7129745483,45.5823059082],"type":"Point"}
}