{
  "type": "Feature",
  "properties": {
    "addr:full":"100 Turbine Dr North York ON M9L 2S2",
    "addr:housenumber":"100",
    "addr:postcode":"m9l 2s2",
    "addr:street":"Turbine Dr",
    "iso:country":"CA",
    "sg:address":"100 Turbine Dr",
    "sg:city":"North York",
    "sg:classifiers":[
        {
            "category":"Home & Garden",
            "subcategory":"Hardware",
            "type":"Retail Goods"
        }
    ],
    "sg:phone":"+1 416 741 6469",
    "sg:postcode":"M9L 2S2",
    "sg:province":"ON",
    "wof:name":"Sappa Distributors",
    "wof:placetype":"venue"
},
  "geometry": {"coordinates":[-79.55744934080001,43.7666664124],"type":"Point"}
}