{
  "type": "Feature",
  "properties": {
    "addr:full":"1944 Rue Sainte-Catherine O Montreal QC H3H 1M4",
    "addr:housenumber":"1944",
    "addr:postcode":"h3h 1m4",
    "addr:street":"Rue Sainte-Catherine O",
    "iso:country":"CA",
    "sg:address":"1944 Rue Sainte-Catherine O",
    "sg:city":"Montreal",
    "sg:classifiers":[
        {
            "category":"Bars & Pubs",
            "type":"Food & Drink"
        }
    ],
    "sg:phone":"+1 514 933 4556",
    "sg:postcode":"H3H 1M4",
    "sg:province":"QC",
    "wof:name":"Cock'n Bull Pub Ltd",
    "wof:placetype":"venue"
},
  "geometry": {"coordinates":[-73.55136899999999,45.523582],"type":"Point"}
}