{
  "type": "Feature",
  "properties": {
    "iso:country":"CA",
    "sg:address":"400 Lansdowne St E",
    "sg:city":"Peterborough",
    "sg:classifiers":[
        {
            "category":"Shopping",
            "subcategory":"Pharmacy",
            "type":"Retail Goods"
        }
    ],
    "sg:phone":"+1 705 740 0263",
    "sg:postcode":"K9J 6X9",
    "sg:province":"ON",
    "wof:name":"Drug Store Pharmacy",
    "wof:placetype":"venue"
},
  "geometry": {"coordinates":[-78.28889465330001,44.2925300598],"type":"Point"}
}