{
  "type": "Feature",
  "properties": {
    "addr:full":"160 King St S Waterloo ON N2J 1P6",
    "addr:housenumber":"160",
    "addr:postcode":"n2j 1p6",
    "addr:street":"King St S",
    "iso:country":"CA",
    "sg:address":"160 King St S",
    "sg:city":"Waterloo",
    "sg:classifiers":[
        {
            "category":"Health Services",
            "subcategory":"Doctor",
            "type":"Services"
        }
    ],
    "sg:phone":"+1 519 742 0531",
    "sg:postcode":"N2J 1P6",
    "sg:province":"ON",
    "sg:tags":[
        "dentist"
    ],
    "wof:name":"Burchell, Robert DDS",
    "wof:placetype":"venue"
},
  "geometry": {"coordinates":[-80.520584,43.461208],"type":"Point"}
}