{
  "type": "Feature",
  "properties": {
    "addr:full":"7251 Sierra Morena Blvd SW Calgary AB T3H 3N5",
    "addr:housenumber":"7251",
    "addr:postcode":"t3h 3n5",
    "addr:street":"Sierra Morena Blvd Sw",
    "iso:country":"CA",
    "sg:address":"7251 Sierra Morena Blvd SW",
    "sg:city":"Calgary",
    "sg:classifiers":[
        {
            "category":"Organizations",
            "subcategory":"Religious Organization",
            "type":"Services"
        }
    ],
    "sg:phone":"+1 403 242 1256",
    "sg:postcode":"T3H 3N5",
    "sg:province":"AB",
    "sg:tags":[
        "church"
    ],
    "wof:name":"Richmond Hill Baptist Church",
    "wof:placetype":"venue"
},
  "geometry": {"coordinates":[-114.176139831,51.013507843],"type":"Point"}
}