{
  "type": "Feature",
  "properties": {
    "addr:full":"Courtenay BC V9N 7S7",
    "addr:postcode":"v9n 7s7",
    "iso:country":"CA",
    "sg:city":"Courtenay",
    "sg:classifiers":[
        {
            "category":"Retail",
            "subcategory":"Auto Repair",
            "type":"Services"
        }
    ],
    "sg:phone":"+1 250 338 4379",
    "sg:postcode":"V9N 7S7",
    "sg:province":"BC",
    "sg:tags":[
        "exchanging",
        "machine",
        "shop"
    ],
    "wof:name":"Adm Machine Shop",
    "wof:placetype":"venue"
},
  "geometry": {"coordinates":[-124.981255,49.668842],"type":"Point"}
}