{
  "type": "Feature",
  "properties": {
    "iso:country":"CA",
    "sg:city":"Spruce Grove",
    "sg:classifiers":[
        {
            "category":"Personal",
            "subcategory":"Beauty Salon",
            "type":"Services"
        }
    ],
    "sg:phone":"+1 780 962 6663",
    "sg:postcode":"T7X 2K5",
    "sg:province":"AB",
    "wof:name":"Final Touch Hair Design",
    "wof:placetype":"venue"
},
  "geometry": {"coordinates":[-113.905067444,53.5421943665],"type":"Point"}
}