{
  "type": "Feature",
  "properties": {
    "addr:full":"Calgary AB T2Y 3S5",
    "addr:postcode":"t2y 3s5",
    "iso:country":"CA",
    "sg:city":"Calgary",
    "sg:classifiers":[
        {
            "category":"Health Services",
            "subcategory":"Doctor",
            "type":"Services"
        }
    ],
    "sg:phone":"+1 403 201 2483",
    "sg:postcode":"T2Y 3S5",
    "sg:province":"AB",
    "sg:tags":[
        "dentist"
    ],
    "wof:name":"Bite Dental Works",
    "wof:placetype":"venue"
},
  "geometry": {"coordinates":[-114.06420135499999,50.9076042175],"type":"Point"}
}