{
  "type": "Feature",
  "properties": {
    "addr:full":"46252 Yale Rd Chilliwack BC V2P 2P3",
    "addr:housenumber":"46252",
    "addr:postcode":"v2p 2p3",
    "addr:street":"Yale Rd",
    "iso:country":"CA",
    "sg:address":"46252 Yale Rd",
    "sg:city":"Chilliwack",
    "sg:classifiers":[
        {
            "category":"Autos & Motor Vehicles",
            "subcategory":"Motorcycle Sales",
            "type":"Retail Goods"
        }
    ],
    "sg:phone":"+1 604 792 9696",
    "sg:postcode":"V2P 2P3",
    "sg:province":"BC",
    "sg:tags":[
        "scooter"
    ],
    "wof:name":"Son's of Thunder Motorcycle",
    "wof:placetype":"venue"
},
  "geometry": {"coordinates":[-121.948982239,49.1719322205],"type":"Point"}
}