{
  "type": "Feature",
  "properties": {
    "addr:full":"4544 Dufferin St North York ON M3H 5X2",
    "addr:housenumber":"4544",
    "addr:postcode":"m3h 5x2",
    "addr:street":"Dufferin St",
    "iso:country":"CA",
    "sg:address":"4544 Dufferin St",
    "sg:city":"North York",
    "sg:classifiers":[
        {
            "category":"Professional",
            "subcategory":"Management & Consulting",
            "type":"Services"
        }
    ],
    "sg:phone":"+1 416 665 6999",
    "sg:postcode":"M3H 5X2",
    "sg:province":"ON",
    "sg:tags":[
        "consultant",
        "telecommunication"
    ],
    "wof:name":"Ipsmarx Technology Inc",
    "wof:placetype":"venue"
},
  "geometry": {"coordinates":[-79.4670181274,43.7684822083],"type":"Point"}
}