{
  "type": "Feature",
  "properties": {
    "addr:full":"Vancouver BC V6B 2L3",
    "addr:postcode":"v6b 2l3",
    "iso:country":"CA",
    "sg:city":"Vancouver",
    "sg:classifiers":[
        {
            "category":"Arts & Performance",
            "subcategory":"Theater",
            "type":"Entertainment"
        }
    ],
    "sg:phone":"+1 604 681 6060",
    "sg:postcode":"V6B 2L3",
    "sg:province":"BC",
    "sg:tags":[
        "band",
        "orchestra"
    ],
    "wof:name":"Dal Richards Orchestra",
    "wof:placetype":"venue"
},
  "geometry": {"coordinates":[-123.10942840600001,49.2805213928],"type":"Point"}
}