{
  "type": "Feature",
  "properties": {
    "addr:full":"5435 Cogswell St Halifax NS B3J 1R1",
    "addr:housenumber":"5435",
    "addr:postcode":"ns b3j 1r1",
    "addr:street":"Cogswell St",
    "iso:country":"CA",
    "sg:address":"5435 Cogswell St",
    "sg:city":"Halifax",
    "sg:classifiers":[
        {
            "category":"Organizations",
            "subcategory":"Religious Organization",
            "type":"Services"
        }
    ],
    "sg:phone":"+1 902 423 7077",
    "sg:postcode":"B3J 1R1",
    "sg:province":"NS",
    "sg:tags":[
        "church"
    ],
    "wof:name":"Trinity Church",
    "wof:placetype":"venue"
},
  "geometry": {"coordinates":[-63.5804023743,44.6508598328],"type":"Point"}
}