{
  "type": "Feature",
  "properties": {
    "addr:full":"904 Colborne St Brantford ON N3S 3T4",
    "addr:housenumber":"904",
    "addr:postcode":"n3s 3t4",
    "addr:street":"Colborne St",
    "iso:country":"CA",
    "sg:address":"904 Colborne St",
    "sg:city":"Brantford",
    "sg:classifiers":[
        {
            "category":"Retail",
            "subcategory":"Veterinary Services",
            "type":"Services"
        }
    ],
    "sg:phone":"+1 519 752 3431",
    "sg:postcode":"N3S 3T4",
    "sg:province":"ON",
    "sg:tags":[
        "veterinarian"
    ],
    "wof:name":"Mantle, Lorna DVM",
    "wof:placetype":"venue"
},
  "geometry": {"coordinates":[-80.2174072266,43.14453125],"type":"Point"}
}