{
  "type": "Feature",
  "properties": {
    "addr:full":"803 St Clair Ave W Toronto ON M6C 1B9",
    "addr:housenumber":"803",
    "addr:postcode":"m6c 1b9",
    "addr:street":"St Clair Ave W",
    "iso:country":"CA",
    "sg:address":"803 St Clair Ave W",
    "sg:city":"Toronto",
    "sg:classifiers":[
        {
            "category":"Government",
            "subcategory":"Office",
            "type":"Public Place"
        }
    ],
    "sg:phone":"+1 416 656 0943",
    "sg:postcode":"M6C 1B9",
    "sg:province":"ON",
    "wof:name":"Ontario Provincial Parliament",
    "wof:placetype":"venue"
},
  "geometry": {"coordinates":[-79.4303817749,43.6806030273],"type":"Point"}
}