{
  "type": "Feature",
  "properties": {
    "addr:full":"1191 Av Cartier Quebec QC G1R 2S9",
    "addr:housenumber":"1191",
    "addr:postcode":"g1r 2s9",
    "addr:street":"Av Cartier",
    "iso:country":"CA",
    "sg:address":"1191 Av Cartier",
    "sg:city":"Quebec",
    "sg:classifiers":[
        {
            "category":"Health Services",
            "subcategory":"Health Practitioner",
            "type":"Services"
        }
    ],
    "sg:phone":"+1 418 522 1911",
    "sg:postcode":"G1R 2S9",
    "sg:province":"QC",
    "sg:tags":[
        "dietitian"
    ],
    "wof:name":"Girard, Christiane",
    "wof:placetype":"venue"
},
  "geometry": {"coordinates":[-71.22453308110001,46.8027229309],"type":"Point"}
}