{
  "type": "Feature",
  "properties": {
    "addr:full":"2740 Slough St Mississauga ON L4T 1G3",
    "addr:housenumber":"2740",
    "addr:postcode":"l4t 1g3",
    "addr:street":"Slough St",
    "iso:country":"CA",
    "sg:address":"2740 Slough St",
    "sg:city":"Mississauga",
    "sg:classifiers":[
        {
            "category":"Freight",
            "type":"Transportation"
        }
    ],
    "sg:phone":"+1 905 612 9992",
    "sg:postcode":"L4T 1G3",
    "sg:province":"ON",
    "sg:tags":[
        "cartage"
    ],
    "wof:name":"Cam Cartage Inc",
    "wof:placetype":"venue"
},
  "geometry": {"coordinates":[-79.65986599999999,43.709267],"type":"Point"}
}