{
  "type": "Feature",
  "properties": {
    "addr:full":"74 1st St S Souris MB R0K 2C0",
    "addr:housenumber":"74",
    "addr:postcode":"r0k 2c0",
    "addr:street":"1St St S",
    "iso:country":"CA",
    "sg:address":"74 1st St S",
    "sg:city":"Souris",
    "sg:classifiers":[
        {
            "category":"Organizations",
            "subcategory":"Community Association",
            "type":"Services"
        }
    ],
    "sg:phone":"+1 204 483 2659",
    "sg:postcode":"R0K 2C0",
    "sg:province":"MB",
    "sg:tags":[
        "club"
    ],
    "wof:name":"Royal Canadian Legion",
    "wof:placetype":"venue"
},
  "geometry": {"coordinates":[-100.258865356,49.6208343506],"type":"Point"}
}