{
  "type": "Feature",
  "properties": {
    "iso:country":"CA",
    "sg:address":"135 Antibes Dr",
    "sg:city":"North York",
    "sg:classifiers":[
        {
            "category":"Real Estate",
            "subcategory":"Real Estate Operator",
            "type":"Services"
        }
    ],
    "sg:phone":"+1 416 665 7154",
    "sg:postcode":"M2R 2Z1",
    "sg:province":"ON",
    "sg:tags":[
        "condominium"
    ],
    "wof:name":"York Condominium Corp",
    "wof:placetype":"venue"
},
  "geometry": {"coordinates":[-79.446083,43.780441],"type":"Point"}
}