{
  "type": "Feature",
  "properties": {
    "addr:full":"525 Rue Jean-Talon O Montreal QC H3N 1R6",
    "addr:housenumber":"525",
    "addr:postcode":"h3n 1r6",
    "addr:street":"Rue Jean-Talon O",
    "iso:country":"CA",
    "sg:address":"525 Rue Jean-Talon O",
    "sg:city":"Montreal",
    "sg:classifiers":[
        {
            "category":"Shopping",
            "subcategory":"Discount & Variety Stores",
            "type":"Retail Goods"
        }
    ],
    "sg:phone":"+1 514 274 7885",
    "sg:postcode":"H3N 1R6",
    "sg:province":"QC",
    "wof:name":"Dollartheque",
    "wof:placetype":"venue"
},
  "geometry": {"coordinates":[-73.61385300000001,45.539379],"type":"Point"}
}