{
  "type": "Feature",
  "properties": {
    "iso:country":"CA",
    "sg:city":"Westwold",
    "sg:classifiers":[
        {
            "category":"Education",
            "subcategory":"School",
            "type":"Public Place"
        }
    ],
    "sg:phone":"+1 250 375 2252",
    "sg:postcode":"V0E 3B0",
    "sg:province":"BC",
    "wof:name":"Westwold Elementary School",
    "wof:placetype":"venue"
},
  "geometry": {"coordinates":[-119.73866271999999,50.4658966064],"type":"Point"}
}