{
  "type": "Feature",
  "properties": {
    "addr:full":"520 McCaffrey St. St-Laurent Quebec H4T 1N1",
    "addr:housenumber":"520",
    "addr:postcode":"h4t 1n1",
    "addr:street":"Mccaffrey St.",
    "iso:country":"CA",
    "sg:address":"520 McCaffrey St. St-Laurent",
    "sg:city":"Quebec",
    "sg:classifiers":[
        {
            "category":"Professional",
            "subcategory":"Computer Services",
            "type":"Services"
        }
    ],
    "sg:postcode":"H4T 1N1",
    "sg:website":"http://www.lxsix.com",
    "wof:name":"LxDATA",
    "wof:placetype":"venue"
},
  "geometry": {"coordinates":[-73.7108027,45.48712],"type":"Point"}
}