{
  "type": "Feature",
  "properties": {
    "iso:country":"CA",
    "sg:address":"11 Rue Roussel",
    "sg:city":"Saint-Quentin",
    "sg:classifiers":[
        {
            "category":"Organizations",
            "subcategory":"Religious Organization",
            "type":"Services"
        }
    ],
    "sg:phone":"+1 506 235 2284",
    "sg:postcode":"E8A 1Z7",
    "sg:province":"NB",
    "wof:name":"Centre Foi & Interiorite",
    "wof:placetype":"venue"
},
  "geometry": {"coordinates":[-67.3898010254,47.5157661438],"type":"Point"}
}