{
  "type": "Feature",
  "properties": {
    "iso:country":"CA",
    "sg:address":"45 Shirley Blvd",
    "sg:city":"Nepean",
    "sg:classifiers":[
        {
            "category":"Organizations",
            "subcategory":"Professional Association",
            "type":"Services"
        }
    ],
    "sg:phone":"+1 613 829 8281",
    "sg:postcode":"K2K 2W6",
    "sg:province":"ON",
    "wof:name":"Dominion of Canada Rifle Assn",
    "wof:placetype":"venue"
},
  "geometry": {"coordinates":[-75.881149,45.365417],"type":"Point"}
}