{
  "type": "Feature",
  "properties": {
    "iso:country":"CA",
    "sg:address":"948 Old Glass Rd",
    "sg:city":"Wallaceburg",
    "sg:classifiers":[
        {
            "category":"Wholesale",
            "subcategory":"Machinery & Supplies",
            "type":"Manufacturing & Wholesale Goods"
        }
    ],
    "sg:phone":"+1 519 627 5419",
    "sg:postcode":"N8A 3S8",
    "sg:province":"ON",
    "sg:tags":[
        "equipment",
        "material",
        "handling"
    ],
    "wof:name":"Ogie's Lift Truck Svc",
    "wof:placetype":"venue"
},
  "geometry": {"coordinates":[-82.3964309692,42.5837020874],"type":"Point"}
}