{
  "type": "Feature",
  "properties": {
    "iso:country":"CA",
    "sg:address":"1004 Rue Notre-Dame",
    "sg:city":"Repentigny",
    "sg:classifiers":[
        {
            "category":"Manufacturing",
            "subcategory":"Printing",
            "type":"Manufacturing & Wholesale Goods"
        }
    ],
    "sg:phone":"+1 450 581 5120",
    "sg:postcode":"J5Y 1S9",
    "sg:province":"QC",
    "sg:tags":[
        "publisher"
    ],
    "wof:name":"Hebdos Transcontinental",
    "wof:placetype":"venue"
},
  "geometry": {"coordinates":[-73.41143035890001,45.774066925],"type":"Point"}
}