{
  "type": "Feature",
  "properties": {
    "iso:country":"CA",
    "sg:address":"1 Whitmore Rd # 6",
    "sg:city":"Woodbridge",
    "sg:classifiers":[
        {
            "category":"Manufacturing",
            "subcategory":"Food",
            "type":"Manufacturing & Wholesale Goods"
        }
    ],
    "sg:phone":"+1 905 850 0007",
    "sg:postcode":"L4L 8G4",
    "sg:province":"ON",
    "sg:tags":[
        "product",
        "dairy",
        "manufacturer"
    ],
    "wof:name":"Gelati Deluxe Ltd",
    "wof:placetype":"venue"
},
  "geometry": {"coordinates":[-79.55418396,43.7818412781],"type":"Point"}
}