{
  "type": "Feature",
  "properties": {
    "addr:full":"PO Box 1317 STN Main Okotoks AB T1S 1B3",
    "addr:housenumber":"po",
    "addr:postcode":"t1s 1b3",
    "addr:street":"Box 1317 Stn Main Okotoks Ab",
    "iso:country":"CA",
    "sg:address":"PO Box 1317 STN Main",
    "sg:city":"Okotoks",
    "sg:classifiers":[
        {
            "category":"Manufacturing",
            "subcategory":"Buildings",
            "type":"Manufacturing & Wholesale Goods"
        }
    ],
    "sg:phone":"+1 403 938 3715",
    "sg:postcode":"T1S 1B3",
    "sg:province":"AB",
    "sg:tags":[
        "home",
        "log",
        "cabin"
    ],
    "wof:name":"Crazy Creek Timber Frames",
    "wof:placetype":"venue"
},
  "geometry": {"coordinates":[-113.974937439,50.7258911133],"type":"Point"}
}