{
  "type": "Feature",
  "properties": {
    "iso:country":"CA",
    "sg:address":"8528 Granville St",
    "sg:city":"Vancouver",
    "sg:classifiers":[
        {
            "category":"Professional",
            "subcategory":"Business Services",
            "type":"Services"
        }
    ],
    "sg:phone":"+1 604 266 8970",
    "sg:postcode":"V6P 4Z7",
    "sg:province":"BC",
    "sg:tags":[
        "notary"
    ],
    "wof:name":"Maguire & CO",
    "wof:placetype":"venue"
},
  "geometry": {"coordinates":[-123.140319824,49.2091369629],"type":"Point"}
}