{
  "type": "Feature",
  "properties": {
    "addr:full":"154 Thom St Owen Sound ON N4K 5N7",
    "addr:housenumber":"154",
    "addr:postcode":"n4k 5n7",
    "addr:street":"Thom St",
    "iso:country":"CA",
    "sg:address":"154 Thom St",
    "sg:city":"Owen Sound",
    "sg:classifiers":[
        {
            "category":"Manufacturing",
            "subcategory":"Tools & Machinery",
            "type":"Manufacturing & Wholesale Goods"
        }
    ],
    "sg:phone":"+1 519 376 0283",
    "sg:postcode":"N4K 5N7",
    "sg:province":"ON",
    "sg:tags":[
        "equipment",
        "product",
        "industrial",
        "manufacturer",
        "supply"
    ],
    "wof:name":"Scott's Industrial & Farm Supl",
    "wof:placetype":"venue"
},
  "geometry": {"coordinates":[-80.942604,44.564877],"type":"Point"}
}