{
  "type": "Feature",
  "properties": {
    "addr:full":"425 21A St N Lethbridge AB T1H 6L6",
    "addr:housenumber":"425 21a",
    "addr:postcode":"t1h 6l6",
    "addr:street":"St N",
    "iso:country":"CA",
    "sg:address":"425 21A St N",
    "sg:city":"Lethbridge",
    "sg:classifiers":[
        {
            "category":"Bars & Pubs",
            "type":"Food & Drink"
        }
    ],
    "sg:phone":"+1 403 328 0066",
    "sg:postcode":"T1H 6L6",
    "sg:province":"AB",
    "wof:name":"Bo Diddly's Pub & Grill",
    "wof:placetype":"venue"
},
  "geometry": {"coordinates":[-112.81053900000001,49.704533],"type":"Point"}
}