{
  "type": "Feature",
  "properties": {
    "addr:full":"477 Boul Dr Albiny-Paquette Mont-Laurier QC J9L 1K8",
    "addr:housenumber":"477",
    "addr:postcode":"j9l 1k8",
    "addr:street":"Boul Dr Albiny-Paquette",
    "iso:country":"CA",
    "sg:address":"477 Boul Dr Albiny-Paquette",
    "sg:city":"Mont-Laurier",
    "sg:classifiers":[
        {
            "category":"Shopping",
            "subcategory":"Florist",
            "type":"Retail Goods"
        }
    ],
    "sg:phone":"+1 819 623 2796",
    "sg:postcode":"J9L 1K8",
    "sg:province":"QC",
    "wof:name":"Mont-Laurier Fleuriste Enr",
    "wof:placetype":"venue"
},
  "geometry": {"coordinates":[-75.49773399999999,46.550011],"type":"Point"}
}