{
  "type": "Feature",
  "properties": {
    "iso:country":"CA",
    "sg:city":"Burlington",
    "sg:classifiers":[
        {
            "category":"Building & Trades",
            "subcategory":"Construction",
            "type":"Services"
        }
    ],
    "sg:phone":"+1 905 333 2895",
    "sg:postcode":"L7N 3P5",
    "sg:province":"ON",
    "sg:tags":[
        "contractor"
    ],
    "wof:name":"Passport Homes Ltd",
    "wof:placetype":"venue"
},
  "geometry": {"coordinates":[-79.78347,43.338245],"type":"Point"}
}