{
  "type": "Feature",
  "properties": {
    "addr:full":"27 Lauderdale Dr North York ON M2L 2A8",
    "addr:housenumber":"27",
    "addr:postcode":"m2l 2a8",
    "addr:street":"Lauderdale Dr",
    "iso:country":"CA",
    "sg:address":"27 Lauderdale Dr",
    "sg:city":"North York",
    "sg:classifiers":[
        {
            "category":"Wholesale",
            "subcategory":"Non-durable Goods",
            "type":"Manufacturing & Wholesale Goods"
        }
    ],
    "sg:phone":"+1 416 385 2427",
    "sg:postcode":"M2L 2A8",
    "sg:province":"ON",
    "sg:tags":[
        "material",
        "artist"
    ],
    "wof:name":"Mapac Canada Ltd",
    "wof:placetype":"venue"
},
  "geometry": {"coordinates":[-79.379242,43.754539],"type":"Point"}
}