{
  "type": "Feature",
  "properties": {
    "addr:full":"606 Berford St Wiarton ON N0H 2T0",
    "addr:housenumber":"606",
    "addr:postcode":"n0h 2t0",
    "addr:street":"Berford St",
    "iso:country":"CA",
    "sg:address":"606 Berford St",
    "sg:city":"Wiarton",
    "sg:classifiers":[
        {
            "category":"Shopping",
            "subcategory":"Clothing, Apparel, & Fashions",
            "type":"Retail Goods"
        }
    ],
    "sg:phone":"+1 519 534 5129",
    "sg:postcode":"N0H 2T0",
    "sg:province":"ON",
    "wof:name":"Northern Images",
    "wof:placetype":"venue"
},
  "geometry": {"coordinates":[-81.14108299999999,44.743275],"type":"Point"}
}