{
  "type": "Feature",
  "properties": {
    "iso:country":"CA",
    "sg:address":"510 Airlies St",
    "sg:city":"Winnipeg",
    "sg:classifiers":[
        {
            "category":"Personal",
            "subcategory":"Barber",
            "type":"Services"
        }
    ],
    "sg:phone":"+1 204 582 6073",
    "sg:postcode":"R2X 2B2",
    "sg:province":"MB",
    "wof:name":"Linda & Chris's Barber Shop",
    "wof:placetype":"venue"
},
  "geometry": {"coordinates":[-97.1557006836,49.9328765869],"type":"Point"}
}