{
  "type": "Feature",
  "properties": {
    "addr:full":"10350 144 Ave Grande Prairie AB T8V 7J9",
    "addr:housenumber":"10350",
    "addr:postcode":"t8v 7j9",
    "addr:street":"144 Ave",
    "iso:country":"CA",
    "sg:address":"10350 144 Ave",
    "sg:city":"Grande Prairie",
    "sg:classifiers":[
        {
            "category":"Manufacturing",
            "subcategory":"Metals",
            "type":"Manufacturing & Wholesale Goods"
        }
    ],
    "sg:phone":"+1 780 532 5278",
    "sg:postcode":"T8V 7J9",
    "sg:province":"AB",
    "sg:tags":[
        "coating"
    ],
    "wof:name":"Blastaway Enterprises Ltd",
    "wof:placetype":"venue"
},
  "geometry": {"coordinates":[-118.802864075,55.211605072],"type":"Point"}
}