{
  "type": "Feature",
  "properties": {
    "addr:full":"32786 Lougheed Hwy Mission BC V2V 1A7",
    "addr:housenumber":"32786",
    "addr:postcode":"v2v 1a7",
    "addr:street":"Lougheed Hwy",
    "iso:country":"CA",
    "sg:address":"32786 Lougheed Hwy",
    "sg:city":"Mission",
    "sg:classifiers":[
        {
            "category":"Restaurant",
            "type":"Food & Drink"
        }
    ],
    "sg:phone":"+1 604 826 7612",
    "sg:postcode":"V2V 1A7",
    "sg:province":"BC",
    "wof:name":"Rocko's Family Diner",
    "wof:placetype":"venue"
},
  "geometry": {"coordinates":[-122.31682586700001,49.1328735352],"type":"Point"}
}