{
  "type": "Feature",
  "properties": {
    "addr:full":"Calgary AB T2S 2S7",
    "addr:postcode":"t2s 2s7",
    "iso:country":"CA",
    "sg:city":"Calgary",
    "sg:classifiers":[
        {
            "category":"Building & Trades",
            "subcategory":"Equipment Rental",
            "type":"Services"
        }
    ],
    "sg:phone":"+1 403 255 5508",
    "sg:postcode":"T2S 2S7",
    "sg:province":"AB",
    "sg:tags":[
        "financing",
        "leasing"
    ],
    "wof:name":"First Capital Leasing Ltd",
    "wof:placetype":"venue"
},
  "geometry": {"coordinates":[-114.07164,51.032356],"type":"Point"}
}