{
  "type": "Feature",
  "properties": {
    "iso:country":"CA",
    "sg:address":"308 Wallace St",
    "sg:city":"Hope",
    "sg:classifiers":[
        {
            "category":"Shopping",
            "subcategory":"Pharmacy",
            "type":"Retail Goods"
        }
    ],
    "sg:phone":"+1 604 869 5654",
    "sg:postcode":"V0X 1L0",
    "sg:province":"BC",
    "wof:name":"Toy's Pharmacy",
    "wof:placetype":"venue"
},
  "geometry": {"coordinates":[-121.441184998,49.3795166016],"type":"Point"}
}