{
  "type": "Feature",
  "properties": {
    "addr:full":"Saint-Agapit QC G0S 1Z0",
    "addr:postcode":"g0s 1z0",
    "iso:country":"CA",
    "sg:city":"Saint-Agapit",
    "sg:classifiers":[
        {
            "category":"Government",
            "subcategory":"Office",
            "type":"Public Place"
        }
    ],
    "sg:phone":"+1 418 888 9811",
    "sg:postcode":"G0S 1Z0",
    "sg:province":"QC",
    "sg:tags":[
        "amusement",
        "village"
    ],
    "wof:name":"Centre Culturel",
    "wof:placetype":"venue"
},
  "geometry": {"coordinates":[-71.43723300000001,46.562954],"type":"Point"}
}