{
  "type": "Feature",
  "properties": {
    "addr:full":"14140 Riverside Dr E Windsor ON N8N 1B6",
    "addr:housenumber":"14140",
    "addr:postcode":"n8n 1b6",
    "addr:street":"Riverside Dr E",
    "iso:country":"CA",
    "sg:address":"14140 Riverside Dr E",
    "sg:city":"Windsor",
    "sg:classifiers":[
        {
            "category":"Professional",
            "subcategory":"Engineering",
            "type":"Services"
        }
    ],
    "sg:phone":"+1 519 979 8336",
    "sg:postcode":"N8N 1B6",
    "sg:province":"ON",
    "sg:tags":[
        "consultant",
        "management",
        "business"
    ],
    "wof:name":"Mind Quest Inc",
    "wof:placetype":"venue"
},
  "geometry": {"coordinates":[-82.895996,42.332741],"type":"Point"}
}