{
  "type": "Feature",
  "properties": {
    "addr:full":"590 Moray St Winnipeg MB R3J 3V9",
    "addr:housenumber":"590",
    "addr:postcode":"r3j 3v9",
    "addr:street":"Moray St",
    "iso:country":"CA",
    "sg:address":"590 Moray St",
    "sg:city":"Winnipeg",
    "sg:classifiers":[
        {
            "category":"Shopping",
            "subcategory":"Clothing, Apparel, & Fashions",
            "type":"Retail Goods"
        }
    ],
    "sg:phone":"+1 204 885 4200",
    "sg:postcode":"R3J 3V9",
    "sg:province":"MB",
    "wof:name":"Warehouse One Ltd",
    "wof:placetype":"venue"
},
  "geometry": {"coordinates":[-97.2621307373,49.8887557983],"type":"Point"}
}