{
  "type": "Feature",
  "properties": {
    "addr:full":"2240 All Saints Cres Oakville ON L6J 5N2",
    "addr:housenumber":"2240",
    "addr:postcode":"l6j 5n2",
    "addr:street":"All Saints Cres",
    "iso:country":"CA",
    "sg:address":"2240 All Saints Cres",
    "sg:city":"Oakville",
    "sg:classifiers":[
        {
            "category":"Professional",
            "subcategory":"Computer Services",
            "type":"Services"
        }
    ],
    "sg:phone":"+1 905 827 1001",
    "sg:postcode":"L6J 5N2",
    "sg:province":"ON",
    "sg:tags":[
        "consultant"
    ],
    "wof:name":"Swansea Computer Specialists",
    "wof:placetype":"venue"
},
  "geometry": {"coordinates":[-79.638031,43.474571],"type":"Point"}
}