{
  "type": "Feature",
  "properties": {
    "addr:full":"1976 Yonge St Toronto ON M4S 1Z7",
    "addr:housenumber":"1976",
    "addr:postcode":"m4s 1z7",
    "addr:street":"Yonge St",
    "iso:country":"CA",
    "sg:address":"1976 Yonge St",
    "sg:city":"Toronto",
    "sg:classifiers":[
        {
            "category":"Retail",
            "subcategory":"Auto Rental",
            "type":"Services"
        }
    ],
    "sg:phone":"+1 416 288 0682",
    "sg:postcode":"M4S 1Z7",
    "sg:province":"ON",
    "sg:tags":[
        "renting",
        "automobile",
        "leasing",
        "truck"
    ],
    "wof:name":"Somerville National Leasing",
    "wof:placetype":"venue"
},
  "geometry": {"coordinates":[-79.397133,43.699905],"type":"Point"}
}