{
  "type": "Feature",
  "properties": {
    "addr:full":"214 Burns St Atikokan ON P0T 1C0",
    "addr:housenumber":"214",
    "addr:postcode":"p0t 1c0",
    "addr:street":"Burns St",
    "iso:country":"CA",
    "sg:address":"214 Burns St",
    "sg:city":"Atikokan",
    "sg:classifiers":[
        {
            "category":"Restaurant",
            "type":"Food & Drink"
        }
    ],
    "sg:phone":"+1 807 597 4640",
    "sg:postcode":"P0T 1C0",
    "sg:province":"ON",
    "sg:tags":[
        "club",
        "night"
    ],
    "wof:name":"Nite Club Tavern",
    "wof:placetype":"venue"
},
  "geometry": {"coordinates":[-91.6205291748,48.7576675415],"type":"Point"}
}