{
  "type": "Feature",
  "properties": {
    "iso:country":"CA",
    "sg:address":"5130 Rue Saint-Hubert",
    "sg:city":"Montreal",
    "sg:classifiers":[
        {
            "category":"Professional",
            "subcategory":"Lawyer & Legal Services",
            "type":"Services"
        }
    ],
    "sg:phone":"+1 514 277 0110",
    "sg:postcode":"H2J 2Y3",
    "sg:province":"QC",
    "sg:tags":[
        "attorney"
    ],
    "wof:name":"Burnelle, Pierre",
    "wof:placetype":"venue"
},
  "geometry": {"coordinates":[-73.58837127690001,45.5290908813],"type":"Point"}
}