{
  "type": "Feature",
  "properties": {
    "iso:country":"CA",
    "sg:address":"35 Blackmarsh Rd",
    "sg:city":"St. John's",
    "sg:classifiers":[
        {
            "category":"Professional",
            "subcategory":"Management & Consulting",
            "type":"Services"
        }
    ],
    "sg:phone":"+1 709 758 5590",
    "sg:postcode":"A1E 1S4",
    "sg:province":"NL",
    "sg:tags":[
        "consultant",
        "business"
    ],
    "wof:name":"Jenkins Anthony Inc",
    "wof:placetype":"venue"
},
  "geometry": {"coordinates":[-52.728462,47.552856],"type":"Point"}
}