{
  "type": "Feature",
  "properties": {
    "addr:full":"235 Simcoe St S Oshawa ON L1H 4H3",
    "addr:housenumber":"235",
    "addr:postcode":"l1h 4h3",
    "addr:street":"Simcoe St S",
    "iso:country":"CA",
    "sg:address":"235 Simcoe St S",
    "sg:city":"Oshawa",
    "sg:classifiers":[
        {
            "category":"Restaurant",
            "type":"Food & Drink"
        }
    ],
    "sg:phone":"+1 905 576 9693",
    "sg:postcode":"L1H 4H3",
    "sg:province":"ON",
    "sg:tags":[
        "parlor",
        "ice",
        "cream"
    ],
    "wof:name":"Dairy Queen",
    "wof:placetype":"venue"
},
  "geometry": {"coordinates":[-78.86060333250001,43.8914375305],"type":"Point"}
}