{
  "type": "Feature",
  "properties": {
    "addr:full":"3476 Dutch Village Rd Halifax NS B3N 2R9",
    "addr:housenumber":"3476",
    "addr:postcode":"b3n 2r9",
    "addr:street":"Dutch Village Rd",
    "iso:country":"CA",
    "sg:address":"3476 Dutch Village Rd",
    "sg:city":"Halifax",
    "sg:classifiers":[
        {
            "category":"Real Estate",
            "subcategory":"Real Estate Agent",
            "type":"Services"
        }
    ],
    "sg:phone":"+1 902 456 0256",
    "sg:postcode":"B3N 2R9",
    "sg:province":"NS",
    "wof:name":"Bancroft, Colin",
    "wof:placetype":"venue"
},
  "geometry": {"coordinates":[-63.6322517395,44.6550941467],"type":"Point"}
}