{
  "type": "Feature",
  "properties": {
    "addr:full":"8777 Ave Chanteau Saint-Leonard QC H1P 3A6",
    "addr:housenumber":"8777",
    "addr:postcode":"h1p 3a6",
    "addr:street":"Ave",
    "iso:country":"CA",
    "sg:address":"8777 Ave Chanteau",
    "sg:city":"Saint-Leonard",
    "sg:classifiers":[
        {
            "category":"Manufacturing",
            "subcategory":"Printing",
            "type":"Manufacturing & Wholesale Goods"
        }
    ],
    "sg:phone":"+1 514 326 3450",
    "sg:postcode":"H1P 3A6",
    "sg:province":"QC",
    "sg:tags":[
        "printer"
    ],
    "wof:name":"Maison Gutenberg Inc",
    "wof:placetype":"venue"
},
  "geometry": {"coordinates":[-73.595856,45.586124],"type":"Point"}
}