{
  "type": "Feature",
  "properties": {
    "addr:full":"121 Dufferin St Perth ON K7H 3A5",
    "addr:housenumber":"121",
    "addr:postcode":"k7h 3a5",
    "addr:street":"Dufferin St",
    "iso:country":"CA",
    "sg:address":"121 Dufferin St",
    "sg:city":"Perth",
    "sg:classifiers":[
        {
            "category":"Manufacturing",
            "subcategory":"Food",
            "type":"Manufacturing & Wholesale Goods"
        }
    ],
    "sg:phone":"+1 613 264 1087",
    "sg:postcode":"K7H 3A5",
    "sg:province":"ON",
    "sg:tags":[
        "brewer"
    ],
    "wof:name":"Perth Brewing & Wine CO",
    "wof:placetype":"venue"
},
  "geometry": {"coordinates":[-76.267143,44.908314],"type":"Point"}
}