{
  "type": "Feature",
  "properties": {
    "addr:full":"10600 100 St Fort St John BC V1J 4L6",
    "addr:housenumber":"10600",
    "addr:postcode":"v1j 4l6",
    "addr:street":"100 St",
    "iso:country":"CA",
    "sg:address":"10600 100 St",
    "sg:city":"Fort St John",
    "sg:classifiers":[
        {
            "category":"Government",
            "subcategory":"Police Station",
            "type":"Public Place"
        }
    ],
    "sg:phone":"+1 250 787 3209",
    "sg:postcode":"V1J 4L6",
    "sg:province":"BC",
    "sg:tags":[
        "department"
    ],
    "wof:name":"BC Sheriff Svc",
    "wof:placetype":"venue"
},
  "geometry": {"coordinates":[-120.847702,56.251675],"type":"Point"}
}