{
  "type": "Feature",
  "properties": {
    "addr:full":"1085 Devonshire Ave Woodstock ON N4S 5S1",
    "addr:housenumber":"1085",
    "addr:postcode":"n4s 5s1",
    "addr:street":"Devonshire Ave",
    "iso:country":"CA",
    "sg:address":"1085 Devonshire Ave",
    "sg:city":"Woodstock",
    "sg:classifiers":[
        {
            "category":"Education",
            "subcategory":"School",
            "type":"Public Place"
        }
    ],
    "sg:phone":"+1 519 537 7592",
    "sg:postcode":"N4S 5S1",
    "sg:province":"ON",
    "wof:name":"St Michael's School",
    "wof:placetype":"venue"
},
  "geometry": {"coordinates":[-80.731590271,43.1465034485],"type":"Point"}
}