{
  "type": "Feature",
  "properties": {
    "addr:full":"Etobicoke ON M9W 5X6",
    "addr:postcode":"m9w 5x6",
    "iso:country":"CA",
    "sg:city":"Etobicoke",
    "sg:classifiers":[
        {
            "category":"Food & Beverages",
            "subcategory":"Meat & Fish",
            "type":"Retail Goods"
        }
    ],
    "sg:phone":"+1 416 675 3737",
    "sg:postcode":"M9W 5X6",
    "sg:province":"ON",
    "sg:tags":[
        "frozen"
    ],
    "wof:name":"Bolton Food Products Inc",
    "wof:placetype":"venue"
},
  "geometry": {"coordinates":[-79.585526,43.679722],"type":"Point"}
}