{
  "type": "Feature",
  "properties": {
    "iso:country":"CA",
    "sg:address":"49 Main St",
    "sg:city":"Flin Flon",
    "sg:classifiers":[
        {
            "category":"Shopping",
            "subcategory":"Crafts & Fabrics",
            "type":"Retail Goods"
        }
    ],
    "sg:phone":"+1 204 687 4363",
    "sg:postcode":"R8A 1J7",
    "sg:province":"MB",
    "sg:tags":[
        "shop"
    ],
    "wof:name":"Faktor's Fashions & Fabrics",
    "wof:placetype":"venue"
},
  "geometry": {"coordinates":[-101.87548065199999,54.7650604248],"type":"Point"}
}