{
  "type": "Feature",
  "properties": {
    "addr:full":"Mississauga ON L5N 6B8",
    "addr:postcode":"l5n 6b8",
    "iso:country":"CA",
    "sg:city":"Mississauga",
    "sg:classifiers":[
        {
            "category":"Restaurant",
            "type":"Food & Drink"
        }
    ],
    "sg:phone":"+1 905 567 0234",
    "sg:postcode":"L5N 6B8",
    "sg:province":"ON",
    "sg:tags":[
        "delicatessen"
    ],
    "wof:name":"Sezam Fine Food Ltd",
    "wof:placetype":"venue"
},
  "geometry": {"coordinates":[-79.759834,43.596977],"type":"Point"}
}