{
  "type": "Feature",
  "properties": {
    "addr:full":"422 Rue Chicoine Vaudreuil-Dorion QC J7V 7E4",
    "addr:housenumber":"422",
    "addr:postcode":"j7v 7e4",
    "addr:street":"Rue Chicoine",
    "iso:country":"CA",
    "sg:address":"422 Rue Chicoine",
    "sg:city":"Vaudreuil-Dorion",
    "sg:classifiers":[
        {
            "category":"Wholesale",
            "subcategory":"Electrical",
            "type":"Manufacturing & Wholesale Goods"
        }
    ],
    "sg:phone":"+1 450 424 6743",
    "sg:postcode":"J7V 7E4",
    "sg:province":"QC",
    "sg:tags":[
        "radio"
    ],
    "wof:name":"Hutton Communications Canada",
    "wof:placetype":"venue"
},
  "geometry": {"coordinates":[-74.0196,45.377728],"type":"Point"}
}