{
  "type": "Feature",
  "properties": {
    "addr:full":"Fonthill ON L0S 1E6",
    "addr:postcode":"l0s 1e6",
    "iso:country":"CA",
    "sg:city":"Fonthill",
    "sg:classifiers":[
        {
            "category":"Organizations",
            "subcategory":"Professional Association",
            "type":"Services"
        }
    ],
    "sg:phone":"+1 905 892 0270",
    "sg:postcode":"L0S 1E6",
    "sg:province":"ON",
    "wof:name":"Elementary Teachers Niagara",
    "wof:placetype":"venue"
},
  "geometry": {"coordinates":[-79.31098937989999,43.0434188843],"type":"Point"}
}