{
  "type": "Feature",
  "properties": {
    "addr:full":"206 Ch DE LA Traverse Saint-Ignace-DE-Loyola QC J0K 2P0",
    "addr:housenumber":"206",
    "addr:postcode":"j0k 2p0",
    "addr:street":"Ch De La Traverse",
    "iso:country":"CA",
    "sg:address":"206 Ch DE LA Traverse",
    "sg:city":"Saint-Ignace-DE-Loyola",
    "sg:classifiers":[
        {
            "category":"Food & Beverages",
            "subcategory":"Groceries & Convenience Stores",
            "type":"Retail Goods"
        }
    ],
    "sg:phone":"+1 450 836 3358",
    "sg:postcode":"J0K 2P0",
    "sg:province":"QC",
    "wof:name":"Depanneur Chez Pierre",
    "wof:placetype":"venue"
},
  "geometry": {"coordinates":[-73.13004302980001,46.0681228638],"type":"Point"}
}