{
  "type": "Feature",
  "properties": {
    "addr:full":"8205 Rue Saint-Denis Montreal QC H2P 2G7",
    "addr:housenumber":"8205",
    "addr:postcode":"h2p 2g7",
    "addr:street":"Rue Saint-Denis",
    "iso:country":"CA",
    "sg:address":"8205 Rue Saint-Denis",
    "sg:city":"Montreal",
    "sg:classifiers":[
        {
            "category":"Shopping",
            "subcategory":"Hobbies, Toys, & Games",
            "type":"Retail Goods"
        }
    ],
    "sg:phone":"+1 514 387 5239",
    "sg:postcode":"H2P 2G7",
    "sg:province":"QC",
    "sg:tags":[
        "model",
        "supply"
    ],
    "wof:name":"Boutique DE Trains Charley",
    "wof:placetype":"venue"
},
  "geometry": {"coordinates":[-73.63074493409999,45.5431861877],"type":"Point"}
}