{
  "type": "Feature",
  "properties": {
    "addr:full":"81 Rue Saint-Jean-Baptiste O Montmagny QC G5V 3B8",
    "addr:housenumber":"81",
    "addr:postcode":"g5v 3b8",
    "addr:street":"Rue Saint-Jean-Baptiste O",
    "iso:country":"CA",
    "sg:address":"81 Rue Saint-Jean-Baptiste O",
    "sg:city":"Montmagny",
    "sg:classifiers":[
        {
            "category":"Building & Trades",
            "subcategory":"Electrical",
            "type":"Services"
        }
    ],
    "sg:phone":"+1 418 248 0210",
    "sg:postcode":"G5V 3B8",
    "sg:province":"QC",
    "sg:tags":[
        "electric",
        "contractor"
    ],
    "wof:name":"Rene Samson Inc",
    "wof:placetype":"venue"
},
  "geometry": {"coordinates":[-70.5593795776,46.9801177979],"type":"Point"}
}