{
  "type": "Feature",
  "properties": {
    "iso:country":"CA",
    "sg:address":"30 Tsse Page",
    "sg:city":"L'Ile-Bizard",
    "sg:classifiers":[
        {
            "category":"Professional",
            "subcategory":"Computer Services",
            "type":"Services"
        }
    ],
    "sg:phone":"+1 514 620 3185",
    "sg:postcode":"H9E 1N7",
    "sg:province":"QC",
    "sg:tags":[
        "consultant",
        "electric",
        "contractor"
    ],
    "wof:name":"Gbm Systek Inc",
    "wof:placetype":"venue"
},
  "geometry": {"coordinates":[-73.9103088379,45.5057029724],"type":"Point"}
}