{
  "type": "Feature",
  "properties": {
    "addr:full":"312 Dundas St W Whitby ON L1N 2M5",
    "addr:housenumber":"312",
    "addr:postcode":"l1n 2m5",
    "addr:street":"Dundas St W",
    "iso:country":"CA",
    "sg:address":"312 Dundas St W",
    "sg:city":"Whitby",
    "sg:classifiers":[
        {
            "category":"Health Services",
            "subcategory":"Doctor",
            "type":"Services"
        }
    ],
    "sg:phone":"+1 905 668 6301",
    "sg:postcode":"L1N 2M5",
    "sg:province":"ON",
    "sg:tags":[
        "dentist"
    ],
    "wof:name":"Appleton, R Todd DDS",
    "wof:placetype":"venue"
},
  "geometry": {"coordinates":[-78.9449920654,43.8793640137],"type":"Point"}
}