{
  "type": "Feature",
  "properties": {
    "addr:full":"681 Rue Principale Clair NB E7A 2H3",
    "addr:housenumber":"681",
    "addr:postcode":"e7a 2h3",
    "addr:street":"Rue Principale",
    "iso:country":"CA",
    "sg:address":"681 Rue Principale",
    "sg:city":"Clair",
    "sg:classifiers":[
        {
            "category":"Shopping",
            "subcategory":"Clothing, Apparel, & Fashions",
            "type":"Retail Goods"
        }
    ],
    "sg:phone":"+1 506 992 3602",
    "sg:postcode":"E7A 2H3",
    "sg:province":"NB",
    "sg:tags":[
        "dressmaker"
    ],
    "wof:name":"Confection Bl Inc",
    "wof:placetype":"venue"
},
  "geometry": {"coordinates":[-68.60233306879999,47.254486084],"type":"Point"}
}