{
  "type": "Feature",
  "properties": {
    "addr:full":"Longlac ON P0T 2A0",
    "addr:postcode":"p0t 2a0",
    "iso:country":"CA",
    "sg:city":"Longlac",
    "sg:classifiers":[
        {
            "category":"Insurance",
            "subcategory":"Insurance Agent",
            "type":"Services"
        }
    ],
    "sg:phone":"+1 807 876 4772",
    "sg:postcode":"P0T 2A0",
    "sg:province":"ON",
    "wof:name":"Canada Brokerlink Inc",
    "wof:placetype":"venue"
},
  "geometry": {"coordinates":[-86.53510300000001,49.779587],"type":"Point"}
}