{
  "type": "Feature",
  "properties": {
    "addr:full":"1170 Rue Beauregard Saint-Hyacinthe QC J2T 2K5",
    "addr:housenumber":"1170",
    "addr:postcode":"j2t 2k5",
    "addr:street":"Rue Beauregard",
    "iso:country":"CA",
    "sg:address":"1170 Rue Beauregard",
    "sg:city":"Saint-Hyacinthe",
    "sg:classifiers":[
        {
            "category":"Health Services",
            "subcategory":"Nursing And Care Facility",
            "type":"Services"
        }
    ],
    "sg:phone":"+1 450 773 5466",
    "sg:postcode":"J2T 2K5",
    "sg:province":"QC",
    "sg:tags":[
        "home",
        "retirement",
        "community"
    ],
    "wof:name":"Villa St-Joseph",
    "wof:placetype":"venue"
},
  "geometry": {"coordinates":[-72.933052,45.618465],"type":"Point"}
}