{
  "type": "Feature",
  "properties": {
    "addr:full":"4567 Hwy 93 Hillsdale ON L0L 1V0",
    "addr:housenumber":"4567",
    "addr:postcode":"l0l 1v0",
    "addr:street":"Hwy 93",
    "iso:country":"CA",
    "sg:address":"4567 Hwy 93",
    "sg:city":"Hillsdale",
    "sg:classifiers":[
        {
            "category":"Retail",
            "subcategory":"Auto Repair",
            "type":"Services"
        }
    ],
    "sg:phone":"+1 705 835 2522",
    "sg:postcode":"L0L 1V0",
    "sg:province":"ON",
    "sg:tags":[
        "repairing",
        "automobile"
    ],
    "wof:name":"Hillsdale Service Ctr",
    "wof:placetype":"venue"
},
  "geometry": {"coordinates":[-79.7603378296,44.5797691345],"type":"Point"}
}