{
  "type": "Feature",
  "properties": {
    "addr:full":"Surrey BC V3W 6J3",
    "addr:postcode":"v3w 6j3",
    "iso:country":"CA",
    "sg:city":"Surrey",
    "sg:classifiers":[
        {
            "category":"Retail",
            "subcategory":"Auto Repair",
            "type":"Services"
        }
    ],
    "sg:phone":"+1 604 594 6966",
    "sg:postcode":"V3W 6J3",
    "sg:province":"BC",
    "sg:tags":[
        "repairing",
        "automobile"
    ],
    "wof:name":"Jack's Automotive",
    "wof:placetype":"venue"
},
  "geometry": {"coordinates":[-122.86792755099999,49.1410598755],"type":"Point"}
}