{
  "type": "Feature",
  "properties": {
    "addr:full":"2695 Drew Rd Mississauga ON L4T 3X1",
    "addr:housenumber":"2695",
    "addr:postcode":"l4t 3x1",
    "addr:street":"Drew Rd",
    "iso:country":"CA",
    "sg:address":"2695 Drew Rd",
    "sg:city":"Mississauga",
    "sg:classifiers":[
        {
            "category":"Wholesale",
            "subcategory":"Scrap",
            "type":"Manufacturing & Wholesale Goods"
        }
    ],
    "sg:phone":"+1 905 678 2483",
    "sg:postcode":"L4T 3X1",
    "sg:province":"ON",
    "sg:tags":[
        "recycling",
        "center"
    ],
    "wof:name":"Canadian Resource Recovery",
    "wof:placetype":"venue"
},
  "geometry": {"coordinates":[-79.6550750732,43.70337677],"type":"Point"}
}