{
  "type": "Feature",
  "properties": {
    "addr:full":"North York ON M6B 3K1",
    "addr:postcode":"m6b 3k1",
    "iso:country":"CA",
    "sg:city":"North York",
    "sg:classifiers":[
        {
            "category":"Social Services",
            "type":"Services"
        }
    ],
    "sg:phone":"+1 416 783 7554",
    "sg:postcode":"M6B 3K1",
    "sg:province":"ON",
    "sg:tags":[
        "organization",
        "welfare"
    ],
    "wof:name":"Mazon Canada",
    "wof:placetype":"venue"
},
  "geometry": {"coordinates":[-79.446472,43.715084],"type":"Point"}
}