{
  "type": "Feature",
  "properties": {
    "addr:full":"1560 Rue Chabanel O Montreal QC H4N 1H4",
    "addr:housenumber":"1560",
    "addr:postcode":"h4n 1h4",
    "addr:street":"Rue Chabanel O",
    "iso:country":"CA",
    "sg:address":"1560 Rue Chabanel O",
    "sg:city":"Montreal",
    "sg:classifiers":[
        {
            "category":"Wholesale",
            "subcategory":"Toys & Hobbies",
            "type":"Manufacturing & Wholesale Goods"
        }
    ],
    "sg:phone":"+1 514 381 1273",
    "sg:postcode":"H4N 1H4",
    "sg:province":"QC",
    "wof:name":"Distributions D Coderre Inc",
    "wof:placetype":"venue"
},
  "geometry": {"coordinates":[-73.658134,45.531349],"type":"Point"}
}