{
  "type": "Feature",
  "properties": {
    "addr:full":"877 Mariners Erieau ON N0P 1N0",
    "addr:housenumber":"877",
    "addr:postcode":"n0p 1n0",
    "addr:street":"Mariners",
    "iso:country":"CA",
    "sg:address":"877 Mariners",
    "sg:city":"Erieau",
    "sg:classifiers":[
        {
            "category":"Shopping",
            "subcategory":"Used Merchandise",
            "type":"Retail Goods"
        }
    ],
    "sg:phone":"+1 519 676 1669",
    "sg:postcode":"N0P 1N0",
    "sg:province":"ON",
    "sg:tags":[
        "antique"
    ],
    "wof:name":"Erieu Antiques & Collectibles",
    "wof:placetype":"venue"
},
  "geometry": {"coordinates":[-81.9187088013,42.2605171204],"type":"Point"}
}