{
  "type": "Feature",
  "properties": {
    "addr:full":"14 Ormond St N Thorold ON L2V 1Y8",
    "addr:housenumber":"14",
    "addr:postcode":"l2v 1y8",
    "addr:street":"Ormond St N",
    "iso:country":"CA",
    "sg:address":"14 Ormond St N",
    "sg:city":"Thorold",
    "sg:classifiers":[
        {
            "category":"Education",
            "subcategory":"Library",
            "type":"Public Place"
        }
    ],
    "sg:phone":"+1 905 227 2581",
    "sg:postcode":"L2V 1Y8",
    "sg:province":"ON",
    "wof:name":"Thorold Public Library",
    "wof:placetype":"venue"
},
  "geometry": {"coordinates":[-79.198868,43.125957],"type":"Point"}
}