{
  "type": "Feature",
  "properties": {
    "addr:full":"PO Box 78017 Rpo Meriline Nepean ON K2E 1B1",
    "addr:housenumber":"po box",
    "addr:postcode":"78017;k2e 1b1",
    "iso:country":"CA",
    "sg:address":"PO Box 78017 Rpo Meriline",
    "sg:city":"Nepean",
    "sg:classifiers":[
        {
            "category":"Home & Garden",
            "subcategory":"Garden Supply",
            "type":"Retail Goods"
        }
    ],
    "sg:phone":"+1 613 746 3879",
    "sg:postcode":"K2E 1B1",
    "sg:province":"ON",
    "sg:tags":[
        "sprinkler"
    ],
    "wof:name":"Ottawa Irrigation",
    "wof:placetype":"venue"
},
  "geometry": {"coordinates":[-75.7636566162,45.3434257507],"type":"Point"}
}