{
  "type": "Feature",
  "properties": {
    "addr:full":"Toronto ON M4X 1W5",
    "addr:postcode":"m4x 1w5",
    "iso:country":"CA",
    "sg:city":"Toronto",
    "sg:classifiers":[
        {
            "category":"Organizations",
            "subcategory":"Non-profit Organization",
            "type":"Services"
        }
    ],
    "sg:phone":"+1 416 944 0315",
    "sg:postcode":"M4X 1W5",
    "sg:province":"ON",
    "sg:tags":[
        "charitable",
        "institution"
    ],
    "wof:name":"Art City in St James Town",
    "wof:placetype":"venue"
},
  "geometry": {"coordinates":[-79.37531300000001,43.66869],"type":"Point"}
}