{
  "type": "Feature",
  "properties": {
    "addr:full":"5307 Ch Queen-Mary Montreal QC H3X 1T9",
    "addr:postcode":"5307;h3x 1t9",
    "addr:street":"Ch Queen-Mary",
    "iso:country":"CA",
    "sg:address":"5307 Ch Queen-Mary",
    "sg:city":"Montreal",
    "sg:classifiers":[
        {
            "category":"Shopping",
            "subcategory":"Shoes",
            "type":"Retail Goods"
        }
    ],
    "sg:phone":"+1 514 481 2108",
    "sg:postcode":"H3X 1T9",
    "sg:province":"QC",
    "wof:name":"Larry's Shoe Shop",
    "wof:placetype":"venue"
},
  "geometry": {"coordinates":[-73.629608,45.483406],"type":"Point"}
}