{
  "type": "Feature",
  "properties": {
    "addr:full":"11 White Oak Dr E Sault Ste Marie ON P6B 4J7",
    "addr:housenumber":"11",
    "addr:postcode":"p6b 4j7",
    "addr:street":"White Oak Dr E",
    "iso:country":"CA",
    "sg:address":"11 White Oak Dr E",
    "sg:city":"Sault Ste Marie",
    "sg:classifiers":[
        {
            "category":"Wholesale",
            "subcategory":"Groceries",
            "type":"Manufacturing & Wholesale Goods"
        }
    ],
    "sg:phone":"+1 705 946 0500",
    "sg:postcode":"P6B 4J7",
    "sg:province":"ON",
    "sg:tags":[
        "grocer"
    ],
    "wof:name":"Lumsden Brothers Ltd Cash",
    "wof:placetype":"venue"
},
  "geometry": {"coordinates":[-84.3345565796,46.5374221802],"type":"Point"}
}