{
  "type": "Feature",
  "properties": {
    "addr:full":"1046 Robson St Vancouver BC V6E 1A7",
    "addr:housenumber":"1046",
    "addr:postcode":"v6e 1a7",
    "addr:street":"Robson St",
    "iso:country":"CA",
    "sg:address":"1046 Robson St",
    "sg:city":"Vancouver",
    "sg:classifiers":[
        {
            "category":"Shopping",
            "subcategory":"Gifts & Souvenirs",
            "type":"Retail Goods"
        }
    ],
    "sg:phone":"+1 604 681 8979",
    "sg:postcode":"V6E 1A7",
    "sg:province":"BC",
    "sg:tags":[
        "shop"
    ],
    "wof:name":"Grand Maple Enterprises Inc",
    "wof:placetype":"venue"
},
  "geometry": {"coordinates":[-123.12388610799999,49.2838096619],"type":"Point"}
}