{
  "type": "Feature",
  "properties": {
    "iso:country":"CA",
    "sg:city":"Edmonton",
    "sg:classifiers":[
        {
            "category":"Professional",
            "subcategory":"Lawyer & Legal Services",
            "type":"Services"
        }
    ],
    "sg:phone":"+1 780 486 4443",
    "sg:postcode":"T5S 1K7",
    "sg:province":"AB",
    "sg:tags":[
        "attorney"
    ],
    "wof:name":"Horwitz, William K",
    "wof:placetype":"venue"
},
  "geometry": {"coordinates":[-113.616653442,53.545375824],"type":"Point"}
}