{
  "type": "Feature",
  "properties": {
    "iso:country":"CA",
    "sg:city":"Calgary",
    "sg:classifiers":[
        {
            "category":"Building & Trades",
            "subcategory":"Construction",
            "type":"Services"
        }
    ],
    "sg:phone":"+1 403 230 7425",
    "sg:postcode":"T2E 1J5",
    "sg:province":"AB",
    "sg:tags":[
        "designer"
    ],
    "wof:name":"Cadd Consortium Ltd",
    "wof:placetype":"venue"
},
  "geometry": {"coordinates":[-114.060997009,51.0671195984],"type":"Point"}
}