{
  "type": "Feature",
  "properties": {
    "addr:full":"865 King Edward St Winnipeg MB R3H 0P8",
    "addr:housenumber":"865",
    "addr:postcode":"r3h 0p8",
    "addr:street":"King Edward St",
    "iso:country":"CA",
    "sg:address":"865 King Edward St",
    "sg:city":"Winnipeg",
    "sg:classifiers":[
        {
            "category":"Manufacturing",
            "subcategory":"Glass & Minerals",
            "type":"Manufacturing & Wholesale Goods"
        }
    ],
    "sg:phone":"+1 204 772 2406",
    "sg:postcode":"R3H 0P8",
    "sg:province":"MB",
    "sg:tags":[
        "refractory"
    ],
    "wof:name":"Rhi Canada Inc",
    "wof:placetype":"venue"
},
  "geometry": {"coordinates":[-97.206688,49.903378],"type":"Point"}
}