{
  "type": "Feature",
  "properties": {
    "addr:full":"185 Broadway W Vancouver BC V5Y 1P4",
    "addr:housenumber":"185",
    "addr:postcode":"v5y 1p4",
    "addr:street":"Broadway W",
    "iso:country":"CA",
    "sg:address":"185 Broadway W",
    "sg:city":"Vancouver",
    "sg:classifiers":[
        {
            "category":"Retail",
            "subcategory":"Repair Shop",
            "type":"Services"
        }
    ],
    "sg:phone":"+1 604 872 4858",
    "sg:postcode":"V5Y 1P4",
    "sg:province":"BC",
    "sg:tags":[
        "leather",
        "good"
    ],
    "wof:name":"Leslie's Luggage & Handbag Rpr",
    "wof:placetype":"venue"
},
  "geometry": {"coordinates":[-123.10889400000001,49.263241],"type":"Point"}
}