{
  "type": "Feature",
  "properties": {
    "iso:country":"CA",
    "sg:address":"18 Ch Des Chutes",
    "sg:city":"Frelighsburg",
    "sg:classifiers":[
        {
            "category":"Travel",
            "subcategory":"Campground",
            "type":"Entertainment"
        }
    ],
    "sg:phone":"+1 450 298 5005",
    "sg:postcode":"J0J 1C0",
    "sg:province":"QC",
    "wof:name":"Camping Des Chutes Hunter",
    "wof:placetype":"venue"
},
  "geometry": {"coordinates":[-72.87072000000001,45.066208],"type":"Point"}
}