{
  "type": "Feature",
  "properties": {
    "addr:full":"3300 27 St Vernon BC V1T 4W7",
    "addr:housenumber":"3300",
    "addr:postcode":"v1t 4w7",
    "addr:street":"27 St",
    "iso:country":"CA",
    "sg:address":"3300 27 St",
    "sg:city":"Vernon",
    "sg:classifiers":[
        {
            "category":"Social Services",
            "subcategory":"Child Care",
            "type":"Services"
        }
    ],
    "sg:phone":"+1 250 558 9963",
    "sg:postcode":"V1T 4W7",
    "sg:province":"BC",
    "wof:name":"North Okanagan Child Care Scty",
    "wof:placetype":"venue"
},
  "geometry": {"coordinates":[-119.26693,50.266098],"type":"Point"}
}