{
  "type": "Feature",
  "properties": {
    "addr:full":"Nanaimo BC V9S 3B5",
    "addr:postcode":"v9s 3b5",
    "iso:country":"CA",
    "sg:city":"Nanaimo",
    "sg:classifiers":[
        {
            "category":"Retail",
            "subcategory":"Auto Repair",
            "type":"Services"
        }
    ],
    "sg:phone":"+1 250 758 4812",
    "sg:postcode":"V9S 3B5",
    "sg:province":"BC",
    "sg:tags":[
        "body",
        "automobile",
        "painting"
    ],
    "wof:name":"Erndor Auto Body Inc",
    "wof:placetype":"venue"
},
  "geometry": {"coordinates":[-123.98380299999999,49.192123],"type":"Point"}
}