{
  "type": "Feature",
  "properties": {
    "addr:full":"9771 33 Hwy Bath ON K0H 1G0",
    "addr:housenumber":"9771",
    "addr:postcode":"k0h 1g0",
    "addr:street":"33 Hwy",
    "iso:country":"CA",
    "sg:address":"9771 33 Hwy",
    "sg:city":"Bath",
    "sg:classifiers":[
        {
            "category":"Shopping",
            "subcategory":"Gifts & Souvenirs",
            "type":"Retail Goods"
        }
    ],
    "sg:phone":"+1 613 373 2885",
    "sg:postcode":"K0H 1G0",
    "sg:province":"ON",
    "sg:tags":[
        "shop"
    ],
    "wof:name":"Great Piddlesbury Country Barn",
    "wof:placetype":"venue"
},
  "geometry": {"coordinates":[-76.76936340330001,44.1847000122],"type":"Point"}
}