{
  "type": "Feature",
  "properties": {
    "addr:full":"Mississauga ON L5A 3M9",
    "addr:postcode":"l5a 3m9",
    "iso:country":"CA",
    "sg:city":"Mississauga",
    "sg:classifiers":[
        {
            "category":"Professional",
            "subcategory":"Management & Consulting",
            "type":"Services"
        }
    ],
    "sg:phone":"+1 905 272 1122",
    "sg:postcode":"L5A 3M9",
    "sg:province":"ON",
    "sg:tags":[
        "communications",
        "consultant"
    ],
    "wof:name":"Clarke Marketing & Corp Comms",
    "wof:placetype":"venue"
},
  "geometry": {"coordinates":[-79.62318399999999,43.599735],"type":"Point"}
}