{
  "type": "Feature",
  "properties": {
    "addr:full":"Queen & Ville Marie Dr Marystown NL A0E 2M0",
    "addr:postcode":"a0e 2m0",
    "addr:street":"Marie",
    "iso:country":"CA",
    "sg:address":"Queen & Ville Marie Dr",
    "sg:city":"Marystown",
    "sg:classifiers":[
        {
            "category":"Insurance",
            "subcategory":"Insurance Agent",
            "type":"Services"
        }
    ],
    "sg:phone":"+1 709 279 3200",
    "sg:postcode":"A0E 2M0",
    "sg:province":"NL",
    "wof:name":"Farrell, Aubrey",
    "wof:placetype":"venue"
},
  "geometry": {"coordinates":[-55.15239,47.167347],"type":"Point"}
}