{
  "type": "Feature",
  "properties": {
    "addr:full":"10 Montreal Rd Cornwall ON K6H 1B1",
    "addr:housenumber":"10",
    "addr:postcode":"k6h 1b1",
    "addr:street":"Montreal Rd",
    "iso:country":"CA",
    "sg:address":"10 Montreal Rd",
    "sg:city":"Cornwall",
    "sg:classifiers":[
        {
            "category":"Health Services",
            "subcategory":"Optometrist",
            "type":"Services"
        }
    ],
    "sg:phone":"+1 613 932 6634",
    "sg:postcode":"K6H 1B1",
    "sg:province":"ON",
    "wof:name":"Dubuc, Michel OD",
    "wof:placetype":"venue"
},
  "geometry": {"coordinates":[-74.7161331177,45.0184860229],"type":"Point"}
}