{
  "type": "Feature",
  "properties": {
    "addr:full":"Vancouver BC V6M 1Z1",
    "addr:postcode":"v6m 1z1",
    "iso:country":"CA",
    "sg:city":"Vancouver",
    "sg:classifiers":[
        {
            "category":"Restaurant",
            "type":"Food & Drink"
        }
    ],
    "sg:phone":"+1 604 267 0077",
    "sg:postcode":"V6M 1Z1",
    "sg:province":"BC",
    "wof:name":"Asa Japanese Restaurant",
    "wof:placetype":"venue"
},
  "geometry": {"coordinates":[-123.15795900000001,49.234489],"type":"Point"}
}