{
  "type": "Feature",
  "properties": {
    "addr:full":"Anjou QC H1M 2Y2",
    "addr:postcode":"h1m 2y2",
    "iso:country":"CA",
    "sg:city":"Anjou",
    "sg:classifiers":[
        {
            "category":"Real Estate",
            "subcategory":"Real Estate Agent",
            "type":"Services"
        }
    ],
    "sg:phone":"+1 514 353 1414",
    "sg:postcode":"H1M 2Y2",
    "sg:province":"QC",
    "sg:tags":[
        "management"
    ],
    "wof:name":"Gestion Immobiliere Perigor",
    "wof:placetype":"venue"
},
  "geometry": {"coordinates":[-73.5576477051,45.5936813354],"type":"Point"}
}