{
  "type": "Feature",
  "properties": {
    "addr:full":"PO Box 1079 STN Main Whitecourt AB T7S 1P9",
    "addr:housenumber":"po",
    "addr:postcode":"t7s 1p9",
    "addr:street":"Box 1079 Stn Main",
    "iso:country":"CA",
    "sg:address":"PO Box 1079 STN Main",
    "sg:city":"Whitecourt",
    "sg:classifiers":[
        {
            "category":"Manufacturing",
            "subcategory":"Lumber",
            "type":"Manufacturing & Wholesale Goods"
        }
    ],
    "sg:phone":"+1 780 648 6200",
    "sg:postcode":"T7S 1P9",
    "sg:province":"AB",
    "sg:tags":[
        "building",
        "material"
    ],
    "wof:name":"Blue Ridge Lumber Inc",
    "wof:placetype":"venue"
},
  "geometry": {"coordinates":[-115.70787799999999,54.139435],"type":"Point"}
}