{
  "type": "Feature",
  "properties": {
    "addr:full":"14228 Rue DE Montigny Montreal QC H1A 1K7",
    "addr:housenumber":"14228",
    "addr:postcode":"h1a 1k7",
    "addr:street":"Rue De Montigny",
    "iso:country":"CA",
    "sg:address":"14228 Rue DE Montigny",
    "sg:city":"Montreal",
    "sg:classifiers":[
        {
            "category":"Personal",
            "subcategory":"Beauty Salon",
            "type":"Services"
        }
    ],
    "sg:phone":"+1 514 642 2242",
    "sg:postcode":"H1A 1K7",
    "sg:province":"QC",
    "wof:name":"Pro Style Coiffure Enr",
    "wof:placetype":"venue"
},
  "geometry": {"coordinates":[-73.498375,45.671562],"type":"Point"}
}