{
  "type": "Feature",
  "properties": {
    "addr:full":"Calgary AB T2E 6L5",
    "addr:postcode":"t2e 6l5",
    "iso:country":"CA",
    "sg:city":"Calgary",
    "sg:classifiers":[
        {
            "category":"Building & Trades",
            "subcategory":"Electrical",
            "type":"Services"
        }
    ],
    "sg:phone":"+1 403 291 3930",
    "sg:postcode":"T2E 6L5",
    "sg:province":"AB",
    "sg:tags":[
        "electric",
        "contractor"
    ],
    "wof:name":"Tyme Electric Svc",
    "wof:placetype":"venue"
},
  "geometry": {"coordinates":[-114.032875,51.091621],"type":"Point"}
}