{
  "type": "Feature",
  "properties": {
    "addr:full":"158 Maple Ave Berwick NS B0P 1E0",
    "addr:housenumber":"158",
    "addr:postcode":"b0p 1e0",
    "addr:street":"Maple Ave",
    "iso:country":"CA",
    "sg:address":"158 Maple Ave",
    "sg:city":"Berwick",
    "sg:classifiers":[
        {
            "category":"Professional",
            "subcategory":"Accounting & Tax Preparation",
            "type":"Services"
        }
    ],
    "sg:phone":"+1 902 538 8798",
    "sg:postcode":"B0P 1E0",
    "sg:province":"NS",
    "sg:tags":[
        "bookkeeping",
        "general"
    ],
    "wof:name":"Reeves Accounting",
    "wof:placetype":"venue"
},
  "geometry": {"coordinates":[-64.7320098877,45.0485153198],"type":"Point"}
}