{
  "type": "Feature",
  "properties": {
    "addr:full":"1300 St Peter Ave Bathurst NB E2A 3A6",
    "addr:housenumber":"1300",
    "addr:postcode":"e2a 3a6",
    "addr:street":"St Peter Ave",
    "iso:country":"CA",
    "sg:address":"1300 St Peter Ave",
    "sg:city":"Bathurst",
    "sg:classifiers":[
        {
            "category":"Shopping",
            "subcategory":"Shoes",
            "type":"Retail Goods"
        }
    ],
    "sg:phone":"+1 506 545 7331",
    "sg:postcode":"E2A 3A6",
    "sg:province":"NB",
    "wof:name":"Yellow Shoes",
    "wof:placetype":"venue"
},
  "geometry": {"coordinates":[-65.6801528931,47.6394233704],"type":"Point"}
}