{
  "type": "Feature",
  "properties": {
    "addr:full":"161 Main St Heatherton NL A0N 1M0",
    "addr:housenumber":"161",
    "addr:postcode":"a0n 1m0",
    "addr:street":"Main St",
    "iso:country":"CA",
    "sg:address":"161 Main St",
    "sg:city":"Heatherton",
    "sg:classifiers":[
        {
            "category":"Home & Garden",
            "subcategory":"Building Materials",
            "type":"Retail Goods"
        }
    ],
    "sg:phone":"+1 709 645 2700",
    "sg:postcode":"A0N 1M0",
    "sg:province":"NL",
    "wof:name":"Hulan's Home Hardware Ltd",
    "wof:placetype":"venue"
},
  "geometry": {"coordinates":[-58.759663,48.279926],"type":"Point"}
}