{
  "type": "Feature",
  "properties": {
    "addr:full":"545 Boul Industriel Shawinigan-Sud QC G9N 6T5",
    "addr:housenumber":"545",
    "addr:postcode":"g9n 6t5",
    "addr:street":"Boul Industriel",
    "iso:country":"CA",
    "sg:address":"545 Boul Industriel",
    "sg:city":"Shawinigan-Sud",
    "sg:classifiers":[
        {
            "category":"Building & Trades",
            "subcategory":"Plumbing",
            "type":"Services"
        }
    ],
    "sg:phone":"+1 819 536 0196",
    "sg:postcode":"G9N 6T5",
    "sg:province":"QC",
    "sg:tags":[
        "contractor"
    ],
    "wof:name":"Plomberie Mont-Carmel Inc",
    "wof:placetype":"venue"
},
  "geometry": {"coordinates":[-72.7130355835,46.5087432861],"type":"Point"}
}