{
  "type": "Feature",
  "properties": {
    "iso:country":"CA",
    "sg:address":"43 Charles St W",
    "sg:city":"Toronto",
    "sg:classifiers":[
        {
            "category":"Retail",
            "subcategory":"Laundry & Dry Cleaning",
            "type":"Services"
        }
    ],
    "sg:phone":"+1 416 962 7281",
    "sg:postcode":"M4Y 2R4",
    "sg:province":"ON",
    "sg:tags":[
        "cleaners"
    ],
    "wof:name":"Suzanna's Cleaners & More",
    "wof:placetype":"venue"
},
  "geometry": {"coordinates":[-79.387993,43.668228],"type":"Point"}
}