{
  "type": "Feature",
  "properties": {
    "addr:full":"2349 Queen St E Toronto ON M4E 1H2",
    "addr:housenumber":"2349",
    "addr:postcode":"m4e 1h2",
    "addr:street":"Queen St E",
    "iso:country":"CA",
    "sg:address":"2349 Queen St E",
    "sg:city":"Toronto",
    "sg:classifiers":[
        {
            "category":"Communications",
            "subcategory":"Film & Video Production",
            "type":"Services"
        }
    ],
    "sg:phone":"+1 416 690 0142",
    "sg:postcode":"M4E 1H2",
    "sg:province":"ON",
    "sg:tags":[
        "television",
        "producer"
    ],
    "wof:name":"Graham Sanborn Media Inc",
    "wof:placetype":"venue"
},
  "geometry": {"coordinates":[-79.289368,43.67215],"type":"Point"}
}