{
  "type": "Feature",
  "properties": {
    "addr:full":"4417 Rue Saint-Denis Montreal QC H2J 2L2",
    "addr:housenumber":"4417",
    "addr:postcode":"h2j 2l2",
    "addr:street":"Rue Saint-Denis",
    "iso:country":"CA",
    "sg:address":"4417 Rue Saint-Denis",
    "sg:city":"Montreal",
    "sg:classifiers":[
        {
            "category":"Personal",
            "subcategory":"Beauty Salon",
            "type":"Services"
        }
    ],
    "sg:phone":"+1 514 848 1731",
    "sg:postcode":"H2J 2L2",
    "sg:province":"QC",
    "wof:name":"Camil Coloriste",
    "wof:placetype":"venue"
},
  "geometry": {"coordinates":[-73.58152,45.523506],"type":"Point"}
}