{
  "type": "Feature",
  "properties": {
    "addr:full":"2393 Bloor St W Toronto ON M6S 1P6",
    "addr:housenumber":"2393",
    "addr:postcode":"m6s 1p6",
    "addr:street":"Bloor St W",
    "iso:country":"CA",
    "sg:address":"2393 Bloor St W",
    "sg:city":"Toronto",
    "sg:classifiers":[
        {
            "category":"Home & Garden",
            "subcategory":"Furniture",
            "type":"Retail Goods"
        }
    ],
    "sg:phone":"+1 416 763 5487",
    "sg:postcode":"M6S 1P6",
    "sg:province":"ON",
    "sg:tags":[
        "linen",
        "mattress"
    ],
    "wof:name":"High Park Drapery & Bedding",
    "wof:placetype":"venue"
},
  "geometry": {"coordinates":[-79.4825744629,43.6496124268],"type":"Point"}
}