{
  "type": "Feature",
  "properties": {
    "addr:full":"3898 Brockton Pl North Vancouver BC V7G 2L7",
    "addr:housenumber":"3898",
    "addr:postcode":"v7g 2l7",
    "addr:street":"Brockton Pl",
    "iso:country":"CA",
    "sg:address":"3898 Brockton Pl",
    "sg:city":"North Vancouver",
    "sg:classifiers":[
        {
            "category":"Railroad",
            "type":"Transportation"
        }
    ],
    "sg:phone":"+1 604 924 3988",
    "sg:postcode":"V7G 2L7",
    "sg:province":"BC",
    "wof:name":"Union Pacific Railroad",
    "wof:placetype":"venue"
},
  "geometry": {"coordinates":[-122.963043,49.316967],"type":"Point"}
}