{
  "type": "Feature",
  "properties": {
    "addr:full":"280 Speedvale Ave W Guelph ON N1H 1C4",
    "addr:housenumber":"280",
    "addr:postcode":"n1h 1c4",
    "addr:street":"Speedvale Ave W",
    "iso:country":"CA",
    "sg:address":"280 Speedvale Ave W",
    "sg:city":"Guelph",
    "sg:classifiers":[
        {
            "category":"Manufacturing",
            "subcategory":"Tools & Machinery",
            "type":"Manufacturing & Wholesale Goods"
        }
    ],
    "sg:phone":"+1 519 824 8899",
    "sg:postcode":"N1H 1C4",
    "sg:province":"ON",
    "sg:tags":[
        "machine",
        "shop"
    ],
    "wof:name":"Traxle Manufacturing Ltd",
    "wof:placetype":"venue"
},
  "geometry": {"coordinates":[-80.28510300000001,43.54599],"type":"Point"}
}