{
  "type": "Feature",
  "properties": {
    "iso:country":"CA",
    "sg:address":"320 Bay St",
    "sg:city":"Sault Ste Marie",
    "sg:classifiers":[
        {
            "category":"Organizations",
            "subcategory":"Labor Organization",
            "type":"Services"
        }
    ],
    "sg:phone":"+1 705 254 2724",
    "sg:postcode":"P6A 1X1",
    "sg:province":"ON",
    "wof:name":"Uswa Local 2724",
    "wof:placetype":"venue"
},
  "geometry": {"coordinates":[-84.33675384519999,46.5127067566],"type":"Point"}
}