{
  "type": "Feature",
  "properties": {
    "iso:country":"CA",
    "sg:address":"3335 Lakefield Rd",
    "sg:city":"Lakefield",
    "sg:classifiers":[
        {
            "category":"Building & Trades",
            "subcategory":"Plumbing",
            "type":"Services"
        }
    ],
    "sg:phone":"+1 705 652 9393",
    "sg:postcode":"K0L 2H0",
    "sg:province":"ON",
    "sg:tags":[
        "contractor"
    ],
    "wof:name":"Trent Plumbing Inc",
    "wof:placetype":"venue"
},
  "geometry": {"coordinates":[-78.26388549799999,44.4247283936],"type":"Point"}
}