{
  "type": "Feature",
  "properties": {
    "iso:country":"CA",
    "sg:city":"Calgary",
    "sg:classifiers":[
        {
            "category":"Shopping",
            "subcategory":"Books",
            "type":"Retail Goods"
        }
    ],
    "sg:phone":"+1 403 249 8124",
    "sg:postcode":"T3E 6S6",
    "sg:province":"AB",
    "sg:tags":[
        "dealer"
    ],
    "wof:name":"Beehive Books",
    "wof:placetype":"venue"
},
  "geometry": {"coordinates":[-114.162262,51.038013],"type":"Point"}
}