{
  "type": "Feature",
  "properties": {
    "addr:full":"730 Milford Dr Kingston ON K7P 1C6",
    "addr:housenumber":"730",
    "addr:postcode":"k7p 1c6",
    "addr:street":"Milford Dr",
    "iso:country":"CA",
    "sg:address":"730 Milford Dr",
    "sg:city":"Kingston",
    "sg:classifiers":[
        {
            "category":"Retail",
            "subcategory":"Laundry & Dry Cleaning",
            "type":"Services"
        }
    ],
    "sg:phone":"+1 613 389 9867",
    "sg:postcode":"K7P 1C6",
    "sg:province":"ON",
    "sg:tags":[
        "cleaners",
        "fur"
    ],
    "wof:name":"Flindall's Cleaners",
    "wof:placetype":"venue"
},
  "geometry": {"coordinates":[-76.58092499999999,44.248734],"type":"Point"}
}