{
  "type": "Feature",
  "properties": {
    "addr:full":"Winnipeg MB R3G 0G3",
    "addr:postcode":"r3g 0g3",
    "iso:country":"CA",
    "sg:city":"Winnipeg",
    "sg:classifiers":[
        {
            "category":"Banks & Credit Unions",
            "subcategory":"Bank",
            "type":"Services"
        }
    ],
    "sg:phone":"+1 204 988 6565",
    "sg:postcode":"R3G 0G3",
    "sg:province":"MB",
    "wof:name":"Royal Bank Financial Group",
    "wof:placetype":"venue"
},
  "geometry": {"coordinates":[-97.19663199999999,49.894245],"type":"Point"}
}