{
  "type": "Feature",
  "properties": {
    "addr:full":"1713 Av Champlain Shawinigan QC G9N 2K8",
    "addr:housenumber":"1713",
    "addr:postcode":"g9n 2k8",
    "addr:street":"Av Champlain",
    "iso:country":"CA",
    "sg:address":"1713 Av Champlain",
    "sg:city":"Shawinigan",
    "sg:classifiers":[
        {
            "category":"Health Services",
            "subcategory":"Nursing And Care Facility",
            "type":"Services"
        }
    ],
    "sg:phone":"+1 819 536 0303",
    "sg:postcode":"G9N 2K8",
    "sg:province":"QC",
    "sg:tags":[
        "home",
        "retirement",
        "community"
    ],
    "wof:name":"Residence DE Carufel",
    "wof:placetype":"venue"
},
  "geometry": {"coordinates":[-72.745689,46.552238],"type":"Point"}
}