{
  "type": "Feature",
  "properties": {
    "addr:full":"16 Rue Dollard Ville-Marie QC J9V 1L2",
    "addr:housenumber":"16",
    "addr:postcode":"j9v 1l2",
    "addr:street":"Rue Dollard",
    "iso:country":"CA",
    "sg:address":"16 Rue Dollard",
    "sg:city":"Ville-Marie",
    "sg:classifiers":[
        {
            "category":"Travel",
            "subcategory":"Hotels & Motels",
            "type":"Entertainment"
        }
    ],
    "sg:phone":"+1 819 629 2733",
    "sg:postcode":"J9V 1L2",
    "sg:province":"QC",
    "wof:name":"Motel Le Manoir",
    "wof:placetype":"venue"
},
  "geometry": {"coordinates":[-79.44194793699999,47.3329238892],"type":"Point"}
}