{
  "type": "Feature",
  "properties": {
    "addr:full":"NW 26 7 20 Souris MB R0K 2C0",
    "addr:housenumber":"20",
    "addr:postcode":"r0k 2c0",
    "addr:street":"Nw 26 7",
    "iso:country":"CA",
    "sg:address":"NW 26 7 20",
    "sg:city":"Souris",
    "sg:classifiers":[
        {
            "category":"Building & Trades",
            "subcategory":"Construction",
            "type":"Services"
        }
    ],
    "sg:phone":"+1 204 483 3706",
    "sg:postcode":"R0K 2C0",
    "sg:province":"MB",
    "sg:tags":[
        "maker",
        "cabinet"
    ],
    "wof:name":"Dimensional Woodworking",
    "wof:placetype":"venue"
},
  "geometry": {"coordinates":[-100.258865356,49.6208343506],"type":"Point"}
}