{
  "type": "Feature",
  "properties": {
    "iso:country":"CA",
    "sg:address":"9355 Boul Sainte-Anne",
    "sg:city":"Sainte-Anne-DE-Beaupre",
    "sg:classifiers":[
        {
            "category":"Personal",
            "subcategory":"Beauty Salon",
            "type":"Services"
        }
    ],
    "sg:phone":"+1 418 827 5540",
    "sg:postcode":"G0A 3C0",
    "sg:province":"QC",
    "wof:name":"Salon Coiffure LA Diva",
    "wof:placetype":"venue"
},
  "geometry": {"coordinates":[-70.8884963989,47.0488700867],"type":"Point"}
}