{
  "type": "Feature",
  "properties": {
    "addr:full":"55 Almont Ave New Glasgow NS B2H 3G5",
    "addr:housenumber":"55",
    "addr:postcode":"b2h 3g5",
    "addr:street":"Almont Ave",
    "iso:country":"CA",
    "sg:address":"55 Almont Ave",
    "sg:city":"New Glasgow",
    "sg:classifiers":[
        {
            "category":"Retail",
            "subcategory":"Funeral Services",
            "type":"Services"
        }
    ],
    "sg:phone":"+1 902 752 4122",
    "sg:postcode":"B2H 3G5",
    "sg:province":"NS",
    "sg:tags":[
        "director"
    ],
    "wof:name":"R H Porter Funeral Homes Ltd",
    "wof:placetype":"venue"
},
  "geometry": {"coordinates":[-62.640083,45.590244],"type":"Point"}
}