{
  "type": "Feature",
  "properties": {
    "addr:full":"360 Sheldon Dr Cambridge ON N1T 1A9",
    "addr:housenumber":"360",
    "addr:postcode":"n1t 1a9",
    "addr:street":"Sheldon Dr",
    "iso:country":"CA",
    "sg:address":"360 Sheldon Dr",
    "sg:city":"Cambridge",
    "sg:classifiers":[
        {
            "category":"Manufacturing",
            "subcategory":"Metals",
            "type":"Manufacturing & Wholesale Goods"
        }
    ],
    "sg:phone":"+1 519 622 7900",
    "sg:postcode":"N1T 1A9",
    "sg:province":"ON",
    "sg:tags":[
        "bronze"
    ],
    "wof:name":"Bearing Bronze Ltd",
    "wof:placetype":"venue"
},
  "geometry": {"coordinates":[-80.29791299999999,43.407925],"type":"Point"}
}