{
  "type": "Feature",
  "properties": {
    "addr:full":"43 Scott St Blind River ON P0R 1B0",
    "addr:housenumber":"43",
    "addr:postcode":"p0r 1b0",
    "addr:street":"Scott St",
    "iso:country":"CA",
    "sg:address":"43 Scott St",
    "sg:city":"Blind River",
    "sg:classifiers":[
        {
            "category":"Social Services",
            "subcategory":"Child Care",
            "type":"Services"
        }
    ],
    "sg:phone":"+1 705 356 1537",
    "sg:postcode":"P0R 1B0",
    "sg:province":"ON",
    "wof:name":"Over the Rainbow Day Care Ctr",
    "wof:placetype":"venue"
},
  "geometry": {"coordinates":[-82.9524230957,46.1851043701],"type":"Point"}
}