{
  "type": "Feature",
  "properties": {
    "addr:full":"14 Cosentino Dr Scarborough ON M1P 3A2",
    "addr:housenumber":"14",
    "addr:postcode":"m1p 3a2",
    "addr:street":"Cosentino Dr",
    "iso:country":"CA",
    "sg:address":"14 Cosentino Dr",
    "sg:city":"Scarborough",
    "sg:classifiers":[
        {
            "category":"Organizations",
            "subcategory":"Labor Organization",
            "type":"Services"
        }
    ],
    "sg:phone":"+1 416 299 7260",
    "sg:postcode":"M1P 3A2",
    "sg:province":"ON",
    "wof:name":"Sheet Metal Workers Union",
    "wof:placetype":"venue"
},
  "geometry": {"coordinates":[-79.27130099999999,43.77166],"type":"Point"}
}