{
  "type": "Feature",
  "properties": {
    "addr:full":"Timmins ON P4N 2K1",
    "addr:postcode":"p4n 2k1",
    "iso:country":"CA",
    "sg:city":"Timmins",
    "sg:classifiers":[
        {
            "category":"Personal",
            "type":"Services"
        }
    ],
    "sg:phone":"+1 705 268 4211",
    "sg:postcode":"P4N 2K1",
    "sg:province":"ON",
    "sg:tags":[
        "therapist",
        "massage"
    ],
    "wof:name":"Melanie Brousseau Rmt Massage",
    "wof:placetype":"venue"
},
  "geometry": {"coordinates":[-81.32852200000001,48.474403],"type":"Point"}
}