{
  "type": "Feature",
  "properties": {
    "addr:full":"58 York St Bridgewater NS B4V 1P9",
    "addr:housenumber":"58",
    "addr:postcode":"b4v 1p9",
    "addr:street":"York St",
    "iso:country":"CA",
    "sg:address":"58 York St",
    "sg:city":"Bridgewater",
    "sg:classifiers":[
        {
            "category":"Health Services",
            "subcategory":"Doctor",
            "type":"Services"
        }
    ],
    "sg:phone":"+1 902 543 7824",
    "sg:postcode":"B4V 1P9",
    "sg:province":"NS",
    "sg:tags":[
        "physician",
        "surgeon"
    ],
    "wof:name":"Barss, David H MD",
    "wof:placetype":"venue"
},
  "geometry": {"coordinates":[-64.520645,44.375671],"type":"Point"}
}