{
  "type": "Feature",
  "properties": {
    "addr:full":"66 Waterloo St # 225 Saint John NB E2L 3P4",
    "addr:housenumber":"66;225",
    "addr:postcode":"e2l 3p4",
    "addr:street":"Waterloo St #",
    "iso:country":"CA",
    "sg:address":"66 Waterloo St # 225",
    "sg:city":"Saint John",
    "sg:classifiers":[
        {
            "category":"Professional",
            "subcategory":"Accounting & Tax Preparation",
            "type":"Services"
        }
    ],
    "sg:phone":"+1 506 693 2665",
    "sg:postcode":"E2L 3P4",
    "sg:province":"NB",
    "sg:tags":[
        "accountant",
        "bookkeeping",
        "general"
    ],
    "wof:name":"Ledgers Professional Bkpng",
    "wof:placetype":"venue"
},
  "geometry": {"coordinates":[-66.056206,45.277374],"type":"Point"}
}