{
  "type": "Feature",
  "properties": {
    "addr:full":"1856 Brampton St Hamilton ON L8H 3S3",
    "addr:housenumber":"1856",
    "addr:postcode":"l8h 3s3",
    "addr:street":"Brampton St",
    "iso:country":"CA",
    "sg:address":"1856 Brampton St",
    "sg:city":"Hamilton",
    "sg:classifiers":[
        {
            "category":"Manufacturing",
            "subcategory":"Metals",
            "type":"Manufacturing & Wholesale Goods"
        }
    ],
    "sg:phone":"+1 905 545 7840",
    "sg:postcode":"L8H 3S3",
    "sg:province":"ON",
    "sg:tags":[
        "steel"
    ],
    "wof:name":"Bouling Metals Ltd",
    "wof:placetype":"venue"
},
  "geometry": {"coordinates":[-79.78346999999999,43.251694],"type":"Point"}
}