{
  "type": "Feature",
  "properties": {
    "addr:full":"12592 110 Ave Surrey BC V3V 3J8",
    "addr:housenumber":"12592",
    "addr:postcode":"v3v 3j8",
    "addr:street":"110 Ave",
    "iso:country":"CA",
    "sg:address":"12592 110 Ave",
    "sg:city":"Surrey",
    "sg:classifiers":[
        {
            "category":"Autos & Motor Vehicles",
            "subcategory":"Automobile Sales",
            "type":"Retail Goods"
        }
    ],
    "sg:phone":"+1 604 580 7752",
    "sg:postcode":"V3V 3J8",
    "sg:province":"BC",
    "sg:tags":[
        "car",
        "dealer"
    ],
    "wof:name":"Alkel Auto Sales Ltd",
    "wof:placetype":"venue"
},
  "geometry": {"coordinates":[-122.87351200000001,49.202492],"type":"Point"}
}