{
  "type": "Feature",
  "properties": {
    "addr:full":"13105 Cabot Trail Rd Grand Etang NS B0E 1L0",
    "addr:housenumber":"13105",
    "addr:postcode":"b0e 1l0",
    "addr:street":"Cabot Trail Rd",
    "iso:country":"CA",
    "sg:address":"13105 Cabot Trail Rd",
    "sg:city":"Grand Etang",
    "sg:classifiers":[
        {
            "category":"Food & Beverages",
            "subcategory":"Groceries & Convenience Stores",
            "type":"Retail Goods"
        }
    ],
    "sg:phone":"+1 902 224 3335",
    "sg:postcode":"B0E 1L0",
    "sg:province":"NS",
    "sg:tags":[
        "grocer"
    ],
    "wof:name":"Lemoyne CO-OP Society Ltd",
    "wof:placetype":"venue"
},
  "geometry": {"coordinates":[-61.0423431396,46.5471382141],"type":"Point"}
}