{
  "type": "Feature",
  "properties": {
    "addr:full":"1121 Ch Des Patriotes Sorel-Tracy QC J3P 2M9",
    "addr:housenumber":"1121",
    "addr:postcode":"j3p 2m9",
    "addr:street":"Ch Des Patriotes",
    "iso:country":"CA",
    "sg:address":"1121 Ch Des Patriotes",
    "sg:city":"Sorel-Tracy",
    "sg:classifiers":[
        {
            "category":"Shopping",
            "subcategory":"Hobbies, Toys, & Games",
            "type":"Retail Goods"
        }
    ],
    "sg:phone":"+1 450 743 6600",
    "sg:postcode":"J3P 2M9",
    "sg:province":"QC",
    "sg:tags":[
        "product",
        "ceramic"
    ],
    "wof:name":"Ceramique Claudette Inc",
    "wof:placetype":"venue"
},
  "geometry": {"coordinates":[-73.126045,46.012455],"type":"Point"}
}