{
  "type": "Feature",
  "properties": {
    "addr:full":"155 Rue Millier Mont-Saint-Hilaire QC J3H 3L1",
    "addr:housenumber":"155",
    "addr:postcode":"j3h 3l1",
    "addr:street":"Rue Millier",
    "iso:country":"CA",
    "sg:address":"155 Rue Millier",
    "sg:city":"Mont-Saint-Hilaire",
    "sg:classifiers":[
        {
            "category":"Building & Trades",
            "subcategory":"Construction",
            "type":"Services"
        }
    ],
    "sg:phone":"+1 450 467 1540",
    "sg:postcode":"J3H 3L1",
    "sg:province":"QC",
    "sg:tags":[
        "contractor"
    ],
    "wof:name":"Construction Claude Casavant",
    "wof:placetype":"venue"
},
  "geometry": {"coordinates":[-73.190552,45.57235],"type":"Point"}
}