{
  "type": "Feature",
  "properties": {
    "addr:full":"337 Conception Bay Hwy Bay Roberts NL A0A 1G0",
    "addr:housenumber":"337",
    "addr:postcode":"a0a 1g0",
    "addr:street":"Conception Bay Hwy Bay",
    "iso:country":"CA",
    "sg:address":"337 Conception Bay Hwy",
    "sg:city":"Bay Roberts",
    "sg:classifiers":[
        {
            "category":"Health Services",
            "subcategory":"Chiropractor",
            "type":"Services"
        }
    ],
    "sg:phone":"+1 709 786 3873",
    "sg:postcode":"A0A 1G0",
    "sg:province":"NL",
    "wof:name":"Gateway Family Chiropractic",
    "wof:placetype":"venue"
},
  "geometry": {"coordinates":[-53.2890052795,47.566242218],"type":"Point"}
}