{
  "type": "Feature",
  "properties": {
    "addr:full":"906 Railway Ave Dysart SK S0G 1H0",
    "addr:housenumber":"906",
    "addr:postcode":"s0g 1h0",
    "addr:street":"Railway Ave",
    "iso:country":"CA",
    "sg:address":"906 Railway Ave",
    "sg:city":"Dysart",
    "sg:classifiers":[
        {
            "category":"Real Estate",
            "subcategory":"Real Estate Agent",
            "type":"Services"
        }
    ],
    "sg:phone":"+1 306 432 2221",
    "sg:postcode":"S0G 1H0",
    "sg:province":"SK",
    "sg:tags":[
        "cooperative"
    ],
    "wof:name":"Dysart CO-OP",
    "wof:placetype":"venue"
},
  "geometry": {"coordinates":[-104.030845642,50.9448852539],"type":"Point"}
}