{
  "type": "Feature",
  "properties": {
    "addr:full":"6525 Boul Hebert Saint-Timothee QC J6S 6G6",
    "addr:housenumber":"6525",
    "addr:postcode":"j6s 6g6",
    "addr:street":"Boul Hebert Saint-Timothee",
    "iso:country":"CA",
    "sg:address":"6525 Boul Hebert",
    "sg:city":"Saint-Timothee",
    "sg:classifiers":[
        {
            "category":"Real Estate",
            "subcategory":"Real Estate Agent",
            "type":"Services"
        }
    ],
    "sg:phone":"+1 450 373 1000",
    "sg:postcode":"J6S 6G6",
    "sg:province":"QC",
    "wof:name":"Centre Professionnel Immobilie",
    "wof:placetype":"venue"
},
  "geometry": {"coordinates":[-74.016792,45.299789],"type":"Point"}
}