{
  "type": "Feature",
  "properties": {
    "iso:country":"CA",
    "sg:address":"1000 Progress Dr",
    "sg:city":"London",
    "sg:classifiers":[
        {
            "category":"Manufacturing",
            "subcategory":"Tools & Machinery",
            "type":"Manufacturing & Wholesale Goods"
        }
    ],
    "sg:phone":"+1 519 686 1123",
    "sg:postcode":"N6N 1B8",
    "sg:province":"ON",
    "sg:tags":[
        "contractor"
    ],
    "wof:name":"Marcel Equipment Ltd",
    "wof:placetype":"venue"
},
  "geometry": {"coordinates":[-81.181152,42.932556],"type":"Point"}
}