{
  "type": "Feature",
  "properties": {
    "addr:full":"33 Northumberland St Ayr ON N0B 1E0",
    "addr:housenumber":"33",
    "addr:postcode":"n0b 1e0",
    "addr:street":"Northumberland St",
    "iso:country":"CA",
    "sg:address":"33 Northumberland St",
    "sg:city":"Ayr",
    "sg:classifiers":[
        {
            "category":"Restaurant",
            "type":"Food & Drink"
        }
    ],
    "sg:phone":"+1 519 632 9133",
    "sg:postcode":"N0B 1E0",
    "sg:province":"ON",
    "wof:name":"Rambell's Waterside Dining",
    "wof:placetype":"venue"
},
  "geometry": {"coordinates":[-80.451171875,43.2864189148],"type":"Point"}
}