{
  "type": "Feature",
  "properties": {
    "addr:full":"Boisbriand QC J7G 1A9",
    "addr:postcode":"j7g 1a9",
    "iso:country":"CA",
    "sg:city":"Boisbriand",
    "sg:classifiers":[
        {
            "category":"Building & Trades",
            "subcategory":"Plumbing",
            "type":"Services"
        }
    ],
    "sg:phone":"+1 450 430 1125",
    "sg:postcode":"J7G 1A9",
    "sg:province":"QC",
    "sg:tags":[
        "refrigeration",
        "contractor"
    ],
    "wof:name":"Nord-Sud Refrigeration Inc",
    "wof:placetype":"venue"
},
  "geometry": {"coordinates":[-73.835007,45.605904],"type":"Point"}
}