{
  "type": "Feature",
  "properties": {
    "addr:full":"Concord ON L4K 1W1",
    "addr:postcode":"l4k 1w1",
    "iso:country":"CA",
    "sg:city":"Concord",
    "sg:classifiers":[
        {
            "category":"Professional",
            "subcategory":"Business Services",
            "type":"Services"
        }
    ],
    "sg:phone":"+1 905 660 0441",
    "sg:postcode":"L4K 1W1",
    "sg:province":"ON",
    "sg:tags":[
        "drafting"
    ],
    "wof:name":"Concord Drafting Ltd",
    "wof:placetype":"venue"
},
  "geometry": {"coordinates":[-79.51692199999999,43.795773],"type":"Point"}
}