{
  "type": "Feature",
  "properties": {
    "iso:country":"CA",
    "sg:address":"4451 Lancelot Dr",
    "sg:city":"Richmond",
    "sg:classifiers":[
        {
            "category":"Wholesale",
            "subcategory":"Machinery & Supplies",
            "type":"Manufacturing & Wholesale Goods"
        }
    ],
    "sg:phone":"+1 604 272 1550",
    "sg:postcode":"V7C 4S4",
    "sg:province":"BC",
    "sg:tags":[
        "ship",
        "chandler"
    ],
    "wof:name":"Orion Marine Supply Ltd",
    "wof:placetype":"venue"
},
  "geometry": {"coordinates":[-123.17219543500001,49.1517677307],"type":"Point"}
}