{
  "type": "Feature",
  "properties": {
    "addr:full":"1221 Farewell St Oshawa ON L1H 6N8",
    "addr:housenumber":"1221",
    "addr:postcode":"l1h 6n8",
    "addr:street":"Farewell St",
    "iso:country":"CA",
    "sg:address":"1221 Farewell St",
    "sg:city":"Oshawa",
    "sg:classifiers":[
        {
            "category":"Building & Trades",
            "subcategory":"Construction",
            "type":"Services"
        }
    ],
    "sg:phone":"+1 905 436 2946",
    "sg:postcode":"L1H 6N8",
    "sg:province":"ON",
    "sg:tags":[
        "product",
        "asphalt"
    ],
    "wof:name":"Mc Asphalt Industries Ltd",
    "wof:placetype":"venue"
},
  "geometry": {"coordinates":[-78.824348,43.870686],"type":"Point"}
}