{
  "type": "Feature",
  "properties": {
    "iso:country":"CA",
    "sg:address":"13 School St",
    "sg:city":"Perth-Andover",
    "sg:classifiers":[
        {
            "category":"Education",
            "subcategory":"School",
            "type":"Public Place"
        }
    ],
    "sg:phone":"+1 506 273 4762",
    "sg:postcode":"E7H 4T4",
    "sg:province":"NB",
    "wof:name":"Southern Victoria High School",
    "wof:placetype":"venue"
},
  "geometry": {"coordinates":[-67.69798299999999,46.750343],"type":"Point"}
}