{
  "type": "Feature",
  "properties": {
    "addr:full":"Fingal ON N0L 1K0",
    "addr:postcode":"n0l 1k0",
    "iso:country":"CA",
    "sg:city":"Fingal",
    "sg:classifiers":[
        {
            "category":"Autos & Motor Vehicles",
            "subcategory":"Auto Supplies",
            "type":"Retail Goods"
        }
    ],
    "sg:phone":"+1 519 769 2404",
    "sg:postcode":"N0L 1K0",
    "sg:province":"ON",
    "sg:tags":[
        "tire"
    ],
    "wof:name":"Stan's Total Tire Sales & Svc",
    "wof:placetype":"venue"
},
  "geometry": {"coordinates":[-81.293869,42.699421],"type":"Point"}
}