{
  "type": "Feature",
  "properties": {
    "addr:full":"6256 Rue Notre-Dame O Montreal QC H4C 1V4",
    "addr:housenumber":"6256",
    "addr:postcode":"h4c 1v4",
    "addr:street":"Rue Notre-Dame O",
    "iso:country":"CA",
    "sg:address":"6256 Rue Notre-Dame O",
    "sg:city":"Montreal",
    "sg:classifiers":[
        {
            "category":"Manufacturing",
            "subcategory":"Printing",
            "type":"Manufacturing & Wholesale Goods"
        }
    ],
    "sg:phone":"+1 514 937 4111",
    "sg:postcode":"H4C 1V4",
    "sg:province":"QC",
    "sg:tags":[
        "screen"
    ],
    "wof:name":"Ecusson T Connor",
    "wof:placetype":"venue"
},
  "geometry": {"coordinates":[-73.51907300000001,45.572475],"type":"Point"}
}