{
  "type": "Feature",
  "properties": {
    "addr:full":"14 Centennial Dr Penetanguishene ON L9M 1R8",
    "addr:housenumber":"14",
    "addr:postcode":"l9m 1r8",
    "addr:street":"Centennial Dr",
    "iso:country":"CA",
    "sg:address":"14 Centennial Dr",
    "sg:city":"Penetanguishene",
    "sg:classifiers":[
        {
            "category":"Manufacturing",
            "subcategory":"Motor Vehicles & Parts",
            "type":"Manufacturing & Wholesale Goods"
        }
    ],
    "sg:phone":"+1 705 549 7406",
    "sg:postcode":"L9M 1R8",
    "sg:province":"ON",
    "sg:tags":[
        "automobile",
        "supply"
    ],
    "wof:name":"Techform Products Ltd",
    "wof:placetype":"venue"
},
  "geometry": {"coordinates":[-79.91745,44.779682],"type":"Point"}
}