{
  "type": "Feature",
  "properties": {
    "addr:full":"1822 County Rd 15 Arden ON K0H 1B0",
    "addr:housenumber":"1822;15",
    "addr:postcode":"k0h 1b0",
    "addr:street":"County Rd",
    "iso:country":"CA",
    "sg:address":"1822 County Rd 15",
    "sg:city":"Arden",
    "sg:classifiers":[
        {
            "category":"Building & Trades",
            "subcategory":"Construction",
            "type":"Services"
        }
    ],
    "sg:phone":"+1 613 379 5018",
    "sg:postcode":"K0H 1B0",
    "sg:province":"ON",
    "sg:tags":[
        "woodworker"
    ],
    "wof:name":"Raw Necessities",
    "wof:placetype":"venue"
},
  "geometry": {"coordinates":[-76.924057,44.720909],"type":"Point"}
}