{
  "type": "Feature",
  "properties": {
    "addr:full":"555 Saddledome Rise SE Calgary AB T2G 2W1",
    "addr:housenumber":"555",
    "addr:postcode":"t2g 2w1",
    "addr:street":"Saddledome Rise Se",
    "iso:country":"CA",
    "sg:address":"555 Saddledome Rise SE",
    "sg:city":"Calgary",
    "sg:classifiers":[
        {
            "category":"Arena",
            "subcategory":"Sports Club",
            "type":"Entertainment"
        }
    ],
    "sg:phone":"+1 403 777 2177",
    "sg:postcode":"T2G 2W1",
    "sg:province":"AB",
    "sg:tags":[
        "athletic",
        "fields",
        "tourist",
        "stadium",
        "attraction"
    ],
    "wof:name":"Pengrowth Saddledome",
    "wof:placetype":"venue"
},
  "geometry": {"coordinates":[-114.05146026600001,51.0380744934],"type":"Point"}
}