{
  "type": "Feature",
  "properties": {
    "iso:country":"CA",
    "sg:city":"Concord",
    "sg:classifiers":[
        {
            "category":"Manufacturing",
            "subcategory":"Signs",
            "type":"Manufacturing & Wholesale Goods"
        }
    ],
    "sg:phone":"+1 905 660 6400",
    "sg:postcode":"L4K 4M7",
    "sg:province":"ON",
    "wof:name":"E Stiege Signs Ltd",
    "wof:placetype":"venue"
},
  "geometry": {"coordinates":[-79.489136,43.816147],"type":"Point"}
}