{
  "type": "Feature",
  "properties": {
    "iso:country":"CA",
    "sg:address":"700 Harper Rd",
    "sg:city":"Peterborough",
    "sg:classifiers":[
        {
            "category":"Freight",
            "type":"Transportation"
        }
    ],
    "sg:phone":"+1 705 876 9753",
    "sg:postcode":"K9J 6X6",
    "sg:province":"ON",
    "sg:tags":[
        "commercial",
        "storage"
    ],
    "wof:name":"Peterborough Stor'n Lok",
    "wof:placetype":"venue"
},
  "geometry": {"coordinates":[-78.34759521479999,44.2741928101],"type":"Point"}
}