{
  "type": "Feature",
  "properties": {
    "addr:full":"103 King St W Brockville ON K6V 3R2",
    "addr:housenumber":"103",
    "addr:postcode":"k6v 3r2",
    "addr:street":"King St W",
    "iso:country":"CA",
    "sg:address":"103 King St W",
    "sg:city":"Brockville",
    "sg:classifiers":[
        {
            "category":"Organizations",
            "subcategory":"Professional Association",
            "type":"Services"
        }
    ],
    "sg:phone":"+1 613 342 5634",
    "sg:postcode":"K6V 3R2",
    "sg:province":"ON",
    "wof:name":"Ioof",
    "wof:placetype":"venue"
},
  "geometry": {"coordinates":[-75.685799,44.588593],"type":"Point"}
}