{
  "type": "Feature",
  "properties": {
    "addr:full":"Nestor Falls ON P0X 1K0",
    "addr:postcode":"p0x 1k0",
    "addr:street":"Nestor Falls",
    "iso:country":"CA",
    "sg:city":"Nestor Falls",
    "sg:classifiers":[
        {
            "category":"Restaurant",
            "type":"Food & Drink"
        }
    ],
    "sg:phone":"+1 807 484 2402",
    "sg:postcode":"P0X 1K0",
    "sg:province":"ON",
    "wof:name":"Lawg Caybun Restaurant",
    "wof:placetype":"venue"
},
  "geometry": {"coordinates":[-93.946129,49.196758],"type":"Point"}
}