{
  "type": "Feature",
  "properties": {
    "addr:full":"2110 Oxford Station Rd Oxford Station ON K0G 1T0",
    "addr:housenumber":"2110",
    "addr:postcode":"k0g 1t0",
    "addr:street":"Oxford Station Rd",
    "iso:country":"CA",
    "sg:address":"2110 Oxford Station Rd",
    "sg:city":"Oxford Station",
    "sg:classifiers":[
        {
            "category":"Restaurant",
            "type":"Food & Drink"
        }
    ],
    "sg:phone":"+1 613 258 9977",
    "sg:postcode":"K0G 1T0",
    "sg:province":"ON",
    "wof:name":"Garden of Eat'n",
    "wof:placetype":"venue"
},
  "geometry": {"coordinates":[-75.61193799999999,44.933975],"type":"Point"}
}