{
  "type": "Feature",
  "properties": {
    "iso:country":"CA",
    "sg:city":"Montreal",
    "sg:classifiers":[
        {
            "category":"Shopping",
            "subcategory":"Bicycles & Sporting Goods",
            "type":"Retail Goods"
        }
    ],
    "sg:phone":"+1 514 381 8076",
    "sg:postcode":"H2N 2E3",
    "sg:province":"QC",
    "wof:name":"Brador Skiwear",
    "wof:placetype":"venue"
},
  "geometry": {"coordinates":[-73.6601409912,45.538860321],"type":"Point"}
}