{
  "type": "Feature",
  "properties": {
    "addr:full":"256 Rang Du Haut-DE-LA-Riviere Saint-Cesaire QC J0L 1T0",
    "addr:housenumber":"256",
    "addr:postcode":"j0l 1t0",
    "addr:street":"Rang Du Haut-De-La-Riviere Saint-Cesaire",
    "iso:country":"CA",
    "sg:address":"256 Rang Du Haut-DE-LA-Riviere",
    "sg:city":"Saint-Cesaire",
    "sg:classifiers":[
        {
            "category":"Home & Garden",
            "subcategory":"Garden Supply",
            "type":"Retail Goods"
        }
    ],
    "sg:phone":"+1 450 469 3380",
    "sg:postcode":"J0L 1T0",
    "sg:province":"QC",
    "sg:tags":[
        "nurseryman"
    ],
    "wof:name":"Pepiniere A Masse Inc",
    "wof:placetype":"venue"
},
  "geometry": {"coordinates":[-72.994499,45.351528],"type":"Point"}
}