{
  "type": "Feature",
  "properties": {
    "iso:country":"CA",
    "sg:city":"Calgary",
    "sg:classifiers":[
        {
            "category":"Professional",
            "subcategory":"Engineering",
            "type":"Services"
        }
    ],
    "sg:phone":"+1 403 250 2911",
    "sg:postcode":"T2E 6L5",
    "sg:province":"AB",
    "sg:tags":[
        "engineer"
    ],
    "wof:name":"Micrologic Limited",
    "wof:placetype":"venue"
},
  "geometry": {"coordinates":[-114.03256225600001,51.0916213989],"type":"Point"}
}