{
  "type": "Feature",
  "properties": {
    "iso:country":"CA",
    "sg:address":"435 Boul Saint-Francis",
    "sg:city":"Chateauguay",
    "sg:classifiers":[
        {
            "category":"Real Estate",
            "subcategory":"Real Estate Agent",
            "type":"Services"
        }
    ],
    "sg:phone":"+1 450 692 1090",
    "sg:postcode":"J6J 1Z6",
    "sg:province":"QC",
    "wof:name":"Immeubles Re/Max",
    "wof:placetype":"venue"
},
  "geometry": {"coordinates":[-73.7130279541,45.3689346313],"type":"Point"}
}