{
  "type": "Feature",
  "properties": {
    "iso:country":"CA",
    "sg:address":"34 Grimes Ave",
    "sg:city":"Dartmouth",
    "sg:classifiers":[
        {
            "category":"Freight",
            "type":"Transportation"
        }
    ],
    "sg:phone":"+1 902 434 2600",
    "sg:postcode":"B2W 3L7",
    "sg:province":"NS",
    "sg:tags":[
        "delivery",
        "courier"
    ],
    "wof:name":"Legal Express Courier Delivery",
    "wof:placetype":"venue"
},
  "geometry": {"coordinates":[-63.509872,44.68391],"type":"Point"}
}