{
  "type": "Feature",
  "properties": {
    "addr:full":"143 Rue Principale O Sainte-Henedine QC G0S 2R0",
    "addr:housenumber":"143",
    "addr:postcode":"g0s 2r0",
    "addr:street":"Rue Principale O Sainte-Henedine",
    "iso:country":"CA",
    "sg:address":"143 Rue Principale O",
    "sg:city":"Sainte-Henedine",
    "sg:classifiers":[
        {
            "category":"Wholesale",
            "subcategory":"Construction Materials",
            "type":"Manufacturing & Wholesale Goods"
        }
    ],
    "sg:phone":"+1 418 935 3868",
    "sg:postcode":"G0S 2R0",
    "sg:province":"QC",
    "sg:tags":[
        "brick",
        "common",
        "face"
    ],
    "wof:name":"Real Sylvain Inc",
    "wof:placetype":"venue"
},
  "geometry": {"coordinates":[-70.98918914790001,46.5562744141],"type":"Point"}
}