{
  "type": "Feature",
  "properties": {
    "addr:full":"475 Rue Saint-Vincent Granby QC J2G 9B2",
    "addr:housenumber":"475",
    "addr:postcode":"j2g 9b2",
    "addr:street":"Rue Saint-Vincent",
    "iso:country":"CA",
    "sg:address":"475 Rue Saint-Vincent",
    "sg:city":"Granby",
    "sg:classifiers":[
        {
            "category":"Education",
            "subcategory":"School",
            "type":"Public Place"
        }
    ],
    "sg:phone":"+1 450 378 7925",
    "sg:postcode":"J2G 9B2",
    "sg:province":"QC",
    "wof:name":"Ecole Ave-Maria",
    "wof:placetype":"venue"
},
  "geometry": {"coordinates":[-72.738136,45.388798],"type":"Point"}
}