{
  "type": "Feature",
  "properties": {
    "addr:full":"4444 Boul Henri-Bourassa E Montreal-Nord QC H1H 3J3",
    "addr:housenumber":"4444",
    "addr:postcode":"h1h 3j3",
    "addr:street":"Boul Henri-Bourassa E",
    "iso:country":"CA",
    "sg:address":"4444 Boul Henri-Bourassa E",
    "sg:city":"Montreal-Nord",
    "sg:classifiers":[
        {
            "category":"Organizations",
            "subcategory":"Professional Association",
            "type":"Services"
        }
    ],
    "sg:phone":"+1 514 321 1936",
    "sg:postcode":"H1H 3J3",
    "sg:province":"QC",
    "sg:tags":[
        "club"
    ],
    "wof:name":"Club Gymkhana DE Mtrl-Nord Inc",
    "wof:placetype":"venue"
},
  "geometry": {"coordinates":[-73.636459,45.600994],"type":"Point"}
}