{
  "type": "Feature",
  "properties": {
    "addr:full":"15 Epsom Ave East York ON M4C 2A5",
    "addr:housenumber":"15",
    "addr:postcode":"m4c 2a5",
    "addr:street":"Epsom Ave",
    "iso:country":"CA",
    "sg:address":"15 Epsom Ave",
    "sg:city":"East York",
    "sg:classifiers":[
        {
            "category":"Building & Trades",
            "subcategory":"Construction",
            "type":"Services"
        }
    ],
    "sg:phone":"+1 416 423 3101",
    "sg:postcode":"M4C 2A5",
    "sg:province":"ON",
    "sg:tags":[
        "home",
        "general",
        "improvement",
        "contractor"
    ],
    "wof:name":"Reliable Handiman",
    "wof:placetype":"venue"
},
  "geometry": {"coordinates":[-79.30798299999999,43.69125],"type":"Point"}
}