{
  "type": "Feature",
  "properties": {
    "addr:full":"232 Rainbow Rd Salt Spring Island BC V8K 2M3",
    "addr:housenumber":"232",
    "addr:postcode":"v8k 2m3",
    "addr:street":"Rainbow Rd",
    "iso:country":"CA",
    "sg:address":"232 Rainbow Rd",
    "sg:city":"Salt Spring Island",
    "sg:classifiers":[
        {
            "category":"Social Services",
            "type":"Services"
        }
    ],
    "sg:phone":"+1 250 537 4693",
    "sg:postcode":"V8K 2M3",
    "sg:province":"BC",
    "sg:tags":[
        "organization",
        "welfare"
    ],
    "wof:name":"School District No 64",
    "wof:placetype":"venue"
},
  "geometry": {"coordinates":[-123.510856628,48.8543891907],"type":"Point"}
}