{
  "type": "Feature",
  "properties": {
    "iso:country":"CA",
    "sg:address":"103 12th St",
    "sg:city":"Fort Macleod",
    "sg:classifiers":[
        {
            "category":"Autos & Motor Vehicles",
            "subcategory":"Auto Supplies",
            "type":"Retail Goods"
        }
    ],
    "sg:phone":"+1 403 553 3157",
    "sg:postcode":"T0L 0Z0",
    "sg:province":"AB",
    "sg:tags":[
        "tire"
    ],
    "wof:name":"Collar Tire & Mechanical",
    "wof:placetype":"venue"
},
  "geometry": {"coordinates":[-113.411155701,49.7164993286],"type":"Point"}
}