{
  "type": "Feature",
  "properties": {
    "addr:full":"3322 32 St NE Calgary AB T1Y 6B9",
    "addr:housenumber":"3322",
    "addr:postcode":"t1y 6b9",
    "addr:street":"32 St Ne",
    "iso:country":"CA",
    "sg:address":"3322 32 St NE",
    "sg:city":"Calgary",
    "sg:classifiers":[
        {
            "category":"Retail",
            "subcategory":"Car Wash",
            "type":"Services"
        }
    ],
    "sg:phone":"+1 403 250 2009",
    "sg:postcode":"T1Y 6B9",
    "sg:province":"AB",
    "sg:tags":[
        "polishing",
        "washing"
    ],
    "wof:name":"Autobath Car Wash",
    "wof:placetype":"venue"
},
  "geometry": {"coordinates":[-113.98839599999999,51.081959],"type":"Point"}
}