{
  "type": "Feature",
  "properties": {
    "addr:full":"1521 Hibernia Rd Caledonia NS B0T 1B0",
    "addr:housenumber":"1521",
    "addr:postcode":"b0t 1b0",
    "addr:street":"Hibernia Rd",
    "iso:country":"CA",
    "sg:address":"1521 Hibernia Rd",
    "sg:city":"Caledonia",
    "sg:classifiers":[
        {
            "category":"Building & Trades",
            "subcategory":"Electrical",
            "type":"Services"
        }
    ],
    "sg:phone":"+1 902 682 2663",
    "sg:postcode":"B0T 1B0",
    "sg:province":"NS",
    "sg:tags":[
        "electric",
        "contractor"
    ],
    "wof:name":"Caledonia Electric Ltd",
    "wof:placetype":"venue"
},
  "geometry": {"coordinates":[-65.030861,44.37318],"type":"Point"}
}