{
  "type": "Feature",
  "properties": {
    "iso:country":"CA",
    "sg:address":"379 Davis Rd",
    "sg:city":"Ladysmith",
    "sg:classifiers":[
        {
            "category":"Professional",
            "subcategory":"Business Services",
            "type":"Services"
        }
    ],
    "sg:phone":"+1 250 245 7127",
    "sg:postcode":"V9G 1V1",
    "sg:province":"BC",
    "sg:tags":[
        "notary"
    ],
    "wof:name":"Joan Phillips Notary Corp",
    "wof:placetype":"venue"
},
  "geometry": {"coordinates":[-123.80473327599999,48.9769706726],"type":"Point"}
}