{
  "type": "Feature",
  "properties": {
    "addr:full":"5440 Jaskow Dr Richmond BC V7E 5Z2",
    "addr:housenumber":"5440",
    "addr:postcode":"v7e 5z2",
    "addr:street":"Jaskow Dr",
    "iso:country":"CA",
    "sg:address":"5440 Jaskow Dr",
    "sg:city":"Richmond",
    "sg:classifiers":[
        {
            "category":"Manufacturing",
            "subcategory":"Food",
            "type":"Manufacturing & Wholesale Goods"
        }
    ],
    "sg:phone":"+1 604 275 2337",
    "sg:postcode":"V7E 5Z2",
    "sg:province":"BC",
    "sg:tags":[
        "brewer"
    ],
    "wof:name":"Heineken Canada",
    "wof:placetype":"venue"
},
  "geometry": {"coordinates":[-123.16291809099999,49.1458244324],"type":"Point"}
}