{
  "type": "Feature",
  "properties": {
    "addr:full":"4 Robert Angus Dr Amherst NS B4H 4R7",
    "addr:housenumber":"4",
    "addr:postcode":"b4h 4r7",
    "addr:street":"Robert Angus Dr",
    "iso:country":"CA",
    "sg:address":"4 Robert Angus Dr",
    "sg:city":"Amherst",
    "sg:classifiers":[
        {
            "category":"Health Services",
            "subcategory":"Doctor",
            "type":"Services"
        }
    ],
    "sg:phone":"+1 902 667 7733",
    "sg:postcode":"B4H 4R7",
    "sg:province":"NS",
    "sg:tags":[
        "physician",
        "surgeon"
    ],
    "wof:name":"Cumberland Eye Care",
    "wof:placetype":"venue"
},
  "geometry": {"coordinates":[-64.201111,45.813683],"type":"Point"}
}