{
  "type": "Feature",
  "properties": {
    "addr:full":"238 3rd Ave W Melville SK S0A 2P0",
    "addr:housenumber":"238",
    "addr:postcode":"s0a 2p0",
    "addr:street":"3Rd Ave W",
    "iso:country":"CA",
    "sg:address":"238 3rd Ave W",
    "sg:city":"Melville",
    "sg:classifiers":[
        {
            "category":"Government",
            "subcategory":"Office",
            "type":"Public Place"
        }
    ],
    "sg:phone":"+1 306 728 2818",
    "sg:postcode":"S0A 2P0",
    "sg:province":"SK",
    "sg:tags":[
        "municipality"
    ],
    "wof:name":"Rural Municipality of Stanley",
    "wof:placetype":"venue"
},
  "geometry": {"coordinates":[-102.816093,50.931126],"type":"Point"}
}