{
  "type": "Feature",
  "properties": {
    "iso:country":"CA",
    "sg:address":"450 Rue Des Erables",
    "sg:city":"Cap-DE-LA-Madeleine",
    "sg:classifiers":[
        {
            "category":"Professional",
            "subcategory":"Business Services",
            "type":"Services"
        }
    ],
    "sg:phone":"+1 819 371 3233",
    "sg:postcode":"G8T 5H9",
    "sg:province":"QC",
    "wof:name":"Groupe Gescabec Inc",
    "wof:placetype":"venue"
},
  "geometry": {"coordinates":[-72.520966,46.37759],"type":"Point"}
}