{
  "type": "Feature",
  "properties": {
    "addr:full":"Calmar AB T0C 0V0",
    "addr:postcode":"t0c 0v0",
    "iso:country":"CA",
    "sg:city":"Calmar",
    "sg:classifiers":[
        {
            "category":"Autos & Motor Vehicles",
            "subcategory":"Boat Sales",
            "type":"Retail Goods"
        }
    ],
    "sg:phone":"+1 780 985 4200",
    "sg:postcode":"T0C 0V0",
    "sg:province":"AB",
    "sg:tags":[
        "dealer"
    ],
    "wof:name":"Wizard Lake Marine Inc",
    "wof:placetype":"venue"
},
  "geometry": {"coordinates":[-113.788963318,53.265460968],"type":"Point"}
}