{
  "type": "Feature",
  "properties": {
    "iso:country":"CA",
    "sg:city":"Dollard-Des-Ormeaux",
    "sg:classifiers":[
        {
            "category":"Health Services",
            "subcategory":"Optometrist",
            "type":"Services"
        }
    ],
    "sg:phone":"+1 514 683 8797",
    "sg:postcode":"H8Y 3B7",
    "sg:province":"QC",
    "wof:name":"Jas Optical",
    "wof:placetype":"venue"
},
  "geometry": {"coordinates":[-73.8104476929,45.4966773987],"type":"Point"}
}