{
  "type": "Feature",
  "properties": {
    "addr:full":"4850 Rue Du Sourcin Saint-Augustin-DE-Desmaures QC G3A 2B2",
    "addr:housenumber":"4850",
    "addr:postcode":"g3a 2b2",
    "addr:street":"Rue Du Sourcin",
    "iso:country":"CA",
    "sg:address":"4850 Rue Du Sourcin",
    "sg:city":"Saint-Augustin-DE-Desmaures",
    "sg:classifiers":[
        {
            "category":"Social Services",
            "type":"Services"
        }
    ],
    "sg:phone":"+1 418 872 4091",
    "sg:postcode":"G3A 2B2",
    "sg:province":"QC",
    "sg:tags":[
        "youth",
        "organization",
        "center"
    ],
    "wof:name":"Maison Des Jeunes",
    "wof:placetype":"venue"
},
  "geometry": {"coordinates":[-71.37953948969999,46.7415275574],"type":"Point"}
}