{
  "type": "Feature",
  "properties": {
    "addr:full":"3316 Lakeshore Rd Kelowna BC V1W 3T1",
    "addr:housenumber":"3316",
    "addr:postcode":"v1w 3t1",
    "addr:street":"Lakeshore Rd",
    "iso:country":"CA",
    "sg:address":"3316 Lakeshore Rd",
    "sg:city":"Kelowna",
    "sg:classifiers":[
        {
            "category":"Travel",
            "subcategory":"Campground",
            "type":"Entertainment"
        }
    ],
    "sg:phone":"+1 250 762 6302",
    "sg:postcode":"V1W 3T1",
    "sg:province":"BC",
    "wof:name":"Willow Creek Family Campground",
    "wof:placetype":"venue"
},
  "geometry": {"coordinates":[-119.49140167199999,49.857509613],"type":"Point"}
}