{
  "type": "Feature",
  "properties": {
    "iso:country":"CA",
    "sg:address":"32 Amber St",
    "sg:city":"Sault Ste Marie",
    "sg:classifiers":[
        {
            "category":"Communications",
            "subcategory":"Film & Video Production",
            "type":"Services"
        }
    ],
    "sg:phone":"+1 705 759 3475",
    "sg:postcode":"P6A 5G1",
    "sg:province":"ON",
    "sg:tags":[
        "taping"
    ],
    "wof:name":"Patchwork Productions Inc",
    "wof:placetype":"venue"
},
  "geometry": {"coordinates":[-84.256149,46.514042],"type":"Point"}
}