{
  "type": "Feature",
  "properties": {
    "addr:full":"1055 Pape Ave East York ON M4K 3W3",
    "addr:housenumber":"1055",
    "addr:postcode":"m4k 3w3",
    "addr:street":"Pape Ave",
    "iso:country":"CA",
    "sg:address":"1055 Pape Ave",
    "sg:city":"East York",
    "sg:classifiers":[
        {
            "category":"Food & Beverages",
            "subcategory":"Bakery",
            "type":"Retail Goods"
        }
    ],
    "sg:phone":"+1 416 421 3010",
    "sg:postcode":"M4K 3W3",
    "sg:province":"ON",
    "sg:tags":[
        "baker"
    ],
    "wof:name":"Donlands Bakery",
    "wof:placetype":"venue"
},
  "geometry": {"coordinates":[-79.348923,43.690269],"type":"Point"}
}