{
  "type": "Feature",
  "properties": {
    "iso:country":"CA",
    "sg:address":"124 Barker St",
    "sg:city":"London",
    "sg:classifiers":[
        {
            "category":"Health Services",
            "subcategory":"Health Practitioner",
            "type":"Services"
        }
    ],
    "sg:phone":"+1 519 451 4511",
    "sg:postcode":"N5Y 1Y1",
    "sg:province":"ON",
    "sg:tags":[
        "physiotherapist"
    ],
    "wof:name":"Spine & Joint Physiotherapy",
    "wof:placetype":"venue"
},
  "geometry": {"coordinates":[-81.226852,43.007828],"type":"Point"}
}