{
  "type": "Feature",
  "properties": {
    "addr:full":"9581 Rue Basile-Routhier Montreal QC H2M 1T9",
    "addr:housenumber":"9581",
    "addr:postcode":"h2m 1t9",
    "addr:street":"Rue Basile-Routhier",
    "iso:country":"CA",
    "sg:address":"9581 Rue Basile-Routhier",
    "sg:city":"Montreal",
    "sg:classifiers":[
        {
            "category":"Professional",
            "subcategory":"Accounting & Tax Preparation",
            "type":"Services"
        }
    ],
    "sg:phone":"+1 514 387 8451",
    "sg:postcode":"H2M 1T9",
    "sg:province":"QC",
    "sg:tags":[
        "return",
        "filing"
    ],
    "wof:name":"Info Taxe",
    "wof:placetype":"venue"
},
  "geometry": {"coordinates":[-73.6521682739,45.5512924194],"type":"Point"}
}