{
  "type": "Feature",
  "properties": {
    "addr:full":"147 Church St Keswick ON L4P 1J4",
    "addr:housenumber":"147",
    "addr:postcode":"l4p 1j4",
    "addr:street":"Church St",
    "iso:country":"CA",
    "sg:address":"147 Church St",
    "sg:city":"Keswick",
    "sg:classifiers":[
        {
            "category":"Shopping",
            "subcategory":"Computers & Home Electronics",
            "type":"Retail Goods"
        }
    ],
    "sg:phone":"+1 905 476 7577",
    "sg:postcode":"L4P 1J4",
    "sg:province":"ON",
    "sg:tags":[
        "radio",
        "television",
        "video",
        "equipment"
    ],
    "wof:name":"J & B Tv Svc",
    "wof:placetype":"venue"
},
  "geometry": {"coordinates":[-79.465523,44.244862],"type":"Point"}
}