{
  "type": "Feature",
  "properties": {
    "addr:full":"1695 1st Ave W Prince Albert SK S6V 4Z4",
    "addr:housenumber":"1695",
    "addr:postcode":"s6v 4z4",
    "addr:street":"1St Ave W",
    "iso:country":"CA",
    "sg:address":"1695 1st Ave W",
    "sg:city":"Prince Albert",
    "sg:classifiers":[
        {
            "category":"Home & Garden",
            "subcategory":"Carpets & Floor Coverings",
            "type":"Retail Goods"
        }
    ],
    "sg:phone":"+1 306 764 4474",
    "sg:postcode":"S6V 4Z4",
    "sg:province":"SK",
    "sg:tags":[
        "rug"
    ],
    "wof:name":"Carpet World",
    "wof:placetype":"venue"
},
  "geometry": {"coordinates":[-105.757217,53.197758],"type":"Point"}
}