{
  "type": "Feature",
  "properties": {
    "addr:full":"2515 Dougall Ave Windsor ON N8X 1T3",
    "addr:housenumber":"2515",
    "addr:postcode":"n8x 1t3",
    "addr:street":"Dougall Ave",
    "iso:country":"CA",
    "sg:address":"2515 Dougall Ave",
    "sg:city":"Windsor",
    "sg:classifiers":[
        {
            "category":"Recreation",
            "type":"Entertainment"
        }
    ],
    "sg:phone":"+1 519 969 2443",
    "sg:postcode":"N8X 1T3",
    "sg:province":"ON",
    "sg:tags":[
        "bingo",
        "game"
    ],
    "wof:name":"Big D Bingo Emporium",
    "wof:placetype":"venue"
},
  "geometry": {"coordinates":[-83.02234649659999,42.2857398987],"type":"Point"}
}