{
  "type": "Feature",
  "properties": {
    "addr:full":"Watrous SK S0K 4T0",
    "addr:postcode":"s0k 4t0",
    "addr:street":"Watrous",
    "iso:country":"CA",
    "sg:city":"Watrous",
    "sg:classifiers":[
        {
            "category":"Retail",
            "subcategory":"Repair Shop",
            "type":"Services"
        }
    ],
    "sg:phone":"+1 306 946 2665",
    "sg:postcode":"S0K 4T0",
    "sg:province":"SK",
    "sg:tags":[
        "welding"
    ],
    "wof:name":"Janzen Metal-Fab Ltd",
    "wof:placetype":"venue"
},
  "geometry": {"coordinates":[-105.46787999999999,51.671623],"type":"Point"}
}