{
  "type": "Feature",
  "properties": {
    "addr:full":"1230 Glenayre Dr Port Moody BC V3H 1J9",
    "addr:housenumber":"1230",
    "addr:postcode":"v3h 1j9",
    "addr:street":"Glenayre Dr",
    "iso:country":"CA",
    "sg:address":"1230 Glenayre Dr",
    "sg:city":"Port Moody",
    "sg:classifiers":[
        {
            "category":"Health Services",
            "subcategory":"Clinic",
            "type":"Services"
        }
    ],
    "sg:phone":"+1 604 931 2995",
    "sg:postcode":"V3H 1J9",
    "sg:province":"BC",
    "sg:tags":[
        "therapist",
        "massage"
    ],
    "wof:name":"Glenayre Massage Therapy",
    "wof:placetype":"venue"
},
  "geometry": {"coordinates":[-122.880386,49.280476],"type":"Point"}
}