{
  "type": "Feature",
  "properties": {
    "addr:full":"232 Principale Saint-Alexis-DE-Montcalm QC J0K 1T0",
    "addr:housenumber":"232",
    "addr:postcode":"j0k 1t0",
    "addr:street":"Principale Saint-Alexis-De-Montcalm",
    "iso:country":"CA",
    "sg:address":"232 Principale",
    "sg:city":"Saint-Alexis-DE-Montcalm",
    "sg:classifiers":[
        {
            "category":"Government",
            "subcategory":"Office",
            "type":"Public Place"
        }
    ],
    "sg:phone":"+1 450 839 7277",
    "sg:postcode":"J0K 1T0",
    "sg:province":"QC",
    "sg:tags":[
        "municipality"
    ],
    "wof:name":"St Alexis Corp Municipale",
    "wof:placetype":"venue"
},
  "geometry": {"coordinates":[-73.613266,45.932964],"type":"Point"}
}