{
  "type": "Feature",
  "properties": {
    "addr:full":"Surrey BC V3W 3N3",
    "addr:postcode":"v3w 3n3",
    "iso:country":"CA",
    "sg:city":"Surrey",
    "sg:classifiers":[
        {
            "category":"Home & Garden",
            "subcategory":"Building Materials",
            "type":"Retail Goods"
        }
    ],
    "sg:phone":"+1 604 599 9313",
    "sg:postcode":"V3W 3N3",
    "sg:province":"BC",
    "sg:tags":[
        "paint"
    ],
    "wof:name":"General Paint Ltd",
    "wof:placetype":"venue"
},
  "geometry": {"coordinates":[-122.890236,49.150181],"type":"Point"}
}