{
  "type": "Feature",
  "properties": {
    "addr:full":"55 Dawson Rd Guelph ON N1H 1B1",
    "addr:housenumber":"55",
    "addr:postcode":"n1h 1b1",
    "addr:street":"Dawson Rd",
    "iso:country":"CA",
    "sg:address":"55 Dawson Rd",
    "sg:city":"Guelph",
    "sg:classifiers":[
        {
            "category":"Home & Garden",
            "subcategory":"Building Materials",
            "type":"Retail Goods"
        }
    ],
    "sg:phone":"+1 519 821 5744",
    "sg:postcode":"N1H 1B1",
    "sg:province":"ON",
    "sg:tags":[
        "lumber"
    ],
    "wof:name":"Rona Cashway Building Ctr",
    "wof:placetype":"venue"
},
  "geometry": {"coordinates":[-80.275879,43.547089],"type":"Point"}
}