{
  "type": "Feature",
  "properties": {
    "addr:full":"1500 Bank St Ottawa ON K1H 7Z2",
    "addr:housenumber":"1500",
    "addr:postcode":"k1h 7z2",
    "addr:street":"Bank St",
    "iso:country":"CA",
    "sg:address":"1500 Bank St",
    "sg:city":"Ottawa",
    "sg:classifiers":[
        {
            "category":"Home & Garden",
            "subcategory":"Garden Supply",
            "type":"Retail Goods"
        }
    ],
    "sg:phone":"+1 613 521 7333",
    "sg:postcode":"K1H 7Z2",
    "sg:province":"ON",
    "sg:tags":[
        "house",
        "bird",
        "feeder"
    ],
    "wof:name":"Wild Birds Unlimited",
    "wof:placetype":"venue"
},
  "geometry": {"coordinates":[-75.6703109741,45.3819236755],"type":"Point"}
}