{
  "type": "Feature",
  "properties": {
    "addr:full":"Richmond BC V6Y 4C6",
    "addr:postcode":"v6y 4c6",
    "iso:country":"CA",
    "sg:city":"Richmond",
    "sg:classifiers":[
        {
            "category":"Personal",
            "subcategory":"Beauty Salon",
            "type":"Services"
        }
    ],
    "sg:phone":"+1 604 273 8973",
    "sg:postcode":"V6Y 4C6",
    "sg:province":"BC",
    "wof:name":"Liko Hair Salon",
    "wof:placetype":"venue"
},
  "geometry": {"coordinates":[-123.133407593,49.1687278748],"type":"Point"}
}