{
  "type": "Feature",
  "properties": {
    "iso:country":"CA",
    "sg:address":"3405 Boul Dagenais O",
    "sg:city":"Laval",
    "sg:classifiers":[
        {
            "category":"Restaurant",
            "type":"Food & Drink"
        }
    ],
    "sg:phone":"+1 450 625 0721",
    "sg:postcode":"H7P 4V9",
    "sg:province":"QC",
    "sg:tags":[
        "pizza"
    ],
    "wof:name":"Milano Restaurant Pizzeria",
    "wof:placetype":"venue"
},
  "geometry": {"coordinates":[-73.807915,45.578487],"type":"Point"}
}