{
  "type": "Feature",
  "properties": {
    "addr:full":"3405 Boul Dagenais O Laval QC H7P 4V9",
    "addr:housenumber":"3405",
    "addr:postcode":"h7p 4v9",
    "addr:street":"Boul Dagenais O",
    "iso:country":"CA",
    "sg:address":"3405 Boul Dagenais O",
    "sg:city":"Laval",
    "sg:classifiers":[
        {
            "category":"Restaurant",
            "type":"Food & Drink"
        }
    ],
    "sg:phone":"+1 450 625 0721",
    "sg:postcode":"H7P 4V9",
    "sg:province":"QC",
    "sg:tags":[
        "pizza"
    ],
    "wof:name":"Milano Restaurant Pizzeria",
    "wof:placetype":"venue"
},
  "geometry": {"coordinates":[-73.80791499999999,45.578487],"type":"Point"}
}