{
  "type": "Feature",
  "properties": {
    "addr:full":"715 Mckinnon Ave S Saskatoon SK S7H 2G2",
    "addr:housenumber":"715",
    "addr:postcode":"s7h 2g2",
    "addr:street":"Mckinnon Ave S",
    "iso:country":"CA",
    "sg:address":"715 Mckinnon Ave S",
    "sg:city":"Saskatoon",
    "sg:classifiers":[
        {
            "category":"Organizations",
            "subcategory":"Religious Organization",
            "type":"Services"
        }
    ],
    "sg:phone":"+1 306 343 7023",
    "sg:postcode":"S7H 2G2",
    "sg:province":"SK",
    "sg:tags":[
        "synagogue"
    ],
    "wof:name":"Congregation Agudas Israel",
    "wof:placetype":"venue"
},
  "geometry": {"coordinates":[-106.643837,52.118469],"type":"Point"}
}