{
  "type": "Feature",
  "properties": {
    "addr:full":"Saint-Hubert QC J4T 2V3",
    "addr:postcode":"j4t 2v3",
    "iso:country":"CA",
    "sg:city":"Saint-Hubert",
    "sg:classifiers":[
        {
            "category":"Restaurant",
            "type":"Food & Drink"
        }
    ],
    "sg:phone":"+1 450 678 7030",
    "sg:postcode":"J4T 2V3",
    "sg:province":"QC",
    "sg:tags":[
        "pizza"
    ],
    "wof:name":"Pizzeria Chez Jenni",
    "wof:placetype":"venue"
},
  "geometry": {"coordinates":[-73.469635,45.492519],"type":"Point"}
}