{
  "type": "Feature",
  "properties": {
    "addr:full":"2455 Boul Laurier Sillery QC G1T 1C4",
    "addr:housenumber":"2455",
    "addr:postcode":"g1t 1c4",
    "addr:street":"Boul Laurier",
    "iso:country":"CA",
    "sg:address":"2455 Boul Laurier",
    "sg:city":"Sillery",
    "sg:classifiers":[
        {
            "category":"Restaurant",
            "type":"Food & Drink"
        }
    ],
    "sg:phone":"+1 418 656 6153",
    "sg:postcode":"G1T 1C4",
    "sg:province":"QC",
    "sg:tags":[
        "parcel",
        "gift",
        "ice",
        "parlor",
        "basket",
        "cream"
    ],
    "wof:name":"Laura Secord",
    "wof:placetype":"venue"
},
  "geometry": {"coordinates":[-71.27376599999999,46.774258],"type":"Point"}
}