{
  "type": "Feature",
  "properties": {
    "addr:full":"74 Elm Cres Stittsville ON K2S 1R7",
    "addr:housenumber":"74",
    "addr:postcode":"k2s 1r7",
    "addr:street":"Elm Cres",
    "iso:country":"CA",
    "sg:address":"74 Elm Cres",
    "sg:city":"Stittsville",
    "sg:classifiers":[
        {
            "category":"Shopping",
            "subcategory":"Jewelry",
            "type":"Retail Goods"
        }
    ],
    "sg:phone":"+1 613 836 7770",
    "sg:postcode":"K2S 1R7",
    "sg:province":"ON",
    "sg:tags":[
        "jeweler"
    ],
    "wof:name":"Fifth Avenue Collection",
    "wof:placetype":"venue"
},
  "geometry": {"coordinates":[-75.92185211180001,45.2510871887],"type":"Point"}
}