{
  "type": "Feature",
  "properties": {
    "iso:country":"CA",
    "sg:address":"8719 8E Av",
    "sg:city":"Montreal",
    "sg:classifiers":[
        {
            "category":"Shopping",
            "subcategory":"Gifts & Souvenirs",
            "type":"Retail Goods"
        }
    ],
    "sg:phone":"+1 514 721 4434",
    "sg:postcode":"H1Z 2X4",
    "sg:province":"QC",
    "sg:tags":[
        "supply",
        "consultant",
        "design",
        "interior",
        "party",
        "decorator"
    ],
    "wof:name":"Variance Decor",
    "wof:placetype":"venue"
},
  "geometry": {"coordinates":[-73.6212310791,45.5664863586],"type":"Point"}
}