{
  "type": "Feature",
  "properties": {
    "addr:full":"764 Bernard Ave Kelowna BC V1Y 6P5",
    "addr:housenumber":"764",
    "addr:postcode":"v1y 6p5",
    "addr:street":"Bernard Ave",
    "iso:country":"CA",
    "sg:address":"764 Bernard Ave",
    "sg:city":"Kelowna",
    "sg:classifiers":[
        {
            "category":"Real Estate",
            "subcategory":"Real Estate Agent",
            "type":"Services"
        }
    ],
    "sg:phone":"+1 250 717 3561",
    "sg:postcode":"V1Y 6P5",
    "sg:province":"BC",
    "sg:tags":[
        "consultant"
    ],
    "wof:name":"Tybrelita Properties Corp",
    "wof:placetype":"venue"
},
  "geometry": {"coordinates":[-119.48644299999999,49.886429],"type":"Point"}
}