{
  "type": "Feature",
  "properties": {
    "iso:country":"CA",
    "sg:address":"323 Ch DE LA Grande-Cote",
    "sg:city":"Rosemere",
    "sg:classifiers":[
        {
            "category":"Professional",
            "type":"Services"
        }
    ],
    "sg:phone":"+1 450 965 9657",
    "sg:postcode":"J7A 1J9",
    "sg:province":"QC",
    "sg:tags":[
        "therapist",
        "establishment",
        "massage"
    ],
    "wof:name":"Metayer-Beaudin, Gisele",
    "wof:placetype":"venue"
},
  "geometry": {"coordinates":[-73.794006,45.635563],"type":"Point"}
}