{
  "type": "Feature",
  "properties": {
    "addr:full":"2080 Scarboro Ave Vancouver BC V5P 2L3",
    "addr:housenumber":"2080",
    "addr:postcode":"v5p 2l3",
    "addr:street":"Scarboro Ave",
    "iso:country":"CA",
    "sg:address":"2080 Scarboro Ave",
    "sg:city":"Vancouver",
    "sg:classifiers":[
        {
            "category":"Building & Trades",
            "subcategory":"Landscaping Services",
            "type":"Services"
        }
    ],
    "sg:phone":"+1 604 327 7541",
    "sg:postcode":"V5P 2L3",
    "sg:province":"BC",
    "sg:tags":[
        "designer",
        "landscape"
    ],
    "wof:name":"Fred Liu & Assoc",
    "wof:placetype":"venue"
},
  "geometry": {"coordinates":[-123.06366,49.213383],"type":"Point"}
}