{
  "type": "Feature",
  "properties": {
    "iso:country":"CA",
    "sg:address":"1515 Rue Sainte-Marguerite",
    "sg:city":"Trois-Rivieres",
    "sg:classifiers":[
        {
            "category":"Education",
            "subcategory":"School",
            "type":"Public Place"
        }
    ],
    "sg:phone":"+1 819 379 6565",
    "sg:postcode":"G8Z 1W2",
    "sg:province":"QC",
    "wof:name":"Commission Scolaire Du Chemin",
    "wof:placetype":"venue"
},
  "geometry": {"coordinates":[-72.557419,46.34317],"type":"Point"}
}