{
  "type": "Feature",
  "properties": {
    "addr:full":"50 Eagle St W Newmarket ON L3Y 6B1",
    "addr:housenumber":"50",
    "addr:postcode":"l3y 6b1",
    "addr:street":"Eagle St W",
    "iso:country":"CA",
    "sg:address":"50 Eagle St W",
    "sg:city":"Newmarket",
    "sg:classifiers":[
        {
            "category":"Government",
            "subcategory":"Office",
            "type":"Public Place"
        }
    ],
    "sg:phone":"+1 905 895 1561",
    "sg:postcode":"L3Y 6B1",
    "sg:province":"ON",
    "wof:name":"Ontario Land Registry Office",
    "wof:placetype":"venue"
},
  "geometry": {"coordinates":[-79.4805145264,44.0448036194],"type":"Point"}
}