{
  "type": "Feature",
  "properties": {
    "iso:country":"CA",
    "sg:address":"150 Rue Louvain",
    "sg:city":"Repentigny",
    "sg:classifiers":[
        {
            "category":"Food & Beverages",
            "subcategory":"Groceries & Convenience Stores",
            "type":"Retail Goods"
        }
    ],
    "sg:phone":"+1 450 585 1445",
    "sg:postcode":"J6A 8J7",
    "sg:province":"QC",
    "sg:tags":[
        "grocer"
    ],
    "wof:name":"Super Marche Marquis Inc",
    "wof:placetype":"venue"
},
  "geometry": {"coordinates":[-73.4526596069,45.7482566833],"type":"Point"}
}