{
  "type": "Feature",
  "properties": {
    "iso:country":"CA",
    "sg:address":"530 Av Ogilvy",
    "sg:city":"Montreal",
    "sg:classifiers":[
        {
            "category":"Food & Beverages",
            "subcategory":"Groceries & Convenience Stores",
            "type":"Retail Goods"
        }
    ],
    "sg:phone":"+1 514 274 5250",
    "sg:postcode":"H3N 1M8",
    "sg:province":"QC",
    "sg:tags":[
        "grocer"
    ],
    "wof:name":"Marche Madhubon Inc",
    "wof:placetype":"venue"
},
  "geometry": {"coordinates":[-73.625198,45.528797],"type":"Point"}
}