{
  "type": "Feature",
  "properties": {
    "iso:country":"CA",
    "sg:address":"25 Station Rd N",
    "sg:city":"Kirkland Lake",
    "sg:classifiers":[
        {
            "category":"Food & Beverages",
            "subcategory":"Liquor & Beverages",
            "type":"Retail Goods"
        }
    ],
    "sg:phone":"+1 705 567 4243",
    "sg:postcode":"P2N 1N1",
    "sg:province":"ON",
    "sg:tags":[
        "beer",
        "store"
    ],
    "wof:name":"Beer Store",
    "wof:placetype":"venue"
},
  "geometry": {"coordinates":[-80.0283660889,48.157081604],"type":"Point"}
}