{
  "type": "Feature",
  "properties": {
    "addr:full":"140 Roy Blvd Brantford ON N3R 7K2",
    "addr:housenumber":"140",
    "addr:postcode":"n3r 7k2",
    "addr:street":"Roy Blvd",
    "iso:country":"CA",
    "sg:address":"140 Roy Blvd",
    "sg:city":"Brantford",
    "sg:classifiers":[
        {
            "category":"Manufacturing",
            "subcategory":"Rubber & Plastics",
            "type":"Manufacturing & Wholesale Goods"
        }
    ],
    "sg:phone":"+1 519 759 5111",
    "sg:postcode":"N3R 7K2",
    "sg:province":"ON",
    "sg:tags":[
        "tubing",
        "hose"
    ],
    "wof:name":"Kuriyama Canada Inc",
    "wof:placetype":"venue"
},
  "geometry": {"coordinates":[-80.23625946040001,43.1701316833],"type":"Point"}
}