{
  "type": "Feature",
  "properties": {
    "addr:full":"4471 Boul Samson Laval QC H7W 2H2",
    "addr:housenumber":"4471",
    "addr:postcode":"h7w 2h2",
    "addr:street":"Boul Samson",
    "iso:country":"CA",
    "sg:address":"4471 Boul Samson",
    "sg:city":"Laval",
    "sg:classifiers":[
        {
            "category":"Restaurant",
            "type":"Food & Drink"
        }
    ],
    "sg:phone":"+1 450 978 9991",
    "sg:postcode":"H7W 2H2",
    "sg:province":"QC",
    "sg:tags":[
        "cafe"
    ],
    "wof:name":"Cafe Publiks",
    "wof:placetype":"venue"
},
  "geometry": {"coordinates":[-73.754929,45.530315],"type":"Point"}
}