{
  "type": "Feature",
  "properties": {
    "addr:full":"47 Rue Trottier Dollard-Des-Ormeaux QC H9A 2C8",
    "addr:housenumber":"47",
    "addr:postcode":"h9a 2c8",
    "addr:street":"Rue Trottier",
    "iso:country":"CA",
    "sg:address":"47 Rue Trottier",
    "sg:city":"Dollard-Des-Ormeaux",
    "sg:classifiers":[
        {
            "category":"Wholesale",
            "subcategory":"Chemicals & Plastics",
            "type":"Manufacturing & Wholesale Goods"
        }
    ],
    "sg:phone":"+1 514 685 0619",
    "sg:postcode":"H9A 2C8",
    "sg:province":"QC",
    "wof:name":"Bodyshield",
    "wof:placetype":"venue"
},
  "geometry": {"coordinates":[-73.82147999999999,45.503014],"type":"Point"}
}