{
  "type": "Feature",
  "properties": {
    "addr:full":"Duncan BC V9L 6W3",
    "addr:postcode":"v9l 6w3",
    "iso:country":"CA",
    "sg:city":"Duncan",
    "sg:classifiers":[
        {
            "category":"Retail",
            "subcategory":"Auto Repair",
            "type":"Services"
        }
    ],
    "sg:phone":"+1 250 748 0441",
    "sg:postcode":"V9L 6W3",
    "sg:province":"BC",
    "sg:tags":[
        "repairing",
        "automobile"
    ],
    "wof:name":"Kroffat Brake & Wheel Ltd",
    "wof:placetype":"venue"
},
  "geometry": {"coordinates":[-123.69583900000001,48.760227],"type":"Point"}
}