{
  "type": "Feature",
  "properties": {
    "iso:country":"CA",
    "sg:address":"120 Front St E",
    "sg:city":"Toronto",
    "sg:classifiers":[
        {
            "category":"Cinema",
            "subcategory":"Movie Rental",
            "type":"Entertainment"
        }
    ],
    "sg:phone":"+1 416 955 9555",
    "sg:postcode":"M5A 4L9",
    "sg:province":"ON",
    "sg:tags":[
        "leasing",
        "video",
        "disc",
        "tape"
    ],
    "wof:name":"Rogers Video",
    "wof:placetype":"venue"
},
  "geometry": {"coordinates":[-79.370209,43.649933],"type":"Point"}
}