{
  "type": "Feature",
  "properties": {
    "addr:full":"101 Indian Pond Dr Conception Bay South NL A1X 6P2",
    "addr:housenumber":"101",
    "addr:postcode":"a1x 6p2",
    "addr:street":"Indian Pond Dr",
    "iso:country":"CA",
    "sg:address":"101 Indian Pond Dr",
    "sg:city":"Conception Bay South",
    "sg:classifiers":[
        {
            "category":"Wholesale",
            "subcategory":"Electrical",
            "type":"Manufacturing & Wholesale Goods"
        }
    ],
    "sg:phone":"+1 709 745 2852",
    "sg:postcode":"A1X 6P2",
    "sg:province":"NL",
    "sg:tags":[
        "light",
        "tube",
        "bulb"
    ],
    "wof:name":"Bulb Man",
    "wof:placetype":"venue"
},
  "geometry": {"coordinates":[-53.0882377625,47.4592399597],"type":"Point"}
}