{
  "type": "Feature",
  "properties": {
    "iso:country":"CA",
    "sg:address":"113 Rue Poirier",
    "sg:city":"Saint-Jean-Sur-Richelieu",
    "sg:classifiers":[
        {
            "category":"Building & Trades",
            "subcategory":"Construction",
            "type":"Services"
        }
    ],
    "sg:phone":"+1 450 346 6761",
    "sg:postcode":"J3B 4E9",
    "sg:province":"QC",
    "sg:tags":[
        "designer",
        "dealer",
        "pool",
        "swimming"
    ],
    "wof:name":"Piscines Hebert Enr",
    "wof:placetype":"venue"
},
  "geometry": {"coordinates":[-73.25328063960001,45.2695236206],"type":"Point"}
}