{
  "type": "Feature",
  "properties": {
    "iso:country":"CA",
    "sg:address":"10123 Princess Elizabeth Ave N",
    "sg:city":"Edmonton",
    "sg:classifiers":[
        {
            "category":"Organizations",
            "subcategory":"Religious Organization",
            "type":"Services"
        }
    ],
    "sg:phone":"+1 780 471 2250",
    "sg:postcode":"T5G 0X9",
    "sg:province":"AB",
    "sg:tags":[
        "church"
    ],
    "wof:name":"Christian Life Ctr",
    "wof:placetype":"venue"
},
  "geometry": {"coordinates":[-113.49568176299999,53.5694503784],"type":"Point"}
}