{
  "type": "Feature",
  "properties": {
    "addr:full":"21 Atlantic Ave Toronto ON M6K 3E7",
    "addr:housenumber":"21",
    "addr:postcode":"m6k 3e7",
    "addr:street":"Atlantic Ave",
    "iso:country":"CA",
    "sg:address":"21 Atlantic Ave",
    "sg:city":"Toronto",
    "sg:classifiers":[
        {
            "category":"Professional",
            "subcategory":"Advertising",
            "type":"Services"
        }
    ],
    "sg:phone":"+1 416 531 3920",
    "sg:postcode":"M6K 3E7",
    "sg:province":"ON",
    "wof:name":"Grassroots Advertising Inc",
    "wof:placetype":"venue"
},
  "geometry": {"coordinates":[-79.419838,43.637043],"type":"Point"}
}