{
  "type": "Feature",
  "properties": {
    "addr:full":"407 Kelly St New Westminster BC V3L 3T7",
    "addr:housenumber":"407",
    "addr:postcode":"v3l 3t7",
    "addr:street":"Kelly St",
    "iso:country":"CA",
    "sg:address":"407 Kelly St",
    "sg:city":"New Westminster",
    "sg:classifiers":[
        {
            "category":"Social Services",
            "type":"Services"
        }
    ],
    "sg:phone":"+1 604 290 6663",
    "sg:postcode":"V3L 3T7",
    "sg:province":"BC",
    "sg:tags":[
        "information",
        "organization",
        "treatment",
        "alcoholism",
        "welfare"
    ],
    "wof:name":"Lana House Post Recovery Prgrm",
    "wof:placetype":"venue"
},
  "geometry": {"coordinates":[-122.891594,49.22831],"type":"Point"}
}