{
  "type": "Feature",
  "properties": {
    "addr:full":"2779 170 Rte Laterriere QC G7N 1A8",
    "addr:housenumber":"2779",
    "addr:postcode":"g7n 1a8",
    "addr:street":"170 Rte Laterriere",
    "iso:country":"CA",
    "sg:address":"2779 170 Rte",
    "sg:city":"Laterriere",
    "sg:classifiers":[
        {
            "category":"Building & Trades",
            "subcategory":"Landscaping Services",
            "type":"Services"
        }
    ],
    "sg:phone":"+1 418 678 1515",
    "sg:postcode":"G7N 1A8",
    "sg:province":"QC",
    "sg:tags":[
        "landscape",
        "contractor"
    ],
    "wof:name":"Amenagement Grenon",
    "wof:placetype":"venue"
},
  "geometry": {"coordinates":[-71.1181335449,48.3027496338],"type":"Point"}
}