{
  "type": "Feature",
  "properties": {
    "addr:full":"8816 159A Ave NW Edmonton AB T5Z 3E7",
    "addr:housenumber":"8816",
    "addr:postcode":"t5z 3e7",
    "addr:street":"159A Ave Nw",
    "iso:country":"CA",
    "sg:address":"8816 159A Ave NW",
    "sg:city":"Edmonton",
    "sg:classifiers":[
        {
            "category":"Wholesale",
            "subcategory":"Apparel",
            "type":"Manufacturing & Wholesale Goods"
        }
    ],
    "sg:phone":"+1 780 473 7496",
    "sg:postcode":"T5Z 3E7",
    "sg:province":"AB",
    "sg:tags":[
        "advertising"
    ],
    "wof:name":"Auriga Inc",
    "wof:placetype":"venue"
},
  "geometry": {"coordinates":[-113.47614299999999,53.619919],"type":"Point"}
}