{
  "type": "Feature",
  "properties": {
    "addr:full":"1299 Av Papineau Montreal QC H2K 4H3",
    "addr:housenumber":"1299",
    "addr:postcode":"h2k 4h3",
    "addr:street":"Av Papineau",
    "iso:country":"CA",
    "sg:address":"1299 Av Papineau",
    "sg:city":"Montreal",
    "sg:classifiers":[
        {
            "category":"Retail",
            "subcategory":"Laundry & Dry Cleaning",
            "type":"Services"
        }
    ],
    "sg:phone":"+1 514 529 0464",
    "sg:postcode":"H2K 4H3",
    "sg:province":"QC",
    "sg:tags":[
        "cleaners"
    ],
    "wof:name":"Nettoyeur Super Dave",
    "wof:placetype":"venue"
},
  "geometry": {"coordinates":[-73.55147599999999,45.522346],"type":"Point"}
}