{
  "type": "Feature",
  "properties": {
    "addr:full":"12 William Kitchen Rd Scarborough ON M1P 5B7",
    "addr:housenumber":"12",
    "addr:postcode":"m1p 5b7",
    "addr:street":"William Kitchen Rd",
    "iso:country":"CA",
    "sg:address":"12 William Kitchen Rd",
    "sg:city":"Scarborough",
    "sg:classifiers":[
        {
            "category":"Retail",
            "subcategory":"Animal Services",
            "type":"Services"
        }
    ],
    "sg:phone":"+1 416 335 7922",
    "sg:postcode":"M1P 5B7",
    "sg:province":"ON",
    "sg:tags":[
        "pet",
        "grooming",
        "washing",
        "supply"
    ],
    "wof:name":"Super Pet",
    "wof:placetype":"venue"
},
  "geometry": {"coordinates":[-79.279274,43.771156],"type":"Point"}
}