{
  "type": "Feature",
  "properties": {
    "addr:full":"5 Marylebone Cres Richmond Hill ON L4E 2L2",
    "addr:housenumber":"5",
    "addr:postcode":"l4e 2l2",
    "addr:street":"Marylebone Cres",
    "iso:country":"CA",
    "sg:address":"5 Marylebone Cres",
    "sg:city":"Richmond Hill",
    "sg:classifiers":[
        {
            "category":"Wholesale",
            "subcategory":"Auto Parts",
            "type":"Manufacturing & Wholesale Goods"
        }
    ],
    "sg:phone":"+1 905 773 3709",
    "sg:postcode":"L4E 2L2",
    "sg:province":"ON",
    "sg:tags":[
        "automobile",
        "supply"
    ],
    "wof:name":"Corteco",
    "wof:placetype":"venue"
},
  "geometry": {"coordinates":[-79.45120199999999,43.950542],"type":"Point"}
}