{
  "type": "Feature",
  "properties": {
    "addr:full":"3700 Rue Griffith Saint-Laurent QC H4T 2B3",
    "addr:housenumber":"3700",
    "addr:postcode":"h4t 2b3",
    "addr:street":"Rue Griffith",
    "iso:country":"CA",
    "sg:address":"3700 Rue Griffith",
    "sg:city":"Saint-Laurent",
    "sg:classifiers":[
        {
            "category":"Shopping",
            "subcategory":"Computers & Home Electronics",
            "type":"Retail Goods"
        }
    ],
    "sg:phone":"+1 514 345 1441",
    "sg:postcode":"H4T 2B3",
    "sg:province":"QC",
    "sg:tags":[
        "software"
    ],
    "wof:name":"9098-4380 QC Inc",
    "wof:placetype":"venue"
},
  "geometry": {"coordinates":[-73.6972961426,45.4857635498],"type":"Point"}
}