{
  "type": "Feature",
  "properties": {
    "iso:country":"CA",
    "sg:address":"545 Boul Du Seminaire N",
    "sg:city":"Saint-Jean-Sur-Richelieu",
    "sg:classifiers":[
        {
            "category":"Travel",
            "subcategory":"Travel Agent",
            "type":"Entertainment"
        }
    ],
    "sg:phone":"+1 450 348 9291",
    "sg:postcode":"J3B 5L9",
    "sg:province":"QC",
    "sg:tags":[
        "agency",
        "bureau"
    ],
    "wof:name":"Club Voyages Eden",
    "wof:placetype":"venue"
},
  "geometry": {"coordinates":[-73.2639465332,45.3176765442],"type":"Point"}
}