{
  "type": "Feature",
  "properties": {
    "addr:full":"510 Hogarth Ave W Geraldton ON P0T 1M0",
    "addr:housenumber":"510",
    "addr:postcode":"p0t 1m0",
    "addr:street":"Hogarth Ave W",
    "iso:country":"CA",
    "sg:address":"510 Hogarth Ave W",
    "sg:city":"Geraldton",
    "sg:classifiers":[
        {
            "category":"Health Services",
            "subcategory":"Doctor",
            "type":"Services"
        }
    ],
    "sg:phone":"+1 807 854 1426",
    "sg:postcode":"P0T 1M0",
    "sg:province":"ON",
    "sg:tags":[
        "dentist"
    ],
    "wof:name":"Dzijacky, Frank DDS",
    "wof:placetype":"venue"
},
  "geometry": {"coordinates":[-86.94931800000001,49.722111],"type":"Point"}
}