{
  "type": "Feature",
  "properties": {
    "addr:full":"132 Shannon Cres SW Calgary AB T2Y 2T7",
    "addr:housenumber":"132",
    "addr:postcode":"t2y 2t7",
    "addr:street":"Shannon Cres Sw",
    "iso:country":"CA",
    "sg:address":"132 Shannon Cres SW",
    "sg:city":"Calgary",
    "sg:classifiers":[
        {
            "category":"Wholesale",
            "subcategory":"Machinery & Supplies",
            "type":"Manufacturing & Wholesale Goods"
        }
    ],
    "sg:phone":"+1 403 219 0393",
    "sg:postcode":"T2Y 2T7",
    "sg:province":"AB",
    "sg:tags":[
        "machine",
        "tool"
    ],
    "wof:name":"Gross Machinery Group",
    "wof:placetype":"venue"
},
  "geometry": {"coordinates":[-114.089027,50.910591],"type":"Point"}
}