{
  "type": "Feature",
  "properties": {
    "addr:full":"Sept-Iles QC G4R 2X1",
    "addr:postcode":"g4r 2x1",
    "iso:country":"CA",
    "sg:city":"Sept-Iles",
    "sg:classifiers":[
        {
            "category":"Personal",
            "subcategory":"Tanning Parlor",
            "type":"Services"
        }
    ],
    "sg:phone":"+1 418 968 0118",
    "sg:postcode":"G4R 2X1",
    "sg:province":"QC",
    "sg:tags":[
        "salon"
    ],
    "wof:name":"Studio Soleil Enr",
    "wof:placetype":"venue"
},
  "geometry": {"coordinates":[-66.386756897,50.2073440552],"type":"Point"}
}