{
  "type": "Feature",
  "properties": {
    "iso:country":"CA",
    "sg:address":"1820 Selkirk Ave",
    "sg:city":"Winnipeg",
    "sg:classifiers":[
        {
            "category":"Wholesale",
            "subcategory":"Machinery & Supplies",
            "type":"Manufacturing & Wholesale Goods"
        }
    ],
    "sg:phone":"+1 204 632 9040",
    "sg:postcode":"R2R 0N6",
    "sg:province":"MB",
    "sg:tags":[
        "dry wall",
        "contractor"
    ],
    "wof:name":"Ames Taping Tools of Canada",
    "wof:placetype":"venue"
},
  "geometry": {"coordinates":[-97.1995544434,49.9310836792],"type":"Point"}
}