{
  "type": "Feature",
  "properties": {
    "iso:country":"CA",
    "sg:address":"55 Rue Principale",
    "sg:city":"Saint-Adalbert",
    "sg:classifiers":[
        {
            "category":"Government",
            "subcategory":"Office",
            "type":"Public Place"
        }
    ],
    "sg:phone":"+1 418 356 5271",
    "sg:postcode":"G0R 2M0",
    "sg:province":"QC",
    "sg:tags":[
        "city",
        "hall"
    ],
    "wof:name":"St-Adalbert Municipalite",
    "wof:placetype":"venue"
},
  "geometry": {"coordinates":[-69.897277832,46.8645515442],"type":"Point"}
}