{
  "type": "Feature",
  "properties": {
    "addr:full":"32 Lakewood Blvd Winnipeg MB R2J 2M6",
    "addr:housenumber":"32",
    "addr:postcode":"r2j 2m6",
    "addr:street":"Lakewood Blvd",
    "iso:country":"CA",
    "sg:address":"32 Lakewood Blvd",
    "sg:city":"Winnipeg",
    "sg:classifiers":[
        {
            "category":"Health Services",
            "subcategory":"Doctor",
            "type":"Services"
        }
    ],
    "sg:phone":"+1 204 257 6961",
    "sg:postcode":"R2J 2M6",
    "sg:province":"MB",
    "sg:tags":[
        "dentist"
    ],
    "wof:name":"Lakewood Dental Corp",
    "wof:placetype":"venue"
},
  "geometry": {"coordinates":[-97.078926,49.854462],"type":"Point"}
}