{
  "type": "Feature",
  "properties": {
    "addr:full":"5062 Mount Albert Rd Mount Albert ON L0G 1M0",
    "addr:housenumber":"5062",
    "addr:postcode":"l0g 1m0",
    "addr:street":"Mount Albert Rd",
    "iso:country":"CA",
    "sg:address":"5062 Mount Albert Rd",
    "sg:city":"Mount Albert",
    "sg:classifiers":[
        {
            "category":"Shopping",
            "subcategory":"Crafts & Fabrics",
            "type":"Retail Goods"
        }
    ],
    "sg:phone":"+1 905 473 1033",
    "sg:postcode":"L0G 1M0",
    "sg:province":"ON",
    "sg:tags":[
        "supply"
    ],
    "wof:name":"Gemini Fibres",
    "wof:placetype":"venue"
},
  "geometry": {"coordinates":[-80.06774900000001,43.177685],"type":"Point"}
}