{
  "type": "Feature",
  "properties": {
    "addr:full":"1024 Upper Wentworth St Hamilton ON L9A 4V9",
    "addr:housenumber":"1024",
    "addr:postcode":"l9a 4v9",
    "addr:street":"Upper Wentworth St",
    "iso:country":"CA",
    "sg:address":"1024 Upper Wentworth St",
    "sg:city":"Hamilton",
    "sg:classifiers":[
        {
            "category":"Home & Garden",
            "subcategory":"Home Furnishings",
            "type":"Retail Goods"
        }
    ],
    "sg:phone":"+1 905 385 8646",
    "sg:postcode":"L9A 4V9",
    "sg:province":"ON",
    "sg:tags":[
        "venetian",
        "blind"
    ],
    "wof:name":"Blinds To Go",
    "wof:placetype":"venue"
},
  "geometry": {"coordinates":[-79.86505099999999,43.216686],"type":"Point"}
}