{
  "type": "Feature",
  "properties": {
    "addr:full":"66 Lakeview Dr Iroquois ON K0E 1K0",
    "addr:housenumber":"66",
    "addr:postcode":"k0e 1k0",
    "addr:street":"Lakeview Dr",
    "iso:country":"CA",
    "sg:address":"66 Lakeview Dr",
    "sg:city":"Iroquois",
    "sg:classifiers":[
        {
            "category":"Education",
            "subcategory":"School",
            "type":"Public Place"
        }
    ],
    "sg:phone":"+1 613 652 4580",
    "sg:postcode":"K0E 1K0",
    "sg:province":"ON",
    "wof:name":"Iroquois Public School",
    "wof:placetype":"venue"
},
  "geometry": {"coordinates":[-75.31171399999999,44.849545],"type":"Point"}
}