{
  "type": "Feature",
  "properties": {
    "addr:full":"2 Stanley Cres SW Calgary AB T2S 1G1",
    "addr:housenumber":"2",
    "addr:postcode":"t2s 1g1",
    "addr:street":"Stanley Cres Sw",
    "iso:country":"CA",
    "sg:address":"2 Stanley Cres SW",
    "sg:city":"Calgary",
    "sg:classifiers":[
        {
            "category":"Health Services",
            "subcategory":"Medical Lab",
            "type":"Services"
        }
    ],
    "sg:phone":"+1 403 270 7711",
    "sg:postcode":"T2S 1G1",
    "sg:province":"AB",
    "sg:tags":[
        "laboratory"
    ],
    "wof:name":"Kensington Dental Laboratory",
    "wof:placetype":"venue"
},
  "geometry": {"coordinates":[-114.070877075,51.0104217529],"type":"Point"}
}