{
  "type": "Feature",
  "properties": {
    "addr:full":"403 Ontario St St Catharines ON L2N 1L5",
    "addr:housenumber":"403",
    "addr:postcode":"l2n 1l5",
    "addr:street":"Ontario St",
    "iso:country":"CA",
    "sg:address":"403 Ontario St",
    "sg:city":"St Catharines",
    "sg:classifiers":[
        {
            "category":"Social Services",
            "subcategory":"Child Care",
            "type":"Services"
        }
    ],
    "sg:phone":"+1 905 934 3364",
    "sg:postcode":"L2N 1L5",
    "sg:province":"ON",
    "wof:name":"Meadowvale Nursery School",
    "wof:placetype":"venue"
},
  "geometry": {"coordinates":[-79.26653289790001,43.1830215454],"type":"Point"}
}