{
  "type": "Feature",
  "properties": {
    "addr:full":"Manseau QC G0X 1V0",
    "addr:postcode":"g0x 1v0",
    "iso:country":"CA",
    "sg:city":"Manseau",
    "sg:classifiers":[
        {
            "category":"Wholesale",
            "subcategory":"Machinery & Supplies",
            "type":"Manufacturing & Wholesale Goods"
        }
    ],
    "sg:phone":"+1 819 356 2516",
    "sg:postcode":"G0X 1V0",
    "sg:province":"QC",
    "sg:tags":[
        "farm",
        "equipment"
    ],
    "wof:name":"Garage Gaston Soucy",
    "wof:placetype":"venue"
},
  "geometry": {"coordinates":[-72.0048370361,46.370300293],"type":"Point"}
}