{
  "type": "Feature",
  "properties": {
    "iso:country":"CA",
    "sg:city":"Terrace",
    "sg:classifiers":[
        {
            "category":"Shopping",
            "subcategory":"Bicycles & Sporting Goods",
            "type":"Retail Goods"
        }
    ],
    "sg:phone":"+1 250 635 5225",
    "sg:postcode":"V8G 1T2",
    "sg:province":"BC",
    "wof:name":"Mc Bike Shop",
    "wof:placetype":"venue"
},
  "geometry": {"coordinates":[-128.59396362300001,54.5178642273],"type":"Point"}
}