{
  "type": "Feature",
  "properties": {
    "addr:full":"485 Rue Lavoie Vanier QC G1M 2V2",
    "addr:housenumber":"485",
    "addr:postcode":"g1m 2v2",
    "addr:street":"Rue Lavoie",
    "iso:country":"CA",
    "sg:address":"485 Rue Lavoie",
    "sg:city":"Vanier",
    "sg:classifiers":[
        {
            "category":"Manufacturing",
            "subcategory":"Food",
            "type":"Manufacturing & Wholesale Goods"
        }
    ],
    "sg:phone":"+1 418 687 2840",
    "sg:postcode":"G1M 2V2",
    "sg:province":"QC",
    "sg:tags":[
        "product",
        "meat",
        "manufacturer"
    ],
    "wof:name":"Charcuterie LA Tour Eiffel Inc",
    "wof:placetype":"venue"
},
  "geometry": {"coordinates":[-71.27658099999999,46.820599],"type":"Point"}
}