{
  "type": "Feature",
  "properties": {
    "addr:full":"635 Oster Lane Concord ON L4K 2B9",
    "addr:housenumber":"635",
    "addr:postcode":"l4k 2b9",
    "addr:street":"Oster Lane",
    "iso:country":"CA",
    "sg:address":"635 Oster Lane",
    "sg:city":"Concord",
    "sg:classifiers":[
        {
            "category":"Manufacturing",
            "subcategory":"Furniture",
            "type":"Manufacturing & Wholesale Goods"
        }
    ],
    "sg:phone":"+1 905 738 8880",
    "sg:postcode":"L4K 2B9",
    "sg:province":"ON",
    "sg:tags":[
        "fixture",
        "store"
    ],
    "wof:name":"Tnt Metal Fabricating Inc",
    "wof:placetype":"venue"
},
  "geometry": {"coordinates":[-79.49505615229999,43.8061523438],"type":"Point"}
}