{
  "type": "Feature",
  "properties": {
    "addr:full":"779 Mccallum Dr Victoria BC V9B 6A2",
    "addr:housenumber":"779",
    "addr:postcode":"v9b 6a2",
    "addr:street":"Mccallum Dr",
    "iso:country":"CA",
    "sg:address":"779 Mccallum Dr",
    "sg:city":"Victoria",
    "sg:classifiers":[
        {
            "category":"Shopping",
            "subcategory":"Computers & Home Electronics",
            "type":"Retail Goods"
        }
    ],
    "sg:phone":"+1 250 391 4514",
    "sg:postcode":"V9B 6A2",
    "sg:province":"BC",
    "sg:tags":[
        "equipment",
        "electronic",
        "electric",
        "supply"
    ],
    "wof:name":"Future Shop",
    "wof:placetype":"venue"
},
  "geometry": {"coordinates":[-123.36451700000001,48.428314],"type":"Point"}
}