{
  "type": "Feature",
  "properties": {
    "addr:full":"349 25 St SE Calgary AB T2A 7H8",
    "addr:housenumber":"25",
    "addr:postcode":"t2a 7h8",
    "addr:street":"349;St Se",
    "iso:country":"CA",
    "sg:address":"349 25 St SE",
    "sg:city":"Calgary",
    "sg:classifiers":[
        {
            "category":"Shopping",
            "subcategory":"Computers & Home Electronics",
            "type":"Retail Goods"
        }
    ],
    "sg:phone":"+1 403 248 3883",
    "sg:postcode":"T2A 7H8",
    "sg:province":"AB",
    "sg:tags":[
        "equipment",
        "dealer"
    ],
    "wof:name":"Toshiba of Canada Ltd",
    "wof:placetype":"venue"
},
  "geometry": {"coordinates":[-114.000084,51.048496],"type":"Point"}
}