{
  "type": "Feature",
  "properties": {
    "addr:full":"5772 Rue Marie-Victorin Sainte-Croix QC G0S 2H0",
    "addr:housenumber":"5772",
    "addr:postcode":"g0s 2h0",
    "addr:street":"Rue Marie-Victorin",
    "iso:country":"CA",
    "sg:address":"5772 Rue Marie-Victorin",
    "sg:city":"Sainte-Croix",
    "sg:classifiers":[
        {
            "category":"Professional",
            "subcategory":"Printing & Photocopies",
            "type":"Services"
        }
    ],
    "sg:phone":"+1 418 926 3970",
    "sg:postcode":"G0S 2H0",
    "sg:province":"QC",
    "sg:tags":[
        "duplicating",
        "copying"
    ],
    "wof:name":"Document Express",
    "wof:placetype":"venue"
},
  "geometry": {"coordinates":[-71.709198,46.622581],"type":"Point"}
}