{
  "type": "Feature",
  "properties": {
    "addr:full":"Trail BC V1R 4A4",
    "addr:postcode":"bc v1r 4a4",
    "addr:street":"Trail",
    "iso:country":"CA",
    "sg:city":"Trail",
    "sg:classifiers":[
        {
            "category":"Organizations",
            "subcategory":"Professional Association",
            "type":"Services"
        }
    ],
    "sg:phone":"+1 250 368 3144",
    "sg:postcode":"V1R 4A4",
    "sg:province":"BC",
    "wof:name":"Chamber of Commerce",
    "wof:placetype":"venue"
},
  "geometry": {"coordinates":[-117.708892822,49.0970191956],"type":"Point"}
}