{
  "type": "Feature",
  "properties": {
    "addr:full":"4933 Victoria Dr Vancouver BC V5P 3T7",
    "addr:housenumber":"4933",
    "addr:postcode":"v5p 3t7",
    "addr:street":"Victoria Dr",
    "iso:country":"CA",
    "sg:address":"4933 Victoria Dr",
    "sg:city":"Vancouver",
    "sg:classifiers":[
        {
            "category":"Autos & Motor Vehicles",
            "subcategory":"Fuel & Gas Station",
            "type":"Retail Goods"
        }
    ],
    "sg:phone":"+1 604 327 2211",
    "sg:postcode":"V5P 3T7",
    "sg:province":"BC",
    "sg:tags":[
        "oil"
    ],
    "wof:name":"Victoria Drive Mohawk",
    "wof:placetype":"venue"
},
  "geometry": {"coordinates":[-123.065506,49.239746],"type":"Point"}
}