{
  "type": "Feature",
  "properties": {
    "addr:full":"536 Rue DE LA Riviere Cowansville QC J2K 3G6",
    "addr:housenumber":"536",
    "addr:postcode":"j2k 3g6",
    "addr:street":"Rue De La Riviere",
    "iso:country":"CA",
    "sg:address":"536 Rue DE LA Riviere",
    "sg:city":"Cowansville",
    "sg:classifiers":[
        {
            "category":"Manufacturing",
            "subcategory":"Chemicals & Compounds",
            "type":"Manufacturing & Wholesale Goods"
        }
    ],
    "sg:phone":"+1 450 263 1848",
    "sg:postcode":"J2K 3G6",
    "sg:province":"QC",
    "sg:tags":[
        "paint"
    ],
    "wof:name":"Pepin Industries",
    "wof:placetype":"venue"
},
  "geometry": {"coordinates":[-72.79070299999999,45.210793],"type":"Point"}
}