{
  "type": "Feature",
  "properties": {
    "addr:full":"1773 Rue Brulotte O Fleurimont QC J1E 3P4",
    "addr:housenumber":"1773",
    "addr:postcode":"j1e 3p4",
    "addr:street":"Rue Brulotte O Fleurimont",
    "iso:country":"CA",
    "sg:address":"1773 Rue Brulotte O",
    "sg:city":"Fleurimont",
    "sg:classifiers":[
        {
            "category":"Personal",
            "subcategory":"Beauty Salon",
            "type":"Services"
        }
    ],
    "sg:phone":"+1 819 562 9587",
    "sg:postcode":"J1E 3P4",
    "sg:province":"QC",
    "wof:name":"Salon Coif-Mode Elle & Lui Enr",
    "wof:placetype":"venue"
},
  "geometry": {"coordinates":[-71.874985,45.428391],"type":"Point"}
}