{
  "type": "Feature",
  "properties": {
    "addr:full":"Winnipeg MB R2J 3K4",
    "addr:postcode":"r2j 3k4",
    "iso:country":"CA",
    "sg:city":"Winnipeg",
    "sg:classifiers":[
        {
            "category":"Wholesale",
            "subcategory":"Office Equipment",
            "type":"Manufacturing & Wholesale Goods"
        }
    ],
    "sg:phone":"+1 204 663 6240",
    "sg:postcode":"R2J 3K4",
    "sg:province":"MB",
    "sg:tags":[
        "register",
        "cash",
        "supply"
    ],
    "wof:name":"Retail Management Systems",
    "wof:placetype":"venue"
},
  "geometry": {"coordinates":[-97.071518,49.876797],"type":"Point"}
}