{
  "type": "Feature",
  "properties": {
    "addr:full":"208 54 St Delta BC V4M 3G5",
    "addr:housenumber":"208 54",
    "addr:postcode":"v4m 3g5",
    "addr:street":"St",
    "iso:country":"CA",
    "sg:address":"208 54 St",
    "sg:city":"Delta",
    "sg:classifiers":[
        {
            "category":"Shopping",
            "type":"Retail Goods"
        }
    ],
    "sg:phone":"+1 604 943 3034",
    "sg:postcode":"V4M 3G5",
    "sg:province":"BC",
    "sg:tags":[
        "equipment",
        "wine",
        "supply"
    ],
    "wof:name":"Pebble Hill Industries Inc",
    "wof:placetype":"venue"
},
  "geometry": {"coordinates":[-123.07390594500001,49.0068664551],"type":"Point"}
}