{
  "type": "Feature",
  "properties": {
    "addr:full":"790 Boul Des Seigneurs Terrebonne QC J6W 1T7",
    "addr:housenumber":"790",
    "addr:postcode":"j6w 1t7",
    "addr:street":"Boul Des Seigneurs",
    "iso:country":"CA",
    "sg:address":"790 Boul Des Seigneurs",
    "sg:city":"Terrebonne",
    "sg:classifiers":[
        {
            "category":"Professional",
            "subcategory":"Accounting & Tax Preparation",
            "type":"Services"
        }
    ],
    "sg:phone":"+1 450 471 8173",
    "sg:postcode":"J6W 1T7",
    "sg:province":"QC",
    "sg:tags":[
        "accountant"
    ],
    "wof:name":"Belzile, Jacques CA",
    "wof:placetype":"venue"
},
  "geometry": {"coordinates":[-73.638245,45.702557],"type":"Point"}
}