{
  "type": "Feature",
  "properties": {
    "addr:full":"31 Main St Kagawong ON P0P 1J0",
    "addr:housenumber":"31",
    "addr:postcode":"p0p 1j0",
    "addr:street":"Main St",
    "iso:country":"CA",
    "sg:address":"31 Main St",
    "sg:city":"Kagawong",
    "sg:classifiers":[
        {
            "category":"Building & Trades",
            "subcategory":"Construction",
            "type":"Services"
        }
    ],
    "sg:phone":"+1 705 282 2593",
    "sg:postcode":"P0P 1J0",
    "sg:province":"ON",
    "sg:tags":[
        "contractor"
    ],
    "wof:name":"Bridal Veil Esso",
    "wof:placetype":"venue"
},
  "geometry": {"coordinates":[-82.2756195068,45.9125404358],"type":"Point"}
}