{
  "type": "Feature",
  "properties": {
    "addr:full":"Surrey BC V3W 3B2",
    "addr:postcode":"v3w 3b2",
    "iso:country":"CA",
    "sg:city":"Surrey",
    "sg:classifiers":[
        {
            "category":"Building & Trades",
            "subcategory":"Construction",
            "type":"Services"
        }
    ],
    "sg:phone":"+1 604 501 0828",
    "sg:postcode":"V3W 3B2",
    "sg:province":"BC",
    "sg:tags":[
        "fire",
        "restoration",
        "damage"
    ],
    "wof:name":"On Side Restoration Svc",
    "wof:placetype":"venue"
},
  "geometry": {"coordinates":[-122.863693,49.148033],"type":"Point"}
}