{
  "type": "Feature",
  "properties": {
    "iso:country":"CA",
    "sg:address":"433 Dunlop St W",
    "sg:city":"Barrie",
    "sg:classifiers":[
        {
            "category":"Retail",
            "subcategory":"Auto Repair",
            "type":"Services"
        }
    ],
    "sg:phone":"+1 705 728 2472",
    "sg:postcode":"L4N 1C3",
    "sg:province":"ON",
    "sg:tags":[
        "transmission",
        "automobile",
        "repairing"
    ],
    "wof:name":"Barrie Transmission",
    "wof:placetype":"venue"
},
  "geometry": {"coordinates":[-79.718124,44.376759],"type":"Point"}
}