{
  "type": "Feature",
  "properties": {
    "iso:country":"CA",
    "sg:address":"79 Boul Sainte-Madeleine",
    "sg:city":"Cap-DE-LA-Madeleine",
    "sg:classifiers":[
        {
            "category":"Restaurant",
            "type":"Food & Drink"
        }
    ],
    "sg:phone":"+1 819 376 4424",
    "sg:postcode":"G8T 3K9",
    "sg:province":"QC",
    "wof:name":"Rotisseries Ti-Coq",
    "wof:placetype":"venue"
},
  "geometry": {"coordinates":[-72.512573,46.36396],"type":"Point"}
}