{
  "type": "Feature",
  "properties": {
    "addr:full":"709 Cote Joyeuse Saint-Raymond QC G3L 4B2",
    "addr:housenumber":"709",
    "addr:postcode":"g3l 4b2",
    "addr:street":"Cote Joyeuse",
    "iso:country":"CA",
    "sg:address":"709 Cote Joyeuse",
    "sg:city":"Saint-Raymond",
    "sg:classifiers":[
        {
            "category":"Retail",
            "subcategory":"Auto Repair",
            "type":"Services"
        }
    ],
    "sg:phone":"+1 418 337 8400",
    "sg:postcode":"G3L 4B2",
    "sg:province":"QC",
    "sg:tags":[
        "body",
        "automobile",
        "painting"
    ],
    "wof:name":"Carrossier Pro-Art Inc",
    "wof:placetype":"venue"
},
  "geometry": {"coordinates":[-71.83428192140001,46.8716011047],"type":"Point"}
}