{
  "type": "Feature",
  "properties": {
    "addr:full":"Kitchener ON N2M 5H5",
    "addr:postcode":"n2m 5h5",
    "iso:country":"CA",
    "sg:city":"Kitchener",
    "sg:classifiers":[
        {
            "category":"Real Estate",
            "subcategory":"Real Estate Agent",
            "type":"Services"
        }
    ],
    "sg:phone":"+1 519 579 6401",
    "sg:postcode":"N2M 5H5",
    "sg:province":"ON",
    "sg:tags":[
        "housing"
    ],
    "wof:name":"Hislacan Homes",
    "wof:placetype":"venue"
},
  "geometry": {"coordinates":[-80.5222854614,43.4315605164],"type":"Point"}
}