{
  "type": "Feature",
  "properties": {
    "addr:full":"Cargill ON N0G 1J0",
    "addr:postcode":"n0g 1j0",
    "iso:country":"CA",
    "sg:city":"Cargill",
    "sg:classifiers":[
        {
            "category":"Government",
            "subcategory":"Office",
            "type":"Public Place"
        }
    ],
    "sg:phone":"+1 519 366 2226",
    "sg:postcode":"N0G 1J0",
    "sg:province":"ON",
    "sg:tags":[
        "village"
    ],
    "wof:name":"Greenock Garage",
    "wof:placetype":"venue"
},
  "geometry": {"coordinates":[-81.2453079224,44.1960983276],"type":"Point"}
}