{
  "type": "Feature",
  "properties": {
    "addr:full":"417 Broadway Ave Killarney MB R0K 1G0",
    "addr:housenumber":"417",
    "addr:postcode":"r0k 1g0",
    "addr:street":"Broadway Ave",
    "iso:country":"CA",
    "sg:address":"417 Broadway Ave",
    "sg:city":"Killarney",
    "sg:classifiers":[
        {
            "category":"Government",
            "subcategory":"Office",
            "type":"Public Place"
        }
    ],
    "sg:phone":"+1 204 523 7261",
    "sg:postcode":"R0K 1G0",
    "sg:province":"MB",
    "sg:tags":[
        "village"
    ],
    "wof:name":"Killarney Area Planning Dist",
    "wof:placetype":"venue"
},
  "geometry": {"coordinates":[-99.665115,49.182182],"type":"Point"}
}