{
  "type": "Feature",
  "properties": {
    "addr:full":"17 Pine St Stratford ON N5A 1W2",
    "addr:housenumber":"17",
    "addr:postcode":"n5a 1w2",
    "addr:street":"Pine St",
    "iso:country":"CA",
    "sg:address":"17 Pine St",
    "sg:city":"Stratford",
    "sg:classifiers":[
        {
            "category":"Farming",
            "subcategory":"Poultry Farm",
            "type":"Manufacturing & Wholesale Goods"
        }
    ],
    "sg:phone":"+1 519 275 2240",
    "sg:postcode":"N5A 1W2",
    "sg:province":"ON",
    "wof:name":"Stratford Chick Hatchery",
    "wof:placetype":"venue"
},
  "geometry": {"coordinates":[-80.992805,43.356613],"type":"Point"}
}