{
  "type": "Feature",
  "properties": {
    "addr:full":"York ON M6B 3V1",
    "addr:postcode":"m6b 3v1",
    "iso:country":"CA",
    "sg:city":"York",
    "sg:classifiers":[
        {
            "category":"Building & Trades",
            "subcategory":"Plumbing",
            "type":"Services"
        }
    ],
    "sg:phone":"+1 416 787 7231",
    "sg:postcode":"M6B 3V1",
    "sg:province":"ON",
    "sg:tags":[
        "contractor"
    ],
    "wof:name":"Bob Cude Plumbing & Heating",
    "wof:placetype":"venue"
},
  "geometry": {"coordinates":[-79.45449829099999,43.6996192932],"type":"Point"}
}