{
  "type": "Feature",
  "properties": {
    "addr:full":"261 Belsize Dr Toronto ON M4S 1M5",
    "addr:housenumber":"261",
    "addr:postcode":"m4s 1m5",
    "addr:street":"Belsize Dr",
    "iso:country":"CA",
    "sg:address":"261 Belsize Dr",
    "sg:city":"Toronto",
    "sg:classifiers":[
        {
            "category":"Professional",
            "subcategory":"Business Services",
            "type":"Services"
        }
    ],
    "sg:phone":"+1 416 485 2251",
    "sg:postcode":"M4S 1M5",
    "sg:province":"ON",
    "sg:tags":[
        "interior",
        "consultant",
        "design",
        "decorator"
    ],
    "wof:name":"Interior Dressings By Janelle",
    "wof:placetype":"venue"
},
  "geometry": {"coordinates":[-79.3842544556,43.7030487061],"type":"Point"}
}