{
  "type": "Feature",
  "properties": {
    "addr:full":"Scarborough ON M1H 1A8",
    "addr:postcode":"m1h 1a8",
    "iso:country":"CA",
    "sg:city":"Scarborough",
    "sg:classifiers":[
        {
            "category":"Manufacturing",
            "subcategory":"Signs",
            "type":"Manufacturing & Wholesale Goods"
        }
    ],
    "sg:phone":"+1 416 438 9811",
    "sg:postcode":"M1H 1A8",
    "sg:province":"ON",
    "wof:name":"Signs Now",
    "wof:placetype":"venue"
},
  "geometry": {"coordinates":[-79.234085083,43.7578125],"type":"Point"}
}