{
  "type": "Feature",
  "properties": {
    "iso:country":"CA",
    "sg:address":"1901 1st Ave W",
    "sg:city":"Vancouver",
    "sg:classifiers":[
        {
            "category":"Food & Beverages",
            "subcategory":"Fruits & Vegetables",
            "type":"Retail Goods"
        }
    ],
    "sg:phone":"+1 604 731 2818",
    "sg:postcode":"V6J 1G7",
    "sg:province":"BC",
    "sg:tags":[
        "produce"
    ],
    "wof:name":"Central Gourmet Produce Ltd",
    "wof:placetype":"venue"
},
  "geometry": {"coordinates":[-123.14810900000001,49.27079],"type":"Point"}
}