{
  "type": "Feature",
  "properties": {
    "addr:full":"14 Rue Leger Sherbrooke QC J1L 1W1",
    "addr:housenumber":"14",
    "addr:postcode":"j1l 1w1",
    "addr:street":"Rue Leger",
    "iso:country":"CA",
    "sg:address":"14 Rue Leger",
    "sg:city":"Sherbrooke",
    "sg:classifiers":[
        {
            "category":"Restaurant",
            "type":"Food & Drink"
        }
    ],
    "sg:phone":"+1 819 564 2606",
    "sg:postcode":"J1L 1W1",
    "sg:province":"QC",
    "sg:tags":[
        "pub"
    ],
    "wof:name":"Brasserie LA Seigneurie",
    "wof:placetype":"venue"
},
  "geometry": {"coordinates":[-71.9636459351,45.3860778809],"type":"Point"}
}