{
  "type": "Feature",
  "properties": {
    "addr:full":"66 Rothesay Dr Kanata ON K2L 2X1",
    "addr:housenumber":"66",
    "addr:postcode":"k2l 2x1",
    "addr:street":"Rothesay Dr",
    "iso:country":"CA",
    "sg:address":"66 Rothesay Dr",
    "sg:city":"Kanata",
    "sg:classifiers":[
        {
            "category":"Manufacturing",
            "subcategory":"Metals",
            "type":"Manufacturing & Wholesale Goods"
        }
    ],
    "sg:phone":"+1 613 797 4353",
    "sg:postcode":"K2L 2X1",
    "sg:province":"ON",
    "sg:tags":[
        "door"
    ],
    "wof:name":"Can Built Door & Trim",
    "wof:placetype":"venue"
},
  "geometry": {"coordinates":[-75.872231,45.291252],"type":"Point"}
}