{
  "type": "Feature",
  "properties": {
    "addr:full":"8140 No. 2 Rd Richmond BC V7C 5J9",
    "addr:postcode":"8140;bc v7c 5j9",
    "addr:street":"2 Rd",
    "iso:country":"CA",
    "sg:address":"8140 No. 2 Rd",
    "sg:city":"Richmond",
    "sg:classifiers":[
        {
            "category":"Restaurant",
            "type":"Food & Drink"
        }
    ],
    "sg:phone":"+1 604 718 1100",
    "sg:postcode":"V7C 5J9",
    "sg:province":"BC",
    "wof:name":"Mc Donald's",
    "wof:placetype":"venue"
},
  "geometry": {"coordinates":[-123.15877533,49.1546134949],"type":"Point"}
}