{
  "type": "Feature",
  "properties": {
    "addr:full":"Scarborough ON M1X 1M1",
    "addr:postcode":"m1x 1m1",
    "iso:country":"CA",
    "sg:city":"Scarborough",
    "sg:classifiers":[
        {
            "category":"Shopping",
            "subcategory":"Department Store",
            "type":"Retail Goods"
        }
    ],
    "sg:phone":"+1 905 479 9517",
    "sg:postcode":"M1X 1M1",
    "sg:province":"ON",
    "sg:tags":[
        "shop"
    ],
    "wof:name":"Sonia Enterprise",
    "wof:placetype":"venue"
},
  "geometry": {"coordinates":[-79.24746704099999,43.8280105591],"type":"Point"}
}