{
  "type": "Feature",
  "properties": {
    "addr:full":"20241 68 Ave Langley BC V2Y 1P7",
    "addr:housenumber":"20241",
    "addr:postcode":"v2y 1p7",
    "addr:street":"68 Ave",
    "iso:country":"CA",
    "sg:address":"20241 68 Ave",
    "sg:city":"Langley",
    "sg:classifiers":[
        {
            "category":"Organizations",
            "subcategory":"Religious Organization",
            "type":"Services"
        }
    ],
    "sg:phone":"+1 604 534 0004",
    "sg:postcode":"V2Y 1P7",
    "sg:province":"BC",
    "sg:tags":[
        "church"
    ],
    "wof:name":"Jehovah's Witnesses",
    "wof:placetype":"venue"
},
  "geometry": {"coordinates":[-122.661568,49.126328],"type":"Point"}
}