{
  "type": "Feature",
  "properties": {
    "addr:full":"4205 23 Ave NW Edmonton AB T6L 5Z8",
    "addr:housenumber":"4205",
    "addr:postcode":"t6l 5z8",
    "addr:street":"23 Ave Nw",
    "iso:country":"CA",
    "sg:address":"4205 23 Ave NW",
    "sg:city":"Edmonton",
    "sg:classifiers":[
        {
            "category":"Food & Beverages",
            "subcategory":"Groceries & Convenience Stores",
            "type":"Retail Goods"
        }
    ],
    "sg:phone":"+1 780 414 6517",
    "sg:postcode":"T6L 5Z8",
    "sg:province":"AB",
    "sg:tags":[
        "grocer"
    ],
    "wof:name":"Daly Grove Mini Mart",
    "wof:placetype":"venue"
},
  "geometry": {"coordinates":[-113.404976,53.454712],"type":"Point"}
}