{
  "type": "Feature",
  "properties": {
    "addr:full":"23 Easton Crt Ajax ON L1S 3H9",
    "addr:housenumber":"23",
    "addr:postcode":"l1s 3h9",
    "addr:street":"Easton Crt",
    "iso:country":"CA",
    "sg:address":"23 Easton Crt",
    "sg:city":"Ajax",
    "sg:classifiers":[
        {
            "category":"Wholesale",
            "subcategory":"Electrical",
            "type":"Manufacturing & Wholesale Goods"
        }
    ],
    "sg:phone":"+1 905 428 2524",
    "sg:postcode":"L1S 3H9",
    "sg:province":"ON",
    "sg:tags":[
        "fire",
        "equipment",
        "protection"
    ],
    "wof:name":"Double C Safety",
    "wof:placetype":"venue"
},
  "geometry": {"coordinates":[-79.01736450200001,43.8284759521],"type":"Point"}
}