{
  "type": "Feature",
  "properties": {
    "addr:full":"1073 Av Laurier O Outremont QC H2V 2L2",
    "addr:housenumber":"1073",
    "addr:postcode":"h2v 2l2",
    "addr:street":"Av Laurier O",
    "iso:country":"CA",
    "sg:address":"1073 Av Laurier O",
    "sg:city":"Outremont",
    "sg:classifiers":[
        {
            "category":"Shopping",
            "subcategory":"Clothing, Apparel, & Fashions",
            "type":"Retail Goods"
        }
    ],
    "sg:phone":"+1 514 277 5151",
    "sg:postcode":"H2V 2L2",
    "sg:province":"QC",
    "sg:tags":[
        "boutique",
        "kitchen",
        "accessory"
    ],
    "wof:name":"Maison D'Emilie",
    "wof:placetype":"venue"
},
  "geometry": {"coordinates":[-73.5972518921,45.517742157],"type":"Point"}
}