{
  "type": "Feature",
  "properties": {
    "iso:country":"CA",
    "sg:address":"5 Park St",
    "sg:city":"Brockville",
    "sg:classifiers":[
        {
            "category":"Home & Garden",
            "subcategory":"Household Appliances",
            "type":"Retail Goods"
        }
    ],
    "sg:phone":"+1 613 342 2532",
    "sg:postcode":"K6V 2G1",
    "sg:province":"ON",
    "wof:name":"Electric Appliance Svc Ctr",
    "wof:placetype":"venue"
},
  "geometry": {"coordinates":[-75.679397583,44.5916023254],"type":"Point"}
}