{
  "type": "Feature",
  "properties": {
    "addr:full":"1370 Dalhousie Dr Kamloops BC V2C 5P7",
    "addr:housenumber":"1370",
    "addr:postcode":"bc v2c 5p7",
    "addr:street":"Dalhousie Dr",
    "iso:country":"CA",
    "sg:address":"1370 Dalhousie Dr",
    "sg:city":"Kamloops",
    "sg:classifiers":[
        {
            "category":"Building & Trades",
            "subcategory":"Construction",
            "type":"Services"
        }
    ],
    "sg:phone":"+1 250 374 4431",
    "sg:postcode":"V2C 5P7",
    "sg:province":"BC",
    "sg:tags":[
        "planning",
        "remodeling",
        "maker",
        "kitchen",
        "cabinet"
    ],
    "wof:name":"Mastercraft Cabinets Ltd",
    "wof:placetype":"venue"
},
  "geometry": {"coordinates":[-120.362717,50.66151],"type":"Point"}
}