{
  "type": "Feature",
  "properties": {
    "addr:full":"12 Pinsonneault Rue Sherrington QC J0L 2N0",
    "addr:housenumber":"12",
    "addr:postcode":"j0l 2n0",
    "addr:street":"Rue Sherrington",
    "iso:country":"CA",
    "sg:address":"12 Pinsonneault Rue",
    "sg:city":"Sherrington",
    "sg:classifiers":[
        {
            "category":"Retail",
            "subcategory":"Auto Repair",
            "type":"Services"
        }
    ],
    "sg:phone":"+1 450 454 6776",
    "sg:postcode":"J0L 2N0",
    "sg:province":"QC",
    "sg:tags":[
        "repairing",
        "automobile"
    ],
    "wof:name":"Garage Marcel Beaudin Enr",
    "wof:placetype":"venue"
},
  "geometry": {"coordinates":[-73.52572600000001,45.167347],"type":"Point"}
}