{
  "type": "Feature",
  "properties": {
    "addr:full":"Enderby BC V0E 1V0",
    "addr:postcode":"v0e 1v0",
    "iso:country":"CA",
    "sg:city":"Enderby",
    "sg:classifiers":[
        {
            "category":"Food & Beverages",
            "subcategory":"Bakery",
            "type":"Retail Goods"
        }
    ],
    "sg:phone":"+1 250 838 7234",
    "sg:postcode":"V0E 1V0",
    "sg:province":"BC",
    "sg:tags":[
        "baker"
    ],
    "wof:name":"Sutherland's Bakery",
    "wof:placetype":"venue"
},
  "geometry": {"coordinates":[-119.141373,50.556763],"type":"Point"}
}