{
  "type": "Feature",
  "properties": {
    "addr:full":"Saint-Sylvestre QC G0S 3C0",
    "addr:postcode":"g0s 3c0",
    "iso:country":"CA",
    "sg:city":"Saint-Sylvestre",
    "sg:classifiers":[
        {
            "category":"Personal",
            "subcategory":"Beauty Salon",
            "type":"Services"
        }
    ],
    "sg:phone":"+1 418 596 2009",
    "sg:postcode":"G0S 3C0",
    "sg:province":"QC",
    "wof:name":"Salon DE Coiffure Lorry",
    "wof:placetype":"venue"
},
  "geometry": {"coordinates":[-71.226685,46.364452],"type":"Point"}
}