{
  "type": "Feature",
  "properties": {
    "iso:country":"CA",
    "sg:address":"3747 Boul Harvey",
    "sg:city":"Jonquiere",
    "sg:classifiers":[
        {
            "category":"Home & Garden",
            "subcategory":"Building Materials",
            "type":"Retail Goods"
        }
    ],
    "sg:phone":"+1 418 695 4844",
    "sg:postcode":"G7X 3A4",
    "sg:province":"QC",
    "sg:tags":[
        "windows",
        "door"
    ],
    "wof:name":"Fenetres Agm Inc",
    "wof:placetype":"venue"
},
  "geometry": {"coordinates":[-71.24239349370001,48.412651062],"type":"Point"}
}