{
  "type": "Feature",
  "properties": {
    "addr:full":"Calgary AB T2X 3J3",
    "addr:postcode":"t2x 3j3",
    "iso:country":"CA",
    "sg:city":"Calgary",
    "sg:classifiers":[
        {
            "category":"Professional",
            "subcategory":"Lawyer & Legal Services",
            "type":"Services"
        }
    ],
    "sg:phone":"+1 403 278 9411",
    "sg:postcode":"T2X 3J3",
    "sg:province":"AB",
    "sg:tags":[
        "attorney"
    ],
    "wof:name":"Mc Leod & CO",
    "wof:placetype":"venue"
},
  "geometry": {"coordinates":[-114.070404053,50.9237594604],"type":"Point"}
}