{
  "type": "Feature",
  "properties": {
    "addr:full":"157 Prince Edward St Saint John NB E2L 3S3",
    "addr:housenumber":"157",
    "addr:postcode":"nb e2l 3s3",
    "addr:street":"Prince Edward St",
    "iso:country":"CA",
    "sg:address":"157 Prince Edward St",
    "sg:city":"Saint John",
    "sg:classifiers":[
        {
            "category":"Manufacturing",
            "subcategory":"Building Materials",
            "type":"Manufacturing & Wholesale Goods"
        }
    ],
    "sg:phone":"+1 506 632 9323",
    "sg:postcode":"E2L 3S3",
    "sg:province":"NB",
    "sg:tags":[
        "frame",
        "door"
    ],
    "wof:name":"Baytown Hardware Ltd",
    "wof:placetype":"venue"
},
  "geometry": {"coordinates":[-66.05401611329999,45.277961731],"type":"Point"}
}