{
  "type": "Feature",
  "properties": {
    "addr:full":"69 Third Ave E Flin Flon MB R8A 0W8",
    "addr:housenumber":"69",
    "addr:postcode":"r8a 0w8",
    "addr:street":"Third Ave E Flin Flon",
    "iso:country":"CA",
    "sg:address":"69 Third Ave E",
    "sg:city":"Flin Flon",
    "sg:classifiers":[
        {
            "category":"Restaurant",
            "type":"Food & Drink"
        }
    ],
    "sg:phone":"+1 204 687 6078",
    "sg:postcode":"R8A 0W8",
    "sg:province":"MB",
    "wof:name":"Kfc",
    "wof:placetype":"venue"
},
  "geometry": {"coordinates":[-101.86378499999999,54.768147],"type":"Point"}
}