{
  "type": "Feature",
  "properties": {
    "addr:full":"436 Rte 133 Pike River QC J0J 1P0",
    "addr:housenumber":"436",
    "addr:postcode":"j0j 1p0",
    "addr:street":"Rte 133 Pike",
    "iso:country":"CA",
    "sg:address":"436 Rte 133",
    "sg:city":"Pike River",
    "sg:classifiers":[
        {
            "category":"Building & Trades",
            "subcategory":"Plumbing",
            "type":"Services"
        }
    ],
    "sg:phone":"+1 450 248 7810",
    "sg:postcode":"J0J 1P0",
    "sg:province":"QC",
    "sg:tags":[
        "oil",
        "heating",
        "contractor"
    ],
    "wof:name":"Sonic",
    "wof:placetype":"venue"
},
  "geometry": {"coordinates":[-73.07347900000001,45.124901],"type":"Point"}
}