{
  "type": "Feature",
  "properties": {
    "iso:country":"CA",
    "sg:address":"80 Glen Shields Ave",
    "sg:city":"Concord",
    "sg:classifiers":[
        {
            "category":"Recreation",
            "type":"Entertainment"
        }
    ],
    "sg:phone":"+1 905 738 1616",
    "sg:postcode":"L4K 1T7",
    "sg:province":"ON",
    "sg:tags":[
        "martial",
        "arts",
        "instruction"
    ],
    "wof:name":"Academy of Traditional",
    "wof:placetype":"venue"
},
  "geometry": {"coordinates":[-79.477562,43.791615],"type":"Point"}
}