{
  "type": "Feature",
  "properties": {
    "iso:country":"CA",
    "sg:address":"1935 Wilson Ave",
    "sg:city":"North York",
    "sg:classifiers":[
        {
            "category":"Professional",
            "subcategory":"Employment Agencies",
            "type":"Services"
        }
    ],
    "sg:phone":"+1 416 743 5026",
    "sg:postcode":"M9M 1A9",
    "sg:province":"ON",
    "sg:tags":[
        "opportunity"
    ],
    "wof:name":"Personnel Temp Network",
    "wof:placetype":"venue"
},
  "geometry": {"coordinates":[-79.531052,43.715656],"type":"Point"}
}