{
  "type": "Feature",
  "properties": {
    "addr:full":"1665 Rue Rachel E Montreal QC H2J 2K6",
    "addr:housenumber":"1665",
    "addr:postcode":"h2j 2k6",
    "addr:street":"Rue Rachel E",
    "iso:country":"CA",
    "sg:address":"1665 Rue Rachel E",
    "sg:city":"Montreal",
    "sg:classifiers":[
        {
            "category":"Travel",
            "subcategory":"Travel Agent",
            "type":"Entertainment"
        }
    ],
    "sg:phone":"+1 514 529 9559",
    "sg:postcode":"H2J 2K6",
    "sg:province":"QC",
    "sg:tags":[
        "tours"
    ],
    "wof:name":"Rvi Club Vacances",
    "wof:placetype":"venue"
},
  "geometry": {"coordinates":[-73.5700836182,45.5301513672],"type":"Point"}
}