{
  "type": "Feature",
  "properties": {
    "addr:full":"1357 Rte DE LA Seigneurie Saint-Roch-Des-Aulnaies QC G0R 4E0",
    "addr:housenumber":"1357",
    "addr:postcode":"g0r 4e0",
    "addr:street":"Rte De La Seigneurie",
    "iso:country":"CA",
    "sg:address":"1357 Rte DE LA Seigneurie",
    "sg:city":"Saint-Roch-Des-Aulnaies",
    "sg:classifiers":[
        {
            "category":"Retail",
            "subcategory":"Auto Repair",
            "type":"Services"
        }
    ],
    "sg:phone":"+1 418 354 2375",
    "sg:postcode":"G0R 4E0",
    "sg:province":"QC",
    "sg:tags":[
        "repairing",
        "automobile"
    ],
    "wof:name":"Garage Marcel Laurendeau",
    "wof:placetype":"venue"
},
  "geometry": {"coordinates":[-70.2107925415,47.2874221802],"type":"Point"}
}