{
  "type": "Feature",
  "properties": {
    "addr:full":"117 Kearney Lake Rd Halifax NS B3M 4N9",
    "addr:housenumber":"117",
    "addr:postcode":"b3m 4n9",
    "addr:street":"Kearney Lake Rd",
    "iso:country":"CA",
    "sg:address":"117 Kearney Lake Rd",
    "sg:city":"Halifax",
    "sg:classifiers":[
        {
            "category":"Food & Beverages",
            "subcategory":"Groceries & Convenience Stores",
            "type":"Retail Goods"
        }
    ],
    "sg:phone":"+1 902 443 6640",
    "sg:postcode":"B3M 4N9",
    "sg:province":"NS",
    "sg:tags":[
        "grocer"
    ],
    "wof:name":"Red Rooster Convenience",
    "wof:placetype":"venue"
},
  "geometry": {"coordinates":[-63.674,44.684155],"type":"Point"}
}