{
  "type": "Feature",
  "properties": {
    "addr:full":"5255 Boul DE LA Rive-Sud Levis QC G6V 4Z4",
    "addr:housenumber":"5255",
    "addr:postcode":"g6v 4z4",
    "addr:street":"Boul De La Rive-Sud",
    "iso:country":"CA",
    "sg:address":"5255 Boul DE LA Rive-Sud",
    "sg:city":"Levis",
    "sg:classifiers":[
        {
            "category":"Health Services",
            "subcategory":"Health Practitioner",
            "type":"Services"
        }
    ],
    "sg:phone":"+1 418 835 5320",
    "sg:postcode":"G6V 4Z4",
    "sg:province":"QC",
    "sg:tags":[
        "psychologist"
    ],
    "wof:name":"Daigle, Suzanne PhD",
    "wof:placetype":"venue"
},
  "geometry": {"coordinates":[-71.18135100000001,46.79229],"type":"Point"}
}