{
  "type": "Feature",
  "properties": {
    "addr:full":"647 Glenholme Ave York ON M6E 3H1",
    "addr:housenumber":"647",
    "addr:postcode":"m6e 3h1",
    "addr:street":"Glenholme Ave",
    "iso:country":"CA",
    "sg:address":"647 Glenholme Ave",
    "sg:city":"York",
    "sg:classifiers":[
        {
            "category":"Shopping",
            "subcategory":"Computers & Home Electronics",
            "type":"Retail Goods"
        }
    ],
    "sg:phone":"+1 416 783 4105",
    "sg:postcode":"M6E 3H1",
    "sg:province":"ON",
    "sg:tags":[
        "television",
        "radio"
    ],
    "wof:name":"Tony Electronics & Tv",
    "wof:placetype":"venue"
},
  "geometry": {"coordinates":[-79.4448928833,43.6962280273],"type":"Point"}
}