{
  "type": "Feature",
  "properties": {
    "addr:full":"705 23 Ave Nisku AB T9E 7Y5",
    "addr:postcode":"t9e 7y5",
    "addr:street":"705 23 Ave",
    "iso:country":"CA",
    "sg:address":"705 23 Ave",
    "sg:city":"Nisku",
    "sg:classifiers":[
        {
            "category":"Manufacturing",
            "subcategory":"Tools & Machinery",
            "type":"Manufacturing & Wholesale Goods"
        }
    ],
    "sg:phone":"+1 780 955 7671",
    "sg:postcode":"T9E 7Y5",
    "sg:province":"AB",
    "sg:tags":[
        "crane"
    ],
    "wof:name":"W F Welding & Overhead Cranes",
    "wof:placetype":"venue"
},
  "geometry": {"coordinates":[-113.520386,53.34399],"type":"Point"}
}