{
  "type": "Feature",
  "properties": {
    "addr:full":"Chester Basin NS B0J 1K0",
    "addr:postcode":"b0j 1k0",
    "iso:country":"CA",
    "sg:city":"Chester Basin",
    "sg:classifiers":[
        {
            "category":"Wholesale",
            "subcategory":"Meat",
            "type":"Manufacturing & Wholesale Goods"
        }
    ],
    "sg:phone":"+1 902 275 5401",
    "sg:postcode":"B0J 1K0",
    "sg:province":"NS",
    "sg:tags":[
        "butchering"
    ],
    "wof:name":"Riverview Meat Market",
    "wof:placetype":"venue"
},
  "geometry": {"coordinates":[-64.30893707280001,44.5657234192],"type":"Point"}
}