{
  "type": "Feature",
  "properties": {
    "addr:full":"2112 Bridletowne Cir Scarborough ON M1W 2L1",
    "addr:housenumber":"2112",
    "addr:postcode":"m1w 2l1",
    "addr:street":"Bridletowne Cir",
    "iso:country":"CA",
    "sg:address":"2112 Bridletowne Cir",
    "sg:city":"Scarborough",
    "sg:classifiers":[
        {
            "category":"Retail",
            "subcategory":"Laundry & Dry Cleaning",
            "type":"Services"
        }
    ],
    "sg:phone":"+1 416 496 8452",
    "sg:postcode":"M1W 2L1",
    "sg:province":"ON",
    "sg:tags":[
        "cleaners"
    ],
    "wof:name":"Echo Cleaners",
    "wof:placetype":"venue"
},
  "geometry": {"coordinates":[-79.313232,43.79892],"type":"Point"}
}