{
  "type": "Feature",
  "properties": {
    "addr:full":"180 Rue Du Pacifique O Bromont QC J2L 1J6",
    "addr:housenumber":"180",
    "addr:postcode":"j2l 1j6",
    "addr:street":"Rue Du Pacifique O",
    "iso:country":"CA",
    "sg:address":"180 Rue Du Pacifique O",
    "sg:city":"Bromont",
    "sg:classifiers":[
        {
            "category":"Autos & Motor Vehicles",
            "subcategory":"Auto Supplies",
            "type":"Retail Goods"
        }
    ],
    "sg:phone":"+1 450 534 2114",
    "sg:postcode":"J2L 1J6",
    "sg:province":"QC",
    "sg:tags":[
        "alternator",
        "generator"
    ],
    "wof:name":"Bromont Auto Electrique Inc",
    "wof:placetype":"venue"
},
  "geometry": {"coordinates":[-72.6785812378,45.3045883179],"type":"Point"}
}