{
  "type": "Feature",
  "properties": {
    "iso:country":"CA",
    "sg:address":"23 Balsam Ave",
    "sg:city":"Bragg Creek",
    "sg:classifiers":[
        {
            "category":"Restaurant",
            "type":"Food & Drink"
        }
    ],
    "sg:phone":"+1 403 949 2750",
    "sg:postcode":"T0L 0K0",
    "sg:province":"AB",
    "wof:name":"Madrina's Ristorante",
    "wof:placetype":"venue"
},
  "geometry": {"coordinates":[-114.561378,50.952332],"type":"Point"}
}