{
  "type": "Feature",
  "properties": {
    "addr:full":"611 4 St SW Calgary AB T2P 1T5",
    "addr:housenumber":"611 4",
    "addr:postcode":"t2p 1t5",
    "addr:street":"St Sw",
    "iso:country":"CA",
    "sg:address":"611 4 St SW",
    "sg:city":"Calgary",
    "sg:classifiers":[
        {
            "category":"Government",
            "subcategory":"Office",
            "type":"Public Place"
        }
    ],
    "sg:phone":"+1 403 297 7405",
    "sg:postcode":"T2P 1T5",
    "sg:province":"AB",
    "wof:name":"Alberta Court Judge's Chambers",
    "wof:placetype":"venue"
},
  "geometry": {"coordinates":[-114.07169342,51.0474777222],"type":"Point"}
}