{
  "type": "Feature",
  "properties": {
    "addr:full":"4190 Fairview St #11 Burlington ON L7L 4Y8",
    "addr:housenumber":"4190",
    "addr:postcode":"l7l 4y8",
    "addr:street":"Fairview St # 11",
    "iso:country":"CA",
    "sg:address":"4190 Fairview St #11",
    "sg:city":"Burlington",
    "sg:classifiers":[
        {
            "category":"Home & Garden",
            "subcategory":"Home Furnishings",
            "type":"Retail Goods"
        }
    ],
    "sg:phone":"+1 905 634 6567",
    "sg:postcode":"L7L 4Y8",
    "sg:province":"ON",
    "sg:tags":[
        "fixture",
        "bathroom",
        "remodeling"
    ],
    "wof:name":"Bathroom Gallery Lokert Ltd",
    "wof:placetype":"venue"
},
  "geometry": {"coordinates":[-79.7740097046,43.3644790649],"type":"Point"}
}