{
  "type": "Feature",
  "properties": {
    "addr:full":"221 Centre St Regina Beach SK S0G 4C0",
    "addr:housenumber":"221",
    "addr:postcode":"s0g 4c0",
    "addr:street":"Centre St",
    "iso:country":"CA",
    "sg:address":"221 Centre St",
    "sg:city":"Regina Beach",
    "sg:classifiers":[
        {
            "category":"Autos & Motor Vehicles",
            "subcategory":"Automobile Sales",
            "type":"Retail Goods"
        }
    ],
    "sg:phone":"+1 306 729 3500",
    "sg:postcode":"S0G 4C0",
    "sg:province":"SK",
    "sg:tags":[
        "snowmobile"
    ],
    "wof:name":"Saskatchewan Snowmobile Assn",
    "wof:placetype":"venue"
},
  "geometry": {"coordinates":[-104.97403,50.787136],"type":"Point"}
}