{
  "type": "Feature",
  "properties": {
    "addr:full":"2725 Chalmer Ave Youngs Point ON K0L 3G0",
    "addr:housenumber":"2725",
    "addr:postcode":"k0l 3g0",
    "addr:street":"Chalmer Ave Youngs",
    "iso:country":"CA",
    "sg:address":"2725 Chalmer Ave",
    "sg:city":"Youngs Point",
    "sg:classifiers":[
        {
            "category":"Education",
            "subcategory":"School",
            "type":"Public Place"
        }
    ],
    "sg:phone":"+1 705 652 8648",
    "sg:postcode":"K0L 3G0",
    "sg:province":"ON",
    "wof:name":"Young's Point Public",
    "wof:placetype":"venue"
},
  "geometry": {"coordinates":[-78.239555,44.487953],"type":"Point"}
}