{
  "type": "Feature",
  "properties": {
    "addr:full":"565 Ch DE LA Savane Le Gardeur QC J5Z 4C7",
    "addr:housenumber":"565",
    "addr:postcode":"j5z 4c7",
    "addr:street":"Ch De La Savane;Gardeur",
    "iso:country":"CA",
    "sg:address":"565 Ch DE LA Savane",
    "sg:city":"Le Gardeur",
    "sg:classifiers":[
        {
            "category":"Building & Trades",
            "subcategory":"Plumbing",
            "type":"Services"
        }
    ],
    "sg:phone":"+1 450 582 3918",
    "sg:postcode":"J5Z 4C7",
    "sg:province":"QC",
    "sg:tags":[
        "contractor"
    ],
    "wof:name":"Plomberie Repentigny Inc",
    "wof:placetype":"venue"
},
  "geometry": {"coordinates":[-73.49890899659999,45.7842750549],"type":"Point"}
}