{
  "type": "Feature",
  "properties": {
    "addr:full":"Tisdale SK S0E 1T0",
    "addr:postcode":"s0e 1t0",
    "addr:street":"Tisdale",
    "iso:country":"CA",
    "sg:city":"Tisdale",
    "sg:classifiers":[
        {
            "category":"Autos & Motor Vehicles",
            "subcategory":"Automobile Sales",
            "type":"Retail Goods"
        }
    ],
    "sg:phone":"+1 306 873 2633",
    "sg:postcode":"S0E 1T0",
    "sg:province":"SK",
    "sg:tags":[
        "car",
        "dealer"
    ],
    "wof:name":"Bow-Mar Sales Ltd",
    "wof:placetype":"venue"
},
  "geometry": {"coordinates":[-104.047523498,52.8418731689],"type":"Point"}
}