{
  "type": "Feature",
  "properties": {
    "addr:full":"75 Marsh St Ext Ridgetown ON N0P 2C0",
    "addr:housenumber":"75",
    "addr:postcode":"n0p 2c0",
    "addr:street":"Marsh St Ext",
    "iso:country":"CA",
    "sg:address":"75 Marsh St Ext",
    "sg:city":"Ridgetown",
    "sg:classifiers":[
        {
            "category":"Building & Trades",
            "subcategory":"Electrical",
            "type":"Services"
        }
    ],
    "sg:phone":"+1 519 674 2811",
    "sg:postcode":"N0P 2C0",
    "sg:province":"ON",
    "sg:tags":[
        "electric",
        "contractor"
    ],
    "wof:name":"Walter Spence Enterprises",
    "wof:placetype":"venue"
},
  "geometry": {"coordinates":[-81.879761,42.429543],"type":"Point"}
}