{
  "type": "Feature",
  "properties": {
    "addr:full":"17 Belmont Rd Newport NS B0N 2A0",
    "addr:housenumber":"17",
    "addr:postcode":"b0n 2a0",
    "addr:street":"Belmont Rd",
    "iso:country":"CA",
    "sg:address":"17 Belmont Rd",
    "sg:city":"Newport",
    "sg:classifiers":[
        {
            "category":"Restaurant",
            "type":"Food & Drink"
        }
    ],
    "sg:phone":"+1 902 757 3565",
    "sg:postcode":"B0N 2A0",
    "sg:province":"NS",
    "sg:tags":[
        "tea",
        "rooms"
    ],
    "wof:name":"Avon River Heritage Society",
    "wof:placetype":"venue"
},
  "geometry": {"coordinates":[-63.982685,44.974148],"type":"Point"}
}