{
  "type": "Feature",
  "properties": {
    "addr:full":"2126 1/2 Queen St E Toronto ON M4E 1E3",
    "addr:housenumber":"2126 1 / 2",
    "addr:postcode":"m4e 1e3",
    "addr:street":"Queen St E",
    "iso:country":"CA",
    "sg:address":"2126 1/2 Queen St E",
    "sg:city":"Toronto",
    "sg:classifiers":[
        {
            "category":"Education",
            "subcategory":"Special Training",
            "type":"Public Place"
        }
    ],
    "sg:phone":"+1 416 691 7323",
    "sg:postcode":"M4E 1E3",
    "sg:province":"ON",
    "sg:tags":[
        "tutoring"
    ],
    "wof:name":"Sylvan Learning Ctr",
    "wof:placetype":"venue"
},
  "geometry": {"coordinates":[-79.29418200000001,43.671425],"type":"Point"}
}