{
  "type": "Feature",
  "properties": {
    "addr:full":"7630 Winston St Burnaby BC V5A 2H4",
    "addr:housenumber":"7630",
    "addr:postcode":"v5a 2h4",
    "addr:street":"Winston St",
    "iso:country":"CA",
    "sg:address":"7630 Winston St",
    "sg:city":"Burnaby",
    "sg:classifiers":[
        {
            "category":"Manufacturing",
            "subcategory":"Food",
            "type":"Manufacturing & Wholesale Goods"
        }
    ],
    "sg:phone":"+1 604 420 4808",
    "sg:postcode":"V5A 2H4",
    "sg:province":"BC",
    "sg:tags":[
        "brewer"
    ],
    "wof:name":"Beverage Concepts Intl",
    "wof:placetype":"venue"
},
  "geometry": {"coordinates":[-122.94105529799999,49.2481231689],"type":"Point"}
}