{
  "type": "Feature",
  "properties": {
    "addr:full":"916 LA Ronge Ave LA Ronge SK S0J 1L0",
    "addr:housenumber":"916",
    "addr:postcode":"s0j 1l0",
    "addr:street":"La Ronge Ave",
    "iso:country":"CA",
    "sg:address":"916 LA Ronge Ave",
    "sg:city":"LA Ronge",
    "sg:classifiers":[
        {
            "category":"Health Services",
            "subcategory":"Doctor",
            "type":"Services"
        }
    ],
    "sg:phone":"+1 306 425 2033",
    "sg:postcode":"S0J 1L0",
    "sg:province":"SK",
    "sg:tags":[
        "dentist"
    ],
    "wof:name":"Malaxos, Dany DDS",
    "wof:placetype":"venue"
},
  "geometry": {"coordinates":[-105.295326,55.112495],"type":"Point"}
}