{
  "type": "Feature",
  "properties": {
    "addr:full":"123 Rue Rotobec Sainte-Justine QC G0R 1Y0",
    "addr:housenumber":"123",
    "addr:postcode":"g0r 1y0",
    "addr:street":"Rue Rotobec",
    "iso:country":"CA",
    "sg:address":"123 Rue Rotobec",
    "sg:city":"Sainte-Justine",
    "sg:classifiers":[
        {
            "category":"Personal",
            "subcategory":"Beauty Salon",
            "type":"Services"
        }
    ],
    "sg:phone":"+1 418 383 5108",
    "sg:postcode":"G0R 1Y0",
    "sg:province":"QC",
    "wof:name":"Salon Au Feminin Enr",
    "wof:placetype":"venue"
},
  "geometry": {"coordinates":[-70.3613739014,46.4025917053],"type":"Point"}
}