{
  "type": "Feature",
  "properties": {
    "addr:full":"1111 Finch Ave W North York ON M3J 2E5",
    "addr:housenumber":"1111",
    "addr:postcode":"m3j 2e5",
    "addr:street":"Finch Ave W",
    "iso:country":"CA",
    "sg:address":"1111 Finch Ave W",
    "sg:city":"North York",
    "sg:classifiers":[
        {
            "category":"Home & Garden",
            "subcategory":"Building Materials",
            "type":"Retail Goods"
        }
    ],
    "sg:phone":"+1 416 661 6300",
    "sg:postcode":"M3J 2E5",
    "sg:province":"ON",
    "sg:tags":[
        "windows"
    ],
    "wof:name":"Delta Windows & Door",
    "wof:placetype":"venue"
},
  "geometry": {"coordinates":[-79.4723739624,43.7674980164],"type":"Point"}
}