{
  "type": "Feature",
  "properties": {
    "addr:full":"1340 Ellis St Kelowna BC V1Y 9N1",
    "addr:housenumber":"1340",
    "addr:postcode":"v1y 9n1",
    "addr:street":"Ellis St",
    "iso:country":"CA",
    "sg:address":"1340 Ellis St",
    "sg:city":"Kelowna",
    "sg:classifiers":[
        {
            "category":"Government",
            "subcategory":"Office",
            "type":"Public Place"
        }
    ],
    "sg:phone":"+1 250 868 7700",
    "sg:postcode":"V1Y 9N1",
    "sg:province":"BC",
    "wof:name":"BC Health Units-South Okanagn",
    "wof:placetype":"venue"
},
  "geometry": {"coordinates":[-119.49374400000001,49.890549],"type":"Point"}
}