{
  "type": "Feature",
  "properties": {
    "addr:full":"276 Main St W Hamilton ON L8P 1J8",
    "addr:housenumber":"276",
    "addr:postcode":"l8p 1j8",
    "addr:street":"Main St W",
    "iso:country":"CA",
    "sg:address":"276 Main St W",
    "sg:city":"Hamilton",
    "sg:classifiers":[
        {
            "category":"Professional",
            "subcategory":"Business Services",
            "type":"Services"
        }
    ],
    "sg:phone":"+1 905 546 1358",
    "sg:postcode":"L8P 1J8",
    "sg:province":"ON",
    "sg:tags":[
        "interior",
        "consultant",
        "design",
        "decorator"
    ],
    "wof:name":"Slc Designs Ltd",
    "wof:placetype":"venue"
},
  "geometry": {"coordinates":[-79.88125610349999,43.2581787109],"type":"Point"}
}