{
  "type": "Feature",
  "properties": {
    "iso:country":"CA",
    "sg:city":"Pickering",
    "sg:classifiers":[
        {
            "category":"Personal",
            "subcategory":"Beauty Salon",
            "type":"Services"
        }
    ],
    "sg:phone":"+1 905 839 9372",
    "sg:postcode":"L1V 3B4",
    "sg:province":"ON",
    "wof:name":"Professional Hair Salon",
    "wof:placetype":"venue"
},
  "geometry": {"coordinates":[-79.08725738530001,43.8383483887],"type":"Point"}
}