{
  "type": "Feature",
  "properties": {
    "addr:full":"Munden Dr Mount Pearl NL A1N 2T5",
    "addr:postcode":"a1n 2t5",
    "addr:street":"Munden Dr",
    "iso:country":"CA",
    "sg:address":"Munden Dr",
    "sg:city":"Mount Pearl",
    "sg:classifiers":[
        {
            "category":"Education",
            "subcategory":"School",
            "type":"Public Place"
        }
    ],
    "sg:phone":"+1 709 368 0189",
    "sg:postcode":"A1N 2T5",
    "sg:province":"NL",
    "wof:name":"St Peter's Junior High School",
    "wof:placetype":"venue"
},
  "geometry": {"coordinates":[-52.8102378845,47.5065002441],"type":"Point"}
}