{
  "type": "Feature",
  "properties": {
    "addr:full":"2601 Skaha Lake Rd # 101 Penticton BC V2A 6E8",
    "addr:housenumber":"2601",
    "addr:postcode":"v2a 6e8",
    "addr:street":"Skaha Lake Rd # 101",
    "iso:country":"CA",
    "sg:address":"2601 Skaha Lake Rd # 101",
    "sg:city":"Penticton",
    "sg:classifiers":[
        {
            "category":"Utilities",
            "subcategory":"Mobile Phone",
            "type":"Services"
        }
    ],
    "sg:phone":"+1 250 493 3800",
    "sg:postcode":"V2A 6E8",
    "sg:province":"BC",
    "sg:tags":[
        "telephone",
        "cellular"
    ],
    "wof:name":"Andre's Audiotronic",
    "wof:placetype":"venue"
},
  "geometry": {"coordinates":[-119.58556400000001,49.46751],"type":"Point"}
}