{
  "type": "Feature",
  "properties": {
    "addr:full":"45620 Yale Rd Chilliwack BC V2P 2N2",
    "addr:housenumber":"45620",
    "addr:postcode":"v2p 2n2",
    "addr:street":"Yale Rd",
    "iso:country":"CA",
    "sg:address":"45620 Yale Rd",
    "sg:city":"Chilliwack",
    "sg:classifiers":[
        {
            "category":"Travel",
            "subcategory":"Hotels & Motels",
            "type":"Entertainment"
        }
    ],
    "sg:phone":"+1 604 792 6412",
    "sg:postcode":"V2P 2N2",
    "sg:province":"BC",
    "wof:name":"Rainbow Motor Inn",
    "wof:placetype":"venue"
},
  "geometry": {"coordinates":[-121.96207428,49.1540107727],"type":"Point"}
}