{
  "type": "Feature",
  "properties": {
    "addr:full":"235 Lakeshore Rd E Mississauga ON L5G 1G8",
    "addr:housenumber":"235",
    "addr:postcode":"l5g 1g8",
    "addr:street":"Lakeshore Rd E",
    "iso:country":"CA",
    "sg:address":"235 Lakeshore Rd E",
    "sg:city":"Mississauga",
    "sg:classifiers":[
        {
            "category":"Shopping",
            "subcategory":"Used Merchandise",
            "type":"Retail Goods"
        }
    ],
    "sg:phone":"+1 905 274 5569",
    "sg:postcode":"L5G 1G8",
    "sg:province":"ON",
    "sg:tags":[
        "shop",
        "second",
        "consignment",
        "store",
        "hand"
    ],
    "wof:name":"Twice Is Nice",
    "wof:placetype":"venue"
},
  "geometry": {"coordinates":[-79.5771865845,43.559299469],"type":"Point"}
}