{
  "type": "Feature",
  "properties": {
    "iso:country":"CA",
    "sg:address":"7755 Rue Grenache",
    "sg:city":"Anjou",
    "sg:classifiers":[
        {
            "category":"Wholesale",
            "subcategory":"Meat",
            "type":"Manufacturing & Wholesale Goods"
        }
    ],
    "sg:phone":"+1 514 327 1310",
    "sg:postcode":"H1J 1C4",
    "sg:province":"QC",
    "sg:tags":[
        "product"
    ],
    "wof:name":"Viandes Montcalm Inc",
    "wof:placetype":"venue"
},
  "geometry": {"coordinates":[-73.5740432739,45.6108055115],"type":"Point"}
}