{
  "type": "Feature",
  "properties": {
    "addr:full":"1 Capitaine Fournier Port-Daniel QC G0C 2N0",
    "addr:housenumber":"1",
    "addr:postcode":"g0c 2n0",
    "addr:street":"Capitaine Fournier",
    "iso:country":"CA",
    "sg:address":"1 Capitaine Fournier",
    "sg:city":"Port-Daniel",
    "sg:classifiers":[
        {
            "category":"Freight",
            "type":"Transportation"
        }
    ],
    "sg:phone":"+1 418 396 2310",
    "sg:postcode":"G0C 2N0",
    "sg:province":"QC",
    "sg:tags":[
        "warehouse",
        "storage"
    ],
    "wof:name":"Entrepots Frigorifiques Ours",
    "wof:placetype":"venue"
},
  "geometry": {"coordinates":[-64.95777099999999,48.18737],"type":"Point"}
}