{
  "type": "Feature",
  "properties": {
    "addr:full":"5787 Steeles Ave W North York ON M9L 2W3",
    "addr:housenumber":"5787",
    "addr:postcode":"m9l 2w3",
    "addr:street":"Steeles Ave W",
    "iso:country":"CA",
    "sg:address":"5787 Steeles Ave W",
    "sg:city":"North York",
    "sg:classifiers":[
        {
            "category":"Professional",
            "subcategory":"Advertising",
            "type":"Services"
        }
    ],
    "sg:phone":"+1 416 745 1209",
    "sg:postcode":"M9L 2W3",
    "sg:province":"ON",
    "sg:tags":[
        "designer",
        "display",
        "producer"
    ],
    "wof:name":"E Pd Engineered Plastic Design",
    "wof:placetype":"venue"
},
  "geometry": {"coordinates":[-79.566422,43.766068],"type":"Point"}
}