{
  "type": "Feature",
  "properties": {
    "addr:full":"St Catharines ON L2R 3C8",
    "addr:postcode":"l2r 3c8",
    "iso:country":"CA",
    "sg:city":"St Catharines",
    "sg:classifiers":[
        {
            "category":"Professional",
            "subcategory":"Accounting & Tax Preparation",
            "type":"Services"
        }
    ],
    "sg:phone":"+1 905 687 8141",
    "sg:postcode":"L2R 3C8",
    "sg:province":"ON",
    "sg:tags":[
        "bookkeeping",
        "general"
    ],
    "wof:name":"Mc Sween, Marianne",
    "wof:placetype":"venue"
},
  "geometry": {"coordinates":[-79.245186,43.161686],"type":"Point"}
}