{
  "type": "Feature",
  "properties": {
    "iso:country":"CA",
    "sg:address":"256 Victoria St S",
    "sg:city":"Kitchener",
    "sg:classifiers":[
        {
            "category":"Shopping",
            "subcategory":"Discount & Variety Stores",
            "type":"Retail Goods"
        }
    ],
    "sg:phone":"+1 519 745 3851",
    "sg:postcode":"N2G 2C2",
    "sg:province":"ON",
    "wof:name":"J & J Milk Variety",
    "wof:placetype":"venue"
},
  "geometry": {"coordinates":[-80.50555419920001,43.4458847046],"type":"Point"}
}