{
  "type": "Feature",
  "properties": {
    "addr:full":"Lindsay ON K9V 6C5",
    "addr:postcode":"k9v 6c5",
    "iso:country":"CA",
    "sg:city":"Lindsay",
    "sg:classifiers":[
        {
            "category":"Health Services",
            "subcategory":"Doctor",
            "type":"Services"
        }
    ],
    "sg:phone":"+1 705 324 5990",
    "sg:postcode":"K9V 6C5",
    "sg:province":"ON",
    "sg:tags":[
        "physician",
        "surgeon"
    ],
    "wof:name":"Evans, Keith MD",
    "wof:placetype":"venue"
},
  "geometry": {"coordinates":[-78.74826049799999,44.3453102112],"type":"Point"}
}