{
  "type": "Feature",
  "properties": {
    "iso:country":"CA",
    "sg:address":"189 Rue Dube",
    "sg:city":"Thetford Mines",
    "sg:classifiers":[
        {
            "category":"Social Services",
            "type":"Services"
        }
    ],
    "sg:phone":"+1 418 335 3732",
    "sg:postcode":"G6G 3B6",
    "sg:province":"QC",
    "sg:tags":[
        "organization",
        "welfare"
    ],
    "wof:name":"Crdi Chaudiere-Appalache",
    "wof:placetype":"venue"
},
  "geometry": {"coordinates":[-71.2950592041,46.091796875],"type":"Point"}
}