{
  "type": "Feature",
  "properties": {
    "addr:full":"10423 Montee Sainte-Marianne Mirabel QC J7J 2B1",
    "addr:housenumber":"10423",
    "addr:postcode":"j7j 2b1",
    "addr:street":"Montee Sainte-Marianne",
    "iso:country":"CA",
    "sg:address":"10423 Montee Sainte-Marianne",
    "sg:city":"Mirabel",
    "sg:classifiers":[
        {
            "category":"Recreation",
            "type":"Entertainment"
        }
    ],
    "sg:phone":"+1 450 435 6510",
    "sg:postcode":"J7J 2B1",
    "sg:province":"QC",
    "sg:tags":[
        "provincial",
        "parks"
    ],
    "wof:name":"Parc Du Domaine Vert",
    "wof:placetype":"venue"
},
  "geometry": {"coordinates":[-73.90879099999999,45.658497],"type":"Point"}
}