{
  "type": "Feature",
  "properties": {
    "addr:full":"313 Main St Rosetown SK S0L 2V0",
    "addr:housenumber":"313",
    "addr:postcode":"s0l 2v0",
    "addr:street":"Main St",
    "iso:country":"CA",
    "sg:address":"313 Main St",
    "sg:city":"Rosetown",
    "sg:classifiers":[
        {
            "category":"Food & Beverages",
            "subcategory":"Groceries & Convenience Stores",
            "type":"Retail Goods"
        }
    ],
    "sg:phone":"+1 306 882 2226",
    "sg:postcode":"S0L 2V0",
    "sg:province":"SK",
    "sg:tags":[
        "product"
    ],
    "wof:name":"Bins-N-Barrels",
    "wof:placetype":"venue"
},
  "geometry": {"coordinates":[-107.992088,51.551716],"type":"Point"}
}