{
  "type": "Feature",
  "properties": {
    "addr:full":"176 Francis St Exeter ON N0M 1S3",
    "addr:housenumber":"176",
    "addr:postcode":"n0m 1s3",
    "addr:street":"Francis St",
    "iso:country":"CA",
    "sg:address":"176 Francis St",
    "sg:city":"Exeter",
    "sg:classifiers":[
        {
            "category":"Building & Trades",
            "subcategory":"Landscaping Services",
            "type":"Services"
        }
    ],
    "sg:phone":"+1 519 235 1885",
    "sg:postcode":"N0M 1S3",
    "sg:province":"ON",
    "sg:tags":[
        "lawn",
        "maintenance",
        "grounds"
    ],
    "wof:name":"Casey's Lawn Care",
    "wof:placetype":"venue"
},
  "geometry": {"coordinates":[-81.48632000000001,43.360847],"type":"Point"}
}