{
  "type": "Feature",
  "properties": {
    "addr:full":"5318 47 St Camrose AB T4V 1K6",
    "addr:housenumber":"5318",
    "addr:postcode":"t4v 1k6",
    "addr:street":"47 St",
    "iso:country":"CA",
    "sg:address":"5318 47 St",
    "sg:city":"Camrose",
    "sg:classifiers":[
        {
            "category":"Wholesale",
            "subcategory":"Electrical",
            "type":"Manufacturing & Wholesale Goods"
        }
    ],
    "sg:phone":"+1 780 672 3980",
    "sg:postcode":"T4V 1K6",
    "sg:province":"AB",
    "sg:tags":[
        "appliance"
    ],
    "wof:name":"Skiba Appliance Repairs Ltd",
    "wof:placetype":"venue"
},
  "geometry": {"coordinates":[-112.820487976,53.0284156799],"type":"Point"}
}