{
  "type": "Feature",
  "properties": {
    "addr:full":"Ottawa ON K1K 3Y3",
    "addr:postcode":"k1k 3y3",
    "iso:country":"CA",
    "sg:city":"Ottawa",
    "sg:classifiers":[
        {
            "category":"Real Estate",
            "subcategory":"Real Estate Operator",
            "type":"Services"
        }
    ],
    "sg:phone":"+1 613 747 2960",
    "sg:postcode":"K1K 3Y3",
    "sg:province":"ON",
    "sg:tags":[
        "management",
        "apartment"
    ],
    "wof:name":"Shelter Canadian Properties",
    "wof:placetype":"venue"
},
  "geometry": {"coordinates":[-75.62499200000001,45.446323],"type":"Point"}
}