{
  "type": "Feature",
  "properties": {
    "addr:full":"1094 Selkirk Ave Winnipeg MB R2X 0C3",
    "addr:housenumber":"1094",
    "addr:postcode":"r2x 0c3",
    "addr:street":"Selkirk Ave",
    "iso:country":"CA",
    "sg:address":"1094 Selkirk Ave",
    "sg:city":"Winnipeg",
    "sg:classifiers":[
        {
            "category":"Retail",
            "subcategory":"Auto Repair",
            "type":"Services"
        }
    ],
    "sg:phone":"+1 204 582 2700",
    "sg:postcode":"R2X 0C3",
    "sg:province":"MB",
    "sg:tags":[
        "repairing",
        "automobile",
        "painting"
    ],
    "wof:name":"Harby's Auto & Body Shop",
    "wof:placetype":"venue"
},
  "geometry": {"coordinates":[-97.168457,49.923031],"type":"Point"}
}