{
  "type": "Feature",
  "properties": {
    "iso:country":"CA",
    "sg:address":"377 Allbirch Rd",
    "sg:city":"Woodlawn",
    "sg:classifiers":[
        {
            "category":"Organizations",
            "subcategory":"Professional Association",
            "type":"Services"
        }
    ],
    "sg:phone":"+1 613 832 2082",
    "sg:postcode":"K0A 3M0",
    "sg:province":"ON",
    "wof:name":"Royal Canadian Legion",
    "wof:placetype":"venue"
},
  "geometry": {"coordinates":[-76.0752792358,45.4623985291],"type":"Point"}
}