{
  "type": "Feature",
  "properties": {
    "addr:full":"301 Spadina Ave #3 Toronto ON M5T 2E6",
    "addr:housenumber":"301",
    "addr:postcode":"m5t 2e6",
    "addr:street":"Spadina Ave # 3",
    "iso:country":"CA",
    "sg:address":"301 Spadina Ave #3",
    "sg:city":"Toronto",
    "sg:classifiers":[
        {
            "category":"Shopping",
            "subcategory":"Jewelry",
            "type":"Retail Goods"
        }
    ],
    "sg:phone":"+1 416 979 7084",
    "sg:postcode":"M5T 2E6",
    "sg:province":"ON",
    "sg:tags":[
        "jeweler"
    ],
    "wof:name":"Thai Kwang Jewellery",
    "wof:placetype":"venue"
},
  "geometry": {"coordinates":[-79.3979644775,43.6535148621],"type":"Point"}
}