{
  "type": "Feature",
  "properties": {
    "addr:full":"106 Humphrey Rd Labrador City NL A2V 2J8",
    "addr:housenumber":"106",
    "addr:postcode":"a2v 2j8",
    "addr:street":"Humphrey Rd",
    "iso:country":"CA",
    "sg:address":"106 Humphrey Rd",
    "sg:city":"Labrador City",
    "sg:classifiers":[
        {
            "category":"Wholesale",
            "subcategory":"Durable Goods & Equipment",
            "type":"Manufacturing & Wholesale Goods"
        }
    ],
    "sg:phone":"+1 709 944 6665",
    "sg:postcode":"A2V 2J8",
    "sg:province":"NL",
    "sg:tags":[
        "fire",
        "extinguisher",
        "gas",
        "propane"
    ],
    "wof:name":"J & B Propane Ltd",
    "wof:placetype":"venue"
},
  "geometry": {"coordinates":[-66.89966583250001,52.9483642578],"type":"Point"}
}