{
  "type": "Feature",
  "properties": {
    "addr:full":"40 Rue Sainte-Anne Baie-Saint-Paul QC G3Z 1P2",
    "addr:housenumber":"40",
    "addr:postcode":"g3z 1p2",
    "addr:street":"Rue Sainte-Anne",
    "iso:country":"CA",
    "sg:address":"40 Rue Sainte-Anne",
    "sg:city":"Baie-Saint-Paul",
    "sg:classifiers":[
        {
            "category":"Personal",
            "type":"Services"
        }
    ],
    "sg:phone":"+1 418 435 2283",
    "sg:postcode":"G3Z 1P2",
    "sg:province":"QC",
    "sg:tags":[
        "electrolysis"
    ],
    "wof:name":"Esthetique Andree Simard",
    "wof:placetype":"venue"
},
  "geometry": {"coordinates":[-70.503731,47.43935],"type":"Point"}
}