{
  "type": "Feature",
  "properties": {
    "addr:full":"PO Box 2116 STN Main Swift Current SK S9H 4V1",
    "addr:housenumber":"po",
    "addr:postcode":"s9h 4v1",
    "addr:street":"Box 2116 Stn Main",
    "iso:country":"CA",
    "sg:address":"PO Box 2116 STN Main",
    "sg:city":"Swift Current",
    "sg:classifiers":[
        {
            "category":"Retail",
            "subcategory":"Laundry & Dry Cleaning",
            "type":"Services"
        }
    ],
    "sg:phone":"+1 306 773 1255",
    "sg:postcode":"S9H 4V1",
    "sg:province":"SK",
    "sg:tags":[
        "cleaners",
        "rug",
        "carpet"
    ],
    "wof:name":"Top-Value Carpet & Uphlstry",
    "wof:placetype":"venue"
},
  "geometry": {"coordinates":[-107.800552,50.292759],"type":"Point"}
}