{
  "type": "Feature",
  "properties": {
    "addr:full":"1592 Boul Saint-Elzear O Laval QC H7L 3N2",
    "addr:housenumber":"1592",
    "addr:postcode":"h7l 3n2",
    "addr:street":"Boul Saint-Elzear O",
    "iso:country":"CA",
    "sg:address":"1592 Boul Saint-Elzear O",
    "sg:city":"Laval",
    "sg:classifiers":[
        {
            "category":"Manufacturing",
            "subcategory":"Printing",
            "type":"Manufacturing & Wholesale Goods"
        }
    ],
    "sg:phone":"+1 450 681 7753",
    "sg:postcode":"H7L 3N2",
    "sg:province":"QC",
    "sg:tags":[
        "printer"
    ],
    "wof:name":"Impressions Numericart Inc",
    "wof:placetype":"venue"
},
  "geometry": {"coordinates":[-73.746025,45.586437],"type":"Point"}
}