{
  "type": "Feature",
  "properties": {
    "addr:full":"Mississauga ON L4W 4K8",
    "addr:postcode":"l4w 4k8",
    "iso:country":"CA",
    "sg:city":"Mississauga",
    "sg:classifiers":[
        {
            "category":"Professional",
            "subcategory":"Management & Consulting",
            "type":"Services"
        }
    ],
    "sg:phone":"+1 905 624 0105",
    "sg:postcode":"L4W 4K8",
    "sg:province":"ON",
    "sg:tags":[
        "consultant"
    ],
    "wof:name":"Business Foundation Canada",
    "wof:placetype":"venue"
},
  "geometry": {"coordinates":[-79.622429,43.644943],"type":"Point"}
}