{
  "type": "Feature",
  "properties": {
    "iso:country":"CA",
    "sg:address":"27 Erie St N",
    "sg:city":"Leamington",
    "sg:classifiers":[
        {
            "category":"Autos & Motor Vehicles",
            "subcategory":"Automobile Sales",
            "type":"Retail Goods"
        }
    ],
    "sg:phone":"+1 519 326 1045",
    "sg:postcode":"N8H 2Z2",
    "sg:province":"ON",
    "sg:tags":[
        "cart"
    ],
    "wof:name":"Ideal Karts & Parts",
    "wof:placetype":"venue"
},
  "geometry": {"coordinates":[-82.5998916626,42.0537719727],"type":"Point"}
}