{
  "type": "Feature",
  "properties": {
    "iso:country":"CA",
    "sg:city":"Montreal",
    "sg:classifiers":[
        {
            "category":"Manufacturing",
            "subcategory":"Motor Vehicles & Parts",
            "type":"Manufacturing & Wholesale Goods"
        }
    ],
    "sg:phone":"+1 514 273 5192",
    "sg:postcode":"H2T 1X6",
    "sg:province":"QC",
    "sg:tags":[
        "lining"
    ],
    "wof:name":"Canada Pad",
    "wof:placetype":"venue"
},
  "geometry": {"coordinates":[-73.596169,45.526493],"type":"Point"}
}