{
  "type": "Feature",
  "properties": {
    "addr:full":"125 16th Ave Richmond Hill ON L4C 7A5",
    "addr:housenumber":"125",
    "addr:postcode":"l4c 7a5",
    "addr:street":"16Th Ave",
    "iso:country":"CA",
    "sg:address":"125 16th Ave",
    "sg:city":"Richmond Hill",
    "sg:classifiers":[
        {
            "category":"Retail",
            "subcategory":"Auto Repair",
            "type":"Services"
        }
    ],
    "sg:phone":"+1 905 881 8560",
    "sg:postcode":"L4C 7A5",
    "sg:province":"ON",
    "sg:tags":[
        "truck"
    ],
    "wof:name":"Alati Auto Truck Svc Ltd",
    "wof:placetype":"venue"
},
  "geometry": {"coordinates":[-79.42925262449999,43.8536911011],"type":"Point"}
}