{
  "type": "Feature",
  "properties": {
    "addr:full":"98 Ellice St Rocanville SK S0A 3L0",
    "addr:housenumber":"98",
    "addr:postcode":"s0a 3l0",
    "addr:street":"Ellice St",
    "iso:country":"CA",
    "sg:address":"98 Ellice St",
    "sg:city":"Rocanville",
    "sg:classifiers":[
        {
            "category":"Retail",
            "subcategory":"Auto Repair",
            "type":"Services"
        }
    ],
    "sg:phone":"+1 306 645 2119",
    "sg:postcode":"S0A 3L0",
    "sg:province":"SK",
    "sg:tags":[
        "repairing",
        "automobile"
    ],
    "wof:name":"M R Challice Sales",
    "wof:placetype":"venue"
},
  "geometry": {"coordinates":[-101.699920654,50.3824424744],"type":"Point"}
}