{
  "type": "Feature",
  "properties": {
    "addr:full":"9 Carmichael Bay Regina SK S4R 0C7",
    "addr:housenumber":"9",
    "addr:postcode":"s4r 0c7",
    "addr:street":"Carmichael Bay",
    "iso:country":"CA",
    "sg:address":"9 Carmichael Bay",
    "sg:city":"Regina",
    "sg:classifiers":[
        {
            "category":"Organizations",
            "subcategory":"Religious Organization",
            "type":"Services"
        }
    ],
    "sg:phone":"+1 306 543 5905",
    "sg:postcode":"S4R 0C7",
    "sg:province":"SK",
    "sg:tags":[
        "church"
    ],
    "wof:name":"Church of the Epiphany",
    "wof:placetype":"venue"
},
  "geometry": {"coordinates":[-104.616333,50.488979],"type":"Point"}
}