{
  "type": "Feature",
  "properties": {
    "addr:full":"623 Rue DE LA Sabliere Bois-Des-Filion QC J6Z 4T2",
    "addr:housenumber":"623",
    "addr:postcode":"j6z 4t2",
    "addr:street":"Rue De La Sabliere",
    "iso:country":"CA",
    "sg:address":"623 Rue DE LA Sabliere",
    "sg:city":"Bois-Des-Filion",
    "sg:classifiers":[
        {
            "category":"Manufacturing",
            "subcategory":"Metals",
            "type":"Manufacturing & Wholesale Goods"
        }
    ],
    "sg:phone":"+1 450 621 2280",
    "sg:postcode":"J6Z 4T2",
    "sg:province":"QC",
    "sg:tags":[
        "steel"
    ],
    "wof:name":"Paldi Metal",
    "wof:placetype":"venue"
},
  "geometry": {"coordinates":[-73.764183,45.681381],"type":"Point"}
}