{
  "type": "Feature",
  "properties": {
    "addr:full":"Saint-Alexis-Des-Monts QC J0K 1V0",
    "addr:postcode":"j0k 1v0",
    "iso:country":"CA",
    "sg:city":"Saint-Alexis-Des-Monts",
    "sg:classifiers":[
        {
            "category":"Real Estate",
            "subcategory":"Real Estate Agent",
            "type":"Services"
        }
    ],
    "sg:phone":"+1 819 265 4142",
    "sg:postcode":"J0K 1V0",
    "sg:province":"QC",
    "sg:tags":[
        "agency",
        "rental"
    ],
    "wof:name":"Centre Multi-Svc",
    "wof:placetype":"venue"
},
  "geometry": {"coordinates":[-73.147919,46.452576],"type":"Point"}
}