{
  "type": "Feature",
  "properties": {
    "iso:country":"CA",
    "sg:address":"1320 Bloor St W",
    "sg:city":"Toronto",
    "sg:classifiers":[
        {
            "category":"Food & Beverages",
            "subcategory":"Groceries & Convenience Stores",
            "type":"Retail Goods"
        }
    ],
    "sg:phone":"+1 416 516 0552",
    "sg:postcode":"M6H 1P2",
    "sg:province":"ON",
    "sg:tags":[
        "grocer"
    ],
    "wof:name":"Bala Brothers Ltd",
    "wof:placetype":"venue"
},
  "geometry": {"coordinates":[-79.44323,43.658379],"type":"Point"}
}