{
  "type": "Feature",
  "properties": {
    "addr:full":"Aldergrove BC V4W 2Z7",
    "addr:postcode":"v4w 2z7",
    "iso:country":"CA",
    "sg:city":"Aldergrove",
    "sg:classifiers":[
        {
            "category":"Personal",
            "subcategory":"Beauty Salon",
            "type":"Services"
        }
    ],
    "sg:phone":"+1 604 607 7866",
    "sg:postcode":"V4W 2Z7",
    "sg:province":"BC",
    "wof:name":"Hair Masters",
    "wof:placetype":"venue"
},
  "geometry": {"coordinates":[-122.492721558,49.059551239],"type":"Point"}
}