{
  "type": "Feature",
  "properties": {
    "addr:full":"345 Rang 3 N Saint-Victor QC G0M 2B0",
    "addr:housenumber":"345",
    "addr:postcode":"g0m 2b0",
    "addr:street":"Rang 3 N",
    "iso:country":"CA",
    "sg:address":"345 Rang 3 N",
    "sg:city":"Saint-Victor",
    "sg:classifiers":[
        {
            "category":"Home & Garden",
            "subcategory":"Household Appliances",
            "type":"Retail Goods"
        }
    ],
    "sg:phone":"+1 418 588 6405",
    "sg:postcode":"G0M 2B0",
    "sg:province":"QC",
    "sg:tags":[
        "cleaners",
        "sewing",
        "vacuum"
    ],
    "wof:name":"Service Guy Fortin",
    "wof:placetype":"venue"
},
  "geometry": {"coordinates":[-70.9389801025,46.1695785522],"type":"Point"}
}