{
  "type": "Feature",
  "properties": {
    "addr:full":"Richmond BC V7E 2Z1",
    "addr:postcode":"v7e 2z1",
    "iso:country":"CA",
    "sg:city":"Richmond",
    "sg:classifiers":[
        {
            "category":"Personal",
            "type":"Services"
        }
    ],
    "sg:phone":"+1 604 275 4641",
    "sg:postcode":"V7E 2Z1",
    "sg:province":"BC",
    "sg:tags":[
        "therapist",
        "massage"
    ],
    "wof:name":"Turning Point Therapeutic",
    "wof:placetype":"venue"
},
  "geometry": {"coordinates":[-123.185486,49.126614],"type":"Point"}
}