{
  "type": "Feature",
  "properties": {
    "addr:full":"1649 Dufferin St Toronto ON M6H 4H5",
    "addr:housenumber":"1649",
    "addr:postcode":"m6h 4h5",
    "addr:street":"Dufferin St",
    "iso:country":"CA",
    "sg:address":"1649 Dufferin St",
    "sg:city":"Toronto",
    "sg:classifiers":[
        {
            "category":"Health Services",
            "subcategory":"Doctor",
            "type":"Services"
        }
    ],
    "sg:phone":"+1 416 652 3222",
    "sg:postcode":"M6H 4H5",
    "sg:province":"ON",
    "sg:tags":[
        "dentist"
    ],
    "wof:name":"Shelson's Offices",
    "wof:placetype":"venue"
},
  "geometry": {"coordinates":[-79.44263458250001,43.6773147583],"type":"Point"}
}