{
  "type": "Feature",
  "properties": {
    "addr:full":"17830 Yonge St Newmarket ON L3Y 8S1",
    "addr:housenumber":"17830",
    "addr:postcode":"l3y 8s1",
    "addr:street":"Yonge St",
    "iso:country":"CA",
    "sg:address":"17830 Yonge St",
    "sg:city":"Newmarket",
    "sg:classifiers":[
        {
            "category":"Restaurant",
            "type":"Food & Drink"
        }
    ],
    "sg:phone":"+1 905 967 0401",
    "sg:postcode":"L3Y 8S1",
    "sg:province":"ON",
    "wof:name":"Jack Astor's",
    "wof:placetype":"venue"
},
  "geometry": {"coordinates":[-79.482384,44.062225],"type":"Point"}
}