{
  "type": "Feature",
  "properties": {
    "addr:full":"500 Du Lac Saint-Benjamin QC G0M 1N0",
    "addr:housenumber":"500",
    "addr:postcode":"g0m 1n0",
    "addr:street":"Du Lac",
    "iso:country":"CA",
    "sg:address":"500 Du Lac",
    "sg:city":"Saint-Benjamin",
    "sg:classifiers":[
        {
            "category":"Government",
            "subcategory":"Office",
            "type":"Public Place"
        }
    ],
    "sg:phone":"+1 418 594 8988",
    "sg:postcode":"G0M 1N0",
    "sg:province":"QC",
    "sg:tags":[
        "village"
    ],
    "wof:name":"St-Benjamin Garage Municipal",
    "wof:placetype":"venue"
},
  "geometry": {"coordinates":[-70.599586,46.278755],"type":"Point"}
}