{
  "type": "Feature",
  "properties": {
    "addr:full":"130 Elgin St Brantford ON N3S 5A5",
    "addr:housenumber":"130",
    "addr:postcode":"n3s 5a5",
    "addr:street":"Elgin St",
    "iso:country":"CA",
    "sg:address":"130 Elgin St",
    "sg:city":"Brantford",
    "sg:classifiers":[
        {
            "category":"Organizations",
            "subcategory":"Religious Organization",
            "type":"Services"
        }
    ],
    "sg:phone":"+1 519 753 2361",
    "sg:postcode":"N3S 5A5",
    "sg:province":"ON",
    "sg:tags":[
        "church"
    ],
    "wof:name":"St Luke's Anglican Church",
    "wof:placetype":"venue"
},
  "geometry": {"coordinates":[-80.251625,43.149479],"type":"Point"}
}