{
  "type": "Feature",
  "properties": {
    "addr:full":"1695 Boul Saint-Joseph E Montreal QC H2J 1N1",
    "addr:housenumber":"1695",
    "addr:postcode":"h2j 1n1",
    "addr:street":"Boul Saint-Joseph E",
    "iso:country":"CA",
    "sg:address":"1695 Boul Saint-Joseph E",
    "sg:city":"Montreal",
    "sg:classifiers":[
        {
            "category":"Health Services",
            "subcategory":"Health Practitioner",
            "type":"Services"
        }
    ],
    "sg:phone":"+1 514 522 9155",
    "sg:postcode":"H2J 1N1",
    "sg:province":"QC",
    "sg:tags":[
        "acupuncture"
    ],
    "wof:name":"Harvey, Suzanne",
    "wof:placetype":"venue"
},
  "geometry": {"coordinates":[-73.58010899999999,45.534931],"type":"Point"}
}