{
  "type": "Feature",
  "properties": {
    "addr:full":"1320 3 Ave S Lethbridge AB T1J 0K5",
    "addr:housenumber":"1320",
    "addr:postcode":"t1j 0k5",
    "addr:street":"3 Ave S",
    "iso:country":"CA",
    "sg:address":"1320 3 Ave S",
    "sg:city":"Lethbridge",
    "sg:classifiers":[
        {
            "category":"Banks & Credit Unions",
            "subcategory":"Bank",
            "type":"Services"
        }
    ],
    "sg:phone":"+1 403 329 4677",
    "sg:postcode":"T1J 0K5",
    "sg:province":"AB",
    "wof:name":"First Choice Savings & Cu Ltd",
    "wof:placetype":"venue"
},
  "geometry": {"coordinates":[-112.822487,49.696472],"type":"Point"}
}