{
  "type": "Feature",
  "properties": {
    "addr:full":"North York ON M3C 3S2",
    "addr:postcode":"m3c 3s2",
    "iso:country":"CA",
    "sg:city":"North York",
    "sg:classifiers":[
        {
            "category":"Real Estate",
            "subcategory":"Developer",
            "type":"Services"
        }
    ],
    "sg:phone":"+1 416 444 9061",
    "sg:postcode":"M3C 3S2",
    "sg:province":"ON",
    "sg:tags":[
        "building",
        "contractor"
    ],
    "wof:name":"Bowood Properties",
    "wof:placetype":"venue"
},
  "geometry": {"coordinates":[-79.33697509770001,43.7235908508],"type":"Point"}
}