{
  "type": "Feature",
  "properties": {
    "iso:country":"CA",
    "sg:address":"332 Boul Cremazie O",
    "sg:city":"Montreal",
    "sg:classifiers":[
        {
            "category":"Shopping",
            "subcategory":"Clothing, Apparel, & Fashions",
            "type":"Retail Goods"
        }
    ],
    "sg:phone":"+1 514 858 7494",
    "sg:postcode":"H2P 1C7",
    "sg:province":"QC",
    "sg:tags":[
        "item",
        "boutique"
    ],
    "wof:name":"Boutique Colori",
    "wof:placetype":"venue"
},
  "geometry": {"coordinates":[-73.63910675050001,45.544418335],"type":"Point"}
}