{
  "type": "Feature",
  "properties": {
    "addr:full":"4819 47 Ave Vermilion AB T9X 1J4",
    "addr:housenumber":"4819",
    "addr:postcode":"t9x 1j4",
    "addr:street":"47 Ave",
    "iso:country":"CA",
    "sg:address":"4819 47 Ave",
    "sg:city":"Vermilion",
    "sg:classifiers":[
        {
            "category":"Manufacturing",
            "subcategory":"Metals",
            "type":"Manufacturing & Wholesale Goods"
        }
    ],
    "sg:phone":"+1 780 872 7440",
    "sg:postcode":"T9X 1J4",
    "sg:province":"AB",
    "sg:tags":[
        "pipe",
        "field",
        "oil",
        "bending",
        "fabricating"
    ],
    "wof:name":"Flint Energy Svc Ltd",
    "wof:placetype":"venue"
},
  "geometry": {"coordinates":[-110.84691619900001,53.3491821289],"type":"Point"}
}