{
  "type": "Feature",
  "properties": {
    "iso:country":"CA",
    "sg:address":"7151 Rue Jean-Talon E",
    "sg:city":"Anjou",
    "sg:classifiers":[
        {
            "category":"Professional",
            "subcategory":"Business Services",
            "type":"Services"
        }
    ],
    "sg:phone":"+1 514 351 6561",
    "sg:postcode":"H1M 3N8",
    "sg:province":"QC",
    "wof:name":"Sylvestre Freres Inc",
    "wof:placetype":"venue"
},
  "geometry": {"coordinates":[-73.56968688960001,45.5984230042],"type":"Point"}
}