{
  "type": "Feature",
  "properties": {
    "addr:full":"Surrey BC V3W 8J9",
    "addr:postcode":"v3w 8j9",
    "iso:country":"CA",
    "sg:city":"Surrey",
    "sg:classifiers":[
        {
            "category":"Manufacturing",
            "subcategory":"Tools & Machinery",
            "type":"Manufacturing & Wholesale Goods"
        }
    ],
    "sg:phone":"+1 604 596 0282",
    "sg:postcode":"V3W 8J9",
    "sg:province":"BC",
    "sg:tags":[
        "ozone",
        "machine"
    ],
    "wof:name":"Azco Industries Ltd",
    "wof:placetype":"venue"
},
  "geometry": {"coordinates":[-122.861969,49.150162],"type":"Point"}
}