{
  "type": "Feature",
  "properties": {
    "addr:full":"Cambridge ON N1R 7W4",
    "addr:postcode":"n1r 7w4",
    "iso:country":"CA",
    "sg:city":"Cambridge",
    "sg:classifiers":[
        {
            "category":"Manufacturing",
            "subcategory":"Tools & Machinery",
            "type":"Manufacturing & Wholesale Goods"
        }
    ],
    "sg:phone":"+1 519 621 2650",
    "sg:postcode":"N1R 7W4",
    "sg:province":"ON",
    "sg:tags":[
        "control"
    ],
    "wof:name":"Electrical Panel Shop Inc",
    "wof:placetype":"venue"
},
  "geometry": {"coordinates":[-80.3053359985,43.4019317627],"type":"Point"}
}