{
  "type": "Feature",
  "properties": {
    "addr:full":"67 First St Collingwood ON L9Y 1A2",
    "addr:housenumber":"67",
    "addr:postcode":"l9y 1a2",
    "addr:street":"First St",
    "iso:country":"CA",
    "sg:address":"67 First St",
    "sg:city":"Collingwood",
    "sg:classifiers":[
        {
            "category":"Real Estate",
            "subcategory":"Real Estate Agent",
            "type":"Services"
        }
    ],
    "sg:phone":"+1 705 445 8500",
    "sg:postcode":"L9Y 1A2",
    "sg:province":"ON",
    "wof:name":"Four Seasons Realty Ltd",
    "wof:placetype":"venue"
},
  "geometry": {"coordinates":[-80.219269,44.502811],"type":"Point"}
}