{
  "type": "Feature",
  "properties": {
    "iso:country":"CA",
    "sg:city":"Vancouver",
    "sg:classifiers":[
        {
            "category":"Mining & Drilling",
            "type":"Manufacturing & Wholesale Goods"
        }
    ],
    "sg:phone":"+1 604 922 1351",
    "sg:postcode":"V6C 1V5",
    "sg:province":"BC",
    "sg:tags":[
        "company"
    ],
    "wof:name":"Bitterroot Resources Ltd",
    "wof:placetype":"venue"
},
  "geometry": {"coordinates":[-123.114273071,49.2847709656],"type":"Point"}
}