{
  "type": "Feature",
  "properties": {
    "addr:full":"94 1st St S Souris MB R0K 2C0",
    "addr:housenumber":"94",
    "addr:postcode":"r0k 2c0",
    "addr:street":"1St St S",
    "iso:country":"CA",
    "sg:address":"94 1st St S",
    "sg:city":"Souris",
    "sg:classifiers":[
        {
            "category":"Shopping",
            "subcategory":"Florist",
            "type":"Retail Goods"
        }
    ],
    "sg:phone":"+1 204 483 3174",
    "sg:postcode":"R0K 2C0",
    "sg:province":"MB",
    "wof:name":"Plaza Petals",
    "wof:placetype":"venue"
},
  "geometry": {"coordinates":[-100.258865356,49.6208343506],"type":"Point"}
}