{
  "type": "Feature",
  "properties": {
    "iso:country":"CA",
    "sg:address":"188 Samuelson St",
    "sg:city":"Cambridge",
    "sg:classifiers":[
        {
            "category":"Personal",
            "subcategory":"Beauty Salon",
            "type":"Services"
        }
    ],
    "sg:phone":"+1 519 623 3031",
    "sg:postcode":"N1R 1K4",
    "sg:province":"ON",
    "wof:name":"Majestic Hair Stylists",
    "wof:placetype":"venue"
},
  "geometry": {"coordinates":[-80.3047332764,43.3703575134],"type":"Point"}
}