{
  "type": "Feature",
  "properties": {
    "addr:full":"24 Av Du Mont-Royal O #403A Montreal QC H2T 2S2",
    "addr:postcode":"h2t 2s2",
    "addr:street":"24 Av Du Mont-Royal O # 403A",
    "iso:country":"CA",
    "sg:address":"24 Av Du Mont-Royal O #403A",
    "sg:city":"Montreal",
    "sg:classifiers":[
        {
            "category":"Professional",
            "subcategory":"Business Services",
            "type":"Services"
        }
    ],
    "sg:phone":"+1 514 286 1188",
    "sg:postcode":"H2T 2S2",
    "sg:province":"QC",
    "sg:tags":[
        "fund",
        "promotion",
        "raising"
    ],
    "wof:name":"Harmony Entertainment",
    "wof:placetype":"venue"
},
  "geometry": {"coordinates":[-73.5859451294,45.5202827454],"type":"Point"}
}