{
  "type": "Feature",
  "properties": {
    "addr:full":"25 Barque Crt Lower Sackville NS B4E 2T7",
    "addr:housenumber":"25",
    "addr:postcode":"b4e 2t7",
    "addr:street":"Barque Crt",
    "iso:country":"CA",
    "sg:address":"25 Barque Crt",
    "sg:city":"Lower Sackville",
    "sg:classifiers":[
        {
            "category":"Building & Trades",
            "subcategory":"Construction",
            "type":"Services"
        }
    ],
    "sg:phone":"+1 902 864 0335",
    "sg:postcode":"B4E 2T7",
    "sg:province":"NS",
    "sg:tags":[
        "paving",
        "contractor"
    ],
    "wof:name":"First Choice Asphalt Sealing",
    "wof:placetype":"venue"
},
  "geometry": {"coordinates":[-63.709137,44.782356],"type":"Point"}
}