{
  "type": "Feature",
  "properties": {
    "addr:full":"Hemmingford QC J0L 1H0",
    "addr:postcode":"j0l 1h0",
    "iso:country":"CA",
    "sg:city":"Hemmingford",
    "sg:classifiers":[
        {
            "category":"Manufacturing",
            "subcategory":"Tools & Machinery",
            "type":"Manufacturing & Wholesale Goods"
        }
    ],
    "sg:phone":"+1 450 247 3522",
    "sg:postcode":"J0L 1H0",
    "sg:province":"QC",
    "sg:tags":[
        "machine",
        "shop"
    ],
    "wof:name":"Lasalle Instrument Parts CO",
    "wof:placetype":"venue"
},
  "geometry": {"coordinates":[-73.52649700000001,45.072453],"type":"Point"}
}