{
  "type": "Feature",
  "properties": {
    "addr:full":"21 Commerce Park Dr Barrie ON L4N 8X1",
    "addr:housenumber":"21",
    "addr:postcode":"l4n 8x1",
    "addr:street":"Commerce Park Dr",
    "iso:country":"CA",
    "sg:address":"21 Commerce Park Dr",
    "sg:city":"Barrie",
    "sg:classifiers":[
        {
            "category":"Restaurant",
            "type":"Food & Drink"
        }
    ],
    "sg:phone":"+1 705 730 6886",
    "sg:postcode":"L4N 8X1",
    "sg:province":"ON",
    "wof:name":"Shoeless Joe's Restaurant",
    "wof:placetype":"venue"
},
  "geometry": {"coordinates":[-79.686256,44.32967],"type":"Point"}
}