{
  "type": "Feature",
  "properties": {
    "addr:full":"144 3rd Ave W Melville SK S0A 2P0",
    "addr:housenumber":"144",
    "addr:postcode":"s0a 2p0",
    "addr:street":"3Rd Ave W",
    "iso:country":"CA",
    "sg:address":"144 3rd Ave W",
    "sg:city":"Melville",
    "sg:classifiers":[
        {
            "category":"Professional",
            "subcategory":"Lawyer & Legal Services",
            "type":"Services"
        }
    ],
    "sg:phone":"+1 306 728 4533",
    "sg:postcode":"S0A 2P0",
    "sg:province":"SK",
    "sg:tags":[
        "attorney"
    ],
    "wof:name":"Gattinger Law Office",
    "wof:placetype":"venue"
},
  "geometry": {"coordinates":[-102.816093,50.931126],"type":"Point"}
}