{
  "type": "Feature",
  "properties": {
    "iso:country":"CA",
    "sg:address":"2094 Dundas St",
    "sg:city":"London",
    "sg:classifiers":[
        {
            "category":"Food & Beverages",
            "subcategory":"Bakery",
            "type":"Retail Goods"
        }
    ],
    "sg:phone":"+1 519 453 9758",
    "sg:postcode":"N5V 1R2",
    "sg:province":"ON",
    "sg:tags":[
        "tea",
        "coffee",
        "doughnut"
    ],
    "wof:name":"Tim Hortons",
    "wof:placetype":"venue"
},
  "geometry": {"coordinates":[-81.161453,43.008877],"type":"Point"}
}