{
  "type": "Feature",
  "properties": {
    "addr:full":"189 Hutchinson Rd Lowbanks ON N0A 1K0",
    "addr:housenumber":"189",
    "addr:postcode":"n0a 1k0",
    "addr:street":"Hutchinson Rd",
    "iso:country":"CA",
    "sg:address":"189 Hutchinson Rd",
    "sg:city":"Lowbanks",
    "sg:classifiers":[
        {
            "category":"Retail",
            "subcategory":"Repair Shop",
            "type":"Services"
        }
    ],
    "sg:phone":"+1 905 899 3355",
    "sg:postcode":"N0A 1K0",
    "sg:province":"ON",
    "sg:tags":[
        "upholsterer"
    ],
    "wof:name":"Dana's Upholstery & Draperies",
    "wof:placetype":"venue"
},
  "geometry": {"coordinates":[-79.45966300000001,42.887207],"type":"Point"}
}