{
  "type": "Feature",
  "properties": {
    "addr:full":"212 Second St S Kenora ON P9N 1G2",
    "addr:housenumber":"212",
    "addr:postcode":"p9n 1g2",
    "addr:street":"Second St S",
    "iso:country":"CA",
    "sg:address":"212 Second St S",
    "sg:city":"Kenora",
    "sg:classifiers":[
        {
            "category":"Manufacturing",
            "subcategory":"Electronics",
            "type":"Manufacturing & Wholesale Goods"
        }
    ],
    "sg:phone":"+1 807 468 6660",
    "sg:postcode":"P9N 1G2",
    "sg:province":"ON",
    "sg:tags":[
        "machine",
        "communication",
        "duplicating",
        "copying"
    ],
    "wof:name":"Wilson's Business Solutions",
    "wof:placetype":"venue"
},
  "geometry": {"coordinates":[-94.490082,49.766312],"type":"Point"}
}