{
  "type": "Feature",
  "properties": {
    "addr:full":"100 Clifford St Sarnia ON N7T 8C4",
    "addr:housenumber":"100",
    "addr:postcode":"n7t 8c4",
    "addr:street":"Clifford St",
    "iso:country":"CA",
    "sg:address":"100 Clifford St",
    "sg:city":"Sarnia",
    "sg:classifiers":[
        {
            "category":"Wholesale",
            "subcategory":"Construction Materials",
            "type":"Manufacturing & Wholesale Goods"
        }
    ],
    "sg:phone":"+1 519 332 1557",
    "sg:postcode":"N7T 8C4",
    "sg:province":"ON",
    "sg:tags":[
        "sand",
        "gravel",
        "stone"
    ],
    "wof:name":"Lafarge Canada Inc",
    "wof:placetype":"venue"
},
  "geometry": {"coordinates":[-82.418297,42.95615],"type":"Point"}
}