{
  "type": "Feature",
  "properties": {
    "addr:full":"364 Huron St E RR 3 Exeter ON N0M 1S5",
    "addr:housenumber":"364",
    "addr:postcode":"n0m 1s5",
    "addr:street":"Huron St;Rr 3",
    "iso:country":"CA",
    "sg:address":"364 Huron St E RR 3",
    "sg:city":"Exeter",
    "sg:classifiers":[
        {
            "category":"Social Services",
            "type":"Services"
        }
    ],
    "sg:phone":"+1 519 235 2963",
    "sg:postcode":"N0M 1S5",
    "sg:province":"ON",
    "sg:tags":[
        "organization",
        "welfare"
    ],
    "wof:name":"Anago Resources",
    "wof:placetype":"venue"
},
  "geometry": {"coordinates":[-81.480225,43.345482],"type":"Point"}
}