{
  "type": "Feature",
  "properties": {
    "addr:full":"5717 50A Ave Stettler AB T0C 2L2",
    "addr:housenumber":"5717",
    "addr:postcode":"t0c 2l2",
    "addr:street":"50A Ave",
    "iso:country":"CA",
    "sg:address":"5717 50A Ave",
    "sg:city":"Stettler",
    "sg:classifiers":[
        {
            "category":"Organizations",
            "subcategory":"Religious Organization",
            "type":"Services"
        }
    ],
    "sg:phone":"+1 403 742 2210",
    "sg:postcode":"T0C 2L2",
    "sg:province":"AB",
    "sg:tags":[
        "church"
    ],
    "wof:name":"Church of the Nazarene",
    "wof:placetype":"venue"
},
  "geometry": {"coordinates":[-112.716347,52.325821],"type":"Point"}
}