{
  "type": "Feature",
  "properties": {
    "addr:full":"205 Toryork Dr North York ON M9L 1Y2",
    "addr:housenumber":"205",
    "addr:postcode":"m9l 1y2",
    "addr:street":"Toryork Dr",
    "iso:country":"CA",
    "sg:address":"205 Toryork Dr",
    "sg:city":"North York",
    "sg:classifiers":[
        {
            "category":"Retail",
            "subcategory":"Auto Repair",
            "type":"Services"
        }
    ],
    "sg:phone":"+1 416 748 2525",
    "sg:postcode":"M9L 1Y2",
    "sg:province":"ON",
    "sg:tags":[
        "wrecker"
    ],
    "wof:name":"A K Towing Inc",
    "wof:placetype":"venue"
},
  "geometry": {"coordinates":[-79.559921,43.760597],"type":"Point"}
}