{
  "type": "Feature",
  "properties": {
    "addr:full":"454 Haines St Ingersoll ON N5C 2S5",
    "addr:housenumber":"454",
    "addr:postcode":"n5c 2s5",
    "addr:street":"Haines St",
    "iso:country":"CA",
    "sg:address":"454 Haines St",
    "sg:city":"Ingersoll",
    "sg:classifiers":[
        {
            "category":"Building & Trades",
            "subcategory":"Plumbing",
            "type":"Services"
        }
    ],
    "sg:phone":"+1 519 485 2728",
    "sg:postcode":"N5C 2S5",
    "sg:province":"ON",
    "sg:tags":[
        "conditioning",
        "air",
        "refrigeration",
        "system",
        "contractor"
    ],
    "wof:name":"R Dorland Refrigeration Ltd",
    "wof:placetype":"venue"
},
  "geometry": {"coordinates":[-80.88385,43.038116],"type":"Point"}
}