{
  "type": "Feature",
  "properties": {
    "addr:full":"249 Hector Cres Regina SK S4Y 1C4",
    "addr:housenumber":"249",
    "addr:postcode":"s4y 1c4",
    "addr:street":"Hector Cres",
    "iso:country":"CA",
    "sg:address":"249 Hector Cres",
    "sg:city":"Regina",
    "sg:classifiers":[
        {
            "category":"Professional",
            "subcategory":"Engineering",
            "type":"Services"
        }
    ],
    "sg:phone":"+1 306 545 5586",
    "sg:postcode":"S4Y 1C4",
    "sg:province":"SK",
    "sg:tags":[
        "engineer"
    ],
    "wof:name":"Beval Engineering Inc",
    "wof:placetype":"venue"
},
  "geometry": {"coordinates":[-104.69465599999999,50.480659],"type":"Point"}
}