{
  "type": "Feature",
  "properties": {
    "addr:full":"195 Rue Marquette Sherbrooke QC J1H 1L6",
    "addr:housenumber":"195",
    "addr:postcode":"j1h 1l6",
    "addr:street":"Rue Marquette",
    "iso:country":"CA",
    "sg:address":"195 Rue Marquette",
    "sg:city":"Sherbrooke",
    "sg:classifiers":[
        {
            "category":"Education",
            "subcategory":"School",
            "type":"Public Place"
        }
    ],
    "sg:phone":"+1 819 563 2050",
    "sg:postcode":"J1H 1L6",
    "sg:province":"QC",
    "wof:name":"Seminaire DE Sherbrooke",
    "wof:placetype":"venue"
},
  "geometry": {"coordinates":[-71.8937911987,45.4027061462],"type":"Point"}
}