{
  "type": "Feature",
  "properties": {
    "addr:full":"110 Rue Saint-Hubert L'Assomption QC J5W 3S7",
    "addr:housenumber":"110",
    "addr:postcode":"j5w 3s7",
    "addr:street":"Rue Saint-Hubert",
    "iso:country":"CA",
    "sg:address":"110 Rue Saint-Hubert",
    "sg:city":"L'Assomption",
    "sg:classifiers":[
        {
            "category":"Retail",
            "subcategory":"Auto Repair",
            "type":"Services"
        }
    ],
    "sg:phone":"+1 450 589 4307",
    "sg:postcode":"J5W 3S7",
    "sg:province":"QC",
    "sg:tags":[
        "repairing",
        "automobile"
    ],
    "wof:name":"Garage Simon Martel",
    "wof:placetype":"venue"
},
  "geometry": {"coordinates":[-73.41886901860001,45.8268928528],"type":"Point"}
}