{
  "type": "Feature",
  "properties": {
    "iso:country":"CA",
    "sg:address":"682 110th St",
    "sg:city":"North Battleford",
    "sg:classifiers":[
        {
            "category":"Retail",
            "subcategory":"Auto Repair",
            "type":"Services"
        }
    ],
    "sg:phone":"+1 306 445 0400",
    "sg:postcode":"S9A 2G6",
    "sg:province":"SK",
    "sg:tags":[
        "body",
        "automobile",
        "painting"
    ],
    "wof:name":"North Town Auto Body Svc",
    "wof:placetype":"venue"
},
  "geometry": {"coordinates":[-108.284095764,52.7673606873],"type":"Point"}
}