{
  "type": "Feature",
  "properties": {
    "addr:full":"Galiano BC V0N 1P0",
    "addr:postcode":"v0n 1p0",
    "iso:country":"CA",
    "sg:city":"Galiano",
    "sg:classifiers":[
        {
            "category":"Education",
            "subcategory":"Vocational School",
            "type":"Public Place"
        }
    ],
    "sg:phone":"+1 250 539 5729",
    "sg:postcode":"V0N 1P0",
    "sg:province":"BC",
    "sg:tags":[
        "technical",
        "trade"
    ],
    "wof:name":"Gulf Island Film & Television",
    "wof:placetype":"venue"
},
  "geometry": {"coordinates":[-123.576561,48.988461],"type":"Point"}
}