{
  "type": "Feature",
  "properties": {
    "addr:full":"118 Union St Woodstock NB E7M 2X1",
    "addr:housenumber":"118",
    "addr:postcode":"e7m 2x1",
    "addr:street":"Union St",
    "iso:country":"CA",
    "sg:address":"118 Union St",
    "sg:city":"Woodstock",
    "sg:classifiers":[
        {
            "category":"Shopping",
            "subcategory":"Bicycles & Sporting Goods",
            "type":"Retail Goods"
        }
    ],
    "sg:phone":"+1 506 328 3150",
    "sg:postcode":"E7M 2X1",
    "sg:province":"NB",
    "wof:name":"Steeves Bike Shop Ltd",
    "wof:placetype":"venue"
},
  "geometry": {"coordinates":[-67.5776062012,46.144618988],"type":"Point"}
}