{
  "type": "Feature",
  "properties": {
    "addr:full":"723 Millidge Ave Saint John NB E2K 2N7",
    "addr:housenumber":"723",
    "addr:postcode":"e2k 2n7",
    "addr:street":"Millidge Ave",
    "iso:country":"CA",
    "sg:address":"723 Millidge Ave",
    "sg:city":"Saint John",
    "sg:classifiers":[
        {
            "category":"Health Services",
            "subcategory":"Doctor",
            "type":"Services"
        }
    ],
    "sg:phone":"+1 506 634 6869",
    "sg:postcode":"E2K 2N7",
    "sg:province":"NB",
    "sg:tags":[
        "physician",
        "surgeon"
    ],
    "wof:name":"Comeau, Laurel MD",
    "wof:placetype":"venue"
},
  "geometry": {"coordinates":[-66.09716796879999,45.2948303223],"type":"Point"}
}