{
  "type": "Feature",
  "properties": {
    "addr:full":"450 Av Ogilvy Montreal QC H3N 1M6",
    "addr:housenumber":"450",
    "addr:postcode":"h3n 1m6",
    "addr:street":"Av Ogilvy",
    "iso:country":"CA",
    "sg:address":"450 Av Ogilvy",
    "sg:city":"Montreal",
    "sg:classifiers":[
        {
            "category":"Food & Beverages",
            "subcategory":"Groceries & Convenience Stores",
            "type":"Retail Goods"
        }
    ],
    "sg:phone":"+1 514 279 9767",
    "sg:postcode":"H3N 1M6",
    "sg:province":"QC",
    "sg:tags":[
        "grocer"
    ],
    "wof:name":"C & C Food Inc",
    "wof:placetype":"venue"
},
  "geometry": {"coordinates":[-73.6248626709,45.5295600891],"type":"Point"}
}