{
  "type": "Feature",
  "properties": {
    "iso:country":"CA",
    "sg:address":"522 Rte DE LA Seigneurie",
    "sg:city":"Saint-Roch-Des-Aulnaies",
    "sg:classifiers":[
        {
            "category":"Retail",
            "subcategory":"Veterinary Services",
            "type":"Services"
        }
    ],
    "sg:phone":"+1 418 354 7760",
    "sg:postcode":"G0R 4E0",
    "sg:province":"QC",
    "sg:tags":[
        "veterinarian"
    ],
    "wof:name":"Clinique Veterinaire-Aulnaies",
    "wof:placetype":"venue"
},
  "geometry": {"coordinates":[-70.14339447019999,47.3160133362],"type":"Point"}
}