{
  "type": "Feature",
  "properties": {
    "addr:full":"Oakville ON L6K 2E9",
    "addr:postcode":"l6k 2e9",
    "iso:country":"CA",
    "sg:city":"Oakville",
    "sg:classifiers":[
        {
            "category":"Food & Beverages",
            "subcategory":"Specialty",
            "type":"Retail Goods"
        }
    ],
    "sg:phone":"+1 905 844 4736",
    "sg:postcode":"L6K 2E9",
    "sg:province":"ON",
    "sg:tags":[
        "water",
        "bulk",
        "treatment"
    ],
    "wof:name":"Oakville Vacuum Ltd",
    "wof:placetype":"venue"
},
  "geometry": {"coordinates":[-79.68955200000001,43.443977],"type":"Point"}
}