{
  "type": "Feature",
  "properties": {
    "addr:full":"Montreal QC H3B 4J1",
    "addr:postcode":"h3b 4j1",
    "iso:country":"CA",
    "sg:city":"Montreal",
    "sg:classifiers":[
        {
            "category":"Banks & Credit Unions",
            "subcategory":"Investment Brokerage",
            "type":"Services"
        }
    ],
    "sg:phone":"+1 514 394 3000",
    "sg:postcode":"H3B 4J1",
    "sg:province":"QC",
    "wof:name":"Mac Dougall Mac Dougall Inc",
    "wof:placetype":"venue"
},
  "geometry": {"coordinates":[-73.55368804930001,45.5153923035],"type":"Point"}
}