{
  "type": "Feature",
  "properties": {
    "addr:full":"286 Regal Ave Winnipeg MB R2M 0P5",
    "addr:housenumber":"286",
    "addr:postcode":"r2m 0p5",
    "addr:street":"Regal Ave",
    "iso:country":"CA",
    "sg:address":"286 Regal Ave",
    "sg:city":"Winnipeg",
    "sg:classifiers":[
        {
            "category":"Recreation",
            "type":"Entertainment"
        }
    ],
    "sg:phone":"+1 204 256 3623",
    "sg:postcode":"R2M 0P5",
    "sg:province":"MB",
    "sg:tags":[
        "club",
        "curling"
    ],
    "wof:name":"St Vital Curling Club",
    "wof:placetype":"venue"
},
  "geometry": {"coordinates":[-97.103279,49.85857],"type":"Point"}
}