{
  "type": "Feature",
  "properties": {
    "addr:full":"625 Third Line Oakville ON L6L 4A8",
    "addr:housenumber":"625",
    "addr:postcode":"l6l 4a8",
    "addr:street":"Third Line",
    "iso:country":"CA",
    "sg:address":"625 Third Line",
    "sg:city":"Oakville",
    "sg:classifiers":[
        {
            "category":"Restaurant",
            "type":"Food & Drink"
        }
    ],
    "sg:phone":"+1 905 827 2581",
    "sg:postcode":"L6L 4A8",
    "sg:province":"ON",
    "wof:name":"A & W Family Restaurant",
    "wof:placetype":"venue"
},
  "geometry": {"coordinates":[-79.716644,43.418343],"type":"Point"}
}