{
  "type": "Feature",
  "properties": {
    "addr:full":"135 Oak St N Eastend SK S0N 0T0",
    "addr:housenumber":"135",
    "addr:postcode":"s0n 0t0",
    "addr:street":"Oak St N Eastend",
    "iso:country":"CA",
    "sg:address":"135 Oak St N",
    "sg:city":"Eastend",
    "sg:classifiers":[
        {
            "category":"Recreation",
            "type":"Entertainment"
        }
    ],
    "sg:phone":"+1 306 295 3788",
    "sg:postcode":"S0N 0T0",
    "sg:province":"SK",
    "sg:tags":[
        "hall",
        "auditorium"
    ],
    "wof:name":"Eastend Memorial Hall",
    "wof:placetype":"venue"
},
  "geometry": {"coordinates":[-108.82870483400001,49.5136566162],"type":"Point"}
}