{
  "type": "Feature",
  "properties": {
    "addr:full":"Guelph ON N1E 6L9",
    "addr:postcode":"n1e 6l9",
    "iso:country":"CA",
    "sg:city":"Guelph",
    "sg:classifiers":[
        {
            "category":"Health Services",
            "subcategory":"Doctor",
            "type":"Services"
        }
    ],
    "sg:phone":"+1 519 763 7433",
    "sg:postcode":"N1E 6L9",
    "sg:province":"ON",
    "sg:tags":[
        "physician",
        "surgeon"
    ],
    "wof:name":"Armstrong, Don MD",
    "wof:placetype":"venue"
},
  "geometry": {"coordinates":[-80.252281189,43.5548171997],"type":"Point"}
}