{
  "type": "Feature",
  "properties": {
    "addr:full":"6957 Beresford St Burnaby BC V5E 1B9",
    "addr:housenumber":"6957",
    "addr:postcode":"v5e 1b9",
    "addr:street":"Beresford St",
    "iso:country":"CA",
    "sg:address":"6957 Beresford St",
    "sg:city":"Burnaby",
    "sg:classifiers":[
        {
            "category":"Home & Garden",
            "subcategory":"Hardware",
            "type":"Retail Goods"
        }
    ],
    "sg:phone":"+1 604 522 5611",
    "sg:postcode":"V5E 1B9",
    "sg:province":"BC",
    "sg:tags":[
        "saw"
    ],
    "wof:name":"Regent Steel Specialties Ltd",
    "wof:placetype":"venue"
},
  "geometry": {"coordinates":[-122.960083,49.217239],"type":"Point"}
}