{
  "type": "Feature",
  "properties": {
    "iso:country":"CA",
    "sg:address":"2320 Keele St",
    "sg:city":"North York",
    "sg:classifiers":[
        {
            "category":"Home & Garden",
            "subcategory":"Furniture",
            "type":"Retail Goods"
        }
    ],
    "sg:phone":"+1 416 245 1712",
    "sg:postcode":"M6M 3Z8",
    "sg:province":"ON",
    "sg:tags":[
        "infant",
        "wear"
    ],
    "wof:name":"Keele Furniture Warehouse Ltd",
    "wof:placetype":"venue"
},
  "geometry": {"coordinates":[-79.477127,43.703884],"type":"Point"}
}