{
  "type": "Feature",
  "properties": {
    "addr:full":"12709 228 St Maple Ridge BC V2X 3M1",
    "addr:housenumber":"12709",
    "addr:postcode":"v2x 3m1",
    "addr:street":"228 St",
    "iso:country":"CA",
    "sg:address":"12709 228 St",
    "sg:city":"Maple Ridge",
    "sg:classifiers":[
        {
            "category":"Building & Trades",
            "subcategory":"Construction",
            "type":"Services"
        }
    ],
    "sg:phone":"+1 604 467 3626",
    "sg:postcode":"V2X 3M1",
    "sg:province":"BC",
    "sg:tags":[
        "general",
        "contractor"
    ],
    "wof:name":"Ugs Contractors Ltd",
    "wof:placetype":"venue"
},
  "geometry": {"coordinates":[-122.590431,49.232883],"type":"Point"}
}