{
  "type": "Feature",
  "properties": {
    "addr:full":"7464 Boul Maurice-Duplessis #A Montreal QC H1E 3Y1",
    "addr:housenumber":"7464",
    "addr:postcode":"h1e 3y1",
    "addr:street":"Boul Maurice-Duplessis # A",
    "iso:country":"CA",
    "sg:address":"7464 Boul Maurice-Duplessis #A",
    "sg:city":"Montreal",
    "sg:classifiers":[
        {
            "category":"Shopping",
            "subcategory":"Clothing, Apparel, & Fashions",
            "type":"Retail Goods"
        }
    ],
    "sg:phone":"+1 514 881 1028",
    "sg:postcode":"H1E 3Y1",
    "sg:province":"QC",
    "sg:tags":[
        "tailor"
    ],
    "wof:name":"Creations Angelo",
    "wof:placetype":"venue"
},
  "geometry": {"coordinates":[-73.599174,45.625092],"type":"Point"}
}