{
  "type": "Feature",
  "properties": {
    "addr:full":"52 Lanewood Dr Aurora ON L4G 4V3",
    "addr:housenumber":"52",
    "addr:postcode":"l4g 4v3",
    "addr:street":"Lanewood Dr",
    "iso:country":"CA",
    "sg:address":"52 Lanewood Dr",
    "sg:city":"Aurora",
    "sg:classifiers":[
        {
            "category":"Building & Trades",
            "subcategory":"Construction",
            "type":"Services"
        }
    ],
    "sg:phone":"+1 905 727 6753",
    "sg:postcode":"L4G 4V3",
    "sg:province":"ON",
    "sg:tags":[
        "general",
        "contractor"
    ],
    "wof:name":"Martin P Paivio & Assoc Ltd",
    "wof:placetype":"venue"
},
  "geometry": {"coordinates":[-79.48611450200001,44.0085792542],"type":"Point"}
}