{
  "type": "Feature",
  "properties": {
    "iso:country":"CA",
    "sg:address":"847 Rue Cherrier",
    "sg:city":"Montreal",
    "sg:classifiers":[
        {
            "category":"Professional",
            "subcategory":"Lawyer & Legal Services",
            "type":"Services"
        }
    ],
    "sg:phone":"+1 514 596 0299",
    "sg:postcode":"H2L 1H6",
    "sg:province":"QC",
    "sg:tags":[
        "attorney"
    ],
    "wof:name":"DE Latremoille & Messier",
    "wof:placetype":"venue"
},
  "geometry": {"coordinates":[-73.5680923462,45.5204772949],"type":"Point"}
}