{
  "type": "Feature",
  "properties": {
    "addr:full":"Calgary AB T2R 1M6",
    "addr:postcode":"t2r 1m6",
    "iso:country":"CA",
    "sg:city":"Calgary",
    "sg:classifiers":[
        {
            "category":"Mining & Drilling",
            "type":"Manufacturing & Wholesale Goods"
        }
    ],
    "sg:phone":"+1 403 229 3020",
    "sg:postcode":"T2R 1M6",
    "sg:province":"AB",
    "sg:tags":[
        "company",
        "oil"
    ],
    "wof:name":"Ace Resources Corp",
    "wof:placetype":"venue"
},
  "geometry": {"coordinates":[-114.081832886,51.0406150818],"type":"Point"}
}