{
  "type": "Feature",
  "properties": {
    "addr:full":"SW 1-15-12W Gladstone MB R0J 0T0",
    "addr:postcode":"r0j 0t0",
    "addr:street":"Sw",
    "iso:country":"CA",
    "sg:address":"SW 1-15-12W",
    "sg:city":"Gladstone",
    "sg:classifiers":[
        {
            "category":"Professional",
            "subcategory":"Accounting & Tax Preparation",
            "type":"Services"
        }
    ],
    "sg:phone":"+1 204 385 2812",
    "sg:postcode":"R0J 0T0",
    "sg:province":"MB",
    "sg:tags":[
        "return",
        "filing"
    ],
    "wof:name":"A & M Income Tax Svc",
    "wof:placetype":"venue"
},
  "geometry": {"coordinates":[-98.9507522583,50.2254219055],"type":"Point"}
}