{
  "type": "Feature",
  "properties": {
    "iso:country":"CA",
    "sg:address":"1660 Bloor St W",
    "sg:city":"Toronto",
    "sg:classifiers":[
        {
            "category":"Retail",
            "subcategory":"Auto Repair",
            "type":"Services"
        }
    ],
    "sg:phone":"+1 416 762 7571",
    "sg:postcode":"M6P 1A8",
    "sg:province":"ON",
    "sg:tags":[
        "repairing",
        "automobile"
    ],
    "wof:name":"Midas Auto Svc Experts",
    "wof:placetype":"venue"
},
  "geometry": {"coordinates":[-79.457436,43.655396],"type":"Point"}
}