{
  "type": "Feature",
  "properties": {
    "addr:full":"384 Rideau St Ottawa ON K1N 5Y8",
    "addr:housenumber":"384",
    "addr:postcode":"k1n 5y8",
    "addr:street":"Rideau St",
    "iso:country":"CA",
    "sg:address":"384 Rideau St",
    "sg:city":"Ottawa",
    "sg:classifiers":[
        {
            "category":"Manufacturing",
            "subcategory":"Food",
            "type":"Manufacturing & Wholesale Goods"
        }
    ],
    "sg:phone":"+1 613 789 1019",
    "sg:postcode":"K1N 5Y8",
    "sg:province":"ON",
    "sg:tags":[
        "bakery",
        "prod",
        "cookie"
    ],
    "wof:name":"Rideau Bakery",
    "wof:placetype":"venue"
},
  "geometry": {"coordinates":[-75.68296100000001,45.429787],"type":"Point"}
}