{
  "type": "Feature",
  "properties": {
    "addr:full":"232 Av Paquet Pointe-Au-Pere QC G5M 1J6",
    "addr:housenumber":"232",
    "addr:postcode":"g5m 1j6",
    "addr:street":"Av Paquet Pointe-Au-Pere",
    "iso:country":"CA",
    "sg:address":"232 Av Paquet",
    "sg:city":"Pointe-Au-Pere",
    "sg:classifiers":[
        {
            "category":"Building & Trades",
            "subcategory":"Construction",
            "type":"Services"
        }
    ],
    "sg:phone":"+1 418 725 7070",
    "sg:postcode":"G5M 1J6",
    "sg:province":"QC",
    "sg:tags":[
        "repairing",
        "remodeling",
        "contractor"
    ],
    "wof:name":"Renovation Serge Thibault",
    "wof:placetype":"venue"
},
  "geometry": {"coordinates":[-68.474739,48.502258],"type":"Point"}
}