{
  "type": "Feature",
  "properties": {
    "iso:country":"CA",
    "sg:address":"1172 Goyeau St",
    "sg:city":"Windsor",
    "sg:classifiers":[
        {
            "category":"Real Estate",
            "subcategory":"Real Estate Agent",
            "type":"Services"
        }
    ],
    "sg:phone":"+1 519 971 2070",
    "sg:postcode":"N9A 1J1",
    "sg:province":"ON",
    "sg:tags":[
        "appraiser"
    ],
    "wof:name":"Vanguard Appraisal",
    "wof:placetype":"venue"
},
  "geometry": {"coordinates":[-83.0295791626,42.3067207336],"type":"Point"}
}