{
  "type": "Feature",
  "properties": {
    "addr:full":"355 Rue Bonin Acton Vale QC J0H 1A0",
    "addr:housenumber":"355",
    "addr:postcode":"j0h 1a0",
    "addr:street":"Rue Bonin",
    "iso:country":"CA",
    "sg:address":"355 Rue Bonin",
    "sg:city":"Acton Vale",
    "sg:classifiers":[
        {
            "category":"Manufacturing",
            "subcategory":"Food",
            "type":"Manufacturing & Wholesale Goods"
        }
    ],
    "sg:phone":"+1 450 546 3279",
    "sg:postcode":"J0H 1A0",
    "sg:province":"QC",
    "sg:tags":[
        "product",
        "manufacturer"
    ],
    "wof:name":"Miss Arachew",
    "wof:placetype":"venue"
},
  "geometry": {"coordinates":[-72.5754699707,45.6379737854],"type":"Point"}
}