{
  "type": "Feature",
  "properties": {
    "addr:full":"24 Huron Ave Sydney Mines NS B1V 2H3",
    "addr:housenumber":"24",
    "addr:postcode":"b1v 2h3",
    "addr:street":"Huron Ave",
    "iso:country":"CA",
    "sg:address":"24 Huron Ave",
    "sg:city":"Sydney Mines",
    "sg:classifiers":[
        {
            "category":"Organizations",
            "subcategory":"Religious Organization",
            "type":"Services"
        }
    ],
    "sg:phone":"+1 902 736 9233",
    "sg:postcode":"B1V 2H3",
    "sg:province":"NS",
    "sg:tags":[
        "church"
    ],
    "wof:name":"Carmen United Church Manse",
    "wof:placetype":"venue"
},
  "geometry": {"coordinates":[-60.227043,46.237576],"type":"Point"}
}