{
  "type": "Feature",
  "properties": {
    "addr:full":"62 Rue Wakeham Gaspe QC G4X 1P8",
    "addr:housenumber":"62",
    "addr:postcode":"g4x 1p8",
    "addr:street":"Rue Wakeham",
    "iso:country":"CA",
    "sg:address":"62 Rue Wakeham",
    "sg:city":"Gaspe",
    "sg:classifiers":[
        {
            "category":"Building & Trades",
            "subcategory":"Electrical",
            "type":"Services"
        }
    ],
    "sg:phone":"+1 418 368 5333",
    "sg:postcode":"G4X 1P8",
    "sg:province":"QC",
    "sg:tags":[
        "electric",
        "contractor"
    ],
    "wof:name":"Cote, Ange-Marie",
    "wof:placetype":"venue"
},
  "geometry": {"coordinates":[-64.49211099999999,48.83194],"type":"Point"}
}