{
  "type": "Feature",
  "properties": {
    "addr:full":"Lynn Haven Dr Gads Hill Station ON N0K 1J0",
    "addr:postcode":"n0k 1j0",
    "addr:street":"Lynn Haven Dr;Station",
    "iso:country":"CA",
    "sg:address":"Lynn Haven Dr",
    "sg:city":"Gads Hill Station",
    "sg:classifiers":[
        {
            "category":"Shopping",
            "subcategory":"Hobbies, Toys, & Games",
            "type":"Retail Goods"
        }
    ],
    "sg:phone":"+1 519 271 8620",
    "sg:postcode":"N0K 1J0",
    "sg:province":"ON",
    "sg:tags":[
        "equipment",
        "ceramic",
        "supply"
    ],
    "wof:name":"Plain & Fancy Ceramics",
    "wof:placetype":"venue"
},
  "geometry": {"coordinates":[-80.925247,43.444206],"type":"Point"}
}