{
  "type": "Feature",
  "properties": {
    "addr:full":"384 St Paul Ave Brantford ON N3R 4N4",
    "addr:housenumber":"384",
    "addr:postcode":"n3r 4n4",
    "addr:street":"St Paul Ave",
    "iso:country":"CA",
    "sg:address":"384 St Paul Ave",
    "sg:city":"Brantford",
    "sg:classifiers":[
        {
            "category":"Health Services",
            "subcategory":"Nursing And Care Facility",
            "type":"Services"
        }
    ],
    "sg:phone":"+1 519 754 0000",
    "sg:postcode":"N3R 4N4",
    "sg:province":"ON",
    "sg:tags":[
        "home",
        "retirement",
        "community"
    ],
    "wof:name":"Amber Lea Place",
    "wof:placetype":"venue"
},
  "geometry": {"coordinates":[-80.273849,43.157349],"type":"Point"}
}