{
  "type": "Feature",
  "properties": {
    "addr:full":"202 3rd Ave W Biggar SK S0K 0M0",
    "addr:housenumber":"202",
    "addr:postcode":"s0k 0m0",
    "addr:street":"3Rd Ave W Biggar",
    "iso:country":"CA",
    "sg:address":"202 3rd Ave W",
    "sg:city":"Biggar",
    "sg:classifiers":[
        {
            "category":"Government",
            "subcategory":"Office",
            "type":"Public Place"
        }
    ],
    "sg:phone":"+1 306 948 3317",
    "sg:postcode":"S0K 0M0",
    "sg:province":"SK",
    "sg:tags":[
        "municipality"
    ],
    "wof:name":"Biggar Town Office",
    "wof:placetype":"venue"
},
  "geometry": {"coordinates":[-107.98709100000001,52.063854],"type":"Point"}
}