{
  "type": "Feature",
  "properties": {
    "addr:full":"Scarborough ON M1E 3E6",
    "addr:postcode":"m1e 3e6",
    "iso:country":"CA",
    "sg:city":"Scarborough",
    "sg:classifiers":[
        {
            "category":"Shopping",
            "subcategory":"Tobacco",
            "type":"Retail Goods"
        }
    ],
    "sg:phone":"+1 416 281 9540",
    "sg:postcode":"M1E 3E6",
    "sg:province":"ON",
    "sg:tags":[
        "cigarette",
        "cigar",
        "dealer"
    ],
    "wof:name":"Villager Smoke & Gift",
    "wof:placetype":"venue"
},
  "geometry": {"coordinates":[-79.18607299999999,43.768829],"type":"Point"}
}