{
  "type": "Feature",
  "properties": {
    "addr:full":"608 Rue Principale LA Sarre QC J9Z 2P3",
    "addr:housenumber":"608",
    "addr:postcode":"j9z 2p3",
    "addr:street":"Rue Principale La Sarre",
    "iso:country":"CA",
    "sg:address":"608 Rue Principale",
    "sg:city":"LA Sarre",
    "sg:classifiers":[
        {
            "category":"Farming",
            "subcategory":"Livestock Farm",
            "type":"Manufacturing & Wholesale Goods"
        }
    ],
    "sg:phone":"+1 819 333 4152",
    "sg:postcode":"J9Z 2P3",
    "sg:province":"QC",
    "sg:tags":[
        "circus",
        "broker",
        "animal",
        "dealer"
    ],
    "wof:name":"Entreprises C Pouliot Inc",
    "wof:placetype":"venue"
},
  "geometry": {"coordinates":[-79.2054901123,48.7926864624],"type":"Point"}
}