{
  "type": "Feature",
  "properties": {
    "iso:country":"CA",
    "sg:address":"637 the Queensway #1A",
    "sg:city":"Peterborough",
    "sg:classifiers":[
        {
            "category":"Shopping",
            "subcategory":"Clothing, Apparel, & Fashions",
            "type":"Retail Goods"
        }
    ],
    "sg:phone":"+1 705 876 9743",
    "sg:postcode":"K9J 7J6",
    "sg:province":"ON",
    "sg:tags":[
        "advisory",
        "financial",
        "surplus",
        "merchandise",
        "salvage"
    ],
    "wof:name":"V K Patel & Assoc",
    "wof:placetype":"venue"
},
  "geometry": {"coordinates":[-78.337196,44.276962],"type":"Point"}
}