{
  "type": "Feature",
  "properties": {
    "addr:full":"4190 Carey Rd Victoria BC V8Z 4G8",
    "addr:housenumber":"4190",
    "addr:postcode":"v8z 4g8",
    "addr:street":"Carey Rd",
    "iso:country":"CA",
    "sg:address":"4190 Carey Rd",
    "sg:city":"Victoria",
    "sg:classifiers":[
        {
            "category":"Education",
            "subcategory":"School",
            "type":"Public Place"
        }
    ],
    "sg:phone":"+1 250 479 8293",
    "sg:postcode":"V8Z 4G8",
    "sg:province":"BC",
    "wof:name":"Northridge Elementary School",
    "wof:placetype":"venue"
},
  "geometry": {"coordinates":[-123.36451700000001,48.428314],"type":"Point"}
}