{
  "type": "Feature",
  "properties": {
    "iso:country":"CA",
    "sg:address":"2162 Rue Sherbrooke O",
    "sg:city":"Montreal",
    "sg:classifiers":[
        {
            "category":"Banks & Credit Unions",
            "subcategory":"Investment Brokerage",
            "type":"Services"
        }
    ],
    "sg:phone":"+1 514 989 8278",
    "sg:postcode":"H3H 1G7",
    "sg:province":"QC",
    "sg:tags":[
        "advisory",
        "financial"
    ],
    "wof:name":"Yaldez Investment & Financial",
    "wof:placetype":"venue"
},
  "geometry": {"coordinates":[-73.5625,45.531807],"type":"Point"}
}