{
  "type": "Feature",
  "properties": {
    "addr:full":"133 Spruce St S Timmins ON P4N 2M7",
    "addr:housenumber":"133",
    "addr:postcode":"p4n 2m7",
    "addr:street":"Spruce St S",
    "iso:country":"CA",
    "sg:address":"133 Spruce St S",
    "sg:city":"Timmins",
    "sg:classifiers":[
        {
            "category":"Insurance",
            "subcategory":"Insurance Agent",
            "type":"Services"
        }
    ],
    "sg:phone":"+1 705 267 7922",
    "sg:postcode":"P4N 2M7",
    "sg:province":"ON",
    "wof:name":"Al Poulin & Assoc Financial",
    "wof:placetype":"venue"
},
  "geometry": {"coordinates":[-81.327232,48.473515],"type":"Point"}
}