{
  "type": "Feature",
  "properties": {
    "addr:full":"Oakville ON L6L 6M4",
    "addr:postcode":"l6l 6m4",
    "iso:country":"CA",
    "sg:city":"Oakville",
    "sg:classifiers":[
        {
            "category":"Building & Trades",
            "subcategory":"Landscaping Services",
            "type":"Services"
        }
    ],
    "sg:phone":"+1 905 827 1134",
    "sg:postcode":"L6L 6M4",
    "sg:province":"ON",
    "sg:tags":[
        "horticultural",
        "tree",
        "consultant"
    ],
    "wof:name":"Farm & Forest Research CO Ltd",
    "wof:placetype":"venue"
},
  "geometry": {"coordinates":[-79.7348403931,43.4131965637],"type":"Point"}
}