{
  "type": "Feature",
  "properties": {
    "addr:full":"Hamilton ON L8E 2X2",
    "addr:postcode":"l8e 2x2",
    "iso:country":"CA",
    "sg:city":"Hamilton",
    "sg:classifiers":[
        {
            "category":"Retail",
            "subcategory":"Car Wash",
            "type":"Services"
        }
    ],
    "sg:phone":"+1 905 578 6866",
    "sg:postcode":"L8E 2X2",
    "sg:province":"ON",
    "sg:tags":[
        "polishing",
        "washing"
    ],
    "wof:name":"Tony's Car Clean Up",
    "wof:placetype":"venue"
},
  "geometry": {"coordinates":[-79.7545013428,43.2355499268],"type":"Point"}
}