{
  "type": "Feature",
  "properties": {
    "addr:full":"59 Winston Rd Wawa ON P0S 1K0",
    "addr:housenumber":"59",
    "addr:postcode":"p0s 1k0",
    "addr:street":"Winston Rd",
    "iso:country":"CA",
    "sg:address":"59 Winston Rd",
    "sg:city":"Wawa",
    "sg:classifiers":[
        {
            "category":"Freight",
            "type":"Transportation"
        }
    ],
    "sg:phone":"+1 705 856 7177",
    "sg:postcode":"P0S 1K0",
    "sg:province":"ON",
    "sg:tags":[
        "commercial",
        "storage"
    ],
    "wof:name":"Pinewood Storage & Warehouse",
    "wof:placetype":"venue"
},
  "geometry": {"coordinates":[-84.77285766599999,47.9869918823],"type":"Point"}
}