{
  "type": "Feature",
  "properties": {
    "addr:full":"200 Boul DE LA Cote-Vertu Saint-Laurent QC H4N 1C9",
    "addr:housenumber":"200",
    "addr:postcode":"h4n 1c9",
    "addr:street":"Boul De La Cote-Vertu",
    "iso:country":"CA",
    "sg:address":"200 Boul DE LA Cote-Vertu",
    "sg:city":"Saint-Laurent",
    "sg:classifiers":[
        {
            "category":"Autos & Motor Vehicles",
            "subcategory":"Fuel & Gas Station",
            "type":"Retail Goods"
        }
    ],
    "sg:phone":"+1 514 334 8626",
    "sg:postcode":"H4N 1C9",
    "sg:province":"QC",
    "sg:tags":[
        "oil"
    ],
    "wof:name":"Ultramar",
    "wof:placetype":"venue"
},
  "geometry": {"coordinates":[-73.668976,45.528324],"type":"Point"}
}