{
  "type": "Feature",
  "properties": {
    "addr:full":"202 Grand Ave W Chatham ON N7L 1C1",
    "addr:housenumber":"202",
    "addr:postcode":"n7l 1c1",
    "addr:street":"Grand Ave W",
    "iso:country":"CA",
    "sg:address":"202 Grand Ave W",
    "sg:city":"Chatham",
    "sg:classifiers":[
        {
            "category":"Retail",
            "subcategory":"Laundry & Dry Cleaning",
            "type":"Services"
        }
    ],
    "sg:phone":"+1 519 351 0610",
    "sg:postcode":"N7L 1C1",
    "sg:province":"ON",
    "sg:tags":[
        "cleaners",
        "tailor"
    ],
    "wof:name":"Chatham Cleaners Ltd",
    "wof:placetype":"venue"
},
  "geometry": {"coordinates":[-82.196899,42.403717],"type":"Point"}
}