{
  "type": "Feature",
  "properties": {
    "addr:full":"359 Rue Du Vigneau Gatineau QC J8P 5V1",
    "addr:housenumber":"359",
    "addr:postcode":"j8p 5v1",
    "addr:street":"Rue Du Vigneau",
    "iso:country":"CA",
    "sg:address":"359 Rue Du Vigneau",
    "sg:city":"Gatineau",
    "sg:classifiers":[
        {
            "category":"Real Estate",
            "subcategory":"Real Estate Agent",
            "type":"Services"
        }
    ],
    "sg:phone":"+1 819 663 8343",
    "sg:postcode":"J8P 5V1",
    "sg:province":"QC",
    "wof:name":"Investissements Laurentiens",
    "wof:placetype":"venue"
},
  "geometry": {"coordinates":[-75.654381,45.492569],"type":"Point"}
}