{
  "type": "Feature",
  "properties": {
    "addr:full":"190 Golden Grove Rd Saint John NB E2H 1X4",
    "addr:housenumber":"190",
    "addr:postcode":"e2h 1x4",
    "addr:street":"Golden Grove Rd",
    "iso:country":"CA",
    "sg:address":"190 Golden Grove Rd",
    "sg:city":"Saint John",
    "sg:classifiers":[
        {
            "category":"Building & Trades",
            "subcategory":"Construction",
            "type":"Services"
        }
    ],
    "sg:phone":"+1 506 696 2662",
    "sg:postcode":"E2H 1X4",
    "sg:province":"NB",
    "sg:tags":[
        "sand",
        "gravel",
        "general",
        "contractor"
    ],
    "wof:name":"Thomas Construction Ltd",
    "wof:placetype":"venue"
},
  "geometry": {"coordinates":[-66.00444,45.319687],"type":"Point"}
}