{
  "type": "Feature",
  "properties": {
    "addr:full":"Morell PE C0A 1S0",
    "addr:postcode":"c0a 1s0",
    "iso:country":"CA",
    "sg:city":"Morell",
    "sg:classifiers":[
        {
            "category":"Government",
            "subcategory":"Office",
            "type":"Public Place"
        }
    ],
    "sg:phone":"+1 902 961 3011",
    "sg:postcode":"C0A 1S0",
    "sg:province":"PE",
    "wof:name":"Canada Food Inspection Agency",
    "wof:placetype":"venue"
},
  "geometry": {"coordinates":[-62.704388,46.416115],"type":"Point"}
}