{
  "type": "Feature",
  "properties": {
    "iso:country":"CA",
    "sg:address":"1080 Portage Ave",
    "sg:city":"Winnipeg",
    "sg:classifiers":[
        {
            "category":"Health Services",
            "subcategory":"Clinic",
            "type":"Services"
        }
    ],
    "sg:phone":"+1 204 774 5421",
    "sg:postcode":"R3G 3M3",
    "sg:province":"MB",
    "sg:tags":[
        "organization"
    ],
    "wof:name":"Canadian National Inst Blind",
    "wof:placetype":"venue"
},
  "geometry": {"coordinates":[-97.1783828735,49.8840484619],"type":"Point"}
}