{
  "type": "Feature",
  "properties": {
    "addr:full":"Etobicoke ON M9W 5R7",
    "addr:postcode":"m9w 5r7",
    "iso:country":"CA",
    "sg:city":"Etobicoke",
    "sg:classifiers":[
        {
            "category":"Wholesale",
            "subcategory":"Machinery & Supplies",
            "type":"Manufacturing & Wholesale Goods"
        }
    ],
    "sg:phone":"+1 416 675 3220",
    "sg:postcode":"M9W 5R7",
    "sg:province":"ON",
    "wof:name":"C & B Products CO",
    "wof:placetype":"venue"
},
  "geometry": {"coordinates":[-79.58863100000001,43.682041],"type":"Point"}
}