{
  "type": "Feature",
  "properties": {
    "iso:country":"CA",
    "sg:address":"4350 Rue Notre-Dame O",
    "sg:city":"Montreal",
    "sg:classifiers":[
        {
            "category":"Restaurant",
            "type":"Food & Drink"
        }
    ],
    "sg:phone":"+1 514 932 2246",
    "sg:postcode":"H4C 1R8",
    "sg:province":"QC",
    "wof:name":"Restaurant John",
    "wof:placetype":"venue"
},
  "geometry": {"coordinates":[-73.531349,45.55072],"type":"Point"}
}