{
  "type": "Feature",
  "properties": {
    "addr:full":"4350 Rue Notre-Dame O Montreal QC H4C 1R8",
    "addr:housenumber":"4350",
    "addr:postcode":"h4c 1r8",
    "addr:street":"Rue Notre-Dame O",
    "iso:country":"CA",
    "sg:address":"4350 Rue Notre-Dame O",
    "sg:city":"Montreal",
    "sg:classifiers":[
        {
            "category":"Restaurant",
            "type":"Food & Drink"
        }
    ],
    "sg:phone":"+1 514 932 2246",
    "sg:postcode":"H4C 1R8",
    "sg:province":"QC",
    "wof:name":"Restaurant John",
    "wof:placetype":"venue"
},
  "geometry": {"coordinates":[-73.53134900000001,45.55072],"type":"Point"}
}