{
  "type": "Feature",
  "properties": {
    "addr:full":"10186 106 St NW Edmonton AB T5J 1H4",
    "addr:housenumber":"10186",
    "addr:postcode":"t5j 1h4",
    "addr:street":"106 St Nw",
    "iso:country":"CA",
    "sg:address":"10186 106 St NW",
    "sg:city":"Edmonton",
    "sg:classifiers":[
        {
            "category":"Organizations",
            "subcategory":"Professional Association",
            "type":"Services"
        }
    ],
    "sg:phone":"+1 780 488 6611",
    "sg:postcode":"T5J 1H4",
    "sg:province":"AB",
    "wof:name":"Alberta Craft Council",
    "wof:placetype":"venue"
},
  "geometry": {"coordinates":[-113.503089905,53.5425720215],"type":"Point"}
}