{
  "type": "Feature",
  "properties": {
    "addr:full":"London ON N6A 4V2",
    "addr:postcode":"n6a 4v2",
    "iso:country":"CA",
    "sg:city":"London",
    "sg:classifiers":[
        {
            "category":"Health Services",
            "subcategory":"Doctor",
            "type":"Services"
        }
    ],
    "sg:phone":"+1 519 646 6050",
    "sg:postcode":"N6A 4V2",
    "sg:province":"ON",
    "sg:tags":[
        "physician",
        "surgeon"
    ],
    "wof:name":"Roth, J H MD",
    "wof:placetype":"venue"
},
  "geometry": {"coordinates":[-81.25341,43.000298],"type":"Point"}
}