{
  "type": "Feature",
  "properties": {
    "addr:full":"1145 Ch Du Lac-Echo Prevost QC J0R 1T0",
    "addr:housenumber":"1145",
    "addr:postcode":"j0r 1t0",
    "addr:street":"Ch Du Lac-Echo Prevost",
    "iso:country":"CA",
    "sg:address":"1145 Ch Du Lac-Echo",
    "sg:city":"Prevost",
    "sg:classifiers":[
        {
            "category":"Wholesale",
            "subcategory":"Machinery & Supplies",
            "type":"Manufacturing & Wholesale Goods"
        }
    ],
    "sg:phone":"+1 450 224 4537",
    "sg:postcode":"J0R 1T0",
    "sg:province":"QC",
    "sg:tags":[
        "pump"
    ],
    "wof:name":"Pompes Experts 2000",
    "wof:placetype":"venue"
},
  "geometry": {"coordinates":[-74.05420684809999,45.8653144836],"type":"Point"}
}