{
  "type": "Feature",
  "properties": {
    "addr:full":"Saskatoon SK S7K 3Y5",
    "addr:postcode":"s7k 3y5",
    "iso:country":"CA",
    "sg:city":"Saskatoon",
    "sg:classifiers":[
        {
            "category":"Home & Garden",
            "subcategory":"Building Materials",
            "type":"Retail Goods"
        }
    ],
    "sg:phone":"+1 306 931 4010",
    "sg:postcode":"S7K 3Y5",
    "sg:province":"SK",
    "sg:tags":[
        "glass",
        "window",
        "plate"
    ],
    "wof:name":"Crystal Glass Canada Ltd",
    "wof:placetype":"venue"
},
  "geometry": {"coordinates":[-106.651939392,52.1704864502],"type":"Point"}
}