{
  "type": "Feature",
  "properties": {
    "addr:full":"214 Sixth St New Westminster BC V3L 3A2",
    "addr:housenumber":"214",
    "addr:postcode":"v3l 3a2",
    "addr:street":"Sixth St",
    "iso:country":"CA",
    "sg:address":"214 Sixth St",
    "sg:city":"New Westminster",
    "sg:classifiers":[
        {
            "category":"Social Services",
            "type":"Services"
        }
    ],
    "sg:phone":"+1 604 525 5481",
    "sg:postcode":"V3L 3A2",
    "sg:province":"BC",
    "sg:tags":[
        "organization",
        "welfare"
    ],
    "wof:name":"Hope International Development",
    "wof:placetype":"venue"
},
  "geometry": {"coordinates":[-122.913673,49.207752],"type":"Point"}
}