{
  "type": "Feature",
  "properties": {
    "addr:full":"3563 Rue Georges-Corbeil Terrebonne QC J6X 4J5",
    "addr:housenumber":"3563",
    "addr:postcode":"j6x 4j5",
    "addr:street":"Rue Georges-Corbeil",
    "iso:country":"CA",
    "sg:address":"3563 Rue Georges-Corbeil",
    "sg:city":"Terrebonne",
    "sg:classifiers":[
        {
            "category":"Wholesale",
            "subcategory":"Electrical",
            "type":"Manufacturing & Wholesale Goods"
        }
    ],
    "sg:phone":"+1 450 477 6677",
    "sg:postcode":"J6X 4J5",
    "sg:province":"QC",
    "sg:tags":[
        "refrigerator",
        "refrigerating"
    ],
    "wof:name":"Refrigeration Klm",
    "wof:placetype":"venue"
},
  "geometry": {"coordinates":[-73.676559,45.726742],"type":"Point"}
}