{
  "type": "Feature",
  "properties": {
    "addr:full":"1115 Murray Dr Williams Lake BC V2G 4K8",
    "addr:housenumber":"1115",
    "addr:postcode":"v2g 4k8",
    "addr:street":"Murray Dr",
    "iso:country":"CA",
    "sg:address":"1115 Murray Dr",
    "sg:city":"Williams Lake",
    "sg:classifiers":[
        {
            "category":"Freight",
            "type":"Transportation"
        }
    ],
    "sg:phone":"+1 250 398 9090",
    "sg:postcode":"V2G 4K8",
    "sg:province":"BC",
    "sg:tags":[
        "commercial",
        "storage"
    ],
    "wof:name":"Williams Lake Cold Storage",
    "wof:placetype":"venue"
},
  "geometry": {"coordinates":[-122.160850525,52.1423377991],"type":"Point"}
}