{
  "type": "Feature",
  "properties": {
    "addr:full":"1389 Aroostook Rd Perth-Andover NB E7H 1A9",
    "addr:housenumber":"1389",
    "addr:postcode":"e7h 1a9",
    "addr:street":"Aroostook Rd",
    "iso:country":"CA",
    "sg:address":"1389 Aroostook Rd",
    "sg:city":"Perth-Andover",
    "sg:classifiers":[
        {
            "category":"Retail",
            "subcategory":"Auto Repair",
            "type":"Services"
        }
    ],
    "sg:phone":"+1 506 273 2752",
    "sg:postcode":"E7H 1A9",
    "sg:province":"NB",
    "sg:tags":[
        "automobile",
        "electric"
    ],
    "wof:name":"Hurley's Auto Electric Ltd",
    "wof:placetype":"venue"
},
  "geometry": {"coordinates":[-67.70024100000001,46.759109],"type":"Point"}
}