{
  "type": "Feature",
  "properties": {
    "iso:country":"CA",
    "sg:city":"Richmond",
    "sg:classifiers":[
        {
            "category":"Utilities",
            "subcategory":"Mobile Phone",
            "type":"Services"
        }
    ],
    "sg:phone":"+1 604 231 9303",
    "sg:postcode":"V6X 4A5",
    "sg:province":"BC",
    "sg:tags":[
        "telephone",
        "cellular"
    ],
    "wof:name":"Oasis Telecom",
    "wof:placetype":"venue"
},
  "geometry": {"coordinates":[-123.126693726,49.1835136414],"type":"Point"}
}