{
  "type": "Feature",
  "properties": {
    "addr:full":"104 Gordon Ave W Gilbert Plains MB R0L 0X0",
    "addr:housenumber":"104",
    "addr:postcode":"r0l 0x0",
    "addr:street":"Gordon Ave W Gilbert",
    "iso:country":"CA",
    "sg:address":"104 Gordon Ave W",
    "sg:city":"Gilbert Plains",
    "sg:classifiers":[
        {
            "category":"Shopping",
            "subcategory":"Florist",
            "type":"Retail Goods"
        }
    ],
    "sg:phone":"+1 204 548 2304",
    "sg:postcode":"R0L 0X0",
    "sg:province":"MB",
    "wof:name":"Straight From the Heart",
    "wof:placetype":"venue"
},
  "geometry": {"coordinates":[-100.485573,51.147266],"type":"Point"}
}