{
  "type": "Feature",
  "properties": {
    "iso:country":"CA",
    "sg:address":"36 Hazel St",
    "sg:city":"Waubaushene",
    "sg:classifiers":[
        {
            "category":"Education",
            "subcategory":"School",
            "type":"Public Place"
        }
    ],
    "sg:phone":"+1 705 538 2212",
    "sg:postcode":"L0K 2C0",
    "sg:province":"ON",
    "wof:name":"Waubaushene Elementary School",
    "wof:placetype":"venue"
},
  "geometry": {"coordinates":[-79.7100448608,44.7574577332],"type":"Point"}
}