{
  "type": "Feature",
  "properties": {
    "addr:full":"1274 Carling Ave Ottawa ON K1Z 7K8",
    "addr:housenumber":"1274",
    "addr:postcode":"k1z 7k8",
    "addr:street":"Carling Ave",
    "iso:country":"CA",
    "sg:address":"1274 Carling Ave",
    "sg:city":"Ottawa",
    "sg:classifiers":[
        {
            "category":"Travel",
            "subcategory":"Hotels & Motels",
            "type":"Entertainment"
        }
    ],
    "sg:phone":"+1 613 728 1951",
    "sg:postcode":"K1Z 7K8",
    "sg:province":"ON",
    "wof:name":"Best Western Macies Hotel",
    "wof:placetype":"venue"
},
  "geometry": {"coordinates":[-75.733475,45.38612],"type":"Point"}
}