{
  "type": "Feature",
  "properties": {
    "addr:full":"1832 52 St SE Calgary AB T2B 1N1",
    "addr:housenumber":"1832",
    "addr:postcode":"t2b 1n1",
    "addr:street":"52 St Se",
    "iso:country":"CA",
    "sg:address":"1832 52 St SE",
    "sg:city":"Calgary",
    "sg:classifiers":[
        {
            "category":"Wholesale",
            "subcategory":"Construction Materials",
            "type":"Manufacturing & Wholesale Goods"
        }
    ],
    "sg:phone":"+1 403 273 8280",
    "sg:postcode":"T2B 1N1",
    "sg:province":"AB",
    "sg:tags":[
        "building",
        "fence"
    ],
    "wof:name":"Totem Building Supplies Ltd",
    "wof:placetype":"venue"
},
  "geometry": {"coordinates":[-113.958107,51.037437],"type":"Point"}
}