{
  "type": "Feature",
  "properties": {
    "addr:full":"510 Rue Collard O Alma QC G8B 1N2",
    "addr:housenumber":"510",
    "addr:postcode":"g8b 1n2",
    "addr:street":"Rue Collard O",
    "iso:country":"CA",
    "sg:address":"510 Rue Collard O",
    "sg:city":"Alma",
    "sg:classifiers":[
        {
            "category":"Professional",
            "subcategory":"Business Services",
            "type":"Services"
        }
    ],
    "sg:phone":"+1 418 668 2336",
    "sg:postcode":"G8B 1N2",
    "sg:province":"QC",
    "sg:tags":[
        "notary"
    ],
    "wof:name":"Parizeau Tremblay Forest",
    "wof:placetype":"venue"
},
  "geometry": {"coordinates":[-71.65036000000001,48.548676],"type":"Point"}
}