{
  "type": "Feature",
  "properties": {
    "addr:full":"Melville SK S0A 2P0",
    "addr:postcode":"s0a 2p0",
    "iso:country":"CA",
    "sg:city":"Melville",
    "sg:classifiers":[
        {
            "category":"Education",
            "subcategory":"School",
            "type":"Public Place"
        }
    ],
    "sg:phone":"+1 306 728 4471",
    "sg:postcode":"S0A 2P0",
    "sg:province":"SK",
    "wof:name":"Parkland Regional College",
    "wof:placetype":"venue"
},
  "geometry": {"coordinates":[-102.801071167,50.9337310791],"type":"Point"}
}