{
  "type": "Feature",
  "properties": {
    "addr:full":"2577 Claude Ave Niagara Falls ON L2J 2C7",
    "addr:housenumber":"2577",
    "addr:postcode":"l2j 2c7",
    "addr:street":"Claude Ave",
    "iso:country":"CA",
    "sg:address":"2577 Claude Ave",
    "sg:city":"Niagara Falls",
    "sg:classifiers":[
        {
            "category":"Building & Trades",
            "subcategory":"Construction",
            "type":"Services"
        }
    ],
    "sg:phone":"+1 905 356 3299",
    "sg:postcode":"L2J 2C7",
    "sg:province":"ON",
    "sg:tags":[
        "dry wall",
        "contractor"
    ],
    "wof:name":"N J Stranges Drywall & Constr",
    "wof:placetype":"venue"
},
  "geometry": {"coordinates":[-79.091667,43.134083],"type":"Point"}
}