{
  "type": "Feature",
  "properties": {
    "addr:full":"Stirling ON K0K 3E0",
    "addr:postcode":"k0k 3e0",
    "iso:country":"CA",
    "sg:city":"Stirling",
    "sg:classifiers":[
        {
            "category":"Shopping",
            "type":"Retail Goods"
        }
    ],
    "sg:phone":"+1 613 395 0002",
    "sg:postcode":"K0K 3E0",
    "sg:province":"ON",
    "sg:tags":[
        "equipment",
        "wine",
        "supply"
    ],
    "wof:name":"Wine Kitz",
    "wof:placetype":"venue"
},
  "geometry": {"coordinates":[-77.5490188599,44.2994384766],"type":"Point"}
}