{
  "type": "Feature",
  "properties": {
    "addr:full":"662 Fennell Ave E # 8 Hamilton ON L8V 1V1",
    "addr:housenumber":"662",
    "addr:postcode":"l8v 1v1",
    "addr:street":"Fennell Ave E # 8",
    "iso:country":"CA",
    "sg:address":"662 Fennell Ave E # 8",
    "sg:city":"Hamilton",
    "sg:classifiers":[
        {
            "category":"Organizations",
            "subcategory":"Religious Organization",
            "type":"Services"
        }
    ],
    "sg:phone":"+1 905 387 9469",
    "sg:postcode":"L8V 1V1",
    "sg:province":"ON",
    "wof:name":"Focus on the World Ministries",
    "wof:placetype":"venue"
},
  "geometry": {"coordinates":[-79.8507,43.230618],"type":"Point"}
}