{
  "type": "Feature",
  "properties": {
    "addr:full":"1237 Greenway Dr Parkhill ON N0M 2K0",
    "addr:housenumber":"1237",
    "addr:postcode":"n0m 2k0",
    "addr:street":"Greenway Dr",
    "iso:country":"CA",
    "sg:address":"1237 Greenway Dr",
    "sg:city":"Parkhill",
    "sg:classifiers":[
        {
            "category":"Wholesale",
            "subcategory":"Farm Supplies",
            "type":"Manufacturing & Wholesale Goods"
        }
    ],
    "sg:phone":"+1 519 294 0014",
    "sg:postcode":"N0M 2K0",
    "sg:province":"ON",
    "sg:tags":[
        "grain"
    ],
    "wof:name":"Cargill Ltd",
    "wof:placetype":"venue"
},
  "geometry": {"coordinates":[-81.68399047849999,43.1628913879],"type":"Point"}
}