{
  "type": "Feature",
  "properties": {
    "addr:full":"5000 Ch Queen-Mary Montreal QC H3W 1X2",
    "addr:postcode":"5000;h3w 1x2",
    "addr:street":"Ch Queen-Mary",
    "iso:country":"CA",
    "sg:address":"5000 Ch Queen-Mary",
    "sg:city":"Montreal",
    "sg:classifiers":[
        {
            "category":"Retail",
            "subcategory":"Portrait Studio",
            "type":"Services"
        }
    ],
    "sg:phone":"+1 514 739 7070",
    "sg:postcode":"H3W 1X2",
    "sg:province":"QC",
    "sg:tags":[
        "photographer"
    ],
    "wof:name":"Photo Flash Plus",
    "wof:placetype":"venue"
},
  "geometry": {"coordinates":[-73.6267318726,45.4862098694],"type":"Point"}
}