{
  "type": "Feature",
  "properties": {
    "addr:full":"1108 Rue Principale Saint-Donat-DE-Montcalm QC J0T 2C0",
    "addr:housenumber":"1108",
    "addr:postcode":"j0t 2c0",
    "addr:street":"Rue Principale",
    "iso:country":"CA",
    "sg:address":"1108 Rue Principale",
    "sg:city":"Saint-Donat-DE-Montcalm",
    "sg:classifiers":[
        {
            "category":"Autos & Motor Vehicles",
            "subcategory":"Boat Sales",
            "type":"Retail Goods"
        }
    ],
    "sg:phone":"+1 819 424 3433",
    "sg:postcode":"J0T 2C0",
    "sg:province":"QC",
    "sg:tags":[
        "dealer"
    ],
    "wof:name":"Sport & Marine Mv Inc",
    "wof:placetype":"venue"
},
  "geometry": {"coordinates":[-74.20358299999999,46.305958],"type":"Point"}
}