{
  "type": "Feature",
  "properties": {
    "addr:full":"Tecumseh Hwy #4 Wallaceburg ON N8A 4K9",
    "addr:postcode":"n8a 4k9",
    "addr:street":"Tecumseh Hwy # 4",
    "iso:country":"CA",
    "sg:address":"Tecumseh Hwy #4",
    "sg:city":"Wallaceburg",
    "sg:classifiers":[
        {
            "category":"Shopping",
            "subcategory":"Discount & Variety Stores",
            "type":"Retail Goods"
        }
    ],
    "sg:phone":"+1 519 627 9100",
    "sg:postcode":"N8A 4K9",
    "sg:province":"ON",
    "wof:name":"Pit Stop",
    "wof:placetype":"venue"
},
  "geometry": {"coordinates":[-82.474411,42.592823],"type":"Point"}
}