{
  "type": "Feature",
  "properties": {
    "addr:full":"500 Tecumseh Rd E Windsor ON N8X 2S2",
    "addr:housenumber":"500",
    "addr:postcode":"n8x 2s2",
    "addr:street":"Tecumseh Rd E",
    "iso:country":"CA",
    "sg:address":"500 Tecumseh Rd E",
    "sg:city":"Windsor",
    "sg:classifiers":[
        {
            "category":"Shopping",
            "subcategory":"Pharmacy",
            "type":"Retail Goods"
        }
    ],
    "sg:phone":"+1 519 253 1115",
    "sg:postcode":"N8X 2S2",
    "sg:province":"ON",
    "wof:name":"Shoppers Drug Mart",
    "wof:placetype":"venue"
},
  "geometry": {"coordinates":[-83.0168,42.298206],"type":"Point"}
}