{
  "type": "Feature",
  "properties": {
    "iso:country":"CA",
    "sg:address":"3275 1Re Rue # 8",
    "sg:city":"Saint-Hubert",
    "sg:classifiers":[
        {
            "category":"Wholesale",
            "subcategory":"Durable Goods & Equipment",
            "type":"Manufacturing & Wholesale Goods"
        }
    ],
    "sg:phone":"+1 450 676 8776",
    "sg:postcode":"J3Y 8Y6",
    "sg:province":"QC",
    "sg:tags":[
        "laboratory",
        "supply"
    ],
    "wof:name":"Jeol Canada Inc",
    "wof:placetype":"venue"
},
  "geometry": {"coordinates":[-73.391151,45.477432],"type":"Point"}
}