{
  "type": "Feature",
  "properties": {
    "addr:full":"188 Montague St St Andrews NB E5B 1J2",
    "addr:housenumber":"188",
    "addr:postcode":"e5b 1j2",
    "addr:street":"Montague St",
    "iso:country":"CA",
    "sg:address":"188 Montague St",
    "sg:city":"St Andrews",
    "sg:classifiers":[
        {
            "category":"Museum",
            "type":"Entertainment"
        }
    ],
    "sg:phone":"+1 506 529 5124",
    "sg:postcode":"E5B 1J2",
    "sg:province":"NB",
    "wof:name":"Ross Memorial Museum",
    "wof:placetype":"venue"
},
  "geometry": {"coordinates":[-67.051834,45.075912],"type":"Point"}
}