{
  "type": "Feature",
  "properties": {
    "addr:full":"255 Conmee Ave Sault Ste Marie ON P6C 1W4",
    "addr:housenumber":"255",
    "addr:postcode":"p6c 1w4",
    "addr:street":"Conmee Ave",
    "iso:country":"CA",
    "sg:address":"255 Conmee Ave",
    "sg:city":"Sault Ste Marie",
    "sg:classifiers":[
        {
            "category":"Manufacturing",
            "subcategory":"Food",
            "type":"Manufacturing & Wholesale Goods"
        }
    ],
    "sg:phone":"+1 705 256 7775",
    "sg:postcode":"P6C 1W4",
    "sg:province":"ON",
    "sg:tags":[
        "brewer"
    ],
    "wof:name":"Custom Brew & Bottle",
    "wof:placetype":"venue"
},
  "geometry": {"coordinates":[-84.34768699999999,46.532215],"type":"Point"}
}