{
  "type": "Feature",
  "properties": {
    "addr:full":"291 French Fort Rd Miramichi NB E1V 5N1",
    "addr:housenumber":"291",
    "addr:postcode":"e1v 5n1",
    "addr:street":"French Fort Rd",
    "iso:country":"CA",
    "sg:address":"291 French Fort Rd",
    "sg:city":"Miramichi",
    "sg:classifiers":[
        {
            "category":"Autos & Motor Vehicles",
            "subcategory":"Motorcycle Sales",
            "type":"Retail Goods"
        }
    ],
    "sg:phone":"+1 506 622 3141",
    "sg:postcode":"E1V 5N1",
    "sg:province":"NB",
    "sg:tags":[
        "recreational"
    ],
    "wof:name":"Rae's Trailer & Sports Ctr Ltd",
    "wof:placetype":"venue"
},
  "geometry": {"coordinates":[-65.54242706300001,47.020942688],"type":"Point"}
}