{
  "type": "Feature",
  "properties": {
    "addr:full":"90 Centre St Chatham ON N7M 4W4",
    "addr:housenumber":"90",
    "addr:postcode":"n7m 4w4",
    "addr:street":"Centre St",
    "iso:country":"CA",
    "sg:address":"90 Centre St",
    "sg:city":"Chatham",
    "sg:classifiers":[
        {
            "category":"Retail",
            "subcategory":"Laundry & Dry Cleaning",
            "type":"Services"
        }
    ],
    "sg:phone":"+1 519 354 2840",
    "sg:postcode":"N7M 4W4",
    "sg:province":"ON",
    "sg:tags":[
        "cleaners"
    ],
    "wof:name":"Betty Brite",
    "wof:placetype":"venue"
},
  "geometry": {"coordinates":[-82.1828613281,42.4021148682],"type":"Point"}
}