{
  "type": "Feature",
  "properties": {
    "addr:full":"529 2nd Ave Rivers MB R0K 1X0",
    "addr:housenumber":"529",
    "addr:postcode":"r0k 1x0",
    "addr:street":"2Nd Ave",
    "iso:country":"CA",
    "sg:address":"529 2nd Ave",
    "sg:city":"Rivers",
    "sg:classifiers":[
        {
            "category":"Manufacturing",
            "subcategory":"Printing",
            "type":"Manufacturing & Wholesale Goods"
        }
    ],
    "sg:phone":"+1 204 328 7494",
    "sg:postcode":"R0K 1X0",
    "sg:province":"MB",
    "sg:tags":[
        "newspaper"
    ],
    "wof:name":"Rivers Banner",
    "wof:placetype":"venue"
},
  "geometry": {"coordinates":[-100.23764,50.029285],"type":"Point"}
}