{
  "type": "Feature",
  "properties": {
    "addr:full":"49 Gage Ave N Hamilton ON L8L 6Z8",
    "addr:housenumber":"49",
    "addr:postcode":"l8l 6z8",
    "addr:street":"Gage Ave N",
    "iso:country":"CA",
    "sg:address":"49 Gage Ave N",
    "sg:city":"Hamilton",
    "sg:classifiers":[
        {
            "category":"Restaurant",
            "type":"Food & Drink"
        }
    ],
    "sg:phone":"+1 905 545 1197",
    "sg:postcode":"L8L 6Z8",
    "sg:province":"ON",
    "wof:name":"China City Restaurant",
    "wof:placetype":"venue"
},
  "geometry": {"coordinates":[-79.827927,43.250004],"type":"Point"}
}