{
  "type": "Feature",
  "properties": {
    "addr:full":"341 Rue Heroux Saint-Liguori QC J0K 2X0",
    "addr:housenumber":"341",
    "addr:postcode":"j0k 2x0",
    "addr:street":"Rue Heroux",
    "iso:country":"CA",
    "sg:address":"341 Rue Heroux",
    "sg:city":"Saint-Liguori",
    "sg:classifiers":[
        {
            "category":"Food & Beverages",
            "subcategory":"Groceries & Convenience Stores",
            "type":"Retail Goods"
        }
    ],
    "sg:phone":"+1 450 752 8385",
    "sg:postcode":"J0K 2X0",
    "sg:province":"QC",
    "wof:name":"Marche Des Rapides",
    "wof:placetype":"venue"
},
  "geometry": {"coordinates":[-73.5688323975,46.0110244751],"type":"Point"}
}