{
  "type": "Feature",
  "properties": {
    "addr:full":"2227 South Millway Mississauga ON L5L 3R6",
    "addr:housenumber":"2227",
    "addr:postcode":"l5l 3r6",
    "addr:street":"South Millway",
    "iso:country":"CA",
    "sg:address":"2227 South Millway",
    "sg:city":"Mississauga",
    "sg:classifiers":[
        {
            "category":"Health Services",
            "subcategory":"Health Practitioner",
            "type":"Services"
        }
    ],
    "sg:phone":"+1 905 828 0038",
    "sg:postcode":"L5L 3R6",
    "sg:province":"ON",
    "sg:tags":[
        "nutritionist",
        "dietitian"
    ],
    "wof:name":"Dietitians in Private Practice",
    "wof:placetype":"venue"
},
  "geometry": {"coordinates":[-79.682953,43.542343],"type":"Point"}
}