{
  "type": "Feature",
  "properties": {
    "addr:full":"Oliver BC V0H 1T0",
    "addr:postcode":"bc v0h 1t0",
    "iso:country":"CA",
    "sg:city":"Oliver",
    "sg:classifiers":[
        {
            "category":"Real Estate",
            "subcategory":"Real Estate Operator",
            "type":"Services"
        }
    ],
    "sg:phone":"+1 250 498 6266",
    "sg:postcode":"V0H 1T0",
    "sg:province":"BC",
    "sg:tags":[
        "home",
        "retirement",
        "community",
        "condominium"
    ],
    "wof:name":"Park Place",
    "wof:placetype":"venue"
},
  "geometry": {"coordinates":[-119.545074,49.184677],"type":"Point"}
}