{
  "type": "Feature",
  "properties": {
    "addr:full":"12020 Vulcan Way # 30 Richmond BC V6V 1J8",
    "addr:housenumber":"12020;30",
    "addr:postcode":"v6v 1j8",
    "addr:street":"Vulcan Way #",
    "iso:country":"CA",
    "sg:address":"12020 Vulcan Way # 30",
    "sg:city":"Richmond",
    "sg:classifiers":[
        {
            "category":"Shopping",
            "subcategory":"Computers & Home Electronics",
            "type":"Retail Goods"
        }
    ],
    "sg:phone":"+1 604 207 1788",
    "sg:postcode":"V6V 1J8",
    "sg:province":"BC",
    "sg:tags":[
        "equipment",
        "dealer"
    ],
    "wof:name":"Q Plus Computer Inc",
    "wof:placetype":"venue"
},
  "geometry": {"coordinates":[-123.090363,49.193722],"type":"Point"}
}