{
  "type": "Feature",
  "properties": {
    "addr:full":"Calgary AB T2S 1V8",
    "addr:postcode":"t2s 1v8",
    "iso:country":"CA",
    "sg:city":"Calgary",
    "sg:classifiers":[
        {
            "category":"Professional",
            "subcategory":"Lawyer & Legal Services",
            "type":"Services"
        }
    ],
    "sg:phone":"+1 403 264 1234",
    "sg:postcode":"T2S 1V8",
    "sg:province":"AB",
    "sg:tags":[
        "attorney"
    ],
    "wof:name":"Hadley & Davis",
    "wof:placetype":"venue"
},
  "geometry": {"coordinates":[-114.071533203,51.0372085571],"type":"Point"}
}