{
  "type": "Feature",
  "properties": {
    "addr:full":"3020 Danforth Ave East York ON M4C 1M7",
    "addr:housenumber":"3020",
    "addr:postcode":"m4c 1m7",
    "addr:street":"Danforth Ave",
    "iso:country":"CA",
    "sg:address":"3020 Danforth Ave",
    "sg:city":"East York",
    "sg:classifiers":[
        {
            "category":"Professional",
            "subcategory":"Business Services",
            "type":"Services"
        }
    ],
    "sg:phone":"+1 416 690 6992",
    "sg:postcode":"M4C 1M7",
    "sg:province":"ON",
    "sg:tags":[
        "carpet",
        "dealer",
        "rug"
    ],
    "wof:name":"Brothers Carpetland",
    "wof:placetype":"venue"
},
  "geometry": {"coordinates":[-79.29053500000001,43.690853],"type":"Point"}
}