{
  "type": "Feature",
  "properties": {
    "iso:country":"CA",
    "sg:address":"3020 Danforth Ave",
    "sg:city":"East York",
    "sg:classifiers":[
        {
            "category":"Professional",
            "subcategory":"Business Services",
            "type":"Services"
        }
    ],
    "sg:phone":"+1 416 690 6992",
    "sg:postcode":"M4C 1M7",
    "sg:province":"ON",
    "sg:tags":[
        "carpet",
        "dealer",
        "rug"
    ],
    "wof:name":"Brothers Carpetland",
    "wof:placetype":"venue"
},
  "geometry": {"coordinates":[-79.290535,43.690853],"type":"Point"}
}