{
  "type": "Feature",
  "properties": {
    "addr:full":"333 Spadina Ave Toronto ON M5T 2E9",
    "addr:housenumber":"333",
    "addr:postcode":"m5t 2e9",
    "addr:street":"Spadina Ave",
    "iso:country":"CA",
    "sg:address":"333 Spadina Ave",
    "sg:city":"Toronto",
    "sg:classifiers":[
        {
            "category":"Manufacturing",
            "subcategory":"Apparel",
            "type":"Manufacturing & Wholesale Goods"
        }
    ],
    "sg:phone":"+1 416 977 1378",
    "sg:postcode":"M5T 2E9",
    "sg:province":"ON",
    "sg:tags":[
        "clothing"
    ],
    "wof:name":"Samet Hosiery Inc",
    "wof:placetype":"venue"
},
  "geometry": {"coordinates":[-79.398537,43.654816],"type":"Point"}
}