{
  "type": "Feature",
  "properties": {
    "addr:full":"RR 4 Cobden ON K0J 1K0",
    "addr:postcode":"k0j 1k0",
    "addr:street":"Rr 4",
    "iso:country":"CA",
    "sg:address":"RR 4",
    "sg:city":"Cobden",
    "sg:classifiers":[
        {
            "category":"Shopping",
            "subcategory":"Computers & Home Electronics",
            "type":"Retail Goods"
        }
    ],
    "sg:phone":"+1 613 646 7582",
    "sg:postcode":"K0J 1K0",
    "sg:province":"ON",
    "sg:tags":[
        "equipment",
        "dealer"
    ],
    "wof:name":"Audible Eye",
    "wof:placetype":"venue"
},
  "geometry": {"coordinates":[-76.879982,45.627075],"type":"Point"}
}