{
  "type": "Feature",
  "properties": {
    "addr:full":"Quebec QC G1P 4C6",
    "addr:postcode":"g1p 4c6",
    "iso:country":"CA",
    "sg:city":"Quebec",
    "sg:classifiers":[
        {
            "category":"Manufacturing",
            "subcategory":"Signs",
            "type":"Manufacturing & Wholesale Goods"
        }
    ],
    "sg:phone":"+1 418 686 1234",
    "sg:postcode":"G1P 4C6",
    "sg:province":"QC",
    "wof:name":"Enseignes Image in",
    "wof:placetype":"venue"
},
  "geometry": {"coordinates":[-71.3047866821,46.8062515259],"type":"Point"}
}