{
  "type": "Feature",
  "properties": {
    "iso:country":"CA",
    "sg:address":"11440 97 Ave",
    "sg:city":"Grande Prairie",
    "sg:classifiers":[
        {
            "category":"Retail",
            "subcategory":"Repair Shop",
            "type":"Services"
        }
    ],
    "sg:phone":"+1 780 814 7195",
    "sg:postcode":"T8V 5Z5",
    "sg:province":"AB",
    "sg:tags":[
        "welding"
    ],
    "wof:name":"Unitech Mechanical Svc Ltd",
    "wof:placetype":"venue"
},
  "geometry": {"coordinates":[-118.840003967,55.1672782898],"type":"Point"}
}