{
  "type": "Feature",
  "properties": {
    "addr:full":"Victoria BC V8T 4N2",
    "addr:postcode":"v8t 4n2",
    "iso:country":"CA",
    "sg:city":"Victoria",
    "sg:classifiers":[
        {
            "category":"Home & Garden",
            "subcategory":"Furniture",
            "type":"Retail Goods"
        }
    ],
    "sg:phone":"+1 250 386 2229",
    "sg:postcode":"V8T 4N2",
    "sg:province":"BC",
    "wof:name":"T J's Kiddies Korner",
    "wof:placetype":"venue"
},
  "geometry": {"coordinates":[-123.370063782,48.4443054199],"type":"Point"}
}