{
  "type": "Feature",
  "properties": {
    "addr:full":"8520 132 St Surrey BC V3W 4N7",
    "addr:housenumber":"8520",
    "addr:postcode":"v3w 4n7",
    "addr:street":"132 St",
    "iso:country":"CA",
    "sg:address":"8520 132 St",
    "sg:city":"Surrey",
    "sg:classifiers":[
        {
            "category":"Organizations",
            "subcategory":"Religious Organization",
            "type":"Services"
        }
    ],
    "sg:phone":"+1 604 591 2922",
    "sg:postcode":"V3W 4N7",
    "sg:province":"BC",
    "sg:tags":[
        "church"
    ],
    "wof:name":"Seventh-Day Adventist Church",
    "wof:placetype":"venue"
},
  "geometry": {"coordinates":[-122.856583,49.157906],"type":"Point"}
}