{
  "type": "Feature",
  "properties": {
    "addr:full":"6880 Financial Dr Mississauga ON L5N 8E8",
    "addr:housenumber":"6880",
    "addr:postcode":"l5n 8e8",
    "addr:street":"Financial Dr",
    "iso:country":"CA",
    "sg:address":"6880 Financial Dr",
    "sg:city":"Mississauga",
    "sg:classifiers":[
        {
            "category":"Real Estate",
            "subcategory":"Developer",
            "type":"Services"
        }
    ],
    "sg:phone":"+1 905 542 1073",
    "sg:postcode":"L5N 8E8",
    "sg:province":"ON",
    "wof:name":"Bentall Properties Ltd",
    "wof:placetype":"venue"
},
  "geometry": {"coordinates":[-79.743629,43.609154],"type":"Point"}
}