{
  "type": "Feature",
  "properties": {
    "iso:country":"CA",
    "sg:address":"147 Sophia Rd",
    "sg:city":"Markham",
    "sg:classifiers":[
        {
            "category":"Building & Trades",
            "subcategory":"Electrical",
            "type":"Services"
        }
    ],
    "sg:phone":"+1 905 201 9275",
    "sg:postcode":"L3S 3Y9",
    "sg:province":"ON",
    "sg:tags":[
        "electric",
        "contractor"
    ],
    "wof:name":"Star Electric",
    "wof:placetype":"venue"
},
  "geometry": {"coordinates":[-79.26555633540001,43.8472900391],"type":"Point"}
}