{
  "type": "Feature",
  "properties": {
    "addr:full":"25 Royal Crest Crt Markham ON L3R 9X4",
    "addr:housenumber":"25",
    "addr:postcode":"l3r 9x4",
    "addr:street":"Royal Crest Crt",
    "iso:country":"CA",
    "sg:address":"25 Royal Crest Crt",
    "sg:city":"Markham",
    "sg:classifiers":[
        {
            "category":"Freight",
            "type":"Transportation"
        }
    ],
    "sg:phone":"+1 905 513 8781",
    "sg:postcode":"L3R 9X4",
    "sg:province":"ON",
    "sg:tags":[
        "mover"
    ],
    "wof:name":"Swen Moving",
    "wof:placetype":"venue"
},
  "geometry": {"coordinates":[-79.328011,43.840515],"type":"Point"}
}