{
  "type": "Feature",
  "properties": {
    "addr:full":"8 Howard St Toronto ON M4X 1J5",
    "addr:housenumber":"8",
    "addr:postcode":"m4x 1j5",
    "addr:street":"Howard St",
    "iso:country":"CA",
    "sg:address":"8 Howard St",
    "sg:city":"Toronto",
    "sg:classifiers":[
        {
            "category":"Banks & Credit Unions",
            "subcategory":"Bank",
            "type":"Services"
        }
    ],
    "sg:phone":"+1 416 962 1167",
    "sg:postcode":"M4X 1J5",
    "sg:province":"ON",
    "sg:tags":[
        "money",
        "order",
        "transfer"
    ],
    "wof:name":"Gemini Exchange Intl",
    "wof:placetype":"venue"
},
  "geometry": {"coordinates":[-79.3753662109,43.6713218689],"type":"Point"}
}