{
  "type": "Feature",
  "properties": {
    "addr:full":"5892 Av Papineau Montreal QC H2G 2W6",
    "addr:housenumber":"5892",
    "addr:postcode":"h2g 2w6",
    "addr:street":"Av Papineau",
    "iso:country":"CA",
    "sg:address":"5892 Av Papineau",
    "sg:city":"Montreal",
    "sg:classifiers":[
        {
            "category":"Building & Trades",
            "subcategory":"Construction",
            "type":"Services"
        }
    ],
    "sg:phone":"+1 514 271 9900",
    "sg:postcode":"H2G 2W6",
    "sg:province":"QC",
    "sg:tags":[
        "roofing",
        "tin",
        "contractor",
        "plate"
    ],
    "wof:name":"Bardeaux & Gravier Lelievre",
    "wof:placetype":"venue"
},
  "geometry": {"coordinates":[-73.591042,45.540405],"type":"Point"}
}