{
  "type": "Feature",
  "properties": {
    "addr:full":"232 Hood Rd Markham ON L3R 3K8",
    "addr:housenumber":"232",
    "addr:postcode":"l3r 3k8",
    "addr:street":"Hood Rd",
    "iso:country":"CA",
    "sg:address":"232 Hood Rd",
    "sg:city":"Markham",
    "sg:classifiers":[
        {
            "category":"Wholesale",
            "subcategory":"Medical Equipment & Supplies",
            "type":"Manufacturing & Wholesale Goods"
        }
    ],
    "sg:phone":"+1 416 421 9211",
    "sg:postcode":"L3R 3K8",
    "sg:province":"ON",
    "sg:tags":[
        "hospital"
    ],
    "wof:name":"Diros Technology Inc",
    "wof:placetype":"venue"
},
  "geometry": {"coordinates":[-79.327675,43.824612],"type":"Point"}
}