{
  "type": "Feature",
  "properties": {
    "addr:full":"Alberton PE C0B 1B0",
    "addr:postcode":"c0b 1b0",
    "iso:country":"CA",
    "sg:city":"Alberton",
    "sg:classifiers":[
        {
            "category":"Retail",
            "subcategory":"Auto Repair",
            "type":"Services"
        }
    ],
    "sg:phone":"+1 902 853 3387",
    "sg:postcode":"C0B 1B0",
    "sg:province":"PE",
    "sg:tags":[
        "repairing",
        "automobile",
        "wheel",
        "axle"
    ],
    "wof:name":"Kevin's Front End Svc",
    "wof:placetype":"venue"
},
  "geometry": {"coordinates":[-64.065322876,46.8134651184],"type":"Point"}
}