{
  "type": "Feature",
  "properties": {
    "addr:full":"2039 Mount Forest Dr Burlington ON L7P 1H4",
    "addr:housenumber":"2039",
    "addr:postcode":"l7p 1h4",
    "addr:street":"Mount Forest Dr",
    "iso:country":"CA",
    "sg:address":"2039 Mount Forest Dr",
    "sg:city":"Burlington",
    "sg:classifiers":[
        {
            "category":"Personal",
            "subcategory":"Barber",
            "type":"Services"
        }
    ],
    "sg:phone":"+1 905 332 8257",
    "sg:postcode":"L7P 1H4",
    "sg:province":"ON",
    "wof:name":"Mount Royal Barber Shop",
    "wof:placetype":"venue"
},
  "geometry": {"coordinates":[-79.8275756836,43.347328186],"type":"Point"}
}