{
  "type": "Feature",
  "properties": {
    "addr:full":"Vancouver BC V5V 4C2",
    "addr:postcode":"v5v 4c2",
    "iso:country":"CA",
    "sg:city":"Vancouver",
    "sg:classifiers":[
        {
            "category":"Restaurant",
            "type":"Food & Drink"
        }
    ],
    "sg:phone":"+1 604 708 9925",
    "sg:postcode":"V5V 4C2",
    "sg:province":"BC",
    "wof:name":"Sushi Depot Tarafuka",
    "wof:placetype":"venue"
},
  "geometry": {"coordinates":[-123.08997345,49.2551498413],"type":"Point"}
}