{
  "type": "Feature",
  "properties": {
    "addr:full":"844 Princess St Kingston ON K7L 1G5",
    "addr:housenumber":"844",
    "addr:postcode":"k7l 1g5",
    "addr:street":"Princess St",
    "iso:country":"CA",
    "sg:address":"844 Princess St",
    "sg:city":"Kingston",
    "sg:classifiers":[
        {
            "category":"Organizations",
            "subcategory":"Professional Association",
            "type":"Services"
        }
    ],
    "sg:phone":"+1 613 549 7540",
    "sg:postcode":"K7L 1G5",
    "sg:province":"ON",
    "sg:tags":[
        "aids",
        "testing",
        "information"
    ],
    "wof:name":"Ontario Aboriginal Hivaids",
    "wof:placetype":"venue"
},
  "geometry": {"coordinates":[-76.50914001460001,44.2399330139],"type":"Point"}
}