{
  "type": "Feature",
  "properties": {
    "iso:country":"CA",
    "sg:address":"13135 116 Ave",
    "sg:city":"Surrey",
    "sg:classifiers":[
        {
            "category":"Manufacturing",
            "subcategory":"Metals",
            "type":"Manufacturing & Wholesale Goods"
        }
    ],
    "sg:phone":"+1 604 580 3337",
    "sg:postcode":"V3R 2S8",
    "sg:province":"BC",
    "sg:tags":[
        "steel"
    ],
    "wof:name":"World Fabricators Ltd",
    "wof:placetype":"venue"
},
  "geometry": {"coordinates":[-122.858292,49.213676],"type":"Point"}
}