{
  "type": "Feature",
  "properties": {
    "addr:full":"13135 116 Ave Surrey BC V3R 2S8",
    "addr:housenumber":"13135",
    "addr:postcode":"v3r 2s8",
    "addr:street":"116 Ave",
    "iso:country":"CA",
    "sg:address":"13135 116 Ave",
    "sg:city":"Surrey",
    "sg:classifiers":[
        {
            "category":"Manufacturing",
            "subcategory":"Metals",
            "type":"Manufacturing & Wholesale Goods"
        }
    ],
    "sg:phone":"+1 604 580 3337",
    "sg:postcode":"V3R 2S8",
    "sg:province":"BC",
    "sg:tags":[
        "steel"
    ],
    "wof:name":"World Fabricators Ltd",
    "wof:placetype":"venue"
},
  "geometry": {"coordinates":[-122.85829200000001,49.213676],"type":"Point"}
}