{
  "type": "Feature",
  "properties": {
    "addr:full":"1228 Rue Bishop Montreal QC H3G 2E3",
    "addr:housenumber":"1228",
    "addr:postcode":"h3g 2e3",
    "addr:street":"Rue Bishop",
    "iso:country":"CA",
    "sg:address":"1228 Rue Bishop",
    "sg:city":"Montreal",
    "sg:classifiers":[
        {
            "category":"Personal",
            "subcategory":"Massage",
            "type":"Services"
        }
    ],
    "sg:phone":"+1 514 861 1228",
    "sg:postcode":"H3G 2E3",
    "sg:province":"QC",
    "wof:name":"Massage-Plus",
    "wof:placetype":"venue"
},
  "geometry": {"coordinates":[-73.575378,45.495953],"type":"Point"}
}