{
  "type": "Feature",
  "properties": {
    "iso:country":"CA",
    "sg:city":"Richmond",
    "sg:classifiers":[
        {
            "category":"Government",
            "subcategory":"Office",
            "type":"Public Place"
        }
    ],
    "sg:phone":"+1 604 775 0891",
    "sg:postcode":"V6Y 2N9",
    "sg:province":"BC",
    "wof:name":"B C Members of the Legislative",
    "wof:placetype":"venue"
},
  "geometry": {"coordinates":[-123.125076294,49.1550331116],"type":"Point"}
}