{
  "type": "Feature",
  "properties": {
    "addr:full":"1040 Martin Grove Rd # 4 Etobicoke ON M9W 4W4",
    "addr:housenumber":"1040",
    "addr:postcode":"m9w 4w4",
    "addr:street":"Martin Grove Rd # 4",
    "iso:country":"CA",
    "sg:address":"1040 Martin Grove Rd # 4",
    "sg:city":"Etobicoke",
    "sg:classifiers":[
        {
            "category":"Professional",
            "subcategory":"Detective & Security Services",
            "type":"Services"
        }
    ],
    "sg:phone":"+1 416 398 7774",
    "sg:postcode":"M9W 4W4",
    "sg:province":"ON",
    "sg:tags":[
        "car",
        "armored"
    ],
    "wof:name":"Avero Security Gtai Inc",
    "wof:placetype":"venue"
},
  "geometry": {"coordinates":[-79.57337200000001,43.696651],"type":"Point"}
}