{
  "type": "Feature",
  "properties": {
    "addr:full":"83 Apple Tree Lane Kentville NS B4N 5C1",
    "addr:housenumber":"83",
    "addr:postcode":"b4n 5c1",
    "addr:street":"Apple Tree Lane",
    "iso:country":"CA",
    "sg:address":"83 Apple Tree Lane",
    "sg:city":"Kentville",
    "sg:classifiers":[
        {
            "category":"Shopping",
            "subcategory":"Computers & Home Electronics",
            "type":"Retail Goods"
        }
    ],
    "sg:phone":"+1 902 678 5454",
    "sg:postcode":"B4N 5C1",
    "sg:province":"NS",
    "sg:tags":[
        "software"
    ],
    "wof:name":"Best View Systems",
    "wof:placetype":"venue"
},
  "geometry": {"coordinates":[-64.483581543,45.0831565857],"type":"Point"}
}