{
  "type": "Feature",
  "properties": {
    "iso:country":"CA",
    "sg:address":"340 Elgin St",
    "sg:city":"Ottawa",
    "sg:classifiers":[
        {
            "category":"Restaurant",
            "type":"Food & Drink"
        }
    ],
    "sg:phone":"+1 613 232 5771",
    "sg:postcode":"K2P 1M6",
    "sg:province":"ON",
    "wof:name":"Maxwell's Bistro & Club",
    "wof:placetype":"venue"
},
  "geometry": {"coordinates":[-75.6887969971,45.4158248901],"type":"Point"}
}