{
  "type": "Feature",
  "properties": {
    "addr:full":"45768 Gaetz St # 2 Chilliwack BC V2R 4E5",
    "addr:postcode":"45768;v2r 4e5",
    "addr:street":"Gaetz St # 2",
    "iso:country":"CA",
    "sg:address":"45768 Gaetz St # 2",
    "sg:city":"Chilliwack",
    "sg:classifiers":[
        {
            "category":"Bars & Pubs",
            "type":"Food & Drink"
        }
    ],
    "sg:phone":"+1 604 858 4088",
    "sg:postcode":"V2R 4E5",
    "sg:province":"BC",
    "wof:name":"Major League 2",
    "wof:placetype":"venue"
},
  "geometry": {"coordinates":[-121.95752,49.136093],"type":"Point"}
}