{
  "type": "Feature",
  "properties": {
    "addr:full":"Shippagan NB E8S 1M1",
    "addr:postcode":"e8s 1m1",
    "iso:country":"CA",
    "sg:city":"Shippagan",
    "sg:classifiers":[
        {
            "category":"Travel",
            "subcategory":"Campground",
            "type":"Entertainment"
        }
    ],
    "sg:phone":"+1 506 336 3960",
    "sg:postcode":"E8S 1M1",
    "sg:province":"NB",
    "wof:name":"Camping Shippagan",
    "wof:placetype":"venue"
},
  "geometry": {"coordinates":[-64.7160491943,47.7408103943],"type":"Point"}
}