{
  "type": "Feature",
  "properties": {
    "iso:country":"CA",
    "sg:address":"8040 Rue Jarry E",
    "sg:city":"Anjou",
    "sg:classifiers":[
        {
            "category":"Wholesale",
            "subcategory":"Medical Equipment & Supplies",
            "type":"Manufacturing & Wholesale Goods"
        }
    ],
    "sg:phone":"+1 514 262 5223",
    "sg:postcode":"H1J 1H5",
    "sg:province":"QC",
    "sg:tags":[
        "dental"
    ],
    "wof:name":"Ramdent Inc",
    "wof:placetype":"venue"
},
  "geometry": {"coordinates":[-73.5662155151,45.6121940613],"type":"Point"}
}