{
  "type": "Feature",
  "properties": {
    "addr:full":"214 King St W Toronto ON M5H 3S6",
    "addr:housenumber":"214",
    "addr:postcode":"m5h 3s6",
    "addr:street":"King St W",
    "iso:country":"CA",
    "sg:address":"214 King St W",
    "sg:city":"Toronto",
    "sg:classifiers":[
        {
            "category":"Professional",
            "subcategory":"Management & Consulting",
            "type":"Services"
        }
    ],
    "sg:phone":"+1 416 860 3899",
    "sg:postcode":"M5H 3S6",
    "sg:province":"ON",
    "sg:tags":[
        "communications",
        "consultant"
    ],
    "wof:name":"Itpr",
    "wof:placetype":"venue"
},
  "geometry": {"coordinates":[-79.386314,43.647449],"type":"Point"}
}