{
  "type": "Feature",
  "properties": {
    "addr:full":"216 Lindsay St Winnipeg MB R3N 1H1",
    "addr:housenumber":"216",
    "addr:postcode":"r3n 1h1",
    "addr:street":"Lindsay St",
    "iso:country":"CA",
    "sg:address":"216 Lindsay St",
    "sg:city":"Winnipeg",
    "sg:classifiers":[
        {
            "category":"Wholesale",
            "subcategory":"Photographic Equipment",
            "type":"Manufacturing & Wholesale Goods"
        }
    ],
    "sg:phone":"+1 204 487 1207",
    "sg:postcode":"R3N 1H1",
    "sg:province":"MB",
    "sg:tags":[
        "audio"
    ],
    "wof:name":"Sound Advice Group",
    "wof:placetype":"venue"
},
  "geometry": {"coordinates":[-97.192902,49.872681],"type":"Point"}
}