{
  "type": "Feature",
  "properties": {
    "iso:country":"CA",
    "sg:city":"Trois-Pistoles",
    "sg:classifiers":[
        {
            "category":"Shopping",
            "type":"Retail Goods"
        }
    ],
    "sg:phone":"+1 418 851 1656",
    "sg:postcode":"G0L 4K0",
    "sg:province":"QC",
    "sg:tags":[
        "art",
        "gallery",
        "dealer"
    ],
    "wof:name":"Maison Du Notaire",
    "wof:placetype":"venue"
},
  "geometry": {"coordinates":[-69.1705856323,48.1273269653],"type":"Point"}
}