{
  "type": "Feature",
  "properties": {
    "iso:country":"CA",
    "sg:address":"69 Walker St",
    "sg:city":"Truro",
    "sg:classifiers":[
        {
            "category":"Utilities",
            "subcategory":"Telephone",
            "type":"Services"
        }
    ],
    "sg:phone":"+1 902 843 2800",
    "sg:postcode":"B2N 4A8",
    "sg:province":"NS",
    "sg:tags":[
        "company"
    ],
    "wof:name":"Eastlink",
    "wof:placetype":"venue"
},
  "geometry": {"coordinates":[-63.2726135254,45.3651275635],"type":"Point"}
}