{
  "type": "Feature",
  "properties": {
    "addr:full":"Fort Mcmurray AB T9H 1L2",
    "addr:postcode":"t9h 1l2",
    "iso:country":"CA",
    "sg:city":"Fort Mcmurray",
    "sg:classifiers":[
        {
            "category":"Food & Beverages",
            "subcategory":"Groceries & Convenience Stores",
            "type":"Retail Goods"
        }
    ],
    "sg:phone":"+1 780 799 4419",
    "sg:postcode":"T9H 1L2",
    "sg:province":"AB",
    "wof:name":"Concourse News Ltd",
    "wof:placetype":"venue"
},
  "geometry": {"coordinates":[-111.380966187,56.7248878479],"type":"Point"}
}