{
  "type": "Feature",
  "properties": {
    "addr:full":"909 Grey St Regina SK S4T 5H1",
    "addr:housenumber":"909",
    "addr:postcode":"s4t 5h1",
    "addr:street":"Grey St",
    "iso:country":"CA",
    "sg:address":"909 Grey St",
    "sg:city":"Regina",
    "sg:classifiers":[
        {
            "category":"Real Estate",
            "subcategory":"Real Estate Operator",
            "type":"Services"
        }
    ],
    "sg:phone":"+1 306 751 2270",
    "sg:postcode":"S4T 5H1",
    "sg:province":"SK",
    "sg:tags":[
        "apartment"
    ],
    "wof:name":"Grey Apartments",
    "wof:placetype":"venue"
},
  "geometry": {"coordinates":[-104.655158997,50.4637794495],"type":"Point"}
}