{
  "type": "Feature",
  "properties": {
    "addr:full":"416 16 Ave NE Calgary AB T2E 1K2",
    "addr:postcode":"416;t2e 1k2",
    "addr:street":"16 Ave Ne",
    "iso:country":"CA",
    "sg:address":"416 16 Ave NE",
    "sg:city":"Calgary",
    "sg:classifiers":[
        {
            "category":"Restaurant",
            "type":"Food & Drink"
        }
    ],
    "sg:phone":"+1 403 230 9267",
    "sg:postcode":"T2E 1K2",
    "sg:province":"AB",
    "wof:name":"Eastern Fortune Restaurant",
    "wof:placetype":"venue"
},
  "geometry": {"coordinates":[-114.054504395,51.0671195984],"type":"Point"}
}