{
  "type": "Feature",
  "properties": {
    "iso:country":"CA",
    "sg:address":"50 Boul Morin",
    "sg:city":"Sainte-Agathe-Des-Monts",
    "sg:classifiers":[
        {
            "category":"Autos & Motor Vehicles",
            "subcategory":"Auto Supplies",
            "type":"Retail Goods"
        }
    ],
    "sg:phone":"+1 819 326 8900",
    "sg:postcode":"J8C 2V6",
    "sg:province":"QC",
    "sg:tags":[
        "repairing",
        "automobile",
        "parts"
    ],
    "wof:name":"Canadian Tire",
    "wof:placetype":"venue"
},
  "geometry": {"coordinates":[-74.28346252439999,46.0474090576],"type":"Point"}
}