{
  "type": "Feature",
  "properties": {
    "addr:full":"116 Mitton St N Sarnia ON N7T 6G4",
    "addr:housenumber":"116",
    "addr:postcode":"n7t 6g4",
    "addr:street":"Mitton St N",
    "iso:country":"CA",
    "sg:address":"116 Mitton St N",
    "sg:city":"Sarnia",
    "sg:classifiers":[
        {
            "category":"Health Services",
            "subcategory":"Doctor",
            "type":"Services"
        }
    ],
    "sg:phone":"+1 519 332 1811",
    "sg:postcode":"N7T 6G4",
    "sg:province":"ON",
    "sg:tags":[
        "physician",
        "surgeon"
    ],
    "wof:name":"Shetty, Pandu MD",
    "wof:placetype":"venue"
},
  "geometry": {"coordinates":[-82.3981704712,42.9711227417],"type":"Point"}
}