{
  "type": "Feature",
  "properties": {
    "addr:full":"468 Rue Graveline Gatineau QC J8P 3H1",
    "addr:housenumber":"468",
    "addr:postcode":"j8p 3h1",
    "addr:street":"Rue Graveline",
    "iso:country":"CA",
    "sg:address":"468 Rue Graveline",
    "sg:city":"Gatineau",
    "sg:classifiers":[
        {
            "category":"Wholesale",
            "subcategory":"Meat",
            "type":"Manufacturing & Wholesale Goods"
        }
    ],
    "sg:phone":"+1 819 663 4395",
    "sg:postcode":"J8P 3H1",
    "sg:province":"QC",
    "sg:tags":[
        "butchering"
    ],
    "wof:name":"Boucherie Allard & Belisle Enr",
    "wof:placetype":"venue"
},
  "geometry": {"coordinates":[-75.669067,45.486622],"type":"Point"}
}