{
  "type": "Feature",
  "properties": {
    "addr:full":"1905 Ch Hemming Saint-Charles-DE-Drummond QC J2B 7T5",
    "addr:housenumber":"1905",
    "addr:postcode":"j2b 7t5",
    "addr:street":"Ch Hemming",
    "iso:country":"CA",
    "sg:address":"1905 Ch Hemming",
    "sg:city":"Saint-Charles-DE-Drummond",
    "sg:classifiers":[
        {
            "category":"Manufacturing",
            "subcategory":"Signs",
            "type":"Manufacturing & Wholesale Goods"
        }
    ],
    "sg:phone":"+1 819 474 4878",
    "sg:postcode":"J2B 7T5",
    "sg:province":"QC",
    "wof:name":"Enseignes Drummond",
    "wof:placetype":"venue"
},
  "geometry": {"coordinates":[-72.423096,45.862907],"type":"Point"}
}