{
  "type": "Feature",
  "properties": {
    "addr:full":"215 8 Ave SE Calgary AB T2G 0K8",
    "addr:housenumber":"215",
    "addr:postcode":"t2g 0k8",
    "addr:street":"8 Ave Se",
    "iso:country":"CA",
    "sg:address":"215 8 Ave SE",
    "sg:city":"Calgary",
    "sg:classifiers":[
        {
            "category":"Shopping",
            "subcategory":"Gifts & Souvenirs",
            "type":"Retail Goods"
        }
    ],
    "sg:phone":"+1 403 294 7474",
    "sg:postcode":"T2G 0K8",
    "sg:province":"AB",
    "sg:tags":[
        "shop"
    ],
    "wof:name":"Atp Just the Ticket Gift Shp",
    "wof:placetype":"venue"
},
  "geometry": {"coordinates":[-114.06001999999999,51.045307],"type":"Point"}
}