{
  "type": "Feature",
  "properties": {
    "iso:country":"CA",
    "sg:address":"493 12E Av",
    "sg:city":"Senneterre",
    "sg:classifiers":[
        {
            "category":"Organizations",
            "subcategory":"Religious Organization",
            "type":"Services"
        }
    ],
    "sg:phone":"+1 819 737 2834",
    "sg:postcode":"J0Y 2M0",
    "sg:province":"QC",
    "sg:tags":[
        "church"
    ],
    "wof:name":"Eglise Bonne Nouvelle",
    "wof:placetype":"venue"
},
  "geometry": {"coordinates":[-77.23705291749999,48.3925323486],"type":"Point"}
}