{
  "type": "Feature",
  "properties": {
    "addr:full":"455 Av Du Phare E Matane QC G4W 1A5",
    "addr:postcode":"g4w 1a5",
    "addr:street":"455 Av Du Phare E",
    "iso:country":"CA",
    "sg:address":"455 Av Du Phare E",
    "sg:city":"Matane",
    "sg:classifiers":[
        {
            "category":"Wholesale",
            "subcategory":"Machinery & Supplies",
            "type":"Manufacturing & Wholesale Goods"
        }
    ],
    "sg:phone":"+1 418 562 0823",
    "sg:postcode":"G4W 1A5",
    "sg:province":"QC",
    "sg:tags":[
        "farm",
        "equipment"
    ],
    "wof:name":"E Desjardins & Fils Inc",
    "wof:placetype":"venue"
},
  "geometry": {"coordinates":[-67.51705200000001,48.852283],"type":"Point"}
}