{
  "type": "Feature",
  "properties": {
    "addr:full":"2000 Dundas St London ON N5V 3Z1",
    "addr:housenumber":"2000",
    "addr:postcode":"n5v 3z1",
    "addr:street":"Dundas St",
    "iso:country":"CA",
    "sg:address":"2000 Dundas St",
    "sg:city":"London",
    "sg:classifiers":[
        {
            "category":"Restaurant",
            "type":"Food & Drink"
        }
    ],
    "sg:phone":"+1 519 457 2468",
    "sg:postcode":"N5V 3Z1",
    "sg:province":"ON",
    "wof:name":"Harvey's",
    "wof:placetype":"venue"
},
  "geometry": {"coordinates":[-81.170288,43.006439],"type":"Point"}
}