{
  "type": "Feature",
  "properties": {
    "addr:full":"300 Fairview Dr Brantford ON N3R 2X6",
    "addr:housenumber":"300",
    "addr:postcode":"n3r 2x6",
    "addr:street":"Fairview Dr",
    "iso:country":"CA",
    "sg:address":"300 Fairview Dr",
    "sg:city":"Brantford",
    "sg:classifiers":[
        {
            "category":"Organizations",
            "subcategory":"Religious Organization",
            "type":"Services"
        }
    ],
    "sg:phone":"+1 519 752 3778",
    "sg:postcode":"N3R 2X6",
    "sg:province":"ON",
    "sg:tags":[
        "church"
    ],
    "wof:name":"Central Baptist Church",
    "wof:placetype":"venue"
},
  "geometry": {"coordinates":[-80.26016199999999,43.170135],"type":"Point"}
}