{
  "type": "Feature",
  "properties": {
    "addr:full":"10065 100 St NW Edmonton AB T5J 0N6",
    "addr:housenumber":"10065",
    "addr:postcode":"t5j 0n6",
    "addr:street":"100 St Nw",
    "iso:country":"CA",
    "sg:address":"10065 100 St NW",
    "sg:city":"Edmonton",
    "sg:classifiers":[
        {
            "category":"Personal",
            "type":"Services"
        }
    ],
    "sg:phone":"+1 780 429 6423",
    "sg:postcode":"T5J 0N6",
    "sg:province":"AB",
    "sg:tags":[
        "therapist",
        "massage"
    ],
    "wof:name":"Mac Donald Health Club",
    "wof:placetype":"venue"
},
  "geometry": {"coordinates":[-113.489974976,53.5404205322],"type":"Point"}
}