{
  "type": "Feature",
  "properties": {
    "addr:full":"525 116 Rte Acton Vale QC J0H 1A0",
    "addr:housenumber":"116",
    "addr:postcode":"j0h 1a0",
    "addr:street":"Rte",
    "iso:country":"CA",
    "sg:address":"525 116 Rte",
    "sg:city":"Acton Vale",
    "sg:classifiers":[
        {
            "category":"Manufacturing",
            "subcategory":"Glass & Minerals",
            "type":"Manufacturing & Wholesale Goods"
        }
    ],
    "sg:phone":"+1 450 546 3201",
    "sg:postcode":"J0H 1A0",
    "sg:province":"QC",
    "sg:tags":[
        "stone"
    ],
    "wof:name":"Carriere D'Acton Vale Ltee",
    "wof:placetype":"venue"
},
  "geometry": {"coordinates":[-72.42334700000001,45.629257],"type":"Point"}
}