{
  "type": "Feature",
  "properties": {
    "addr:full":"218 Girton Blvd Winnipeg MB R3P 0A7",
    "addr:housenumber":"218",
    "addr:postcode":"r3p 0a7",
    "addr:street":"Girton Blvd",
    "iso:country":"CA",
    "sg:address":"218 Girton Blvd",
    "sg:city":"Winnipeg",
    "sg:classifiers":[
        {
            "category":"Professional",
            "type":"Services"
        }
    ],
    "sg:phone":"+1 204 489 6766",
    "sg:postcode":"R3P 0A7",
    "sg:province":"MB",
    "sg:tags":[
        "consulting",
        "chemist"
    ],
    "wof:name":"Spdf Chemical Assoc Ltd",
    "wof:placetype":"venue"
},
  "geometry": {"coordinates":[-97.2142562866,49.8695297241],"type":"Point"}
}