{
  "type": "Feature",
  "properties": {
    "addr:full":"Anjou QC H1M 1W9",
    "addr:postcode":"h1m 1w9",
    "iso:country":"CA",
    "sg:city":"Anjou",
    "sg:classifiers":[
        {
            "category":"Shopping",
            "subcategory":"Jewelry",
            "type":"Retail Goods"
        }
    ],
    "sg:phone":"+1 514 354 5606",
    "sg:postcode":"H1M 1W9",
    "sg:province":"QC",
    "sg:tags":[
        "jeweler"
    ],
    "wof:name":"Doucet Bijoutiers",
    "wof:placetype":"venue"
},
  "geometry": {"coordinates":[-73.539665,45.610252],"type":"Point"}
}