{
  "type": "Feature",
  "properties": {
    "addr:full":"690 Rue Notre-Dame O Victoriaville QC G6P 1T4",
    "addr:housenumber":"690",
    "addr:postcode":"g6p 1t4",
    "addr:street":"Rue Notre-Dame O",
    "iso:country":"CA",
    "sg:address":"690 Rue Notre-Dame O",
    "sg:city":"Victoriaville",
    "sg:classifiers":[
        {
            "category":"Retail",
            "subcategory":"Auto Repair",
            "type":"Services"
        }
    ],
    "sg:phone":"+1 819 752 4015",
    "sg:postcode":"G6P 1T4",
    "sg:province":"QC",
    "sg:tags":[
        "transmission",
        "automobile",
        "repairing"
    ],
    "wof:name":"Beaulieu Transmission Atmtq",
    "wof:placetype":"venue"
},
  "geometry": {"coordinates":[-71.9423675537,46.0635528564],"type":"Point"}
}