{
  "type": "Feature",
  "properties": {
    "addr:full":"5506 Willow Ave Powell River BC V8A 4P4",
    "addr:housenumber":"5506",
    "addr:postcode":"v8a 4p4",
    "addr:street":"Willow Ave Powell",
    "iso:country":"CA",
    "sg:address":"5506 Willow Ave",
    "sg:city":"Powell River",
    "sg:classifiers":[
        {
            "category":"Education",
            "subcategory":"School",
            "type":"Public Place"
        }
    ],
    "sg:phone":"+1 604 483 9162",
    "sg:postcode":"V8A 4P4",
    "sg:province":"BC",
    "wof:name":"Henderson Elementary School",
    "wof:placetype":"venue"
},
  "geometry": {"coordinates":[-124.54359436,49.8646087646],"type":"Point"}
}