{
  "type": "Feature",
  "properties": {
    "addr:full":"Blainville QC J7C 2N8",
    "addr:postcode":"j7c 2n8",
    "iso:country":"CA",
    "sg:city":"Blainville",
    "sg:classifiers":[
        {
            "category":"Food & Beverages",
            "subcategory":"Groceries & Convenience Stores",
            "type":"Retail Goods"
        }
    ],
    "sg:phone":"+1 450 435 9400",
    "sg:postcode":"J7C 2N8",
    "sg:province":"QC",
    "sg:tags":[
        "grocer"
    ],
    "wof:name":"Depanneur Propio",
    "wof:placetype":"venue"
},
  "geometry": {"coordinates":[-73.89894104,45.6858596802],"type":"Point"}
}