{
  "type": "Feature",
  "properties": {
    "addr:full":"618 Boul Renault Beauceville QC G5X 1M8",
    "addr:housenumber":"618",
    "addr:postcode":"g5x 1m8",
    "addr:street":"Boul Renault",
    "iso:country":"CA",
    "sg:address":"618 Boul Renault",
    "sg:city":"Beauceville",
    "sg:classifiers":[
        {
            "category":"Shopping",
            "subcategory":"Pharmacy",
            "type":"Retail Goods"
        }
    ],
    "sg:phone":"+1 418 774 3343",
    "sg:postcode":"G5X 1M8",
    "sg:province":"QC",
    "wof:name":"Pharmacie Uniprix",
    "wof:placetype":"venue"
},
  "geometry": {"coordinates":[-70.77398700000001,46.208328],"type":"Point"}
}