{
  "type": "Feature",
  "properties": {
    "addr:full":"90 Emchiss Way Bamfield BC V0R 1B0",
    "addr:housenumber":"90",
    "addr:postcode":"v0r 1b0",
    "addr:street":"Emchiss Way",
    "iso:country":"CA",
    "sg:address":"90 Emchiss Way",
    "sg:city":"Bamfield",
    "sg:classifiers":[
        {
            "category":"Organizations",
            "subcategory":"Professional Association",
            "type":"Services"
        }
    ],
    "sg:phone":"+1 250 728 3414",
    "sg:postcode":"V0R 1B0",
    "sg:province":"BC",
    "wof:name":"Ohiaht Band Office",
    "wof:placetype":"venue"
},
  "geometry": {"coordinates":[-125.134743,48.819843],"type":"Point"}
}