{
  "type": "Feature",
  "properties": {
    "iso:country":"CA",
    "sg:address":"10580 Av Lamoureux",
    "sg:city":"Montreal-Nord",
    "sg:classifiers":[
        {
            "category":"Retail",
            "subcategory":"Auto Repair",
            "type":"Services"
        }
    ],
    "sg:phone":"+1 514 321 6886",
    "sg:postcode":"H1G 5L3",
    "sg:province":"QC",
    "sg:tags":[
        "repairing",
        "automobile"
    ],
    "wof:name":"Auto 37",
    "wof:placetype":"venue"
},
  "geometry": {"coordinates":[-73.62265,45.594448],"type":"Point"}
}