{
  "type": "Feature",
  "properties": {
    "iso:country":"CA",
    "sg:address":"191 Dawn Dr",
    "sg:city":"London",
    "sg:classifiers":[
        {
            "category":"Education",
            "subcategory":"School",
            "type":"Public Place"
        }
    ],
    "sg:phone":"+1 519 452 8480",
    "sg:postcode":"N5W 4W9",
    "sg:province":"ON",
    "wof:name":"Princess Anne School",
    "wof:placetype":"venue"
},
  "geometry": {"coordinates":[-81.18,42.992283],"type":"Point"}
}