{
  "type": "Feature",
  "properties": {
    "addr:full":"837 Dundas St W Toronto ON M6J 1V4",
    "addr:housenumber":"837",
    "addr:postcode":"m6j 1v4",
    "addr:street":"Dundas St W",
    "iso:country":"CA",
    "sg:address":"837 Dundas St W",
    "sg:city":"Toronto",
    "sg:classifiers":[
        {
            "category":"Wholesale",
            "subcategory":"Meat",
            "type":"Manufacturing & Wholesale Goods"
        }
    ],
    "sg:phone":"+1 416 603 0921",
    "sg:postcode":"M6J 1V4",
    "sg:province":"ON",
    "sg:tags":[
        "butchering"
    ],
    "wof:name":"Portuguese Butcher",
    "wof:placetype":"venue"
},
  "geometry": {"coordinates":[-79.409424,43.651459],"type":"Point"}
}