{
  "type": "Feature",
  "properties": {
    "addr:full":"117 Rue Saint-Charles-Borromee Joliette QC J6E 4R3",
    "addr:housenumber":"117",
    "addr:postcode":"j6e 4r3",
    "addr:street":"Rue Saint-Charles-Borromee",
    "iso:country":"CA",
    "sg:address":"117 Rue Saint-Charles-Borromee",
    "sg:city":"Joliette",
    "sg:classifiers":[
        {
            "category":"Shopping",
            "subcategory":"Bicycles & Sporting Goods",
            "type":"Retail Goods"
        }
    ],
    "sg:phone":"+1 450 759 3312",
    "sg:postcode":"J6E 4R3",
    "sg:province":"QC",
    "sg:tags":[
        "tackle",
        "fishing"
    ],
    "wof:name":"Morin Sports",
    "wof:placetype":"venue"
},
  "geometry": {"coordinates":[-73.438774,46.027824],"type":"Point"}
}