{
  "type": "Feature",
  "properties": {
    "iso:country":"CA",
    "sg:address":"5752 Nickerson Rd",
    "sg:city":"Sechelt",
    "sg:classifiers":[
        {
            "category":"Retail",
            "subcategory":"Repair Shop",
            "type":"Services"
        }
    ],
    "sg:phone":"+1 604 885 9816",
    "sg:postcode":"V0N 3A7",
    "sg:province":"BC",
    "sg:tags":[
        "television",
        "radio"
    ],
    "wof:name":"Sunshine Coast Tv Ltd",
    "wof:placetype":"venue"
},
  "geometry": {"coordinates":[-123.79060363799999,49.4800338745],"type":"Point"}
}