{
  "type": "Feature",
  "properties": {
    "iso:country":"CA",
    "sg:address":"3240 Yonge St",
    "sg:city":"Toronto",
    "sg:classifiers":[
        {
            "category":"Personal",
            "subcategory":"Beauty Salon",
            "type":"Services"
        }
    ],
    "sg:phone":"+1 416 482 2772",
    "sg:postcode":"M4N 2L4",
    "sg:province":"ON",
    "wof:name":"Sebastian's Hair Design",
    "wof:placetype":"venue"
},
  "geometry": {"coordinates":[-79.40344238279999,43.7294845581],"type":"Point"}
}