{
  "type": "Feature",
  "properties": {
    "addr:full":"350 Silvercreek Pky N Guelph ON N1H 1E7",
    "addr:housenumber":"350",
    "addr:postcode":"n1h 1e7",
    "addr:street":"Silvercreek Pky N",
    "iso:country":"CA",
    "sg:address":"350 Silvercreek Pky N",
    "sg:city":"Guelph",
    "sg:classifiers":[
        {
            "category":"Wholesale",
            "subcategory":"Metals & Minerals",
            "type":"Manufacturing & Wholesale Goods"
        }
    ],
    "sg:phone":"+1 519 829 3292",
    "sg:postcode":"N1H 1E7",
    "sg:province":"ON",
    "sg:tags":[
        "specialty"
    ],
    "wof:name":"Wright Metal Fabricators Ltd",
    "wof:placetype":"venue"
},
  "geometry": {"coordinates":[-80.29070299999999,43.547195],"type":"Point"}
}