{
  "type": "Feature",
  "properties": {
    "addr:full":"141 Rue Notre-Dame Yamachiche QC G0X 3L0",
    "addr:housenumber":"141",
    "addr:postcode":"g0x 3l0",
    "addr:street":"Rue Notre-Dame",
    "iso:country":"CA",
    "sg:address":"141 Rue Notre-Dame",
    "sg:city":"Yamachiche",
    "sg:classifiers":[
        {
            "category":"Professional",
            "subcategory":"Business Services",
            "type":"Services"
        }
    ],
    "sg:phone":"+1 819 296 3404",
    "sg:postcode":"G0X 3L0",
    "sg:province":"QC",
    "sg:tags":[
        "notary"
    ],
    "wof:name":"Leboeuf, Renee",
    "wof:placetype":"venue"
},
  "geometry": {"coordinates":[-72.8300628662,46.283744812],"type":"Point"}
}