{
  "type": "Feature",
  "properties": {
    "addr:full":"1423 70 Ave NW Edmonton AB T6P 1N5",
    "addr:housenumber":"1423",
    "addr:postcode":"t6p 1n5",
    "addr:street":"70 Ave Nw",
    "iso:country":"CA",
    "sg:address":"1423 70 Ave NW",
    "sg:city":"Edmonton",
    "sg:classifiers":[
        {
            "category":"Building & Trades",
            "subcategory":"Construction",
            "type":"Services"
        }
    ],
    "sg:phone":"+1 780 440 4140",
    "sg:postcode":"T6P 1N5",
    "sg:province":"AB",
    "sg:tags":[
        "roofing",
        "contractor"
    ],
    "wof:name":"Acron Roofing Systems Inc",
    "wof:placetype":"venue"
},
  "geometry": {"coordinates":[-113.364716,53.506546],"type":"Point"}
}