{
  "type": "Feature",
  "properties": {
    "addr:full":"1515 Kerr Ave Erieau ON N0P 1N0",
    "addr:housenumber":"1515",
    "addr:postcode":"n0p 1n0",
    "addr:street":"Kerr Ave",
    "iso:country":"CA",
    "sg:address":"1515 Kerr Ave",
    "sg:city":"Erieau",
    "sg:classifiers":[
        {
            "category":"Recreation",
            "subcategory":"Marina",
            "type":"Entertainment"
        }
    ],
    "sg:phone":"+1 519 676 4511",
    "sg:postcode":"N0P 1N0",
    "sg:province":"ON",
    "sg:tags":[
        "repairing",
        "boat"
    ],
    "wof:name":"Barney's Boats Inc",
    "wof:placetype":"venue"
},
  "geometry": {"coordinates":[-81.909752,42.260769],"type":"Point"}
}