{
  "type": "Feature",
  "properties": {
    "addr:full":"7707 104 St NW Edmonton AB T6E 4C4",
    "addr:housenumber":"7707",
    "addr:postcode":"t6e 4c4",
    "addr:street":"104 St Nw",
    "iso:country":"CA",
    "sg:address":"7707 104 St NW",
    "sg:city":"Edmonton",
    "sg:classifiers":[
        {
            "category":"Professional",
            "subcategory":"Management & Consulting",
            "type":"Services"
        }
    ],
    "sg:phone":"+1 780 434 6666",
    "sg:postcode":"T6E 4C4",
    "sg:province":"AB",
    "sg:tags":[
        "consultant",
        "satellite",
        "lighting",
        "system",
        "equipment"
    ],
    "wof:name":"Systems Inc",
    "wof:placetype":"venue"
},
  "geometry": {"coordinates":[-113.49726099999999,53.513428],"type":"Point"}
}