{
  "type": "Feature",
  "properties": {
    "addr:full":"878 Route 113 Inkerman NB E8P 1C9",
    "addr:housenumber":"878",
    "addr:postcode":"e8p 1c9",
    "addr:street":"Route 113",
    "iso:country":"CA",
    "sg:address":"878 Route 113",
    "sg:city":"Inkerman",
    "sg:classifiers":[
        {
            "category":"Autos & Motor Vehicles",
            "subcategory":"Auto Supplies",
            "type":"Retail Goods"
        }
    ],
    "sg:phone":"+1 506 336 4738",
    "sg:postcode":"E8P 1C9",
    "sg:province":"NB",
    "sg:tags":[
        "automobile",
        "parts"
    ],
    "wof:name":"Basque Gilles Sales Ltd",
    "wof:placetype":"venue"
},
  "geometry": {"coordinates":[-64.82586669920001,47.6679382324],"type":"Point"}
}