{
  "type": "Feature",
  "properties": {
    "addr:full":"32566 Fourteenth Ave Mission BC V2V 2N9",
    "addr:housenumber":"32566",
    "addr:postcode":"v2v 2n9",
    "addr:street":"Fourteenth Ave",
    "iso:country":"CA",
    "sg:address":"32566 Fourteenth Ave",
    "sg:city":"Mission",
    "sg:classifiers":[
        {
            "category":"Building & Trades",
            "subcategory":"Cleaning & Sanitation",
            "type":"Services"
        }
    ],
    "sg:phone":"+1 604 826 6637",
    "sg:postcode":"V2V 2N9",
    "sg:province":"BC",
    "sg:tags":[
        "house"
    ],
    "wof:name":"Your Time To Shine House Clng",
    "wof:placetype":"venue"
},
  "geometry": {"coordinates":[-122.322135925,49.1471824646],"type":"Point"}
}