{
  "type": "Feature",
  "properties": {
    "iso:country":"CA",
    "sg:address":"4128 South Service Rd",
    "sg:city":"Burlington",
    "sg:classifiers":[
        {
            "category":"Manufacturing",
            "subcategory":"Metals",
            "type":"Manufacturing & Wholesale Goods"
        }
    ],
    "sg:phone":"+1 905 631 0990",
    "sg:postcode":"L7L 4X5",
    "sg:province":"ON",
    "sg:tags":[
        "garbage",
        "collection"
    ],
    "wof:name":"Happy Harry's",
    "wof:placetype":"venue"
},
  "geometry": {"coordinates":[-79.78354644780001,43.3695449829],"type":"Point"}
}