{
  "type": "Feature",
  "properties": {
    "iso:country":"CA",
    "sg:city":"Richmond",
    "sg:classifiers":[
        {
            "category":"Freight",
            "type":"Transportation"
        }
    ],
    "sg:phone":"+1 604 821 1145",
    "sg:postcode":"V6V 1P3",
    "sg:province":"BC",
    "sg:tags":[
        "warehouse",
        "public"
    ],
    "wof:name":"Paramount Storage Ltd",
    "wof:placetype":"venue"
},
  "geometry": {"coordinates":[-123.069450378,49.1960487366],"type":"Point"}
}