{
  "type": "Feature",
  "properties": {
    "addr:full":"785 Rue Brault Verdun QC H4H 2B3",
    "addr:housenumber":"785",
    "addr:postcode":"h4h 2b3",
    "addr:street":"Rue Brault",
    "iso:country":"CA",
    "sg:address":"785 Rue Brault",
    "sg:city":"Verdun",
    "sg:classifiers":[
        {
            "category":"Organizations",
            "subcategory":"Religious Organization",
            "type":"Services"
        }
    ],
    "sg:phone":"+1 514 769 3459",
    "sg:postcode":"H4H 2B3",
    "sg:province":"QC",
    "sg:tags":[
        "church"
    ],
    "wof:name":"Notre Dame DE LA Garde Eglise",
    "wof:placetype":"venue"
},
  "geometry": {"coordinates":[-73.57473,45.448097],"type":"Point"}
}