{
  "type": "Feature",
  "properties": {
    "addr:full":"2631 Douglas St Victoria BC V8T 4M2",
    "addr:housenumber":"2631",
    "addr:postcode":"v8t 4m2",
    "addr:street":"Douglas St",
    "iso:country":"CA",
    "sg:address":"2631 Douglas St",
    "sg:city":"Victoria",
    "sg:classifiers":[
        {
            "category":"Government",
            "subcategory":"Office",
            "type":"Public Place"
        }
    ],
    "sg:phone":"+1 250 387 5585",
    "sg:postcode":"V8T 4M2",
    "sg:province":"BC",
    "wof:name":"BC Dangerous Goods",
    "wof:placetype":"venue"
},
  "geometry": {"coordinates":[-123.36594390899999,48.4370574951],"type":"Point"}
}