{
  "type": "Feature",
  "properties": {
    "addr:full":"PO Box 121 Hunter River PE C0A 1N0",
    "addr:housenumber":"po",
    "addr:postcode":"c0a 1n0",
    "addr:street":"Box 121",
    "iso:country":"CA",
    "sg:address":"PO Box 121",
    "sg:city":"Hunter River",
    "sg:classifiers":[
        {
            "category":"Wholesale",
            "subcategory":"Hardware",
            "type":"Manufacturing & Wholesale Goods"
        }
    ],
    "sg:phone":"+1 902 964 3006",
    "sg:postcode":"C0A 1N0",
    "sg:province":"PE",
    "sg:tags":[
        "equipment",
        "energy",
        "solar"
    ],
    "wof:name":"Dba Solar",
    "wof:placetype":"venue"
},
  "geometry": {"coordinates":[-63.343147,46.351761],"type":"Point"}
}