{
  "type": "Feature",
  "properties": {
    "addr:full":"Clerval QC J0Z 1R0",
    "addr:postcode":"j0z 1r0",
    "iso:country":"CA",
    "sg:city":"Clerval",
    "sg:classifiers":[
        {
            "category":"Restaurant",
            "type":"Food & Drink"
        }
    ],
    "sg:phone":"+1 819 783 2176",
    "sg:postcode":"J0Z 1R0",
    "sg:province":"QC",
    "wof:name":"Resto Bar Soleil Couchant",
    "wof:placetype":"venue"
},
  "geometry": {"coordinates":[-79.460724,48.727207],"type":"Point"}
}