{
  "type": "Feature",
  "properties": {
    "addr:full":"2953 Bathurst St North York ON M6B 3B2",
    "addr:housenumber":"2953",
    "addr:postcode":"m6b 3b2",
    "addr:street":"Bathurst St",
    "iso:country":"CA",
    "sg:address":"2953 Bathurst St",
    "sg:city":"North York",
    "sg:classifiers":[
        {
            "category":"Professional",
            "subcategory":"Accounting & Tax Preparation",
            "type":"Services"
        }
    ],
    "sg:phone":"+1 416 785 7444",
    "sg:postcode":"M6B 3B2",
    "sg:province":"ON",
    "sg:tags":[
        "consultant"
    ],
    "wof:name":"U S Tax Recovery Inc",
    "wof:placetype":"venue"
},
  "geometry": {"coordinates":[-79.42888600000001,43.71637],"type":"Point"}
}