{
  "type": "Feature",
  "properties": {
    "addr:full":"2962 Millar Ave Saskatoon SK S7K 5X7",
    "addr:housenumber":"2962",
    "addr:postcode":"s7k 5x7",
    "addr:street":"Millar Ave",
    "iso:country":"CA",
    "sg:address":"2962 Millar Ave",
    "sg:city":"Saskatoon",
    "sg:classifiers":[
        {
            "category":"Retail",
            "subcategory":"Auto Repair",
            "type":"Services"
        }
    ],
    "sg:phone":"+1 306 934 2666",
    "sg:postcode":"S7K 5X7",
    "sg:province":"SK",
    "sg:tags":[
        "body",
        "automobile",
        "painting"
    ],
    "wof:name":"Mark's Auto Body Ltd",
    "wof:placetype":"venue"
},
  "geometry": {"coordinates":[-106.646294,52.175709],"type":"Point"}
}