{
  "type": "Feature",
  "properties": {
    "addr:full":"332 York St London ON N6B 1P8",
    "addr:housenumber":"332",
    "addr:postcode":"n6b 1p8",
    "addr:street":"York St",
    "iso:country":"CA",
    "sg:address":"332 York St",
    "sg:city":"London",
    "sg:classifiers":[
        {
            "category":"Autos & Motor Vehicles",
            "subcategory":"Automobile Sales",
            "type":"Retail Goods"
        }
    ],
    "sg:phone":"+1 519 661 0412",
    "sg:postcode":"N6B 1P8",
    "sg:province":"ON",
    "sg:tags":[
        "car",
        "dealer"
    ],
    "wof:name":"Gabie's Auto Sales & Svc",
    "wof:placetype":"venue"
},
  "geometry": {"coordinates":[-81.24188232420001,42.9832763672],"type":"Point"}
}