{
  "type": "Feature",
  "properties": {
    "addr:full":"805 Av Du Mont-Royal E Montreal QC H2J 1W9",
    "addr:postcode":"h2j 1w9",
    "addr:street":"805 Av Du Mont-Royal E",
    "iso:country":"CA",
    "sg:address":"805 Av Du Mont-Royal E",
    "sg:city":"Montreal",
    "sg:classifiers":[
        {
            "category":"Professional",
            "subcategory":"Art Services",
            "type":"Services"
        }
    ],
    "sg:phone":"+1 514 528 6757",
    "sg:postcode":"H2J 1W9",
    "sg:province":"QC",
    "sg:tags":[
        "graphic",
        "designer"
    ],
    "wof:name":"Zeste Graphique Enr",
    "wof:placetype":"venue"
},
  "geometry": {"coordinates":[-73.58107800000001,45.526115],"type":"Point"}
}