{
  "type": "Feature",
  "properties": {
    "addr:full":"Acton Vale QC J0H 1A0",
    "addr:postcode":"j0h 1a0",
    "iso:country":"CA",
    "sg:city":"Acton Vale",
    "sg:classifiers":[
        {
            "category":"Retail",
            "subcategory":"Auto Repair",
            "type":"Services"
        }
    ],
    "sg:phone":"+1 450 549 4352",
    "sg:postcode":"J0H 1A0",
    "sg:province":"QC",
    "sg:tags":[
        "repairing",
        "automobile"
    ],
    "wof:name":"Acton Auto Svc Enrg",
    "wof:placetype":"venue"
},
  "geometry": {"coordinates":[-72.589775,45.644066],"type":"Point"}
}