{
  "type": "Feature",
  "properties": {
    "addr:full":"Lasalle QC H8P 2T7",
    "addr:postcode":"h8p 2t7",
    "iso:country":"CA",
    "sg:city":"Lasalle",
    "sg:classifiers":[
        {
            "category":"Shopping",
            "subcategory":"Musical Instruments",
            "type":"Retail Goods"
        }
    ],
    "sg:phone":"+1 514 368 5540",
    "sg:postcode":"H8P 2T7",
    "sg:province":"QC",
    "sg:tags":[
        "piano"
    ],
    "wof:name":"Accord & Reparation DE Piano",
    "wof:placetype":"venue"
},
  "geometry": {"coordinates":[-73.6628189087,45.4286575317],"type":"Point"}
}