{
  "type": "Feature",
  "properties": {
    "iso:country":"CA",
    "sg:address":"34 Labbe Ave",
    "sg:city":"Blind River",
    "sg:classifiers":[
        {
            "category":"Building & Trades",
            "subcategory":"Construction",
            "type":"Services"
        }
    ],
    "sg:phone":"+1 705 356 2862",
    "sg:postcode":"P0R 1B0",
    "sg:province":"ON",
    "sg:tags":[
        "glass",
        "general",
        "contractor"
    ],
    "wof:name":"R J's Auto Glass & Accessories",
    "wof:placetype":"venue"
},
  "geometry": {"coordinates":[-82.9424133301,46.1845970154],"type":"Point"}
}