{
  "type": "Feature",
  "properties": {
    "iso:country":"CA",
    "sg:city":"Canmore",
    "sg:classifiers":[
        {
            "category":"Manufacturing",
            "subcategory":"Building Materials",
            "type":"Manufacturing & Wholesale Goods"
        }
    ],
    "sg:phone":"+1 403 678 4767",
    "sg:postcode":"T1W 1L2",
    "sg:province":"AB",
    "wof:name":"Canmore Woodcrafters Ltd",
    "wof:placetype":"venue"
},
  "geometry": {"coordinates":[-115.323532105,51.0781555176],"type":"Point"}
}