{
  "type": "Feature",
  "properties": {
    "addr:full":"460 Rue Perreault Saint-Romuald QC G6W 7V6",
    "addr:housenumber":"460",
    "addr:postcode":"g6w 7v6",
    "addr:street":"Rue Perreault",
    "iso:country":"CA",
    "sg:address":"460 Rue Perreault",
    "sg:city":"Saint-Romuald",
    "sg:classifiers":[
        {
            "category":"Building & Trades",
            "subcategory":"Construction",
            "type":"Services"
        }
    ],
    "sg:phone":"+1 418 839 6776",
    "sg:postcode":"G6W 7V6",
    "sg:province":"QC",
    "sg:tags":[
        "insulation",
        "heat",
        "contractor"
    ],
    "wof:name":"Isotex-Pro Intl Inc",
    "wof:placetype":"venue"
},
  "geometry": {"coordinates":[-71.21115112299999,46.761680603],"type":"Point"}
}