{
  "type": "Feature",
  "properties": {
    "addr:full":"15 Petrolia St Guelph ON N1H 2V7",
    "addr:housenumber":"15",
    "addr:postcode":"n1h 2v7",
    "addr:street":"Petrolia St",
    "iso:country":"CA",
    "sg:address":"15 Petrolia St",
    "sg:city":"Guelph",
    "sg:classifiers":[
        {
            "category":"Freight",
            "type":"Transportation"
        }
    ],
    "sg:phone":"+1 905 693 9395",
    "sg:postcode":"N1H 2V7",
    "sg:province":"ON",
    "sg:tags":[
        "mover"
    ],
    "wof:name":"Swan Moving & Storage",
    "wof:placetype":"venue"
},
  "geometry": {"coordinates":[-80.264015,43.536469],"type":"Point"}
}