{
  "type": "Feature",
  "properties": {
    "addr:full":"22326 Mcintosh Ave Maple Ridge BC V2X 3C1",
    "addr:housenumber":"22326",
    "addr:postcode":"v2x 3c1",
    "addr:street":"Mcintosh Ave",
    "iso:country":"CA",
    "sg:address":"22326 Mcintosh Ave",
    "sg:city":"Maple Ridge",
    "sg:classifiers":[
        {
            "category":"Professional",
            "subcategory":"Lawyer & Legal Services",
            "type":"Services"
        }
    ],
    "sg:phone":"+1 604 463 8890",
    "sg:postcode":"V2X 3C1",
    "sg:province":"BC",
    "sg:tags":[
        "attorney"
    ],
    "wof:name":"Cuddeford, R J",
    "wof:placetype":"venue"
},
  "geometry": {"coordinates":[-122.603645,49.219273],"type":"Point"}
}