{
  "type": "Feature",
  "properties": {
    "addr:full":"20 Wellington St Brantford ON N3T 2L4",
    "addr:housenumber":"20",
    "addr:postcode":"n3t 2l4",
    "addr:street":"Wellington St",
    "iso:country":"CA",
    "sg:address":"20 Wellington St",
    "sg:city":"Brantford",
    "sg:classifiers":[
        {
            "category":"Professional",
            "subcategory":"Lawyer & Legal Services",
            "type":"Services"
        }
    ],
    "sg:phone":"+1 519 759 6220",
    "sg:postcode":"N3T 2L4",
    "sg:province":"ON",
    "sg:tags":[
        "attorney"
    ],
    "wof:name":"Quinlan, Peter M",
    "wof:placetype":"venue"
},
  "geometry": {"coordinates":[-80.2669677734,43.1411476135],"type":"Point"}
}