{
  "type": "Feature",
  "properties": {
    "addr:full":"87 Rue Francois-Gauthier Boucherville QC J4B 4N5",
    "addr:housenumber":"87",
    "addr:postcode":"j4b 4n5",
    "addr:street":"Rue Francois-Gauthier",
    "iso:country":"CA",
    "sg:address":"87 Rue Francois-Gauthier",
    "sg:city":"Boucherville",
    "sg:classifiers":[
        {
            "category":"Building & Trades",
            "subcategory":"Electrical",
            "type":"Services"
        }
    ],
    "sg:phone":"+1 450 655 9561",
    "sg:postcode":"J4B 4N5",
    "sg:province":"QC",
    "sg:tags":[
        "electric",
        "contractor"
    ],
    "wof:name":"Services Electrotech Paquin",
    "wof:placetype":"venue"
},
  "geometry": {"coordinates":[-73.4500579834,45.6193618774],"type":"Point"}
}