{
  "type": "Feature",
  "properties": {
    "addr:full":"77 5th Ave NW Moose Jaw SK S6H 3X8",
    "addr:housenumber":"77",
    "addr:postcode":"s6h 3x8",
    "addr:street":"5Th Ave Nw",
    "iso:country":"CA",
    "sg:address":"77 5th Ave NW",
    "sg:city":"Moose Jaw",
    "sg:classifiers":[
        {
            "category":"Home & Garden",
            "subcategory":"Building Materials",
            "type":"Retail Goods"
        }
    ],
    "sg:phone":"+1 306 692 1855",
    "sg:postcode":"S6H 3X8",
    "sg:province":"SK",
    "sg:tags":[
        "mixed",
        "concrete"
    ],
    "wof:name":"Inland Concrete Ltd",
    "wof:placetype":"venue"
},
  "geometry": {"coordinates":[-105.546829,50.39035],"type":"Point"}
}