{
  "type": "Feature",
  "properties": {
    "addr:full":"70 Clementi Lakefield ON K0L 2H0",
    "addr:housenumber":"70",
    "addr:postcode":"k0l 2h0",
    "addr:street":"Clementi Lakefield",
    "iso:country":"CA",
    "sg:address":"70 Clementi",
    "sg:city":"Lakefield",
    "sg:classifiers":[
        {
            "category":"Health Services",
            "subcategory":"Health Practitioner",
            "type":"Services"
        }
    ],
    "sg:phone":"+1 705 652 7860",
    "sg:postcode":"K0L 2H0",
    "sg:province":"ON",
    "sg:tags":[
        "psychotherapist",
        "stress",
        "management"
    ],
    "wof:name":"Evans, Bruce",
    "wof:placetype":"venue"
},
  "geometry": {"coordinates":[-78.276917,44.421669],"type":"Point"}
}