{
  "type": "Feature",
  "properties": {
    "addr:full":"276 Willard Ave Toronto ON M6S 3R2",
    "addr:housenumber":"276",
    "addr:postcode":"m6s 3r2",
    "addr:street":"Willard Ave",
    "iso:country":"CA",
    "sg:address":"276 Willard Ave",
    "sg:city":"Toronto",
    "sg:classifiers":[
        {
            "category":"Health Services",
            "subcategory":"Health Practitioner",
            "type":"Services"
        }
    ],
    "sg:phone":"+1 416 767 6266",
    "sg:postcode":"M6S 3R2",
    "sg:province":"ON",
    "sg:tags":[
        "acupuncture"
    ],
    "wof:name":"Chinese Herb & Health Clinic",
    "wof:placetype":"venue"
},
  "geometry": {"coordinates":[-79.4822921753,43.6507873535],"type":"Point"}
}