{
  "type": "Feature",
  "properties": {
    "iso:country":"CA",
    "sg:address":"1535 Rosslyn Rd",
    "sg:city":"Thunder Bay",
    "sg:classifiers":[
        {
            "category":"Organizations",
            "subcategory":"Membership Organization",
            "type":"Services"
        }
    ],
    "sg:phone":"+1 807 475 8803",
    "sg:postcode":"P7E 6W2",
    "sg:province":"ON",
    "sg:tags":[
        "protection",
        "animal"
    ],
    "wof:name":"Thunder Bay & District Humane",
    "wof:placetype":"venue"
},
  "geometry": {"coordinates":[-89.325874,48.362663],"type":"Point"}
}