{
  "type": "Feature",
  "properties": {
    "iso:country":"CA",
    "sg:address":"16 Oakvale Ave",
    "sg:city":"Ottawa",
    "sg:classifiers":[
        {
            "category":"Building & Trades",
            "subcategory":"Construction",
            "type":"Services"
        }
    ],
    "sg:phone":"+1 613 724 3200",
    "sg:postcode":"K1Y 3S4",
    "sg:province":"ON",
    "sg:tags":[
        "general",
        "contractor"
    ],
    "wof:name":"Sirois & Sons General Contr",
    "wof:placetype":"venue"
},
  "geometry": {"coordinates":[-75.716721,45.399124],"type":"Point"}
}