{
  "type": "Feature",
  "properties": {
    "addr:full":"285 Niagara Blvd Niagara on the Lake ON L0S 1J0",
    "addr:housenumber":"285",
    "addr:postcode":"l0s 1j0",
    "addr:street":"Niagara Blvd;On",
    "iso:country":"CA",
    "sg:address":"285 Niagara Blvd",
    "sg:city":"Niagara on the Lake",
    "sg:classifiers":[
        {
            "category":"Shopping",
            "type":"Retail Goods"
        }
    ],
    "sg:phone":"+1 905 468 2009",
    "sg:postcode":"L0S 1J0",
    "sg:province":"ON",
    "sg:tags":[
        "art",
        "gallery",
        "dealer"
    ],
    "wof:name":"Moggridge Studio",
    "wof:placetype":"venue"
},
  "geometry": {"coordinates":[-79.0886001587,43.2616348267],"type":"Point"}
}