{
  "type": "Feature",
  "properties": {
    "addr:full":"346 Ch Larocque Salaberry-DE-Valleyfield QC J6T 4C3",
    "addr:housenumber":"346",
    "addr:postcode":"j6t 4c3",
    "addr:street":"Ch Larocque",
    "iso:country":"CA",
    "sg:address":"346 Ch Larocque",
    "sg:city":"Salaberry-DE-Valleyfield",
    "sg:classifiers":[
        {
            "category":"Education",
            "subcategory":"School",
            "type":"Public Place"
        }
    ],
    "sg:phone":"+1 450 373 3061",
    "sg:postcode":"J6T 4C3",
    "sg:province":"QC",
    "wof:name":"Dominique-Savio Ecole",
    "wof:placetype":"venue"
},
  "geometry": {"coordinates":[-74.128494,45.244682],"type":"Point"}
}