{
  "type": "Feature",
  "properties": {
    "addr:full":"1401 13E Av Grand-Mere QC G9T 1M1",
    "addr:housenumber":"1401",
    "addr:postcode":"g9t 1m1",
    "addr:street":"13E Av Grand-Mere",
    "iso:country":"CA",
    "sg:address":"1401 13E Av",
    "sg:city":"Grand-Mere",
    "sg:classifiers":[
        {
            "category":"Wholesale",
            "subcategory":"Apparel",
            "type":"Manufacturing & Wholesale Goods"
        }
    ],
    "sg:phone":"+1 819 533 3655",
    "sg:postcode":"G9T 1M1",
    "sg:province":"QC",
    "sg:tags":[
        "shoes"
    ],
    "wof:name":"Agence DE Chaussures Avaro Inc",
    "wof:placetype":"venue"
},
  "geometry": {"coordinates":[-72.707054,46.611698],"type":"Point"}
}