{
  "type": "Feature",
  "properties": {
    "addr:full":"921 343 Rte Saint-Ambroise-DE-Kildare QC J0K 1C0",
    "addr:housenumber":"343",
    "addr:postcode":"j0k 1c0",
    "addr:street":"Rte Saint-Ambroise-De-Kildare",
    "iso:country":"CA",
    "sg:address":"921 343 Rte",
    "sg:city":"Saint-Ambroise-DE-Kildare",
    "sg:classifiers":[
        {
            "category":"Home & Garden",
            "subcategory":"Garden Supply",
            "type":"Retail Goods"
        }
    ],
    "sg:phone":"+1 450 753 9400",
    "sg:postcode":"J0K 1C0",
    "sg:province":"QC",
    "sg:tags":[
        "nurseryman"
    ],
    "wof:name":"Jardins Pepiniere St Ambroise",
    "wof:placetype":"venue"
},
  "geometry": {"coordinates":[-73.55443572999999,46.0767784119],"type":"Point"}
}