{
  "type": "Feature",
  "properties": {
    "addr:full":"523 Richards St Vancouver BC V6B 2Z5",
    "addr:housenumber":"523",
    "addr:postcode":"bc v6b 2z5",
    "addr:street":"Richards St",
    "iso:country":"CA",
    "sg:address":"523 Richards St",
    "sg:city":"Vancouver",
    "sg:classifiers":[
        {
            "category":"Shopping",
            "subcategory":"Music",
            "type":"Retail Goods"
        }
    ],
    "sg:phone":"+1 604 662 3113",
    "sg:postcode":"V6B 2Z5",
    "sg:province":"BC",
    "sg:tags":[
        "compact",
        "record",
        "book",
        "tape",
        "dealer"
    ],
    "wof:name":"Albion Books",
    "wof:placetype":"venue"
},
  "geometry": {"coordinates":[-123.11340300000001,49.283161],"type":"Point"}
}