{
  "type": "Feature",
  "properties": {
    "addr:full":"840 Boul DE L'Ange-Gardien N # 5 L'Assomption QC J5W 1P6",
    "addr:housenumber":"840",
    "addr:postcode":"j5w 1p6",
    "addr:street":"Boul De L'Ange-Gardien N # 5",
    "iso:country":"CA",
    "sg:address":"840 Boul DE L'Ange-Gardien N # 5",
    "sg:city":"L'Assomption",
    "sg:classifiers":[
        {
            "category":"Food & Beverages",
            "subcategory":"Bakery",
            "type":"Retail Goods"
        }
    ],
    "sg:phone":"+1 450 589 6448",
    "sg:postcode":"J5W 1P6",
    "sg:province":"QC",
    "sg:tags":[
        "doughnut"
    ],
    "wof:name":"Tim Hortons",
    "wof:placetype":"venue"
},
  "geometry": {"coordinates":[-73.417587,45.833038],"type":"Point"}
}