{
  "type": "Feature",
  "properties": {
    "addr:full":"7211 96A Ave NW Edmonton AB T6B 1B5",
    "addr:housenumber":"7211",
    "addr:postcode":"t6b 1b5",
    "addr:street":"96A Ave Nw",
    "iso:country":"CA",
    "sg:address":"7211 96A Ave NW",
    "sg:city":"Edmonton",
    "sg:classifiers":[
        {
            "category":"Education",
            "subcategory":"Special Training",
            "type":"Public Place"
        }
    ],
    "sg:phone":"+1 780 469 7382",
    "sg:postcode":"T6B 1B5",
    "sg:province":"AB",
    "sg:tags":[
        "instruction",
        "music"
    ],
    "wof:name":"Society For Talent Education",
    "wof:placetype":"venue"
},
  "geometry": {"coordinates":[-113.439018,53.534744],"type":"Point"}
}