{
  "type": "Feature",
  "properties": {
    "addr:full":"214 Rang DE L'Ile Pierreville QC J0G 1J0",
    "addr:housenumber":"214",
    "addr:postcode":"j0g 1j0",
    "addr:street":"Rang De L'Ile",
    "iso:country":"CA",
    "sg:address":"214 Rang DE L'Ile",
    "sg:city":"Pierreville",
    "sg:classifiers":[
        {
            "category":"Building & Trades",
            "subcategory":"Construction",
            "type":"Services"
        }
    ],
    "sg:phone":"+1 450 568 2806",
    "sg:postcode":"J0G 1J0",
    "sg:province":"QC",
    "sg:tags":[
        "designer",
        "marine",
        "contractor"
    ],
    "wof:name":"Dragage St Maurice Inc",
    "wof:placetype":"venue"
},
  "geometry": {"coordinates":[-72.812782,46.070213],"type":"Point"}
}