{
  "type": "Feature",
  "properties": {
    "addr:full":"5 Main St S Callander ON P0H 1H0",
    "addr:housenumber":"5",
    "addr:postcode":"p0h 1h0",
    "addr:street":"Main St S Callander",
    "iso:country":"CA",
    "sg:address":"5 Main St S",
    "sg:city":"Callander",
    "sg:classifiers":[
        {
            "category":"Bars & Pubs",
            "type":"Food & Drink"
        }
    ],
    "sg:phone":"+1 705 752 3500",
    "sg:postcode":"P0H 1H0",
    "sg:province":"ON",
    "wof:name":"Callander Tavern",
    "wof:placetype":"venue"
},
  "geometry": {"coordinates":[-79.36502838129999,46.2224235535],"type":"Point"}
}