{
  "type": "Feature",
  "properties": {
    "addr:full":"4921 47 St Red Deer AB T4N 1R4",
    "addr:housenumber":"4921",
    "addr:postcode":"t4n 1r4",
    "addr:street":"47 St",
    "iso:country":"CA",
    "sg:address":"4921 47 St",
    "sg:city":"Red Deer",
    "sg:classifiers":[
        {
            "category":"Professional",
            "subcategory":"Accounting & Tax Preparation",
            "type":"Services"
        }
    ],
    "sg:phone":"+1 403 342 5900",
    "sg:postcode":"T4N 1R4",
    "sg:province":"AB",
    "sg:tags":[
        "accountant"
    ],
    "wof:name":"Brown, Gary D CA",
    "wof:placetype":"venue"
},
  "geometry": {"coordinates":[-113.813782,52.266045],"type":"Point"}
}