{
  "type": "Feature",
  "properties": {
    "addr:full":"400 Rue Raymond Gatineau QC J8P 5H4",
    "addr:housenumber":"400",
    "addr:postcode":"j8p 5h4",
    "addr:street":"Rue Raymond",
    "iso:country":"CA",
    "sg:address":"400 Rue Raymond",
    "sg:city":"Gatineau",
    "sg:classifiers":[
        {
            "category":"Organizations",
            "subcategory":"Religious Organization",
            "type":"Services"
        }
    ],
    "sg:phone":"+1 819 663 4240",
    "sg:postcode":"J8P 5H4",
    "sg:province":"QC",
    "sg:tags":[
        "church"
    ],
    "wof:name":"St-Rene Goupil",
    "wof:placetype":"venue"
},
  "geometry": {"coordinates":[-75.65065800000001,45.491634],"type":"Point"}
}