{
  "type": "Feature",
  "properties": {
    "addr:full":"Westlock AB T7P 2E5",
    "addr:postcode":"t7p 2e5",
    "iso:country":"CA",
    "sg:city":"Westlock",
    "sg:classifiers":[
        {
            "category":"Recreation",
            "type":"Entertainment"
        }
    ],
    "sg:phone":"+1 780 349 6677",
    "sg:postcode":"T7P 2E5",
    "sg:province":"AB",
    "sg:tags":[
        "center"
    ],
    "wof:name":"Westlock Recreation Ctr",
    "wof:placetype":"venue"
},
  "geometry": {"coordinates":[-113.84903,54.159679],"type":"Point"}
}