{
  "type": "Feature",
  "properties": {
    "iso:country":"CA",
    "sg:address":"2397 Moxon Rd",
    "sg:city":"Anahim Lake",
    "sg:classifiers":[
        {
            "category":"Recreation",
            "type":"Entertainment"
        }
    ],
    "sg:phone":"+1 250 742 3535",
    "sg:postcode":"V0L 1C0",
    "sg:province":"BC",
    "sg:tags":[
        "guide"
    ],
    "wof:name":"Moose Lake Lodge",
    "wof:placetype":"venue"
},
  "geometry": {"coordinates":[-125.30149078399999,52.4591064453],"type":"Point"}
}