{
  "type": "Feature",
  "properties": {
    "addr:full":"161 Boul Marie-Victorin Kingsey Falls QC J0A 1B0",
    "addr:housenumber":"161",
    "addr:postcode":"j0a 1b0",
    "addr:street":"Boul Marie-Victorin",
    "iso:country":"CA",
    "sg:address":"161 Boul Marie-Victorin",
    "sg:city":"Kingsey Falls",
    "sg:classifiers":[
        {
            "category":"Personal",
            "subcategory":"Beauty Salon",
            "type":"Services"
        }
    ],
    "sg:phone":"+1 819 363 2618",
    "sg:postcode":"J0A 1B0",
    "sg:province":"QC",
    "wof:name":"Salon Nicole",
    "wof:placetype":"venue"
},
  "geometry": {"coordinates":[-72.0799331665,45.8396568298],"type":"Point"}
}