{
  "type": "Feature",
  "properties": {
    "addr:full":"33 Lansdowne Ave Carleton Place ON K7C 3S9",
    "addr:housenumber":"33",
    "addr:postcode":"k7c 3s9",
    "addr:street":"Lansdowne Ave",
    "iso:country":"CA",
    "sg:address":"33 Lansdowne Ave",
    "sg:city":"Carleton Place",
    "sg:classifiers":[
        {
            "category":"Banks & Credit Unions",
            "subcategory":"Bank",
            "type":"Services"
        }
    ],
    "sg:phone":"+1 613 257 1880",
    "sg:postcode":"K7C 3S9",
    "sg:province":"ON",
    "wof:name":"Cibc",
    "wof:placetype":"venue"
},
  "geometry": {"coordinates":[-76.140404,45.13567],"type":"Point"}
}