{
  "type": "Feature",
  "properties": {
    "addr:full":"2210 70 Ave NW Edmonton AB T6P 1N6",
    "addr:housenumber":"2210",
    "addr:postcode":"t6p 1n6",
    "addr:street":"70 Ave Nw",
    "iso:country":"CA",
    "sg:address":"2210 70 Ave NW",
    "sg:city":"Edmonton",
    "sg:classifiers":[
        {
            "category":"Manufacturing",
            "subcategory":"Metals",
            "type":"Manufacturing & Wholesale Goods"
        }
    ],
    "sg:phone":"+1 780 440 1045",
    "sg:postcode":"T6P 1N6",
    "sg:province":"AB",
    "sg:tags":[
        "heat",
        "exchanger"
    ],
    "wof:name":"Alberta Exchanger Ltd",
    "wof:placetype":"venue"
},
  "geometry": {"coordinates":[-113.37685399999999,53.507122],"type":"Point"}
}