{
  "type": "Feature",
  "properties": {
    "addr:full":"640 Mohawk Rd W Hamilton ON L9C 1X6",
    "addr:housenumber":"640",
    "addr:postcode":"l9c 1x6",
    "addr:street":"Mohawk Rd W",
    "iso:country":"CA",
    "sg:address":"640 Mohawk Rd W",
    "sg:city":"Hamilton",
    "sg:classifiers":[
        {
            "category":"Personal",
            "subcategory":"Beauty Salon",
            "type":"Services"
        }
    ],
    "sg:phone":"+1 905 385 2722",
    "sg:postcode":"L9C 1X6",
    "sg:province":"ON",
    "wof:name":"Michael's Hair Design",
    "wof:placetype":"venue"
},
  "geometry": {"coordinates":[-79.9109802246,43.2331848145],"type":"Point"}
}