{
  "type": "Feature",
  "properties": {
    "addr:full":"1332 Clifton St Winnipeg MB R3E 2V2",
    "addr:housenumber":"1332",
    "addr:postcode":"r3e 2v2",
    "addr:street":"Clifton St",
    "iso:country":"CA",
    "sg:address":"1332 Clifton St",
    "sg:city":"Winnipeg",
    "sg:classifiers":[
        {
            "category":"Wholesale",
            "subcategory":"Durable Goods & Equipment",
            "type":"Manufacturing & Wholesale Goods"
        }
    ],
    "sg:phone":"+1 204 774 5464",
    "sg:postcode":"R3E 2V2",
    "sg:province":"MB",
    "sg:tags":[
        "representative",
        "manufacturer"
    ],
    "wof:name":"Wheeler Agencies Ltd",
    "wof:placetype":"venue"
},
  "geometry": {"coordinates":[-97.184769,49.905319],"type":"Point"}
}