{
  "type": "Feature",
  "properties": {
    "iso:country":"CA",
    "sg:city":"Montreal",
    "sg:classifiers":[
        {
            "category":"Shopping",
            "type":"Retail Goods"
        }
    ],
    "sg:phone":"+1 514 271 2343",
    "sg:postcode":"H2V 4G9",
    "sg:province":"QC",
    "sg:tags":[
        "picture",
        "frame"
    ],
    "wof:name":"Galerie Liberto",
    "wof:placetype":"venue"
},
  "geometry": {"coordinates":[-73.647156,45.536121],"type":"Point"}
}