{
  "type": "Feature",
  "properties": {
    "iso:country":"CA",
    "sg:address":"7575 Rte Transcanadienne",
    "sg:city":"Saint-Laurent",
    "sg:classifiers":[
        {
            "category":"Professional",
            "subcategory":"Management & Consulting",
            "type":"Services"
        }
    ],
    "sg:phone":"+1 514 337 4272",
    "sg:postcode":"H4T 1V6",
    "sg:province":"QC",
    "sg:tags":[
        "consultant",
        "business"
    ],
    "wof:name":"Atlantic & Gulf Svc Ltd",
    "wof:placetype":"venue"
},
  "geometry": {"coordinates":[-73.710876,45.489342],"type":"Point"}
}