{
  "type": "Feature",
  "properties": {
    "addr:full":"1100 Mcintosh St Regina SK S4T 5B7",
    "addr:housenumber":"1100",
    "addr:postcode":"s4t 5b7",
    "addr:street":"Mcintosh St",
    "iso:country":"CA",
    "sg:address":"1100 Mcintosh St",
    "sg:city":"Regina",
    "sg:classifiers":[
        {
            "category":"Education",
            "subcategory":"School",
            "type":"Public Place"
        }
    ],
    "sg:phone":"+1 306 791 8360",
    "sg:postcode":"S4T 5B7",
    "sg:province":"SK",
    "wof:name":"Martin Collegiate",
    "wof:placetype":"venue"
},
  "geometry": {"coordinates":[-104.65271799999999,50.461761],"type":"Point"}
}