{
  "type": "Feature",
  "properties": {
    "addr:full":"1300 King St E Oshawa ON L1H 8J4",
    "addr:housenumber":"1300",
    "addr:postcode":"l1h 8j4",
    "addr:street":"King St E",
    "iso:country":"CA",
    "sg:address":"1300 King St E",
    "sg:city":"Oshawa",
    "sg:classifiers":[
        {
            "category":"Building & Trades",
            "subcategory":"Plumbing",
            "type":"Services"
        }
    ],
    "sg:phone":"+1 905 579 0462",
    "sg:postcode":"L1H 8J4",
    "sg:province":"ON",
    "sg:tags":[
        "contractor"
    ],
    "wof:name":"D Gabourie Plumbing",
    "wof:placetype":"venue"
},
  "geometry": {"coordinates":[-78.81547500000001,43.906456],"type":"Point"}
}