{
  "type": "Feature",
  "properties": {
    "addr:full":"Edmonton AB T5M 3Z7",
    "addr:postcode":"t5m 3z7",
    "iso:country":"CA",
    "sg:city":"Edmonton",
    "sg:classifiers":[
        {
            "category":"Food & Beverages",
            "subcategory":"Groceries & Convenience Stores",
            "type":"Retail Goods"
        }
    ],
    "sg:phone":"+1 780 451 9079",
    "sg:postcode":"T5M 3Z7",
    "sg:province":"AB",
    "sg:tags":[
        "grocer"
    ],
    "wof:name":"C & C Store",
    "wof:placetype":"venue"
},
  "geometry": {"coordinates":[-113.56871,53.559082],"type":"Point"}
}