{
  "type": "Feature",
  "properties": {
    "addr:full":"10011 102 St Fort Saskatchewan AB T8L 2C5",
    "addr:housenumber":"10011",
    "addr:postcode":"t8l 2c5",
    "addr:street":"102 St",
    "iso:country":"CA",
    "sg:address":"10011 102 St",
    "sg:city":"Fort Saskatchewan",
    "sg:classifiers":[
        {
            "category":"Education",
            "subcategory":"Library",
            "type":"Public Place"
        }
    ],
    "sg:phone":"+1 780 998 4271",
    "sg:postcode":"T8L 2C5",
    "sg:province":"AB",
    "wof:name":"Fort Saskatchewan Library",
    "wof:placetype":"venue"
},
  "geometry": {"coordinates":[-113.21363067599999,53.7125778198],"type":"Point"}
}