{
  "type": "Feature",
  "properties": {
    "addr:full":"3882 Hwy 14 Upper Rawdon NS B0N 2N0",
    "addr:housenumber":"3882",
    "addr:postcode":"b0n 2n0",
    "addr:street":"Hwy 14",
    "iso:country":"CA",
    "sg:address":"3882 Hwy 14",
    "sg:city":"Upper Rawdon",
    "sg:classifiers":[
        {
            "category":"Government",
            "subcategory":"Post Office",
            "type":"Public Place"
        }
    ],
    "sg:phone":"+1 902 632 2521",
    "sg:postcode":"B0N 2N0",
    "sg:province":"NS",
    "wof:name":"Upper Rawdon Post Office",
    "wof:placetype":"venue"
},
  "geometry": {"coordinates":[-63.678932,45.078259],"type":"Point"}
}