{
  "type": "Feature",
  "properties": {
    "iso:country":"CA",
    "sg:address":"2959 Broadway W",
    "sg:city":"Vancouver",
    "sg:classifiers":[
        {
            "category":"Shopping",
            "type":"Retail Goods"
        }
    ],
    "sg:phone":"+1 604 733 2892",
    "sg:postcode":"V6K 2G9",
    "sg:province":"BC",
    "sg:tags":[
        "cosmetic",
        "perfume"
    ],
    "wof:name":"Pure Radiant Energy Fine Body",
    "wof:placetype":"venue"
},
  "geometry": {"coordinates":[-123.17124939,49.2641792297],"type":"Point"}
}