{
  "type": "Feature",
  "properties": {
    "addr:full":"Delta BC V4G 1K7",
    "addr:postcode":"v4g 1k7",
    "iso:country":"CA",
    "sg:city":"Delta",
    "sg:classifiers":[
        {
            "category":"Wholesale",
            "subcategory":"Machinery & Supplies",
            "type":"Manufacturing & Wholesale Goods"
        }
    ],
    "sg:phone":"+1 604 940 3811",
    "sg:postcode":"V4G 1K7",
    "sg:province":"BC",
    "sg:tags":[
        "equipment",
        "motel",
        "hotel"
    ],
    "wof:name":"Hospitality House of Amenities",
    "wof:placetype":"venue"
},
  "geometry": {"coordinates":[-123.025024,49.135567],"type":"Point"}
}