{
  "type": "Feature",
  "properties": {
    "addr:full":"Stettler AB T0C 2L1",
    "addr:postcode":"t0c 2l1",
    "iso:country":"CA",
    "sg:city":"Stettler",
    "sg:classifiers":[
        {
            "category":"Mining & Drilling",
            "type":"Manufacturing & Wholesale Goods"
        }
    ],
    "sg:phone":"+1 403 742 8965",
    "sg:postcode":"T0C 2L1",
    "sg:province":"AB",
    "sg:tags":[
        "field",
        "oil"
    ],
    "wof:name":"Endeavor E-Line Svc Inc",
    "wof:placetype":"venue"
},
  "geometry": {"coordinates":[-112.687675,52.322323],"type":"Point"}
}