{
  "type": "Feature",
  "properties": {
    "addr:full":"189 Rue Du Prince # 210 Sorel-Tracy QC J3P 4K6",
    "addr:housenumber":"189",
    "addr:postcode":"j3p 4k6",
    "addr:street":"Rue Du Prince # 210",
    "iso:country":"CA",
    "sg:address":"189 Rue Du Prince # 210",
    "sg:city":"Sorel-Tracy",
    "sg:classifiers":[
        {
            "category":"Organizations",
            "subcategory":"Professional Association",
            "type":"Services"
        }
    ],
    "sg:phone":"+1 450 743 2751",
    "sg:postcode":"J3P 4K6",
    "sg:province":"QC",
    "wof:name":"Centre Communautaire N-Dame",
    "wof:placetype":"venue"
},
  "geometry": {"coordinates":[-73.11232757569999,46.0399208069],"type":"Point"}
}