{
  "type": "Feature",
  "properties": {
    "addr:full":"Chicoutimi QC G7H 5B1",
    "addr:postcode":"g7h 5b1",
    "iso:country":"CA",
    "sg:city":"Chicoutimi",
    "sg:classifiers":[
        {
            "category":"Freight",
            "type":"Transportation"
        }
    ],
    "sg:phone":"+1 418 698 4186",
    "sg:postcode":"G7H 5B1",
    "sg:province":"QC",
    "sg:tags":[
        "courier",
        "trucking"
    ],
    "wof:name":"Transport Mc",
    "wof:placetype":"venue"
},
  "geometry": {"coordinates":[-71.10328699999999,48.356228],"type":"Point"}
}