{
  "type": "Feature",
  "properties": {
    "addr:full":"1 Exploration Dr Devon AB T9G 1Z5",
    "addr:housenumber":"1",
    "addr:postcode":"t9g 1z5",
    "addr:street":"Exploration Dr",
    "iso:country":"CA",
    "sg:address":"1 Exploration Dr",
    "sg:city":"Devon",
    "sg:classifiers":[
        {
            "category":"Retail",
            "subcategory":"Veterinary Services",
            "type":"Services"
        }
    ],
    "sg:phone":"+1 780 987 5780",
    "sg:postcode":"T9G 1Z5",
    "sg:province":"AB",
    "sg:tags":[
        "veterinarian"
    ],
    "wof:name":"Devonian Veterinary Svc",
    "wof:placetype":"venue"
},
  "geometry": {"coordinates":[-113.731781,53.343361],"type":"Point"}
}