{
  "type": "Feature",
  "properties": {
    "iso:country":"CA",
    "sg:address":"76 Saulter St",
    "sg:city":"Toronto",
    "sg:classifiers":[
        {
            "category":"Professional",
            "subcategory":"Art Services",
            "type":"Services"
        }
    ],
    "sg:phone":"+1 416 465 7007",
    "sg:postcode":"M4M 2H7",
    "sg:province":"ON",
    "sg:tags":[
        "photographer"
    ],
    "wof:name":"Sheldon Rudner Photography",
    "wof:placetype":"venue"
},
  "geometry": {"coordinates":[-79.3473358154,43.6587371826],"type":"Point"}
}