{
  "type": "Feature",
  "properties": {
    "addr:full":"220 Deercrest Pl SE Calgary AB T2J 5W4",
    "addr:housenumber":"220",
    "addr:postcode":"t2j 5w4",
    "addr:street":"Deercrest Pl Se",
    "iso:country":"CA",
    "sg:address":"220 Deercrest Pl SE",
    "sg:city":"Calgary",
    "sg:classifiers":[
        {
            "category":"Retail",
            "subcategory":"Auto Repair",
            "type":"Services"
        }
    ],
    "sg:phone":"+1 403 278 0155",
    "sg:postcode":"T2J 5W4",
    "sg:province":"AB",
    "sg:tags":[
        "glass",
        "material",
        "coating",
        "tinting"
    ],
    "wof:name":"Suntec Products Inc",
    "wof:placetype":"venue"
},
  "geometry": {"coordinates":[-114.012871,50.925678],"type":"Point"}
}