{
  "type": "Feature",
  "properties": {
    "addr:full":"1191 Sutherland Ave Kelowna BC V1Y 5Y2",
    "addr:housenumber":"1191",
    "addr:postcode":"v1y 5y2",
    "addr:street":"Sutherland Ave",
    "iso:country":"CA",
    "sg:address":"1191 Sutherland Ave",
    "sg:city":"Kelowna",
    "sg:classifiers":[
        {
            "category":"Personal",
            "subcategory":"Barber",
            "type":"Services"
        }
    ],
    "sg:phone":"+1 250 860 0722",
    "sg:postcode":"V1Y 5Y2",
    "sg:province":"BC",
    "wof:name":"Econo Barber Shop",
    "wof:placetype":"venue"
},
  "geometry": {"coordinates":[-119.47423553500001,49.8800010681],"type":"Point"}
}