{
  "type": "Feature",
  "properties": {
    "addr:full":"Enderby BC V0E 1V0",
    "addr:postcode":"v0e 1v0",
    "iso:country":"CA",
    "sg:city":"Enderby",
    "sg:classifiers":[
        {
            "category":"Shopping",
            "subcategory":"Used Merchandise",
            "type":"Retail Goods"
        }
    ],
    "sg:phone":"+1 250 838 6822",
    "sg:postcode":"V0E 1V0",
    "sg:province":"BC",
    "sg:tags":[
        "clothing"
    ],
    "wof:name":"Twice But Nice",
    "wof:placetype":"venue"
},
  "geometry": {"coordinates":[-119.140159607,50.5507011414],"type":"Point"}
}