{
  "type": "Feature",
  "properties": {
    "addr:full":"88 Ch Pelletier Saint-Francois-DE-Madawaska NB E7A 1P1",
    "addr:housenumber":"88",
    "addr:postcode":"e7a 1p1",
    "addr:street":"Ch Pelletier",
    "iso:country":"CA",
    "sg:address":"88 Ch Pelletier",
    "sg:city":"Saint-Francois-DE-Madawaska",
    "sg:classifiers":[
        {
            "category":"Farming",
            "subcategory":"Farm",
            "type":"Manufacturing & Wholesale Goods"
        }
    ],
    "sg:phone":"+1 506 992 3691",
    "sg:postcode":"E7A 1P1",
    "sg:province":"NB",
    "wof:name":"Ouellet, Jean-Paul",
    "wof:placetype":"venue"
},
  "geometry": {"coordinates":[-68.153702,47.634754],"type":"Point"}
}