{
  "type": "Feature",
  "properties": {
    "addr:full":"11735 225 St Maple Ridge BC V2X 6E3",
    "addr:housenumber":"11735",
    "addr:postcode":"v2x 6e3",
    "addr:street":"225 St",
    "iso:country":"CA",
    "sg:address":"11735 225 St",
    "sg:city":"Maple Ridge",
    "sg:classifiers":[
        {
            "category":"Real Estate",
            "subcategory":"Real Estate Operator",
            "type":"Services"
        }
    ],
    "sg:phone":"+1 604 467 9420",
    "sg:postcode":"V2X 6E3",
    "sg:province":"BC",
    "sg:tags":[
        "apartment"
    ],
    "wof:name":"Imperial Apartments",
    "wof:placetype":"venue"
},
  "geometry": {"coordinates":[-122.59910600000001,49.215591],"type":"Point"}
}