{
  "type": "Feature",
  "properties": {
    "addr:full":"87 Ch Hogan Cantley QC J8V 3C2",
    "addr:housenumber":"87",
    "addr:postcode":"j8v 3c2",
    "addr:street":"Ch Hogan",
    "iso:country":"CA",
    "sg:address":"87 Ch Hogan",
    "sg:city":"Cantley",
    "sg:classifiers":[
        {
            "category":"Wholesale",
            "subcategory":"Construction Materials",
            "type":"Manufacturing & Wholesale Goods"
        }
    ],
    "sg:phone":"+1 819 827 9995",
    "sg:postcode":"J8V 3C2",
    "sg:province":"QC",
    "sg:tags":[
        "fence"
    ],
    "wof:name":"Clotures Raymond Monfils",
    "wof:placetype":"venue"
},
  "geometry": {"coordinates":[-75.76939400000001,45.572876],"type":"Point"}
}