{
  "type": "Feature",
  "properties": {
    "addr:full":"Vancouver BC V6A 1T1",
    "addr:postcode":"v6a 1t1",
    "iso:country":"CA",
    "sg:city":"Vancouver",
    "sg:classifiers":[
        {
            "category":"Travel",
            "subcategory":"Travel Agent",
            "type":"Entertainment"
        }
    ],
    "sg:phone":"+1 604 688 7886",
    "sg:postcode":"V6A 1T1",
    "sg:province":"BC",
    "sg:tags":[
        "agency",
        "bureau"
    ],
    "wof:name":"Empress Travel",
    "wof:placetype":"venue"
},
  "geometry": {"coordinates":[-123.104156,49.280365],"type":"Point"}
}