{
  "type": "Feature",
  "properties": {
    "addr:full":"4020 26 Ave SE Calgary AB T2B 0C9",
    "addr:housenumber":"4020",
    "addr:postcode":"t2b 0c9",
    "addr:street":"26 Ave Se",
    "iso:country":"CA",
    "sg:address":"4020 26 Ave SE",
    "sg:city":"Calgary",
    "sg:classifiers":[
        {
            "category":"Organizations",
            "subcategory":"Professional Association",
            "type":"Services"
        }
    ],
    "sg:phone":"+1 403 272 3150",
    "sg:postcode":"T2B 0C9",
    "sg:province":"AB",
    "wof:name":"Forest Lawn Community Assoc",
    "wof:placetype":"venue"
},
  "geometry": {"coordinates":[-113.976349,51.030666],"type":"Point"}
}