{
  "type": "Feature",
  "properties": {
    "addr:full":"2955 Boul Matte Brossard QC J4Y 2P4",
    "addr:housenumber":"2955",
    "addr:postcode":"j4y 2p4",
    "addr:street":"Boul Matte",
    "iso:country":"CA",
    "sg:address":"2955 Boul Matte",
    "sg:city":"Brossard",
    "sg:classifiers":[
        {
            "category":"Building & Trades",
            "subcategory":"Construction",
            "type":"Services"
        }
    ],
    "sg:phone":"+1 450 659 4402",
    "sg:postcode":"J4Y 2P4",
    "sg:province":"QC",
    "sg:tags":[
        "builder",
        "furniture",
        "gazebo",
        "patio",
        "accessory"
    ],
    "wof:name":"Sojag Inc",
    "wof:placetype":"venue"
},
  "geometry": {"coordinates":[-73.47096252439999,45.4330215454],"type":"Point"}
}