{
  "type": "Feature",
  "properties": {
    "addr:full":"Windsor QC J1S 1J2",
    "addr:postcode":"j1s 1j2",
    "iso:country":"CA",
    "sg:city":"Windsor",
    "sg:classifiers":[
        {
            "category":"Health Services",
            "subcategory":"Doctor",
            "type":"Services"
        }
    ],
    "sg:phone":"+1 819 845 4945",
    "sg:postcode":"J1S 1J2",
    "sg:province":"QC",
    "sg:tags":[
        "dentist"
    ],
    "wof:name":"Ctr DE Sante Dentaire Lafrance",
    "wof:placetype":"venue"
},
  "geometry": {"coordinates":[-72.0037994385,45.5699005127],"type":"Point"}
}