{
  "type": "Feature",
  "properties": {
    "addr:full":"295 Broadway Winnipeg MB R3C 0R9",
    "addr:housenumber":"295",
    "addr:postcode":"r3c 0r9",
    "addr:street":"Broadway",
    "iso:country":"CA",
    "sg:address":"295 Broadway",
    "sg:city":"Winnipeg",
    "sg:classifiers":[
        {
            "category":"Professional",
            "subcategory":"Lawyer & Legal Services",
            "type":"Services"
        }
    ],
    "sg:phone":"+1 204 925 2525",
    "sg:postcode":"R3C 0R9",
    "sg:province":"MB",
    "sg:tags":[
        "attorney"
    ],
    "wof:name":"Restall & Restall",
    "wof:placetype":"venue"
},
  "geometry": {"coordinates":[-97.1393356323,49.8880691528],"type":"Point"}
}