{
  "type": "Feature",
  "properties": {
    "addr:full":"11520 2 St NW Edmonton AB T6S 1G1",
    "addr:housenumber":"11520",
    "addr:postcode":"t6s 1g1",
    "addr:street":"2 St Nw",
    "iso:country":"CA",
    "sg:address":"11520 2 St NW",
    "sg:city":"Edmonton",
    "sg:classifiers":[
        {
            "category":"Manufacturing",
            "subcategory":"Motor Vehicles & Parts",
            "type":"Manufacturing & Wholesale Goods"
        }
    ],
    "sg:phone":"+1 780 467 1020",
    "sg:postcode":"T6S 1G1",
    "sg:province":"AB",
    "sg:tags":[
        "body",
        "equipment",
        "truck"
    ],
    "wof:name":"Truck Master Mfg & Equipment",
    "wof:placetype":"venue"
},
  "geometry": {"coordinates":[-113.42420199999999,53.604031],"type":"Point"}
}