{
  "type": "Feature",
  "properties": {
    "addr:full":"400 Deerhurst Dr Brampton ON L6T 5H9",
    "addr:housenumber":"400",
    "addr:postcode":"l6t 5h9",
    "addr:street":"Deerhurst Dr",
    "iso:country":"CA",
    "sg:address":"400 Deerhurst Dr",
    "sg:city":"Brampton",
    "sg:classifiers":[
        {
            "category":"Wholesale",
            "subcategory":"Electrical",
            "type":"Manufacturing & Wholesale Goods"
        }
    ],
    "sg:phone":"+1 905 793 6883",
    "sg:postcode":"L6T 5H9",
    "sg:province":"ON",
    "sg:tags":[
        "discharge",
        "machining"
    ],
    "wof:name":"Precision Cut Inc",
    "wof:placetype":"venue"
},
  "geometry": {"coordinates":[-79.6745223999,43.7486839294],"type":"Point"}
}