{
  "type": "Feature",
  "properties": {
    "addr:full":"2666 Rue Marquette Longueuil QC J4K 4K4",
    "addr:housenumber":"2666",
    "addr:postcode":"j4k 4k4",
    "addr:street":"Rue Marquette",
    "iso:country":"CA",
    "sg:address":"2666 Rue Marquette",
    "sg:city":"Longueuil",
    "sg:classifiers":[
        {
            "category":"Manufacturing",
            "subcategory":"Tools & Machinery",
            "type":"Manufacturing & Wholesale Goods"
        }
    ],
    "sg:phone":"+1 450 442 4741",
    "sg:postcode":"J4K 4K4",
    "sg:province":"QC",
    "sg:tags":[
        "equipment",
        "safety",
        "clothing"
    ],
    "wof:name":"Riendeau Entreprises",
    "wof:placetype":"venue"
},
  "geometry": {"coordinates":[-73.472054,45.512066],"type":"Point"}
}