{
  "type": "Feature",
  "properties": {
    "addr:full":"109 Main St Geraldton ON P0T 1M0",
    "addr:housenumber":"109",
    "addr:postcode":"p0t 1m0",
    "addr:street":"Main St",
    "iso:country":"CA",
    "sg:address":"109 Main St",
    "sg:city":"Geraldton",
    "sg:classifiers":[
        {
            "category":"Banks & Credit Unions",
            "subcategory":"Bank",
            "type":"Services"
        }
    ],
    "sg:phone":"+1 807 854 0691",
    "sg:postcode":"P0T 1M0",
    "sg:province":"ON",
    "wof:name":"Royal Bank Financial Group",
    "wof:placetype":"venue"
},
  "geometry": {"coordinates":[-86.9483413696,49.7260055542],"type":"Point"}
}