{
  "type": "Feature",
  "properties": {
    "addr:full":"228 Bartlett Ave Toronto ON M6H 3G4",
    "addr:housenumber":"228",
    "addr:postcode":"m6h 3g4",
    "addr:street":"Bartlett Ave",
    "iso:country":"CA",
    "sg:address":"228 Bartlett Ave",
    "sg:city":"Toronto",
    "sg:classifiers":[
        {
            "category":"Social Services",
            "subcategory":"Child Care",
            "type":"Services"
        }
    ],
    "sg:phone":"+1 416 533 7337",
    "sg:postcode":"M6H 3G4",
    "sg:province":"ON",
    "wof:name":"Dover Gardens Nursery School",
    "wof:placetype":"venue"
},
  "geometry": {"coordinates":[-79.43575300000001,43.666828],"type":"Point"}
}