{
  "type": "Feature",
  "properties": {
    "addr:full":"Saint-Antonin QC G0L 2J0",
    "addr:postcode":"g0l 2j0",
    "iso:country":"CA",
    "sg:city":"Saint-Antonin",
    "sg:classifiers":[
        {
            "category":"Autos & Motor Vehicles",
            "subcategory":"Motorcycle Sales",
            "type":"Retail Goods"
        }
    ],
    "sg:phone":"+1 418 862 6423",
    "sg:postcode":"G0L 2J0",
    "sg:province":"QC",
    "sg:tags":[
        "parts",
        "snowmobile",
        "accessory"
    ],
    "wof:name":"Bsl Distributions Inc",
    "wof:placetype":"venue"
},
  "geometry": {"coordinates":[-69.47109985349999,47.7999610901],"type":"Point"}
}