{
  "type": "Feature",
  "properties": {
    "addr:full":"102 Booth Rd North Bay ON P1B 8Z4",
    "addr:housenumber":"102",
    "addr:postcode":"p1b 8z4",
    "addr:street":"Booth Rd",
    "iso:country":"CA",
    "sg:address":"102 Booth Rd",
    "sg:city":"North Bay",
    "sg:classifiers":[
        {
            "category":"Retail",
            "subcategory":"Auto Repair",
            "type":"Services"
        }
    ],
    "sg:phone":"+1 705 840 2937",
    "sg:postcode":"P1B 8Z4",
    "sg:province":"ON",
    "sg:tags":[
        "repairing",
        "automobile"
    ],
    "wof:name":"Ayer's Automotive & Accessorie",
    "wof:placetype":"venue"
},
  "geometry": {"coordinates":[-79.4214019775,46.2682304382],"type":"Point"}
}