{
  "type": "Feature",
  "properties": {
    "addr:full":"Grimsby ON L3M 1R4",
    "addr:postcode":"l3m 1r4",
    "iso:country":"CA",
    "sg:city":"Grimsby",
    "sg:classifiers":[
        {
            "category":"Professional",
            "subcategory":"Computer Services",
            "type":"Services"
        }
    ],
    "sg:phone":"+1 905 309 7007",
    "sg:postcode":"L3M 1R4",
    "sg:province":"ON",
    "sg:tags":[
        "equipment",
        "dealer",
        "consultant"
    ],
    "wof:name":"All Areas Computer & Solutions",
    "wof:placetype":"venue"
},
  "geometry": {"coordinates":[-79.561089,43.193501],"type":"Point"}
}