{
  "type": "Feature",
  "properties": {
    "addr:full":"Kanata ON K2L 2T4",
    "addr:postcode":"k2l 2t4",
    "iso:country":"CA",
    "sg:city":"Kanata",
    "sg:classifiers":[
        {
            "category":"Real Estate",
            "subcategory":"Real Estate Operator",
            "type":"Services"
        }
    ],
    "sg:phone":"+1 613 592 1858",
    "sg:postcode":"K2L 2T4",
    "sg:province":"ON",
    "sg:tags":[
        "apartment"
    ],
    "wof:name":"Hungerford Park Apartments",
    "wof:placetype":"venue"
},
  "geometry": {"coordinates":[-75.895980835,45.3024101257],"type":"Point"}
}