{
  "type": "Feature",
  "properties": {
    "addr:full":"Kelowna BC V1Y 2E4",
    "addr:postcode":"v1y 2e4",
    "iso:country":"CA",
    "sg:city":"Kelowna",
    "sg:classifiers":[
        {
            "category":"Professional",
            "subcategory":"Lawyer & Legal Services",
            "type":"Services"
        }
    ],
    "sg:phone":"+1 250 763 6441",
    "sg:postcode":"V1Y 2E4",
    "sg:province":"BC",
    "sg:tags":[
        "attorney"
    ],
    "wof:name":"Wrzesniewski, Joanna E",
    "wof:placetype":"venue"
},
  "geometry": {"coordinates":[-119.491691589,49.8880081177],"type":"Point"}
}