{
  "type": "Feature",
  "properties": {
    "addr:full":"218 3rd Ave W Melville SK S0A 2P0",
    "addr:housenumber":"218",
    "addr:postcode":"s0a 2p0",
    "addr:street":"3Rd Ave W",
    "iso:country":"CA",
    "sg:address":"218 3rd Ave W",
    "sg:city":"Melville",
    "sg:classifiers":[
        {
            "category":"Manufacturing",
            "subcategory":"Printing",
            "type":"Manufacturing & Wholesale Goods"
        }
    ],
    "sg:phone":"+1 306 728 5448",
    "sg:postcode":"S0A 2P0",
    "sg:province":"SK",
    "sg:tags":[
        "newspaper",
        "printer"
    ],
    "wof:name":"Melville Advance Publishing CO",
    "wof:placetype":"venue"
},
  "geometry": {"coordinates":[-102.81609344500001,50.9311256409],"type":"Point"}
}