{
  "type": "Feature",
  "properties": {
    "addr:full":"2473 Dundas St W Toronto ON M6P 1X3",
    "addr:housenumber":"2473",
    "addr:postcode":"m6p 1x3",
    "addr:street":"Dundas St W",
    "iso:country":"CA",
    "sg:address":"2473 Dundas St W",
    "sg:city":"Toronto",
    "sg:classifiers":[
        {
            "category":"Wholesale",
            "subcategory":"Machinery & Supplies",
            "type":"Manufacturing & Wholesale Goods"
        }
    ],
    "sg:phone":"+1 416 533 0993",
    "sg:postcode":"M6P 1X3",
    "sg:province":"ON",
    "sg:tags":[
        "environmental",
        "ecological",
        "carpet",
        "cleaning",
        "rug"
    ],
    "wof:name":"Environmental Mould Specialist",
    "wof:placetype":"venue"
},
  "geometry": {"coordinates":[-79.453742981,43.6596603394],"type":"Point"}
}