{
  "type": "Feature",
  "properties": {
    "addr:full":"Calgary AB T2H 2B8",
    "addr:postcode":"t2h 2b8",
    "iso:country":"CA",
    "sg:city":"Calgary",
    "sg:classifiers":[
        {
            "category":"Professional",
            "subcategory":"Lawyer & Legal Services",
            "type":"Services"
        }
    ],
    "sg:phone":"+1 403 531 0181",
    "sg:postcode":"T2H 2B8",
    "sg:province":"AB",
    "sg:tags":[
        "attorney"
    ],
    "wof:name":"Phipps Law Office",
    "wof:placetype":"venue"
},
  "geometry": {"coordinates":[-114.071250916,50.9834747314],"type":"Point"}
}