{
  "type": "Feature",
  "properties": {
    "addr:full":"157 Water St Campbellton NB E3N 3L4",
    "addr:housenumber":"157",
    "addr:postcode":"e3n 3l4",
    "addr:street":"Water St",
    "iso:country":"CA",
    "sg:address":"157 Water St",
    "sg:city":"Campbellton",
    "sg:classifiers":[
        {
            "category":"Travel",
            "subcategory":"Hotels & Motels",
            "type":"Entertainment"
        }
    ],
    "sg:phone":"+1 506 753 4133",
    "sg:postcode":"E3N 3L4",
    "sg:province":"NB",
    "wof:name":"Howard Johnson Hotel",
    "wof:placetype":"venue"
},
  "geometry": {"coordinates":[-66.675804,48.00666],"type":"Point"}
}