{
  "type": "Feature",
  "properties": {
    "addr:full":"366 Ben Jackson Rd Hantsport NS B0P 1P0",
    "addr:housenumber":"366",
    "addr:postcode":"b0p 1p0",
    "addr:street":"Ben Jackson Rd",
    "iso:country":"CA",
    "sg:address":"366 Ben Jackson Rd",
    "sg:city":"Hantsport",
    "sg:classifiers":[
        {
            "category":"Personal",
            "subcategory":"Beauty Salon",
            "type":"Services"
        }
    ],
    "sg:phone":"+1 902 684 3233",
    "sg:postcode":"B0P 1P0",
    "sg:province":"NS",
    "wof:name":"Your Hair Only Designs",
    "wof:placetype":"venue"
},
  "geometry": {"coordinates":[-64.18389129640001,45.0649223328],"type":"Point"}
}