{
  "type": "Feature",
  "properties": {
    "addr:full":"Vancouver BC V6J 1Z2",
    "addr:postcode":"v6j 1z2",
    "iso:country":"CA",
    "sg:city":"Vancouver",
    "sg:classifiers":[
        {
            "category":"Personal",
            "subcategory":"Beauty Salon",
            "type":"Services"
        }
    ],
    "sg:phone":"+1 604 733 9733",
    "sg:postcode":"V6J 1Z2",
    "sg:province":"BC",
    "sg:tags":[
        "aromatherapy"
    ],
    "wof:name":"Potions & Lotions Enterprises",
    "wof:placetype":"venue"
},
  "geometry": {"coordinates":[-123.149376,49.263653],"type":"Point"}
}