{
  "type": "Feature",
  "properties": {
    "addr:full":"Penticton BC V2A 2E9",
    "addr:postcode":"v2a 2e9",
    "iso:country":"CA",
    "sg:city":"Penticton",
    "sg:classifiers":[
        {
            "category":"Real Estate",
            "subcategory":"Real Estate Operator",
            "type":"Services"
        }
    ],
    "sg:phone":"+1 250 493 1055",
    "sg:postcode":"V2A 2E9",
    "sg:province":"BC",
    "sg:tags":[
        "apartment"
    ],
    "wof:name":"Forestcreek Manor",
    "wof:placetype":"venue"
},
  "geometry": {"coordinates":[-119.57654599999999,49.492603],"type":"Point"}
}