{
  "type": "Feature",
  "properties": {
    "addr:full":"269 Aquaduct Dr Brooks AB T1R 1B3",
    "addr:housenumber":"269",
    "addr:postcode":"t1r 1b3",
    "addr:street":"Aquaduct Dr",
    "iso:country":"CA",
    "sg:address":"269 Aquaduct Dr",
    "sg:city":"Brooks",
    "sg:classifiers":[
        {
            "category":"Mining & Drilling",
            "type":"Manufacturing & Wholesale Goods"
        }
    ],
    "sg:phone":"+1 403 362 2526",
    "sg:postcode":"T1R 1B3",
    "sg:province":"AB",
    "sg:tags":[
        "field",
        "oil"
    ],
    "wof:name":"Pronghorn Controls Ltd",
    "wof:placetype":"venue"
},
  "geometry": {"coordinates":[-111.890548706,50.5583992004],"type":"Point"}
}