{
  "type": "Feature",
  "properties": {
    "addr:full":"Winnipeg MB R3V 1J8",
    "addr:postcode":"r3v 1j8",
    "iso:country":"CA",
    "sg:city":"Winnipeg",
    "sg:classifiers":[
        {
            "category":"Organizations",
            "subcategory":"Religious Organization",
            "type":"Services"
        }
    ],
    "sg:phone":"+1 204 269 3240",
    "sg:postcode":"R3V 1J8",
    "sg:province":"MB",
    "sg:tags":[
        "church"
    ],
    "wof:name":"St Norbert Parish",
    "wof:placetype":"venue"
},
  "geometry": {"coordinates":[-97.1437454224,49.7644004822],"type":"Point"}
}