{
  "type": "Feature",
  "properties": {
    "addr:full":"4 Dundas St E Napanee ON K7R 1H6",
    "addr:housenumber":"4",
    "addr:postcode":"k7r 1h6",
    "addr:street":"Dundas St",
    "iso:country":"CA",
    "sg:address":"4 Dundas St E",
    "sg:city":"Napanee",
    "sg:classifiers":[
        {
            "category":"Banks & Credit Unions",
            "subcategory":"Bank",
            "type":"Services"
        }
    ],
    "sg:phone":"+1 613 354 3327",
    "sg:postcode":"K7R 1H6",
    "sg:province":"ON",
    "wof:name":"Bank of Montreal",
    "wof:placetype":"venue"
},
  "geometry": {"coordinates":[-76.950188,44.247307],"type":"Point"}
}