{
  "type": "Feature",
  "properties": {
    "addr:full":"6675 Av Des Perron Laval QC H7J 1G3",
    "addr:housenumber":"6675",
    "addr:postcode":"h7j 1g3",
    "addr:street":"Av Des Perron",
    "iso:country":"CA",
    "sg:address":"6675 Av Des Perron",
    "sg:city":"Laval",
    "sg:classifiers":[
        {
            "category":"Building & Trades",
            "subcategory":"Landscaping Services",
            "type":"Services"
        }
    ],
    "sg:phone":"+1 450 625 6880",
    "sg:postcode":"H7J 1G3",
    "sg:province":"QC",
    "sg:tags":[
        "center",
        "garden",
        "landscape",
        "contractor"
    ],
    "wof:name":"Serres Beaulieu",
    "wof:placetype":"venue"
},
  "geometry": {"coordinates":[-73.692986,45.652439],"type":"Point"}
}