{
  "type": "Feature",
  "properties": {
    "iso:country":"CA",
    "sg:address":"2331 New St",
    "sg:city":"Burlington",
    "sg:classifiers":[
        {
            "category":"Education",
            "subcategory":"Library",
            "type":"Public Place"
        }
    ],
    "sg:phone":"+1 905 639 3611",
    "sg:postcode":"L7R 1J4",
    "sg:province":"ON",
    "wof:name":"Burlington Public Library",
    "wof:placetype":"venue"
},
  "geometry": {"coordinates":[-79.7891159058,43.3349571228],"type":"Point"}
}