{
  "type": "Feature",
  "properties": {
    "addr:full":"PO Box 841 STN Main North Bay ON P1B 8K1",
    "addr:housenumber":"po",
    "addr:postcode":"p1b 8k1",
    "addr:street":"Box 841 Stn Main",
    "iso:country":"CA",
    "sg:address":"PO Box 841 STN Main",
    "sg:city":"North Bay",
    "sg:classifiers":[
        {
            "category":"Building & Trades",
            "subcategory":"Electrical",
            "type":"Services"
        }
    ],
    "sg:phone":"+1 705 752 4044",
    "sg:postcode":"P1B 8K1",
    "sg:province":"ON",
    "sg:tags":[
        "electric",
        "contractor"
    ],
    "wof:name":"W C Electric",
    "wof:placetype":"venue"
},
  "geometry": {"coordinates":[-79.45993,46.306629],"type":"Point"}
}