{
  "type": "Feature",
  "properties": {
    "addr:full":"Bracebridge ON P1L 1V5",
    "addr:postcode":"p1l 1v5",
    "iso:country":"CA",
    "sg:city":"Bracebridge",
    "sg:classifiers":[
        {
            "category":"Professional",
            "subcategory":"Lawyer & Legal Services",
            "type":"Services"
        }
    ],
    "sg:phone":"+1 705 645 1421",
    "sg:postcode":"P1L 1V5",
    "sg:province":"ON",
    "sg:tags":[
        "attorney"
    ],
    "wof:name":"E Jean Polak Law Office",
    "wof:placetype":"venue"
},
  "geometry": {"coordinates":[-79.310974,45.040615],"type":"Point"}
}