{
  "type": "Feature",
  "properties": {
    "addr:full":"71 1E Av O Amos QC J9T 1T7",
    "addr:housenumber":"71",
    "addr:postcode":"j9t 1t7",
    "addr:street":"1E Av O Amos",
    "iso:country":"CA",
    "sg:address":"71 1E Av O",
    "sg:city":"Amos",
    "sg:classifiers":[
        {
            "category":"Shopping",
            "subcategory":"Gifts & Souvenirs",
            "type":"Retail Goods"
        }
    ],
    "sg:phone":"+1 819 732 9781",
    "sg:postcode":"J9T 1T7",
    "sg:province":"QC",
    "sg:tags":[
        "shop"
    ],
    "wof:name":"Illusion",
    "wof:placetype":"venue"
},
  "geometry": {"coordinates":[-78.114197,48.572052],"type":"Point"}
}