{
  "type": "Feature",
  "properties": {
    "iso:country":"CA",
    "sg:address":"723 Portage Ave",
    "sg:city":"Winnipeg",
    "sg:classifiers":[
        {
            "category":"Education",
            "subcategory":"School",
            "type":"Public Place"
        }
    ],
    "sg:phone":"+1 204 775 8175",
    "sg:postcode":"R3G 0M8",
    "sg:province":"MB",
    "wof:name":"Herzing Career College",
    "wof:placetype":"venue"
},
  "geometry": {"coordinates":[-97.16241455079999,49.8876266479],"type":"Point"}
}