{
  "type": "Feature",
  "properties": {
    "iso:country":"CA",
    "sg:address":"420 Manora Rise NE",
    "sg:city":"Calgary",
    "sg:classifiers":[
        {
            "category":"Professional",
            "subcategory":"Art Services",
            "type":"Services"
        }
    ],
    "sg:phone":"+1 403 248 1611",
    "sg:postcode":"T2A 4S2",
    "sg:province":"AB",
    "sg:tags":[
        "photographer"
    ],
    "wof:name":"Lhc Images",
    "wof:placetype":"venue"
},
  "geometry": {"coordinates":[-113.94670105,51.0646781921],"type":"Point"}
}