{
  "type": "Feature",
  "properties": {
    "addr:full":"3410 St Mary's Rd Winnipeg MB R2N 4E2",
    "addr:housenumber":"3410",
    "addr:postcode":"r2n 4e2",
    "addr:street":"St Mary'S Rd",
    "iso:country":"CA",
    "sg:address":"3410 St Mary's Rd",
    "sg:city":"Winnipeg",
    "sg:classifiers":[
        {
            "category":"Food & Beverages",
            "subcategory":"Specialty",
            "type":"Retail Goods"
        }
    ],
    "sg:phone":"+1 204 257 2715",
    "sg:postcode":"R2N 4E2",
    "sg:province":"MB",
    "sg:tags":[
        "herb",
        "greenhouse"
    ],
    "wof:name":"Sage Gardens Herbs",
    "wof:placetype":"venue"
},
  "geometry": {"coordinates":[-97.12804412840001,49.7609176636],"type":"Point"}
}