{
  "type": "Feature",
  "properties": {
    "addr:full":"Saint-Edouard-DE-Maskinonge QC J0K 2H0",
    "addr:postcode":"j0k 2h0",
    "iso:country":"CA",
    "sg:city":"Saint-Edouard-DE-Maskinonge",
    "sg:classifiers":[
        {
            "category":"Manufacturing",
            "subcategory":"Furniture",
            "type":"Manufacturing & Wholesale Goods"
        }
    ],
    "sg:phone":"+1 819 268 4252",
    "sg:postcode":"J0K 2H0",
    "sg:province":"QC",
    "wof:name":"Techni-Bois Rb",
    "wof:placetype":"venue"
},
  "geometry": {"coordinates":[-73.1453170776,46.3298034668],"type":"Point"}
}