{
  "type": "Feature",
  "properties": {
    "addr:full":"Farm Saskatoon SK S7K 8B7",
    "addr:postcode":"s7k 8b7",
    "addr:street":"Farm",
    "iso:country":"CA",
    "sg:address":"Farm",
    "sg:city":"Saskatoon",
    "sg:classifiers":[
        {
            "category":"Retail",
            "subcategory":"Auto Repair",
            "type":"Services"
        }
    ],
    "sg:phone":"+1 306 242 6644",
    "sg:postcode":"S7K 8B7",
    "sg:province":"SK",
    "sg:tags":[
        "repairing",
        "automobile"
    ],
    "wof:name":"North End Auto Svc",
    "wof:placetype":"venue"
},
  "geometry": {"coordinates":[-106.627578735,52.130859375],"type":"Point"}
}