{
  "type": "Feature",
  "properties": {
    "addr:full":"2593 Kingsway Ave Port Coquitlam BC V3C 1T5",
    "addr:housenumber":"2593",
    "addr:postcode":"v3c 1t5",
    "addr:street":"Kingsway Ave",
    "iso:country":"CA",
    "sg:address":"2593 Kingsway Ave",
    "sg:city":"Port Coquitlam",
    "sg:classifiers":[
        {
            "category":"Building & Trades",
            "subcategory":"Plumbing",
            "type":"Services"
        }
    ],
    "sg:phone":"+1 604 944 2598",
    "sg:postcode":"V3C 1T5",
    "sg:province":"BC",
    "sg:tags":[
        "sheet",
        "work",
        "metal",
        "contractor"
    ],
    "wof:name":"Smith Sheet Metal Works Ltd",
    "wof:placetype":"venue"
},
  "geometry": {"coordinates":[-122.786537,49.265903],"type":"Point"}
}