{
  "type": "Feature",
  "properties": {
    "addr:full":"Hull QC J8Z 1V3",
    "addr:postcode":"j8z 1v3",
    "iso:country":"CA",
    "sg:city":"Hull",
    "sg:classifiers":[
        {
            "category":"Manufacturing",
            "subcategory":"Printing",
            "type":"Manufacturing & Wholesale Goods"
        }
    ],
    "sg:phone":"+1 819 777 1407",
    "sg:postcode":"J8Z 1V3",
    "sg:province":"QC",
    "sg:tags":[
        "printer"
    ],
    "wof:name":"Imprimerie Vincent Ltee",
    "wof:placetype":"venue"
},
  "geometry": {"coordinates":[-75.734489,45.46653],"type":"Point"}
}