{
  "type": "Feature",
  "properties": {
    "addr:full":"2009 Rue Frontenac Montreal QC H2K 2Z2",
    "addr:housenumber":"2009",
    "addr:postcode":"h2k 2z2",
    "addr:street":"Rue Frontenac",
    "iso:country":"CA",
    "sg:address":"2009 Rue Frontenac",
    "sg:city":"Montreal",
    "sg:classifiers":[
        {
            "category":"Personal",
            "subcategory":"Barber",
            "type":"Services"
        }
    ],
    "sg:phone":"+1 514 522 6809",
    "sg:postcode":"H2K 2Z2",
    "sg:province":"QC",
    "wof:name":"Chez Jean-Guy Le Barbier",
    "wof:placetype":"venue"
},
  "geometry": {"coordinates":[-73.5531387329,45.5333175659],"type":"Point"}
}