{
  "type": "Feature",
  "properties": {
    "addr:full":"5804 50 Ave Innisfail AB T4G 1R7",
    "addr:housenumber":"5804",
    "addr:postcode":"t4g 1r7",
    "addr:street":"50 Ave",
    "iso:country":"CA",
    "sg:address":"5804 50 Ave",
    "sg:city":"Innisfail",
    "sg:classifiers":[
        {
            "category":"Organizations",
            "subcategory":"Professional Association",
            "type":"Services"
        }
    ],
    "sg:phone":"+1 403 227 4180",
    "sg:postcode":"T4G 1R7",
    "sg:province":"AB",
    "wof:name":"Dodd Lake Manor",
    "wof:placetype":"venue"
},
  "geometry": {"coordinates":[-113.948928833,52.0326538086],"type":"Point"}
}