{
  "type": "Feature",
  "properties": {
    "addr:full":"Kamloops BC V2C 2N8",
    "addr:postcode":"bc v2c 2n8",
    "iso:country":"CA",
    "sg:city":"Kamloops",
    "sg:classifiers":[
        {
            "category":"Autos & Motor Vehicles",
            "subcategory":"Auto Supplies",
            "type":"Retail Goods"
        }
    ],
    "sg:phone":"+1 250 374 8914",
    "sg:postcode":"V2C 2N8",
    "sg:province":"BC",
    "sg:tags":[
        "repairing",
        "automobile"
    ],
    "wof:name":"Battery Direct",
    "wof:placetype":"venue"
},
  "geometry": {"coordinates":[-120.306861877,50.6732559204],"type":"Point"}
}