{
  "type": "Feature",
  "properties": {
    "addr:full":"316 Barber Cres Saskatoon SK S7M 5K9",
    "addr:housenumber":"316",
    "addr:postcode":"s7m 5k9",
    "addr:street":"Barber Cres",
    "iso:country":"CA",
    "sg:address":"316 Barber Cres",
    "sg:city":"Saskatoon",
    "sg:classifiers":[
        {
            "category":"Home & Garden",
            "subcategory":"Home Furnishings",
            "type":"Retail Goods"
        }
    ],
    "sg:phone":"+1 306 382 1331",
    "sg:postcode":"S7M 5K9",
    "sg:province":"SK",
    "sg:tags":[
        "venetian",
        "blind",
        "made",
        "drapery"
    ],
    "wof:name":"A & V Window Decorations",
    "wof:placetype":"venue"
},
  "geometry": {"coordinates":[-106.73690000000001,52.119076],"type":"Point"}
}