{
  "type": "Feature",
  "properties": {
    "addr:full":"147 Argyle Ave N Listowel ON N4W 1M7",
    "addr:housenumber":"147",
    "addr:postcode":"n4w 1m7",
    "addr:street":"Argyle Ave N",
    "iso:country":"CA",
    "sg:address":"147 Argyle Ave N",
    "sg:city":"Listowel",
    "sg:classifiers":[
        {
            "category":"Health Services",
            "subcategory":"Medical Lab",
            "type":"Services"
        }
    ],
    "sg:phone":"+1 519 291 1234",
    "sg:postcode":"N4W 1M7",
    "sg:province":"ON",
    "wof:name":"Listowel Denture Clinic",
    "wof:placetype":"venue"
},
  "geometry": {"coordinates":[-80.9541931152,43.7325897217],"type":"Point"}
}