{
  "type": "Feature",
  "properties": {
    "addr:full":"106 Main St Unionville ON L3R 2E9",
    "addr:housenumber":"106",
    "addr:postcode":"l3r 2e9",
    "addr:street":"Main St",
    "iso:country":"CA",
    "sg:address":"106 Main St",
    "sg:city":"Unionville",
    "sg:classifiers":[
        {
            "category":"Shopping",
            "subcategory":"Gifts & Souvenirs",
            "type":"Retail Goods"
        }
    ],
    "sg:phone":"+1 905 471 7820",
    "sg:postcode":"L3R 2E9",
    "sg:province":"ON",
    "sg:tags":[
        "shop"
    ],
    "wof:name":"Cornercopia",
    "wof:placetype":"venue"
},
  "geometry": {"coordinates":[-79.3099594116,43.8620452881],"type":"Point"}
}