{
  "type": "Feature",
  "properties": {
    "addr:full":"Strathmore AB T1P 1K1",
    "addr:postcode":"t1p 1k1",
    "iso:country":"CA",
    "sg:city":"Strathmore",
    "sg:classifiers":[
        {
            "category":"Insurance",
            "subcategory":"Insurance Agent",
            "type":"Services"
        }
    ],
    "sg:phone":"+1 403 934 3221",
    "sg:postcode":"T1P 1K1",
    "sg:province":"AB",
    "wof:name":"Coldwell Agencies",
    "wof:placetype":"venue"
},
  "geometry": {"coordinates":[-113.394119,51.043594],"type":"Point"}
}