{
  "type": "Feature",
  "properties": {
    "addr:full":"130 Cawthra Ave Toronto ON M6N 3C2",
    "addr:housenumber":"130",
    "addr:postcode":"m6n 3c2",
    "addr:street":"Cawthra Ave",
    "iso:country":"CA",
    "sg:address":"130 Cawthra Ave",
    "sg:city":"Toronto",
    "sg:classifiers":[
        {
            "category":"Food & Beverages",
            "subcategory":"Bakery",
            "type":"Retail Goods"
        }
    ],
    "sg:phone":"+1 416 767 8367",
    "sg:postcode":"M6N 3C2",
    "sg:province":"ON",
    "sg:tags":[
        "baker"
    ],
    "wof:name":"Central Bakery of Toronto",
    "wof:placetype":"venue"
},
  "geometry": {"coordinates":[-79.4645309448,43.6707763672],"type":"Point"}
}