{
  "type": "Feature",
  "properties": {
    "addr:full":"Oakville ON L6J 7J8",
    "addr:postcode":"l6j 7j8",
    "iso:country":"CA",
    "sg:city":"Oakville",
    "sg:classifiers":[
        {
            "category":"Professional",
            "subcategory":"Management & Consulting",
            "type":"Services"
        }
    ],
    "sg:phone":"+1 905 829 0188",
    "sg:postcode":"L6J 7J8",
    "sg:province":"ON",
    "sg:tags":[
        "consultant",
        "business"
    ],
    "wof:name":"Msx Intl",
    "wof:placetype":"venue"
},
  "geometry": {"coordinates":[-79.66481,43.507473],"type":"Point"}
}