{
  "type": "Feature",
  "properties": {
    "addr:full":"1685 Wilson Ave North York ON M3L 1A5",
    "addr:housenumber":"1685",
    "addr:postcode":"m3l 1a5",
    "addr:street":"Wilson Ave",
    "iso:country":"CA",
    "sg:address":"1685 Wilson Ave",
    "sg:city":"North York",
    "sg:classifiers":[
        {
            "category":"Retail",
            "subcategory":"Auto Repair",
            "type":"Services"
        }
    ],
    "sg:phone":"+1 416 247 6188",
    "sg:postcode":"M3L 1A5",
    "sg:province":"ON",
    "sg:tags":[
        "muffler",
        "exhaust",
        "brake",
        "system"
    ],
    "wof:name":"Speedy Auto Svc",
    "wof:placetype":"venue"
},
  "geometry": {"coordinates":[-79.51644899999999,43.719067],"type":"Point"}
}