{
  "type": "Feature",
  "properties": {
    "iso:country":"CA",
    "sg:address":"84 Morrow Rd",
    "sg:city":"Barrie",
    "sg:classifiers":[
        {
            "category":"Wholesale",
            "subcategory":"Groceries",
            "type":"Manufacturing & Wholesale Goods"
        }
    ],
    "sg:phone":"+1 705 721 7979",
    "sg:postcode":"L4N 3V8",
    "sg:province":"ON",
    "sg:tags":[
        "food",
        "product"
    ],
    "wof:name":"J & J Distributors",
    "wof:placetype":"venue"
},
  "geometry": {"coordinates":[-79.7038574219,44.3630981445],"type":"Point"}
}