{
  "type": "Feature",
  "properties": {
    "addr:full":"2101 Elliot Dr Parkhill ON N0M 2K0",
    "addr:housenumber":"2101",
    "addr:postcode":"n0m 2k0",
    "addr:street":"Elliot Dr",
    "iso:country":"CA",
    "sg:address":"2101 Elliot Dr",
    "sg:city":"Parkhill",
    "sg:classifiers":[
        {
            "category":"Wholesale",
            "subcategory":"Farm Supplies",
            "type":"Manufacturing & Wholesale Goods"
        }
    ],
    "sg:phone":"+1 519 294 6750",
    "sg:postcode":"N0M 2K0",
    "sg:province":"ON",
    "sg:tags":[
        "fertilizer"
    ],
    "wof:name":"Mc Gee Farm Svc Ltd",
    "wof:placetype":"venue"
},
  "geometry": {"coordinates":[-81.69467926030001,43.1544342041],"type":"Point"}
}