{
  "type": "Feature",
  "properties": {
    "addr:full":"123 4th Ave E Assiniboia SK S0H 0B0",
    "addr:housenumber":"123",
    "addr:postcode":"s0h 0b0",
    "addr:street":"4Th Ave E Assiniboia",
    "iso:country":"CA",
    "sg:address":"123 4th Ave E",
    "sg:city":"Assiniboia",
    "sg:classifiers":[
        {
            "category":"Retail",
            "subcategory":"Funeral Services",
            "type":"Services"
        }
    ],
    "sg:phone":"+1 306 642 3373",
    "sg:postcode":"S0H 0B0",
    "sg:province":"SK",
    "sg:tags":[
        "director"
    ],
    "wof:name":"Ross Funeral Svc",
    "wof:placetype":"venue"
},
  "geometry": {"coordinates":[-105.98747253400001,49.6303863525],"type":"Point"}
}