{
  "type": "Feature",
  "properties": {
    "addr:full":"3072 Sunnyhurst Rd North Vancouver BC V7K 2G3",
    "addr:housenumber":"3072",
    "addr:postcode":"v7k 2g3",
    "addr:street":"Sunnyhurst Rd",
    "iso:country":"CA",
    "sg:address":"3072 Sunnyhurst Rd",
    "sg:city":"North Vancouver",
    "sg:classifiers":[
        {
            "category":"Building & Trades",
            "subcategory":"Construction",
            "type":"Services"
        }
    ],
    "sg:phone":"+1 604 986 2434",
    "sg:postcode":"V7K 2G3",
    "sg:province":"BC",
    "sg:tags":[
        "equipment",
        "designer",
        "dealer",
        "pool",
        "swimming"
    ],
    "wof:name":"Select Pool & Spa Svc",
    "wof:placetype":"venue"
},
  "geometry": {"coordinates":[-123.042107,49.337051],"type":"Point"}
}