{
  "type": "Feature",
  "properties": {
    "iso:country":"CA",
    "sg:city":"Jasper",
    "sg:classifiers":[
        {
            "category":"Health Services",
            "subcategory":"Nursing And Care Facility",
            "type":"Services"
        }
    ],
    "sg:phone":"+1 613 283 5471",
    "sg:postcode":"K0G 1G0",
    "sg:province":"ON",
    "sg:tags":[
        "home",
        "convalescent"
    ],
    "wof:name":"Rosebridge Manor",
    "wof:placetype":"venue"
},
  "geometry": {"coordinates":[-75.9413604736,44.8259162903],"type":"Point"}
}