{
  "type": "Feature",
  "properties": {
    "addr:full":"14 Rue Price O Chicoutimi QC G7J 1G3",
    "addr:housenumber":"14",
    "addr:postcode":"g7j 1g3",
    "addr:street":"Rue Price O",
    "iso:country":"CA",
    "sg:address":"14 Rue Price O",
    "sg:city":"Chicoutimi",
    "sg:classifiers":[
        {
            "category":"Restaurant",
            "type":"Food & Drink"
        }
    ],
    "sg:phone":"+1 418 549 6161",
    "sg:postcode":"G7J 1G3",
    "sg:province":"QC",
    "wof:name":"4 Saisons",
    "wof:placetype":"venue"
},
  "geometry": {"coordinates":[-71.068253,48.425266],"type":"Point"}
}