{
  "type": "Feature",
  "properties": {
    "addr:full":"906 Rue Comeau Chicoutimi QC G7J 3J3",
    "addr:housenumber":"906",
    "addr:postcode":"g7j 3j3",
    "addr:street":"Rue Comeau",
    "iso:country":"CA",
    "sg:address":"906 Rue Comeau",
    "sg:city":"Chicoutimi",
    "sg:classifiers":[
        {
            "category":"Education",
            "subcategory":"School",
            "type":"Public Place"
        }
    ],
    "sg:phone":"+1 418 698 5126",
    "sg:postcode":"G7J 3J3",
    "sg:province":"QC",
    "wof:name":"Ecole DE LA Pulperie",
    "wof:placetype":"venue"
},
  "geometry": {"coordinates":[-71.084129,48.416145],"type":"Point"}
}