{
  "type": "Feature",
  "properties": {
    "addr:full":"709 Gauthier Larouche QC G0W 1Z0",
    "addr:housenumber":"709",
    "addr:postcode":"g0w 1z0",
    "addr:street":"Gauthier Larouche",
    "iso:country":"CA",
    "sg:address":"709 Gauthier",
    "sg:city":"Larouche",
    "sg:classifiers":[
        {
            "category":"Utilities",
            "subcategory":"Cable",
            "type":"Services"
        }
    ],
    "sg:phone":"+1 418 695 4648",
    "sg:postcode":"G0W 1Z0",
    "sg:province":"QC",
    "sg:tags":[
        "television"
    ],
    "wof:name":"Television Communautaire",
    "wof:placetype":"venue"
},
  "geometry": {"coordinates":[-71.525291,48.449623],"type":"Point"}
}