{
  "type": "Feature",
  "properties": {
    "addr:full":"465 Second Line E Sault Ste Marie ON P6B 4K2",
    "addr:housenumber":"465",
    "addr:postcode":"p6b 4k2",
    "addr:street":"Second Line E",
    "iso:country":"CA",
    "sg:address":"465 Second Line E",
    "sg:city":"Sault Ste Marie",
    "sg:classifiers":[
        {
            "category":"Manufacturing",
            "subcategory":"Metals",
            "type":"Manufacturing & Wholesale Goods"
        }
    ],
    "sg:phone":"+1 705 254 7182",
    "sg:postcode":"P6B 4K2",
    "sg:province":"ON",
    "sg:tags":[
        "sewer",
        "sign"
    ],
    "wof:name":"Northern Pipe Supply Ltd",
    "wof:placetype":"venue"
},
  "geometry": {"coordinates":[-84.32862091059999,46.5380020142],"type":"Point"}
}