{
  "type": "Feature",
  "properties": {
    "addr:full":"270 Stanford Lake Rd Chester NS B0J 1J0",
    "addr:housenumber":"270",
    "addr:postcode":"b0j 1j0",
    "addr:street":"Stanford Lake Rd",
    "iso:country":"CA",
    "sg:address":"270 Stanford Lake Rd",
    "sg:city":"Chester",
    "sg:classifiers":[
        {
            "category":"Home & Garden",
            "subcategory":"Furniture",
            "type":"Retail Goods"
        }
    ],
    "sg:phone":"+1 902 275 5833",
    "sg:postcode":"B0J 1J0",
    "sg:province":"NS",
    "sg:tags":[
        "builder",
        "custom"
    ],
    "wof:name":"Chester Funiture Ltd",
    "wof:placetype":"venue"
},
  "geometry": {"coordinates":[-64.24443100000001,44.555016],"type":"Point"}
}