{
  "type": "Feature",
  "properties": {
    "addr:full":"Saint-Louis-DE-France QC G8T 1G1",
    "addr:postcode":"g8t 1g1",
    "iso:country":"CA",
    "sg:city":"Saint-Louis-DE-France",
    "sg:classifiers":[
        {
            "category":"Building & Trades",
            "subcategory":"Construction",
            "type":"Services"
        }
    ],
    "sg:phone":"+1 819 376 3138",
    "sg:postcode":"G8T 1G1",
    "sg:province":"QC",
    "sg:tags":[
        "painter"
    ],
    "wof:name":"Peinture Arc-En-Ciel",
    "wof:placetype":"venue"
},
  "geometry": {"coordinates":[-72.585571,46.41732],"type":"Point"}
}