{
  "type": "Feature",
  "properties": {
    "addr:full":"1572 Argyle St Halifax NS B3J 2B3",
    "addr:housenumber":"1572",
    "addr:postcode":"ns b3j 2b3",
    "addr:street":"Argyle St",
    "iso:country":"CA",
    "sg:address":"1572 Argyle St",
    "sg:city":"Halifax",
    "sg:classifiers":[
        {
            "category":"Restaurant",
            "type":"Food & Drink"
        }
    ],
    "sg:phone":"+1 902 425 3039",
    "sg:postcode":"B3J 2B3",
    "sg:province":"NS",
    "wof:name":"Bitter End",
    "wof:placetype":"venue"
},
  "geometry": {"coordinates":[-63.574196,44.645527],"type":"Point"}
}