{
  "type": "Feature",
  "properties": {
    "addr:full":"227 Lake St Pembroke ON K8A 5M2",
    "addr:housenumber":"227",
    "addr:postcode":"k8a 5m2",
    "addr:street":"Lake St",
    "iso:country":"CA",
    "sg:address":"227 Lake St",
    "sg:city":"Pembroke",
    "sg:classifiers":[
        {
            "category":"Health Services",
            "subcategory":"Doctor",
            "type":"Services"
        }
    ],
    "sg:phone":"+1 613 735 1089",
    "sg:postcode":"K8A 5M2",
    "sg:province":"ON",
    "sg:tags":[
        "physician",
        "surgeon"
    ],
    "wof:name":"Coleman, L J MD",
    "wof:placetype":"venue"
},
  "geometry": {"coordinates":[-77.118881,45.825642],"type":"Point"}
}