{
  "type": "Feature",
  "properties": {
    "addr:full":"Calgary AB T2J 0P6",
    "addr:postcode":"t2j 0p6",
    "iso:country":"CA",
    "sg:city":"Calgary",
    "sg:classifiers":[
        {
            "category":"Shopping",
            "subcategory":"Florist",
            "type":"Retail Goods"
        }
    ],
    "sg:phone":"+1 403 258 2526",
    "sg:postcode":"T2J 0P6",
    "sg:province":"AB",
    "wof:name":"Southland Florist",
    "wof:placetype":"venue"
},
  "geometry": {"coordinates":[-114.07185363799999,50.9671783447],"type":"Point"}
}