{
  "type": "Feature",
  "properties": {
    "addr:full":"75 Kenwood Ave York ON M6C 2S1",
    "addr:housenumber":"75",
    "addr:postcode":"m6c 2s1",
    "addr:street":"Kenwood Ave",
    "iso:country":"CA",
    "sg:address":"75 Kenwood Ave",
    "sg:city":"York",
    "sg:classifiers":[
        {
            "category":"Professional",
            "subcategory":"Research",
            "type":"Services"
        }
    ],
    "sg:phone":"+1 416 656 6676",
    "sg:postcode":"M6C 2S1",
    "sg:province":"ON",
    "sg:tags":[
        "computer",
        "ergonomics",
        "software"
    ],
    "wof:name":"Behavioural Team A Corp",
    "wof:placetype":"venue"
},
  "geometry": {"coordinates":[-79.422791,43.684959],"type":"Point"}
}