{
  "type": "Feature",
  "properties": {
    "iso:country":"CA",
    "sg:address":"2193 Shawanaga Trail",
    "sg:city":"Mississauga",
    "sg:classifiers":[
        {
            "category":"Professional",
            "subcategory":"Management & Consulting",
            "type":"Services"
        }
    ],
    "sg:phone":"+1 905 891 1666",
    "sg:postcode":"L5H 3X6",
    "sg:province":"ON",
    "sg:tags":[
        "consultant",
        "business"
    ],
    "wof:name":"Business Resource Group",
    "wof:placetype":"venue"
},
  "geometry": {"coordinates":[-79.634758,43.544628],"type":"Point"}
}