{
  "type": "Feature",
  "properties": {
    "iso:country":"CA",
    "sg:address":"1147 Lawrence Ave W #2",
    "sg:city":"North York",
    "sg:classifiers":[
        {
            "category":"Retail",
            "subcategory":"Auto Repair",
            "type":"Services"
        }
    ],
    "sg:phone":"+1 416 781 9309",
    "sg:postcode":"M6A 1E1",
    "sg:province":"ON",
    "sg:tags":[
        "transmission"
    ],
    "wof:name":"Diamond Transmission Ltd",
    "wof:placetype":"venue"
},
  "geometry": {"coordinates":[-79.4650726318,43.7116737366],"type":"Point"}
}