{
  "type": "Feature",
  "properties": {
    "iso:country":"CA",
    "sg:city":"Winnipeg",
    "sg:classifiers":[
        {
            "category":"Health Services",
            "subcategory":"Doctor",
            "type":"Services"
        }
    ],
    "sg:phone":"+1 204 269 6378",
    "sg:postcode":"R3T 5J9",
    "sg:province":"MB",
    "sg:tags":[
        "dentist"
    ],
    "wof:name":"Chancellor Dental Ctr",
    "wof:placetype":"venue"
},
  "geometry": {"coordinates":[-97.151932,49.815926],"type":"Point"}
}