{
  "type": "Feature",
  "properties": {
    "addr:full":"RR 3 Indian River ON K0L 2B0",
    "addr:postcode":"k0l 2b0",
    "addr:street":"Rr 3",
    "iso:country":"CA",
    "sg:address":"RR 3",
    "sg:city":"Indian River",
    "sg:classifiers":[
        {
            "category":"Building & Trades",
            "subcategory":"Construction",
            "type":"Services"
        }
    ],
    "sg:phone":"+1 705 295 4673",
    "sg:postcode":"K0L 2B0",
    "sg:province":"ON",
    "sg:tags":[
        "home",
        "improvement"
    ],
    "wof:name":"Earl Ivey Construction",
    "wof:placetype":"venue"
},
  "geometry": {"coordinates":[-78.141159,44.34341],"type":"Point"}
}