{
  "type": "Feature",
  "properties": {
    "addr:full":"6 Armstrong Ave Toronto ON M6H 1V8",
    "addr:housenumber":"6",
    "addr:postcode":"m6h 1v8",
    "addr:street":"Armstrong Ave",
    "iso:country":"CA",
    "sg:address":"6 Armstrong Ave",
    "sg:city":"Toronto",
    "sg:classifiers":[
        {
            "category":"Home & Garden",
            "subcategory":"Household Appliances",
            "type":"Retail Goods"
        }
    ],
    "sg:phone":"+1 416 534 7331",
    "sg:postcode":"M6H 1V8",
    "sg:province":"ON",
    "sg:tags":[
        "machine",
        "washing"
    ],
    "wof:name":"Luso Can Appliance Svc",
    "wof:placetype":"venue"
},
  "geometry": {"coordinates":[-79.4381027222,43.664680481],"type":"Point"}
}