{
  "type": "Feature",
  "properties": {
    "iso:country":"CA",
    "sg:address":"1301 Fewster Dr",
    "sg:city":"Mississauga",
    "sg:classifiers":[
        {
            "category":"Building & Trades",
            "subcategory":"Construction",
            "type":"Services"
        }
    ],
    "sg:phone":"+1 905 602 4200",
    "sg:postcode":"L4W 1A2",
    "sg:province":"ON",
    "sg:tags":[
        "general",
        "contractor"
    ],
    "wof:name":"Bcc Contracting",
    "wof:placetype":"venue"
},
  "geometry": {"coordinates":[-79.618309,43.630489],"type":"Point"}
}