{
  "type": "Feature",
  "properties": {
    "addr:full":"200 Main St Antigonish NS B2G 2B9",
    "addr:housenumber":"200",
    "addr:postcode":"b2g 2b9",
    "addr:street":"Main St",
    "iso:country":"CA",
    "sg:address":"200 Main St",
    "sg:city":"Antigonish",
    "sg:classifiers":[
        {
            "category":"Shopping",
            "subcategory":"Clothing, Apparel, & Fashions",
            "type":"Retail Goods"
        }
    ],
    "sg:phone":"+1 902 863 5557",
    "sg:postcode":"B2G 2B9",
    "sg:province":"NS",
    "wof:name":"Pacesetter",
    "wof:placetype":"venue"
},
  "geometry": {"coordinates":[-61.9887962341,45.6228866577],"type":"Point"}
}