{
  "type": "Feature",
  "properties": {
    "addr:full":"3870 Rue Isabelle Brossard QC J4Y 2R3",
    "addr:housenumber":"3870",
    "addr:postcode":"j4y 2r3",
    "addr:street":"Rue Isabelle",
    "iso:country":"CA",
    "sg:address":"3870 Rue Isabelle",
    "sg:city":"Brossard",
    "sg:classifiers":[
        {
            "category":"Wholesale",
            "subcategory":"Groceries",
            "type":"Manufacturing & Wholesale Goods"
        }
    ],
    "sg:phone":"+1 450 444 7337",
    "sg:postcode":"J4Y 2R3",
    "sg:province":"QC",
    "sg:tags":[
        "tea",
        "coffee"
    ],
    "wof:name":"Brulerie Lacoursiere",
    "wof:placetype":"venue"
},
  "geometry": {"coordinates":[-73.4671707153,45.4276809692],"type":"Point"}
}