{
  "type": "Feature",
  "properties": {
    "addr:full":"5516 Main St Osgoode ON K0A 2W0",
    "addr:housenumber":"5516",
    "addr:postcode":"k0a 2w0",
    "addr:street":"Main St",
    "iso:country":"CA",
    "sg:address":"5516 Main St",
    "sg:city":"Osgoode",
    "sg:classifiers":[
        {
            "category":"Restaurant",
            "type":"Food & Drink"
        }
    ],
    "sg:phone":"+1 613 826 0110",
    "sg:postcode":"K0A 2W0",
    "sg:province":"ON",
    "wof:name":"Mr Mozzarella",
    "wof:placetype":"venue"
},
  "geometry": {"coordinates":[-75.60958862299999,45.1444015503],"type":"Point"}
}