{
  "type": "Feature",
  "properties": {
    "addr:full":"Edmonton AB T6H 5C3",
    "addr:postcode":"t6h 5c3",
    "iso:country":"CA",
    "sg:city":"Edmonton",
    "sg:classifiers":[
        {
            "category":"Restaurant",
            "type":"Food & Drink"
        }
    ],
    "sg:phone":"+1 780 435 6796",
    "sg:postcode":"T6H 5C3",
    "sg:province":"AB",
    "wof:name":"Daltons Steak & Seafood Dining",
    "wof:placetype":"venue"
},
  "geometry": {"coordinates":[-113.490371704,53.5462188721],"type":"Point"}
}