{
  "type": "Feature",
  "properties": {
    "addr:full":"5037 50 St # 104 Olds AB T4H 1R8",
    "addr:housenumber":"5037",
    "addr:postcode":"t4h 1r8",
    "addr:street":"50 St # 104",
    "iso:country":"CA",
    "sg:address":"5037 50 St # 104",
    "sg:city":"Olds",
    "sg:classifiers":[
        {
            "category":"Professional",
            "subcategory":"Management & Consulting",
            "type":"Services"
        }
    ],
    "sg:phone":"+1 403 556 8755",
    "sg:postcode":"T4H 1R8",
    "sg:province":"AB",
    "sg:tags":[
        "agricultural",
        "consultant"
    ],
    "wof:name":"Sunmotor International Ltd",
    "wof:placetype":"venue"
},
  "geometry": {"coordinates":[-114.106056,51.792015],"type":"Point"}
}