{
  "type": "Feature",
  "properties": {
    "addr:full":"150 Savannah Oaks Dr Brantford ON N3V 1E7",
    "addr:housenumber":"150",
    "addr:postcode":"n3v 1e7",
    "addr:street":"Savannah Oaks Dr",
    "iso:country":"CA",
    "sg:address":"150 Savannah Oaks Dr",
    "sg:city":"Brantford",
    "sg:classifiers":[
        {
            "category":"Manufacturing",
            "subcategory":"Motor Vehicles & Parts",
            "type":"Manufacturing & Wholesale Goods"
        }
    ],
    "sg:phone":"+1 519 750 0000",
    "sg:postcode":"N3V 1E7",
    "sg:province":"ON",
    "sg:tags":[
        "muffler",
        "exhaust",
        "system"
    ],
    "wof:name":"Wescast Industries Inc",
    "wof:placetype":"venue"
},
  "geometry": {"coordinates":[-80.3351516724,43.1637573242],"type":"Point"}
}