{
  "type": "Feature",
  "properties": {
    "addr:full":"150 219 Rte Hemmingford QC J0L 1H0",
    "addr:housenumber":"219",
    "addr:postcode":"j0l 1h0",
    "addr:street":"Rte",
    "iso:country":"CA",
    "sg:address":"150 219 Rte",
    "sg:city":"Hemmingford",
    "sg:classifiers":[
        {
            "category":"Freight",
            "type":"Transportation"
        }
    ],
    "sg:phone":"+1 450 247 3171",
    "sg:postcode":"J0L 1H0",
    "sg:province":"QC",
    "sg:tags":[
        "trucking"
    ],
    "wof:name":"Menaco Transport Inc",
    "wof:placetype":"venue"
},
  "geometry": {"coordinates":[-73.5807647705,45.0999412537],"type":"Point"}
}