{
  "type": "Feature",
  "properties": {
    "addr:full":"Vanier ON K1L 8H2",
    "addr:postcode":"k1l 8h2",
    "iso:country":"CA",
    "sg:city":"Vanier",
    "sg:classifiers":[
        {
            "category":"Personal",
            "type":"Services"
        }
    ],
    "sg:phone":"+1 613 745 1212",
    "sg:postcode":"K1L 8H2",
    "sg:province":"ON",
    "sg:tags":[
        "counseling",
        "credit",
        "debt",
        "trustee",
        "bankruptcy"
    ],
    "wof:name":"Fontaine & Assoc Inc",
    "wof:placetype":"venue"
},
  "geometry": {"coordinates":[-75.6650924683,45.4346199036],"type":"Point"}
}