{
  "type": "Feature",
  "properties": {
    "addr:full":"4200 Cowley Cres Richmond BC V7B 1B8",
    "addr:housenumber":"4200",
    "addr:postcode":"v7b 1b8",
    "addr:street":"Cowley Cres",
    "iso:country":"CA",
    "sg:address":"4200 Cowley Cres",
    "sg:city":"Richmond",
    "sg:classifiers":[
        {
            "category":"Autos & Motor Vehicles",
            "subcategory":"Automobile Sales",
            "type":"Retail Goods"
        }
    ],
    "sg:phone":"+1 604 278 2105",
    "sg:postcode":"V7B 1B8",
    "sg:province":"BC",
    "sg:tags":[
        "equipment",
        "aircraft",
        "parts",
        "supply"
    ],
    "wof:name":"Pacific Avionics & Instruments",
    "wof:placetype":"venue"
},
  "geometry": {"coordinates":[-123.168274,49.180565],"type":"Point"}
}