{
  "type": "Feature",
  "properties": {
    "addr:full":"3979 Rue Ontario E Montreal QC H1W 1T1",
    "addr:housenumber":"3979",
    "addr:postcode":"h1w 1t1",
    "addr:street":"Rue Ontario E",
    "iso:country":"CA",
    "sg:address":"3979 Rue Ontario E",
    "sg:city":"Montreal",
    "sg:classifiers":[
        {
            "category":"Restaurant",
            "type":"Food & Drink"
        }
    ],
    "sg:phone":"+1 514 525 0939",
    "sg:postcode":"H1W 1T1",
    "sg:province":"QC",
    "sg:tags":[
        "delicatessen"
    ],
    "wof:name":"Gfq",
    "wof:placetype":"venue"
},
  "geometry": {"coordinates":[-73.542084,45.549339],"type":"Point"}
}