{
  "type": "Feature",
  "properties": {
    "iso:country":"CA",
    "sg:address":"996 Main St",
    "sg:city":"Penticton",
    "sg:classifiers":[
        {
            "category":"Organizations",
            "subcategory":"Non-profit Organization",
            "type":"Services"
        }
    ],
    "sg:phone":"+1 250 492 0400",
    "sg:postcode":"V2A 5E4",
    "sg:province":"BC",
    "sg:tags":[
        "info",
        "information",
        "drug",
        "abuse",
        "treatment",
        "addiction",
        "alcoholism"
    ],
    "wof:name":"Pathways Addictions Resource",
    "wof:placetype":"venue"
},
  "geometry": {"coordinates":[-119.587600708,49.4895820618],"type":"Point"}
}