{
  "type": "Feature",
  "properties": {
    "iso:country":"CA",
    "sg:address":"204 Main St",
    "sg:city":"Milk River",
    "sg:classifiers":[
        {
            "category":"Professional",
            "subcategory":"Lawyer & Legal Services",
            "type":"Services"
        }
    ],
    "sg:phone":"+1 403 647 7300",
    "sg:postcode":"T0K 1M0",
    "sg:province":"AB",
    "sg:tags":[
        "attorney"
    ],
    "wof:name":"Millar Thiessen & Keith",
    "wof:placetype":"venue"
},
  "geometry": {"coordinates":[-112.086555481,49.1492424011],"type":"Point"}
}