{
  "type": "Feature",
  "properties": {
    "iso:country":"CA",
    "sg:address":"258 Lake Dalrimple Rd",
    "sg:city":"Sebright",
    "sg:classifiers":[
        {
            "category":"Recreation",
            "type":"Entertainment"
        }
    ],
    "sg:phone":"+1 705 833 1551",
    "sg:postcode":"L0K 1W0",
    "sg:province":"ON",
    "sg:tags":[
        "center"
    ],
    "wof:name":"Carden Recreation Ctr",
    "wof:placetype":"venue"
},
  "geometry": {"coordinates":[-79.163391,44.696003],"type":"Point"}
}