{
  "type": "Feature",
  "properties": {
    "addr:full":"885 Lansdowne St W Peterborough ON K9J 1Z5",
    "addr:housenumber":"885",
    "addr:postcode":"k9j 1z5",
    "addr:street":"Lansdowne St W",
    "iso:country":"CA",
    "sg:address":"885 Lansdowne St W",
    "sg:city":"Peterborough",
    "sg:classifiers":[
        {
            "category":"Retail",
            "subcategory":"Laundry & Dry Cleaning",
            "type":"Services"
        }
    ],
    "sg:phone":"+1 705 742 3831",
    "sg:postcode":"K9J 1Z5",
    "sg:province":"ON",
    "sg:tags":[
        "rental",
        "uniform"
    ],
    "wof:name":"Grainger Uniform Rentals",
    "wof:placetype":"venue"
},
  "geometry": {"coordinates":[-78.340012,44.283138],"type":"Point"}
}