{
  "type": "Feature",
  "properties": {
    "addr:full":"Vernon BC V1T 9G1",
    "addr:postcode":"v1t 9g1",
    "iso:country":"CA",
    "sg:city":"Vernon",
    "sg:classifiers":[
        {
            "category":"Health Services",
            "subcategory":"Health Practitioner",
            "type":"Services"
        }
    ],
    "sg:phone":"+1 250 503 2112",
    "sg:postcode":"V1T 9G1",
    "sg:province":"BC",
    "sg:tags":[
        "physiotherapist"
    ],
    "wof:name":"Kalamalka Physiotherapy Ctr",
    "wof:placetype":"venue"
},
  "geometry": {"coordinates":[-119.26646423299999,50.2390441895],"type":"Point"}
}