{
  "type": "Feature",
  "properties": {
    "addr:full":"3827 39 St Red Deer AB T4N 0Y6",
    "addr:housenumber":"3827",
    "addr:postcode":"t4n 0y6",
    "addr:street":"39 St",
    "iso:country":"CA",
    "sg:address":"3827 39 St",
    "sg:city":"Red Deer",
    "sg:classifiers":[
        {
            "category":"Government",
            "subcategory":"Office",
            "type":"Public Place"
        }
    ],
    "sg:phone":"+1 403 342 8262",
    "sg:postcode":"T4N 0Y6",
    "sg:province":"AB",
    "sg:tags":[
        "village"
    ],
    "wof:name":"Red Deer Cultural Svc",
    "wof:placetype":"venue"
},
  "geometry": {"coordinates":[-113.787071228,52.2592010498],"type":"Point"}
}