{
  "type": "Feature",
  "properties": {
    "addr:full":"227 Main St N Exeter ON N0M 1S3",
    "addr:housenumber":"227",
    "addr:postcode":"n0m 1s3",
    "addr:street":"Main St N",
    "iso:country":"CA",
    "sg:address":"227 Main St N",
    "sg:city":"Exeter",
    "sg:classifiers":[
        {
            "category":"Restaurant",
            "type":"Food & Drink"
        }
    ],
    "sg:phone":"+1 519 235 2424",
    "sg:postcode":"N0M 1S3",
    "sg:province":"ON",
    "wof:name":"Kfc",
    "wof:placetype":"venue"
},
  "geometry": {"coordinates":[-81.483459,43.362392],"type":"Point"}
}