{
  "type": "Feature",
  "properties": {
    "addr:full":"Burlington ON L7L 6M6",
    "addr:postcode":"l7l 6m6",
    "iso:country":"CA",
    "sg:city":"Burlington",
    "sg:classifiers":[
        {
            "category":"Shopping",
            "subcategory":"Tobacco",
            "type":"Retail Goods"
        }
    ],
    "sg:phone":"+1 905 315 8115",
    "sg:postcode":"L7L 6M6",
    "sg:province":"ON",
    "sg:tags":[
        "cigarette",
        "cigar",
        "dealer"
    ],
    "wof:name":"Cigar Etc",
    "wof:placetype":"venue"
},
  "geometry": {"coordinates":[-79.7910308838,43.3941764832],"type":"Point"}
}