{
  "type": "Feature",
  "properties": {
    "iso:country":"CA",
    "sg:city":"St Thomas",
    "sg:classifiers":[
        {
            "category":"Shopping",
            "subcategory":"Pharmacy",
            "type":"Retail Goods"
        }
    ],
    "sg:phone":"+1 519 631 1550",
    "sg:postcode":"N5R 4P5",
    "sg:province":"ON",
    "wof:name":"Health Centre Pharmacy",
    "wof:placetype":"venue"
},
  "geometry": {"coordinates":[-81.1761703491,42.7626724243],"type":"Point"}
}