{
  "type": "Feature",
  "properties": {
    "addr:full":"420 Prince St Imperial SK S0G 2J0",
    "addr:housenumber":"420",
    "addr:postcode":"s0g 2j0",
    "addr:street":"Prince St",
    "iso:country":"CA",
    "sg:address":"420 Prince St",
    "sg:city":"Imperial",
    "sg:classifiers":[
        {
            "category":"Organizations",
            "subcategory":"Religious Organization",
            "type":"Services"
        }
    ],
    "sg:phone":"+1 306 963 2217",
    "sg:postcode":"S0G 2J0",
    "sg:province":"SK",
    "sg:tags":[
        "church"
    ],
    "wof:name":"Pentecostal Church",
    "wof:placetype":"venue"
},
  "geometry": {"coordinates":[-105.440086365,51.344329834],"type":"Point"}
}