{
  "type": "Feature",
  "properties": {
    "addr:full":"Lasalle QC H8R 3H6",
    "addr:postcode":"h8r 3h6",
    "iso:country":"CA",
    "sg:city":"Lasalle",
    "sg:classifiers":[
        {
            "category":"Health Services",
            "subcategory":"Health Practitioner",
            "type":"Services"
        }
    ],
    "sg:phone":"+1 514 367 0597",
    "sg:postcode":"H8R 3H6",
    "sg:province":"QC",
    "sg:tags":[
        "occupational",
        "therapist",
        "rehabilitation"
    ],
    "wof:name":"Maison DE L'Enfance",
    "wof:placetype":"venue"
},
  "geometry": {"coordinates":[-73.646843,45.431919],"type":"Point"}
}