{
  "type": "Feature",
  "properties": {
    "addr:full":"10049 Yonge St Richmond Hill ON L4C 1T7",
    "addr:housenumber":"10049",
    "addr:postcode":"l4c 1t7",
    "addr:street":"Yonge St",
    "iso:country":"CA",
    "sg:address":"10049 Yonge St",
    "sg:city":"Richmond Hill",
    "sg:classifiers":[
        {
            "category":"Health Services",
            "subcategory":"Doctor",
            "type":"Services"
        }
    ],
    "sg:phone":"+1 905 884 1154",
    "sg:postcode":"L4C 1T7",
    "sg:province":"ON",
    "sg:tags":[
        "physician",
        "surgeon"
    ],
    "wof:name":"Kirby, J M MD",
    "wof:placetype":"venue"
},
  "geometry": {"coordinates":[-79.437302,43.872509],"type":"Point"}
}