{
  "type": "Feature",
  "properties": {
    "addr:full":"181 Main St W North Bay ON P1B 2T6",
    "addr:housenumber":"181",
    "addr:postcode":"p1b 2t6",
    "addr:street":"Main St W",
    "iso:country":"CA",
    "sg:address":"181 Main St W",
    "sg:city":"North Bay",
    "sg:classifiers":[
        {
            "category":"Shopping",
            "subcategory":"Hobbies, Toys, & Games",
            "type":"Retail Goods"
        }
    ],
    "sg:phone":"+1 705 472 9832",
    "sg:postcode":"P1B 2T6",
    "sg:province":"ON",
    "wof:name":"Creative Learning",
    "wof:placetype":"venue"
},
  "geometry": {"coordinates":[-79.465462,46.311749],"type":"Point"}
}