{
  "type": "Feature",
  "properties": {
    "addr:full":"Linwood ON N0B 2A0",
    "addr:postcode":"n0b 2a0",
    "iso:country":"CA",
    "sg:city":"Linwood",
    "sg:classifiers":[
        {
            "category":"Organizations",
            "subcategory":"Professional Association",
            "type":"Services"
        }
    ],
    "sg:phone":"+1 519 698 2580",
    "sg:postcode":"N0B 2A0",
    "sg:province":"ON",
    "sg:tags":[
        "club"
    ],
    "wof:name":"Linwood Community Ctr",
    "wof:placetype":"venue"
},
  "geometry": {"coordinates":[-80.7273025513,43.5825843811],"type":"Point"}
}