{
  "type": "Feature",
  "properties": {
    "addr:full":"Saint-Fulgence QC G0V 1S0",
    "addr:postcode":"g0v 1s0",
    "iso:country":"CA",
    "sg:city":"Saint-Fulgence",
    "sg:classifiers":[
        {
            "category":"Building & Trades",
            "subcategory":"Construction",
            "type":"Services"
        }
    ],
    "sg:phone":"+1 418 674 2707",
    "sg:postcode":"G0V 1S0",
    "sg:province":"QC",
    "sg:tags":[
        "excavating",
        "contractor",
        "general"
    ],
    "wof:name":"Construction Norfor Inc",
    "wof:placetype":"venue"
},
  "geometry": {"coordinates":[-70.945831,48.455265],"type":"Point"}
}