{
  "type": "Feature",
  "properties": {
    "addr:full":"1850 Rosser Ave Burnaby BC V5C 5E1",
    "addr:housenumber":"1850",
    "addr:postcode":"v5c 5e1",
    "addr:street":"Rosser Ave",
    "iso:country":"CA",
    "sg:address":"1850 Rosser Ave",
    "sg:city":"Burnaby",
    "sg:classifiers":[
        {
            "category":"Health Services",
            "subcategory":"Nursing And Care Facility",
            "type":"Services"
        }
    ],
    "sg:phone":"+1 604 291 1801",
    "sg:postcode":"V5C 5E1",
    "sg:province":"BC",
    "sg:tags":[
        "home",
        "retirement",
        "community"
    ],
    "wof:name":"Rideau Manor",
    "wof:placetype":"venue"
},
  "geometry": {"coordinates":[-123.00587463399999,49.2677650452],"type":"Point"}
}