{
  "type": "Feature",
  "properties": {
    "addr:full":"Scarborough ON M1X 1L7",
    "addr:postcode":"m1x 1l7",
    "iso:country":"CA",
    "sg:city":"Scarborough",
    "sg:classifiers":[
        {
            "category":"Manufacturing",
            "subcategory":"Printing",
            "type":"Manufacturing & Wholesale Goods"
        }
    ],
    "sg:phone":"+1 416 291 9300",
    "sg:postcode":"M1X 1L7",
    "sg:province":"ON",
    "sg:tags":[
        "bookbinder"
    ],
    "wof:name":"Commercial Bookbinding",
    "wof:placetype":"venue"
},
  "geometry": {"coordinates":[-79.249961853,43.829624176],"type":"Point"}
}