{
  "type": "Feature",
  "properties": {
    "iso:country":"CA",
    "sg:address":"105 Commerce Valley Dr W #20",
    "sg:city":"Thornhill",
    "sg:classifiers":[
        {
            "category":"Restaurant",
            "type":"Food & Drink"
        }
    ],
    "sg:phone":"+1 905 731 6799",
    "sg:postcode":"L3T 7W3",
    "sg:province":"ON",
    "sg:tags":[
        "shop",
        "coffee"
    ],
    "wof:name":"Treats Coffee Emporium",
    "wof:placetype":"venue"
},
  "geometry": {"coordinates":[-79.383308,43.839466],"type":"Point"}
}