{
  "type": "Feature",
  "properties": {
    "addr:full":"151 Thornhill Dr Dartmouth NS B3B 1S2",
    "addr:housenumber":"151",
    "addr:postcode":"b3b 1s2",
    "addr:street":"Thornhill Dr",
    "iso:country":"CA",
    "sg:address":"151 Thornhill Dr",
    "sg:city":"Dartmouth",
    "sg:classifiers":[
        {
            "category":"Manufacturing",
            "subcategory":"Tools & Machinery",
            "type":"Manufacturing & Wholesale Goods"
        }
    ],
    "sg:phone":"+1 902 468 7352",
    "sg:postcode":"B3B 1S2",
    "sg:province":"NS",
    "sg:tags":[
        "equipment",
        "material",
        "handling"
    ],
    "wof:name":"Wajax Industries Ltd",
    "wof:placetype":"venue"
},
  "geometry": {"coordinates":[-63.5923881531,44.6922225952],"type":"Point"}
}