{
  "type": "Feature",
  "properties": {
    "addr:full":"440 28E Av Lachine QC H8S 3Z4",
    "addr:housenumber":"440",
    "addr:postcode":"h8s 3z4",
    "addr:street":"28E Av",
    "iso:country":"CA",
    "sg:address":"440 28E Av",
    "sg:city":"Lachine",
    "sg:classifiers":[
        {
            "category":"Retail",
            "subcategory":"Self-service Laundry",
            "type":"Services"
        }
    ],
    "sg:phone":"+1 514 639 1999",
    "sg:postcode":"H8S 3Z4",
    "sg:province":"QC",
    "wof:name":"Laundromat H20 Et Assoc",
    "wof:placetype":"venue"
},
  "geometry": {"coordinates":[-73.6884384155,45.4368362427],"type":"Point"}
}