{
  "type": "Feature",
  "properties": {
    "addr:full":"35 Highway 638 Bruce Mines ON P0R 1C0",
    "addr:housenumber":"35",
    "addr:postcode":"p0r 1c0",
    "addr:street":"Highway 638",
    "iso:country":"CA",
    "sg:address":"35 Highway 638",
    "sg:city":"Bruce Mines",
    "sg:classifiers":[
        {
            "category":"Arena",
            "subcategory":"Sports Club",
            "type":"Entertainment"
        }
    ],
    "sg:phone":"+1 705 785 3791",
    "sg:postcode":"P0R 1C0",
    "sg:province":"ON",
    "sg:tags":[
        "athletic",
        "fields",
        "stadium",
        "government"
    ],
    "wof:name":"Plummer Central Algoma",
    "wof:placetype":"venue"
},
  "geometry": {"coordinates":[-83.794144,46.300209],"type":"Point"}
}