{
  "type": "Feature",
  "properties": {
    "addr:full":"1108 Maplegate Rd Pickering ON L1X 1B8",
    "addr:housenumber":"1108",
    "addr:postcode":"l1x 1b8",
    "addr:street":"Maplegate Rd",
    "iso:country":"CA",
    "sg:address":"1108 Maplegate Rd",
    "sg:city":"Pickering",
    "sg:classifiers":[
        {
            "category":"Building & Trades",
            "subcategory":"Landscaping Services",
            "type":"Services"
        }
    ],
    "sg:phone":"+1 905 420 2962",
    "sg:postcode":"L1X 1B8",
    "sg:province":"ON",
    "sg:tags":[
        "landscape",
        "contractor"
    ],
    "wof:name":"Breezewood Landscaping & Dsgn",
    "wof:placetype":"venue"
},
  "geometry": {"coordinates":[-79.103539,43.847446],"type":"Point"}
}