{
  "type": "Feature",
  "properties": {
    "addr:full":"866 Eglinton Ave E East York ON M4G 2L1",
    "addr:housenumber":"866",
    "addr:postcode":"m4g 2l1",
    "addr:street":"Eglinton Ave E",
    "iso:country":"CA",
    "sg:address":"866 Eglinton Ave E",
    "sg:city":"East York",
    "sg:classifiers":[
        {
            "category":"Restaurant",
            "type":"Food & Drink"
        }
    ],
    "sg:phone":"+1 416 423 3004",
    "sg:postcode":"M4G 2L1",
    "sg:province":"ON",
    "wof:name":"Eglinton Fish & Chips",
    "wof:placetype":"venue"
},
  "geometry": {"coordinates":[-79.365303,43.713623],"type":"Point"}
}