{
  "type": "Feature",
  "properties": {
    "addr:full":"1706 Francis St Regina SK S4N 6H1",
    "addr:housenumber":"1706",
    "addr:postcode":"s4n 6h1",
    "addr:street":"Francis St",
    "iso:country":"CA",
    "sg:address":"1706 Francis St",
    "sg:city":"Regina",
    "sg:classifiers":[
        {
            "category":"Retail",
            "subcategory":"Auto Repair",
            "type":"Services"
        }
    ],
    "sg:phone":"+1 306 949 0444",
    "sg:postcode":"S4N 6H1",
    "sg:province":"SK",
    "sg:tags":[
        "wrecker"
    ],
    "wof:name":"Big Rig Towing Inc",
    "wof:placetype":"venue"
},
  "geometry": {"coordinates":[-104.57944500000001,50.451672],"type":"Point"}
}