{
  "type": "Feature",
  "properties": {
    "addr:full":"398 King St E Kitchener ON N2G 2L5",
    "addr:housenumber":"398",
    "addr:postcode":"n2g 2l5",
    "addr:street":"King St E",
    "iso:country":"CA",
    "sg:address":"398 King St E",
    "sg:city":"Kitchener",
    "sg:classifiers":[
        {
            "category":"Personal",
            "subcategory":"Tattoo Parlor",
            "type":"Services"
        }
    ],
    "sg:phone":"+1 519 742 1020",
    "sg:postcode":"N2G 2L5",
    "sg:province":"ON",
    "sg:tags":[
        "tattooing"
    ],
    "wof:name":"Exotic Skin Shop",
    "wof:placetype":"venue"
},
  "geometry": {"coordinates":[-80.4828109741,43.4471130371],"type":"Point"}
}