{
  "type": "Feature",
  "properties": {
    "addr:full":"120 Main St Cudworth SK S0K 1B0",
    "addr:housenumber":"120",
    "addr:postcode":"s0k 1b0",
    "addr:street":"Main St",
    "iso:country":"CA",
    "sg:address":"120 Main St",
    "sg:city":"Cudworth",
    "sg:classifiers":[
        {
            "category":"Retail",
            "subcategory":"Auto Repair",
            "type":"Services"
        }
    ],
    "sg:phone":"+1 306 256 3342",
    "sg:postcode":"S0K 1B0",
    "sg:province":"SK",
    "sg:tags":[
        "repairing",
        "automobile"
    ],
    "wof:name":"Heritage Service",
    "wof:placetype":"venue"
},
  "geometry": {"coordinates":[-105.733291626,52.4929008484],"type":"Point"}
}