{
  "type": "Feature",
  "properties": {
    "addr:full":"3627 Boul Des Sources Dollard-Des-Ormeaux QC H9B 2K4",
    "addr:housenumber":"3627",
    "addr:postcode":"h9b 2k4",
    "addr:street":"Boul Des Sources",
    "iso:country":"CA",
    "sg:address":"3627 Boul Des Sources",
    "sg:city":"Dollard-Des-Ormeaux",
    "sg:classifiers":[
        {
            "category":"Banks & Credit Unions",
            "subcategory":"Bank",
            "type":"Services"
        }
    ],
    "sg:phone":"+1 514 684 5670",
    "sg:postcode":"H9B 2K4",
    "sg:province":"QC",
    "wof:name":"Banque Nationale Du Canada",
    "wof:placetype":"venue"
},
  "geometry": {"coordinates":[-73.8008804321,45.4885826111],"type":"Point"}
}