{
  "type": "Feature",
  "properties": {
    "iso:country":"CA",
    "sg:address":"3627 Boul Des Sources",
    "sg:city":"Dollard-Des-Ormeaux",
    "sg:classifiers":[
        {
            "category":"Banks & Credit Unions",
            "subcategory":"Bank",
            "type":"Services"
        }
    ],
    "sg:phone":"+1 514 684 5670",
    "sg:postcode":"H9B 2K4",
    "sg:province":"QC",
    "wof:name":"Banque Nationale Du Canada",
    "wof:placetype":"venue"
},
  "geometry": {"coordinates":[-73.8008804321,45.4885826111],"type":"Point"}
}