{
  "type": "Feature",
  "properties": {
    "addr:full":"553 1E Rue O Amos QC J9T 2M9",
    "addr:housenumber":"553",
    "addr:postcode":"j9t 2m9",
    "addr:street":"1E Rue O Amos",
    "iso:country":"CA",
    "sg:address":"553 1E Rue O",
    "sg:city":"Amos",
    "sg:classifiers":[
        {
            "category":"Health Services",
            "subcategory":"Doctor",
            "type":"Services"
        }
    ],
    "sg:phone":"+1 819 732 6066",
    "sg:postcode":"J9T 2M9",
    "sg:province":"QC",
    "sg:tags":[
        "physician",
        "surgeon"
    ],
    "wof:name":"Adam, Robert MD",
    "wof:placetype":"venue"
},
  "geometry": {"coordinates":[-78.11126708979999,48.5624160767],"type":"Point"}
}