{
  "type": "Feature",
  "properties": {
    "addr:full":"51 Mill St E Tilbury ON N0P 2L0",
    "addr:housenumber":"51",
    "addr:postcode":"n0p 2l0",
    "addr:street":"Mill St",
    "iso:country":"CA",
    "sg:address":"51 Mill St E",
    "sg:city":"Tilbury",
    "sg:classifiers":[
        {
            "category":"Freight",
            "type":"Transportation"
        }
    ],
    "sg:phone":"+1 519 682 2694",
    "sg:postcode":"N0P 2L0",
    "sg:province":"ON",
    "sg:tags":[
        "trucking"
    ],
    "wof:name":"Rene Blain Trucking Ltd",
    "wof:placetype":"venue"
},
  "geometry": {"coordinates":[-82.422646,42.264969],"type":"Point"}
}