{
  "type": "Feature",
  "properties": {
    "addr:full":"880 Goyeau St Windsor ON N9A 1H8",
    "addr:housenumber":"880",
    "addr:postcode":"n9a 1h8",
    "addr:street":"Goyeau St",
    "iso:country":"CA",
    "sg:address":"880 Goyeau St",
    "sg:city":"Windsor",
    "sg:classifiers":[
        {
            "category":"Shopping",
            "subcategory":"Pharmacy",
            "type":"Retail Goods"
        }
    ],
    "sg:phone":"+1 519 256 7006",
    "sg:postcode":"N9A 1H8",
    "sg:province":"ON",
    "wof:name":"Drug Basics",
    "wof:placetype":"venue"
},
  "geometry": {"coordinates":[-83.03254699999999,42.311302],"type":"Point"}
}