{
  "type": "Feature",
  "properties": {
    "iso:country":"CA",
    "sg:address":"855 Rue Richelieu",
    "sg:city":"LA Malbaie",
    "sg:classifiers":[
        {
            "category":"Education",
            "subcategory":"College",
            "type":"Public Place"
        }
    ],
    "sg:phone":"+1 418 665 6606",
    "sg:postcode":"G5A 2X7",
    "sg:province":"QC",
    "sg:tags":[
        "academic",
        "school"
    ],
    "wof:name":"Centre D'Etudes Collegiales",
    "wof:placetype":"venue"
},
  "geometry": {"coordinates":[-70.1430511475,47.6332778931],"type":"Point"}
}