{
  "type": "Feature",
  "properties": {
    "addr:full":"2640 Boul Lapiniere Brossard QC J4Z 2M3",
    "addr:housenumber":"2640",
    "addr:postcode":"j4z 2m3",
    "addr:street":"Boul Lapiniere",
    "iso:country":"CA",
    "sg:address":"2640 Boul Lapiniere",
    "sg:city":"Brossard",
    "sg:classifiers":[
        {
            "category":"Shopping",
            "subcategory":"Bicycles & Sporting Goods",
            "type":"Retail Goods"
        }
    ],
    "sg:phone":"+1 450 678 5880",
    "sg:postcode":"J4Z 2M3",
    "sg:province":"QC",
    "wof:name":"Neron Sports Inc",
    "wof:placetype":"venue"
},
  "geometry": {"coordinates":[-73.46156311039999,45.4676856995],"type":"Point"}
}