{
  "type": "Feature",
  "properties": {
    "addr:full":"3119 Rue Masson Montreal QC H1Y 1X9",
    "addr:housenumber":"3119",
    "addr:postcode":"h1y 1x9",
    "addr:street":"Rue Masson",
    "iso:country":"CA",
    "sg:address":"3119 Rue Masson",
    "sg:city":"Montreal",
    "sg:classifiers":[
        {
            "category":"Restaurant",
            "type":"Food & Drink"
        }
    ],
    "sg:phone":"+1 514 729 3777",
    "sg:postcode":"H1Y 1X9",
    "sg:province":"QC",
    "sg:tags":[
        "shop",
        "coffee"
    ],
    "wof:name":"Cafe Lezard",
    "wof:placetype":"venue"
},
  "geometry": {"coordinates":[-73.57421100000001,45.549538],"type":"Point"}
}