{
  "type": "Feature",
  "properties": {
    "addr:full":"22380 Lougheed Hwy Maple Ridge BC V2X 2T4",
    "addr:housenumber":"22380",
    "addr:postcode":"v2x 2t4",
    "addr:street":"Lougheed Hwy",
    "iso:country":"CA",
    "sg:address":"22380 Lougheed Hwy",
    "sg:city":"Maple Ridge",
    "sg:classifiers":[
        {
            "category":"Real Estate",
            "subcategory":"Architect",
            "type":"Services"
        }
    ],
    "sg:phone":"+1 604 467 4724",
    "sg:postcode":"V2X 2T4",
    "sg:province":"BC",
    "sg:tags":[
        "home",
        "planning"
    ],
    "wof:name":"Davenport Design Group Ltd",
    "wof:placetype":"venue"
},
  "geometry": {"coordinates":[-122.602295,49.216751],"type":"Point"}
}