{
  "type": "Feature",
  "properties": {
    "addr:full":"1010 Point Abino Rd S Ridgeway ON L0S 1N0",
    "addr:housenumber":"1010",
    "addr:postcode":"l0s 1n0",
    "addr:street":"Point Abino Rd",
    "iso:country":"CA",
    "sg:address":"1010 Point Abino Rd S",
    "sg:city":"Ridgeway",
    "sg:classifiers":[
        {
            "category":"Organizations",
            "subcategory":"Professional Association",
            "type":"Services"
        }
    ],
    "sg:phone":"+1 905 894 3223",
    "sg:postcode":"L0S 1N0",
    "sg:province":"ON",
    "sg:tags":[
        "club"
    ],
    "wof:name":"Bertie Boating Club",
    "wof:placetype":"venue"
},
  "geometry": {"coordinates":[-79.051811,42.878105],"type":"Point"}
}