{
  "type": "Feature",
  "properties": {
    "addr:full":"8075 Old Waneta Rd Trail BC V1R 4X1",
    "addr:housenumber":"8075",
    "addr:postcode":"bc v1r 4x1",
    "addr:street":"Old Waneta Rd Trail",
    "iso:country":"CA",
    "sg:address":"8075 Old Waneta Rd",
    "sg:city":"Trail",
    "sg:classifiers":[
        {
            "category":"Wholesale",
            "subcategory":"Fruits & Vegetables",
            "type":"Manufacturing & Wholesale Goods"
        }
    ],
    "sg:phone":"+1 250 368 5518",
    "sg:postcode":"V1R 4X1",
    "sg:province":"BC",
    "wof:name":"F & W Wholesale Ltd",
    "wof:placetype":"venue"
},
  "geometry": {"coordinates":[-117.63750457800001,49.089630127],"type":"Point"}
}