{
  "type": "Feature",
  "properties": {
    "addr:full":"151 Ontario St N Kitchener ON N2H 4Y5",
    "addr:housenumber":"151",
    "addr:postcode":"n2h 4y5",
    "addr:street":"Ontario St N",
    "iso:country":"CA",
    "sg:address":"151 Ontario St N",
    "sg:city":"Kitchener",
    "sg:classifiers":[
        {
            "category":"Insurance",
            "subcategory":"Insurance Agent",
            "type":"Services"
        }
    ],
    "sg:phone":"+1 519 743 6303",
    "sg:postcode":"N2H 4Y5",
    "sg:province":"ON",
    "wof:name":"Wong, Simon",
    "wof:placetype":"venue"
},
  "geometry": {"coordinates":[-80.4890213013,43.4519538879],"type":"Point"}
}