{
  "type": "Feature",
  "properties": {
    "addr:full":"481 Gibb St Oshawa ON L1J 1Z4",
    "addr:housenumber":"481",
    "addr:postcode":"l1j 1z4",
    "addr:street":"Gibb St",
    "iso:country":"CA",
    "sg:address":"481 Gibb St",
    "sg:city":"Oshawa",
    "sg:classifiers":[
        {
            "category":"Retail",
            "subcategory":"Laundry & Dry Cleaning",
            "type":"Services"
        }
    ],
    "sg:phone":"+1 905 743 0406",
    "sg:postcode":"L1J 1Z4",
    "sg:province":"ON",
    "sg:tags":[
        "cleaners"
    ],
    "wof:name":"Dry Cleaner",
    "wof:placetype":"venue"
},
  "geometry": {"coordinates":[-78.879097,43.886162],"type":"Point"}
}