{
  "type": "Feature",
  "properties": {
    "addr:full":"1400 Norman St Timmins ON P4N 8R2",
    "addr:housenumber":"1400",
    "addr:postcode":"p4n 8r2",
    "addr:street":"Norman St",
    "iso:country":"CA",
    "sg:address":"1400 Norman St",
    "sg:city":"Timmins",
    "sg:classifiers":[
        {
            "category":"Building & Trades",
            "subcategory":"Construction",
            "type":"Services"
        }
    ],
    "sg:phone":"+1 705 267 7208",
    "sg:postcode":"P4N 8R2",
    "sg:province":"ON",
    "sg:tags":[
        "excavating",
        "contractor",
        "general"
    ],
    "wof:name":"Kapel's Backhoe",
    "wof:placetype":"venue"
},
  "geometry": {"coordinates":[-81.35669708250001,48.4840278625],"type":"Point"}
}