{
  "type": "Feature",
  "properties": {
    "addr:full":"878 Bethany Hills Rd Bethany ON L0A 1A0",
    "addr:housenumber":"878",
    "addr:postcode":"l0a 1a0",
    "addr:street":"Bethany Hills Rd",
    "iso:country":"CA",
    "sg:address":"878 Bethany Hills Rd",
    "sg:city":"Bethany",
    "sg:classifiers":[
        {
            "category":"Travel",
            "subcategory":"Hotels & Motels",
            "type":"Entertainment"
        }
    ],
    "sg:phone":"+1 705 277 2012",
    "sg:postcode":"L0A 1A0",
    "sg:province":"ON",
    "sg:tags":[
        "resort",
        "center",
        "skiing"
    ],
    "wof:name":"Devil's Elbow Ski Area",
    "wof:placetype":"venue"
},
  "geometry": {"coordinates":[-78.566734314,44.1828651428],"type":"Point"}
}