{
  "type": "Feature",
  "properties": {
    "addr:full":"Edmonton AB T6E 6M3",
    "addr:postcode":"t6e 6m3",
    "iso:country":"CA",
    "sg:city":"Edmonton",
    "sg:classifiers":[
        {
            "category":"Home & Garden",
            "subcategory":"Home Furnishings",
            "type":"Retail Goods"
        }
    ],
    "sg:phone":"+1 780 430 8241",
    "sg:postcode":"T6E 6M3",
    "sg:province":"AB",
    "sg:tags":[
        "curtain",
        "made",
        "drapery"
    ],
    "wof:name":"Econo Window Fashions",
    "wof:placetype":"venue"
},
  "geometry": {"coordinates":[-113.48194100000001,53.47438],"type":"Point"}
}