{
  "type": "Feature",
  "properties": {
    "addr:full":"3050 Yonge St Toronto ON M4N 2K4",
    "addr:housenumber":"3050",
    "addr:postcode":"m4n 2k4",
    "addr:street":"Yonge St",
    "iso:country":"CA",
    "sg:address":"3050 Yonge St",
    "sg:city":"Toronto",
    "sg:classifiers":[
        {
            "category":"Food & Beverages",
            "subcategory":"Bakery",
            "type":"Retail Goods"
        }
    ],
    "sg:phone":"+1 416 486 5037",
    "sg:postcode":"M4N 2K4",
    "sg:province":"ON",
    "sg:tags":[
        "doughnut"
    ],
    "wof:name":"Coffee Time Donuts",
    "wof:placetype":"venue"
},
  "geometry": {"coordinates":[-79.4023513794,43.7249336243],"type":"Point"}
}