{
  "type": "Feature",
  "properties": {
    "addr:full":"82 Sandiford Dr Stouffville ON L4A 7X5",
    "addr:housenumber":"82",
    "addr:postcode":"l4a 7x5",
    "addr:street":"Sandiford Dr",
    "iso:country":"CA",
    "sg:address":"82 Sandiford Dr",
    "sg:city":"Stouffville",
    "sg:classifiers":[
        {
            "category":"Retail",
            "subcategory":"Auto Repair",
            "type":"Services"
        }
    ],
    "sg:phone":"+1 905 642 9433",
    "sg:postcode":"L4A 7X5",
    "sg:province":"ON",
    "sg:tags":[
        "repairing",
        "automobile"
    ],
    "wof:name":"Wideman's Auto Works",
    "wof:placetype":"venue"
},
  "geometry": {"coordinates":[-79.2699356079,43.9647331238],"type":"Point"}
}