{
  "type": "Feature",
  "properties": {
    "addr:full":"471 Main St Lawrencetown. NS B0S 1M0",
    "addr:housenumber":"471",
    "addr:postcode":"b0s 1m0",
    "addr:street":"Main St",
    "iso:country":"CA",
    "sg:address":"471 Main St",
    "sg:city":"Lawrencetown.",
    "sg:classifiers":[
        {
            "category":"Professional",
            "subcategory":"Accounting & Tax Preparation",
            "type":"Services"
        }
    ],
    "sg:phone":"+1 902 584 3700",
    "sg:postcode":"B0S 1M0",
    "sg:province":"NS",
    "sg:tags":[
        "bookkeeping",
        "general"
    ],
    "wof:name":"Triple Play Tax Svc",
    "wof:placetype":"venue"
},
  "geometry": {"coordinates":[-63.338531,44.645439],"type":"Point"}
}