{
  "type": "Feature",
  "properties": {
    "addr:full":"17 Albert St N Southampton ON N0H 2L0",
    "addr:housenumber":"17",
    "addr:postcode":"n0h 2l0",
    "addr:street":"Albert St N",
    "iso:country":"CA",
    "sg:address":"17 Albert St N",
    "sg:city":"Southampton",
    "sg:classifiers":[
        {
            "category":"Restaurant",
            "type":"Food & Drink"
        }
    ],
    "sg:phone":"+1 519 797 2991",
    "sg:postcode":"N0H 2L0",
    "sg:province":"ON",
    "wof:name":"Chips Ahoy",
    "wof:placetype":"venue"
},
  "geometry": {"coordinates":[-81.3709869385,44.4960136414],"type":"Point"}
}