{
  "type": "Feature",
  "properties": {
    "addr:full":"8 Kluhini Cres Whitehorse YT Y1A 3P3",
    "addr:housenumber":"8",
    "addr:postcode":"y1a 3p3",
    "addr:street":"Kluhini Cres",
    "iso:country":"CA",
    "sg:address":"8 Kluhini Cres",
    "sg:city":"Whitehorse",
    "sg:classifiers":[
        {
            "category":"Banks & Credit Unions",
            "subcategory":"Financial Services",
            "type":"Services"
        }
    ],
    "sg:phone":"+1 867 668 4385",
    "sg:postcode":"Y1A 3P3",
    "sg:province":"YT",
    "sg:tags":[
        "company",
        "holding"
    ],
    "wof:name":"Kluhini Holdings",
    "wof:placetype":"venue"
},
  "geometry": {"coordinates":[-135.03256200000001,60.709774],"type":"Point"}
}