{
  "type": "Feature",
  "properties": {
    "addr:full":"1232 Bedford Hwy Bedford NS B4A 1C6",
    "addr:housenumber":"1232",
    "addr:postcode":"b4a 1c6",
    "addr:street":"Bedford Hwy",
    "iso:country":"CA",
    "sg:address":"1232 Bedford Hwy",
    "sg:city":"Bedford",
    "sg:classifiers":[
        {
            "category":"Shopping",
            "subcategory":"Florist",
            "type":"Retail Goods"
        }
    ],
    "sg:phone":"+1 902 835 9551",
    "sg:postcode":"B4A 1C6",
    "sg:province":"NS",
    "sg:tags":[
        "garden",
        "center"
    ],
    "wof:name":"Atlantic Gardens Inc",
    "wof:placetype":"venue"
},
  "geometry": {"coordinates":[-63.66996,44.724251],"type":"Point"}
}