{
  "type": "Feature",
  "properties": {
    "addr:full":"Pointe-Au-Pere QC G5M 1J2",
    "addr:postcode":"g5m 1j2",
    "iso:country":"CA",
    "sg:city":"Pointe-Au-Pere",
    "sg:classifiers":[
        {
            "category":"Health Services",
            "subcategory":"Doctor",
            "type":"Services"
        }
    ],
    "sg:phone":"+1 418 724 6615",
    "sg:postcode":"G5M 1J2",
    "sg:province":"QC",
    "sg:tags":[
        "clinic",
        "dentist"
    ],
    "wof:name":"Clinique Dentaire Jean Quesnel",
    "wof:placetype":"venue"
},
  "geometry": {"coordinates":[-68.46096038819999,48.5063247681],"type":"Point"}
}