{
  "type": "Feature",
  "properties": {
    "addr:full":"66 High St Deer Lake NL A8A 1N7",
    "addr:housenumber":"66",
    "addr:postcode":"a8a 1n7",
    "addr:street":"High St",
    "iso:country":"CA",
    "sg:address":"66 High St",
    "sg:city":"Deer Lake",
    "sg:classifiers":[
        {
            "category":"Food & Beverages",
            "subcategory":"Groceries & Convenience Stores",
            "type":"Retail Goods"
        }
    ],
    "sg:phone":"+1 709 635 7111",
    "sg:postcode":"A8A 1N7",
    "sg:province":"NL",
    "wof:name":"Sharon's Mini Mart",
    "wof:placetype":"venue"
},
  "geometry": {"coordinates":[-57.425163,49.174728],"type":"Point"}
}