{
  "type": "Feature",
  "properties": {
    "addr:full":"Regina SK S4V 2X7",
    "addr:postcode":"s4v 2x7",
    "iso:country":"CA",
    "sg:city":"Regina",
    "sg:classifiers":[
        {
            "category":"Retail",
            "subcategory":"Laundry & Dry Cleaning",
            "type":"Services"
        }
    ],
    "sg:phone":"+1 306 789 9666",
    "sg:postcode":"S4V 2X7",
    "sg:province":"SK",
    "sg:tags":[
        "cleaners"
    ],
    "wof:name":"Busy Bee Dry Cleaners",
    "wof:placetype":"venue"
},
  "geometry": {"coordinates":[-104.539124,50.445881],"type":"Point"}
}