{
  "type": "Feature",
  "properties": {
    "addr:full":"Montreal QC H3S 2B4",
    "addr:postcode":"h3s 2b4",
    "iso:country":"CA",
    "sg:city":"Montreal",
    "sg:classifiers":[
        {
            "category":"Organizations",
            "subcategory":"Professional Association",
            "type":"Services"
        }
    ],
    "sg:phone":"+1 514 341 6777",
    "sg:postcode":"H3S 2B4",
    "sg:province":"QC",
    "wof:name":"Services Aux Aine S DE Mtl",
    "wof:placetype":"venue"
},
  "geometry": {"coordinates":[-73.63618469239999,45.502822876],"type":"Point"}
}