{
  "type": "Feature",
  "properties": {
    "addr:full":"1601 Ch Saint-Louis Sillery QC G1S 1G4",
    "addr:housenumber":"1601",
    "addr:postcode":"g1s 1g4",
    "addr:street":"Ch Saint-Louis",
    "iso:country":"CA",
    "sg:address":"1601 Ch Saint-Louis",
    "sg:city":"Sillery",
    "sg:classifiers":[
        {
            "category":"Real Estate",
            "subcategory":"Developer",
            "type":"Services"
        }
    ],
    "sg:phone":"+1 418 527 1045",
    "sg:postcode":"G1S 1G4",
    "sg:province":"QC",
    "sg:tags":[
        "cemetery"
    ],
    "wof:name":"St Patrick's Cemetery",
    "wof:placetype":"venue"
},
  "geometry": {"coordinates":[-71.246414,46.785355],"type":"Point"}
}