{
  "type": "Feature",
  "properties": {
    "iso:country":"CA",
    "sg:city":"Dawson Creek",
    "sg:classifiers":[
        {
            "category":"Social Services",
            "type":"Services"
        }
    ],
    "sg:phone":"+1 250 782 1514",
    "sg:postcode":"V1G 2C8",
    "sg:province":"BC",
    "sg:tags":[
        "counselor",
        "marriage",
        "family"
    ],
    "wof:name":"Peace Counselling & Clinical",
    "wof:placetype":"venue"
},
  "geometry": {"coordinates":[-120.238502502,55.7593002319],"type":"Point"}
}