{
  "type": "Feature",
  "properties": {
    "addr:full":"714 Queen St E Toronto ON M4M 1H2",
    "addr:housenumber":"714",
    "addr:postcode":"m4m 1h2",
    "addr:street":"Queen St E",
    "iso:country":"CA",
    "sg:address":"714 Queen St E",
    "sg:city":"Toronto",
    "sg:classifiers":[
        {
            "category":"Restaurant",
            "type":"Food & Drink"
        }
    ],
    "sg:phone":"+1 416 463 7310",
    "sg:postcode":"M4M 1H2",
    "sg:province":"ON",
    "wof:name":"Dangerous Dan's Diner",
    "wof:placetype":"venue"
},
  "geometry": {"coordinates":[-79.3496170044,43.6590576172],"type":"Point"}
}