{
  "type": "Feature",
  "properties": {
    "iso:country":"CA",
    "sg:address":"4801 50 Ave",
    "sg:city":"Leduc",
    "sg:classifiers":[
        {
            "category":"Shopping",
            "subcategory":"Clothing, Apparel, & Fashions",
            "type":"Retail Goods"
        }
    ],
    "sg:phone":"+1 780 986 4223",
    "sg:postcode":"T9E 6X8",
    "sg:province":"AB",
    "sg:tags":[
        "furnishing"
    ],
    "wof:name":"Komfolio's",
    "wof:placetype":"venue"
},
  "geometry": {"coordinates":[-113.54814910899999,53.2646484375],"type":"Point"}
}