{
  "type": "Feature",
  "properties": {
    "addr:full":"334 Riverside Dr Toronto ON M6S 4B2",
    "addr:housenumber":"334",
    "addr:postcode":"m6s 4b2",
    "addr:street":"Riverside Dr",
    "iso:country":"CA",
    "sg:address":"334 Riverside Dr",
    "sg:city":"Toronto",
    "sg:classifiers":[
        {
            "category":"Social Services",
            "type":"Services"
        }
    ],
    "sg:phone":"+1 416 769 0964",
    "sg:postcode":"M6S 4B2",
    "sg:province":"ON",
    "sg:tags":[
        "organization",
        "welfare"
    ],
    "wof:name":"Care Canada",
    "wof:placetype":"venue"
},
  "geometry": {"coordinates":[-79.4880981445,43.6472091675],"type":"Point"}
}