{
  "type": "Feature",
  "properties": {
    "addr:full":"West Vancouver BC V7V 1K4",
    "addr:postcode":"v7v 1k4",
    "iso:country":"CA",
    "sg:city":"West Vancouver",
    "sg:classifiers":[
        {
            "category":"Restaurant",
            "type":"Food & Drink"
        }
    ],
    "sg:phone":"+1 604 925 0667",
    "sg:postcode":"V7V 1K4",
    "sg:province":"BC",
    "wof:name":"Zen Japanese Restaurant Corp",
    "wof:placetype":"venue"
},
  "geometry": {"coordinates":[-123.172821,49.331493],"type":"Point"}
}