{
  "type": "Feature",
  "properties": {
    "addr:full":"1533 Jane St North York ON M9N 2R2",
    "addr:housenumber":"1533",
    "addr:postcode":"m9n 2r2",
    "addr:street":"Jane St",
    "iso:country":"CA",
    "sg:address":"1533 Jane St",
    "sg:city":"North York",
    "sg:classifiers":[
        {
            "category":"Food & Beverages",
            "subcategory":"Bakery",
            "type":"Retail Goods"
        }
    ],
    "sg:phone":"+1 416 247 4445",
    "sg:postcode":"M9N 2R2",
    "sg:province":"ON",
    "sg:tags":[
        "doughnut"
    ],
    "wof:name":"Country Style Donuts",
    "wof:placetype":"venue"
},
  "geometry": {"coordinates":[-79.50211334230001,43.6973304749],"type":"Point"}
}