{
  "type": "Feature",
  "properties": {
    "addr:full":"401 Meyers Ave Kinistino SK S0J 1H0",
    "addr:housenumber":"401",
    "addr:postcode":"s0j 1h0",
    "addr:street":"Meyers Ave",
    "iso:country":"CA",
    "sg:address":"401 Meyers Ave",
    "sg:city":"Kinistino",
    "sg:classifiers":[
        {
            "category":"Health Services",
            "subcategory":"Doctor",
            "type":"Services"
        }
    ],
    "sg:phone":"+1 306 864 2212",
    "sg:postcode":"S0J 1H0",
    "sg:province":"SK",
    "sg:tags":[
        "physician",
        "surgeon"
    ],
    "wof:name":"Kinistino Medical Clinic",
    "wof:placetype":"venue"
},
  "geometry": {"coordinates":[-105.034217834,52.9511146545],"type":"Point"}
}