{
  "type": "Feature",
  "properties": {
    "addr:full":"7555 Boul Taschereau Brossard QC J4Y 1A2",
    "addr:housenumber":"7555",
    "addr:postcode":"j4y 1a2",
    "addr:street":"Boul Taschereau",
    "iso:country":"CA",
    "sg:address":"7555 Boul Taschereau",
    "sg:city":"Brossard",
    "sg:classifiers":[
        {
            "category":"Home & Garden",
            "subcategory":"Building Materials",
            "type":"Retail Goods"
        }
    ],
    "sg:phone":"+1 450 678 7146",
    "sg:postcode":"J4Y 1A2",
    "sg:province":"QC",
    "sg:tags":[
        "paint"
    ],
    "wof:name":"Betonel",
    "wof:placetype":"venue"
},
  "geometry": {"coordinates":[-73.46468400000001,45.457298],"type":"Point"}
}