{
  "type": "Feature",
  "properties": {
    "addr:full":"650 Boul Pere-Lelievre # 115 Vanier QC G1M 3T2",
    "addr:housenumber":"650",
    "addr:postcode":"g1m 3t2",
    "addr:street":"Boul Pere-Lelievre # 115",
    "iso:country":"CA",
    "sg:address":"650 Boul Pere-Lelievre # 115",
    "sg:city":"Vanier",
    "sg:classifiers":[
        {
            "category":"Retail",
            "subcategory":"Auto Repair",
            "type":"Services"
        }
    ],
    "sg:phone":"+1 418 686 5052",
    "sg:postcode":"G1M 3T2",
    "sg:province":"QC",
    "sg:tags":[
        "repairing",
        "automobile"
    ],
    "wof:name":"Auto Technique VT",
    "wof:placetype":"venue"
},
  "geometry": {"coordinates":[-71.273796,46.813469],"type":"Point"}
}