{
  "type": "Feature",
  "properties": {
    "addr:full":"21117 108 Ave NW Edmonton AB T5S 1X3",
    "addr:housenumber":"21117",
    "addr:postcode":"t5s 1x3",
    "addr:street":"108 Ave Nw",
    "iso:country":"CA",
    "sg:address":"21117 108 Ave NW",
    "sg:city":"Edmonton",
    "sg:classifiers":[
        {
            "category":"Retail",
            "subcategory":"Auto Repair",
            "type":"Services"
        }
    ],
    "sg:phone":"+1 780 455 6122",
    "sg:postcode":"T5S 1X3",
    "sg:province":"AB",
    "sg:tags":[
        "repairing",
        "automobile"
    ],
    "wof:name":"Reesonable Auto Repair",
    "wof:placetype":"venue"
},
  "geometry": {"coordinates":[-113.682823,53.553265],"type":"Point"}
}