{
  "type": "Feature",
  "properties": {
    "addr:full":"3030 Rue King O Sherbrooke QC J1L 1Y7",
    "addr:housenumber":"3030",
    "addr:postcode":"j1l 1y7",
    "addr:street":"Rue King O",
    "iso:country":"CA",
    "sg:address":"3030 Rue King O",
    "sg:city":"Sherbrooke",
    "sg:phone":"+1 819 566 1377",
    "sg:postcode":"J1L 1Y7",
    "sg:province":"QC",
    "sg:tags":[
        "equipment",
        "station",
        "garage"
    ],
    "wof:name":"Equipements DE Garage Bouchard",
    "wof:placetype":"venue"
},
  "geometry": {"coordinates":[-71.944557,45.396545],"type":"Point"}
}