{
  "type": "Feature",
  "properties": {
    "addr:full":"66 Pleasant Valley Rd Brookfield NS B0N 1C0",
    "addr:housenumber":"66",
    "addr:postcode":"b0n 1c0",
    "addr:street":"Pleasant Valley Rd",
    "iso:country":"CA",
    "sg:address":"66 Pleasant Valley Rd",
    "sg:city":"Brookfield",
    "sg:classifiers":[
        {
            "category":"Manufacturing",
            "subcategory":"Lumber",
            "type":"Manufacturing & Wholesale Goods"
        }
    ],
    "sg:phone":"+1 902 673 2508",
    "sg:postcode":"B0N 1C0",
    "sg:province":"NS",
    "wof:name":"Marwood Limited",
    "wof:placetype":"venue"
},
  "geometry": {"coordinates":[-63.2815132141,45.2532081604],"type":"Point"}
}