{
  "type": "Feature",
  "properties": {
    "addr:full":"389 Oliver Rd Thunder Bay ON P7B 2G1",
    "addr:housenumber":"389",
    "addr:postcode":"p7b 2g1",
    "addr:street":"Oliver Rd",
    "iso:country":"CA",
    "sg:address":"389 Oliver Rd",
    "sg:city":"Thunder Bay",
    "sg:classifiers":[
        {
            "category":"Retail",
            "subcategory":"Repair Shop",
            "type":"Services"
        }
    ],
    "sg:phone":"+1 807 345 5546",
    "sg:postcode":"P7B 2G1",
    "sg:province":"ON",
    "sg:tags":[
        "upholsterer"
    ],
    "wof:name":"Bernie's Upholstery",
    "wof:placetype":"venue"
},
  "geometry": {"coordinates":[-89.23809799999999,48.429066],"type":"Point"}
}