{
  "type": "Feature",
  "properties": {
    "addr:full":"171 Main St West Lorne ON N0L 2P0",
    "addr:housenumber":"171",
    "addr:postcode":"n0l 2p0",
    "addr:street":"Main St",
    "iso:country":"CA",
    "sg:address":"171 Main St",
    "sg:city":"West Lorne",
    "sg:classifiers":[
        {
            "category":"Health Services",
            "subcategory":"Doctor",
            "type":"Services"
        }
    ],
    "sg:phone":"+1 519 768 1326",
    "sg:postcode":"N0L 2P0",
    "sg:province":"ON",
    "sg:tags":[
        "physician",
        "surgeon"
    ],
    "wof:name":"West Elgin Medical Ctr",
    "wof:placetype":"venue"
},
  "geometry": {"coordinates":[-81.6074523926,42.603351593],"type":"Point"}
}