{
  "type": "Feature",
  "properties": {
    "addr:full":"1040 Rang Saint-Joseph Saint-Flavien QC G0S 2M0",
    "addr:housenumber":"1040",
    "addr:postcode":"g0s 2m0",
    "addr:street":"Rang Saint-Joseph",
    "iso:country":"CA",
    "sg:address":"1040 Rang Saint-Joseph",
    "sg:city":"Saint-Flavien",
    "sg:classifiers":[
        {
            "category":"Retail",
            "subcategory":"Auto Repair",
            "type":"Services"
        }
    ],
    "sg:phone":"+1 418 728 4232",
    "sg:postcode":"G0S 2M0",
    "sg:province":"QC",
    "sg:tags":[
        "repairing",
        "automobile"
    ],
    "wof:name":"Garage Hilaire Cote",
    "wof:placetype":"venue"
},
  "geometry": {"coordinates":[-71.6097946167,46.5230064392],"type":"Point"}
}