{
  "type": "Feature",
  "properties": {
    "addr:full":"462 Av DE LA Station Shawinigan QC G9N 1W1",
    "addr:postcode":"g9n 1w1",
    "addr:street":"462 Av De La Station",
    "iso:country":"CA",
    "sg:address":"462 Av DE LA Station",
    "sg:city":"Shawinigan",
    "sg:classifiers":[
        {
            "category":"Personal",
            "subcategory":"Beauty Salon",
            "type":"Services"
        }
    ],
    "sg:phone":"+1 819 537 4487",
    "sg:postcode":"G9N 1W1",
    "sg:province":"QC",
    "wof:name":"Salon DE Beaute Deesse Enr",
    "wof:placetype":"venue"
},
  "geometry": {"coordinates":[-72.7518005371,46.5401115417],"type":"Point"}
}