{
  "type": "Feature",
  "properties": {
    "addr:full":"4609 49 St Camrose AB T4V 1M4",
    "addr:housenumber":"4609",
    "addr:postcode":"t4v 1m4",
    "addr:street":"49 St",
    "iso:country":"CA",
    "sg:address":"4609 49 St",
    "sg:city":"Camrose",
    "sg:classifiers":[
        {
            "category":"Arena",
            "subcategory":"Sports Club",
            "type":"Entertainment"
        }
    ],
    "sg:phone":"+1 780 672 8338",
    "sg:postcode":"T4V 1M4",
    "sg:province":"AB",
    "sg:tags":[
        "athletic",
        "fields",
        "stadium"
    ],
    "wof:name":"Wildrose Arena",
    "wof:placetype":"venue"
},
  "geometry": {"coordinates":[-112.823975,53.014645],"type":"Point"}
}