{
  "type": "Feature",
  "properties": {
    "addr:full":"Saskatoon SK S7L 1P2",
    "addr:postcode":"s7l 1p2",
    "iso:country":"CA",
    "sg:city":"Saskatoon",
    "sg:classifiers":[
        {
            "category":"Organizations",
            "subcategory":"Religious Organization",
            "type":"Services"
        }
    ],
    "sg:phone":"+1 306 652 3479",
    "sg:postcode":"S7L 1P2",
    "sg:province":"SK",
    "sg:tags":[
        "church"
    ],
    "wof:name":"Church of God",
    "wof:placetype":"venue"
},
  "geometry": {"coordinates":[-106.674919128,52.1460571289],"type":"Point"}
}