{
  "type": "Feature",
  "properties": {
    "addr:full":"160 William St Oakville ON L6J 1C5",
    "addr:housenumber":"160",
    "addr:postcode":"l6j 1c5",
    "addr:street":"William St",
    "iso:country":"CA",
    "sg:address":"160 William St",
    "sg:city":"Oakville",
    "sg:classifiers":[
        {
            "category":"Social Services",
            "subcategory":"Child Care",
            "type":"Services"
        }
    ],
    "sg:phone":"+1 905 338 5247",
    "sg:postcode":"L6J 1C5",
    "sg:province":"ON",
    "sg:tags":[
        "school"
    ],
    "wof:name":"Hopedale Montessori School",
    "wof:placetype":"venue"
},
  "geometry": {"coordinates":[-79.667259,43.443977],"type":"Point"}
}