{
  "type": "Feature",
  "properties": {
    "addr:full":"251 Spokane St Kimberley BC V1A 2E6",
    "addr:housenumber":"251",
    "addr:postcode":"v1a 2e6",
    "addr:street":"Spokane St",
    "iso:country":"CA",
    "sg:address":"251 Spokane St",
    "sg:city":"Kimberley",
    "sg:classifiers":[
        {
            "category":"Organizations",
            "subcategory":"Professional Association",
            "type":"Services"
        }
    ],
    "sg:phone":"+1 250 427 4711",
    "sg:postcode":"V1A 2E6",
    "sg:province":"BC",
    "wof:name":"Land Conservancy of British",
    "wof:placetype":"venue"
},
  "geometry": {"coordinates":[-115.982978821,49.6858177185],"type":"Point"}
}