{
  "type": "Feature",
  "properties": {
    "addr:full":"5000 Rue Armand-Viau Quebec QC G2C 1Z9",
    "addr:housenumber":"5000",
    "addr:postcode":"qc g2c 1z9",
    "addr:street":"Rue Armand-Viau",
    "iso:country":"CA",
    "sg:address":"5000 Rue Armand-Viau",
    "sg:city":"Quebec",
    "sg:classifiers":[
        {
            "category":"Retail",
            "subcategory":"Auto Rental",
            "type":"Services"
        }
    ],
    "sg:phone":"+1 418 871 2933",
    "sg:postcode":"G2C 1Z9",
    "sg:province":"QC",
    "sg:tags":[
        "renting",
        "truck",
        "agency",
        "leasing"
    ],
    "wof:name":"U-Haul Cie Ltee",
    "wof:placetype":"venue"
},
  "geometry": {"coordinates":[-71.3367233276,46.8154640198],"type":"Point"}
}