{
  "type": "Feature",
  "properties": {
    "addr:full":"8 Garamond Crt North York ON M3C 1Z4",
    "addr:housenumber":"8",
    "addr:postcode":"m3c 1z4",
    "addr:street":"Garamond Crt",
    "iso:country":"CA",
    "sg:address":"8 Garamond Crt",
    "sg:city":"North York",
    "sg:classifiers":[
        {
            "category":"Wholesale",
            "subcategory":"Apparel",
            "type":"Manufacturing & Wholesale Goods"
        }
    ],
    "sg:phone":"+1 416 510 8383",
    "sg:postcode":"M3C 1Z4",
    "sg:province":"ON",
    "sg:tags":[
        "label"
    ],
    "wof:name":"J B Woven Labels Ltd",
    "wof:placetype":"venue"
},
  "geometry": {"coordinates":[-79.333923,43.725842],"type":"Point"}
}