{
  "type": "Feature",
  "properties": {
    "addr:full":"475 Av Westminster Dollard-Des-Ormeaux QC H9G 2S3",
    "addr:housenumber":"475",
    "addr:postcode":"h9g 2s3",
    "addr:street":"Av Westminster",
    "iso:country":"CA",
    "sg:address":"475 Av Westminster",
    "sg:city":"Dollard-Des-Ormeaux",
    "sg:classifiers":[
        {
            "category":"Wholesale",
            "subcategory":"Drugs",
            "type":"Manufacturing & Wholesale Goods"
        }
    ],
    "sg:phone":"+1 514 696 0303",
    "sg:postcode":"H9G 2S3",
    "sg:province":"QC",
    "sg:tags":[
        "pharmaceutical",
        "product"
    ],
    "wof:name":"Merlin International Comm Inc",
    "wof:placetype":"venue"
},
  "geometry": {"coordinates":[-73.83930969239999,45.4760360718],"type":"Point"}
}