{
  "type": "Feature",
  "properties": {
    "addr:full":"Regina SK S4R 2N4",
    "addr:postcode":"s4r 2n4",
    "iso:country":"CA",
    "sg:city":"Regina",
    "sg:classifiers":[
        {
            "category":"Utilities",
            "subcategory":"Mobile Phone",
            "type":"Services"
        }
    ],
    "sg:phone":"+1 306 569 0600",
    "sg:postcode":"S4R 2N4",
    "sg:province":"SK",
    "sg:tags":[
        "telephone",
        "cellular"
    ],
    "wof:name":"Prairie Mobile Communications",
    "wof:placetype":"venue"
},
  "geometry": {"coordinates":[-104.618423462,50.474571228],"type":"Point"}
}