{
  "type": "Feature",
  "properties": {
    "addr:full":"108 Boundary Rd Brighton ON K0K 1H0",
    "addr:housenumber":"108",
    "addr:postcode":"k0k 1h0",
    "addr:street":"Boundary Rd",
    "iso:country":"CA",
    "sg:address":"108 Boundary Rd",
    "sg:city":"Brighton",
    "sg:classifiers":[
        {
            "category":"Education",
            "subcategory":"School",
            "type":"Public Place"
        }
    ],
    "sg:phone":"+1 613 475 3893",
    "sg:postcode":"K0K 1H0",
    "sg:province":"ON",
    "wof:name":"Brighton Cis",
    "wof:placetype":"venue"
},
  "geometry": {"coordinates":[-77.737801,44.042019],"type":"Point"}
}