{
  "type": "Feature",
  "properties": {
    "addr:full":"646 Rue Lafontaine #201 Riviere-Du-Loup QC G5R 3C8",
    "addr:housenumber":"646;#",
    "addr:postcode":"g5r 3c8",
    "addr:street":"Rue Lafontaine;Riviere-Du-Loup",
    "iso:country":"CA",
    "sg:address":"646 Rue Lafontaine #201",
    "sg:city":"Riviere-Du-Loup",
    "sg:classifiers":[
        {
            "category":"Professional",
            "subcategory":"Management & Consulting",
            "type":"Services"
        }
    ],
    "sg:phone":"+1 418 867 4272",
    "sg:postcode":"G5R 3C8",
    "sg:province":"QC",
    "sg:tags":[
        "consultant",
        "business"
    ],
    "wof:name":"Societe D'Aide Du Dev",
    "wof:placetype":"venue"
},
  "geometry": {"coordinates":[-69.52606964109999,47.8233604431],"type":"Point"}
}