{
  "type": "Feature",
  "properties": {
    "addr:full":"NE 1-24-14W Hwy 68 # 2 Ste Rose Du Lac MB R0L 1S0",
    "addr:postcode":"r0l 1s0",
    "addr:street":"Ne 1-24-14W Hwy 68 # 2 Ste Rose Du Lac",
    "iso:country":"CA",
    "sg:address":"NE 1-24-14W Hwy 68 # 2",
    "sg:city":"Ste Rose Du Lac",
    "sg:classifiers":[
        {
            "category":"Professional",
            "subcategory":"Accounting & Tax Preparation",
            "type":"Services"
        }
    ],
    "sg:phone":"+1 204 448 2109",
    "sg:postcode":"R0L 1S0",
    "sg:province":"MB",
    "sg:tags":[
        "return",
        "filing"
    ],
    "wof:name":"Wilkinson's Tax Discounting",
    "wof:placetype":"venue"
},
  "geometry": {"coordinates":[-99.5232009888,51.0591850281],"type":"Point"}
}