{
  "type": "Feature",
  "properties": {
    "addr:full":"243 Huron St S Southampton ON N0H 2L0",
    "addr:housenumber":"243",
    "addr:postcode":"n0h 2l0",
    "addr:street":"Huron St S",
    "iso:country":"CA",
    "sg:address":"243 Huron St S",
    "sg:city":"Southampton",
    "sg:classifiers":[
        {
            "category":"Travel",
            "subcategory":"Hotels & Motels",
            "type":"Entertainment"
        }
    ],
    "sg:phone":"+1 519 797 3777",
    "sg:postcode":"N0H 2L0",
    "sg:province":"ON",
    "wof:name":"Cedar Court Motel",
    "wof:placetype":"venue"
},
  "geometry": {"coordinates":[-81.38121,44.489227],"type":"Point"}
}