{
  "type": "Feature",
  "properties": {
    "addr:full":"3906 35A St Vernon BC V1T 6W1",
    "addr:housenumber":"3906",
    "addr:postcode":"v1t 6w1",
    "addr:street":"35A St",
    "iso:country":"CA",
    "sg:address":"3906 35A St",
    "sg:city":"Vernon",
    "sg:classifiers":[
        {
            "category":"Organizations",
            "subcategory":"Religious Organization",
            "type":"Services"
        }
    ],
    "sg:phone":"+1 250 542 4135",
    "sg:postcode":"V1T 6W1",
    "sg:province":"BC",
    "sg:tags":[
        "church"
    ],
    "wof:name":"Alexis Park Church",
    "wof:placetype":"venue"
},
  "geometry": {"coordinates":[-119.21476699999999,50.299519],"type":"Point"}
}