{
  "type": "Feature",
  "properties": {
    "iso:country":"CA",
    "sg:city":"Havelock",
    "sg:classifiers":[
        {
            "category":"Professional",
            "subcategory":"Accounting & Tax Preparation",
            "type":"Services"
        }
    ],
    "sg:phone":"+1 705 778 2615",
    "sg:postcode":"K0L 1Z0",
    "sg:province":"ON",
    "sg:tags":[
        "bookkeeping",
        "return",
        "filing",
        "general"
    ],
    "wof:name":"Your Office",
    "wof:placetype":"venue"
},
  "geometry": {"coordinates":[-77.88157653810001,44.4333610535],"type":"Point"}
}