{
  "type": "Feature",
  "properties": {
    "addr:full":"140 Rue Des Bosquets Dolbeau-Mistassini QC G8L 3R6",
    "addr:housenumber":"140",
    "addr:postcode":"g8l 3r6",
    "addr:street":"Rue Des Bosquets",
    "iso:country":"CA",
    "sg:address":"140 Rue Des Bosquets",
    "sg:city":"Dolbeau-Mistassini",
    "sg:classifiers":[
        {
            "category":"Freight",
            "type":"Transportation"
        }
    ],
    "sg:phone":"+1 418 276 2841",
    "sg:postcode":"G8L 3R6",
    "sg:province":"QC",
    "sg:tags":[
        "trucking"
    ],
    "wof:name":"Coursiers Sm Inc",
    "wof:placetype":"venue"
},
  "geometry": {"coordinates":[-72.2106170654,48.8618583679],"type":"Point"}
}