{
  "type": "Feature",
  "properties": {
    "addr:full":"21774 Woodbine Ave Queensville ON L0G 1R0",
    "addr:housenumber":"21774",
    "addr:postcode":"l0g 1r0",
    "addr:street":"Woodbine Ave",
    "iso:country":"CA",
    "sg:address":"21774 Woodbine Ave",
    "sg:city":"Queensville",
    "sg:classifiers":[
        {
            "category":"Building & Trades",
            "subcategory":"Landscaping Services",
            "type":"Services"
        }
    ],
    "sg:phone":"+1 905 478 2899",
    "sg:postcode":"L0G 1R0",
    "sg:province":"ON",
    "sg:tags":[
        "sod",
        "sodding"
    ],
    "wof:name":"Lipani & Lapani Sodding",
    "wof:placetype":"venue"
},
  "geometry": {"coordinates":[-79.431038,44.164001],"type":"Point"}
}