{
  "type": "Feature",
  "properties": {
    "addr:full":"581013 Grey Rd 25 Chesley ON N0G 1L0",
    "addr:housenumber":"581013;25",
    "addr:postcode":"n0g 1l0",
    "addr:street":"Grey Rd",
    "iso:country":"CA",
    "sg:address":"581013 Grey Rd 25",
    "sg:city":"Chesley",
    "sg:classifiers":[
        {
            "category":"Manufacturing",
            "subcategory":"Wood Products",
            "type":"Manufacturing & Wholesale Goods"
        }
    ],
    "sg:phone":"+1 519 363 3011",
    "sg:postcode":"N0G 1L0",
    "sg:province":"ON",
    "sg:tags":[
        "pallet",
        "skid"
    ],
    "wof:name":"Findlay Pallet CO Ltd",
    "wof:placetype":"venue"
},
  "geometry": {"coordinates":[-81.096497,44.302277],"type":"Point"}
}