{
  "type": "Feature",
  "properties": {
    "iso:country":"CA",
    "sg:address":"10635 Boul DE L'Ormiere",
    "sg:city":"Quebec",
    "sg:classifiers":[
        {
            "category":"Personal",
            "subcategory":"Beauty Salon",
            "type":"Services"
        }
    ],
    "sg:phone":"+1 418 845 0929",
    "sg:postcode":"G2B 3L5",
    "sg:province":"QC",
    "wof:name":"Coiffure Jose Ross Enr",
    "wof:placetype":"venue"
},
  "geometry": {"coordinates":[-71.339935,46.824921],"type":"Point"}
}