{
  "type": "Feature",
  "properties": {
    "addr:full":"16683 Boul Du Cure-Labelle Mirabel QC J7J 2G7",
    "addr:housenumber":"16683",
    "addr:postcode":"j7j 2g7",
    "addr:street":"Boul Du Cure-Labelle",
    "iso:country":"CA",
    "sg:address":"16683 Boul Du Cure-Labelle",
    "sg:city":"Mirabel",
    "sg:classifiers":[
        {
            "category":"Home & Garden",
            "subcategory":"Building Materials",
            "type":"Retail Goods"
        }
    ],
    "sg:phone":"+1 450 432 6555",
    "sg:postcode":"J7J 2G7",
    "sg:province":"QC",
    "wof:name":"Materiaux",
    "wof:placetype":"venue"
},
  "geometry": {"coordinates":[-73.9722976685,45.7429885864],"type":"Point"}
}