{
  "type": "Feature",
  "properties": {
    "addr:full":"3794 Boul Saint-Laurent Montreal QC H2W 1X6",
    "addr:housenumber":"3794",
    "addr:postcode":"h2w 1x6",
    "addr:street":"Boul Saint-Laurent",
    "iso:country":"CA",
    "sg:address":"3794 Boul Saint-Laurent",
    "sg:city":"Montreal",
    "sg:classifiers":[
        {
            "category":"Shopping",
            "subcategory":"Clothing, Apparel, & Fashions",
            "type":"Retail Goods"
        }
    ],
    "sg:phone":"+1 514 843 3643",
    "sg:postcode":"H2W 1X6",
    "sg:province":"QC",
    "sg:tags":[
        "jean"
    ],
    "wof:name":"Adam & Lillith",
    "wof:placetype":"venue"
},
  "geometry": {"coordinates":[-73.57621,45.515396],"type":"Point"}
}