{
  "type": "Feature",
  "properties": {
    "addr:full":"North Bay ON P1A 4C2",
    "addr:postcode":"p1a 4c2",
    "iso:country":"CA",
    "sg:city":"North Bay",
    "sg:classifiers":[
        {
            "category":"Real Estate",
            "subcategory":"Real Estate Agent",
            "type":"Services"
        }
    ],
    "sg:phone":"+1 705 476 0052",
    "sg:postcode":"P1A 4C2",
    "sg:province":"ON",
    "sg:tags":[
        "housing"
    ],
    "wof:name":"Harmony Haven Housing Inc",
    "wof:placetype":"venue"
},
  "geometry": {"coordinates":[-79.4330368042,46.2830276489],"type":"Point"}
}