{
  "type": "Feature",
  "properties": {
    "addr:full":"94 Cumberland St Toronto ON M5R 1A3",
    "addr:housenumber":"94",
    "addr:postcode":"m5r 1a3",
    "addr:street":"Cumberland St",
    "iso:country":"CA",
    "sg:address":"94 Cumberland St",
    "sg:city":"Toronto",
    "sg:classifiers":[
        {
            "category":"Professional",
            "subcategory":"Business Services",
            "type":"Services"
        }
    ],
    "sg:phone":"+1 416 961 5612",
    "sg:postcode":"M5R 1A3",
    "sg:province":"ON",
    "wof:name":"Marmer Penner Inc",
    "wof:placetype":"venue"
},
  "geometry": {"coordinates":[-79.390732,43.670498],"type":"Point"}
}