{
  "type": "Feature",
  "properties": {
    "addr:full":"5305 Tecumseh Rd E Windsor ON N8T 1C5",
    "addr:housenumber":"5305",
    "addr:postcode":"n8t 1c5",
    "addr:street":"Tecumseh Rd E",
    "iso:country":"CA",
    "sg:address":"5305 Tecumseh Rd E",
    "sg:city":"Windsor",
    "sg:classifiers":[
        {
            "category":"Education",
            "subcategory":"School",
            "type":"Public Place"
        }
    ],
    "sg:phone":"+1 519 945 2628",
    "sg:postcode":"N8T 1C5",
    "sg:province":"ON",
    "wof:name":"St Therese Ecole",
    "wof:placetype":"venue"
},
  "geometry": {"coordinates":[-82.9603500366,42.3086624146],"type":"Point"}
}