{
  "type": "Feature",
  "properties": {
    "addr:full":"950 Rue Roy E Montreal QC H2L 1E8",
    "addr:housenumber":"950",
    "addr:postcode":"h2l 1e8",
    "addr:street":"Rue Roy E",
    "iso:country":"CA",
    "sg:address":"950 Rue Roy E",
    "sg:city":"Montreal",
    "sg:classifiers":[
        {
            "category":"Restaurant",
            "type":"Food & Drink"
        }
    ],
    "sg:phone":"+1 514 527 8500",
    "sg:postcode":"H2L 1E8",
    "sg:province":"QC",
    "wof:name":"Grille-Pain",
    "wof:placetype":"venue"
},
  "geometry": {"coordinates":[-73.56940460209999,45.5223083496],"type":"Point"}
}