{
  "type": "Feature",
  "properties": {
    "addr:full":"5740 Rue Hamilton Montreal QC H4E 3B8",
    "addr:housenumber":"5740",
    "addr:postcode":"h4e 3b8",
    "addr:street":"Rue Hamilton",
    "iso:country":"CA",
    "sg:address":"5740 Rue Hamilton",
    "sg:city":"Montreal",
    "sg:classifiers":[
        {
            "category":"Manufacturing",
            "subcategory":"Chemicals & Compounds",
            "type":"Manufacturing & Wholesale Goods"
        }
    ],
    "sg:phone":"+1 514 766 2383",
    "sg:postcode":"H4E 3B8",
    "sg:province":"QC",
    "wof:name":"Produits Chimiques Adro Inc",
    "wof:placetype":"venue"
},
  "geometry": {"coordinates":[-73.5989456177,45.4608268738],"type":"Point"}
}