{
  "type": "Feature",
  "properties": {
    "addr:full":"Newmarket ON L3Y 3E3",
    "addr:postcode":"l3y 3e3",
    "iso:country":"CA",
    "sg:city":"Newmarket",
    "sg:classifiers":[
        {
            "category":"Education",
            "subcategory":"School",
            "type":"Public Place"
        }
    ],
    "sg:phone":"+1 905 836 4939",
    "sg:postcode":"L3Y 3E3",
    "sg:province":"ON",
    "sg:tags":[
        "instruction",
        "dancing"
    ],
    "wof:name":"York Dance Academy",
    "wof:placetype":"venue"
},
  "geometry": {"coordinates":[-79.4328079224,44.0700836182],"type":"Point"}
}