{
  "type": "Feature",
  "properties": {
    "addr:full":"Winnipeg MB R3G 0W4",
    "addr:postcode":"r3g 0w4",
    "iso:country":"CA",
    "sg:city":"Winnipeg",
    "sg:classifiers":[
        {
            "category":"Food & Beverages",
            "subcategory":"Bakery",
            "type":"Retail Goods"
        }
    ],
    "sg:phone":"+1 204 772 4100",
    "sg:postcode":"R3G 0W4",
    "sg:province":"MB",
    "sg:tags":[
        "product"
    ],
    "wof:name":"Pretzelmaker",
    "wof:placetype":"venue"
},
  "geometry": {"coordinates":[-97.19825,49.88102],"type":"Point"}
}