{
  "type": "Feature",
  "properties": {
    "addr:full":"33833 Enterprise Ave Abbotsford BC V2T 6L6",
    "addr:housenumber":"33833",
    "addr:postcode":"v2t 6l6",
    "addr:street":"Enterprise Ave",
    "iso:country":"CA",
    "sg:address":"33833 Enterprise Ave",
    "sg:city":"Abbotsford",
    "sg:classifiers":[
        {
            "category":"Wholesale",
            "subcategory":"Farm Supplies",
            "type":"Manufacturing & Wholesale Goods"
        }
    ],
    "sg:phone":"+1 604 853 5901",
    "sg:postcode":"V2T 6L6",
    "sg:province":"BC",
    "sg:tags":[
        "feed"
    ],
    "wof:name":"Clearbrook Grain & Milling CO",
    "wof:placetype":"venue"
},
  "geometry": {"coordinates":[-122.2891922,49.060382843],"type":"Point"}
}