{
  "type": "Feature",
  "properties": {
    "addr:full":"2765 Huron Church Rd Windsor ON N9E 3Y7",
    "addr:housenumber":"2765",
    "addr:postcode":"n9e 3y7",
    "addr:street":"Huron Church Rd",
    "iso:country":"CA",
    "sg:address":"2765 Huron Church Rd",
    "sg:city":"Windsor",
    "sg:classifiers":[
        {
            "category":"Restaurant",
            "type":"Food & Drink"
        }
    ],
    "sg:phone":"+1 519 966 8300",
    "sg:postcode":"N9E 3Y7",
    "sg:province":"ON",
    "wof:name":"Golden Griddle Family Rstrnt",
    "wof:placetype":"venue"
},
  "geometry": {"coordinates":[-83.0446548462,42.2657432556],"type":"Point"}
}