{
  "type": "Feature",
  "properties": {
    "addr:full":"2024 Rue Holmes Saint-Hubert QC J4T 1R5",
    "addr:housenumber":"2024",
    "addr:postcode":"j4t 1r5",
    "addr:street":"Rue Holmes",
    "iso:country":"CA",
    "sg:address":"2024 Rue Holmes",
    "sg:city":"Saint-Hubert",
    "sg:classifiers":[
        {
            "category":"Retail",
            "subcategory":"Auto Repair",
            "type":"Services"
        }
    ],
    "sg:phone":"+1 450 678 6900",
    "sg:postcode":"J4T 1R5",
    "sg:province":"QC",
    "sg:tags":[
        "repairing",
        "automobile"
    ],
    "wof:name":"Mecanique Mario Et Jacques Inc",
    "wof:placetype":"venue"
},
  "geometry": {"coordinates":[-73.4733428955,45.4939308167],"type":"Point"}
}