{
  "type": "Feature",
  "properties": {
    "iso:country":"CA",
    "sg:address":"1163 Kingston Rd",
    "sg:city":"Pickering",
    "sg:classifiers":[
        {
            "category":"Personal",
            "subcategory":"Beauty Salon",
            "type":"Services"
        }
    ],
    "sg:phone":"+1 905 831 1403",
    "sg:postcode":"L1V 1B5",
    "sg:province":"ON",
    "wof:name":"Noble Beauty Salon",
    "wof:placetype":"venue"
},
  "geometry": {"coordinates":[-79.09656524659999,43.8307609558],"type":"Point"}
}