{
  "type": "Feature",
  "properties": {
    "addr:full":"11 Rue DE L' Eglise Saint-Felix-DE-Dalquier QC J0Y 1G0",
    "addr:housenumber":"11",
    "addr:postcode":"j0y 1g0",
    "addr:street":"Rue De L ' Eglise Saint-Felix-De-Dalquier",
    "iso:country":"CA",
    "sg:address":"11 Rue DE L' Eglise",
    "sg:city":"Saint-Felix-DE-Dalquier",
    "sg:classifiers":[
        {
            "category":"Education",
            "subcategory":"School",
            "type":"Public Place"
        }
    ],
    "sg:phone":"+1 819 732 4900",
    "sg:postcode":"J0Y 1G0",
    "sg:province":"QC",
    "wof:name":"Ecole Notre-Dame Des Ecoles",
    "wof:placetype":"venue"
},
  "geometry": {"coordinates":[-78.1141586304,48.67786026],"type":"Point"}
}