{
  "type": "Feature",
  "properties": {
    "addr:full":"462 Ch DE LA Grande-Cote Boisbriand QC J7E 4H4",
    "addr:housenumber":"462",
    "addr:postcode":"j7e 4h4",
    "addr:street":"Ch De La Grande-Cote",
    "iso:country":"CA",
    "sg:address":"462 Ch DE LA Grande-Cote",
    "sg:city":"Boisbriand",
    "sg:classifiers":[
        {
            "category":"Education",
            "subcategory":"School",
            "type":"Public Place"
        }
    ],
    "sg:phone":"+1 450 621 9192",
    "sg:postcode":"J7E 4H4",
    "sg:province":"QC",
    "wof:name":"Pre-Maternelle Lano",
    "wof:placetype":"venue"
},
  "geometry": {"coordinates":[-73.83657100000001,45.603035],"type":"Point"}
}