{
  "type": "Feature",
  "properties": {
    "addr:full":"555 Notre Dame St Belle River ON N0R 1A0",
    "addr:housenumber":"555",
    "addr:postcode":"n0r 1a0",
    "addr:street":"Notre Dame St",
    "iso:country":"CA",
    "sg:address":"555 Notre Dame St",
    "sg:city":"Belle River",
    "sg:classifiers":[
        {
            "category":"Banks & Credit Unions",
            "subcategory":"Bank",
            "type":"Services"
        }
    ],
    "sg:phone":"+1 519 728 1410",
    "sg:postcode":"N0R 1A0",
    "sg:province":"ON",
    "wof:name":"National Bank of Canada",
    "wof:placetype":"venue"
},
  "geometry": {"coordinates":[-82.70893100000001,42.293308],"type":"Point"}
}