{
  "type": "Feature",
  "properties": {
    "addr:full":"4700 50th St Chetwynd BC V0C 1J0",
    "addr:housenumber":"4700",
    "addr:postcode":"bc v0c 1j0",
    "addr:street":"50Th St",
    "iso:country":"CA",
    "sg:address":"4700 50th St",
    "sg:city":"Chetwynd",
    "sg:classifiers":[
        {
            "category":"Manufacturing",
            "subcategory":"Lumber",
            "type":"Manufacturing & Wholesale Goods"
        }
    ],
    "sg:phone":"+1 250 788 2231",
    "sg:postcode":"V0C 1J0",
    "sg:province":"BC",
    "wof:name":"Canadian Forest Products Ltd",
    "wof:placetype":"venue"
},
  "geometry": {"coordinates":[-121.62954711899999,55.7016296387],"type":"Point"}
}