{
  "type": "Feature",
  "properties": {
    "iso:country":"CA",
    "sg:city":"Vancouver",
    "sg:classifiers":[
        {
            "category":"Social Services",
            "type":"Services"
        }
    ],
    "sg:phone":"+1 604 730 1907",
    "sg:postcode":"V6H 1E3",
    "sg:province":"BC",
    "sg:tags":[
        "counselor"
    ],
    "wof:name":"Vision Quest Counselling",
    "wof:placetype":"venue"
},
  "geometry": {"coordinates":[-123.127563477,49.2635650635],"type":"Point"}
}