{
  "type": "Feature",
  "properties": {
    "addr:full":"3849 Hastings St Burnaby BC V5C 2H7",
    "addr:housenumber":"3849",
    "addr:postcode":"v5c 2h7",
    "addr:street":"Hastings St",
    "iso:country":"CA",
    "sg:address":"3849 Hastings St",
    "sg:city":"Burnaby",
    "sg:classifiers":[
        {
            "category":"Retail",
            "subcategory":"Animal Services",
            "type":"Services"
        }
    ],
    "sg:phone":"+1 604 298 3544",
    "sg:postcode":"V5C 2H7",
    "sg:province":"BC",
    "sg:tags":[
        "pet",
        "grooming",
        "washing"
    ],
    "wof:name":"Gladys' Doggy Salon",
    "wof:placetype":"venue"
},
  "geometry": {"coordinates":[-123.019714355,49.2812843323],"type":"Point"}
}