{
  "type": "Feature",
  "properties": {
    "addr:full":"Richmond QC J0B 2H0",
    "addr:postcode":"j0b 2h0",
    "iso:country":"CA",
    "sg:city":"Richmond",
    "sg:classifiers":[
        {
            "category":"Health Services",
            "subcategory":"Hospital",
            "type":"Services"
        }
    ],
    "sg:phone":"+1 819 826 5303",
    "sg:postcode":"J0B 2H0",
    "sg:province":"QC",
    "sg:tags":[
        "mental"
    ],
    "wof:name":"Rivage Du Val St-Francois",
    "wof:placetype":"venue"
},
  "geometry": {"coordinates":[-72.1497421265,45.6679801941],"type":"Point"}
}