{
  "type": "Feature",
  "properties": {
    "iso:country":"CA",
    "sg:address":"346 Rue Chapel",
    "sg:city":"Grand-Sault/Grand Falls",
    "sg:classifiers":[
        {
            "category":"Professional",
            "subcategory":"Lawyer & Legal Services",
            "type":"Services"
        }
    ],
    "sg:phone":"+1 506 473 2221",
    "sg:postcode":"E3Z 2M4",
    "sg:province":"NB",
    "sg:tags":[
        "attorney"
    ],
    "wof:name":"Deschenes, Diane",
    "wof:placetype":"venue"
},
  "geometry": {"coordinates":[-67.74095153810001,47.0450057983],"type":"Point"}
}