{
  "type": "Feature",
  "properties": {
    "addr:full":"RR 1 Freelton ON L0R 1K0",
    "addr:postcode":"l0r 1k0",
    "addr:street":"Rr 1 Freelton",
    "iso:country":"CA",
    "sg:address":"RR 1",
    "sg:city":"Freelton",
    "sg:classifiers":[
        {
            "category":"Wholesale",
            "subcategory":"Machinery & Supplies",
            "type":"Manufacturing & Wholesale Goods"
        }
    ],
    "sg:phone":"+1 905 659 1094",
    "sg:postcode":"L0R 1K0",
    "sg:province":"ON",
    "sg:tags":[
        "farm",
        "equipment"
    ],
    "wof:name":"Regional Tractor Sales Ltd",
    "wof:placetype":"venue"
},
  "geometry": {"coordinates":[-80.0391464233,43.4004554749],"type":"Point"}
}