{
  "type": "Feature",
  "properties": {
    "addr:full":"525 Guelph St Norval ON L0P 1K0",
    "addr:housenumber":"525",
    "addr:postcode":"l0p 1k0",
    "addr:street":"Guelph St",
    "iso:country":"CA",
    "sg:address":"525 Guelph St",
    "sg:city":"Norval",
    "sg:classifiers":[
        {
            "category":"Food & Beverages",
            "subcategory":"Groceries & Convenience Stores",
            "type":"Retail Goods"
        }
    ],
    "sg:phone":"+1 905 873 7104",
    "sg:postcode":"L0P 1K0",
    "sg:province":"ON",
    "wof:name":"Norval Convenience Store",
    "wof:placetype":"venue"
},
  "geometry": {"coordinates":[-79.858459,43.646973],"type":"Point"}
}