{
  "type": "Feature",
  "properties": {
    "addr:full":"Cambridge Station NS B0P 1G0",
    "addr:postcode":"b0p 1g0",
    "addr:street":"Cambridge",
    "iso:country":"CA",
    "sg:city":"Cambridge Station",
    "sg:classifiers":[
        {
            "category":"Home & Garden",
            "subcategory":"Furniture",
            "type":"Retail Goods"
        }
    ],
    "sg:phone":"+1 902 538 8711",
    "sg:postcode":"B0P 1G0",
    "sg:province":"NS",
    "sg:tags":[
        "equipment",
        "kitchen",
        "cabinet"
    ],
    "wof:name":"First Choice Kitchens",
    "wof:placetype":"venue"
},
  "geometry": {"coordinates":[-64.6443481445,45.0558433533],"type":"Point"}
}