{
  "type": "Feature",
  "properties": {
    "addr:full":"7 Rue DE Louvain O Montreal QC H2N 1A3",
    "addr:housenumber":"7",
    "addr:postcode":"h2n 1a3",
    "addr:street":"Rue De Louvain O",
    "iso:country":"CA",
    "sg:address":"7 Rue DE Louvain O",
    "sg:city":"Montreal",
    "sg:classifiers":[
        {
            "category":"Professional",
            "subcategory":"Business Services",
            "type":"Services"
        }
    ],
    "sg:phone":"+1 514 388 6668",
    "sg:postcode":"H2N 1A3",
    "sg:province":"QC",
    "sg:tags":[
        "screen",
        "printing",
        "embroidery"
    ],
    "wof:name":"Zahra Embroidery Inc",
    "wof:placetype":"venue"
},
  "geometry": {"coordinates":[-73.65514400000001,45.545109],"type":"Point"}
}