{
  "type": "Feature",
  "properties": {
    "addr:full":"1135 Lansdowne St W Peterborough ON K9J 7M2",
    "addr:housenumber":"1135",
    "addr:postcode":"k9j 7m2",
    "addr:street":"Lansdowne St W",
    "iso:country":"CA",
    "sg:address":"1135 Lansdowne St W",
    "sg:city":"Peterborough",
    "sg:classifiers":[
        {
            "category":"Shopping",
            "subcategory":"Clothing, Apparel, & Fashions",
            "type":"Retail Goods"
        }
    ],
    "sg:phone":"+1 705 748 9570",
    "sg:postcode":"K9J 7M2",
    "sg:province":"ON",
    "sg:tags":[
        "furnishing"
    ],
    "wof:name":"Mark's Work Wearhouse Ltd",
    "wof:placetype":"venue"
},
  "geometry": {"coordinates":[-78.348732,44.280933],"type":"Point"}
}