{
  "type": "Feature",
  "properties": {
    "iso:country":"CA",
    "sg:address":"14 Highgate Dr",
    "sg:city":"Markham",
    "sg:classifiers":[
        {
            "category":"Social Services",
            "subcategory":"Child Care",
            "type":"Services"
        }
    ],
    "sg:phone":"+1 905 479 9855",
    "sg:postcode":"L3R 3R6",
    "sg:province":"ON",
    "wof:name":"High Birch Child Care",
    "wof:placetype":"venue"
},
  "geometry": {"coordinates":[-79.316055,43.826889],"type":"Point"}
}