{
  "type": "Feature",
  "properties": {
    "iso:country":"CA",
    "sg:city":"Mississauga",
    "sg:classifiers":[
        {
            "category":"Travel",
            "subcategory":"Travel Agent",
            "type":"Entertainment"
        }
    ],
    "sg:phone":"+1 905 565 9299",
    "sg:postcode":"L5T 2K5",
    "sg:province":"ON",
    "sg:tags":[
        "agency",
        "bureau"
    ],
    "wof:name":"Eurojets Inc",
    "wof:placetype":"venue"
},
  "geometry": {"coordinates":[-79.668381,43.664928],"type":"Point"}
}