{
  "type": "Feature",
  "properties": {
    "addr:full":"54 St. Paul St W St Catharines ON L2S 2C2",
    "addr:housenumber":"54",
    "addr:postcode":"l2s 2c2",
    "addr:street":"St. Paul St W",
    "iso:country":"CA",
    "sg:address":"54 St. Paul St W",
    "sg:city":"St Catharines",
    "sg:classifiers":[
        {
            "category":"Personal",
            "subcategory":"Barber",
            "type":"Services"
        }
    ],
    "sg:phone":"+1 905 682 0434",
    "sg:postcode":"L2S 2C2",
    "sg:province":"ON",
    "wof:name":"Hair Quarters",
    "wof:placetype":"venue"
},
  "geometry": {"coordinates":[-79.2496337891,43.1493530273],"type":"Point"}
}