{
  "type": "Feature",
  "properties": {
    "iso:country":"CA",
    "sg:address":"112 Ferrier St",
    "sg:city":"Markham",
    "sg:classifiers":[
        {
            "category":"Manufacturing",
            "subcategory":"Metals",
            "type":"Manufacturing & Wholesale Goods"
        }
    ],
    "sg:phone":"+1 905 474 1675",
    "sg:postcode":"L3R 2Z5",
    "sg:province":"ON",
    "sg:tags":[
        "steel"
    ],
    "wof:name":"Lee Scott Industries Ltd",
    "wof:placetype":"venue"
},
  "geometry": {"coordinates":[-79.3310165405,43.824634552],"type":"Point"}
}