{
  "type": "Feature",
  "properties": {
    "addr:full":"2360 No. 8 Rd Richmond BC V6V 1S1",
    "addr:postcode":"2360;v6v 1s1",
    "addr:street":"8 Rd",
    "iso:country":"CA",
    "sg:address":"2360 No. 8 Rd",
    "sg:city":"Richmond",
    "sg:classifiers":[
        {
            "category":"Building & Trades",
            "subcategory":"Landscaping Services",
            "type":"Services"
        }
    ],
    "sg:phone":"+1 604 273 8750",
    "sg:postcode":"V6V 1S1",
    "sg:province":"BC",
    "sg:tags":[
        "lawn",
        "contractor",
        "landscape",
        "maintenance",
        "grounds"
    ],
    "wof:name":"Coastal Care Gardening Svc Ltd",
    "wof:placetype":"venue"
},
  "geometry": {"coordinates":[-123.024009705,49.1960868835],"type":"Point"}
}