{
  "type": "Feature",
  "properties": {
    "addr:full":"19 James St W Cobourg ON K9A 2J8",
    "addr:housenumber":"19",
    "addr:postcode":"k9a 2j8",
    "addr:street":"James St W",
    "iso:country":"CA",
    "sg:address":"19 James St W",
    "sg:city":"Cobourg",
    "sg:classifiers":[
        {
            "category":"Health Services",
            "subcategory":"Nursing And Care Facility",
            "type":"Services"
        }
    ],
    "sg:phone":"+1 905 372 0163",
    "sg:postcode":"K9A 2J8",
    "sg:province":"ON",
    "sg:tags":[
        "home",
        "rest"
    ],
    "wof:name":"Streamway Villa Nursing Home",
    "wof:placetype":"venue"
},
  "geometry": {"coordinates":[-78.16783100000001,43.962299],"type":"Point"}
}