{
  "type": "Feature",
  "properties": {
    "addr:full":"150 Argyle Ave Ottawa ON K2P 1B7",
    "addr:housenumber":"150",
    "addr:postcode":"k2p 1b7",
    "addr:street":"Argyle Ave",
    "iso:country":"CA",
    "sg:address":"150 Argyle Ave",
    "sg:city":"Ottawa",
    "sg:classifiers":[
        {
            "category":"Real Estate",
            "subcategory":"Real Estate Operator",
            "type":"Services"
        }
    ],
    "sg:phone":"+1 613 235 1281",
    "sg:postcode":"K2P 1B7",
    "sg:province":"ON",
    "sg:tags":[
        "apartment"
    ],
    "wof:name":"Windsor Arms",
    "wof:placetype":"venue"
},
  "geometry": {"coordinates":[-75.6882781982,45.4120941162],"type":"Point"}
}