{
  "type": "Feature",
  "properties": {
    "addr:full":"1 Marine Dr Harbour Breton NL A0H 1P0",
    "addr:housenumber":"1",
    "addr:postcode":"a0h 1p0",
    "addr:street":"Marine Dr",
    "iso:country":"CA",
    "sg:address":"1 Marine Dr",
    "sg:city":"Harbour Breton",
    "sg:classifiers":[
        {
            "category":"Home & Garden",
            "subcategory":"Hardware",
            "type":"Retail Goods"
        }
    ],
    "sg:phone":"+1 709 885 2278",
    "sg:postcode":"A0H 1P0",
    "sg:province":"NL",
    "wof:name":"Jackman's Home Ctr",
    "wof:placetype":"venue"
},
  "geometry": {"coordinates":[-55.8215065002,47.469493866],"type":"Point"}
}