{
  "type": "Feature",
  "properties": {
    "addr:full":"Etobicoke ON M9W 5T6",
    "addr:postcode":"m9w 5t6",
    "iso:country":"CA",
    "sg:city":"Etobicoke",
    "sg:classifiers":[
        {
            "category":"Home & Garden",
            "subcategory":"Carpets & Floor Coverings",
            "type":"Retail Goods"
        }
    ],
    "sg:phone":"+1 416 679 8104",
    "sg:postcode":"M9W 5T6",
    "sg:province":"ON",
    "sg:tags":[
        "dealer",
        "rug"
    ],
    "wof:name":"North Wood Carpet & Tile CO",
    "wof:placetype":"venue"
},
  "geometry": {"coordinates":[-79.619148,43.740353],"type":"Point"}
}