{
  "type": "Feature",
  "properties": {
    "addr:full":"Kelowna BC V1Z 2S9",
    "addr:postcode":"v1z 2s9",
    "iso:country":"CA",
    "sg:city":"Kelowna",
    "sg:classifiers":[
        {
            "category":"Retail",
            "subcategory":"Repair Shop",
            "type":"Services"
        }
    ],
    "sg:phone":"+1 250 769 6691",
    "sg:postcode":"V1Z 2S9",
    "sg:province":"BC",
    "sg:tags":[
        "refinishing",
        "furniture"
    ],
    "wof:name":"Westside Refinishing",
    "wof:placetype":"venue"
},
  "geometry": {"coordinates":[-119.572189331,49.8661994934],"type":"Point"}
}