{
  "type": "Feature",
  "properties": {
    "addr:full":"2600 Boul Saint-Joseph E #204 Montreal QC H1Y 2A4",
    "addr:housenumber":"2600",
    "addr:postcode":"h1y 2a4",
    "addr:street":"Boul Saint-Joseph E # 204",
    "iso:country":"CA",
    "sg:address":"2600 Boul Saint-Joseph E #204",
    "sg:city":"Montreal",
    "sg:classifiers":[
        {
            "category":"Professional",
            "subcategory":"Research",
            "type":"Services"
        }
    ],
    "sg:phone":"+1 514 523 5325",
    "sg:postcode":"H1Y 2A4",
    "sg:province":"QC",
    "sg:tags":[
        "foundation",
        "philanthropic"
    ],
    "wof:name":"Fondation Des Pompiers Du QC",
    "wof:placetype":"venue"
},
  "geometry": {"coordinates":[-73.571647644,45.5436096191],"type":"Point"}
}