{
  "type": "Feature",
  "properties": {
    "addr:full":"464 Rue Saint-Jean Gatineau QC J8P 5Y7",
    "addr:housenumber":"464",
    "addr:postcode":"j8p 5y7",
    "addr:street":"Rue Saint-Jean",
    "iso:country":"CA",
    "sg:address":"464 Rue Saint-Jean",
    "sg:city":"Gatineau",
    "sg:classifiers":[
        {
            "category":"Banks & Credit Unions",
            "subcategory":"Investment Brokerage",
            "type":"Services"
        }
    ],
    "sg:phone":"+1 819 669 0344",
    "sg:postcode":"J8P 5Y7",
    "sg:province":"QC",
    "sg:tags":[
        "advisory",
        "financial"
    ],
    "wof:name":"Assurances Jean-Pierre Bernard",
    "wof:placetype":"venue"
},
  "geometry": {"coordinates":[-75.661102,45.494007],"type":"Point"}
}