{
  "type": "Feature",
  "properties": {
    "addr:full":"801 Rue Fleury E Montreal QC H2C 1P3",
    "addr:housenumber":"801",
    "addr:postcode":"h2c 1p3",
    "addr:street":"Rue Fleury E",
    "iso:country":"CA",
    "sg:address":"801 Rue Fleury E",
    "sg:city":"Montreal",
    "sg:classifiers":[
        {
            "category":"Manufacturing",
            "subcategory":"Printing",
            "type":"Manufacturing & Wholesale Goods"
        }
    ],
    "sg:phone":"+1 514 383 4133",
    "sg:postcode":"H2C 1P3",
    "sg:province":"QC",
    "sg:tags":[
        "printer"
    ],
    "wof:name":"Industries Pvb",
    "wof:placetype":"venue"
},
  "geometry": {"coordinates":[-73.660248,45.556435],"type":"Point"}
}