{
  "type": "Feature",
  "properties": {
    "iso:country":"CA",
    "sg:address":"PO Box 254",
    "sg:city":"Norman Wells",
    "sg:classifiers":[
        {
            "category":"Building & Trades",
            "subcategory":"Equipment Rental",
            "type":"Services"
        }
    ],
    "sg:phone":"+1 867 587 2827",
    "sg:postcode":"X0E 0V0",
    "sg:province":"NT",
    "sg:tags":[
        "aircraft",
        "leasing",
        "charter"
    ],
    "wof:name":"Sahtu Helicopters",
    "wof:placetype":"venue"
},
  "geometry": {"coordinates":[-126.706687927,65.30633544920001],"type":"Point"}
}