{
  "type": "Feature",
  "properties": {
    "iso:country":"CA",
    "sg:address":"262 Mud St",
    "sg:city":"Grassie",
    "sg:classifiers":[
        {
            "category":"Education",
            "subcategory":"Special Training",
            "type":"Public Place"
        }
    ],
    "sg:phone":"+1 905 945 6161",
    "sg:postcode":"L0R 1M0",
    "sg:province":"ON",
    "sg:tags":[
        "aircraft",
        "school"
    ],
    "wof:name":"Grimsby Aviation",
    "wof:placetype":"venue"
},
  "geometry": {"coordinates":[-79.607711792,43.154006958],"type":"Point"}
}