{
  "type": "Feature",
  "properties": {
    "addr:full":"142 28th St Brandon MB R7B 2G3",
    "addr:housenumber":"142",
    "addr:postcode":"r7b 2g3",
    "addr:street":"28Th St",
    "iso:country":"CA",
    "sg:address":"142 28th St",
    "sg:city":"Brandon",
    "sg:classifiers":[
        {
            "category":"Social Services",
            "subcategory":"Child Care",
            "type":"Services"
        }
    ],
    "sg:phone":"+1 204 727 8080",
    "sg:postcode":"R7B 2G3",
    "sg:province":"MB",
    "sg:tags":[
        "kindergarten",
        "academic",
        "school"
    ],
    "wof:name":"Wee Wisdom Nursery School",
    "wof:placetype":"venue"
},
  "geometry": {"coordinates":[-99.97616600000001,49.847797],"type":"Point"}
}