{
  "type": "Feature",
  "properties": {
    "addr:full":"3801 42nd Ave S Cranbrook BC V1C 6Z8",
    "addr:housenumber":"3801",
    "addr:postcode":"bc v1c 6z8",
    "addr:street":"42Nd Ave S",
    "iso:country":"CA",
    "sg:address":"3801 42nd Ave S",
    "sg:city":"Cranbrook",
    "sg:classifiers":[
        {
            "category":"Retail",
            "subcategory":"Auto Repair",
            "type":"Services"
        }
    ],
    "sg:phone":"+1 250 489 2126",
    "sg:postcode":"V1C 6Z8",
    "sg:province":"BC",
    "sg:tags":[
        "repairing",
        "automobile"
    ],
    "wof:name":"Jrt Auto & Marine",
    "wof:placetype":"venue"
},
  "geometry": {"coordinates":[-115.7687,49.5135],"type":"Point"}
}