{
  "type": "Feature",
  "properties": {
    "addr:full":"Montreal QC H2B 1K4",
    "addr:postcode":"h2b 1k4",
    "iso:country":"CA",
    "sg:city":"Montreal",
    "sg:classifiers":[
        {
            "category":"Health Services",
            "subcategory":"Medical Lab",
            "type":"Services"
        }
    ],
    "sg:phone":"+1 514 381 4214",
    "sg:postcode":"H2B 1K4",
    "sg:province":"QC",
    "wof:name":"Breard, Serge",
    "wof:placetype":"venue"
},
  "geometry": {"coordinates":[-73.64960499999999,45.572903],"type":"Point"}
}