{
  "type": "Feature",
  "properties": {
    "addr:full":"6325 Mississauga Rd Mississauga ON L5N 1A5",
    "addr:housenumber":"6325",
    "addr:postcode":"l5n 1a5",
    "addr:street":"Mississauga Rd",
    "iso:country":"CA",
    "sg:address":"6325 Mississauga Rd",
    "sg:city":"Mississauga",
    "sg:classifiers":[
        {
            "category":"Retail",
            "subcategory":"Auto Rental",
            "type":"Services"
        }
    ],
    "sg:phone":"+1 905 826 8388",
    "sg:postcode":"L5N 1A5",
    "sg:province":"ON",
    "sg:tags":[
        "renting",
        "automobile"
    ],
    "wof:name":"Discount Car & Truck Rentals",
    "wof:placetype":"venue"
},
  "geometry": {"coordinates":[-79.731514,43.595051],"type":"Point"}
}