{
  "type": "Feature",
  "properties": {
    "iso:country":"CA",
    "sg:address":"711 Waterloo Row",
    "sg:city":"Fredericton",
    "sg:classifiers":[
        {
            "category":"Professional",
            "subcategory":"Secretarial Services",
            "type":"Services"
        }
    ],
    "sg:phone":"+1 506 451 1112",
    "sg:postcode":"E3B 1Z6",
    "sg:province":"NB",
    "sg:tags":[
        "convention",
        "court",
        "reporter"
    ],
    "wof:name":"P Lynch Enterprises",
    "wof:placetype":"venue"
},
  "geometry": {"coordinates":[-66.631866,45.941654],"type":"Point"}
}