{
  "type": "Feature",
  "properties": {
    "iso:country":"CA",
    "sg:address":"PO Box 1794",
    "sg:city":"High Prairie",
    "sg:classifiers":[
        {
            "category":"Building & Trades",
            "subcategory":"Plumbing",
            "type":"Services"
        }
    ],
    "sg:phone":"+1 780 523 4648",
    "sg:postcode":"T0G 1E0",
    "sg:province":"AB",
    "sg:tags":[
        "contractor"
    ],
    "wof:name":"D & C Plbg Htg-Gsftng",
    "wof:placetype":"venue"
},
  "geometry": {"coordinates":[-116.48042297400001,55.4328842163],"type":"Point"}
}