{
  "type": "Feature",
  "properties": {
    "addr:full":"80 Costa Rd Concord ON L4K 1N2",
    "addr:housenumber":"80",
    "addr:postcode":"l4k 1n2",
    "addr:street":"Costa Rd",
    "iso:country":"CA",
    "sg:address":"80 Costa Rd",
    "sg:city":"Concord",
    "sg:classifiers":[
        {
            "category":"Building & Trades",
            "subcategory":"Construction",
            "type":"Services"
        }
    ],
    "sg:phone":"+1 905 669 5923",
    "sg:postcode":"L4K 1N2",
    "sg:province":"ON",
    "sg:tags":[
        "excavating",
        "contractor"
    ],
    "wof:name":"Dynex Excavating Contractors",
    "wof:placetype":"venue"
},
  "geometry": {"coordinates":[-79.51467100000001,43.794628],"type":"Point"}
}