{
  "type": "Feature",
  "properties": {
    "addr:full":"404 Henry St Victoria BC V9A 3J4",
    "addr:housenumber":"404",
    "addr:postcode":"v9a 3j4",
    "addr:street":"Henry St",
    "iso:country":"CA",
    "sg:address":"404 Henry St",
    "sg:city":"Victoria",
    "sg:classifiers":[
        {
            "category":"Real Estate",
            "subcategory":"Architect",
            "type":"Services"
        }
    ],
    "sg:phone":"+1 250 383 6874",
    "sg:postcode":"V9A 3J4",
    "sg:province":"BC",
    "wof:name":"Hodgson, Alan J",
    "wof:placetype":"venue"
},
  "geometry": {"coordinates":[-123.386154,48.432114],"type":"Point"}
}