{
  "type": "Feature",
  "properties": {
    "iso:country":"CA",
    "sg:address":"580 Rue Saint-Georges",
    "sg:city":"Saint-Jerome",
    "sg:classifiers":[
        {
            "category":"Organizations",
            "subcategory":"Professional Association",
            "type":"Services"
        }
    ],
    "sg:phone":"+1 450 431 3437",
    "sg:postcode":"J7Z 5B8",
    "sg:province":"QC",
    "wof:name":"Caphpl",
    "wof:placetype":"venue"
},
  "geometry": {"coordinates":[-74.00178527830001,45.7835044861],"type":"Point"}
}