{
  "type": "Feature",
  "properties": {
    "iso:country":"CA",
    "sg:city":"Ottawa",
    "sg:classifiers":[
        {
            "category":"Shopping",
            "subcategory":"Jewelry",
            "type":"Retail Goods"
        }
    ],
    "sg:phone":"+1 613 238 1886",
    "sg:postcode":"K1N 9J7",
    "sg:province":"ON",
    "sg:tags":[
        "jeweler"
    ],
    "wof:name":"Jubilee Fine Jewellers",
    "wof:placetype":"venue"
},
  "geometry": {"coordinates":[-75.6917648315,45.4444313049],"type":"Point"}
}