{
  "type": "Feature",
  "properties": {
    "addr:full":"980 Pape Ave East York ON M4K 3V7",
    "addr:housenumber":"980",
    "addr:postcode":"m4k 3v7",
    "addr:street":"Pape Ave",
    "iso:country":"CA",
    "sg:address":"980 Pape Ave",
    "sg:city":"East York",
    "sg:classifiers":[
        {
            "category":"Personal",
            "subcategory":"Beauty Salon",
            "type":"Services"
        }
    ],
    "sg:phone":"+1 416 424 4572",
    "sg:postcode":"M4K 3V7",
    "sg:province":"ON",
    "wof:name":"Hair Cutters Unisex",
    "wof:placetype":"venue"
},
  "geometry": {"coordinates":[-79.3484115601,43.6878623962],"type":"Point"}
}