{
  "type": "Feature",
  "properties": {
    "addr:full":"Maple Creek SK S0N 1N0",
    "addr:postcode":"s0n 1n0",
    "addr:street":"Maple Creek",
    "iso:country":"CA",
    "sg:city":"Maple Creek",
    "sg:classifiers":[
        {
            "category":"Organizations",
            "subcategory":"Community Association",
            "type":"Services"
        }
    ],
    "sg:phone":"+1 306 662 3660",
    "sg:postcode":"S0N 1N0",
    "sg:province":"SK",
    "sg:tags":[
        "native"
    ],
    "wof:name":"Nikaneet Band Office",
    "wof:placetype":"venue"
},
  "geometry": {"coordinates":[-109.480407715,49.9065856934],"type":"Point"}
}