{
  "type": "Feature",
  "properties": {
    "addr:full":"Burlington ON L7P 3N8",
    "addr:postcode":"l7p 3n8",
    "iso:country":"CA",
    "sg:city":"Burlington",
    "sg:classifiers":[
        {
            "category":"Shopping",
            "subcategory":"Tobacco",
            "type":"Retail Goods"
        }
    ],
    "sg:phone":"+1 905 335 8946",
    "sg:postcode":"L7P 3N8",
    "sg:province":"ON",
    "sg:tags":[
        "cigarette",
        "cigar",
        "dealer"
    ],
    "wof:name":"Brant Smoke & Gift",
    "wof:placetype":"venue"
},
  "geometry": {"coordinates":[-79.8414840698,43.3555603027],"type":"Point"}
}