{
  "type": "Feature",
  "properties": {
    "addr:full":"Saint-Anaclet QC G0K 1H0",
    "addr:postcode":"g0k 1h0",
    "iso:country":"CA",
    "sg:city":"Saint-Anaclet",
    "sg:classifiers":[
        {
            "category":"Building & Trades",
            "subcategory":"Construction",
            "type":"Services"
        }
    ],
    "sg:phone":"+1 418 723 8648",
    "sg:postcode":"G0K 1H0",
    "sg:province":"QC",
    "sg:tags":[
        "concrete",
        "contractor"
    ],
    "wof:name":"Tremblay, Laurent",
    "wof:placetype":"venue"
},
  "geometry": {"coordinates":[-68.409882,48.466511],"type":"Point"}
}