{
  "type": "Feature",
  "properties": {
    "addr:full":"994 Dundas St W Toronto ON M6J 1W6",
    "addr:housenumber":"994",
    "addr:postcode":"m6j 1w6",
    "addr:street":"Dundas St W",
    "iso:country":"CA",
    "sg:address":"994 Dundas St W",
    "sg:city":"Toronto",
    "sg:classifiers":[
        {
            "category":"Personal",
            "subcategory":"Beauty Salon",
            "type":"Services"
        }
    ],
    "sg:phone":"+1 416 533 2767",
    "sg:postcode":"M6J 1W6",
    "sg:province":"ON",
    "wof:name":"Lucy's Coiffure Salon",
    "wof:placetype":"venue"
},
  "geometry": {"coordinates":[-79.415436,43.650536],"type":"Point"}
}