{
  "type": "Feature",
  "properties": {
    "addr:full":"536 19th St E Prince Albert SK S6V 1K2",
    "addr:housenumber":"536",
    "addr:postcode":"s6v 1k2",
    "addr:street":"19Th St",
    "iso:country":"CA",
    "sg:address":"536 19th St E",
    "sg:city":"Prince Albert",
    "sg:classifiers":[
        {
            "category":"Shopping",
            "subcategory":"Clothing, Apparel, & Fashions",
            "type":"Retail Goods"
        }
    ],
    "sg:phone":"+1 306 764 2100",
    "sg:postcode":"S6V 1K2",
    "sg:province":"SK",
    "sg:tags":[
        "t"
    ],
    "wof:name":"New Impressions Ltd",
    "wof:placetype":"venue"
},
  "geometry": {"coordinates":[-105.739967346,53.196056366],"type":"Point"}
}