{
  "type": "Feature",
  "properties": {
    "addr:full":"9030 Rue Champ D'Eau Saint-Leonard QC H1P 3M4",
    "addr:housenumber":"9030",
    "addr:postcode":"h1p 3m4",
    "addr:street":"Rue Champ D'Eau",
    "iso:country":"CA",
    "sg:address":"9030 Rue Champ D'Eau",
    "sg:city":"Saint-Leonard",
    "sg:classifiers":[
        {
            "category":"Autos & Motor Vehicles",
            "subcategory":"Auto Supplies",
            "type":"Retail Goods"
        }
    ],
    "sg:phone":"+1 514 323 9960",
    "sg:postcode":"H1P 3M4",
    "sg:province":"QC",
    "sg:tags":[
        "automobile",
        "parts"
    ],
    "wof:name":"Pieces D'Autos Lavoisier Inc",
    "wof:placetype":"venue"
},
  "geometry": {"coordinates":[-73.5953369141,45.589389801],"type":"Point"}
}