{
  "type": "Feature",
  "properties": {
    "addr:full":"28592 Centre Rd Strathroy ON N7G 3H6",
    "addr:housenumber":"28592",
    "addr:postcode":"n7g 3h6",
    "addr:street":"Centre Rd",
    "iso:country":"CA",
    "sg:address":"28592 Centre Rd",
    "sg:city":"Strathroy",
    "sg:classifiers":[
        {
            "category":"Home & Garden",
            "subcategory":"Furniture",
            "type":"Retail Goods"
        }
    ],
    "sg:phone":"+1 519 245 1206",
    "sg:postcode":"N7G 3H6",
    "sg:province":"ON",
    "sg:tags":[
        "builder",
        "custom"
    ],
    "wof:name":"Vandercraft Furniture Ltd",
    "wof:placetype":"venue"
},
  "geometry": {"coordinates":[-81.622299,42.955772],"type":"Point"}
}