{
  "type": "Feature",
  "properties": {
    "iso:country":"CA",
    "sg:address":"4000 Steeles Ave W",
    "sg:city":"Woodbridge",
    "sg:classifiers":[
        {
            "category":"Building & Trades",
            "subcategory":"Plumbing",
            "type":"Services"
        }
    ],
    "sg:phone":"+1 905 264 1241",
    "sg:postcode":"L4L 4V9",
    "sg:province":"ON",
    "sg:tags":[
        "contractor"
    ],
    "wof:name":"Camar Mechanical Inc",
    "wof:placetype":"venue"
},
  "geometry": {"coordinates":[-79.551041,43.769485],"type":"Point"}
}