{
  "type": "Feature",
  "properties": {
    "addr:full":"Nelson BC V1L 4H6",
    "addr:postcode":"bc v1l 4h6",
    "iso:country":"CA",
    "sg:city":"Nelson",
    "sg:classifiers":[
        {
            "category":"Banks & Credit Unions",
            "subcategory":"Investment Brokerage",
            "type":"Services"
        }
    ],
    "sg:phone":"+1 250 354 1822",
    "sg:postcode":"V1L 4H6",
    "sg:province":"BC",
    "wof:name":"Money Concepts",
    "wof:placetype":"venue"
},
  "geometry": {"coordinates":[-117.295890808,49.4914245605],"type":"Point"}
}