{
  "type": "Feature",
  "properties": {
    "addr:full":"Orangeville ON L9W 3X3",
    "addr:postcode":"l9w 3x3",
    "iso:country":"CA",
    "sg:city":"Orangeville",
    "sg:classifiers":[
        {
            "category":"Health Services",
            "subcategory":"Podiatrist",
            "type":"Services"
        }
    ],
    "sg:phone":"+1 519 942 4705",
    "sg:postcode":"L9W 3X3",
    "sg:province":"ON",
    "wof:name":"Foot Clinic",
    "wof:placetype":"venue"
},
  "geometry": {"coordinates":[-80.1004562378,43.920791626],"type":"Point"}
}