{
  "type": "Feature",
  "properties": {
    "addr:full":"Cap-Chat QC G0J 1E0",
    "addr:postcode":"g0j 1e0",
    "iso:country":"CA",
    "sg:city":"Cap-Chat",
    "sg:classifiers":[
        {
            "category":"Government",
            "subcategory":"Office",
            "type":"Public Place"
        }
    ],
    "sg:phone":"+1 418 786 5538",
    "sg:postcode":"G0J 1E0",
    "sg:province":"QC",
    "sg:tags":[
        "village"
    ],
    "wof:name":"Cap-Chat Caserne DE Pompiers",
    "wof:placetype":"venue"
},
  "geometry": {"coordinates":[-66.6837768555,49.0977554321],"type":"Point"}
}