{
  "type": "Feature",
  "properties": {
    "addr:full":"178 Guelph St Georgetown ON L7G 4A7",
    "addr:housenumber":"178",
    "addr:postcode":"l7g 4a7",
    "addr:street":"Guelph St",
    "iso:country":"CA",
    "sg:address":"178 Guelph St",
    "sg:city":"Georgetown",
    "sg:classifiers":[
        {
            "category":"Retail",
            "subcategory":"Auto Repair",
            "type":"Services"
        }
    ],
    "sg:phone":"+1 905 873 1621",
    "sg:postcode":"L7G 4A7",
    "sg:province":"ON",
    "sg:tags":[
        "repairing",
        "automobile"
    ],
    "wof:name":"Midas Auto Svc Experts",
    "wof:placetype":"venue"
},
  "geometry": {"coordinates":[-79.907478,43.65033],"type":"Point"}
}