{
  "type": "Feature",
  "properties": {
    "iso:country":"CA",
    "sg:address":"3100 Rue Saint-Prosper",
    "sg:city":"Saint-Hyacinthe",
    "sg:classifiers":[
        {
            "category":"Freight",
            "type":"Transportation"
        }
    ],
    "sg:phone":"+1 450 773 9565",
    "sg:postcode":"J2S 2A4",
    "sg:province":"QC",
    "sg:tags":[
        "warehouse",
        "storage"
    ],
    "wof:name":"Frigo Royal Inc",
    "wof:placetype":"venue"
},
  "geometry": {"coordinates":[-72.96492004389999,45.6223983765],"type":"Point"}
}