{
  "type": "Feature",
  "properties": {
    "addr:full":"504 Railway Ave Glenboro MB R0K 0X0",
    "addr:housenumber":"504",
    "addr:postcode":"r0k 0x0",
    "addr:street":"Railway Ave",
    "iso:country":"CA",
    "sg:address":"504 Railway Ave",
    "sg:city":"Glenboro",
    "sg:classifiers":[
        {
            "category":"Shopping",
            "subcategory":"Pharmacy",
            "type":"Retail Goods"
        }
    ],
    "sg:phone":"+1 204 827 2841",
    "sg:postcode":"R0K 0X0",
    "sg:province":"MB",
    "wof:name":"Glenboro Pharmacy",
    "wof:placetype":"venue"
},
  "geometry": {"coordinates":[-99.28044128419999,49.55493927],"type":"Point"}
}