{
  "type": "Feature",
  "properties": {
    "addr:full":"8885 Woodbine Ave Markham ON L3R 5G1",
    "addr:housenumber":"8885",
    "addr:postcode":"l3r 5g1",
    "addr:street":"Woodbine Ave",
    "iso:country":"CA",
    "sg:address":"8885 Woodbine Ave",
    "sg:city":"Markham",
    "sg:classifiers":[
        {
            "category":"Wholesale",
            "subcategory":"Non-durable Goods",
            "type":"Manufacturing & Wholesale Goods"
        }
    ],
    "sg:phone":"+1 905 470 8883",
    "sg:postcode":"L3R 5G1",
    "sg:province":"ON",
    "sg:tags":[
        "novelty"
    ],
    "wof:name":"Thinkway Toys",
    "wof:placetype":"venue"
},
  "geometry": {"coordinates":[-79.3627624512,43.867931366],"type":"Point"}
}