{
  "type": "Feature",
  "properties": {
    "addr:full":"5124 Montrose Rd Niagara Falls ON L2H 1K5",
    "addr:housenumber":"5124",
    "addr:postcode":"l2h 1k5",
    "addr:street":"Montrose Rd",
    "iso:country":"CA",
    "sg:address":"5124 Montrose Rd",
    "sg:city":"Niagara Falls",
    "sg:classifiers":[
        {
            "category":"Wholesale",
            "subcategory":"Electrical",
            "type":"Manufacturing & Wholesale Goods"
        }
    ],
    "sg:phone":"+1 905 357 9999",
    "sg:postcode":"L2H 1K5",
    "sg:province":"ON",
    "sg:tags":[
        "hardware",
        "equipment",
        "electric"
    ],
    "wof:name":"Torbram Electric Supply",
    "wof:placetype":"venue"
},
  "geometry": {"coordinates":[-79.1237106323,43.099193573],"type":"Point"}
}