{
  "type": "Feature",
  "properties": {
    "addr:full":"519 Route 785 Utopia NB E5C 2K3",
    "addr:housenumber":"519",
    "addr:postcode":"e5c 2k3",
    "addr:street":"Route 785",
    "iso:country":"CA",
    "sg:address":"519 Route 785",
    "sg:city":"Utopia",
    "sg:classifiers":[
        {
            "category":"Food & Beverages",
            "subcategory":"Groceries & Convenience Stores",
            "type":"Retail Goods"
        }
    ],
    "sg:phone":"+1 506 755 3500",
    "sg:postcode":"E5C 2K3",
    "sg:province":"NB",
    "wof:name":"Utopia Convenience Store",
    "wof:placetype":"venue"
},
  "geometry": {"coordinates":[-66.77666473390001,45.1467552185],"type":"Point"}
}