{
  "type": "Feature",
  "properties": {
    "iso:country":"CA",
    "sg:address":"4853 Highway 3",
    "sg:city":"Glenwood",
    "sg:classifiers":[
        {
            "category":"Manufacturing",
            "subcategory":"Watercraft",
            "type":"Manufacturing & Wholesale Goods"
        }
    ],
    "sg:phone":"+1 902 643 2699",
    "sg:postcode":"B0W 1W0",
    "sg:province":"NS",
    "sg:tags":[
        "dealer",
        "boat",
        "sales"
    ],
    "wof:name":"Carmarc Marine Svc",
    "wof:placetype":"venue"
},
  "geometry": {"coordinates":[-65.878616333,43.7930984497],"type":"Point"}
}