{
  "type": "Feature",
  "properties": {
    "addr:full":"143 Victoria Rd Lunenburg NS B0J 2C0",
    "addr:housenumber":"143",
    "addr:postcode":"b0j 2c0",
    "addr:street":"Victoria Rd",
    "iso:country":"CA",
    "sg:address":"143 Victoria Rd",
    "sg:city":"Lunenburg",
    "sg:classifiers":[
        {
            "category":"Food & Beverages",
            "subcategory":"Groceries & Convenience Stores",
            "type":"Retail Goods"
        }
    ],
    "sg:phone":"+1 902 634 3751",
    "sg:postcode":"B0J 2C0",
    "sg:province":"NS",
    "sg:tags":[
        "grocer"
    ],
    "wof:name":"Lunenburg Save Easy",
    "wof:placetype":"venue"
},
  "geometry": {"coordinates":[-64.325363,44.375774],"type":"Point"}
}