{
  "type": "Feature",
  "properties": {
    "addr:full":"1358 Hawthorne Dr Sudbury ON P3A 1K9",
    "addr:housenumber":"1358",
    "addr:postcode":"p3a 1k9",
    "addr:street":"Hawthorne Dr",
    "iso:country":"CA",
    "sg:address":"1358 Hawthorne Dr",
    "sg:city":"Sudbury",
    "sg:classifiers":[
        {
            "category":"Professional",
            "subcategory":"Advertising",
            "type":"Services"
        }
    ],
    "sg:phone":"+1 705 560 6766",
    "sg:postcode":"P3A 1K9",
    "sg:province":"ON",
    "wof:name":"Northern Homes Real Estate",
    "wof:placetype":"venue"
},
  "geometry": {"coordinates":[-80.94589999999999,46.515423],"type":"Point"}
}