{
  "type": "Feature",
  "properties": {
    "iso:country":"CA",
    "sg:address":"PO Box 23 STN Main",
    "sg:city":"Parksville",
    "sg:classifiers":[
        {
            "category":"Building & Trades",
            "subcategory":"Cleaning & Sanitation",
            "type":"Services"
        }
    ],
    "sg:phone":"+1 250 752 1575",
    "sg:postcode":"V9P 2G3",
    "sg:province":"BC",
    "sg:tags":[
        "janitor"
    ],
    "wof:name":"R & G Cleaning Svc",
    "wof:placetype":"venue"
},
  "geometry": {"coordinates":[-124.31364440900001,49.3196907043],"type":"Point"}
}