{
  "type": "Feature",
  "properties": {
    "addr:full":"Oshawa ON L1J 2K1",
    "addr:postcode":"l1j 2k1",
    "iso:country":"CA",
    "sg:city":"Oshawa",
    "sg:classifiers":[
        {
            "category":"Health Services",
            "subcategory":"Doctor",
            "type":"Services"
        }
    ],
    "sg:phone":"+1 905 725 8632",
    "sg:postcode":"L1J 2K1",
    "sg:province":"ON",
    "sg:tags":[
        "physician",
        "surgeon"
    ],
    "wof:name":"Cha, James MD",
    "wof:placetype":"venue"
},
  "geometry": {"coordinates":[-78.8747711182,43.8951683044],"type":"Point"}
}