{
  "type": "Feature",
  "properties": {
    "iso:country":"CA",
    "sg:address":"401 Main St",
    "sg:city":"Kentville",
    "sg:classifiers":[
        {
            "category":"Health Services",
            "subcategory":"Medical Lab",
            "type":"Services"
        }
    ],
    "sg:phone":"+1 902 678 2521",
    "sg:postcode":"B4N 1K7",
    "sg:province":"NS",
    "wof:name":"Valley Denture Svc Ltd",
    "wof:placetype":"venue"
},
  "geometry": {"coordinates":[-64.4905166626,45.075756073],"type":"Point"}
}