{
  "type": "Feature",
  "properties": {
    "addr:full":"471 Warner Rd Niagara on the Lake ON L0S 1J0",
    "addr:housenumber":"471",
    "addr:postcode":"l0s 1j0",
    "addr:street":"Warner Rd;On",
    "iso:country":"CA",
    "sg:address":"471 Warner Rd",
    "sg:city":"Niagara on the Lake",
    "sg:classifiers":[
        {
            "category":"Recreation",
            "type":"Entertainment"
        }
    ],
    "sg:phone":"+1 905 262 5101",
    "sg:postcode":"L0S 1J0",
    "sg:province":"ON",
    "sg:tags":[
        "riding",
        "amusement",
        "academy"
    ],
    "wof:name":"Niagara Riding Stables",
    "wof:placetype":"venue"
},
  "geometry": {"coordinates":[-79.1283569336,43.1513252258],"type":"Point"}
}