{
  "type": "Feature",
  "properties": {
    "addr:full":"Montauban QC G0X 1W0",
    "addr:postcode":"g0x 1w0",
    "iso:country":"CA",
    "sg:city":"Montauban",
    "sg:classifiers":[
        {
            "category":"Wholesale",
            "subcategory":"Machinery & Supplies",
            "type":"Manufacturing & Wholesale Goods"
        }
    ],
    "sg:phone":"+1 418 336 2383",
    "sg:postcode":"G0X 1W0",
    "sg:province":"QC",
    "sg:tags":[
        "chains"
    ],
    "wof:name":"Ubartas, Victor",
    "wof:placetype":"venue"
},
  "geometry": {"coordinates":[-72.3096618652,46.876411438],"type":"Point"}
}