{
  "type": "Feature",
  "properties": {
    "addr:full":"PO Box 720 Blairmore AB T0K 0E0",
    "addr:housenumber":"po",
    "addr:postcode":"t0k 0e0",
    "addr:street":"Box 720",
    "iso:country":"CA",
    "sg:address":"PO Box 720",
    "sg:city":"Blairmore",
    "sg:classifiers":[
        {
            "category":"Organizations",
            "subcategory":"Religious Organization",
            "type":"Services"
        }
    ],
    "sg:phone":"+1 403 562 3537",
    "sg:postcode":"T0K 0E0",
    "sg:province":"AB",
    "sg:tags":[
        "church"
    ],
    "wof:name":"Community Christian Centre",
    "wof:placetype":"venue"
},
  "geometry": {"coordinates":[-114.436981,49.607658],"type":"Point"}
}