{
  "type": "Feature",
  "properties": {
    "addr:full":"10066 156 St NW Edmonton AB T5P 2P8",
    "addr:housenumber":"10066",
    "addr:postcode":"t5p 2p8",
    "addr:street":"156 St Nw",
    "iso:country":"CA",
    "sg:address":"10066 156 St NW",
    "sg:city":"Edmonton",
    "sg:classifiers":[
        {
            "category":"Shopping",
            "subcategory":"Music",
            "type":"Retail Goods"
        }
    ],
    "sg:phone":"+1 780 481 4767",
    "sg:postcode":"T5P 2P8",
    "sg:province":"AB",
    "sg:tags":[
        "compact",
        "record",
        "disc",
        "tape"
    ],
    "wof:name":"Just For Fun",
    "wof:placetype":"venue"
},
  "geometry": {"coordinates":[-113.59055328399999,53.5407562256],"type":"Point"}
}