{
  "type": "Feature",
  "properties": {
    "addr:full":"1597 Bedford Hwy Bedford NS B4A 1E7",
    "addr:housenumber":"1597",
    "addr:postcode":"b4a 1e7",
    "addr:street":"Bedford Hwy",
    "iso:country":"CA",
    "sg:address":"1597 Bedford Hwy",
    "sg:city":"Bedford",
    "sg:classifiers":[
        {
            "category":"Banks & Credit Unions",
            "subcategory":"Bank",
            "type":"Services"
        }
    ],
    "sg:phone":"+1 902 421 8844",
    "sg:postcode":"B4A 1E7",
    "sg:province":"NS",
    "wof:name":"Royal Bank Financial Group",
    "wof:placetype":"venue"
},
  "geometry": {"coordinates":[-63.655682,44.733288],"type":"Point"}
}