{
  "type": "Feature",
  "properties": {
    "addr:full":"93 Bessborough Ave Moncton NB E1E 1P6",
    "addr:housenumber":"93",
    "addr:postcode":"e1e 1p6",
    "addr:street":"Bessborough Ave",
    "iso:country":"CA",
    "sg:address":"93 Bessborough Ave",
    "sg:city":"Moncton",
    "sg:classifiers":[
        {
            "category":"Education",
            "subcategory":"School",
            "type":"Public Place"
        }
    ],
    "sg:phone":"+1 506 856 3404",
    "sg:postcode":"E1E 1P6",
    "sg:province":"NB",
    "wof:name":"Bessborough School",
    "wof:placetype":"venue"
},
  "geometry": {"coordinates":[-64.809753418,46.079662323],"type":"Point"}
}