{
  "type": "Feature",
  "properties": {
    "addr:full":"Water St Bonne Bay NL A0K 1P0",
    "addr:postcode":"a0k 1p0",
    "addr:street":"Water St",
    "iso:country":"CA",
    "sg:address":"Water St",
    "sg:city":"Bonne Bay",
    "sg:classifiers":[
        {
            "category":"Bars & Pubs",
            "type":"Food & Drink"
        }
    ],
    "sg:phone":"+1 709 453 2211",
    "sg:postcode":"A0K 1P0",
    "sg:province":"NL",
    "sg:tags":[
        "lounge",
        "cocktail"
    ],
    "wof:name":"Sea Breeze Lounge",
    "wof:placetype":"venue"
},
  "geometry": {"coordinates":[-57.9161186218,49.5032196045],"type":"Point"}
}