{
  "type": "Feature",
  "properties": {
    "iso:country":"CA",
    "sg:address":"21 Somerset St",
    "sg:city":"Kinkora",
    "sg:classifiers":[
        {
            "category":"Retail",
            "subcategory":"Funeral Services",
            "type":"Services"
        }
    ],
    "sg:phone":"+1 902 887 2600",
    "sg:postcode":"C0B 1N0",
    "sg:province":"PE",
    "sg:tags":[
        "director"
    ],
    "wof:name":"Lawless Funeral Home",
    "wof:placetype":"venue"
},
  "geometry": {"coordinates":[-63.6039543152,46.3257904053],"type":"Point"}
}