{
  "type": "Feature",
  "properties": {
    "iso:country":"CA",
    "sg:city":"Stony Mountain",
    "sg:classifiers":[
        {
            "category":"Building & Trades",
            "subcategory":"Construction",
            "type":"Services"
        }
    ],
    "sg:phone":"+1 204 344 5630",
    "sg:postcode":"R0C 3A0",
    "sg:province":"MB",
    "sg:tags":[
        "masonry",
        "contractor"
    ],
    "wof:name":"Egan Construction Ltd",
    "wof:placetype":"venue"
},
  "geometry": {"coordinates":[-97.2225265503,50.0869293213],"type":"Point"}
}