{
  "type": "Feature",
  "properties": {
    "addr:full":"1050 Simcoe St N Oshawa ON L1G 4W5",
    "addr:housenumber":"1050",
    "addr:postcode":"l1g 4w5",
    "addr:street":"Simcoe St N",
    "iso:country":"CA",
    "sg:address":"1050 Simcoe St N",
    "sg:city":"Oshawa",
    "sg:classifiers":[
        {
            "category":"Restaurant",
            "type":"Food & Drink"
        }
    ],
    "sg:phone":"+1 905 721 1728",
    "sg:postcode":"L1G 4W5",
    "sg:province":"ON",
    "wof:name":"Mickey Finn's Sports Cafe",
    "wof:placetype":"venue"
},
  "geometry": {"coordinates":[-78.87595367430001,43.925693512],"type":"Point"}
}