{
  "type": "Feature",
  "properties": {
    "addr:full":"2377 Ch Saint-Henri Mascouche QC J7K 3C3",
    "addr:housenumber":"2377",
    "addr:postcode":"j7k 3c3",
    "addr:street":"Ch Saint-Henri",
    "iso:country":"CA",
    "sg:address":"2377 Ch Saint-Henri",
    "sg:city":"Mascouche",
    "sg:classifiers":[
        {
            "category":"Manufacturing",
            "subcategory":"Lumber",
            "type":"Manufacturing & Wholesale Goods"
        }
    ],
    "sg:phone":"+1 450 474 2808",
    "sg:postcode":"J7K 3C3",
    "sg:province":"QC",
    "sg:tags":[
        "sawmill"
    ],
    "wof:name":"Moulin St-Andre Enrg",
    "wof:placetype":"venue"
},
  "geometry": {"coordinates":[-73.58754730219999,45.7835044861],"type":"Point"}
}