{
  "type": "Feature",
  "properties": {
    "addr:full":"994 Hecate St Nanaimo BC V9R 4K8",
    "addr:housenumber":"994",
    "addr:postcode":"v9r 4k8",
    "addr:street":"Hecate St",
    "iso:country":"CA",
    "sg:address":"994 Hecate St",
    "sg:city":"Nanaimo",
    "sg:classifiers":[
        {
            "category":"Health Services",
            "subcategory":"Nursing And Care Facility",
            "type":"Services"
        }
    ],
    "sg:phone":"+1 250 751 4933",
    "sg:postcode":"V9R 4K8",
    "sg:province":"BC",
    "sg:tags":[
        "home",
        "retirement",
        "convalescent",
        "community"
    ],
    "wof:name":"Hecate Lodge",
    "wof:placetype":"venue"
},
  "geometry": {"coordinates":[-123.940208,49.156494],"type":"Point"}
}