{
  "type": "Feature",
  "properties": {
    "addr:full":"40 Mccabe Ave Welland ON L3B 5H8",
    "addr:housenumber":"40",
    "addr:postcode":"l3b 5h8",
    "addr:street":"Mccabe Ave",
    "iso:country":"CA",
    "sg:address":"40 Mccabe Ave",
    "sg:city":"Welland",
    "sg:classifiers":[
        {
            "category":"Restaurant",
            "type":"Food & Drink"
        }
    ],
    "sg:phone":"+1 905 735 0741",
    "sg:postcode":"L3B 5H8",
    "sg:province":"ON",
    "sg:tags":[
        "banquet",
        "rooms"
    ],
    "wof:name":"Ukrainian Cultural Ctr",
    "wof:placetype":"venue"
},
  "geometry": {"coordinates":[-79.23178900000001,42.968342],"type":"Point"}
}