{
  "type": "Feature",
  "properties": {
    "addr:full":"202 Dundas St W Mississauga ON L5B 1J1",
    "addr:housenumber":"202",
    "addr:postcode":"l5b 1j1",
    "addr:street":"Dundas St W",
    "iso:country":"CA",
    "sg:address":"202 Dundas St W",
    "sg:city":"Mississauga",
    "sg:classifiers":[
        {
            "category":"Autos & Motor Vehicles",
            "subcategory":"Automobile Sales",
            "type":"Retail Goods"
        }
    ],
    "sg:phone":"+1 905 276 0841",
    "sg:postcode":"L5B 1J1",
    "sg:province":"ON",
    "sg:tags":[
        "equipment",
        "air",
        "conditioning",
        "car"
    ],
    "wof:name":"Solutions Automotive Svc",
    "wof:placetype":"venue"
},
  "geometry": {"coordinates":[-79.621117,43.575947],"type":"Point"}
}