{
  "type": "Feature",
  "properties": {
    "iso:country":"CA",
    "sg:address":"10519 100 Ave",
    "sg:city":"Westlock",
    "sg:classifiers":[
        {
            "category":"Restaurant",
            "type":"Food & Drink"
        }
    ],
    "sg:phone":"+1 780 349 3055",
    "sg:postcode":"T7P 2J3",
    "sg:province":"AB",
    "wof:name":"Alberta Cafe",
    "wof:placetype":"venue"
},
  "geometry": {"coordinates":[-113.860443115,54.1544189453],"type":"Point"}
}