{
  "type": "Feature",
  "properties": {
    "iso:country":"CA",
    "sg:address":"Main St",
    "sg:city":"St Lunaire-Griquet",
    "sg:classifiers":[
        {
            "category":"Organizations",
            "subcategory":"Religious Organization",
            "type":"Services"
        }
    ],
    "sg:phone":"+1 709 623 2120",
    "sg:postcode":"A0K 2X0",
    "sg:province":"NL",
    "sg:tags":[
        "church"
    ],
    "wof:name":"Calvary Pentecostal Church",
    "wof:placetype":"venue"
},
  "geometry": {"coordinates":[-55.4839439392,51.5050582886],"type":"Point"}
}