{
  "type": "Feature",
  "properties": {
    "addr:full":"14787 108 Ave Surrey BC V3R 1V9",
    "addr:housenumber":"14787",
    "addr:postcode":"v3r 1v9",
    "addr:street":"108 Ave",
    "iso:country":"CA",
    "sg:address":"14787 108 Ave",
    "sg:city":"Surrey",
    "sg:classifiers":[
        {
            "category":"Shopping",
            "subcategory":"Optical Goods",
            "type":"Retail Goods"
        }
    ],
    "sg:phone":"+1 604 585 3132",
    "sg:postcode":"V3R 1V9",
    "sg:province":"BC",
    "sg:tags":[
        "optician"
    ],
    "wof:name":"Artwork Optical Ltd",
    "wof:placetype":"venue"
},
  "geometry": {"coordinates":[-122.812943,49.198956],"type":"Point"}
}