{
  "type": "Feature",
  "properties": {
    "addr:full":"125 Martin St S Crystal City MB R0K 0N0",
    "addr:housenumber":"125",
    "addr:postcode":"r0k 0n0",
    "addr:street":"Martin St S",
    "iso:country":"CA",
    "sg:address":"125 Martin St S",
    "sg:city":"Crystal City",
    "sg:classifiers":[
        {
            "category":"Education",
            "subcategory":"School",
            "type":"Public Place"
        }
    ],
    "sg:phone":"+1 204 873 2476",
    "sg:postcode":"R0K 0N0",
    "sg:province":"MB",
    "wof:name":"Crystal City Early Years Schl",
    "wof:placetype":"venue"
},
  "geometry": {"coordinates":[-98.944138,49.147984],"type":"Point"}
}