{
  "type": "Feature",
  "properties": {
    "addr:full":"100 Adelaide St W Toronto ON M5H 1S3",
    "addr:housenumber":"100",
    "addr:postcode":"m5h 1s3",
    "addr:street":"Adelaide St W",
    "iso:country":"CA",
    "sg:address":"100 Adelaide St W",
    "sg:city":"Toronto",
    "sg:classifiers":[
        {
            "category":"Real Estate",
            "subcategory":"Real Estate Agent",
            "type":"Services"
        }
    ],
    "sg:phone":"+1 416 367 0197",
    "sg:postcode":"M5H 1S3",
    "sg:province":"ON",
    "wof:name":"Eccleston O'Brien Inc",
    "wof:placetype":"venue"
},
  "geometry": {"coordinates":[-79.3824234009,43.6496734619],"type":"Point"}
}