{
  "type": "Feature",
  "properties": {
    "addr:full":"6645 Rue Saint-Jacques Montreal QC H4B 1V3",
    "addr:housenumber":"6645",
    "addr:postcode":"h4b 1v3",
    "addr:street":"Rue Saint-Jacques",
    "iso:country":"CA",
    "sg:address":"6645 Rue Saint-Jacques",
    "sg:city":"Montreal",
    "sg:classifiers":[
        {
            "category":"Autos & Motor Vehicles",
            "subcategory":"Automobile Sales",
            "type":"Retail Goods"
        }
    ],
    "sg:phone":"+1 514 489 8631",
    "sg:postcode":"H4B 1V3",
    "sg:province":"QC",
    "sg:tags":[
        "truck"
    ],
    "wof:name":"Centre DE Camions Chevrolet",
    "wof:placetype":"venue"
},
  "geometry": {"coordinates":[-73.626831,45.459686],"type":"Point"}
}