{
  "type": "Feature",
  "properties": {
    "addr:full":"11612 145 St NW Edmonton AB T5M 1V8",
    "addr:housenumber":"11612",
    "addr:postcode":"t5m 1v8",
    "addr:street":"145 St Nw",
    "iso:country":"CA",
    "sg:address":"11612 145 St NW",
    "sg:city":"Edmonton",
    "sg:classifiers":[
        {
            "category":"Building & Trades",
            "subcategory":"Construction",
            "type":"Services"
        }
    ],
    "sg:phone":"+1 780 414 0558",
    "sg:postcode":"T5M 1V8",
    "sg:province":"AB",
    "sg:tags":[
        "builder",
        "deck"
    ],
    "wof:name":"Town & Country Construction",
    "wof:placetype":"venue"
},
  "geometry": {"coordinates":[-113.570824,53.568027],"type":"Point"}
}