{
  "type": "Feature",
  "properties": {
    "addr:full":"2093 Av DE LA Montagne Shawinigan QC G9N 6J6",
    "addr:housenumber":"2093",
    "addr:postcode":"g9n 6j6",
    "addr:street":"Av De La Montagne",
    "iso:country":"CA",
    "sg:address":"2093 Av DE LA Montagne",
    "sg:city":"Shawinigan",
    "sg:classifiers":[
        {
            "category":"Restaurant",
            "type":"Food & Drink"
        }
    ],
    "sg:phone":"+1 819 539 1029",
    "sg:postcode":"G9N 6J6",
    "sg:province":"QC",
    "wof:name":"Casse-Croute St-Charles Inc",
    "wof:placetype":"venue"
},
  "geometry": {"coordinates":[-72.76355700000001,46.570305],"type":"Point"}
}