{
  "type": "Feature",
  "properties": {
    "addr:full":"Senneterre QC J0Y 2M0",
    "addr:postcode":"j0y 2m0",
    "iso:country":"CA",
    "sg:city":"Senneterre",
    "sg:classifiers":[
        {
            "category":"Travel",
            "subcategory":"Campground",
            "type":"Entertainment"
        }
    ],
    "sg:phone":"+1 819 737 8681",
    "sg:postcode":"J0Y 2M0",
    "sg:province":"QC",
    "sg:tags":[
        "camp",
        "fishing"
    ],
    "wof:name":"Pourvoirie Du Balbuzard Inc",
    "wof:placetype":"venue"
},
  "geometry": {"coordinates":[-77.22463226319999,48.3581199646],"type":"Point"}
}