{
  "type": "Feature",
  "properties": {
    "addr:full":"Mississauga ON L5T 2A7",
    "addr:postcode":"l5t 2a7",
    "iso:country":"CA",
    "sg:city":"Mississauga",
    "sg:classifiers":[
        {
            "category":"Restaurant",
            "type":"Food & Drink"
        }
    ],
    "sg:phone":"+1 905 565 9300",
    "sg:postcode":"L5T 2A7",
    "sg:province":"ON",
    "sg:tags":[
        "caterer"
    ],
    "wof:name":"Gourmet Cuisine",
    "wof:placetype":"venue"
},
  "geometry": {"coordinates":[-79.685028,43.660919],"type":"Point"}
}