{
  "type": "Feature",
  "properties": {
    "addr:full":"1955 Caribou St W Moose Jaw SK S6H 4R3",
    "addr:housenumber":"1955",
    "addr:postcode":"s6h 4r3",
    "addr:street":"Caribou St W",
    "iso:country":"CA",
    "sg:address":"1955 Caribou St W",
    "sg:city":"Moose Jaw",
    "sg:classifiers":[
        {
            "category":"Autos & Motor Vehicles",
            "subcategory":"Recreational Vehicle Sales",
            "type":"Retail Goods"
        }
    ],
    "sg:phone":"+1 306 693 4992",
    "sg:postcode":"S6H 4R3",
    "sg:province":"SK",
    "sg:tags":[
        "canopy",
        "shell",
        "truck",
        "cap"
    ],
    "wof:name":"Raider Industries Inc",
    "wof:placetype":"venue"
},
  "geometry": {"coordinates":[-105.584152,50.3969],"type":"Point"}
}