{
  "type": "Feature",
  "properties": {
    "addr:full":"246 Joel Crt Strathroy ON N7G 4B3",
    "addr:housenumber":"246",
    "addr:postcode":"n7g 4b3",
    "addr:street":"Joel Crt",
    "iso:country":"CA",
    "sg:address":"246 Joel Crt",
    "sg:city":"Strathroy",
    "sg:classifiers":[
        {
            "category":"Wholesale",
            "subcategory":"Chemicals & Plastics",
            "type":"Manufacturing & Wholesale Goods"
        }
    ],
    "sg:phone":"+1 519 245 8151",
    "sg:postcode":"N7G 4B3",
    "sg:province":"ON",
    "sg:tags":[
        "plant"
    ],
    "wof:name":"Duochem Inc",
    "wof:placetype":"venue"
},
  "geometry": {"coordinates":[-81.6203613281,42.9728851318],"type":"Point"}
}