{
  "type": "Feature",
  "properties": {
    "addr:full":"99 Rue Principale Saint-Honore-DE-Temiscouata QC G0L 3K0",
    "addr:housenumber":"99",
    "addr:postcode":"g0l 3k0",
    "addr:street":"Rue Principale",
    "iso:country":"CA",
    "sg:address":"99 Rue Principale",
    "sg:city":"Saint-Honore-DE-Temiscouata",
    "sg:classifiers":[
        {
            "category":"Government",
            "subcategory":"Office",
            "type":"Public Place"
        }
    ],
    "sg:phone":"+1 418 497 2588",
    "sg:postcode":"G0L 3K0",
    "sg:province":"QC",
    "sg:tags":[
        "village"
    ],
    "wof:name":"St-Honore Municipalite Office",
    "wof:placetype":"venue"
},
  "geometry": {"coordinates":[-69.1364059448,47.7084541321],"type":"Point"}
}