{
  "type": "Feature",
  "properties": {
    "iso:country":"CA",
    "sg:city":"North York",
    "sg:classifiers":[
        {
            "category":"Home & Garden",
            "subcategory":"Home Furnishings",
            "type":"Retail Goods"
        }
    ],
    "sg:phone":"+1 416 222 1554",
    "sg:postcode":"M2N 5S3",
    "sg:province":"ON",
    "sg:tags":[
        "curtain",
        "made",
        "drapery"
    ],
    "wof:name":"Uptown Design & Drapery",
    "wof:placetype":"venue"
},
  "geometry": {"coordinates":[-79.41497802729999,43.7782669067],"type":"Point"}
}