{
  "type": "Feature",
  "properties": {
    "addr:full":"Vancouver BC V6E 4M3",
    "addr:postcode":"v6e 4m3",
    "iso:country":"CA",
    "sg:city":"Vancouver",
    "sg:classifiers":[
        {
            "category":"Real Estate",
            "subcategory":"Real Estate Agent",
            "type":"Services"
        }
    ],
    "sg:phone":"+1 604 696 6100",
    "sg:postcode":"V6E 4M3",
    "sg:province":"BC",
    "wof:name":"Scraper Corp Real Estate Svc",
    "wof:placetype":"venue"
},
  "geometry": {"coordinates":[-123.123336792,49.2860832214],"type":"Point"}
}