{
  "type": "Feature",
  "properties": {
    "addr:full":"2870 Boul Base-DE-Roc Joliette QC J6E 3Z1",
    "addr:housenumber":"2870",
    "addr:postcode":"j6e 3z1",
    "addr:street":"Boul Base-De-Roc",
    "iso:country":"CA",
    "sg:address":"2870 Boul Base-DE-Roc",
    "sg:city":"Joliette",
    "sg:classifiers":[
        {
            "category":"Sports & Exercise",
            "subcategory":"Golf",
            "type":"Entertainment"
        }
    ],
    "sg:phone":"+1 450 759 1818",
    "sg:postcode":"J6E 3Z1",
    "sg:province":"QC",
    "sg:tags":[
        "sporting",
        "good"
    ],
    "wof:name":"Club DE Golf Base DE Roc",
    "wof:placetype":"venue"
},
  "geometry": {"coordinates":[-73.3926086426,45.9895095825],"type":"Point"}
}