{
  "type": "Feature",
  "properties": {
    "addr:full":"43 Whitewood Ave New Liskeard ON P0J 1P0",
    "addr:housenumber":"43",
    "addr:postcode":"p0j 1p0",
    "addr:street":"Whitewood Ave",
    "iso:country":"CA",
    "sg:address":"43 Whitewood Ave",
    "sg:city":"New Liskeard",
    "sg:classifiers":[
        {
            "category":"Shopping",
            "type":"Retail Goods"
        }
    ],
    "sg:phone":"+1 705 647 6644",
    "sg:postcode":"P0J 1P0",
    "sg:province":"ON",
    "sg:tags":[
        "art",
        "gallery",
        "dealer"
    ],
    "wof:name":"Canvas & Clay",
    "wof:placetype":"venue"
},
  "geometry": {"coordinates":[-79.66999053959999,47.5086288452],"type":"Point"}
}