{
  "type": "Feature",
  "properties": {
    "iso:country":"CA",
    "sg:city":"North York",
    "sg:classifiers":[
        {
            "category":"Professional",
            "subcategory":"Business Services",
            "type":"Services"
        }
    ],
    "sg:phone":"+1 416 736 0606",
    "sg:postcode":"M3H 5Y4",
    "sg:province":"ON",
    "sg:tags":[
        "interior",
        "consultant",
        "design",
        "decorator"
    ],
    "wof:name":"Great Gulf Decor Ctr",
    "wof:placetype":"venue"
},
  "geometry": {"coordinates":[-79.468201,43.787506],"type":"Point"}
}