{
  "type": "Feature",
  "properties": {
    "addr:full":"North York ON M3H 5Y4",
    "addr:postcode":"m3h 5y4",
    "iso:country":"CA",
    "sg:city":"North York",
    "sg:classifiers":[
        {
            "category":"Professional",
            "subcategory":"Business Services",
            "type":"Services"
        }
    ],
    "sg:phone":"+1 416 736 0606",
    "sg:postcode":"M3H 5Y4",
    "sg:province":"ON",
    "sg:tags":[
        "interior",
        "consultant",
        "design",
        "decorator"
    ],
    "wof:name":"Great Gulf Decor Ctr",
    "wof:placetype":"venue"
},
  "geometry": {"coordinates":[-79.46820099999999,43.787506],"type":"Point"}
}