{
  "type": "Feature",
  "properties": {
    "addr:full":"5013 48 St Camrose AB T4V 1L9",
    "addr:housenumber":"5013",
    "addr:postcode":"t4v 1l9",
    "addr:street":"48 St",
    "iso:country":"CA",
    "sg:address":"5013 48 St",
    "sg:city":"Camrose",
    "sg:classifiers":[
        {
            "category":"Manufacturing",
            "subcategory":"Tools & Machinery",
            "type":"Manufacturing & Wholesale Goods"
        }
    ],
    "sg:phone":"+1 780 672 2273",
    "sg:postcode":"T4V 1L9",
    "sg:province":"AB",
    "sg:tags":[
        "machine",
        "shop"
    ],
    "wof:name":"Camrose Machine & Welding Ltd",
    "wof:placetype":"venue"
},
  "geometry": {"coordinates":[-112.82154800000001,53.022282],"type":"Point"}
}