{
  "type": "Feature",
  "properties": {
    "addr:full":"100 Argyle St Regina SK S4R 4C3",
    "addr:housenumber":"100",
    "addr:postcode":"s4r 4c3",
    "addr:street":"Argyle St",
    "iso:country":"CA",
    "sg:address":"100 Argyle St",
    "sg:city":"Regina",
    "sg:classifiers":[
        {
            "category":"Organizations",
            "subcategory":"Religious Organization",
            "type":"Services"
        }
    ],
    "sg:phone":"+1 306 545 4411",
    "sg:postcode":"S4R 4C3",
    "sg:province":"SK",
    "sg:tags":[
        "church"
    ],
    "wof:name":"St Peter's Catholic Church",
    "wof:placetype":"venue"
},
  "geometry": {"coordinates":[-104.632774353,50.4778442383],"type":"Point"}
}