{
  "type": "Feature",
  "properties": {
    "iso:country":"CA",
    "sg:address":"1 Whitmore Rd # 1617",
    "sg:city":"Woodbridge",
    "sg:classifiers":[
        {
            "category":"Freight",
            "type":"Transportation"
        }
    ],
    "sg:phone":"+1 905 850 3044",
    "sg:postcode":"L4L 8G4",
    "sg:province":"ON",
    "sg:tags":[
        "trucking"
    ],
    "wof:name":"United Independent Operators",
    "wof:placetype":"venue"
},
  "geometry": {"coordinates":[-79.554184,43.781841],"type":"Point"}
}