{
  "type": "Feature",
  "properties": {
    "addr:full":"55 Stanley Dr St Albert AB T8N 0J6",
    "addr:housenumber":"55",
    "addr:postcode":"t8n 0j6",
    "addr:street":"Stanley Dr",
    "iso:country":"CA",
    "sg:address":"55 Stanley Dr",
    "sg:city":"St Albert",
    "sg:classifiers":[
        {
            "category":"Organizations",
            "subcategory":"Religious Organization",
            "type":"Services"
        }
    ],
    "sg:phone":"+1 780 458 5119",
    "sg:postcode":"T8N 0J6",
    "sg:province":"AB",
    "sg:tags":[
        "church"
    ],
    "wof:name":"St Peter's Evangel Luth Church",
    "wof:placetype":"venue"
},
  "geometry": {"coordinates":[-113.603127,53.627953],"type":"Point"}
}