{
  "type": "Feature",
  "properties": {
    "addr:full":"85 Rue Yargeau Victoriaville QC G6P 8V7",
    "addr:housenumber":"85",
    "addr:postcode":"g6p 8v7",
    "addr:street":"Rue Yargeau",
    "iso:country":"CA",
    "sg:address":"85 Rue Yargeau",
    "sg:city":"Victoriaville",
    "sg:classifiers":[
        {
            "category":"Health Services",
            "subcategory":"Nursing And Care Facility",
            "type":"Services"
        }
    ],
    "sg:phone":"+1 819 758 7868",
    "sg:postcode":"G6P 8V7",
    "sg:province":"QC",
    "sg:tags":[
        "home",
        "retirement",
        "community"
    ],
    "wof:name":"Villa Emelie",
    "wof:placetype":"venue"
},
  "geometry": {"coordinates":[-71.9502410889,46.0675811768],"type":"Point"}
}