{
  "type": "Feature",
  "properties": {
    "addr:full":"6320 50 Ave Red Deer AB T4N 4C6",
    "addr:housenumber":"6320",
    "addr:postcode":"t4n 4c6",
    "addr:street":"50 Ave",
    "iso:country":"CA",
    "sg:address":"6320 50 Ave",
    "sg:city":"Red Deer",
    "sg:classifiers":[
        {
            "category":"Restaurant",
            "type":"Food & Drink"
        }
    ],
    "sg:phone":"+1 403 346 6100",
    "sg:postcode":"T4N 4C6",
    "sg:province":"AB",
    "wof:name":"A & W Family Restaurant",
    "wof:placetype":"venue"
},
  "geometry": {"coordinates":[-113.814186096,52.2831306458],"type":"Point"}
}