{
  "type": "Feature",
  "properties": {
    "addr:full":"Vancouver BC V6C 2G6",
    "addr:postcode":"v6c 2g6",
    "iso:country":"CA",
    "sg:city":"Vancouver",
    "sg:classifiers":[
        {
            "category":"Education",
            "subcategory":"Special Training",
            "type":"Public Place"
        }
    ],
    "sg:phone":"+1 604 633 0505",
    "sg:postcode":"V6C 2G6",
    "sg:province":"BC",
    "sg:tags":[
        "school",
        "language"
    ],
    "wof:name":"E F Intl Language Schools",
    "wof:placetype":"venue"
},
  "geometry": {"coordinates":[-123.116653,49.287506],"type":"Point"}
}