{
  "type": "Feature",
  "properties": {
    "addr:full":"220 Prospect Rd Berwick NS B0P 1E0",
    "addr:housenumber":"220",
    "addr:postcode":"b0p 1e0",
    "addr:street":"Prospect Rd",
    "iso:country":"CA",
    "sg:address":"220 Prospect Rd",
    "sg:city":"Berwick",
    "sg:classifiers":[
        {
            "category":"Wholesale",
            "subcategory":"Fruits & Vegetables",
            "type":"Manufacturing & Wholesale Goods"
        }
    ],
    "sg:phone":"+1 902 538 3341",
    "sg:postcode":"B0P 1E0",
    "sg:province":"NS",
    "sg:tags":[
        "shipper"
    ],
    "wof:name":"Mountain Crest Farm",
    "wof:placetype":"venue"
},
  "geometry": {"coordinates":[-64.737724,45.049816],"type":"Point"}
}