{
  "type": "Feature",
  "properties": {
    "addr:full":"1788 Weston Rd York ON M9N 1V8",
    "addr:housenumber":"1788",
    "addr:postcode":"m9n 1v8",
    "addr:street":"Weston Rd",
    "iso:country":"CA",
    "sg:address":"1788 Weston Rd",
    "sg:city":"York",
    "sg:classifiers":[
        {
            "category":"Restaurant",
            "type":"Food & Drink"
        }
    ],
    "sg:phone":"+1 416 244 5727",
    "sg:postcode":"M9N 1V8",
    "sg:province":"ON",
    "wof:name":"Oda Restaurant & Tavern",
    "wof:placetype":"venue"
},
  "geometry": {"coordinates":[-79.5130081177,43.6988258362],"type":"Point"}
}