{
  "type": "Feature",
  "properties": {
    "addr:full":"485 Frood Rd Sudbury ON P3C 5A2",
    "addr:housenumber":"485",
    "addr:postcode":"p3c 5a2",
    "addr:street":"Frood Rd",
    "iso:country":"CA",
    "sg:address":"485 Frood Rd",
    "sg:city":"Sudbury",
    "sg:classifiers":[
        {
            "category":"Shopping",
            "subcategory":"Bicycles & Sporting Goods",
            "type":"Retail Goods"
        }
    ],
    "sg:phone":"+1 705 670 9009",
    "sg:postcode":"P3C 5A2",
    "sg:province":"ON",
    "sg:tags":[
        "diving",
        "instruction"
    ],
    "wof:name":"Water Ways",
    "wof:placetype":"venue"
},
  "geometry": {"coordinates":[-81.0071640015,46.5048751831],"type":"Point"}
}