{
  "type": "Feature",
  "properties": {
    "addr:full":"10808 98 St NW Edmonton AB T5H 2P1",
    "addr:housenumber":"10808",
    "addr:postcode":"t5h 2p1",
    "addr:street":"98 St Nw",
    "iso:country":"CA",
    "sg:address":"10808 98 St NW",
    "sg:city":"Edmonton",
    "sg:classifiers":[
        {
            "category":"Personal",
            "subcategory":"Beauty Salon",
            "type":"Services"
        }
    ],
    "sg:phone":"+1 780 429 9074",
    "sg:postcode":"T5H 2P1",
    "sg:province":"AB",
    "wof:name":"Palazzo Hair Design",
    "wof:placetype":"venue"
},
  "geometry": {"coordinates":[-113.491669,53.553329],"type":"Point"}
}