{
  "type": "Feature",
  "properties": {
    "addr:full":"11 Rue Chapleau Granby QC J2G 6K1",
    "addr:housenumber":"11",
    "addr:postcode":"j2g 6k1",
    "addr:street":"Rue Chapleau",
    "iso:country":"CA",
    "sg:address":"11 Rue Chapleau",
    "sg:city":"Granby",
    "sg:classifiers":[
        {
            "category":"Organizations",
            "subcategory":"Labor Organization",
            "type":"Services"
        }
    ],
    "sg:phone":"+1 450 375 1122",
    "sg:postcode":"J2G 6K1",
    "sg:province":"QC",
    "wof:name":"Centrale Des Syndicats Demcrtq",
    "wof:placetype":"venue"
},
  "geometry": {"coordinates":[-72.743065,45.409058],"type":"Point"}
}