{
  "type": "Feature",
  "properties": {
    "addr:full":"1166 Weston Rd York ON M6M 4P4",
    "addr:housenumber":"1166",
    "addr:postcode":"m6m 4p4",
    "addr:street":"Weston Rd",
    "iso:country":"CA",
    "sg:address":"1166 Weston Rd",
    "sg:city":"York",
    "sg:classifiers":[
        {
            "category":"Restaurant",
            "type":"Food & Drink"
        }
    ],
    "sg:phone":"+1 416 244 7777",
    "sg:postcode":"M6M 4P4",
    "sg:province":"ON",
    "sg:tags":[
        "pizza"
    ],
    "wof:name":"244 Pizza & Wings",
    "wof:placetype":"venue"
},
  "geometry": {"coordinates":[-79.490532,43.687229],"type":"Point"}
}