{
  "type": "Feature",
  "properties": {
    "iso:country":"CA",
    "sg:city":"Regina",
    "sg:classifiers":[
        {
            "category":"Manufacturing",
            "subcategory":"Signs",
            "type":"Manufacturing & Wholesale Goods"
        }
    ],
    "sg:phone":"+1 306 789 9988",
    "sg:postcode":"S4V 0P8",
    "sg:province":"SK",
    "wof:name":"Sign of the Times Inc",
    "wof:placetype":"venue"
},
  "geometry": {"coordinates":[-104.554679871,50.4385566711],"type":"Point"}
}