{
  "type": "Feature",
  "properties": {
    "addr:full":"17 Colborne St E Orillia ON L3V 1T4",
    "addr:housenumber":"17",
    "addr:postcode":"l3v 1t4",
    "addr:street":"Colborne St E",
    "iso:country":"CA",
    "sg:address":"17 Colborne St E",
    "sg:city":"Orillia",
    "sg:classifiers":[
        {
            "category":"Shopping",
            "subcategory":"Computers & Home Electronics",
            "type":"Retail Goods"
        }
    ],
    "sg:phone":"+1 705 326 4254",
    "sg:postcode":"L3V 1T4",
    "sg:province":"ON",
    "sg:tags":[
        "software"
    ],
    "wof:name":"Quick Inc",
    "wof:placetype":"venue"
},
  "geometry": {"coordinates":[-79.4178695679,44.607383728],"type":"Point"}
}