{
  "type": "Feature",
  "properties": {
    "addr:full":"Quebec QC G1P 4M4",
    "addr:postcode":"g1p 4m4",
    "iso:country":"CA",
    "sg:city":"Quebec",
    "sg:classifiers":[
        {
            "category":"Wholesale",
            "subcategory":"Machinery & Supplies",
            "type":"Manufacturing & Wholesale Goods"
        }
    ],
    "sg:phone":"+1 418 871 1363",
    "sg:postcode":"G1P 4M4",
    "sg:province":"QC",
    "sg:tags":[
        "pump"
    ],
    "wof:name":"Armstrong Darling Inc",
    "wof:placetype":"venue"
},
  "geometry": {"coordinates":[-71.3041000366,46.8048973083],"type":"Point"}
}