{
  "type": "Feature",
  "properties": {
    "addr:full":"1220 Rue Tellier Laval QC H7C 2H2",
    "addr:housenumber":"1220",
    "addr:postcode":"h7c 2h2",
    "addr:street":"Rue Tellier",
    "iso:country":"CA",
    "sg:address":"1220 Rue Tellier",
    "sg:city":"Laval",
    "sg:classifiers":[
        {
            "category":"Retail",
            "subcategory":"Auto Repair",
            "type":"Services"
        }
    ],
    "sg:phone":"+1 450 661 7028",
    "sg:postcode":"H7C 2H2",
    "sg:province":"QC",
    "sg:tags":[
        "repairing",
        "automobile"
    ],
    "wof:name":"Garage Mario Lalonde Inc",
    "wof:placetype":"venue"
},
  "geometry": {"coordinates":[-73.65850067140001,45.6156921387],"type":"Point"}
}