{
  "type": "Feature",
  "properties": {
    "addr:full":"4812 50 Ave Athabasca AB T9S 1H5",
    "addr:housenumber":"4812",
    "addr:postcode":"t9s 1h5",
    "addr:street":"50 Ave",
    "iso:country":"CA",
    "sg:address":"4812 50 Ave",
    "sg:city":"Athabasca",
    "sg:classifiers":[
        {
            "category":"Shopping",
            "subcategory":"Computers & Home Electronics",
            "type":"Retail Goods"
        }
    ],
    "sg:phone":"+1 780 675 2458",
    "sg:postcode":"T9S 1H5",
    "sg:province":"AB",
    "sg:tags":[
        "equipment",
        "satellite",
        "system"
    ],
    "wof:name":"Winto Pro Satellite",
    "wof:placetype":"venue"
},
  "geometry": {"coordinates":[-113.282928,54.721165],"type":"Point"}
}