{
  "type": "Feature",
  "properties": {
    "addr:full":"18 Rue Du Ruisseau Lameque NB E8T 1L8",
    "addr:housenumber":"18",
    "addr:postcode":"e8t 1l8",
    "addr:street":"Rue Du Ruisseau",
    "iso:country":"CA",
    "sg:address":"18 Rue Du Ruisseau",
    "sg:city":"Lameque",
    "sg:classifiers":[
        {
            "category":"Shopping",
            "subcategory":"Bicycles & Sporting Goods",
            "type":"Retail Goods"
        }
    ],
    "sg:phone":"+1 506 344 5005",
    "sg:postcode":"E8T 1L8",
    "sg:province":"NB",
    "sg:tags":[
        "tackle",
        "fishing"
    ],
    "wof:name":"Imp Group Ltee",
    "wof:placetype":"venue"
},
  "geometry": {"coordinates":[-64.652618,47.79467],"type":"Point"}
}