{
  "type": "Feature",
  "properties": {
    "iso:country":"CA",
    "sg:address":"510 Admiral Dr",
    "sg:city":"London",
    "sg:classifiers":[
        {
            "category":"Food & Beverages",
            "subcategory":"Bakery",
            "type":"Retail Goods"
        }
    ],
    "sg:phone":"+1 519 455 4201",
    "sg:postcode":"N5V 5H2",
    "sg:province":"ON",
    "sg:tags":[
        "tea",
        "coffee",
        "doughnut"
    ],
    "wof:name":"Tim Hortons",
    "wof:placetype":"venue"
},
  "geometry": {"coordinates":[-81.1531219482,43.0035057068],"type":"Point"}
}