{
  "type": "Feature",
  "properties": {
    "addr:full":"Richmond BC V6Y 2V7",
    "addr:postcode":"v6y 2v7",
    "iso:country":"CA",
    "sg:city":"Richmond",
    "sg:classifiers":[
        {
            "category":"Restaurant",
            "type":"Food & Drink"
        }
    ],
    "sg:phone":"+1 604 270 7124",
    "sg:postcode":"V6Y 2V7",
    "sg:province":"BC",
    "sg:tags":[
        "shop",
        "tea",
        "coffee"
    ],
    "wof:name":"Second Cup",
    "wof:placetype":"venue"
},
  "geometry": {"coordinates":[-123.140045,49.169788],"type":"Point"}
}