{
  "type": "Feature",
  "properties": {
    "addr:full":"72 Churchill Dr Sydney NS B1S 2B3",
    "addr:housenumber":"72",
    "addr:postcode":"b1s 2b3",
    "addr:street":"Churchill Dr",
    "iso:country":"CA",
    "sg:address":"72 Churchill Dr",
    "sg:city":"Sydney",
    "sg:classifiers":[
        {
            "category":"Education",
            "subcategory":"School",
            "type":"Public Place"
        }
    ],
    "sg:phone":"+1 902 564 9706",
    "sg:postcode":"B1S 2B3",
    "sg:province":"NS",
    "wof:name":"A-One Driving School",
    "wof:placetype":"venue"
},
  "geometry": {"coordinates":[-60.1989746094,46.121509552],"type":"Point"}
}