{
  "type": "Feature",
  "properties": {
    "iso:country":"CA",
    "sg:address":"1201 1st Ave E",
    "sg:city":"Owen Sound",
    "sg:classifiers":[
        {
            "category":"Building & Trades",
            "subcategory":"Plumbing",
            "type":"Services"
        }
    ],
    "sg:phone":"+1 519 376 0736",
    "sg:postcode":"N4K 2E4",
    "sg:province":"ON",
    "sg:tags":[
        "electric",
        "contractor"
    ],
    "wof:name":"Riddell Contracting Ltd",
    "wof:placetype":"venue"
},
  "geometry": {"coordinates":[-80.94169599999999,44.572464],"type":"Point"}
}