{
  "type": "Feature",
  "properties": {
    "addr:full":"Main Tatamagouche NS B0K 1V0",
    "addr:postcode":"b0k 1v0",
    "iso:country":"CA",
    "sg:address":"Main",
    "sg:city":"Tatamagouche",
    "sg:classifiers":[
        {
            "category":"Organizations",
            "subcategory":"Religious Organization",
            "type":"Services"
        }
    ],
    "sg:phone":"+1 902 657 3877",
    "sg:postcode":"B0K 1V0",
    "sg:province":"NS",
    "sg:tags":[
        "church"
    ],
    "wof:name":"Kingdom Hall",
    "wof:placetype":"venue"
},
  "geometry": {"coordinates":[-63.29599,45.713791],"type":"Point"}
}