{
  "type": "Feature",
  "properties": {
    "addr:full":"249 Murray St Brantford ON N3S 5S4",
    "addr:housenumber":"249",
    "addr:postcode":"n3s 5s4",
    "addr:street":"Murray St",
    "iso:country":"CA",
    "sg:address":"249 Murray St",
    "sg:city":"Brantford",
    "sg:classifiers":[
        {
            "category":"Home & Garden",
            "subcategory":"Furniture",
            "type":"Retail Goods"
        }
    ],
    "sg:phone":"+1 519 759 3132",
    "sg:postcode":"N3S 5S4",
    "sg:province":"ON",
    "wof:name":"Bargain Centre",
    "wof:placetype":"venue"
},
  "geometry": {"coordinates":[-80.252762,43.144859],"type":"Point"}
}