{
  "type": "Feature",
  "properties": {
    "addr:full":"22 Perma Crt St Catharines ON L2R 7K8",
    "addr:housenumber":"22",
    "addr:postcode":"l2r 7k8",
    "addr:street":"Perma Crt",
    "iso:country":"CA",
    "sg:address":"22 Perma Crt",
    "sg:city":"St Catharines",
    "sg:classifiers":[
        {
            "category":"Building & Trades",
            "subcategory":"Electrical",
            "type":"Services"
        }
    ],
    "sg:phone":"+1 905 353 1721",
    "sg:postcode":"L2R 7K8",
    "sg:province":"ON",
    "sg:tags":[
        "electric",
        "contractor"
    ],
    "wof:name":"Corrol Technologies",
    "wof:placetype":"venue"
},
  "geometry": {"coordinates":[-79.2295074463,43.1681900024],"type":"Point"}
}