{
  "type": "Feature",
  "properties": {
    "iso:country":"CA",
    "sg:address":"7380 Rue Verite",
    "sg:city":"Saint-Laurent",
    "sg:classifiers":[
        {
            "category":"Manufacturing",
            "subcategory":"Glass & Minerals",
            "type":"Manufacturing & Wholesale Goods"
        }
    ],
    "sg:phone":"+1 514 335 3020",
    "sg:postcode":"H4S 1C5",
    "sg:province":"QC",
    "sg:tags":[
        "fabricator",
        "fiber"
    ],
    "wof:name":"Certel Composites Inc",
    "wof:placetype":"venue"
},
  "geometry": {"coordinates":[-73.7487030029,45.4784965515],"type":"Point"}
}