{
  "type": "Feature",
  "properties": {
    "addr:full":"1804 Alstep Dr Mississauga ON L5S 1W1",
    "addr:housenumber":"1804",
    "addr:postcode":"l5s 1w1",
    "addr:street":"Alstep Dr",
    "iso:country":"CA",
    "sg:address":"1804 Alstep Dr",
    "sg:city":"Mississauga",
    "sg:classifiers":[
        {
            "category":"Building & Trades",
            "subcategory":"Construction",
            "type":"Services"
        }
    ],
    "sg:phone":"+1 905 672 2808",
    "sg:postcode":"L5S 1W1",
    "sg:province":"ON",
    "sg:tags":[
        "tennis",
        "court"
    ],
    "wof:name":"Court Contractors Ltd",
    "wof:placetype":"venue"
},
  "geometry": {"coordinates":[-79.665756,43.680313],"type":"Point"}
}