{
  "type": "Feature",
  "properties": {
    "addr:full":"Cambridge ON N1R 5S7",
    "addr:postcode":"n1r 5s7",
    "iso:country":"CA",
    "sg:city":"Cambridge",
    "sg:classifiers":[
        {
            "category":"Manufacturing",
            "subcategory":"Tools & Machinery",
            "type":"Manufacturing & Wholesale Goods"
        }
    ],
    "sg:phone":"+1 519 622 4924",
    "sg:postcode":"N1R 5S7",
    "sg:province":"ON",
    "sg:tags":[
        "equipment",
        "system",
        "automation"
    ],
    "wof:name":"Applied Automation Canada Inc",
    "wof:placetype":"venue"
},
  "geometry": {"coordinates":[-80.28385900000001,43.373623],"type":"Point"}
}