{
  "type": "Feature",
  "properties": {
    "addr:full":"Kipling SK S0G 2S0",
    "addr:postcode":"s0g 2s0",
    "iso:country":"CA",
    "sg:city":"Kipling",
    "sg:classifiers":[
        {
            "category":"Building & Trades",
            "subcategory":"Construction",
            "type":"Services"
        }
    ],
    "sg:phone":"+1 306 736 2356",
    "sg:postcode":"S0G 2S0",
    "sg:province":"SK",
    "sg:tags":[
        "excavating",
        "contractor",
        "general"
    ],
    "wof:name":"Gee Bee Construction Ltd",
    "wof:placetype":"venue"
},
  "geometry": {"coordinates":[-102.62356567400001,50.1018791199],"type":"Point"}
}