{
  "type": "Feature",
  "properties": {
    "addr:full":"5634 Boul Henri-Bourassa E Montreal-Nord QC H1G 2T2",
    "addr:housenumber":"5634",
    "addr:postcode":"h1g 2t2",
    "addr:street":"Boul Henri-Bourassa E",
    "iso:country":"CA",
    "sg:address":"5634 Boul Henri-Bourassa E",
    "sg:city":"Montreal-Nord",
    "sg:classifiers":[
        {
            "category":"Shopping",
            "subcategory":"Pharmacy",
            "type":"Retail Goods"
        }
    ],
    "sg:phone":"+1 514 329 0900",
    "sg:postcode":"H1G 2T2",
    "sg:province":"QC",
    "wof:name":"Uniprix",
    "wof:placetype":"venue"
},
  "geometry": {"coordinates":[-73.620811,45.606159],"type":"Point"}
}