{
  "type": "Feature",
  "properties": {
    "addr:full":"158 University Ave W Cobourg ON K9A 2H2",
    "addr:housenumber":"158",
    "addr:postcode":"k9a 2h2",
    "addr:street":"University Ave W",
    "iso:country":"CA",
    "sg:address":"158 University Ave W",
    "sg:city":"Cobourg",
    "sg:classifiers":[
        {
            "category":"Home & Garden",
            "subcategory":"Household Appliances",
            "type":"Retail Goods"
        }
    ],
    "sg:phone":"+1 905 372 8723",
    "sg:postcode":"K9A 2H2",
    "sg:province":"ON",
    "sg:tags":[
        "cleaners",
        "vacuum"
    ],
    "wof:name":"Doris Vacuum Ctr",
    "wof:placetype":"venue"
},
  "geometry": {"coordinates":[-78.173958,43.962845],"type":"Point"}
}