{
  "type": "Feature",
  "properties": {
    "addr:full":"Whistler BC V0N 1B4",
    "addr:postcode":"v0n 1b4",
    "iso:country":"CA",
    "sg:city":"Whistler",
    "sg:classifiers":[
        {
            "category":"Home & Garden",
            "subcategory":"Home Furnishings",
            "type":"Retail Goods"
        }
    ],
    "sg:phone":"+1 604 938 1688",
    "sg:postcode":"V0N 1B4",
    "sg:province":"BC",
    "sg:tags":[
        "glassware",
        "chinaware"
    ],
    "wof:name":"Svepol Crystal",
    "wof:placetype":"venue"
},
  "geometry": {"coordinates":[-122.957603455,50.1186332703],"type":"Point"}
}