{
  "type": "Feature",
  "properties": {
    "addr:full":"825 Boul Saint-Joseph Drummondville QC J2C 2C4",
    "addr:housenumber":"825",
    "addr:postcode":"j2c 2c4",
    "addr:street":"Boul Saint-Joseph",
    "iso:country":"CA",
    "sg:address":"825 Boul Saint-Joseph",
    "sg:city":"Drummondville",
    "sg:classifiers":[
        {
            "category":"Autos & Motor Vehicles",
            "subcategory":"Automobile Sales",
            "type":"Retail Goods"
        }
    ],
    "sg:phone":"+1 819 477 2323",
    "sg:postcode":"J2C 2C4",
    "sg:province":"QC",
    "sg:tags":[
        "car",
        "dealer"
    ],
    "wof:name":"Larocque Pontiac Buick Gmc",
    "wof:placetype":"venue"
},
  "geometry": {"coordinates":[-72.509766,45.890163],"type":"Point"}
}