{
  "type": "Feature",
  "properties": {
    "addr:full":"Burnaby BC V5B 3A6",
    "addr:postcode":"v5b 3a6",
    "iso:country":"CA",
    "sg:city":"Burnaby",
    "sg:classifiers":[
        {
            "category":"Shopping",
            "subcategory":"Computers & Home Electronics",
            "type":"Retail Goods"
        }
    ],
    "sg:phone":"+1 604 299 4932",
    "sg:postcode":"V5B 3A6",
    "sg:province":"BC",
    "sg:tags":[
        "software"
    ],
    "wof:name":"Tamco Technology Ltd",
    "wof:placetype":"venue"
},
  "geometry": {"coordinates":[-122.975906372,49.2560157776],"type":"Point"}
}