{
  "type": "Feature",
  "properties": {
    "addr:full":"215 St Catharine St Smithville ON L0R 2A0",
    "addr:housenumber":"215",
    "addr:postcode":"l0r 2a0",
    "addr:street":"St Catharine St",
    "iso:country":"CA",
    "sg:address":"215 St Catharine St",
    "sg:city":"Smithville",
    "sg:classifiers":[
        {
            "category":"Retail",
            "subcategory":"Auto Repair",
            "type":"Services"
        }
    ],
    "sg:phone":"+1 905 957 7035",
    "sg:postcode":"L0R 2A0",
    "sg:province":"ON",
    "sg:tags":[
        "repairing",
        "automobile"
    ],
    "wof:name":"Smithville Garage",
    "wof:placetype":"venue"
},
  "geometry": {"coordinates":[-79.5405960083,43.0954437256],"type":"Point"}
}