{
  "type": "Feature",
  "properties": {
    "iso:country":"CA",
    "sg:address":"373 Rue Temiscouata",
    "sg:city":"Riviere-Du-Loup",
    "sg:classifiers":[
        {
            "category":"Manufacturing",
            "subcategory":"Metals",
            "type":"Manufacturing & Wholesale Goods"
        }
    ],
    "sg:phone":"+1 418 868 6688",
    "sg:postcode":"G5R 2Y9",
    "sg:province":"QC",
    "sg:tags":[
        "supply",
        "equipment",
        "fiber",
        "system",
        "telephone"
    ],
    "wof:name":"Rdl Telecom Inc",
    "wof:placetype":"venue"
},
  "geometry": {"coordinates":[-69.5055847168,47.8213691711],"type":"Point"}
}