{
  "type": "Feature",
  "properties": {
    "addr:full":"769 4th Ave E Owen Sound ON N4K 2N5",
    "addr:housenumber":"769",
    "addr:postcode":"n4k 2n5",
    "addr:street":"4Th Ave E",
    "iso:country":"CA",
    "sg:address":"769 4th Ave E",
    "sg:city":"Owen Sound",
    "sg:classifiers":[
        {
            "category":"Social Services",
            "type":"Services"
        }
    ],
    "sg:phone":"+1 519 371 9251",
    "sg:postcode":"N4K 2N5",
    "sg:province":"ON",
    "sg:tags":[
        "organization",
        "welfare"
    ],
    "wof:name":"Community Living Owen Sound",
    "wof:placetype":"venue"
},
  "geometry": {"coordinates":[-80.9383926392,44.5637016296],"type":"Point"}
}