{
  "type": "Feature",
  "properties": {
    "addr:full":"3535 Grand Marais Rd E Windsor ON N8W 5C1",
    "addr:housenumber":"3535",
    "addr:postcode":"n8w 5c1",
    "addr:street":"Grand Marais Rd E",
    "iso:country":"CA",
    "sg:address":"3535 Grand Marais Rd E",
    "sg:city":"Windsor",
    "sg:classifiers":[
        {
            "category":"Freight",
            "type":"Transportation"
        }
    ],
    "sg:phone":"+1 519 944 3003",
    "sg:postcode":"N8W 5C1",
    "sg:province":"ON",
    "sg:tags":[
        "trucking"
    ],
    "wof:name":"Cassens Transport",
    "wof:placetype":"venue"
},
  "geometry": {"coordinates":[-82.9740982056,42.2938346863],"type":"Point"}
}