{
  "type": "Feature",
  "properties": {
    "iso:country":"CA",
    "sg:address":"173 Roncesvalles Ave",
    "sg:city":"Toronto",
    "sg:classifiers":[
        {
            "category":"Food & Beverages",
            "subcategory":"Bakery",
            "type":"Retail Goods"
        }
    ],
    "sg:phone":"+1 416 535 7143",
    "sg:postcode":"M6R 2L3",
    "sg:province":"ON",
    "sg:tags":[
        "baker"
    ],
    "wof:name":"Roncesvalles Bakery & Deli",
    "wof:placetype":"venue"
},
  "geometry": {"coordinates":[-79.4481124878,43.6444206238],"type":"Point"}
}