{
  "type": "Feature",
  "properties": {
    "addr:full":"2696 Hastings St E Vancouver BC V5K 1Z6",
    "addr:housenumber":"2696",
    "addr:postcode":"v5k 1z6",
    "addr:street":"Hastings St E",
    "iso:country":"CA",
    "sg:address":"2696 Hastings St E",
    "sg:city":"Vancouver",
    "sg:classifiers":[
        {
            "category":"Cinema",
            "subcategory":"Movie Rental",
            "type":"Entertainment"
        }
    ],
    "sg:phone":"+1 604 254 9555",
    "sg:postcode":"V5K 1Z6",
    "sg:province":"BC",
    "sg:tags":[
        "leasing",
        "video",
        "disc",
        "tape"
    ],
    "wof:name":"Rogers Video",
    "wof:placetype":"venue"
},
  "geometry": {"coordinates":[-123.049591065,49.28099823],"type":"Point"}
}