{
  "type": "Feature",
  "properties": {
    "addr:full":"7015 Leslie St Thornhill ON L3T 6L6",
    "addr:housenumber":"7015",
    "addr:postcode":"l3t 6l6",
    "addr:street":"Leslie St",
    "iso:country":"CA",
    "sg:address":"7015 Leslie St",
    "sg:city":"Thornhill",
    "sg:classifiers":[
        {
            "category":"Organizations",
            "subcategory":"Community Association",
            "type":"Services"
        }
    ],
    "sg:phone":"+1 905 882 7700",
    "sg:postcode":"L3T 6L6",
    "sg:province":"ON",
    "sg:tags":[
        "club"
    ],
    "wof:name":"Sports Club of Canada",
    "wof:placetype":"venue"
},
  "geometry": {"coordinates":[-79.373154,43.809582],"type":"Point"}
}