{
  "type": "Feature",
  "properties": {
    "addr:full":"4 Boul Jutras E Victoriaville QC G6P 4K3",
    "addr:housenumber":"4",
    "addr:postcode":"g6p 4k3",
    "addr:street":"Boul Jutras E",
    "iso:country":"CA",
    "sg:address":"4 Boul Jutras E",
    "sg:city":"Victoriaville",
    "sg:classifiers":[
        {
            "category":"Professional",
            "subcategory":"Business Services",
            "type":"Services"
        }
    ],
    "sg:phone":"+1 819 752 9813",
    "sg:postcode":"G6P 4K3",
    "sg:province":"QC",
    "sg:tags":[
        "translator",
        "interpreter"
    ],
    "wof:name":"Productions Jp Piche",
    "wof:placetype":"venue"
},
  "geometry": {"coordinates":[-71.95993799999999,46.051834],"type":"Point"}
}