{
  "type": "Feature",
  "properties": {
    "addr:full":"45 Av Du Bassin N Montmagny QC G5V 4E5",
    "addr:postcode":"g5v 4e5",
    "addr:street":"45 Av Du Bassin N",
    "iso:country":"CA",
    "sg:address":"45 Av Du Bassin N",
    "sg:city":"Montmagny",
    "sg:classifiers":[
        {
            "category":"Travel",
            "subcategory":"Campground",
            "type":"Entertainment"
        }
    ],
    "sg:phone":"+1 418 248 9710",
    "sg:postcode":"G5V 4E5",
    "sg:province":"QC",
    "wof:name":"Camping Pointe Aux Oies",
    "wof:placetype":"venue"
},
  "geometry": {"coordinates":[-70.546333,46.987949],"type":"Point"}
}