{
  "type": "Feature",
  "properties": {
    "addr:full":"Chilliwack BC V2R 1A1",
    "addr:postcode":"v2r 1a1",
    "iso:country":"CA",
    "sg:city":"Chilliwack",
    "sg:classifiers":[
        {
            "category":"Shopping",
            "subcategory":"Clothing, Apparel, & Fashions",
            "type":"Retail Goods"
        }
    ],
    "sg:phone":"+1 604 824 9885",
    "sg:postcode":"V2R 1A1",
    "sg:province":"BC",
    "wof:name":"Suzy Shier",
    "wof:placetype":"venue"
},
  "geometry": {"coordinates":[-121.961967468,49.1408920288],"type":"Point"}
}