{
  "type": "Feature",
  "properties": {
    "addr:full":"4645 34A St SE Calgary AB T2B 3J6",
    "addr:housenumber":"4645",
    "addr:postcode":"t2b 3j6",
    "addr:street":"34A St Se",
    "iso:country":"CA",
    "sg:address":"4645 34A St SE",
    "sg:city":"Calgary",
    "sg:classifiers":[
        {
            "category":"Building & Trades",
            "subcategory":"Construction",
            "type":"Services"
        }
    ],
    "sg:phone":"+1 403 248 5740",
    "sg:postcode":"T2B 3J6",
    "sg:province":"AB",
    "sg:tags":[
        "boring",
        "road"
    ],
    "wof:name":"Crossroads Coring",
    "wof:placetype":"venue"
},
  "geometry": {"coordinates":[-113.983039856,51.0128669739],"type":"Point"}
}