{
  "type": "Feature",
  "properties": {
    "addr:full":"6076 Golf Rd Agassiz BC V0M 1A1",
    "addr:housenumber":"6076",
    "addr:postcode":"v0m 1a1",
    "addr:street":"Golf Rd",
    "iso:country":"CA",
    "sg:address":"6076 Golf Rd",
    "sg:city":"Agassiz",
    "sg:classifiers":[
        {
            "category":"Building & Trades",
            "subcategory":"Construction",
            "type":"Services"
        }
    ],
    "sg:phone":"+1 604 796 2030",
    "sg:postcode":"V0M 1A1",
    "sg:province":"BC",
    "sg:tags":[
        "demolition",
        "contractor"
    ],
    "wof:name":"Staex Resources",
    "wof:placetype":"venue"
},
  "geometry": {"coordinates":[-121.763756,49.238304],"type":"Point"}
}