{
  "type": "Feature",
  "properties": {
    "addr:full":"144 Main St Truro NS B2N 4G9",
    "addr:housenumber":"144",
    "addr:postcode":"b2n 4g9",
    "addr:street":"Main St",
    "iso:country":"CA",
    "sg:address":"144 Main St",
    "sg:city":"Truro",
    "sg:classifiers":[
        {
            "category":"Retail",
            "subcategory":"Auto Repair",
            "type":"Services"
        }
    ],
    "sg:phone":"+1 902 895 7962",
    "sg:postcode":"B2N 4G9",
    "sg:province":"NS",
    "sg:tags":[
        "transmission"
    ],
    "wof:name":"Carl's Transmission",
    "wof:placetype":"venue"
},
  "geometry": {"coordinates":[-63.28904,45.36602],"type":"Point"}
}