{
  "type": "Feature",
  "properties": {
    "iso:country":"CA",
    "sg:city":"Vancouver",
    "sg:classifiers":[
        {
            "category":"Mining & Drilling",
            "type":"Manufacturing & Wholesale Goods"
        }
    ],
    "sg:phone":"+1 604 684 5300",
    "sg:postcode":"V6E 4A2",
    "sg:province":"BC",
    "sg:tags":[
        "company"
    ],
    "wof:name":"North American Tungsten Corp",
    "wof:placetype":"venue"
},
  "geometry": {"coordinates":[-123.125007629,49.2867851257],"type":"Point"}
}