{
  "type": "Feature",
  "properties": {
    "addr:full":"Vancouver BC V6J 4R1",
    "addr:postcode":"v6j 4r1",
    "iso:country":"CA",
    "sg:city":"Vancouver",
    "sg:classifiers":[
        {
            "category":"Real Estate",
            "subcategory":"Real Estate Operator",
            "type":"Services"
        }
    ],
    "sg:phone":"+1 604 732 4255",
    "sg:postcode":"V6J 4R1",
    "sg:province":"BC",
    "sg:tags":[
        "mall",
        "shopping",
        "center"
    ],
    "wof:name":"Arbutus Shopping Ctr",
    "wof:placetype":"venue"
},
  "geometry": {"coordinates":[-123.153481,49.248325],"type":"Point"}
}