{
  "type": "Feature",
  "properties": {
    "addr:full":"Hwy 899 Provost AB T0B 3S0",
    "addr:postcode":"t0b 3s0",
    "addr:street":"Hwy 899 Provost",
    "iso:country":"CA",
    "sg:address":"Hwy 899",
    "sg:city":"Provost",
    "sg:classifiers":[
        {
            "category":"Banks & Credit Unions",
            "subcategory":"Investment Brokerage",
            "type":"Services"
        }
    ],
    "sg:phone":"+1 780 753 6097",
    "sg:postcode":"T0B 3S0",
    "sg:province":"AB",
    "sg:tags":[
        "consultant",
        "planning",
        "financial"
    ],
    "wof:name":"Trilogy Oilfield Ltd",
    "wof:placetype":"venue"
},
  "geometry": {"coordinates":[-110.244842529,52.3553390503],"type":"Point"}
}