{
  "type": "Feature",
  "properties": {
    "addr:full":"Chateauguay QC J6K 3B1",
    "addr:postcode":"j6k 3b1",
    "iso:country":"CA",
    "sg:city":"Chateauguay",
    "sg:classifiers":[
        {
            "category":"Health Services",
            "subcategory":"Hospital",
            "type":"Services"
        }
    ],
    "sg:phone":"+1 450 699 7059",
    "sg:postcode":"J6K 3B1",
    "sg:province":"QC",
    "sg:tags":[
        "mental"
    ],
    "wof:name":"Accolade Chateauguay",
    "wof:placetype":"venue"
},
  "geometry": {"coordinates":[-73.717224,45.356697],"type":"Point"}
}