{
  "type": "Feature",
  "properties": {
    "addr:full":"51 Rue D'Auteuil Quebec QC G1R 4C2",
    "addr:housenumber":"51",
    "addr:postcode":"g1r 4c2",
    "addr:street":"Rue D'Auteuil",
    "iso:country":"CA",
    "sg:address":"51 Rue D'Auteuil",
    "sg:city":"Quebec",
    "sg:classifiers":[
        {
            "category":"Professional",
            "subcategory":"Business Services",
            "type":"Services"
        }
    ],
    "sg:phone":"+1 418 692 6636",
    "sg:postcode":"G1R 4C2",
    "sg:province":"QC",
    "sg:tags":[
        "convention",
        "meeting",
        "facility"
    ],
    "wof:name":"Jpdl Quebec Inc",
    "wof:placetype":"venue"
},
  "geometry": {"coordinates":[-71.2119674683,46.8119697571],"type":"Point"}
}