{
  "type": "Feature",
  "properties": {
    "iso:country":"CA",
    "sg:address":"10523 100 Ave NW",
    "sg:city":"Edmonton",
    "sg:classifiers":[
        {
            "category":"Social Services",
            "type":"Services"
        }
    ],
    "sg:phone":"+1 780 421 1175",
    "sg:postcode":"T5J 0A8",
    "sg:province":"AB",
    "sg:tags":[
        "organization",
        "welfare"
    ],
    "wof:name":"Elizabeth Fry Society/Edmonton",
    "wof:placetype":"venue"
},
  "geometry": {"coordinates":[-113.501617432,53.5386047363],"type":"Point"}
}