{
  "type": "Feature",
  "properties": {
    "addr:full":"PO Box 959 Lewisporte NL A0G 3A0",
    "addr:housenumber":"po",
    "addr:postcode":"a0g 3a0",
    "addr:street":"Box 959",
    "iso:country":"CA",
    "sg:address":"PO Box 959",
    "sg:city":"Lewisporte",
    "sg:classifiers":[
        {
            "category":"Organizations",
            "subcategory":"Religious Organization",
            "type":"Services"
        }
    ],
    "sg:phone":"+1 709 535 6772",
    "sg:postcode":"A0G 3A0",
    "sg:province":"NL",
    "sg:tags":[
        "church"
    ],
    "wof:name":"Bethel Pentecostal Church",
    "wof:placetype":"venue"
},
  "geometry": {"coordinates":[-55.0599365234,49.2417984009],"type":"Point"}
}