{
  "type": "Feature",
  "properties": {
    "addr:full":"East Broughton QC G0N 1G0",
    "addr:postcode":"g0n 1g0",
    "iso:country":"CA",
    "sg:city":"East Broughton",
    "sg:classifiers":[
        {
            "category":"Health Services",
            "subcategory":"Nursing And Care Facility",
            "type":"Services"
        }
    ],
    "sg:phone":"+1 418 427 5493",
    "sg:postcode":"G0N 1G0",
    "sg:province":"QC",
    "sg:tags":[
        "home",
        "retirement",
        "community"
    ],
    "wof:name":"Residence Ste-Famille",
    "wof:placetype":"venue"
},
  "geometry": {"coordinates":[-71.07707977290001,46.2193756104],"type":"Point"}
}