{
  "type": "Feature",
  "properties": {
    "addr:full":"305 Bank St Ottawa ON K2P 1X7",
    "addr:housenumber":"305",
    "addr:postcode":"k2p 1x7",
    "addr:street":"Bank St",
    "iso:country":"CA",
    "sg:address":"305 Bank St",
    "sg:city":"Ottawa",
    "sg:classifiers":[
        {
            "category":"Shopping",
            "subcategory":"Bicycles & Sporting Goods",
            "type":"Retail Goods"
        }
    ],
    "sg:phone":"+1 613 236 9611",
    "sg:postcode":"K2P 1X7",
    "sg:province":"ON",
    "wof:name":"Foster's Sports Ctr Ltd",
    "wof:placetype":"venue"
},
  "geometry": {"coordinates":[-75.69580078120001,45.4149436951],"type":"Point"}
}