{
  "type": "Feature",
  "properties": {
    "addr:full":"3004 Dunning Rd Sarsfield ON K0A 3E0",
    "addr:housenumber":"3004",
    "addr:postcode":"k0a 3e0",
    "addr:street":"Dunning Rd",
    "iso:country":"CA",
    "sg:address":"3004 Dunning Rd",
    "sg:city":"Sarsfield",
    "sg:classifiers":[
        {
            "category":"Wholesale",
            "subcategory":"Meat",
            "type":"Manufacturing & Wholesale Goods"
        }
    ],
    "sg:phone":"+1 613 835 3653",
    "sg:postcode":"K0A 3E0",
    "sg:province":"ON",
    "sg:tags":[
        "butchering"
    ],
    "wof:name":"Country Meat & Kitchen",
    "wof:placetype":"venue"
},
  "geometry": {"coordinates":[-75.369377,45.45422],"type":"Point"}
}