{
  "type": "Feature",
  "properties": {
    "addr:full":"Mcbride BC V0J 2E0",
    "addr:postcode":"v0j 2e0",
    "iso:country":"CA",
    "sg:city":"Mcbride",
    "sg:classifiers":[
        {
            "category":"Real Estate",
            "subcategory":"Real Estate Agent",
            "type":"Services"
        }
    ],
    "sg:phone":"+1 250 569 3330",
    "sg:postcode":"V0J 2E0",
    "sg:province":"BC",
    "sg:tags":[
        "authorities",
        "housing"
    ],
    "wof:name":"B C Housing",
    "wof:placetype":"venue"
},
  "geometry": {"coordinates":[-120.163032532,53.3008308411],"type":"Point"}
}