{
  "type": "Feature",
  "properties": {
    "addr:full":"4020 11A St SE Calgary AB T2G 3H3",
    "addr:housenumber":"4020",
    "addr:postcode":"t2g 3h3",
    "addr:street":"11A St Se",
    "iso:country":"CA",
    "sg:address":"4020 11A St SE",
    "sg:city":"Calgary",
    "sg:classifiers":[
        {
            "category":"Wholesale",
            "subcategory":"Machinery & Supplies",
            "type":"Manufacturing & Wholesale Goods"
        }
    ],
    "sg:phone":"+1 403 253 2236",
    "sg:postcode":"T2G 3H3",
    "sg:province":"AB",
    "sg:tags":[
        "equipment",
        "hydraulic"
    ],
    "wof:name":"Psi Fluid Power Ltd",
    "wof:placetype":"venue"
},
  "geometry": {"coordinates":[-114.03604126,51.0191764832],"type":"Point"}
}