{
  "type": "Feature",
  "properties": {
    "addr:full":"Pelly Crossing YT Y0B 1P0",
    "addr:postcode":"y0b 1p0",
    "iso:country":"CA",
    "sg:city":"Pelly Crossing",
    "sg:classifiers":[
        {
            "category":"Professional",
            "type":"Services"
        }
    ],
    "sg:phone":"+1 867 537 3831",
    "sg:postcode":"Y0B 1P0",
    "sg:province":"YT",
    "sg:tags":[
        "consultant",
        "educational",
        "establishment"
    ],
    "wof:name":"Tutors & Assoc",
    "wof:placetype":"venue"
},
  "geometry": {"coordinates":[-136.57951399999999,62.825802],"type":"Point"}
}