{
  "type": "Feature",
  "properties": {
    "addr:full":"4500 Rang Saint-Michel Shawinigan-Sud QC G9P 5G6",
    "addr:housenumber":"4500",
    "addr:postcode":"g9p 5g6",
    "addr:street":"Rang Saint-Michel",
    "iso:country":"CA",
    "sg:address":"4500 Rang Saint-Michel",
    "sg:city":"Shawinigan-Sud",
    "sg:classifiers":[
        {
            "category":"Farming",
            "subcategory":"Farm",
            "type":"Manufacturing & Wholesale Goods"
        }
    ],
    "sg:phone":"+1 819 536 4223",
    "sg:postcode":"G9P 5G6",
    "sg:province":"QC",
    "wof:name":"Ferme Du Domaine 2000 Inc",
    "wof:placetype":"venue"
},
  "geometry": {"coordinates":[-72.7285,46.497631],"type":"Point"}
}