{
  "type": "Feature",
  "properties": {
    "iso:country":"CA",
    "sg:address":"1380 Kootenay St",
    "sg:city":"Vancouver",
    "sg:classifiers":[
        {
            "category":"Professional",
            "subcategory":"Computer Services",
            "type":"Services"
        }
    ],
    "sg:phone":"+1 604 299 1231",
    "sg:postcode":"V5K 4R1",
    "sg:province":"BC",
    "sg:tags":[
        "repair",
        "dealer",
        "equipment"
    ],
    "wof:name":"Logic Computer Svc",
    "wof:placetype":"venue"
},
  "geometry": {"coordinates":[-123.027305603,49.2721710205],"type":"Point"}
}