{
  "type": "Feature",
  "properties": {
    "addr:full":"Calgary AB T2P 1G3",
    "addr:postcode":"t2p 1g3",
    "iso:country":"CA",
    "sg:city":"Calgary",
    "sg:classifiers":[
        {
            "category":"Health Services",
            "subcategory":"Chiropractor",
            "type":"Services"
        }
    ],
    "sg:phone":"+1 403 264 9621",
    "sg:postcode":"T2P 1G3",
    "sg:province":"AB",
    "wof:name":"Penny Lane Chiropractic Clinic",
    "wof:placetype":"venue"
},
  "geometry": {"coordinates":[-114.072006226,51.0456695557],"type":"Point"}
}