{
  "type": "Feature",
  "properties": {
    "addr:full":"520 Edinburgh Dr Moncton NB E1E 4C6",
    "addr:housenumber":"520",
    "addr:postcode":"e1e 4c6",
    "addr:street":"Edinburgh Dr",
    "iso:country":"CA",
    "sg:address":"520 Edinburgh Dr",
    "sg:city":"Moncton",
    "sg:classifiers":[
        {
            "category":"Wholesale",
            "subcategory":"Machinery & Supplies",
            "type":"Manufacturing & Wholesale Goods"
        }
    ],
    "sg:phone":"+1 506 856 6355",
    "sg:postcode":"E1E 4C6",
    "sg:province":"NB",
    "sg:tags":[
        "fitting",
        "hose",
        "coupling"
    ],
    "wof:name":"Associated Industrial Rubber",
    "wof:placetype":"venue"
},
  "geometry": {"coordinates":[-64.8409957886,46.0881004333],"type":"Point"}
}