{
  "type": "Feature",
  "properties": {
    "addr:full":"14142 Rd 3E Teulon MB R0C 3B0",
    "addr:housenumber":"14142",
    "addr:postcode":"r0c 3b0",
    "addr:street":"Rd",
    "iso:country":"CA",
    "sg:address":"14142 Rd 3E",
    "sg:city":"Teulon",
    "sg:classifiers":[
        {
            "category":"Travel",
            "subcategory":"Hotels & Motels",
            "type":"Entertainment"
        }
    ],
    "sg:phone":"+1 204 886 3818",
    "sg:postcode":"R0C 3B0",
    "sg:province":"MB",
    "sg:tags":[
        "breakfast",
        "accommodation",
        "bed"
    ],
    "wof:name":"Nordin Heritage Inn",
    "wof:placetype":"venue"
},
  "geometry": {"coordinates":[-97.26309204099999,50.3857460022],"type":"Point"}
}