{
  "type": "Feature",
  "properties": {
    "addr:full":"78 11th St W Prince Albert SK S6V 3A9",
    "addr:housenumber":"78",
    "addr:postcode":"s6v 3a9",
    "addr:street":"11Th St",
    "iso:country":"CA",
    "sg:address":"78 11th St W",
    "sg:city":"Prince Albert",
    "sg:classifiers":[
        {
            "category":"Shopping",
            "subcategory":"Used Merchandise",
            "type":"Retail Goods"
        }
    ],
    "sg:phone":"+1 306 922 6444",
    "sg:postcode":"S6V 3A9",
    "sg:province":"SK",
    "sg:tags":[
        "pawnbroker"
    ],
    "wof:name":"Prince Albert Pawn Shop",
    "wof:placetype":"venue"
},
  "geometry": {"coordinates":[-105.75636299999999,53.20319],"type":"Point"}
}