{
  "type": "Feature",
  "properties": {
    "addr:full":"4520 Rue DE Palerme Saint-Leonard QC H1S 3B8",
    "addr:housenumber":"4520",
    "addr:postcode":"h1s 3b8",
    "addr:street":"Rue De Palerme",
    "iso:country":"CA",
    "sg:address":"4520 Rue DE Palerme",
    "sg:city":"Saint-Leonard",
    "sg:classifiers":[
        {
            "category":"Wholesale",
            "subcategory":"Electrical",
            "type":"Manufacturing & Wholesale Goods"
        }
    ],
    "sg:phone":"+1 514 729 1745",
    "sg:postcode":"H1S 3B8",
    "sg:province":"QC",
    "sg:tags":[
        "protective",
        "fire",
        "equipment",
        "protection",
        "robbery",
        "burglary"
    ],
    "wof:name":"Fsa Securite",
    "wof:placetype":"venue"
},
  "geometry": {"coordinates":[-73.58519,45.569462],"type":"Point"}
}