{
  "type": "Feature",
  "properties": {
    "addr:full":"439 Av Notre-Dame Saint-Lambert QC J4P 2K5",
    "addr:postcode":"j4p 2k5",
    "addr:street":"439 Av Notre-Dame",
    "iso:country":"CA",
    "sg:address":"439 Av Notre-Dame",
    "sg:city":"Saint-Lambert",
    "sg:classifiers":[
        {
            "category":"Professional",
            "subcategory":"Lawyer & Legal Services",
            "type":"Services"
        }
    ],
    "sg:phone":"+1 450 923 9936",
    "sg:postcode":"J4P 2K5",
    "sg:province":"QC",
    "sg:tags":[
        "attorney"
    ],
    "wof:name":"Lupien, Pierre",
    "wof:placetype":"venue"
},
  "geometry": {"coordinates":[-73.51151275629999,45.5023765564],"type":"Point"}
}