{
  "type": "Feature",
  "properties": {
    "addr:full":"4 Barn Rd St Anthony NL A0K 4S0",
    "addr:housenumber":"4",
    "addr:postcode":"a0k 4s0",
    "addr:street":"Barn Rd",
    "iso:country":"CA",
    "sg:address":"4 Barn Rd",
    "sg:city":"St Anthony",
    "sg:classifiers":[
        {
            "category":"Autos & Motor Vehicles",
            "subcategory":"Automobile Sales",
            "type":"Retail Goods"
        }
    ],
    "sg:phone":"+1 709 454 4141",
    "sg:postcode":"A0K 4S0",
    "sg:province":"NL",
    "sg:tags":[
        "parts",
        "snowmobile"
    ],
    "wof:name":"K & S Artic Cat",
    "wof:placetype":"venue"
},
  "geometry": {"coordinates":[-55.5955810547,51.3685340881],"type":"Point"}
}