{
  "type": "Feature",
  "properties": {
    "iso:country":"CA",
    "sg:address":"43 Main St W",
    "sg:city":"Ashern",
    "sg:classifiers":[
        {
            "category":"Shopping",
            "subcategory":"Pharmacy",
            "type":"Retail Goods"
        }
    ],
    "sg:phone":"+1 204 768 2824",
    "sg:postcode":"R0C 0E0",
    "sg:province":"MB",
    "wof:name":"Ashern Pharmacy",
    "wof:placetype":"venue"
},
  "geometry": {"coordinates":[-98.3502655029,51.1808052063],"type":"Point"}
}