{
  "type": "Feature",
  "properties": {
    "addr:full":"44 Hilton Ave Toronto ON M5R 3E6",
    "addr:housenumber":"44",
    "addr:postcode":"m5r 3e6",
    "addr:street":"Hilton Ave",
    "iso:country":"CA",
    "sg:address":"44 Hilton Ave",
    "sg:city":"Toronto",
    "sg:classifiers":[
        {
            "category":"Social Services",
            "subcategory":"Child Care",
            "type":"Services"
        }
    ],
    "sg:phone":"+1 416 532 1841",
    "sg:postcode":"M5R 3E6",
    "sg:province":"ON",
    "wof:name":"Wychwood Tiger Daycare Ctr",
    "wof:placetype":"venue"
},
  "geometry": {"coordinates":[-79.415802,43.679455],"type":"Point"}
}