{
  "type": "Feature",
  "properties": {
    "addr:full":"887 Riverside Dr Port Coquitlam BC V3B 7T6",
    "addr:housenumber":"887",
    "addr:postcode":"v3b 7t6",
    "addr:street":"Riverside Dr",
    "iso:country":"CA",
    "sg:address":"887 Riverside Dr",
    "sg:city":"Port Coquitlam",
    "sg:classifiers":[
        {
            "category":"Professional",
            "subcategory":"Detective & Security Services",
            "type":"Services"
        }
    ],
    "sg:phone":"+1 604 945 3805",
    "sg:postcode":"V3B 7T6",
    "sg:province":"BC",
    "sg:tags":[
        "system"
    ],
    "wof:name":"Infra-Tech Enterprises Ltd",
    "wof:placetype":"venue"
},
  "geometry": {"coordinates":[-122.73902893099999,49.2673187256],"type":"Point"}
}