{
  "type": "Feature",
  "properties": {
    "iso:country":"CA",
    "sg:address":"3345 North Service Rd",
    "sg:city":"Burlington",
    "sg:classifiers":[
        {
            "category":"Wholesale",
            "subcategory":"Hardware",
            "type":"Manufacturing & Wholesale Goods"
        }
    ],
    "sg:phone":"+1 905 336 6622",
    "sg:postcode":"L7N 3G2",
    "sg:province":"ON",
    "sg:tags":[
        "tool"
    ],
    "wof:name":"Jobborn Manufacturing Ltd",
    "wof:placetype":"venue"
},
  "geometry": {"coordinates":[-79.7933502197,43.3623504639],"type":"Point"}
}