{
  "type": "Feature",
  "properties": {
    "addr:full":"521 9th St Humboldt SK S0K 2A0",
    "addr:housenumber":"521",
    "addr:postcode":"s0k 2a0",
    "addr:street":"9Th St",
    "iso:country":"CA",
    "sg:address":"521 9th St",
    "sg:city":"Humboldt",
    "sg:classifiers":[
        {
            "category":"Wholesale",
            "subcategory":"Machinery & Supplies",
            "type":"Manufacturing & Wholesale Goods"
        }
    ],
    "sg:phone":"+1 306 682 1716",
    "sg:postcode":"S0K 2A0",
    "sg:province":"SK",
    "sg:tags":[
        "pump"
    ],
    "wof:name":"Schenn's Farm Supply",
    "wof:placetype":"venue"
},
  "geometry": {"coordinates":[-105.124641,52.198124],"type":"Point"}
}