{
  "type": "Feature",
  "properties": {
    "addr:full":"4846 Athalmer Rd Invermere BC V0A 1K3",
    "addr:housenumber":"4846",
    "addr:postcode":"v0a 1k3",
    "addr:street":"Athalmer Rd",
    "iso:country":"CA",
    "sg:address":"4846 Athalmer Rd",
    "sg:city":"Invermere",
    "sg:classifiers":[
        {
            "category":"Organizations",
            "subcategory":"Professional Association",
            "type":"Services"
        }
    ],
    "sg:phone":"+1 250 342 6361",
    "sg:postcode":"V0A 1K3",
    "sg:province":"BC",
    "wof:name":"Shuswap Band Administration",
    "wof:placetype":"venue"
},
  "geometry": {"coordinates":[-116.03037261999999,50.5091705322],"type":"Point"}
}