{
  "type": "Feature",
  "properties": {
    "iso:country":"CA",
    "sg:city":"Langley",
    "sg:classifiers":[
        {
            "category":"Banks & Credit Unions",
            "subcategory":"Bank",
            "type":"Services"
        }
    ],
    "sg:phone":"+1 604 539 8770",
    "sg:postcode":"V2Y 1A5",
    "sg:province":"BC",
    "sg:tags":[
        "exchange",
        "cashing",
        "dealer",
        "broker",
        "foreign",
        "check"
    ],
    "wof:name":"Money Mart",
    "wof:placetype":"venue"
},
  "geometry": {"coordinates":[-122.67861175500001,49.1159706116],"type":"Point"}
}