{
  "type": "Feature",
  "properties": {
    "addr:full":"137 Queen St S Kitchener ON N2G 1W2",
    "addr:housenumber":"137",
    "addr:postcode":"n2g 1w2",
    "addr:street":"Queen St S",
    "iso:country":"CA",
    "sg:address":"137 Queen St S",
    "sg:city":"Kitchener",
    "sg:classifiers":[
        {
            "category":"Organizations",
            "subcategory":"Religious Organization",
            "type":"Services"
        }
    ],
    "sg:phone":"+1 519 745 4891",
    "sg:postcode":"N2G 1W2",
    "sg:province":"ON",
    "sg:tags":[
        "church"
    ],
    "wof:name":"St Paul's Lutheran Church",
    "wof:placetype":"venue"
},
  "geometry": {"coordinates":[-80.4905548096,43.4481811523],"type":"Point"}
}