{
  "type": "Feature",
  "properties": {
    "iso:country":"CA",
    "sg:address":"1 Harbour Sq",
    "sg:city":"Toronto",
    "sg:classifiers":[
        {
            "category":"Restaurant",
            "type":"Food & Drink"
        }
    ],
    "sg:phone":"+1 416 777 2002",
    "sg:postcode":"M5J 1A6",
    "sg:province":"ON",
    "wof:name":"Toula Fine Dining",
    "wof:placetype":"venue"
},
  "geometry": {"coordinates":[-79.3754730225,43.6414871216],"type":"Point"}
}