{
  "type": "Feature",
  "properties": {
    "addr:full":"Calgary AB T2G 0A4",
    "addr:postcode":"t2g 0a4",
    "iso:country":"CA",
    "sg:city":"Calgary",
    "sg:classifiers":[
        {
            "category":"Wholesale",
            "subcategory":"Electrical",
            "type":"Manufacturing & Wholesale Goods"
        }
    ],
    "sg:phone":"+1 403 214 6778",
    "sg:postcode":"T2G 0A4",
    "sg:province":"AB",
    "sg:tags":[
        "control",
        "security",
        "system"
    ],
    "wof:name":"Armax Security & Alarm",
    "wof:placetype":"venue"
},
  "geometry": {"coordinates":[-114.06426239,51.0155715942],"type":"Point"}
}