{
  "type": "Feature",
  "properties": {
    "addr:full":"85 Ottawa St N Hamilton ON L8H 3Y9",
    "addr:housenumber":"85",
    "addr:postcode":"l8h 3y9",
    "addr:street":"Ottawa St N",
    "iso:country":"CA",
    "sg:address":"85 Ottawa St N",
    "sg:city":"Hamilton",
    "sg:classifiers":[
        {
            "category":"Shopping",
            "subcategory":"Photographic Equipment",
            "type":"Retail Goods"
        }
    ],
    "sg:phone":"+1 905 545 8877",
    "sg:postcode":"L8H 3Y9",
    "sg:province":"ON",
    "sg:tags":[
        "supply"
    ],
    "wof:name":"Bell Arte Camera",
    "wof:placetype":"venue"
},
  "geometry": {"coordinates":[-79.8189239502,43.2450485229],"type":"Point"}
}