{
  "type": "Feature",
  "properties": {
    "addr:full":"North York ON M2N 5M1",
    "addr:postcode":"m2n 5m1",
    "iso:country":"CA",
    "sg:city":"North York",
    "sg:classifiers":[
        {
            "category":"Cinema",
            "subcategory":"Movie Rental",
            "type":"Entertainment"
        }
    ],
    "sg:phone":"+1 416 512 2075",
    "sg:postcode":"M2N 5M1",
    "sg:province":"ON",
    "sg:tags":[
        "leasing",
        "video",
        "disc",
        "tape"
    ],
    "wof:name":"Video Plus",
    "wof:placetype":"venue"
},
  "geometry": {"coordinates":[-79.4102630615,43.7580108643],"type":"Point"}
}