{
  "type": "Feature",
  "properties": {
    "addr:full":"Guelph ON N1G 4W4",
    "addr:postcode":"n1g 4w4",
    "iso:country":"CA",
    "sg:city":"Guelph",
    "sg:classifiers":[
        {
            "category":"Professional",
            "subcategory":"Computer Services",
            "type":"Services"
        }
    ],
    "sg:phone":"+1 519 837 2711",
    "sg:postcode":"N1G 4W4",
    "sg:province":"ON",
    "sg:tags":[
        "website",
        "design",
        "internet"
    ],
    "wof:name":"Active Web Corp",
    "wof:placetype":"venue"
},
  "geometry": {"coordinates":[-80.234138,43.519444],"type":"Point"}
}