{
  "type": "Feature",
  "properties": {
    "addr:full":"90 Deer Island Point Rd Cummings Cove NB E5V 1R1",
    "addr:housenumber":"90",
    "addr:postcode":"e5v 1r1",
    "addr:street":"Deer Island Point Rd",
    "iso:country":"CA",
    "sg:address":"90 Deer Island Point Rd",
    "sg:city":"Cummings Cove",
    "sg:classifiers":[
        {
            "category":"Manufacturing",
            "subcategory":"Food",
            "type":"Manufacturing & Wholesale Goods"
        }
    ],
    "sg:phone":"+1 506 747 2369",
    "sg:postcode":"E5V 1R1",
    "sg:province":"NB",
    "sg:tags":[
        "product",
        "seafood",
        "fish",
        "prepared"
    ],
    "wof:name":"Island Shellfish Ltd",
    "wof:placetype":"venue"
},
  "geometry": {"coordinates":[-66.9856185913,44.9272232056],"type":"Point"}
}