{
  "type": "Feature",
  "properties": {
    "addr:full":"543 Hillcrest St Coquitlam BC V3J 6N6",
    "addr:housenumber":"543",
    "addr:postcode":"v3j 6n6",
    "addr:street":"Hillcrest St",
    "iso:country":"CA",
    "sg:address":"543 Hillcrest St",
    "sg:city":"Coquitlam",
    "sg:classifiers":[
        {
            "category":"Building & Trades",
            "subcategory":"Plumbing",
            "type":"Services"
        }
    ],
    "sg:phone":"+1 604 939 6220",
    "sg:postcode":"V3J 6N6",
    "sg:province":"BC",
    "sg:tags":[
        "contractor"
    ],
    "wof:name":"R Snowden & Son Plumbing Svc",
    "wof:placetype":"venue"
},
  "geometry": {"coordinates":[-122.835327148,49.2505455017],"type":"Point"}
}