{
  "type": "Feature",
  "properties": {
    "addr:full":"327 Prince Albert Rd Dartmouth NS B2Y 1N7",
    "addr:housenumber":"327",
    "addr:postcode":"b2y 1n7",
    "addr:street":"Prince Albert Rd",
    "iso:country":"CA",
    "sg:address":"327 Prince Albert Rd",
    "sg:city":"Dartmouth",
    "sg:classifiers":[
        {
            "category":"Real Estate",
            "subcategory":"Surveying",
            "type":"Services"
        }
    ],
    "sg:phone":"+1 902 465 7300",
    "sg:postcode":"B2Y 1N7",
    "sg:province":"NS",
    "sg:tags":[
        "surveyor"
    ],
    "wof:name":"Alderney Surveying",
    "wof:placetype":"venue"
},
  "geometry": {"coordinates":[-63.548283,44.680061],"type":"Point"}
}