{
  "type": "Feature",
  "properties": {
    "addr:full":"Crabtree QC J0K 1B0",
    "addr:postcode":"j0k 1b0",
    "iso:country":"CA",
    "sg:city":"Crabtree",
    "sg:classifiers":[
        {
            "category":"Retail",
            "subcategory":"Auto Repair",
            "type":"Services"
        }
    ],
    "sg:phone":"+1 450 754 4111",
    "sg:postcode":"J0K 1B0",
    "sg:province":"QC",
    "sg:tags":[
        "repairing",
        "automobile"
    ],
    "wof:name":"Garage Coco Venne",
    "wof:placetype":"venue"
},
  "geometry": {"coordinates":[-73.478027,45.964294],"type":"Point"}
}