{
  "type": "Feature",
  "properties": {
    "addr:full":"172 Government Rd Kapuskasing ON P5N 2W9",
    "addr:housenumber":"172",
    "addr:postcode":"p5n 2w9",
    "addr:street":"Rd",
    "iso:country":"CA",
    "sg:address":"172 Government Rd",
    "sg:city":"Kapuskasing",
    "sg:classifiers":[
        {
            "category":"Government",
            "subcategory":"Office",
            "type":"Public Place"
        }
    ],
    "sg:phone":"+1 705 335 8583",
    "sg:postcode":"P5N 2W9",
    "sg:province":"ON",
    "sg:tags":[
        "city",
        "motel",
        "hotel",
        "hall"
    ],
    "wof:name":"Comfort Inn",
    "wof:placetype":"venue"
},
  "geometry": {"coordinates":[-82.402687,49.409126],"type":"Point"}
}