{
  "type": "Feature",
  "properties": {
    "addr:full":"2845 Av Desaulniers Saint-Hyacinthe QC J2S 6C8",
    "addr:housenumber":"2845",
    "addr:postcode":"j2s 6c8",
    "addr:street":"Av Desaulniers",
    "iso:country":"CA",
    "sg:address":"2845 Av Desaulniers",
    "sg:city":"Saint-Hyacinthe",
    "sg:classifiers":[
        {
            "category":"Home & Garden",
            "subcategory":"Home Furnishings",
            "type":"Retail Goods"
        }
    ],
    "sg:phone":"+1 450 773 2430",
    "sg:postcode":"J2S 6C8",
    "sg:province":"QC",
    "sg:tags":[
        "made",
        "consultant",
        "design",
        "decorator",
        "interior",
        "drapery"
    ],
    "wof:name":"Beaufort Textiles Inc",
    "wof:placetype":"venue"
},
  "geometry": {"coordinates":[-72.9673614502,45.6301307678],"type":"Point"}
}