{
  "type": "Feature",
  "properties": {
    "iso:country":"CA",
    "sg:city":"Thunder Bay",
    "sg:classifiers":[
        {
            "category":"Professional",
            "subcategory":"Lawyer & Legal Services",
            "type":"Services"
        }
    ],
    "sg:phone":"+1 807 344 6651",
    "sg:postcode":"P7B 5Z6",
    "sg:province":"ON",
    "sg:tags":[
        "attorney"
    ],
    "wof:name":"Christie Potestio Freitag",
    "wof:placetype":"venue"
},
  "geometry": {"coordinates":[-89.25425720210001,48.4107971191],"type":"Point"}
}