{
  "type": "Feature",
  "properties": {
    "addr:full":"823 2nd Ave E Owen Sound ON N4K 2H2",
    "addr:housenumber":"823",
    "addr:postcode":"n4k 2h2",
    "addr:street":"2Nd Ave E",
    "iso:country":"CA",
    "sg:address":"823 2nd Ave E",
    "sg:city":"Owen Sound",
    "sg:classifiers":[
        {
            "category":"Health Services",
            "subcategory":"Optometrist",
            "type":"Services"
        }
    ],
    "sg:phone":"+1 519 376 5888",
    "sg:postcode":"N4K 2H2",
    "sg:province":"ON",
    "wof:name":"Shouldice, Mary OD",
    "wof:placetype":"venue"
},
  "geometry": {"coordinates":[-80.942322,44.564484],"type":"Point"}
}