{
  "type": "Feature",
  "properties": {
    "addr:full":"London ON N6G 3Y9",
    "addr:postcode":"n6g 3y9",
    "iso:country":"CA",
    "sg:city":"London",
    "sg:classifiers":[
        {
            "category":"Banks & Credit Unions",
            "subcategory":"Bank",
            "type":"Services"
        }
    ],
    "sg:phone":"+1 519 850 0111",
    "sg:postcode":"N6G 3Y9",
    "sg:province":"ON",
    "sg:tags":[
        "broker",
        "foreign",
        "dealer",
        "exchange"
    ],
    "wof:name":"Continental Currency Exchange",
    "wof:placetype":"venue"
},
  "geometry": {"coordinates":[-81.281654,43.025227],"type":"Point"}
}