{
  "type": "Feature",
  "properties": {
    "addr:full":"5105 Falconridge Blvd NE Calgary AB T3J 3K9",
    "addr:housenumber":"5105",
    "addr:postcode":"t3j 3k9",
    "addr:street":"Falconridge Blvd Ne",
    "iso:country":"CA",
    "sg:address":"5105 Falconridge Blvd NE",
    "sg:city":"Calgary",
    "sg:classifiers":[
        {
            "category":"Restaurant",
            "type":"Food & Drink"
        }
    ],
    "sg:phone":"+1 403 285 1243",
    "sg:postcode":"T3J 3K9",
    "sg:province":"AB",
    "wof:name":"Taco Bell",
    "wof:placetype":"venue"
},
  "geometry": {"coordinates":[-113.958733,51.098213],"type":"Point"}
}