{
  "type": "Feature",
  "properties": {
    "addr:full":"Kamloops BC V2C 2J6",
    "addr:postcode":"bc v2c 2j6",
    "iso:country":"CA",
    "sg:city":"Kamloops",
    "sg:classifiers":[
        {
            "category":"Real Estate",
            "subcategory":"Real Estate Agent",
            "type":"Services"
        }
    ],
    "sg:phone":"+1 250 372 3053",
    "sg:postcode":"V2C 2J6",
    "sg:province":"BC",
    "sg:tags":[
        "desk",
        "space"
    ],
    "wof:name":"Riverview Execu-Suite",
    "wof:placetype":"venue"
},
  "geometry": {"coordinates":[-120.33139801,50.6742324829],"type":"Point"}
}