{
  "type": "Feature",
  "properties": {
    "addr:full":"2337 High Rd Arichat NS B0E 1A0",
    "addr:housenumber":"2337",
    "addr:postcode":"b0e 1a0",
    "addr:street":"High Rd",
    "iso:country":"CA",
    "sg:address":"2337 High Rd",
    "sg:city":"Arichat",
    "sg:classifiers":[
        {
            "category":"Food & Beverages",
            "subcategory":"Groceries & Convenience Stores",
            "type":"Retail Goods"
        }
    ],
    "sg:phone":"+1 902 226 2186",
    "sg:postcode":"B0E 1A0",
    "sg:province":"NS",
    "sg:tags":[
        "grocer"
    ],
    "wof:name":"Jeantie's Mini-Mart",
    "wof:placetype":"venue"
},
  "geometry": {"coordinates":[-61.0165023804,45.5118560791],"type":"Point"}
}