{
  "type": "Feature",
  "properties": {
    "addr:full":"132 Main St Niverville MB R0A 1E0",
    "addr:housenumber":"132",
    "addr:postcode":"r0a 1e0",
    "addr:street":"Main St",
    "iso:country":"CA",
    "sg:address":"132 Main St",
    "sg:city":"Niverville",
    "sg:classifiers":[
        {
            "category":"Home & Garden",
            "subcategory":"Furniture",
            "type":"Retail Goods"
        }
    ],
    "sg:phone":"+1 204 388 4149",
    "sg:postcode":"R0A 1E0",
    "sg:province":"MB",
    "wof:name":"Wiens Furniture Village",
    "wof:placetype":"venue"
},
  "geometry": {"coordinates":[-97.0414428711,49.6059188843],"type":"Point"}
}