{
  "type": "Feature",
  "properties": {
    "addr:full":"Surrey BC V3R 4G5",
    "addr:postcode":"v3r 4g5",
    "iso:country":"CA",
    "sg:city":"Surrey",
    "sg:classifiers":[
        {
            "category":"Restaurant",
            "type":"Food & Drink"
        }
    ],
    "sg:phone":"+1 604 583 8333",
    "sg:postcode":"V3R 4G5",
    "sg:province":"BC",
    "sg:tags":[
        "caterer"
    ],
    "wof:name":"Funky Pickle Cafe",
    "wof:placetype":"venue"
},
  "geometry": {"coordinates":[-122.801147461,49.183631897],"type":"Point"}
}