{
  "type": "Feature",
  "properties": {
    "addr:full":"LA Plaine QC J7M 1V3",
    "addr:postcode":"j7m 1v3",
    "iso:country":"CA",
    "sg:city":"LA Plaine",
    "sg:classifiers":[
        {
            "category":"Retail",
            "subcategory":"Auto Repair",
            "type":"Services"
        }
    ],
    "sg:phone":"+1 450 478 1166",
    "sg:postcode":"J7M 1V3",
    "sg:province":"QC",
    "sg:tags":[
        "body",
        "automobile",
        "painting"
    ],
    "wof:name":"Tony Debosselage & Peinture",
    "wof:placetype":"venue"
},
  "geometry": {"coordinates":[-73.763794,45.789822],"type":"Point"}
}