{
  "type": "Feature",
  "properties": {
    "addr:full":"189 Rue DE Martigny O Saint-Jerome QC J7Y 2G4",
    "addr:housenumber":"189",
    "addr:postcode":"j7y 2g4",
    "addr:street":"Rue De Martigny O Saint-Jerome",
    "iso:country":"CA",
    "sg:address":"189 Rue DE Martigny O",
    "sg:city":"Saint-Jerome",
    "sg:classifiers":[
        {
            "category":"Health Services",
            "subcategory":"Doctor",
            "type":"Services"
        }
    ],
    "sg:phone":"+1 450 431 5053",
    "sg:postcode":"J7Y 2G4",
    "sg:province":"QC",
    "sg:tags":[
        "dentist"
    ],
    "wof:name":"Bouchard, Francois DDS",
    "wof:placetype":"venue"
},
  "geometry": {"coordinates":[-74.013451,45.779572],"type":"Point"}
}