{
  "type": "Feature",
  "properties": {
    "addr:full":"132 Michigan Ave Point Edward ON N7V 1E6",
    "addr:housenumber":"132",
    "addr:postcode":"n7v 1e6",
    "addr:street":"Michigan Ave",
    "iso:country":"CA",
    "sg:address":"132 Michigan Ave",
    "sg:city":"Point Edward",
    "sg:classifiers":[
        {
            "category":"Wholesale",
            "subcategory":"Vending Machines",
            "type":"Manufacturing & Wholesale Goods"
        }
    ],
    "sg:phone":"+1 519 344 4431",
    "sg:postcode":"N7V 1E6",
    "sg:province":"ON",
    "wof:name":"Savco Food Svc Ltd",
    "wof:placetype":"venue"
},
  "geometry": {"coordinates":[-82.416534,42.998058],"type":"Point"}
}