{
  "type": "Feature",
  "properties": {
    "addr:full":"348 138 Rte Cap-Sante QC G0A 1L0",
    "addr:housenumber":"138",
    "addr:postcode":"g0a 1l0",
    "addr:street":"Rte Cap-Sante",
    "iso:country":"CA",
    "sg:address":"348 138 Rte",
    "sg:city":"Cap-Sante",
    "sg:classifiers":[
        {
            "category":"Health Services",
            "subcategory":"Nursing And Care Facility",
            "type":"Services"
        }
    ],
    "sg:phone":"+1 418 285 3030",
    "sg:postcode":"G0A 1L0",
    "sg:province":"QC",
    "sg:tags":[
        "home",
        "retirement",
        "community"
    ],
    "wof:name":"Manoir Cap-Sante",
    "wof:placetype":"venue"
},
  "geometry": {"coordinates":[-71.792877,46.673054],"type":"Point"}
}