{
  "type": "Feature",
  "properties": {
    "addr:full":"330 Preston St Ottawa ON K1S 4M6",
    "addr:housenumber":"330",
    "addr:postcode":"k1s 4m6",
    "addr:street":"Preston St",
    "iso:country":"CA",
    "sg:address":"330 Preston St",
    "sg:city":"Ottawa",
    "sg:classifiers":[
        {
            "category":"Restaurant",
            "type":"Food & Drink"
        }
    ],
    "sg:phone":"+1 613 232 1675",
    "sg:postcode":"K1S 4M6",
    "sg:province":"ON",
    "wof:name":"Ciccio Caffe",
    "wof:placetype":"venue"
},
  "geometry": {"coordinates":[-75.71075399999999,45.402489],"type":"Point"}
}