{
  "type": "Feature",
  "properties": {
    "addr:full":"2045 Rue Bishop Montreal QC H3G 2E8",
    "addr:housenumber":"2045",
    "addr:postcode":"h3g 2e8",
    "addr:street":"Rue Bishop",
    "iso:country":"CA",
    "sg:address":"2045 Rue Bishop",
    "sg:city":"Montreal",
    "sg:classifiers":[
        {
            "category":"Food & Beverages",
            "subcategory":"Groceries & Convenience Stores",
            "type":"Retail Goods"
        }
    ],
    "sg:phone":"+1 514 499 2974",
    "sg:postcode":"H3G 2E8",
    "sg:province":"QC",
    "wof:name":"Tanni Moni",
    "wof:placetype":"venue"
},
  "geometry": {"coordinates":[-73.578423,45.497761],"type":"Point"}
}