{
  "type": "Feature",
  "properties": {
    "addr:full":"1029 2nd Ave E Owen Sound ON N4K 2H8",
    "addr:housenumber":"1029",
    "addr:postcode":"n4k 2h8",
    "addr:street":"2Nd Ave E",
    "iso:country":"CA",
    "sg:address":"1029 2nd Ave E",
    "sg:city":"Owen Sound",
    "sg:classifiers":[
        {
            "category":"Government",
            "subcategory":"Office",
            "type":"Public Place"
        }
    ],
    "sg:phone":"+1 519 371 1561",
    "sg:postcode":"N4K 2H8",
    "sg:province":"ON",
    "wof:name":"Canada Parliament Members",
    "wof:placetype":"venue"
},
  "geometry": {"coordinates":[-80.942657,44.568485],"type":"Point"}
}