{
  "type": "Feature",
  "properties": {
    "iso:country":"CA",
    "sg:address":"508 Rue Lafontaine",
    "sg:city":"Riviere-Du-Loup",
    "sg:classifiers":[
        {
            "category":"Shopping",
            "subcategory":"Shoes",
            "type":"Retail Goods"
        }
    ],
    "sg:phone":"+1 418 862 2372",
    "sg:postcode":"G5R 3C4",
    "sg:province":"QC",
    "sg:tags":[
        "clothing",
        "furnishing"
    ],
    "wof:name":"Vezina Mercerie Ltee",
    "wof:placetype":"venue"
},
  "geometry": {"coordinates":[-69.5305938721,47.8277511597],"type":"Point"}
}