{
  "type": "Feature",
  "properties": {
    "addr:full":"Crooked Creek AB T0H 0Y0",
    "addr:postcode":"t0h 0y0",
    "iso:country":"CA",
    "sg:city":"Crooked Creek",
    "sg:classifiers":[
        {
            "category":"Social Services",
            "subcategory":"Adult Care",
            "type":"Services"
        }
    ],
    "sg:phone":"+1 780 957 2372",
    "sg:postcode":"T0H 0Y0",
    "sg:province":"AB",
    "sg:tags":[
        "senior",
        "housing",
        "citizen"
    ],
    "wof:name":"Ridgevalley Seniors Home",
    "wof:placetype":"venue"
},
  "geometry": {"coordinates":[-117.83482360799999,55.1559753418],"type":"Point"}
}