{
  "type": "Feature",
  "properties": {
    "addr:full":"3113 30 Ave SE Calgary AB T2B 0G9",
    "addr:housenumber":"3113",
    "addr:postcode":"t2b 0g9",
    "addr:street":"30 Ave Se",
    "iso:country":"CA",
    "sg:address":"3113 30 Ave SE",
    "sg:city":"Calgary",
    "sg:classifiers":[
        {
            "category":"Education",
            "subcategory":"School",
            "type":"Public Place"
        }
    ],
    "sg:phone":"+1 403 777 8260",
    "sg:postcode":"T2B 0G9",
    "sg:province":"AB",
    "wof:name":"West Dover Elementary School",
    "wof:placetype":"venue"
},
  "geometry": {"coordinates":[-113.99028015099999,51.0268287659],"type":"Point"}
}