{
  "type": "Feature",
  "properties": {
    "addr:full":"1159 Clyde Crt Kingston ON K7P 2E4",
    "addr:housenumber":"1159",
    "addr:postcode":"k7p 2e4",
    "addr:street":"Clyde Crt",
    "iso:country":"CA",
    "sg:address":"1159 Clyde Crt",
    "sg:city":"Kingston",
    "sg:classifiers":[
        {
            "category":"Building & Trades",
            "subcategory":"Construction",
            "type":"Services"
        }
    ],
    "sg:phone":"+1 613 389 3583",
    "sg:postcode":"K7P 2E4",
    "sg:province":"ON",
    "sg:tags":[
        "masonry",
        "contractor",
        "general"
    ],
    "wof:name":"A Santin Mason Contractor Ltd",
    "wof:placetype":"venue"
},
  "geometry": {"coordinates":[-76.5633850098,44.2672233582],"type":"Point"}
}