{
  "type": "Feature",
  "properties": {
    "addr:full":"1395 Benvenuto Ave Brentwood Bay BC V8M 1J5",
    "addr:housenumber":"1395",
    "addr:postcode":"v8m 1j5",
    "addr:street":"Benvenuto Ave",
    "iso:country":"CA",
    "sg:address":"1395 Benvenuto Ave",
    "sg:city":"Brentwood Bay",
    "sg:classifiers":[
        {
            "category":"Home & Garden",
            "subcategory":"Garden Supply",
            "type":"Retail Goods"
        }
    ],
    "sg:phone":"+1 250 652 1539",
    "sg:postcode":"V8M 1J5",
    "sg:province":"BC",
    "sg:tags":[
        "nurseryman",
        "nursery"
    ],
    "wof:name":"Brentwood Bay Nurseries Ltd",
    "wof:placetype":"venue"
},
  "geometry": {"coordinates":[-123.453186,48.564072],"type":"Point"}
}