{
  "type": "Feature",
  "properties": {
    "addr:full":"1530 St. Peter Ave Bathurst NB E2A 3A9",
    "addr:housenumber":"1530",
    "addr:postcode":"e2a 3a9",
    "addr:street":"St. Peter Ave",
    "iso:country":"CA",
    "sg:address":"1530 St. Peter Ave",
    "sg:city":"Bathurst",
    "sg:classifiers":[
        {
            "category":"Shopping",
            "type":"Retail Goods"
        }
    ],
    "sg:phone":"+1 506 548 8009",
    "sg:postcode":"E2A 3A9",
    "sg:province":"NB",
    "sg:tags":[
        "picture",
        "frame"
    ],
    "wof:name":"Rachel Cyr Laminating & Framin",
    "wof:placetype":"venue"
},
  "geometry": {"coordinates":[-65.68273162840001,47.6419868469],"type":"Point"}
}