{
  "type": "Feature",
  "properties": {
    "addr:full":"949 Keyes Dr Woodstock ON N4V 1C3",
    "addr:housenumber":"949",
    "addr:postcode":"n4v 1c3",
    "addr:street":"Keyes Dr",
    "iso:country":"CA",
    "sg:address":"949 Keyes Dr",
    "sg:city":"Woodstock",
    "sg:classifiers":[
        {
            "category":"Building & Trades",
            "subcategory":"Construction",
            "type":"Services"
        }
    ],
    "sg:phone":"+1 519 421 1414",
    "sg:postcode":"N4V 1C3",
    "sg:province":"ON",
    "sg:tags":[
        "builder",
        "stair"
    ],
    "wof:name":"Dan Craft Stairs",
    "wof:placetype":"venue"
},
  "geometry": {"coordinates":[-80.7277832031,43.1199188232],"type":"Point"}
}