{
  "type": "Feature",
  "properties": {
    "addr:full":"155 Bayside Dr Saint John NB E2J 1A3",
    "addr:housenumber":"155",
    "addr:postcode":"e2j 1a3",
    "addr:street":"Bayside Dr",
    "iso:country":"CA",
    "sg:address":"155 Bayside Dr",
    "sg:city":"Saint John",
    "sg:classifiers":[
        {
            "category":"Insurance",
            "subcategory":"Insurance Agent",
            "type":"Services"
        }
    ],
    "sg:phone":"+1 506 633 1990",
    "sg:postcode":"E2J 1A3",
    "sg:province":"NB",
    "wof:name":"Walker, Jeff",
    "wof:placetype":"venue"
},
  "geometry": {"coordinates":[-66.03904,45.283092],"type":"Point"}
}