{
  "type": "Feature",
  "properties": {
    "iso:country":"CA",
    "sg:address":"Community Ctr",
    "sg:city":"Kensington",
    "sg:classifiers":[
        {
            "category":"Government",
            "subcategory":"Office",
            "type":"Public Place"
        }
    ],
    "sg:phone":"+1 902 836 3863",
    "sg:postcode":"C0B 1M0",
    "sg:province":"PE",
    "wof:name":"PE Public Health Nursing",
    "wof:placetype":"venue"
},
  "geometry": {"coordinates":[-63.6368484497,46.436882019],"type":"Point"}
}