{
  "type": "Feature",
  "properties": {
    "addr:full":"Medicine Hat AB T1A 8A9",
    "addr:postcode":"t1a 8a9",
    "iso:country":"CA",
    "sg:city":"Medicine Hat",
    "sg:classifiers":[
        {
            "category":"Shopping",
            "subcategory":"Bicycles & Sporting Goods",
            "type":"Retail Goods"
        }
    ],
    "sg:phone":"+1 403 529 9248",
    "sg:postcode":"T1A 8A9",
    "sg:province":"AB",
    "wof:name":"Outdoorsman",
    "wof:placetype":"venue"
},
  "geometry": {"coordinates":[-110.664062,50.029091],"type":"Point"}
}