{
  "type": "Feature",
  "properties": {
    "addr:full":"453 16 Ave NE Calgary AB T2E 1K3",
    "addr:postcode":"t2e 1k3",
    "addr:street":"453 16 Ave Ne",
    "iso:country":"CA",
    "sg:address":"453 16 Ave NE",
    "sg:city":"Calgary",
    "sg:classifiers":[
        {
            "category":"Personal",
            "subcategory":"Beauty Salon",
            "type":"Services"
        }
    ],
    "sg:phone":"+1 403 568 4000",
    "sg:postcode":"T2E 1K3",
    "sg:province":"AB",
    "wof:name":"Shananaa Braiding & Hair Extns",
    "wof:placetype":"venue"
},
  "geometry": {"coordinates":[-114.054100037,51.0668487549],"type":"Point"}
}