{
  "type": "Feature",
  "properties": {
    "iso:country":"CA",
    "sg:address":"85 Rue Saint-Charles O",
    "sg:city":"Longueuil",
    "sg:classifiers":[
        {
            "category":"Wholesale",
            "subcategory":"Photographic Equipment",
            "type":"Manufacturing & Wholesale Goods"
        }
    ],
    "sg:phone":"+1 450 670 1881",
    "sg:postcode":"J4H 1C5",
    "sg:province":"QC",
    "sg:tags":[
        "identification"
    ],
    "wof:name":"I Denticam Systems Canada Ltd",
    "wof:placetype":"venue"
},
  "geometry": {"coordinates":[-73.507828,45.541626],"type":"Point"}
}