{
  "type": "Feature",
  "properties": {
    "addr:full":"15 Teal Ave Stoney Creek ON L8E 2P1",
    "addr:housenumber":"15",
    "addr:postcode":"l8e 2p1",
    "addr:street":"Teal Ave",
    "iso:country":"CA",
    "sg:address":"15 Teal Ave",
    "sg:city":"Stoney Creek",
    "sg:classifiers":[
        {
            "category":"Building & Trades",
            "subcategory":"Plumbing",
            "type":"Services"
        }
    ],
    "sg:phone":"+1 905 664 1333",
    "sg:postcode":"L8E 2P1",
    "sg:province":"ON",
    "sg:tags":[
        "conditioning",
        "air",
        "refrigeration",
        "system",
        "contractor"
    ],
    "wof:name":"Air Tech Svc Inc",
    "wof:placetype":"venue"
},
  "geometry": {"coordinates":[-79.732201,43.237583],"type":"Point"}
}