{
  "type": "Feature",
  "properties": {
    "addr:full":"Maple ON L6A 2E8",
    "addr:postcode":"l6a 2e8",
    "iso:country":"CA",
    "sg:city":"Maple",
    "sg:classifiers":[
        {
            "category":"Retail",
            "subcategory":"Laundry & Dry Cleaning",
            "type":"Services"
        }
    ],
    "sg:phone":"+1 905 303 1505",
    "sg:postcode":"L6A 2E8",
    "sg:province":"ON",
    "sg:tags":[
        "cleaners"
    ],
    "wof:name":"Stay Fresh Cleaners",
    "wof:placetype":"venue"
},
  "geometry": {"coordinates":[-79.5225524902,43.8526535034],"type":"Point"}
}