{
  "type": "Feature",
  "properties": {
    "iso:country":"CA",
    "sg:address":"1123 Broad St E",
    "sg:city":"Dunnville",
    "sg:classifiers":[
        {
            "category":"Restaurant",
            "type":"Food & Drink"
        }
    ],
    "sg:phone":"+1 905 774 7671",
    "sg:postcode":"N1A 2Z5",
    "sg:province":"ON",
    "sg:tags":[
        "center",
        "bowling"
    ],
    "wof:name":"Grimm's Country Place",
    "wof:placetype":"venue"
},
  "geometry": {"coordinates":[-79.59307861329999,42.9047622681],"type":"Point"}
}