{
  "type": "Feature",
  "properties": {
    "addr:full":"115 Dieppe Rd St Catharines ON L2M 7N6",
    "addr:housenumber":"115",
    "addr:postcode":"l2m 7n6",
    "addr:street":"Dieppe Rd",
    "iso:country":"CA",
    "sg:address":"115 Dieppe Rd",
    "sg:city":"St Catharines",
    "sg:phone":"+1 905 688 8823",
    "sg:postcode":"L2M 7N6",
    "sg:province":"ON",
    "sg:tags":[
        "machine",
        "vending"
    ],
    "wof:name":"Kane's Distributing Ltd",
    "wof:placetype":"venue"
},
  "geometry": {"coordinates":[-79.218338,43.170589],"type":"Point"}
}