{
  "type": "Feature",
  "properties": {
    "iso:country":"CA",
    "sg:city":"Concord",
    "sg:classifiers":[
        {
            "category":"Building & Trades",
            "subcategory":"Construction",
            "type":"Services"
        }
    ],
    "sg:phone":"+1 905 738 3940",
    "sg:postcode":"L4K 3R3",
    "sg:province":"ON",
    "sg:tags":[
        "woodworker"
    ],
    "wof:name":"Fine Line Arch Woodworking",
    "wof:placetype":"venue"
},
  "geometry": {"coordinates":[-79.4808731079,43.8270759583],"type":"Point"}
}