{
  "type": "Feature",
  "properties": {
    "iso:country":"CA",
    "sg:address":"998 Frances St",
    "sg:city":"Ottawa",
    "sg:classifiers":[
        {
            "category":"Social Services",
            "subcategory":"Child Care",
            "type":"Services"
        }
    ],
    "sg:phone":"+1 613 744 0010",
    "sg:postcode":"K1K 3L5",
    "sg:province":"ON",
    "wof:name":"Garderie Providence Day Care",
    "wof:placetype":"venue"
},
  "geometry": {"coordinates":[-75.6478347778,45.4269294739],"type":"Point"}
}