{
  "type": "Feature",
  "properties": {
    "addr:full":"7937 Heron Line Chatham ON N7M 5J8",
    "addr:housenumber":"7937",
    "addr:postcode":"n7m 5j8",
    "addr:street":"Heron Line",
    "iso:country":"CA",
    "sg:address":"7937 Heron Line",
    "sg:city":"Chatham",
    "sg:classifiers":[
        {
            "category":"Building & Trades",
            "subcategory":"Construction",
            "type":"Services"
        }
    ],
    "sg:phone":"+1 519 354 5150",
    "sg:postcode":"N7M 5J8",
    "sg:province":"ON",
    "sg:tags":[
        "concrete",
        "contractor"
    ],
    "wof:name":"John Harris Concrete Ltd",
    "wof:placetype":"venue"
},
  "geometry": {"coordinates":[-82.3017425537,42.442440033],"type":"Point"}
}