{
  "type": "Feature",
  "properties": {
    "iso:country":"CA",
    "sg:address":"152 Gore Vale Ave",
    "sg:city":"Toronto",
    "sg:classifiers":[
        {
            "category":"Building & Trades",
            "subcategory":"Landscaping Services",
            "type":"Services"
        }
    ],
    "sg:phone":"+1 416 603 1995",
    "sg:postcode":"M6J 2R6",
    "sg:province":"ON",
    "sg:tags":[
        "landscape",
        "contractor"
    ],
    "wof:name":"Spring Valley Landscaping",
    "wof:placetype":"venue"
},
  "geometry": {"coordinates":[-79.4130477905,43.6492156982],"type":"Point"}
}