{
  "type": "Feature",
  "properties": {
    "addr:full":"6185 Ordan Dr Mississauga ON L5T 2E1",
    "addr:housenumber":"6185",
    "addr:postcode":"l5t 2e1",
    "addr:street":"Ordan Dr",
    "iso:country":"CA",
    "sg:address":"6185 Ordan Dr",
    "sg:city":"Mississauga",
    "sg:classifiers":[
        {
            "category":"Shopping",
            "subcategory":"Shoes",
            "type":"Retail Goods"
        }
    ],
    "sg:phone":"+1 905 564 5844",
    "sg:postcode":"L5T 2E1",
    "sg:province":"ON",
    "wof:name":"Aldo Shoes Inc",
    "wof:placetype":"venue"
},
  "geometry": {"coordinates":[-79.653419,43.657135],"type":"Point"}
}