{
  "type": "Feature",
  "properties": {
    "addr:full":"Hickson ON N0J 1L0",
    "addr:postcode":"n0j 1l0",
    "iso:country":"CA",
    "sg:city":"Hickson",
    "sg:classifiers":[
        {
            "category":"Professional",
            "subcategory":"Management & Consulting",
            "type":"Services"
        }
    ],
    "sg:phone":"+1 519 462 1033",
    "sg:postcode":"N0J 1L0",
    "sg:province":"ON",
    "sg:tags":[
        "agricultural",
        "consultant"
    ],
    "wof:name":"Trillium Agronomics",
    "wof:placetype":"venue"
},
  "geometry": {"coordinates":[-80.80777740480001,43.2376747131],"type":"Point"}
}