{
  "type": "Feature",
  "properties": {
    "addr:full":"632 Rue DE Lanaudiere Joliette QC J6E 3M7",
    "addr:housenumber":"632",
    "addr:postcode":"j6e 3m7",
    "addr:street":"Rue De Lanaudiere",
    "iso:country":"CA",
    "sg:address":"632 Rue DE Lanaudiere",
    "sg:city":"Joliette",
    "sg:classifiers":[
        {
            "category":"Government",
            "subcategory":"Office",
            "type":"Public Place"
        }
    ],
    "sg:phone":"+1 450 759 2237",
    "sg:postcode":"J6E 3M7",
    "sg:province":"QC",
    "sg:tags":[
        "village"
    ],
    "wof:name":"Joliette Municipalite",
    "wof:placetype":"venue"
},
  "geometry": {"coordinates":[-73.4403762817,46.0214195251],"type":"Point"}
}