{
  "type": "Feature",
  "properties": {
    "addr:full":"169 Boul Du Seminaire N Saint-Jean-Sur-Richelieu QC J3B 5K4",
    "addr:housenumber":"169",
    "addr:postcode":"j3b 5k4",
    "addr:street":"Boul Du Seminaire N",
    "iso:country":"CA",
    "sg:address":"169 Boul Du Seminaire N",
    "sg:city":"Saint-Jean-Sur-Richelieu",
    "sg:classifiers":[
        {
            "category":"Personal",
            "subcategory":"Tanning Parlor",
            "type":"Services"
        }
    ],
    "sg:phone":"+1 450 542 9322",
    "sg:postcode":"J3B 5K4",
    "sg:province":"QC",
    "sg:tags":[
        "salon"
    ],
    "wof:name":"Bronzage Soleil Detente",
    "wof:placetype":"venue"
},
  "geometry": {"coordinates":[-73.26580800000001,45.305069],"type":"Point"}
}