{
  "type": "Feature",
  "properties": {
    "addr:full":"775 Algonquin Ave North Bay ON P1B 4X3",
    "addr:housenumber":"775",
    "addr:postcode":"p1b 4x3",
    "addr:street":"Algonquin Ave",
    "iso:country":"CA",
    "sg:address":"775 Algonquin Ave",
    "sg:city":"North Bay",
    "sg:classifiers":[
        {
            "category":"Health Services",
            "subcategory":"Doctor",
            "type":"Services"
        }
    ],
    "sg:phone":"+1 705 474 6280",
    "sg:postcode":"P1B 4X3",
    "sg:province":"ON",
    "sg:tags":[
        "dentist"
    ],
    "wof:name":"Paleczny, Glenn DDS",
    "wof:placetype":"venue"
},
  "geometry": {"coordinates":[-79.466347,46.322155],"type":"Point"}
}