{
  "type": "Feature",
  "properties": {
    "addr:full":"77 Main St Lions Head ON N0H 1W0",
    "addr:housenumber":"77",
    "addr:postcode":"n0h 1w0",
    "addr:street":"Main St",
    "iso:country":"CA",
    "sg:address":"77 Main St",
    "sg:city":"Lions Head",
    "sg:classifiers":[
        {
            "category":"Professional",
            "subcategory":"Computer Services",
            "type":"Services"
        }
    ],
    "sg:phone":"+1 519 793 3111",
    "sg:postcode":"N0H 1W0",
    "sg:province":"ON",
    "sg:tags":[
        "company",
        "telephone",
        "internet"
    ],
    "wof:name":"Amtelecom Communications",
    "wof:placetype":"venue"
},
  "geometry": {"coordinates":[-81.25451700000001,44.987568],"type":"Point"}
}