{
  "type": "Feature",
  "properties": {
    "iso:country":"CA",
    "sg:address":"10 Hospital St",
    "sg:city":"Miramichi",
    "sg:classifiers":[
        {
            "category":"Health Services",
            "subcategory":"Doctor",
            "type":"Services"
        }
    ],
    "sg:phone":"+1 506 773 3293",
    "sg:postcode":"E1N 3X7",
    "sg:province":"NB",
    "sg:tags":[
        "physician",
        "surgeon"
    ],
    "wof:name":"Losier, Gerard B MD",
    "wof:placetype":"venue"
},
  "geometry": {"coordinates":[-65.4680862427,47.0238761902],"type":"Point"}
}