{
  "type": "Feature",
  "properties": {
    "addr:full":"Burnaby BC V3J 1N3",
    "addr:postcode":"v3j 1n3",
    "iso:country":"CA",
    "sg:city":"Burnaby",
    "sg:classifiers":[
        {
            "category":"Professional",
            "subcategory":"Credit Reporting & Collection",
            "type":"Services"
        }
    ],
    "sg:phone":"+1 604 420 4664",
    "sg:postcode":"V3J 1N3",
    "sg:province":"BC",
    "sg:tags":[
        "agency"
    ],
    "wof:name":"Vanguard Collection Agencies",
    "wof:placetype":"venue"
},
  "geometry": {"coordinates":[-122.893913,49.246338],"type":"Point"}
}