{
  "type": "Feature",
  "properties": {
    "addr:full":"7 Pleasant St Campbellton NB E3N 3T4",
    "addr:housenumber":"7",
    "addr:postcode":"e3n 3t4",
    "addr:street":"Pleasant St",
    "iso:country":"CA",
    "sg:address":"7 Pleasant St",
    "sg:city":"Campbellton",
    "sg:classifiers":[
        {
            "category":"Taxi",
            "type":"Transportation"
        }
    ],
    "sg:phone":"+1 506 753 3366",
    "sg:postcode":"E3N 3T4",
    "sg:province":"NB",
    "sg:tags":[
        "taxicab"
    ],
    "wof:name":"Central Taxi Inc",
    "wof:placetype":"venue"
},
  "geometry": {"coordinates":[-66.6723022461,48.0091362],"type":"Point"}
}