{
  "type": "Feature",
  "properties": {
    "addr:full":"Hwy 5 SE 10-7-14W Glenboro MB R0K 0X0",
    "addr:postcode":"r0k 0x0",
    "addr:street":"Hwy 5 Se 10-7-14W",
    "iso:country":"CA",
    "sg:address":"Hwy 5 SE 10-7-14W",
    "sg:city":"Glenboro",
    "sg:classifiers":[
        {
            "category":"Retail",
            "subcategory":"Veterinary Services",
            "type":"Services"
        }
    ],
    "sg:phone":"+1 204 827 2546",
    "sg:postcode":"R0K 0X0",
    "sg:province":"MB",
    "sg:tags":[
        "veterinarian"
    ],
    "wof:name":"Tomlinson, C A DVM",
    "wof:placetype":"venue"
},
  "geometry": {"coordinates":[-99.29020690919999,49.5583190918],"type":"Point"}
}