{
  "type": "Feature",
  "properties": {
    "addr:full":"134 Mainprize Midale SK S0C 1S0",
    "addr:housenumber":"134",
    "addr:postcode":"s0c 1s0",
    "addr:street":"Mainprize Midale",
    "iso:country":"CA",
    "sg:address":"134 Mainprize",
    "sg:city":"Midale",
    "sg:classifiers":[
        {
            "category":"Organizations",
            "subcategory":"Religious Organization",
            "type":"Services"
        }
    ],
    "sg:phone":"+1 306 458 2284",
    "sg:postcode":"S0C 1S0",
    "sg:province":"SK",
    "sg:tags":[
        "church"
    ],
    "wof:name":"Baptist Church",
    "wof:placetype":"venue"
},
  "geometry": {"coordinates":[-103.410499573,49.3946762085],"type":"Point"}
}