{
  "type": "Feature",
  "properties": {
    "addr:full":"39 Humber St Stratford ON N5A 6S4",
    "addr:housenumber":"39",
    "addr:postcode":"n5a 6s4",
    "addr:street":"Humber St",
    "iso:country":"CA",
    "sg:address":"39 Humber St",
    "sg:city":"Stratford",
    "sg:classifiers":[
        {
            "category":"Building & Trades",
            "subcategory":"Construction",
            "type":"Services"
        }
    ],
    "sg:phone":"+1 519 273 4391",
    "sg:postcode":"N5A 6S4",
    "sg:province":"ON",
    "sg:tags":[
        "concrete",
        "contractor"
    ],
    "wof:name":"Nicholson Concrete",
    "wof:placetype":"venue"
},
  "geometry": {"coordinates":[-80.9825134277,43.3524856567],"type":"Point"}
}