{
  "type": "Feature",
  "properties": {
    "addr:full":"2170 Windsor St Halifax NS B3K 5B6",
    "addr:housenumber":"2170",
    "addr:postcode":"b3k 5b6",
    "addr:street":"Windsor St",
    "iso:country":"CA",
    "sg:address":"2170 Windsor St",
    "sg:city":"Halifax",
    "sg:classifiers":[
        {
            "category":"Personal",
            "subcategory":"Barber",
            "type":"Services"
        }
    ],
    "sg:phone":"+1 902 423 6596",
    "sg:postcode":"B3K 5B6",
    "sg:province":"NS",
    "wof:name":"Phat's Barber Shop",
    "wof:placetype":"venue"
},
  "geometry": {"coordinates":[-63.594909668,44.6496276855],"type":"Point"}
}