{
  "type": "Feature",
  "properties": {
    "addr:full":"260 Rue Hemond Saint-Eustache QC J7P 2C4",
    "addr:housenumber":"260",
    "addr:postcode":"j7p 2c4",
    "addr:street":"Rue Hemond",
    "iso:country":"CA",
    "sg:address":"260 Rue Hemond",
    "sg:city":"Saint-Eustache",
    "sg:classifiers":[
        {
            "category":"Retail",
            "subcategory":"Laundry & Dry Cleaning",
            "type":"Services"
        }
    ],
    "sg:phone":"+1 450 491 0111",
    "sg:postcode":"J7P 2C4",
    "sg:province":"QC",
    "sg:tags":[
        "cleaners"
    ],
    "wof:name":"Nettoyeur Luxor Inc",
    "wof:placetype":"venue"
},
  "geometry": {"coordinates":[-73.901008606,45.5629615784],"type":"Point"}
}