{
  "type": "Feature",
  "properties": {
    "addr:full":"221 Baird Ave Cochrane AB T4C 1C8",
    "addr:housenumber":"221",
    "addr:postcode":"t4c 1c8",
    "addr:street":"Baird Ave",
    "iso:country":"CA",
    "sg:address":"221 Baird Ave",
    "sg:city":"Cochrane",
    "sg:classifiers":[
        {
            "category":"Home & Garden",
            "subcategory":"Building Materials",
            "type":"Retail Goods"
        }
    ],
    "sg:phone":"+1 403 932 6097",
    "sg:postcode":"T4C 1C8",
    "sg:province":"AB",
    "sg:tags":[
        "hardwood"
    ],
    "wof:name":"Buckler's Hardwood Flooring",
    "wof:placetype":"venue"
},
  "geometry": {"coordinates":[-114.458320618,51.1893920898],"type":"Point"}
}