{
  "type": "Feature",
  "properties": {
    "addr:full":"2 John St Newboro ON K0G 1P0",
    "addr:housenumber":"2",
    "addr:postcode":"k0g 1p0",
    "addr:street":"John St",
    "iso:country":"CA",
    "sg:address":"2 John St",
    "sg:city":"Newboro",
    "sg:classifiers":[
        {
            "category":"Health Services",
            "subcategory":"Doctor",
            "type":"Services"
        }
    ],
    "sg:phone":"+1 613 272 2682",
    "sg:postcode":"K0G 1P0",
    "sg:province":"ON",
    "sg:tags":[
        "dentist"
    ],
    "wof:name":"Freeman, Donald DDS",
    "wof:placetype":"venue"
},
  "geometry": {"coordinates":[-76.316742,44.653046],"type":"Point"}
}