{
  "type": "Feature",
  "properties": {
    "iso:country":"CA",
    "sg:address":"170 Curry St",
    "sg:city":"Moncton",
    "sg:classifiers":[
        {
            "category":"Education",
            "subcategory":"School",
            "type":"Public Place"
        }
    ],
    "sg:phone":"+1 506 856 3459",
    "sg:postcode":"E1A 3W1",
    "sg:province":"NB",
    "wof:name":"Sunny Brae Middle School",
    "wof:placetype":"venue"
},
  "geometry": {"coordinates":[-64.7771987915,46.1065330505],"type":"Point"}
}