{
  "type": "Feature",
  "properties": {
    "addr:full":"217 Main St N Exeter ON N0M 1S3",
    "addr:housenumber":"217",
    "addr:postcode":"n0m 1s3",
    "addr:street":"Main St N",
    "iso:country":"CA",
    "sg:address":"217 Main St N",
    "sg:city":"Exeter",
    "sg:classifiers":[
        {
            "category":"Food & Beverages",
            "subcategory":"Bakery",
            "type":"Retail Goods"
        }
    ],
    "sg:phone":"+1 519 235 1838",
    "sg:postcode":"N0M 1S3",
    "sg:province":"ON",
    "sg:tags":[
        "baker"
    ],
    "wof:name":"Donuts Now",
    "wof:placetype":"venue"
},
  "geometry": {"coordinates":[-81.483429,43.36224],"type":"Point"}
}