{
  "type": "Feature",
  "properties": {
    "iso:country":"CA",
    "sg:city":"Mississauga",
    "sg:classifiers":[
        {
            "category":"Health Services",
            "subcategory":"Doctor",
            "type":"Services"
        }
    ],
    "sg:phone":"+1 905 803 0278",
    "sg:postcode":"L5C 4G3",
    "sg:province":"ON",
    "sg:tags":[
        "dentist"
    ],
    "wof:name":"Eller, David DDS",
    "wof:placetype":"venue"
},
  "geometry": {"coordinates":[-79.6545333862,43.576625824],"type":"Point"}
}