{
  "type": "Feature",
  "properties": {
    "addr:full":"983 Boliva Havre-Saint-Pierre QC G0G 1P0",
    "addr:housenumber":"983",
    "addr:postcode":"g0g 1p0",
    "addr:street":"Boliva Havre-Saint-Pierre",
    "iso:country":"CA",
    "sg:address":"983 Boliva",
    "sg:city":"Havre-Saint-Pierre",
    "sg:classifiers":[
        {
            "category":"Organizations",
            "subcategory":"Professional Association",
            "type":"Services"
        }
    ],
    "sg:phone":"+1 418 538 2606",
    "sg:postcode":"G0G 1P0",
    "sg:province":"QC",
    "wof:name":"Association Chasse & Peche",
    "wof:placetype":"venue"
},
  "geometry": {"coordinates":[-63.6068191528,50.2404251099],"type":"Point"}
}