{
  "type": "Feature",
  "properties": {
    "addr:full":"60 Ch Du Fleuve Coteau-Du-Lac QC J0P 1B0",
    "addr:housenumber":"60",
    "addr:postcode":"j0p 1b0",
    "addr:street":"Ch Du Fleuve",
    "iso:country":"CA",
    "sg:address":"60 Ch Du Fleuve",
    "sg:city":"Coteau-Du-Lac",
    "sg:classifiers":[
        {
            "category":"Health Services",
            "subcategory":"Nursing And Care Facility",
            "type":"Services"
        }
    ],
    "sg:phone":"+1 450 267 3379",
    "sg:postcode":"J0P 1B0",
    "sg:province":"QC",
    "sg:tags":[
        "home",
        "convalescent"
    ],
    "wof:name":"Pavillon Laura Ferguson",
    "wof:placetype":"venue"
},
  "geometry": {"coordinates":[-74.195572,45.263008],"type":"Point"}
}