{
  "type": "Feature",
  "properties": {
    "addr:full":"3598 Linda St Innisfil ON L9S 2L2",
    "addr:housenumber":"3598",
    "addr:postcode":"l9s 2l2",
    "addr:street":"Linda St",
    "iso:country":"CA",
    "sg:address":"3598 Linda St",
    "sg:city":"Innisfil",
    "sg:classifiers":[
        {
            "category":"Building & Trades",
            "subcategory":"Construction",
            "type":"Services"
        }
    ],
    "sg:phone":"+1 705 431 8615",
    "sg:postcode":"L9S 2L2",
    "sg:province":"ON",
    "sg:tags":[
        "concrete"
    ],
    "wof:name":"Simcoe Concrete Forming",
    "wof:placetype":"venue"
},
  "geometry": {"coordinates":[-79.52948000000001,44.386017],"type":"Point"}
}