{
  "type": "Feature",
  "properties": {
    "addr:full":"1631 Queen St E Toronto ON M4L 1G4",
    "addr:housenumber":"1631",
    "addr:postcode":"m4l 1g4",
    "addr:street":"Queen St E",
    "iso:country":"CA",
    "sg:address":"1631 Queen St E",
    "sg:city":"Toronto",
    "sg:classifiers":[
        {
            "category":"Social Services",
            "subcategory":"Child Care",
            "type":"Services"
        }
    ],
    "sg:phone":"+1 416 392 5076",
    "sg:postcode":"M4L 1G4",
    "sg:province":"ON",
    "sg:tags":[
        "government"
    ],
    "wof:name":"Toronto Child Care Ctr",
    "wof:placetype":"venue"
},
  "geometry": {"coordinates":[-79.31558200000001,43.666431],"type":"Point"}
}