{
  "type": "Feature",
  "properties": {
    "iso:country":"CA",
    "sg:address":"224 Rue Montcalm",
    "sg:city":"Hull",
    "sg:classifiers":[
        {
            "category":"Personal",
            "subcategory":"Barber",
            "type":"Services"
        }
    ],
    "sg:phone":"+1 819 771 7643",
    "sg:postcode":"J8Y 3B8",
    "sg:province":"QC",
    "wof:name":"Salon Jacques",
    "wof:placetype":"venue"
},
  "geometry": {"coordinates":[-75.731819,45.431259],"type":"Point"}
}