{
  "type": "Feature",
  "properties": {
    "addr:full":"600 Jefferson Ave Winnipeg MB R2V 0P2",
    "addr:housenumber":"600",
    "addr:postcode":"r2v 0p2",
    "addr:street":"Jefferson Ave",
    "iso:country":"CA",
    "sg:address":"600 Jefferson Ave",
    "sg:city":"Winnipeg",
    "sg:classifiers":[
        {
            "category":"Education",
            "subcategory":"School",
            "type":"Public Place"
        }
    ],
    "sg:phone":"+1 204 338 6150",
    "sg:postcode":"R2V 0P2",
    "sg:province":"MB",
    "wof:name":"Faith Academy Middle School",
    "wof:placetype":"venue"
},
  "geometry": {"coordinates":[-97.14004516599999,49.9401397705],"type":"Point"}
}