{
  "type": "Feature",
  "properties": {
    "iso:country":"CA",
    "sg:address":"327 Boul Saint-Martin O",
    "sg:city":"Laval",
    "sg:classifiers":[
        {
            "category":"Restaurant",
            "type":"Food & Drink"
        }
    ],
    "sg:phone":"+1 450 967 9466",
    "sg:postcode":"H7M 1Y7",
    "sg:province":"QC",
    "wof:name":"Restaurant Chanchhaya",
    "wof:placetype":"venue"
},
  "geometry": {"coordinates":[-73.7101364136,45.578830719],"type":"Point"}
}