{
  "type": "Feature",
  "properties": {
    "iso:country":"CA",
    "sg:address":"15802 Stony Plain Rd NW",
    "sg:city":"Edmonton",
    "sg:classifiers":[
        {
            "category":"Wholesale",
            "subcategory":"Auto Parts",
            "type":"Manufacturing & Wholesale Goods"
        }
    ],
    "sg:phone":"+1 780 489 2383",
    "sg:postcode":"T5P 3Z6",
    "sg:province":"AB",
    "sg:tags":[
        "sporting",
        "truck",
        "accessory"
    ],
    "wof:name":"Racks For Cars",
    "wof:placetype":"venue"
},
  "geometry": {"coordinates":[-113.59404000000001,53.541397],"type":"Point"}
}