{
  "type": "Feature",
  "properties": {
    "addr:full":"366 Rue Mayor # 200 Montreal QC H3A 1N8",
    "addr:housenumber":"366",
    "addr:postcode":"h3a 1n8",
    "addr:street":"Rue Mayor # 200",
    "iso:country":"CA",
    "sg:address":"366 Rue Mayor # 200",
    "sg:city":"Montreal",
    "sg:classifiers":[
        {
            "category":"Wholesale",
            "subcategory":"Apparel",
            "type":"Manufacturing & Wholesale Goods"
        }
    ],
    "sg:phone":"+1 514 842 7660",
    "sg:postcode":"H3A 1N8",
    "sg:province":"QC",
    "sg:tags":[
        "clothing"
    ],
    "wof:name":"Jivan Creations Regd",
    "wof:placetype":"venue"
},
  "geometry": {"coordinates":[-73.568459,45.506172],"type":"Point"}
}