{
  "type": "Feature",
  "properties": {
    "iso:country":"CA",
    "sg:city":"Calgary",
    "sg:classifiers":[
        {
            "category":"Government",
            "subcategory":"Office",
            "type":"Public Place"
        }
    ],
    "sg:phone":"+1 403 292 5605",
    "sg:postcode":"T2P 0M9",
    "sg:province":"AB",
    "wof:name":"Canada Measurement",
    "wof:placetype":"venue"
},
  "geometry": {"coordinates":[-114.074645996,51.0485687256],"type":"Point"}
}