{
  "type": "Feature",
  "properties": {
    "addr:full":"Bury QC J0B 1J0",
    "addr:postcode":"j0b 1j0",
    "iso:country":"CA",
    "sg:city":"Bury",
    "sg:classifiers":[
        {
            "category":"Personal",
            "type":"Services"
        }
    ],
    "sg:phone":"+1 819 872 1010",
    "sg:postcode":"J0B 1J0",
    "sg:province":"QC",
    "sg:tags":[
        "therapist",
        "massage"
    ],
    "wof:name":"Sylvie Turmel Masso",
    "wof:placetype":"venue"
},
  "geometry": {"coordinates":[-71.496887,45.473549],"type":"Point"}
}