{
  "type": "Feature",
  "properties": {
    "addr:full":"208 Ferry Rd Cornwall PE C0A 1H0",
    "addr:housenumber":"208",
    "addr:postcode":"c0a 1h0",
    "addr:street":"Ferry Rd",
    "iso:country":"CA",
    "sg:address":"208 Ferry Rd",
    "sg:city":"Cornwall",
    "sg:classifiers":[
        {
            "category":"Travel",
            "subcategory":"Campground",
            "type":"Entertainment"
        }
    ],
    "sg:phone":"+1 902 566 2421",
    "sg:postcode":"C0A 1H0",
    "sg:province":"PE",
    "wof:name":"Holiday Haven Campground",
    "wof:placetype":"venue"
},
  "geometry": {"coordinates":[-63.197101593,46.2262878418],"type":"Point"}
}