{
  "type": "Feature",
  "properties": {
    "addr:full":"2700 Rue King O Sherbrooke QC J1L 1C5",
    "addr:housenumber":"2700",
    "addr:postcode":"j1l 1c5",
    "addr:street":"Rue King O",
    "iso:country":"CA",
    "sg:address":"2700 Rue King O",
    "sg:city":"Sherbrooke",
    "sg:classifiers":[
        {
            "category":"Utilities",
            "subcategory":"Mobile Phone",
            "type":"Services"
        }
    ],
    "sg:phone":"+1 819 823 9994",
    "sg:postcode":"J1L 1C5",
    "sg:province":"QC",
    "sg:tags":[
        "telephone",
        "cellular"
    ],
    "wof:name":"Rcc Sherbrooke Inc",
    "wof:placetype":"venue"
},
  "geometry": {"coordinates":[-71.9389419556,45.3979454041],"type":"Point"}
}