{
  "type": "Feature",
  "properties": {
    "addr:full":"264 Division St Cobourg ON K9A 3R1",
    "addr:housenumber":"264",
    "addr:postcode":"k9a 3r1",
    "addr:street":"Division St",
    "iso:country":"CA",
    "sg:address":"264 Division St",
    "sg:city":"Cobourg",
    "sg:classifiers":[
        {
            "category":"Shopping",
            "subcategory":"Stationery & Office Supplies",
            "type":"Retail Goods"
        }
    ],
    "sg:phone":"+1 905 373 7283",
    "sg:postcode":"K9A 3R1",
    "sg:province":"ON",
    "wof:name":"Discount Office Supply Store",
    "wof:placetype":"venue"
},
  "geometry": {"coordinates":[-78.165695,43.960739],"type":"Point"}
}