{
  "type": "Feature",
  "properties": {
    "addr:full":"Nanaimo BC V9S 5W3",
    "addr:postcode":"v9s 5w3",
    "iso:country":"CA",
    "sg:city":"Nanaimo",
    "sg:classifiers":[
        {
            "category":"Health Services",
            "subcategory":"Doctor",
            "type":"Services"
        }
    ],
    "sg:phone":"+1 250 758 1168",
    "sg:postcode":"V9S 5W3",
    "sg:province":"BC",
    "sg:tags":[
        "dentist"
    ],
    "wof:name":"Brooks Landing Dental Clinic",
    "wof:placetype":"venue"
},
  "geometry": {"coordinates":[-123.967659,49.190746],"type":"Point"}
}