{
  "type": "Feature",
  "properties": {
    "iso:country":"CA",
    "sg:address":"2062 Tomlinson Crt",
    "sg:city":"Kamloops",
    "sg:classifiers":[
        {
            "category":"Wholesale",
            "subcategory":"Machinery & Supplies",
            "type":"Manufacturing & Wholesale Goods"
        }
    ],
    "sg:phone":"+1 250 374 0233",
    "sg:postcode":"V2E 2M7",
    "sg:province":"BC",
    "sg:tags":[
        "equipment",
        "mining",
        "drilling",
        "boring"
    ],
    "wof:name":"Team Manufacturing Ltd",
    "wof:placetype":"venue"
},
  "geometry": {"coordinates":[-120.345359802,50.6463127136],"type":"Point"}
}