{
  "type": "Feature",
  "properties": {
    "addr:full":"PO Box 548 Stettler AB T0C 2L0",
    "addr:housenumber":"po",
    "addr:postcode":"t0c 2l0",
    "addr:street":"Box 548",
    "iso:country":"CA",
    "sg:address":"PO Box 548",
    "sg:city":"Stettler",
    "sg:classifiers":[
        {
            "category":"Shopping",
            "subcategory":"Computers & Home Electronics",
            "type":"Retail Goods"
        }
    ],
    "sg:phone":"+1 403 742 3634",
    "sg:postcode":"T0C 2L0",
    "sg:province":"AB",
    "sg:tags":[
        "equipment",
        "television",
        "electronic",
        "supply"
    ],
    "wof:name":"Bill's Electronic Repair Svc",
    "wof:placetype":"venue"
},
  "geometry": {"coordinates":[-112.71101400000001,52.323536],"type":"Point"}
}