{
  "type": "Feature",
  "properties": {
    "addr:full":"1099 Hamilton St New Westminster BC V3M 2M8",
    "addr:housenumber":"1099",
    "addr:postcode":"v3m 2m8",
    "addr:street":"Hamilton St",
    "iso:country":"CA",
    "sg:address":"1099 Hamilton St",
    "sg:city":"New Westminster",
    "sg:classifiers":[
        {
            "category":"Home & Garden",
            "subcategory":"Building Materials",
            "type":"Retail Goods"
        }
    ],
    "sg:phone":"+1 604 524 8923",
    "sg:postcode":"V3M 2M8",
    "sg:province":"BC",
    "sg:tags":[
        "glass",
        "window",
        "plate"
    ],
    "wof:name":"Fred Cirillo Glass Repair",
    "wof:placetype":"venue"
},
  "geometry": {"coordinates":[-122.93132,49.210796],"type":"Point"}
}