{
  "type": "Feature",
  "properties": {
    "addr:full":"Stittsville ON K2S 1B8",
    "addr:postcode":"k2s 1b8",
    "iso:country":"CA",
    "sg:city":"Stittsville",
    "sg:classifiers":[
        {
            "category":"Retail",
            "subcategory":"Laundry & Dry Cleaning",
            "type":"Services"
        }
    ],
    "sg:phone":"+1 613 831 7827",
    "sg:postcode":"K2S 1B8",
    "sg:province":"ON",
    "sg:tags":[
        "cleaners"
    ],
    "wof:name":"Star Fashion Cleaners",
    "wof:placetype":"venue"
},
  "geometry": {"coordinates":[-75.927216,45.263855],"type":"Point"}
}