{
  "type": "Feature",
  "properties": {
    "addr:full":"Coquitlam BC V3B 6B4",
    "addr:postcode":"v3b 6b4",
    "iso:country":"CA",
    "sg:city":"Coquitlam",
    "sg:classifiers":[
        {
            "category":"Professional",
            "subcategory":"Accounting & Tax Preparation",
            "type":"Services"
        }
    ],
    "sg:phone":"+1 604 464 1437",
    "sg:postcode":"V3B 6B4",
    "sg:province":"BC",
    "sg:tags":[
        "accountant"
    ],
    "wof:name":"Mc Bride Lauwers & Bosma",
    "wof:placetype":"venue"
},
  "geometry": {"coordinates":[-122.792472839,49.2790184021],"type":"Point"}
}