{
  "type": "Feature",
  "properties": {
    "addr:full":"525 Dominion Midland ON L4R 1P7",
    "addr:housenumber":"525",
    "addr:postcode":"l4r 1p7",
    "addr:street":"Dominion",
    "iso:country":"CA",
    "sg:address":"525 Dominion",
    "sg:city":"Midland",
    "sg:classifiers":[
        {
            "category":"Government",
            "subcategory":"Office",
            "type":"Public Place"
        }
    ],
    "sg:phone":"+1 705 526 3746",
    "sg:postcode":"L4R 1P7",
    "sg:province":"ON",
    "wof:name":"Canada Employment Ctr",
    "wof:placetype":"venue"
},
  "geometry": {"coordinates":[-79.88665008540001,44.7505683899],"type":"Point"}
}