{
  "type": "Feature",
  "properties": {
    "addr:full":"4 Davis Lane Hare Bay Bb NL A0G 2P0",
    "addr:housenumber":"4",
    "addr:postcode":"a0g 2p0",
    "addr:street":"Davis Lane",
    "iso:country":"CA",
    "sg:address":"4 Davis Lane",
    "sg:city":"Hare Bay Bb",
    "sg:classifiers":[
        {
            "category":"Freight",
            "type":"Transportation"
        }
    ],
    "sg:phone":"+1 709 537 2159",
    "sg:postcode":"A0G 2P0",
    "sg:province":"NL",
    "sg:tags":[
        "trucking"
    ],
    "wof:name":"J & G Trucking",
    "wof:placetype":"venue"
},
  "geometry": {"coordinates":[-54.010029,48.854649],"type":"Point"}
}