{
  "type": "Feature",
  "properties": {
    "addr:full":"North York ON M5M 1C4",
    "addr:postcode":"m5m 1c4",
    "iso:country":"CA",
    "sg:city":"North York",
    "sg:classifiers":[
        {
            "category":"Retail",
            "subcategory":"Veterinary Services",
            "type":"Services"
        }
    ],
    "sg:phone":"+1 416 787 1831",
    "sg:postcode":"M5M 1C4",
    "sg:province":"ON",
    "sg:tags":[
        "veterinarian"
    ],
    "wof:name":"Lawrence Veterinary Clinic",
    "wof:placetype":"venue"
},
  "geometry": {"coordinates":[-79.4292984009,43.7195205688],"type":"Point"}
}