{
  "type": "Feature",
  "properties": {
    "addr:full":"Quebec QC G1N 3Y5",
    "addr:postcode":"g1n 3y5",
    "iso:country":"CA",
    "sg:city":"Quebec",
    "sg:classifiers":[
        {
            "category":"Social Services",
            "type":"Services"
        }
    ],
    "sg:phone":"+1 418 687 5423",
    "sg:postcode":"G1N 3Y5",
    "sg:province":"QC",
    "sg:tags":[
        "organization",
        "welfare"
    ],
    "wof:name":"Residence DE L'Entraide",
    "wof:placetype":"venue"
},
  "geometry": {"coordinates":[-71.2880859375,46.80834198],"type":"Point"}
}