{
  "type": "Feature",
  "properties": {
    "addr:full":"Kingston NS B0P 1R0",
    "addr:postcode":"b0p 1r0",
    "iso:country":"CA",
    "sg:city":"Kingston",
    "sg:classifiers":[
        {
            "category":"Retail",
            "subcategory":"Animal Services",
            "type":"Services"
        }
    ],
    "sg:phone":"+1 902 765 2500",
    "sg:postcode":"B0P 1R0",
    "sg:province":"NS",
    "sg:tags":[
        "pet",
        "boarding",
        "grooming",
        "washing",
        "sitting"
    ],
    "wof:name":"Mac Beth's Grooming & Boarding",
    "wof:placetype":"venue"
},
  "geometry": {"coordinates":[-64.9493560791,44.9874382019],"type":"Point"}
}