{
  "type": "Feature",
  "properties": {
    "addr:full":"5621 Av Du Pont N Alma QC G8E 1V7",
    "addr:housenumber":"5621",
    "addr:postcode":"g8e 1v7",
    "addr:street":"Av Du Pont N",
    "iso:country":"CA",
    "sg:address":"5621 Av Du Pont N",
    "sg:city":"Alma",
    "sg:classifiers":[
        {
            "category":"Restaurant",
            "type":"Food & Drink"
        }
    ],
    "sg:phone":"+1 418 347 3003",
    "sg:postcode":"G8E 1V7",
    "sg:province":"QC",
    "wof:name":"Resto-Pub Chez Jules",
    "wof:placetype":"venue"
},
  "geometry": {"coordinates":[-71.695412,48.631775],"type":"Point"}
}