{
  "type": "Feature",
  "properties": {
    "addr:full":"1064 Moyer Dr Sherwood Park AB T8A 1E6",
    "addr:housenumber":"1064",
    "addr:postcode":"t8a 1e6",
    "addr:street":"Moyer Dr",
    "iso:country":"CA",
    "sg:address":"1064 Moyer Dr",
    "sg:city":"Sherwood Park",
    "sg:classifiers":[
        {
            "category":"Retail",
            "subcategory":"Repair Shop",
            "type":"Services"
        }
    ],
    "sg:phone":"+1 780 467 6380",
    "sg:postcode":"T8A 1E6",
    "sg:province":"AB",
    "sg:tags":[
        "repairing",
        "piano",
        "refinishing"
    ],
    "wof:name":"Piano Action",
    "wof:placetype":"venue"
},
  "geometry": {"coordinates":[-113.330741882,53.5195846558],"type":"Point"}
}