{
  "type": "Feature",
  "properties": {
    "iso:country":"CA",
    "sg:address":"4553 Park Ave",
    "sg:city":"Terrace",
    "sg:classifiers":[
        {
            "category":"Social Services",
            "type":"Services"
        }
    ],
    "sg:phone":"+1 250 638 1863",
    "sg:postcode":"V8G 1V3",
    "sg:province":"BC",
    "sg:tags":[
        "community"
    ],
    "wof:name":"Family Place One Stop Access",
    "wof:placetype":"venue"
},
  "geometry": {"coordinates":[-128.58184814399999,54.5176391602],"type":"Point"}
}