{
  "type": "Feature",
  "properties": {
    "addr:full":"2108 Albert St Regina SK S4P 2T9",
    "addr:housenumber":"2108",
    "addr:postcode":"s4p 2t9",
    "addr:street":"Albert St",
    "iso:country":"CA",
    "sg:address":"2108 Albert St",
    "sg:city":"Regina",
    "sg:classifiers":[
        {
            "category":"Food & Beverages",
            "subcategory":"Groceries & Convenience Stores",
            "type":"Retail Goods"
        }
    ],
    "sg:phone":"+1 306 347 7866",
    "sg:postcode":"S4P 2T9",
    "sg:province":"SK",
    "wof:name":"Mac's Convenience Stores Ltd",
    "wof:placetype":"venue"
},
  "geometry": {"coordinates":[-104.61833190900001,50.4452705383],"type":"Point"}
}