{
  "type": "Feature",
  "properties": {
    "addr:full":"1 O'Connor Dr Jacksons Point ON L0E 1L0",
    "addr:housenumber":"1",
    "addr:postcode":"l0e 1l0",
    "addr:street":"O'Connor Dr Jacksons Point",
    "iso:country":"CA",
    "sg:address":"1 O'Connor Dr",
    "sg:city":"Jacksons Point",
    "sg:classifiers":[
        {
            "category":"Shopping",
            "type":"Retail Goods"
        }
    ],
    "sg:phone":"+1 905 722 9448",
    "sg:postcode":"L0E 1L0",
    "sg:province":"ON",
    "sg:tags":[
        "picture",
        "frame",
        "art",
        "gallery",
        "dealer"
    ],
    "wof:name":"Kat's Gallery & Framing Shop",
    "wof:placetype":"venue"
},
  "geometry": {"coordinates":[-79.370262146,44.3225898743],"type":"Point"}
}