{
  "type": "Feature",
  "properties": {
    "addr:full":"24 Scarlett Rd York ON M6N 4K1",
    "addr:housenumber":"24",
    "addr:postcode":"m6n 4k1",
    "addr:street":"Scarlett Rd",
    "iso:country":"CA",
    "sg:address":"24 Scarlett Rd",
    "sg:city":"York",
    "sg:classifiers":[
        {
            "category":"Personal",
            "subcategory":"Beauty Salon",
            "type":"Services"
        }
    ],
    "sg:phone":"+1 416 762 0886",
    "sg:postcode":"M6N 4K1",
    "sg:province":"ON",
    "wof:name":"Style Nails",
    "wof:placetype":"venue"
},
  "geometry": {"coordinates":[-79.50009900000001,43.667393],"type":"Point"}
}