{
  "type": "Feature",
  "properties": {
    "addr:full":"Vancouver BC V6G 2V3",
    "addr:postcode":"v6g 2v3",
    "iso:country":"CA",
    "sg:city":"Vancouver",
    "sg:classifiers":[
        {
            "category":"Professional",
            "subcategory":"Detective & Security Services",
            "type":"Services"
        }
    ],
    "sg:phone":"+1 604 685 6011",
    "sg:postcode":"V6G 2V3",
    "sg:province":"BC",
    "sg:tags":[
        "guard",
        "patrol"
    ],
    "wof:name":"Securiguard Services",
    "wof:placetype":"venue"
},
  "geometry": {"coordinates":[-123.130752563,49.2908401489],"type":"Point"}
}