{
  "type": "Feature",
  "properties": {
    "addr:full":"181 University Ave #1206 Toronto ON M5H 3M7",
    "addr:housenumber":"181",
    "addr:postcode":"m5h 3m7",
    "addr:street":"University Ave # 1206",
    "iso:country":"CA",
    "sg:address":"181 University Ave #1206",
    "sg:city":"Toronto",
    "sg:classifiers":[
        {
            "category":"Banks & Credit Unions",
            "subcategory":"Bank",
            "type":"Services"
        }
    ],
    "sg:phone":"+1 416 947 1492",
    "sg:postcode":"M5H 3M7",
    "sg:province":"ON",
    "sg:tags":[
        "financing"
    ],
    "wof:name":"Techbanc Inc",
    "wof:placetype":"venue"
},
  "geometry": {"coordinates":[-79.3854141235,43.6490478516],"type":"Point"}
}