{
  "type": "Feature",
  "properties": {
    "addr:full":"1671 6E Av Grand-Mere QC G9T 2K2",
    "addr:housenumber":"1671",
    "addr:postcode":"g9t 2k2",
    "addr:street":"6E Av Grand-Mere",
    "iso:country":"CA",
    "sg:address":"1671 6E Av",
    "sg:city":"Grand-Mere",
    "sg:classifiers":[
        {
            "category":"Personal",
            "subcategory":"Beauty Salon",
            "type":"Services"
        }
    ],
    "sg:phone":"+1 819 538 6838",
    "sg:postcode":"G9T 2K2",
    "sg:province":"QC",
    "wof:name":"Salon Impulsion Coiffure",
    "wof:placetype":"venue"
},
  "geometry": {"coordinates":[-72.70536,46.605499],"type":"Point"}
}