{
  "type": "Feature",
  "properties": {
    "iso:country":"CA",
    "sg:address":"2130 Bleams Rd",
    "sg:city":"Petersburg",
    "sg:classifiers":[
        {
            "category":"Building & Trades",
            "subcategory":"Construction",
            "type":"Services"
        }
    ],
    "sg:phone":"+1 519 634 5553",
    "sg:postcode":"N0B 2H0",
    "sg:province":"ON",
    "sg:tags":[
        "masonry",
        "contractor"
    ],
    "wof:name":"E & G Miller Masonry Constr",
    "wof:placetype":"venue"
},
  "geometry": {"coordinates":[-80.6027832031,43.4138717651],"type":"Point"}
}