{
  "type": "Feature",
  "properties": {
    "addr:full":"1221 Topsail Rd Mount Pearl NL A1N 5G2",
    "addr:housenumber":"1221",
    "addr:postcode":"a1n 5g2",
    "addr:street":"Topsail Rd",
    "iso:country":"CA",
    "sg:address":"1221 Topsail Rd",
    "sg:city":"Mount Pearl",
    "sg:classifiers":[
        {
            "category":"Building & Trades",
            "subcategory":"Construction",
            "type":"Services"
        }
    ],
    "sg:phone":"+1 709 368 2654",
    "sg:postcode":"A1N 5G2",
    "sg:province":"NL",
    "sg:tags":[
        "masonry",
        "contractor"
    ],
    "wof:name":"Superior Masonry Ltd",
    "wof:placetype":"venue"
},
  "geometry": {"coordinates":[-52.827454,47.528828],"type":"Point"}
}