{
  "type": "Feature",
  "properties": {
    "addr:full":"Burlington ON L7R 2L8",
    "addr:postcode":"l7r 2l8",
    "iso:country":"CA",
    "sg:city":"Burlington",
    "sg:classifiers":[
        {
            "category":"Personal",
            "subcategory":"Beauty Salon",
            "type":"Services"
        }
    ],
    "sg:phone":"+1 905 631 8810",
    "sg:postcode":"L7R 2L8",
    "sg:province":"ON",
    "wof:name":"Hairitage House",
    "wof:placetype":"venue"
},
  "geometry": {"coordinates":[-79.79594400000001,43.326122],"type":"Point"}
}