{
  "type": "Feature",
  "properties": {
    "addr:full":"Erbs Cove NB E5N 1X1",
    "addr:postcode":"e5n 1x1",
    "addr:street":"Cove",
    "iso:country":"CA",
    "sg:city":"Erbs Cove",
    "sg:classifiers":[
        {
            "category":"Professional",
            "subcategory":"Accounting & Tax Preparation",
            "type":"Services"
        }
    ],
    "sg:phone":"+1 506 832 2460",
    "sg:postcode":"E5N 1X1",
    "sg:province":"NB",
    "sg:tags":[
        "accountant"
    ],
    "wof:name":"Urquhart, R Dale",
    "wof:placetype":"venue"
},
  "geometry": {"coordinates":[-65.9361953735,45.5851097107],"type":"Point"}
}