{
  "type": "Feature",
  "properties": {
    "iso:country":"CA",
    "sg:address":"25 Montreal Rd",
    "sg:city":"Vanier",
    "sg:classifiers":[
        {
            "category":"Professional",
            "subcategory":"Computer Services",
            "type":"Services"
        }
    ],
    "sg:phone":"+1 613 747 1070",
    "sg:postcode":"K1L 6E8",
    "sg:province":"ON",
    "sg:tags":[
        "repair",
        "printer"
    ],
    "wof:name":"Office Equipment Specialists",
    "wof:placetype":"venue"
},
  "geometry": {"coordinates":[-75.6689910889,45.433391571],"type":"Point"}
}