{
  "type": "Feature",
  "properties": {
    "addr:full":"1709 Bloor St W Toronto ON M6P 4E5",
    "addr:housenumber":"1709",
    "addr:postcode":"m6p 4e5",
    "addr:street":"Bloor St W",
    "iso:country":"CA",
    "sg:address":"1709 Bloor St W",
    "sg:city":"Toronto",
    "sg:classifiers":[
        {
            "category":"Professional",
            "subcategory":"Lawyer & Legal Services",
            "type":"Services"
        }
    ],
    "sg:phone":"+1 416 769 3522",
    "sg:postcode":"M6P 4E5",
    "sg:province":"ON",
    "sg:tags":[
        "attorney"
    ],
    "wof:name":"Anderson, Dwight",
    "wof:placetype":"venue"
},
  "geometry": {"coordinates":[-79.4590301514,43.6547889709],"type":"Point"}
}