{
  "type": "Feature",
  "properties": {
    "iso:country":"CA",
    "sg:address":"341 3rd Ave W",
    "sg:city":"Unity",
    "sg:classifiers":[
        {
            "category":"Retail",
            "subcategory":"Portrait Studio",
            "type":"Services"
        }
    ],
    "sg:phone":"+1 306 228 2458",
    "sg:postcode":"S0K 4L0",
    "sg:province":"SK",
    "sg:tags":[
        "photography"
    ],
    "wof:name":"Unity Photos",
    "wof:placetype":"venue"
},
  "geometry": {"coordinates":[-109.163444519,52.4459342957],"type":"Point"}
}