{
  "type": "Feature",
  "properties": {
    "addr:full":"5 Centenniel Cres Melville SK S0A 2P0",
    "addr:housenumber":"5",
    "addr:postcode":"s0a 2p0",
    "addr:street":"Centenniel Cres",
    "iso:country":"CA",
    "sg:address":"5 Centenniel Cres",
    "sg:city":"Melville",
    "sg:classifiers":[
        {
            "category":"Shopping",
            "subcategory":"Luggage & Leather Goods",
            "type":"Retail Goods"
        }
    ],
    "sg:phone":"+1 306 728 5018",
    "sg:postcode":"S0A 2P0",
    "sg:province":"SK",
    "wof:name":"Gene Arnold's Harness Repair",
    "wof:placetype":"venue"
},
  "geometry": {"coordinates":[-102.788231,50.929493],"type":"Point"}
}