{
  "type": "Feature",
  "properties": {
    "addr:full":"Queen Charlotte BC V0T 1S1",
    "addr:postcode":"v0t 1s1",
    "iso:country":"CA",
    "sg:city":"Queen Charlotte",
    "sg:classifiers":[
        {
            "category":"Shopping",
            "subcategory":"Jewelry",
            "type":"Retail Goods"
        }
    ],
    "sg:phone":"+1 250 559 8013",
    "sg:postcode":"V0T 1S1",
    "sg:province":"BC",
    "sg:tags":[
        "shop",
        "gift"
    ],
    "wof:name":"Longhouse Gift Shop",
    "wof:placetype":"venue"
},
  "geometry": {"coordinates":[-131.991714,53.262383],"type":"Point"}
}