{
  "type": "Feature",
  "properties": {
    "addr:full":"274 Lakeshore Dr W Penticton BC V2A 1B8",
    "addr:housenumber":"274",
    "addr:postcode":"v2a 1b8",
    "addr:street":"Lakeshore Dr W",
    "iso:country":"CA",
    "sg:address":"274 Lakeshore Dr W",
    "sg:city":"Penticton",
    "sg:classifiers":[
        {
            "category":"Travel",
            "subcategory":"Hotels & Motels",
            "type":"Entertainment"
        }
    ],
    "sg:phone":"+1 250 492 4008",
    "sg:postcode":"V2A 1B8",
    "sg:province":"BC",
    "wof:name":"Penticton Slumber Lodge",
    "wof:placetype":"venue"
},
  "geometry": {"coordinates":[-119.599014,49.501816],"type":"Point"}
}