{
  "type": "Feature",
  "properties": {
    "addr:full":"3285 Simcoe St N Oshawa ON L1H 7K4",
    "addr:housenumber":"3285",
    "addr:postcode":"l1h 7k4",
    "addr:street":"Simcoe St N",
    "iso:country":"CA",
    "sg:address":"3285 Simcoe St N",
    "sg:city":"Oshawa",
    "sg:classifiers":[
        {
            "category":"Organizations",
            "subcategory":"Religious Organization",
            "type":"Services"
        }
    ],
    "sg:phone":"+1 905 655 8852",
    "sg:postcode":"L1H 7K4",
    "sg:province":"ON",
    "sg:tags":[
        "church"
    ],
    "wof:name":"Columbus United Church",
    "wof:placetype":"venue"
},
  "geometry": {"coordinates":[-78.910622,43.981129],"type":"Point"}
}