{
  "type": "Feature",
  "properties": {
    "addr:full":"Vanier QC G1M 3B2",
    "addr:postcode":"g1m 3b2",
    "iso:country":"CA",
    "sg:city":"Vanier",
    "sg:classifiers":[
        {
            "category":"Manufacturing",
            "subcategory":"Motor Vehicles & Parts",
            "type":"Manufacturing & Wholesale Goods"
        }
    ],
    "sg:phone":"+1 418 681 2212",
    "sg:postcode":"G1M 3B2",
    "sg:province":"QC",
    "sg:tags":[
        "transmission"
    ],
    "wof:name":"Convertisseurs Plus Gv Inc",
    "wof:placetype":"venue"
},
  "geometry": {"coordinates":[-71.264442,46.82156],"type":"Point"}
}