{
  "type": "Feature",
  "properties": {
    "addr:full":"19947 56 Ave Langley BC V3A 3Y2",
    "addr:housenumber":"19947",
    "addr:postcode":"v3a 3y2",
    "addr:street":"56 Ave",
    "iso:country":"CA",
    "sg:address":"19947 56 Ave",
    "sg:city":"Langley",
    "sg:classifiers":[
        {
            "category":"Wholesale",
            "subcategory":"Durable Goods & Equipment",
            "type":"Manufacturing & Wholesale Goods"
        }
    ],
    "sg:phone":"+1 604 533 2876",
    "sg:postcode":"V3A 3Y2",
    "sg:province":"BC",
    "sg:tags":[
        "fire",
        "extinguisher"
    ],
    "wof:name":"Allied Surrey Fire & Safety",
    "wof:placetype":"venue"
},
  "geometry": {"coordinates":[-122.670051575,49.1045303345],"type":"Point"}
}