{
  "type": "Feature",
  "properties": {
    "addr:full":"Laval QC H7J 1G6",
    "addr:postcode":"h7j 1g6",
    "iso:country":"CA",
    "sg:city":"Laval",
    "sg:classifiers":[
        {
            "category":"Farming",
            "subcategory":"Farm",
            "type":"Manufacturing & Wholesale Goods"
        }
    ],
    "sg:phone":"+1 450 628 0702",
    "sg:postcode":"H7J 1G6",
    "sg:province":"QC",
    "wof:name":"Fermes Berard Enr",
    "wof:placetype":"venue"
},
  "geometry": {"coordinates":[-73.7134933472,45.6508636475],"type":"Point"}
}