{
  "type": "Feature",
  "properties": {
    "iso:country":"CA",
    "sg:address":"15830 100A Ave NW",
    "sg:city":"Edmonton",
    "sg:classifiers":[
        {
            "category":"Shopping",
            "type":"Retail Goods"
        }
    ],
    "sg:phone":"+1 780 483 7592",
    "sg:postcode":"T5P 0L8",
    "sg:province":"AB",
    "sg:tags":[
        "breast",
        "artificial"
    ],
    "wof:name":"Specially For You",
    "wof:placetype":"venue"
},
  "geometry": {"coordinates":[-113.594604492,53.5404853821],"type":"Point"}
}