{
  "type": "Feature",
  "properties": {
    "iso:country":"CA",
    "sg:address":"200 Wallinger Ave",
    "sg:city":"Kimberley",
    "sg:classifiers":[
        {
            "category":"Banks & Credit Unions",
            "subcategory":"Bank",
            "type":"Services"
        }
    ],
    "sg:phone":"+1 250 427 2288",
    "sg:postcode":"V1A 1Z1",
    "sg:province":"BC",
    "wof:name":"Kootenay Savings Credit Union",
    "wof:placetype":"venue"
},
  "geometry": {"coordinates":[-115.98230743400001,49.6853790283],"type":"Point"}
}