{
  "type": "Feature",
  "properties": {
    "addr:full":"5267 10A Ave Delta BC V4M 1Y5",
    "addr:housenumber":"5267",
    "addr:postcode":"v4m 1y5",
    "addr:street":"10A Ave",
    "iso:country":"CA",
    "sg:address":"5267 10A Ave",
    "sg:city":"Delta",
    "sg:classifiers":[
        {
            "category":"Shopping",
            "type":"Retail Goods"
        }
    ],
    "sg:phone":"+1 604 948 1308",
    "sg:postcode":"V4M 1Y5",
    "sg:province":"BC",
    "sg:tags":[
        "cosmetic",
        "perfume"
    ],
    "wof:name":"Mary Kay Cosmetics",
    "wof:placetype":"venue"
},
  "geometry": {"coordinates":[-123.05961600000001,49.084801],"type":"Point"}
}