{
  "type": "Feature",
  "properties": {
    "addr:full":"Saint-Andre-Avellin QC J0V 1W0",
    "addr:postcode":"j0v 1w0",
    "iso:country":"CA",
    "sg:city":"Saint-Andre-Avellin",
    "sg:classifiers":[
        {
            "category":"Building & Trades",
            "subcategory":"Pest Control",
            "type":"Services"
        }
    ],
    "sg:phone":"+1 819 983 3924",
    "sg:postcode":"J0V 1W0",
    "sg:province":"QC",
    "wof:name":"Extermination Le Vert",
    "wof:placetype":"venue"
},
  "geometry": {"coordinates":[-75.0551986694,45.7229499817],"type":"Point"}
}