{
  "type": "Feature",
  "properties": {
    "addr:full":"150 Laguna Pky Brechin ON L0K 1B0",
    "addr:housenumber":"150",
    "addr:postcode":"l0k 1b0",
    "addr:street":"Laguna Pky",
    "iso:country":"CA",
    "sg:address":"150 Laguna Pky",
    "sg:city":"Brechin",
    "sg:classifiers":[
        {
            "category":"Recreation",
            "subcategory":"Marina",
            "type":"Entertainment"
        }
    ],
    "sg:phone":"+1 705 484 5063",
    "sg:postcode":"L0K 1B0",
    "sg:province":"ON",
    "wof:name":"Lagoon City Marine Ctr",
    "wof:placetype":"venue"
},
  "geometry": {"coordinates":[-79.20579528810001,44.5537872314],"type":"Point"}
}