{
  "type": "Feature",
  "properties": {
    "iso:country":"CA",
    "sg:address":"13605 Highway 3",
    "sg:city":"Bridgewater",
    "sg:classifiers":[
        {
            "category":"Building & Trades",
            "subcategory":"Electrical",
            "type":"Services"
        }
    ],
    "sg:phone":"+1 902 527 0252",
    "sg:postcode":"B4V 2W2",
    "sg:province":"NS",
    "sg:tags":[
        "electric",
        "contractor"
    ],
    "wof:name":"Mason Quentin Electrical Svc",
    "wof:placetype":"venue"
},
  "geometry": {"coordinates":[-64.5230331421,44.3804969788],"type":"Point"}
}