{
  "type": "Feature",
  "properties": {
    "addr:full":"700 D'Arcy St # 3 Cobourg ON K9A 5T3",
    "addr:housenumber":"700",
    "addr:postcode":"k9a 5t3",
    "addr:street":"D'Arcy St # 3",
    "iso:country":"CA",
    "sg:address":"700 D'Arcy St # 3",
    "sg:city":"Cobourg",
    "sg:classifiers":[
        {
            "category":"Social Services",
            "type":"Services"
        }
    ],
    "sg:phone":"+1 905 377 0192",
    "sg:postcode":"K9A 5T3",
    "sg:province":"ON",
    "sg:tags":[
        "organization",
        "welfare"
    ],
    "wof:name":"Five Counties Children's Ctr",
    "wof:placetype":"venue"
},
  "geometry": {"coordinates":[-78.1677780151,43.9595794678],"type":"Point"}
}