{
  "type": "Feature",
  "properties": {
    "addr:full":"410 Centre Ave Stonewall MB R0C 2Z0",
    "addr:housenumber":"410",
    "addr:postcode":"r0c 2z0",
    "addr:street":"Centre Ave",
    "iso:country":"CA",
    "sg:address":"410 Centre Ave",
    "sg:city":"Stonewall",
    "sg:classifiers":[
        {
            "category":"Banks & Credit Unions",
            "subcategory":"Investment Brokerage",
            "type":"Services"
        }
    ],
    "sg:phone":"+1 204 467 2153",
    "sg:postcode":"R0C 2Z0",
    "sg:province":"MB",
    "wof:name":"Credential Securities",
    "wof:placetype":"venue"
},
  "geometry": {"coordinates":[-97.322357,50.134701],"type":"Point"}
}