{
  "type": "Feature",
  "properties": {
    "addr:full":"Vanier QC G1M 3R8",
    "addr:postcode":"g1m 3r8",
    "iso:country":"CA",
    "sg:city":"Vanier",
    "sg:classifiers":[
        {
            "category":"Health Services",
            "subcategory":"Optometrist",
            "type":"Services"
        }
    ],
    "sg:phone":"+1 418 682 6612",
    "sg:postcode":"G1M 3R8",
    "sg:province":"QC",
    "wof:name":"Latour, Leome-Denis",
    "wof:placetype":"venue"
},
  "geometry": {"coordinates":[-71.27471923829999,46.8262405396],"type":"Point"}
}