{
  "type": "Feature",
  "properties": {
    "addr:full":"PO Box 40 Makwa SK S0M 1N0",
    "addr:housenumber":"po box 40",
    "addr:postcode":"s0m 1n0",
    "addr:street":"Makwa",
    "iso:country":"CA",
    "sg:address":"PO Box 40",
    "sg:city":"Makwa",
    "sg:classifiers":[
        {
            "category":"Education",
            "subcategory":"Library",
            "type":"Public Place"
        }
    ],
    "sg:phone":"+1 306 236 3995",
    "sg:postcode":"S0M 1N0",
    "sg:province":"SK",
    "wof:name":"Makwa Lakeland Library",
    "wof:placetype":"venue"
},
  "geometry": {"coordinates":[-108.905205,54.006096],"type":"Point"}
}