{
  "type": "Feature",
  "properties": {
    "addr:full":"1333 Av Du Phare O Matane QC G4W 3M6",
    "addr:housenumber":"1333",
    "addr:postcode":"g4w 3m6",
    "addr:street":"Av Du Phare O",
    "iso:country":"CA",
    "sg:address":"1333 Av Du Phare O",
    "sg:city":"Matane",
    "sg:classifiers":[
        {
            "category":"Government",
            "subcategory":"Police Station",
            "type":"Public Place"
        }
    ],
    "sg:phone":"+1 418 562 2222",
    "sg:postcode":"G4W 3M6",
    "sg:province":"QC",
    "sg:tags":[
        "department"
    ],
    "wof:name":"Quebec Police",
    "wof:placetype":"venue"
},
  "geometry": {"coordinates":[-67.56353,48.841248],"type":"Point"}
}