{
  "type": "Feature",
  "properties": {
    "addr:full":"317 Albert St E Sault Ste Marie ON P6A 2J7",
    "addr:housenumber":"317",
    "addr:postcode":"p6a 2j7",
    "addr:street":"Albert St E",
    "iso:country":"CA",
    "sg:address":"317 Albert St E",
    "sg:city":"Sault Ste Marie",
    "sg:classifiers":[
        {
            "category":"Communications",
            "subcategory":"Radio Station",
            "type":"Services"
        }
    ],
    "sg:phone":"+1 705 941 0101",
    "sg:postcode":"P6A 2J7",
    "sg:province":"ON",
    "sg:tags":[
        "company",
        "broadcasting",
        "advertising"
    ],
    "wof:name":"Wsue 101 FM",
    "wof:placetype":"venue"
},
  "geometry": {"coordinates":[-84.3341140747,46.5140838623],"type":"Point"}
}