{
  "type": "Feature",
  "properties": {
    "iso:country":"CA",
    "sg:city":"Sudbury",
    "sg:classifiers":[
        {
            "category":"Shopping",
            "subcategory":"Stationery & Office Supplies",
            "type":"Retail Goods"
        }
    ],
    "sg:phone":"+1 705 523 2167",
    "sg:postcode":"P3E 3C5",
    "sg:province":"ON",
    "sg:tags":[
        "educational",
        "material"
    ],
    "wof:name":"Scholar's Choice",
    "wof:placetype":"venue"
},
  "geometry": {"coordinates":[-81.00220489500001,46.4540367126],"type":"Point"}
}