{
  "type": "Feature",
  "properties": {
    "iso:country":"CA",
    "sg:address":"1028 Notre Dame St",
    "sg:city":"Embrun",
    "sg:classifiers":[
        {
            "category":"Personal",
            "subcategory":"Beauty Salon",
            "type":"Services"
        }
    ],
    "sg:phone":"+1 613 443 3579",
    "sg:postcode":"K0A 1W0",
    "sg:province":"ON",
    "sg:tags":[
        "barber"
    ],
    "wof:name":"Cuts & Go",
    "wof:placetype":"venue"
},
  "geometry": {"coordinates":[-75.27555847169999,45.2737045288],"type":"Point"}
}