{
  "type": "Feature",
  "properties": {
    "iso:country":"CA",
    "sg:address":"270 Ch Du Rocher",
    "sg:city":"Eastman",
    "sg:classifiers":[
        {
            "category":"Health Services",
            "subcategory":"Health Practitioner",
            "type":"Services"
        }
    ],
    "sg:phone":"+1 450 297 0099",
    "sg:postcode":"J0E 1P0",
    "sg:province":"QC",
    "sg:tags":[
        "psychotherapist"
    ],
    "wof:name":"Racette, Louise",
    "wof:placetype":"venue"
},
  "geometry": {"coordinates":[-72.3162765503,45.301525116],"type":"Point"}
}