{
  "type": "Feature",
  "properties": {
    "iso:country":"CA",
    "sg:address":"8931 Rang Saint-Vincent",
    "sg:city":"Mirabel",
    "sg:classifiers":[
        {
            "category":"Manufacturing",
            "subcategory":"Metals",
            "type":"Manufacturing & Wholesale Goods"
        }
    ],
    "sg:phone":"+1 450 258 2144",
    "sg:postcode":"J7N 2V4",
    "sg:province":"QC",
    "sg:tags":[
        "steel"
    ],
    "wof:name":"App Lauzon Inc",
    "wof:placetype":"venue"
},
  "geometry": {"coordinates":[-74.1032028198,45.6182365417],"type":"Point"}
}