{
  "type": "Feature",
  "properties": {
    "addr:full":"145 Rue Principale O Farnham QC J2N 1K3",
    "addr:housenumber":"145",
    "addr:postcode":"j2n 1k3",
    "addr:street":"Rue Principale O",
    "iso:country":"CA",
    "sg:address":"145 Rue Principale O",
    "sg:city":"Farnham",
    "sg:classifiers":[
        {
            "category":"Restaurant",
            "type":"Food & Drink"
        }
    ],
    "sg:phone":"+1 450 293 6662",
    "sg:postcode":"J2N 1K3",
    "sg:province":"QC",
    "sg:tags":[
        "parlor",
        "ice",
        "cream"
    ],
    "wof:name":"Bar Laitier Mariette",
    "wof:placetype":"venue"
},
  "geometry": {"coordinates":[-72.978874,45.285194],"type":"Point"}
}