{
  "type": "Feature",
  "properties": {
    "addr:full":"269 Rue Sherbrooke O Montreal QC H2X 1Y1",
    "addr:housenumber":"269",
    "addr:postcode":"h2x 1y1",
    "addr:street":"Rue Sherbrooke O",
    "iso:country":"CA",
    "sg:address":"269 Rue Sherbrooke O",
    "sg:city":"Montreal",
    "sg:classifiers":[
        {
            "category":"Shopping",
            "subcategory":"Used Merchandise",
            "type":"Retail Goods"
        }
    ],
    "sg:phone":"+1 514 288 1001",
    "sg:postcode":"H2X 1Y1",
    "sg:province":"QC",
    "sg:tags":[
        "antique"
    ],
    "wof:name":"Antiquites Montreal Universels",
    "wof:placetype":"venue"
},
  "geometry": {"coordinates":[-73.568298,45.515453],"type":"Point"}
}