{
  "type": "Feature",
  "properties": {
    "addr:full":"205 Windsor St Thunder Bay ON P7B 1V5",
    "addr:housenumber":"205",
    "addr:postcode":"p7b 1v5",
    "addr:street":"Windsor St",
    "iso:country":"CA",
    "sg:address":"205 Windsor St",
    "sg:city":"Thunder Bay",
    "sg:classifiers":[
        {
            "category":"Building & Trades",
            "subcategory":"Construction",
            "type":"Services"
        }
    ],
    "sg:phone":"+1 807 768 1112",
    "sg:postcode":"P7B 1V5",
    "sg:province":"ON",
    "sg:tags":[
        "marking",
        "maintenance",
        "parking"
    ],
    "wof:name":"Seal & Save Black Topping",
    "wof:placetype":"venue"
},
  "geometry": {"coordinates":[-89.2554931641,48.440990448],"type":"Point"}
}