{
  "type": "Feature",
  "properties": {
    "addr:full":"2200 Martin Grove Rd # 2 Etobicoke ON M9V 5H9",
    "addr:housenumber":"2200",
    "addr:postcode":"m9v 5h9",
    "addr:street":"Martin Grove Rd # 2",
    "iso:country":"CA",
    "sg:address":"2200 Martin Grove Rd # 2",
    "sg:city":"Etobicoke",
    "sg:classifiers":[
        {
            "category":"Personal",
            "subcategory":"Barber",
            "type":"Services"
        }
    ],
    "sg:phone":"+1 416 749 5201",
    "sg:postcode":"M9V 5H9",
    "sg:province":"ON",
    "wof:name":"Luigi & Angelo's Barber Shop",
    "wof:placetype":"venue"
},
  "geometry": {"coordinates":[-79.599236,43.751816],"type":"Point"}
}