{
  "type": "Feature",
  "properties": {
    "addr:full":"32 Berwick Ave Toronto ON M5P 1H1",
    "addr:housenumber":"32",
    "addr:postcode":"m5p 1h1",
    "addr:street":"Berwick Ave",
    "iso:country":"CA",
    "sg:address":"32 Berwick Ave",
    "sg:city":"Toronto",
    "sg:classifiers":[
        {
            "category":"Health Services",
            "subcategory":"Health Practitioner",
            "type":"Services"
        }
    ],
    "sg:phone":"+1 647 225 0719",
    "sg:postcode":"M5P 1H1",
    "sg:province":"ON",
    "sg:tags":[
        "acupuncture"
    ],
    "wof:name":"Natural Elements Acupuncture",
    "wof:placetype":"venue"
},
  "geometry": {"coordinates":[-79.398735,43.704079],"type":"Point"}
}