{
  "type": "Feature",
  "properties": {
    "addr:full":"339 Main St Russell MB R0J 1W0",
    "addr:housenumber":"339",
    "addr:postcode":"r0j 1w0",
    "addr:street":"Main St",
    "iso:country":"CA",
    "sg:address":"339 Main St",
    "sg:city":"Russell",
    "sg:classifiers":[
        {
            "category":"Education",
            "subcategory":"Library",
            "type":"Public Place"
        }
    ],
    "sg:phone":"+1 204 773 3127",
    "sg:postcode":"R0J 1W0",
    "sg:province":"MB",
    "wof:name":"Russell & District Reg Library",
    "wof:placetype":"venue"
},
  "geometry": {"coordinates":[-101.288025,50.782051],"type":"Point"}
}