{
  "type": "Feature",
  "properties": {
    "addr:full":"110 14th St W North Vancouver BC V7M 1N9",
    "addr:housenumber":"110",
    "addr:postcode":"v7m 1n9",
    "addr:street":"14Th St W",
    "iso:country":"CA",
    "sg:address":"110 14th St W",
    "sg:city":"North Vancouver",
    "sg:classifiers":[
        {
            "category":"Restaurant",
            "type":"Food & Drink"
        }
    ],
    "sg:phone":"+1 604 987 6654",
    "sg:postcode":"V7M 1N9",
    "sg:province":"BC",
    "wof:name":"Eighties Restaurant",
    "wof:placetype":"venue"
},
  "geometry": {"coordinates":[-123.07332599999999,49.32119],"type":"Point"}
}