{
  "type": "Feature",
  "properties": {
    "iso:country":"CA",
    "sg:address":"1451 Tecumseh Rd E",
    "sg:city":"Windsor",
    "sg:classifiers":[
        {
            "category":"Shopping",
            "subcategory":"Clothing, Apparel, & Fashions",
            "type":"Retail Goods"
        }
    ],
    "sg:phone":"+1 519 258 0228",
    "sg:postcode":"N8W 1C2",
    "sg:province":"ON",
    "sg:tags":[
        "dressmaker",
        "tailor"
    ],
    "wof:name":"Seams To Fit",
    "wof:placetype":"venue"
},
  "geometry": {"coordinates":[-83.0041046143,42.300327301],"type":"Point"}
}