{
  "type": "Feature",
  "properties": {
    "iso:country":"CA",
    "sg:address":"3245 North Talbot Rd",
    "sg:city":"Oldcastle",
    "sg:classifiers":[
        {
            "category":"Manufacturing",
            "subcategory":"Tools & Machinery",
            "type":"Manufacturing & Wholesale Goods"
        }
    ],
    "sg:phone":"+1 519 737 1522",
    "sg:postcode":"N0R 1L0",
    "sg:province":"ON",
    "sg:tags":[
        "mold"
    ],
    "wof:name":"B & B Tool Mold",
    "wof:placetype":"venue"
},
  "geometry": {"coordinates":[-82.95757293699999,42.2372245789],"type":"Point"}
}