{
  "type": "Feature",
  "properties": {
    "addr:full":"4316 81 Ave NW Edmonton AB T6B 2M2",
    "addr:housenumber":"4316",
    "addr:postcode":"t6b 2m2",
    "addr:street":"81 Ave Nw",
    "iso:country":"CA",
    "sg:address":"4316 81 Ave NW",
    "sg:city":"Edmonton",
    "sg:classifiers":[
        {
            "category":"Wholesale",
            "subcategory":"Machinery & Supplies",
            "type":"Manufacturing & Wholesale Goods"
        }
    ],
    "sg:phone":"+1 780 468 4318",
    "sg:postcode":"T6B 2M2",
    "sg:province":"AB",
    "sg:tags":[
        "tailor"
    ],
    "wof:name":"H A Kidd & CO Ltd",
    "wof:placetype":"venue"
},
  "geometry": {"coordinates":[-113.408417,53.516426],"type":"Point"}
}