{
  "type": "Feature",
  "properties": {
    "addr:full":"Armstrong BC V0E 1B1",
    "addr:postcode":"v0e 1b1",
    "iso:country":"CA",
    "sg:city":"Armstrong",
    "sg:classifiers":[
        {
            "category":"Personal",
            "subcategory":"Barber",
            "type":"Services"
        }
    ],
    "sg:phone":"+1 250 546 4151",
    "sg:postcode":"V0E 1B1",
    "sg:province":"BC",
    "wof:name":"Armstrong Barber Shop",
    "wof:placetype":"venue"
},
  "geometry": {"coordinates":[-119.184394836,50.4470939636],"type":"Point"}
}