{
  "type": "Feature",
  "properties": {
    "iso:country":"CA",
    "sg:address":"140 Rue Saint-Viateur",
    "sg:city":"Saint-Eustache",
    "sg:classifiers":[
        {
            "category":"Shopping",
            "subcategory":"Musical Instruments",
            "type":"Retail Goods"
        }
    ],
    "sg:phone":"+1 450 491 1036",
    "sg:postcode":"J7R 2C5",
    "sg:province":"QC",
    "wof:name":"Piano Jc",
    "wof:placetype":"venue"
},
  "geometry": {"coordinates":[-73.8922576904,45.5611419678],"type":"Point"}
}