{
  "type": "Feature",
  "properties": {
    "addr:full":"1125 Boul Saint-Joseph Drummondville QC J2C 2C8",
    "addr:housenumber":"1125",
    "addr:postcode":"j2c 2c8",
    "addr:street":"Boul Saint-Joseph",
    "iso:country":"CA",
    "sg:address":"1125 Boul Saint-Joseph",
    "sg:city":"Drummondville",
    "sg:classifiers":[
        {
            "category":"Insurance",
            "subcategory":"Insurance Agent",
            "type":"Services"
        }
    ],
    "sg:phone":"+1 819 474 1056",
    "sg:postcode":"J2C 2C8",
    "sg:province":"QC",
    "sg:tags":[
        "employment",
        "agency",
        "opportunity"
    ],
    "wof:name":"Agathe Romanesky Svc Financier",
    "wof:placetype":"venue"
},
  "geometry": {"coordinates":[-72.50533299999999,45.887608],"type":"Point"}
}