{
  "type": "Feature",
  "properties": {
    "iso:country":"CA",
    "sg:address":"100 Victoria St N # E",
    "sg:city":"Kitchener",
    "sg:classifiers":[
        {
            "category":"Food & Beverages",
            "subcategory":"Groceries & Convenience Stores",
            "type":"Retail Goods"
        }
    ],
    "sg:phone":"+1 519 743 5088",
    "sg:postcode":"N2H 6R5",
    "sg:province":"ON",
    "wof:name":"Victoria Convenience",
    "wof:placetype":"venue"
},
  "geometry": {"coordinates":[-80.4941253662,43.4548683167],"type":"Point"}
}