{
  "type": "Feature",
  "properties": {
    "addr:full":"5707 Rue Sherbrooke O Montreal QC H4A 1W9",
    "addr:housenumber":"5707",
    "addr:postcode":"h4a 1w9",
    "addr:street":"Rue Sherbrooke O",
    "iso:country":"CA",
    "sg:address":"5707 Rue Sherbrooke O",
    "sg:city":"Montreal",
    "sg:classifiers":[
        {
            "category":"Shopping",
            "subcategory":"Clothing, Apparel, & Fashions",
            "type":"Retail Goods"
        }
    ],
    "sg:phone":"+1 514 488 4478",
    "sg:postcode":"H4A 1W9",
    "sg:province":"QC",
    "sg:tags":[
        "dressmaker",
        "consultant"
    ],
    "wof:name":"Isabelle Fashion House",
    "wof:placetype":"venue"
},
  "geometry": {"coordinates":[-73.5490951538,45.5737190247],"type":"Point"}
}