{
  "type": "Feature",
  "properties": {
    "iso:country":"CA",
    "sg:address":"203 Boul Industriel",
    "sg:city":"Rouyn-Noranda",
    "sg:classifiers":[
        {
            "category":"Building & Trades",
            "subcategory":"Construction",
            "type":"Services"
        }
    ],
    "sg:phone":"+1 819 797 0122",
    "sg:postcode":"J9X 6P2",
    "sg:province":"QC",
    "sg:tags":[
        "contractor"
    ],
    "wof:name":"Construction Tablon Inc",
    "wof:placetype":"venue"
},
  "geometry": {"coordinates":[-79.0179138184,48.2212982178],"type":"Point"}
}