{
  "type": "Feature",
  "properties": {
    "addr:full":"885 Highway 8 Stoney Creek ON L8E 5H7",
    "addr:housenumber":"885",
    "addr:postcode":"l8e 5h7",
    "addr:street":"Highway 8",
    "iso:country":"CA",
    "sg:address":"885 Highway 8",
    "sg:city":"Stoney Creek",
    "sg:classifiers":[
        {
            "category":"Retail",
            "subcategory":"Auto Repair",
            "type":"Services"
        }
    ],
    "sg:phone":"+1 905 643 4460",
    "sg:postcode":"L8E 5H7",
    "sg:province":"ON",
    "sg:tags":[
        "repairing",
        "automobile"
    ],
    "wof:name":"Precise Car Svc",
    "wof:placetype":"venue"
},
  "geometry": {"coordinates":[-79.68988,43.212067],"type":"Point"}
}