{
  "type": "Feature",
  "properties": {
    "addr:full":"Calgary AB T2P 3P1",
    "addr:postcode":"t2p 3p1",
    "iso:country":"CA",
    "sg:city":"Calgary",
    "sg:classifiers":[
        {
            "category":"Health Services",
            "subcategory":"Doctor",
            "type":"Services"
        }
    ],
    "sg:phone":"+1 403 262 5057",
    "sg:postcode":"T2P 3P1",
    "sg:province":"AB",
    "sg:tags":[
        "dentist"
    ],
    "wof:name":"Burgess, Darryl DDS",
    "wof:placetype":"venue"
},
  "geometry": {"coordinates":[-114.080139,51.045902],"type":"Point"}
}