{
  "type": "Feature",
  "properties": {
    "addr:full":"North York ON M2L 2X9",
    "addr:postcode":"m2l 2x9",
    "iso:country":"CA",
    "sg:city":"North York",
    "sg:classifiers":[
        {
            "category":"Professional",
            "subcategory":"Management & Consulting",
            "type":"Services"
        }
    ],
    "sg:phone":"+1 416 225 5728",
    "sg:postcode":"M2L 2X9",
    "sg:province":"ON",
    "sg:tags":[
        "consultant",
        "business"
    ],
    "wof:name":"Invia Consulting Inc",
    "wof:placetype":"venue"
},
  "geometry": {"coordinates":[-79.387184,43.760635],"type":"Point"}
}