{
  "type": "Feature",
  "properties": {
    "addr:full":"6663 Line 88 Gowanstown ON N0G 1Y0",
    "addr:housenumber":"6663",
    "addr:postcode":"n0g 1y0",
    "addr:street":"Line 88",
    "iso:country":"CA",
    "sg:address":"6663 Line 88",
    "sg:city":"Gowanstown",
    "sg:classifiers":[
        {
            "category":"Wholesale",
            "subcategory":"Farm Supplies",
            "type":"Manufacturing & Wholesale Goods"
        }
    ],
    "sg:phone":"+1 519 291 2220",
    "sg:postcode":"N0G 1Y0",
    "sg:province":"ON",
    "sg:tags":[
        "feed",
        "grain"
    ],
    "wof:name":"Boyd's Elevators Ltd",
    "wof:placetype":"venue"
},
  "geometry": {"coordinates":[-80.939667,43.78178],"type":"Point"}
}