{
  "type": "Feature",
  "properties": {
    "addr:full":"22B Peter St S Orillia ON L3V 5A9",
    "addr:housenumber":"22b",
    "addr:postcode":"l3v 5a9",
    "addr:street":"Peter St S",
    "iso:country":"CA",
    "sg:address":"22B Peter St S",
    "sg:city":"Orillia",
    "sg:classifiers":[
        {
            "category":"Professional",
            "subcategory":"Printing & Photocopies",
            "type":"Services"
        }
    ],
    "sg:phone":"+1 705 325 7205",
    "sg:postcode":"L3V 5A9",
    "sg:province":"ON",
    "sg:tags":[
        "material",
        "blueprinting",
        "artist",
        "supply"
    ],
    "wof:name":"Tiffin's Creative Ctr",
    "wof:placetype":"venue"
},
  "geometry": {"coordinates":[-79.417084,44.608673],"type":"Point"}
}