{
  "type": "Feature",
  "properties": {
    "addr:full":"48054 Riverside St Boston Bar BC V0K 1C0",
    "addr:housenumber":"48054",
    "addr:postcode":"v0k 1c0",
    "addr:street":"Riverside St",
    "iso:country":"CA",
    "sg:address":"48054 Riverside St",
    "sg:city":"Boston Bar",
    "sg:classifiers":[
        {
            "category":"Freight",
            "type":"Transportation"
        }
    ],
    "sg:phone":"+1 604 867 9225",
    "sg:postcode":"V0K 1C0",
    "sg:province":"BC",
    "sg:tags":[
        "hauling",
        "log",
        "trucking"
    ],
    "wof:name":"Formans Transport Ltd",
    "wof:placetype":"venue"
},
  "geometry": {"coordinates":[-121.442428589,49.8695716858],"type":"Point"}
}