{
  "type": "Feature",
  "properties": {
    "iso:country":"CA",
    "sg:address":"11958 96 Ave",
    "sg:city":"Delta",
    "sg:classifiers":[
        {
            "category":"Building & Trades",
            "subcategory":"Construction",
            "type":"Services"
        }
    ],
    "sg:phone":"+1 604 588 1051",
    "sg:postcode":"V4C 3W8",
    "sg:province":"BC",
    "sg:tags":[
        "resurfacing",
        "laying",
        "refinishing",
        "floor"
    ],
    "wof:name":"Acorn Wood Floor Maintenance",
    "wof:placetype":"venue"
},
  "geometry": {"coordinates":[-122.891578674,49.1769638062],"type":"Point"}
}