{
  "type": "Feature",
  "properties": {
    "addr:full":"PO Box 153 Tilley AB T0J 3K0",
    "addr:housenumber":"po",
    "addr:postcode":"t0j 3k0",
    "addr:street":"Box 153 Tilley",
    "iso:country":"CA",
    "sg:address":"PO Box 153",
    "sg:city":"Tilley",
    "sg:classifiers":[
        {
            "category":"Mining & Drilling",
            "type":"Manufacturing & Wholesale Goods"
        }
    ],
    "sg:phone":"+1 403 362 3883",
    "sg:postcode":"T0J 3K0",
    "sg:province":"AB",
    "sg:tags":[
        "field",
        "oil"
    ],
    "wof:name":"George's Power Tong Svc Ltd",
    "wof:placetype":"venue"
},
  "geometry": {"coordinates":[-111.652793884,50.4507102966],"type":"Point"}
}