{
  "type": "Feature",
  "properties": {
    "addr:full":"102 Rue DE L'Hotel-DE-Ville Hull QC J8X 2E6",
    "addr:housenumber":"102",
    "addr:postcode":"j8x 2e6",
    "addr:street":"Rue De L'Hotel-De-Ville",
    "iso:country":"CA",
    "sg:address":"102 Rue DE L'Hotel-DE-Ville",
    "sg:city":"Hull",
    "sg:classifiers":[
        {
            "category":"Restaurant",
            "type":"Food & Drink"
        }
    ],
    "sg:phone":"+1 819 770 2029",
    "sg:postcode":"J8X 2E6",
    "sg:province":"QC",
    "wof:name":"Wang Thai Restaurant",
    "wof:placetype":"venue"
},
  "geometry": {"coordinates":[-75.718872,45.427853],"type":"Point"}
}