{
  "type": "Feature",
  "properties": {
    "addr:full":"20 Mgr Parenteau Yamaska QC J0G 1W0",
    "addr:housenumber":"20",
    "addr:postcode":"j0g 1w0",
    "addr:street":"Mgr Parenteau",
    "iso:country":"CA",
    "sg:address":"20 Mgr Parenteau",
    "sg:city":"Yamaska",
    "sg:classifiers":[
        {
            "category":"Restaurant",
            "type":"Food & Drink"
        }
    ],
    "sg:phone":"+1 450 789 2299",
    "sg:postcode":"J0G 1W0",
    "sg:province":"QC",
    "wof:name":"Restaurant Ti-Den",
    "wof:placetype":"venue"
},
  "geometry": {"coordinates":[-72.9139633179,46.0045433044],"type":"Point"}
}