{
  "type": "Feature",
  "properties": {
    "addr:full":"679 Windsor Back Rd Windsor NS B0N 2T0",
    "addr:housenumber":"679",
    "addr:postcode":"b0n 2t0",
    "addr:street":"Windsor Back Rd",
    "iso:country":"CA",
    "sg:address":"679 Windsor Back Rd",
    "sg:city":"Windsor",
    "sg:classifiers":[
        {
            "category":"Building & Trades",
            "subcategory":"Construction",
            "type":"Services"
        }
    ],
    "sg:phone":"+1 902 798 4121",
    "sg:postcode":"B0N 2T0",
    "sg:province":"NS",
    "sg:tags":[
        "concrete",
        "contractor"
    ],
    "wof:name":"Valley Concrete Finishers",
    "wof:placetype":"venue"
},
  "geometry": {"coordinates":[-64.1306762695,44.98985672],"type":"Point"}
}