{
  "type": "Feature",
  "properties": {
    "iso:country":"CA",
    "sg:address":"5012 51st St",
    "sg:city":"St Paul",
    "sg:classifiers":[
        {
            "category":"Health Services",
            "subcategory":"Medical Lab",
            "type":"Services"
        }
    ],
    "sg:phone":"+1 780 645 4343",
    "sg:postcode":"T0A 3A0",
    "sg:province":"AB",
    "wof:name":"St Paul Denture Clinic",
    "wof:placetype":"venue"
},
  "geometry": {"coordinates":[-111.29994201700001,53.9915466309],"type":"Point"}
}