{
  "type": "Feature",
  "properties": {
    "addr:full":"1883 Bradley Side Rd Carp ON K0A 1L0",
    "addr:housenumber":"1883",
    "addr:postcode":"k0a 1l0",
    "addr:street":"Bradley Side Rd",
    "iso:country":"CA",
    "sg:address":"1883 Bradley Side Rd",
    "sg:city":"Carp",
    "sg:classifiers":[
        {
            "category":"Organizations",
            "subcategory":"Non-profit Organization",
            "type":"Services"
        }
    ],
    "sg:phone":"+1 613 831 1903",
    "sg:postcode":"K0A 1L0",
    "sg:province":"ON",
    "sg:tags":[
        "addiction",
        "treatment",
        "center"
    ],
    "wof:name":"Meadow Creek Farm",
    "wof:placetype":"venue"
},
  "geometry": {"coordinates":[-75.96060900000001,45.304691],"type":"Point"}
}