{
  "type": "Feature",
  "properties": {
    "addr:full":"1526 Kingsway Vancouver BC V5N 2R9",
    "addr:housenumber":"1526",
    "addr:postcode":"v5n 2r9",
    "addr:street":"Kingsway",
    "iso:country":"CA",
    "sg:address":"1526 Kingsway",
    "sg:city":"Vancouver",
    "sg:classifiers":[
        {
            "category":"Retail",
            "subcategory":"Car Wash",
            "type":"Services"
        }
    ],
    "sg:phone":"+1 604 876 9274",
    "sg:postcode":"V5N 2R9",
    "sg:province":"BC",
    "sg:tags":[
        "polishing",
        "washing"
    ],
    "wof:name":"Final Touch",
    "wof:placetype":"venue"
},
  "geometry": {"coordinates":[-123.072289,49.248356],"type":"Point"}
}