{
  "type": "Feature",
  "properties": {
    "addr:full":"3300 Cowichan Lake Rd Duncan BC V9L 4C3",
    "addr:housenumber":"3300",
    "addr:postcode":"v9l 4c3",
    "addr:street":"Cowichan Lake Rd",
    "iso:country":"CA",
    "sg:address":"3300 Cowichan Lake Rd",
    "sg:city":"Duncan",
    "sg:classifiers":[
        {
            "category":"Retail",
            "subcategory":"Auto Rental",
            "type":"Services"
        }
    ],
    "sg:phone":"+1 250 748 4894",
    "sg:postcode":"V9L 4C3",
    "sg:province":"BC",
    "sg:tags":[
        "renting",
        "truck",
        "leasing"
    ],
    "wof:name":"U-Haul CO Ltd",
    "wof:placetype":"venue"
},
  "geometry": {"coordinates":[-123.70738220200001,48.779094696],"type":"Point"}
}