{
  "type": "Feature",
  "properties": {
    "addr:full":"Kelowna BC V1Y 9V8",
    "addr:postcode":"v1y 9v8",
    "iso:country":"CA",
    "sg:city":"Kelowna",
    "sg:classifiers":[
        {
            "category":"Shopping",
            "subcategory":"Used Merchandise",
            "type":"Retail Goods"
        }
    ],
    "sg:phone":"+1 250 763 0100",
    "sg:postcode":"V1Y 9V8",
    "sg:province":"BC",
    "sg:tags":[
        "equipment",
        "laundry"
    ],
    "wof:name":"Slim's Industries Inc",
    "wof:placetype":"venue"
},
  "geometry": {"coordinates":[-119.494347,49.892628],"type":"Point"}
}