{
  "type": "Feature",
  "properties": {
    "addr:full":"Etobicoke ON M9W 6J3",
    "addr:postcode":"m9w 6j3",
    "iso:country":"CA",
    "sg:city":"Etobicoke",
    "sg:classifiers":[
        {
            "category":"Building & Trades",
            "subcategory":"Construction",
            "type":"Services"
        }
    ],
    "sg:phone":"+1 416 746 9425",
    "sg:postcode":"M9W 6J3",
    "sg:province":"ON",
    "sg:tags":[
        "general",
        "contractor"
    ],
    "wof:name":"Magacon Construction",
    "wof:placetype":"venue"
},
  "geometry": {"coordinates":[-79.5757904053,43.7203674316],"type":"Point"}
}