{
  "type": "Feature",
  "properties": {
    "addr:full":"1176 Union St Kitchener ON N2H 6K2",
    "addr:housenumber":"1176",
    "addr:postcode":"n2h 6k2",
    "addr:street":"Union St",
    "iso:country":"CA",
    "sg:address":"1176 Union St",
    "sg:city":"Kitchener",
    "sg:classifiers":[
        {
            "category":"Organizations",
            "subcategory":"Professional Association",
            "type":"Services"
        }
    ],
    "sg:phone":"+1 519 570 1424",
    "sg:postcode":"N2H 6K2",
    "sg:province":"ON",
    "wof:name":"Cep Communications Energy",
    "wof:placetype":"venue"
},
  "geometry": {"coordinates":[-80.483017,43.471699],"type":"Point"}
}