{
  "type": "Feature",
  "properties": {
    "addr:full":"Perth-Andover NB E7H 1Z6",
    "addr:postcode":"e7h 1z6",
    "iso:country":"CA",
    "sg:city":"Perth-Andover",
    "sg:classifiers":[
        {
            "category":"Insurance",
            "subcategory":"Insurance Agent",
            "type":"Services"
        }
    ],
    "sg:phone":"+1 506 273 9400",
    "sg:postcode":"E7H 1Z6",
    "sg:province":"NB",
    "wof:name":"Alliance Insurance Inc",
    "wof:placetype":"venue"
},
  "geometry": {"coordinates":[-67.70329284669999,46.7360305786],"type":"Point"}
}