{
  "type": "Feature",
  "properties": {
    "iso:country":"CA",
    "sg:address":"4312 Village Centre Crt",
    "sg:city":"Mississauga",
    "sg:classifiers":[
        {
            "category":"Real Estate",
            "subcategory":"Real Estate Agent",
            "type":"Services"
        }
    ],
    "sg:phone":"+1 905 949 0070",
    "sg:postcode":"L4Z 1S2",
    "sg:province":"ON",
    "wof:name":"Homelife Response Realty Inc",
    "wof:placetype":"venue"
},
  "geometry": {"coordinates":[-79.6405410767,43.6010055542],"type":"Point"}
}