{
  "type": "Feature",
  "properties": {
    "iso:country":"CA",
    "sg:address":"120 Welham Rd",
    "sg:city":"Barrie",
    "sg:classifiers":[
        {
            "category":"Retail",
            "subcategory":"Auto Repair",
            "type":"Services"
        }
    ],
    "sg:phone":"+1 705 737 2300",
    "sg:postcode":"L4M 5M4",
    "sg:province":"ON",
    "sg:tags":[
        "axle"
    ],
    "wof:name":"Dana Canada Inc",
    "wof:placetype":"venue"
},
  "geometry": {"coordinates":[-79.673065,44.354404],"type":"Point"}
}