{
  "type": "Feature",
  "properties": {
    "addr:full":"120 Welham Rd Barrie ON L4M 5M4",
    "addr:housenumber":"120",
    "addr:postcode":"l4m 5m4",
    "addr:street":"Welham Rd",
    "iso:country":"CA",
    "sg:address":"120 Welham Rd",
    "sg:city":"Barrie",
    "sg:classifiers":[
        {
            "category":"Retail",
            "subcategory":"Auto Repair",
            "type":"Services"
        }
    ],
    "sg:phone":"+1 705 737 2300",
    "sg:postcode":"L4M 5M4",
    "sg:province":"ON",
    "sg:tags":[
        "axle"
    ],
    "wof:name":"Dana Canada Inc",
    "wof:placetype":"venue"
},
  "geometry": {"coordinates":[-79.67306499999999,44.354404],"type":"Point"}
}