{
  "type": "Feature",
  "properties": {
    "addr:full":"509 Davidson Ave Kelvington SK S0A 1W0",
    "addr:housenumber":"509",
    "addr:postcode":"s0a 1w0",
    "addr:street":"Davidson Ave",
    "iso:country":"CA",
    "sg:address":"509 Davidson Ave",
    "sg:city":"Kelvington",
    "sg:classifiers":[
        {
            "category":"Home & Garden",
            "subcategory":"Garden Supply",
            "type":"Retail Goods"
        }
    ],
    "sg:phone":"+1 306 327 4226",
    "sg:postcode":"S0A 1W0",
    "sg:province":"SK",
    "sg:tags":[
        "lawn",
        "saw",
        "mower"
    ],
    "wof:name":"Kelvington Small Engine Repair",
    "wof:placetype":"venue"
},
  "geometry": {"coordinates":[-103.529502869,52.16456604],"type":"Point"}
}