{
  "type": "Feature",
  "properties": {
    "addr:full":"379 Danforth Ave Ottawa ON K2A 0E1",
    "addr:housenumber":"379",
    "addr:postcode":"k2a 0e1",
    "addr:street":"Danforth Ave",
    "iso:country":"CA",
    "sg:address":"379 Danforth Ave",
    "sg:city":"Ottawa",
    "sg:classifiers":[
        {
            "category":"Insurance",
            "subcategory":"Insurance Agent",
            "type":"Services"
        }
    ],
    "sg:phone":"+1 613 225 1182",
    "sg:postcode":"K2A 0E1",
    "sg:province":"ON",
    "wof:name":"Life Trends Insurance CO",
    "wof:placetype":"venue"
},
  "geometry": {"coordinates":[-75.755707,45.390614],"type":"Point"}
}