{
  "type": "Feature",
  "properties": {
    "addr:full":"55 Clegg Rd Markham ON L6G 1B9",
    "addr:housenumber":"55",
    "addr:postcode":"l6g 1b9",
    "addr:street":"Clegg Rd",
    "iso:country":"CA",
    "sg:address":"55 Clegg Rd",
    "sg:city":"Markham",
    "sg:classifiers":[
        {
            "category":"Shopping",
            "type":"Retail Goods"
        }
    ],
    "sg:phone":"+1 905 477 2916",
    "sg:postcode":"L6G 1B9",
    "sg:province":"ON",
    "sg:tags":[
        "equipment",
        "brewer",
        "wine",
        "supply"
    ],
    "wof:name":"Wine Kitz",
    "wof:placetype":"venue"
},
  "geometry": {"coordinates":[-79.338928,43.851982],"type":"Point"}
}