{
  "type": "Feature",
  "properties": {
    "iso:country":"CA",
    "sg:address":"2700 Av Laurier E",
    "sg:city":"Montreal",
    "sg:classifiers":[
        {
            "category":"Food & Beverages",
            "subcategory":"Groceries & Convenience Stores",
            "type":"Retail Goods"
        }
    ],
    "sg:phone":"+1 514 527 9966",
    "sg:postcode":"H1Y 1Y7",
    "sg:province":"QC",
    "wof:name":"Depanneur Kiatou",
    "wof:placetype":"venue"
},
  "geometry": {"coordinates":[-73.57251,45.545517],"type":"Point"}
}