{
  "type": "Feature",
  "properties": {
    "addr:full":"2368 Bloor St W Toronto ON M6S 1P5",
    "addr:housenumber":"2368",
    "addr:postcode":"m6s 1p5",
    "addr:street":"Bloor St W",
    "iso:country":"CA",
    "sg:address":"2368 Bloor St W",
    "sg:city":"Toronto",
    "sg:classifiers":[
        {
            "category":"Shopping",
            "subcategory":"Gifts & Souvenirs",
            "type":"Retail Goods"
        }
    ],
    "sg:phone":"+1 416 762 9638",
    "sg:postcode":"M6S 1P5",
    "sg:province":"ON",
    "sg:tags":[
        "shop"
    ],
    "wof:name":"Jolanta Interiors",
    "wof:placetype":"venue"
},
  "geometry": {"coordinates":[-79.4820327759,43.6499595642],"type":"Point"}
}