{
  "type": "Feature",
  "properties": {
    "addr:full":"224 Hunter St W Peterborough ON K9H 2L2",
    "addr:housenumber":"224",
    "addr:postcode":"k9h 2l2",
    "addr:street":"Hunter St W",
    "iso:country":"CA",
    "sg:address":"224 Hunter St W",
    "sg:city":"Peterborough",
    "sg:classifiers":[
        {
            "category":"Retail",
            "subcategory":"Auto Repair",
            "type":"Services"
        }
    ],
    "sg:phone":"+1 705 743 3410",
    "sg:postcode":"K9H 2L2",
    "sg:province":"ON",
    "sg:tags":[
        "repairing",
        "radiator",
        "automobile",
        "air",
        "equipment",
        "conditioning"
    ],
    "wof:name":"Madill & Post Radiator Svc",
    "wof:placetype":"venue"
},
  "geometry": {"coordinates":[-78.322624,44.305927],"type":"Point"}
}