{
  "type": "Feature",
  "properties": {
    "addr:full":"212 Rue Principale Memramcook NB E4K 1B1",
    "addr:housenumber":"212",
    "addr:postcode":"e4k 1b1",
    "addr:street":"Rue Principale",
    "iso:country":"CA",
    "sg:address":"212 Rue Principale",
    "sg:city":"Memramcook",
    "sg:classifiers":[
        {
            "category":"Retail",
            "subcategory":"Animal Services",
            "type":"Services"
        }
    ],
    "sg:phone":"+1 506 852 9785",
    "sg:postcode":"E4K 1B1",
    "sg:province":"NB",
    "sg:tags":[
        "pet",
        "boarding",
        "sitting"
    ],
    "wof:name":"Lazy Bones Kennels",
    "wof:placetype":"venue"
},
  "geometry": {"coordinates":[-64.69103200000001,46.008419],"type":"Point"}
}