{
  "type": "Feature",
  "properties": {
    "addr:full":"6500 Viscount Rd Mississauga ON L4V 1H3",
    "addr:housenumber":"6500",
    "addr:postcode":"l4v 1h3",
    "addr:street":"Viscount Rd",
    "iso:country":"CA",
    "sg:address":"6500 Viscount Rd",
    "sg:city":"Mississauga",
    "sg:classifiers":[
        {
            "category":"Manufacturing",
            "subcategory":"Retail Goods",
            "type":"Manufacturing & Wholesale Goods"
        }
    ],
    "sg:phone":"+1 905 673 1212",
    "sg:postcode":"L4V 1H3",
    "sg:province":"ON",
    "sg:tags":[
        "marking",
        "devices"
    ],
    "wof:name":"Videojet Technologies Canada",
    "wof:placetype":"venue"
},
  "geometry": {"coordinates":[-79.62638099999999,43.695152],"type":"Point"}
}