{
  "type": "Feature",
  "properties": {
    "iso:country":"CA",
    "sg:address":"6500 Viscount Rd",
    "sg:city":"Mississauga",
    "sg:classifiers":[
        {
            "category":"Manufacturing",
            "subcategory":"Retail Goods",
            "type":"Manufacturing & Wholesale Goods"
        }
    ],
    "sg:phone":"+1 905 673 1212",
    "sg:postcode":"L4V 1H3",
    "sg:province":"ON",
    "sg:tags":[
        "marking",
        "devices"
    ],
    "wof:name":"Videojet Technologies Canada",
    "wof:placetype":"venue"
},
  "geometry": {"coordinates":[-79.626381,43.695152],"type":"Point"}
}