{
  "type": "Feature",
  "properties": {
    "iso:country":"CA",
    "sg:address":"681 Rue DE LA Commune O",
    "sg:city":"Montreal",
    "sg:classifiers":[
        {
            "category":"Restaurant",
            "type":"Food & Drink"
        }
    ],
    "sg:phone":"+1 514 879 1874",
    "sg:postcode":"H3C 1X6",
    "sg:province":"QC",
    "wof:name":"Restaurant Ritz MB",
    "wof:placetype":"venue"
},
  "geometry": {"coordinates":[-73.55027771,45.5109138489],"type":"Point"}
}