{
  "type": "Feature",
  "properties": {
    "addr:full":"Stony Mountain MB R0C 3A0",
    "addr:postcode":"r0c 3a0",
    "iso:country":"CA",
    "sg:city":"Stony Mountain",
    "sg:classifiers":[
        {
            "category":"Travel",
            "subcategory":"Hotels & Motels",
            "type":"Entertainment"
        }
    ],
    "sg:phone":"+1 204 344 5511",
    "sg:postcode":"R0C 3A0",
    "sg:province":"MB",
    "wof:name":"Mountain Motor Inn",
    "wof:placetype":"venue"
},
  "geometry": {"coordinates":[-101.086395264,52.3841896057],"type":"Point"}
}