{
  "type": "Feature",
  "properties": {
    "addr:full":"Cap-DE-LA-Madeleine QC G8T 7B4",
    "addr:postcode":"g8t 7b4",
    "iso:country":"CA",
    "sg:city":"Cap-DE-LA-Madeleine",
    "sg:classifiers":[
        {
            "category":"Home & Garden",
            "subcategory":"Carpets & Floor Coverings",
            "type":"Retail Goods"
        }
    ],
    "sg:phone":"+1 819 370 2027",
    "sg:postcode":"G8T 7B4",
    "sg:province":"QC",
    "sg:tags":[
        "material"
    ],
    "wof:name":"Centre DE Tapis & Decoration",
    "wof:placetype":"venue"
},
  "geometry": {"coordinates":[-72.560585022,46.394733429],"type":"Point"}
}