{
  "type": "Feature",
  "properties": {
    "addr:full":"Victoria BC V8V 4V6",
    "addr:postcode":"v8v 4v6",
    "iso:country":"CA",
    "sg:city":"Victoria",
    "sg:classifiers":[
        {
            "category":"Real Estate",
            "subcategory":"Real Estate Operator",
            "type":"Services"
        }
    ],
    "sg:phone":"+1 250 383 1833",
    "sg:postcode":"V8V 4V6",
    "sg:province":"BC",
    "sg:tags":[
        "apartment"
    ],
    "wof:name":"Tara Place",
    "wof:placetype":"venue"
},
  "geometry": {"coordinates":[-123.355583,48.424263],"type":"Point"}
}