{
  "type": "Feature",
  "properties": {
    "addr:full":"141 Dundas St London ON N6A 1G3",
    "addr:housenumber":"141",
    "addr:postcode":"n6a 1g3",
    "addr:street":"Dundas St",
    "iso:country":"CA",
    "sg:address":"141 Dundas St",
    "sg:city":"London",
    "sg:classifiers":[
        {
            "category":"Shopping",
            "subcategory":"Pharmacy",
            "type":"Retail Goods"
        }
    ],
    "sg:phone":"+1 519 672 7965",
    "sg:postcode":"N6A 1G3",
    "sg:province":"ON",
    "wof:name":"Shoppers Drug Mart",
    "wof:placetype":"venue"
},
  "geometry": {"coordinates":[-81.25049591059999,42.9833450317],"type":"Point"}
}