{
  "type": "Feature",
  "properties": {
    "addr:full":"31 Collingwood Cres Winnipeg MB R2J 3L3",
    "addr:housenumber":"31",
    "addr:postcode":"r2j 3l3",
    "addr:street":"Collingwood Cres",
    "iso:country":"CA",
    "sg:address":"31 Collingwood Cres",
    "sg:city":"Winnipeg",
    "sg:classifiers":[
        {
            "category":"Professional",
            "subcategory":"Accounting & Tax Preparation",
            "type":"Services"
        }
    ],
    "sg:phone":"+1 204 254 0524",
    "sg:postcode":"R2J 3L3",
    "sg:province":"MB",
    "sg:tags":[
        "bookkeeping",
        "general"
    ],
    "wof:name":"Den Bookkeeping Ltd",
    "wof:placetype":"venue"
},
  "geometry": {"coordinates":[-97.07096900000001,49.845882],"type":"Point"}
}