{
  "type": "Feature",
  "properties": {
    "addr:full":"176 Raglan St S Renfrew ON K7V 1R1",
    "addr:housenumber":"176",
    "addr:postcode":"k7v 1r1",
    "addr:street":"Raglan St S",
    "iso:country":"CA",
    "sg:address":"176 Raglan St S",
    "sg:city":"Renfrew",
    "sg:classifiers":[
        {
            "category":"Home & Garden",
            "subcategory":"Furniture",
            "type":"Retail Goods"
        }
    ],
    "sg:phone":"+1 613 432 9324",
    "sg:postcode":"K7V 1R1",
    "sg:province":"ON",
    "wof:name":"Korner Hutch",
    "wof:placetype":"venue"
},
  "geometry": {"coordinates":[-76.68450199999999,45.472054],"type":"Point"}
}