{
  "type": "Feature",
  "properties": {
    "iso:country":"CA",
    "sg:address":"31 Rue DE LA Reine",
    "sg:city":"Sorel-Tracy",
    "sg:classifiers":[
        {
            "category":"Organizations",
            "subcategory":"Professional Association",
            "type":"Services"
        }
    ],
    "sg:phone":"+1 450 743 6719",
    "sg:postcode":"J3P 4R3",
    "sg:province":"QC",
    "wof:name":"Harmonie Calixa-Lavallee Inc",
    "wof:placetype":"venue"
},
  "geometry": {"coordinates":[-73.1178894043,46.0449447632],"type":"Point"}
}