{
  "type": "Feature",
  "properties": {
    "addr:full":"35 Ontario St Clinton ON N0M 1L0",
    "addr:housenumber":"35",
    "addr:postcode":"n0m 1l0",
    "addr:street":"Ontario St",
    "iso:country":"CA",
    "sg:address":"35 Ontario St",
    "sg:city":"Clinton",
    "sg:classifiers":[
        {
            "category":"Professional",
            "subcategory":"Lawyer & Legal Services",
            "type":"Services"
        }
    ],
    "sg:phone":"+1 519 482 1434",
    "sg:postcode":"N0M 1L0",
    "sg:province":"ON",
    "sg:tags":[
        "attorney"
    ],
    "wof:name":"Cornish, Philip B",
    "wof:placetype":"venue"
},
  "geometry": {"coordinates":[-81.53861999999999,43.616829],"type":"Point"}
}