{
  "type": "Feature",
  "properties": {
    "addr:full":"Scarborough ON M1S 4R5",
    "addr:postcode":"m1s 4r5",
    "iso:country":"CA",
    "sg:city":"Scarborough",
    "sg:classifiers":[
        {
            "category":"Health Services",
            "subcategory":"Doctor",
            "type":"Services"
        }
    ],
    "sg:phone":"+1 416 293 4119",
    "sg:postcode":"M1S 4R5",
    "sg:province":"ON",
    "sg:tags":[
        "dentist"
    ],
    "wof:name":"Voudoudouris, Ari DDS",
    "wof:placetype":"venue"
},
  "geometry": {"coordinates":[-79.288033,43.783466],"type":"Point"}
}