{
  "type": "Feature",
  "properties": {
    "iso:country":"CA",
    "sg:address":"10412 110th St",
    "sg:city":"Fairview",
    "sg:classifiers":[
        {
            "category":"Retail",
            "subcategory":"Laundry & Dry Cleaning",
            "type":"Services"
        }
    ],
    "sg:phone":"+1 780 835 2518",
    "sg:postcode":"T0H 1L0",
    "sg:province":"AB",
    "sg:tags":[
        "cleaners"
    ],
    "wof:name":"Landry's Dry Cleaning",
    "wof:placetype":"venue"
},
  "geometry": {"coordinates":[-118.384559631,56.068862915],"type":"Point"}
}