{
  "type": "Feature",
  "properties": {
    "addr:full":"673 Berford St Wiarton ON N0H 2T0",
    "addr:housenumber":"673",
    "addr:postcode":"n0h 2t0",
    "addr:street":"Berford St",
    "iso:country":"CA",
    "sg:address":"673 Berford St",
    "sg:city":"Wiarton",
    "sg:classifiers":[
        {
            "category":"Professional",
            "subcategory":"Accounting & Tax Preparation",
            "type":"Services"
        }
    ],
    "sg:phone":"+1 519 534 1122",
    "sg:postcode":"N0H 2T0",
    "sg:province":"ON",
    "sg:tags":[
        "accountant"
    ],
    "wof:name":"Campbell & Wakeford",
    "wof:placetype":"venue"
},
  "geometry": {"coordinates":[-81.14083100000001,44.745228],"type":"Point"}
}