{
  "type": "Feature",
  "properties": {
    "addr:full":"Rouyn-Noranda QC J9X 3B6",
    "addr:postcode":"j9x 3b6",
    "iso:country":"CA",
    "sg:city":"Rouyn-Noranda",
    "sg:classifiers":[
        {
            "category":"Professional",
            "subcategory":"Lawyer & Legal Services",
            "type":"Services"
        }
    ],
    "sg:phone":"+1 819 762 9777",
    "sg:postcode":"J9X 3B6",
    "sg:province":"QC",
    "sg:tags":[
        "attorney"
    ],
    "wof:name":"Lemire-Grygiel",
    "wof:placetype":"venue"
},
  "geometry": {"coordinates":[-79.0196151733,48.2400665283],"type":"Point"}
}