{
  "type": "Feature",
  "properties": {
    "addr:full":"675 Boul Decarie Saint-Laurent QC H4L 3L3",
    "addr:housenumber":"675",
    "addr:postcode":"h4l 3l3",
    "addr:street":"Boul Decarie",
    "iso:country":"CA",
    "sg:address":"675 Boul Decarie",
    "sg:city":"Saint-Laurent",
    "sg:classifiers":[
        {
            "category":"Organizations",
            "subcategory":"Professional Association",
            "type":"Services"
        }
    ],
    "sg:phone":"+1 514 855 8995",
    "sg:postcode":"H4L 3L3",
    "sg:province":"QC",
    "wof:name":"Ruban En Route",
    "wof:placetype":"venue"
},
  "geometry": {"coordinates":[-73.6761550903,45.5103645325],"type":"Point"}
}