{
  "type": "Feature",
  "properties": {
    "addr:full":"360 Topsail Rd St. John's NL A1E 2B6",
    "addr:housenumber":"360",
    "addr:postcode":"a1e 2b6",
    "addr:street":"Topsail Rd",
    "iso:country":"CA",
    "sg:address":"360 Topsail Rd",
    "sg:city":"St. John's",
    "sg:classifiers":[
        {
            "category":"Personal",
            "subcategory":"Beauty Salon",
            "type":"Services"
        }
    ],
    "sg:phone":"+1 709 364 7002",
    "sg:postcode":"A1E 2B6",
    "sg:province":"NL",
    "wof:name":"Frances' Beauty Shoppe",
    "wof:placetype":"venue"
},
  "geometry": {"coordinates":[-52.742664,47.536381],"type":"Point"}
}