{
  "type": "Feature",
  "properties": {
    "addr:full":"2236 35 St SE Calgary AB T2B 0X1",
    "addr:housenumber":"2236",
    "addr:postcode":"t2b 0x1",
    "addr:street":"35 St Se",
    "iso:country":"CA",
    "sg:address":"2236 35 St SE",
    "sg:city":"Calgary",
    "sg:classifiers":[
        {
            "category":"Organizations",
            "subcategory":"Religious Organization",
            "type":"Services"
        }
    ],
    "sg:phone":"+1 403 272 2393",
    "sg:postcode":"T2B 0X1",
    "sg:province":"AB",
    "sg:tags":[
        "church"
    ],
    "wof:name":"Forest Lawn United Church",
    "wof:placetype":"venue"
},
  "geometry": {"coordinates":[-113.982879639,51.0343971252],"type":"Point"}
}