{
  "type": "Feature",
  "properties": {
    "addr:full":"133 Rue Raymond Saint-Louis-Du-Ha-Ha QC G0L 3S0",
    "addr:housenumber":"133",
    "addr:postcode":"g0l 3s0",
    "addr:street":"Rue Raymond Saint-Louis-Du-Ha-Ha",
    "iso:country":"CA",
    "sg:address":"133 Rue Raymond",
    "sg:city":"Saint-Louis-Du-Ha-Ha",
    "sg:classifiers":[
        {
            "category":"Manufacturing",
            "subcategory":"Metals",
            "type":"Manufacturing & Wholesale Goods"
        }
    ],
    "sg:phone":"+1 418 854 2422",
    "sg:postcode":"G0L 3S0",
    "sg:province":"QC",
    "sg:tags":[
        "equipment",
        "heating"
    ],
    "wof:name":"Ferblanterie Dube & Fils Enr",
    "wof:placetype":"venue"
},
  "geometry": {"coordinates":[-68.97788238530001,47.6709709167],"type":"Point"}
}