{
  "type": "Feature",
  "properties": {
    "addr:full":"2122 20 St Nanton AB T0L 1R0",
    "addr:housenumber":"2122",
    "addr:postcode":"t0l 1r0",
    "addr:street":"20 St",
    "iso:country":"CA",
    "sg:address":"2122 20 St",
    "sg:city":"Nanton",
    "sg:classifiers":[
        {
            "category":"Restaurant",
            "type":"Food & Drink"
        }
    ],
    "sg:phone":"+1 403 646 1155",
    "sg:postcode":"T0L 1R0",
    "sg:province":"AB",
    "sg:tags":[
        "shop",
        "coffee"
    ],
    "wof:name":"Main Street Cafe",
    "wof:placetype":"venue"
},
  "geometry": {"coordinates":[-113.772010803,50.3486213684],"type":"Point"}
}