{
  "type": "Feature",
  "properties": {
    "addr:full":"925 Rue Lacasse Montreal QC H4C 2Z2",
    "addr:housenumber":"925",
    "addr:postcode":"h4c 2z2",
    "addr:street":"Rue Lacasse",
    "iso:country":"CA",
    "sg:address":"925 Rue Lacasse",
    "sg:city":"Montreal",
    "sg:classifiers":[
        {
            "category":"Wholesale",
            "subcategory":"Hardware",
            "type":"Manufacturing & Wholesale Goods"
        }
    ],
    "sg:phone":"+1 514 937 9496",
    "sg:postcode":"H4C 2Z2",
    "sg:province":"QC",
    "sg:tags":[
        "fastener"
    ],
    "wof:name":"Techni-Vis Ltee",
    "wof:placetype":"venue"
},
  "geometry": {"coordinates":[-73.59111,45.477104],"type":"Point"}
}