{
  "type": "Feature",
  "properties": {
    "addr:full":"320 Boul Industriel Saint-Eustache QC J7R 5R4",
    "addr:housenumber":"320",
    "addr:postcode":"j7r 5r4",
    "addr:street":"Boul Industriel",
    "iso:country":"CA",
    "sg:address":"320 Boul Industriel",
    "sg:city":"Saint-Eustache",
    "sg:classifiers":[
        {
            "category":"Shopping",
            "type":"Retail Goods"
        }
    ],
    "sg:phone":"+1 450 473 8000",
    "sg:postcode":"J7R 5R4",
    "sg:province":"QC",
    "sg:tags":[
        "ice"
    ],
    "wof:name":"Service DE Glace St-Eustache",
    "wof:placetype":"venue"
},
  "geometry": {"coordinates":[-73.925438,45.564606],"type":"Point"}
}