{
  "type": "Feature",
  "properties": {
    "addr:full":"Winnipeg MB R3J 0Y4",
    "addr:postcode":"r3j 0y4",
    "iso:country":"CA",
    "sg:city":"Winnipeg",
    "sg:classifiers":[
        {
            "category":"Restaurant",
            "type":"Food & Drink"
        }
    ],
    "sg:phone":"+1 204 982 5556",
    "sg:postcode":"R3J 0Y4",
    "sg:province":"MB",
    "sg:tags":[
        "pizza"
    ],
    "wof:name":"Big Time Pizza",
    "wof:placetype":"venue"
},
  "geometry": {"coordinates":[-97.214935,49.883835],"type":"Point"}
}