{
  "type": "Feature",
  "properties": {
    "addr:full":"Saint-Basile-Le-Grand QC J3N 1L7",
    "addr:postcode":"j3n 1l7",
    "iso:country":"CA",
    "sg:city":"Saint-Basile-Le-Grand",
    "sg:classifiers":[
        {
            "category":"Health Services",
            "subcategory":"Doctor",
            "type":"Services"
        }
    ],
    "sg:phone":"+1 450 441 4888",
    "sg:postcode":"J3N 1L7",
    "sg:province":"QC",
    "sg:tags":[
        "clinic",
        "chiropractor"
    ],
    "wof:name":"Clinique Chiropractique",
    "wof:placetype":"venue"
},
  "geometry": {"coordinates":[-73.28877300000001,45.527634],"type":"Point"}
}