{
  "type": "Feature",
  "properties": {
    "iso:country":"CA",
    "sg:city":"Quebec",
    "sg:classifiers":[
        {
            "category":"Autos & Motor Vehicles",
            "subcategory":"Boat Sales",
            "type":"Retail Goods"
        }
    ],
    "sg:phone":"+1 418 692 5334",
    "sg:postcode":"G1K 8N1",
    "sg:province":"QC",
    "sg:tags":[
        "equipment",
        "dealer",
        "supply"
    ],
    "wof:name":"Global Marine Inc",
    "wof:placetype":"venue"
},
  "geometry": {"coordinates":[-71.212753,46.819126],"type":"Point"}
}