{
  "type": "Feature",
  "properties": {
    "iso:country":"CA",
    "sg:address":"7420 51 Ave NW",
    "sg:city":"Edmonton",
    "sg:classifiers":[
        {
            "category":"Manufacturing",
            "subcategory":"Tools & Machinery",
            "type":"Manufacturing & Wholesale Goods"
        }
    ],
    "sg:phone":"+1 780 450 6707",
    "sg:postcode":"T6B 3C1",
    "sg:province":"AB",
    "sg:tags":[
        "machine",
        "shop"
    ],
    "wof:name":"W K Machine Tech Inc",
    "wof:placetype":"venue"
},
  "geometry": {"coordinates":[-113.439788818,53.4881362915],"type":"Point"}
}