{
  "type": "Feature",
  "properties": {
    "addr:full":"1114 Cole Harbour Rd Dartmouth NS B2V 1E7",
    "addr:housenumber":"1114",
    "addr:postcode":"b2v 1e7",
    "addr:street":"Cole Harbour Rd",
    "iso:country":"CA",
    "sg:address":"1114 Cole Harbour Rd",
    "sg:city":"Dartmouth",
    "sg:classifiers":[
        {
            "category":"Retail",
            "subcategory":"Laundry & Dry Cleaning",
            "type":"Services"
        }
    ],
    "sg:phone":"+1 902 462 2732",
    "sg:postcode":"B2V 1E7",
    "sg:province":"NS",
    "wof:name":"Lion Laundry",
    "wof:placetype":"venue"
},
  "geometry": {"coordinates":[-63.4861068726,44.6719512939],"type":"Point"}
}