{
  "type": "Feature",
  "properties": {
    "addr:full":"295 Charlotte St Sydney NS B1P 1C6",
    "addr:housenumber":"295",
    "addr:postcode":"b1p 1c6",
    "addr:street":"Charlotte St",
    "iso:country":"CA",
    "sg:address":"295 Charlotte St",
    "sg:city":"Sydney",
    "sg:classifiers":[
        {
            "category":"Government",
            "subcategory":"Office",
            "type":"Public Place"
        }
    ],
    "sg:phone":"+1 902 563 2100",
    "sg:postcode":"B1P 1C6",
    "sg:province":"NS",
    "wof:name":"Nova Scotia Environment",
    "wof:placetype":"venue"
},
  "geometry": {"coordinates":[-60.1946105957,46.1385002136],"type":"Point"}
}