{
  "type": "Feature",
  "properties": {
    "addr:full":"5000 Aut Transcanadienne Pointe-Claire QC H9R 1B6",
    "addr:postcode":"5000;h9r 1b6",
    "addr:street":"Transcanadienne",
    "iso:country":"CA",
    "sg:address":"5000 Aut Transcanadienne",
    "sg:city":"Pointe-Claire",
    "sg:classifiers":[
        {
            "category":"Manufacturing",
            "subcategory":"Motor Vehicles & Parts",
            "type":"Manufacturing & Wholesale Goods"
        }
    ],
    "sg:phone":"+1 514 630 6209",
    "sg:postcode":"H9R 1B6",
    "sg:province":"QC",
    "sg:tags":[
        "automobile"
    ],
    "wof:name":"General Motors of Canada Ltd",
    "wof:placetype":"venue"
},
  "geometry": {"coordinates":[-73.838219,45.457832],"type":"Point"}
}