{
  "type": "Feature",
  "properties": {
    "addr:full":"2747 Rue Principale Dunham QC J0E 1M0",
    "addr:housenumber":"2747",
    "addr:postcode":"j0e 1m0",
    "addr:street":"Rue Principale",
    "iso:country":"CA",
    "sg:address":"2747 Rue Principale",
    "sg:city":"Dunham",
    "sg:classifiers":[
        {
            "category":"Retail",
            "subcategory":"Auto Repair",
            "type":"Services"
        }
    ],
    "sg:phone":"+1 450 263 7444",
    "sg:postcode":"J0E 1M0",
    "sg:province":"QC",
    "sg:tags":[
        "body",
        "automobile",
        "painting"
    ],
    "wof:name":"Carrosserie 202 Inc",
    "wof:placetype":"venue"
},
  "geometry": {"coordinates":[-72.776588,45.170601],"type":"Point"}
}