{
  "type": "Feature",
  "properties": {
    "iso:country":"CA",
    "sg:address":"1580 Trinity Dr",
    "sg:city":"Mississauga",
    "sg:classifiers":[
        {
            "category":"Home & Garden",
            "subcategory":"Garden Supply",
            "type":"Retail Goods"
        }
    ],
    "sg:phone":"+1 905 565 6238",
    "sg:postcode":"L5T 1L6",
    "sg:province":"ON",
    "sg:tags":[
        "center"
    ],
    "wof:name":"Husquarna Forest & Garden Ctr",
    "wof:placetype":"venue"
},
  "geometry": {"coordinates":[-79.64933776860001,43.6595840454],"type":"Point"}
}