{
  "type": "Feature",
  "properties": {
    "addr:full":"294 Caribou St W Moose Jaw SK S6H 2J8",
    "addr:housenumber":"294",
    "addr:postcode":"s6h 2j8",
    "addr:street":"Caribou St W",
    "iso:country":"CA",
    "sg:address":"294 Caribou St W",
    "sg:city":"Moose Jaw",
    "sg:classifiers":[
        {
            "category":"Home & Garden",
            "subcategory":"Household Appliances",
            "type":"Retail Goods"
        }
    ],
    "sg:phone":"+1 306 693 8555",
    "sg:postcode":"S6H 2J8",
    "sg:province":"SK",
    "wof:name":"Western Appliance Svc",
    "wof:placetype":"venue"
},
  "geometry": {"coordinates":[-105.541900635,50.3970108032],"type":"Point"}
}