{
  "type": "Feature",
  "properties": {
    "addr:full":"Calgary AB T2P 3R5",
    "addr:postcode":"t2p 3r5",
    "iso:country":"CA",
    "sg:city":"Calgary",
    "sg:classifiers":[
        {
            "category":"Mining & Drilling",
            "type":"Manufacturing & Wholesale Goods"
        }
    ],
    "sg:phone":"+1 403 262 6000",
    "sg:postcode":"T2P 3R5",
    "sg:province":"AB",
    "sg:tags":[
        "development",
        "gas",
        "oil",
        "exploration"
    ],
    "wof:name":"Emerald Bay Energy Inc",
    "wof:placetype":"venue"
},
  "geometry": {"coordinates":[-114.07811,51.045845],"type":"Point"}
}