{
  "type": "Feature",
  "properties": {
    "addr:full":"Toronto ON M5T 2E8",
    "addr:postcode":"m5t 2e8",
    "iso:country":"CA",
    "sg:city":"Toronto",
    "sg:classifiers":[
        {
            "category":"Shopping",
            "subcategory":"Clothing, Apparel, & Fashions",
            "type":"Retail Goods"
        }
    ],
    "sg:phone":"+1 416 597 0122",
    "sg:postcode":"M5T 2E8",
    "sg:province":"ON",
    "sg:tags":[
        "dressmaker"
    ],
    "wof:name":"Annie Fashions",
    "wof:placetype":"venue"
},
  "geometry": {"coordinates":[-79.398537,43.653362],"type":"Point"}
}