{
  "type": "Feature",
  "properties": {
    "addr:full":"10 Cedar Bay Brandon MB R7B 0Z4",
    "addr:housenumber":"10",
    "addr:postcode":"r7b 0z4",
    "addr:street":"Cedar Bay",
    "iso:country":"CA",
    "sg:address":"10 Cedar Bay",
    "sg:city":"Brandon",
    "sg:classifiers":[
        {
            "category":"Manufacturing",
            "subcategory":"Metals",
            "type":"Manufacturing & Wholesale Goods"
        }
    ],
    "sg:phone":"+1 204 728 2514",
    "sg:postcode":"R7B 0Z4",
    "sg:province":"MB",
    "sg:tags":[
        "tank"
    ],
    "wof:name":"A & J Pump Svc",
    "wof:placetype":"venue"
},
  "geometry": {"coordinates":[-99.97782100000001,49.837532],"type":"Point"}
}