{
  "type": "Feature",
  "properties": {
    "addr:full":"5345 Munro Crt Burlington ON L7L 5M7",
    "addr:housenumber":"5345",
    "addr:postcode":"l7l 5m7",
    "addr:street":"Munro Crt",
    "iso:country":"CA",
    "sg:address":"5345 Munro Crt",
    "sg:city":"Burlington",
    "sg:classifiers":[
        {
            "category":"Manufacturing",
            "subcategory":"Metals",
            "type":"Manufacturing & Wholesale Goods"
        }
    ],
    "sg:phone":"+1 905 639 8010",
    "sg:postcode":"L7L 5M7",
    "sg:province":"ON",
    "sg:tags":[
        "finisher"
    ],
    "wof:name":"Peen & Clean Ltd",
    "wof:placetype":"venue"
},
  "geometry": {"coordinates":[-79.758369,43.389877],"type":"Point"}
}