{
  "type": "Feature",
  "properties": {
    "iso:country":"CA",
    "sg:city":"Centralia",
    "sg:classifiers":[
        {
            "category":"Organizations",
            "subcategory":"Religious Organization",
            "type":"Services"
        }
    ],
    "sg:phone":"+1 519 235 2661",
    "sg:postcode":"N0M 1K0",
    "sg:province":"ON",
    "sg:tags":[
        "church"
    ],
    "wof:name":"Emmanuel Baptist Church",
    "wof:placetype":"venue"
},
  "geometry": {"coordinates":[-81.4677886963,43.2831497192],"type":"Point"}
}