{
  "type": "Feature",
  "properties": {
    "addr:full":"39 Rue DE LA Fabrique Thetford Mines QC G6G 2N4",
    "addr:housenumber":"39",
    "addr:postcode":"g6g 2n4",
    "addr:street":"Rue De La Fabrique",
    "iso:country":"CA",
    "sg:address":"39 Rue DE LA Fabrique",
    "sg:city":"Thetford Mines",
    "sg:classifiers":[
        {
            "category":"Building & Trades",
            "subcategory":"Construction",
            "type":"Services"
        }
    ],
    "sg:phone":"+1 418 335 6782",
    "sg:postcode":"G6G 2N4",
    "sg:province":"QC",
    "sg:tags":[
        "masonry",
        "contractor"
    ],
    "wof:name":"Brique Rp Inc",
    "wof:placetype":"venue"
},
  "geometry": {"coordinates":[-71.302772522,46.0914573669],"type":"Point"}
}