{
  "type": "Feature",
  "properties": {
    "addr:full":"Main St Glenside SK S0H 1T0",
    "addr:postcode":"s0h 1t0",
    "addr:street":"Main St",
    "iso:country":"CA",
    "sg:address":"Main St",
    "sg:city":"Glenside",
    "sg:classifiers":[
        {
            "category":"Government",
            "subcategory":"Post Office",
            "type":"Public Place"
        }
    ],
    "sg:phone":"+1 306 867 1800",
    "sg:postcode":"S0H 1T0",
    "sg:province":"SK",
    "wof:name":"Glenside Post Office",
    "wof:placetype":"venue"
},
  "geometry": {"coordinates":[-106.80075100000001,51.453026],"type":"Point"}
}