{
  "type": "Feature",
  "properties": {
    "iso:country":"CA",
    "sg:address":"1318 Rue Principale",
    "sg:city":"St-Valerien",
    "sg:classifiers":[
        {
            "category":"Building & Trades",
            "subcategory":"Cleaning & Sanitation",
            "type":"Services"
        }
    ],
    "sg:phone":"+1 450 549 2411",
    "sg:postcode":"J0H 2B0",
    "sg:province":"QC",
    "sg:tags":[
        "equipment",
        "snow",
        "removal"
    ],
    "wof:name":"Tenco Ltee",
    "wof:placetype":"venue"
},
  "geometry": {"coordinates":[-68.67347717289999,48.3350715637],"type":"Point"}
}