{
  "type": "Feature",
  "properties": {
    "addr:full":"Mississauga ON L4X 1M4",
    "addr:postcode":"l4x 1m4",
    "iso:country":"CA",
    "sg:city":"Mississauga",
    "sg:classifiers":[
        {
            "category":"Manufacturing",
            "subcategory":"Signs",
            "type":"Manufacturing & Wholesale Goods"
        }
    ],
    "sg:phone":"+1 905 624 2472",
    "sg:postcode":"L4X 1M4",
    "sg:province":"ON",
    "wof:name":"Leger's Awnings",
    "wof:placetype":"venue"
},
  "geometry": {"coordinates":[-79.58223700000001,43.615952],"type":"Point"}
}