{
  "type": "Feature",
  "properties": {
    "addr:full":"6494 Mercer Rd 100 Mile House BC V0K 2E3",
    "addr:housenumber":"6494",
    "addr:postcode":"v0k 2e3",
    "addr:street":"Mercer Rd",
    "iso:country":"CA",
    "sg:address":"6494 Mercer Rd",
    "sg:city":"100 Mile House",
    "sg:classifiers":[
        {
            "category":"Freight",
            "type":"Transportation"
        }
    ],
    "sg:phone":"+1 250 395 3952",
    "sg:postcode":"V0K 2E3",
    "sg:province":"BC",
    "sg:tags":[
        "trucking"
    ],
    "wof:name":"Dennis Skopyk Ent Ltd",
    "wof:placetype":"venue"
},
  "geometry": {"coordinates":[-121.391159058,51.3140258789],"type":"Point"}
}