{
  "type": "Feature",
  "properties": {
    "addr:full":"253 Rue Dufferin Stanstead QC J0B 3E2",
    "addr:housenumber":"253",
    "addr:postcode":"j0b 3e2",
    "addr:street":"Rue Dufferin",
    "iso:country":"CA",
    "sg:address":"253 Rue Dufferin",
    "sg:city":"Stanstead",
    "sg:classifiers":[
        {
            "category":"Personal",
            "type":"Services"
        }
    ],
    "sg:phone":"+1 819 876 7272",
    "sg:postcode":"J0B 3E2",
    "sg:province":"QC",
    "sg:tags":[
        "electrolysis"
    ],
    "wof:name":"Esthetique L'Attirance",
    "wof:placetype":"venue"
},
  "geometry": {"coordinates":[-72.0986480713,45.0075798035],"type":"Point"}
}