{
  "type": "Feature",
  "properties": {
    "addr:full":"390 Rue Principale Leeds Village QC G0N 1J0",
    "addr:housenumber":"390",
    "addr:postcode":"g0n 1j0",
    "addr:street":"Rue Principale Leeds Village",
    "iso:country":"CA",
    "sg:address":"390 Rue Principale",
    "sg:city":"Leeds Village",
    "sg:classifiers":[
        {
            "category":"Food & Beverages",
            "subcategory":"Groceries & Convenience Stores",
            "type":"Retail Goods"
        }
    ],
    "sg:phone":"+1 418 424 3878",
    "sg:postcode":"G0N 1J0",
    "sg:province":"QC",
    "sg:tags":[
        "grocer"
    ],
    "wof:name":"C R Nadeau Inc",
    "wof:placetype":"venue"
},
  "geometry": {"coordinates":[-71.3382110596,46.2879104614],"type":"Point"}
}