{
  "type": "Feature",
  "properties": {
    "addr:full":"Vancouver BC V6Z 2B8",
    "addr:postcode":"v6z 2b8",
    "iso:country":"CA",
    "sg:city":"Vancouver",
    "sg:classifiers":[
        {
            "category":"Professional",
            "subcategory":"Employment Agencies",
            "type":"Services"
        }
    ],
    "sg:phone":"+1 604 682 2905",
    "sg:postcode":"V6Z 2B8",
    "sg:province":"BC",
    "sg:tags":[
        "opportunity"
    ],
    "wof:name":"English Teachers Overseas",
    "wof:placetype":"venue"
},
  "geometry": {"coordinates":[-123.13117217999999,49.2776527405],"type":"Point"}
}