{
  "type": "Feature",
  "properties": {
    "addr:full":"59 Jays Dr Whitby ON L1R 2T8",
    "addr:housenumber":"59",
    "addr:postcode":"l1r 2t8",
    "addr:street":"Jays Dr",
    "iso:country":"CA",
    "sg:address":"59 Jays Dr",
    "sg:city":"Whitby",
    "sg:classifiers":[
        {
            "category":"Banks & Credit Unions",
            "subcategory":"Investment Brokerage",
            "type":"Services"
        }
    ],
    "sg:phone":"+1 905 430 0292",
    "sg:postcode":"L1R 2T8",
    "sg:province":"ON",
    "sg:tags":[
        "consultant",
        "financing"
    ],
    "wof:name":"Alexus Financial Group Inc",
    "wof:placetype":"venue"
},
  "geometry": {"coordinates":[-78.95605500000001,43.906727],"type":"Point"}
}