{
  "type": "Feature",
  "properties": {
    "iso:country":"CA",
    "sg:address":"General Delivery",
    "sg:city":"Kegaska",
    "sg:classifiers":[
        {
            "category":"Food & Beverages",
            "subcategory":"Groceries & Convenience Stores",
            "type":"Retail Goods"
        }
    ],
    "sg:phone":"+1 418 726 3070",
    "sg:postcode":"G0G 1S0",
    "sg:province":"QC",
    "sg:tags":[
        "grocer"
    ],
    "wof:name":"Rogers Retail",
    "wof:placetype":"venue"
},
  "geometry": {"coordinates":[-61.2722892761,50.1883735657],"type":"Point"}
}