{
  "type": "Feature",
  "properties": {
    "addr:full":"Maple Ridge BC V2X 5Z6",
    "addr:postcode":"v2x 5z6",
    "iso:country":"CA",
    "sg:city":"Maple Ridge",
    "sg:classifiers":[
        {
            "category":"Government",
            "subcategory":"Office",
            "type":"Public Place"
        }
    ],
    "sg:phone":"+1 604 476 7070",
    "sg:postcode":"V2X 5Z6",
    "sg:province":"BC",
    "wof:name":"Freaser Health Audiology",
    "wof:placetype":"venue"
},
  "geometry": {"coordinates":[-122.599152,49.220371],"type":"Point"}
}