{
  "type": "Feature",
  "properties": {
    "addr:full":"802 Exeter Rd # 200 London ON N6E 1L5",
    "addr:housenumber":"802",
    "addr:postcode":"n6e 1l5",
    "addr:street":"Exeter Rd # 200",
    "iso:country":"CA",
    "sg:address":"802 Exeter Rd # 200",
    "sg:city":"London",
    "sg:classifiers":[
        {
            "category":"Personal",
            "subcategory":"Massage",
            "type":"Services"
        }
    ],
    "sg:phone":"+1 519 686 2574",
    "sg:postcode":"N6E 1L5",
    "sg:province":"ON",
    "wof:name":"Ambiance Health Studio",
    "wof:placetype":"venue"
},
  "geometry": {"coordinates":[-81.216156,42.926121],"type":"Point"}
}