{
  "type": "Feature",
  "properties": {
    "iso:country":"CA",
    "sg:address":"6195 Boul Des Roseraies",
    "sg:city":"Anjou",
    "sg:classifiers":[
        {
            "category":"Real Estate",
            "subcategory":"Real Estate Agent",
            "type":"Services"
        }
    ],
    "sg:phone":"+1 514 255 4949",
    "sg:postcode":"H1M 1T9",
    "sg:province":"QC",
    "wof:name":"Immeubles Ls Soleil Inc",
    "wof:placetype":"venue"
},
  "geometry": {"coordinates":[-73.551612854,45.5957794189],"type":"Point"}
}