{
  "type": "Feature",
  "properties": {
    "addr:full":"1466 Rue Des Copains Sainte-Adele QC J8B 2A1",
    "addr:housenumber":"1466",
    "addr:postcode":"j8b 2a1",
    "addr:street":"Rue Des Copains Sainte-Adele",
    "iso:country":"CA",
    "sg:address":"1466 Rue Des Copains",
    "sg:city":"Sainte-Adele",
    "sg:classifiers":[
        {
            "category":"Recreation",
            "type":"Entertainment"
        }
    ],
    "sg:phone":"+1 450 229 6600",
    "sg:postcode":"J8B 2A1",
    "sg:province":"QC",
    "sg:tags":[
        "course",
        "golf"
    ],
    "wof:name":"Club DE Golf Alpine",
    "wof:placetype":"venue"
},
  "geometry": {"coordinates":[-74.12019348139999,45.9854354858],"type":"Point"}
}