{
  "type": "Feature",
  "properties": {
    "addr:full":"Windsor ON N9A 1A9",
    "addr:postcode":"n9a 1a9",
    "iso:country":"CA",
    "sg:city":"Windsor",
    "sg:classifiers":[
        {
            "category":"Professional",
            "subcategory":"Lawyer & Legal Services",
            "type":"Services"
        }
    ],
    "sg:phone":"+1 519 253 7461",
    "sg:postcode":"N9A 1A9",
    "sg:province":"ON",
    "sg:tags":[
        "attorney"
    ],
    "wof:name":"Jovanovic, D Stephen",
    "wof:placetype":"venue"
},
  "geometry": {"coordinates":[-83.0383758545,42.3167953491],"type":"Point"}
}