{
  "type": "Feature",
  "properties": {
    "iso:country":"CA",
    "sg:address":"1144 Confederation Dr",
    "sg:city":"Port Coquitlam",
    "sg:classifiers":[
        {
            "category":"Education",
            "subcategory":"School",
            "type":"Public Place"
        }
    ],
    "sg:phone":"+1 604 468 8620",
    "sg:postcode":"V3C 6P1",
    "sg:province":"BC",
    "wof:name":"Castle Park Elementary",
    "wof:placetype":"venue"
},
  "geometry": {"coordinates":[-122.785415649,49.2334671021],"type":"Point"}
}