{
  "type": "Feature",
  "properties": {
    "addr:full":"10050 River Rd W Oakville MB R0H 0Y0",
    "addr:housenumber":"10050",
    "addr:postcode":"r0h 0y0",
    "addr:street":"River Rd W",
    "iso:country":"CA",
    "sg:address":"10050 River Rd W",
    "sg:city":"Oakville",
    "sg:classifiers":[
        {
            "category":"Education",
            "subcategory":"School",
            "type":"Public Place"
        }
    ],
    "sg:phone":"+1 204 267 2547",
    "sg:postcode":"R0H 0Y0",
    "sg:province":"MB",
    "wof:name":"Poplar Point Colony School",
    "wof:placetype":"venue"
},
  "geometry": {"coordinates":[-98.003952,49.92976],"type":"Point"}
}