{
  "type": "Feature",
  "properties": {
    "addr:full":"42 Rue Turgeon # B Sainte-Therese QC J7E 3H4",
    "addr:housenumber":"42;# b",
    "addr:postcode":"j7e 3h4",
    "addr:street":"Rue Turgeon;Sainte-Therese",
    "iso:country":"CA",
    "sg:address":"42 Rue Turgeon # B",
    "sg:city":"Sainte-Therese",
    "sg:classifiers":[
        {
            "category":"Professional",
            "subcategory":"Management & Consulting",
            "type":"Services"
        }
    ],
    "sg:phone":"+1 450 434 8787",
    "sg:postcode":"J7E 3H4",
    "sg:province":"QC",
    "sg:tags":[
        "control",
        "consultant",
        "quality"
    ],
    "wof:name":"Pracxis International Qualite",
    "wof:placetype":"venue"
},
  "geometry": {"coordinates":[-73.840508,45.638279],"type":"Point"}
}