{
  "type": "Feature",
  "properties": {
    "addr:full":"129 Rue Saint-Patrice E Magog QC J1X 1T7",
    "addr:housenumber":"129",
    "addr:postcode":"j1x 1t7",
    "addr:street":"Rue Saint-Patrice E",
    "iso:country":"CA",
    "sg:address":"129 Rue Saint-Patrice E",
    "sg:city":"Magog",
    "sg:classifiers":[
        {
            "category":"Personal",
            "subcategory":"Beauty Salon",
            "type":"Services"
        }
    ],
    "sg:phone":"+1 819 843 6813",
    "sg:postcode":"J1X 1T7",
    "sg:province":"QC",
    "sg:tags":[
        "barber"
    ],
    "wof:name":"Coiffure LA Belle Image",
    "wof:placetype":"venue"
},
  "geometry": {"coordinates":[-72.14212000000001,45.265179],"type":"Point"}
}