{
  "type": "Feature",
  "properties": {
    "addr:full":"85 Rue Jean-Proulx Hull QC J8Z 1W2",
    "addr:housenumber":"85",
    "addr:postcode":"j8z 1w2",
    "addr:street":"Rue Jean-Proulx",
    "iso:country":"CA",
    "sg:address":"85 Rue Jean-Proulx",
    "sg:city":"Hull",
    "sg:classifiers":[
        {
            "category":"Government",
            "subcategory":"Police Station",
            "type":"Public Place"
        }
    ],
    "sg:phone":"+1 819 770 9111",
    "sg:postcode":"J8Z 1W2",
    "sg:province":"QC",
    "sg:tags":[
        "department"
    ],
    "wof:name":"Quebec Surete",
    "wof:placetype":"venue"
},
  "geometry": {"coordinates":[-75.7410736084,45.4677886963],"type":"Point"}
}