{
  "type": "Feature",
  "properties": {
    "addr:full":"71 Mearns Crt # 10 Bowmanville ON L1C 4N4",
    "addr:housenumber":"71",
    "addr:postcode":"l1c 4n4",
    "addr:street":"Mearns Crt # 10",
    "iso:country":"CA",
    "sg:address":"71 Mearns Crt # 10",
    "sg:city":"Bowmanville",
    "sg:classifiers":[
        {
            "category":"Retail",
            "subcategory":"Auto Repair",
            "type":"Services"
        }
    ],
    "sg:phone":"+1 905 697 2011",
    "sg:postcode":"L1C 4N4",
    "sg:province":"ON",
    "sg:tags":[
        "automobile",
        "rustproofing",
        "undercoating"
    ],
    "wof:name":"Bob's Oil Rust Proofing Ltd",
    "wof:placetype":"venue"
},
  "geometry": {"coordinates":[-78.6656112671,43.9020767212],"type":"Point"}
}