{
  "type": "Feature",
  "properties": {
    "iso:country":"CA",
    "sg:address":"PO Box 40",
    "sg:city":"Alberta Beach",
    "sg:classifiers":[
        {
            "category":"Wholesale",
            "subcategory":"Construction Materials",
            "type":"Manufacturing & Wholesale Goods"
        }
    ],
    "sg:phone":"+1 780 924 2498",
    "sg:postcode":"T0E 0A0",
    "sg:province":"AB",
    "sg:tags":[
        "sand",
        "gravel"
    ],
    "wof:name":"Doug Heron Trucking",
    "wof:placetype":"venue"
},
  "geometry": {"coordinates":[-114.360534668,53.6718482971],"type":"Point"}
}