{
  "type": "Feature",
  "properties": {
    "addr:full":"Vancouver BC V6H 3V9",
    "addr:postcode":"v6h 3v9",
    "iso:country":"CA",
    "sg:city":"Vancouver",
    "sg:classifiers":[
        {
            "category":"Professional",
            "subcategory":"Lawyer & Legal Services",
            "type":"Services"
        }
    ],
    "sg:phone":"+1 604 739 4655",
    "sg:postcode":"V6H 3V9",
    "sg:province":"BC",
    "sg:tags":[
        "attorney"
    ],
    "wof:name":"Lichtenwald, Rhona M",
    "wof:placetype":"venue"
},
  "geometry": {"coordinates":[-123.135795593,49.2646408081],"type":"Point"}
}