{
  "type": "Feature",
  "properties": {
    "addr:full":"Tillsonburg ON N4G 4G8",
    "addr:postcode":"n4g 4g8",
    "iso:country":"CA",
    "sg:city":"Tillsonburg",
    "sg:classifiers":[
        {
            "category":"Organizations",
            "subcategory":"Religious Organization",
            "type":"Services"
        }
    ],
    "sg:phone":"+1 519 842 3251",
    "sg:postcode":"N4G 4G8",
    "sg:province":"ON",
    "sg:tags":[
        "church"
    ],
    "wof:name":"New Hope Baptist Independent",
    "wof:placetype":"venue"
},
  "geometry": {"coordinates":[-80.75561500000001,42.838322],"type":"Point"}
}