{
  "type": "Feature",
  "properties": {
    "addr:full":"460 Mountjoy St S Timmins ON P4N 1V6",
    "addr:housenumber":"460",
    "addr:postcode":"p4n 1v6",
    "addr:street":"Mountjoy St S",
    "iso:country":"CA",
    "sg:address":"460 Mountjoy St S",
    "sg:city":"Timmins",
    "sg:classifiers":[
        {
            "category":"Building & Trades",
            "subcategory":"Plumbing",
            "type":"Services"
        }
    ],
    "sg:phone":"+1 705 264 5989",
    "sg:postcode":"P4N 1V6",
    "sg:province":"ON",
    "sg:tags":[
        "contractor"
    ],
    "wof:name":"Theriault Plumbing & Heating",
    "wof:placetype":"venue"
},
  "geometry": {"coordinates":[-81.33554100000001,48.467079],"type":"Point"}
}