{
  "type": "Feature",
  "properties": {
    "addr:full":"1650 Dundas St E Whitby ON L1N 2K8",
    "addr:housenumber":"1650",
    "addr:postcode":"l1n 2k8",
    "addr:street":"Dundas St E",
    "iso:country":"CA",
    "sg:address":"1650 Dundas St E",
    "sg:city":"Whitby",
    "sg:classifiers":[
        {
            "category":"Home & Garden",
            "subcategory":"Furniture",
            "type":"Retail Goods"
        }
    ],
    "sg:phone":"+1 905 571 7700",
    "sg:postcode":"L1N 2K8",
    "sg:province":"ON",
    "wof:name":"Double Discount Furniture",
    "wof:placetype":"venue"
},
  "geometry": {"coordinates":[-78.910706,43.887131],"type":"Point"}
}