{
  "type": "Feature",
  "properties": {
    "iso:country":"CA",
    "sg:address":"207 Danforth Ave",
    "sg:city":"Toronto",
    "sg:classifiers":[
        {
            "category":"Cinema",
            "subcategory":"Movie Rental",
            "type":"Entertainment"
        }
    ],
    "sg:phone":"+1 416 778 5776",
    "sg:postcode":"M4K 1N2",
    "sg:province":"ON",
    "sg:tags":[
        "leasing",
        "video",
        "disc",
        "tape"
    ],
    "wof:name":"Revue Video",
    "wof:placetype":"venue"
},
  "geometry": {"coordinates":[-79.355659,43.676662],"type":"Point"}
}