{
  "type": "Feature",
  "properties": {
    "addr:full":"3425 Semenyk Crt Mississauga ON L5C 4P9",
    "addr:housenumber":"3425",
    "addr:postcode":"l5c 4p9",
    "addr:street":"Semenyk Crt",
    "iso:country":"CA",
    "sg:address":"3425 Semenyk Crt",
    "sg:city":"Mississauga",
    "sg:classifiers":[
        {
            "category":"Manufacturing",
            "subcategory":"Tools & Machinery",
            "type":"Manufacturing & Wholesale Goods"
        }
    ],
    "sg:phone":"+1 905 897 9800",
    "sg:postcode":"L5C 4P9",
    "sg:province":"ON",
    "sg:tags":[
        "compressor"
    ],
    "wof:name":"National Compressed Air Canada",
    "wof:placetype":"venue"
},
  "geometry": {"coordinates":[-79.6523590088,43.5681266785],"type":"Point"}
}