{
  "type": "Feature",
  "properties": {
    "addr:full":"5012 Airport Dr Fort Nelson BC V0C 1R0",
    "addr:housenumber":"5012",
    "addr:postcode":"bc v0c 1r0",
    "addr:street":"Airport Dr",
    "iso:country":"CA",
    "sg:address":"5012 Airport Dr",
    "sg:city":"Fort Nelson",
    "sg:classifiers":[
        {
            "category":"Real Estate",
            "subcategory":"Real Estate Agent",
            "type":"Services"
        }
    ],
    "sg:phone":"+1 250 774 7653",
    "sg:postcode":"V0C 1R0",
    "sg:province":"BC",
    "wof:name":"Fort Nelson Realty Ltd",
    "wof:placetype":"venue"
},
  "geometry": {"coordinates":[-122.696907,58.805649],"type":"Point"}
}