{
  "type": "Feature",
  "properties": {
    "addr:full":"10750 97th Ave Grande Cache AB T0E 0Y0",
    "addr:housenumber":"10750",
    "addr:postcode":"t0e 0y0",
    "addr:street":"97Th Ave Grande",
    "iso:country":"CA",
    "sg:address":"10750 97th Ave",
    "sg:city":"Grande Cache",
    "sg:classifiers":[
        {
            "category":"Social Services",
            "type":"Services"
        }
    ],
    "sg:phone":"+1 780 827 3776",
    "sg:postcode":"T0E 0Y0",
    "sg:province":"AB",
    "sg:tags":[
        "crisis",
        "center"
    ],
    "wof:name":"Grande Cache Transition House",
    "wof:placetype":"venue"
},
  "geometry": {"coordinates":[-119.131264,53.881283],"type":"Point"}
}