{
  "type": "Feature",
  "properties": {
    "addr:full":"4811 50 Ave Leduc AB T9E 6X8",
    "addr:housenumber":"4811",
    "addr:postcode":"t9e 6x8",
    "addr:street":"50 Ave",
    "iso:country":"CA",
    "sg:address":"4811 50 Ave",
    "sg:city":"Leduc",
    "sg:classifiers":[
        {
            "category":"Shopping",
            "subcategory":"Clothing, Apparel, & Fashions",
            "type":"Retail Goods"
        }
    ],
    "sg:phone":"+1 780 986 0250",
    "sg:postcode":"T9E 6X8",
    "sg:province":"AB",
    "wof:name":"Leg's N Things Boutique",
    "wof:placetype":"venue"
},
  "geometry": {"coordinates":[-113.549019,53.264645],"type":"Point"}
}