{
  "type": "Feature",
  "properties": {
    "addr:full":"Calgary AB T2P 4V1",
    "addr:postcode":"t2p 4v1",
    "iso:country":"CA",
    "sg:city":"Calgary",
    "sg:classifiers":[
        {
            "category":"Professional",
            "subcategory":"Accounting & Tax Preparation",
            "type":"Services"
        }
    ],
    "sg:phone":"+1 403 234 0734",
    "sg:postcode":"T2P 4V1",
    "sg:province":"AB",
    "sg:tags":[
        "accountant"
    ],
    "wof:name":"Joyce, James R",
    "wof:placetype":"venue"
},
  "geometry": {"coordinates":[-114.08380127,51.049118042],"type":"Point"}
}