{
  "type": "Feature",
  "properties": {
    "addr:full":"360 Bay St Victoria BC V8T 1P7",
    "addr:housenumber":"360",
    "addr:postcode":"v8t 1p7",
    "addr:street":"Bay St",
    "iso:country":"CA",
    "sg:address":"360 Bay St",
    "sg:city":"Victoria",
    "sg:classifiers":[
        {
            "category":"Shopping",
            "subcategory":"Computers & Home Electronics",
            "type":"Retail Goods"
        }
    ],
    "sg:phone":"+1 250 360 1116",
    "sg:postcode":"V8T 1P7",
    "sg:province":"BC",
    "sg:tags":[
        "equipment",
        "dealer"
    ],
    "wof:name":"Paradon Computer Systems",
    "wof:placetype":"venue"
},
  "geometry": {"coordinates":[-123.375366,48.435062],"type":"Point"}
}