{
  "type": "Feature",
  "properties": {
    "iso:country":"CA",
    "sg:address":"5700 Rue Philippe-Turcot",
    "sg:city":"Montreal",
    "sg:classifiers":[
        {
            "category":"Manufacturing",
            "subcategory":"Metals",
            "type":"Manufacturing & Wholesale Goods"
        }
    ],
    "sg:phone":"+1 514 937 6187",
    "sg:postcode":"H4C 1V6",
    "sg:province":"QC",
    "sg:tags":[
        "heat",
        "exchanger"
    ],
    "wof:name":"H C Vidal Ltee",
    "wof:placetype":"venue"
},
  "geometry": {"coordinates":[-73.599594,45.46389],"type":"Point"}
}