{
  "type": "Feature",
  "properties": {
    "addr:full":"750 Rue Notre-Dame Repentigny QC J5Y 1B5",
    "addr:housenumber":"750",
    "addr:postcode":"j5y 1b5",
    "addr:street":"Rue Notre-Dame",
    "iso:country":"CA",
    "sg:address":"750 Rue Notre-Dame",
    "sg:city":"Repentigny",
    "sg:classifiers":[
        {
            "category":"Health Services",
            "subcategory":"Doctor",
            "type":"Services"
        }
    ],
    "sg:phone":"+1 450 585 0668",
    "sg:postcode":"J5Y 1B5",
    "sg:province":"QC",
    "sg:tags":[
        "clinic",
        "veterinarian"
    ],
    "wof:name":"Hopital Veterinaire P Lanoue",
    "wof:placetype":"venue"
},
  "geometry": {"coordinates":[-73.426338,45.758469],"type":"Point"}
}