{
  "type": "Feature",
  "properties": {
    "addr:full":"123 Rue Saint-Louis Saint-Eustache QC J7R 1X9",
    "addr:housenumber":"123",
    "addr:postcode":"j7r 1x9",
    "addr:street":"Rue Saint-Louis",
    "iso:country":"CA",
    "sg:address":"123 Rue Saint-Louis",
    "sg:city":"Saint-Eustache",
    "sg:classifiers":[
        {
            "category":"Real Estate",
            "subcategory":"Developer",
            "type":"Services"
        }
    ],
    "sg:phone":"+1 450 473 7859",
    "sg:postcode":"J7R 1X9",
    "sg:province":"QC",
    "sg:tags":[
        "cemetery"
    ],
    "wof:name":"Cimetiere St-Eustache",
    "wof:placetype":"venue"
},
  "geometry": {"coordinates":[-73.889679,45.556999],"type":"Point"}
}