{
  "type": "Feature",
  "properties": {
    "addr:full":"Sparwood BC V0B 2G0",
    "addr:postcode":"bc v0b 2g0",
    "iso:country":"CA",
    "sg:city":"Sparwood",
    "sg:classifiers":[
        {
            "category":"Education",
            "subcategory":"Library",
            "type":"Public Place"
        }
    ],
    "sg:phone":"+1 250 425 2299",
    "sg:postcode":"V0B 2G0",
    "sg:province":"BC",
    "wof:name":"Sparwood Public Library",
    "wof:placetype":"venue"
},
  "geometry": {"coordinates":[-114.881058,49.73436],"type":"Point"}
}