{
  "type": "Feature",
  "properties": {
    "addr:full":"7725 Rue Saint-Denis Montreal QC H2R 2E9",
    "addr:housenumber":"7725",
    "addr:postcode":"h2r 2e9",
    "addr:street":"Rue Saint-Denis",
    "iso:country":"CA",
    "sg:address":"7725 Rue Saint-Denis",
    "sg:city":"Montreal",
    "sg:classifiers":[
        {
            "category":"Travel",
            "subcategory":"Travel Agent",
            "type":"Entertainment"
        }
    ],
    "sg:phone":"+1 514 273 3301",
    "sg:postcode":"H2R 2E9",
    "sg:province":"QC",
    "sg:tags":[
        "agency",
        "bureau"
    ],
    "wof:name":"Agence DE Voyages Bergeron Inc",
    "wof:placetype":"venue"
},
  "geometry": {"coordinates":[-73.62352752690001,45.5411071777],"type":"Point"}
}