{
  "type": "Feature",
  "properties": {
    "addr:full":"100 Rue DE L'Eveche O Rimouski QC G5L 4H7",
    "addr:housenumber":"100",
    "addr:postcode":"g5l 4h7",
    "addr:street":"Rue De L'Eveche O",
    "iso:country":"CA",
    "sg:address":"100 Rue DE L'Eveche O",
    "sg:city":"Rimouski",
    "sg:classifiers":[
        {
            "category":"Organizations",
            "subcategory":"Professional Association",
            "type":"Services"
        }
    ],
    "sg:phone":"+1 418 723 7456",
    "sg:postcode":"G5L 4H7",
    "sg:province":"QC",
    "wof:name":"Salon Du Livre DE Rimouski",
    "wof:placetype":"venue"
},
  "geometry": {"coordinates":[-68.52568100000001,48.447529],"type":"Point"}
}