{
  "type": "Feature",
  "properties": {
    "addr:full":"575 Palmer Rd NE Calgary AB T2E 7G4",
    "addr:housenumber":"575",
    "addr:postcode":"t2e 7g4",
    "addr:street":"Palmer Rd Ne",
    "iso:country":"CA",
    "sg:address":"575 Palmer Rd NE",
    "sg:city":"Calgary",
    "sg:classifiers":[
        {
            "category":"Building & Trades",
            "subcategory":"Equipment Rental",
            "type":"Services"
        }
    ],
    "sg:phone":"+1 403 735 5914",
    "sg:postcode":"T2E 7G4",
    "sg:province":"AB",
    "sg:tags":[
        "helicopter",
        "aircraft",
        "leasing",
        "charter"
    ],
    "wof:name":"Canadian Helicopters Ltd",
    "wof:placetype":"venue"
},
  "geometry": {"coordinates":[-114.01159699999999,51.099403],"type":"Point"}
}