{
  "type": "Feature",
  "properties": {
    "iso:country":"CA",
    "sg:city":"Portage LA Prairie",
    "sg:classifiers":[
        {
            "category":"Insurance",
            "subcategory":"Insurance Agent",
            "type":"Services"
        }
    ],
    "sg:phone":"+1 204 857 2830",
    "sg:postcode":"R1N 0K5",
    "sg:province":"MB",
    "wof:name":"Dewis, Larry",
    "wof:placetype":"venue"
},
  "geometry": {"coordinates":[-98.28128100000001,49.972706],"type":"Point"}
}