{
  "type": "Feature",
  "properties": {
    "addr:full":"1402 Queen St W Toronto ON M6K 1L9",
    "addr:housenumber":"1402",
    "addr:postcode":"m6k 1l9",
    "addr:street":"Queen St W",
    "iso:country":"CA",
    "sg:address":"1402 Queen St W",
    "sg:city":"Toronto",
    "sg:classifiers":[
        {
            "category":"Food & Beverages",
            "subcategory":"Bakery",
            "type":"Retail Goods"
        }
    ],
    "sg:phone":"+1 416 535 2087",
    "sg:postcode":"M6K 1L9",
    "sg:province":"ON",
    "sg:tags":[
        "doughnut"
    ],
    "wof:name":"Coffee Time Donuts Inc",
    "wof:placetype":"venue"
},
  "geometry": {"coordinates":[-79.434265,43.641125],"type":"Point"}
}