{
  "type": "Feature",
  "properties": {
    "addr:full":"2876 Ellesmere Rd Scarborough ON M1E 4B8",
    "addr:housenumber":"2876",
    "addr:postcode":"m1e 4b8",
    "addr:street":"Ellesmere Rd",
    "iso:country":"CA",
    "sg:address":"2876 Ellesmere Rd",
    "sg:city":"Scarborough",
    "sg:classifiers":[
        {
            "category":"Food & Beverages",
            "subcategory":"Fruits & Vegetables",
            "type":"Retail Goods"
        }
    ],
    "sg:phone":"+1 416 282 5498",
    "sg:postcode":"M1E 4B8",
    "sg:province":"ON",
    "sg:tags":[
        "produce"
    ],
    "wof:name":"Young Fruit Market",
    "wof:placetype":"venue"
},
  "geometry": {"coordinates":[-79.2037658691,43.7830314636],"type":"Point"}
}