{
  "type": "Feature",
  "properties": {
    "addr:full":"Calgary AB T2E 7Y2",
    "addr:postcode":"t2e 7y2",
    "iso:country":"CA",
    "sg:city":"Calgary",
    "sg:classifiers":[
        {
            "category":"Professional",
            "subcategory":"Lawyer & Legal Services",
            "type":"Services"
        }
    ],
    "sg:phone":"+1 403 230 8088",
    "sg:postcode":"T2E 7Y2",
    "sg:province":"AB",
    "sg:tags":[
        "attorney"
    ],
    "wof:name":"Stewart, John B P",
    "wof:placetype":"venue"
},
  "geometry": {"coordinates":[-114.062637,51.067047],"type":"Point"}
}