{
  "type": "Feature",
  "properties": {
    "addr:full":"707 Park Royal N West Vancouver BC V7T 1H9",
    "addr:housenumber":"707",
    "addr:postcode":"v7t 1h9",
    "addr:street":"Park Royal N",
    "iso:country":"CA",
    "sg:address":"707 Park Royal N",
    "sg:city":"West Vancouver",
    "sg:classifiers":[
        {
            "category":"Shopping",
            "subcategory":"Clothing, Apparel, & Fashions",
            "type":"Retail Goods"
        }
    ],
    "sg:phone":"+1 604 922 4204",
    "sg:postcode":"V7T 1H9",
    "sg:province":"BC",
    "wof:name":"Aldila Boutique",
    "wof:placetype":"venue"
},
  "geometry": {"coordinates":[-123.13707700000001,49.327438],"type":"Point"}
}