{
  "type": "Feature",
  "properties": {
    "addr:full":"302 Rue Saint-Cyrille Tring-Jonction QC G0N 1X0",
    "addr:housenumber":"302",
    "addr:postcode":"g0n 1x0",
    "addr:street":"Rue Saint-Cyrille",
    "iso:country":"CA",
    "sg:address":"302 Rue Saint-Cyrille",
    "sg:city":"Tring-Jonction",
    "sg:classifiers":[
        {
            "category":"Education",
            "subcategory":"School",
            "type":"Public Place"
        }
    ],
    "sg:phone":"+1 418 426 2848",
    "sg:postcode":"G0N 1X0",
    "sg:province":"QC",
    "wof:name":"Ecole Ste-Famille",
    "wof:placetype":"venue"
},
  "geometry": {"coordinates":[-70.99636099999999,46.268032],"type":"Point"}
}