{
  "type": "Feature",
  "properties": {
    "iso:country":"CA",
    "sg:address":"1982 Jefferson Blvd",
    "sg:city":"Windsor",
    "sg:classifiers":[
        {
            "category":"Building & Trades",
            "subcategory":"Construction",
            "type":"Services"
        }
    ],
    "sg:phone":"+1 519 945 2449",
    "sg:postcode":"N8T 2W2",
    "sg:province":"ON",
    "sg:tags":[
        "painter"
    ],
    "wof:name":"Robert Belanger Painting",
    "wof:placetype":"venue"
},
  "geometry": {"coordinates":[-82.9531173706,42.3127784729],"type":"Point"}
}