{
  "type": "Feature",
  "properties": {
    "addr:full":"St Albert AB T8N 3B9",
    "addr:postcode":"t8n 3b9",
    "iso:country":"CA",
    "sg:city":"St Albert",
    "sg:classifiers":[
        {
            "category":"Social Services",
            "subcategory":"Child Care",
            "type":"Services"
        }
    ],
    "sg:phone":"+1 780 459 0888",
    "sg:postcode":"T8N 3B9",
    "sg:province":"AB",
    "wof:name":"An Enchanted Forest Daycare",
    "wof:placetype":"venue"
},
  "geometry": {"coordinates":[-113.59658050500001,53.6524085999],"type":"Point"}
}