{
  "type": "Feature",
  "properties": {
    "addr:full":"Campbell River BC V9W 2C6",
    "addr:postcode":"v9w 2c6",
    "iso:country":"CA",
    "sg:city":"Campbell River",
    "sg:classifiers":[
        {
            "category":"Professional",
            "subcategory":"Lawyer & Legal Services",
            "type":"Services"
        }
    ],
    "sg:phone":"+1 250 287 2050",
    "sg:postcode":"V9W 2C6",
    "sg:province":"BC",
    "sg:tags":[
        "attorney"
    ],
    "wof:name":"Henning, Harold A",
    "wof:placetype":"venue"
},
  "geometry": {"coordinates":[-125.24445342999999,50.0261306763],"type":"Point"}
}