{
  "type": "Feature",
  "properties": {
    "addr:full":"309 Fifth Line E Sault Ste Marie ON P6A 5K8",
    "addr:housenumber":"309",
    "addr:postcode":"p6a 5k8",
    "addr:street":"Fifth Line E",
    "iso:country":"CA",
    "sg:address":"309 Fifth Line E",
    "sg:city":"Sault Ste Marie",
    "sg:classifiers":[
        {
            "category":"Freight",
            "type":"Transportation"
        }
    ],
    "sg:phone":"+1 705 759 3941",
    "sg:postcode":"P6A 5K8",
    "sg:province":"ON",
    "sg:tags":[
        "trucking"
    ],
    "wof:name":"Norwood Trucking",
    "wof:placetype":"venue"
},
  "geometry": {"coordinates":[-84.325417,46.581306],"type":"Point"}
}