{
  "type": "Feature",
  "properties": {
    "addr:full":"520 Boul Saint-Joseph Drummondville QC J2C 2B8",
    "addr:housenumber":"520",
    "addr:postcode":"j2c 2b8",
    "addr:street":"Boul Saint-Joseph",
    "iso:country":"CA",
    "sg:address":"520 Boul Saint-Joseph",
    "sg:city":"Drummondville",
    "sg:classifiers":[
        {
            "category":"Personal",
            "subcategory":"Tanning Parlor",
            "type":"Services"
        }
    ],
    "sg:phone":"+1 819 472 4031",
    "sg:postcode":"J2C 2B8",
    "sg:province":"QC",
    "sg:tags":[
        "salon"
    ],
    "wof:name":"Soleil Detente Drummond",
    "wof:placetype":"venue"
},
  "geometry": {"coordinates":[-72.51528167719999,45.8938865662],"type":"Point"}
}