{
  "type": "Feature",
  "properties": {
    "iso:country":"CA",
    "sg:address":"540 South Railway St SE",
    "sg:city":"Medicine Hat",
    "sg:classifiers":[
        {
            "category":"Retail",
            "subcategory":"Funeral Services",
            "type":"Services"
        }
    ],
    "sg:phone":"+1 403 526 2214",
    "sg:postcode":"T1A 2V6",
    "sg:province":"AB",
    "sg:tags":[
        "director"
    ],
    "wof:name":"Pattison Funeral Home",
    "wof:placetype":"venue"
},
  "geometry": {"coordinates":[-110.671516419,50.0375595093],"type":"Point"}
}