{
  "type": "Feature",
  "properties": {
    "addr:full":"866 Rue Moisan Chibougamau QC G8P 2W9",
    "addr:housenumber":"866",
    "addr:postcode":"g8p 2w9",
    "addr:street":"Rue Moisan",
    "iso:country":"CA",
    "sg:address":"866 Rue Moisan",
    "sg:city":"Chibougamau",
    "sg:classifiers":[
        {
            "category":"Organizations",
            "subcategory":"Professional Association",
            "type":"Services"
        }
    ],
    "sg:phone":"+1 418 748 2411",
    "sg:postcode":"G8P 2W9",
    "sg:province":"QC",
    "wof:name":"Chevaliers DE Colomb Inc",
    "wof:placetype":"venue"
},
  "geometry": {"coordinates":[-74.3852386475,49.9178886414],"type":"Point"}
}