{
  "type": "Feature",
  "properties": {
    "addr:full":"55 Glen Cameron Rd # 201 Thornhill ON L3T 1P2",
    "addr:housenumber":"55",
    "addr:postcode":"l3t 1p2",
    "addr:street":"Glen Cameron Rd # 201",
    "iso:country":"CA",
    "sg:address":"55 Glen Cameron Rd # 201",
    "sg:city":"Thornhill",
    "sg:classifiers":[
        {
            "category":"Professional",
            "subcategory":"Management & Consulting",
            "type":"Services"
        }
    ],
    "sg:phone":"+1 905 764 1608",
    "sg:postcode":"L3T 1P2",
    "sg:province":"ON",
    "sg:tags":[
        "marketing",
        "consultant"
    ],
    "wof:name":"Winick Repetski & Assoc Inc",
    "wof:placetype":"venue"
},
  "geometry": {"coordinates":[-79.41693100000001,43.806282],"type":"Point"}
}