{
  "type": "Feature",
  "properties": {
    "addr:full":"1421 Boul Du Saguenay E Chicoutimi QC G7H 1H2",
    "addr:housenumber":"1421",
    "addr:postcode":"g7h 1h2",
    "addr:street":"Boul Du Saguenay E",
    "iso:country":"CA",
    "sg:address":"1421 Boul Du Saguenay E",
    "sg:city":"Chicoutimi",
    "sg:classifiers":[
        {
            "category":"Retail",
            "subcategory":"Auto Repair",
            "type":"Services"
        }
    ],
    "sg:phone":"+1 418 549 2433",
    "sg:postcode":"G7H 1H2",
    "sg:province":"QC",
    "sg:tags":[
        "repairing",
        "automobile"
    ],
    "wof:name":"Denis Esso Svc",
    "wof:placetype":"venue"
},
  "geometry": {"coordinates":[-71.024597,48.427811],"type":"Point"}
}