{
  "type": "Feature",
  "properties": {
    "addr:full":"104 Mcphillips Ave Salt Spring Island BC V8K 2T5",
    "addr:housenumber":"104",
    "addr:postcode":"v8k 2t5",
    "addr:street":"Mcphillips Ave",
    "iso:country":"CA",
    "sg:address":"104 Mcphillips Ave",
    "sg:city":"Salt Spring Island",
    "sg:classifiers":[
        {
            "category":"Shopping",
            "subcategory":"Books",
            "type":"Retail Goods"
        }
    ],
    "sg:phone":"+1 250 537 2812",
    "sg:postcode":"V8K 2T5",
    "sg:province":"BC",
    "sg:tags":[
        "magazine"
    ],
    "wof:name":"Salt Spring Books",
    "wof:placetype":"venue"
},
  "geometry": {"coordinates":[-123.500229,48.852837],"type":"Point"}
}