{
  "type": "Feature",
  "properties": {
    "addr:full":"636 5E Rue Shawinigan QC G9N 1E9",
    "addr:housenumber":"636",
    "addr:postcode":"g9n 1e9",
    "addr:street":"5E Rue",
    "iso:country":"CA",
    "sg:address":"636 5E Rue",
    "sg:city":"Shawinigan",
    "sg:classifiers":[
        {
            "category":"Shopping",
            "subcategory":"Used Merchandise",
            "type":"Retail Goods"
        }
    ],
    "sg:phone":"+1 819 537 8651",
    "sg:postcode":"G9N 1E9",
    "sg:province":"QC",
    "sg:tags":[
        "pawnbroker"
    ],
    "wof:name":"Urgent Comptant Inc",
    "wof:placetype":"venue"
},
  "geometry": {"coordinates":[-72.750771,46.54055],"type":"Point"}
}