{
  "type": "Feature",
  "properties": {
    "iso:country":"CA",
    "sg:address":"136 Rue Saint-Louis",
    "sg:city":"Saint-Eustache",
    "sg:classifiers":[
        {
            "category":"Health Services",
            "subcategory":"Chiropractor",
            "type":"Services"
        }
    ],
    "sg:phone":"+1 450 623 8828",
    "sg:postcode":"J7R 1Y2",
    "sg:province":"QC",
    "wof:name":"Clinique Chiropratique",
    "wof:placetype":"venue"
},
  "geometry": {"coordinates":[-73.8893356323,45.5576705933],"type":"Point"}
}