{
  "type": "Feature",
  "properties": {
    "addr:full":"Richmond Hill ON L4B 1G8",
    "addr:postcode":"l4b 1g8",
    "iso:country":"CA",
    "sg:city":"Richmond Hill",
    "sg:classifiers":[
        {
            "category":"Wholesale",
            "subcategory":"Non-durable Goods",
            "type":"Manufacturing & Wholesale Goods"
        }
    ],
    "sg:phone":"+1 905 764 0111",
    "sg:postcode":"L4B 1G8",
    "sg:province":"ON",
    "wof:name":"Innovation",
    "wof:placetype":"venue"
},
  "geometry": {"coordinates":[-79.380501,43.858044],"type":"Point"}
}