{
  "type": "Feature",
  "properties": {
    "addr:full":"1667 Rue Saint-Calixte Plessisville QC G6L 1R1",
    "addr:housenumber":"1667",
    "addr:postcode":"g6l 1r1",
    "addr:street":"Rue Saint-Calixte",
    "iso:country":"CA",
    "sg:address":"1667 Rue Saint-Calixte",
    "sg:city":"Plessisville",
    "sg:classifiers":[
        {
            "category":"Personal",
            "subcategory":"Barber",
            "type":"Services"
        }
    ],
    "sg:phone":"+1 819 362 2041",
    "sg:postcode":"G6L 1R1",
    "sg:province":"QC",
    "wof:name":"Salon Royal Dubois",
    "wof:placetype":"venue"
},
  "geometry": {"coordinates":[-71.772926,46.218666],"type":"Point"}
}