{
  "type": "Feature",
  "properties": {
    "addr:full":"16 Spinnaker Way # 5 Concord ON L4K 2T8",
    "addr:housenumber":"16",
    "addr:postcode":"l4k 2t8",
    "addr:street":"Spinnaker Way # 5",
    "iso:country":"CA",
    "sg:address":"16 Spinnaker Way # 5",
    "sg:city":"Concord",
    "sg:classifiers":[
        {
            "category":"Wholesale",
            "subcategory":"Hardware",
            "type":"Manufacturing & Wholesale Goods"
        }
    ],
    "sg:phone":"+1 905 738 2295",
    "sg:postcode":"L4K 2T8",
    "sg:province":"ON",
    "sg:tags":[
        "equipment",
        "heating",
        "system"
    ],
    "wof:name":"R & T Sheet Metal",
    "wof:placetype":"venue"
},
  "geometry": {"coordinates":[-79.49133300779999,43.8217849731],"type":"Point"}
}