{
  "type": "Feature",
  "properties": {
    "addr:full":"2630 Upper Dwyer Hill Rd Almonte ON K0A 1A0",
    "addr:housenumber":"2630",
    "addr:postcode":"k0a 1a0",
    "addr:street":"Upper Dwyer Hill Rd",
    "iso:country":"CA",
    "sg:address":"2630 Upper Dwyer Hill Rd",
    "sg:city":"Almonte",
    "sg:classifiers":[
        {
            "category":"Retail",
            "subcategory":"Repair Shop",
            "type":"Services"
        }
    ],
    "sg:phone":"+1 613 256 7563",
    "sg:postcode":"K0A 1A0",
    "sg:province":"ON",
    "sg:tags":[
        "muffler",
        "exhaust",
        "system",
        "welding"
    ],
    "wof:name":"Panmure Products",
    "wof:placetype":"venue"
},
  "geometry": {"coordinates":[-76.1942062378,45.2287406921],"type":"Point"}
}