{
  "type": "Feature",
  "properties": {
    "addr:full":"Norman Wells NT X0E 0V0",
    "addr:postcode":"x0e 0v0",
    "iso:country":"CA",
    "sg:city":"Norman Wells",
    "sg:classifiers":[
        {
            "category":"Professional",
            "subcategory":"Accounting & Tax Preparation",
            "type":"Services"
        }
    ],
    "sg:phone":"+1 867 587 3069",
    "sg:postcode":"X0E 0V0",
    "sg:province":"NT",
    "sg:tags":[
        "accountant"
    ],
    "wof:name":"Tremblay, Lorraine",
    "wof:placetype":"venue"
},
  "geometry": {"coordinates":[-126.706687927,65.30633544920001],"type":"Point"}
}