{
  "type": "Feature",
  "properties": {
    "addr:full":"1514 Bay St North Vancouver BC V7J 1A1",
    "addr:housenumber":"1514",
    "addr:postcode":"v7j 1a1",
    "addr:street":"Bay St",
    "iso:country":"CA",
    "sg:address":"1514 Bay St",
    "sg:city":"North Vancouver",
    "sg:classifiers":[
        {
            "category":"Manufacturing",
            "subcategory":"Tools & Machinery",
            "type":"Manufacturing & Wholesale Goods"
        }
    ],
    "sg:phone":"+1 604 988 1130",
    "sg:postcode":"V7J 1A1",
    "sg:province":"BC",
    "sg:tags":[
        "machine",
        "shop"
    ],
    "wof:name":"Westec Equipment Intl Ltd",
    "wof:placetype":"venue"
},
  "geometry": {"coordinates":[-123.031631,49.301628],"type":"Point"}
}