{
  "type": "Feature",
  "properties": {
    "addr:full":"15 Dufferin St W Swift Current SK S9H 5A1",
    "addr:housenumber":"15",
    "addr:postcode":"s9h 5a1",
    "addr:street":"Dufferin St W",
    "iso:country":"CA",
    "sg:address":"15 Dufferin St W",
    "sg:city":"Swift Current",
    "sg:classifiers":[
        {
            "category":"Travel",
            "subcategory":"Travel Agent",
            "type":"Entertainment"
        }
    ],
    "sg:phone":"+1 306 773 8363",
    "sg:postcode":"S9H 5A1",
    "sg:province":"SK",
    "sg:tags":[
        "agency",
        "bureau"
    ],
    "wof:name":"Caa Saskatchewan",
    "wof:placetype":"venue"
},
  "geometry": {"coordinates":[-107.800621033,50.2914428711],"type":"Point"}
}