{
  "type": "Feature",
  "properties": {
    "iso:country":"CA",
    "sg:address":"36 Wright St",
    "sg:city":"St Catharines",
    "sg:classifiers":[
        {
            "category":"Restaurant",
            "type":"Food & Drink"
        }
    ],
    "sg:phone":"+1 905 684 9990",
    "sg:postcode":"L2P 3J4",
    "sg:province":"ON",
    "wof:name":"Puddy's Niagara Inc",
    "wof:placetype":"venue"
},
  "geometry": {"coordinates":[-79.217285,43.167587],"type":"Point"}
}