{
  "type": "Feature",
  "properties": {
    "iso:country":"CA",
    "sg:address":"1375 32E Av",
    "sg:city":"Lachine",
    "sg:classifiers":[
        {
            "category":"Wholesale",
            "subcategory":"Machinery & Supplies",
            "type":"Manufacturing & Wholesale Goods"
        }
    ],
    "sg:phone":"+1 514 636 3195",
    "sg:postcode":"H8T 3H2",
    "sg:province":"QC",
    "sg:tags":[
        "equipment",
        "printing"
    ],
    "wof:name":"Escher Grad Inc",
    "wof:placetype":"venue"
},
  "geometry": {"coordinates":[-73.70031738279999,45.4569816589],"type":"Point"}
}