{
  "type": "Feature",
  "properties": {
    "addr:full":"316 Knowlton Rd # 2 Knowlton QC J0E 1V0",
    "addr:housenumber":"316",
    "addr:postcode":"j0e 1v0",
    "addr:street":"Knowlton Rd # 2 Knowlton",
    "iso:country":"CA",
    "sg:address":"316 Knowlton Rd # 2",
    "sg:city":"Knowlton",
    "sg:classifiers":[
        {
            "category":"Real Estate",
            "subcategory":"Real Estate Agent",
            "type":"Services"
        }
    ],
    "sg:phone":"+1 450 242 1525",
    "sg:postcode":"J0E 1V0",
    "sg:province":"QC",
    "wof:name":"Immeubles Stuart",
    "wof:placetype":"venue"
},
  "geometry": {"coordinates":[-72.5132827759,45.216758728],"type":"Point"}
}