{
  "type": "Feature",
  "properties": {
    "addr:full":"Lumby BC V0E 2G6",
    "addr:postcode":"v0e 2g6",
    "iso:country":"CA",
    "sg:city":"Lumby",
    "sg:classifiers":[
        {
            "category":"Retail",
            "subcategory":"Auto Repair",
            "type":"Services"
        }
    ],
    "sg:phone":"+1 250 547 0008",
    "sg:postcode":"V0E 2G6",
    "sg:province":"BC",
    "sg:tags":[
        "wrecker"
    ],
    "wof:name":"Excel Towing",
    "wof:placetype":"venue"
},
  "geometry": {"coordinates":[-118.81146200000001,50.306858],"type":"Point"}
}