{
  "type": "Feature",
  "properties": {
    "addr:full":"Ottawa ON K1N 5W8",
    "addr:postcode":"k1n 5w8",
    "iso:country":"CA",
    "sg:city":"Ottawa",
    "sg:classifiers":[
        {
            "category":"Personal",
            "subcategory":"Beauty Salon",
            "type":"Services"
        }
    ],
    "sg:phone":"+1 613 241 7770",
    "sg:postcode":"K1N 5W8",
    "sg:province":"ON",
    "wof:name":"Holtz Spa",
    "wof:placetype":"venue"
},
  "geometry": {"coordinates":[-75.69199399999999,45.444214],"type":"Point"}
}