{
  "type": "Feature",
  "properties": {
    "addr:full":"380 Rue Principale E Farnham QC J2N 1L8",
    "addr:housenumber":"380",
    "addr:postcode":"j2n 1l8",
    "addr:street":"Rue Principale E",
    "iso:country":"CA",
    "sg:address":"380 Rue Principale E",
    "sg:city":"Farnham",
    "sg:classifiers":[
        {
            "category":"Personal",
            "subcategory":"Barber",
            "type":"Services"
        }
    ],
    "sg:phone":"+1 450 293 5415",
    "sg:postcode":"J2N 1L8",
    "sg:province":"QC",
    "wof:name":"Salon Guy Gendron",
    "wof:placetype":"venue"
},
  "geometry": {"coordinates":[-72.97560882569999,45.2833480835],"type":"Point"}
}