{
  "type": "Feature",
  "properties": {
    "iso:country":"CA",
    "sg:address":"272 Main St",
    "sg:city":"Iroquois Falls A",
    "sg:classifiers":[
        {
            "category":"Shopping",
            "subcategory":"Catalog Store",
            "type":"Retail Goods"
        }
    ],
    "sg:phone":"+1 705 232 4044",
    "sg:postcode":"P0K 1G0",
    "sg:province":"ON",
    "sg:tags":[
        "mail",
        "order",
        "internet"
    ],
    "wof:name":"Sears Canada Inc",
    "wof:placetype":"venue"
},
  "geometry": {"coordinates":[-80.6861114502,48.7582855225],"type":"Point"}
}