{
  "type": "Feature",
  "properties": {
    "addr:full":"74 Walnut St S Hamilton ON L8N 2L3",
    "addr:housenumber":"74",
    "addr:postcode":"l8n 2l3",
    "addr:street":"Walnut St S",
    "iso:country":"CA",
    "sg:address":"74 Walnut St S",
    "sg:city":"Hamilton",
    "sg:classifiers":[
        {
            "category":"Professional",
            "subcategory":"Accounting & Tax Preparation",
            "type":"Services"
        }
    ],
    "sg:phone":"+1 905 529 9119",
    "sg:postcode":"L8N 2L3",
    "sg:province":"ON",
    "sg:tags":[
        "accountant"
    ],
    "wof:name":"Klein, John M",
    "wof:placetype":"venue"
},
  "geometry": {"coordinates":[-79.864403,43.252548],"type":"Point"}
}