{
  "type": "Feature",
  "properties": {
    "addr:full":"1254 Plains Rd E Burlington ON L7S 1W6",
    "addr:housenumber":"1254",
    "addr:postcode":"l7s 1w6",
    "addr:street":"Plains Rd E",
    "iso:country":"CA",
    "sg:address":"1254 Plains Rd E",
    "sg:city":"Burlington",
    "sg:classifiers":[
        {
            "category":"Retail",
            "subcategory":"Auto Repair",
            "type":"Services"
        }
    ],
    "sg:phone":"+1 905 637 1921",
    "sg:postcode":"L7S 1W6",
    "sg:province":"ON",
    "sg:tags":[
        "body",
        "automobile",
        "painting"
    ],
    "wof:name":"Global Tech Collision",
    "wof:placetype":"venue"
},
  "geometry": {"coordinates":[-79.82172393800001,43.3327941895],"type":"Point"}
}