{
  "type": "Feature",
  "properties": {
    "addr:full":"16 Martin Ross Ave North York ON M3J 2K8",
    "addr:housenumber":"16",
    "addr:postcode":"m3j 2k8",
    "addr:street":"Martin Ross Ave",
    "iso:country":"CA",
    "sg:address":"16 Martin Ross Ave",
    "sg:city":"North York",
    "sg:classifiers":[
        {
            "category":"Home & Garden",
            "subcategory":"Furniture",
            "type":"Retail Goods"
        }
    ],
    "sg:phone":"+1 416 667 8383",
    "sg:postcode":"M3J 2K8",
    "sg:province":"ON",
    "sg:tags":[
        "equipment",
        "kitchen",
        "cabinet"
    ],
    "wof:name":"California Kitchen & Baths Ltd",
    "wof:placetype":"venue"
},
  "geometry": {"coordinates":[-79.469871521,43.7749824524],"type":"Point"}
}