{
  "type": "Feature",
  "properties": {
    "iso:country":"CA",
    "sg:address":"609 Regent Ave W",
    "sg:city":"Winnipeg",
    "sg:classifiers":[
        {
            "category":"Autos & Motor Vehicles",
            "subcategory":"Fuel & Gas Station",
            "type":"Retail Goods"
        }
    ],
    "sg:phone":"+1 204 222 9431",
    "sg:postcode":"R2C 1R9",
    "sg:province":"MB",
    "sg:tags":[
        "oil"
    ],
    "wof:name":"Shell Canada Products Ltd",
    "wof:placetype":"venue"
},
  "geometry": {"coordinates":[-97.020248,49.895309],"type":"Point"}
}