{
  "type": "Feature",
  "properties": {
    "addr:full":"510 Concession St Hamilton ON L9A 1C4",
    "addr:housenumber":"510",
    "addr:postcode":"l9a 1c4",
    "addr:street":"Concession St",
    "iso:country":"CA",
    "sg:address":"510 Concession St",
    "sg:city":"Hamilton",
    "sg:classifiers":[
        {
            "category":"Restaurant",
            "type":"Food & Drink"
        }
    ],
    "sg:phone":"+1 905 387 3211",
    "sg:postcode":"L9A 1C4",
    "sg:province":"ON",
    "sg:tags":[
        "caterer"
    ],
    "wof:name":"Hillcrest",
    "wof:placetype":"venue"
},
  "geometry": {"coordinates":[-79.854355,43.241444],"type":"Point"}
}