{
  "type": "Feature",
  "properties": {
    "addr:full":"565 2nd Ave Rivers MB R0K 1X0",
    "addr:housenumber":"565",
    "addr:postcode":"r0k 1x0",
    "addr:street":"2Nd Ave",
    "iso:country":"CA",
    "sg:address":"565 2nd Ave",
    "sg:city":"Rivers",
    "sg:classifiers":[
        {
            "category":"Home & Garden",
            "subcategory":"Building Materials",
            "type":"Retail Goods"
        }
    ],
    "sg:phone":"+1 204 328 7474",
    "sg:postcode":"R0K 1X0",
    "sg:province":"MB",
    "sg:tags":[
        "lumber"
    ],
    "wof:name":"North American Lumber Ltd",
    "wof:placetype":"venue"
},
  "geometry": {"coordinates":[-100.23764,50.029285],"type":"Point"}
}