{
  "type": "Feature",
  "properties": {
    "addr:full":"4811 52 St Red Deer AB T4N 2C6",
    "addr:housenumber":"4811",
    "addr:postcode":"t4n 2c6",
    "addr:street":"52 St",
    "iso:country":"CA",
    "sg:address":"4811 52 St",
    "sg:city":"Red Deer",
    "sg:classifiers":[
        {
            "category":"Organizations",
            "subcategory":"Community Association",
            "type":"Services"
        }
    ],
    "sg:phone":"+1 403 346 2544",
    "sg:postcode":"T4N 2C6",
    "sg:province":"AB",
    "sg:tags":[
        "sorority",
        "fraternity",
        "fraternal"
    ],
    "wof:name":"Red Deer Masonic Temple",
    "wof:placetype":"venue"
},
  "geometry": {"coordinates":[-113.809479,52.270767],"type":"Point"}
}