{
  "type": "Feature",
  "properties": {
    "iso:country":"CA",
    "sg:address":"31 Laing Blvd",
    "sg:city":"St Thomas",
    "sg:classifiers":[
        {
            "category":"Manufacturing",
            "subcategory":"Printing",
            "type":"Manufacturing & Wholesale Goods"
        }
    ],
    "sg:phone":"+1 519 633 1580",
    "sg:postcode":"N5P 3Z4",
    "sg:province":"ON",
    "sg:tags":[
        "printer"
    ],
    "wof:name":"Impressions Printing",
    "wof:placetype":"venue"
},
  "geometry": {"coordinates":[-81.153076,42.787708],"type":"Point"}
}