{
  "type": "Feature",
  "properties": {
    "iso:country":"CA",
    "sg:address":"3003 Boul Le Carrefour",
    "sg:city":"Laval",
    "sg:classifiers":[
        {
            "category":"Restaurant",
            "type":"Food & Drink"
        }
    ],
    "sg:phone":"+1 450 973 8582",
    "sg:postcode":"H7T 1C7",
    "sg:province":"QC",
    "wof:name":"Tiki Ming Inc",
    "wof:placetype":"venue"
},
  "geometry": {"coordinates":[-73.747925,45.569653],"type":"Point"}
}