{
  "type": "Feature",
  "properties": {
    "addr:full":"Saint-Albert QC J0A 1E0",
    "addr:postcode":"j0a 1e0",
    "iso:country":"CA",
    "sg:city":"Saint-Albert",
    "sg:classifiers":[
        {
            "category":"Autos & Motor Vehicles",
            "subcategory":"Automobile Sales",
            "type":"Retail Goods"
        }
    ],
    "sg:phone":"+1 819 353 1224",
    "sg:postcode":"J0A 1E0",
    "sg:province":"QC",
    "sg:tags":[
        "repairing",
        "car"
    ],
    "wof:name":"Auto St-Albert",
    "wof:placetype":"venue"
},
  "geometry": {"coordinates":[-72.111115,45.998955],"type":"Point"}
}