{
  "type": "Feature",
  "properties": {
    "addr:full":"1030 117 Rte Val-David QC J0T 2N0",
    "addr:housenumber":"1030",
    "addr:postcode":"j0t 2n0",
    "addr:street":"117 Rte Val-David",
    "iso:country":"CA",
    "sg:address":"1030 117 Rte",
    "sg:city":"Val-David",
    "sg:classifiers":[
        {
            "category":"Restaurant",
            "type":"Food & Drink"
        }
    ],
    "sg:phone":"+1 819 322 2246",
    "sg:postcode":"J0T 2N0",
    "sg:province":"QC",
    "wof:name":"Rotisserie Au Petit Poucet Inc",
    "wof:placetype":"venue"
},
  "geometry": {"coordinates":[-76.8017578125,45.8977661133],"type":"Point"}
}