{
  "type": "Feature",
  "properties": {
    "addr:full":"295 Western Ave Williams Lake BC V2G 2H6",
    "addr:housenumber":"295",
    "addr:postcode":"v2g 2h6",
    "addr:street":"Western Ave",
    "iso:country":"CA",
    "sg:address":"295 Western Ave",
    "sg:city":"Williams Lake",
    "sg:classifiers":[
        {
            "category":"Organizations",
            "subcategory":"Religious Organization",
            "type":"Services"
        }
    ],
    "sg:phone":"+1 250 392 4937",
    "sg:postcode":"V2G 2H6",
    "sg:province":"BC",
    "sg:tags":[
        "church"
    ],
    "wof:name":"First Baptist Church",
    "wof:placetype":"venue"
},
  "geometry": {"coordinates":[-122.136627,52.136879],"type":"Point"}
}