{
  "type": "Feature",
  "properties": {
    "addr:full":"5547 Rue Bossuet Montreal QC H1M 2M6",
    "addr:housenumber":"5547",
    "addr:postcode":"h1m 2m6",
    "addr:street":"Rue Bossuet",
    "iso:country":"CA",
    "sg:address":"5547 Rue Bossuet",
    "sg:city":"Montreal",
    "sg:classifiers":[
        {
            "category":"Retail",
            "subcategory":"Repair Shop",
            "type":"Services"
        }
    ],
    "sg:phone":"+1 514 995 3175",
    "sg:postcode":"H1M 2M6",
    "sg:province":"QC",
    "sg:tags":[
        "appliance"
    ],
    "wof:name":"Electromenagers Rob Belanger",
    "wof:placetype":"venue"
},
  "geometry": {"coordinates":[-73.55471038819999,45.5789794922],"type":"Point"}
}