{
  "type": "Feature",
  "properties": {
    "iso:country":"CA",
    "sg:address":"301 Main St",
    "sg:city":"Blaine Lake",
    "sg:classifiers":[
        {
            "category":"Professional",
            "subcategory":"Computer Services",
            "type":"Services"
        }
    ],
    "sg:phone":"+1 306 497 3100",
    "sg:postcode":"S0J 0J0",
    "sg:province":"SK",
    "sg:tags":[
        "internet"
    ],
    "wof:name":"Blaine Lake/Marcelin & Dist",
    "wof:placetype":"venue"
},
  "geometry": {"coordinates":[-106.87867,52.827629],"type":"Point"}
}