{
  "type": "Feature",
  "properties": {
    "addr:full":"45610 Luckakuck Way Chilliwack BC V2R 1A2",
    "addr:postcode":"45610;v2r 1a2",
    "addr:street":"Luckakuck Way",
    "iso:country":"CA",
    "sg:address":"45610 Luckakuck Way",
    "sg:city":"Chilliwack",
    "sg:classifiers":[
        {
            "category":"Shopping",
            "subcategory":"Pharmacy",
            "type":"Retail Goods"
        }
    ],
    "sg:phone":"+1 604 858 0437",
    "sg:postcode":"V2R 1A2",
    "sg:province":"BC",
    "sg:tags":[
        "grocer"
    ],
    "wof:name":"Safeway Pharmacy",
    "wof:placetype":"venue"
},
  "geometry": {"coordinates":[-121.961731,49.140621],"type":"Point"}
}