{
  "type": "Feature",
  "properties": {
    "addr:full":"100 Fundy Bay Blvd Scarborough ON M1W 3G1",
    "addr:housenumber":"100",
    "addr:postcode":"m1w 3g1",
    "addr:street":"Fundy Bay Blvd",
    "iso:country":"CA",
    "sg:address":"100 Fundy Bay Blvd",
    "sg:city":"Scarborough",
    "sg:classifiers":[
        {
            "category":"Education",
            "subcategory":"School",
            "type":"Public Place"
        }
    ],
    "sg:phone":"+1 416 393 5412",
    "sg:postcode":"M1W 3G1",
    "sg:province":"ON",
    "wof:name":"Saint Maximilian Kolbe Elem",
    "wof:placetype":"venue"
},
  "geometry": {"coordinates":[-79.31641399999999,43.809006],"type":"Point"}
}