{
  "type": "Feature",
  "properties": {
    "iso:country":"CA",
    "sg:address":"260 Rue Principale",
    "sg:city":"Pointe-Verte",
    "sg:classifiers":[
        {
            "category":"Building & Trades",
            "subcategory":"Electrical",
            "type":"Services"
        }
    ],
    "sg:phone":"+1 506 783 8624",
    "sg:postcode":"E8J 2W8",
    "sg:province":"NB",
    "sg:tags":[
        "electric",
        "contractor"
    ],
    "wof:name":"Daniel Electrique Ltee",
    "wof:placetype":"venue"
},
  "geometry": {"coordinates":[-65.772644043,47.8609466553],"type":"Point"}
}