{
  "type": "Feature",
  "properties": {
    "addr:full":"Vancouver BC V6Z 1G3",
    "addr:postcode":"v6z 1g3",
    "iso:country":"CA",
    "sg:city":"Vancouver",
    "sg:classifiers":[
        {
            "category":"Personal",
            "type":"Services"
        }
    ],
    "sg:phone":"+1 604 687 4078",
    "sg:postcode":"V6Z 1G3",
    "sg:province":"BC",
    "sg:tags":[
        "therapist",
        "massage"
    ],
    "wof:name":"Pacific Coast Massage Therapy",
    "wof:placetype":"venue"
},
  "geometry": {"coordinates":[-123.118606567,49.281955719],"type":"Point"}
}