{
  "type": "Feature",
  "properties": {
    "addr:full":"8051 Rue George Lasalle QC H8P 3S5",
    "addr:housenumber":"8051",
    "addr:postcode":"h8p 3s5",
    "addr:street":"Rue George",
    "iso:country":"CA",
    "sg:address":"8051 Rue George",
    "sg:city":"Lasalle",
    "sg:classifiers":[
        {
            "category":"Food & Beverages",
            "subcategory":"Groceries & Convenience Stores",
            "type":"Retail Goods"
        }
    ],
    "sg:phone":"+1 514 366 1457",
    "sg:postcode":"H8P 3S5",
    "sg:province":"QC",
    "wof:name":"Depan-Escompte Couche-Tard",
    "wof:placetype":"venue"
},
  "geometry": {"coordinates":[-73.6083526611,45.4255561829],"type":"Point"}
}