{
  "type": "Feature",
  "properties": {
    "addr:full":"84 Marquis Pl SE Airdrie AB T4A 1Z1",
    "addr:housenumber":"84",
    "addr:postcode":"t4a 1z1",
    "addr:street":"Marquis Pl Se",
    "iso:country":"CA",
    "sg:address":"84 Marquis Pl SE",
    "sg:city":"Airdrie",
    "sg:classifiers":[
        {
            "category":"Communications",
            "subcategory":"Film & Video Production",
            "type":"Services"
        }
    ],
    "sg:phone":"+1 403 948 6823",
    "sg:postcode":"T4A 1Z1",
    "sg:province":"AB",
    "sg:tags":[
        "animated"
    ],
    "wof:name":"Lost Pencil Animation Studios",
    "wof:placetype":"venue"
},
  "geometry": {"coordinates":[-113.985291,51.271278],"type":"Point"}
}