{
  "type": "Feature",
  "properties": {
    "addr:full":"895 Yonge St Toronto ON M4W 2H2",
    "addr:housenumber":"895",
    "addr:postcode":"m4w 2h2",
    "addr:street":"Yonge St",
    "iso:country":"CA",
    "sg:address":"895 Yonge St",
    "sg:city":"Toronto",
    "sg:classifiers":[
        {
            "category":"Health Services",
            "subcategory":"Doctor",
            "type":"Services"
        }
    ],
    "sg:phone":"+1 905 849 1835",
    "sg:postcode":"M4W 2H2",
    "sg:province":"ON",
    "sg:tags":[
        "clinic"
    ],
    "wof:name":"Ontario Vein Clinics",
    "wof:placetype":"venue"
},
  "geometry": {"coordinates":[-79.38835899999999,43.674549],"type":"Point"}
}