{
  "type": "Feature",
  "properties": {
    "addr:full":"25 Front Rd Port Au Port NL A0N 1T0",
    "addr:housenumber":"25",
    "addr:postcode":"a0n 1t0",
    "addr:street":"Front Rd;Au Port",
    "iso:country":"CA",
    "sg:address":"25 Front Rd",
    "sg:city":"Port Au Port",
    "sg:classifiers":[
        {
            "category":"Shopping",
            "subcategory":"Discount & Variety Stores",
            "type":"Retail Goods"
        }
    ],
    "sg:phone":"+1 709 648 2663",
    "sg:postcode":"A0N 1T0",
    "sg:province":"NL",
    "wof:name":"Wayne's Variety",
    "wof:placetype":"venue"
},
  "geometry": {"coordinates":[-58.710091,48.556732],"type":"Point"}
}