{
  "type": "Feature",
  "properties": {
    "addr:full":"906 8 St S Lethbridge AB T1J 2K8",
    "addr:housenumber":"906 8",
    "addr:postcode":"t1j 2k8",
    "addr:street":"St",
    "iso:country":"CA",
    "sg:address":"906 8 St S",
    "sg:city":"Lethbridge",
    "sg:classifiers":[
        {
            "category":"Building & Trades",
            "subcategory":"Construction",
            "type":"Services"
        }
    ],
    "sg:phone":"+1 403 320 9230",
    "sg:postcode":"T1J 2K8",
    "sg:province":"AB",
    "sg:tags":[
        "asbestos",
        "removal"
    ],
    "wof:name":"Fox Renovations",
    "wof:placetype":"venue"
},
  "geometry": {"coordinates":[-112.833984,49.685711],"type":"Point"}
}