{
  "type": "Feature",
  "properties": {
    "addr:full":"3409 20 St SW Calgary AB T2T 4Z6",
    "addr:housenumber":"3409",
    "addr:postcode":"t2t 4z6",
    "addr:street":"20 St Sw",
    "iso:country":"CA",
    "sg:address":"3409 20 St SW",
    "sg:city":"Calgary",
    "sg:classifiers":[
        {
            "category":"Personal",
            "subcategory":"Beauty Salon",
            "type":"Services"
        }
    ],
    "sg:phone":"+1 403 242 0104",
    "sg:postcode":"T2T 4Z6",
    "sg:province":"AB",
    "wof:name":"Elaments Salon & Day Spa",
    "wof:placetype":"venue"
},
  "geometry": {"coordinates":[-114.109550476,51.0238380432],"type":"Point"}
}