{
  "type": "Feature",
  "properties": {
    "addr:full":"118 Main Hwy Bay Roberts NL A0A 1G0",
    "addr:housenumber":"118",
    "addr:postcode":"a0a 1g0",
    "addr:street":"Main Hwy Bay",
    "iso:country":"CA",
    "sg:address":"118 Main Hwy",
    "sg:city":"Bay Roberts",
    "sg:classifiers":[
        {
            "category":"Home & Garden",
            "subcategory":"Carpets & Floor Coverings",
            "type":"Retail Goods"
        }
    ],
    "sg:phone":"+1 709 786 5678",
    "sg:postcode":"A0A 1G0",
    "sg:province":"NL",
    "sg:tags":[
        "dealer",
        "rug"
    ],
    "wof:name":"Flooring & More Inc",
    "wof:placetype":"venue"
},
  "geometry": {"coordinates":[-53.328342,47.573586],"type":"Point"}
}