{
  "type": "Feature",
  "properties": {
    "addr:full":"51 Forest Hills Pky Dartmouth NS B2W 6C6",
    "addr:housenumber":"51",
    "addr:postcode":"b2w 6c6",
    "addr:street":"Forest Hills Pky",
    "iso:country":"CA",
    "sg:address":"51 Forest Hills Pky",
    "sg:city":"Dartmouth",
    "sg:classifiers":[
        {
            "category":"Government",
            "subcategory":"Office",
            "type":"Public Place"
        }
    ],
    "sg:phone":"+1 902 435 7472",
    "sg:postcode":"B2W 6C6",
    "sg:province":"NS",
    "wof:name":"Nova Scotia Special Assitance",
    "wof:placetype":"venue"
},
  "geometry": {"coordinates":[-63.490868,44.682747],"type":"Point"}
}