{
  "type": "Feature",
  "properties": {
    "addr:full":"200 James A. Brennan Rd Gananoque ON K7G 1N7",
    "addr:housenumber":"200",
    "addr:postcode":"k7g 1n7",
    "addr:street":"James A. Brennan Rd",
    "iso:country":"CA",
    "sg:address":"200 James A. Brennan Rd",
    "sg:city":"Gananoque",
    "sg:classifiers":[
        {
            "category":"Retail",
            "subcategory":"Repair Shop",
            "type":"Services"
        }
    ],
    "sg:phone":"+1 613 382 4042",
    "sg:postcode":"K7G 1N7",
    "sg:province":"ON",
    "sg:tags":[
        "welding"
    ],
    "wof:name":"Tennant Welding",
    "wof:placetype":"venue"
},
  "geometry": {"coordinates":[-76.16918200000001,44.339375],"type":"Point"}
}