{
  "type": "Feature",
  "properties": {
    "iso:country":"CA",
    "sg:city":"West Brome",
    "sg:classifiers":[
        {
            "category":"Shopping",
            "subcategory":"Clothing, Apparel, & Fashions",
            "type":"Retail Goods"
        }
    ],
    "sg:phone":"+1 450 263 1331",
    "sg:postcode":"J0E 2P0",
    "sg:province":"QC",
    "sg:tags":[
        "riding",
        "equipment"
    ],
    "wof:name":"Station Equestre",
    "wof:placetype":"venue"
},
  "geometry": {"coordinates":[-72.6710968018,45.2011375427],"type":"Point"}
}