{
  "type": "Feature",
  "properties": {
    "addr:full":"5 Main St Sanford MB R0G 2J0",
    "addr:housenumber":"5",
    "addr:postcode":"r0g 2j0",
    "addr:street":"Main St",
    "iso:country":"CA",
    "sg:address":"5 Main St",
    "sg:city":"Sanford",
    "sg:classifiers":[
        {
            "category":"Social Services",
            "subcategory":"Child Care",
            "type":"Services"
        }
    ],
    "sg:phone":"+1 204 736 3289",
    "sg:postcode":"R0G 2J0",
    "sg:province":"MB",
    "wof:name":"J A Cuddy Child Care Ctr",
    "wof:placetype":"venue"
},
  "geometry": {"coordinates":[-97.4463729858,49.6804656982],"type":"Point"}
}