{
  "type": "Feature",
  "properties": {
    "iso:country":"CA",
    "sg:city":"Waterloo",
    "sg:classifiers":[
        {
            "category":"Professional",
            "subcategory":"Computer Services",
            "type":"Services"
        }
    ],
    "sg:phone":"+1 519 885 2708",
    "sg:postcode":"N2V 1W2",
    "sg:province":"ON",
    "sg:tags":[
        "consultant"
    ],
    "wof:name":"Computer Planning & Mgmt",
    "wof:placetype":"venue"
},
  "geometry": {"coordinates":[-80.5365982056,43.5103645325],"type":"Point"}
}