{
  "type": "Feature",
  "properties": {
    "addr:full":"Kingsgate BC V0B 1V0",
    "addr:postcode":"bc v0b 1v0",
    "addr:street":"Kingsgate",
    "iso:country":"CA",
    "sg:city":"Kingsgate",
    "sg:classifiers":[
        {
            "category":"Government",
            "subcategory":"Office",
            "type":"Public Place"
        }
    ],
    "sg:phone":"+1 250 424 5391",
    "sg:postcode":"V0B 1V0",
    "sg:province":"BC",
    "wof:name":"Canada Customs",
    "wof:placetype":"venue"
},
  "geometry": {"coordinates":[-116.187644959,49.0109558105],"type":"Point"}
}