{
  "type": "Feature",
  "properties": {
    "addr:full":"545 Sherbourne St Toronto ON M4X 1W5",
    "addr:housenumber":"545",
    "addr:postcode":"m4x 1w5",
    "addr:street":"Sherbourne St",
    "iso:country":"CA",
    "sg:address":"545 Sherbourne St",
    "sg:city":"Toronto",
    "sg:classifiers":[
        {
            "category":"Banks & Credit Unions",
            "subcategory":"Bank",
            "type":"Services"
        }
    ],
    "sg:phone":"+1 416 960 8488",
    "sg:postcode":"M4X 1W5",
    "sg:province":"ON",
    "wof:name":"Pnb Remittance CO",
    "wof:placetype":"venue"
},
  "geometry": {"coordinates":[-79.3753128052,43.6686897278],"type":"Point"}
}