{
  "type": "Feature",
  "properties": {
    "addr:full":"547 Crystal Falls Rd Crystal Falls ON P0H 1L0",
    "addr:housenumber":"547",
    "addr:postcode":"p0h 1l0",
    "addr:street":"Crystal Falls Rd",
    "iso:country":"CA",
    "sg:address":"547 Crystal Falls Rd",
    "sg:city":"Crystal Falls",
    "sg:classifiers":[
        {
            "category":"Social Services",
            "type":"Services"
        }
    ],
    "sg:phone":"+1 705 758 9592",
    "sg:postcode":"P0H 1L0",
    "sg:province":"ON",
    "sg:tags":[
        "senior",
        "citizen"
    ],
    "wof:name":"Club Des Bon Ami",
    "wof:placetype":"venue"
},
  "geometry": {"coordinates":[-79.90273999999999,46.462276],"type":"Point"}
}