{
  "type": "Feature",
  "properties": {
    "addr:full":"237 Silver Birch Ave Toronto ON M4E 3L6",
    "addr:housenumber":"237",
    "addr:postcode":"m4e 3l6",
    "addr:street":"Silver Birch Ave",
    "iso:country":"CA",
    "sg:address":"237 Silver Birch Ave",
    "sg:city":"Toronto",
    "sg:classifiers":[
        {
            "category":"Social Services",
            "type":"Services"
        }
    ],
    "sg:phone":"+1 416 693 8614",
    "sg:postcode":"M4E 3L6",
    "sg:province":"ON",
    "sg:tags":[
        "counselor",
        "marriage",
        "family"
    ],
    "wof:name":"Watson, Penny",
    "wof:placetype":"venue"
},
  "geometry": {"coordinates":[-79.286934,43.677822],"type":"Point"}
}