{
  "type": "Feature",
  "properties": {
    "addr:full":"Vancouver BC V6Z 2T1",
    "addr:postcode":"v6z 2t1",
    "iso:country":"CA",
    "sg:city":"Vancouver",
    "sg:classifiers":[
        {
            "category":"Professional",
            "subcategory":"Research",
            "type":"Services"
        }
    ],
    "sg:phone":"+1 604 685 3747",
    "sg:postcode":"V6Z 2T1",
    "sg:province":"BC",
    "sg:tags":[
        "development",
        "laboratory"
    ],
    "wof:name":"Viron Clinical Sciences Ltd",
    "wof:placetype":"venue"
},
  "geometry": {"coordinates":[-123.124961853,49.2789993286],"type":"Point"}
}