{
  "type": "Feature",
  "properties": {
    "addr:full":"24540 16 Ave Langley BC V2Z 1J9",
    "addr:housenumber":"24540",
    "addr:postcode":"v2z 1j9",
    "addr:street":"16 Ave",
    "iso:country":"CA",
    "sg:address":"24540 16 Ave",
    "sg:city":"Langley",
    "sg:classifiers":[
        {
            "category":"Home & Garden",
            "subcategory":"Building Materials",
            "type":"Retail Goods"
        }
    ],
    "sg:phone":"+1 604 530 4633",
    "sg:postcode":"V2Z 1J9",
    "sg:province":"BC",
    "sg:tags":[
        "lumber"
    ],
    "wof:name":"Dawson-Brill Lumber CO Ltd",
    "wof:placetype":"venue"
},
  "geometry": {"coordinates":[-122.54547100000001,49.030354],"type":"Point"}
}