{
  "type": "Feature",
  "properties": {
    "addr:full":"RR 8 Lcd 8 Calgary AB T2J 2T9",
    "addr:housenumber":"8",
    "addr:postcode":"t2j 2t9",
    "addr:street":"Rr 8 Lcd",
    "iso:country":"CA",
    "sg:address":"RR 8 Lcd 8",
    "sg:city":"Calgary",
    "sg:classifiers":[
        {
            "category":"Recreation",
            "type":"Entertainment"
        }
    ],
    "sg:phone":"+1 403 256 4113",
    "sg:postcode":"T2J 2T9",
    "sg:province":"AB",
    "sg:tags":[
        "hall",
        "auditorium"
    ],
    "wof:name":"Red Deer Lake Community Ctr",
    "wof:placetype":"venue"
},
  "geometry": {"coordinates":[-114.063194,51.045074],"type":"Point"}
}