{
  "type": "Feature",
  "properties": {
    "iso:country":"CA",
    "sg:address":"120 2nd Ave SW",
    "sg:city":"Falher",
    "sg:classifiers":[
        {
            "category":"Travel",
            "subcategory":"Hotels & Motels",
            "type":"Entertainment"
        }
    ],
    "sg:phone":"+1 780 837 2513",
    "sg:postcode":"T0H 1M0",
    "sg:province":"AB",
    "wof:name":"Gerry's Suites & Motel",
    "wof:placetype":"venue"
},
  "geometry": {"coordinates":[-117.205612183,55.7356300354],"type":"Point"}
}