{
  "type": "Feature",
  "properties": {
    "addr:full":"425 Rue Blainville E Sainte-Therese QC J7E 1N7",
    "addr:housenumber":"425",
    "addr:postcode":"j7e 1n7",
    "addr:street":"Rue Blainville E Sainte-Therese",
    "iso:country":"CA",
    "sg:address":"425 Rue Blainville E",
    "sg:city":"Sainte-Therese",
    "sg:classifiers":[
        {
            "category":"Education",
            "subcategory":"School",
            "type":"Public Place"
        }
    ],
    "sg:phone":"+1 450 434 1130",
    "sg:postcode":"J7E 1N7",
    "sg:province":"QC",
    "wof:name":"Academie Ste Therese",
    "wof:placetype":"venue"
},
  "geometry": {"coordinates":[-73.817055,45.641495],"type":"Point"}
}