{
  "type": "Feature",
  "properties": {
    "addr:full":"152 1Re Rue Shippagan NB E8S 1T1",
    "addr:housenumber":"152",
    "addr:postcode":"e8s 1t1",
    "addr:street":"1Re Rue Shippagan",
    "iso:country":"CA",
    "sg:address":"152 1Re Rue",
    "sg:city":"Shippagan",
    "sg:classifiers":[
        {
            "category":"Retail",
            "subcategory":"Laundry & Dry Cleaning",
            "type":"Services"
        }
    ],
    "sg:phone":"+1 506 336 0006",
    "sg:postcode":"E8S 1T1",
    "sg:province":"NB",
    "sg:tags":[
        "cleaners"
    ],
    "wof:name":"Nettoyeur Vert Ltee",
    "wof:placetype":"venue"
},
  "geometry": {"coordinates":[-64.721153,47.740356],"type":"Point"}
}