{
  "type": "Feature",
  "properties": {
    "addr:full":"Huntingdon QC J0S 1H0",
    "addr:postcode":"j0s 1h0",
    "iso:country":"CA",
    "sg:city":"Huntingdon",
    "sg:classifiers":[
        {
            "category":"Manufacturing",
            "subcategory":"Signs",
            "type":"Manufacturing & Wholesale Goods"
        }
    ],
    "sg:phone":"+1 450 264 6122",
    "sg:postcode":"J0S 1H0",
    "sg:province":"QC",
    "wof:name":"Folia Industries Inc",
    "wof:placetype":"venue"
},
  "geometry": {"coordinates":[-74.175438,45.090397],"type":"Point"}
}