{
  "type": "Feature",
  "properties": {
    "addr:full":"18 Ch Pembroke Chapeau QC J0X 1M0",
    "addr:housenumber":"18",
    "addr:postcode":"j0x 1m0",
    "addr:street":"Ch Pembroke",
    "iso:country":"CA",
    "sg:address":"18 Ch Pembroke",
    "sg:city":"Chapeau",
    "sg:classifiers":[
        {
            "category":"Building & Trades",
            "subcategory":"Construction",
            "type":"Services"
        }
    ],
    "sg:phone":"+1 819 689 2359",
    "sg:postcode":"J0X 1M0",
    "sg:province":"QC",
    "sg:tags":[
        "excavating",
        "contractor"
    ],
    "wof:name":"M Kidd & Sons Ltd",
    "wof:placetype":"venue"
},
  "geometry": {"coordinates":[-77.19360399999999,45.946419],"type":"Point"}
}