{
  "type": "Feature",
  "properties": {
    "addr:full":"390 King St Fredericton NB E3B 1E3",
    "addr:housenumber":"390",
    "addr:postcode":"e3b 1e3",
    "addr:street":"King St",
    "iso:country":"CA",
    "sg:address":"390 King St",
    "sg:city":"Fredericton",
    "sg:classifiers":[
        {
            "category":"Education",
            "subcategory":"School",
            "type":"Public Place"
        }
    ],
    "sg:phone":"+1 506 454 5437",
    "sg:postcode":"E3B 1E3",
    "sg:province":"NB",
    "sg:tags":[
        "academic",
        "special"
    ],
    "wof:name":"Advocacy For Youth",
    "wof:placetype":"venue"
},
  "geometry": {"coordinates":[-66.6449050903,45.9622764587],"type":"Point"}
}