{
  "type": "Feature",
  "properties": {
    "addr:full":"Burnaby BC V5C 5M8",
    "addr:postcode":"v5c 5m8",
    "iso:country":"CA",
    "sg:city":"Burnaby",
    "sg:classifiers":[
        {
            "category":"Freight",
            "type":"Transportation"
        }
    ],
    "sg:phone":"+1 604 294 4636",
    "sg:postcode":"V5C 5M8",
    "sg:province":"BC",
    "sg:tags":[
        "trucking"
    ],
    "wof:name":"Sokil Express Lines Ltd",
    "wof:placetype":"venue"
},
  "geometry": {"coordinates":[-122.99741400000001,49.263817],"type":"Point"}
}