{
  "type": "Feature",
  "properties": {
    "iso:country":"CA",
    "sg:address":"3648 Burnsland Rd SE",
    "sg:city":"Calgary",
    "sg:classifiers":[
        {
            "category":"Retail",
            "subcategory":"Auto Repair",
            "type":"Services"
        }
    ],
    "sg:phone":"+1 403 243 2886",
    "sg:postcode":"T2G 3Z2",
    "sg:province":"AB",
    "sg:tags":[
        "body",
        "automobile",
        "painting"
    ],
    "wof:name":"Sos Paint & Body Shop Ltd",
    "wof:placetype":"venue"
},
  "geometry": {"coordinates":[-114.058021545,51.0222587585],"type":"Point"}
}