{
  "type": "Feature",
  "properties": {
    "addr:full":"611 Niagara Blvd Fort Erie ON L2A 3H6",
    "addr:housenumber":"611",
    "addr:postcode":"l2a 3h6",
    "addr:street":"Niagara Blvd",
    "iso:country":"CA",
    "sg:address":"611 Niagara Blvd",
    "sg:city":"Fort Erie",
    "sg:classifiers":[
        {
            "category":"Bars & Pubs",
            "type":"Food & Drink"
        }
    ],
    "sg:phone":"+1 905 871 7800",
    "sg:postcode":"L2A 3H6",
    "sg:province":"ON",
    "sg:tags":[
        "club",
        "night"
    ],
    "wof:name":"Pure Platinum",
    "wof:placetype":"venue"
},
  "geometry": {"coordinates":[-78.91422300000001,42.929947],"type":"Point"}
}