{
  "type": "Feature",
  "properties": {
    "addr:full":"114 Queen St Woodstock NB E7M 2M9",
    "addr:housenumber":"114",
    "addr:postcode":"e7m 2m9",
    "addr:street":"Queen St",
    "iso:country":"CA",
    "sg:address":"114 Queen St",
    "sg:city":"Woodstock",
    "sg:classifiers":[
        {
            "category":"Shopping",
            "subcategory":"Clothing, Apparel, & Fashions",
            "type":"Retail Goods"
        }
    ],
    "sg:phone":"+1 506 328 6018",
    "sg:postcode":"E7M 2M9",
    "sg:province":"NB",
    "sg:tags":[
        "dressmaker",
        "tailor"
    ],
    "wof:name":"Hemlines & Alterations",
    "wof:placetype":"venue"
},
  "geometry": {"coordinates":[-67.57255600000001,46.14983],"type":"Point"}
}