{
  "type": "Feature",
  "properties": {
    "addr:full":"Sainte-Marie QC G6E 1B5",
    "addr:postcode":"g6e 1b5",
    "iso:country":"CA",
    "sg:city":"Sainte-Marie",
    "sg:classifiers":[
        {
            "category":"Mining & Drilling",
            "type":"Manufacturing & Wholesale Goods"
        }
    ],
    "sg:phone":"+1 418 681 3272",
    "sg:postcode":"G6E 1B5",
    "sg:province":"QC",
    "sg:tags":[
        "stone"
    ],
    "wof:name":"Epandage Cmd Inc",
    "wof:placetype":"venue"
},
  "geometry": {"coordinates":[-65.9838256836,48.1726264954],"type":"Point"}
}