{
  "type": "Feature",
  "properties": {
    "addr:full":"453 Dunlop St W Barrie ON L4N 1C3",
    "addr:housenumber":"453",
    "addr:postcode":"l4n 1c3",
    "addr:street":"Dunlop St W",
    "iso:country":"CA",
    "sg:address":"453 Dunlop St W",
    "sg:city":"Barrie",
    "sg:classifiers":[
        {
            "category":"Food & Beverages",
            "subcategory":"Groceries & Convenience Stores",
            "type":"Retail Goods"
        }
    ],
    "sg:phone":"+1 705 734 9263",
    "sg:postcode":"L4N 1C3",
    "sg:province":"ON",
    "wof:name":"Dunlop Convenience Store",
    "wof:placetype":"venue"
},
  "geometry": {"coordinates":[-79.7192764282,44.376247406],"type":"Point"}
}