{
  "type": "Feature",
  "properties": {
    "addr:full":"Guysborough NS B0H 1N0",
    "addr:postcode":"b0h 1n0",
    "iso:country":"CA",
    "sg:city":"Guysborough",
    "sg:classifiers":[
        {
            "category":"Organizations",
            "subcategory":"Membership Organization",
            "type":"Services"
        }
    ],
    "sg:phone":"+1 902 533 2101",
    "sg:postcode":"B0H 1N0",
    "sg:province":"NS",
    "wof:name":"Sunnyville Access Committee",
    "wof:placetype":"venue"
},
  "geometry": {"coordinates":[-61.5052375793,45.3843193054],"type":"Point"}
}