{
  "type": "Feature",
  "properties": {
    "iso:country":"CA",
    "sg:address":"10610 Timberland Rd",
    "sg:city":"Surrey",
    "sg:classifiers":[
        {
            "category":"Freight",
            "type":"Transportation"
        }
    ],
    "sg:phone":"+1 604 951 9133",
    "sg:postcode":"V3V 7Z1",
    "sg:province":"BC",
    "sg:tags":[
        "trucking"
    ],
    "wof:name":"Tms Transportation Mgmt Svc",
    "wof:placetype":"venue"
},
  "geometry": {"coordinates":[-122.900955,49.193436],"type":"Point"}
}