{
  "type": "Feature",
  "properties": {
    "iso:country":"CA",
    "sg:city":"Fort Mcmurray",
    "sg:classifiers":[
        {
            "category":"Health Services",
            "subcategory":"Optometrist",
            "type":"Services"
        }
    ],
    "sg:phone":"+1 780 791 5308",
    "sg:postcode":"T9H 1L2",
    "sg:province":"AB",
    "wof:name":"G C Shen & Assoc",
    "wof:placetype":"venue"
},
  "geometry": {"coordinates":[-111.380966187,56.7248878479],"type":"Point"}
}