{
  "type": "Feature",
  "properties": {
    "addr:full":"800 Champlain Rd Penetanguishene ON L9M 1R2",
    "addr:housenumber":"800",
    "addr:postcode":"l9m 1r2",
    "addr:street":"Champlain Rd",
    "iso:country":"CA",
    "sg:address":"800 Champlain Rd",
    "sg:city":"Penetanguishene",
    "sg:classifiers":[
        {
            "category":"Building & Trades",
            "subcategory":"Plumbing",
            "type":"Services"
        }
    ],
    "sg:phone":"+1 705 549 7181",
    "sg:postcode":"L9M 1R2",
    "sg:province":"ON",
    "sg:tags":[
        "disposal",
        "system",
        "sewage",
        "septic"
    ],
    "wof:name":"Georgian Bay Sanitation",
    "wof:placetype":"venue"
},
  "geometry": {"coordinates":[-79.945869,44.799641],"type":"Point"}
}