{
  "type": "Feature",
  "properties": {
    "addr:full":"168 John St Barrie ON L4N 2L2",
    "addr:housenumber":"168",
    "addr:postcode":"l4n 2l2",
    "addr:street":"John St",
    "iso:country":"CA",
    "sg:address":"168 John St",
    "sg:city":"Barrie",
    "sg:classifiers":[
        {
            "category":"Freight",
            "type":"Transportation"
        }
    ],
    "sg:phone":"+1 705 728 3335",
    "sg:postcode":"L4N 2L2",
    "sg:province":"ON",
    "sg:tags":[
        "delivery"
    ],
    "wof:name":"Canpar",
    "wof:placetype":"venue"
},
  "geometry": {"coordinates":[-79.7045288086,44.3763694763],"type":"Point"}
}