{
  "type": "Feature",
  "properties": {
    "iso:country":"CA",
    "sg:address":"1665 Rue King O",
    "sg:city":"Sherbrooke",
    "sg:classifiers":[
        {
            "category":"Restaurant",
            "type":"Food & Drink"
        }
    ],
    "sg:phone":"+1 819 564 1090",
    "sg:postcode":"J1J 2C8",
    "sg:province":"QC",
    "wof:name":"Mikes Restaurant",
    "wof:placetype":"venue"
},
  "geometry": {"coordinates":[-71.91613,45.398701],"type":"Point"}
}