{
  "type": "Feature",
  "properties": {
    "addr:full":"1705 Rue Lapierre Lasalle QC H8N 2M4",
    "addr:housenumber":"1705",
    "addr:postcode":"h8n 2m4",
    "addr:street":"Rue Lapierre",
    "iso:country":"CA",
    "sg:address":"1705 Rue Lapierre",
    "sg:city":"Lasalle",
    "sg:classifiers":[
        {
            "category":"Food & Beverages",
            "subcategory":"Groceries & Convenience Stores",
            "type":"Retail Goods"
        }
    ],
    "sg:phone":"+1 514 365 3316",
    "sg:postcode":"H8N 2M4",
    "sg:province":"QC",
    "wof:name":"Beau-Soir",
    "wof:placetype":"venue"
},
  "geometry": {"coordinates":[-73.61243399999999,45.436508],"type":"Point"}
}