{
  "type": "Feature",
  "properties": {
    "addr:full":"400 Dundas St E Mississauga ON L5A 1X5",
    "addr:housenumber":"400",
    "addr:postcode":"l5a 1x5",
    "addr:street":"Dundas St E",
    "iso:country":"CA",
    "sg:address":"400 Dundas St E",
    "sg:city":"Mississauga",
    "sg:classifiers":[
        {
            "category":"Shopping",
            "subcategory":"Computers & Home Electronics",
            "type":"Retail Goods"
        }
    ],
    "sg:phone":"+1 905 281 0204",
    "sg:postcode":"L5A 1X5",
    "sg:province":"ON",
    "sg:tags":[
        "equipment",
        "dealer"
    ],
    "wof:name":"Wintronic Computers Plus",
    "wof:placetype":"venue"
},
  "geometry": {"coordinates":[-79.606926,43.58836],"type":"Point"}
}