{
  "type": "Feature",
  "properties": {
    "addr:full":"22 Rue Saint-Paul E Montreal QC H2Y 1G3",
    "addr:housenumber":"22",
    "addr:postcode":"h2y 1g3",
    "addr:street":"Rue Saint-Paul E",
    "iso:country":"CA",
    "sg:address":"22 Rue Saint-Paul E",
    "sg:city":"Montreal",
    "sg:classifiers":[
        {
            "category":"Restaurant",
            "type":"Food & Drink"
        }
    ],
    "sg:phone":"+1 514 879 4678",
    "sg:postcode":"H2Y 1G3",
    "sg:province":"QC",
    "wof:name":"Restaurant Umberto",
    "wof:placetype":"venue"
},
  "geometry": {"coordinates":[-73.55345199999999,45.505924],"type":"Point"}
}