{
  "type": "Feature",
  "properties": {
    "iso:country":"CA",
    "sg:city":"Prince Albert",
    "sg:classifiers":[
        {
            "category":"Shopping",
            "subcategory":"Computers & Home Electronics",
            "type":"Retail Goods"
        }
    ],
    "sg:phone":"+1 306 763 3000",
    "sg:postcode":"S6V 7L7",
    "sg:province":"SK",
    "sg:tags":[
        "machine",
        "equipment",
        "duplicating",
        "copying",
        "dealer"
    ],
    "wof:name":"Prince Albert Photocopier Ltd",
    "wof:placetype":"venue"
},
  "geometry": {"coordinates":[-105.75327301,53.1804466248],"type":"Point"}
}