{
  "type": "Feature",
  "properties": {
    "iso:country":"CA",
    "sg:address":"2995 Albion Rd N",
    "sg:city":"Ottawa",
    "sg:classifiers":[
        {
            "category":"Real Estate",
            "subcategory":"Real Estate Operator",
            "type":"Services"
        }
    ],
    "sg:phone":"+1 613 731 8338",
    "sg:postcode":"K1V 8Z2",
    "sg:province":"ON",
    "sg:tags":[
        "apartment"
    ],
    "wof:name":"Oaks Apartments",
    "wof:placetype":"venue"
},
  "geometry": {"coordinates":[-75.652267,45.370529],"type":"Point"}
}