{
  "type": "Feature",
  "properties": {
    "addr:full":"2995 Albion Rd N Ottawa ON K1V 8Z2",
    "addr:housenumber":"2995",
    "addr:postcode":"k1v 8z2",
    "addr:street":"Albion Rd N",
    "iso:country":"CA",
    "sg:address":"2995 Albion Rd N",
    "sg:city":"Ottawa",
    "sg:classifiers":[
        {
            "category":"Real Estate",
            "subcategory":"Real Estate Operator",
            "type":"Services"
        }
    ],
    "sg:phone":"+1 613 731 8338",
    "sg:postcode":"K1V 8Z2",
    "sg:province":"ON",
    "sg:tags":[
        "apartment"
    ],
    "wof:name":"Oaks Apartments",
    "wof:placetype":"venue"
},
  "geometry": {"coordinates":[-75.65226699999999,45.370529],"type":"Point"}
}