{
  "type": "Feature",
  "properties": {
    "addr:full":"385 Enford Rd Richmond Hill ON L4C 3G2",
    "addr:housenumber":"385",
    "addr:postcode":"l4c 3g2",
    "addr:street":"Enford Rd",
    "iso:country":"CA",
    "sg:address":"385 Enford Rd",
    "sg:city":"Richmond Hill",
    "sg:classifiers":[
        {
            "category":"Wholesale",
            "subcategory":"Electrical",
            "type":"Manufacturing & Wholesale Goods"
        }
    ],
    "sg:phone":"+1 905 508 2199",
    "sg:postcode":"L4C 3G2",
    "sg:province":"ON",
    "sg:tags":[
        "equipment",
        "electric",
        "supply"
    ],
    "wof:name":"Boz Electric Supply Ltd",
    "wof:placetype":"venue"
},
  "geometry": {"coordinates":[-79.43796500000001,43.889572],"type":"Point"}
}