{
  "type": "Feature",
  "properties": {
    "addr:full":"5486 Spring Garden Rd Halifax NS B3J 1G4",
    "addr:housenumber":"5486",
    "addr:postcode":"ns b3j 1g4",
    "addr:street":"Spring Garden Rd",
    "iso:country":"CA",
    "sg:address":"5486 Spring Garden Rd",
    "sg:city":"Halifax",
    "sg:classifiers":[
        {
            "category":"Shopping",
            "subcategory":"Clothing, Apparel, & Fashions",
            "type":"Retail Goods"
        }
    ],
    "sg:phone":"+1 902 429 6111",
    "sg:postcode":"B3J 1G4",
    "sg:province":"NS",
    "wof:name":"Mills Brothers",
    "wof:placetype":"venue"
},
  "geometry": {"coordinates":[-63.576443,44.643021],"type":"Point"}
}