{
  "type": "Feature",
  "properties": {
    "addr:full":"2815 2 Ave S Lethbridge AB T1J 0G8",
    "addr:housenumber":"2815",
    "addr:postcode":"t1j 0g8",
    "addr:street":"2 Ave S",
    "iso:country":"CA",
    "sg:address":"2815 2 Ave S",
    "sg:city":"Lethbridge",
    "sg:classifiers":[
        {
            "category":"Wholesale",
            "subcategory":"Machinery & Supplies",
            "type":"Manufacturing & Wholesale Goods"
        }
    ],
    "sg:phone":"+1 403 327 1577",
    "sg:postcode":"T1J 0G8",
    "sg:province":"AB",
    "sg:tags":[
        "valve"
    ],
    "wof:name":"Crane Supply",
    "wof:placetype":"venue"
},
  "geometry": {"coordinates":[-112.80100299999999,49.697369],"type":"Point"}
}