{
  "type": "Feature",
  "properties": {
    "iso:country":"CA",
    "sg:address":"679 the Queensway",
    "sg:city":"Etobicoke",
    "sg:classifiers":[
        {
            "category":"Food & Beverages",
            "subcategory":"Groceries & Convenience Stores",
            "type":"Retail Goods"
        }
    ],
    "sg:phone":"+1 416 252 3222",
    "sg:postcode":"M8Y 1K8",
    "sg:province":"ON",
    "wof:name":"Queensway Convenience",
    "wof:placetype":"venue"
},
  "geometry": {"coordinates":[-79.499283,43.626953],"type":"Point"}
}