{
  "type": "Feature",
  "properties": {
    "addr:full":"Collingwood ON L9Y 3Z2",
    "addr:postcode":"l9y 3z2",
    "iso:country":"CA",
    "sg:city":"Collingwood",
    "sg:classifiers":[
        {
            "category":"Travel",
            "subcategory":"Hotels & Motels",
            "type":"Entertainment"
        }
    ],
    "sg:phone":"+1 705 446 0259",
    "sg:postcode":"L9Y 3Z2",
    "sg:province":"ON",
    "sg:tags":[
        "breakfast",
        "accommodation",
        "bed"
    ],
    "wof:name":"Aspen Lodge Bed & Breakfast",
    "wof:placetype":"venue"
},
  "geometry": {"coordinates":[-80.2168273926,44.4998893738],"type":"Point"}
}