{
  "type": "Feature",
  "properties": {
    "iso:country":"CA",
    "sg:city":"Saint-Hubert",
    "sg:classifiers":[
        {
            "category":"Freight",
            "type":"Transportation"
        }
    ],
    "sg:phone":"+1 450 443 1699",
    "sg:postcode":"J3Y 8Z8",
    "sg:province":"QC",
    "sg:tags":[
        "trucking"
    ],
    "wof:name":"Target Transport",
    "wof:placetype":"venue"
},
  "geometry": {"coordinates":[-73.42247,45.466698],"type":"Point"}
}