{
  "type": "Feature",
  "properties": {
    "addr:full":"PO Box 730 Manuels STN Main Conception Bay South NL A1W 1N3",
    "addr:housenumber":"po",
    "addr:postcode":"a1w 1n3",
    "addr:street":"Box 730 Manuels Stn Main",
    "iso:country":"CA",
    "sg:address":"PO Box 730 Manuels STN Main",
    "sg:city":"Conception Bay South",
    "sg:classifiers":[
        {
            "category":"Travel",
            "subcategory":"Hotels & Motels",
            "type":"Entertainment"
        }
    ],
    "sg:phone":"+1 709 521 2778",
    "sg:postcode":"A1W 1N3",
    "sg:province":"NL",
    "sg:tags":[
        "breakfast",
        "accommodation",
        "bed"
    ],
    "wof:name":"Salmonier Country Manor",
    "wof:placetype":"venue"
},
  "geometry": {"coordinates":[-52.968875885,47.5126190186],"type":"Point"}
}