{
  "type": "Feature",
  "properties": {
    "addr:full":"47 Lakeshore Rd E Mississauga ON L5G 1C9",
    "addr:housenumber":"47",
    "addr:postcode":"l5g 1c9",
    "addr:street":"Lakeshore Rd E",
    "iso:country":"CA",
    "sg:address":"47 Lakeshore Rd E",
    "sg:city":"Mississauga",
    "sg:classifiers":[
        {
            "category":"Personal",
            "subcategory":"Beauty Salon",
            "type":"Services"
        }
    ],
    "sg:phone":"+1 905 891 8088",
    "sg:postcode":"L5G 1C9",
    "sg:province":"ON",
    "wof:name":"Rose Beauty Ctr",
    "wof:placetype":"venue"
},
  "geometry": {"coordinates":[-79.58470916749999,43.5523262024],"type":"Point"}
}