{
  "type": "Feature",
  "properties": {
    "iso:country":"CA",
    "sg:address":"7 Beach St",
    "sg:city":"St Martins",
    "sg:classifiers":[
        {
            "category":"Restaurant",
            "type":"Food & Drink"
        }
    ],
    "sg:phone":"+1 506 833 1997",
    "sg:postcode":"E5R 1C6",
    "sg:province":"NB",
    "wof:name":"Coastal Tides Restaurant",
    "wof:placetype":"venue"
},
  "geometry": {"coordinates":[-65.5401687622,45.3533744812],"type":"Point"}
}