{
  "type": "Feature",
  "properties": {
    "addr:full":"166 Rue Saint-Jacques Saint-Jacques QC J0K 2R0",
    "addr:housenumber":"166",
    "addr:postcode":"j0k 2r0",
    "addr:street":"Rue Saint-Jacques",
    "iso:country":"CA",
    "sg:address":"166 Rue Saint-Jacques",
    "sg:city":"Saint-Jacques",
    "sg:classifiers":[
        {
            "category":"Professional",
            "subcategory":"Management & Consulting",
            "type":"Services"
        }
    ],
    "sg:phone":"+1 450 839 7897",
    "sg:postcode":"J0K 2R0",
    "sg:province":"QC",
    "sg:tags":[
        "agricultural",
        "consultant"
    ],
    "wof:name":"Club Sup-Parc Lanaudiere",
    "wof:placetype":"venue"
},
  "geometry": {"coordinates":[-73.5743255615,45.9508628845],"type":"Point"}
}