{
  "type": "Feature",
  "properties": {
    "addr:full":"Mine Centre ON P0W 1H0",
    "addr:postcode":"p0w 1h0",
    "iso:country":"CA",
    "sg:city":"Mine Centre",
    "sg:classifiers":[
        {
            "category":"Travel",
            "subcategory":"Hotels & Motels",
            "type":"Entertainment"
        }
    ],
    "sg:phone":"+1 807 599 2712",
    "sg:postcode":"P0W 1H0",
    "sg:province":"ON",
    "sg:tags":[
        "resort"
    ],
    "wof:name":"Hyatt's Manion Lake Camp",
    "wof:placetype":"venue"
},
  "geometry": {"coordinates":[-92.640602,48.760971],"type":"Point"}
}