{
  "type": "Feature",
  "properties": {
    "addr:full":"935 Ramsey Lake Rd Sudbury ON P3E 2C6",
    "addr:housenumber":"935",
    "addr:postcode":"p3e 2c6",
    "addr:street":"Ramsey Lake Rd",
    "iso:country":"CA",
    "sg:address":"935 Ramsey Lake Rd",
    "sg:city":"Sudbury",
    "sg:classifiers":[
        {
            "category":"Education",
            "subcategory":"College",
            "type":"Public Place"
        }
    ],
    "sg:phone":"+1 705 688 0200",
    "sg:postcode":"P3E 2C6",
    "sg:province":"ON",
    "sg:tags":[
        "academic",
        "school"
    ],
    "wof:name":"Northeastern Ontario Medical",
    "wof:placetype":"venue"
},
  "geometry": {"coordinates":[-80.972649,46.470764],"type":"Point"}
}