{
  "type": "Feature",
  "properties": {
    "addr:full":"124 Craig St Russell ON K4R 1A1",
    "addr:housenumber":"124",
    "addr:postcode":"k4r 1a1",
    "addr:street":"Craig St",
    "iso:country":"CA",
    "sg:address":"124 Craig St",
    "sg:city":"Russell",
    "sg:classifiers":[
        {
            "category":"Food & Beverages",
            "subcategory":"Groceries & Convenience Stores",
            "type":"Retail Goods"
        }
    ],
    "sg:phone":"+1 613 445 5308",
    "sg:postcode":"K4R 1A1",
    "sg:province":"ON",
    "sg:tags":[
        "grocer"
    ],
    "wof:name":"Foodland",
    "wof:placetype":"venue"
},
  "geometry": {"coordinates":[-75.37151299999999,45.256802],"type":"Point"}
}