{
  "type": "Feature",
  "properties": {
    "addr:full":"77 Rue Paul Sainte-Anne-DE-Sorel QC J3P 5N3",
    "addr:housenumber":"77",
    "addr:postcode":"j3p 5n3",
    "addr:street":"Rue Paul",
    "iso:country":"CA",
    "sg:address":"77 Rue Paul",
    "sg:city":"Sainte-Anne-DE-Sorel",
    "sg:classifiers":[
        {
            "category":"Home & Garden",
            "subcategory":"Household Appliances",
            "type":"Retail Goods"
        }
    ],
    "sg:phone":"+1 450 746 0887",
    "sg:postcode":"J3P 5N3",
    "sg:province":"QC",
    "wof:name":"Piche Marco Svc",
    "wof:placetype":"venue"
},
  "geometry": {"coordinates":[-73.077209,46.046417],"type":"Point"}
}