{
  "type": "Feature",
  "properties": {
    "iso:country":"CA",
    "sg:address":"4618 41 Ave",
    "sg:city":"Red Deer",
    "sg:classifiers":[
        {
            "category":"Organizations",
            "subcategory":"Religious Organization",
            "type":"Services"
        }
    ],
    "sg:phone":"+1 403 347 6267",
    "sg:postcode":"T4N 2Y4",
    "sg:province":"AB",
    "sg:tags":[
        "church"
    ],
    "wof:name":"Church of God Michener Hill",
    "wof:placetype":"venue"
},
  "geometry": {"coordinates":[-113.792473,52.265163],"type":"Point"}
}