{
  "type": "Feature",
  "properties": {
    "addr:full":"1920 Mcara St Regina SK S4N 5R1",
    "addr:housenumber":"1920",
    "addr:postcode":"s4n 5r1",
    "addr:street":"Mcara St",
    "iso:country":"CA",
    "sg:address":"1920 Mcara St",
    "sg:city":"Regina",
    "sg:classifiers":[
        {
            "category":"Professional",
            "subcategory":"Accounting & Tax Preparation",
            "type":"Services"
        }
    ],
    "sg:phone":"+1 306 331 7808",
    "sg:postcode":"S4N 5R1",
    "sg:province":"SK",
    "sg:tags":[
        "accountant"
    ],
    "wof:name":"Mc Naughton & CO",
    "wof:placetype":"venue"
},
  "geometry": {"coordinates":[-104.58240499999999,50.448322],"type":"Point"}
}