{
  "type": "Feature",
  "properties": {
    "iso:country":"CA",
    "sg:city":"Montreal",
    "sg:classifiers":[
        {
            "category":"Shopping",
            "subcategory":"Gifts & Souvenirs",
            "type":"Retail Goods"
        }
    ],
    "sg:phone":"+1 514 279 0680",
    "sg:postcode":"H2G 2H4",
    "sg:province":"QC",
    "sg:tags":[
        "cards",
        "material",
        "wrapping",
        "greeting"
    ],
    "wof:name":"Robinson Greeting Cards Inc",
    "wof:placetype":"venue"
},
  "geometry": {"coordinates":[-73.581505,45.542648],"type":"Point"}
}