{
  "type": "Feature",
  "properties": {
    "addr:full":"1700 Cowichan Bay Rd Cowichan Bay BC V0R 1N0",
    "addr:housenumber":"1700",
    "addr:postcode":"v0r 1n0",
    "addr:street":"Cowichan Bay Rd",
    "iso:country":"CA",
    "sg:address":"1700 Cowichan Bay Rd",
    "sg:city":"Cowichan Bay",
    "sg:classifiers":[
        {
            "category":"Recreation",
            "subcategory":"Marina",
            "type":"Entertainment"
        }
    ],
    "sg:phone":"+1 250 746 5911",
    "sg:postcode":"V0R 1N0",
    "sg:province":"BC",
    "sg:tags":[
        "government"
    ],
    "wof:name":"Cowichan Bay Fisherman's Wharf",
    "wof:placetype":"venue"
},
  "geometry": {"coordinates":[-123.618683,48.740074],"type":"Point"}
}