{
  "type": "Feature",
  "properties": {
    "addr:full":"1400 Rue DE Jaffa Laval QC H7P 4K9",
    "addr:housenumber":"1400",
    "addr:postcode":"h7p 4k9",
    "addr:street":"Rue De Jaffa",
    "iso:country":"CA",
    "sg:address":"1400 Rue DE Jaffa",
    "sg:city":"Laval",
    "sg:classifiers":[
        {
            "category":"Real Estate",
            "subcategory":"Real Estate Agent",
            "type":"Services"
        }
    ],
    "sg:phone":"+1 450 625 0202",
    "sg:postcode":"H7P 4K9",
    "sg:province":"QC",
    "sg:tags":[
        "agency",
        "rental",
        "scaffolding"
    ],
    "wof:name":"Hertz Equipment Rental",
    "wof:placetype":"venue"
},
  "geometry": {"coordinates":[-73.80614471440001,45.6000785828],"type":"Point"}
}