{
  "type": "Feature",
  "properties": {
    "addr:full":"172 Logy Bay Rd St. John's NL A1A 1J8",
    "addr:housenumber":"172",
    "addr:postcode":"a1a 1j8",
    "addr:street":"Logy Bay Rd",
    "iso:country":"CA",
    "sg:address":"172 Logy Bay Rd",
    "sg:city":"St. John's",
    "sg:classifiers":[
        {
            "category":"Food & Beverages",
            "subcategory":"Groceries & Convenience Stores",
            "type":"Retail Goods"
        }
    ],
    "sg:phone":"+1 709 738 3737",
    "sg:postcode":"A1A 1J8",
    "sg:province":"NL",
    "wof:name":"Breen's Superette",
    "wof:placetype":"venue"
},
  "geometry": {"coordinates":[-52.6795082092,47.6290397644],"type":"Point"}
}