{
  "type": "Feature",
  "properties": {
    "addr:full":"375 Exeter Rd London ON N6E 2Z3",
    "addr:housenumber":"375",
    "addr:postcode":"n6e 2z3",
    "addr:street":"Exeter Rd",
    "iso:country":"CA",
    "sg:address":"375 Exeter Rd",
    "sg:city":"London",
    "sg:classifiers":[
        {
            "category":"Wholesale",
            "subcategory":"Chemicals & Plastics",
            "type":"Manufacturing & Wholesale Goods"
        }
    ],
    "sg:phone":"+1 519 685 7700",
    "sg:postcode":"N6E 2Z3",
    "sg:province":"ON",
    "sg:tags":[
        "cleaning",
        "compound"
    ],
    "wof:name":"Quixtar Canada Corp",
    "wof:placetype":"venue"
},
  "geometry": {"coordinates":[-81.24402618409999,42.9234275818],"type":"Point"}
}