{
  "type": "Feature",
  "properties": {
    "addr:full":"675 Rue Hauterive Laval QC H7G 4L8",
    "addr:housenumber":"675",
    "addr:postcode":"qc h7g 4l8",
    "addr:street":"Rue Hauterive",
    "iso:country":"CA",
    "sg:address":"675 Rue Hauterive",
    "sg:city":"Laval",
    "sg:classifiers":[
        {
            "category":"Retail",
            "subcategory":"Auto Repair",
            "type":"Services"
        }
    ],
    "sg:phone":"+1 450 663 5729",
    "sg:postcode":"H7G 4L8",
    "sg:province":"QC",
    "sg:tags":[
        "body",
        "automobile",
        "painting"
    ],
    "wof:name":"Luja Auto Enr",
    "wof:placetype":"venue"
},
  "geometry": {"coordinates":[-73.674103,45.579247],"type":"Point"}
}