{
  "type": "Feature",
  "properties": {
    "addr:full":"1494 Rue Notre-Dame N Thetford Mines QC G6G 7G4",
    "addr:housenumber":"1494",
    "addr:postcode":"g6g 7g4",
    "addr:street":"Rue Notre-Dame N",
    "iso:country":"CA",
    "sg:address":"1494 Rue Notre-Dame N",
    "sg:city":"Thetford Mines",
    "sg:classifiers":[
        {
            "category":"Health Services",
            "subcategory":"Doctor",
            "type":"Services"
        }
    ],
    "sg:phone":"+1 418 338 4567",
    "sg:postcode":"G6G 7G4",
    "sg:province":"QC",
    "sg:tags":[
        "clinic"
    ],
    "wof:name":"Clinique Medicale DE Thetford",
    "wof:placetype":"venue"
},
  "geometry": {"coordinates":[-71.2788925171,46.1070594788],"type":"Point"}
}