{
  "type": "Feature",
  "properties": {
    "iso:country":"CA",
    "sg:address":"38 Adelaide St N",
    "sg:city":"London",
    "sg:classifiers":[
        {
            "category":"Freight",
            "type":"Transportation"
        }
    ],
    "sg:phone":"+1 519 963 0600",
    "sg:postcode":"N6B 3N5",
    "sg:province":"ON",
    "sg:tags":[
        "warehouse",
        "self",
        "storage"
    ],
    "wof:name":"Adelaide Warehousing & Storage",
    "wof:placetype":"venue"
},
  "geometry": {"coordinates":[-81.22640228269999,42.9773139954],"type":"Point"}
}