{
  "type": "Feature",
  "properties": {
    "iso:country":"CA",
    "sg:address":"152 Boul Wilfrid-Hamel",
    "sg:city":"Vanier",
    "sg:classifiers":[
        {
            "category":"Retail",
            "subcategory":"Auto Repair",
            "type":"Services"
        }
    ],
    "sg:phone":"+1 418 683 1313",
    "sg:postcode":"G1M 2R2",
    "sg:province":"QC",
    "sg:tags":[
        "repairing",
        "automobile"
    ],
    "wof:name":"Hamel Electrique Inc",
    "wof:placetype":"venue"
},
  "geometry": {"coordinates":[-71.25080871580001,46.8167686462],"type":"Point"}
}