{
  "type": "Feature",
  "properties": {
    "addr:full":"2675 Av Dalton Sainte-Foy QC G1P 3S8",
    "addr:housenumber":"2675",
    "addr:postcode":"g1p 3s8",
    "addr:street":"Av Dalton",
    "iso:country":"CA",
    "sg:address":"2675 Av Dalton",
    "sg:city":"Sainte-Foy",
    "sg:classifiers":[
        {
            "category":"Manufacturing",
            "subcategory":"Building Materials",
            "type":"Manufacturing & Wholesale Goods"
        }
    ],
    "sg:phone":"+1 418 650 2110",
    "sg:postcode":"G1P 3S8",
    "sg:province":"QC",
    "wof:name":"Fransyl Limitee",
    "wof:placetype":"venue"
},
  "geometry": {"coordinates":[-71.3066253662,46.7891921997],"type":"Point"}
}