{
  "type": "Feature",
  "properties": {
    "iso:country":"CA",
    "sg:city":"Vancouver",
    "sg:classifiers":[
        {
            "category":"Shopping",
            "subcategory":"Clothing, Apparel, & Fashions",
            "type":"Retail Goods"
        }
    ],
    "sg:phone":"+1 604 879 6789",
    "sg:postcode":"V5Z 3X7",
    "sg:province":"BC",
    "sg:tags":[
        "item",
        "boutique"
    ],
    "wof:name":"Lorita Enterprises",
    "wof:placetype":"venue"
},
  "geometry": {"coordinates":[-123.116402,49.260601],"type":"Point"}
}