{
  "type": "Feature",
  "properties": {
    "addr:full":"28 Centre St Marsden SK S0M 1P0",
    "addr:housenumber":"28",
    "addr:postcode":"s0m 1p0",
    "addr:street":"Centre St",
    "iso:country":"CA",
    "sg:address":"28 Centre St",
    "sg:city":"Marsden",
    "sg:classifiers":[
        {
            "category":"Personal",
            "subcategory":"Beauty Salon",
            "type":"Services"
        }
    ],
    "sg:phone":"+1 306 826 5515",
    "sg:postcode":"S0M 1P0",
    "sg:province":"SK",
    "wof:name":"Nadine's Hair Salon",
    "wof:placetype":"venue"
},
  "geometry": {"coordinates":[-109.820915,52.842075],"type":"Point"}
}