{
  "type": "Feature",
  "properties": {
    "addr:full":"64 Boul Brunswick Pointe-Claire QC H9B 2L3",
    "addr:housenumber":"64",
    "addr:postcode":"h9b 2l3",
    "addr:street":"Boul Brunswick",
    "iso:country":"CA",
    "sg:address":"64 Boul Brunswick",
    "sg:city":"Pointe-Claire",
    "sg:classifiers":[
        {
            "category":"Manufacturing",
            "subcategory":"Electronics",
            "type":"Manufacturing & Wholesale Goods"
        }
    ],
    "sg:phone":"+1 514 421 4445",
    "sg:postcode":"H9B 2L3",
    "sg:province":"QC",
    "sg:tags":[
        "equipment",
        "electronic",
        "supply"
    ],
    "wof:name":"A T & A Inc",
    "wof:placetype":"venue"
},
  "geometry": {"coordinates":[-73.7988815308,45.4818382263],"type":"Point"}
}