{
  "type": "Feature",
  "properties": {
    "addr:full":"404 College St Toronto ON M5T 1S8",
    "addr:housenumber":"404",
    "addr:postcode":"m5t 1s8",
    "addr:street":"College St",
    "iso:country":"CA",
    "sg:address":"404 College St",
    "sg:city":"Toronto",
    "sg:classifiers":[
        {
            "category":"Restaurant",
            "type":"Food & Drink"
        }
    ],
    "sg:phone":"+1 416 929 5691",
    "sg:postcode":"M5T 1S8",
    "sg:province":"ON",
    "wof:name":"Jing Peking Restaurant",
    "wof:placetype":"venue"
},
  "geometry": {"coordinates":[-79.4062042236,43.6569023132],"type":"Point"}
}