{
  "type": "Feature",
  "properties": {
    "iso:country":"CA",
    "sg:city":"Scarborough",
    "sg:classifiers":[
        {
            "category":"Food & Beverages",
            "subcategory":"Bakery",
            "type":"Retail Goods"
        }
    ],
    "sg:phone":"+1 416 292 3909",
    "sg:postcode":"M1V 3S1",
    "sg:province":"ON",
    "sg:tags":[
        "baker"
    ],
    "wof:name":"Allan's Pastry Shop",
    "wof:placetype":"venue"
},
  "geometry": {"coordinates":[-79.305214,43.819962],"type":"Point"}
}