{
  "type": "Feature",
  "properties": {
    "iso:country":"CA",
    "sg:address":"58 Rue Alexandre",
    "sg:city":"Salaberry-DE-Valleyfield",
    "sg:classifiers":[
        {
            "category":"Professional",
            "subcategory":"Business Services",
            "type":"Services"
        }
    ],
    "sg:phone":"+1 450 377 9083",
    "sg:postcode":"J6S 3J5",
    "sg:province":"QC",
    "sg:tags":[
        "interior",
        "consultant",
        "design",
        "decorator"
    ],
    "wof:name":"Vice Versa Design",
    "wof:placetype":"venue"
},
  "geometry": {"coordinates":[-74.13376617430001,45.2623748779],"type":"Point"}
}