{
  "type": "Feature",
  "properties": {
    "addr:full":"4720 Debruge Rd Elizabethtown ON K6T 1A5",
    "addr:housenumber":"4720",
    "addr:postcode":"k6t 1a5",
    "addr:street":"Debruge Rd",
    "iso:country":"CA",
    "sg:address":"4720 Debruge Rd",
    "sg:city":"Elizabethtown",
    "sg:classifiers":[
        {
            "category":"Home & Garden",
            "subcategory":"Hardware",
            "type":"Retail Goods"
        }
    ],
    "sg:phone":"+1 613 345 1921",
    "sg:postcode":"K6T 1A5",
    "sg:province":"ON",
    "sg:tags":[
        "saw"
    ],
    "wof:name":"John Benton Svc",
    "wof:placetype":"venue"
},
  "geometry": {"coordinates":[-75.728233,44.634377],"type":"Point"}
}