{
  "type": "Feature",
  "properties": {
    "iso:country":"CA",
    "sg:address":"130 Cree Cres",
    "sg:city":"Winnipeg",
    "sg:classifiers":[
        {
            "category":"Professional",
            "subcategory":"Engineering",
            "type":"Services"
        }
    ],
    "sg:phone":"+1 204 889 9202",
    "sg:postcode":"R3J 3W1",
    "sg:province":"MB",
    "sg:tags":[
        "engineer"
    ],
    "wof:name":"Dem Allen & Assoc Ltd",
    "wof:placetype":"venue"
},
  "geometry": {"coordinates":[-97.263779,49.893627],"type":"Point"}
}