{
  "type": "Feature",
  "properties": {
    "addr:full":"4665 139 Rte Saint-Nicephore QC J2A 4E5",
    "addr:housenumber":"4665",
    "addr:postcode":"j2a 4e5",
    "addr:street":"139 Rte Saint-Nicephore",
    "iso:country":"CA",
    "sg:address":"4665 139 Rte",
    "sg:city":"Saint-Nicephore",
    "sg:classifiers":[
        {
            "category":"Autos & Motor Vehicles",
            "subcategory":"Automobile Sales",
            "type":"Retail Goods"
        }
    ],
    "sg:phone":"+1 819 398 6881",
    "sg:postcode":"J2A 4E5",
    "sg:province":"QC",
    "sg:tags":[
        "repairing",
        "car"
    ],
    "wof:name":"Chabert Autos Inc",
    "wof:placetype":"venue"
},
  "geometry": {"coordinates":[-72.443932,45.808636],"type":"Point"}
}