{
  "type": "Feature",
  "properties": {
    "iso:country":"CA",
    "sg:city":"Ottawa",
    "sg:classifiers":[
        {
            "category":"Retail",
            "subcategory":"Laundry & Dry Cleaning",
            "type":"Services"
        }
    ],
    "sg:phone":"+1 613 746 2000",
    "sg:postcode":"K1K 3B8",
    "sg:province":"ON",
    "sg:tags":[
        "cleaners"
    ],
    "wof:name":"Pelican Cleaners & Tailoring",
    "wof:placetype":"venue"
},
  "geometry": {"coordinates":[-75.637352,45.423752],"type":"Point"}
}