{
  "type": "Feature",
  "properties": {
    "iso:country":"CA",
    "sg:city":"Saint-Jerome",
    "sg:classifiers":[
        {
            "category":"Restaurant",
            "type":"Food & Drink"
        }
    ],
    "sg:phone":"+1 450 560 9563",
    "sg:postcode":"J7Z 4M2",
    "sg:province":"QC",
    "wof:name":"Restaurant Valentine",
    "wof:placetype":"venue"
},
  "geometry": {"coordinates":[-73.9930343628,45.7626266479],"type":"Point"}
}