{
  "type": "Feature",
  "properties": {
    "addr:full":"590 Grande Allee E Quebec QC G1R 2K5",
    "addr:housenumber":"590",
    "addr:postcode":"g1r 2k5",
    "addr:street":"Grande Allee E",
    "iso:country":"CA",
    "sg:address":"590 Grande Allee E",
    "sg:city":"Quebec",
    "sg:classifiers":[
        {
            "category":"Restaurant",
            "type":"Food & Drink"
        }
    ],
    "sg:phone":"+1 418 529 2243",
    "sg:postcode":"G1R 2K5",
    "sg:province":"QC",
    "wof:name":"Restaurant Le Paris-Brest",
    "wof:placetype":"venue"
},
  "geometry": {"coordinates":[-71.21742999999999,46.806011],"type":"Point"}
}