{
  "type": "Feature",
  "properties": {
    "iso:country":"CA",
    "sg:address":"590 Grande Allee E",
    "sg:city":"Quebec",
    "sg:classifiers":[
        {
            "category":"Restaurant",
            "type":"Food & Drink"
        }
    ],
    "sg:phone":"+1 418 529 2243",
    "sg:postcode":"G1R 2K5",
    "sg:province":"QC",
    "wof:name":"Restaurant Le Paris-Brest",
    "wof:placetype":"venue"
},
  "geometry": {"coordinates":[-71.21743,46.806011],"type":"Point"}
}