{
  "type": "Feature",
  "properties": {
    "addr:full":"425 123E Rue Shawinigan-Sud QC G9P 3R1",
    "addr:housenumber":"425",
    "addr:postcode":"g9p 3r1",
    "addr:street":"123E Rue Shawinigan-Sud",
    "iso:country":"CA",
    "sg:address":"425 123E Rue",
    "sg:city":"Shawinigan-Sud",
    "sg:classifiers":[
        {
            "category":"Health Services",
            "subcategory":"Podiatrist",
            "type":"Services"
        }
    ],
    "sg:phone":"+1 819 536 7132",
    "sg:postcode":"G9P 3R1",
    "sg:province":"QC",
    "wof:name":"Lacombe, Marie DPM",
    "wof:placetype":"venue"
},
  "geometry": {"coordinates":[-72.7443695068,46.5194816589],"type":"Point"}
}