{
  "type": "Feature",
  "properties": {
    "addr:full":"Winnipeg MB R2G 1M3",
    "addr:postcode":"r2g 1m3",
    "iso:country":"CA",
    "sg:city":"Winnipeg",
    "sg:classifiers":[
        {
            "category":"Restaurant",
            "type":"Food & Drink"
        }
    ],
    "sg:phone":"+1 204 334 2333",
    "sg:postcode":"R2G 1M3",
    "sg:province":"MB",
    "wof:name":"Perkins Family Restaurant",
    "wof:placetype":"venue"
},
  "geometry": {"coordinates":[-97.0892410278,49.9415893555],"type":"Point"}
}