{
  "type": "Feature",
  "properties": {
    "addr:full":"Gillam MB R0B 0L0",
    "addr:postcode":"r0b 0l0",
    "iso:country":"CA",
    "sg:city":"Gillam",
    "sg:classifiers":[
        {
            "category":"Government",
            "subcategory":"Office",
            "type":"Public Place"
        }
    ],
    "sg:phone":"+1 204 456 2356",
    "sg:postcode":"R0B 0L0",
    "sg:province":"MB",
    "wof:name":"Manitoba Warehouse",
    "wof:placetype":"venue"
},
  "geometry": {"coordinates":[-94.70893100000001,56.349422],"type":"Point"}
}