{
  "type": "Feature",
  "properties": {
    "addr:full":"348 Harris St Ingersoll ON N5C 3J8",
    "addr:housenumber":"348",
    "addr:postcode":"n5c 3j8",
    "addr:street":"Harris St",
    "iso:country":"CA",
    "sg:address":"348 Harris St",
    "sg:city":"Ingersoll",
    "sg:classifiers":[
        {
            "category":"Autos & Motor Vehicles",
            "subcategory":"Automobile Sales",
            "type":"Retail Goods"
        }
    ],
    "sg:phone":"+1 519 485 3130",
    "sg:postcode":"N5C 3J8",
    "sg:province":"ON",
    "sg:tags":[
        "car",
        "dealer"
    ],
    "wof:name":"Rod Dench Motors Ltd",
    "wof:placetype":"venue"
},
  "geometry": {"coordinates":[-80.86879,43.038647],"type":"Point"}
}