{
  "type": "Feature",
  "properties": {
    "addr:full":"155 Main St Unionville ON L3R 2G8",
    "addr:housenumber":"155",
    "addr:postcode":"l3r 2g8",
    "addr:street":"Main St",
    "iso:country":"CA",
    "sg:address":"155 Main St",
    "sg:city":"Unionville",
    "sg:classifiers":[
        {
            "category":"Shopping",
            "type":"Retail Goods"
        }
    ],
    "sg:phone":"+1 905 944 0088",
    "sg:postcode":"L3R 2G8",
    "sg:province":"ON",
    "sg:tags":[
        "cosmetic",
        "perfume"
    ],
    "wof:name":"Professional Esthetics",
    "wof:placetype":"venue"
},
  "geometry": {"coordinates":[-79.31150100000001,43.866684],"type":"Point"}
}