{
  "type": "Feature",
  "properties": {
    "addr:full":"108 Conrad Cres Williams Lake BC V2G 3M4",
    "addr:housenumber":"108",
    "addr:postcode":"bc v2g 3m4",
    "addr:street":"Conrad Cres",
    "iso:country":"CA",
    "sg:address":"108 Conrad Cres",
    "sg:city":"Williams Lake",
    "sg:classifiers":[
        {
            "category":"Retail",
            "subcategory":"Repair Shop",
            "type":"Services"
        }
    ],
    "sg:phone":"+1 250 392 3131",
    "sg:postcode":"V2G 3M4",
    "sg:province":"BC",
    "sg:tags":[
        "upholsterer"
    ],
    "wof:name":"Cariboo Custom Upholstery",
    "wof:placetype":"venue"
},
  "geometry": {"coordinates":[-122.141082764,52.1286506653],"type":"Point"}
}