{
  "type": "Feature",
  "properties": {
    "addr:full":"Toronto ON M5S 2G8",
    "addr:postcode":"m5s 2g8",
    "iso:country":"CA",
    "sg:city":"Toronto",
    "sg:classifiers":[
        {
            "category":"Health Services",
            "subcategory":"Health Practitioner",
            "type":"Services"
        }
    ],
    "sg:phone":"+1 416 977 8949",
    "sg:postcode":"M5S 2G8",
    "sg:province":"ON",
    "sg:tags":[
        "psychologist"
    ],
    "wof:name":"Day, D A",
    "wof:placetype":"venue"
},
  "geometry": {"coordinates":[-79.399857,43.658096],"type":"Point"}
}