{
  "type": "Feature",
  "properties": {
    "addr:full":"128 Lakeshore Rd E Mississauga ON L5G 1E4",
    "addr:housenumber":"128",
    "addr:postcode":"l5g 1e4",
    "addr:street":"Lakeshore Rd E",
    "iso:country":"CA",
    "sg:address":"128 Lakeshore Rd E",
    "sg:city":"Mississauga",
    "sg:classifiers":[
        {
            "category":"Retail",
            "subcategory":"Funeral Services",
            "type":"Services"
        }
    ],
    "sg:phone":"+1 905 278 5546",
    "sg:postcode":"L5G 1E4",
    "sg:province":"ON",
    "sg:tags":[
        "director"
    ],
    "wof:name":"Skinner & Middlebrook Ltd",
    "wof:placetype":"venue"
},
  "geometry": {"coordinates":[-79.582581,43.554684],"type":"Point"}
}