{
  "type": "Feature",
  "properties": {
    "addr:full":"9397 Longwood Rd RR 1 Chatham ON N7M 5J1",
    "addr:housenumber":"9397",
    "addr:postcode":"n7m 5j1",
    "addr:street":"Longwood Rd;1",
    "iso:country":"CA",
    "sg:address":"9397 Longwood Rd RR 1",
    "sg:city":"Chatham",
    "sg:classifiers":[
        {
            "category":"Food & Beverages",
            "subcategory":"Groceries & Convenience Stores",
            "type":"Retail Goods"
        }
    ],
    "sg:phone":"+1 519 354 2236",
    "sg:postcode":"N7M 5J1",
    "sg:province":"ON",
    "wof:name":"Young's Variety",
    "wof:placetype":"venue"
},
  "geometry": {"coordinates":[-82.1895828247,42.4044456482],"type":"Point"}
}