{
  "type": "Feature",
  "properties": {
    "addr:full":"1910 Rue Du Centre Jonquiere QC G7S 2X3",
    "addr:housenumber":"1910",
    "addr:postcode":"g7s 2x3",
    "addr:street":"Rue Du Centre",
    "iso:country":"CA",
    "sg:address":"1910 Rue Du Centre",
    "sg:city":"Jonquiere",
    "sg:classifiers":[
        {
            "category":"Recreation",
            "type":"Entertainment"
        }
    ],
    "sg:phone":"+1 418 699 6070",
    "sg:postcode":"G7S 2X3",
    "sg:province":"QC",
    "sg:tags":[
        "center",
        "government"
    ],
    "wof:name":"Jonquiere Loisirs",
    "wof:placetype":"venue"
},
  "geometry": {"coordinates":[-71.185059,48.426811],"type":"Point"}
}