{
  "type": "Feature",
  "properties": {
    "addr:full":"256 King St N Waterloo ON N2J 2Y9",
    "addr:housenumber":"256",
    "addr:postcode":"n2j 2y9",
    "addr:street":"King St N",
    "iso:country":"CA",
    "sg:address":"256 King St N",
    "sg:city":"Waterloo",
    "sg:classifiers":[
        {
            "category":"Manufacturing",
            "subcategory":"Printing",
            "type":"Manufacturing & Wholesale Goods"
        }
    ],
    "sg:phone":"+1 519 746 5300",
    "sg:postcode":"N2J 2Y9",
    "sg:province":"ON",
    "sg:tags":[
        "printer"
    ],
    "wof:name":"Signature Printing",
    "wof:placetype":"venue"
},
  "geometry": {"coordinates":[-80.524902,43.4767],"type":"Point"}
}