{
  "type": "Feature",
  "properties": {
    "addr:full":"Nanaimo BC V9V 1S3",
    "addr:postcode":"v9v 1s3",
    "iso:country":"CA",
    "sg:city":"Nanaimo",
    "sg:classifiers":[
        {
            "category":"Banks & Credit Unions",
            "subcategory":"Bank",
            "type":"Services"
        }
    ],
    "sg:phone":"+1 250 390 5975",
    "sg:postcode":"V9V 1S3",
    "sg:province":"BC",
    "wof:name":"Scotiabank",
    "wof:placetype":"venue"
},
  "geometry": {"coordinates":[-124.04763,49.237976],"type":"Point"}
}