{
  "type": "Feature",
  "properties": {
    "addr:full":"68 West St Goderich ON N7A 2K3",
    "addr:housenumber":"68",
    "addr:postcode":"n7a 2k3",
    "addr:street":"West St",
    "iso:country":"CA",
    "sg:address":"68 West St",
    "sg:city":"Goderich",
    "sg:classifiers":[
        {
            "category":"Health Services",
            "subcategory":"Optometrist",
            "type":"Services"
        }
    ],
    "sg:phone":"+1 519 524 7251",
    "sg:postcode":"N7A 2K3",
    "sg:province":"ON",
    "wof:name":"Nisbett, D R OD",
    "wof:placetype":"venue"
},
  "geometry": {"coordinates":[-81.713928,43.743198],"type":"Point"}
}