{
  "type": "Feature",
  "properties": {
    "iso:country":"CA",
    "sg:address":"505 Ingersoll St",
    "sg:city":"Winnipeg",
    "sg:classifiers":[
        {
            "category":"Building & Trades",
            "subcategory":"Cleaning & Sanitation",
            "type":"Services"
        }
    ],
    "sg:phone":"+1 204 786 0095",
    "sg:postcode":"R3G 2J5",
    "sg:province":"MB",
    "sg:tags":[
        "janitor"
    ],
    "wof:name":"Terra Enterprises",
    "wof:placetype":"venue"
},
  "geometry": {"coordinates":[-97.174438,49.887062],"type":"Point"}
}