{
  "type": "Feature",
  "properties": {
    "iso:country":"CA",
    "sg:address":"363 Lakeshore Rd W",
    "sg:city":"Oakville",
    "sg:classifiers":[
        {
            "category":"Building & Trades",
            "subcategory":"Construction",
            "type":"Services"
        }
    ],
    "sg:phone":"+1 905 849 1926",
    "sg:postcode":"L6K 1G4",
    "sg:province":"ON",
    "sg:tags":[
        "roofing",
        "contractor",
        "general"
    ],
    "wof:name":"A Rightway Contracting & Mntnc",
    "wof:placetype":"venue"
},
  "geometry": {"coordinates":[-79.6831741333,43.4320716858],"type":"Point"}
}