{
  "type": "Feature",
  "properties": {
    "addr:full":"1700 Wilson Ave North York ON M3L 1B2",
    "addr:housenumber":"1700",
    "addr:postcode":"m3l 1b2",
    "addr:street":"Wilson Ave",
    "iso:country":"CA",
    "sg:address":"1700 Wilson Ave",
    "sg:city":"North York",
    "sg:classifiers":[
        {
            "category":"Shopping",
            "type":"Retail Goods"
        }
    ],
    "sg:phone":"+1 416 244 4000",
    "sg:postcode":"M3L 1B2",
    "sg:province":"ON",
    "sg:tags":[
        "telephone",
        "cellular"
    ],
    "wof:name":"Bell World Stores",
    "wof:placetype":"venue"
},
  "geometry": {"coordinates":[-79.513023,43.720051],"type":"Point"}
}