{
  "type": "Feature",
  "properties": {
    "iso:country":"CA",
    "sg:address":"965 Dugas St",
    "sg:city":"Winnipeg",
    "sg:classifiers":[
        {
            "category":"Building & Trades",
            "subcategory":"Electrical",
            "type":"Services"
        }
    ],
    "sg:phone":"+1 204 237 6910",
    "sg:postcode":"R2J 0Z9",
    "sg:province":"MB",
    "sg:tags":[
        "electric",
        "contractor"
    ],
    "wof:name":"R Paille Electric Inc",
    "wof:placetype":"venue"
},
  "geometry": {"coordinates":[-97.0767745972,49.8720474243],"type":"Point"}
}