{
  "type": "Feature",
  "properties": {
    "addr:full":"1507 Powell St Vancouver BC V5L 5C3",
    "addr:housenumber":"1507",
    "addr:postcode":"v5l 5c3",
    "addr:street":"Powell St",
    "iso:country":"CA",
    "sg:address":"1507 Powell St",
    "sg:city":"Vancouver",
    "sg:classifiers":[
        {
            "category":"Manufacturing",
            "subcategory":"Rubber & Plastics",
            "type":"Manufacturing & Wholesale Goods"
        }
    ],
    "sg:phone":"+1 604 251 3174",
    "sg:postcode":"V5L 5C3",
    "sg:province":"BC",
    "wof:name":"Peregrine Plastics",
    "wof:placetype":"venue"
},
  "geometry": {"coordinates":[-123.073791504,49.2834663391],"type":"Point"}
}