{
  "type": "Feature",
  "properties": {
    "addr:full":"1460 Av Dollard Lasalle QC H8N 1T4",
    "addr:housenumber":"1460",
    "addr:postcode":"h8n 1t4",
    "addr:street":"Av Dollard",
    "iso:country":"CA",
    "sg:address":"1460 Av Dollard",
    "sg:city":"Lasalle",
    "sg:classifiers":[
        {
            "category":"Restaurant",
            "type":"Food & Drink"
        }
    ],
    "sg:phone":"+1 514 364 7373",
    "sg:postcode":"H8N 1T4",
    "sg:province":"QC",
    "wof:name":"Restaurant LA Belle Lasalle",
    "wof:placetype":"venue"
},
  "geometry": {"coordinates":[-73.62748718260001,45.4268684387],"type":"Point"}
}