{
  "type": "Feature",
  "properties": {
    "iso:country":"CA",
    "sg:address":"213 Rue DE Tourville",
    "sg:city":"Canton-DE-Granby",
    "sg:classifiers":[
        {
            "category":"Wholesale",
            "subcategory":"Hardware",
            "type":"Manufacturing & Wholesale Goods"
        }
    ],
    "sg:phone":"+1 450 378 6707",
    "sg:postcode":"J2H 2A2",
    "sg:province":"QC",
    "sg:tags":[
        "ventilating",
        "equipment",
        "appliance"
    ],
    "wof:name":"Marcel Corbeil & Fils Inc",
    "wof:placetype":"venue"
},
  "geometry": {"coordinates":[-72.73992919920001,45.4249382019],"type":"Point"}
}