{
  "type": "Feature",
  "properties": {
    "addr:full":"78 Wharf Rd Clarks Harbour NS B0W 1P0",
    "addr:housenumber":"78",
    "addr:postcode":"b0w 1p0",
    "addr:street":"Wharf Rd",
    "iso:country":"CA",
    "sg:address":"78 Wharf Rd",
    "sg:city":"Clarks Harbour",
    "sg:classifiers":[
        {
            "category":"Food & Beverages",
            "subcategory":"Meat & Fish",
            "type":"Retail Goods"
        }
    ],
    "sg:phone":"+1 902 745 2354",
    "sg:postcode":"B0W 1P0",
    "sg:province":"NS",
    "sg:tags":[
        "seafood"
    ],
    "wof:name":"J & J Nickerson Fisheries Ltd",
    "wof:placetype":"venue"
},
  "geometry": {"coordinates":[-63.0893707275,44.7192192078],"type":"Point"}
}