{
  "type": "Feature",
  "properties": {
    "addr:full":"994 Rue Principale Montauban QC G0X 1W0",
    "addr:housenumber":"994",
    "addr:postcode":"g0x 1w0",
    "addr:street":"Rue Principale",
    "iso:country":"CA",
    "sg:address":"994 Rue Principale",
    "sg:city":"Montauban",
    "sg:classifiers":[
        {
            "category":"Freight",
            "type":"Transportation"
        }
    ],
    "sg:phone":"+1 418 336 2155",
    "sg:postcode":"G0X 1W0",
    "sg:province":"QC",
    "sg:tags":[
        "building",
        "house",
        "mover"
    ],
    "wof:name":"Deplacement DE Maison Rl Inc",
    "wof:placetype":"venue"
},
  "geometry": {"coordinates":[-72.309662,46.876411],"type":"Point"}
}