{
  "type": "Feature",
  "properties": {
    "addr:full":"104 Edmonton Trail SE Airdrie AB T4B 1S2",
    "addr:housenumber":"104",
    "addr:postcode":"t4b 1s2",
    "addr:street":"Edmonton Trail Se",
    "iso:country":"CA",
    "sg:address":"104 Edmonton Trail SE",
    "sg:city":"Airdrie",
    "sg:classifiers":[
        {
            "category":"Restaurant",
            "type":"Food & Drink"
        }
    ],
    "sg:phone":"+1 403 948 6000",
    "sg:postcode":"T4B 1S2",
    "sg:province":"AB",
    "wof:name":"Mc Donald's",
    "wof:placetype":"venue"
},
  "geometry": {"coordinates":[-114.00111389200001,51.2906265259],"type":"Point"}
}