{
  "type": "Feature",
  "properties": {
    "iso:country":"CA",
    "sg:address":"746 Boul Mercure",
    "sg:city":"Drummondville",
    "sg:classifiers":[
        {
            "category":"Recreation",
            "type":"Entertainment"
        }
    ],
    "sg:phone":"+1 819 478 0907",
    "sg:postcode":"J2B 3K4",
    "sg:province":"QC",
    "sg:tags":[
        "provincial",
        "parks",
        "government"
    ],
    "wof:name":"Drummondville Parc Nautique",
    "wof:placetype":"venue"
},
  "geometry": {"coordinates":[-72.4751815796,45.8742027283],"type":"Point"}
}