{
  "type": "Feature",
  "properties": {
    "addr:full":"4631 Highway 33 E Kelowna BC V1P 1H3",
    "addr:housenumber":"4631",
    "addr:postcode":"v1p 1h3",
    "addr:street":"Highway 33 E",
    "iso:country":"CA",
    "sg:address":"4631 Highway 33 E",
    "sg:city":"Kelowna",
    "sg:classifiers":[
        {
            "category":"Home & Garden",
            "subcategory":"Garden Supply",
            "type":"Retail Goods"
        }
    ],
    "sg:phone":"+1 250 491 3113",
    "sg:postcode":"V1P 1H3",
    "sg:province":"BC",
    "sg:tags":[
        "center"
    ],
    "wof:name":"Penny's Garden Ctr",
    "wof:placetype":"venue"
},
  "geometry": {"coordinates":[-119.49659729,49.8868141174],"type":"Point"}
}