{
  "type": "Feature",
  "properties": {
    "addr:full":"8 Queen St Port Hope ON L1A 2Y7",
    "addr:housenumber":"8",
    "addr:postcode":"l1a 2y7",
    "addr:street":"Queen St",
    "iso:country":"CA",
    "sg:address":"8 Queen St",
    "sg:city":"Port Hope",
    "sg:classifiers":[
        {
            "category":"Retail",
            "subcategory":"Photofinishing",
            "type":"Services"
        }
    ],
    "sg:phone":"+1 905 885 0889",
    "sg:postcode":"L1A 2Y7",
    "sg:province":"ON",
    "sg:tags":[
        "photo",
        "finishing"
    ],
    "wof:name":"Photo Plus Ltd",
    "wof:placetype":"venue"
},
  "geometry": {"coordinates":[-78.293221,43.950821],"type":"Point"}
}