{
  "type": "Feature",
  "properties": {
    "addr:full":"118 Disco St Sydney NS B1P 7G3",
    "addr:housenumber":"118",
    "addr:postcode":"b1p 7g3",
    "addr:street":"Disco St",
    "iso:country":"CA",
    "sg:address":"118 Disco St",
    "sg:city":"Sydney",
    "sg:classifiers":[
        {
            "category":"Retail",
            "subcategory":"Auto Rental",
            "type":"Services"
        }
    ],
    "sg:phone":"+1 902 562 1155",
    "sg:postcode":"B1P 7G3",
    "sg:province":"NS",
    "sg:tags":[
        "renting",
        "automobile"
    ],
    "wof:name":"Discount Car & Truck Rentals",
    "wof:placetype":"venue"
},
  "geometry": {"coordinates":[-60.177116,46.142441],"type":"Point"}
}