{
  "type": "Feature",
  "properties": {
    "iso:country":"CA",
    "sg:address":"745 Mount Pleasant Rd",
    "sg:city":"Toronto",
    "sg:classifiers":[
        {
            "category":"Restaurant",
            "type":"Food & Drink"
        }
    ],
    "sg:phone":"+1 416 489 6599",
    "sg:postcode":"M4S 2N4",
    "sg:province":"ON",
    "wof:name":"Steam City",
    "wof:placetype":"venue"
},
  "geometry": {"coordinates":[-79.38962554930001,43.7075157166],"type":"Point"}
}