{
  "type": "Feature",
  "properties": {
    "addr:full":"372 22E Rue Quebec QC G1L 1X7",
    "addr:housenumber":"372",
    "addr:postcode":"g1l 1x7",
    "addr:street":"22E Rue Quebec",
    "iso:country":"CA",
    "sg:address":"372 22E Rue",
    "sg:city":"Quebec",
    "sg:classifiers":[
        {
            "category":"Personal",
            "type":"Services"
        }
    ],
    "sg:phone":"+1 418 648 0555",
    "sg:postcode":"G1L 1X7",
    "sg:province":"QC",
    "sg:tags":[
        "electrolysis"
    ],
    "wof:name":"Clinique Vision Beaute Enr",
    "wof:placetype":"venue"
},
  "geometry": {"coordinates":[-71.23561100000001,46.834595],"type":"Point"}
}