{
  "type": "Feature",
  "properties": {
    "addr:full":"6001 Edwards Blvd Mississauga ON L5T 2W7",
    "addr:housenumber":"6001",
    "addr:postcode":"l5t 2w7",
    "addr:street":"Edwards Blvd",
    "iso:country":"CA",
    "sg:address":"6001 Edwards Blvd",
    "sg:city":"Mississauga",
    "sg:classifiers":[
        {
            "category":"Wholesale",
            "subcategory":"Stationery",
            "type":"Manufacturing & Wholesale Goods"
        }
    ],
    "sg:phone":"+1 905 564 0600",
    "sg:postcode":"L5T 2W7",
    "sg:province":"ON",
    "sg:tags":[
        "core",
        "tube",
        "paper",
        "form",
        "concrete"
    ],
    "wof:name":"Newark Paperboard Products",
    "wof:placetype":"venue"
},
  "geometry": {"coordinates":[-79.6778640747,43.6386985779],"type":"Point"}
}