{
  "type": "Feature",
  "properties": {
    "addr:full":"Summerside PE C1N 4J8",
    "addr:postcode":"c1n 4j8",
    "iso:country":"CA",
    "sg:city":"Summerside",
    "sg:classifiers":[
        {
            "category":"Manufacturing",
            "subcategory":"Tools & Machinery",
            "type":"Manufacturing & Wholesale Goods"
        }
    ],
    "sg:phone":"+1 902 436 9208",
    "sg:postcode":"C1N 4J8",
    "sg:province":"PE",
    "sg:tags":[
        "ventilating",
        "contractor"
    ],
    "wof:name":"Sherbrooke Mechanical Contrs",
    "wof:placetype":"venue"
},
  "geometry": {"coordinates":[-63.7919425964,46.3940849304],"type":"Point"}
}