{
  "type": "Feature",
  "properties": {
    "addr:full":"44 Dalroy Cres NW Calgary AB T3A 1G3",
    "addr:housenumber":"44",
    "addr:postcode":"t3a 1g3",
    "addr:street":"Dalroy Cres Nw",
    "iso:country":"CA",
    "sg:address":"44 Dalroy Cres NW",
    "sg:city":"Calgary",
    "sg:classifiers":[
        {
            "category":"Mining & Drilling",
            "type":"Manufacturing & Wholesale Goods"
        }
    ],
    "sg:phone":"+1 403 232 8170",
    "sg:postcode":"T3A 1G3",
    "sg:province":"AB",
    "sg:tags":[
        "company",
        "oil"
    ],
    "wof:name":"Cheryl Resources",
    "wof:placetype":"venue"
},
  "geometry": {"coordinates":[-114.144203,51.105011],"type":"Point"}
}