{
  "type": "Feature",
  "properties": {
    "addr:full":"Winnipeg MB R3K 2G7",
    "addr:postcode":"r3k 2g7",
    "iso:country":"CA",
    "sg:city":"Winnipeg",
    "sg:classifiers":[
        {
            "category":"Health Services",
            "subcategory":"Doctor",
            "type":"Services"
        }
    ],
    "sg:phone":"+1 204 896 5888",
    "sg:postcode":"R3K 2G7",
    "sg:province":"MB",
    "sg:tags":[
        "dentist"
    ],
    "wof:name":"Crestwood Dental Ctr",
    "wof:placetype":"venue"
},
  "geometry": {"coordinates":[-97.299088,49.882877],"type":"Point"}
}