{
  "type": "Feature",
  "properties": {
    "addr:full":"RR 2 Bothwell ON N0P 1C0",
    "addr:postcode":"n0p 1c0",
    "addr:street":"Rr 2",
    "iso:country":"CA",
    "sg:address":"RR 2",
    "sg:city":"Bothwell",
    "sg:classifiers":[
        {
            "category":"Wholesale",
            "subcategory":"Farm Supplies",
            "type":"Manufacturing & Wholesale Goods"
        }
    ],
    "sg:phone":"+1 519 695 3248",
    "sg:postcode":"N0P 1C0",
    "sg:province":"ON",
    "sg:tags":[
        "horse",
        "dealer"
    ],
    "wof:name":"Flying Dutchman Ranch",
    "wof:placetype":"venue"
},
  "geometry": {"coordinates":[-81.872192,42.631901],"type":"Point"}
}