{
  "type": "Feature",
  "properties": {
    "addr:full":"1399 Hammond St North Bay ON P1B 2J2",
    "addr:housenumber":"1399",
    "addr:postcode":"p1b 2j2",
    "addr:street":"Hammond St",
    "iso:country":"CA",
    "sg:address":"1399 Hammond St",
    "sg:city":"North Bay",
    "sg:classifiers":[
        {
            "category":"Wholesale",
            "subcategory":"Electrical",
            "type":"Manufacturing & Wholesale Goods"
        }
    ],
    "sg:phone":"+1 705 476 3084",
    "sg:postcode":"P1B 2J2",
    "sg:province":"ON",
    "sg:tags":[
        "alarm",
        "burglar",
        "system"
    ],
    "wof:name":"North Bay Security Comms Ltd",
    "wof:placetype":"venue"
},
  "geometry": {"coordinates":[-79.445457,46.311558],"type":"Point"}
}