{
  "type": "Feature",
  "properties": {
    "addr:full":"23 Boul Evain O Evain QC J0Z 1Y0",
    "addr:housenumber":"23",
    "addr:postcode":"j0z 1y0",
    "addr:street":"Boul Evain O Evain",
    "iso:country":"CA",
    "sg:address":"23 Boul Evain O",
    "sg:city":"Evain",
    "sg:classifiers":[
        {
            "category":"Food & Beverages",
            "subcategory":"Groceries & Convenience Stores",
            "type":"Retail Goods"
        }
    ],
    "sg:phone":"+1 819 768 3018",
    "sg:postcode":"J0Z 1Y0",
    "sg:province":"QC",
    "sg:tags":[
        "grocer"
    ],
    "wof:name":"Provigo",
    "wof:placetype":"venue"
},
  "geometry": {"coordinates":[-79.2306976318,48.322769165],"type":"Point"}
}