{
  "type": "Feature",
  "properties": {
    "addr:full":"54 132 Rte Lac-Au-Saumon QC G0J 1M0",
    "addr:housenumber":"132",
    "addr:postcode":"g0j 1m0",
    "addr:street":"54;Rte Lac-Au-Saumon",
    "iso:country":"CA",
    "sg:address":"54 132 Rte",
    "sg:city":"Lac-Au-Saumon",
    "sg:classifiers":[
        {
            "category":"Travel",
            "subcategory":"Hotels & Motels",
            "type":"Entertainment"
        }
    ],
    "sg:phone":"+1 418 778 5815",
    "sg:postcode":"G0J 1M0",
    "sg:province":"QC",
    "wof:name":"Motel Des Cedres",
    "wof:placetype":"venue"
},
  "geometry": {"coordinates":[-67.3433837891,48.4227561951],"type":"Point"}
}