{
  "type": "Feature",
  "properties": {
    "addr:full":"174 Bridge St Kingston NS B0P 1R0",
    "addr:housenumber":"174",
    "addr:postcode":"b0p 1r0",
    "addr:street":"Bridge St",
    "iso:country":"CA",
    "sg:address":"174 Bridge St",
    "sg:city":"Kingston",
    "sg:classifiers":[
        {
            "category":"Organizations",
            "subcategory":"Religious Organization",
            "type":"Services"
        }
    ],
    "sg:phone":"+1 902 765 6361",
    "sg:postcode":"B0P 1R0",
    "sg:province":"NS",
    "sg:tags":[
        "church"
    ],
    "wof:name":"Fellowship Baptist Church",
    "wof:placetype":"venue"
},
  "geometry": {"coordinates":[-64.9488601685,44.985408783],"type":"Point"}
}