{
  "type": "Feature",
  "properties": {
    "iso:country":"CA",
    "sg:address":"2020 Ch Oka",
    "sg:city":"Oka",
    "sg:classifiers":[
        {
            "category":"Government",
            "subcategory":"Office",
            "type":"Public Place"
        }
    ],
    "sg:phone":"+1 450 479 8365",
    "sg:postcode":"J0N 1E0",
    "sg:province":"QC",
    "wof:name":"Quebec Loisir Chasse & Peche",
    "wof:placetype":"venue"
},
  "geometry": {"coordinates":[-74.0611114502,45.4757766724],"type":"Point"}
}