{
  "type": "Feature",
  "properties": {
    "addr:full":"3384 Ch D'Oka Saint-Joseph-Du-Lac QC J0N 1M0",
    "addr:postcode":"3384;j0n 1m0",
    "addr:street":"Ch D'Oka",
    "iso:country":"CA",
    "sg:address":"3384 Ch D'Oka",
    "sg:city":"Saint-Joseph-Du-Lac",
    "sg:classifiers":[
        {
            "category":"Retail",
            "subcategory":"Auto Repair",
            "type":"Services"
        }
    ],
    "sg:phone":"+1 450 974 1767",
    "sg:postcode":"J0N 1M0",
    "sg:province":"QC",
    "sg:tags":[
        "repairing",
        "automobile"
    ],
    "wof:name":"Garage Guy Charbonneau Enr",
    "wof:placetype":"venue"
},
  "geometry": {"coordinates":[-73.99696400000001,45.501682],"type":"Point"}
}