{
  "type": "Feature",
  "properties": {
    "iso:country":"CA",
    "sg:address":"2587 Rue Roussel",
    "sg:city":"Chicoutimi",
    "sg:classifiers":[
        {
            "category":"Government",
            "subcategory":"Fire Station",
            "type":"Public Place"
        }
    ],
    "sg:phone":"+1 ",
    "sg:postcode":"G7G 1X9",
    "sg:province":"QC",
    "sg:tags":[
        "department"
    ],
    "wof:name":"Chicoutimi Pompier Adm",
    "wof:placetype":"venue"
},
  "geometry": {"coordinates":[-71.0783462524,48.4395141602],"type":"Point"}
}