{
  "type": "Feature",
  "properties": {
    "iso:country":"CA",
    "sg:city":"Delta",
    "sg:classifiers":[
        {
            "category":"Wholesale",
            "subcategory":"Durable Goods & Equipment",
            "type":"Manufacturing & Wholesale Goods"
        }
    ],
    "sg:phone":"+1 604 946 9613",
    "sg:postcode":"V4G 1E2",
    "sg:province":"BC",
    "sg:tags":[
        "laser"
    ],
    "wof:name":"Nam Laser Inc",
    "wof:placetype":"venue"
},
  "geometry": {"coordinates":[-123.018951,49.132328],"type":"Point"}
}