{
  "type": "Feature",
  "properties": {
    "addr:full":"5244 Boul Saint-Laurent Montreal QC H2T 1S1",
    "addr:housenumber":"5244",
    "addr:postcode":"h2t 1s1",
    "addr:street":"Boul Saint-Laurent",
    "iso:country":"CA",
    "sg:address":"5244 Boul Saint-Laurent",
    "sg:city":"Montreal",
    "sg:classifiers":[
        {
            "category":"Wholesale",
            "subcategory":"Electrical",
            "type":"Manufacturing & Wholesale Goods"
        }
    ],
    "sg:phone":"+1 514 272 0880",
    "sg:postcode":"H2T 1S1",
    "sg:province":"QC",
    "sg:tags":[
        "elements",
        "electric",
        "heating"
    ],
    "wof:name":"Distributeurs Mapco Inc",
    "wof:placetype":"venue"
},
  "geometry": {"coordinates":[-73.5954360962,45.5240783691],"type":"Point"}
}