{
  "type": "Feature",
  "properties": {
    "iso:country":"CA",
    "sg:address":"18 Brunelle Rd S",
    "sg:city":"Kapuskasing",
    "sg:classifiers":[
        {
            "category":"Home & Garden",
            "subcategory":"Building Materials",
            "type":"Retail Goods"
        }
    ],
    "sg:phone":"+1 705 337 5757",
    "sg:postcode":"P5N 2T2",
    "sg:province":"ON",
    "sg:tags":[
        "plate",
        "window",
        "maker",
        "cabinet"
    ],
    "wof:name":"Gerald Cabinet & Glass Shop",
    "wof:placetype":"venue"
},
  "geometry": {"coordinates":[-82.4031448364,49.4072685242],"type":"Point"}
}