{
  "type": "Feature",
  "properties": {
    "addr:full":"18 Orde St Toronto ON M5T 1N7",
    "addr:housenumber":"18",
    "addr:postcode":"m5t 1n7",
    "addr:street":"Orde St",
    "iso:country":"CA",
    "sg:address":"18 Orde St",
    "sg:city":"Toronto",
    "sg:classifiers":[
        {
            "category":"Education",
            "subcategory":"School",
            "type":"Public Place"
        }
    ],
    "sg:phone":"+1 416 393 1900",
    "sg:postcode":"M5T 1N7",
    "sg:province":"ON",
    "wof:name":"Orde Street Junior Public Schl",
    "wof:placetype":"venue"
},
  "geometry": {"coordinates":[-79.3916473389,43.6584396362],"type":"Point"}
}