{
  "type": "Feature",
  "properties": {
    "iso:country":"CA",
    "sg:city":"Edmonton",
    "sg:classifiers":[
        {
            "category":"Professional",
            "subcategory":"Management & Consulting",
            "type":"Services"
        }
    ],
    "sg:phone":"+1 780 413 9262",
    "sg:postcode":"T6E 1X2",
    "sg:province":"AB",
    "sg:tags":[
        "consultant",
        "business"
    ],
    "wof:name":"Toma & Bouma Management",
    "wof:placetype":"venue"
},
  "geometry": {"coordinates":[-113.495658874,53.5172119141],"type":"Point"}
}