{
  "type": "Feature",
  "properties": {
    "addr:full":"12560 Trans Canada Hwy Ladysmith BC V9G 1M6",
    "addr:housenumber":"12560",
    "addr:postcode":"v9g 1m6",
    "addr:street":"Trans Canada Hwy",
    "iso:country":"CA",
    "sg:address":"12560 Trans Canada Hwy",
    "sg:city":"Ladysmith",
    "sg:classifiers":[
        {
            "category":"Wholesale",
            "subcategory":"Plants",
            "type":"Manufacturing & Wholesale Goods"
        }
    ],
    "sg:phone":"+1 250 245 4545",
    "sg:postcode":"V9G 1M6",
    "sg:province":"BC",
    "sg:tags":[
        "florist"
    ],
    "wof:name":"Ladysmith Evergreens Ltd",
    "wof:placetype":"venue"
},
  "geometry": {"coordinates":[-123.80508399999999,48.98127],"type":"Point"}
}