{
  "type": "Feature",
  "properties": {
    "addr:full":"656 Ch Deblois Ascot Corner QC J0B 1A0",
    "addr:housenumber":"656",
    "addr:postcode":"j0b 1a0",
    "addr:street":"Ch Deblois",
    "iso:country":"CA",
    "sg:address":"656 Ch Deblois",
    "sg:city":"Ascot Corner",
    "sg:classifiers":[
        {
            "category":"Manufacturing",
            "subcategory":"Lumber",
            "type":"Manufacturing & Wholesale Goods"
        }
    ],
    "sg:phone":"+1 819 562 4247",
    "sg:postcode":"J0B 1A0",
    "sg:province":"QC",
    "sg:tags":[
        "wood"
    ],
    "wof:name":"Tournage Js",
    "wof:placetype":"venue"
},
  "geometry": {"coordinates":[-71.762199,45.469051],"type":"Point"}
}