{
  "type": "Feature",
  "properties": {
    "iso:country":"CA",
    "sg:city":"Brossard",
    "sg:classifiers":[
        {
            "category":"Insurance",
            "subcategory":"Insurance Agent",
            "type":"Services"
        }
    ],
    "sg:phone":"+1 450 445 0879",
    "sg:postcode":"J4Z 3P2",
    "sg:province":"QC",
    "wof:name":"Jobin, Guy",
    "wof:placetype":"venue"
},
  "geometry": {"coordinates":[-73.4639968872,45.4679946899],"type":"Point"}
}