{
  "type": "Feature",
  "properties": {
    "addr:full":"212 King St Port Colborne ON L3K 4G7",
    "addr:housenumber":"212",
    "addr:postcode":"l3k 4g7",
    "addr:street":"King St",
    "iso:country":"CA",
    "sg:address":"212 King St",
    "sg:city":"Port Colborne",
    "sg:classifiers":[
        {
            "category":"Museum",
            "subcategory":"Botanical Garden",
            "type":"Entertainment"
        }
    ],
    "sg:phone":"+1 905 834 6667",
    "sg:postcode":"L3K 4G7",
    "sg:province":"ON",
    "sg:tags":[
        "zoo"
    ],
    "wof:name":"Dragon Farms Inc",
    "wof:placetype":"venue"
},
  "geometry": {"coordinates":[-79.251442,42.885319],"type":"Point"}
}