{
  "type": "Feature",
  "properties": {
    "addr:full":"1425 Tecumseh Rd E Windsor ON N8W 1C2",
    "addr:housenumber":"1425",
    "addr:postcode":"n8w 1c2",
    "addr:street":"Tecumseh Rd E",
    "iso:country":"CA",
    "sg:address":"1425 Tecumseh Rd E",
    "sg:city":"Windsor",
    "sg:classifiers":[
        {
            "category":"Education",
            "subcategory":"Library",
            "type":"Public Place"
        }
    ],
    "sg:phone":"+1 519 253 3600",
    "sg:postcode":"N8W 1C2",
    "sg:province":"ON",
    "wof:name":"South Walkerville Library",
    "wof:placetype":"venue"
},
  "geometry": {"coordinates":[-83.004341,42.300282],"type":"Point"}
}