{
  "type": "Feature",
  "properties": {
    "iso:country":"CA",
    "sg:address":"290 Armstrong St N",
    "sg:city":"New Liskeard",
    "sg:classifiers":[
        {
            "category":"Professional",
            "subcategory":"Employment Agencies",
            "type":"Services"
        }
    ],
    "sg:phone":"+1 705 647 4544",
    "sg:postcode":"P0J 1P0",
    "sg:province":"ON",
    "sg:tags":[
        "opportunity"
    ],
    "wof:name":"Job Connect",
    "wof:placetype":"venue"
},
  "geometry": {"coordinates":[-79.671836853,47.5153198242],"type":"Point"}
}