{
  "type": "Feature",
  "properties": {
    "iso:country":"CA",
    "sg:address":"74 Cedar Pointe Dr",
    "sg:city":"Barrie",
    "sg:classifiers":[
        {
            "category":"Personal",
            "type":"Services"
        }
    ],
    "sg:phone":"+1 705 735 4211",
    "sg:postcode":"L4N 5R7",
    "sg:province":"ON",
    "sg:tags":[
        "control",
        "weight"
    ],
    "wof:name":"Bernstein, S K",
    "wof:placetype":"venue"
},
  "geometry": {"coordinates":[-79.712044,44.382992],"type":"Point"}
}