{
  "type": "Feature",
  "properties": {
    "addr:full":"Duncan BC V9L 4X2",
    "addr:postcode":"v9l 4x2",
    "iso:country":"CA",
    "sg:city":"Duncan",
    "sg:classifiers":[
        {
            "category":"Building & Trades",
            "subcategory":"Construction",
            "type":"Services"
        }
    ],
    "sg:phone":"+1 250 715 1215",
    "sg:postcode":"V9L 4X2",
    "sg:province":"BC",
    "sg:tags":[
        "tile",
        "dealer"
    ],
    "wof:name":"Castle Tile & Marble",
    "wof:placetype":"venue"
},
  "geometry": {"coordinates":[-123.69882200000001,48.780491],"type":"Point"}
}