{
  "type": "Feature",
  "properties": {
    "addr:full":"1663 Av Laurier E Montreal QC H2J 1J3",
    "addr:housenumber":"1663",
    "addr:postcode":"h2j 1j3",
    "addr:street":"Av Laurier E",
    "iso:country":"CA",
    "sg:address":"1663 Av Laurier E",
    "sg:city":"Montreal",
    "sg:classifiers":[
        {
            "category":"Organizations",
            "subcategory":"Professional Association",
            "type":"Services"
        }
    ],
    "sg:phone":"+1 514 527 9060",
    "sg:postcode":"H2J 1J3",
    "sg:province":"QC",
    "wof:name":"Federatin Des Anciens",
    "wof:placetype":"venue"
},
  "geometry": {"coordinates":[-73.582069,45.535511],"type":"Point"}
}