{
  "type": "Feature",
  "properties": {
    "addr:full":"75 Spring St Summerside PE C1N 3E5",
    "addr:housenumber":"75",
    "addr:postcode":"c1n 3e5",
    "addr:street":"Spring St",
    "iso:country":"CA",
    "sg:address":"75 Spring St",
    "sg:city":"Summerside",
    "sg:classifiers":[
        {
            "category":"Museum",
            "type":"Entertainment"
        }
    ],
    "sg:phone":"+1 902 432 1327",
    "sg:postcode":"C1N 3E5",
    "sg:province":"PE",
    "wof:name":"Wyatt Heritage Properties",
    "wof:placetype":"venue"
},
  "geometry": {"coordinates":[-63.7892112732,46.3936004639],"type":"Point"}
}