{
  "type": "Feature",
  "properties": {
    "addr:full":"925 Main St W Hamilton ON L8S 4P3",
    "addr:housenumber":"925",
    "addr:postcode":"l8s 4p3",
    "addr:street":"Main St W",
    "iso:country":"CA",
    "sg:address":"925 Main St W",
    "sg:city":"Hamilton",
    "sg:classifiers":[
        {
            "category":"Autos & Motor Vehicles",
            "subcategory":"Automobile Sales",
            "type":"Retail Goods"
        }
    ],
    "sg:phone":"+1 905 528 7335",
    "sg:postcode":"L8S 4P3",
    "sg:province":"ON",
    "sg:tags":[
        "car",
        "dealer"
    ],
    "wof:name":"Acura of Hamilton",
    "wof:placetype":"venue"
},
  "geometry": {"coordinates":[-79.902672,43.258942],"type":"Point"}
}