{
  "type": "Feature",
  "properties": {
    "addr:full":"504 Rue Du Sud Cowansville QC J2K 2X8",
    "addr:housenumber":"504",
    "addr:postcode":"j2k 2x8",
    "addr:street":"Rue Du Sud",
    "iso:country":"CA",
    "sg:address":"504 Rue Du Sud",
    "sg:city":"Cowansville",
    "sg:classifiers":[
        {
            "category":"Social Services",
            "type":"Services"
        }
    ],
    "sg:phone":"+1 450 260 1823",
    "sg:postcode":"J2K 2X8",
    "sg:province":"QC",
    "sg:tags":[
        "youth",
        "organization",
        "center"
    ],
    "wof:name":"Cellule Jeunesse",
    "wof:placetype":"venue"
},
  "geometry": {"coordinates":[-72.74709300000001,45.20372],"type":"Point"}
}