{
  "type": "Feature",
  "properties": {
    "addr:full":"Spencerville ON K0E 1X0",
    "addr:postcode":"k0e 1x0",
    "iso:country":"CA",
    "sg:city":"Spencerville",
    "sg:classifiers":[
        {
            "category":"Wholesale",
            "subcategory":"Machinery & Supplies",
            "type":"Manufacturing & Wholesale Goods"
        }
    ],
    "sg:phone":"+1 613 658 3159",
    "sg:postcode":"K0E 1X0",
    "sg:province":"ON",
    "sg:tags":[
        "farm",
        "equipment"
    ],
    "wof:name":"Roebuck Enterprises",
    "wof:placetype":"venue"
},
  "geometry": {"coordinates":[-75.5466842651,44.8430595398],"type":"Point"}
}