{
  "type": "Feature",
  "properties": {
    "addr:full":"5211 Airport Rd Fort Nelson BC V0C 1R0",
    "addr:housenumber":"5211",
    "addr:postcode":"bc v0c 1r0",
    "addr:street":"Airport Rd",
    "iso:country":"CA",
    "sg:address":"5211 Airport Rd",
    "sg:city":"Fort Nelson",
    "sg:classifiers":[
        {
            "category":"Retail",
            "subcategory":"Self-service Laundry",
            "type":"Services"
        }
    ],
    "sg:phone":"+1 250 774 7786",
    "sg:postcode":"V0C 1R0",
    "sg:province":"BC",
    "wof:name":"Sukhi's Coin-Op Laundromat",
    "wof:placetype":"venue"
},
  "geometry": {"coordinates":[-122.696243286,58.8075904846],"type":"Point"}
}