{
  "type": "Feature",
  "properties": {
    "addr:full":"2150 Rue Bombardier Sainte-Julie QC J3E 2J9",
    "addr:housenumber":"2150",
    "addr:postcode":"j3e 2j9",
    "addr:street":"Rue Bombardier",
    "iso:country":"CA",
    "sg:address":"2150 Rue Bombardier",
    "sg:city":"Sainte-Julie",
    "sg:classifiers":[
        {
            "category":"Wholesale",
            "subcategory":"Groceries",
            "type":"Manufacturing & Wholesale Goods"
        }
    ],
    "sg:phone":"+1 450 649 9595",
    "sg:postcode":"J3E 2J9",
    "sg:province":"QC",
    "sg:tags":[
        "food",
        "broker"
    ],
    "wof:name":"Access Ingredients Inc",
    "wof:placetype":"venue"
},
  "geometry": {"coordinates":[-73.30926513670001,45.5778961182],"type":"Point"}
}