{
  "type": "Feature",
  "properties": {
    "addr:full":"295 16th St W Prince Albert SK S6V 3V4",
    "addr:housenumber":"295",
    "addr:postcode":"s6v 3v4",
    "addr:street":"16Th St",
    "iso:country":"CA",
    "sg:address":"295 16th St W",
    "sg:city":"Prince Albert",
    "sg:classifiers":[
        {
            "category":"Retail",
            "subcategory":"Auto Repair",
            "type":"Services"
        }
    ],
    "sg:phone":"+1 306 763 3139",
    "sg:postcode":"S6V 3V4",
    "sg:province":"SK",
    "sg:tags":[
        "repairing",
        "automobile",
        "radiator"
    ],
    "wof:name":"P A Radiator Shop",
    "wof:placetype":"venue"
},
  "geometry": {"coordinates":[-105.76200900000001,53.198315],"type":"Point"}
}