{
  "type": "Feature",
  "properties": {
    "addr:full":"412 Nelson St W Port Dover ON N0A 1N0",
    "addr:housenumber":"412",
    "addr:postcode":"n0a 1n0",
    "addr:street":"Nelson St W Port Dover",
    "iso:country":"CA",
    "sg:address":"412 Nelson St W",
    "sg:city":"Port Dover",
    "sg:classifiers":[
        {
            "category":"Building & Trades",
            "subcategory":"Electrical",
            "type":"Services"
        }
    ],
    "sg:phone":"+1 519 583 2135",
    "sg:postcode":"N0A 1N0",
    "sg:province":"ON",
    "sg:tags":[
        "electric",
        "contractor"
    ],
    "wof:name":"Ken Simpson Electric",
    "wof:placetype":"venue"
},
  "geometry": {"coordinates":[-80.21270800000001,42.784641],"type":"Point"}
}