{
  "type": "Feature",
  "properties": {
    "addr:full":"18 4E Av O Macamic QC J0Z 2S0",
    "addr:housenumber":"18",
    "addr:postcode":"j0z 2s0",
    "addr:street":"4E Av O",
    "iso:country":"CA",
    "sg:address":"18 4E Av O",
    "sg:city":"Macamic",
    "sg:classifiers":[
        {
            "category":"Personal",
            "subcategory":"Beauty Salon",
            "type":"Services"
        }
    ],
    "sg:phone":"+1 819 782 4337",
    "sg:postcode":"J0Z 2S0",
    "sg:province":"QC",
    "wof:name":"Salon Margot",
    "wof:placetype":"venue"
},
  "geometry": {"coordinates":[-78.999443,48.752495],"type":"Point"}
}