{
  "type": "Feature",
  "properties": {
    "iso:country":"CA",
    "sg:address":"387 Simcoe St S",
    "sg:city":"Oshawa",
    "sg:classifiers":[
        {
            "category":"Social Services",
            "type":"Services"
        }
    ],
    "sg:phone":"+1 905 728 7525",
    "sg:postcode":"L1H 4J2",
    "sg:province":"ON",
    "sg:tags":[
        "organization",
        "welfare"
    ],
    "wof:name":"Simcoe Hall Settlement House",
    "wof:placetype":"venue"
},
  "geometry": {"coordinates":[-78.858887,43.887386],"type":"Point"}
}