{
  "type": "Feature",
  "properties": {
    "addr:full":"3110 Marentette Ave Windsor ON N8X 4G2",
    "addr:housenumber":"3110",
    "addr:postcode":"n8x 4g2",
    "addr:street":"Marentette Ave",
    "iso:country":"CA",
    "sg:address":"3110 Marentette Ave",
    "sg:city":"Windsor",
    "sg:classifiers":[
        {
            "category":"Manufacturing",
            "subcategory":"Food",
            "type":"Manufacturing & Wholesale Goods"
        }
    ],
    "sg:phone":"+1 519 966 9733",
    "sg:postcode":"N8X 4G2",
    "sg:province":"ON",
    "sg:tags":[
        "tea",
        "coffee"
    ],
    "wof:name":"Colonial Coffee CO Ltd",
    "wof:placetype":"venue"
},
  "geometry": {"coordinates":[-82.999161,42.276508],"type":"Point"}
}