{
  "type": "Feature",
  "properties": {
    "iso:country":"CA",
    "sg:address":"121 Government Rd",
    "sg:city":"Kearns",
    "sg:classifiers":[
        {
            "category":"Autos & Motor Vehicles",
            "subcategory":"Fuel & Gas Station",
            "type":"Retail Goods"
        }
    ],
    "sg:phone":"+1 705 634 2640",
    "sg:postcode":"P0K 1J0",
    "sg:province":"ON",
    "sg:tags":[
        "oil"
    ],
    "wof:name":"Guy's Service Station",
    "wof:placetype":"venue"
},
  "geometry": {"coordinates":[-79.5646896362,48.1424674988],"type":"Point"}
}