{
  "type": "Feature",
  "properties": {
    "addr:full":"3061 Orlando Dr Mississauga ON L4V 1L6",
    "addr:housenumber":"3061",
    "addr:postcode":"l4v 1l6",
    "addr:street":"Orlando Dr",
    "iso:country":"CA",
    "sg:address":"3061 Orlando Dr",
    "sg:city":"Mississauga",
    "sg:classifiers":[
        {
            "category":"Wholesale",
            "subcategory":"Electrical",
            "type":"Manufacturing & Wholesale Goods"
        }
    ],
    "sg:phone":"+1 905 671 4747",
    "sg:postcode":"L4V 1L6",
    "sg:province":"ON",
    "sg:tags":[
        "appliance"
    ],
    "wof:name":"Maroline Distributing",
    "wof:placetype":"venue"
},
  "geometry": {"coordinates":[-79.629158,43.696342],"type":"Point"}
}