{
  "type": "Feature",
  "properties": {
    "addr:full":"Sparwood BC V0B 2G0",
    "addr:postcode":"bc v0b 2g0",
    "iso:country":"CA",
    "sg:city":"Sparwood",
    "sg:classifiers":[
        {
            "category":"Real Estate",
            "subcategory":"Real Estate Operator",
            "type":"Services"
        }
    ],
    "sg:phone":"+1 250 425 2832",
    "sg:postcode":"V0B 2G0",
    "sg:province":"BC",
    "sg:tags":[
        "mobile",
        "home",
        "community"
    ],
    "wof:name":"Mountainview Mobile Home Park",
    "wof:placetype":"venue"
},
  "geometry": {"coordinates":[-114.88078299999999,49.73436],"type":"Point"}
}