{
  "type": "Feature",
  "properties": {
    "addr:full":"Farm North Battleford SK S9A 2Y1",
    "addr:postcode":"s9a 2y1",
    "iso:country":"CA",
    "sg:address":"Farm",
    "sg:city":"North Battleford",
    "sg:classifiers":[
        {
            "category":"Farming",
            "subcategory":"Nursery",
            "type":"Manufacturing & Wholesale Goods"
        }
    ],
    "sg:phone":"+1 306 445 2939",
    "sg:postcode":"S9A 2Y1",
    "sg:province":"SK",
    "sg:tags":[
        "seed"
    ],
    "wof:name":"Charabin Seed Farm",
    "wof:placetype":"venue"
},
  "geometry": {"coordinates":[-108.313141,52.736237],"type":"Point"}
}