{
  "type": "Feature",
  "properties": {
    "addr:full":"58 Scarsdale Rd North York ON M3B 2R7",
    "addr:housenumber":"58",
    "addr:postcode":"m3b 2r7",
    "addr:street":"Scarsdale Rd",
    "iso:country":"CA",
    "sg:address":"58 Scarsdale Rd",
    "sg:city":"North York",
    "sg:classifiers":[
        {
            "category":"Manufacturing",
            "subcategory":"Rubber & Plastics",
            "type":"Manufacturing & Wholesale Goods"
        }
    ],
    "sg:phone":"+1 416 510 1035",
    "sg:postcode":"M3B 2R7",
    "sg:province":"ON",
    "sg:tags":[
        "mold",
        "maker"
    ],
    "wof:name":"Comp Tech Mfg Inc",
    "wof:placetype":"venue"
},
  "geometry": {"coordinates":[-79.35437011720001,43.74817276],"type":"Point"}
}