{
  "type": "Feature",
  "properties": {
    "addr:full":"2065 20th Side Rd Thunder Bay ON P7K 1H6",
    "addr:housenumber":"2065",
    "addr:postcode":"p7k 1h6",
    "addr:street":"20Th Side Rd",
    "iso:country":"CA",
    "sg:address":"2065 20th Side Rd",
    "sg:city":"Thunder Bay",
    "sg:classifiers":[
        {
            "category":"Government",
            "subcategory":"Fire Station",
            "type":"Public Place"
        }
    ],
    "sg:phone":"+1 807 473 4990",
    "sg:postcode":"P7K 1H6",
    "sg:province":"ON",
    "sg:tags":[
        "department"
    ],
    "wof:name":"Thunder Bay Fire Station",
    "wof:placetype":"venue"
},
  "geometry": {"coordinates":[-89.3611755371,48.3655700684],"type":"Point"}
}