{
  "type": "Feature",
  "properties": {
    "addr:full":"Oshawa ON L1G 7W4",
    "addr:postcode":"l1g 7w4",
    "iso:country":"CA",
    "sg:city":"Oshawa",
    "sg:classifiers":[
        {
            "category":"Health Services",
            "subcategory":"Doctor",
            "type":"Services"
        }
    ],
    "sg:phone":"+1 905 576 6861",
    "sg:postcode":"L1G 7W4",
    "sg:province":"ON",
    "sg:tags":[
        "dentist"
    ],
    "wof:name":"Robert Cox & Assoc",
    "wof:placetype":"venue"
},
  "geometry": {"coordinates":[-78.8697967529,43.9364814758],"type":"Point"}
}