{
  "type": "Feature",
  "properties": {
    "addr:full":"160 Argyle St S Caledonia ON N3W 1K7",
    "addr:housenumber":"160",
    "addr:postcode":"n3w 1k7",
    "addr:street":"Argyle St S",
    "iso:country":"CA",
    "sg:address":"160 Argyle St S",
    "sg:city":"Caledonia",
    "sg:classifiers":[
        {
            "category":"Autos & Motor Vehicles",
            "subcategory":"Automobile Sales",
            "type":"Retail Goods"
        }
    ],
    "sg:phone":"+1 905 765 4424",
    "sg:postcode":"N3W 1K7",
    "sg:province":"ON",
    "sg:tags":[
        "car",
        "dealer"
    ],
    "wof:name":"Dennis Searles Chev Olds Ltd",
    "wof:placetype":"venue"
},
  "geometry": {"coordinates":[-79.95630645750001,43.0673522949],"type":"Point"}
}