{
  "type": "Feature",
  "properties": {
    "addr:full":"5739 Foster Rue Waterloo QC J0E 2N0",
    "addr:housenumber":"5739",
    "addr:postcode":"j0e 2n0",
    "addr:street":"Foster Rue",
    "iso:country":"CA",
    "sg:address":"5739 Foster Rue",
    "sg:city":"Waterloo",
    "sg:classifiers":[
        {
            "category":"Personal",
            "subcategory":"Beauty Salon",
            "type":"Services"
        }
    ],
    "sg:phone":"+1 450 539 3949",
    "sg:postcode":"J0E 2N0",
    "sg:province":"QC",
    "wof:name":"Salon Jouvence",
    "wof:placetype":"venue"
},
  "geometry": {"coordinates":[-72.516273,45.34866],"type":"Point"}
}