{
  "type": "Feature",
  "properties": {
    "iso:country":"CA",
    "sg:address":"2440 Princess St",
    "sg:city":"Kingston",
    "sg:classifiers":[
        {
            "category":"Restaurant",
            "type":"Food & Drink"
        }
    ],
    "sg:phone":"+1 613 542 0352",
    "sg:postcode":"K7M 3G4",
    "sg:province":"ON",
    "wof:name":"Cafe Biarritz",
    "wof:placetype":"venue"
},
  "geometry": {"coordinates":[-76.558311,44.258354],"type":"Point"}
}