{
  "type": "Feature",
  "properties": {
    "addr:full":"5908 82 Ave NW Edmonton AB T6B 0E7",
    "addr:housenumber":"5908",
    "addr:postcode":"t6b 0e7",
    "addr:street":"82 Ave Nw",
    "iso:country":"CA",
    "sg:address":"5908 82 Ave NW",
    "sg:city":"Edmonton",
    "sg:classifiers":[
        {
            "category":"Retail",
            "subcategory":"Auto Repair",
            "type":"Services"
        }
    ],
    "sg:phone":"+1 780 465 5571",
    "sg:postcode":"T6B 0E7",
    "sg:province":"AB",
    "sg:tags":[
        "repairing",
        "automobile"
    ],
    "wof:name":"Bettcher's Auto Svc",
    "wof:placetype":"venue"
},
  "geometry": {"coordinates":[-113.42536163299999,53.5182647705],"type":"Point"}
}