{
  "type": "Feature",
  "properties": {
    "addr:full":"5126 52nd Ave Drayton Valley AB T7A 1R6",
    "addr:housenumber":"5126",
    "addr:postcode":"t7a 1r6",
    "addr:street":"52Nd Ave",
    "iso:country":"CA",
    "sg:address":"5126 52nd Ave",
    "sg:city":"Drayton Valley",
    "sg:classifiers":[
        {
            "category":"Shopping",
            "subcategory":"Florist",
            "type":"Retail Goods"
        }
    ],
    "sg:phone":"+1 780 542 5232",
    "sg:postcode":"T7A 1R6",
    "sg:province":"AB",
    "wof:name":"Valley House of Flowers",
    "wof:placetype":"venue"
},
  "geometry": {"coordinates":[-114.978843689,53.2240943909],"type":"Point"}
}