{
  "type": "Feature",
  "properties": {
    "addr:full":"70 Rue Commerciale Saint-Boniface-DE-Shawinigan QC G0X 2L0",
    "addr:housenumber":"70",
    "addr:postcode":"g0x 2l0",
    "addr:street":"Rue Commerciale",
    "iso:country":"CA",
    "sg:address":"70 Rue Commerciale",
    "sg:city":"Saint-Boniface-DE-Shawinigan",
    "sg:classifiers":[
        {
            "category":"Home & Garden",
            "subcategory":"Hardware",
            "type":"Retail Goods"
        }
    ],
    "sg:phone":"+1 819 535 3812",
    "sg:postcode":"G0X 2L0",
    "sg:province":"QC",
    "wof:name":"Houle Maison Maurice & Fils",
    "wof:placetype":"venue"
},
  "geometry": {"coordinates":[-72.82907899999999,46.506454],"type":"Point"}
}