{
  "type": "Feature",
  "properties": {
    "addr:full":"Marystown NL A0E 2M0",
    "addr:postcode":"a0e 2m0",
    "iso:country":"CA",
    "sg:city":"Marystown",
    "sg:classifiers":[
        {
            "category":"Shopping",
            "subcategory":"Pharmacy",
            "type":"Retail Goods"
        }
    ],
    "sg:phone":"+1 709 279 1932",
    "sg:postcode":"A0E 2M0",
    "sg:province":"NL",
    "wof:name":"Sobey's Pharmacy",
    "wof:placetype":"venue"
},
  "geometry": {"coordinates":[-55.15239,47.167347],"type":"Point"}
}