{
  "type": "Feature",
  "properties": {
    "addr:full":"20 Victoria St Toronto ON M5C 2N8",
    "addr:housenumber":"20",
    "addr:postcode":"m5c 2n8",
    "addr:street":"Victoria St",
    "iso:country":"CA",
    "sg:address":"20 Victoria St",
    "sg:city":"Toronto",
    "sg:classifiers":[
        {
            "category":"Real Estate",
            "subcategory":"Architect",
            "type":"Services"
        }
    ],
    "sg:phone":"+1 416 367 4131",
    "sg:postcode":"M5C 2N8",
    "sg:province":"ON",
    "wof:name":"Pellow & Assoc Architects Inc",
    "wof:placetype":"venue"
},
  "geometry": {"coordinates":[-79.376999,43.649502],"type":"Point"}
}