{
  "type": "Feature",
  "properties": {
    "addr:full":"Coteau-Du-Lac QC J0P 1B0",
    "addr:postcode":"j0p 1b0",
    "iso:country":"CA",
    "sg:city":"Coteau-Du-Lac",
    "sg:classifiers":[
        {
            "category":"Personal",
            "subcategory":"Beauty Salon",
            "type":"Services"
        }
    ],
    "sg:phone":"+1 450 763 0354",
    "sg:postcode":"J0P 1B0",
    "sg:province":"QC",
    "wof:name":"Salon Lucien Coiffure",
    "wof:placetype":"venue"
},
  "geometry": {"coordinates":[-74.179131,45.285736],"type":"Point"}
}