{
  "type": "Feature",
  "properties": {
    "iso:country":"CA",
    "sg:city":"Fort Mackay",
    "sg:classifiers":[
        {
            "category":"Social Services",
            "subcategory":"Child Care",
            "type":"Services"
        }
    ],
    "sg:phone":"+1 780 828 0004",
    "sg:postcode":"T0P 1C0",
    "sg:province":"AB",
    "wof:name":"Mothers of Mc Kay",
    "wof:placetype":"venue"
},
  "geometry": {"coordinates":[-111.479980469,56.9960136414],"type":"Point"}
}