{
  "type": "Feature",
  "properties": {
    "addr:full":"1826 Mcara St Regina SK S4N 6C4",
    "addr:housenumber":"1826",
    "addr:postcode":"s4n 6c4",
    "addr:street":"Mcara St",
    "iso:country":"CA",
    "sg:address":"1826 Mcara St",
    "sg:city":"Regina",
    "sg:classifiers":[
        {
            "category":"Arts & Performance",
            "subcategory":"Theater",
            "type":"Entertainment"
        }
    ],
    "sg:phone":"+1 306 359 6909",
    "sg:postcode":"S4N 6C4",
    "sg:province":"SK",
    "sg:tags":[
        "entertainer",
        "training",
        "dog"
    ],
    "wof:name":"Regina Kennel & Obedience Club",
    "wof:placetype":"venue"
},
  "geometry": {"coordinates":[-104.58234400000001,50.449863],"type":"Point"}
}