{
  "type": "Feature",
  "properties": {
    "addr:full":"702 46th St E Saskatoon SK S7K 0W9",
    "addr:housenumber":"702",
    "addr:postcode":"s7k 0w9",
    "addr:street":"46Th St E",
    "iso:country":"CA",
    "sg:address":"702 46th St E",
    "sg:city":"Saskatoon",
    "sg:classifiers":[
        {
            "category":"Wholesale",
            "subcategory":"Machinery & Supplies",
            "type":"Manufacturing & Wholesale Goods"
        }
    ],
    "sg:phone":"+1 306 653 0988",
    "sg:postcode":"S7K 0W9",
    "sg:province":"SK",
    "sg:tags":[
        "equipment",
        "mining"
    ],
    "wof:name":"Bit Service CO Ltd",
    "wof:placetype":"venue"
},
  "geometry": {"coordinates":[-106.658203125,52.1647567749],"type":"Point"}
}