{
  "type": "Feature",
  "properties": {
    "iso:country":"CA",
    "sg:address":"33 Rue Beausejour",
    "sg:city":"Saint-Louis-DE-Kent",
    "sg:classifiers":[
        {
            "category":"Communications",
            "subcategory":"Radio Station",
            "type":"Services"
        }
    ],
    "sg:phone":"+1 506 876 2299",
    "sg:postcode":"E4X 1A5",
    "sg:province":"NB",
    "sg:tags":[
        "company",
        "broadcasting"
    ],
    "wof:name":"Radio Beausejour",
    "wof:placetype":"venue"
},
  "geometry": {"coordinates":[-64.973251,46.734653],"type":"Point"}
}