{
  "type": "Feature",
  "properties": {
    "addr:full":"650 Av DE L'Hotel-Dieu Saint-Hyacinthe QC J2S 5J7",
    "addr:housenumber":"650",
    "addr:postcode":"j2s 5j7",
    "addr:street":"Av De L'Hotel-Dieu",
    "iso:country":"CA",
    "sg:address":"650 Av DE L'Hotel-Dieu",
    "sg:city":"Saint-Hyacinthe",
    "sg:classifiers":[
        {
            "category":"Personal",
            "subcategory":"Beauty Salon",
            "type":"Services"
        }
    ],
    "sg:phone":"+1 450 773 0873",
    "sg:postcode":"J2S 5J7",
    "sg:province":"QC",
    "wof:name":"Salon Prestige Coiffure Enr",
    "wof:placetype":"venue"
},
  "geometry": {"coordinates":[-72.94593,45.622738],"type":"Point"}
}