{
  "type": "Feature",
  "properties": {
    "addr:full":"Vancouver BC V6J 4A6",
    "addr:postcode":"v6j 4a6",
    "iso:country":"CA",
    "sg:city":"Vancouver",
    "sg:classifiers":[
        {
            "category":"Social Services",
            "subcategory":"Child Care",
            "type":"Services"
        }
    ],
    "sg:phone":"+1 604 732 9627",
    "sg:postcode":"V6J 4A6",
    "sg:province":"BC",
    "sg:tags":[
        "kindergarten",
        "academic",
        "school"
    ],
    "wof:name":"Little Acorn Academy",
    "wof:placetype":"venue"
},
  "geometry": {"coordinates":[-123.15222199999999,49.256622],"type":"Point"}
}