{
  "type": "Feature",
  "properties": {
    "iso:country":"CA",
    "sg:address":"4924 50 Ave",
    "sg:city":"Beaumont",
    "sg:classifiers":[
        {
            "category":"Food & Beverages",
            "subcategory":"Liquor & Beverages",
            "type":"Retail Goods"
        }
    ],
    "sg:phone":"+1 780 929 5511",
    "sg:postcode":"T4X 1J9",
    "sg:province":"AB",
    "sg:tags":[
        "store"
    ],
    "wof:name":"Hilltop Liquor Store Ltd",
    "wof:placetype":"venue"
},
  "geometry": {"coordinates":[-113.41411590600001,53.3525466919],"type":"Point"}
}