{
  "type": "Feature",
  "properties": {
    "addr:full":"Gimli MB R0C 1B0",
    "addr:postcode":"r0c 1b0",
    "iso:country":"CA",
    "sg:city":"Gimli",
    "sg:classifiers":[
        {
            "category":"Professional",
            "type":"Services"
        }
    ],
    "sg:phone":"+1 204 642 8015",
    "sg:postcode":"R0C 1B0",
    "sg:province":"MB",
    "sg:tags":[
        "writer"
    ],
    "wof:name":"Newman, Roger",
    "wof:placetype":"venue"
},
  "geometry": {"coordinates":[-96.9941864014,50.6368637085],"type":"Point"}
}