{
  "type": "Feature",
  "properties": {
    "addr:full":"9580 Pendleton Rd Richmond BC V7E 4N1",
    "addr:housenumber":"9580",
    "addr:postcode":"v7e 4n1",
    "addr:street":"Pendleton Rd",
    "iso:country":"CA",
    "sg:address":"9580 Pendleton Rd",
    "sg:city":"Richmond",
    "sg:classifiers":[
        {
            "category":"Social Services",
            "type":"Services"
        }
    ],
    "sg:phone":"+1 604 275 3337",
    "sg:postcode":"V7E 4N1",
    "sg:province":"BC",
    "sg:tags":[
        "organization",
        "welfare"
    ],
    "wof:name":"Richmond Society For Community",
    "wof:placetype":"venue"
},
  "geometry": {"coordinates":[-123.17688,49.144924],"type":"Point"}
}