{
  "type": "Feature",
  "properties": {
    "addr:full":"Geraldton Airport #6 Geraldton ON P0T 1M0",
    "addr:postcode":"p0t 1m0",
    "iso:country":"CA",
    "sg:address":"Geraldton Airport #6",
    "sg:city":"Geraldton",
    "sg:classifiers":[
        {
            "category":"Professional",
            "subcategory":"Management & Consulting",
            "type":"Services"
        }
    ],
    "sg:phone":"+1 807 854 2425",
    "sg:postcode":"P0T 1M0",
    "sg:province":"ON",
    "sg:tags":[
        "aviation",
        "aircraft",
        "maintenance",
        "consultant"
    ],
    "wof:name":"Recon Air",
    "wof:placetype":"venue"
},
  "geometry": {"coordinates":[-86.9506454468,49.7301521301],"type":"Point"}
}