{
  "type": "Feature",
  "properties": {
    "iso:country":"CA",
    "sg:address":"405 Ch DE LA Grande-Cote",
    "sg:city":"Boisbriand",
    "sg:classifiers":[
        {
            "category":"Shopping",
            "subcategory":"Clothing, Apparel, & Fashions",
            "type":"Retail Goods"
        }
    ],
    "sg:phone":"+1 450 437 5292",
    "sg:postcode":"J7G 1A9",
    "sg:province":"QC",
    "sg:tags":[
        "dressmaker"
    ],
    "wof:name":"Atelier DE Couture Boisbriand",
    "wof:placetype":"venue"
},
  "geometry": {"coordinates":[-73.8350067139,45.6059036255],"type":"Point"}
}