{
  "type": "Feature",
  "properties": {
    "addr:full":"6704 74A Ave NW Edmonton AB T6B 3H7",
    "addr:housenumber":"6704",
    "addr:postcode":"t6b 3h7",
    "addr:street":"74A Ave Nw",
    "iso:country":"CA",
    "sg:address":"6704 74A Ave NW",
    "sg:city":"Edmonton",
    "sg:classifiers":[
        {
            "category":"Manufacturing",
            "subcategory":"Metals",
            "type":"Manufacturing & Wholesale Goods"
        }
    ],
    "sg:phone":"+1 780 414 6701",
    "sg:postcode":"T6B 3H7",
    "sg:province":"AB",
    "sg:tags":[
        "steel"
    ],
    "wof:name":"Petrochem Fabricators Ltd",
    "wof:placetype":"venue"
},
  "geometry": {"coordinates":[-113.43079400000001,53.510822],"type":"Point"}
}