{
  "type": "Feature",
  "properties": {
    "addr:full":"398 Vine St St Catharines ON L2M 3S2",
    "addr:housenumber":"398",
    "addr:postcode":"l2m 3s2",
    "addr:street":"Vine St",
    "iso:country":"CA",
    "sg:address":"398 Vine St",
    "sg:city":"St Catharines",
    "sg:classifiers":[
        {
            "category":"Health Services",
            "subcategory":"Nursing And Care Facility",
            "type":"Services"
        }
    ],
    "sg:phone":"+1 905 935 1921",
    "sg:postcode":"L2M 3S2",
    "sg:province":"ON",
    "sg:tags":[
        "home",
        "retirement",
        "community",
        "rest"
    ],
    "wof:name":"Niagara Retirement Manor",
    "wof:placetype":"venue"
},
  "geometry": {"coordinates":[-79.230797,43.189964],"type":"Point"}
}