{
  "type": "Feature",
  "properties": {
    "addr:full":"423 Rue Dequen Saint-Gedeon QC G0W 2P0",
    "addr:housenumber":"423",
    "addr:postcode":"g0w 2p0",
    "addr:street":"Rue Dequen Saint-Gedeon",
    "iso:country":"CA",
    "sg:address":"423 Rue Dequen",
    "sg:city":"Saint-Gedeon",
    "sg:classifiers":[
        {
            "category":"Home & Garden",
            "subcategory":"Garden Supply",
            "type":"Retail Goods"
        }
    ],
    "sg:phone":"+1 418 345 2445",
    "sg:postcode":"G0W 2P0",
    "sg:province":"QC",
    "sg:tags":[
        "engine"
    ],
    "wof:name":"Atelier Jpl Enr",
    "wof:placetype":"venue"
},
  "geometry": {"coordinates":[-71.773765564,48.4978485107],"type":"Point"}
}