{
  "type": "Feature",
  "properties": {
    "addr:full":"511 Edinburgh Rd S # 204 Guelph ON N1G 4S5",
    "addr:housenumber":"511",
    "addr:postcode":"n1g 4s5",
    "addr:street":"Edinburgh Rd S # 204",
    "iso:country":"CA",
    "sg:address":"511 Edinburgh Rd S # 204",
    "sg:city":"Guelph",
    "sg:classifiers":[
        {
            "category":"Education",
            "subcategory":"Special Training",
            "type":"Public Place"
        }
    ],
    "sg:phone":"+1 519 826 5365",
    "sg:postcode":"N1G 4S5",
    "sg:province":"ON",
    "sg:tags":[
        "tutoring"
    ],
    "wof:name":"Oxford Learning Ctr",
    "wof:placetype":"venue"
},
  "geometry": {"coordinates":[-80.2334365845,43.5193824768],"type":"Point"}
}