{
  "type": "Feature",
  "properties": {
    "iso:country":"CA",
    "sg:address":"2341 Alfred-Nobel Blvd",
    "sg:city":"Saint-Laurent",
    "sg:classifiers":[
        {
            "category":"Shopping",
            "type":"Retail Goods"
        }
    ],
    "sg:phone":"+1 514 818 1010",
    "sg:postcode":"H4S 2B8",
    "sg:province":"QC",
    "sg:tags":[
        "equipment",
        "telephone",
        "supply"
    ],
    "wof:name":"Nortel Networks",
    "wof:placetype":"venue"
},
  "geometry": {"coordinates":[-73.7610321045,45.4821548462],"type":"Point"}
}