{
  "type": "Feature",
  "properties": {
    "addr:full":"Vancouver BC V6B 2J2",
    "addr:postcode":"v6b 2j2",
    "iso:country":"CA",
    "sg:city":"Vancouver",
    "sg:classifiers":[
        {
            "category":"Professional",
            "subcategory":"Lawyer & Legal Services",
            "type":"Services"
        }
    ],
    "sg:phone":"+1 604 688 9377",
    "sg:postcode":"V6B 2J2",
    "sg:province":"BC",
    "sg:tags":[
        "attorney"
    ],
    "wof:name":"Yes Dispute Resolution Svc",
    "wof:placetype":"venue"
},
  "geometry": {"coordinates":[-123.104469299,49.2828445435],"type":"Point"}
}