{
  "type": "Feature",
  "properties": {
    "iso:country":"CA",
    "sg:address":"2105 Royal Windsor Dr",
    "sg:city":"Mississauga",
    "sg:classifiers":[
        {
            "category":"Recreation",
            "type":"Entertainment"
        }
    ],
    "sg:phone":"+1 905 823 4001",
    "sg:postcode":"L5J 1K5",
    "sg:province":"ON",
    "sg:tags":[
        "skating",
        "rink"
    ],
    "wof:name":"Scooter's Roller Palace",
    "wof:placetype":"venue"
},
  "geometry": {"coordinates":[-79.632599,43.508743],"type":"Point"}
}