{
  "type": "Feature",
  "properties": {
    "iso:country":"CA",
    "sg:address":"5481 Highway 69 N",
    "sg:city":"Hanmer",
    "sg:classifiers":[
        {
            "category":"Building & Trades",
            "subcategory":"Construction",
            "type":"Services"
        }
    ],
    "sg:phone":"+1 705 969 9666",
    "sg:postcode":"P3P 1E4",
    "sg:province":"ON",
    "sg:tags":[
        "excavating",
        "contractor"
    ],
    "wof:name":"Labelle Trucking & Excavating",
    "wof:placetype":"venue"
},
  "geometry": {"coordinates":[-80.9448013306,46.6524963379],"type":"Point"}
}