{
  "type": "Feature",
  "properties": {
    "addr:full":"555 Elizabeth St Midland ON L4R 2A4",
    "addr:housenumber":"555",
    "addr:postcode":"l4r 2a4",
    "addr:street":"Elizabeth St",
    "iso:country":"CA",
    "sg:address":"555 Elizabeth St",
    "sg:city":"Midland",
    "sg:classifiers":[
        {
            "category":"Real Estate",
            "subcategory":"Surveying",
            "type":"Services"
        }
    ],
    "sg:phone":"+1 705 527 7272",
    "sg:postcode":"L4R 2A4",
    "sg:province":"ON",
    "sg:tags":[
        "surveyor"
    ],
    "wof:name":"Rodney G Reynolds Ontario Land",
    "wof:placetype":"venue"
},
  "geometry": {"coordinates":[-79.8857345581,44.7475891113],"type":"Point"}
}