{
  "type": "Feature",
  "properties": {
    "addr:full":"192 Rue Fleury O Montreal QC H3L 1T5",
    "addr:housenumber":"192",
    "addr:postcode":"h3l 1t5",
    "addr:street":"Rue Fleury O",
    "iso:country":"CA",
    "sg:address":"192 Rue Fleury O",
    "sg:city":"Montreal",
    "sg:classifiers":[
        {
            "category":"Personal",
            "subcategory":"Tanning Parlor",
            "type":"Services"
        }
    ],
    "sg:phone":"+1 514 382 9274",
    "sg:postcode":"H3L 1T5",
    "sg:province":"QC",
    "sg:tags":[
        "salon"
    ],
    "wof:name":"Bronzage Tan Tan",
    "wof:placetype":"venue"
},
  "geometry": {"coordinates":[-73.663757,45.549969],"type":"Point"}
}