{
  "type": "Feature",
  "properties": {
    "addr:full":"164 Laurier Ave W Ottawa ON K1P 5J4",
    "addr:housenumber":"164",
    "addr:postcode":"k1p 5j4",
    "addr:street":"Laurier Ave W",
    "iso:country":"CA",
    "sg:address":"164 Laurier Ave W",
    "sg:city":"Ottawa",
    "sg:classifiers":[
        {
            "category":"Restaurant",
            "type":"Food & Drink"
        }
    ],
    "sg:phone":"+1 613 234 8882",
    "sg:postcode":"K1P 5J4",
    "sg:province":"ON",
    "wof:name":"Buffet Moni Mahal",
    "wof:placetype":"venue"
},
  "geometry": {"coordinates":[-75.69399300000001,45.420486],"type":"Point"}
}