{
  "type": "Feature",
  "properties": {
    "addr:full":"1696 Avenue Rd North York ON M5M 3Y4",
    "addr:housenumber":"1696",
    "addr:postcode":"m5m 3y4",
    "addr:street":"Avenue Rd",
    "iso:country":"CA",
    "sg:address":"1696 Avenue Rd",
    "sg:city":"North York",
    "sg:classifiers":[
        {
            "category":"Social Services",
            "subcategory":"Job Training",
            "type":"Services"
        }
    ],
    "sg:phone":"+1 416 630 1412",
    "sg:postcode":"M5M 3Y4",
    "sg:province":"ON",
    "sg:tags":[
        "rehabilitation"
    ],
    "wof:name":"Catalyst Rehab & Management",
    "wof:placetype":"venue"
},
  "geometry": {"coordinates":[-79.41793800000001,43.727558],"type":"Point"}
}