{
  "type": "Feature",
  "properties": {
    "addr:full":"681 Rue DE Montcalm Berthierville QC J0K 1A0",
    "addr:housenumber":"681",
    "addr:postcode":"j0k 1a0",
    "addr:street":"Rue De Montcalm",
    "iso:country":"CA",
    "sg:address":"681 Rue DE Montcalm",
    "sg:city":"Berthierville",
    "sg:classifiers":[
        {
            "category":"Restaurant",
            "type":"Food & Drink"
        }
    ],
    "sg:phone":"+1 450 836 6527",
    "sg:postcode":"J0K 1A0",
    "sg:province":"QC",
    "sg:tags":[
        "caterer"
    ],
    "wof:name":"Buffet Champlain",
    "wof:placetype":"venue"
},
  "geometry": {"coordinates":[-73.17627,46.08234],"type":"Point"}
}