{
  "type": "Feature",
  "properties": {
    "addr:full":"2506 Highway 69 N Val Caron ON P3N 1K6",
    "addr:housenumber":"2506",
    "addr:postcode":"p3n 1k6",
    "addr:street":"Highway 69 N",
    "iso:country":"CA",
    "sg:address":"2506 Highway 69 N",
    "sg:city":"Val Caron",
    "sg:classifiers":[
        {
            "category":"Shopping",
            "subcategory":"Used Merchandise",
            "type":"Retail Goods"
        }
    ],
    "sg:phone":"+1 705 897 1212",
    "sg:postcode":"P3N 1K6",
    "sg:province":"ON",
    "sg:tags":[
        "second",
        "store",
        "hand"
    ],
    "wof:name":"St Vincent DE Paul Society",
    "wof:placetype":"venue"
},
  "geometry": {"coordinates":[-81.008644,46.610432],"type":"Point"}
}