{
  "type": "Feature",
  "properties": {
    "addr:full":"701 9th St W Meadow Lake SK S9X 1T1",
    "addr:housenumber":"701",
    "addr:postcode":"s9x 1t1",
    "addr:street":"9Th St W Meadow",
    "iso:country":"CA",
    "sg:address":"701 9th St W",
    "sg:city":"Meadow Lake",
    "sg:classifiers":[
        {
            "category":"Home & Garden",
            "subcategory":"Building Materials",
            "type":"Retail Goods"
        }
    ],
    "sg:phone":"+1 306 236 4457",
    "sg:postcode":"S9X 1T1",
    "sg:province":"SK",
    "sg:tags":[
        "lumber"
    ],
    "wof:name":"Meadow Lake Building Supplies",
    "wof:placetype":"venue"
},
  "geometry": {"coordinates":[-108.45320100000001,54.124229],"type":"Point"}
}