{
  "type": "Feature",
  "properties": {
    "addr:full":"105 Keats St Southey SK S0G 4P0",
    "addr:housenumber":"105",
    "addr:postcode":"s0g 4p0",
    "addr:street":"Keats St",
    "iso:country":"CA",
    "sg:address":"105 Keats St",
    "sg:city":"Southey",
    "sg:classifiers":[
        {
            "category":"Shopping",
            "subcategory":"Computers & Home Electronics",
            "type":"Retail Goods"
        }
    ],
    "sg:phone":"+1 306 726 2998",
    "sg:postcode":"S0G 4P0",
    "sg:province":"SK",
    "sg:tags":[
        "hardware",
        "equipment",
        "satellite"
    ],
    "wof:name":"Service Hardware",
    "wof:placetype":"venue"
},
  "geometry": {"coordinates":[-104.499123,50.938309],"type":"Point"}
}