{
  "type": "Feature",
  "properties": {
    "addr:full":"180 Rue Genest Asbestos QC J1T 1A9",
    "addr:housenumber":"180",
    "addr:postcode":"j1t 1a9",
    "addr:street":"Rue Genest",
    "iso:country":"CA",
    "sg:address":"180 Rue Genest",
    "sg:city":"Asbestos",
    "sg:classifiers":[
        {
            "category":"Education",
            "subcategory":"School",
            "type":"Public Place"
        }
    ],
    "sg:phone":"+1 819 879 6303",
    "sg:postcode":"J1T 1A9",
    "sg:province":"QC",
    "wof:name":"Ecole LA Tourelle",
    "wof:placetype":"venue"
},
  "geometry": {"coordinates":[-71.912781,45.7822],"type":"Point"}
}