{
  "type": "Feature",
  "properties": {
    "addr:full":"28 Crown Steel Dr Markham ON L3R 9Y1",
    "addr:housenumber":"28",
    "addr:postcode":"l3r 9y1",
    "addr:street":"Crown Steel Dr",
    "iso:country":"CA",
    "sg:address":"28 Crown Steel Dr",
    "sg:city":"Markham",
    "sg:classifiers":[
        {
            "category":"Wholesale",
            "subcategory":"Machinery & Supplies",
            "type":"Manufacturing & Wholesale Goods"
        }
    ],
    "sg:phone":"+1 905 474 9853",
    "sg:postcode":"L3R 9Y1",
    "sg:province":"ON",
    "sg:tags":[
        "salon",
        "beauty"
    ],
    "wof:name":"Argus Beauty Supply",
    "wof:placetype":"venue"
},
  "geometry": {"coordinates":[-79.3254623413,43.839466095],"type":"Point"}
}