{
  "type": "Feature",
  "properties": {
    "addr:full":"150 Milner Ave Scarborough ON M1S 3R3",
    "addr:housenumber":"150",
    "addr:postcode":"m1s 3r3",
    "addr:street":"Milner Ave",
    "iso:country":"CA",
    "sg:address":"150 Milner Ave",
    "sg:city":"Scarborough",
    "sg:classifiers":[
        {
            "category":"Manufacturing",
            "subcategory":"Paper Products",
            "type":"Manufacturing & Wholesale Goods"
        }
    ],
    "sg:phone":"+1 416 754 3196",
    "sg:postcode":"M1S 3R3",
    "sg:province":"ON",
    "sg:tags":[
        "bag"
    ],
    "wof:name":"Yellow River Plastic Bag",
    "wof:placetype":"venue"
},
  "geometry": {"coordinates":[-79.24567399999999,43.785706],"type":"Point"}
}