{
  "type": "Feature",
  "properties": {
    "addr:full":"5758 Av Royalmount Mont-Royal QC H4P 1K5",
    "addr:housenumber":"5758",
    "addr:postcode":"h4p 1k5",
    "addr:street":"Av Royalmount",
    "iso:country":"CA",
    "sg:address":"5758 Av Royalmount",
    "sg:city":"Mont-Royal",
    "sg:classifiers":[
        {
            "category":"Shopping",
            "subcategory":"Computers & Home Electronics",
            "type":"Retail Goods"
        }
    ],
    "sg:phone":"+1 514 383 0660",
    "sg:postcode":"H4P 1K5",
    "sg:province":"QC",
    "sg:tags":[
        "equipment",
        "satellite",
        "system"
    ],
    "wof:name":"Diego International Inc",
    "wof:placetype":"venue"
},
  "geometry": {"coordinates":[-73.670433,45.490974],"type":"Point"}
}