{
  "type": "Feature",
  "properties": {
    "iso:country":"CA",
    "sg:address":"60 Courtland Ave",
    "sg:city":"Concord",
    "sg:classifiers":[
        {
            "category":"Manufacturing",
            "subcategory":"Rubber & Plastics",
            "type":"Manufacturing & Wholesale Goods"
        }
    ],
    "sg:phone":"+1 905 660 7856",
    "sg:postcode":"L4K 5B3",
    "sg:province":"ON",
    "wof:name":"Accord Plastics",
    "wof:placetype":"venue"
},
  "geometry": {"coordinates":[-79.531158,43.814919],"type":"Point"}
}