{
  "type": "Feature",
  "properties": {
    "addr:full":"Vancouver BC V6J 3J6",
    "addr:postcode":"v6j 3j6",
    "iso:country":"CA",
    "sg:city":"Vancouver",
    "sg:classifiers":[
        {
            "category":"Health Services",
            "subcategory":"Clinic",
            "type":"Services"
        }
    ],
    "sg:phone":"+1 604 732 8765",
    "sg:postcode":"V6J 3J6",
    "sg:province":"BC",
    "sg:tags":[
        "therapist",
        "massage"
    ],
    "wof:name":"Burrard & Broadway Massage",
    "wof:placetype":"venue"
},
  "geometry": {"coordinates":[-123.14597320599999,49.2635231018],"type":"Point"}
}