{
  "type": "Feature",
  "properties": {
    "addr:full":"Rougemont QC J0L 1M0",
    "addr:postcode":"j0l 1m0",
    "iso:country":"CA",
    "sg:city":"Rougemont",
    "sg:classifiers":[
        {
            "category":"Wholesale",
            "subcategory":"Durable Goods & Equipment",
            "type":"Manufacturing & Wholesale Goods"
        }
    ],
    "sg:phone":"+1 450 776 0103",
    "sg:postcode":"J0L 1M0",
    "sg:province":"QC",
    "sg:tags":[
        "fire",
        "extinguisher"
    ],
    "wof:name":"Extincteur Superieur",
    "wof:placetype":"venue"
},
  "geometry": {"coordinates":[-73.0767364502,45.4641685486],"type":"Point"}
}