{
  "type": "Feature",
  "properties": {
    "iso:country":"CA",
    "sg:city":"Wainwright",
    "sg:classifiers":[
        {
            "category":"Shopping",
            "subcategory":"Department Store",
            "type":"Retail Goods"
        }
    ],
    "sg:phone":"+1 780 842 4992",
    "sg:postcode":"T9W 1C5",
    "sg:province":"AB",
    "wof:name":"Saan Stores Ltd",
    "wof:placetype":"venue"
},
  "geometry": {"coordinates":[-110.86215199999999,52.835026],"type":"Point"}
}