{
  "type": "Feature",
  "properties": {
    "iso:country":"CA",
    "sg:city":"Milton",
    "sg:classifiers":[
        {
            "category":"Wholesale",
            "subcategory":"Machinery & Supplies",
            "type":"Manufacturing & Wholesale Goods"
        }
    ],
    "sg:phone":"+1 905 875 1590",
    "sg:postcode":"L9T 5A3",
    "sg:province":"ON",
    "sg:tags":[
        "contractor"
    ],
    "wof:name":"Ironwood Fabricating",
    "wof:placetype":"venue"
},
  "geometry": {"coordinates":[-79.8811340332,43.5031661987],"type":"Point"}
}