{
  "type": "Feature",
  "properties": {
    "addr:full":"5305 44 St Beaumont AB T4X 1J1",
    "addr:housenumber":"5305",
    "addr:postcode":"t4x 1j1",
    "addr:street":"44 St",
    "iso:country":"CA",
    "sg:address":"5305 44 St",
    "sg:city":"Beaumont",
    "sg:classifiers":[
        {
            "category":"Shopping",
            "subcategory":"Bicycles & Sporting Goods",
            "type":"Retail Goods"
        }
    ],
    "sg:phone":"+1 780 929 9000",
    "sg:postcode":"T4X 1J1",
    "sg:province":"AB",
    "wof:name":"Recycle-A-Bike Repairs",
    "wof:placetype":"venue"
},
  "geometry": {"coordinates":[-113.40778350799999,53.3563728333],"type":"Point"}
}