{
  "type": "Feature",
  "properties": {
    "addr:full":"1933 105 St NW Edmonton AB T6J 5V9",
    "addr:housenumber":"1933",
    "addr:postcode":"t6j 5v9",
    "addr:street":"105 St Nw",
    "iso:country":"CA",
    "sg:address":"1933 105 St NW",
    "sg:city":"Edmonton",
    "sg:classifiers":[
        {
            "category":"Health Services",
            "subcategory":"Doctor",
            "type":"Services"
        }
    ],
    "sg:phone":"+1 780 436 7001",
    "sg:postcode":"T6J 5V9",
    "sg:province":"AB",
    "sg:tags":[
        "dentist"
    ],
    "wof:name":"Bearspaw Dental Office",
    "wof:placetype":"venue"
},
  "geometry": {"coordinates":[-113.500519,53.44883],"type":"Point"}
}