{
  "type": "Feature",
  "properties": {
    "addr:full":"155 Rosedale Ave Halifax NS B3N 2K2",
    "addr:housenumber":"155",
    "addr:postcode":"b3n 2k2",
    "addr:street":"Rosedale Ave",
    "iso:country":"CA",
    "sg:address":"155 Rosedale Ave",
    "sg:city":"Halifax",
    "sg:classifiers":[
        {
            "category":"Education",
            "subcategory":"School",
            "type":"Public Place"
        }
    ],
    "sg:phone":"+1 902 457 8960",
    "sg:postcode":"B3N 2K2",
    "sg:province":"NS",
    "wof:name":"Fairview Junior High School",
    "wof:placetype":"venue"
},
  "geometry": {"coordinates":[-63.6468811035,44.649143219],"type":"Point"}
}