{
  "type": "Feature",
  "properties": {
    "addr:full":"158 Hunt St Ajax ON L1S 1P5",
    "addr:housenumber":"158",
    "addr:postcode":"l1s 1p5",
    "addr:street":"Hunt St",
    "iso:country":"CA",
    "sg:address":"158 Hunt St",
    "sg:city":"Ajax",
    "sg:classifiers":[
        {
            "category":"Retail",
            "subcategory":"Auto Repair",
            "type":"Services"
        }
    ],
    "sg:phone":"+1 905 683 7591",
    "sg:postcode":"L1S 1P5",
    "sg:province":"ON",
    "sg:tags":[
        "repairing",
        "automobile",
        "lubrication"
    ],
    "wof:name":"Hajson Lube Inc",
    "wof:placetype":"venue"
},
  "geometry": {"coordinates":[-79.025238,43.84639],"type":"Point"}
}