{
  "type": "Feature",
  "properties": {
    "addr:full":"1150 Sheppard Ave W North York ON M3K 2B5",
    "addr:housenumber":"1150",
    "addr:postcode":"m3k 2b5",
    "addr:street":"Sheppard Ave W",
    "iso:country":"CA",
    "sg:address":"1150 Sheppard Ave W",
    "sg:city":"North York",
    "sg:classifiers":[
        {
            "category":"Government",
            "subcategory":"Office",
            "type":"Public Place"
        }
    ],
    "sg:phone":"+1 416 781 1398",
    "sg:postcode":"M3K 2B5",
    "sg:province":"ON",
    "sg:tags":[
        "license"
    ],
    "wof:name":"North York Driver & Vehicle",
    "wof:placetype":"venue"
},
  "geometry": {"coordinates":[-79.468887,43.753735],"type":"Point"}
}