{
  "type": "Feature",
  "properties": {
    "iso:country":"CA",
    "sg:city":"Ottawa",
    "sg:classifiers":[
        {
            "category":"Building & Trades",
            "subcategory":"Construction",
            "type":"Services"
        }
    ],
    "sg:phone":"+1 613 563 8151",
    "sg:postcode":"K1S 3W3",
    "sg:province":"ON",
    "sg:tags":[
        "general",
        "real estate",
        "contractor",
        "developer"
    ],
    "wof:name":"Spaceform Constructors Inc",
    "wof:placetype":"venue"
},
  "geometry": {"coordinates":[-75.6875915527,45.4013404846],"type":"Point"}
}