{
  "type": "Feature",
  "properties": {
    "addr:full":"Mississauga ON L5N 7X8",
    "addr:postcode":"l5n 7x8",
    "iso:country":"CA",
    "sg:city":"Mississauga",
    "sg:classifiers":[
        {
            "category":"Shopping",
            "subcategory":"Clothing, Apparel, & Fashions",
            "type":"Retail Goods"
        }
    ],
    "sg:phone":"+1 905 814 6199",
    "sg:postcode":"L5N 7X8",
    "sg:province":"ON",
    "sg:tags":[
        "furnishing",
        "uniform"
    ],
    "wof:name":"Beatties Mc Kimm Ltd",
    "wof:placetype":"venue"
},
  "geometry": {"coordinates":[-79.775948,43.599499],"type":"Point"}
}