{
  "type": "Feature",
  "properties": {
    "iso:country":"CA",
    "sg:address":"325 Margaret Ave",
    "sg:city":"Wallaceburg",
    "sg:classifiers":[
        {
            "category":"Health Services",
            "subcategory":"Doctor",
            "type":"Services"
        }
    ],
    "sg:phone":"+1 519 628 4134",
    "sg:postcode":"N8A 2A7",
    "sg:province":"ON",
    "sg:tags":[
        "physician",
        "surgeon"
    ],
    "wof:name":"Vaughan, George E R MD",
    "wof:placetype":"venue"
},
  "geometry": {"coordinates":[-82.36688232420001,42.5975074768],"type":"Point"}
}