{
  "type": "Feature",
  "properties": {
    "addr:full":"2885 Laurel Chemainus BC V0R 1K0",
    "addr:housenumber":"2885",
    "addr:postcode":"v0r 1k0",
    "addr:street":"Laurel",
    "iso:country":"CA",
    "sg:address":"2885 Laurel",
    "sg:city":"Chemainus",
    "sg:classifiers":[
        {
            "category":"Restaurant",
            "type":"Food & Drink"
        }
    ],
    "sg:phone":"+1 250 416 0107",
    "sg:postcode":"V0R 1K0",
    "sg:province":"BC",
    "wof:name":"Harborside Cafe",
    "wof:placetype":"venue"
},
  "geometry": {"coordinates":[-123.71874200000001,48.924976],"type":"Point"}
}