{
  "type": "Feature",
  "properties": {
    "iso:country":"CA",
    "sg:city":"Calgary",
    "sg:classifiers":[
        {
            "category":"Wholesale",
            "subcategory":"Groceries",
            "type":"Manufacturing & Wholesale Goods"
        }
    ],
    "sg:phone":"+1 403 720 0703",
    "sg:postcode":"T2C 2E7",
    "sg:province":"AB",
    "sg:tags":[
        "food",
        "broker",
        "meat"
    ],
    "wof:name":"Westrow Food Group",
    "wof:placetype":"venue"
},
  "geometry": {"coordinates":[-113.995040894,50.9797096252],"type":"Point"}
}