{
  "type": "Feature",
  "properties": {
    "addr:full":"Hamilton ON L8L 4J5",
    "addr:postcode":"l8l 4j5",
    "iso:country":"CA",
    "sg:city":"Hamilton",
    "sg:classifiers":[
        {
            "category":"Freight",
            "type":"Transportation"
        }
    ],
    "sg:phone":"+1 905 529 0090",
    "sg:postcode":"L8L 4J5",
    "sg:province":"ON",
    "sg:tags":[
        "laboratory"
    ],
    "wof:name":"Its Caleb Brett",
    "wof:placetype":"venue"
},
  "geometry": {"coordinates":[-79.8357467651,43.2665748596],"type":"Point"}
}