{
  "type": "Feature",
  "properties": {
    "addr:full":"5309 Durham Rd 30 Stouffville ON L4A 7X4",
    "addr:housenumber":"5309;30",
    "addr:postcode":"l4a 7x4",
    "addr:street":"Durham Rd",
    "iso:country":"CA",
    "sg:address":"5309 Durham Rd 30",
    "sg:city":"Stouffville",
    "sg:classifiers":[
        {
            "category":"Wholesale",
            "subcategory":"Farm Supplies",
            "type":"Manufacturing & Wholesale Goods"
        }
    ],
    "sg:phone":"+1 905 640 1583",
    "sg:postcode":"L4A 7X4",
    "sg:province":"ON",
    "wof:name":"Reesor Seed & Grain",
    "wof:placetype":"venue"
},
  "geometry": {"coordinates":[-79.24802398680001,43.9710845947],"type":"Point"}
}