{
  "type": "Feature",
  "properties": {
    "iso:country":"CA",
    "sg:address":"757 Greenbriar Dr",
    "sg:city":"Oshawa",
    "sg:classifiers":[
        {
            "category":"Banks & Credit Unions",
            "subcategory":"Investment Brokerage",
            "type":"Services"
        }
    ],
    "sg:phone":"+1 905 432 3740",
    "sg:postcode":"L1G 7J5",
    "sg:province":"ON",
    "sg:tags":[
        "consultant",
        "planning",
        "financial"
    ],
    "wof:name":"Bothwell, Bob",
    "wof:placetype":"venue"
},
  "geometry": {"coordinates":[-78.8393859863,43.9147605896],"type":"Point"}
}