{
  "type": "Feature",
  "properties": {
    "addr:full":"618 Colborne St Brantford ON N3S 3P7",
    "addr:housenumber":"618",
    "addr:postcode":"n3s 3p7",
    "addr:street":"Colborne St",
    "iso:country":"CA",
    "sg:address":"618 Colborne St",
    "sg:city":"Brantford",
    "sg:classifiers":[
        {
            "category":"Autos & Motor Vehicles",
            "subcategory":"Fuel & Gas Station",
            "type":"Retail Goods"
        }
    ],
    "sg:phone":"+1 519 753 1821",
    "sg:postcode":"N3S 3P7",
    "sg:province":"ON",
    "sg:tags":[
        "oil"
    ],
    "wof:name":"Esso",
    "wof:placetype":"venue"
},
  "geometry": {"coordinates":[-80.24141693120001,43.1404266357],"type":"Point"}
}