{
  "type": "Feature",
  "properties": {
    "addr:full":"Kennetcook NS B0N 1P0",
    "addr:postcode":"b0n 1p0",
    "iso:country":"CA",
    "sg:city":"Kennetcook",
    "sg:classifiers":[
        {
            "category":"Government",
            "subcategory":"Office",
            "type":"Public Place"
        }
    ],
    "sg:phone":"+1 902 362 2246",
    "sg:postcode":"B0N 1P0",
    "sg:province":"NS",
    "wof:name":"Brison, Scott",
    "wof:placetype":"venue"
},
  "geometry": {"coordinates":[-63.721973,45.17746],"type":"Point"}
}