{
  "type": "Feature",
  "properties": {
    "addr:full":"3399 Cambie St Vancouver BC V5Z 2W6",
    "addr:housenumber":"3399",
    "addr:postcode":"v5z 2w6",
    "addr:street":"Cambie St",
    "iso:country":"CA",
    "sg:address":"3399 Cambie St",
    "sg:city":"Vancouver",
    "sg:classifiers":[
        {
            "category":"Food & Beverages",
            "subcategory":"Groceries & Convenience Stores",
            "type":"Retail Goods"
        }
    ],
    "sg:phone":"+1 604 876 1010",
    "sg:postcode":"V5Z 2W6",
    "sg:province":"BC",
    "sg:tags":[
        "grocer"
    ],
    "wof:name":"Cambie General Store",
    "wof:placetype":"venue"
},
  "geometry": {"coordinates":[-123.115272522,49.2551002502],"type":"Point"}
}