{
  "type": "Feature",
  "properties": {
    "addr:full":"1105 Wellington Rd London ON N6E 1V4",
    "addr:housenumber":"1105",
    "addr:postcode":"n6e 1v4",
    "addr:street":"Wellington Rd",
    "iso:country":"CA",
    "sg:address":"1105 Wellington Rd",
    "sg:city":"London",
    "sg:classifiers":[
        {
            "category":"Banks & Credit Unions",
            "subcategory":"Bank",
            "type":"Services"
        }
    ],
    "sg:phone":"+1 519 649 4011",
    "sg:postcode":"N6E 1V4",
    "sg:province":"ON",
    "wof:name":"Royal Bank Financial Group",
    "wof:placetype":"venue"
},
  "geometry": {"coordinates":[-81.2216415405,42.9316215515],"type":"Point"}
}