{
  "type": "Feature",
  "properties": {
    "addr:full":"555 Main St W North Bay ON P1B 2V3",
    "addr:housenumber":"555",
    "addr:postcode":"p1b 2v3",
    "addr:street":"Main St W",
    "iso:country":"CA",
    "sg:address":"555 Main St W",
    "sg:city":"North Bay",
    "sg:classifiers":[
        {
            "category":"Social Services",
            "type":"Services"
        }
    ],
    "sg:phone":"+1 705 471 0437",
    "sg:postcode":"P1B 2V3",
    "sg:province":"ON",
    "sg:tags":[
        "counselor",
        "marriage",
        "family"
    ],
    "wof:name":"Beaudoin, Julie",
    "wof:placetype":"venue"
},
  "geometry": {"coordinates":[-79.4691696167,46.315612793],"type":"Point"}
}