{
  "type": "Feature",
  "properties": {
    "iso:country":"CA",
    "sg:city":"Calgary",
    "sg:classifiers":[
        {
            "category":"Real Estate",
            "subcategory":"Real Estate Operator",
            "type":"Services"
        }
    ],
    "sg:phone":"+1 403 239 1600",
    "sg:postcode":"T3G 1P3",
    "sg:province":"AB",
    "sg:tags":[
        "apartment"
    ],
    "wof:name":"Raintree Village",
    "wof:placetype":"venue"
},
  "geometry": {"coordinates":[-114.17704773,51.1153068542],"type":"Point"}
}