{
  "type": "Feature",
  "properties": {
    "addr:full":"25 Old York Mills Rd North York ON M2P 1B5",
    "addr:housenumber":"25",
    "addr:postcode":"m2p 1b5",
    "addr:street":"Old York Mills Rd",
    "iso:country":"CA",
    "sg:address":"25 Old York Mills Rd",
    "sg:city":"North York",
    "sg:classifiers":[
        {
            "category":"Organizations",
            "subcategory":"Religious Organization",
            "type":"Services"
        }
    ],
    "sg:phone":"+1 416 486 0466",
    "sg:postcode":"M2P 1B5",
    "sg:province":"ON",
    "sg:tags":[
        "church"
    ],
    "wof:name":"Swedish Lutheran Church",
    "wof:placetype":"venue"
},
  "geometry": {"coordinates":[-79.404602,43.743553],"type":"Point"}
}