{
  "type": "Feature",
  "properties": {
    "addr:full":"Collins Armstrong Station ON P0T 1A0",
    "addr:postcode":"p0t 1a0",
    "iso:country":"CA",
    "sg:address":"Collins",
    "sg:city":"Armstrong Station",
    "sg:classifiers":[
        {
            "category":"Education",
            "subcategory":"School",
            "type":"Public Place"
        }
    ],
    "sg:phone":"+1 807 583 2593",
    "sg:postcode":"P0T 1A0",
    "sg:province":"ON",
    "wof:name":"Bernier Stokes Public School",
    "wof:placetype":"venue"
},
  "geometry": {"coordinates":[-89.0389633179,50.3039283752],"type":"Point"}
}