{
  "type": "Feature",
  "properties": {
    "iso:country":"CA",
    "sg:address":"217 169 Rte",
    "sg:city":"Albanel",
    "sg:classifiers":[
        {
            "category":"Building & Trades",
            "subcategory":"Construction",
            "type":"Services"
        }
    ],
    "sg:phone":"+1 418 276 5811",
    "sg:postcode":"G8M 3N6",
    "sg:province":"QC",
    "sg:tags":[
        "insulation",
        "repairing",
        "remodeling",
        "contractor"
    ],
    "wof:name":"Isolation Fortin Inc",
    "wof:placetype":"venue"
},
  "geometry": {"coordinates":[-72.4411849976,48.8838195801],"type":"Point"}
}