{
  "type": "Feature",
  "properties": {
    "addr:full":"364 1st Ave S Chesley ON N0G 1L0",
    "addr:housenumber":"364",
    "addr:postcode":"n0g 1l0",
    "addr:street":"1St Ave S Chesley",
    "iso:country":"CA",
    "sg:address":"364 1st Ave S",
    "sg:city":"Chesley",
    "sg:classifiers":[
        {
            "category":"Restaurant",
            "type":"Food & Drink"
        }
    ],
    "sg:phone":"+1 519 363 9851",
    "sg:postcode":"N0G 1L0",
    "sg:province":"ON",
    "wof:name":"Rhoda's Drive in",
    "wof:placetype":"venue"
},
  "geometry": {"coordinates":[-81.093216,44.290363],"type":"Point"}
}