{
  "type": "Feature",
  "properties": {
    "addr:full":"Grand Marais MB R0E 0T0",
    "addr:postcode":"r0e 0t0",
    "iso:country":"CA",
    "sg:city":"Grand Marais",
    "sg:classifiers":[
        {
            "category":"Restaurant",
            "type":"Food & Drink"
        }
    ],
    "sg:phone":"+1 204 754 3603",
    "sg:postcode":"R0E 0T0",
    "sg:province":"MB",
    "wof:name":"Blue Hound Grill Inc",
    "wof:placetype":"venue"
},
  "geometry": {"coordinates":[-96.681145,49.539619],"type":"Point"}
}