{
  "type": "Feature",
  "properties": {
    "iso:country":"CA",
    "sg:city":"St Catharines",
    "sg:classifiers":[
        {
            "category":"Professional",
            "subcategory":"Lawyer & Legal Services",
            "type":"Services"
        }
    ],
    "sg:phone":"+1 905 641 2020",
    "sg:postcode":"L2R 3H5",
    "sg:province":"ON",
    "sg:tags":[
        "attorney"
    ],
    "wof:name":"Richard, Christopher",
    "wof:placetype":"venue"
},
  "geometry": {"coordinates":[-79.24678,43.157845],"type":"Point"}
}