{
  "type": "Feature",
  "properties": {
    "iso:country":"CA",
    "sg:city":"Burnaby",
    "sg:classifiers":[
        {
            "category":"Building & Trades",
            "subcategory":"Construction",
            "type":"Services"
        }
    ],
    "sg:phone":"+1 604 298 7782",
    "sg:postcode":"V5B 1S9",
    "sg:province":"BC",
    "sg:tags":[
        "insulation",
        "heat",
        "contractor"
    ],
    "wof:name":"Capitol Hill Contracting Ltd",
    "wof:placetype":"venue"
},
  "geometry": {"coordinates":[-122.960647583,49.2802429199],"type":"Point"}
}