{
  "type": "Feature",
  "properties": {
    "addr:full":"Langley BC V3A 2P1",
    "addr:postcode":"v3a 2p1",
    "iso:country":"CA",
    "sg:city":"Langley",
    "sg:classifiers":[
        {
            "category":"Health Services",
            "subcategory":"Chiropractor",
            "type":"Services"
        }
    ],
    "sg:phone":"+1 604 532 9887",
    "sg:postcode":"V3A 2P1",
    "sg:province":"BC",
    "wof:name":"Murrayville Chiropractic",
    "wof:placetype":"venue"
},
  "geometry": {"coordinates":[-122.611732483,49.0901412964],"type":"Point"}
}