{
  "type": "Feature",
  "properties": {
    "addr:full":"60 Esna Park Dr Markham ON L3R 1E1",
    "addr:housenumber":"60",
    "addr:postcode":"l3r 1e1",
    "addr:street":"Esna Park Dr",
    "iso:country":"CA",
    "sg:address":"60 Esna Park Dr",
    "sg:city":"Markham",
    "sg:classifiers":[
        {
            "category":"Building & Trades",
            "subcategory":"Electrical",
            "type":"Services"
        }
    ],
    "sg:phone":"+1 905 475 6650",
    "sg:postcode":"L3R 1E1",
    "sg:province":"ON",
    "sg:tags":[
        "electric",
        "contractor"
    ],
    "wof:name":"Standard Electric Inc",
    "wof:placetype":"venue"
},
  "geometry": {"coordinates":[-79.343315,43.827721],"type":"Point"}
}