{
  "type": "Feature",
  "properties": {
    "iso:country":"CA",
    "sg:address":"60 Esna Park Dr",
    "sg:city":"Markham",
    "sg:classifiers":[
        {
            "category":"Building & Trades",
            "subcategory":"Electrical",
            "type":"Services"
        }
    ],
    "sg:phone":"+1 905 475 6650",
    "sg:postcode":"L3R 1E1",
    "sg:province":"ON",
    "sg:tags":[
        "electric",
        "contractor"
    ],
    "wof:name":"Standard Electric Inc",
    "wof:placetype":"venue"
},
  "geometry": {"coordinates":[-79.343315,43.827721],"type":"Point"}
}