{
  "type": "Feature",
  "properties": {
    "iso:country":"CA",
    "sg:address":"6374 Campbell Rd",
    "sg:city":"Chetwynd",
    "sg:classifiers":[
        {
            "category":"Building & Trades",
            "subcategory":"Plumbing",
            "type":"Services"
        }
    ],
    "sg:phone":"+1 250 788 9105",
    "sg:postcode":"V0C 1J0",
    "sg:province":"BC",
    "sg:tags":[
        "conditioning",
        "air",
        "system",
        "contractor"
    ],
    "wof:name":"Northern Xposure Mechanical",
    "wof:placetype":"venue"
},
  "geometry": {"coordinates":[-121.627746582,55.6975326538],"type":"Point"}
}