{
  "type": "Feature",
  "properties": {
    "iso:country":"CA",
    "sg:address":"9630 Boul Saint-Laurent",
    "sg:city":"Montreal",
    "sg:classifiers":[
        {
            "category":"Wholesale",
            "subcategory":"Apparel",
            "type":"Manufacturing & Wholesale Goods"
        }
    ],
    "sg:phone":"+1 514 389 8293",
    "sg:postcode":"H2N 1R1",
    "sg:province":"QC",
    "sg:tags":[
        "textile"
    ],
    "wof:name":"Tonitex Inc",
    "wof:placetype":"venue"
},
  "geometry": {"coordinates":[-73.65632629389999,45.5459518433],"type":"Point"}
}