{
  "type": "Feature",
  "properties": {
    "addr:full":"Kamloops BC V2C 1Z5",
    "addr:postcode":"bc v2c 1z5",
    "iso:country":"CA",
    "sg:city":"Kamloops",
    "sg:classifiers":[
        {
            "category":"Personal",
            "type":"Services"
        }
    ],
    "sg:phone":"+1 250 851 0078",
    "sg:postcode":"V2C 1Z5",
    "sg:province":"BC",
    "sg:tags":[
        "shopping"
    ],
    "wof:name":"In Home Care Inc",
    "wof:placetype":"venue"
},
  "geometry": {"coordinates":[-120.338119507,50.6760292053],"type":"Point"}
}