{
  "type": "Feature",
  "properties": {
    "addr:full":"10415 89 Ave Fort St John BC V1J 5P8",
    "addr:housenumber":"10415",
    "addr:postcode":"v1j 5p8",
    "addr:street":"89 Ave",
    "iso:country":"CA",
    "sg:address":"10415 89 Ave",
    "sg:city":"Fort St John",
    "sg:classifiers":[
        {
            "category":"Wholesale",
            "subcategory":"Chemicals & Plastics",
            "type":"Manufacturing & Wholesale Goods"
        }
    ],
    "sg:phone":"+1 250 785 2379",
    "sg:postcode":"V1J 5P8",
    "sg:province":"BC",
    "wof:name":"Baker Petrolite",
    "wof:placetype":"venue"
},
  "geometry": {"coordinates":[-120.855171,56.235485],"type":"Point"}
}