{
  "type": "Feature",
  "properties": {
    "iso:country":"CA",
    "sg:city":"Castlegar",
    "sg:classifiers":[
        {
            "category":"Banks & Credit Unions",
            "subcategory":"Investment Brokerage",
            "type":"Services"
        }
    ],
    "sg:phone":"+1 250 365 0095",
    "sg:postcode":"V1N 4G7",
    "sg:province":"BC",
    "sg:tags":[
        "consultant",
        "planning",
        "financial"
    ],
    "wof:name":"Growth Financial Corp",
    "wof:placetype":"venue"
},
  "geometry": {"coordinates":[-117.655090332,49.3011665344],"type":"Point"}
}