{
  "type": "Feature",
  "properties": {
    "iso:country":"CA",
    "sg:city":"Longueuil",
    "sg:classifiers":[
        {
            "category":"Banks & Credit Unions",
            "subcategory":"Financial Services",
            "type":"Services"
        }
    ],
    "sg:phone":"+1 450 545 1070",
    "sg:postcode":"J4H 4B9",
    "sg:province":"QC",
    "sg:tags":[
        "bankruptcy",
        "consultant",
        "management",
        "business",
        "trustee"
    ],
    "wof:name":"Primeau Proulx & Assoc Inc",
    "wof:placetype":"venue"
},
  "geometry": {"coordinates":[-73.4965515137,45.5493011475],"type":"Point"}
}