{
  "type": "Feature",
  "properties": {
    "addr:full":"580 Rue Saint-Georges Saint-Jerome QC J7Z 5B8",
    "addr:housenumber":"580",
    "addr:postcode":"j7z 5b8",
    "addr:street":"Rue Saint-Georges Saint-Jerome",
    "iso:country":"CA",
    "sg:address":"580 Rue Saint-Georges",
    "sg:city":"Saint-Jerome",
    "sg:classifiers":[
        {
            "category":"Health Services",
            "subcategory":"Health Practitioner",
            "type":"Services"
        }
    ],
    "sg:phone":"+1 450 602 7050",
    "sg:postcode":"J7Z 5B8",
    "sg:province":"QC",
    "sg:tags":[
        "psychotherapist"
    ],
    "wof:name":"Berube, Jacques",
    "wof:placetype":"venue"
},
  "geometry": {"coordinates":[-74.00178527830001,45.7835044861],"type":"Point"}
}