{
  "type": "Feature",
  "properties": {
    "iso:country":"CA",
    "sg:address":"101 Boul Champlain",
    "sg:city":"Quebec",
    "sg:classifiers":[
        {
            "category":"Wholesale",
            "subcategory":"Groceries",
            "type":"Manufacturing & Wholesale Goods"
        }
    ],
    "sg:phone":"+1 418 647 4353",
    "sg:postcode":"G1K 4H9",
    "sg:province":"QC",
    "sg:tags":[
        "salt"
    ],
    "wof:name":"Mines Seleine Inc",
    "wof:placetype":"venue"
},
  "geometry": {"coordinates":[-71.2031555176,46.8091888428],"type":"Point"}
}