{
  "type": "Feature",
  "properties": {
    "addr:full":"29 Mccullough St Marathon ON P0T 2E0",
    "addr:housenumber":"29",
    "addr:postcode":"p0t 2e0",
    "addr:street":"Mccullough St",
    "iso:country":"CA",
    "sg:address":"29 Mccullough St",
    "sg:city":"Marathon",
    "sg:classifiers":[
        {
            "category":"Retail",
            "subcategory":"Laundry & Dry Cleaning",
            "type":"Services"
        }
    ],
    "sg:phone":"+1 807 229 2256",
    "sg:postcode":"P0T 2E0",
    "sg:province":"ON",
    "sg:tags":[
        "cleaners",
        "janitor",
        "rug",
        "carpet"
    ],
    "wof:name":"Dust Buster Cleaning",
    "wof:placetype":"venue"
},
  "geometry": {"coordinates":[-86.38490299999999,48.718369],"type":"Point"}
}