{
  "type": "Feature",
  "properties": {
    "addr:full":"Fox Creek AB T0H 1P0",
    "addr:postcode":"t0h 1p0",
    "iso:country":"CA",
    "sg:city":"Fox Creek",
    "sg:classifiers":[
        {
            "category":"Mining & Drilling",
            "type":"Manufacturing & Wholesale Goods"
        }
    ],
    "sg:phone":"+1 780 622 2216",
    "sg:postcode":"T0H 1P0",
    "sg:province":"AB",
    "sg:tags":[
        "field",
        "oil"
    ],
    "wof:name":"New Adventure Trucking",
    "wof:placetype":"venue"
},
  "geometry": {"coordinates":[-117.629310608,56.9252319336],"type":"Point"}
}