{
  "type": "Feature",
  "properties": {
    "addr:full":"5679 Place Leon-Methot Trois-Rivieres QC G8Y 5S9",
    "addr:housenumber":"5679",
    "addr:postcode":"g8y 5s9",
    "addr:street":"Place Leon-Methot Trois-Rivieres",
    "iso:country":"CA",
    "sg:address":"5679 Place Leon-Methot",
    "sg:city":"Trois-Rivieres",
    "sg:classifiers":[
        {
            "category":"Health Services",
            "subcategory":"Health Practitioner",
            "type":"Services"
        }
    ],
    "sg:phone":"+1 819 373 7094",
    "sg:postcode":"G8Y 5S9",
    "sg:province":"QC",
    "sg:tags":[
        "psychologist",
        "therapist",
        "massage"
    ],
    "wof:name":"Clinique DE Sante Psycho",
    "wof:placetype":"venue"
},
  "geometry": {"coordinates":[-72.597511,46.363503],"type":"Point"}
}