{
  "type": "Feature",
  "properties": {
    "addr:full":"2212 9 Ave SE Calgary AB T2G 5P7",
    "addr:housenumber":"2212",
    "addr:postcode":"t2g 5p7",
    "addr:street":"9 Ave Se",
    "iso:country":"CA",
    "sg:address":"2212 9 Ave SE",
    "sg:city":"Calgary",
    "sg:classifiers":[
        {
            "category":"Professional",
            "subcategory":"Employment Agencies",
            "type":"Services"
        }
    ],
    "sg:phone":"+1 403 289 5802",
    "sg:postcode":"T2G 5P7",
    "sg:province":"AB",
    "sg:tags":[
        "opportunity"
    ],
    "wof:name":"Bailey Professional Search",
    "wof:placetype":"venue"
},
  "geometry": {"coordinates":[-114.013786,51.032715],"type":"Point"}
}