{
  "type": "Feature",
  "properties": {
    "addr:full":"110 Ch Des Forts St-Joseph-DE-LA-Pointe-DE-Levy QC G6V 6N4",
    "addr:housenumber":"110",
    "addr:postcode":"g6v 6n4",
    "addr:street":"Ch Des Forts St-Joseph-De-La-Pointe-De-Levy",
    "iso:country":"CA",
    "sg:address":"110 Ch Des Forts",
    "sg:city":"St-Joseph-DE-LA-Pointe-DE-Levy",
    "sg:classifiers":[
        {
            "category":"Building & Trades",
            "subcategory":"Electrical",
            "type":"Services"
        }
    ],
    "sg:phone":"+1 418 837 4979",
    "sg:postcode":"G6V 6N4",
    "sg:province":"QC",
    "sg:tags":[
        "electric",
        "contractor"
    ],
    "wof:name":"Entreprises D'Elec G Belanger",
    "wof:placetype":"venue"
},
  "geometry": {"coordinates":[-71.128227,46.794746],"type":"Point"}
}