{
  "type": "Feature",
  "properties": {
    "iso:country":"CA",
    "sg:address":"34800 Mierau St",
    "sg:city":"Abbotsford",
    "sg:classifiers":[
        {
            "category":"Education",
            "subcategory":"School",
            "type":"Public Place"
        }
    ],
    "sg:phone":"+1 604 850 1615",
    "sg:postcode":"V2S 5Y4",
    "sg:province":"BC",
    "wof:name":"Special Education",
    "wof:placetype":"venue"
},
  "geometry": {"coordinates":[-122.260826111,49.0664787292],"type":"Point"}
}