{
  "type": "Feature",
  "properties": {
    "addr:full":"494 Goodwin Rd Campbell River BC V9W 6R7",
    "addr:housenumber":"494",
    "addr:postcode":"v9w 6r7",
    "addr:street":"Goodwin Rd",
    "iso:country":"CA",
    "sg:address":"494 Goodwin Rd",
    "sg:city":"Campbell River",
    "sg:classifiers":[
        {
            "category":"Building & Trades",
            "subcategory":"Construction",
            "type":"Services"
        }
    ],
    "sg:phone":"+1 250 923 6952",
    "sg:postcode":"V9W 6R7",
    "sg:province":"BC",
    "sg:tags":[
        "excavating",
        "contractor"
    ],
    "wof:name":"Emerald Excavating",
    "wof:placetype":"venue"
},
  "geometry": {"coordinates":[-125.23661041299999,49.9712677002],"type":"Point"}
}