{
  "type": "Feature",
  "properties": {
    "iso:country":"CA",
    "sg:address":"9721 90 St",
    "sg:city":"Fort Saskatchewan",
    "sg:classifiers":[
        {
            "category":"Restaurant",
            "type":"Food & Drink"
        }
    ],
    "sg:phone":"+1 780 998 9550",
    "sg:postcode":"T8L 1K5",
    "sg:province":"AB",
    "wof:name":"Rainbow Restaurant",
    "wof:placetype":"venue"
},
  "geometry": {"coordinates":[-113.22992706300001,53.6982269287],"type":"Point"}
}