{
  "type": "Feature",
  "properties": {
    "addr:full":"9721 90 St Fort Saskatchewan AB T8L 1K5",
    "addr:housenumber":"9721",
    "addr:postcode":"t8l 1k5",
    "addr:street":"90 St",
    "iso:country":"CA",
    "sg:address":"9721 90 St",
    "sg:city":"Fort Saskatchewan",
    "sg:classifiers":[
        {
            "category":"Restaurant",
            "type":"Food & Drink"
        }
    ],
    "sg:phone":"+1 780 998 9550",
    "sg:postcode":"T8L 1K5",
    "sg:province":"AB",
    "wof:name":"Rainbow Restaurant",
    "wof:placetype":"venue"
},
  "geometry": {"coordinates":[-113.22992706300001,53.6982269287],"type":"Point"}
}