{
  "type": "Feature",
  "properties": {
    "iso:country":"CA",
    "sg:address":"7046 Rue Saint-Urbain",
    "sg:city":"Montreal",
    "sg:classifiers":[
        {
            "category":"Retail",
            "subcategory":"Auto Repair",
            "type":"Services"
        }
    ],
    "sg:phone":"+1 514 274 4642",
    "sg:postcode":"H2S 3H5",
    "sg:province":"QC",
    "sg:tags":[
        "transmission"
    ],
    "wof:name":"Laurier Transmission & Dfrntl",
    "wof:placetype":"venue"
},
  "geometry": {"coordinates":[-73.617348,45.532471],"type":"Point"}
}