{
  "type": "Feature",
  "properties": {
    "addr:full":"157 Thomson Ave Regina SK S4N 5L2",
    "addr:housenumber":"157",
    "addr:postcode":"s4n 5l2",
    "addr:street":"Thomson Ave",
    "iso:country":"CA",
    "sg:address":"157 Thomson Ave",
    "sg:city":"Regina",
    "sg:classifiers":[
        {
            "category":"Organizations",
            "subcategory":"Religious Organization",
            "type":"Services"
        }
    ],
    "sg:phone":"+1 306 337 2843",
    "sg:postcode":"S4N 5L2",
    "sg:province":"SK",
    "sg:tags":[
        "church"
    ],
    "wof:name":"St George's Church",
    "wof:placetype":"venue"
},
  "geometry": {"coordinates":[-104.543488,50.451729],"type":"Point"}
}