{
  "type": "Feature",
  "properties": {
    "addr:full":"1096 Broadway W Vancouver BC V6H 1E6",
    "addr:housenumber":"1096",
    "addr:postcode":"v6h 1e6",
    "addr:street":"Broadway W",
    "iso:country":"CA",
    "sg:address":"1096 Broadway W",
    "sg:city":"Vancouver",
    "sg:classifiers":[
        {
            "category":"Retail",
            "subcategory":"Funeral Services",
            "type":"Services"
        }
    ],
    "sg:phone":"+1 604 736 0268",
    "sg:postcode":"V6H 1E6",
    "sg:province":"BC",
    "sg:tags":[
        "director"
    ],
    "wof:name":"Kearney Funeral Svc",
    "wof:placetype":"venue"
},
  "geometry": {"coordinates":[-123.128715515,49.2633171082],"type":"Point"}
}