{
  "type": "Feature",
  "properties": {
    "addr:full":"10019 Macdonald Ave Fort Mcmurray AB T9H 1S9",
    "addr:housenumber":"10019",
    "addr:postcode":"t9h 1s9",
    "addr:street":"Macdonald Ave",
    "iso:country":"CA",
    "sg:address":"10019 Macdonald Ave",
    "sg:city":"Fort Mcmurray",
    "sg:classifiers":[
        {
            "category":"Shopping",
            "subcategory":"Bicycles & Sporting Goods",
            "type":"Retail Goods"
        }
    ],
    "sg:phone":"+1 780 743 8888",
    "sg:postcode":"T9H 1S9",
    "sg:province":"AB",
    "wof:name":"Sport Wise Inc",
    "wof:placetype":"venue"
},
  "geometry": {"coordinates":[-111.383460998,56.72706604],"type":"Point"}
}