{
  "type": "Feature",
  "properties": {
    "addr:full":"115 Broadway St Carnduff SK S0C 0S0",
    "addr:housenumber":"115",
    "addr:postcode":"s0c 0s0",
    "addr:street":"Broadway St",
    "iso:country":"CA",
    "sg:address":"115 Broadway St",
    "sg:city":"Carnduff",
    "sg:classifiers":[
        {
            "category":"Home & Garden",
            "subcategory":"Hardware",
            "type":"Retail Goods"
        }
    ],
    "sg:phone":"+1 306 482 3403",
    "sg:postcode":"S0C 0S0",
    "sg:province":"SK",
    "wof:name":"Mac Leods True Value",
    "wof:placetype":"venue"
},
  "geometry": {"coordinates":[-101.799049377,49.1772232056],"type":"Point"}
}