{
  "type": "Feature",
  "properties": {
    "addr:full":"Qualicum Beach BC V9K 1W5",
    "addr:postcode":"v9k 1w5",
    "iso:country":"CA",
    "sg:city":"Qualicum Beach",
    "sg:classifiers":[
        {
            "category":"Retail",
            "subcategory":"Animal Services",
            "type":"Services"
        }
    ],
    "sg:phone":"+1 250 752 6583",
    "sg:postcode":"V9K 1W5",
    "sg:province":"BC",
    "sg:tags":[
        "pet",
        "boarding",
        "shelter",
        "sitting"
    ],
    "wof:name":"Cats Only Boarding Cattery",
    "wof:placetype":"venue"
},
  "geometry": {"coordinates":[-124.44561,49.299461],"type":"Point"}
}