{
  "type": "Feature",
  "properties": {
    "addr:full":"Midland ON L4R 4K4",
    "addr:postcode":"l4r 4k4",
    "iso:country":"CA",
    "sg:city":"Midland",
    "sg:classifiers":[
        {
            "category":"Shopping",
            "subcategory":"Gifts & Souvenirs",
            "type":"Retail Goods"
        }
    ],
    "sg:phone":"+1 705 526 4710",
    "sg:postcode":"L4R 4K4",
    "sg:province":"ON",
    "sg:tags":[
        "cards",
        "greeting"
    ],
    "wof:name":"Carlton Cards",
    "wof:placetype":"venue"
},
  "geometry": {"coordinates":[-79.89306640620001,44.70911026],"type":"Point"}
}