{
  "type": "Feature",
  "properties": {
    "addr:full":"347 Binns Ave Newmarket ON L3X 1T6",
    "addr:housenumber":"347",
    "addr:postcode":"l3x 1t6",
    "addr:street":"Binns Ave",
    "iso:country":"CA",
    "sg:address":"347 Binns Ave",
    "sg:city":"Newmarket",
    "sg:classifiers":[
        {
            "category":"Professional",
            "subcategory":"Accounting & Tax Preparation",
            "type":"Services"
        }
    ],
    "sg:phone":"+1 905 898 2442",
    "sg:postcode":"L3X 1T6",
    "sg:province":"ON",
    "sg:tags":[
        "accountant"
    ],
    "wof:name":"Mc Ilmoyle, Glenn R",
    "wof:placetype":"venue"
},
  "geometry": {"coordinates":[-79.4982833862,44.0427589417],"type":"Point"}
}