{
  "type": "Feature",
  "properties": {
    "addr:full":"1646 Landry Rd Clarence Creek ON K0A 1N0",
    "addr:postcode":"1646;k0a 1n0",
    "addr:street":"Landry Rd",
    "iso:country":"CA",
    "sg:address":"1646 Landry Rd",
    "sg:city":"Clarence Creek",
    "sg:classifiers":[
        {
            "category":"Organizations",
            "subcategory":"Religious Organization",
            "type":"Services"
        }
    ],
    "sg:phone":"+1 613 488 2000",
    "sg:postcode":"K0A 1N0",
    "sg:province":"ON",
    "sg:tags":[
        "church"
    ],
    "wof:name":"Paroisse Ste Felicite",
    "wof:placetype":"venue"
},
  "geometry": {"coordinates":[-75.220787,45.508198],"type":"Point"}
}