{
  "type": "Feature",
  "properties": {
    "iso:country":"CA",
    "sg:address":"1818 3rd St",
    "sg:city":"Estevan",
    "sg:phone":"+1 306 634 6866",
    "sg:postcode":"S4A 0T2",
    "sg:province":"SK",
    "sg:tags":[
        "oil"
    ],
    "wof:name":"Ensco Additives",
    "wof:placetype":"venue"
},
  "geometry": {"coordinates":[-103.008247376,49.1441841125],"type":"Point"}
}