{
  "type": "Feature",
  "properties": {
    "addr:full":"506 4 Ave S Lethbridge AB T1J 0N5",
    "addr:housenumber":"506",
    "addr:postcode":"t1j 0n5",
    "addr:street":"4 Ave S",
    "iso:country":"CA",
    "sg:address":"506 4 Ave S",
    "sg:city":"Lethbridge",
    "sg:classifiers":[
        {
            "category":"Education",
            "subcategory":"Special Training",
            "type":"Public Place"
        }
    ],
    "sg:phone":"+1 403 320 2057",
    "sg:postcode":"T1J 0N5",
    "sg:province":"AB",
    "sg:tags":[
        "school",
        "language"
    ],
    "wof:name":"Flexibility Learning Systems",
    "wof:placetype":"venue"
},
  "geometry": {"coordinates":[-112.83988952599999,49.6941833496],"type":"Point"}
}