{
  "type": "Feature",
  "properties": {
    "iso:country":"CA",
    "sg:address":"966 Pantera Dr",
    "sg:city":"Mississauga",
    "sg:classifiers":[
        {
            "category":"Professional",
            "subcategory":"Management & Consulting",
            "type":"Services"
        }
    ],
    "sg:phone":"+1 905 624 4848",
    "sg:postcode":"L4W 2S1",
    "sg:province":"ON",
    "sg:tags":[
        "consultant",
        "business"
    ],
    "wof:name":"Albert Joseph Longo Ltd",
    "wof:placetype":"venue"
},
  "geometry": {"coordinates":[-79.63837432859999,43.6301269531],"type":"Point"}
}