{
  "type": "Feature",
  "properties": {
    "addr:full":"1142 Alloy Dr Thunder Bay ON P7B 6M9",
    "addr:housenumber":"1142",
    "addr:postcode":"p7b 6m9",
    "addr:street":"Alloy Dr",
    "iso:country":"CA",
    "sg:address":"1142 Alloy Dr",
    "sg:city":"Thunder Bay",
    "sg:classifiers":[
        {
            "category":"Autos & Motor Vehicles",
            "subcategory":"Automobile Sales",
            "type":"Retail Goods"
        }
    ],
    "sg:phone":"+1 807 346 5809",
    "sg:postcode":"P7B 6M9",
    "sg:province":"ON",
    "sg:tags":[
        "car",
        "dealer"
    ],
    "wof:name":"Marostica Motors Ltd",
    "wof:placetype":"venue"
},
  "geometry": {"coordinates":[-89.2589645386,48.4088668823],"type":"Point"}
}