{
  "type": "Feature",
  "properties": {
    "addr:full":"2240 Keating Cross Rd Saanichton BC V8M 2A6",
    "addr:housenumber":"2240",
    "addr:postcode":"v8m 2a6",
    "addr:street":"Keating Cross Rd",
    "iso:country":"CA",
    "sg:address":"2240 Keating Cross Rd",
    "sg:city":"Saanichton",
    "sg:classifiers":[
        {
            "category":"Wholesale",
            "subcategory":"Scrap",
            "type":"Manufacturing & Wholesale Goods"
        }
    ],
    "sg:phone":"+1 250 652 4414",
    "sg:postcode":"V8M 2A6",
    "sg:province":"BC",
    "sg:tags":[
        "recycling",
        "center"
    ],
    "wof:name":"Bfi Canada",
    "wof:placetype":"venue"
},
  "geometry": {"coordinates":[-123.416893,48.5952],"type":"Point"}
}