{
  "type": "Feature",
  "properties": {
    "addr:full":"445 Rue Papin Sainte-Foy QC G1P 3T8",
    "addr:housenumber":"445",
    "addr:postcode":"g1p 3t8",
    "addr:street":"Rue Papin",
    "iso:country":"CA",
    "sg:address":"445 Rue Papin",
    "sg:city":"Sainte-Foy",
    "sg:classifiers":[
        {
            "category":"Building & Trades",
            "subcategory":"Construction",
            "type":"Services"
        }
    ],
    "sg:phone":"+1 418 652 1144",
    "sg:postcode":"G1P 3T8",
    "sg:province":"QC",
    "sg:tags":[
        "acoustical",
        "contractor",
        "general"
    ],
    "wof:name":"Matrex Acoustique Inc",
    "wof:placetype":"venue"
},
  "geometry": {"coordinates":[-71.2996139526,46.7907028198],"type":"Point"}
}