{
  "type": "Feature",
  "properties": {
    "addr:full":"1920 Francis St Regina SK S4N 6B3",
    "addr:housenumber":"1920",
    "addr:postcode":"s4n 6b3",
    "addr:street":"Francis St",
    "iso:country":"CA",
    "sg:address":"1920 Francis St",
    "sg:city":"Regina",
    "sg:classifiers":[
        {
            "category":"Retail",
            "subcategory":"Car Wash",
            "type":"Services"
        }
    ],
    "sg:phone":"+1 306 569 9274",
    "sg:postcode":"S4N 6B3",
    "sg:province":"SK",
    "sg:tags":[
        "polishing",
        "washing"
    ],
    "wof:name":"Magic Wand Car Wash",
    "wof:placetype":"venue"
},
  "geometry": {"coordinates":[-104.579521,50.44849],"type":"Point"}
}