{
  "type": "Feature",
  "properties": {
    "addr:full":"Hillcrest Access Rd Hillcrest Mines AB T0K 1C0",
    "addr:postcode":"t0k 1c0",
    "addr:street":"Hillcrest Access Rd",
    "iso:country":"CA",
    "sg:address":"Hillcrest Access Rd",
    "sg:city":"Hillcrest Mines",
    "sg:classifiers":[
        {
            "category":"Home & Garden",
            "subcategory":"Garden Supply",
            "type":"Retail Goods"
        }
    ],
    "sg:phone":"+1 403 564 4964",
    "sg:postcode":"T0K 1C0",
    "sg:province":"AB",
    "sg:tags":[
        "nurseryman",
        "center"
    ],
    "wof:name":"Crowsnest Greenhouses & Garden",
    "wof:placetype":"venue"
},
  "geometry": {"coordinates":[-114.37668600000001,49.570126],"type":"Point"}
}