{
  "type": "Feature",
  "properties": {
    "addr:full":"595 Harmston Ave Courtenay BC V9N 2X4",
    "addr:housenumber":"595",
    "addr:postcode":"v9n 2x4",
    "addr:street":"Harmston Ave",
    "iso:country":"CA",
    "sg:address":"595 Harmston Ave",
    "sg:city":"Courtenay",
    "sg:classifiers":[
        {
            "category":"Social Services",
            "subcategory":"Child Care",
            "type":"Services"
        }
    ],
    "sg:phone":"+1 250 703 0125",
    "sg:postcode":"V9N 2X4",
    "sg:province":"BC",
    "wof:name":"Willow Day Care",
    "wof:placetype":"venue"
},
  "geometry": {"coordinates":[-125.003189087,49.6885147095],"type":"Point"}
}