{
  "type": "Feature",
  "properties": {
    "addr:full":"6392 Egrement Dr Komoka ON N0L 1R0",
    "addr:postcode":"6392;n0l 1r0",
    "addr:street":"Egrement Dr",
    "iso:country":"CA",
    "sg:address":"6392 Egrement Dr",
    "sg:city":"Komoka",
    "sg:classifiers":[
        {
            "category":"Autos & Motor Vehicles",
            "subcategory":"Boat Sales",
            "type":"Retail Goods"
        }
    ],
    "sg:phone":"+1 519 666 1354",
    "sg:postcode":"N0L 1R0",
    "sg:province":"ON",
    "sg:tags":[
        "top",
        "upholstery",
        "cover",
        "upholsterer"
    ],
    "wof:name":"Kury Kraft Upholstery",
    "wof:placetype":"venue"
},
  "geometry": {"coordinates":[-81.42195129389999,43.0002593994],"type":"Point"}
}