{
  "type": "Feature",
  "properties": {
    "addr:full":"37 Gore St E Perth ON K7H 1H4",
    "addr:housenumber":"37",
    "addr:postcode":"k7h 1h4",
    "addr:street":"Gore St E",
    "iso:country":"CA",
    "sg:address":"37 Gore St E",
    "sg:city":"Perth",
    "sg:classifiers":[
        {
            "category":"Shopping",
            "subcategory":"Shoes",
            "type":"Retail Goods"
        }
    ],
    "sg:phone":"+1 613 267 2544",
    "sg:postcode":"K7H 1H4",
    "sg:province":"ON",
    "wof:name":"Wiseman's Shoe Store",
    "wof:placetype":"venue"
},
  "geometry": {"coordinates":[-76.2500076294,44.9005622864],"type":"Point"}
}