{
  "type": "Feature",
  "properties": {
    "iso:country":"CA",
    "sg:address":"2271 Ch DE Chambly",
    "sg:city":"Longueuil",
    "sg:classifiers":[
        {
            "category":"Retail",
            "subcategory":"Auto Repair",
            "type":"Services"
        }
    ],
    "sg:phone":"+1 450 647 1476",
    "sg:postcode":"J4J 3Z5",
    "sg:province":"QC",
    "sg:tags":[
        "repairing",
        "automobile"
    ],
    "wof:name":"Garage Gravel & Freres",
    "wof:placetype":"venue"
},
  "geometry": {"coordinates":[-73.474281,45.526482],"type":"Point"}
}