{
  "type": "Feature",
  "properties": {
    "iso:country":"CA",
    "sg:address":"5322 Boul Saint-Laurent",
    "sg:city":"Montreal",
    "sg:classifiers":[
        {
            "category":"Bars & Pubs",
            "type":"Food & Drink"
        }
    ],
    "sg:phone":"+1 514 279 0200",
    "sg:postcode":"H2T 1S1",
    "sg:province":"QC",
    "sg:tags":[
        "lounge",
        "cocktail"
    ],
    "wof:name":"Mile End Bar",
    "wof:placetype":"venue"
},
  "geometry": {"coordinates":[-73.5967636108,45.5246887207],"type":"Point"}
}