{
  "type": "Feature",
  "properties": {
    "iso:country":"CA",
    "sg:address":"826 Regal Cres",
    "sg:city":"Pickering",
    "sg:classifiers":[
        {
            "category":"Professional",
            "subcategory":"Business Services",
            "type":"Services"
        }
    ],
    "sg:phone":"+1 905 831 7921",
    "sg:postcode":"L1X 2P8",
    "sg:province":"ON",
    "sg:tags":[
        "monogram",
        "embroidery"
    ],
    "wof:name":"Gloria's Personalized Monogrms",
    "wof:placetype":"venue"
},
  "geometry": {"coordinates":[-79.11926269529999,43.8412208557],"type":"Point"}
}