{
  "type": "Feature",
  "properties": {
    "addr:full":"Vancouver BC V6M 2A3",
    "addr:postcode":"v6m 2a3",
    "iso:country":"CA",
    "sg:city":"Vancouver",
    "sg:classifiers":[
        {
            "category":"Health Services",
            "subcategory":"Clinic",
            "type":"Services"
        }
    ],
    "sg:phone":"+1 604 261 7999",
    "sg:postcode":"V6M 2A3",
    "sg:province":"BC",
    "sg:tags":[
        "holistic",
        "practitioner"
    ],
    "wof:name":"Aei Enterprises Ltd",
    "wof:placetype":"venue"
},
  "geometry": {"coordinates":[-123.16004180900001,49.2347373962],"type":"Point"}
}