{
  "type": "Feature",
  "properties": {
    "addr:full":"4846 Rue Rivard Montreal QC H2J 2N6",
    "addr:housenumber":"4846",
    "addr:postcode":"h2j 2n6",
    "addr:street":"Rue Rivard",
    "iso:country":"CA",
    "sg:address":"4846 Rue Rivard",
    "sg:city":"Montreal",
    "sg:classifiers":[
        {
            "category":"Health Services",
            "subcategory":"Doctor",
            "type":"Services"
        }
    ],
    "sg:phone":"+1 514 848 0306",
    "sg:postcode":"H2J 2N6",
    "sg:province":"QC",
    "sg:tags":[
        "physician",
        "surgeon"
    ],
    "wof:name":"Clinique DE Physiotherapie",
    "wof:placetype":"venue"
},
  "geometry": {"coordinates":[-73.5868225098,45.5264015198],"type":"Point"}
}