{
  "type": "Feature",
  "properties": {
    "iso:country":"CA",
    "sg:address":"235 Rue Tanguay",
    "sg:city":"Roberval",
    "sg:classifiers":[
        {
            "category":"Government",
            "subcategory":"Police Station",
            "type":"Public Place"
        }
    ],
    "sg:phone":"+1 418 275 0433",
    "sg:postcode":"G8H 3B3",
    "sg:province":"QC",
    "sg:tags":[
        "department"
    ],
    "wof:name":"Quebec Surete Du Quebec",
    "wof:placetype":"venue"
},
  "geometry": {"coordinates":[-72.2257766724,48.5004196167],"type":"Point"}
}