{
  "type": "Feature",
  "properties": {
    "addr:full":"Longueuil QC J4K 2T4",
    "addr:postcode":"j4k 2t4",
    "iso:country":"CA",
    "sg:city":"Longueuil",
    "sg:classifiers":[
        {
            "category":"Shopping",
            "subcategory":"Clothing, Apparel, & Fashions",
            "type":"Retail Goods"
        }
    ],
    "sg:phone":"+1 450 677 1546",
    "sg:postcode":"J4K 2T4",
    "sg:province":"QC",
    "sg:tags":[
        "item",
        "boutique"
    ],
    "wof:name":"Limite Boutiques",
    "wof:placetype":"venue"
},
  "geometry": {"coordinates":[-73.52253,45.525345],"type":"Point"}
}