{
  "type": "Feature",
  "properties": {
    "addr:full":"Innisfail AB T4G 1M5",
    "addr:postcode":"t4g 1m5",
    "iso:country":"CA",
    "sg:city":"Innisfail",
    "sg:classifiers":[
        {
            "category":"Home & Garden",
            "subcategory":"Hardware",
            "type":"Retail Goods"
        }
    ],
    "sg:phone":"+1 403 227 5552",
    "sg:postcode":"T4G 1M5",
    "sg:province":"AB",
    "sg:tags":[
        "lumber"
    ],
    "wof:name":"Innisfail CO-OP Home Ctr",
    "wof:placetype":"venue"
},
  "geometry": {"coordinates":[-113.950408935,52.0209159851],"type":"Point"}
}