{
  "type": "Feature",
  "properties": {
    "addr:full":"115 Ch Du Ruisseau-Saint-Louis Marieville QC J3M 1P7",
    "addr:housenumber":"115",
    "addr:postcode":"j3m 1p7",
    "addr:street":"Ch Du Ruisseau-Saint-Louis",
    "iso:country":"CA",
    "sg:address":"115 Ch Du Ruisseau-Saint-Louis",
    "sg:city":"Marieville",
    "sg:classifiers":[
        {
            "category":"Utilities",
            "subcategory":"Fuel Oil & Lpg",
            "type":"Services"
        }
    ],
    "sg:phone":"+1 450 460 3900",
    "sg:postcode":"J3M 1P7",
    "sg:province":"QC",
    "sg:tags":[
        "propane",
        "gas"
    ],
    "wof:name":"Action Propane",
    "wof:placetype":"venue"
},
  "geometry": {"coordinates":[-73.1690750122,45.4398574829],"type":"Point"}
}