{
  "type": "Feature",
  "properties": {
    "addr:full":"1025 103 Ave Dawson Creek BC V1G 2G6",
    "addr:housenumber":"1025",
    "addr:postcode":"v1g 2g6",
    "addr:street":"103 Ave",
    "iso:country":"CA",
    "sg:address":"1025 103 Ave",
    "sg:city":"Dawson Creek",
    "sg:classifiers":[
        {
            "category":"Health Services",
            "subcategory":"Doctor",
            "type":"Services"
        }
    ],
    "sg:phone":"+1 250 782 1186",
    "sg:postcode":"V1G 2G6",
    "sg:province":"BC",
    "sg:tags":[
        "physician",
        "surgeon"
    ],
    "wof:name":"Gorton Gorton & Ashwell",
    "wof:placetype":"venue"
},
  "geometry": {"coordinates":[-120.230186,55.757668],"type":"Point"}
}