{
  "type": "Feature",
  "properties": {
    "addr:full":"10050 116 Ave Grande Prairie AB T8V 4K5",
    "addr:housenumber":"10050",
    "addr:postcode":"t8v 4k5",
    "addr:street":"116 Ave",
    "iso:country":"CA",
    "sg:address":"10050 116 Ave",
    "sg:city":"Grande Prairie",
    "sg:classifiers":[
        {
            "category":"Travel",
            "subcategory":"Hotels & Motels",
            "type":"Entertainment"
        }
    ],
    "sg:phone":"+1 780 532 8288",
    "sg:postcode":"T8V 4K5",
    "sg:province":"AB",
    "wof:name":"Super 8 Motel",
    "wof:placetype":"venue"
},
  "geometry": {"coordinates":[-118.79655456499999,55.186542511],"type":"Point"}
}