{
  "type": "Feature",
  "properties": {
    "addr:full":"Kincaid SK S0H 2J0",
    "addr:postcode":"s0h 2j0",
    "addr:street":"Kincaid",
    "iso:country":"CA",
    "sg:city":"Kincaid",
    "sg:classifiers":[
        {
            "category":"Wholesale",
            "subcategory":"Machinery & Supplies",
            "type":"Manufacturing & Wholesale Goods"
        }
    ],
    "sg:phone":"+1 306 264 5142",
    "sg:postcode":"S0H 2J0",
    "sg:province":"SK",
    "sg:tags":[
        "agricultural",
        "implement"
    ],
    "wof:name":"Sadowski Service",
    "wof:placetype":"venue"
},
  "geometry": {"coordinates":[-107.003936768,49.6722297668],"type":"Point"}
}