{
  "type": "Feature",
  "properties": {
    "addr:full":"1122 Rue Saint-Vallier E Quebec QC G1K 3R7",
    "addr:housenumber":"1122",
    "addr:postcode":"g1k 3r7",
    "addr:street":"Rue Saint-Vallier E",
    "iso:country":"CA",
    "sg:address":"1122 Rue Saint-Vallier E",
    "sg:city":"Quebec",
    "sg:classifiers":[
        {
            "category":"Real Estate",
            "subcategory":"Architect",
            "type":"Services"
        }
    ],
    "sg:phone":"+1 418 694 9393",
    "sg:postcode":"G1K 3R7",
    "sg:province":"QC",
    "wof:name":"Lafond Cote Architectures",
    "wof:placetype":"venue"
},
  "geometry": {"coordinates":[-71.21217346189999,46.8160705566],"type":"Point"}
}