{
  "type": "Feature",
  "properties": {
    "iso:country":"CA",
    "sg:address":"2655 Boul Du Royaume",
    "sg:city":"Jonquiere",
    "sg:classifiers":[
        {
            "category":"Shopping",
            "subcategory":"Used Merchandise",
            "type":"Retail Goods"
        }
    ],
    "sg:phone":"+1 418 699 0000",
    "sg:postcode":"G7S 4S9",
    "sg:province":"QC",
    "sg:tags":[
        "book",
        "rare",
        "dealer"
    ],
    "wof:name":"Boutique Trouvailles",
    "wof:placetype":"venue"
},
  "geometry": {"coordinates":[-71.16847229,48.4050102234],"type":"Point"}
}