{
  "type": "Feature",
  "properties": {
    "addr:full":"Mississauga ON L5B 1M2",
    "addr:postcode":"l5b 1m2",
    "iso:country":"CA",
    "sg:city":"Mississauga",
    "sg:classifiers":[
        {
            "category":"Professional",
            "subcategory":"Management & Consulting",
            "type":"Services"
        }
    ],
    "sg:phone":"+1 905 896 2022",
    "sg:postcode":"L5B 1M2",
    "sg:province":"ON",
    "sg:tags":[
        "employee",
        "consultant",
        "benefit"
    ],
    "wof:name":"Comprehensive Benefit Sltns",
    "wof:placetype":"venue"
},
  "geometry": {"coordinates":[-79.639923,43.594799],"type":"Point"}
}