{
  "type": "Feature",
  "properties": {
    "addr:full":"1242 Rue Mackay Montreal QC H3G 2H4",
    "addr:housenumber":"1242",
    "addr:postcode":"h3g 2h4",
    "addr:street":"Rue Mackay",
    "iso:country":"CA",
    "sg:address":"1242 Rue Mackay",
    "sg:city":"Montreal",
    "sg:classifiers":[
        {
            "category":"Restaurant",
            "type":"Food & Drink"
        }
    ],
    "sg:phone":"+1 514 932 7099",
    "sg:postcode":"H3G 2H4",
    "sg:province":"QC",
    "wof:name":"Baguette D'Ivoire",
    "wof:placetype":"venue"
},
  "geometry": {"coordinates":[-73.57624053959999,45.4953346252],"type":"Point"}
}