{
  "type": "Feature",
  "properties": {
    "iso:country":"CA",
    "sg:city":"London",
    "sg:classifiers":[
        {
            "category":"Shopping",
            "subcategory":"Discount & Variety Stores",
            "type":"Retail Goods"
        }
    ],
    "sg:phone":"+1 519 642 2499",
    "sg:postcode":"N6C 4N5",
    "sg:province":"ON",
    "wof:name":"K R Mini Mart",
    "wof:placetype":"venue"
},
  "geometry": {"coordinates":[-81.232231,42.967323],"type":"Point"}
}