{
  "type": "Feature",
  "properties": {
    "iso:country":"CA",
    "sg:address":"121 Durham St",
    "sg:city":"Sudbury",
    "sg:classifiers":[
        {
            "category":"Professional",
            "subcategory":"Engineering",
            "type":"Services"
        }
    ],
    "sg:phone":"+1 705 674 4401",
    "sg:postcode":"P3E 3M9",
    "sg:province":"ON",
    "sg:tags":[
        "engineer"
    ],
    "wof:name":"Northland Engineering Ltd",
    "wof:placetype":"venue"
},
  "geometry": {"coordinates":[-80.99523925779999,46.4908485413],"type":"Point"}
}