{
  "type": "Feature",
  "properties": {
    "addr:full":"400 Rue Thomas Lachute QC J8H 1V7",
    "addr:housenumber":"400",
    "addr:postcode":"j8h 1v7",
    "addr:street":"Rue Thomas",
    "iso:country":"CA",
    "sg:address":"400 Rue Thomas",
    "sg:city":"Lachute",
    "sg:classifiers":[
        {
            "category":"Real Estate",
            "subcategory":"Real Estate Operator",
            "type":"Services"
        }
    ],
    "sg:phone":"+1 450 562 7479",
    "sg:postcode":"J8H 1V7",
    "sg:province":"QC",
    "sg:tags":[
        "apartment",
        "rental",
        "agency"
    ],
    "wof:name":"Appartements Brownsburg",
    "wof:placetype":"venue"
},
  "geometry": {"coordinates":[-74.3404464722,45.6584815979],"type":"Point"}
}