{
  "type": "Feature",
  "properties": {
    "iso:country":"CA",
    "sg:address":"345 Mcgill St",
    "sg:city":"Peterborough",
    "sg:classifiers":[
        {
            "category":"Professional",
            "subcategory":"Management & Consulting",
            "type":"Services"
        }
    ],
    "sg:phone":"+1 705 740 9371",
    "sg:postcode":"K9J 1W6",
    "sg:province":"ON",
    "sg:tags":[
        "marketing",
        "consultant"
    ],
    "wof:name":"Davis Campbell",
    "wof:placetype":"venue"
},
  "geometry": {"coordinates":[-78.3200836182,44.2856140137],"type":"Point"}
}