{
  "type": "Feature",
  "properties": {
    "addr:full":"210 Kenny St Winnipeg MB R2H 2E4",
    "addr:housenumber":"210",
    "addr:postcode":"r2h 2e4",
    "addr:street":"Kenny St",
    "iso:country":"CA",
    "sg:address":"210 Kenny St",
    "sg:city":"Winnipeg",
    "sg:classifiers":[
        {
            "category":"Social Services",
            "type":"Services"
        }
    ],
    "sg:phone":"+1 204 237 9263",
    "sg:postcode":"R2H 2E4",
    "sg:province":"MB",
    "sg:tags":[
        "organization",
        "welfare"
    ],
    "wof:name":"Sara Riel Inc",
    "wof:placetype":"venue"
},
  "geometry": {"coordinates":[-97.119759,49.877853],"type":"Point"}
}