{
  "type": "Feature",
  "properties": {
    "addr:full":"345 Albright Rd Hamilton ON L8K 6N3",
    "addr:housenumber":"345",
    "addr:postcode":"l8k 6n3",
    "addr:street":"Albright Rd",
    "iso:country":"CA",
    "sg:address":"345 Albright Rd",
    "sg:city":"Hamilton",
    "sg:classifiers":[
        {
            "category":"Education",
            "subcategory":"School",
            "type":"Public Place"
        }
    ],
    "sg:phone":"+1 905 561 3966",
    "sg:postcode":"L8K 6N3",
    "sg:province":"ON",
    "wof:name":"St Luke's School",
    "wof:placetype":"venue"
},
  "geometry": {"coordinates":[-79.795723,43.218899],"type":"Point"}
}