{
  "type": "Feature",
  "properties": {
    "addr:full":"Terrebonne QC J6X 4H6",
    "addr:postcode":"j6x 4h6",
    "iso:country":"CA",
    "sg:city":"Terrebonne",
    "sg:classifiers":[
        {
            "category":"Home & Garden",
            "subcategory":"Home Furnishings",
            "type":"Retail Goods"
        }
    ],
    "sg:phone":"+1 450 477 2863",
    "sg:postcode":"J6X 4H6",
    "sg:province":"QC",
    "sg:tags":[
        "equipment",
        "fireplace"
    ],
    "wof:name":"Impact Foyer Inc",
    "wof:placetype":"venue"
},
  "geometry": {"coordinates":[-73.6707229614,45.7273902893],"type":"Point"}
}