{
  "type": "Feature",
  "properties": {
    "iso:country":"CA",
    "sg:city":"Roxboro",
    "sg:classifiers":[
        {
            "category":"Health Services",
            "subcategory":"Chiropractor",
            "type":"Services"
        }
    ],
    "sg:phone":"+1 514 683 3476",
    "sg:postcode":"H8Y 1W4",
    "sg:province":"QC",
    "wof:name":"Theoret, Andre DC",
    "wof:placetype":"venue"
},
  "geometry": {"coordinates":[-73.853065,45.493565],"type":"Point"}
}