{
  "type": "Feature",
  "properties": {
    "addr:full":"344 Main St St Adolphe MB R5A 1B5",
    "addr:housenumber":"344",
    "addr:postcode":"r5a 1b5",
    "addr:street":"Main St St Adolphe",
    "iso:country":"CA",
    "sg:address":"344 Main St",
    "sg:city":"St Adolphe",
    "sg:classifiers":[
        {
            "category":"Organizations",
            "subcategory":"Professional Association",
            "type":"Services"
        }
    ],
    "sg:phone":"+1 204 883 2575",
    "sg:postcode":"R5A 1B5",
    "sg:province":"MB",
    "sg:tags":[
        "club"
    ],
    "wof:name":"St Adolphe Nursery School",
    "wof:placetype":"venue"
},
  "geometry": {"coordinates":[-97.111519,49.671444],"type":"Point"}
}