{
  "type": "Feature",
  "properties": {
    "addr:full":"173 Sylvestre St Saint-Germain-DE-Grantham QC J0C 1K0",
    "addr:housenumber":"173",
    "addr:postcode":"j0c 1k0",
    "addr:street":"Sylvestre St",
    "iso:country":"CA",
    "sg:address":"173 Sylvestre St",
    "sg:city":"Saint-Germain-DE-Grantham",
    "sg:classifiers":[
        {
            "category":"Retail",
            "subcategory":"Auto Repair",
            "type":"Services"
        }
    ],
    "sg:phone":"+1 819 395 4256",
    "sg:postcode":"J0C 1K0",
    "sg:province":"QC",
    "sg:tags":[
        "truck"
    ],
    "wof:name":"Garage C Charbonneau Inc",
    "wof:placetype":"venue"
},
  "geometry": {"coordinates":[-72.57711,45.854996],"type":"Point"}
}