{
  "type": "Feature",
  "properties": {
    "addr:full":"Richmond BC V6Y 2T7",
    "addr:postcode":"v6y 2t7",
    "iso:country":"CA",
    "sg:city":"Richmond",
    "sg:classifiers":[
        {
            "category":"Professional",
            "subcategory":"Management & Consulting",
            "type":"Services"
        }
    ],
    "sg:phone":"+1 604 275 2124",
    "sg:postcode":"V6Y 2T7",
    "sg:province":"BC",
    "sg:tags":[
        "communications",
        "consultant"
    ],
    "wof:name":"Richcom Communications Ltd",
    "wof:placetype":"venue"
},
  "geometry": {"coordinates":[-123.114364624,49.1488265991],"type":"Point"}
}