{
  "type": "Feature",
  "properties": {
    "addr:full":"1025 Michigan Ave Sarnia ON N7S 2B3",
    "addr:housenumber":"1025",
    "addr:postcode":"n7s 2b3",
    "addr:street":"Michigan Ave",
    "iso:country":"CA",
    "sg:address":"1025 Michigan Ave",
    "sg:city":"Sarnia",
    "sg:classifiers":[
        {
            "category":"Organizations",
            "subcategory":"Professional Association",
            "type":"Services"
        }
    ],
    "sg:phone":"+1 519 542 1346",
    "sg:postcode":"N7S 2B3",
    "sg:province":"ON",
    "wof:name":"Horizon House Lambton I",
    "wof:placetype":"venue"
},
  "geometry": {"coordinates":[-82.3703536987,42.9980278015],"type":"Point"}
}