{
  "type": "Feature",
  "properties": {
    "addr:full":"5803 Cornell Cres Mississauga ON L5M 5R5",
    "addr:housenumber":"5803",
    "addr:postcode":"l5m 5r5",
    "addr:street":"Cornell Cres",
    "iso:country":"CA",
    "sg:address":"5803 Cornell Cres",
    "sg:city":"Mississauga",
    "sg:classifiers":[
        {
            "category":"Manufacturing",
            "subcategory":"Printing",
            "type":"Manufacturing & Wholesale Goods"
        }
    ],
    "sg:phone":"+1 905 858 3784",
    "sg:postcode":"L5M 5R5",
    "sg:province":"ON",
    "sg:tags":[
        "publisher",
        "guide"
    ],
    "wof:name":"Genesis Publications",
    "wof:placetype":"venue"
},
  "geometry": {"coordinates":[-79.734917,43.571079],"type":"Point"}
}