{
  "type": "Feature",
  "properties": {
    "iso:country":"CA",
    "sg:address":"1041 Boul Saint-Joseph E",
    "sg:city":"Montreal",
    "sg:classifiers":[
        {
            "category":"Building & Trades",
            "subcategory":"Construction",
            "type":"Services"
        }
    ],
    "sg:phone":"+1 514 289 9616",
    "sg:postcode":"H2J 1L2",
    "sg:province":"QC",
    "sg:tags":[
        "steel"
    ],
    "wof:name":"Dessins Michel Choquet Inc",
    "wof:placetype":"venue"
},
  "geometry": {"coordinates":[-73.584732,45.529987],"type":"Point"}
}