{
  "type": "Feature",
  "properties": {
    "addr:full":"16 Rue Principale Saint-Basile-Le-Grand QC J3N 1M3",
    "addr:housenumber":"16",
    "addr:postcode":"j3n 1m3",
    "addr:street":"Rue Principale",
    "iso:country":"CA",
    "sg:address":"16 Rue Principale",
    "sg:city":"Saint-Basile-Le-Grand",
    "sg:classifiers":[
        {
            "category":"Building & Trades",
            "subcategory":"Construction",
            "type":"Services"
        }
    ],
    "sg:phone":"+1 450 461 1117",
    "sg:postcode":"J3N 1M3",
    "sg:province":"QC",
    "sg:tags":[
        "repairing",
        "foundation",
        "remodeling",
        "contractor"
    ],
    "wof:name":"Fondation Rive-Sud Inc",
    "wof:placetype":"venue"
},
  "geometry": {"coordinates":[-73.268204,45.552612],"type":"Point"}
}