{
  "type": "Feature",
  "properties": {
    "addr:full":"Selkirk MB R1A 3T4",
    "addr:postcode":"r1a 3t4",
    "iso:country":"CA",
    "sg:city":"Selkirk",
    "sg:classifiers":[
        {
            "category":"Real Estate",
            "subcategory":"Real Estate Agent",
            "type":"Services"
        }
    ],
    "sg:phone":"+1 204 482 3365",
    "sg:postcode":"R1A 3T4",
    "sg:province":"MB",
    "sg:tags":[
        "housing"
    ],
    "wof:name":"Selkirk Kiwanis on the Red",
    "wof:placetype":"venue"
},
  "geometry": {"coordinates":[-96.86705000000001,50.14587],"type":"Point"}
}