{
  "type": "Feature",
  "properties": {
    "iso:country":"CA",
    "sg:address":"PO Box 39",
    "sg:city":"Long Harbour",
    "sg:classifiers":[
        {
            "category":"Manufacturing",
            "subcategory":"Food",
            "type":"Manufacturing & Wholesale Goods"
        }
    ],
    "sg:phone":"+1 709 228 2480",
    "sg:postcode":"A0B 2J0",
    "sg:province":"NL",
    "sg:tags":[
        "packer",
        "fish"
    ],
    "wof:name":"Newfoundland Bait Svc Ltd",
    "wof:placetype":"venue"
},
  "geometry": {"coordinates":[-53.7712783813,47.4449310303],"type":"Point"}
}