{
  "type": "Feature",
  "properties": {
    "iso:country":"CA",
    "sg:address":"5875 Rochdale Blvd # 306",
    "sg:city":"Regina",
    "sg:classifiers":[
        {
            "category":"Shopping",
            "subcategory":"Pharmacy",
            "type":"Retail Goods"
        }
    ],
    "sg:phone":"+1 306 949 6616",
    "sg:postcode":"S4X 2P9",
    "sg:province":"SK",
    "wof:name":"Shoppers Drug Mart",
    "wof:placetype":"venue"
},
  "geometry": {"coordinates":[-104.66532898,50.495552063],"type":"Point"}
}