{
  "type": "Feature",
  "properties": {
    "addr:full":"58 Three Valleys Dr North York ON M3A 3B5",
    "addr:housenumber":"58",
    "addr:postcode":"m3a 3b5",
    "addr:street":"Three Valleys Dr",
    "iso:country":"CA",
    "sg:address":"58 Three Valleys Dr",
    "sg:city":"North York",
    "sg:classifiers":[
        {
            "category":"Retail",
            "subcategory":"Auto Repair",
            "type":"Services"
        }
    ],
    "sg:phone":"+1 416 444 6350",
    "sg:postcode":"M3A 3B5",
    "sg:province":"ON",
    "sg:tags":[
        "repairing",
        "automobile"
    ],
    "wof:name":"Three Valleys Auto Ctr",
    "wof:placetype":"venue"
},
  "geometry": {"coordinates":[-79.33622699999999,43.751556],"type":"Point"}
}