{
  "type": "Feature",
  "properties": {
    "addr:full":"12303 Jasper Ave NW Edmonton AB T5N 3K7",
    "addr:housenumber":"12303",
    "addr:postcode":"t5n 3k7",
    "addr:street":"Jasper Ave Nw",
    "iso:country":"CA",
    "sg:address":"12303 Jasper Ave NW",
    "sg:city":"Edmonton",
    "sg:classifiers":[
        {
            "category":"Personal",
            "subcategory":"Beauty Salon",
            "type":"Services"
        }
    ],
    "sg:phone":"+1 780 488 0849",
    "sg:postcode":"T5N 3K7",
    "sg:province":"AB",
    "wof:name":"Hands Feet & Face",
    "wof:placetype":"venue"
},
  "geometry": {"coordinates":[-113.534325,53.541313],"type":"Point"}
}