{
  "type": "Feature",
  "properties": {
    "iso:country":"CA",
    "sg:address":"1256 185 Rte S",
    "sg:city":"Degelis",
    "sg:classifiers":[
        {
            "category":"Home & Garden",
            "subcategory":"Furniture",
            "type":"Retail Goods"
        }
    ],
    "sg:phone":"+1 418 853 3611",
    "sg:postcode":"G5T 1P8",
    "sg:province":"QC",
    "wof:name":"Meubles Degelis Ltee",
    "wof:placetype":"venue"
},
  "geometry": {"coordinates":[-68.64251708979999,47.5469894409],"type":"Point"}
}