{
  "type": "Feature",
  "properties": {
    "addr:full":"11250 153 Ave NW Edmonton AB T5X 5H2",
    "addr:housenumber":"11250",
    "addr:postcode":"t5x 5h2",
    "addr:street":"153 Ave Nw",
    "iso:country":"CA",
    "sg:address":"11250 153 Ave NW",
    "sg:city":"Edmonton",
    "sg:classifiers":[
        {
            "category":"Organizations",
            "subcategory":"Religious Organization",
            "type":"Services"
        }
    ],
    "sg:phone":"+1 780 456 9348",
    "sg:postcode":"T5X 5H2",
    "sg:province":"AB",
    "sg:tags":[
        "church"
    ],
    "wof:name":"Castle Downs Baptist Church",
    "wof:placetype":"venue"
},
  "geometry": {"coordinates":[-113.514030456,53.6143455505],"type":"Point"}
}