{
  "type": "Feature",
  "properties": {
    "iso:country":"CA",
    "sg:address":"1033 Marinaside Cres",
    "sg:city":"Vancouver",
    "sg:classifiers":[
        {
            "category":"Professional",
            "subcategory":"Accounting & Tax Preparation",
            "type":"Services"
        }
    ],
    "sg:phone":"+1 604 692 0099",
    "sg:postcode":"V6Z 3A3",
    "sg:province":"BC",
    "sg:tags":[
        "accountant"
    ],
    "wof:name":"Eldsvik & Assoc",
    "wof:placetype":"venue"
},
  "geometry": {"coordinates":[-123.116119,49.273212],"type":"Point"}
}