{
  "type": "Feature",
  "properties": {
    "addr:full":"15 Rue Des Emeraudes Levis QC G6W 6Y7",
    "addr:housenumber":"15",
    "addr:postcode":"g6w 6y7",
    "addr:street":"Rue Des Emeraudes",
    "iso:country":"CA",
    "sg:address":"15 Rue Des Emeraudes",
    "sg:city":"Levis",
    "sg:classifiers":[
        {
            "category":"Wholesale",
            "subcategory":"Auto Parts",
            "type":"Manufacturing & Wholesale Goods"
        }
    ],
    "sg:phone":"+1 418 835 3024",
    "sg:postcode":"G6W 6Y7",
    "sg:province":"QC",
    "sg:tags":[
        "equipment",
        "truck"
    ],
    "wof:name":"Pieces DE Citerne Rive-Sud Enr",
    "wof:placetype":"venue"
},
  "geometry": {"coordinates":[-71.19863100000001,46.771317],"type":"Point"}
}