{
  "type": "Feature",
  "properties": {
    "addr:full":"Barrington NS B0W 1E0",
    "addr:postcode":"b0w 1e0",
    "iso:country":"CA",
    "sg:city":"Barrington",
    "sg:classifiers":[
        {
            "category":"Government",
            "subcategory":"Office",
            "type":"Public Place"
        }
    ],
    "sg:phone":"+1 902 637 2903",
    "sg:postcode":"B0W 1E0",
    "sg:province":"NS",
    "sg:tags":[
        "village"
    ],
    "wof:name":"Barrington Recreation Coordntr",
    "wof:placetype":"venue"
},
  "geometry": {"coordinates":[-65.563225,43.563828],"type":"Point"}
}