{
  "type": "Feature",
  "properties": {
    "iso:country":"CA",
    "sg:address":"950 Rue Saint-Gerard",
    "sg:city":"Disraeli",
    "sg:classifiers":[
        {
            "category":"Education",
            "subcategory":"School",
            "type":"Public Place"
        }
    ],
    "sg:phone":"+1 418 449 3200",
    "sg:postcode":"G0N 1E0",
    "sg:province":"QC",
    "wof:name":"Polyvalente Disraeli",
    "wof:placetype":"venue"
},
  "geometry": {"coordinates":[-71.354347229,45.9084396362],"type":"Point"}
}