{
  "type": "Feature",
  "properties": {
    "iso:country":"CA",
    "sg:address":"74 Home St",
    "sg:city":"Dundas",
    "sg:classifiers":[
        {
            "category":"Wholesale",
            "subcategory":"Machinery & Supplies",
            "type":"Manufacturing & Wholesale Goods"
        }
    ],
    "sg:phone":"+1 905 524 3775",
    "sg:postcode":"L9H 5V7",
    "sg:province":"ON",
    "sg:tags":[
        "repairing"
    ],
    "wof:name":"Rcr Millwright Svc",
    "wof:placetype":"venue"
},
  "geometry": {"coordinates":[-79.911133,43.30492],"type":"Point"}
}