{
  "type": "Feature",
  "properties": {
    "iso:country":"CA",
    "sg:address":"971 Rue Riverview",
    "sg:city":"Verdun",
    "sg:classifiers":[
        {
            "category":"Education",
            "subcategory":"School",
            "type":"Public Place"
        }
    ],
    "sg:phone":"+1 514 761 4524",
    "sg:postcode":"H4H 2C3",
    "sg:province":"QC",
    "wof:name":"Riverview School",
    "wof:placetype":"venue"
},
  "geometry": {"coordinates":[-73.57749176030001,45.4470672607],"type":"Point"}
}