{
  "type": "Feature",
  "properties": {
    "addr:full":"Locust Hill ON L0H 1J0",
    "addr:postcode":"l0h 1j0",
    "addr:street":"Locust Hill",
    "iso:country":"CA",
    "sg:city":"Locust Hill",
    "sg:classifiers":[
        {
            "category":"Retail",
            "subcategory":"Auto Repair",
            "type":"Services"
        }
    ],
    "sg:phone":"+1 905 294 0724",
    "sg:postcode":"L0H 1J0",
    "sg:province":"ON",
    "sg:tags":[
        "body",
        "automobile",
        "painting"
    ],
    "wof:name":"Stan's Power Paint",
    "wof:placetype":"venue"
},
  "geometry": {"coordinates":[-79.20450599999999,43.885571],"type":"Point"}
}