{
  "type": "Feature",
  "properties": {
    "addr:full":"1601 Burnwood Dr Burnaby BC V5A 4H1",
    "addr:housenumber":"1601",
    "addr:postcode":"v5a 4h1",
    "addr:street":"Burnwood Dr",
    "iso:country":"CA",
    "sg:address":"1601 Burnwood Dr",
    "sg:city":"Burnaby",
    "sg:classifiers":[
        {
            "category":"Food & Beverages",
            "subcategory":"Liquor & Beverages",
            "type":"Retail Goods"
        }
    ],
    "sg:phone":"+1 604 421 3114",
    "sg:postcode":"V5A 4H1",
    "sg:province":"BC",
    "sg:tags":[
        "store"
    ],
    "wof:name":"Hop & Vine Cold Beer & Wine",
    "wof:placetype":"venue"
},
  "geometry": {"coordinates":[-122.94536600000001,49.270088],"type":"Point"}
}