{
  "type": "Feature",
  "properties": {
    "addr:full":"6623 4 Ave SE Calgary AB T2A 3V1",
    "addr:housenumber":"6623",
    "addr:postcode":"t2a 3v1",
    "addr:street":"4 Ave Se",
    "iso:country":"CA",
    "sg:address":"6623 4 Ave SE",
    "sg:city":"Calgary",
    "sg:classifiers":[
        {
            "category":"Building & Trades",
            "subcategory":"Plumbing",
            "type":"Services"
        }
    ],
    "sg:phone":"+1 403 248 4141",
    "sg:postcode":"T2A 3V1",
    "sg:province":"AB",
    "sg:tags":[
        "contractor"
    ],
    "wof:name":"Gill Brothers Plumbing & Htg",
    "wof:placetype":"venue"
},
  "geometry": {"coordinates":[-113.940315247,51.0491218567],"type":"Point"}
}