{
  "type": "Feature",
  "properties": {
    "addr:full":"38 Elgin St Trenton ON K8V 3X8",
    "addr:housenumber":"38",
    "addr:postcode":"k8v 3x8",
    "addr:street":"Elgin St",
    "iso:country":"CA",
    "sg:address":"38 Elgin St",
    "sg:city":"Trenton",
    "sg:classifiers":[
        {
            "category":"Wholesale",
            "subcategory":"Electrical",
            "type":"Manufacturing & Wholesale Goods"
        }
    ],
    "sg:phone":"+1 613 392 9261",
    "sg:postcode":"K8V 3X8",
    "sg:province":"ON",
    "sg:tags":[
        "equipment",
        "electric",
        "supply"
    ],
    "wof:name":"Gimpel Electric Supply Ltd",
    "wof:placetype":"venue"
},
  "geometry": {"coordinates":[-77.57672100000001,44.102528],"type":"Point"}
}