{
  "type": "Feature",
  "properties": {
    "iso:country":"CA",
    "sg:address":"1007 St Mary's Rd",
    "sg:city":"Winnipeg",
    "sg:classifiers":[
        {
            "category":"Organizations",
            "subcategory":"Religious Organization",
            "type":"Services"
        }
    ],
    "sg:phone":"+1 204 257 0869",
    "sg:postcode":"R2M 3S5",
    "sg:province":"MB",
    "sg:tags":[
        "church"
    ],
    "wof:name":"St Eugene Church",
    "wof:placetype":"venue"
},
  "geometry": {"coordinates":[-97.1119232178,49.8401832581],"type":"Point"}
}