{
  "type": "Feature",
  "properties": {
    "addr:full":"1151 Rue Chartrand LA Plaine QC J7M 2B1",
    "addr:housenumber":"1151",
    "addr:postcode":"j7m 2b1",
    "addr:street":"Rue Chartrand",
    "iso:country":"CA",
    "sg:address":"1151 Rue Chartrand",
    "sg:city":"LA Plaine",
    "sg:classifiers":[
        {
            "category":"Restaurant",
            "type":"Food & Drink"
        }
    ],
    "sg:phone":"+1 450 968 0424",
    "sg:postcode":"J7M 2B1",
    "sg:province":"QC",
    "wof:name":"Patates Ti-Will",
    "wof:placetype":"venue"
},
  "geometry": {"coordinates":[-73.705727,45.751598],"type":"Point"}
}