{
  "type": "Feature",
  "properties": {
    "addr:full":"5302 72A Ave NW Edmonton AB T6B 2H9",
    "addr:housenumber":"5302",
    "addr:postcode":"t6b 2h9",
    "addr:street":"72A Ave Nw",
    "iso:country":"CA",
    "sg:address":"5302 72A Ave NW",
    "sg:city":"Edmonton",
    "sg:classifiers":[
        {
            "category":"Retail",
            "subcategory":"Repair Shop",
            "type":"Services"
        }
    ],
    "sg:phone":"+1 780 413 7183",
    "sg:postcode":"T6B 2H9",
    "sg:province":"AB",
    "sg:tags":[
        "valve"
    ],
    "wof:name":"Inntertech Valve Ltd",
    "wof:placetype":"venue"
},
  "geometry": {"coordinates":[-113.421211243,53.5087089539],"type":"Point"}
}