{
  "type": "Feature",
  "properties": {
    "addr:full":"582 Chilcotin Rd Kamloops BC V2H 1G5",
    "addr:housenumber":"582",
    "addr:postcode":"bc v2h 1g5",
    "addr:street":"Chilcotin Rd",
    "iso:country":"CA",
    "sg:address":"582 Chilcotin Rd",
    "sg:city":"Kamloops",
    "sg:classifiers":[
        {
            "category":"Mining & Drilling",
            "type":"Manufacturing & Wholesale Goods"
        }
    ],
    "sg:phone":"+1 250 372 9333",
    "sg:postcode":"V2H 1G5",
    "sg:province":"BC",
    "sg:tags":[
        "contractor"
    ],
    "wof:name":"Dynatec Corp",
    "wof:placetype":"venue"
},
  "geometry": {"coordinates":[-120.324944,50.690685],"type":"Point"}
}