{
  "type": "Feature",
  "properties": {
    "addr:full":"127 Ave Du Festival Saint-Simeon QC G0T 1X0",
    "addr:housenumber":"127",
    "addr:postcode":"g0t 1x0",
    "addr:street":"Ave Du Festival",
    "iso:country":"CA",
    "sg:address":"127 Ave Du Festival",
    "sg:city":"Saint-Simeon",
    "sg:classifiers":[
        {
            "category":"Restaurant",
            "type":"Food & Drink"
        }
    ],
    "sg:phone":"+1 418 638 5144",
    "sg:postcode":"G0T 1X0",
    "sg:province":"QC",
    "wof:name":"Casse-Croute DE L'Attente",
    "wof:placetype":"venue"
},
  "geometry": {"coordinates":[-69.875893,47.841915],"type":"Point"}
}