{
  "type": "Feature",
  "properties": {
    "addr:full":"286 S Railway Ave Winkler MB R6W 4A8",
    "addr:housenumber":"286",
    "addr:postcode":"r6w 4a8",
    "addr:street":"S Railway Ave",
    "iso:country":"CA",
    "sg:address":"286 S Railway Ave",
    "sg:city":"Winkler",
    "sg:classifiers":[
        {
            "category":"Social Services",
            "subcategory":"Job Training",
            "type":"Services"
        }
    ],
    "sg:phone":"+1 204 325 8555",
    "sg:postcode":"R6W 4A8",
    "sg:province":"MB",
    "sg:tags":[
        "physiotherapist",
        "rehabilitation"
    ],
    "wof:name":"Pembina Valley Physiotherapy",
    "wof:placetype":"venue"
},
  "geometry": {"coordinates":[-97.9361572266,49.1831130981],"type":"Point"}
}