{
  "type": "Feature",
  "properties": {
    "addr:full":"3429 Rue Sainte-Famille Montreal QC H2X 2K6",
    "addr:housenumber":"3429",
    "addr:postcode":"h2x 2k6",
    "addr:street":"Rue Sainte-Famille",
    "iso:country":"CA",
    "sg:address":"3429 Rue Sainte-Famille",
    "sg:city":"Montreal",
    "sg:classifiers":[
        {
            "category":"Personal",
            "subcategory":"Adult",
            "type":"Services"
        }
    ],
    "sg:phone":"+1 514 845 1669",
    "sg:postcode":"H2X 2K6",
    "sg:province":"QC",
    "sg:tags":[
        "escort"
    ],
    "wof:name":"Admirable",
    "wof:placetype":"venue"
},
  "geometry": {"coordinates":[-73.5713882446,45.510471344],"type":"Point"}
}