{
  "type": "Feature",
  "properties": {
    "addr:full":"Pohenegamook QC G0L 1J0",
    "addr:postcode":"g0l 1j0",
    "iso:country":"CA",
    "sg:city":"Pohenegamook",
    "sg:classifiers":[
        {
            "category":"Retail",
            "subcategory":"Funeral Services",
            "type":"Services"
        }
    ],
    "sg:phone":"+1 418 859 3332",
    "sg:postcode":"G0L 1J0",
    "sg:province":"QC",
    "sg:tags":[
        "director"
    ],
    "wof:name":"Maison Funeraire Jp Morin",
    "wof:placetype":"venue"
},
  "geometry": {"coordinates":[-69.223236,47.460735],"type":"Point"}
}