{
  "type": "Feature",
  "properties": {
    "addr:full":"Saint-Jerome QC J7Y 2V4",
    "addr:postcode":"j7y 2v4",
    "iso:country":"CA",
    "sg:city":"Saint-Jerome",
    "sg:classifiers":[
        {
            "category":"Restaurant",
            "type":"Food & Drink"
        }
    ],
    "sg:phone":"+1 450 432 6363",
    "sg:postcode":"J7Y 2V4",
    "sg:province":"QC",
    "wof:name":"Patate St Pierre",
    "wof:placetype":"venue"
},
  "geometry": {"coordinates":[-74.00730900000001,45.785248],"type":"Point"}
}