{
  "type": "Feature",
  "properties": {
    "addr:full":"126 Reed Ave St Andrews NB E5B 1A1",
    "addr:housenumber":"126",
    "addr:postcode":"e5b 1a1",
    "addr:street":"Reed Ave",
    "iso:country":"CA",
    "sg:address":"126 Reed Ave",
    "sg:city":"St Andrews",
    "sg:classifiers":[
        {
            "category":"Retail",
            "subcategory":"Veterinary Services",
            "type":"Services"
        }
    ],
    "sg:phone":"+1 506 887 2608",
    "sg:postcode":"E5B 1A1",
    "sg:province":"NB",
    "sg:tags":[
        "veterinarian"
    ],
    "wof:name":"St Andrews Animal Hospital",
    "wof:placetype":"venue"
},
  "geometry": {"coordinates":[-67.0603561401,45.082157135],"type":"Point"}
}