{
  "type": "Feature",
  "properties": {
    "addr:full":"470 Pioneer Hill Dr Port Mcneill BC V0N 2R0",
    "addr:housenumber":"470",
    "addr:postcode":"v0n 2r0",
    "addr:street":"Pioneer Hill Dr",
    "iso:country":"CA",
    "sg:address":"470 Pioneer Hill Dr",
    "sg:city":"Port Mcneill",
    "sg:classifiers":[
        {
            "category":"Wholesale",
            "subcategory":"Machinery & Supplies",
            "type":"Manufacturing & Wholesale Goods"
        }
    ],
    "sg:phone":"+1 250 956 4401",
    "sg:postcode":"V0N 2R0",
    "sg:province":"BC",
    "sg:tags":[
        "equipment",
        "hydraulic"
    ],
    "wof:name":"North Island Pacific Parts",
    "wof:placetype":"venue"
},
  "geometry": {"coordinates":[-127.085831,50.583858],"type":"Point"}
}