{
  "type": "Feature",
  "properties": {
    "addr:full":"2644 Rue DE Louvieres Sainte-Foy QC G1V 2A5",
    "addr:housenumber":"2644",
    "addr:postcode":"g1v 2a5",
    "addr:street":"Rue De Louvieres",
    "iso:country":"CA",
    "sg:address":"2644 Rue DE Louvieres",
    "sg:city":"Sainte-Foy",
    "sg:classifiers":[
        {
            "category":"Real Estate",
            "subcategory":"Real Estate Agent",
            "type":"Services"
        }
    ],
    "sg:phone":"+1 418 658 5200",
    "sg:postcode":"G1V 2A5",
    "sg:province":"QC",
    "wof:name":"Groupe Sa Vilbec Inc",
    "wof:placetype":"venue"
},
  "geometry": {"coordinates":[-71.289261,46.777454],"type":"Point"}
}