{
  "type": "Feature",
  "properties": {
    "addr:full":"4 Goderich Rd Spanish ON P0P 2A0",
    "addr:housenumber":"4",
    "addr:postcode":"p0p 2a0",
    "addr:street":"Goderich Rd",
    "iso:country":"CA",
    "sg:address":"4 Goderich Rd",
    "sg:city":"Spanish",
    "sg:classifiers":[
        {
            "category":"Food & Beverages",
            "subcategory":"Liquor & Beverages",
            "type":"Retail Goods"
        }
    ],
    "sg:phone":"+1 705 844 2244",
    "sg:postcode":"P0P 2A0",
    "sg:province":"ON",
    "sg:tags":[
        "store"
    ],
    "wof:name":"Liquor Control Board of Ont",
    "wof:placetype":"venue"
},
  "geometry": {"coordinates":[-82.343063,46.194046],"type":"Point"}
}