{
  "type": "Feature",
  "properties": {
    "addr:full":"3415 Rue DE L'Aeroport Mascouche QC J7K 3C1",
    "addr:housenumber":"3415",
    "addr:postcode":"j7k 3c1",
    "addr:street":"Rue De L'Aeroport",
    "iso:country":"CA",
    "sg:address":"3415 Rue DE L'Aeroport",
    "sg:city":"Mascouche",
    "sg:classifiers":[
        {
            "category":"Airport",
            "type":"Transportation"
        }
    ],
    "sg:phone":"+1 450 966 1256",
    "sg:postcode":"J7K 3C1",
    "sg:province":"QC",
    "sg:tags":[
        "aircraft",
        "maintenance"
    ],
    "wof:name":"Aero Dynamic",
    "wof:placetype":"venue"
},
  "geometry": {"coordinates":[-73.58867600000001,45.719299],"type":"Point"}
}