{
  "type": "Feature",
  "properties": {
    "iso:country":"CA",
    "sg:address":"37 Westroyal Rd",
    "sg:city":"Etobicoke",
    "sg:classifiers":[
        {
            "category":"Building & Trades",
            "subcategory":"Cleaning & Sanitation",
            "type":"Services"
        }
    ],
    "sg:phone":"+1 416 249 3212",
    "sg:postcode":"M9P 2C4",
    "sg:province":"ON",
    "sg:tags":[
        "janitor"
    ],
    "wof:name":"Queensway Janitorial Svc",
    "wof:placetype":"venue"
},
  "geometry": {"coordinates":[-79.536315918,43.6927261353],"type":"Point"}
}