{
  "type": "Feature",
  "properties": {
    "addr:full":"7026 Bathurst St Thornhill ON L4J 8K3",
    "addr:housenumber":"7026",
    "addr:postcode":"l4j 8k3",
    "addr:street":"Bathurst St",
    "iso:country":"CA",
    "sg:address":"7026 Bathurst St",
    "sg:city":"Thornhill",
    "sg:classifiers":[
        {
            "category":"Organizations",
            "subcategory":"Religious Organization",
            "type":"Services"
        }
    ],
    "sg:phone":"+1 905 669 6243",
    "sg:postcode":"L4J 8K3",
    "sg:province":"ON",
    "sg:tags":[
        "synagogue"
    ],
    "wof:name":"Sephardic Rabbinate of Ontario",
    "wof:placetype":"venue"
},
  "geometry": {"coordinates":[-79.446335,43.79443],"type":"Point"}
}