{
  "type": "Feature",
  "properties": {
    "iso:country":"CA",
    "sg:address":"9940 147 St NW",
    "sg:city":"Edmonton",
    "sg:classifiers":[
        {
            "category":"Arena",
            "subcategory":"Sports Club",
            "type":"Entertainment"
        }
    ],
    "sg:phone":"+1 780 944 7440",
    "sg:postcode":"T5N 4A6",
    "sg:province":"AB",
    "sg:tags":[
        "athletic",
        "fields",
        "stadium"
    ],
    "wof:name":"Crestwood Arena",
    "wof:placetype":"venue"
},
  "geometry": {"coordinates":[-113.574653626,53.5383720398],"type":"Point"}
}