{
  "type": "Feature",
  "properties": {
    "addr:full":"816 Nashville Rd Kleinburg ON L0J 1C0",
    "addr:housenumber":"816",
    "addr:postcode":"l0j 1c0",
    "addr:street":"Nashville Rd",
    "iso:country":"CA",
    "sg:address":"816 Nashville Rd",
    "sg:city":"Kleinburg",
    "sg:phone":"+1 905 893 1712",
    "sg:postcode":"L0J 1C0",
    "sg:province":"ON",
    "sg:tags":[
        "oil"
    ],
    "wof:name":"Maw's Fuels Ltd",
    "wof:placetype":"venue"
},
  "geometry": {"coordinates":[-79.65836334230001,43.8422622681],"type":"Point"}
}