{
  "type": "Feature",
  "properties": {
    "iso:country":"CA",
    "sg:address":"46 Rue Maxime-Raymond",
    "sg:city":"Chateauguay",
    "sg:classifiers":[
        {
            "category":"Retail",
            "subcategory":"Repair Shop",
            "type":"Services"
        }
    ],
    "sg:phone":"+1 450 691 4425",
    "sg:postcode":"J6K 5A9",
    "sg:province":"QC",
    "sg:tags":[
        "equipment"
    ],
    "wof:name":"Equipement DE Cuisine Diamond",
    "wof:placetype":"venue"
},
  "geometry": {"coordinates":[-73.750869751,45.3474082947],"type":"Point"}
}