{
  "type": "Feature",
  "properties": {
    "addr:full":"Montreal QC H3B 2H7",
    "addr:postcode":"h3b 2h7",
    "iso:country":"CA",
    "sg:city":"Montreal",
    "sg:classifiers":[
        {
            "category":"Banks & Credit Unions",
            "subcategory":"Investment Brokerage",
            "type":"Services"
        }
    ],
    "sg:phone":"+1 514 397 9073",
    "sg:postcode":"H3B 2H7",
    "sg:province":"QC",
    "wof:name":"Norstar Securities",
    "wof:placetype":"venue"
},
  "geometry": {"coordinates":[-73.554436,45.517063],"type":"Point"}
}