{
  "type": "Feature",
  "properties": {
    "addr:full":"Grande Prairie AB T8V 4Z1",
    "addr:postcode":"t8v 4z1",
    "iso:country":"CA",
    "sg:city":"Grande Prairie",
    "sg:classifiers":[
        {
            "category":"Restaurant",
            "type":"Food & Drink"
        }
    ],
    "sg:phone":"+1 780 538 4694",
    "sg:postcode":"T8V 4Z1",
    "sg:province":"AB",
    "sg:tags":[
        "caterer"
    ],
    "wof:name":"Camp Tamarack Assn",
    "wof:placetype":"venue"
},
  "geometry": {"coordinates":[-118.79489100000001,55.171162],"type":"Point"}
}