{
  "type": "Feature",
  "properties": {
    "addr:full":"2930 32 Ave NE Calgary AB T1Y 5J4",
    "addr:housenumber":"2930",
    "addr:postcode":"t1y 5j4",
    "addr:street":"32 Ave Ne",
    "iso:country":"CA",
    "sg:address":"2930 32 Ave NE",
    "sg:city":"Calgary",
    "sg:classifiers":[
        {
            "category":"Shopping",
            "subcategory":"Computers & Home Electronics",
            "type":"Retail Goods"
        }
    ],
    "sg:phone":"+1 403 250 9107",
    "sg:postcode":"T1Y 5J4",
    "sg:province":"AB",
    "sg:tags":[
        "high",
        "equipment",
        "fidelity",
        "stereophonic",
        "video"
    ],
    "wof:name":"Visions the Best Name-Elctrncs",
    "wof:placetype":"venue"
},
  "geometry": {"coordinates":[-113.99293518099999,51.0816917419],"type":"Point"}
}