{
  "type": "Feature",
  "properties": {
    "addr:full":"229 Rue Saint-Omer Levis QC G6V 6N4",
    "addr:housenumber":"229",
    "addr:postcode":"g6v 6n4",
    "addr:street":"Rue Saint-Omer",
    "iso:country":"CA",
    "sg:address":"229 Rue Saint-Omer",
    "sg:city":"Levis",
    "sg:classifiers":[
        {
            "category":"Local Transit",
            "type":"Transportation"
        }
    ],
    "sg:phone":"+1 418 837 2401",
    "sg:postcode":"G6V 6N4",
    "sg:province":"QC",
    "sg:tags":[
        "bus",
        "line"
    ],
    "wof:name":"Societe DE Transport DE Levis",
    "wof:placetype":"venue"
},
  "geometry": {"coordinates":[-71.1623306274,46.805809021],"type":"Point"}
}