{
  "type": "Feature",
  "properties": {
    "iso:country":"CA",
    "sg:city":"Coquitlam",
    "sg:classifiers":[
        {
            "category":"Building & Trades",
            "subcategory":"Construction",
            "type":"Services"
        }
    ],
    "sg:phone":"+1 604 686 5450",
    "sg:postcode":"V3J 3X4",
    "sg:province":"BC",
    "sg:tags":[
        "painter"
    ],
    "wof:name":"H & J Painting",
    "wof:placetype":"venue"
},
  "geometry": {"coordinates":[-122.890053,49.261757],"type":"Point"}
}