{
  "type": "Feature",
  "properties": {
    "iso:country":"CA",
    "sg:address":"580 Wonderland Rd S",
    "sg:city":"London",
    "sg:classifiers":[
        {
            "category":"Banks & Credit Unions",
            "subcategory":"Bank",
            "type":"Services"
        }
    ],
    "sg:phone":"+1 519 471 0812",
    "sg:postcode":"N6K 2Y8",
    "sg:province":"ON",
    "wof:name":"Scotiabank",
    "wof:placetype":"venue"
},
  "geometry": {"coordinates":[-81.2907791138,42.9553489685],"type":"Point"}
}