{
  "type": "Feature",
  "properties": {
    "addr:full":"67 Rue Sainte-Ursule Quebec QC G1R 4E7",
    "addr:housenumber":"67",
    "addr:postcode":"g1r 4e7",
    "addr:street":"Rue Sainte-Ursule",
    "iso:country":"CA",
    "sg:address":"67 Rue Sainte-Ursule",
    "sg:city":"Quebec",
    "sg:classifiers":[
        {
            "category":"Professional",
            "subcategory":"Lawyer & Legal Services",
            "type":"Services"
        }
    ],
    "sg:phone":"+1 418 692 3010",
    "sg:postcode":"G1R 4E7",
    "sg:province":"QC",
    "sg:tags":[
        "attorney"
    ],
    "wof:name":"Michaud, Jean-Paul",
    "wof:placetype":"venue"
},
  "geometry": {"coordinates":[-71.208946228,46.8105697632],"type":"Point"}
}