{
  "type": "Feature",
  "properties": {
    "addr:full":"Ottawa ON K1Z 7T2",
    "addr:postcode":"k1z 7t2",
    "iso:country":"CA",
    "sg:city":"Ottawa",
    "sg:classifiers":[
        {
            "category":"Retail",
            "subcategory":"Auto Repair",
            "type":"Services"
        }
    ],
    "sg:phone":"+1 613 728 2388",
    "sg:postcode":"K1Z 7T2",
    "sg:province":"ON",
    "sg:tags":[
        "repairing",
        "automobile"
    ],
    "wof:name":"Yeung's Auto Svc",
    "wof:placetype":"venue"
},
  "geometry": {"coordinates":[-75.7448043823,45.3767127991],"type":"Point"}
}