{
  "type": "Feature",
  "properties": {
    "addr:full":"21 Nelson St W Brampton ON L6X 1B6",
    "addr:housenumber":"21",
    "addr:postcode":"l6x 1b6",
    "addr:street":"Nelson St W",
    "iso:country":"CA",
    "sg:address":"21 Nelson St W",
    "sg:city":"Brampton",
    "sg:classifiers":[
        {
            "category":"Restaurant",
            "type":"Food & Drink"
        }
    ],
    "sg:phone":"+1 905 450 9548",
    "sg:postcode":"L6X 1B6",
    "sg:province":"ON",
    "wof:name":"Canada Eats",
    "wof:placetype":"venue"
},
  "geometry": {"coordinates":[-79.76234436039999,43.6862945557],"type":"Point"}
}