{
  "type": "Feature",
  "properties": {
    "addr:full":"175 Rue Lindsay Drummondville QC J2C 1N8",
    "addr:housenumber":"175",
    "addr:postcode":"j2c 1n8",
    "addr:street":"Rue Lindsay",
    "iso:country":"CA",
    "sg:address":"175 Rue Lindsay",
    "sg:city":"Drummondville",
    "sg:classifiers":[
        {
            "category":"Home & Garden",
            "subcategory":"Furniture",
            "type":"Retail Goods"
        }
    ],
    "sg:phone":"+1 819 475 9933",
    "sg:postcode":"J2C 1N8",
    "sg:province":"QC",
    "sg:tags":[
        "builder",
        "door",
        "custom"
    ],
    "wof:name":"Concept Dj Inc",
    "wof:placetype":"venue"
},
  "geometry": {"coordinates":[-72.4911651611,45.8845481873],"type":"Point"}
}