{
  "type": "Feature",
  "properties": {
    "addr:full":"5030 67 St Red Deer AB T4N 2R6",
    "addr:housenumber":"5030",
    "addr:postcode":"t4n 2r6",
    "addr:street":"67 St",
    "iso:country":"CA",
    "sg:address":"5030 67 St",
    "sg:city":"Red Deer",
    "sg:classifiers":[
        {
            "category":"Retail",
            "subcategory":"Auto Repair",
            "type":"Services"
        }
    ],
    "sg:phone":"+1 403 346 4124",
    "sg:postcode":"T4N 2R6",
    "sg:province":"AB",
    "sg:tags":[
        "repairing",
        "automobile",
        "tire"
    ],
    "wof:name":"Kal Tire",
    "wof:placetype":"venue"
},
  "geometry": {"coordinates":[-113.816574097,52.2887954712],"type":"Point"}
}