{
  "type": "Feature",
  "properties": {
    "addr:full":"5 Fourth St Walkerton ON N0G 2V0",
    "addr:housenumber":"5",
    "addr:postcode":"n0g 2v0",
    "addr:street":"Fourth St",
    "iso:country":"CA",
    "sg:address":"5 Fourth St",
    "sg:city":"Walkerton",
    "sg:classifiers":[
        {
            "category":"Professional",
            "subcategory":"Research",
            "type":"Services"
        }
    ],
    "sg:phone":"+1 519 881 0710",
    "sg:postcode":"N0G 2V0",
    "sg:province":"ON",
    "sg:tags":[
        "foundation",
        "philanthropic"
    ],
    "wof:name":"Walkerton Community Foundation",
    "wof:placetype":"venue"
},
  "geometry": {"coordinates":[-81.14976501460001,44.1177101135],"type":"Point"}
}