{
  "type": "Feature",
  "properties": {
    "addr:full":"858 Corydon Ave Winnipeg MB R3M 0Y4",
    "addr:housenumber":"858",
    "addr:postcode":"r3m 0y4",
    "addr:street":"Corydon Ave",
    "iso:country":"CA",
    "sg:address":"858 Corydon Ave",
    "sg:city":"Winnipeg",
    "sg:classifiers":[
        {
            "category":"Shopping",
            "subcategory":"Clothing, Apparel, & Fashions",
            "type":"Retail Goods"
        }
    ],
    "sg:phone":"+1 204 475 3148",
    "sg:postcode":"R3M 0Y4",
    "sg:province":"MB",
    "sg:tags":[
        "designer"
    ],
    "wof:name":"Olga Fashion Salon",
    "wof:placetype":"venue"
},
  "geometry": {"coordinates":[-97.15766143800001,49.8692169189],"type":"Point"}
}