{
  "type": "Feature",
  "properties": {
    "iso:country":"CA",
    "sg:city":"Kelowna",
    "sg:classifiers":[
        {
            "category":"Shopping",
            "subcategory":"Stationery & Office Supplies",
            "type":"Retail Goods"
        }
    ],
    "sg:phone":"+1 604 270 4648",
    "sg:postcode":"V1Y 5A1",
    "sg:province":"BC",
    "sg:tags":[
        "map"
    ],
    "wof:name":"Advanced Satellite Productions",
    "wof:placetype":"venue"
},
  "geometry": {"coordinates":[-119.474472046,49.8649711609],"type":"Point"}
}