{
  "type": "Feature",
  "properties": {
    "iso:country":"CA",
    "sg:address":"630 Montee Sainte-Julie",
    "sg:city":"Sainte-Julie",
    "sg:classifiers":[
        {
            "category":"Retail",
            "subcategory":"Portrait Studio",
            "type":"Services"
        }
    ],
    "sg:phone":"+1 450 649 5507",
    "sg:postcode":"J3E 1W8",
    "sg:province":"QC",
    "sg:tags":[
        "photographer"
    ],
    "wof:name":"Claude Lapointe Fotografik",
    "wof:placetype":"venue"
},
  "geometry": {"coordinates":[-73.33921051030001,45.5935897827],"type":"Point"}
}