{
  "type": "Feature",
  "properties": {
    "addr:full":"Calumet QC J0V 1B0",
    "addr:postcode":"j0v 1b0",
    "iso:country":"CA",
    "sg:city":"Calumet",
    "sg:classifiers":[
        {
            "category":"Food & Beverages",
            "subcategory":"Groceries & Convenience Stores",
            "type":"Retail Goods"
        }
    ],
    "sg:phone":"+1 819 242 9696",
    "sg:postcode":"J0V 1B0",
    "sg:province":"QC",
    "sg:tags":[
        "grocer"
    ],
    "wof:name":"Depanneur DE LA Place",
    "wof:placetype":"venue"
},
  "geometry": {"coordinates":[-74.7461853027,45.6446800232],"type":"Point"}
}