{
  "type": "Feature",
  "properties": {
    "addr:full":"1508 Yew St Vancouver BC V6K 3E4",
    "addr:housenumber":"1508",
    "addr:postcode":"v6k 3e4",
    "addr:street":"Yew St",
    "iso:country":"CA",
    "sg:address":"1508 Yew St",
    "sg:city":"Vancouver",
    "sg:classifiers":[
        {
            "category":"Restaurant",
            "type":"Food & Drink"
        }
    ],
    "sg:phone":"+1 604 731 4482",
    "sg:postcode":"V6K 3E4",
    "sg:province":"BC",
    "wof:name":"Kibune Sushi Restaurant",
    "wof:placetype":"venue"
},
  "geometry": {"coordinates":[-123.15476200000001,49.272476],"type":"Point"}
}