{
  "type": "Feature",
  "properties": {
    "iso:country":"CA",
    "sg:address":"55 Weston Crt",
    "sg:city":"Dartmouth",
    "sg:classifiers":[
        {
            "category":"Wholesale",
            "subcategory":"Groceries",
            "type":"Manufacturing & Wholesale Goods"
        }
    ],
    "sg:phone":"+1 902 468 8990",
    "sg:postcode":"B3B 2C8",
    "sg:province":"NS",
    "sg:tags":[
        "food",
        "broker"
    ],
    "wof:name":"Concord National",
    "wof:placetype":"venue"
},
  "geometry": {"coordinates":[-63.5835800171,44.7127876282],"type":"Point"}
}