{
  "type": "Feature",
  "properties": {
    "addr:full":"5400 Portage Rd #S605 Niagara Falls ON L2G 5X7",
    "addr:housenumber":"5400",
    "addr:postcode":"l2g 5x7",
    "addr:street":"Portage Rd # S605",
    "iso:country":"CA",
    "sg:address":"5400 Portage Rd #S605",
    "sg:city":"Niagara Falls",
    "sg:classifiers":[
        {
            "category":"Health Services",
            "subcategory":"Doctor",
            "type":"Services"
        }
    ],
    "sg:phone":"+1 905 356 7919",
    "sg:postcode":"L2G 5X7",
    "sg:province":"ON",
    "sg:tags":[
        "dentist"
    ],
    "wof:name":"Doucet Orthodontics",
    "wof:placetype":"venue"
},
  "geometry": {"coordinates":[-79.0908050537,43.0959663391],"type":"Point"}
}