{
  "type": "Feature",
  "properties": {
    "addr:full":"5757 Boul Thimens Saint-Laurent QC H4R 2H6",
    "addr:housenumber":"5757",
    "addr:postcode":"h4r 2h6",
    "addr:street":"Boul Thimens",
    "iso:country":"CA",
    "sg:address":"5757 Boul Thimens",
    "sg:city":"Saint-Laurent",
    "sg:classifiers":[
        {
            "category":"Wholesale",
            "subcategory":"Stationery",
            "type":"Manufacturing & Wholesale Goods"
        }
    ],
    "sg:phone":"+1 514 335 0333",
    "sg:postcode":"H4R 2H6",
    "sg:province":"QC",
    "sg:tags":[
        "packaging",
        "material"
    ],
    "wof:name":"Dorfin Distribution Inc",
    "wof:placetype":"venue"
},
  "geometry": {"coordinates":[-73.732956,45.500671],"type":"Point"}
}