{
  "type": "Feature",
  "properties": {
    "addr:full":"906 Wilson Ave North York ON M3K 1E7",
    "addr:housenumber":"906",
    "addr:postcode":"m3k 1e7",
    "addr:street":"Wilson Ave",
    "iso:country":"CA",
    "sg:address":"906 Wilson Ave",
    "sg:city":"North York",
    "sg:classifiers":[
        {
            "category":"Shopping",
            "type":"Retail Goods"
        }
    ],
    "sg:phone":"+1 416 630 3873",
    "sg:postcode":"M3K 1E7",
    "sg:province":"ON",
    "sg:tags":[
        "equipment",
        "telephone",
        "supply"
    ],
    "wof:name":"Telecord Communications",
    "wof:placetype":"venue"
},
  "geometry": {"coordinates":[-79.4694900513,43.7301864624],"type":"Point"}
}