{
  "type": "Feature",
  "properties": {
    "addr:full":"321 Boul D'Youville Chateauguay QC J6J 4S1",
    "addr:housenumber":"321",
    "addr:postcode":"j6j 4s1",
    "addr:street":"Boul D'Youville",
    "iso:country":"CA",
    "sg:address":"321 Boul D'Youville",
    "sg:city":"Chateauguay",
    "sg:classifiers":[
        {
            "category":"Autos & Motor Vehicles",
            "subcategory":"Boat Sales",
            "type":"Retail Goods"
        }
    ],
    "sg:phone":"+1 450 699 9217",
    "sg:postcode":"J6J 4S1",
    "sg:province":"QC",
    "sg:tags":[
        "dealer"
    ],
    "wof:name":"R L Marine & Sports",
    "wof:placetype":"venue"
},
  "geometry": {"coordinates":[-73.7498474121,45.3612518311],"type":"Point"}
}