{
  "type": "Feature",
  "properties": {
    "addr:full":"260 Av Labrosse Pointe-Claire QC H9R 5L5",
    "addr:housenumber":"260",
    "addr:postcode":"h9r 5l5",
    "addr:street":"Av Labrosse",
    "iso:country":"CA",
    "sg:address":"260 Av Labrosse",
    "sg:city":"Pointe-Claire",
    "sg:classifiers":[
        {
            "category":"Professional",
            "subcategory":"Advertising",
            "type":"Services"
        }
    ],
    "sg:phone":"+1 514 695 1430",
    "sg:postcode":"H9R 5L5",
    "sg:province":"QC",
    "sg:tags":[
        "mail",
        "mailing",
        "shipping"
    ],
    "wof:name":"Harling Marketing Inc",
    "wof:placetype":"venue"
},
  "geometry": {"coordinates":[-73.827835083,45.4711036682],"type":"Point"}
}