{
  "type": "Feature",
  "properties": {
    "iso:country":"CA",
    "sg:address":"585 Algonquin Blvd E",
    "sg:city":"Timmins",
    "sg:classifiers":[
        {
            "category":"Real Estate",
            "subcategory":"Real Estate Operator",
            "type":"Services"
        }
    ],
    "sg:phone":"+1 705 264 8986",
    "sg:postcode":"P4N 7N6",
    "sg:province":"ON",
    "sg:tags":[
        "apartment"
    ],
    "wof:name":"Senator Place Apartments",
    "wof:placetype":"venue"
},
  "geometry": {"coordinates":[-81.3189620972,48.4766693115],"type":"Point"}
}