{
  "type": "Feature",
  "properties": {
    "addr:full":"100 Boul Pie-Xii Magog QC J1X 1E5",
    "addr:housenumber":"100",
    "addr:postcode":"j1x 1e5",
    "addr:street":"Boul Pie-Xii",
    "iso:country":"CA",
    "sg:address":"100 Boul Pie-Xii",
    "sg:city":"Magog",
    "sg:classifiers":[
        {
            "category":"Home & Garden",
            "subcategory":"Household Appliances",
            "type":"Retail Goods"
        }
    ],
    "sg:phone":"+1 819 843 4677",
    "sg:postcode":"J1X 1E5",
    "sg:province":"QC",
    "sg:tags":[
        "cleaners",
        "vacuum"
    ],
    "wof:name":"Vacuum Rp Magog Inc",
    "wof:placetype":"venue"
},
  "geometry": {"coordinates":[-72.140396,45.272926],"type":"Point"}
}