{
  "type": "Feature",
  "properties": {
    "addr:full":"770 Pass Lake E Rd Pass Lake ON P0T 2M0",
    "addr:housenumber":"770",
    "addr:postcode":"p0t 2m0",
    "addr:street":"Pass Lake E Rd",
    "iso:country":"CA",
    "sg:address":"770 Pass Lake E Rd",
    "sg:city":"Pass Lake",
    "sg:classifiers":[
        {
            "category":"Retail",
            "subcategory":"Animal Services",
            "type":"Services"
        }
    ],
    "sg:phone":"+1 807 977 2469",
    "sg:postcode":"P0T 2M0",
    "sg:province":"ON",
    "sg:tags":[
        "pet",
        "boarding",
        "sitting"
    ],
    "wof:name":"Thunder Bear Boarding Kennels",
    "wof:placetype":"venue"
},
  "geometry": {"coordinates":[-88.738029,48.563972],"type":"Point"}
}