{
  "type": "Feature",
  "properties": {
    "iso:country":"CA",
    "sg:address":"185 Rideau Street Second Floor",
    "sg:city":"Ottawa",
    "sg:classifiers":[
        {
            "category":"Professional",
            "subcategory":"Computer Services",
            "type":"Services"
        }
    ],
    "sg:postcode":"K1N 5X8",
    "sg:tags":[
        "Shopify",
        "e-commerce",
        "jaded-Pixel",
        "online-store",
        "e-store",
        "Ruby-on-Rails",
        "Rails"
    ],
    "sg:website":"http://www.shopify.com",
    "wof:name":"jaded Pixel",
    "wof:placetype":"venue"
},
  "geometry": {"coordinates":[-75.689004,45.42739],"type":"Point"}
}