{
  "type": "Feature",
  "properties": {
    "iso:country":"CA",
    "sg:address":"317 Main St",
    "sg:city":"Selkirk",
    "sg:classifiers":[
        {
            "category":"Shopping",
            "subcategory":"Gifts & Souvenirs",
            "type":"Retail Goods"
        }
    ],
    "sg:phone":"+1 204 482 9260",
    "sg:postcode":"R1A 1S7",
    "sg:province":"MB",
    "sg:tags":[
        "shop"
    ],
    "wof:name":"For Keeps",
    "wof:placetype":"venue"
},
  "geometry": {"coordinates":[-96.87744903559999,50.1414031982],"type":"Point"}
}