{
  "type": "Feature",
  "properties": {
    "addr:full":"688 Main St Birtle MB R0M 0C0",
    "addr:housenumber":"688",
    "addr:postcode":"r0m 0c0",
    "addr:street":"Main St",
    "iso:country":"CA",
    "sg:address":"688 Main St",
    "sg:city":"Birtle",
    "sg:classifiers":[
        {
            "category":"Professional",
            "subcategory":"Lawyer & Legal Services",
            "type":"Services"
        }
    ],
    "sg:phone":"+1 204 842 3355",
    "sg:postcode":"R0M 0C0",
    "sg:province":"MB",
    "sg:tags":[
        "attorney"
    ],
    "wof:name":"Sims & CO",
    "wof:placetype":"venue"
},
  "geometry": {"coordinates":[-101.049088,50.421989],"type":"Point"}
}