{
  "type": "Feature",
  "properties": {
    "addr:full":"3877 Av Draper Montreal QC H4A 2N9",
    "addr:housenumber":"3877",
    "addr:postcode":"h4a 2n9",
    "addr:street":"Av Draper",
    "iso:country":"CA",
    "sg:address":"3877 Av Draper",
    "sg:city":"Montreal",
    "sg:classifiers":[
        {
            "category":"Communications",
            "subcategory":"Film & Video Production",
            "type":"Services"
        }
    ],
    "sg:phone":"+1 514 486 8456",
    "sg:postcode":"H4A 2N9",
    "sg:province":"QC",
    "sg:tags":[
        "taping"
    ],
    "wof:name":"Kerrigan Productions Inc",
    "wof:placetype":"venue"
},
  "geometry": {"coordinates":[-73.620712,45.470638],"type":"Point"}
}