{
  "type": "Feature",
  "properties": {
    "addr:full":"3880 74 Ave NW Edmonton AB T6B 2P7",
    "addr:housenumber":"3880",
    "addr:postcode":"t6b 2p7",
    "addr:street":"74 Ave Nw",
    "iso:country":"CA",
    "sg:address":"3880 74 Ave NW",
    "sg:city":"Edmonton",
    "sg:classifiers":[
        {
            "category":"Manufacturing",
            "subcategory":"Metals",
            "type":"Manufacturing & Wholesale Goods"
        }
    ],
    "sg:phone":"+1 780 466 9869",
    "sg:postcode":"T6B 2P7",
    "sg:province":"AB",
    "sg:tags":[
        "fastener"
    ],
    "wof:name":"Precision Bolting Ltd",
    "wof:placetype":"venue"
},
  "geometry": {"coordinates":[-113.400887,53.510445],"type":"Point"}
}