{
  "type": "Feature",
  "properties": {
    "addr:full":"2550 Kingsway Vancouver BC V5R 5H2",
    "addr:housenumber":"2550",
    "addr:postcode":"v5r 5h2",
    "addr:street":"Kingsway",
    "iso:country":"CA",
    "sg:address":"2550 Kingsway",
    "sg:city":"Vancouver",
    "sg:classifiers":[
        {
            "category":"Restaurant",
            "type":"Food & Drink"
        }
    ],
    "sg:phone":"+1 604 439 1318",
    "sg:postcode":"V5R 5H2",
    "sg:province":"BC",
    "wof:name":"Tsui Yuen Restaurant",
    "wof:placetype":"venue"
},
  "geometry": {"coordinates":[-123.05313099999999,49.239418],"type":"Point"}
}