{
  "type": "Feature",
  "properties": {
    "iso:country":"CA",
    "sg:address":"3950 14th Ave # 503",
    "sg:city":"Markham",
    "sg:classifiers":[
        {
            "category":"Professional",
            "subcategory":"Accounting & Tax Preparation",
            "type":"Services"
        }
    ],
    "sg:phone":"+1 905 948 8830",
    "sg:postcode":"L3R 0A9",
    "sg:province":"ON",
    "sg:tags":[
        "accountant"
    ],
    "wof:name":"Sound Count Consultant",
    "wof:placetype":"venue"
},
  "geometry": {"coordinates":[-79.322624,43.839436],"type":"Point"}
}