{
  "type": "Feature",
  "properties": {
    "addr:full":"21 Market St Foxwarren MB R0J 0R0",
    "addr:housenumber":"21",
    "addr:postcode":"r0j 0r0",
    "addr:street":"Market St",
    "iso:country":"CA",
    "sg:address":"21 Market St",
    "sg:city":"Foxwarren",
    "sg:classifiers":[
        {
            "category":"Retail",
            "subcategory":"Repair Shop",
            "type":"Services"
        }
    ],
    "sg:phone":"+1 204 847 2227",
    "sg:postcode":"R0J 0R0",
    "sg:province":"MB",
    "sg:tags":[
        "welding"
    ],
    "wof:name":"Moulson's Welding",
    "wof:placetype":"venue"
},
  "geometry": {"coordinates":[-101.15329,50.520729],"type":"Point"}
}