{
  "type": "Feature",
  "properties": {
    "addr:full":"635 Hood Rd Markham ON L3R 4N6",
    "addr:housenumber":"635",
    "addr:postcode":"l3r 4n6",
    "addr:street":"Hood Rd",
    "iso:country":"CA",
    "sg:address":"635 Hood Rd",
    "sg:city":"Markham",
    "sg:classifiers":[
        {
            "category":"Manufacturing",
            "subcategory":"Electronics",
            "type":"Manufacturing & Wholesale Goods"
        }
    ],
    "sg:phone":"+1 905 479 1810",
    "sg:postcode":"L3R 4N6",
    "sg:province":"ON",
    "sg:tags":[
        "equipment",
        "electronic",
        "supply"
    ],
    "wof:name":"Smtc Corp",
    "wof:placetype":"venue"
},
  "geometry": {"coordinates":[-79.33029174799999,43.8354721069],"type":"Point"}
}