{
  "type": "Feature",
  "properties": {
    "iso:country":"CA",
    "sg:address":"250 Bloor St W",
    "sg:city":"Oshawa",
    "sg:classifiers":[
        {
            "category":"Retail",
            "subcategory":"Repair Shop",
            "type":"Services"
        }
    ],
    "sg:phone":"+1 905 404 0480",
    "sg:postcode":"L1J 1P8",
    "sg:province":"ON",
    "sg:tags":[
        "upholsterer"
    ],
    "wof:name":"L A Upholstery & Custom Design",
    "wof:placetype":"venue"
},
  "geometry": {"coordinates":[-78.864983,43.87849],"type":"Point"}
}