{
  "type": "Feature",
  "properties": {
    "addr:full":"Saint-Joseph-DE-Beauce QC G0S 2V0",
    "addr:postcode":"g0s 2v0",
    "iso:country":"CA",
    "sg:city":"Saint-Joseph-DE-Beauce",
    "sg:classifiers":[
        {
            "category":"Taxi",
            "type":"Transportation"
        }
    ],
    "sg:phone":"+1 418 397 6222",
    "sg:postcode":"G0S 2V0",
    "sg:province":"QC",
    "sg:tags":[
        "taxicab"
    ],
    "wof:name":"Taxi Adrien Plante",
    "wof:placetype":"venue"
},
  "geometry": {"coordinates":[-70.880608,46.30788],"type":"Point"}
}