{
  "type": "Feature",
  "properties": {
    "addr:full":"Pickering ON L1V 1B8",
    "addr:postcode":"l1v 1b8",
    "iso:country":"CA",
    "sg:city":"Pickering",
    "sg:classifiers":[
        {
            "category":"Shopping",
            "subcategory":"Jewelry",
            "type":"Retail Goods"
        }
    ],
    "sg:phone":"+1 905 421 0255",
    "sg:postcode":"L1V 1B8",
    "sg:province":"ON",
    "sg:tags":[
        "jeweler"
    ],
    "wof:name":"Oro Jewellers",
    "wof:placetype":"venue"
},
  "geometry": {"coordinates":[-79.0872421265,43.8379707336],"type":"Point"}
}