{
  "type": "Feature",
  "properties": {
    "addr:full":"4593 Ch Saint-Isidore Jonquiere QC G7X 7V5",
    "addr:postcode":"4593;g7x 7v5",
    "addr:street":"Ch Saint-Isidore",
    "iso:country":"CA",
    "sg:address":"4593 Ch Saint-Isidore",
    "sg:city":"Jonquiere",
    "sg:classifiers":[
        {
            "category":"Freight",
            "type":"Transportation"
        }
    ],
    "sg:phone":"+1 418 547 4921",
    "sg:postcode":"G7X 7V5",
    "sg:province":"QC",
    "sg:tags":[
        "mover"
    ],
    "wof:name":"Demenagement Jcl Inc",
    "wof:placetype":"venue"
},
  "geometry": {"coordinates":[-71.305244,48.423832],"type":"Point"}
}