{
  "type": "Feature",
  "properties": {
    "addr:full":"Regina SK S4S 7B9",
    "addr:postcode":"s4s 7b9",
    "iso:country":"CA",
    "sg:city":"Regina",
    "sg:classifiers":[
        {
            "category":"Professional",
            "subcategory":"Engineering",
            "type":"Services"
        }
    ],
    "sg:phone":"+1 306 584 8833",
    "sg:postcode":"S4S 7B9",
    "sg:province":"SK",
    "sg:tags":[
        "engineer"
    ],
    "wof:name":"Brownlee Beaton Kreke",
    "wof:placetype":"venue"
},
  "geometry": {"coordinates":[-104.64113616900001,50.4149971008],"type":"Point"}
}