{
  "type": "Feature",
  "properties": {
    "addr:full":"382 Main St Antigonish NS B2G 2L6",
    "addr:housenumber":"382",
    "addr:postcode":"b2g 2l6",
    "addr:street":"Main St",
    "iso:country":"CA",
    "sg:address":"382 Main St",
    "sg:city":"Antigonish",
    "sg:classifiers":[
        {
            "category":"Restaurant",
            "type":"Food & Drink"
        }
    ],
    "sg:phone":"+1 902 863 4565",
    "sg:postcode":"B2G 2L6",
    "sg:province":"NS",
    "wof:name":"Wheel Pizza & Sub Shop",
    "wof:placetype":"venue"
},
  "geometry": {"coordinates":[-61.994648,45.621948],"type":"Point"}
}