{
  "type": "Feature",
  "properties": {
    "addr:full":"445 Eastchester Ave E St Catharines ON L2M 6S2",
    "addr:housenumber":"445",
    "addr:postcode":"l2m 6s2",
    "addr:street":"Eastchester Ave E",
    "iso:country":"CA",
    "sg:address":"445 Eastchester Ave E",
    "sg:city":"St Catharines",
    "sg:classifiers":[
        {
            "category":"Building & Trades",
            "subcategory":"Construction",
            "type":"Services"
        }
    ],
    "sg:phone":"+1 905 688 9777",
    "sg:postcode":"L2M 6S2",
    "sg:province":"ON",
    "sg:tags":[
        "woodworker"
    ],
    "wof:name":"Cnc Woodcraft Ltd",
    "wof:placetype":"venue"
},
  "geometry": {"coordinates":[-79.203742981,43.1694793701],"type":"Point"}
}