{
  "type": "Feature",
  "properties": {
    "addr:full":"Highway 17 White River ON P0M 3G0",
    "addr:postcode":"p0m 3g0",
    "addr:street":"Highway 17",
    "iso:country":"CA",
    "sg:address":"Highway 17",
    "sg:city":"White River",
    "sg:classifiers":[
        {
            "category":"Travel",
            "subcategory":"Hotels & Motels",
            "type":"Entertainment"
        }
    ],
    "sg:phone":"+1 807 822 2386",
    "sg:postcode":"P0M 3G0",
    "sg:province":"ON",
    "sg:tags":[
        "resort"
    ],
    "wof:name":"White Lake Lodge",
    "wof:placetype":"venue"
},
  "geometry": {"coordinates":[-85.274811,48.593121],"type":"Point"}
}