{
  "type": "Feature",
  "properties": {
    "addr:full":"219 1st St E Regina Beach SK S0G 4C0",
    "addr:housenumber":"219",
    "addr:postcode":"s0g 4c0",
    "addr:street":"1St St E Regina Beach",
    "iso:country":"CA",
    "sg:address":"219 1st St E",
    "sg:city":"Regina Beach",
    "sg:classifiers":[
        {
            "category":"Government",
            "subcategory":"Post Office",
            "type":"Public Place"
        }
    ],
    "sg:phone":"+1 306 729 4999",
    "sg:postcode":"S0G 4C0",
    "sg:province":"SK",
    "wof:name":"Canada Post",
    "wof:placetype":"venue"
},
  "geometry": {"coordinates":[-104.97403,50.787136],"type":"Point"}
}