{
  "type": "Feature",
  "properties": {
    "iso:country":"CA",
    "sg:address":"1152 Rue Hebert",
    "sg:city":"Desbiens",
    "sg:classifiers":[
        {
            "category":"Food & Beverages",
            "subcategory":"Groceries & Convenience Stores",
            "type":"Retail Goods"
        }
    ],
    "sg:phone":"+1 418 346 5624",
    "sg:postcode":"G0W 1N0",
    "sg:province":"QC",
    "wof:name":"Depanneur Ld Frigon",
    "wof:placetype":"venue"
},
  "geometry": {"coordinates":[-71.94547300000001,48.417114],"type":"Point"}
}