{
  "type": "Feature",
  "properties": {
    "iso:country":"CA",
    "sg:city":"Greenfield Park",
    "sg:classifiers":[
        {
            "category":"Real Estate",
            "subcategory":"Real Estate Agent",
            "type":"Services"
        }
    ],
    "sg:phone":"+1 450 671 6300",
    "sg:postcode":"J4V 1M9",
    "sg:province":"QC",
    "sg:tags":[
        "management"
    ],
    "wof:name":"Immocredit Inc",
    "wof:placetype":"venue"
},
  "geometry": {"coordinates":[-73.474747,45.477051],"type":"Point"}
}