{
  "type": "Feature",
  "properties": {
    "addr:full":"1400 Industrial Rd Kelowna BC V1Z 1G5",
    "addr:housenumber":"1400",
    "addr:postcode":"v1z 1g5",
    "addr:street":"Industrial Rd",
    "iso:country":"CA",
    "sg:address":"1400 Industrial Rd",
    "sg:city":"Kelowna",
    "sg:classifiers":[
        {
            "category":"Manufacturing",
            "subcategory":"Metals",
            "type":"Manufacturing & Wholesale Goods"
        }
    ],
    "sg:phone":"+1 250 769 4001",
    "sg:postcode":"V1Z 1G5",
    "sg:province":"BC",
    "sg:tags":[
        "steel"
    ],
    "wof:name":"Northside Industries Inc",
    "wof:placetype":"venue"
},
  "geometry": {"coordinates":[-119.56955000000001,49.864307],"type":"Point"}
}