{
  "type": "Feature",
  "properties": {
    "iso:country":"CA",
    "sg:address":"81 Peter St",
    "sg:city":"Toronto",
    "sg:classifiers":[
        {
            "category":"Professional",
            "subcategory":"Computer Services",
            "type":"Services"
        }
    ],
    "sg:phone":"+1 416 408 1212",
    "sg:postcode":"M5V 2G4",
    "sg:province":"ON",
    "sg:tags":[
        "consulting",
        "multimedia",
        "dev",
        "internet",
        "home",
        "page"
    ],
    "wof:name":"Web Feat Multimedia Inc",
    "wof:placetype":"venue"
},
  "geometry": {"coordinates":[-79.39250946040001,43.6470298767],"type":"Point"}
}