{
  "type": "Feature",
  "properties": {
    "addr:full":"9704 27 Ave NW Edmonton AB T6N 1B2",
    "addr:housenumber":"9704",
    "addr:postcode":"t6n 1b2",
    "addr:street":"27 Ave Nw",
    "iso:country":"CA",
    "sg:address":"9704 27 Ave NW",
    "sg:city":"Edmonton",
    "sg:classifiers":[
        {
            "category":"Retail",
            "subcategory":"Auto Repair",
            "type":"Services"
        }
    ],
    "sg:phone":"+1 780 414 6755",
    "sg:postcode":"T6N 1B2",
    "sg:province":"AB",
    "sg:tags":[
        "body",
        "automobile",
        "painting"
    ],
    "wof:name":"Cosmo's Auto Body & Repair Ltd",
    "wof:placetype":"venue"
},
  "geometry": {"coordinates":[-113.47777600000001,53.457043],"type":"Point"}
}