{
  "type": "Feature",
  "properties": {
    "addr:full":"1725 Boul Lemire Drummondville QC J2C 5A5",
    "addr:housenumber":"1725",
    "addr:postcode":"j2c 5a5",
    "addr:street":"Boul Lemire",
    "iso:country":"CA",
    "sg:address":"1725 Boul Lemire",
    "sg:city":"Drummondville",
    "sg:classifiers":[
        {
            "category":"Building & Trades",
            "subcategory":"Plumbing",
            "type":"Services"
        }
    ],
    "sg:phone":"+1 819 477 1070",
    "sg:postcode":"J2C 5A5",
    "sg:province":"QC",
    "sg:tags":[
        "system",
        "air",
        "parts",
        "conditioning",
        "contractor",
        "refrigerating"
    ],
    "wof:name":"Midbec Limitee",
    "wof:placetype":"venue"
},
  "geometry": {"coordinates":[-72.50885009770001,45.8694419861],"type":"Point"}
}