{
  "type": "Feature",
  "properties": {
    "addr:full":"876 72nd Ave Grand Forks BC V0H 1H0",
    "addr:housenumber":"876",
    "addr:postcode":"v0h 1h0",
    "addr:street":"72Nd Ave",
    "iso:country":"CA",
    "sg:address":"876 72nd Ave",
    "sg:city":"Grand Forks",
    "sg:classifiers":[
        {
            "category":"Health Services",
            "subcategory":"Nursing And Care Facility",
            "type":"Services"
        }
    ],
    "sg:phone":"+1 250 442 2223",
    "sg:postcode":"V0H 1H0",
    "sg:province":"BC",
    "sg:tags":[
        "home",
        "retirement",
        "community"
    ],
    "wof:name":"Abbeyfield Centennial House",
    "wof:placetype":"venue"
},
  "geometry": {"coordinates":[-118.444633,49.029381],"type":"Point"}
}