{
  "type": "Feature",
  "properties": {
    "addr:full":"250 Trans Canada Hwy Duncan BC V9L 3P9",
    "addr:housenumber":"250",
    "addr:postcode":"v9l 3p9",
    "addr:street":"Trans Canada Hwy",
    "iso:country":"CA",
    "sg:address":"250 Trans Canada Hwy",
    "sg:city":"Duncan",
    "sg:classifiers":[
        {
            "category":"Restaurant",
            "type":"Food & Drink"
        }
    ],
    "sg:phone":"+1 250 715 1118",
    "sg:postcode":"V9L 3P9",
    "sg:province":"BC",
    "wof:name":"Salty's Fish & Chips",
    "wof:placetype":"venue"
},
  "geometry": {"coordinates":[-123.698623657,48.7763061523],"type":"Point"}
}