{
  "type": "Feature",
  "properties": {
    "addr:full":"976 Rue Lacasse Montreal QC H4C 2Z3",
    "addr:housenumber":"976",
    "addr:postcode":"h4c 2z3",
    "addr:street":"Rue Lacasse",
    "iso:country":"CA",
    "sg:address":"976 Rue Lacasse",
    "sg:city":"Montreal",
    "sg:classifiers":[
        {
            "category":"Building & Trades",
            "subcategory":"Construction",
            "type":"Services"
        }
    ],
    "sg:phone":"+1 514 939 3522",
    "sg:postcode":"H4C 2Z3",
    "sg:province":"QC",
    "sg:tags":[
        "maker",
        "cabinet"
    ],
    "wof:name":"Ebenisterie Nova Style Enr",
    "wof:placetype":"venue"
},
  "geometry": {"coordinates":[-73.59166,45.477081],"type":"Point"}
}