{
  "type": "Feature",
  "properties": {
    "addr:full":"28 Melanie Dr # 3 Brampton ON L6T 4H7",
    "addr:housenumber":"28",
    "addr:postcode":"l6t 4h7",
    "addr:street":"Melanie Dr # 3",
    "iso:country":"CA",
    "sg:address":"28 Melanie Dr # 3",
    "sg:city":"Brampton",
    "sg:classifiers":[
        {
            "category":"Retail",
            "subcategory":"Auto Repair",
            "type":"Services"
        }
    ],
    "sg:phone":"+1 905 792 4358",
    "sg:postcode":"L6T 4H7",
    "sg:province":"ON",
    "sg:tags":[
        "repairing",
        "automobile"
    ],
    "wof:name":"Five Star Auto & Truck Svc",
    "wof:placetype":"venue"
},
  "geometry": {"coordinates":[-79.6799240112,43.7110404968],"type":"Point"}
}