{
  "type": "Feature",
  "properties": {
    "addr:full":"16 Lisa St Brampton ON L6T 5R2",
    "addr:housenumber":"16",
    "addr:postcode":"l6t 5r2",
    "addr:street":"Lisa St",
    "iso:country":"CA",
    "sg:address":"16 Lisa St",
    "sg:city":"Brampton",
    "sg:classifiers":[
        {
            "category":"Cinema",
            "subcategory":"Movie Rental",
            "type":"Entertainment"
        }
    ],
    "sg:phone":"+1 905 453 3799",
    "sg:postcode":"L6T 5R2",
    "sg:province":"ON",
    "sg:tags":[
        "leasing",
        "video",
        "disc",
        "tape"
    ],
    "wof:name":"Rogers Video",
    "wof:placetype":"venue"
},
  "geometry": {"coordinates":[-79.72732499999999,43.712242],"type":"Point"}
}