{
  "type": "Feature",
  "properties": {
    "addr:full":"1021 Wonderland Rd S London ON N6K 3V1",
    "addr:housenumber":"1021",
    "addr:postcode":"n6k 3v1",
    "addr:street":"Wonderland Rd",
    "iso:country":"CA",
    "sg:address":"1021 Wonderland Rd S",
    "sg:city":"London",
    "sg:classifiers":[
        {
            "category":"Personal",
            "subcategory":"Tanning Parlor",
            "type":"Services"
        }
    ],
    "sg:phone":"+1 519 649 0385",
    "sg:postcode":"N6K 3V1",
    "sg:province":"ON",
    "sg:tags":[
        "salon"
    ],
    "wof:name":"Hollywood Tan",
    "wof:placetype":"venue"
},
  "geometry": {"coordinates":[-81.282562,42.941547],"type":"Point"}
}