{
  "type": "Feature",
  "properties": {
    "addr:full":"53 Pembroke St W Pembroke ON K8A 5M5",
    "addr:housenumber":"53",
    "addr:postcode":"k8a 5m5",
    "addr:street":"Pembroke St W",
    "iso:country":"CA",
    "sg:address":"53 Pembroke St W",
    "sg:city":"Pembroke",
    "sg:classifiers":[
        {
            "category":"Shopping",
            "subcategory":"Florist",
            "type":"Retail Goods"
        }
    ],
    "sg:phone":"+1 613 735 0626",
    "sg:postcode":"K8A 5M5",
    "sg:province":"ON",
    "wof:name":"Fraser Flowers Ltd",
    "wof:placetype":"venue"
},
  "geometry": {"coordinates":[-77.113998,45.826092],"type":"Point"}
}