{
  "type": "Feature",
  "properties": {
    "addr:full":"24 9th St E Cornwall ON K6H 2T8",
    "addr:housenumber":"24",
    "addr:postcode":"k6h 2t8",
    "addr:street":"9Th St E",
    "iso:country":"CA",
    "sg:address":"24 9th St E",
    "sg:city":"Cornwall",
    "sg:classifiers":[
        {
            "category":"Wholesale",
            "subcategory":"Machinery & Supplies",
            "type":"Manufacturing & Wholesale Goods"
        }
    ],
    "sg:phone":"+1 613 932 7010",
    "sg:postcode":"K6H 2T8",
    "sg:province":"ON",
    "sg:tags":[
        "equipment",
        "winery",
        "wine"
    ],
    "wof:name":"Cornwall Fine Wines",
    "wof:placetype":"venue"
},
  "geometry": {"coordinates":[-74.7340621948,45.0287666321],"type":"Point"}
}