{
  "type": "Feature",
  "properties": {
    "addr:full":"9651 Boul Louis-H.-Lafontaine Anjou QC H1J 2A3",
    "addr:housenumber":"9651",
    "addr:postcode":"h1j 2a3",
    "addr:street":"Boul Louis-H.-Lafontaine",
    "iso:country":"CA",
    "sg:address":"9651 Boul Louis-H.-Lafontaine",
    "sg:city":"Anjou",
    "sg:classifiers":[
        {
            "category":"Retail",
            "subcategory":"Auto Rental",
            "type":"Services"
        }
    ],
    "sg:phone":"+1 514 351 6940",
    "sg:postcode":"H1J 2A3",
    "sg:province":"QC",
    "sg:tags":[
        "renting",
        "truck",
        "leasing"
    ],
    "wof:name":"Camions Lague Inc",
    "wof:placetype":"venue"
},
  "geometry": {"coordinates":[-73.57710299999999,45.610184],"type":"Point"}
}