{
  "type": "Feature",
  "properties": {
    "addr:full":"9301 19th Ave North Battleford SK S9A 3N5",
    "addr:housenumber":"9301",
    "addr:postcode":"s9a 3n5",
    "addr:street":"19Th Ave",
    "iso:country":"CA",
    "sg:address":"9301 19th Ave",
    "sg:city":"North Battleford",
    "sg:classifiers":[
        {
            "category":"Education",
            "subcategory":"School",
            "type":"Public Place"
        }
    ],
    "sg:phone":"+1 306 445 6158",
    "sg:postcode":"S9A 3N5",
    "sg:province":"SK",
    "wof:name":"North West Roman Catholic Schl",
    "wof:placetype":"venue"
},
  "geometry": {"coordinates":[-108.30727400000001,52.785576],"type":"Point"}
}