{
  "type": "Feature",
  "properties": {
    "addr:full":"9516 342nd Ave Oliver BC V0H 1T0",
    "addr:housenumber":"9516",
    "addr:postcode":"bc v0h 1t0",
    "addr:street":"342Nd Ave",
    "iso:country":"CA",
    "sg:address":"9516 342nd Ave",
    "sg:city":"Oliver",
    "sg:classifiers":[
        {
            "category":"Organizations",
            "subcategory":"Religious Organization",
            "type":"Services"
        }
    ],
    "sg:phone":"+1 250 498 2152",
    "sg:postcode":"V0H 1T0",
    "sg:province":"BC",
    "sg:tags":[
        "church"
    ],
    "wof:name":"St Paul's Lutheran Church",
    "wof:placetype":"venue"
},
  "geometry": {"coordinates":[-119.552627563,49.1742706299],"type":"Point"}
}