{
  "type": "Feature",
  "properties": {
    "addr:full":"6 Valor Crt Stoney Creek ON L8E 4S5",
    "addr:housenumber":"6",
    "addr:postcode":"l8e 4s5",
    "addr:street":"Valor Crt",
    "iso:country":"CA",
    "sg:address":"6 Valor Crt",
    "sg:city":"Stoney Creek",
    "sg:classifiers":[
        {
            "category":"Building & Trades",
            "subcategory":"Construction",
            "type":"Services"
        }
    ],
    "sg:phone":"+1 905 643 0151",
    "sg:postcode":"L8E 4S5",
    "sg:province":"ON",
    "sg:tags":[
        "concrete",
        "contractor"
    ],
    "wof:name":"Greco's Bobcat Svc & Concrete",
    "wof:placetype":"venue"
},
  "geometry": {"coordinates":[-79.6898803711,43.2120666504],"type":"Point"}
}