{
  "type": "Feature",
  "properties": {
    "addr:full":"2086 Cliffwood Lane North Vancouver BC V7G 2A7",
    "addr:housenumber":"2086",
    "addr:postcode":"v7g 2a7",
    "addr:street":"Cliffwood Lane",
    "iso:country":"CA",
    "sg:address":"2086 Cliffwood Lane",
    "sg:city":"North Vancouver",
    "sg:classifiers":[
        {
            "category":"Building & Trades",
            "subcategory":"Construction",
            "type":"Services"
        }
    ],
    "sg:phone":"+1 604 984 7594",
    "sg:postcode":"V7G 2A7",
    "sg:province":"BC",
    "sg:tags":[
        "general",
        "contractor"
    ],
    "wof:name":"Merletti Construction Ltd",
    "wof:placetype":"venue"
},
  "geometry": {"coordinates":[-122.954406738,49.3254318237],"type":"Point"}
}