{
  "type": "Feature",
  "properties": {
    "addr:full":"3 Greenleaf Dr Charlottetown PE C1A 8E7",
    "addr:housenumber":"3",
    "addr:postcode":"c1a 8e7",
    "addr:street":"Greenleaf Dr",
    "iso:country":"CA",
    "sg:address":"3 Greenleaf Dr",
    "sg:city":"Charlottetown",
    "sg:classifiers":[
        {
            "category":"Professional",
            "subcategory":"Engineering",
            "type":"Services"
        }
    ],
    "sg:phone":"+1 902 566 5456",
    "sg:postcode":"C1A 8E7",
    "sg:province":"PE",
    "sg:tags":[
        "engineer"
    ],
    "wof:name":"Garg Associates Ltd",
    "wof:placetype":"venue"
},
  "geometry": {"coordinates":[-63.1308860779,46.2636795044],"type":"Point"}
}