{
  "type": "Feature",
  "properties": {
    "addr:full":"Salmon Arm BC V1E 1T3",
    "addr:postcode":"v1e 1t3",
    "iso:country":"CA",
    "sg:city":"Salmon Arm",
    "sg:classifiers":[
        {
            "category":"Personal",
            "subcategory":"Beauty Salon",
            "type":"Services"
        }
    ],
    "sg:phone":"+1 250 832 8746",
    "sg:postcode":"V1E 1T3",
    "sg:province":"BC",
    "wof:name":"Tangles Hair Design",
    "wof:placetype":"venue"
},
  "geometry": {"coordinates":[-119.29866800000001,50.692726],"type":"Point"}
}