{
  "type": "Feature",
  "properties": {
    "addr:full":"Blairmore AB T0K 0E0",
    "addr:postcode":"t0k 0e0",
    "iso:country":"CA",
    "sg:city":"Blairmore",
    "sg:classifiers":[
        {
            "category":"Professional",
            "subcategory":"Accounting & Tax Preparation",
            "type":"Services"
        }
    ],
    "sg:phone":"+1 403 562 2895",
    "sg:postcode":"T0K 0E0",
    "sg:province":"AB",
    "sg:tags":[
        "accountant"
    ],
    "wof:name":"Martini, Alan CA",
    "wof:placetype":"venue"
},
  "geometry": {"coordinates":[-114.44162,49.608425],"type":"Point"}
}