{
  "type": "Feature",
  "properties": {
    "addr:full":"21 Quebec St Guelph ON N1H 2T1",
    "addr:housenumber":"21",
    "addr:postcode":"n1h 2t1",
    "addr:street":"Quebec St",
    "iso:country":"CA",
    "sg:address":"21 Quebec St",
    "sg:city":"Guelph",
    "sg:classifiers":[
        {
            "category":"Wholesale",
            "subcategory":"Farm Supplies",
            "type":"Manufacturing & Wholesale Goods"
        }
    ],
    "sg:phone":"+1 519 836 2070",
    "sg:postcode":"N1H 2T1",
    "sg:province":"ON",
    "sg:tags":[
        "livestock"
    ],
    "wof:name":"M & M Livestock",
    "wof:placetype":"venue"
},
  "geometry": {"coordinates":[-80.2510604858,43.545425415],"type":"Point"}
}