{
  "type": "Feature",
  "properties": {
    "addr:full":"1155 Rue Du Parc-Industriel Normandin QC G8M 4C6",
    "addr:housenumber":"1155",
    "addr:postcode":"g8m 4c6",
    "addr:street":"Rue Du Parc-Industriel",
    "iso:country":"CA",
    "sg:address":"1155 Rue Du Parc-Industriel",
    "sg:city":"Normandin",
    "sg:classifiers":[
        {
            "category":"Government",
            "subcategory":"Office",
            "type":"Public Place"
        }
    ],
    "sg:phone":"+1 418 274 3064",
    "sg:postcode":"G8M 4C6",
    "sg:province":"QC",
    "sg:tags":[
        "village"
    ],
    "wof:name":"Normandin Garage",
    "wof:placetype":"venue"
},
  "geometry": {"coordinates":[-72.53555299999999,48.835579],"type":"Point"}
}