{
  "type": "Feature",
  "properties": {
    "addr:full":"1904 Kokanee Pl N Cranbrook BC V1C 6E5",
    "addr:housenumber":"1904",
    "addr:postcode":"v1c 6e5",
    "addr:street":"Kokanee Pl N",
    "iso:country":"CA",
    "sg:address":"1904 Kokanee Pl N",
    "sg:city":"Cranbrook",
    "sg:classifiers":[
        {
            "category":"Professional",
            "subcategory":"Accounting & Tax Preparation",
            "type":"Services"
        }
    ],
    "sg:phone":"+1 250 426 5611",
    "sg:postcode":"V1C 6E5",
    "sg:province":"BC",
    "sg:tags":[
        "television",
        "bookkeeping",
        "radio",
        "general"
    ],
    "wof:name":"Draco Trade Svc",
    "wof:placetype":"venue"
},
  "geometry": {"coordinates":[-115.741760254,49.5301780701],"type":"Point"}
}