{
  "type": "Feature",
  "properties": {
    "addr:full":"48 Lida St Brantford ON N3S 2R4",
    "addr:housenumber":"48",
    "addr:postcode":"n3s 2r4",
    "addr:street":"Lida St",
    "iso:country":"CA",
    "sg:address":"48 Lida St",
    "sg:city":"Brantford",
    "sg:classifiers":[
        {
            "category":"Shopping",
            "subcategory":"Discount & Variety Stores",
            "type":"Retail Goods"
        }
    ],
    "sg:phone":"+1 519 752 0526",
    "sg:postcode":"N3S 2R4",
    "sg:province":"ON",
    "wof:name":"Stan's Confectionery",
    "wof:placetype":"venue"
},
  "geometry": {"coordinates":[-80.247467,43.125202],"type":"Point"}
}