{
  "type": "Feature",
  "properties": {
    "addr:full":"PO Box 306 Endiang AB T0J 1G0",
    "addr:housenumber":"po",
    "addr:postcode":"t0j 1g0",
    "addr:street":"Box 306 Endiang",
    "iso:country":"CA",
    "sg:address":"PO Box 306",
    "sg:city":"Endiang",
    "sg:classifiers":[
        {
            "category":"Recreation",
            "type":"Entertainment"
        }
    ],
    "sg:phone":"+1 403 579 2437",
    "sg:postcode":"T0J 1G0",
    "sg:province":"AB",
    "sg:tags":[
        "hall",
        "auditorium"
    ],
    "wof:name":"Endiang Community Hall",
    "wof:placetype":"venue"
},
  "geometry": {"coordinates":[-112.160301209,51.9542808533],"type":"Point"}
}