{
  "type": "Feature",
  "properties": {
    "iso:country":"CA",
    "sg:address":"8030 Sussex Ave",
    "sg:city":"Burnaby",
    "sg:classifiers":[
        {
            "category":"Building & Trades",
            "subcategory":"Construction",
            "type":"Services"
        }
    ],
    "sg:phone":"+1 604 433 4433",
    "sg:postcode":"V5J 3W3",
    "sg:province":"BC",
    "sg:tags":[
        "concrete",
        "contractor"
    ],
    "wof:name":"Can-Tech Shotcrete Inc",
    "wof:placetype":"venue"
},
  "geometry": {"coordinates":[-123.00474548299999,49.2110137939],"type":"Point"}
}