{
  "type": "Feature",
  "properties": {
    "addr:full":"16 Pauline Pl Guelph ON N1H 7P3",
    "addr:housenumber":"16",
    "addr:postcode":"n1h 7p3",
    "addr:street":"Pauline Pl",
    "iso:country":"CA",
    "sg:address":"16 Pauline Pl",
    "sg:city":"Guelph",
    "sg:classifiers":[
        {
            "category":"Retail",
            "subcategory":"Laundry & Dry Cleaning",
            "type":"Services"
        }
    ],
    "sg:phone":"+1 519 822 4712",
    "sg:postcode":"N1H 7P3",
    "sg:province":"ON",
    "sg:tags":[
        "cleaners",
        "rug",
        "carpet"
    ],
    "wof:name":"Shea's Mobile Cleaning Svc Ltd",
    "wof:placetype":"venue"
},
  "geometry": {"coordinates":[-80.288826,43.540085],"type":"Point"}
}