{
  "type": "Feature",
  "properties": {
    "addr:full":"141 Rue Principale Saint-Benoit-Labre QC G0M 1P0",
    "addr:housenumber":"141",
    "addr:postcode":"g0m 1p0",
    "addr:street":"Rue Principale",
    "iso:country":"CA",
    "sg:address":"141 Rue Principale",
    "sg:city":"Saint-Benoit-Labre",
    "sg:classifiers":[
        {
            "category":"Food & Beverages",
            "subcategory":"Groceries & Convenience Stores",
            "type":"Retail Goods"
        }
    ],
    "sg:phone":"+1 418 227 2199",
    "sg:postcode":"G0M 1P0",
    "sg:province":"QC",
    "sg:tags":[
        "grocer"
    ],
    "wof:name":"Depanneur Ki-A-Tout Enr",
    "wof:placetype":"venue"
},
  "geometry": {"coordinates":[-70.791527,46.069473],"type":"Point"}
}