{
  "type": "Feature",
  "properties": {
    "addr:full":"2816 Columbia Ave Castlegar BC V1N 2X9",
    "addr:housenumber":"2816",
    "addr:postcode":"v1n 2x9",
    "addr:street":"Columbia Ave",
    "iso:country":"CA",
    "sg:address":"2816 Columbia Ave",
    "sg:city":"Castlegar",
    "sg:classifiers":[
        {
            "category":"Restaurant",
            "type":"Food & Drink"
        }
    ],
    "sg:phone":"+1 250 304 2633",
    "sg:postcode":"V1N 2X9",
    "sg:province":"BC",
    "wof:name":"Weezie's Borscht Hut",
    "wof:placetype":"venue"
},
  "geometry": {"coordinates":[-117.648742676,49.2770576477],"type":"Point"}
}