{
  "type": "Feature",
  "properties": {
    "iso:country":"CA",
    "sg:address":"438 8 Ave SE",
    "sg:city":"Calgary",
    "sg:classifiers":[
        {
            "category":"Professional",
            "subcategory":"Employment Agencies",
            "type":"Services"
        }
    ],
    "sg:phone":"+1 403 262 4060",
    "sg:postcode":"T2G 0L7",
    "sg:province":"AB",
    "sg:tags":[
        "opportunity",
        "contractor"
    ],
    "wof:name":"Calgary Industrial Labour Ltd",
    "wof:placetype":"venue"
},
  "geometry": {"coordinates":[-114.053970337,51.0453834534],"type":"Point"}
}