{
  "type": "Feature",
  "properties": {
    "iso:country":"CA",
    "sg:address":"2350 Albert St # 700",
    "sg:city":"Regina",
    "sg:classifiers":[
        {
            "category":"Government",
            "subcategory":"Office",
            "type":"Public Place"
        }
    ],
    "sg:phone":"+1 306 787 7450",
    "sg:postcode":"S4P 4A6",
    "sg:province":"SK",
    "wof:name":"Sask Provincial Comptrollers",
    "wof:placetype":"venue"
},
  "geometry": {"coordinates":[-104.61843109100001,50.4416007996],"type":"Point"}
}