{
  "type": "Feature",
  "properties": {
    "addr:full":"250 Picnic Point Rd Longlac ON P0T 2A0",
    "addr:housenumber":"250",
    "addr:postcode":"p0t 2a0",
    "addr:street":"Picnic Point Rd",
    "iso:country":"CA",
    "sg:address":"250 Picnic Point Rd",
    "sg:city":"Longlac",
    "sg:classifiers":[
        {
            "category":"Autos & Motor Vehicles",
            "subcategory":"Boat Sales",
            "type":"Retail Goods"
        }
    ],
    "sg:phone":"+1 807 876 4628",
    "sg:postcode":"P0T 2A0",
    "sg:province":"ON",
    "sg:tags":[
        "dealer"
    ],
    "wof:name":"Wild Country Sports",
    "wof:placetype":"venue"
},
  "geometry": {"coordinates":[-86.525955,49.779903],"type":"Point"}
}