{
  "type": "Feature",
  "properties": {
    "addr:full":"12675 Rue Sherbrooke E # 39 Pointe-Aux-Trembles QC H1A 3W7",
    "addr:housenumber":"12675",
    "addr:postcode":"h1a 3w7",
    "addr:street":"Rue Sherbrooke E # 39",
    "iso:country":"CA",
    "sg:address":"12675 Rue Sherbrooke E # 39",
    "sg:city":"Pointe-Aux-Trembles",
    "sg:classifiers":[
        {
            "category":"Shopping",
            "subcategory":"Jewelry",
            "type":"Retail Goods"
        }
    ],
    "sg:phone":"+1 514 642 3245",
    "sg:postcode":"H1A 3W7",
    "sg:province":"QC",
    "sg:tags":[
        "jeweler"
    ],
    "wof:name":"Ardene",
    "wof:placetype":"venue"
},
  "geometry": {"coordinates":[-73.510811,45.653515],"type":"Point"}
}