{
  "type": "Feature",
  "properties": {
    "addr:full":"78 Boul Perron O Caplan QC G0C 1H0",
    "addr:housenumber":"78",
    "addr:postcode":"g0c 1h0",
    "addr:street":"Boul Perron O",
    "iso:country":"CA",
    "sg:address":"78 Boul Perron O",
    "sg:city":"Caplan",
    "sg:classifiers":[
        {
            "category":"Food & Beverages",
            "subcategory":"Groceries & Convenience Stores",
            "type":"Retail Goods"
        }
    ],
    "sg:phone":"+1 418 388 5714",
    "sg:postcode":"G0C 1H0",
    "sg:province":"QC",
    "sg:tags":[
        "grocer"
    ],
    "wof:name":"Depanneur Sl Inc",
    "wof:placetype":"venue"
},
  "geometry": {"coordinates":[-65.6712265015,48.0982322693],"type":"Point"}
}