{
  "type": "Feature",
  "properties": {
    "addr:full":"52 Six Point Rd Etobicoke ON M8Z 2X2",
    "addr:housenumber":"52",
    "addr:postcode":"m8z 2x2",
    "addr:street":"Six Point Rd",
    "iso:country":"CA",
    "sg:address":"52 Six Point Rd",
    "sg:city":"Etobicoke",
    "sg:classifiers":[
        {
            "category":"Professional",
            "subcategory":"Computer Services",
            "type":"Services"
        }
    ],
    "sg:phone":"+1 416 231 7766",
    "sg:postcode":"M8Z 2X2",
    "sg:province":"ON",
    "sg:tags":[
        "website",
        "design",
        "internet"
    ],
    "wof:name":"Netmosphere Design Inc",
    "wof:placetype":"venue"
},
  "geometry": {"coordinates":[-79.525642,43.635983],"type":"Point"}
}