{
  "type": "Feature",
  "properties": {
    "addr:full":"977 Rue Labelle Saint-Jerome QC J7Z 5N4",
    "addr:housenumber":"977",
    "addr:postcode":"j7z 5n4",
    "addr:street":"Rue Labelle Saint-Jerome",
    "iso:country":"CA",
    "sg:address":"977 Rue Labelle",
    "sg:city":"Saint-Jerome",
    "sg:classifiers":[
        {
            "category":"Home & Garden",
            "subcategory":"Building Materials",
            "type":"Retail Goods"
        }
    ],
    "sg:phone":"+1 450 432 7646",
    "sg:postcode":"J7Z 5N4",
    "sg:province":"QC",
    "sg:tags":[
        "plate",
        "window",
        "radio",
        "stereo",
        "automobile"
    ],
    "wof:name":"Duro Vitres & Acces D'Autos",
    "wof:placetype":"venue"
},
  "geometry": {"coordinates":[-74.007721,45.792118],"type":"Point"}
}