{
  "type": "Feature",
  "properties": {
    "iso:country":"CA",
    "sg:address":"410 Spadina Rd",
    "sg:city":"Toronto",
    "sg:classifiers":[
        {
            "category":"Shopping",
            "type":"Retail Goods"
        }
    ],
    "sg:phone":"+1 416 487 8733",
    "sg:postcode":"M5P 2W2",
    "sg:province":"ON",
    "sg:tags":[
        "art",
        "gallery",
        "dealer"
    ],
    "wof:name":"Lonsdale Gallery",
    "wof:placetype":"venue"
},
  "geometry": {"coordinates":[-79.4128112793,43.688419342],"type":"Point"}
}