{
  "type": "Feature",
  "properties": {
    "addr:full":"42621 Walnut St Union ON N0L 2L0",
    "addr:housenumber":"42621",
    "addr:postcode":"n0l 2l0",
    "addr:street":"Walnut St",
    "iso:country":"CA",
    "sg:address":"42621 Walnut St",
    "sg:city":"Union",
    "sg:classifiers":[
        {
            "category":"Building & Trades",
            "subcategory":"Construction",
            "type":"Services"
        }
    ],
    "sg:phone":"+1 519 633 1900",
    "sg:postcode":"N0L 2L0",
    "sg:province":"ON",
    "sg:tags":[
        "excavating",
        "pile",
        "driving",
        "contractor"
    ],
    "wof:name":"Higgs Construction Ltd",
    "wof:placetype":"venue"
},
  "geometry": {"coordinates":[-81.19092559809999,42.7019844055],"type":"Point"}
}