{
  "type": "Feature",
  "properties": {
    "addr:full":"219 Rang Saint-Andre Saint-Bernard-DE-Lacolle QC J0J 1V0",
    "addr:housenumber":"219",
    "addr:postcode":"j0j 1v0",
    "addr:street":"Rang Saint-Andre",
    "iso:country":"CA",
    "sg:address":"219 Rang Saint-Andre",
    "sg:city":"Saint-Bernard-DE-Lacolle",
    "sg:classifiers":[
        {
            "category":"Recreation",
            "type":"Entertainment"
        }
    ],
    "sg:phone":"+1 450 246 2598",
    "sg:postcode":"J0J 1V0",
    "sg:province":"QC",
    "sg:tags":[
        "provincial",
        "parks"
    ],
    "wof:name":"Parc St Bernard",
    "wof:placetype":"venue"
},
  "geometry": {"coordinates":[-73.433044,45.054447],"type":"Point"}
}