{
  "type": "Feature",
  "properties": {
    "addr:full":"885 Boul Queen Saint-Lambert QC J4S 1V6",
    "addr:housenumber":"885",
    "addr:postcode":"j4s 1v6",
    "addr:street":"Boul Queen",
    "iso:country":"CA",
    "sg:address":"885 Boul Queen",
    "sg:city":"Saint-Lambert",
    "sg:classifiers":[
        {
            "category":"Manufacturing",
            "subcategory":"Tools & Machinery",
            "type":"Manufacturing & Wholesale Goods"
        }
    ],
    "sg:phone":"+1 450 466 6619",
    "sg:postcode":"J4S 1V6",
    "sg:province":"QC",
    "sg:tags":[
        "industry",
        "aerospace"
    ],
    "wof:name":"Advanced Jet Propulsion Tech",
    "wof:placetype":"venue"
},
  "geometry": {"coordinates":[-73.496872,45.482899],"type":"Point"}
}