{
  "type": "Feature",
  "properties": {
    "iso:country":"CA",
    "sg:address":"125 Christina St N",
    "sg:city":"Sarnia",
    "sg:classifiers":[
        {
            "category":"Shopping",
            "subcategory":"Clothing, Apparel, & Fashions",
            "type":"Retail Goods"
        }
    ],
    "sg:phone":"+1 519 337 8111",
    "sg:postcode":"N7T 5T7",
    "sg:province":"ON",
    "sg:tags":[
        "wig",
        "toupee",
        "salon",
        "hairpiece",
        "beauty"
    ],
    "wof:name":"Betty Dee Hair Fashions",
    "wof:placetype":"venue"
},
  "geometry": {"coordinates":[-82.4077835083,42.9714698792],"type":"Point"}
}