{
  "type": "Feature",
  "properties": {
    "addr:full":"67 Rte 125 Saint-Esprit QC J0K 2L0",
    "addr:housenumber":"67",
    "addr:postcode":"j0k 2l0",
    "addr:street":"Rte 125",
    "iso:country":"CA",
    "sg:address":"67 Rte 125",
    "sg:city":"Saint-Esprit",
    "sg:classifiers":[
        {
            "category":"Wholesale",
            "subcategory":"Construction Materials",
            "type":"Manufacturing & Wholesale Goods"
        }
    ],
    "sg:phone":"+1 450 839 2281",
    "sg:postcode":"J0K 2L0",
    "sg:province":"QC",
    "sg:tags":[
        "sand",
        "gravel",
        "excavating",
        "contractor"
    ],
    "wof:name":"Latendresse Asphalte Inc",
    "wof:placetype":"venue"
},
  "geometry": {"coordinates":[-73.68413543699999,45.9151420593],"type":"Point"}
}