{
  "type": "Feature",
  "properties": {
    "iso:country":"CA",
    "sg:address":"10300 101st Ave",
    "sg:city":"Fairview",
    "sg:classifiers":[
        {
            "category":"Mining & Drilling",
            "type":"Manufacturing & Wholesale Goods"
        }
    ],
    "sg:phone":"+1 780 835 2739",
    "sg:postcode":"T0H 1L0",
    "sg:province":"AB",
    "sg:tags":[
        "field",
        "oil"
    ],
    "wof:name":"Alltime Oilfield Svc Ltd",
    "wof:placetype":"venue"
},
  "geometry": {"coordinates":[-118.37059021,56.0656929016],"type":"Point"}
}