{
  "type": "Feature",
  "properties": {
    "addr:full":"1088 Rue Emelie-Chamard Sainte-Foy QC G1X 4S9",
    "addr:housenumber":"1088",
    "addr:postcode":"g1x 4s9",
    "addr:street":"Rue Emelie-Chamard",
    "iso:country":"CA",
    "sg:address":"1088 Rue Emelie-Chamard",
    "sg:city":"Sainte-Foy",
    "sg:classifiers":[
        {
            "category":"Health Services",
            "subcategory":"Clinic",
            "type":"Services"
        }
    ],
    "sg:phone":"+1 418 659 5626",
    "sg:postcode":"G1X 4S9",
    "sg:province":"QC",
    "sg:tags":[
        "school",
        "vocational",
        "aid",
        "educ",
        "special",
        "first"
    ],
    "wof:name":"Educ Sante Joan Therrien",
    "wof:placetype":"venue"
},
  "geometry": {"coordinates":[-71.363541,46.764217],"type":"Point"}
}