{
  "type": "Feature",
  "properties": {
    "addr:full":"6560 Av DE L'Esplanade Montreal QC H2V 4L5",
    "addr:housenumber":"6560",
    "addr:postcode":"h2v 4l5",
    "addr:street":"Av De L'Esplanade",
    "iso:country":"CA",
    "sg:address":"6560 Av DE L'Esplanade",
    "sg:city":"Montreal",
    "sg:classifiers":[
        {
            "category":"Professional",
            "subcategory":"Employment Agencies",
            "type":"Services"
        }
    ],
    "sg:phone":"+1 514 273 4217",
    "sg:postcode":"H2V 4L5",
    "sg:province":"QC",
    "sg:tags":[
        "modeling"
    ],
    "wof:name":"Agence Joanne Sheskay",
    "wof:placetype":"venue"
},
  "geometry": {"coordinates":[-73.55435900000001,45.51231],"type":"Point"}
}