{
  "type": "Feature",
  "properties": {
    "addr:full":"403 Rang Terrebonne Pont-Rouge QC G3H 1C7",
    "addr:housenumber":"403",
    "addr:postcode":"g3h 1c7",
    "addr:street":"Rang Terrebonne",
    "iso:country":"CA",
    "sg:address":"403 Rang Terrebonne",
    "sg:city":"Pont-Rouge",
    "sg:classifiers":[
        {
            "category":"Manufacturing",
            "subcategory":"Metals",
            "type":"Manufacturing & Wholesale Goods"
        }
    ],
    "sg:phone":"+1 418 873 3399",
    "sg:postcode":"G3H 1C7",
    "sg:province":"QC",
    "sg:tags":[
        "solder"
    ],
    "wof:name":"Soudure Jfcd Auger Inc",
    "wof:placetype":"venue"
},
  "geometry": {"coordinates":[-71.75046500000001,46.755535],"type":"Point"}
}