{
  "type": "Feature",
  "properties": {
    "addr:full":"87 Allan St Oakville ON L6J 3M7",
    "addr:housenumber":"87",
    "addr:postcode":"l6j 3m7",
    "addr:street":"Allan St",
    "iso:country":"CA",
    "sg:address":"87 Allan St",
    "sg:city":"Oakville",
    "sg:classifiers":[
        {
            "category":"Shopping",
            "subcategory":"Computers & Home Electronics",
            "type":"Retail Goods"
        }
    ],
    "sg:phone":"+1 905 339 3198",
    "sg:postcode":"L6J 3M7",
    "sg:province":"ON",
    "sg:tags":[
        "software"
    ],
    "wof:name":"II Tech Solutions Inc",
    "wof:placetype":"venue"
},
  "geometry": {"coordinates":[-79.6641616821,43.4487838745],"type":"Point"}
}