{
  "type": "Feature",
  "properties": {
    "addr:full":"2530 St Joseph Blvd #2 Orleans ON K1C 1G1",
    "addr:housenumber":"2530",
    "addr:postcode":"k1c 1g1",
    "addr:street":"St Joseph Blvd # 2",
    "iso:country":"CA",
    "sg:address":"2530 St Joseph Blvd #2",
    "sg:city":"Orleans",
    "sg:classifiers":[
        {
            "category":"Health Services",
            "subcategory":"Doctor",
            "type":"Services"
        }
    ],
    "sg:phone":"+1 613 830 9139",
    "sg:postcode":"K1C 1G1",
    "sg:province":"ON",
    "sg:tags":[
        "dentist"
    ],
    "wof:name":"Chung, Wendy DDS",
    "wof:placetype":"venue"
},
  "geometry": {"coordinates":[-75.5262145996,45.4702529907],"type":"Point"}
}