{
  "type": "Feature",
  "properties": {
    "addr:full":"103 2E Ave LA Pocatiere QC G0R 1Z0",
    "addr:housenumber":"103",
    "addr:postcode":"g0r 1z0",
    "addr:street":"2E Ave",
    "iso:country":"CA",
    "sg:address":"103 2E Ave",
    "sg:city":"LA Pocatiere",
    "sg:classifiers":[
        {
            "category":"Taxi",
            "type":"Transportation"
        }
    ],
    "sg:phone":"+1 418 856 1722",
    "sg:postcode":"G0R 1Z0",
    "sg:province":"QC",
    "sg:tags":[
        "taxicab"
    ],
    "wof:name":"Taxis DE LA Falaise Enr",
    "wof:placetype":"venue"
},
  "geometry": {"coordinates":[-70.03224945069999,47.36901474],"type":"Point"}
}