{
  "type": "Feature",
  "properties": {
    "addr:full":"4523 4 Ave Edson AB T7E 1C3",
    "addr:housenumber":"4523",
    "addr:postcode":"t7e 1c3",
    "addr:street":"4 Ave",
    "iso:country":"CA",
    "sg:address":"4523 4 Ave",
    "sg:city":"Edson",
    "sg:classifiers":[
        {
            "category":"Restaurant",
            "type":"Food & Drink"
        }
    ],
    "sg:phone":"+1 780 712 7300",
    "sg:postcode":"T7E 1C3",
    "sg:province":"AB",
    "wof:name":"Boston Pizza",
    "wof:placetype":"venue"
},
  "geometry": {"coordinates":[-116.420982,53.58633],"type":"Point"}
}