{
  "type": "Feature",
  "properties": {
    "addr:full":"PO Box 129 Galahad AB T0B 1R0",
    "addr:housenumber":"po",
    "addr:postcode":"t0b 1r0",
    "addr:street":"Box 129",
    "iso:country":"CA",
    "sg:address":"PO Box 129",
    "sg:city":"Galahad",
    "sg:classifiers":[
        {
            "category":"Mining & Drilling",
            "type":"Manufacturing & Wholesale Goods"
        }
    ],
    "sg:phone":"+1 780 583 2158",
    "sg:postcode":"T0B 1R0",
    "sg:province":"AB",
    "sg:tags":[
        "field",
        "oil"
    ],
    "wof:name":"Du-All Oilfield Svc",
    "wof:placetype":"venue"
},
  "geometry": {"coordinates":[-111.93000030499999,52.5140037537],"type":"Point"}
}