{
  "type": "Feature",
  "properties": {
    "addr:full":"Victoria BC V8T 4Y4",
    "addr:postcode":"v8t 4y4",
    "iso:country":"CA",
    "sg:city":"Victoria",
    "sg:classifiers":[
        {
            "category":"Shopping",
            "subcategory":"Computers & Home Electronics",
            "type":"Retail Goods"
        }
    ],
    "sg:phone":"+1 250 920 9828",
    "sg:postcode":"V8T 4Y4",
    "sg:province":"BC",
    "sg:tags":[
        "equipment",
        "dealer"
    ],
    "wof:name":"Campus Computers Ltd",
    "wof:placetype":"venue"
},
  "geometry": {"coordinates":[-123.37293200000001,48.436298],"type":"Point"}
}