{
  "type": "Feature",
  "properties": {
    "addr:full":"General Delivery Bearskin Lake ON P0V 1E0",
    "addr:postcode":"p0v 1e0",
    "iso:country":"CA",
    "sg:address":"General Delivery",
    "sg:city":"Bearskin Lake",
    "sg:classifiers":[
        {
            "category":"Social Services",
            "type":"Services"
        }
    ],
    "sg:phone":"+1 807 363 2505",
    "sg:postcode":"P0V 1E0",
    "sg:province":"ON",
    "sg:tags":[
        "organization",
        "welfare"
    ],
    "wof:name":"Bearskin Lake Band Community",
    "wof:placetype":"venue"
},
  "geometry": {"coordinates":[-90.991562,53.899502],"type":"Point"}
}