{
  "type": "Feature",
  "properties": {
    "addr:full":"Woodbridge ON L4L 8L8",
    "addr:postcode":"l4l 8l8",
    "iso:country":"CA",
    "sg:city":"Woodbridge",
    "sg:classifiers":[
        {
            "category":"Home & Garden",
            "subcategory":"Building Materials",
            "type":"Retail Goods"
        }
    ],
    "sg:phone":"+1 905 850 8733",
    "sg:postcode":"L4L 8L8",
    "sg:province":"ON",
    "sg:tags":[
        "windows"
    ],
    "wof:name":"Bow Line Aluminum Products Ltd",
    "wof:placetype":"venue"
},
  "geometry": {"coordinates":[-79.6108016968,43.7690238953],"type":"Point"}
}