{
  "type": "Feature",
  "properties": {
    "addr:full":"101 Rue Principale East Farnham QC J2K 4T8",
    "addr:housenumber":"101",
    "addr:postcode":"j2k 4t8",
    "addr:street":"Rue Principale",
    "iso:country":"CA",
    "sg:address":"101 Rue Principale",
    "sg:city":"East Farnham",
    "sg:classifiers":[
        {
            "category":"Retail",
            "subcategory":"Auto Repair",
            "type":"Services"
        }
    ],
    "sg:phone":"+1 450 263 4474",
    "sg:postcode":"J2K 4T8",
    "sg:province":"QC",
    "sg:tags":[
        "truck"
    ],
    "wof:name":"G D Diezel Inc",
    "wof:placetype":"venue"
},
  "geometry": {"coordinates":[-72.772789,45.226833],"type":"Point"}
}