{
  "type": "Feature",
  "properties": {
    "addr:full":"Railway Ave Eatonia SK S0L 0Y0",
    "addr:postcode":"s0l 0y0",
    "addr:street":"Railway Ave",
    "iso:country":"CA",
    "sg:address":"Railway Ave",
    "sg:city":"Eatonia",
    "sg:classifiers":[
        {
            "category":"Education",
            "subcategory":"Library",
            "type":"Public Place"
        }
    ],
    "sg:phone":"+1 306 967 2224",
    "sg:postcode":"S0L 0Y0",
    "sg:province":"SK",
    "wof:name":"Library-Eatonia",
    "wof:placetype":"venue"
},
  "geometry": {"coordinates":[-109.389266968,51.2211494446],"type":"Point"}
}