{
  "type": "Feature",
  "properties": {
    "addr:full":"17500 Rue DE LA Paix # 200 Mirabel QC J7J 1M3",
    "addr:housenumber":"17500",
    "addr:postcode":"j7j 1m3",
    "addr:street":"Rue De La Paix # 200",
    "iso:country":"CA",
    "sg:address":"17500 Rue DE LA Paix # 200",
    "sg:city":"Mirabel",
    "sg:classifiers":[
        {
            "category":"Retail",
            "subcategory":"Auto Repair",
            "type":"Services"
        }
    ],
    "sg:phone":"+1 450 437 9774",
    "sg:postcode":"J7J 1M3",
    "sg:province":"QC",
    "sg:tags":[
        "repairing",
        "automobile"
    ],
    "wof:name":"Garage Multi Shop Inc",
    "wof:placetype":"venue"
},
  "geometry": {"coordinates":[-73.93608856199999,45.7102737427],"type":"Point"}
}