{
  "type": "Feature",
  "properties": {
    "addr:full":"Calgary AB T2V 1K3",
    "addr:postcode":"t2v 1k3",
    "iso:country":"CA",
    "sg:city":"Calgary",
    "sg:classifiers":[
        {
            "category":"Real Estate",
            "subcategory":"Real Estate Operator",
            "type":"Services"
        }
    ],
    "sg:phone":"+1 403 259 8758",
    "sg:postcode":"T2V 1K3",
    "sg:province":"AB",
    "sg:tags":[
        "apartment"
    ],
    "wof:name":"Hastings Apartments",
    "wof:placetype":"venue"
},
  "geometry": {"coordinates":[-114.083359,50.984722],"type":"Point"}
}