{
  "type": "Feature",
  "properties": {
    "iso:country":"CA",
    "sg:address":"1069 Clarke Rd",
    "sg:city":"London",
    "sg:classifiers":[
        {
            "category":"Wholesale",
            "subcategory":"Electrical",
            "type":"Manufacturing & Wholesale Goods"
        }
    ],
    "sg:phone":"+1 519 453 3368",
    "sg:postcode":"N5V 3B3",
    "sg:province":"ON",
    "sg:tags":[
        "sound",
        "equipment",
        "system"
    ],
    "wof:name":"Horizon Audio Svc",
    "wof:placetype":"venue"
},
  "geometry": {"coordinates":[-81.186485,43.025776],"type":"Point"}
}