{
  "type": "Feature",
  "properties": {
    "addr:full":"2935 Rue Saint-Pierre O Saint-Hyacinthe QC J2T 1R7",
    "addr:housenumber":"2935",
    "addr:postcode":"j2t 1r7",
    "addr:street":"Rue Saint-Pierre O",
    "iso:country":"CA",
    "sg:address":"2935 Rue Saint-Pierre O",
    "sg:city":"Saint-Hyacinthe",
    "sg:classifiers":[
        {
            "category":"Health Services",
            "subcategory":"Nursing And Care Facility",
            "type":"Services"
        }
    ],
    "sg:phone":"+1 450 774 1927",
    "sg:postcode":"J2T 1R7",
    "sg:province":"QC",
    "sg:tags":[
        "home",
        "retirement",
        "community"
    ],
    "wof:name":"Residence Heroux",
    "wof:placetype":"venue"
},
  "geometry": {"coordinates":[-72.956245,45.615932],"type":"Point"}
}