{
  "type": "Feature",
  "properties": {
    "iso:country":"CA",
    "sg:address":"420 Springbank Dr",
    "sg:city":"London",
    "sg:classifiers":[
        {
            "category":"Retail",
            "subcategory":"Auto Repair",
            "type":"Services"
        }
    ],
    "sg:phone":"+1 519 473 3110",
    "sg:postcode":"N6J 1G8",
    "sg:province":"ON",
    "sg:tags":[
        "repairing",
        "automobile"
    ],
    "wof:name":"Tony Clark Car Care",
    "wof:placetype":"venue"
},
  "geometry": {"coordinates":[-81.283699,42.967995],"type":"Point"}
}