{
  "type": "Feature",
  "properties": {
    "iso:country":"CA",
    "sg:address":"13330 Maycrest Way",
    "sg:city":"Richmond",
    "sg:classifiers":[
        {
            "category":"Wholesale",
            "subcategory":"Electrical",
            "type":"Manufacturing & Wholesale Goods"
        }
    ],
    "sg:phone":"+1 604 276 9473",
    "sg:postcode":"V6V 2J7",
    "sg:province":"BC",
    "sg:tags":[
        "equipment",
        "electric",
        "supply"
    ],
    "wof:name":"Ecs Electrical Cable Supply",
    "wof:placetype":"venue"
},
  "geometry": {"coordinates":[-123.071502685,49.1817016602],"type":"Point"}
}