{
  "type": "Feature",
  "properties": {
    "addr:full":"1042 Lundell Rd Revelstoke BC V0E 2S0",
    "addr:housenumber":"1042",
    "addr:postcode":"v0e 2s0",
    "addr:street":"Lundell Rd",
    "iso:country":"CA",
    "sg:address":"1042 Lundell Rd",
    "sg:city":"Revelstoke",
    "sg:classifiers":[
        {
            "category":"Utilities",
            "subcategory":"Refuse",
            "type":"Services"
        }
    ],
    "sg:phone":"+1 250 837 4680",
    "sg:postcode":"V0E 2S0",
    "sg:province":"BC",
    "sg:tags":[
        "garbage",
        "collection"
    ],
    "wof:name":"Jowen Contractors",
    "wof:placetype":"venue"
},
  "geometry": {"coordinates":[-118.22026062,50.994102478],"type":"Point"}
}