{
  "type": "Feature",
  "properties": {
    "addr:full":"1527 Antler Heriot Bay BC V0P 1H0",
    "addr:housenumber":"1527",
    "addr:postcode":"v0p 1h0",
    "addr:street":"Antler Heriot",
    "iso:country":"CA",
    "sg:address":"1527 Antler",
    "sg:city":"Heriot Bay",
    "sg:classifiers":[
        {
            "category":"Health Services",
            "subcategory":"Health Practitioner",
            "type":"Services"
        }
    ],
    "sg:phone":"+1 250 285 2107",
    "sg:postcode":"V0P 1H0",
    "sg:province":"BC",
    "sg:tags":[
        "acupuncture"
    ],
    "wof:name":"Plum Blossom Acupuncture",
    "wof:placetype":"venue"
},
  "geometry": {"coordinates":[-125.201438904,50.094367981],"type":"Point"}
}