{
  "type": "Feature",
  "properties": {
    "addr:full":"800 John St W Mattawa ON P0H 1V0",
    "addr:housenumber":"800",
    "addr:postcode":"p0h 1v0",
    "addr:street":"John St W",
    "iso:country":"CA",
    "sg:address":"800 John St W",
    "sg:city":"Mattawa",
    "sg:classifiers":[
        {
            "category":"Education",
            "subcategory":"School",
            "type":"Public Place"
        }
    ],
    "sg:phone":"+1 705 744 5860",
    "sg:postcode":"P0H 1V0",
    "sg:province":"ON",
    "wof:name":"St Victor School",
    "wof:placetype":"venue"
},
  "geometry": {"coordinates":[-78.711128,46.310013],"type":"Point"}
}