{
  "type": "Feature",
  "properties": {
    "addr:full":"780 Rang Du Bas-Corbin Saint-Damase QC J0H 1J0",
    "addr:housenumber":"780",
    "addr:postcode":"j0h 1j0",
    "addr:street":"Rang Du Bas-Corbin",
    "iso:country":"CA",
    "sg:address":"780 Rang Du Bas-Corbin",
    "sg:city":"Saint-Damase",
    "sg:classifiers":[
        {
            "category":"Health Services",
            "subcategory":"Nursing And Care Facility",
            "type":"Services"
        }
    ],
    "sg:phone":"+1 450 797 3648",
    "sg:postcode":"J0H 1J0",
    "sg:province":"QC",
    "sg:tags":[
        "home",
        "retirement",
        "community"
    ],
    "wof:name":"Manoir St Damase",
    "wof:placetype":"venue"
},
  "geometry": {"coordinates":[-72.993095,45.540737],"type":"Point"}
}