{
  "type": "Feature",
  "properties": {
    "addr:full":"1193 Rue Principale Saint-Agapit QC G0S 1Z0",
    "addr:housenumber":"1193",
    "addr:postcode":"g0s 1z0",
    "addr:street":"Rue Principale",
    "iso:country":"CA",
    "sg:address":"1193 Rue Principale",
    "sg:city":"Saint-Agapit",
    "sg:classifiers":[
        {
            "category":"Health Services",
            "subcategory":"Doctor",
            "type":"Services"
        }
    ],
    "sg:phone":"+1 418 888 3951",
    "sg:postcode":"G0S 1Z0",
    "sg:province":"QC",
    "sg:tags":[
        "clinic"
    ],
    "wof:name":"Clinique Medicale St-Agapit",
    "wof:placetype":"venue"
},
  "geometry": {"coordinates":[-71.43952178959999,46.5599822998],"type":"Point"}
}