{
  "type": "Feature",
  "properties": {
    "addr:full":"3100 Temple Dr Windsor ON N8W 5J6",
    "addr:housenumber":"3100",
    "addr:postcode":"n8w 5j6",
    "addr:street":"Temple Dr",
    "iso:country":"CA",
    "sg:address":"3100 Temple Dr",
    "sg:city":"Windsor",
    "sg:classifiers":[
        {
            "category":"Banks & Credit Unions",
            "subcategory":"Investment Brokerage",
            "type":"Services"
        }
    ],
    "sg:phone":"+1 519 944 9941",
    "sg:postcode":"N8W 5J6",
    "sg:province":"ON",
    "sg:tags":[
        "consultant",
        "planning",
        "financial"
    ],
    "wof:name":"Rmp Financial Svc",
    "wof:placetype":"venue"
},
  "geometry": {"coordinates":[-82.971771,42.287392],"type":"Point"}
}