{
  "type": "Feature",
  "properties": {
    "iso:country":"CA",
    "sg:address":"26 Hesse Cres",
    "sg:city":"Stittsville",
    "sg:classifiers":[
        {
            "category":"Professional",
            "subcategory":"Computer Services",
            "type":"Services"
        }
    ],
    "sg:phone":"+1 613 836 0498",
    "sg:postcode":"K2S 1E4",
    "sg:province":"ON",
    "sg:tags":[
        "consultant"
    ],
    "wof:name":"Micom Technologies",
    "wof:placetype":"venue"
},
  "geometry": {"coordinates":[-75.9234008789,45.2658462524],"type":"Point"}
}