{
  "type": "Feature",
  "properties": {
    "addr:full":"314 Aberdeen Ave Carbon AB T0M 0L0",
    "addr:housenumber":"314",
    "addr:postcode":"t0m 0l0",
    "addr:street":"Aberdeen Ave",
    "iso:country":"CA",
    "sg:address":"314 Aberdeen Ave",
    "sg:city":"Carbon",
    "sg:classifiers":[
        {
            "category":"Professional",
            "subcategory":"Business Services",
            "type":"Services"
        }
    ],
    "sg:phone":"+1 403 572 3525",
    "sg:postcode":"T0M 0L0",
    "sg:province":"AB",
    "sg:tags":[
        "inspection",
        "welding"
    ],
    "wof:name":"L & S Metal Fabricators",
    "wof:placetype":"venue"
},
  "geometry": {"coordinates":[-113.155715942,51.4854316711],"type":"Point"}
}