{
  "type": "Feature",
  "properties": {
    "iso:country":"CA",
    "sg:address":"2276 Taunton Rd W",
    "sg:city":"Hampton",
    "sg:classifiers":[
        {
            "category":"Recreation",
            "type":"Entertainment"
        }
    ],
    "sg:phone":"+1 905 263 2906",
    "sg:postcode":"L0B 1J0",
    "sg:province":"ON",
    "sg:tags":[
        "skating",
        "rink"
    ],
    "wof:name":"Darlington Sport Ctr",
    "wof:placetype":"venue"
},
  "geometry": {"coordinates":[-78.74485778810001,43.963973999],"type":"Point"}
}