{
  "type": "Feature",
  "properties": {
    "addr:full":"Coquitlam BC V3K 6X7",
    "addr:postcode":"v3k 6x7",
    "iso:country":"CA",
    "sg:city":"Coquitlam",
    "sg:classifiers":[
        {
            "category":"Manufacturing",
            "subcategory":"Motor Vehicles & Parts",
            "type":"Manufacturing & Wholesale Goods"
        }
    ],
    "sg:phone":"+1 604 525 7885",
    "sg:postcode":"V3K 6X7",
    "sg:province":"BC",
    "sg:tags":[
        "bus"
    ],
    "wof:name":"Cannwest Bus Sales",
    "wof:placetype":"venue"
},
  "geometry": {"coordinates":[-122.854744,49.227818],"type":"Point"}
}