{
  "type": "Feature",
  "properties": {
    "addr:full":"Line 6 S Driveway 214 Oro ON L0L 2X0",
    "addr:housenumber":"214",
    "addr:postcode":"l0l 2x0",
    "addr:street":"Line 6 S Driveway",
    "iso:country":"CA",
    "sg:address":"Line 6 S Driveway 214",
    "sg:city":"Oro",
    "sg:classifiers":[
        {
            "category":"Shopping",
            "subcategory":"Bicycles & Sporting Goods",
            "type":"Retail Goods"
        }
    ],
    "sg:phone":"+1 705 487 7821",
    "sg:postcode":"L0L 2X0",
    "sg:province":"ON",
    "sg:tags":[
        "equipment",
        "camping"
    ],
    "wof:name":"Fun Camp CO",
    "wof:placetype":"venue"
},
  "geometry": {"coordinates":[-79.629501,44.494049],"type":"Point"}
}