{
  "type": "Feature",
  "properties": {
    "addr:full":"2730 2nd Ave W Prince Albert SK S6V 5E6",
    "addr:housenumber":"2730",
    "addr:postcode":"s6v 5e6",
    "addr:street":"2Nd Ave W",
    "iso:country":"CA",
    "sg:address":"2730 2nd Ave W",
    "sg:city":"Prince Albert",
    "sg:classifiers":[
        {
            "category":"Restaurant",
            "type":"Food & Drink"
        }
    ],
    "sg:phone":"+1 306 764 4411",
    "sg:postcode":"S6V 5E6",
    "sg:province":"SK",
    "wof:name":"Mr Sub",
    "wof:placetype":"venue"
},
  "geometry": {"coordinates":[-105.759765625,53.1883125305],"type":"Point"}
}