{
  "type": "Feature",
  "properties": {
    "iso:country":"CA",
    "sg:address":"723 Colborne St",
    "sg:city":"Brantford",
    "sg:classifiers":[
        {
            "category":"Education",
            "subcategory":"School",
            "type":"Public Place"
        }
    ],
    "sg:phone":"+1 519 753 2931",
    "sg:postcode":"N3S 3R5",
    "sg:province":"ON",
    "wof:name":"Echo Place School",
    "wof:placetype":"venue"
},
  "geometry": {"coordinates":[-80.23248291020001,43.1422576904],"type":"Point"}
}