{
  "type": "Feature",
  "properties": {
    "addr:full":"22 Main St W Ridgetown ON N0P 2C0",
    "addr:housenumber":"22",
    "addr:postcode":"n0p 2c0",
    "addr:street":"Main St W",
    "iso:country":"CA",
    "sg:address":"22 Main St W",
    "sg:city":"Ridgetown",
    "sg:classifiers":[
        {
            "category":"Shopping",
            "type":"Retail Goods"
        }
    ],
    "sg:phone":"+1 519 674 5463",
    "sg:postcode":"N0P 2C0",
    "sg:province":"ON",
    "sg:tags":[
        "cosmetic",
        "pharmacy"
    ],
    "wof:name":"Shoppers Drug Mart",
    "wof:placetype":"venue"
},
  "geometry": {"coordinates":[-81.8874206543,42.4387931824],"type":"Point"}
}