{
  "type": "Feature",
  "properties": {
    "addr:full":"8877 Hwy 42 # A Westport ON K0G 1X0",
    "addr:housenumber":"8877",
    "addr:postcode":"k0g 1x0",
    "addr:street":"Hwy 42 # A",
    "iso:country":"CA",
    "sg:address":"8877 Hwy 42 # A",
    "sg:city":"Westport",
    "sg:classifiers":[
        {
            "category":"Shopping",
            "subcategory":"Bicycles & Sporting Goods",
            "type":"Retail Goods"
        }
    ],
    "sg:phone":"+1 613 273 6462",
    "sg:postcode":"K0G 1X0",
    "sg:province":"ON",
    "sg:tags":[
        "tackle",
        "fishing"
    ],
    "wof:name":"Norris's Live Bait & Tackle",
    "wof:placetype":"venue"
},
  "geometry": {"coordinates":[-76.4005813599,44.6769256592],"type":"Point"}
}