{
  "type": "Feature",
  "properties": {
    "addr:full":"318 Mcdermot Ave Winnipeg MB R3A 0A2",
    "addr:housenumber":"318",
    "addr:postcode":"r3a 0a2",
    "addr:street":"Mcdermot Ave",
    "iso:country":"CA",
    "sg:address":"318 Mcdermot Ave",
    "sg:city":"Winnipeg",
    "sg:classifiers":[
        {
            "category":"Building & Trades",
            "subcategory":"Landscaping Services",
            "type":"Services"
        }
    ],
    "sg:phone":"+1 204 946 0688",
    "sg:postcode":"R3A 0A2",
    "sg:province":"MB",
    "sg:tags":[
        "landscape",
        "contractor"
    ],
    "wof:name":"Jess Dixon Design",
    "wof:placetype":"venue"
},
  "geometry": {"coordinates":[-97.143265,49.897854],"type":"Point"}
}