{
  "type": "Feature",
  "properties": {
    "addr:full":"1 Marsh Lane # 101 Ajax ON L1T 3W3",
    "addr:housenumber":"1",
    "addr:postcode":"l1t 3w3",
    "addr:street":"Marsh Lane # 101",
    "iso:country":"CA",
    "sg:address":"1 Marsh Lane # 101",
    "sg:city":"Ajax",
    "sg:classifiers":[
        {
            "category":"Social Services",
            "type":"Services"
        }
    ],
    "sg:phone":"+1 905 619 2287",
    "sg:postcode":"L1T 3W3",
    "sg:province":"ON",
    "sg:tags":[
        "housing",
        "assistance"
    ],
    "wof:name":"Life Centre Non Profit Housing",
    "wof:placetype":"venue"
},
  "geometry": {"coordinates":[-79.0557632446,43.8739624023],"type":"Point"}
}