{
  "type": "Feature",
  "properties": {
    "addr:full":"1500 Taylor Ave Winnipeg MB R3N 1Y1",
    "addr:housenumber":"1500",
    "addr:postcode":"r3n 1y1",
    "addr:street":"Taylor Ave",
    "iso:country":"CA",
    "sg:address":"1500 Taylor Ave",
    "sg:city":"Winnipeg",
    "sg:classifiers":[
        {
            "category":"Recreation",
            "type":"Entertainment"
        }
    ],
    "sg:phone":"+1 204 488 4480",
    "sg:postcode":"R3N 1Y1",
    "sg:province":"MB",
    "sg:tags":[
        "tennis",
        "court"
    ],
    "wof:name":"Taylor Tennis Club",
    "wof:placetype":"venue"
},
  "geometry": {"coordinates":[-97.18499,49.850536],"type":"Point"}
}