{
  "type": "Feature",
  "properties": {
    "iso:country":"CA",
    "sg:city":"Belleville",
    "sg:classifiers":[
        {
            "category":"Banks & Credit Unions",
            "subcategory":"Bank",
            "type":"Services"
        }
    ],
    "sg:phone":"+1 613 966 9181",
    "sg:postcode":"K8P 3C3",
    "sg:province":"ON",
    "sg:tags":[
        "loan",
        "real estate"
    ],
    "wof:name":"Citi Financial Svc",
    "wof:placetype":"venue"
},
  "geometry": {"coordinates":[-77.394203186,44.1843070984],"type":"Point"}
}