{
  "type": "Feature",
  "properties": {
    "addr:full":"Saskatoon SK S7K 8G1",
    "addr:postcode":"s7k 8g1",
    "iso:country":"CA",
    "sg:city":"Saskatoon",
    "sg:classifiers":[
        {
            "category":"Wholesale",
            "subcategory":"Electrical",
            "type":"Manufacturing & Wholesale Goods"
        }
    ],
    "sg:phone":"+1 306 657 2424",
    "sg:postcode":"S7K 8G1",
    "sg:province":"SK",
    "sg:tags":[
        "equipment",
        "electric",
        "supply"
    ],
    "wof:name":"Choice Electrical Supply Ltd",
    "wof:placetype":"venue"
},
  "geometry": {"coordinates":[-106.651062,52.173649],"type":"Point"}
}