{
  "type": "Feature",
  "properties": {
    "addr:full":"Red Deer AB T4N 1C7",
    "addr:postcode":"t4n 1c7",
    "iso:country":"CA",
    "sg:city":"Red Deer",
    "sg:classifiers":[
        {
            "category":"Health Services",
            "subcategory":"Doctor",
            "type":"Services"
        }
    ],
    "sg:phone":"+1 403 347 5200",
    "sg:postcode":"T4N 1C7",
    "sg:province":"AB",
    "sg:tags":[
        "physician",
        "surgeon"
    ],
    "wof:name":"Hamilton, Donald J MD",
    "wof:placetype":"venue"
},
  "geometry": {"coordinates":[-113.820007,52.262234],"type":"Point"}
}