{
  "type": "Feature",
  "properties": {
    "addr:full":"2 Sheppard Ave E #2000 North York ON M2N 5Y7",
    "addr:housenumber":"2",
    "addr:postcode":"m2n 5y7",
    "addr:street":"Sheppard Ave E # 2000",
    "iso:country":"CA",
    "sg:address":"2 Sheppard Ave E #2000",
    "sg:city":"North York",
    "sg:classifiers":[
        {
            "category":"Insurance",
            "subcategory":"Insurance Agent",
            "type":"Services"
        }
    ],
    "sg:phone":"+1 416 733 4364",
    "sg:postcode":"M2N 5Y7",
    "sg:province":"ON",
    "wof:name":"Tci Tribal Custom Insurance",
    "wof:placetype":"venue"
},
  "geometry": {"coordinates":[-79.410652,43.761757],"type":"Point"}
}