{
  "type": "Feature",
  "properties": {
    "addr:full":"852 Gorham St Newmarket ON L3Y 1L8",
    "addr:housenumber":"852",
    "addr:postcode":"l3y 1l8",
    "addr:street":"Gorham St",
    "iso:country":"CA",
    "sg:address":"852 Gorham St",
    "sg:city":"Newmarket",
    "sg:classifiers":[
        {
            "category":"Retail",
            "subcategory":"Veterinary Services",
            "type":"Services"
        }
    ],
    "sg:phone":"+1 905 895 4552",
    "sg:postcode":"L3Y 1L8",
    "sg:province":"ON",
    "sg:tags":[
        "veterinarian"
    ],
    "wof:name":"Gorham Animal Hospital",
    "wof:placetype":"venue"
},
  "geometry": {"coordinates":[-79.440254,44.054295],"type":"Point"}
}