{
  "type": "Feature",
  "properties": {
    "iso:country":"CA",
    "sg:address":"14 Queen St N",
    "sg:city":"Mississauga",
    "sg:classifiers":[
        {
            "category":"Retail",
            "subcategory":"Auto Repair",
            "type":"Services"
        }
    ],
    "sg:phone":"+1 905 826 7000",
    "sg:postcode":"L5N 1A1",
    "sg:province":"ON",
    "sg:tags":[
        "repairing",
        "automobile",
        "tire"
    ],
    "wof:name":"Active Green & Ross",
    "wof:placetype":"venue"
},
  "geometry": {"coordinates":[-79.59317,43.549656],"type":"Point"}
}