{
  "type": "Feature",
  "properties": {
    "iso:country":"CA",
    "sg:address":"SW 21-7-12W",
    "sg:city":"Cypress River",
    "sg:classifiers":[
        {
            "category":"Manufacturing",
            "subcategory":"Metals",
            "type":"Manufacturing & Wholesale Goods"
        }
    ],
    "sg:phone":"+1 204 743 2266",
    "sg:postcode":"R0K 0P0",
    "sg:province":"MB",
    "sg:tags":[
        "equipment",
        "livestock",
        "supply"
    ],
    "wof:name":"Cypress Industries",
    "wof:placetype":"venue"
},
  "geometry": {"coordinates":[-99.0869979858,49.5551185608],"type":"Point"}
}