{
  "type": "Feature",
  "properties": {
    "addr:full":"Chatsworth ON N0H 1G0",
    "addr:postcode":"n0h 1g0",
    "iso:country":"CA",
    "sg:city":"Chatsworth",
    "sg:classifiers":[
        {
            "category":"Government",
            "subcategory":"Fire Station",
            "type":"Public Place"
        }
    ],
    "sg:phone":"+1 519 794 3188",
    "sg:postcode":"N0H 1G0",
    "sg:province":"ON",
    "sg:tags":[
        "department"
    ],
    "wof:name":"Chatsworth Fire Dept",
    "wof:placetype":"venue"
},
  "geometry": {"coordinates":[-80.8974075317,44.4536552429],"type":"Point"}
}