{
  "type": "Feature",
  "properties": {
    "addr:full":"584 Pioneer Tower Rd Kitchener ON N2P 2H9",
    "addr:housenumber":"584",
    "addr:postcode":"n2p 2h9",
    "addr:street":"Pioneer Tower Rd",
    "iso:country":"CA",
    "sg:address":"584 Pioneer Tower Rd",
    "sg:city":"Kitchener",
    "sg:classifiers":[
        {
            "category":"Recreation",
            "type":"Entertainment"
        }
    ],
    "sg:phone":"+1 519 653 4686",
    "sg:postcode":"N2P 2H9",
    "sg:province":"ON",
    "sg:tags":[
        "stable"
    ],
    "wof:name":"Central Ontario Development",
    "wof:placetype":"venue"
},
  "geometry": {"coordinates":[-80.422714,43.403984],"type":"Point"}
}