{
  "type": "Feature",
  "properties": {
    "addr:full":"3802 47 Ave Stettler AB T0C 2L1",
    "addr:housenumber":"3802",
    "addr:postcode":"t0c 2l1",
    "addr:street":"47 Ave",
    "iso:country":"CA",
    "sg:address":"3802 47 Ave",
    "sg:city":"Stettler",
    "sg:classifiers":[
        {
            "category":"Wholesale",
            "subcategory":"Petroleum",
            "type":"Manufacturing & Wholesale Goods"
        }
    ],
    "sg:phone":"+1 403 742 2115",
    "sg:postcode":"T0C 2L1",
    "sg:province":"AB",
    "sg:tags":[
        "bulk",
        "oil",
        "gasoline"
    ],
    "wof:name":"Shell Canada Ltd",
    "wof:placetype":"venue"
},
  "geometry": {"coordinates":[-112.680588,52.322914],"type":"Point"}
}