{
  "type": "Feature",
  "properties": {
    "addr:full":"Victoria BC V8Z 3K3",
    "addr:postcode":"v8z 3k3",
    "iso:country":"CA",
    "sg:city":"Victoria",
    "sg:classifiers":[
        {
            "category":"Wholesale",
            "subcategory":"Groceries",
            "type":"Manufacturing & Wholesale Goods"
        }
    ],
    "sg:phone":"+1 250 382 1116",
    "sg:postcode":"V8Z 3K3",
    "sg:province":"BC",
    "sg:tags":[
        "food",
        "product"
    ],
    "wof:name":"Jugo Juice",
    "wof:placetype":"venue"
},
  "geometry": {"coordinates":[-123.371407,48.446381],"type":"Point"}
}