{
  "type": "Feature",
  "properties": {
    "addr:full":"16 Dalton Cres S Orillia ON L3V 5J8",
    "addr:housenumber":"16",
    "addr:postcode":"l3v 5j8",
    "addr:street":"Dalton Cres S",
    "iso:country":"CA",
    "sg:address":"16 Dalton Cres S",
    "sg:city":"Orillia",
    "sg:classifiers":[
        {
            "category":"Communications",
            "subcategory":"Film & Video Production",
            "type":"Services"
        }
    ],
    "sg:phone":"+1 705 325 5791",
    "sg:postcode":"L3V 5J8",
    "sg:province":"ON",
    "sg:tags":[
        "taping"
    ],
    "wof:name":"Vid Com Enterprises",
    "wof:placetype":"venue"
},
  "geometry": {"coordinates":[-79.42594146730001,44.6141319275],"type":"Point"}
}