{
  "type": "Feature",
  "properties": {
    "addr:full":"Brantford ON N3R 7V5",
    "addr:postcode":"n3r 7v5",
    "iso:country":"CA",
    "sg:city":"Brantford",
    "sg:classifiers":[
        {
            "category":"Insurance",
            "subcategory":"Insurance Agent",
            "type":"Services"
        }
    ],
    "sg:phone":"+1 519 759 0033",
    "sg:postcode":"N3R 7V5",
    "sg:province":"ON",
    "wof:name":"Dorsey Group Insurance Planner",
    "wof:placetype":"venue"
},
  "geometry": {"coordinates":[-80.25882,43.154739],"type":"Point"}
}