{
  "type": "Feature",
  "properties": {
    "addr:full":"437 36 Ave SE Calgary AB T2G 1W5",
    "addr:housenumber":"437",
    "addr:postcode":"t2g 1w5",
    "addr:street":"36 Ave Se",
    "iso:country":"CA",
    "sg:address":"437 36 Ave SE",
    "sg:city":"Calgary",
    "sg:classifiers":[
        {
            "category":"Professional",
            "subcategory":"Business Services",
            "type":"Services"
        }
    ],
    "sg:phone":"+1 403 243 5141",
    "sg:postcode":"T2G 1W5",
    "sg:province":"AB",
    "sg:tags":[
        "water",
        "treatment"
    ],
    "wof:name":"Culligan Water Conditioning",
    "wof:placetype":"venue"
},
  "geometry": {"coordinates":[-114.05484800000001,51.021263],"type":"Point"}
}