{
  "type": "Feature",
  "properties": {
    "addr:full":"21883 Prespatou Rd Prespatou BC V0C 2S0",
    "addr:housenumber":"21883",
    "addr:postcode":"bc v0c 2s0",
    "addr:street":"Prespatou Rd",
    "iso:country":"CA",
    "sg:address":"21883 Prespatou Rd",
    "sg:city":"Prespatou",
    "sg:classifiers":[
        {
            "category":"Health Services",
            "subcategory":"Nursing And Care Facility",
            "type":"Services"
        }
    ],
    "sg:phone":"+1 250 630 2517",
    "sg:postcode":"V0C 2S0",
    "sg:province":"BC",
    "sg:tags":[
        "home",
        "retirement",
        "community"
    ],
    "wof:name":"Prespatou Independent Housing",
    "wof:placetype":"venue"
},
  "geometry": {"coordinates":[-121.06047100000001,56.918491],"type":"Point"}
}