{
  "type": "Feature",
  "properties": {
    "addr:full":"PO Box 192 STN Main Port Hope ON L1A 3W3",
    "addr:housenumber":"po",
    "addr:postcode":"l1a 3w3",
    "addr:street":"Box 192 Stn Main",
    "iso:country":"CA",
    "sg:address":"PO Box 192 STN Main",
    "sg:city":"Port Hope",
    "sg:classifiers":[
        {
            "category":"Farming",
            "subcategory":"Farm & Veterinary Services",
            "type":"Manufacturing & Wholesale Goods"
        }
    ],
    "sg:phone":"+1 905 786 2412",
    "sg:postcode":"L1A 3W3",
    "sg:province":"ON",
    "sg:tags":[
        "control",
        "weed"
    ],
    "wof:name":"Clarke's Lawn Care",
    "wof:placetype":"venue"
},
  "geometry": {"coordinates":[-78.291611,43.950119],"type":"Point"}
}