{
  "type": "Feature",
  "properties": {
    "addr:full":"Upper Nine Mile River NS B2S 2Y2",
    "addr:postcode":"b2s 2y2",
    "iso:country":"CA",
    "sg:city":"Upper Nine Mile River",
    "sg:classifiers":[
        {
            "category":"Manufacturing",
            "subcategory":"Tools & Machinery",
            "type":"Manufacturing & Wholesale Goods"
        }
    ],
    "sg:phone":"+1 902 883 2340",
    "sg:postcode":"B2S 2Y2",
    "sg:province":"NS",
    "sg:tags":[
        "steel",
        "machine",
        "shop"
    ],
    "wof:name":"Mac Donell Welding & Metal Ltd",
    "wof:placetype":"venue"
},
  "geometry": {"coordinates":[-63.650352478,45.0828323364],"type":"Point"}
}