{
  "type": "Feature",
  "properties": {
    "addr:full":"Beausejour MB R0E 0C0",
    "addr:postcode":"r0e 0c0",
    "iso:country":"CA",
    "sg:city":"Beausejour",
    "sg:classifiers":[
        {
            "category":"Travel",
            "subcategory":"Campground",
            "type":"Entertainment"
        }
    ],
    "sg:phone":"+1 204 268 2814",
    "sg:postcode":"R0E 0C0",
    "sg:province":"MB",
    "wof:name":"Great Woods Park & Campground",
    "wof:placetype":"venue"
},
  "geometry": {"coordinates":[-96.514297,50.061787],"type":"Point"}
}