{
  "type": "Feature",
  "properties": {
    "addr:full":"81 Liberton Dr St Albert AB T8N 5J1",
    "addr:housenumber":"81",
    "addr:postcode":"t8n 5j1",
    "addr:street":"Liberton Dr",
    "iso:country":"CA",
    "sg:address":"81 Liberton Dr",
    "sg:city":"St Albert",
    "sg:classifiers":[
        {
            "category":"Shopping",
            "type":"Retail Goods"
        }
    ],
    "sg:phone":"+1 780 458 3544",
    "sg:postcode":"T8N 5J1",
    "sg:province":"AB",
    "sg:tags":[
        "picture",
        "frame"
    ],
    "wof:name":"Frame Corner",
    "wof:placetype":"venue"
},
  "geometry": {"coordinates":[-113.629707336,53.6488800049],"type":"Point"}
}