{
  "type": "Feature",
  "properties": {
    "iso:country":"CA",
    "sg:address":"937 Carling Ave",
    "sg:city":"Ottawa",
    "sg:classifiers":[
        {
            "category":"Restaurant",
            "type":"Food & Drink"
        }
    ],
    "sg:phone":"+1 613 728 3749",
    "sg:postcode":"K1Y 4E4",
    "sg:province":"ON",
    "wof:name":"Cypress Garden",
    "wof:placetype":"venue"
},
  "geometry": {"coordinates":[-75.713081,45.39542],"type":"Point"}
}