{
  "type": "Feature",
  "properties": {
    "addr:full":"122 3rd Ave S Saskatoon SK S7K 1L3",
    "addr:housenumber":"122",
    "addr:postcode":"s7k 1l3",
    "addr:street":"3Rd Ave S",
    "iso:country":"CA",
    "sg:address":"122 3rd Ave S",
    "sg:city":"Saskatoon",
    "sg:classifiers":[
        {
            "category":"Government",
            "subcategory":"Office",
            "type":"Public Place"
        }
    ],
    "sg:phone":"+1 306 933 7094",
    "sg:postcode":"S7K 1L3",
    "sg:province":"SK",
    "wof:name":"Sask Fine Option Program",
    "wof:placetype":"venue"
},
  "geometry": {"coordinates":[-106.66209411600001,52.127986908],"type":"Point"}
}