{
  "type": "Feature",
  "properties": {
    "iso:country":"CA",
    "sg:address":"195 Rue DE Bellechasse",
    "sg:city":"Montreal",
    "sg:classifiers":[
        {
            "category":"Bars & Pubs",
            "type":"Food & Drink"
        }
    ],
    "sg:phone":"+1 514 271 1762",
    "sg:postcode":"H2S 1W3",
    "sg:province":"QC",
    "wof:name":"Taverne Bellechasse",
    "wof:placetype":"venue"
},
  "geometry": {"coordinates":[-73.603867,45.530506],"type":"Point"}
}