{
  "type": "Feature",
  "properties": {
    "addr:full":"225 Rue Chabanel O Montreal QC H2N 2C9",
    "addr:housenumber":"225",
    "addr:postcode":"h2n 2c9",
    "addr:street":"Rue Chabanel O",
    "iso:country":"CA",
    "sg:address":"225 Rue Chabanel O",
    "sg:city":"Montreal",
    "sg:classifiers":[
        {
            "category":"Wholesale",
            "subcategory":"Apparel",
            "type":"Manufacturing & Wholesale Goods"
        }
    ],
    "sg:phone":"+1 514 384 3551",
    "sg:postcode":"H2N 2C9",
    "sg:province":"QC",
    "sg:tags":[
        "clothing"
    ],
    "wof:name":"Groupe Js Intl",
    "wof:placetype":"venue"
},
  "geometry": {"coordinates":[-73.65353393549999,45.5406227112],"type":"Point"}
}