{
  "type": "Feature",
  "properties": {
    "addr:full":"565 Rue Sagard Saint-Bruno QC J3V 6C1",
    "addr:housenumber":"565",
    "addr:postcode":"j3v 6c1",
    "addr:street":"Rue Sagard",
    "iso:country":"CA",
    "sg:address":"565 Rue Sagard",
    "sg:city":"Saint-Bruno",
    "sg:classifiers":[
        {
            "category":"Building & Trades",
            "subcategory":"Construction",
            "type":"Services"
        }
    ],
    "sg:phone":"+1 450 461 2088",
    "sg:postcode":"J3V 6C1",
    "sg:province":"QC",
    "sg:tags":[
        "excavating",
        "contractor"
    ],
    "wof:name":"Mini Excavation Beloeil Inc",
    "wof:placetype":"venue"
},
  "geometry": {"coordinates":[-71.67552185060001,48.4717712402],"type":"Point"}
}