{
  "type": "Feature",
  "properties": {
    "addr:full":"6 Rue Des Erables Cabano QC G0L 1E0",
    "addr:housenumber":"6",
    "addr:postcode":"g0l 1e0",
    "addr:street":"Rue Des Erables",
    "iso:country":"CA",
    "sg:address":"6 Rue Des Erables",
    "sg:city":"Cabano",
    "sg:classifiers":[
        {
            "category":"Autos & Motor Vehicles",
            "subcategory":"Motorcycle Sales",
            "type":"Retail Goods"
        }
    ],
    "sg:phone":"+1 418 854 2680",
    "sg:postcode":"G0L 1E0",
    "sg:province":"QC",
    "sg:tags":[
        "all",
        "terrain"
    ],
    "wof:name":"Garage Roger A Pelletier",
    "wof:placetype":"venue"
},
  "geometry": {"coordinates":[-68.878616333,47.6762924194],"type":"Point"}
}