{
  "type": "Feature",
  "properties": {
    "addr:full":"548 Rue Des Ecarts Rimouski QC G5L 7W5",
    "addr:housenumber":"548",
    "addr:postcode":"g5l 7w5",
    "addr:street":"Rue Des Ecarts",
    "iso:country":"CA",
    "sg:address":"548 Rue Des Ecarts",
    "sg:city":"Rimouski",
    "sg:classifiers":[
        {
            "category":"Building & Trades",
            "subcategory":"Cleaning & Sanitation",
            "type":"Services"
        }
    ],
    "sg:phone":"+1 418 722 8499",
    "sg:postcode":"G5L 7W5",
    "sg:province":"QC",
    "sg:tags":[
        "snow",
        "removal"
    ],
    "wof:name":"Pro-Neige",
    "wof:placetype":"venue"
},
  "geometry": {"coordinates":[-68.54920199999999,48.43206],"type":"Point"}
}