{
  "type": "Feature",
  "properties": {
    "iso:country":"CA",
    "sg:address":"74 Colonnade Rd",
    "sg:city":"Nepean",
    "sg:classifiers":[
        {
            "category":"Insurance",
            "subcategory":"Insurance Agent",
            "type":"Services"
        }
    ],
    "sg:phone":"+1 613 224 4010",
    "sg:postcode":"K2E 7L2",
    "sg:province":"ON",
    "wof:name":"Leafloor, Ron",
    "wof:placetype":"venue"
},
  "geometry": {"coordinates":[-75.711273,45.346542],"type":"Point"}
}