{
  "type": "Feature",
  "properties": {
    "addr:full":"74 Colonnade Rd Nepean ON K2E 7L2",
    "addr:housenumber":"74",
    "addr:postcode":"k2e 7l2",
    "addr:street":"Colonnade Rd",
    "iso:country":"CA",
    "sg:address":"74 Colonnade Rd",
    "sg:city":"Nepean",
    "sg:classifiers":[
        {
            "category":"Insurance",
            "subcategory":"Insurance Agent",
            "type":"Services"
        }
    ],
    "sg:phone":"+1 613 224 4010",
    "sg:postcode":"K2E 7L2",
    "sg:province":"ON",
    "wof:name":"Leafloor, Ron",
    "wof:placetype":"venue"
},
  "geometry": {"coordinates":[-75.71127300000001,45.346542],"type":"Point"}
}