{
  "type": "Feature",
  "properties": {
    "addr:full":"20 Millwick Dr #3 North York ON M9L 1Y3",
    "addr:housenumber":"20",
    "addr:postcode":"m9l 1y3",
    "addr:street":"Millwick Dr # 3",
    "iso:country":"CA",
    "sg:address":"20 Millwick Dr #3",
    "sg:city":"North York",
    "sg:classifiers":[
        {
            "category":"Wholesale",
            "subcategory":"Electrical",
            "type":"Manufacturing & Wholesale Goods"
        }
    ],
    "sg:phone":"+1 416 740 4081",
    "sg:postcode":"M9L 1Y3",
    "sg:province":"ON",
    "sg:tags":[
        "packaging",
        "material",
        "tape"
    ],
    "wof:name":"Taypco Inc",
    "wof:placetype":"venue"
},
  "geometry": {"coordinates":[-79.5591430664,43.7572288513],"type":"Point"}
}