{
  "type": "Feature",
  "properties": {
    "addr:full":"2993 Bathurst St North York ON M6B 3B3",
    "addr:housenumber":"2993",
    "addr:postcode":"m6b 3b3",
    "addr:street":"Bathurst St",
    "iso:country":"CA",
    "sg:address":"2993 Bathurst St",
    "sg:city":"North York",
    "sg:classifiers":[
        {
            "category":"Personal",
            "subcategory":"Beauty Salon",
            "type":"Services"
        }
    ],
    "sg:phone":"+1 416 789 5381",
    "sg:postcode":"M6B 3B3",
    "sg:province":"ON",
    "wof:name":"DE Ville Salon",
    "wof:placetype":"venue"
},
  "geometry": {"coordinates":[-79.42907700000001,43.717182],"type":"Point"}
}