{
  "type": "Feature",
  "properties": {
    "addr:full":"201 Elm St W Durham ON N0G 1R0",
    "addr:housenumber":"201",
    "addr:postcode":"n0g 1r0",
    "addr:street":"Elm St W",
    "iso:country":"CA",
    "sg:address":"201 Elm St W",
    "sg:city":"Durham",
    "sg:classifiers":[
        {
            "category":"Retail",
            "subcategory":"Veterinary Services",
            "type":"Services"
        }
    ],
    "sg:phone":"+1 519 369 9946",
    "sg:postcode":"N0G 1R0",
    "sg:province":"ON",
    "sg:tags":[
        "veterinarian"
    ],
    "wof:name":"Grein, Melanie DVM",
    "wof:placetype":"venue"
},
  "geometry": {"coordinates":[-80.818451,44.167671],"type":"Point"}
}