{
  "type": "Feature",
  "properties": {
    "addr:full":"5516 5 St SE Calgary AB T2H 1L3",
    "addr:housenumber":"5516 5",
    "addr:postcode":"t2h 1l3",
    "addr:street":"St Se",
    "iso:country":"CA",
    "sg:address":"5516 5 St SE",
    "sg:city":"Calgary",
    "sg:classifiers":[
        {
            "category":"Manufacturing",
            "subcategory":"Printing",
            "type":"Manufacturing & Wholesale Goods"
        }
    ],
    "sg:phone":"+1 403 258 3788",
    "sg:postcode":"T2H 1L3",
    "sg:province":"AB",
    "sg:tags":[
        "printer"
    ],
    "wof:name":"Trans-Continental Printing Inc",
    "wof:placetype":"venue"
},
  "geometry": {"coordinates":[-114.05188800000001,51.004631],"type":"Point"}
}