{
  "type": "Feature",
  "properties": {
    "iso:country":"CA",
    "sg:address":"3501 Rue Saint-Hubert",
    "sg:city":"Montreal",
    "sg:classifiers":[
        {
            "category":"Banks & Credit Unions",
            "subcategory":"Bank",
            "type":"Services"
        }
    ],
    "sg:phone":"+1 514 526 4905",
    "sg:postcode":"H2L 3Z8",
    "sg:province":"QC",
    "wof:name":"Banque Nationale Du Canada",
    "wof:placetype":"venue"
},
  "geometry": {"coordinates":[-73.567253,45.519493],"type":"Point"}
}