{
  "type": "Feature",
  "properties": {
    "addr:full":"Abbotsford BC V2S 8A3",
    "addr:postcode":"v2s 8a3",
    "iso:country":"CA",
    "sg:city":"Abbotsford",
    "sg:classifiers":[
        {
            "category":"Restaurant",
            "type":"Food & Drink"
        }
    ],
    "sg:phone":"+1 604 853 2532",
    "sg:postcode":"V2S 8A3",
    "sg:province":"BC",
    "sg:tags":[
        "shop",
        "coffee"
    ],
    "wof:name":"C'Ya Latte Ltd",
    "wof:placetype":"venue"
},
  "geometry": {"coordinates":[-122.29295349100001,49.0304336548],"type":"Point"}
}