{
  "type": "Feature",
  "properties": {
    "addr:full":"Hwy 3 Carman MB R0G 0J0",
    "addr:postcode":"r0g 0j0",
    "addr:street":"Hwy 3",
    "iso:country":"CA",
    "sg:address":"Hwy 3",
    "sg:city":"Carman",
    "sg:classifiers":[
        {
            "category":"Home & Garden",
            "subcategory":"Garden Supply",
            "type":"Retail Goods"
        }
    ],
    "sg:phone":"+1 204 745 6703",
    "sg:postcode":"R0G 0J0",
    "sg:province":"MB",
    "sg:tags":[
        "nurseryman"
    ],
    "wof:name":"Aubin Nurseries Ltd",
    "wof:placetype":"venue"
},
  "geometry": {"coordinates":[-98.0016403198,49.4978637695],"type":"Point"}
}