{
  "type": "Feature",
  "properties": {
    "addr:full":"51475 Range Road 231 Sherwood Park AB T8B 1K9",
    "addr:housenumber":"51475",
    "addr:postcode":"t8b 1k9",
    "addr:street":"Range Road 231;Park",
    "iso:country":"CA",
    "sg:address":"51475 Range Road 231",
    "sg:city":"Sherwood Park",
    "sg:classifiers":[
        {
            "category":"Professional",
            "subcategory":"Detective & Security Services",
            "type":"Services"
        }
    ],
    "sg:phone":"+1 780 449 4059",
    "sg:postcode":"T8B 1K9",
    "sg:province":"AB",
    "sg:tags":[
        "control",
        "signal",
        "traffic",
        "sign"
    ],
    "wof:name":"Can-Traffic Svc Ltd",
    "wof:placetype":"venue"
},
  "geometry": {"coordinates":[-113.27080535899999,53.5728111267],"type":"Point"}
}