{
  "type": "Feature",
  "properties": {
    "addr:full":"Toronto ON M5V 1K4",
    "addr:postcode":"m5v 1k4",
    "iso:country":"CA",
    "sg:city":"Toronto",
    "sg:classifiers":[
        {
            "category":"Recreation",
            "subcategory":"Arcade",
            "type":"Entertainment"
        }
    ],
    "sg:phone":"+1 416 597 1585",
    "sg:postcode":"M5V 1K4",
    "sg:province":"ON",
    "sg:tags":[
        "amusement",
        "devices"
    ],
    "wof:name":"Simex Inc",
    "wof:placetype":"venue"
},
  "geometry": {"coordinates":[-79.397835,43.644775],"type":"Point"}
}