{
  "type": "Feature",
  "properties": {
    "addr:full":"170 Esna Park Dr Markham ON L3R 1E3",
    "addr:housenumber":"170",
    "addr:postcode":"l3r 1e3",
    "addr:street":"Esna Park Dr",
    "iso:country":"CA",
    "sg:address":"170 Esna Park Dr",
    "sg:city":"Markham",
    "sg:classifiers":[
        {
            "category":"Shopping",
            "subcategory":"Computers & Home Electronics",
            "type":"Retail Goods"
        }
    ],
    "sg:phone":"+1 905 477 1129",
    "sg:postcode":"L3R 1E3",
    "sg:province":"ON",
    "sg:tags":[
        "equipment",
        "dealer"
    ],
    "wof:name":"Micro Express",
    "wof:placetype":"venue"
},
  "geometry": {"coordinates":[-79.338364,43.826279],"type":"Point"}
}