{
  "type": "Feature",
  "properties": {
    "addr:full":"4403 Kennisis Lake Rd Haliburton ON K0M 1S0",
    "addr:housenumber":"4403",
    "addr:postcode":"k0m 1s0",
    "addr:street":"Kennisis Lake Rd",
    "iso:country":"CA",
    "sg:address":"4403 Kennisis Lake Rd",
    "sg:city":"Haliburton",
    "sg:classifiers":[
        {
            "category":"Building & Trades",
            "subcategory":"Plumbing",
            "type":"Services"
        }
    ],
    "sg:phone":"+1 705 754 9074",
    "sg:postcode":"K0M 1S0",
    "sg:province":"ON",
    "sg:tags":[
        "marina",
        "tank",
        "septic"
    ],
    "wof:name":"Everitt's Enterprises",
    "wof:placetype":"venue"
},
  "geometry": {"coordinates":[-78.5088043213,45.0466995239],"type":"Point"}
}