{
  "type": "Feature",
  "properties": {
    "addr:full":"300 Boul DE LA Grande-Baie N # 3 LA Baie QC G7B 3K3",
    "addr:housenumber":"300",
    "addr:postcode":"g7b 3k3",
    "addr:street":"Boul De La Grande-Baie N # 3",
    "iso:country":"CA",
    "sg:address":"300 Boul DE LA Grande-Baie N # 3",
    "sg:city":"LA Baie",
    "sg:classifiers":[
        {
            "category":"Home & Garden",
            "subcategory":"Building Materials",
            "type":"Retail Goods"
        }
    ],
    "sg:phone":"+1 418 544 3361",
    "sg:postcode":"G7B 3K3",
    "sg:province":"QC",
    "wof:name":"Produits Alba Inc",
    "wof:placetype":"venue"
},
  "geometry": {"coordinates":[-70.882233,48.337948],"type":"Point"}
}