{
  "type": "Feature",
  "properties": {
    "addr:full":"77 Foster St Perth ON K7H 1R9",
    "addr:housenumber":"77",
    "addr:postcode":"k7h 1r9",
    "addr:street":"Foster St",
    "iso:country":"CA",
    "sg:address":"77 Foster St",
    "sg:city":"Perth",
    "sg:classifiers":[
        {
            "category":"Personal",
            "subcategory":"Beauty Salon",
            "type":"Services"
        }
    ],
    "sg:phone":"+1 613 267 4618",
    "sg:postcode":"K7H 1R9",
    "sg:province":"ON",
    "wof:name":"Lorna's Cut'n Curl",
    "wof:placetype":"venue"
},
  "geometry": {"coordinates":[-76.25206,44.900875],"type":"Point"}
}