{
  "type": "Feature",
  "properties": {
    "addr:full":"135 Dundas St Cambridge ON N1R 5N9",
    "addr:housenumber":"135",
    "addr:postcode":"n1r 5n9",
    "addr:street":"Dundas St",
    "iso:country":"CA",
    "sg:address":"135 Dundas St",
    "sg:city":"Cambridge",
    "sg:classifiers":[
        {
            "category":"Manufacturing",
            "subcategory":"Tools & Machinery",
            "type":"Manufacturing & Wholesale Goods"
        }
    ],
    "sg:phone":"+1 519 623 1810",
    "sg:postcode":"N1R 5N9",
    "sg:province":"ON",
    "sg:tags":[
        "equipment",
        "automation",
        "electric",
        "consultant"
    ],
    "wof:name":"Rockwell Automation Canada Inc",
    "wof:placetype":"venue"
},
  "geometry": {"coordinates":[-80.296387,43.360233],"type":"Point"}
}