{
  "type": "Feature",
  "properties": {
    "addr:full":"29 Talbot St E Aylmer ON N5H 1H3",
    "addr:housenumber":"29",
    "addr:postcode":"n5h 1h3",
    "addr:street":"Talbot St E",
    "iso:country":"CA",
    "sg:address":"29 Talbot St E",
    "sg:city":"Aylmer",
    "sg:classifiers":[
        {
            "category":"Personal",
            "subcategory":"Beauty Salon",
            "type":"Services"
        }
    ],
    "sg:phone":"+1 519 773 5318",
    "sg:postcode":"N5H 1H3",
    "sg:province":"ON",
    "wof:name":"Hair Stop",
    "wof:placetype":"venue"
},
  "geometry": {"coordinates":[-80.982277,42.773125],"type":"Point"}
}