{
  "type": "Feature",
  "properties": {
    "addr:full":"184 Fielding Rd Lively ON P3Y 1L6",
    "addr:housenumber":"184",
    "addr:postcode":"p3y 1l6",
    "addr:street":"Fielding Rd",
    "iso:country":"CA",
    "sg:address":"184 Fielding Rd",
    "sg:city":"Lively",
    "sg:classifiers":[
        {
            "category":"Manufacturing",
            "subcategory":"Metals",
            "type":"Manufacturing & Wholesale Goods"
        }
    ],
    "sg:phone":"+1 705 682 0400",
    "sg:postcode":"P3Y 1L6",
    "sg:province":"ON",
    "sg:tags":[
        "steel"
    ],
    "wof:name":"Sudbury Welding & Engineering",
    "wof:placetype":"venue"
},
  "geometry": {"coordinates":[-81.09795379640001,46.4397659302],"type":"Point"}
}