{
  "type": "Feature",
  "properties": {
    "addr:full":"North York ON M3N 2K1",
    "addr:postcode":"m3n 2k1",
    "iso:country":"CA",
    "sg:city":"North York",
    "sg:classifiers":[
        {
            "category":"Food & Beverages",
            "subcategory":"Specialty",
            "type":"Retail Goods"
        }
    ],
    "sg:phone":"+1 416 630 5995",
    "sg:postcode":"M3N 2K1",
    "sg:province":"ON",
    "sg:tags":[
        "tea",
        "coffee"
    ],
    "wof:name":"Wrap Express",
    "wof:placetype":"venue"
},
  "geometry": {"coordinates":[-79.5174789429,43.7569389343],"type":"Point"}
}