{
  "type": "Feature",
  "properties": {
    "iso:country":"CA",
    "sg:address":"2810 Matheson Blvd E # 200",
    "sg:city":"Mississauga",
    "sg:classifiers":[
        {
            "category":"Real Estate",
            "subcategory":"Developer",
            "type":"Services"
        }
    ],
    "sg:phone":"+1 905 282 1414",
    "sg:postcode":"L4W 4X7",
    "sg:province":"ON",
    "wof:name":"Higgins Development Partners",
    "wof:placetype":"venue"
},
  "geometry": {"coordinates":[-79.59484863279999,43.665145874],"type":"Point"}
}