{
  "type": "Feature",
  "properties": {
    "addr:full":"3408 River Trail Stevensville ON L0S 1S0",
    "addr:housenumber":"3408",
    "addr:postcode":"l0s 1s0",
    "addr:street":"River Trail",
    "iso:country":"CA",
    "sg:address":"3408 River Trail",
    "sg:city":"Stevensville",
    "sg:classifiers":[
        {
            "category":"Retail",
            "subcategory":"Auto Rental",
            "type":"Services"
        }
    ],
    "sg:phone":"+1 905 382 2736",
    "sg:postcode":"L0S 1S0",
    "sg:province":"ON",
    "sg:tags":[
        "recreational",
        "leasing",
        "vehicle"
    ],
    "wof:name":"Black Creek Rv Rentals Ltd",
    "wof:placetype":"venue"
},
  "geometry": {"coordinates":[-79.054672,42.943707],"type":"Point"}
}