{
  "type": "Feature",
  "properties": {
    "addr:full":"Sainte-Foy QC G1P 3T2",
    "addr:postcode":"g1p 3t2",
    "iso:country":"CA",
    "sg:city":"Sainte-Foy",
    "sg:classifiers":[
        {
            "category":"Manufacturing",
            "subcategory":"Apparel",
            "type":"Manufacturing & Wholesale Goods"
        }
    ],
    "sg:phone":"+1 418 653 1198",
    "sg:postcode":"G1P 3T2",
    "sg:province":"QC",
    "sg:tags":[
        "awning",
        "textile"
    ],
    "wof:name":"Textiles Letourneau",
    "wof:placetype":"venue"
},
  "geometry": {"coordinates":[-71.2998199463,46.7892913818],"type":"Point"}
}