{
  "type": "Feature",
  "properties": {
    "iso:country":"CA",
    "sg:address":"1516 King St W",
    "sg:city":"Toronto",
    "sg:classifiers":[
        {
            "category":"Real Estate",
            "subcategory":"Real Estate Operator",
            "type":"Services"
        }
    ],
    "sg:phone":"+1 416 534 4031",
    "sg:postcode":"M6K 1J5",
    "sg:province":"ON",
    "sg:tags":[
        "boarding",
        "house"
    ],
    "wof:name":"Tom Clo",
    "wof:placetype":"venue"
},
  "geometry": {"coordinates":[-79.4412155151,43.6366424561],"type":"Point"}
}