{
  "type": "Feature",
  "properties": {
    "addr:full":"1516 King St W Toronto ON M6K 1J5",
    "addr:housenumber":"1516",
    "addr:postcode":"m6k 1j5",
    "addr:street":"King St W",
    "iso:country":"CA",
    "sg:address":"1516 King St W",
    "sg:city":"Toronto",
    "sg:classifiers":[
        {
            "category":"Real Estate",
            "subcategory":"Real Estate Operator",
            "type":"Services"
        }
    ],
    "sg:phone":"+1 416 534 4031",
    "sg:postcode":"M6K 1J5",
    "sg:province":"ON",
    "sg:tags":[
        "boarding",
        "house"
    ],
    "wof:name":"Tom Clo",
    "wof:placetype":"venue"
},
  "geometry": {"coordinates":[-79.4412155151,43.6366424561],"type":"Point"}
}