{
  "type": "Feature",
  "properties": {
    "addr:full":"5100 Genoa Bay Rd Duncan BC V9L 5Y8",
    "addr:housenumber":"5100",
    "addr:postcode":"v9l 5y8",
    "addr:street":"Genoa Bay Rd",
    "iso:country":"CA",
    "sg:address":"5100 Genoa Bay Rd",
    "sg:city":"Duncan",
    "sg:classifiers":[
        {
            "category":"Autos & Motor Vehicles",
            "subcategory":"Boat Sales",
            "type":"Retail Goods"
        }
    ],
    "sg:phone":"+1 250 746 8882",
    "sg:postcode":"V9L 5Y8",
    "sg:province":"BC",
    "sg:tags":[
        "dealer"
    ],
    "wof:name":"Arctic Tropic Cruising Boats",
    "wof:placetype":"venue"
},
  "geometry": {"coordinates":[-123.70738220200001,48.779094696],"type":"Point"}
}