{
  "type": "Feature",
  "properties": {
    "addr:full":"410 St Vincent St Barrie ON L4M 4A6",
    "addr:housenumber":"410",
    "addr:postcode":"l4m 4a6",
    "addr:street":"St Vincent St",
    "iso:country":"CA",
    "sg:address":"410 St Vincent St",
    "sg:city":"Barrie",
    "sg:classifiers":[
        {
            "category":"Restaurant",
            "type":"Food & Drink"
        }
    ],
    "sg:phone":"+1 705 728 1412",
    "sg:postcode":"L4M 4A6",
    "sg:province":"ON",
    "sg:tags":[
        "supply",
        "hall",
        "rooms",
        "wedding",
        "banquet",
        "auditorium"
    ],
    "wof:name":"Royal Canadian Legion Lounge",
    "wof:placetype":"venue"
},
  "geometry": {"coordinates":[-79.68897200000001,44.411324],"type":"Point"}
}