{
  "type": "Feature",
  "properties": {
    "addr:full":"28 Annina Cres Markham ON L3R 4S4",
    "addr:housenumber":"28",
    "addr:postcode":"l3r 4s4",
    "addr:street":"Annina Cres",
    "iso:country":"CA",
    "sg:address":"28 Annina Cres",
    "sg:city":"Markham",
    "sg:classifiers":[
        {
            "category":"Building & Trades",
            "subcategory":"Landscaping Services",
            "type":"Services"
        }
    ],
    "sg:phone":"+1 905 947 9944",
    "sg:postcode":"L3R 4S4",
    "sg:province":"ON",
    "sg:tags":[
        "landscape",
        "contractor"
    ],
    "wof:name":"Sunvalley Landscaping Inc",
    "wof:placetype":"venue"
},
  "geometry": {"coordinates":[-79.2874984741,43.8619308472],"type":"Point"}
}