{
  "type": "Feature",
  "properties": {
    "addr:full":"Salmon Arm BC V1E 1X3",
    "addr:postcode":"v1e 1x3",
    "iso:country":"CA",
    "sg:city":"Salmon Arm",
    "sg:classifiers":[
        {
            "category":"Autos & Motor Vehicles",
            "subcategory":"Automobile Sales",
            "type":"Retail Goods"
        }
    ],
    "sg:phone":"+1 250 832 6207",
    "sg:postcode":"V1E 1X3",
    "sg:province":"BC",
    "sg:tags":[
        "truck"
    ],
    "wof:name":"Gemm Diesel Ltd",
    "wof:placetype":"venue"
},
  "geometry": {"coordinates":[-119.226288,50.669502],"type":"Point"}
}