{
  "type": "Feature",
  "properties": {
    "iso:country":"CA",
    "sg:address":"7470 22E Av",
    "sg:city":"Montreal",
    "sg:classifiers":[
        {
            "category":"Building & Trades",
            "subcategory":"Plumbing",
            "type":"Services"
        }
    ],
    "sg:phone":"+1 514 725 9551",
    "sg:postcode":"H2A 2H6",
    "sg:province":"QC",
    "sg:tags":[
        "contractor"
    ],
    "wof:name":"Jean Charlebois Enr",
    "wof:placetype":"venue"
},
  "geometry": {"coordinates":[-73.595917,45.5676],"type":"Point"}
}