{
  "type": "Feature",
  "properties": {
    "addr:full":"3730 Rue Pascal-Gagnon Terrebonne QC J6X 4J2",
    "addr:housenumber":"3730",
    "addr:postcode":"j6x 4j2",
    "addr:street":"Rue Pascal-Gagnon",
    "iso:country":"CA",
    "sg:address":"3730 Rue Pascal-Gagnon",
    "sg:city":"Terrebonne",
    "sg:classifiers":[
        {
            "category":"Retail",
            "subcategory":"Auto Repair",
            "type":"Services"
        }
    ],
    "sg:phone":"+1 450 477 0499",
    "sg:postcode":"J6X 4J2",
    "sg:province":"QC",
    "sg:tags":[
        "body",
        "automobile",
        "painting"
    ],
    "wof:name":"Carrosseries Bronco Enr",
    "wof:placetype":"venue"
},
  "geometry": {"coordinates":[-73.677261,45.728168],"type":"Point"}
}