{
  "type": "Feature",
  "properties": {
    "addr:full":"1875 Rue Bercy Montreal QC H2K 2T9",
    "addr:housenumber":"1875",
    "addr:postcode":"h2k 2t9",
    "addr:street":"Rue Bercy",
    "iso:country":"CA",
    "sg:address":"1875 Rue Bercy",
    "sg:city":"Montreal",
    "sg:classifiers":[
        {
            "category":"Manufacturing",
            "subcategory":"Food",
            "type":"Manufacturing & Wholesale Goods"
        }
    ],
    "sg:phone":"+1 514 524 3676",
    "sg:postcode":"H2K 2T9",
    "sg:province":"QC",
    "sg:tags":[
        "product",
        "chinese",
        "manufacturer"
    ],
    "wof:name":"Aliments Wong Wing Inc",
    "wof:placetype":"venue"
},
  "geometry": {"coordinates":[-73.54940795900001,45.5341682434],"type":"Point"}
}