{
  "type": "Feature",
  "properties": {
    "addr:full":"Owen Sound ON N4K 5N3",
    "addr:postcode":"n4k 5n3",
    "iso:country":"CA",
    "sg:city":"Owen Sound",
    "sg:classifiers":[
        {
            "category":"Wholesale",
            "subcategory":"Machinery & Supplies",
            "type":"Manufacturing & Wholesale Goods"
        }
    ],
    "sg:phone":"+1 519 371 4290",
    "sg:postcode":"N4K 5N3",
    "sg:province":"ON",
    "sg:tags":[
        "equipment",
        "welding"
    ],
    "wof:name":"Praxair",
    "wof:placetype":"venue"
},
  "geometry": {"coordinates":[-80.90831756590001,44.5850982666],"type":"Point"}
}