{
  "type": "Feature",
  "properties": {
    "addr:full":"8803 26 Ave NW Edmonton AB T6K 2W9",
    "addr:housenumber":"8803",
    "addr:postcode":"t6k 2w9",
    "addr:street":"26 Ave Nw",
    "iso:country":"CA",
    "sg:address":"8803 26 Ave NW",
    "sg:city":"Edmonton",
    "sg:classifiers":[
        {
            "category":"Freight",
            "type":"Transportation"
        }
    ],
    "sg:phone":"+1 780 907 0809",
    "sg:postcode":"T6K 2W9",
    "sg:province":"AB",
    "sg:tags":[
        "consultant",
        "customs"
    ],
    "wof:name":"Tradecan International Inc",
    "wof:placetype":"venue"
},
  "geometry": {"coordinates":[-113.46367645300001,53.4557228088],"type":"Point"}
}