{
  "type": "Feature",
  "properties": {
    "iso:country":"CA",
    "sg:address":"240 Cordova St E",
    "sg:city":"Vancouver",
    "sg:classifiers":[
        {
            "category":"Museum",
            "type":"Entertainment"
        }
    ],
    "sg:phone":"+1 604 665 3346",
    "sg:postcode":"V6A 1L3",
    "sg:province":"BC",
    "wof:name":"Vancouver Police Centennial",
    "wof:placetype":"venue"
},
  "geometry": {"coordinates":[-123.098747253,49.2821464539],"type":"Point"}
}