{
  "type": "Feature",
  "properties": {
    "iso:country":"CA",
    "sg:address":"22 Rue Canvin",
    "sg:city":"Kirkland",
    "sg:classifiers":[
        {
            "category":"Health Services",
            "subcategory":"Doctor",
            "type":"Services"
        }
    ],
    "sg:phone":"+1 514 694 5716",
    "sg:postcode":"H9H 4S4",
    "sg:province":"QC",
    "sg:tags":[
        "dentist"
    ],
    "wof:name":"Badro, Hala DDS",
    "wof:placetype":"venue"
},
  "geometry": {"coordinates":[-73.8356628418,45.4499702454],"type":"Point"}
}