{
  "type": "Feature",
  "properties": {
    "addr:full":"Brossard QC J4Y 3A5",
    "addr:postcode":"j4y 3a5",
    "iso:country":"CA",
    "sg:city":"Brossard",
    "sg:classifiers":[
        {
            "category":"Wholesale",
            "subcategory":"Machinery & Supplies",
            "type":"Manufacturing & Wholesale Goods"
        }
    ],
    "sg:phone":"+1 450 659 7688",
    "sg:postcode":"J4Y 3A5",
    "sg:province":"QC",
    "sg:tags":[
        "asphalt"
    ],
    "wof:name":"Asybco Inc",
    "wof:placetype":"venue"
},
  "geometry": {"coordinates":[-73.4692001343,45.4284629822],"type":"Point"}
}