{
  "type": "Feature",
  "properties": {
    "addr:full":"301 South Ave Melfort SK S0E 1A0",
    "addr:housenumber":"301",
    "addr:postcode":"s0e 1a0",
    "addr:street":"South Ave",
    "iso:country":"CA",
    "sg:address":"301 South Ave",
    "sg:city":"Melfort",
    "sg:classifiers":[
        {
            "category":"Freight",
            "type":"Transportation"
        }
    ],
    "sg:phone":"+1 306 752 9090",
    "sg:postcode":"S0E 1A0",
    "sg:province":"SK",
    "sg:tags":[
        "trucking"
    ],
    "wof:name":"Folden Trucking",
    "wof:placetype":"venue"
},
  "geometry": {"coordinates":[-104.61425800000001,52.859497],"type":"Point"}
}