{
  "type": "Feature",
  "properties": {
    "addr:full":"6633 Highway 7 # 307 Markham ON L3P 7P2",
    "addr:housenumber":"6633",
    "addr:postcode":"l3p 7p2",
    "addr:street":"Highway 7 # 307",
    "iso:country":"CA",
    "sg:address":"6633 Highway 7 # 307",
    "sg:city":"Markham",
    "sg:classifiers":[
        {
            "category":"Health Services",
            "subcategory":"Doctor",
            "type":"Services"
        }
    ],
    "sg:phone":"+1 905 471 2221",
    "sg:postcode":"L3P 7P2",
    "sg:province":"ON",
    "sg:tags":[
        "physician",
        "surgeon"
    ],
    "wof:name":"Shirali, Hemant MD",
    "wof:placetype":"venue"
},
  "geometry": {"coordinates":[-79.33994300000001,43.856033],"type":"Point"}
}