{
  "type": "Feature",
  "properties": {
    "iso:country":"CA",
    "sg:city":"Victoria",
    "sg:classifiers":[
        {
            "category":"Professional",
            "subcategory":"Accounting & Tax Preparation",
            "type":"Services"
        }
    ],
    "sg:phone":"+1 250 385 0312",
    "sg:postcode":"V8T 4W9",
    "sg:province":"BC",
    "sg:tags":[
        "accountant"
    ],
    "wof:name":"Schell & Assoc",
    "wof:placetype":"venue"
},
  "geometry": {"coordinates":[-123.365311,48.440514],"type":"Point"}
}