{
  "type": "Feature",
  "properties": {
    "addr:full":"762 Sea Girt Rd Gabriola BC V0R 1X1",
    "addr:housenumber":"762",
    "addr:postcode":"v0r 1x1",
    "addr:street":"Sea Girt Rd",
    "iso:country":"CA",
    "sg:address":"762 Sea Girt Rd",
    "sg:city":"Gabriola",
    "sg:classifiers":[
        {
            "category":"Building & Trades",
            "subcategory":"Construction",
            "type":"Services"
        }
    ],
    "sg:phone":"+1 250 247 9391",
    "sg:postcode":"V0R 1X1",
    "sg:province":"BC",
    "sg:tags":[
        "boring",
        "drilling",
        "contractor"
    ],
    "wof:name":"D Windecker Water Wells",
    "wof:placetype":"venue"
},
  "geometry": {"coordinates":[-123.83266449,49.2000999451],"type":"Point"}
}