{
  "type": "Feature",
  "properties": {
    "addr:full":"1100 Berkshire Blvd NW Calgary AB T3K 3M3",
    "addr:housenumber":"1100",
    "addr:postcode":"t3k 3m3",
    "addr:street":"Berkshire Blvd Nw",
    "iso:country":"CA",
    "sg:address":"1100 Berkshire Blvd NW",
    "sg:city":"Calgary",
    "sg:classifiers":[
        {
            "category":"Recreation",
            "type":"Entertainment"
        }
    ],
    "sg:phone":"+1 403 295 8100",
    "sg:postcode":"T3K 3M3",
    "sg:province":"AB",
    "sg:tags":[
        "church",
        "hall",
        "auditorium"
    ],
    "wof:name":"Sandstone Valley Ecumenical",
    "wof:placetype":"venue"
},
  "geometry": {"coordinates":[-114.087029,51.134872],"type":"Point"}
}