{
  "type": "Feature",
  "properties": {
    "addr:full":"Ottawa ON K1R 1B1",
    "addr:postcode":"k1r 1b1",
    "iso:country":"CA",
    "sg:city":"Ottawa",
    "sg:classifiers":[
        {
            "category":"Organizations",
            "subcategory":"Professional Association",
            "type":"Services"
        }
    ],
    "sg:phone":"+1 613 563 1236",
    "sg:postcode":"K1R 1B1",
    "sg:province":"ON",
    "wof:name":"Association of Universities",
    "wof:placetype":"venue"
},
  "geometry": {"coordinates":[-75.70388793950001,45.4182319641],"type":"Point"}
}