{
  "type": "Feature",
  "properties": {
    "addr:full":"644 William Ave Winnipeg MB R3A 0K3",
    "addr:housenumber":"644",
    "addr:postcode":"r3a 0k3",
    "addr:street":"William Ave",
    "iso:country":"CA",
    "sg:address":"644 William Ave",
    "sg:city":"Winnipeg",
    "sg:classifiers":[
        {
            "category":"Personal",
            "subcategory":"Beauty Salon",
            "type":"Services"
        }
    ],
    "sg:phone":"+1 204 775 5293",
    "sg:postcode":"R3A 0K3",
    "sg:province":"MB",
    "wof:name":"Josephine Beauty Salon",
    "wof:placetype":"venue"
},
  "geometry": {"coordinates":[-97.1548461914,49.9037818909],"type":"Point"}
}