{
  "type": "Feature",
  "properties": {
    "addr:full":"5575 North Service Rd # 200 Burlington ON L7L 6M1",
    "addr:housenumber":"5575",
    "addr:postcode":"l7l 6m1",
    "addr:street":"North Service Rd # 200",
    "iso:country":"CA",
    "sg:address":"5575 North Service Rd # 200",
    "sg:city":"Burlington",
    "sg:classifiers":[
        {
            "category":"Professional",
            "subcategory":"Management & Consulting",
            "type":"Services"
        }
    ],
    "sg:phone":"+1 905 331 5060",
    "sg:postcode":"L7L 6M1",
    "sg:province":"ON",
    "sg:tags":[
        "consultant",
        "educational"
    ],
    "wof:name":"Pink Elephant Inc",
    "wof:placetype":"venue"
},
  "geometry": {"coordinates":[-79.76323699949999,43.3974266052],"type":"Point"}
}