{
  "type": "Feature",
  "properties": {
    "addr:full":"15453 Rue DE Saint-Augustin Mirabel QC J7N 2B1",
    "addr:housenumber":"15453",
    "addr:postcode":"j7n 2b1",
    "addr:street":"Rue De Saint-Augustin",
    "iso:country":"CA",
    "sg:address":"15453 Rue DE Saint-Augustin",
    "sg:city":"Mirabel",
    "sg:classifiers":[
        {
            "category":"Professional",
            "subcategory":"Engineering",
            "type":"Services"
        }
    ],
    "sg:phone":"+1 450 475 8199",
    "sg:postcode":"J7N 2B1",
    "sg:province":"QC",
    "sg:tags":[
        "engineer"
    ],
    "wof:name":"Dorcosult Inc",
    "wof:placetype":"venue"
},
  "geometry": {"coordinates":[-73.975151,45.626202],"type":"Point"}
}