{
  "type": "Feature",
  "properties": {
    "addr:full":"646 Av Du Phare E Matane QC G4W 1B1",
    "addr:postcode":"g4w 1b1",
    "addr:street":"646 Av Du Phare E",
    "iso:country":"CA",
    "sg:address":"646 Av Du Phare E",
    "sg:city":"Matane",
    "sg:classifiers":[
        {
            "category":"Food & Beverages",
            "subcategory":"Bakery",
            "type":"Retail Goods"
        }
    ],
    "sg:phone":"+1 418 562 9033",
    "sg:postcode":"G4W 1B1",
    "sg:province":"QC",
    "sg:tags":[
        "baker"
    ],
    "wof:name":"Patisserie LA Bonne Fournee",
    "wof:placetype":"venue"
},
  "geometry": {"coordinates":[-67.50614899999999,48.852524],"type":"Point"}
}