{
  "type": "Feature",
  "properties": {
    "addr:full":"Abbotsford BC V2T 5M4",
    "addr:postcode":"v2t 5m4",
    "iso:country":"CA",
    "sg:city":"Abbotsford",
    "sg:classifiers":[
        {
            "category":"Health Services",
            "subcategory":"Doctor",
            "type":"Services"
        }
    ],
    "sg:phone":"+1 604 853 1334",
    "sg:postcode":"V2T 5M4",
    "sg:province":"BC",
    "sg:tags":[
        "physician",
        "surgeon"
    ],
    "wof:name":"Strydom, Gerhard MD",
    "wof:placetype":"venue"
},
  "geometry": {"coordinates":[-122.323852539,49.0538444519],"type":"Point"}
}