{
  "type": "Feature",
  "properties": {
    "addr:full":"92 Rue DE LA Gauchetiere O Montreal QC H2Z 1C1",
    "addr:housenumber":"92",
    "addr:postcode":"h2z 1c1",
    "addr:street":"Rue De La Gauchetiere O",
    "iso:country":"CA",
    "sg:address":"92 Rue DE LA Gauchetiere O",
    "sg:city":"Montreal",
    "sg:classifiers":[
        {
            "category":"Restaurant",
            "type":"Food & Drink"
        }
    ],
    "sg:phone":"+1 514 861 2003",
    "sg:postcode":"H2Z 1C1",
    "sg:province":"QC",
    "wof:name":"Beijing Restaurant Inc",
    "wof:placetype":"venue"
},
  "geometry": {"coordinates":[-73.5589752197,45.5092086792],"type":"Point"}
}