{
  "type": "Feature",
  "properties": {
    "addr:full":"1210 Boul Des Seigneurs Terrebonne QC J6W 3W4",
    "addr:housenumber":"1210",
    "addr:postcode":"j6w 3w4",
    "addr:street":"Boul Des Seigneurs",
    "iso:country":"CA",
    "sg:address":"1210 Boul Des Seigneurs",
    "sg:city":"Terrebonne",
    "sg:classifiers":[
        {
            "category":"Health Services",
            "subcategory":"Optometrist",
            "type":"Services"
        }
    ],
    "sg:phone":"+1 450 492 2212",
    "sg:postcode":"J6W 3W4",
    "sg:province":"QC",
    "wof:name":"Optometristes Luc Doyle",
    "wof:placetype":"venue"
},
  "geometry": {"coordinates":[-73.64674377439999,45.7000923157],"type":"Point"}
}