{
  "type": "Feature",
  "properties": {
    "addr:full":"2083 Boul Edouard Saint-Hubert QC J4T 2A2",
    "addr:housenumber":"2083",
    "addr:postcode":"j4t 2a2",
    "addr:street":"Boul Edouard",
    "iso:country":"CA",
    "sg:address":"2083 Boul Edouard",
    "sg:city":"Saint-Hubert",
    "sg:classifiers":[
        {
            "category":"Restaurant",
            "type":"Food & Drink"
        }
    ],
    "sg:phone":"+1 450 672 0812",
    "sg:postcode":"J4T 2A2",
    "sg:province":"QC",
    "wof:name":"John Dias Restaurant",
    "wof:placetype":"venue"
},
  "geometry": {"coordinates":[-73.4807128906,45.4965019226],"type":"Point"}
}