{
  "type": "Feature",
  "properties": {
    "iso:country":"CA",
    "sg:address":"2151 Jane St",
    "sg:city":"North York",
    "sg:classifiers":[
        {
            "category":"Retail",
            "subcategory":"Auto Repair",
            "type":"Services"
        }
    ],
    "sg:phone":"+1 416 244 5322",
    "sg:postcode":"M3M 1A2",
    "sg:province":"ON",
    "sg:tags":[
        "repairing",
        "automobile",
        "tire"
    ],
    "wof:name":"Active Green & Ross",
    "wof:placetype":"venue"
},
  "geometry": {"coordinates":[-79.50831599999999,43.720459],"type":"Point"}
}