{
  "type": "Feature",
  "properties": {
    "addr:full":"25919 112 Ave Maple Ridge BC V2W 1H1",
    "addr:housenumber":"25919",
    "addr:postcode":"v2w 1h1",
    "addr:street":"112 Ave",
    "iso:country":"CA",
    "sg:address":"25919 112 Ave",
    "sg:city":"Maple Ridge",
    "sg:classifiers":[
        {
            "category":"Farming",
            "subcategory":"Farm & Veterinary Services",
            "type":"Manufacturing & Wholesale Goods"
        }
    ],
    "sg:phone":"+1 604 462 0637",
    "sg:postcode":"V2W 1H1",
    "sg:province":"BC",
    "sg:tags":[
        "control",
        "weed"
    ],
    "wof:name":"Western Weed Control Ltd",
    "wof:placetype":"venue"
},
  "geometry": {"coordinates":[-122.503677,49.205925],"type":"Point"}
}