{
  "type": "Feature",
  "properties": {
    "addr:full":"607 Main St Sussex NB E4E 7H5",
    "addr:housenumber":"607",
    "addr:postcode":"e4e 7h5",
    "addr:street":"Main St",
    "iso:country":"CA",
    "sg:address":"607 Main St",
    "sg:city":"Sussex",
    "sg:classifiers":[
        {
            "category":"Shopping",
            "subcategory":"Clothing, Apparel, & Fashions",
            "type":"Retail Goods"
        }
    ],
    "sg:phone":"+1 506 433 3975",
    "sg:postcode":"E4E 7H5",
    "sg:province":"NB",
    "wof:name":"Black's Fashions & Shoes Ltd",
    "wof:placetype":"venue"
},
  "geometry": {"coordinates":[-65.5079116821,45.7230148315],"type":"Point"}
}