{
  "type": "Feature",
  "properties": {
    "iso:country":"CA",
    "sg:address":"PO Box 39",
    "sg:city":"St Pauls",
    "sg:classifiers":[
        {
            "category":"Food & Beverages",
            "subcategory":"Groceries & Convenience Stores",
            "type":"Retail Goods"
        }
    ],
    "sg:phone":"+1 709 243 2370",
    "sg:postcode":"A0K 4Y0",
    "sg:province":"NL",
    "sg:tags":[
        "grocer"
    ],
    "wof:name":"Bennetts Grocery",
    "wof:placetype":"venue"
},
  "geometry": {"coordinates":[-57.806778,49.85223],"type":"Point"}
}