{
  "type": "Feature",
  "properties": {
    "addr:full":"211 York Rd Dundas ON L9H 1M9",
    "addr:housenumber":"211",
    "addr:postcode":"l9h 1m9",
    "addr:street":"York Rd",
    "iso:country":"CA",
    "sg:address":"211 York Rd",
    "sg:city":"Dundas",
    "sg:classifiers":[
        {
            "category":"Real Estate",
            "subcategory":"Real Estate Operator",
            "type":"Services"
        }
    ],
    "sg:phone":"+1 905 628 4831",
    "sg:postcode":"L9H 1M9",
    "sg:province":"ON",
    "sg:tags":[
        "apartment"
    ],
    "wof:name":"Yorkville Place",
    "wof:placetype":"venue"
},
  "geometry": {"coordinates":[-79.94156646730001,43.2757263184],"type":"Point"}
}