{
  "type": "Feature",
  "properties": {
    "addr:full":"315 Rue Principale # A Courcelles QC G0M 1C0",
    "addr:housenumber":"315",
    "addr:postcode":"g0m 1c0",
    "addr:street":"Rue Principale # A",
    "iso:country":"CA",
    "sg:address":"315 Rue Principale # A",
    "sg:city":"Courcelles",
    "sg:classifiers":[
        {
            "category":"Manufacturing",
            "subcategory":"Tools & Machinery",
            "type":"Manufacturing & Wholesale Goods"
        }
    ],
    "sg:phone":"+1 418 483 5747",
    "sg:postcode":"G0M 1C0",
    "sg:province":"QC",
    "sg:tags":[
        "equipment",
        "motel",
        "hotel",
        "supply"
    ],
    "wof:name":"Bidulart Miroirs Decoratifs",
    "wof:placetype":"venue"
},
  "geometry": {"coordinates":[-70.981735,45.870403],"type":"Point"}
}