{
  "type": "Feature",
  "properties": {
    "addr:full":"925 Tenth St New Westminster BC V3M 4A8",
    "addr:housenumber":"925",
    "addr:postcode":"v3m 4a8",
    "addr:street":"Tenth St",
    "iso:country":"CA",
    "sg:address":"925 Tenth St",
    "sg:city":"New Westminster",
    "sg:classifiers":[
        {
            "category":"Organizations",
            "subcategory":"Religious Organization",
            "type":"Services"
        }
    ],
    "sg:phone":"+1 604 526 8077",
    "sg:postcode":"V3M 4A8",
    "sg:province":"BC",
    "sg:tags":[
        "church"
    ],
    "wof:name":"Mainland Baptist Fellowship",
    "wof:placetype":"venue"
},
  "geometry": {"coordinates":[-122.933189,49.214905],"type":"Point"}
}