{
  "type": "Feature",
  "properties": {
    "addr:full":"7110 Ogden Dale Rd SE Calgary AB T2C 3A9",
    "addr:housenumber":"7110",
    "addr:postcode":"t2c 3a9",
    "addr:street":"Ogden Dale Rd Se",
    "iso:country":"CA",
    "sg:address":"7110 Ogden Dale Rd SE",
    "sg:city":"Calgary",
    "sg:classifiers":[
        {
            "category":"Freight",
            "type":"Transportation"
        }
    ],
    "sg:phone":"+1 403 236 7676",
    "sg:postcode":"T2C 3A9",
    "sg:province":"AB",
    "sg:tags":[
        "mover"
    ],
    "wof:name":"L Hansen's Forwarding",
    "wof:placetype":"venue"
},
  "geometry": {"coordinates":[-113.99042511,50.9896392822],"type":"Point"}
}