{
  "type": "Feature",
  "properties": {
    "addr:full":"Edmonton AB T6E 6C3",
    "addr:postcode":"t6e 6c3",
    "iso:country":"CA",
    "sg:city":"Edmonton",
    "sg:classifiers":[
        {
            "category":"Professional",
            "subcategory":"Lawyer & Legal Services",
            "type":"Services"
        }
    ],
    "sg:phone":"+1 780 438 4972",
    "sg:postcode":"T6E 6C3",
    "sg:province":"AB",
    "sg:tags":[
        "attorney"
    ],
    "wof:name":"Harker, Darrel B",
    "wof:placetype":"venue"
},
  "geometry": {"coordinates":[-113.494705,53.515202],"type":"Point"}
}