{
  "type": "Feature",
  "properties": {
    "addr:full":"Wallenstein ON N0B 2S0",
    "addr:postcode":"n0b 2s0",
    "iso:country":"CA",
    "sg:city":"Wallenstein",
    "sg:classifiers":[
        {
            "category":"Wholesale",
            "subcategory":"Farm Supplies",
            "type":"Manufacturing & Wholesale Goods"
        }
    ],
    "sg:phone":"+1 519 699 4360",
    "sg:postcode":"N0B 2S0",
    "sg:province":"ON",
    "sg:tags":[
        "chemical",
        "agricultural"
    ],
    "wof:name":"David C Martin & Son",
    "wof:placetype":"venue"
},
  "geometry": {"coordinates":[-80.634216,43.599659],"type":"Point"}
}