{
  "type": "Feature",
  "properties": {
    "addr:full":"504 Main St Mahone Bay NS B0J 2E0",
    "addr:housenumber":"504",
    "addr:postcode":"b0j 2e0",
    "addr:street":"Main St",
    "iso:country":"CA",
    "sg:address":"504 Main St",
    "sg:city":"Mahone Bay",
    "sg:classifiers":[
        {
            "category":"Shopping",
            "subcategory":"Used Merchandise",
            "type":"Retail Goods"
        }
    ],
    "sg:phone":"+1 902 531 3119",
    "sg:postcode":"B0J 2E0",
    "sg:province":"NS",
    "sg:tags":[
        "antique"
    ],
    "wof:name":"Puddle Dock Emporium",
    "wof:placetype":"venue"
},
  "geometry": {"coordinates":[-64.381462,44.448589],"type":"Point"}
}