{
  "type": "Feature",
  "properties": {
    "addr:full":"317 Atherley Rd Orillia ON L3V 1N8",
    "addr:housenumber":"317",
    "addr:postcode":"l3v 1n8",
    "addr:street":"Atherley Rd",
    "iso:country":"CA",
    "sg:address":"317 Atherley Rd",
    "sg:city":"Orillia",
    "sg:classifiers":[
        {
            "category":"Retail",
            "subcategory":"Self-service Laundry",
            "type":"Services"
        }
    ],
    "sg:phone":"+1 705 326 9465",
    "sg:postcode":"L3V 1N8",
    "sg:province":"ON",
    "wof:name":"Atherley Road Coin Laundry",
    "wof:placetype":"venue"
},
  "geometry": {"coordinates":[-79.396439,44.605701],"type":"Point"}
}