{
  "type": "Feature",
  "properties": {
    "addr:full":"2262 Av Du Pont N Alma QC G8E 1P9",
    "addr:housenumber":"2262",
    "addr:postcode":"g8e 1p9",
    "addr:street":"Av Du Pont N",
    "iso:country":"CA",
    "sg:address":"2262 Av Du Pont N",
    "sg:city":"Alma",
    "sg:classifiers":[
        {
            "category":"Building & Trades",
            "subcategory":"Electrical",
            "type":"Services"
        }
    ],
    "sg:phone":"+1 418 662 5663",
    "sg:postcode":"G8E 1P9",
    "sg:province":"QC",
    "sg:tags":[
        "electric",
        "contractor",
        "system",
        "heating"
    ],
    "wof:name":"Remi Bouchard Inc",
    "wof:placetype":"venue"
},
  "geometry": {"coordinates":[-71.63107299799999,48.5921020508],"type":"Point"}
}