{
  "type": "Feature",
  "properties": {
    "addr:full":"475 Rue Saint-Pierre Drummondville QC J2C 3W4",
    "addr:housenumber":"475",
    "addr:postcode":"j2c 3w4",
    "addr:street":"Rue Saint-Pierre",
    "iso:country":"CA",
    "sg:address":"475 Rue Saint-Pierre",
    "sg:city":"Drummondville",
    "sg:classifiers":[
        {
            "category":"Manufacturing",
            "subcategory":"Retail Goods",
            "type":"Manufacturing & Wholesale Goods"
        }
    ],
    "sg:phone":"+1 819 474 4057",
    "sg:postcode":"J2C 3W4",
    "sg:province":"QC",
    "sg:tags":[
        "rubber",
        "stamp"
    ],
    "wof:name":"Estampes Jrp Inc",
    "wof:placetype":"venue"
},
  "geometry": {"coordinates":[-72.503311,45.883274],"type":"Point"}
}