{
  "type": "Feature",
  "properties": {
    "addr:full":"520 Locust St Burlington ON L7S 1V2",
    "addr:housenumber":"520",
    "addr:postcode":"l7s 1v2",
    "addr:street":"Locust St",
    "iso:country":"CA",
    "sg:address":"520 Locust St",
    "sg:city":"Burlington",
    "sg:classifiers":[
        {
            "category":"Health Services",
            "subcategory":"Doctor",
            "type":"Services"
        }
    ],
    "sg:phone":"+1 905 631 6288",
    "sg:postcode":"L7S 1V2",
    "sg:province":"ON",
    "sg:tags":[
        "surgery",
        "salon",
        "beauty",
        "cosmetic"
    ],
    "wof:name":"Cosmedica Professional Skin",
    "wof:placetype":"venue"
},
  "geometry": {"coordinates":[-79.801033,43.32642],"type":"Point"}
}