{
  "type": "Feature",
  "properties": {
    "addr:full":"3291 LA Grande-Allee Saint-Hubert QC J4T 2S8",
    "addr:housenumber":"3291",
    "addr:postcode":"j4t 2s8",
    "addr:street":"La Grande-Allee",
    "iso:country":"CA",
    "sg:address":"3291 LA Grande-Allee",
    "sg:city":"Saint-Hubert",
    "sg:classifiers":[
        {
            "category":"Restaurant",
            "type":"Food & Drink"
        }
    ],
    "sg:phone":"+1 450 443 8492",
    "sg:postcode":"J4T 2S8",
    "sg:province":"QC",
    "sg:tags":[
        "delicatessen"
    ],
    "wof:name":"Charcuterie Cracovie",
    "wof:placetype":"venue"
},
  "geometry": {"coordinates":[-73.4762496948,45.4968719482],"type":"Point"}
}