{
  "type": "Feature",
  "properties": {
    "addr:full":"319 Selkirk Ave Winnipeg MB R2W 2L8",
    "addr:housenumber":"319",
    "addr:postcode":"r2w 2l8",
    "addr:street":"Selkirk Ave",
    "iso:country":"CA",
    "sg:address":"319 Selkirk Ave",
    "sg:city":"Winnipeg",
    "sg:classifiers":[
        {
            "category":"Education",
            "subcategory":"School",
            "type":"Public Place"
        }
    ],
    "sg:phone":"+1 204 582 1053",
    "sg:postcode":"R2W 2L8",
    "sg:province":"MB",
    "wof:name":"Holy Ghost School",
    "wof:placetype":"venue"
},
  "geometry": {"coordinates":[-97.13799299999999,49.913593],"type":"Point"}
}