{
  "type": "Feature",
  "properties": {
    "addr:full":"42 Av Lussier Pincourt QC J7V 5A9",
    "addr:postcode":"j7v 5a9",
    "addr:street":"42 Av Lussier",
    "iso:country":"CA",
    "sg:address":"42 Av Lussier",
    "sg:city":"Pincourt",
    "sg:classifiers":[
        {
            "category":"Restaurant",
            "type":"Food & Drink"
        }
    ],
    "sg:phone":"+1 514 453 6666",
    "sg:postcode":"J7V 5A9",
    "sg:province":"QC",
    "wof:name":"Rotisserie Du Parc",
    "wof:placetype":"venue"
},
  "geometry": {"coordinates":[-73.99183654789999,45.3718109131],"type":"Point"}
}