{
  "type": "Feature",
  "properties": {
    "addr:full":"1100 Lorne Park Rd Mississauga ON L5H 3A3",
    "addr:housenumber":"1100",
    "addr:postcode":"l5h 3a3",
    "addr:street":"Lorne Park Rd",
    "iso:country":"CA",
    "sg:address":"1100 Lorne Park Rd",
    "sg:city":"Mississauga",
    "sg:classifiers":[
        {
            "category":"Personal",
            "subcategory":"Beauty Salon",
            "type":"Services"
        }
    ],
    "sg:phone":"+1 905 274 1660",
    "sg:postcode":"L5H 3A3",
    "sg:province":"ON",
    "wof:name":"Salon of Lorne Park",
    "wof:placetype":"venue"
},
  "geometry": {"coordinates":[-79.612495,43.531334],"type":"Point"}
}