{
  "type": "Feature",
  "properties": {
    "addr:full":"7497 Wrenwood Cres Mississauga ON L4T 2V8",
    "addr:housenumber":"7497",
    "addr:postcode":"l4t 2v8",
    "addr:street":"Wrenwood Cres",
    "iso:country":"CA",
    "sg:address":"7497 Wrenwood Cres",
    "sg:city":"Mississauga",
    "sg:classifiers":[
        {
            "category":"Retail",
            "subcategory":"Portrait Studio",
            "type":"Services"
        }
    ],
    "sg:phone":"+1 905 672 0005",
    "sg:postcode":"L4T 2V8",
    "sg:province":"ON",
    "sg:tags":[
        "photographer"
    ],
    "wof:name":"Bobby's Photography",
    "wof:placetype":"venue"
},
  "geometry": {"coordinates":[-79.640793,43.72953],"type":"Point"}
}