{
  "type": "Feature",
  "properties": {
    "addr:full":"11781 Fraser St Maple Ridge BC V2X 6C6",
    "addr:housenumber":"11781",
    "addr:postcode":"v2x 6c6",
    "addr:street":"Fraser St",
    "iso:country":"CA",
    "sg:address":"11781 Fraser St",
    "sg:city":"Maple Ridge",
    "sg:classifiers":[
        {
            "category":"Professional",
            "type":"Services"
        }
    ],
    "sg:phone":"+1 604 467 4955",
    "sg:postcode":"V2X 6C6",
    "sg:province":"BC",
    "sg:tags":[
        "establishment",
        "television",
        "radio"
    ],
    "wof:name":"Haney Tv & Sound Svc Ltd",
    "wof:placetype":"venue"
},
  "geometry": {"coordinates":[-122.60041,49.216557],"type":"Point"}
}