{
  "type": "Feature",
  "properties": {
    "addr:full":"227 10th Ave S Cranbrook BC V1C 2N3",
    "addr:housenumber":"227",
    "addr:postcode":"bc v1c 2n3",
    "addr:street":"10Th Ave S",
    "iso:country":"CA",
    "sg:address":"227 10th Ave S",
    "sg:city":"Cranbrook",
    "sg:classifiers":[
        {
            "category":"Personal",
            "type":"Services"
        }
    ],
    "sg:phone":"+1 250 426 8706",
    "sg:postcode":"V1C 2N3",
    "sg:province":"BC",
    "sg:tags":[
        "therapist",
        "massage"
    ],
    "wof:name":"East Kootenay Massage",
    "wof:placetype":"venue"
},
  "geometry": {"coordinates":[-115.767799,49.507915],"type":"Point"}
}