{
  "type": "Feature",
  "properties": {
    "addr:full":"Sylvan Lake AB T4S 1P5",
    "addr:postcode":"t4s 1p5",
    "iso:country":"CA",
    "sg:city":"Sylvan Lake",
    "sg:classifiers":[
        {
            "category":"Building & Trades",
            "subcategory":"Equipment Rental",
            "type":"Services"
        }
    ],
    "sg:phone":"+1 403 887 5011",
    "sg:postcode":"T4S 1P5",
    "sg:province":"AB",
    "sg:tags":[
        "yard"
    ],
    "wof:name":"Sylvan Lake Rentals & Sales",
    "wof:placetype":"venue"
},
  "geometry": {"coordinates":[-114.07231140099999,52.3179702759],"type":"Point"}
}