{
  "type": "Feature",
  "properties": {
    "iso:country":"CA",
    "sg:address":"RR 3 STN Main",
    "sg:city":"Orillia",
    "sg:classifiers":[
        {
            "category":"Farming",
            "subcategory":"Farm",
            "type":"Manufacturing & Wholesale Goods"
        }
    ],
    "sg:phone":"+1 705 329 1916",
    "sg:postcode":"L3V 6H3",
    "sg:province":"ON",
    "wof:name":"Highland Farm",
    "wof:placetype":"venue"
},
  "geometry": {"coordinates":[-79.41822814939999,44.606590271],"type":"Point"}
}