{
  "type": "Feature",
  "properties": {
    "iso:country":"CA",
    "sg:city":"Otterburn Park",
    "sg:classifiers":[
        {
            "category":"Building & Trades",
            "subcategory":"Electrical",
            "type":"Services"
        }
    ],
    "sg:phone":"+1 450 467 9217",
    "sg:postcode":"J3H 1W8",
    "sg:province":"QC",
    "sg:tags":[
        "electric",
        "contractor"
    ],
    "wof:name":"Gerard Petit Inc",
    "wof:placetype":"venue"
},
  "geometry": {"coordinates":[-73.200089,45.546173],"type":"Point"}
}