{
  "type": "Feature",
  "properties": {
    "addr:full":"Otterburn Park QC J3H 1W8",
    "addr:postcode":"j3h 1w8",
    "addr:street":"Park",
    "iso:country":"CA",
    "sg:city":"Otterburn Park",
    "sg:classifiers":[
        {
            "category":"Building & Trades",
            "subcategory":"Electrical",
            "type":"Services"
        }
    ],
    "sg:phone":"+1 450 467 9217",
    "sg:postcode":"J3H 1W8",
    "sg:province":"QC",
    "sg:tags":[
        "electric",
        "contractor"
    ],
    "wof:name":"Gerard Petit Inc",
    "wof:placetype":"venue"
},
  "geometry": {"coordinates":[-73.20008900000001,45.546173],"type":"Point"}
}