{
  "type": "Feature",
  "properties": {
    "addr:full":"210 Bloomington Rd Aurora ON L4G 3G8",
    "addr:housenumber":"210",
    "addr:postcode":"l4g 3g8",
    "addr:street":"Bloomington Rd",
    "iso:country":"CA",
    "sg:address":"210 Bloomington Rd",
    "sg:city":"Aurora",
    "sg:classifiers":[
        {
            "category":"Restaurant",
            "type":"Food & Drink"
        }
    ],
    "sg:phone":"+1 905 841 6278",
    "sg:postcode":"L4G 3G8",
    "sg:province":"ON",
    "sg:tags":[
        "caterer"
    ],
    "wof:name":"Nellaos Catering Ltd",
    "wof:placetype":"venue"
},
  "geometry": {"coordinates":[-79.451538,43.964596],"type":"Point"}
}