{
  "type": "Feature",
  "properties": {
    "addr:full":"523 Boul Des Laurentides Laval QC H7G 2V3",
    "addr:housenumber":"523",
    "addr:postcode":"qc h7g 2v3",
    "addr:street":"Boul Des Laurentides",
    "iso:country":"CA",
    "sg:address":"523 Boul Des Laurentides",
    "sg:city":"Laval",
    "sg:classifiers":[
        {
            "category":"Home & Garden",
            "subcategory":"Building Materials",
            "type":"Retail Goods"
        }
    ],
    "sg:phone":"+1 450 669 4838",
    "sg:postcode":"H7G 2V3",
    "sg:province":"QC",
    "sg:tags":[
        "plate",
        "window",
        "mirror"
    ],
    "wof:name":"Vitrerie Pont Viau Inc",
    "wof:placetype":"venue"
},
  "geometry": {"coordinates":[-73.6923675537,45.5708961487],"type":"Point"}
}