{
  "type": "Feature",
  "properties": {
    "iso:country":"CA",
    "sg:city":"Sudbury",
    "sg:classifiers":[
        {
            "category":"Building & Trades",
            "subcategory":"Construction",
            "type":"Services"
        }
    ],
    "sg:phone":"+1 705 560 6974",
    "sg:postcode":"P3B 1R5",
    "sg:province":"ON",
    "sg:tags":[
        "sewer",
        "contractor"
    ],
    "wof:name":"F H R Construction CO Ltd",
    "wof:placetype":"venue"
},
  "geometry": {"coordinates":[-80.954147,46.494766],"type":"Point"}
}