{
  "type": "Feature",
  "properties": {
    "addr:full":"26317 Route 2 Summerside PE C1N 4J8",
    "addr:housenumber":"26317",
    "addr:postcode":"c1n 4j8",
    "addr:street":"Route 2",
    "iso:country":"CA",
    "sg:address":"26317 Route 2",
    "sg:city":"Summerside",
    "sg:classifiers":[
        {
            "category":"Shopping",
            "subcategory":"Used Merchandise",
            "type":"Retail Goods"
        }
    ],
    "sg:phone":"+1 902 436 4977",
    "sg:postcode":"C1N 4J8",
    "sg:province":"PE",
    "sg:tags":[
        "antique"
    ],
    "wof:name":"Riverview Antiques",
    "wof:placetype":"venue"
},
  "geometry": {"coordinates":[-63.7919425964,46.3940849304],"type":"Point"}
}