{
  "type": "Feature",
  "properties": {
    "addr:full":"769 King St W Hamilton ON L8S 1J9",
    "addr:housenumber":"769",
    "addr:postcode":"l8s 1j9",
    "addr:street":"King St W",
    "iso:country":"CA",
    "sg:address":"769 King St W",
    "sg:city":"Hamilton",
    "sg:classifiers":[
        {
            "category":"Health Services",
            "subcategory":"Doctor",
            "type":"Services"
        }
    ],
    "sg:phone":"+1 905 528 5858",
    "sg:postcode":"L8S 1J9",
    "sg:province":"ON",
    "sg:tags":[
        "physician",
        "surgeon"
    ],
    "wof:name":"Westdale Women's Clinic",
    "wof:placetype":"venue"
},
  "geometry": {"coordinates":[-79.8964538574,43.2619018555],"type":"Point"}
}