{
  "type": "Feature",
  "properties": {
    "iso:country":"CA",
    "sg:address":"5 Rue Cholette",
    "sg:city":"Hull",
    "sg:classifiers":[
        {
            "category":"Retail",
            "subcategory":"Portrait Studio",
            "type":"Services"
        }
    ],
    "sg:phone":"+1 819 771 8958",
    "sg:postcode":"J8Y 1J5",
    "sg:province":"QC",
    "sg:tags":[
        "photographer"
    ],
    "wof:name":"Studio Sokolowski",
    "wof:placetype":"venue"
},
  "geometry": {"coordinates":[-75.7523651123,45.4535598755],"type":"Point"}
}