{
  "type": "Feature",
  "properties": {
    "addr:full":"80 Charles St E # Ll Toronto ON M4Y 2W6",
    "addr:housenumber":"80",
    "addr:postcode":"m4y 2w6",
    "addr:street":"Charles St E # Ll",
    "iso:country":"CA",
    "sg:address":"80 Charles St E # Ll",
    "sg:city":"Toronto",
    "sg:classifiers":[
        {
            "category":"Health Services",
            "subcategory":"Doctor",
            "type":"Services"
        }
    ],
    "sg:phone":"+1 416 926 1502",
    "sg:postcode":"M4Y 2W6",
    "sg:province":"ON",
    "sg:tags":[
        "dentist"
    ],
    "wof:name":"Compton, Robin DDS",
    "wof:placetype":"venue"
},
  "geometry": {"coordinates":[-79.3822555542,43.6695785522],"type":"Point"}
}