{
  "type": "Feature",
  "properties": {
    "iso:country":"CA",
    "sg:address":"1319 Victoria Ave E",
    "sg:city":"Thunder Bay",
    "sg:classifiers":[
        {
            "category":"Shopping",
            "subcategory":"Hobbies, Toys, & Games",
            "type":"Retail Goods"
        }
    ],
    "sg:phone":"+1 807 622 8401",
    "sg:postcode":"P7C 1C3",
    "sg:province":"ON",
    "sg:tags":[
        "equipment",
        "model",
        "wine",
        "supply"
    ],
    "wof:name":"Narwhal Stamp & Coin",
    "wof:placetype":"venue"
},
  "geometry": {"coordinates":[-89.25564575200001,48.3843231201],"type":"Point"}
}