{
  "type": "Feature",
  "properties": {
    "addr:full":"5437 Rue DE Verdun Verdun QC H4H 1K6",
    "addr:housenumber":"5437",
    "addr:postcode":"h4h 1k6",
    "addr:street":"Rue De Verdun",
    "iso:country":"CA",
    "sg:address":"5437 Rue DE Verdun",
    "sg:city":"Verdun",
    "sg:classifiers":[
        {
            "category":"Health Services",
            "subcategory":"Doctor",
            "type":"Services"
        }
    ],
    "sg:phone":"+1 514 768 1131",
    "sg:postcode":"H4H 1K6",
    "sg:province":"QC",
    "sg:tags":[
        "dentist"
    ],
    "wof:name":"Clinique Dentaire St-Onge",
    "wof:placetype":"venue"
},
  "geometry": {"coordinates":[-73.572456,45.452869],"type":"Point"}
}