{
  "type": "Feature",
  "properties": {
    "iso:country":"CA",
    "sg:city":"Pointe-Claire",
    "sg:classifiers":[
        {
            "category":"Wholesale",
            "subcategory":"Groceries",
            "type":"Manufacturing & Wholesale Goods"
        }
    ],
    "sg:phone":"+1 514 630 0900",
    "sg:postcode":"H9R 5M9",
    "sg:province":"QC",
    "sg:tags":[
        "salt"
    ],
    "wof:name":"Canadian Salt CO Ltd",
    "wof:placetype":"venue"
},
  "geometry": {"coordinates":[-73.8284,45.467186],"type":"Point"}
}