{
  "type": "Feature",
  "properties": {
    "iso:country":"CA",
    "sg:address":"70 Lewisville Rd",
    "sg:city":"Moncton",
    "sg:classifiers":[
        {
            "category":"Home & Garden",
            "subcategory":"Building Materials",
            "type":"Retail Goods"
        }
    ],
    "sg:phone":"+1 506 859 4433",
    "sg:postcode":"E1A 2K2",
    "sg:province":"NB",
    "sg:tags":[
        "plumbing",
        "fixture",
        "supply"
    ],
    "wof:name":"Mr Plumber",
    "wof:placetype":"venue"
},
  "geometry": {"coordinates":[-64.7733917236,46.1004981995],"type":"Point"}
}