{
  "type": "Feature",
  "properties": {
    "addr:full":"8 Main St W Kingsville ON N9Y 1H1",
    "addr:housenumber":"8",
    "addr:postcode":"n9y 1h1",
    "addr:street":"Main St W",
    "iso:country":"CA",
    "sg:address":"8 Main St W",
    "sg:city":"Kingsville",
    "sg:classifiers":[
        {
            "category":"Shopping",
            "subcategory":"Clothing, Apparel, & Fashions",
            "type":"Retail Goods"
        }
    ],
    "sg:phone":"+1 519 733 4317",
    "sg:postcode":"N9Y 1H1",
    "sg:province":"ON",
    "sg:tags":[
        "furnishing"
    ],
    "wof:name":"Towne Shoppe",
    "wof:placetype":"venue"
},
  "geometry": {"coordinates":[-82.740013,42.03801],"type":"Point"}
}