{
  "type": "Feature",
  "properties": {
    "iso:country":"CA",
    "sg:address":"82 Germain St",
    "sg:city":"Saint John",
    "sg:classifiers":[
        {
            "category":"Health Services",
            "subcategory":"Health Practitioner",
            "type":"Services"
        }
    ],
    "sg:phone":"+1 506 658 1162",
    "sg:postcode":"E2L 2E7",
    "sg:province":"NB",
    "sg:tags":[
        "psychologist"
    ],
    "wof:name":"Creary, Fred",
    "wof:placetype":"venue"
},
  "geometry": {"coordinates":[-66.06029510499999,45.2728691101],"type":"Point"}
}