{
  "type": "Feature",
  "properties": {
    "addr:full":"546 Rogers Rd York ON M6M 1B5",
    "addr:housenumber":"546",
    "addr:postcode":"m6m 1b5",
    "addr:street":"Rogers Rd",
    "iso:country":"CA",
    "sg:address":"546 Rogers Rd",
    "sg:city":"York",
    "sg:classifiers":[
        {
            "category":"Restaurant",
            "type":"Food & Drink"
        }
    ],
    "sg:phone":"+1 416 638 8835",
    "sg:postcode":"M6M 1B5",
    "sg:province":"ON",
    "wof:name":"Dehavilland Restaurant",
    "wof:placetype":"venue"
},
  "geometry": {"coordinates":[-79.469849,43.682365],"type":"Point"}
}