{
  "type": "Feature",
  "properties": {
    "iso:country":"CA",
    "sg:city":"Quebec",
    "sg:classifiers":[
        {
            "category":"Real Estate",
            "subcategory":"Real Estate Agent",
            "type":"Services"
        }
    ],
    "sg:phone":"+1 418 877 7777",
    "sg:postcode":"G1P 2J9",
    "sg:province":"QC",
    "sg:tags":[
        "appraiser"
    ],
    "wof:name":"Aubert Sylvain & Assoc Inc",
    "wof:placetype":"venue"
},
  "geometry": {"coordinates":[-71.32431,46.805756],"type":"Point"}
}