{
  "type": "Feature",
  "properties": {
    "iso:country":"CA",
    "sg:address":"1118 Rue Berlier",
    "sg:city":"Laval",
    "sg:classifiers":[
        {
            "category":"Professional",
            "subcategory":"Business Services",
            "type":"Services"
        }
    ],
    "sg:phone":"+1 450 663 2221",
    "sg:postcode":"H7L 3R9",
    "sg:province":"QC",
    "sg:tags":[
        "embroidery"
    ],
    "wof:name":"Royal Tech",
    "wof:placetype":"venue"
},
  "geometry": {"coordinates":[-73.741569519,45.5862312317],"type":"Point"}
}