{
  "type": "Feature",
  "properties": {
    "iso:country":"CA",
    "sg:address":"14 King William St",
    "sg:city":"Huntsville",
    "sg:classifiers":[
        {
            "category":"Restaurant",
            "type":"Food & Drink"
        }
    ],
    "sg:phone":"+1 705 789 9211",
    "sg:postcode":"P1H 1G5",
    "sg:province":"ON",
    "sg:tags":[
        "chicken",
        "dinner"
    ],
    "wof:name":"Kfc",
    "wof:placetype":"venue"
},
  "geometry": {"coordinates":[-79.2110748291,45.3299407959],"type":"Point"}
}