{
  "type": "Feature",
  "properties": {
    "addr:full":"609 Broughton St Victoria BC V8W 1C8",
    "addr:housenumber":"609",
    "addr:postcode":"v8w 1c8",
    "addr:street":"Broughton St",
    "iso:country":"CA",
    "sg:address":"609 Broughton St",
    "sg:city":"Victoria",
    "sg:classifiers":[
        {
            "category":"Government",
            "subcategory":"Office",
            "type":"Public Place"
        }
    ],
    "sg:phone":"+1 250 952 6246",
    "sg:postcode":"V8W 1C8",
    "sg:province":"BC",
    "wof:name":"B C Assets & Land Corp",
    "wof:placetype":"venue"
},
  "geometry": {"coordinates":[-123.367577,48.424011],"type":"Point"}
}