{
  "type": "Feature",
  "properties": {
    "iso:country":"CA",
    "sg:city":"Prince George",
    "sg:classifiers":[
        {
            "category":"Real Estate",
            "subcategory":"Real Estate Operator",
            "type":"Services"
        }
    ],
    "sg:phone":"+1 250 561 1446",
    "sg:postcode":"V2L 4X5",
    "sg:province":"BC",
    "sg:tags":[
        "apartment"
    ],
    "wof:name":"Venice Place",
    "wof:placetype":"venue"
},
  "geometry": {"coordinates":[-122.7420578,53.9115943909],"type":"Point"}
}