{
  "type": "Feature",
  "properties": {
    "addr:full":"3rd St & Main St Halkirk AB T0C 1M0",
    "addr:postcode":"t0c 1m0",
    "addr:street":"3Rd St & Main St",
    "iso:country":"CA",
    "sg:address":"3rd St & Main St",
    "sg:city":"Halkirk",
    "sg:classifiers":[
        {
            "category":"Mining & Drilling",
            "type":"Manufacturing & Wholesale Goods"
        }
    ],
    "sg:phone":"+1 403 884 2500",
    "sg:postcode":"T0C 1M0",
    "sg:province":"AB",
    "sg:tags":[
        "equipment",
        "field",
        "oil",
        "well",
        "supply"
    ],
    "wof:name":"Midfield Supply Ltd",
    "wof:placetype":"venue"
},
  "geometry": {"coordinates":[-112.153992,52.282417],"type":"Point"}
}