{
  "type": "Feature",
  "properties": {
    "addr:full":"2235 Kennedy Rd Scarborough ON M1T 3G8",
    "addr:housenumber":"2235",
    "addr:postcode":"m1t 3g8",
    "addr:street":"Kennedy Rd",
    "iso:country":"CA",
    "sg:address":"2235 Kennedy Rd",
    "sg:city":"Scarborough",
    "sg:classifiers":[
        {
            "category":"Health Services",
            "subcategory":"Doctor",
            "type":"Services"
        }
    ],
    "sg:phone":"+1 416 754 3937",
    "sg:postcode":"M1T 3G8",
    "sg:province":"ON",
    "sg:tags":[
        "physician",
        "surgeon"
    ],
    "wof:name":"Assya Management",
    "wof:placetype":"venue"
},
  "geometry": {"coordinates":[-79.28733800000001,43.781998],"type":"Point"}
}