{
  "type": "Feature",
  "properties": {
    "addr:full":"168 St Joseph St Notre Dame DE Lourdes MB R0G 1M0",
    "addr:housenumber":"168",
    "addr:postcode":"r0g 1m0",
    "addr:street":"St Joseph St",
    "iso:country":"CA",
    "sg:address":"168 St Joseph St",
    "sg:city":"Notre Dame DE Lourdes",
    "sg:classifiers":[
        {
            "category":"Retail",
            "subcategory":"Auto Repair",
            "type":"Services"
        }
    ],
    "sg:phone":"+1 204 248 2126",
    "sg:postcode":"R0G 1M0",
    "sg:province":"MB",
    "sg:tags":[
        "truck"
    ],
    "wof:name":"Gdt Parts & Svc",
    "wof:placetype":"venue"
},
  "geometry": {"coordinates":[-98.557503,49.532719],"type":"Point"}
}