{
  "type": "Feature",
  "properties": {
    "addr:full":"4004 26 St SE Calgary AB T2B 2Y4",
    "addr:housenumber":"4004",
    "addr:postcode":"t2b 2y4",
    "addr:street":"26 St Se",
    "iso:country":"CA",
    "sg:address":"4004 26 St SE",
    "sg:city":"Calgary",
    "sg:classifiers":[
        {
            "category":"Food & Beverages",
            "subcategory":"Groceries & Convenience Stores",
            "type":"Retail Goods"
        }
    ],
    "sg:phone":"+1 403 235 0009",
    "sg:postcode":"T2B 2Y4",
    "sg:province":"AB",
    "sg:tags":[
        "grocer"
    ],
    "wof:name":"Tucker's Food Store",
    "wof:placetype":"venue"
},
  "geometry": {"coordinates":[-113.998901367,51.0185394287],"type":"Point"}
}