{
  "type": "Feature",
  "properties": {
    "addr:full":"434 Hwy 36 Lindsay ON K9V 4R3",
    "addr:housenumber":"434",
    "addr:postcode":"k9v 4r3",
    "addr:street":"Hwy 36",
    "iso:country":"CA",
    "sg:address":"434 Hwy 36",
    "sg:city":"Lindsay",
    "sg:classifiers":[
        {
            "category":"Home & Garden",
            "subcategory":"Garden Supply",
            "type":"Retail Goods"
        }
    ],
    "sg:phone":"+1 705 324 2040",
    "sg:postcode":"K9V 4R3",
    "sg:province":"ON",
    "sg:tags":[
        "greenhouse",
        "center"
    ],
    "wof:name":"Cedarview Landscaping",
    "wof:placetype":"venue"
},
  "geometry": {"coordinates":[-78.72305299999999,44.369976],"type":"Point"}
}