{
  "type": "Feature",
  "properties": {
    "addr:full":"64 Deerhurst Rd Stoney Creek ON L8E 2E6",
    "addr:housenumber":"64",
    "addr:postcode":"l8e 2e6",
    "addr:street":"Deerhurst Rd",
    "iso:country":"CA",
    "sg:address":"64 Deerhurst Rd",
    "sg:city":"Stoney Creek",
    "sg:classifiers":[
        {
            "category":"Professional",
            "subcategory":"Engineering",
            "type":"Services"
        }
    ],
    "sg:phone":"+1 905 664 3143",
    "sg:postcode":"L8E 2E6",
    "sg:province":"ON",
    "sg:tags":[
        "engineer"
    ],
    "wof:name":"Deerhurst Engineering Ltd",
    "wof:placetype":"venue"
},
  "geometry": {"coordinates":[-79.72498299999999,43.223404],"type":"Point"}
}