{
  "type": "Feature",
  "properties": {
    "addr:full":"96 John St S Hamilton ON L8N 2C1",
    "addr:housenumber":"96",
    "addr:postcode":"l8n 2c1",
    "addr:street":"John St S",
    "iso:country":"CA",
    "sg:address":"96 John St S",
    "sg:city":"Hamilton",
    "sg:classifiers":[
        {
            "category":"Shopping",
            "subcategory":"Jewelry",
            "type":"Retail Goods"
        }
    ],
    "sg:phone":"+1 905 529 2488",
    "sg:postcode":"L8N 2C1",
    "sg:province":"ON",
    "sg:tags":[
        "jeweler"
    ],
    "wof:name":"24 Karat Jewellery Ltd",
    "wof:placetype":"venue"
},
  "geometry": {"coordinates":[-79.867859,43.253426],"type":"Point"}
}