{
  "type": "Feature",
  "properties": {
    "addr:full":"1400 Regent Ave W Winnipeg MB R2C 3A8",
    "addr:housenumber":"1400",
    "addr:postcode":"r2c 3a8",
    "addr:street":"Regent Ave W",
    "iso:country":"CA",
    "sg:address":"1400 Regent Ave W",
    "sg:city":"Winnipeg",
    "sg:classifiers":[
        {
            "category":"Autos & Motor Vehicles",
            "subcategory":"Fuel & Gas Station",
            "type":"Retail Goods"
        }
    ],
    "sg:phone":"+1 204 661 6838",
    "sg:postcode":"R2C 3A8",
    "sg:province":"MB",
    "sg:tags":[
        "oil"
    ],
    "wof:name":"Shell Canada Products Ltd",
    "wof:placetype":"venue"
},
  "geometry": {"coordinates":[-97.04248,49.895123],"type":"Point"}
}