{
  "type": "Feature",
  "properties": {
    "addr:full":"135 Rue Gamache Victoriaville QC G6P 3S8",
    "addr:housenumber":"135",
    "addr:postcode":"g6p 3s8",
    "addr:street":"Rue Gamache",
    "iso:country":"CA",
    "sg:address":"135 Rue Gamache",
    "sg:city":"Victoriaville",
    "sg:classifiers":[
        {
            "category":"Shopping",
            "subcategory":"Bicycles & Sporting Goods",
            "type":"Retail Goods"
        }
    ],
    "sg:phone":"+1 819 752 5325",
    "sg:postcode":"G6P 3S8",
    "sg:province":"QC",
    "wof:name":"Gagne Sarto",
    "wof:placetype":"venue"
},
  "geometry": {"coordinates":[-71.961113,46.052589],"type":"Point"}
}