{
  "type": "Feature",
  "properties": {
    "addr:full":"410 John St N Aylmer ON N5H 2B8",
    "addr:housenumber":"410",
    "addr:postcode":"n5h 2b8",
    "addr:street":"John St N",
    "iso:country":"CA",
    "sg:address":"410 John St N",
    "sg:city":"Aylmer",
    "sg:classifiers":[
        {
            "category":"Retail",
            "subcategory":"Auto Repair",
            "type":"Services"
        }
    ],
    "sg:phone":"+1 519 773 2077",
    "sg:postcode":"N5H 2B8",
    "sg:province":"ON",
    "sg:tags":[
        "wrecker"
    ],
    "wof:name":"Northside Towing",
    "wof:placetype":"venue"
},
  "geometry": {"coordinates":[-80.98297100000001,42.778976],"type":"Point"}
}