{
  "type": "Feature",
  "properties": {
    "addr:full":"519 22nd Ave Hanover ON N4N 3T6",
    "addr:housenumber":"519",
    "addr:postcode":"n4n 3t6",
    "addr:street":"22Nd Ave",
    "iso:country":"CA",
    "sg:address":"519 22nd Ave",
    "sg:city":"Hanover",
    "sg:classifiers":[
        {
            "category":"Wholesale",
            "subcategory":"Electrical",
            "type":"Manufacturing & Wholesale Goods"
        }
    ],
    "sg:phone":"+1 519 364 1878",
    "sg:postcode":"N4N 3T6",
    "sg:province":"ON",
    "sg:tags":[
        "circuit",
        "breakers"
    ],
    "wof:name":"Electrical Contacts Ltd",
    "wof:placetype":"venue"
},
  "geometry": {"coordinates":[-81.00942999999999,44.155476],"type":"Point"}
}