{
  "type": "Feature",
  "properties": {
    "addr:full":"Burks Falls ON P0A 1C0",
    "addr:postcode":"p0a 1c0",
    "addr:street":"Burks",
    "iso:country":"CA",
    "sg:city":"Burks Falls",
    "sg:classifiers":[
        {
            "category":"Building & Trades",
            "subcategory":"Construction",
            "type":"Services"
        }
    ],
    "sg:phone":"+1 705 382 2132",
    "sg:postcode":"P0A 1C0",
    "sg:province":"ON",
    "sg:tags":[
        "contractor"
    ],
    "wof:name":"J Moffit Construction Ltd",
    "wof:placetype":"venue"
},
  "geometry": {"coordinates":[-79.41059875489999,45.6194953918],"type":"Point"}
}