{
  "type": "Feature",
  "properties": {
    "addr:full":"Toronto ON M4S 1Z4",
    "addr:postcode":"m4s 1z4",
    "iso:country":"CA",
    "sg:city":"Toronto",
    "sg:classifiers":[
        {
            "category":"Personal",
            "subcategory":"Beauty Salon",
            "type":"Services"
        }
    ],
    "sg:phone":"+1 416 489 9313",
    "sg:postcode":"M4S 1Z4",
    "sg:province":"ON",
    "sg:tags":[
        "electrolysis"
    ],
    "wof:name":"Aesthetics By Christine",
    "wof:placetype":"venue"
},
  "geometry": {"coordinates":[-79.39701100000001,43.699444],"type":"Point"}
}