{
  "type": "Feature",
  "properties": {
    "iso:country":"CA",
    "sg:address":"5 Kitchener St",
    "sg:city":"Stewiacke",
    "sg:classifiers":[
        {
            "category":"Education",
            "subcategory":"School",
            "type":"Public Place"
        }
    ],
    "sg:phone":"+1 902 639 3100",
    "sg:postcode":"B0N 2J0",
    "sg:province":"NS",
    "wof:name":"Stewiacke Elementary School",
    "wof:placetype":"venue"
},
  "geometry": {"coordinates":[-63.3344230652,45.1349906921],"type":"Point"}
}