{
  "type": "Feature",
  "properties": {
    "iso:country":"CA",
    "sg:city":"Richmond",
    "sg:classifiers":[
        {
            "category":"Restaurant",
            "type":"Food & Drink"
        }
    ],
    "sg:phone":"+1 604 270 7325",
    "sg:postcode":"V6V 1Z4",
    "sg:province":"BC",
    "wof:name":"Bathgate Cafe",
    "wof:placetype":"venue"
},
  "geometry": {"coordinates":[-123.08190918,49.1890144348],"type":"Point"}
}