{
  "type": "Feature",
  "properties": {
    "addr:full":"Sainte-Sophie QC J5J 2S8",
    "addr:postcode":"j5j 2s8",
    "iso:country":"CA",
    "sg:city":"Sainte-Sophie",
    "sg:classifiers":[
        {
            "category":"Home & Garden",
            "subcategory":"Furniture",
            "type":"Retail Goods"
        }
    ],
    "sg:phone":"+1 450 438 8092",
    "sg:postcode":"J5J 2S8",
    "sg:province":"QC",
    "sg:tags":[
        "equipment",
        "kitchen",
        "cabinet"
    ],
    "wof:name":"Roger Cuisines Enr",
    "wof:placetype":"venue"
},
  "geometry": {"coordinates":[-73.98743399999999,45.845318],"type":"Point"}
}