{
  "type": "Feature",
  "properties": {
    "addr:full":"602 Main St Melville SK S0A 2P0",
    "addr:housenumber":"602",
    "addr:postcode":"s0a 2p0",
    "addr:street":"Main St",
    "iso:country":"CA",
    "sg:address":"602 Main St",
    "sg:city":"Melville",
    "sg:classifiers":[
        {
            "category":"Organizations",
            "subcategory":"Religious Organization",
            "type":"Services"
        }
    ],
    "sg:phone":"+1 306 728 5764",
    "sg:postcode":"S0A 2P0",
    "sg:province":"SK",
    "sg:tags":[
        "church"
    ],
    "wof:name":"All Saints Anglican Church",
    "wof:placetype":"venue"
},
  "geometry": {"coordinates":[-102.818237305,50.9316902161],"type":"Point"}
}