{
  "type": "Feature",
  "properties": {
    "addr:full":"137 Brock St Barrie ON L4N 2M3",
    "addr:housenumber":"137",
    "addr:postcode":"l4n 2m3",
    "addr:street":"Brock St",
    "iso:country":"CA",
    "sg:address":"137 Brock St",
    "sg:city":"Barrie",
    "sg:classifiers":[
        {
            "category":"Taxi",
            "type":"Transportation"
        }
    ],
    "sg:phone":"+1 705 835 3650",
    "sg:postcode":"L4N 2M3",
    "sg:province":"ON",
    "sg:tags":[
        "taxicab",
        "airport"
    ],
    "wof:name":"Simcoe County Airports Svc",
    "wof:placetype":"venue"
},
  "geometry": {"coordinates":[-79.70214799999999,44.373409],"type":"Point"}
}