{
  "type": "Feature",
  "properties": {
    "addr:full":"111 Rte Campagna Saint-Henri-DE-Levis QC G0R 3E0",
    "addr:housenumber":"111",
    "addr:postcode":"g0r 3e0",
    "addr:street":"Rte Campagna Saint-Henri-De-Levis",
    "iso:country":"CA",
    "sg:address":"111 Rte Campagna",
    "sg:city":"Saint-Henri-DE-Levis",
    "sg:classifiers":[
        {
            "category":"Personal",
            "subcategory":"Beauty Salon",
            "type":"Services"
        }
    ],
    "sg:phone":"+1 418 882 0282",
    "sg:postcode":"G0R 3E0",
    "sg:province":"QC",
    "wof:name":"Salon Lucia Enr",
    "wof:placetype":"venue"
},
  "geometry": {"coordinates":[-71.176940918,46.80286026],"type":"Point"}
}