{
  "type": "Feature",
  "properties": {
    "addr:full":"Yorkton SK S3N 0M4",
    "addr:postcode":"s3n 0m4",
    "iso:country":"CA",
    "sg:city":"Yorkton",
    "sg:classifiers":[
        {
            "category":"Banks & Credit Unions",
            "subcategory":"Bank",
            "type":"Services"
        }
    ],
    "sg:phone":"+1 306 782 2218",
    "sg:postcode":"S3N 0M4",
    "sg:province":"SK",
    "sg:tags":[
        "loan",
        "real estate"
    ],
    "wof:name":"Citi Financial",
    "wof:placetype":"venue"
},
  "geometry": {"coordinates":[-102.470611572,51.2099456787],"type":"Point"}
}