{
  "type": "Feature",
  "properties": {
    "addr:full":"Beauharnois QC J6N 3P7",
    "addr:postcode":"j6n 3p7",
    "iso:country":"CA",
    "sg:city":"Beauharnois",
    "sg:classifiers":[
        {
            "category":"Social Services",
            "type":"Services"
        }
    ],
    "sg:phone":"+1 450 429 4442",
    "sg:postcode":"J6N 3P7",
    "sg:province":"QC",
    "sg:tags":[
        "organization",
        "welfare"
    ],
    "wof:name":"Regroupement Des Handicapes",
    "wof:placetype":"venue"
},
  "geometry": {"coordinates":[-73.877129,45.313618],"type":"Point"}
}