{
  "type": "Feature",
  "properties": {
    "addr:full":"6 Place DE Broussey Lorraine QC J6Z 4L7",
    "addr:housenumber":"6",
    "addr:postcode":"j6z 4l7",
    "addr:street":"Place De Broussey",
    "iso:country":"CA",
    "sg:address":"6 Place DE Broussey",
    "sg:city":"Lorraine",
    "sg:classifiers":[
        {
            "category":"Professional",
            "subcategory":"Business Services",
            "type":"Services"
        }
    ],
    "sg:phone":"+1 450 621 2743",
    "sg:postcode":"J6Z 4L7",
    "sg:province":"QC",
    "sg:tags":[
        "translator",
        "interpreter"
    ],
    "wof:name":"Communication Cinq Sur Cinq",
    "wof:placetype":"venue"
},
  "geometry": {"coordinates":[-73.77712200000001,45.672459],"type":"Point"}
}