{
  "type": "Feature",
  "properties": {
    "addr:full":"Mine Centre ON P0W 1H0",
    "addr:postcode":"p0w 1h0",
    "iso:country":"CA",
    "sg:city":"Mine Centre",
    "sg:classifiers":[
        {
            "category":"Education",
            "subcategory":"School",
            "type":"Public Place"
        }
    ],
    "sg:phone":"+1 807 599 2870",
    "sg:postcode":"P0W 1H0",
    "sg:province":"ON",
    "sg:tags":[
        "academic",
        "special"
    ],
    "wof:name":"Seine River Comm Learning Ctr",
    "wof:placetype":"venue"
},
  "geometry": {"coordinates":[-92.64061,48.760941],"type":"Point"}
}