{
  "type": "Feature",
  "properties": {
    "addr:full":"Alban ON P0M 1A0",
    "addr:postcode":"p0m 1a0",
    "iso:country":"CA",
    "sg:city":"Alban",
    "sg:classifiers":[
        {
            "category":"Travel",
            "subcategory":"Campground",
            "type":"Entertainment"
        }
    ],
    "sg:phone":"+1 705 857 2203",
    "sg:postcode":"P0M 1A0",
    "sg:province":"ON",
    "sg:tags":[
        "camp",
        "fishing"
    ],
    "wof:name":"Kagamaga Lodge",
    "wof:placetype":"venue"
},
  "geometry": {"coordinates":[-80.6227111816,46.1047058105],"type":"Point"}
}