{
  "type": "Feature",
  "properties": {
    "addr:full":"383 Rathburn Rd Etobicoke ON M9B 2M2",
    "addr:housenumber":"383",
    "addr:postcode":"m9b 2m2",
    "addr:street":"Rathburn Rd",
    "iso:country":"CA",
    "sg:address":"383 Rathburn Rd",
    "sg:city":"Etobicoke",
    "sg:classifiers":[
        {
            "category":"Health Services",
            "subcategory":"Doctor",
            "type":"Services"
        }
    ],
    "sg:phone":"+1 416 621 0352",
    "sg:postcode":"M9B 2M2",
    "sg:province":"ON",
    "sg:tags":[
        "dentist"
    ],
    "wof:name":"Szawlowski, Elizabeth DDS",
    "wof:placetype":"venue"
},
  "geometry": {"coordinates":[-79.56287399999999,43.655132],"type":"Point"}
}