{
  "type": "Feature",
  "properties": {
    "addr:full":"230 Chestnut St Dunnville ON N1A 2H1",
    "addr:housenumber":"230",
    "addr:postcode":"n1a 2h1",
    "addr:street":"Chestnut St",
    "iso:country":"CA",
    "sg:address":"230 Chestnut St",
    "sg:city":"Dunnville",
    "sg:classifiers":[
        {
            "category":"Social Services",
            "type":"Services"
        }
    ],
    "sg:phone":"+1 905 774 4251",
    "sg:postcode":"N1A 2H1",
    "sg:province":"ON",
    "sg:tags":[
        "organization",
        "welfare"
    ],
    "wof:name":"Salvation Army Social Svc",
    "wof:placetype":"venue"
},
  "geometry": {"coordinates":[-79.61721799999999,42.902817],"type":"Point"}
}