{
  "type": "Feature",
  "properties": {
    "addr:full":"2675 Portage Ave Winnipeg MB R3J 0P9",
    "addr:housenumber":"2675",
    "addr:postcode":"r3j 0p9",
    "addr:street":"Portage Ave",
    "iso:country":"CA",
    "sg:address":"2675 Portage Ave",
    "sg:city":"Winnipeg",
    "sg:classifiers":[
        {
            "category":"Restaurant",
            "type":"Food & Drink"
        }
    ],
    "sg:phone":"+1 204 895 4565",
    "sg:postcode":"R3J 0P9",
    "sg:province":"MB",
    "wof:name":"Perkins Restaurant & Bakery",
    "wof:placetype":"venue"
},
  "geometry": {"coordinates":[-97.27104199999999,49.877785],"type":"Point"}
}