{
  "type": "Feature",
  "properties": {
    "addr:full":"1190 Wallace Ave N Listowel ON N4W 1M5",
    "addr:housenumber":"1190",
    "addr:postcode":"n4w 1m5",
    "addr:street":"Wallace Ave N",
    "iso:country":"CA",
    "sg:address":"1190 Wallace Ave N",
    "sg:city":"Listowel",
    "sg:classifiers":[
        {
            "category":"Shopping",
            "subcategory":"Florist",
            "type":"Retail Goods"
        }
    ],
    "sg:phone":"+1 519 291 3032",
    "sg:postcode":"N4W 1M5",
    "sg:province":"ON",
    "wof:name":"Petalessence",
    "wof:placetype":"venue"
},
  "geometry": {"coordinates":[-80.9451675415,43.741394043],"type":"Point"}
}