{
  "type": "Feature",
  "properties": {
    "addr:full":"1722 Fielding St Sudbury ON P3A 1P1",
    "addr:housenumber":"1722",
    "addr:postcode":"p3a 1p1",
    "addr:street":"Fielding St",
    "iso:country":"CA",
    "sg:address":"1722 Fielding St",
    "sg:city":"Sudbury",
    "sg:classifiers":[
        {
            "category":"Education",
            "subcategory":"School",
            "type":"Public Place"
        }
    ],
    "sg:phone":"+1 705 566 5130",
    "sg:postcode":"P3A 1P1",
    "sg:province":"ON",
    "wof:name":"Churchill Public School",
    "wof:placetype":"venue"
},
  "geometry": {"coordinates":[-80.93409,46.518238],"type":"Point"}
}