{
  "type": "Feature",
  "properties": {
    "addr:full":"Waterdown ON L0R 2H0",
    "addr:postcode":"l0r 2h0",
    "iso:country":"CA",
    "sg:city":"Waterdown",
    "sg:classifiers":[
        {
            "category":"Health Services",
            "subcategory":"Doctor",
            "type":"Services"
        }
    ],
    "sg:phone":"+1 905 689 6134",
    "sg:postcode":"L0R 2H0",
    "sg:province":"ON",
    "sg:tags":[
        "physician",
        "surgeon"
    ],
    "wof:name":"Cross, Randolph MD",
    "wof:placetype":"venue"
},
  "geometry": {"coordinates":[-79.9010314941,43.3347358704],"type":"Point"}
}