{
  "type": "Feature",
  "properties": {
    "addr:full":"Cambridge ON N1S 5A5",
    "addr:postcode":"n1s 5a5",
    "iso:country":"CA",
    "sg:city":"Cambridge",
    "sg:classifiers":[
        {
            "category":"Shopping",
            "subcategory":"Catalog Store",
            "type":"Retail Goods"
        }
    ],
    "sg:phone":"+1 519 622 5130",
    "sg:postcode":"N1S 5A5",
    "sg:province":"ON",
    "sg:tags":[
        "mail",
        "order",
        "internet"
    ],
    "wof:name":"Sears Canada Inc",
    "wof:placetype":"venue"
},
  "geometry": {"coordinates":[-80.32828499999999,43.351799],"type":"Point"}
}