{
  "type": "Feature",
  "properties": {
    "addr:full":"2576 7th Ave W Vancouver BC V6K 1Y9",
    "addr:housenumber":"2576",
    "addr:postcode":"v6k 1y9",
    "addr:street":"7Th Ave W",
    "iso:country":"CA",
    "sg:address":"2576 7th Ave W",
    "sg:city":"Vancouver",
    "sg:classifiers":[
        {
            "category":"Professional",
            "subcategory":"Research",
            "type":"Services"
        }
    ],
    "sg:phone":"+1 604 731 2697",
    "sg:postcode":"V6K 1Y9",
    "sg:province":"BC",
    "sg:tags":[
        "environmental",
        "ecological"
    ],
    "wof:name":"Robert Hornal & Assoc Ltd",
    "wof:placetype":"venue"
},
  "geometry": {"coordinates":[-123.16381800000001,49.265675],"type":"Point"}
}