{
  "type": "Feature",
  "properties": {
    "addr:full":"21443 Township Road 550 Fort Saskatchewan AB T8L 4B9",
    "addr:housenumber":"21443",
    "addr:postcode":"t8l 4b9",
    "addr:street":"Township Road 550",
    "iso:country":"CA",
    "sg:address":"21443 Township Road 550",
    "sg:city":"Fort Saskatchewan",
    "sg:classifiers":[
        {
            "category":"Building & Trades",
            "subcategory":"Construction",
            "type":"Services"
        }
    ],
    "sg:phone":"+1 780 998 2491",
    "sg:postcode":"T8L 4B9",
    "sg:province":"AB",
    "sg:tags":[
        "roofing",
        "contractor"
    ],
    "wof:name":"Rivard Roofing Ltd",
    "wof:placetype":"venue"
},
  "geometry": {"coordinates":[-113.173447,53.715221],"type":"Point"}
}