{
  "type": "Feature",
  "properties": {
    "addr:full":"777 Lawrence Ave E North York ON M3C 1P2",
    "addr:housenumber":"777",
    "addr:postcode":"m3c 1p2",
    "addr:street":"Lawrence Ave E",
    "iso:country":"CA",
    "sg:address":"777 Lawrence Ave E",
    "sg:city":"North York",
    "sg:classifiers":[
        {
            "category":"Government",
            "subcategory":"Office",
            "type":"Public Place"
        }
    ],
    "sg:phone":"+1 416 392 8186",
    "sg:postcode":"M3C 1P2",
    "sg:province":"ON",
    "sg:tags":[
        "village"
    ],
    "wof:name":"Edwards Gardens & Conserv",
    "wof:placetype":"venue"
},
  "geometry": {"coordinates":[-79.357834,43.734524],"type":"Point"}
}