{
  "type": "Feature",
  "properties": {
    "iso:country":"CA",
    "sg:address":"251 Queen St E",
    "sg:city":"Brampton",
    "sg:classifiers":[
        {
            "category":"Retail",
            "subcategory":"Auto Repair",
            "type":"Services"
        }
    ],
    "sg:phone":"+1 905 459 7822",
    "sg:postcode":"L6W 2B8",
    "sg:province":"ON",
    "sg:tags":[
        "repairing",
        "automobile"
    ],
    "wof:name":"Speedy Auto Svc",
    "wof:placetype":"venue"
},
  "geometry": {"coordinates":[-79.7449264526,43.6994552612],"type":"Point"}
}