{
  "type": "Feature",
  "properties": {
    "addr:full":"Balcarres SK S0G 0C0",
    "addr:postcode":"s0g 0c0",
    "addr:street":"Balcarres",
    "iso:country":"CA",
    "sg:city":"Balcarres",
    "sg:classifiers":[
        {
            "category":"Organizations",
            "subcategory":"Religious Organization",
            "type":"Services"
        }
    ],
    "sg:phone":"+1 306 334 2784",
    "sg:postcode":"S0G 0C0",
    "sg:province":"SK",
    "sg:tags":[
        "church"
    ],
    "wof:name":"Holy Faith Anglican Church",
    "wof:placetype":"venue"
},
  "geometry": {"coordinates":[-103.547821,50.798161],"type":"Point"}
}