{
  "type": "Feature",
  "properties": {
    "addr:full":"Scarborough ON M1V 5J4",
    "addr:postcode":"m1v 5j4",
    "iso:country":"CA",
    "sg:city":"Scarborough",
    "sg:classifiers":[
        {
            "category":"Building & Trades",
            "subcategory":"Construction",
            "type":"Services"
        }
    ],
    "sg:phone":"+1 416 332 8394",
    "sg:postcode":"M1V 5J4",
    "sg:province":"ON",
    "sg:tags":[
        "equipment",
        "rooms",
        "clean"
    ],
    "wof:name":"Perotech Sciences Inc",
    "wof:placetype":"venue"
},
  "geometry": {"coordinates":[-79.2660751343,43.8295516968],"type":"Point"}
}