{
  "type": "Feature",
  "properties": {
    "iso:country":"CA",
    "sg:address":"185 Echo Ridge Rd",
    "sg:city":"Kearney",
    "sg:classifiers":[
        {
            "category":"Building & Trades",
            "subcategory":"Construction",
            "type":"Services"
        }
    ],
    "sg:phone":"+1 705 636 5317",
    "sg:postcode":"P0A 1M0",
    "sg:province":"ON",
    "sg:tags":[
        "masonry",
        "fireplace",
        "cleaning",
        "chimney",
        "contractor"
    ],
    "wof:name":"Diernegger Construction",
    "wof:placetype":"venue"
},
  "geometry": {"coordinates":[-79.1931838989,45.557762146],"type":"Point"}
}