{
  "type": "Feature",
  "properties": {
    "addr:full":"581 Rue Martin Nicolet QC J3T 1C7",
    "addr:housenumber":"581",
    "addr:postcode":"j3t 1c7",
    "addr:street":"Rue Martin",
    "iso:country":"CA",
    "sg:address":"581 Rue Martin",
    "sg:city":"Nicolet",
    "sg:classifiers":[
        {
            "category":"Manufacturing",
            "subcategory":"Printing",
            "type":"Manufacturing & Wholesale Goods"
        }
    ],
    "sg:phone":"+1 819 293 4541",
    "sg:postcode":"J3T 1C7",
    "sg:province":"QC",
    "sg:tags":[
        "printer"
    ],
    "wof:name":"Imprimerie DE LA Rive Sud Ltee",
    "wof:placetype":"venue"
},
  "geometry": {"coordinates":[-72.610855,46.228409],"type":"Point"}
}