{
  "type": "Feature",
  "properties": {
    "addr:full":"9 Rue Du Pre Natashquan QC G0G 2E0",
    "addr:housenumber":"9",
    "addr:postcode":"g0g 2e0",
    "addr:street":"Rue Du Pre",
    "iso:country":"CA",
    "sg:address":"9 Rue Du Pre",
    "sg:city":"Natashquan",
    "sg:classifiers":[
        {
            "category":"Restaurant",
            "type":"Food & Drink"
        }
    ],
    "sg:phone":"+1 418 726 3333",
    "sg:postcode":"G0G 2E0",
    "sg:province":"QC",
    "wof:name":"John Debardeur",
    "wof:placetype":"venue"
},
  "geometry": {"coordinates":[-61.825405,50.188457],"type":"Point"}
}