{
  "type": "Feature",
  "properties": {
    "addr:full":"1400 Mission Rd Vernon BC V1T 9C3",
    "addr:housenumber":"1400",
    "addr:postcode":"v1t 9c3",
    "addr:street":"Mission Rd",
    "iso:country":"CA",
    "sg:address":"1400 Mission Rd",
    "sg:city":"Vernon",
    "sg:classifiers":[
        {
            "category":"Government",
            "subcategory":"Office",
            "type":"Public Place"
        }
    ],
    "sg:phone":"+1 250 545 9167",
    "sg:postcode":"V1T 9C3",
    "sg:province":"BC",
    "wof:name":"Noric House",
    "wof:placetype":"venue"
},
  "geometry": {"coordinates":[-119.279808,50.252014],"type":"Point"}
}