{
  "type": "Feature",
  "properties": {
    "addr:full":"3513 Lake Shore Blvd W Etobicoke ON M8W 1N5",
    "addr:housenumber":"3513",
    "addr:postcode":"m8w 1n5",
    "addr:street":"Lake Shore Blvd W",
    "iso:country":"CA",
    "sg:address":"3513 Lake Shore Blvd W",
    "sg:city":"Etobicoke",
    "sg:classifiers":[
        {
            "category":"Shopping",
            "subcategory":"Used Merchandise",
            "type":"Retail Goods"
        }
    ],
    "sg:phone":"+1 416 251 3637",
    "sg:postcode":"M8W 1N5",
    "sg:province":"ON",
    "sg:tags":[
        "second",
        "hand",
        "store",
        "furniture"
    ],
    "wof:name":"Long Branch Furn & Appliances",
    "wof:placetype":"venue"
},
  "geometry": {"coordinates":[-79.531586,43.594795],"type":"Point"}
}