{
  "type": "Feature",
  "properties": {
    "addr:full":"45 Overlea Blvd # 117 Toronto ON M4H 1C3",
    "addr:housenumber":"45",
    "addr:postcode":"m4h 1c3",
    "addr:street":"Overlea Blvd # 117",
    "iso:country":"CA",
    "sg:address":"45 Overlea Blvd # 117",
    "sg:city":"Toronto",
    "sg:classifiers":[
        {
            "category":"Shopping",
            "subcategory":"Clothing, Apparel, & Fashions",
            "type":"Retail Goods"
        }
    ],
    "sg:phone":"+1 416 424 4654",
    "sg:postcode":"M4H 1C3",
    "sg:province":"ON",
    "wof:name":"Lebaas 4 All",
    "wof:placetype":"venue"
},
  "geometry": {"coordinates":[-79.349304,43.705124],"type":"Point"}
}