{
  "type": "Feature",
  "properties": {
    "iso:country":"CA",
    "sg:address":"12811 157 Ave NW",
    "sg:city":"Edmonton",
    "sg:classifiers":[
        {
            "category":"Retail",
            "subcategory":"Auto Repair",
            "type":"Services"
        }
    ],
    "sg:phone":"+1 780 990 7306",
    "sg:postcode":"T6V 1A9",
    "sg:province":"AB",
    "sg:tags":[
        "wrecker"
    ],
    "wof:name":"Mister H Towing",
    "wof:placetype":"venue"
},
  "geometry": {"coordinates":[-113.542495727,53.6191253662],"type":"Point"}
}