{
  "type": "Feature",
  "properties": {
    "addr:full":"Edmonton AB T5Y 2B6",
    "addr:postcode":"t5y 2b6",
    "iso:country":"CA",
    "sg:city":"Edmonton",
    "sg:classifiers":[
        {
            "category":"Health Services",
            "subcategory":"Doctor",
            "type":"Services"
        }
    ],
    "sg:phone":"+1 780 473 4417",
    "sg:postcode":"T5Y 2B6",
    "sg:province":"AB",
    "sg:tags":[
        "physician",
        "surgeon"
    ],
    "wof:name":"Ng, David MD",
    "wof:placetype":"venue"
},
  "geometry": {"coordinates":[-113.384827,53.604557],"type":"Point"}
}