{
  "type": "Feature",
  "properties": {
    "addr:full":"1701 Rue Perrot Notre-Dame-DE-L'Ile-Perrot QC J7V 7P2",
    "addr:housenumber":"1701",
    "addr:postcode":"j7v 7p2",
    "addr:street":"Rue Perrot Notre-Dame-De-L'Ile-Perrot",
    "iso:country":"CA",
    "sg:address":"1701 Rue Perrot",
    "sg:city":"Notre-Dame-DE-L'Ile-Perrot",
    "sg:classifiers":[
        {
            "category":"Shopping",
            "type":"Retail Goods"
        }
    ],
    "sg:phone":"+1 514 453 8913",
    "sg:postcode":"J7V 7P2",
    "sg:province":"QC",
    "sg:tags":[
        "water",
        "heater"
    ],
    "wof:name":"Petroles Charbonneau Inc",
    "wof:placetype":"venue"
},
  "geometry": {"coordinates":[-73.955368042,45.3937644958],"type":"Point"}
}