{
  "type": "Feature",
  "properties": {
    "addr:full":"Hope BC V0X 1L0",
    "addr:postcode":"v0x 1l0",
    "iso:country":"CA",
    "sg:city":"Hope",
    "sg:classifiers":[
        {
            "category":"Government",
            "subcategory":"Office",
            "type":"Public Place"
        }
    ],
    "sg:phone":"+1 604 869 9330",
    "sg:postcode":"V0X 1L0",
    "sg:province":"BC",
    "wof:name":"BC Weigh Scales",
    "wof:placetype":"venue"
},
  "geometry": {"coordinates":[-121.44452699999999,49.378937],"type":"Point"}
}