{
  "type": "Feature",
  "properties": {
    "addr:full":"Etobicoke ON M8Y 1K4",
    "addr:postcode":"m8y 1k4",
    "iso:country":"CA",
    "sg:city":"Etobicoke",
    "sg:classifiers":[
        {
            "category":"Personal",
            "subcategory":"Beauty Salon",
            "type":"Services"
        }
    ],
    "sg:phone":"+1 416 201 8571",
    "sg:postcode":"M8Y 1K4",
    "sg:province":"ON",
    "wof:name":"Salon Charm",
    "wof:placetype":"venue"
},
  "geometry": {"coordinates":[-79.496002,43.627682],"type":"Point"}
}