{
  "type": "Feature",
  "properties": {
    "addr:full":"Fox Valley SK S0N 0V0",
    "addr:postcode":"s0n 0v0",
    "addr:street":"Fox Valley",
    "iso:country":"CA",
    "sg:city":"Fox Valley",
    "sg:classifiers":[
        {
            "category":"Travel",
            "subcategory":"Hotels & Motels",
            "type":"Entertainment"
        }
    ],
    "sg:phone":"+1 306 666 2040",
    "sg:postcode":"S0N 0V0",
    "sg:province":"SK",
    "wof:name":"Fox Den Motel Ltd",
    "wof:placetype":"venue"
},
  "geometry": {"coordinates":[-109.486931,50.463875],"type":"Point"}
}