{
  "type": "Feature",
  "properties": {
    "addr:full":"1645 Boul Mercure Drummondville QC J2B 3N2",
    "addr:housenumber":"1645",
    "addr:postcode":"j2b 3n2",
    "addr:street":"Boul Mercure",
    "iso:country":"CA",
    "sg:address":"1645 Boul Mercure",
    "sg:city":"Drummondville",
    "sg:classifiers":[
        {
            "category":"Retail",
            "subcategory":"Auto Repair",
            "type":"Services"
        }
    ],
    "sg:phone":"+1 819 472 6319",
    "sg:postcode":"J2B 3N2",
    "sg:province":"QC",
    "sg:tags":[
        "body",
        "automobile",
        "painting"
    ],
    "wof:name":"Garage Blanchard 2000",
    "wof:placetype":"venue"
},
  "geometry": {"coordinates":[-72.466438,45.861622],"type":"Point"}
}