{
  "type": "Feature",
  "properties": {
    "addr:full":"1421 Larkin Rd Merville BC V0R 2M0",
    "addr:housenumber":"1421",
    "addr:postcode":"v0r 2m0",
    "addr:street":"Larkin Rd",
    "iso:country":"CA",
    "sg:address":"1421 Larkin Rd",
    "sg:city":"Merville",
    "sg:classifiers":[
        {
            "category":"Home & Garden",
            "subcategory":"Carpets & Floor Coverings",
            "type":"Retail Goods"
        }
    ],
    "sg:phone":"+1 250 337 8075",
    "sg:postcode":"V0R 2M0",
    "sg:province":"BC",
    "wof:name":"Greenforrest Products Ltd",
    "wof:placetype":"venue"
},
  "geometry": {"coordinates":[-125.052230835,49.7814064026],"type":"Point"}
}