{
  "type": "Feature",
  "properties": {
    "addr:full":"1443 Rue Lambert-Closse Montreal QC H3H 1Z5",
    "addr:housenumber":"1443",
    "addr:postcode":"h3h 1z5",
    "addr:street":"Rue Lambert-Closse",
    "iso:country":"CA",
    "sg:address":"1443 Rue Lambert-Closse",
    "sg:city":"Montreal",
    "sg:classifiers":[
        {
            "category":"Health Services",
            "subcategory":"Health Practitioner",
            "type":"Services"
        }
    ],
    "sg:phone":"+1 514 939 1444",
    "sg:postcode":"H3H 1Z5",
    "sg:province":"QC",
    "sg:tags":[
        "physiotherapist"
    ],
    "wof:name":"Action Sport Physiotherapy",
    "wof:placetype":"venue"
},
  "geometry": {"coordinates":[-73.584076,45.490582],"type":"Point"}
}