{
  "type": "Feature",
  "properties": {
    "iso:country":"CA",
    "sg:address":"16 Midlake Blvd SE",
    "sg:city":"Calgary",
    "sg:classifiers":[
        {
            "category":"Wholesale",
            "subcategory":"Jewelry",
            "type":"Manufacturing & Wholesale Goods"
        }
    ],
    "sg:phone":"+1 403 254 6050",
    "sg:postcode":"T2X 2X7",
    "sg:province":"AB",
    "sg:tags":[
        "jeweler"
    ],
    "wof:name":"Alberta Jewelry Claims",
    "wof:placetype":"venue"
},
  "geometry": {"coordinates":[-114.06312561,50.9147071838],"type":"Point"}
}