{
  "type": "Feature",
  "properties": {
    "addr:full":"Christina Lake BC V0H 1E2",
    "addr:postcode":"bc v0h 1e2",
    "iso:country":"CA",
    "sg:city":"Christina Lake",
    "sg:classifiers":[
        {
            "category":"Travel",
            "subcategory":"Hotels & Motels",
            "type":"Entertainment"
        }
    ],
    "sg:phone":"+1 250 447 9312",
    "sg:postcode":"V0H 1E2",
    "sg:province":"BC",
    "wof:name":"New Horizon Motel",
    "wof:placetype":"venue"
},
  "geometry": {"coordinates":[-118.213295,49.056713],"type":"Point"}
}