{
  "type": "Feature",
  "properties": {
    "addr:full":"89 Mcintosh St Lac Du Bonnet MB R0E 1A0",
    "addr:housenumber":"89",
    "addr:postcode":"r0e 1a0",
    "addr:street":"Mcintosh St",
    "iso:country":"CA",
    "sg:address":"89 Mcintosh St",
    "sg:city":"Lac Du Bonnet",
    "sg:classifiers":[
        {
            "category":"Health Services",
            "subcategory":"Doctor",
            "type":"Services"
        }
    ],
    "sg:phone":"+1 204 345 8173",
    "sg:postcode":"R0E 1A0",
    "sg:province":"MB",
    "sg:tags":[
        "physician",
        "surgeon"
    ],
    "wof:name":"Van Gent, R MD",
    "wof:placetype":"venue"
},
  "geometry": {"coordinates":[-96.061966,50.251637],"type":"Point"}
}