{
  "type": "Feature",
  "properties": {
    "addr:full":"Marathon Lease Provost AB T0B 3S0",
    "addr:postcode":"t0b 3s0",
    "iso:country":"CA",
    "sg:address":"Marathon Lease",
    "sg:city":"Provost",
    "sg:classifiers":[
        {
            "category":"Manufacturing",
            "subcategory":"Chemicals & Compounds",
            "type":"Manufacturing & Wholesale Goods"
        }
    ],
    "sg:phone":"+1 780 753 2812",
    "sg:postcode":"T0B 3S0",
    "sg:province":"AB",
    "sg:tags":[
        "fertilizer"
    ],
    "wof:name":"West-Chem Agra Svc Ltd",
    "wof:placetype":"venue"
},
  "geometry": {"coordinates":[-110.268295288,52.3611373901],"type":"Point"}
}