{
  "type": "Feature",
  "properties": {
    "iso:country":"CA",
    "sg:city":"Montreal",
    "sg:classifiers":[
        {
            "category":"Health Services",
            "subcategory":"Doctor",
            "type":"Services"
        }
    ],
    "sg:phone":"+1 514 731 7600",
    "sg:postcode":"H3W 1R4",
    "sg:province":"QC",
    "sg:tags":[
        "dentist"
    ],
    "wof:name":"Francuz, P DDS",
    "wof:placetype":"venue"
},
  "geometry": {"coordinates":[-73.62757873539999,45.4922981262],"type":"Point"}
}