{
  "type": "Feature",
  "properties": {
    "addr:full":"200 4th Ave E Prince Rupert BC V8J 1N5",
    "addr:housenumber":"200",
    "addr:postcode":"v8j 1n5",
    "addr:street":"4Th Ave E",
    "iso:country":"CA",
    "sg:address":"200 4th Ave E",
    "sg:city":"Prince Rupert",
    "sg:classifiers":[
        {
            "category":"Organizations",
            "subcategory":"Religious Organization",
            "type":"Services"
        }
    ],
    "sg:phone":"+1 250 624 6080",
    "sg:postcode":"V8J 1N5",
    "sg:province":"BC",
    "sg:tags":[
        "church"
    ],
    "wof:name":"Sikh Temple",
    "wof:placetype":"venue"
},
  "geometry": {"coordinates":[-130.31828300000001,54.315205],"type":"Point"}
}