{
  "type": "Feature",
  "properties": {
    "iso:country":"CA",
    "sg:address":"407 Main St",
    "sg:city":"Gravelbourg",
    "sg:classifiers":[
        {
            "category":"Restaurant",
            "type":"Food & Drink"
        }
    ],
    "sg:phone":"+1 306 648 2255",
    "sg:postcode":"S0H 1X0",
    "sg:province":"SK",
    "wof:name":"Peking Garden Family Rstrnt",
    "wof:placetype":"venue"
},
  "geometry": {"coordinates":[-106.557495117,49.8757972717],"type":"Point"}
}