{
  "type": "Feature",
  "properties": {
    "addr:full":"614 Rte Marie-Victorin Sorel-Tracy QC J3R 1K7",
    "addr:housenumber":"614",
    "addr:postcode":"j3r 1k7",
    "addr:street":"Rte Marie-Victorin",
    "iso:country":"CA",
    "sg:address":"614 Rte Marie-Victorin",
    "sg:city":"Sorel-Tracy",
    "sg:classifiers":[
        {
            "category":"Professional",
            "subcategory":"Business Services",
            "type":"Services"
        }
    ],
    "sg:phone":"+1 450 743 4543",
    "sg:postcode":"J3R 1K7",
    "sg:province":"QC",
    "sg:tags":[
        "interior",
        "consultant",
        "design",
        "decorator"
    ],
    "wof:name":"Louise Levesque Decoration Enr",
    "wof:placetype":"venue"
},
  "geometry": {"coordinates":[-73.124748,46.039883],"type":"Point"}
}