{
  "type": "Feature",
  "properties": {
    "addr:full":"25 Elm Ave Toronto ON M4W 1M9",
    "addr:housenumber":"25",
    "addr:postcode":"m4w 1m9",
    "addr:street":"Elm Ave",
    "iso:country":"CA",
    "sg:address":"25 Elm Ave",
    "sg:city":"Toronto",
    "sg:classifiers":[
        {
            "category":"Manufacturing",
            "subcategory":"Printing",
            "type":"Manufacturing & Wholesale Goods"
        }
    ],
    "sg:phone":"+1 416 961 1325",
    "sg:postcode":"M4W 1M9",
    "sg:province":"ON",
    "sg:tags":[
        "publisher"
    ],
    "wof:name":"Graphic Exchange Magazine",
    "wof:placetype":"venue"
},
  "geometry": {"coordinates":[-79.378136,43.674843],"type":"Point"}
}