{
  "type": "Feature",
  "properties": {
    "addr:full":"Surrey BC V3W 3N1",
    "addr:postcode":"v3w 3n1",
    "iso:country":"CA",
    "sg:city":"Surrey",
    "sg:classifiers":[
        {
            "category":"Utilities",
            "subcategory":"Mobile Phone",
            "type":"Services"
        }
    ],
    "sg:phone":"+1 604 507 4000",
    "sg:postcode":"V3W 3N1",
    "sg:province":"BC",
    "sg:tags":[
        "telephone",
        "cellular"
    ],
    "wof:name":"Sky-Net Computers Ltd",
    "wof:placetype":"venue"
},
  "geometry": {"coordinates":[-122.890182,49.139282],"type":"Point"}
}