{
  "type": "Feature",
  "properties": {
    "addr:full":"18 Victoria S Southampton ON N0H 2L0",
    "addr:housenumber":"18",
    "addr:postcode":"n0h 2l0",
    "addr:street":"Victoria S",
    "iso:country":"CA",
    "sg:address":"18 Victoria S",
    "sg:city":"Southampton",
    "sg:classifiers":[
        {
            "category":"Organizations",
            "subcategory":"Religious Organization",
            "type":"Services"
        }
    ],
    "sg:phone":"+1 519 797 3803",
    "sg:postcode":"N0H 2L0",
    "sg:province":"ON",
    "sg:tags":[
        "church"
    ],
    "wof:name":"Southampton United Church",
    "wof:placetype":"venue"
},
  "geometry": {"coordinates":[-81.369576,44.494366],"type":"Point"}
}