{
  "type": "Feature",
  "properties": {
    "addr:full":"2440 Rue DE L'Aeroport Saint-Mathieu-DE-Beloeil QC J3G 4S5",
    "addr:housenumber":"2440",
    "addr:postcode":"j3g 4s5",
    "addr:street":"Rue De L'Aeroport",
    "iso:country":"CA",
    "sg:address":"2440 Rue DE L'Aeroport",
    "sg:city":"Saint-Mathieu-DE-Beloeil",
    "sg:classifiers":[
        {
            "category":"Airport",
            "type":"Transportation"
        }
    ],
    "sg:phone":"+1 450 446 2570",
    "sg:postcode":"J3G 4S5",
    "sg:province":"QC",
    "sg:tags":[
        "aircraft",
        "maintenance"
    ],
    "wof:name":"Aviamax Inc",
    "wof:placetype":"venue"
},
  "geometry": {"coordinates":[-73.23925,45.589924],"type":"Point"}
}