{
  "type": "Feature",
  "properties": {
    "addr:full":"134 Rue Principale Saint-Anselme QC G0R 2N0",
    "addr:housenumber":"134",
    "addr:postcode":"g0r 2n0",
    "addr:street":"Rue Principale",
    "iso:country":"CA",
    "sg:address":"134 Rue Principale",
    "sg:city":"Saint-Anselme",
    "sg:classifiers":[
        {
            "category":"Government",
            "subcategory":"Office",
            "type":"Public Place"
        }
    ],
    "sg:phone":"+1 418 885 4977",
    "sg:postcode":"G0R 2N0",
    "sg:province":"QC",
    "sg:tags":[
        "village"
    ],
    "wof:name":"Municipalite DE Saint-Anselme",
    "wof:placetype":"venue"
},
  "geometry": {"coordinates":[-70.97287799999999,46.62862],"type":"Point"}
}