{
  "type": "Feature",
  "properties": {
    "addr:full":"130 Bancroft Rd Grand Manan NB E5G 1E1",
    "addr:housenumber":"130",
    "addr:postcode":"e5g 1e1",
    "addr:street":"Bancroft Rd",
    "iso:country":"CA",
    "sg:address":"130 Bancroft Rd",
    "sg:city":"Grand Manan",
    "sg:classifiers":[
        {
            "category":"Freight",
            "type":"Transportation"
        }
    ],
    "sg:phone":"+1 506 662 8194",
    "sg:postcode":"E5G 1E1",
    "sg:province":"NB",
    "sg:tags":[
        "trucking",
        "general",
        "contractor"
    ],
    "wof:name":"Dutchmen Contracting Ltd",
    "wof:placetype":"venue"
},
  "geometry": {"coordinates":[-66.79814910890001,44.675453186],"type":"Point"}
}