{
  "type": "Feature",
  "properties": {
    "iso:country":"CA",
    "sg:address":"3046 Viewmount Rd",
    "sg:city":"Oakville",
    "sg:classifiers":[
        {
            "category":"Manufacturing",
            "subcategory":"Tools & Machinery",
            "type":"Manufacturing & Wholesale Goods"
        }
    ],
    "sg:phone":"+1 905 827 2654",
    "sg:postcode":"L6L 5M7",
    "sg:province":"ON",
    "sg:tags":[
        "machine",
        "making",
        "snow"
    ],
    "wof:name":"Twincore Inc",
    "wof:placetype":"venue"
},
  "geometry": {"coordinates":[-79.730782,43.400448],"type":"Point"}
}