{
  "type": "Feature",
  "properties": {
    "addr:full":"614 Broadway St Wyoming ON N0N 1T0",
    "addr:housenumber":"614",
    "addr:postcode":"n0n 1t0",
    "addr:street":"Broadway St",
    "iso:country":"CA",
    "sg:address":"614 Broadway St",
    "sg:city":"Wyoming",
    "sg:classifiers":[
        {
            "category":"Professional",
            "subcategory":"Computer Services",
            "type":"Services"
        }
    ],
    "sg:phone":"+1 519 845 0034",
    "sg:postcode":"N0N 1T0",
    "sg:province":"ON",
    "sg:tags":[
        "repair",
        "dealer",
        "equipment"
    ],
    "wof:name":"Protech",
    "wof:placetype":"venue"
},
  "geometry": {"coordinates":[-82.118904,42.949539],"type":"Point"}
}