{
  "type": "Feature",
  "properties": {
    "addr:full":"255 136E Rue Saint-Georges QC G5Y 2N7",
    "addr:housenumber":"255",
    "addr:postcode":"g5y 2n7",
    "addr:street":"136E Rue",
    "iso:country":"CA",
    "sg:address":"255 136E Rue",
    "sg:city":"Saint-Georges",
    "sg:classifiers":[
        {
            "category":"Retail",
            "subcategory":"Portrait Studio",
            "type":"Services"
        }
    ],
    "sg:phone":"+1 418 227 5112",
    "sg:postcode":"G5Y 2N7",
    "sg:province":"QC",
    "sg:tags":[
        "photographer"
    ],
    "wof:name":"Photographe Francis Quirion",
    "wof:placetype":"venue"
},
  "geometry": {"coordinates":[-70.67115,46.123348],"type":"Point"}
}