{
  "type": "Feature",
  "properties": {
    "addr:full":"360 Pacific Ave Brandon MB R7A 0H5",
    "addr:housenumber":"360",
    "addr:postcode":"r7a 0h5",
    "addr:street":"Pacific Ave",
    "iso:country":"CA",
    "sg:address":"360 Pacific Ave",
    "sg:city":"Brandon",
    "sg:classifiers":[
        {
            "category":"Wholesale",
            "subcategory":"Electrical",
            "type":"Manufacturing & Wholesale Goods"
        }
    ],
    "sg:phone":"+1 204 727 7292",
    "sg:postcode":"R7A 0H5",
    "sg:province":"MB",
    "sg:tags":[
        "electric",
        "motor"
    ],
    "wof:name":"Harold's Electric Svc",
    "wof:placetype":"venue"
},
  "geometry": {"coordinates":[-99.9426727295,49.8494300842],"type":"Point"}
}