{
  "type": "Feature",
  "properties": {
    "addr:full":"4146 Rue Belanger Montreal QC H1T 1A1",
    "addr:housenumber":"4146",
    "addr:postcode":"h1t 1a1",
    "addr:street":"Rue Belanger",
    "iso:country":"CA",
    "sg:address":"4146 Rue Belanger",
    "sg:city":"Montreal",
    "sg:classifiers":[
        {
            "category":"Health Services",
            "subcategory":"Chiropractor",
            "type":"Services"
        }
    ],
    "sg:phone":"+1 514 725 9588",
    "sg:postcode":"H1T 1A1",
    "sg:province":"QC",
    "wof:name":"Clinique BC Chiropratique",
    "wof:placetype":"venue"
},
  "geometry": {"coordinates":[-73.58683776860001,45.5652427673],"type":"Point"}
}