{
  "type": "Feature",
  "properties": {
    "addr:full":"Courtice ON L1E 3C3",
    "addr:postcode":"l1e 3c3",
    "iso:country":"CA",
    "sg:city":"Courtice",
    "sg:classifiers":[
        {
            "category":"Health Services",
            "subcategory":"Health Practitioner",
            "type":"Services"
        }
    ],
    "sg:phone":"+1 905 721 4335",
    "sg:postcode":"L1E 3C3",
    "sg:province":"ON",
    "sg:tags":[
        "physiotherapist"
    ],
    "wof:name":"Active Recovery Clinic",
    "wof:placetype":"venue"
},
  "geometry": {"coordinates":[-78.8076705933,43.907207489],"type":"Point"}
}