{
  "type": "Feature",
  "properties": {
    "addr:full":"630 Rte Des Campagnards Val-Senneville QC J0Y 2P0",
    "addr:housenumber":"630",
    "addr:postcode":"j0y 2p0",
    "addr:street":"Rte Des Campagnards",
    "iso:country":"CA",
    "sg:address":"630 Rte Des Campagnards",
    "sg:city":"Val-Senneville",
    "sg:classifiers":[
        {
            "category":"Retail",
            "subcategory":"Auto Repair",
            "type":"Services"
        }
    ],
    "sg:phone":"+1 819 874 1188",
    "sg:postcode":"J0Y 2P0",
    "sg:province":"QC",
    "sg:tags":[
        "repairing",
        "automobile"
    ],
    "wof:name":"Sennevilleneuve",
    "wof:placetype":"venue"
},
  "geometry": {"coordinates":[-77.6555099487,48.1801223755],"type":"Point"}
}