{
  "type": "Feature",
  "properties": {
    "addr:full":"875 Av Castelneau Saint-Hyacinthe QC J2S 6S7",
    "addr:postcode":"j2s 6s7",
    "addr:street":"875 Av Castelneau",
    "iso:country":"CA",
    "sg:address":"875 Av Castelneau",
    "sg:city":"Saint-Hyacinthe",
    "sg:classifiers":[
        {
            "category":"Retail",
            "subcategory":"Laundry & Dry Cleaning",
            "type":"Services"
        }
    ],
    "sg:phone":"+1 450 773 6271",
    "sg:postcode":"J2S 6S7",
    "sg:province":"QC",
    "sg:tags":[
        "cleaners"
    ],
    "wof:name":"Nettoyeurs Chatel Inc",
    "wof:placetype":"venue"
},
  "geometry": {"coordinates":[-72.973091,45.607357],"type":"Point"}
}