{
  "type": "Feature",
  "properties": {
    "addr:full":"723 53 Ave SW Calgary AB T2V 0C4",
    "addr:housenumber":"723",
    "addr:postcode":"t2v 0c4",
    "addr:street":"53 Ave Sw",
    "iso:country":"CA",
    "sg:address":"723 53 Ave SW",
    "sg:city":"Calgary",
    "sg:classifiers":[
        {
            "category":"Recreation",
            "type":"Entertainment"
        }
    ],
    "sg:phone":"+1 403 253 9697",
    "sg:postcode":"T2V 0C4",
    "sg:province":"AB",
    "sg:tags":[
        "leasing",
        "amusement"
    ],
    "wof:name":"Rwh Recreation",
    "wof:placetype":"venue"
},
  "geometry": {"coordinates":[-114.079521,51.005913],"type":"Point"}
}