{
  "type": "Feature",
  "properties": {
    "addr:full":"4603 Lakeshore Dr Sylvan Lake AB T4S 1C3",
    "addr:housenumber":"4603",
    "addr:postcode":"t4s 1c3",
    "addr:street":"Lakeshore Dr",
    "iso:country":"CA",
    "sg:address":"4603 Lakeshore Dr",
    "sg:city":"Sylvan Lake",
    "sg:classifiers":[
        {
            "category":"Restaurant",
            "type":"Food & Drink"
        }
    ],
    "sg:phone":"+1 403 887 5533",
    "sg:postcode":"T4S 1C3",
    "sg:province":"AB",
    "sg:tags":[
        "parlor",
        "ice",
        "cream"
    ],
    "wof:name":"Big Moo Ice Cream Parlor",
    "wof:placetype":"venue"
},
  "geometry": {"coordinates":[-114.09362,52.311268],"type":"Point"}
}