{
  "type": "Feature",
  "properties": {
    "addr:full":"843 Rue Clemenceau Beauport QC G1C 2K6",
    "addr:housenumber":"843",
    "addr:postcode":"qc g1c 2k6",
    "addr:street":"Rue Clemenceau",
    "iso:country":"CA",
    "sg:address":"843 Rue Clemenceau",
    "sg:city":"Beauport",
    "sg:classifiers":[
        {
            "category":"Shopping",
            "subcategory":"Stationery & Office Supplies",
            "type":"Retail Goods"
        }
    ],
    "sg:phone":"+1 418 660 5222",
    "sg:postcode":"G1C 2K6",
    "sg:province":"QC",
    "sg:tags":[
        "equipment",
        "computer",
        "dealer"
    ],
    "wof:name":"Bureau En Gros",
    "wof:placetype":"venue"
},
  "geometry": {"coordinates":[-71.202057,46.870865],"type":"Point"}
}