{
  "type": "Feature",
  "properties": {
    "addr:full":"9050 Shaughnessy St Vancouver BC V6P 6E5",
    "addr:postcode":"9050;v6p 6e5",
    "addr:street":"Shaughnessy St",
    "iso:country":"CA",
    "sg:address":"9050 Shaughnessy St",
    "sg:city":"Vancouver",
    "sg:classifiers":[
        {
            "category":"Manufacturing",
            "subcategory":"Printing",
            "type":"Manufacturing & Wholesale Goods"
        }
    ],
    "sg:phone":"+1 604 323 7100",
    "sg:postcode":"V6P 6E5",
    "sg:province":"BC",
    "sg:tags":[
        "publisher"
    ],
    "wof:name":"Raincoast Book Distribution",
    "wof:placetype":"venue"
},
  "geometry": {"coordinates":[-123.126839,49.2033],"type":"Point"}
}