{
  "type": "Feature",
  "properties": {
    "addr:full":"2447 Valley Forest Way Oakville ON L6H 6X3",
    "addr:housenumber":"2447",
    "addr:postcode":"l6h 6x3",
    "addr:street":"Valley Forest Way",
    "iso:country":"CA",
    "sg:address":"2447 Valley Forest Way",
    "sg:city":"Oakville",
    "sg:classifiers":[
        {
            "category":"Professional",
            "subcategory":"Management & Consulting",
            "type":"Services"
        }
    ],
    "sg:phone":"+1 905 257 8689",
    "sg:postcode":"L6H 6X3",
    "sg:province":"ON",
    "sg:tags":[
        "consultant",
        "business"
    ],
    "wof:name":"Profit Max Canada",
    "wof:placetype":"venue"
},
  "geometry": {"coordinates":[-79.74462890620001,43.4611358643],"type":"Point"}
}