{
  "type": "Feature",
  "properties": {
    "addr:full":"3548 Novalea Dr Halifax NS B3K 3E8",
    "addr:housenumber":"3548",
    "addr:postcode":"b3k 3e8",
    "addr:street":"Novalea Dr",
    "iso:country":"CA",
    "sg:address":"3548 Novalea Dr",
    "sg:city":"Halifax",
    "sg:classifiers":[
        {
            "category":"Personal",
            "subcategory":"Barber",
            "type":"Services"
        }
    ],
    "sg:phone":"+1 902 453 9621",
    "sg:postcode":"B3K 3E8",
    "sg:province":"NS",
    "wof:name":"Canadiana Barber Shop",
    "wof:placetype":"venue"
},
  "geometry": {"coordinates":[-63.607162,44.668022],"type":"Point"}
}