{
  "type": "Feature",
  "properties": {
    "iso:country":"CA",
    "sg:address":"957 Westney Rd S #7",
    "sg:city":"Ajax",
    "sg:classifiers":[
        {
            "category":"Shopping",
            "subcategory":"Pharmacy",
            "type":"Retail Goods"
        }
    ],
    "sg:phone":"+1 905 683 1314",
    "sg:postcode":"L1S 3K7",
    "sg:province":"ON",
    "wof:name":"Pharma Plus Drugmart",
    "wof:placetype":"venue"
},
  "geometry": {"coordinates":[-79.0171203613,43.8308639526],"type":"Point"}
}