{
  "type": "Feature",
  "properties": {
    "iso:country":"CA",
    "sg:address":"1376 Mcphillips St",
    "sg:city":"Winnipeg",
    "sg:classifiers":[
        {
            "category":"Banks & Credit Unions",
            "subcategory":"Bank",
            "type":"Services"
        }
    ],
    "sg:phone":"+1 204 632 8733",
    "sg:postcode":"R2X 2M4",
    "sg:province":"MB",
    "sg:tags":[
        "loan"
    ],
    "wof:name":"Money Tree Payday Loans Inc",
    "wof:placetype":"venue"
},
  "geometry": {"coordinates":[-97.15934,49.94025],"type":"Point"}
}