{
  "type": "Feature",
  "properties": {
    "addr:full":"3260 Parsons Rd NW Edmonton AB T6N 1B3",
    "addr:housenumber":"3260",
    "addr:postcode":"t6n 1b3",
    "addr:street":"Parsons Rd Nw",
    "iso:country":"CA",
    "sg:address":"3260 Parsons Rd NW",
    "sg:city":"Edmonton",
    "sg:classifiers":[
        {
            "category":"Manufacturing",
            "subcategory":"Motor Vehicles & Parts",
            "type":"Manufacturing & Wholesale Goods"
        }
    ],
    "sg:phone":"+1 780 463 4291",
    "sg:postcode":"T6N 1B3",
    "sg:province":"AB",
    "sg:tags":[
        "equipment",
        "truck"
    ],
    "wof:name":"City Spring Ltd",
    "wof:placetype":"venue"
},
  "geometry": {"coordinates":[-113.48625199999999,53.465153],"type":"Point"}
}