{
  "type": "Feature",
  "properties": {
    "addr:full":"467 Rue Cremazie Mont-Laurier QC J9L 2M6",
    "addr:housenumber":"467",
    "addr:postcode":"j9l 2m6",
    "addr:street":"Rue Cremazie",
    "iso:country":"CA",
    "sg:address":"467 Rue Cremazie",
    "sg:city":"Mont-Laurier",
    "sg:classifiers":[
        {
            "category":"Organizations",
            "subcategory":"Professional Association",
            "type":"Services"
        }
    ],
    "sg:phone":"+1 819 623 1893",
    "sg:postcode":"J9L 2M6",
    "sg:province":"QC",
    "wof:name":"Chevaliers DE Colomb",
    "wof:placetype":"venue"
},
  "geometry": {"coordinates":[-75.502174,46.550659],"type":"Point"}
}