{
  "type": "Feature",
  "properties": {
    "iso:country":"CA",
    "sg:address":"24 Mill St # 4",
    "sg:city":"Almonte",
    "sg:classifiers":[
        {
            "category":"Shopping",
            "subcategory":"Pharmacy",
            "type":"Retail Goods"
        }
    ],
    "sg:phone":"+1 613 256 2466",
    "sg:postcode":"K0A 1A0",
    "sg:province":"ON",
    "wof:name":"Almonte Pharmasave",
    "wof:placetype":"venue"
},
  "geometry": {"coordinates":[-76.197296,45.225136],"type":"Point"}
}