{
  "type": "Feature",
  "properties": {
    "addr:full":"Vermilion AB T9X 1G1",
    "addr:postcode":"t9x 1g1",
    "iso:country":"CA",
    "sg:city":"Vermilion",
    "sg:classifiers":[
        {
            "category":"Shopping",
            "subcategory":"Jewelry",
            "type":"Retail Goods"
        }
    ],
    "sg:phone":"+1 780 853 4408",
    "sg:postcode":"T9X 1G1",
    "sg:province":"AB",
    "sg:tags":[
        "jeweler"
    ],
    "wof:name":"Diamonds For You",
    "wof:placetype":"venue"
},
  "geometry": {"coordinates":[-110.83532,53.349979],"type":"Point"}
}