{
  "type": "Feature",
  "properties": {
    "addr:full":"2700 Boul Laurier Sainte-Foy QC G1V 2L8",
    "addr:housenumber":"2700",
    "addr:postcode":"g1v 2l8",
    "addr:street":"Boul Laurier",
    "iso:country":"CA",
    "sg:address":"2700 Boul Laurier",
    "sg:city":"Sainte-Foy",
    "sg:classifiers":[
        {
            "category":"Professional",
            "subcategory":"Accounting & Tax Preparation",
            "type":"Services"
        }
    ],
    "sg:phone":"+1 418 658 2121",
    "sg:postcode":"G1V 2L8",
    "sg:province":"QC",
    "sg:tags":[
        "return",
        "filing"
    ],
    "wof:name":"H & R Block Canada Inc",
    "wof:placetype":"venue"
},
  "geometry": {"coordinates":[-71.284072876,46.7696762085],"type":"Point"}
}