{
  "type": "Feature",
  "properties": {
    "addr:full":"Atholville NB E3N 4E8",
    "addr:postcode":"e3n 4e8",
    "iso:country":"CA",
    "sg:city":"Atholville",
    "sg:classifiers":[
        {
            "category":"Building & Trades",
            "subcategory":"Construction",
            "type":"Services"
        }
    ],
    "sg:phone":"+1 506 753 4478",
    "sg:postcode":"E3N 4E8",
    "sg:province":"NB",
    "sg:tags":[
        "contractor",
        "demolition",
        "general"
    ],
    "wof:name":"High Country Crushed Stone Ltd",
    "wof:placetype":"venue"
},
  "geometry": {"coordinates":[-66.738983,47.98576],"type":"Point"}
}