{
  "type": "Feature",
  "properties": {
    "addr:full":"943 Dundas St Woodstock ON N4S 1H2",
    "addr:housenumber":"943",
    "addr:postcode":"n4s 1h2",
    "addr:street":"Dundas St",
    "iso:country":"CA",
    "sg:address":"943 Dundas St",
    "sg:city":"Woodstock",
    "sg:classifiers":[
        {
            "category":"Banks & Credit Unions",
            "subcategory":"Bank",
            "type":"Services"
        }
    ],
    "sg:phone":"+1 519 539 4813",
    "sg:postcode":"N4S 1H2",
    "sg:province":"ON",
    "wof:name":"Rochdale Credit Union Ltd",
    "wof:placetype":"venue"
},
  "geometry": {"coordinates":[-80.73262,43.133713],"type":"Point"}
}