{
  "type": "Feature",
  "properties": {
    "addr:full":"Calgary AB T2E 7P4",
    "addr:postcode":"t2e 7p4",
    "iso:country":"CA",
    "sg:city":"Calgary",
    "sg:classifiers":[
        {
            "category":"Shopping",
            "subcategory":"Jewelry",
            "type":"Retail Goods"
        }
    ],
    "sg:phone":"+1 403 274 3633",
    "sg:postcode":"T2E 7P4",
    "sg:province":"AB",
    "sg:tags":[
        "jeweler"
    ],
    "wof:name":"Peoples Jewellers",
    "wof:placetype":"venue"
},
  "geometry": {"coordinates":[-114.041115,51.110344],"type":"Point"}
}