{
  "type": "Feature",
  "properties": {
    "iso:country":"CA",
    "sg:address":"301 Pretty River Pky N",
    "sg:city":"Collingwood",
    "sg:classifiers":[
        {
            "category":"Retail",
            "subcategory":"Auto Repair",
            "type":"Services"
        }
    ],
    "sg:phone":"+1 705 445 6443",
    "sg:postcode":"L9Y 4J4",
    "sg:province":"ON",
    "sg:tags":[
        "body",
        "automobile",
        "painting"
    ],
    "wof:name":"Parkway Collision Ltd",
    "wof:placetype":"venue"
},
  "geometry": {"coordinates":[-80.1964874268,44.5017356873],"type":"Point"}
}