{
  "type": "Feature",
  "properties": {
    "addr:full":"380 Dansbury Dr Waterloo ON N2K 3C2",
    "addr:housenumber":"380",
    "addr:postcode":"n2k 3c2",
    "addr:street":"Dansbury Dr",
    "iso:country":"CA",
    "sg:address":"380 Dansbury Dr",
    "sg:city":"Waterloo",
    "sg:classifiers":[
        {
            "category":"Building & Trades",
            "subcategory":"Cleaning & Sanitation",
            "type":"Services"
        }
    ],
    "sg:phone":"+1 519 888 6830",
    "sg:postcode":"N2K 3C2",
    "sg:province":"ON",
    "sg:tags":[
        "window",
        "maintenance"
    ],
    "wof:name":"Windowclean",
    "wof:placetype":"venue"
},
  "geometry": {"coordinates":[-80.50034332280001,43.4977302551],"type":"Point"}
}