{
  "type": "Feature",
  "properties": {
    "addr:full":"Saint-Agapit QC G0S 1Z0",
    "addr:postcode":"g0s 1z0",
    "iso:country":"CA",
    "sg:city":"Saint-Agapit",
    "sg:classifiers":[
        {
            "category":"Education",
            "subcategory":"School",
            "type":"Public Place"
        }
    ],
    "sg:phone":"+1 418 888 3961",
    "sg:postcode":"G0S 1Z0",
    "sg:province":"QC",
    "wof:name":"Ecole Secondaire Beaurivage",
    "wof:placetype":"venue"
},
  "geometry": {"coordinates":[-71.43733978269999,46.5629348755],"type":"Point"}
}