{
  "type": "Feature",
  "properties": {
    "addr:full":"Hwy 129 Chapleau ON P0M 1K0",
    "addr:postcode":"p0m 1k0",
    "addr:street":"Hwy 129",
    "iso:country":"CA",
    "sg:address":"Hwy 129",
    "sg:city":"Chapleau",
    "sg:classifiers":[
        {
            "category":"Travel",
            "subcategory":"Hotels & Motels",
            "type":"Entertainment"
        }
    ],
    "sg:phone":"+1 705 864 2588",
    "sg:postcode":"P0M 1K0",
    "sg:province":"ON",
    "sg:tags":[
        "resort"
    ],
    "wof:name":"Flame Lake Lodge Ltd",
    "wof:placetype":"venue"
},
  "geometry": {"coordinates":[-83.398438,47.819649],"type":"Point"}
}