{
  "type": "Feature",
  "properties": {
    "addr:full":"Winnipeg MB R3C 0L7",
    "addr:postcode":"r3c 0l7",
    "iso:country":"CA",
    "sg:city":"Winnipeg",
    "sg:classifiers":[
        {
            "category":"Health Services",
            "subcategory":"Doctor",
            "type":"Services"
        }
    ],
    "sg:phone":"+1 204 944 9707",
    "sg:postcode":"R3C 0L7",
    "sg:province":"MB",
    "sg:tags":[
        "physician",
        "surgeon",
        "laboratory"
    ],
    "wof:name":"Trainor Laboratory",
    "wof:placetype":"venue"
},
  "geometry": {"coordinates":[-97.14743799999999,49.890495],"type":"Point"}
}