{
  "type": "Feature",
  "properties": {
    "addr:full":"75 Rue Saint-Henri Riviere-Du-Loup QC G5R 2A4",
    "addr:housenumber":"75",
    "addr:postcode":"g5r 2a4",
    "addr:street":"Rue Saint-Henri Riviere-Du-Loup",
    "iso:country":"CA",
    "sg:address":"75 Rue Saint-Henri",
    "sg:city":"Riviere-Du-Loup",
    "sg:classifiers":[
        {
            "category":"Health Services",
            "subcategory":"Doctor",
            "type":"Services"
        }
    ],
    "sg:phone":"+1 418 862 6611",
    "sg:postcode":"G5R 2A4",
    "sg:province":"QC",
    "sg:tags":[
        "physician",
        "surgeon"
    ],
    "wof:name":"Maranda, Jacques MD",
    "wof:placetype":"venue"
},
  "geometry": {"coordinates":[-69.535515,47.821251],"type":"Point"}
}