{
  "type": "Feature",
  "properties": {
    "addr:full":"Vaudreuil-Dorion QC J7V 8P2",
    "addr:postcode":"j7v 8p2",
    "iso:country":"CA",
    "sg:city":"Vaudreuil-Dorion",
    "sg:classifiers":[
        {
            "category":"Freight",
            "type":"Transportation"
        }
    ],
    "sg:phone":"+1 450 455 0123",
    "sg:postcode":"J7V 8P2",
    "sg:province":"QC",
    "sg:tags":[
        "mover",
        "commercial"
    ],
    "wof:name":"Mini Entreposage-Harwood",
    "wof:placetype":"venue"
},
  "geometry": {"coordinates":[-74.032944,45.373013],"type":"Point"}
}