{
  "type": "Feature",
  "properties": {
    "addr:full":"444 Boul Adelard-Savoie Dieppe NB E1A 7E6",
    "addr:housenumber":"444",
    "addr:postcode":"e1a 7e6",
    "addr:street":"Boul Adelard-Savoie",
    "iso:country":"CA",
    "sg:address":"444 Boul Adelard-Savoie",
    "sg:city":"Dieppe",
    "sg:classifiers":[
        {
            "category":"Freight",
            "type":"Transportation"
        }
    ],
    "sg:phone":"+1 506 853 0883",
    "sg:postcode":"E1A 7E6",
    "sg:province":"NB",
    "sg:tags":[
        "commercial",
        "storage"
    ],
    "wof:name":"Atcan Self Storage",
    "wof:placetype":"venue"
},
  "geometry": {"coordinates":[-64.7057342529,46.1074333191],"type":"Point"}
}