{
  "type": "Feature",
  "properties": {
    "addr:full":"80 Bennett Rd Scarborough ON M1E 3Y3",
    "addr:housenumber":"80",
    "addr:postcode":"m1e 3y3",
    "addr:street":"Bennett Rd",
    "iso:country":"CA",
    "sg:address":"80 Bennett Rd",
    "sg:city":"Scarborough",
    "sg:classifiers":[
        {
            "category":"Education",
            "subcategory":"School",
            "type":"Public Place"
        }
    ],
    "sg:phone":"+1 416 393 5336",
    "sg:postcode":"M1E 3Y3",
    "sg:province":"ON",
    "wof:name":"Saint Malachy Catholic School",
    "wof:placetype":"venue"
},
  "geometry": {"coordinates":[-79.165398,43.77026],"type":"Point"}
}