{
  "type": "Feature",
  "properties": {
    "addr:full":"25 Lakewood Cres Naughton ON P0M 2M0",
    "addr:housenumber":"25",
    "addr:postcode":"p0m 2m0",
    "addr:street":"Lakewood Cres Naughton",
    "iso:country":"CA",
    "sg:address":"25 Lakewood Cres",
    "sg:city":"Naughton",
    "sg:classifiers":[
        {
            "category":"Retail",
            "subcategory":"Auto Repair",
            "type":"Services"
        }
    ],
    "sg:phone":"+1 705 690 3232",
    "sg:postcode":"P0M 2M0",
    "sg:province":"ON",
    "sg:tags":[
        "body",
        "automobile",
        "painting"
    ],
    "wof:name":"Automagic Sudbury",
    "wof:placetype":"venue"
},
  "geometry": {"coordinates":[-81.19115447999999,46.4020805359],"type":"Point"}
}