{
  "type": "Feature",
  "properties": {
    "addr:full":"1301 Squire Lefroy ON L0L 1W0",
    "addr:housenumber":"1301",
    "addr:postcode":"l0l 1w0",
    "addr:street":"Squire Lefroy",
    "iso:country":"CA",
    "sg:address":"1301 Squire",
    "sg:city":"Lefroy",
    "sg:classifiers":[
        {
            "category":"Building & Trades",
            "subcategory":"Cleaning & Sanitation",
            "type":"Services"
        }
    ],
    "sg:phone":"+1 705 456 7771",
    "sg:postcode":"L0L 1W0",
    "sg:province":"ON",
    "sg:tags":[
        "house"
    ],
    "wof:name":"Mini Maid",
    "wof:placetype":"venue"
},
  "geometry": {"coordinates":[-79.5563201904,44.2708015442],"type":"Point"}
}