{
  "type": "Feature",
  "properties": {
    "addr:full":"Edmonton AB T6L 6X3",
    "addr:postcode":"t6l 6x3",
    "iso:country":"CA",
    "sg:city":"Edmonton",
    "sg:classifiers":[
        {
            "category":"Communications",
            "subcategory":"Film & Video Production",
            "type":"Services"
        }
    ],
    "sg:phone":"+1 780 414 0620",
    "sg:postcode":"T6L 6X3",
    "sg:province":"AB",
    "sg:tags":[
        "taping"
    ],
    "wof:name":"Secured By Video",
    "wof:placetype":"venue"
},
  "geometry": {"coordinates":[-113.427711,53.465302],"type":"Point"}
}