{
  "type": "Feature",
  "properties": {
    "addr:full":"187 Shropshire Dr Scarborough ON M1P 1Z6",
    "addr:housenumber":"187",
    "addr:postcode":"m1p 1z6",
    "addr:street":"Shropshire Dr",
    "iso:country":"CA",
    "sg:address":"187 Shropshire Dr",
    "sg:city":"Scarborough",
    "sg:classifiers":[
        {
            "category":"Shopping",
            "type":"Retail Goods"
        }
    ],
    "sg:phone":"+1 416 755 8311",
    "sg:postcode":"M1P 1Z6",
    "sg:province":"ON",
    "sg:tags":[
        "equipment",
        "wine",
        "supply"
    ],
    "wof:name":"Wine Kitz",
    "wof:placetype":"venue"
},
  "geometry": {"coordinates":[-79.278801,43.757317],"type":"Point"}
}