{
  "type": "Feature",
  "properties": {
    "iso:country":"CA",
    "sg:city":"Saskatoon",
    "sg:classifiers":[
        {
            "category":"Personal",
            "type":"Services"
        }
    ],
    "sg:phone":"+1 306 665 2020",
    "sg:postcode":"S7K 1W4",
    "sg:province":"SK",
    "sg:tags":[
        "electrolysis"
    ],
    "wof:name":"Electrolysis By Marg",
    "wof:placetype":"venue"
},
  "geometry": {"coordinates":[-106.663131714,52.1566162109],"type":"Point"}
}