{
  "type": "Feature",
  "properties": {
    "addr:full":"5505 Av Papineau Montreal QC H2H 1W3",
    "addr:housenumber":"5505",
    "addr:postcode":"h2h 1w3",
    "addr:street":"Av Papineau",
    "iso:country":"CA",
    "sg:address":"5505 Av Papineau",
    "sg:city":"Montreal",
    "sg:classifiers":[
        {
            "category":"Building & Trades",
            "subcategory":"Plumbing",
            "type":"Services"
        }
    ],
    "sg:phone":"+1 514 524 1473",
    "sg:postcode":"H2H 1W3",
    "sg:province":"QC",
    "sg:tags":[
        "conditioning",
        "air",
        "system",
        "contractor"
    ],
    "wof:name":"Gestion D'Air Inc",
    "wof:placetype":"venue"
},
  "geometry": {"coordinates":[-73.5850524902,45.537902832],"type":"Point"}
}