{
  "type": "Feature",
  "properties": {
    "addr:full":"121 Rue Mombleau Saint-Jean-Sur-Richelieu QC J3B 6Y8",
    "addr:housenumber":"121",
    "addr:postcode":"j3b 6y8",
    "addr:street":"Rue Mombleau",
    "iso:country":"CA",
    "sg:address":"121 Rue Mombleau",
    "sg:city":"Saint-Jean-Sur-Richelieu",
    "sg:classifiers":[
        {
            "category":"Travel",
            "subcategory":"Campground",
            "type":"Entertainment"
        }
    ],
    "sg:phone":"+1 450 347 4528",
    "sg:postcode":"J3B 6Y8",
    "sg:province":"QC",
    "wof:name":"Camping Du Haut Richelieu",
    "wof:placetype":"venue"
},
  "geometry": {"coordinates":[-73.249596,45.2397],"type":"Point"}
}