{
  "type": "Feature",
  "properties": {
    "iso:country":"CA",
    "sg:address":"777 Century St",
    "sg:city":"Winnipeg",
    "sg:classifiers":[
        {
            "category":"Manufacturing",
            "subcategory":"Tools & Machinery",
            "type":"Manufacturing & Wholesale Goods"
        }
    ],
    "sg:phone":"+1 204 774 3461",
    "sg:postcode":"R3H 0M2",
    "sg:province":"MB",
    "sg:tags":[
        "pipe",
        "water",
        "works",
        "equipment"
    ],
    "wof:name":"Mueller Flow Control",
    "wof:placetype":"venue"
},
  "geometry": {"coordinates":[-97.20240783689999,49.9003219604],"type":"Point"}
}