{
  "type": "Feature",
  "properties": {
    "iso:country":"CA",
    "sg:address":"100 Park Royal S # 1110",
    "sg:city":"West Vancouver",
    "sg:classifiers":[
        {
            "category":"Professional",
            "subcategory":"Lawyer & Legal Services",
            "type":"Services"
        }
    ],
    "sg:phone":"+1 604 925 0045",
    "sg:postcode":"V7T 1A2",
    "sg:province":"BC",
    "sg:tags":[
        "attorney"
    ],
    "wof:name":"Forsyth, David",
    "wof:placetype":"venue"
},
  "geometry": {"coordinates":[-123.134994507,49.3251304626],"type":"Point"}
}