{
  "type": "Feature",
  "properties": {
    "iso:country":"CA",
    "sg:address":"157 Davis Dr",
    "sg:city":"Newmarket",
    "sg:classifiers":[
        {
            "category":"Health Services",
            "subcategory":"Medical Lab",
            "type":"Services"
        }
    ],
    "sg:phone":"+1 905 853 2633",
    "sg:postcode":"L3Y 2N3",
    "sg:province":"ON",
    "wof:name":"Dean Rhyno Denture Clinic",
    "wof:placetype":"venue"
},
  "geometry": {"coordinates":[-79.4729309082,44.0565872192],"type":"Point"}
}