{
  "type": "Feature",
  "properties": {
    "iso:country":"CA",
    "sg:address":"25 Dundas St E",
    "sg:city":"Belleville",
    "sg:classifiers":[
        {
            "category":"Restaurant",
            "type":"Food & Drink"
        }
    ],
    "sg:phone":"+1 613 969 1445",
    "sg:postcode":"K8N 1B6",
    "sg:province":"ON",
    "sg:tags":[
        "caterer"
    ],
    "wof:name":"Funky Carp",
    "wof:placetype":"venue"
},
  "geometry": {"coordinates":[-77.38162231450001,44.1609687805],"type":"Point"}
}