{
  "type": "Feature",
  "properties": {
    "addr:full":"Castlegar BC V1N 1R5",
    "addr:postcode":"v1n 1r5",
    "iso:country":"CA",
    "sg:city":"Castlegar",
    "sg:classifiers":[
        {
            "category":"Education",
            "subcategory":"School",
            "type":"Public Place"
        }
    ],
    "sg:phone":"+1 250 365 7735",
    "sg:postcode":"V1N 1R5",
    "sg:province":"BC",
    "wof:name":"Stanley Humphries Secondary",
    "wof:placetype":"venue"
},
  "geometry": {"coordinates":[-117.659858704,49.3199424744],"type":"Point"}
}