{
  "type": "Feature",
  "properties": {
    "addr:full":"Azilda Centre D'Achats Azilda ON P0M 1B0",
    "addr:postcode":"p0m 1b0",
    "iso:country":"CA",
    "sg:address":"Azilda Centre D'Achats",
    "sg:city":"Azilda",
    "sg:classifiers":[
        {
            "category":"Banks & Credit Unions",
            "subcategory":"Bank",
            "type":"Services"
        }
    ],
    "sg:phone":"+1 705 983 4201",
    "sg:postcode":"P0M 1B0",
    "sg:province":"ON",
    "wof:name":"Scotiabank",
    "wof:placetype":"venue"
},
  "geometry": {"coordinates":[-81.13400300000001,46.561539],"type":"Point"}
}