{
  "type": "Feature",
  "properties": {
    "addr:full":"Lloydminster SK S9V 1E6",
    "addr:postcode":"s9v 1e6",
    "iso:country":"CA",
    "sg:city":"Lloydminster",
    "sg:classifiers":[
        {
            "category":"Mining & Drilling",
            "type":"Manufacturing & Wholesale Goods"
        }
    ],
    "sg:phone":"+1 306 825 4065",
    "sg:postcode":"S9V 1E6",
    "sg:province":"SK",
    "sg:tags":[
        "oil",
        "well"
    ],
    "wof:name":"Apollo Pumpjack Svc",
    "wof:placetype":"venue"
},
  "geometry": {"coordinates":[-109.99789428699999,53.2641220093],"type":"Point"}
}