{
  "type": "Feature",
  "properties": {
    "addr:full":"Calgary AB T2H 0T2",
    "addr:postcode":"t2h 0t2",
    "iso:country":"CA",
    "sg:city":"Calgary",
    "sg:classifiers":[
        {
            "category":"Manufacturing",
            "subcategory":"Tools & Machinery",
            "type":"Manufacturing & Wholesale Goods"
        }
    ],
    "sg:phone":"+1 403 253 4224",
    "sg:postcode":"T2H 0T2",
    "sg:province":"AB",
    "sg:tags":[
        "control"
    ],
    "wof:name":"Fotron Control Systems Inc",
    "wof:placetype":"venue"
},
  "geometry": {"coordinates":[-114.056862,50.992142],"type":"Point"}
}