{
  "type": "Feature",
  "properties": {
    "addr:full":"494 Riverbend Sq NW Edmonton AB T6R 2E3",
    "addr:housenumber":"494",
    "addr:postcode":"t6r 2e3",
    "addr:street":"Riverbend Sq Nw",
    "iso:country":"CA",
    "sg:address":"494 Riverbend Sq NW",
    "sg:city":"Edmonton",
    "sg:classifiers":[
        {
            "category":"Restaurant",
            "type":"Food & Drink"
        }
    ],
    "sg:phone":"+1 780 414 8403",
    "sg:postcode":"T6R 2E3",
    "sg:province":"AB",
    "wof:name":"Mc Donald's",
    "wof:placetype":"venue"
},
  "geometry": {"coordinates":[-113.58672332800001,53.4694900513],"type":"Point"}
}