{
  "type": "Feature",
  "properties": {
    "iso:country":"CA",
    "sg:city":"Vancouver",
    "sg:classifiers":[
        {
            "category":"Professional",
            "subcategory":"Lawyer & Legal Services",
            "type":"Services"
        }
    ],
    "sg:phone":"+1 604 408 8277",
    "sg:postcode":"V6E 4H1",
    "sg:province":"BC",
    "sg:tags":[
        "attorney"
    ],
    "wof:name":"Church & CO",
    "wof:placetype":"venue"
},
  "geometry": {"coordinates":[-123.122032,49.284874],"type":"Point"}
}