{
  "type": "Feature",
  "properties": {
    "addr:full":"5657 Spring Garden Rd Halifax NS B3J 1G9",
    "addr:housenumber":"5657",
    "addr:postcode":"ns b3j 1g9",
    "addr:street":"Spring Garden Rd",
    "iso:country":"CA",
    "sg:address":"5657 Spring Garden Rd",
    "sg:city":"Halifax",
    "sg:classifiers":[
        {
            "category":"Home & Garden",
            "subcategory":"Furniture",
            "type":"Retail Goods"
        }
    ],
    "sg:phone":"+1 902 425 9273",
    "sg:postcode":"B3J 1G9",
    "sg:province":"NS",
    "wof:name":"Backyard & Veranda Inc",
    "wof:placetype":"venue"
},
  "geometry": {"coordinates":[-63.578651,44.642662],"type":"Point"}
}