{
  "type": "Feature",
  "properties": {
    "addr:full":"3487 9th St Houston BC V0J 1Z0",
    "addr:housenumber":"3487",
    "addr:postcode":"v0j 1z0",
    "addr:street":"9Th St",
    "iso:country":"CA",
    "sg:address":"3487 9th St",
    "sg:city":"Houston",
    "sg:classifiers":[
        {
            "category":"Shopping",
            "subcategory":"Department Store",
            "type":"Retail Goods"
        }
    ],
    "sg:phone":"+1 250 845 7343",
    "sg:postcode":"V0J 1Z0",
    "sg:province":"BC",
    "wof:name":"Sears Canada Inc",
    "wof:placetype":"venue"
},
  "geometry": {"coordinates":[-126.647148132,54.400352478],"type":"Point"}
}