{
  "type": "Feature",
  "properties": {
    "addr:full":"9920 Main St Summerland BC V0H 1Z0",
    "addr:housenumber":"9920",
    "addr:postcode":"v0h 1z0",
    "addr:street":"Main St",
    "iso:country":"CA",
    "sg:address":"9920 Main St",
    "sg:city":"Summerland",
    "sg:classifiers":[
        {
            "category":"Banks & Credit Unions",
            "subcategory":"Bank",
            "type":"Services"
        }
    ],
    "sg:phone":"+1 250 404 4000",
    "sg:postcode":"V0H 1Z0",
    "sg:province":"BC",
    "wof:name":"Cibc",
    "wof:placetype":"venue"
},
  "geometry": {"coordinates":[-119.681838989,49.6014862061],"type":"Point"}
}