{
  "type": "Feature",
  "properties": {
    "addr:full":"4355 Jingle Pot Rd Nanaimo BC V9T 5P4",
    "addr:postcode":"4355;v9t 5p4",
    "addr:street":"Jingle Pot Rd",
    "iso:country":"CA",
    "sg:address":"4355 Jingle Pot Rd",
    "sg:city":"Nanaimo",
    "sg:classifiers":[
        {
            "category":"Education",
            "subcategory":"School",
            "type":"Public Place"
        }
    ],
    "sg:phone":"+1 250 758 1536",
    "sg:postcode":"V9T 5P4",
    "sg:province":"BC",
    "wof:name":"MT Benson School",
    "wof:placetype":"venue"
},
  "geometry": {"coordinates":[-124.019981,49.205532],"type":"Point"}
}