{
  "type": "Feature",
  "properties": {
    "addr:full":"35 Wilson Ave St Thomas ON N5R 3P9",
    "addr:housenumber":"35",
    "addr:postcode":"n5r 3p9",
    "addr:street":"Wilson Ave",
    "iso:country":"CA",
    "sg:address":"35 Wilson Ave",
    "sg:city":"St Thomas",
    "sg:classifiers":[
        {
            "category":"Building & Trades",
            "subcategory":"Construction",
            "type":"Services"
        }
    ],
    "sg:phone":"+1 519 631 1755",
    "sg:postcode":"N5R 3P9",
    "sg:province":"ON",
    "sg:tags":[
        "concrete",
        "contractor"
    ],
    "wof:name":"Gor Dan Concrete",
    "wof:placetype":"venue"
},
  "geometry": {"coordinates":[-81.196472,42.769169],"type":"Point"}
}