{
  "type": "Feature",
  "properties": {
    "addr:full":"Fortune Bay Seal Cove Fb NL A0H 2G0",
    "addr:postcode":"a0h 2g0",
    "iso:country":"CA",
    "sg:address":"Fortune Bay",
    "sg:city":"Seal Cove Fb",
    "sg:classifiers":[
        {
            "category":"Professional",
            "subcategory":"Advertising",
            "type":"Services"
        }
    ],
    "sg:phone":"+1 709 851 3131",
    "sg:postcode":"A0H 2G0",
    "sg:province":"NL",
    "wof:name":"Ad Zone",
    "wof:placetype":"venue"
},
  "geometry": {"coordinates":[-53.0861358643,47.4647445679],"type":"Point"}
}