{
  "type": "Feature",
  "properties": {
    "iso:country":"CA",
    "sg:address":"12935 97 St NW",
    "sg:city":"Edmonton",
    "sg:classifiers":[
        {
            "category":"Health Services",
            "subcategory":"Chiropractor",
            "type":"Services"
        }
    ],
    "sg:phone":"+1 780 473 6441",
    "sg:postcode":"T5E 4C2",
    "sg:province":"AB",
    "wof:name":"North Edmonton Chiropractic",
    "wof:placetype":"venue"
},
  "geometry": {"coordinates":[-113.491844177,53.5883483887],"type":"Point"}
}