{
  "type": "Feature",
  "properties": {
    "addr:full":"Pointe-Claire QC H9R 3J1",
    "addr:postcode":"h9r 3j1",
    "iso:country":"CA",
    "sg:city":"Pointe-Claire",
    "sg:classifiers":[
        {
            "category":"Shopping",
            "subcategory":"Jewelry",
            "type":"Retail Goods"
        }
    ],
    "sg:phone":"+1 514 694 6850",
    "sg:postcode":"H9R 3J1",
    "sg:province":"QC",
    "sg:tags":[
        "diamond",
        "jeweler"
    ],
    "wof:name":"Bijouterie Dj",
    "wof:placetype":"venue"
},
  "geometry": {"coordinates":[-73.816193,45.445686],"type":"Point"}
}