{
  "type": "Feature",
  "properties": {
    "addr:full":"2047 Avenue Rd North York ON M5M 4A7",
    "addr:housenumber":"2047",
    "addr:postcode":"m5m 4a7",
    "addr:street":"Avenue Rd",
    "iso:country":"CA",
    "sg:address":"2047 Avenue Rd",
    "sg:city":"North York",
    "sg:classifiers":[
        {
            "category":"Shopping",
            "subcategory":"Pharmacy",
            "type":"Retail Goods"
        }
    ],
    "sg:phone":"+1 416 789 1122",
    "sg:postcode":"M5M 4A7",
    "sg:province":"ON",
    "wof:name":"Main Drug Mart",
    "wof:placetype":"venue"
},
  "geometry": {"coordinates":[-79.41255187989999,43.7679138184],"type":"Point"}
}