{
  "type": "Feature",
  "properties": {
    "addr:full":"273 Mill St Port Elgin ON N0H 2C0",
    "addr:housenumber":"273",
    "addr:postcode":"n0h 2c0",
    "addr:street":"Mill St",
    "iso:country":"CA",
    "sg:address":"273 Mill St",
    "sg:city":"Port Elgin",
    "sg:classifiers":[
        {
            "category":"Travel",
            "subcategory":"Hotels & Motels",
            "type":"Entertainment"
        }
    ],
    "sg:phone":"+1 519 389 5555",
    "sg:postcode":"N0H 2C0",
    "sg:province":"ON",
    "sg:tags":[
        "breakfast",
        "accommodation",
        "bed"
    ],
    "wof:name":"Franklin House Bed & Breakfast",
    "wof:placetype":"venue"
},
  "geometry": {"coordinates":[-81.398628,44.442066],"type":"Point"}
}