{
  "type": "Feature",
  "properties": {
    "addr:full":"Ottawa ON K2P 1W7",
    "addr:postcode":"k2p 1w7",
    "iso:country":"CA",
    "sg:city":"Ottawa",
    "sg:classifiers":[
        {
            "category":"Professional",
            "subcategory":"Accounting & Tax Preparation",
            "type":"Services"
        }
    ],
    "sg:phone":"+1 613 234 0598",
    "sg:postcode":"K2P 1W7",
    "sg:province":"ON",
    "sg:tags":[
        "consultant",
        "accountant",
        "planning",
        "financial"
    ],
    "wof:name":"Elliott, Daniel S CA",
    "wof:placetype":"venue"
},
  "geometry": {"coordinates":[-75.69818115229999,45.4177398682],"type":"Point"}
}