{
  "type": "Feature",
  "properties": {
    "addr:full":"Arviat NU X0C 0E0",
    "addr:postcode":"x0c 0e0",
    "iso:country":"CA",
    "sg:city":"Arviat",
    "sg:classifiers":[
        {
            "category":"Government",
            "subcategory":"Office",
            "type":"Public Place"
        }
    ],
    "sg:phone":"+1 867 857 2937",
    "sg:postcode":"X0C 0E0",
    "sg:province":"NU",
    "sg:tags":[
        "village"
    ],
    "wof:name":"Arviat Community Tv Dish",
    "wof:placetype":"venue"
},
  "geometry": {"coordinates":[-94.0589981079,61.1097068787],"type":"Point"}
}