{
  "type": "Feature",
  "properties": {
    "addr:full":"2730 Princess St Kingston ON K7P 2W6",
    "addr:housenumber":"2730",
    "addr:postcode":"k7p 2w6",
    "addr:street":"Princess St",
    "iso:country":"CA",
    "sg:address":"2730 Princess St",
    "sg:city":"Kingston",
    "sg:classifiers":[
        {
            "category":"Home & Garden",
            "subcategory":"Furniture",
            "type":"Retail Goods"
        }
    ],
    "sg:phone":"+1 613 384 2418",
    "sg:postcode":"K7P 2W6",
    "sg:province":"ON",
    "wof:name":"Leon's Furniture & Appliances",
    "wof:placetype":"venue"
},
  "geometry": {"coordinates":[-76.578789,44.259079],"type":"Point"}
}