{
  "type": "Feature",
  "properties": {
    "addr:full":"5361 Woodburn Rd Binbrook ON L0R 1C0",
    "addr:housenumber":"5361",
    "addr:postcode":"l0r 1c0",
    "addr:street":"Woodburn Rd",
    "iso:country":"CA",
    "sg:address":"5361 Woodburn Rd",
    "sg:city":"Binbrook",
    "sg:classifiers":[
        {
            "category":"Autos & Motor Vehicles",
            "subcategory":"Motorcycle Sales",
            "type":"Retail Goods"
        }
    ],
    "sg:phone":"+1 905 692 4721",
    "sg:postcode":"L0R 1C0",
    "sg:province":"ON",
    "sg:tags":[
        "car",
        "golf",
        "cart"
    ],
    "wof:name":"Niagara Golf Carts",
    "wof:placetype":"venue"
},
  "geometry": {"coordinates":[-79.80169677729999,43.1276855469],"type":"Point"}
}