{
  "type": "Feature",
  "properties": {
    "addr:full":"161 Av Champagnat Vanier QC G1M 3W4",
    "addr:postcode":"g1m 3w4",
    "addr:street":"161 Av Champagnat",
    "iso:country":"CA",
    "sg:address":"161 Av Champagnat",
    "sg:city":"Vanier",
    "sg:classifiers":[
        {
            "category":"Social Services",
            "subcategory":"Child Care",
            "type":"Services"
        }
    ],
    "sg:phone":"+1 418 527 8715",
    "sg:postcode":"G1M 3W4",
    "sg:province":"QC",
    "wof:name":"Cpe L'Essentiel",
    "wof:placetype":"venue"
},
  "geometry": {"coordinates":[-71.26219940190001,46.8114318848],"type":"Point"}
}