{
  "type": "Feature",
  "properties": {
    "addr:full":"10 Place Bourget S Joliette QC J6E 5E7",
    "addr:housenumber":"10",
    "addr:postcode":"j6e 5e7",
    "addr:street":"Place Bourget S",
    "iso:country":"CA",
    "sg:address":"10 Place Bourget S",
    "sg:city":"Joliette",
    "sg:classifiers":[
        {
            "category":"Shopping",
            "subcategory":"Clothing, Apparel, & Fashions",
            "type":"Retail Goods"
        }
    ],
    "sg:phone":"+1 450 753 5111",
    "sg:postcode":"J6E 5E7",
    "sg:province":"QC",
    "sg:tags":[
        "furnishing"
    ],
    "wof:name":"Claude Kid Nadeau Mercerie",
    "wof:placetype":"venue"
},
  "geometry": {"coordinates":[-73.43993399999999,46.024719],"type":"Point"}
}