{
  "type": "Feature",
  "properties": {
    "addr:full":"4702 50 Ave Camrose AB T4V 0R8",
    "addr:housenumber":"4702",
    "addr:postcode":"t4v 0r8",
    "addr:street":"50 Ave",
    "iso:country":"CA",
    "sg:address":"4702 50 Ave",
    "sg:city":"Camrose",
    "sg:classifiers":[
        {
            "category":"Recreation",
            "type":"Entertainment"
        }
    ],
    "sg:phone":"+1 780 672 7436",
    "sg:postcode":"T4V 0R8",
    "sg:province":"AB",
    "sg:tags":[
        "hall",
        "auditorium"
    ],
    "wof:name":"Elks Lodge 70",
    "wof:placetype":"venue"
},
  "geometry": {"coordinates":[-112.820381,53.021904],"type":"Point"}
}