{
  "type": "Feature",
  "properties": {
    "iso:country":"CA",
    "sg:address":"6605 Rue Jarry E",
    "sg:city":"Saint-Leonard",
    "sg:classifiers":[
        {
            "category":"Retail",
            "subcategory":"Car Wash",
            "type":"Services"
        }
    ],
    "sg:phone":"+1 514 321 3704",
    "sg:postcode":"H1P 1W5",
    "sg:province":"QC",
    "sg:tags":[
        "polishing",
        "washing"
    ],
    "wof:name":"Lave-Auto Jarry Enr",
    "wof:placetype":"venue"
},
  "geometry": {"coordinates":[-73.58080291749999,45.5958938599],"type":"Point"}
}