{
  "type": "Feature",
  "properties": {
    "iso:country":"CA",
    "sg:address":"441 St Mary's Rd",
    "sg:city":"Winnipeg",
    "sg:classifiers":[
        {
            "category":"Home & Garden",
            "subcategory":"Carpets & Floor Coverings",
            "type":"Retail Goods"
        }
    ],
    "sg:phone":"+1 204 233 8158",
    "sg:postcode":"R2M 3K7",
    "sg:province":"MB",
    "sg:tags":[
        "material",
        "dealer",
        "rug"
    ],
    "wof:name":"Exclusive Carpets Ltd",
    "wof:placetype":"venue"
},
  "geometry": {"coordinates":[-97.14911651609999,49.8891181946],"type":"Point"}
}