{
  "type": "Feature",
  "properties": {
    "addr:full":"Shediac NB E4P 2A9",
    "addr:postcode":"e4p 2a9",
    "iso:country":"CA",
    "sg:city":"Shediac",
    "sg:classifiers":[
        {
            "category":"Home & Garden",
            "subcategory":"Hardware",
            "type":"Retail Goods"
        }
    ],
    "sg:phone":"+1 506 532 5170",
    "sg:postcode":"E4P 2A9",
    "sg:province":"NB",
    "wof:name":"Shediac Home Hardware",
    "wof:placetype":"venue"
},
  "geometry": {"coordinates":[-64.5482788086,46.2191085815],"type":"Point"}
}