{
  "type": "Feature",
  "properties": {
    "addr:full":"165 Iber Rd Stittsville ON K2S 1E7",
    "addr:housenumber":"165",
    "addr:postcode":"k2s 1e7",
    "addr:street":"Iber Rd",
    "iso:country":"CA",
    "sg:address":"165 Iber Rd",
    "sg:city":"Stittsville",
    "sg:classifiers":[
        {
            "category":"Freight",
            "type":"Transportation"
        }
    ],
    "sg:phone":"+1 613 831 4734",
    "sg:postcode":"K2S 1E7",
    "sg:province":"ON",
    "sg:tags":[
        "mover"
    ],
    "wof:name":"Campbell Moving Systems Inc",
    "wof:placetype":"venue"
},
  "geometry": {"coordinates":[-75.90152740480001,45.2747955322],"type":"Point"}
}