{
  "type": "Feature",
  "properties": {
    "addr:full":"Grande Prairie AB T8V 2V4",
    "addr:postcode":"t8v 2v4",
    "iso:country":"CA",
    "sg:city":"Grande Prairie",
    "sg:classifiers":[
        {
            "category":"Professional",
            "subcategory":"Accounting & Tax Preparation",
            "type":"Services"
        }
    ],
    "sg:phone":"+1 780 831 1700",
    "sg:postcode":"T8V 2V4",
    "sg:province":"AB",
    "sg:tags":[
        "accountant"
    ],
    "wof:name":"Meyers Norris Penny & CO",
    "wof:placetype":"venue"
},
  "geometry": {"coordinates":[-118.801125,55.169952],"type":"Point"}
}