{
  "type": "Feature",
  "properties": {
    "addr:full":"1856 Angus St Regina SK S4T 1Z4",
    "addr:housenumber":"1856",
    "addr:postcode":"s4t 1z4",
    "addr:street":"Angus St",
    "iso:country":"CA",
    "sg:address":"1856 Angus St",
    "sg:city":"Regina",
    "sg:classifiers":[
        {
            "category":"Professional",
            "subcategory":"Computer Services",
            "type":"Services"
        }
    ],
    "sg:phone":"+1 306 522 7827",
    "sg:postcode":"S4T 1Z4",
    "sg:province":"SK",
    "sg:tags":[
        "consultant"
    ],
    "wof:name":"Allstar Technologies Canada",
    "wof:placetype":"venue"
},
  "geometry": {"coordinates":[-104.61983499999999,50.449493],"type":"Point"}
}