{
  "type": "Feature",
  "properties": {
    "addr:full":"339 First St Midland ON L4R 3P3",
    "addr:housenumber":"339",
    "addr:postcode":"l4r 3p3",
    "addr:street":"First St",
    "iso:country":"CA",
    "sg:address":"339 First St",
    "sg:city":"Midland",
    "sg:classifiers":[
        {
            "category":"Taxi",
            "type":"Transportation"
        }
    ],
    "sg:phone":"+1 705 526 5461",
    "sg:postcode":"L4R 3P3",
    "sg:province":"ON",
    "sg:tags":[
        "taxicab"
    ],
    "wof:name":"Ron's Taxi",
    "wof:placetype":"venue"
},
  "geometry": {"coordinates":[-79.885178,44.747772],"type":"Point"}
}