{
  "type": "Feature",
  "properties": {
    "iso:country":"CA",
    "sg:address":"Lot 7",
    "sg:city":"Bissett",
    "sg:classifiers":[
        {
            "category":"Building & Trades",
            "subcategory":"Construction",
            "type":"Services"
        }
    ],
    "sg:phone":"+1 204 277 5220",
    "sg:postcode":"R0E 0J0",
    "sg:province":"MB",
    "sg:tags":[
        "boring",
        "drilling",
        "contractor"
    ],
    "wof:name":"Wynne Drilling Ltd",
    "wof:placetype":"venue"
},
  "geometry": {"coordinates":[-95.65171813960001,51.0265007019],"type":"Point"}
}