{
  "type": "Feature",
  "properties": {
    "addr:full":"3969 Montrose Rd # 3 Niagara Falls ON L2H 3A1",
    "addr:housenumber":"3969",
    "addr:postcode":"l2h 3a1",
    "addr:street":"Montrose Rd # 3",
    "iso:country":"CA",
    "sg:address":"3969 Montrose Rd # 3",
    "sg:city":"Niagara Falls",
    "sg:classifiers":[
        {
            "category":"Food & Beverages",
            "subcategory":"Bakery",
            "type":"Retail Goods"
        }
    ],
    "sg:phone":"+1 905 353 1121",
    "sg:postcode":"L2H 3A1",
    "sg:province":"ON",
    "sg:tags":[
        "doughnut"
    ],
    "wof:name":"Donut Diner Cafe",
    "wof:placetype":"venue"
},
  "geometry": {"coordinates":[-79.1248474121,43.1151580811],"type":"Point"}
}