{
  "type": "Feature",
  "properties": {
    "addr:full":"35 Van Horne Ave # 100 Dryden ON P8N 3B4",
    "addr:housenumber":"35",
    "addr:postcode":"p8n 3b4",
    "addr:street":"Van Horne Ave # 100",
    "iso:country":"CA",
    "sg:address":"35 Van Horne Ave # 100",
    "sg:city":"Dryden",
    "sg:classifiers":[
        {
            "category":"Social Services",
            "type":"Services"
        }
    ],
    "sg:phone":"+1 807 223 5278",
    "sg:postcode":"P8N 3B4",
    "sg:province":"ON",
    "sg:tags":[
        "senior",
        "citizen"
    ],
    "wof:name":"Patricia Region Senior Svc Inc",
    "wof:placetype":"venue"
},
  "geometry": {"coordinates":[-92.8361282349,49.7836036682],"type":"Point"}
}