{
  "type": "Feature",
  "properties": {
    "addr:full":"146 Kingston St Victoria BC V8V 1V4",
    "addr:housenumber":"146",
    "addr:postcode":"v8v 1v4",
    "addr:street":"Kingston St",
    "iso:country":"CA",
    "sg:address":"146 Kingston St",
    "sg:city":"Victoria",
    "sg:classifiers":[
        {
            "category":"Ferry",
            "type":"Transportation"
        }
    ],
    "sg:phone":"+1 250 383 2254",
    "sg:postcode":"V8V 1V4",
    "sg:province":"BC",
    "sg:tags":[
        "whale",
        "watching"
    ],
    "wof:name":"Seacoast Expeditions Ltd",
    "wof:placetype":"venue"
},
  "geometry": {"coordinates":[-123.379768,48.422005],"type":"Point"}
}