{
  "type": "Feature",
  "properties": {
    "addr:full":"7199 Rue Boyer Montreal QC H2R 2R6",
    "addr:housenumber":"7199",
    "addr:postcode":"h2r 2r6",
    "addr:street":"Rue Boyer",
    "iso:country":"CA",
    "sg:address":"7199 Rue Boyer",
    "sg:city":"Montreal",
    "sg:classifiers":[
        {
            "category":"Professional",
            "subcategory":"Business Services",
            "type":"Services"
        }
    ],
    "sg:phone":"+1 514 953 0546",
    "sg:postcode":"H2R 2R6",
    "sg:province":"QC",
    "sg:tags":[
        "inspection"
    ],
    "wof:name":"Sylvain Dionne Enr",
    "wof:placetype":"venue"
},
  "geometry": {"coordinates":[-73.6134262085,45.5421905518],"type":"Point"}
}