{
  "type": "Feature",
  "properties": {
    "addr:full":"395 Whiteridge Cres NE Calgary AB T1Y 2Y9",
    "addr:housenumber":"395",
    "addr:postcode":"t1y 2y9",
    "addr:street":"Whiteridge Cres Ne",
    "iso:country":"CA",
    "sg:address":"395 Whiteridge Cres NE",
    "sg:city":"Calgary",
    "sg:classifiers":[
        {
            "category":"Mining & Drilling",
            "type":"Manufacturing & Wholesale Goods"
        }
    ],
    "sg:phone":"+1 403 293 5489",
    "sg:postcode":"T1Y 2Y9",
    "sg:province":"AB",
    "sg:tags":[
        "consultant",
        "oil",
        "gas"
    ],
    "wof:name":"Bohdan Consulting Ltd",
    "wof:placetype":"venue"
},
  "geometry": {"coordinates":[-113.965431,51.091511],"type":"Point"}
}