{
  "type": "Feature",
  "properties": {
    "iso:country":"CA",
    "sg:city":"Kitchener",
    "sg:classifiers":[
        {
            "category":"Wholesale",
            "subcategory":"Machinery & Supplies",
            "type":"Manufacturing & Wholesale Goods"
        }
    ],
    "sg:phone":"+1 519 741 9600",
    "sg:postcode":"N2H 5X8",
    "sg:province":"ON",
    "sg:tags":[
        "janitor"
    ],
    "wof:name":"Ralston Distributors on Ltd",
    "wof:placetype":"venue"
},
  "geometry": {"coordinates":[-80.4759902954,43.4668769836],"type":"Point"}
}