{
  "type": "Feature",
  "properties": {
    "addr:full":"332 Great Northern Rd Sault Ste Marie ON P6B 4Z7",
    "addr:housenumber":"332",
    "addr:postcode":"p6b 4z7",
    "addr:street":"Great Northern Rd",
    "iso:country":"CA",
    "sg:address":"332 Great Northern Rd",
    "sg:city":"Sault Ste Marie",
    "sg:classifiers":[
        {
            "category":"Restaurant",
            "type":"Food & Drink"
        }
    ],
    "sg:phone":"+1 705 256 2677",
    "sg:postcode":"P6B 4Z7",
    "sg:province":"ON",
    "wof:name":"Swiss Chalet Rotisserie/Grill",
    "wof:placetype":"venue"
},
  "geometry": {"coordinates":[-84.31870269780001,46.5356330872],"type":"Point"}
}