{
  "type": "Feature",
  "properties": {
    "addr:full":"545 Donald B Munro Dr Carp ON K0A 1L0",
    "addr:housenumber":"545",
    "addr:postcode":"k0a 1l0",
    "addr:street":"Donald B Munro Dr",
    "iso:country":"CA",
    "sg:address":"545 Donald B Munro Dr",
    "sg:city":"Carp",
    "sg:classifiers":[
        {
            "category":"Home & Garden",
            "subcategory":"Hardware",
            "type":"Retail Goods"
        }
    ],
    "sg:phone":"+1 613 839 3467",
    "sg:postcode":"K0A 1L0",
    "sg:province":"ON",
    "wof:name":"Deka Builders & Supplies Ltd",
    "wof:placetype":"venue"
},
  "geometry": {"coordinates":[-76.04306800000001,45.342556],"type":"Point"}
}