{
  "type": "Feature",
  "properties": {
    "iso:country":"CA",
    "sg:address":"6457 Montrose Rd",
    "sg:city":"Niagara Falls",
    "sg:classifiers":[
        {
            "category":"Organizations",
            "subcategory":"Religious Organization",
            "type":"Services"
        }
    ],
    "sg:phone":"+1 905 374 3866",
    "sg:postcode":"L2H 1M1",
    "sg:province":"ON",
    "sg:tags":[
        "church"
    ],
    "wof:name":"Jehovah's Witnesses Kingdom",
    "wof:placetype":"venue"
},
  "geometry": {"coordinates":[-79.1231842041,43.081451416],"type":"Point"}
}