{
  "type": "Feature",
  "properties": {
    "addr:full":"45 Dean Ave Sudbury ON P3C 3B8",
    "addr:housenumber":"45",
    "addr:postcode":"p3c 3b8",
    "addr:street":"Dean Ave",
    "iso:country":"CA",
    "sg:address":"45 Dean Ave",
    "sg:city":"Sudbury",
    "sg:classifiers":[
        {
            "category":"Professional",
            "subcategory":"Accounting & Tax Preparation",
            "type":"Services"
        }
    ],
    "sg:phone":"+1 705 674 9713",
    "sg:postcode":"P3C 3B8",
    "sg:province":"ON",
    "sg:tags":[
        "bookkeeping",
        "return",
        "filing",
        "general"
    ],
    "wof:name":"C & L Bookkeeping Svc",
    "wof:placetype":"venue"
},
  "geometry": {"coordinates":[-81.03012099999999,46.473911],"type":"Point"}
}