{
  "type": "Feature",
  "properties": {
    "addr:full":"685 W Hwy 16 Burns Lake BC V0J 1E0",
    "addr:housenumber":"685",
    "addr:postcode":"v0j 1e0",
    "addr:street":"W Hwy 16 Burns",
    "iso:country":"CA",
    "sg:address":"685 W Hwy 16",
    "sg:city":"Burns Lake",
    "sg:classifiers":[
        {
            "category":"Education",
            "subcategory":"School",
            "type":"Public Place"
        }
    ],
    "sg:phone":"+1 250 692 4338",
    "sg:postcode":"V0J 1E0",
    "sg:province":"BC",
    "wof:name":"Learning Centre",
    "wof:placetype":"venue"
},
  "geometry": {"coordinates":[-125.765396,54.233727],"type":"Point"}
}