{
  "type": "Feature",
  "properties": {
    "addr:full":"107 S Railway Ave Balcarres SK S0G 0C0",
    "addr:housenumber":"107",
    "addr:postcode":"s0g 0c0",
    "addr:street":"S Railway Ave",
    "iso:country":"CA",
    "sg:address":"107 S Railway Ave",
    "sg:city":"Balcarres",
    "sg:classifiers":[
        {
            "category":"Wholesale",
            "subcategory":"Farm Supplies",
            "type":"Manufacturing & Wholesale Goods"
        }
    ],
    "sg:phone":"+1 306 334 2455",
    "sg:postcode":"S0G 0C0",
    "sg:province":"SK",
    "sg:tags":[
        "oil"
    ],
    "wof:name":"Petro-Canada",
    "wof:placetype":"venue"
},
  "geometry": {"coordinates":[-103.54782104500001,50.798160553],"type":"Point"}
}