{
  "type": "Feature",
  "properties": {
    "addr:full":"3050 King George Hwy Surrey BC V4P 1A2",
    "addr:housenumber":"3050",
    "addr:postcode":"v4p 1a2",
    "addr:street":"King George Hwy",
    "iso:country":"CA",
    "sg:address":"3050 King George Hwy",
    "sg:city":"Surrey",
    "sg:classifiers":[
        {
            "category":"Autos & Motor Vehicles",
            "subcategory":"Automobile Sales",
            "type":"Retail Goods"
        }
    ],
    "sg:phone":"+1 604 531 8804",
    "sg:postcode":"V4P 1A2",
    "sg:province":"BC",
    "sg:tags":[
        "car",
        "dealer"
    ],
    "wof:name":"Ocean Park Ford Sales",
    "wof:placetype":"venue"
},
  "geometry": {"coordinates":[-122.80805206300001,49.0575065613],"type":"Point"}
}