{
  "type": "Feature",
  "properties": {
    "addr:full":"180 Av Principale Rouyn-Noranda QC J9X 4P8",
    "addr:housenumber":"180",
    "addr:postcode":"j9x 4p8",
    "addr:street":"Av Principale",
    "iso:country":"CA",
    "sg:address":"180 Av Principale",
    "sg:city":"Rouyn-Noranda",
    "sg:classifiers":[
        {
            "category":"Government",
            "subcategory":"Office",
            "type":"Public Place"
        }
    ],
    "sg:phone":"+1 819 763 3759",
    "sg:postcode":"J9X 4P8",
    "sg:province":"QC",
    "wof:name":"Quebec Societe DE Financement",
    "wof:placetype":"venue"
},
  "geometry": {"coordinates":[-79.02015686039999,48.2381324768],"type":"Point"}
}