{
  "type": "Feature",
  "properties": {
    "addr:full":"5552 George St Niagara Falls ON L2E 3E2",
    "addr:housenumber":"5552",
    "addr:postcode":"l2e 3e2",
    "addr:street":"George St",
    "iso:country":"CA",
    "sg:address":"5552 George St",
    "sg:city":"Niagara Falls",
    "sg:classifiers":[
        {
            "category":"Retail",
            "subcategory":"Auto Repair",
            "type":"Services"
        }
    ],
    "sg:phone":"+1 905 357 0232",
    "sg:postcode":"L2E 3E2",
    "sg:province":"ON",
    "sg:tags":[
        "repairing",
        "automobile"
    ],
    "wof:name":"Niagara High Tech Auto Repair",
    "wof:placetype":"venue"
},
  "geometry": {"coordinates":[-79.0866241455,43.1132507324],"type":"Point"}
}