{
  "type": "Feature",
  "properties": {
    "addr:full":"18 Ontario Rue Notre-Dame-Du-Nord QC J0Z 3B0",
    "addr:housenumber":"18",
    "addr:postcode":"j0z 3b0",
    "addr:street":"Ontario Rue",
    "iso:country":"CA",
    "sg:address":"18 Ontario Rue",
    "sg:city":"Notre-Dame-Du-Nord",
    "sg:classifiers":[
        {
            "category":"Professional",
            "subcategory":"Business Services",
            "type":"Services"
        }
    ],
    "sg:phone":"+1 819 723 2411",
    "sg:postcode":"J0Z 3B0",
    "sg:province":"QC",
    "sg:tags":[
        "estate"
    ],
    "wof:name":"Jolette & Drolet",
    "wof:placetype":"venue"
},
  "geometry": {"coordinates":[-79.486153,47.593418],"type":"Point"}
}