{
  "type": "Feature",
  "properties": {
    "addr:full":"95 Lombard St # 1305 Toronto ON M5C 2V3",
    "addr:housenumber":"95",
    "addr:postcode":"m5c 2v3",
    "addr:street":"Lombard St # 1305",
    "iso:country":"CA",
    "sg:address":"95 Lombard St # 1305",
    "sg:city":"Toronto",
    "sg:classifiers":[
        {
            "category":"Professional",
            "subcategory":"Management & Consulting",
            "type":"Services"
        }
    ],
    "sg:phone":"+1 416 306 2243",
    "sg:postcode":"M5C 2V3",
    "sg:province":"ON",
    "sg:tags":[
        "consultant",
        "resource",
        "human"
    ],
    "wof:name":"Lynne Sullivan & Assoc Inc",
    "wof:placetype":"venue"
},
  "geometry": {"coordinates":[-79.3742980957,43.6518707275],"type":"Point"}
}