{
  "type": "Feature",
  "properties": {
    "addr:full":"74 Broadway Corner Brook NL A2H 4C8",
    "addr:housenumber":"74",
    "addr:postcode":"a2h 4c8",
    "addr:street":"Broadway",
    "iso:country":"CA",
    "sg:address":"74 Broadway",
    "sg:city":"Corner Brook",
    "sg:classifiers":[
        {
            "category":"Shopping",
            "subcategory":"Jewelry",
            "type":"Retail Goods"
        }
    ],
    "sg:phone":"+1 709 639 9286",
    "sg:postcode":"A2H 4C8",
    "sg:province":"NL",
    "sg:tags":[
        "jeweler"
    ],
    "wof:name":"Alteen's Jewellers",
    "wof:placetype":"venue"
},
  "geometry": {"coordinates":[-57.955581665,48.952709198],"type":"Point"}
}