{
  "type": "Feature",
  "properties": {
    "addr:full":"1593 Argyle St Halifax NS B3J 2B2",
    "addr:housenumber":"1593",
    "addr:postcode":"ns b3j 2b2",
    "addr:street":"Argyle St",
    "iso:country":"CA",
    "sg:address":"1593 Argyle St",
    "sg:city":"Halifax",
    "sg:classifiers":[
        {
            "category":"Cinema",
            "subcategory":"Movie Theater",
            "type":"Entertainment"
        }
    ],
    "sg:phone":"+1 902 429 7300",
    "sg:postcode":"B3J 2B2",
    "sg:province":"NS",
    "sg:tags":[
        "charitable",
        "institution"
    ],
    "wof:name":"Neptune Theatre",
    "wof:placetype":"venue"
},
  "geometry": {"coordinates":[-63.574028,44.645966],"type":"Point"}
}