{
  "type": "Feature",
  "properties": {
    "addr:full":"Orillia ON L3V 6H4",
    "addr:postcode":"l3v 6h4",
    "iso:country":"CA",
    "sg:city":"Orillia",
    "sg:classifiers":[
        {
            "category":"Personal",
            "subcategory":"Beauty Salon",
            "type":"Services"
        }
    ],
    "sg:phone":"+1 705 325 9237",
    "sg:postcode":"L3V 6H4",
    "sg:province":"ON",
    "wof:name":"Studio Esthetics",
    "wof:placetype":"venue"
},
  "geometry": {"coordinates":[-79.41822814939999,44.606590271],"type":"Point"}
}