{
  "type": "Feature",
  "properties": {
    "addr:full":"356 10 St N Lethbridge AB T1H 2C7",
    "addr:housenumber":"356 10",
    "addr:postcode":"t1h 2c7",
    "iso:country":"CA",
    "sg:address":"356 10 St N",
    "sg:city":"Lethbridge",
    "sg:classifiers":[
        {
            "category":"Retail",
            "subcategory":"Repair Shop",
            "type":"Services"
        }
    ],
    "sg:phone":"+1 403 327 4333",
    "sg:postcode":"T1H 2C7",
    "sg:province":"AB",
    "sg:tags":[
        "refinishing",
        "furniture"
    ],
    "wof:name":"Triangle Woods Products Ltd",
    "wof:placetype":"venue"
},
  "geometry": {"coordinates":[-112.832588196,49.7038917542],"type":"Point"}
}