{
  "type": "Feature",
  "properties": {
    "addr:full":"24 Regina St N Waterloo ON N2J 3A1",
    "addr:housenumber":"24",
    "addr:postcode":"n2j 3a1",
    "addr:street":"Regina St N",
    "iso:country":"CA",
    "sg:address":"24 Regina St N",
    "sg:city":"Waterloo",
    "sg:classifiers":[
        {
            "category":"Shopping",
            "subcategory":"Books",
            "type":"Retail Goods"
        }
    ],
    "sg:phone":"+1 519 725 2681",
    "sg:postcode":"N2J 3A1",
    "sg:province":"ON",
    "sg:tags":[
        "dealer"
    ],
    "wof:name":"Hollyoak",
    "wof:placetype":"venue"
},
  "geometry": {"coordinates":[-80.52142333979999,43.4665679932],"type":"Point"}
}