{
  "type": "Feature",
  "properties": {
    "addr:full":"45 Oregon Dr Stephenville NL A2N 2X7",
    "addr:housenumber":"45",
    "addr:postcode":"a2n 2x7",
    "addr:street":"Oregon Dr",
    "iso:country":"CA",
    "sg:address":"45 Oregon Dr",
    "sg:city":"Stephenville",
    "sg:classifiers":[
        {
            "category":"Organizations",
            "subcategory":"Professional Association",
            "type":"Services"
        }
    ],
    "sg:phone":"+1 709 643 2077",
    "sg:postcode":"A2N 2X7",
    "sg:province":"NL",
    "sg:tags":[
        "club"
    ],
    "wof:name":"Royal Canadian Legion",
    "wof:placetype":"venue"
},
  "geometry": {"coordinates":[-58.5591468811,48.5492362976],"type":"Point"}
}