{
  "type": "Feature",
  "properties": {
    "addr:full":"6117 46A St Leduc AB T9E 7A6",
    "addr:housenumber":"6117",
    "addr:postcode":"t9e 7a6",
    "addr:street":"46A St",
    "iso:country":"CA",
    "sg:address":"6117 46A St",
    "sg:city":"Leduc",
    "sg:classifiers":[
        {
            "category":"Freight",
            "type":"Transportation"
        }
    ],
    "sg:phone":"+1 780 986 8484",
    "sg:postcode":"T9E 7A6",
    "sg:province":"AB",
    "sg:tags":[
        "mover",
        "trucking"
    ],
    "wof:name":"Leduc Moving & Storage",
    "wof:placetype":"venue"
},
  "geometry": {"coordinates":[-113.548568726,53.2593765259],"type":"Point"}
}