{
  "type": "Feature",
  "properties": {
    "addr:full":"665 Justus Dr Kingston ON K7M 4H5",
    "addr:housenumber":"665",
    "addr:postcode":"k7m 4h5",
    "addr:street":"Justus Dr",
    "iso:country":"CA",
    "sg:address":"665 Justus Dr",
    "sg:city":"Kingston",
    "sg:classifiers":[
        {
            "category":"Manufacturing",
            "subcategory":"Tools & Machinery",
            "type":"Manufacturing & Wholesale Goods"
        }
    ],
    "sg:phone":"+1 613 634 2094",
    "sg:postcode":"K7M 4H5",
    "sg:province":"ON",
    "sg:tags":[
        "steel",
        "machine",
        "shop"
    ],
    "wof:name":"Bgm Metal Works",
    "wof:placetype":"venue"
},
  "geometry": {"coordinates":[-76.5725402832,44.2455368042],"type":"Point"}
}