{
  "type": "Feature",
  "properties": {
    "addr:full":"Lebret SK S0G 2Y0",
    "addr:postcode":"s0g 2y0",
    "addr:street":"Lebret Sk",
    "iso:country":"CA",
    "sg:city":"Lebret",
    "sg:classifiers":[
        {
            "category":"Government",
            "subcategory":"Office",
            "type":"Public Place"
        }
    ],
    "sg:phone":"+1 306 332 5839",
    "sg:postcode":"S0G 2Y0",
    "sg:province":"SK",
    "sg:tags":[
        "village"
    ],
    "wof:name":"Lebret Work Shop",
    "wof:placetype":"venue"
},
  "geometry": {"coordinates":[-103.70463599999999,50.757671],"type":"Point"}
}