{
  "type": "Feature",
  "properties": {
    "iso:country":"CA",
    "sg:address":"356 Av Fairmount O",
    "sg:city":"Montreal",
    "sg:classifiers":[
        {
            "category":"Wholesale",
            "subcategory":"Meat",
            "type":"Manufacturing & Wholesale Goods"
        }
    ],
    "sg:phone":"+1 514 273 2600",
    "sg:postcode":"H2V 2G4",
    "sg:province":"QC",
    "sg:tags":[
        "butchering"
    ],
    "wof:name":"New Omonoia Fish & Meat Mkt",
    "wof:placetype":"venue"
},
  "geometry": {"coordinates":[-73.597603,45.520027],"type":"Point"}
}