{
  "type": "Feature",
  "properties": {
    "addr:full":"6249 205 St #103 Langley BC V2Y 1N7",
    "addr:housenumber":"6249",
    "addr:postcode":"v2y 1n7",
    "addr:street":"205 St # 103",
    "iso:country":"CA",
    "sg:address":"6249 205 St #103",
    "sg:city":"Langley",
    "sg:classifiers":[
        {
            "category":"Wholesale",
            "subcategory":"Groceries",
            "type":"Manufacturing & Wholesale Goods"
        }
    ],
    "sg:phone":"+1 604 626 0606",
    "sg:postcode":"V2Y 1N7",
    "sg:province":"BC",
    "sg:tags":[
        "food",
        "product",
        "health"
    ],
    "wof:name":"Nutraforce International Inc",
    "wof:placetype":"venue"
},
  "geometry": {"coordinates":[-122.65464782700001,49.1157913208],"type":"Point"}
}