{
  "type": "Feature",
  "properties": {
    "addr:full":"Vancouver BC V6Z 2N2",
    "addr:postcode":"v6z 2n2",
    "iso:country":"CA",
    "sg:city":"Vancouver",
    "sg:classifiers":[
        {
            "category":"Education",
            "subcategory":"Special Training",
            "type":"Public Place"
        }
    ],
    "sg:phone":"+1 604 899 4480",
    "sg:postcode":"V6Z 2N2",
    "sg:province":"BC",
    "sg:tags":[
        "school",
        "language"
    ],
    "wof:name":"Tamwood International College",
    "wof:placetype":"venue"
},
  "geometry": {"coordinates":[-123.12457999999999,49.282238],"type":"Point"}
}