{
  "type": "Feature",
  "properties": {
    "addr:full":"155 Winges Rd # 8 Woodbridge ON L4L 6C7",
    "addr:housenumber":"155",
    "addr:postcode":"l4l 6c7",
    "addr:street":"Winges Rd # 8",
    "iso:country":"CA",
    "sg:address":"155 Winges Rd # 8",
    "sg:city":"Woodbridge",
    "sg:classifiers":[
        {
            "category":"Home & Garden",
            "subcategory":"Furniture",
            "type":"Retail Goods"
        }
    ],
    "sg:phone":"+1 905 856 5427",
    "sg:postcode":"L4L 6C7",
    "sg:province":"ON",
    "wof:name":"F & B Importing & Furniture",
    "wof:placetype":"venue"
},
  "geometry": {"coordinates":[-79.551659,43.787102],"type":"Point"}
}