{
  "type": "Feature",
  "properties": {
    "iso:country":"CA",
    "sg:city":"Waterville Carleton CO",
    "sg:classifiers":[
        {
            "category":"Building & Trades",
            "subcategory":"Electrical",
            "type":"Services"
        }
    ],
    "sg:phone":"+1 506 375 6531",
    "sg:postcode":"E7P 1B4",
    "sg:province":"NB",
    "sg:tags":[
        "electric",
        "contractor"
    ],
    "wof:name":"Anderson Electric 2006 Ltd",
    "wof:placetype":"venue"
},
  "geometry": {"coordinates":[-67.5839538574,46.2647705078],"type":"Point"}
}