{
  "type": "Feature",
  "properties": {
    "addr:full":"1302 College Dr Saskatoon SK S7N 0W5",
    "addr:housenumber":"1302",
    "addr:postcode":"s7n 0w5",
    "addr:street":"College Dr",
    "iso:country":"CA",
    "sg:address":"1302 College Dr",
    "sg:city":"Saskatoon",
    "sg:classifiers":[
        {
            "category":"Organizations",
            "subcategory":"Religious Organization",
            "type":"Services"
        }
    ],
    "sg:phone":"+1 306 653 2509",
    "sg:postcode":"S7N 0W5",
    "sg:province":"SK",
    "sg:tags":[
        "church"
    ],
    "wof:name":"Lutheran Campus Ctr",
    "wof:placetype":"venue"
},
  "geometry": {"coordinates":[-106.63861084,52.128692627],"type":"Point"}
}