{
  "type": "Feature",
  "properties": {
    "addr:full":"Cornwall PE C0A 1H0",
    "addr:postcode":"c0a 1h0",
    "iso:country":"CA",
    "sg:city":"Cornwall",
    "sg:classifiers":[
        {
            "category":"Shopping",
            "subcategory":"Florist",
            "type":"Retail Goods"
        }
    ],
    "sg:phone":"+1 902 368 7170",
    "sg:postcode":"C0A 1H0",
    "sg:province":"PE",
    "wof:name":"Bouquets & Baskets",
    "wof:placetype":"venue"
},
  "geometry": {"coordinates":[-63.218075,46.22768],"type":"Point"}
}