{
  "type": "Feature",
  "properties": {
    "addr:full":"Richmond BC V6V 2J5",
    "addr:postcode":"v6v 2j5",
    "iso:country":"CA",
    "sg:city":"Richmond",
    "sg:classifiers":[
        {
            "category":"Wholesale",
            "subcategory":"Computers",
            "type":"Manufacturing & Wholesale Goods"
        }
    ],
    "sg:phone":"+1 604 232 3981",
    "sg:postcode":"V6V 2J5",
    "sg:province":"BC",
    "wof:name":"Allway Technologies Inc",
    "wof:placetype":"venue"
},
  "geometry": {"coordinates":[-123.073425,49.186832],"type":"Point"}
}