{
  "type": "Feature",
  "properties": {
    "addr:full":"Mississauga ON L5T 2J8",
    "addr:postcode":"l5t 2j8",
    "iso:country":"CA",
    "sg:city":"Mississauga",
    "sg:classifiers":[
        {
            "category":"Building & Trades",
            "subcategory":"Construction",
            "type":"Services"
        }
    ],
    "sg:phone":"+1 905 670 7707",
    "sg:postcode":"L5T 2J8",
    "sg:province":"ON",
    "sg:tags":[
        "contractor"
    ],
    "wof:name":"Gana Contracting Inc",
    "wof:placetype":"venue"
},
  "geometry": {"coordinates":[-79.6853027344,43.6654014587],"type":"Point"}
}