{
  "type": "Feature",
  "properties": {
    "addr:full":"Toronto ON M4S 2C6",
    "addr:postcode":"m4s 2c6",
    "iso:country":"CA",
    "sg:city":"Toronto",
    "sg:classifiers":[
        {
            "category":"Shopping",
            "type":"Retail Goods"
        }
    ],
    "sg:phone":"+1 416 932 3852",
    "sg:postcode":"M4S 2C6",
    "sg:province":"ON",
    "sg:tags":[
        "clothing",
        "cosmetic"
    ],
    "wof:name":"City Looks",
    "wof:placetype":"venue"
},
  "geometry": {"coordinates":[-79.3982009888,43.7050056458],"type":"Point"}
}