{
  "type": "Feature",
  "properties": {
    "iso:country":"CA",
    "sg:address":"469 Mcnicoll Ave",
    "sg:city":"North York",
    "sg:classifiers":[
        {
            "category":"Wholesale",
            "subcategory":"Computers",
            "type":"Manufacturing & Wholesale Goods"
        }
    ],
    "sg:phone":"+1 416 498 3633",
    "sg:postcode":"M2H 2C9",
    "sg:province":"ON",
    "wof:name":"Mega Power Computing Tech",
    "wof:placetype":"venue"
},
  "geometry": {"coordinates":[-79.34075927729999,43.8034896851],"type":"Point"}
}