{
  "type": "Feature",
  "properties": {
    "iso:country":"CA",
    "sg:address":"1064 Dundas St",
    "sg:city":"London",
    "sg:classifiers":[
        {
            "category":"Personal",
            "subcategory":"Barber",
            "type":"Services"
        }
    ],
    "sg:phone":"+1 519 453 9433",
    "sg:postcode":"N5W 3A6",
    "sg:province":"ON",
    "wof:name":"Armand's Barber Shop",
    "wof:placetype":"venue"
},
  "geometry": {"coordinates":[-81.215668,42.993534],"type":"Point"}
}