{
  "type": "Feature",
  "properties": {
    "addr:full":"5545 Ladner Trunk Rd Delta BC V4K 1X1",
    "addr:housenumber":"5545",
    "addr:postcode":"v4k 1x1",
    "addr:street":"Ladner Trunk Rd",
    "iso:country":"CA",
    "sg:address":"5545 Ladner Trunk Rd",
    "sg:city":"Delta",
    "sg:classifiers":[
        {
            "category":"Social Services",
            "subcategory":"Child Care",
            "type":"Services"
        }
    ],
    "sg:phone":"+1 604 940 8077",
    "sg:postcode":"V4K 1X1",
    "sg:province":"BC",
    "wof:name":"Creation Station Daycare",
    "wof:placetype":"venue"
},
  "geometry": {"coordinates":[-123.069656372,49.0903968811],"type":"Point"}
}