{
  "type": "Feature",
  "properties": {
    "addr:full":"35 Queen St Harrow ON N0R 1G0",
    "addr:housenumber":"35",
    "addr:postcode":"n0r 1g0",
    "addr:street":"Queen St",
    "iso:country":"CA",
    "sg:address":"35 Queen St",
    "sg:city":"Harrow",
    "sg:classifiers":[
        {
            "category":"Personal",
            "subcategory":"Beauty Salon",
            "type":"Services"
        }
    ],
    "sg:phone":"+1 519 738 3101",
    "sg:postcode":"N0R 1G0",
    "sg:province":"ON",
    "wof:name":"Hairline Unisex",
    "wof:placetype":"venue"
},
  "geometry": {"coordinates":[-82.91832700000001,42.035973],"type":"Point"}
}