{
  "type": "Feature",
  "properties": {
    "addr:full":"Toronto ON M5G 1K2",
    "addr:postcode":"m5g 1k2",
    "iso:country":"CA",
    "sg:city":"Toronto",
    "sg:classifiers":[
        {
            "category":"Shopping",
            "subcategory":"Photographic Equipment",
            "type":"Retail Goods"
        }
    ],
    "sg:phone":"+1 416 977 2132",
    "sg:postcode":"M5G 1K2",
    "sg:province":"ON",
    "wof:name":"Kominek Camera & Optical Rpr",
    "wof:placetype":"venue"
},
  "geometry": {"coordinates":[-79.3843612671,43.6612319946],"type":"Point"}
}