{
  "type": "Feature",
  "properties": {
    "iso:country":"CA",
    "sg:address":"4105 Boul Saint-Joseph",
    "sg:city":"Drummondville",
    "sg:classifiers":[
        {
            "category":"Freight",
            "type":"Transportation"
        }
    ],
    "sg:phone":"+1 819 478 4483",
    "sg:postcode":"J2B 1T6",
    "sg:province":"QC",
    "sg:tags":[
        "trucking"
    ],
    "wof:name":"Transport Frechette Inc",
    "wof:placetype":"venue"
},
  "geometry": {"coordinates":[-72.45296478269999,45.8496894836],"type":"Point"}
}