{
  "type": "Feature",
  "properties": {
    "addr:full":"Mont-Saint-Gregoire QC J0J 1K0",
    "addr:postcode":"j0j 1k0",
    "iso:country":"CA",
    "sg:city":"Mont-Saint-Gregoire",
    "sg:classifiers":[
        {
            "category":"Building & Trades",
            "subcategory":"Construction",
            "type":"Services"
        }
    ],
    "sg:phone":"+1 450 347 7687",
    "sg:postcode":"J0J 1K0",
    "sg:province":"QC",
    "sg:tags":[
        "fixture",
        "bathroom",
        "remodeling",
        "accessory"
    ],
    "wof:name":"Bain-Magique St-Jean Enr",
    "wof:placetype":"venue"
},
  "geometry": {"coordinates":[-73.159874,45.336544],"type":"Point"}
}