{
  "type": "Feature",
  "properties": {
    "addr:full":"106 Rue Olivier Laurier-Station QC G0S 1N0",
    "addr:housenumber":"106",
    "addr:postcode":"g0s 1n0",
    "addr:street":"Rue Olivier",
    "iso:country":"CA",
    "sg:address":"106 Rue Olivier",
    "sg:city":"Laurier-Station",
    "sg:classifiers":[
        {
            "category":"Restaurant",
            "type":"Food & Drink"
        }
    ],
    "sg:phone":"+1 418 728 4834",
    "sg:postcode":"G0S 1N0",
    "sg:province":"QC",
    "wof:name":"Casse-Croute Marie-Jo",
    "wof:placetype":"venue"
},
  "geometry": {"coordinates":[-71.6331481934,46.5452423096],"type":"Point"}
}