{
  "type": "Feature",
  "properties": {
    "iso:country":"CA",
    "sg:address":"4715 Eleniak Rd NW",
    "sg:city":"Edmonton",
    "sg:classifiers":[
        {
            "category":"Manufacturing",
            "subcategory":"Glass & Minerals",
            "type":"Manufacturing & Wholesale Goods"
        }
    ],
    "sg:phone":"+1 780 468 6754",
    "sg:postcode":"T6B 2N1",
    "sg:province":"AB",
    "sg:tags":[
        "door"
    ],
    "wof:name":"C P Distributors Ltd",
    "wof:placetype":"venue"
},
  "geometry": {"coordinates":[-113.41352081300001,53.5018386841],"type":"Point"}
}