{
  "type": "Feature",
  "properties": {
    "addr:full":"434 Main St Penticton BC V2A 5C5",
    "addr:housenumber":"434",
    "addr:postcode":"v2a 5c5",
    "addr:street":"Main St",
    "iso:country":"CA",
    "sg:address":"434 Main St",
    "sg:city":"Penticton",
    "sg:classifiers":[
        {
            "category":"Professional",
            "subcategory":"Business Services",
            "type":"Services"
        }
    ],
    "sg:phone":"+1 250 492 3110",
    "sg:postcode":"V2A 5C5",
    "sg:province":"BC",
    "sg:tags":[
        "notary"
    ],
    "wof:name":"Binfet & CO",
    "wof:placetype":"venue"
},
  "geometry": {"coordinates":[-119.591148377,49.4966506958],"type":"Point"}
}