{
  "type": "Feature",
  "properties": {
    "addr:full":"Richmond BC V6V 1J8",
    "addr:postcode":"v6v 1j8",
    "iso:country":"CA",
    "sg:city":"Richmond",
    "sg:classifiers":[
        {
            "category":"Wholesale",
            "subcategory":"Groceries",
            "type":"Manufacturing & Wholesale Goods"
        }
    ],
    "sg:phone":"+1 604 273 8577",
    "sg:postcode":"V6V 1J8",
    "sg:province":"BC",
    "sg:tags":[
        "pet",
        "food"
    ],
    "wof:name":"Amore Pet Foods",
    "wof:placetype":"venue"
},
  "geometry": {"coordinates":[-123.088447571,49.1937294006],"type":"Point"}
}