{
  "type": "Feature",
  "properties": {
    "addr:full":"905 Av Munck Laval QC H7S 1A9",
    "addr:postcode":"h7s 1a9",
    "addr:street":"905 Av Munck",
    "iso:country":"CA",
    "sg:address":"905 Av Munck",
    "sg:city":"Laval",
    "sg:classifiers":[
        {
            "category":"Professional",
            "type":"Services"
        }
    ],
    "sg:phone":"+1 450 663 8052",
    "sg:postcode":"H7S 1A9",
    "sg:province":"QC",
    "sg:tags":[
        "establishment",
        "material",
        "wrapping",
        "gift"
    ],
    "wof:name":"Graphic Finishers Inc",
    "wof:placetype":"venue"
},
  "geometry": {"coordinates":[-73.72657,45.581165],"type":"Point"}
}