{
  "type": "Feature",
  "properties": {
    "addr:full":"Vernon Bridge PE C0A 2E0",
    "addr:postcode":"c0a 2e0",
    "iso:country":"CA",
    "sg:city":"Vernon Bridge",
    "sg:classifiers":[
        {
            "category":"Autos & Motor Vehicles",
            "subcategory":"Automobile Sales",
            "type":"Retail Goods"
        }
    ],
    "sg:phone":"+1 902 651 2315",
    "sg:postcode":"C0A 2E0",
    "sg:province":"PE",
    "sg:tags":[
        "repairing",
        "car"
    ],
    "wof:name":"Rudisch's Garage Ltd",
    "wof:placetype":"venue"
},
  "geometry": {"coordinates":[-62.882526,46.176277],"type":"Point"}
}