{
  "type": "Feature",
  "properties": {
    "addr:full":"Picton ON K0K 2T0",
    "addr:postcode":"k0k 2t0",
    "iso:country":"CA",
    "sg:city":"Picton",
    "sg:classifiers":[
        {
            "category":"Personal",
            "subcategory":"Beauty Salon",
            "type":"Services"
        }
    ],
    "sg:phone":"+1 613 476 3049",
    "sg:postcode":"K0K 2T0",
    "sg:province":"ON",
    "wof:name":"Diane's Hairstyling",
    "wof:placetype":"venue"
},
  "geometry": {"coordinates":[-77.152008,43.999989],"type":"Point"}
}