{
  "type": "Feature",
  "properties": {
    "addr:full":"500 Main St Montague PE C0A 1R0",
    "addr:housenumber":"500",
    "addr:postcode":"c0a 1r0",
    "addr:street":"Main St",
    "iso:country":"CA",
    "sg:address":"500 Main St",
    "sg:city":"Montague",
    "sg:classifiers":[
        {
            "category":"Shopping",
            "subcategory":"Clothing, Apparel, & Fashions",
            "type":"Retail Goods"
        }
    ],
    "sg:phone":"+1 902 838 3464",
    "sg:postcode":"C0A 1R0",
    "sg:province":"PE",
    "wof:name":"Daly Wear Clothing CO",
    "wof:placetype":"venue"
},
  "geometry": {"coordinates":[-62.650909,46.17268],"type":"Point"}
}