{
  "type": "Feature",
  "properties": {
    "iso:country":"CA",
    "sg:address":"4789 Leslie St",
    "sg:city":"North York",
    "sg:classifiers":[
        {
            "category":"Food & Beverages",
            "subcategory":"Groceries & Convenience Stores",
            "type":"Retail Goods"
        }
    ],
    "sg:phone":"+1 416 499 2644",
    "sg:postcode":"M2J 2K8",
    "sg:province":"ON",
    "wof:name":"Kitchen Food Fair",
    "wof:placetype":"venue"
},
  "geometry": {"coordinates":[-79.3652038574,43.7786712646],"type":"Point"}
}