{
  "type": "Feature",
  "properties": {
    "addr:full":"Meaford ON N4L 1W7",
    "addr:postcode":"n4l 1w7",
    "iso:country":"CA",
    "sg:city":"Meaford",
    "sg:classifiers":[
        {
            "category":"Retail",
            "subcategory":"Repair Shop",
            "type":"Services"
        }
    ],
    "sg:phone":"+1 519 538 5222",
    "sg:postcode":"N4L 1W7",
    "sg:province":"ON",
    "sg:tags":[
        "upholsterer"
    ],
    "wof:name":"Upholstery Studio",
    "wof:placetype":"venue"
},
  "geometry": {"coordinates":[-80.5928573608,44.6066551208],"type":"Point"}
}