{
  "type": "Feature",
  "properties": {
    "addr:full":"207 Eastern Ave Toronto ON M5A 1H7",
    "addr:housenumber":"207",
    "addr:postcode":"m5a 1h7",
    "addr:street":"Eastern Ave",
    "iso:country":"CA",
    "sg:address":"207 Eastern Ave",
    "sg:city":"Toronto",
    "sg:classifiers":[
        {
            "category":"Manufacturing",
            "subcategory":"Tools & Machinery",
            "type":"Manufacturing & Wholesale Goods"
        }
    ],
    "sg:phone":"+1 416 868 0440",
    "sg:postcode":"M5A 1H7",
    "sg:province":"ON",
    "sg:tags":[
        "motion",
        "picture",
        "supply"
    ],
    "wof:name":"Acme Power & Lights",
    "wof:placetype":"venue"
},
  "geometry": {"coordinates":[-79.354485,43.654785],"type":"Point"}
}