{
  "type": "Feature",
  "properties": {
    "iso:country":"CA",
    "sg:city":"Vancouver",
    "sg:classifiers":[
        {
            "category":"Mining & Drilling",
            "type":"Manufacturing & Wholesale Goods"
        }
    ],
    "sg:phone":"+1 604 688 5755",
    "sg:postcode":"V6C 3E1",
    "sg:province":"BC",
    "sg:tags":[
        "contractor"
    ],
    "wof:name":"Ivanhoe Mines Ltd",
    "wof:placetype":"venue"
},
  "geometry": {"coordinates":[-123.114899,49.288002],"type":"Point"}
}