{
  "type": "Feature",
  "properties": {
    "addr:full":"8 Gloucester St # A Toronto ON M4Y 1L5",
    "addr:housenumber":"8",
    "addr:postcode":"m4y 1l5",
    "addr:street":"Gloucester St # A",
    "iso:country":"CA",
    "sg:address":"8 Gloucester St # A",
    "sg:city":"Toronto",
    "sg:classifiers":[
        {
            "category":"Restaurant",
            "type":"Food & Drink"
        }
    ],
    "sg:phone":"+1 416 960 0092",
    "sg:postcode":"M4Y 1L5",
    "sg:province":"ON",
    "wof:name":"Olympic 76 Pizza",
    "wof:placetype":"venue"
},
  "geometry": {"coordinates":[-79.38497924799999,43.666721344],"type":"Point"}
}