{
  "type": "Feature",
  "properties": {
    "iso:country":"CA",
    "sg:address":"3872 Boul Saint-Laurent",
    "sg:city":"Montreal",
    "sg:classifiers":[
        {
            "category":"Restaurant",
            "type":"Food & Drink"
        }
    ],
    "sg:phone":"+1 514 843 7283",
    "sg:postcode":"H2W 1Y2",
    "sg:province":"QC",
    "sg:tags":[
        "cafe"
    ],
    "wof:name":"Restaurant LA Cabane-Portugal",
    "wof:placetype":"venue"
},
  "geometry": {"coordinates":[-73.57758331300001,45.5160064697],"type":"Point"}
}