{
  "type": "Feature",
  "properties": {
    "addr:full":"42479 Yarrow Central Rd Chilliwack BC V2R 5C8",
    "addr:housenumber":"42479",
    "addr:postcode":"v2r 5c8",
    "addr:street":"Yarrow Central Rd",
    "iso:country":"CA",
    "sg:address":"42479 Yarrow Central Rd",
    "sg:city":"Chilliwack",
    "sg:classifiers":[
        {
            "category":"Organizations",
            "subcategory":"Religious Organization",
            "type":"Services"
        }
    ],
    "sg:phone":"+1 604 823 6767",
    "sg:postcode":"V2R 5C8",
    "sg:province":"BC",
    "sg:tags":[
        "church"
    ],
    "wof:name":"Yarrow Alliance Church",
    "wof:placetype":"venue"
},
  "geometry": {"coordinates":[-122.048522949,49.0822105408],"type":"Point"}
}