{
  "type": "Feature",
  "properties": {
    "addr:full":"126 Lynden Rd # 1 Brantford ON N3R 8A3",
    "addr:housenumber":"126",
    "addr:postcode":"n3r 8a3",
    "addr:street":"Lynden Rd # 1",
    "iso:country":"CA",
    "sg:address":"126 Lynden Rd # 1",
    "sg:city":"Brantford",
    "sg:classifiers":[
        {
            "category":"Shopping",
            "subcategory":"Jewelry",
            "type":"Retail Goods"
        }
    ],
    "sg:phone":"+1 519 752 2330",
    "sg:postcode":"N3R 8A3",
    "sg:province":"ON",
    "sg:tags":[
        "jeweler"
    ],
    "wof:name":"J H Young & Sons Ltd",
    "wof:placetype":"venue"
},
  "geometry": {"coordinates":[-80.23764801030001,43.1739616394],"type":"Point"}
}