{
  "type": "Feature",
  "properties": {
    "addr:full":"1443 Dominion St North Vancouver BC V7J 1B3",
    "addr:housenumber":"1443",
    "addr:postcode":"v7j 1b3",
    "addr:street":"Dominion St",
    "iso:country":"CA",
    "sg:address":"1443 Dominion St",
    "sg:city":"North Vancouver",
    "sg:classifiers":[
        {
            "category":"Manufacturing",
            "subcategory":"Metals",
            "type":"Manufacturing & Wholesale Goods"
        }
    ],
    "sg:phone":"+1 604 988 8366",
    "sg:postcode":"V7J 1B3",
    "sg:province":"BC",
    "sg:tags":[
        "plating"
    ],
    "wof:name":"Specialty Plating CO Ltd",
    "wof:placetype":"venue"
},
  "geometry": {"coordinates":[-123.033333,49.303131],"type":"Point"}
}