{
  "type": "Feature",
  "properties": {
    "addr:full":"4429 Victoria Quay Port Alberni BC V9Y 6G1",
    "addr:housenumber":"4429",
    "addr:postcode":"v9y 6g1",
    "addr:street":"Victoria Quay",
    "iso:country":"CA",
    "sg:address":"4429 Victoria Quay",
    "sg:city":"Port Alberni",
    "sg:classifiers":[
        {
            "category":"Building & Trades",
            "subcategory":"Construction",
            "type":"Services"
        }
    ],
    "sg:phone":"+1 250 724 5790",
    "sg:postcode":"V9Y 6G1",
    "sg:province":"BC",
    "sg:tags":[
        "general",
        "contractor"
    ],
    "wof:name":"Alberni Construction Ltd",
    "wof:placetype":"venue"
},
  "geometry": {"coordinates":[-124.811943,49.255894],"type":"Point"}
}