{
  "type": "Feature",
  "properties": {
    "addr:full":"Lequille Annapolis Royal NS B0S 1A0",
    "addr:postcode":"b0s 1a0",
    "iso:country":"CA",
    "sg:address":"Lequille",
    "sg:city":"Annapolis Royal",
    "sg:classifiers":[
        {
            "category":"Government",
            "subcategory":"Office",
            "type":"Public Place"
        }
    ],
    "sg:phone":"+1 902 532 2844",
    "sg:postcode":"B0S 1A0",
    "sg:province":"NS",
    "wof:name":"Nova Scotia Transportation",
    "wof:placetype":"venue"
},
  "geometry": {"coordinates":[-65.51557200000001,44.742386],"type":"Point"}
}