{
  "type": "Feature",
  "properties": {
    "addr:full":"680 Boul Lemire Drummondville QC J2C 7W9",
    "addr:housenumber":"680",
    "addr:postcode":"j2c 7w9",
    "addr:street":"Boul Lemire",
    "iso:country":"CA",
    "sg:address":"680 Boul Lemire",
    "sg:city":"Drummondville",
    "sg:classifiers":[
        {
            "category":"Wholesale",
            "subcategory":"Jewelry",
            "type":"Manufacturing & Wholesale Goods"
        }
    ],
    "sg:phone":"+1 819 477 4189",
    "sg:postcode":"J2C 7W9",
    "sg:province":"QC",
    "sg:tags":[
        "ribbon"
    ],
    "wof:name":"Mti Inc",
    "wof:placetype":"venue"
},
  "geometry": {"coordinates":[-72.52852630620001,45.8806304932],"type":"Point"}
}