{
  "type": "Feature",
  "properties": {
    "addr:full":"66 King St W Dundas ON L9H 1T8",
    "addr:housenumber":"66",
    "addr:postcode":"l9h 1t8",
    "addr:street":"King St W",
    "iso:country":"CA",
    "sg:address":"66 King St W",
    "sg:city":"Dundas",
    "sg:classifiers":[
        {
            "category":"Insurance",
            "subcategory":"Insurance Agent",
            "type":"Services"
        }
    ],
    "sg:phone":"+1 905 521 0242",
    "sg:postcode":"L9H 1T8",
    "sg:province":"ON",
    "wof:name":"Curry Elkin & Kelly Insurance",
    "wof:placetype":"venue"
},
  "geometry": {"coordinates":[-79.9564285278,43.2663040161],"type":"Point"}
}