{
  "type": "Feature",
  "properties": {
    "addr:full":"9932 121 Ave Grande Prairie AB T8V 4J1",
    "addr:housenumber":"9932",
    "addr:postcode":"t8v 4j1",
    "addr:street":"121 Ave",
    "iso:country":"CA",
    "sg:address":"9932 121 Ave",
    "sg:city":"Grande Prairie",
    "sg:classifiers":[
        {
            "category":"Shopping",
            "subcategory":"Clothing, Apparel, & Fashions",
            "type":"Retail Goods"
        }
    ],
    "sg:phone":"+1 780 532 1094",
    "sg:postcode":"T8V 4J1",
    "sg:province":"AB",
    "sg:tags":[
        "furnishing"
    ],
    "wof:name":"Edward's Factory Outlet",
    "wof:placetype":"venue"
},
  "geometry": {"coordinates":[-118.792114258,55.1896362305],"type":"Point"}
}