{
  "type": "Feature",
  "properties": {
    "addr:full":"38 Lane Rd Dunnville ON N1A 2W1",
    "addr:housenumber":"38",
    "addr:postcode":"n1a 2w1",
    "addr:street":"Lane Rd",
    "iso:country":"CA",
    "sg:address":"38 Lane Rd",
    "sg:city":"Dunnville",
    "sg:classifiers":[
        {
            "category":"Building & Trades",
            "subcategory":"Construction",
            "type":"Services"
        }
    ],
    "sg:phone":"+1 905 774 3789",
    "sg:postcode":"N1A 2W1",
    "sg:province":"ON",
    "sg:tags":[
        "excavating",
        "contractor"
    ],
    "wof:name":"Egger Excavating Ltd",
    "wof:placetype":"venue"
},
  "geometry": {"coordinates":[-79.6264343262,42.9857177734],"type":"Point"}
}