{
  "type": "Feature",
  "properties": {
    "addr:full":"185 Rue Isabella Salaberry-DE-Valleyfield QC J6T 4Z5",
    "addr:housenumber":"185",
    "addr:postcode":"j6t 4z5",
    "addr:street":"Rue Isabella",
    "iso:country":"CA",
    "sg:address":"185 Rue Isabella",
    "sg:city":"Salaberry-DE-Valleyfield",
    "sg:classifiers":[
        {
            "category":"Building & Trades",
            "subcategory":"Construction",
            "type":"Services"
        }
    ],
    "sg:phone":"+1 450 377 4063",
    "sg:postcode":"J6T 4Z5",
    "sg:province":"QC",
    "sg:tags":[
        "painter"
    ],
    "wof:name":"Arc En Ciel Peinture Enr",
    "wof:placetype":"venue"
},
  "geometry": {"coordinates":[-74.12083435060001,45.2501029968],"type":"Point"}
}