{
  "type": "Feature",
  "properties": {
    "addr:full":"7 Saskatchewan Ave W Devon AB T9G 1B2",
    "addr:housenumber":"7",
    "addr:postcode":"t9g 1b2",
    "addr:street":"Saskatchewan Ave W",
    "iso:country":"CA",
    "sg:address":"7 Saskatchewan Ave W",
    "sg:city":"Devon",
    "sg:classifiers":[
        {
            "category":"Autos & Motor Vehicles",
            "subcategory":"Automobile Sales",
            "type":"Retail Goods"
        }
    ],
    "sg:phone":"+1 780 987 2433",
    "sg:postcode":"T9G 1B2",
    "sg:province":"AB",
    "sg:tags":[
        "car",
        "dealer"
    ],
    "wof:name":"Devon Chevrolet Oldsmobile Ltd",
    "wof:placetype":"venue"
},
  "geometry": {"coordinates":[-113.73380299999999,53.366634],"type":"Point"}
}