{
  "type": "Feature",
  "properties": {
    "addr:full":"70 Heritage Dr New Hamburg ON N3A 2J4",
    "addr:housenumber":"70",
    "addr:postcode":"n3a 2j4",
    "addr:street":"Heritage Dr",
    "iso:country":"CA",
    "sg:address":"70 Heritage Dr",
    "sg:city":"New Hamburg",
    "sg:classifiers":[
        {
            "category":"Farming",
            "subcategory":"Poultry Farm",
            "type":"Manufacturing & Wholesale Goods"
        }
    ],
    "sg:phone":"+1 519 662 1501",
    "sg:postcode":"N3A 2J4",
    "sg:province":"ON",
    "wof:name":"Maple Leaf Poultry",
    "wof:placetype":"venue"
},
  "geometry": {"coordinates":[-80.69189453120001,43.3768234253],"type":"Point"}
}