{
  "type": "Feature",
  "properties": {
    "addr:full":"151 Water St Vancouver BC V6B 1A7",
    "addr:housenumber":"151",
    "addr:postcode":"v6b 1a7",
    "addr:street":"Water St",
    "iso:country":"CA",
    "sg:address":"151 Water St",
    "sg:city":"Vancouver",
    "sg:classifiers":[
        {
            "category":"Shopping",
            "subcategory":"Gifts & Souvenirs",
            "type":"Retail Goods"
        }
    ],
    "sg:phone":"+1 604 685 1828",
    "sg:postcode":"V6B 1A7",
    "sg:province":"BC",
    "sg:tags":[
        "shop"
    ],
    "wof:name":"Frances Hill's",
    "wof:placetype":"venue"
},
  "geometry": {"coordinates":[-123.10759,49.284248],"type":"Point"}
}