{
  "type": "Feature",
  "properties": {
    "addr:full":"20 Brooksbank Ave North Vancouver BC V7J 2B8",
    "addr:housenumber":"20",
    "addr:postcode":"v7j 2b8",
    "addr:street":"Brooksbank Ave",
    "iso:country":"CA",
    "sg:address":"20 Brooksbank Ave",
    "sg:city":"North Vancouver",
    "sg:classifiers":[
        {
            "category":"Wholesale",
            "subcategory":"Machinery & Supplies",
            "type":"Manufacturing & Wholesale Goods"
        }
    ],
    "sg:phone":"+1 604 924 0325",
    "sg:postcode":"V7J 2B8",
    "sg:province":"BC",
    "sg:tags":[
        "equipment",
        "marine"
    ],
    "wof:name":"Manly Marine Closures Ltd",
    "wof:placetype":"venue"
},
  "geometry": {"coordinates":[-123.040367127,49.3039245605],"type":"Point"}
}