{
  "type": "Feature",
  "properties": {
    "addr:full":"Maple Ridge BC V2X 2Z8",
    "addr:postcode":"v2x 2z8",
    "iso:country":"CA",
    "sg:city":"Maple Ridge",
    "sg:classifiers":[
        {
            "category":"Health Services",
            "subcategory":"Doctor",
            "type":"Services"
        }
    ],
    "sg:phone":"+1 604 463 7222",
    "sg:postcode":"V2X 2Z8",
    "sg:province":"BC",
    "sg:tags":[
        "dentist"
    ],
    "wof:name":"Meridian Dental Ctr",
    "wof:placetype":"venue"
},
  "geometry": {"coordinates":[-122.59304,49.218742],"type":"Point"}
}