{
  "type": "Feature",
  "properties": {
    "addr:full":"1010 Rue Filiatrault Sorel-Tracy QC J3R 3T3",
    "addr:housenumber":"1010",
    "addr:postcode":"j3r 3t3",
    "addr:street":"Rue Filiatrault",
    "iso:country":"CA",
    "sg:address":"1010 Rue Filiatrault",
    "sg:city":"Sorel-Tracy",
    "sg:classifiers":[
        {
            "category":"Manufacturing",
            "subcategory":"Printing",
            "type":"Manufacturing & Wholesale Goods"
        }
    ],
    "sg:phone":"+1 450 742 2036",
    "sg:postcode":"J3R 3T3",
    "sg:province":"QC",
    "sg:tags":[
        "screen"
    ],
    "wof:name":"Serigraphie Sorel Souvenirs",
    "wof:placetype":"venue"
},
  "geometry": {"coordinates":[-73.1289901733,46.0397109985],"type":"Point"}
}