{
  "type": "Feature",
  "properties": {
    "addr:full":"1547 Merivale Rd Nepean ON K2G 4V3",
    "addr:housenumber":"1547",
    "addr:postcode":"k2g 4v3",
    "addr:street":"Merivale Rd",
    "iso:country":"CA",
    "sg:address":"1547 Merivale Rd",
    "sg:city":"Nepean",
    "sg:classifiers":[
        {
            "category":"Retail",
            "subcategory":"Animal Services",
            "type":"Services"
        }
    ],
    "sg:phone":"+1 613 224 1212",
    "sg:postcode":"K2G 4V3",
    "sg:province":"ON",
    "sg:tags":[
        "pet",
        "shop",
        "grooming",
        "washing"
    ],
    "wof:name":"Super Pet",
    "wof:placetype":"venue"
},
  "geometry": {"coordinates":[-75.7352600098,45.3544311523],"type":"Point"}
}