{
  "type": "Feature",
  "properties": {
    "addr:full":"10844 95 St NW Edmonton AB T5H 2E4",
    "addr:housenumber":"10844",
    "addr:postcode":"t5h 2e4",
    "addr:street":"95 St Nw",
    "iso:country":"CA",
    "sg:address":"10844 95 St NW",
    "sg:city":"Edmonton",
    "sg:classifiers":[
        {
            "category":"Restaurant",
            "type":"Food & Drink"
        }
    ],
    "sg:phone":"+1 780 425 0960",
    "sg:postcode":"T5H 2E4",
    "sg:province":"AB",
    "wof:name":"Sorrentino's Bistro-Bar",
    "wof:placetype":"venue"
},
  "geometry": {"coordinates":[-113.48481,53.555714],"type":"Point"}
}