{
  "type": "Feature",
  "properties": {
    "iso:country":"CA",
    "sg:address":"407 Laval Blvd W",
    "sg:city":"Lethbridge",
    "sg:classifiers":[
        {
            "category":"Bars & Pubs",
            "type":"Food & Drink"
        }
    ],
    "sg:phone":"+1 403 380 2811",
    "sg:postcode":"T1K 3W7",
    "sg:province":"AB",
    "wof:name":"Backstreet Pub & Pizza",
    "wof:placetype":"venue"
},
  "geometry": {"coordinates":[-112.874778748,49.673374176],"type":"Point"}
}