{
  "type": "Feature",
  "properties": {
    "addr:full":"6133 47 St Barrhead AB T7N 1A3",
    "addr:housenumber":"6133",
    "addr:postcode":"t7n 1a3",
    "addr:street":"47 St",
    "iso:country":"CA",
    "sg:address":"6133 47 St",
    "sg:city":"Barrhead",
    "sg:classifiers":[
        {
            "category":"Home & Garden",
            "subcategory":"Building Materials",
            "type":"Retail Goods"
        }
    ],
    "sg:phone":"+1 780 674 3397",
    "sg:postcode":"T7N 1A3",
    "sg:province":"AB",
    "wof:name":"Barrhead Building Products",
    "wof:placetype":"venue"
},
  "geometry": {"coordinates":[-114.396339,54.132561],"type":"Point"}
}