{
  "type": "Feature",
  "properties": {
    "addr:full":"1720 Douglas St Victoria BC V8W 2G7",
    "addr:housenumber":"1720",
    "addr:postcode":"v8w 2g7",
    "addr:street":"Douglas St",
    "iso:country":"CA",
    "sg:address":"1720 Douglas St",
    "sg:city":"Victoria",
    "sg:classifiers":[
        {
            "category":"Banks & Credit Unions",
            "subcategory":"Bank",
            "type":"Services"
        }
    ],
    "sg:phone":"+1 250 386 3535",
    "sg:postcode":"V8W 2G7",
    "sg:province":"BC",
    "sg:tags":[
        "cashing",
        "check"
    ],
    "wof:name":"Money Mart",
    "wof:placetype":"venue"
},
  "geometry": {"coordinates":[-123.364655,48.429611],"type":"Point"}
}