{
  "type": "Feature",
  "properties": {
    "addr:full":"872 Eglinton Ave E East York ON M4G 2L1",
    "addr:housenumber":"872",
    "addr:postcode":"m4g 2l1",
    "addr:street":"Eglinton Ave E",
    "iso:country":"CA",
    "sg:address":"872 Eglinton Ave E",
    "sg:city":"East York",
    "sg:classifiers":[
        {
            "category":"Shopping",
            "subcategory":"Clothing, Apparel, & Fashions",
            "type":"Retail Goods"
        }
    ],
    "sg:phone":"+1 416 566 6569",
    "sg:postcode":"M4G 2L1",
    "sg:province":"ON",
    "sg:tags":[
        "lingerie"
    ],
    "wof:name":"What's Sexy Inc",
    "wof:placetype":"venue"
},
  "geometry": {"coordinates":[-79.3651885986,43.7136459351],"type":"Point"}
}