{
  "type": "Feature",
  "properties": {
    "addr:full":"11 Coronation Dr Yellowknife NT X1A 2P7",
    "addr:housenumber":"11",
    "addr:postcode":"x1a 2p7",
    "addr:street":"Coronation Dr",
    "iso:country":"CA",
    "sg:address":"11 Coronation Dr",
    "sg:city":"Yellowknife",
    "sg:classifiers":[
        {
            "category":"Wholesale",
            "subcategory":"Electrical",
            "type":"Manufacturing & Wholesale Goods"
        }
    ],
    "sg:phone":"+1 867 920 2337",
    "sg:postcode":"X1A 2P7",
    "sg:province":"NT",
    "sg:tags":[
        "consultant",
        "radio",
        "telecommunication",
        "communication"
    ],
    "wof:name":"Ncns Paging",
    "wof:placetype":"venue"
},
  "geometry": {"coordinates":[-114.410133,62.4338],"type":"Point"}
}