{
  "type": "Feature",
  "properties": {
    "addr:full":"3480 Boul Des Sources Dollard-Des-Ormeaux QC H9B 1Z9",
    "addr:housenumber":"3480",
    "addr:postcode":"h9b 1z9",
    "addr:street":"Boul Des Sources",
    "iso:country":"CA",
    "sg:address":"3480 Boul Des Sources",
    "sg:city":"Dollard-Des-Ormeaux",
    "sg:classifiers":[
        {
            "category":"Retail",
            "subcategory":"Auto Rental",
            "type":"Services"
        }
    ],
    "sg:phone":"+1 514 685 8501",
    "sg:postcode":"H9B 1Z9",
    "sg:province":"QC",
    "sg:tags":[
        "renting",
        "automobile"
    ],
    "wof:name":"Enterprise Location D'Autos",
    "wof:placetype":"venue"
},
  "geometry": {"coordinates":[-73.798492,45.48539],"type":"Point"}
}