{
  "type": "Feature",
  "properties": {
    "iso:country":"CA",
    "sg:address":"101 John St",
    "sg:city":"Orangeville",
    "sg:classifiers":[
        {
            "category":"Wholesale",
            "subcategory":"Chemicals & Plastics",
            "type":"Manufacturing & Wholesale Goods"
        }
    ],
    "sg:phone":"+1 519 941 0720",
    "sg:postcode":"L9W 2R1",
    "sg:province":"ON",
    "wof:name":"Clorox CO of Canada",
    "wof:placetype":"venue"
},
  "geometry": {"coordinates":[-80.090134,43.911472],"type":"Point"}
}