{
  "type": "Feature",
  "properties": {
    "addr:full":"1100 Princess St Kingston ON K7L 5G8",
    "addr:housenumber":"1100",
    "addr:postcode":"k7l 5g8",
    "addr:street":"Princess St",
    "iso:country":"CA",
    "sg:address":"1100 Princess St",
    "sg:city":"Kingston",
    "sg:classifiers":[
        {
            "category":"Shopping",
            "subcategory":"Florist",
            "type":"Retail Goods"
        }
    ],
    "sg:phone":"+1 613 530 2602",
    "sg:postcode":"K7L 5G8",
    "sg:province":"ON",
    "wof:name":"Loblaws Gardens",
    "wof:placetype":"venue"
},
  "geometry": {"coordinates":[-76.5165710449,44.2432022095],"type":"Point"}
}