{
  "type": "Feature",
  "properties": {
    "addr:full":"367 Ch Du Grand-Bernier N Saint-Jean-Sur-Richelieu QC J3B 4R9",
    "addr:housenumber":"367",
    "addr:postcode":"j3b 4r9",
    "addr:street":"Ch Du Grand-Bernier N",
    "iso:country":"CA",
    "sg:address":"367 Ch Du Grand-Bernier N",
    "sg:city":"Saint-Jean-Sur-Richelieu",
    "sg:classifiers":[
        {
            "category":"Manufacturing",
            "subcategory":"Building Materials",
            "type":"Manufacturing & Wholesale Goods"
        }
    ],
    "sg:phone":"+1 450 346 8426",
    "sg:postcode":"J3B 4R9",
    "sg:province":"QC",
    "sg:tags":[
        "molding"
    ],
    "wof:name":"DPM Decoration Architecture",
    "wof:placetype":"venue"
},
  "geometry": {"coordinates":[-73.2929153442,45.3104782104],"type":"Point"}
}