{
  "type": "Feature",
  "properties": {
    "addr:full":"1231 Rue Principale Saint-Come QC J0K 2B0",
    "addr:housenumber":"1231",
    "addr:postcode":"j0k 2b0",
    "addr:street":"Rue Principale",
    "iso:country":"CA",
    "sg:address":"1231 Rue Principale",
    "sg:city":"Saint-Come",
    "sg:classifiers":[
        {
            "category":"Building & Trades",
            "subcategory":"Electrical",
            "type":"Services"
        }
    ],
    "sg:phone":"+1 450 883 5133",
    "sg:postcode":"J0K 2B0",
    "sg:province":"QC",
    "sg:tags":[
        "electric",
        "contractor"
    ],
    "wof:name":"Jocelyn Breault Inc",
    "wof:placetype":"venue"
},
  "geometry": {"coordinates":[-73.77001953120001,46.2744064331],"type":"Point"}
}