{
  "type": "Feature",
  "properties": {
    "addr:full":"17603 100 Ave NW Edmonton AB T5S 2M1",
    "addr:housenumber":"17603",
    "addr:postcode":"t5s 2m1",
    "addr:street":"100 Ave Nw",
    "iso:country":"CA",
    "sg:address":"17603 100 Ave NW",
    "sg:city":"Edmonton",
    "sg:classifiers":[
        {
            "category":"Banks & Credit Unions",
            "subcategory":"Bank",
            "type":"Services"
        }
    ],
    "sg:phone":"+1 780 484 7407",
    "sg:postcode":"T5S 2M1",
    "sg:province":"AB",
    "wof:name":"Canadian Western Bank",
    "wof:placetype":"venue"
},
  "geometry": {"coordinates":[-113.623275757,53.538269043],"type":"Point"}
}