{
  "type": "Feature",
  "properties": {
    "addr:full":"Guelph ON N1K 1B8",
    "addr:postcode":"n1k 1b8",
    "iso:country":"CA",
    "sg:city":"Guelph",
    "sg:classifiers":[
        {
            "category":"Manufacturing",
            "subcategory":"Motor Vehicles & Parts",
            "type":"Manufacturing & Wholesale Goods"
        }
    ],
    "sg:phone":"+1 519 767 2863",
    "sg:postcode":"N1K 1B8",
    "sg:province":"ON",
    "sg:tags":[
        "automobile",
        "supply"
    ],
    "wof:name":"Marble Electronics Inc",
    "wof:placetype":"venue"
},
  "geometry": {"coordinates":[-80.3100204468,43.5411376953],"type":"Point"}
}