{
  "type": "Feature",
  "properties": {
    "addr:full":"Vancouver BC V5N 5L9",
    "addr:postcode":"v5n 5l9",
    "iso:country":"CA",
    "sg:city":"Vancouver",
    "sg:classifiers":[
        {
            "category":"Education",
            "subcategory":"College",
            "type":"Public Place"
        }
    ],
    "sg:phone":"+1 604 253 7008",
    "sg:postcode":"V5N 5L9",
    "sg:province":"BC",
    "sg:tags":[
        "academic",
        "school"
    ],
    "wof:name":"Cec Canada Foundation Assn",
    "wof:placetype":"venue"
},
  "geometry": {"coordinates":[-123.074913025,49.2685050964],"type":"Point"}
}