{
  "type": "Feature",
  "properties": {
    "addr:full":"7310 101 Ave NW Edmonton AB T6A 0J2",
    "addr:housenumber":"7310",
    "addr:postcode":"t6a 0j2",
    "addr:street":"101 Ave Nw",
    "iso:country":"CA",
    "sg:address":"7310 101 Ave NW",
    "sg:city":"Edmonton",
    "sg:classifiers":[
        {
            "category":"Health Services",
            "subcategory":"Medical Lab",
            "type":"Services"
        }
    ],
    "sg:phone":"+1 780 465 5894",
    "sg:postcode":"T6A 0J2",
    "sg:province":"AB",
    "sg:tags":[
        "laboratory"
    ],
    "wof:name":"Ward Denture Clinics Ltd",
    "wof:placetype":"venue"
},
  "geometry": {"coordinates":[-113.440224,53.541386],"type":"Point"}
}