{
  "type": "Feature",
  "properties": {
    "iso:country":"CA",
    "sg:address":"1145 8th Ave",
    "sg:city":"Regina",
    "sg:classifiers":[
        {
            "category":"Wholesale",
            "subcategory":"Hardware",
            "type":"Manufacturing & Wholesale Goods"
        }
    ],
    "sg:phone":"+1 306 757 5656",
    "sg:postcode":"S4R 1E1",
    "sg:province":"SK",
    "sg:tags":[
        "ventilating",
        "equipment",
        "pump"
    ],
    "wof:name":"Cypress Sales Partnership",
    "wof:placetype":"venue"
},
  "geometry": {"coordinates":[-104.597122192,50.4566001892],"type":"Point"}
}