{
  "type": "Feature",
  "properties": {
    "addr:full":"377 Lerwick Rd Courtenay BC V9N 9G4",
    "addr:housenumber":"377",
    "addr:postcode":"v9n 9g4",
    "addr:street":"Lerwick Rd",
    "iso:country":"CA",
    "sg:address":"377 Lerwick Rd",
    "sg:city":"Courtenay",
    "sg:classifiers":[
        {
            "category":"Recreation",
            "type":"Entertainment"
        }
    ],
    "sg:phone":"+1 250 334 2527",
    "sg:postcode":"V9N 9G4",
    "sg:province":"BC",
    "sg:tags":[
        "pool",
        "swimming"
    ],
    "wof:name":"Comox Valley Sports & Aquatic",
    "wof:placetype":"venue"
},
  "geometry": {"coordinates":[-124.96625518800001,49.7106704712],"type":"Point"}
}