{
  "type": "Feature",
  "properties": {
    "addr:full":"17 Kimberdale Cres Scarborough ON M1W 1Y4",
    "addr:housenumber":"17",
    "addr:postcode":"m1w 1y4",
    "addr:street":"Kimberdale Cres",
    "iso:country":"CA",
    "sg:address":"17 Kimberdale Cres",
    "sg:city":"Scarborough",
    "sg:classifiers":[
        {
            "category":"Shopping",
            "subcategory":"Hobbies, Toys, & Games",
            "type":"Retail Goods"
        }
    ],
    "sg:phone":"+1 416 497 5400",
    "sg:postcode":"M1W 1Y4",
    "sg:province":"ON",
    "sg:tags":[
        "craft",
        "supply"
    ],
    "wof:name":"F S Head & Assoc Ltd",
    "wof:placetype":"venue"
},
  "geometry": {"coordinates":[-79.309532,43.786835],"type":"Point"}
}