{
  "type": "Feature",
  "properties": {
    "addr:full":"1700 Varsity Estates Dr NW Calgary AB T3B 2W9",
    "addr:housenumber":"1700",
    "addr:postcode":"t3b 2w9",
    "addr:street":"Varsity Estates Dr Nw",
    "iso:country":"CA",
    "sg:address":"1700 Varsity Estates Dr NW",
    "sg:city":"Calgary",
    "sg:classifiers":[
        {
            "category":"Professional",
            "subcategory":"Accounting & Tax Preparation",
            "type":"Services"
        }
    ],
    "sg:phone":"+1 403 286 7784",
    "sg:postcode":"T3B 2W9",
    "sg:province":"AB",
    "sg:tags":[
        "accountant"
    ],
    "wof:name":"Ritchie, Alex",
    "wof:placetype":"venue"
},
  "geometry": {"coordinates":[-114.172080994,51.0976600647],"type":"Point"}
}