{
  "type": "Feature",
  "properties": {
    "iso:country":"CA",
    "sg:address":"3425 Barnsdale Rd",
    "sg:city":"Ottawa",
    "sg:classifiers":[
        {
            "category":"Shopping",
            "subcategory":"Gifts & Souvenirs",
            "type":"Retail Goods"
        }
    ],
    "sg:phone":"+1 613 692 9237",
    "sg:postcode":"K2C 3H2",
    "sg:province":"ON",
    "sg:tags":[
        "basket",
        "parcel"
    ],
    "wof:name":"Wellington Gifts Baskets",
    "wof:placetype":"venue"
},
  "geometry": {"coordinates":[-75.7088775635,45.2422142029],"type":"Point"}
}