{
  "type": "Feature",
  "properties": {
    "addr:full":"7160 Rue Saint-Denis Montreal QC H2R 2E2",
    "addr:housenumber":"7160",
    "addr:postcode":"h2r 2e2",
    "addr:street":"Rue Saint-Denis",
    "iso:country":"CA",
    "sg:address":"7160 Rue Saint-Denis",
    "sg:city":"Montreal",
    "sg:classifiers":[
        {
            "category":"Personal",
            "subcategory":"Beauty Salon",
            "type":"Services"
        }
    ],
    "sg:phone":"+1 514 276 5821",
    "sg:postcode":"H2R 2E2",
    "sg:province":"QC",
    "wof:name":"Salon DE Coiffure Clermathe",
    "wof:placetype":"venue"
},
  "geometry": {"coordinates":[-73.61515799999999,45.538395],"type":"Point"}
}