{
  "type": "Feature",
  "properties": {
    "addr:full":"174 Harwood Ave S Ajax ON L1S 2H6",
    "addr:housenumber":"174",
    "addr:postcode":"l1s 2h6",
    "addr:street":"Harwood Ave S",
    "iso:country":"CA",
    "sg:address":"174 Harwood Ave S",
    "sg:city":"Ajax",
    "sg:classifiers":[
        {
            "category":"Health Services",
            "subcategory":"Doctor",
            "type":"Services"
        }
    ],
    "sg:phone":"+1 905 683 3220",
    "sg:postcode":"L1S 2H6",
    "sg:province":"ON",
    "sg:tags":[
        "physician",
        "surgeon"
    ],
    "wof:name":"Fan, Michael K MD",
    "wof:placetype":"venue"
},
  "geometry": {"coordinates":[-79.0208206177,43.8491516113],"type":"Point"}
}