{
  "type": "Feature",
  "properties": {
    "iso:country":"CA",
    "sg:address":"4320 Harvester Rd",
    "sg:city":"Burlington",
    "sg:classifiers":[
        {
            "category":"Autos & Motor Vehicles",
            "subcategory":"Automobile Sales",
            "type":"Retail Goods"
        }
    ],
    "sg:phone":"+1 905 632 0300",
    "sg:postcode":"L7L 5S4",
    "sg:province":"ON",
    "sg:tags":[
        "truck"
    ],
    "wof:name":"Sheehan's Truck Ctr",
    "wof:placetype":"venue"
},
  "geometry": {"coordinates":[-79.774033,43.371353],"type":"Point"}
}