{
  "type": "Feature",
  "properties": {
    "iso:country":"CA",
    "sg:address":"35 Anne St S",
    "sg:city":"Barrie",
    "sg:classifiers":[
        {
            "category":"Freight",
            "type":"Transportation"
        }
    ],
    "sg:phone":"+1 705 728 3431",
    "sg:postcode":"L4N 2C7",
    "sg:province":"ON",
    "sg:tags":[
        "trucking"
    ],
    "wof:name":"Sts Logistics",
    "wof:placetype":"venue"
},
  "geometry": {"coordinates":[-79.703339,44.380512],"type":"Point"}
}