{
  "type": "Feature",
  "properties": {
    "addr:full":"1149 Rue Notre-Dame Lachine QC H8S 2C5",
    "addr:housenumber":"1149",
    "addr:postcode":"h8s 2c5",
    "addr:street":"Rue Notre-Dame",
    "iso:country":"CA",
    "sg:address":"1149 Rue Notre-Dame",
    "sg:city":"Lachine",
    "sg:classifiers":[
        {
            "category":"Shopping",
            "subcategory":"Tobacco",
            "type":"Retail Goods"
        }
    ],
    "sg:phone":"+1 514 637 3207",
    "sg:postcode":"H8S 2C5",
    "sg:province":"QC",
    "sg:tags":[
        "cigarette",
        "convenience",
        "cigar",
        "store"
    ],
    "wof:name":"Depanneur Daigneault",
    "wof:placetype":"venue"
},
  "geometry": {"coordinates":[-73.674065,45.434792],"type":"Point"}
}