{
  "type": "Feature",
  "properties": {
    "addr:full":"302 Russett Dr Arnprior ON K7S 3G8",
    "addr:housenumber":"302",
    "addr:postcode":"k7s 3g8",
    "addr:street":"Russett Dr",
    "iso:country":"CA",
    "sg:address":"302 Russett Dr",
    "sg:city":"Arnprior",
    "sg:classifiers":[
        {
            "category":"Wholesale",
            "subcategory":"Machinery & Supplies",
            "type":"Manufacturing & Wholesale Goods"
        }
    ],
    "sg:phone":"+1 613 623 3187",
    "sg:postcode":"K7S 3G8",
    "sg:province":"ON",
    "sg:tags":[
        "farm",
        "equipment"
    ],
    "wof:name":"Rath Farm Equipment Ltd",
    "wof:placetype":"venue"
},
  "geometry": {"coordinates":[-76.378677,45.422291],"type":"Point"}
}