{
  "type": "Feature",
  "properties": {
    "addr:full":"30 Colborne St W Lindsay ON K9V 3S8",
    "addr:housenumber":"30",
    "addr:postcode":"k9v 3s8",
    "addr:street":"Colborne St W",
    "iso:country":"CA",
    "sg:address":"30 Colborne St W",
    "sg:city":"Lindsay",
    "sg:classifiers":[
        {
            "category":"Building & Trades",
            "subcategory":"Electrical",
            "type":"Services"
        }
    ],
    "sg:phone":"+1 705 878 3717",
    "sg:postcode":"K9V 3S8",
    "sg:province":"ON",
    "sg:tags":[
        "electric",
        "contractor"
    ],
    "wof:name":"Mariposa Electric Ltd",
    "wof:placetype":"venue"
},
  "geometry": {"coordinates":[-78.74221,44.360218],"type":"Point"}
}