{
  "type": "Feature",
  "properties": {
    "addr:full":"830 Av Des Ruisseaux Pintendre QC G6C 1N7",
    "addr:postcode":"g6c 1n7",
    "addr:street":"830 Av Des Ruisseaux Pintendre",
    "iso:country":"CA",
    "sg:address":"830 Av Des Ruisseaux",
    "sg:city":"Pintendre",
    "sg:classifiers":[
        {
            "category":"Restaurant",
            "type":"Food & Drink"
        }
    ],
    "sg:phone":"+1 418 833 4906",
    "sg:postcode":"G6C 1N7",
    "sg:province":"QC",
    "wof:name":"Restaurant LA Ferme Djerba",
    "wof:placetype":"venue"
},
  "geometry": {"coordinates":[-71.096626,46.789371],"type":"Point"}
}