{
  "type": "Feature",
  "properties": {
    "addr:full":"48 Elgin St Orillia ON L3V 1S2",
    "addr:housenumber":"48",
    "addr:postcode":"l3v 1s2",
    "addr:street":"Elgin St",
    "iso:country":"CA",
    "sg:address":"48 Elgin St",
    "sg:city":"Orillia",
    "sg:classifiers":[
        {
            "category":"Building & Trades",
            "subcategory":"Landscaping Services",
            "type":"Services"
        }
    ],
    "sg:phone":"+1 705 326 0335",
    "sg:postcode":"L3V 1S2",
    "sg:province":"ON",
    "sg:tags":[
        "masonry",
        "landscape",
        "contractor"
    ],
    "wof:name":"Steven Tucci Masonry",
    "wof:placetype":"venue"
},
  "geometry": {"coordinates":[-79.415665,44.607056],"type":"Point"}
}