{
  "type": "Feature",
  "properties": {
    "iso:country":"CA",
    "sg:city":"Scarborough",
    "sg:classifiers":[
        {
            "category":"Restaurant",
            "type":"Food & Drink"
        }
    ],
    "sg:phone":"+1 416 335 6538",
    "sg:postcode":"M1T 3T8",
    "sg:province":"ON",
    "wof:name":"Lucky Elephant Thai Kitchen",
    "wof:placetype":"venue"
},
  "geometry": {"coordinates":[-79.28820800779999,43.7835693359],"type":"Point"}
}