{
  "type": "Feature",
  "properties": {
    "addr:full":"Calgary AB T2S 3C4",
    "addr:postcode":"t2s 3c4",
    "iso:country":"CA",
    "sg:city":"Calgary",
    "sg:classifiers":[
        {
            "category":"Health Services",
            "subcategory":"Health Practitioner",
            "type":"Services"
        }
    ],
    "sg:phone":"+1 403 244 9527",
    "sg:postcode":"T2S 3C4",
    "sg:province":"AB",
    "sg:tags":[
        "psychologist",
        "reading",
        "instruction",
        "improvement"
    ],
    "wof:name":"Reading Foundation",
    "wof:placetype":"venue"
},
  "geometry": {"coordinates":[-114.068932,51.032391],"type":"Point"}
}