{
  "type": "Feature",
  "properties": {
    "addr:full":"Guelph ON N1G 4W3",
    "addr:postcode":"n1g 4w3",
    "iso:country":"CA",
    "sg:city":"Guelph",
    "sg:classifiers":[
        {
            "category":"Health Services",
            "subcategory":"Doctor",
            "type":"Services"
        }
    ],
    "sg:phone":"+1 519 824 9009",
    "sg:postcode":"N1G 4W3",
    "sg:province":"ON",
    "sg:tags":[
        "dentist"
    ],
    "wof:name":"Dickson & Jutlah Family Dent",
    "wof:placetype":"venue"
},
  "geometry": {"coordinates":[-80.211517,43.521351],"type":"Point"}
}