{
  "type": "Feature",
  "properties": {
    "addr:full":"12100 Rue Urgel-Charbonneau Montreal QC H1B 5X1",
    "addr:housenumber":"12100",
    "addr:postcode":"h1b 5x1",
    "addr:street":"Rue Urgel-Charbonneau",
    "iso:country":"CA",
    "sg:address":"12100 Rue Urgel-Charbonneau",
    "sg:city":"Montreal",
    "sg:classifiers":[
        {
            "category":"Organizations",
            "subcategory":"Labor Organization",
            "type":"Services"
        }
    ],
    "sg:phone":"+1 514 645 9016",
    "sg:postcode":"H1B 5X1",
    "sg:province":"QC",
    "wof:name":"Teamsters Local 106",
    "wof:placetype":"venue"
},
  "geometry": {"coordinates":[-73.523605,45.646378],"type":"Point"}
}