{
  "type": "Feature",
  "properties": {
    "addr:full":"2285 Rue Saint-Mathieu Montreal QC H3H 2J7",
    "addr:housenumber":"2285",
    "addr:postcode":"h3h 2j7",
    "addr:street":"Rue Saint-Mathieu",
    "iso:country":"CA",
    "sg:address":"2285 Rue Saint-Mathieu",
    "sg:city":"Montreal",
    "sg:classifiers":[
        {
            "category":"Restaurant",
            "type":"Food & Drink"
        }
    ],
    "sg:phone":"+1 514 934 7337",
    "sg:postcode":"H3H 2J7",
    "sg:province":"QC",
    "wof:name":"Walima-Snack",
    "wof:placetype":"venue"
},
  "geometry": {"coordinates":[-73.58174099999999,45.495468],"type":"Point"}
}