{
  "type": "Feature",
  "properties": {
    "addr:full":"Concord ON L4K 4R9",
    "addr:postcode":"l4k 4r9",
    "iso:country":"CA",
    "sg:city":"Concord",
    "sg:classifiers":[
        {
            "category":"Travel",
            "subcategory":"Travel Agent",
            "type":"Entertainment"
        }
    ],
    "sg:phone":"+1 905 660 7771",
    "sg:postcode":"L4K 4R9",
    "sg:province":"ON",
    "sg:tags":[
        "agency",
        "bureau"
    ],
    "wof:name":"Corporate Travel Svc",
    "wof:placetype":"venue"
},
  "geometry": {"coordinates":[-79.5248184204,43.813621521],"type":"Point"}
}