{
  "type": "Feature",
  "properties": {
    "addr:full":"Delta BC V4G 1J5",
    "addr:postcode":"v4g 1j5",
    "iso:country":"CA",
    "sg:city":"Delta",
    "sg:classifiers":[
        {
            "category":"Professional",
            "subcategory":"Business Services",
            "type":"Services"
        }
    ],
    "sg:phone":"+1 604 930 5202",
    "sg:postcode":"V4G 1J5",
    "sg:province":"BC",
    "sg:tags":[
        "recording",
        "studio"
    ],
    "wof:name":"Ear Art Music Studios",
    "wof:placetype":"venue"
},
  "geometry": {"coordinates":[-122.940940857,49.1502914429],"type":"Point"}
}