{
  "type": "Feature",
  "properties": {
    "addr:full":"4 Inglis Pl Truro NS B2N 4B4",
    "addr:housenumber":"4",
    "addr:postcode":"b2n 4b4",
    "addr:street":"Inglis Pl",
    "iso:country":"CA",
    "sg:address":"4 Inglis Pl",
    "sg:city":"Truro",
    "sg:classifiers":[
        {
            "category":"Shopping",
            "subcategory":"Optical Goods",
            "type":"Retail Goods"
        }
    ],
    "sg:phone":"+1 902 893 3455",
    "sg:postcode":"B2N 4B4",
    "sg:province":"NS",
    "sg:tags":[
        "contact",
        "lense",
        "optician"
    ],
    "wof:name":"Vogue Optical Ltd",
    "wof:placetype":"venue"
},
  "geometry": {"coordinates":[-63.2766418457,45.3644447327],"type":"Point"}
}