{
  "type": "Feature",
  "properties": {
    "addr:full":"50 Bysham Park Dr Woodstock ON N4T 1R2",
    "addr:housenumber":"50",
    "addr:postcode":"n4t 1r2",
    "addr:street":"Bysham Park Dr",
    "iso:country":"CA",
    "sg:address":"50 Bysham Park Dr",
    "sg:city":"Woodstock",
    "sg:classifiers":[
        {
            "category":"Building & Trades",
            "subcategory":"Construction",
            "type":"Services"
        }
    ],
    "sg:phone":"+1 519 537 8425",
    "sg:postcode":"N4T 1R2",
    "sg:province":"ON",
    "sg:tags":[
        "roofing",
        "contractor",
        "general"
    ],
    "wof:name":"A P Hurley Construction",
    "wof:placetype":"venue"
},
  "geometry": {"coordinates":[-80.7197570801,43.1377716064],"type":"Point"}
}