{
  "type": "Feature",
  "properties": {
    "addr:full":"Burlington ON L7M 1A6",
    "addr:postcode":"l7m 1a6",
    "iso:country":"CA",
    "sg:city":"Burlington",
    "sg:classifiers":[
        {
            "category":"Building & Trades",
            "subcategory":"Construction",
            "type":"Services"
        }
    ],
    "sg:phone":"+1 905 331 9067",
    "sg:postcode":"L7M 1A6",
    "sg:province":"ON",
    "sg:tags":[
        "concrete",
        "contractor",
        "cutting",
        "breaking",
        "sawing"
    ],
    "wof:name":"Accurate Concrete Cutting",
    "wof:placetype":"venue"
},
  "geometry": {"coordinates":[-79.801109,43.366562],"type":"Point"}
}