{
  "type": "Feature",
  "properties": {
    "addr:full":"116 Av DE LA Gare Montmagny QC G5V 2T3",
    "addr:postcode":"g5v 2t3",
    "addr:street":"116 Av De La Gare",
    "iso:country":"CA",
    "sg:address":"116 Av DE LA Gare",
    "sg:city":"Montmagny",
    "sg:classifiers":[
        {
            "category":"Real Estate",
            "subcategory":"Real Estate Agent",
            "type":"Services"
        }
    ],
    "sg:phone":"+1 418 248 7472",
    "sg:postcode":"G5V 2T3",
    "sg:province":"QC",
    "sg:tags":[
        "desk",
        "space"
    ],
    "wof:name":"Immeubles Roger Blanchet",
    "wof:placetype":"venue"
},
  "geometry": {"coordinates":[-70.559242,46.978424],"type":"Point"}
}