{
  "type": "Feature",
  "properties": {
    "addr:full":"225 Main St S Russell MB R0J 1W0",
    "addr:housenumber":"225",
    "addr:postcode":"r0j 1w0",
    "addr:street":"Main St S",
    "iso:country":"CA",
    "sg:address":"225 Main St S",
    "sg:city":"Russell",
    "sg:classifiers":[
        {
            "category":"Home & Garden",
            "subcategory":"Garden Supply",
            "type":"Retail Goods"
        }
    ],
    "sg:phone":"+1 204 773 3770",
    "sg:postcode":"R0J 1W0",
    "sg:province":"MB",
    "sg:tags":[
        "nurseryman"
    ],
    "wof:name":"Hardy Zone",
    "wof:placetype":"venue"
},
  "geometry": {"coordinates":[-101.28787199999999,50.77787],"type":"Point"}
}