{
  "type": "Feature",
  "properties": {
    "addr:full":"Waterloo ON N2V 2B5",
    "addr:postcode":"n2v 2b5",
    "iso:country":"CA",
    "sg:city":"Waterloo",
    "sg:classifiers":[
        {
            "category":"Wholesale",
            "subcategory":"Durable Goods & Equipment",
            "type":"Manufacturing & Wholesale Goods"
        }
    ],
    "sg:phone":"+1 519 747 5454",
    "sg:postcode":"N2V 2B5",
    "sg:province":"ON",
    "sg:tags":[
        "advertising",
        "representative"
    ],
    "wof:name":"Jmb Sales",
    "wof:placetype":"venue"
},
  "geometry": {"coordinates":[-80.536613,43.509377],"type":"Point"}
}