{
  "type": "Feature",
  "properties": {
    "addr:full":"13 King St W Harrow ON N0R 1G0",
    "addr:housenumber":"13",
    "addr:postcode":"n0r 1g0",
    "addr:street":"King St W",
    "iso:country":"CA",
    "sg:address":"13 King St W",
    "sg:city":"Harrow",
    "sg:classifiers":[
        {
            "category":"Professional",
            "subcategory":"Lawyer & Legal Services",
            "type":"Services"
        }
    ],
    "sg:phone":"+1 519 738 4111",
    "sg:postcode":"N0R 1G0",
    "sg:province":"ON",
    "sg:tags":[
        "attorney"
    ],
    "wof:name":"Golden & Golden",
    "wof:placetype":"venue"
},
  "geometry": {"coordinates":[-82.918373,42.035439],"type":"Point"}
}