{
  "type": "Feature",
  "properties": {
    "addr:full":"2046 Rue Lapierre Lasalle QC H8N 2S2",
    "addr:housenumber":"2046",
    "addr:postcode":"h8n 2s2",
    "addr:street":"Rue Lapierre",
    "iso:country":"CA",
    "sg:address":"2046 Rue Lapierre",
    "sg:city":"Lasalle",
    "sg:classifiers":[
        {
            "category":"Restaurant",
            "type":"Food & Drink"
        }
    ],
    "sg:phone":"+1 514 365 4134",
    "sg:postcode":"H8N 2S2",
    "sg:province":"QC",
    "sg:tags":[
        "cafe"
    ],
    "wof:name":"Cafe Lo Stivalo",
    "wof:placetype":"venue"
},
  "geometry": {"coordinates":[-73.615402,45.436779],"type":"Point"}
}