{
  "type": "Feature",
  "properties": {
    "addr:full":"319 Ponderosa Ave Kaleden BC V0H 1K0",
    "addr:housenumber":"319",
    "addr:postcode":"v0h 1k0",
    "addr:street":"Ponderosa Ave",
    "iso:country":"CA",
    "sg:address":"319 Ponderosa Ave",
    "sg:city":"Kaleden",
    "sg:classifiers":[
        {
            "category":"Travel",
            "subcategory":"Hotels & Motels",
            "type":"Entertainment"
        }
    ],
    "sg:phone":"+1 250 497 5354",
    "sg:postcode":"V0H 1K0",
    "sg:province":"BC",
    "sg:tags":[
        "resort"
    ],
    "wof:name":"Ponderosa Point",
    "wof:placetype":"venue"
},
  "geometry": {"coordinates":[-119.602142,49.392677],"type":"Point"}
}