{
  "type": "Feature",
  "properties": {
    "addr:full":"660 1st St E Owen Sound ON N4K 6K4",
    "addr:housenumber":"660",
    "addr:postcode":"n4k 6k4",
    "addr:street":"1St St E",
    "iso:country":"CA",
    "sg:address":"660 1st St E",
    "sg:city":"Owen Sound",
    "sg:classifiers":[
        {
            "category":"Building & Trades",
            "subcategory":"Landscaping Services",
            "type":"Services"
        }
    ],
    "sg:phone":"+1 519 376 1042",
    "sg:postcode":"N4K 6K4",
    "sg:province":"ON",
    "sg:tags":[
        "landscape",
        "contractor"
    ],
    "wof:name":"Image Landscapes",
    "wof:placetype":"venue"
},
  "geometry": {"coordinates":[-80.930359,44.550663],"type":"Point"}
}