{
  "type": "Feature",
  "properties": {
    "addr:full":"3060 Sawmill Rd St Jacobs ON N0B 2N0",
    "addr:housenumber":"3060",
    "addr:postcode":"n0b 2n0",
    "addr:street":"Sawmill Rd St",
    "iso:country":"CA",
    "sg:address":"3060 Sawmill Rd",
    "sg:city":"St Jacobs",
    "sg:classifiers":[
        {
            "category":"Manufacturing",
            "subcategory":"Pottery",
            "type":"Manufacturing & Wholesale Goods"
        }
    ],
    "sg:phone":"+1 519 664 2289",
    "sg:postcode":"N0B 2N0",
    "sg:province":"ON",
    "wof:name":"A & F Gift & Souvenir CO",
    "wof:placetype":"venue"
},
  "geometry": {"coordinates":[-80.549911499,43.5446014404],"type":"Point"}
}