{
  "type": "Feature",
  "properties": {
    "addr:full":"Paris ON N3L 3E3",
    "addr:postcode":"n3l 3e3",
    "iso:country":"CA",
    "sg:city":"Paris",
    "sg:classifiers":[
        {
            "category":"Retail",
            "subcategory":"Auto Repair",
            "type":"Services"
        }
    ],
    "sg:phone":"+1 519 442 7110",
    "sg:postcode":"N3L 3E3",
    "sg:province":"ON",
    "sg:tags":[
        "repairing",
        "automobile"
    ],
    "wof:name":"Knd Automotive Ltd",
    "wof:placetype":"venue"
},
  "geometry": {"coordinates":[-80.39357800000001,43.182503],"type":"Point"}
}