{
  "type": "Feature",
  "properties": {
    "addr:full":"Saint-Damase QC J0H 1J0",
    "addr:postcode":"j0h 1j0",
    "iso:country":"CA",
    "sg:city":"Saint-Damase",
    "sg:classifiers":[
        {
            "category":"Recreation",
            "type":"Entertainment"
        }
    ],
    "sg:phone":"+1 450 797 2500",
    "sg:postcode":"J0H 1J0",
    "sg:province":"QC",
    "sg:tags":[
        "government",
        "hall",
        "auditorium"
    ],
    "wof:name":"Centre Communautaire",
    "wof:placetype":"venue"
},
  "geometry": {"coordinates":[-73.00928500000001,45.527142],"type":"Point"}
}