{
  "type": "Feature",
  "properties": {
    "iso:country":"CA",
    "sg:address":"102 Main St",
    "sg:city":"Nokomis",
    "sg:classifiers":[
        {
            "category":"Restaurant",
            "type":"Food & Drink"
        }
    ],
    "sg:phone":"+1 306 528 4545",
    "sg:postcode":"S0G 3R0",
    "sg:province":"SK",
    "wof:name":"Nokomis Pizza",
    "wof:placetype":"venue"
},
  "geometry": {"coordinates":[-105.007972717,51.5091514587],"type":"Point"}
}