{
  "type": "Feature",
  "properties": {
    "iso:country":"CA",
    "sg:address":"3010 Don Mills Rd",
    "sg:city":"North York",
    "sg:classifiers":[
        {
            "category":"Health Services",
            "subcategory":"Health Practitioner",
            "type":"Services"
        }
    ],
    "sg:phone":"+1 416 492 3831",
    "sg:postcode":"M2J 3C1",
    "sg:province":"ON",
    "sg:tags":[
        "acupuncture"
    ],
    "wof:name":"Zhang's Clinic of Acupuncture",
    "wof:placetype":"venue"
},
  "geometry": {"coordinates":[-79.35334777830001,43.7876663208],"type":"Point"}
}