{
  "type": "Feature",
  "properties": {
    "addr:full":"59 Eagle Dr Winnipeg MB R2R 1V4",
    "addr:housenumber":"59",
    "addr:postcode":"r2r 1v4",
    "addr:street":"Eagle Dr",
    "iso:country":"CA",
    "sg:address":"59 Eagle Dr",
    "sg:city":"Winnipeg",
    "sg:classifiers":[
        {
            "category":"Autos & Motor Vehicles",
            "subcategory":"Automobile Sales",
            "type":"Retail Goods"
        }
    ],
    "sg:phone":"+1 204 783 8512",
    "sg:postcode":"R2R 1V4",
    "sg:province":"MB",
    "sg:tags":[
        "equipment",
        "aircraft",
        "parts",
        "supply"
    ],
    "wof:name":"Goulet Aircraft Supply Ltd",
    "wof:placetype":"venue"
},
  "geometry": {"coordinates":[-97.2248916626,49.9354629517],"type":"Point"}
}