{
  "type": "Feature",
  "properties": {
    "addr:full":"174 Main St S Alexandria ON K0C 1A0",
    "addr:housenumber":"174",
    "addr:postcode":"k0c 1a0",
    "addr:street":"Main St S",
    "iso:country":"CA",
    "sg:address":"174 Main St S",
    "sg:city":"Alexandria",
    "sg:classifiers":[
        {
            "category":"Building & Trades",
            "subcategory":"Electrical",
            "type":"Services"
        }
    ],
    "sg:phone":"+1 613 525 2156",
    "sg:postcode":"K0C 1A0",
    "sg:province":"ON",
    "sg:tags":[
        "electric",
        "contractor"
    ],
    "wof:name":"Cdm Electric Inc",
    "wof:placetype":"venue"
},
  "geometry": {"coordinates":[-74.632744,45.306164],"type":"Point"}
}