{
  "type": "Feature",
  "properties": {
    "addr:full":"2188 No 5 Rd # 180 Richmond BC V6X 2T1",
    "addr:housenumber":"180",
    "addr:postcode":"2188;v6x 2t1",
    "addr:street":"No 5 Rd #",
    "iso:country":"CA",
    "sg:address":"2188 No 5 Rd # 180",
    "sg:city":"Richmond",
    "sg:classifiers":[
        {
            "category":"Real Estate",
            "subcategory":"Real Estate Agent",
            "type":"Services"
        }
    ],
    "sg:phone":"+1 604 273 6801",
    "sg:postcode":"V6X 2T1",
    "sg:province":"BC",
    "sg:tags":[
        "management"
    ],
    "wof:name":"Gold Team Management Svc Ltd",
    "wof:placetype":"venue"
},
  "geometry": {"coordinates":[-123.09128570599999,49.1957321167],"type":"Point"}
}