{
  "type": "Feature",
  "properties": {
    "addr:full":"Calgary AB T2R 1M6",
    "addr:postcode":"t2r 1m6",
    "iso:country":"CA",
    "sg:city":"Calgary",
    "sg:classifiers":[
        {
            "category":"Health Services",
            "subcategory":"Doctor",
            "type":"Services"
        }
    ],
    "sg:phone":"+1 403 244 3030",
    "sg:postcode":"T2R 1M6",
    "sg:province":"AB",
    "sg:tags":[
        "dentist"
    ],
    "wof:name":"Monzingo, Steve C DDS",
    "wof:placetype":"venue"
},
  "geometry": {"coordinates":[-114.081832886,51.0406150818],"type":"Point"}
}