{
  "type": "Feature",
  "properties": {
    "addr:full":"Terrace BC V8G 4R6",
    "addr:postcode":"v8g 4r6",
    "iso:country":"CA",
    "sg:city":"Terrace",
    "sg:classifiers":[
        {
            "category":"Organizations",
            "subcategory":"Professional Association",
            "type":"Services"
        }
    ],
    "sg:phone":"+1 250 635 1500",
    "sg:postcode":"V8G 4R6",
    "sg:province":"BC",
    "wof:name":"Skeena Native Development Soc",
    "wof:placetype":"venue"
},
  "geometry": {"coordinates":[-128.586838,54.510445],"type":"Point"}
}