{
  "type": "Feature",
  "properties": {
    "addr:full":"Montreal-Ouest QC H4X 1Z3",
    "addr:postcode":"h4x 1z3",
    "iso:country":"CA",
    "sg:city":"Montreal-Ouest",
    "sg:classifiers":[
        {
            "category":"Shopping",
            "subcategory":"Clothing, Apparel, & Fashions",
            "type":"Retail Goods"
        }
    ],
    "sg:phone":"+1 514 485 1351",
    "sg:postcode":"H4X 1Z3",
    "sg:province":"QC",
    "wof:name":"Rhonda's",
    "wof:placetype":"venue"
},
  "geometry": {"coordinates":[-73.648438,45.454239],"type":"Point"}
}