{
  "type": "Feature",
  "properties": {
    "iso:country":"CA",
    "sg:address":"8461 Hwy 9",
    "sg:city":"Clandeboye",
    "sg:classifiers":[
        {
            "category":"Education",
            "subcategory":"School",
            "type":"Public Place"
        }
    ],
    "sg:phone":"+1 204 738 4700",
    "sg:postcode":"R0C 0P0",
    "sg:province":"MB",
    "wof:name":"William S Patterson School",
    "wof:placetype":"venue"
},
  "geometry": {"coordinates":[-96.97472381590001,50.2417182922],"type":"Point"}
}