{
  "type": "Feature",
  "properties": {
    "iso:country":"CA",
    "sg:address":"29 Airport Rd NW",
    "sg:city":"Edmonton",
    "sg:classifiers":[
        {
            "category":"Building & Trades",
            "subcategory":"Equipment Rental",
            "type":"Services"
        }
    ],
    "sg:phone":"+1 780 453 2313",
    "sg:postcode":"T5G 0W6",
    "sg:province":"AB",
    "sg:tags":[
        "aircraft",
        "leasing",
        "charter"
    ],
    "wof:name":"Rjm Aviation Ltd",
    "wof:placetype":"venue"
},
  "geometry": {"coordinates":[-113.518814087,53.5672912598],"type":"Point"}
}