{
  "type": "Feature",
  "properties": {
    "addr:full":"North York ON M6B 3Y1",
    "addr:postcode":"m6b 3y1",
    "iso:country":"CA",
    "sg:city":"North York",
    "sg:classifiers":[
        {
            "category":"Wholesale",
            "subcategory":"Hardware",
            "type":"Manufacturing & Wholesale Goods"
        }
    ],
    "sg:phone":"+1 416 781 3399",
    "sg:postcode":"M6B 3Y1",
    "sg:province":"ON",
    "sg:tags":[
        "fastener"
    ],
    "wof:name":"Process Products Ltd",
    "wof:placetype":"venue"
},
  "geometry": {"coordinates":[-79.465057,43.705208],"type":"Point"}
}