{
  "type": "Feature",
  "properties": {
    "addr:full":"Concord ON L4K 4M1",
    "addr:postcode":"l4k 4m1",
    "iso:country":"CA",
    "sg:city":"Concord",
    "sg:classifiers":[
        {
            "category":"Manufacturing",
            "subcategory":"Musical Instruments",
            "type":"Manufacturing & Wholesale Goods"
        }
    ],
    "sg:phone":"+1 905 761 8549",
    "sg:postcode":"L4K 4M1",
    "sg:province":"ON",
    "wof:name":"Perri's Leathers Ltd",
    "wof:placetype":"venue"
},
  "geometry": {"coordinates":[-79.49215700000001,43.825283],"type":"Point"}
}