{
  "type": "Feature",
  "properties": {
    "addr:full":"2021 Merchants Gate Oakville ON L6M 3J1",
    "addr:housenumber":"2021",
    "addr:postcode":"l6m 3j1",
    "addr:street":"Merchants Gate",
    "iso:country":"CA",
    "sg:address":"2021 Merchants Gate",
    "sg:city":"Oakville",
    "sg:classifiers":[
        {
            "category":"Real Estate",
            "subcategory":"Real Estate Operator",
            "type":"Services"
        }
    ],
    "sg:phone":"+1 905 847 7170",
    "sg:postcode":"L6M 3J1",
    "sg:province":"ON",
    "sg:tags":[
        "apartment"
    ],
    "wof:name":"Oaklands",
    "wof:placetype":"venue"
},
  "geometry": {"coordinates":[-79.7395248413,43.4339942932],"type":"Point"}
}