{
  "type": "Feature",
  "properties": {
    "addr:full":"15 Kent St St Catharines ON L2S 1G9",
    "addr:housenumber":"15",
    "addr:postcode":"l2s 1g9",
    "addr:street":"Kent St",
    "iso:country":"CA",
    "sg:address":"15 Kent St",
    "sg:city":"St Catharines",
    "sg:classifiers":[
        {
            "category":"Retail",
            "subcategory":"Repair Shop",
            "type":"Services"
        }
    ],
    "sg:phone":"+1 905 682 5729",
    "sg:postcode":"L2S 1G9",
    "sg:province":"ON",
    "sg:tags":[
        "steel",
        "welding"
    ],
    "wof:name":"Dressels Steel Works Ltd",
    "wof:placetype":"venue"
},
  "geometry": {"coordinates":[-79.25135,43.141232],"type":"Point"}
}