{
  "type": "Feature",
  "properties": {
    "addr:full":"920 Cannell Rd SW Calgary AB T2W 1T4",
    "addr:housenumber":"920",
    "addr:postcode":"t2w 1t4",
    "addr:street":"Cannell Rd Sw",
    "iso:country":"CA",
    "sg:address":"920 Cannell Rd SW",
    "sg:city":"Calgary",
    "sg:classifiers":[
        {
            "category":"Organizations",
            "subcategory":"Professional Association",
            "type":"Services"
        }
    ],
    "sg:phone":"+1 403 241 7774",
    "sg:postcode":"T2W 1T4",
    "sg:province":"AB",
    "wof:name":"Ukranian Canadian Congress",
    "wof:placetype":"venue"
},
  "geometry": {"coordinates":[-114.078148,50.940018],"type":"Point"}
}