{
  "type": "Feature",
  "properties": {
    "addr:full":"1765 Jane St North Bay ON P1B 3K3",
    "addr:housenumber":"1765",
    "addr:postcode":"p1b 3k3",
    "addr:street":"Jane St",
    "iso:country":"CA",
    "sg:address":"1765 Jane St",
    "sg:city":"North Bay",
    "sg:classifiers":[
        {
            "category":"Government",
            "subcategory":"Office",
            "type":"Public Place"
        }
    ],
    "sg:phone":"+1 705 476 6400",
    "sg:postcode":"P1B 3K3",
    "sg:province":"ON",
    "wof:name":"North Bay Mental Health Svc",
    "wof:placetype":"venue"
},
  "geometry": {"coordinates":[-79.48657989500001,46.325050354],"type":"Point"}
}