{
  "type": "Feature",
  "properties": {
    "addr:full":"1323 Central Ave Prince Albert SK S6V 4W1",
    "addr:housenumber":"1323",
    "addr:postcode":"s6v 4w1",
    "addr:street":"Central Ave",
    "iso:country":"CA",
    "sg:address":"1323 Central Ave",
    "sg:city":"Prince Albert",
    "sg:classifiers":[
        {
            "category":"Shopping",
            "subcategory":"Gifts & Souvenirs",
            "type":"Retail Goods"
        }
    ],
    "sg:phone":"+1 306 922 5877",
    "sg:postcode":"S6V 4W1",
    "sg:province":"SK",
    "sg:tags":[
        "shop",
        "jeweler"
    ],
    "wof:name":"Isabella's Imports",
    "wof:placetype":"venue"
},
  "geometry": {"coordinates":[-105.754402,53.200668],"type":"Point"}
}