{
  "type": "Feature",
  "properties": {
    "addr:full":"1369 Pembroke St W Pembroke ON K8A 7A5",
    "addr:housenumber":"1369",
    "addr:postcode":"k8a 7a5",
    "addr:street":"Pembroke St W",
    "iso:country":"CA",
    "sg:address":"1369 Pembroke St W",
    "sg:city":"Pembroke",
    "sg:classifiers":[
        {
            "category":"Freight",
            "type":"Transportation"
        }
    ],
    "sg:phone":"+1 613 735 3961",
    "sg:postcode":"K8A 7A5",
    "sg:province":"ON",
    "sg:tags":[
        "trucking"
    ],
    "wof:name":"Manitoulin Transport Inc",
    "wof:placetype":"venue"
},
  "geometry": {"coordinates":[-77.15371704099999,45.8348808289],"type":"Point"}
}