{
  "type": "Feature",
  "properties": {
    "addr:full":"Alexandria ON K0C 1A0",
    "addr:postcode":"k0c 1a0",
    "iso:country":"CA",
    "sg:city":"Alexandria",
    "sg:classifiers":[
        {
            "category":"Insurance",
            "subcategory":"Insurance Agent",
            "type":"Services"
        }
    ],
    "sg:phone":"+1 613 525 2557",
    "sg:postcode":"K0C 1A0",
    "sg:province":"ON",
    "wof:name":"Glengarry Farmers Mutual Fire",
    "wof:placetype":"venue"
},
  "geometry": {"coordinates":[-74.63692474370001,45.3117980957],"type":"Point"}
}