{
  "type": "Feature",
  "properties": {
    "iso:country":"CA",
    "sg:city":"Massey",
    "sg:classifiers":[
        {
            "category":"Education",
            "subcategory":"Library",
            "type":"Public Place"
        }
    ],
    "sg:phone":"+1 705 865 2970",
    "sg:postcode":"P0P 1P0",
    "sg:province":"ON",
    "wof:name":"Sagamok Anishnawbek Public Lib",
    "wof:placetype":"venue"
},
  "geometry": {"coordinates":[-82.0762176514,46.2126159668],"type":"Point"}
}