{
  "type": "Feature",
  "properties": {
    "addr:full":"1 Rochford St # 14 Charlottetown PE C1A 9L2",
    "addr:housenumber":"1",
    "addr:postcode":"c1a 9l2",
    "addr:street":"Rochford St # 14",
    "iso:country":"CA",
    "sg:address":"1 Rochford St # 14",
    "sg:city":"Charlottetown",
    "sg:classifiers":[
        {
            "category":"Health Services",
            "subcategory":"Podiatrist",
            "type":"Services"
        }
    ],
    "sg:phone":"+1 902 892 7043",
    "sg:postcode":"C1A 9L2",
    "sg:province":"PE",
    "wof:name":"Bettles, K DPM",
    "wof:placetype":"venue"
},
  "geometry": {"coordinates":[-63.1296386719,46.231388092],"type":"Point"}
}