{
  "type": "Feature",
  "properties": {
    "addr:full":"381 Mcarthur Ave Vanier ON K1L 6N5",
    "addr:housenumber":"381",
    "addr:postcode":"k1l 6n5",
    "addr:street":"Mcarthur Ave",
    "iso:country":"CA",
    "sg:address":"381 Mcarthur Ave",
    "sg:city":"Vanier",
    "sg:classifiers":[
        {
            "category":"Food & Beverages",
            "subcategory":"Groceries & Convenience Stores",
            "type":"Retail Goods"
        }
    ],
    "sg:phone":"+1 613 749 1247",
    "sg:postcode":"K1L 6N5",
    "sg:province":"ON",
    "sg:tags":[
        "grocer"
    ],
    "wof:name":"Mario's Food Centre",
    "wof:placetype":"venue"
},
  "geometry": {"coordinates":[-75.650536,45.432056],"type":"Point"}
}