{
  "type": "Feature",
  "properties": {
    "addr:full":"Surrey BC V3W 1K7",
    "addr:postcode":"v3w 1k7",
    "iso:country":"CA",
    "sg:city":"Surrey",
    "sg:classifiers":[
        {
            "category":"Retail",
            "subcategory":"Repair Shop",
            "type":"Services"
        }
    ],
    "sg:phone":"+1 604 597 3888",
    "sg:postcode":"V3W 1K7",
    "sg:province":"BC",
    "sg:tags":[
        "upholsterer"
    ],
    "wof:name":"Unique Custom Upholstery",
    "wof:placetype":"venue"
},
  "geometry": {"coordinates":[-122.86393700000001,49.155319],"type":"Point"}
}