{
  "type": "Feature",
  "properties": {
    "iso:country":"CA",
    "sg:city":"Concord",
    "sg:classifiers":[
        {
            "category":"Professional",
            "subcategory":"Business Services",
            "type":"Services"
        }
    ],
    "sg:phone":"+1 905 660 6626",
    "sg:postcode":"L4K 4G7",
    "sg:province":"ON",
    "sg:tags":[
        "license",
        "government"
    ],
    "wof:name":"Ontario Driver & Vehicle Lcnsg",
    "wof:placetype":"venue"
},
  "geometry": {"coordinates":[-79.500259,43.80302],"type":"Point"}
}