{
  "type": "Feature",
  "properties": {
    "addr:full":"1271 Av Bernard Outremont QC H2V 1V8",
    "addr:housenumber":"1271",
    "addr:postcode":"h2v 1v8",
    "addr:street":"Av Bernard",
    "iso:country":"CA",
    "sg:address":"1271 Av Bernard",
    "sg:city":"Outremont",
    "sg:classifiers":[
        {
            "category":"Food & Beverages",
            "subcategory":"Bakery",
            "type":"Retail Goods"
        }
    ],
    "sg:phone":"+1 514 270 2559",
    "sg:postcode":"H2V 1V8",
    "sg:province":"QC",
    "sg:tags":[
        "baker"
    ],
    "wof:name":"Boulangerie Premiere Moisson",
    "wof:placetype":"venue"
},
  "geometry": {"coordinates":[-73.609352,45.519688],"type":"Point"}
}