{
  "type": "Feature",
  "properties": {
    "iso:country":"CA",
    "sg:address":"114 Macdonald Ave",
    "sg:city":"Sault Ste Marie",
    "sg:classifiers":[
        {
            "category":"Organizations",
            "subcategory":"Religious Organization",
            "type":"Services"
        }
    ],
    "sg:phone":"+1 705 942 8546",
    "sg:postcode":"P6B 1H3",
    "sg:province":"ON",
    "sg:tags":[
        "church"
    ],
    "wof:name":"Our Lady of Good Counsel Chrch",
    "wof:placetype":"venue"
},
  "geometry": {"coordinates":[-84.3226470947,46.5158538818],"type":"Point"}
}