{
  "type": "Feature",
  "properties": {
    "addr:full":"417 Keltic Dr Sydney NS B1L 1B8",
    "addr:housenumber":"417",
    "addr:postcode":"b1l 1b8",
    "addr:street":"Keltic Dr",
    "iso:country":"CA",
    "sg:address":"417 Keltic Dr",
    "sg:city":"Sydney",
    "sg:classifiers":[
        {
            "category":"Building & Trades",
            "subcategory":"Construction",
            "type":"Services"
        }
    ],
    "sg:phone":"+1 902 567 3600",
    "sg:postcode":"B1L 1B8",
    "sg:province":"NS",
    "sg:tags":[
        "home",
        "general",
        "improvement",
        "contractor"
    ],
    "wof:name":"Cormack Builders Ltd",
    "wof:placetype":"venue"
},
  "geometry": {"coordinates":[-60.242821,46.122669],"type":"Point"}
}