{
  "type": "Feature",
  "properties": {
    "iso:country":"CA",
    "sg:address":"9680 10E Av # 203",
    "sg:city":"Saint-Georges",
    "sg:classifiers":[
        {
            "category":"Building & Trades",
            "subcategory":"Electrical",
            "type":"Services"
        }
    ],
    "sg:phone":"+1 418 227 7575",
    "sg:postcode":"G5Y 8J8",
    "sg:province":"QC",
    "sg:tags":[
        "electric",
        "contractor"
    ],
    "wof:name":"Electricite Quebec Nord-Sud",
    "wof:placetype":"venue"
},
  "geometry": {"coordinates":[-70.67115020750001,46.1233482361],"type":"Point"}
}