{
  "type": "Feature",
  "properties": {
    "iso:country":"CA",
    "sg:city":"Oakville",
    "sg:classifiers":[
        {
            "category":"Health Services",
            "subcategory":"Doctor",
            "type":"Services"
        }
    ],
    "sg:phone":"+1 905 845 2141",
    "sg:postcode":"L6L 2X4",
    "sg:province":"ON",
    "sg:tags":[
        "dentist"
    ],
    "wof:name":"Shaughnessy, Stephen DDS",
    "wof:placetype":"venue"
},
  "geometry": {"coordinates":[-79.704674,43.430939],"type":"Point"}
}