{
  "type": "Feature",
  "properties": {
    "iso:country":"CA",
    "sg:address":"2177 Plains Rd E",
    "sg:city":"Burlington",
    "sg:classifiers":[
        {
            "category":"Manufacturing",
            "subcategory":"Motor Vehicles & Parts",
            "type":"Manufacturing & Wholesale Goods"
        }
    ],
    "sg:phone":"+1 905 528 1104",
    "sg:postcode":"L7R 3R3",
    "sg:province":"ON",
    "sg:tags":[
        "body",
        "equipment",
        "truck"
    ],
    "wof:name":"Del Equipment Ltd",
    "wof:placetype":"venue"
},
  "geometry": {"coordinates":[-79.8134689331,43.3433494568],"type":"Point"}
}