{
  "type": "Feature",
  "properties": {
    "addr:full":"607 Main St Shediac NB E4P 2C6",
    "addr:housenumber":"607",
    "addr:postcode":"e4p 2c6",
    "addr:street":"Main St",
    "iso:country":"CA",
    "sg:address":"607 Main St",
    "sg:city":"Shediac",
    "sg:classifiers":[
        {
            "category":"Restaurant",
            "type":"Food & Drink"
        }
    ],
    "sg:phone":"+1 506 533 9008",
    "sg:postcode":"E4P 2C6",
    "sg:province":"NB",
    "sg:tags":[
        "pub"
    ],
    "wof:name":"Bayou Pub & Eatery",
    "wof:placetype":"venue"
},
  "geometry": {"coordinates":[-64.51132200000001,46.224758],"type":"Point"}
}