{
  "type": "Feature",
  "properties": {
    "addr:full":"1911 Ch Gascon Lachenaie QC J6X 4H2",
    "addr:postcode":"1911;j6x 4h2",
    "addr:street":"Ch Gascon",
    "iso:country":"CA",
    "sg:address":"1911 Ch Gascon",
    "sg:city":"Lachenaie",
    "sg:classifiers":[
        {
            "category":"Bars & Pubs",
            "type":"Food & Drink"
        }
    ],
    "sg:phone":"+1 450 471 9169",
    "sg:postcode":"J6X 4H2",
    "sg:province":"QC",
    "sg:tags":[
        "lounge",
        "cocktail"
    ],
    "wof:name":"O'Gascon Inc",
    "wof:placetype":"venue"
},
  "geometry": {"coordinates":[-73.657768,45.719219],"type":"Point"}
}