{
  "type": "Feature",
  "properties": {
    "iso:country":"CA",
    "sg:city":"Montreal",
    "sg:classifiers":[
        {
            "category":"Education",
            "subcategory":"Vocational School",
            "type":"Public Place"
        }
    ],
    "sg:phone":"+1 514 866 6646",
    "sg:postcode":"H2Z 1V7",
    "sg:province":"QC",
    "sg:tags":[
        "training",
        "computer"
    ],
    "wof:name":"Sofitech Inc",
    "wof:placetype":"venue"
},
  "geometry": {"coordinates":[-73.55745697019999,45.513343811],"type":"Point"}
}