{
  "type": "Feature",
  "properties": {
    "iso:country":"CA",
    "sg:address":"2517 Rue Guenette",
    "sg:city":"Saint-Laurent",
    "sg:classifiers":[
        {
            "category":"Professional",
            "subcategory":"Computer Services",
            "type":"Services"
        }
    ],
    "sg:phone":"+1 514 338 3700",
    "sg:postcode":"H4R 2E9",
    "sg:province":"QC",
    "sg:tags":[
        "information",
        "system",
        "consultant"
    ],
    "wof:name":"Intelect Solution Inc",
    "wof:placetype":"venue"
},
  "geometry": {"coordinates":[-73.72998809809999,45.501247406],"type":"Point"}
}