{
  "type": "Feature",
  "properties": {
    "addr:full":"1780 Rue Brouillette Saint-Hyacinthe QC J2T 2G8",
    "addr:housenumber":"1780",
    "addr:postcode":"j2t 2g8",
    "addr:street":"Rue Brouillette",
    "iso:country":"CA",
    "sg:address":"1780 Rue Brouillette",
    "sg:city":"Saint-Hyacinthe",
    "sg:classifiers":[
        {
            "category":"Building & Trades",
            "subcategory":"Construction",
            "type":"Services"
        }
    ],
    "sg:phone":"+1 450 774 7923",
    "sg:postcode":"J2T 2G8",
    "sg:province":"QC",
    "sg:tags":[
        "excavating",
        "contractor"
    ],
    "wof:name":"Terramex Inc",
    "wof:placetype":"venue"
},
  "geometry": {"coordinates":[-72.92385899999999,45.628914],"type":"Point"}
}