{
  "type": "Feature",
  "properties": {
    "iso:country":"CA",
    "sg:address":"100 Market Dr",
    "sg:city":"Milton",
    "sg:classifiers":[
        {
            "category":"Freight",
            "type":"Transportation"
        }
    ],
    "sg:phone":"+1 905 693 8088",
    "sg:postcode":"L9T 3H5",
    "sg:province":"ON",
    "sg:tags":[
        "trucking"
    ],
    "wof:name":"Peter Hodge Transport Ltd",
    "wof:placetype":"venue"
},
  "geometry": {"coordinates":[-79.9021682739,43.5218582153],"type":"Point"}
}