{
  "type": "Feature",
  "properties": {
    "iso:country":"CA",
    "sg:address":"1100 Av Galibois",
    "sg:city":"Vanier",
    "sg:classifiers":[
        {
            "category":"Shopping",
            "subcategory":"Computers & Home Electronics",
            "type":"Retail Goods"
        }
    ],
    "sg:phone":"+1 418 684 2244",
    "sg:postcode":"G1M 3M7",
    "sg:province":"QC",
    "sg:tags":[
        "equipment",
        "dealer"
    ],
    "wof:name":"Centre Laser Plus",
    "wof:placetype":"venue"
},
  "geometry": {"coordinates":[-71.271721,46.832531],"type":"Point"}
}