{
  "type": "Feature",
  "properties": {
    "iso:country":"CA",
    "sg:address":"225 Nebo Rd",
    "sg:city":"Hamilton",
    "sg:classifiers":[
        {
            "category":"Home & Garden",
            "subcategory":"Home Furnishings",
            "type":"Retail Goods"
        }
    ],
    "sg:phone":"+1 905 574 8806",
    "sg:postcode":"L8W 2E1",
    "sg:province":"ON",
    "sg:tags":[
        "lighting",
        "fixture"
    ],
    "wof:name":"Home Lighting Factory Outlet",
    "wof:placetype":"venue"
},
  "geometry": {"coordinates":[-79.83749389650001,43.1922225952],"type":"Point"}
}