{
  "type": "Feature",
  "properties": {
    "iso:country":"CA",
    "sg:address":"20285 Dewdney Trunk Rd",
    "sg:city":"Maple Ridge",
    "sg:classifiers":[
        {
            "category":"Organizations",
            "subcategory":"Religious Organization",
            "type":"Services"
        }
    ],
    "sg:phone":"+1 604 465 5383",
    "sg:postcode":"V2X 3C9",
    "sg:province":"BC",
    "sg:tags":[
        "church"
    ],
    "wof:name":"St Luke's Catholic Church",
    "wof:placetype":"venue"
},
  "geometry": {"coordinates":[-122.658546448,49.2216148376],"type":"Point"}
}