{
  "type": "Feature",
  "properties": {
    "iso:country":"CA",
    "sg:address":"Conception Bay Hwy",
    "sg:city":"Bay Roberts",
    "sg:classifiers":[
        {
            "category":"Real Estate",
            "subcategory":"Real Estate Operator",
            "type":"Services"
        }
    ],
    "sg:phone":"+1 709 786 3941",
    "sg:postcode":"A0A 1G0",
    "sg:province":"NL",
    "sg:tags":[
        "mall",
        "shopping",
        "center"
    ],
    "wof:name":"Bay Roberts Mall",
    "wof:placetype":"venue"
},
  "geometry": {"coordinates":[-53.2798576355,47.5817451477],"type":"Point"}
}