{
  "type": "Feature",
  "properties": {
    "addr:full":"175 Rue Charlotte Sorel-Tracy QC J3P 1H7",
    "addr:housenumber":"175",
    "addr:postcode":"j3p 1h7",
    "addr:street":"Rue Charlotte",
    "iso:country":"CA",
    "sg:address":"175 Rue Charlotte",
    "sg:city":"Sorel-Tracy",
    "sg:classifiers":[
        {
            "category":"Organizations",
            "subcategory":"Professional Association",
            "type":"Services"
        }
    ],
    "sg:phone":"+1 450 742 7297",
    "sg:postcode":"J3P 1H7",
    "sg:province":"QC",
    "wof:name":"Club L'Age D'Or Bas Richelieu",
    "wof:placetype":"venue"
},
  "geometry": {"coordinates":[-73.10704800000001,46.044937],"type":"Point"}
}