{
  "type": "Feature",
  "properties": {
    "addr:full":"1054 Harcourt Harcourt ON K0L 1X0",
    "addr:housenumber":"1054",
    "addr:postcode":"k0l 1x0",
    "addr:street":"Harcourt Harcourt",
    "iso:country":"CA",
    "sg:address":"1054 Harcourt",
    "sg:city":"Harcourt",
    "sg:classifiers":[
        {
            "category":"Organizations",
            "subcategory":"Religious Organization",
            "type":"Services"
        }
    ],
    "sg:phone":"+1 705 448 2957",
    "sg:postcode":"K0L 1X0",
    "sg:province":"ON",
    "sg:tags":[
        "church"
    ],
    "wof:name":"Harcourt Community Chapel",
    "wof:placetype":"venue"
},
  "geometry": {"coordinates":[-78.147476,45.08493],"type":"Point"}
}