{
  "type": "Feature",
  "properties": {
    "addr:full":"110 Principale St N North Hatley QC J0B 2C0",
    "addr:housenumber":"110",
    "addr:postcode":"j0b 2c0",
    "addr:street":"Principale St N",
    "iso:country":"CA",
    "sg:address":"110 Principale St N",
    "sg:city":"North Hatley",
    "sg:classifiers":[
        {
            "category":"Restaurant",
            "type":"Food & Drink"
        }
    ],
    "sg:phone":"+1 819 842 2782",
    "sg:postcode":"J0B 2C0",
    "sg:province":"QC",
    "wof:name":"Jay's Place",
    "wof:placetype":"venue"
},
  "geometry": {"coordinates":[-71.9894104004,45.1822166443],"type":"Point"}
}