{
  "type": "Feature",
  "properties": {
    "addr:full":"3202 Wharton Way Mississauga ON L4X 2C1",
    "addr:housenumber":"3202",
    "addr:postcode":"l4x 2c1",
    "addr:street":"Wharton Way",
    "iso:country":"CA",
    "sg:address":"3202 Wharton Way",
    "sg:city":"Mississauga",
    "sg:classifiers":[
        {
            "category":"Manufacturing",
            "subcategory":"Tools & Machinery",
            "type":"Manufacturing & Wholesale Goods"
        }
    ],
    "sg:phone":"+1 905 625 0367",
    "sg:postcode":"L4X 2C1",
    "sg:province":"ON",
    "sg:tags":[
        "machine",
        "shop"
    ],
    "wof:name":"Wintech Cnc Machining",
    "wof:placetype":"venue"
},
  "geometry": {"coordinates":[-79.5791397095,43.6226997375],"type":"Point"}
}