{
  "type": "Feature",
  "properties": {
    "addr:full":"328 Ritson Rd N Oshawa ON L1G 5P8",
    "addr:housenumber":"328",
    "addr:postcode":"l1g 5p8",
    "addr:street":"Ritson Rd N",
    "iso:country":"CA",
    "sg:address":"328 Ritson Rd N",
    "sg:city":"Oshawa",
    "sg:classifiers":[
        {
            "category":"Home & Garden",
            "subcategory":"Building Materials",
            "type":"Retail Goods"
        }
    ],
    "sg:phone":"+1 905 725 4744",
    "sg:postcode":"L1G 5P8",
    "sg:province":"ON",
    "sg:tags":[
        "lumber"
    ],
    "wof:name":"Peacock Lumber Ltd",
    "wof:placetype":"venue"
},
  "geometry": {"coordinates":[-78.8579330444,43.9087638855],"type":"Point"}
}