{
  "type": "Feature",
  "properties": {
    "iso:country":"CA",
    "sg:address":"2010 Appleby Line",
    "sg:city":"Burlington",
    "sg:classifiers":[
        {
            "category":"Food & Beverages",
            "subcategory":"Groceries & Convenience Stores",
            "type":"Retail Goods"
        }
    ],
    "sg:phone":"+1 905 331 7900",
    "sg:postcode":"L7L 6M6",
    "sg:province":"ON",
    "sg:tags":[
        "grocer"
    ],
    "wof:name":"Ultra Food & Drug",
    "wof:placetype":"venue"
},
  "geometry": {"coordinates":[-79.791222,43.394264],"type":"Point"}
}