{
  "type": "Feature",
  "properties": {
    "addr:full":"428 Huron Rd Mar ON N0H 1X0",
    "addr:housenumber":"428",
    "addr:postcode":"n0h 1x0",
    "addr:street":"Huron Rd",
    "iso:country":"CA",
    "sg:address":"428 Huron Rd",
    "sg:city":"Mar",
    "sg:classifiers":[
        {
            "category":"Travel",
            "subcategory":"Hotels & Motels",
            "type":"Entertainment"
        }
    ],
    "sg:phone":"+1 519 534 2098",
    "sg:postcode":"N0H 1X0",
    "sg:province":"ON",
    "sg:tags":[
        "cottage",
        "campground",
        "cabin"
    ],
    "wof:name":"Red Bay Tent & Trailer Camp",
    "wof:placetype":"venue"
},
  "geometry": {"coordinates":[-81.21215100000001,44.820702],"type":"Point"}
}