{
  "type": "Feature",
  "properties": {
    "addr:full":"6100 Ch DE LA Cote-DE-Liesse Saint-Laurent QC H4T 1E3",
    "addr:postcode":"6100;h4t 1e3",
    "addr:street":"Ch De La Cote-De-Liesse",
    "iso:country":"CA",
    "sg:address":"6100 Ch DE LA Cote-DE-Liesse",
    "sg:city":"Saint-Laurent",
    "sg:classifiers":[
        {
            "category":"Wholesale",
            "subcategory":"Groceries",
            "type":"Manufacturing & Wholesale Goods"
        }
    ],
    "sg:phone":"+1 514 343 4463",
    "sg:postcode":"H4T 1E3",
    "sg:province":"QC",
    "sg:tags":[
        "food",
        "broker"
    ],
    "wof:name":"Aliments Midlon Foods Inc",
    "wof:placetype":"venue"
},
  "geometry": {"coordinates":[-73.687408,45.488487],"type":"Point"}
}