{
  "type": "Feature",
  "properties": {
    "addr:full":"PO Box 210 Shelburne NS B0T 1W0",
    "addr:housenumber":"po",
    "addr:postcode":"b0t 1w0",
    "addr:street":"Box 210",
    "iso:country":"CA",
    "sg:address":"PO Box 210",
    "sg:city":"Shelburne",
    "sg:classifiers":[
        {
            "category":"Organizations",
            "subcategory":"Religious Organization",
            "type":"Services"
        }
    ],
    "sg:phone":"+1 902 723 2491",
    "sg:postcode":"B0T 1W0",
    "sg:province":"NS",
    "sg:tags":[
        "church"
    ],
    "wof:name":"Woods Harbour Baptist Church",
    "wof:placetype":"venue"
},
  "geometry": {"coordinates":[-65.31564299999999,43.765659],"type":"Point"}
}