{
  "type": "Feature",
  "properties": {
    "addr:full":"32 Paint St Port Hawkesbury NS B9A 3J8",
    "addr:housenumber":"32",
    "addr:postcode":"b9a 3j8",
    "addr:street":"Paint St",
    "iso:country":"CA",
    "sg:address":"32 Paint St",
    "sg:city":"Port Hawkesbury",
    "sg:classifiers":[
        {
            "category":"Government",
            "subcategory":"Office",
            "type":"Public Place"
        }
    ],
    "sg:phone":"+1 902 625 3200",
    "sg:postcode":"B9A 3J8",
    "sg:province":"NS",
    "wof:name":"Nova Scotia Economic Dev Dept",
    "wof:placetype":"venue"
},
  "geometry": {"coordinates":[-61.333633,45.617886],"type":"Point"}
}