{
  "type": "Feature",
  "properties": {
    "addr:full":"508 Helmcken St Vancouver BC V6B 5C7",
    "addr:housenumber":"508",
    "addr:postcode":"bc v6b 5c7",
    "addr:street":"Helmcken St",
    "iso:country":"CA",
    "sg:address":"508 Helmcken St",
    "sg:city":"Vancouver",
    "sg:classifiers":[
        {
            "category":"Real Estate",
            "subcategory":"Real Estate Agent",
            "type":"Services"
        }
    ],
    "sg:phone":"+1 604 688 8298",
    "sg:postcode":"V6B 5C7",
    "sg:province":"BC",
    "sg:tags":[
        "authorities",
        "housing"
    ],
    "wof:name":"Jubilee House",
    "wof:placetype":"venue"
},
  "geometry": {"coordinates":[-123.12294,49.276974],"type":"Point"}
}