{
  "type": "Feature",
  "properties": {
    "addr:full":"425 Cecelia St Pembroke ON K8A 1S7",
    "addr:housenumber":"425",
    "addr:postcode":"k8a 1s7",
    "addr:street":"Cecelia St",
    "iso:country":"CA",
    "sg:address":"425 Cecelia St",
    "sg:city":"Pembroke",
    "sg:classifiers":[
        {
            "category":"Social Services",
            "type":"Services"
        }
    ],
    "sg:phone":"+1 613 735 1921",
    "sg:postcode":"K8A 1S7",
    "sg:province":"ON",
    "sg:tags":[
        "organization",
        "welfare"
    ],
    "wof:name":"Canadian National Institute",
    "wof:placetype":"venue"
},
  "geometry": {"coordinates":[-77.10335499999999,45.821167],"type":"Point"}
}