{
  "type": "Feature",
  "properties": {
    "addr:full":"1100 11 St SE Calgary AB T2G 4T3",
    "addr:housenumber":"1100",
    "addr:postcode":"t2g 4t3",
    "addr:street":"11 St Se",
    "iso:country":"CA",
    "sg:address":"1100 11 St SE",
    "sg:city":"Calgary",
    "sg:classifiers":[
        {
            "category":"Manufacturing",
            "subcategory":"Metals",
            "type":"Manufacturing & Wholesale Goods"
        }
    ],
    "sg:phone":"+1 403 263 0657",
    "sg:postcode":"T2G 4T3",
    "sg:province":"AB",
    "sg:tags":[
        "coating",
        "powder"
    ],
    "wof:name":"Alberta Powder Coating",
    "wof:placetype":"venue"
},
  "geometry": {"coordinates":[-114.038132,51.040359],"type":"Point"}
}