{
  "type": "Feature",
  "properties": {
    "addr:full":"Calgary AB T2V 0L8",
    "addr:postcode":"t2v 0l8",
    "iso:country":"CA",
    "sg:city":"Calgary",
    "sg:classifiers":[
        {
            "category":"Shopping",
            "subcategory":"Clothing, Apparel, & Fashions",
            "type":"Retail Goods"
        }
    ],
    "sg:phone":"+1 403 238 2605",
    "sg:postcode":"T2V 0L8",
    "sg:province":"AB",
    "sg:tags":[
        "alteration"
    ],
    "wof:name":"Anna's Alterations",
    "wof:placetype":"venue"
},
  "geometry": {"coordinates":[-114.116241,50.972012],"type":"Point"}
}