{
  "type": "Feature",
  "properties": {
    "iso:country":"CA",
    "sg:address":"10 Rexway Rd",
    "sg:city":"London",
    "sg:classifiers":[
        {
            "category":"Retail",
            "subcategory":"Animal Services",
            "type":"Services"
        }
    ],
    "sg:phone":"+1 519 472 3439",
    "sg:postcode":"N6G 3C3",
    "sg:province":"ON",
    "sg:tags":[
        "pet",
        "boarding",
        "sitting"
    ],
    "wof:name":"Pets At Home",
    "wof:placetype":"venue"
},
  "geometry": {"coordinates":[-81.319443,43.01136],"type":"Point"}
}