{
  "type": "Feature",
  "properties": {
    "iso:country":"CA",
    "sg:city":"Fredericton",
    "sg:classifiers":[
        {
            "category":"Professional",
            "subcategory":"Lawyer & Legal Services",
            "type":"Services"
        }
    ],
    "sg:phone":"+1 506 453 0900",
    "sg:postcode":"E3B 6Z3",
    "sg:province":"NB",
    "sg:tags":[
        "attorney"
    ],
    "wof:name":"Rowan, Donald F",
    "wof:placetype":"venue"
},
  "geometry": {"coordinates":[-66.6460800171,45.9633331299],"type":"Point"}
}