{
  "type": "Feature",
  "properties": {
    "addr:full":"Abbotsford BC V2S 3R1",
    "addr:postcode":"v2s 3r1",
    "iso:country":"CA",
    "sg:city":"Abbotsford",
    "sg:classifiers":[
        {
            "category":"Shopping",
            "subcategory":"Jewelry",
            "type":"Retail Goods"
        }
    ],
    "sg:phone":"+1 604 853 9192",
    "sg:postcode":"V2S 3R1",
    "sg:province":"BC",
    "sg:tags":[
        "jeweler"
    ],
    "wof:name":"Lee's Fine Jewellery Ltd",
    "wof:placetype":"venue"
},
  "geometry": {"coordinates":[-122.293755,49.048443],"type":"Point"}
}