{
  "type": "Feature",
  "properties": {
    "addr:full":"225 Admiral Blvd Mississauga ON L5T 2T3",
    "addr:housenumber":"225",
    "addr:postcode":"l5t 2t3",
    "addr:street":"Admiral Blvd",
    "iso:country":"CA",
    "sg:address":"225 Admiral Blvd",
    "sg:city":"Mississauga",
    "sg:classifiers":[
        {
            "category":"Manufacturing",
            "subcategory":"Tools & Machinery",
            "type":"Manufacturing & Wholesale Goods"
        }
    ],
    "sg:phone":"+1 905 565 6700",
    "sg:postcode":"L5T 2T3",
    "sg:province":"ON",
    "sg:tags":[
        "flashlight"
    ],
    "wof:name":"Shariffa Imports",
    "wof:placetype":"venue"
},
  "geometry": {"coordinates":[-79.697807,43.646629],"type":"Point"}
}