{
  "type": "Feature",
  "properties": {
    "addr:full":"220 Hodsman Rd Regina SK S4N 5X4",
    "addr:housenumber":"220",
    "addr:postcode":"s4n 5x4",
    "addr:street":"Hodsman Rd",
    "iso:country":"CA",
    "sg:address":"220 Hodsman Rd",
    "sg:city":"Regina",
    "sg:classifiers":[
        {
            "category":"Manufacturing",
            "subcategory":"Tools & Machinery",
            "type":"Manufacturing & Wholesale Goods"
        }
    ],
    "sg:phone":"+1 306 721 2104",
    "sg:postcode":"S4N 5X4",
    "sg:province":"SK",
    "sg:tags":[
        "washing",
        "car",
        "well",
        "water",
        "drilling",
        "polishing"
    ],
    "wof:name":"Clark's Supply & Svc Ltd",
    "wof:placetype":"venue"
},
  "geometry": {"coordinates":[-104.583473,50.478413],"type":"Point"}
}