{
  "type": "Feature",
  "properties": {
    "addr:full":"346 Rue Seguin Saint-Colomban QC J5K 1W1",
    "addr:housenumber":"346",
    "addr:postcode":"j5k 1w1",
    "addr:street":"Rue Seguin",
    "iso:country":"CA",
    "sg:address":"346 Rue Seguin",
    "sg:city":"Saint-Colomban",
    "sg:classifiers":[
        {
            "category":"Professional",
            "type":"Services"
        }
    ],
    "sg:phone":"+1 450 436 2126",
    "sg:postcode":"J5K 1W1",
    "sg:province":"QC",
    "sg:tags":[
        "consultant"
    ],
    "wof:name":"Jolicoeur, Marcel",
    "wof:placetype":"venue"
},
  "geometry": {"coordinates":[-74.10002900000001,45.755814],"type":"Point"}
}