{
  "type": "Feature",
  "properties": {
    "addr:full":"23 Union St Smiths Falls ON K7A 2S3",
    "addr:housenumber":"23",
    "addr:postcode":"k7a 2s3",
    "addr:street":"Union St",
    "iso:country":"CA",
    "sg:address":"23 Union St",
    "sg:city":"Smiths Falls",
    "sg:classifiers":[
        {
            "category":"Restaurant",
            "type":"Food & Drink"
        }
    ],
    "sg:phone":"+1 613 283 8635",
    "sg:postcode":"K7A 2S3",
    "sg:province":"ON",
    "wof:name":"Country Diner Restaurant",
    "wof:placetype":"venue"
},
  "geometry": {"coordinates":[-76.02114105219999,44.9109344482],"type":"Point"}
}