{
  "type": "Feature",
  "properties": {
    "addr:full":"Orangeville ON L9W 2Z1",
    "addr:postcode":"l9w 2z1",
    "iso:country":"CA",
    "sg:city":"Orangeville",
    "sg:classifiers":[
        {
            "category":"Manufacturing",
            "subcategory":"Metals",
            "type":"Manufacturing & Wholesale Goods"
        }
    ],
    "sg:phone":"+1 519 941 7026",
    "sg:postcode":"L9W 2Z1",
    "sg:province":"ON",
    "sg:tags":[
        "foundry"
    ],
    "wof:name":"Tiffany Metal Casting Ltd",
    "wof:placetype":"venue"
},
  "geometry": {"coordinates":[-80.09349060060001,43.9201164246],"type":"Point"}
}