{
  "type": "Feature",
  "properties": {
    "addr:full":"1453 Rue Amherst Montreal QC H2L 3L2",
    "addr:housenumber":"1453",
    "addr:postcode":"h2l 3l2",
    "addr:street":"Rue Amherst",
    "iso:country":"CA",
    "sg:address":"1453 Rue Amherst",
    "sg:city":"Montreal",
    "sg:classifiers":[
        {
            "category":"Communications",
            "subcategory":"Film & Video Production",
            "type":"Services"
        }
    ],
    "sg:phone":"+1 514 521 4460",
    "sg:postcode":"H2L 3L2",
    "sg:province":"QC",
    "sg:tags":[
        "producer",
        "taping"
    ],
    "wof:name":"Sous-Titrage Plus Inc",
    "wof:placetype":"venue"
},
  "geometry": {"coordinates":[-73.5577087402,45.5179367065],"type":"Point"}
}