{
  "type": "Feature",
  "properties": {
    "addr:full":"29 Rue Leguerrier Blainville QC J7E 4H5",
    "addr:housenumber":"29",
    "addr:postcode":"j7e 4h5",
    "addr:street":"Rue Leguerrier",
    "iso:country":"CA",
    "sg:address":"29 Rue Leguerrier",
    "sg:city":"Blainville",
    "sg:classifiers":[
        {
            "category":"Building & Trades",
            "subcategory":"Cleaning & Sanitation",
            "type":"Services"
        }
    ],
    "sg:phone":"+1 450 430 1789",
    "sg:postcode":"J7E 4H5",
    "sg:province":"QC",
    "sg:tags":[
        "snow",
        "removal"
    ],
    "wof:name":"Deneigements F Bigras Inc",
    "wof:placetype":"venue"
},
  "geometry": {"coordinates":[-73.8406829834,45.6737747192],"type":"Point"}
}