{
  "type": "Feature",
  "properties": {
    "addr:full":"Southend SK S0J 2L0",
    "addr:postcode":"s0j 2l0",
    "addr:street":"Southend",
    "iso:country":"CA",
    "sg:city":"Southend",
    "sg:classifiers":[
        {
            "category":"Taxi",
            "type":"Transportation"
        }
    ],
    "sg:phone":"+1 306 758 2042",
    "sg:postcode":"S0J 2L0",
    "sg:province":"SK",
    "sg:tags":[
        "taxicab"
    ],
    "wof:name":"Clarke's Taxi",
    "wof:placetype":"venue"
},
  "geometry": {"coordinates":[-103.242004395,56.3293762207],"type":"Point"}
}