{
  "type": "Feature",
  "properties": {
    "addr:full":"2901 Bayview Ave #140 North York ON M2K 1E6",
    "addr:housenumber":"2901",
    "addr:postcode":"m2k 1e6",
    "addr:street":"Bayview Ave # 140",
    "iso:country":"CA",
    "sg:address":"2901 Bayview Ave #140",
    "sg:city":"North York",
    "sg:classifiers":[
        {
            "category":"Personal",
            "subcategory":"Beauty Salon",
            "type":"Services"
        }
    ],
    "sg:phone":"+1 416 223 1177",
    "sg:postcode":"M2K 1E6",
    "sg:province":"ON",
    "wof:name":"Petros Hair Design",
    "wof:placetype":"venue"
},
  "geometry": {"coordinates":[-79.3885421753,43.769115448],"type":"Point"}
}