{
  "type": "Feature",
  "properties": {
    "addr:full":"27 Balsam Ave #4 Bragg Creek AB T0L 0K0",
    "addr:housenumber":"27",
    "addr:postcode":"t0l 0k0",
    "addr:street":"Balsam Ave # 4",
    "iso:country":"CA",
    "sg:address":"27 Balsam Ave #4",
    "sg:city":"Bragg Creek",
    "sg:classifiers":[
        {
            "category":"Health Services",
            "subcategory":"Health Practitioner",
            "type":"Services"
        }
    ],
    "sg:phone":"+1 403 949 4008",
    "sg:postcode":"T0L 0K0",
    "sg:province":"AB",
    "sg:tags":[
        "therapist",
        "physical"
    ],
    "wof:name":"Bragg Creek Physiotherapy",
    "wof:placetype":"venue"
},
  "geometry": {"coordinates":[-114.56156900000001,50.952351],"type":"Point"}
}