{
  "type": "Feature",
  "properties": {
    "addr:full":"158 11th Ave E Vancouver BC V5T 2C2",
    "addr:housenumber":"158",
    "addr:postcode":"v5t 2c2",
    "addr:street":"11Th Ave E",
    "iso:country":"CA",
    "sg:address":"158 11th Ave E",
    "sg:city":"Vancouver",
    "sg:classifiers":[
        {
            "category":"Health Services",
            "subcategory":"Clinic",
            "type":"Services"
        }
    ],
    "sg:phone":"+1 604 873 4150",
    "sg:postcode":"V5T 2C2",
    "sg:province":"BC",
    "sg:tags":[
        "therapist",
        "massage"
    ],
    "wof:name":"Massage Therapy Ctr",
    "wof:placetype":"venue"
},
  "geometry": {"coordinates":[-123.101799,49.261047],"type":"Point"}
}