{
  "type": "Feature",
  "properties": {
    "addr:full":"311 3rd Ave E Hanna AB T0J 1P0",
    "addr:housenumber":"311",
    "addr:postcode":"t0j 1p0",
    "addr:street":"3Rd Ave E",
    "iso:country":"CA",
    "sg:address":"311 3rd Ave E",
    "sg:city":"Hanna",
    "sg:classifiers":[
        {
            "category":"Organizations",
            "subcategory":"Professional Association",
            "type":"Services"
        }
    ],
    "sg:phone":"+1 403 854 3737",
    "sg:postcode":"T0J 1P0",
    "sg:province":"AB",
    "wof:name":"Ducks Unlimited",
    "wof:placetype":"venue"
},
  "geometry": {"coordinates":[-111.920578003,51.6453361511],"type":"Point"}
}