{
  "type": "Feature",
  "properties": {
    "addr:full":"St Albert AB T8N 5A6",
    "addr:postcode":"t8n 5a6",
    "iso:country":"CA",
    "sg:city":"St Albert",
    "sg:classifiers":[
        {
            "category":"Restaurant",
            "type":"Food & Drink"
        }
    ],
    "sg:phone":"+1 780 419 3300",
    "sg:postcode":"T8N 5A6",
    "sg:province":"AB",
    "sg:tags":[
        "caterer"
    ],
    "wof:name":"Ashgrove Catering Inc",
    "wof:placetype":"venue"
},
  "geometry": {"coordinates":[-113.572982788,53.6374397278],"type":"Point"}
}