{
  "type": "Feature",
  "properties": {
    "addr:full":"308 Wellington St St Thomas ON N5R 2S9",
    "addr:housenumber":"308",
    "addr:postcode":"n5r 2s9",
    "addr:street":"Wellington St",
    "iso:country":"CA",
    "sg:address":"308 Wellington St",
    "sg:city":"St Thomas",
    "sg:classifiers":[
        {
            "category":"Restaurant",
            "type":"Food & Drink"
        }
    ],
    "sg:phone":"+1 519 633 9830",
    "sg:postcode":"N5R 2S9",
    "sg:province":"ON",
    "sg:tags":[
        "pizza"
    ],
    "wof:name":"Little Caesars Pizza",
    "wof:placetype":"venue"
},
  "geometry": {"coordinates":[-81.176033,42.774834],"type":"Point"}
}