{
  "type": "Feature",
  "properties": {
    "addr:full":"Montreal QC H4A 1T6",
    "addr:postcode":"h4a 1t6",
    "iso:country":"CA",
    "sg:city":"Montreal",
    "sg:classifiers":[
        {
            "category":"Manufacturing",
            "subcategory":"Printing",
            "type":"Manufacturing & Wholesale Goods"
        }
    ],
    "sg:phone":"+1 514 481 5892",
    "sg:postcode":"H4A 1T6",
    "sg:province":"QC",
    "sg:tags":[
        "publisher"
    ],
    "wof:name":"Kylix Media Inc",
    "wof:placetype":"venue"
},
  "geometry": {"coordinates":[-73.553055,45.567905],"type":"Point"}
}