{
  "type": "Feature",
  "properties": {
    "addr:full":"Victoria BC V8W 2Z6",
    "addr:postcode":"v8w 2z6",
    "iso:country":"CA",
    "sg:city":"Victoria",
    "sg:classifiers":[
        {
            "category":"Professional",
            "subcategory":"Employment Agencies",
            "type":"Services"
        }
    ],
    "sg:phone":"+1 250 388 7350",
    "sg:postcode":"V8W 2Z6",
    "sg:province":"BC",
    "sg:tags":[
        "opportunity",
        "association"
    ],
    "wof:name":"Societe Francophone-Victoria",
    "wof:placetype":"venue"
},
  "geometry": {"coordinates":[-123.36953699999999,48.426662],"type":"Point"}
}