{
  "type": "Feature",
  "properties": {
    "addr:full":"868 N Frontage Rd Mcbride BC V0J 2E0",
    "addr:housenumber":"868",
    "addr:postcode":"v0j 2e0",
    "addr:street":"N Frontage Rd",
    "iso:country":"CA",
    "sg:address":"868 N Frontage Rd",
    "sg:city":"Mcbride",
    "sg:classifiers":[
        {
            "category":"Travel",
            "subcategory":"Hotels & Motels",
            "type":"Entertainment"
        }
    ],
    "sg:phone":"+1 250 569 0001",
    "sg:postcode":"V0J 2E0",
    "sg:province":"BC",
    "wof:name":"North Country Lodge",
    "wof:placetype":"venue"
},
  "geometry": {"coordinates":[-120.156952,53.30246],"type":"Point"}
}