{
  "type": "Feature",
  "properties": {
    "iso:country":"CA",
    "sg:address":"234 Rue Dufferin # 6",
    "sg:city":"Sherbrooke",
    "sg:classifiers":[
        {
            "category":"Health Services",
            "subcategory":"Health Practitioner",
            "type":"Services"
        }
    ],
    "sg:phone":"+1 819 620 6206",
    "sg:postcode":"J1H 4M2",
    "sg:province":"QC",
    "sg:tags":[
        "psychotherapist"
    ],
    "wof:name":"Gosselin, Claudette",
    "wof:placetype":"venue"
},
  "geometry": {"coordinates":[-71.89408874510001,45.4051589966],"type":"Point"}
}