{
  "type": "Feature",
  "properties": {
    "addr:full":"Laval QC H7A 1Z6",
    "addr:postcode":"h7a 1z6",
    "iso:country":"CA",
    "sg:city":"Laval",
    "sg:classifiers":[
        {
            "category":"Professional",
            "subcategory":"Business Services",
            "type":"Services"
        }
    ],
    "sg:phone":"+1 450 665 0380",
    "sg:postcode":"H7A 1Z6",
    "sg:province":"QC",
    "sg:tags":[
        "notary"
    ],
    "wof:name":"Farley, Robert",
    "wof:placetype":"venue"
},
  "geometry": {"coordinates":[-73.57540130620001,45.6695823669],"type":"Point"}
}