{
  "type": "Feature",
  "properties": {
    "addr:full":"Ponoka AB T4J 1J8",
    "addr:postcode":"t4j 1j8",
    "iso:country":"CA",
    "sg:city":"Ponoka",
    "sg:classifiers":[
        {
            "category":"Retail",
            "subcategory":"Car Wash",
            "type":"Services"
        }
    ],
    "sg:phone":"+1 403 783 8388",
    "sg:postcode":"T4J 1J8",
    "sg:province":"AB",
    "sg:tags":[
        "automobile",
        "detail",
        "clean"
    ],
    "wof:name":"First Stop Auto Care",
    "wof:placetype":"venue"
},
  "geometry": {"coordinates":[-113.600838,52.672112],"type":"Point"}
}