{
  "type": "Feature",
  "properties": {
    "addr:full":"PO Box 72 Newton ON N0K 1R0",
    "addr:housenumber":"po box 72",
    "addr:postcode":"n0k 1r0",
    "iso:country":"CA",
    "sg:address":"PO Box 72",
    "sg:city":"Newton",
    "sg:classifiers":[
        {
            "category":"Manufacturing",
            "subcategory":"Metals",
            "type":"Manufacturing & Wholesale Goods"
        }
    ],
    "sg:phone":"+1 519 595 4563",
    "sg:postcode":"N0K 1R0",
    "sg:province":"ON",
    "sg:tags":[
        "steel"
    ],
    "wof:name":"Schmidt Brothers Steels Fbrctr",
    "wof:placetype":"venue"
},
  "geometry": {"coordinates":[-80.878693,43.590065],"type":"Point"}
}