{
  "type": "Feature",
  "properties": {
    "addr:full":"Edmonton AB T5J 3E8",
    "addr:postcode":"t5j 3e8",
    "iso:country":"CA",
    "sg:city":"Edmonton",
    "sg:classifiers":[
        {
            "category":"Insurance",
            "subcategory":"Insurance Agent",
            "type":"Services"
        }
    ],
    "sg:phone":"+1 780 428 7510",
    "sg:postcode":"T5J 3E8",
    "sg:province":"AB",
    "wof:name":"Axa Pacific Insurance CO",
    "wof:placetype":"venue"
},
  "geometry": {"coordinates":[-113.49339294400001,53.5448913574],"type":"Point"}
}