{
  "type": "Feature",
  "properties": {
    "addr:full":"242 Rue Notre-Dame Tring-Jonction QC G0N 1X0",
    "addr:housenumber":"242",
    "addr:postcode":"g0n 1x0",
    "addr:street":"Rue Notre-Dame",
    "iso:country":"CA",
    "sg:address":"242 Rue Notre-Dame",
    "sg:city":"Tring-Jonction",
    "sg:classifiers":[
        {
            "category":"Personal",
            "subcategory":"Beauty Salon",
            "type":"Services"
        }
    ],
    "sg:phone":"+1 418 426 5225",
    "sg:postcode":"G0N 1X0",
    "sg:province":"QC",
    "wof:name":"Emmanuel Coiffure",
    "wof:placetype":"venue"
},
  "geometry": {"coordinates":[-70.995255,46.273708],"type":"Point"}
}