{
  "type": "Feature",
  "properties": {
    "iso:country":"CA",
    "sg:city":"Calgary",
    "sg:classifiers":[
        {
            "category":"Food & Beverages",
            "subcategory":"Liquor & Beverages",
            "type":"Retail Goods"
        }
    ],
    "sg:phone":"+1 403 242 6907",
    "sg:postcode":"T3E 7C4",
    "sg:province":"AB",
    "sg:tags":[
        "store"
    ],
    "wof:name":"City Liquor",
    "wof:placetype":"venue"
},
  "geometry": {"coordinates":[-114.162216187,51.0176429749],"type":"Point"}
}