{
  "type": "Feature",
  "properties": {
    "addr:full":"115 Keewatin Ave Longlac ON P0T 2A0",
    "addr:housenumber":"115",
    "addr:postcode":"p0t 2a0",
    "addr:street":"Keewatin Ave",
    "iso:country":"CA",
    "sg:address":"115 Keewatin Ave",
    "sg:city":"Longlac",
    "sg:classifiers":[
        {
            "category":"Retail",
            "subcategory":"Auto Repair",
            "type":"Services"
        }
    ],
    "sg:phone":"+1 807 876 2644",
    "sg:postcode":"P0T 2A0",
    "sg:province":"ON",
    "sg:tags":[
        "truck"
    ],
    "wof:name":"Mercier Truck Ctr",
    "wof:placetype":"venue"
},
  "geometry": {"coordinates":[-86.53379099999999,49.779999],"type":"Point"}
}