{
  "type": "Feature",
  "properties": {
    "addr:full":"439 Rue Saint-Etienne LA Malbaie QC G5A 1H4",
    "addr:housenumber":"439",
    "addr:postcode":"g5a 1h4",
    "addr:street":"Rue Saint-Etienne",
    "iso:country":"CA",
    "sg:address":"439 Rue Saint-Etienne",
    "sg:city":"LA Malbaie",
    "sg:classifiers":[
        {
            "category":"Restaurant",
            "type":"Food & Drink"
        }
    ],
    "sg:phone":"+1 418 665 1070",
    "sg:postcode":"G5A 1H4",
    "sg:province":"QC",
    "wof:name":"Restaurant L'Orchidee Inc",
    "wof:placetype":"venue"
},
  "geometry": {"coordinates":[-70.150696,47.650623],"type":"Point"}
}