{
  "type": "Feature",
  "properties": {
    "iso:country":"CA",
    "sg:city":"Boucherville",
    "sg:classifiers":[
        {
            "category":"Shopping",
            "subcategory":"Computers & Home Electronics",
            "type":"Retail Goods"
        }
    ],
    "sg:phone":"+1 450 449 1940",
    "sg:postcode":"J4B 7L3",
    "sg:province":"QC",
    "sg:tags":[
        "software"
    ],
    "wof:name":"Contalitec Informatique Inc",
    "wof:placetype":"venue"
},
  "geometry": {"coordinates":[-73.446823,45.571865],"type":"Point"}
}