{
  "type": "Feature",
  "properties": {
    "addr:full":"Saint-Jean-DE-Matha QC J0K 2S0",
    "addr:postcode":"j0k 2s0",
    "iso:country":"CA",
    "sg:city":"Saint-Jean-DE-Matha",
    "sg:classifiers":[
        {
            "category":"Manufacturing",
            "subcategory":"Rubber & Plastics",
            "type":"Manufacturing & Wholesale Goods"
        }
    ],
    "sg:phone":"+1 450 886 3757",
    "sg:postcode":"J0K 2S0",
    "sg:province":"QC",
    "sg:tags":[
        "excavating",
        "container",
        "contractor"
    ],
    "wof:name":"Genereux Construction Inc",
    "wof:placetype":"venue"
},
  "geometry": {"coordinates":[-73.5150756836,46.2158126831],"type":"Point"}
}