{
  "type": "Feature",
  "properties": {
    "iso:country":"CA",
    "sg:address":"5009 12th Ave",
    "sg:city":"Okanagan Falls",
    "sg:classifiers":[
        {
            "category":"Organizations",
            "subcategory":"Community Association",
            "type":"Services"
        }
    ],
    "sg:phone":"+1 250 497 8338",
    "sg:postcode":"V0H 1R0",
    "sg:province":"BC",
    "sg:tags":[
        "fraternal"
    ],
    "wof:name":"Royal Canadian Legion",
    "wof:placetype":"venue"
},
  "geometry": {"coordinates":[-119.57300567599999,49.3418998718],"type":"Point"}
}