{
  "type": "Feature",
  "properties": {
    "addr:full":"212 Somerset St E Ottawa ON K1N 6V4",
    "addr:housenumber":"212",
    "addr:postcode":"k1n 6v4",
    "addr:street":"Somerset St E",
    "iso:country":"CA",
    "sg:address":"212 Somerset St E",
    "sg:city":"Ottawa",
    "sg:classifiers":[
        {
            "category":"Organizations",
            "subcategory":"Religious Organization",
            "type":"Services"
        }
    ],
    "sg:phone":"+1 613 565 6544",
    "sg:postcode":"K1N 6V4",
    "sg:province":"ON",
    "sg:tags":[
        "church"
    ],
    "wof:name":"Hare Krishna Temple",
    "wof:placetype":"venue"
},
  "geometry": {"coordinates":[-75.679039,45.422413],"type":"Point"}
}