{
  "type": "Feature",
  "properties": {
    "iso:country":"CA",
    "sg:city":"Vernon",
    "sg:classifiers":[
        {
            "category":"Retail",
            "subcategory":"Laundry & Dry Cleaning",
            "type":"Services"
        }
    ],
    "sg:phone":"+1 250 549 2883",
    "sg:postcode":"V1T 9H2",
    "sg:province":"BC",
    "sg:tags":[
        "cleaners"
    ],
    "wof:name":"Henderson's Cleaners",
    "wof:placetype":"venue"
},
  "geometry": {"coordinates":[-119.27421569800001,50.2766571045],"type":"Point"}
}