{
  "type": "Feature",
  "properties": {
    "addr:full":"Conception Bay South NL A1W 4W4",
    "addr:postcode":"a1w 4w4",
    "iso:country":"CA",
    "sg:city":"Conception Bay South",
    "sg:classifiers":[
        {
            "category":"Autos & Motor Vehicles",
            "subcategory":"Boat Sales",
            "type":"Retail Goods"
        }
    ],
    "sg:phone":"+1 709 834 4348",
    "sg:postcode":"A1W 4W4",
    "sg:province":"NL",
    "sg:tags":[
        "machine",
        "equipment",
        "marine",
        "shop",
        "supply"
    ],
    "wof:name":"Rebuildall Cylinder Head Svc",
    "wof:placetype":"venue"
},
  "geometry": {"coordinates":[-52.9651412964,47.5130233765],"type":"Point"}
}