{
  "type": "Feature",
  "properties": {
    "addr:full":"8718 112 St Fort Saskatchewan AB T8L 2S8",
    "addr:housenumber":"8718",
    "addr:postcode":"t8l 2s8",
    "addr:street":"112 St",
    "iso:country":"CA",
    "sg:address":"8718 112 St",
    "sg:city":"Fort Saskatchewan",
    "sg:classifiers":[
        {
            "category":"Building & Trades",
            "subcategory":"Plumbing",
            "type":"Services"
        }
    ],
    "sg:phone":"+1 780 998 3847",
    "sg:postcode":"T8L 2S8",
    "sg:province":"AB",
    "sg:tags":[
        "contractor"
    ],
    "wof:name":"Robertson's Plumbing & Gsfttng",
    "wof:placetype":"venue"
},
  "geometry": {"coordinates":[-113.19198608400001,53.7066688538],"type":"Point"}
}