{
  "type": "Feature",
  "properties": {
    "addr:full":"430 Boul Decarie Saint-Laurent QC H4L 3K9",
    "addr:housenumber":"430",
    "addr:postcode":"h4l 3k9",
    "addr:street":"Boul Decarie",
    "iso:country":"CA",
    "sg:address":"430 Boul Decarie",
    "sg:city":"Saint-Laurent",
    "sg:classifiers":[
        {
            "category":"Wholesale",
            "subcategory":"Office Equipment",
            "type":"Manufacturing & Wholesale Goods"
        }
    ],
    "sg:phone":"+1 514 744 4346",
    "sg:postcode":"H4L 3K9",
    "sg:province":"QC",
    "sg:tags":[
        "accounting",
        "bookkeeping",
        "system"
    ],
    "wof:name":"Chacra & CO Enr",
    "wof:placetype":"venue"
},
  "geometry": {"coordinates":[-73.6732406616,45.5080833435],"type":"Point"}
}