{
  "type": "Feature",
  "properties": {
    "iso:country":"CA",
    "sg:address":"8465 Boul Viau",
    "sg:city":"Saint-Leonard",
    "sg:classifiers":[
        {
            "category":"Health Services",
            "subcategory":"Doctor",
            "type":"Services"
        }
    ],
    "sg:phone":"+1 514 326 9850",
    "sg:postcode":"H1R 2T6",
    "sg:province":"QC",
    "sg:tags":[
        "x",
        "clinic"
    ],
    "wof:name":"Radiologie Viau",
    "wof:placetype":"venue"
},
  "geometry": {"coordinates":[-73.602699,45.581558],"type":"Point"}
}