{
  "type": "Feature",
  "properties": {
    "addr:full":"391 Main St Shawville QC J0X 2Y0",
    "addr:housenumber":"391",
    "addr:postcode":"j0x 2y0",
    "addr:street":"Main St",
    "iso:country":"CA",
    "sg:address":"391 Main St",
    "sg:city":"Shawville",
    "sg:classifiers":[
        {
            "category":"Insurance",
            "subcategory":"Insurance Agent",
            "type":"Services"
        }
    ],
    "sg:phone":"+1 819 647 3737",
    "sg:postcode":"J0X 2Y0",
    "sg:province":"QC",
    "wof:name":"F H Rowat Insurance",
    "wof:placetype":"venue"
},
  "geometry": {"coordinates":[-76.49295806879999,45.6044044495],"type":"Point"}
}