{
  "type": "Feature",
  "properties": {
    "addr:full":"2648 Harris Rd Dorchester ON N0L 1G5",
    "addr:housenumber":"2648",
    "addr:postcode":"n0l 1g5",
    "addr:street":"Harris Rd",
    "iso:country":"CA",
    "sg:address":"2648 Harris Rd",
    "sg:city":"Dorchester",
    "sg:classifiers":[
        {
            "category":"Wholesale",
            "subcategory":"Farm Supplies",
            "type":"Manufacturing & Wholesale Goods"
        }
    ],
    "sg:phone":"+1 519 268 3096",
    "sg:postcode":"N0L 1G5",
    "sg:province":"ON",
    "sg:tags":[
        "livestock"
    ],
    "wof:name":"Weavercroft International",
    "wof:placetype":"venue"
},
  "geometry": {"coordinates":[-81.07712554930001,42.9731521606],"type":"Point"}
}