{
  "type": "Feature",
  "properties": {
    "addr:full":"Baie-Comeau QC G4Z 2L5",
    "addr:postcode":"g4z 2l5",
    "iso:country":"CA",
    "sg:city":"Baie-Comeau",
    "sg:classifiers":[
        {
            "category":"Banks & Credit Unions",
            "subcategory":"Bank",
            "type":"Services"
        }
    ],
    "sg:phone":"+1 418 296 3368",
    "sg:postcode":"G4Z 2L5",
    "sg:province":"QC",
    "wof:name":"Banque Royale",
    "wof:placetype":"venue"
},
  "geometry": {"coordinates":[-68.1524734497,49.2210388184],"type":"Point"}
}