{
  "type": "Feature",
  "properties": {
    "addr:full":"106 Commercial St Dominion NS B1G 1B4",
    "addr:housenumber":"106",
    "addr:postcode":"b1g 1b4",
    "addr:street":"Commercial St",
    "iso:country":"CA",
    "sg:address":"106 Commercial St",
    "sg:city":"Dominion",
    "sg:classifiers":[
        {
            "category":"Building & Trades",
            "subcategory":"Plumbing",
            "type":"Services"
        }
    ],
    "sg:phone":"+1 902 849 5737",
    "sg:postcode":"B1G 1B4",
    "sg:province":"NS",
    "sg:tags":[
        "furnace",
        "heating",
        "contractor"
    ],
    "wof:name":"Hickey & Lynk Oil Burner Svc",
    "wof:placetype":"venue"
},
  "geometry": {"coordinates":[-60.02351,46.210789],"type":"Point"}
}