{
  "type": "Feature",
  "properties": {
    "addr:full":"522 Av Meloche Dorval QC H9P 2T2",
    "addr:postcode":"h9p 2t2",
    "addr:street":"522 Av Meloche",
    "iso:country":"CA",
    "sg:address":"522 Av Meloche",
    "sg:city":"Dorval",
    "sg:classifiers":[
        {
            "category":"Wholesale",
            "subcategory":"Medical Equipment & Supplies",
            "type":"Manufacturing & Wholesale Goods"
        }
    ],
    "sg:phone":"+1 514 636 6898",
    "sg:postcode":"H9P 2T2",
    "sg:province":"QC",
    "sg:tags":[
        "hospital"
    ],
    "wof:name":"Qualisys Canada Inc",
    "wof:placetype":"venue"
},
  "geometry": {"coordinates":[-73.726471,45.451134],"type":"Point"}
}