{
  "type": "Feature",
  "properties": {
    "addr:full":"4434 Boul Decarie Montreal QC H4A 3P2",
    "addr:housenumber":"4434",
    "addr:postcode":"h4a 3p2",
    "addr:street":"Boul Decarie",
    "iso:country":"CA",
    "sg:address":"4434 Boul Decarie",
    "sg:city":"Montreal",
    "sg:classifiers":[
        {
            "category":"Social Services",
            "type":"Services"
        }
    ],
    "sg:phone":"+1 514 485 5678",
    "sg:postcode":"H4A 3P2",
    "sg:province":"QC",
    "sg:tags":[
        "organization",
        "welfare"
    ],
    "wof:name":"Centre Jeunesse DE Montreal",
    "wof:placetype":"venue"
},
  "geometry": {"coordinates":[-73.6228561401,45.4805908203],"type":"Point"}
}