{
  "type": "Feature",
  "properties": {
    "addr:full":"1441 Kebet Way Port Coquitlam BC V3C 6L3",
    "addr:housenumber":"1441",
    "addr:postcode":"v3c 6l3",
    "addr:street":"Kebet Way",
    "iso:country":"CA",
    "sg:address":"1441 Kebet Way",
    "sg:city":"Port Coquitlam",
    "sg:classifiers":[
        {
            "category":"Wholesale",
            "subcategory":"Durable Goods & Equipment",
            "type":"Manufacturing & Wholesale Goods"
        }
    ],
    "sg:phone":"+1 604 945 1010",
    "sg:postcode":"V3C 6L3",
    "sg:province":"BC",
    "sg:tags":[
        "representative",
        "manufacturer"
    ],
    "wof:name":"Barclay Sales Ltd",
    "wof:placetype":"venue"
},
  "geometry": {"coordinates":[-122.751365662,49.2426071167],"type":"Point"}
}