{
  "type": "Feature",
  "properties": {
    "iso:country":"CA",
    "sg:address":"8821 Weston Rd",
    "sg:city":"Woodbridge",
    "sg:classifiers":[
        {
            "category":"Manufacturing",
            "subcategory":"Building Materials",
            "type":"Manufacturing & Wholesale Goods"
        }
    ],
    "sg:phone":"+1 416 747 0988",
    "sg:postcode":"L4L 1A6",
    "sg:province":"ON",
    "wof:name":"Best Way Stone Ltd",
    "wof:placetype":"venue"
},
  "geometry": {"coordinates":[-79.5537490845,43.8165168762],"type":"Point"}
}