{
  "type": "Feature",
  "properties": {
    "iso:country":"CA",
    "sg:address":"904 Alsgard St",
    "sg:city":"Kelowna",
    "sg:classifiers":[
        {
            "category":"Manufacturing",
            "subcategory":"Metals",
            "type":"Manufacturing & Wholesale Goods"
        }
    ],
    "sg:phone":"+1 250 765 1468",
    "sg:postcode":"V1X 7J2",
    "sg:province":"BC",
    "sg:tags":[
        "fence"
    ],
    "wof:name":"Lynx Brand Fence Prod Ltd",
    "wof:placetype":"venue"
},
  "geometry": {"coordinates":[-119.40701294,49.8993873596],"type":"Point"}
}