{
  "type": "Feature",
  "properties": {
    "iso:country":"CA",
    "sg:address":"6 Rue Martin",
    "sg:city":"Saint-Charles-DE-Bellechasse",
    "sg:classifiers":[
        {
            "category":"Building & Trades",
            "subcategory":"Construction",
            "type":"Services"
        }
    ],
    "sg:phone":"+1 418 887 3171",
    "sg:postcode":"G0R 2T0",
    "sg:province":"QC",
    "sg:tags":[
        "excavating",
        "contractor"
    ],
    "wof:name":"Excavation St-Charles Inc",
    "wof:placetype":"venue"
},
  "geometry": {"coordinates":[-70.94701385499999,46.7697525024],"type":"Point"}
}