{
  "type": "Feature",
  "properties": {
    "addr:full":"2750 Victoria Park Ave North York ON M2J 4A8",
    "addr:housenumber":"2750",
    "addr:postcode":"m2j 4a8",
    "addr:street":"Victoria Park Ave",
    "iso:country":"CA",
    "sg:address":"2750 Victoria Park Ave",
    "sg:city":"North York",
    "sg:classifiers":[
        {
            "category":"Retail",
            "subcategory":"Auto Repair",
            "type":"Services"
        }
    ],
    "sg:phone":"+1 416 494 0178",
    "sg:postcode":"M2J 4A8",
    "sg:province":"ON",
    "sg:tags":[
        "repairing",
        "automobile",
        "painting"
    ],
    "wof:name":"Pleasant View Auto Ctr",
    "wof:placetype":"venue"
},
  "geometry": {"coordinates":[-79.3283691406,43.7862548828],"type":"Point"}
}