{
  "type": "Feature",
  "properties": {
    "iso:country":"CA",
    "sg:address":"692 Forest Lake Rd",
    "sg:city":"Sundridge",
    "sg:classifiers":[
        {
            "category":"Mining & Drilling",
            "type":"Manufacturing & Wholesale Goods"
        }
    ],
    "sg:phone":"+1 705 384 7037",
    "sg:postcode":"P0A 1Z0",
    "sg:province":"ON",
    "sg:tags":[
        "stone"
    ],
    "wof:name":"Alex Preston Sand & Gravel",
    "wof:placetype":"venue"
},
  "geometry": {"coordinates":[-79.39953613279999,45.7665786743],"type":"Point"}
}