{
  "type": "Feature",
  "properties": {
    "addr:full":"Valemount BC V0E 2Z0",
    "addr:postcode":"v0e 2z0",
    "iso:country":"CA",
    "sg:city":"Valemount",
    "sg:classifiers":[
        {
            "category":"Travel",
            "subcategory":"Hotels & Motels",
            "type":"Entertainment"
        }
    ],
    "sg:phone":"+1 250 566 9160",
    "sg:postcode":"V0E 2Z0",
    "sg:province":"BC",
    "sg:tags":[
        "resort"
    ],
    "wof:name":"Twin Peaks Resort Inc",
    "wof:placetype":"venue"
},
  "geometry": {"coordinates":[-119.279106,52.831242],"type":"Point"}
}