{
  "type": "Feature",
  "properties": {
    "iso:country":"CA",
    "sg:address":"18 Gibbons St",
    "sg:city":"Oshawa",
    "sg:classifiers":[
        {
            "category":"Health Services",
            "subcategory":"Chiropractor",
            "type":"Services"
        }
    ],
    "sg:phone":"+1 905 723 3543",
    "sg:postcode":"L1J 4X7",
    "sg:province":"ON",
    "wof:name":"Chiropractic Centre",
    "wof:placetype":"venue"
},
  "geometry": {"coordinates":[-78.878906,43.894733],"type":"Point"}
}