{
  "type": "Feature",
  "properties": {
    "iso:country":"CA",
    "sg:city":"Laval",
    "sg:classifiers":[
        {
            "category":"Personal",
            "subcategory":"Barber",
            "type":"Services"
        }
    ],
    "sg:phone":"+1 450 625 4492",
    "sg:postcode":"H7P 1V7",
    "sg:province":"QC",
    "wof:name":"Coiffure Masculine R Cloutier",
    "wof:placetype":"venue"
},
  "geometry": {"coordinates":[-73.8112335205,45.576171875],"type":"Point"}
}