{
  "type": "Feature",
  "properties": {
    "addr:full":"6630 Rue Bombardier Saint-Leonard QC H1P 1E4",
    "addr:housenumber":"6630",
    "addr:postcode":"h1p 1e4",
    "addr:street":"Rue Bombardier",
    "iso:country":"CA",
    "sg:address":"6630 Rue Bombardier",
    "sg:city":"Saint-Leonard",
    "sg:classifiers":[
        {
            "category":"Retail",
            "subcategory":"Auto Repair",
            "type":"Services"
        }
    ],
    "sg:phone":"+1 514 325 0928",
    "sg:postcode":"H1P 1E4",
    "sg:province":"QC",
    "sg:tags":[
        "body",
        "automobile",
        "painting"
    ],
    "wof:name":"Carrosserie Ml Enr",
    "wof:placetype":"venue"
},
  "geometry": {"coordinates":[-73.5917816162,45.6017074585],"type":"Point"}
}