{
  "type": "Feature",
  "properties": {
    "iso:country":"CA",
    "sg:address":"2150 Rue DE LA Montagne",
    "sg:city":"Montreal",
    "sg:classifiers":[
        {
            "category":"Restaurant",
            "type":"Food & Drink"
        }
    ],
    "sg:phone":"+1 514 844 8714",
    "sg:postcode":"H3G 1Z7",
    "sg:province":"QC",
    "wof:name":"Restaurant Lo Stivale D'Oro",
    "wof:placetype":"venue"
},
  "geometry": {"coordinates":[-73.577888,45.499126],"type":"Point"}
}