{
  "type": "Feature",
  "properties": {
    "addr:full":"185 Concession St Lakefield ON K0L 2H0",
    "addr:housenumber":"185",
    "addr:postcode":"k0l 2h0",
    "addr:street":"Concession St",
    "iso:country":"CA",
    "sg:address":"185 Concession St",
    "sg:city":"Lakefield",
    "sg:classifiers":[
        {
            "category":"Professional",
            "subcategory":"Testing Lab",
            "type":"Services"
        }
    ],
    "sg:phone":"+1 705 652 2000",
    "sg:postcode":"K0L 2H0",
    "sg:province":"ON",
    "sg:tags":[
        "environmental",
        "ecological"
    ],
    "wof:name":"Sgs Lakefield Research",
    "wof:placetype":"venue"
},
  "geometry": {"coordinates":[-78.2655715942,44.4199981689],"type":"Point"}
}