{
  "type": "Feature",
  "properties": {
    "addr:full":"103 Rabbit Hill Crt NW Edmonton AB T6R 2V3",
    "addr:housenumber":"103",
    "addr:postcode":"t6r 2v3",
    "addr:street":"Rabbit Hill Crt Nw",
    "iso:country":"CA",
    "sg:address":"103 Rabbit Hill Crt NW",
    "sg:city":"Edmonton",
    "sg:classifiers":[
        {
            "category":"Health Services",
            "subcategory":"Nursing And Care Facility",
            "type":"Services"
        }
    ],
    "sg:phone":"+1 780 438 2777",
    "sg:postcode":"T6R 2V3",
    "sg:province":"AB",
    "sg:tags":[
        "home",
        "housing",
        "convalescent",
        "senior",
        "citizen"
    ],
    "wof:name":"Riverbend Retirement Residence",
    "wof:placetype":"venue"
},
  "geometry": {"coordinates":[-113.592224,53.471111],"type":"Point"}
}