{
  "type": "Feature",
  "properties": {
    "addr:full":"75 Caradoc St N Strathroy ON N7G 2M5",
    "addr:housenumber":"75",
    "addr:postcode":"n7g 2m5",
    "addr:street":"Caradoc St N",
    "iso:country":"CA",
    "sg:address":"75 Caradoc St N",
    "sg:city":"Strathroy",
    "sg:classifiers":[
        {
            "category":"Health Services",
            "subcategory":"Doctor",
            "type":"Services"
        }
    ],
    "sg:phone":"+1 519 245 0751",
    "sg:postcode":"N7G 2M5",
    "sg:province":"ON",
    "sg:tags":[
        "dentist"
    ],
    "wof:name":"Mc Lachlan, P J DDS",
    "wof:placetype":"venue"
},
  "geometry": {"coordinates":[-81.6232452393,42.9579772949],"type":"Point"}
}