{
  "type": "Feature",
  "properties": {
    "addr:full":"Sault Ste Marie ON P6A 2C5",
    "addr:postcode":"p6a 2c5",
    "iso:country":"CA",
    "sg:city":"Sault Ste Marie",
    "sg:classifiers":[
        {
            "category":"Health Services",
            "subcategory":"Doctor",
            "type":"Services"
        }
    ],
    "sg:phone":"+1 705 759 1752",
    "sg:postcode":"P6A 2C5",
    "sg:province":"ON",
    "sg:tags":[
        "physician",
        "surgeon"
    ],
    "wof:name":"Kuntz, Michael MD",
    "wof:placetype":"venue"
},
  "geometry": {"coordinates":[-84.318062,46.505554],"type":"Point"}
}