{
  "type": "Feature",
  "properties": {
    "addr:full":"635 Rue Saint-Michel Longueuil QC J4J 1N5",
    "addr:housenumber":"635",
    "addr:postcode":"j4j 1n5",
    "addr:street":"Rue Saint-Michel",
    "iso:country":"CA",
    "sg:address":"635 Rue Saint-Michel",
    "sg:city":"Longueuil",
    "sg:classifiers":[
        {
            "category":"Home & Garden",
            "subcategory":"Garden Supply",
            "type":"Retail Goods"
        }
    ],
    "sg:phone":"+1 450 442 2454",
    "sg:postcode":"J4J 1N5",
    "sg:province":"QC",
    "sg:tags":[
        "sprinkler"
    ],
    "wof:name":"Irrigation Multi-Jets Inc",
    "wof:placetype":"venue"
},
  "geometry": {"coordinates":[-73.4835510254,45.5382843018],"type":"Point"}
}