{
  "type": "Feature",
  "properties": {
    "iso:country":"CA",
    "sg:address":"543 Holland St",
    "sg:city":"Dugald",
    "sg:classifiers":[
        {
            "category":"Education",
            "subcategory":"School",
            "type":"Public Place"
        }
    ],
    "sg:phone":"+1 204 853 7929",
    "sg:postcode":"R0E 0K0",
    "sg:province":"MB",
    "wof:name":"Ecole Dugald School",
    "wof:placetype":"venue"
},
  "geometry": {"coordinates":[-96.8401184082,49.8859062195],"type":"Point"}
}