{
  "type": "Feature",
  "properties": {
    "addr:full":"2087 Mcmillan Rd Abbotsford BC V2S 4Y3",
    "addr:housenumber":"2087",
    "addr:postcode":"v2s 4y3",
    "addr:street":"Mcmillan Rd",
    "iso:country":"CA",
    "sg:address":"2087 Mcmillan Rd",
    "sg:city":"Abbotsford",
    "sg:classifiers":[
        {
            "category":"Organizations",
            "subcategory":"Religious Organization",
            "type":"Services"
        }
    ],
    "sg:phone":"+1 604 859 9937",
    "sg:postcode":"V2S 4Y3",
    "sg:province":"BC",
    "sg:tags":[
        "church"
    ],
    "wof:name":"Grace Evangelical Bible Church",
    "wof:placetype":"venue"
},
  "geometry": {"coordinates":[-122.26067352299999,49.0401496887],"type":"Point"}
}