{
  "type": "Feature",
  "properties": {
    "addr:full":"408 Rue Principale Saint-Sebastien-DE-Frontenac QC G0Y 1M0",
    "addr:housenumber":"408",
    "addr:postcode":"g0y 1m0",
    "addr:street":"Rue Principale",
    "iso:country":"CA",
    "sg:address":"408 Rue Principale",
    "sg:city":"Saint-Sebastien-DE-Frontenac",
    "sg:classifiers":[
        {
            "category":"Manufacturing",
            "subcategory":"Glass & Minerals",
            "type":"Manufacturing & Wholesale Goods"
        }
    ],
    "sg:phone":"+1 819 652 2772",
    "sg:postcode":"G0Y 1M0",
    "sg:province":"QC",
    "sg:tags":[
        "wheel",
        "grinding"
    ],
    "wof:name":"Abressa Canada Inc",
    "wof:placetype":"venue"
},
  "geometry": {"coordinates":[-70.9776687622,45.7860183716],"type":"Point"}
}