{
  "type": "Feature",
  "properties": {
    "addr:full":"46 Boul Cartier O Laval QC H7N 2H4",
    "addr:housenumber":"46",
    "addr:postcode":"h7n 2h4",
    "addr:street":"Boul Cartier O",
    "iso:country":"CA",
    "sg:address":"46 Boul Cartier O",
    "sg:city":"Laval",
    "sg:classifiers":[
        {
            "category":"Restaurant",
            "type":"Food & Drink"
        }
    ],
    "sg:phone":"+1 450 668 8625",
    "sg:postcode":"H7N 2H4",
    "sg:province":"QC",
    "wof:name":"Chez Gerard",
    "wof:placetype":"venue"
},
  "geometry": {"coordinates":[-73.688278,45.559269],"type":"Point"}
}