{
  "type": "Feature",
  "properties": {
    "iso:country":"CA",
    "sg:address":"191 Rue DE Quen",
    "sg:city":"Dolbeau-Mistassini",
    "sg:classifiers":[
        {
            "category":"Restaurant",
            "type":"Food & Drink"
        }
    ],
    "sg:phone":"+1 418 276 8466",
    "sg:postcode":"G8L 4S1",
    "sg:province":"QC",
    "wof:name":"Resto Des Copains",
    "wof:placetype":"venue"
},
  "geometry": {"coordinates":[-72.201897,48.884197],"type":"Point"}
}