{
  "type": "Feature",
  "properties": {
    "addr:full":"Laval QC H7E 4Y6",
    "addr:postcode":"h7e 4y6",
    "iso:country":"CA",
    "sg:city":"Laval",
    "sg:classifiers":[
        {
            "category":"Health Services",
            "subcategory":"Doctor",
            "type":"Services"
        }
    ],
    "sg:phone":"+1 450 661 5930",
    "sg:postcode":"H7E 4Y6",
    "sg:province":"QC",
    "sg:tags":[
        "clinic"
    ],
    "wof:name":"Clinique Chirurgie Plastique",
    "wof:placetype":"venue"
},
  "geometry": {"coordinates":[-73.682236,45.599735],"type":"Point"}
}