{
  "type": "Feature",
  "properties": {
    "addr:full":"Black Lake QC G6H 2A9",
    "addr:postcode":"g6h 2a9",
    "addr:street":"Black Lake",
    "iso:country":"CA",
    "sg:city":"Black Lake",
    "sg:classifiers":[
        {
            "category":"Bars & Pubs",
            "type":"Food & Drink"
        }
    ],
    "sg:phone":"+1 418 423 7066",
    "sg:postcode":"G6H 2A9",
    "sg:province":"QC",
    "sg:tags":[
        "lounge",
        "cocktail"
    ],
    "wof:name":"Bar Caserne Du Boulevard",
    "wof:placetype":"venue"
},
  "geometry": {"coordinates":[-71.369865,46.050205],"type":"Point"}
}