{
  "type": "Feature",
  "properties": {
    "iso:country":"CA",
    "sg:address":"777 3rd Ave E",
    "sg:city":"Owen Sound",
    "sg:classifiers":[
        {
            "category":"Taxi",
            "type":"Transportation"
        }
    ],
    "sg:phone":"+1 519 371 5555",
    "sg:postcode":"N4K 2K4",
    "sg:province":"ON",
    "sg:tags":[
        "taxicab"
    ],
    "wof:name":"Bayshore Taxi",
    "wof:placetype":"venue"
},
  "geometry": {"coordinates":[-80.94022369379999,44.5636100769],"type":"Point"}
}