{
  "type": "Feature",
  "properties": {
    "addr:full":"10013 100th Ave Peace River AB T8S 1S6",
    "addr:housenumber":"10013",
    "addr:postcode":"t8s 1s6",
    "addr:street":"100Th Ave",
    "iso:country":"CA",
    "sg:address":"10013 100th Ave",
    "sg:city":"Peace River",
    "sg:classifiers":[
        {
            "category":"Shopping",
            "subcategory":"Pharmacy",
            "type":"Retail Goods"
        }
    ],
    "sg:phone":"+1 780 624 1200",
    "sg:postcode":"T8S 1S6",
    "sg:province":"AB",
    "wof:name":"Harders Drug Mart",
    "wof:placetype":"venue"
},
  "geometry": {"coordinates":[-117.288703919,56.2338943481],"type":"Point"}
}