{
  "type": "Feature",
  "properties": {
    "addr:full":"5737 Boul Davis Saint-Hubert QC J3Y 8H7",
    "addr:housenumber":"5737",
    "addr:postcode":"j3y 8h7",
    "addr:street":"Boul Davis",
    "iso:country":"CA",
    "sg:address":"5737 Boul Davis",
    "sg:city":"Saint-Hubert",
    "sg:classifiers":[
        {
            "category":"Professional",
            "subcategory":"Accounting & Tax Preparation",
            "type":"Services"
        }
    ],
    "sg:phone":"+1 450 656 6717",
    "sg:postcode":"J3Y 8H7",
    "sg:province":"QC",
    "sg:tags":[
        "accountant"
    ],
    "wof:name":"Bissonnette, C",
    "wof:placetype":"venue"
},
  "geometry": {"coordinates":[-73.419624,45.491234],"type":"Point"}
}