{
  "type": "Feature",
  "properties": {
    "iso:country":"CA",
    "sg:address":"2210 Speers Ave",
    "sg:city":"Saskatoon",
    "sg:classifiers":[
        {
            "category":"Manufacturing",
            "subcategory":"Tools & Machinery",
            "type":"Manufacturing & Wholesale Goods"
        }
    ],
    "sg:phone":"+1 306 931 2967",
    "sg:postcode":"S7L 5X7",
    "sg:province":"SK",
    "sg:tags":[
        "electric",
        "motor"
    ],
    "wof:name":"Klassen Electric Motor Svc Ltd",
    "wof:placetype":"venue"
},
  "geometry": {"coordinates":[-106.67616271999999,52.1598625183],"type":"Point"}
}