{
  "type": "Feature",
  "properties": {
    "addr:full":"57 Av Sainte-Helene Saint-Lambert QC J4R 1S4",
    "addr:postcode":"j4r 1s4",
    "addr:street":"57 Av Sainte-Helene",
    "iso:country":"CA",
    "sg:address":"57 Av Sainte-Helene",
    "sg:city":"Saint-Lambert",
    "sg:classifiers":[
        {
            "category":"Home & Garden",
            "subcategory":"Building Materials",
            "type":"Retail Goods"
        }
    ],
    "sg:phone":"+1 450 466 1637",
    "sg:postcode":"J4R 1S4",
    "sg:province":"QC",
    "wof:name":"Edouard Beauchesne 1985 Inc",
    "wof:placetype":"venue"
},
  "geometry": {"coordinates":[-73.49932861329999,45.4974479675],"type":"Point"}
}