{
  "type": "Feature",
  "properties": {
    "addr:full":"401 Av Courtemanche Montreal-Est QC H1B 4X7",
    "addr:housenumber":"401",
    "addr:postcode":"h1b 4x7",
    "addr:street":"Av Courtemanche",
    "iso:country":"CA",
    "sg:address":"401 Av Courtemanche",
    "sg:city":"Montreal-Est",
    "sg:classifiers":[
        {
            "category":"Home & Garden",
            "subcategory":"Building Materials",
            "type":"Retail Goods"
        }
    ],
    "sg:phone":"+1 514 645 8707",
    "sg:postcode":"H1B 4X7",
    "sg:province":"QC",
    "sg:tags":[
        "siding"
    ],
    "wof:name":"Kbp Ltee",
    "wof:placetype":"venue"
},
  "geometry": {"coordinates":[-73.51062,45.633923],"type":"Point"}
}