{
  "type": "Feature",
  "properties": {
    "addr:full":"Nanaimo BC V9S 5G1",
    "addr:postcode":"v9s 5g1",
    "iso:country":"CA",
    "sg:city":"Nanaimo",
    "sg:classifiers":[
        {
            "category":"Real Estate",
            "subcategory":"Real Estate Operator",
            "type":"Services"
        }
    ],
    "sg:phone":"+1 250 758 8432",
    "sg:postcode":"V9S 5G1",
    "sg:province":"BC",
    "sg:tags":[
        "apartment"
    ],
    "wof:name":"Executive House",
    "wof:placetype":"venue"
},
  "geometry": {"coordinates":[-123.980019,49.196709],"type":"Point"}
}