{
  "type": "Feature",
  "properties": {
    "iso:country":"CA",
    "sg:city":"Winkler",
    "sg:classifiers":[
        {
            "category":"Personal",
            "subcategory":"Beauty Salon",
            "type":"Services"
        }
    ],
    "sg:phone":"+1 204 325 5149",
    "sg:postcode":"R6W 4A5",
    "sg:province":"MB",
    "wof:name":"Hair's the Place",
    "wof:placetype":"venue"
},
  "geometry": {"coordinates":[-97.9395065308,49.1821517944],"type":"Point"}
}