{
  "type": "Feature",
  "properties": {
    "addr:full":"109 Tingley St Ashcroft BC V0K 1A0",
    "addr:housenumber":"109",
    "addr:postcode":"v0k 1a0",
    "addr:street":"Tingley St",
    "iso:country":"CA",
    "sg:address":"109 Tingley St",
    "sg:city":"Ashcroft",
    "sg:classifiers":[
        {
            "category":"Manufacturing",
            "subcategory":"Tools & Machinery",
            "type":"Manufacturing & Wholesale Goods"
        }
    ],
    "sg:phone":"+1 250 453 9063",
    "sg:postcode":"V0K 1A0",
    "sg:province":"BC",
    "sg:tags":[
        "heating",
        "contractor"
    ],
    "wof:name":"Precision Sheet Metal",
    "wof:placetype":"venue"
},
  "geometry": {"coordinates":[-121.278893,50.729961],"type":"Point"}
}