{
  "type": "Feature",
  "properties": {
    "addr:full":"782 Mckay Rd Pickering ON L1W 2Y4",
    "addr:housenumber":"782",
    "addr:postcode":"l1w 2y4",
    "addr:street":"Mckay Rd",
    "iso:country":"CA",
    "sg:address":"782 Mckay Rd",
    "sg:city":"Pickering",
    "sg:classifiers":[
        {
            "category":"Manufacturing",
            "subcategory":"Paper Products",
            "type":"Manufacturing & Wholesale Goods"
        }
    ],
    "sg:phone":"+1 905 686 3251",
    "sg:postcode":"L1W 2Y4",
    "sg:province":"ON",
    "sg:tags":[
        "corrugated",
        "solid",
        "fiber",
        "box"
    ],
    "wof:name":"Terlyn Industries Ltd",
    "wof:placetype":"venue"
},
  "geometry": {"coordinates":[-79.0557632446,43.8207397461],"type":"Point"}
}