{
  "type": "Feature",
  "properties": {
    "addr:full":"910 Rue Douglas Saint-Jean-Sur-Richelieu QC J3A 1V1",
    "addr:housenumber":"910",
    "addr:postcode":"j3a 1v1",
    "addr:street":"Rue Douglas",
    "iso:country":"CA",
    "sg:address":"910 Rue Douglas",
    "sg:city":"Saint-Jean-Sur-Richelieu",
    "sg:classifiers":[
        {
            "category":"Home & Garden",
            "subcategory":"Building Materials",
            "type":"Retail Goods"
        }
    ],
    "sg:phone":"+1 450 348 9245",
    "sg:postcode":"J3A 1V1",
    "sg:province":"QC",
    "sg:tags":[
        "glass",
        "window",
        "plate"
    ],
    "wof:name":"Lebeau Vitres D'Autos",
    "wof:placetype":"venue"
},
  "geometry": {"coordinates":[-73.2845840454,45.3322410583],"type":"Point"}
}