{
  "type": "Feature",
  "properties": {
    "iso:country":"CA",
    "sg:city":"Manitowaning",
    "sg:classifiers":[
        {
            "category":"Government",
            "subcategory":"Fire Station",
            "type":"Public Place"
        }
    ],
    "sg:phone":"+1 705 368 3335",
    "sg:postcode":"P0P 1N0",
    "sg:province":"ON",
    "sg:tags":[
        "department"
    ],
    "wof:name":"Northeastern Manitoulin & Isld",
    "wof:placetype":"venue"
},
  "geometry": {"coordinates":[-81.82930755620001,45.7488365173],"type":"Point"}
}