{
  "type": "Feature",
  "properties": {
    "iso:country":"CA",
    "sg:address":"63 Centennial Rd",
    "sg:city":"Orangeville",
    "sg:classifiers":[
        {
            "category":"Wholesale",
            "subcategory":"Hardware",
            "type":"Manufacturing & Wholesale Goods"
        }
    ],
    "sg:phone":"+1 519 941 7420",
    "sg:postcode":"L9W 3R1",
    "sg:province":"ON",
    "sg:tags":[
        "fastener"
    ],
    "wof:name":"Brafasco",
    "wof:placetype":"venue"
},
  "geometry": {"coordinates":[-80.112907,43.90707],"type":"Point"}
}