{
  "type": "Feature",
  "properties": {
    "iso:country":"CA",
    "sg:address":"702 Main St",
    "sg:city":"Humboldt",
    "sg:classifiers":[
        {
            "category":"Retail",
            "subcategory":"Portrait Studio",
            "type":"Services"
        }
    ],
    "sg:phone":"+1 306 682 3111",
    "sg:postcode":"S0K 2A0",
    "sg:province":"SK",
    "sg:tags":[
        "photography"
    ],
    "wof:name":"Reflections By Richard",
    "wof:placetype":"venue"
},
  "geometry": {"coordinates":[-105.122718811,52.2005500793],"type":"Point"}
}