{
  "type": "Feature",
  "properties": {
    "addr:full":"Scarborough ON M1W 3Y1",
    "addr:postcode":"m1w 3y1",
    "iso:country":"CA",
    "sg:city":"Scarborough",
    "sg:classifiers":[
        {
            "category":"Education",
            "subcategory":"Vocational School",
            "type":"Public Place"
        }
    ],
    "sg:phone":"+1 416 720 3221",
    "sg:postcode":"M1W 3Y1",
    "sg:province":"ON",
    "sg:tags":[
        "training",
        "computer"
    ],
    "wof:name":"Compu Ed",
    "wof:placetype":"venue"
},
  "geometry": {"coordinates":[-79.3230133057,43.8160514832],"type":"Point"}
}