{
  "type": "Feature",
  "properties": {
    "iso:country":"CA",
    "sg:address":"650 Dominion St",
    "sg:city":"Prince George",
    "sg:classifiers":[
        {
            "category":"Travel",
            "subcategory":"Hotels & Motels",
            "type":"Entertainment"
        }
    ],
    "sg:phone":"+1 250 563 9241",
    "sg:postcode":"V2L 1T8",
    "sg:province":"BC",
    "wof:name":"Downtown Motel",
    "wof:placetype":"venue"
},
  "geometry": {"coordinates":[-122.746353149,53.9141387939],"type":"Point"}
}