{
  "type": "Feature",
  "properties": {
    "addr:full":"3013 30 Ave Vernon BC V1T 2C1",
    "addr:housenumber":"3013",
    "addr:postcode":"v1t 2c1",
    "addr:street":"30 Ave",
    "iso:country":"CA",
    "sg:address":"3013 30 Ave",
    "sg:city":"Vernon",
    "sg:classifiers":[
        {
            "category":"Shopping",
            "subcategory":"Used Merchandise",
            "type":"Retail Goods"
        }
    ],
    "sg:phone":"+1 250 542 2677",
    "sg:postcode":"V1T 2C1",
    "sg:province":"BC",
    "sg:tags":[
        "shop",
        "consignment"
    ],
    "wof:name":"Carousel Consignments",
    "wof:placetype":"venue"
},
  "geometry": {"coordinates":[-119.271034,50.263885],"type":"Point"}
}