{
  "type": "Feature",
  "properties": {
    "iso:country":"CA",
    "sg:address":"451 Main St S",
    "sg:city":"Exeter",
    "sg:classifiers":[
        {
            "category":"Home & Garden",
            "subcategory":"Building Materials",
            "type":"Retail Goods"
        }
    ],
    "sg:phone":"+1 519 235 0181",
    "sg:postcode":"N0M 1S1",
    "sg:province":"ON",
    "sg:tags":[
        "paint"
    ],
    "wof:name":"Partners Paint & Paper",
    "wof:placetype":"venue"
},
  "geometry": {"coordinates":[-81.4801483154,43.3441886902],"type":"Point"}
}