{
  "type": "Feature",
  "properties": {
    "addr:full":"1689 Av Du Mont-Royal E Montreal QC H2J 1Z6",
    "addr:housenumber":"1689",
    "addr:postcode":"h2j 1z6",
    "addr:street":"Av Du Mont-Royal E",
    "iso:country":"CA",
    "sg:address":"1689 Av Du Mont-Royal E",
    "sg:city":"Montreal",
    "sg:classifiers":[
        {
            "category":"Restaurant",
            "type":"Food & Drink"
        }
    ],
    "sg:phone":"+1 514 523 1727",
    "sg:postcode":"H2J 1Z6",
    "sg:province":"QC",
    "wof:name":"Steerburger Tous Les Jours",
    "wof:placetype":"venue"
},
  "geometry": {"coordinates":[-73.575104,45.532585],"type":"Point"}
}