{
  "type": "Feature",
  "properties": {
    "addr:full":"250 Rue Du Parc Laurier-Station QC G0S 1N0",
    "addr:housenumber":"250",
    "addr:postcode":"g0s 1n0",
    "addr:street":"Rue Du Parc",
    "iso:country":"CA",
    "sg:address":"250 Rue Du Parc",
    "sg:city":"Laurier-Station",
    "sg:classifiers":[
        {
            "category":"Manufacturing",
            "subcategory":"Wood Products",
            "type":"Manufacturing & Wholesale Goods"
        }
    ],
    "sg:phone":"+1 418 728 2903",
    "sg:postcode":"G0S 1N0",
    "sg:province":"QC",
    "sg:tags":[
        "pallet",
        "skid"
    ],
    "wof:name":"Recuperation DE Palettes",
    "wof:placetype":"venue"
},
  "geometry": {"coordinates":[-71.6310958862,46.5385513306],"type":"Point"}
}