{
  "type": "Feature",
  "properties": {
    "addr:full":"77 Woolastook Dr Grand Bay-Westfield NB E5K 1S3",
    "addr:housenumber":"77",
    "addr:postcode":"e5k 1s3",
    "addr:street":"Woolastook Dr",
    "iso:country":"CA",
    "sg:address":"77 Woolastook Dr",
    "sg:city":"Grand Bay-Westfield",
    "sg:classifiers":[
        {
            "category":"Organizations",
            "subcategory":"Religious Organization",
            "type":"Services"
        }
    ],
    "sg:phone":"+1 506 738 8423",
    "sg:postcode":"E5K 1S3",
    "sg:province":"NB",
    "sg:tags":[
        "church"
    ],
    "wof:name":"Grand Bay United Baptist Chr",
    "wof:placetype":"venue"
},
  "geometry": {"coordinates":[-66.196144104,45.3129882812],"type":"Point"}
}