{
  "type": "Feature",
  "properties": {
    "addr:full":"720 Boul Lebourgneuf Quebec QC G2J 1E2",
    "addr:housenumber":"720",
    "addr:postcode":"g2j 1e2",
    "addr:street":"Boul Lebourgneuf",
    "iso:country":"CA",
    "sg:address":"720 Boul Lebourgneuf",
    "sg:city":"Quebec",
    "sg:classifiers":[
        {
            "category":"Food & Beverages",
            "subcategory":"Groceries & Convenience Stores",
            "type":"Retail Goods"
        }
    ],
    "sg:phone":"+1 418 623 7402",
    "sg:postcode":"G2J 1E2",
    "sg:province":"QC",
    "wof:name":"Produits Shell Canada",
    "wof:placetype":"venue"
},
  "geometry": {"coordinates":[-71.2796783447,46.8434867859],"type":"Point"}
}