{
  "type": "Feature",
  "properties": {
    "iso:country":"CA",
    "sg:address":"Mapleview Dr E",
    "sg:city":"Barrie",
    "sg:classifiers":[
        {
            "category":"Real Estate",
            "subcategory":"Developer",
            "type":"Services"
        }
    ],
    "sg:phone":"+1 705 722 9640",
    "sg:postcode":"L4M 4S7",
    "sg:province":"ON",
    "sg:tags":[
        "cemetery"
    ],
    "wof:name":"St Paul's Innisfil Cemetery",
    "wof:placetype":"venue"
},
  "geometry": {"coordinates":[-79.620331,44.350029],"type":"Point"}
}