{
  "type": "Feature",
  "properties": {
    "addr:full":"1062 Bloor St W Toronto ON M6H 1M3",
    "addr:housenumber":"1062",
    "addr:postcode":"m6h 1m3",
    "addr:street":"Bloor St W",
    "iso:country":"CA",
    "sg:address":"1062 Bloor St W",
    "sg:city":"Toronto",
    "sg:classifiers":[
        {
            "category":"Food & Beverages",
            "subcategory":"Groceries & Convenience Stores",
            "type":"Retail Goods"
        }
    ],
    "sg:phone":"+1 416 534 1904",
    "sg:postcode":"M6H 1M3",
    "sg:province":"ON",
    "sg:tags":[
        "grocer"
    ],
    "wof:name":"Mediterranean Food Store",
    "wof:placetype":"venue"
},
  "geometry": {"coordinates":[-79.43283099999999,43.660442],"type":"Point"}
}