{
  "type": "Feature",
  "properties": {
    "addr:full":"190 Main St E Hamilton ON L8N 1H3",
    "addr:housenumber":"190",
    "addr:postcode":"l8n 1h3",
    "addr:street":"Main St E",
    "iso:country":"CA",
    "sg:address":"190 Main St E",
    "sg:city":"Hamilton",
    "sg:classifiers":[
        {
            "category":"Health Services",
            "subcategory":"Clinic",
            "type":"Services"
        }
    ],
    "sg:phone":"+1 905 525 5877",
    "sg:postcode":"L8N 1H3",
    "sg:province":"ON",
    "sg:tags":[
        "wheel",
        "home",
        "chair",
        "scooter"
    ],
    "wof:name":"Andre's Home Health Care",
    "wof:placetype":"venue"
},
  "geometry": {"coordinates":[-79.862274,43.253372],"type":"Point"}
}