{
  "type": "Feature",
  "properties": {
    "addr:full":"484 Currie Rd Swan River MB R0L 1Z0",
    "addr:housenumber":"484",
    "addr:postcode":"r0l 1z0",
    "addr:street":"Currie Rd",
    "iso:country":"CA",
    "sg:address":"484 Currie Rd",
    "sg:city":"Swan River",
    "sg:classifiers":[
        {
            "category":"Restaurant",
            "type":"Food & Drink"
        }
    ],
    "sg:phone":"+1 204 734 2600",
    "sg:postcode":"R0L 1Z0",
    "sg:province":"MB",
    "wof:name":"Mr Ribs Family Restaurant",
    "wof:placetype":"venue"
},
  "geometry": {"coordinates":[-101.251495361,52.1132888794],"type":"Point"}
}