{
  "type": "Feature",
  "properties": {
    "addr:full":"577 Main St Sussex NB E4E 7H4",
    "addr:housenumber":"577",
    "addr:postcode":"e4e 7h4",
    "addr:street":"Main St",
    "iso:country":"CA",
    "sg:address":"577 Main St",
    "sg:city":"Sussex",
    "sg:classifiers":[
        {
            "category":"Shopping",
            "subcategory":"Used Merchandise",
            "type":"Retail Goods"
        }
    ],
    "sg:phone":"+1 506 432 6246",
    "sg:postcode":"E4E 7H4",
    "sg:province":"NB",
    "sg:tags":[
        "book",
        "rare",
        "dealer"
    ],
    "wof:name":"Main Street Books",
    "wof:placetype":"venue"
},
  "geometry": {"coordinates":[-65.508675,45.723083],"type":"Point"}
}