{
  "type": "Feature",
  "properties": {
    "addr:full":"3604 76 Ave NW Edmonton AB T6B 2N8",
    "addr:housenumber":"3604",
    "addr:postcode":"t6b 2n8",
    "addr:street":"76 Ave Nw",
    "iso:country":"CA",
    "sg:address":"3604 76 Ave NW",
    "sg:city":"Edmonton",
    "sg:classifiers":[
        {
            "category":"Professional",
            "subcategory":"Business Services",
            "type":"Services"
        }
    ],
    "sg:phone":"+1 780 465 1520",
    "sg:postcode":"T6B 2N8",
    "sg:province":"AB",
    "sg:tags":[
        "drafting"
    ],
    "wof:name":"M & D Drafting Ltd",
    "wof:placetype":"venue"
},
  "geometry": {"coordinates":[-113.39716339100001,53.5125083923],"type":"Point"}
}