{
  "type": "Feature",
  "properties": {
    "iso:country":"CA",
    "sg:address":"Hwy 3 S",
    "sg:city":"Prince Albert",
    "sg:classifiers":[
        {
            "category":"Freight",
            "type":"Transportation"
        }
    ],
    "sg:phone":"+1 306 764 1855",
    "sg:postcode":"S6V 5R5",
    "sg:province":"SK",
    "sg:tags":[
        "trucking"
    ],
    "wof:name":"Jay's Moving & Storage",
    "wof:placetype":"venue"
},
  "geometry": {"coordinates":[-105.738777161,53.1803245544],"type":"Point"}
}