{
  "type": "Feature",
  "properties": {
    "addr:full":"123 Rue Couture Thetford Mines QC G6G 1C2",
    "addr:housenumber":"123",
    "addr:postcode":"g6g 1c2",
    "addr:street":"Rue Couture",
    "iso:country":"CA",
    "sg:address":"123 Rue Couture",
    "sg:city":"Thetford Mines",
    "sg:classifiers":[
        {
            "category":"Shopping",
            "subcategory":"Jewelry",
            "type":"Retail Goods"
        }
    ],
    "sg:phone":"+1 418 338 1679",
    "sg:postcode":"G6G 1C2",
    "sg:province":"QC",
    "sg:tags":[
        "jeweler"
    ],
    "wof:name":"Bijouterie Claire Lefebvre",
    "wof:placetype":"venue"
},
  "geometry": {"coordinates":[-71.314728,46.10804],"type":"Point"}
}