{
  "type": "Feature",
  "properties": {
    "addr:full":"206 2nd Ave W Unity SK S0K 4L0",
    "addr:housenumber":"206",
    "addr:postcode":"s0k 4l0",
    "addr:street":"2Nd Ave W",
    "iso:country":"CA",
    "sg:address":"206 2nd Ave W",
    "sg:city":"Unity",
    "sg:classifiers":[
        {
            "category":"Professional",
            "subcategory":"Lawyer & Legal Services",
            "type":"Services"
        }
    ],
    "sg:phone":"+1 306 228 2693",
    "sg:postcode":"S0K 4L0",
    "sg:province":"SK",
    "sg:tags":[
        "attorney"
    ],
    "wof:name":"Neil, L Kenneth",
    "wof:placetype":"venue"
},
  "geometry": {"coordinates":[-109.161239624,52.4434356689],"type":"Point"}
}