{
  "type": "Feature",
  "properties": {
    "iso:country":"CA",
    "sg:address":"20619 Eastleigh Cres",
    "sg:city":"Langley",
    "sg:classifiers":[
        {
            "category":"Social Services",
            "subcategory":"Adult Care",
            "type":"Services"
        }
    ],
    "sg:phone":"+1 604 534 7186",
    "sg:postcode":"V3A 4C3",
    "sg:province":"BC",
    "sg:tags":[
        "community",
        "facility"
    ],
    "wof:name":"Highland Lodge",
    "wof:placetype":"venue"
},
  "geometry": {"coordinates":[-122.651016235,49.1069297791],"type":"Point"}
}