{
  "type": "Feature",
  "properties": {
    "iso:country":"CA",
    "sg:address":"396 Drew St",
    "sg:city":"Oshawa",
    "sg:classifiers":[
        {
            "category":"Autos & Motor Vehicles",
            "subcategory":"Auto Supplies",
            "type":"Retail Goods"
        }
    ],
    "sg:phone":"+1 905 579 0741",
    "sg:postcode":"L1H 5B5",
    "sg:province":"ON",
    "sg:tags":[
        "equipment",
        "racing",
        "car",
        "automobile"
    ],
    "wof:name":"Tjt Racing Products",
    "wof:placetype":"venue"
},
  "geometry": {"coordinates":[-78.85150146479999,43.8880882263],"type":"Point"}
}