{
  "type": "Feature",
  "properties": {
    "addr:full":"134 Fenmar Dr North York ON M9L 1M6",
    "addr:housenumber":"134",
    "addr:postcode":"m9l 1m6",
    "addr:street":"Fenmar Dr",
    "iso:country":"CA",
    "sg:address":"134 Fenmar Dr",
    "sg:city":"North York",
    "sg:classifiers":[
        {
            "category":"Wholesale",
            "subcategory":"Machinery & Supplies",
            "type":"Manufacturing & Wholesale Goods"
        }
    ],
    "sg:phone":"+1 416 743 2627",
    "sg:postcode":"M9L 1M6",
    "sg:province":"ON",
    "sg:tags":[
        "equipment",
        "hydraulic"
    ],
    "wof:name":"Fenmar Diesel & Hydraulics Ltd",
    "wof:placetype":"venue"
},
  "geometry": {"coordinates":[-79.55043000000001,43.76033],"type":"Point"}
}