{
  "type": "Feature",
  "properties": {
    "addr:full":"23 Collingwood St Flesherton ON N0C 1E0",
    "addr:housenumber":"23",
    "addr:postcode":"n0c 1e0",
    "addr:street":"Collingwood St",
    "iso:country":"CA",
    "sg:address":"23 Collingwood St",
    "sg:city":"Flesherton",
    "sg:classifiers":[
        {
            "category":"Cinema",
            "subcategory":"Movie Rental",
            "type":"Entertainment"
        }
    ],
    "sg:phone":"+1 519 924 0230",
    "sg:postcode":"N0C 1E0",
    "sg:province":"ON",
    "sg:tags":[
        "leasing",
        "video",
        "disc",
        "tape"
    ],
    "wof:name":"Jolley's Dairy Bar & Video",
    "wof:placetype":"venue"
},
  "geometry": {"coordinates":[-80.549599,44.262402],"type":"Point"}
}