{
  "type": "Feature",
  "properties": {
    "addr:full":"91 Thornhill Dr Halifax NS B3R 2J4",
    "addr:housenumber":"91",
    "addr:postcode":"b3r 2j4",
    "addr:street":"Thornhill Dr",
    "iso:country":"CA",
    "sg:address":"91 Thornhill Dr",
    "sg:city":"Halifax",
    "sg:classifiers":[
        {
            "category":"Organizations",
            "subcategory":"Religious Organization",
            "type":"Services"
        }
    ],
    "sg:phone":"+1 902 477 4099",
    "sg:postcode":"B3R 2J4",
    "sg:province":"NS",
    "sg:tags":[
        "church"
    ],
    "wof:name":"Calvary United Baptist Church",
    "wof:placetype":"venue"
},
  "geometry": {"coordinates":[-63.615532,44.605865],"type":"Point"}
}