{
  "type": "Feature",
  "properties": {
    "addr:full":"3800 Wellington Rd Crystal Beach ON L0S 1B0",
    "addr:housenumber":"3800",
    "addr:postcode":"l0s 1b0",
    "addr:street":"Wellington Rd",
    "iso:country":"CA",
    "sg:address":"3800 Wellington Rd",
    "sg:city":"Crystal Beach",
    "sg:classifiers":[
        {
            "category":"Education",
            "subcategory":"School",
            "type":"Public Place"
        }
    ],
    "sg:phone":"+1 905 894 3670",
    "sg:postcode":"L0S 1B0",
    "sg:province":"ON",
    "wof:name":"St George Catholic",
    "wof:placetype":"venue"
},
  "geometry": {"coordinates":[-79.057266,42.873611],"type":"Point"}
}