{
  "type": "Feature",
  "properties": {
    "addr:full":"76 Starrs Rd Yarmouth NS B5A 2T5",
    "addr:housenumber":"76",
    "addr:postcode":"b5a 2t5",
    "addr:street":"Starrs Rd",
    "iso:country":"CA",
    "sg:address":"76 Starrs Rd",
    "sg:city":"Yarmouth",
    "sg:classifiers":[
        {
            "category":"Shopping",
            "subcategory":"Books",
            "type":"Retail Goods"
        }
    ],
    "sg:phone":"+1 902 742 2835",
    "sg:postcode":"B5A 2T5",
    "sg:province":"NS",
    "sg:tags":[
        "dealer"
    ],
    "wof:name":"Coles",
    "wof:placetype":"venue"
},
  "geometry": {"coordinates":[-66.09865570069999,43.8413314819],"type":"Point"}
}