{
  "type": "Feature",
  "properties": {
    "addr:full":"366 Bulyea Rd NW Edmonton AB T6R 2B3",
    "addr:housenumber":"366",
    "addr:postcode":"t6r 2b3",
    "addr:street":"Bulyea Rd Nw",
    "iso:country":"CA",
    "sg:address":"366 Bulyea Rd NW",
    "sg:city":"Edmonton",
    "sg:classifiers":[
        {
            "category":"Health Services",
            "subcategory":"Doctor",
            "type":"Services"
        }
    ],
    "sg:phone":"+1 780 430 8788",
    "sg:postcode":"T6R 2B3",
    "sg:province":"AB",
    "sg:tags":[
        "physician",
        "clinic",
        "surgeon"
    ],
    "wof:name":"Brookview Medical Clinic",
    "wof:placetype":"venue"
},
  "geometry": {"coordinates":[-113.572914,53.475594],"type":"Point"}
}