{
  "type": "Feature",
  "properties": {
    "addr:full":"2019 Yonge St Toronto ON M4S 2A2",
    "addr:housenumber":"2019",
    "addr:postcode":"m4s 2a2",
    "addr:street":"Yonge St",
    "iso:country":"CA",
    "sg:address":"2019 Yonge St",
    "sg:city":"Toronto",
    "sg:classifiers":[
        {
            "category":"Retail",
            "subcategory":"Animal Services",
            "type":"Services"
        }
    ],
    "sg:phone":"+1 416 487 6267",
    "sg:postcode":"M4S 2A2",
    "sg:province":"ON",
    "sg:tags":[
        "pet",
        "food",
        "supply"
    ],
    "wof:name":"Global Pet Foods",
    "wof:placetype":"venue"
},
  "geometry": {"coordinates":[-79.3970870972,43.7012825012],"type":"Point"}
}