{
  "type": "Feature",
  "properties": {
    "iso:country":"CA",
    "sg:address":"306 Korah Rd",
    "sg:city":"Sault Ste Marie",
    "sg:classifiers":[
        {
            "category":"Travel",
            "subcategory":"Hotels & Motels",
            "type":"Entertainment"
        }
    ],
    "sg:phone":"+1 705 253 1411",
    "sg:postcode":"P6C 4H1",
    "sg:province":"ON",
    "wof:name":"Roosevelt Hotel",
    "wof:placetype":"venue"
},
  "geometry": {"coordinates":[-84.3618927002,46.5313949585],"type":"Point"}
}