{
  "type": "Feature",
  "properties": {
    "iso:country":"CA",
    "sg:address":"7 Superior St # A",
    "sg:city":"Devon",
    "sg:classifiers":[
        {
            "category":"Sports & Exercise",
            "subcategory":"Gym",
            "type":"Entertainment"
        }
    ],
    "sg:phone":"+1 780 987 7324",
    "sg:postcode":"T9G 1E9",
    "sg:province":"AB",
    "sg:tags":[
        "club",
        "health",
        "studio",
        "gymnasium"
    ],
    "wof:name":"Curves For Women",
    "wof:placetype":"venue"
},
  "geometry": {"coordinates":[-113.73240661600001,53.366191864],"type":"Point"}
}