{
  "type": "Feature",
  "properties": {
    "addr:full":"8 Lee Centre Dr # 16 Scarborough ON M1H 3H8",
    "addr:housenumber":"8",
    "addr:postcode":"m1h 3h8",
    "addr:street":"Lee Centre Dr # 16",
    "iso:country":"CA",
    "sg:address":"8 Lee Centre Dr # 16",
    "sg:city":"Scarborough",
    "sg:classifiers":[
        {
            "category":"Retail",
            "subcategory":"Laundry & Dry Cleaning",
            "type":"Services"
        }
    ],
    "sg:phone":"+1 416 289 4622",
    "sg:postcode":"M1H 3H8",
    "sg:province":"ON",
    "sg:tags":[
        "cleaners"
    ],
    "wof:name":"Hillsborough Cleaners",
    "wof:placetype":"venue"
},
  "geometry": {"coordinates":[-79.2463607788,43.781539917],"type":"Point"}
}