{
  "type": "Feature",
  "properties": {
    "addr:full":"Thompson MB R8N 0C6",
    "addr:postcode":"r8n 0c6",
    "iso:country":"CA",
    "sg:city":"Thompson",
    "sg:classifiers":[
        {
            "category":"Health Services",
            "subcategory":"Doctor",
            "type":"Services"
        }
    ],
    "sg:phone":"+1 204 677 4526",
    "sg:postcode":"R8N 0C6",
    "sg:province":"MB",
    "sg:tags":[
        "dentist"
    ],
    "wof:name":"Westwood Dental Clinic",
    "wof:placetype":"venue"
},
  "geometry": {"coordinates":[-97.87329864500001,55.7462310791],"type":"Point"}
}