{
  "type": "Feature",
  "properties": {
    "iso:country":"CA",
    "sg:address":"6835 Rue Jean-Talon E",
    "sg:city":"Saint-Leonard",
    "sg:classifiers":[
        {
            "category":"Shopping",
            "subcategory":"Shoes",
            "type":"Retail Goods"
        }
    ],
    "sg:phone":"+1 514 253 6555",
    "sg:postcode":"H1S 1N2",
    "sg:province":"QC",
    "sg:tags":[
        "clothing",
        "furnishing"
    ],
    "wof:name":"Moores Vetements Pour Hommes",
    "wof:placetype":"venue"
},
  "geometry": {"coordinates":[-73.5721359253,45.5956306458],"type":"Point"}
}