{
  "type": "Feature",
  "properties": {
    "iso:country":"CA",
    "sg:address":"626 Rue Notre-Dame Est",
    "sg:city":"Cap-DE-LA-Madeleine",
    "sg:classifiers":[
        {
            "category":"Organizations",
            "subcategory":"Religious Organization",
            "type":"Services"
        }
    ],
    "sg:phone":"+1 819 374 2441",
    "sg:postcode":"G8T 4G9",
    "sg:province":"QC",
    "sg:tags":[
        "church"
    ],
    "wof:name":"Sanctuaire Notre Dame-Cap Shrn",
    "wof:placetype":"venue"
},
  "geometry": {"coordinates":[-72.4977798462,46.3708381653],"type":"Point"}
}