{
  "type": "Feature",
  "properties": {
    "addr:full":"North York ON M4A 2M2",
    "addr:postcode":"m4a 2m2",
    "iso:country":"CA",
    "sg:city":"North York",
    "sg:classifiers":[
        {
            "category":"Personal",
            "subcategory":"Beauty Salon",
            "type":"Services"
        }
    ],
    "sg:phone":"+1 416 750 9976",
    "sg:postcode":"M4A 2M2",
    "sg:province":"ON",
    "sg:tags":[
        "manicuring"
    ],
    "wof:name":"Nails Pro",
    "wof:placetype":"venue"
},
  "geometry": {"coordinates":[-79.3020019531,43.7227134705],"type":"Point"}
}