{
  "type": "Feature",
  "properties": {
    "addr:full":"4624 12 St NE Calgary AB T2E 4R4",
    "addr:housenumber":"4624",
    "addr:postcode":"t2e 4r4",
    "addr:street":"12 St Ne",
    "iso:country":"CA",
    "sg:address":"4624 12 St NE",
    "sg:city":"Calgary",
    "sg:classifiers":[
        {
            "category":"Wholesale",
            "subcategory":"Painting Supplies",
            "type":"Manufacturing & Wholesale Goods"
        }
    ],
    "sg:phone":"+1 403 250 7735",
    "sg:postcode":"T2E 4R4",
    "sg:province":"AB",
    "sg:tags":[
        "equipment",
        "painter"
    ],
    "wof:name":"Lemmer Spray Systems Ltd",
    "wof:placetype":"venue"
},
  "geometry": {"coordinates":[-114.033195496,51.0936851501],"type":"Point"}
}