{
  "type": "Feature",
  "properties": {
    "addr:full":"PO Box 969 Hanna AB T0J 1P0",
    "addr:housenumber":"po",
    "addr:postcode":"t0j 1p0",
    "addr:street":"Box 969 Hanna",
    "iso:country":"CA",
    "sg:address":"PO Box 969",
    "sg:city":"Hanna",
    "sg:classifiers":[
        {
            "category":"Building & Trades",
            "subcategory":"Construction",
            "type":"Services"
        }
    ],
    "sg:phone":"+1 403 854 2223",
    "sg:postcode":"T0J 1P0",
    "sg:province":"AB",
    "sg:tags":[
        "contractor"
    ],
    "wof:name":"Wes Karg Construction",
    "wof:placetype":"venue"
},
  "geometry": {"coordinates":[-111.942024231,51.6398353577],"type":"Point"}
}