{
  "type": "Feature",
  "properties": {
    "iso:country":"CA",
    "sg:address":"2575 Steeles Ave E",
    "sg:city":"Brampton",
    "sg:classifiers":[
        {
            "category":"Professional",
            "type":"Services"
        }
    ],
    "sg:phone":"+1 905 789 5559",
    "sg:postcode":"L6T 5T1",
    "sg:province":"ON",
    "sg:tags":[
        "financing",
        "establishment"
    ],
    "wof:name":"Infotax Consultants",
    "wof:placetype":"venue"
},
  "geometry": {"coordinates":[-79.6704330444,43.7222213745],"type":"Point"}
}