{
  "type": "Feature",
  "properties": {
    "addr:full":"1100 Main St Moncton NB E1C 1H4",
    "addr:housenumber":"1100",
    "addr:postcode":"e1c 1h4",
    "addr:street":"Main St",
    "iso:country":"CA",
    "sg:address":"1100 Main St",
    "sg:city":"Moncton",
    "sg:classifiers":[
        {
            "category":"Shopping",
            "subcategory":"Department Store",
            "type":"Retail Goods"
        }
    ],
    "sg:phone":"+1 506 855 1545",
    "sg:postcode":"E1C 1H4",
    "sg:province":"NB",
    "wof:name":"Bay",
    "wof:placetype":"venue"
},
  "geometry": {"coordinates":[-64.784645,46.086277],"type":"Point"}
}