{
  "type": "Feature",
  "properties": {
    "addr:full":"16605 S Hwy 7 & 12 Sunderland ON L0C 1H0",
    "addr:housenumber":"16605",
    "addr:postcode":"l0c 1h0",
    "addr:street":"S Hwy 7 & 12",
    "iso:country":"CA",
    "sg:address":"16605 S Hwy 7 & 12",
    "sg:city":"Sunderland",
    "sg:classifiers":[
        {
            "category":"Restaurant",
            "type":"Food & Drink"
        }
    ],
    "sg:phone":"+1 705 357 3882",
    "sg:postcode":"L0C 1H0",
    "sg:province":"ON",
    "wof:name":"Brock Stop",
    "wof:placetype":"venue"
},
  "geometry": {"coordinates":[-79.0705795288,44.2826042175],"type":"Point"}
}