{
  "type": "Feature",
  "properties": {
    "addr:full":"651 Rue Villeray Montreal QC H2R 1H9",
    "addr:housenumber":"651",
    "addr:postcode":"h2r 1h9",
    "addr:street":"Rue Villeray",
    "iso:country":"CA",
    "sg:address":"651 Rue Villeray",
    "sg:city":"Montreal",
    "sg:classifiers":[
        {
            "category":"Shopping",
            "subcategory":"Bicycles & Sporting Goods",
            "type":"Retail Goods"
        }
    ],
    "sg:phone":"+1 514 272 5834",
    "sg:postcode":"H2R 1H9",
    "sg:province":"QC",
    "wof:name":"Dumoulin Bicyclettes Enr",
    "wof:placetype":"venue"
},
  "geometry": {"coordinates":[-73.62190246580001,45.5433425903],"type":"Point"}
}