{
  "type": "Feature",
  "properties": {
    "addr:full":"1650 Boul LA Morille Quebec QC G2K 2L2",
    "addr:housenumber":"1650",
    "addr:postcode":"g2k 2l2",
    "addr:street":"Boul La Morille",
    "iso:country":"CA",
    "sg:address":"1650 Boul LA Morille",
    "sg:city":"Quebec",
    "sg:classifiers":[
        {
            "category":"Recreation",
            "type":"Entertainment"
        }
    ],
    "sg:phone":"+1 418 641 6272",
    "sg:postcode":"G2K 2L2",
    "sg:province":"QC",
    "sg:tags":[
        "government",
        "hall",
        "auditorium"
    ],
    "wof:name":"Lebourgneuf",
    "wof:placetype":"venue"
},
  "geometry": {"coordinates":[-71.30596199999999,46.842381],"type":"Point"}
}