{
  "type": "Feature",
  "properties": {
    "addr:full":"Barrie ON L4M 4Z8",
    "addr:postcode":"l4m 4z8",
    "iso:country":"CA",
    "sg:city":"Barrie",
    "sg:classifiers":[
        {
            "category":"Shopping",
            "subcategory":"Clothing, Apparel, & Fashions",
            "type":"Retail Goods"
        }
    ],
    "sg:phone":"+1 705 726 5917",
    "sg:postcode":"L4M 4Z8",
    "sg:province":"ON",
    "sg:tags":[
        "tailor"
    ],
    "wof:name":"Stitch It Canada's Tailor",
    "wof:placetype":"venue"
},
  "geometry": {"coordinates":[-79.7113571167,44.4139251709],"type":"Point"}
}