{
  "type": "Feature",
  "properties": {
    "addr:full":"775 Trojan Ave Ottawa ON K1K 2P6",
    "addr:housenumber":"775",
    "addr:postcode":"k1k 2p6",
    "addr:street":"Trojan Ave",
    "iso:country":"CA",
    "sg:address":"775 Trojan Ave",
    "sg:city":"Ottawa",
    "sg:classifiers":[
        {
            "category":"Professional",
            "subcategory":"Computer Services",
            "type":"Services"
        }
    ],
    "sg:phone":"+1 613 748 6222",
    "sg:postcode":"K1K 2P6",
    "sg:province":"ON",
    "wof:name":"Net Runner Inc",
    "wof:placetype":"venue"
},
  "geometry": {"coordinates":[-75.6392211914,45.4363555908],"type":"Point"}
}