{
  "type": "Feature",
  "properties": {
    "iso:country":"CA",
    "sg:address":"52 Maple Grove Rd",
    "sg:city":"Scotland",
    "sg:classifiers":[
        {
            "category":"Farming",
            "subcategory":"Farm",
            "type":"Manufacturing & Wholesale Goods"
        }
    ],
    "sg:phone":"+1 519 446 2424",
    "sg:postcode":"N0E 1R0",
    "sg:province":"ON",
    "wof:name":"Shawson Garden Inc",
    "wof:placetype":"venue"
},
  "geometry": {"coordinates":[-80.3589630127,43.0535697937],"type":"Point"}
}