{
  "type": "Feature",
  "properties": {
    "addr:full":"312 Warwick St Digby NS B0V 1A0",
    "addr:housenumber":"312",
    "addr:postcode":"b0v 1a0",
    "addr:street":"Warwick St",
    "iso:country":"CA",
    "sg:address":"312 Warwick St",
    "sg:city":"Digby",
    "sg:classifiers":[
        {
            "category":"Sports & Exercise",
            "subcategory":"Bowling",
            "type":"Entertainment"
        }
    ],
    "sg:phone":"+1 902 245 4444",
    "sg:postcode":"B0V 1A0",
    "sg:province":"NS",
    "sg:tags":[
        "center"
    ],
    "wof:name":"Wilson's Bowling Ctr",
    "wof:placetype":"venue"
},
  "geometry": {"coordinates":[-65.764656,44.616001],"type":"Point"}
}