{
  "type": "Feature",
  "properties": {
    "addr:full":"Montreal QC H2T 2S6",
    "addr:postcode":"h2t 2s6",
    "iso:country":"CA",
    "sg:city":"Montreal",
    "sg:classifiers":[
        {
            "category":"Building & Trades",
            "subcategory":"Landscaping Services",
            "type":"Services"
        }
    ],
    "sg:phone":"+1 514 399 9889",
    "sg:postcode":"H2T 2S6",
    "sg:province":"QC",
    "sg:tags":[
        "designer",
        "landscape"
    ],
    "wof:name":"Vlan Paysages",
    "wof:placetype":"venue"
},
  "geometry": {"coordinates":[-73.585876,45.520737],"type":"Point"}
}