{
  "type": "Feature",
  "properties": {
    "iso:country":"CA",
    "sg:address":"110 Eugenie St W",
    "sg:city":"Windsor",
    "sg:classifiers":[
        {
            "category":"Organizations",
            "subcategory":"Professional Association",
            "type":"Services"
        }
    ],
    "sg:phone":"+1 519 977 1432",
    "sg:postcode":"N8X 4Y6",
    "sg:province":"ON",
    "wof:name":"Women's Economic Forum",
    "wof:placetype":"venue"
},
  "geometry": {"coordinates":[-83.019104,42.286255],"type":"Point"}
}