{
  "type": "Feature",
  "properties": {
    "addr:full":"230 Lucasville Rd Lower Sackville NS B4B 1S1",
    "addr:housenumber":"230",
    "addr:postcode":"b4b 1s1",
    "addr:street":"Lucasville Rd Lower",
    "iso:country":"CA",
    "sg:address":"230 Lucasville Rd",
    "sg:city":"Lower Sackville",
    "sg:classifiers":[
        {
            "category":"Wholesale",
            "subcategory":"Construction Materials",
            "type":"Manufacturing & Wholesale Goods"
        }
    ],
    "sg:phone":"+1 902 865 1158",
    "sg:postcode":"B4B 1S1",
    "sg:province":"NS",
    "sg:tags":[
        "lumber"
    ],
    "wof:name":"Hefler Forest Products Ltd",
    "wof:placetype":"venue"
},
  "geometry": {"coordinates":[-63.7142906189,44.7766914368],"type":"Point"}
}