{
  "type": "Feature",
  "properties": {
    "addr:full":"81 Riverside Dr Corner Brook NL A2H 2N2",
    "addr:housenumber":"81",
    "addr:postcode":"a2h 2n2",
    "addr:street":"Riverside Dr",
    "iso:country":"CA",
    "sg:address":"81 Riverside Dr",
    "sg:city":"Corner Brook",
    "sg:classifiers":[
        {
            "category":"Wholesale",
            "subcategory":"Construction Materials",
            "type":"Manufacturing & Wholesale Goods"
        }
    ],
    "sg:phone":"+1 709 634 8251",
    "sg:postcode":"A2H 2N2",
    "sg:province":"NL",
    "sg:tags":[
        "cement"
    ],
    "wof:name":"St Lawrence Cement Inc",
    "wof:placetype":"venue"
},
  "geometry": {"coordinates":[-57.9430809021,48.956161499],"type":"Point"}
}