{
  "type": "Feature",
  "properties": {
    "addr:full":"3476 Glen Erin Dr Mississauga ON L5L 3R4",
    "addr:housenumber":"3476",
    "addr:postcode":"l5l 3r4",
    "addr:street":"Glen Erin Dr",
    "iso:country":"CA",
    "sg:address":"3476 Glen Erin Dr",
    "sg:city":"Mississauga",
    "sg:classifiers":[
        {
            "category":"Health Services",
            "subcategory":"Doctor",
            "type":"Services"
        }
    ],
    "sg:phone":"+1 905 820 4440",
    "sg:postcode":"L5L 3R4",
    "sg:province":"ON",
    "sg:tags":[
        "dentist"
    ],
    "wof:name":"Dally, Roba DDS",
    "wof:placetype":"venue"
},
  "geometry": {"coordinates":[-79.68841552729999,43.538482666],"type":"Point"}
}