{
  "type": "Feature",
  "properties": {
    "addr:full":"490 Ch Du Lac Boucherville QC J4B 6X3",
    "addr:housenumber":"490",
    "addr:postcode":"j4b 6x3",
    "addr:street":"Ch Du Lac",
    "iso:country":"CA",
    "sg:address":"490 Ch Du Lac",
    "sg:city":"Boucherville",
    "sg:classifiers":[
        {
            "category":"Shopping",
            "subcategory":"Bicycles & Sporting Goods",
            "type":"Retail Goods"
        }
    ],
    "sg:phone":"+1 450 655 4444",
    "sg:postcode":"J4B 6X3",
    "sg:province":"QC",
    "wof:name":"Suzan Gauthier Sports Enr",
    "wof:placetype":"venue"
},
  "geometry": {"coordinates":[-73.4474563599,45.6042442322],"type":"Point"}
}