{
  "type": "Feature",
  "properties": {
    "iso:country":"CA",
    "sg:address":"2354 Rue Jean-Talon E",
    "sg:city":"Montreal",
    "sg:classifiers":[
        {
            "category":"Shopping",
            "subcategory":"Optical Goods",
            "type":"Retail Goods"
        }
    ],
    "sg:phone":"+1 514 593 9899",
    "sg:postcode":"H2E 1V9",
    "sg:province":"QC",
    "sg:tags":[
        "optician"
    ],
    "wof:name":"Centre Visuel Iberville",
    "wof:placetype":"venue"
},
  "geometry": {"coordinates":[-73.602905,45.55249],"type":"Point"}
}