{
  "type": "Feature",
  "properties": {
    "addr:full":"585009 Beachville Rd Woodstock ON N4S 7V6",
    "addr:housenumber":"585009",
    "addr:postcode":"n4s 7v6",
    "addr:street":"Beachville Rd",
    "iso:country":"CA",
    "sg:address":"585009 Beachville Rd",
    "sg:city":"Woodstock",
    "sg:classifiers":[
        {
            "category":"Autos & Motor Vehicles",
            "subcategory":"Automobile Sales",
            "type":"Retail Goods"
        }
    ],
    "sg:phone":"+1 519 539 3933",
    "sg:postcode":"N4S 7V6",
    "sg:province":"ON",
    "sg:tags":[
        "polishing",
        "car",
        "washing"
    ],
    "wof:name":"John's Car Care",
    "wof:placetype":"venue"
},
  "geometry": {"coordinates":[-80.756561,43.130112],"type":"Point"}
}