{
  "type": "Feature",
  "properties": {
    "iso:country":"CA",
    "sg:address":"560 Denison St # 7",
    "sg:city":"Markham",
    "sg:classifiers":[
        {
            "category":"Autos & Motor Vehicles",
            "subcategory":"Auto Supplies",
            "type":"Retail Goods"
        }
    ],
    "sg:phone":"+1 905 475 5501",
    "sg:postcode":"L3R 2M8",
    "sg:province":"ON",
    "sg:tags":[
        "automobile",
        "parts"
    ],
    "wof:name":"Carquest",
    "wof:placetype":"venue"
},
  "geometry": {"coordinates":[-79.343033,43.823822],"type":"Point"}
}