{
  "type": "Feature",
  "properties": {
    "addr:full":"72 Doncaster Ave Thornhill ON L3T 1L3",
    "addr:housenumber":"72",
    "addr:postcode":"l3t 1l3",
    "addr:street":"Doncaster Ave",
    "iso:country":"CA",
    "sg:address":"72 Doncaster Ave",
    "sg:city":"Thornhill",
    "sg:classifiers":[
        {
            "category":"Retail",
            "subcategory":"Portrait Studio",
            "type":"Services"
        }
    ],
    "sg:phone":"+1 905 882 6770",
    "sg:postcode":"L3T 1L3",
    "sg:province":"ON",
    "sg:tags":[
        "photographer"
    ],
    "wof:name":"David Amoils Photography",
    "wof:placetype":"venue"
},
  "geometry": {"coordinates":[-79.415802,43.804253],"type":"Point"}
}