{
  "type": "Feature",
  "properties": {
    "addr:full":"5300 Maple St Vancouver BC V6M 3T6",
    "addr:housenumber":"5300",
    "addr:postcode":"v6m 3t6",
    "addr:street":"Maple St",
    "iso:country":"CA",
    "sg:address":"5300 Maple St",
    "sg:city":"Vancouver",
    "sg:classifiers":[
        {
            "category":"Education",
            "subcategory":"School",
            "type":"Public Place"
        }
    ],
    "sg:phone":"+1 604 713 5420",
    "sg:postcode":"V6M 3T6",
    "sg:province":"BC",
    "wof:name":"Quilchena Elementary",
    "wof:placetype":"venue"
},
  "geometry": {"coordinates":[-123.151748657,49.2382316589],"type":"Point"}
}