{
  "type": "Feature",
  "properties": {
    "addr:full":"1800 18th St N Brandon MB R7C 1A5",
    "addr:housenumber":"1800",
    "addr:postcode":"r7c 1a5",
    "addr:street":"18Th St N",
    "iso:country":"CA",
    "sg:address":"1800 18th St N",
    "sg:city":"Brandon",
    "sg:classifiers":[
        {
            "category":"Wholesale",
            "subcategory":"Farm Supplies",
            "type":"Manufacturing & Wholesale Goods"
        }
    ],
    "sg:phone":"+1 204 726 0601",
    "sg:postcode":"R7C 1A5",
    "sg:province":"MB",
    "sg:tags":[
        "equipment",
        "hydraulic"
    ],
    "wof:name":"Princess Auto Ltd",
    "wof:placetype":"venue"
},
  "geometry": {"coordinates":[-99.962097,49.878262],"type":"Point"}
}