{
  "type": "Feature",
  "properties": {
    "iso:country":"CA",
    "sg:address":"135 Macbeath Ave",
    "sg:city":"Moncton",
    "sg:classifiers":[
        {
            "category":"Shopping",
            "subcategory":"Florist",
            "type":"Retail Goods"
        }
    ],
    "sg:phone":"+1 506 857 3040",
    "sg:postcode":"E1C 6Z8",
    "sg:province":"NB",
    "wof:name":"Flower World",
    "wof:placetype":"venue"
},
  "geometry": {"coordinates":[-64.8060684204,46.104549408],"type":"Point"}
}