{
  "type": "Feature",
  "properties": {
    "addr:full":"9833 Keele St Maple ON L6A 1R6",
    "addr:housenumber":"9833",
    "addr:postcode":"l6a 1r6",
    "addr:street":"Keele St",
    "iso:country":"CA",
    "sg:address":"9833 Keele St",
    "sg:city":"Maple",
    "sg:classifiers":[
        {
            "category":"Retail",
            "subcategory":"Laundry & Dry Cleaning",
            "type":"Services"
        }
    ],
    "sg:phone":"+1 905 417 0305",
    "sg:postcode":"L6A 1R6",
    "sg:province":"ON",
    "sg:tags":[
        "cleaners"
    ],
    "wof:name":"St Andrews Cleaners",
    "wof:placetype":"venue"
},
  "geometry": {"coordinates":[-79.51123809809999,43.8507003784],"type":"Point"}
}