{
  "type": "Feature",
  "properties": {
    "addr:full":"1572 Third Ave St Catharines ON L2R 6P9",
    "addr:housenumber":"1572",
    "addr:postcode":"l2r 6p9",
    "addr:street":"Third Ave",
    "iso:country":"CA",
    "sg:address":"1572 Third Ave",
    "sg:city":"St Catharines",
    "sg:classifiers":[
        {
            "category":"Food & Beverages",
            "subcategory":"Specialty",
            "type":"Retail Goods"
        }
    ],
    "sg:phone":"+1 905 984 3366",
    "sg:postcode":"L2R 6P9",
    "sg:province":"ON",
    "sg:tags":[
        "health",
        "diet"
    ],
    "wof:name":"Super Tech Systems",
    "wof:placetype":"venue"
},
  "geometry": {"coordinates":[-79.2872085571,43.1708526611],"type":"Point"}
}