{
  "type": "Feature",
  "properties": {
    "addr:full":"204 Princess St Kingston ON K7L 1B2",
    "addr:housenumber":"204",
    "addr:postcode":"k7l 1b2",
    "addr:street":"Princess St",
    "iso:country":"CA",
    "sg:address":"204 Princess St",
    "sg:city":"Kingston",
    "sg:classifiers":[
        {
            "category":"Real Estate",
            "subcategory":"Real Estate Operator",
            "type":"Services"
        }
    ],
    "sg:phone":"+1 613 548 7919",
    "sg:postcode":"K7L 1B2",
    "sg:province":"ON",
    "sg:tags":[
        "apartment"
    ],
    "wof:name":"Harford Apartments",
    "wof:placetype":"venue"
},
  "geometry": {"coordinates":[-76.485992,44.231941],"type":"Point"}
}