{
  "type": "Feature",
  "properties": {
    "addr:full":"203 Broadway St W Nakusp BC V0G 1R0",
    "addr:housenumber":"203",
    "addr:postcode":"v0g 1r0",
    "addr:street":"Broadway St W",
    "iso:country":"CA",
    "sg:address":"203 Broadway St W",
    "sg:city":"Nakusp",
    "sg:classifiers":[
        {
            "category":"Home & Garden",
            "subcategory":"Building Materials",
            "type":"Retail Goods"
        }
    ],
    "sg:phone":"+1 250 265 3252",
    "sg:postcode":"V0G 1R0",
    "sg:province":"BC",
    "sg:tags":[
        "glass",
        "window",
        "plate"
    ],
    "wof:name":"Nakusp Glass",
    "wof:placetype":"venue"
},
  "geometry": {"coordinates":[-117.800179,50.238762],"type":"Point"}
}