{
  "type": "Feature",
  "properties": {
    "iso:country":"CA",
    "sg:address":"10 Rooksnest Trail",
    "sg:city":"Scarborough",
    "sg:classifiers":[
        {
            "category":"Autos & Motor Vehicles",
            "subcategory":"Auto Supplies",
            "type":"Retail Goods"
        }
    ],
    "sg:phone":"+1 416 321 5507",
    "sg:postcode":"M1S 3W2",
    "sg:province":"ON",
    "sg:tags":[
        "equipment",
        "air",
        "conditioning",
        "automobile"
    ],
    "wof:name":"Tops Mobile Auto Air",
    "wof:placetype":"venue"
},
  "geometry": {"coordinates":[-79.2624588013,43.801071167],"type":"Point"}
}