{
  "type": "Feature",
  "properties": {
    "iso:country":"CA",
    "sg:address":"6140 Boul Sainte-Anne",
    "sg:city":"L'Ange Gardien",
    "sg:classifiers":[
        {
            "category":"Real Estate",
            "subcategory":"Real Estate Agent",
            "type":"Services"
        }
    ],
    "sg:phone":"+1 418 822 0543",
    "sg:postcode":"G0A 2K0",
    "sg:province":"QC",
    "sg:tags":[
        "management",
        "contractor"
    ],
    "wof:name":"Macyro Group Inc",
    "wof:placetype":"venue"
},
  "geometry": {"coordinates":[-72.9380264282,45.357460022],"type":"Point"}
}