{
  "type": "Feature",
  "properties": {
    "addr:full":"2149 25th Ave Bowden AB T0M 0K0",
    "addr:housenumber":"2149",
    "addr:postcode":"t0m 0k0",
    "addr:street":"25Th Ave",
    "iso:country":"CA",
    "sg:address":"2149 25th Ave",
    "sg:city":"Bowden",
    "sg:classifiers":[
        {
            "category":"Wholesale",
            "subcategory":"Non-durable Goods",
            "type":"Manufacturing & Wholesale Goods"
        }
    ],
    "sg:phone":"+1 403 224 2454",
    "sg:postcode":"T0M 0K0",
    "sg:province":"AB",
    "sg:tags":[
        "advertising"
    ],
    "wof:name":"G & D Promotions",
    "wof:placetype":"venue"
},
  "geometry": {"coordinates":[-114.034447,51.936642],"type":"Point"}
}