{
  "type": "Feature",
  "properties": {
    "iso:country":"CA",
    "sg:city":"Kamloops",
    "sg:classifiers":[
        {
            "category":"Shopping",
            "type":"Retail Goods"
        }
    ],
    "sg:phone":"+1 250 851 3638",
    "sg:postcode":"V2C 6T6",
    "sg:province":"BC",
    "sg:tags":[
        "picture",
        "frame"
    ],
    "wof:name":"Access Picture Framing",
    "wof:placetype":"venue"
},
  "geometry": {"coordinates":[-120.349052429,50.6628952026],"type":"Point"}
}