{
  "type": "Feature",
  "properties": {
    "addr:full":"4236 Hwy 14 Windsor NS B0N 2T0",
    "addr:housenumber":"4236",
    "addr:postcode":"b0n 2t0",
    "addr:street":"Hwy 14",
    "iso:country":"CA",
    "sg:address":"4236 Hwy 14",
    "sg:city":"Windsor",
    "sg:classifiers":[
        {
            "category":"Shopping",
            "subcategory":"Used Merchandise",
            "type":"Retail Goods"
        }
    ],
    "sg:phone":"+1 902 798 0003",
    "sg:postcode":"B0N 2T0",
    "sg:province":"NS",
    "sg:tags":[
        "furniture"
    ],
    "wof:name":"Foley Traders Main Store",
    "wof:placetype":"venue"
},
  "geometry": {"coordinates":[-64.143967,44.967953],"type":"Point"}
}