{
  "type": "Feature",
  "properties": {
    "addr:full":"6671 Rue Saint-Denis Montreal QC H2S 2S1",
    "addr:housenumber":"6671",
    "addr:postcode":"h2s 2s1",
    "addr:street":"Rue Saint-Denis",
    "iso:country":"CA",
    "sg:address":"6671 Rue Saint-Denis",
    "sg:city":"Montreal",
    "sg:classifiers":[
        {
            "category":"Shopping",
            "subcategory":"Gifts & Souvenirs",
            "type":"Retail Goods"
        }
    ],
    "sg:phone":"+1 514 744 0411",
    "sg:postcode":"H2S 2S1",
    "sg:province":"QC",
    "sg:tags":[
        "party",
        "supply"
    ],
    "wof:name":"Daniele Normand Inc",
    "wof:placetype":"venue"
},
  "geometry": {"coordinates":[-73.60760500000001,45.535339],"type":"Point"}
}