{
  "type": "Feature",
  "properties": {
    "addr:full":"57 Av Roberval Roberval QC G8H 1G9",
    "addr:postcode":"g8h 1g9",
    "addr:street":"57 Av Roberval",
    "iso:country":"CA",
    "sg:address":"57 Av Roberval",
    "sg:city":"Roberval",
    "sg:classifiers":[
        {
            "category":"Health Services",
            "subcategory":"Doctor",
            "type":"Services"
        }
    ],
    "sg:phone":"+1 418 275 3833",
    "sg:postcode":"G8H 1G9",
    "sg:province":"QC",
    "sg:tags":[
        "physician",
        "clinic",
        "surgeon"
    ],
    "wof:name":"Clinique Medicale DE Robvl Enr",
    "wof:placetype":"venue"
},
  "geometry": {"coordinates":[-72.222328186,48.5151977539],"type":"Point"}
}