{
  "type": "Feature",
  "properties": {
    "addr:full":"Calgary AB T2R 1J4",
    "addr:postcode":"t2r 1j4",
    "iso:country":"CA",
    "sg:city":"Calgary",
    "sg:classifiers":[
        {
            "category":"Professional",
            "subcategory":"Employment Agencies",
            "type":"Services"
        }
    ],
    "sg:phone":"+1 403 232 1333",
    "sg:postcode":"T2R 1J4",
    "sg:province":"AB",
    "sg:tags":[
        "consultant",
        "opportunity",
        "personnel"
    ],
    "wof:name":"Questus Recruitment Corp",
    "wof:placetype":"venue"
},
  "geometry": {"coordinates":[-114.07155609100001,51.043056488],"type":"Point"}
}