{
  "type": "Feature",
  "properties": {
    "addr:full":"900 Greenbank Rd Nepean ON K2J 1S8",
    "addr:housenumber":"900",
    "addr:postcode":"k2j 1s8",
    "addr:street":"Greenbank Rd",
    "iso:country":"CA",
    "sg:address":"900 Greenbank Rd",
    "sg:city":"Nepean",
    "sg:classifiers":[
        {
            "category":"Professional",
            "subcategory":"Computer Services",
            "type":"Services"
        }
    ],
    "sg:phone":"+1 613 843 9358",
    "sg:postcode":"K2J 1S8",
    "sg:province":"ON",
    "sg:tags":[
        "internet"
    ],
    "wof:name":"Nebularis Information Systems",
    "wof:placetype":"venue"
},
  "geometry": {"coordinates":[-75.755355835,45.2848625183],"type":"Point"}
}