{
  "type": "Feature",
  "properties": {
    "iso:country":"CA",
    "sg:city":"Whitby",
    "sg:classifiers":[
        {
            "category":"Retail",
            "subcategory":"Auto Repair",
            "type":"Services"
        }
    ],
    "sg:phone":"+1 905 666 2885",
    "sg:postcode":"L1N 6A6",
    "sg:province":"ON",
    "sg:tags":[
        "repairing",
        "automobile"
    ],
    "wof:name":"G N Auto Svc",
    "wof:placetype":"venue"
},
  "geometry": {"coordinates":[-78.92446136469999,43.8738822937],"type":"Point"}
}