{
  "type": "Feature",
  "properties": {
    "addr:full":"Christina Lake BC V0H 1E3",
    "addr:postcode":"bc v0h 1e3",
    "iso:country":"CA",
    "sg:city":"Christina Lake",
    "sg:classifiers":[
        {
            "category":"Travel",
            "subcategory":"Hotels & Motels",
            "type":"Entertainment"
        }
    ],
    "sg:phone":"+1 250 447 9358",
    "sg:postcode":"V0H 1E3",
    "sg:province":"BC",
    "wof:name":"Lakeview Motel",
    "wof:placetype":"venue"
},
  "geometry": {"coordinates":[-118.220458984,49.0230064392],"type":"Point"}
}