{
  "type": "Feature",
  "properties": {
    "addr:full":"1276 Boul Des Seigneurs Terrebonne QC J6W 4Z1",
    "addr:housenumber":"1276",
    "addr:postcode":"j6w 4z1",
    "addr:street":"Boul Des Seigneurs",
    "iso:country":"CA",
    "sg:address":"1276 Boul Des Seigneurs",
    "sg:city":"Terrebonne",
    "sg:classifiers":[
        {
            "category":"Restaurant",
            "type":"Food & Drink"
        }
    ],
    "sg:phone":"+1 450 492 4000",
    "sg:postcode":"J6W 4Z1",
    "sg:province":"QC",
    "wof:name":"Surprise Pizza",
    "wof:placetype":"venue"
},
  "geometry": {"coordinates":[-73.65467099999999,45.699413],"type":"Point"}
}