{
  "type": "Feature",
  "properties": {
    "iso:country":"CA",
    "sg:address":"1276 Boul Des Seigneurs",
    "sg:city":"Terrebonne",
    "sg:classifiers":[
        {
            "category":"Restaurant",
            "type":"Food & Drink"
        }
    ],
    "sg:phone":"+1 450 492 4000",
    "sg:postcode":"J6W 4Z1",
    "sg:province":"QC",
    "wof:name":"Surprise Pizza",
    "wof:placetype":"venue"
},
  "geometry": {"coordinates":[-73.654671,45.699413],"type":"Point"}
}