{
  "type": "Feature",
  "properties": {
    "addr:full":"Sherbrooke QC J1H 1M3",
    "addr:postcode":"j1h 1m3",
    "iso:country":"CA",
    "sg:city":"Sherbrooke",
    "sg:classifiers":[
        {
            "category":"Professional",
            "subcategory":"Business Services",
            "type":"Services"
        }
    ],
    "sg:phone":"+1 819 566 4881",
    "sg:postcode":"J1H 1M3",
    "sg:province":"QC",
    "sg:tags":[
        "estate"
    ],
    "wof:name":"Samson, Charron",
    "wof:placetype":"venue"
},
  "geometry": {"coordinates":[-71.8948440552,45.4014396667],"type":"Point"}
}