{
  "type": "Feature",
  "properties": {
    "addr:full":"82 Lucerne Dr Kitchener ON N2E 1B3",
    "addr:housenumber":"82",
    "addr:postcode":"n2e 1b3",
    "addr:street":"Lucerne Dr",
    "iso:country":"CA",
    "sg:address":"82 Lucerne Dr",
    "sg:city":"Kitchener",
    "sg:classifiers":[
        {
            "category":"Freight",
            "type":"Transportation"
        }
    ],
    "sg:phone":"+1 519 579 1800",
    "sg:postcode":"N2E 1B3",
    "sg:province":"ON",
    "sg:tags":[
        "mover"
    ],
    "wof:name":"Evergreen Transfer Moving Svc",
    "wof:placetype":"venue"
},
  "geometry": {"coordinates":[-80.483299,43.420055],"type":"Point"}
}