{
  "type": "Feature",
  "properties": {
    "addr:full":"600 Centennial St Winkler MB R6W 4A4",
    "addr:housenumber":"600",
    "addr:postcode":"r6w 4a4",
    "addr:street":"Centennial St",
    "iso:country":"CA",
    "sg:address":"600 Centennial St",
    "sg:city":"Winkler",
    "sg:classifiers":[
        {
            "category":"Home & Garden",
            "subcategory":"Building Materials",
            "type":"Retail Goods"
        }
    ],
    "sg:phone":"+1 204 325 8387",
    "sg:postcode":"R6W 4A4",
    "sg:province":"MB",
    "sg:tags":[
        "wallpaper"
    ],
    "wof:name":"Janzen's Hobby Land",
    "wof:placetype":"venue"
},
  "geometry": {"coordinates":[-97.9341583252,49.1876525879],"type":"Point"}
}