{
  "type": "Feature",
  "properties": {
    "addr:full":"367 the Country Way Kitchener ON N2E 2S3",
    "addr:housenumber":"367",
    "addr:postcode":"n2e 2s3",
    "addr:street":"The Country Way",
    "iso:country":"CA",
    "sg:address":"367 the Country Way",
    "sg:city":"Kitchener",
    "sg:classifiers":[
        {
            "category":"Education",
            "subcategory":"School",
            "type":"Public Place"
        }
    ],
    "sg:phone":"+1 519 745 5950",
    "sg:postcode":"N2E 2S3",
    "sg:province":"ON",
    "wof:name":"Blessed Sacrament School",
    "wof:placetype":"venue"
},
  "geometry": {"coordinates":[-80.48378,43.406651],"type":"Point"}
}