{
  "type": "Feature",
  "properties": {
    "addr:full":"121 Main St Shelburne ON L0N 1S0",
    "addr:housenumber":"121",
    "addr:postcode":"l0n 1s0",
    "addr:street":"Main St",
    "iso:country":"CA",
    "sg:address":"121 Main St",
    "sg:city":"Shelburne",
    "sg:classifiers":[
        {
            "category":"Shopping",
            "subcategory":"Computers & Home Electronics",
            "type":"Retail Goods"
        }
    ],
    "sg:phone":"+1 519 986 1253",
    "sg:postcode":"L0N 1S0",
    "sg:province":"ON",
    "sg:tags":[
        "equipment",
        "satellite",
        "system"
    ],
    "wof:name":"Stewart Satellite & Tv Inc",
    "wof:placetype":"venue"
},
  "geometry": {"coordinates":[-80.2037277222,44.0783348083],"type":"Point"}
}