{
  "type": "Feature",
  "properties": {
    "iso:country":"CA",
    "sg:address":"1021 Coupland Rd",
    "sg:city":"Sydenham",
    "sg:classifiers":[
        {
            "category":"Professional",
            "subcategory":"Engineering",
            "type":"Services"
        }
    ],
    "sg:phone":"+1 613 376 3329",
    "sg:postcode":"K0H 2T0",
    "sg:province":"ON",
    "sg:tags":[
        "engineer"
    ],
    "wof:name":"Mitchell Pound & Braddock Ltd",
    "wof:placetype":"venue"
},
  "geometry": {"coordinates":[-76.5965805054,44.4086112976],"type":"Point"}
}