{
  "type": "Feature",
  "properties": {
    "addr:full":"1 Marshall Crt Stephenville NL A2N 2Z8",
    "addr:housenumber":"1",
    "addr:postcode":"a2n 2z8",
    "addr:street":"Marshall Crt",
    "iso:country":"CA",
    "sg:address":"1 Marshall Crt",
    "sg:city":"Stephenville",
    "sg:classifiers":[
        {
            "category":"Organizations",
            "subcategory":"Professional Association",
            "type":"Services"
        }
    ],
    "sg:phone":"+1 709 643 6612",
    "sg:postcode":"A2N 2Z8",
    "sg:province":"NL",
    "wof:name":"Circle of Friends Tennants",
    "wof:placetype":"venue"
},
  "geometry": {"coordinates":[-58.584667,48.548855],"type":"Point"}
}