{
  "type": "Feature",
  "properties": {
    "iso:country":"CA",
    "sg:city":"Aurora",
    "sg:classifiers":[
        {
            "category":"Freight",
            "type":"Transportation"
        }
    ],
    "sg:phone":"+1 905 841 8111",
    "sg:postcode":"L4G 1H5",
    "sg:province":"ON",
    "wof:name":"Fleetwood Freight Consultants",
    "wof:placetype":"venue"
},
  "geometry": {"coordinates":[-79.4667053223,43.9999732971],"type":"Point"}
}