{
  "type": "Feature",
  "properties": {
    "addr:full":"17 Oakland Ave North York ON M9M 2H9",
    "addr:housenumber":"17",
    "addr:postcode":"m9m 2h9",
    "addr:street":"Oakland Ave",
    "iso:country":"CA",
    "sg:address":"17 Oakland Ave",
    "sg:city":"North York",
    "sg:classifiers":[
        {
            "category":"Building & Trades",
            "subcategory":"Construction",
            "type":"Services"
        }
    ],
    "sg:phone":"+1 416 741 2999",
    "sg:postcode":"M9M 2H9",
    "sg:province":"ON",
    "sg:tags":[
        "bridge",
        "builder"
    ],
    "wof:name":"Anscon Contracting Inc",
    "wof:placetype":"venue"
},
  "geometry": {"coordinates":[-79.52653503419999,43.7173347473],"type":"Point"}
}