{
  "type": "Feature",
  "properties": {
    "addr:full":"993 Rue Bagot LA Baie QC G7B 2N6",
    "addr:housenumber":"993",
    "addr:postcode":"g7b 2n6",
    "addr:street":"Rue Bagot",
    "iso:country":"CA",
    "sg:address":"993 Rue Bagot",
    "sg:city":"LA Baie",
    "sg:classifiers":[
        {
            "category":"Government",
            "subcategory":"Office",
            "type":"Public Place"
        }
    ],
    "sg:phone":"+1 418 544 3378",
    "sg:postcode":"G7B 2N6",
    "sg:province":"QC",
    "wof:name":"Quebec Centres Travail",
    "wof:placetype":"venue"
},
  "geometry": {"coordinates":[-70.88145400000001,48.338272],"type":"Point"}
}