{
  "type": "Feature",
  "properties": {
    "iso:country":"CA",
    "sg:address":"993 Rue Bagot",
    "sg:city":"LA Baie",
    "sg:classifiers":[
        {
            "category":"Government",
            "subcategory":"Office",
            "type":"Public Place"
        }
    ],
    "sg:phone":"+1 418 544 3378",
    "sg:postcode":"G7B 2N6",
    "sg:province":"QC",
    "wof:name":"Quebec Centres Travail",
    "wof:placetype":"venue"
},
  "geometry": {"coordinates":[-70.881454,48.338272],"type":"Point"}
}