{
  "type": "Feature",
  "properties": {
    "addr:full":"Lloydminster AB T9V 0M1",
    "addr:postcode":"t9v 0m1",
    "iso:country":"CA",
    "sg:city":"Lloydminster",
    "sg:classifiers":[
        {
            "category":"Shopping",
            "subcategory":"Clothing, Apparel, & Fashions",
            "type":"Retail Goods"
        }
    ],
    "sg:phone":"+1 780 875 6597",
    "sg:postcode":"T9V 0M1",
    "sg:province":"AB",
    "sg:tags":[
        "shoes"
    ],
    "wof:name":"Feminine Flare By Phylliss Ltd",
    "wof:placetype":"venue"
},
  "geometry": {"coordinates":[-110.005928,53.283676],"type":"Point"}
}