{
  "type": "Feature",
  "properties": {
    "addr:full":"11 132 Rte Shigawake QC G0C 3E0",
    "addr:housenumber":"132",
    "addr:postcode":"g0c 3e0",
    "addr:street":"11;Rte Shigawake",
    "iso:country":"CA",
    "sg:address":"11 132 Rte",
    "sg:city":"Shigawake",
    "sg:classifiers":[
        {
            "category":"Manufacturing",
            "subcategory":"Food",
            "type":"Manufacturing & Wholesale Goods"
        }
    ],
    "sg:phone":"+1 418 752 3524",
    "sg:postcode":"G0C 3E0",
    "sg:province":"QC",
    "sg:tags":[
        "product",
        "seafood",
        "fish",
        "prepared"
    ],
    "wof:name":"Assels Seafoods Inc",
    "wof:placetype":"venue"
},
  "geometry": {"coordinates":[-65.08257293699999,48.0928039551],"type":"Point"}
}