{
  "type": "Feature",
  "properties": {
    "addr:full":"Bedford Charlottetown PE C1A 6W4",
    "addr:postcode":"c1a 6w4",
    "addr:street":"Bedford",
    "iso:country":"CA",
    "sg:address":"Bedford",
    "sg:city":"Charlottetown",
    "sg:classifiers":[
        {
            "category":"Retail",
            "subcategory":"Portrait Studio",
            "type":"Services"
        }
    ],
    "sg:phone":"+1 902 892 2232",
    "sg:postcode":"C1A 6W4",
    "sg:province":"PE",
    "sg:tags":[
        "jeweler"
    ],
    "wof:name":"Jostens Canada Ltd",
    "wof:placetype":"venue"
},
  "geometry": {"coordinates":[-63.12817,46.236591],"type":"Point"}
}