{
  "type": "Feature",
  "properties": {
    "addr:full":"330 Bay St Toronto ON M5H 2S8",
    "addr:housenumber":"330",
    "addr:postcode":"m5h 2s8",
    "addr:street":"Bay St",
    "iso:country":"CA",
    "sg:address":"330 Bay St",
    "sg:city":"Toronto",
    "sg:classifiers":[
        {
            "category":"Professional",
            "subcategory":"Management & Consulting",
            "type":"Services"
        }
    ],
    "sg:phone":"+1 416 368 7867",
    "sg:postcode":"M5H 2S8",
    "sg:province":"ON",
    "sg:tags":[
        "consultant",
        "business"
    ],
    "wof:name":"Rfh & Assoc",
    "wof:placetype":"venue"
},
  "geometry": {"coordinates":[-79.38106536870001,43.6500816345],"type":"Point"}
}