{
  "type": "Feature",
  "properties": {
    "addr:full":"540 Rte Begin Saint-Anselme QC G0R 2N0",
    "addr:housenumber":"540",
    "addr:postcode":"g0r 2n0",
    "addr:street":"Rte Begin",
    "iso:country":"CA",
    "sg:address":"540 Rte Begin",
    "sg:city":"Saint-Anselme",
    "sg:classifiers":[
        {
            "category":"Travel",
            "subcategory":"Hotels & Motels",
            "type":"Entertainment"
        }
    ],
    "sg:phone":"+1 418 885 4533",
    "sg:postcode":"G0R 2N0",
    "sg:province":"QC",
    "sg:tags":[
        "breakfast",
        "accommodation",
        "bed"
    ],
    "wof:name":"Douces Evasions Gabrielle Corr",
    "wof:placetype":"venue"
},
  "geometry": {"coordinates":[-70.98481,46.637383],"type":"Point"}
}