{
  "type": "Feature",
  "properties": {
    "addr:full":"863 Main St E Milton ON L9T 3Z3",
    "addr:housenumber":"863",
    "addr:postcode":"l9t 3z3",
    "addr:street":"Main St E",
    "iso:country":"CA",
    "sg:address":"863 Main St E",
    "sg:city":"Milton",
    "sg:classifiers":[
        {
            "category":"Freight",
            "type":"Transportation"
        }
    ],
    "sg:phone":"+1 905 821 1010",
    "sg:postcode":"L9T 3Z3",
    "sg:province":"ON",
    "sg:tags":[
        "mover"
    ],
    "wof:name":"Atlas Scannell Moving & Stge",
    "wof:placetype":"venue"
},
  "geometry": {"coordinates":[-79.869675,43.525818],"type":"Point"}
}