{
  "type": "Feature",
  "properties": {
    "iso:country":"CA",
    "sg:address":"338 Sherwood Rd",
    "sg:city":"Regina",
    "sg:classifiers":[
        {
            "category":"Building & Trades",
            "subcategory":"Construction",
            "type":"Services"
        }
    ],
    "sg:phone":"+1 306 545 7155",
    "sg:postcode":"S4P 3R9",
    "sg:province":"SK",
    "sg:tags":[
        "paving",
        "contractor"
    ],
    "wof:name":"Pasqua Paving",
    "wof:placetype":"venue"
},
  "geometry": {"coordinates":[-104.632637024,50.475528717],"type":"Point"}
}