{
  "type": "Feature",
  "properties": {
    "iso:country":"CA",
    "sg:address":"473 Basaltic Rd",
    "sg:city":"Concord",
    "sg:classifiers":[
        {
            "category":"Freight",
            "type":"Transportation"
        }
    ],
    "sg:phone":"+1 905 303 7725",
    "sg:postcode":"L4K 4W8",
    "sg:province":"ON",
    "sg:tags":[
        "courier"
    ],
    "wof:name":"Canpar",
    "wof:placetype":"venue"
},
  "geometry": {"coordinates":[-79.4992675781,43.8323707581],"type":"Point"}
}