{
  "type": "Feature",
  "properties": {
    "addr:full":"19 Memorial Blvd Dauphin MB R7N 2A5",
    "addr:housenumber":"19",
    "addr:postcode":"r7n 2a5",
    "addr:street":"Memorial Blvd",
    "iso:country":"CA",
    "sg:address":"19 Memorial Blvd",
    "sg:city":"Dauphin",
    "sg:classifiers":[
        {
            "category":"Restaurant",
            "type":"Food & Drink"
        }
    ],
    "sg:phone":"+1 204 638 6080",
    "sg:postcode":"R7N 2A5",
    "sg:province":"MB",
    "wof:name":"Thunder's Country Restaurant",
    "wof:placetype":"venue"
},
  "geometry": {"coordinates":[-100.051331,51.147797],"type":"Point"}
}