{
  "type": "Feature",
  "properties": {
    "addr:full":"600 Northmount Dr NW Calgary AB T2K 3J5",
    "addr:housenumber":"600",
    "addr:postcode":"t2k 3j5",
    "addr:street":"Northmount Dr Nw",
    "iso:country":"CA",
    "sg:address":"600 Northmount Dr NW",
    "sg:city":"Calgary",
    "sg:classifiers":[
        {
            "category":"Education",
            "subcategory":"School",
            "type":"Public Place"
        }
    ],
    "sg:phone":"+1 403 282 4220",
    "sg:postcode":"T2K 3J5",
    "sg:province":"AB",
    "wof:name":"Edelweiss Preparatory School",
    "wof:placetype":"venue"
},
  "geometry": {"coordinates":[-114.087456,51.087017],"type":"Point"}
}