{
  "type": "Feature",
  "properties": {
    "iso:country":"CA",
    "sg:city":"Victoria",
    "sg:classifiers":[
        {
            "category":"Shopping",
            "subcategory":"Clothing, Apparel, & Fashions",
            "type":"Retail Goods"
        }
    ],
    "sg:phone":"+1 250 382 5459",
    "sg:postcode":"V8W 1M2",
    "sg:province":"BC",
    "sg:tags":[
        "item",
        "boutique"
    ],
    "wof:name":"Smoking Lily",
    "wof:placetype":"venue"
},
  "geometry": {"coordinates":[-123.36833190900001,48.4274482727],"type":"Point"}
}