{
  "type": "Feature",
  "properties": {
    "addr:full":"9005 Shaughnessy St Vancouver BC V6P 6R9",
    "addr:housenumber":"9005",
    "addr:postcode":"v6p 6r9",
    "addr:street":"Shaughnessy St",
    "iso:country":"CA",
    "sg:address":"9005 Shaughnessy St",
    "sg:city":"Vancouver",
    "sg:classifiers":[
        {
            "category":"Manufacturing",
            "subcategory":"Food",
            "type":"Manufacturing & Wholesale Goods"
        }
    ],
    "sg:phone":"+1 604 322 1030",
    "sg:postcode":"V6P 6R9",
    "sg:province":"BC",
    "sg:tags":[
        "grocer",
        "product",
        "manufacturer"
    ],
    "wof:name":"Me'n Yooz Incredible Foodz",
    "wof:placetype":"venue"
},
  "geometry": {"coordinates":[-123.127685547,49.2034568787],"type":"Point"}
}