{
  "type": "Feature",
  "properties": {
    "addr:full":"290 7E Rue Shawinigan QC G9N 1C4",
    "addr:housenumber":"290",
    "addr:postcode":"g9n 1c4",
    "addr:street":"7E Rue",
    "iso:country":"CA",
    "sg:address":"290 7E Rue",
    "sg:city":"Shawinigan",
    "sg:classifiers":[
        {
            "category":"Retail",
            "subcategory":"Funeral Services",
            "type":"Services"
        }
    ],
    "sg:phone":"+1 819 537 7221",
    "sg:postcode":"G9N 1C4",
    "sg:province":"QC",
    "sg:tags":[
        "director"
    ],
    "wof:name":"Pellerin Complexe Funeraire",
    "wof:placetype":"venue"
},
  "geometry": {"coordinates":[-72.7460861206,46.5421981812],"type":"Point"}
}