{
  "type": "Feature",
  "properties": {
    "addr:full":"12 Bridge St Lakefield ON K0L 2H0",
    "addr:housenumber":"12",
    "addr:postcode":"k0l 2h0",
    "addr:street":"Bridge St",
    "iso:country":"CA",
    "sg:address":"12 Bridge St",
    "sg:city":"Lakefield",
    "sg:classifiers":[
        {
            "category":"Shopping",
            "type":"Retail Goods"
        }
    ],
    "sg:phone":"+1 705 652 8282",
    "sg:postcode":"K0L 2H0",
    "sg:province":"ON",
    "sg:tags":[
        "equipment",
        "wine",
        "supply"
    ],
    "wof:name":"Wine Connection",
    "wof:placetype":"venue"
},
  "geometry": {"coordinates":[-78.272942,44.422588],"type":"Point"}
}