{
  "type": "Feature",
  "properties": {
    "addr:full":"Hope BC V0X 1L0",
    "addr:postcode":"v0x 1l0",
    "iso:country":"CA",
    "sg:city":"Hope",
    "sg:classifiers":[
        {
            "category":"Social Services",
            "type":"Services"
        }
    ],
    "sg:phone":"+1 604 869 3201",
    "sg:postcode":"V0X 1L0",
    "sg:province":"BC",
    "sg:tags":[
        "counselor"
    ],
    "wof:name":"Ann Davis Svc",
    "wof:placetype":"venue"
},
  "geometry": {"coordinates":[-121.444519,49.378929],"type":"Point"}
}