{
  "type": "Feature",
  "properties": {
    "iso:country":"CA",
    "sg:address":"11889 Av Ethier",
    "sg:city":"Montreal-Nord",
    "sg:classifiers":[
        {
            "category":"Manufacturing",
            "subcategory":"Printing",
            "type":"Manufacturing & Wholesale Goods"
        }
    ],
    "sg:phone":"+1 514 322 8676",
    "sg:postcode":"H1H 3H5",
    "sg:province":"QC",
    "sg:tags":[
        "printer"
    ],
    "wof:name":"Imprimerie Omni Inc",
    "wof:placetype":"venue"
},
  "geometry": {"coordinates":[-73.639137,45.603642],"type":"Point"}
}