{
  "type": "Feature",
  "properties": {
    "addr:full":"402 Rue DE Guyenne Laval QC H7N 4A3",
    "addr:housenumber":"402",
    "addr:postcode":"h7n 4a3",
    "addr:street":"Rue De Guyenne",
    "iso:country":"CA",
    "sg:address":"402 Rue DE Guyenne",
    "sg:city":"Laval",
    "sg:classifiers":[
        {
            "category":"Professional",
            "subcategory":"Computer Services",
            "type":"Services"
        }
    ],
    "sg:phone":"+1 450 629 2776",
    "sg:postcode":"H7N 4A3",
    "sg:province":"QC",
    "sg:tags":[
        "consultant"
    ],
    "wof:name":"Programmation Ultra",
    "wof:placetype":"venue"
},
  "geometry": {"coordinates":[-73.703323,45.559566],"type":"Point"}
}