{
  "type": "Feature",
  "properties": {
    "addr:full":"St Isidore ON K0C 2B0",
    "addr:postcode":"k0c 2b0",
    "addr:street":"St Isidore",
    "iso:country":"CA",
    "sg:city":"St Isidore",
    "sg:classifiers":[
        {
            "category":"Government",
            "subcategory":"Fire Station",
            "type":"Public Place"
        }
    ],
    "sg:phone":"+1 613 524 5787",
    "sg:postcode":"K0C 2B0",
    "sg:province":"ON",
    "sg:tags":[
        "department"
    ],
    "wof:name":"St Isidore Nation",
    "wof:placetype":"venue"
},
  "geometry": {"coordinates":[-74.9058303833,45.3857307434],"type":"Point"}
}