{
  "type": "Feature",
  "properties": {
    "addr:full":"Saint-Pie QC J0H 1W0",
    "addr:postcode":"j0h 1w0",
    "iso:country":"CA",
    "sg:city":"Saint-Pie",
    "sg:classifiers":[
        {
            "category":"Banks & Credit Unions",
            "subcategory":"Investment Brokerage",
            "type":"Services"
        }
    ],
    "sg:phone":"+1 450 773 7467",
    "sg:postcode":"J0H 1W0",
    "sg:province":"QC",
    "sg:tags":[
        "consultant",
        "planning",
        "financial"
    ],
    "wof:name":"Services Financiers Duchesneau",
    "wof:placetype":"venue"
},
  "geometry": {"coordinates":[-72.96301269529999,45.5490150452],"type":"Point"}
}