{
  "type": "Feature",
  "properties": {
    "addr:full":"1000 Boul Des Cascades O Alma QC G8B 3G4",
    "addr:housenumber":"1000",
    "addr:postcode":"g8b 3g4",
    "addr:street":"Boul Des Cascades O",
    "iso:country":"CA",
    "sg:address":"1000 Boul Des Cascades O",
    "sg:city":"Alma",
    "sg:classifiers":[
        {
            "category":"Travel",
            "subcategory":"Hotels & Motels",
            "type":"Entertainment"
        }
    ],
    "sg:phone":"+1 418 668 5261",
    "sg:postcode":"G8B 3G4",
    "sg:province":"QC",
    "wof:name":"Hotel Motel Universel",
    "wof:placetype":"venue"
},
  "geometry": {"coordinates":[-71.65268707280001,48.5516891479],"type":"Point"}
}