{
  "type": "Feature",
  "properties": {
    "addr:full":"2107 16 Ave NW Calgary AB T2M 0M3",
    "addr:housenumber":"2107",
    "addr:postcode":"t2m 0m3",
    "addr:street":"16 Ave Nw",
    "iso:country":"CA",
    "sg:address":"2107 16 Ave NW",
    "sg:city":"Calgary",
    "sg:classifiers":[
        {
            "category":"Travel",
            "subcategory":"Hotels & Motels",
            "type":"Entertainment"
        }
    ],
    "sg:phone":"+1 403 282 9101",
    "sg:postcode":"T2M 0M3",
    "sg:province":"AB",
    "wof:name":"Banff Trail Motel",
    "wof:placetype":"venue"
},
  "geometry": {"coordinates":[-114.109764,51.066875],"type":"Point"}
}