{
  "type": "Feature",
  "properties": {
    "addr:full":"3 Rue Gerard-Morisset Cap-Sante QC G0A 1L0",
    "addr:housenumber":"3",
    "addr:postcode":"g0a 1l0",
    "addr:street":"Rue Gerard-Morisset Cap-Sante",
    "iso:country":"CA",
    "sg:address":"3 Rue Gerard-Morisset",
    "sg:city":"Cap-Sante",
    "sg:classifiers":[
        {
            "category":"Insurance",
            "subcategory":"Insurance Agent",
            "type":"Services"
        }
    ],
    "sg:phone":"+1 418 285 2434",
    "sg:postcode":"G0A 1L0",
    "sg:province":"QC",
    "wof:name":"Assurances Generales-Caisses",
    "wof:placetype":"venue"
},
  "geometry": {"coordinates":[-71.7685852051,46.6699333191],"type":"Point"}
}