{
  "type": "Feature",
  "properties": {
    "addr:full":"130 Adelaide St W #2200 Toronto ON M5H 3P5",
    "addr:housenumber":"130",
    "addr:postcode":"m5h 3p5",
    "addr:street":"Adelaide St W # 2200",
    "iso:country":"CA",
    "sg:address":"130 Adelaide St W #2200",
    "sg:city":"Toronto",
    "sg:classifiers":[
        {
            "category":"Banks & Credit Unions",
            "subcategory":"Investment Brokerage",
            "type":"Services"
        }
    ],
    "sg:phone":"+1 416 368 9426",
    "sg:postcode":"M5H 3P5",
    "sg:province":"ON",
    "sg:tags":[
        "consultant",
        "planning",
        "financial"
    ],
    "wof:name":"Pineridge Financial",
    "wof:placetype":"venue"
},
  "geometry": {"coordinates":[-79.3838882446,43.6493530273],"type":"Point"}
}