{
  "type": "Feature",
  "properties": {
    "addr:full":"1244 Av Beaumont Mont-Royal QC H3P 3E5",
    "addr:housenumber":"1244",
    "addr:postcode":"h3p 3e5",
    "addr:street":"Av Beaumont",
    "iso:country":"CA",
    "sg:address":"1244 Av Beaumont",
    "sg:city":"Mont-Royal",
    "sg:classifiers":[
        {
            "category":"Restaurant",
            "type":"Food & Drink"
        }
    ],
    "sg:phone":"+1 514 739 2243",
    "sg:postcode":"H3P 3E5",
    "sg:province":"QC",
    "wof:name":"Cage Aux Sports",
    "wof:placetype":"venue"
},
  "geometry": {"coordinates":[-73.62454200000001,45.521767],"type":"Point"}
}