{
  "type": "Feature",
  "properties": {
    "iso:country":"CA",
    "sg:address":"1244 Av Beaumont",
    "sg:city":"Mont-Royal",
    "sg:classifiers":[
        {
            "category":"Restaurant",
            "type":"Food & Drink"
        }
    ],
    "sg:phone":"+1 514 739 2243",
    "sg:postcode":"H3P 3E5",
    "sg:province":"QC",
    "wof:name":"Cage Aux Sports",
    "wof:placetype":"venue"
},
  "geometry": {"coordinates":[-73.624542,45.521767],"type":"Point"}
}