{
  "type": "Feature",
  "properties": {
    "iso:country":"CA",
    "sg:city":"Gracefield",
    "sg:classifiers":[
        {
            "category":"Travel",
            "subcategory":"Travel Agent",
            "type":"Entertainment"
        }
    ],
    "sg:phone":"+1 819 463 4915",
    "sg:postcode":"J0X 1W0",
    "sg:province":"QC",
    "sg:tags":[
        "agency",
        "bureau"
    ],
    "wof:name":"Voyages LA Chaudiere Inc",
    "wof:placetype":"venue"
},
  "geometry": {"coordinates":[-76.05322265620001,46.0929527283],"type":"Point"}
}