{
  "type": "Feature",
  "properties": {
    "addr:full":"Hwy 2 S Prince Albert SK S6V 5P9",
    "addr:postcode":"s6v 5p9",
    "addr:street":"Hwy 2 S",
    "iso:country":"CA",
    "sg:address":"Hwy 2 S",
    "sg:city":"Prince Albert",
    "sg:classifiers":[
        {
            "category":"Travel",
            "subcategory":"Hotels & Motels",
            "type":"Entertainment"
        }
    ],
    "sg:phone":"+1 306 764 2374",
    "sg:postcode":"S6V 5P9",
    "sg:province":"SK",
    "wof:name":"Countryview Motel",
    "wof:placetype":"venue"
},
  "geometry": {"coordinates":[-105.760108948,53.1980934143],"type":"Point"}
}