{
  "type": "Feature",
  "properties": {
    "iso:country":"CA",
    "sg:address":"6754 Boul Saint-Laurent",
    "sg:city":"Montreal",
    "sg:classifiers":[
        {
            "category":"Retail",
            "subcategory":"Portrait Studio",
            "type":"Services"
        }
    ],
    "sg:phone":"+1 514 273 9198",
    "sg:postcode":"H2S 3C7",
    "sg:province":"QC",
    "sg:tags":[
        "photographer"
    ],
    "wof:name":"Augustis Photo",
    "wof:placetype":"venue"
},
  "geometry": {"coordinates":[-73.613174,45.532192],"type":"Point"}
}