{
  "type": "Feature",
  "properties": {
    "iso:country":"CA",
    "sg:address":"3899 Stoneham Way",
    "sg:city":"Mississauga",
    "sg:classifiers":[
        {
            "category":"Real Estate",
            "subcategory":"Surveying",
            "type":"Services"
        }
    ],
    "sg:phone":"+1 905 785 0360",
    "sg:postcode":"L5N 6Y7",
    "sg:province":"ON",
    "sg:tags":[
        "development",
        "consultant",
        "land"
    ],
    "wof:name":"Prasad & Assoc Inc",
    "wof:placetype":"venue"
},
  "geometry": {"coordinates":[-79.7862701416,43.5773735046],"type":"Point"}
}