{
  "type": "Feature",
  "properties": {
    "iso:country":"CA",
    "sg:city":"Edmonton",
    "sg:classifiers":[
        {
            "category":"Professional",
            "subcategory":"Lawyer & Legal Services",
            "type":"Services"
        }
    ],
    "sg:phone":"+1 780 427 7575",
    "sg:postcode":"T5J 4A1",
    "sg:province":"AB",
    "sg:tags":[
        "attorney",
        "government"
    ],
    "wof:name":"Legal Aid Society of Alberta",
    "wof:placetype":"venue"
},
  "geometry": {"coordinates":[-113.497902,53.54314],"type":"Point"}
}