{
  "type": "Feature",
  "properties": {
    "addr:full":"148 3rd St W North Vancouver BC V7M 1E8",
    "addr:housenumber":"148",
    "addr:postcode":"v7m 1e8",
    "addr:street":"3Rd St W",
    "iso:country":"CA",
    "sg:address":"148 3rd St W",
    "sg:city":"North Vancouver",
    "sg:classifiers":[
        {
            "category":"Cinema",
            "subcategory":"Movie Rental",
            "type":"Entertainment"
        }
    ],
    "sg:phone":"+1 604 987 2127",
    "sg:postcode":"V7M 1E8",
    "sg:province":"BC",
    "sg:tags":[
        "leasing",
        "video",
        "disc",
        "tape"
    ],
    "wof:name":"Odyssey Video",
    "wof:placetype":"venue"
},
  "geometry": {"coordinates":[-123.078423,49.314236],"type":"Point"}
}