{
  "type": "Feature",
  "properties": {
    "addr:full":"67 Rue DE L'Anse S Beaumont QC G0R 1C0",
    "addr:housenumber":"67",
    "addr:postcode":"g0r 1c0",
    "addr:street":"Rue De L'Anse S",
    "iso:country":"CA",
    "sg:address":"67 Rue DE L'Anse S",
    "sg:city":"Beaumont",
    "sg:classifiers":[
        {
            "category":"Autos & Motor Vehicles",
            "subcategory":"Automobile Sales",
            "type":"Retail Goods"
        }
    ],
    "sg:phone":"+1 418 833 2423",
    "sg:postcode":"G0R 1C0",
    "sg:province":"QC",
    "sg:tags":[
        "car",
        "dealer"
    ],
    "wof:name":"Garage Yvan Asselin Inc",
    "wof:placetype":"venue"
},
  "geometry": {"coordinates":[-69.9272613525,47.0548095703],"type":"Point"}
}