{
  "type": "Feature",
  "properties": {
    "addr:full":"North York ON M2L 2G1",
    "addr:postcode":"m2l 2g1",
    "iso:country":"CA",
    "sg:city":"North York",
    "sg:classifiers":[
        {
            "category":"Personal",
            "subcategory":"Beauty Salon",
            "type":"Services"
        }
    ],
    "sg:phone":"+1 416 445 2611",
    "sg:postcode":"M2L 2G1",
    "sg:province":"ON",
    "wof:name":"York Mills Beauty Boutique",
    "wof:placetype":"venue"
},
  "geometry": {"coordinates":[-79.361305,43.754593],"type":"Point"}
}