{
  "type": "Feature",
  "properties": {
    "addr:full":"7295 Rue Tellier Montreal QC H1N 3S9",
    "addr:housenumber":"7295",
    "addr:postcode":"h1n 3s9",
    "addr:street":"Rue Tellier",
    "iso:country":"CA",
    "sg:address":"7295 Rue Tellier",
    "sg:city":"Montreal",
    "sg:classifiers":[
        {
            "category":"Manufacturing",
            "subcategory":"Rubber & Plastics",
            "type":"Manufacturing & Wholesale Goods"
        }
    ],
    "sg:phone":"+1 514 251 9550",
    "sg:postcode":"H1N 3S9",
    "sg:province":"QC",
    "sg:tags":[
        "mold",
        "maker"
    ],
    "wof:name":"Produits DE Plastique Age Inc",
    "wof:placetype":"venue"
},
  "geometry": {"coordinates":[-73.522819519,45.5835380554],"type":"Point"}
}