{
  "type": "Feature",
  "properties": {
    "addr:full":"Calgary AB T2R 0E1",
    "addr:postcode":"t2r 0e1",
    "iso:country":"CA",
    "sg:city":"Calgary",
    "sg:classifiers":[
        {
            "category":"Building & Trades",
            "subcategory":"Landscaping Services",
            "type":"Services"
        }
    ],
    "sg:phone":"+1 403 234 8544",
    "sg:postcode":"T2R 0E1",
    "sg:province":"AB",
    "sg:tags":[
        "designer",
        "landscape"
    ],
    "wof:name":"Carson-Mc Culloch Assoc Ltd",
    "wof:placetype":"venue"
},
  "geometry": {"coordinates":[-114.074371,51.042553],"type":"Point"}
}