{
  "type": "Feature",
  "properties": {
    "addr:full":"186 Boul St-Pierre O Caraquet NB E1W 1A5",
    "addr:housenumber":"186",
    "addr:postcode":"e1w 1a5",
    "addr:street":"Boul St-Pierre O",
    "iso:country":"CA",
    "sg:address":"186 Boul St-Pierre O",
    "sg:city":"Caraquet",
    "sg:classifiers":[
        {
            "category":"Restaurant",
            "type":"Food & Drink"
        }
    ],
    "sg:phone":"+1 506 727 9469",
    "sg:postcode":"E1W 1A5",
    "sg:province":"NB",
    "wof:name":"Cafe Phare",
    "wof:placetype":"venue"
},
  "geometry": {"coordinates":[-64.91301727290001,47.7953109741],"type":"Point"}
}