{
  "type": "Feature",
  "properties": {
    "addr:full":"371 Rue Carreau Thetford Mines QC G6G 2K8",
    "addr:housenumber":"371",
    "addr:postcode":"g6g 2k8",
    "addr:street":"Rue Carreau",
    "iso:country":"CA",
    "sg:address":"371 Rue Carreau",
    "sg:city":"Thetford Mines",
    "sg:classifiers":[
        {
            "category":"Retail",
            "subcategory":"Laundry & Dry Cleaning",
            "type":"Services"
        }
    ],
    "sg:phone":"+1 418 338 5381",
    "sg:postcode":"G6G 2K8",
    "sg:province":"QC",
    "sg:tags":[
        "cleaners",
        "rug",
        "carpet"
    ],
    "wof:name":"Service DE Nettoyage Reno",
    "wof:placetype":"venue"
},
  "geometry": {"coordinates":[-71.2964477539,46.0971870422],"type":"Point"}
}