{
  "type": "Feature",
  "properties": {
    "addr:full":"Jubilee St Worsley AB T0H 3W0",
    "addr:postcode":"t0h 3w0",
    "addr:street":"Jubilee St",
    "iso:country":"CA",
    "sg:address":"Jubilee St",
    "sg:city":"Worsley",
    "sg:classifiers":[
        {
            "category":"Organizations",
            "subcategory":"Professional Association",
            "type":"Services"
        }
    ],
    "sg:phone":"+1 780 685 2078",
    "sg:postcode":"T0H 3W0",
    "sg:province":"AB",
    "sg:tags":[
        "club"
    ],
    "wof:name":"Worsley Pioneer Club",
    "wof:placetype":"venue"
},
  "geometry": {"coordinates":[-119.13988494900001,56.5087165833],"type":"Point"}
}