{
  "type": "Feature",
  "properties": {
    "addr:full":"Okotoks AB T1S 1Z6",
    "addr:postcode":"t1s 1z6",
    "iso:country":"CA",
    "sg:city":"Okotoks",
    "sg:classifiers":[
        {
            "category":"Retail",
            "subcategory":"Veterinary Services",
            "type":"Services"
        }
    ],
    "sg:phone":"+1 403 938 0350",
    "sg:postcode":"T1S 1Z6",
    "sg:province":"AB",
    "sg:tags":[
        "veterinarian"
    ],
    "wof:name":"Animal Care Ctr-Okotoks",
    "wof:placetype":"venue"
},
  "geometry": {"coordinates":[-113.98303199999999,50.71854],"type":"Point"}
}