{
  "type": "Feature",
  "properties": {
    "addr:full":"14 Court St Truro NS B2N 3H7",
    "addr:housenumber":"14",
    "addr:postcode":"b2n 3h7",
    "addr:street":"Court St",
    "iso:country":"CA",
    "sg:address":"14 Court St",
    "sg:city":"Truro",
    "sg:classifiers":[
        {
            "category":"Government",
            "subcategory":"Office",
            "type":"Public Place"
        }
    ],
    "sg:phone":"+1 902 893 0070",
    "sg:postcode":"B2N 3H7",
    "sg:province":"NS",
    "wof:name":"Canada Student Employment",
    "wof:placetype":"venue"
},
  "geometry": {"coordinates":[-63.2872962952,45.3667411804],"type":"Point"}
}