{
  "type": "Feature",
  "properties": {
    "addr:full":"240 Rue Fleury E Montreal QC H3L 1E8",
    "addr:housenumber":"240",
    "addr:postcode":"h3l 1e8",
    "addr:street":"Rue Fleury E",
    "iso:country":"CA",
    "sg:address":"240 Rue Fleury E",
    "sg:city":"Montreal",
    "sg:classifiers":[
        {
            "category":"Building & Trades",
            "subcategory":"Electrical",
            "type":"Services"
        }
    ],
    "sg:phone":"+1 514 383 4040",
    "sg:postcode":"H3L 1E8",
    "sg:province":"QC",
    "sg:tags":[
        "electric",
        "contractor"
    ],
    "wof:name":"Andre Blais Electrique Inc",
    "wof:placetype":"venue"
},
  "geometry": {"coordinates":[-73.66342899999999,45.550514],"type":"Point"}
}