{
  "type": "Feature",
  "properties": {
    "iso:country":"CA",
    "sg:city":"Whitby",
    "sg:classifiers":[
        {
            "category":"Autos & Motor Vehicles",
            "subcategory":"Boat Sales",
            "type":"Retail Goods"
        }
    ],
    "sg:phone":"+1 905 668 4077",
    "sg:postcode":"L1N 1B9",
    "sg:province":"ON",
    "sg:tags":[
        "equipment",
        "marine",
        "supply"
    ],
    "wof:name":"Port Whitby Marine Supplies",
    "wof:placetype":"venue"
},
  "geometry": {"coordinates":[-78.936073,43.860909],"type":"Point"}
}