{
  "type": "Feature",
  "properties": {
    "iso:country":"CA",
    "sg:address":"40 Tiffield Rd # 1",
    "sg:city":"Scarborough",
    "sg:classifiers":[
        {
            "category":"Manufacturing",
            "subcategory":"Tools & Machinery",
            "type":"Manufacturing & Wholesale Goods"
        }
    ],
    "sg:phone":"+1 416 298 9255",
    "sg:postcode":"M1V 5B6",
    "sg:province":"ON",
    "sg:tags":[
        "machine",
        "shop"
    ],
    "wof:name":"Thermadie Tooling Inc",
    "wof:placetype":"venue"
},
  "geometry": {"coordinates":[-79.2542266846,43.8134460449],"type":"Point"}
}