{
  "type": "Feature",
  "properties": {
    "addr:full":"Quebec QC G1R 2H8",
    "addr:postcode":"g1r 2h8",
    "iso:country":"CA",
    "sg:city":"Quebec",
    "sg:classifiers":[
        {
            "category":"Organizations",
            "subcategory":"Professional Association",
            "type":"Services"
        }
    ],
    "sg:phone":"+1 418 522 3434",
    "sg:postcode":"G1R 2H8",
    "sg:province":"QC",
    "wof:name":"Chambre DE Commerce & Ind",
    "wof:placetype":"venue"
},
  "geometry": {"coordinates":[-71.22023,46.804024],"type":"Point"}
}