{
  "type": "Feature",
  "properties": {
    "addr:full":"2283 Belcourt Blvd Orleans ON K1C 1M7",
    "addr:housenumber":"2283",
    "addr:postcode":"k1c 1m7",
    "addr:street":"Belcourt Blvd",
    "iso:country":"CA",
    "sg:address":"2283 Belcourt Blvd",
    "sg:city":"Orleans",
    "sg:classifiers":[
        {
            "category":"Restaurant",
            "type":"Food & Drink"
        }
    ],
    "sg:phone":"+1 613 824 2283",
    "sg:postcode":"K1C 1M7",
    "sg:province":"ON",
    "sg:tags":[
        "out"
    ],
    "wof:name":"Belcourt Pizza",
    "wof:placetype":"venue"
},
  "geometry": {"coordinates":[-75.51150512700001,45.4533882141],"type":"Point"}
}