{
  "type": "Feature",
  "properties": {
    "iso:country":"CA",
    "sg:address":"30 Christopher Dr",
    "sg:city":"Cambridge",
    "sg:classifiers":[
        {
            "category":"Social Services",
            "subcategory":"Child Care",
            "type":"Services"
        }
    ],
    "sg:phone":"+1 519 621 6525",
    "sg:postcode":"N1R 4R4",
    "sg:province":"ON",
    "sg:tags":[
        "government"
    ],
    "wof:name":"Christopher House Day Care Ctr",
    "wof:placetype":"venue"
},
  "geometry": {"coordinates":[-80.3024673462,43.3529434204],"type":"Point"}
}