{
  "type": "Feature",
  "properties": {
    "addr:full":"Salaberry-DE-Valleyfield QC J6S 3V7",
    "addr:postcode":"j6s 3v7",
    "iso:country":"CA",
    "sg:city":"Salaberry-DE-Valleyfield",
    "sg:classifiers":[
        {
            "category":"Personal",
            "subcategory":"Beauty Salon",
            "type":"Services"
        }
    ],
    "sg:phone":"+1 450 373 5455",
    "sg:postcode":"J6S 3V7",
    "sg:province":"QC",
    "wof:name":"Salon Ninon",
    "wof:placetype":"venue"
},
  "geometry": {"coordinates":[-74.13249999999999,45.268887],"type":"Point"}
}