{
  "type": "Feature",
  "properties": {
    "addr:full":"324 Ch DE LA Normandie Laval QC H7G 2A8",
    "addr:housenumber":"324",
    "addr:postcode":"qc h7g 2a8",
    "addr:street":"Ch De La Normandie",
    "iso:country":"CA",
    "sg:address":"324 Ch DE LA Normandie",
    "sg:city":"Laval",
    "sg:classifiers":[
        {
            "category":"Shopping",
            "subcategory":"Department Store",
            "type":"Retail Goods"
        }
    ],
    "sg:phone":"+1 450 663 9888",
    "sg:postcode":"H7G 2A8",
    "sg:province":"QC",
    "sg:tags":[
        "shop",
        "variety"
    ],
    "wof:name":"Expert En Dollar Plus",
    "wof:placetype":"venue"
},
  "geometry": {"coordinates":[-73.74463653559999,45.5515670776],"type":"Point"}
}