{
  "type": "Feature",
  "properties": {
    "iso:country":"CA",
    "sg:address":"223 4th Ave SE",
    "sg:city":"Eston",
    "sg:classifiers":[
        {
            "category":"Health Services",
            "subcategory":"Doctor",
            "type":"Services"
        }
    ],
    "sg:phone":"+1 306 962 3616",
    "sg:postcode":"S0L 1A0",
    "sg:province":"SK",
    "sg:tags":[
        "physician",
        "surgeon"
    ],
    "wof:name":"Eston Clinic",
    "wof:placetype":"venue"
},
  "geometry": {"coordinates":[-108.75845336899999,51.1495742798],"type":"Point"}
}