{
  "type": "Feature",
  "properties": {
    "addr:full":"Windsor ON N9E 4C9",
    "addr:postcode":"n9e 4c9",
    "iso:country":"CA",
    "sg:city":"Windsor",
    "sg:classifiers":[
        {
            "category":"Health Services",
            "subcategory":"Chiropractor",
            "type":"Services"
        }
    ],
    "sg:phone":"+1 519 972 8044",
    "sg:postcode":"N9E 4C9",
    "sg:province":"ON",
    "wof:name":"Huron Line Chiropractic Clinic",
    "wof:placetype":"venue"
},
  "geometry": {"coordinates":[-83.0425186157,42.2616119385],"type":"Point"}
}