{
  "type": "Feature",
  "properties": {
    "addr:full":"Saint-Bernard QC G0S 2G0",
    "addr:postcode":"g0s 2g0",
    "iso:country":"CA",
    "sg:city":"Saint-Bernard",
    "sg:classifiers":[
        {
            "category":"Banks & Credit Unions",
            "subcategory":"Bank",
            "type":"Services"
        }
    ],
    "sg:phone":"+1 418 475 6651",
    "sg:postcode":"G0S 2G0",
    "sg:province":"QC",
    "wof:name":"Caisses Desjardins",
    "wof:placetype":"venue"
},
  "geometry": {"coordinates":[-71.137154,46.498344],"type":"Point"}
}