{
  "type": "Feature",
  "properties": {
    "addr:full":"Terrace BC V8G 1S6",
    "addr:postcode":"v8g 1s6",
    "iso:country":"CA",
    "sg:city":"Terrace",
    "sg:classifiers":[
        {
            "category":"Real Estate",
            "subcategory":"Real Estate Agent",
            "type":"Services"
        }
    ],
    "sg:phone":"+1 250 635 0615",
    "sg:postcode":"V8G 1S6",
    "sg:province":"BC",
    "sg:tags":[
        "appraiser"
    ],
    "wof:name":"Appraisals Northwest",
    "wof:placetype":"venue"
},
  "geometry": {"coordinates":[-128.590698,54.517719],"type":"Point"}
}