{
  "type": "Feature",
  "properties": {
    "addr:full":"480 Keith Rd West Vancouver BC V7T 1L7",
    "addr:housenumber":"480",
    "addr:postcode":"v7t 1l7",
    "addr:street":"Keith Rd",
    "iso:country":"CA",
    "sg:address":"480 Keith Rd",
    "sg:city":"West Vancouver",
    "sg:classifiers":[
        {
            "category":"Manufacturing",
            "subcategory":"Lumber",
            "type":"Manufacturing & Wholesale Goods"
        }
    ],
    "sg:phone":"+1 604 925 8646",
    "sg:postcode":"V7T 1L7",
    "sg:province":"BC",
    "sg:tags":[
        "forester"
    ],
    "wof:name":"Akehurst & Giltrap Refrstn",
    "wof:placetype":"venue"
},
  "geometry": {"coordinates":[-123.12880699999999,49.330704],"type":"Point"}
}