{
  "type": "Feature",
  "properties": {
    "addr:full":"154 Lansdowne St E Peterborough ON K9J 7N9",
    "addr:housenumber":"154",
    "addr:postcode":"k9j 7n9",
    "addr:street":"Lansdowne St E",
    "iso:country":"CA",
    "sg:address":"154 Lansdowne St E",
    "sg:city":"Peterborough",
    "sg:classifiers":[
        {
            "category":"Restaurant",
            "type":"Food & Drink"
        }
    ],
    "sg:phone":"+1 705 742 8541",
    "sg:postcode":"K9J 7N9",
    "sg:province":"ON",
    "sg:tags":[
        "parlor",
        "ice",
        "cream"
    ],
    "wof:name":"Dairy Queen",
    "wof:placetype":"venue"
},
  "geometry": {"coordinates":[-78.2997741699,44.2895431519],"type":"Point"}
}