{
  "type": "Feature",
  "properties": {
    "addr:full":"799 Sackville Dr Lower Sackville NS B4E 1R6",
    "addr:housenumber":"799",
    "addr:postcode":"b4e 1r6",
    "addr:street":"Sackville Dr",
    "iso:country":"CA",
    "sg:address":"799 Sackville Dr",
    "sg:city":"Lower Sackville",
    "sg:classifiers":[
        {
            "category":"Banks & Credit Unions",
            "subcategory":"Bank",
            "type":"Services"
        }
    ],
    "sg:phone":"+1 902 865 6871",
    "sg:postcode":"B4E 1R6",
    "sg:province":"NS",
    "sg:tags":[
        "financing",
        "loan",
        "real estate"
    ],
    "wof:name":"Citifinancial",
    "wof:placetype":"venue"
},
  "geometry": {"coordinates":[-63.693611,44.774704],"type":"Point"}
}