{
  "type": "Feature",
  "properties": {
    "iso:country":"CA",
    "sg:address":"3870 Av Van Horne",
    "sg:city":"Montreal",
    "sg:classifiers":[
        {
            "category":"Health Services",
            "subcategory":"Doctor",
            "type":"Services"
        }
    ],
    "sg:phone":"+1 514 342 0558",
    "sg:postcode":"H3S 1R8",
    "sg:province":"QC",
    "sg:tags":[
        "dentist"
    ],
    "wof:name":"Le Quang, Gerald DDS",
    "wof:placetype":"venue"
},
  "geometry": {"coordinates":[-73.633133,45.499142],"type":"Point"}
}