{
  "type": "Feature",
  "properties": {
    "addr:full":"200 Saulteaux Cres Winnipeg MB R3J 3W3",
    "addr:housenumber":"200",
    "addr:postcode":"r3j 3w3",
    "addr:street":"Saulteaux Cres",
    "iso:country":"CA",
    "sg:address":"200 Saulteaux Cres",
    "sg:city":"Winnipeg",
    "sg:classifiers":[
        {
            "category":"Government",
            "subcategory":"Office",
            "type":"Public Place"
        }
    ],
    "sg:phone":"+1 204 945 6784",
    "sg:postcode":"R3J 3W3",
    "sg:province":"MB",
    "wof:name":"Manitoba Trapping Licence",
    "wof:placetype":"venue"
},
  "geometry": {"coordinates":[-97.258049,49.898285],"type":"Point"}
}