{
  "type": "Feature",
  "properties": {
    "addr:full":"451 Boul Des Seigneurs Terrebonne QC J6W 4C1",
    "addr:housenumber":"451",
    "addr:postcode":"j6w 4c1",
    "addr:street":"Boul Des Seigneurs",
    "iso:country":"CA",
    "sg:address":"451 Boul Des Seigneurs",
    "sg:city":"Terrebonne",
    "sg:classifiers":[
        {
            "category":"Insurance",
            "subcategory":"Insurance Agent",
            "type":"Services"
        }
    ],
    "sg:phone":"+1 450 471 2855",
    "sg:postcode":"J6W 4C1",
    "sg:province":"QC",
    "wof:name":"Andre Desjardins Assurances",
    "wof:placetype":"venue"
},
  "geometry": {"coordinates":[-73.632019,45.70417],"type":"Point"}
}