{
  "type": "Feature",
  "properties": {
    "iso:country":"CA",
    "sg:address":"330 Carlow Rd",
    "sg:city":"Port Stanley",
    "sg:classifiers":[
        {
            "category":"Building & Trades",
            "subcategory":"Electrical",
            "type":"Services"
        }
    ],
    "sg:phone":"+1 519 782 3589",
    "sg:postcode":"N5L 1B6",
    "sg:province":"ON",
    "sg:tags":[
        "electric",
        "contractor"
    ],
    "wof:name":"Mac Kinnon Electrical Svc",
    "wof:placetype":"venue"
},
  "geometry": {"coordinates":[-81.2200927734,42.6703643799],"type":"Point"}
}