{
  "type": "Feature",
  "properties": {
    "iso:country":"CA",
    "sg:address":"3142 Yonge St",
    "sg:city":"Toronto",
    "sg:classifiers":[
        {
            "category":"Food & Beverages",
            "subcategory":"Groceries & Convenience Stores",
            "type":"Retail Goods"
        }
    ],
    "sg:phone":"+1 416 484 0750",
    "sg:postcode":"M4N 2K6",
    "sg:province":"ON",
    "sg:tags":[
        "grocer"
    ],
    "wof:name":"Dominion Food Stores",
    "wof:placetype":"venue"
},
  "geometry": {"coordinates":[-79.4027938843,43.7267112732],"type":"Point"}
}