{
  "type": "Feature",
  "properties": {
    "addr:full":"12930 82 St NW Edmonton AB T5E 2T2",
    "addr:housenumber":"12930",
    "addr:postcode":"t5e 2t2",
    "addr:street":"82 St Nw",
    "iso:country":"CA",
    "sg:address":"12930 82 St NW",
    "sg:city":"Edmonton",
    "sg:classifiers":[
        {
            "category":"Shopping",
            "subcategory":"Pharmacy",
            "type":"Retail Goods"
        }
    ],
    "sg:phone":"+1 780 476 8737",
    "sg:postcode":"T5E 2T2",
    "sg:province":"AB",
    "wof:name":"Delton Super Drugs",
    "wof:placetype":"venue"
},
  "geometry": {"coordinates":[-113.467399597,53.5874252319],"type":"Point"}
}