{
  "type": "Feature",
  "properties": {
    "addr:full":"Monarch AB T0L 1M0",
    "addr:postcode":"t0l 1m0",
    "iso:country":"CA",
    "sg:city":"Monarch",
    "sg:classifiers":[
        {
            "category":"Farming",
            "subcategory":"Nursery",
            "type":"Manufacturing & Wholesale Goods"
        }
    ],
    "sg:phone":"+1 403 553 3175",
    "sg:postcode":"T0L 1M0",
    "sg:province":"AB",
    "sg:tags":[
        "greenhouse"
    ],
    "wof:name":"Hilltop Greenhouses",
    "wof:placetype":"venue"
},
  "geometry": {"coordinates":[-113.10066999999999,49.804657],"type":"Point"}
}