{
  "type": "Feature",
  "properties": {
    "addr:full":"246 Saskatchewan Ave E Portage LA Prairie MB R1N 0K9",
    "addr:housenumber":"246",
    "addr:postcode":"r1n 0k9",
    "addr:street":"Saskatchewan Ave E",
    "iso:country":"CA",
    "sg:address":"246 Saskatchewan Ave E",
    "sg:city":"Portage LA Prairie",
    "sg:classifiers":[
        {
            "category":"Shopping",
            "subcategory":"Bicycles & Sporting Goods",
            "type":"Retail Goods"
        }
    ],
    "sg:phone":"+1 204 857 3496",
    "sg:postcode":"R1N 0K9",
    "sg:province":"MB",
    "wof:name":"Mac Donalds Sporting Goods Ltd",
    "wof:placetype":"venue"
},
  "geometry": {"coordinates":[-98.28684997560001,49.9730262756],"type":"Point"}
}