{
  "type": "Feature",
  "properties": {
    "iso:country":"CA",
    "sg:address":"27 Roundel Rd",
    "sg:city":"Whitehorse",
    "sg:classifiers":[
        {
            "category":"Building & Trades",
            "subcategory":"Construction",
            "type":"Services"
        }
    ],
    "sg:phone":"+1 867 668 2321",
    "sg:postcode":"Y1A 3H4",
    "sg:province":"YT",
    "sg:tags":[
        "resurfacing",
        "laying",
        "refinishing",
        "floor"
    ],
    "wof:name":"Walk Easy Hardwood Floors",
    "wof:placetype":"venue"
},
  "geometry": {"coordinates":[-135.088790894,60.7127914429],"type":"Point"}
}