{
  "type": "Feature",
  "properties": {
    "addr:full":"225 Bagot St Kingston ON K7L 3G3",
    "addr:housenumber":"225",
    "addr:postcode":"k7l 3g3",
    "addr:street":"Bagot St",
    "iso:country":"CA",
    "sg:address":"225 Bagot St",
    "sg:city":"Kingston",
    "sg:classifiers":[
        {
            "category":"Professional",
            "subcategory":"Lawyer & Legal Services",
            "type":"Services"
        }
    ],
    "sg:phone":"+1 613 549 2222",
    "sg:postcode":"K7L 3G3",
    "sg:province":"ON",
    "sg:tags":[
        "attorney"
    ],
    "wof:name":"Black & Black",
    "wof:placetype":"venue"
},
  "geometry": {"coordinates":[-76.484848,44.230236],"type":"Point"}
}