{
  "type": "Feature",
  "properties": {
    "addr:full":"9 Fifth Ave N Yorkton SK S3N 0Y9",
    "addr:housenumber":"9",
    "addr:postcode":"s3n 0y9",
    "addr:street":"Fifth Ave N",
    "iso:country":"CA",
    "sg:address":"9 Fifth Ave N",
    "sg:city":"Yorkton",
    "sg:classifiers":[
        {
            "category":"Banks & Credit Unions",
            "subcategory":"Investment Brokerage",
            "type":"Services"
        }
    ],
    "sg:phone":"+1 306 783 3171",
    "sg:postcode":"S3N 0Y9",
    "sg:province":"SK",
    "sg:tags":[
        "consultant",
        "planning",
        "financial"
    ],
    "wof:name":"Harris Financial Svc",
    "wof:placetype":"venue"
},
  "geometry": {"coordinates":[-102.456954956,51.2105636597],"type":"Point"}
}