{
  "type": "Feature",
  "properties": {
    "addr:full":"7207 10th Ave Burnaby BC V3N 2R7",
    "addr:housenumber":"7207",
    "addr:postcode":"v3n 2r7",
    "addr:street":"10Th Ave",
    "iso:country":"CA",
    "sg:address":"7207 10th Ave",
    "sg:city":"Burnaby",
    "sg:classifiers":[
        {
            "category":"Shopping",
            "subcategory":"Computers & Home Electronics",
            "type":"Retail Goods"
        }
    ],
    "sg:phone":"+1 604 524 4123",
    "sg:postcode":"V3N 2R7",
    "sg:province":"BC",
    "sg:tags":[
        "sound",
        "equipment",
        "system"
    ],
    "wof:name":"T W Productions",
    "wof:placetype":"venue"
},
  "geometry": {"coordinates":[-122.944138,49.210201],"type":"Point"}
}