{
  "type": "Feature",
  "properties": {
    "addr:full":"122 Av Fairmount O Montreal QC H2T 2M5",
    "addr:postcode":"h2t 2m5",
    "addr:street":"122 Av Fairmount O",
    "iso:country":"CA",
    "sg:address":"122 Av Fairmount O",
    "sg:city":"Montreal",
    "sg:classifiers":[
        {
            "category":"Food & Beverages",
            "subcategory":"Bakery",
            "type":"Retail Goods"
        }
    ],
    "sg:phone":"+1 514 271 1078",
    "sg:postcode":"H2T 2M5",
    "sg:province":"QC",
    "sg:tags":[
        "baker"
    ],
    "wof:name":"Kamenitsa",
    "wof:placetype":"venue"
},
  "geometry": {"coordinates":[-73.59325408940001,45.5252456665],"type":"Point"}
}