{
  "type": "Feature",
  "properties": {
    "iso:country":"CA",
    "sg:city":"Brockville",
    "sg:classifiers":[
        {
            "category":"Building & Trades",
            "subcategory":"Construction",
            "type":"Services"
        }
    ],
    "sg:phone":"+1 613 345 3617",
    "sg:postcode":"K6V 5T1",
    "sg:province":"ON",
    "sg:tags":[
        "designer",
        "dealer",
        "pool",
        "swimming"
    ],
    "wof:name":"Aquarius Pools & Spas",
    "wof:placetype":"venue"
},
  "geometry": {"coordinates":[-75.68301391599999,44.5903892517],"type":"Point"}
}