{
  "type": "Feature",
  "properties": {
    "addr:full":"111 Albert St #200 Ottawa ON K1P 1A5",
    "addr:housenumber":"111",
    "addr:postcode":"k1p 1a5",
    "addr:street":"Albert St # 200",
    "iso:country":"CA",
    "sg:address":"111 Albert St #200",
    "sg:city":"Ottawa",
    "sg:classifiers":[
        {
            "category":"Shopping",
            "subcategory":"Florist",
            "type":"Retail Goods"
        }
    ],
    "sg:phone":"+1 613 234 6777",
    "sg:postcode":"K1P 1A5",
    "sg:province":"ON",
    "wof:name":"Phulero Dola Swing of Flowers",
    "wof:placetype":"venue"
},
  "geometry": {"coordinates":[-75.696877,45.421577],"type":"Point"}
}