{
  "type": "Feature",
  "properties": {
    "iso:country":"CA",
    "sg:city":"Hamilton",
    "sg:classifiers":[
        {
            "category":"Manufacturing",
            "subcategory":"Printing",
            "type":"Manufacturing & Wholesale Goods"
        }
    ],
    "sg:phone":"+1 905 388 0999",
    "sg:postcode":"L9C 2Z1",
    "sg:province":"ON",
    "sg:tags":[
        "printer",
        "duplicating",
        "copying"
    ],
    "wof:name":"Hamilton Copy Copy Printing",
    "wof:placetype":"venue"
},
  "geometry": {"coordinates":[-79.87776947019999,43.2381896973],"type":"Point"}
}