{
  "type": "Feature",
  "properties": {
    "addr:full":"44 Holm Cres Thornhill ON L3T 5J3",
    "addr:housenumber":"44",
    "addr:postcode":"l3t 5j3",
    "addr:street":"Holm Cres",
    "iso:country":"CA",
    "sg:address":"44 Holm Cres",
    "sg:city":"Thornhill",
    "sg:classifiers":[
        {
            "category":"Wholesale",
            "subcategory":"Durable Goods & Equipment",
            "type":"Manufacturing & Wholesale Goods"
        }
    ],
    "sg:phone":"+1 905 882 9782",
    "sg:postcode":"L3T 5J3",
    "sg:province":"ON",
    "sg:tags":[
        "exporter"
    ],
    "wof:name":"Portex Canada",
    "wof:placetype":"venue"
},
  "geometry": {"coordinates":[-79.39250199999999,43.826492],"type":"Point"}
}