{
  "type": "Feature",
  "properties": {
    "addr:full":"394 King St E Toronto ON M5A 1K9",
    "addr:housenumber":"394",
    "addr:postcode":"m5a 1k9",
    "addr:street":"King St E",
    "iso:country":"CA",
    "sg:address":"394 King St E",
    "sg:city":"Toronto",
    "sg:classifiers":[
        {
            "category":"Real Estate",
            "subcategory":"Architect",
            "type":"Services"
        }
    ],
    "sg:phone":"+1 416 364 5710",
    "sg:postcode":"M5A 1K9",
    "sg:province":"ON",
    "wof:name":"Thomas Brown Architects Inc",
    "wof:placetype":"venue"
},
  "geometry": {"coordinates":[-79.3610992432,43.6540184021],"type":"Point"}
}