{
  "type": "Feature",
  "properties": {
    "addr:full":"Prince George BC V2N 1V7",
    "addr:postcode":"v2n 1v7",
    "iso:country":"CA",
    "sg:city":"Prince George",
    "sg:classifiers":[
        {
            "category":"Professional",
            "subcategory":"Management & Consulting",
            "type":"Services"
        }
    ],
    "sg:phone":"+1 250 564 1702",
    "sg:postcode":"V2N 1V7",
    "sg:province":"BC",
    "sg:tags":[
        "consultant",
        "business"
    ],
    "wof:name":"Ivan Andersen Holdings Ltd",
    "wof:placetype":"venue"
},
  "geometry": {"coordinates":[-122.78715515099999,53.9097442627],"type":"Point"}
}