{
  "type": "Feature",
  "properties": {
    "addr:full":"22 Higgins Bay Regina SK S4R 6B6",
    "addr:housenumber":"22",
    "addr:postcode":"s4r 6b6",
    "addr:street":"Higgins Bay",
    "iso:country":"CA",
    "sg:address":"22 Higgins Bay",
    "sg:city":"Regina",
    "sg:classifiers":[
        {
            "category":"Personal",
            "type":"Services"
        }
    ],
    "sg:phone":"+1 306 533 5362",
    "sg:postcode":"S4R 6B6",
    "sg:province":"SK",
    "sg:tags":[
        "electrolysis"
    ],
    "wof:name":"Looking Glass",
    "wof:placetype":"venue"
},
  "geometry": {"coordinates":[-104.60470581,50.4882125854],"type":"Point"}
}