{
  "type": "Feature",
  "properties": {
    "addr:full":"106 Rue Principale Saint-Irenee QC G0T 1V0",
    "addr:housenumber":"106",
    "addr:postcode":"g0t 1v0",
    "addr:street":"Rue Principale",
    "iso:country":"CA",
    "sg:address":"106 Rue Principale",
    "sg:city":"Saint-Irenee",
    "sg:classifiers":[
        {
            "category":"Shopping",
            "subcategory":"Hobbies, Toys, & Games",
            "type":"Retail Goods"
        }
    ],
    "sg:phone":"+1 418 452 3518",
    "sg:postcode":"G0T 1V0",
    "sg:province":"QC",
    "sg:tags":[
        "craft"
    ],
    "wof:name":"Idee Forgee",
    "wof:placetype":"venue"
},
  "geometry": {"coordinates":[-70.2086715698,47.5715026855],"type":"Point"}
}