{
  "type": "Feature",
  "properties": {
    "addr:full":"2500 Boul Casavant O Saint-Hyacinthe QC J2S 7R8",
    "addr:housenumber":"2500",
    "addr:postcode":"j2s 7r8",
    "addr:street":"Boul Casavant O",
    "iso:country":"CA",
    "sg:address":"2500 Boul Casavant O",
    "sg:city":"Saint-Hyacinthe",
    "sg:classifiers":[
        {
            "category":"Banks & Credit Unions",
            "subcategory":"Investment Brokerage",
            "type":"Services"
        }
    ],
    "sg:phone":"+1 450 261 0777",
    "sg:postcode":"J2S 7R8",
    "sg:province":"QC",
    "sg:tags":[
        "stock",
        "broker",
        "bond"
    ],
    "wof:name":"Groupe Option Retraite",
    "wof:placetype":"venue"
},
  "geometry": {"coordinates":[-72.96942138670001,45.6329154968],"type":"Point"}
}