{
  "type": "Feature",
  "properties": {
    "addr:full":"111 Maurice Dr Oakville ON L6K 2W6",
    "addr:housenumber":"111",
    "addr:postcode":"l6k 2w6",
    "addr:street":"Maurice Dr",
    "iso:country":"CA",
    "sg:address":"111 Maurice Dr",
    "sg:city":"Oakville",
    "sg:classifiers":[
        {
            "category":"Food & Beverages",
            "subcategory":"Groceries & Convenience Stores",
            "type":"Retail Goods"
        }
    ],
    "sg:phone":"+1 905 842 2269",
    "sg:postcode":"L6K 2W6",
    "sg:province":"ON",
    "sg:tags":[
        "grocer"
    ],
    "wof:name":"Mac's Convenience Stores Ltd",
    "wof:placetype":"venue"
},
  "geometry": {"coordinates":[-79.678223,43.437096],"type":"Point"}
}