{
  "type": "Feature",
  "properties": {
    "addr:full":"1754 Ch Du Clocher L'Acadie QC J2Y 1C8",
    "addr:postcode":"1754;j2y 1c8",
    "addr:street":"Ch Du Clocher",
    "iso:country":"CA",
    "sg:address":"1754 Ch Du Clocher",
    "sg:city":"L'Acadie",
    "sg:classifiers":[
        {
            "category":"Building & Trades",
            "subcategory":"Construction",
            "type":"Services"
        }
    ],
    "sg:phone":"+1 450 542 9050",
    "sg:postcode":"J2Y 1C8",
    "sg:province":"QC",
    "sg:tags":[
        "excavating",
        "contractor",
        "general"
    ],
    "wof:name":"Entreprises Lcg",
    "wof:placetype":"venue"
},
  "geometry": {"coordinates":[-73.35964199999999,45.312496],"type":"Point"}
}