{
  "type": "Feature",
  "properties": {
    "addr:full":"100 Rue Principale Saint-Edouard-DE-Napierville QC J0L 1Y0",
    "addr:housenumber":"100",
    "addr:postcode":"j0l 1y0",
    "addr:street":"Rue Principale",
    "iso:country":"CA",
    "sg:address":"100 Rue Principale",
    "sg:city":"Saint-Edouard-DE-Napierville",
    "sg:classifiers":[
        {
            "category":"Home & Garden",
            "subcategory":"Garden Supply",
            "type":"Retail Goods"
        }
    ],
    "sg:phone":"+1 450 454 4533",
    "sg:postcode":"J0L 1Y0",
    "sg:province":"QC",
    "sg:tags":[
        "engine"
    ],
    "wof:name":"Garage Thibert Inc",
    "wof:placetype":"venue"
},
  "geometry": {"coordinates":[-73.5099639893,45.2393455505],"type":"Point"}
}