{
  "type": "Feature",
  "properties": {
    "addr:full":"120 Boul Des Bois-Francs N Victoriaville QC G6P 1E7",
    "addr:housenumber":"120",
    "addr:postcode":"g6p 1e7",
    "addr:street":"Boul Des Bois-Francs N",
    "iso:country":"CA",
    "sg:address":"120 Boul Des Bois-Francs N",
    "sg:city":"Victoriaville",
    "sg:classifiers":[
        {
            "category":"Restaurant",
            "type":"Food & Drink"
        }
    ],
    "sg:phone":"+1 819 758 4955",
    "sg:postcode":"G6P 1E7",
    "sg:province":"QC",
    "wof:name":"Paradis D'Asie Inc",
    "wof:placetype":"venue"
},
  "geometry": {"coordinates":[-71.954071,46.060234],"type":"Point"}
}