{
  "type": "Feature",
  "properties": {
    "addr:full":"Edmonton AB T6K 4B6",
    "addr:postcode":"t6k 4b6",
    "iso:country":"CA",
    "sg:city":"Edmonton",
    "sg:classifiers":[
        {
            "category":"Shopping",
            "subcategory":"Luggage & Leather Goods",
            "type":"Retail Goods"
        }
    ],
    "sg:phone":"+1 780 490 6099",
    "sg:postcode":"T6K 4B6",
    "sg:province":"AB",
    "wof:name":"Bentley Leather & Luggage",
    "wof:placetype":"venue"
},
  "geometry": {"coordinates":[-113.434273,53.454388],"type":"Point"}
}