{
  "type": "Feature",
  "properties": {
    "iso:country":"CA",
    "sg:address":"4478 Chesswood Dr",
    "sg:city":"North York",
    "sg:classifiers":[
        {
            "category":"Manufacturing",
            "subcategory":"Tools & Machinery",
            "type":"Manufacturing & Wholesale Goods"
        }
    ],
    "sg:phone":"+1 416 398 9446",
    "sg:postcode":"M3J 2B9",
    "sg:province":"ON",
    "sg:tags":[
        "machine"
    ],
    "wof:name":"Canada Broach",
    "wof:placetype":"venue"
},
  "geometry": {"coordinates":[-79.4765167236,43.7629852295],"type":"Point"}
}