{
  "type": "Feature",
  "properties": {
    "addr:full":"19300 Centre St Mount Albert ON L0G 1M0",
    "addr:housenumber":"19300",
    "addr:postcode":"l0g 1m0",
    "addr:street":"Centre St",
    "iso:country":"CA",
    "sg:address":"19300 Centre St",
    "sg:city":"Mount Albert",
    "sg:classifiers":[
        {
            "category":"Education",
            "subcategory":"Library",
            "type":"Public Place"
        }
    ],
    "sg:phone":"+1 905 473 2472",
    "sg:postcode":"L0G 1M0",
    "sg:province":"ON",
    "wof:name":"East Gwillimbury Public",
    "wof:placetype":"venue"
},
  "geometry": {"coordinates":[-79.309555,44.140308],"type":"Point"}
}