{
  "type": "Feature",
  "properties": {
    "iso:country":"CA",
    "sg:city":"Winnipeg",
    "sg:classifiers":[
        {
            "category":"Professional",
            "subcategory":"Computer Services",
            "type":"Services"
        }
    ],
    "sg:phone":"+1 204 480 3003",
    "sg:postcode":"R3B 1Y6",
    "sg:province":"MB",
    "sg:tags":[
        "repair"
    ],
    "wof:name":"Northern Computer Solutions",
    "wof:placetype":"venue"
},
  "geometry": {"coordinates":[-97.15036,49.893829],"type":"Point"}
}