{
  "type": "Feature",
  "properties": {
    "addr:full":"561 David St Victoria BC V8T 2C7",
    "addr:housenumber":"561",
    "addr:postcode":"v8t 2c7",
    "addr:street":"David St",
    "iso:country":"CA",
    "sg:address":"561 David St",
    "sg:city":"Victoria",
    "sg:classifiers":[
        {
            "category":"Retail",
            "subcategory":"Auto Repair",
            "type":"Services"
        }
    ],
    "sg:phone":"+1 250 380 0288",
    "sg:postcode":"V8T 2C7",
    "sg:province":"BC",
    "sg:tags":[
        "repairing",
        "automobile"
    ],
    "wof:name":"Mike's Auto Repair",
    "wof:placetype":"venue"
},
  "geometry": {"coordinates":[-123.371559143,48.4380302429],"type":"Point"}
}