{
  "type": "Feature",
  "properties": {
    "addr:full":"6291 Groveland Dr Nanaimo BC V9V 1B2",
    "addr:housenumber":"6291",
    "addr:postcode":"v9v 1b2",
    "addr:street":"Groveland Dr",
    "iso:country":"CA",
    "sg:address":"6291 Groveland Dr",
    "sg:city":"Nanaimo",
    "sg:classifiers":[
        {
            "category":"Restaurant",
            "type":"Food & Drink"
        }
    ],
    "sg:phone":"+1 250 756 2382",
    "sg:postcode":"V9V 1B2",
    "sg:province":"BC",
    "wof:name":"Beefeater's Chop House & Grill",
    "wof:placetype":"venue"
},
  "geometry": {"coordinates":[-124.03894805900001,49.2446937561],"type":"Point"}
}