{
  "type": "Feature",
  "properties": {
    "addr:full":"10 Plastics Ave Etobicoke ON M8Z 4B7",
    "addr:housenumber":"10",
    "addr:postcode":"m8z 4b7",
    "addr:street":"Plastics Ave",
    "iso:country":"CA",
    "sg:address":"10 Plastics Ave",
    "sg:city":"Etobicoke",
    "sg:classifiers":[
        {
            "category":"Manufacturing",
            "subcategory":"Food",
            "type":"Manufacturing & Wholesale Goods"
        }
    ],
    "sg:phone":"+1 416 255 0416",
    "sg:postcode":"M8Z 4B7",
    "sg:province":"ON",
    "sg:tags":[
        "baker",
        "cookie",
        "bakery"
    ],
    "wof:name":"Shasha Bread CO",
    "wof:placetype":"venue"
},
  "geometry": {"coordinates":[-79.509918,43.624142],"type":"Point"}
}