{
  "type": "Feature",
  "properties": {
    "addr:full":"164 Pitt St Cornwall ON K6J 3P4",
    "addr:housenumber":"164",
    "addr:postcode":"k6j 3p4",
    "addr:street":"Pitt St",
    "iso:country":"CA",
    "sg:address":"164 Pitt St",
    "sg:city":"Cornwall",
    "sg:classifiers":[
        {
            "category":"Shopping",
            "subcategory":"Computers & Home Electronics",
            "type":"Retail Goods"
        }
    ],
    "sg:phone":"+1 613 933 0110",
    "sg:postcode":"K6J 3P4",
    "sg:province":"ON",
    "sg:tags":[
        "equipment",
        "dealer"
    ],
    "wof:name":"J L Computer",
    "wof:placetype":"venue"
},
  "geometry": {"coordinates":[-74.72857666020001,45.0176887512],"type":"Point"}
}