{
  "type": "Feature",
  "properties": {
    "addr:full":"15185 Yonge St Aurora ON L4G 1L8",
    "addr:housenumber":"15185",
    "addr:postcode":"l4g 1l8",
    "addr:street":"Yonge St",
    "iso:country":"CA",
    "sg:address":"15185 Yonge St",
    "sg:city":"Aurora",
    "sg:classifiers":[
        {
            "category":"Health Services",
            "subcategory":"Doctor",
            "type":"Services"
        }
    ],
    "sg:phone":"+1 905 727 1989",
    "sg:postcode":"L4G 1L8",
    "sg:province":"ON",
    "sg:tags":[
        "dentist"
    ],
    "wof:name":"Farquhar, Russ DDS",
    "wof:placetype":"venue"
},
  "geometry": {"coordinates":[-79.4670410156,43.998298645],"type":"Point"}
}