{
  "type": "Feature",
  "properties": {
    "addr:full":"528 Cassells St North Bay ON P1B 3Z7",
    "addr:housenumber":"528",
    "addr:postcode":"p1b 3z7",
    "addr:street":"Cassells St",
    "iso:country":"CA",
    "sg:address":"528 Cassells St",
    "sg:city":"North Bay",
    "sg:classifiers":[
        {
            "category":"Real Estate",
            "subcategory":"Architect",
            "type":"Services"
        }
    ],
    "sg:phone":"+1 705 472 0980",
    "sg:postcode":"P1B 3Z7",
    "sg:province":"ON",
    "wof:name":"Critchley Delean Trussler",
    "wof:placetype":"venue"
},
  "geometry": {"coordinates":[-79.46421051030001,46.3145980835],"type":"Point"}
}