{
  "type": "Feature",
  "properties": {
    "addr:full":"1588 Finfar Crt Mississauga ON L5J 4K1",
    "addr:housenumber":"1588",
    "addr:postcode":"l5j 4k1",
    "addr:street":"Finfar Crt",
    "iso:country":"CA",
    "sg:address":"1588 Finfar Crt",
    "sg:city":"Mississauga",
    "sg:classifiers":[
        {
            "category":"Shopping",
            "subcategory":"Florist",
            "type":"Retail Goods"
        }
    ],
    "sg:phone":"+1 905 855 2922",
    "sg:postcode":"L5J 4K1",
    "sg:province":"ON",
    "wof:name":"CEO Floral Svc",
    "wof:placetype":"venue"
},
  "geometry": {"coordinates":[-79.65284,43.517765],"type":"Point"}
}