{
  "type": "Feature",
  "properties": {
    "addr:full":"1752 Fir St Prince George BC V2L 1E7",
    "addr:housenumber":"1752",
    "addr:postcode":"v2l 1e7",
    "addr:street":"Fir St",
    "iso:country":"CA",
    "sg:address":"1752 Fir St",
    "sg:city":"Prince George",
    "sg:classifiers":[
        {
            "category":"Professional",
            "subcategory":"Employment Agencies",
            "type":"Services"
        }
    ],
    "sg:phone":"+1 250 561 9197",
    "sg:postcode":"V2L 1E7",
    "sg:province":"BC",
    "sg:tags":[
        "opportunity"
    ],
    "wof:name":"Centre D'Emploi Francophone",
    "wof:placetype":"venue"
},
  "geometry": {"coordinates":[-122.736419678,53.9083557129],"type":"Point"}
}