{
  "type": "Feature",
  "properties": {
    "addr:full":"100 Mcculloch Dr Espanola ON P5E 1J1",
    "addr:housenumber":"100",
    "addr:postcode":"p5e 1j1",
    "addr:street":"Mcculloch Dr",
    "iso:country":"CA",
    "sg:address":"100 Mcculloch Dr",
    "sg:city":"Espanola",
    "sg:classifiers":[
        {
            "category":"Building & Trades",
            "subcategory":"Construction",
            "type":"Services"
        }
    ],
    "sg:phone":"+1 705 869 3440",
    "sg:postcode":"P5E 1J1",
    "sg:province":"ON",
    "sg:tags":[
        "general",
        "contractor"
    ],
    "wof:name":"G F Freeman Construction Ltd",
    "wof:placetype":"venue"
},
  "geometry": {"coordinates":[-81.7551193237,46.2479782104],"type":"Point"}
}