{
  "type": "Feature",
  "properties": {
    "addr:full":"3083 Bathurst St North York ON M6A 2A3",
    "addr:housenumber":"3083",
    "addr:postcode":"m6a 2a3",
    "addr:street":"Bathurst St",
    "iso:country":"CA",
    "sg:address":"3083 Bathurst St",
    "sg:city":"North York",
    "sg:classifiers":[
        {
            "category":"Banks & Credit Unions",
            "subcategory":"Bank",
            "type":"Services"
        }
    ],
    "sg:phone":"+1 416 785 3117",
    "sg:postcode":"M6A 2A3",
    "sg:province":"ON",
    "sg:tags":[
        "cashing",
        "check"
    ],
    "wof:name":"Money Mart",
    "wof:placetype":"venue"
},
  "geometry": {"coordinates":[-79.4297790527,43.7202072144],"type":"Point"}
}