{
  "type": "Feature",
  "properties": {
    "iso:country":"CA",
    "sg:address":"6505 Rte Transcanadienne",
    "sg:city":"Saint-Laurent",
    "sg:classifiers":[
        {
            "category":"Restaurant",
            "type":"Food & Drink"
        }
    ],
    "sg:phone":"+1 514 748 0929",
    "sg:postcode":"H4T 1S3",
    "sg:province":"QC",
    "sg:tags":[
        "shop",
        "coffee"
    ],
    "wof:name":"Cafe 6505",
    "wof:placetype":"venue"
},
  "geometry": {"coordinates":[-73.6894607544,45.4949836731],"type":"Point"}
}