{
  "type": "Feature",
  "properties": {
    "addr:full":"Highway 9 S Hudson Bay SK S0E 0Y0",
    "addr:postcode":"s0e 0y0",
    "addr:street":"Highway 9 S",
    "iso:country":"CA",
    "sg:address":"Highway 9 S",
    "sg:city":"Hudson Bay",
    "sg:classifiers":[
        {
            "category":"Real Estate",
            "subcategory":"Real Estate Operator",
            "type":"Services"
        }
    ],
    "sg:phone":"+1 306 865 2378",
    "sg:postcode":"S0E 0Y0",
    "sg:province":"SK",
    "sg:tags":[
        "mobile",
        "home",
        "community"
    ],
    "wof:name":"West Bay Trailer Court",
    "wof:placetype":"venue"
},
  "geometry": {"coordinates":[-102.38885500000001,52.862659],"type":"Point"}
}