{
  "type": "Feature",
  "properties": {
    "addr:full":"1932 Route 475 Saint-Edouard-DE-Kent NB E4S 4W9",
    "addr:housenumber":"1932",
    "addr:postcode":"e4s 4w9",
    "addr:street":"Route 475",
    "iso:country":"CA",
    "sg:address":"1932 Route 475",
    "sg:city":"Saint-Edouard-DE-Kent",
    "sg:classifiers":[
        {
            "category":"Recreation",
            "type":"Entertainment"
        }
    ],
    "sg:phone":"+1 506 743 2600",
    "sg:postcode":"E4S 4W9",
    "sg:province":"NB",
    "sg:tags":[
        "provincial",
        "parks"
    ],
    "wof:name":"Park Naturel Irving LA Dune",
    "wof:placetype":"venue"
},
  "geometry": {"coordinates":[-67.6262435913,46.530418396],"type":"Point"}
}