{
  "type": "Feature",
  "properties": {
    "addr:full":"Winkler MB R6W 1G3",
    "addr:postcode":"r6w 1g3",
    "iso:country":"CA",
    "sg:city":"Winkler",
    "sg:classifiers":[
        {
            "category":"Education",
            "subcategory":"College",
            "type":"Public Place"
        }
    ],
    "sg:phone":"+1 204 325 9672",
    "sg:postcode":"R6W 1G3",
    "sg:province":"MB",
    "sg:tags":[
        "academic",
        "school"
    ],
    "wof:name":"Red River College",
    "wof:placetype":"venue"
},
  "geometry": {"coordinates":[-97.9390869141,49.1865577698],"type":"Point"}
}