{
  "type": "Feature",
  "properties": {
    "addr:full":"124 Oakside Bay SW Calgary AB T2V 4P2",
    "addr:housenumber":"124",
    "addr:postcode":"t2v 4p2",
    "addr:street":"Oakside Bay Sw",
    "iso:country":"CA",
    "sg:address":"124 Oakside Bay SW",
    "sg:city":"Calgary",
    "sg:classifiers":[
        {
            "category":"Real Estate",
            "subcategory":"Real Estate Agent",
            "type":"Services"
        }
    ],
    "sg:phone":"+1 403 251 0377",
    "sg:postcode":"T2V 4P2",
    "sg:province":"AB",
    "sg:tags":[
        "management"
    ],
    "wof:name":"Amira Developments Ltd",
    "wof:placetype":"venue"
},
  "geometry": {"coordinates":[-114.12597700000001,50.970345],"type":"Point"}
}