{
  "type": "Feature",
  "properties": {
    "addr:full":"2477 Trans Canada Hwy E Kamloops BC V2C 4A9",
    "addr:housenumber":"2477",
    "addr:postcode":"bc v2c 4a9",
    "addr:street":"Trans Canada Hwy E",
    "iso:country":"CA",
    "sg:address":"2477 Trans Canada Hwy E",
    "sg:city":"Kamloops",
    "sg:classifiers":[
        {
            "category":"Autos & Motor Vehicles",
            "subcategory":"Automobile Sales",
            "type":"Retail Goods"
        }
    ],
    "sg:phone":"+1 250 372 5588",
    "sg:postcode":"V2C 4A9",
    "sg:province":"BC",
    "sg:tags":[
        "car",
        "dealer"
    ],
    "wof:name":"Rivershore Chrysler Dodge Jeep",
    "wof:placetype":"venue"
},
  "geometry": {"coordinates":[-120.248771667,50.6762695312],"type":"Point"}
}