{
  "type": "Feature",
  "properties": {
    "addr:full":"551 Creditstone Rd Concord ON L4K 1N8",
    "addr:housenumber":"551",
    "addr:postcode":"l4k 1n8",
    "addr:street":"Creditstone Rd",
    "iso:country":"CA",
    "sg:address":"551 Creditstone Rd",
    "sg:city":"Concord",
    "sg:classifiers":[
        {
            "category":"Retail",
            "subcategory":"Auto Repair",
            "type":"Services"
        }
    ],
    "sg:phone":"+1 905 660 0412",
    "sg:postcode":"L4K 1N8",
    "sg:province":"ON",
    "sg:tags":[
        "automobile",
        "co",
        "appraiser",
        "transporter"
    ],
    "wof:name":"Sea Rail Cargo Surveys Ltd",
    "wof:placetype":"venue"
},
  "geometry": {"coordinates":[-79.5191421509,43.8021392822],"type":"Point"}
}