{
  "type": "Feature",
  "properties": {
    "addr:full":"46 Georges Forest Pl Winnipeg MB R2H 3H5",
    "addr:housenumber":"46",
    "addr:postcode":"r2h 3h5",
    "addr:street":"Georges Forest Pl",
    "iso:country":"CA",
    "sg:address":"46 Georges Forest Pl",
    "sg:city":"Winnipeg",
    "sg:classifiers":[
        {
            "category":"Professional",
            "subcategory":"Business Services",
            "type":"Services"
        }
    ],
    "sg:phone":"+1 204 233 7555",
    "sg:postcode":"R2H 3H5",
    "sg:province":"MB",
    "sg:tags":[
        "translator",
        "interpreter"
    ],
    "wof:name":"Jamais Vu Inc",
    "wof:placetype":"venue"
},
  "geometry": {"coordinates":[-97.10720825200001,49.8854598999],"type":"Point"}
}