{
  "type": "Feature",
  "properties": {
    "addr:full":"3045 Clayhill Rd Mississauga ON L5B 4L2",
    "addr:housenumber":"3045",
    "addr:postcode":"l5b 4l2",
    "addr:street":"Clayhill Rd",
    "iso:country":"CA",
    "sg:address":"3045 Clayhill Rd",
    "sg:city":"Mississauga",
    "sg:classifiers":[
        {
            "category":"Personal",
            "subcategory":"Beauty Salon",
            "type":"Services"
        }
    ],
    "sg:phone":"+1 905 276 0701",
    "sg:postcode":"L5B 4L2",
    "sg:province":"ON",
    "wof:name":"Hair Fitness",
    "wof:placetype":"venue"
},
  "geometry": {"coordinates":[-79.62915,43.571659],"type":"Point"}
}