{
  "type": "Feature",
  "properties": {
    "addr:full":"99 River St Toronto ON M5A 3P4",
    "addr:housenumber":"99",
    "addr:postcode":"m5a 3p4",
    "addr:street":"River St",
    "iso:country":"CA",
    "sg:address":"99 River St",
    "sg:city":"Toronto",
    "sg:classifiers":[
        {
            "category":"Professional",
            "subcategory":"Art Services",
            "type":"Services"
        }
    ],
    "sg:phone":"+1 416 861 8626",
    "sg:postcode":"M5A 3P4",
    "sg:province":"ON",
    "sg:tags":[
        "photographer"
    ],
    "wof:name":"Frank Tancredi Photography",
    "wof:placetype":"venue"
},
  "geometry": {"coordinates":[-79.3576965332,43.6602935791],"type":"Point"}
}