{
  "type": "Feature",
  "properties": {
    "addr:full":"Saint-Andre-DE-Kamouraska QC G0L 2H0",
    "addr:postcode":"g0l 2h0",
    "iso:country":"CA",
    "sg:city":"Saint-Andre-DE-Kamouraska",
    "sg:classifiers":[
        {
            "category":"Government",
            "subcategory":"Office",
            "type":"Public Place"
        }
    ],
    "sg:phone":"+1 418 493 2085",
    "sg:postcode":"G0L 2H0",
    "sg:province":"QC",
    "sg:tags":[
        "village"
    ],
    "wof:name":"St-Andre Municipal Office",
    "wof:placetype":"venue"
},
  "geometry": {"coordinates":[-69.733238,47.670952],"type":"Point"}
}