{
  "type": "Feature",
  "properties": {
    "addr:full":"1209 Prince St Hearst ON P0L 1N0",
    "addr:housenumber":"1209",
    "addr:postcode":"p0l 1n0",
    "addr:street":"Prince St",
    "iso:country":"CA",
    "sg:address":"1209 Prince St",
    "sg:city":"Hearst",
    "sg:classifiers":[
        {
            "category":"Shopping",
            "type":"Retail Goods"
        }
    ],
    "sg:phone":"+1 705 372 1321",
    "sg:postcode":"P0L 1N0",
    "sg:province":"ON",
    "sg:tags":[
        "monument"
    ],
    "wof:name":"Northern Monument Du Nord",
    "wof:placetype":"venue"
},
  "geometry": {"coordinates":[-83.673149,49.688465],"type":"Point"}
}