{
  "type": "Feature",
  "properties": {
    "iso:country":"CA",
    "sg:address":"6075 Mavis Rd # 6",
    "sg:city":"Mississauga",
    "sg:classifiers":[
        {
            "category":"Shopping",
            "subcategory":"Shoes",
            "type":"Retail Goods"
        }
    ],
    "sg:phone":"+1 905 507 0449",
    "sg:postcode":"L5R 4G6",
    "sg:province":"ON",
    "wof:name":"Kodiak & Iseco",
    "wof:placetype":"venue"
},
  "geometry": {"coordinates":[-79.697456,43.61364],"type":"Point"}
}