{
  "type": "Feature",
  "properties": {
    "iso:country":"CA",
    "sg:city":"Verdun",
    "sg:classifiers":[
        {
            "category":"Retail",
            "subcategory":"Auto Repair",
            "type":"Services"
        }
    ],
    "sg:phone":"+1 514 639 0005",
    "sg:postcode":"H4G 2V5",
    "sg:province":"QC",
    "sg:tags":[
        "automobile",
        "electric"
    ],
    "wof:name":"Traxx Technologies",
    "wof:placetype":"venue"
},
  "geometry": {"coordinates":[-73.56949615480001,45.4583702087],"type":"Point"}
}