{
  "type": "Feature",
  "properties": {
    "addr:full":"807 Garner Rd E Ancaster ON L9G 3K9",
    "addr:housenumber":"807",
    "addr:postcode":"l9g 3k9",
    "addr:street":"Garner Rd E",
    "iso:country":"CA",
    "sg:address":"807 Garner Rd E",
    "sg:city":"Ancaster",
    "sg:classifiers":[
        {
            "category":"Building & Trades",
            "subcategory":"Landscaping Services",
            "type":"Services"
        }
    ],
    "sg:phone":"+1 905 545 2313",
    "sg:postcode":"L9G 3K9",
    "sg:province":"ON",
    "sg:tags":[
        "excavating",
        "landscape",
        "contractor"
    ],
    "wof:name":"Ciccarelli & Sons Contracting",
    "wof:placetype":"venue"
},
  "geometry": {"coordinates":[-79.946175,43.207756],"type":"Point"}
}