{
  "type": "Feature",
  "properties": {
    "addr:full":"10126 101st Ave Lac LA Biche AB T0A 2C0",
    "addr:housenumber":"10126",
    "addr:postcode":"t0a 2c0",
    "addr:street":"101St Ave",
    "iso:country":"CA",
    "sg:address":"10126 101st Ave",
    "sg:city":"Lac LA Biche",
    "sg:classifiers":[
        {
            "category":"Banks & Credit Unions",
            "subcategory":"Bank",
            "type":"Services"
        }
    ],
    "sg:phone":"+1 780 623 4418",
    "sg:postcode":"T0A 2C0",
    "sg:province":"AB",
    "wof:name":"Cibc",
    "wof:placetype":"venue"
},
  "geometry": {"coordinates":[-111.97667694099999,54.7704391479],"type":"Point"}
}