{
  "type": "Feature",
  "properties": {
    "addr:full":"900 Av Bourdages N Saint-Hyacinthe QC J2S 5N9",
    "addr:housenumber":"900",
    "addr:postcode":"j2s 5n9",
    "addr:street":"Av Bourdages N",
    "iso:country":"CA",
    "sg:address":"900 Av Bourdages N",
    "sg:city":"Saint-Hyacinthe",
    "sg:classifiers":[
        {
            "category":"Real Estate",
            "subcategory":"Real Estate Agent",
            "type":"Services"
        }
    ],
    "sg:phone":"+1 450 773 1867",
    "sg:postcode":"J2S 5N9",
    "sg:province":"QC",
    "sg:tags":[
        "investment"
    ],
    "wof:name":"Placements Yvon Marcil Inc",
    "wof:placetype":"venue"
},
  "geometry": {"coordinates":[-72.9509887695,45.6242980957],"type":"Point"}
}