{
  "type": "Feature",
  "properties": {
    "addr:full":"120 Banbury Rd North York ON M3B 2L3",
    "addr:housenumber":"120",
    "addr:postcode":"m3b 2l3",
    "addr:street":"Banbury Rd",
    "iso:country":"CA",
    "sg:address":"120 Banbury Rd",
    "sg:city":"North York",
    "sg:classifiers":[
        {
            "category":"Recreation",
            "type":"Entertainment"
        }
    ],
    "sg:phone":"+1 416 395 7845",
    "sg:postcode":"M3B 2L3",
    "sg:province":"ON",
    "sg:tags":[
        "government",
        "village",
        "hall",
        "auditorium"
    ],
    "wof:name":"Banbury Community Rec Ctr",
    "wof:placetype":"venue"
},
  "geometry": {"coordinates":[-79.368797,43.742764],"type":"Point"}
}