{
  "type": "Feature",
  "properties": {
    "addr:full":"70 Boul Du Seminaire N Saint-Jean-Sur-Richelieu QC J3B 5J7",
    "addr:housenumber":"70",
    "addr:postcode":"j3b 5j7",
    "addr:street":"Boul Du Seminaire N",
    "iso:country":"CA",
    "sg:address":"70 Boul Du Seminaire N",
    "sg:city":"Saint-Jean-Sur-Richelieu",
    "sg:classifiers":[
        {
            "category":"Retail",
            "subcategory":"Car Wash",
            "type":"Services"
        }
    ],
    "sg:phone":"+1 450 347 7274",
    "sg:postcode":"J3B 5J7",
    "sg:province":"QC",
    "sg:tags":[
        "polishing",
        "washing"
    ],
    "wof:name":"Petrole Du Quebec",
    "wof:placetype":"venue"
},
  "geometry": {"coordinates":[-73.26683,45.30151],"type":"Point"}
}