{
  "type": "Feature",
  "properties": {
    "iso:country":"CA",
    "sg:address":"37 Belair Way",
    "sg:city":"Woodbridge",
    "sg:classifiers":[
        {
            "category":"Building & Trades",
            "subcategory":"Cleaning & Sanitation",
            "type":"Services"
        }
    ],
    "sg:phone":"+1 905 850 0645",
    "sg:postcode":"L4L 7S6",
    "sg:province":"ON",
    "sg:tags":[
        "janitor"
    ],
    "wof:name":"New Way Maintenance",
    "wof:placetype":"venue"
},
  "geometry": {"coordinates":[-79.5565567017,43.8009109497],"type":"Point"}
}