{
  "type": "Feature",
  "properties": {
    "addr:full":"Tisdale SK S0E 1T0",
    "addr:postcode":"s0e 1t0",
    "addr:street":"Tisdale",
    "iso:country":"CA",
    "sg:city":"Tisdale",
    "sg:classifiers":[
        {
            "category":"Travel",
            "subcategory":"Hotels & Motels",
            "type":"Entertainment"
        }
    ],
    "sg:phone":"+1 306 873 2607",
    "sg:postcode":"S0E 1T0",
    "sg:province":"SK",
    "wof:name":"Park Motel",
    "wof:placetype":"venue"
},
  "geometry": {"coordinates":[-104.047623,52.841801],"type":"Point"}
}