{
  "type": "Feature",
  "properties": {
    "addr:full":"4546 Highway 35 N Cameron ON K0M 1G0",
    "addr:housenumber":"4546",
    "addr:postcode":"k0m 1g0",
    "addr:street":"Highway 35 N",
    "iso:country":"CA",
    "sg:address":"4546 Highway 35 N",
    "sg:city":"Cameron",
    "sg:classifiers":[
        {
            "category":"Recreation",
            "subcategory":"Marina",
            "type":"Entertainment"
        }
    ],
    "sg:phone":"+1 705 887 2664",
    "sg:postcode":"K0M 1G0",
    "sg:province":"ON",
    "wof:name":"Anchor Line Marine",
    "wof:placetype":"venue"
},
  "geometry": {"coordinates":[-78.774597168,44.4392433167],"type":"Point"}
}