{
  "type": "Feature",
  "properties": {
    "iso:country":"CA",
    "sg:address":"284 King St",
    "sg:city":"Spruce Grove",
    "sg:classifiers":[
        {
            "category":"Shopping",
            "subcategory":"Jewelry",
            "type":"Retail Goods"
        }
    ],
    "sg:phone":"+1 780 962 1704",
    "sg:postcode":"T7X 3A7",
    "sg:province":"AB",
    "sg:tags":[
        "jeweler"
    ],
    "wof:name":"Sokanne's",
    "wof:placetype":"venue"
},
  "geometry": {"coordinates":[-113.900283813,53.5438613892],"type":"Point"}
}