{
  "type": "Feature",
  "properties": {
    "iso:country":"CA",
    "sg:address":"14B30 Lakeshore Rd",
    "sg:city":"Wainfleet",
    "sg:classifiers":[
        {
            "category":"Organizations",
            "subcategory":"Religious Organization",
            "type":"Services"
        }
    ],
    "sg:phone":"+1 905 899 1218",
    "sg:postcode":"L0S 1V0",
    "sg:province":"ON",
    "sg:tags":[
        "church"
    ],
    "wof:name":"Morgan's Point United Church",
    "wof:placetype":"venue"
},
  "geometry": {"coordinates":[-79.2802658081,42.8738594055],"type":"Point"}
}