{
  "type": "Feature",
  "properties": {
    "addr:full":"240 Rue Saint-Jacques # 600 Lachine QC H8R 1E2",
    "addr:housenumber":"240",
    "addr:postcode":"h8r 1e2",
    "addr:street":"Rue Saint-Jacques # 600",
    "iso:country":"CA",
    "sg:address":"240 Rue Saint-Jacques # 600",
    "sg:city":"Lachine",
    "sg:classifiers":[
        {
            "category":"Professional",
            "subcategory":"Lawyer & Legal Services",
            "type":"Services"
        }
    ],
    "sg:phone":"+1 514 849 9265",
    "sg:postcode":"H8R 1E2",
    "sg:province":"QC",
    "sg:tags":[
        "attorney"
    ],
    "wof:name":"Houde, Jerome",
    "wof:placetype":"venue"
},
  "geometry": {"coordinates":[-73.64617200000001,45.444675],"type":"Point"}
}