{
  "type": "Feature",
  "properties": {
    "addr:full":"844 Red River Rd Thunder Bay ON P7B 1K2",
    "addr:housenumber":"844",
    "addr:postcode":"p7b 1k2",
    "addr:street":"Red River Rd",
    "iso:country":"CA",
    "sg:address":"844 Red River Rd",
    "sg:city":"Thunder Bay",
    "sg:classifiers":[
        {
            "category":"Real Estate",
            "subcategory":"Real Estate Operator",
            "type":"Services"
        }
    ],
    "sg:phone":"+1 807 767 5532",
    "sg:postcode":"P7B 1K2",
    "sg:province":"ON",
    "sg:tags":[
        "apartment"
    ],
    "wof:name":"Red River Towers",
    "wof:placetype":"venue"
},
  "geometry": {"coordinates":[-89.248009,48.445869],"type":"Point"}
}