{
  "type": "Feature",
  "properties": {
    "addr:full":"291 Edgeley Blvd Concord ON L4K 3Z4",
    "addr:housenumber":"291",
    "addr:postcode":"l4k 3z4",
    "addr:street":"Edgeley Blvd",
    "iso:country":"CA",
    "sg:address":"291 Edgeley Blvd",
    "sg:city":"Concord",
    "sg:classifiers":[
        {
            "category":"Building & Trades",
            "subcategory":"Construction",
            "type":"Services"
        }
    ],
    "sg:phone":"+1 905 760 0200",
    "sg:postcode":"L4K 3Z4",
    "sg:province":"ON",
    "sg:tags":[
        "masonry",
        "contractor"
    ],
    "wof:name":"Neivex Masonary Inc",
    "wof:placetype":"venue"
},
  "geometry": {"coordinates":[-79.53369140620001,43.7996253967],"type":"Point"}
}