{
  "type": "Feature",
  "properties": {
    "addr:full":"Fort St John BC V1J 2B3",
    "addr:postcode":"v1j 2b3",
    "iso:country":"CA",
    "sg:city":"Fort St John",
    "sg:classifiers":[
        {
            "category":"Mining & Drilling",
            "type":"Manufacturing & Wholesale Goods"
        }
    ],
    "sg:phone":"+1 250 787 2341",
    "sg:postcode":"V1J 2B3",
    "sg:province":"BC",
    "sg:tags":[
        "company",
        "oil"
    ],
    "wof:name":"Husky Oil Operations Ltd",
    "wof:placetype":"venue"
},
  "geometry": {"coordinates":[-120.849815369,56.2475776672],"type":"Point"}
}