{
  "type": "Feature",
  "properties": {
    "addr:full":"316 99 Ave Dawson Creek BC V1G 1S9",
    "addr:postcode":"v1g 1s9",
    "addr:street":"316 99 Ave",
    "iso:country":"CA",
    "sg:address":"316 99 Ave",
    "sg:city":"Dawson Creek",
    "sg:classifiers":[
        {
            "category":"Communications",
            "subcategory":"Film & Video Production",
            "type":"Services"
        }
    ],
    "sg:phone":"+1 250 782 3661",
    "sg:postcode":"V1G 1S9",
    "sg:province":"BC",
    "sg:tags":[
        "taping"
    ],
    "wof:name":"North East Productions",
    "wof:placetype":"venue"
},
  "geometry": {"coordinates":[-120.214996,55.762501],"type":"Point"}
}