{
  "type": "Feature",
  "properties": {
    "addr:full":"338 Valleymede Dr Richmond Hill ON L4B 2C9",
    "addr:housenumber":"338",
    "addr:postcode":"l4b 2c9",
    "addr:street":"Valleymede Dr",
    "iso:country":"CA",
    "sg:address":"338 Valleymede Dr",
    "sg:city":"Richmond Hill",
    "sg:classifiers":[
        {
            "category":"Real Estate",
            "subcategory":"Real Estate Agent",
            "type":"Services"
        }
    ],
    "sg:phone":"+1 905 886 0708",
    "sg:postcode":"L4B 2C9",
    "sg:province":"ON",
    "wof:name":"Winland Real Estate Svc Inc",
    "wof:placetype":"venue"
},
  "geometry": {"coordinates":[-79.39642333979999,43.8581504822],"type":"Point"}
}