{
  "type": "Feature",
  "properties": {
    "addr:full":"Mississauga ON L5S 1V4",
    "addr:postcode":"l5s 1v4",
    "iso:country":"CA",
    "sg:city":"Mississauga",
    "sg:classifiers":[
        {
            "category":"Shopping",
            "subcategory":"Gifts & Souvenirs",
            "type":"Retail Goods"
        }
    ],
    "sg:phone":"+1 905 673 7445",
    "sg:postcode":"L5S 1V4",
    "sg:province":"ON",
    "sg:tags":[
        "basket",
        "florist",
        "parcel"
    ],
    "wof:name":"Bloomie's Flowers & Gifts",
    "wof:placetype":"venue"
},
  "geometry": {"coordinates":[-79.6699752808,43.6808815002],"type":"Point"}
}