{
  "type": "Feature",
  "properties": {
    "iso:country":"CA",
    "sg:address":"9 Industrial Dr SE",
    "sg:city":"Redcliff",
    "sg:classifiers":[
        {
            "category":"Building & Trades",
            "subcategory":"Cleaning & Sanitation",
            "type":"Services"
        }
    ],
    "sg:phone":"+1 403 548 7144",
    "sg:postcode":"T0J 2P0",
    "sg:province":"AB",
    "sg:tags":[
        "management",
        "janitor",
        "real estate"
    ],
    "wof:name":"Renke Property Management Ltd",
    "wof:placetype":"venue"
},
  "geometry": {"coordinates":[-110.761054993,50.0749053955],"type":"Point"}
}