{
  "type": "Feature",
  "properties": {
    "addr:full":"6227 Bathurst St North York ON M2R 2A5",
    "addr:housenumber":"6227",
    "addr:postcode":"m2r 2a5",
    "addr:street":"Bathurst St",
    "iso:country":"CA",
    "sg:address":"6227 Bathurst St",
    "sg:city":"North York",
    "sg:classifiers":[
        {
            "category":"Health Services",
            "subcategory":"Doctor",
            "type":"Services"
        }
    ],
    "sg:phone":"+1 416 222 7044",
    "sg:postcode":"M2R 2A5",
    "sg:province":"ON",
    "sg:tags":[
        "physician",
        "surgeon"
    ],
    "wof:name":"Nadasdi, M MD",
    "wof:placetype":"venue"
},
  "geometry": {"coordinates":[-79.445206,43.791042],"type":"Point"}
}