{
  "type": "Feature",
  "properties": {
    "addr:full":"1701 Boul Wallberg Dolbeau-Mistassini QC G8L 1H7",
    "addr:housenumber":"1701",
    "addr:postcode":"g8l 1h7",
    "addr:street":"Boul Wallberg",
    "iso:country":"CA",
    "sg:address":"1701 Boul Wallberg",
    "sg:city":"Dolbeau-Mistassini",
    "sg:classifiers":[
        {
            "category":"Restaurant",
            "type":"Food & Drink"
        }
    ],
    "sg:phone":"+1 418 276 7071",
    "sg:postcode":"G8L 1H7",
    "sg:province":"QC",
    "wof:name":"Mikes Restaurant",
    "wof:placetype":"venue"
},
  "geometry": {"coordinates":[-72.23163599999999,48.880913],"type":"Point"}
}