{
  "type": "Feature",
  "properties": {
    "addr:full":"1510 Rue Michelin Laval QC H7L 4R3",
    "addr:housenumber":"1510",
    "addr:postcode":"h7l 4r3",
    "addr:street":"Rue Michelin",
    "iso:country":"CA",
    "sg:address":"1510 Rue Michelin",
    "sg:city":"Laval",
    "sg:classifiers":[
        {
            "category":"Wholesale",
            "subcategory":"Machinery & Supplies",
            "type":"Manufacturing & Wholesale Goods"
        }
    ],
    "sg:phone":"+1 450 688 5044",
    "sg:postcode":"H7L 4R3",
    "sg:province":"QC",
    "sg:tags":[
        "dyer",
        "cleaners",
        "equipment"
    ],
    "wof:name":"Topos Canada Inc",
    "wof:placetype":"venue"
},
  "geometry": {"coordinates":[-73.74762,45.589798],"type":"Point"}
}