{
  "type": "Feature",
  "properties": {
    "iso:country":"CA",
    "sg:address":"4857 Main St",
    "sg:city":"Vancouver",
    "sg:classifiers":[
        {
            "category":"Retail",
            "subcategory":"Repair Shop",
            "type":"Services"
        }
    ],
    "sg:phone":"+1 604 873 0881",
    "sg:postcode":"V5V 3R9",
    "sg:province":"BC",
    "sg:tags":[
        "television",
        "radio"
    ],
    "wof:name":"New World Tv & Sound Svc Ltd",
    "wof:placetype":"venue"
},
  "geometry": {"coordinates":[-123.101578,49.24123],"type":"Point"}
}