{
  "type": "Feature",
  "properties": {
    "addr:full":"121 11 St S Lethbridge AB T1J 4B8",
    "addr:housenumber":"121 11",
    "addr:postcode":"t1j 4b8",
    "addr:street":"St S",
    "iso:country":"CA",
    "sg:address":"121 11 St S",
    "sg:city":"Lethbridge",
    "sg:classifiers":[
        {
            "category":"Wholesale",
            "subcategory":"Electrical",
            "type":"Manufacturing & Wholesale Goods"
        }
    ],
    "sg:phone":"+1 403 328 0011",
    "sg:postcode":"T1J 4B8",
    "sg:province":"AB",
    "sg:tags":[
        "appliance"
    ],
    "wof:name":"Ron's Appliance Svc Ltd",
    "wof:placetype":"venue"
},
  "geometry": {"coordinates":[-112.830741882,49.6975097656],"type":"Point"}
}