{
  "type": "Feature",
  "properties": {
    "addr:full":"1102 Rosser Ave Brandon MB R7A 0L7",
    "addr:housenumber":"1102",
    "addr:postcode":"r7a 0l7",
    "addr:street":"Rosser Ave",
    "iso:country":"CA",
    "sg:address":"1102 Rosser Ave",
    "sg:city":"Brandon",
    "sg:classifiers":[
        {
            "category":"Professional",
            "subcategory":"Art Services",
            "type":"Services"
        }
    ],
    "sg:phone":"+1 204 571 4500",
    "sg:postcode":"R7A 0L7",
    "sg:province":"MB",
    "sg:tags":[
        "graphic",
        "designer"
    ],
    "wof:name":"Innovative Media Group",
    "wof:placetype":"venue"
},
  "geometry": {"coordinates":[-99.95298,49.848335],"type":"Point"}
}