{
  "type": "Feature",
  "properties": {
    "addr:full":"300 Elm Ave Jasper AB T0E 1E0",
    "addr:housenumber":"300",
    "addr:postcode":"t0e 1e0",
    "addr:street":"Elm Ave",
    "iso:country":"CA",
    "sg:address":"300 Elm Ave",
    "sg:city":"Jasper",
    "sg:classifiers":[
        {
            "category":"Education",
            "subcategory":"School",
            "type":"Public Place"
        }
    ],
    "sg:phone":"+1 780 852 4447",
    "sg:postcode":"T0E 1E0",
    "sg:province":"AB",
    "wof:name":"Jasper Elementary School",
    "wof:placetype":"venue"
},
  "geometry": {"coordinates":[-118.083832,52.87764],"type":"Point"}
}