{
  "type": "Feature",
  "properties": {
    "addr:full":"10101 101st St LA Crete AB T0H 2H0",
    "addr:housenumber":"10101",
    "addr:postcode":"t0h 2h0",
    "addr:street":"101St St",
    "iso:country":"CA",
    "sg:address":"10101 101st St",
    "sg:city":"LA Crete",
    "sg:classifiers":[
        {
            "category":"Travel",
            "subcategory":"Hotels & Motels",
            "type":"Entertainment"
        }
    ],
    "sg:phone":"+1 780 928 3806",
    "sg:postcode":"T0H 2H0",
    "sg:province":"AB",
    "wof:name":"LA Crete Motel",
    "wof:placetype":"venue"
},
  "geometry": {"coordinates":[-116.409637,58.20961],"type":"Point"}
}