{
  "type": "Feature",
  "properties": {
    "addr:full":"420 Prince St Sydney NS B1P 5K9",
    "addr:housenumber":"420",
    "addr:postcode":"b1p 5k9",
    "addr:street":"Prince St",
    "iso:country":"CA",
    "sg:address":"420 Prince St",
    "sg:city":"Sydney",
    "sg:classifiers":[
        {
            "category":"Autos & Motor Vehicles",
            "subcategory":"Automobile Sales",
            "type":"Retail Goods"
        }
    ],
    "sg:phone":"+1 902 562 4258",
    "sg:postcode":"B1P 5K9",
    "sg:province":"NS",
    "sg:tags":[
        "car",
        "dealer"
    ],
    "wof:name":"Used Car Value Mart",
    "wof:placetype":"venue"
},
  "geometry": {"coordinates":[-60.179909,46.140144],"type":"Point"}
}