{
  "type": "Feature",
  "properties": {
    "addr:full":"Tillsonburg ON N4G 4G8",
    "addr:postcode":"n4g 4g8",
    "iso:country":"CA",
    "sg:city":"Tillsonburg",
    "sg:classifiers":[
        {
            "category":"Shopping",
            "subcategory":"Computers & Home Electronics",
            "type":"Retail Goods"
        }
    ],
    "sg:phone":"+1 519 688 3667",
    "sg:postcode":"N4G 4G8",
    "sg:province":"ON",
    "sg:tags":[
        "equipment",
        "dealer"
    ],
    "wof:name":"Hitech Solutions Computer Syst",
    "wof:placetype":"venue"
},
  "geometry": {"coordinates":[-80.727867,42.860676],"type":"Point"}
}