{
  "type": "Feature",
  "properties": {
    "addr:full":"282 Rue Des Forges Trois-Rivieres QC G9A 2G8",
    "addr:housenumber":"282",
    "addr:postcode":"g9a 2g8",
    "addr:street":"Rue Des Forges Trois-Rivieres",
    "iso:country":"CA",
    "sg:address":"282 Rue Des Forges",
    "sg:city":"Trois-Rivieres",
    "sg:classifiers":[
        {
            "category":"Bars & Pubs",
            "type":"Food & Drink"
        }
    ],
    "sg:phone":"+1 819 694 4457",
    "sg:postcode":"G9A 2G8",
    "sg:province":"QC",
    "sg:tags":[
        "lounge",
        "cocktail"
    ],
    "wof:name":"Cafe Bar D'Artagnan's",
    "wof:placetype":"venue"
},
  "geometry": {"coordinates":[-72.5420837402,46.3422203064],"type":"Point"}
}