{
  "type": "Feature",
  "properties": {
    "addr:full":"3 Bestobell Rd Etobicoke ON M8W 4H2",
    "addr:housenumber":"3",
    "addr:postcode":"m8w 4h2",
    "addr:street":"Bestobell Rd",
    "iso:country":"CA",
    "sg:address":"3 Bestobell Rd",
    "sg:city":"Etobicoke",
    "sg:classifiers":[
        {
            "category":"Manufacturing",
            "subcategory":"Printing",
            "type":"Manufacturing & Wholesale Goods"
        }
    ],
    "sg:phone":"+1 416 259 1621",
    "sg:postcode":"M8W 4H2",
    "sg:province":"ON",
    "sg:tags":[
        "printer"
    ],
    "wof:name":"Pristine Printing",
    "wof:placetype":"venue"
},
  "geometry": {"coordinates":[-79.540161,43.612888],"type":"Point"}
}