{
  "type": "Feature",
  "properties": {
    "addr:full":"1915 Ch Sainte-Angelique Saint-Lazare QC J7T 2Y2",
    "addr:housenumber":"1915",
    "addr:postcode":"j7t 2y2",
    "addr:street":"Ch Sainte-Angelique",
    "iso:country":"CA",
    "sg:address":"1915 Ch Sainte-Angelique",
    "sg:city":"Saint-Lazare",
    "sg:classifiers":[
        {
            "category":"Home & Garden",
            "subcategory":"Furniture",
            "type":"Retail Goods"
        }
    ],
    "sg:phone":"+1 450 455 9393",
    "sg:postcode":"J7T 2Y2",
    "sg:province":"QC",
    "wof:name":"Ameublement Denis & Fils Ltee",
    "wof:placetype":"venue"
},
  "geometry": {"coordinates":[-74.139915,45.400215],"type":"Point"}
}