{
  "type": "Feature",
  "properties": {
    "addr:full":"Saint-Eustache QC J7P 2A7",
    "addr:postcode":"j7p 2a7",
    "iso:country":"CA",
    "sg:city":"Saint-Eustache",
    "sg:classifiers":[
        {
            "category":"Manufacturing",
            "subcategory":"Signs",
            "type":"Manufacturing & Wholesale Goods"
        }
    ],
    "sg:phone":"+1 450 472 5002",
    "sg:postcode":"J7P 2A7",
    "sg:province":"QC",
    "wof:name":"Studio DE Lettrage St-Eustache",
    "wof:placetype":"venue"
},
  "geometry": {"coordinates":[-73.895927,45.561417],"type":"Point"}
}