{
  "type": "Feature",
  "properties": {
    "addr:full":"Ingolf ON P0Y 1A0",
    "addr:postcode":"p0y 1a0",
    "addr:street":"Ingolf",
    "iso:country":"CA",
    "sg:city":"Ingolf",
    "sg:classifiers":[
        {
            "category":"Travel",
            "subcategory":"Hotels & Motels",
            "type":"Entertainment"
        }
    ],
    "sg:phone":"+1 807 733 3301",
    "sg:postcode":"P0Y 1A0",
    "sg:province":"ON",
    "sg:tags":[
        "resort"
    ],
    "wof:name":"Ingolf Inn",
    "wof:placetype":"venue"
},
  "geometry": {"coordinates":[-95.12414550779999,49.795539856],"type":"Point"}
}