{
  "type": "Feature",
  "properties": {
    "iso:country":"CA",
    "sg:address":"50 Mcnaughton Ave",
    "sg:city":"Wallaceburg",
    "sg:classifiers":[
        {
            "category":"Restaurant",
            "type":"Food & Drink"
        }
    ],
    "sg:phone":"+1 519 627 3376",
    "sg:postcode":"N8A 1R9",
    "sg:province":"ON",
    "wof:name":"Mc Donald's",
    "wof:placetype":"venue"
},
  "geometry": {"coordinates":[-82.3846664429,42.5876197815],"type":"Point"}
}