{
  "type": "Feature",
  "properties": {
    "addr:full":"2900 Boul DE Portland Sherbrooke QC J1L 1R8",
    "addr:housenumber":"2900",
    "addr:postcode":"j1l 1r8",
    "addr:street":"Boul De Portland",
    "iso:country":"CA",
    "sg:address":"2900 Boul DE Portland",
    "sg:city":"Sherbrooke",
    "sg:classifiers":[
        {
            "category":"Autos & Motor Vehicles",
            "subcategory":"Fuel & Gas Station",
            "type":"Retail Goods"
        }
    ],
    "sg:phone":"+1 819 569 0404",
    "sg:postcode":"J1L 1R8",
    "sg:province":"QC",
    "sg:tags":[
        "oil"
    ],
    "wof:name":"Esso",
    "wof:placetype":"venue"
},
  "geometry": {"coordinates":[-71.9473724365,45.403427124],"type":"Point"}
}