{
  "type": "Feature",
  "properties": {
    "iso:country":"CA",
    "sg:address":"1755 Plummer St # 17",
    "sg:city":"Pickering",
    "sg:classifiers":[
        {
            "category":"Home & Garden",
            "subcategory":"Building Materials",
            "type":"Retail Goods"
        }
    ],
    "sg:phone":"+1 905 839 2215",
    "sg:postcode":"L1W 3S1",
    "sg:province":"ON",
    "sg:tags":[
        "windows"
    ],
    "wof:name":"J & K Window Mfr Inc",
    "wof:placetype":"venue"
},
  "geometry": {"coordinates":[-79.069893,43.834465],"type":"Point"}
}