{
  "type": "Feature",
  "properties": {
    "addr:full":"176 Madrona Dr Galiano BC V0N 1P0",
    "addr:housenumber":"176",
    "addr:postcode":"v0n 1p0",
    "addr:street":"Madrona Dr",
    "iso:country":"CA",
    "sg:address":"176 Madrona Dr",
    "sg:city":"Galiano",
    "sg:classifiers":[
        {
            "category":"Shopping",
            "subcategory":"Books",
            "type":"Retail Goods"
        }
    ],
    "sg:phone":"+1 250 539 3340",
    "sg:postcode":"V0N 1P0",
    "sg:province":"BC",
    "sg:tags":[
        "dealer"
    ],
    "wof:name":"Galiano Island Books",
    "wof:placetype":"venue"
},
  "geometry": {"coordinates":[-123.31910705599999,48.877571106],"type":"Point"}
}