{
  "type": "Feature",
  "properties": {
    "addr:full":"467 Route 108 E Saint-Victor QC G0M 2B0",
    "addr:housenumber":"467",
    "addr:postcode":"g0m 2b0",
    "addr:street":"Route 108 E",
    "iso:country":"CA",
    "sg:address":"467 Route 108 E",
    "sg:city":"Saint-Victor",
    "sg:classifiers":[
        {
            "category":"Autos & Motor Vehicles",
            "subcategory":"Automobile Sales",
            "type":"Retail Goods"
        }
    ],
    "sg:phone":"+1 418 588 6647",
    "sg:postcode":"G0M 2B0",
    "sg:province":"QC",
    "sg:tags":[
        "car",
        "dealer"
    ],
    "wof:name":"Lessard, Marc",
    "wof:placetype":"venue"
},
  "geometry": {"coordinates":[-70.883904,46.162052],"type":"Point"}
}