{
  "type": "Feature",
  "properties": {
    "addr:full":"9003 100 Ave Fort St John BC V1J 1X5",
    "addr:housenumber":"9003",
    "addr:postcode":"v1j 1x5",
    "addr:street":"100 Ave",
    "iso:country":"CA",
    "sg:address":"9003 100 Ave",
    "sg:city":"Fort St John",
    "sg:classifiers":[
        {
            "category":"Food & Beverages",
            "subcategory":"Groceries & Convenience Stores",
            "type":"Retail Goods"
        }
    ],
    "sg:phone":"+1 250 785 9779",
    "sg:postcode":"V1J 1X5",
    "sg:province":"BC",
    "sg:tags":[
        "grocer"
    ],
    "wof:name":"Central Q-Mart",
    "wof:placetype":"venue"
},
  "geometry": {"coordinates":[-120.829475,56.24622],"type":"Point"}
}