{
  "type": "Feature",
  "properties": {
    "addr:full":"20450 Fraser Hwy #200 Langley BC V3A 4G2",
    "addr:housenumber":"20450",
    "addr:postcode":"v3a 4g2",
    "addr:street":"Fraser Hwy # 200",
    "iso:country":"CA",
    "sg:address":"20450 Fraser Hwy #200",
    "sg:city":"Langley",
    "sg:classifiers":[
        {
            "category":"Professional",
            "subcategory":"Lawyer & Legal Services",
            "type":"Services"
        }
    ],
    "sg:phone":"+1 604 530 3141",
    "sg:postcode":"V3A 4G2",
    "sg:province":"BC",
    "sg:tags":[
        "attorney"
    ],
    "wof:name":"Mac Donald Boyle & Jeffery",
    "wof:placetype":"venue"
},
  "geometry": {"coordinates":[-122.65517425500001,49.1042900085],"type":"Point"}
}