{
  "type": "Feature",
  "properties": {
    "addr:full":"207 Queens Quay W Toronto ON M5J 1A7",
    "addr:housenumber":"207",
    "addr:postcode":"m5j 1a7",
    "addr:street":"Queens Quay W",
    "iso:country":"CA",
    "sg:address":"207 Queens Quay W",
    "sg:city":"Toronto",
    "sg:classifiers":[
        {
            "category":"Shopping",
            "subcategory":"Gifts & Souvenirs",
            "type":"Retail Goods"
        }
    ],
    "sg:phone":"+1 416 203 0365",
    "sg:postcode":"M5J 1A7",
    "sg:province":"ON",
    "sg:tags":[
        "shop"
    ],
    "wof:name":"Canadian Naturalist",
    "wof:placetype":"venue"
},
  "geometry": {"coordinates":[-79.3806686401,43.6396141052],"type":"Point"}
}