{
  "type": "Feature",
  "properties": {
    "addr:full":"1709 King George Hwy Miramichi NB E1V 5L7",
    "addr:housenumber":"1709",
    "addr:postcode":"e1v 5l7",
    "addr:street":"King George Hwy",
    "iso:country":"CA",
    "sg:address":"1709 King George Hwy",
    "sg:city":"Miramichi",
    "sg:classifiers":[
        {
            "category":"Food & Beverages",
            "subcategory":"Groceries & Convenience Stores",
            "type":"Retail Goods"
        }
    ],
    "sg:phone":"+1 506 622 1661",
    "sg:postcode":"E1V 5L7",
    "sg:province":"NB",
    "wof:name":"Courtesy Convenience & Gas Bar",
    "wof:placetype":"venue"
},
  "geometry": {"coordinates":[-65.5325622559,47.0217628479],"type":"Point"}
}