{
  "type": "Feature",
  "properties": {
    "addr:full":"120 Oakmeadow Blvd Scarborough ON M1E 4G7",
    "addr:housenumber":"120",
    "addr:postcode":"m1e 4g7",
    "addr:street":"Oakmeadow Blvd",
    "iso:country":"CA",
    "sg:address":"120 Oakmeadow Blvd",
    "sg:city":"Scarborough",
    "sg:classifiers":[
        {
            "category":"Retail",
            "subcategory":"Laundry & Dry Cleaning",
            "type":"Services"
        }
    ],
    "sg:phone":"+1 416 283 3512",
    "sg:postcode":"M1E 4G7",
    "sg:province":"ON",
    "sg:tags":[
        "cleaners",
        "rug",
        "carpet"
    ],
    "wof:name":"Soft Surfaces",
    "wof:placetype":"venue"
},
  "geometry": {"coordinates":[-79.2194061279,43.7874908447],"type":"Point"}
}