{
  "type": "Feature",
  "properties": {
    "addr:full":"Fort St John BC V1J 2B4",
    "addr:postcode":"v1j 2b4",
    "iso:country":"CA",
    "sg:city":"Fort St John",
    "sg:classifiers":[
        {
            "category":"Professional",
            "subcategory":"Detective & Security Services",
            "type":"Services"
        }
    ],
    "sg:phone":"+1 250 787 7505",
    "sg:postcode":"V1J 2B4",
    "sg:province":"BC",
    "sg:tags":[
        "guard",
        "patrol"
    ],
    "wof:name":"Centurian Knights Safety",
    "wof:placetype":"venue"
},
  "geometry": {"coordinates":[-120.849754,56.247311],"type":"Point"}
}