{
  "type": "Feature",
  "properties": {
    "addr:full":"722 11 Ave SW Calgary AB T2R 0E4",
    "addr:housenumber":"722",
    "addr:postcode":"t2r 0e4",
    "addr:street":"11 Ave Sw",
    "iso:country":"CA",
    "sg:address":"722 11 Ave SW",
    "sg:city":"Calgary",
    "sg:classifiers":[
        {
            "category":"Shopping",
            "subcategory":"Books",
            "type":"Retail Goods"
        }
    ],
    "sg:phone":"+1 403 265 6066",
    "sg:postcode":"T2R 0E4",
    "sg:province":"AB",
    "sg:tags":[
        "grocer"
    ],
    "wof:name":"Cookbook CO Cooks",
    "wof:placetype":"venue"
},
  "geometry": {"coordinates":[-114.077194214,51.0428924561],"type":"Point"}
}