{
  "type": "Feature",
  "properties": {
    "addr:full":"19096 115th Rd N Gimli MB R0C 1B0",
    "addr:housenumber":"19096",
    "addr:postcode":"r0c 1b0",
    "addr:street":"115Th Rd N",
    "iso:country":"CA",
    "sg:address":"19096 115th Rd N",
    "sg:city":"Gimli",
    "sg:classifiers":[
        {
            "category":"Manufacturing",
            "subcategory":"Tools & Machinery",
            "type":"Manufacturing & Wholesale Goods"
        }
    ],
    "sg:phone":"+1 204 642 7687",
    "sg:postcode":"R0C 1B0",
    "sg:province":"MB",
    "sg:tags":[
        "equipment",
        "janitor"
    ],
    "wof:name":"Interlake Chemicals Ltd",
    "wof:placetype":"venue"
},
  "geometry": {"coordinates":[-96.9941864014,50.6368637085],"type":"Point"}
}