{
  "type": "Feature",
  "properties": {
    "addr:full":"431 2E Av Iberville QC J2X 2B7",
    "addr:housenumber":"431",
    "addr:postcode":"j2x 2b7",
    "addr:street":"2E Av",
    "iso:country":"CA",
    "sg:address":"431 2E Av",
    "sg:city":"Iberville",
    "sg:classifiers":[
        {
            "category":"Retail",
            "subcategory":"Laundry & Dry Cleaning",
            "type":"Services"
        }
    ],
    "sg:phone":"+1 450 346 5546",
    "sg:postcode":"J2X 2B7",
    "sg:province":"QC",
    "sg:tags":[
        "diaper"
    ],
    "wof:name":"Incontinence Plus",
    "wof:placetype":"venue"
},
  "geometry": {"coordinates":[-73.23086499999999,45.304073],"type":"Point"}
}