{
  "type": "Feature",
  "properties": {
    "iso:country":"CA",
    "sg:address":"288 Place Du Coteau",
    "sg:city":"Bois-Des-Filion",
    "sg:classifiers":[
        {
            "category":"Professional",
            "subcategory":"Business Services",
            "type":"Services"
        }
    ],
    "sg:phone":"+1 450 621 7771",
    "sg:postcode":"J6Z 3Y6",
    "sg:province":"QC",
    "sg:tags":[
        "translator",
        "interpreter"
    ],
    "wof:name":"Traductin Technique Louise",
    "wof:placetype":"venue"
},
  "geometry": {"coordinates":[-73.756538,45.680363],"type":"Point"}
}