{
  "type": "Feature",
  "properties": {
    "iso:country":"CA",
    "sg:address":"78 Pender St E",
    "sg:city":"Vancouver",
    "sg:classifiers":[
        {
            "category":"Shopping",
            "subcategory":"Books",
            "type":"Retail Goods"
        }
    ],
    "sg:phone":"+1 604 688 3785",
    "sg:postcode":"V6A 1T1",
    "sg:province":"BC",
    "sg:tags":[
        "dealer"
    ],
    "wof:name":"Sino United Publishing Ltd",
    "wof:placetype":"venue"
},
  "geometry": {"coordinates":[-123.10272999999999,49.280308],"type":"Point"}
}