{
  "type": "Feature",
  "properties": {
    "addr:full":"259 Albert St Kingston ON K7L 3V4",
    "addr:housenumber":"259",
    "addr:postcode":"k7l 3v4",
    "addr:street":"Albert St",
    "iso:country":"CA",
    "sg:address":"259 Albert St",
    "sg:city":"Kingston",
    "sg:classifiers":[
        {
            "category":"Social Services",
            "subcategory":"Child Care",
            "type":"Services"
        }
    ],
    "sg:phone":"+1 613 531 7957",
    "sg:postcode":"K7L 3V4",
    "sg:province":"ON",
    "wof:name":"Rocking Horse Day Care",
    "wof:placetype":"venue"
},
  "geometry": {"coordinates":[-76.499855,44.229572],"type":"Point"}
}