{
  "type": "Feature",
  "properties": {
    "addr:full":"11 Mission Rd Wawa ON P0S 1K0",
    "addr:housenumber":"11",
    "addr:postcode":"p0s 1k0",
    "addr:street":"Mission Rd",
    "iso:country":"CA",
    "sg:address":"11 Mission Rd",
    "sg:city":"Wawa",
    "sg:classifiers":[
        {
            "category":"Building & Trades",
            "subcategory":"Equipment Rental",
            "type":"Services"
        }
    ],
    "sg:phone":"+1 705 856 4233",
    "sg:postcode":"P0S 1K0",
    "sg:province":"ON",
    "sg:tags":[
        "aircraft",
        "leasing",
        "charter"
    ],
    "wof:name":"Watson's Skyways Ltd",
    "wof:placetype":"venue"
},
  "geometry": {"coordinates":[-84.77233886720001,47.9910011292],"type":"Point"}
}