{
  "type": "Feature",
  "properties": {
    "addr:full":"Vancouver BC V6E 3V7",
    "addr:postcode":"v6e 3v7",
    "iso:country":"CA",
    "sg:city":"Vancouver",
    "sg:classifiers":[
        {
            "category":"Health Services",
            "subcategory":"Doctor",
            "type":"Services"
        }
    ],
    "sg:phone":"+1 604 689 8505",
    "sg:postcode":"V6E 3V7",
    "sg:province":"BC",
    "sg:tags":[
        "dentist"
    ],
    "wof:name":"Yau, Bernard G DDS",
    "wof:placetype":"venue"
},
  "geometry": {"coordinates":[-123.122986,49.28548],"type":"Point"}
}