{
  "type": "Feature",
  "properties": {
    "iso:country":"CA",
    "sg:city":"Mississauga",
    "sg:classifiers":[
        {
            "category":"Education",
            "subcategory":"Dance Studio",
            "type":"Public Place"
        }
    ],
    "sg:phone":"+1 905 564 2139",
    "sg:postcode":"L5T 1H8",
    "sg:province":"ON",
    "sg:tags":[
        "instruction",
        "dancing"
    ],
    "wof:name":"Canadian Dance Teachers Assn",
    "wof:placetype":"venue"
},
  "geometry": {"coordinates":[-79.65650939939999,43.6493606567],"type":"Point"}
}