{
  "type": "Feature",
  "properties": {
    "addr:full":"102 Lancelot Dr Quispamsis NB E2E 1R8",
    "addr:housenumber":"102",
    "addr:postcode":"e2e 1r8",
    "addr:street":"Lancelot Dr",
    "iso:country":"CA",
    "sg:address":"102 Lancelot Dr",
    "sg:city":"Quispamsis",
    "sg:classifiers":[
        {
            "category":"Insurance",
            "subcategory":"Insurance Agent",
            "type":"Services"
        }
    ],
    "sg:phone":"+1 506 849 0921",
    "sg:postcode":"E2E 1R8",
    "sg:province":"NB",
    "wof:name":"Lowell E Jones Insurance Svc",
    "wof:placetype":"venue"
},
  "geometry": {"coordinates":[-65.9886856079,45.4312362671],"type":"Point"}
}