{
  "type": "Feature",
  "properties": {
    "addr:full":"823 Av DE Grande-Ile # 2 Grande-Ile QC J6S 3N9",
    "addr:postcode":"j6s 3n9",
    "addr:street":"823 Av De Grande-Ile # 2 Grande-Ile",
    "iso:country":"CA",
    "sg:address":"823 Av DE Grande-Ile # 2",
    "sg:city":"Grande-Ile",
    "sg:classifiers":[
        {
            "category":"Wholesale",
            "subcategory":"Machinery & Supplies",
            "type":"Manufacturing & Wholesale Goods"
        }
    ],
    "sg:phone":"+1 450 373 5606",
    "sg:postcode":"J6S 3N9",
    "sg:province":"QC",
    "sg:tags":[
        "equipment",
        "irrigation",
        "system"
    ],
    "wof:name":"Pelouse & Jardin Express",
    "wof:placetype":"venue"
},
  "geometry": {"coordinates":[-74.1455,45.280872],"type":"Point"}
}