{
  "type": "Feature",
  "properties": {
    "addr:full":"Drumheller AB T0J 0Y0",
    "addr:postcode":"t0j 0y0",
    "iso:country":"CA",
    "sg:city":"Drumheller",
    "sg:classifiers":[
        {
            "category":"Retail",
            "subcategory":"Repair Shop",
            "type":"Services"
        }
    ],
    "sg:phone":"+1 403 823 7151",
    "sg:postcode":"T0J 0Y0",
    "sg:province":"AB",
    "sg:tags":[
        "welding"
    ],
    "wof:name":"Unique Pressure Welding Ltd",
    "wof:placetype":"venue"
},
  "geometry": {"coordinates":[-112.706917,51.46101],"type":"Point"}
}