{
  "type": "Feature",
  "properties": {
    "iso:country":"CA",
    "sg:address":"153 Division St",
    "sg:city":"Wiarton",
    "sg:classifiers":[
        {
            "category":"Food & Beverages",
            "subcategory":"Meat & Fish",
            "type":"Retail Goods"
        }
    ],
    "sg:phone":"+1 519 534 0850",
    "sg:postcode":"N0H 2T0",
    "sg:province":"ON",
    "sg:tags":[
        "seafood"
    ],
    "wof:name":"Howell's Fish",
    "wof:placetype":"venue"
},
  "geometry": {"coordinates":[-81.1471786499,44.7452697754],"type":"Point"}
}