{
  "type": "Feature",
  "properties": {
    "addr:full":"2485 Milltower Crt Mississauga ON L5N 5Z6",
    "addr:housenumber":"2485",
    "addr:postcode":"l5n 5z6",
    "addr:street":"Milltower Crt",
    "iso:country":"CA",
    "sg:address":"2485 Milltower Crt",
    "sg:city":"Mississauga",
    "sg:classifiers":[
        {
            "category":"Wholesale",
            "subcategory":"Chemicals & Plastics",
            "type":"Manufacturing & Wholesale Goods"
        }
    ],
    "sg:phone":"+1 905 821 2995",
    "sg:postcode":"L5N 5Z6",
    "sg:province":"ON",
    "wof:name":"Alphachem Limited",
    "wof:placetype":"venue"
},
  "geometry": {"coordinates":[-79.7583312988,43.5963783264],"type":"Point"}
}