{
  "type": "Feature",
  "properties": {
    "addr:full":"7034 Oxford St Niagara Falls ON L2J 1J2",
    "addr:housenumber":"7034",
    "addr:postcode":"l2j 1j2",
    "addr:street":"Oxford St",
    "iso:country":"CA",
    "sg:address":"7034 Oxford St",
    "sg:city":"Niagara Falls",
    "sg:classifiers":[
        {
            "category":"Home & Garden",
            "subcategory":"Building Materials",
            "type":"Retail Goods"
        }
    ],
    "sg:phone":"+1 905 356 6991",
    "sg:postcode":"L2J 1J2",
    "sg:province":"ON",
    "sg:tags":[
        "door"
    ],
    "wof:name":"Factory Outlet Windows",
    "wof:placetype":"venue"
},
  "geometry": {"coordinates":[-79.11489105219999,43.1200942993],"type":"Point"}
}