{
  "type": "Feature",
  "properties": {
    "addr:full":"Orleans ON K1C 4M8",
    "addr:postcode":"k1c 4m8",
    "iso:country":"CA",
    "sg:city":"Orleans",
    "sg:classifiers":[
        {
            "category":"Shopping",
            "type":"Retail Goods"
        }
    ],
    "sg:phone":"+1 613 830 8779",
    "sg:postcode":"K1C 4M8",
    "sg:province":"ON",
    "sg:tags":[
        "picture",
        "frame",
        "art",
        "gallery",
        "dealer"
    ],
    "wof:name":"Modern Painting & Framing Shop",
    "wof:placetype":"venue"
},
  "geometry": {"coordinates":[-75.550346,45.464039],"type":"Point"}
}