{
  "type": "Feature",
  "properties": {
    "addr:full":"528 Syndicate Ave S Thunder Bay ON P7E 1E7",
    "addr:housenumber":"528",
    "addr:postcode":"p7e 1e7",
    "addr:street":"Syndicate Ave S Thunder",
    "iso:country":"CA",
    "sg:address":"528 Syndicate Ave S",
    "sg:city":"Thunder Bay",
    "sg:classifiers":[
        {
            "category":"Retail",
            "subcategory":"Auto Repair",
            "type":"Services"
        }
    ],
    "sg:phone":"+1 807 622 4021",
    "sg:postcode":"P7E 1E7",
    "sg:province":"ON",
    "sg:tags":[
        "repairing",
        "automobile"
    ],
    "wof:name":"Matfra Motors",
    "wof:placetype":"venue"
},
  "geometry": {"coordinates":[-89.2483673096,48.3769721985],"type":"Point"}
}