{
  "type": "Feature",
  "properties": {
    "addr:full":"Grande-Vallee QC G0E 1K0",
    "addr:postcode":"g0e 1k0",
    "iso:country":"CA",
    "sg:city":"Grande-Vallee",
    "sg:classifiers":[
        {
            "category":"Travel",
            "subcategory":"Hotels & Motels",
            "type":"Entertainment"
        }
    ],
    "sg:phone":"+1 418 393 2648",
    "sg:postcode":"G0E 1K0",
    "sg:province":"QC",
    "wof:name":"Hotel Motel Grande Vallee",
    "wof:placetype":"venue"
},
  "geometry": {"coordinates":[-65.1363296509,49.227684021],"type":"Point"}
}