{
  "type": "Feature",
  "properties": {
    "iso:country":"CA",
    "sg:address":"Rl 124 Old 14 S",
    "sg:city":"Letellier",
    "sg:classifiers":[
        {
            "category":"Farming",
            "subcategory":"Farm",
            "type":"Manufacturing & Wholesale Goods"
        }
    ],
    "sg:phone":"+1 204 737 2100",
    "sg:postcode":"R0G 1C0",
    "sg:province":"MB",
    "wof:name":"Dansereau Farms Ltd",
    "wof:placetype":"venue"
},
  "geometry": {"coordinates":[-97.30285644529999,49.142326355],"type":"Point"}
}