{
  "type": "Feature",
  "properties": {
    "addr:full":"Whitby ON L1N 3Y9",
    "addr:postcode":"l1n 3y9",
    "iso:country":"CA",
    "sg:city":"Whitby",
    "sg:classifiers":[
        {
            "category":"Health Services",
            "subcategory":"Doctor",
            "type":"Services"
        }
    ],
    "sg:phone":"+1 905 668 5815",
    "sg:postcode":"L1N 3Y9",
    "sg:province":"ON",
    "sg:tags":[
        "dentist"
    ],
    "wof:name":"Daemi, M DDS",
    "wof:placetype":"venue"
},
  "geometry": {"coordinates":[-78.93993377690001,43.8801307678],"type":"Point"}
}