{
  "type": "Feature",
  "properties": {
    "addr:full":"619 Kingston Rd Pickering ON L1V 3N7",
    "addr:housenumber":"619",
    "addr:postcode":"l1v 3n7",
    "addr:street":"Kingston Rd",
    "iso:country":"CA",
    "sg:address":"619 Kingston Rd",
    "sg:city":"Pickering",
    "sg:classifiers":[
        {
            "category":"Food & Beverages",
            "subcategory":"Bakery",
            "type":"Retail Goods"
        }
    ],
    "sg:phone":"+1 905 420 6200",
    "sg:postcode":"L1V 3N7",
    "sg:province":"ON",
    "sg:tags":[
        "baker"
    ],
    "wof:name":"But'N'Ben Scottish Bakery",
    "wof:placetype":"venue"
},
  "geometry": {"coordinates":[-79.117645,43.81723],"type":"Point"}
}