{
  "type": "Feature",
  "properties": {
    "addr:full":"1550 Rue Watkins Saint-Charles-DE-Drummond QC J2B 7T5",
    "addr:housenumber":"1550",
    "addr:postcode":"j2b 7t5",
    "addr:street":"Rue Watkins",
    "iso:country":"CA",
    "sg:address":"1550 Rue Watkins",
    "sg:city":"Saint-Charles-DE-Drummond",
    "sg:classifiers":[
        {
            "category":"Building & Trades",
            "subcategory":"Cleaning & Sanitation",
            "type":"Services"
        }
    ],
    "sg:phone":"+1 819 472 8264",
    "sg:postcode":"J2B 7T5",
    "sg:province":"QC",
    "sg:tags":[
        "window",
        "janitor"
    ],
    "wof:name":"Action Cr",
    "wof:placetype":"venue"
},
  "geometry": {"coordinates":[-72.36937,45.850281],"type":"Point"}
}