{
  "type": "Feature",
  "properties": {
    "addr:full":"Maple Ridge BC V2X 0Y9",
    "addr:postcode":"v2x 0y9",
    "iso:country":"CA",
    "sg:city":"Maple Ridge",
    "sg:classifiers":[
        {
            "category":"Manufacturing",
            "subcategory":"Tools & Machinery",
            "type":"Manufacturing & Wholesale Goods"
        }
    ],
    "sg:phone":"+1 604 465 0270",
    "sg:postcode":"V2X 0Y9",
    "sg:province":"BC",
    "sg:tags":[
        "machine",
        "shop"
    ],
    "wof:name":"Haven Tooling Inc",
    "wof:placetype":"venue"
},
  "geometry": {"coordinates":[-122.605827331,49.2168464661],"type":"Point"}
}