{
  "type": "Feature",
  "properties": {
    "addr:full":"626 58th Ave E Vancouver BC V5X 1W2",
    "addr:housenumber":"626",
    "addr:postcode":"v5x 1w2",
    "addr:street":"58Th Ave E",
    "iso:country":"CA",
    "sg:address":"626 58th Ave E",
    "sg:city":"Vancouver",
    "sg:classifiers":[
        {
            "category":"Organizations",
            "subcategory":"Religious Organization",
            "type":"Services"
        }
    ],
    "sg:phone":"+1 604 325 2719",
    "sg:postcode":"V5X 1W2",
    "sg:province":"BC",
    "sg:tags":[
        "church"
    ],
    "wof:name":"Newbern Memorial Chinese Allnc",
    "wof:placetype":"venue"
},
  "geometry": {"coordinates":[-123.092979,49.216999],"type":"Point"}
}