{
  "type": "Feature",
  "properties": {
    "addr:full":"14 Hoy St Cardinal ON K0E 1E0",
    "addr:housenumber":"14",
    "addr:postcode":"k0e 1e0",
    "addr:street":"Hoy St",
    "iso:country":"CA",
    "sg:address":"14 Hoy St",
    "sg:city":"Cardinal",
    "sg:classifiers":[
        {
            "category":"Retail",
            "subcategory":"Auto Repair",
            "type":"Services"
        }
    ],
    "sg:phone":"+1 613 657 1682",
    "sg:postcode":"K0E 1E0",
    "sg:province":"ON",
    "sg:tags":[
        "wrecker"
    ],
    "wof:name":"Grenville Towing Svc",
    "wof:placetype":"venue"
},
  "geometry": {"coordinates":[-75.3879394531,44.7874946594],"type":"Point"}
}