{
  "type": "Feature",
  "properties": {
    "addr:full":"11605 11 Hwy Stratton ON P0W 1N0",
    "addr:housenumber":"11605",
    "addr:postcode":"p0w 1n0",
    "addr:street":"11 Hwy",
    "iso:country":"CA",
    "sg:address":"11605 11 Hwy",
    "sg:city":"Stratton",
    "sg:classifiers":[
        {
            "category":"Organizations",
            "subcategory":"Professional Association",
            "type":"Services"
        }
    ],
    "sg:phone":"+1 807 483 5857",
    "sg:postcode":"P0W 1N0",
    "sg:province":"ON",
    "wof:name":"Stratton Seniors Friendship",
    "wof:placetype":"venue"
},
  "geometry": {"coordinates":[-94.1632156372,48.6835632324],"type":"Point"}
}