{
  "type": "Feature",
  "properties": {
    "addr:full":"Stevens Marathon ON P0T 2E0",
    "addr:postcode":"p0t 2e0",
    "iso:country":"CA",
    "sg:address":"Stevens",
    "sg:city":"Marathon",
    "sg:classifiers":[
        {
            "category":"Recreation",
            "type":"Entertainment"
        }
    ],
    "sg:phone":"+1 807 229 1370",
    "sg:postcode":"P0T 2E0",
    "sg:province":"ON",
    "sg:tags":[
        "club",
        "curling"
    ],
    "wof:name":"Marathon Curling Club",
    "wof:placetype":"venue"
},
  "geometry": {"coordinates":[-86.383156,48.718655],"type":"Point"}
}