{
  "type": "Feature",
  "properties": {
    "addr:full":"1346 Sandy Falls Rd Timmins ON P4N 7C3",
    "addr:housenumber":"1346",
    "addr:postcode":"p4n 7c3",
    "addr:street":"Sandy Falls Rd",
    "iso:country":"CA",
    "sg:address":"1346 Sandy Falls Rd",
    "sg:city":"Timmins",
    "sg:classifiers":[
        {
            "category":"Wholesale",
            "subcategory":"Auto Parts",
            "type":"Manufacturing & Wholesale Goods"
        }
    ],
    "sg:phone":"+1 705 268 3027",
    "sg:postcode":"P4N 7C3",
    "sg:province":"ON",
    "sg:tags":[
        "automobile",
        "wrecking"
    ],
    "wof:name":"Labelle Auto Wreckers",
    "wof:placetype":"venue"
},
  "geometry": {"coordinates":[-81.4177932739,48.5009536743],"type":"Point"}
}