{
  "type": "Feature",
  "properties": {
    "iso:country":"CA",
    "sg:address":"19 Rue Martin",
    "sg:city":"Riviere-Du-Loup",
    "sg:classifiers":[
        {
            "category":"Personal",
            "subcategory":"Beauty Salon",
            "type":"Services"
        }
    ],
    "sg:phone":"+1 418 868 1156",
    "sg:postcode":"G5R 1G2",
    "sg:province":"QC",
    "wof:name":"Coiffure Signee Renee",
    "wof:placetype":"venue"
},
  "geometry": {"coordinates":[-69.54318237299999,47.8365402222],"type":"Point"}
}