{
  "type": "Feature",
  "properties": {
    "iso:country":"CA",
    "sg:address":"4144 Rue Jean-Talon E",
    "sg:city":"Montreal",
    "sg:classifiers":[
        {
            "category":"Personal",
            "subcategory":"Beauty Salon",
            "type":"Services"
        }
    ],
    "sg:phone":"+1 514 248 1320",
    "sg:postcode":"H1S 2V4",
    "sg:province":"QC",
    "sg:tags":[
        "manicuring"
    ],
    "wof:name":"Jessica Jourdan Inc",
    "wof:placetype":"venue"
},
  "geometry": {"coordinates":[-73.590897,45.566795],"type":"Point"}
}