{
  "type": "Feature",
  "properties": {
    "iso:country":"CA",
    "sg:city":"Mississauga",
    "sg:classifiers":[
        {
            "category":"Retail",
            "subcategory":"Repair Shop",
            "type":"Services"
        }
    ],
    "sg:phone":"+1 905 565 0194",
    "sg:postcode":"L4W 4E2",
    "sg:province":"ON",
    "sg:tags":[
        "upholsterer"
    ],
    "wof:name":"Sofa So Good",
    "wof:placetype":"venue"
},
  "geometry": {"coordinates":[-79.640434,43.6619],"type":"Point"}
}