{
  "type": "Feature",
  "properties": {
    "addr:full":"1804 Bay Shore Rd SW Calgary AB T2V 3M1",
    "addr:housenumber":"1804",
    "addr:postcode":"t2v 3m1",
    "addr:street":"Bay Shore Rd Sw",
    "iso:country":"CA",
    "sg:address":"1804 Bay Shore Rd SW",
    "sg:city":"Calgary",
    "sg:classifiers":[
        {
            "category":"Shopping",
            "subcategory":"Computers & Home Electronics",
            "type":"Retail Goods"
        }
    ],
    "sg:phone":"+1 403 251 5678",
    "sg:postcode":"T2V 3M1",
    "sg:province":"AB",
    "sg:tags":[
        "software"
    ],
    "wof:name":"Ontrack Engineering Ltd",
    "wof:placetype":"venue"
},
  "geometry": {"coordinates":[-114.102272,50.973244],"type":"Point"}
}