{
  "type": "Feature",
  "properties": {
    "addr:full":"Montreal QC H3J 1S6",
    "addr:postcode":"h3j 1s6",
    "iso:country":"CA",
    "sg:city":"Montreal",
    "sg:classifiers":[
        {
            "category":"Professional",
            "subcategory":"Advertising",
            "type":"Services"
        }
    ],
    "sg:phone":"+1 514 932 4044",
    "sg:postcode":"H3J 1S6",
    "sg:province":"QC",
    "sg:tags":[
        "counselor",
        "publishing"
    ],
    "wof:name":"Penega Communications Inc",
    "wof:placetype":"venue"
},
  "geometry": {"coordinates":[-73.5659790039,45.4893760681],"type":"Point"}
}