{
  "type": "Feature",
  "properties": {
    "addr:full":"2 Rue Radisson Candiac QC J5R 3X8",
    "addr:housenumber":"2",
    "addr:postcode":"j5r 3x8",
    "addr:street":"Rue Radisson",
    "iso:country":"CA",
    "sg:address":"2 Rue Radisson",
    "sg:city":"Candiac",
    "sg:classifiers":[
        {
            "category":"Professional",
            "subcategory":"Business Services",
            "type":"Services"
        }
    ],
    "sg:phone":"+1 450 635 3764",
    "sg:postcode":"J5R 3X8",
    "sg:province":"QC",
    "sg:tags":[
        "storage"
    ],
    "wof:name":"Roi DE L'Entreposage Inc",
    "wof:placetype":"venue"
},
  "geometry": {"coordinates":[-73.53498840330001,45.3789024353],"type":"Point"}
}