{
  "type": "Feature",
  "properties": {
    "addr:full":"Hanmer ON P3P 1R9",
    "addr:postcode":"p3p 1r9",
    "iso:country":"CA",
    "sg:city":"Hanmer",
    "sg:classifiers":[
        {
            "category":"Restaurant",
            "type":"Food & Drink"
        }
    ],
    "sg:phone":"+1 705 969 3354",
    "sg:postcode":"P3P 1R9",
    "sg:province":"ON",
    "sg:tags":[
        "delicatessen"
    ],
    "wof:name":"Pam's Bakery & Deli",
    "wof:placetype":"venue"
},
  "geometry": {"coordinates":[-80.94602966310001,46.6564598083],"type":"Point"}
}