{
  "type": "Feature",
  "properties": {
    "addr:full":"5778 Boul Saint-Laurent Montreal QC H2T 1S8",
    "addr:housenumber":"5778",
    "addr:postcode":"h2t 1s8",
    "addr:street":"Boul Saint-Laurent",
    "iso:country":"CA",
    "sg:address":"5778 Boul Saint-Laurent",
    "sg:city":"Montreal",
    "sg:classifiers":[
        {
            "category":"Shopping",
            "subcategory":"Used Merchandise",
            "type":"Retail Goods"
        }
    ],
    "sg:phone":"+1 514 278 0827",
    "sg:postcode":"H2T 1S8",
    "sg:province":"QC",
    "sg:tags":[
        "auctioneer"
    ],
    "wof:name":"Maison Des Encans DE Montreal",
    "wof:placetype":"venue"
},
  "geometry": {"coordinates":[-73.60154,45.526882],"type":"Point"}
}