{
  "type": "Feature",
  "properties": {
    "addr:full":"4875 Boul Metropolitain E Saint-Leonard QC H1R 3J2",
    "addr:housenumber":"4875",
    "addr:postcode":"h1r 3j2",
    "addr:street":"Boul Metropolitain E",
    "iso:country":"CA",
    "sg:address":"4875 Boul Metropolitain E",
    "sg:city":"Saint-Leonard",
    "sg:classifiers":[
        {
            "category":"Insurance",
            "subcategory":"Insurance Agent",
            "type":"Services"
        }
    ],
    "sg:phone":"+1 514 592 5849",
    "sg:postcode":"H1R 3J2",
    "sg:province":"QC",
    "wof:name":"Jean-Guy St-Onge & Assoc",
    "wof:placetype":"venue"
},
  "geometry": {"coordinates":[-73.59317799999999,45.578144],"type":"Point"}
}