{
  "type": "Feature",
  "properties": {
    "addr:full":"405 3rd St E Lashburn SK S0M 1H0",
    "addr:housenumber":"405",
    "addr:postcode":"s0m 1h0",
    "addr:street":"3Rd St E Lashburn",
    "iso:country":"CA",
    "sg:address":"405 3rd St E",
    "sg:city":"Lashburn",
    "sg:classifiers":[
        {
            "category":"Education",
            "subcategory":"School",
            "type":"Public Place"
        }
    ],
    "sg:phone":"+1 306 285 3505",
    "sg:postcode":"S0M 1H0",
    "sg:province":"SK",
    "wof:name":"Lashburn High School",
    "wof:placetype":"venue"
},
  "geometry": {"coordinates":[-109.613274,53.123459],"type":"Point"}
}