{
  "type": "Feature",
  "properties": {
    "addr:full":"2265 Royal Windsor Dr # 4 Mississauga ON L5J 1K5",
    "addr:housenumber":"2265",
    "addr:postcode":"l5j 1k5",
    "addr:street":"Royal Windsor Dr # 4",
    "iso:country":"CA",
    "sg:address":"2265 Royal Windsor Dr # 4",
    "sg:city":"Mississauga",
    "sg:classifiers":[
        {
            "category":"Building & Trades",
            "subcategory":"Construction",
            "type":"Services"
        }
    ],
    "sg:phone":"+1 905 855 9040",
    "sg:postcode":"L5J 1K5",
    "sg:province":"ON",
    "sg:tags":[
        "designer",
        "dealer",
        "pool",
        "swimming"
    ],
    "wof:name":"Able Pool Svc",
    "wof:placetype":"venue"
},
  "geometry": {"coordinates":[-79.63507080079999,43.506477356],"type":"Point"}
}