{
  "type": "Feature",
  "properties": {
    "addr:full":"22 Rue Crepeault Amos QC J9T 3L7",
    "addr:housenumber":"22",
    "addr:postcode":"j9t 3l7",
    "addr:street":"Rue Crepeault Amos",
    "iso:country":"CA",
    "sg:address":"22 Rue Crepeault",
    "sg:city":"Amos",
    "sg:classifiers":[
        {
            "category":"Personal",
            "type":"Services"
        }
    ],
    "sg:phone":"+1 819 732 0134",
    "sg:postcode":"J9T 3L7",
    "sg:province":"QC",
    "sg:tags":[
        "therapist",
        "massage"
    ],
    "wof:name":"Centre Energie Beaute",
    "wof:placetype":"venue"
},
  "geometry": {"coordinates":[-78.1352310181,48.5758171082],"type":"Point"}
}