{
  "type": "Feature",
  "properties": {
    "iso:country":"CA",
    "sg:address":"419 King St W # 206",
    "sg:city":"Oshawa",
    "sg:classifiers":[
        {
            "category":"Professional",
            "subcategory":"Accounting & Tax Preparation",
            "type":"Services"
        }
    ],
    "sg:phone":"+1 905 436 1438",
    "sg:postcode":"L1J 2K5",
    "sg:province":"ON",
    "sg:tags":[
        "consultant"
    ],
    "wof:name":"Roche Tax",
    "wof:placetype":"venue"
},
  "geometry": {"coordinates":[-78.880028,43.893684],"type":"Point"}
}