{
  "type": "Feature",
  "properties": {
    "addr:full":"Taber AB T1G 2C4",
    "addr:postcode":"t1g 2c4",
    "iso:country":"CA",
    "sg:city":"Taber",
    "sg:classifiers":[
        {
            "category":"Wholesale",
            "subcategory":"Farm Supplies",
            "type":"Manufacturing & Wholesale Goods"
        }
    ],
    "sg:phone":"+1 403 223 3922",
    "sg:postcode":"T1G 2C4",
    "sg:province":"AB",
    "sg:tags":[
        "fertilizer"
    ],
    "wof:name":"Lakeside Fertilizer",
    "wof:placetype":"venue"
},
  "geometry": {"coordinates":[-112.12660200000001,49.790352],"type":"Point"}
}