{
  "type": "Feature",
  "properties": {
    "addr:full":"526 Campbell St Lucknow ON N0G 2H0",
    "addr:housenumber":"526",
    "addr:postcode":"n0g 2h0",
    "addr:street":"Campbell St",
    "iso:country":"CA",
    "sg:address":"526 Campbell St",
    "sg:city":"Lucknow",
    "sg:classifiers":[
        {
            "category":"Education",
            "subcategory":"Library",
            "type":"Public Place"
        }
    ],
    "sg:phone":"+1 519 528 3011",
    "sg:postcode":"N0G 2H0",
    "sg:province":"ON",
    "wof:name":"Lucknow Public Library",
    "wof:placetype":"venue"
},
  "geometry": {"coordinates":[-81.51338199999999,43.960083],"type":"Point"}
}