{
  "type": "Feature",
  "properties": {
    "iso:country":"CA",
    "sg:address":"175 Grande Allee W",
    "sg:city":"Quebec",
    "sg:classifiers":[
        {
            "category":"Organizations",
            "subcategory":"Religious Organization",
            "type":"Services"
        }
    ],
    "sg:phone":"+1 418 522 3963",
    "sg:postcode":"G1R 2H1",
    "sg:province":"QC",
    "sg:tags":[
        "church"
    ],
    "wof:name":"Peres Dominicains",
    "wof:placetype":"venue"
},
  "geometry": {"coordinates":[-71.225075,46.801231],"type":"Point"}
}