{
  "type": "Feature",
  "properties": {
    "addr:full":"Montreal-Nord QC H1G 6L2",
    "addr:postcode":"h1g 6l2",
    "iso:country":"CA",
    "sg:city":"Montreal-Nord",
    "sg:classifiers":[
        {
            "category":"Personal",
            "subcategory":"Beauty Salon",
            "type":"Services"
        }
    ],
    "sg:phone":"+1 514 321 6076",
    "sg:postcode":"H1G 6L2",
    "sg:province":"QC",
    "wof:name":"Coiffure Coiftel",
    "wof:placetype":"venue"
},
  "geometry": {"coordinates":[-73.6217803955,45.6275978088],"type":"Point"}
}