{
  "type": "Feature",
  "properties": {
    "addr:full":"695 Main St Morris MB R0G 1K0",
    "addr:housenumber":"695",
    "addr:postcode":"r0g 1k0",
    "addr:street":"Main St",
    "iso:country":"CA",
    "sg:address":"695 Main St",
    "sg:city":"Morris",
    "sg:classifiers":[
        {
            "category":"Wholesale",
            "subcategory":"Motor Vehicles",
            "type":"Manufacturing & Wholesale Goods"
        }
    ],
    "sg:phone":"+1 204 746 6605",
    "sg:postcode":"R0G 1K0",
    "sg:province":"MB",
    "sg:tags":[
        "trailer"
    ],
    "wof:name":"Southern Trailer Sales",
    "wof:placetype":"venue"
},
  "geometry": {"coordinates":[-97.36526499999999,49.345886],"type":"Point"}
}