{
  "type": "Feature",
  "properties": {
    "addr:full":"1710 Charles St Whitby ON L1N 1C2",
    "addr:housenumber":"1710",
    "addr:postcode":"l1n 1c2",
    "addr:street":"Charles St",
    "iso:country":"CA",
    "sg:address":"1710 Charles St",
    "sg:city":"Whitby",
    "sg:classifiers":[
        {
            "category":"Manufacturing",
            "subcategory":"Watercraft",
            "type":"Manufacturing & Wholesale Goods"
        }
    ],
    "sg:phone":"+1 905 430 8299",
    "sg:postcode":"L1N 1C2",
    "sg:province":"ON",
    "sg:tags":[
        "repairing",
        "boat"
    ],
    "wof:name":"Custom Yacht Builder",
    "wof:placetype":"venue"
},
  "geometry": {"coordinates":[-78.935242,43.858944],"type":"Point"}
}