{
  "type": "Feature",
  "properties": {
    "addr:full":"Calgary AB T2E 6S7",
    "addr:postcode":"t2e 6s7",
    "iso:country":"CA",
    "sg:city":"Calgary",
    "sg:classifiers":[
        {
            "category":"Retail",
            "subcategory":"Auto Repair",
            "type":"Services"
        }
    ],
    "sg:phone":"+1 403 230 2070",
    "sg:postcode":"T2E 6S7",
    "sg:province":"AB",
    "sg:tags":[
        "repairing",
        "automobile"
    ],
    "wof:name":"Coldwell Automotive",
    "wof:placetype":"venue"
},
  "geometry": {"coordinates":[-114.053688049,51.0875434875],"type":"Point"}
}