{
  "type": "Feature",
  "properties": {
    "iso:country":"CA",
    "sg:address":"663 Boul Taschereau",
    "sg:city":"LA Prairie",
    "sg:classifiers":[
        {
            "category":"Personal",
            "subcategory":"Beauty Salon",
            "type":"Services"
        }
    ],
    "sg:phone":"+1 450 659 5183",
    "sg:postcode":"J5R 1V7",
    "sg:province":"QC",
    "wof:name":"Salon Trois Etoiles",
    "wof:placetype":"venue"
},
  "geometry": {"coordinates":[-73.493812561,45.4107971191],"type":"Point"}
}