{
  "type": "Feature",
  "properties": {
    "iso:country":"CA",
    "sg:address":"24 Falcon Ridge Dr",
    "sg:city":"Alma",
    "sg:classifiers":[
        {
            "category":"Travel",
            "subcategory":"Hotels & Motels",
            "type":"Entertainment"
        }
    ],
    "sg:phone":"+1 506 887 1110",
    "sg:postcode":"E4H 4Z3",
    "sg:province":"NB",
    "sg:tags":[
        "breakfast",
        "accommodation",
        "bed"
    ],
    "wof:name":"Falcon Ridge Inn",
    "wof:placetype":"venue"
},
  "geometry": {"coordinates":[-64.94673156739999,45.6066017151],"type":"Point"}
}