{
  "type": "Feature",
  "properties": {
    "addr:full":"SW 32-9-9W Edwin MB R0H 0G0",
    "addr:postcode":"r0h 0g0",
    "addr:street":"Sw",
    "iso:country":"CA",
    "sg:address":"SW 32-9-9W",
    "sg:city":"Edwin",
    "sg:classifiers":[
        {
            "category":"Building & Trades",
            "subcategory":"Construction",
            "type":"Services"
        }
    ],
    "sg:phone":"+1 204 252 2502",
    "sg:postcode":"R0H 0G0",
    "sg:province":"MB",
    "sg:tags":[
        "painter"
    ],
    "wof:name":"West End Painting & Decorating",
    "wof:placetype":"venue"
},
  "geometry": {"coordinates":[-98.5145645142,49.8939056396],"type":"Point"}
}