{
  "type": "Feature",
  "properties": {
    "iso:country":"CA",
    "sg:city":"Blainville",
    "sg:classifiers":[
        {
            "category":"Professional",
            "subcategory":"Business Services",
            "type":"Services"
        }
    ],
    "sg:phone":"+1 450 979 6881",
    "sg:postcode":"J7C 5E2",
    "sg:province":"QC",
    "sg:tags":[
        "building",
        "inspection"
    ],
    "wof:name":"Centre D'Expertises Legales",
    "wof:placetype":"venue"
},
  "geometry": {"coordinates":[-73.9000091553,45.6684837341],"type":"Point"}
}