{
  "type": "Feature",
  "properties": {
    "addr:full":"539 Grenville Ave Thunder Bay ON P7A 2C3",
    "addr:housenumber":"539",
    "addr:postcode":"p7a 2c3",
    "addr:street":"Grenville Ave",
    "iso:country":"CA",
    "sg:address":"539 Grenville Ave",
    "sg:city":"Thunder Bay",
    "sg:classifiers":[
        {
            "category":"Education",
            "subcategory":"School",
            "type":"Public Place"
        }
    ],
    "sg:phone":"+1 807 683 8941",
    "sg:postcode":"P7A 2C3",
    "sg:province":"ON",
    "wof:name":"St Paul School",
    "wof:placetype":"venue"
},
  "geometry": {"coordinates":[-89.1879730225,48.4708442688],"type":"Point"}
}