{
  "type": "Feature",
  "properties": {
    "iso:country":"CA",
    "sg:city":"Greenfield Park",
    "sg:classifiers":[
        {
            "category":"Retail",
            "subcategory":"Auto Repair",
            "type":"Services"
        }
    ],
    "sg:phone":"+1 450 923 4656",
    "sg:postcode":"J4V 1M7",
    "sg:province":"QC",
    "sg:tags":[
        "repairing",
        "automobile",
        "tire"
    ],
    "wof:name":"Pneus Trudeau Mecanique",
    "wof:placetype":"venue"
},
  "geometry": {"coordinates":[-73.476746,45.478458],"type":"Point"}
}