{
  "type": "Feature",
  "properties": {
    "addr:full":"Gerald SK S0A 1B0",
    "addr:postcode":"s0a 1b0",
    "addr:street":"Gerald",
    "iso:country":"CA",
    "sg:city":"Gerald",
    "sg:classifiers":[
        {
            "category":"Wholesale",
            "subcategory":"Machinery & Supplies",
            "type":"Manufacturing & Wholesale Goods"
        }
    ],
    "sg:phone":"+1 306 745 2711",
    "sg:postcode":"S0A 1B0",
    "sg:province":"SK",
    "sg:tags":[
        "agricultural",
        "implement"
    ],
    "wof:name":"Bridgeview Manufacturing",
    "wof:placetype":"venue"
},
  "geometry": {"coordinates":[-101.789795,50.666843],"type":"Point"}
}