{
  "type": "Feature",
  "properties": {
    "addr:full":"Farm Big River SK S0J 0E0",
    "addr:postcode":"s0j 0e0",
    "iso:country":"CA",
    "sg:address":"Farm",
    "sg:city":"Big River",
    "sg:classifiers":[
        {
            "category":"Building & Trades",
            "subcategory":"Construction",
            "type":"Services"
        }
    ],
    "sg:phone":"+1 306 469 2255",
    "sg:postcode":"S0J 0E0",
    "sg:province":"SK",
    "sg:tags":[
        "excavating",
        "contractor"
    ],
    "wof:name":"B R Concrete & Excavation Ltd",
    "wof:placetype":"venue"
},
  "geometry": {"coordinates":[-107.031937,53.834133],"type":"Point"}
}