{
  "type": "Feature",
  "properties": {
    "addr:full":"1081 Rue Johnson Thetford Mines QC G6G 5W7",
    "addr:housenumber":"1081",
    "addr:postcode":"g6g 5w7",
    "addr:street":"Rue Johnson",
    "iso:country":"CA",
    "sg:address":"1081 Rue Johnson",
    "sg:city":"Thetford Mines",
    "sg:classifiers":[
        {
            "category":"Food & Beverages",
            "subcategory":"Specialty",
            "type":"Retail Goods"
        }
    ],
    "sg:phone":"+1 418 338 8088",
    "sg:postcode":"G6G 5W7",
    "sg:province":"QC",
    "wof:name":"Prele Des Champs Inc",
    "wof:placetype":"venue"
},
  "geometry": {"coordinates":[-71.33330535890001,46.0901031494],"type":"Point"}
}