{
  "type": "Feature",
  "properties": {
    "addr:full":"4704 Macleod Trail SW Calgary AB T2G 0A8",
    "addr:housenumber":"4704",
    "addr:postcode":"t2g 0a8",
    "addr:street":"Macleod Trail Sw",
    "iso:country":"CA",
    "sg:address":"4704 Macleod Trail SW",
    "sg:city":"Calgary",
    "sg:classifiers":[
        {
            "category":"Food & Beverages",
            "subcategory":"Liquor & Beverages",
            "type":"Retail Goods"
        }
    ],
    "sg:phone":"+1 403 287 1794",
    "sg:postcode":"T2G 0A8",
    "sg:province":"AB",
    "sg:tags":[
        "store"
    ],
    "wof:name":"Blue Bay's Liquor Store",
    "wof:placetype":"venue"
},
  "geometry": {"coordinates":[-114.06636,51.011032],"type":"Point"}
}