{
  "type": "Feature",
  "properties": {
    "iso:country":"CA",
    "sg:address":"591 Rang Du Boulevard",
    "sg:city":"Saint-Barthelemy",
    "sg:classifiers":[
        {
            "category":"Restaurant",
            "type":"Food & Drink"
        }
    ],
    "sg:phone":"+1 450 885 3007",
    "sg:postcode":"J0K 1X0",
    "sg:province":"QC",
    "wof:name":"Restaurant Le Gauzier",
    "wof:placetype":"venue"
},
  "geometry": {"coordinates":[-73.0925979614,46.1759567261],"type":"Point"}
}