{
  "type": "Feature",
  "properties": {
    "addr:full":"9701 Franklin Ave Fort Mcmurray AB T9H 2K1",
    "addr:housenumber":"9701",
    "addr:postcode":"t9h 2k1",
    "addr:street":"Franklin Ave",
    "iso:country":"CA",
    "sg:address":"9701 Franklin Ave",
    "sg:city":"Fort Mcmurray",
    "sg:classifiers":[
        {
            "category":"Organizations",
            "subcategory":"Professional Association",
            "type":"Services"
        }
    ],
    "sg:phone":"+1 780 790 1233",
    "sg:postcode":"T9H 2K1",
    "sg:province":"AB",
    "sg:tags":[
        "club"
    ],
    "wof:name":"Fort Mc Murray Manta Swim Club",
    "wof:placetype":"venue"
},
  "geometry": {"coordinates":[-111.374176025,56.7246284485],"type":"Point"}
}