{
  "type": "Feature",
  "properties": {
    "addr:full":"139 Taurus Dr Hanwell NB E3C 1N1",
    "addr:housenumber":"139",
    "addr:postcode":"e3c 1n1",
    "addr:street":"Taurus Dr",
    "iso:country":"CA",
    "sg:address":"139 Taurus Dr",
    "sg:city":"Hanwell",
    "sg:classifiers":[
        {
            "category":"Professional",
            "subcategory":"Engineering",
            "type":"Services"
        }
    ],
    "sg:phone":"+1 506 459 8476",
    "sg:postcode":"E3C 1N1",
    "sg:province":"NB",
    "sg:tags":[
        "engineer"
    ],
    "wof:name":"Phillips Engineering Svc",
    "wof:placetype":"venue"
},
  "geometry": {"coordinates":[-66.7954406738,45.8684844971],"type":"Point"}
}