{
  "type": "Feature",
  "properties": {
    "addr:full":"5959 Anderson St # 1A Whitby ON L1M 2E9",
    "addr:housenumber":"5959",
    "addr:postcode":"l1m 2e9",
    "addr:street":"Anderson St # 1A",
    "iso:country":"CA",
    "sg:address":"5959 Anderson St # 1A",
    "sg:city":"Whitby",
    "sg:classifiers":[
        {
            "category":"Health Services",
            "subcategory":"Doctor",
            "type":"Services"
        }
    ],
    "sg:phone":"+1 905 655 3321",
    "sg:postcode":"L1M 2E9",
    "sg:province":"ON",
    "sg:tags":[
        "clinic"
    ],
    "wof:name":"Brooklin Medical Ctr",
    "wof:placetype":"venue"
},
  "geometry": {"coordinates":[-78.94663199999999,43.955826],"type":"Point"}
}