{
  "type": "Feature",
  "properties": {
    "addr:full":"6993 Union St Dublin ON N0K 1E0",
    "addr:housenumber":"6993",
    "addr:postcode":"n0k 1e0",
    "addr:street":"Union St",
    "iso:country":"CA",
    "sg:address":"6993 Union St",
    "sg:city":"Dublin",
    "sg:classifiers":[
        {
            "category":"Wholesale",
            "subcategory":"Farm Supplies",
            "type":"Manufacturing & Wholesale Goods"
        }
    ],
    "sg:phone":"+1 519 345 2330",
    "sg:postcode":"N0K 1E0",
    "sg:province":"ON",
    "sg:tags":[
        "feed"
    ],
    "wof:name":"Dublin Feed Mill",
    "wof:placetype":"venue"
},
  "geometry": {"coordinates":[-81.287521,43.502369],"type":"Point"}
}