{
  "type": "Feature",
  "properties": {
    "iso:country":"CA",
    "sg:address":"112 Rue St-Joseph",
    "sg:city":"Henryville",
    "sg:classifiers":[
        {
            "category":"Wholesale",
            "subcategory":"Farm Supplies",
            "type":"Manufacturing & Wholesale Goods"
        }
    ],
    "sg:phone":"+1 450 299 2721",
    "sg:postcode":"J0J 1E0",
    "sg:province":"QC",
    "sg:tags":[
        "fertilizer"
    ],
    "wof:name":"William Houde Ltee",
    "wof:placetype":"venue"
},
  "geometry": {"coordinates":[-73.1900024414,45.137336731],"type":"Point"}
}