{
  "type": "Feature",
  "properties": {
    "addr:full":"75 Lucerne Dr Kitchener ON N2E 1B4",
    "addr:housenumber":"75",
    "addr:postcode":"n2e 1b4",
    "addr:street":"Lucerne Dr",
    "iso:country":"CA",
    "sg:address":"75 Lucerne Dr",
    "sg:city":"Kitchener",
    "sg:classifiers":[
        {
            "category":"Education",
            "subcategory":"School",
            "type":"Public Place"
        }
    ],
    "sg:phone":"+1 519 743 4338",
    "sg:postcode":"N2E 1B4",
    "sg:province":"ON",
    "wof:name":"Alpine Public School",
    "wof:placetype":"venue"
},
  "geometry": {"coordinates":[-80.483116,43.420311],"type":"Point"}
}