{
  "type": "Feature",
  "properties": {
    "iso:country":"CA",
    "sg:address":"4301 Echo Field Rd",
    "sg:city":"Cranbrook",
    "sg:classifiers":[
        {
            "category":"Building & Trades",
            "subcategory":"Construction",
            "type":"Services"
        }
    ],
    "sg:phone":"+1 250 426 2455",
    "sg:postcode":"V1C 7B6",
    "sg:province":"BC",
    "sg:tags":[
        "boring",
        "drilling",
        "contractor"
    ],
    "wof:name":"Owen's Drilling Ltd",
    "wof:placetype":"venue"
},
  "geometry": {"coordinates":[-115.76808929400001,49.5383682251],"type":"Point"}
}