{
  "type": "Feature",
  "properties": {
    "addr:full":"Broadway St Holland MB R0G 0X0",
    "addr:postcode":"r0g 0x0",
    "addr:street":"Broadway St",
    "iso:country":"CA",
    "sg:address":"Broadway St",
    "sg:city":"Holland",
    "sg:classifiers":[
        {
            "category":"Organizations",
            "subcategory":"Religious Organization",
            "type":"Services"
        }
    ],
    "sg:phone":"+1 204 526 2215",
    "sg:postcode":"R0G 0X0",
    "sg:province":"MB",
    "sg:tags":[
        "church"
    ],
    "wof:name":"Holland United Church",
    "wof:placetype":"venue"
},
  "geometry": {"coordinates":[-98.87896728520001,49.5974998474],"type":"Point"}
}