{
  "type": "Feature",
  "properties": {
    "addr:full":"2 Blueberry Bay Winnipeg MB R2J 2G7",
    "addr:housenumber":"2",
    "addr:postcode":"r2j 2g7",
    "addr:street":"Blueberry Bay",
    "iso:country":"CA",
    "sg:address":"2 Blueberry Bay",
    "sg:city":"Winnipeg",
    "sg:classifiers":[
        {
            "category":"Building & Trades",
            "subcategory":"Construction",
            "type":"Services"
        }
    ],
    "sg:phone":"+1 204 256 5747",
    "sg:postcode":"R2J 2G7",
    "sg:province":"MB",
    "sg:tags":[
        "home",
        "improvement"
    ],
    "wof:name":"Rab Construction",
    "wof:placetype":"venue"
},
  "geometry": {"coordinates":[-97.086647,49.865688],"type":"Point"}
}