{
  "type": "Feature",
  "properties": {
    "addr:full":"3975 Boul Industriel Sherbrooke QC J1L 2S7",
    "addr:housenumber":"3975",
    "addr:postcode":"j1l 2s7",
    "addr:street":"Boul Industriel",
    "iso:country":"CA",
    "sg:address":"3975 Boul Industriel",
    "sg:city":"Sherbrooke",
    "sg:classifiers":[
        {
            "category":"Wholesale",
            "subcategory":"Electrical",
            "type":"Manufacturing & Wholesale Goods"
        }
    ],
    "sg:phone":"+1 819 562 2660",
    "sg:postcode":"J1L 2S7",
    "sg:province":"QC",
    "sg:tags":[
        "equipment",
        "electric",
        "supply"
    ],
    "wof:name":"Westburne Quebec",
    "wof:placetype":"venue"
},
  "geometry": {"coordinates":[-71.96352386469999,45.3978843689],"type":"Point"}
}