{
  "type": "Feature",
  "properties": {
    "addr:full":"8141 127 Ave NW Edmonton AB T5C 1R9",
    "addr:housenumber":"8141",
    "addr:postcode":"t5c 1r9",
    "addr:street":"127 Ave Nw",
    "iso:country":"CA",
    "sg:address":"8141 127 Ave NW",
    "sg:city":"Edmonton",
    "sg:classifiers":[
        {
            "category":"Restaurant",
            "type":"Food & Drink"
        }
    ],
    "sg:phone":"+1 780 414 8344",
    "sg:postcode":"T5C 1R9",
    "sg:province":"AB",
    "wof:name":"Mc Donald's",
    "wof:placetype":"venue"
},
  "geometry": {"coordinates":[-113.466003418,53.584690094],"type":"Point"}
}