{
  "type": "Feature",
  "properties": {
    "iso:country":"CA",
    "sg:address":"1068 Erie St E",
    "sg:city":"Windsor",
    "sg:classifiers":[
        {
            "category":"Restaurant",
            "type":"Food & Drink"
        }
    ],
    "sg:phone":"+1 519 560 3502",
    "sg:postcode":"N9A 3Z1",
    "sg:province":"ON",
    "wof:name":"Aldo Goldberg's Deli & Rstrnt",
    "wof:placetype":"venue"
},
  "geometry": {"coordinates":[-83.018555,42.314453],"type":"Point"}
}