{
  "type": "Feature",
  "properties": {
    "iso:country":"CA",
    "sg:address":"5272 Rue Monsabre",
    "sg:city":"Montreal",
    "sg:classifiers":[
        {
            "category":"Building & Trades",
            "subcategory":"Construction",
            "type":"Services"
        }
    ],
    "sg:phone":"+1 514 256 2221",
    "sg:postcode":"H1M 2R2",
    "sg:province":"QC",
    "sg:tags":[
        "dry wall",
        "contractor"
    ],
    "wof:name":"Systeme Interieur Repentigny",
    "wof:placetype":"venue"
},
  "geometry": {"coordinates":[-73.554359,45.575928],"type":"Point"}
}