{
  "type": "Feature",
  "properties": {
    "addr:full":"1525 Vincent Massey Dr Cornwall ON K6H 5R6",
    "addr:housenumber":"1525",
    "addr:postcode":"k6h 5r6",
    "addr:street":"Vincent Massey Dr",
    "iso:country":"CA",
    "sg:address":"1525 Vincent Massey Dr",
    "sg:city":"Cornwall",
    "sg:classifiers":[
        {
            "category":"Autos & Motor Vehicles",
            "subcategory":"Automobile Sales",
            "type":"Retail Goods"
        }
    ],
    "sg:phone":"+1 613 938 7667",
    "sg:postcode":"K6H 5R6",
    "sg:province":"ON",
    "sg:tags":[
        "car",
        "dealer"
    ],
    "wof:name":"Great Canadian Car CO",
    "wof:placetype":"venue"
},
  "geometry": {"coordinates":[-74.75913238530001,45.0310325623],"type":"Point"}
}