{
  "type": "Feature",
  "properties": {
    "addr:full":"95 Guildwood Pky Scarborough ON M1E 1P1",
    "addr:housenumber":"95",
    "addr:postcode":"m1e 1p1",
    "addr:street":"Guildwood Pky",
    "iso:country":"CA",
    "sg:address":"95 Guildwood Pky",
    "sg:city":"Scarborough",
    "sg:classifiers":[
        {
            "category":"Banks & Credit Unions",
            "subcategory":"Bank",
            "type":"Services"
        }
    ],
    "sg:phone":"+1 416 692 2683",
    "sg:postcode":"M1E 1P1",
    "sg:province":"ON",
    "wof:name":"Cibc",
    "wof:placetype":"venue"
},
  "geometry": {"coordinates":[-79.20056200000001,43.74707],"type":"Point"}
}