{
  "type": "Feature",
  "properties": {
    "addr:full":"73 King St # 102 Sioux Lookout ON P8T 1C3",
    "addr:housenumber":"73",
    "addr:postcode":"p8t 1c3",
    "addr:street":"King St # 102",
    "iso:country":"CA",
    "sg:address":"73 King St # 102",
    "sg:city":"Sioux Lookout",
    "sg:classifiers":[
        {
            "category":"Real Estate",
            "subcategory":"Real Estate Agent",
            "type":"Services"
        }
    ],
    "sg:phone":"+1 807 737 8100",
    "sg:postcode":"P8T 1C3",
    "sg:province":"ON",
    "wof:name":"Sioux Mountain Realty",
    "wof:placetype":"venue"
},
  "geometry": {"coordinates":[-91.9197463989,50.0988922119],"type":"Point"}
}