{
  "type": "Feature",
  "properties": {
    "addr:full":"78 Quarry Edge Dr #G Brampton ON L6V 4L4",
    "addr:housenumber":"78",
    "addr:postcode":"l6v 4l4",
    "addr:street":"Quarry Edge Dr # G",
    "iso:country":"CA",
    "sg:address":"78 Quarry Edge Dr #G",
    "sg:city":"Brampton",
    "sg:classifiers":[
        {
            "category":"Shopping",
            "subcategory":"Shoes",
            "type":"Retail Goods"
        }
    ],
    "sg:phone":"+1 905 453 6117",
    "sg:postcode":"L6V 4L4",
    "sg:province":"ON",
    "wof:name":"Payless Shoe Source",
    "wof:placetype":"venue"
},
  "geometry": {"coordinates":[-79.7821884155,43.7062568665],"type":"Point"}
}