{
  "type": "Feature",
  "properties": {
    "addr:full":"920 Agnes St New Westminster BC V3M 1H6",
    "addr:housenumber":"920",
    "addr:postcode":"v3m 1h6",
    "addr:street":"Agnes St",
    "iso:country":"CA",
    "sg:address":"920 Agnes St",
    "sg:city":"New Westminster",
    "sg:classifiers":[
        {
            "category":"Retail",
            "subcategory":"Auto Repair",
            "type":"Services"
        }
    ],
    "sg:phone":"+1 604 524 9747",
    "sg:postcode":"V3M 1H6",
    "sg:province":"BC",
    "sg:tags":[
        "transmission",
        "automobile",
        "repairing"
    ],
    "wof:name":"Bert's Auto Transmissions",
    "wof:placetype":"venue"
},
  "geometry": {"coordinates":[-122.915779114,49.2014198303],"type":"Point"}
}