{
  "type": "Feature",
  "properties": {
    "addr:full":"38975 Talbot Line RR 7 St Thomas ON N5P 3T2",
    "addr:housenumber":"38975",
    "addr:postcode":"n5p 3t2",
    "addr:street":"Talbot Line Rr 7",
    "iso:country":"CA",
    "sg:address":"38975 Talbot Line RR 7",
    "sg:city":"St Thomas",
    "sg:classifiers":[
        {
            "category":"Manufacturing",
            "subcategory":"Tools & Machinery",
            "type":"Manufacturing & Wholesale Goods"
        }
    ],
    "sg:phone":"+1 519 637 2460",
    "sg:postcode":"N5P 3T2",
    "sg:province":"ON",
    "sg:tags":[
        "machine",
        "shop"
    ],
    "wof:name":"Geormach Machine & Tool Inc",
    "wof:placetype":"venue"
},
  "geometry": {"coordinates":[-81.193146,42.778938],"type":"Point"}
}