{
  "type": "Feature",
  "properties": {
    "addr:full":"145 Sherwood Cres Dorchester ON N0L 1G3",
    "addr:housenumber":"145",
    "addr:postcode":"n0l 1g3",
    "addr:street":"Sherwood Cres",
    "iso:country":"CA",
    "sg:address":"145 Sherwood Cres",
    "sg:city":"Dorchester",
    "sg:classifiers":[
        {
            "category":"Building & Trades",
            "subcategory":"Landscaping Services",
            "type":"Services"
        }
    ],
    "sg:phone":"+1 519 268 3509",
    "sg:postcode":"N0L 1G3",
    "sg:province":"ON",
    "sg:tags":[
        "landscape",
        "contractor"
    ],
    "wof:name":"R A Bish Landscape Design",
    "wof:placetype":"venue"
},
  "geometry": {"coordinates":[-81.05542800000001,42.981434],"type":"Point"}
}