{
  "type": "Feature",
  "properties": {
    "addr:full":"4750 Oak St Vancouver BC V6H 2N9",
    "addr:housenumber":"4750",
    "addr:postcode":"v6h 2n9",
    "addr:street":"Oak St",
    "iso:country":"CA",
    "sg:address":"4750 Oak St",
    "sg:city":"Vancouver",
    "sg:classifiers":[
        {
            "category":"Organizations",
            "subcategory":"Professional Association",
            "type":"Services"
        }
    ],
    "sg:phone":"+1 604 707 3400",
    "sg:postcode":"V6H 2N9",
    "sg:province":"BC",
    "sg:tags":[
        "clinic"
    ],
    "wof:name":"Canadian Blood Svc",
    "wof:placetype":"venue"
},
  "geometry": {"coordinates":[-123.12752500000001,49.242989],"type":"Point"}
}