{
  "type": "Feature",
  "properties": {
    "iso:country":"CA",
    "sg:city":"Westmount",
    "sg:classifiers":[
        {
            "category":"Health Services",
            "subcategory":"Health Practitioner",
            "type":"Services"
        }
    ],
    "sg:phone":"+1 514 933 6488",
    "sg:postcode":"H3Z 1K9",
    "sg:province":"QC",
    "sg:tags":[
        "psychotherapist"
    ],
    "wof:name":"Mc Elhone, Andrea",
    "wof:placetype":"venue"
},
  "geometry": {"coordinates":[-73.59079,45.488899],"type":"Point"}
}