{
  "type": "Feature",
  "properties": {
    "addr:full":"21 Micmac Dr Dartmouth NS B2X 2H4",
    "addr:housenumber":"21",
    "addr:postcode":"b2x 2h4",
    "addr:street":"Micmac Dr",
    "iso:country":"CA",
    "sg:address":"21 Micmac Dr",
    "sg:city":"Dartmouth",
    "sg:classifiers":[
        {
            "category":"Home & Garden",
            "subcategory":"Furniture",
            "type":"Retail Goods"
        }
    ],
    "sg:phone":"+1 902 463 5729",
    "sg:postcode":"B2X 2H4",
    "sg:province":"NS",
    "wof:name":"Wicker Emporium",
    "wof:placetype":"venue"
},
  "geometry": {"coordinates":[-63.5445976257,44.6948623657],"type":"Point"}
}