{
  "type": "Feature",
  "properties": {
    "addr:full":"Scarborough ON M1H 2X1",
    "addr:postcode":"m1h 2x1",
    "iso:country":"CA",
    "sg:city":"Scarborough",
    "sg:classifiers":[
        {
            "category":"Wholesale",
            "subcategory":"Machinery & Supplies",
            "type":"Manufacturing & Wholesale Goods"
        }
    ],
    "sg:phone":"+1 416 438 1233",
    "sg:postcode":"M1H 2X1",
    "sg:province":"ON",
    "sg:tags":[
        "fitting",
        "hose",
        "coupling"
    ],
    "wof:name":"Avon Fluid System Technologies",
    "wof:placetype":"venue"
},
  "geometry": {"coordinates":[-79.246628,43.778156],"type":"Point"}
}