{
  "type": "Feature",
  "properties": {
    "addr:full":"820 8th Ave W Beaverlodge AB T0H 0C0",
    "addr:housenumber":"820",
    "addr:postcode":"t0h 0c0",
    "addr:street":"8Th Ave W",
    "iso:country":"CA",
    "sg:address":"820 8th Ave W",
    "sg:city":"Beaverlodge",
    "sg:classifiers":[
        {
            "category":"Recreation",
            "type":"Entertainment"
        }
    ],
    "sg:phone":"+1 780 354 3013",
    "sg:postcode":"T0H 0C0",
    "sg:province":"AB",
    "sg:tags":[
        "bingo",
        "game"
    ],
    "wof:name":"Bingo Hall",
    "wof:placetype":"venue"
},
  "geometry": {"coordinates":[-119.436249,55.208046],"type":"Point"}
}