{
  "type": "Feature",
  "properties": {
    "addr:full":"111 Waterton Ave Waterton Park AB T0K 2M0",
    "addr:housenumber":"111",
    "addr:postcode":"t0k 2m0",
    "addr:street":"Waterton Ave Waterton",
    "iso:country":"CA",
    "sg:address":"111 Waterton Ave",
    "sg:city":"Waterton Park",
    "sg:classifiers":[
        {
            "category":"Travel",
            "subcategory":"Hotels & Motels",
            "type":"Entertainment"
        }
    ],
    "sg:phone":"+1 403 859 2211",
    "sg:postcode":"T0K 2M0",
    "sg:province":"AB",
    "wof:name":"Bayshore Inn",
    "wof:placetype":"venue"
},
  "geometry": {"coordinates":[-113.907051086,49.0498352051],"type":"Point"}
}