{
  "type": "Feature",
  "properties": {
    "addr:full":"272 King St E Virden MB R0M 2C0",
    "addr:housenumber":"272",
    "addr:postcode":"r0m 2c0",
    "addr:street":"King St E Virden",
    "iso:country":"CA",
    "sg:address":"272 King St E",
    "sg:city":"Virden",
    "sg:classifiers":[
        {
            "category":"Autos & Motor Vehicles",
            "subcategory":"Auto Supplies",
            "type":"Retail Goods"
        }
    ],
    "sg:phone":"+1 204 748 4040",
    "sg:postcode":"R0M 2C0",
    "sg:province":"MB",
    "sg:tags":[
        "tire"
    ],
    "wof:name":"K K Penner & Sons",
    "wof:placetype":"venue"
},
  "geometry": {"coordinates":[-100.93099975600001,49.8534393311],"type":"Point"}
}