{
  "type": "Feature",
  "properties": {
    "addr:full":"1017 38 Ave SW Calgary AB T2T 2J3",
    "addr:housenumber":"1017",
    "addr:postcode":"t2t 2j3",
    "addr:street":"38 Ave Sw",
    "iso:country":"CA",
    "sg:address":"1017 38 Ave SW",
    "sg:city":"Calgary",
    "sg:classifiers":[
        {
            "category":"Mining & Drilling",
            "type":"Manufacturing & Wholesale Goods"
        }
    ],
    "sg:phone":"+1 403 265 7100",
    "sg:postcode":"T2T 2J3",
    "sg:province":"AB",
    "sg:tags":[
        "company",
        "oil"
    ],
    "wof:name":"Cosmos",
    "wof:placetype":"venue"
},
  "geometry": {"coordinates":[-114.086662,51.02],"type":"Point"}
}