{
  "type": "Feature",
  "properties": {
    "addr:full":"1071 Midland Ave Kingston ON K7P 2X8",
    "addr:housenumber":"1071",
    "addr:postcode":"k7p 2x8",
    "addr:street":"Midland Ave",
    "iso:country":"CA",
    "sg:address":"1071 Midland Ave",
    "sg:city":"Kingston",
    "sg:classifiers":[
        {
            "category":"Professional",
            "subcategory":"Lawyer & Legal Services",
            "type":"Services"
        }
    ],
    "sg:phone":"+1 613 384 1296",
    "sg:postcode":"K7P 2X8",
    "sg:province":"ON",
    "sg:tags":[
        "attorney"
    ],
    "wof:name":"William John Poulos Law Office",
    "wof:placetype":"venue"
},
  "geometry": {"coordinates":[-76.574326,44.261925],"type":"Point"}
}