{
  "type": "Feature",
  "properties": {
    "addr:full":"Cat Lake ON P0V 1J0",
    "addr:postcode":"p0v 1j0",
    "addr:street":"Cat",
    "iso:country":"CA",
    "sg:city":"Cat Lake",
    "sg:classifiers":[
        {
            "category":"Education",
            "subcategory":"School",
            "type":"Public Place"
        }
    ],
    "sg:phone":"+1 807 347 2454",
    "sg:postcode":"P0V 1J0",
    "sg:province":"ON",
    "wof:name":"Internet High School",
    "wof:placetype":"venue"
},
  "geometry": {"coordinates":[-91.83532700000001,51.726238],"type":"Point"}
}