{
  "type": "Feature",
  "properties": {
    "addr:full":"1124 Kensington Rd NW #A Calgary AB T2N 3P3",
    "addr:housenumber":"1124",
    "addr:postcode":"t2n 3p3",
    "addr:street":"Kensington Rd Nw # A",
    "iso:country":"CA",
    "sg:address":"1124 Kensington Rd NW #A",
    "sg:city":"Calgary",
    "sg:classifiers":[
        {
            "category":"Shopping",
            "subcategory":"Gifts & Souvenirs",
            "type":"Retail Goods"
        }
    ],
    "sg:phone":"+1 403 270 4165",
    "sg:postcode":"T2N 3P3",
    "sg:province":"AB",
    "sg:tags":[
        "shop",
        "toy"
    ],
    "wof:name":"Livingstone & Cavell Extraord",
    "wof:placetype":"venue"
},
  "geometry": {"coordinates":[-114.08757,51.052658],"type":"Point"}
}