{
  "type": "Feature",
  "properties": {
    "addr:full":"1600 Regent Ave W Winnipeg MB R2C 3B5",
    "addr:housenumber":"1600",
    "addr:postcode":"r2c 3b5",
    "addr:street":"Regent Ave W",
    "iso:country":"CA",
    "sg:address":"1600 Regent Ave W",
    "sg:city":"Winnipeg",
    "sg:classifiers":[
        {
            "category":"Restaurant",
            "type":"Food & Drink"
        }
    ],
    "sg:phone":"+1 204 668 6881",
    "sg:postcode":"R2C 3B5",
    "sg:province":"MB",
    "wof:name":"Burger Factory",
    "wof:placetype":"venue"
},
  "geometry": {"coordinates":[-97.065788269,49.8975410461],"type":"Point"}
}