{
  "type": "Feature",
  "properties": {
    "addr:full":"2014 Dufferin Ave Wallaceburg ON N8A 4M4",
    "addr:housenumber":"2014",
    "addr:postcode":"n8a 4m4",
    "addr:street":"Dufferin Ave",
    "iso:country":"CA",
    "sg:address":"2014 Dufferin Ave",
    "sg:city":"Wallaceburg",
    "sg:classifiers":[
        {
            "category":"Organizations",
            "subcategory":"Religious Organization",
            "type":"Services"
        }
    ],
    "sg:phone":"+1 519 627 5377",
    "sg:postcode":"N8A 4M4",
    "sg:province":"ON",
    "sg:tags":[
        "church"
    ],
    "wof:name":"Living World Assembly",
    "wof:placetype":"venue"
},
  "geometry": {"coordinates":[-82.42392,42.593681],"type":"Point"}
}