{
  "type": "Feature",
  "properties": {
    "iso:country":"CA",
    "sg:address":"572 Peto Pl",
    "sg:city":"Victoria",
    "sg:classifiers":[
        {
            "category":"Farming",
            "subcategory":"Nursery",
            "type":"Manufacturing & Wholesale Goods"
        }
    ],
    "sg:phone":"+1 250 727 0067",
    "sg:postcode":"V8Z 2K6",
    "sg:province":"BC",
    "sg:tags":[
        "greenhouse"
    ],
    "wof:name":"Davis Construction Ltd",
    "wof:placetype":"venue"
},
  "geometry": {"coordinates":[-123.364517212,48.428314209],"type":"Point"}
}