{
  "type": "Feature",
  "properties": {
    "addr:full":"Montreal QC H2B 1Y7",
    "addr:postcode":"h2b 1y7",
    "iso:country":"CA",
    "sg:city":"Montreal",
    "sg:classifiers":[
        {
            "category":"Health Services",
            "subcategory":"Nursing And Care Facility",
            "type":"Services"
        }
    ],
    "sg:phone":"+1 514 384 0450",
    "sg:postcode":"H2B 1Y7",
    "sg:province":"QC",
    "sg:tags":[
        "home",
        "rest"
    ],
    "wof:name":"Maison Dehon",
    "wof:placetype":"venue"
},
  "geometry": {"coordinates":[-73.6531677246,45.5815925598],"type":"Point"}
}