{
  "type": "Feature",
  "properties": {
    "addr:full":"374 Queen St E Sault Ste Marie ON P6A 1Z1",
    "addr:housenumber":"374",
    "addr:postcode":"p6a 1z1",
    "addr:street":"Queen St E",
    "iso:country":"CA",
    "sg:address":"374 Queen St E",
    "sg:city":"Sault Ste Marie",
    "sg:classifiers":[
        {
            "category":"Personal",
            "subcategory":"Tanning Parlor",
            "type":"Services"
        }
    ],
    "sg:phone":"+1 705 949 7710",
    "sg:postcode":"P6A 1Z1",
    "sg:province":"ON",
    "sg:tags":[
        "salon",
        "swimwear",
        "accessory"
    ],
    "wof:name":"Paradise Swimwear & Tanning",
    "wof:placetype":"venue"
},
  "geometry": {"coordinates":[-84.33419036870001,46.512714386],"type":"Point"}
}