{
  "type": "Feature",
  "properties": {
    "addr:full":"1120 Martin Grove Rd Etobicoke ON M9W 4W1",
    "addr:housenumber":"1120",
    "addr:postcode":"m9w 4w1",
    "addr:street":"Martin Grove Rd",
    "iso:country":"CA",
    "sg:address":"1120 Martin Grove Rd",
    "sg:city":"Etobicoke",
    "sg:classifiers":[
        {
            "category":"Recreation",
            "type":"Entertainment"
        }
    ],
    "sg:phone":"+1 416 247 5742",
    "sg:postcode":"M9W 4W1",
    "sg:province":"ON",
    "sg:tags":[
        "skating",
        "rink"
    ],
    "wof:name":"Canlan Ice Sports Etobicoke",
    "wof:placetype":"venue"
},
  "geometry": {"coordinates":[-79.5749969482,43.7002372742],"type":"Point"}
}