{
  "type": "Feature",
  "properties": {
    "addr:full":"25 Westside Dr Etobicoke ON M9C 1B3",
    "addr:housenumber":"25",
    "addr:postcode":"m9c 1b3",
    "addr:street":"Westside Dr",
    "iso:country":"CA",
    "sg:address":"25 Westside Dr",
    "sg:city":"Etobicoke",
    "sg:classifiers":[
        {
            "category":"Autos & Motor Vehicles",
            "subcategory":"Automobile Sales",
            "type":"Retail Goods"
        }
    ],
    "sg:phone":"+1 905 848 5037",
    "sg:postcode":"M9C 1B3",
    "sg:province":"ON",
    "sg:tags":[
        "truck"
    ],
    "wof:name":"Truck Locator",
    "wof:placetype":"venue"
},
  "geometry": {"coordinates":[-79.56347700000001,43.618008],"type":"Point"}
}