{
  "type": "Feature",
  "properties": {
    "addr:full":"6050 Almon St Halifax NS B3K 1T8",
    "addr:housenumber":"6050",
    "addr:postcode":"b3k 1t8",
    "addr:street":"Almon St",
    "iso:country":"CA",
    "sg:address":"6050 Almon St",
    "sg:city":"Halifax",
    "sg:classifiers":[
        {
            "category":"Wholesale",
            "subcategory":"Machinery & Supplies",
            "type":"Manufacturing & Wholesale Goods"
        }
    ],
    "sg:phone":"+1 902 455 6664",
    "sg:postcode":"B3K 1T8",
    "sg:province":"NS",
    "sg:tags":[
        "ship",
        "chandler"
    ],
    "wof:name":"Walmar Atlantic Ltd",
    "wof:placetype":"venue"
},
  "geometry": {"coordinates":[-63.598984,44.656952],"type":"Point"}
}