{
  "type": "Feature",
  "properties": {
    "iso:country":"CA",
    "sg:city":"Ancaster",
    "sg:classifiers":[
        {
            "category":"Professional",
            "subcategory":"Engineering",
            "type":"Services"
        }
    ],
    "sg:phone":"+1 905 648 5522",
    "sg:postcode":"L9G 4V5",
    "sg:province":"ON",
    "sg:tags":[
        "engineer"
    ],
    "wof:name":"Origin & Cause Inc",
    "wof:placetype":"venue"
},
  "geometry": {"coordinates":[-80.02755737299999,43.1923370361],"type":"Point"}
}