{
  "type": "Feature",
  "properties": {
    "addr:full":"178 Main St Unionville ON L3R 2G9",
    "addr:housenumber":"178",
    "addr:postcode":"l3r 2g9",
    "addr:street":"Main St",
    "iso:country":"CA",
    "sg:address":"178 Main St",
    "sg:city":"Unionville",
    "sg:classifiers":[
        {
            "category":"Wholesale",
            "subcategory":"Stationery",
            "type":"Manufacturing & Wholesale Goods"
        }
    ],
    "sg:phone":"+1 905 513 9753",
    "sg:postcode":"L3R 2G9",
    "sg:province":"ON",
    "sg:tags":[
        "school",
        "supply"
    ],
    "wof:name":"Binney & Smith Canada",
    "wof:placetype":"venue"
},
  "geometry": {"coordinates":[-79.31224060060001,43.8674049377],"type":"Point"}
}