{
  "type": "Feature",
  "properties": {
    "addr:full":"3645 Bathurst St North York ON M6A 2E4",
    "addr:housenumber":"3645",
    "addr:postcode":"m6a 2e4",
    "addr:street":"Bathurst St",
    "iso:country":"CA",
    "sg:address":"3645 Bathurst St",
    "sg:city":"North York",
    "sg:classifiers":[
        {
            "category":"Health Services",
            "subcategory":"Doctor",
            "type":"Services"
        }
    ],
    "sg:phone":"+1 416 781 1161",
    "sg:postcode":"M6A 2E4",
    "sg:province":"ON",
    "sg:tags":[
        "dentist"
    ],
    "wof:name":"Silverberg, Morton DDS",
    "wof:placetype":"venue"
},
  "geometry": {"coordinates":[-79.4328384399,43.7334213257],"type":"Point"}
}