{
  "type": "Feature",
  "properties": {
    "addr:full":"693 Rue Saint-Alphonse N Thetford Mines QC G6G 3X3",
    "addr:housenumber":"693",
    "addr:postcode":"g6g 3x3",
    "addr:street":"Rue Saint-Alphonse N",
    "iso:country":"CA",
    "sg:address":"693 Rue Saint-Alphonse N",
    "sg:city":"Thetford Mines",
    "sg:classifiers":[
        {
            "category":"Government",
            "subcategory":"Police Station",
            "type":"Public Place"
        }
    ],
    "sg:phone":"+1 418 338 3151",
    "sg:postcode":"G6G 3X3",
    "sg:province":"QC",
    "sg:tags":[
        "department"
    ],
    "wof:name":"Quebec Surete Du",
    "wof:placetype":"venue"
},
  "geometry": {"coordinates":[-71.2910614014,46.0836372375],"type":"Point"}
}