{
  "type": "Feature",
  "properties": {
    "iso:country":"CA",
    "sg:city":"Wetaskiwin",
    "sg:classifiers":[
        {
            "category":"Banks & Credit Unions",
            "subcategory":"Bank",
            "type":"Services"
        }
    ],
    "sg:phone":"+1 780 352 9261",
    "sg:postcode":"T9A 2V6",
    "sg:province":"AB",
    "wof:name":"Scotiabank",
    "wof:placetype":"venue"
},
  "geometry": {"coordinates":[-113.389854,52.954975],"type":"Point"}
}