{
  "type": "Feature",
  "properties": {
    "addr:full":"14 Rue Acadie Bouctouche NB E4S 2T2",
    "addr:housenumber":"14",
    "addr:postcode":"e4s 2t2",
    "addr:street":"Rue Acadie",
    "iso:country":"CA",
    "sg:address":"14 Rue Acadie",
    "sg:city":"Bouctouche",
    "sg:classifiers":[
        {
            "category":"Travel",
            "subcategory":"Travel Agent",
            "type":"Entertainment"
        }
    ],
    "sg:phone":"+1 506 743 8811",
    "sg:postcode":"E4S 2T2",
    "sg:province":"NB",
    "sg:tags":[
        "information",
        "tourist"
    ],
    "wof:name":"Centre D'Information Aux",
    "wof:placetype":"venue"
},
  "geometry": {"coordinates":[-64.71835299999999,46.471771],"type":"Point"}
}