{
  "type": "Feature",
  "properties": {
    "addr:full":"Chilliwack BC V2R 3N3",
    "addr:postcode":"v2r 3n3",
    "iso:country":"CA",
    "sg:city":"Chilliwack",
    "sg:classifiers":[
        {
            "category":"Shopping",
            "subcategory":"Bicycles & Sporting Goods",
            "type":"Retail Goods"
        }
    ],
    "sg:phone":"+1 604 858 3011",
    "sg:postcode":"V2R 3N3",
    "sg:province":"BC",
    "wof:name":"Jack's Cycle",
    "wof:placetype":"venue"
},
  "geometry": {"coordinates":[-121.958946228,49.1067085266],"type":"Point"}
}