{
  "type": "Feature",
  "properties": {
    "addr:full":"201 Centre St Rosedale Station AB T0J 2V0",
    "addr:housenumber":"201",
    "addr:postcode":"t0j 2v0",
    "addr:street":"Centre St",
    "iso:country":"CA",
    "sg:address":"201 Centre St",
    "sg:city":"Rosedale Station",
    "sg:classifiers":[
        {
            "category":"Manufacturing",
            "subcategory":"Apparel",
            "type":"Manufacturing & Wholesale Goods"
        }
    ],
    "sg:phone":"+1 403 823 6252",
    "sg:postcode":"T0J 2V0",
    "sg:province":"AB",
    "sg:tags":[
        "tarpaulin"
    ],
    "wof:name":"Inland Plastics Ltd",
    "wof:placetype":"venue"
},
  "geometry": {"coordinates":[-112.631889,51.418919],"type":"Point"}
}