{
  "type": "Feature",
  "properties": {
    "addr:full":"285 Shuter St Toronto ON M5A 1W5",
    "addr:housenumber":"285",
    "addr:postcode":"m5a 1w5",
    "addr:street":"Shuter St",
    "iso:country":"CA",
    "sg:address":"285 Shuter St",
    "sg:city":"Toronto",
    "sg:classifiers":[
        {
            "category":"Professional",
            "subcategory":"Management & Consulting",
            "type":"Services"
        }
    ],
    "sg:phone":"+1 416 777 1702",
    "sg:postcode":"M5A 1W5",
    "sg:province":"ON",
    "sg:tags":[
        "consultant",
        "business"
    ],
    "wof:name":"Holmes Whitaker & Assoc",
    "wof:placetype":"venue"
},
  "geometry": {"coordinates":[-79.367035,43.656406],"type":"Point"}
}