{
  "type": "Feature",
  "properties": {
    "addr:full":"20 Edinburgh Dr Mount Pearl NL A1N 1E8",
    "addr:housenumber":"20",
    "addr:postcode":"a1n 1e8",
    "addr:street":"Edinburgh Dr",
    "iso:country":"CA",
    "sg:address":"20 Edinburgh Dr",
    "sg:city":"Mount Pearl",
    "sg:classifiers":[
        {
            "category":"Building & Trades",
            "subcategory":"Electrical",
            "type":"Services"
        }
    ],
    "sg:phone":"+1 709 364 7393",
    "sg:postcode":"A1N 1E8",
    "sg:province":"NL",
    "sg:tags":[
        "electric",
        "contractor"
    ],
    "wof:name":"Unique Electric Ltd",
    "wof:placetype":"venue"
},
  "geometry": {"coordinates":[-52.809299,47.516747],"type":"Point"}
}