{
  "type": "Feature",
  "properties": {
    "addr:full":"New Westminster BC V3M 1A5",
    "addr:postcode":"v3m 1a5",
    "iso:country":"CA",
    "sg:city":"New Westminster",
    "sg:classifiers":[
        {
            "category":"Professional",
            "subcategory":"Management & Consulting",
            "type":"Services"
        }
    ],
    "sg:phone":"+1 604 526 7706",
    "sg:postcode":"V3M 1A5",
    "sg:province":"BC",
    "sg:tags":[
        "consultant",
        "business"
    ],
    "wof:name":"Fletcher & CO",
    "wof:placetype":"venue"
},
  "geometry": {"coordinates":[-122.907867,49.202995],"type":"Point"}
}