{
  "type": "Feature",
  "properties": {
    "addr:full":"200 North Service Rd W Oakville ON L6M 2Y1",
    "addr:housenumber":"200",
    "addr:postcode":"l6m 2y1",
    "addr:street":"North Service Rd W",
    "iso:country":"CA",
    "sg:address":"200 North Service Rd W",
    "sg:city":"Oakville",
    "sg:classifiers":[
        {
            "category":"Shopping",
            "subcategory":"Music",
            "type":"Retail Goods"
        }
    ],
    "sg:phone":"+1 905 842 7411",
    "sg:postcode":"L6M 2Y1",
    "sg:province":"ON",
    "sg:tags":[
        "compact",
        "record",
        "disc",
        "tape"
    ],
    "wof:name":"Hmv",
    "wof:placetype":"venue"
},
  "geometry": {"coordinates":[-79.70203399659999,43.450553894],"type":"Point"}
}