{
  "type": "Feature",
  "properties": {
    "addr:full":"289 Rue DE Cordoue Laval QC H7M 4P5",
    "addr:housenumber":"289",
    "addr:postcode":"h7m 4p5",
    "addr:street":"Rue De Cordoue",
    "iso:country":"CA",
    "sg:address":"289 Rue DE Cordoue",
    "sg:city":"Laval",
    "sg:classifiers":[
        {
            "category":"Real Estate",
            "subcategory":"Architect",
            "type":"Services"
        }
    ],
    "sg:phone":"+1 450 629 8322",
    "sg:postcode":"H7M 4P5",
    "sg:province":"QC",
    "wof:name":"Miron, Christian",
    "wof:placetype":"venue"
},
  "geometry": {"coordinates":[-73.71777299999999,45.610332],"type":"Point"}
}