{
  "type": "Feature",
  "properties": {
    "addr:full":"3219 Eby St # 101 Terrace BC V8G 4R3",
    "addr:housenumber":"3219",
    "addr:postcode":"v8g 4r3",
    "addr:street":"Eby St # 101",
    "iso:country":"CA",
    "sg:address":"3219 Eby St # 101",
    "sg:city":"Terrace",
    "sg:classifiers":[
        {
            "category":"Professional",
            "subcategory":"Lawyer & Legal Services",
            "type":"Services"
        }
    ],
    "sg:phone":"+1 250 638 1137",
    "sg:postcode":"V8G 4R3",
    "sg:province":"BC",
    "sg:tags":[
        "attorney"
    ],
    "wof:name":"Talstra & CO",
    "wof:placetype":"venue"
},
  "geometry": {"coordinates":[-128.59909057600001,54.5173492432],"type":"Point"}
}