{
  "type": "Feature",
  "properties": {
    "addr:full":"290 Rue DE Carillon Quebec QC G1K 5B2",
    "addr:housenumber":"290",
    "addr:postcode":"g1k 5b2",
    "addr:street":"Rue De Carillon",
    "iso:country":"CA",
    "sg:address":"290 Rue DE Carillon",
    "sg:city":"Quebec",
    "sg:classifiers":[
        {
            "category":"Recreation",
            "type":"Entertainment"
        }
    ],
    "sg:phone":"+1 418 648 2133",
    "sg:postcode":"G1K 5B2",
    "sg:province":"QC",
    "sg:tags":[
        "bingo",
        "game"
    ],
    "wof:name":"Bingo DE LA Pente Douce",
    "wof:placetype":"venue"
},
  "geometry": {"coordinates":[-71.2375488281,46.811668396],"type":"Point"}
}