{
  "type": "Feature",
  "properties": {
    "iso:country":"CA",
    "sg:city":"Nominingue",
    "sg:classifiers":[
        {
            "category":"Retail",
            "subcategory":"Auto Repair",
            "type":"Services"
        }
    ],
    "sg:phone":"+1 819 278 3214",
    "sg:postcode":"J0W 1R0",
    "sg:province":"QC",
    "sg:tags":[
        "repairing",
        "automobile",
        "painting"
    ],
    "wof:name":"Automobiles G Leclerc Ltee",
    "wof:placetype":"venue"
},
  "geometry": {"coordinates":[-75.0283279419,46.3955154419],"type":"Point"}
}