{
  "type": "Feature",
  "properties": {
    "addr:full":"2602 Boul Des Promenades Deux-Montagnes QC J7R 6L2",
    "addr:housenumber":"2602",
    "addr:postcode":"j7r 6l2",
    "addr:street":"Boul Des Promenades",
    "iso:country":"CA",
    "sg:address":"2602 Boul Des Promenades",
    "sg:city":"Deux-Montagnes",
    "sg:classifiers":[
        {
            "category":"Recreation",
            "type":"Entertainment"
        }
    ],
    "sg:phone":"+1 450 472 6202",
    "sg:postcode":"J7R 6L2",
    "sg:province":"QC",
    "sg:tags":[
        "skating",
        "rink"
    ],
    "wof:name":"Patinoire Deux Montagnes",
    "wof:placetype":"venue"
},
  "geometry": {"coordinates":[-73.919884,45.543072],"type":"Point"}
}