{
  "type": "Feature",
  "properties": {
    "addr:full":"1899 Merivale Rd Nepean ON K2G 1E7",
    "addr:housenumber":"1899",
    "addr:postcode":"k2g 1e7",
    "addr:street":"Merivale Rd",
    "iso:country":"CA",
    "sg:address":"1899 Merivale Rd",
    "sg:city":"Nepean",
    "sg:classifiers":[
        {
            "category":"Retail",
            "subcategory":"Auto Repair",
            "type":"Services"
        }
    ],
    "sg:phone":"+1 613 742 7878",
    "sg:postcode":"K2G 1E7",
    "sg:province":"ON",
    "sg:tags":[
        "repairing",
        "automobile",
        "rustproofing",
        "undercoating"
    ],
    "wof:name":"Metropolitan Rust Proofing",
    "wof:placetype":"venue"
},
  "geometry": {"coordinates":[-75.7215270996,45.3308105469],"type":"Point"}
}