{
  "type": "Feature",
  "properties": {
    "addr:full":"1039 Princess Ave Brandon MB R7A 4J5",
    "addr:housenumber":"1039",
    "addr:postcode":"r7a 4j5",
    "addr:street":"Princess Ave",
    "iso:country":"CA",
    "sg:address":"1039 Princess Ave",
    "sg:city":"Brandon",
    "sg:classifiers":[
        {
            "category":"Government",
            "subcategory":"Office",
            "type":"Public Place"
        }
    ],
    "sg:phone":"+1 204 726 7669",
    "sg:postcode":"R7A 4J5",
    "sg:province":"MB",
    "wof:name":"Canada Tax Svc Ofc",
    "wof:placetype":"venue"
},
  "geometry": {"coordinates":[-99.95199599999999,49.847057],"type":"Point"}
}