{
  "type": "Feature",
  "properties": {
    "addr:full":"Ormstown QC J0S 1K0",
    "addr:postcode":"j0s 1k0",
    "iso:country":"CA",
    "sg:city":"Ormstown",
    "sg:classifiers":[
        {
            "category":"Shopping",
            "subcategory":"Jewelry",
            "type":"Retail Goods"
        }
    ],
    "sg:phone":"+1 450 829 3998",
    "sg:postcode":"J0S 1K0",
    "sg:province":"QC",
    "sg:tags":[
        "jeweler"
    ],
    "wof:name":"Bijouterie Ormstown Enr",
    "wof:placetype":"venue"
},
  "geometry": {"coordinates":[-73.989456,45.12101],"type":"Point"}
}