{
  "type": "Feature",
  "properties": {
    "addr:full":"2770 Aberdeen Rd Westbank BC V4T 1J3",
    "addr:housenumber":"2770",
    "addr:postcode":"v4t 1j3",
    "addr:street":"Aberdeen Rd",
    "iso:country":"CA",
    "sg:address":"2770 Aberdeen Rd",
    "sg:city":"Westbank",
    "sg:classifiers":[
        {
            "category":"Building & Trades",
            "subcategory":"Construction",
            "type":"Services"
        }
    ],
    "sg:phone":"+1 250 768 7847",
    "sg:postcode":"V4T 1J3",
    "sg:province":"BC",
    "sg:tags":[
        "excavating",
        "demolition",
        "contractor"
    ],
    "wof:name":"Drew Blasting Ltd",
    "wof:placetype":"venue"
},
  "geometry": {"coordinates":[-119.647140503,49.834941864],"type":"Point"}
}