{
  "type": "Feature",
  "properties": {
    "addr:full":"161 Bay St Toronto ON M5J 2S1",
    "addr:housenumber":"161",
    "addr:postcode":"m5j 2s1",
    "addr:street":"Bay St",
    "iso:country":"CA",
    "sg:address":"161 Bay St",
    "sg:city":"Toronto",
    "sg:classifiers":[
        {
            "category":"Restaurant",
            "type":"Food & Drink"
        }
    ],
    "sg:phone":"+1 416 862 9000",
    "sg:postcode":"M5J 2S1",
    "sg:province":"ON",
    "wof:name":"Piazza Manna",
    "wof:placetype":"venue"
},
  "geometry": {"coordinates":[-79.379158,43.646511],"type":"Point"}
}