{
  "type": "Feature",
  "properties": {
    "iso:country":"CA",
    "sg:address":"714 Queenston Rd",
    "sg:city":"Hamilton",
    "sg:classifiers":[
        {
            "category":"Shopping",
            "subcategory":"Gifts & Souvenirs",
            "type":"Retail Goods"
        }
    ],
    "sg:phone":"+1 905 578 1881",
    "sg:postcode":"L8G 1A2",
    "sg:province":"ON",
    "sg:tags":[
        "party",
        "supply"
    ],
    "wof:name":"Paper Factory",
    "wof:placetype":"venue"
},
  "geometry": {"coordinates":[-79.77099609379999,43.2292938232],"type":"Point"}
}