{
  "type": "Feature",
  "properties": {
    "addr:full":"129 Cliff St Yarmouth NS B5A 3K1",
    "addr:housenumber":"129",
    "addr:postcode":"b5a 3k1",
    "addr:street":"Cliff St",
    "iso:country":"CA",
    "sg:address":"129 Cliff St",
    "sg:city":"Yarmouth",
    "sg:classifiers":[
        {
            "category":"Freight",
            "type":"Transportation"
        }
    ],
    "sg:phone":"+1 902 749 4560",
    "sg:postcode":"B5A 3K1",
    "sg:province":"NS",
    "sg:tags":[
        "trucking"
    ],
    "wof:name":"Armour Transportation Systems",
    "wof:placetype":"venue"
},
  "geometry": {"coordinates":[-66.107224,43.834362],"type":"Point"}
}