{
  "type": "Feature",
  "properties": {
    "addr:full":"Etobicoke ON M8V 1J7",
    "addr:postcode":"m8v 1j7",
    "iso:country":"CA",
    "sg:city":"Etobicoke",
    "sg:classifiers":[
        {
            "category":"Professional",
            "subcategory":"Management & Consulting",
            "type":"Services"
        }
    ],
    "sg:phone":"+1 416 252 2889",
    "sg:postcode":"M8V 1J7",
    "sg:province":"ON",
    "sg:tags":[
        "aviation",
        "consultant"
    ],
    "wof:name":"Star Navigation Systems Group",
    "wof:placetype":"venue"
},
  "geometry": {"coordinates":[-79.50629425050001,43.6007080078],"type":"Point"}
}