{
  "type": "Feature",
  "properties": {
    "addr:full":"9651 102 Ave NW Edmonton AB T5H 0E5",
    "addr:housenumber":"9651",
    "addr:postcode":"t5h 0e5",
    "addr:street":"102 Ave Nw",
    "iso:country":"CA",
    "sg:address":"9651 102 Ave NW",
    "sg:city":"Edmonton",
    "sg:classifiers":[
        {
            "category":"Manufacturing",
            "subcategory":"Tools & Machinery",
            "type":"Manufacturing & Wholesale Goods"
        }
    ],
    "sg:phone":"+1 780 428 4575",
    "sg:postcode":"T5H 0E5",
    "sg:province":"AB",
    "sg:tags":[
        "model",
        "maker"
    ],
    "wof:name":"Ellis Associates Ltd",
    "wof:placetype":"venue"
},
  "geometry": {"coordinates":[-113.48434399999999,53.544189],"type":"Point"}
}