{
  "type": "Feature",
  "properties": {
    "addr:full":"6395 Parkhouse Dr Melbourne ON N0L 1T0",
    "addr:housenumber":"6395",
    "addr:postcode":"n0l 1t0",
    "addr:street":"Parkhouse Dr",
    "iso:country":"CA",
    "sg:address":"6395 Parkhouse Dr",
    "sg:city":"Melbourne",
    "sg:classifiers":[
        {
            "category":"Recreation",
            "type":"Entertainment"
        }
    ],
    "sg:phone":"+1 519 289 2011",
    "sg:postcode":"N0L 1T0",
    "sg:province":"ON",
    "sg:tags":[
        "course",
        "golf"
    ],
    "wof:name":"Gentleman Creek Golf Club Ltd",
    "wof:placetype":"venue"
},
  "geometry": {"coordinates":[-81.5837860107,42.8279914856],"type":"Point"}
}