{
  "type": "Feature",
  "properties": {
    "addr:full":"10 King St W Dundas ON L9H 1T7",
    "addr:housenumber":"10",
    "addr:postcode":"l9h 1t7",
    "addr:street":"King St W",
    "iso:country":"CA",
    "sg:address":"10 King St W",
    "sg:city":"Dundas",
    "sg:classifiers":[
        {
            "category":"Shopping",
            "type":"Retail Goods"
        }
    ],
    "sg:phone":"+1 905 627 4265",
    "sg:postcode":"L9H 1T7",
    "sg:province":"ON",
    "sg:tags":[
        "art",
        "gallery",
        "dealer"
    ],
    "wof:name":"Carnegie Gallery",
    "wof:placetype":"venue"
},
  "geometry": {"coordinates":[-79.9547195435,43.2661323547],"type":"Point"}
}