{
  "type": "Feature",
  "properties": {
    "addr:full":"214 66 St Delta BC V4L 1M8",
    "addr:housenumber":"214 66",
    "addr:postcode":"v4l 1m8",
    "addr:street":"St",
    "iso:country":"CA",
    "sg:address":"214 66 St",
    "sg:city":"Delta",
    "sg:classifiers":[
        {
            "category":"Building & Trades",
            "subcategory":"Plumbing",
            "type":"Services"
        }
    ],
    "sg:phone":"+1 604 943 5792",
    "sg:postcode":"V4L 1M8",
    "sg:province":"BC",
    "sg:tags":[
        "contractor"
    ],
    "wof:name":"King Plumbing & Heating Ltd",
    "wof:placetype":"venue"
},
  "geometry": {"coordinates":[-123.040916,49.006378],"type":"Point"}
}