{
  "type": "Feature",
  "properties": {
    "addr:full":"586 Boul St-Pierre O Caraquet NB E1W 1A2",
    "addr:housenumber":"586",
    "addr:postcode":"e1w 1a2",
    "addr:street":"Boul St-Pierre O",
    "iso:country":"CA",
    "sg:address":"586 Boul St-Pierre O",
    "sg:city":"Caraquet",
    "sg:classifiers":[
        {
            "category":"Retail",
            "subcategory":"Repair Shop",
            "type":"Services"
        }
    ],
    "sg:phone":"+1 506 727 9090",
    "sg:postcode":"E1W 1A2",
    "sg:province":"NB",
    "sg:tags":[
        "taxidermist"
    ],
    "wof:name":"Tannerie Taxidermie Caraquet",
    "wof:placetype":"venue"
},
  "geometry": {"coordinates":[-65.0127792358,47.7732925415],"type":"Point"}
}