{
  "type": "Feature",
  "properties": {
    "addr:full":"77 Dufferin St Bridgewater NS B4V 3W8",
    "addr:housenumber":"77",
    "addr:postcode":"b4v 3w8",
    "addr:street":"Dufferin St",
    "iso:country":"CA",
    "sg:address":"77 Dufferin St",
    "sg:city":"Bridgewater",
    "sg:classifiers":[
        {
            "category":"Government",
            "subcategory":"Office",
            "type":"Public Place"
        }
    ],
    "sg:phone":"+1 902 527 5524",
    "sg:postcode":"B4V 3W8",
    "sg:province":"NS",
    "wof:name":"Human Resource Ctr of Canada",
    "wof:placetype":"venue"
},
  "geometry": {"coordinates":[-64.51860000000001,44.374054],"type":"Point"}
}