{
  "type": "Feature",
  "properties": {
    "addr:full":"3011 31 Ave Vernon BC V1T 2G6",
    "addr:housenumber":"3011",
    "addr:postcode":"v1t 2g6",
    "addr:street":"31 Ave",
    "iso:country":"CA",
    "sg:address":"3011 31 Ave",
    "sg:city":"Vernon",
    "sg:classifiers":[
        {
            "category":"Shopping",
            "subcategory":"Florist",
            "type":"Retail Goods"
        }
    ],
    "sg:phone":"+1 250 545 2181",
    "sg:postcode":"V1T 2G6",
    "sg:province":"BC",
    "wof:name":"Vernon Flower Shop",
    "wof:placetype":"venue"
},
  "geometry": {"coordinates":[-119.271011,50.264778],"type":"Point"}
}