{
  "type": "Feature",
  "properties": {
    "addr:full":"31 Saint Phillips Rd Etobicoke ON M9P 2N7",
    "addr:housenumber":"31",
    "addr:postcode":"m9p 2n7",
    "addr:street":"Saint Phillips Rd",
    "iso:country":"CA",
    "sg:address":"31 Saint Phillips Rd",
    "sg:city":"Etobicoke",
    "sg:classifiers":[
        {
            "category":"Organizations",
            "subcategory":"Religious Organization",
            "type":"Services"
        }
    ],
    "sg:phone":"+1 416 247 5181",
    "sg:postcode":"M9P 2N7",
    "sg:province":"ON",
    "sg:tags":[
        "church"
    ],
    "wof:name":"St Philip's Anglican Church",
    "wof:placetype":"venue"
},
  "geometry": {"coordinates":[-79.533455,43.701168],"type":"Point"}
}