{
  "type": "Feature",
  "properties": {
    "addr:full":"3629 Rue Ontario E Montreal QC H1W 1R8",
    "addr:housenumber":"3629",
    "addr:postcode":"h1w 1r8",
    "addr:street":"Rue Ontario E",
    "iso:country":"CA",
    "sg:address":"3629 Rue Ontario E",
    "sg:city":"Montreal",
    "sg:classifiers":[
        {
            "category":"Home & Garden",
            "subcategory":"Carpets & Floor Coverings",
            "type":"Retail Goods"
        }
    ],
    "sg:phone":"+1 514 522 1767",
    "sg:postcode":"H1W 1R8",
    "sg:province":"QC",
    "sg:tags":[
        "dealer",
        "rug"
    ],
    "wof:name":"Tapis Lm Peinture",
    "wof:placetype":"venue"
},
  "geometry": {"coordinates":[-73.544785,45.545502],"type":"Point"}
}