{
  "type": "Feature",
  "properties": {
    "iso:country":"CA",
    "sg:address":"148 Hillsview Dr",
    "sg:city":"Richmond Hill",
    "sg:classifiers":[
        {
            "category":"Building & Trades",
            "subcategory":"Landscaping Services",
            "type":"Services"
        }
    ],
    "sg:phone":"+1 905 884 9481",
    "sg:postcode":"L4C 1T2",
    "sg:province":"ON",
    "sg:tags":[
        "landscape",
        "contractor"
    ],
    "wof:name":"Avalon Landscaping Tech Inc",
    "wof:placetype":"venue"
},
  "geometry": {"coordinates":[-79.421822,43.865227],"type":"Point"}
}