{
  "type": "Feature",
  "properties": {
    "addr:full":"148 Hillsview Dr Richmond Hill ON L4C 1T2",
    "addr:housenumber":"148",
    "addr:postcode":"l4c 1t2",
    "addr:street":"Hillsview Dr",
    "iso:country":"CA",
    "sg:address":"148 Hillsview Dr",
    "sg:city":"Richmond Hill",
    "sg:classifiers":[
        {
            "category":"Building & Trades",
            "subcategory":"Landscaping Services",
            "type":"Services"
        }
    ],
    "sg:phone":"+1 905 884 9481",
    "sg:postcode":"L4C 1T2",
    "sg:province":"ON",
    "sg:tags":[
        "landscape",
        "contractor"
    ],
    "wof:name":"Avalon Landscaping Tech Inc",
    "wof:placetype":"venue"
},
  "geometry": {"coordinates":[-79.42182200000001,43.865227],"type":"Point"}
}