{
  "type": "Feature",
  "properties": {
    "addr:full":"Concord ON L4K 1T7",
    "addr:postcode":"l4k 1t7",
    "iso:country":"CA",
    "sg:city":"Concord",
    "sg:classifiers":[
        {
            "category":"Personal",
            "subcategory":"Beauty Salon",
            "type":"Services"
        }
    ],
    "sg:phone":"+1 905 738 1262",
    "sg:postcode":"L4K 1T7",
    "sg:province":"ON",
    "wof:name":"Unisex Beauty Salon",
    "wof:placetype":"venue"
},
  "geometry": {"coordinates":[-79.47756195069999,43.7916145325],"type":"Point"}
}