{
  "type": "Feature",
  "properties": {
    "addr:full":"Quebec QC G2K 2E4",
    "addr:postcode":"g2k 2e4",
    "iso:country":"CA",
    "sg:city":"Quebec",
    "sg:classifiers":[
        {
            "category":"Banks & Credit Unions",
            "subcategory":"Investment Brokerage",
            "type":"Services"
        }
    ],
    "sg:phone":"+1 418 621 7491",
    "sg:postcode":"G2K 2E4",
    "sg:province":"QC",
    "sg:tags":[
        "retirement",
        "planning"
    ],
    "wof:name":"Privilege Retraite Inc",
    "wof:placetype":"venue"
},
  "geometry": {"coordinates":[-71.296783,46.83548],"type":"Point"}
}