{
  "type": "Feature",
  "properties": {
    "addr:full":"1568 Hollis St #500 Halifax NS B3J 1V3",
    "addr:housenumber":"1568",
    "addr:postcode":"ns b3j 1v3",
    "addr:street":"Hollis St # 500",
    "iso:country":"CA",
    "sg:address":"1568 Hollis St #500",
    "sg:city":"Halifax",
    "sg:classifiers":[
        {
            "category":"Professional",
            "subcategory":"Lawyer & Legal Services",
            "type":"Services"
        }
    ],
    "sg:phone":"+1 902 425 6000",
    "sg:postcode":"B3J 1V3",
    "sg:province":"NS",
    "sg:tags":[
        "attorney"
    ],
    "wof:name":"Mac Keigan, Pamela J",
    "wof:placetype":"venue"
},
  "geometry": {"coordinates":[-63.572067,44.645676],"type":"Point"}
}