{
  "type": "Feature",
  "properties": {
    "iso:country":"CA",
    "sg:city":"London",
    "sg:classifiers":[
        {
            "category":"Professional",
            "subcategory":"Lawyer & Legal Services",
            "type":"Services"
        }
    ],
    "sg:phone":"+1 519 434 6881",
    "sg:postcode":"N6A 5P6",
    "sg:province":"ON",
    "sg:tags":[
        "attorney"
    ],
    "wof:name":"Stoddart, Robert C",
    "wof:placetype":"venue"
},
  "geometry": {"coordinates":[-81.249115,42.993244],"type":"Point"}
}