{
  "type": "Feature",
  "properties": {
    "iso:country":"CA",
    "sg:address":"1403 Central Ave",
    "sg:city":"Prince Albert",
    "sg:classifiers":[
        {
            "category":"Restaurant",
            "type":"Food & Drink"
        }
    ],
    "sg:phone":"+1 306 922 1488",
    "sg:postcode":"S6V 7J4",
    "sg:province":"SK",
    "wof:name":"A & W Family Restaurant",
    "wof:placetype":"venue"
},
  "geometry": {"coordinates":[-105.754501,53.199947],"type":"Point"}
}