{
  "type": "Feature",
  "properties": {
    "addr:full":"525 Welland Ave #14 St Catharines ON L2M 6P3",
    "addr:housenumber":"525",
    "addr:postcode":"l2m 6p3",
    "addr:street":"Welland Ave # 14",
    "iso:country":"CA",
    "sg:address":"525 Welland Ave #14",
    "sg:city":"St Catharines",
    "sg:classifiers":[
        {
            "category":"Food & Beverages",
            "subcategory":"Bakery",
            "type":"Retail Goods"
        }
    ],
    "sg:phone":"+1 905 682 3935",
    "sg:postcode":"L2M 6P3",
    "sg:province":"ON",
    "sg:tags":[
        "doughnut"
    ],
    "wof:name":"Tim Hortons",
    "wof:placetype":"venue"
},
  "geometry": {"coordinates":[-79.2119216919,43.1761016846],"type":"Point"}
}