{
  "type": "Feature",
  "properties": {
    "addr:full":"450 Matheson Blvd E # 52 Mississauga ON L4Z 1R5",
    "addr:housenumber":"450",
    "addr:postcode":"l4z 1r5",
    "addr:street":"Matheson Blvd E # 52",
    "iso:country":"CA",
    "sg:address":"450 Matheson Blvd E # 52",
    "sg:city":"Mississauga",
    "sg:classifiers":[
        {
            "category":"Wholesale",
            "subcategory":"Computers",
            "type":"Manufacturing & Wholesale Goods"
        }
    ],
    "sg:phone":"+1 905 712 8818",
    "sg:postcode":"L4Z 1R5",
    "sg:province":"ON",
    "wof:name":"Goldiwell Enterprises Inc",
    "wof:placetype":"venue"
},
  "geometry": {"coordinates":[-79.656654,43.625381],"type":"Point"}
}