{
  "type": "Feature",
  "properties": {
    "iso:country":"CA",
    "sg:address":"450 Boul Lebeau",
    "sg:city":"Saint-Laurent",
    "sg:classifiers":[
        {
            "category":"Shopping",
            "subcategory":"Department Store",
            "type":"Retail Goods"
        }
    ],
    "sg:phone":"+1 514 335 6255",
    "sg:postcode":"H4N 1R7",
    "sg:province":"QC",
    "wof:name":"Michael Rossy Ltee",
    "wof:placetype":"venue"
},
  "geometry": {"coordinates":[-73.660316,45.526157],"type":"Point"}
}