{
  "type": "Feature",
  "properties": {
    "addr:full":"450 Boul Lebeau Saint-Laurent QC H4N 1R7",
    "addr:housenumber":"450",
    "addr:postcode":"h4n 1r7",
    "addr:street":"Boul Lebeau",
    "iso:country":"CA",
    "sg:address":"450 Boul Lebeau",
    "sg:city":"Saint-Laurent",
    "sg:classifiers":[
        {
            "category":"Shopping",
            "subcategory":"Department Store",
            "type":"Retail Goods"
        }
    ],
    "sg:phone":"+1 514 335 6255",
    "sg:postcode":"H4N 1R7",
    "sg:province":"QC",
    "wof:name":"Michael Rossy Ltee",
    "wof:placetype":"venue"
},
  "geometry": {"coordinates":[-73.66031599999999,45.526157],"type":"Point"}
}