{
  "type": "Feature",
  "properties": {
    "addr:full":"Red Deer AB T4P 2A6",
    "addr:postcode":"t4p 2a6",
    "iso:country":"CA",
    "sg:city":"Red Deer",
    "sg:classifiers":[
        {
            "category":"Real Estate",
            "subcategory":"Developer",
            "type":"Services"
        }
    ],
    "sg:phone":"+1 403 346 9111",
    "sg:postcode":"T4P 2A6",
    "sg:province":"AB",
    "sg:tags":[
        "mobile",
        "home"
    ],
    "wof:name":"Northwoods Estates Mobile Home",
    "wof:placetype":"venue"
},
  "geometry": {"coordinates":[-113.820747376,52.3033218384],"type":"Point"}
}