{
  "type": "Feature",
  "properties": {
    "addr:full":"711 Cote DE LA Place-D'Armes Montreal QC H2Y 2X6",
    "addr:housenumber":"711",
    "addr:postcode":"h2y 2x6",
    "addr:street":"Cote De La Place-D'Armes",
    "iso:country":"CA",
    "sg:address":"711 Cote DE LA Place-D'Armes",
    "sg:city":"Montreal",
    "sg:classifiers":[
        {
            "category":"Restaurant",
            "type":"Food & Drink"
        }
    ],
    "sg:phone":"+1 514 843 3837",
    "sg:postcode":"H2Y 2X6",
    "sg:province":"QC",
    "wof:name":"Restaurant Nava",
    "wof:placetype":"venue"
},
  "geometry": {"coordinates":[-73.5570449829,45.5050430298],"type":"Point"}
}