{
  "type": "Feature",
  "properties": {
    "addr:full":"234 Victor Rd Prescott ON K0E 1T0",
    "addr:housenumber":"234",
    "addr:postcode":"k0e 1t0",
    "addr:street":"Victor Rd",
    "iso:country":"CA",
    "sg:address":"234 Victor Rd",
    "sg:city":"Prescott",
    "sg:classifiers":[
        {
            "category":"Organizations",
            "subcategory":"Professional Association",
            "type":"Services"
        }
    ],
    "sg:phone":"+1 613 925 0479",
    "sg:postcode":"K0E 1T0",
    "sg:province":"ON",
    "wof:name":"Prescott & District Lions Club",
    "wof:placetype":"venue"
},
  "geometry": {"coordinates":[-75.52621499999999,44.720661],"type":"Point"}
}