{
  "type": "Feature",
  "properties": {
    "iso:country":"CA",
    "sg:address":"234 Victor Rd",
    "sg:city":"Prescott",
    "sg:classifiers":[
        {
            "category":"Organizations",
            "subcategory":"Professional Association",
            "type":"Services"
        }
    ],
    "sg:phone":"+1 613 925 0479",
    "sg:postcode":"K0E 1T0",
    "sg:province":"ON",
    "wof:name":"Prescott & District Lions Club",
    "wof:placetype":"venue"
},
  "geometry": {"coordinates":[-75.526215,44.720661],"type":"Point"}
}