{
  "type": "Feature",
  "properties": {
    "addr:full":"Edmonton AB T5J 2Z2",
    "addr:postcode":"t5j 2z2",
    "iso:country":"CA",
    "sg:city":"Edmonton",
    "sg:classifiers":[
        {
            "category":"Real Estate",
            "subcategory":"Real Estate Operator",
            "type":"Services"
        }
    ],
    "sg:phone":"+1 780 426 8444",
    "sg:postcode":"T5J 2Z2",
    "sg:province":"AB",
    "sg:tags":[
        "mall",
        "shopping",
        "center"
    ],
    "wof:name":"Edmonton City Centre",
    "wof:placetype":"venue"
},
  "geometry": {"coordinates":[-113.493431,53.543591],"type":"Point"}
}