{
  "type": "Feature",
  "properties": {
    "iso:country":"CA",
    "sg:city":"Vancouver",
    "sg:classifiers":[
        {
            "category":"Insurance",
            "subcategory":"Insurance Agent",
            "type":"Services"
        }
    ],
    "sg:phone":"+1 604 687 6333",
    "sg:postcode":"V6E 4M3",
    "sg:province":"BC",
    "sg:tags":[
        "consultant"
    ],
    "wof:name":"Hodsman Financial Svc",
    "wof:placetype":"venue"
},
  "geometry": {"coordinates":[-123.123336792,49.2860832214],"type":"Point"}
}