{
  "type": "Feature",
  "properties": {
    "addr:full":"Lachute QC J8H 3Y3",
    "addr:postcode":"j8h 3y3",
    "iso:country":"CA",
    "sg:city":"Lachute",
    "sg:classifiers":[
        {
            "category":"Restaurant",
            "type":"Food & Drink"
        }
    ],
    "sg:phone":"+1 450 562 7810",
    "sg:postcode":"J8H 3Y3",
    "sg:province":"QC",
    "wof:name":"Casse-Croute Chez Bruno",
    "wof:placetype":"venue"
},
  "geometry": {"coordinates":[-74.349625,45.633793],"type":"Point"}
}