{
  "type": "Feature",
  "properties": {
    "addr:full":"6810 50 Ave Stettler AB T0C 2L2",
    "addr:housenumber":"6810",
    "addr:postcode":"t0c 2l2",
    "addr:street":"50 Ave",
    "iso:country":"CA",
    "sg:address":"6810 50 Ave",
    "sg:city":"Stettler",
    "sg:classifiers":[
        {
            "category":"Retail",
            "subcategory":"Auto Rental",
            "type":"Services"
        }
    ],
    "sg:phone":"+1 403 742 1749",
    "sg:postcode":"T0C 2L2",
    "sg:province":"AB",
    "sg:tags":[
        "renting",
        "truck",
        "leasing"
    ],
    "wof:name":"U-Haul CO Ltd",
    "wof:placetype":"venue"
},
  "geometry": {"coordinates":[-112.738426,52.32526],"type":"Point"}
}