{
  "type": "Feature",
  "properties": {
    "addr:full":"563 Rue Saint-Clement Montreal QC H1V 3C8",
    "addr:housenumber":"563",
    "addr:postcode":"h1v 3c8",
    "addr:street":"Rue Saint-Clement",
    "iso:country":"CA",
    "sg:address":"563 Rue Saint-Clement",
    "sg:city":"Montreal",
    "sg:classifiers":[
        {
            "category":"Manufacturing",
            "subcategory":"Printing",
            "type":"Manufacturing & Wholesale Goods"
        }
    ],
    "sg:phone":"+1 514 251 1280",
    "sg:postcode":"H1V 3C8",
    "sg:province":"QC",
    "sg:tags":[
        "printer"
    ],
    "wof:name":"Imprimerie Express",
    "wof:placetype":"venue"
},
  "geometry": {"coordinates":[-73.529419,45.556519],"type":"Point"}
}