{
  "type": "Feature",
  "properties": {
    "addr:full":"6403 Bowness Rd NW Calgary AB T3B 0E6",
    "addr:housenumber":"6403",
    "addr:postcode":"t3b 0e6",
    "addr:street":"Bowness Rd Nw",
    "iso:country":"CA",
    "sg:address":"6403 Bowness Rd NW",
    "sg:city":"Calgary",
    "sg:classifiers":[
        {
            "category":"Shopping",
            "subcategory":"Pharmacy",
            "type":"Retail Goods"
        }
    ],
    "sg:phone":"+1 403 288 2211",
    "sg:postcode":"T3B 0E6",
    "sg:province":"AB",
    "wof:name":"Bowness Drug Ltd",
    "wof:placetype":"venue"
},
  "geometry": {"coordinates":[-114.180328,51.085636],"type":"Point"}
}