{
  "type": "Feature",
  "properties": {
    "addr:full":"715 1st Ave W Meadow Lake SK S9X 1N1",
    "addr:housenumber":"715",
    "addr:postcode":"s9x 1n1",
    "addr:street":"1St Ave W Meadow",
    "iso:country":"CA",
    "sg:address":"715 1st Ave W",
    "sg:city":"Meadow Lake",
    "sg:classifiers":[
        {
            "category":"Food & Beverages",
            "subcategory":"Groceries & Convenience Stores",
            "type":"Retail Goods"
        }
    ],
    "sg:phone":"+1 306 236 6585",
    "sg:postcode":"S9X 1N1",
    "sg:province":"SK",
    "sg:tags":[
        "grocer"
    ],
    "wof:name":"Ed's Wholesale Groceries",
    "wof:placetype":"venue"
},
  "geometry": {"coordinates":[-108.441727,54.133259],"type":"Point"}
}