{
  "type": "Feature",
  "properties": {
    "iso:country":"CA",
    "sg:address":"1 Dawnridge Trail",
    "sg:city":"Brampton",
    "sg:classifiers":[
        {
            "category":"Building & Trades",
            "subcategory":"Construction",
            "type":"Services"
        }
    ],
    "sg:phone":"+1 905 846 9666",
    "sg:postcode":"L6Z 1Z7",
    "sg:province":"ON",
    "sg:tags":[
        "general",
        "contractor"
    ],
    "wof:name":"Eclar Construction Ltd",
    "wof:placetype":"venue"
},
  "geometry": {"coordinates":[-79.8074874878,43.7312850952],"type":"Point"}
}