{
  "type": "Feature",
  "properties": {
    "addr:full":"12780 Peggys Cove Rd Tantallon NS B3Z 2M9",
    "addr:housenumber":"12780",
    "addr:postcode":"b3z 2m9",
    "addr:street":"Peggys Cove Rd",
    "iso:country":"CA",
    "sg:address":"12780 Peggys Cove Rd",
    "sg:city":"Tantallon",
    "sg:classifiers":[
        {
            "category":"Retail",
            "subcategory":"Auto Repair",
            "type":"Services"
        }
    ],
    "sg:phone":"+1 902 826 1000",
    "sg:postcode":"B3Z 2M9",
    "sg:province":"NS",
    "sg:tags":[
        "repairing",
        "automobile"
    ],
    "wof:name":"Masons Auto Works",
    "wof:placetype":"venue"
},
  "geometry": {"coordinates":[-63.900421,44.661411],"type":"Point"}
}