{
  "type": "Feature",
  "properties": {
    "addr:full":"2553 Pinewood Dr Winnipeg MB R3J 0C3",
    "addr:housenumber":"2553",
    "addr:postcode":"r3j 0c3",
    "addr:street":"Pinewood Dr",
    "iso:country":"CA",
    "sg:address":"2553 Pinewood Dr",
    "sg:city":"Winnipeg",
    "sg:classifiers":[
        {
            "category":"Building & Trades",
            "subcategory":"Construction",
            "type":"Services"
        }
    ],
    "sg:phone":"+1 204 885 1330",
    "sg:postcode":"R3J 0C3",
    "sg:province":"MB",
    "sg:tags":[
        "foundation"
    ],
    "wof:name":"Sturgeon Construction Found",
    "wof:placetype":"venue"
},
  "geometry": {"coordinates":[-97.261032,49.873962],"type":"Point"}
}