{
  "type": "Feature",
  "properties": {
    "addr:full":"2272 Rue Notre-Dame E Thetford Mines QC G6G 2W2",
    "addr:housenumber":"2272",
    "addr:postcode":"g6g 2w2",
    "addr:street":"Rue Notre-Dame E",
    "iso:country":"CA",
    "sg:address":"2272 Rue Notre-Dame E",
    "sg:city":"Thetford Mines",
    "sg:classifiers":[
        {
            "category":"Autos & Motor Vehicles",
            "subcategory":"Automobile Sales",
            "type":"Retail Goods"
        }
    ],
    "sg:phone":"+1 418 338 4665",
    "sg:postcode":"G6G 2W2",
    "sg:province":"QC",
    "sg:tags":[
        "car",
        "dealer"
    ],
    "wof:name":"Automobiles Hyundai Ruby Auto",
    "wof:placetype":"venue"
},
  "geometry": {"coordinates":[-71.1822280884,46.1642150879],"type":"Point"}
}