{
  "type": "Feature",
  "properties": {
    "addr:full":"Langley BC V2Y 1A2",
    "addr:postcode":"v2y 1a2",
    "iso:country":"CA",
    "sg:city":"Langley",
    "sg:classifiers":[
        {
            "category":"Shopping",
            "subcategory":"Clothing, Apparel, & Fashions",
            "type":"Retail Goods"
        }
    ],
    "sg:phone":"+1 604 514 6801",
    "sg:postcode":"V2Y 1A2",
    "sg:province":"BC",
    "sg:tags":[
        "leather"
    ],
    "wof:name":"Danier Leather",
    "wof:placetype":"venue"
},
  "geometry": {"coordinates":[-122.669014,49.113926],"type":"Point"}
}