{
  "type": "Feature",
  "properties": {
    "addr:full":"Gatineau QC J8T 6H8",
    "addr:postcode":"j8t 6h8",
    "iso:country":"CA",
    "sg:city":"Gatineau",
    "sg:classifiers":[
        {
            "category":"Retail",
            "subcategory":"Auto Rental",
            "type":"Services"
        }
    ],
    "sg:phone":"+1 819 243 3935",
    "sg:postcode":"J8T 6H8",
    "sg:province":"QC",
    "sg:tags":[
        "renting",
        "automobile"
    ],
    "wof:name":"Enterprise Rent-A-Car",
    "wof:placetype":"venue"
},
  "geometry": {"coordinates":[-75.700996,45.479523],"type":"Point"}
}