{
  "type": "Feature",
  "properties": {
    "iso:country":"CA",
    "sg:city":"Bentley",
    "sg:classifiers":[
        {
            "category":"Personal",
            "subcategory":"Beauty Salon",
            "type":"Services"
        }
    ],
    "sg:phone":"+1 403 748 4321",
    "sg:postcode":"T0C 0J0",
    "sg:province":"AB",
    "wof:name":"Moonlighting Hair Studio",
    "wof:placetype":"venue"
},
  "geometry": {"coordinates":[-114.04248809800001,52.4663124084],"type":"Point"}
}