{
  "type": "Feature",
  "properties": {
    "addr:full":"22662 Komoka Rd Komoka ON N0L 1R0",
    "addr:housenumber":"22662",
    "addr:postcode":"n0l 1r0",
    "addr:street":"Komoka Rd",
    "iso:country":"CA",
    "sg:address":"22662 Komoka Rd",
    "sg:city":"Komoka",
    "sg:classifiers":[
        {
            "category":"Home & Garden",
            "subcategory":"Carpets & Floor Coverings",
            "type":"Retail Goods"
        }
    ],
    "sg:phone":"+1 519 473 4444",
    "sg:postcode":"N0L 1R0",
    "sg:province":"ON",
    "sg:tags":[
        "material"
    ],
    "wof:name":"Four City Tile & Flooring",
    "wof:placetype":"venue"
},
  "geometry": {"coordinates":[-81.439163208,42.9510650635],"type":"Point"}
}