{
  "type": "Feature",
  "properties": {
    "addr:full":"162 Elm St Ottawa ON K1R 6N5",
    "addr:housenumber":"162",
    "addr:postcode":"k1r 6n5",
    "addr:street":"Elm St",
    "iso:country":"CA",
    "sg:address":"162 Elm St",
    "sg:city":"Ottawa",
    "sg:classifiers":[
        {
            "category":"Wholesale",
            "subcategory":"Hardware",
            "type":"Manufacturing & Wholesale Goods"
        }
    ],
    "sg:phone":"+1 613 230 7160",
    "sg:postcode":"K1R 6N5",
    "sg:province":"ON",
    "sg:tags":[
        "equipment",
        "heating",
        "system"
    ],
    "wof:name":"Powrmatic of Canada Ltd",
    "wof:placetype":"venue"
},
  "geometry": {"coordinates":[-75.7167816162,45.4090423584],"type":"Point"}
}