{
  "type": "Feature",
  "properties": {
    "addr:full":"105 Dundas St W Mississauga ON L5B 1H8",
    "addr:housenumber":"105",
    "addr:postcode":"l5b 1h8",
    "addr:street":"Dundas St W",
    "iso:country":"CA",
    "sg:address":"105 Dundas St W",
    "sg:city":"Mississauga",
    "sg:classifiers":[
        {
            "category":"Cinema",
            "subcategory":"Movie Rental",
            "type":"Entertainment"
        }
    ],
    "sg:phone":"+1 905 306 1380",
    "sg:postcode":"L5B 1H8",
    "sg:province":"ON",
    "sg:tags":[
        "leasing",
        "video",
        "disc",
        "tape"
    ],
    "wof:name":"Vicar Marketing",
    "wof:placetype":"venue"
},
  "geometry": {"coordinates":[-79.6191940308,43.5779457092],"type":"Point"}
}