{
  "type": "Feature",
  "properties": {
    "addr:full":"Calgary AB T2V 0E4",
    "addr:postcode":"t2v 0e4",
    "iso:country":"CA",
    "sg:city":"Calgary",
    "sg:classifiers":[
        {
            "category":"Professional",
            "subcategory":"Lawyer & Legal Services",
            "type":"Services"
        }
    ],
    "sg:phone":"+1 403 259 5041",
    "sg:postcode":"T2V 0E4",
    "sg:province":"AB",
    "sg:tags":[
        "attorney"
    ],
    "wof:name":"Hookenson, Clarence J",
    "wof:placetype":"venue"
},
  "geometry": {"coordinates":[-114.08329000000001,50.993153],"type":"Point"}
}