{
  "type": "Feature",
  "properties": {
    "addr:full":"Truro NS B2N 2K3",
    "addr:postcode":"b2n 2k3",
    "iso:country":"CA",
    "sg:city":"Truro",
    "sg:classifiers":[
        {
            "category":"Real Estate",
            "subcategory":"Real Estate Operator",
            "type":"Services"
        }
    ],
    "sg:phone":"+1 902 893 4403",
    "sg:postcode":"B2N 2K3",
    "sg:province":"NS",
    "sg:tags":[
        "apartment"
    ],
    "wof:name":"Village Court Apartments",
    "wof:placetype":"venue"
},
  "geometry": {"coordinates":[-63.2740745544,45.3632507324],"type":"Point"}
}