{
  "type": "Feature",
  "properties": {
    "addr:full":"3705 Queens Line Tilbury ON N0P 2L0",
    "addr:housenumber":"3705",
    "addr:postcode":"n0p 2l0",
    "addr:street":"Queens Line",
    "iso:country":"CA",
    "sg:address":"3705 Queens Line",
    "sg:city":"Tilbury",
    "sg:classifiers":[
        {
            "category":"Home & Garden",
            "subcategory":"Building Materials",
            "type":"Retail Goods"
        }
    ],
    "sg:phone":"+1 519 682 1354",
    "sg:postcode":"N0P 2L0",
    "sg:province":"ON",
    "sg:tags":[
        "door"
    ],
    "wof:name":"Ducana Windows & Doors Ltd",
    "wof:placetype":"venue"
},
  "geometry": {"coordinates":[-82.414513,42.266788],"type":"Point"}
}