{
  "type": "Feature",
  "properties": {
    "addr:full":"474 Main St Selkirk MB R1A 1W2",
    "addr:housenumber":"474",
    "addr:postcode":"r1a 1w2",
    "addr:street":"Main St",
    "iso:country":"CA",
    "sg:address":"474 Main St",
    "sg:city":"Selkirk",
    "sg:classifiers":[
        {
            "category":"Home & Garden",
            "subcategory":"Carpets & Floor Coverings",
            "type":"Retail Goods"
        }
    ],
    "sg:phone":"+1 204 482 4404",
    "sg:postcode":"R1A 1W2",
    "sg:province":"MB",
    "sg:tags":[
        "rug",
        "flooring"
    ],
    "wof:name":"Hart's House of Flooring",
    "wof:placetype":"venue"
},
  "geometry": {"coordinates":[-96.868149,50.147453],"type":"Point"}
}