{
  "type": "Feature",
  "properties": {
    "iso:country":"CA",
    "sg:city":"Mackenzie",
    "sg:classifiers":[
        {
            "category":"Organizations",
            "subcategory":"Professional Association",
            "type":"Services"
        }
    ],
    "sg:phone":"+1 250 997 3557",
    "sg:postcode":"V0J 2C0",
    "sg:province":"BC",
    "sg:tags":[
        "club"
    ],
    "wof:name":"Mac Kenzie Elks Lodge",
    "wof:placetype":"venue"
},
  "geometry": {"coordinates":[-123.0965271,55.3361167908],"type":"Point"}
}