{
  "type": "Feature",
  "properties": {
    "addr:full":"1786 Italy Cross Rd Petite-Riviere-Bridge NS B0J 2P0",
    "addr:housenumber":"1786",
    "addr:postcode":"b0j 2p0",
    "addr:street":"Italy Cross Rd",
    "iso:country":"CA",
    "sg:address":"1786 Italy Cross Rd",
    "sg:city":"Petite-Riviere-Bridge",
    "sg:classifiers":[
        {
            "category":"Building & Trades",
            "subcategory":"Electrical",
            "type":"Services"
        }
    ],
    "sg:phone":"+1 902 688 2175",
    "sg:postcode":"B0J 2P0",
    "sg:province":"NS",
    "sg:tags":[
        "electric",
        "contractor"
    ],
    "wof:name":"C Edwin Sperry Electrical Ltd",
    "wof:placetype":"venue"
},
  "geometry": {"coordinates":[-64.45236199999999,44.235912],"type":"Point"}
}