{
  "type": "Feature",
  "properties": {
    "iso:country":"CA",
    "sg:address":"1555 Regent Ave W",
    "sg:city":"Winnipeg",
    "sg:classifiers":[
        {
            "category":"Shopping",
            "subcategory":"Clothing, Apparel, & Fashions",
            "type":"Retail Goods"
        }
    ],
    "sg:phone":"+1 204 663 3730",
    "sg:postcode":"R2C 4J2",
    "sg:province":"MB",
    "sg:tags":[
        "item",
        "boutique"
    ],
    "wof:name":"Le Chateau",
    "wof:placetype":"venue"
},
  "geometry": {"coordinates":[-97.06182861329999,49.897277832],"type":"Point"}
}