{
  "type": "Feature",
  "properties": {
    "addr:full":"Coquitlam BC V3K 3N9",
    "addr:postcode":"v3k 3n9",
    "iso:country":"CA",
    "sg:city":"Coquitlam",
    "sg:classifiers":[
        {
            "category":"Professional",
            "subcategory":"Lawyer & Legal Services",
            "type":"Services"
        }
    ],
    "sg:phone":"+1 604 939 8321",
    "sg:postcode":"V3K 3N9",
    "sg:province":"BC",
    "sg:tags":[
        "attorney"
    ],
    "wof:name":"Orstad, Sharene D",
    "wof:placetype":"venue"
},
  "geometry": {"coordinates":[-122.866478,49.249107],"type":"Point"}
}