{
  "type": "Feature",
  "properties": {
    "addr:full":"10576 104 St NW Edmonton AB T5H 2W1",
    "addr:housenumber":"10576",
    "addr:postcode":"t5h 2w1",
    "addr:street":"104 St Nw",
    "iso:country":"CA",
    "sg:address":"10576 104 St NW",
    "sg:city":"Edmonton",
    "sg:classifiers":[
        {
            "category":"Organizations",
            "subcategory":"Labor Organization",
            "type":"Services"
        }
    ],
    "sg:phone":"+1 780 426 7545",
    "sg:postcode":"T5H 2W1",
    "sg:province":"AB",
    "wof:name":"Bricklayers Union",
    "wof:placetype":"venue"
},
  "geometry": {"coordinates":[-113.499336243,53.5492362976],"type":"Point"}
}