{
  "type": "Feature",
  "properties": {
    "addr:full":"8041 204 Rte Lac-Megantic QC G6B 2S1",
    "addr:housenumber":"8041",
    "addr:postcode":"g6b 2s1",
    "addr:street":"204 Rte Lac-Megantic",
    "iso:country":"CA",
    "sg:address":"8041 204 Rte",
    "sg:city":"Lac-Megantic",
    "sg:classifiers":[
        {
            "category":"Bars & Pubs",
            "type":"Food & Drink"
        }
    ],
    "sg:phone":"+1 819 583 4588",
    "sg:postcode":"G6B 2S1",
    "sg:province":"QC",
    "sg:tags":[
        "lounge",
        "cocktail"
    ],
    "wof:name":"Bar Sportif",
    "wof:placetype":"venue"
},
  "geometry": {"coordinates":[-70.87944030760001,45.572593689],"type":"Point"}
}