{
  "type": "Feature",
  "properties": {
    "iso:country":"CA",
    "sg:city":"Montreal",
    "sg:classifiers":[
        {
            "category":"Professional",
            "subcategory":"Accounting & Tax Preparation",
            "type":"Services"
        }
    ],
    "sg:phone":"+1 514 342 8787",
    "sg:postcode":"H4P 2H2",
    "sg:province":"QC",
    "sg:tags":[
        "accountant"
    ],
    "wof:name":"Shapiro Baer",
    "wof:placetype":"venue"
},
  "geometry": {"coordinates":[-73.65715789790001,45.4974937439],"type":"Point"}
}