{
  "type": "Feature",
  "properties": {
    "addr:full":"75 Bruyere St Ottawa ON K1N 5C7",
    "addr:housenumber":"75",
    "addr:postcode":"k1n 5c7",
    "addr:street":"Bruyere St",
    "iso:country":"CA",
    "sg:address":"75 Bruyere St",
    "sg:city":"Ottawa",
    "sg:classifiers":[
        {
            "category":"Health Services",
            "subcategory":"Doctor",
            "type":"Services"
        }
    ],
    "sg:phone":"+1 613 244 0006",
    "sg:postcode":"K1N 5C7",
    "sg:province":"ON",
    "sg:tags":[
        "clinic"
    ],
    "wof:name":"New Edinburgh Family Medical",
    "wof:placetype":"venue"
},
  "geometry": {"coordinates":[-75.6958770752,45.4323158264],"type":"Point"}
}