{
  "type": "Feature",
  "properties": {
    "addr:full":"481 Ellesmere Ave Burnaby BC V5B 3T3",
    "addr:housenumber":"481",
    "addr:postcode":"v5b 3t3",
    "addr:street":"Ellesmere Ave",
    "iso:country":"CA",
    "sg:address":"481 Ellesmere Ave",
    "sg:city":"Burnaby",
    "sg:classifiers":[
        {
            "category":"Manufacturing",
            "subcategory":"Tools & Machinery",
            "type":"Manufacturing & Wholesale Goods"
        }
    ],
    "sg:phone":"+1 604 299 2977",
    "sg:postcode":"V5B 3T3",
    "sg:province":"BC",
    "sg:tags":[
        "contractor"
    ],
    "wof:name":"Adriatic Concrete Cutting",
    "wof:placetype":"venue"
},
  "geometry": {"coordinates":[-122.982384,49.279793],"type":"Point"}
}