{
  "type": "Feature",
  "properties": {
    "addr:full":"Toronto ON M5G 2E9",
    "addr:postcode":"m5g 2e9",
    "iso:country":"CA",
    "sg:city":"Toronto",
    "sg:classifiers":[
        {
            "category":"Social Services",
            "subcategory":"Job Training",
            "type":"Services"
        }
    ],
    "sg:phone":"+1 416 977 3009",
    "sg:postcode":"M5G 2E9",
    "sg:province":"ON",
    "sg:tags":[
        "career",
        "counseling",
        "vocational"
    ],
    "wof:name":"Eisen Consulting Group Inc",
    "wof:placetype":"venue"
},
  "geometry": {"coordinates":[-79.3881530762,43.6552429199],"type":"Point"}
}