{
  "type": "Feature",
  "properties": {
    "addr:full":"30 Rte Seigneuriale Joly QC G0S 1M0",
    "addr:housenumber":"30",
    "addr:postcode":"g0s 1m0",
    "addr:street":"Rte Seigneuriale",
    "iso:country":"CA",
    "sg:address":"30 Rte Seigneuriale",
    "sg:city":"Joly",
    "sg:classifiers":[
        {
            "category":"Professional",
            "subcategory":"Testing Lab",
            "type":"Services"
        }
    ],
    "sg:phone":"+1 418 728 2408",
    "sg:postcode":"G0S 1M0",
    "sg:province":"QC",
    "sg:tags":[
        "soil"
    ],
    "wof:name":"Forages Boissonneault Inc",
    "wof:placetype":"venue"
},
  "geometry": {"coordinates":[-71.66822814939999,46.484752655],"type":"Point"}
}