{
  "type": "Feature",
  "properties": {
    "addr:full":"2114 College Ave Regina SK S4P 1C5",
    "addr:housenumber":"2114",
    "addr:postcode":"s4p 1c5",
    "addr:street":"College Ave",
    "iso:country":"CA",
    "sg:address":"2114 College Ave",
    "sg:city":"Regina",
    "sg:classifiers":[
        {
            "category":"Health Services",
            "subcategory":"Health Practitioner",
            "type":"Services"
        }
    ],
    "sg:phone":"+1 306 359 6111",
    "sg:postcode":"S4P 1C5",
    "sg:province":"SK",
    "sg:tags":[
        "psychologist"
    ],
    "wof:name":"Miller, Harold PhD",
    "wof:placetype":"venue"
},
  "geometry": {"coordinates":[-104.611153,50.441017],"type":"Point"}
}