{
  "type": "Feature",
  "properties": {
    "addr:full":"Maria QC G0C 1Y0",
    "addr:postcode":"g0c 1y0",
    "addr:street":"Maria",
    "iso:country":"CA",
    "sg:city":"Maria",
    "sg:classifiers":[
        {
            "category":"Government",
            "subcategory":"Office",
            "type":"Public Place"
        }
    ],
    "sg:phone":"+1 418 759 3308",
    "sg:postcode":"G0C 1Y0",
    "sg:province":"QC",
    "sg:tags":[
        "village"
    ],
    "wof:name":"Maria Maison Des Jeunes",
    "wof:placetype":"venue"
},
  "geometry": {"coordinates":[-65.98382599999999,48.172626],"type":"Point"}
}