{
  "type": "Feature",
  "properties": {
    "addr:full":"236 Margaret Ave Kitchener ON N2H 4J5",
    "addr:housenumber":"236",
    "addr:postcode":"n2h 4j5",
    "addr:street":"Margaret Ave",
    "iso:country":"CA",
    "sg:address":"236 Margaret Ave",
    "sg:city":"Kitchener",
    "sg:classifiers":[
        {
            "category":"Retail",
            "subcategory":"Laundry & Dry Cleaning",
            "type":"Services"
        }
    ],
    "sg:phone":"+1 519 570 4519",
    "sg:postcode":"N2H 4J5",
    "sg:province":"ON",
    "sg:tags":[
        "cleaners"
    ],
    "wof:name":"Prime Cleaners & Water Store",
    "wof:placetype":"venue"
},
  "geometry": {"coordinates":[-80.493645,43.462757],"type":"Point"}
}