{
  "type": "Feature",
  "properties": {
    "addr:full":"1660 Huron Church Rd Windsor ON N9C 2L1",
    "addr:housenumber":"1660",
    "addr:postcode":"n9c 2l1",
    "addr:street":"Huron Church Rd",
    "iso:country":"CA",
    "sg:address":"1660 Huron Church Rd",
    "sg:city":"Windsor",
    "sg:classifiers":[
        {
            "category":"Retail",
            "subcategory":"Auto Repair",
            "type":"Services"
        }
    ],
    "sg:phone":"+1 519 255 7799",
    "sg:postcode":"N9C 2L1",
    "sg:province":"ON",
    "sg:tags":[
        "repairing",
        "automobile"
    ],
    "wof:name":"Huron Automotive Svc",
    "wof:placetype":"venue"
},
  "geometry": {"coordinates":[-83.05726623539999,42.2865867615],"type":"Point"}
}