{
  "type": "Feature",
  "properties": {
    "addr:full":"72 Smith St E Yorkton SK S3N 2Y4",
    "addr:housenumber":"72",
    "addr:postcode":"s3n 2y4",
    "addr:street":"Smith St E",
    "iso:country":"CA",
    "sg:address":"72 Smith St E",
    "sg:city":"Yorkton",
    "sg:classifiers":[
        {
            "category":"Government",
            "subcategory":"Office",
            "type":"Public Place"
        }
    ],
    "sg:phone":"+1 306 786 1300",
    "sg:postcode":"S3N 2Y4",
    "sg:province":"SK",
    "wof:name":"Saskatchewan Welfare",
    "wof:placetype":"venue"
},
  "geometry": {"coordinates":[-102.45816000000001,51.211796],"type":"Point"}
}