{
  "type": "Feature",
  "properties": {
    "iso:country":"CA",
    "sg:address":"215 Main St N",
    "sg:city":"Carman",
    "sg:classifiers":[
        {
            "category":"Autos & Motor Vehicles",
            "subcategory":"Auto Supplies",
            "type":"Retail Goods"
        }
    ],
    "sg:phone":"+1 204 745 2076",
    "sg:postcode":"R0G 0J0",
    "sg:province":"MB",
    "sg:tags":[
        "repairing",
        "automobile"
    ],
    "wof:name":"Wes's Tire Shop",
    "wof:placetype":"venue"
},
  "geometry": {"coordinates":[-98.0015945435,49.5092544556],"type":"Point"}
}