{
  "type": "Feature",
  "properties": {
    "addr:full":"570 Ch Larocque Salaberry-DE-Valleyfield QC J6T 4C5",
    "addr:housenumber":"570",
    "addr:postcode":"j6t 4c5",
    "addr:street":"Ch Larocque",
    "iso:country":"CA",
    "sg:address":"570 Ch Larocque",
    "sg:city":"Salaberry-DE-Valleyfield",
    "sg:classifiers":[
        {
            "category":"Retail",
            "subcategory":"Auto Repair",
            "type":"Services"
        }
    ],
    "sg:phone":"+1 450 371 2881",
    "sg:postcode":"J6T 4C5",
    "sg:province":"QC",
    "sg:tags":[
        "repairing",
        "automobile"
    ],
    "wof:name":"Coin Du Camion Enr",
    "wof:placetype":"venue"
},
  "geometry": {"coordinates":[-74.121613,45.23687],"type":"Point"}
}