{
  "type": "Feature",
  "properties": {
    "addr:full":"4904 50 Ave Rocky Mountain House AB T4T 1C1",
    "addr:housenumber":"4904",
    "addr:postcode":"t4t 1c1",
    "addr:street":"50 Ave",
    "iso:country":"CA",
    "sg:address":"4904 50 Ave",
    "sg:city":"Rocky Mountain House",
    "sg:classifiers":[
        {
            "category":"Shopping",
            "subcategory":"Department Store",
            "type":"Retail Goods"
        }
    ],
    "sg:phone":"+1 403 845 6017",
    "sg:postcode":"T4T 1C1",
    "sg:province":"AB",
    "wof:name":"Saan Stores Ltd",
    "wof:placetype":"venue"
},
  "geometry": {"coordinates":[-114.917900085,52.3745117188],"type":"Point"}
}