{
  "type": "Feature",
  "properties": {
    "addr:full":"512 3E Rang N Saint-Charles-Sur-Richelieu QC J0H 2G0",
    "addr:housenumber":"512",
    "addr:postcode":"j0h 2g0",
    "addr:street":"3E Rang N",
    "iso:country":"CA",
    "sg:address":"512 3E Rang N",
    "sg:city":"Saint-Charles-Sur-Richelieu",
    "sg:classifiers":[
        {
            "category":"Travel",
            "subcategory":"Campground",
            "type":"Entertainment"
        }
    ],
    "sg:phone":"+1 450 584 2444",
    "sg:postcode":"J0H 2G0",
    "sg:province":"QC",
    "wof:name":"Camping Domaine Madalle",
    "wof:placetype":"venue"
},
  "geometry": {"coordinates":[-73.146805,45.686504],"type":"Point"}
}