{
  "type": "Feature",
  "properties": {
    "addr:full":"Calgary AB T2P 3P1",
    "addr:postcode":"t2p 3p1",
    "iso:country":"CA",
    "sg:city":"Calgary",
    "sg:classifiers":[
        {
            "category":"Health Services",
            "subcategory":"Clinic",
            "type":"Services"
        }
    ],
    "sg:phone":"+1 403 262 5002",
    "sg:postcode":"T2P 3P1",
    "sg:province":"AB",
    "sg:tags":[
        "physician",
        "program",
        "referral",
        "information"
    ],
    "wof:name":"S Skaken Naturopathic Med Inc",
    "wof:placetype":"venue"
},
  "geometry": {"coordinates":[-114.08013916,51.0459022522],"type":"Point"}
}