{
  "type": "Feature",
  "properties": {
    "addr:full":"420 Main St Selkirk MB R1A 1V3",
    "addr:housenumber":"420",
    "addr:postcode":"r1a 1v3",
    "addr:street":"Main St",
    "iso:country":"CA",
    "sg:address":"420 Main St",
    "sg:city":"Selkirk",
    "sg:classifiers":[
        {
            "category":"Travel",
            "subcategory":"Hotels & Motels",
            "type":"Entertainment"
        }
    ],
    "sg:phone":"+1 204 482 4334",
    "sg:postcode":"R1A 1V3",
    "sg:province":"MB",
    "wof:name":"Lord Selkirk Hotel Grill",
    "wof:placetype":"venue"
},
  "geometry": {"coordinates":[-96.871826,50.145222],"type":"Point"}
}