{
  "type": "Feature",
  "properties": {
    "addr:full":"12617 Fort Rd NW Edmonton AB T5C 3C2",
    "addr:housenumber":"12617",
    "addr:postcode":"t5c 3c2",
    "addr:street":"Fort Rd Nw",
    "iso:country":"CA",
    "sg:address":"12617 Fort Rd NW",
    "sg:city":"Edmonton",
    "sg:classifiers":[
        {
            "category":"Autos & Motor Vehicles",
            "subcategory":"Automobile Sales",
            "type":"Retail Goods"
        }
    ],
    "sg:phone":"+1 780 477 5055",
    "sg:postcode":"T5C 3C2",
    "sg:province":"AB",
    "sg:tags":[
        "car",
        "dealer"
    ],
    "wof:name":"Auto Wholesale Direct Inc",
    "wof:placetype":"venue"
},
  "geometry": {"coordinates":[-113.445137024,53.5840187073],"type":"Point"}
}