{
  "type": "Feature",
  "properties": {
    "iso:country":"CA",
    "sg:address":"PO Box 1032 STN Main",
    "sg:city":"Brooks",
    "sg:classifiers":[
        {
            "category":"Building & Trades",
            "subcategory":"Construction",
            "type":"Services"
        }
    ],
    "sg:phone":"+1 403 362 6637",
    "sg:postcode":"T1R 1B8",
    "sg:province":"AB",
    "wof:name":"Armor Building Systems Ltd",
    "wof:placetype":"venue"
},
  "geometry": {"coordinates":[-111.89849090600001,50.5658531189],"type":"Point"}
}