{
  "type": "Feature",
  "properties": {
    "addr:full":"4797 50 Ave Vegreville AB T9C 1K9",
    "addr:housenumber":"4797",
    "addr:postcode":"t9c 1k9",
    "addr:street":"50 Ave",
    "iso:country":"CA",
    "sg:address":"4797 50 Ave",
    "sg:city":"Vegreville",
    "sg:classifiers":[
        {
            "category":"Travel",
            "subcategory":"Hotels & Motels",
            "type":"Entertainment"
        }
    ],
    "sg:phone":"+1 780 632 3288",
    "sg:postcode":"T9C 1K9",
    "sg:province":"AB",
    "wof:name":"Vista Motel",
    "wof:placetype":"venue"
},
  "geometry": {"coordinates":[-112.04741668699999,53.4924049377],"type":"Point"}
}