{
  "type": "Feature",
  "properties": {
    "addr:full":"395 Kinchant St Quesnel BC V2J 2R5",
    "addr:housenumber":"395",
    "addr:postcode":"v2j 2r5",
    "addr:street":"Kinchant St",
    "iso:country":"CA",
    "sg:address":"395 Kinchant St",
    "sg:city":"Quesnel",
    "sg:classifiers":[
        {
            "category":"Banks & Credit Unions",
            "subcategory":"Investment Brokerage",
            "type":"Services"
        }
    ],
    "sg:phone":"+1 250 992 1028",
    "sg:postcode":"V2J 2R5",
    "sg:province":"BC",
    "wof:name":"Investors Group Financial Svc",
    "wof:placetype":"venue"
},
  "geometry": {"coordinates":[-122.494140625,52.9789276123],"type":"Point"}
}