{
  "type": "Feature",
  "properties": {
    "addr:full":"2122 Route 774 Wilsons Beach NB E5E 1L1",
    "addr:housenumber":"2122",
    "addr:postcode":"e5e 1l1",
    "addr:street":"Route 774",
    "iso:country":"CA",
    "sg:address":"2122 Route 774",
    "sg:city":"Wilsons Beach",
    "sg:classifiers":[
        {
            "category":"Food & Beverages",
            "subcategory":"Groceries & Convenience Stores",
            "type":"Retail Goods"
        }
    ],
    "sg:phone":"+1 506 752 2362",
    "sg:postcode":"E5E 1L1",
    "sg:province":"NB",
    "wof:name":"Harbour-View Variety",
    "wof:placetype":"venue"
},
  "geometry": {"coordinates":[-66.927612,44.925564],"type":"Point"}
}