{
  "type": "Feature",
  "properties": {
    "addr:full":"1280 Grande Cote Berthierville QC J0K 1A0",
    "addr:housenumber":"1280",
    "addr:postcode":"j0k 1a0",
    "addr:street":"Grande Cote",
    "iso:country":"CA",
    "sg:address":"1280 Grande Cote",
    "sg:city":"Berthierville",
    "sg:classifiers":[
        {
            "category":"Building & Trades",
            "subcategory":"Electrical",
            "type":"Services"
        }
    ],
    "sg:phone":"+1 450 836 1994",
    "sg:postcode":"J0K 1A0",
    "sg:province":"QC",
    "sg:tags":[
        "electric",
        "contractor"
    ],
    "wof:name":"Services Electriques Ch Inc",
    "wof:placetype":"venue"
},
  "geometry": {"coordinates":[-73.178467,46.080906],"type":"Point"}
}