{
  "type": "Feature",
  "properties": {
    "addr:full":"8730 10E Av Montreal QC H1Z 3B8",
    "addr:housenumber":"8730",
    "addr:postcode":"h1z 3b8",
    "addr:street":"10E Av",
    "iso:country":"CA",
    "sg:address":"8730 10E Av",
    "sg:city":"Montreal",
    "sg:classifiers":[
        {
            "category":"Manufacturing",
            "subcategory":"Tools & Machinery",
            "type":"Manufacturing & Wholesale Goods"
        }
    ],
    "sg:phone":"+1 514 723 0461",
    "sg:postcode":"H1Z 3B8",
    "sg:province":"QC",
    "sg:tags":[
        "motion",
        "picture",
        "supply"
    ],
    "wof:name":"Eclipse Groupe Ltee",
    "wof:placetype":"venue"
},
  "geometry": {"coordinates":[-73.621269,45.567947],"type":"Point"}
}