{
  "type": "Feature",
  "properties": {
    "addr:full":"4201 Boul Robert Montreal QC H1Z 1Y9",
    "addr:housenumber":"4201",
    "addr:postcode":"h1z 1y9",
    "addr:street":"Boul Robert",
    "iso:country":"CA",
    "sg:address":"4201 Boul Robert",
    "sg:city":"Montreal",
    "sg:classifiers":[
        {
            "category":"Restaurant",
            "type":"Food & Drink"
        }
    ],
    "sg:phone":"+1 514 376 3218",
    "sg:postcode":"H1Z 1Y9",
    "sg:province":"QC",
    "wof:name":"Mon Resto St-Michel",
    "wof:placetype":"venue"
},
  "geometry": {"coordinates":[-73.60972595210001,45.5763168335],"type":"Point"}
}