{
  "type": "Feature",
  "properties": {
    "addr:full":"214 Scott St Fort Frances ON P9A 1G7",
    "addr:housenumber":"214",
    "addr:postcode":"p9a 1g7",
    "addr:street":"Scott St",
    "iso:country":"CA",
    "sg:address":"214 Scott St",
    "sg:city":"Fort Frances",
    "sg:classifiers":[
        {
            "category":"Shopping",
            "subcategory":"Jewelry",
            "type":"Retail Goods"
        }
    ],
    "sg:phone":"+1 807 274 9880",
    "sg:postcode":"P9A 1G7",
    "sg:province":"ON",
    "sg:tags":[
        "jeweler"
    ],
    "wof:name":"Mario's Jewellers Inc",
    "wof:placetype":"venue"
},
  "geometry": {"coordinates":[-93.39798,48.610111],"type":"Point"}
}