{
  "type": "Feature",
  "properties": {
    "addr:full":"273 Parkview Hills Dr Cobourg ON K9A 5S3",
    "addr:housenumber":"273",
    "addr:postcode":"k9a 5s3",
    "addr:street":"Parkview Hills Dr",
    "iso:country":"CA",
    "sg:address":"273 Parkview Hills Dr",
    "sg:city":"Cobourg",
    "sg:classifiers":[
        {
            "category":"Real Estate",
            "subcategory":"Real Estate Agent",
            "type":"Services"
        }
    ],
    "sg:phone":"+1 905 372 6990",
    "sg:postcode":"K9A 5S3",
    "sg:province":"ON",
    "sg:tags":[
        "appraiser"
    ],
    "wof:name":"Baayen & Assoc Ltd",
    "wof:placetype":"venue"
},
  "geometry": {"coordinates":[-78.1645812988,43.9849815369],"type":"Point"}
}