{
  "type": "Feature",
  "properties": {
    "addr:full":"Calgary AB T2S 0M3",
    "addr:postcode":"t2s 0m3",
    "iso:country":"CA",
    "sg:city":"Calgary",
    "sg:classifiers":[
        {
            "category":"Real Estate",
            "subcategory":"Architect",
            "type":"Services"
        }
    ],
    "sg:phone":"+1 403 660 6537",
    "sg:postcode":"T2S 0M3",
    "sg:province":"AB",
    "wof:name":"Hogge, Ron",
    "wof:placetype":"venue"
},
  "geometry": {"coordinates":[-114.06439971899999,51.0293312073],"type":"Point"}
}