{
  "type": "Feature",
  "properties": {
    "addr:full":"Waterloo ON N2J 4H7",
    "addr:postcode":"n2j 4h7",
    "iso:country":"CA",
    "sg:city":"Waterloo",
    "sg:classifiers":[
        {
            "category":"Food & Beverages",
            "subcategory":"Groceries & Convenience Stores",
            "type":"Retail Goods"
        }
    ],
    "sg:phone":"+1 519 885 0184",
    "sg:postcode":"N2J 4H7",
    "sg:province":"ON",
    "wof:name":"Glenridge Variety",
    "wof:placetype":"venue"
},
  "geometry": {"coordinates":[-80.50639343260001,43.4826698303],"type":"Point"}
}