{
  "type": "Feature",
  "properties": {
    "addr:full":"4880 Boul Bourque Rock Forest QC J1N 2A7",
    "addr:housenumber":"4880",
    "addr:postcode":"j1n 2a7",
    "addr:street":"Boul Bourque",
    "iso:country":"CA",
    "sg:address":"4880 Boul Bourque",
    "sg:city":"Rock Forest",
    "sg:classifiers":[
        {
            "category":"Autos & Motor Vehicles",
            "subcategory":"Automobile Sales",
            "type":"Retail Goods"
        }
    ],
    "sg:phone":"+1 819 823 1400",
    "sg:postcode":"J1N 2A7",
    "sg:province":"QC",
    "sg:tags":[
        "car",
        "dealer"
    ],
    "wof:name":"Sherbrooke Saturn Saab Isuzu",
    "wof:placetype":"venue"
},
  "geometry": {"coordinates":[-71.98709100000001,45.37162],"type":"Point"}
}