{
  "type": "Feature",
  "properties": {
    "iso:country":"CA",
    "sg:city":"Richmond Hill",
    "sg:classifiers":[
        {
            "category":"Professional",
            "subcategory":"Accounting & Tax Preparation",
            "type":"Services"
        }
    ],
    "sg:phone":"+1 905 886 4025",
    "sg:postcode":"L4B 1K1",
    "sg:province":"ON",
    "sg:tags":[
        "accountant"
    ],
    "wof:name":"Total Accounting & Tax Cnsltnt",
    "wof:placetype":"venue"
},
  "geometry": {"coordinates":[-79.388756,43.852489],"type":"Point"}
}