{
  "type": "Feature",
  "properties": {
    "addr:full":"1853 Grant Ave Winnipeg MB R3N 1Z2",
    "addr:housenumber":"1853",
    "addr:postcode":"r3n 1z2",
    "addr:street":"Grant Ave",
    "iso:country":"CA",
    "sg:address":"1853 Grant Ave",
    "sg:city":"Winnipeg",
    "sg:classifiers":[
        {
            "category":"Retail",
            "subcategory":"Car Wash",
            "type":"Services"
        }
    ],
    "sg:phone":"+1 204 489 9174",
    "sg:postcode":"R3N 1Z2",
    "sg:province":"MB",
    "sg:tags":[
        "polishing",
        "washing",
        "fence"
    ],
    "wof:name":"Qualified Mobile Wash",
    "wof:placetype":"venue"
},
  "geometry": {"coordinates":[-97.2033233643,49.8572807312],"type":"Point"}
}