{
  "type": "Feature",
  "properties": {
    "iso:country":"CA",
    "sg:address":"34 Eglinton Ave W",
    "sg:city":"Toronto",
    "sg:classifiers":[
        {
            "category":"Professional",
            "subcategory":"Advertising",
            "type":"Services"
        }
    ],
    "sg:phone":"+1 416 482 5855",
    "sg:postcode":"M4R 2H6",
    "sg:province":"ON",
    "sg:tags":[
        "mailing",
        "shipping",
        "courier"
    ],
    "wof:name":"Mail Boxes Etc",
    "wof:placetype":"venue"
},
  "geometry": {"coordinates":[-79.3997497559,43.7065811157],"type":"Point"}
}