{
  "type": "Feature",
  "properties": {
    "addr:full":"2073 Boul A. Paquette Mont-Laurier QC J9L 3G5",
    "addr:housenumber":"2073",
    "addr:postcode":"j9l 3g5",
    "addr:street":"Boul A. Paquette",
    "iso:country":"CA",
    "sg:address":"2073 Boul A. Paquette",
    "sg:city":"Mont-Laurier",
    "sg:classifiers":[
        {
            "category":"Building & Trades",
            "subcategory":"Construction",
            "type":"Services"
        }
    ],
    "sg:phone":"+1 819 623 3569",
    "sg:postcode":"J9L 3G5",
    "sg:province":"QC",
    "sg:tags":[
        "general",
        "contractor"
    ],
    "wof:name":"Construction Gilles Paquette",
    "wof:placetype":"venue"
},
  "geometry": {"coordinates":[-75.446747,46.547596],"type":"Point"}
}