{
  "type": "Feature",
  "properties": {
    "addr:full":"1345 Rosemount Ave Cornwall ON K6J 3E5",
    "addr:housenumber":"1345",
    "addr:postcode":"k6j 3e5",
    "addr:street":"Rosemount Ave",
    "iso:country":"CA",
    "sg:address":"1345 Rosemount Ave",
    "sg:city":"Cornwall",
    "sg:classifiers":[
        {
            "category":"Professional",
            "subcategory":"Engineering",
            "type":"Services"
        }
    ],
    "sg:phone":"+1 613 933 5602",
    "sg:postcode":"K6J 3E5",
    "sg:province":"ON",
    "sg:tags":[
        "architect"
    ],
    "wof:name":"Thompson Rosemount Group Inc",
    "wof:placetype":"venue"
},
  "geometry": {"coordinates":[-74.758865,45.028927],"type":"Point"}
}