{
  "type": "Feature",
  "properties": {
    "addr:full":"19015 Boul Des Acadiens Becancour QC G9H 1M5",
    "addr:housenumber":"19015",
    "addr:postcode":"g9h 1m5",
    "addr:street":"Boul Des Acadiens Becancour",
    "iso:country":"CA",
    "sg:address":"19015 Boul Des Acadiens",
    "sg:city":"Becancour",
    "sg:classifiers":[
        {
            "category":"Manufacturing",
            "subcategory":"Metals",
            "type":"Manufacturing & Wholesale Goods"
        }
    ],
    "sg:phone":"+1 819 233 2263",
    "sg:postcode":"G9H 1M5",
    "sg:province":"QC",
    "sg:tags":[
        "solder",
        "trailer"
    ],
    "wof:name":"Atelier DE Soudure St-Gregoire",
    "wof:placetype":"venue"
},
  "geometry": {"coordinates":[-72.523781,46.258865],"type":"Point"}
}