{
  "type": "Feature",
  "properties": {
    "addr:full":"915 Mcdonald St Regina SK S4N 2X5",
    "addr:housenumber":"915",
    "addr:postcode":"s4n 2x5",
    "addr:street":"Mcdonald St",
    "iso:country":"CA",
    "sg:address":"915 Mcdonald St",
    "sg:city":"Regina",
    "sg:classifiers":[
        {
            "category":"Building & Trades",
            "subcategory":"Construction",
            "type":"Services"
        }
    ],
    "sg:phone":"+1 306 569 0334",
    "sg:postcode":"S4N 2X5",
    "sg:province":"SK",
    "sg:tags":[
        "maker",
        "cabinet"
    ],
    "wof:name":"J Maslany Cabinet Mfg Ltd",
    "wof:placetype":"venue"
},
  "geometry": {"coordinates":[-104.58339700000001,50.46418],"type":"Point"}
}