{
  "type": "Feature",
  "properties": {
    "addr:full":"910 Westport Cres Mississauga ON L5T 1G1",
    "addr:housenumber":"910",
    "addr:postcode":"l5t 1g1",
    "addr:street":"Westport Cres",
    "iso:country":"CA",
    "sg:address":"910 Westport Cres",
    "sg:city":"Mississauga",
    "sg:classifiers":[
        {
            "category":"Wholesale",
            "subcategory":"Auto Parts",
            "type":"Manufacturing & Wholesale Goods"
        }
    ],
    "sg:phone":"+1 905 565 9891",
    "sg:postcode":"L5T 1G1",
    "sg:province":"ON",
    "sg:tags":[
        "automobile",
        "supply"
    ],
    "wof:name":"National Sales Inc",
    "wof:placetype":"venue"
},
  "geometry": {"coordinates":[-79.65709699999999,43.649021],"type":"Point"}
}