{
  "type": "Feature",
  "properties": {
    "addr:full":"140 Kingston Rd E Ajax ON L1Z 1G1",
    "addr:housenumber":"140",
    "addr:postcode":"l1z 1g1",
    "addr:street":"Kingston Rd E",
    "iso:country":"CA",
    "sg:address":"140 Kingston Rd E",
    "sg:city":"Ajax",
    "sg:classifiers":[
        {
            "category":"Shopping",
            "type":"Retail Goods"
        }
    ],
    "sg:phone":"+1 905 686 7089",
    "sg:postcode":"L1Z 1G1",
    "sg:province":"ON",
    "sg:tags":[
        "pet",
        "grooming",
        "washing",
        "supply"
    ],
    "wof:name":"Petcetera",
    "wof:placetype":"venue"
},
  "geometry": {"coordinates":[-79.023376,43.861988],"type":"Point"}
}