{
  "type": "Feature",
  "properties": {
    "iso:country":"CA",
    "sg:address":"441 Tranquille Rd",
    "sg:city":"Kamloops",
    "sg:classifiers":[
        {
            "category":"Professional",
            "subcategory":"Lawyer & Legal Services",
            "type":"Services"
        }
    ],
    "sg:phone":"+1 250 376 1211",
    "sg:postcode":"V2B 3G9",
    "sg:province":"BC",
    "sg:tags":[
        "attorney"
    ],
    "wof:name":"Plested, Roger",
    "wof:placetype":"venue"
},
  "geometry": {"coordinates":[-120.359085,50.691227],"type":"Point"}
}