{
  "type": "Feature",
  "properties": {
    "addr:full":"1246 Southview Dr Sudbury ON P3E 2L6",
    "addr:housenumber":"1246",
    "addr:postcode":"p3e 2l6",
    "addr:street":"Southview Dr",
    "iso:country":"CA",
    "sg:address":"1246 Southview Dr",
    "sg:city":"Sudbury",
    "sg:classifiers":[
        {
            "category":"Professional",
            "subcategory":"Business Services",
            "type":"Services"
        }
    ],
    "sg:phone":"+1 705 523 2327",
    "sg:postcode":"P3E 2L6",
    "sg:province":"ON",
    "sg:tags":[
        "drafting"
    ],
    "wof:name":"Homebuilders Design",
    "wof:placetype":"venue"
},
  "geometry": {"coordinates":[-81.014572,46.465446],"type":"Point"}
}