{
  "type": "Feature",
  "properties": {
    "addr:full":"1650 Rue Villeray Montreal QC H2E 1H4",
    "addr:housenumber":"1650",
    "addr:postcode":"h2e 1h4",
    "addr:street":"Rue Villeray",
    "iso:country":"CA",
    "sg:address":"1650 Rue Villeray",
    "sg:city":"Montreal",
    "sg:classifiers":[
        {
            "category":"Personal",
            "subcategory":"Barber",
            "type":"Services"
        }
    ],
    "sg:phone":"+1 514 721 0914",
    "sg:postcode":"H2E 1H4",
    "sg:province":"QC",
    "wof:name":"Dominic & Franco Coiffeurs",
    "wof:placetype":"venue"
},
  "geometry": {"coordinates":[-73.615005,45.550697],"type":"Point"}
}