{
  "type": "Feature",
  "properties": {
    "addr:full":"1205 Highbury Ave N London ON N5Y 1A6",
    "addr:housenumber":"1205",
    "addr:postcode":"n5y 1a6",
    "addr:street":"Highbury Ave N",
    "iso:country":"CA",
    "sg:address":"1205 Highbury Ave N",
    "sg:city":"London",
    "sg:classifiers":[
        {
            "category":"Restaurant",
            "type":"Food & Drink"
        }
    ],
    "sg:phone":"+1 519 451 7555",
    "sg:postcode":"N5Y 1A6",
    "sg:province":"ON",
    "wof:name":"Fast Eddie's",
    "wof:placetype":"venue"
},
  "geometry": {"coordinates":[-81.2139205933,43.0167198181],"type":"Point"}
}