{
  "type": "Feature",
  "properties": {
    "addr:full":"125 Gibson Dr Markham ON L3R 3K7",
    "addr:housenumber":"125",
    "addr:postcode":"l3r 3k7",
    "addr:street":"Gibson Dr",
    "iso:country":"CA",
    "sg:address":"125 Gibson Dr",
    "sg:city":"Markham",
    "sg:classifiers":[
        {
            "category":"Wholesale",
            "subcategory":"Electrical",
            "type":"Manufacturing & Wholesale Goods"
        }
    ],
    "sg:phone":"+1 905 946 8972",
    "sg:postcode":"L3R 3K7",
    "sg:province":"ON",
    "sg:tags":[
        "equipment",
        "electronic",
        "supply"
    ],
    "wof:name":"Span Manufacturing Ltd",
    "wof:placetype":"venue"
},
  "geometry": {"coordinates":[-79.329208374,43.8229980469],"type":"Point"}
}