{
  "type": "Feature",
  "properties": {
    "addr:full":"769 Juliana Dr Woodstock ON N4V 1E9",
    "addr:housenumber":"769",
    "addr:postcode":"n4v 1e9",
    "addr:street":"Juliana Dr",
    "iso:country":"CA",
    "sg:address":"769 Juliana Dr",
    "sg:city":"Woodstock",
    "sg:classifiers":[
        {
            "category":"Organizations",
            "subcategory":"Religious Organization",
            "type":"Services"
        }
    ],
    "sg:phone":"+1 519 539 9345",
    "sg:postcode":"N4V 1E9",
    "sg:province":"ON",
    "sg:tags":[
        "church"
    ],
    "wof:name":"Salvation Army",
    "wof:placetype":"venue"
},
  "geometry": {"coordinates":[-80.739586,43.11335],"type":"Point"}
}