{
  "type": "Feature",
  "properties": {
    "iso:country":"CA",
    "sg:address":"132 Main St",
    "sg:city":"Fredericton",
    "sg:classifiers":[
        {
            "category":"Insurance",
            "subcategory":"Insurance Agent",
            "type":"Services"
        }
    ],
    "sg:phone":"+1 506 452 2327",
    "sg:postcode":"E3A 1C7",
    "sg:province":"NB",
    "wof:name":"Andrew H Williams Insurance",
    "wof:placetype":"venue"
},
  "geometry": {"coordinates":[-66.65574646,45.9791297913],"type":"Point"}
}