{
  "type": "Feature",
  "properties": {
    "addr:full":"Airdrie AB T4A 2G5",
    "addr:postcode":"t4a 2g5",
    "iso:country":"CA",
    "sg:city":"Airdrie",
    "sg:classifiers":[
        {
            "category":"Utilities",
            "subcategory":"Fuel Oil & Lpg",
            "type":"Services"
        }
    ],
    "sg:phone":"+1 403 912 8392",
    "sg:postcode":"T4A 2G5",
    "sg:province":"AB",
    "sg:tags":[
        "propane",
        "gas"
    ],
    "wof:name":"Federated CO-Operatives Ltd",
    "wof:placetype":"venue"
},
  "geometry": {"coordinates":[-113.994140625,51.2888450623],"type":"Point"}
}