{
  "type": "Feature",
  "properties": {
    "addr:full":"Toronto ON M4R 1V2",
    "addr:postcode":"m4r 1v2",
    "iso:country":"CA",
    "sg:city":"Toronto",
    "sg:classifiers":[
        {
            "category":"Local Transit",
            "type":"Transportation"
        }
    ],
    "sg:phone":"+1 416 818 9411",
    "sg:postcode":"M4R 1V2",
    "sg:province":"ON",
    "sg:tags":[
        "limousine"
    ],
    "wof:name":"Bay Street Executive Limo Svc",
    "wof:placetype":"venue"
},
  "geometry": {"coordinates":[-79.4004974365,43.7074165344],"type":"Point"}
}