{
  "type": "Feature",
  "properties": {
    "addr:full":"325 Boul Cremazie O Montreal QC H2N 1L9",
    "addr:housenumber":"325",
    "addr:postcode":"h2n 1l9",
    "addr:street":"Boul Cremazie O",
    "iso:country":"CA",
    "sg:address":"325 Boul Cremazie O",
    "sg:city":"Montreal",
    "sg:classifiers":[
        {
            "category":"Home & Garden",
            "subcategory":"Carpets & Floor Coverings",
            "type":"Retail Goods"
        }
    ],
    "sg:phone":"+1 514 385 1665",
    "sg:postcode":"H2N 1L9",
    "sg:province":"QC",
    "sg:tags":[
        "dealer",
        "rug"
    ],
    "wof:name":"Liquidation Escomptes Tapis",
    "wof:placetype":"venue"
},
  "geometry": {"coordinates":[-73.63975499999999,45.544754],"type":"Point"}
}