{
  "type": "Feature",
  "properties": {
    "addr:full":"76 Prince Charles Dr St Catharines ON L2N 3Z1",
    "addr:housenumber":"76",
    "addr:postcode":"l2n 3z1",
    "addr:street":"Prince Charles Dr",
    "iso:country":"CA",
    "sg:address":"76 Prince Charles Dr",
    "sg:city":"St Catharines",
    "sg:classifiers":[
        {
            "category":"Manufacturing",
            "subcategory":"Signs",
            "type":"Manufacturing & Wholesale Goods"
        }
    ],
    "sg:phone":"+1 905 646 4568",
    "sg:postcode":"L2N 3Z1",
    "sg:province":"ON",
    "wof:name":"Line Design",
    "wof:placetype":"venue"
},
  "geometry": {"coordinates":[-79.248161,43.198624],"type":"Point"}
}