{
  "type": "Feature",
  "properties": {
    "addr:full":"1450 Glen Abbey Gate Oakville ON L6M 2V7",
    "addr:housenumber":"1450",
    "addr:postcode":"l6m 2v7",
    "addr:street":"Glen Abbey Gate",
    "iso:country":"CA",
    "sg:address":"1450 Glen Abbey Gate",
    "sg:city":"Oakville",
    "sg:classifiers":[
        {
            "category":"Real Estate",
            "subcategory":"Real Estate Operator",
            "type":"Services"
        }
    ],
    "sg:phone":"+1 905 825 3327",
    "sg:postcode":"L6M 2V7",
    "sg:province":"ON",
    "sg:tags":[
        "apartment"
    ],
    "wof:name":"Glen Abbey Village",
    "wof:placetype":"venue"
},
  "geometry": {"coordinates":[-79.73640399999999,43.435474],"type":"Point"}
}