{
  "type": "Feature",
  "properties": {
    "addr:full":"17510 105 Ave NW Edmonton AB T5S 1G4",
    "addr:housenumber":"17510",
    "addr:postcode":"t5s 1g4",
    "addr:street":"105 Ave Nw",
    "iso:country":"CA",
    "sg:address":"17510 105 Ave NW",
    "sg:city":"Edmonton",
    "sg:classifiers":[
        {
            "category":"Shopping",
            "type":"Retail Goods"
        }
    ],
    "sg:phone":"+1 780 481 2412",
    "sg:postcode":"T5S 1G4",
    "sg:province":"AB",
    "sg:tags":[
        "orthopedic",
        "appliance"
    ],
    "wof:name":"Matrix Orthotics Repairs",
    "wof:placetype":"venue"
},
  "geometry": {"coordinates":[-113.622292,53.54874],"type":"Point"}
}