{
  "type": "Feature",
  "properties": {
    "addr:full":"50 George St N Cambridge ON N1S 2M8",
    "addr:housenumber":"50",
    "addr:postcode":"n1s 2m8",
    "addr:street":"George St N",
    "iso:country":"CA",
    "sg:address":"50 George St N",
    "sg:city":"Cambridge",
    "sg:classifiers":[
        {
            "category":"Health Services",
            "subcategory":"Doctor",
            "type":"Services"
        }
    ],
    "sg:phone":"+1 519 623 3438",
    "sg:postcode":"N1S 2M8",
    "sg:province":"ON",
    "sg:tags":[
        "physician",
        "surgeon"
    ],
    "wof:name":"Peirson, Glenn MD",
    "wof:placetype":"venue"
},
  "geometry": {"coordinates":[-80.31888600000001,43.360668],"type":"Point"}
}