{
  "type": "Feature",
  "properties": {
    "addr:full":"5095 9E Av Montreal QC H1Y 2J3",
    "addr:housenumber":"5095",
    "addr:postcode":"h1y 2j3",
    "addr:street":"9E Av",
    "iso:country":"CA",
    "sg:address":"5095 9E Av",
    "sg:city":"Montreal",
    "sg:classifiers":[
        {
            "category":"Social Services",
            "type":"Services"
        }
    ],
    "sg:phone":"+1 514 527 5188",
    "sg:postcode":"H1Y 2J3",
    "sg:province":"QC",
    "sg:tags":[
        "organization",
        "welfare"
    ],
    "wof:name":"Carrefour Familial Lintermede",
    "wof:placetype":"venue"
},
  "geometry": {"coordinates":[-73.5703201294,45.5489006042],"type":"Point"}
}