{
  "type": "Feature",
  "properties": {
    "addr:full":"302 Prince St Sydney NS B1P 5K6",
    "addr:housenumber":"302",
    "addr:postcode":"b1p 5k6",
    "addr:street":"Prince St",
    "iso:country":"CA",
    "sg:address":"302 Prince St",
    "sg:city":"Sydney",
    "sg:classifiers":[
        {
            "category":"Shopping",
            "subcategory":"Clothing, Apparel, & Fashions",
            "type":"Retail Goods"
        }
    ],
    "sg:phone":"+1 902 562 3177",
    "sg:postcode":"B1P 5K6",
    "sg:province":"NS",
    "wof:name":"Reitmans",
    "wof:placetype":"venue"
},
  "geometry": {"coordinates":[-60.185123,46.139397],"type":"Point"}
}