{
  "type": "Feature",
  "properties": {
    "addr:full":"98 Main St E Vankleek Hill ON K0B 1R0",
    "addr:housenumber":"98",
    "addr:postcode":"k0b 1r0",
    "addr:street":"Main St E Vankleek Hill",
    "iso:country":"CA",
    "sg:address":"98 Main St E",
    "sg:city":"Vankleek Hill",
    "sg:classifiers":[
        {
            "category":"Personal",
            "subcategory":"Barber",
            "type":"Services"
        }
    ],
    "sg:phone":"+1 613 678 3143",
    "sg:postcode":"K0B 1R0",
    "sg:province":"ON",
    "wof:name":"Vankleek Hill Barber Shop",
    "wof:placetype":"venue"
},
  "geometry": {"coordinates":[-74.649277,45.518776],"type":"Point"}
}