{
  "type": "Feature",
  "properties": {
    "iso:country":"CA",
    "sg:address":"320 Blake St",
    "sg:city":"Barrie",
    "sg:classifiers":[
        {
            "category":"Autos & Motor Vehicles",
            "subcategory":"Fuel & Gas Station",
            "type":"Retail Goods"
        }
    ],
    "sg:phone":"+1 705 727 1917",
    "sg:postcode":"L4M 1K9",
    "sg:province":"ON",
    "sg:tags":[
        "oil"
    ],
    "wof:name":"Sunoco",
    "wof:placetype":"venue"
},
  "geometry": {"coordinates":[-79.657272,44.397133],"type":"Point"}
}