{
  "type": "Feature",
  "properties": {
    "iso:country":"CA",
    "sg:address":"113 Rue Sylvio",
    "sg:city":"Beauport",
    "sg:classifiers":[
        {
            "category":"Building & Trades",
            "subcategory":"Electrical",
            "type":"Services"
        }
    ],
    "sg:phone":"+1 418 667 4337",
    "sg:postcode":"G1C 4H1",
    "sg:province":"QC",
    "sg:tags":[
        "electric",
        "contractor"
    ],
    "wof:name":"Regis Lepage Beauport Inc",
    "wof:placetype":"venue"
},
  "geometry": {"coordinates":[-71.1566162109,46.8911170959],"type":"Point"}
}