{
  "type": "Feature",
  "properties": {
    "addr:full":"55 Main St Mount Moriah NL A0L 1J0",
    "addr:housenumber":"55",
    "addr:postcode":"a0l 1j0",
    "addr:street":"Main St",
    "iso:country":"CA",
    "sg:address":"55 Main St",
    "sg:city":"Mount Moriah",
    "sg:classifiers":[
        {
            "category":"Food & Beverages",
            "subcategory":"Groceries & Convenience Stores",
            "type":"Retail Goods"
        }
    ],
    "sg:phone":"+1 709 785 2913",
    "sg:postcode":"A0L 1J0",
    "sg:province":"NL",
    "wof:name":"Cash & Carry",
    "wof:placetype":"venue"
},
  "geometry": {"coordinates":[-58.041412,48.968456],"type":"Point"}
}