{
  "type": "Feature",
  "properties": {
    "addr:full":"Calgary AB T2J 7C3",
    "addr:postcode":"t2j 7c3",
    "iso:country":"CA",
    "sg:city":"Calgary",
    "sg:classifiers":[
        {
            "category":"Cinema",
            "subcategory":"Movie Rental",
            "type":"Entertainment"
        }
    ],
    "sg:phone":"+1 403 271 2266",
    "sg:postcode":"T2J 7C3",
    "sg:province":"AB",
    "sg:tags":[
        "player",
        "recorder",
        "video",
        "leasing",
        "tape"
    ],
    "wof:name":"Blockbuster Video",
    "wof:placetype":"venue"
},
  "geometry": {"coordinates":[-114.063507,50.93037],"type":"Point"}
}