{
  "type": "Feature",
  "properties": {
    "addr:full":"20 Thornmount Dr Scarborough ON M1B 3J4",
    "addr:housenumber":"20",
    "addr:postcode":"m1b 3j4",
    "addr:street":"Thornmount Dr",
    "iso:country":"CA",
    "sg:address":"20 Thornmount Dr",
    "sg:city":"Scarborough",
    "sg:classifiers":[
        {
            "category":"Building & Trades",
            "subcategory":"Plumbing",
            "type":"Services"
        }
    ],
    "sg:phone":"+1 416 283 7374",
    "sg:postcode":"M1B 3J4",
    "sg:province":"ON",
    "sg:tags":[
        "sheet",
        "work",
        "metal",
        "contractor"
    ],
    "wof:name":"Metal Air Contractors Ltd",
    "wof:placetype":"venue"
},
  "geometry": {"coordinates":[-79.19652600000001,43.808426],"type":"Point"}
}