{
  "type": "Feature",
  "properties": {
    "addr:full":"3221 Wood Kilton Rd Dunrobin ON K0A 1T0",
    "addr:housenumber":"3221",
    "addr:postcode":"k0a 1t0",
    "addr:street":"Wood Kilton Rd",
    "iso:country":"CA",
    "sg:address":"3221 Wood Kilton Rd",
    "sg:city":"Dunrobin",
    "sg:classifiers":[
        {
            "category":"Taxi",
            "type":"Transportation"
        }
    ],
    "sg:phone":"+1 613 725 7316",
    "sg:postcode":"K0A 1T0",
    "sg:province":"ON",
    "sg:tags":[
        "taxicab"
    ],
    "wof:name":"West Carleton Taxi Inc",
    "wof:placetype":"venue"
},
  "geometry": {"coordinates":[-76.0557174683,45.4292297363],"type":"Point"}
}