{
  "type": "Feature",
  "properties": {
    "addr:full":"490 the Queensway S Keswick ON L4P 2E3",
    "addr:housenumber":"490",
    "addr:postcode":"l4p 2e3",
    "addr:street":"The Queensway S",
    "iso:country":"CA",
    "sg:address":"490 the Queensway S",
    "sg:city":"Keswick",
    "sg:classifiers":[
        {
            "category":"Retail",
            "subcategory":"Funeral Services",
            "type":"Services"
        }
    ],
    "sg:phone":"+1 905 476 7711",
    "sg:postcode":"L4P 2E3",
    "sg:province":"ON",
    "sg:tags":[
        "director"
    ],
    "wof:name":"M W Becker Funeral Home",
    "wof:placetype":"venue"
},
  "geometry": {"coordinates":[-79.4655456543,44.21118927],"type":"Point"}
}