{
  "type": "Feature",
  "properties": {
    "iso:country":"CA",
    "sg:address":"9704 54 Ave NW",
    "sg:city":"Edmonton",
    "sg:classifiers":[
        {
            "category":"Restaurant",
            "type":"Food & Drink"
        }
    ],
    "sg:phone":"+1 780 413 9558",
    "sg:postcode":"T6E 0A9",
    "sg:province":"AB",
    "wof:name":"Cafe on 54th",
    "wof:placetype":"venue"
},
  "geometry": {"coordinates":[-113.479874,53.489964],"type":"Point"}
}