{
  "type": "Feature",
  "properties": {
    "addr:full":"692 Rte 397 S Barraute QC J0Y 1A0",
    "addr:housenumber":"692",
    "addr:postcode":"j0y 1a0",
    "addr:street":"Rte 397 S",
    "iso:country":"CA",
    "sg:address":"692 Rte 397 S",
    "sg:city":"Barraute",
    "sg:classifiers":[
        {
            "category":"Manufacturing",
            "subcategory":"Lumber",
            "type":"Manufacturing & Wholesale Goods"
        }
    ],
    "sg:phone":"+1 819 734 6743",
    "sg:postcode":"J0Y 1A0",
    "sg:province":"QC",
    "sg:tags":[
        "sawmill"
    ],
    "wof:name":"Precibois Inc",
    "wof:placetype":"venue"
},
  "geometry": {"coordinates":[-77.637238,48.441151],"type":"Point"}
}