{
  "type": "Feature",
  "properties": {
    "addr:full":"Main St Port Blandford NL A0C 2G0",
    "addr:postcode":"a0c 2g0",
    "addr:street":"Main St",
    "iso:country":"CA",
    "sg:address":"Main St",
    "sg:city":"Port Blandford",
    "sg:classifiers":[
        {
            "category":"Building & Trades",
            "subcategory":"Equipment Rental",
            "type":"Services"
        }
    ],
    "sg:phone":"+1 709 543 2233",
    "sg:postcode":"A0C 2G0",
    "sg:province":"NL",
    "sg:tags":[
        "crane"
    ],
    "wof:name":"Hann Enterprises Ltd",
    "wof:placetype":"venue"
},
  "geometry": {"coordinates":[-54.171997,48.357121],"type":"Point"}
}