{
  "type": "Feature",
  "properties": {
    "addr:full":"167 Rue Saint-Pierre S Joliette QC J6E 5Y8",
    "addr:housenumber":"167",
    "addr:postcode":"j6e 5y8",
    "addr:street":"Rue Saint-Pierre S",
    "iso:country":"CA",
    "sg:address":"167 Rue Saint-Pierre S",
    "sg:city":"Joliette",
    "sg:classifiers":[
        {
            "category":"Food & Beverages",
            "subcategory":"Groceries & Convenience Stores",
            "type":"Retail Goods"
        }
    ],
    "sg:phone":"+1 450 753 5252",
    "sg:postcode":"J6E 5Y8",
    "sg:province":"QC",
    "wof:name":"Depanneur Nico Enr",
    "wof:placetype":"venue"
},
  "geometry": {"coordinates":[-73.4450912476,46.0183143616],"type":"Point"}
}