{
  "type": "Feature",
  "properties": {
    "iso:country":"CA",
    "sg:address":"1022 Hubrey Rd",
    "sg:city":"London",
    "sg:phone":"+1 519 681 0161",
    "sg:postcode":"N6N 1B5",
    "sg:province":"ON",
    "sg:tags":[
        "equipment",
        "station"
    ],
    "wof:name":"Middlesex Supply & Maintenance",
    "wof:placetype":"venue"
},
  "geometry": {"coordinates":[-81.1838760376,42.931854248],"type":"Point"}
}