{
  "type": "Feature",
  "properties": {
    "addr:full":"1024 103 Ave Dawson Creek BC V1G 2G5",
    "addr:housenumber":"1024",
    "addr:postcode":"v1g 2g5",
    "addr:street":"103 Ave",
    "iso:country":"CA",
    "sg:address":"1024 103 Ave",
    "sg:city":"Dawson Creek",
    "sg:classifiers":[
        {
            "category":"Health Services",
            "subcategory":"Doctor",
            "type":"Services"
        }
    ],
    "sg:phone":"+1 250 782 4440",
    "sg:postcode":"V1G 2G5",
    "sg:province":"BC",
    "sg:tags":[
        "dentist"
    ],
    "wof:name":"Mark Sevier Inc",
    "wof:placetype":"venue"
},
  "geometry": {"coordinates":[-120.22998,55.757912],"type":"Point"}
}