{
  "type": "Feature",
  "properties": {
    "addr:full":"402 7th Ave E Wilkie SK S0K 4W0",
    "addr:housenumber":"402",
    "addr:postcode":"s0k 4w0",
    "addr:street":"7Th Ave E Wilkie",
    "iso:country":"CA",
    "sg:address":"402 7th Ave E",
    "sg:city":"Wilkie",
    "sg:classifiers":[
        {
            "category":"Health Services",
            "subcategory":"Clinic",
            "type":"Services"
        }
    ],
    "sg:phone":"+1 306 843 2234",
    "sg:postcode":"S0K 4W0",
    "sg:province":"SK",
    "sg:tags":[
        "home"
    ],
    "wof:name":"Bethany Enhanced Living",
    "wof:placetype":"venue"
},
  "geometry": {"coordinates":[-108.711029053,52.405708313],"type":"Point"}
}