{
  "type": "Feature",
  "properties": {
    "addr:full":"2565 St. Peter Ave Bathurst NB E2A 7K3",
    "addr:housenumber":"2565",
    "addr:postcode":"e2a 7k3",
    "addr:street":"St. Peter Ave",
    "iso:country":"CA",
    "sg:address":"2565 St. Peter Ave",
    "sg:city":"Bathurst",
    "sg:classifiers":[
        {
            "category":"Retail",
            "subcategory":"Auto Repair",
            "type":"Services"
        }
    ],
    "sg:phone":"+1 506 546 3454",
    "sg:postcode":"E2A 7K3",
    "sg:province":"NB",
    "sg:tags":[
        "repairing",
        "automobile",
        "radiator"
    ],
    "wof:name":"Bathurst Radiator & Spring Ltd",
    "wof:placetype":"venue"
},
  "geometry": {"coordinates":[-65.683571,47.662186],"type":"Point"}
}