{
  "type": "Feature",
  "properties": {
    "addr:full":"1163 Kingston Rd Pickering ON L1V 1B5",
    "addr:housenumber":"1163",
    "addr:postcode":"l1v 1b5",
    "addr:street":"Kingston Rd",
    "iso:country":"CA",
    "sg:address":"1163 Kingston Rd",
    "sg:city":"Pickering",
    "sg:classifiers":[
        {
            "category":"Restaurant",
            "type":"Food & Drink"
        }
    ],
    "sg:phone":"+1 905 837 1011",
    "sg:postcode":"L1V 1B5",
    "sg:province":"ON",
    "sg:tags":[
        "pizza"
    ],
    "wof:name":"Panzerotto Pizza",
    "wof:placetype":"venue"
},
  "geometry": {"coordinates":[-79.096565,43.830761],"type":"Point"}
}