{
  "type": "Feature",
  "properties": {
    "iso:country":"CA",
    "sg:city":"Winnipeg",
    "sg:classifiers":[
        {
            "category":"Manufacturing",
            "subcategory":"Printing",
            "type":"Manufacturing & Wholesale Goods"
        }
    ],
    "sg:phone":"+1 204 985 9780",
    "sg:postcode":"R3J 0K4",
    "sg:province":"MB",
    "sg:tags":[
        "publisher"
    ],
    "wof:name":"Craig Kelman & Assoc Ltd",
    "wof:placetype":"venue"
},
  "geometry": {"coordinates":[-97.22955322270001,49.8774414062],"type":"Point"}
}