{
  "type": "Feature",
  "properties": {
    "addr:full":"RR 1 Collingwood Corner NS B0M 1E0",
    "addr:postcode":"b0m 1e0",
    "addr:street":"Rr 1",
    "iso:country":"CA",
    "sg:address":"RR 1",
    "sg:city":"Collingwood Corner",
    "sg:classifiers":[
        {
            "category":"Manufacturing",
            "subcategory":"Food",
            "type":"Manufacturing & Wholesale Goods"
        }
    ],
    "sg:phone":"+1 902 686 3117",
    "sg:postcode":"B0M 1E0",
    "sg:province":"NS",
    "sg:tags":[
        "winery"
    ],
    "wof:name":"Williamsdale Winery",
    "wof:placetype":"venue"
},
  "geometry": {"coordinates":[-63.937004,45.608299],"type":"Point"}
}