{
  "type": "Feature",
  "properties": {
    "iso:country":"CA",
    "sg:address":"105 Av Du Parc",
    "sg:city":"Chibougamau",
    "sg:classifiers":[
        {
            "category":"Health Services",
            "subcategory":"Hospital",
            "type":"Services"
        }
    ],
    "sg:phone":"+1 418 748 2225",
    "sg:postcode":"G8P 3A5",
    "sg:province":"QC",
    "sg:tags":[
        "mental"
    ],
    "wof:name":"Corp Le Zephir Inc",
    "wof:placetype":"venue"
},
  "geometry": {"coordinates":[-74.37004852290001,49.9157371521],"type":"Point"}
}