{
  "type": "Feature",
  "properties": {
    "addr:full":"501 Brink St Ashcroft BC V0K 1A0",
    "addr:housenumber":"501",
    "addr:postcode":"v0k 1a0",
    "addr:street":"Brink St",
    "iso:country":"CA",
    "sg:address":"501 Brink St",
    "sg:city":"Ashcroft",
    "sg:classifiers":[
        {
            "category":"Organizations",
            "subcategory":"Religious Organization",
            "type":"Services"
        }
    ],
    "sg:phone":"+1 250 453 9909",
    "sg:postcode":"V0K 1A0",
    "sg:province":"BC",
    "sg:tags":[
        "church"
    ],
    "wof:name":"St Alban's Anglican Church",
    "wof:placetype":"venue"
},
  "geometry": {"coordinates":[-121.281936645,50.7206382751],"type":"Point"}
}