{
  "type": "Feature",
  "properties": {
    "addr:full":"107 Boardwalk Dr Toronto ON M4L 3X9",
    "addr:housenumber":"107",
    "addr:postcode":"m4l 3x9",
    "addr:street":"Boardwalk Dr",
    "iso:country":"CA",
    "sg:address":"107 Boardwalk Dr",
    "sg:city":"Toronto",
    "sg:classifiers":[
        {
            "category":"Education",
            "subcategory":"Special Training",
            "type":"Public Place"
        }
    ],
    "sg:phone":"+1 416 699 6107",
    "sg:postcode":"M4L 3X9",
    "sg:province":"ON",
    "sg:tags":[
        "management"
    ],
    "wof:name":"Experience It Inc",
    "wof:placetype":"venue"
},
  "geometry": {"coordinates":[-79.30574799999999,43.666145],"type":"Point"}
}