{
  "type": "Feature",
  "properties": {
    "iso:country":"CA",
    "sg:address":"4844 Joyce Ave",
    "sg:city":"Powell River",
    "sg:classifiers":[
        {
            "category":"Professional",
            "subcategory":"Computer Services",
            "type":"Services"
        }
    ],
    "sg:phone":"+1 604 485 5793",
    "sg:postcode":"V8A 3B8",
    "sg:province":"BC",
    "sg:tags":[
        "repair",
        "television",
        "radio"
    ],
    "wof:name":"Diamond Tv & Radio",
    "wof:placetype":"venue"
},
  "geometry": {"coordinates":[-124.521034241,49.8468093872],"type":"Point"}
}