{
  "type": "Feature",
  "properties": {
    "addr:full":"9738 Rue LA Martiniere Montreal QC H1C 1Z2",
    "addr:housenumber":"9738",
    "addr:postcode":"h1c 1z2",
    "addr:street":"Rue La Martiniere",
    "iso:country":"CA",
    "sg:address":"9738 Rue LA Martiniere",
    "sg:city":"Montreal",
    "sg:classifiers":[
        {
            "category":"Building & Trades",
            "subcategory":"Landscaping Services",
            "type":"Services"
        }
    ],
    "sg:phone":"+1 514 648 3847",
    "sg:postcode":"H1C 1Z2",
    "sg:province":"QC",
    "sg:tags":[
        "excavating",
        "contractor",
        "lawn",
        "maintenance",
        "grounds"
    ],
    "wof:name":"Excavation Castonguay Inc",
    "wof:placetype":"venue"
},
  "geometry": {"coordinates":[-73.556129,45.645611],"type":"Point"}
}