{
  "type": "Feature",
  "properties": {
    "iso:country":"CA",
    "sg:address":"1281 Rue Des Champs-Elysees",
    "sg:city":"Chicoutimi",
    "sg:classifiers":[
        {
            "category":"Retail",
            "subcategory":"Laundry & Dry Cleaning",
            "type":"Services"
        }
    ],
    "sg:phone":"+1 418 696 1226",
    "sg:postcode":"G7H 5Y4",
    "sg:province":"QC",
    "sg:tags":[
        "cleaners"
    ],
    "wof:name":"Nettoyeur Michel Forget",
    "wof:placetype":"venue"
},
  "geometry": {"coordinates":[-71.052063,48.406612],"type":"Point"}
}