{
  "type": "Feature",
  "properties": {
    "addr:full":"761 O'Shea Rd Gibsons BC V0N 1V9",
    "addr:housenumber":"761",
    "addr:postcode":"v0n 1v9",
    "addr:street":"O'Shea Rd",
    "iso:country":"CA",
    "sg:address":"761 O'Shea Rd",
    "sg:city":"Gibsons",
    "sg:classifiers":[
        {
            "category":"Taxi",
            "type":"Transportation"
        }
    ],
    "sg:phone":"+1 604 885 3666",
    "sg:postcode":"V0N 1V9",
    "sg:province":"BC",
    "sg:tags":[
        "delivery",
        "taxicab"
    ],
    "wof:name":"Sunshine Coast Taxi Ltd",
    "wof:placetype":"venue"
},
  "geometry": {"coordinates":[-123.503433227,49.4034500122],"type":"Point"}
}