{
  "type": "Feature",
  "properties": {
    "addr:full":"Port Coquitlam BC V3C 1S5",
    "addr:postcode":"v3c 1s5",
    "iso:country":"CA",
    "sg:city":"Port Coquitlam",
    "sg:classifiers":[
        {
            "category":"Manufacturing",
            "subcategory":"Glass & Minerals",
            "type":"Manufacturing & Wholesale Goods"
        }
    ],
    "sg:phone":"+1 604 942 6719",
    "sg:postcode":"V3C 1S5",
    "sg:province":"BC",
    "sg:tags":[
        "fabricator",
        "fiber"
    ],
    "wof:name":"Brownlow's Performance Fabr",
    "wof:placetype":"venue"
},
  "geometry": {"coordinates":[-122.77302551299999,49.2571411133],"type":"Point"}
}