{
  "type": "Feature",
  "properties": {
    "addr:full":"965 Cottonwood Rd Winnipeg MB R2J 1G3",
    "addr:housenumber":"965",
    "addr:postcode":"r2j 1g3",
    "addr:street":"Cottonwood Rd",
    "iso:country":"CA",
    "sg:address":"965 Cottonwood Rd",
    "sg:city":"Winnipeg",
    "sg:classifiers":[
        {
            "category":"Autos & Motor Vehicles",
            "subcategory":"Auto Supplies",
            "type":"Retail Goods"
        }
    ],
    "sg:phone":"+1 204 254 8769",
    "sg:postcode":"R2J 1G3",
    "sg:province":"MB",
    "sg:tags":[
        "tire"
    ],
    "wof:name":"Tirecraft",
    "wof:placetype":"venue"
},
  "geometry": {"coordinates":[-97.0760650635,49.8612556458],"type":"Point"}
}