{
  "type": "Feature",
  "properties": {
    "addr:full":"4314 Boul Industriel Sherbrooke QC J1L 2S8",
    "addr:housenumber":"4314",
    "addr:postcode":"j1l 2s8",
    "addr:street":"Boul Industriel",
    "iso:country":"CA",
    "sg:address":"4314 Boul Industriel",
    "sg:city":"Sherbrooke",
    "sg:classifiers":[
        {
            "category":"Manufacturing",
            "subcategory":"Motor Vehicles & Parts",
            "type":"Manufacturing & Wholesale Goods"
        }
    ],
    "sg:phone":"+1 819 563 2222",
    "sg:postcode":"J1L 2S8",
    "sg:province":"QC",
    "sg:tags":[
        "equipment",
        "truck"
    ],
    "wof:name":"Palmar Inc",
    "wof:placetype":"venue"
},
  "geometry": {"coordinates":[-71.97068,45.395611],"type":"Point"}
}