{
  "type": "Feature",
  "properties": {
    "iso:country":"CA",
    "sg:address":"1959 Boul Saint-Joseph O",
    "sg:city":"Saint-Majorique",
    "sg:classifiers":[
        {
            "category":"Food & Beverages",
            "subcategory":"Groceries & Convenience Stores",
            "type":"Retail Goods"
        }
    ],
    "sg:phone":"+1 819 475 0010",
    "sg:postcode":"J2B 8A8",
    "sg:province":"QC",
    "sg:tags":[
        "grocer"
    ],
    "wof:name":"Depanneur Bm Rodier",
    "wof:placetype":"venue"
},
  "geometry": {"coordinates":[-72.5808792114,45.9308242798],"type":"Point"}
}