{
  "type": "Feature",
  "properties": {
    "iso:country":"CA",
    "sg:address":"139 Pearl St",
    "sg:city":"Brantford",
    "sg:classifiers":[
        {
            "category":"Restaurant",
            "type":"Food & Drink"
        }
    ],
    "sg:phone":"+1 519 752 7703",
    "sg:postcode":"N3T 3P3",
    "sg:province":"ON",
    "sg:tags":[
        "delicatessen"
    ],
    "wof:name":"Huzul's Meat & Deli",
    "wof:placetype":"venue"
},
  "geometry": {"coordinates":[-80.27243804930001,43.1475372314],"type":"Point"}
}