{
  "type": "Feature",
  "properties": {
    "addr:full":"5081 Gore Rd Dorchester ON N0L 1G4",
    "addr:housenumber":"5081",
    "addr:postcode":"n0l 1g4",
    "addr:street":"Gore Rd",
    "iso:country":"CA",
    "sg:address":"5081 Gore Rd",
    "sg:city":"Dorchester",
    "sg:classifiers":[
        {
            "category":"Travel",
            "subcategory":"Campground",
            "type":"Entertainment"
        }
    ],
    "sg:phone":"+1 519 268 1928",
    "sg:postcode":"N0L 1G4",
    "sg:province":"ON",
    "sg:tags":[
        "camp",
        "establishment"
    ],
    "wof:name":"Stevenson Childrens Camp Fndtn",
    "wof:placetype":"venue"
},
  "geometry": {"coordinates":[-81.068054,43.009331],"type":"Point"}
}