{
  "type": "Feature",
  "properties": {
    "addr:full":"4 Beaufort Ave Stellarton NS B0K 1S0",
    "addr:housenumber":"4",
    "addr:postcode":"b0k 1s0",
    "addr:street":"Beaufort Ave",
    "iso:country":"CA",
    "sg:address":"4 Beaufort Ave",
    "sg:city":"Stellarton",
    "sg:classifiers":[
        {
            "category":"Organizations",
            "subcategory":"Labor Organization",
            "type":"Services"
        }
    ],
    "sg:phone":"+1 902 752 3176",
    "sg:postcode":"B0K 1S0",
    "sg:province":"NS",
    "wof:name":"N S & Pei Regional Council",
    "wof:placetype":"venue"
},
  "geometry": {"coordinates":[-62.685703,45.556206],"type":"Point"}
}