{
  "type": "Feature",
  "properties": {
    "iso:country":"CA",
    "sg:address":"244 Rue Labbe",
    "sg:city":"Thetford Mines",
    "sg:classifiers":[
        {
            "category":"Organizations",
            "subcategory":"Professional Association",
            "type":"Services"
        }
    ],
    "sg:phone":"+1 418 335 9855",
    "sg:postcode":"G6G 1Z1",
    "sg:province":"QC",
    "wof:name":"Club DE L'Age D'Or Notre-Dame",
    "wof:placetype":"venue"
},
  "geometry": {"coordinates":[-71.29964447019999,46.0973815918],"type":"Point"}
}