{
  "type": "Feature",
  "properties": {
    "addr:full":"6408 Bay St West Vancouver BC V7W 2H1",
    "addr:housenumber":"6408",
    "addr:postcode":"v7w 2h1",
    "addr:street":"Bay St",
    "iso:country":"CA",
    "sg:address":"6408 Bay St",
    "sg:city":"West Vancouver",
    "sg:classifiers":[
        {
            "category":"Restaurant",
            "type":"Food & Drink"
        }
    ],
    "sg:phone":"+1 604 921 7755",
    "sg:postcode":"V7W 2H1",
    "sg:province":"BC",
    "wof:name":"Troll's Restaurant",
    "wof:placetype":"venue"
},
  "geometry": {"coordinates":[-123.274666,49.374531],"type":"Point"}
}