{
  "type": "Feature",
  "properties": {
    "iso:country":"CA",
    "sg:address":"1154 Bank St",
    "sg:city":"Ottawa",
    "sg:classifiers":[
        {
            "category":"Home & Garden",
            "subcategory":"Garden Supply",
            "type":"Retail Goods"
        }
    ],
    "sg:phone":"+1 613 730 2691",
    "sg:postcode":"K1S 3X6",
    "sg:province":"ON",
    "sg:tags":[
        "seed",
        "center"
    ],
    "wof:name":"Hortus Urbanus",
    "wof:placetype":"venue"
},
  "geometry": {"coordinates":[-75.6826629639,45.3929901123],"type":"Point"}
}