{
  "type": "Feature",
  "properties": {
    "addr:full":"3535 Rue King O Sherbrooke QC J1L 1P8",
    "addr:housenumber":"3535",
    "addr:postcode":"j1l 1p8",
    "addr:street":"Rue King O",
    "iso:country":"CA",
    "sg:address":"3535 Rue King O",
    "sg:city":"Sherbrooke",
    "sg:classifiers":[
        {
            "category":"Travel",
            "subcategory":"Hotels & Motels",
            "type":"Entertainment"
        }
    ],
    "sg:phone":"+1 819 563 2941",
    "sg:postcode":"J1L 1P8",
    "sg:province":"QC",
    "wof:name":"Hotel Le President",
    "wof:placetype":"venue"
},
  "geometry": {"coordinates":[-71.95510101319999,45.3928794861],"type":"Point"}
}