{
  "type": "Feature",
  "properties": {
    "addr:full":"33 Cranfield Rd East York ON M4B 3H2",
    "addr:housenumber":"33",
    "addr:postcode":"m4b 3h2",
    "addr:street":"Cranfield Rd",
    "iso:country":"CA",
    "sg:address":"33 Cranfield Rd",
    "sg:city":"East York",
    "sg:classifiers":[
        {
            "category":"Manufacturing",
            "subcategory":"Tools & Machinery",
            "type":"Manufacturing & Wholesale Goods"
        }
    ],
    "sg:phone":"+1 416 755 1191",
    "sg:postcode":"M4B 3H2",
    "sg:province":"ON",
    "sg:tags":[
        "transformer"
    ],
    "wof:name":"Allanson International Inc",
    "wof:placetype":"venue"
},
  "geometry": {"coordinates":[-79.31164550779999,43.7122421265],"type":"Point"}
}