{
  "type": "Feature",
  "properties": {
    "iso:country":"CA",
    "sg:address":"1580 Merivale Rd # 201",
    "sg:city":"Nepean",
    "sg:classifiers":[
        {
            "category":"Professional",
            "type":"Services"
        }
    ],
    "sg:phone":"+1 613 238 1246",
    "sg:postcode":"K2G 4B5",
    "sg:province":"ON",
    "sg:tags":[
        "scientist"
    ],
    "wof:name":"Tradewind Scientific Ltd",
    "wof:placetype":"venue"
},
  "geometry": {"coordinates":[-75.73403167719999,45.35131073],"type":"Point"}
}