{
  "type": "Feature",
  "properties": {
    "iso:country":"CA",
    "sg:address":"816 101st Ave",
    "sg:city":"Tisdale",
    "sg:classifiers":[
        {
            "category":"Home & Garden",
            "subcategory":"Building Materials",
            "type":"Retail Goods"
        }
    ],
    "sg:phone":"+1 306 873 2628",
    "sg:postcode":"S0E 1T0",
    "sg:province":"SK",
    "sg:tags":[
        "lumber"
    ],
    "wof:name":"Beeland CO-OP Assoc Ltd",
    "wof:placetype":"venue"
},
  "geometry": {"coordinates":[-104.04914856000001,52.8490562439],"type":"Point"}
}