{
  "type": "Feature",
  "properties": {
    "addr:full":"372 Marlee Ave North York ON M6B 3H8",
    "addr:housenumber":"372",
    "addr:postcode":"m6b 3h8",
    "addr:street":"Marlee Ave",
    "iso:country":"CA",
    "sg:address":"372 Marlee Ave",
    "sg:city":"North York",
    "sg:classifiers":[
        {
            "category":"Food & Beverages",
            "subcategory":"Bakery",
            "type":"Retail Goods"
        }
    ],
    "sg:phone":"+1 416 787 4249",
    "sg:postcode":"M6B 3H8",
    "sg:province":"ON",
    "sg:tags":[
        "baker"
    ],
    "wof:name":"Odessa Deli",
    "wof:placetype":"venue"
},
  "geometry": {"coordinates":[-79.443138,43.706867],"type":"Point"}
}