{
  "type": "Feature",
  "properties": {
    "addr:full":"Surrey BC V3W 1A4",
    "addr:postcode":"v3w 1a4",
    "iso:country":"CA",
    "sg:city":"Surrey",
    "sg:classifiers":[
        {
            "category":"Professional",
            "subcategory":"Accounting & Tax Preparation",
            "type":"Services"
        }
    ],
    "sg:phone":"+1 604 572 4586",
    "sg:postcode":"V3W 1A4",
    "sg:province":"BC",
    "sg:tags":[
        "accountant"
    ],
    "wof:name":"Dale Matheson Carr-Hilton",
    "wof:placetype":"venue"
},
  "geometry": {"coordinates":[-122.842949,49.136292],"type":"Point"}
}