{
  "type": "Feature",
  "properties": {
    "addr:full":"3126 Ch DE Chambly Longueuil QC J4L 1N5",
    "addr:postcode":"3126;j4l 1n5",
    "addr:street":"Ch De Chambly",
    "iso:country":"CA",
    "sg:address":"3126 Ch DE Chambly",
    "sg:city":"Longueuil",
    "sg:classifiers":[
        {
            "category":"Bars & Pubs",
            "type":"Food & Drink"
        }
    ],
    "sg:phone":"+1 450 679 7628",
    "sg:postcode":"J4L 1N5",
    "sg:province":"QC",
    "sg:tags":[
        "lounge",
        "cocktail"
    ],
    "wof:name":"Cactus Bar",
    "wof:placetype":"venue"
},
  "geometry": {"coordinates":[-73.45347595210001,45.5173683167],"type":"Point"}
}