{
  "type": "Feature",
  "properties": {
    "addr:full":"753 Mcnabb St Sault Ste Marie ON P6A 6W3",
    "addr:housenumber":"753",
    "addr:postcode":"p6a 6w3",
    "addr:street":"Mcnabb St",
    "iso:country":"CA",
    "sg:address":"753 Mcnabb St",
    "sg:city":"Sault Ste Marie",
    "sg:classifiers":[
        {
            "category":"Organizations",
            "subcategory":"Religious Organization",
            "type":"Services"
        }
    ],
    "sg:phone":"+1 705 949 6134",
    "sg:postcode":"P6A 6W3",
    "sg:province":"ON",
    "sg:tags":[
        "church"
    ],
    "wof:name":"Free Methodist Church",
    "wof:placetype":"venue"
},
  "geometry": {"coordinates":[-84.2892379761,46.5218009949],"type":"Point"}
}