{
  "type": "Feature",
  "properties": {
    "addr:full":"Saint-Laurent QC H4T 1Z6",
    "addr:postcode":"h4t 1z6",
    "iso:country":"CA",
    "sg:city":"Saint-Laurent",
    "sg:classifiers":[
        {
            "category":"Professional",
            "subcategory":"Employment Agencies",
            "type":"Services"
        }
    ],
    "sg:phone":"+1 514 744 2121",
    "sg:postcode":"H4T 1Z6",
    "sg:province":"QC",
    "sg:tags":[
        "opportunity"
    ],
    "wof:name":"Can Tech Svc",
    "wof:placetype":"venue"
},
  "geometry": {"coordinates":[-73.6791610718,45.4955101013],"type":"Point"}
}