{
  "type": "Feature",
  "properties": {
    "addr:full":"Dewberry AB T0B 1G0",
    "addr:postcode":"t0b 1g0",
    "iso:country":"CA",
    "sg:city":"Dewberry",
    "sg:classifiers":[
        {
            "category":"Professional",
            "subcategory":"Accounting & Tax Preparation",
            "type":"Services"
        }
    ],
    "sg:phone":"+1 780 847 4166",
    "sg:postcode":"T0B 1G0",
    "sg:province":"AB",
    "sg:tags":[
        "bookkeeping",
        "general"
    ],
    "wof:name":"Dewberry Data Svc",
    "wof:placetype":"venue"
},
  "geometry": {"coordinates":[-110.522057,53.585194],"type":"Point"}
}