{
  "type": "Feature",
  "properties": {
    "addr:full":"333 Wyecroft Rd # 3 Oakville ON L6K 2H2",
    "addr:housenumber":"333",
    "addr:postcode":"l6k 2h2",
    "addr:street":"Wyecroft Rd # 3",
    "iso:country":"CA",
    "sg:address":"333 Wyecroft Rd # 3",
    "sg:city":"Oakville",
    "sg:classifiers":[
        {
            "category":"Professional",
            "subcategory":"Accounting & Tax Preparation",
            "type":"Services"
        }
    ],
    "sg:phone":"+1 905 338 2900",
    "sg:postcode":"L6K 2H2",
    "sg:province":"ON",
    "sg:tags":[
        "accountant"
    ],
    "wof:name":"Phelan & Stodulski",
    "wof:placetype":"venue"
},
  "geometry": {"coordinates":[-79.701553,43.4417],"type":"Point"}
}