{
  "type": "Feature",
  "properties": {
    "addr:full":"410 22nd St E #1400 Saskatoon SK S7K 5T6",
    "addr:housenumber":"410",
    "addr:postcode":"s7k 5t6",
    "addr:street":"22Nd St E # 1400",
    "iso:country":"CA",
    "sg:address":"410 22nd St E #1400",
    "sg:city":"Saskatoon",
    "sg:classifiers":[
        {
            "category":"Banks & Credit Unions",
            "subcategory":"Financial Services",
            "type":"Services"
        }
    ],
    "sg:phone":"+1 306 668 5599",
    "sg:postcode":"S7K 5T6",
    "sg:province":"SK",
    "sg:tags":[
        "bankruptcy",
        "trustee"
    ],
    "wof:name":"Burlingham Associates",
    "wof:placetype":"venue"
},
  "geometry": {"coordinates":[-106.660042,52.128242],"type":"Point"}
}