{
  "type": "Feature",
  "properties": {
    "addr:full":"411 11 St S Lethbridge AB T1J 2N9",
    "addr:housenumber":"411 11",
    "addr:postcode":"t1j 2n9",
    "addr:street":"St S",
    "iso:country":"CA",
    "sg:address":"411 11 St S",
    "sg:city":"Lethbridge",
    "sg:classifiers":[
        {
            "category":"Organizations",
            "subcategory":"Religious Organization",
            "type":"Services"
        }
    ],
    "sg:phone":"+1 403 327 3970",
    "sg:postcode":"T1J 2N9",
    "sg:province":"AB",
    "sg:tags":[
        "church"
    ],
    "wof:name":"Saint Augustine's Anglican Chr",
    "wof:placetype":"venue"
},
  "geometry": {"coordinates":[-112.830421,49.694435],"type":"Point"}
}