{
  "type": "Feature",
  "properties": {
    "addr:full":"NE 9 39 24W Birch River MB R0L 0E0",
    "addr:housenumber":"39 24w birch",
    "addr:postcode":"r0l 0e0",
    "addr:street":"Ne 9",
    "iso:country":"CA",
    "sg:address":"NE 9 39 24W",
    "sg:city":"Birch River",
    "sg:classifiers":[
        {
            "category":"Government",
            "subcategory":"Office",
            "type":"Public Place"
        }
    ],
    "sg:phone":"+1 204 236 4380",
    "sg:postcode":"R0L 0E0",
    "sg:province":"MB",
    "wof:name":"Canada Lenswood & Birch River",
    "wof:placetype":"venue"
},
  "geometry": {"coordinates":[-101.103363,52.391064],"type":"Point"}
}