{
  "type": "Feature",
  "properties": {
    "addr:full":"Winnipeg MB R2M 2Y1",
    "addr:postcode":"r2m 2y1",
    "iso:country":"CA",
    "sg:city":"Winnipeg",
    "sg:classifiers":[
        {
            "category":"Recreation",
            "subcategory":"Arcade",
            "type":"Entertainment"
        }
    ],
    "sg:phone":"+1 204 231 2696",
    "sg:postcode":"R2M 2Y1",
    "sg:province":"MB",
    "sg:tags":[
        "amusement",
        "devices"
    ],
    "wof:name":"Premier Amusement Inc",
    "wof:placetype":"venue"
},
  "geometry": {"coordinates":[-97.14073944090001,49.8994216919],"type":"Point"}
}