{
  "type": "Feature",
  "properties": {
    "addr:full":"Farm Turtleford SK S0M 2Y0",
    "addr:postcode":"s0m 2y0",
    "iso:country":"CA",
    "sg:address":"Farm",
    "sg:city":"Turtleford",
    "sg:classifiers":[
        {
            "category":"Freight",
            "type":"Transportation"
        }
    ],
    "sg:phone":"+1 306 845 3740",
    "sg:postcode":"S0M 2Y0",
    "sg:province":"SK",
    "sg:tags":[
        "commercial",
        "storage"
    ],
    "wof:name":"Turtle Lake Storage",
    "wof:placetype":"venue"
},
  "geometry": {"coordinates":[-108.959076,53.38847],"type":"Point"}
}