{
  "type": "Feature",
  "properties": {
    "addr:full":"346 Arvin Ave Stoney Creek ON L8E 2M4",
    "addr:housenumber":"346",
    "addr:postcode":"l8e 2m4",
    "addr:street":"Arvin Ave",
    "iso:country":"CA",
    "sg:address":"346 Arvin Ave",
    "sg:city":"Stoney Creek",
    "sg:classifiers":[
        {
            "category":"Manufacturing",
            "subcategory":"Leather Goods",
            "type":"Manufacturing & Wholesale Goods"
        }
    ],
    "sg:phone":"+1 905 664 3930",
    "sg:postcode":"L8E 2M4",
    "sg:province":"ON",
    "sg:tags":[
        "shoes"
    ],
    "wof:name":"Baffin Inc",
    "wof:placetype":"venue"
},
  "geometry": {"coordinates":[-79.72156524659999,43.2303733826],"type":"Point"}
}