{
  "type": "Feature",
  "properties": {
    "addr:full":"107 Henry St St Catharines ON L2R 5V6",
    "addr:housenumber":"107",
    "addr:postcode":"l2r 5v6",
    "addr:street":"Henry St",
    "iso:country":"CA",
    "sg:address":"107 Henry St",
    "sg:city":"St Catharines",
    "sg:classifiers":[
        {
            "category":"Health Services",
            "subcategory":"Chiropractor",
            "type":"Services"
        }
    ],
    "sg:phone":"+1 905 685 7422",
    "sg:postcode":"L2R 5V6",
    "sg:province":"ON",
    "wof:name":"Bartelings, Derick C DC",
    "wof:placetype":"venue"
},
  "geometry": {"coordinates":[-79.249527,43.169331],"type":"Point"}
}