{
  "type": "Feature",
  "properties": {
    "addr:full":"139 Daniel St N Arnprior ON K7S 2L2",
    "addr:housenumber":"139",
    "addr:postcode":"k7s 2l2",
    "addr:street":"Daniel St N",
    "iso:country":"CA",
    "sg:address":"139 Daniel St N",
    "sg:city":"Arnprior",
    "sg:classifiers":[
        {
            "category":"Manufacturing",
            "subcategory":"Printing",
            "type":"Manufacturing & Wholesale Goods"
        }
    ],
    "sg:phone":"+1 613 623 4359",
    "sg:postcode":"K7S 2L2",
    "sg:province":"ON",
    "sg:tags":[
        "printer"
    ],
    "wof:name":"H Brittle Printing Ltd",
    "wof:placetype":"venue"
},
  "geometry": {"coordinates":[-76.3520889282,45.4338111877],"type":"Point"}
}