{
  "type": "Feature",
  "properties": {
    "addr:full":"975 Rue Du Centre-Sportif Normandin QC G8M 4L7",
    "addr:housenumber":"975",
    "addr:postcode":"g8m 4l7",
    "addr:street":"Rue Du Centre-Sportif",
    "iso:country":"CA",
    "sg:address":"975 Rue Du Centre-Sportif",
    "sg:city":"Normandin",
    "sg:classifiers":[
        {
            "category":"Social Services",
            "type":"Services"
        }
    ],
    "sg:phone":"+1 418 274 7163",
    "sg:postcode":"G8M 4L7",
    "sg:province":"QC",
    "sg:tags":[
        "youth",
        "organization",
        "center"
    ],
    "wof:name":"Maison Des Jeunes Le Pentagone",
    "wof:placetype":"venue"
},
  "geometry": {"coordinates":[-72.5249404907,48.835647583],"type":"Point"}
}