{
  "type": "Feature",
  "properties": {
    "addr:full":"2905 Rue DE Miniac Saint-Laurent QC H4S 1L8",
    "addr:housenumber":"2905",
    "addr:postcode":"h4s 1l8",
    "addr:street":"Rue De Miniac",
    "iso:country":"CA",
    "sg:address":"2905 Rue DE Miniac",
    "sg:city":"Saint-Laurent",
    "sg:classifiers":[
        {
            "category":"Manufacturing",
            "subcategory":"Tools & Machinery",
            "type":"Manufacturing & Wholesale Goods"
        }
    ],
    "sg:phone":"+1 514 335 7571",
    "sg:postcode":"H4S 1L8",
    "sg:province":"QC",
    "sg:tags":[
        "equipment",
        "conveyor",
        "conveying"
    ],
    "wof:name":"Danox Inc",
    "wof:placetype":"venue"
},
  "geometry": {"coordinates":[-73.75065600000001,45.495358],"type":"Point"}
}