{
  "type": "Feature",
  "properties": {
    "iso:country":"CA",
    "sg:address":"303 St Patrick St",
    "sg:city":"Ottawa",
    "sg:classifiers":[
        {
            "category":"Restaurant",
            "type":"Food & Drink"
        }
    ],
    "sg:phone":"+1 613 562 0848",
    "sg:postcode":"K1N 5K4",
    "sg:province":"ON",
    "wof:name":"Lorenzo's Pizzeria",
    "wof:placetype":"venue"
},
  "geometry": {"coordinates":[-75.69140625,45.431640625],"type":"Point"}
}