{
  "type": "Feature",
  "properties": {
    "addr:full":"889 Rue Champlain Magog QC J1X 2N1",
    "addr:housenumber":"889",
    "addr:postcode":"j1x 2n1",
    "addr:street":"Rue Champlain",
    "iso:country":"CA",
    "sg:address":"889 Rue Champlain",
    "sg:city":"Magog",
    "sg:classifiers":[
        {
            "category":"Home & Garden",
            "subcategory":"Home Furnishings",
            "type":"Retail Goods"
        }
    ],
    "sg:phone":"+1 819 843 6066",
    "sg:postcode":"J1X 2N1",
    "sg:province":"QC",
    "sg:tags":[
        "shop",
        "made",
        "fabric",
        "drapery"
    ],
    "wof:name":"Bagatelle",
    "wof:placetype":"venue"
},
  "geometry": {"coordinates":[-72.1419677734,45.2730331421],"type":"Point"}
}