{
  "type": "Feature",
  "properties": {
    "addr:full":"Dartmouth NS B3B 1L5",
    "addr:postcode":"b3b 1l5",
    "iso:country":"CA",
    "sg:city":"Dartmouth",
    "sg:classifiers":[
        {
            "category":"Home & Garden",
            "subcategory":"Building Materials",
            "type":"Retail Goods"
        }
    ],
    "sg:phone":"+1 902 468 8201",
    "sg:postcode":"B3B 1L5",
    "sg:province":"NS",
    "sg:tags":[
        "glass",
        "window",
        "plate"
    ],
    "wof:name":"Apple Auto Glass",
    "wof:placetype":"venue"
},
  "geometry": {"coordinates":[-63.5923957825,44.7032432556],"type":"Point"}
}