{
  "type": "Feature",
  "properties": {
    "addr:full":"Claresholm AB T0L 0T0",
    "addr:postcode":"t0l 0t0",
    "iso:country":"CA",
    "sg:city":"Claresholm",
    "sg:classifiers":[
        {
            "category":"Insurance",
            "subcategory":"Insurance Agent",
            "type":"Services"
        }
    ],
    "sg:phone":"+1 403 625 4066",
    "sg:postcode":"T0L 0T0",
    "sg:province":"AB",
    "wof:name":"Willow Creek Insurance Ltd",
    "wof:placetype":"venue"
},
  "geometry": {"coordinates":[-113.583611,50.024372],"type":"Point"}
}