{
  "type": "Feature",
  "properties": {
    "addr:full":"3880 Ch Salaberry Carignan QC J3L 3P9",
    "addr:postcode":"3880;j3l 3p9",
    "addr:street":"Ch Salaberry",
    "iso:country":"CA",
    "sg:address":"3880 Ch Salaberry",
    "sg:city":"Carignan",
    "sg:classifiers":[
        {
            "category":"Building & Trades",
            "subcategory":"Electrical",
            "type":"Services"
        }
    ],
    "sg:phone":"+1 450 658 5376",
    "sg:postcode":"J3L 3P9",
    "sg:province":"QC",
    "sg:tags":[
        "electric",
        "contractor"
    ],
    "wof:name":"Chambly Electrique Inc",
    "wof:placetype":"venue"
},
  "geometry": {"coordinates":[-73.336975,45.434139],"type":"Point"}
}