{
  "type": "Feature",
  "properties": {
    "addr:full":"Saint-Laurent QC H4R 2M6",
    "addr:postcode":"h4r 2m6",
    "iso:country":"CA",
    "sg:city":"Saint-Laurent",
    "sg:classifiers":[
        {
            "category":"Professional",
            "subcategory":"Accounting & Tax Preparation",
            "type":"Services"
        }
    ],
    "sg:phone":"+1 514 337 8100",
    "sg:postcode":"H4R 2M6",
    "sg:province":"QC",
    "sg:tags":[
        "accountant"
    ],
    "wof:name":"Biancardi, R CA",
    "wof:placetype":"venue"
},
  "geometry": {"coordinates":[-73.710922,45.520515],"type":"Point"}
}