{
  "type": "Feature",
  "properties": {
    "iso:country":"CA",
    "sg:city":"Saskatoon",
    "sg:classifiers":[
        {
            "category":"Government",
            "subcategory":"Office",
            "type":"Public Place"
        }
    ],
    "sg:phone":"+1 306 975 4298",
    "sg:postcode":"S7K 6G7",
    "sg:province":"SK",
    "wof:name":"Canada Office-Superintendent",
    "wof:placetype":"venue"
},
  "geometry": {"coordinates":[-106.660011,52.132362],"type":"Point"}
}