{
  "type": "Feature",
  "properties": {
    "iso:country":"CA",
    "sg:city":"Drayton Valley",
    "sg:classifiers":[
        {
            "category":"Freight",
            "type":"Transportation"
        }
    ],
    "sg:phone":"+1 780 542 3333",
    "sg:postcode":"T7A 1S6",
    "sg:province":"AB",
    "sg:tags":[
        "trucking"
    ],
    "wof:name":"R Floden Svc Ltd",
    "wof:placetype":"venue"
},
  "geometry": {"coordinates":[-114.9868927,53.2279968262],"type":"Point"}
}