{
  "type": "Feature",
  "properties": {
    "addr:full":"204 1st Ave W Three Hills AB T0M 2A0",
    "addr:housenumber":"204",
    "addr:postcode":"t0m 2a0",
    "addr:street":"1St Ave W Three",
    "iso:country":"CA",
    "sg:address":"204 1st Ave W",
    "sg:city":"Three Hills",
    "sg:classifiers":[
        {
            "category":"Wholesale",
            "subcategory":"Farm Supplies",
            "type":"Manufacturing & Wholesale Goods"
        }
    ],
    "sg:phone":"+1 403 443 2355",
    "sg:postcode":"T0M 2A0",
    "sg:province":"AB",
    "sg:tags":[
        "fertilizer"
    ],
    "wof:name":"Kneehill Soil Svc Ltd",
    "wof:placetype":"venue"
},
  "geometry": {"coordinates":[-113.274032593,51.7041664124],"type":"Point"}
}