{
  "type": "Feature",
  "properties": {
    "addr:full":"504 29th St W Saskatoon SK S7L 0M5",
    "addr:housenumber":"504",
    "addr:postcode":"s7l 0m5",
    "addr:street":"29Th St W",
    "iso:country":"CA",
    "sg:address":"504 29th St W",
    "sg:city":"Saskatoon",
    "sg:classifiers":[
        {
            "category":"Organizations",
            "subcategory":"Religious Organization",
            "type":"Services"
        }
    ],
    "sg:phone":"+1 306 652 8405",
    "sg:postcode":"S7L 0M5",
    "sg:province":"SK",
    "sg:tags":[
        "church"
    ],
    "wof:name":"Seventh-Day Adventist Church",
    "wof:placetype":"venue"
},
  "geometry": {"coordinates":[-106.67699399999999,52.137238],"type":"Point"}
}