{
  "type": "Feature",
  "properties": {
    "addr:full":"Nepean ON K2E 8A5",
    "addr:postcode":"k2e 8a5",
    "iso:country":"CA",
    "sg:city":"Nepean",
    "sg:classifiers":[
        {
            "category":"Shopping",
            "subcategory":"Computers & Home Electronics",
            "type":"Retail Goods"
        }
    ],
    "sg:phone":"+1 613 727 8184",
    "sg:postcode":"K2E 8A5",
    "sg:province":"ON",
    "sg:tags":[
        "software"
    ],
    "wof:name":"New Vision Technologies Inc",
    "wof:placetype":"venue"
},
  "geometry": {"coordinates":[-75.705254,45.330959],"type":"Point"}
}