{
  "type": "Feature",
  "properties": {
    "addr:full":"14522 123 Ave NW Edmonton AB T5L 2Y3",
    "addr:housenumber":"14522",
    "addr:postcode":"t5l 2y3",
    "addr:street":"123 Ave Nw",
    "iso:country":"CA",
    "sg:address":"14522 123 Ave NW",
    "sg:city":"Edmonton",
    "sg:phone":"+1 780 452 6640",
    "sg:postcode":"T5L 2Y3",
    "sg:province":"AB",
    "sg:tags":[
        "equipment",
        "station"
    ],
    "wof:name":"Keller Equipment Supply Ltd",
    "wof:placetype":"venue"
},
  "geometry": {"coordinates":[-113.57214399999999,53.576977],"type":"Point"}
}