{
  "type": "Feature",
  "properties": {
    "addr:full":"544 Bridgeport Rd E Kitchener ON N2K 1N7",
    "addr:housenumber":"544",
    "addr:postcode":"n2k 1n7",
    "addr:street":"Bridgeport Rd E",
    "iso:country":"CA",
    "sg:address":"544 Bridgeport Rd E",
    "sg:city":"Kitchener",
    "sg:classifiers":[
        {
            "category":"Organizations",
            "subcategory":"Religious Organization",
            "type":"Services"
        }
    ],
    "sg:phone":"+1 519 743 4464",
    "sg:postcode":"N2K 1N7",
    "sg:province":"ON",
    "sg:tags":[
        "church"
    ],
    "wof:name":"St Paul's Lutheran Church",
    "wof:placetype":"venue"
},
  "geometry": {"coordinates":[-80.4859085083,43.4762382507],"type":"Point"}
}