{
  "type": "Feature",
  "properties": {
    "addr:full":"350 Dundas St W Toronto ON M5T 1G5",
    "addr:housenumber":"350",
    "addr:postcode":"m5t 1g5",
    "addr:street":"Dundas St W",
    "iso:country":"CA",
    "sg:address":"350 Dundas St W",
    "sg:city":"Toronto",
    "sg:classifiers":[
        {
            "category":"Organizations",
            "subcategory":"Professional Association",
            "type":"Services"
        }
    ],
    "sg:phone":"+1 416 977 3688",
    "sg:postcode":"M5T 1G5",
    "sg:province":"ON",
    "sg:tags":[
        "club"
    ],
    "wof:name":"Chinese United Dramatic Scty",
    "wof:placetype":"venue"
},
  "geometry": {"coordinates":[-79.393089,43.654102],"type":"Point"}
}