{
  "type": "Feature",
  "properties": {
    "addr:full":"927 Liverpool Rd Pickering ON L1W 1S7",
    "addr:housenumber":"927",
    "addr:postcode":"l1w 1s7",
    "addr:street":"Liverpool Rd",
    "iso:country":"CA",
    "sg:address":"927 Liverpool Rd",
    "sg:city":"Pickering",
    "sg:classifiers":[
        {
            "category":"Health Services",
            "subcategory":"Doctor",
            "type":"Services"
        }
    ],
    "sg:phone":"+1 905 839 5951",
    "sg:postcode":"L1W 1S7",
    "sg:province":"ON",
    "sg:tags":[
        "dentist"
    ],
    "wof:name":"Weiner, Steven DDS",
    "wof:placetype":"venue"
},
  "geometry": {"coordinates":[-79.08678399999999,43.827972],"type":"Point"}
}