{
  "type": "Feature",
  "properties": {
    "addr:full":"13395 Desro Dr Windsor ON N8N 2L9",
    "addr:housenumber":"13395",
    "addr:postcode":"n8n 2l9",
    "addr:street":"Desro Dr",
    "iso:country":"CA",
    "sg:address":"13395 Desro Dr",
    "sg:city":"Windsor",
    "sg:classifiers":[
        {
            "category":"Retail",
            "subcategory":"Auto Repair",
            "type":"Services"
        }
    ],
    "sg:phone":"+1 519 735 8113",
    "sg:postcode":"N8N 2L9",
    "sg:province":"ON",
    "sg:tags":[
        "body",
        "automobile",
        "painting"
    ],
    "wof:name":"G & G Auto Body",
    "wof:placetype":"venue"
},
  "geometry": {"coordinates":[-83.033913,42.317822],"type":"Point"}
}