{
  "type": "Feature",
  "properties": {
    "addr:full":"Nepean ON K2E 8C4",
    "addr:postcode":"k2e 8c4",
    "iso:country":"CA",
    "sg:city":"Nepean",
    "sg:classifiers":[
        {
            "category":"Shopping",
            "subcategory":"Computers & Home Electronics",
            "type":"Retail Goods"
        }
    ],
    "sg:phone":"+1 613 225 2300",
    "sg:postcode":"K2E 8C4",
    "sg:province":"ON",
    "sg:tags":[
        "software"
    ],
    "wof:name":"Ihs Solutions Ltd",
    "wof:placetype":"venue"
},
  "geometry": {"coordinates":[-75.70534499999999,45.335648],"type":"Point"}
}