{
  "type": "Feature",
  "properties": {
    "addr:full":"Pembroke ON K8A 4P1",
    "addr:postcode":"k8a 4p1",
    "iso:country":"CA",
    "sg:city":"Pembroke",
    "sg:classifiers":[
        {
            "category":"Food & Beverages",
            "subcategory":"Groceries & Convenience Stores",
            "type":"Retail Goods"
        }
    ],
    "sg:phone":"+1 613 735 4605",
    "sg:postcode":"K8A 4P1",
    "sg:province":"ON",
    "sg:tags":[
        "grocer"
    ],
    "wof:name":"Tempo Convenience Store",
    "wof:placetype":"venue"
},
  "geometry": {"coordinates":[-77.12112399999999,45.821854],"type":"Point"}
}