{
  "type": "Feature",
  "properties": {
    "iso:country":"CA",
    "sg:address":"300 Silver Springs Blvd",
    "sg:city":"Scarborough",
    "sg:classifiers":[
        {
            "category":"Recreation",
            "type":"Entertainment"
        }
    ],
    "sg:phone":"+1 416 396 4041",
    "sg:postcode":"M1V 1S4",
    "sg:province":"ON",
    "sg:tags":[
        "tennis",
        "court"
    ],
    "wof:name":"Lamorux Tennis Ctr",
    "wof:placetype":"venue"
},
  "geometry": {"coordinates":[-79.302803,43.805878],"type":"Point"}
}