{
  "type": "Feature",
  "properties": {
    "iso:country":"CA",
    "sg:address":"3905 Manchester Rd SE",
    "sg:city":"Calgary",
    "sg:classifiers":[
        {
            "category":"Retail",
            "subcategory":"Car Wash",
            "type":"Services"
        }
    ],
    "sg:phone":"+1 403 243 7174",
    "sg:postcode":"T2G 4A1",
    "sg:province":"AB",
    "sg:tags":[
        "automobile",
        "detail",
        "clean"
    ],
    "wof:name":"Auto Protectors",
    "wof:placetype":"venue"
},
  "geometry": {"coordinates":[-114.058921814,51.0193901062],"type":"Point"}
}