{
  "type": "Feature",
  "properties": {
    "iso:country":"CA",
    "sg:city":"London",
    "sg:classifiers":[
        {
            "category":"Shopping",
            "subcategory":"Gifts & Souvenirs",
            "type":"Retail Goods"
        }
    ],
    "sg:phone":"+1 519 673 6599",
    "sg:postcode":"N6G 3Y9",
    "sg:province":"ON",
    "sg:tags":[
        "novelty"
    ],
    "wof:name":"As Seen on Tv Showcase",
    "wof:placetype":"venue"
},
  "geometry": {"coordinates":[-81.281654,43.025227],"type":"Point"}
}