{
  "type": "Feature",
  "properties": {
    "addr:full":"386 106E Av Saint-Georges-DE-Champlain QC G9T 3J8",
    "addr:housenumber":"386",
    "addr:postcode":"g9t 3j8",
    "addr:street":"106E Av Saint-Georges-De-Champlain",
    "iso:country":"CA",
    "sg:address":"386 106E Av",
    "sg:city":"Saint-Georges-DE-Champlain",
    "sg:classifiers":[
        {
            "category":"Wholesale",
            "subcategory":"Meat",
            "type":"Manufacturing & Wholesale Goods"
        }
    ],
    "sg:phone":"+1 819 538 2066",
    "sg:postcode":"G9T 3J8",
    "sg:province":"QC",
    "sg:tags":[
        "butchering"
    ],
    "wof:name":"Fugere Tancrede Enr",
    "wof:placetype":"venue"
},
  "geometry": {"coordinates":[-72.34311676030001,46.4410400391],"type":"Point"}
}