{
  "type": "Feature",
  "properties": {
    "iso:country":"CA",
    "sg:city":"Brampton",
    "sg:classifiers":[
        {
            "category":"Manufacturing",
            "subcategory":"Textiles",
            "type":"Manufacturing & Wholesale Goods"
        }
    ],
    "sg:phone":"+1 905 790 6333",
    "sg:postcode":"L6T 5B4",
    "sg:province":"ON",
    "sg:tags":[
        "curtain"
    ],
    "wof:name":"Hospitality Contrct Drapery",
    "wof:placetype":"venue"
},
  "geometry": {"coordinates":[-79.6802368164,43.7335777283],"type":"Point"}
}