{
  "type": "Feature",
  "properties": {
    "addr:full":"2780 Norland Ave Burnaby BC V5B 3A6",
    "addr:housenumber":"2780",
    "addr:postcode":"v5b 3a6",
    "addr:street":"Norland Ave",
    "iso:country":"CA",
    "sg:address":"2780 Norland Ave",
    "sg:city":"Burnaby",
    "sg:classifiers":[
        {
            "category":"Manufacturing",
            "subcategory":"Tools & Machinery",
            "type":"Manufacturing & Wholesale Goods"
        }
    ],
    "sg:phone":"+1 604 437 7625",
    "sg:postcode":"V5B 3A6",
    "sg:province":"BC",
    "sg:tags":[
        "boring",
        "drilling"
    ],
    "wof:name":"Traxxon Rock Drills Ltd",
    "wof:placetype":"venue"
},
  "geometry": {"coordinates":[-122.98158264200001,49.2593765259],"type":"Point"}
}