{
  "type": "Feature",
  "properties": {
    "addr:full":"4921 Straume Ave Terrace BC V8G 2C9",
    "addr:postcode":"4921;v8g 2c9",
    "addr:street":"Straume Ave",
    "iso:country":"CA",
    "sg:address":"4921 Straume Ave",
    "sg:city":"Terrace",
    "sg:classifiers":[
        {
            "category":"Building & Trades",
            "subcategory":"Landscaping Services",
            "type":"Services"
        }
    ],
    "sg:phone":"+1 250 615 8638",
    "sg:postcode":"V8G 2C9",
    "sg:province":"BC",
    "sg:tags":[
        "marking",
        "parking",
        "maintenance",
        "landscape",
        "contractor"
    ],
    "wof:name":"Master Sweeper Parking Lot",
    "wof:placetype":"venue"
},
  "geometry": {"coordinates":[-128.60731506400001,54.5240745544],"type":"Point"}
}