{
  "type": "Feature",
  "properties": {
    "addr:full":"Ottawa ON K2A 1C4",
    "addr:postcode":"k2a 1c4",
    "iso:country":"CA",
    "sg:city":"Ottawa",
    "sg:classifiers":[
        {
            "category":"Insurance",
            "subcategory":"Insurance Agent",
            "type":"Services"
        }
    ],
    "sg:phone":"+1 613 729 6370",
    "sg:postcode":"K2A 1C4",
    "sg:province":"ON",
    "wof:name":"Michael W Henderson Insurance",
    "wof:placetype":"venue"
},
  "geometry": {"coordinates":[-75.74987,45.379456],"type":"Point"}
}