{
  "type": "Feature",
  "properties": {
    "addr:full":"Toronto ON M5J 2R9",
    "addr:postcode":"m5j 2r9",
    "iso:country":"CA",
    "sg:city":"Toronto",
    "sg:classifiers":[
        {
            "category":"Recreation",
            "type":"Entertainment"
        }
    ],
    "sg:phone":"+1 416 723 0364",
    "sg:postcode":"M5J 2R9",
    "sg:province":"ON",
    "sg:tags":[
        "party",
        "fishing"
    ],
    "wof:name":"Murray's Fly Fishing School",
    "wof:placetype":"venue"
},
  "geometry": {"coordinates":[-79.375214,43.641857],"type":"Point"}
}