{
  "type": "Feature",
  "properties": {
    "addr:full":"6995 Av DE Monkland Montreal QC H4B 1J8",
    "addr:housenumber":"6995",
    "addr:postcode":"h4b 1j8",
    "addr:street":"Av De Monkland",
    "iso:country":"CA",
    "sg:address":"6995 Av DE Monkland",
    "sg:city":"Montreal",
    "sg:classifiers":[
        {
            "category":"Restaurant",
            "type":"Food & Drink"
        }
    ],
    "sg:phone":"+1 514 482 0040",
    "sg:postcode":"H4B 1J8",
    "sg:province":"QC",
    "wof:name":"Souvlaki Georges",
    "wof:placetype":"venue"
},
  "geometry": {"coordinates":[-73.63697814939999,45.4598388672],"type":"Point"}
}