{
  "type": "Feature",
  "properties": {
    "addr:full":"150 Seventh Conc E Millgrove ON L0R 1V0",
    "addr:housenumber":"150",
    "addr:postcode":"l0r 1v0",
    "addr:street":"Seventh Conc E Millgrove",
    "iso:country":"CA",
    "sg:address":"150 Seventh Conc E",
    "sg:city":"Millgrove",
    "sg:classifiers":[
        {
            "category":"Travel",
            "subcategory":"Campground",
            "type":"Entertainment"
        }
    ],
    "sg:phone":"+1 905 689 3000",
    "sg:postcode":"L0R 1V0",
    "sg:province":"ON",
    "sg:tags":[
        "camp",
        "fishing"
    ],
    "wof:name":"Red Pine Wilderness Lodge",
    "wof:placetype":"venue"
},
  "geometry": {"coordinates":[-79.958023,43.33577],"type":"Point"}
}