{
  "type": "Feature",
  "properties": {
    "addr:full":"6071 Av Notre-Dame-DE-Grace Montreal QC H4A 1N3",
    "addr:housenumber":"6071",
    "addr:postcode":"h4a 1n3",
    "addr:street":"Av Notre-Dame-De-Grace",
    "iso:country":"CA",
    "sg:address":"6071 Av Notre-Dame-DE-Grace",
    "sg:city":"Montreal",
    "sg:classifiers":[
        {
            "category":"Professional",
            "subcategory":"Management & Consulting",
            "type":"Services"
        }
    ],
    "sg:phone":"+1 514 938 1616",
    "sg:postcode":"H4A 1N3",
    "sg:province":"QC",
    "sg:tags":[
        "consultant",
        "instructional"
    ],
    "wof:name":"Challenge-Action",
    "wof:placetype":"venue"
},
  "geometry": {"coordinates":[-73.6231765747,45.4687767029],"type":"Point"}
}