{
  "type": "Feature",
  "properties": {
    "iso:country":"CA",
    "sg:address":"2620 4th Ave W",
    "sg:city":"Vancouver",
    "sg:classifiers":[
        {
            "category":"Building & Trades",
            "subcategory":"Plumbing",
            "type":"Services"
        }
    ],
    "sg:phone":"+1 604 738 8533",
    "sg:postcode":"V6K 1P7",
    "sg:province":"BC",
    "sg:tags":[
        "furnace",
        "heating",
        "contractor"
    ],
    "wof:name":"Maple Repair Heating & Gas",
    "wof:placetype":"venue"
},
  "geometry": {"coordinates":[-123.164894104,49.2681541443],"type":"Point"}
}