{
  "type": "Feature",
  "properties": {
    "iso:country":"CA",
    "sg:address":"4225 44 Ave NE",
    "sg:city":"Calgary",
    "sg:classifiers":[
        {
            "category":"Education",
            "subcategory":"School",
            "type":"Public Place"
        }
    ],
    "sg:phone":"+1 403 285 4170",
    "sg:postcode":"T1Y 4Y1",
    "sg:province":"AB",
    "wof:name":"St Wilfrid Elementary School",
    "wof:placetype":"venue"
},
  "geometry": {"coordinates":[-113.969337463,51.0924453735],"type":"Point"}
}