{
  "type": "Feature",
  "properties": {
    "addr:full":"155 Rue Richelieu Saint-Jean-Sur-Richelieu QC J3B 6X7",
    "addr:housenumber":"155",
    "addr:postcode":"j3b 6x7",
    "addr:street":"Rue Richelieu",
    "iso:country":"CA",
    "sg:address":"155 Rue Richelieu",
    "sg:city":"Saint-Jean-Sur-Richelieu",
    "sg:classifiers":[
        {
            "category":"Shopping",
            "subcategory":"Hobbies, Toys, & Games",
            "type":"Retail Goods"
        }
    ],
    "sg:phone":"+1 450 357 1649",
    "sg:postcode":"J3B 6X7",
    "sg:province":"QC",
    "sg:tags":[
        "craft"
    ],
    "wof:name":"Atelier D'Angelyne",
    "wof:placetype":"venue"
},
  "geometry": {"coordinates":[-73.25058,45.305187],"type":"Point"}
}