{
  "type": "Feature",
  "properties": {
    "addr:full":"Huntingdon QC J0S 1H0",
    "addr:postcode":"j0s 1h0",
    "iso:country":"CA",
    "sg:city":"Huntingdon",
    "sg:classifiers":[
        {
            "category":"Professional",
            "subcategory":"Business Services",
            "type":"Services"
        }
    ],
    "sg:phone":"+1 450 264 5336",
    "sg:postcode":"J0S 1H0",
    "sg:province":"QC",
    "sg:tags":[
        "notary"
    ],
    "wof:name":"Pilon Menard & Pilon",
    "wof:placetype":"venue"
},
  "geometry": {"coordinates":[-74.1731643677,45.0879402161],"type":"Point"}
}