{
  "type": "Feature",
  "properties": {
    "addr:full":"Woodbridge ON L4L 5W1",
    "addr:postcode":"l4l 5w1",
    "iso:country":"CA",
    "sg:city":"Woodbridge",
    "sg:classifiers":[
        {
            "category":"Restaurant",
            "type":"Food & Drink"
        }
    ],
    "sg:phone":"+1 905 851 1514",
    "sg:postcode":"L4L 5W1",
    "sg:province":"ON",
    "wof:name":"Mega Bites Cafe",
    "wof:placetype":"venue"
},
  "geometry": {"coordinates":[-79.571686,43.7803],"type":"Point"}
}