{
  "type": "Feature",
  "properties": {
    "addr:full":"116 Clarendon Cres London ON N6C 5B8",
    "addr:housenumber":"116",
    "addr:postcode":"n6c 5b8",
    "addr:street":"Clarendon Cres",
    "iso:country":"CA",
    "sg:address":"116 Clarendon Cres",
    "sg:city":"London",
    "sg:classifiers":[
        {
            "category":"Retail",
            "subcategory":"Portrait Studio",
            "type":"Services"
        }
    ],
    "sg:phone":"+1 519 319 8465",
    "sg:postcode":"N6C 5B8",
    "sg:province":"ON",
    "sg:tags":[
        "photographer"
    ],
    "wof:name":"Countryside Memories",
    "wof:placetype":"venue"
},
  "geometry": {"coordinates":[-81.2427597046,42.9474601746],"type":"Point"}
}