{
  "type": "Feature",
  "properties": {
    "addr:full":"1892 Parkedale Ave E Brockville ON K6V 5T2",
    "addr:housenumber":"1892",
    "addr:postcode":"k6v 5t2",
    "addr:street":"Parkedale Ave E",
    "iso:country":"CA",
    "sg:address":"1892 Parkedale Ave E",
    "sg:city":"Brockville",
    "sg:classifiers":[
        {
            "category":"Professional",
            "subcategory":"Business Services",
            "type":"Services"
        }
    ],
    "sg:phone":"+1 613 342 0978",
    "sg:postcode":"K6V 5T2",
    "sg:province":"ON",
    "sg:tags":[
        "sweeping",
        "swimming"
    ],
    "wof:name":"J L Pryer High Pressure Clng",
    "wof:placetype":"venue"
},
  "geometry": {"coordinates":[-75.679451,44.617928],"type":"Point"}
}