{
  "type": "Feature",
  "properties": {
    "addr:full":"Frankford ON K0K 2C0",
    "addr:postcode":"k0k 2c0",
    "iso:country":"CA",
    "sg:city":"Frankford",
    "sg:classifiers":[
        {
            "category":"Shopping",
            "subcategory":"Discount & Variety Stores",
            "type":"Retail Goods"
        }
    ],
    "sg:phone":"+1 613 398 7511",
    "sg:postcode":"K0K 2C0",
    "sg:province":"ON",
    "wof:name":"Helen's Variety",
    "wof:placetype":"venue"
},
  "geometry": {"coordinates":[-77.593948,44.195709],"type":"Point"}
}