{
  "type": "Feature",
  "properties": {
    "addr:full":"3099 Av Des Eglantines Chertsey QC J0K 3K0",
    "addr:housenumber":"3099",
    "addr:postcode":"j0k 3k0",
    "addr:street":"Av Des Eglantines",
    "iso:country":"CA",
    "sg:address":"3099 Av Des Eglantines",
    "sg:city":"Chertsey",
    "sg:classifiers":[
        {
            "category":"Food & Beverages",
            "subcategory":"Groceries & Convenience Stores",
            "type":"Retail Goods"
        }
    ],
    "sg:phone":"+1 450 882 2966",
    "sg:postcode":"J0K 3K0",
    "sg:province":"QC",
    "wof:name":"Magasin General Grande Vallee",
    "wof:placetype":"venue"
},
  "geometry": {"coordinates":[-73.8805007935,46.1672134399],"type":"Point"}
}