{
  "type": "Feature",
  "properties": {
    "iso:country":"CA",
    "sg:address":"18 8E Av",
    "sg:city":"Melocheville",
    "sg:classifiers":[
        {
            "category":"Government",
            "subcategory":"Office",
            "type":"Public Place"
        }
    ],
    "sg:phone":"+1 450 429 7475",
    "sg:postcode":"J0S 1J0",
    "sg:province":"QC",
    "sg:tags":[
        "village"
    ],
    "wof:name":"Melocheville Garage Municipal",
    "wof:placetype":"venue"
},
  "geometry": {"coordinates":[-73.9648742676,45.3133277893],"type":"Point"}
}