{
  "type": "Feature",
  "properties": {
    "iso:country":"CA",
    "sg:address":"1100 Boul Vanier",
    "sg:city":"Laval",
    "sg:classifiers":[
        {
            "category":"Banks & Credit Unions",
            "subcategory":"Bank",
            "type":"Services"
        }
    ],
    "sg:phone":"+1 450 661 7272",
    "sg:postcode":"H7C 2R6",
    "sg:province":"QC",
    "wof:name":"Caisses Desjardins Ctr DE Svc",
    "wof:placetype":"venue"
},
  "geometry": {"coordinates":[-73.65799713129999,45.6101875305],"type":"Point"}
}