{
  "type": "Feature",
  "properties": {
    "addr:full":"580 Glovers Rd Hannon ON L0R 1P0",
    "addr:postcode":"l0r 1p0",
    "addr:street":"580 Glovers Rd",
    "iso:country":"CA",
    "sg:address":"580 Glovers Rd",
    "sg:city":"Hannon",
    "sg:classifiers":[
        {
            "category":"Building & Trades",
            "subcategory":"Construction",
            "type":"Services"
        }
    ],
    "sg:phone":"+1 905 692 9998",
    "sg:postcode":"L0R 1P0",
    "sg:province":"ON",
    "sg:tags":[
        "general",
        "contractor"
    ],
    "wof:name":"Digmor Excavating Ltd",
    "wof:placetype":"venue"
},
  "geometry": {"coordinates":[-79.8377380371,43.1985397339],"type":"Point"}
}