{
  "type": "Feature",
  "properties": {
    "addr:full":"5220 Boul Metropolitain E Saint-Leonard QC H1S 1A5",
    "addr:housenumber":"5220",
    "addr:postcode":"h1s 1a5",
    "addr:street":"Boul Metropolitain E",
    "iso:country":"CA",
    "sg:address":"5220 Boul Metropolitain E",
    "sg:city":"Saint-Leonard",
    "sg:classifiers":[
        {
            "category":"Shopping",
            "subcategory":"Clothing, Apparel, & Fashions",
            "type":"Retail Goods"
        }
    ],
    "sg:phone":"+1 514 593 1169",
    "sg:postcode":"H1S 1A5",
    "sg:province":"QC",
    "sg:tags":[
        "lingerie"
    ],
    "wof:name":"Boutique Seduction",
    "wof:placetype":"venue"
},
  "geometry": {"coordinates":[-73.590233,45.580296],"type":"Point"}
}