{
  "type": "Feature",
  "properties": {
    "addr:full":"565 Canarctic Dr North York ON M3J 2P9",
    "addr:housenumber":"565",
    "addr:postcode":"m3j 2p9",
    "addr:street":"Canarctic Dr",
    "iso:country":"CA",
    "sg:address":"565 Canarctic Dr",
    "sg:city":"North York",
    "sg:classifiers":[
        {
            "category":"Manufacturing",
            "subcategory":"Metals",
            "type":"Manufacturing & Wholesale Goods"
        }
    ],
    "sg:phone":"+1 416 663 2620",
    "sg:postcode":"M3J 2P9",
    "sg:province":"ON",
    "sg:tags":[
        "stamping"
    ],
    "wof:name":"City Metal Mfg",
    "wof:placetype":"venue"
},
  "geometry": {"coordinates":[-79.4848022461,43.7771148682],"type":"Point"}
}