{
  "type": "Feature",
  "properties": {
    "addr:full":"4 Rue DE Cernay Lorraine QC J6Z 2Z1",
    "addr:housenumber":"4",
    "addr:postcode":"j6z 2z1",
    "addr:street":"Rue De Cernay",
    "iso:country":"CA",
    "sg:address":"4 Rue DE Cernay",
    "sg:city":"Lorraine",
    "sg:classifiers":[
        {
            "category":"Manufacturing",
            "subcategory":"Metals",
            "type":"Manufacturing & Wholesale Goods"
        }
    ],
    "sg:phone":"+1 450 965 1932",
    "sg:postcode":"J6Z 2Z1",
    "sg:province":"QC",
    "sg:tags":[
        "plate",
        "tin"
    ],
    "wof:name":"Ferblanterie Reyco Inc",
    "wof:placetype":"venue"
},
  "geometry": {"coordinates":[-73.7822265625,45.6687355042],"type":"Point"}
}