{
  "type": "Feature",
  "properties": {
    "addr:full":"1615 Rue Du Sud Cowansville QC J2K 2Z4",
    "addr:housenumber":"1615",
    "addr:postcode":"j2k 2z4",
    "addr:street":"Rue Du Sud",
    "iso:country":"CA",
    "sg:address":"1615 Rue Du Sud",
    "sg:city":"Cowansville",
    "sg:classifiers":[
        {
            "category":"Food & Beverages",
            "subcategory":"Bakery",
            "type":"Retail Goods"
        }
    ],
    "sg:phone":"+1 450 263 9945",
    "sg:postcode":"J2K 2Z4",
    "sg:province":"QC",
    "sg:tags":[
        "doughnut"
    ],
    "wof:name":"Tim Hortons",
    "wof:placetype":"venue"
},
  "geometry": {"coordinates":[-72.754608,45.191105],"type":"Point"}
}