{
  "type": "Feature",
  "properties": {
    "addr:full":"5425 Av Casgrain # 702 Montreal QC H2T 1X6",
    "addr:housenumber":"5425;# 702",
    "addr:postcode":"h2t 1x6",
    "addr:street":"Av Casgrain",
    "iso:country":"CA",
    "sg:address":"5425 Av Casgrain # 702",
    "sg:city":"Montreal",
    "sg:classifiers":[
        {
            "category":"Manufacturing",
            "subcategory":"Textiles",
            "type":"Manufacturing & Wholesale Goods"
        }
    ],
    "sg:phone":"+1 514 276 2192",
    "sg:postcode":"H2T 1X6",
    "sg:province":"QC",
    "sg:tags":[
        "curtain"
    ],
    "wof:name":"Westmount Drapery Inc",
    "wof:placetype":"venue"
},
  "geometry": {"coordinates":[-73.596169,45.526493],"type":"Point"}
}