{
  "type": "Feature",
  "properties": {
    "iso:country":"CA",
    "sg:address":"125 Sun Pac Blvd",
    "sg:city":"Brampton",
    "sg:classifiers":[
        {
            "category":"Manufacturing",
            "subcategory":"Electronics",
            "type":"Manufacturing & Wholesale Goods"
        }
    ],
    "sg:phone":"+1 905 790 2200",
    "sg:postcode":"L6S 5Z6",
    "sg:province":"ON",
    "sg:tags":[
        "equipment",
        "electronic",
        "supply"
    ],
    "wof:name":"Conec Corp",
    "wof:placetype":"venue"
},
  "geometry": {"coordinates":[-79.6935577393,43.7560005188],"type":"Point"}
}