{
  "type": "Feature",
  "properties": {
    "addr:full":"770 Fraser Rd Hope BC V0X 1L0",
    "addr:housenumber":"770",
    "addr:postcode":"v0x 1l0",
    "addr:street":"Fraser Rd",
    "iso:country":"CA",
    "sg:address":"770 Fraser Rd",
    "sg:city":"Hope",
    "sg:classifiers":[
        {
            "category":"Shopping",
            "subcategory":"Department Store",
            "type":"Retail Goods"
        }
    ],
    "sg:phone":"+1 604 869 9205",
    "sg:postcode":"V0X 1L0",
    "sg:province":"BC",
    "wof:name":"Fields Stores",
    "wof:placetype":"venue"
},
  "geometry": {"coordinates":[-121.44362599999999,49.379543],"type":"Point"}
}