{
  "type": "Feature",
  "properties": {
    "iso:country":"CA",
    "sg:address":"102 Saskatchewan Ave E",
    "sg:city":"Portage LA Prairie",
    "sg:classifiers":[
        {
            "category":"Shopping",
            "subcategory":"Shoes",
            "type":"Retail Goods"
        }
    ],
    "sg:phone":"+1 204 239 0078",
    "sg:postcode":"R1N 0L1",
    "sg:province":"MB",
    "wof:name":"Shooz Fashion Footwear",
    "wof:placetype":"venue"
},
  "geometry": {"coordinates":[-98.2896575928,49.9731674194],"type":"Point"}
}