{
  "type": "Feature",
  "properties": {
    "addr:full":"Richmond BC V6X 2X9",
    "addr:postcode":"v6x 2x9",
    "iso:country":"CA",
    "sg:city":"Richmond",
    "sg:classifiers":[
        {
            "category":"Personal",
            "subcategory":"Beauty Salon",
            "type":"Services"
        }
    ],
    "sg:phone":"+1 604 270 7333",
    "sg:postcode":"V6X 2X9",
    "sg:province":"BC",
    "wof:name":"Sparky's Kutz For Kidz",
    "wof:placetype":"venue"
},
  "geometry": {"coordinates":[-123.136291504,49.1751708984],"type":"Point"}
}