{
  "type": "Feature",
  "properties": {
    "addr:full":"Schumacher ON P0N 1G0",
    "addr:postcode":"p0n 1g0",
    "iso:country":"CA",
    "sg:city":"Schumacher",
    "sg:classifiers":[
        {
            "category":"Professional",
            "subcategory":"Engineering",
            "type":"Services"
        }
    ],
    "sg:phone":"+1 705 360 5252",
    "sg:postcode":"P0N 1G0",
    "sg:province":"ON",
    "sg:tags":[
        "engineer"
    ],
    "wof:name":"Acculab Engineering & Testing",
    "wof:placetype":"venue"
},
  "geometry": {"coordinates":[-81.297302,48.47691],"type":"Point"}
}