{
  "type": "Feature",
  "properties": {
    "addr:full":"403 N 9th Ave Golden BC V0A 1H0",
    "addr:housenumber":"403",
    "addr:postcode":"v0a 1h0",
    "addr:street":"N 9Th Ave",
    "iso:country":"CA",
    "sg:address":"403 N 9th Ave",
    "sg:city":"Golden",
    "sg:classifiers":[
        {
            "category":"Shopping",
            "subcategory":"Department Store",
            "type":"Retail Goods"
        }
    ],
    "sg:phone":"+1 250 344 2775",
    "sg:postcode":"V0A 1H0",
    "sg:province":"BC",
    "sg:tags":[
        "shop"
    ],
    "wof:name":"Golden Dollar Store",
    "wof:placetype":"venue"
},
  "geometry": {"coordinates":[-116.966393,51.299911],"type":"Point"}
}