{
  "type": "Feature",
  "properties": {
    "addr:full":"1445 Rue Lambert-Closse Montreal QC H3H 1Z5",
    "addr:housenumber":"1445",
    "addr:postcode":"h3h 1z5",
    "addr:street":"Rue Lambert-Closse",
    "iso:country":"CA",
    "sg:address":"1445 Rue Lambert-Closse",
    "sg:city":"Montreal",
    "sg:classifiers":[
        {
            "category":"Professional",
            "subcategory":"Management & Consulting",
            "type":"Services"
        }
    ],
    "sg:phone":"+1 514 932 9652",
    "sg:postcode":"H3H 1Z5",
    "sg:province":"QC",
    "sg:tags":[
        "consultant",
        "telecommunication"
    ],
    "wof:name":"Berlan Syscomm Inc",
    "wof:placetype":"venue"
},
  "geometry": {"coordinates":[-73.58409881590001,45.4905891418],"type":"Point"}
}