{
  "type": "Feature",
  "properties": {
    "iso:country":"CA",
    "sg:address":"40 Godstone Rd",
    "sg:city":"North York",
    "sg:classifiers":[
        {
            "category":"Real Estate",
            "subcategory":"Real Estate Operator",
            "type":"Services"
        }
    ],
    "sg:phone":"+1 416 499 9103",
    "sg:postcode":"M2J 3C7",
    "sg:province":"ON",
    "sg:tags":[
        "apartment"
    ],
    "wof:name":"Venice Park Developments Ltd",
    "wof:placetype":"venue"
},
  "geometry": {"coordinates":[-79.34707641599999,43.7818527222],"type":"Point"}
}