{
  "type": "Feature",
  "properties": {
    "addr:full":"6955 Millcreek Dr Mississauga ON L5N 5Z6",
    "addr:housenumber":"6955",
    "addr:postcode":"l5n 5z6",
    "addr:street":"Millcreek Dr",
    "iso:country":"CA",
    "sg:address":"6955 Millcreek Dr",
    "sg:city":"Mississauga",
    "sg:classifiers":[
        {
            "category":"Organizations",
            "subcategory":"Religious Organization",
            "type":"Services"
        }
    ],
    "sg:phone":"+1 905 542 1522",
    "sg:postcode":"L5N 5Z6",
    "sg:province":"ON",
    "sg:tags":[
        "church"
    ],
    "wof:name":"Logos Baptist Church",
    "wof:placetype":"venue"
},
  "geometry": {"coordinates":[-79.7591781616,43.5965843201],"type":"Point"}
}