{
  "type": "Feature",
  "properties": {
    "addr:full":"1499 Main St E Hamilton ON L8K 1C9",
    "addr:housenumber":"1499",
    "addr:postcode":"l8k 1c9",
    "addr:street":"Main St E",
    "iso:country":"CA",
    "sg:address":"1499 Main St E",
    "sg:city":"Hamilton",
    "sg:classifiers":[
        {
            "category":"Personal",
            "subcategory":"Beauty Salon",
            "type":"Services"
        }
    ],
    "sg:phone":"+1 905 544 3124",
    "sg:postcode":"L8K 1C9",
    "sg:province":"ON",
    "wof:name":"Axion Hair Design & Esthetics",
    "wof:placetype":"venue"
},
  "geometry": {"coordinates":[-79.8056945801,43.2395401001],"type":"Point"}
}