{
  "type": "Feature",
  "properties": {
    "addr:full":"1514 9th Ave E Owen Sound ON N4K 3G1",
    "addr:housenumber":"1514",
    "addr:postcode":"n4k 3g1",
    "addr:street":"9Th Ave E",
    "iso:country":"CA",
    "sg:address":"1514 9th Ave E",
    "sg:city":"Owen Sound",
    "sg:classifiers":[
        {
            "category":"Health Services",
            "subcategory":"Medical Lab",
            "type":"Services"
        }
    ],
    "sg:phone":"+1 519 371 2594",
    "sg:postcode":"N4K 3G1",
    "sg:province":"ON",
    "wof:name":"Stokes, Bob",
    "wof:placetype":"venue"
},
  "geometry": {"coordinates":[-80.92849,44.570187],"type":"Point"}
}