{
  "type": "Feature",
  "properties": {
    "addr:full":"2827 14 St SW Calgary AB T2T 3V3",
    "addr:housenumber":"2827",
    "addr:postcode":"t2t 3v3",
    "addr:street":"14 St Sw",
    "iso:country":"CA",
    "sg:address":"2827 14 St SW",
    "sg:city":"Calgary",
    "sg:classifiers":[
        {
            "category":"Restaurant",
            "type":"Food & Drink"
        }
    ],
    "sg:phone":"+1 403 294 9494",
    "sg:postcode":"T2T 3V3",
    "sg:province":"AB",
    "sg:tags":[
        "pizza"
    ],
    "wof:name":"Isa's Pizza Ltd",
    "wof:placetype":"venue"
},
  "geometry": {"coordinates":[-114.094909668,51.0292243958],"type":"Point"}
}