{
  "type": "Feature",
  "properties": {
    "addr:full":"20 Rue DE LA Cathedrale Gaspe QC G4X 1N8",
    "addr:housenumber":"20",
    "addr:postcode":"g4x 1n8",
    "addr:street":"Rue De La Cathedrale",
    "iso:country":"CA",
    "sg:address":"20 Rue DE LA Cathedrale",
    "sg:city":"Gaspe",
    "sg:classifiers":[
        {
            "category":"Organizations",
            "subcategory":"Religious Organization",
            "type":"Services"
        }
    ],
    "sg:phone":"+1 418 368 5541",
    "sg:postcode":"G4X 1N8",
    "sg:province":"QC",
    "sg:tags":[
        "church"
    ],
    "wof:name":"Presbyteres Gaspe Christ-Roy",
    "wof:placetype":"venue"
},
  "geometry": {"coordinates":[-64.4868011475,48.8298950195],"type":"Point"}
}