{
  "type": "Feature",
  "properties": {
    "addr:full":"613 Rue King E Sherbrooke QC J1G 1B9",
    "addr:housenumber":"613",
    "addr:postcode":"j1g 1b9",
    "addr:street":"Rue King E",
    "iso:country":"CA",
    "sg:address":"613 Rue King E",
    "sg:city":"Sherbrooke",
    "sg:classifiers":[
        {
            "category":"Retail",
            "subcategory":"Laundry & Dry Cleaning",
            "type":"Services"
        }
    ],
    "sg:phone":"+1 819 566 0253",
    "sg:postcode":"J1G 1B9",
    "sg:province":"QC",
    "sg:tags":[
        "apparel",
        "maternity",
        "diaper"
    ],
    "wof:name":"Boutique Mere Poule",
    "wof:placetype":"venue"
},
  "geometry": {"coordinates":[-71.875427,45.408218],"type":"Point"}
}