{
  "type": "Feature",
  "properties": {
    "addr:full":"2190 Rue Crescent Montreal QC H3G 2B8",
    "addr:housenumber":"2190",
    "addr:postcode":"h3g 2b8",
    "addr:street":"Rue Crescent",
    "iso:country":"CA",
    "sg:address":"2190 Rue Crescent",
    "sg:city":"Montreal",
    "sg:classifiers":[
        {
            "category":"Personal",
            "subcategory":"Beauty Salon",
            "type":"Services"
        }
    ],
    "sg:phone":"+1 514 844 4590",
    "sg:postcode":"H3G 2B8",
    "sg:province":"QC",
    "sg:tags":[
        "day",
        "massage"
    ],
    "wof:name":"St James Spa",
    "wof:placetype":"venue"
},
  "geometry": {"coordinates":[-73.57875061039999,45.4985237122],"type":"Point"}
}