{
  "type": "Feature",
  "properties": {
    "addr:full":"1288 Hwy 7A Bethany ON L0A 1A0",
    "addr:housenumber":"1288",
    "addr:postcode":"l0a 1a0",
    "addr:street":"Hwy 7A",
    "iso:country":"CA",
    "sg:address":"1288 Hwy 7A",
    "sg:city":"Bethany",
    "sg:classifiers":[
        {
            "category":"Restaurant",
            "type":"Food & Drink"
        }
    ],
    "sg:phone":"+1 705 277 2291",
    "sg:postcode":"L0A 1A0",
    "sg:province":"ON",
    "wof:name":"Granary Restaurant",
    "wof:placetype":"venue"
},
  "geometry": {"coordinates":[-78.587891,44.177277],"type":"Point"}
}