{
  "type": "Feature",
  "properties": {
    "addr:full":"10265 143 St Surrey BC V3T 4T4",
    "addr:housenumber":"10265",
    "addr:postcode":"v3t 4t4",
    "addr:street":"143 St",
    "iso:country":"CA",
    "sg:address":"10265 143 St",
    "sg:city":"Surrey",
    "sg:classifiers":[
        {
            "category":"Professional",
            "subcategory":"Detective & Security Services",
            "type":"Services"
        }
    ],
    "sg:phone":"+1 604 584 0882",
    "sg:postcode":"V3T 4T4",
    "sg:province":"BC",
    "sg:tags":[
        "system"
    ],
    "wof:name":"Endurance Security",
    "wof:placetype":"venue"
},
  "geometry": {"coordinates":[-122.826179504,49.1889801025],"type":"Point"}
}