{
  "type": "Feature",
  "properties": {
    "addr:full":"2090 10E Rue Grand-Mere QC G9T 6V8",
    "addr:housenumber":"2090",
    "addr:postcode":"g9t 6v8",
    "addr:street":"10E Rue Grand-Mere",
    "iso:country":"CA",
    "sg:address":"2090 10E Rue",
    "sg:city":"Grand-Mere",
    "sg:classifiers":[
        {
            "category":"Social Services",
            "subcategory":"Child Care",
            "type":"Services"
        }
    ],
    "sg:phone":"+1 819 538 1554",
    "sg:postcode":"G9T 6V8",
    "sg:province":"QC",
    "wof:name":"Cpe Manege Des Tout-Petits",
    "wof:placetype":"venue"
},
  "geometry": {"coordinates":[-72.712318,46.605419],"type":"Point"}
}