{
  "type": "Feature",
  "properties": {
    "addr:full":"59 Ch Bullard Stanbridge East QC J0J 2H0",
    "addr:housenumber":"59",
    "addr:postcode":"j0j 2h0",
    "addr:street":"Ch Bullard",
    "iso:country":"CA",
    "sg:address":"59 Ch Bullard",
    "sg:city":"Stanbridge East",
    "sg:classifiers":[
        {
            "category":"Retail",
            "subcategory":"Auto Repair",
            "type":"Services"
        }
    ],
    "sg:phone":"+1 450 248 4119",
    "sg:postcode":"J0J 2H0",
    "sg:province":"QC",
    "sg:tags":[
        "repairing",
        "equipment",
        "parts",
        "tractor",
        "automobile"
    ],
    "wof:name":"Garage D & C Messier Inc",
    "wof:placetype":"venue"
},
  "geometry": {"coordinates":[-72.929237,45.137749],"type":"Point"}
}