{
  "type": "Feature",
  "properties": {
    "addr:full":"536 Av Mondor Saint-Hyacinthe QC J2S 5A9",
    "addr:postcode":"j2s 5a9",
    "addr:street":"536 Av Mondor",
    "iso:country":"CA",
    "sg:address":"536 Av Mondor",
    "sg:city":"Saint-Hyacinthe",
    "sg:classifiers":[
        {
            "category":"Food & Beverages",
            "subcategory":"Specialty",
            "type":"Retail Goods"
        }
    ],
    "sg:phone":"+1 450 773 5225",
    "sg:postcode":"J2S 5A9",
    "sg:province":"QC",
    "wof:name":"Dame Nature Enr",
    "wof:placetype":"venue"
},
  "geometry": {"coordinates":[-72.94519,45.625427],"type":"Point"}
}