{
  "type": "Feature",
  "properties": {
    "addr:full":"101 Main St N Markham ON L3P 1X9",
    "addr:housenumber":"101",
    "addr:postcode":"l3p 1x9",
    "addr:street":"Main St N",
    "iso:country":"CA",
    "sg:address":"101 Main St N",
    "sg:city":"Markham",
    "sg:classifiers":[
        {
            "category":"Banks & Credit Unions",
            "subcategory":"Bank",
            "type":"Services"
        }
    ],
    "sg:phone":"+1 905 294 3113",
    "sg:postcode":"L3P 1X9",
    "sg:province":"ON",
    "wof:name":"Scotiabank",
    "wof:placetype":"venue"
},
  "geometry": {"coordinates":[-79.260704,43.877689],"type":"Point"}
}