{
  "type": "Feature",
  "properties": {
    "addr:full":"5305 48th Ave Hughenden AB T0B 2E0",
    "addr:housenumber":"5305",
    "addr:postcode":"t0b 2e0",
    "addr:street":"48Th Ave",
    "iso:country":"CA",
    "sg:address":"5305 48th Ave",
    "sg:city":"Hughenden",
    "sg:classifiers":[
        {
            "category":"Recreation",
            "type":"Entertainment"
        }
    ],
    "sg:phone":"+1 780 856 3731",
    "sg:postcode":"T0B 2E0",
    "sg:province":"AB",
    "sg:tags":[
        "hall",
        "auditorium"
    ],
    "wof:name":"Amisk Community Hall",
    "wof:placetype":"venue"
},
  "geometry": {"coordinates":[-110.975334,52.509483],"type":"Point"}
}