{
  "type": "Feature",
  "properties": {
    "addr:full":"Kitchener ON N2B 3C1",
    "addr:postcode":"n2b 3c1",
    "iso:country":"CA",
    "sg:city":"Kitchener",
    "sg:classifiers":[
        {
            "category":"Professional",
            "subcategory":"Employment Agencies",
            "type":"Services"
        }
    ],
    "sg:phone":"+1 519 576 0920",
    "sg:postcode":"N2B 3C1",
    "sg:province":"ON",
    "sg:tags":[
        "opportunity",
        "contractor"
    ],
    "wof:name":"Grand River Personnel Ltd",
    "wof:placetype":"venue"
},
  "geometry": {"coordinates":[-80.4674911499,43.4634094238],"type":"Point"}
}