{
  "type": "Feature",
  "properties": {
    "iso:country":"CA",
    "sg:city":"Collingwood",
    "sg:classifiers":[
        {
            "category":"Retail",
            "subcategory":"Auto Repair",
            "type":"Services"
        }
    ],
    "sg:phone":"+1 705 444 2531",
    "sg:postcode":"L9Y 3Z1",
    "sg:province":"ON",
    "sg:tags":[
        "body",
        "automobile",
        "painting"
    ],
    "wof:name":"Rentner Auto Refinishing",
    "wof:placetype":"venue"
},
  "geometry": {"coordinates":[-80.216827,44.499889],"type":"Point"}
}