{
  "type": "Feature",
  "properties": {
    "addr:full":"14 Peter St S Orillia ON L3V 5A9",
    "addr:housenumber":"14",
    "addr:postcode":"l3v 5a9",
    "addr:street":"Peter St S",
    "iso:country":"CA",
    "sg:address":"14 Peter St S",
    "sg:city":"Orillia",
    "sg:classifiers":[
        {
            "category":"Personal",
            "type":"Services"
        }
    ],
    "sg:phone":"+1 705 327 0457",
    "sg:postcode":"L3V 5A9",
    "sg:province":"ON",
    "sg:tags":[
        "therapist",
        "massage"
    ],
    "wof:name":"Pro Active Health Care",
    "wof:placetype":"venue"
},
  "geometry": {"coordinates":[-79.417213,44.608826],"type":"Point"}
}