{
  "type": "Feature",
  "properties": {
    "iso:country":"CA",
    "sg:address":"1041 East Lakeview Rd",
    "sg:city":"Chestermere",
    "sg:classifiers":[
        {
            "category":"Travel",
            "subcategory":"Campground",
            "type":"Entertainment"
        }
    ],
    "sg:phone":"+1 403 272 6030",
    "sg:postcode":"T1X 1B1",
    "sg:province":"AB",
    "sg:tags":[
        "camp"
    ],
    "wof:name":"Camp Chestermere",
    "wof:placetype":"venue"
},
  "geometry": {"coordinates":[-113.815994,51.021221],"type":"Point"}
}