{
  "type": "Feature",
  "properties": {
    "addr:full":"St Catharines ON L2N 7H8",
    "addr:postcode":"l2n 7h8",
    "iso:country":"CA",
    "sg:city":"St Catharines",
    "sg:classifiers":[
        {
            "category":"Health Services",
            "subcategory":"Doctor",
            "type":"Services"
        }
    ],
    "sg:phone":"+1 905 646 3814",
    "sg:postcode":"L2N 7H8",
    "sg:province":"ON",
    "sg:tags":[
        "physician",
        "clinic",
        "surgeon"
    ],
    "wof:name":"Medemerg Walk in Clinics",
    "wof:placetype":"venue"
},
  "geometry": {"coordinates":[-79.259803772,43.1955986023],"type":"Point"}
}