{
  "type": "Feature",
  "properties": {
    "addr:full":"6482 County Rd 17 Plantagenet ON K0B 1L0",
    "addr:housenumber":"6482;17",
    "addr:postcode":"k0b 1l0",
    "addr:street":"County Rd",
    "iso:country":"CA",
    "sg:address":"6482 County Rd 17",
    "sg:city":"Plantagenet",
    "sg:classifiers":[
        {
            "category":"Retail",
            "subcategory":"Repair Shop",
            "type":"Services"
        }
    ],
    "sg:phone":"+1 613 673 2058",
    "sg:postcode":"K0B 1L0",
    "sg:province":"ON",
    "sg:tags":[
        "welding"
    ],
    "wof:name":"Gaetan Lamoureux Welding",
    "wof:placetype":"venue"
},
  "geometry": {"coordinates":[-74.99816894529999,45.5352592468],"type":"Point"}
}