{
  "type": "Feature",
  "properties": {
    "addr:full":"8200 Esquesing Line Milton ON L9T 2X9",
    "addr:housenumber":"8200",
    "addr:postcode":"l9t 2x9",
    "addr:street":"Esquesing Line",
    "iso:country":"CA",
    "sg:address":"8200 Esquesing Line",
    "sg:city":"Milton",
    "sg:classifiers":[
        {
            "category":"Autos & Motor Vehicles",
            "subcategory":"Automobile Sales",
            "type":"Retail Goods"
        }
    ],
    "sg:phone":"+1 905 878 0132",
    "sg:postcode":"L9T 2X9",
    "sg:province":"ON",
    "sg:tags":[
        "car",
        "dealer"
    ],
    "wof:name":"Prestige Auto Sales",
    "wof:placetype":"venue"
},
  "geometry": {"coordinates":[-79.8824996948,43.5455703735],"type":"Point"}
}