{
  "type": "Feature",
  "properties": {
    "addr:full":"85 Main St E Grimsby ON L3M 1N6",
    "addr:housenumber":"85",
    "addr:postcode":"l3m 1n6",
    "addr:street":"Main St E",
    "iso:country":"CA",
    "sg:address":"85 Main St E",
    "sg:city":"Grimsby",
    "sg:classifiers":[
        {
            "category":"Health Services",
            "subcategory":"Nursing And Care Facility",
            "type":"Services"
        }
    ],
    "sg:phone":"+1 905 945 7044",
    "sg:postcode":"L3M 1N6",
    "sg:province":"ON",
    "sg:tags":[
        "home",
        "retirement",
        "community"
    ],
    "wof:name":"Maplecrest Village",
    "wof:placetype":"venue"
},
  "geometry": {"coordinates":[-79.55518341059999,43.1908683777],"type":"Point"}
}