{
  "type": "Feature",
  "properties": {
    "iso:country":"CA",
    "sg:address":"117 Lakeport Rd",
    "sg:city":"St Catharines",
    "sg:classifiers":[
        {
            "category":"Home & Garden",
            "subcategory":"Building Materials",
            "type":"Retail Goods"
        }
    ],
    "sg:phone":"+1 905 646 4606",
    "sg:postcode":"L2N 4R2",
    "sg:province":"ON",
    "sg:tags":[
        "paint"
    ],
    "wof:name":"Lakeport Paint & Wallpaper",
    "wof:placetype":"venue"
},
  "geometry": {"coordinates":[-79.2599411011,43.1959266663],"type":"Point"}
}