{
  "type": "Feature",
  "properties": {
    "addr:full":"132 Carroll St New Westminster BC V3L 4E4",
    "addr:housenumber":"132",
    "addr:postcode":"v3l 4e4",
    "addr:street":"Carroll St",
    "iso:country":"CA",
    "sg:address":"132 Carroll St",
    "sg:city":"New Westminster",
    "sg:classifiers":[
        {
            "category":"Shopping",
            "subcategory":"Computers & Home Electronics",
            "type":"Retail Goods"
        }
    ],
    "sg:phone":"+1 604 521 4001",
    "sg:postcode":"V3L 4E4",
    "sg:province":"BC",
    "sg:tags":[
        "publishing"
    ],
    "wof:name":"Windy Dawn Marketing",
    "wof:placetype":"venue"
},
  "geometry": {"coordinates":[-122.900597,49.221245],"type":"Point"}
}