{
  "type": "Feature",
  "properties": {
    "addr:full":"62 Essa Rd Barrie ON L4N 3K6",
    "addr:housenumber":"62",
    "addr:postcode":"l4n 3k6",
    "addr:street":"Essa Rd",
    "iso:country":"CA",
    "sg:address":"62 Essa Rd",
    "sg:city":"Barrie",
    "sg:classifiers":[
        {
            "category":"Food & Beverages",
            "subcategory":"Groceries & Convenience Stores",
            "type":"Retail Goods"
        }
    ],
    "sg:phone":"+1 705 737 2125",
    "sg:postcode":"L4N 3K6",
    "sg:province":"ON",
    "wof:name":"Mac's Convenience Stores Ltd",
    "wof:placetype":"venue"
},
  "geometry": {"coordinates":[-79.691696167,44.3722496033],"type":"Point"}
}