{
  "type": "Feature",
  "properties": {
    "addr:full":"9 Wheatley Rd Maple ON L6A 1V5",
    "addr:housenumber":"9",
    "addr:postcode":"l6a 1v5",
    "addr:street":"Wheatley Rd",
    "iso:country":"CA",
    "sg:address":"9 Wheatley Rd",
    "sg:city":"Maple",
    "sg:classifiers":[
        {
            "category":"Professional",
            "subcategory":"Business Services",
            "type":"Services"
        }
    ],
    "sg:phone":"+1 905 479 0974",
    "sg:postcode":"L6A 1V5",
    "sg:province":"ON",
    "sg:tags":[
        "lecture",
        "bureau",
        "seminar"
    ],
    "wof:name":"Peak Performers Network",
    "wof:placetype":"venue"
},
  "geometry": {"coordinates":[-79.51812700000001,43.842655],"type":"Point"}
}