{
  "type": "Feature",
  "properties": {
    "addr:full":"4651 Vanguard Rd Richmond BC V6X 2P7",
    "addr:housenumber":"4651",
    "addr:postcode":"v6x 2p7",
    "addr:street":"Vanguard Rd",
    "iso:country":"CA",
    "sg:address":"4651 Vanguard Rd",
    "sg:city":"Richmond",
    "sg:classifiers":[
        {
            "category":"Building & Trades",
            "subcategory":"Construction",
            "type":"Services"
        }
    ],
    "sg:phone":"+1 604 278 3445",
    "sg:postcode":"V6X 2P7",
    "sg:province":"BC",
    "sg:tags":[
        "maker",
        "cabinet"
    ],
    "wof:name":"Suncrest Cabinets",
    "wof:placetype":"venue"
},
  "geometry": {"coordinates":[-123.10122699999999,49.17942],"type":"Point"}
}