{
  "type": "Feature",
  "properties": {
    "addr:full":"4104 Tapestry Trail Mississauga ON L4W 4B7",
    "addr:housenumber":"4104",
    "addr:postcode":"l4w 4b7",
    "addr:street":"Tapestry Trail",
    "iso:country":"CA",
    "sg:address":"4104 Tapestry Trail",
    "sg:city":"Mississauga",
    "sg:classifiers":[
        {
            "category":"Building & Trades",
            "subcategory":"Construction",
            "type":"Services"
        }
    ],
    "sg:phone":"+1 905 238 9493",
    "sg:postcode":"L4W 4B7",
    "sg:province":"ON",
    "sg:tags":[
        "carpenter",
        "contractor"
    ],
    "wof:name":"A & L Carpentry Corp",
    "wof:placetype":"venue"
},
  "geometry": {"coordinates":[-79.592567,43.636124],"type":"Point"}
}