{
  "type": "Feature",
  "properties": {
    "addr:full":"Halifax NS B3K 5J7",
    "addr:postcode":"b3k 5j7",
    "iso:country":"CA",
    "sg:city":"Halifax",
    "sg:classifiers":[
        {
            "category":"Organizations",
            "subcategory":"Professional Association",
            "type":"Services"
        }
    ],
    "sg:phone":"+1 902 425 2445",
    "sg:postcode":"B3K 5J7",
    "sg:province":"NS",
    "wof:name":"Atlantic Dairy Council",
    "wof:placetype":"venue"
},
  "geometry": {"coordinates":[-63.5907897949,44.6473655701],"type":"Point"}
}