{
  "type": "Feature",
  "properties": {
    "addr:full":"725 Rosser Ave Brandon MB R7A 0K8",
    "addr:housenumber":"725",
    "addr:postcode":"r7a 0k8",
    "addr:street":"Rosser Ave",
    "iso:country":"CA",
    "sg:address":"725 Rosser Ave",
    "sg:city":"Brandon",
    "sg:classifiers":[
        {
            "category":"Education",
            "subcategory":"School",
            "type":"Public Place"
        }
    ],
    "sg:phone":"+1 204 725 8735",
    "sg:postcode":"R7A 0K8",
    "sg:province":"MB",
    "sg:tags":[
        "educational",
        "program"
    ],
    "wof:name":"Brandon Adult Learning Ctr",
    "wof:placetype":"venue"
},
  "geometry": {"coordinates":[-99.9477767944,49.8486785889],"type":"Point"}
}