{
  "type": "Feature",
  "properties": {
    "iso:country":"CA",
    "sg:address":"1120 Denman St",
    "sg:city":"Vancouver",
    "sg:classifiers":[
        {
            "category":"Restaurant",
            "type":"Food & Drink"
        }
    ],
    "sg:phone":"+1 604 662 8303",
    "sg:postcode":"V6G 2M8",
    "sg:province":"BC",
    "wof:name":"Pho No 1 Vietnamese Restaurant",
    "wof:placetype":"venue"
},
  "geometry": {"coordinates":[-123.140449524,49.2879867554],"type":"Point"}
}