{
  "type": "Feature",
  "properties": {
    "addr:full":"8 Municipal Ave Mount Pearl NL A1N 1M3",
    "addr:housenumber":"8",
    "addr:postcode":"a1n 1m3",
    "addr:street":"Municipal Ave",
    "iso:country":"CA",
    "sg:address":"8 Municipal Ave",
    "sg:city":"Mount Pearl",
    "sg:classifiers":[
        {
            "category":"Building & Trades",
            "subcategory":"Construction",
            "type":"Services"
        }
    ],
    "sg:phone":"+1 709 368 7403",
    "sg:postcode":"A1N 1M3",
    "sg:province":"NL",
    "sg:tags":[
        "carpenter"
    ],
    "wof:name":"G M Contracting",
    "wof:placetype":"venue"
},
  "geometry": {"coordinates":[-52.792706,47.52158],"type":"Point"}
}