{
  "type": "Feature",
  "properties": {
    "addr:full":"Big River NB E2A 6N6",
    "addr:postcode":"e2a 6n6",
    "iso:country":"CA",
    "sg:city":"Big River",
    "sg:classifiers":[
        {
            "category":"Sports & Exercise",
            "subcategory":"Bowling",
            "type":"Entertainment"
        }
    ],
    "sg:phone":"+1 506 546 3312",
    "sg:postcode":"E2A 6N6",
    "sg:province":"NB",
    "sg:tags":[
        "center"
    ],
    "wof:name":"Chaleur Centre Lanes",
    "wof:placetype":"venue"
},
  "geometry": {"coordinates":[-65.66407,47.580002],"type":"Point"}
}