{
  "type": "Feature",
  "properties": {
    "addr:full":"223 Louisa St Kitchener ON N2H 5M6",
    "addr:housenumber":"223",
    "addr:postcode":"n2h 5m6",
    "addr:street":"Louisa St",
    "iso:country":"CA",
    "sg:address":"223 Louisa St",
    "sg:city":"Kitchener",
    "sg:classifiers":[
        {
            "category":"Food & Beverages",
            "subcategory":"Groceries & Convenience Stores",
            "type":"Retail Goods"
        }
    ],
    "sg:phone":"+1 519 578 8690",
    "sg:postcode":"N2H 5M6",
    "sg:province":"ON",
    "wof:name":"Sung Convenience",
    "wof:placetype":"venue"
},
  "geometry": {"coordinates":[-80.4943313599,43.4581413269],"type":"Point"}
}