{
  "type": "Feature",
  "properties": {
    "iso:country":"CA",
    "sg:city":"Loretteville",
    "sg:classifiers":[
        {
            "category":"Professional",
            "subcategory":"Accounting & Tax Preparation",
            "type":"Services"
        }
    ],
    "sg:phone":"+1 418 840 3078",
    "sg:postcode":"G2B 1G5",
    "sg:province":"QC",
    "sg:tags":[
        "accountant",
        "bankruptcy",
        "trustee"
    ],
    "wof:name":"Raymond Chabot Inc",
    "wof:placetype":"venue"
},
  "geometry": {"coordinates":[-71.366142,46.846161],"type":"Point"}
}