{
  "type": "Feature",
  "properties": {
    "addr:full":"1550 Rue Beaubien E Montreal QC H2G 1L2",
    "addr:housenumber":"1550",
    "addr:postcode":"h2g 1l2",
    "addr:street":"Rue Beaubien E",
    "iso:country":"CA",
    "sg:address":"1550 Rue Beaubien E",
    "sg:city":"Montreal",
    "sg:classifiers":[
        {
            "category":"Food & Beverages",
            "subcategory":"Groceries & Convenience Stores",
            "type":"Retail Goods"
        }
    ],
    "sg:phone":"+1 514 272 7552",
    "sg:postcode":"H2G 1L2",
    "sg:province":"QC",
    "wof:name":"Depanneur Chez Nicole",
    "wof:placetype":"venue"
},
  "geometry": {"coordinates":[-73.597588,45.542015],"type":"Point"}
}