{
  "type": "Feature",
  "properties": {
    "iso:country":"CA",
    "sg:address":"91 Bay St",
    "sg:city":"Sturgeon Falls",
    "sg:classifiers":[
        {
            "category":"Building & Trades",
            "subcategory":"Construction",
            "type":"Services"
        }
    ],
    "sg:phone":"+1 705 753 0868",
    "sg:postcode":"P2B 3G6",
    "sg:province":"ON",
    "sg:tags":[
        "general",
        "contractor"
    ],
    "wof:name":"Nipshore Construction",
    "wof:placetype":"venue"
},
  "geometry": {"coordinates":[-79.944443,46.363937],"type":"Point"}
}