{
  "type": "Feature",
  "properties": {
    "addr:full":"Gracefield QC J0X 1W0",
    "addr:postcode":"j0x 1w0",
    "iso:country":"CA",
    "sg:city":"Gracefield",
    "sg:classifiers":[
        {
            "category":"Organizations",
            "subcategory":"Religious Organization",
            "type":"Services"
        }
    ],
    "sg:phone":"+1 819 463 2857",
    "sg:postcode":"J0X 1W0",
    "sg:province":"QC",
    "sg:tags":[
        "church"
    ],
    "wof:name":"Presbytere DE Gracefield",
    "wof:placetype":"venue"
},
  "geometry": {"coordinates":[-76.0447235107,46.0994911194],"type":"Point"}
}