{
  "type": "Feature",
  "properties": {
    "addr:full":"316 7E Av L'Ile-Perrot QC J7V 4T7",
    "addr:housenumber":"316",
    "addr:postcode":"j7v 4t7",
    "addr:street":"7E Av L'Ile-Perrot",
    "iso:country":"CA",
    "sg:address":"316 7E Av",
    "sg:city":"L'Ile-Perrot",
    "sg:classifiers":[
        {
            "category":"Building & Trades",
            "subcategory":"Electrical",
            "type":"Services"
        }
    ],
    "sg:phone":"+1 514 453 1007",
    "sg:postcode":"J7V 4T7",
    "sg:province":"QC",
    "sg:tags":[
        "electric",
        "contractor"
    ],
    "wof:name":"Richard Proulx Electrique",
    "wof:placetype":"venue"
},
  "geometry": {"coordinates":[-73.955368042,45.3937644958],"type":"Point"}
}