{
  "type": "Feature",
  "properties": {
    "iso:country":"CA",
    "sg:address":"1129 Vanier Rd",
    "sg:city":"Sarnia",
    "sg:classifiers":[
        {
            "category":"Home & Garden",
            "subcategory":"Building Materials",
            "type":"Retail Goods"
        }
    ],
    "sg:phone":"+1 519 337 3211",
    "sg:postcode":"N7S 3Y6",
    "sg:province":"ON",
    "sg:tags":[
        "glass",
        "window",
        "plate"
    ],
    "wof:name":"Afg Glass Ctr",
    "wof:placetype":"venue"
},
  "geometry": {"coordinates":[-82.373916626,42.9582138062],"type":"Point"}
}