{
  "type": "Feature",
  "properties": {
    "addr:full":"Slave Lake AB T0G 2A0",
    "addr:postcode":"t0g 2a0",
    "iso:country":"CA",
    "sg:city":"Slave Lake",
    "sg:classifiers":[
        {
            "category":"Retail",
            "subcategory":"Auto Repair",
            "type":"Services"
        }
    ],
    "sg:phone":"+1 780 849 6107",
    "sg:postcode":"T0G 2A0",
    "sg:province":"AB",
    "sg:tags":[
        "body",
        "automobile",
        "painting"
    ],
    "wof:name":"Bryken Auto Body",
    "wof:placetype":"venue"
},
  "geometry": {"coordinates":[-114.780449,55.290092],"type":"Point"}
}