{
  "type": "Feature",
  "properties": {
    "iso:country":"CA",
    "sg:address":"385 Fairway Rd S",
    "sg:city":"Kitchener",
    "sg:classifiers":[
        {
            "category":"Freight",
            "type":"Transportation"
        }
    ],
    "sg:phone":"+1 519 742 1748",
    "sg:postcode":"N2C 2N9",
    "sg:province":"ON",
    "sg:tags":[
        "trucking"
    ],
    "wof:name":"Showcase Carriers Inc",
    "wof:placetype":"venue"
},
  "geometry": {"coordinates":[-80.4421386719,43.4210090637],"type":"Point"}
}