{
  "type": "Feature",
  "properties": {
    "addr:full":"754 Rue Notre-Dame N Thetford Mines QC G6G 2S7",
    "addr:housenumber":"754",
    "addr:postcode":"g6g 2s7",
    "addr:street":"Rue Notre-Dame N",
    "iso:country":"CA",
    "sg:address":"754 Rue Notre-Dame N",
    "sg:city":"Thetford Mines",
    "sg:classifiers":[
        {
            "category":"Personal",
            "subcategory":"Beauty Salon",
            "type":"Services"
        }
    ],
    "sg:phone":"+1 418 334 0777",
    "sg:postcode":"G6G 2S7",
    "sg:province":"QC",
    "wof:name":"Coiffure Histoire DE Filles",
    "wof:placetype":"venue"
},
  "geometry": {"coordinates":[-71.2880783081,46.0994033813],"type":"Point"}
}