{
  "type": "Feature",
  "properties": {
    "iso:country":"CA",
    "sg:address":"209 Warden Wilson Ave",
    "sg:city":"Whitby",
    "sg:classifiers":[
        {
            "category":"Home & Garden",
            "subcategory":"Household Appliances",
            "type":"Retail Goods"
        }
    ],
    "sg:phone":"+1 905 668 5273",
    "sg:postcode":"L1N 5L2",
    "sg:province":"ON",
    "wof:name":"Brown Appliance Repair & Used",
    "wof:placetype":"venue"
},
  "geometry": {"coordinates":[-78.9550933838,43.8793792725],"type":"Point"}
}