{
  "type": "Feature",
  "properties": {
    "iso:country":"CA",
    "sg:city":"Vancouver",
    "sg:classifiers":[
        {
            "category":"Shopping",
            "type":"Retail Goods"
        }
    ],
    "sg:phone":"+1 604 222 1160",
    "sg:postcode":"V6K 1T4",
    "sg:province":"BC",
    "sg:tags":[
        "equipment",
        "beer",
        "supply"
    ],
    "wof:name":"United Canadian Malt",
    "wof:placetype":"venue"
},
  "geometry": {"coordinates":[-123.167037964,49.2674179077],"type":"Point"}
}