{
  "type": "Feature",
  "properties": {
    "iso:country":"CA",
    "sg:address":"532 Morris Ave",
    "sg:city":"Gladstone",
    "sg:classifiers":[
        {
            "category":"Government",
            "subcategory":"Office",
            "type":"Public Place"
        }
    ],
    "sg:phone":"+1 204 385 6630",
    "sg:postcode":"R0J 0T0",
    "sg:province":"MB",
    "wof:name":"Manitoba Livestock Technician",
    "wof:placetype":"venue"
},
  "geometry": {"coordinates":[-98.9507522583,50.2254219055],"type":"Point"}
}