{
  "type": "Feature",
  "properties": {
    "addr:full":"407 Cumberland Ave S Saskatoon SK S7H 2L3",
    "addr:housenumber":"407",
    "addr:postcode":"s7h 2l3",
    "addr:street":"Cumberland Ave S",
    "iso:country":"CA",
    "sg:address":"407 Cumberland Ave S",
    "sg:city":"Saskatoon",
    "sg:classifiers":[
        {
            "category":"Organizations",
            "subcategory":"Professional Association",
            "type":"Services"
        }
    ],
    "sg:phone":"+1 306 934 2402",
    "sg:postcode":"S7H 2L3",
    "sg:province":"SK",
    "wof:name":"Saskatchewan Special Olympics",
    "wof:placetype":"venue"
},
  "geometry": {"coordinates":[-106.634552,52.121643],"type":"Point"}
}