{
  "type": "Feature",
  "properties": {
    "addr:full":"7046 Kelly Rd S Prince George BC V2K 2G9",
    "addr:housenumber":"7046",
    "addr:postcode":"v2k 2g9",
    "addr:street":"Kelly Rd",
    "iso:country":"CA",
    "sg:address":"7046 Kelly Rd S",
    "sg:city":"Prince George",
    "sg:classifiers":[
        {
            "category":"Organizations",
            "subcategory":"Religious Organization",
            "type":"Services"
        }
    ],
    "sg:phone":"+1 250 962 6420",
    "sg:postcode":"V2K 2G9",
    "sg:province":"BC",
    "sg:tags":[
        "church"
    ],
    "wof:name":"Kelly Road Gospel Chapel",
    "wof:placetype":"venue"
},
  "geometry": {"coordinates":[-122.801078796,53.9937171936],"type":"Point"}
}