{
  "type": "Feature",
  "properties": {
    "addr:full":"5307 4 St SE Calgary AB T2H 1K6",
    "addr:housenumber":"5307 4",
    "addr:postcode":"t2h 1k6",
    "addr:street":"St Se",
    "iso:country":"CA",
    "sg:address":"5307 4 St SE",
    "sg:city":"Calgary",
    "sg:phone":"+1 403 253 4888",
    "sg:postcode":"T2H 1K6",
    "sg:province":"AB",
    "sg:tags":[
        "equipment",
        "supply"
    ],
    "wof:name":"Crown Food Equipment Ltd",
    "wof:placetype":"venue"
},
  "geometry": {"coordinates":[-114.05393219,51.0072441101],"type":"Point"}
}