{
  "type": "Feature",
  "properties": {
    "addr:full":"790 Lillooet St W Moose Jaw SK S6H 8B4",
    "addr:housenumber":"790",
    "addr:postcode":"s6h 8b4",
    "addr:street":"Lillooet St W",
    "iso:country":"CA",
    "sg:address":"790 Lillooet St W",
    "sg:city":"Moose Jaw",
    "sg:classifiers":[
        {
            "category":"Retail",
            "subcategory":"Veterinary Services",
            "type":"Services"
        }
    ],
    "sg:phone":"+1 306 694 1639",
    "sg:postcode":"S6H 8B4",
    "sg:province":"SK",
    "sg:tags":[
        "veterinarian"
    ],
    "wof:name":"Bellamy Harrison Animal Hosp",
    "wof:placetype":"venue"
},
  "geometry": {"coordinates":[-105.552498,50.384331],"type":"Point"}
}