{
  "type": "Feature",
  "properties": {
    "addr:full":"10505 107 St NW Edmonton AB T5H 2Y5",
    "addr:housenumber":"10505",
    "addr:postcode":"t5h 2y5",
    "addr:street":"107 St Nw",
    "iso:country":"CA",
    "sg:address":"10505 107 St NW",
    "sg:city":"Edmonton",
    "sg:classifiers":[
        {
            "category":"Manufacturing",
            "subcategory":"Printing",
            "type":"Manufacturing & Wholesale Goods"
        }
    ],
    "sg:phone":"+1 780 420 1267",
    "sg:postcode":"T5H 2Y5",
    "sg:province":"AB",
    "sg:tags":[
        "screen"
    ],
    "wof:name":"Arttec Advertising Inc",
    "wof:placetype":"venue"
},
  "geometry": {"coordinates":[-113.504616,53.548046],"type":"Point"}
}