{
  "type": "Feature",
  "properties": {
    "addr:full":"852 Ch DE LA Paix St-Sauveur QC J0R 1R2",
    "addr:housenumber":"852",
    "addr:postcode":"j0r 1r2",
    "addr:street":"Ch De La Paix St-Sauveur",
    "iso:country":"CA",
    "sg:address":"852 Ch DE LA Paix",
    "sg:city":"St-Sauveur",
    "sg:classifiers":[
        {
            "category":"Professional",
            "subcategory":"Engineering",
            "type":"Services"
        }
    ],
    "sg:phone":"+1 450 227 4771",
    "sg:postcode":"J0R 1R2",
    "sg:province":"QC",
    "sg:tags":[
        "engineer"
    ],
    "wof:name":"Guy Goulet Svc Geologiques Inc",
    "wof:placetype":"venue"
},
  "geometry": {"coordinates":[-74.204239,45.868084],"type":"Point"}
}