{
  "type": "Feature",
  "properties": {
    "iso:country":"CA",
    "sg:city":"Quesnel",
    "sg:classifiers":[
        {
            "category":"Professional",
            "subcategory":"Engineering",
            "type":"Services"
        }
    ],
    "sg:phone":"+1 250 992 9555",
    "sg:postcode":"V2J 2M2",
    "sg:province":"BC",
    "sg:tags":[
        "engineer"
    ],
    "wof:name":"Urban Systems Ltd",
    "wof:placetype":"venue"
},
  "geometry": {"coordinates":[-122.496315002,52.9765014648],"type":"Point"}
}