{
  "type": "Feature",
  "properties": {
    "addr:full":"1229 Advance Rd Burlington ON L7M 1G7",
    "addr:housenumber":"1229",
    "addr:postcode":"l7m 1g7",
    "addr:street":"Advance Rd",
    "iso:country":"CA",
    "sg:address":"1229 Advance Rd",
    "sg:city":"Burlington",
    "sg:classifiers":[
        {
            "category":"Banks & Credit Unions",
            "subcategory":"Investment Brokerage",
            "type":"Services"
        }
    ],
    "sg:phone":"+1 905 319 9393",
    "sg:postcode":"L7M 1G7",
    "sg:province":"ON",
    "sg:tags":[
        "trade",
        "barter",
        "exchange"
    ],
    "wof:name":"Neco Inc",
    "wof:placetype":"venue"
},
  "geometry": {"coordinates":[-79.808098,43.360413],"type":"Point"}
}