{
  "type": "Feature",
  "properties": {
    "iso:country":"CA",
    "sg:address":"1199 Boul Jacques-Cartier",
    "sg:city":"Mont-Joli",
    "sg:classifiers":[
        {
            "category":"Retail",
            "subcategory":"Auto Repair",
            "type":"Services"
        }
    ],
    "sg:phone":"+1 418 775 3308",
    "sg:postcode":"G5H 2S5",
    "sg:province":"QC",
    "sg:tags":[
        "repairing",
        "automobile"
    ],
    "wof:name":"Services Verro Inc",
    "wof:placetype":"venue"
},
  "geometry": {"coordinates":[-68.20036315919999,48.5935440063],"type":"Point"}
}