{
  "type": "Feature",
  "properties": {
    "addr:full":"1 Av Du College Beauport QC G1E 2X3",
    "addr:postcode":"qc g1e 2x3",
    "addr:street":"Av Du College",
    "iso:country":"CA",
    "sg:address":"1 Av Du College",
    "sg:city":"Beauport",
    "sg:classifiers":[
        {
            "category":"Health Services",
            "subcategory":"Nursing And Care Facility",
            "type":"Services"
        }
    ],
    "sg:phone":"+1 418 664 1587",
    "sg:postcode":"G1E 2X3",
    "sg:province":"QC",
    "sg:tags":[
        "home",
        "retirement",
        "community",
        "rest"
    ],
    "wof:name":"Residence Du College",
    "wof:placetype":"venue"
},
  "geometry": {"coordinates":[-71.18891143800001,46.8595504761],"type":"Point"}
}