{
  "type": "Feature",
  "properties": {
    "addr:full":"Agassiz BC V0M 1A0",
    "addr:postcode":"v0m 1a0",
    "iso:country":"CA",
    "sg:city":"Agassiz",
    "sg:classifiers":[
        {
            "category":"Manufacturing",
            "subcategory":"Printing",
            "type":"Manufacturing & Wholesale Goods"
        }
    ],
    "sg:phone":"+1 604 796 4300",
    "sg:postcode":"V0M 1A0",
    "sg:province":"BC",
    "sg:tags":[
        "newspaper"
    ],
    "wof:name":"Agassiz-Harrison Observer",
    "wof:placetype":"venue"
},
  "geometry": {"coordinates":[-121.759659,49.238514],"type":"Point"}
}