{
  "type": "Feature",
  "properties": {
    "addr:full":"2193 St Joseph Blvd Orleans ON K1C 1E7",
    "addr:housenumber":"2193",
    "addr:postcode":"k1c 1e7",
    "addr:street":"St Joseph Blvd",
    "iso:country":"CA",
    "sg:address":"2193 St Joseph Blvd",
    "sg:city":"Orleans",
    "sg:classifiers":[
        {
            "category":"Retail",
            "subcategory":"Auto Repair",
            "type":"Services"
        }
    ],
    "sg:phone":"+1 613 834 8884",
    "sg:postcode":"K1C 1E7",
    "sg:province":"ON",
    "sg:tags":[
        "repairing",
        "automobile"
    ],
    "wof:name":"Orleans Autopro",
    "wof:placetype":"venue"
},
  "geometry": {"coordinates":[-75.53388200000001,45.467167],"type":"Point"}
}