{
  "type": "Feature",
  "properties": {
    "iso:country":"CA",
    "sg:address":"2193 St Joseph Blvd",
    "sg:city":"Orleans",
    "sg:classifiers":[
        {
            "category":"Retail",
            "subcategory":"Auto Repair",
            "type":"Services"
        }
    ],
    "sg:phone":"+1 613 834 8884",
    "sg:postcode":"K1C 1E7",
    "sg:province":"ON",
    "sg:tags":[
        "repairing",
        "automobile"
    ],
    "wof:name":"Orleans Autopro",
    "wof:placetype":"venue"
},
  "geometry": {"coordinates":[-75.533882,45.467167],"type":"Point"}
}