{
  "type": "Feature",
  "properties": {
    "iso:country":"CA",
    "sg:address":"39 Old Bonne Bay Rd",
    "sg:city":"Deer Lake",
    "sg:classifiers":[
        {
            "category":"Professional",
            "subcategory":"Business Services",
            "type":"Services"
        }
    ],
    "sg:phone":"+1 709 635 5941",
    "sg:postcode":"A8A 1X7",
    "sg:province":"NL",
    "sg:tags":[
        "interior",
        "consultant",
        "design",
        "decorator",
        "paint"
    ],
    "wof:name":"Paint Shop",
    "wof:placetype":"venue"
},
  "geometry": {"coordinates":[-57.4122657776,49.1819038391],"type":"Point"}
}