{
  "type": "Feature",
  "properties": {
    "iso:country":"CA",
    "sg:address":"7545 Boul Henri-Bourassa E",
    "sg:city":"Montreal",
    "sg:classifiers":[
        {
            "category":"Restaurant",
            "type":"Food & Drink"
        }
    ],
    "sg:phone":"+1 514 494 1135",
    "sg:postcode":"H1E 1N9",
    "sg:province":"QC",
    "sg:tags":[
        "cafe"
    ],
    "wof:name":"Bistro Xo Plus",
    "wof:placetype":"venue"
},
  "geometry": {"coordinates":[-73.5887756348,45.6206893921],"type":"Point"}
}