{
  "type": "Feature",
  "properties": {
    "iso:country":"CA",
    "sg:city":"Vegreville",
    "sg:classifiers":[
        {
            "category":"Utilities",
            "subcategory":"Natural Gas",
            "type":"Services"
        }
    ],
    "sg:phone":"+1 780 632 2131",
    "sg:postcode":"T9C 1R7",
    "sg:province":"AB",
    "sg:tags":[
        "company"
    ],
    "wof:name":"Atco Gas Ltd",
    "wof:placetype":"venue"
},
  "geometry": {"coordinates":[-112.050064087,53.494594574],"type":"Point"}
}