{
  "type": "Feature",
  "properties": {
    "addr:full":"2951 Dundas St W Toronto ON M6P 1Z2",
    "addr:housenumber":"2951",
    "addr:postcode":"m6p 1z2",
    "addr:street":"Dundas St W",
    "iso:country":"CA",
    "sg:address":"2951 Dundas St W",
    "sg:city":"Toronto",
    "sg:classifiers":[
        {
            "category":"Shopping",
            "subcategory":"Used Merchandise",
            "type":"Retail Goods"
        }
    ],
    "sg:phone":"+1 416 767 5833",
    "sg:postcode":"M6P 1Z2",
    "sg:province":"ON",
    "sg:tags":[
        "pawnbroker"
    ],
    "wof:name":"Dundas West Pawn Brokers Ctr",
    "wof:placetype":"venue"
},
  "geometry": {"coordinates":[-79.46759,43.66531],"type":"Point"}
}