{
  "type": "Feature",
  "properties": {
    "iso:country":"CA",
    "sg:address":"2174 Hwy 203",
    "sg:city":"Kemptville",
    "sg:classifiers":[
        {
            "category":"Food & Beverages",
            "subcategory":"Groceries & Convenience Stores",
            "type":"Retail Goods"
        }
    ],
    "sg:phone":"+1 902 761 2286",
    "sg:postcode":"B0W 1Y0",
    "sg:province":"NS",
    "sg:tags":[
        "grocer"
    ],
    "wof:name":"Kemptville Corner Store",
    "wof:placetype":"venue"
},
  "geometry": {"coordinates":[-65.83605194090001,44.0443115234],"type":"Point"}
}