{
  "type": "Feature",
  "properties": {
    "iso:country":"CA",
    "sg:city":"Oakville",
    "sg:classifiers":[
        {
            "category":"Health Services",
            "subcategory":"Chiropractor",
            "type":"Services"
        }
    ],
    "sg:phone":"+1 905 825 9529",
    "sg:postcode":"L6M 3H4",
    "sg:province":"ON",
    "wof:name":"Oakville Chiropractic Life Ctr",
    "wof:placetype":"venue"
},
  "geometry": {"coordinates":[-79.7462387085,43.4297943115],"type":"Point"}
}