{
  "type": "Feature",
  "properties": {
    "iso:country":"CA",
    "sg:city":"Brampton",
    "sg:classifiers":[
        {
            "category":"Food & Beverages",
            "subcategory":"Groceries & Convenience Stores",
            "type":"Retail Goods"
        }
    ],
    "sg:phone":"+1 905 840 0211",
    "sg:postcode":"L6Z 4R3",
    "sg:province":"ON",
    "sg:tags":[
        "grocer"
    ],
    "wof:name":"7 Star Convenience Store",
    "wof:placetype":"venue"
},
  "geometry": {"coordinates":[-79.813263,43.72628],"type":"Point"}
}