{
  "type": "Feature",
  "properties": {
    "addr:full":"333 Main St Truro NS B2N 5G6",
    "addr:housenumber":"333",
    "addr:postcode":"b2n 5g6",
    "addr:street":"Main St",
    "iso:country":"CA",
    "sg:address":"333 Main St",
    "sg:city":"Truro",
    "sg:classifiers":[
        {
            "category":"Freight",
            "type":"Transportation"
        }
    ],
    "sg:phone":"+1 902 893 3388",
    "sg:postcode":"B2N 5G6",
    "sg:province":"NS",
    "sg:tags":[
        "commercial",
        "storage"
    ],
    "wof:name":"Central Self Storage Ltd",
    "wof:placetype":"venue"
},
  "geometry": {"coordinates":[-63.2890396118,45.3660202026],"type":"Point"}
}