{
  "type": "Feature",
  "properties": {
    "iso:country":"CA",
    "sg:address":"216 Rue Richelieu",
    "sg:city":"Saint-Jean-Sur-Richelieu",
    "sg:classifiers":[
        {
            "category":"Shopping",
            "subcategory":"Used Merchandise",
            "type":"Retail Goods"
        }
    ],
    "sg:phone":"+1 450 347 9000",
    "sg:postcode":"J3B 6X8",
    "sg:province":"QC",
    "sg:tags":[
        "antique"
    ],
    "wof:name":"Antiquites Pednault",
    "wof:placetype":"venue"
},
  "geometry": {"coordinates":[-73.2509231567,45.306552887],"type":"Point"}
}