{
  "type": "Feature",
  "properties": {
    "addr:full":"2010 Industrial Ave Bathurst NB E2A 4W7",
    "addr:housenumber":"2010",
    "addr:postcode":"e2a 4w7",
    "addr:street":"Industrial Ave",
    "iso:country":"CA",
    "sg:address":"2010 Industrial Ave",
    "sg:city":"Bathurst",
    "sg:classifiers":[
        {
            "category":"Manufacturing",
            "subcategory":"Food",
            "type":"Manufacturing & Wholesale Goods"
        }
    ],
    "sg:phone":"+1 506 548 9280",
    "sg:postcode":"E2A 4W7",
    "sg:province":"NB",
    "sg:tags":[
        "chips"
    ],
    "wof:name":"Hostess Frito-Lay",
    "wof:placetype":"venue"
},
  "geometry": {"coordinates":[-65.6231384277,47.5989074707],"type":"Point"}
}