{
  "type": "Feature",
  "properties": {
    "addr:full":"726 Kingston Rd Pickering ON L1V 1A8",
    "addr:housenumber":"726",
    "addr:postcode":"l1v 1a8",
    "addr:street":"Kingston Rd",
    "iso:country":"CA",
    "sg:address":"726 Kingston Rd",
    "sg:city":"Pickering",
    "sg:classifiers":[
        {
            "category":"Travel",
            "subcategory":"Travel Agent",
            "type":"Entertainment"
        }
    ],
    "sg:phone":"+1 905 831 5253",
    "sg:postcode":"L1V 1A8",
    "sg:province":"ON",
    "sg:tags":[
        "agency",
        "bureau"
    ],
    "wof:name":"Caa Travel Inc",
    "wof:placetype":"venue"
},
  "geometry": {"coordinates":[-79.113815,43.820358],"type":"Point"}
}