{
  "type": "Feature",
  "properties": {
    "addr:full":"57 Crane Lake Dr Halifax NS B3S 1B5",
    "addr:housenumber":"57",
    "addr:postcode":"b3s 1b5",
    "addr:street":"Crane Lake Dr",
    "iso:country":"CA",
    "sg:address":"57 Crane Lake Dr",
    "sg:city":"Halifax",
    "sg:classifiers":[
        {
            "category":"Building & Trades",
            "subcategory":"Plumbing",
            "type":"Services"
        }
    ],
    "sg:phone":"+1 902 450 5651",
    "sg:postcode":"B3S 1B5",
    "sg:province":"NS",
    "sg:tags":[
        "conditioning",
        "air",
        "system",
        "contractor"
    ],
    "wof:name":"Halifax Heating & Air Cond Inc",
    "wof:placetype":"venue"
},
  "geometry": {"coordinates":[-63.6678276062,44.6393051147],"type":"Point"}
}