{
  "type": "Feature",
  "properties": {
    "addr:full":"10835 126 St NW Edmonton AB T5M 0P2",
    "addr:housenumber":"10835",
    "addr:postcode":"t5m 0p2",
    "addr:street":"126 St Nw",
    "iso:country":"CA",
    "sg:address":"10835 126 St NW",
    "sg:city":"Edmonton",
    "sg:classifiers":[
        {
            "category":"Professional",
            "subcategory":"Management & Consulting",
            "type":"Services"
        }
    ],
    "sg:phone":"+1 780 413 9440",
    "sg:postcode":"T5M 0P2",
    "sg:province":"AB",
    "sg:tags":[
        "counselor",
        "public",
        "relations"
    ],
    "wof:name":"Fat Cat Media",
    "wof:placetype":"venue"
},
  "geometry": {"coordinates":[-113.53923,53.553082],"type":"Point"}
}