{
  "type": "Feature",
  "properties": {
    "addr:full":"1723 Rue Saint-Hubert Montreal QC H2L 3Z1",
    "addr:housenumber":"1723",
    "addr:postcode":"h2l 3z1",
    "addr:street":"Rue Saint-Hubert",
    "iso:country":"CA",
    "sg:address":"1723 Rue Saint-Hubert",
    "sg:city":"Montreal",
    "sg:classifiers":[
        {
            "category":"Travel",
            "subcategory":"Hotels & Motels",
            "type":"Entertainment"
        }
    ],
    "sg:phone":"+1 514 529 5210",
    "sg:postcode":"H2L 3Z1",
    "sg:province":"QC",
    "wof:name":"Hotel Dynastie",
    "wof:placetype":"venue"
},
  "geometry": {"coordinates":[-73.562523,45.517288],"type":"Point"}
}