{
  "type": "Feature",
  "properties": {
    "addr:full":"2525 Alps Rd Ayr ON N0B 1E0",
    "addr:housenumber":"2525",
    "addr:postcode":"n0b 1e0",
    "addr:street":"Alps Rd",
    "iso:country":"CA",
    "sg:address":"2525 Alps Rd",
    "sg:city":"Ayr",
    "sg:classifiers":[
        {
            "category":"Building & Trades",
            "subcategory":"Construction",
            "type":"Services"
        }
    ],
    "sg:phone":"+1 519 632 9138",
    "sg:postcode":"N0B 1E0",
    "sg:province":"ON",
    "sg:tags":[
        "roofing",
        "siding",
        "contractor"
    ],
    "wof:name":"Alltype Metals",
    "wof:placetype":"venue"
},
  "geometry": {"coordinates":[-80.4499969482,43.2856559753],"type":"Point"}
}