{
  "type": "Feature",
  "properties": {
    "addr:full":"12953 20 Ave Surrey BC V4A 1Z1",
    "addr:housenumber":"12953",
    "addr:postcode":"v4a 1z1",
    "addr:street":"20 Ave",
    "iso:country":"CA",
    "sg:address":"12953 20 Ave",
    "sg:city":"Surrey",
    "sg:classifiers":[
        {
            "category":"Organizations",
            "subcategory":"Religious Organization",
            "type":"Services"
        }
    ],
    "sg:phone":"+1 604 535 8841",
    "sg:postcode":"V4A 1Z1",
    "sg:province":"BC",
    "sg:tags":[
        "church"
    ],
    "wof:name":"St Mark's Anglican Church",
    "wof:placetype":"venue"
},
  "geometry": {"coordinates":[-122.86319732699999,49.0386238098],"type":"Point"}
}