{
  "type": "Feature",
  "properties": {
    "addr:full":"1707 Dugald Rd Winnipeg MB R2J 0H3",
    "addr:housenumber":"1707",
    "addr:postcode":"r2j 0h3",
    "addr:street":"Dugald Rd",
    "iso:country":"CA",
    "sg:address":"1707 Dugald Rd",
    "sg:city":"Winnipeg",
    "sg:classifiers":[
        {
            "category":"Wholesale",
            "subcategory":"Stationery",
            "type":"Manufacturing & Wholesale Goods"
        }
    ],
    "sg:phone":"+1 204 661 8333",
    "sg:postcode":"R2J 0H3",
    "sg:province":"MB",
    "sg:tags":[
        "product",
        "paper"
    ],
    "wof:name":"Mayers Fibre Tube & Core",
    "wof:placetype":"venue"
},
  "geometry": {"coordinates":[-97.039253,49.88615],"type":"Point"}
}