{
  "type": "Feature",
  "properties": {
    "addr:full":"1058 Skiboff Rd South Slocan BC V0G 2G0",
    "addr:housenumber":"1058",
    "addr:postcode":"v0g 2g0",
    "addr:street":"Skiboff Rd",
    "iso:country":"CA",
    "sg:address":"1058 Skiboff Rd",
    "sg:city":"South Slocan",
    "sg:classifiers":[
        {
            "category":"Building & Trades",
            "subcategory":"Construction",
            "type":"Services"
        }
    ],
    "sg:phone":"+1 250 354 9015",
    "sg:postcode":"V0G 2G0",
    "sg:province":"BC",
    "sg:tags":[
        "painter"
    ],
    "wof:name":"A & A Painting",
    "wof:placetype":"venue"
},
  "geometry": {"coordinates":[-117.540466309,49.4424591064],"type":"Point"}
}