{
  "type": "Feature",
  "properties": {
    "addr:full":"19633 98B Ave Langley BC V1M 3G5",
    "addr:housenumber":"19633",
    "addr:postcode":"v1m 3g5",
    "addr:street":"98B Ave",
    "iso:country":"CA",
    "sg:address":"19633 98B Ave",
    "sg:city":"Langley",
    "sg:classifiers":[
        {
            "category":"Manufacturing",
            "subcategory":"Lumber",
            "type":"Manufacturing & Wholesale Goods"
        }
    ],
    "sg:phone":"+1 604 881 0006",
    "sg:postcode":"V1M 3G5",
    "sg:province":"BC",
    "sg:tags":[
        "company",
        "logging"
    ],
    "wof:name":"Stave River Trading Ltd",
    "wof:placetype":"venue"
},
  "geometry": {"coordinates":[-122.65657043500001,49.1041221619],"type":"Point"}
}