{
  "type": "Feature",
  "properties": {
    "addr:full":"30 Bell Lane Brantford ON N3T 5L5",
    "addr:housenumber":"30",
    "addr:postcode":"n3t 5l5",
    "addr:street":"Bell Lane",
    "iso:country":"CA",
    "sg:address":"30 Bell Lane",
    "sg:city":"Brantford",
    "sg:classifiers":[
        {
            "category":"Social Services",
            "subcategory":"Child Care",
            "type":"Services"
        }
    ],
    "sg:phone":"+1 519 759 1701",
    "sg:postcode":"N3T 5L5",
    "sg:province":"ON",
    "wof:name":"West End Y Day Care",
    "wof:placetype":"venue"
},
  "geometry": {"coordinates":[-80.28121899999999,43.126011],"type":"Point"}
}