{
  "type": "Feature",
  "properties": {
    "iso:country":"CA",
    "sg:address":"873 Somerset St W",
    "sg:city":"Ottawa",
    "sg:classifiers":[
        {
            "category":"Restaurant",
            "type":"Food & Drink"
        }
    ],
    "sg:phone":"+1 613 563 0788",
    "sg:postcode":"K1R 6R6",
    "sg:province":"ON",
    "wof:name":"Pho Bac Oriental Cuisine",
    "wof:placetype":"venue"
},
  "geometry": {"coordinates":[-75.7133483887,45.408782959],"type":"Point"}
}