{
  "type": "Feature",
  "properties": {
    "addr:full":"69 Davis Dr Newmarket ON L3Y 2M9",
    "addr:housenumber":"69",
    "addr:postcode":"l3y 2m9",
    "addr:street":"Davis Dr",
    "iso:country":"CA",
    "sg:address":"69 Davis Dr",
    "sg:city":"Newmarket",
    "sg:classifiers":[
        {
            "category":"Retail",
            "subcategory":"Auto Repair",
            "type":"Services"
        }
    ],
    "sg:phone":"+1 905 967 0004",
    "sg:postcode":"L3Y 2M9",
    "sg:province":"ON",
    "sg:tags":[
        "repairing",
        "automobile"
    ],
    "wof:name":"Aamco Transmissions Inc",
    "wof:placetype":"venue"
},
  "geometry": {"coordinates":[-79.477051,44.055698],"type":"Point"}
}