{
  "type": "Feature",
  "properties": {
    "addr:full":"215 First Ave Spruce Grove AB T7X 3X2",
    "addr:housenumber":"215",
    "addr:postcode":"t7x 3x2",
    "addr:street":"First Ave",
    "iso:country":"CA",
    "sg:address":"215 First Ave",
    "sg:city":"Spruce Grove",
    "sg:classifiers":[
        {
            "category":"Restaurant",
            "type":"Food & Drink"
        }
    ],
    "sg:phone":"+1 780 962 1005",
    "sg:postcode":"T7X 3X2",
    "sg:province":"AB",
    "wof:name":"Joey's Only Seafood Restaurant",
    "wof:placetype":"venue"
},
  "geometry": {"coordinates":[-113.90698999999999,53.541187],"type":"Point"}
}