{
  "type": "Feature",
  "properties": {
    "addr:full":"64 Goo-Ow Lane # 2 Cambridge Station NS B0P 1G0",
    "addr:housenumber":"64",
    "addr:postcode":"b0p 1g0",
    "addr:street":"Goo-Ow Lane # 2 Cambridge",
    "iso:country":"CA",
    "sg:address":"64 Goo-Ow Lane # 2",
    "sg:city":"Cambridge Station",
    "sg:classifiers":[
        {
            "category":"Organizations",
            "subcategory":"Professional Association",
            "type":"Services"
        }
    ],
    "sg:phone":"+1 902 538 7149",
    "sg:postcode":"B0P 1G0",
    "sg:province":"NS",
    "sg:tags":[
        "native"
    ],
    "wof:name":"Annapolis Valley Band Council",
    "wof:placetype":"venue"
},
  "geometry": {"coordinates":[-64.635651,45.057102],"type":"Point"}
}