{
  "type": "Feature",
  "properties": {
    "iso:country":"CA",
    "sg:address":"40 Allee Des Brises Du Fleuve",
    "sg:city":"Verdun",
    "sg:classifiers":[
        {
            "category":"Professional",
            "subcategory":"Management & Consulting",
            "type":"Services"
        }
    ],
    "sg:phone":"+1 514 987 9560",
    "sg:postcode":"H4G 3M9",
    "sg:province":"QC",
    "sg:tags":[
        "consultant",
        "instructional"
    ],
    "wof:name":"Formation Humani-Ka",
    "wof:placetype":"venue"
},
  "geometry": {"coordinates":[-73.56163787840001,45.4605140686],"type":"Point"}
}