{
  "type": "Feature",
  "properties": {
    "addr:full":"1656 Dreyber Crt Pickering ON L1V 3H9",
    "addr:housenumber":"1656",
    "addr:postcode":"l1v 3h9",
    "addr:street":"Dreyber Crt",
    "iso:country":"CA",
    "sg:address":"1656 Dreyber Crt",
    "sg:city":"Pickering",
    "sg:classifiers":[
        {
            "category":"Shopping",
            "subcategory":"Computers & Home Electronics",
            "type":"Retail Goods"
        }
    ],
    "sg:phone":"+1 905 427 2712",
    "sg:postcode":"L1V 3H9",
    "sg:province":"ON",
    "sg:tags":[
        "television",
        "radio"
    ],
    "wof:name":"A To Z Television",
    "wof:placetype":"venue"
},
  "geometry": {"coordinates":[-79.0743560791,43.8410453796],"type":"Point"}
}