{
  "type": "Feature",
  "properties": {
    "addr:full":"301 Rue Principale Courcelles QC G0M 1C0",
    "addr:housenumber":"301",
    "addr:postcode":"g0m 1c0",
    "addr:street":"Rue Principale",
    "iso:country":"CA",
    "sg:address":"301 Rue Principale",
    "sg:city":"Courcelles",
    "sg:classifiers":[
        {
            "category":"Wholesale",
            "subcategory":"Machinery & Supplies",
            "type":"Manufacturing & Wholesale Goods"
        }
    ],
    "sg:phone":"+1 418 483 5321",
    "sg:postcode":"G0M 1C0",
    "sg:province":"QC",
    "sg:tags":[
        "farm",
        "equipment",
        "parts",
        "tractor"
    ],
    "wof:name":"Benoit Rouillard Inc",
    "wof:placetype":"venue"
},
  "geometry": {"coordinates":[-70.9826965332,45.870716095],"type":"Point"}
}