{
  "type": "Feature",
  "properties": {
    "addr:full":"1176 Rue Principale Saint-Faustin-Lac-Carre QC J0T 1J1",
    "addr:housenumber":"1176",
    "addr:postcode":"j0t 1j1",
    "addr:street":"Rue Principale",
    "iso:country":"CA",
    "sg:address":"1176 Rue Principale",
    "sg:city":"Saint-Faustin-Lac-Carre",
    "sg:classifiers":[
        {
            "category":"Government",
            "subcategory":"Office",
            "type":"Public Place"
        }
    ],
    "sg:phone":"+1 819 688 2626",
    "sg:postcode":"J0T 1J1",
    "sg:province":"QC",
    "sg:tags":[
        "village"
    ],
    "wof:name":"St-Faustin Centres Comm",
    "wof:placetype":"venue"
},
  "geometry": {"coordinates":[-74.4760131836,46.1227760315],"type":"Point"}
}