{
  "type": "Feature",
  "properties": {
    "addr:full":"Etobicoke ON M9W 6K4",
    "addr:postcode":"m9w 6k4",
    "iso:country":"CA",
    "sg:city":"Etobicoke",
    "sg:classifiers":[
        {
            "category":"Wholesale",
            "subcategory":"Non-durable Goods",
            "type":"Manufacturing & Wholesale Goods"
        }
    ],
    "sg:phone":"+1 416 798 1131",
    "sg:postcode":"M9W 6K4",
    "sg:province":"ON",
    "sg:tags":[
        "advertising"
    ],
    "wof:name":"Union Yes Promotions",
    "wof:placetype":"venue"
},
  "geometry": {"coordinates":[-79.587379,43.677578],"type":"Point"}
}