{
  "type": "Feature",
  "properties": {
    "addr:full":"252 Rue Marquis Saint-Celestin QC J0C 1G0",
    "addr:housenumber":"252",
    "addr:postcode":"j0c 1g0",
    "addr:street":"Rue Marquis Saint-Celestin",
    "iso:country":"CA",
    "sg:address":"252 Rue Marquis",
    "sg:city":"Saint-Celestin",
    "sg:classifiers":[
        {
            "category":"Manufacturing",
            "subcategory":"Metals",
            "type":"Manufacturing & Wholesale Goods"
        }
    ],
    "sg:phone":"+1 819 229 3636",
    "sg:postcode":"J0C 1G0",
    "sg:province":"QC",
    "sg:tags":[
        "steel"
    ],
    "wof:name":"Acier Marquis Inc",
    "wof:placetype":"venue"
},
  "geometry": {"coordinates":[-72.436752,46.216904],"type":"Point"}
}