{
  "type": "Feature",
  "properties": {
    "addr:full":"1800 Beardsmore Rd Peterborough ON K9J 6X6",
    "addr:housenumber":"1800",
    "addr:postcode":"k9j 6x6",
    "addr:street":"Beardsmore Rd",
    "iso:country":"CA",
    "sg:address":"1800 Beardsmore Rd",
    "sg:city":"Peterborough",
    "sg:classifiers":[
        {
            "category":"Shopping",
            "subcategory":"Used Merchandise",
            "type":"Retail Goods"
        }
    ],
    "sg:phone":"+1 705 742 1792",
    "sg:postcode":"K9J 6X6",
    "sg:province":"ON",
    "sg:tags":[
        "building",
        "demolition",
        "contractor"
    ],
    "wof:name":"Cardwell Construction",
    "wof:placetype":"venue"
},
  "geometry": {"coordinates":[-78.32131195069999,44.3007316589],"type":"Point"}
}