{
  "type": "Feature",
  "properties": {
    "addr:full":"5207 Line 88 Gowanstown ON N0G 1Y0",
    "addr:housenumber":"5207",
    "addr:postcode":"n0g 1y0",
    "addr:street":"Line 88",
    "iso:country":"CA",
    "sg:address":"5207 Line 88",
    "sg:city":"Gowanstown",
    "sg:classifiers":[
        {
            "category":"Shopping",
            "subcategory":"Crafts & Fabrics",
            "type":"Retail Goods"
        }
    ],
    "sg:phone":"+1 519 291 1515",
    "sg:postcode":"N0G 1Y0",
    "sg:province":"ON",
    "sg:tags":[
        "shop"
    ],
    "wof:name":"Jantzi's Country Store",
    "wof:placetype":"venue"
},
  "geometry": {"coordinates":[-80.899742,43.76556],"type":"Point"}
}