{
  "type": "Feature",
  "properties": {
    "addr:full":"Ripon QC J0V 1V0",
    "addr:postcode":"j0v 1v0",
    "iso:country":"CA",
    "sg:city":"Ripon",
    "sg:classifiers":[
        {
            "category":"Retail",
            "subcategory":"Auto Repair",
            "type":"Services"
        }
    ],
    "sg:phone":"+1 819 983 6424",
    "sg:postcode":"J0V 1V0",
    "sg:province":"QC",
    "sg:tags":[
        "body",
        "automobile",
        "painting"
    ],
    "wof:name":"Garage Marcel Sabourin",
    "wof:placetype":"venue"
},
  "geometry": {"coordinates":[-75.10011299999999,45.779575],"type":"Point"}
}