{
  "type": "Feature",
  "properties": {
    "addr:full":"32 Ch River Cantley QC J8V 3A1",
    "addr:housenumber":"32",
    "addr:postcode":"j8v 3a1",
    "addr:street":"Ch River",
    "iso:country":"CA",
    "sg:address":"32 Ch River",
    "sg:city":"Cantley",
    "sg:classifiers":[
        {
            "category":"Professional",
            "subcategory":"Business Services",
            "type":"Services"
        }
    ],
    "sg:phone":"+1 819 827 0086",
    "sg:postcode":"J8V 3A1",
    "sg:province":"QC",
    "sg:tags":[
        "convention",
        "meeting",
        "facility"
    ],
    "wof:name":"Econiche House",
    "wof:placetype":"venue"
},
  "geometry": {"coordinates":[-75.78856658940001,45.5493354797],"type":"Point"}
}