{
  "type": "Feature",
  "properties": {
    "addr:full":"12 Chesham Ave London ON N6G 3S9",
    "addr:housenumber":"12",
    "addr:postcode":"n6g 3s9",
    "addr:street":"Chesham Ave",
    "iso:country":"CA",
    "sg:address":"12 Chesham Ave",
    "sg:city":"London",
    "sg:classifiers":[
        {
            "category":"Personal",
            "subcategory":"Beauty Salon",
            "type":"Services"
        }
    ],
    "sg:phone":"+1 519 657 3606",
    "sg:postcode":"N6G 3S9",
    "sg:province":"ON",
    "wof:name":"Gina's Unique Hair Design",
    "wof:placetype":"venue"
},
  "geometry": {"coordinates":[-81.286934,42.997417],"type":"Point"}
}