{
  "type": "Feature",
  "properties": {
    "iso:country":"CA",
    "sg:address":"8555 Boul Levesque E",
    "sg:city":"Laval",
    "sg:classifiers":[
        {
            "category":"Recreation",
            "type":"Entertainment"
        }
    ],
    "sg:phone":"+1 450 665 8984",
    "sg:postcode":"H7A 1W7",
    "sg:province":"QC",
    "sg:tags":[
        "government",
        "hall",
        "auditorium"
    ],
    "wof:name":"Centre St Noel-Chabanel",
    "wof:placetype":"venue"
},
  "geometry": {"coordinates":[-73.5718994141,45.6666755676],"type":"Point"}
}