{
  "type": "Feature",
  "properties": {
    "addr:full":"5778 Boul Thimens Saint-Laurent QC H4R 2K9",
    "addr:housenumber":"5778",
    "addr:postcode":"h4r 2k9",
    "addr:street":"Boul Thimens",
    "iso:country":"CA",
    "sg:address":"5778 Boul Thimens",
    "sg:city":"Saint-Laurent",
    "sg:classifiers":[
        {
            "category":"Wholesale",
            "subcategory":"Medical Equipment & Supplies",
            "type":"Manufacturing & Wholesale Goods"
        }
    ],
    "sg:phone":"+1 514 956 1602",
    "sg:postcode":"H4R 2K9",
    "sg:province":"QC",
    "sg:tags":[
        "hospital"
    ],
    "wof:name":"Iso Tech Design Canada Inc",
    "wof:placetype":"venue"
},
  "geometry": {"coordinates":[-73.7339477539,45.5001449585],"type":"Point"}
}