{
  "type": "Feature",
  "properties": {
    "addr:full":"9300 Trustee Rd Port Hardy BC V0N 2P0",
    "addr:postcode":"9300;v0n 2p0",
    "addr:street":"Trustee Rd",
    "iso:country":"CA",
    "sg:address":"9300 Trustee Rd",
    "sg:city":"Port Hardy",
    "sg:classifiers":[
        {
            "category":"Manufacturing",
            "subcategory":"Food",
            "type":"Manufacturing & Wholesale Goods"
        }
    ],
    "sg:phone":"+1 250 949 8781",
    "sg:postcode":"V0N 2P0",
    "sg:province":"BC",
    "sg:tags":[
        "smoking",
        "fish",
        "curing"
    ],
    "wof:name":"Hardy Buoys Smoked Fish Inc",
    "wof:placetype":"venue"
},
  "geometry": {"coordinates":[-127.507324,50.718056],"type":"Point"}
}