{
  "type": "Feature",
  "properties": {
    "addr:full":"353 Rue DE L'Hotel-DE-Ville Farnham QC J2N 2H1",
    "addr:housenumber":"353",
    "addr:postcode":"j2n 2h1",
    "addr:street":"Rue De L'Hotel-De-Ville",
    "iso:country":"CA",
    "sg:address":"353 Rue DE L'Hotel-DE-Ville",
    "sg:city":"Farnham",
    "sg:classifiers":[
        {
            "category":"Bars & Pubs",
            "type":"Food & Drink"
        }
    ],
    "sg:phone":"+1 450 293 6018",
    "sg:postcode":"J2N 2H1",
    "sg:province":"QC",
    "sg:tags":[
        "lounge",
        "motel",
        "hotel",
        "cocktail"
    ],
    "wof:name":"Hotel Farnham",
    "wof:placetype":"venue"
},
  "geometry": {"coordinates":[-72.978172,45.282303],"type":"Point"}
}