{
  "type": "Feature",
  "properties": {
    "iso:country":"CA",
    "sg:address":"1896 Rue Cunard",
    "sg:city":"Laval",
    "sg:classifiers":[
        {
            "category":"Retail",
            "subcategory":"Auto Repair",
            "type":"Services"
        }
    ],
    "sg:phone":"+1 514 591 6323",
    "sg:postcode":"H7S 2B2",
    "sg:province":"QC",
    "sg:tags":[
        "wrecker"
    ],
    "wof:name":"Remorquages Elegance",
    "wof:placetype":"venue"
},
  "geometry": {"coordinates":[-73.741104126,45.5765762329],"type":"Point"}
}