{
  "type": "Feature",
  "properties": {
    "addr:full":"2931 Rte Marie-Victorin Varennes QC J3X 1P7",
    "addr:housenumber":"2931",
    "addr:postcode":"j3x 1p7",
    "addr:street":"Rte Marie-Victorin",
    "iso:country":"CA",
    "sg:address":"2931 Rte Marie-Victorin",
    "sg:city":"Varennes",
    "sg:classifiers":[
        {
            "category":"Manufacturing",
            "subcategory":"Chemicals & Compounds",
            "type":"Manufacturing & Wholesale Goods"
        }
    ],
    "sg:phone":"+1 450 652 2971",
    "sg:postcode":"J3X 1P7",
    "sg:province":"QC",
    "wof:name":"Petromont & CO Lp",
    "wof:placetype":"venue"
},
  "geometry": {"coordinates":[-73.424179,45.700161],"type":"Point"}
}