{
  "type": "Feature",
  "properties": {
    "addr:full":"103 Main St N Ituna SK S0A 1N0",
    "addr:housenumber":"103",
    "addr:postcode":"s0a 1n0",
    "addr:street":"Main St N",
    "iso:country":"CA",
    "sg:address":"103 Main St N",
    "sg:city":"Ituna",
    "sg:classifiers":[
        {
            "category":"Retail",
            "subcategory":"Funeral Services",
            "type":"Services"
        }
    ],
    "sg:phone":"+1 306 795 2481",
    "sg:postcode":"S0A 1N0",
    "sg:province":"SK",
    "sg:tags":[
        "director"
    ],
    "wof:name":"Bailey's Funeral Home",
    "wof:placetype":"venue"
},
  "geometry": {"coordinates":[-103.49578099999999,51.171314],"type":"Point"}
}