{
  "type": "Feature",
  "properties": {
    "addr:full":"2913 Poole Crt Val Caron ON P3N 1B2",
    "addr:housenumber":"2913",
    "addr:postcode":"p3n 1b2",
    "addr:street":"Poole Crt",
    "iso:country":"CA",
    "sg:address":"2913 Poole Crt",
    "sg:city":"Val Caron",
    "sg:classifiers":[
        {
            "category":"Manufacturing",
            "subcategory":"Metals",
            "type":"Manufacturing & Wholesale Goods"
        }
    ],
    "sg:phone":"+1 705 897 2535",
    "sg:postcode":"P3N 1B2",
    "sg:province":"ON",
    "sg:tags":[
        "ventilating",
        "equipment"
    ],
    "wof:name":"Steelnorth Fabricators Ltd",
    "wof:placetype":"venue"
},
  "geometry": {"coordinates":[-81.031105,46.607944],"type":"Point"}
}