{
  "type": "Feature",
  "properties": {
    "addr:full":"3455 Harvester Rd # 23 Burlington ON L7N 3P2",
    "addr:housenumber":"3455",
    "addr:postcode":"l7n 3p2",
    "addr:street":"Harvester Rd # 23",
    "iso:country":"CA",
    "sg:address":"3455 Harvester Rd # 23",
    "sg:city":"Burlington",
    "sg:classifiers":[
        {
            "category":"Wholesale",
            "subcategory":"Metals & Minerals",
            "type":"Manufacturing & Wholesale Goods"
        }
    ],
    "sg:phone":"+1 905 336 9466",
    "sg:postcode":"L7N 3P2",
    "sg:province":"ON",
    "sg:tags":[
        "steel",
        "warehouse"
    ],
    "wof:name":"New Century Steel Inc",
    "wof:placetype":"venue"
},
  "geometry": {"coordinates":[-79.78672,43.361034],"type":"Point"}
}