{
  "type": "Feature",
  "properties": {
    "addr:full":"PO Box 180 Vauxhall AB T0K 2K0",
    "addr:housenumber":"po;180",
    "addr:postcode":"t0k 2k0",
    "addr:street":"Box",
    "iso:country":"CA",
    "sg:address":"PO Box 180",
    "sg:city":"Vauxhall",
    "sg:classifiers":[
        {
            "category":"Farming",
            "subcategory":"Farm",
            "type":"Manufacturing & Wholesale Goods"
        }
    ],
    "sg:phone":"+1 403 654 2626",
    "sg:postcode":"T0K 2K0",
    "sg:province":"AB",
    "wof:name":"S-Scan Farms Ltd",
    "wof:placetype":"venue"
},
  "geometry": {"coordinates":[-112.09733581499999,50.0708847046],"type":"Point"}
}