{
  "type": "Feature",
  "properties": {
    "addr:full":"2636 Rang Saint-Jacques Saint-Jacques QC J0K 2R0",
    "addr:housenumber":"2636",
    "addr:postcode":"j0k 2r0",
    "addr:street":"Rang Saint-Jacques",
    "iso:country":"CA",
    "sg:address":"2636 Rang Saint-Jacques",
    "sg:city":"Saint-Jacques",
    "sg:classifiers":[
        {
            "category":"Building & Trades",
            "subcategory":"Construction",
            "type":"Services"
        }
    ],
    "sg:phone":"+1 450 839 2383",
    "sg:postcode":"J0K 2R0",
    "sg:province":"QC",
    "sg:tags":[
        "excavating",
        "contractor"
    ],
    "wof:name":"Marion Pierre",
    "wof:placetype":"venue"
},
  "geometry": {"coordinates":[-73.606308,45.973072],"type":"Point"}
}