{
  "type": "Feature",
  "properties": {
    "addr:full":"815 College St Toronto ON M6G 1C9",
    "addr:housenumber":"815",
    "addr:postcode":"m6g 1c9",
    "addr:street":"College St",
    "iso:country":"CA",
    "sg:address":"815 College St",
    "sg:city":"Toronto",
    "sg:classifiers":[
        {
            "category":"Health Services",
            "subcategory":"Medical Lab",
            "type":"Services"
        }
    ],
    "sg:phone":"+1 416 537 9500",
    "sg:postcode":"M6G 1C9",
    "sg:province":"ON",
    "sg:tags":[
        "laboratory"
    ],
    "wof:name":"Labcare Inc",
    "wof:placetype":"venue"
},
  "geometry": {"coordinates":[-79.42190600000001,43.654415],"type":"Point"}
}