{
  "type": "Feature",
  "properties": {
    "iso:country":"CA",
    "sg:address":"1428 Roxbury Rd",
    "sg:city":"North Vancouver",
    "sg:classifiers":[
        {
            "category":"Shopping",
            "type":"Retail Goods"
        }
    ],
    "sg:phone":"+1 604 929 4440",
    "sg:postcode":"V7G 1X7",
    "sg:province":"BC",
    "sg:tags":[
        "material",
        "artist",
        "supply"
    ],
    "wof:name":"Opulence Silks & Dyes Ltd",
    "wof:placetype":"venue"
},
  "geometry": {"coordinates":[-122.940796,49.319618],"type":"Point"}
}