{
  "type": "Feature",
  "properties": {
    "iso:country":"CA",
    "sg:city":"Barrie",
    "sg:classifiers":[
        {
            "category":"Shopping",
            "subcategory":"Books",
            "type":"Retail Goods"
        }
    ],
    "sg:phone":"+1 705 737 5671",
    "sg:postcode":"L4N 1A5",
    "sg:province":"ON",
    "sg:tags":[
        "dealer"
    ],
    "wof:name":"Bell Book & Candle",
    "wof:placetype":"venue"
},
  "geometry": {"coordinates":[-79.69281,44.387943],"type":"Point"}
}