{
  "type": "Feature",
  "properties": {
    "addr:full":"645 Caleb Pike Rd Victoria BC V9B 6G8",
    "addr:housenumber":"645",
    "addr:postcode":"bc v9b 6g8",
    "addr:street":"Caleb Pike Rd",
    "iso:country":"CA",
    "sg:address":"645 Caleb Pike Rd",
    "sg:city":"Victoria",
    "sg:classifiers":[
        {
            "category":"Retail",
            "subcategory":"Auto Repair",
            "type":"Services"
        }
    ],
    "sg:phone":"+1 250 474 7724",
    "sg:postcode":"V9B 6G8",
    "sg:province":"BC",
    "sg:tags":[
        "body",
        "automobile",
        "painting"
    ],
    "wof:name":"G & L Collision Ctr Ltd",
    "wof:placetype":"venue"
},
  "geometry": {"coordinates":[-123.364517212,48.428314209],"type":"Point"}
}