{
  "type": "Feature",
  "properties": {
    "iso:country":"CA",
    "sg:address":"340 Montee DE LA Riviere-Du-Su",
    "sg:city":"Montmagny",
    "sg:classifiers":[
        {
            "category":"Travel",
            "subcategory":"Campground",
            "type":"Entertainment"
        }
    ],
    "sg:phone":"+1 418 248 2625",
    "sg:postcode":"G5V 3R9",
    "sg:province":"QC",
    "sg:tags":[
        "camp",
        "fishing"
    ],
    "wof:name":"Claude Coulombe Pourvoirie",
    "wof:placetype":"venue"
},
  "geometry": {"coordinates":[-70.58950042719999,46.9400367737],"type":"Point"}
}