{
  "type": "Feature",
  "properties": {
    "iso:country":"CA",
    "sg:address":"71 Mccaul St",
    "sg:city":"Toronto",
    "sg:classifiers":[
        {
            "category":"Shopping",
            "subcategory":"Clothing, Apparel, & Fashions",
            "type":"Retail Goods"
        }
    ],
    "sg:phone":"+1 416 977 2097",
    "sg:postcode":"M5T 2X1",
    "sg:province":"ON",
    "sg:tags":[
        "furnishing"
    ],
    "wof:name":"Knicker Boxer's",
    "wof:placetype":"venue"
},
  "geometry": {"coordinates":[-79.39055633540001,43.6526603699],"type":"Point"}
}