{
  "type": "Feature",
  "properties": {
    "addr:full":"Havelock ON K0L 1Z0",
    "addr:postcode":"k0l 1z0",
    "iso:country":"CA",
    "sg:city":"Havelock",
    "sg:classifiers":[
        {
            "category":"Autos & Motor Vehicles",
            "subcategory":"Recreational Vehicle Sales",
            "type":"Retail Goods"
        }
    ],
    "sg:phone":"+1 705 778 3371",
    "sg:postcode":"K0L 1Z0",
    "sg:province":"ON",
    "sg:tags":[
        "parts",
        "trailer"
    ],
    "wof:name":"Havelock Hauler Trailer Parts",
    "wof:placetype":"venue"
},
  "geometry": {"coordinates":[-77.886383,44.433201],"type":"Point"}
}