{
  "type": "Feature",
  "properties": {
    "addr:full":"Hwy 31 Darlingford MB R0G 0L0",
    "addr:postcode":"r0g 0l0",
    "addr:street":"Hwy 31 Darlingford",
    "iso:country":"CA",
    "sg:address":"Hwy 31",
    "sg:city":"Darlingford",
    "sg:classifiers":[
        {
            "category":"Government",
            "subcategory":"Office",
            "type":"Public Place"
        }
    ],
    "sg:phone":"+1 204 246 2201",
    "sg:postcode":"R0G 0L0",
    "sg:province":"MB",
    "wof:name":"Canada Customs",
    "wof:placetype":"venue"
},
  "geometry": {"coordinates":[-98.3776626587,49.2043609619],"type":"Point"}
}