{
  "type": "Feature",
  "properties": {
    "addr:full":"65 Maitland Terr Strathroy ON N7G 1L2",
    "addr:housenumber":"65",
    "addr:postcode":"n7g 1l2",
    "addr:street":"Maitland Terr",
    "iso:country":"CA",
    "sg:address":"65 Maitland Terr",
    "sg:city":"Strathroy",
    "sg:classifiers":[
        {
            "category":"Food & Beverages",
            "subcategory":"Bakery",
            "type":"Retail Goods"
        }
    ],
    "sg:phone":"+1 519 245 6200",
    "sg:postcode":"N7G 1L2",
    "sg:province":"ON",
    "sg:tags":[
        "baker"
    ],
    "wof:name":"Jerry's Home Bakery & Minimart",
    "wof:placetype":"venue"
},
  "geometry": {"coordinates":[-81.622925,42.953918],"type":"Point"}
}