{
  "type": "Feature",
  "properties": {
    "addr:full":"26 County Rd 3 W Brucefield ON N0M 1J0",
    "addr:housenumber":"26",
    "addr:postcode":"n0m 1j0",
    "addr:street":"County Rd 3 W Brucefield",
    "iso:country":"CA",
    "sg:address":"26 County Rd 3 W",
    "sg:city":"Brucefield",
    "sg:classifiers":[
        {
            "category":"Shopping",
            "subcategory":"Used Merchandise",
            "type":"Retail Goods"
        }
    ],
    "sg:phone":"+1 519 233 3277",
    "sg:postcode":"N0M 1J0",
    "sg:province":"ON",
    "sg:tags":[
        "furniture"
    ],
    "wof:name":"Trading Post",
    "wof:placetype":"venue"
},
  "geometry": {"coordinates":[-81.51799800000001,43.525501],"type":"Point"}
}