{
  "type": "Feature",
  "properties": {
    "iso:country":"CA",
    "sg:address":"1054 2E Rue",
    "sg:city":"Disraeli",
    "sg:classifiers":[
        {
            "category":"Building & Trades",
            "subcategory":"Electrical",
            "type":"Services"
        }
    ],
    "sg:phone":"+1 418 449 3421",
    "sg:postcode":"G0N 1E0",
    "sg:province":"QC",
    "sg:tags":[
        "electric",
        "contractor"
    ],
    "wof:name":"Entreprises Gaetan Faucher",
    "wof:placetype":"venue"
},
  "geometry": {"coordinates":[-71.3576049805,45.91173172],"type":"Point"}
}