{
  "type": "Feature",
  "properties": {
    "addr:full":"9 Av Saint-Charles Vaudreuil-Dorion QC J7V 2K3",
    "addr:postcode":"j7v 2k3",
    "addr:street":"Av Saint-Charles",
    "iso:country":"CA",
    "sg:address":"9 Av Saint-Charles",
    "sg:city":"Vaudreuil-Dorion",
    "sg:classifiers":[
        {
            "category":"Restaurant",
            "type":"Food & Drink"
        }
    ],
    "sg:phone":"+1 450 455 9342",
    "sg:postcode":"J7V 2K3",
    "sg:province":"QC",
    "wof:name":"Restaurant Le Verlaine",
    "wof:placetype":"venue"
},
  "geometry": {"coordinates":[-74.00933074949999,45.3839530945],"type":"Point"}
}