{
  "type": "Feature",
  "properties": {
    "addr:full":"Richmond BC V7A 4E8",
    "addr:postcode":"v7a 4e8",
    "iso:country":"CA",
    "sg:city":"Richmond",
    "sg:classifiers":[
        {
            "category":"Wholesale",
            "subcategory":"Durable Goods & Equipment",
            "type":"Manufacturing & Wholesale Goods"
        }
    ],
    "sg:phone":"+1 604 274 1514",
    "sg:postcode":"V7A 4E8",
    "sg:province":"BC",
    "sg:tags":[
        "representative",
        "manufacturer"
    ],
    "wof:name":"Hamilton Daro Agencies Ltd",
    "wof:placetype":"venue"
},
  "geometry": {"coordinates":[-123.09215500000001,49.127449],"type":"Point"}
}