{
  "type": "Feature",
  "properties": {
    "addr:full":"3780 Island Hwy #2 Campbell River BC V9W 2J1",
    "addr:housenumber":"3780",
    "addr:postcode":"v9w 2j1",
    "addr:street":"Island Hwy # 2",
    "iso:country":"CA",
    "sg:address":"3780 Island Hwy #2",
    "sg:city":"Campbell River",
    "sg:classifiers":[
        {
            "category":"Building & Trades",
            "subcategory":"Electrical",
            "type":"Services"
        }
    ],
    "sg:phone":"+1 250 287 9467",
    "sg:postcode":"V9W 2J1",
    "sg:province":"BC",
    "sg:tags":[
        "electric",
        "contractor"
    ],
    "wof:name":"Beaton Electric",
    "wof:placetype":"venue"
},
  "geometry": {"coordinates":[-125.27312469500001,50.0571212769],"type":"Point"}
}