{
  "type": "Feature",
  "properties": {
    "addr:full":"488 Rte 167 S Chibougamau QC G8P 2K6",
    "addr:housenumber":"488",
    "addr:postcode":"g8p 2k6",
    "addr:street":"Rte 167 S",
    "iso:country":"CA",
    "sg:address":"488 Rte 167 S",
    "sg:city":"Chibougamau",
    "sg:classifiers":[
        {
            "category":"Wholesale",
            "subcategory":"Construction Materials",
            "type":"Manufacturing & Wholesale Goods"
        }
    ],
    "sg:phone":"+1 418 748 2787",
    "sg:postcode":"G8P 2K6",
    "sg:province":"QC",
    "sg:tags":[
        "concrete",
        "sand",
        "gravel"
    ],
    "wof:name":"Beton Tremblay Inc",
    "wof:placetype":"venue"
},
  "geometry": {"coordinates":[-74.407364,49.749958],"type":"Point"}
}