{
  "type": "Feature",
  "properties": {
    "addr:full":"2025 Caroline St Burlington ON L7R 1L1",
    "addr:housenumber":"2025",
    "addr:postcode":"l7r 1l1",
    "addr:street":"Caroline St",
    "iso:country":"CA",
    "sg:address":"2025 Caroline St",
    "sg:city":"Burlington",
    "sg:classifiers":[
        {
            "category":"Social Services",
            "type":"Services"
        }
    ],
    "sg:phone":"+1 905 681 6700",
    "sg:postcode":"L7R 1L1",
    "sg:province":"ON",
    "sg:tags":[
        "counselor",
        "marriage",
        "family"
    ],
    "wof:name":"Bekeris, Diane",
    "wof:placetype":"venue"
},
  "geometry": {"coordinates":[-79.79992675779999,43.3283653259],"type":"Point"}
}