{
  "type": "Feature",
  "properties": {
    "addr:full":"320 Olmstead St Vanier ON K1L 7K3",
    "addr:housenumber":"320",
    "addr:postcode":"k1l 7k3",
    "addr:street":"Olmstead St",
    "iso:country":"CA",
    "sg:address":"320 Olmstead St",
    "sg:city":"Vanier",
    "sg:classifiers":[
        {
            "category":"Organizations",
            "subcategory":"Religious Organization",
            "type":"Services"
        }
    ],
    "sg:phone":"+1 613 746 8503",
    "sg:postcode":"K1L 7K3",
    "sg:province":"ON",
    "sg:tags":[
        "church"
    ],
    "wof:name":"Our Lady of Assumption Church",
    "wof:placetype":"venue"
},
  "geometry": {"coordinates":[-75.66139221189999,45.4339866638],"type":"Point"}
}