{
  "type": "Feature",
  "properties": {
    "addr:full":"800 Ryan Rd Courtenay BC V9N 7T1",
    "addr:housenumber":"800",
    "addr:postcode":"v9n 7t1",
    "addr:street":"Ryan Rd",
    "iso:country":"CA",
    "sg:address":"800 Ryan Rd",
    "sg:city":"Courtenay",
    "sg:classifiers":[
        {
            "category":"Organizations",
            "subcategory":"Professional Association",
            "type":"Services"
        }
    ],
    "sg:phone":"+1 ",
    "sg:postcode":"V9N 7T1",
    "sg:province":"BC",
    "wof:name":"Comox Valley Crime Stoppers",
    "wof:placetype":"venue"
},
  "geometry": {"coordinates":[-124.987327576,49.6990394592],"type":"Point"}
}