{
  "type": "Feature",
  "properties": {
    "addr:full":"Rocky Mountain House AB T4T 1B6",
    "addr:postcode":"t4t 1b6",
    "iso:country":"CA",
    "sg:city":"Rocky Mountain House",
    "sg:classifiers":[
        {
            "category":"Restaurant",
            "type":"Food & Drink"
        }
    ],
    "sg:phone":"+1 403 845 3120",
    "sg:postcode":"T4T 1B6",
    "sg:province":"AB",
    "wof:name":"Pearl Restaurant",
    "wof:placetype":"venue"
},
  "geometry": {"coordinates":[-114.919556,52.374798],"type":"Point"}
}