{
  "type": "Feature",
  "properties": {
    "addr:full":"323 6th St E North Vancouver BC V7L 1P7",
    "addr:housenumber":"323",
    "addr:postcode":"v7l 1p7",
    "addr:street":"6Th St E",
    "iso:country":"CA",
    "sg:address":"323 6th St E",
    "sg:city":"North Vancouver",
    "sg:classifiers":[
        {
            "category":"Professional",
            "subcategory":"Business Services",
            "type":"Services"
        }
    ],
    "sg:phone":"+1 604 983 9799",
    "sg:postcode":"V7L 1P7",
    "sg:province":"BC",
    "sg:tags":[
        "event"
    ],
    "wof:name":"Kidsworld Entertainment Ltd",
    "wof:placetype":"venue"
},
  "geometry": {"coordinates":[-123.067795,49.312881],"type":"Point"}
}