{
  "type": "Feature",
  "properties": {
    "addr:full":"3440 Ch Des Quatre-Bourgeois Sainte-Foy QC G1W 4T3",
    "addr:postcode":"3440;g1w 4t3",
    "addr:street":"Ch Des Quatre-Bourgeois",
    "iso:country":"CA",
    "sg:address":"3440 Ch Des Quatre-Bourgeois",
    "sg:city":"Sainte-Foy",
    "sg:classifiers":[
        {
            "category":"Food & Beverages",
            "subcategory":"Groceries & Convenience Stores",
            "type":"Retail Goods"
        }
    ],
    "sg:phone":"+1 418 653 6241",
    "sg:postcode":"G1W 4T3",
    "sg:province":"QC",
    "sg:tags":[
        "grocer"
    ],
    "wof:name":"Provigo",
    "wof:placetype":"venue"
},
  "geometry": {"coordinates":[-71.317436,46.762863],"type":"Point"}
}