{
  "type": "Feature",
  "properties": {
    "iso:country":"CA",
    "sg:address":"2037 Av Francis-Hughes",
    "sg:city":"Laval",
    "sg:phone":"+1 450 669 3002",
    "sg:postcode":"H7S 2G2",
    "sg:province":"QC",
    "sg:tags":[
        "fixture",
        "store"
    ],
    "wof:name":"Ebenisterie St Patrick",
    "wof:placetype":"venue"
},
  "geometry": {"coordinates":[-73.722588,45.580173],"type":"Point"}
}