{
  "type": "Feature",
  "properties": {
    "addr:full":"2037 Av Francis-Hughes Laval QC H7S 2G2",
    "addr:housenumber":"2037",
    "addr:postcode":"h7s 2g2",
    "addr:street":"Av Francis-Hughes",
    "iso:country":"CA",
    "sg:address":"2037 Av Francis-Hughes",
    "sg:city":"Laval",
    "sg:phone":"+1 450 669 3002",
    "sg:postcode":"H7S 2G2",
    "sg:province":"QC",
    "sg:tags":[
        "fixture",
        "store"
    ],
    "wof:name":"Ebenisterie St Patrick",
    "wof:placetype":"venue"
},
  "geometry": {"coordinates":[-73.722588,45.580173],"type":"Point"}
}