{
  "type": "Feature",
  "properties": {
    "addr:full":"10 Galbraith Pl Saint John NB E2M 7L1",
    "addr:housenumber":"10",
    "addr:postcode":"e2m 7l1",
    "addr:street":"Galbraith Pl",
    "iso:country":"CA",
    "sg:address":"10 Galbraith Pl",
    "sg:city":"Saint John",
    "sg:classifiers":[
        {
            "category":"Manufacturing",
            "subcategory":"Building Materials",
            "type":"Manufacturing & Wholesale Goods"
        }
    ],
    "sg:phone":"+1 506 634 7474",
    "sg:postcode":"E2M 7L1",
    "sg:province":"NB",
    "sg:tags":[
        "truss"
    ],
    "wof:name":"Shamrock Truss & Components",
    "wof:placetype":"venue"
},
  "geometry": {"coordinates":[-66.169067,45.21891],"type":"Point"}
}