{
  "type": "Feature",
  "properties": {
    "addr:full":"Edmonton AB T5N 2B1",
    "addr:postcode":"t5n 2b1",
    "iso:country":"CA",
    "sg:city":"Edmonton",
    "sg:classifiers":[
        {
            "category":"Travel",
            "subcategory":"Travel Agent",
            "type":"Entertainment"
        }
    ],
    "sg:phone":"+1 780 455 7447",
    "sg:postcode":"T5N 2B1",
    "sg:province":"AB",
    "sg:tags":[
        "cruise"
    ],
    "wof:name":"Cruise Vacations Inc",
    "wof:placetype":"venue"
},
  "geometry": {"coordinates":[-113.553123,53.545773],"type":"Point"}
}