{
  "type": "Feature",
  "properties": {
    "addr:full":"3402 8th St E Saskatoon SK S7H 4Z8",
    "addr:housenumber":"3402",
    "addr:postcode":"s7h 4z8",
    "addr:street":"8Th St E",
    "iso:country":"CA",
    "sg:address":"3402 8th St E",
    "sg:city":"Saskatoon",
    "sg:classifiers":[
        {
            "category":"Autos & Motor Vehicles",
            "subcategory":"Fuel & Gas Station",
            "type":"Retail Goods"
        }
    ],
    "sg:phone":"+1 306 373 5772",
    "sg:postcode":"S7H 4Z8",
    "sg:province":"SK",
    "sg:tags":[
        "oil"
    ],
    "wof:name":"Wildwood Esso",
    "wof:placetype":"venue"
},
  "geometry": {"coordinates":[-106.59841900000001,52.114487],"type":"Point"}
}