{
  "type": "Feature",
  "properties": {
    "addr:full":"1349 Burnhamthorpe Rd E Mississauga ON L4Y 3V8",
    "addr:housenumber":"1349",
    "addr:postcode":"l4y 3v8",
    "addr:street":"Burnhamthorpe Rd E",
    "iso:country":"CA",
    "sg:address":"1349 Burnhamthorpe Rd E",
    "sg:city":"Mississauga",
    "sg:classifiers":[
        {
            "category":"Autos & Motor Vehicles",
            "subcategory":"Fuel & Gas Station",
            "type":"Retail Goods"
        }
    ],
    "sg:phone":"+1 905 238 0070",
    "sg:postcode":"L4Y 3V8",
    "sg:province":"ON",
    "sg:tags":[
        "oil"
    ],
    "wof:name":"Shell Canada Products Ltd",
    "wof:placetype":"venue"
},
  "geometry": {"coordinates":[-79.603477478,43.6218948364],"type":"Point"}
}