{
  "type": "Feature",
  "properties": {
    "addr:full":"Melfort SK S0E 1A0",
    "addr:postcode":"s0e 1a0",
    "addr:street":"Melfort",
    "iso:country":"CA",
    "sg:city":"Melfort",
    "sg:classifiers":[
        {
            "category":"Home & Garden",
            "subcategory":"Building Materials",
            "type":"Retail Goods"
        }
    ],
    "sg:phone":"+1 306 752 4219",
    "sg:postcode":"S0E 1A0",
    "sg:province":"SK",
    "sg:tags":[
        "roofing"
    ],
    "wof:name":"Mel-View Metal Inc",
    "wof:placetype":"venue"
},
  "geometry": {"coordinates":[-104.59176600000001,52.841789],"type":"Point"}
}