{
  "type": "Feature",
  "properties": {
    "addr:full":"724 Lakeshore Rd E Mississauga ON L5G 1J6",
    "addr:housenumber":"724",
    "addr:postcode":"l5g 1j6",
    "addr:street":"Lakeshore Rd E",
    "iso:country":"CA",
    "sg:address":"724 Lakeshore Rd E",
    "sg:city":"Mississauga",
    "sg:classifiers":[
        {
            "category":"Food & Beverages",
            "subcategory":"Groceries & Convenience Stores",
            "type":"Retail Goods"
        }
    ],
    "sg:phone":"+1 905 274 0992",
    "sg:postcode":"L5G 1J6",
    "sg:province":"ON",
    "sg:tags":[
        "grocer"
    ],
    "wof:name":"Jack's Milk",
    "wof:placetype":"venue"
},
  "geometry": {"coordinates":[-79.5655136108,43.5703201294],"type":"Point"}
}