{
  "type": "Feature",
  "properties": {
    "addr:full":"10705 101 St NW Edmonton AB T5H 2S4",
    "addr:housenumber":"10705",
    "addr:postcode":"t5h 2s4",
    "addr:street":"101 St Nw",
    "iso:country":"CA",
    "sg:address":"10705 101 St NW",
    "sg:city":"Edmonton",
    "sg:classifiers":[
        {
            "category":"Home & Garden",
            "subcategory":"Furniture",
            "type":"Retail Goods"
        }
    ],
    "sg:phone":"+1 780 497 4900",
    "sg:postcode":"T5H 2S4",
    "sg:province":"AB",
    "wof:name":"Brick",
    "wof:placetype":"venue"
},
  "geometry": {"coordinates":[-113.493606567,53.5510292053],"type":"Point"}
}