{
  "type": "Feature",
  "properties": {
    "iso:country":"CA",
    "sg:address":"1683 Dundas St",
    "sg:city":"London",
    "sg:classifiers":[
        {
            "category":"Restaurant",
            "type":"Food & Drink"
        }
    ],
    "sg:phone":"+1 519 451 0464",
    "sg:postcode":"N5W 3C8",
    "sg:province":"ON",
    "wof:name":"Kfc",
    "wof:placetype":"venue"
},
  "geometry": {"coordinates":[-81.1877746582,43.0012893677],"type":"Point"}
}