{
  "type": "Feature",
  "properties": {
    "addr:full":"274 Rue Perras Greenfield Park QC J4V 1T4",
    "addr:housenumber":"274",
    "addr:postcode":"j4v 1t4",
    "addr:street":"Rue Perras;Park",
    "iso:country":"CA",
    "sg:address":"274 Rue Perras",
    "sg:city":"Greenfield Park",
    "sg:classifiers":[
        {
            "category":"Professional",
            "subcategory":"Computer Services",
            "type":"Services"
        }
    ],
    "sg:phone":"+1 450 923 8281",
    "sg:postcode":"J4V 1T4",
    "sg:province":"QC",
    "sg:tags":[
        "information",
        "system",
        "consultant"
    ],
    "wof:name":"Gsk Technologies Inc",
    "wof:placetype":"venue"
},
  "geometry": {"coordinates":[-73.487503,45.49012],"type":"Point"}
}