{
  "type": "Feature",
  "properties": {
    "iso:country":"CA",
    "sg:address":"5 Trans Canada Hwy",
    "sg:city":"Corner Brook",
    "sg:classifiers":[
        {
            "category":"Food & Beverages",
            "subcategory":"Bakery",
            "type":"Retail Goods"
        }
    ],
    "sg:phone":"+1 709 634 8800",
    "sg:postcode":"A2H 2N2",
    "sg:province":"NL",
    "sg:tags":[
        "doughnut"
    ],
    "wof:name":"Tim Hortons",
    "wof:placetype":"venue"
},
  "geometry": {"coordinates":[-57.9100990295,48.9570846558],"type":"Point"}
}