{
  "type": "Feature",
  "properties": {
    "addr:full":"4710 Boul Talbot Laterriere QC G7N 1V2",
    "addr:housenumber":"4710",
    "addr:postcode":"g7n 1v2",
    "addr:street":"Boul Talbot Laterriere",
    "iso:country":"CA",
    "sg:address":"4710 Boul Talbot",
    "sg:city":"Laterriere",
    "sg:classifiers":[
        {
            "category":"Freight",
            "type":"Transportation"
        }
    ],
    "sg:phone":"+1 418 549 1454",
    "sg:postcode":"G7N 1V2",
    "sg:province":"QC",
    "sg:tags":[
        "trucking"
    ],
    "wof:name":"Express Girard Transport Inc",
    "wof:placetype":"venue"
},
  "geometry": {"coordinates":[-71.11406700000001,48.338764],"type":"Point"}
}