{
  "type": "Feature",
  "properties": {
    "addr:full":"678 Bishop St N Cambridge ON N3H 4V6",
    "addr:housenumber":"678",
    "addr:postcode":"n3h 4v6",
    "addr:street":"Bishop St N",
    "iso:country":"CA",
    "sg:address":"678 Bishop St N",
    "sg:city":"Cambridge",
    "sg:classifiers":[
        {
            "category":"Retail",
            "subcategory":"Auto Repair",
            "type":"Services"
        }
    ],
    "sg:phone":"+1 519 650 1800",
    "sg:postcode":"N3H 4V6",
    "sg:province":"ON",
    "sg:tags":[
        "repairing",
        "automobile",
        "body"
    ],
    "wof:name":"Warren Automobiles",
    "wof:placetype":"venue"
},
  "geometry": {"coordinates":[-80.33745574949999,43.3926620483],"type":"Point"}
}