{
  "type": "Feature",
  "properties": {
    "addr:full":"2121 Hartley Ave Coquitlam BC V3K 6Z3",
    "addr:housenumber":"2121",
    "addr:postcode":"v3k 6z3",
    "addr:street":"Hartley Ave",
    "iso:country":"CA",
    "sg:address":"2121 Hartley Ave",
    "sg:city":"Coquitlam",
    "sg:classifiers":[
        {
            "category":"Retail",
            "subcategory":"Auto Repair",
            "type":"Services"
        }
    ],
    "sg:phone":"+1 604 524 1789",
    "sg:postcode":"V3K 6Z3",
    "sg:province":"BC",
    "sg:tags":[
        "repairing",
        "automobile"
    ],
    "wof:name":"Dmm Auto Svc",
    "wof:placetype":"venue"
},
  "geometry": {"coordinates":[-122.83659400000001,49.226028],"type":"Point"}
}