{
  "type": "Feature",
  "properties": {
    "addr:full":"101 Fanshawe Park Rd N London ON N5X 3V9",
    "addr:housenumber":"101",
    "addr:postcode":"n5x 3v9",
    "addr:street":"Fanshawe Park Rd N",
    "iso:country":"CA",
    "sg:address":"101 Fanshawe Park Rd N",
    "sg:city":"London",
    "sg:classifiers":[
        {
            "category":"Personal",
            "subcategory":"Beauty Salon",
            "type":"Services"
        }
    ],
    "sg:phone":"+1 519 663 9502",
    "sg:postcode":"N5X 3V9",
    "sg:province":"ON",
    "wof:name":"First Choice Haircutters",
    "wof:placetype":"venue"
},
  "geometry": {"coordinates":[-81.27610799999999,43.028358],"type":"Point"}
}