{
  "type": "Feature",
  "properties": {
    "addr:full":"16 Mills Dr Goodwood NS B3T 1P3",
    "addr:housenumber":"16",
    "addr:postcode":"b3t 1p3",
    "addr:street":"Mills Dr",
    "iso:country":"CA",
    "sg:address":"16 Mills Dr",
    "sg:city":"Goodwood",
    "sg:classifiers":[
        {
            "category":"Wholesale",
            "subcategory":"Scrap",
            "type":"Manufacturing & Wholesale Goods"
        }
    ],
    "sg:phone":"+1 902 876 1866",
    "sg:postcode":"B3T 1P3",
    "sg:province":"NS",
    "sg:tags":[
        "recycling",
        "center"
    ],
    "wof:name":"Halifax County C & D Recycling",
    "wof:placetype":"venue"
},
  "geometry": {"coordinates":[-63.6754722595,44.6036682129],"type":"Point"}
}