{
  "type": "Feature",
  "properties": {
    "iso:country":"CA",
    "sg:city":"Markham",
    "sg:classifiers":[
        {
            "category":"Manufacturing",
            "subcategory":"Signs",
            "type":"Manufacturing & Wholesale Goods"
        }
    ],
    "sg:phone":"+1 905 479 5962",
    "sg:postcode":"L3R 0H8",
    "sg:province":"ON",
    "wof:name":"Lettercraft",
    "wof:placetype":"venue"
},
  "geometry": {"coordinates":[-79.345375061,43.8336601257],"type":"Point"}
}