{
  "type": "Feature",
  "properties": {
    "addr:full":"NW 30 5 5W Carman MB R0G 0J0",
    "addr:housenumber":"5 5w",
    "addr:postcode":"r0g 0j0",
    "addr:street":"Nw 30",
    "iso:country":"CA",
    "sg:address":"NW 30 5 5W",
    "sg:city":"Carman",
    "sg:classifiers":[
        {
            "category":"Farming",
            "subcategory":"Farm & Veterinary Services",
            "type":"Manufacturing & Wholesale Goods"
        }
    ],
    "sg:phone":"+1 204 745 3301",
    "sg:postcode":"R0G 0J0",
    "sg:province":"MB",
    "sg:tags":[
        "seed",
        "grain",
        "cleaning"
    ],
    "wof:name":"Elias Seeds",
    "wof:placetype":"venue"
},
  "geometry": {"coordinates":[-98.002319,49.508606],"type":"Point"}
}