{
  "type": "Feature",
  "properties": {
    "addr:full":"10505 169 St NW Edmonton AB T5P 4Y7",
    "addr:housenumber":"10505",
    "addr:postcode":"t5p 4y7",
    "addr:street":"169 St Nw",
    "iso:country":"CA",
    "sg:address":"10505 169 St NW",
    "sg:city":"Edmonton",
    "sg:classifiers":[
        {
            "category":"Manufacturing",
            "subcategory":"Toys & Sporting Goods",
            "type":"Manufacturing & Wholesale Goods"
        }
    ],
    "sg:phone":"+1 780 484 4422",
    "sg:postcode":"T5P 4Y7",
    "sg:province":"AB",
    "sg:tags":[
        "textile",
        "hobby",
        "model"
    ],
    "wof:name":"Davey Fabrics Inc",
    "wof:placetype":"venue"
},
  "geometry": {"coordinates":[-113.612846374,53.550567627],"type":"Point"}
}