{
  "type": "Feature",
  "properties": {
    "addr:full":"Burlington ON L7P 4M8",
    "addr:postcode":"l7p 4m8",
    "iso:country":"CA",
    "sg:city":"Burlington",
    "sg:classifiers":[
        {
            "category":"Shopping",
            "subcategory":"Jewelry",
            "type":"Retail Goods"
        }
    ],
    "sg:phone":"+1 905 335 1377",
    "sg:postcode":"L7P 4M8",
    "sg:province":"ON",
    "sg:tags":[
        "diamond"
    ],
    "wof:name":"Gold & Diamond Depot Ltd",
    "wof:placetype":"venue"
},
  "geometry": {"coordinates":[-79.823364,43.365807],"type":"Point"}
}