{
  "type": "Feature",
  "properties": {
    "addr:full":"232 Red River Rd Thunder Bay ON P7B 1A6",
    "addr:housenumber":"232",
    "addr:postcode":"p7b 1a6",
    "addr:street":"Red River Rd",
    "iso:country":"CA",
    "sg:address":"232 Red River Rd",
    "sg:city":"Thunder Bay",
    "sg:classifiers":[
        {
            "category":"Shopping",
            "subcategory":"Gifts & Souvenirs",
            "type":"Retail Goods"
        }
    ],
    "sg:phone":"+1 807 344 3582",
    "sg:postcode":"P7B 1A6",
    "sg:province":"ON",
    "sg:tags":[
        "shop"
    ],
    "wof:name":"Treasure House Ltd",
    "wof:placetype":"venue"
},
  "geometry": {"coordinates":[-89.221169,48.43552],"type":"Point"}
}