{
  "type": "Feature",
  "properties": {
    "addr:full":"15531 24 Ave # 7 Surrey BC V4A 2J4",
    "addr:housenumber":"15531",
    "addr:postcode":"v4a 2j4",
    "addr:street":"24 Ave # 7",
    "iso:country":"CA",
    "sg:address":"15531 24 Ave # 7",
    "sg:city":"Surrey",
    "sg:classifiers":[
        {
            "category":"Recreation",
            "type":"Entertainment"
        }
    ],
    "sg:phone":"+1 604 536 3746",
    "sg:postcode":"V4A 2J4",
    "sg:province":"BC",
    "sg:tags":[
        "martial",
        "arts",
        "instruction"
    ],
    "wof:name":"Dragon's Den Pure Defense",
    "wof:placetype":"venue"
},
  "geometry": {"coordinates":[-122.792366028,49.0457191467],"type":"Point"}
}