{
  "type": "Feature",
  "properties": {
    "iso:country":"CA",
    "sg:address":"100 Fullarton St",
    "sg:city":"London",
    "sg:classifiers":[
        {
            "category":"Professional",
            "subcategory":"Lawyer & Legal Services",
            "type":"Services"
        }
    ],
    "sg:phone":"+1 519 432 2417",
    "sg:postcode":"N6A 1K1",
    "sg:province":"ON",
    "sg:tags":[
        "attorney"
    ],
    "wof:name":"Antin Jaremchuk Law Office",
    "wof:placetype":"venue"
},
  "geometry": {"coordinates":[-81.2532577515,42.9848861694],"type":"Point"}
}