{
  "type": "Feature",
  "properties": {
    "iso:country":"CA",
    "sg:city":"Richmond",
    "sg:classifiers":[
        {
            "category":"Professional",
            "subcategory":"Engineering",
            "type":"Services"
        }
    ],
    "sg:phone":"+1 604 276 2555",
    "sg:postcode":"V6Y 3T8",
    "sg:province":"BC",
    "sg:tags":[
        "engineer"
    ],
    "wof:name":"D S Lee Engineering",
    "wof:placetype":"venue"
},
  "geometry": {"coordinates":[-123.134292602,49.1666717529],"type":"Point"}
}