{
  "type": "Feature",
  "properties": {
    "addr:full":"811 Progress Ave Scarborough ON M1H 2X4",
    "addr:housenumber":"811",
    "addr:postcode":"m1h 2x4",
    "addr:street":"Progress Ave",
    "iso:country":"CA",
    "sg:address":"811 Progress Ave",
    "sg:city":"Scarborough",
    "sg:classifiers":[
        {
            "category":"Wholesale",
            "subcategory":"Construction Materials",
            "type":"Manufacturing & Wholesale Goods"
        }
    ],
    "sg:phone":"+1 416 431 5556",
    "sg:postcode":"M1H 2X4",
    "sg:province":"ON",
    "sg:tags":[
        "fence"
    ],
    "wof:name":"Mc Gowan Fence & Supply Ltd",
    "wof:placetype":"venue"
},
  "geometry": {"coordinates":[-79.242439,43.780334],"type":"Point"}
}