{
  "type": "Feature",
  "properties": {
    "addr:full":"323 Avenue A S Saskatoon SK S7M 1L7",
    "addr:housenumber":"323",
    "addr:postcode":"s7m 1l7",
    "addr:street":"Avenue A S",
    "iso:country":"CA",
    "sg:address":"323 Avenue A S",
    "sg:city":"Saskatoon",
    "sg:classifiers":[
        {
            "category":"Insurance",
            "subcategory":"Insurance Agent",
            "type":"Services"
        }
    ],
    "sg:phone":"+1 306 934 0580",
    "sg:postcode":"S7M 1L7",
    "sg:province":"SK",
    "sg:tags":[
        "appraiser"
    ],
    "wof:name":"Collectors Auto Appraisals",
    "wof:placetype":"venue"
},
  "geometry": {"coordinates":[-106.67043304400001,52.1254196167],"type":"Point"}
}