{
  "type": "Feature",
  "properties": {
    "addr:full":"18 Maplewood Dr Shelburne ON L0N 1S5",
    "addr:housenumber":"18",
    "addr:postcode":"l0n 1s5",
    "addr:street":"Maplewood Dr",
    "iso:country":"CA",
    "sg:address":"18 Maplewood Dr",
    "sg:city":"Shelburne",
    "sg:classifiers":[
        {
            "category":"Building & Trades",
            "subcategory":"Construction",
            "type":"Services"
        }
    ],
    "sg:phone":"+1 519 925 2056",
    "sg:postcode":"L0N 1S5",
    "sg:province":"ON",
    "sg:tags":[
        "general",
        "contractor"
    ],
    "wof:name":"Jamieson Construction",
    "wof:placetype":"venue"
},
  "geometry": {"coordinates":[-80.20208700000001,44.078785],"type":"Point"}
}