{
  "type": "Feature",
  "properties": {
    "iso:country":"CA",
    "sg:address":"380 Scott St",
    "sg:city":"St Catharines",
    "sg:classifiers":[
        {
            "category":"Autos & Motor Vehicles",
            "subcategory":"Auto Supplies",
            "type":"Retail Goods"
        }
    ],
    "sg:phone":"+1 905 934 6142",
    "sg:postcode":"L2M 3W4",
    "sg:province":"ON",
    "sg:tags":[
        "automobile",
        "parts"
    ],
    "wof:name":"Canadian Tire Gas Bar",
    "wof:placetype":"venue"
},
  "geometry": {"coordinates":[-79.228409,43.189007],"type":"Point"}
}