{
  "type": "Feature",
  "properties": {
    "addr:full":"168 King Edward Ave Ottawa ON K1N 7L3",
    "addr:housenumber":"168",
    "addr:postcode":"k1n 7l3",
    "addr:street":"King Edward Ave",
    "iso:country":"CA",
    "sg:address":"168 King Edward Ave",
    "sg:city":"Ottawa",
    "sg:classifiers":[
        {
            "category":"Food & Beverages",
            "subcategory":"Groceries & Convenience Stores",
            "type":"Retail Goods"
        }
    ],
    "sg:phone":"+1 613 562 1532",
    "sg:postcode":"K1N 7L3",
    "sg:province":"ON",
    "wof:name":"Blue Nile Grocery Store",
    "wof:placetype":"venue"
},
  "geometry": {"coordinates":[-75.6902999878,45.4337463379],"type":"Point"}
}