{
  "type": "Feature",
  "properties": {
    "iso:country":"CA",
    "sg:address":"7205 Boul Taschereau",
    "sg:city":"Brossard",
    "sg:classifiers":[
        {
            "category":"Recreation",
            "type":"Entertainment"
        }
    ],
    "sg:phone":"+1 450 462 8807",
    "sg:postcode":"J4Y 1A1",
    "sg:province":"QC",
    "sg:tags":[
        "amusement"
    ],
    "wof:name":"Grand-Prix Karting Inc",
    "wof:placetype":"venue"
},
  "geometry": {"coordinates":[-73.46505737299999,45.4612731934],"type":"Point"}
}