{
  "type": "Feature",
  "properties": {
    "addr:full":"Saint-Laurent QC H4T 1J8",
    "addr:postcode":"h4t 1j8",
    "iso:country":"CA",
    "sg:city":"Saint-Laurent",
    "sg:classifiers":[
        {
            "category":"Freight",
            "type":"Transportation"
        }
    ],
    "sg:phone":"+1 514 344 5067",
    "sg:postcode":"H4T 1J8",
    "sg:province":"QC",
    "sg:tags":[
        "warehouse",
        "storage"
    ],
    "wof:name":"Entrepot Frigorifique Intl Inc",
    "wof:placetype":"venue"
},
  "geometry": {"coordinates":[-73.70017199999999,45.470833],"type":"Point"}
}