{
  "type": "Feature",
  "properties": {
    "addr:full":"9 Alice St Waterford ON N0E 1Y0",
    "addr:housenumber":"9",
    "addr:postcode":"n0e 1y0",
    "addr:street":"Alice St",
    "iso:country":"CA",
    "sg:address":"9 Alice St",
    "sg:city":"Waterford",
    "sg:classifiers":[
        {
            "category":"Banks & Credit Unions",
            "subcategory":"Bank",
            "type":"Services"
        }
    ],
    "sg:phone":"+1 519 443 8639",
    "sg:postcode":"N0E 1Y0",
    "sg:province":"ON",
    "wof:name":"Bank of Montreal",
    "wof:placetype":"venue"
},
  "geometry": {"coordinates":[-80.2919464111,42.9350280762],"type":"Point"}
}