{
  "type": "Feature",
  "properties": {
    "addr:full":"196 Caverly Rd Aylmer ON N5H 2P7",
    "addr:housenumber":"196",
    "addr:postcode":"n5h 2p7",
    "addr:street":"Caverly Rd",
    "iso:country":"CA",
    "sg:address":"196 Caverly Rd",
    "sg:city":"Aylmer",
    "sg:classifiers":[
        {
            "category":"Manufacturing",
            "subcategory":"Metals",
            "type":"Manufacturing & Wholesale Goods"
        }
    ],
    "sg:phone":"+1 519 765 1249",
    "sg:postcode":"N5H 2P7",
    "sg:province":"ON",
    "sg:tags":[
        "door"
    ],
    "wof:name":"Jlw Aluminum",
    "wof:placetype":"venue"
},
  "geometry": {"coordinates":[-80.995834,42.764366],"type":"Point"}
}