{
  "type": "Feature",
  "properties": {
    "iso:country":"CA",
    "sg:address":"605 Rue Jacques-Cartier S",
    "sg:city":"Farnham",
    "sg:classifiers":[
        {
            "category":"Building & Trades",
            "subcategory":"Construction",
            "type":"Services"
        }
    ],
    "sg:phone":"+1 450 293 3001",
    "sg:postcode":"J2N 1Y7",
    "sg:province":"QC",
    "sg:tags":[
        "acoustical",
        "contractor",
        "general"
    ],
    "wof:name":"Systemes Interieurs Inc",
    "wof:placetype":"venue"
},
  "geometry": {"coordinates":[-72.9838638306,45.2725944519],"type":"Point"}
}