{
  "type": "Feature",
  "properties": {
    "addr:full":"9901 100th St # 5400 LA Crete AB T0H 2H0",
    "addr:housenumber":"9901",
    "addr:postcode":"5400;t0h 2h0",
    "addr:street":"100Th St #",
    "iso:country":"CA",
    "sg:address":"9901 100th St # 5400",
    "sg:city":"LA Crete",
    "sg:classifiers":[
        {
            "category":"Home & Garden",
            "subcategory":"Hardware",
            "type":"Retail Goods"
        }
    ],
    "sg:phone":"+1 780 928 3750",
    "sg:postcode":"T0H 2H0",
    "sg:province":"AB",
    "wof:name":"Home Hardware",
    "wof:placetype":"venue"
},
  "geometry": {"coordinates":[-116.404426575,58.1867523193],"type":"Point"}
}