{
  "type": "Feature",
  "properties": {
    "addr:full":"32 Airpark Pl Guelph ON N1L 1B2",
    "addr:housenumber":"32",
    "addr:postcode":"n1l 1b2",
    "addr:street":"Airpark Pl",
    "iso:country":"CA",
    "sg:address":"32 Airpark Pl",
    "sg:city":"Guelph",
    "sg:classifiers":[
        {
            "category":"Manufacturing",
            "subcategory":"Metals",
            "type":"Manufacturing & Wholesale Goods"
        }
    ],
    "sg:phone":"+1 519 836 6672",
    "sg:postcode":"N1L 1B2",
    "sg:province":"ON",
    "sg:tags":[
        "stamping"
    ],
    "wof:name":"Gunn Metal Stampings Inc",
    "wof:placetype":"venue"
},
  "geometry": {"coordinates":[-80.20151519780001,43.5630302429],"type":"Point"}
}