{
  "type": "Feature",
  "properties": {
    "addr:full":"20 Rue Alain LA Prairie QC J5R 2H1",
    "addr:housenumber":"20",
    "addr:postcode":"j5r 2h1",
    "addr:street":"Rue Alain",
    "iso:country":"CA",
    "sg:address":"20 Rue Alain",
    "sg:city":"LA Prairie",
    "sg:classifiers":[
        {
            "category":"Building & Trades",
            "subcategory":"Construction",
            "type":"Services"
        }
    ],
    "sg:phone":"+1 450 444 5775",
    "sg:postcode":"J5R 2H1",
    "sg:province":"QC",
    "sg:tags":[
        "general",
        "contractor"
    ],
    "wof:name":"Constructions DE Marque",
    "wof:placetype":"venue"
},
  "geometry": {"coordinates":[-73.474487,45.411823],"type":"Point"}
}