{
  "type": "Feature",
  "properties": {
    "iso:country":"CA",
    "sg:address":"1268 Rue Belanger",
    "sg:city":"Montreal",
    "sg:classifiers":[
        {
            "category":"Building & Trades",
            "subcategory":"Electrical",
            "type":"Services"
        }
    ],
    "sg:phone":"+1 514 273 7281",
    "sg:postcode":"H2S 1H9",
    "sg:province":"QC",
    "sg:tags":[
        "electric",
        "contractor"
    ],
    "wof:name":"Charles Belanger & Fils Ltee",
    "wof:placetype":"venue"
},
  "geometry": {"coordinates":[-73.606728,45.542583],"type":"Point"}
}