{
  "type": "Feature",
  "properties": {
    "addr:full":"70 Rue Wellington N Sherbrooke QC J1H 5B8",
    "addr:housenumber":"70",
    "addr:postcode":"j1h 5b8",
    "addr:street":"Rue Wellington N",
    "iso:country":"CA",
    "sg:address":"70 Rue Wellington N",
    "sg:city":"Sherbrooke",
    "sg:classifiers":[
        {
            "category":"Food & Beverages",
            "subcategory":"Bakery",
            "type":"Retail Goods"
        }
    ],
    "sg:phone":"+1 819 569 1445",
    "sg:postcode":"J1H 5B8",
    "sg:province":"QC",
    "sg:tags":[
        "doughnut"
    ],
    "wof:name":"Dunkin Donuts",
    "wof:placetype":"venue"
},
  "geometry": {"coordinates":[-71.89097595210001,45.4026374817],"type":"Point"}
}