{
  "type": "Feature",
  "properties": {
    "iso:country":"CA",
    "sg:city":"Etobicoke",
    "sg:classifiers":[
        {
            "category":"Shopping",
            "subcategory":"Jewelry",
            "type":"Retail Goods"
        }
    ],
    "sg:phone":"+1 416 236 9595",
    "sg:postcode":"M9B 3Y8",
    "sg:province":"ON",
    "sg:tags":[
        "jeweler"
    ],
    "wof:name":"Belgium Diamonds",
    "wof:placetype":"venue"
},
  "geometry": {"coordinates":[-79.554649353,43.6326751709],"type":"Point"}
}