{
  "type": "Feature",
  "properties": {
    "addr:full":"6007 Ch Cypres Saint-Michel-Des-Saints QC J0K 3B0",
    "addr:postcode":"6007;j0k 3b0",
    "addr:street":"Ch Cypres",
    "iso:country":"CA",
    "sg:address":"6007 Ch Cypres",
    "sg:city":"Saint-Michel-Des-Saints",
    "sg:classifiers":[
        {
            "category":"Government",
            "subcategory":"Office",
            "type":"Public Place"
        }
    ],
    "sg:phone":"+1 450 833 5530",
    "sg:postcode":"J0K 3B0",
    "sg:province":"QC",
    "sg:tags":[
        "camp",
        "fishing"
    ],
    "wof:name":"Reserve Rouge-Matawin Poste",
    "wof:placetype":"venue"
},
  "geometry": {"coordinates":[-74.04167200000001,46.632641],"type":"Point"}
}