{
  "type": "Feature",
  "properties": {
    "addr:full":"160 Smithfield Ave Winnipeg MB R2V 0C2",
    "addr:housenumber":"160",
    "addr:postcode":"r2v 0c2",
    "addr:street":"Smithfield Ave",
    "iso:country":"CA",
    "sg:address":"160 Smithfield Ave",
    "sg:city":"Winnipeg",
    "sg:classifiers":[
        {
            "category":"Organizations",
            "subcategory":"Religious Organization",
            "type":"Services"
        }
    ],
    "sg:phone":"+1 204 339 7519",
    "sg:postcode":"R2V 0C2",
    "sg:province":"MB",
    "sg:tags":[
        "church"
    ],
    "wof:name":"St Martin-In-the-Field Anglcn",
    "wof:placetype":"venue"
},
  "geometry": {"coordinates":[-97.119598,49.930103],"type":"Point"}
}