{
  "type": "Feature",
  "properties": {
    "addr:full":"PO Box 462 Buchans NL A0H 1G0",
    "addr:housenumber":"po",
    "addr:postcode":"a0h 1g0",
    "addr:street":"Box 462",
    "iso:country":"CA",
    "sg:address":"PO Box 462",
    "sg:city":"Buchans",
    "sg:classifiers":[
        {
            "category":"Travel",
            "subcategory":"Campground",
            "type":"Entertainment"
        }
    ],
    "sg:phone":"+1 709 672 4425",
    "sg:postcode":"A0H 1G0",
    "sg:province":"NL",
    "sg:tags":[
        "camp",
        "fishing"
    ],
    "wof:name":"Owl's Nest Lodge",
    "wof:placetype":"venue"
},
  "geometry": {"coordinates":[-56.855198,48.825554],"type":"Point"}
}