{
  "type": "Feature",
  "properties": {
    "iso:country":"CA",
    "sg:address":"519 Brant St",
    "sg:city":"Burlington",
    "sg:classifiers":[
        {
            "category":"Banks & Credit Unions",
            "subcategory":"Bank",
            "type":"Services"
        }
    ],
    "sg:phone":"+1 905 637 8224",
    "sg:postcode":"L7R 2G6",
    "sg:province":"ON",
    "wof:name":"Bank of Montreal",
    "wof:placetype":"venue"
},
  "geometry": {"coordinates":[-79.801025,43.328087],"type":"Point"}
}