{
  "type": "Feature",
  "properties": {
    "addr:full":"320 Boul Industriel Saint-Eustache QC J7R 5R4",
    "addr:housenumber":"320",
    "addr:postcode":"j7r 5r4",
    "addr:street":"Boul Industriel",
    "iso:country":"CA",
    "sg:address":"320 Boul Industriel",
    "sg:city":"Saint-Eustache",
    "sg:classifiers":[
        {
            "category":"Manufacturing",
            "subcategory":"Tools & Machinery",
            "type":"Manufacturing & Wholesale Goods"
        }
    ],
    "sg:phone":"+1 450 472 8492",
    "sg:postcode":"J7R 5R4",
    "sg:province":"QC",
    "sg:tags":[
        "machine",
        "shop"
    ],
    "wof:name":"M-Tech Atelier D'Usinage",
    "wof:placetype":"venue"
},
  "geometry": {"coordinates":[-73.92543792719999,45.5646057129],"type":"Point"}
}