{
  "type": "Feature",
  "properties": {
    "addr:full":"9301 66th Ave Osoyoos BC V0H 1V0",
    "addr:housenumber":"9301",
    "addr:postcode":"v0h 1v0",
    "addr:street":"66Th Ave",
    "iso:country":"CA",
    "sg:address":"9301 66th Ave",
    "sg:city":"Osoyoos",
    "sg:classifiers":[
        {
            "category":"Recreation",
            "type":"Entertainment"
        }
    ],
    "sg:phone":"+1 250 495 3478",
    "sg:postcode":"V0H 1V0",
    "sg:province":"BC",
    "sg:tags":[
        "club",
        "hockey"
    ],
    "wof:name":"South Okanagon Minor Hockey",
    "wof:placetype":"venue"
},
  "geometry": {"coordinates":[-119.463195801,49.0293083191],"type":"Point"}
}