{
  "type": "Feature",
  "properties": {
    "addr:full":"97 Principale Saint-Aime-Des-Lacs QC G0T 1S0",
    "addr:housenumber":"97",
    "addr:postcode":"g0t 1s0",
    "addr:street":"Principale Saint-Aime-Des-Lacs",
    "iso:country":"CA",
    "sg:address":"97 Principale",
    "sg:city":"Saint-Aime-Des-Lacs",
    "sg:classifiers":[
        {
            "category":"Organizations",
            "subcategory":"Religious Organization",
            "type":"Services"
        }
    ],
    "sg:phone":"+1 418 439 2078",
    "sg:postcode":"G0T 1S0",
    "sg:province":"QC",
    "sg:tags":[
        "church"
    ],
    "wof:name":"Presbytere St-Aime-Des-Lacs",
    "wof:placetype":"venue"
},
  "geometry": {"coordinates":[-70.3077087402,47.6825027466],"type":"Point"}
}