{
  "type": "Feature",
  "properties": {
    "iso:country":"CA",
    "sg:address":"520 Rue Grande-Allee",
    "sg:city":"Terrebonne",
    "sg:classifiers":[
        {
            "category":"Building & Trades",
            "subcategory":"Pest Control",
            "type":"Services"
        }
    ],
    "sg:phone":"+1 450 492 9090",
    "sg:postcode":"J6W 4S9",
    "sg:province":"QC",
    "wof:name":"Extermination Express Enr",
    "wof:placetype":"venue"
},
  "geometry": {"coordinates":[-73.655396,45.697369],"type":"Point"}
}