{
  "type": "Feature",
  "properties": {
    "addr:full":"520 Rue Grande-Allee Terrebonne QC J6W 4S9",
    "addr:housenumber":"520",
    "addr:postcode":"j6w 4s9",
    "addr:street":"Rue Grande-Allee",
    "iso:country":"CA",
    "sg:address":"520 Rue Grande-Allee",
    "sg:city":"Terrebonne",
    "sg:classifiers":[
        {
            "category":"Building & Trades",
            "subcategory":"Pest Control",
            "type":"Services"
        }
    ],
    "sg:phone":"+1 450 492 9090",
    "sg:postcode":"J6W 4S9",
    "sg:province":"QC",
    "wof:name":"Extermination Express Enr",
    "wof:placetype":"venue"
},
  "geometry": {"coordinates":[-73.655396,45.697369],"type":"Point"}
}