{
  "type": "Feature",
  "properties": {
    "iso:country":"CA",
    "sg:city":"Mississauga",
    "sg:classifiers":[
        {
            "category":"Health Services",
            "subcategory":"Doctor",
            "type":"Services"
        }
    ],
    "sg:phone":"+1 905 273 4055",
    "sg:postcode":"L5B 2P7",
    "sg:province":"ON",
    "sg:tags":[
        "physician",
        "surgeon"
    ],
    "wof:name":"Adleman, N MD",
    "wof:placetype":"venue"
},
  "geometry": {"coordinates":[-79.610687,43.571804],"type":"Point"}
}