{
  "type": "Feature",
  "properties": {
    "addr:full":"4310 Black Gold Dr Leduc AB T9E 3C3",
    "addr:housenumber":"4310",
    "addr:postcode":"t9e 3c3",
    "addr:street":"Black Gold Dr",
    "iso:country":"CA",
    "sg:address":"4310 Black Gold Dr",
    "sg:city":"Leduc",
    "sg:classifiers":[
        {
            "category":"Organizations",
            "subcategory":"Religious Organization",
            "type":"Services"
        }
    ],
    "sg:phone":"+1 780 986 1414",
    "sg:postcode":"T9E 3C3",
    "sg:province":"AB",
    "sg:tags":[
        "church"
    ],
    "wof:name":"Family Worship Ctr",
    "wof:placetype":"venue"
},
  "geometry": {"coordinates":[-113.52810700000001,53.255974],"type":"Point"}
}