{
  "type": "Feature",
  "properties": {
    "addr:full":"214 Ontario St Brighton ON K0K 1H0",
    "addr:housenumber":"214",
    "addr:postcode":"k0k 1h0",
    "addr:street":"Ontario St",
    "iso:country":"CA",
    "sg:address":"214 Ontario St",
    "sg:city":"Brighton",
    "sg:classifiers":[
        {
            "category":"Home & Garden",
            "subcategory":"Garden Supply",
            "type":"Retail Goods"
        }
    ],
    "sg:phone":"+1 613 475 0350",
    "sg:postcode":"K0K 1H0",
    "sg:province":"ON",
    "sg:tags":[
        "center"
    ],
    "wof:name":"Wain's Greenhouses Garden Ctr",
    "wof:placetype":"venue"
},
  "geometry": {"coordinates":[-77.7389373779,44.0222167969],"type":"Point"}
}