{
  "type": "Feature",
  "properties": {
    "addr:full":"4282 Rue Saint-Felix Cap-Rouge QC G1Y 1X5",
    "addr:housenumber":"4282",
    "addr:postcode":"g1y 1x5",
    "addr:street":"Rue Saint-Felix",
    "iso:country":"CA",
    "sg:address":"4282 Rue Saint-Felix",
    "sg:city":"Cap-Rouge",
    "sg:classifiers":[
        {
            "category":"Professional",
            "type":"Services"
        }
    ],
    "sg:phone":"+1 418 654 2081",
    "sg:postcode":"G1Y 1X5",
    "sg:province":"QC",
    "sg:tags":[
        "establishment",
        "event"
    ],
    "wof:name":"Diafa Productions",
    "wof:placetype":"venue"
},
  "geometry": {"coordinates":[-71.34730529789999,46.7478218079],"type":"Point"}
}