{
  "type": "Feature",
  "properties": {
    "addr:full":"593692 County Rd 13 Burgessville ON N0J 1C0",
    "addr:housenumber":"593692;13",
    "addr:postcode":"n0j 1c0",
    "addr:street":"County Rd",
    "iso:country":"CA",
    "sg:address":"593692 County Rd 13",
    "sg:city":"Burgessville",
    "sg:classifiers":[
        {
            "category":"Freight",
            "type":"Transportation"
        }
    ],
    "sg:phone":"+1 519 424 9841",
    "sg:postcode":"N0J 1C0",
    "sg:province":"ON",
    "sg:tags":[
        "trucking"
    ],
    "wof:name":"Noblewood Transport Ltd",
    "wof:placetype":"venue"
},
  "geometry": {"coordinates":[-80.6519699097,43.0240097046],"type":"Point"}
}