{
  "type": "Feature",
  "properties": {
    "addr:full":"75 Boul Industriel Shawinigan-Sud QC G9N 6T5",
    "addr:housenumber":"75",
    "addr:postcode":"g9n 6t5",
    "addr:street":"Boul Industriel",
    "iso:country":"CA",
    "sg:address":"75 Boul Industriel",
    "sg:city":"Shawinigan-Sud",
    "sg:classifiers":[
        {
            "category":"Wholesale",
            "subcategory":"Electrical",
            "type":"Manufacturing & Wholesale Goods"
        }
    ],
    "sg:phone":"+1 819 536 2609",
    "sg:postcode":"G9N 6T5",
    "sg:province":"QC",
    "sg:tags":[
        "electric",
        "motor"
    ],
    "wof:name":"Moteurs & Roulements pm Inc",
    "wof:placetype":"venue"
},
  "geometry": {"coordinates":[-72.752197,46.518978],"type":"Point"}
}