{
  "type": "Feature",
  "properties": {
    "addr:full":"147 Memorial Ave Orillia ON L3V 5X3",
    "addr:housenumber":"147",
    "addr:postcode":"l3v 5x3",
    "addr:street":"Memorial Ave",
    "iso:country":"CA",
    "sg:address":"147 Memorial Ave",
    "sg:city":"Orillia",
    "sg:classifiers":[
        {
            "category":"Building & Trades",
            "subcategory":"Construction",
            "type":"Services"
        }
    ],
    "sg:phone":"+1 705 326 8122",
    "sg:postcode":"L3V 5X3",
    "sg:province":"ON",
    "sg:tags":[
        "dry wall",
        "contractor"
    ],
    "wof:name":"Classic Drywall & Plastering",
    "wof:placetype":"venue"
},
  "geometry": {"coordinates":[-79.425774,44.600506],"type":"Point"}
}