{
  "type": "Feature",
  "properties": {
    "addr:full":"1108 Derwent Way Delta BC V3M 5R1",
    "addr:housenumber":"1108",
    "addr:postcode":"v3m 5r1",
    "addr:street":"Derwent Way",
    "iso:country":"CA",
    "sg:address":"1108 Derwent Way",
    "sg:city":"Delta",
    "sg:classifiers":[
        {
            "category":"Wholesale",
            "subcategory":"Scrap",
            "type":"Manufacturing & Wholesale Goods"
        }
    ],
    "sg:phone":"+1 604 524 6313",
    "sg:postcode":"V3M 5R1",
    "sg:province":"BC",
    "sg:tags":[
        "recycling",
        "center"
    ],
    "wof:name":"Pacific Shredding Ltd",
    "wof:placetype":"venue"
},
  "geometry": {"coordinates":[-122.942162,49.16798],"type":"Point"}
}