{
  "type": "Feature",
  "properties": {
    "addr:full":"61 202 Rte Lacolle QC J0J 1J0",
    "addr:housenumber":"202",
    "addr:postcode":"j0j 1j0",
    "addr:street":"61;Rte Lacolle",
    "iso:country":"CA",
    "sg:address":"61 202 Rte",
    "sg:city":"Lacolle",
    "sg:classifiers":[
        {
            "category":"Autos & Motor Vehicles",
            "subcategory":"Fuel & Gas Station",
            "type":"Retail Goods"
        }
    ],
    "sg:phone":"+1 450 246 3213",
    "sg:postcode":"J0J 1J0",
    "sg:province":"QC",
    "sg:tags":[
        "oil"
    ],
    "wof:name":"Station Service M Daigneault",
    "wof:placetype":"venue"
},
  "geometry": {"coordinates":[-73.372902,45.082474],"type":"Point"}
}