{
  "type": "Feature",
  "properties": {
    "iso:country":"CA",
    "sg:address":"10180 101 St NW # 1150",
    "sg:city":"Edmonton",
    "sg:classifiers":[
        {
            "category":"Government",
            "subcategory":"Office",
            "type":"Public Place"
        }
    ],
    "sg:phone":"+1 780 426 1457",
    "sg:postcode":"T5J 3S4",
    "sg:province":"AB",
    "sg:tags":[
        "federal",
        "affairs"
    ],
    "wof:name":"Royal Danish Consulate",
    "wof:placetype":"venue"
},
  "geometry": {"coordinates":[-113.493934631,53.5425872803],"type":"Point"}
}