{
  "type": "Feature",
  "properties": {
    "addr:full":"1 Wortley Rd London ON N6C 3N7",
    "addr:housenumber":"1",
    "addr:postcode":"n6c 3n7",
    "addr:street":"Wortley Rd",
    "iso:country":"CA",
    "sg:address":"1 Wortley Rd",
    "sg:city":"London",
    "sg:classifiers":[
        {
            "category":"Professional",
            "subcategory":"Engineering",
            "type":"Services"
        }
    ],
    "sg:phone":"+1 519 672 8511",
    "sg:postcode":"N6C 3N7",
    "sg:province":"ON",
    "sg:tags":[
        "engineer"
    ],
    "wof:name":"Smylie & Crow Assoc Inc",
    "wof:placetype":"venue"
},
  "geometry": {"coordinates":[-81.2568740845,42.9789352417],"type":"Point"}
}