{
  "type": "Feature",
  "properties": {
    "addr:full":"1190 6E Ave Saint-Georges QC G5Y 3V3",
    "addr:housenumber":"1190",
    "addr:postcode":"g5y 3v3",
    "addr:street":"6E Ave",
    "iso:country":"CA",
    "sg:address":"1190 6E Ave",
    "sg:city":"Saint-Georges",
    "sg:classifiers":[
        {
            "category":"Personal",
            "subcategory":"Beauty Salon",
            "type":"Services"
        }
    ],
    "sg:phone":"+1 418 228 5485",
    "sg:postcode":"G5Y 3V3",
    "sg:province":"QC",
    "wof:name":"Salon Michael Inc",
    "wof:placetype":"venue"
},
  "geometry": {"coordinates":[-70.67115020750001,46.1233482361],"type":"Point"}
}