{
  "type": "Feature",
  "properties": {
    "addr:full":"North York ON M3B 3N3",
    "addr:postcode":"m3b 3n3",
    "iso:country":"CA",
    "sg:city":"North York",
    "sg:classifiers":[
        {
            "category":"Real Estate",
            "subcategory":"Real Estate Agent",
            "type":"Services"
        }
    ],
    "sg:phone":"+1 416 510 2333",
    "sg:postcode":"M3B 3N3",
    "sg:province":"ON",
    "wof:name":"Retail Leasing Consultants",
    "wof:placetype":"venue"
},
  "geometry": {"coordinates":[-79.34730529789999,43.7506866455],"type":"Point"}
}