{
  "type": "Feature",
  "properties": {
    "iso:country":"CA",
    "sg:address":"883 Upper Wentworth St",
    "sg:city":"Hamilton",
    "sg:classifiers":[
        {
            "category":"Personal",
            "type":"Services"
        }
    ],
    "sg:phone":"+1 905 575 1010",
    "sg:postcode":"L9A 4Y6",
    "sg:province":"ON",
    "sg:tags":[
        "program",
        "physical",
        "exercise",
        "fitness"
    ],
    "wof:name":"Exclusively Women's Fitness",
    "wof:placetype":"venue"
},
  "geometry": {"coordinates":[-79.863113,43.219872],"type":"Point"}
}