{
  "type": "Feature",
  "properties": {
    "iso:country":"CA",
    "sg:address":"66 Rue Saint-Jacques",
    "sg:city":"Hull",
    "sg:classifiers":[
        {
            "category":"Health Services",
            "subcategory":"Health Practitioner",
            "type":"Services"
        }
    ],
    "sg:phone":"+1 819 770 9163",
    "sg:postcode":"J8X 2Y8",
    "sg:province":"QC",
    "sg:tags":[
        "psychologist"
    ],
    "wof:name":"Poirier, Pierre-Paul",
    "wof:placetype":"venue"
},
  "geometry": {"coordinates":[-75.719101,45.427708],"type":"Point"}
}