{
  "type": "Feature",
  "properties": {
    "addr:full":"Allenford ON N0H 1A0",
    "addr:postcode":"n0h 1a0",
    "iso:country":"CA",
    "sg:city":"Allenford",
    "sg:classifiers":[
        {
            "category":"Food & Beverages",
            "subcategory":"Groceries & Convenience Stores",
            "type":"Retail Goods"
        }
    ],
    "sg:phone":"+1 519 934 0260",
    "sg:postcode":"N0H 1A0",
    "sg:province":"ON",
    "wof:name":"Allean's Corner Store & Esso",
    "wof:placetype":"venue"
},
  "geometry": {"coordinates":[-81.18269348139999,44.5354499817],"type":"Point"}
}