{
  "type": "Feature",
  "properties": {
    "addr:full":"3 Jones Crt Sussex NB E4E 2S2",
    "addr:housenumber":"3",
    "addr:postcode":"e4e 2s2",
    "addr:street":"Jones Crt",
    "iso:country":"CA",
    "sg:address":"3 Jones Crt",
    "sg:city":"Sussex",
    "sg:classifiers":[
        {
            "category":"Manufacturing",
            "subcategory":"Printing",
            "type":"Manufacturing & Wholesale Goods"
        }
    ],
    "sg:phone":"+1 506 633 1165",
    "sg:postcode":"E4E 2S2",
    "sg:province":"NB",
    "sg:tags":[
        "printer"
    ],
    "wof:name":"Rainbow Printing Ltd",
    "wof:placetype":"venue"
},
  "geometry": {"coordinates":[-65.4826431274,45.729385376],"type":"Point"}
}