{
  "type": "Feature",
  "properties": {
    "iso:country":"CA",
    "sg:address":"3165 Ch Galvin",
    "sg:city":"Fleurimont",
    "sg:classifiers":[
        {
            "category":"Building & Trades",
            "subcategory":"Construction",
            "type":"Services"
        }
    ],
    "sg:phone":"+1 819 563 3809",
    "sg:postcode":"J1G 5E6",
    "sg:province":"QC",
    "sg:tags":[
        "contractor",
        "general"
    ],
    "wof:name":"Constructions Luc Stebenne Inc",
    "wof:placetype":"venue"
},
  "geometry": {"coordinates":[-71.8207244873,45.4016609192],"type":"Point"}
}