{
  "type": "Feature",
  "properties": {
    "addr:full":"Mississauga ON L4Y 4H3",
    "addr:postcode":"l4y 4h3",
    "iso:country":"CA",
    "sg:city":"Mississauga",
    "sg:classifiers":[
        {
            "category":"Shopping",
            "subcategory":"Gifts & Souvenirs",
            "type":"Retail Goods"
        }
    ],
    "sg:phone":"+1 905 629 2347",
    "sg:postcode":"L4Y 4H3",
    "sg:province":"ON",
    "sg:tags":[
        "shop"
    ],
    "wof:name":"Something Special",
    "wof:placetype":"venue"
},
  "geometry": {"coordinates":[-79.599609375,43.6204719543],"type":"Point"}
}