{
  "type": "Feature",
  "properties": {
    "addr:full":"11 Macbeath Ave Moncton NB E1C 6Z1",
    "addr:housenumber":"11",
    "addr:postcode":"e1c 6z1",
    "addr:street":"Macbeath Ave",
    "iso:country":"CA",
    "sg:address":"11 Macbeath Ave",
    "sg:city":"Moncton",
    "sg:classifiers":[
        {
            "category":"Health Services",
            "subcategory":"Doctor",
            "type":"Services"
        }
    ],
    "sg:phone":"+1 506 855 2110",
    "sg:postcode":"E1C 6Z1",
    "sg:province":"NB",
    "sg:tags":[
        "dentist"
    ],
    "wof:name":"Cormier, Victor DDS",
    "wof:placetype":"venue"
},
  "geometry": {"coordinates":[-64.804237,46.099735],"type":"Point"}
}