{
  "type": "Feature",
  "properties": {
    "addr:full":"3212 115 St NW Edmonton AB T6J 3H8",
    "addr:housenumber":"3212",
    "addr:postcode":"t6j 3h8",
    "addr:street":"115 St Nw",
    "iso:country":"CA",
    "sg:address":"3212 115 St NW",
    "sg:city":"Edmonton",
    "sg:classifiers":[
        {
            "category":"Wholesale",
            "subcategory":"Durable Goods & Equipment",
            "type":"Manufacturing & Wholesale Goods"
        }
    ],
    "sg:phone":"+1 780 430 0330",
    "sg:postcode":"T6J 3H8",
    "sg:province":"AB",
    "sg:tags":[
        "representative",
        "manufacturer"
    ],
    "wof:name":"Technalines Mfr's Agency",
    "wof:placetype":"venue"
},
  "geometry": {"coordinates":[-113.531677,53.464531],"type":"Point"}
}