{
  "type": "Feature",
  "properties": {
    "addr:full":"15 Central Ave E Brockville ON K6V 1W5",
    "addr:housenumber":"15",
    "addr:postcode":"k6v 1w5",
    "addr:street":"Central Ave E",
    "iso:country":"CA",
    "sg:address":"15 Central Ave E",
    "sg:city":"Brockville",
    "sg:classifiers":[
        {
            "category":"Shopping",
            "subcategory":"Books",
            "type":"Retail Goods"
        }
    ],
    "sg:phone":"+1 613 345 2122",
    "sg:postcode":"K6V 1W5",
    "sg:province":"ON",
    "sg:tags":[
        "religious"
    ],
    "wof:name":"Searchlight Book Store",
    "wof:placetype":"venue"
},
  "geometry": {"coordinates":[-75.68937683110001,44.6017723083],"type":"Point"}
}