{
  "type": "Feature",
  "properties": {
    "iso:country":"CA",
    "sg:address":"3901 Huron Church Line Rd",
    "sg:city":"Windsor",
    "sg:classifiers":[
        {
            "category":"Recreation",
            "type":"Entertainment"
        }
    ],
    "sg:phone":"+1 519 966 7625",
    "sg:postcode":"N9H 1G7",
    "sg:province":"ON",
    "sg:tags":[
        "amusement"
    ],
    "wof:name":"Gibraltar Climbing CO",
    "wof:placetype":"venue"
},
  "geometry": {"coordinates":[-83.033577,42.249691],"type":"Point"}
}