{
  "type": "Feature",
  "properties": {
    "addr:full":"Kleinburg ON L0J 1C0",
    "addr:postcode":"l0j 1c0",
    "iso:country":"CA",
    "sg:city":"Kleinburg",
    "sg:classifiers":[
        {
            "category":"Farming",
            "subcategory":"Farm & Veterinary Services",
            "type":"Manufacturing & Wholesale Goods"
        }
    ],
    "sg:phone":"+1 905 951 9333",
    "sg:postcode":"L0J 1C0",
    "sg:province":"ON",
    "sg:tags":[
        "control",
        "weed"
    ],
    "wof:name":"Lawn Medics",
    "wof:placetype":"venue"
},
  "geometry": {"coordinates":[-79.70974699999999,43.872971],"type":"Point"}
}