{
  "type": "Feature",
  "properties": {
    "addr:full":"York ON M6N 4B3",
    "addr:postcode":"m6n 4b3",
    "iso:country":"CA",
    "sg:city":"York",
    "sg:classifiers":[
        {
            "category":"Health Services",
            "subcategory":"Doctor",
            "type":"Services"
        }
    ],
    "sg:phone":"+1 416 767 7017",
    "sg:postcode":"M6N 4B3",
    "sg:province":"ON",
    "sg:tags":[
        "physician",
        "surgeon"
    ],
    "wof:name":"Chiu, B Y MD",
    "wof:placetype":"venue"
},
  "geometry": {"coordinates":[-79.4931182861,43.6706504822],"type":"Point"}
}