{
  "type": "Feature",
  "properties": {
    "addr:full":"219 Main St E Langham SK S0K 2L0",
    "addr:housenumber":"219",
    "addr:postcode":"s0k 2l0",
    "addr:street":"Main St E",
    "iso:country":"CA",
    "sg:address":"219 Main St E",
    "sg:city":"Langham",
    "sg:classifiers":[
        {
            "category":"Professional",
            "subcategory":"Management & Consulting",
            "type":"Services"
        }
    ],
    "sg:phone":"+1 306 283 4496",
    "sg:postcode":"S0K 2L0",
    "sg:province":"SK",
    "sg:tags":[
        "fire",
        "equipment",
        "protection",
        "safety",
        "consultant"
    ],
    "wof:name":"Trans-Care",
    "wof:placetype":"venue"
},
  "geometry": {"coordinates":[-106.958190918,52.3611793518],"type":"Point"}
}