{
  "type": "Feature",
  "properties": {
    "addr:full":"114 Dunlop St E Barrie ON L4M 1A4",
    "addr:housenumber":"114",
    "addr:postcode":"l4m 1a4",
    "addr:street":"Dunlop St E",
    "iso:country":"CA",
    "sg:address":"114 Dunlop St E",
    "sg:city":"Barrie",
    "sg:classifiers":[
        {
            "category":"Shopping",
            "subcategory":"Stationery & Office Supplies",
            "type":"Retail Goods"
        }
    ],
    "sg:phone":"+1 705 726 6602",
    "sg:postcode":"L4M 1A4",
    "sg:province":"ON",
    "wof:name":"Grand & Toy",
    "wof:placetype":"venue"
},
  "geometry": {"coordinates":[-79.68602752690001,44.3894424438],"type":"Point"}
}