{
  "type": "Feature",
  "properties": {
    "iso:country":"CA",
    "sg:address":"1199 Grant St",
    "sg:city":"Vancouver",
    "sg:classifiers":[
        {
            "category":"Wholesale",
            "subcategory":"Electrical",
            "type":"Manufacturing & Wholesale Goods"
        }
    ],
    "sg:phone":"+1 604 253 2422",
    "sg:postcode":"V6A 2J7",
    "sg:province":"BC",
    "sg:tags":[
        "meter"
    ],
    "wof:name":"West Coast Meter Svc",
    "wof:placetype":"venue"
},
  "geometry": {"coordinates":[-123.07866668699999,49.2716598511],"type":"Point"}
}