{
  "type": "Feature",
  "properties": {
    "addr:full":"Debden SK S0J 0S0",
    "addr:postcode":"s0j 0s0",
    "addr:street":"Debden",
    "iso:country":"CA",
    "sg:city":"Debden",
    "sg:classifiers":[
        {
            "category":"Social Services",
            "subcategory":"Child Care",
            "type":"Services"
        }
    ],
    "sg:phone":"+1 306 724 4410",
    "sg:postcode":"S0J 0S0",
    "sg:province":"SK",
    "wof:name":"Big River 1st Nations Day Care",
    "wof:placetype":"venue"
},
  "geometry": {"coordinates":[-106.878227,53.527225],"type":"Point"}
}