{
  "type": "Feature",
  "properties": {
    "addr:full":"17 Mary Walk Elliot Lake ON P5A 1Z9",
    "addr:housenumber":"17",
    "addr:postcode":"p5a 1z9",
    "addr:street":"Mary Walk",
    "iso:country":"CA",
    "sg:address":"17 Mary Walk",
    "sg:city":"Elliot Lake",
    "sg:classifiers":[
        {
            "category":"Banks & Credit Unions",
            "subcategory":"Bank",
            "type":"Services"
        }
    ],
    "sg:phone":"+1 705 848 2211",
    "sg:postcode":"P5A 1Z9",
    "sg:province":"ON",
    "wof:name":"Bank of Montreal",
    "wof:placetype":"venue"
},
  "geometry": {"coordinates":[-82.649055,46.386948],"type":"Point"}
}