{
  "type": "Feature",
  "properties": {
    "addr:full":"617 3rd Ave W Prince Rupert BC V8J 1M3",
    "addr:housenumber":"617",
    "addr:postcode":"v8j 1m3",
    "addr:street":"3Rd Ave W",
    "iso:country":"CA",
    "sg:address":"617 3rd Ave W",
    "sg:city":"Prince Rupert",
    "sg:classifiers":[
        {
            "category":"Food & Beverages",
            "subcategory":"Bakery",
            "type":"Retail Goods"
        }
    ],
    "sg:phone":"+1 250 624 4031",
    "sg:postcode":"V8J 1M3",
    "sg:province":"BC",
    "sg:tags":[
        "baker"
    ],
    "wof:name":"Baker Boy",
    "wof:placetype":"venue"
},
  "geometry": {"coordinates":[-130.32673600000001,54.311367],"type":"Point"}
}