{
  "type": "Feature",
  "properties": {
    "addr:full":"200 Tuxedo Ave Winnipeg MB R3P 0R3",
    "addr:housenumber":"200",
    "addr:postcode":"r3p 0r3",
    "addr:street":"Tuxedo Ave",
    "iso:country":"CA",
    "sg:address":"200 Tuxedo Ave",
    "sg:city":"Winnipeg",
    "sg:classifiers":[
        {
            "category":"Real Estate",
            "subcategory":"Real Estate Operator",
            "type":"Services"
        }
    ],
    "sg:phone":"+1 204 489 7820",
    "sg:postcode":"R3P 0R3",
    "sg:province":"MB",
    "sg:tags":[
        "condominium"
    ],
    "wof:name":"200 Tuxedo Boulevard",
    "wof:placetype":"venue"
},
  "geometry": {"coordinates":[-97.214142,49.86776],"type":"Point"}
}