{
  "type": "Feature",
  "properties": {
    "iso:country":"CA",
    "sg:city":"North Gower",
    "sg:classifiers":[
        {
            "category":"Shopping",
            "subcategory":"Computers & Home Electronics",
            "type":"Retail Goods"
        }
    ],
    "sg:phone":"+1 613 489 1632",
    "sg:postcode":"K0A 2T0",
    "sg:province":"ON",
    "sg:tags":[
        "supply",
        "parts",
        "software"
    ],
    "wof:name":"Qrx Technology Group",
    "wof:placetype":"venue"
},
  "geometry": {"coordinates":[-75.71337890620001,45.1366348267],"type":"Point"}
}