{
  "type": "Feature",
  "properties": {
    "iso:country":"CA",
    "sg:address":"111 Martindale Rd",
    "sg:city":"St Catharines",
    "sg:classifiers":[
        {
            "category":"Health Services",
            "subcategory":"Doctor",
            "type":"Services"
        }
    ],
    "sg:phone":"+1 905 685 0000",
    "sg:postcode":"L2S 2X5",
    "sg:province":"ON",
    "sg:tags":[
        "dentist"
    ],
    "wof:name":"Kumar, Ravinder V DDS",
    "wof:placetype":"venue"
},
  "geometry": {"coordinates":[-79.268341,43.165394],"type":"Point"}
}