{
  "type": "Feature",
  "properties": {
    "addr:full":"Saint-Michel QC J0L 2J0",
    "addr:postcode":"j0l 2j0",
    "iso:country":"CA",
    "sg:city":"Saint-Michel",
    "sg:classifiers":[
        {
            "category":"Social Services",
            "subcategory":"Child Care",
            "type":"Services"
        }
    ],
    "sg:phone":"+1 450 454 5957",
    "sg:postcode":"J0L 2J0",
    "sg:province":"QC",
    "sg:tags":[
        "kindergarten",
        "academic",
        "school"
    ],
    "wof:name":"Choupettes",
    "wof:placetype":"venue"
},
  "geometry": {"coordinates":[-73.5709609985,45.2346038818],"type":"Point"}
}