{
  "type": "Feature",
  "properties": {
    "addr:full":"190 Nelson St W Virden MB R0M 2C0",
    "addr:housenumber":"190",
    "addr:postcode":"r0m 2c0",
    "addr:street":"Nelson St W Virden",
    "iso:country":"CA",
    "sg:address":"190 Nelson St W",
    "sg:city":"Virden",
    "sg:classifiers":[
        {
            "category":"Banks & Credit Unions",
            "subcategory":"Bank",
            "type":"Services"
        }
    ],
    "sg:phone":"+1 204 748 2251",
    "sg:postcode":"R0M 2C0",
    "sg:province":"MB",
    "wof:name":"Scotiabank",
    "wof:placetype":"venue"
},
  "geometry": {"coordinates":[-100.91971599999999,49.856026],"type":"Point"}
}