{
  "type": "Feature",
  "properties": {
    "addr:full":"4265 Barton Cres Windsor ON N9G 2Z1",
    "addr:housenumber":"4265",
    "addr:postcode":"n9g 2z1",
    "addr:street":"Barton Cres",
    "iso:country":"CA",
    "sg:address":"4265 Barton Cres",
    "sg:city":"Windsor",
    "sg:classifiers":[
        {
            "category":"Restaurant",
            "type":"Food & Drink"
        }
    ],
    "sg:phone":"+1 519 966 7005",
    "sg:postcode":"N9G 2Z1",
    "sg:province":"ON",
    "sg:tags":[
        "caterer"
    ],
    "wof:name":"Giovanna Fine Catering",
    "wof:placetype":"venue"
},
  "geometry": {"coordinates":[-82.9809875488,42.2484092712],"type":"Point"}
}