{
  "type": "Feature",
  "properties": {
    "addr:full":"8615 Rue Du Creusot Saint-Leonard QC H1P 2A8",
    "addr:housenumber":"8615",
    "addr:postcode":"h1p 2a8",
    "addr:street":"Rue Du Creusot",
    "iso:country":"CA",
    "sg:address":"8615 Rue Du Creusot",
    "sg:city":"Saint-Leonard",
    "sg:classifiers":[
        {
            "category":"Airline",
            "type":"Transportation"
        }
    ],
    "sg:phone":"+1 514 324 3910",
    "sg:postcode":"H1P 2A8",
    "sg:province":"QC",
    "sg:tags":[
        "paint",
        "company"
    ],
    "wof:name":"Distribution Morello Inc",
    "wof:placetype":"venue"
},
  "geometry": {"coordinates":[-73.589348,45.601219],"type":"Point"}
}