{
  "type": "Feature",
  "properties": {
    "addr:full":"85 Macdonell St Guelph ON N1H 2Z7",
    "addr:housenumber":"85",
    "addr:postcode":"n1h 2z7",
    "addr:street":"Macdonell St",
    "iso:country":"CA",
    "sg:address":"85 Macdonell St",
    "sg:city":"Guelph",
    "sg:classifiers":[
        {
            "category":"Shopping",
            "subcategory":"Music",
            "type":"Retail Goods"
        }
    ],
    "sg:phone":"+1 519 829 2020",
    "sg:postcode":"N1H 2Z7",
    "sg:province":"ON",
    "sg:tags":[
        "compact",
        "record",
        "disc",
        "tape"
    ],
    "wof:name":"Well Charged Music",
    "wof:placetype":"venue"
},
  "geometry": {"coordinates":[-80.24723052980001,43.5450286865],"type":"Point"}
}