{
  "type": "Feature",
  "properties": {
    "addr:full":"7421 East Saanich Rd Saanichton BC V8M 1W2",
    "addr:housenumber":"7421",
    "addr:postcode":"v8m 1w2",
    "addr:street":"East Saanich Rd",
    "iso:country":"CA",
    "sg:address":"7421 East Saanich Rd",
    "sg:city":"Saanichton",
    "sg:classifiers":[
        {
            "category":"Farming",
            "subcategory":"Farm",
            "type":"Manufacturing & Wholesale Goods"
        }
    ],
    "sg:phone":"+1 250 652 5344",
    "sg:postcode":"V8M 1W2",
    "sg:province":"BC",
    "wof:name":"Heritage Valley Farm",
    "wof:placetype":"venue"
},
  "geometry": {"coordinates":[-123.41928900000001,48.588718],"type":"Point"}
}