{
  "type": "Feature",
  "properties": {
    "iso:country":"CA",
    "sg:address":"447 Brunswick St",
    "sg:city":"Stratford",
    "sg:classifiers":[
        {
            "category":"Professional",
            "subcategory":"Accounting & Tax Preparation",
            "type":"Services"
        }
    ],
    "sg:phone":"+1 519 272 1170",
    "sg:postcode":"N5A 3N5",
    "sg:province":"ON",
    "sg:tags":[
        "accountant"
    ],
    "wof:name":"Johns, David G CA",
    "wof:placetype":"venue"
},
  "geometry": {"coordinates":[-80.9638290405,43.3692626953],"type":"Point"}
}