{
  "type": "Feature",
  "properties": {
    "addr:full":"2040 Rte York Saint-Cuthbert QC J0K 2C0",
    "addr:housenumber":"2040",
    "addr:postcode":"j0k 2c0",
    "addr:street":"Rte York",
    "iso:country":"CA",
    "sg:address":"2040 Rte York",
    "sg:city":"Saint-Cuthbert",
    "sg:classifiers":[
        {
            "category":"Travel",
            "subcategory":"Hotels & Motels",
            "type":"Entertainment"
        }
    ],
    "sg:phone":"+1 450 885 1530",
    "sg:postcode":"J0K 2C0",
    "sg:province":"QC",
    "sg:tags":[
        "breakfast",
        "accommodation",
        "bed"
    ],
    "wof:name":"L'Hibiscus",
    "wof:placetype":"venue"
},
  "geometry": {"coordinates":[-73.178802,46.156864],"type":"Point"}
}