{
  "type": "Feature",
  "properties": {
    "addr:full":"2404 4 St NW Calgary AB T2M 2Z7",
    "addr:housenumber":"2404 4",
    "addr:postcode":"t2m 2z7",
    "addr:street":"St Nw",
    "iso:country":"CA",
    "sg:address":"2404 4 St NW",
    "sg:city":"Calgary",
    "sg:classifiers":[
        {
            "category":"Retail",
            "subcategory":"Auto Repair",
            "type":"Services"
        }
    ],
    "sg:phone":"+1 403 276 6669",
    "sg:postcode":"T2M 2Z7",
    "sg:province":"AB",
    "sg:tags":[
        "repairing",
        "automobile"
    ],
    "wof:name":"Leader Tire & Auto Repair Ltd",
    "wof:placetype":"venue"
},
  "geometry": {"coordinates":[-114.07132,51.073406],"type":"Point"}
}