{
  "type": "Feature",
  "properties": {
    "addr:full":"7284 Cypress St Vancouver BC V6P 5M3",
    "addr:housenumber":"7284",
    "addr:postcode":"v6p 5m3",
    "addr:street":"Cypress St",
    "iso:country":"CA",
    "sg:address":"7284 Cypress St",
    "sg:city":"Vancouver",
    "sg:classifiers":[
        {
            "category":"Social Services",
            "subcategory":"Child Care",
            "type":"Services"
        }
    ],
    "sg:phone":"+1 604 261 4315",
    "sg:postcode":"V6P 5M3",
    "sg:province":"BC",
    "wof:name":"Stepping Stone Pre-School",
    "wof:placetype":"venue"
},
  "geometry": {"coordinates":[-123.149398804,49.2198295593],"type":"Point"}
}