{
  "type": "Feature",
  "properties": {
    "addr:full":"188 1/2 Charlotte St Peterborough ON K9J 2T8",
    "addr:housenumber":"188 1 / 2",
    "addr:postcode":"k9j 2t8",
    "addr:street":"Charlotte St",
    "iso:country":"CA",
    "sg:address":"188 1/2 Charlotte St",
    "sg:city":"Peterborough",
    "sg:classifiers":[
        {
            "category":"Retail",
            "subcategory":"Portrait Studio",
            "type":"Services"
        }
    ],
    "sg:phone":"+1 705 742 2062",
    "sg:postcode":"K9J 2T8",
    "sg:province":"ON",
    "sg:tags":[
        "photographic",
        "supply"
    ],
    "wof:name":"Peterborough Photo Svc",
    "wof:placetype":"venue"
},
  "geometry": {"coordinates":[-78.3215179443,44.3034973145],"type":"Point"}
}