{
  "type": "Feature",
  "properties": {
    "iso:country":"CA",
    "sg:city":"Brooks",
    "sg:classifiers":[
        {
            "category":"Wholesale",
            "subcategory":"Machinery & Supplies",
            "type":"Manufacturing & Wholesale Goods"
        }
    ],
    "sg:phone":"+1 403 362 6208",
    "sg:postcode":"T1R 0M9",
    "sg:province":"AB",
    "sg:tags":[
        "bearing",
        "implement",
        "agricultural"
    ],
    "wof:name":"Bomart Enterprises Ltd",
    "wof:placetype":"venue"
},
  "geometry": {"coordinates":[-111.891326904,50.575088501],"type":"Point"}
}