{
  "type": "Feature",
  "properties": {
    "iso:country":"CA",
    "sg:city":"Winnipeg",
    "sg:classifiers":[
        {
            "category":"Shopping",
            "subcategory":"Gifts & Souvenirs",
            "type":"Retail Goods"
        }
    ],
    "sg:phone":"+1 204 661 8137",
    "sg:postcode":"R2C 4J2",
    "sg:province":"MB",
    "sg:tags":[
        "shop",
        "engraver"
    ],
    "wof:name":"Key Man Engravables",
    "wof:placetype":"venue"
},
  "geometry": {"coordinates":[-97.061989,49.897373],"type":"Point"}
}