{
  "type": "Feature",
  "properties": {
    "addr:full":"290 Edgepark Blvd NW Calgary AB T3A 4H4",
    "addr:housenumber":"290",
    "addr:postcode":"t3a 4h4",
    "addr:street":"Edgepark Blvd Nw",
    "iso:country":"CA",
    "sg:address":"290 Edgepark Blvd NW",
    "sg:city":"Calgary",
    "sg:classifiers":[
        {
            "category":"Organizations",
            "subcategory":"Religious Organization",
            "type":"Services"
        }
    ],
    "sg:phone":"+1 403 241 1443",
    "sg:postcode":"T3A 4H4",
    "sg:province":"AB",
    "sg:tags":[
        "church"
    ],
    "wof:name":"Westminster Presbyterian Chr",
    "wof:placetype":"venue"
},
  "geometry": {"coordinates":[-114.15712000000001,51.135128],"type":"Point"}
}