{
  "type": "Feature",
  "properties": {
    "iso:country":"CA",
    "sg:address":"1912 Ch Gascon",
    "sg:city":"Terrebonne",
    "sg:classifiers":[
        {
            "category":"Food & Beverages",
            "subcategory":"Groceries & Convenience Stores",
            "type":"Retail Goods"
        }
    ],
    "sg:phone":"+1 450 961 4971",
    "sg:postcode":"J6X 2E4",
    "sg:province":"QC",
    "wof:name":"Depanneur Gascon",
    "wof:placetype":"venue"
},
  "geometry": {"coordinates":[-73.65808105470001,45.7190551758],"type":"Point"}
}