{
  "type": "Feature",
  "properties": {
    "iso:country":"CA",
    "sg:address":"379 Oliver Rd",
    "sg:city":"Thunder Bay",
    "sg:classifiers":[
        {
            "category":"Restaurant",
            "type":"Food & Drink"
        }
    ],
    "sg:phone":"+1 807 344 6761",
    "sg:postcode":"P7B 2G1",
    "sg:province":"ON",
    "wof:name":"Kangas Sauna Ltd",
    "wof:placetype":"venue"
},
  "geometry": {"coordinates":[-89.2378997803,48.4290542603],"type":"Point"}
}