{
  "type": "Feature",
  "properties": {
    "iso:country":"CA",
    "sg:address":"17 Pullman Crt",
    "sg:city":"Scarborough",
    "sg:classifiers":[
        {
            "category":"Wholesale",
            "subcategory":"Furniture",
            "type":"Manufacturing & Wholesale Goods"
        }
    ],
    "sg:phone":"+1 416 297 1645",
    "sg:postcode":"M1X 1E4",
    "sg:province":"ON",
    "wof:name":"Ticana Furnishings Inc",
    "wof:placetype":"venue"
},
  "geometry": {"coordinates":[-79.2378997803,43.8207321167],"type":"Point"}
}