{
  "type": "Feature",
  "properties": {
    "iso:country":"CA",
    "sg:city":"Toronto",
    "sg:classifiers":[
        {
            "category":"Food & Beverages",
            "subcategory":"Specialty",
            "type":"Retail Goods"
        }
    ],
    "sg:phone":"+1 416 968 1225",
    "sg:postcode":"M4T 1Y4",
    "sg:province":"ON",
    "sg:tags":[
        "health",
        "diet"
    ],
    "wof:name":"Health Shoppe",
    "wof:placetype":"venue"
},
  "geometry": {"coordinates":[-79.3932723999,43.686630249],"type":"Point"}
}