{
  "type": "Feature",
  "properties": {
    "addr:full":"42 Hwy 358 Port Williams NS B0P 1T0",
    "addr:postcode":"b0p 1t0",
    "addr:street":"42 Hwy 358",
    "iso:country":"CA",
    "sg:address":"42 Hwy 358",
    "sg:city":"Port Williams",
    "sg:classifiers":[
        {
            "category":"Wholesale",
            "subcategory":"Fruits & Vegetables",
            "type":"Manufacturing & Wholesale Goods"
        }
    ],
    "sg:phone":"+1 902 542 2263",
    "sg:postcode":"B0P 1T0",
    "sg:province":"NS",
    "wof:name":"Agri-Growers Ltd",
    "wof:placetype":"venue"
},
  "geometry": {"coordinates":[-64.421494,45.104347],"type":"Point"}
}