{
  "type": "Feature",
  "properties": {
    "iso:country":"CA",
    "sg:city":"Richmond",
    "sg:classifiers":[
        {
            "category":"Personal",
            "subcategory":"Beauty Salon",
            "type":"Services"
        }
    ],
    "sg:phone":"+1 604 277 3936",
    "sg:postcode":"V7C 1V2",
    "sg:province":"BC",
    "wof:name":"Seafair Hair Salon",
    "wof:placetype":"venue"
},
  "geometry": {"coordinates":[-123.18145,49.149433],"type":"Point"}
}