{
  "type": "Feature",
  "properties": {
    "addr:full":"931 Queenston Rd Stoney Creek ON L8G 1B8",
    "addr:housenumber":"931",
    "addr:postcode":"l8g 1b8",
    "addr:street":"Queenston Rd",
    "iso:country":"CA",
    "sg:address":"931 Queenston Rd",
    "sg:city":"Stoney Creek",
    "sg:classifiers":[
        {
            "category":"Home & Garden",
            "subcategory":"Furniture",
            "type":"Retail Goods"
        }
    ],
    "sg:phone":"+1 905 662 0538",
    "sg:postcode":"L8G 1B8",
    "sg:province":"ON",
    "wof:name":"Outlet Furniture Liquidation",
    "wof:placetype":"venue"
},
  "geometry": {"coordinates":[-79.753777,43.225792],"type":"Point"}
}