{
  "type": "Feature",
  "properties": {
    "addr:full":"372 Barrie Rd Orillia ON L3V 2R9",
    "addr:housenumber":"372",
    "addr:postcode":"l3v 2r9",
    "addr:street":"Barrie Rd",
    "iso:country":"CA",
    "sg:address":"372 Barrie Rd",
    "sg:city":"Orillia",
    "sg:classifiers":[
        {
            "category":"Building & Trades",
            "subcategory":"Construction",
            "type":"Services"
        }
    ],
    "sg:phone":"+1 705 325 8558",
    "sg:postcode":"L3V 2R9",
    "sg:province":"ON",
    "sg:tags":[
        "masonry",
        "contractor"
    ],
    "wof:name":"Reda Masonry",
    "wof:placetype":"venue"
},
  "geometry": {"coordinates":[-79.43489099999999,44.595066],"type":"Point"}
}