{
  "type": "Feature",
  "properties": {
    "addr:full":"1145 Ch Du Petit-Bernier Saint-Jean-Sur-Richelieu QC J3B 6Y8",
    "addr:housenumber":"1145",
    "addr:postcode":"j3b 6y8",
    "addr:street":"Ch Du Petit-Bernier",
    "iso:country":"CA",
    "sg:address":"1145 Ch Du Petit-Bernier",
    "sg:city":"Saint-Jean-Sur-Richelieu",
    "sg:classifiers":[
        {
            "category":"Recreation",
            "type":"Entertainment"
        }
    ],
    "sg:phone":"+1 450 346 3442",
    "sg:postcode":"J3B 6Y8",
    "sg:province":"QC",
    "sg:tags":[
        "auditorium",
        "rooms",
        "banquet",
        "hall"
    ],
    "wof:name":"Erabliere Au Pain DE Sucre",
    "wof:placetype":"venue"
},
  "geometry": {"coordinates":[-73.3069,45.24921],"type":"Point"}
}