{
  "type": "Feature",
  "properties": {
    "addr:full":"306 Gerrard St E Toronto ON M5A 2G7",
    "addr:housenumber":"306",
    "addr:postcode":"m5a 2g7",
    "addr:street":"Gerrard St E",
    "iso:country":"CA",
    "sg:address":"306 Gerrard St E",
    "sg:city":"Toronto",
    "sg:classifiers":[
        {
            "category":"Shopping",
            "subcategory":"Used Merchandise",
            "type":"Retail Goods"
        }
    ],
    "sg:phone":"+1 416 921 3396",
    "sg:postcode":"M5A 2G7",
    "sg:province":"ON",
    "sg:tags":[
        "second",
        "store",
        "hand"
    ],
    "wof:name":"Goodwill Toronto",
    "wof:placetype":"venue"
},
  "geometry": {"coordinates":[-79.3663864136,43.6622161865],"type":"Point"}
}