{
  "type": "Feature",
  "properties": {
    "addr:full":"42 8th Ave W Vancouver BC V5Y 1M7",
    "addr:housenumber":"42",
    "addr:postcode":"v5y 1m7",
    "addr:street":"8Th Ave W",
    "iso:country":"CA",
    "sg:address":"42 8th Ave W",
    "sg:city":"Vancouver",
    "sg:classifiers":[
        {
            "category":"Building & Trades",
            "subcategory":"Construction",
            "type":"Services"
        }
    ],
    "sg:phone":"+1 604 675 9888",
    "sg:postcode":"V5Y 1M7",
    "sg:province":"BC",
    "sg:tags":[
        "general",
        "contractor"
    ],
    "wof:name":"Trasolini Chetner Construction",
    "wof:placetype":"venue"
},
  "geometry": {"coordinates":[-123.105728,49.263653],"type":"Point"}
}