{
  "type": "Feature",
  "properties": {
    "iso:country":"CA",
    "sg:address":"795 Rue Benjamin-Loiseau",
    "sg:city":"Boucherville",
    "sg:classifiers":[
        {
            "category":"Education",
            "subcategory":"School",
            "type":"Public Place"
        }
    ],
    "sg:phone":"+1 450 655 5288",
    "sg:postcode":"J4B 3T3",
    "sg:province":"QC",
    "wof:name":"Ecole Louis H Lafontaine",
    "wof:placetype":"venue"
},
  "geometry": {"coordinates":[-73.449982,45.622173],"type":"Point"}
}