{
  "type": "Feature",
  "properties": {
    "addr:full":"795 Rue Benjamin-Loiseau Boucherville QC J4B 3T3",
    "addr:housenumber":"795",
    "addr:postcode":"j4b 3t3",
    "addr:street":"Rue Benjamin-Loiseau",
    "iso:country":"CA",
    "sg:address":"795 Rue Benjamin-Loiseau",
    "sg:city":"Boucherville",
    "sg:classifiers":[
        {
            "category":"Education",
            "subcategory":"School",
            "type":"Public Place"
        }
    ],
    "sg:phone":"+1 450 655 5288",
    "sg:postcode":"J4B 3T3",
    "sg:province":"QC",
    "wof:name":"Ecole Louis H Lafontaine",
    "wof:placetype":"venue"
},
  "geometry": {"coordinates":[-73.44998200000001,45.622173],"type":"Point"}
}