{
  "type": "Feature",
  "properties": {
    "addr:full":"Surrey BC V4N 4S1",
    "addr:postcode":"v4n 4s1",
    "iso:country":"CA",
    "sg:city":"Surrey",
    "sg:classifiers":[
        {
            "category":"Manufacturing",
            "subcategory":"Tools & Machinery",
            "type":"Manufacturing & Wholesale Goods"
        }
    ],
    "sg:phone":"+1 604 888 3883",
    "sg:postcode":"V4N 4S1",
    "sg:province":"BC",
    "sg:tags":[
        "machine",
        "shop"
    ],
    "wof:name":"Can West Machinery Ltd",
    "wof:placetype":"venue"
},
  "geometry": {"coordinates":[-122.685096741,49.17370224],"type":"Point"}
}