{
  "type": "Feature",
  "properties": {
    "iso:country":"CA",
    "sg:address":"55 Rue Racine O",
    "sg:city":"Chicoutimi",
    "sg:classifiers":[
        {
            "category":"Retail",
            "subcategory":"Auto Repair",
            "type":"Services"
        }
    ],
    "sg:phone":"+1 418 543 9875",
    "sg:postcode":"G7J 1E5",
    "sg:province":"QC",
    "sg:tags":[
        "automobile",
        "electric"
    ],
    "wof:name":"Aubin Auto Electrique Enr",
    "wof:placetype":"venue"
},
  "geometry": {"coordinates":[-71.0667953491,48.4280204773],"type":"Point"}
}