{
  "type": "Feature",
  "properties": {
    "addr:full":"5102 51 St Olds AB T4H 1P5",
    "addr:housenumber":"5102",
    "addr:postcode":"t4h 1p5",
    "addr:street":"51 St",
    "iso:country":"CA",
    "sg:address":"5102 51 St",
    "sg:city":"Olds",
    "sg:classifiers":[
        {
            "category":"Social Services",
            "type":"Services"
        }
    ],
    "sg:phone":"+1 403 556 1000",
    "sg:postcode":"T4H 1P5",
    "sg:province":"AB",
    "sg:tags":[
        "organization",
        "disability",
        "welfare"
    ],
    "wof:name":"Padnoma Support Svc Inc",
    "wof:placetype":"venue"
},
  "geometry": {"coordinates":[-114.10816199999999,51.791767],"type":"Point"}
}