{
  "type": "Feature",
  "properties": {
    "addr:full":"660 Berry St Winnipeg MB R3H 0S5",
    "addr:housenumber":"660",
    "addr:postcode":"r3h 0s5",
    "addr:street":"Berry St",
    "iso:country":"CA",
    "sg:address":"660 Berry St",
    "sg:city":"Winnipeg",
    "sg:classifiers":[
        {
            "category":"Airport",
            "type":"Transportation"
        }
    ],
    "sg:phone":"+1 204 775 8331",
    "sg:postcode":"R3H 0S5",
    "sg:province":"MB",
    "sg:tags":[
        "aircraft",
        "maintenance"
    ],
    "wof:name":"Bristol Aerospace Ltd",
    "wof:placetype":"venue"
},
  "geometry": {"coordinates":[-97.21002197270001,49.8961639404],"type":"Point"}
}