{
  "type": "Feature",
  "properties": {
    "iso:country":"CA",
    "sg:city":"Surrey",
    "sg:classifiers":[
        {
            "category":"Retail",
            "subcategory":"Car Wash",
            "type":"Services"
        }
    ],
    "sg:phone":"+1 604 535 9669",
    "sg:postcode":"V4P 1H5",
    "sg:province":"BC",
    "sg:tags":[
        "automobile",
        "detail",
        "clean"
    ],
    "wof:name":"Classic Auto Stylists Ltd",
    "wof:placetype":"venue"
},
  "geometry": {"coordinates":[-122.796653748,49.048286438],"type":"Point"}
}