{
  "type": "Feature",
  "properties": {
    "addr:full":"445 Cranston Cres Midland ON L4R 1Y1",
    "addr:housenumber":"445",
    "addr:postcode":"l4r 1y1",
    "addr:street":"Cranston Cres",
    "iso:country":"CA",
    "sg:address":"445 Cranston Cres",
    "sg:city":"Midland",
    "sg:classifiers":[
        {
            "category":"Wholesale",
            "subcategory":"Electrical",
            "type":"Manufacturing & Wholesale Goods"
        }
    ],
    "sg:phone":"+1 705 526 6099",
    "sg:postcode":"L4R 1Y1",
    "sg:province":"ON",
    "sg:tags":[
        "fire",
        "equipment",
        "protection"
    ],
    "wof:name":"Target Fire Prevention",
    "wof:placetype":"venue"
},
  "geometry": {"coordinates":[-79.864716,44.728802],"type":"Point"}
}