{
  "type": "Feature",
  "properties": {
    "iso:country":"CA",
    "sg:address":"7777 Boul DE LA Rive-Sud",
    "sg:city":"Levis",
    "sg:classifiers":[
        {
            "category":"Travel",
            "subcategory":"Travel Agent",
            "type":"Entertainment"
        }
    ],
    "sg:phone":"+1 418 833 8423",
    "sg:postcode":"G6V 6Z1",
    "sg:province":"QC",
    "sg:tags":[
        "agency",
        "bureau"
    ],
    "wof:name":"Agence DE Voyages Fascination",
    "wof:placetype":"venue"
},
  "geometry": {"coordinates":[-71.1460952759,46.816204071],"type":"Point"}
}