{
  "type": "Feature",
  "properties": {
    "iso:country":"CA",
    "sg:address":"138 Main St",
    "sg:city":"Ailsa Craig",
    "sg:classifiers":[
        {
            "category":"Building & Trades",
            "subcategory":"Plumbing",
            "type":"Services"
        }
    ],
    "sg:phone":"+1 519 293 3027",
    "sg:postcode":"N0M 1A0",
    "sg:province":"ON",
    "sg:tags":[
        "heating",
        "contractor"
    ],
    "wof:name":"Turnbull's Heating",
    "wof:placetype":"venue"
},
  "geometry": {"coordinates":[-81.53717803959999,43.1477737427],"type":"Point"}
}