{
  "type": "Feature",
  "properties": {
    "iso:country":"CA",
    "sg:address":"45 Mayfair Ave",
    "sg:city":"Dundas",
    "sg:classifiers":[
        {
            "category":"Professional",
            "subcategory":"Accounting & Tax Preparation",
            "type":"Services"
        }
    ],
    "sg:phone":"+1 905 628 2268",
    "sg:postcode":"L9H 3K9",
    "sg:province":"ON",
    "sg:tags":[
        "return",
        "filing"
    ],
    "wof:name":"Castle, David B",
    "wof:placetype":"venue"
},
  "geometry": {"coordinates":[-79.9661865234,43.2600440979],"type":"Point"}
}