{
  "type": "Feature",
  "properties": {
    "addr:full":"66 Louisa St Ottawa ON K1R 6Y8",
    "addr:housenumber":"66",
    "addr:postcode":"k1r 6y8",
    "addr:street":"Louisa St",
    "iso:country":"CA",
    "sg:address":"66 Louisa St",
    "sg:city":"Ottawa",
    "sg:classifiers":[
        {
            "category":"Building & Trades",
            "subcategory":"Construction",
            "type":"Services"
        }
    ],
    "sg:phone":"+1 613 233 2448",
    "sg:postcode":"K1R 6Y8",
    "sg:province":"ON",
    "sg:tags":[
        "general",
        "contractor"
    ],
    "wof:name":"Barry Grace General Cntrctrs",
    "wof:placetype":"venue"
},
  "geometry": {"coordinates":[-75.707291,45.405178],"type":"Point"}
}