{
  "type": "Feature",
  "properties": {
    "iso:country":"CA",
    "sg:address":"3150 Radisson Ave",
    "sg:city":"Windsor",
    "sg:classifiers":[
        {
            "category":"Social Services",
            "type":"Services"
        }
    ],
    "sg:phone":"+1 519 966 7108",
    "sg:postcode":"N9E 1Y5",
    "sg:province":"ON",
    "sg:tags":[
        "youth",
        "organization",
        "center"
    ],
    "wof:name":"Teen Missions Canada Inc",
    "wof:placetype":"venue"
},
  "geometry": {"coordinates":[-83.0159988403,42.2687454224],"type":"Point"}
}