{
  "type": "Feature",
  "properties": {
    "addr:full":"92 Queen St Charlottetown PE C1A 4B1",
    "addr:housenumber":"92",
    "addr:postcode":"c1a 4b1",
    "addr:street":"Queen St",
    "iso:country":"CA",
    "sg:address":"92 Queen St",
    "sg:city":"Charlottetown",
    "sg:classifiers":[
        {
            "category":"Insurance",
            "subcategory":"Insurance Agent",
            "type":"Services"
        }
    ],
    "sg:phone":"+1 902 566 5534",
    "sg:postcode":"C1A 4B1",
    "sg:province":"PE",
    "wof:name":"Peake & Mc Innis Ltd",
    "wof:placetype":"venue"
},
  "geometry": {"coordinates":[-63.1264,46.233227],"type":"Point"}
}