{
  "type": "Feature",
  "properties": {
    "addr:full":"1073 Riverside Dr Fredericton NB E3A 8P9",
    "addr:housenumber":"1073",
    "addr:postcode":"e3a 8p9",
    "addr:street":"Riverside Dr",
    "iso:country":"CA",
    "sg:address":"1073 Riverside Dr",
    "sg:city":"Fredericton",
    "sg:classifiers":[
        {
            "category":"Freight",
            "type":"Transportation"
        }
    ],
    "sg:phone":"+1 506 462 9247",
    "sg:postcode":"E3A 8P9",
    "sg:province":"NB",
    "sg:tags":[
        "commercial",
        "storage"
    ],
    "wof:name":"AAA Storage",
    "wof:placetype":"venue"
},
  "geometry": {"coordinates":[-66.5969161987,45.9275817871],"type":"Point"}
}