{
  "type": "Feature",
  "properties": {
    "addr:full":"8851 Beckwith Rd # 150 Richmond BC V6X 1V4",
    "addr:housenumber":"8851;150",
    "addr:postcode":"v6x 1v4",
    "addr:street":"Beckwith Rd #",
    "iso:country":"CA",
    "sg:address":"8851 Beckwith Rd # 150",
    "sg:city":"Richmond",
    "sg:classifiers":[
        {
            "category":"Wholesale",
            "subcategory":"Seafood",
            "type":"Manufacturing & Wholesale Goods"
        }
    ],
    "sg:phone":"+1 604 244 9936",
    "sg:postcode":"V6X 1V4",
    "sg:province":"BC",
    "wof:name":"Pacific Northwest Shellfish",
    "wof:placetype":"venue"
},
  "geometry": {"coordinates":[-123.126724,49.193958],"type":"Point"}
}