{
  "type": "Feature",
  "properties": {
    "addr:full":"1020 9 Ave SE Calgary AB T2G 0S7",
    "addr:housenumber":"1020",
    "addr:postcode":"t2g 0s7",
    "addr:street":"9 Ave Se",
    "iso:country":"CA",
    "sg:address":"1020 9 Ave SE",
    "sg:city":"Calgary",
    "sg:classifiers":[
        {
            "category":"Retail",
            "subcategory":"Auto Repair",
            "type":"Services"
        }
    ],
    "sg:phone":"+1 403 265 6122",
    "sg:postcode":"T2G 0S7",
    "sg:province":"AB",
    "sg:tags":[
        "body",
        "automobile",
        "painting"
    ],
    "wof:name":"Arrow Carstar Collision",
    "wof:placetype":"venue"
},
  "geometry": {"coordinates":[-114.037918,51.042622],"type":"Point"}
}