{
  "type": "Feature",
  "properties": {
    "iso:country":"CA",
    "sg:address":"629 4th Ave",
    "sg:city":"Carberry",
    "sg:phone":"+1 204 834 3356",
    "sg:postcode":"R0K 0H0",
    "sg:province":"MB",
    "sg:tags":[
        "oil"
    ],
    "wof:name":"Esso",
    "wof:placetype":"venue"
},
  "geometry": {"coordinates":[-99.36019134519999,49.8660545349],"type":"Point"}
}