{
  "type": "Feature",
  "properties": {
    "addr:full":"1251 Wellington Rd London ON N6E 1M4",
    "addr:housenumber":"1251",
    "addr:postcode":"n6e 1m4",
    "addr:street":"Wellington Rd",
    "iso:country":"CA",
    "sg:address":"1251 Wellington Rd",
    "sg:city":"London",
    "sg:classifiers":[
        {
            "category":"Autos & Motor Vehicles",
            "subcategory":"Fuel & Gas Station",
            "type":"Retail Goods"
        }
    ],
    "sg:phone":"+1 519 691 0335",
    "sg:postcode":"N6E 1M4",
    "sg:province":"ON",
    "sg:tags":[
        "oil"
    ],
    "wof:name":"Heather's Esso",
    "wof:placetype":"venue"
},
  "geometry": {"coordinates":[-81.218315,42.926994],"type":"Point"}
}