{
  "type": "Feature",
  "properties": {
    "addr:full":"Repentigny QC J6A 2S5",
    "addr:postcode":"j6a 2s5",
    "iso:country":"CA",
    "sg:city":"Repentigny",
    "sg:classifiers":[
        {
            "category":"Restaurant",
            "type":"Food & Drink"
        }
    ],
    "sg:phone":"+1 450 581 7888",
    "sg:postcode":"J6A 2S5",
    "sg:province":"QC",
    "wof:name":"Restaurant Le Vieux Four",
    "wof:placetype":"venue"
},
  "geometry": {"coordinates":[-73.45317799999999,45.732609],"type":"Point"}
}