{
  "type": "Feature",
  "properties": {
    "addr:full":"958 Garth St Hamilton ON L9C 4L4",
    "addr:housenumber":"958",
    "addr:postcode":"l9c 4l4",
    "addr:street":"Garth St",
    "iso:country":"CA",
    "sg:address":"958 Garth St",
    "sg:city":"Hamilton",
    "sg:classifiers":[
        {
            "category":"Food & Beverages",
            "subcategory":"Groceries & Convenience Stores",
            "type":"Retail Goods"
        }
    ],
    "sg:phone":"+1 905 385 9970",
    "sg:postcode":"L9C 4L4",
    "sg:province":"ON",
    "wof:name":"Big Bee Convenience",
    "wof:placetype":"venue"
},
  "geometry": {"coordinates":[-79.9020614624,43.2309303284],"type":"Point"}
}