{
  "type": "Feature",
  "properties": {
    "iso:country":"CA",
    "sg:address":"2221 Folkestone Way # 101",
    "sg:city":"West Vancouver",
    "sg:classifiers":[
        {
            "category":"Professional",
            "subcategory":"Lawyer & Legal Services",
            "type":"Services"
        }
    ],
    "sg:phone":"+1 604 926 4524",
    "sg:postcode":"V7S 2Y6",
    "sg:province":"BC",
    "sg:tags":[
        "attorney"
    ],
    "wof:name":"Mc Crea & CO",
    "wof:placetype":"venue"
},
  "geometry": {"coordinates":[-123.174423218,49.3449363708],"type":"Point"}
}