{
  "type": "Feature",
  "properties": {
    "addr:full":"21 Merino Rd Peterborough ON K9J 6M8",
    "addr:housenumber":"21",
    "addr:postcode":"k9j 6m8",
    "addr:street":"Merino Rd",
    "iso:country":"CA",
    "sg:address":"21 Merino Rd",
    "sg:city":"Peterborough",
    "sg:classifiers":[
        {
            "category":"Professional",
            "subcategory":"Business Services",
            "type":"Services"
        }
    ],
    "sg:phone":"+1 705 750 4663",
    "sg:postcode":"K9J 6M8",
    "sg:province":"ON",
    "sg:tags":[
        "building",
        "inspection"
    ],
    "wof:name":"Amerispec Home Inspection",
    "wof:placetype":"venue"
},
  "geometry": {"coordinates":[-78.35660552980001,44.3039131165],"type":"Point"}
}