{
  "type": "Feature",
  "properties": {
    "addr:full":"Montreal QC H3A 1H3",
    "addr:postcode":"h3a 1h3",
    "iso:country":"CA",
    "sg:city":"Montreal",
    "sg:classifiers":[
        {
            "category":"Personal",
            "subcategory":"Beauty Salon",
            "type":"Services"
        }
    ],
    "sg:phone":"+1 514 288 6131",
    "sg:postcode":"H3A 1H3",
    "sg:province":"QC",
    "wof:name":"Coupe",
    "wof:placetype":"venue"
},
  "geometry": {"coordinates":[-73.5657501221,45.5215873718],"type":"Point"}
}