{
  "type": "Feature",
  "properties": {
    "addr:full":"5090 Victoria Dr Vancouver BC V5P 3T8",
    "addr:housenumber":"5090",
    "addr:postcode":"v5p 3t8",
    "addr:street":"Victoria Dr",
    "iso:country":"CA",
    "sg:address":"5090 Victoria Dr",
    "sg:city":"Vancouver",
    "sg:classifiers":[
        {
            "category":"Personal",
            "subcategory":"Beauty Salon",
            "type":"Services"
        }
    ],
    "sg:phone":"+1 604 322 5539",
    "sg:postcode":"V5P 3T8",
    "sg:province":"BC",
    "wof:name":"Annie Hair Design & Beauty",
    "wof:placetype":"venue"
},
  "geometry": {"coordinates":[-123.06521600000001,49.238464],"type":"Point"}
}