{
  "type": "Feature",
  "properties": {
    "iso:country":"CA",
    "sg:address":"2562 Av Dalton",
    "sg:city":"Sainte-Foy",
    "sg:classifiers":[
        {
            "category":"Wholesale",
            "subcategory":"Machinery & Supplies",
            "type":"Manufacturing & Wholesale Goods"
        }
    ],
    "sg:phone":"+1 418 652 1611",
    "sg:postcode":"G1P 3S4",
    "sg:province":"QC",
    "sg:tags":[
        "compressor",
        "gas"
    ],
    "wof:name":"Comairco Limitee",
    "wof:placetype":"venue"
},
  "geometry": {"coordinates":[-71.303581,46.790806],"type":"Point"}
}