{
  "type": "Feature",
  "properties": {
    "addr:full":"Scarborough ON M1L 2K6",
    "addr:postcode":"m1l 2k6",
    "iso:country":"CA",
    "sg:city":"Scarborough",
    "sg:classifiers":[
        {
            "category":"Retail",
            "subcategory":"Auto Repair",
            "type":"Services"
        }
    ],
    "sg:phone":"+1 416 285 7511",
    "sg:postcode":"M1L 2K6",
    "sg:province":"ON",
    "sg:tags":[
        "repairing",
        "automobile"
    ],
    "wof:name":"Choice Auto Svc",
    "wof:placetype":"venue"
},
  "geometry": {"coordinates":[-79.2855,43.72718],"type":"Point"}
}