{
  "type": "Feature",
  "properties": {
    "addr:full":"766 9E Rang E Plessisville QC G6L 2Y2",
    "addr:housenumber":"766",
    "addr:postcode":"g6l 2y2",
    "addr:street":"9E Rang E",
    "iso:country":"CA",
    "sg:address":"766 9E Rang E",
    "sg:city":"Plessisville",
    "sg:classifiers":[
        {
            "category":"Food & Beverages",
            "subcategory":"Dairy",
            "type":"Retail Goods"
        }
    ],
    "sg:phone":"+1 819 362 7472",
    "sg:postcode":"G6L 2Y2",
    "sg:province":"QC",
    "sg:tags":[
        "product"
    ],
    "wof:name":"Eco-Delices",
    "wof:placetype":"venue"
},
  "geometry": {"coordinates":[-71.797501,46.184242],"type":"Point"}
}