{
  "type": "Feature",
  "properties": {
    "addr:full":"Red Deer AB T4P 1Y3",
    "addr:postcode":"t4p 1y3",
    "iso:country":"CA",
    "sg:city":"Red Deer",
    "sg:classifiers":[
        {
            "category":"Retail",
            "subcategory":"Auto Repair",
            "type":"Services"
        }
    ],
    "sg:phone":"+1 403 347 7811",
    "sg:postcode":"T4P 1Y3",
    "sg:province":"AB",
    "sg:tags":[
        "repairing",
        "automobile",
        "radiator"
    ],
    "wof:name":"Hi-Tech Radiator Inc",
    "wof:placetype":"venue"
},
  "geometry": {"coordinates":[-113.838127,52.287762],"type":"Point"}
}