{
  "type": "Feature",
  "properties": {
    "addr:full":"1560 Major Oaks Rd Pickering ON L1X 2L3",
    "addr:housenumber":"1560",
    "addr:postcode":"l1x 2l3",
    "addr:street":"Major Oaks Rd",
    "iso:country":"CA",
    "sg:address":"1560 Major Oaks Rd",
    "sg:city":"Pickering",
    "sg:classifiers":[
        {
            "category":"Personal",
            "subcategory":"Beauty Salon",
            "type":"Services"
        }
    ],
    "sg:phone":"+1 905 426 8469",
    "sg:postcode":"L1X 2L3",
    "sg:province":"ON",
    "sg:tags":[
        "manicuring"
    ],
    "wof:name":"Nails & Esthetics By Tina",
    "wof:placetype":"venue"
},
  "geometry": {"coordinates":[-79.0889129639,43.859085083],"type":"Point"}
}