{
  "type": "Feature",
  "properties": {
    "addr:full":"301 Blake St Barrie ON L4M 1K7",
    "addr:housenumber":"301",
    "addr:postcode":"l4m 1k7",
    "addr:street":"Blake St",
    "iso:country":"CA",
    "sg:address":"301 Blake St",
    "sg:city":"Barrie",
    "sg:classifiers":[
        {
            "category":"Shopping",
            "subcategory":"Pharmacy",
            "type":"Retail Goods"
        }
    ],
    "sg:phone":"+1 705 728 2429",
    "sg:postcode":"L4M 1K7",
    "sg:province":"ON",
    "wof:name":"Simcoe Pharmasave",
    "wof:placetype":"venue"
},
  "geometry": {"coordinates":[-79.6583557129,44.3964614868],"type":"Point"}
}