{
  "type": "Feature",
  "properties": {
    "addr:full":"1519 Bayview Ave East York ON M4G 3B5",
    "addr:housenumber":"1519",
    "addr:postcode":"m4g 3b5",
    "addr:street":"Bayview Ave",
    "iso:country":"CA",
    "sg:address":"1519 Bayview Ave",
    "sg:city":"East York",
    "sg:classifiers":[
        {
            "category":"Shopping",
            "subcategory":"Computers & Home Electronics",
            "type":"Retail Goods"
        }
    ],
    "sg:phone":"+1 416 480 9856",
    "sg:postcode":"M4G 3B5",
    "sg:province":"ON",
    "sg:tags":[
        "television",
        "radio"
    ],
    "wof:name":"Aireon Tv Sales & Svc Ltd",
    "wof:placetype":"venue"
},
  "geometry": {"coordinates":[-79.3744888306,43.7045059204],"type":"Point"}
}