{
  "type": "Feature",
  "properties": {
    "addr:full":"1057 Oxford St W Springfield MB R2C 2Z2",
    "addr:housenumber":"1057",
    "addr:postcode":"r2c 2z2",
    "addr:street":"Oxford St W",
    "iso:country":"CA",
    "sg:address":"1057 Oxford St W",
    "sg:city":"Springfield",
    "sg:classifiers":[
        {
            "category":"Freight",
            "type":"Transportation"
        }
    ],
    "sg:phone":"+1 204 222 6566",
    "sg:postcode":"R2C 2Z2",
    "sg:province":"MB",
    "sg:tags":[
        "commercial",
        "storage"
    ],
    "wof:name":"Fort Knox Storage",
    "wof:placetype":"venue"
},
  "geometry": {"coordinates":[-97.00198399999999,49.927418],"type":"Point"}
}