{
  "type": "Feature",
  "properties": {
    "iso:country":"CA",
    "sg:address":"533 2 St SE # 204",
    "sg:city":"Medicine Hat",
    "sg:classifiers":[
        {
            "category":"Professional",
            "subcategory":"Accounting & Tax Preparation",
            "type":"Services"
        }
    ],
    "sg:phone":"+1 403 527 6015",
    "sg:postcode":"T1A 0C5",
    "sg:province":"AB",
    "sg:tags":[
        "accountant"
    ],
    "wof:name":"Darcy S Sackman & CO",
    "wof:placetype":"venue"
},
  "geometry": {"coordinates":[-110.67759700000001,50.039989],"type":"Point"}
}