{
  "type": "Feature",
  "properties": {
    "addr:full":"PO Box 165 Main Brook NL A0K 3N0",
    "addr:housenumber":"po;165",
    "addr:postcode":"a0k 3n0",
    "addr:street":"Box",
    "iso:country":"CA",
    "sg:address":"PO Box 165",
    "sg:city":"Main Brook",
    "sg:classifiers":[
        {
            "category":"Professional",
            "subcategory":"Management & Consulting",
            "type":"Services"
        }
    ],
    "sg:phone":"+1 709 865 3476",
    "sg:postcode":"A0K 3N0",
    "sg:province":"NL",
    "sg:tags":[
        "development",
        "economic",
        "agency"
    ],
    "wof:name":"White Bay Central Development",
    "wof:placetype":"venue"
},
  "geometry": {"coordinates":[-56.0192527771,51.1840324402],"type":"Point"}
}