{
  "type": "Feature",
  "properties": {
    "iso:country":"CA",
    "sg:address":"75 5th Ave",
    "sg:city":"Lillooet",
    "sg:classifiers":[
        {
            "category":"Government",
            "subcategory":"Office",
            "type":"Public Place"
        }
    ],
    "sg:phone":"+1 250 256 4279",
    "sg:postcode":"V0K 1V0",
    "sg:province":"BC",
    "sg:tags":[
        "counselor"
    ],
    "wof:name":"Lillooet Mental Health",
    "wof:placetype":"venue"
},
  "geometry": {"coordinates":[-121.930740356,50.6948204041],"type":"Point"}
}