{
  "type": "Feature",
  "properties": {
    "addr:full":"Uxbridge ON L9P 1S9",
    "addr:postcode":"l9p 1s9",
    "iso:country":"CA",
    "sg:city":"Uxbridge",
    "sg:classifiers":[
        {
            "category":"Building & Trades",
            "subcategory":"Construction",
            "type":"Services"
        }
    ],
    "sg:phone":"+1 905 852 3411",
    "sg:postcode":"L9P 1S9",
    "sg:province":"ON",
    "sg:tags":[
        "designer",
        "dealer",
        "pool",
        "swimming"
    ],
    "wof:name":"Hickling Pools & Spas",
    "wof:placetype":"venue"
},
  "geometry": {"coordinates":[-79.13164500000001,44.092236],"type":"Point"}
}