{
  "type": "Feature",
  "properties": {
    "addr:full":"4670 Rue Sainte-Catherine O Westmount QC H3Z 1S5",
    "addr:housenumber":"4670",
    "addr:postcode":"h3z 1s5",
    "addr:street":"Rue Sainte-Catherine O",
    "iso:country":"CA",
    "sg:address":"4670 Rue Sainte-Catherine O",
    "sg:city":"Westmount",
    "sg:classifiers":[
        {
            "category":"Professional",
            "subcategory":"Advertising",
            "type":"Services"
        }
    ],
    "sg:phone":"+1 514 937 3660",
    "sg:postcode":"H3Z 1S5",
    "sg:province":"QC",
    "sg:tags":[
        "counselor"
    ],
    "wof:name":"Rubinger Communications Inc",
    "wof:placetype":"venue"
},
  "geometry": {"coordinates":[-73.596001,45.478615],"type":"Point"}
}