{
  "type": "Feature",
  "properties": {
    "iso:country":"CA",
    "sg:address":"260 North Front St",
    "sg:city":"Belleville",
    "sg:classifiers":[
        {
            "category":"Restaurant",
            "type":"Food & Drink"
        }
    ],
    "sg:phone":"+1 613 962 5361",
    "sg:postcode":"K8P 3C4",
    "sg:province":"ON",
    "wof:name":"Prime Time Steakhouse",
    "wof:placetype":"venue"
},
  "geometry": {"coordinates":[-77.393737793,44.1825218201],"type":"Point"}
}