{
  "type": "Feature",
  "properties": {
    "addr:full":"680 11E Av Senneterre QC J0Y 2M0",
    "addr:housenumber":"680",
    "addr:postcode":"j0y 2m0",
    "addr:street":"11E Av",
    "iso:country":"CA",
    "sg:address":"680 11E Av",
    "sg:city":"Senneterre",
    "sg:classifiers":[
        {
            "category":"Cinema",
            "subcategory":"Movie Rental",
            "type":"Entertainment"
        }
    ],
    "sg:phone":"+1 819 737 8864",
    "sg:postcode":"J0Y 2M0",
    "sg:province":"QC",
    "sg:tags":[
        "leasing",
        "video",
        "disc",
        "tape"
    ],
    "wof:name":"Videopoint Senneterre Inc",
    "wof:placetype":"venue"
},
  "geometry": {"coordinates":[-77.2453,48.391098],"type":"Point"}
}