{
  "type": "Feature",
  "properties": {
    "addr:full":"135 Rue Saint-Gabriel Saint-Gabriel-DE-Brandon QC J0K 2N0",
    "addr:housenumber":"135",
    "addr:postcode":"j0k 2n0",
    "addr:street":"Rue Saint-Gabriel",
    "iso:country":"CA",
    "sg:address":"135 Rue Saint-Gabriel",
    "sg:city":"Saint-Gabriel-DE-Brandon",
    "sg:classifiers":[
        {
            "category":"Insurance",
            "subcategory":"Insurance Agent",
            "type":"Services"
        }
    ],
    "sg:phone":"+1 450 835 3401",
    "sg:postcode":"J0K 2N0",
    "sg:province":"QC",
    "wof:name":"Assurances H Allard & Fils Inc",
    "wof:placetype":"venue"
},
  "geometry": {"coordinates":[-73.38157653810001,46.2913398743],"type":"Point"}
}