{
  "type": "Feature",
  "properties": {
    "addr:full":"319 George St Winnipegosis MB R0L 2G0",
    "addr:housenumber":"319",
    "addr:postcode":"r0l 2g0",
    "addr:street":"George St",
    "iso:country":"CA",
    "sg:address":"319 George St",
    "sg:city":"Winnipegosis",
    "sg:classifiers":[
        {
            "category":"Wholesale",
            "subcategory":"Machinery & Supplies",
            "type":"Manufacturing & Wholesale Goods"
        }
    ],
    "sg:phone":"+1 204 656 4442",
    "sg:postcode":"R0L 2G0",
    "sg:province":"MB",
    "sg:tags":[
        "farm",
        "equipment"
    ],
    "wof:name":"C Bergen Svc Winnipegosis Ltd",
    "wof:placetype":"venue"
},
  "geometry": {"coordinates":[-99.9255065918,51.6529006958],"type":"Point"}
}