{
  "type": "Feature",
  "properties": {
    "iso:country":"CA",
    "sg:address":"7950 Portage Rd",
    "sg:city":"Niagara Falls",
    "sg:classifiers":[
        {
            "category":"Travel",
            "subcategory":"Hotels & Motels",
            "type":"Entertainment"
        }
    ],
    "sg:phone":"+1 905 295 3569",
    "sg:postcode":"L2G 5Y8",
    "sg:province":"ON",
    "wof:name":"Niagara Falls Motor Lodge",
    "wof:placetype":"venue"
},
  "geometry": {"coordinates":[-79.05582427980001,43.061088562],"type":"Point"}
}