{
  "type": "Feature",
  "properties": {
    "addr:full":"2926 Parsons Rd NW Edmonton AB T6N 1A4",
    "addr:housenumber":"2926",
    "addr:postcode":"t6n 1a4",
    "addr:street":"Parsons Rd Nw",
    "iso:country":"CA",
    "sg:address":"2926 Parsons Rd NW",
    "sg:city":"Edmonton",
    "sg:classifiers":[
        {
            "category":"Manufacturing",
            "subcategory":"Tools & Machinery",
            "type":"Manufacturing & Wholesale Goods"
        }
    ],
    "sg:phone":"+1 780 462 5082",
    "sg:postcode":"T6N 1A4",
    "sg:province":"AB",
    "sg:tags":[
        "equipment",
        "dairy",
        "supply"
    ],
    "wof:name":"Agrai-Dairy Mart Ltd",
    "wof:placetype":"venue"
},
  "geometry": {"coordinates":[-113.484673,53.459461],"type":"Point"}
}