{
  "type": "Feature",
  "properties": {
    "addr:full":"Charlottetown PE C1E 1Z3",
    "addr:postcode":"c1e 1z3",
    "iso:country":"CA",
    "sg:city":"Charlottetown",
    "sg:classifiers":[
        {
            "category":"Building & Trades",
            "subcategory":"Construction",
            "type":"Services"
        }
    ],
    "sg:phone":"+1 902 626 5263",
    "sg:postcode":"C1E 1Z3",
    "sg:province":"PE",
    "sg:tags":[
        "paving",
        "contractor"
    ],
    "wof:name":"Action Paving & Construction",
    "wof:placetype":"venue"
},
  "geometry": {"coordinates":[-63.12817,46.236591],"type":"Point"}
}