{
  "type": "Feature",
  "properties": {
    "addr:full":"10 Wanless Ave Toronto ON M4N 1V6",
    "addr:housenumber":"10",
    "addr:postcode":"m4n 1v6",
    "addr:street":"Wanless Ave",
    "iso:country":"CA",
    "sg:address":"10 Wanless Ave",
    "sg:city":"Toronto",
    "sg:classifiers":[
        {
            "category":"Banks & Credit Unions",
            "subcategory":"Investment Brokerage",
            "type":"Services"
        }
    ],
    "sg:phone":"+1 416 322 9700",
    "sg:postcode":"M4N 1V6",
    "sg:province":"ON",
    "sg:tags":[
        "advisory",
        "financial"
    ],
    "wof:name":"Marchant Securities Inc",
    "wof:placetype":"venue"
},
  "geometry": {"coordinates":[-79.402153,43.726498],"type":"Point"}
}