{
  "type": "Feature",
  "properties": {
    "addr:full":"114 Woodlawn Rd Dartmouth NS B2W 2S7",
    "addr:housenumber":"114",
    "addr:postcode":"b2w 2s7",
    "addr:street":"Woodlawn Rd",
    "iso:country":"CA",
    "sg:address":"114 Woodlawn Rd",
    "sg:city":"Dartmouth",
    "sg:classifiers":[
        {
            "category":"Shopping",
            "subcategory":"Clothing, Apparel, & Fashions",
            "type":"Retail Goods"
        }
    ],
    "sg:phone":"+1 902 434 8512",
    "sg:postcode":"B2W 2S7",
    "sg:province":"NS",
    "wof:name":"Penningtons Superstore",
    "wof:placetype":"venue"
},
  "geometry": {"coordinates":[-63.5305709839,44.6731567383],"type":"Point"}
}