{
  "type": "Feature",
  "properties": {
    "addr:full":"680 Montreal Rd Ottawa ON K1K 0T3",
    "addr:housenumber":"680",
    "addr:postcode":"k1k 0t3",
    "addr:street":"Montreal Rd",
    "iso:country":"CA",
    "sg:address":"680 Montreal Rd",
    "sg:city":"Ottawa",
    "sg:classifiers":[
        {
            "category":"Health Services",
            "subcategory":"Optometrist",
            "type":"Services"
        }
    ],
    "sg:phone":"+1 613 745 7844",
    "sg:postcode":"K1K 0T3",
    "sg:province":"ON",
    "wof:name":"Filion, Brigitte OD",
    "wof:placetype":"venue"
},
  "geometry": {"coordinates":[-75.63964799999999,45.443363],"type":"Point"}
}