{
  "type": "Feature",
  "properties": {
    "addr:full":"383 Ch Brouillard Saint-Georges-DE-Windsor QC J0A 1J0",
    "addr:housenumber":"383",
    "addr:postcode":"j0a 1j0",
    "addr:street":"Ch Brouillard",
    "iso:country":"CA",
    "sg:address":"383 Ch Brouillard",
    "sg:city":"Saint-Georges-DE-Windsor",
    "sg:classifiers":[
        {
            "category":"Retail",
            "subcategory":"Auto Repair",
            "type":"Services"
        }
    ],
    "sg:phone":"+1 819 828 2155",
    "sg:postcode":"J0A 1J0",
    "sg:province":"QC",
    "sg:tags":[
        "repairing",
        "automobile"
    ],
    "wof:name":"Garage Leandre Corriveau Inc",
    "wof:placetype":"venue"
},
  "geometry": {"coordinates":[-71.850616,45.690483],"type":"Point"}
}