{
  "type": "Feature",
  "properties": {
    "addr:full":"2600 Rue Dickson Montreal QC H1N 2J3",
    "addr:housenumber":"2600",
    "addr:postcode":"h1n 2j3",
    "addr:street":"Rue Dickson",
    "iso:country":"CA",
    "sg:address":"2600 Rue Dickson",
    "sg:city":"Montreal",
    "sg:classifiers":[
        {
            "category":"Organizations",
            "subcategory":"Religious Organization",
            "type":"Services"
        }
    ],
    "sg:phone":"+1 514 255 5531",
    "sg:postcode":"H1N 2J3",
    "sg:province":"QC",
    "sg:tags":[
        "church"
    ],
    "wof:name":"Chapelle Evangelique Emmanuel",
    "wof:placetype":"venue"
},
  "geometry": {"coordinates":[-73.539635,45.570244],"type":"Point"}
}