{
  "type": "Feature",
  "properties": {
    "addr:full":"4585 Marine Ave Powell River BC V8A 2K7",
    "addr:housenumber":"4585",
    "addr:postcode":"v8a 2k7",
    "addr:street":"Marine Ave Powell",
    "iso:country":"CA",
    "sg:address":"4585 Marine Ave",
    "sg:city":"Powell River",
    "sg:classifiers":[
        {
            "category":"Retail",
            "subcategory":"Laundry & Dry Cleaning",
            "type":"Services"
        }
    ],
    "sg:phone":"+1 604 485 3998",
    "sg:postcode":"V8A 2K7",
    "sg:province":"BC",
    "sg:tags":[
        "cleaners",
        "rug",
        "carpet"
    ],
    "wof:name":"Great Canadian Carpet Cleaners",
    "wof:placetype":"venue"
},
  "geometry": {"coordinates":[-124.52829,49.840038],"type":"Point"}
}