{
  "type": "Feature",
  "properties": {
    "addr:full":"5130 Boul Metropolitain E Saint-Leonard QC H1S 2V7",
    "addr:housenumber":"5130",
    "addr:postcode":"h1s 2v7",
    "addr:street":"Boul Metropolitain E",
    "iso:country":"CA",
    "sg:address":"5130 Boul Metropolitain E",
    "sg:city":"Saint-Leonard",
    "sg:classifiers":[
        {
            "category":"Food & Beverages",
            "subcategory":"Specialty",
            "type":"Retail Goods"
        }
    ],
    "sg:phone":"+1 514 593 5144",
    "sg:postcode":"H1S 2V7",
    "sg:province":"QC",
    "sg:tags":[
        "water",
        "bulk",
        "company"
    ],
    "wof:name":"Amaro Eau DE Source Naturelle",
    "wof:placetype":"venue"
},
  "geometry": {"coordinates":[-73.590805,45.579628],"type":"Point"}
}