{
  "type": "Feature",
  "properties": {
    "addr:full":"High Prairie AB T0G 1E0",
    "addr:postcode":"t0g 1e0",
    "iso:country":"CA",
    "sg:city":"High Prairie",
    "sg:classifiers":[
        {
            "category":"Organizations",
            "subcategory":"Religious Organization",
            "type":"Services"
        }
    ],
    "sg:phone":"+1 780 523 4830",
    "sg:postcode":"T0G 1E0",
    "sg:province":"AB",
    "sg:tags":[
        "church"
    ],
    "wof:name":"Jehovah Witnesses Congregation",
    "wof:placetype":"venue"
},
  "geometry": {"coordinates":[-116.48042297400001,55.4328842163],"type":"Point"}
}