{
  "type": "Feature",
  "properties": {
    "addr:full":"360 Mountain St Sudbury ON P3B 2T7",
    "addr:housenumber":"360",
    "addr:postcode":"p3b 2t7",
    "addr:street":"Mountain St",
    "iso:country":"CA",
    "sg:address":"360 Mountain St",
    "sg:city":"Sudbury",
    "sg:classifiers":[
        {
            "category":"Manufacturing",
            "subcategory":"Paper Products",
            "type":"Manufacturing & Wholesale Goods"
        }
    ],
    "sg:phone":"+1 705 673 7777",
    "sg:postcode":"P3B 2T7",
    "sg:province":"ON",
    "sg:tags":[
        "packaging",
        "material"
    ],
    "wof:name":"Endurapak Inc",
    "wof:placetype":"venue"
},
  "geometry": {"coordinates":[-80.981041,46.500641],"type":"Point"}
}