{
  "type": "Feature",
  "properties": {
    "addr:full":"211 Hincks St Pembroke ON K8A 4N7",
    "addr:housenumber":"211",
    "addr:postcode":"k8a 4n7",
    "addr:street":"Hincks St",
    "iso:country":"CA",
    "sg:address":"211 Hincks St",
    "sg:city":"Pembroke",
    "sg:classifiers":[
        {
            "category":"Professional",
            "subcategory":"Management & Consulting",
            "type":"Services"
        }
    ],
    "sg:phone":"+1 613 735 7113",
    "sg:postcode":"K8A 4N7",
    "sg:province":"ON",
    "sg:tags":[
        "consultant",
        "safety"
    ],
    "wof:name":"Radsafe Canada Ltd",
    "wof:placetype":"venue"
},
  "geometry": {"coordinates":[-77.12009399999999,45.82375],"type":"Point"}
}