{
  "type": "Feature",
  "properties": {
    "addr:full":"Winnipeg MB R2G 1L8",
    "addr:postcode":"r2g 1l8",
    "iso:country":"CA",
    "sg:city":"Winnipeg",
    "sg:classifiers":[
        {
            "category":"Insurance",
            "subcategory":"Insurance Agent",
            "type":"Services"
        }
    ],
    "sg:phone":"+1 204 989 7696",
    "sg:postcode":"R2G 1L8",
    "sg:province":"MB",
    "wof:name":"Legacy Group Insurance & Fncl",
    "wof:placetype":"venue"
},
  "geometry": {"coordinates":[-97.090271,49.940502],"type":"Point"}
}