{
  "type": "Feature",
  "properties": {
    "iso:country":"CA",
    "sg:address":"2037 Quilchena Ave",
    "sg:city":"Merritt",
    "sg:classifiers":[
        {
            "category":"Shopping",
            "subcategory":"Pharmacy",
            "type":"Retail Goods"
        }
    ],
    "sg:phone":"+1 250 378 2155",
    "sg:postcode":"V1K 1B8",
    "sg:province":"BC",
    "wof:name":"Black's Pharmacy Ltd",
    "wof:placetype":"venue"
},
  "geometry": {"coordinates":[-120.78858184800001,50.1101150513],"type":"Point"}
}