{
  "type": "Feature",
  "properties": {
    "addr:full":"581 Pape Ave Toronto ON M4K 3R5",
    "addr:housenumber":"581",
    "addr:postcode":"m4k 3r5",
    "addr:street":"Pape Ave",
    "iso:country":"CA",
    "sg:address":"581 Pape Ave",
    "sg:city":"Toronto",
    "sg:classifiers":[
        {
            "category":"Restaurant",
            "type":"Food & Drink"
        }
    ],
    "sg:phone":"+1 416 466 6493",
    "sg:postcode":"M4K 3R5",
    "sg:province":"ON",
    "sg:tags":[
        "out",
        "store",
        "variety"
    ],
    "wof:name":"Pape Pizza & Variety",
    "wof:placetype":"venue"
},
  "geometry": {"coordinates":[-79.3431472778,43.6750526428],"type":"Point"}
}