{
  "type": "Feature",
  "properties": {
    "addr:full":"690 Stewart Blvd Brockville ON K6V 7H2",
    "addr:housenumber":"690",
    "addr:postcode":"k6v 7h2",
    "addr:street":"Stewart Blvd",
    "iso:country":"CA",
    "sg:address":"690 Stewart Blvd",
    "sg:city":"Brockville",
    "sg:classifiers":[
        {
            "category":"Autos & Motor Vehicles",
            "subcategory":"Fuel & Gas Station",
            "type":"Retail Goods"
        }
    ],
    "sg:phone":"+1 613 345 6771",
    "sg:postcode":"K6V 7H2",
    "sg:province":"ON",
    "sg:tags":[
        "oil"
    ],
    "wof:name":"Seaway Gas & Fuel Ltd",
    "wof:placetype":"venue"
},
  "geometry": {"coordinates":[-75.72358699999999,44.606884],"type":"Point"}
}