{
  "type": "Feature",
  "properties": {
    "addr:full":"480 Rue Jocelyn-Bastille Pohenegamook QC G0L 1J0",
    "addr:housenumber":"480",
    "addr:postcode":"g0l 1j0",
    "addr:street":"Rue Jocelyn-Bastille Pohenegamook",
    "iso:country":"CA",
    "sg:address":"480 Rue Jocelyn-Bastille",
    "sg:city":"Pohenegamook",
    "sg:classifiers":[
        {
            "category":"Manufacturing",
            "subcategory":"Building Materials",
            "type":"Manufacturing & Wholesale Goods"
        }
    ],
    "sg:phone":"+1 418 893 1515",
    "sg:postcode":"G0L 1J0",
    "sg:province":"QC",
    "wof:name":"Poutrelles Internationales Inc",
    "wof:placetype":"venue"
},
  "geometry": {"coordinates":[-69.1597671509,47.4558296204],"type":"Point"}
}