{
  "type": "Feature",
  "properties": {
    "addr:full":"1731 Stagecoach Rd Greely ON K4P 1H1",
    "addr:housenumber":"1731",
    "addr:postcode":"k4p 1h1",
    "addr:street":"Stagecoach Rd",
    "iso:country":"CA",
    "sg:address":"1731 Stagecoach Rd",
    "sg:city":"Greely",
    "sg:classifiers":[
        {
            "category":"Building & Trades",
            "subcategory":"Construction",
            "type":"Services"
        }
    ],
    "sg:phone":"+1 613 769 2079",
    "sg:postcode":"K4P 1H1",
    "sg:province":"ON",
    "sg:tags":[
        "excavating",
        "contractor"
    ],
    "wof:name":"Colron Excavating",
    "wof:placetype":"venue"
},
  "geometry": {"coordinates":[-75.58131408689999,45.2358169556],"type":"Point"}
}