{
  "type": "Feature",
  "properties": {
    "addr:full":"380 Massachusetts Dr Stephenville NL A2N 3A5",
    "addr:housenumber":"380",
    "addr:postcode":"a2n 3a5",
    "addr:street":"Massachusetts Dr",
    "iso:country":"CA",
    "sg:address":"380 Massachusetts Dr",
    "sg:city":"Stephenville",
    "sg:classifiers":[
        {
            "category":"Arts & Performance",
            "subcategory":"Theater",
            "type":"Entertainment"
        }
    ],
    "sg:phone":"+1 709 643 4553",
    "sg:postcode":"A2N 3A5",
    "sg:province":"NL",
    "sg:tags":[
        "government"
    ],
    "wof:name":"Arts & Culture Ctr",
    "wof:placetype":"venue"
},
  "geometry": {"coordinates":[-58.5634155273,48.5530929565],"type":"Point"}
}