{
  "type": "Feature",
  "properties": {
    "addr:full":"3375 Norland Ave Burnaby BC V5B 3A9",
    "addr:housenumber":"3375",
    "addr:postcode":"v5b 3a9",
    "addr:street":"Norland Ave",
    "iso:country":"CA",
    "sg:address":"3375 Norland Ave",
    "sg:city":"Burnaby",
    "sg:classifiers":[
        {
            "category":"Professional",
            "subcategory":"Engineering",
            "type":"Services"
        }
    ],
    "sg:phone":"+1 604 298 2333",
    "sg:postcode":"V5B 3A9",
    "sg:province":"BC",
    "sg:tags":[
        "engineer"
    ],
    "wof:name":"Vector Engineering Svc Ltd",
    "wof:placetype":"venue"
},
  "geometry": {"coordinates":[-122.975204468,49.2540969849],"type":"Point"}
}