{
  "type": "Feature",
  "properties": {
    "addr:full":"638 7th Ave Keremeos BC V0X 1N0",
    "addr:housenumber":"638",
    "addr:postcode":"v0x 1n0",
    "addr:street":"7Th Ave",
    "iso:country":"CA",
    "sg:address":"638 7th Ave",
    "sg:city":"Keremeos",
    "sg:classifiers":[
        {
            "category":"Real Estate",
            "subcategory":"Real Estate Agent",
            "type":"Services"
        }
    ],
    "sg:phone":"+1 250 499 5327",
    "sg:postcode":"V0X 1N0",
    "sg:province":"BC",
    "wof:name":"Royal Le Page Keremeos",
    "wof:placetype":"venue"
},
  "geometry": {"coordinates":[-119.82431800000001,49.205345],"type":"Point"}
}