{
  "type": "Feature",
  "properties": {
    "addr:full":"1789 Longwoods Rd Wardsville ON N0L 2N0",
    "addr:housenumber":"1789",
    "addr:postcode":"n0l 2n0",
    "addr:street":"Longwoods Rd",
    "iso:country":"CA",
    "sg:address":"1789 Longwoods Rd",
    "sg:city":"Wardsville",
    "sg:classifiers":[
        {
            "category":"Banks & Credit Unions",
            "subcategory":"Bank",
            "type":"Services"
        }
    ],
    "sg:phone":"+1 519 693 9936",
    "sg:postcode":"N0L 2N0",
    "sg:province":"ON",
    "wof:name":"Thamesville Community Cu",
    "wof:placetype":"venue"
},
  "geometry": {"coordinates":[-81.7548675537,42.6553382874],"type":"Point"}
}