{
  "type": "Feature",
  "properties": {
    "iso:country":"CA",
    "sg:address":"30 Hughson St",
    "sg:city":"Orangeville",
    "sg:classifiers":[
        {
            "category":"Building & Trades",
            "subcategory":"Construction",
            "type":"Services"
        }
    ],
    "sg:phone":"+1 519 941 6575",
    "sg:postcode":"L9W 2Z1",
    "sg:province":"ON",
    "sg:tags":[
        "general",
        "contractor"
    ],
    "wof:name":"G Breau Masonry Svc",
    "wof:placetype":"venue"
},
  "geometry": {"coordinates":[-80.093491,43.920116],"type":"Point"}
}