{
  "type": "Feature",
  "properties": {
    "iso:country":"CA",
    "sg:city":"Liverpool",
    "sg:classifiers":[
        {
            "category":"Government",
            "subcategory":"Office",
            "type":"Public Place"
        }
    ],
    "sg:phone":"+1 902 354 6030",
    "sg:postcode":"B0T 1K0",
    "sg:province":"NS",
    "wof:name":"Canada Fisheries & Oceans",
    "wof:placetype":"venue"
},
  "geometry": {"coordinates":[-64.72068023680001,44.0357627869],"type":"Point"}
}