{
  "type": "Feature",
  "properties": {
    "addr:full":"Coaticook QC J1A 2S4",
    "addr:postcode":"j1a 2s4",
    "iso:country":"CA",
    "sg:city":"Coaticook",
    "sg:classifiers":[
        {
            "category":"Organizations",
            "subcategory":"Religious Organization",
            "type":"Services"
        }
    ],
    "sg:phone":"+1 819 849 6884",
    "sg:postcode":"J1A 2S4",
    "sg:province":"QC",
    "sg:tags":[
        "church"
    ],
    "wof:name":"St Luc Presbyteres-Eglises",
    "wof:placetype":"venue"
},
  "geometry": {"coordinates":[-71.817902,45.126293],"type":"Point"}
}