{
  "type": "Feature",
  "properties": {
    "iso:country":"CA",
    "sg:address":"237 Hastings St E",
    "sg:city":"Vancouver",
    "sg:classifiers":[
        {
            "category":"Organizations",
            "subcategory":"Professional Association",
            "type":"Services"
        }
    ],
    "sg:phone":"+1 604 681 7751",
    "sg:postcode":"V6A 1P2",
    "sg:province":"BC",
    "wof:name":"Toi Shan Benevolent Society",
    "wof:placetype":"venue"
},
  "geometry": {"coordinates":[-123.098754883,49.281452179],"type":"Point"}
}