{
  "type": "Feature",
  "properties": {
    "addr:full":"425 Boul Manseau Joliette QC J6E 3C9",
    "addr:housenumber":"425",
    "addr:postcode":"j6e 3c9",
    "addr:street":"Boul Manseau",
    "iso:country":"CA",
    "sg:address":"425 Boul Manseau",
    "sg:city":"Joliette",
    "sg:classifiers":[
        {
            "category":"Insurance",
            "subcategory":"Insurance Agent",
            "type":"Services"
        }
    ],
    "sg:phone":"+1 450 759 3022",
    "sg:postcode":"J6E 3C9",
    "sg:province":"QC",
    "wof:name":"Belair Direct",
    "wof:placetype":"venue"
},
  "geometry": {"coordinates":[-73.439781189,46.0248832703],"type":"Point"}
}