{
  "type": "Feature",
  "properties": {
    "iso:country":"CA",
    "sg:address":"103 Pinetown Pl NE",
    "sg:city":"Calgary",
    "sg:classifiers":[
        {
            "category":"Organizations",
            "subcategory":"Religious Organization",
            "type":"Services"
        }
    ],
    "sg:phone":"+1 403 285 7144",
    "sg:postcode":"T1Y 5J1",
    "sg:province":"AB",
    "sg:tags":[
        "church"
    ],
    "wof:name":"Centennial Presbyterian Church",
    "wof:placetype":"venue"
},
  "geometry": {"coordinates":[-113.95301055900001,51.0751533508],"type":"Point"}
}