{
  "type": "Feature",
  "properties": {
    "addr:full":"Calgary AB T2G 4T8",
    "addr:postcode":"t2g 4t8",
    "iso:country":"CA",
    "sg:city":"Calgary",
    "sg:classifiers":[
        {
            "category":"Wholesale",
            "subcategory":"Photographic Equipment",
            "type":"Manufacturing & Wholesale Goods"
        }
    ],
    "sg:phone":"+1 403 261 9880",
    "sg:postcode":"T2G 4T8",
    "sg:province":"AB",
    "sg:tags":[
        "identification"
    ],
    "wof:name":"International Fingerprinting",
    "wof:placetype":"venue"
},
  "geometry": {"coordinates":[-114.058151,51.047096],"type":"Point"}
}