{
  "type": "Feature",
  "properties": {
    "iso:country":"CA",
    "sg:address":"310 Main St",
    "sg:city":"Wilkie",
    "sg:classifiers":[
        {
            "category":"Organizations",
            "subcategory":"Religious Organization",
            "type":"Services"
        }
    ],
    "sg:phone":"+1 306 843 2363",
    "sg:postcode":"S0K 4W0",
    "sg:province":"SK",
    "sg:tags":[
        "church"
    ],
    "wof:name":"United Church",
    "wof:placetype":"venue"
},
  "geometry": {"coordinates":[-108.71386718799999,52.4060935974],"type":"Point"}
}