{
  "type": "Feature",
  "properties": {
    "addr:full":"PO Box 3603 STN Main Courtenay BC V9N 6Z8",
    "addr:housenumber":"po",
    "addr:postcode":"v9n 6z8",
    "addr:street":"Box 3603 Stn Main",
    "iso:country":"CA",
    "sg:address":"PO Box 3603 STN Main",
    "sg:city":"Courtenay",
    "sg:classifiers":[
        {
            "category":"Utilities",
            "subcategory":"Refuse",
            "type":"Services"
        }
    ],
    "sg:phone":"+1 250 337 1734",
    "sg:postcode":"V9N 6Z8",
    "sg:province":"BC",
    "sg:tags":[
        "garbage",
        "collection"
    ],
    "wof:name":"Sun Coast Waste Svc",
    "wof:placetype":"venue"
},
  "geometry": {"coordinates":[-124.99314099999999,49.686722],"type":"Point"}
}