{
  "type": "Feature",
  "properties": {
    "iso:country":"CA",
    "sg:address":"8000 Av Blaise-Pascal",
    "sg:city":"Montreal",
    "sg:classifiers":[
        {
            "category":"Manufacturing",
            "subcategory":"Printing",
            "type":"Manufacturing & Wholesale Goods"
        }
    ],
    "sg:phone":"+1 514 648 1880",
    "sg:postcode":"H1E 2S7",
    "sg:province":"QC",
    "sg:tags":[
        "printer"
    ],
    "wof:name":"Quebecor World",
    "wof:placetype":"venue"
},
  "geometry": {"coordinates":[-73.58654,45.629246],"type":"Point"}
}