{
  "type": "Feature",
  "properties": {
    "addr:full":"71 Rue Robinson Waterloo QC J0E 2N0",
    "addr:housenumber":"71",
    "addr:postcode":"j0e 2n0",
    "addr:street":"Rue Robinson",
    "iso:country":"CA",
    "sg:address":"71 Rue Robinson",
    "sg:city":"Waterloo",
    "sg:classifiers":[
        {
            "category":"Health Services",
            "subcategory":"Nursing And Care Facility",
            "type":"Services"
        }
    ],
    "sg:phone":"+1 450 539 4865",
    "sg:postcode":"J0E 2N0",
    "sg:province":"QC",
    "sg:tags":[
        "holistic",
        "practitioner"
    ],
    "wof:name":"Bienvenue Au Domaine",
    "wof:placetype":"venue"
},
  "geometry": {"coordinates":[-72.52973175050001,45.3546409607],"type":"Point"}
}