{
  "type": "Feature",
  "properties": {
    "addr:full":"490 York Rd # 100 Guelph ON N1E 6V1",
    "addr:housenumber":"490",
    "addr:postcode":"n1e 6v1",
    "addr:street":"York Rd # 100",
    "iso:country":"CA",
    "sg:address":"490 York Rd # 100",
    "sg:city":"Guelph",
    "sg:classifiers":[
        {
            "category":"Professional",
            "subcategory":"Computer Services",
            "type":"Services"
        }
    ],
    "sg:phone":"+1 519 837 8726",
    "sg:postcode":"N1E 6V1",
    "sg:province":"ON",
    "sg:tags":[
        "repair",
        "dealer",
        "equipment"
    ],
    "wof:name":"Advanced Multi Systems",
    "wof:placetype":"venue"
},
  "geometry": {"coordinates":[-80.224785,43.551308],"type":"Point"}
}