{
  "type": "Feature",
  "properties": {
    "iso:country":"CA",
    "sg:address":"RR 1 STN Main",
    "sg:city":"Cumberland",
    "sg:classifiers":[
        {
            "category":"Building & Trades",
            "subcategory":"Cleaning & Sanitation",
            "type":"Services"
        }
    ],
    "sg:phone":"+1 613 860 0436",
    "sg:postcode":"K4C 1E9",
    "sg:province":"ON",
    "sg:tags":[
        "house"
    ],
    "wof:name":"Clean Living Specialist",
    "wof:placetype":"venue"
},
  "geometry": {"coordinates":[-75.4051361084,45.5159835815],"type":"Point"}
}