{
  "type": "Feature",
  "properties": {
    "addr:full":"1060 Boul DE LA Rive-Sud Saint-Romuald QC G6W 5M6",
    "addr:housenumber":"1060",
    "addr:postcode":"g6w 5m6",
    "addr:street":"Boul De La Rive-Sud",
    "iso:country":"CA",
    "sg:address":"1060 Boul DE LA Rive-Sud",
    "sg:city":"Saint-Romuald",
    "sg:classifiers":[
        {
            "category":"Food & Beverages",
            "subcategory":"Groceries & Convenience Stores",
            "type":"Retail Goods"
        }
    ],
    "sg:phone":"+1 418 834 3811",
    "sg:postcode":"G6W 5M6",
    "sg:province":"QC",
    "sg:tags":[
        "grocer"
    ],
    "wof:name":"Iga Extra",
    "wof:placetype":"venue"
},
  "geometry": {"coordinates":[-71.26908899999999,46.732117],"type":"Point"}
}