{
  "type": "Feature",
  "properties": {
    "addr:full":"6908 82 Ave NW Edmonton AB T6B 0E7",
    "addr:housenumber":"6908",
    "addr:postcode":"t6b 0e7",
    "addr:street":"82 Ave Nw",
    "iso:country":"CA",
    "sg:address":"6908 82 Ave NW",
    "sg:city":"Edmonton",
    "sg:classifiers":[
        {
            "category":"Food & Beverages",
            "subcategory":"Groceries & Convenience Stores",
            "type":"Retail Goods"
        }
    ],
    "sg:phone":"+1 780 465 2255",
    "sg:postcode":"T6B 0E7",
    "sg:province":"AB",
    "sg:tags":[
        "grocer"
    ],
    "wof:name":"Consumer's Choice Home Svc",
    "wof:placetype":"venue"
},
  "geometry": {"coordinates":[-113.434158325,53.5181694031],"type":"Point"}
}