{
  "type": "Feature",
  "properties": {
    "addr:full":"9917 112 St NW Edmonton AB T5K 1L6",
    "addr:housenumber":"9917",
    "addr:postcode":"t5k 1l6",
    "addr:street":"112 St Nw",
    "iso:country":"CA",
    "sg:address":"9917 112 St NW",
    "sg:city":"Edmonton",
    "sg:classifiers":[
        {
            "category":"Professional",
            "subcategory":"Management & Consulting",
            "type":"Services"
        }
    ],
    "sg:phone":"+1 780 944 1122",
    "sg:postcode":"T5K 1L6",
    "sg:province":"AB",
    "sg:tags":[
        "consultant",
        "employment",
        "business",
        "contractor"
    ],
    "wof:name":"Executrade Consultants",
    "wof:placetype":"venue"
},
  "geometry": {"coordinates":[-113.51375579800001,53.5376167297],"type":"Point"}
}