{
  "type": "Feature",
  "properties": {
    "addr:full":"Surrey BC V3V 1N1",
    "addr:postcode":"v3v 1n1",
    "iso:country":"CA",
    "sg:city":"Surrey",
    "sg:classifiers":[
        {
            "category":"Health Services",
            "subcategory":"Doctor",
            "type":"Services"
        }
    ],
    "sg:phone":"+1 604 588 5884",
    "sg:postcode":"V3V 1N1",
    "sg:province":"BC",
    "sg:tags":[
        "physician",
        "surgeon"
    ],
    "wof:name":"Barrio, Sally MD",
    "wof:placetype":"venue"
},
  "geometry": {"coordinates":[-122.830215,49.105179],"type":"Point"}
}