{
  "type": "Feature",
  "properties": {
    "addr:full":"259 Boul Alexis-Nihon Saint-Laurent QC H4M 2A4",
    "addr:housenumber":"259",
    "addr:postcode":"h4m 2a4",
    "addr:street":"Alexis-Nihon Saint-Laurent",
    "iso:country":"CA",
    "sg:address":"259 Boul Alexis-Nihon",
    "sg:city":"Saint-Laurent",
    "sg:classifiers":[
        {
            "category":"Food & Beverages",
            "subcategory":"Groceries & Convenience Stores",
            "type":"Retail Goods"
        }
    ],
    "sg:phone":"+1 514 747 9718",
    "sg:postcode":"H4M 2A4",
    "sg:province":"QC",
    "sg:tags":[
        "grocer"
    ],
    "wof:name":"Panier D'Epicerie",
    "wof:placetype":"venue"
},
  "geometry": {"coordinates":[-73.6792144775,45.4983596802],"type":"Point"}
}