{
  "type": "Feature",
  "properties": {
    "iso:country":"CA",
    "sg:address":"175 Rue Leger",
    "sg:city":"Sherbrooke",
    "sg:classifiers":[
        {
            "category":"Building & Trades",
            "subcategory":"Construction",
            "type":"Services"
        }
    ],
    "sg:phone":"+1 819 564 0115",
    "sg:postcode":"J1L 1M2",
    "sg:province":"QC",
    "sg:tags":[
        "general",
        "contractor"
    ],
    "wof:name":"Construction Longer Inc",
    "wof:placetype":"venue"
},
  "geometry": {"coordinates":[-71.9701766968,45.3918952942],"type":"Point"}
}