{
  "type": "Feature",
  "properties": {
    "addr:full":"New Westminster BC V3M 6H7",
    "addr:postcode":"v3m 6h7",
    "iso:country":"CA",
    "sg:city":"New Westminster",
    "sg:classifiers":[
        {
            "category":"Restaurant",
            "type":"Food & Drink"
        }
    ],
    "sg:phone":"+1 604 527 1194",
    "sg:postcode":"V3M 6H7",
    "sg:province":"BC",
    "wof:name":"Hayashi Sushi",
    "wof:placetype":"venue"
},
  "geometry": {"coordinates":[-122.91860961899999,49.2004165649],"type":"Point"}
}