{
  "type": "Feature",
  "properties": {
    "addr:full":"2 Bloomsgrove Ave Port Hope ON L1A 1X4",
    "addr:housenumber":"2",
    "addr:postcode":"l1a 1x4",
    "addr:street":"Bloomsgrove Ave",
    "iso:country":"CA",
    "sg:address":"2 Bloomsgrove Ave",
    "sg:city":"Port Hope",
    "sg:classifiers":[
        {
            "category":"Food & Beverages",
            "subcategory":"Groceries & Convenience Stores",
            "type":"Retail Goods"
        }
    ],
    "sg:phone":"+1 905 885 5312",
    "sg:postcode":"L1A 1X4",
    "sg:province":"ON",
    "sg:tags":[
        "grocer"
    ],
    "wof:name":"Manna Convenience",
    "wof:placetype":"venue"
},
  "geometry": {"coordinates":[-78.292564,43.956429],"type":"Point"}
}