{
  "type": "Feature",
  "properties": {
    "addr:full":"333 Rue Thibault Matane QC G4W 2W5",
    "addr:housenumber":"333",
    "addr:postcode":"g4w 2w5",
    "addr:street":"Rue Thibault",
    "iso:country":"CA",
    "sg:address":"333 Rue Thibault",
    "sg:city":"Matane",
    "sg:classifiers":[
        {
            "category":"Health Services",
            "subcategory":"Doctor",
            "type":"Services"
        }
    ],
    "sg:phone":"+1 418 562 4022",
    "sg:postcode":"G4W 2W5",
    "sg:province":"QC",
    "sg:tags":[
        "physician",
        "surgeon"
    ],
    "wof:name":"Ouellet, Daniel MD",
    "wof:placetype":"venue"
},
  "geometry": {"coordinates":[-67.523438,48.845074],"type":"Point"}
}