{
  "type": "Feature",
  "properties": {
    "addr:full":"60 Tenth St S Earlton ON P0J 1E0",
    "addr:housenumber":"60",
    "addr:postcode":"p0j 1e0",
    "addr:street":"Tenth St S Earlton",
    "iso:country":"CA",
    "sg:address":"60 Tenth St S",
    "sg:city":"Earlton",
    "sg:classifiers":[
        {
            "category":"Building & Trades",
            "subcategory":"Plumbing",
            "type":"Services"
        }
    ],
    "sg:phone":"+1 705 563 8555",
    "sg:postcode":"P0J 1E0",
    "sg:province":"ON",
    "sg:tags":[
        "air",
        "conditioning",
        "contractor",
        "system",
        "heating"
    ],
    "wof:name":"Earlton Heating",
    "wof:placetype":"venue"
},
  "geometry": {"coordinates":[-79.824585,47.708786],"type":"Point"}
}