{
  "type": "Feature",
  "properties": {
    "addr:full":"4707 Ravine Dr Swan Hills AB T0G 2C0",
    "addr:housenumber":"4707",
    "addr:postcode":"t0g 2c0",
    "addr:street":"Ravine Dr",
    "iso:country":"CA",
    "sg:address":"4707 Ravine Dr",
    "sg:city":"Swan Hills",
    "sg:classifiers":[
        {
            "category":"Education",
            "subcategory":"School",
            "type":"Public Place"
        }
    ],
    "sg:phone":"+1 780 333 4471",
    "sg:postcode":"T0G 2C0",
    "sg:province":"AB",
    "wof:name":"Swan Hills School",
    "wof:placetype":"venue"
},
  "geometry": {"coordinates":[-115.394828796,54.7159194946],"type":"Point"}
}