{
  "type": "Feature",
  "properties": {
    "iso:country":"CA",
    "sg:address":"236 Lewisville Rd",
    "sg:city":"Moncton",
    "sg:classifiers":[
        {
            "category":"Bars & Pubs",
            "type":"Food & Drink"
        }
    ],
    "sg:phone":"+1 506 857 9472",
    "sg:postcode":"E1A 2R5",
    "sg:province":"NB",
    "sg:tags":[
        "lounge",
        "cocktail"
    ],
    "wof:name":"Iceberg Pub",
    "wof:placetype":"venue"
},
  "geometry": {"coordinates":[-64.7660903931,46.1020431519],"type":"Point"}
}