{
  "type": "Feature",
  "properties": {
    "addr:full":"5002 Windsor Ave Coronation AB T0C 1C0",
    "addr:housenumber":"5002",
    "addr:postcode":"t0c 1c0",
    "addr:street":"Windsor Ave",
    "iso:country":"CA",
    "sg:address":"5002 Windsor Ave",
    "sg:city":"Coronation",
    "sg:classifiers":[
        {
            "category":"Shopping",
            "subcategory":"Florist",
            "type":"Retail Goods"
        }
    ],
    "sg:phone":"+1 403 578 3340",
    "sg:postcode":"T0C 1C0",
    "sg:province":"AB",
    "wof:name":"Christie's Plant Mart & Grnhs",
    "wof:placetype":"venue"
},
  "geometry": {"coordinates":[-111.449135,52.0933],"type":"Point"}
}