{
  "type": "Feature",
  "properties": {
    "addr:full":"170 Steel St Barrie ON L4M 2G4",
    "addr:housenumber":"170",
    "addr:postcode":"l4m 2g4",
    "addr:street":"Steel St",
    "iso:country":"CA",
    "sg:address":"170 Steel St",
    "sg:city":"Barrie",
    "sg:classifiers":[
        {
            "category":"Organizations",
            "subcategory":"Religious Organization",
            "type":"Services"
        }
    ],
    "sg:phone":"+1 705 728 0541",
    "sg:postcode":"L4M 2G4",
    "sg:province":"ON",
    "sg:tags":[
        "church"
    ],
    "wof:name":"Westminster Presbyterian",
    "wof:placetype":"venue"
},
  "geometry": {"coordinates":[-79.658485,44.401424],"type":"Point"}
}