{
  "type": "Feature",
  "properties": {
    "addr:full":"RR 1 Selkirk ON N0A 1P0",
    "addr:postcode":"n0a 1p0",
    "addr:street":"Rr 1",
    "iso:country":"CA",
    "sg:address":"RR 1",
    "sg:city":"Selkirk",
    "sg:classifiers":[
        {
            "category":"Museum",
            "type":"Entertainment"
        }
    ],
    "sg:phone":"+1 905 776 3319",
    "sg:postcode":"N0A 1P0",
    "sg:province":"ON",
    "sg:tags":[
        "government"
    ],
    "wof:name":"Wilson Mac Donald School Msm",
    "wof:placetype":"venue"
},
  "geometry": {"coordinates":[-79.932076,42.834236],"type":"Point"}
}