{
  "type": "Feature",
  "properties": {
    "addr:full":"Perth-Andover NB E7H 2W7",
    "addr:postcode":"e7h 2w7",
    "iso:country":"CA",
    "sg:city":"Perth-Andover",
    "sg:classifiers":[
        {
            "category":"Professional",
            "subcategory":"Engineering",
            "type":"Services"
        }
    ],
    "sg:phone":"+1 506 273 6640",
    "sg:postcode":"E7H 2W7",
    "sg:province":"NB",
    "sg:tags":[
        "engineer"
    ],
    "wof:name":"Hatchard Consulting",
    "wof:placetype":"venue"
},
  "geometry": {"coordinates":[-67.703552,46.739868],"type":"Point"}
}