{
  "type": "Feature",
  "properties": {
    "addr:full":"94 Trottier Bay Winnipeg MB R3T 3Y5",
    "addr:housenumber":"94",
    "addr:postcode":"r3t 3y5",
    "addr:street":"Trottier Bay",
    "iso:country":"CA",
    "sg:address":"94 Trottier Bay",
    "sg:city":"Winnipeg",
    "sg:classifiers":[
        {
            "category":"Wholesale",
            "subcategory":"Durable Goods & Equipment",
            "type":"Manufacturing & Wholesale Goods"
        }
    ],
    "sg:phone":"+1 204 269 9644",
    "sg:postcode":"R3T 3Y5",
    "sg:province":"MB",
    "sg:tags":[
        "shop",
        "repair",
        "scientific",
        "related",
        "apparatus"
    ],
    "wof:name":"Uniscience Laboratories",
    "wof:placetype":"venue"
},
  "geometry": {"coordinates":[-97.16400146479999,49.8266029358],"type":"Point"}
}