{
  "type": "Feature",
  "properties": {
    "addr:full":"91 Wright Ave Dartmouth NS B3B 1K6",
    "addr:housenumber":"91",
    "addr:postcode":"b3b 1k6",
    "addr:street":"Wright Ave",
    "iso:country":"CA",
    "sg:address":"91 Wright Ave",
    "sg:city":"Dartmouth",
    "sg:classifiers":[
        {
            "category":"Freight",
            "type":"Transportation"
        }
    ],
    "sg:phone":"+1 902 468 9438",
    "sg:postcode":"B3B 1K6",
    "sg:province":"NS",
    "sg:tags":[
        "trucking"
    ],
    "wof:name":"Atlantic Tiltload Svc",
    "wof:placetype":"venue"
},
  "geometry": {"coordinates":[-63.595356,44.705132],"type":"Point"}
}