{
  "type": "Feature",
  "properties": {
    "iso:country":"CA",
    "sg:address":"7146 Nesters Rd",
    "sg:city":"Whistler",
    "sg:classifiers":[
        {
            "category":"Social Services",
            "subcategory":"Child Care",
            "type":"Services"
        }
    ],
    "sg:phone":"+1 604 932 1119",
    "sg:postcode":"V0N 1B7",
    "sg:province":"BC",
    "wof:name":"Whistler Children's Ctr",
    "wof:placetype":"venue"
},
  "geometry": {"coordinates":[-122.960426,50.124176],"type":"Point"}
}