{
  "type": "Feature",
  "properties": {
    "addr:full":"Erin ON N0B 1T0",
    "addr:postcode":"n0b 1t0",
    "iso:country":"CA",
    "sg:city":"Erin",
    "sg:classifiers":[
        {
            "category":"Wholesale",
            "subcategory":"Sporting Goods",
            "type":"Manufacturing & Wholesale Goods"
        }
    ],
    "sg:phone":"+1 519 833 2017",
    "sg:postcode":"N0B 1T0",
    "sg:province":"ON",
    "sg:tags":[
        "furniture",
        "patio",
        "accessory"
    ],
    "wof:name":"Country Garden Concrete",
    "wof:placetype":"venue"
},
  "geometry": {"coordinates":[-80.07428,43.789005],"type":"Point"}
}