{
  "type": "Feature",
  "properties": {
    "addr:full":"1335 Mcnair St Victoria BC V8T 2S2",
    "addr:housenumber":"1335",
    "addr:postcode":"v8t 2s2",
    "addr:street":"Mcnair St",
    "iso:country":"CA",
    "sg:address":"1335 Mcnair St",
    "sg:city":"Victoria",
    "sg:classifiers":[
        {
            "category":"Building & Trades",
            "subcategory":"Construction",
            "type":"Services"
        }
    ],
    "sg:phone":"+1 250 920 5757",
    "sg:postcode":"V8T 2S2",
    "sg:province":"BC",
    "sg:tags":[
        "roofing",
        "contractor"
    ],
    "wof:name":"Advanced Products Roofing",
    "wof:placetype":"venue"
},
  "geometry": {"coordinates":[-123.350540161,48.4458503723],"type":"Point"}
}