{
  "type": "Feature",
  "properties": {
    "addr:full":"509 Parliament St Toronto ON M4X 1P3",
    "addr:housenumber":"509",
    "addr:postcode":"m4x 1p3",
    "addr:street":"Parliament St",
    "iso:country":"CA",
    "sg:address":"509 Parliament St",
    "sg:city":"Toronto",
    "sg:classifiers":[
        {
            "category":"Arts & Performance",
            "subcategory":"Theater",
            "type":"Entertainment"
        }
    ],
    "sg:phone":"+1 416 924 9533",
    "sg:postcode":"M4X 1P3",
    "sg:province":"ON",
    "sg:tags":[
        "equipment",
        "supply",
        "dancing",
        "theatrical"
    ],
    "wof:name":"Studio 509 Dancewear",
    "wof:placetype":"venue"
},
  "geometry": {"coordinates":[-79.368156,43.664974],"type":"Point"}
}