{
  "type": "Feature",
  "properties": {
    "addr:full":"1020 Ottawa St N # 510 Kitchener ON N2A 3Z3",
    "addr:housenumber":"1020;510",
    "addr:postcode":"n2a 3z3",
    "addr:street":"Ottawa St N #",
    "iso:country":"CA",
    "sg:address":"1020 Ottawa St N # 510",
    "sg:city":"Kitchener",
    "sg:classifiers":[
        {
            "category":"Food & Beverages",
            "subcategory":"Bakery",
            "type":"Retail Goods"
        }
    ],
    "sg:phone":"+1 519 894 1499",
    "sg:postcode":"N2A 3Z3",
    "sg:province":"ON",
    "sg:tags":[
        "doughnut"
    ],
    "wof:name":"Tim Hortons",
    "wof:placetype":"venue"
},
  "geometry": {"coordinates":[-80.443825,43.451202],"type":"Point"}
}