{
  "type": "Feature",
  "properties": {
    "addr:full":"Shippagan NB E8S 1T3",
    "addr:postcode":"e8s 1t3",
    "iso:country":"CA",
    "sg:city":"Shippagan",
    "sg:classifiers":[
        {
            "category":"Personal",
            "subcategory":"Barber",
            "type":"Services"
        }
    ],
    "sg:phone":"+1 506 336 8862",
    "sg:postcode":"E8S 1T3",
    "sg:province":"NB",
    "wof:name":"Salon Rousselle",
    "wof:placetype":"venue"
},
  "geometry": {"coordinates":[-64.72126,47.740471],"type":"Point"}
}