{
  "type": "Feature",
  "properties": {
    "addr:full":"115 King St E Gananoque ON K7G 1G3",
    "addr:housenumber":"115",
    "addr:postcode":"k7g 1g3",
    "addr:street":"King St E",
    "iso:country":"CA",
    "sg:address":"115 King St E",
    "sg:city":"Gananoque",
    "sg:classifiers":[
        {
            "category":"Restaurant",
            "type":"Food & Drink"
        }
    ],
    "sg:phone":"+1 613 382 4850",
    "sg:postcode":"K7G 1G3",
    "sg:province":"ON",
    "wof:name":"Tilly's",
    "wof:placetype":"venue"
},
  "geometry": {"coordinates":[-76.161987,44.329758],"type":"Point"}
}