{
  "type": "Feature",
  "properties": {
    "iso:country":"CA",
    "sg:address":"707 Saskatchewan Ave E",
    "sg:city":"Melfort",
    "sg:classifiers":[
        {
            "category":"Restaurant",
            "type":"Food & Drink"
        }
    ],
    "sg:phone":"+1 306 752 5759",
    "sg:postcode":"S0E 1A0",
    "sg:province":"SK",
    "wof:name":"Little Venice",
    "wof:placetype":"venue"
},
  "geometry": {"coordinates":[-104.596427917,52.8563156128],"type":"Point"}
}