{
  "type": "Feature",
  "properties": {
    "addr:full":"11921 80 Ave Delta BC V4C 1Y1",
    "addr:housenumber":"11921",
    "addr:postcode":"v4c 1y1",
    "addr:street":"80 Ave",
    "iso:country":"CA",
    "sg:address":"11921 80 Ave",
    "sg:city":"Delta",
    "sg:classifiers":[
        {
            "category":"Insurance",
            "subcategory":"Insurance Agent",
            "type":"Services"
        }
    ],
    "sg:phone":"+1 604 599 6033",
    "sg:postcode":"V4C 1Y1",
    "sg:province":"BC",
    "wof:name":"Kumar, Shalendra",
    "wof:placetype":"venue"
},
  "geometry": {"coordinates":[-122.89295959499999,49.1487770081],"type":"Point"}
}