{
  "type": "Feature",
  "properties": {
    "addr:full":"Woodbridge ON L4L 6C2",
    "addr:postcode":"l4l 6c2",
    "iso:country":"CA",
    "sg:city":"Woodbridge",
    "sg:classifiers":[
        {
            "category":"Manufacturing",
            "subcategory":"Tools & Machinery",
            "type":"Manufacturing & Wholesale Goods"
        }
    ],
    "sg:phone":"+1 416 665 0163",
    "sg:postcode":"L4L 6C2",
    "sg:province":"ON",
    "sg:tags":[
        "cleaning",
        "system"
    ],
    "wof:name":"Bradco Sales & Svc",
    "wof:placetype":"venue"
},
  "geometry": {"coordinates":[-79.552521,43.78722],"type":"Point"}
}