{
  "type": "Feature",
  "properties": {
    "addr:full":"479 Empire Ave St. John's NL A1E 5N8",
    "addr:housenumber":"479",
    "addr:postcode":"a1e 5n8",
    "addr:street":"Empire Ave",
    "iso:country":"CA",
    "sg:address":"479 Empire Ave",
    "sg:city":"St. John's",
    "sg:classifiers":[
        {
            "category":"Food & Beverages",
            "subcategory":"Groceries & Convenience Stores",
            "type":"Retail Goods"
        }
    ],
    "sg:phone":"+1 709 753 2111",
    "sg:postcode":"A1E 5N8",
    "sg:province":"NL",
    "sg:tags":[
        "grocer"
    ],
    "wof:name":"Goulding's Store",
    "wof:placetype":"venue"
},
  "geometry": {"coordinates":[-52.744888,47.55312],"type":"Point"}
}