{
  "type": "Feature",
  "properties": {
    "addr:full":"3442 Saanich Rd Victoria BC V8X 1W7",
    "addr:housenumber":"3442",
    "addr:postcode":"v8x 1w7",
    "addr:street":"Saanich Rd",
    "iso:country":"CA",
    "sg:address":"3442 Saanich Rd",
    "sg:city":"Victoria",
    "sg:classifiers":[
        {
            "category":"Cinema",
            "subcategory":"Movie Rental",
            "type":"Entertainment"
        }
    ],
    "sg:phone":"+1 250 475 2088",
    "sg:postcode":"V8X 1W7",
    "sg:province":"BC",
    "sg:tags":[
        "leasing",
        "video",
        "disc",
        "tape"
    ],
    "wof:name":"Blockbuster Video",
    "wof:placetype":"venue"
},
  "geometry": {"coordinates":[-123.36451700000001,48.428314],"type":"Point"}
}