{
  "type": "Feature",
  "properties": {
    "addr:full":"344 Rue Dubois Saint-Eustache QC J7P 4W9",
    "addr:housenumber":"344",
    "addr:postcode":"j7p 4w9",
    "addr:street":"Rue Dubois",
    "iso:country":"CA",
    "sg:address":"344 Rue Dubois",
    "sg:city":"Saint-Eustache",
    "sg:classifiers":[
        {
            "category":"Home & Garden",
            "subcategory":"Furniture",
            "type":"Retail Goods"
        }
    ],
    "sg:phone":"+1 450 473 2757",
    "sg:postcode":"J7P 4W9",
    "sg:province":"QC",
    "wof:name":"Domon Meubles Ltee",
    "wof:placetype":"venue"
},
  "geometry": {"coordinates":[-73.895233,45.574883],"type":"Point"}
}