{
  "type": "Feature",
  "properties": {
    "addr:full":"480 Boul Saint-Laurent Montreal QC H2Y 3Y7",
    "addr:housenumber":"480",
    "addr:postcode":"h2y 3y7",
    "addr:street":"Boul Saint-Laurent",
    "iso:country":"CA",
    "sg:address":"480 Boul Saint-Laurent",
    "sg:city":"Montreal",
    "sg:classifiers":[
        {
            "category":"Manufacturing",
            "subcategory":"Printing",
            "type":"Manufacturing & Wholesale Goods"
        }
    ],
    "sg:phone":"+1 514 843 9336",
    "sg:postcode":"H2Y 3Y7",
    "sg:province":"QC",
    "sg:tags":[
        "printer",
        "duplicating",
        "copying"
    ],
    "wof:name":"Copie Rapide Du Vieux Montreal",
    "wof:placetype":"venue"
},
  "geometry": {"coordinates":[-73.555359,45.505936],"type":"Point"}
}