{
  "type": "Feature",
  "properties": {
    "iso:country":"CA",
    "sg:address":"10575 114 St NW",
    "sg:city":"Edmonton",
    "sg:classifiers":[
        {
            "category":"Organizations",
            "subcategory":"Religious Organization",
            "type":"Services"
        }
    ],
    "sg:phone":"+1 780 420 6969",
    "sg:postcode":"T5H 3J6",
    "sg:province":"AB",
    "sg:tags":[
        "church"
    ],
    "wof:name":"Grace Community Church",
    "wof:placetype":"venue"
},
  "geometry": {"coordinates":[-113.517486572,53.549331665],"type":"Point"}
}