{
  "type": "Feature",
  "properties": {
    "addr:full":"922 19 Ave SE Calgary AB T2G 1L8",
    "addr:postcode":"t2g 1l8",
    "addr:street":"922 19 Ave Se",
    "iso:country":"CA",
    "sg:address":"922 19 Ave SE",
    "sg:city":"Calgary",
    "sg:classifiers":[
        {
            "category":"Food & Beverages",
            "subcategory":"Groceries & Convenience Stores",
            "type":"Retail Goods"
        }
    ],
    "sg:phone":"+1 403 265 5206",
    "sg:postcode":"T2G 1L8",
    "sg:province":"AB",
    "sg:tags":[
        "grocer"
    ],
    "wof:name":"Alberta Corner Store",
    "wof:placetype":"venue"
},
  "geometry": {"coordinates":[-114.040741,51.036392],"type":"Point"}
}