{
  "type": "Feature",
  "properties": {
    "addr:full":"9260 22nd Side Rd Hillsburgh ON N0B 1Z0",
    "addr:housenumber":"9260",
    "addr:postcode":"n0b 1z0",
    "addr:street":"22Nd Side Rd",
    "iso:country":"CA",
    "sg:address":"9260 22nd Side Rd",
    "sg:city":"Hillsburgh",
    "sg:classifiers":[
        {
            "category":"Recreation",
            "subcategory":"Marina",
            "type":"Entertainment"
        }
    ],
    "sg:phone":"+1 519 855 6591",
    "sg:postcode":"N0B 1Z0",
    "sg:province":"ON",
    "sg:tags":[
        "repairing",
        "boat"
    ],
    "wof:name":"Hi Top Marine Svc",
    "wof:placetype":"venue"
},
  "geometry": {"coordinates":[-80.1454772949,43.7913627625],"type":"Point"}
}