{
  "type": "Feature",
  "properties": {
    "addr:full":"212 Main St E Milton ON L9T 1N8",
    "addr:housenumber":"212",
    "addr:postcode":"l9t 1n8",
    "addr:street":"Main St E",
    "iso:country":"CA",
    "sg:address":"212 Main St E",
    "sg:city":"Milton",
    "sg:classifiers":[
        {
            "category":"Shopping",
            "subcategory":"Department Store",
            "type":"Retail Goods"
        }
    ],
    "sg:phone":"+1 905 878 4177",
    "sg:postcode":"L9T 1N8",
    "sg:province":"ON",
    "sg:tags":[
        "shop"
    ],
    "wof:name":"Willis Supreme Discount",
    "wof:placetype":"venue"
},
  "geometry": {"coordinates":[-79.883217,43.512859],"type":"Point"}
}