{
  "type": "Feature",
  "properties": {
    "iso:country":"CA",
    "sg:address":"132 132 Rte W",
    "sg:city":"Nouvelle",
    "sg:classifiers":[
        {
            "category":"Professional",
            "subcategory":"Business Services",
            "type":"Services"
        }
    ],
    "sg:phone":"+1 418 794 2241",
    "sg:postcode":"G0C 2E0",
    "sg:province":"QC",
    "sg:tags":[
        "notary"
    ],
    "wof:name":"Normand Arsenault Notaire",
    "wof:placetype":"venue"
},
  "geometry": {"coordinates":[-66.3090057373,48.1343688965],"type":"Point"}
}