{
  "type": "Feature",
  "properties": {
    "addr:full":"5490 Salt Lane Langley BC V3A 5C7",
    "addr:housenumber":"5490",
    "addr:postcode":"v3a 5c7",
    "addr:street":"Salt Lane",
    "iso:country":"CA",
    "sg:address":"5490 Salt Lane",
    "sg:city":"Langley",
    "sg:classifiers":[
        {
            "category":"Shopping",
            "subcategory":"Used Merchandise",
            "type":"Retail Goods"
        }
    ],
    "sg:phone":"+1 604 534 2124",
    "sg:postcode":"V3A 5C7",
    "sg:province":"BC",
    "sg:tags":[
        "book",
        "rare",
        "dealer"
    ],
    "wof:name":"Ambassador Discount Books",
    "wof:placetype":"venue"
},
  "geometry": {"coordinates":[-122.65282440199999,49.1043434143],"type":"Point"}
}