{
  "type": "Feature",
  "properties": {
    "addr:full":"115 Humber Rd Corner Brook NL A2H 1G1",
    "addr:housenumber":"115",
    "addr:postcode":"a2h 1g1",
    "addr:street":"Humber Rd",
    "iso:country":"CA",
    "sg:address":"115 Humber Rd",
    "sg:city":"Corner Brook",
    "sg:classifiers":[
        {
            "category":"Retail",
            "subcategory":"Repair Shop",
            "type":"Services"
        }
    ],
    "sg:phone":"+1 709 634 3294",
    "sg:postcode":"A2H 1G1",
    "sg:province":"NL",
    "sg:tags":[
        "equipment",
        "industrial",
        "parts",
        "supply"
    ],
    "wof:name":"Rideout Tool & Machine Inc",
    "wof:placetype":"venue"
},
  "geometry": {"coordinates":[-57.928806,48.963684],"type":"Point"}
}