{
  "type": "Feature",
  "properties": {
    "addr:full":"Sudbury ON P3B 2E5",
    "addr:postcode":"p3b 2e5",
    "iso:country":"CA",
    "sg:city":"Sudbury",
    "sg:classifiers":[
        {
            "category":"Autos & Motor Vehicles",
            "subcategory":"Automobile Sales",
            "type":"Retail Goods"
        }
    ],
    "sg:phone":"+1 705 670 2266",
    "sg:postcode":"P3B 2E5",
    "sg:province":"ON",
    "sg:tags":[
        "car",
        "dealer"
    ],
    "wof:name":"Sudbury Hyundai",
    "wof:placetype":"venue"
},
  "geometry": {"coordinates":[-80.96839900000001,46.499199],"type":"Point"}
}