{
  "type": "Feature",
  "properties": {
    "addr:full":"1120 Mohawk St Woodstock ON N4T 1A4",
    "addr:housenumber":"1120",
    "addr:postcode":"n4t 1a4",
    "addr:street":"Mohawk St",
    "iso:country":"CA",
    "sg:address":"1120 Mohawk St",
    "sg:city":"Woodstock",
    "sg:classifiers":[
        {
            "category":"Personal",
            "subcategory":"Beauty Salon",
            "type":"Services"
        }
    ],
    "sg:phone":"+1 519 539 7639",
    "sg:postcode":"N4T 1A4",
    "sg:province":"ON",
    "wof:name":"Kim's Hairstyling",
    "wof:placetype":"venue"
},
  "geometry": {"coordinates":[-80.73252100000001,43.149593],"type":"Point"}
}