{
  "type": "Feature",
  "properties": {
    "addr:full":"10748 Plumtree Close Surrey BC V4N 4T3",
    "addr:housenumber":"10748",
    "addr:postcode":"v4n 4t3",
    "addr:street":"Plumtree Close",
    "iso:country":"CA",
    "sg:address":"10748 Plumtree Close",
    "sg:city":"Surrey",
    "sg:classifiers":[
        {
            "category":"Building & Trades",
            "subcategory":"Construction",
            "type":"Services"
        }
    ],
    "sg:phone":"+1 604 583 0440",
    "sg:postcode":"V4N 4T3",
    "sg:province":"BC",
    "sg:tags":[
        "contractor"
    ],
    "wof:name":"Jim Frith Contracting Ltd",
    "wof:placetype":"venue"
},
  "geometry": {"coordinates":[-122.759056,49.198032],"type":"Point"}
}