{
  "type": "Feature",
  "properties": {
    "addr:full":"885 Don Mills Rd North York ON M3C 1V9",
    "addr:housenumber":"885",
    "addr:postcode":"m3c 1v9",
    "addr:street":"Don Mills Rd",
    "iso:country":"CA",
    "sg:address":"885 Don Mills Rd",
    "sg:city":"North York",
    "sg:classifiers":[
        {
            "category":"Professional",
            "subcategory":"Lawyer & Legal Services",
            "type":"Services"
        }
    ],
    "sg:phone":"+1 416 510 8819",
    "sg:postcode":"M3C 1V9",
    "sg:province":"ON",
    "sg:tags":[
        "attorney"
    ],
    "wof:name":"Mlot, Patrick M",
    "wof:placetype":"venue"
},
  "geometry": {"coordinates":[-79.339859,43.725033],"type":"Point"}
}