{
  "type": "Feature",
  "properties": {
    "addr:full":"Calgary AB T2P 1C9",
    "addr:postcode":"t2p 1c9",
    "iso:country":"CA",
    "sg:city":"Calgary",
    "sg:classifiers":[
        {
            "category":"Shopping",
            "subcategory":"Bicycles & Sporting Goods",
            "type":"Retail Goods"
        }
    ],
    "sg:phone":"+1 403 303 8400",
    "sg:postcode":"T2P 1C9",
    "sg:province":"AB",
    "wof:name":"NB Trademarks Inc",
    "wof:placetype":"venue"
},
  "geometry": {"coordinates":[-114.06887817400001,51.0455741882],"type":"Point"}
}