{
  "type": "Feature",
  "properties": {
    "iso:country":"CA",
    "sg:address":"997 Boul St Laurent",
    "sg:city":"Ottawa",
    "sg:classifiers":[
        {
            "category":"Home & Garden",
            "subcategory":"Household Appliances",
            "type":"Retail Goods"
        }
    ],
    "sg:phone":"+1 613 741 7934",
    "sg:postcode":"K1K 3B1",
    "sg:province":"ON",
    "sg:tags":[
        "television",
        "radio"
    ],
    "wof:name":"Bleeker Stereo & Tv Ltd",
    "wof:placetype":"venue"
},
  "geometry": {"coordinates":[-75.63943481450001,45.4284629822],"type":"Point"}
}