{
  "type": "Feature",
  "properties": {
    "iso:country":"CA",
    "sg:address":"10 Grosvenor Cres",
    "sg:city":"Saskatoon",
    "sg:classifiers":[
        {
            "category":"Organizations",
            "subcategory":"Religious Organization",
            "type":"Services"
        }
    ],
    "sg:phone":"+1 306 374 4066",
    "sg:postcode":"S7J 2S2",
    "sg:province":"SK",
    "sg:tags":[
        "church"
    ],
    "wof:name":"St Stephen's Anglican Church",
    "wof:placetype":"venue"
},
  "geometry": {"coordinates":[-106.624619,52.105145],"type":"Point"}
}