{
  "type": "Feature",
  "properties": {
    "addr:full":"5295 Trans Canada Hwy Duncan BC V9L 5J2",
    "addr:housenumber":"5295",
    "addr:postcode":"v9l 5j2",
    "addr:street":"Trans Canada Hwy",
    "iso:country":"CA",
    "sg:address":"5295 Trans Canada Hwy",
    "sg:city":"Duncan",
    "sg:classifiers":[
        {
            "category":"Autos & Motor Vehicles",
            "subcategory":"Auto Supplies",
            "type":"Retail Goods"
        }
    ],
    "sg:phone":"+1 250 746 9815",
    "sg:postcode":"V9L 5J2",
    "sg:province":"BC",
    "sg:tags":[
        "tire"
    ],
    "wof:name":"Kal Tire",
    "wof:placetype":"venue"
},
  "geometry": {"coordinates":[-123.698822022,48.7804908752],"type":"Point"}
}