{
  "type": "Feature",
  "properties": {
    "addr:full":"Vancouver BC V6J 4R1",
    "addr:postcode":"v6j 4r1",
    "iso:country":"CA",
    "sg:city":"Vancouver",
    "sg:classifiers":[
        {
            "category":"Shopping",
            "type":"Retail Goods"
        }
    ],
    "sg:phone":"+1 604 733 9812",
    "sg:postcode":"V6J 4R1",
    "sg:province":"BC",
    "sg:tags":[
        "pet",
        "food",
        "supply"
    ],
    "wof:name":"Petcetera",
    "wof:placetype":"venue"
},
  "geometry": {"coordinates":[-123.15348053,49.2483253479],"type":"Point"}
}