{
  "type": "Feature",
  "properties": {
    "iso:country":"CA",
    "sg:city":"Gatineau",
    "sg:classifiers":[
        {
            "category":"Building & Trades",
            "subcategory":"Construction",
            "type":"Services"
        }
    ],
    "sg:phone":"+1 819 243 8852",
    "sg:postcode":"J8T 2E6",
    "sg:province":"QC",
    "sg:tags":[
        "painter"
    ],
    "wof:name":"Marcel Painting",
    "wof:placetype":"venue"
},
  "geometry": {"coordinates":[-75.49285888670001,45.5239219666],"type":"Point"}
}