{
  "type": "Feature",
  "properties": {
    "addr:full":"North York ON M6A 3B2",
    "addr:postcode":"m6a 3b2",
    "iso:country":"CA",
    "sg:city":"North York",
    "sg:classifiers":[
        {
            "category":"Banks & Credit Unions",
            "subcategory":"Investment Brokerage",
            "type":"Services"
        }
    ],
    "sg:phone":"+1 416 789 4527",
    "sg:postcode":"M6A 3B2",
    "sg:province":"ON",
    "sg:tags":[
        "consultant",
        "planning",
        "financial"
    ],
    "wof:name":"Freedom 55 Financial",
    "wof:placetype":"venue"
},
  "geometry": {"coordinates":[-79.4558792114,43.7184867859],"type":"Point"}
}