{
  "type": "Feature",
  "properties": {
    "addr:full":"6 Spruce Ctr SW Calgary AB T3C 3B3",
    "addr:housenumber":"6",
    "addr:postcode":"t3c 3b3",
    "addr:street":"Spruce Ctr Sw",
    "iso:country":"CA",
    "sg:address":"6 Spruce Ctr SW",
    "sg:city":"Calgary",
    "sg:classifiers":[
        {
            "category":"Food & Beverages",
            "subcategory":"Groceries & Convenience Stores",
            "type":"Retail Goods"
        }
    ],
    "sg:phone":"+1 403 249 5407",
    "sg:postcode":"T3C 3B3",
    "sg:province":"AB",
    "sg:tags":[
        "grocer"
    ],
    "wof:name":"Spruce Cliff Grocery",
    "wof:placetype":"venue"
},
  "geometry": {"coordinates":[-114.13694,51.047878],"type":"Point"}
}