{
  "type": "Feature",
  "properties": {
    "addr:full":"380 Burnham St Peterborough ON K9H 1T6",
    "addr:housenumber":"380",
    "addr:postcode":"k9h 1t6",
    "addr:street":"Burnham St",
    "iso:country":"CA",
    "sg:address":"380 Burnham St",
    "sg:city":"Peterborough",
    "sg:classifiers":[
        {
            "category":"Shopping",
            "subcategory":"Pharmacy",
            "type":"Retail Goods"
        }
    ],
    "sg:phone":"+1 705 741 1199",
    "sg:postcode":"K9H 1T6",
    "sg:province":"ON",
    "wof:name":"Burnham Medical Pharmacy",
    "wof:placetype":"venue"
},
  "geometry": {"coordinates":[-78.3118896484,44.3052101135],"type":"Point"}
}