{
  "type": "Feature",
  "properties": {
    "addr:full":"179 Dundas St W Toronto ON M5G 1C7",
    "addr:housenumber":"179",
    "addr:postcode":"m5g 1c7",
    "addr:street":"Dundas St W",
    "iso:country":"CA",
    "sg:address":"179 Dundas St W",
    "sg:city":"Toronto",
    "sg:classifiers":[
        {
            "category":"Restaurant",
            "type":"Food & Drink"
        }
    ],
    "sg:phone":"+1 416 977 4712",
    "sg:postcode":"M5G 1C7",
    "sg:province":"ON",
    "wof:name":"Thai Thani",
    "wof:placetype":"venue"
},
  "geometry": {"coordinates":[-79.3865432739,43.6549911499],"type":"Point"}
}