{
  "type": "Feature",
  "properties": {
    "iso:country":"CA",
    "sg:address":"600 Garden St",
    "sg:city":"Whitby",
    "sg:classifiers":[
        {
            "category":"Manufacturing",
            "subcategory":"Signs",
            "type":"Manufacturing & Wholesale Goods"
        }
    ],
    "sg:phone":"+1 905 665 5666",
    "sg:postcode":"L1N 7B3",
    "sg:province":"ON",
    "wof:name":"Calibre Signs",
    "wof:placetype":"venue"
},
  "geometry": {"coordinates":[-78.93630981450001,43.8908843994],"type":"Point"}
}