{
  "type": "Feature",
  "properties": {
    "addr:full":"Abbotsford BC V2S 2B9",
    "addr:postcode":"v2s 2b9",
    "iso:country":"CA",
    "sg:city":"Abbotsford",
    "sg:classifiers":[
        {
            "category":"Restaurant",
            "type":"Food & Drink"
        }
    ],
    "sg:phone":"+1 604 852 1908",
    "sg:postcode":"V2S 2B9",
    "sg:province":"BC",
    "wof:name":"Subway Sandwiches & Salads",
    "wof:placetype":"venue"
},
  "geometry": {"coordinates":[-122.292557,49.048588],"type":"Point"}
}