{
  "type": "Feature",
  "properties": {
    "addr:full":"4966 King St E Beamsville ON L0R 1B0",
    "addr:housenumber":"4966",
    "addr:postcode":"l0r 1b0",
    "addr:street":"King St;Beamsville",
    "iso:country":"CA",
    "sg:address":"4966 King St E",
    "sg:city":"Beamsville",
    "sg:classifiers":[
        {
            "category":"Food & Beverages",
            "subcategory":"Bakery",
            "type":"Retail Goods"
        }
    ],
    "sg:phone":"+1 905 563 4533",
    "sg:postcode":"L0R 1B0",
    "sg:province":"ON",
    "sg:tags":[
        "baker"
    ],
    "wof:name":"Beamsville Bakery",
    "wof:placetype":"venue"
},
  "geometry": {"coordinates":[-79.474709,43.165005],"type":"Point"}
}