{
  "type": "Feature",
  "properties": {
    "addr:full":"16 Rue Mgr-Martin O Saint-Quentin NB E8A 1W6",
    "addr:housenumber":"16",
    "addr:postcode":"e8a 1w6",
    "addr:street":"Rue Mgr-Martin O Saint-Quentin",
    "iso:country":"CA",
    "sg:address":"16 Rue Mgr-Martin O",
    "sg:city":"Saint-Quentin",
    "sg:classifiers":[
        {
            "category":"Manufacturing",
            "subcategory":"Tools & Machinery",
            "type":"Manufacturing & Wholesale Goods"
        }
    ],
    "sg:phone":"+1 506 235 3049",
    "sg:postcode":"E8A 1W6",
    "sg:province":"NB",
    "sg:tags":[
        "equipment",
        "hydraulic"
    ],
    "wof:name":"Roy Hydraulique Ltee",
    "wof:placetype":"venue"
},
  "geometry": {"coordinates":[-67.394943,47.513809],"type":"Point"}
}