{
  "type": "Feature",
  "properties": {
    "addr:full":"100 Elm St # 1 Sudbury ON P3C 1T5",
    "addr:housenumber":"100",
    "addr:postcode":"p3c 1t5",
    "addr:street":"Elm St # 1",
    "iso:country":"CA",
    "sg:address":"100 Elm St # 1",
    "sg:city":"Sudbury",
    "sg:classifiers":[
        {
            "category":"Shopping",
            "subcategory":"Clothing, Apparel, & Fashions",
            "type":"Retail Goods"
        }
    ],
    "sg:phone":"+1 705 675 6114",
    "sg:postcode":"P3C 1T5",
    "sg:province":"ON",
    "wof:name":"Bentley Leather",
    "wof:placetype":"venue"
},
  "geometry": {"coordinates":[-80.997772,46.493275],"type":"Point"}
}