{
  "type": "Feature",
  "properties": {
    "addr:full":"3794 Highway 3 Chester NS B0J 1J0",
    "addr:housenumber":"3794",
    "addr:postcode":"b0j 1j0",
    "addr:street":"Highway 3",
    "iso:country":"CA",
    "sg:address":"3794 Highway 3",
    "sg:city":"Chester",
    "sg:classifiers":[
        {
            "category":"Personal",
            "subcategory":"Beauty Salon",
            "type":"Services"
        }
    ],
    "sg:phone":"+1 902 275 3238",
    "sg:postcode":"B0J 1J0",
    "sg:province":"NS",
    "wof:name":"Valerie's Hair Studio",
    "wof:placetype":"venue"
},
  "geometry": {"coordinates":[-64.241783,44.546276],"type":"Point"}
}