{
  "type": "Feature",
  "properties": {
    "addr:full":"1488 St. Paul St Kelowna BC V1Y 2E6",
    "addr:housenumber":"1488",
    "addr:postcode":"v1y 2e6",
    "addr:street":"St. Paul St",
    "iso:country":"CA",
    "sg:address":"1488 St. Paul St",
    "sg:city":"Kelowna",
    "sg:classifiers":[
        {
            "category":"Shopping",
            "subcategory":"Clothing, Apparel, & Fashions",
            "type":"Retail Goods"
        }
    ],
    "sg:phone":"+1 250 762 9137",
    "sg:postcode":"V1Y 2E6",
    "sg:province":"BC",
    "sg:tags":[
        "tailor"
    ],
    "wof:name":"Cosmo Tailoring & Alterations",
    "wof:placetype":"venue"
},
  "geometry": {"coordinates":[-119.492096,49.88681],"type":"Point"}
}