{
  "type": "Feature",
  "properties": {
    "addr:full":"NW 16-8-8E Richer MB R0E 1S0",
    "addr:housenumber":"16-8-8e",
    "addr:postcode":"r0e 1s0",
    "addr:street":"Nw",
    "iso:country":"CA",
    "sg:address":"NW 16-8-8E",
    "sg:city":"Richer",
    "sg:classifiers":[
        {
            "category":"Restaurant",
            "type":"Food & Drink"
        }
    ],
    "sg:phone":"+1 204 422 5719",
    "sg:postcode":"R0E 1S0",
    "sg:province":"MB",
    "wof:name":"Country Corner",
    "wof:placetype":"venue"
},
  "geometry": {"coordinates":[-96.4568023682,49.6563835144],"type":"Point"}
}