{
  "type": "Feature",
  "properties": {
    "iso:country":"CA",
    "sg:address":"1954 Huron Church Rd",
    "sg:city":"Windsor",
    "sg:classifiers":[
        {
            "category":"Travel",
            "subcategory":"Hotels & Motels",
            "type":"Entertainment"
        }
    ],
    "sg:phone":"+1 519 969 7642",
    "sg:postcode":"N9C 2L5",
    "sg:province":"ON",
    "wof:name":"Bestway Motel",
    "wof:placetype":"venue"
},
  "geometry": {"coordinates":[-83.0531234741,42.2799415588],"type":"Point"}
}