{
  "type": "Feature",
  "properties": {
    "iso:country":"CA",
    "sg:address":"306 Nicholson St N",
    "sg:city":"Prince George",
    "sg:classifiers":[
        {
            "category":"Retail",
            "subcategory":"Repair Shop",
            "type":"Services"
        }
    ],
    "sg:phone":"+1 250 563 8394",
    "sg:postcode":"V2M 3H2",
    "sg:province":"BC",
    "sg:tags":[
        "taxidermist"
    ],
    "wof:name":"Rainbow Taxidermy",
    "wof:placetype":"venue"
},
  "geometry": {"coordinates":[-122.78717,53.926537],"type":"Point"}
}