{
  "type": "Feature",
  "properties": {
    "iso:country":"CA",
    "sg:address":"33 Rosedale St",
    "sg:city":"Grimsby",
    "sg:classifiers":[
        {
            "category":"Building & Trades",
            "subcategory":"Construction",
            "type":"Services"
        }
    ],
    "sg:phone":"+1 905 945 1667",
    "sg:postcode":"L3M 3Z4",
    "sg:province":"ON",
    "sg:tags":[
        "concrete",
        "contractor"
    ],
    "wof:name":"Benny's Cement Work & Lndscp",
    "wof:placetype":"venue"
},
  "geometry": {"coordinates":[-79.5966415405,43.2008895874],"type":"Point"}
}