{
  "type": "Feature",
  "properties": {
    "addr:full":"1775 Boul Becancour Becancour QC G9H 3V4",
    "addr:housenumber":"1775",
    "addr:postcode":"g9h 3v4",
    "addr:street":"Boul Becancour Becancour",
    "iso:country":"CA",
    "sg:address":"1775 Boul Becancour",
    "sg:city":"Becancour",
    "sg:classifiers":[
        {
            "category":"Health Services",
            "subcategory":"Doctor",
            "type":"Services"
        }
    ],
    "sg:phone":"+1 819 298 3113",
    "sg:postcode":"G9H 3V4",
    "sg:province":"QC",
    "sg:tags":[
        "physician",
        "surgeon"
    ],
    "wof:name":"Centre Medical DE Gentilly",
    "wof:placetype":"venue"
},
  "geometry": {"coordinates":[-72.27304100000001,46.403572],"type":"Point"}
}