{
  "type": "Feature",
  "properties": {
    "addr:full":"Ste-Catherine-DE-LA-J-Cartier QC G0A 3M0",
    "addr:postcode":"g0a 3m0",
    "iso:country":"CA",
    "sg:city":"Ste-Catherine-DE-LA-J-Cartier",
    "sg:classifiers":[
        {
            "category":"Building & Trades",
            "subcategory":"Construction",
            "type":"Services"
        }
    ],
    "sg:phone":"+1 418 875 2944",
    "sg:postcode":"G0A 3M0",
    "sg:province":"QC",
    "sg:tags":[
        "painter"
    ],
    "wof:name":"Andre Larocque Entrepreneur",
    "wof:placetype":"venue"
},
  "geometry": {"coordinates":[-71.710052,46.860664],"type":"Point"}
}