{
  "type": "Feature",
  "properties": {
    "addr:full":"617 Millstone Ave Nanaimo BC V9S 5B1",
    "addr:housenumber":"617",
    "addr:postcode":"v9s 5b1",
    "addr:street":"Millstone Ave",
    "iso:country":"CA",
    "sg:address":"617 Millstone Ave",
    "sg:city":"Nanaimo",
    "sg:classifiers":[
        {
            "category":"Social Services",
            "subcategory":"Child Care",
            "type":"Services"
        }
    ],
    "sg:phone":"+1 250 754 1289",
    "sg:postcode":"V9S 5B1",
    "sg:province":"BC",
    "wof:name":"Katies Korner Child Care Ctr",
    "wof:placetype":"venue"
},
  "geometry": {"coordinates":[-123.955215,49.178001],"type":"Point"}
}