{
  "type": "Feature",
  "properties": {
    "addr:full":"2198 4th Ave W Vancouver BC V6K 1N6",
    "addr:housenumber":"2198",
    "addr:postcode":"v6k 1n6",
    "addr:street":"4Th Ave W",
    "iso:country":"CA",
    "sg:address":"2198 4th Ave W",
    "sg:city":"Vancouver",
    "sg:classifiers":[
        {
            "category":"Restaurant",
            "type":"Food & Drink"
        }
    ],
    "sg:phone":"+1 604 739 0139",
    "sg:postcode":"V6K 1N6",
    "sg:province":"BC",
    "sg:tags":[
        "shop",
        "coffee"
    ],
    "wof:name":"Kits Coffee CO Ltd",
    "wof:placetype":"venue"
},
  "geometry": {"coordinates":[-123.154839,49.268089],"type":"Point"}
}