{
  "type": "Feature",
  "properties": {
    "iso:country":"CA",
    "sg:city":"Maple Ridge",
    "sg:classifiers":[
        {
            "category":"Personal",
            "subcategory":"Beauty Salon",
            "type":"Services"
        }
    ],
    "sg:phone":"+1 604 466 9440",
    "sg:postcode":"V2X 2W2",
    "sg:province":"BC",
    "wof:name":"Hairformers Studio Ltd",
    "wof:placetype":"venue"
},
  "geometry": {"coordinates":[-122.587097168,49.2128791809],"type":"Point"}
}