{
  "type": "Feature",
  "properties": {
    "addr:full":"2437 Av DE Vitre Quebec QC G1J 4A7",
    "addr:housenumber":"2437",
    "addr:postcode":"g1j 4a7",
    "addr:street":"Av De Vitre",
    "iso:country":"CA",
    "sg:address":"2437 Av DE Vitre",
    "sg:city":"Quebec",
    "sg:classifiers":[
        {
            "category":"Professional",
            "subcategory":"Lawyer & Legal Services",
            "type":"Services"
        }
    ],
    "sg:phone":"+1 418 525 4977",
    "sg:postcode":"G1J 4A7",
    "sg:province":"QC",
    "sg:tags":[
        "attorney"
    ],
    "wof:name":"Monaghan, David",
    "wof:placetype":"venue"
},
  "geometry": {"coordinates":[-71.230942,46.841927],"type":"Point"}
}