{
  "type": "Feature",
  "properties": {
    "addr:full":"104 Mcleod Ave E Melfort SK S0E 1A0",
    "addr:housenumber":"104",
    "addr:postcode":"s0e 1a0",
    "addr:street":"Mcleod Ave E Melfort",
    "iso:country":"CA",
    "sg:address":"104 Mcleod Ave E",
    "sg:city":"Melfort",
    "sg:classifiers":[
        {
            "category":"Health Services",
            "subcategory":"Medical Lab",
            "type":"Services"
        }
    ],
    "sg:phone":"+1 306 752 3346",
    "sg:postcode":"S0E 1A0",
    "sg:province":"SK",
    "wof:name":"Melfort Denture Clinic",
    "wof:placetype":"venue"
},
  "geometry": {"coordinates":[-104.606262,52.860405],"type":"Point"}
}