{
  "type": "Feature",
  "properties": {
    "addr:full":"White Rock BC V4B 4E5",
    "addr:postcode":"v4b 4e5",
    "iso:country":"CA",
    "sg:city":"White Rock",
    "sg:classifiers":[
        {
            "category":"Building & Trades",
            "subcategory":"Construction",
            "type":"Services"
        }
    ],
    "sg:phone":"+1 604 531 6363",
    "sg:postcode":"V4B 4E5",
    "sg:province":"BC",
    "sg:tags":[
        "contractor"
    ],
    "wof:name":"Manor Homes Inc",
    "wof:placetype":"venue"
},
  "geometry": {"coordinates":[-122.79603576700001,49.0288085938],"type":"Point"}
}