{
  "type": "Feature",
  "properties": {
    "iso:country":"CA",
    "sg:address":"5855 Av DE Monkland",
    "sg:city":"Montreal",
    "sg:classifiers":[
        {
            "category":"Food & Beverages",
            "subcategory":"Groceries & Convenience Stores",
            "type":"Retail Goods"
        }
    ],
    "sg:phone":"+1 514 486 4645",
    "sg:postcode":"H4A 1G5",
    "sg:province":"QC",
    "wof:name":"Couche-Tard",
    "wof:placetype":"venue"
},
  "geometry": {"coordinates":[-73.625702,45.472565],"type":"Point"}
}