{
  "type": "Feature",
  "properties": {
    "addr:full":"25 Rue Des Pilotes Les Escoumins QC G0T 1K0",
    "addr:housenumber":"25",
    "addr:postcode":"g0t 1k0",
    "addr:street":"Rue Des Pilotes",
    "iso:country":"CA",
    "sg:address":"25 Rue Des Pilotes",
    "sg:city":"Les Escoumins",
    "sg:classifiers":[
        {
            "category":"Travel",
            "subcategory":"Hotels & Motels",
            "type":"Entertainment"
        }
    ],
    "sg:phone":"+1 418 233 2213",
    "sg:postcode":"G0T 1K0",
    "sg:province":"QC",
    "sg:tags":[
        "cottage",
        "cabin"
    ],
    "wof:name":"Chalets Au Bord DE LA Mer",
    "wof:placetype":"venue"
},
  "geometry": {"coordinates":[-69.416656,48.321514],"type":"Point"}
}