{
  "type": "Feature",
  "properties": {
    "addr:full":"1055 Ch D'Aylmer Aylmer QC J9H 5V2",
    "addr:housenumber":"1055",
    "addr:postcode":"j9h 5v2",
    "addr:street":"Ch D'Aylmer",
    "iso:country":"CA",
    "sg:address":"1055 Ch D'Aylmer",
    "sg:city":"Aylmer",
    "sg:classifiers":[
        {
            "category":"Restaurant",
            "type":"Food & Drink"
        }
    ],
    "sg:phone":"+1 819 778 6742",
    "sg:postcode":"J9H 5V2",
    "sg:province":"QC",
    "sg:tags":[
        "craft",
        "supply"
    ],
    "wof:name":"Tea'n Tole Inc",
    "wof:placetype":"venue"
},
  "geometry": {"coordinates":[-75.824608,45.396294],"type":"Point"}
}