{
  "type": "Feature",
  "properties": {
    "addr:full":"1 Main St Galahad AB T0B 1R0",
    "addr:housenumber":"1",
    "addr:postcode":"t0b 1r0",
    "addr:street":"Main St",
    "iso:country":"CA",
    "sg:address":"1 Main St",
    "sg:city":"Galahad",
    "sg:classifiers":[
        {
            "category":"Health Services",
            "subcategory":"Hospital",
            "type":"Services"
        }
    ],
    "sg:phone":"+1 780 583 3788",
    "sg:postcode":"T0B 1R0",
    "sg:province":"AB",
    "wof:name":"Galahad Health Care Ctr",
    "wof:placetype":"venue"
},
  "geometry": {"coordinates":[-111.93000000000001,52.514004],"type":"Point"}
}