{
  "type": "Feature",
  "properties": {
    "addr:full":"Ottawa ON K2P 0G5",
    "addr:postcode":"k2p 0g5",
    "iso:country":"CA",
    "sg:city":"Ottawa",
    "sg:classifiers":[
        {
            "category":"Building & Trades",
            "subcategory":"Plumbing",
            "type":"Services"
        }
    ],
    "sg:phone":"+1 613 860 1301",
    "sg:postcode":"K2P 0G5",
    "sg:province":"ON",
    "sg:tags":[
        "ventilating",
        "contractor"
    ],
    "wof:name":"N C Sheet Metal Inc",
    "wof:placetype":"venue"
},
  "geometry": {"coordinates":[-75.694298,45.417305],"type":"Point"}
}