{
  "type": "Feature",
  "properties": {
    "iso:country":"CA",
    "sg:city":"Calgary",
    "sg:classifiers":[
        {
            "category":"Restaurant",
            "type":"Food & Drink"
        }
    ],
    "sg:phone":"+1 403 230 3030",
    "sg:postcode":"T2E 6T1",
    "sg:province":"AB",
    "sg:tags":[
        "out"
    ],
    "wof:name":"Pizza Delicious",
    "wof:placetype":"venue"
},
  "geometry": {"coordinates":[-114.051933289,51.0871315002],"type":"Point"}
}