{
  "type": "Feature",
  "properties": {
    "addr:full":"Thornhill ON L3T 7L2",
    "addr:postcode":"l3t 7l2",
    "iso:country":"CA",
    "sg:city":"Thornhill",
    "sg:classifiers":[
        {
            "category":"Health Services",
            "subcategory":"Doctor",
            "type":"Services"
        }
    ],
    "sg:phone":"+1 905 731 8220",
    "sg:postcode":"L3T 7L2",
    "sg:province":"ON",
    "sg:tags":[
        "dentist"
    ],
    "wof:name":"Ciomyk, Taras DDS",
    "wof:placetype":"venue"
},
  "geometry": {"coordinates":[-79.424583,43.816982],"type":"Point"}
}