{
  "type": "Feature",
  "properties": {
    "addr:full":"312 Ch Grande-Ligne Windsor QC J1S 2L5",
    "addr:housenumber":"312",
    "addr:postcode":"j1s 2l5",
    "addr:street":"Ch Grande-Ligne",
    "iso:country":"CA",
    "sg:address":"312 Ch Grande-Ligne",
    "sg:city":"Windsor",
    "sg:classifiers":[
        {
            "category":"Wholesale",
            "subcategory":"Auto Parts",
            "type":"Manufacturing & Wholesale Goods"
        }
    ],
    "sg:phone":"+1 819 845 3390",
    "sg:postcode":"J1S 2L5",
    "sg:province":"QC",
    "sg:tags":[
        "automobile",
        "rebuilt"
    ],
    "wof:name":"Garage Marcel Roy",
    "wof:placetype":"venue"
},
  "geometry": {"coordinates":[-72.0065,45.569019],"type":"Point"}
}