{
  "type": "Feature",
  "properties": {
    "addr:full":"95 Hamilton Rd London ON N6B 1N2",
    "addr:housenumber":"95",
    "addr:postcode":"n6b 1n2",
    "addr:street":"Hamilton Rd",
    "iso:country":"CA",
    "sg:address":"95 Hamilton Rd",
    "sg:city":"London",
    "sg:classifiers":[
        {
            "category":"Wholesale",
            "subcategory":"Auto Parts",
            "type":"Manufacturing & Wholesale Goods"
        }
    ],
    "sg:phone":"+1 519 432 2214",
    "sg:postcode":"N6B 1N2",
    "sg:province":"ON",
    "sg:tags":[
        "repairing",
        "automobile",
        "radiator"
    ],
    "wof:name":"William Kydd Auto Radiator Svc",
    "wof:placetype":"venue"
},
  "geometry": {"coordinates":[-81.232834,42.982529],"type":"Point"}
}