{
  "type": "Feature",
  "properties": {
    "addr:full":"346 Miles St Kamsack SK S0A 1S0",
    "addr:housenumber":"346",
    "addr:postcode":"s0a 1s0",
    "addr:street":"Miles St",
    "iso:country":"CA",
    "sg:address":"346 Miles St",
    "sg:city":"Kamsack",
    "sg:classifiers":[
        {
            "category":"Health Services",
            "subcategory":"Nursing And Care Facility",
            "type":"Services"
        }
    ],
    "sg:phone":"+1 306 542 2620",
    "sg:postcode":"S0A 1S0",
    "sg:province":"SK",
    "sg:tags":[
        "home",
        "rest"
    ],
    "wof:name":"Eaglestone Lodge",
    "wof:placetype":"venue"
},
  "geometry": {"coordinates":[-101.890411,51.55938],"type":"Point"}
}