{
  "type": "Feature",
  "properties": {
    "addr:full":"471 Waterloo St London ON N6B 2P4",
    "addr:housenumber":"471",
    "addr:postcode":"n6b 2p4",
    "addr:street":"Waterloo St",
    "iso:country":"CA",
    "sg:address":"471 Waterloo St",
    "sg:city":"London",
    "sg:classifiers":[
        {
            "category":"Real Estate",
            "subcategory":"Real Estate Agent",
            "type":"Services"
        }
    ],
    "sg:phone":"+1 519 439 9444",
    "sg:postcode":"N6B 2P4",
    "sg:province":"ON",
    "sg:tags":[
        "management"
    ],
    "wof:name":"Pacifico Property Management",
    "wof:placetype":"venue"
},
  "geometry": {"coordinates":[-81.243607,42.987511],"type":"Point"}
}