{
  "type": "Feature",
  "properties": {
    "addr:full":"385 Weber St N Waterloo ON N2J 3J2",
    "addr:housenumber":"385",
    "addr:postcode":"n2j 3j2",
    "addr:street":"Weber St N",
    "iso:country":"CA",
    "sg:address":"385 Weber St N",
    "sg:city":"Waterloo",
    "sg:classifiers":[
        {
            "category":"Wholesale",
            "subcategory":"Machinery & Supplies",
            "type":"Manufacturing & Wholesale Goods"
        }
    ],
    "sg:phone":"+1 519 885 2603",
    "sg:postcode":"N2J 3J2",
    "sg:province":"ON",
    "sg:tags":[
        "salon",
        "beauty"
    ],
    "wof:name":"Intercosmetics",
    "wof:placetype":"venue"
},
  "geometry": {"coordinates":[-80.5249176025,43.4839286804],"type":"Point"}
}