{
  "type": "Feature",
  "properties": {
    "iso:country":"CA",
    "sg:address":"1501 Carling Ave",
    "sg:city":"Ottawa",
    "sg:classifiers":[
        {
            "category":"Professional",
            "subcategory":"Business Services",
            "type":"Services"
        }
    ],
    "sg:phone":"+1 613 728 7828",
    "sg:postcode":"K1Z 7M1",
    "sg:province":"ON",
    "sg:tags":[
        "foreground",
        "music"
    ],
    "wof:name":"Today's Music Inc",
    "wof:placetype":"venue"
},
  "geometry": {"coordinates":[-75.7422027588,45.3834075928],"type":"Point"}
}