{
  "type": "Feature",
  "properties": {
    "addr:full":"Airdrie AB T4B 2B9",
    "addr:postcode":"t4b 2b9",
    "iso:country":"CA",
    "sg:city":"Airdrie",
    "sg:classifiers":[
        {
            "category":"Food & Beverages",
            "subcategory":"Liquor & Beverages",
            "type":"Retail Goods"
        }
    ],
    "sg:phone":"+1 403 948 2222",
    "sg:postcode":"T4B 2B9",
    "sg:province":"AB",
    "sg:tags":[
        "store"
    ],
    "wof:name":"Royal Canada Liquor Store",
    "wof:placetype":"venue"
},
  "geometry": {"coordinates":[-114.01351928699999,51.2972412109],"type":"Point"}
}