{
  "type": "Feature",
  "properties": {
    "addr:full":"Scarborough ON M1X 1L9",
    "addr:postcode":"m1x 1l9",
    "iso:country":"CA",
    "sg:city":"Scarborough",
    "sg:classifiers":[
        {
            "category":"Home & Garden",
            "subcategory":"Home Furnishings",
            "type":"Retail Goods"
        }
    ],
    "sg:phone":"+1 416 321 1969",
    "sg:postcode":"M1X 1L9",
    "sg:province":"ON",
    "sg:tags":[
        "curtain",
        "made",
        "drapery"
    ],
    "wof:name":"Custom Blinds & Drapery",
    "wof:placetype":"venue"
},
  "geometry": {"coordinates":[-79.250237,43.830261],"type":"Point"}
}