{
  "type": "Feature",
  "properties": {
    "addr:full":"1925 Albert St Regina SK S4P 2T5",
    "addr:housenumber":"1925",
    "addr:postcode":"s4p 2t5",
    "addr:street":"Albert St",
    "iso:country":"CA",
    "sg:address":"1925 Albert St",
    "sg:city":"Regina",
    "sg:classifiers":[
        {
            "category":"Restaurant",
            "type":"Food & Drink"
        }
    ],
    "sg:phone":"+1 306 584 0241",
    "sg:postcode":"S4P 2T5",
    "sg:province":"SK",
    "sg:tags":[
        "pizza"
    ],
    "wof:name":"241 Pizza",
    "wof:placetype":"venue"
},
  "geometry": {"coordinates":[-104.617783,50.44836],"type":"Point"}
}