{
  "type": "Feature",
  "properties": {
    "addr:full":"130 Pickering Dr #101 Amherstburg ON N9V 3N6",
    "addr:housenumber":"130",
    "addr:postcode":"n9v 3n6",
    "addr:street":"Pickering Dr # 101",
    "iso:country":"CA",
    "sg:address":"130 Pickering Dr #101",
    "sg:city":"Amherstburg",
    "sg:classifiers":[
        {
            "category":"Real Estate",
            "subcategory":"Real Estate Operator",
            "type":"Services"
        }
    ],
    "sg:phone":"+1 519 736 3389",
    "sg:postcode":"N9V 3N6",
    "sg:province":"ON",
    "sg:tags":[
        "apartment"
    ],
    "wof:name":"Pickering Towers",
    "wof:placetype":"venue"
},
  "geometry": {"coordinates":[-83.110336,42.097626],"type":"Point"}
}