{
  "type": "Feature",
  "properties": {
    "iso:country":"CA",
    "sg:address":"1041 Pembroke St E",
    "sg:city":"Pembroke",
    "sg:classifiers":[
        {
            "category":"Insurance",
            "subcategory":"Insurance Agent",
            "type":"Services"
        }
    ],
    "sg:phone":"+1 613 687 2650",
    "sg:postcode":"K8A 6Z3",
    "sg:province":"ON",
    "sg:tags":[
        "adjuster"
    ],
    "wof:name":"Shumka Craig & Moore",
    "wof:placetype":"venue"
},
  "geometry": {"coordinates":[-77.0855255127,45.8240318298],"type":"Point"}
}