{
  "type": "Feature",
  "properties": {
    "addr:full":"911 Kootenay St N Cranbrook BC V1C 3V4",
    "addr:housenumber":"911",
    "addr:postcode":"v1c 3v4",
    "addr:street":"Kootenay St N",
    "iso:country":"CA",
    "sg:address":"911 Kootenay St N",
    "sg:city":"Cranbrook",
    "sg:classifiers":[
        {
            "category":"Recreation",
            "subcategory":"Marina",
            "type":"Entertainment"
        }
    ],
    "sg:phone":"+1 250 417 3311",
    "sg:postcode":"V1C 3V4",
    "sg:province":"BC",
    "sg:tags":[
        "repairing",
        "boat"
    ],
    "wof:name":"Kootenay Marine & Motor CO",
    "wof:placetype":"venue"
},
  "geometry": {"coordinates":[-115.757256,49.520344],"type":"Point"}
}