{
  "type": "Feature",
  "properties": {
    "addr:full":"1442 Safeway Cres Mississauga ON L4X 1H7",
    "addr:housenumber":"1442",
    "addr:postcode":"l4x 1h7",
    "addr:street":"Safeway Cres",
    "iso:country":"CA",
    "sg:address":"1442 Safeway Cres",
    "sg:city":"Mississauga",
    "sg:classifiers":[
        {
            "category":"Wholesale",
            "subcategory":"Machinery & Supplies",
            "type":"Manufacturing & Wholesale Goods"
        }
    ],
    "sg:phone":"+1 905 566 8196",
    "sg:postcode":"L4X 1H7",
    "sg:province":"ON",
    "sg:tags":[
        "cleaning"
    ],
    "wof:name":"Cavalex Oressure Cleaning",
    "wof:placetype":"venue"
},
  "geometry": {"coordinates":[-79.570847,43.601418],"type":"Point"}
}