{
  "type": "Feature",
  "properties": {
    "addr:full":"917 9 Ave SE Calgary AB T2G 0S5",
    "addr:housenumber":"917",
    "addr:postcode":"t2g 0s5",
    "addr:street":"9 Ave Se",
    "iso:country":"CA",
    "sg:address":"917 9 Ave SE",
    "sg:city":"Calgary",
    "sg:classifiers":[
        {
            "category":"Organizations",
            "subcategory":"Professional Association",
            "type":"Services"
        }
    ],
    "sg:phone":"+1 403 265 4171",
    "sg:postcode":"T2G 0S5",
    "sg:province":"AB",
    "wof:name":"Old Town Calgary Society",
    "wof:placetype":"venue"
},
  "geometry": {"coordinates":[-114.041053772,51.0431137085],"type":"Point"}
}