{
  "type": "Feature",
  "properties": {
    "addr:full":"1680 1E Av Quebec QC G1L 3L6",
    "addr:housenumber":"1680",
    "addr:postcode":"g1l 3l6",
    "addr:street":"1E Av",
    "iso:country":"CA",
    "sg:address":"1680 1E Av",
    "sg:city":"Quebec",
    "sg:classifiers":[
        {
            "category":"Shopping",
            "subcategory":"Optical Goods",
            "type":"Retail Goods"
        }
    ],
    "sg:phone":"+1 418 529 4191",
    "sg:postcode":"G1L 3L6",
    "sg:province":"QC",
    "sg:tags":[
        "optician"
    ],
    "wof:name":"Moreau-Rheume Opticiens",
    "wof:placetype":"venue"
},
  "geometry": {"coordinates":[-71.23664100000001,46.829372],"type":"Point"}
}