{
  "type": "Feature",
  "properties": {
    "iso:country":"CA",
    "sg:address":"3095 St Joseph Blvd",
    "sg:city":"Orleans",
    "sg:classifiers":[
        {
            "category":"Banks & Credit Unions",
            "subcategory":"Investment Brokerage",
            "type":"Services"
        }
    ],
    "sg:phone":"+1 613 824 7777",
    "sg:postcode":"K1E 3W6",
    "sg:province":"ON",
    "wof:name":"W H Stuart & Assoc",
    "wof:placetype":"venue"
},
  "geometry": {"coordinates":[-75.5093765259,45.479801178],"type":"Point"}
}