{
  "type": "Feature",
  "properties": {
    "addr:full":"777 68th Ave W Vancouver BC V6P 2T8",
    "addr:housenumber":"777",
    "addr:postcode":"v6p 2t8",
    "addr:street":"68Th Ave W",
    "iso:country":"CA",
    "sg:address":"777 68th Ave W",
    "sg:city":"Vancouver",
    "sg:classifiers":[
        {
            "category":"Organizations",
            "subcategory":"Religious Organization",
            "type":"Services"
        }
    ],
    "sg:phone":"+1 604 327 8212",
    "sg:postcode":"V6P 2T8",
    "sg:province":"BC",
    "sg:tags":[
        "church"
    ],
    "wof:name":"Heather Bible Chapel Nursery",
    "wof:placetype":"venue"
},
  "geometry": {"coordinates":[-123.122925,49.210426],"type":"Point"}
}