{
  "type": "Feature",
  "properties": {
    "addr:full":"PO Box 2280 STN Main Athabasca AB T9S 2B8",
    "addr:housenumber":"po",
    "addr:postcode":"t9s 2b8",
    "addr:street":"Box 2280 Stn Main",
    "iso:country":"CA",
    "sg:address":"PO Box 2280 STN Main",
    "sg:city":"Athabasca",
    "sg:classifiers":[
        {
            "category":"Professional",
            "subcategory":"Business Services",
            "type":"Services"
        }
    ],
    "sg:phone":"+1 780 525 2262",
    "sg:postcode":"T9S 2B8",
    "sg:province":"AB",
    "sg:tags":[
        "water",
        "field",
        "oil",
        "hauling"
    ],
    "wof:name":"Duniece Brothers Trucking Ltd",
    "wof:placetype":"venue"
},
  "geometry": {"coordinates":[-113.28351592999999,54.7212333679],"type":"Point"}
}