{
  "type": "Feature",
  "properties": {
    "iso:country":"CA",
    "sg:city":"Dartmouth",
    "sg:classifiers":[
        {
            "category":"Professional",
            "subcategory":"Lawyer & Legal Services",
            "type":"Services"
        }
    ],
    "sg:phone":"+1 902 466 2500",
    "sg:postcode":"B2Y 1H2",
    "sg:province":"NS",
    "sg:tags":[
        "attorney"
    ],
    "wof:name":"Coulthard, Peter L",
    "wof:placetype":"venue"
},
  "geometry": {"coordinates":[-63.56690979,44.6651039124],"type":"Point"}
}