{
  "type": "Feature",
  "properties": {
    "addr:full":"11 Sweetnam Dr Stittsville ON K2S 1G3",
    "addr:housenumber":"11",
    "addr:postcode":"k2s 1g3",
    "addr:street":"Sweetnam Dr",
    "iso:country":"CA",
    "sg:address":"11 Sweetnam Dr",
    "sg:city":"Stittsville",
    "sg:classifiers":[
        {
            "category":"Retail",
            "subcategory":"Auto Repair",
            "type":"Services"
        }
    ],
    "sg:phone":"+1 613 831 1931",
    "sg:postcode":"K2S 1G3",
    "sg:province":"ON",
    "sg:tags":[
        "repairing",
        "automobile"
    ],
    "wof:name":"Jim's hi Tech Auto Repairs Inc",
    "wof:placetype":"venue"
},
  "geometry": {"coordinates":[-75.91681699999999,45.278053],"type":"Point"}
}