{
  "type": "Feature",
  "properties": {
    "iso:country":"CA",
    "sg:address":"7260 Boul Julien-Bouthillier",
    "sg:city":"Saint-Hubert",
    "sg:classifiers":[
        {
            "category":"Professional",
            "subcategory":"Accounting & Tax Preparation",
            "type":"Services"
        }
    ],
    "sg:phone":"+1 450 676 7753",
    "sg:postcode":"J3Y 8S3",
    "sg:province":"QC",
    "sg:tags":[
        "accountant"
    ],
    "wof:name":"Cote, Michel CA",
    "wof:placetype":"venue"
},
  "geometry": {"coordinates":[-73.4008026123,45.4771652222],"type":"Point"}
}