{
  "type": "Feature",
  "properties": {
    "iso:country":"CA",
    "sg:address":"111 Rue Des Eglises",
    "sg:city":"Kinnear's Mills",
    "sg:classifiers":[
        {
            "category":"Travel",
            "subcategory":"Campground",
            "type":"Entertainment"
        }
    ],
    "sg:phone":"+1 418 424 3372",
    "sg:postcode":"G0N 1K0",
    "sg:province":"QC",
    "wof:name":"Camping Soleil Enr",
    "wof:placetype":"venue"
},
  "geometry": {"coordinates":[-71.3817977905,46.2222557068],"type":"Point"}
}