{
  "type": "Feature",
  "properties": {
    "addr:full":"2937 Main St Hillsborough NB E4H 2X9",
    "addr:housenumber":"2937",
    "addr:postcode":"e4h 2x9",
    "addr:street":"Main St",
    "iso:country":"CA",
    "sg:address":"2937 Main St",
    "sg:city":"Hillsborough",
    "sg:classifiers":[
        {
            "category":"Wholesale",
            "subcategory":"Fruits & Vegetables",
            "type":"Manufacturing & Wholesale Goods"
        }
    ],
    "sg:phone":"+1 506 734 2360",
    "sg:postcode":"E4H 2X9",
    "sg:province":"NB",
    "sg:tags":[
        "shipper"
    ],
    "wof:name":"Harper's Rasberry U-Pick",
    "wof:placetype":"venue"
},
  "geometry": {"coordinates":[-64.647018,45.92506],"type":"Point"}
}