{
  "type": "Feature",
  "properties": {
    "addr:full":"7199 Rue Saint-Hubert Montreal QC H2R 2N2",
    "addr:housenumber":"7199",
    "addr:postcode":"h2r 2n2",
    "addr:street":"Rue Saint-Hubert",
    "iso:country":"CA",
    "sg:address":"7199 Rue Saint-Hubert",
    "sg:city":"Montreal",
    "sg:classifiers":[
        {
            "category":"Shopping",
            "subcategory":"Gifts & Souvenirs",
            "type":"Retail Goods"
        }
    ],
    "sg:phone":"+1 514 278 7711",
    "sg:postcode":"H2R 2N2",
    "sg:province":"QC",
    "sg:tags":[
        "shop"
    ],
    "wof:name":"Super Prix Familial",
    "wof:placetype":"venue"
},
  "geometry": {"coordinates":[-73.613747,45.541157],"type":"Point"}
}