{
  "type": "Feature",
  "properties": {
    "addr:full":"247 1E Rue N St-Nazaire-Du-Lac-St-Jean QC G0W 2V0",
    "addr:housenumber":"247",
    "addr:postcode":"g0w 2v0",
    "addr:street":"1E Rue N",
    "iso:country":"CA",
    "sg:address":"247 1E Rue N",
    "sg:city":"St-Nazaire-Du-Lac-St-Jean",
    "sg:classifiers":[
        {
            "category":"Building & Trades",
            "subcategory":"Construction",
            "type":"Services"
        }
    ],
    "sg:phone":"+1 418 662 6320",
    "sg:postcode":"G0W 2V0",
    "sg:province":"QC",
    "sg:tags":[
        "excavating",
        "contractor"
    ],
    "wof:name":"Entreprises Nivelac Enr",
    "wof:placetype":"venue"
},
  "geometry": {"coordinates":[-71.4869308472,48.5753669739],"type":"Point"}
}