{
  "type": "Feature",
  "properties": {
    "addr:full":"Saint-Louis-DE-France QC G8T 1E8",
    "addr:postcode":"g8t 1e8",
    "iso:country":"CA",
    "sg:city":"Saint-Louis-DE-France",
    "sg:classifiers":[
        {
            "category":"Cinema",
            "subcategory":"Movie Rental",
            "type":"Entertainment"
        }
    ],
    "sg:phone":"+1 819 691 0796",
    "sg:postcode":"G8T 1E8",
    "sg:province":"QC",
    "sg:tags":[
        "leasing",
        "video",
        "disc",
        "tape"
    ],
    "wof:name":"Club Sos Video",
    "wof:placetype":"venue"
},
  "geometry": {"coordinates":[-72.5753326416,46.409072876],"type":"Point"}
}