{
  "type": "Feature",
  "properties": {
    "iso:country":"CA",
    "sg:address":"1050 Boul Saint-Laurent",
    "sg:city":"Montreal",
    "sg:classifiers":[
        {
            "category":"Food & Beverages",
            "subcategory":"Bakery",
            "type":"Retail Goods"
        }
    ],
    "sg:phone":"+1 514 954 0113",
    "sg:postcode":"H2Z 1J5",
    "sg:province":"QC",
    "sg:tags":[
        "baker"
    ],
    "wof:name":"Banh Ni Then Thanh",
    "wof:placetype":"venue"
},
  "geometry": {"coordinates":[-73.560211,45.508114],"type":"Point"}
}