{
  "type": "Feature",
  "properties": {
    "addr:full":"7652 Tecumseh Rd E Windsor ON N8T 1E9",
    "addr:housenumber":"7652",
    "addr:postcode":"n8t 1e9",
    "addr:street":"Tecumseh Rd E",
    "iso:country":"CA",
    "sg:address":"7652 Tecumseh Rd E",
    "sg:city":"Windsor",
    "sg:classifiers":[
        {
            "category":"Shopping",
            "subcategory":"Clothing, Apparel, & Fashions",
            "type":"Retail Goods"
        }
    ],
    "sg:phone":"+1 519 974 9340",
    "sg:postcode":"N8T 1E9",
    "sg:province":"ON",
    "wof:name":"Smart Set",
    "wof:placetype":"venue"
},
  "geometry": {"coordinates":[-82.9349441528,42.3137931824],"type":"Point"}
}