{
  "type": "Feature",
  "properties": {
    "addr:full":"5108 50 Ave Wetaskiwin AB T9A 0S6",
    "addr:housenumber":"5108",
    "addr:postcode":"t9a 0s6",
    "addr:street":"50 Ave",
    "iso:country":"CA",
    "sg:address":"5108 50 Ave",
    "sg:city":"Wetaskiwin",
    "sg:classifiers":[
        {
            "category":"Health Services",
            "subcategory":"Doctor",
            "type":"Services"
        }
    ],
    "sg:phone":"+1 780 352 2511",
    "sg:postcode":"T9A 0S6",
    "sg:province":"AB",
    "sg:tags":[
        "physician",
        "surgeon"
    ],
    "wof:name":"Community Clinic Wetaskiwin",
    "wof:placetype":"venue"
},
  "geometry": {"coordinates":[-113.376525879,52.9699821472],"type":"Point"}
}