{
  "type": "Feature",
  "properties": {
    "addr:full":"Timberlea NS B3T 1J3",
    "addr:postcode":"b3t 1j3",
    "iso:country":"CA",
    "sg:city":"Timberlea",
    "sg:classifiers":[
        {
            "category":"Food & Beverages",
            "subcategory":"Groceries & Convenience Stores",
            "type":"Retail Goods"
        }
    ],
    "sg:phone":"+1 902 876 2938",
    "sg:postcode":"B3T 1J3",
    "sg:province":"NS",
    "wof:name":"Fitzgerald Grocery",
    "wof:placetype":"venue"
},
  "geometry": {"coordinates":[-63.723133,44.649693],"type":"Point"}
}