{
  "type": "Feature",
  "properties": {
    "iso:country":"CA",
    "sg:address":"2211 Riverside Dr # 302",
    "sg:city":"Ottawa",
    "sg:classifiers":[
        {
            "category":"Health Services",
            "subcategory":"Doctor",
            "type":"Services"
        }
    ],
    "sg:phone":"+1 613 247 2238",
    "sg:postcode":"K1H 7X5",
    "sg:province":"ON",
    "sg:tags":[
        "physician",
        "surgeon"
    ],
    "wof:name":"Jarmuske, Mario MD",
    "wof:placetype":"venue"
},
  "geometry": {"coordinates":[-75.67761993409999,45.3884315491],"type":"Point"}
}