{
  "type": "Feature",
  "properties": {
    "iso:country":"CA",
    "sg:address":"5381 Foxmill Crt",
    "sg:city":"Mississauga",
    "sg:classifiers":[
        {
            "category":"Professional",
            "subcategory":"Management & Consulting",
            "type":"Services"
        }
    ],
    "sg:phone":"+1 905 819 8922",
    "sg:postcode":"L5M 5B6",
    "sg:province":"ON",
    "sg:tags":[
        "consultant",
        "business"
    ],
    "wof:name":"True North Change Management",
    "wof:placetype":"venue"
},
  "geometry": {"coordinates":[-79.71268463129999,43.5695228577],"type":"Point"}
}