{
  "type": "Feature",
  "properties": {
    "addr:full":"21938 Dundonald Rd Glencoe ON N0L 1M0",
    "addr:housenumber":"21938",
    "addr:postcode":"n0l 1m0",
    "addr:street":"Dundonald Rd",
    "iso:country":"CA",
    "sg:address":"21938 Dundonald Rd",
    "sg:city":"Glencoe",
    "sg:classifiers":[
        {
            "category":"Retail",
            "subcategory":"Veterinary Services",
            "type":"Services"
        }
    ],
    "sg:phone":"+1 519 287 2519",
    "sg:postcode":"N0L 1M0",
    "sg:province":"ON",
    "sg:tags":[
        "veterinarian"
    ],
    "wof:name":"Glencoe Animal Hospital",
    "wof:placetype":"venue"
},
  "geometry": {"coordinates":[-81.675468,42.72097],"type":"Point"}
}