{
  "type": "Feature",
  "properties": {
    "iso:country":"CA",
    "sg:city":"Middleton",
    "sg:classifiers":[
        {
            "category":"Recreation",
            "type":"Entertainment"
        }
    ],
    "sg:phone":"+1 902 825 4343",
    "sg:postcode":"B0S 1P0",
    "sg:province":"NS",
    "sg:tags":[
        "bingo",
        "game"
    ],
    "wof:name":"Nictaux Fire Hall",
    "wof:placetype":"venue"
},
  "geometry": {"coordinates":[-65.068649292,44.9424095154],"type":"Point"}
}