{
  "type": "Feature",
  "properties": {
    "addr:full":"191 Grandview Rd Nepean ON K2H 8B9",
    "addr:housenumber":"191",
    "addr:postcode":"k2h 8b9",
    "addr:street":"Grandview Rd",
    "iso:country":"CA",
    "sg:address":"191 Grandview Rd",
    "sg:city":"Nepean",
    "sg:classifiers":[
        {
            "category":"Professional",
            "subcategory":"Management & Consulting",
            "type":"Services"
        }
    ],
    "sg:phone":"+1 613 820 0796",
    "sg:postcode":"K2H 8B9",
    "sg:province":"ON",
    "sg:tags":[
        "consultant",
        "business"
    ],
    "wof:name":"Amc Consulting Group",
    "wof:placetype":"venue"
},
  "geometry": {"coordinates":[-75.858231,45.362633],"type":"Point"}
}