{
  "type": "Feature",
  "properties": {
    "addr:full":"2027 Portage Ave Winnipeg MB R3J 0K6",
    "addr:housenumber":"2027",
    "addr:postcode":"r3j 0k6",
    "addr:street":"Portage Ave",
    "iso:country":"CA",
    "sg:address":"2027 Portage Ave",
    "sg:city":"Winnipeg",
    "sg:classifiers":[
        {
            "category":"Health Services",
            "subcategory":"Doctor",
            "type":"Services"
        }
    ],
    "sg:phone":"+1 204 837 8559",
    "sg:postcode":"R3J 0K6",
    "sg:province":"MB",
    "sg:tags":[
        "dentist"
    ],
    "wof:name":"Avenue Dental Ctr",
    "wof:placetype":"venue"
},
  "geometry": {"coordinates":[-97.229668,49.877731],"type":"Point"}
}