{
  "type": "Feature",
  "properties": {
    "addr:full":"391 Rue Danis Salaberry-DE-Valleyfield QC J6S 1M9",
    "addr:housenumber":"391",
    "addr:postcode":"j6s 1m9",
    "addr:street":"Rue Danis",
    "iso:country":"CA",
    "sg:address":"391 Rue Danis",
    "sg:city":"Salaberry-DE-Valleyfield",
    "sg:classifiers":[
        {
            "category":"Home & Garden",
            "subcategory":"Household Appliances",
            "type":"Retail Goods"
        }
    ],
    "sg:phone":"+1 450 373 0448",
    "sg:postcode":"J6S 1M9",
    "sg:province":"QC",
    "sg:tags":[
        "refrigerator",
        "freezer"
    ],
    "wof:name":"Appareils Menages R Lalonde",
    "wof:placetype":"venue"
},
  "geometry": {"coordinates":[-74.13357499999999,45.265095],"type":"Point"}
}