{
  "type": "Feature",
  "properties": {
    "iso:country":"CA",
    "sg:address":"391 Rue Danis",
    "sg:city":"Salaberry-DE-Valleyfield",
    "sg:classifiers":[
        {
            "category":"Home & Garden",
            "subcategory":"Household Appliances",
            "type":"Retail Goods"
        }
    ],
    "sg:phone":"+1 450 373 0448",
    "sg:postcode":"J6S 1M9",
    "sg:province":"QC",
    "sg:tags":[
        "refrigerator",
        "freezer"
    ],
    "wof:name":"Appareils Menages R Lalonde",
    "wof:placetype":"venue"
},
  "geometry": {"coordinates":[-74.133575,45.265095],"type":"Point"}
}