{
  "type": "Feature",
  "properties": {
    "iso:country":"CA",
    "sg:address":"688 River Rd",
    "sg:city":"Braeside",
    "sg:classifiers":[
        {
            "category":"Manufacturing",
            "subcategory":"Metals",
            "type":"Manufacturing & Wholesale Goods"
        }
    ],
    "sg:phone":"+1 613 623 3967",
    "sg:postcode":"K0A 1G0",
    "sg:province":"ON",
    "sg:tags":[
        "door"
    ],
    "wof:name":"Murdoch's Wood Products",
    "wof:placetype":"venue"
},
  "geometry": {"coordinates":[-76.39901733400001,45.457775116],"type":"Point"}
}