{
  "type": "Feature",
  "properties": {
    "addr:full":"Bridgenorth ON K0L 1H0",
    "addr:postcode":"k0l 1h0",
    "iso:country":"CA",
    "sg:city":"Bridgenorth",
    "sg:classifiers":[
        {
            "category":"Autos & Motor Vehicles",
            "subcategory":"Boat Sales",
            "type":"Retail Goods"
        }
    ],
    "sg:phone":"+1 705 292 0628",
    "sg:postcode":"K0L 1H0",
    "sg:province":"ON",
    "sg:tags":[
        "top",
        "upholstery",
        "cover"
    ],
    "wof:name":"Sew It All",
    "wof:placetype":"venue"
},
  "geometry": {"coordinates":[-78.38603973390001,44.3769226074],"type":"Point"}
}