{
  "type": "Feature",
  "properties": {
    "addr:full":"3291 Ch Sainte-Foy # 111 Sainte-Foy QC G1X 3V2",
    "addr:housenumber":"3291",
    "addr:postcode":"g1x 3v2",
    "addr:street":"Ch Sainte-Foy # 111",
    "iso:country":"CA",
    "sg:address":"3291 Ch Sainte-Foy # 111",
    "sg:city":"Sainte-Foy",
    "sg:classifiers":[
        {
            "category":"Personal",
            "subcategory":"Beauty Salon",
            "type":"Services"
        }
    ],
    "sg:phone":"+1 418 653 8983",
    "sg:postcode":"G1X 3V2",
    "sg:province":"QC",
    "wof:name":"Coiffure Unisexe Original",
    "wof:placetype":"venue"
},
  "geometry": {"coordinates":[-71.2917633057,46.7692108154],"type":"Point"}
}