{
  "type": "Feature",
  "properties": {
    "addr:full":"80 Church St Miramichi NB E1N 1T8",
    "addr:housenumber":"80",
    "addr:postcode":"e1n 1t8",
    "addr:street":"Church St",
    "iso:country":"CA",
    "sg:address":"80 Church St",
    "sg:city":"Miramichi",
    "sg:classifiers":[
        {
            "category":"Wholesale",
            "subcategory":"Scrap",
            "type":"Manufacturing & Wholesale Goods"
        }
    ],
    "sg:phone":"+1 506 773 6845",
    "sg:postcode":"E1N 1T8",
    "sg:province":"NB",
    "sg:tags":[
        "recycling",
        "can",
        "bottle",
        "depot"
    ],
    "wof:name":"Chatham Redemption Ctr",
    "wof:placetype":"venue"
},
  "geometry": {"coordinates":[-65.467026,47.02813],"type":"Point"}
}