{
  "type": "Feature",
  "properties": {
    "addr:full":"1315 Rue Tourigny Laval QC H7W 5G8",
    "addr:housenumber":"1315",
    "addr:postcode":"h7w 5g8",
    "addr:street":"Rue Tourigny",
    "iso:country":"CA",
    "sg:address":"1315 Rue Tourigny",
    "sg:city":"Laval",
    "sg:classifiers":[
        {
            "category":"Building & Trades",
            "subcategory":"Cleaning & Sanitation",
            "type":"Services"
        }
    ],
    "sg:phone":"+1 450 687 6985",
    "sg:postcode":"H7W 5G8",
    "sg:province":"QC",
    "sg:tags":[
        "janitor"
    ],
    "wof:name":"Peter's Building Maintenance",
    "wof:placetype":"venue"
},
  "geometry": {"coordinates":[-73.78679700000001,45.540989],"type":"Point"}
}