{
  "type": "Feature",
  "properties": {
    "addr:full":"6756 Hwy 3 Hunts Point NS B0T 1G0",
    "addr:housenumber":"6756",
    "addr:postcode":"b0t 1g0",
    "addr:street":"Hwy 3",
    "iso:country":"CA",
    "sg:address":"6756 Hwy 3",
    "sg:city":"Hunts Point",
    "sg:classifiers":[
        {
            "category":"Food & Beverages",
            "subcategory":"Groceries & Convenience Stores",
            "type":"Retail Goods"
        }
    ],
    "sg:phone":"+1 902 683 2386",
    "sg:postcode":"B0T 1G0",
    "sg:province":"NS",
    "wof:name":"Hyway Market",
    "wof:placetype":"venue"
},
  "geometry": {"coordinates":[-64.7700576782,43.9538116455],"type":"Point"}
}