{
  "type": "Feature",
  "properties": {
    "addr:full":"4772 MT Albert Side Rd Mount Albert ON L0G 1M0",
    "addr:housenumber":"4772",
    "addr:postcode":"l0g 1m0",
    "addr:street":"Mt;Side Rd",
    "iso:country":"CA",
    "sg:address":"4772 MT Albert Side Rd",
    "sg:city":"Mount Albert",
    "sg:classifiers":[
        {
            "category":"Building & Trades",
            "subcategory":"Construction",
            "type":"Services"
        }
    ],
    "sg:phone":"+1 905 473 2327",
    "sg:postcode":"L0G 1M0",
    "sg:province":"ON",
    "sg:tags":[
        "paving",
        "contractor"
    ],
    "wof:name":"K J Beamish Construction Ltd",
    "wof:placetype":"venue"
},
  "geometry": {"coordinates":[-80.0677490234,43.1776847839],"type":"Point"}
}