{
  "type": "Feature",
  "properties": {
    "iso:country":"CA",
    "sg:city":"Port Coquitlam",
    "sg:classifiers":[
        {
            "category":"Professional",
            "subcategory":"Business Services",
            "type":"Services"
        }
    ],
    "sg:phone":"+1 604 944 4003",
    "sg:postcode":"V3C 6H5",
    "sg:province":"BC",
    "sg:tags":[
        "water",
        "treatment"
    ],
    "wof:name":"Hammachem Water Treatment",
    "wof:placetype":"venue"
},
  "geometry": {"coordinates":[-122.77977,49.257984],"type":"Point"}
}