{
  "type": "Feature",
  "properties": {
    "addr:full":"4431 Hastings St Burnaby BC V5C 2K1",
    "addr:housenumber":"4431",
    "addr:postcode":"v5c 2k1",
    "addr:street":"Hastings St",
    "iso:country":"CA",
    "sg:address":"4431 Hastings St",
    "sg:city":"Burnaby",
    "sg:classifiers":[
        {
            "category":"Retail",
            "subcategory":"Veterinary Services",
            "type":"Services"
        }
    ],
    "sg:phone":"+1 604 298 9941",
    "sg:postcode":"V5C 2K1",
    "sg:province":"BC",
    "sg:tags":[
        "veterinarian"
    ],
    "wof:name":"North Burnaby Veterinary Hosp",
    "wof:placetype":"venue"
},
  "geometry": {"coordinates":[-123.00495100000001,49.281216],"type":"Point"}
}