{
  "type": "Feature",
  "properties": {
    "addr:full":"Sainte-Martine QC J0S 1V0",
    "addr:postcode":"j0s 1v0",
    "iso:country":"CA",
    "sg:city":"Sainte-Martine",
    "sg:classifiers":[
        {
            "category":"Personal",
            "subcategory":"Tanning Parlor",
            "type":"Services"
        }
    ],
    "sg:phone":"+1 450 427 1870",
    "sg:postcode":"J0S 1V0",
    "sg:province":"QC",
    "sg:tags":[
        "salon"
    ],
    "wof:name":"Bronzage Sunset",
    "wof:placetype":"venue"
},
  "geometry": {"coordinates":[-73.799126,45.24902],"type":"Point"}
}