{
  "type": "Feature",
  "properties": {
    "iso:country":"CA",
    "sg:city":"Woodstock",
    "sg:classifiers":[
        {
            "category":"Cinema",
            "subcategory":"Movie Rental",
            "type":"Entertainment"
        }
    ],
    "sg:phone":"+1 519 421 3127",
    "sg:postcode":"N4S 1E8",
    "sg:province":"ON",
    "sg:tags":[
        "leasing",
        "video",
        "disc",
        "tape"
    ],
    "wof:name":"Rogers Video",
    "wof:placetype":"venue"
},
  "geometry": {"coordinates":[-80.74671936039999,43.131690979],"type":"Point"}
}