{
  "type": "Feature",
  "properties": {
    "addr:full":"587 Country Club Mews London ON N6C 5R1",
    "addr:housenumber":"587",
    "addr:postcode":"n6c 5r1",
    "addr:street":"Country Club Mews",
    "iso:country":"CA",
    "sg:address":"587 Country Club Mews",
    "sg:city":"London",
    "sg:classifiers":[
        {
            "category":"Professional",
            "subcategory":"Engineering",
            "type":"Services"
        }
    ],
    "sg:phone":"+1 519 685 1213",
    "sg:postcode":"N6C 5R1",
    "sg:province":"ON",
    "sg:tags":[
        "vibration",
        "measurement"
    ],
    "wof:name":"Predictive Analysis Ltd",
    "wof:placetype":"venue"
},
  "geometry": {"coordinates":[-81.2513580322,42.9509315491],"type":"Point"}
}