{
  "type": "Feature",
  "properties": {
    "addr:full":"735 4th Ave Hope BC V0X 1L0",
    "addr:housenumber":"735",
    "addr:postcode":"v0x 1l0",
    "addr:street":"4Th Ave",
    "iso:country":"CA",
    "sg:address":"735 4th Ave",
    "sg:city":"Hope",
    "sg:classifiers":[
        {
            "category":"Health Services",
            "subcategory":"Doctor",
            "type":"Services"
        }
    ],
    "sg:phone":"+1 604 869 5648",
    "sg:postcode":"V0X 1L0",
    "sg:province":"BC",
    "sg:tags":[
        "physician",
        "surgeon"
    ],
    "wof:name":"Murakami Clinic",
    "wof:placetype":"venue"
},
  "geometry": {"coordinates":[-121.44033050500001,49.3815307617],"type":"Point"}
}