{
  "type": "Feature",
  "properties": {
    "addr:full":"Burnaby BC V5J 4V9",
    "addr:postcode":"v5j 4v9",
    "iso:country":"CA",
    "sg:city":"Burnaby",
    "sg:classifiers":[
        {
            "category":"Retail",
            "subcategory":"Auto Repair",
            "type":"Services"
        }
    ],
    "sg:phone":"+1 604 430 1551",
    "sg:postcode":"V5J 4V9",
    "sg:province":"BC",
    "sg:tags":[
        "recreational",
        "vehicle"
    ],
    "wof:name":"Travco Rv Svc Ctr Ltd",
    "wof:placetype":"venue"
},
  "geometry": {"coordinates":[-122.97451,49.219723],"type":"Point"}
}