{
  "type": "Feature",
  "properties": {
    "addr:full":"4300 Matchette Rd Windsor ON N9C 4C5",
    "addr:housenumber":"4300",
    "addr:postcode":"n9c 4c5",
    "addr:street":"Matchette Rd",
    "iso:country":"CA",
    "sg:address":"4300 Matchette Rd",
    "sg:city":"Windsor",
    "sg:classifiers":[
        {
            "category":"Wholesale",
            "subcategory":"Petroleum",
            "type":"Manufacturing & Wholesale Goods"
        }
    ],
    "sg:phone":"+1 519 254 4332",
    "sg:postcode":"N9C 4C5",
    "sg:province":"ON",
    "sg:tags":[
        "pipe",
        "line",
        "company"
    ],
    "wof:name":"B P Canada Energy CO",
    "wof:placetype":"venue"
},
  "geometry": {"coordinates":[-83.070587,42.278557],"type":"Point"}
}