{
  "type": "Feature",
  "properties": {
    "addr:full":"Vancouver BC V6P 6T3",
    "addr:postcode":"v6p 6t3",
    "iso:country":"CA",
    "sg:city":"Vancouver",
    "sg:classifiers":[
        {
            "category":"Manufacturing",
            "subcategory":"Tools & Machinery",
            "type":"Manufacturing & Wholesale Goods"
        }
    ],
    "sg:phone":"+1 604 324 3822",
    "sg:postcode":"V6P 6T3",
    "sg:province":"BC",
    "sg:tags":[
        "fire",
        "equipment",
        "protection",
        "safety"
    ],
    "wof:name":"Brookdale International Systs",
    "wof:placetype":"venue"
},
  "geometry": {"coordinates":[-123.119232178,49.2062683105],"type":"Point"}
}