{
  "type": "Feature",
  "properties": {
    "addr:full":"350 Principale Lac-Bouchette QC G0W 1V0",
    "addr:housenumber":"350",
    "addr:postcode":"g0w 1v0",
    "addr:street":"Principale",
    "iso:country":"CA",
    "sg:address":"350 Principale",
    "sg:city":"Lac-Bouchette",
    "sg:classifiers":[
        {
            "category":"Recreation",
            "type":"Entertainment"
        }
    ],
    "sg:phone":"+1 418 348 9247",
    "sg:postcode":"G0W 1V0",
    "sg:province":"QC",
    "sg:tags":[
        "auditorium",
        "rooms",
        "banquet",
        "hall"
    ],
    "wof:name":"Salle Communautaire",
    "wof:placetype":"venue"
},
  "geometry": {"coordinates":[-72.1877822876,48.2507476807],"type":"Point"}
}