{
  "type": "Feature",
  "properties": {
    "addr:full":"Scarborough ON M1S 4J9",
    "addr:postcode":"m1s 4j9",
    "iso:country":"CA",
    "sg:city":"Scarborough",
    "sg:classifiers":[
        {
            "category":"Home & Garden",
            "subcategory":"Home Furnishings",
            "type":"Retail Goods"
        }
    ],
    "sg:phone":"+1 416 291 5218",
    "sg:postcode":"M1S 4J9",
    "sg:province":"ON",
    "sg:tags":[
        "housewares"
    ],
    "wof:name":"Full Time Home Appliances Ctr",
    "wof:placetype":"venue"
},
  "geometry": {"coordinates":[-79.265556,43.788307],"type":"Point"}
}