{
  "type": "Feature",
  "properties": {
    "addr:full":"2 Dixon St Kinmount ON K0M 2A0",
    "addr:housenumber":"2",
    "addr:postcode":"k0m 2a0",
    "addr:street":"Dixon St",
    "iso:country":"CA",
    "sg:address":"2 Dixon St",
    "sg:city":"Kinmount",
    "sg:classifiers":[
        {
            "category":"Recreation",
            "type":"Entertainment"
        }
    ],
    "sg:phone":"+1 705 488 2069",
    "sg:postcode":"K0M 2A0",
    "sg:province":"ON",
    "sg:tags":[
        "government",
        "hall",
        "auditorium"
    ],
    "wof:name":"Kinmount Community Ctr",
    "wof:placetype":"venue"
},
  "geometry": {"coordinates":[-78.65147399999999,44.780891],"type":"Point"}
}