{
  "type": "Feature",
  "properties": {
    "addr:full":"2828 County Rd 124 Duntroon ON L0M 1H0",
    "addr:housenumber":"2828",
    "addr:postcode":"l0m 1h0",
    "addr:street":"County Rd 124",
    "iso:country":"CA",
    "sg:address":"2828 County Rd 124",
    "sg:city":"Duntroon",
    "sg:classifiers":[
        {
            "category":"Real Estate",
            "subcategory":"Surveying",
            "type":"Services"
        }
    ],
    "sg:phone":"+1 705 444 6203",
    "sg:postcode":"L0M 1H0",
    "sg:province":"ON",
    "sg:tags":[
        "surveyor"
    ],
    "wof:name":"Martin Knisley/Land Surveyor",
    "wof:placetype":"venue"
},
  "geometry": {"coordinates":[-80.19512899999999,44.399162],"type":"Point"}
}