{
  "type": "Feature",
  "properties": {
    "addr:full":"120 Milltown Blvd St Stephen NB E3L 1G6",
    "addr:housenumber":"120",
    "addr:postcode":"e3l 1g6",
    "addr:street":"Milltown Blvd",
    "iso:country":"CA",
    "sg:address":"120 Milltown Blvd",
    "sg:city":"St Stephen",
    "sg:classifiers":[
        {
            "category":"Government",
            "subcategory":"Office",
            "type":"Public Place"
        }
    ],
    "sg:phone":"+1 506 466 3928",
    "sg:postcode":"E3L 1G6",
    "sg:province":"NB",
    "wof:name":"Member of Parliament",
    "wof:placetype":"venue"
},
  "geometry": {"coordinates":[-67.280128479,45.1923217773],"type":"Point"}
}