{
  "type": "Feature",
  "properties": {
    "iso:country":"CA",
    "sg:address":"301 Boul Iberville",
    "sg:city":"Repentigny",
    "sg:classifiers":[
        {
            "category":"Shopping",
            "subcategory":"Tobacco",
            "type":"Retail Goods"
        }
    ],
    "sg:phone":"+1 450 581 6240",
    "sg:postcode":"J6A 2A4",
    "sg:province":"QC",
    "sg:tags":[
        "cigarette",
        "cigar",
        "dealer"
    ],
    "wof:name":"Tabagie Gilles",
    "wof:placetype":"venue"
},
  "geometry": {"coordinates":[-73.4606933594,45.7310218811],"type":"Point"}
}