{
  "type": "Feature",
  "properties": {
    "addr:full":"General Delivery Ocean Falls BC V0T 1P0",
    "addr:postcode":"v0t 1p0",
    "iso:country":"CA",
    "sg:address":"General Delivery",
    "sg:city":"Ocean Falls",
    "sg:classifiers":[
        {
            "category":"Utilities",
            "subcategory":"Electric",
            "type":"Services"
        }
    ],
    "sg:phone":"+1 250 289 3868",
    "sg:postcode":"V0T 1P0",
    "sg:province":"BC",
    "sg:tags":[
        "company"
    ],
    "wof:name":"Central Coast Power Corp",
    "wof:placetype":"venue"
},
  "geometry": {"coordinates":[-127.69297,52.354076],"type":"Point"}
}