{
  "type": "Feature",
  "properties": {
    "addr:full":"Cornwall ON K6H 4M4",
    "addr:postcode":"k6h 4m4",
    "iso:country":"CA",
    "sg:city":"Cornwall",
    "sg:classifiers":[
        {
            "category":"Health Services",
            "subcategory":"Doctor",
            "type":"Services"
        }
    ],
    "sg:phone":"+1 613 933 6959",
    "sg:postcode":"K6H 4M4",
    "sg:province":"ON",
    "sg:tags":[
        "physician",
        "surgeon"
    ],
    "wof:name":"Blach, Peter MD",
    "wof:placetype":"venue"
},
  "geometry": {"coordinates":[-74.71708700000001,45.027435],"type":"Point"}
}