{
  "type": "Feature",
  "properties": {
    "addr:full":"30 Main St Dowling ON P0M 1R0",
    "addr:housenumber":"30",
    "addr:postcode":"p0m 1r0",
    "addr:street":"Main St",
    "iso:country":"CA",
    "sg:address":"30 Main St",
    "sg:city":"Dowling",
    "sg:classifiers":[
        {
            "category":"Shopping",
            "subcategory":"Pharmacy",
            "type":"Retail Goods"
        }
    ],
    "sg:phone":"+1 705 855 4562",
    "sg:postcode":"P0M 1R0",
    "sg:province":"ON",
    "wof:name":"Dowling Ida Pharmacy",
    "wof:placetype":"venue"
},
  "geometry": {"coordinates":[-81.334396,46.586346],"type":"Point"}
}