{
  "type": "Feature",
  "properties": {
    "addr:full":"Montreal QC H3W 3E3",
    "addr:postcode":"h3w 3e3",
    "iso:country":"CA",
    "sg:city":"Montreal",
    "sg:classifiers":[
        {
            "category":"Health Services",
            "subcategory":"Health Practitioner",
            "type":"Services"
        }
    ],
    "sg:phone":"+1 514 731 1411",
    "sg:postcode":"H3W 3E3",
    "sg:province":"QC",
    "sg:tags":[
        "speech",
        "therapy",
        "hearing"
    ],
    "wof:name":"Wohl, Elaine",
    "wof:placetype":"venue"
},
  "geometry": {"coordinates":[-73.64556899999999,45.491379],"type":"Point"}
}