{
  "type": "Feature",
  "properties": {
    "addr:full":"48 Slater Rd Strathmore AB T1P 1J3",
    "addr:housenumber":"48",
    "addr:postcode":"t1p 1j3",
    "addr:street":"Slater Rd",
    "iso:country":"CA",
    "sg:address":"48 Slater Rd",
    "sg:city":"Strathmore",
    "sg:classifiers":[
        {
            "category":"Freight",
            "type":"Transportation"
        }
    ],
    "sg:phone":"+1 403 934 1911",
    "sg:postcode":"T1P 1J3",
    "sg:province":"AB",
    "sg:tags":[
        "commercial",
        "storage"
    ],
    "wof:name":"Al-Ron Mini Storage",
    "wof:placetype":"venue"
},
  "geometry": {"coordinates":[-113.38497924799999,51.0317878723],"type":"Point"}
}