{
  "type": "Feature",
  "properties": {
    "iso:country":"CA",
    "sg:address":"314 Granville St",
    "sg:city":"Port Hawkesbury",
    "sg:classifiers":[
        {
            "category":"Real Estate",
            "subcategory":"Real Estate Agent",
            "type":"Services"
        }
    ],
    "sg:phone":"+1 902 625 3228",
    "sg:postcode":"B9A 2M6",
    "sg:province":"NS",
    "wof:name":"Mary-Pat Realty",
    "wof:placetype":"venue"
},
  "geometry": {"coordinates":[-61.3632850647,45.6148452759],"type":"Point"}
}