{
  "type": "Feature",
  "properties": {
    "addr:full":"65 University Ave E Waterloo ON N2J 2V9",
    "addr:housenumber":"65",
    "addr:postcode":"n2j 2v9",
    "addr:street":"University Ave E",
    "iso:country":"CA",
    "sg:address":"65 University Ave E",
    "sg:city":"Waterloo",
    "sg:classifiers":[
        {
            "category":"Health Services",
            "subcategory":"Doctor",
            "type":"Services"
        }
    ],
    "sg:phone":"+1 519 886 2241",
    "sg:postcode":"N2J 2V9",
    "sg:province":"ON",
    "sg:tags":[
        "physician",
        "surgeon"
    ],
    "wof:name":"Garboll, G M MD",
    "wof:placetype":"venue"
},
  "geometry": {"coordinates":[-80.5215682983,43.4772453308],"type":"Point"}
}