{
  "type": "Feature",
  "properties": {
    "addr:full":"82 Old Kingston Rd Ajax ON L1T 2Z8",
    "addr:housenumber":"82",
    "addr:postcode":"l1t 2z8",
    "addr:street":"Old Kingston Rd",
    "iso:country":"CA",
    "sg:address":"82 Old Kingston Rd",
    "sg:city":"Ajax",
    "sg:classifiers":[
        {
            "category":"Shopping",
            "subcategory":"Used Merchandise",
            "type":"Retail Goods"
        }
    ],
    "sg:phone":"+1 905 686 4477",
    "sg:postcode":"L1T 2Z8",
    "sg:province":"ON",
    "sg:tags":[
        "second",
        "store",
        "hand"
    ],
    "wof:name":"4477 Shop",
    "wof:placetype":"venue"
},
  "geometry": {"coordinates":[-79.05902862550001,43.8544540405],"type":"Point"}
}