{
  "type": "Feature",
  "properties": {
    "addr:full":"14949 Highway 7 Tangier NS B0J 3H0",
    "addr:housenumber":"14949",
    "addr:postcode":"b0j 3h0",
    "addr:street":"Highway 7",
    "iso:country":"CA",
    "sg:address":"14949 Highway 7",
    "sg:city":"Tangier",
    "sg:classifiers":[
        {
            "category":"Building & Trades",
            "subcategory":"Construction",
            "type":"Services"
        }
    ],
    "sg:phone":"+1 902 772 2985",
    "sg:postcode":"B0J 3H0",
    "sg:province":"NS",
    "sg:tags":[
        "excavating",
        "contractor"
    ],
    "wof:name":"B & P Enterprises Ltd",
    "wof:placetype":"venue"
},
  "geometry": {"coordinates":[-62.69854,44.803349],"type":"Point"}
}