{
  "type": "Feature",
  "properties": {
    "addr:full":"2155 Lawrence Ave E # 10 Scarborough ON M1R 5G9",
    "addr:housenumber":"2155",
    "addr:postcode":"m1r 5g9",
    "addr:street":"Lawrence Ave E # 10",
    "iso:country":"CA",
    "sg:address":"2155 Lawrence Ave E # 10",
    "sg:city":"Scarborough",
    "sg:classifiers":[
        {
            "category":"Health Services",
            "subcategory":"Doctor",
            "type":"Services"
        }
    ],
    "sg:phone":"+1 416 757 9999",
    "sg:postcode":"M1R 5G9",
    "sg:province":"ON",
    "sg:tags":[
        "dentist"
    ],
    "wof:name":"Scarborough Dental Office",
    "wof:placetype":"venue"
},
  "geometry": {"coordinates":[-79.28518699999999,43.747288],"type":"Point"}
}