{
  "type": "Feature",
  "properties": {
    "addr:full":"1507 Merivale Rd Nepean ON K2E 5P3",
    "addr:housenumber":"1507",
    "addr:postcode":"k2e 5p3",
    "addr:street":"Merivale Rd",
    "iso:country":"CA",
    "sg:address":"1507 Merivale Rd",
    "sg:city":"Nepean",
    "sg:classifiers":[
        {
            "category":"Retail",
            "subcategory":"Auto Repair",
            "type":"Services"
        }
    ],
    "sg:phone":"+1 613 224 8171",
    "sg:postcode":"K2E 5P3",
    "sg:province":"ON",
    "sg:tags":[
        "repairing",
        "automobile"
    ],
    "wof:name":"Garry's Service Ctr",
    "wof:placetype":"venue"
},
  "geometry": {"coordinates":[-75.736977,45.357376],"type":"Point"}
}