{
  "type": "Feature",
  "properties": {
    "addr:full":"Hwy 531 Bonfield ON P0H 1E0",
    "addr:postcode":"p0h 1e0",
    "addr:street":"Hwy 531",
    "iso:country":"CA",
    "sg:address":"Hwy 531",
    "sg:city":"Bonfield",
    "sg:classifiers":[
        {
            "category":"Government",
            "subcategory":"Office",
            "type":"Public Place"
        }
    ],
    "sg:phone":"+1 705 776 2278",
    "sg:postcode":"P0H 1E0",
    "sg:province":"ON",
    "sg:tags":[
        "village"
    ],
    "wof:name":"Ontario Employment Resource",
    "wof:placetype":"venue"
},
  "geometry": {"coordinates":[-79.14709499999999,46.238949],"type":"Point"}
}