{
  "type": "Feature",
  "properties": {
    "addr:full":"5209 50th St Tofield AB T0B 4J0",
    "addr:housenumber":"5209",
    "addr:postcode":"t0b 4j0",
    "addr:street":"50Th St",
    "iso:country":"CA",
    "sg:address":"5209 50th St",
    "sg:city":"Tofield",
    "sg:classifiers":[
        {
            "category":"Shopping",
            "type":"Retail Goods"
        }
    ],
    "sg:phone":"+1 780 662 3366",
    "sg:postcode":"T0B 4J0",
    "sg:province":"AB",
    "sg:tags":[
        "picture",
        "frame"
    ],
    "wof:name":"Hearthstone Arts & Crafts Ctr",
    "wof:placetype":"venue"
},
  "geometry": {"coordinates":[-112.667236,53.369301],"type":"Point"}
}