{
  "type": "Feature",
  "properties": {
    "addr:full":"Saint-Jean-DE-Matha QC J0K 2S0",
    "addr:postcode":"j0k 2s0",
    "iso:country":"CA",
    "sg:city":"Saint-Jean-DE-Matha",
    "sg:classifiers":[
        {
            "category":"Health Services",
            "subcategory":"Optometrist",
            "type":"Services"
        }
    ],
    "sg:phone":"+1 450 752 0622",
    "sg:postcode":"J0K 2S0",
    "sg:province":"QC",
    "wof:name":"Lunetterie Joliette Inc",
    "wof:placetype":"venue"
},
  "geometry": {"coordinates":[-73.52838134770001,46.2256088257],"type":"Point"}
}