{
  "type": "Feature",
  "properties": {
    "iso:country":"CA",
    "sg:address":"1361 Rice Rd",
    "sg:city":"Welland",
    "sg:classifiers":[
        {
            "category":"Building & Trades",
            "subcategory":"Landscaping Services",
            "type":"Services"
        }
    ],
    "sg:phone":"+1 905 892 5832",
    "sg:postcode":"L3B 5N5",
    "sg:province":"ON",
    "sg:tags":[
        "center",
        "garden",
        "landscape",
        "contractor"
    ],
    "wof:name":"Rice Road Greenhouses Ltd",
    "wof:placetype":"venue"
},
  "geometry": {"coordinates":[-79.2699966431,43.0283317566],"type":"Point"}
}