{
  "type": "Feature",
  "properties": {
    "addr:full":"Saskatoon SK S7L 4P5",
    "addr:postcode":"s7l 4p5",
    "iso:country":"CA",
    "sg:city":"Saskatoon",
    "sg:classifiers":[
        {
            "category":"Restaurant",
            "type":"Food & Drink"
        }
    ],
    "sg:phone":"+1 306 382 1048",
    "sg:postcode":"S7L 4P5",
    "sg:province":"SK",
    "wof:name":"Jacky D's",
    "wof:placetype":"venue"
},
  "geometry": {"coordinates":[-106.72698211700001,52.1436843872],"type":"Point"}
}