{
  "type": "Feature",
  "properties": {
    "addr:full":"Saint-Laurent QC H4N 1S2",
    "addr:postcode":"h4n 1s2",
    "iso:country":"CA",
    "sg:city":"Saint-Laurent",
    "sg:classifiers":[
        {
            "category":"Manufacturing",
            "subcategory":"Tools & Machinery",
            "type":"Manufacturing & Wholesale Goods"
        }
    ],
    "sg:phone":"+1 514 336 6665",
    "sg:postcode":"H4N 1S2",
    "sg:province":"QC",
    "sg:tags":[
        "equipment",
        "nurseryman",
        "supply"
    ],
    "wof:name":"Perlite Canada Inc",
    "wof:placetype":"venue"
},
  "geometry": {"coordinates":[-73.66198730470001,45.5270423889],"type":"Point"}
}