{
  "type": "Feature",
  "properties": {
    "iso:country":"CA",
    "sg:address":"6828 Melmack Cres",
    "sg:city":"Prince George",
    "sg:classifiers":[
        {
            "category":"Building & Trades",
            "subcategory":"Construction",
            "type":"Services"
        }
    ],
    "sg:phone":"+1 250 563 5490",
    "sg:postcode":"V2M 7C9",
    "sg:province":"BC",
    "sg:tags":[
        "masonry",
        "contractor"
    ],
    "wof:name":"Stella G Masonry Ltd",
    "wof:placetype":"venue"
},
  "geometry": {"coordinates":[-122.84634399399999,53.9378395081],"type":"Point"}
}