{
  "type": "Feature",
  "properties": {
    "addr:full":"235 East Railway Hartney MB R0M 0X0",
    "addr:housenumber":"235",
    "addr:postcode":"r0m 0x0",
    "addr:street":"East Railway",
    "iso:country":"CA",
    "sg:address":"235 East Railway",
    "sg:city":"Hartney",
    "sg:classifiers":[
        {
            "category":"Government",
            "subcategory":"Office",
            "type":"Public Place"
        }
    ],
    "sg:phone":"+1 204 858 2429",
    "sg:postcode":"R0M 0X0",
    "sg:province":"MB",
    "sg:tags":[
        "village"
    ],
    "wof:name":"Hartney Town Offices",
    "wof:placetype":"venue"
},
  "geometry": {"coordinates":[-100.528015137,49.4774780273],"type":"Point"}
}