{
  "type": "Feature",
  "properties": {
    "addr:full":"Surrey BC V3T 2W4",
    "addr:postcode":"v3t 2w4",
    "iso:country":"CA",
    "sg:city":"Surrey",
    "sg:classifiers":[
        {
            "category":"Shopping",
            "subcategory":"Beauty & Cosmetics",
            "type":"Retail Goods"
        }
    ],
    "sg:phone":"+1 604 584 5701",
    "sg:postcode":"V3T 2W4",
    "sg:province":"BC",
    "sg:tags":[
        "surgical",
        "appliance"
    ],
    "wof:name":"Datran Clinical Support Systs",
    "wof:placetype":"venue"
},
  "geometry": {"coordinates":[-122.845153809,49.1856613159],"type":"Point"}
}