{
  "type": "Feature",
  "properties": {
    "iso:country":"CA",
    "sg:address":"1675 Rue Notre-Dame",
    "sg:city":"L'Ancienne-Lorette",
    "sg:classifiers":[
        {
            "category":"Recreation",
            "type":"Entertainment"
        }
    ],
    "sg:phone":"+1 418 877 9494",
    "sg:postcode":"G2E 3B9",
    "sg:province":"QC",
    "sg:tags":[
        "parlor",
        "billiard"
    ],
    "wof:name":"Billard O-Coin",
    "wof:placetype":"venue"
},
  "geometry": {"coordinates":[-71.36145019529999,46.8033599854],"type":"Point"}
}