{
  "type": "Feature",
  "properties": {
    "addr:full":"189 First St Belle River ON N0R 1A0",
    "addr:housenumber":"189",
    "addr:postcode":"n0r 1a0",
    "addr:street":"First St",
    "iso:country":"CA",
    "sg:address":"189 First St",
    "sg:city":"Belle River",
    "sg:classifiers":[
        {
            "category":"Personal",
            "type":"Services"
        }
    ],
    "sg:phone":"+1 519 728 2758",
    "sg:postcode":"N0R 1A0",
    "sg:province":"ON",
    "sg:tags":[
        "program",
        "physical",
        "exercise",
        "fitness"
    ],
    "wof:name":"Beachwalk Family Fitness",
    "wof:placetype":"venue"
},
  "geometry": {"coordinates":[-82.71112100000001,42.293789],"type":"Point"}
}