{
  "type": "Feature",
  "properties": {
    "addr:full":"Earlton ON P0J 1E0",
    "addr:postcode":"p0j 1e0",
    "iso:country":"CA",
    "sg:city":"Earlton",
    "sg:classifiers":[
        {
            "category":"Organizations",
            "subcategory":"Professional Association",
            "type":"Services"
        }
    ],
    "sg:phone":"+1 705 563 2122",
    "sg:postcode":"P0J 1E0",
    "sg:province":"ON",
    "wof:name":"Club Lions D'Earlton",
    "wof:placetype":"venue"
},
  "geometry": {"coordinates":[-79.8243255615,47.7114143372],"type":"Point"}
}