{
  "type": "Feature",
  "properties": {
    "addr:full":"590 David Manchester Rd Carp ON K0A 1L0",
    "addr:housenumber":"590",
    "addr:postcode":"k0a 1l0",
    "addr:street":"David Manchester Rd",
    "iso:country":"CA",
    "sg:address":"590 David Manchester Rd",
    "sg:city":"Carp",
    "sg:classifiers":[
        {
            "category":"Local Transit",
            "type":"Transportation"
        }
    ],
    "sg:phone":"+1 613 831 1603",
    "sg:postcode":"K0A 1L0",
    "sg:province":"ON",
    "sg:tags":[
        "limousine"
    ],
    "wof:name":"Tip Limousine Svc",
    "wof:placetype":"venue"
},
  "geometry": {"coordinates":[-75.9970397949,45.276096344],"type":"Point"}
}