{
  "type": "Feature",
  "properties": {
    "addr:full":"198 132 Rte O Sainte-Luce QC G0K 1P0",
    "addr:housenumber":"132",
    "addr:postcode":"g0k 1p0",
    "addr:street":"Rte O",
    "iso:country":"CA",
    "sg:address":"198 132 Rte O",
    "sg:city":"Sainte-Luce",
    "sg:classifiers":[
        {
            "category":"Retail",
            "subcategory":"Auto Repair",
            "type":"Services"
        }
    ],
    "sg:phone":"+1 418 739 4235",
    "sg:postcode":"G0K 1P0",
    "sg:province":"QC",
    "sg:tags":[
        "repairing",
        "automobile"
    ],
    "wof:name":"Garage Mario DE Champlain",
    "wof:placetype":"venue"
},
  "geometry": {"coordinates":[-68.34484100340001,48.5276412964],"type":"Point"}
}