{
  "type": "Feature",
  "properties": {
    "addr:full":"120 Lappans Lane Kingston ON K7K 6Z4",
    "addr:housenumber":"120",
    "addr:postcode":"k7k 6z4",
    "addr:street":"Lappans Lane",
    "iso:country":"CA",
    "sg:address":"120 Lappans Lane",
    "sg:city":"Kingston",
    "sg:classifiers":[
        {
            "category":"Home & Garden",
            "subcategory":"Building Materials",
            "type":"Retail Goods"
        }
    ],
    "sg:phone":"+1 613 546 2683",
    "sg:postcode":"K7K 6Z4",
    "sg:province":"ON",
    "sg:tags":[
        "mixed",
        "concrete"
    ],
    "wof:name":"Lafarge Construction Materials",
    "wof:placetype":"venue"
},
  "geometry": {"coordinates":[-76.479332,44.231537],"type":"Point"}
}