{
  "type": "Feature",
  "properties": {
    "addr:full":"51 Rue Marie Victorin Port-Menier QC G0G 2Y0",
    "addr:housenumber":"51",
    "addr:postcode":"g0g 2y0",
    "addr:street":"Rue Marie Victorin",
    "iso:country":"CA",
    "sg:address":"51 Rue Marie Victorin",
    "sg:city":"Port-Menier",
    "sg:classifiers":[
        {
            "category":"Retail",
            "subcategory":"Auto Rental",
            "type":"Services"
        }
    ],
    "sg:phone":"+1 418 535 0157",
    "sg:postcode":"G0G 2Y0",
    "sg:province":"QC",
    "sg:tags":[
        "renting",
        "automobile"
    ],
    "wof:name":"Location Aml",
    "wof:placetype":"venue"
},
  "geometry": {"coordinates":[-64.368454,49.826405],"type":"Point"}
}