{
  "type": "Feature",
  "properties": {
    "addr:full":"458 Laurier Blvd Brockville ON K6V 6C5",
    "addr:housenumber":"458",
    "addr:postcode":"k6v 6c5",
    "addr:street":"Laurier Blvd",
    "iso:country":"CA",
    "sg:address":"458 Laurier Blvd",
    "sg:city":"Brockville",
    "sg:classifiers":[
        {
            "category":"Government",
            "subcategory":"Office",
            "type":"Public Place"
        }
    ],
    "sg:phone":"+1 613 345 4101",
    "sg:postcode":"K6V 6C5",
    "sg:province":"ON",
    "sg:tags":[
        "social",
        "organization",
        "welfare",
        "village"
    ],
    "wof:name":"Leeds & Grenville Social Svc",
    "wof:placetype":"venue"
},
  "geometry": {"coordinates":[-75.703041,44.615227],"type":"Point"}
}