{
  "type": "Feature",
  "properties": {
    "iso:country":"CA",
    "sg:address":"42 St Andrews Ave",
    "sg:city":"Grimsby",
    "sg:classifiers":[
        {
            "category":"Restaurant",
            "type":"Food & Drink"
        }
    ],
    "sg:phone":"+1 905 309 7261",
    "sg:postcode":"L3M 3S2",
    "sg:province":"ON",
    "wof:name":"Mr Sub",
    "wof:placetype":"venue"
},
  "geometry": {"coordinates":[-79.56824493409999,43.1960906982],"type":"Point"}
}