{
  "type": "Feature",
  "properties": {
    "addr:full":"6830 Rue Jarry E Saint-Leonard QC H1P 1W3",
    "addr:housenumber":"6830",
    "addr:postcode":"h1p 1w3",
    "addr:street":"Rue Jarry E",
    "iso:country":"CA",
    "sg:address":"6830 Rue Jarry E",
    "sg:city":"Saint-Leonard",
    "sg:classifiers":[
        {
            "category":"Banks & Credit Unions",
            "subcategory":"Bank",
            "type":"Services"
        }
    ],
    "sg:phone":"+1 514 324 5656",
    "sg:postcode":"H1P 1W3",
    "sg:province":"QC",
    "sg:tags":[
        "financing"
    ],
    "wof:name":"Groupe Financier Gps Inc",
    "wof:placetype":"venue"
},
  "geometry": {"coordinates":[-73.5786819458,45.5978240967],"type":"Point"}
}