{
  "type": "Feature",
  "properties": {
    "addr:full":"Saskatoon SK S7K 1Y3",
    "addr:postcode":"s7k 1y3",
    "iso:country":"CA",
    "sg:city":"Saskatoon",
    "sg:classifiers":[
        {
            "category":"Retail",
            "subcategory":"Repair Shop",
            "type":"Services"
        }
    ],
    "sg:phone":"+1 306 664 2251",
    "sg:postcode":"S7K 1Y3",
    "sg:province":"SK",
    "sg:tags":[
        "upholsterer"
    ],
    "wof:name":"Braithwaite's Upholstery Ltd",
    "wof:placetype":"venue"
},
  "geometry": {"coordinates":[-106.659988403,52.1401062012],"type":"Point"}
}