{
  "type": "Feature",
  "properties": {
    "addr:full":"Scarborough ON M1V 5G4",
    "addr:postcode":"m1v 5g4",
    "iso:country":"CA",
    "sg:city":"Scarborough",
    "sg:classifiers":[
        {
            "category":"Communications",
            "subcategory":"Film & Video Production",
            "type":"Services"
        }
    ],
    "sg:phone":"+1 416 321 2546",
    "sg:postcode":"M1V 5G4",
    "sg:province":"ON",
    "sg:tags":[
        "taping"
    ],
    "wof:name":"Pnr Productions Ltd",
    "wof:placetype":"venue"
},
  "geometry": {"coordinates":[-79.25564575200001,43.8293037415],"type":"Point"}
}