{
  "type": "Feature",
  "properties": {
    "addr:full":"Mississauga ON L4T 4H3",
    "addr:postcode":"l4t 4h3",
    "iso:country":"CA",
    "sg:city":"Mississauga",
    "sg:classifiers":[
        {
            "category":"Health Services",
            "subcategory":"Doctor",
            "type":"Services"
        }
    ],
    "sg:phone":"+1 905 673 7874",
    "sg:postcode":"L4T 4H3",
    "sg:province":"ON",
    "sg:tags":[
        "dentist"
    ],
    "wof:name":"Goreway Dental Ctr",
    "wof:placetype":"venue"
},
  "geometry": {"coordinates":[-79.63502502439999,43.7161941528],"type":"Point"}
}