{
  "type": "Feature",
  "properties": {
    "addr:full":"3557 Munster Rd Richmond ON K0A 2Z0",
    "addr:housenumber":"3557",
    "addr:postcode":"k0a 2z0",
    "addr:street":"Munster Rd",
    "iso:country":"CA",
    "sg:address":"3557 Munster Rd",
    "sg:city":"Richmond",
    "sg:classifiers":[
        {
            "category":"Wholesale",
            "subcategory":"Metals & Minerals",
            "type":"Manufacturing & Wholesale Goods"
        }
    ],
    "sg:phone":"+1 613 838 2355",
    "sg:postcode":"K0A 2Z0",
    "sg:province":"ON",
    "sg:tags":[
        "siding",
        "material",
        "aluminum"
    ],
    "wof:name":"John Olsen Ltd",
    "wof:placetype":"venue"
},
  "geometry": {"coordinates":[-75.8365402222,45.1958045959],"type":"Point"}
}