{
  "type": "Feature",
  "properties": {
    "addr:full":"320 7E Av Lasalle QC H8P 2M4",
    "addr:housenumber":"320",
    "addr:postcode":"h8p 2m4",
    "addr:street":"7E Av",
    "iso:country":"CA",
    "sg:address":"320 7E Av",
    "sg:city":"Lasalle",
    "sg:classifiers":[
        {
            "category":"Building & Trades",
            "subcategory":"Construction",
            "type":"Services"
        }
    ],
    "sg:phone":"+1 514 363 6593",
    "sg:postcode":"H8P 2M4",
    "sg:province":"QC",
    "sg:tags":[
        "roofing",
        "contractor"
    ],
    "wof:name":"Couvreur E Leclair & Fils Ltee",
    "wof:placetype":"venue"
},
  "geometry": {"coordinates":[-73.6628189087,45.4286575317],"type":"Point"}
}