{
  "type": "Feature",
  "properties": {
    "iso:country":"CA",
    "sg:address":"514 Queen St",
    "sg:city":"Saskatoon",
    "sg:classifiers":[
        {
            "category":"Shopping",
            "subcategory":"Pharmacy",
            "type":"Retail Goods"
        }
    ],
    "sg:phone":"+1 306 653 5111",
    "sg:postcode":"S7K 0M5",
    "sg:province":"SK",
    "wof:name":"Cheetham's Pharmacy",
    "wof:placetype":"venue"
},
  "geometry": {"coordinates":[-106.65493774399999,52.1367797852],"type":"Point"}
}