{
  "type": "Feature",
  "properties": {
    "addr:full":"67 Principale St LA Salle MB R0G 1B0",
    "addr:housenumber":"67",
    "addr:postcode":"r0g 1b0",
    "addr:street":"Principale St",
    "iso:country":"CA",
    "sg:address":"67 Principale St",
    "sg:city":"LA Salle",
    "sg:classifiers":[
        {
            "category":"Travel",
            "subcategory":"Hotels & Motels",
            "type":"Entertainment"
        }
    ],
    "sg:phone":"+1 204 736 4900",
    "sg:postcode":"R0G 1B0",
    "sg:province":"MB",
    "wof:name":"LA Salle River Inn",
    "wof:placetype":"venue"
},
  "geometry": {"coordinates":[-97.2642211914,49.6934738159],"type":"Point"}
}