{
  "type": "Feature",
  "properties": {
    "addr:full":"Cold Lake AB T9M 1P2",
    "addr:postcode":"t9m 1p2",
    "iso:country":"CA",
    "sg:city":"Cold Lake",
    "sg:classifiers":[
        {
            "category":"Shopping",
            "subcategory":"Pharmacy",
            "type":"Retail Goods"
        }
    ],
    "sg:phone":"+1 780 594 3579",
    "sg:postcode":"T9M 1P2",
    "sg:province":"AB",
    "wof:name":"Norlite Ida Pharmacy",
    "wof:placetype":"venue"
},
  "geometry": {"coordinates":[-110.207588,54.413586],"type":"Point"}
}