{
  "type": "Feature",
  "properties": {
    "addr:full":"75 Musgrave Rd Summerville NS B0N 2K0",
    "addr:housenumber":"75",
    "addr:postcode":"b0n 2k0",
    "addr:street":"Musgrave Rd",
    "iso:country":"CA",
    "sg:address":"75 Musgrave Rd",
    "sg:city":"Summerville",
    "sg:classifiers":[
        {
            "category":"Education",
            "subcategory":"School",
            "type":"Public Place"
        }
    ],
    "sg:phone":"+1 902 633 6300",
    "sg:postcode":"B0N 2K0",
    "sg:province":"NS",
    "wof:name":"Dr Arthur Hines Elementary",
    "wof:placetype":"venue"
},
  "geometry": {"coordinates":[-64.164413,45.098503],"type":"Point"}
}