{
  "type": "Feature",
  "properties": {
    "addr:full":"330 Boul Industriel Saint-Eustache QC J7R 5R4",
    "addr:housenumber":"330",
    "addr:postcode":"j7r 5r4",
    "addr:street":"Boul Industriel",
    "iso:country":"CA",
    "sg:address":"330 Boul Industriel",
    "sg:city":"Saint-Eustache",
    "sg:classifiers":[
        {
            "category":"Shopping",
            "subcategory":"Stationery & Office Supplies",
            "type":"Retail Goods"
        }
    ],
    "sg:phone":"+1 450 491 5050",
    "sg:postcode":"J7R 5R4",
    "sg:province":"QC",
    "wof:name":"Distributions Jcmd Inc",
    "wof:placetype":"venue"
},
  "geometry": {"coordinates":[-73.925453,45.564365],"type":"Point"}
}