{
  "type": "Feature",
  "properties": {
    "iso:country":"CA",
    "sg:address":"1775 Boul Saint-Louis",
    "sg:city":"Trois-Rivieres",
    "sg:classifiers":[
        {
            "category":"Organizations",
            "subcategory":"Religious Organization",
            "type":"Services"
        }
    ],
    "sg:phone":"+1 819 375 3636",
    "sg:postcode":"G8Z 2N7",
    "sg:province":"QC",
    "sg:tags":[
        "church"
    ],
    "wof:name":"Eglise St-Sacrement",
    "wof:placetype":"venue"
},
  "geometry": {"coordinates":[-72.556274,46.3535],"type":"Point"}
}