{
  "type": "Feature",
  "properties": {
    "iso:country":"CA",
    "sg:address":"5312 Av Du Marechal-Joffre",
    "sg:city":"Charny",
    "sg:classifiers":[
        {
            "category":"Building & Trades",
            "subcategory":"Construction",
            "type":"Services"
        }
    ],
    "sg:phone":"+1 418 832 7764",
    "sg:postcode":"G6X 3C7",
    "sg:province":"QC",
    "sg:tags":[
        "concrete",
        "contractor",
        "drainage"
    ],
    "wof:name":"Drainages DE LA Capitale",
    "wof:placetype":"venue"
},
  "geometry": {"coordinates":[-71.25871276860001,46.7154159546],"type":"Point"}
}