{
  "type": "Feature",
  "properties": {
    "addr:full":"16 Rue Montcalm Longueuil QC J4J 2K6",
    "addr:housenumber":"16",
    "addr:postcode":"j4j 2k6",
    "addr:street":"Rue Montcalm",
    "iso:country":"CA",
    "sg:address":"16 Rue Montcalm",
    "sg:city":"Longueuil",
    "sg:classifiers":[
        {
            "category":"Social Services",
            "type":"Services"
        }
    ],
    "sg:phone":"+1 450 677 5281",
    "sg:postcode":"J4J 2K6",
    "sg:province":"QC",
    "sg:tags":[
        "organization",
        "welfare"
    ],
    "wof:name":"Centre DE Benevolat/Rive Sud",
    "wof:placetype":"venue"
},
  "geometry": {"coordinates":[-73.479691,45.529221],"type":"Point"}
}