{
  "type": "Feature",
  "properties": {
    "addr:full":"1571 Lewisham Dr Mississauga ON L5J 3R2",
    "addr:housenumber":"1571",
    "addr:postcode":"l5j 3r2",
    "addr:street":"Lewisham Dr",
    "iso:country":"CA",
    "sg:address":"1571 Lewisham Dr",
    "sg:city":"Mississauga",
    "sg:classifiers":[
        {
            "category":"Building & Trades",
            "subcategory":"Construction",
            "type":"Services"
        }
    ],
    "sg:phone":"+1 905 277 3322",
    "sg:postcode":"L5J 3R2",
    "sg:province":"ON",
    "sg:tags":[
        "designer",
        "dealer",
        "pool",
        "swimming"
    ],
    "wof:name":"Doctor Vinyl CO",
    "wof:placetype":"venue"
},
  "geometry": {"coordinates":[-79.64443199999999,43.518734],"type":"Point"}
}