{
  "type": "Feature",
  "properties": {
    "addr:full":"9100 Barlow Trail NE Calgary AB T3J 3C3",
    "addr:housenumber":"9100",
    "addr:postcode":"t3j 3c3",
    "addr:street":"Barlow Trail Ne",
    "iso:country":"CA",
    "sg:address":"9100 Barlow Trail NE",
    "sg:city":"Calgary",
    "sg:classifiers":[
        {
            "category":"Parking",
            "type":"Transportation"
        }
    ],
    "sg:phone":"+1 403 250 6533",
    "sg:postcode":"T3J 3C3",
    "sg:province":"AB",
    "sg:tags":[
        "garage"
    ],
    "wof:name":"Park 'N Fly",
    "wof:placetype":"venue"
},
  "geometry": {"coordinates":[-114.00020600000001,51.135544],"type":"Point"}
}