{
  "type": "Feature",
  "properties": {
    "iso:country":"CA",
    "sg:address":"9100 Barlow Trail NE",
    "sg:city":"Calgary",
    "sg:classifiers":[
        {
            "category":"Parking",
            "type":"Transportation"
        }
    ],
    "sg:phone":"+1 403 250 6533",
    "sg:postcode":"T3J 3C3",
    "sg:province":"AB",
    "sg:tags":[
        "garage"
    ],
    "wof:name":"Park 'N Fly",
    "wof:placetype":"venue"
},
  "geometry": {"coordinates":[-114.000206,51.135544],"type":"Point"}
}