{
  "type": "Feature",
  "properties": {
    "addr:full":"814 Rue Fabien Rock Forest QC J1N 2J8",
    "addr:housenumber":"814",
    "addr:postcode":"j1n 2j8",
    "addr:street":"Rue Fabien",
    "iso:country":"CA",
    "sg:address":"814 Rue Fabien",
    "sg:city":"Rock Forest",
    "sg:classifiers":[
        {
            "category":"Manufacturing",
            "subcategory":"Electronics",
            "type":"Manufacturing & Wholesale Goods"
        }
    ],
    "sg:phone":"+1 819 864 4545",
    "sg:postcode":"J1N 2J8",
    "sg:province":"QC",
    "sg:tags":[
        "equipment",
        "supply",
        "telephone",
        "communication"
    ],
    "wof:name":"Communication Nelson Bilodeau",
    "wof:placetype":"venue"
},
  "geometry": {"coordinates":[-71.98801400000001,45.357651],"type":"Point"}
}