{
  "type": "Feature",
  "properties": {
    "addr:full":"1911 Dayton St Kelowna BC V1Y 8A7",
    "addr:housenumber":"1911",
    "addr:postcode":"v1y 8a7",
    "addr:street":"Dayton St",
    "iso:country":"CA",
    "sg:address":"1911 Dayton St",
    "sg:city":"Kelowna",
    "sg:classifiers":[
        {
            "category":"Shopping",
            "subcategory":"Clothing, Apparel, & Fashions",
            "type":"Retail Goods"
        }
    ],
    "sg:phone":"+1 250 868 2286",
    "sg:postcode":"V1Y 8A7",
    "sg:province":"BC",
    "sg:tags":[
        "sporting",
        "salvage",
        "surplus",
        "merchandise"
    ],
    "wof:name":"Army Surplus Warehouse",
    "wof:placetype":"venue"
},
  "geometry": {"coordinates":[-119.460915,49.878819],"type":"Point"}
}