{
  "type": "Feature",
  "properties": {
    "addr:full":"4509 Boul Arthur-Sauve Laval QC H7R 5P8",
    "addr:housenumber":"4509",
    "addr:postcode":"h7r 5p8",
    "addr:street":"Boul Arthur-Sauve",
    "iso:country":"CA",
    "sg:address":"4509 Boul Arthur-Sauve",
    "sg:city":"Laval",
    "sg:classifiers":[
        {
            "category":"Restaurant",
            "type":"Food & Drink"
        }
    ],
    "sg:phone":"+1 450 962 4027",
    "sg:postcode":"H7R 5P8",
    "sg:province":"QC",
    "wof:name":"Valentine",
    "wof:placetype":"venue"
},
  "geometry": {"coordinates":[-73.869598,45.552856],"type":"Point"}
}