{
  "type": "Feature",
  "properties": {
    "addr:full":"3580 Wolfedale Rd Mississauga ON L5C 2V6",
    "addr:housenumber":"3580",
    "addr:postcode":"l5c 2v6",
    "addr:street":"Wolfedale Rd",
    "iso:country":"CA",
    "sg:address":"3580 Wolfedale Rd",
    "sg:city":"Mississauga",
    "sg:classifiers":[
        {
            "category":"Wholesale",
            "subcategory":"Machinery & Supplies",
            "type":"Manufacturing & Wholesale Goods"
        }
    ],
    "sg:phone":"+1 905 949 2324",
    "sg:postcode":"L5C 2V6",
    "sg:province":"ON",
    "sg:tags":[
        "equipment",
        "pneumatic",
        "component"
    ],
    "wof:name":"Sempress Canada Inc",
    "wof:placetype":"venue"
},
  "geometry": {"coordinates":[-79.652039,43.573849],"type":"Point"}
}