{
  "type": "Feature",
  "properties": {
    "iso:country":"CA",
    "sg:address":"5736 75 St NW",
    "sg:city":"Edmonton",
    "sg:classifiers":[
        {
            "category":"Restaurant",
            "type":"Food & Drink"
        }
    ],
    "sg:phone":"+1 780 468 4992",
    "sg:postcode":"T6E 5X6",
    "sg:province":"AB",
    "wof:name":"More Subs",
    "wof:placetype":"venue"
},
  "geometry": {"coordinates":[-113.442893982,53.4938621521],"type":"Point"}
}