{
  "type": "Feature",
  "properties": {
    "addr:full":"62 Rue Augusta Sorel-Tracy QC J3P 1A5",
    "addr:housenumber":"62",
    "addr:postcode":"j3p 1a5",
    "addr:street":"Rue Augusta",
    "iso:country":"CA",
    "sg:address":"62 Rue Augusta",
    "sg:city":"Sorel-Tracy",
    "sg:classifiers":[
        {
            "category":"Shopping",
            "subcategory":"Clothing, Apparel, & Fashions",
            "type":"Retail Goods"
        }
    ],
    "sg:phone":"+1 450 743 3602",
    "sg:postcode":"J3P 1A5",
    "sg:province":"QC",
    "sg:tags":[
        "item",
        "boutique"
    ],
    "wof:name":"Lise Bibeau Inc",
    "wof:placetype":"venue"
},
  "geometry": {"coordinates":[-73.1146316528,46.0457191467],"type":"Point"}
}