{
  "type": "Feature",
  "properties": {
    "addr:full":"1643 Rue D'Youville Shawinigan QC G9N 8M8",
    "addr:housenumber":"1643",
    "addr:postcode":"g9n 8m8",
    "addr:street":"Rue D'Youville",
    "iso:country":"CA",
    "sg:address":"1643 Rue D'Youville",
    "sg:city":"Shawinigan",
    "sg:classifiers":[
        {
            "category":"Food & Beverages",
            "subcategory":"Groceries & Convenience Stores",
            "type":"Retail Goods"
        }
    ],
    "sg:phone":"+1 819 536 4412",
    "sg:postcode":"G9N 8M8",
    "sg:province":"QC",
    "sg:tags":[
        "grocer"
    ],
    "wof:name":"Maxi",
    "wof:placetype":"venue"
},
  "geometry": {"coordinates":[-72.612129,46.638981],"type":"Point"}
}