{
  "type": "Feature",
  "properties": {
    "addr:full":"Simcoe ON N3Y 4K6",
    "addr:postcode":"n3y 4k6",
    "iso:country":"CA",
    "sg:city":"Simcoe",
    "sg:classifiers":[
        {
            "category":"Building & Trades",
            "subcategory":"Construction",
            "type":"Services"
        }
    ],
    "sg:phone":"+1 519 428 1221",
    "sg:postcode":"N3Y 4K6",
    "sg:province":"ON",
    "sg:tags":[
        "roofing",
        "contractor"
    ],
    "wof:name":"Howe Brothers Roofing Contrs",
    "wof:placetype":"venue"
},
  "geometry": {"coordinates":[-80.3052902222,42.8359031677],"type":"Point"}
}