{
  "type": "Feature",
  "properties": {
    "addr:full":"3555 St Clair Ave E Scarborough ON M1K 1L6",
    "addr:housenumber":"3555",
    "addr:postcode":"m1k 1l6",
    "addr:street":"St Clair Ave E",
    "iso:country":"CA",
    "sg:address":"3555 St Clair Ave E",
    "sg:city":"Scarborough",
    "sg:classifiers":[
        {
            "category":"Restaurant",
            "type":"Food & Drink"
        }
    ],
    "sg:phone":"+1 416 261 9584",
    "sg:postcode":"M1K 1L6",
    "sg:province":"ON",
    "wof:name":"Wimpy's Diner",
    "wof:placetype":"venue"
},
  "geometry": {"coordinates":[-79.2616195679,43.7163124084],"type":"Point"}
}