{
  "type": "Feature",
  "properties": {
    "addr:full":"567 Adelaide St Woodstock ON N4S 4B7",
    "addr:housenumber":"567",
    "addr:postcode":"n4s 4b7",
    "addr:street":"Adelaide St",
    "iso:country":"CA",
    "sg:address":"567 Adelaide St",
    "sg:city":"Woodstock",
    "sg:classifiers":[
        {
            "category":"Insurance",
            "subcategory":"Insurance Agent",
            "type":"Services"
        }
    ],
    "sg:phone":"+1 519 539 4818",
    "sg:postcode":"N4S 4B7",
    "sg:province":"ON",
    "wof:name":"South Easthope Mutual Ins CO",
    "wof:placetype":"venue"
},
  "geometry": {"coordinates":[-80.75393699999999,43.131485],"type":"Point"}
}