{
  "type": "Feature",
  "properties": {
    "addr:full":"Saint-Tite QC G0X 3H0",
    "addr:postcode":"g0x 3h0",
    "iso:country":"CA",
    "sg:city":"Saint-Tite",
    "sg:classifiers":[
        {
            "category":"Government",
            "subcategory":"Office",
            "type":"Public Place"
        }
    ],
    "sg:phone":"+1 418 365 4365",
    "sg:postcode":"G0X 3H0",
    "sg:province":"QC",
    "sg:tags":[
        "village"
    ],
    "wof:name":"Quebec Surete",
    "wof:placetype":"venue"
},
  "geometry": {"coordinates":[-72.5734786987,46.7276535034],"type":"Point"}
}