{
  "type": "Feature",
  "properties": {
    "iso:country":"CA",
    "sg:address":"1219 Cathcart Blvd",
    "sg:city":"Sarnia",
    "sg:classifiers":[
        {
            "category":"Education",
            "subcategory":"School",
            "type":"Public Place"
        }
    ],
    "sg:phone":"+1 519 542 5651",
    "sg:postcode":"N7S 2H7",
    "sg:province":"ON",
    "wof:name":"Cathcart Boul Public School",
    "wof:placetype":"venue"
},
  "geometry": {"coordinates":[-82.36414337159999,43.0106086731],"type":"Point"}
}