{
  "type": "Feature",
  "properties": {
    "iso:country":"CA",
    "sg:city":"Scarborough",
    "sg:classifiers":[
        {
            "category":"Health Services",
            "subcategory":"Doctor",
            "type":"Services"
        }
    ],
    "sg:phone":"+1 416 491 0737",
    "sg:postcode":"M1T 3K2",
    "sg:province":"ON",
    "sg:tags":[
        "dentist"
    ],
    "wof:name":"Sone, Warren DDS",
    "wof:placetype":"venue"
},
  "geometry": {"coordinates":[-79.3098373413,43.778137207],"type":"Point"}
}