{
  "type": "Feature",
  "properties": {
    "addr:full":"PO Box 99 Rosalind AB T0B 3Y0",
    "addr:housenumber":"po box 99",
    "addr:postcode":"t0b 3y0",
    "addr:street":"Rosalind Ab",
    "iso:country":"CA",
    "sg:address":"PO Box 99",
    "sg:city":"Rosalind",
    "sg:classifiers":[
        {
            "category":"Mining & Drilling",
            "type":"Manufacturing & Wholesale Goods"
        }
    ],
    "sg:phone":"+1 780 375 3922",
    "sg:postcode":"T0B 3Y0",
    "sg:province":"AB",
    "sg:tags":[
        "company",
        "oil"
    ],
    "wof:name":"Canadian Natural Resources Ltd",
    "wof:placetype":"venue"
},
  "geometry": {"coordinates":[-112.441345,52.787998],"type":"Point"}
}