{
  "type": "Feature",
  "properties": {
    "iso:country":"CA",
    "sg:address":"2829 Mill Woods Rd NW",
    "sg:city":"Edmonton",
    "sg:classifiers":[
        {
            "category":"Personal",
            "subcategory":"Tanning Parlor",
            "type":"Services"
        }
    ],
    "sg:phone":"+1 780 462 1814",
    "sg:postcode":"T6K 4A9",
    "sg:province":"AB",
    "sg:tags":[
        "salon"
    ],
    "wof:name":"Fabutan Sun Tan Studios",
    "wof:placetype":"venue"
},
  "geometry": {"coordinates":[-113.447914123,53.459274292],"type":"Point"}
}