{
  "type": "Feature",
  "properties": {
    "addr:full":"Ayr ON N0B 1E0",
    "addr:postcode":"n0b 1e0",
    "iso:country":"CA",
    "sg:city":"Ayr",
    "sg:classifiers":[
        {
            "category":"Food & Beverages",
            "subcategory":"Fruits & Vegetables",
            "type":"Retail Goods"
        }
    ],
    "sg:phone":"+1 519 632 1114",
    "sg:postcode":"N0B 1E0",
    "sg:province":"ON",
    "sg:tags":[
        "produce"
    ],
    "wof:name":"Cream of the Crop Fruit Market",
    "wof:placetype":"venue"
},
  "geometry": {"coordinates":[-80.45143127439999,43.2867431641],"type":"Point"}
}