{
  "type": "Feature",
  "properties": {
    "addr:full":"1677 Newport Rd Westbank BC V4T 1X1",
    "addr:housenumber":"1677",
    "addr:postcode":"v4t 1x1",
    "addr:street":"Newport Rd",
    "iso:country":"CA",
    "sg:address":"1677 Newport Rd",
    "sg:city":"Westbank",
    "sg:classifiers":[
        {
            "category":"Professional",
            "subcategory":"Engineering",
            "type":"Services"
        }
    ],
    "sg:phone":"+1 250 707 1252",
    "sg:postcode":"V4T 1X1",
    "sg:province":"BC",
    "sg:tags":[
        "fire",
        "consultant",
        "protection",
        "engineer"
    ],
    "wof:name":"Fire Tech Systems",
    "wof:placetype":"venue"
},
  "geometry": {"coordinates":[-119.58542633099999,49.8272285461],"type":"Point"}
}