{
  "type": "Feature",
  "properties": {
    "addr:full":"3269 Parsons Rd NW Edmonton AB T6N 1B4",
    "addr:housenumber":"3269",
    "addr:postcode":"t6n 1b4",
    "addr:street":"Parsons Rd Nw",
    "iso:country":"CA",
    "sg:address":"3269 Parsons Rd NW",
    "sg:city":"Edmonton",
    "sg:classifiers":[
        {
            "category":"Building & Trades",
            "subcategory":"Construction",
            "type":"Services"
        }
    ],
    "sg:phone":"+1 780 432 1001",
    "sg:postcode":"T6N 1B4",
    "sg:province":"AB",
    "sg:tags":[
        "general",
        "contractor"
    ],
    "wof:name":"Pagnotta Industries Inc",
    "wof:placetype":"venue"
},
  "geometry": {"coordinates":[-113.48575592,53.465259552],"type":"Point"}
}