{
  "type": "Feature",
  "properties": {
    "iso:country":"CA",
    "sg:address":"251 Rue Principale",
    "sg:city":"Saint-Gervais",
    "sg:classifiers":[
        {
            "category":"Bars & Pubs",
            "type":"Food & Drink"
        }
    ],
    "sg:phone":"+1 418 887 6310",
    "sg:postcode":"G0R 3C0",
    "sg:province":"QC",
    "sg:tags":[
        "lounge",
        "cocktail"
    ],
    "wof:name":"Bar Au Sportif",
    "wof:placetype":"venue"
},
  "geometry": {"coordinates":[-70.8864517212,46.7132453918],"type":"Point"}
}