{
  "type": "Feature",
  "properties": {
    "addr:full":"1215 Ch DE LA Montagne Orford QC J1X 6X9",
    "addr:housenumber":"1215",
    "addr:postcode":"j1x 6x9",
    "addr:street":"Ch De La Montagne",
    "iso:country":"CA",
    "sg:address":"1215 Ch DE LA Montagne",
    "sg:city":"Orford",
    "sg:classifiers":[
        {
            "category":"Travel",
            "subcategory":"Hotels & Motels",
            "type":"Entertainment"
        }
    ],
    "sg:phone":"+1 819 868 4222",
    "sg:postcode":"J1X 6X9",
    "sg:province":"QC",
    "wof:name":"Motel DE LA Montagne",
    "wof:placetype":"venue"
},
  "geometry": {"coordinates":[-72.17643,45.312187],"type":"Point"}
}