{
  "type": "Feature",
  "properties": {
    "addr:full":"3065 Boul Wallberg Dolbeau-Mistassini QC G8L 3P4",
    "addr:housenumber":"3065",
    "addr:postcode":"g8l 3p4",
    "addr:street":"Boul Wallberg",
    "iso:country":"CA",
    "sg:address":"3065 Boul Wallberg",
    "sg:city":"Dolbeau-Mistassini",
    "sg:classifiers":[
        {
            "category":"Organizations",
            "subcategory":"Religious Organization",
            "type":"Services"
        }
    ],
    "sg:phone":"+1 418 276 7613",
    "sg:postcode":"G8L 3P4",
    "sg:province":"QC",
    "sg:tags":[
        "church"
    ],
    "wof:name":"Eglise Baptiste DE LA Grace",
    "wof:placetype":"venue"
},
  "geometry": {"coordinates":[-72.282188,48.888893],"type":"Point"}
}