{
  "type": "Feature",
  "properties": {
    "addr:full":"285112 Pleasant Valley Rd Norwich ON N0J 1P0",
    "addr:housenumber":"285112",
    "addr:postcode":"n0j 1p0",
    "addr:street":"Pleasant Valley Rd",
    "iso:country":"CA",
    "sg:address":"285112 Pleasant Valley Rd",
    "sg:city":"Norwich",
    "sg:classifiers":[
        {
            "category":"Home & Garden",
            "subcategory":"Garden Supply",
            "type":"Retail Goods"
        }
    ],
    "sg:phone":"+1 519 468 6508",
    "sg:postcode":"N0J 1P0",
    "sg:province":"ON",
    "sg:tags":[
        "nurseryman",
        "center"
    ],
    "wof:name":"Mc Millen's Iris Gardens",
    "wof:placetype":"venue"
},
  "geometry": {"coordinates":[-80.6673812866,42.9619483948],"type":"Point"}
}