{
  "type": "Feature",
  "properties": {
    "iso:country":"CA",
    "sg:city":"Mississauga",
    "sg:classifiers":[
        {
            "category":"Professional",
            "subcategory":"Engineering",
            "type":"Services"
        }
    ],
    "sg:phone":"+1 905 670 1770",
    "sg:postcode":"L5T 2N5",
    "sg:province":"ON",
    "sg:tags":[
        "engineer"
    ],
    "wof:name":"Teng & Assoc",
    "wof:placetype":"venue"
},
  "geometry": {"coordinates":[-79.654938,43.659462],"type":"Point"}
}