{
  "type": "Feature",
  "properties": {
    "addr:full":"9151 Rue Airlie Lasalle QC H8R 2A7",
    "addr:housenumber":"9151",
    "addr:postcode":"h8r 2a7",
    "addr:street":"Rue Airlie",
    "iso:country":"CA",
    "sg:address":"9151 Rue Airlie",
    "sg:city":"Lasalle",
    "sg:classifiers":[
        {
            "category":"Autos & Motor Vehicles",
            "subcategory":"Fuel & Gas Station",
            "type":"Retail Goods"
        }
    ],
    "sg:phone":"+1 514 365 3100",
    "sg:postcode":"H8R 2A7",
    "sg:province":"QC",
    "sg:tags":[
        "oil"
    ],
    "wof:name":"Ramy Awad Enr",
    "wof:placetype":"venue"
},
  "geometry": {"coordinates":[-73.6358795166,45.421913147],"type":"Point"}
}