{
  "type": "Feature",
  "properties": {
    "addr:full":"10415 109 Ave Fort St John BC V1J 2S2",
    "addr:housenumber":"10415",
    "addr:postcode":"v1j 2s2",
    "addr:street":"109 Ave",
    "iso:country":"CA",
    "sg:address":"10415 109 Ave",
    "sg:city":"Fort St John",
    "sg:classifiers":[
        {
            "category":"Mining & Drilling",
            "type":"Manufacturing & Wholesale Goods"
        }
    ],
    "sg:phone":"+1 250 785 4572",
    "sg:postcode":"V1J 2S2",
    "sg:province":"BC",
    "sg:tags":[
        "field",
        "oil"
    ],
    "wof:name":"S R Glenn & Son Conslnts Ltd",
    "wof:placetype":"venue"
},
  "geometry": {"coordinates":[-120.854919,56.254189],"type":"Point"}
}