{
  "type": "Feature",
  "properties": {
    "iso:country":"CA",
    "sg:address":"1 Jockvale Rd",
    "sg:city":"Nepean",
    "sg:classifiers":[
        {
            "category":"Wholesale",
            "subcategory":"Meat",
            "type":"Manufacturing & Wholesale Goods"
        }
    ],
    "sg:phone":"+1 613 825 6393",
    "sg:postcode":"K2J 4J9",
    "sg:province":"ON",
    "sg:tags":[
        "butchering"
    ],
    "wof:name":"Pete & Gus Meat Market",
    "wof:placetype":"venue"
},
  "geometry": {"coordinates":[-75.77764129640001,45.2750587463],"type":"Point"}
}