{
  "type": "Feature",
  "properties": {
    "addr:full":"650 Rue Caron Chicoutimi QC G7J 2Z4",
    "addr:housenumber":"650",
    "addr:postcode":"g7j 2z4",
    "addr:street":"Rue Caron",
    "iso:country":"CA",
    "sg:address":"650 Rue Caron",
    "sg:city":"Chicoutimi",
    "sg:classifiers":[
        {
            "category":"Real Estate",
            "subcategory":"Architect",
            "type":"Services"
        }
    ],
    "sg:phone":"+1 418 545 0773",
    "sg:postcode":"G7J 2Z4",
    "sg:province":"QC",
    "wof:name":"Cote, Christiane",
    "wof:placetype":"venue"
},
  "geometry": {"coordinates":[-71.073708,48.42033],"type":"Point"}
}