{
  "type": "Feature",
  "properties": {
    "iso:country":"CA",
    "sg:address":"145 Industrial Court B # 4",
    "sg:city":"Sault Ste Marie",
    "sg:classifiers":[
        {
            "category":"Manufacturing",
            "subcategory":"Signs",
            "type":"Manufacturing & Wholesale Goods"
        }
    ],
    "sg:phone":"+1 705 256 7310",
    "sg:postcode":"P6B 5Z9",
    "sg:province":"ON",
    "wof:name":"Classic Neon & Signs",
    "wof:placetype":"venue"
},
  "geometry": {"coordinates":[-84.326195,46.551086],"type":"Point"}
}