{
  "type": "Feature",
  "properties": {
    "addr:full":"195 Kensington Rd Charlottetown PE C1A 5K1",
    "addr:housenumber":"195",
    "addr:postcode":"c1a 5k1",
    "addr:street":"Kensington Rd",
    "iso:country":"CA",
    "sg:address":"195 Kensington Rd",
    "sg:city":"Charlottetown",
    "sg:classifiers":[
        {
            "category":"Social Services",
            "subcategory":"Child Care",
            "type":"Services"
        }
    ],
    "sg:phone":"+1 902 892 7525",
    "sg:postcode":"C1A 5K1",
    "sg:province":"PE",
    "wof:name":"Tiny Tot Daycare",
    "wof:placetype":"venue"
},
  "geometry": {"coordinates":[-63.112598,46.262745],"type":"Point"}
}