{
  "type": "Feature",
  "properties": {
    "addr:full":"Salmon Arm BC V1E 3B8",
    "addr:postcode":"v1e 3b8",
    "iso:country":"CA",
    "sg:city":"Salmon Arm",
    "sg:classifiers":[
        {
            "category":"Shopping",
            "subcategory":"Musical Instruments",
            "type":"Retail Goods"
        }
    ],
    "sg:phone":"+1 250 832 0176",
    "sg:postcode":"V1E 3B8",
    "sg:province":"BC",
    "wof:name":"Blue Water Music",
    "wof:placetype":"venue"
},
  "geometry": {"coordinates":[-119.28259300000001,50.700871],"type":"Point"}
}