{
  "type": "Feature",
  "properties": {
    "addr:full":"4616 Cumberland Rd Cumberland BC V0R 1S0",
    "addr:housenumber":"4616",
    "addr:postcode":"v0r 1s0",
    "addr:street":"Cumberland Rd",
    "iso:country":"CA",
    "sg:address":"4616 Cumberland Rd",
    "sg:city":"Cumberland",
    "sg:classifiers":[
        {
            "category":"Manufacturing",
            "subcategory":"Glass & Minerals",
            "type":"Manufacturing & Wholesale Goods"
        }
    ],
    "sg:phone":"+1 250 336 8515",
    "sg:postcode":"V0R 1S0",
    "sg:province":"BC",
    "sg:tags":[
        "concrete",
        "brick",
        "block"
    ],
    "wof:name":"Cumberland Ready Mix Ltd",
    "wof:placetype":"venue"
},
  "geometry": {"coordinates":[-125.017547607,49.630569458],"type":"Point"}
}