{
  "type": "Feature",
  "properties": {
    "addr:full":"124 Scarboro Ave Scarborough ON M1C 1M4",
    "addr:housenumber":"124",
    "addr:postcode":"m1c 1m4",
    "addr:street":"Scarboro Ave",
    "iso:country":"CA",
    "sg:address":"124 Scarboro Ave",
    "sg:city":"Scarborough",
    "sg:classifiers":[
        {
            "category":"Building & Trades",
            "subcategory":"Construction",
            "type":"Services"
        }
    ],
    "sg:phone":"+1 416 283 4164",
    "sg:postcode":"M1C 1M4",
    "sg:province":"ON",
    "sg:tags":[
        "general",
        "contractor"
    ],
    "wof:name":"Thunderhill Construction Ltd",
    "wof:placetype":"venue"
},
  "geometry": {"coordinates":[-79.172325,43.795757],"type":"Point"}
}