{
  "type": "Feature",
  "properties": {
    "addr:full":"Winnipeg MB R3B 0R3",
    "addr:postcode":"r3b 0r3",
    "iso:country":"CA",
    "sg:city":"Winnipeg",
    "sg:classifiers":[
        {
            "category":"Real Estate",
            "subcategory":"Architect",
            "type":"Services"
        }
    ],
    "sg:phone":"+1 204 956 0938",
    "sg:postcode":"R3B 0R3",
    "sg:province":"MB",
    "wof:name":"Prairie Architects Inc",
    "wof:placetype":"venue"
},
  "geometry": {"coordinates":[-97.13571899999999,49.89753],"type":"Point"}
}