{
  "type": "Feature",
  "properties": {
    "iso:country":"CA",
    "sg:city":"Montreal",
    "sg:classifiers":[
        {
            "category":"Professional",
            "type":"Services"
        }
    ],
    "sg:phone":"+1 514 939 5419",
    "sg:postcode":"H4C 3G7",
    "sg:province":"QC",
    "sg:tags":[
        "art",
        "restoring"
    ],
    "wof:name":"Dolleans Inc",
    "wof:placetype":"venue"
},
  "geometry": {"coordinates":[-73.593048,45.471809],"type":"Point"}
}