{
  "type": "Feature",
  "properties": {
    "iso:country":"CA",
    "sg:address":"5209 50th Ave",
    "sg:city":"Valleyview",
    "sg:classifiers":[
        {
            "category":"Home & Garden",
            "subcategory":"Hardware",
            "type":"Retail Goods"
        }
    ],
    "sg:phone":"+1 780 524 3181",
    "sg:postcode":"T0H 3N0",
    "sg:province":"AB",
    "wof:name":"Valleyview Home Hardware",
    "wof:placetype":"venue"
},
  "geometry": {"coordinates":[-117.27279663100001,55.0686187744],"type":"Point"}
}