{
  "type": "Feature",
  "properties": {
    "addr:full":"1085 Wilton Grove Rd London ON N6N 1C9",
    "addr:housenumber":"1085",
    "addr:postcode":"n6n 1c9",
    "addr:street":"Wilton Grove Rd",
    "iso:country":"CA",
    "sg:address":"1085 Wilton Grove Rd",
    "sg:city":"London",
    "sg:classifiers":[
        {
            "category":"Building & Trades",
            "subcategory":"Construction",
            "type":"Services"
        }
    ],
    "sg:phone":"+1 519 686 5200",
    "sg:postcode":"N6N 1C9",
    "sg:province":"ON",
    "sg:tags":[
        "general",
        "contractor"
    ],
    "wof:name":"Tonda Construction Ltd",
    "wof:placetype":"venue"
},
  "geometry": {"coordinates":[-81.1906051636,42.9281578064],"type":"Point"}
}