{
  "type": "Feature",
  "properties": {
    "addr:full":"Wagmatcook NS B0E 3N0",
    "addr:postcode":"b0e 3n0",
    "iso:country":"CA",
    "sg:city":"Wagmatcook",
    "sg:classifiers":[
        {
            "category":"Banks & Credit Unions",
            "subcategory":"Bank",
            "type":"Services"
        }
    ],
    "sg:phone":"+1 902 295 1579",
    "sg:postcode":"B0E 3N0",
    "sg:province":"NS",
    "sg:tags":[
        "hatchery",
        "fish"
    ],
    "wof:name":"Wagmatcook Agency Bank",
    "wof:placetype":"venue"
},
  "geometry": {"coordinates":[-60.912373,46.07386],"type":"Point"}
}