{
  "type": "Feature",
  "properties": {
    "addr:full":"2800 Sumas Mtn Rd Abbotsford BC V3G 2J2",
    "addr:housenumber":"2800",
    "addr:postcode":"v3g 2j2",
    "addr:street":"Sumas Mtn Rd",
    "iso:country":"CA",
    "sg:address":"2800 Sumas Mtn Rd",
    "sg:city":"Abbotsford",
    "sg:classifiers":[
        {
            "category":"Recreation",
            "type":"Entertainment"
        }
    ],
    "sg:phone":"+1 604 855 3745",
    "sg:postcode":"V3G 2J2",
    "sg:province":"BC",
    "sg:tags":[
        "hall",
        "auditorium"
    ],
    "wof:name":"Sumas First Nation",
    "wof:placetype":"venue"
},
  "geometry": {"coordinates":[-122.19784545900001,49.0577392578],"type":"Point"}
}