{
  "type": "Feature",
  "properties": {
    "addr:full":"109 3rd St Dalmeny SK S0K 1E0",
    "addr:housenumber":"109",
    "addr:postcode":"s0k 1e0",
    "addr:street":"3Rd St",
    "iso:country":"CA",
    "sg:address":"109 3rd St",
    "sg:city":"Dalmeny",
    "sg:classifiers":[
        {
            "category":"Government",
            "subcategory":"Police Station",
            "type":"Public Place"
        }
    ],
    "sg:phone":"+1 306 254 2114",
    "sg:postcode":"S0K 1E0",
    "sg:province":"SK",
    "sg:tags":[
        "department"
    ],
    "wof:name":"Dalmeny Municipal Police",
    "wof:placetype":"venue"
},
  "geometry": {"coordinates":[-106.77663421600001,52.3392868042],"type":"Point"}
}