{
  "type": "Feature",
  "properties": {
    "addr:full":"400421 Hwy 4 E Flesherton ON N0C 1E0",
    "addr:housenumber":"400421",
    "addr:postcode":"n0c 1e0",
    "addr:street":"Hwy 4 E",
    "iso:country":"CA",
    "sg:address":"400421 Hwy 4 E",
    "sg:city":"Flesherton",
    "sg:classifiers":[
        {
            "category":"Wholesale",
            "subcategory":"Construction Materials",
            "type":"Manufacturing & Wholesale Goods"
        }
    ],
    "sg:phone":"+1 519 924 2429",
    "sg:postcode":"N0C 1E0",
    "sg:province":"ON",
    "sg:tags":[
        "building"
    ],
    "wof:name":"Michael Croft Contracting",
    "wof:placetype":"venue"
},
  "geometry": {"coordinates":[-80.507492,44.286255],"type":"Point"}
}