{
  "type": "Feature",
  "properties": {
    "addr:full":"5339 Rue Ferrier Montreal QC H4P 1M1",
    "addr:housenumber":"5339",
    "addr:postcode":"h4p 1m1",
    "addr:street":"Rue Ferrier",
    "iso:country":"CA",
    "sg:address":"5339 Rue Ferrier",
    "sg:city":"Montreal",
    "sg:classifiers":[
        {
            "category":"Shopping",
            "subcategory":"Computers & Home Electronics",
            "type":"Retail Goods"
        }
    ],
    "sg:phone":"+1 514 737 4531",
    "sg:postcode":"H4P 1M1",
    "sg:province":"QC",
    "sg:tags":[
        "television",
        "radio"
    ],
    "wof:name":"Codell Leisure Products Ltd",
    "wof:placetype":"venue"
},
  "geometry": {"coordinates":[-73.659279,45.496525],"type":"Point"}
}