{
  "type": "Feature",
  "properties": {
    "iso:country":"CA",
    "sg:address":"461 Main St",
    "sg:city":"Esterhazy",
    "sg:classifiers":[
        {
            "category":"Shopping",
            "subcategory":"Computers & Home Electronics",
            "type":"Retail Goods"
        }
    ],
    "sg:phone":"+1 306 745 3476",
    "sg:postcode":"S0A 0X0",
    "sg:province":"SK",
    "sg:tags":[
        "equipment",
        "satellite",
        "dealer"
    ],
    "wof:name":"Reliable Electronics",
    "wof:placetype":"venue"
},
  "geometry": {"coordinates":[-102.078460693,50.654586792],"type":"Point"}
}