{
  "type": "Feature",
  "properties": {
    "addr:full":"105 Dorset St W Port Hope ON L1A 1G4",
    "addr:housenumber":"105",
    "addr:postcode":"l1a 1g4",
    "addr:street":"Dorset St W",
    "iso:country":"CA",
    "sg:address":"105 Dorset St W",
    "sg:city":"Port Hope",
    "sg:classifiers":[
        {
            "category":"Banks & Credit Unions",
            "subcategory":"Investment Brokerage",
            "type":"Services"
        }
    ],
    "sg:phone":"+1 905 885 4977",
    "sg:postcode":"L1A 1G4",
    "sg:province":"ON",
    "sg:tags":[
        "consultant",
        "planning",
        "financial"
    ],
    "wof:name":"Yorkminster Insurance Brokers",
    "wof:placetype":"venue"
},
  "geometry": {"coordinates":[-78.299133,43.947182],"type":"Point"}
}