{
  "type": "Feature",
  "properties": {
    "addr:full":"3456 Dunbar St Vancouver BC V6S 2C2",
    "addr:housenumber":"3456",
    "addr:postcode":"v6s 2c2",
    "addr:street":"Dunbar St",
    "iso:country":"CA",
    "sg:address":"3456 Dunbar St",
    "sg:city":"Vancouver",
    "sg:classifiers":[
        {
            "category":"Government",
            "subcategory":"Post Office",
            "type":"Public Place"
        }
    ],
    "sg:phone":"+1 604 731 3322",
    "sg:postcode":"V6S 2C2",
    "sg:province":"BC",
    "wof:name":"Dunbar Greetings",
    "wof:placetype":"venue"
},
  "geometry": {"coordinates":[-123.18498200000001,49.255981],"type":"Point"}
}