{
  "type": "Feature",
  "properties": {
    "addr:full":"215 Henderson Hwy Winnipeg MB R2L 1M1",
    "addr:housenumber":"215",
    "addr:postcode":"r2l 1m1",
    "addr:street":"Henderson Hwy",
    "iso:country":"CA",
    "sg:address":"215 Henderson Hwy",
    "sg:city":"Winnipeg",
    "sg:classifiers":[
        {
            "category":"Banks & Credit Unions",
            "subcategory":"Bank",
            "type":"Services"
        }
    ],
    "sg:phone":"+1 204 982 3714",
    "sg:postcode":"R2L 1M1",
    "sg:province":"MB",
    "sg:tags":[
        "cashing",
        "check"
    ],
    "wof:name":"Money Mart",
    "wof:placetype":"venue"
},
  "geometry": {"coordinates":[-97.11507400000001,49.9137],"type":"Point"}
}