{
  "type": "Feature",
  "properties": {
    "iso:country":"CA",
    "sg:city":"Granby",
    "sg:classifiers":[
        {
            "category":"Retail",
            "subcategory":"Auto Repair",
            "type":"Services"
        }
    ],
    "sg:phone":"+1 450 378 3977",
    "sg:postcode":"J2G 5G3",
    "sg:province":"QC",
    "sg:tags":[
        "repairing",
        "automobile"
    ],
    "wof:name":"Garage J Normandin Inc",
    "wof:placetype":"venue"
},
  "geometry": {"coordinates":[-72.7295074463,45.402381897],"type":"Point"}
}