{
  "type": "Feature",
  "properties": {
    "addr:full":"5346 Route 117 Baie-Sainte-Anne NB E9A 1C9",
    "addr:housenumber":"5346",
    "addr:postcode":"e9a 1c9",
    "addr:street":"Route 117",
    "iso:country":"CA",
    "sg:address":"5346 Route 117",
    "sg:city":"Baie-Sainte-Anne",
    "sg:classifiers":[
        {
            "category":"Restaurant",
            "type":"Food & Drink"
        }
    ],
    "sg:phone":"+1 506 228 4850",
    "sg:postcode":"E9A 1C9",
    "sg:province":"NB",
    "wof:name":"Villageois",
    "wof:placetype":"venue"
},
  "geometry": {"coordinates":[-64.95611599999999,47.051205],"type":"Point"}
}