{
  "type": "Feature",
  "properties": {
    "addr:full":"43 Bedford St Westport ON K0G 1X0",
    "addr:housenumber":"43",
    "addr:postcode":"k0g 1x0",
    "addr:street":"Bedford St",
    "iso:country":"CA",
    "sg:address":"43 Bedford St",
    "sg:city":"Westport",
    "sg:classifiers":[
        {
            "category":"Shopping",
            "type":"Retail Goods"
        }
    ],
    "sg:phone":"+1 613 273 2848",
    "sg:postcode":"K0G 1X0",
    "sg:province":"ON",
    "sg:tags":[
        "monument"
    ],
    "wof:name":"Thake Monuments",
    "wof:placetype":"venue"
},
  "geometry": {"coordinates":[-76.40031433110001,44.6796607971],"type":"Point"}
}