{
  "type": "Feature",
  "properties": {
    "iso:country":"CA",
    "sg:address":"547 Main St E",
    "sg:city":"Milton",
    "sg:classifiers":[
        {
            "category":"Shopping",
            "subcategory":"Crafts & Fabrics",
            "type":"Retail Goods"
        }
    ],
    "sg:phone":"+1 905 878 0931",
    "sg:postcode":"L9T 3J2",
    "sg:province":"ON",
    "sg:tags":[
        "shop"
    ],
    "wof:name":"Fabricland Distributors",
    "wof:placetype":"venue"
},
  "geometry": {"coordinates":[-79.8747558594,43.5211524963],"type":"Point"}
}