{
  "type": "Feature",
  "properties": {
    "iso:country":"CA",
    "sg:address":"283 Rue Notre-Dame O",
    "sg:city":"Montreal",
    "sg:classifiers":[
        {
            "category":"Personal",
            "subcategory":"Shoe Repair & Shine",
            "type":"Services"
        }
    ],
    "sg:phone":"+1 514 282 3349",
    "sg:postcode":"H2Y 1T8",
    "sg:province":"QC",
    "sg:tags":[
        "repairing",
        "boot"
    ],
    "wof:name":"Cordonnerie Nettoyeur Du Vieux",
    "wof:placetype":"venue"
},
  "geometry": {"coordinates":[-73.55364227290001,45.5090103149],"type":"Point"}
}