{
  "type": "Feature",
  "properties": {
    "addr:full":"156 Rue Don-Bosco Chicoutimi QC G7H 2Z7",
    "addr:housenumber":"156",
    "addr:postcode":"g7h 2z7",
    "addr:street":"Rue Don-Bosco",
    "iso:country":"CA",
    "sg:address":"156 Rue Don-Bosco",
    "sg:city":"Chicoutimi",
    "sg:classifiers":[
        {
            "category":"Organizations",
            "subcategory":"Religious Organization",
            "type":"Services"
        }
    ],
    "sg:phone":"+1 418 545 6990",
    "sg:postcode":"G7H 2Z7",
    "sg:province":"QC",
    "wof:name":"Centre Notre Dame-LA Salette",
    "wof:placetype":"venue"
},
  "geometry": {"coordinates":[-71.06586456300001,48.4092712402],"type":"Point"}
}