{
  "type": "Feature",
  "properties": {
    "addr:full":"Dieppe NB E1A 5R4",
    "addr:postcode":"e1a 5r4",
    "iso:country":"CA",
    "sg:city":"Dieppe",
    "sg:classifiers":[
        {
            "category":"Restaurant",
            "type":"Food & Drink"
        }
    ],
    "sg:phone":"+1 506 858 0150",
    "sg:postcode":"E1A 5R4",
    "sg:province":"NB",
    "wof:name":"Burger King",
    "wof:placetype":"venue"
},
  "geometry": {"coordinates":[-64.76123046879999,46.0990638733],"type":"Point"}
}