{
  "type": "Feature",
  "properties": {
    "addr:full":"3220 4 St NW Calgary AB T2M 3A5",
    "addr:housenumber":"3220 4",
    "addr:postcode":"t2m 3a5",
    "addr:street":"St Nw",
    "iso:country":"CA",
    "sg:address":"3220 4 St NW",
    "sg:city":"Calgary",
    "sg:classifiers":[
        {
            "category":"Retail",
            "subcategory":"Funeral Services",
            "type":"Services"
        }
    ],
    "sg:phone":"+1 403 297 0888",
    "sg:postcode":"T2M 3A5",
    "sg:province":"AB",
    "sg:tags":[
        "director"
    ],
    "wof:name":"Foster's Funeral Homes",
    "wof:placetype":"venue"
},
  "geometry": {"coordinates":[-114.071335,51.080803],"type":"Point"}
}