{
  "type": "Feature",
  "properties": {
    "addr:full":"Montreal QC H1Y 1H7",
    "addr:postcode":"h1y 1h7",
    "iso:country":"CA",
    "sg:city":"Montreal",
    "sg:classifiers":[
        {
            "category":"Social Services",
            "subcategory":"Job Training",
            "type":"Services"
        }
    ],
    "sg:phone":"+1 514 374 3999",
    "sg:postcode":"H1Y 1H7",
    "sg:province":"QC",
    "sg:tags":[
        "career",
        "counseling",
        "organization",
        "vocational",
        "welfare"
    ],
    "wof:name":"Nouveau Depart",
    "wof:placetype":"venue"
},
  "geometry": {"coordinates":[-73.58620500000001,45.554886],"type":"Point"}
}