{
  "type": "Feature",
  "properties": {
    "addr:full":"London ON N6K 1E1",
    "addr:postcode":"n6k 1e1",
    "iso:country":"CA",
    "sg:city":"London",
    "sg:classifiers":[
        {
            "category":"Health Services",
            "subcategory":"Doctor",
            "type":"Services"
        }
    ],
    "sg:phone":"+1 519 474 7777",
    "sg:postcode":"N6K 1E1",
    "sg:province":"ON",
    "sg:tags":[
        "dentist"
    ],
    "wof:name":"Botsford, Mark DDS",
    "wof:placetype":"venue"
},
  "geometry": {"coordinates":[-81.3338928223,42.9599189758],"type":"Point"}
}