{
  "type": "Feature",
  "properties": {
    "addr:full":"110 Rue Sainte-Therese Montreal QC H2Y 1E6",
    "addr:housenumber":"110",
    "addr:postcode":"h2y 1e6",
    "addr:street":"Rue Sainte-Therese",
    "iso:country":"CA",
    "sg:address":"110 Rue Sainte-Therese",
    "sg:city":"Montreal",
    "sg:classifiers":[
        {
            "category":"Organizations",
            "subcategory":"Professional Association",
            "type":"Services"
        }
    ],
    "sg:phone":"+1 514 954 0220",
    "sg:postcode":"H2Y 1E6",
    "sg:province":"QC",
    "wof:name":"Ciaft",
    "wof:placetype":"venue"
},
  "geometry": {"coordinates":[-73.5536651611,45.506942749],"type":"Point"}
}