{
  "type": "Feature",
  "properties": {
    "addr:full":"Westmount QC H3Z 1T3",
    "addr:postcode":"h3z 1t3",
    "iso:country":"CA",
    "sg:city":"Westmount",
    "sg:classifiers":[
        {
            "category":"Real Estate",
            "subcategory":"Real Estate Agent",
            "type":"Services"
        }
    ],
    "sg:phone":"+1 514 487 3480",
    "sg:postcode":"H3Z 1T3",
    "sg:province":"QC",
    "wof:name":"Immeubles Montec",
    "wof:placetype":"venue"
},
  "geometry": {"coordinates":[-73.60199737550001,45.4758796692],"type":"Point"}
}