{
  "type": "Feature",
  "properties": {
    "addr:full":"431 Boler Rd London ON N6K 2K8",
    "addr:housenumber":"431",
    "addr:postcode":"n6k 2k8",
    "addr:street":"Boler Rd",
    "iso:country":"CA",
    "sg:address":"431 Boler Rd",
    "sg:city":"London",
    "sg:classifiers":[
        {
            "category":"Health Services",
            "subcategory":"Doctor",
            "type":"Services"
        }
    ],
    "sg:phone":"+1 519 471 5110",
    "sg:postcode":"N6K 2K8",
    "sg:province":"ON",
    "sg:tags":[
        "dentist"
    ],
    "wof:name":"Byronwood Centre Dental Office",
    "wof:placetype":"venue"
},
  "geometry": {"coordinates":[-81.33122299999999,42.952629],"type":"Point"}
}