{
  "type": "Feature",
  "properties": {
    "iso:country":"CA",
    "sg:address":"431 Boler Rd",
    "sg:city":"London",
    "sg:classifiers":[
        {
            "category":"Health Services",
            "subcategory":"Doctor",
            "type":"Services"
        }
    ],
    "sg:phone":"+1 519 471 5110",
    "sg:postcode":"N6K 2K8",
    "sg:province":"ON",
    "sg:tags":[
        "dentist"
    ],
    "wof:name":"Byronwood Centre Dental Office",
    "wof:placetype":"venue"
},
  "geometry": {"coordinates":[-81.331223,42.952629],"type":"Point"}
}