{
  "type": "Feature",
  "properties": {
    "addr:full":"Hamilton ON L8W 3R4",
    "addr:postcode":"l8w 3r4",
    "iso:country":"CA",
    "sg:city":"Hamilton",
    "sg:classifiers":[
        {
            "category":"Manufacturing",
            "subcategory":"Signs",
            "type":"Manufacturing & Wholesale Goods"
        }
    ],
    "sg:phone":"+1 905 574 6663",
    "sg:postcode":"L8W 3R4",
    "sg:province":"ON",
    "wof:name":"Signs on Spot Ltd",
    "wof:placetype":"venue"
},
  "geometry": {"coordinates":[-79.82209,43.193062],"type":"Point"}
}