{
  "type": "Feature",
  "properties": {
    "addr:full":"368 Main St S Russell MB R0J 1W0",
    "addr:housenumber":"368",
    "addr:postcode":"r0j 1w0",
    "addr:street":"Main St S",
    "iso:country":"CA",
    "sg:address":"368 Main St S",
    "sg:city":"Russell",
    "sg:classifiers":[
        {
            "category":"Retail",
            "subcategory":"Auto Repair",
            "type":"Services"
        }
    ],
    "sg:phone":"+1 204 773 2331",
    "sg:postcode":"R0J 1W0",
    "sg:province":"MB",
    "sg:tags":[
        "truck"
    ],
    "wof:name":"Russell Truck Ctr",
    "wof:placetype":"venue"
},
  "geometry": {"coordinates":[-101.28787199999999,50.77787],"type":"Point"}
}