{
  "type": "Feature",
  "properties": {
    "addr:full":"1286 Kingston Rd Pickering ON L1V 1B7",
    "addr:housenumber":"1286",
    "addr:postcode":"l1v 1b7",
    "addr:street":"Kingston Rd",
    "iso:country":"CA",
    "sg:address":"1286 Kingston Rd",
    "sg:city":"Pickering",
    "sg:classifiers":[
        {
            "category":"Restaurant",
            "type":"Food & Drink"
        }
    ],
    "sg:phone":"+1 905 831 2383",
    "sg:postcode":"L1V 1B7",
    "sg:province":"ON",
    "wof:name":"Mary Brown's Fried Chicken",
    "wof:placetype":"venue"
},
  "geometry": {"coordinates":[-79.0909576416,43.8355522156],"type":"Point"}
}