{
  "type": "Feature",
  "properties": {
    "addr:full":"100 Gateway Park Dr Kitchener ON N2P 2J4",
    "addr:housenumber":"100",
    "addr:postcode":"n2p 2j4",
    "addr:street":"Gateway Park Dr",
    "iso:country":"CA",
    "sg:address":"100 Gateway Park Dr",
    "sg:city":"Kitchener",
    "sg:classifiers":[
        {
            "category":"Building & Trades",
            "subcategory":"Construction",
            "type":"Services"
        }
    ],
    "sg:phone":"+1 519 650 3900",
    "sg:postcode":"N2P 2J4",
    "sg:province":"ON",
    "sg:tags":[
        "home",
        "cabinet",
        "improvement",
        "kitchen",
        "equipment"
    ],
    "wof:name":"Home Depot",
    "wof:placetype":"venue"
},
  "geometry": {"coordinates":[-80.389664,43.407707],"type":"Point"}
}