{
  "type": "Feature",
  "properties": {
    "addr:full":"1042 Rue Notre-Dame N Sainte-Marie QC G6E 2L2",
    "addr:housenumber":"1042",
    "addr:postcode":"g6e 2l2",
    "addr:street":"Rue Notre-Dame N",
    "iso:country":"CA",
    "sg:address":"1042 Rue Notre-Dame N",
    "sg:city":"Sainte-Marie",
    "sg:classifiers":[
        {
            "category":"Professional",
            "subcategory":"Advertising",
            "type":"Services"
        }
    ],
    "sg:phone":"+1 418 387 6693",
    "sg:postcode":"G6E 2L2",
    "sg:province":"QC",
    "sg:tags":[
        "distribution"
    ],
    "wof:name":"Distribution R L'Heureux Ltee",
    "wof:placetype":"venue"
},
  "geometry": {"coordinates":[-71.038948,46.447182],"type":"Point"}
}