{
  "type": "Feature",
  "properties": {
    "addr:full":"5318 50th St Viking AB T0B 4N0",
    "addr:housenumber":"5318",
    "addr:postcode":"t0b 4n0",
    "addr:street":"50Th St",
    "iso:country":"CA",
    "sg:address":"5318 50th St",
    "sg:city":"Viking",
    "sg:classifiers":[
        {
            "category":"Food & Beverages",
            "subcategory":"Liquor & Beverages",
            "type":"Retail Goods"
        }
    ],
    "sg:phone":"+1 780 336 3321",
    "sg:postcode":"T0B 4N0",
    "sg:province":"AB",
    "sg:tags":[
        "store"
    ],
    "wof:name":"Cold Beer & Liquor Store",
    "wof:placetype":"venue"
},
  "geometry": {"coordinates":[-111.776611,53.096188],"type":"Point"}
}