{
  "type": "Feature",
  "properties": {
    "addr:full":"Westlock AB T7P 2L2",
    "addr:postcode":"t7p 2l2",
    "iso:country":"CA",
    "sg:city":"Westlock",
    "sg:classifiers":[
        {
            "category":"Food & Beverages",
            "subcategory":"Specialty",
            "type":"Retail Goods"
        }
    ],
    "sg:phone":"+1 780 349 6203",
    "sg:postcode":"T7P 2L2",
    "sg:province":"AB",
    "sg:tags":[
        "water",
        "bulk",
        "company"
    ],
    "wof:name":"Water Pure & Simple",
    "wof:placetype":"venue"
},
  "geometry": {"coordinates":[-113.874801636,54.1522674561],"type":"Point"}
}