{
  "type": "Feature",
  "properties": {
    "addr:full":"1191 Crestlawn Dr Mississauga ON L4W 1A7",
    "addr:housenumber":"1191",
    "addr:postcode":"l4w 1a7",
    "addr:street":"Crestlawn Dr",
    "iso:country":"CA",
    "sg:address":"1191 Crestlawn Dr",
    "sg:city":"Mississauga",
    "sg:classifiers":[
        {
            "category":"Professional",
            "subcategory":"Art Services",
            "type":"Services"
        }
    ],
    "sg:phone":"+1 905 624 6915",
    "sg:postcode":"L4W 1A7",
    "sg:province":"ON",
    "sg:tags":[
        "graphic",
        "designer"
    ],
    "wof:name":"Studio Touch",
    "wof:placetype":"venue"
},
  "geometry": {"coordinates":[-79.622787,43.630486],"type":"Point"}
}