{
  "type": "Feature",
  "properties": {
    "iso:country":"CA",
    "sg:city":"Victoria",
    "sg:classifiers":[
        {
            "category":"Shopping",
            "subcategory":"Gifts & Souvenirs",
            "type":"Retail Goods"
        }
    ],
    "sg:phone":"+1 250 386 7224",
    "sg:postcode":"V8Z 6E3",
    "sg:province":"BC",
    "sg:tags":[
        "cards",
        "shop",
        "greeting"
    ],
    "wof:name":"Hallmark Card & Gifts",
    "wof:placetype":"venue"
},
  "geometry": {"coordinates":[-123.37140655499999,48.4463806152],"type":"Point"}
}