{
  "type": "Feature",
  "properties": {
    "addr:full":"Vancouver BC V6C 1L6",
    "addr:postcode":"v6c 1l6",
    "iso:country":"CA",
    "sg:city":"Vancouver",
    "sg:classifiers":[
        {
            "category":"Mining & Drilling",
            "type":"Manufacturing & Wholesale Goods"
        }
    ],
    "sg:phone":"+1 604 689 1957",
    "sg:postcode":"V6C 1L6",
    "sg:province":"BC",
    "sg:tags":[
        "contractor"
    ],
    "wof:name":"Candente Resource Corp",
    "wof:placetype":"venue"
},
  "geometry": {"coordinates":[-123.11670684800001,49.2860984802],"type":"Point"}
}