{
  "type": "Feature",
  "properties": {
    "addr:full":"Kitchener ON N2G 2M4",
    "addr:postcode":"n2g 2m4",
    "iso:country":"CA",
    "sg:city":"Kitchener",
    "sg:classifiers":[
        {
            "category":"Social Services",
            "type":"Services"
        }
    ],
    "sg:phone":"+1 519 744 4666",
    "sg:postcode":"N2G 2M4",
    "sg:province":"ON",
    "sg:tags":[
        "organization",
        "addiction",
        "welfare",
        "center",
        "treatment"
    ],
    "wof:name":"Salvation Army",
    "wof:placetype":"venue"
},
  "geometry": {"coordinates":[-80.4788284302,43.4449272156],"type":"Point"}
}