{
  "type": "Feature",
  "properties": {
    "addr:full":"Calgary AB T2G 3T8",
    "addr:postcode":"t2g 3t8",
    "iso:country":"CA",
    "sg:city":"Calgary",
    "sg:classifiers":[
        {
            "category":"Home & Garden",
            "subcategory":"Hardware",
            "type":"Retail Goods"
        }
    ],
    "sg:phone":"+1 403 263 4979",
    "sg:postcode":"T2G 3T8",
    "sg:province":"AB",
    "sg:tags":[
        "saw"
    ],
    "wof:name":"E B Rishworth Inventories Ltd",
    "wof:placetype":"venue"
},
  "geometry": {"coordinates":[-114.02050781200001,51.0182609558],"type":"Point"}
}