{
  "type": "Feature",
  "properties": {
    "addr:full":"2464 Av Saint-Marc Shawinigan QC G9N 2J7",
    "addr:housenumber":"2464",
    "addr:postcode":"g9n 2j7",
    "addr:street":"Av Saint-Marc",
    "iso:country":"CA",
    "sg:address":"2464 Av Saint-Marc",
    "sg:city":"Shawinigan",
    "sg:classifiers":[
        {
            "category":"Professional",
            "subcategory":"Management & Consulting",
            "type":"Services"
        }
    ],
    "sg:phone":"+1 819 539 7313",
    "sg:postcode":"G9N 2J7",
    "sg:province":"QC",
    "sg:tags":[
        "consultant",
        "relation",
        "labor"
    ],
    "wof:name":"Consultants En Relations Du",
    "wof:placetype":"venue"
},
  "geometry": {"coordinates":[-72.7385101318,46.5559768677],"type":"Point"}
}