{
  "type": "Feature",
  "properties": {
    "iso:country":"CA",
    "sg:address":"715 the Kingsway",
    "sg:city":"Peterborough",
    "sg:classifiers":[
        {
            "category":"Autos & Motor Vehicles",
            "subcategory":"Auto Supplies",
            "type":"Retail Goods"
        }
    ],
    "sg:phone":"+1 705 743 9855",
    "sg:postcode":"K9J 6W7",
    "sg:province":"ON",
    "sg:tags":[
        "tire"
    ],
    "wof:name":"Fisher Tire Ltd",
    "wof:placetype":"venue"
},
  "geometry": {"coordinates":[-78.338959,44.278568],"type":"Point"}
}