{
  "type": "Feature",
  "properties": {
    "addr:full":"Bouctouche NB E4S 3K4",
    "addr:postcode":"e4s 3k4",
    "iso:country":"CA",
    "sg:city":"Bouctouche",
    "sg:classifiers":[
        {
            "category":"Food & Beverages",
            "subcategory":"Liquor & Beverages",
            "type":"Retail Goods"
        }
    ],
    "sg:phone":"+1 506 743 2500",
    "sg:postcode":"E4S 3K4",
    "sg:province":"NB",
    "sg:tags":[
        "store"
    ],
    "wof:name":"New Brunswick Liquor Corp",
    "wof:placetype":"venue"
},
  "geometry": {"coordinates":[-64.7332992554,46.4647407532],"type":"Point"}
}