{
  "type": "Feature",
  "properties": {
    "iso:country":"CA",
    "sg:address":"195 James St",
    "sg:city":"New Glasgow",
    "sg:classifiers":[
        {
            "category":"Organizations",
            "subcategory":"Religious Organization",
            "type":"Services"
        }
    ],
    "sg:phone":"+1 902 752 6180",
    "sg:postcode":"B2H 2Y9",
    "sg:province":"NS",
    "sg:tags":[
        "church"
    ],
    "wof:name":"First United Baptist Church",
    "wof:placetype":"venue"
},
  "geometry": {"coordinates":[-62.6438980103,45.5860137939],"type":"Point"}
}