{
  "type": "Feature",
  "properties": {
    "addr:full":"155 7th Ave W Vancouver BC V5Y 1L8",
    "addr:housenumber":"155",
    "addr:postcode":"v5y 1l8",
    "addr:street":"7Th Ave W",
    "iso:country":"CA",
    "sg:address":"155 7th Ave W",
    "sg:city":"Vancouver",
    "sg:classifiers":[
        {
            "category":"Professional",
            "subcategory":"Business Services",
            "type":"Services"
        }
    ],
    "sg:phone":"+1 604 879 9008",
    "sg:postcode":"V5Y 1L8",
    "sg:province":"BC",
    "sg:tags":[
        "embroidery"
    ],
    "wof:name":"Capital Embroidery",
    "wof:placetype":"venue"
},
  "geometry": {"coordinates":[-123.10820770300001,49.264881134],"type":"Point"}
}