{
  "type": "Feature",
  "properties": {
    "addr:full":"1206 7 St Nisku AB T9E 7P3",
    "addr:housenumber":"1206 7",
    "addr:postcode":"t9e 7p3",
    "addr:street":"St",
    "iso:country":"CA",
    "sg:address":"1206 7 St",
    "sg:city":"Nisku",
    "sg:classifiers":[
        {
            "category":"Manufacturing",
            "subcategory":"Tools & Machinery",
            "type":"Manufacturing & Wholesale Goods"
        }
    ],
    "sg:phone":"+1 780 955 3700",
    "sg:postcode":"T9E 7P3",
    "sg:province":"AB",
    "sg:tags":[
        "field",
        "oil",
        "welding"
    ],
    "wof:name":"Lougheed Welding & Fabrication",
    "wof:placetype":"venue"
},
  "geometry": {"coordinates":[-113.521835,53.311687],"type":"Point"}
}