{
  "type": "Feature",
  "properties": {
    "addr:full":"178 Rue DE LA Reine Gaspe QC G4X 1T6",
    "addr:housenumber":"178",
    "addr:postcode":"g4x 1t6",
    "addr:street":"Rue De La Reine Gaspe",
    "iso:country":"CA",
    "sg:address":"178 Rue DE LA Reine",
    "sg:city":"Gaspe",
    "sg:classifiers":[
        {
            "category":"Travel",
            "subcategory":"Hotels & Motels",
            "type":"Entertainment"
        }
    ],
    "sg:phone":"+1 418 368 3355",
    "sg:postcode":"G4X 1T6",
    "sg:province":"QC",
    "wof:name":"Hotel Des Commandants",
    "wof:placetype":"venue"
},
  "geometry": {"coordinates":[-64.485405,48.828789],"type":"Point"}
}