{
  "type": "Feature",
  "properties": {
    "addr:full":"631 13 St N Lethbridge AB T1H 2S9",
    "addr:housenumber":"13",
    "addr:postcode":"t1h 2s9",
    "addr:street":"631;St N",
    "iso:country":"CA",
    "sg:address":"631 13 St N",
    "sg:city":"Lethbridge",
    "sg:classifiers":[
        {
            "category":"Organizations",
            "subcategory":"Professional Association",
            "type":"Services"
        }
    ],
    "sg:phone":"+1 403 327 8365",
    "sg:postcode":"T1H 2S9",
    "sg:province":"AB",
    "sg:tags":[
        "club"
    ],
    "wof:name":"Eagles Hall",
    "wof:placetype":"venue"
},
  "geometry": {"coordinates":[-112.824050903,49.7084274292],"type":"Point"}
}