{
  "type": "Feature",
  "properties": {
    "addr:full":"Hwy 43 Gunn AB T0E 1A0",
    "addr:postcode":"t0e 1a0",
    "addr:street":"Hwy 43 Gunn",
    "iso:country":"CA",
    "sg:address":"Hwy 43",
    "sg:city":"Gunn",
    "sg:classifiers":[
        {
            "category":"Autos & Motor Vehicles",
            "subcategory":"Fuel & Gas Station",
            "type":"Retail Goods"
        }
    ],
    "sg:phone":"+1 780 967 2688",
    "sg:postcode":"T0E 1A0",
    "sg:province":"AB",
    "sg:tags":[
        "oil"
    ],
    "wof:name":"Gunn Esso",
    "wof:placetype":"venue"
},
  "geometry": {"coordinates":[-114.34036254900001,53.7303543091],"type":"Point"}
}