{
  "type": "Feature",
  "properties": {
    "addr:full":"26 Queen Niagara on the Lake ON L0S 1J0",
    "addr:housenumber":"26",
    "addr:postcode":"l0s 1j0",
    "addr:street":"Queen;On",
    "iso:country":"CA",
    "sg:address":"26 Queen",
    "sg:city":"Niagara on the Lake",
    "sg:classifiers":[
        {
            "category":"Recreation",
            "type":"Entertainment"
        }
    ],
    "sg:phone":"+1 905 468 4257",
    "sg:postcode":"L0S 1J0",
    "sg:province":"ON",
    "sg:tags":[
        "historical",
        "government"
    ],
    "wof:name":"Fort George National Historic",
    "wof:placetype":"venue"
},
  "geometry": {"coordinates":[-79.07196,43.255245],"type":"Point"}
}