{
  "type": "Feature",
  "properties": {
    "addr:full":"8188 Rue Jean-Brillon Lasalle QC H8N 2J5",
    "addr:housenumber":"8188",
    "addr:postcode":"h8n 2j5",
    "addr:street":"Rue Jean-Brillon",
    "iso:country":"CA",
    "sg:address":"8188 Rue Jean-Brillon",
    "sg:city":"Lasalle",
    "sg:classifiers":[
        {
            "category":"Wholesale",
            "subcategory":"Durable Goods & Equipment",
            "type":"Manufacturing & Wholesale Goods"
        }
    ],
    "sg:phone":"+1 514 368 1666",
    "sg:postcode":"H8N 2J5",
    "sg:province":"QC",
    "sg:tags":[
        "importer"
    ],
    "wof:name":"Simex Intl Inc",
    "wof:placetype":"venue"
},
  "geometry": {"coordinates":[-73.61705000000001,45.432945],"type":"Point"}
}