{
  "type": "Feature",
  "properties": {
    "addr:full":"385 Frederick St Kitchener ON N2H 2P2",
    "addr:housenumber":"385",
    "addr:postcode":"n2h 2p2",
    "addr:street":"Frederick St",
    "iso:country":"CA",
    "sg:address":"385 Frederick St",
    "sg:city":"Kitchener",
    "sg:classifiers":[
        {
            "category":"Shopping",
            "type":"Retail Goods"
        }
    ],
    "sg:phone":"+1 519 578 1471",
    "sg:postcode":"N2H 2P2",
    "sg:province":"ON",
    "sg:tags":[
        "pet",
        "shop"
    ],
    "wof:name":"Animal Crackers",
    "wof:placetype":"venue"
},
  "geometry": {"coordinates":[-80.47380065919999,43.4577217102],"type":"Point"}
}