{
  "type": "Feature",
  "properties": {
    "addr:full":"110 Eglinton Ave W Toronto ON M4R 1A3",
    "addr:housenumber":"110",
    "addr:postcode":"m4r 1a3",
    "addr:street":"Eglinton Ave W",
    "iso:country":"CA",
    "sg:address":"110 Eglinton Ave W",
    "sg:city":"Toronto",
    "sg:classifiers":[
        {
            "category":"Organizations",
            "subcategory":"Professional Association",
            "type":"Services"
        }
    ],
    "sg:phone":"+1 416 322 4950",
    "sg:postcode":"M4R 1A3",
    "sg:province":"ON",
    "wof:name":"Ontario Councils For Agencies",
    "wof:placetype":"venue"
},
  "geometry": {"coordinates":[-79.40167236329999,43.7061271667],"type":"Point"}
}