{
  "type": "Feature",
  "properties": {
    "addr:full":"2175 Airport Dr Saskatoon SK S7L 7E1",
    "addr:housenumber":"2175",
    "addr:postcode":"s7l 7e1",
    "addr:street":"Airport Dr",
    "iso:country":"CA",
    "sg:address":"2175 Airport Dr",
    "sg:city":"Saskatoon",
    "sg:classifiers":[
        {
            "category":"Organizations",
            "subcategory":"Labor Organization",
            "type":"Services"
        }
    ],
    "sg:phone":"+1 306 665 2065",
    "sg:postcode":"S7L 7E1",
    "sg:province":"SK",
    "sg:tags":[
        "consultant",
        "training"
    ],
    "wof:name":"Operating Engineers Training",
    "wof:placetype":"venue"
},
  "geometry": {"coordinates":[-106.68757600000001,52.158272],"type":"Point"}
}