{
  "type": "Feature",
  "properties": {
    "addr:full":"Farm Kamsack SK S0A 1S0",
    "addr:postcode":"s0a 1s0",
    "iso:country":"CA",
    "sg:address":"Farm",
    "sg:city":"Kamsack",
    "sg:classifiers":[
        {
            "category":"Farming",
            "subcategory":"Nursery",
            "type":"Manufacturing & Wholesale Goods"
        }
    ],
    "sg:phone":"+1 306 542 3854",
    "sg:postcode":"S0A 1S0",
    "sg:province":"SK",
    "sg:tags":[
        "greenhouse"
    ],
    "wof:name":"Linda's Garden Path Greenhouse",
    "wof:placetype":"venue"
},
  "geometry": {"coordinates":[-101.903198242,51.5648117065],"type":"Point"}
}