{
  "type": "Feature",
  "properties": {
    "iso:country":"CA",
    "sg:address":"3105 Ch Capelton",
    "sg:city":"North Hatley",
    "sg:classifiers":[
        {
            "category":"Travel",
            "subcategory":"Hotels & Motels",
            "type":"Entertainment"
        }
    ],
    "sg:phone":"+1 819 842 4994",
    "sg:postcode":"J0B 2C0",
    "sg:province":"QC",
    "sg:tags":[
        "breakfast",
        "accommodation",
        "bed"
    ],
    "wof:name":"Gite Le Cachet",
    "wof:placetype":"venue"
},
  "geometry": {"coordinates":[-71.9724197388,45.2793579102],"type":"Point"}
}