{
  "type": "Feature",
  "properties": {
    "addr:full":"19 Rue Maden Salaberry-DE-Valleyfield QC J6S 3V1",
    "addr:housenumber":"19",
    "addr:postcode":"j6s 3v1",
    "addr:street":"Rue Maden",
    "iso:country":"CA",
    "sg:address":"19 Rue Maden",
    "sg:city":"Salaberry-DE-Valleyfield",
    "sg:classifiers":[
        {
            "category":"Recreation",
            "type":"Entertainment"
        }
    ],
    "sg:phone":"+1 450 373 7441",
    "sg:postcode":"J6S 3V1",
    "sg:province":"QC",
    "sg:tags":[
        "club",
        "curling",
        "hall",
        "auditorium"
    ],
    "wof:name":"Club DE Curling Valleyfield",
    "wof:placetype":"venue"
},
  "geometry": {"coordinates":[-74.128708,45.263493],"type":"Point"}
}