{
  "type": "Feature",
  "properties": {
    "addr:full":"88 Rue Du Parc Amqui QC G5J 2L6",
    "addr:housenumber":"88",
    "addr:postcode":"g5j 2l6",
    "addr:street":"Rue Du Parc",
    "iso:country":"CA",
    "sg:address":"88 Rue Du Parc",
    "sg:city":"Amqui",
    "sg:classifiers":[
        {
            "category":"Organizations",
            "subcategory":"Professional Association",
            "type":"Services"
        }
    ],
    "sg:phone":"+1 418 629 2622",
    "sg:postcode":"G5J 2L6",
    "sg:province":"QC",
    "wof:name":"Club Cooperatif DE Consommatn",
    "wof:placetype":"venue"
},
  "geometry": {"coordinates":[-67.4364242554,48.4595870972],"type":"Point"}
}