{
  "type": "Feature",
  "properties": {
    "addr:full":"200 Boul Provencher Winnipeg MB R2H 0G3",
    "addr:housenumber":"200",
    "addr:postcode":"r2h 0g3",
    "addr:street":"Boul Provencher",
    "iso:country":"CA",
    "sg:address":"200 Boul Provencher",
    "sg:city":"Winnipeg",
    "sg:classifiers":[
        {
            "category":"Shopping",
            "subcategory":"Books",
            "type":"Retail Goods"
        }
    ],
    "sg:phone":"+1 204 233 7223",
    "sg:postcode":"R2H 0G3",
    "sg:province":"MB",
    "sg:tags":[
        "dealer"
    ],
    "wof:name":"A LA Page Inc",
    "wof:placetype":"venue"
},
  "geometry": {"coordinates":[-97.121315,49.892094],"type":"Point"}
}