{
  "type": "Feature",
  "properties": {
    "iso:country":"CA",
    "sg:address":"215 Boul Charest E",
    "sg:city":"Quebec",
    "sg:classifiers":[
        {
            "category":"Restaurant",
            "type":"Food & Drink"
        }
    ],
    "sg:phone":"+1 418 525 5555",
    "sg:postcode":"G1K 3G8",
    "sg:province":"QC",
    "wof:name":"Fusee Rotisseries",
    "wof:placetype":"venue"
},
  "geometry": {"coordinates":[-71.22737121580001,46.8122749329],"type":"Point"}
}