{
  "type": "Feature",
  "properties": {
    "iso:country":"CA",
    "sg:address":"6730 Chris Tierney Priv",
    "sg:city":"Metcalfe",
    "sg:classifiers":[
        {
            "category":"Wholesale",
            "subcategory":"Computers",
            "type":"Manufacturing & Wholesale Goods"
        }
    ],
    "sg:phone":"+1 613 821 7809",
    "sg:postcode":"K0A 2P0",
    "sg:province":"ON",
    "sg:tags":[
        "communications",
        "datum"
    ],
    "wof:name":"Radio Grandis Success",
    "wof:placetype":"venue"
},
  "geometry": {"coordinates":[-75.4721908569,45.2360839844],"type":"Point"}
}