{
  "type": "Feature",
  "properties": {
    "addr:full":"4330 Black Gold Dr Leduc AB T9E 3C3",
    "addr:housenumber":"4330",
    "addr:postcode":"t9e 3c3",
    "addr:street":"Black Gold Dr",
    "iso:country":"CA",
    "sg:address":"4330 Black Gold Dr",
    "sg:city":"Leduc",
    "sg:classifiers":[
        {
            "category":"Recreation",
            "type":"Entertainment"
        }
    ],
    "sg:phone":"+1 780 980 7120",
    "sg:postcode":"T9E 3C3",
    "sg:province":"AB",
    "sg:tags":[
        "center",
        "pool",
        "swimming"
    ],
    "wof:name":"Black Gold Svc Ctr",
    "wof:placetype":"venue"
},
  "geometry": {"coordinates":[-113.528564453,53.256187439],"type":"Point"}
}