{
  "type": "Feature",
  "properties": {
    "addr:full":"Vancouver BC V6K 2E4",
    "addr:postcode":"v6k 2e4",
    "iso:country":"CA",
    "sg:city":"Vancouver",
    "sg:classifiers":[
        {
            "category":"Health Services",
            "subcategory":"Health Practitioner",
            "type":"Services"
        }
    ],
    "sg:phone":"+1 604 734 4892",
    "sg:postcode":"V6K 2E4",
    "sg:province":"BC",
    "sg:tags":[
        "psychologist"
    ],
    "wof:name":"Edline Learning Ctr",
    "wof:placetype":"venue"
},
  "geometry": {"coordinates":[-123.156311,49.264042],"type":"Point"}
}