{
  "type": "Feature",
  "properties": {
    "addr:full":"11440 144 Ave NW Edmonton AB T5X 1L8",
    "addr:housenumber":"11440",
    "addr:postcode":"t5x 1l8",
    "addr:street":"144 Ave Nw",
    "iso:country":"CA",
    "sg:address":"11440 144 Ave NW",
    "sg:city":"Edmonton",
    "sg:classifiers":[
        {
            "category":"Personal",
            "type":"Services"
        }
    ],
    "sg:phone":"+1 780 473 6853",
    "sg:postcode":"T5X 1L8",
    "sg:province":"AB",
    "sg:tags":[
        "dating"
    ],
    "wof:name":"Heart To Heart Introductions",
    "wof:placetype":"venue"
},
  "geometry": {"coordinates":[-113.518867493,53.6063346863],"type":"Point"}
}