{
  "type": "Feature",
  "properties": {
    "addr:full":"2615 31st Ave Regina SK S4S 2R3",
    "addr:housenumber":"2615",
    "addr:postcode":"s4s 2r3",
    "addr:street":"31St Ave",
    "iso:country":"CA",
    "sg:address":"2615 31st Ave",
    "sg:city":"Regina",
    "sg:classifiers":[
        {
            "category":"Health Services",
            "subcategory":"Medical Lab",
            "type":"Services"
        }
    ],
    "sg:phone":"+1 306 522 5697",
    "sg:postcode":"S4S 2R3",
    "sg:province":"SK",
    "sg:tags":[
        "laboratory"
    ],
    "wof:name":"Regina Dental Laboratory",
    "wof:placetype":"venue"
},
  "geometry": {"coordinates":[-104.618667602,50.4100379944],"type":"Point"}
}