{
  "type": "Feature",
  "properties": {
    "addr:full":"1975 Rue Ozanne Jonquiere QC G7X 5B1",
    "addr:housenumber":"1975",
    "addr:postcode":"g7x 5b1",
    "addr:street":"Rue Ozanne",
    "iso:country":"CA",
    "sg:address":"1975 Rue Ozanne",
    "sg:city":"Jonquiere",
    "sg:classifiers":[
        {
            "category":"Organizations",
            "subcategory":"Professional Association",
            "type":"Services"
        }
    ],
    "sg:phone":"+1 418 542 3725",
    "sg:postcode":"G7X 5B1",
    "sg:province":"QC",
    "wof:name":"Regroupement Acadien Saguenay",
    "wof:placetype":"venue"
},
  "geometry": {"coordinates":[-71.2380371094,48.4243850708],"type":"Point"}
}