{
  "type": "Feature",
  "properties": {
    "addr:full":"Kelowna BC V1Y 4N7",
    "addr:postcode":"v1y 4n7",
    "iso:country":"CA",
    "sg:city":"Kelowna",
    "sg:classifiers":[
        {
            "category":"Social Services",
            "type":"Services"
        }
    ],
    "sg:phone":"+1 250 762 2525",
    "sg:postcode":"V1Y 4N7",
    "sg:province":"BC",
    "sg:tags":[
        "counselor",
        "marriage",
        "family"
    ],
    "wof:name":"Sutherland, Jan",
    "wof:placetype":"venue"
},
  "geometry": {"coordinates":[-119.458084106,49.8801040649],"type":"Point"}
}