{
  "type": "Feature",
  "properties": {
    "addr:full":"3 Barrett Lane Truro NS B2N 6A3",
    "addr:housenumber":"3",
    "addr:postcode":"b2n 6a3",
    "addr:street":"Barrett Lane",
    "iso:country":"CA",
    "sg:address":"3 Barrett Lane",
    "sg:city":"Truro",
    "sg:classifiers":[
        {
            "category":"Retail",
            "subcategory":"Auto Repair",
            "type":"Services"
        }
    ],
    "sg:phone":"+1 902 897 6242",
    "sg:postcode":"B2N 6A3",
    "sg:province":"NS",
    "sg:tags":[
        "repairing",
        "automobile"
    ],
    "wof:name":"Kerr's Automotive Svc",
    "wof:placetype":"venue"
},
  "geometry": {"coordinates":[-63.263546,45.367172],"type":"Point"}
}