{
  "type": "Feature",
  "properties": {
    "iso:country":"CA",
    "sg:address":"4370 Steeles Ave E",
    "sg:city":"Markham",
    "sg:classifiers":[
        {
            "category":"Personal",
            "subcategory":"Beauty Salon",
            "type":"Services"
        }
    ],
    "sg:phone":"+1 905 479 7889",
    "sg:postcode":"L3R 9V5",
    "sg:province":"ON",
    "wof:name":"Joe Long's Hair Design",
    "wof:placetype":"venue"
},
  "geometry": {"coordinates":[-79.304703,43.824368],"type":"Point"}
}