{
  "type": "Feature",
  "properties": {
    "addr:full":"48 Prospect St Newmarket ON L3Y 3S9",
    "addr:housenumber":"48",
    "addr:postcode":"l3y 3s9",
    "addr:street":"Prospect St",
    "iso:country":"CA",
    "sg:address":"48 Prospect St",
    "sg:city":"Newmarket",
    "sg:classifiers":[
        {
            "category":"Manufacturing",
            "subcategory":"Tools & Machinery",
            "type":"Manufacturing & Wholesale Goods"
        }
    ],
    "sg:phone":"+1 905 895 3262",
    "sg:postcode":"L3Y 3S9",
    "sg:province":"ON",
    "sg:tags":[
        "equipment",
        "conveyor",
        "conveying"
    ],
    "wof:name":"Momentum",
    "wof:placetype":"venue"
},
  "geometry": {"coordinates":[-79.453987,44.058887],"type":"Point"}
}