{
  "type": "Feature",
  "properties": {
    "addr:full":"79 Seventh Ave S Yorkton SK S3N 3V1",
    "addr:housenumber":"79",
    "addr:postcode":"s3n 3v1",
    "addr:street":"Seventh Ave S",
    "iso:country":"CA",
    "sg:address":"79 Seventh Ave S",
    "sg:city":"Yorkton",
    "sg:classifiers":[
        {
            "category":"Organizations",
            "subcategory":"Membership Organization",
            "type":"Services"
        }
    ],
    "sg:phone":"+1 306 783 4080",
    "sg:postcode":"S3N 3V1",
    "sg:province":"SK",
    "sg:tags":[
        "society",
        "humane"
    ],
    "wof:name":"Society For Prevention-Cruelty",
    "wof:placetype":"venue"
},
  "geometry": {"coordinates":[-102.45266700000001,51.207073],"type":"Point"}
}