{
  "type": "Feature",
  "properties": {
    "addr:full":"1085 Boul Mont-Royal Outremont QC H2V 2H5",
    "addr:housenumber":"1085",
    "addr:postcode":"h2v 2h5",
    "addr:street":"Boul Mont-Royal",
    "iso:country":"CA",
    "sg:address":"1085 Boul Mont-Royal",
    "sg:city":"Outremont",
    "sg:classifiers":[
        {
            "category":"Professional",
            "subcategory":"Computer Services",
            "type":"Services"
        }
    ],
    "sg:phone":"+1 514 276 3934",
    "sg:postcode":"H2V 2H5",
    "sg:province":"QC",
    "sg:tags":[
        "information",
        "system",
        "consultant"
    ],
    "wof:name":"Solidbyte Inc",
    "wof:placetype":"venue"
},
  "geometry": {"coordinates":[-73.5920181274,45.5147285461],"type":"Point"}
}