{
  "type": "Feature",
  "properties": {
    "iso:country":"CA",
    "sg:city":"London",
    "sg:classifiers":[
        {
            "category":"Health Services",
            "subcategory":"Doctor",
            "type":"Services"
        }
    ],
    "sg:phone":"+1 519 685 8479",
    "sg:postcode":"N6C 6B5",
    "sg:province":"ON",
    "sg:tags":[
        "physician",
        "surgeon"
    ],
    "wof:name":"Lohmann, R C MD",
    "wof:placetype":"venue"
},
  "geometry": {"coordinates":[-81.225822,42.95853],"type":"Point"}
}