{
  "type": "Feature",
  "properties": {
    "addr:full":"387 Gladstone Ave Ottawa ON K2P 0Y9",
    "addr:housenumber":"387",
    "addr:postcode":"k2p 0y9",
    "addr:street":"Gladstone Ave",
    "iso:country":"CA",
    "sg:address":"387 Gladstone Ave",
    "sg:city":"Ottawa",
    "sg:classifiers":[
        {
            "category":"Professional",
            "subcategory":"Business Services",
            "type":"Services"
        }
    ],
    "sg:phone":"+1 613 233 4445",
    "sg:postcode":"K2P 0Y9",
    "sg:province":"ON",
    "sg:tags":[
        "made",
        "shoes"
    ],
    "wof:name":"Jadan's Orthopedic Shoes Ltd",
    "wof:placetype":"venue"
},
  "geometry": {"coordinates":[-75.6945724487,45.4119262695],"type":"Point"}
}