{
  "type": "Feature",
  "properties": {
    "addr:full":"Fergus ON N1M 2W5",
    "addr:postcode":"n1m 2w5",
    "iso:country":"CA",
    "sg:city":"Fergus",
    "sg:classifiers":[
        {
            "category":"Building & Trades",
            "subcategory":"Electrical",
            "type":"Services"
        }
    ],
    "sg:phone":"+1 519 843 1833",
    "sg:postcode":"N1M 2W5",
    "sg:province":"ON",
    "sg:tags":[
        "electric",
        "contractor"
    ],
    "wof:name":"W S Smith & Son Electric Ltd",
    "wof:placetype":"venue"
},
  "geometry": {"coordinates":[-80.37814299999999,43.705444],"type":"Point"}
}