{
  "type": "Feature",
  "properties": {
    "addr:full":"385 15th St W Prince Albert SK S6V 3R1",
    "addr:housenumber":"385",
    "addr:postcode":"s6v 3r1",
    "addr:street":"15Th St",
    "iso:country":"CA",
    "sg:address":"385 15th St W",
    "sg:city":"Prince Albert",
    "sg:classifiers":[
        {
            "category":"Shopping",
            "subcategory":"Pharmacy",
            "type":"Retail Goods"
        }
    ],
    "sg:phone":"+1 306 922 3784",
    "sg:postcode":"S6V 3R1",
    "sg:province":"SK",
    "wof:name":"My Pharmacy",
    "wof:placetype":"venue"
},
  "geometry": {"coordinates":[-105.764511,53.199326],"type":"Point"}
}