{
  "type": "Feature",
  "properties": {
    "addr:full":"Paris ON N3L 3E3",
    "addr:postcode":"n3l 3e3",
    "iso:country":"CA",
    "sg:city":"Paris",
    "sg:classifiers":[
        {
            "category":"Freight",
            "type":"Transportation"
        }
    ],
    "sg:phone":"+1 519 442 3106",
    "sg:postcode":"N3L 3E3",
    "sg:province":"ON",
    "sg:tags":[
        "trucking"
    ],
    "wof:name":"H S Knill CO Ltd",
    "wof:placetype":"venue"
},
  "geometry": {"coordinates":[-80.392281,43.183514],"type":"Point"}
}