{
  "type": "Feature",
  "properties": {
    "addr:full":"Lacombe AB T4L 2A2",
    "addr:postcode":"t4l 2a2",
    "iso:country":"CA",
    "sg:city":"Lacombe",
    "sg:classifiers":[
        {
            "category":"Health Services",
            "subcategory":"Chiropractor",
            "type":"Services"
        }
    ],
    "sg:phone":"+1 403 782 3341",
    "sg:postcode":"T4L 2A2",
    "sg:province":"AB",
    "wof:name":"Korsh Chiropractic Ctr",
    "wof:placetype":"venue"
},
  "geometry": {"coordinates":[-113.72303008999999,52.4670028687],"type":"Point"}
}