{
  "type": "Feature",
  "properties": {
    "addr:full":"Calgary AB T2C 2C8",
    "addr:postcode":"t2c 2c8",
    "iso:country":"CA",
    "sg:city":"Calgary",
    "sg:classifiers":[
        {
            "category":"Manufacturing",
            "subcategory":"Metals",
            "type":"Manufacturing & Wholesale Goods"
        }
    ],
    "sg:phone":"+1 403 279 6584",
    "sg:postcode":"T2C 2C8",
    "sg:province":"AB",
    "sg:tags":[
        "foundry"
    ],
    "wof:name":"Bronzart Casting Ltd",
    "wof:placetype":"venue"
},
  "geometry": {"coordinates":[-113.97300720200001,50.9964523315],"type":"Point"}
}