{
  "type": "Feature",
  "properties": {
    "addr:full":"RR 4 STN Main North Bay ON P1B 8G5",
    "addr:postcode":"p1b 8g5",
    "addr:street":"Rr 4 Stn Main",
    "iso:country":"CA",
    "sg:address":"RR 4 STN Main",
    "sg:city":"North Bay",
    "sg:classifiers":[
        {
            "category":"Building & Trades",
            "subcategory":"Plumbing",
            "type":"Services"
        }
    ],
    "sg:phone":"+1 705 840 5566",
    "sg:postcode":"P1B 8G5",
    "sg:province":"ON",
    "sg:tags":[
        "septic"
    ],
    "wof:name":"Kono Septic Svc",
    "wof:placetype":"venue"
},
  "geometry": {"coordinates":[-79.4599304199,46.3066291809],"type":"Point"}
}