{
  "type": "Feature",
  "properties": {
    "addr:full":"106 Railway Ave E Choiceland SK S0J 0M0",
    "addr:housenumber":"106",
    "addr:postcode":"s0j 0m0",
    "addr:street":"Railway Ave E Choiceland",
    "iso:country":"CA",
    "sg:address":"106 Railway Ave E",
    "sg:city":"Choiceland",
    "sg:classifiers":[
        {
            "category":"Recreation",
            "type":"Entertainment"
        }
    ],
    "sg:phone":"+1 306 428 2112",
    "sg:postcode":"S0J 0M0",
    "sg:province":"SK",
    "sg:tags":[
        "hall",
        "auditorium"
    ],
    "wof:name":"Choiceland Elk's Hall",
    "wof:placetype":"venue"
},
  "geometry": {"coordinates":[-104.486954,53.492352],"type":"Point"}
}