{
  "type": "Feature",
  "properties": {
    "addr:full":"Mississauga ON L5J 2W1",
    "addr:postcode":"l5j 2w1",
    "iso:country":"CA",
    "sg:city":"Mississauga",
    "sg:classifiers":[
        {
            "category":"Professional",
            "subcategory":"Art Services",
            "type":"Services"
        }
    ],
    "sg:phone":"+1 905 823 1198",
    "sg:postcode":"L5J 2W1",
    "sg:province":"ON",
    "sg:tags":[
        "graphic",
        "designer"
    ],
    "wof:name":"Boomerang Group",
    "wof:placetype":"venue"
},
  "geometry": {"coordinates":[-79.626083374,43.5193481445],"type":"Point"}
}