{
  "type": "Feature",
  "properties": {
    "addr:full":"5325 Harvester Rd Burlington ON L7L 5K4",
    "addr:housenumber":"5325",
    "addr:postcode":"l7l 5k4",
    "addr:street":"Harvester Rd",
    "iso:country":"CA",
    "sg:address":"5325 Harvester Rd",
    "sg:city":"Burlington",
    "sg:classifiers":[
        {
            "category":"Manufacturing",
            "subcategory":"Tools & Machinery",
            "type":"Manufacturing & Wholesale Goods"
        }
    ],
    "sg:phone":"+1 905 681 3496",
    "sg:postcode":"L7L 5K4",
    "sg:province":"ON",
    "sg:tags":[
        "machine"
    ],
    "wof:name":"Hascotech",
    "wof:placetype":"venue"
},
  "geometry": {"coordinates":[-79.75801849370001,43.3866233826],"type":"Point"}
}