{
  "type": "Feature",
  "properties": {
    "addr:full":"506 Boul Renault Beauceville QC G5X 1N2",
    "addr:housenumber":"506",
    "addr:postcode":"g5x 1n2",
    "addr:street":"Boul Renault",
    "iso:country":"CA",
    "sg:address":"506 Boul Renault",
    "sg:city":"Beauceville",
    "sg:classifiers":[
        {
            "category":"Retail",
            "subcategory":"Auto Repair",
            "type":"Services"
        }
    ],
    "sg:phone":"+1 418 774 6884",
    "sg:postcode":"G5X 1N2",
    "sg:province":"QC",
    "sg:tags":[
        "repairing",
        "automobile"
    ],
    "wof:name":"Garage Rodrigue Raymond Inc",
    "wof:placetype":"venue"
},
  "geometry": {"coordinates":[-70.78070831300001,46.2171096802],"type":"Point"}
}