{
  "type": "Feature",
  "properties": {
    "iso:country":"CA",
    "sg:address":"1375 Av Laurier E",
    "sg:city":"Montreal",
    "sg:classifiers":[
        {
            "category":"Food & Beverages",
            "subcategory":"Dairy",
            "type":"Retail Goods"
        }
    ],
    "sg:phone":"+1 514 528 3293",
    "sg:postcode":"H2J 1H6",
    "sg:province":"QC",
    "sg:tags":[
        "cheese"
    ],
    "wof:name":"Fromagerie Maitre Affineur",
    "wof:placetype":"venue"
},
  "geometry": {"coordinates":[-73.583801,45.533669],"type":"Point"}
}