{
  "type": "Feature",
  "properties": {
    "iso:country":"CA",
    "sg:address":"270 Government St",
    "sg:city":"Victoria",
    "sg:classifiers":[
        {
            "category":"Restaurant",
            "type":"Food & Drink"
        }
    ],
    "sg:phone":"+1 250 388 9928",
    "sg:postcode":"V8V 2L2",
    "sg:province":"BC",
    "sg:tags":[
        "caterer"
    ],
    "wof:name":"Colonial Cafe",
    "wof:placetype":"venue"
},
  "geometry": {"coordinates":[-123.36952209499999,48.4151115417],"type":"Point"}
}