{
  "type": "Feature",
  "properties": {
    "iso:country":"CA",
    "sg:address":"4709 50th St",
    "sg:city":"Two Hills",
    "sg:classifiers":[
        {
            "category":"Personal",
            "subcategory":"Beauty Salon",
            "type":"Services"
        }
    ],
    "sg:phone":"+1 780 657 2340",
    "sg:postcode":"T0B 4K0",
    "sg:province":"AB",
    "wof:name":"Vicky's Beauty Salon",
    "wof:placetype":"venue"
},
  "geometry": {"coordinates":[-111.74378967299999,53.7093048096],"type":"Point"}
}