{
  "type": "Feature",
  "properties": {
    "iso:country":"CA",
    "sg:address":"286 Albert St",
    "sg:city":"Oshawa",
    "sg:classifiers":[
        {
            "category":"Shopping",
            "subcategory":"Discount & Variety Stores",
            "type":"Retail Goods"
        }
    ],
    "sg:phone":"+1 905 723 3653",
    "sg:postcode":"L1H 4R8",
    "sg:province":"ON",
    "wof:name":"Fuller's Variety & Lotto Ctr",
    "wof:placetype":"venue"
},
  "geometry": {"coordinates":[-78.85842132569999,43.8905258179],"type":"Point"}
}