{
  "type": "Feature",
  "properties": {
    "iso:country":"CA",
    "sg:address":"924 8 St NW",
    "sg:city":"Slave Lake",
    "sg:classifiers":[
        {
            "category":"Wholesale",
            "subcategory":"Machinery & Supplies",
            "type":"Manufacturing & Wholesale Goods"
        }
    ],
    "sg:phone":"+1 780 849 2158",
    "sg:postcode":"T0G 2A1",
    "sg:province":"AB",
    "sg:tags":[
        "equipment",
        "industrial"
    ],
    "wof:name":"Franklin Parts & Equipment Ltd",
    "wof:placetype":"venue"
},
  "geometry": {"coordinates":[-114.78328704800001,55.2905654907],"type":"Point"}
}