{
  "type": "Feature",
  "properties": {
    "iso:country":"CA",
    "sg:address":"1600 Rue Notre-Dame O",
    "sg:city":"Montreal",
    "sg:classifiers":[
        {
            "category":"Professional",
            "subcategory":"Advertising",
            "type":"Services"
        }
    ],
    "sg:phone":"+1 514 937 1446",
    "sg:postcode":"H3J 1M1",
    "sg:province":"QC",
    "sg:tags":[
        "counselor"
    ],
    "wof:name":"Boom Works Enterprises",
    "wof:placetype":"venue"
},
  "geometry": {"coordinates":[-73.547958374,45.5182304382],"type":"Point"}
}