{
  "type": "Feature",
  "properties": {
    "addr:full":"355 Rue Sainte-Catherine O # 700 Montreal QC H3B 1A5",
    "addr:housenumber":"355",
    "addr:postcode":"h3b 1a5",
    "addr:street":"Rue Sainte-Catherine O # 700",
    "iso:country":"CA",
    "sg:address":"355 Rue Sainte-Catherine O # 700",
    "sg:city":"Montreal",
    "sg:classifiers":[
        {
            "category":"Manufacturing",
            "subcategory":"Printing",
            "type":"Manufacturing & Wholesale Goods"
        }
    ],
    "sg:phone":"+1 514 848 0805",
    "sg:postcode":"H3B 1A5",
    "sg:province":"QC",
    "sg:tags":[
        "newspaper"
    ],
    "wof:name":"Voir",
    "wof:placetype":"venue"
},
  "geometry": {"coordinates":[-73.56098175050001,45.5133514404],"type":"Point"}
}