{
  "type": "Feature",
  "properties": {
    "iso:country":"CA",
    "sg:address":"3515 Boul Des Entreprises",
    "sg:city":"Terrebonne",
    "sg:classifiers":[
        {
            "category":"Building & Trades",
            "subcategory":"Plumbing",
            "type":"Services"
        }
    ],
    "sg:phone":"+1 450 477 6683",
    "sg:postcode":"J6X 4J9",
    "sg:province":"QC",
    "sg:tags":[
        "conditioning",
        "air",
        "system",
        "contractor"
    ],
    "wof:name":"Ventilation E Boucher Inc",
    "wof:placetype":"venue"
},
  "geometry": {"coordinates":[-73.679222,45.729164],"type":"Point"}
}