{
  "type": "Feature",
  "properties": {
    "iso:country":"CA",
    "sg:address":"5435 Baillie St",
    "sg:city":"Vancouver",
    "sg:classifiers":[
        {
            "category":"Education",
            "subcategory":"School",
            "type":"Public Place"
        }
    ],
    "sg:phone":"+1 604 267 9022",
    "sg:postcode":"V5Z 3M6",
    "sg:province":"BC",
    "wof:name":"Ecole Rose-Des-Vents",
    "wof:placetype":"venue"
},
  "geometry": {"coordinates":[-123.122421,49.236309],"type":"Point"}
}