{
  "type": "Feature",
  "properties": {
    "iso:country":"CA",
    "sg:address":"2267 King St W",
    "sg:city":"Sherbrooke",
    "sg:classifiers":[
        {
            "category":"Retail",
            "subcategory":"Laundry & Dry Cleaning",
            "type":"Services"
        }
    ],
    "sg:phone":"+1 819 569 5253",
    "sg:postcode":"J1J 2G2",
    "sg:province":"QC",
    "sg:tags":[
        "cleaners"
    ],
    "wof:name":"Martinizing Une Heure",
    "wof:placetype":"venue"
},
  "geometry": {"coordinates":[-71.928703,45.398544],"type":"Point"}
}