{
  "type": "Feature",
  "properties": {
    "addr:full":"833 Rue Perreault E Rouyn-Noranda QC J9X 5H5",
    "addr:housenumber":"833",
    "addr:postcode":"j9x 5h5",
    "addr:street":"Rue Perreault E",
    "iso:country":"CA",
    "sg:address":"833 Rue Perreault E",
    "sg:city":"Rouyn-Noranda",
    "sg:classifiers":[
        {
            "category":"Organizations",
            "subcategory":"Religious Organization",
            "type":"Services"
        }
    ],
    "sg:phone":"+1 819 762 5454",
    "sg:postcode":"J9X 5H5",
    "sg:province":"QC",
    "wof:name":"Communaute Jesus-Est Seigneur",
    "wof:placetype":"venue"
},
  "geometry": {"coordinates":[-78.996711731,48.2383537292],"type":"Point"}
}