{
  "type": "Feature",
  "properties": {
    "addr:full":"20 Wertheim Crt # 35 Richmond Hill ON L4B 3A8",
    "addr:housenumber":"20;35",
    "addr:postcode":"l4b 3a8",
    "addr:street":"Wertheim Crt #",
    "iso:country":"CA",
    "sg:address":"20 Wertheim Crt # 35",
    "sg:city":"Richmond Hill",
    "sg:classifiers":[
        {
            "category":"Wholesale",
            "subcategory":"Electrical",
            "type":"Manufacturing & Wholesale Goods"
        }
    ],
    "sg:phone":"+1 905 762 8813",
    "sg:postcode":"L4B 3A8",
    "sg:province":"ON",
    "sg:tags":[
        "equipment",
        "electronic",
        "supply"
    ],
    "wof:name":"Kamvic Corp",
    "wof:placetype":"venue"
},
  "geometry": {"coordinates":[-79.386467,43.845337],"type":"Point"}
}