{
  "type": "Feature",
  "properties": {
    "addr:full":"SW 1-13-1W Grosse Isle MB R0C 1G0",
    "addr:postcode":"r0c 1g0",
    "addr:street":"Sw;Grosse Isle",
    "iso:country":"CA",
    "sg:address":"SW 1-13-1W",
    "sg:city":"Grosse Isle",
    "sg:classifiers":[
        {
            "category":"Retail",
            "subcategory":"Repair Shop",
            "type":"Services"
        }
    ],
    "sg:phone":"+1 204 322 5279",
    "sg:postcode":"R0C 1G0",
    "sg:province":"MB",
    "sg:tags":[
        "welding"
    ],
    "wof:name":"Rocklake Shop",
    "wof:placetype":"venue"
},
  "geometry": {"coordinates":[-97.440392,50.06295],"type":"Point"}
}