{
  "type": "Feature",
  "properties": {
    "iso:country":"CA",
    "sg:address":"837 Hamilton St",
    "sg:city":"Vancouver",
    "sg:classifiers":[
        {
            "category":"Personal",
            "subcategory":"Beauty Salon",
            "type":"Services"
        }
    ],
    "sg:phone":"+1 604 688 3653",
    "sg:postcode":"V6B 2R7",
    "sg:province":"BC",
    "wof:name":"Zero F Innovative Hair Svc",
    "wof:placetype":"venue"
},
  "geometry": {"coordinates":[-123.116699,49.278496],"type":"Point"}
}