{
  "type": "Feature",
  "properties": {
    "addr:full":"157 Falkirk St North York ON M5M 4K4",
    "addr:housenumber":"157",
    "addr:postcode":"m5m 4k4",
    "addr:street":"Falkirk St",
    "iso:country":"CA",
    "sg:address":"157 Falkirk St",
    "sg:city":"North York",
    "sg:classifiers":[
        {
            "category":"Organizations",
            "subcategory":"Religious Organization",
            "type":"Services"
        }
    ],
    "sg:phone":"+1 416 783 2941",
    "sg:postcode":"M5M 4K4",
    "sg:province":"ON",
    "sg:tags":[
        "church"
    ],
    "wof:name":"First Hungarian Baptist Church",
    "wof:placetype":"venue"
},
  "geometry": {"coordinates":[-79.427925,43.730457],"type":"Point"}
}