{
  "type": "Feature",
  "properties": {
    "addr:full":"Richmond BC V6X 1R4",
    "addr:postcode":"v6x 1r4",
    "iso:country":"CA",
    "sg:city":"Richmond",
    "sg:classifiers":[
        {
            "category":"Retail",
            "subcategory":"Auto Repair",
            "type":"Services"
        }
    ],
    "sg:phone":"+1 604 278 2213",
    "sg:postcode":"V6X 1R4",
    "sg:province":"BC",
    "sg:tags":[
        "repairing",
        "automobile"
    ],
    "wof:name":"Nick's Auto Repair",
    "wof:placetype":"venue"
},
  "geometry": {"coordinates":[-123.134407044,49.1890945435],"type":"Point"}
}