{
  "type": "Feature",
  "properties": {
    "iso:country":"CA",
    "sg:address":"911 Rue Jean-Talon E",
    "sg:city":"Montreal",
    "sg:classifiers":[
        {
            "category":"Professional",
            "subcategory":"Management & Consulting",
            "type":"Services"
        }
    ],
    "sg:phone":"+1 514 270 5514",
    "sg:postcode":"H2R 1V5",
    "sg:province":"QC",
    "sg:tags":[
        "communications",
        "consultant"
    ],
    "wof:name":"Acor",
    "wof:placetype":"venue"
},
  "geometry": {"coordinates":[-73.613014,45.541256],"type":"Point"}
}