{
  "type": "Feature",
  "properties": {
    "addr:full":"43 Spalding Dr # 12 Brantford ON N3T 6B7",
    "addr:housenumber":"43",
    "addr:postcode":"n3t 6b7",
    "addr:street":"Spalding Dr # 12",
    "iso:country":"CA",
    "sg:address":"43 Spalding Dr # 12",
    "sg:city":"Brantford",
    "sg:classifiers":[
        {
            "category":"Manufacturing",
            "subcategory":"Tools & Machinery",
            "type":"Manufacturing & Wholesale Goods"
        }
    ],
    "sg:phone":"+1 905 389 6487",
    "sg:postcode":"N3T 6B7",
    "sg:province":"ON",
    "sg:tags":[
        "mold"
    ],
    "wof:name":"Silver Fox Productions Inc",
    "wof:placetype":"venue"
},
  "geometry": {"coordinates":[-80.285797,43.13306],"type":"Point"}
}