{
  "type": "Feature",
  "properties": {
    "addr:full":"2033 1st Ave Prince George BC V2L 2Z1",
    "addr:housenumber":"2033",
    "addr:postcode":"v2l 2z1",
    "addr:street":"1St Ave",
    "iso:country":"CA",
    "sg:address":"2033 1st Ave",
    "sg:city":"Prince George",
    "sg:classifiers":[
        {
            "category":"Home & Garden",
            "subcategory":"Mobile Homes",
            "type":"Retail Goods"
        }
    ],
    "sg:phone":"+1 250 562 2338",
    "sg:postcode":"V2L 2Z1",
    "sg:province":"BC",
    "wof:name":"Wayne Mobile Homes Ltd",
    "wof:placetype":"venue"
},
  "geometry": {"coordinates":[-122.760391235,53.9233093262],"type":"Point"}
}