{
  "type": "Feature",
  "properties": {
    "addr:full":"2520 Centre Ave NE Calgary AB T2A 2L2",
    "addr:housenumber":"2520",
    "addr:postcode":"t2a 2l2",
    "addr:street":"Centre Ave Ne",
    "iso:country":"CA",
    "sg:address":"2520 Centre Ave NE",
    "sg:city":"Calgary",
    "sg:classifiers":[
        {
            "category":"Building & Trades",
            "subcategory":"Cleaning & Sanitation",
            "type":"Services"
        }
    ],
    "sg:phone":"+1 403 272 7801",
    "sg:postcode":"T2A 2L2",
    "sg:province":"AB",
    "sg:tags":[
        "janitor"
    ],
    "wof:name":"Alberta Janitorial Ltd",
    "wof:placetype":"venue"
},
  "geometry": {"coordinates":[-114.00046500000001,51.052498],"type":"Point"}
}