{
  "type": "Feature",
  "properties": {
    "addr:full":"Whitecourt AB T7S 1N3",
    "addr:postcode":"t7s 1n3",
    "iso:country":"CA",
    "sg:city":"Whitecourt",
    "sg:classifiers":[
        {
            "category":"Manufacturing",
            "subcategory":"Lumber",
            "type":"Manufacturing & Wholesale Goods"
        }
    ],
    "sg:phone":"+1 780 778 6460",
    "sg:postcode":"T7S 1N3",
    "sg:province":"AB",
    "sg:tags":[
        "company",
        "logging"
    ],
    "wof:name":"T J Logging Inc",
    "wof:placetype":"venue"
},
  "geometry": {"coordinates":[-115.657753,54.125256],"type":"Point"}
}