{
  "type": "Feature",
  "properties": {
    "addr:full":"1809 343 Rte Saint-Ambroise-DE-Kildare QC J0K 1C0",
    "addr:housenumber":"1809",
    "addr:postcode":"j0k 1c0",
    "addr:street":"343 Rte",
    "iso:country":"CA",
    "sg:address":"1809 343 Rte",
    "sg:city":"Saint-Ambroise-DE-Kildare",
    "sg:classifiers":[
        {
            "category":"Retail",
            "subcategory":"Auto Repair",
            "type":"Services"
        }
    ],
    "sg:phone":"+1 450 753 3647",
    "sg:postcode":"J0K 1C0",
    "sg:province":"QC",
    "sg:tags":[
        "muffler",
        "exhaust",
        "system"
    ],
    "wof:name":"Gregoire, Omer",
    "wof:placetype":"venue"
},
  "geometry": {"coordinates":[-73.55443572999999,46.0767784119],"type":"Point"}
}