{
  "type": "Feature",
  "properties": {
    "addr:full":"345 Blind Line Orangeville ON L9W 4X1",
    "addr:housenumber":"345",
    "addr:postcode":"l9w 4x1",
    "addr:street":"Blind Line",
    "iso:country":"CA",
    "sg:address":"345 Blind Line",
    "sg:city":"Orangeville",
    "sg:classifiers":[
        {
            "category":"Education",
            "subcategory":"School",
            "type":"Public Place"
        }
    ],
    "sg:phone":"+1 519 942 5980",
    "sg:postcode":"L9W 4X1",
    "sg:province":"ON",
    "wof:name":"St Benedict School",
    "wof:placetype":"venue"
},
  "geometry": {"coordinates":[-80.11760700000001,43.929005],"type":"Point"}
}