{
  "type": "Feature",
  "properties": {
    "iso:country":"CA",
    "sg:address":"790 Rue Principale",
    "sg:city":"Saint-Amable",
    "sg:classifiers":[
        {
            "category":"Shopping",
            "subcategory":"Jewelry",
            "type":"Retail Goods"
        }
    ],
    "sg:phone":"+1 450 649 0223",
    "sg:postcode":"J0L 1N0",
    "sg:province":"QC",
    "sg:tags":[
        "jeweler"
    ],
    "wof:name":"Bijouterie Hs Inc",
    "wof:placetype":"venue"
},
  "geometry": {"coordinates":[-73.2999038696,45.6478881836],"type":"Point"}
}