{
  "type": "Feature",
  "properties": {
    "addr:full":"731 Rue Guy Montreal QC H3J 1T6",
    "addr:housenumber":"731",
    "addr:postcode":"h3j 1t6",
    "addr:street":"Rue Guy",
    "iso:country":"CA",
    "sg:address":"731 Rue Guy",
    "sg:city":"Montreal",
    "sg:classifiers":[
        {
            "category":"Building & Trades",
            "subcategory":"Construction",
            "type":"Services"
        }
    ],
    "sg:phone":"+1 514 934 2515",
    "sg:postcode":"H3J 1T6",
    "sg:province":"QC",
    "sg:tags":[
        "contractor"
    ],
    "wof:name":"Samcon Drolet",
    "wof:placetype":"venue"
},
  "geometry": {"coordinates":[-73.5705108643,45.491859436],"type":"Point"}
}