{
  "type": "Feature",
  "properties": {
    "addr:full":"708 Scarlett Rd Etobicoke ON M9P 2T5",
    "addr:housenumber":"708",
    "addr:postcode":"m9p 2t5",
    "addr:street":"Scarlett Rd",
    "iso:country":"CA",
    "sg:address":"708 Scarlett Rd",
    "sg:city":"Etobicoke",
    "sg:classifiers":[
        {
            "category":"Food & Beverages",
            "subcategory":"Groceries & Convenience Stores",
            "type":"Retail Goods"
        }
    ],
    "sg:phone":"+1 416 244 2653",
    "sg:postcode":"M9P 2T5",
    "sg:province":"ON",
    "wof:name":"Becker Milk CO Ltd",
    "wof:placetype":"venue"
},
  "geometry": {"coordinates":[-79.52018700000001,43.695312],"type":"Point"}
}