{
  "type": "Feature",
  "properties": {
    "addr:full":"90 Catherine St Blenheim ON N0P 1A0",
    "addr:housenumber":"90",
    "addr:postcode":"n0p 1a0",
    "addr:street":"Catherine St",
    "iso:country":"CA",
    "sg:address":"90 Catherine St",
    "sg:city":"Blenheim",
    "sg:classifiers":[
        {
            "category":"Organizations",
            "subcategory":"Professional Association",
            "type":"Services"
        }
    ],
    "sg:phone":"+1 519 676 3894",
    "sg:postcode":"N0P 1A0",
    "sg:province":"ON",
    "wof:name":"Blenheim & Community Senior",
    "wof:placetype":"venue"
},
  "geometry": {"coordinates":[-81.99825300000001,42.332878],"type":"Point"}
}