{
  "type": "Feature",
  "properties": {
    "iso:country":"CA",
    "sg:address":"213 Algoma St S",
    "sg:city":"Thunder Bay",
    "sg:classifiers":[
        {
            "category":"Retail",
            "subcategory":"Self-service Laundry",
            "type":"Services"
        }
    ],
    "sg:phone":"+1 807 345 0401",
    "sg:postcode":"P7B 3C1",
    "sg:province":"ON",
    "wof:name":"Barb's Laundromat",
    "wof:placetype":"venue"
},
  "geometry": {"coordinates":[-89.23063659669999,48.4304084778],"type":"Point"}
}