{
  "type": "Feature",
  "properties": {
    "addr:full":"34274 97th St Oliver BC V0H 1T0",
    "addr:housenumber":"34274",
    "addr:postcode":"bc v0h 1t0",
    "addr:street":"97Th St",
    "iso:country":"CA",
    "sg:address":"34274 97th St",
    "sg:city":"Oliver",
    "sg:classifiers":[
        {
            "category":"Autos & Motor Vehicles",
            "subcategory":"Auto Supplies",
            "type":"Retail Goods"
        }
    ],
    "sg:phone":"+1 250 498 0600",
    "sg:postcode":"V0H 1T0",
    "sg:province":"BC",
    "sg:tags":[
        "automobile",
        "parts"
    ],
    "wof:name":"Lordco Parts Ltd",
    "wof:placetype":"venue"
},
  "geometry": {"coordinates":[-119.553864,49.175415],"type":"Point"}
}