{
  "type": "Feature",
  "properties": {
    "addr:full":"Farm Kelvington SK S0A 1W0",
    "addr:postcode":"s0a 1w0",
    "iso:country":"CA",
    "sg:address":"Farm",
    "sg:city":"Kelvington",
    "sg:classifiers":[
        {
            "category":"Autos & Motor Vehicles",
            "subcategory":"Automobile Sales",
            "type":"Retail Goods"
        }
    ],
    "sg:phone":"+1 306 327 5774",
    "sg:postcode":"S0A 1W0",
    "sg:province":"SK",
    "sg:tags":[
        "snowmobile"
    ],
    "wof:name":"Brian Choquette",
    "wof:placetype":"venue"
},
  "geometry": {"coordinates":[-103.52950300000001,52.164566],"type":"Point"}
}