{
  "type": "Feature",
  "properties": {
    "addr:full":"31 Tapscott Rd Scarborough ON M1B 4Y7",
    "addr:housenumber":"31",
    "addr:postcode":"m1b 4y7",
    "addr:street":"Tapscott Rd",
    "iso:country":"CA",
    "sg:address":"31 Tapscott Rd",
    "sg:city":"Scarborough",
    "sg:classifiers":[
        {
            "category":"Shopping",
            "subcategory":"Clothing, Apparel, & Fashions",
            "type":"Retail Goods"
        }
    ],
    "sg:phone":"+1 416 299 7727",
    "sg:postcode":"M1B 4Y7",
    "sg:province":"ON",
    "sg:tags":[
        "furnishing"
    ],
    "wof:name":"John Pomer Menswear",
    "wof:placetype":"venue"
},
  "geometry": {"coordinates":[-79.22133636469999,43.8055305481],"type":"Point"}
}