{
  "type": "Feature",
  "properties": {
    "addr:full":"2100 98E Rue Saint-Georges QC G5Y 8J6",
    "addr:housenumber":"2100",
    "addr:postcode":"g5y 8j6",
    "addr:street":"98E Rue",
    "iso:country":"CA",
    "sg:address":"2100 98E Rue",
    "sg:city":"Saint-Georges",
    "sg:classifiers":[
        {
            "category":"Building & Trades",
            "subcategory":"Construction",
            "type":"Services"
        }
    ],
    "sg:phone":"+1 418 228 8221",
    "sg:postcode":"G5Y 8J6",
    "sg:province":"QC",
    "sg:tags":[
        "concrete",
        "cutting",
        "breaking",
        "sawing"
    ],
    "wof:name":"Sciage DE Beton Robert Inc",
    "wof:placetype":"venue"
},
  "geometry": {"coordinates":[-70.67295799999999,46.13773],"type":"Point"}
}