{
  "type": "Feature",
  "properties": {
    "addr:full":"252 Hunt St Ajax ON L1S 1P7",
    "addr:housenumber":"252",
    "addr:postcode":"l1s 1p7",
    "addr:street":"Hunt St",
    "iso:country":"CA",
    "sg:address":"252 Hunt St",
    "sg:city":"Ajax",
    "sg:classifiers":[
        {
            "category":"Wholesale",
            "subcategory":"Machinery & Supplies",
            "type":"Manufacturing & Wholesale Goods"
        }
    ],
    "sg:phone":"+1 905 683 7303",
    "sg:postcode":"L1S 1P7",
    "sg:province":"ON",
    "sg:tags":[
        "valve"
    ],
    "wof:name":"M A Stewart & Sons Ltd",
    "wof:placetype":"venue"
},
  "geometry": {"coordinates":[-79.0285568237,43.8456382751],"type":"Point"}
}