{
  "type": "Feature",
  "properties": {
    "addr:full":"7505 Boul Taschereau Brossard QC J4Y 1A2",
    "addr:housenumber":"7505",
    "addr:postcode":"j4y 1a2",
    "addr:street":"Boul Taschereau",
    "iso:country":"CA",
    "sg:address":"7505 Boul Taschereau",
    "sg:city":"Brossard",
    "sg:classifiers":[
        {
            "category":"Insurance",
            "subcategory":"Insurance Agent",
            "type":"Services"
        }
    ],
    "sg:phone":"+1 450 676 9677",
    "sg:postcode":"J4Y 1A2",
    "sg:province":"QC",
    "sg:tags":[
        "consultant"
    ],
    "wof:name":"Gestion Vias Ltee",
    "wof:placetype":"venue"
},
  "geometry": {"coordinates":[-73.464714,45.457832],"type":"Point"}
}