{
  "type": "Feature",
  "properties": {
    "addr:full":"2078 Talbot Rd Kingsville ON N9Y 2E4",
    "addr:housenumber":"2078",
    "addr:postcode":"n9y 2e4",
    "addr:street":"Talbot Rd",
    "iso:country":"CA",
    "sg:address":"2078 Talbot Rd",
    "sg:city":"Kingsville",
    "sg:classifiers":[
        {
            "category":"Home & Garden",
            "subcategory":"Garden Supply",
            "type":"Retail Goods"
        }
    ],
    "sg:phone":"+1 519 326 8840",
    "sg:postcode":"N9Y 2E4",
    "sg:province":"ON",
    "sg:tags":[
        "florist",
        "center"
    ],
    "wof:name":"Capogna Flowers",
    "wof:placetype":"venue"
},
  "geometry": {"coordinates":[-82.6510543823,42.0504684448],"type":"Point"}
}