{
  "type": "Feature",
  "properties": {
    "addr:full":"525 Victoria Ave N Hamilton ON L8L 8G7",
    "addr:housenumber":"525",
    "addr:postcode":"l8l 8g7",
    "addr:street":"Victoria Ave N",
    "iso:country":"CA",
    "sg:address":"525 Victoria Ave N",
    "sg:city":"Hamilton",
    "sg:classifiers":[
        {
            "category":"Home & Garden",
            "subcategory":"Building Materials",
            "type":"Retail Goods"
        }
    ],
    "sg:phone":"+1 905 528 1468",
    "sg:postcode":"L8L 8G7",
    "sg:province":"ON",
    "sg:tags":[
        "mixed",
        "concrete"
    ],
    "wof:name":"Lafarge Cananda Inc",
    "wof:placetype":"venue"
},
  "geometry": {"coordinates":[-79.849937439,43.2690162659],"type":"Point"}
}