{
  "type": "Feature",
  "properties": {
    "iso:country":"CA",
    "sg:address":"17600 Yonge St # 356",
    "sg:city":"Newmarket",
    "sg:classifiers":[
        {
            "category":"Shopping",
            "subcategory":"Clothing, Apparel, & Fashions",
            "type":"Retail Goods"
        }
    ],
    "sg:phone":"+1 905 836 9094",
    "sg:postcode":"L3Y 4Z1",
    "sg:province":"ON",
    "sg:tags":[
        "furnishing"
    ],
    "wof:name":"Randy River",
    "wof:placetype":"venue"
},
  "geometry": {"coordinates":[-79.4811096191,44.057056427],"type":"Point"}
}