{
  "type": "Feature",
  "properties": {
    "addr:full":"760 Champlain St Dieppe NB E1A 1P5",
    "addr:housenumber":"760",
    "addr:postcode":"e1a 1p5",
    "addr:street":"Champlain St",
    "iso:country":"CA",
    "sg:address":"760 Champlain St",
    "sg:city":"Dieppe",
    "sg:classifiers":[
        {
            "category":"Restaurant",
            "type":"Food & Drink"
        }
    ],
    "sg:phone":"+1 506 857 3738",
    "sg:postcode":"E1A 1P5",
    "sg:province":"NB",
    "wof:name":"Mooser's Pub & Eatery",
    "wof:placetype":"venue"
},
  "geometry": {"coordinates":[-64.7220993042,46.1006355286],"type":"Point"}
}