{
  "type": "Feature",
  "properties": {
    "addr:full":"3401 Sheppard Ave E Scarborough ON M1T 3K5",
    "addr:housenumber":"3401",
    "addr:postcode":"m1t 3k5",
    "addr:street":"Sheppard Ave E",
    "iso:country":"CA",
    "sg:address":"3401 Sheppard Ave E",
    "sg:city":"Scarborough",
    "sg:classifiers":[
        {
            "category":"Autos & Motor Vehicles",
            "subcategory":"Fuel & Gas Station",
            "type":"Retail Goods"
        }
    ],
    "sg:phone":"+1 416 292 0322",
    "sg:postcode":"M1T 3K5",
    "sg:province":"ON",
    "sg:tags":[
        "oil"
    ],
    "wof:name":"Shell Gas Bar",
    "wof:placetype":"venue"
},
  "geometry": {"coordinates":[-79.3074417114,43.7786865234],"type":"Point"}
}