{
  "type": "Feature",
  "properties": {
    "addr:full":"Edson AB T7E 1T3",
    "addr:postcode":"t7e 1t3",
    "iso:country":"CA",
    "sg:city":"Edson",
    "sg:classifiers":[
        {
            "category":"Real Estate",
            "subcategory":"Real Estate Agent",
            "type":"Services"
        }
    ],
    "sg:phone":"+1 780 723 7444",
    "sg:postcode":"T7E 1T3",
    "sg:province":"AB",
    "sg:tags":[
        "appraiser"
    ],
    "wof:name":"West Central Property Svc Inc",
    "wof:placetype":"venue"
},
  "geometry": {"coordinates":[-116.43409729,53.5821304321],"type":"Point"}
}