{
  "type": "Feature",
  "properties": {
    "addr:full":"160 Broadway St LA Riviere MB R0G 1A0",
    "addr:housenumber":"160",
    "addr:postcode":"r0g 1a0",
    "addr:street":"Broadway St",
    "iso:country":"CA",
    "sg:address":"160 Broadway St",
    "sg:city":"LA Riviere",
    "sg:classifiers":[
        {
            "category":"Autos & Motor Vehicles",
            "subcategory":"Fuel & Gas Station",
            "type":"Retail Goods"
        }
    ],
    "sg:phone":"+1 204 242 2565",
    "sg:postcode":"R0G 1A0",
    "sg:province":"MB",
    "sg:tags":[
        "oil"
    ],
    "wof:name":"L A Wiklund's Garage",
    "wof:placetype":"venue"
},
  "geometry": {"coordinates":[-98.68032073969999,49.2387390137],"type":"Point"}
}