{
  "type": "Feature",
  "properties": {
    "addr:full":"1011 Lansdowne Ave # 100 Toronto ON M6H 4G1",
    "addr:housenumber":"1011",
    "addr:postcode":"m6h 4g1",
    "addr:street":"Lansdowne Ave # 100",
    "iso:country":"CA",
    "sg:address":"1011 Lansdowne Ave # 100",
    "sg:city":"Toronto",
    "sg:classifiers":[
        {
            "category":"Real Estate",
            "subcategory":"Real Estate Operator",
            "type":"Services"
        }
    ],
    "sg:phone":"+1 416 536 2541",
    "sg:postcode":"M6H 4G1",
    "sg:province":"ON",
    "sg:tags":[
        "apartment"
    ],
    "wof:name":"Lansdowne Property Management",
    "wof:placetype":"venue"
},
  "geometry": {"coordinates":[-79.44641900000001,43.667149],"type":"Point"}
}