{
  "type": "Feature",
  "properties": {
    "iso:country":"CA",
    "sg:city":"New Westminster",
    "sg:classifiers":[
        {
            "category":"Real Estate",
            "subcategory":"Surveying",
            "type":"Services"
        }
    ],
    "sg:phone":"+1 604 526 2721",
    "sg:postcode":"V3M 3L7",
    "sg:province":"BC",
    "sg:tags":[
        "surveyor"
    ],
    "wof:name":"Arnold & Assoc",
    "wof:placetype":"venue"
},
  "geometry": {"coordinates":[-122.90990447999999,49.2021751404],"type":"Point"}
}