{
  "type": "Feature",
  "properties": {
    "addr:full":"567 Main St E North Bay ON P1B 1B7",
    "addr:housenumber":"567",
    "addr:postcode":"p1b 1b7",
    "addr:street":"Main St E",
    "iso:country":"CA",
    "sg:address":"567 Main St E",
    "sg:city":"North Bay",
    "sg:classifiers":[
        {
            "category":"Personal",
            "subcategory":"Beauty Salon",
            "type":"Services"
        }
    ],
    "sg:phone":"+1 705 476 7500",
    "sg:postcode":"P1B 1B7",
    "sg:province":"ON",
    "sg:tags":[
        "barber"
    ],
    "wof:name":"Ben's Barber Shop",
    "wof:placetype":"venue"
},
  "geometry": {"coordinates":[-79.45869399999999,46.30423],"type":"Point"}
}