{
  "type": "Feature",
  "properties": {
    "addr:full":"1024 Rue Mathieu Saint-Jerome QC J5L 1Z7",
    "addr:housenumber":"1024",
    "addr:postcode":"j5l 1z7",
    "addr:street":"Rue Mathieu Saint-Jerome",
    "iso:country":"CA",
    "sg:address":"1024 Rue Mathieu",
    "sg:city":"Saint-Jerome",
    "sg:classifiers":[
        {
            "category":"Wholesale",
            "subcategory":"Office Equipment",
            "type":"Manufacturing & Wholesale Goods"
        }
    ],
    "sg:phone":"+1 450 431 4552",
    "sg:postcode":"J5L 1Z7",
    "sg:province":"QC",
    "sg:tags":[
        "accounting",
        "accountant",
        "bookkeeping",
        "system"
    ],
    "wof:name":"Charette, Pierre",
    "wof:placetype":"venue"
},
  "geometry": {"coordinates":[-74.03681899999999,45.79781],"type":"Point"}
}