{
  "type": "Feature",
  "properties": {
    "addr:full":"Fort Mcmurray AB T9H 4B1",
    "addr:postcode":"t9h 4b1",
    "iso:country":"CA",
    "sg:city":"Fort Mcmurray",
    "sg:classifiers":[
        {
            "category":"Retail",
            "subcategory":"Auto Repair",
            "type":"Services"
        }
    ],
    "sg:phone":"+1 780 791 4323",
    "sg:postcode":"T9H 4B1",
    "sg:province":"AB",
    "sg:tags":[
        "repairing",
        "automobile",
        "radiator"
    ],
    "wof:name":"Global Heat Transfer Ltd",
    "wof:placetype":"venue"
},
  "geometry": {"coordinates":[-111.3442,56.669041],"type":"Point"}
}