{
  "type": "Feature",
  "properties": {
    "addr:full":"179 Boul LA Salle Baie-Comeau QC G4Z 1S7",
    "addr:housenumber":"179",
    "addr:postcode":"g4z 1s7",
    "addr:street":"Boul La",
    "iso:country":"CA",
    "sg:address":"179 Boul LA Salle",
    "sg:city":"Baie-Comeau",
    "sg:classifiers":[
        {
            "category":"Manufacturing",
            "subcategory":"Signs",
            "type":"Manufacturing & Wholesale Goods"
        }
    ],
    "sg:phone":"+1 418 296 4318",
    "sg:postcode":"G4Z 1S7",
    "sg:province":"QC",
    "sg:tags":[
        "painter"
    ],
    "wof:name":"Trim Line Baie-Comeau Enr",
    "wof:placetype":"venue"
},
  "geometry": {"coordinates":[-68.15248099999999,49.221039],"type":"Point"}
}