{
  "type": "Feature",
  "properties": {
    "addr:full":"200 Albert St Regina SK S4R 2N4",
    "addr:housenumber":"200",
    "addr:postcode":"s4r 2n4",
    "addr:street":"Albert St",
    "iso:country":"CA",
    "sg:address":"200 Albert St",
    "sg:city":"Regina",
    "sg:classifiers":[
        {
            "category":"Retail",
            "subcategory":"Auto Rental",
            "type":"Services"
        }
    ],
    "sg:phone":"+1 306 352 4222",
    "sg:postcode":"S4R 2N4",
    "sg:province":"SK",
    "sg:tags":[
        "renting",
        "automobile"
    ],
    "wof:name":"Enterprise Rent-A-Car",
    "wof:placetype":"venue"
},
  "geometry": {"coordinates":[-104.618339539,50.4753341675],"type":"Point"}
}