{
  "type": "Feature",
  "properties": {
    "iso:country":"CA",
    "sg:city":"Montreal",
    "sg:classifiers":[
        {
            "category":"Shopping",
            "subcategory":"Jewelry",
            "type":"Retail Goods"
        }
    ],
    "sg:phone":"+1 514 861 5788",
    "sg:postcode":"H3B 3G1",
    "sg:province":"QC",
    "sg:tags":[
        "gemologists"
    ],
    "wof:name":"Groupe Gemmologique Arr",
    "wof:placetype":"venue"
},
  "geometry": {"coordinates":[-73.55439,45.512287],"type":"Point"}
}