{
  "type": "Feature",
  "properties": {
    "addr:full":"4199 River Rd Niagara Falls ON L2E 3E7",
    "addr:housenumber":"4199",
    "addr:postcode":"l2e 3e7",
    "addr:street":"River Rd",
    "iso:country":"CA",
    "sg:address":"4199 River Rd",
    "sg:city":"Niagara Falls",
    "sg:classifiers":[
        {
            "category":"Recreation",
            "type":"Entertainment"
        }
    ],
    "sg:phone":"+1 905 357 1133",
    "sg:postcode":"L2E 3E7",
    "sg:province":"ON",
    "sg:tags":[
        "shop",
        "attraction",
        "tourist",
        "gift"
    ],
    "wof:name":"Souvenir City",
    "wof:placetype":"venue"
},
  "geometry": {"coordinates":[-79.0614776611,43.112865448],"type":"Point"}
}