{
  "type": "Feature",
  "properties": {
    "addr:full":"1037 Ch Denison O Granby QC J2G 8C6",
    "addr:housenumber":"1037",
    "addr:postcode":"j2g 8c6",
    "addr:street":"Ch Denison O",
    "iso:country":"CA",
    "sg:address":"1037 Ch Denison O",
    "sg:city":"Granby",
    "sg:classifiers":[
        {
            "category":"Building & Trades",
            "subcategory":"Construction",
            "type":"Services"
        }
    ],
    "sg:phone":"+1 450 378 9600",
    "sg:postcode":"J2G 8C6",
    "sg:province":"QC",
    "sg:tags":[
        "general",
        "adjuster",
        "insurance",
        "contractor"
    ],
    "wof:name":"Constructions Ultra",
    "wof:placetype":"venue"
},
  "geometry": {"coordinates":[-72.75756072999999,45.3666877747],"type":"Point"}
}