{
  "type": "Feature",
  "properties": {
    "addr:full":"200 Rue Montcalm Hull QC J8Y 3B5",
    "addr:housenumber":"200",
    "addr:postcode":"j8y 3b5",
    "addr:street":"Rue Montcalm",
    "iso:country":"CA",
    "sg:address":"200 Rue Montcalm",
    "sg:city":"Hull",
    "sg:classifiers":[
        {
            "category":"Real Estate",
            "subcategory":"Real Estate Operator",
            "type":"Services"
        }
    ],
    "sg:phone":"+1 819 776 5062",
    "sg:postcode":"J8Y 3B5",
    "sg:province":"QC",
    "sg:tags":[
        "building",
        "parks"
    ],
    "wof:name":"Societe En Commandite Montcalm",
    "wof:placetype":"venue"
},
  "geometry": {"coordinates":[-75.729614,45.430573],"type":"Point"}
}