{
  "type": "Feature",
  "properties": {
    "addr:full":"Erie N Merlin ON N0P 1W0",
    "addr:postcode":"n0p 1w0",
    "addr:street":"N Merlin",
    "iso:country":"CA",
    "sg:address":"Erie N",
    "sg:city":"Merlin",
    "sg:classifiers":[
        {
            "category":"Organizations",
            "subcategory":"Professional Association",
            "type":"Services"
        }
    ],
    "sg:phone":"+1 519 689 4574",
    "sg:postcode":"N0P 1W0",
    "sg:province":"ON",
    "sg:tags":[
        "club"
    ],
    "wof:name":"Merlin Kinsmen Club",
    "wof:placetype":"venue"
},
  "geometry": {"coordinates":[-82.23555755620001,42.2444992065],"type":"Point"}
}