{
  "type": "Feature",
  "properties": {
    "iso:country":"CA",
    "sg:address":"341 Dalhousie St",
    "sg:city":"Ottawa",
    "sg:classifiers":[
        {
            "category":"Personal",
            "subcategory":"Shoe Repair & Shine",
            "type":"Services"
        }
    ],
    "sg:phone":"+1 613 562 2141",
    "sg:postcode":"K1N 7G1",
    "sg:province":"ON",
    "sg:tags":[
        "repairing",
        "boot"
    ],
    "wof:name":"Bytown Shoe Repair",
    "wof:placetype":"venue"
},
  "geometry": {"coordinates":[-75.690567,45.428337],"type":"Point"}
}