{
  "type": "Feature",
  "properties": {
    "addr:full":"Saint John NB E2L 2A9",
    "addr:postcode":"e2l 2a9",
    "iso:country":"CA",
    "sg:city":"Saint John",
    "sg:classifiers":[
        {
            "category":"Banks & Credit Unions",
            "subcategory":"Investment Brokerage",
            "type":"Services"
        }
    ],
    "sg:phone":"+1 506 634 1220",
    "sg:postcode":"E2L 2A9",
    "sg:province":"NB",
    "wof:name":"Cibc Wood Gundy Inc",
    "wof:placetype":"venue"
},
  "geometry": {"coordinates":[-66.062607,45.274921],"type":"Point"}
}