{
  "type": "Feature",
  "properties": {
    "addr:full":"2200 Montreal Rd # C8 Gloucester ON K1J 6M5",
    "addr:housenumber":"2200",
    "addr:postcode":"k1j 6m5",
    "addr:street":"Montreal Rd # C8",
    "iso:country":"CA",
    "sg:address":"2200 Montreal Rd # C8",
    "sg:city":"Gloucester",
    "sg:classifiers":[
        {
            "category":"Personal",
            "subcategory":"Tanning Parlor",
            "type":"Services"
        }
    ],
    "sg:phone":"+1 613 742 7888",
    "sg:postcode":"K1J 6M5",
    "sg:province":"ON",
    "sg:tags":[
        "salon"
    ],
    "wof:name":"Mirage Tanning Ctr",
    "wof:placetype":"venue"
},
  "geometry": {"coordinates":[-75.58802,45.449875],"type":"Point"}
}