{
  "type": "Feature",
  "properties": {
    "iso:country":"CA",
    "sg:address":"1364 Will Scarlett Dr",
    "sg:city":"Oakville",
    "sg:classifiers":[
        {
            "category":"Professional",
            "subcategory":"Management & Consulting",
            "type":"Services"
        }
    ],
    "sg:phone":"+1 905 829 8105",
    "sg:postcode":"L6J 6T8",
    "sg:province":"ON",
    "sg:tags":[
        "consultant",
        "security",
        "system"
    ],
    "wof:name":"Ltd & Assoc",
    "wof:placetype":"venue"
},
  "geometry": {"coordinates":[-79.6615905762,43.5046157837],"type":"Point"}
}