{
  "type": "Feature",
  "properties": {
    "addr:full":"PO Box 5363 STN Main Lacombe AB T4L 1X1",
    "addr:housenumber":"po",
    "addr:postcode":"5363;t4l 1x1",
    "addr:street":"Box;Stn Main",
    "iso:country":"CA",
    "sg:address":"PO Box 5363 STN Main",
    "sg:city":"Lacombe",
    "sg:classifiers":[
        {
            "category":"Wholesale",
            "subcategory":"Machinery & Supplies",
            "type":"Manufacturing & Wholesale Goods"
        }
    ],
    "sg:phone":"+1 403 782 7897",
    "sg:postcode":"T4L 1X1",
    "sg:province":"AB",
    "sg:tags":[
        "director",
        "funeral"
    ],
    "wof:name":"D & L Specialties Inc",
    "wof:placetype":"venue"
},
  "geometry": {"coordinates":[-113.73670199999999,52.463112],"type":"Point"}
}