{
  "type": "Feature",
  "properties": {
    "iso:country":"CA",
    "sg:address":"95 Allaura Blvd",
    "sg:city":"Aurora",
    "sg:classifiers":[
        {
            "category":"Social Services",
            "subcategory":"Child Care",
            "type":"Services"
        }
    ],
    "sg:phone":"+1 905 841 2382",
    "sg:postcode":"L4G 3N2",
    "sg:province":"ON",
    "wof:name":"Crescentbrook Farms Childcare",
    "wof:placetype":"venue"
},
  "geometry": {"coordinates":[-79.4593429565,43.9869155884],"type":"Point"}
}