{
  "type": "Feature",
  "properties": {
    "iso:country":"CA",
    "sg:address":"6986 Mccordick Rd",
    "sg:city":"North Gower",
    "sg:classifiers":[
        {
            "category":"Home & Garden",
            "subcategory":"Garden Supply",
            "type":"Retail Goods"
        }
    ],
    "sg:phone":"+1 613 489 0396",
    "sg:postcode":"K0A 2T0",
    "sg:province":"ON",
    "sg:tags":[
        "center"
    ],
    "wof:name":"Rideau Nursery",
    "wof:placetype":"venue"
},
  "geometry": {"coordinates":[-75.721863,45.10854],"type":"Point"}
}