{
  "type": "Feature",
  "properties": {
    "addr:full":"214 62 Ave SE Calgary AB T2H 2E6",
    "addr:postcode":"t2h 2e6",
    "addr:street":"214 62 Ave Se",
    "iso:country":"CA",
    "sg:address":"214 62 Ave SE",
    "sg:city":"Calgary",
    "sg:classifiers":[
        {
            "category":"Retail",
            "subcategory":"Auto Repair",
            "type":"Services"
        }
    ],
    "sg:phone":"+1 403 253 5568",
    "sg:postcode":"T2H 2E6",
    "sg:province":"AB",
    "sg:tags":[
        "repairing",
        "automobile"
    ],
    "wof:name":"Wagner Automotive Inc",
    "wof:placetype":"venue"
},
  "geometry": {"coordinates":[-114.061683655,50.9966545105],"type":"Point"}
}