{
  "type": "Feature",
  "properties": {
    "addr:full":"44 Reid St Trenton ON K8V 5V9",
    "addr:housenumber":"44",
    "addr:postcode":"k8v 5v9",
    "addr:street":"Reid St",
    "iso:country":"CA",
    "sg:address":"44 Reid St",
    "sg:city":"Trenton",
    "sg:classifiers":[
        {
            "category":"Building & Trades",
            "subcategory":"Construction",
            "type":"Services"
        }
    ],
    "sg:phone":"+1 613 392 1649",
    "sg:postcode":"K8V 5V9",
    "sg:province":"ON",
    "sg:tags":[
        "home",
        "general",
        "improvement",
        "contractor"
    ],
    "wof:name":"Quinn Quest Renovations",
    "wof:placetype":"venue"
},
  "geometry": {"coordinates":[-77.57260100000001,44.121235],"type":"Point"}
}