{
  "type": "Feature",
  "properties": {
    "addr:full":"Oshawa ON L1G 4X8",
    "addr:postcode":"l1g 4x8",
    "iso:country":"CA",
    "sg:city":"Oshawa",
    "sg:classifiers":[
        {
            "category":"Food & Beverages",
            "subcategory":"Groceries & Convenience Stores",
            "type":"Retail Goods"
        }
    ],
    "sg:phone":"+1 905 434 7086",
    "sg:postcode":"L1G 4X8",
    "sg:province":"ON",
    "wof:name":"Glovers Milk",
    "wof:placetype":"venue"
},
  "geometry": {"coordinates":[-78.8808670044,43.9374351501],"type":"Point"}
}