{
  "type": "Feature",
  "properties": {
    "iso:country":"CA",
    "sg:address":"4960 Av Roslyn",
    "sg:city":"Montreal",
    "sg:classifiers":[
        {
            "category":"Professional",
            "subcategory":"Engineering",
            "type":"Services"
        }
    ],
    "sg:phone":"+1 514 737 4283",
    "sg:postcode":"H3W 2L2",
    "sg:province":"QC",
    "sg:tags":[
        "engineer"
    ],
    "wof:name":"J H Britnap Inc",
    "wof:placetype":"venue"
},
  "geometry": {"coordinates":[-73.621429,45.488663],"type":"Point"}
}