{
  "type": "Feature",
  "properties": {
    "addr:full":"14750 St Albert Trail NW Edmonton AB T6V 1H5",
    "addr:housenumber":"14750",
    "addr:postcode":"t6v 1h5",
    "addr:street":"St Albert Trail Nw",
    "iso:country":"CA",
    "sg:address":"14750 St Albert Trail NW",
    "sg:city":"Edmonton",
    "sg:classifiers":[
        {
            "category":"Autos & Motor Vehicles",
            "subcategory":"Automobile Sales",
            "type":"Retail Goods"
        }
    ],
    "sg:phone":"+1 780 454 2000",
    "sg:postcode":"T6V 1H5",
    "sg:province":"AB",
    "sg:tags":[
        "car",
        "dealer"
    ],
    "wof:name":"City Ford Sales Ltd",
    "wof:placetype":"venue"
},
  "geometry": {"coordinates":[-113.587852,53.609261],"type":"Point"}
}