{
  "type": "Feature",
  "properties": {
    "addr:full":"41 Maple St Winnipeg MB R3B 3G4",
    "addr:housenumber":"41",
    "addr:postcode":"r3b 3g4",
    "addr:street":"Maple St",
    "iso:country":"CA",
    "sg:address":"41 Maple St",
    "sg:city":"Winnipeg",
    "sg:classifiers":[
        {
            "category":"Organizations",
            "subcategory":"Religious Organization",
            "type":"Services"
        }
    ],
    "sg:phone":"+1 204 943 5980",
    "sg:postcode":"R3B 3G4",
    "sg:province":"MB",
    "sg:tags":[
        "church"
    ],
    "wof:name":"Pilgrim Baptist Church",
    "wof:placetype":"venue"
},
  "geometry": {"coordinates":[-97.131317,49.903545],"type":"Point"}
}