{
  "type": "Feature",
  "properties": {
    "iso:country":"CA",
    "sg:address":"31 Empress Ave",
    "sg:city":"Hamilton",
    "sg:classifiers":[
        {
            "category":"Organizations",
            "subcategory":"Labor Organization",
            "type":"Services"
        }
    ],
    "sg:phone":"+1 905 317 3977",
    "sg:postcode":"L9A 1M1",
    "sg:province":"ON",
    "wof:name":"Ontario Public Svc Employees",
    "wof:placetype":"venue"
},
  "geometry": {"coordinates":[-79.87520599370001,43.2404899597],"type":"Point"}
}