{
  "type": "Feature",
  "properties": {
    "addr:full":"5166 Ladner Trunk Rd Delta BC V4K 1W3",
    "addr:housenumber":"5166",
    "addr:postcode":"v4k 1w3",
    "addr:street":"Ladner Trunk Rd",
    "iso:country":"CA",
    "sg:address":"5166 Ladner Trunk Rd",
    "sg:city":"Delta",
    "sg:classifiers":[
        {
            "category":"Restaurant",
            "type":"Food & Drink"
        }
    ],
    "sg:phone":"+1 604 940 0655",
    "sg:postcode":"V4K 1W3",
    "sg:province":"BC",
    "wof:name":"Little Caesars Pizza",
    "wof:placetype":"venue"
},
  "geometry": {"coordinates":[-123.079940796,49.0900840759],"type":"Point"}
}