{
  "type": "Feature",
  "properties": {
    "addr:full":"1651 Av Laurier E Montreal QC H2J 1J3",
    "addr:housenumber":"1651",
    "addr:postcode":"h2j 1j3",
    "addr:street":"Av Laurier E",
    "iso:country":"CA",
    "sg:address":"1651 Av Laurier E",
    "sg:city":"Montreal",
    "sg:classifiers":[
        {
            "category":"Food & Beverages",
            "subcategory":"Groceries & Convenience Stores",
            "type":"Retail Goods"
        }
    ],
    "sg:phone":"+1 514 522 6656",
    "sg:postcode":"H2J 1J3",
    "sg:province":"QC",
    "wof:name":"Depanneur oh",
    "wof:placetype":"venue"
},
  "geometry": {"coordinates":[-73.58205413819999,45.5354385376],"type":"Point"}
}