{
  "type": "Feature",
  "properties": {
    "iso:country":"CA",
    "sg:address":"9350 Yonge St",
    "sg:city":"Richmond Hill",
    "sg:classifiers":[
        {
            "category":"Restaurant",
            "type":"Food & Drink"
        }
    ],
    "sg:phone":"+1 905 883 1275",
    "sg:postcode":"L4C 5G2",
    "sg:province":"ON",
    "sg:tags":[
        "parcel",
        "gift",
        "ice",
        "parlor",
        "basket",
        "cream"
    ],
    "wof:name":"Laura Secord",
    "wof:placetype":"venue"
},
  "geometry": {"coordinates":[-79.433525,43.85442],"type":"Point"}
}