{
  "type": "Feature",
  "properties": {
    "iso:country":"CA",
    "sg:city":"Victoria",
    "sg:classifiers":[
        {
            "category":"Banks & Credit Unions",
            "subcategory":"Investment Brokerage",
            "type":"Services"
        }
    ],
    "sg:phone":"+1 250 405 2900",
    "sg:postcode":"V8W 2B7",
    "sg:province":"BC",
    "sg:tags":[
        "consultant",
        "planning",
        "financial"
    ],
    "wof:name":"Pacific International Sec Inc",
    "wof:placetype":"venue"
},
  "geometry": {"coordinates":[-123.36592102,48.4228591919],"type":"Point"}
}