{
  "type": "Feature",
  "properties": {
    "addr:full":"3700 Rue Queen Rawdon QC J0K 1S0",
    "addr:housenumber":"3700",
    "addr:postcode":"j0k 1s0",
    "addr:street":"Rue Queen",
    "iso:country":"CA",
    "sg:address":"3700 Rue Queen",
    "sg:city":"Rawdon",
    "sg:classifiers":[
        {
            "category":"Wholesale",
            "subcategory":"Farm Supplies",
            "type":"Manufacturing & Wholesale Goods"
        }
    ],
    "sg:phone":"+1 450 834 7015",
    "sg:postcode":"J0K 1S0",
    "sg:province":"QC",
    "sg:tags":[
        "feed"
    ],
    "wof:name":"Oiseaux DE ma Cour Boutique",
    "wof:placetype":"venue"
},
  "geometry": {"coordinates":[-73.708939,46.043892],"type":"Point"}
}