{
  "type": "Feature",
  "properties": {
    "addr:full":"Toronto ON M5A 3W7",
    "addr:postcode":"m5a 3w7",
    "iso:country":"CA",
    "sg:city":"Toronto",
    "sg:classifiers":[
        {
            "category":"Retail",
            "subcategory":"Laundry & Dry Cleaning",
            "type":"Services"
        }
    ],
    "sg:phone":"+1 416 923 9599",
    "sg:postcode":"M5A 3W7",
    "sg:province":"ON",
    "sg:tags":[
        "cleaners"
    ],
    "wof:name":"Sky Cleaners",
    "wof:placetype":"venue"
},
  "geometry": {"coordinates":[-79.375496,43.662811],"type":"Point"}
}