{
  "type": "Feature",
  "properties": {
    "iso:country":"CA",
    "sg:address":"25 Madison Ave N",
    "sg:city":"Kitchener",
    "sg:classifiers":[
        {
            "category":"Organizations",
            "subcategory":"Religious Organization",
            "type":"Services"
        }
    ],
    "sg:phone":"+1 519 576 8252",
    "sg:postcode":"N2H 2Z3",
    "sg:province":"ON",
    "sg:tags":[
        "church"
    ],
    "wof:name":"K W Open Bible Pentecostal",
    "wof:placetype":"venue"
},
  "geometry": {"coordinates":[-80.481468,43.44725],"type":"Point"}
}