{
  "type": "Feature",
  "properties": {
    "addr:full":"240 Huckins St Goderich ON N7A 4C6",
    "addr:housenumber":"240",
    "addr:postcode":"n7a 4c6",
    "addr:street":"Huckins St",
    "iso:country":"CA",
    "sg:address":"240 Huckins St",
    "sg:city":"Goderich",
    "sg:classifiers":[
        {
            "category":"Wholesale",
            "subcategory":"Machinery & Supplies",
            "type":"Manufacturing & Wholesale Goods"
        }
    ],
    "sg:phone":"+1 519 524 8328",
    "sg:postcode":"N7A 4C6",
    "sg:province":"ON",
    "sg:tags":[
        "contractor"
    ],
    "wof:name":"Champion Road Machinery Sales",
    "wof:placetype":"venue"
},
  "geometry": {"coordinates":[-81.70058400000001,43.726414],"type":"Point"}
}