{
  "type": "Feature",
  "properties": {
    "iso:country":"CA",
    "sg:address":"417 3E Rue",
    "sg:city":"Chibougamau",
    "sg:classifiers":[
        {
            "category":"Personal",
            "subcategory":"Beauty Salon",
            "type":"Services"
        }
    ],
    "sg:phone":"+1 418 748 2862",
    "sg:postcode":"G8P 1N6",
    "sg:province":"QC",
    "wof:name":"Salon DE Coiffure O oh LA LA",
    "wof:placetype":"venue"
},
  "geometry": {"coordinates":[-74.360489,49.91378],"type":"Point"}
}