{
  "type": "Feature",
  "properties": {
    "addr:full":"Victoria BC V9A 6Y2",
    "addr:postcode":"v9a 6y2",
    "iso:country":"CA",
    "sg:city":"Victoria",
    "sg:classifiers":[
        {
            "category":"Wholesale",
            "subcategory":"Scrap",
            "type":"Manufacturing & Wholesale Goods"
        }
    ],
    "sg:phone":"+1 250 381 0548",
    "sg:postcode":"V9A 6Y2",
    "sg:province":"BC",
    "sg:tags":[
        "recycling",
        "center"
    ],
    "wof:name":"Prism Hauling & Recycling",
    "wof:placetype":"venue"
},
  "geometry": {"coordinates":[-123.384567261,48.4431686401],"type":"Point"}
}