{
  "type": "Feature",
  "properties": {
    "addr:full":"77 Boul Baril O Princeville QC G6L 3V4",
    "addr:housenumber":"77",
    "addr:postcode":"g6l 3v4",
    "addr:street":"Boul Baril O",
    "iso:country":"CA",
    "sg:address":"77 Boul Baril O",
    "sg:city":"Princeville",
    "sg:classifiers":[
        {
            "category":"Restaurant",
            "type":"Food & Drink"
        }
    ],
    "sg:phone":"+1 819 364 5399",
    "sg:postcode":"G6L 3V4",
    "sg:province":"QC",
    "wof:name":"Restaurant Princess",
    "wof:placetype":"venue"
},
  "geometry": {"coordinates":[-71.871925,46.16832],"type":"Point"}
}