{
  "type": "Feature",
  "properties": {
    "addr:full":"Racine QC J0E 1Y0",
    "addr:postcode":"j0e 1y0",
    "iso:country":"CA",
    "sg:city":"Racine",
    "sg:classifiers":[
        {
            "category":"Wholesale",
            "subcategory":"Machinery & Supplies",
            "type":"Manufacturing & Wholesale Goods"
        }
    ],
    "sg:phone":"+1 450 532 2703",
    "sg:postcode":"J0E 1Y0",
    "sg:province":"QC",
    "sg:tags":[
        "farm",
        "equipment",
        "tractor"
    ],
    "wof:name":"Garage Pierre Paul Lussier",
    "wof:placetype":"venue"
},
  "geometry": {"coordinates":[-72.2462692261,45.5033874512],"type":"Point"}
}