{
  "type": "Feature",
  "properties": {
    "addr:full":"1224 John Street Rd Thunder Bay ON P7B 2A3",
    "addr:housenumber":"1224",
    "addr:postcode":"p7b 2a3",
    "addr:street":"John Street Rd",
    "iso:country":"CA",
    "sg:address":"1224 John Street Rd",
    "sg:city":"Thunder Bay",
    "sg:classifiers":[
        {
            "category":"Building & Trades",
            "subcategory":"Construction",
            "type":"Services"
        }
    ],
    "sg:phone":"+1 807 767 2557",
    "sg:postcode":"P7B 2A3",
    "sg:province":"ON",
    "sg:tags":[
        "concrete",
        "contractor"
    ],
    "wof:name":"Amerigo Construction",
    "wof:placetype":"venue"
},
  "geometry": {"coordinates":[-89.269814,48.444881],"type":"Point"}
}