{
  "type": "Feature",
  "properties": {
    "addr:full":"Pth 16 W Neepawa MB R0J 1H0",
    "addr:postcode":"r0j 1h0",
    "addr:street":"Pth 16 W",
    "iso:country":"CA",
    "sg:address":"Pth 16 W",
    "sg:city":"Neepawa",
    "sg:classifiers":[
        {
            "category":"Building & Trades",
            "subcategory":"Construction",
            "type":"Services"
        }
    ],
    "sg:phone":"+1 204 476 3590",
    "sg:postcode":"R0J 1H0",
    "sg:province":"MB",
    "sg:tags":[
        "maker",
        "cabinet"
    ],
    "wof:name":"Neepawa Country Cabinetry",
    "wof:placetype":"venue"
},
  "geometry": {"coordinates":[-99.46517900000001,50.226238],"type":"Point"}
}