{
  "type": "Feature",
  "properties": {
    "addr:full":"Matane QC G4W 1A1",
    "addr:postcode":"g4w 1a1",
    "iso:country":"CA",
    "sg:city":"Matane",
    "sg:classifiers":[
        {
            "category":"Real Estate",
            "subcategory":"Real Estate Agent",
            "type":"Services"
        }
    ],
    "sg:phone":"+1 418 562 1733",
    "sg:postcode":"G4W 1A1",
    "sg:province":"QC",
    "wof:name":"Gagne, Joanne",
    "wof:placetype":"venue"
},
  "geometry": {"coordinates":[-67.51839447019999,48.8525085449],"type":"Point"}
}