{
  "type": "Feature",
  "properties": {
    "addr:full":"Vanier QC G1M 3B1",
    "addr:postcode":"g1m 3b1",
    "iso:country":"CA",
    "sg:city":"Vanier",
    "sg:classifiers":[
        {
            "category":"Retail",
            "subcategory":"Car Wash",
            "type":"Services"
        }
    ],
    "sg:phone":"+1 418 681 4387",
    "sg:postcode":"G1M 3B1",
    "sg:province":"QC",
    "sg:tags":[
        "polishing",
        "washing"
    ],
    "wof:name":"Ross-Pro",
    "wof:placetype":"venue"
},
  "geometry": {"coordinates":[-71.282196,46.823635],"type":"Point"}
}