{
  "type": "Feature",
  "properties": {
    "addr:full":"Concord ON L4K 4K5",
    "addr:postcode":"l4k 4k5",
    "iso:country":"CA",
    "sg:city":"Concord",
    "sg:classifiers":[
        {
            "category":"Building & Trades",
            "subcategory":"Construction",
            "type":"Services"
        }
    ],
    "sg:phone":"+1 905 738 4000",
    "sg:postcode":"L4K 4K5",
    "sg:province":"ON",
    "sg:tags":[
        "excavating",
        "contractor"
    ],
    "wof:name":"Zetra Enterprises Inc",
    "wof:placetype":"venue"
},
  "geometry": {"coordinates":[-79.53323399999999,43.805523],"type":"Point"}
}