{
  "type": "Feature",
  "properties": {
    "addr:full":"1100 Boul Rene-Levesque O Montreal QC H3B 4N4",
    "addr:housenumber":"1100",
    "addr:postcode":"h3b 4n4",
    "addr:street":"Boul Rene-Levesque O",
    "iso:country":"CA",
    "sg:address":"1100 Boul Rene-Levesque O",
    "sg:city":"Montreal",
    "sg:classifiers":[
        {
            "category":"Restaurant",
            "type":"Food & Drink"
        }
    ],
    "sg:phone":"+1 514 398 9240",
    "sg:postcode":"H3B 4N4",
    "sg:province":"QC",
    "sg:tags":[
        "shop",
        "coffee"
    ],
    "wof:name":"Cafe Supreme",
    "wof:placetype":"venue"
},
  "geometry": {"coordinates":[-73.5546417236,45.5164451599],"type":"Point"}
}