{
  "type": "Feature",
  "properties": {
    "addr:full":"2750 Ch Sainte-Foy Sainte-Foy QC G1V 1V6",
    "addr:postcode":"2750;g1v 1v6",
    "addr:street":"Ch Sainte-Foy",
    "iso:country":"CA",
    "sg:address":"2750 Ch Sainte-Foy",
    "sg:city":"Sainte-Foy",
    "sg:classifiers":[
        {
            "category":"Restaurant",
            "type":"Food & Drink"
        }
    ],
    "sg:phone":"+1 418 658 6067",
    "sg:postcode":"G1V 1V6",
    "sg:province":"QC",
    "wof:name":"Restaurant Saint-Germain",
    "wof:placetype":"venue"
},
  "geometry": {"coordinates":[-71.2917633057,46.7692108154],"type":"Point"}
}