{
  "type": "Feature",
  "properties": {
    "addr:full":"3408 16 St SW Calgary AB T2T 6E5",
    "addr:housenumber":"3408",
    "addr:postcode":"t2t 6e5",
    "addr:street":"16 St Sw",
    "iso:country":"CA",
    "sg:address":"3408 16 St SW",
    "sg:city":"Calgary",
    "sg:classifiers":[
        {
            "category":"Professional",
            "subcategory":"Engineering",
            "type":"Services"
        }
    ],
    "sg:phone":"+1 403 270 8187",
    "sg:postcode":"T2T 6E5",
    "sg:province":"AB",
    "sg:tags":[
        "engineer"
    ],
    "wof:name":"R C Park Engineering Ltd",
    "wof:placetype":"venue"
},
  "geometry": {"coordinates":[-114.099449158,51.0238418579],"type":"Point"}
}