{
  "type": "Feature",
  "properties": {
    "addr:full":"999 Boul Saint-Laurent Montreal QC H2Z 1J4",
    "addr:housenumber":"999",
    "addr:postcode":"h2z 1j4",
    "addr:street":"Boul Saint-Laurent",
    "iso:country":"CA",
    "sg:address":"999 Boul Saint-Laurent",
    "sg:city":"Montreal",
    "sg:classifiers":[
        {
            "category":"Health Services",
            "subcategory":"Doctor",
            "type":"Services"
        }
    ],
    "sg:phone":"+1 514 871 8999",
    "sg:postcode":"H2Z 1J4",
    "sg:province":"QC",
    "sg:tags":[
        "clinic"
    ],
    "wof:name":"Centre Dentaire Metro Place",
    "wof:placetype":"venue"
},
  "geometry": {"coordinates":[-73.55907440190001,45.5078620911],"type":"Point"}
}