{
  "type": "Feature",
  "properties": {
    "addr:full":"1 Catharine St Belleville ON K8P 1K8",
    "addr:housenumber":"1",
    "addr:postcode":"k8p 1k8",
    "addr:street":"Catharine St",
    "iso:country":"CA",
    "sg:address":"1 Catharine St",
    "sg:city":"Belleville",
    "sg:classifiers":[
        {
            "category":"Utilities",
            "subcategory":"Telephone",
            "type":"Services"
        }
    ],
    "sg:phone":"+1 613 962 2500",
    "sg:postcode":"K8P 1K8",
    "sg:province":"ON",
    "sg:tags":[
        "company"
    ],
    "wof:name":"Quinte Long Distance Corp",
    "wof:placetype":"venue"
},
  "geometry": {"coordinates":[-77.38664199999999,44.165234],"type":"Point"}
}