{
  "type": "Feature",
  "properties": {
    "addr:full":"550 Boul Saint-Laurent E Louiseville QC J5V 2R5",
    "addr:housenumber":"550",
    "addr:postcode":"j5v 2r5",
    "addr:street":"Boul Saint-Laurent E",
    "iso:country":"CA",
    "sg:address":"550 Boul Saint-Laurent E",
    "sg:city":"Louiseville",
    "sg:classifiers":[
        {
            "category":"Shopping",
            "subcategory":"Department Store",
            "type":"Retail Goods"
        }
    ],
    "sg:phone":"+1 819 228 1661",
    "sg:postcode":"J5V 2R5",
    "sg:province":"QC",
    "wof:name":"Hart Store Inc",
    "wof:placetype":"venue"
},
  "geometry": {"coordinates":[-72.926315,46.256954],"type":"Point"}
}