{
  "type": "Feature",
  "properties": {
    "addr:full":"850 Rue Laudance Sainte-Foy QC G1X 4P1",
    "addr:housenumber":"850",
    "addr:postcode":"g1x 4p1",
    "addr:street":"Rue Laudance",
    "iso:country":"CA",
    "sg:address":"850 Rue Laudance",
    "sg:city":"Sainte-Foy",
    "sg:classifiers":[
        {
            "category":"Restaurant",
            "type":"Food & Drink"
        }
    ],
    "sg:phone":"+1 418 653 2592",
    "sg:postcode":"G1X 4P1",
    "sg:province":"QC",
    "wof:name":"Restaurant Laudance",
    "wof:placetype":"venue"
},
  "geometry": {"coordinates":[-71.33550262449999,46.7611961365],"type":"Point"}
}