{
  "type": "Feature",
  "properties": {
    "addr:full":"PO Box 358 STN Main Vegreville AB T9C 1R3",
    "addr:housenumber":"po",
    "addr:postcode":"t9c 1r3",
    "addr:street":"Box 358 Stn Main",
    "iso:country":"CA",
    "sg:address":"PO Box 358 STN Main",
    "sg:city":"Vegreville",
    "sg:classifiers":[
        {
            "category":"Retail",
            "subcategory":"Repair Shop",
            "type":"Services"
        }
    ],
    "sg:phone":"+1 780 632 4876",
    "sg:postcode":"T9C 1R3",
    "sg:province":"AB",
    "sg:tags":[
        "lock",
        "locksmith"
    ],
    "wof:name":"Tim's Locksmithing",
    "wof:placetype":"venue"
},
  "geometry": {"coordinates":[-112.054199219,53.4952774048],"type":"Point"}
}