{
  "type": "Feature",
  "properties": {
    "addr:full":"257 Rue Notre-Dame E Victoriaville QC G6P 4A2",
    "addr:housenumber":"257",
    "addr:postcode":"g6p 4a2",
    "addr:street":"Rue Notre-Dame E",
    "iso:country":"CA",
    "sg:address":"257 Rue Notre-Dame E",
    "sg:city":"Victoriaville",
    "sg:classifiers":[
        {
            "category":"Shopping",
            "subcategory":"Used Merchandise",
            "type":"Retail Goods"
        }
    ],
    "sg:phone":"+1 819 752 9186",
    "sg:postcode":"G6P 4A2",
    "sg:province":"QC",
    "sg:tags":[
        "clothing"
    ],
    "wof:name":"Friperie Chic",
    "wof:placetype":"venue"
},
  "geometry": {"coordinates":[-71.9520950317,46.0577354431],"type":"Point"}
}