{
  "type": "Feature",
  "properties": {
    "iso:country":"CA",
    "sg:address":"17 Newfoundland Walk",
    "sg:city":"Elliot Lake",
    "sg:classifiers":[
        {
            "category":"Shopping",
            "subcategory":"Computers & Home Electronics",
            "type":"Retail Goods"
        }
    ],
    "sg:phone":"+1 705 848 2366",
    "sg:postcode":"P5A 1Z5",
    "sg:province":"ON",
    "sg:tags":[
        "radio",
        "television",
        "electronic",
        "equipment"
    ],
    "wof:name":"Superior Audio & Video",
    "wof:placetype":"venue"
},
  "geometry": {"coordinates":[-82.6457290649,46.3830833435],"type":"Point"}
}