{
  "type": "Feature",
  "properties": {
    "addr:full":"1364 King St N St Jacobs ON N0B 2N0",
    "addr:housenumber":"1364",
    "addr:postcode":"n0b 2n0",
    "addr:street":"King St N St",
    "iso:country":"CA",
    "sg:address":"1364 King St N",
    "sg:city":"St Jacobs",
    "sg:classifiers":[
        {
            "category":"Shopping",
            "subcategory":"Gifts & Souvenirs",
            "type":"Retail Goods"
        }
    ],
    "sg:phone":"+1 519 664 3275",
    "sg:postcode":"N0B 2N0",
    "sg:province":"ON",
    "sg:tags":[
        "shop"
    ],
    "wof:name":"Creme Decor",
    "wof:placetype":"venue"
},
  "geometry": {"coordinates":[-80.553726,43.537334],"type":"Point"}
}