{
  "type": "Feature",
  "properties": {
    "addr:full":"6123 Norfolk Dr NW Calgary AB T2K 5J8",
    "addr:housenumber":"6123",
    "addr:postcode":"t2k 5j8",
    "addr:street":"Norfolk Dr Nw",
    "iso:country":"CA",
    "sg:address":"6123 Norfolk Dr NW",
    "sg:city":"Calgary",
    "sg:classifiers":[
        {
            "category":"Professional",
            "subcategory":"Accounting & Tax Preparation",
            "type":"Services"
        }
    ],
    "sg:phone":"+1 403 295 2950",
    "sg:postcode":"T2K 5J8",
    "sg:province":"AB",
    "sg:tags":[
        "accountant"
    ],
    "wof:name":"B Robinson Accounting",
    "wof:placetype":"venue"
},
  "geometry": {"coordinates":[-114.07795,51.108448],"type":"Point"}
}