{
  "type": "Feature",
  "properties": {
    "addr:full":"19 Newberry St Belleville ON K8N 3N2",
    "addr:housenumber":"19",
    "addr:postcode":"k8n 3n2",
    "addr:street":"Newberry St",
    "iso:country":"CA",
    "sg:address":"19 Newberry St",
    "sg:city":"Belleville",
    "sg:classifiers":[
        {
            "category":"Home & Garden",
            "subcategory":"Building Materials",
            "type":"Retail Goods"
        }
    ],
    "sg:phone":"+1 613 967 1992",
    "sg:postcode":"K8N 3N2",
    "sg:province":"ON",
    "wof:name":"Peacock Building Supplies",
    "wof:placetype":"venue"
},
  "geometry": {"coordinates":[-77.37222300000001,44.161278],"type":"Point"}
}