{
  "type": "Feature",
  "properties": {
    "iso:country":"CA",
    "sg:address":"171 Chain Lake Dr",
    "sg:city":"Halifax",
    "sg:classifiers":[
        {
            "category":"Real Estate",
            "subcategory":"Real Estate Operator",
            "type":"Services"
        }
    ],
    "sg:phone":"+1 902 450 5641",
    "sg:postcode":"B3S 1B3",
    "sg:province":"NS",
    "sg:tags":[
        "apartment"
    ],
    "wof:name":"Rosno Management & Leasing",
    "wof:placetype":"venue"
},
  "geometry": {"coordinates":[-63.6710357666,44.6456756592],"type":"Point"}
}