{
  "type": "Feature",
  "properties": {
    "iso:country":"CA",
    "sg:address":"3755 3rd Ave",
    "sg:city":"Port Alberni",
    "sg:classifiers":[
        {
            "category":"Travel",
            "subcategory":"Hotels & Motels",
            "type":"Entertainment"
        }
    ],
    "sg:phone":"+1 250 723 1153",
    "sg:postcode":"V9Y 4E9",
    "sg:province":"BC",
    "wof:name":"Bluebird Motel",
    "wof:placetype":"venue"
},
  "geometry": {"coordinates":[-124.80728149399999,49.2444419861],"type":"Point"}
}