{
  "type": "Feature",
  "properties": {
    "addr:full":"109 Domville Arthur ON N0G 1A0",
    "addr:housenumber":"109",
    "addr:postcode":"n0g 1a0",
    "addr:street":"Domville Arthur",
    "iso:country":"CA",
    "sg:address":"109 Domville",
    "sg:city":"Arthur",
    "sg:classifiers":[
        {
            "category":"Wholesale",
            "subcategory":"Farm Supplies",
            "type":"Manufacturing & Wholesale Goods"
        }
    ],
    "sg:phone":"+1 519 848 3038",
    "sg:postcode":"N0G 1A0",
    "sg:province":"ON",
    "sg:tags":[
        "feed"
    ],
    "wof:name":"Ronald Mc Dougall Hay & Straw",
    "wof:placetype":"venue"
},
  "geometry": {"coordinates":[-80.533691,43.836071],"type":"Point"}
}