{
  "type": "Feature",
  "properties": {
    "addr:full":"954 19 St SW Medicine Hat AB T1A 7X1",
    "addr:housenumber":"19",
    "addr:postcode":"t1a 7x1",
    "addr:street":"954;St Sw",
    "iso:country":"CA",
    "sg:address":"954 19 St SW",
    "sg:city":"Medicine Hat",
    "sg:classifiers":[
        {
            "category":"Building & Trades",
            "subcategory":"Electrical",
            "type":"Services"
        }
    ],
    "sg:phone":"+1 403 528 9809",
    "sg:postcode":"T1A 7X1",
    "sg:province":"AB",
    "sg:tags":[
        "electric",
        "contractor"
    ],
    "wof:name":"Elhart's Electric",
    "wof:placetype":"venue"
},
  "geometry": {"coordinates":[-110.708641,50.021759],"type":"Point"}
}