{
  "type": "Feature",
  "properties": {
    "addr:full":"1198 Davie St Vancouver BC V6E 1N1",
    "addr:housenumber":"1198",
    "addr:postcode":"v6e 1n1",
    "addr:street":"Davie St",
    "iso:country":"CA",
    "sg:address":"1198 Davie St",
    "sg:city":"Vancouver",
    "sg:classifiers":[
        {
            "category":"Restaurant",
            "type":"Food & Drink"
        }
    ],
    "sg:phone":"+1 604 633 9333",
    "sg:postcode":"V6E 1N1",
    "sg:province":"BC",
    "wof:name":"White Spot Triple O's",
    "wof:placetype":"venue"
},
  "geometry": {"coordinates":[-123.133301,49.281551],"type":"Point"}
}