{
  "type": "Feature",
  "properties": {
    "iso:country":"CA",
    "sg:address":"607 2nd Ave W",
    "sg:city":"Prince Rupert",
    "sg:classifiers":[
        {
            "category":"Professional",
            "subcategory":"Secretarial Services",
            "type":"Services"
        }
    ],
    "sg:phone":"+1 250 624 4475",
    "sg:postcode":"V8J 1H1",
    "sg:province":"BC",
    "sg:tags":[
        "employment",
        "reporting",
        "court",
        "agency",
        "opportunity"
    ],
    "wof:name":"Northwest Employment Svc",
    "wof:placetype":"venue"
},
  "geometry": {"coordinates":[-130.327682495,54.3119926453],"type":"Point"}
}