{
  "type": "Feature",
  "properties": {
    "addr:full":"139 Ch Musie Loop Chelsea QC J9B 1Y6",
    "addr:housenumber":"139",
    "addr:postcode":"qc j9b 1y6",
    "addr:street":"Ch Musie Loop",
    "iso:country":"CA",
    "sg:address":"139 Ch Musie Loop",
    "sg:city":"Chelsea",
    "sg:classifiers":[
        {
            "category":"Manufacturing",
            "subcategory":"Printing",
            "type":"Manufacturing & Wholesale Goods"
        }
    ],
    "sg:phone":"+1 819 827 3000",
    "sg:postcode":"J9B 1Y6",
    "sg:province":"QC",
    "sg:tags":[
        "publisher"
    ],
    "wof:name":"Clarence Byrd Inc",
    "wof:placetype":"venue"
},
  "geometry": {"coordinates":[-75.824448,45.536304],"type":"Point"}
}