{
  "type": "Feature",
  "properties": {
    "addr:full":"1111 Stellar Dr Newmarket ON L3Y 7B8",
    "addr:housenumber":"1111",
    "addr:postcode":"l3y 7b8",
    "addr:street":"Stellar Dr",
    "iso:country":"CA",
    "sg:address":"1111 Stellar Dr",
    "sg:city":"Newmarket",
    "sg:classifiers":[
        {
            "category":"Health Services",
            "subcategory":"Health Practitioner",
            "type":"Services"
        }
    ],
    "sg:phone":"+1 905 473 7218",
    "sg:postcode":"L3Y 7B8",
    "sg:province":"ON",
    "sg:tags":[
        "psychologist"
    ],
    "wof:name":"Jackson Leadership Systems",
    "wof:placetype":"venue"
},
  "geometry": {"coordinates":[-79.4316864014,44.0767364502],"type":"Point"}
}