{
  "type": "Feature",
  "properties": {
    "addr:full":"4930 Sully Rd Gores Landing ON K0K 2E0",
    "addr:housenumber":"4930",
    "addr:postcode":"k0k 2e0",
    "addr:street":"Sully Rd",
    "iso:country":"CA",
    "sg:address":"4930 Sully Rd",
    "sg:city":"Gores Landing",
    "sg:classifiers":[
        {
            "category":"Home & Garden",
            "subcategory":"Garden Supply",
            "type":"Retail Goods"
        }
    ],
    "sg:phone":"+1 905 342 2537",
    "sg:postcode":"K0K 2E0",
    "sg:province":"ON",
    "sg:tags":[
        "nurseryman"
    ],
    "wof:name":"Viking Nursery Ltd",
    "wof:placetype":"venue"
},
  "geometry": {"coordinates":[-78.23249053959999,44.1192054749],"type":"Point"}
}