{
  "type": "Feature",
  "properties": {
    "addr:full":"Toronto ON M4W 1A5",
    "addr:postcode":"m4w 1a5",
    "iso:country":"CA",
    "sg:city":"Toronto",
    "sg:classifiers":[
        {
            "category":"Professional",
            "subcategory":"Employment Agencies",
            "type":"Services"
        }
    ],
    "sg:phone":"+1 416 922 7777",
    "sg:postcode":"M4W 1A5",
    "sg:province":"ON",
    "sg:tags":[
        "opportunity"
    ],
    "wof:name":"Griffin Sproston Employment",
    "wof:placetype":"venue"
},
  "geometry": {"coordinates":[-79.38867999999999,43.669685],"type":"Point"}
}