{
  "type": "Feature",
  "properties": {
    "iso:country":"CA",
    "sg:address":"460 Parkdale Ave N",
    "sg:city":"Hamilton",
    "sg:classifiers":[
        {
            "category":"Organizations",
            "subcategory":"Labor Organization",
            "type":"Services"
        }
    ],
    "sg:phone":"+1 905 547 3231",
    "sg:postcode":"L8H 5Y2",
    "sg:province":"ON",
    "wof:name":"Teamsters",
    "wof:placetype":"venue"
},
  "geometry": {"coordinates":[-79.78647613530001,43.2492446899],"type":"Point"}
}