{
  "type": "Feature",
  "properties": {
    "iso:country":"CA",
    "sg:address":"111 Macnab St",
    "sg:city":"Strathroy",
    "sg:classifiers":[
        {
            "category":"Building & Trades",
            "subcategory":"Construction",
            "type":"Services"
        }
    ],
    "sg:phone":"+1 519 245 6100",
    "sg:postcode":"N7G 4J6",
    "sg:province":"ON",
    "sg:tags":[
        "elevator"
    ],
    "wof:name":"Dover Corp",
    "wof:placetype":"venue"
},
  "geometry": {"coordinates":[-81.6114273071,42.9608078003],"type":"Point"}
}