{
  "type": "Feature",
  "properties": {
    "iso:country":"CA",
    "sg:address":"875 Notre Dame Ave",
    "sg:city":"Sudbury",
    "sg:classifiers":[
        {
            "category":"Retail",
            "subcategory":"Auto Repair",
            "type":"Services"
        }
    ],
    "sg:phone":"+1 705 566 5603",
    "sg:postcode":"P3A 2T2",
    "sg:province":"ON",
    "sg:tags":[
        "repairing",
        "automobile"
    ],
    "wof:name":"A True Value Automotive",
    "wof:placetype":"venue"
},
  "geometry": {"coordinates":[-80.9856796265,46.5137252808],"type":"Point"}
}