{
  "type": "Feature",
  "properties": {
    "addr:full":"121 Big Bay Point Rd Barrie ON L4N 8M5",
    "addr:housenumber":"121",
    "addr:postcode":"l4n 8m5",
    "addr:street":"Big Bay Point Rd",
    "iso:country":"CA",
    "sg:address":"121 Big Bay Point Rd",
    "sg:city":"Barrie",
    "sg:classifiers":[
        {
            "category":"Freight",
            "type":"Transportation"
        }
    ],
    "sg:phone":"+1 705 727 9293",
    "sg:postcode":"L4N 8M5",
    "sg:province":"ON",
    "sg:tags":[
        "commercial",
        "storage"
    ],
    "wof:name":"Barrie Southend Public Storage",
    "wof:placetype":"venue"
},
  "geometry": {"coordinates":[-79.676247,44.350506],"type":"Point"}
}