{
  "type": "Feature",
  "properties": {
    "iso:country":"CA",
    "sg:city":"Scarborough",
    "sg:classifiers":[
        {
            "category":"Professional",
            "subcategory":"Lawyer & Legal Services",
            "type":"Services"
        }
    ],
    "sg:phone":"+1 416 335 8830",
    "sg:postcode":"M1S 5H6",
    "sg:province":"ON",
    "sg:tags":[
        "attorney"
    ],
    "wof:name":"Lee, Jack F S",
    "wof:placetype":"venue"
},
  "geometry": {"coordinates":[-79.28815460209999,43.8034858704],"type":"Point"}
}