{
  "type": "Feature",
  "properties": {
    "addr:full":"10 Rue Beaumont Saint-Charles-Borromee QC J6E 7K7",
    "addr:housenumber":"10",
    "addr:postcode":"j6e 7k7",
    "addr:street":"Rue Beaumont Saint-Charles-Borromee",
    "iso:country":"CA",
    "sg:address":"10 Rue Beaumont",
    "sg:city":"Saint-Charles-Borromee",
    "sg:classifiers":[
        {
            "category":"Professional",
            "subcategory":"Engineering",
            "type":"Services"
        }
    ],
    "sg:phone":"+1 450 760 9001",
    "sg:postcode":"J6E 7K7",
    "sg:province":"QC",
    "sg:tags":[
        "engineer"
    ],
    "wof:name":"Cla Experts Conseils Inc",
    "wof:placetype":"venue"
},
  "geometry": {"coordinates":[-73.4603347778,46.0539894104],"type":"Point"}
}