{
  "type": "Feature",
  "properties": {
    "addr:full":"1565 Niakwa Rd E Winnipeg MB R2J 3T3",
    "addr:housenumber":"1565",
    "addr:postcode":"r2j 3t3",
    "addr:street":"Niakwa Rd E",
    "iso:country":"CA",
    "sg:address":"1565 Niakwa Rd E",
    "sg:city":"Winnipeg",
    "sg:classifiers":[
        {
            "category":"Recreation",
            "type":"Entertainment"
        }
    ],
    "sg:phone":"+1 204 257 8130",
    "sg:postcode":"R2J 3T3",
    "sg:province":"MB",
    "sg:tags":[
        "range",
        "practice",
        "golf"
    ],
    "wof:name":"Golf-Land Driving Range",
    "wof:placetype":"venue"
},
  "geometry": {"coordinates":[-97.0364,49.856438],"type":"Point"}
}