{
  "type": "Feature",
  "properties": {
    "addr:full":"71 Principale N # 819 Notre-Dame-Du-Nord QC J0Z 3B0",
    "addr:housenumber":"71",
    "addr:postcode":"j0z 3b0",
    "addr:street":"Principale N # 819",
    "iso:country":"CA",
    "sg:address":"71 Principale N # 819",
    "sg:city":"Notre-Dame-Du-Nord",
    "sg:classifiers":[
        {
            "category":"Government",
            "subcategory":"Office",
            "type":"Public Place"
        }
    ],
    "sg:phone":"+1 819 723 2294",
    "sg:postcode":"J0Z 3B0",
    "sg:province":"QC",
    "sg:tags":[
        "village"
    ],
    "wof:name":"Corp Municipale DE Notre-Dame",
    "wof:placetype":"venue"
},
  "geometry": {"coordinates":[-79.48226200000001,47.597275],"type":"Point"}
}