{
  "type": "Feature",
  "properties": {
    "addr:full":"469 Rue Sacre-Coeur O Alma QC G8B 1M4",
    "addr:housenumber":"469",
    "addr:postcode":"g8b 1m4",
    "addr:street":"Rue Sacre-Coeur O",
    "iso:country":"CA",
    "sg:address":"469 Rue Sacre-Coeur O",
    "sg:city":"Alma",
    "sg:classifiers":[
        {
            "category":"Real Estate",
            "subcategory":"Surveying",
            "type":"Services"
        }
    ],
    "sg:phone":"+1 418 662 7329",
    "sg:postcode":"G8B 1M4",
    "sg:province":"QC",
    "sg:tags":[
        "surveyor"
    ],
    "wof:name":"Arpenteurs Geometres Tremblay",
    "wof:placetype":"venue"
},
  "geometry": {"coordinates":[-71.63331599999999,48.543865],"type":"Point"}
}