{
  "type": "Feature",
  "properties": {
    "addr:full":"655 60E Rue E Charlesbourg QC G1H 2C3",
    "addr:housenumber":"655",
    "addr:postcode":"g1h 2c3",
    "addr:street":"60E Rue E",
    "iso:country":"CA",
    "sg:address":"655 60E Rue E",
    "sg:city":"Charlesbourg",
    "sg:classifiers":[
        {
            "category":"Health Services",
            "subcategory":"Optometrist",
            "type":"Services"
        }
    ],
    "sg:phone":"+1 418 563 7731",
    "sg:postcode":"G1H 2C3",
    "sg:province":"QC",
    "sg:tags":[
        "lawn",
        "maintenance",
        "grounds"
    ],
    "wof:name":"Fleuri-Vert Vision",
    "wof:placetype":"venue"
},
  "geometry": {"coordinates":[-71.25131988530001,46.8456497192],"type":"Point"}
}