{
  "type": "Feature",
  "properties": {
    "iso:country":"CA",
    "sg:address":"6058 Quinpool Rd",
    "sg:city":"Halifax",
    "sg:classifiers":[
        {
            "category":"Shopping",
            "subcategory":"Clothing, Apparel, & Fashions",
            "type":"Retail Goods"
        }
    ],
    "sg:phone":"+1 902 422 4252",
    "sg:postcode":"B3L 1A1",
    "sg:province":"NS",
    "sg:tags":[
        "tailor"
    ],
    "wof:name":"Chung's Custom Tailor",
    "wof:placetype":"venue"
},
  "geometry": {"coordinates":[-63.5923461914,44.6466255188],"type":"Point"}
}