{
  "type": "Feature",
  "properties": {
    "addr:full":"84 King St E Gananoque ON K7G 1G1",
    "addr:housenumber":"84",
    "addr:postcode":"k7g 1g1",
    "addr:street":"King St E",
    "iso:country":"CA",
    "sg:address":"84 King St E",
    "sg:city":"Gananoque",
    "sg:classifiers":[
        {
            "category":"Shopping",
            "subcategory":"Clothing, Apparel, & Fashions",
            "type":"Retail Goods"
        }
    ],
    "sg:phone":"+1 613 382 3823",
    "sg:postcode":"K7G 1G1",
    "sg:province":"ON",
    "wof:name":"R J Deir & Sons Ltd",
    "wof:placetype":"venue"
},
  "geometry": {"coordinates":[-76.16306299999999,44.329426],"type":"Point"}
}