{
  "type": "Feature",
  "properties": {
    "addr:full":"530 Premier Rd Drumheller AB T0J 0Y0",
    "addr:housenumber":"530",
    "addr:postcode":"t0j 0y0",
    "addr:street":"Premier Rd",
    "iso:country":"CA",
    "sg:address":"530 Premier Rd",
    "sg:city":"Drumheller",
    "sg:classifiers":[
        {
            "category":"Manufacturing",
            "subcategory":"Tools & Machinery",
            "type":"Manufacturing & Wholesale Goods"
        }
    ],
    "sg:phone":"+1 403 823 6828",
    "sg:postcode":"T0J 0Y0",
    "sg:province":"AB",
    "sg:tags":[
        "machine",
        "shop",
        "welding"
    ],
    "wof:name":"H B Industries Ltd",
    "wof:placetype":"venue"
},
  "geometry": {"coordinates":[-112.728302,51.460979],"type":"Point"}
}