{
  "type": "Feature",
  "properties": {
    "addr:full":"839 Yonge St Toronto ON M4W 2H2",
    "addr:housenumber":"839",
    "addr:postcode":"m4w 2h2",
    "addr:street":"Yonge St",
    "iso:country":"CA",
    "sg:address":"839 Yonge St",
    "sg:city":"Toronto",
    "sg:classifiers":[
        {
            "category":"Retail",
            "subcategory":"Auto Repair",
            "type":"Services"
        }
    ],
    "sg:phone":"+1 416 925 9592",
    "sg:postcode":"M4W 2H2",
    "sg:province":"ON",
    "sg:tags":[
        "repairing",
        "automobile"
    ],
    "wof:name":"Canadian Tire",
    "wof:placetype":"venue"
},
  "geometry": {"coordinates":[-79.38780199999999,43.67321],"type":"Point"}
}