{
  "type": "Feature",
  "properties": {
    "addr:full":"Richmond BC V7B 1C3",
    "addr:postcode":"v7b 1c3",
    "iso:country":"CA",
    "sg:city":"Richmond",
    "sg:classifiers":[
        {
            "category":"Professional",
            "subcategory":"Management & Consulting",
            "type":"Services"
        }
    ],
    "sg:phone":"+1 604 276 6060",
    "sg:postcode":"V7B 1C3",
    "sg:province":"BC",
    "sg:tags":[
        "consultant",
        "business"
    ],
    "wof:name":"Yvr Airport Svc Ltd",
    "wof:placetype":"venue"
},
  "geometry": {"coordinates":[-123.142082,49.19067],"type":"Point"}
}