{
  "type": "Feature",
  "properties": {
    "addr:full":"1444 Lorne St Regina SK S4R 2K4",
    "addr:housenumber":"1444",
    "addr:postcode":"s4r 2k4",
    "addr:street":"Lorne St",
    "iso:country":"CA",
    "sg:address":"1444 Lorne St",
    "sg:city":"Regina",
    "sg:classifiers":[
        {
            "category":"Wholesale",
            "subcategory":"Medical Equipment & Supplies",
            "type":"Manufacturing & Wholesale Goods"
        }
    ],
    "sg:phone":"+1 306 791 9840",
    "sg:postcode":"S4R 2K4",
    "sg:province":"SK",
    "sg:tags":[
        "physician",
        "surgeon",
        "care",
        "health",
        "home"
    ],
    "wof:name":"Automobility Medical",
    "wof:placetype":"venue"
},
  "geometry": {"coordinates":[-104.61393,50.455997],"type":"Point"}
}