{
  "type": "Feature",
  "properties": {
    "addr:full":"2425 Eglinton Ave W York ON M6M 1S8",
    "addr:housenumber":"2425",
    "addr:postcode":"m6m 1s8",
    "addr:street":"Eglinton Ave W",
    "iso:country":"CA",
    "sg:address":"2425 Eglinton Ave W",
    "sg:city":"York",
    "sg:classifiers":[
        {
            "category":"Utilities",
            "subcategory":"Mobile Phone",
            "type":"Services"
        }
    ],
    "sg:phone":"+1 416 658 3145",
    "sg:postcode":"M6M 1S8",
    "sg:province":"ON",
    "sg:tags":[
        "equipment",
        "paging",
        "signaling",
        "system"
    ],
    "wof:name":"Pro Mobility Inc",
    "wof:placetype":"venue"
},
  "geometry": {"coordinates":[-79.46617126460001,43.6917076111],"type":"Point"}
}