{
  "type": "Feature",
  "properties": {
    "addr:full":"Calgary AB T2A 6K1",
    "addr:postcode":"t2a 6k1",
    "iso:country":"CA",
    "sg:city":"Calgary",
    "sg:classifiers":[
        {
            "category":"Home & Garden",
            "subcategory":"Building Materials",
            "type":"Retail Goods"
        }
    ],
    "sg:phone":"+1 403 273 0085",
    "sg:postcode":"T2A 6K1",
    "sg:province":"AB",
    "sg:tags":[
        "glass",
        "window",
        "plate"
    ],
    "wof:name":"Pay-Less Auto & Window Glass",
    "wof:placetype":"venue"
},
  "geometry": {"coordinates":[-113.99316406200001,51.0606422424],"type":"Point"}
}