{
  "type": "Feature",
  "properties": {
    "addr:full":"46 Harrington Cres North York ON M2M 2Y5",
    "addr:housenumber":"46",
    "addr:postcode":"m2m 2y5",
    "addr:street":"Harrington Cres",
    "iso:country":"CA",
    "sg:address":"46 Harrington Cres",
    "sg:city":"North York",
    "sg:classifiers":[
        {
            "category":"Wholesale",
            "subcategory":"Machinery & Supplies",
            "type":"Manufacturing & Wholesale Goods"
        }
    ],
    "sg:phone":"+1 416 591 5494",
    "sg:postcode":"M2M 2Y5",
    "sg:province":"ON",
    "sg:tags":[
        "pulverizing",
        "crushing"
    ],
    "wof:name":"General Comminution",
    "wof:placetype":"venue"
},
  "geometry": {"coordinates":[-79.3817443848,43.8030433655],"type":"Point"}
}