{
  "type": "Feature",
  "properties": {
    "addr:full":"108 Main St SE Falher AB T0H 1M0",
    "addr:housenumber":"108",
    "addr:postcode":"t0h 1m0",
    "addr:street":"Main St Se",
    "iso:country":"CA",
    "sg:address":"108 Main St SE",
    "sg:city":"Falher",
    "sg:classifiers":[
        {
            "category":"Food & Beverages",
            "subcategory":"Groceries & Convenience Stores",
            "type":"Retail Goods"
        }
    ],
    "sg:phone":"+1 780 837 2261",
    "sg:postcode":"T0H 1M0",
    "sg:province":"AB",
    "sg:tags":[
        "grocer"
    ],
    "wof:name":"Falher & District CO-OP Assn",
    "wof:placetype":"venue"
},
  "geometry": {"coordinates":[-117.20169799999999,55.736328],"type":"Point"}
}