{
  "type": "Feature",
  "properties": {
    "addr:full":"220 Spring Valley Rd Kitchener ON N2H 5X8",
    "addr:housenumber":"220",
    "addr:postcode":"n2h 5x8",
    "addr:street":"Spring Valley Rd",
    "iso:country":"CA",
    "sg:address":"220 Spring Valley Rd",
    "sg:city":"Kitchener",
    "sg:classifiers":[
        {
            "category":"Building & Trades",
            "subcategory":"Cleaning & Sanitation",
            "type":"Services"
        }
    ],
    "sg:phone":"+1 519 578 0200",
    "sg:postcode":"N2H 5X8",
    "sg:province":"ON",
    "sg:tags":[
        "ventilating",
        "system"
    ],
    "wof:name":"Ddk Duct Cleaning",
    "wof:placetype":"venue"
},
  "geometry": {"coordinates":[-80.47599,43.466877],"type":"Point"}
}