{
  "type": "Feature",
  "properties": {
    "iso:country":"CA",
    "sg:city":"Guelph",
    "sg:classifiers":[
        {
            "category":"Real Estate",
            "subcategory":"Real Estate Operator",
            "type":"Services"
        }
    ],
    "sg:phone":"+1 519 766 4316",
    "sg:postcode":"N1H 6Y2",
    "sg:province":"ON",
    "sg:tags":[
        "apartment"
    ],
    "wof:name":"Upbuilding Non Profit Homes",
    "wof:placetype":"venue"
},
  "geometry": {"coordinates":[-80.26997375489999,43.5177612305],"type":"Point"}
}