{
  "type": "Feature",
  "properties": {
    "addr:full":"9565 Northlawn Terr Sidney BC V8L 2S4",
    "addr:housenumber":"9565",
    "addr:postcode":"v8l 2s4",
    "addr:street":"Northlawn Terr",
    "iso:country":"CA",
    "sg:address":"9565 Northlawn Terr",
    "sg:city":"Sidney",
    "sg:classifiers":[
        {
            "category":"Wholesale",
            "subcategory":"Construction Materials",
            "type":"Manufacturing & Wholesale Goods"
        }
    ],
    "sg:phone":"+1 250 656 0006",
    "sg:postcode":"V8L 2S4",
    "sg:province":"BC",
    "sg:tags":[
        "sand",
        "gravel"
    ],
    "wof:name":"Ash Equipment",
    "wof:placetype":"venue"
},
  "geometry": {"coordinates":[-123.404258728,48.6418914795],"type":"Point"}
}