{
  "type": "Feature",
  "properties": {
    "iso:country":"CA",
    "sg:address":"RR 2",
    "sg:city":"Puslinch",
    "sg:classifiers":[
        {
            "category":"Manufacturing",
            "subcategory":"Tools & Machinery",
            "type":"Manufacturing & Wholesale Goods"
        }
    ],
    "sg:phone":"+1 519 623 6663",
    "sg:postcode":"N0B 2J0",
    "sg:province":"ON",
    "sg:tags":[
        "machine",
        "shop"
    ],
    "wof:name":"True Turn Machining",
    "wof:placetype":"venue"
},
  "geometry": {"coordinates":[-80.162613,43.467278],"type":"Point"}
}