{
  "type": "Feature",
  "properties": {
    "addr:full":"90 Chapple Ave Sault Ste Marie ON P6B 3N9",
    "addr:housenumber":"90",
    "addr:postcode":"p6b 3n9",
    "addr:street":"Chapple Ave",
    "iso:country":"CA",
    "sg:address":"90 Chapple Ave",
    "sg:city":"Sault Ste Marie",
    "sg:classifiers":[
        {
            "category":"Education",
            "subcategory":"School",
            "type":"Public Place"
        }
    ],
    "sg:phone":"+1 705 945 7149",
    "sg:postcode":"P6B 3N9",
    "sg:province":"ON",
    "wof:name":"Rosedale Elementary School",
    "wof:placetype":"venue"
},
  "geometry": {"coordinates":[-84.31131744379999,46.5240745544],"type":"Point"}
}