{
  "type": "Feature",
  "properties": {
    "addr:full":"1461 Pelham St Fonthill ON L0S 1E0",
    "addr:housenumber":"1461",
    "addr:postcode":"l0s 1e0",
    "addr:street":"Pelham St",
    "iso:country":"CA",
    "sg:address":"1461 Pelham St",
    "sg:city":"Fonthill",
    "sg:classifiers":[
        {
            "category":"Banks & Credit Unions",
            "subcategory":"Bank",
            "type":"Services"
        }
    ],
    "sg:phone":"+1 905 892 5738",
    "sg:postcode":"L0S 1E0",
    "sg:province":"ON",
    "wof:name":"Cibc",
    "wof:placetype":"venue"
},
  "geometry": {"coordinates":[-79.285225,43.044823],"type":"Point"}
}