{
  "type": "Feature",
  "properties": {
    "addr:full":"Waterloo ON N2K 3P9",
    "addr:postcode":"n2k 3p9",
    "iso:country":"CA",
    "sg:city":"Waterloo",
    "sg:classifiers":[
        {
            "category":"Health Services",
            "subcategory":"Doctor",
            "type":"Services"
        }
    ],
    "sg:phone":"+1 519 886 2643",
    "sg:postcode":"N2K 3P9",
    "sg:province":"ON",
    "sg:tags":[
        "physician",
        "surgeon"
    ],
    "wof:name":"Arya, Neil MD",
    "wof:placetype":"venue"
},
  "geometry": {"coordinates":[-80.525871,43.50462],"type":"Point"}
}