{
  "type": "Feature",
  "properties": {
    "addr:full":"100 2nd St S Souris MB R0K 2C0",
    "addr:housenumber":"100",
    "addr:postcode":"r0k 2c0",
    "addr:street":"2Nd St S",
    "iso:country":"CA",
    "sg:address":"100 2nd St S",
    "sg:city":"Souris",
    "sg:classifiers":[
        {
            "category":"Government",
            "subcategory":"Office",
            "type":"Public Place"
        }
    ],
    "sg:phone":"+1 204 483 5080",
    "sg:postcode":"R0K 2C0",
    "sg:province":"MB",
    "wof:name":"Manitoba Intergovernment Afrs",
    "wof:placetype":"venue"
},
  "geometry": {"coordinates":[-100.258865356,49.6208343506],"type":"Point"}
}