{
  "type": "Feature",
  "properties": {
    "addr:full":"93 Ontario St Stratford ON N5A 3H1",
    "addr:housenumber":"93",
    "addr:postcode":"n5a 3h1",
    "addr:street":"Ontario St",
    "iso:country":"CA",
    "sg:address":"93 Ontario St",
    "sg:city":"Stratford",
    "sg:classifiers":[
        {
            "category":"Shopping",
            "subcategory":"Clothing, Apparel, & Fashions",
            "type":"Retail Goods"
        }
    ],
    "sg:phone":"+1 519 273 4410",
    "sg:postcode":"N5A 3H1",
    "sg:province":"ON",
    "wof:name":"Wardrobe of Stratford",
    "wof:placetype":"venue"
},
  "geometry": {"coordinates":[-80.9815826416,43.3712844849],"type":"Point"}
}