{
  "type": "Feature",
  "properties": {
    "addr:full":"Saint-Amable QC J0L 1N0",
    "addr:postcode":"j0l 1n0",
    "iso:country":"CA",
    "sg:city":"Saint-Amable",
    "sg:classifiers":[
        {
            "category":"Shopping",
            "subcategory":"Computers & Home Electronics",
            "type":"Retail Goods"
        }
    ],
    "sg:phone":"+1 450 922 9777",
    "sg:postcode":"J0L 1N0",
    "sg:province":"QC",
    "sg:tags":[
        "equipment",
        "dealer"
    ],
    "wof:name":"Ordynamik",
    "wof:placetype":"venue"
},
  "geometry": {"coordinates":[-73.2990112305,45.6398544312],"type":"Point"}
}