{
  "type": "Feature",
  "properties": {
    "iso:country":"CA",
    "sg:address":"1241 Rue Labadie",
    "sg:city":"Longueuil",
    "sg:classifiers":[
        {
            "category":"Retail",
            "subcategory":"Repair Shop",
            "type":"Services"
        }
    ],
    "sg:phone":"+1 450 670 3882",
    "sg:postcode":"J4N 1E2",
    "sg:province":"QC",
    "sg:tags":[
        "welding"
    ],
    "wof:name":"Soudures Technifab Enr",
    "wof:placetype":"venue"
},
  "geometry": {"coordinates":[-73.454727,45.563911],"type":"Point"}
}