{
  "type": "Feature",
  "properties": {
    "addr:full":"St Albert AB T8N 5C5",
    "addr:postcode":"t8n 5c5",
    "iso:country":"CA",
    "sg:city":"St Albert",
    "sg:classifiers":[
        {
            "category":"Taxi",
            "type":"Transportation"
        }
    ],
    "sg:phone":"+1 780 459 5050",
    "sg:postcode":"T8N 5C5",
    "sg:province":"AB",
    "sg:tags":[
        "taxicab"
    ],
    "wof:name":"St Albert Taxi",
    "wof:placetype":"venue"
},
  "geometry": {"coordinates":[-113.644073486,53.6233482361],"type":"Point"}
}