{
  "type": "Feature",
  "properties": {
    "iso:country":"CA",
    "sg:address":"14 Oxford St",
    "sg:city":"Richmond Hill",
    "sg:classifiers":[
        {
            "category":"Professional",
            "subcategory":"Accounting & Tax Preparation",
            "type":"Services"
        }
    ],
    "sg:phone":"+1 905 773 1344",
    "sg:postcode":"L4C 4L5",
    "sg:province":"ON",
    "sg:tags":[
        "accountant"
    ],
    "wof:name":"Cividale Realty Corp",
    "wof:placetype":"venue"
},
  "geometry": {"coordinates":[-79.4423294067,43.8868560791],"type":"Point"}
}