{
  "type": "Feature",
  "properties": {
    "addr:full":"259 Nashwaak West Rd Nashwaak Bridge NB E6C 2A6",
    "addr:housenumber":"259",
    "addr:postcode":"e6c 2a6",
    "addr:street":"Nashwaak West Rd",
    "iso:country":"CA",
    "sg:address":"259 Nashwaak West Rd",
    "sg:city":"Nashwaak Bridge",
    "sg:classifiers":[
        {
            "category":"Building & Trades",
            "subcategory":"Plumbing",
            "type":"Services"
        }
    ],
    "sg:phone":"+1 506 367 2567",
    "sg:postcode":"E6C 2A6",
    "sg:province":"NB",
    "sg:tags":[
        "tank",
        "septic"
    ],
    "wof:name":"Nashwaak Ventures Ltd",
    "wof:placetype":"venue"
},
  "geometry": {"coordinates":[-66.60794799999999,46.241772],"type":"Point"}
}