{
  "type": "Feature",
  "properties": {
    "addr:full":"3803 Hart Hwy Prince George BC V2K 2Z4",
    "addr:housenumber":"3803",
    "addr:postcode":"v2k 2z4",
    "addr:street":"Hart Hwy",
    "iso:country":"CA",
    "sg:address":"3803 Hart Hwy",
    "sg:city":"Prince George",
    "sg:classifiers":[
        {
            "category":"Restaurant",
            "type":"Food & Drink"
        }
    ],
    "sg:phone":"+1 250 562 3456",
    "sg:postcode":"V2K 2Z4",
    "sg:province":"BC",
    "wof:name":"A & A Burger Bar",
    "wof:placetype":"venue"
},
  "geometry": {"coordinates":[-122.76696800000001,53.95937],"type":"Point"}
}