{
  "type": "Feature",
  "properties": {
    "addr:full":"4200 Beacon Lane Mississauga ON L5C 3V9",
    "addr:housenumber":"4200",
    "addr:postcode":"l5c 3v9",
    "addr:street":"Beacon Lane",
    "iso:country":"CA",
    "sg:address":"4200 Beacon Lane",
    "sg:city":"Mississauga",
    "sg:classifiers":[
        {
            "category":"Education",
            "subcategory":"School",
            "type":"Public Place"
        }
    ],
    "sg:phone":"+1 905 848 4200",
    "sg:postcode":"L5C 3V9",
    "sg:province":"ON",
    "wof:name":"St David of Wales Schools",
    "wof:placetype":"venue"
},
  "geometry": {"coordinates":[-79.6662597656,43.5753974915],"type":"Point"}
}