{
  "type": "Feature",
  "properties": {
    "addr:full":"Bancroft ON K0L 1C0",
    "addr:postcode":"k0l 1c0",
    "iso:country":"CA",
    "sg:city":"Bancroft",
    "sg:classifiers":[
        {
            "category":"Travel",
            "subcategory":"Hotels & Motels",
            "type":"Entertainment"
        }
    ],
    "sg:phone":"+1 613 339 3100",
    "sg:postcode":"K0L 1C0",
    "sg:province":"ON",
    "sg:tags":[
        "resort",
        "tourist",
        "accommodation"
    ],
    "wof:name":"Somerset Inn",
    "wof:placetype":"venue"
},
  "geometry": {"coordinates":[-77.88832855219999,44.4251403809],"type":"Point"}
}