{
  "type": "Feature",
  "properties": {
    "addr:full":"170 Main St Lewisporte NL A0G 3A0",
    "addr:housenumber":"170",
    "addr:postcode":"a0g 3a0",
    "addr:street":"Main St",
    "iso:country":"CA",
    "sg:address":"170 Main St",
    "sg:city":"Lewisporte",
    "sg:classifiers":[
        {
            "category":"Banks & Credit Unions",
            "subcategory":"Bank",
            "type":"Services"
        }
    ],
    "sg:phone":"+1 709 535 0670",
    "sg:postcode":"A0G 3A0",
    "sg:province":"NL",
    "wof:name":"Cibc",
    "wof:placetype":"venue"
},
  "geometry": {"coordinates":[-55.0599365234,49.2417984009],"type":"Point"}
}