{
  "type": "Feature",
  "properties": {
    "addr:full":"Brockville ON K6V 4R8",
    "addr:postcode":"k6v 4r8",
    "iso:country":"CA",
    "sg:city":"Brockville",
    "sg:classifiers":[
        {
            "category":"Social Services",
            "type":"Services"
        }
    ],
    "sg:phone":"+1 613 345 2412",
    "sg:postcode":"K6V 4R8",
    "sg:province":"ON",
    "sg:tags":[
        "senior",
        "citizen"
    ],
    "wof:name":"Shepherd's Welcome Ctr",
    "wof:placetype":"venue"
},
  "geometry": {"coordinates":[-75.684837,44.590782],"type":"Point"}
}