{
  "type": "Feature",
  "properties": {
    "addr:full":"4 Irwin Ave Toronto ON M4Y 1K9",
    "addr:housenumber":"4",
    "addr:postcode":"m4y 1k9",
    "addr:street":"Irwin Ave",
    "iso:country":"CA",
    "sg:address":"4 Irwin Ave",
    "sg:city":"Toronto",
    "sg:classifiers":[
        {
            "category":"Restaurant",
            "type":"Food & Drink"
        }
    ],
    "sg:phone":"+1 416 923 5438",
    "sg:postcode":"M4Y 1K9",
    "sg:province":"ON",
    "wof:name":"Ethiopian House Restaurant",
    "wof:placetype":"venue"
},
  "geometry": {"coordinates":[-79.385559,43.666763],"type":"Point"}
}