{
  "type": "Feature",
  "properties": {
    "addr:full":"2801 Eglinton Ave W York ON M6M 5B4",
    "addr:housenumber":"2801",
    "addr:postcode":"m6m 5b4",
    "addr:street":"Eglinton Ave W",
    "iso:country":"CA",
    "sg:address":"2801 Eglinton Ave W",
    "sg:city":"York",
    "sg:classifiers":[
        {
            "category":"Arena",
            "subcategory":"Sports Club",
            "type":"Entertainment"
        }
    ],
    "sg:phone":"+1 416 394 2733",
    "sg:postcode":"M6M 5B4",
    "sg:province":"ON",
    "sg:tags":[
        "athletic",
        "fields",
        "stadium",
        "government"
    ],
    "wof:name":"Chris Tonks Arena",
    "wof:placetype":"venue"
},
  "geometry": {"coordinates":[-79.48170500000001,43.688499],"type":"Point"}
}