{
  "type": "Feature",
  "properties": {
    "addr:full":"11730 6E Av Montreal QC H1E 1S1",
    "addr:housenumber":"11730",
    "addr:postcode":"h1e 1s1",
    "addr:street":"6E Av",
    "iso:country":"CA",
    "sg:address":"11730 6E Av",
    "sg:city":"Montreal",
    "sg:classifiers":[
        {
            "category":"Building & Trades",
            "subcategory":"Construction",
            "type":"Services"
        }
    ],
    "sg:phone":"+1 514 494 2572",
    "sg:postcode":"H1E 1S1",
    "sg:province":"QC",
    "sg:tags":[
        "excavating",
        "contractor"
    ],
    "wof:name":"Entreprises I Franco Inc",
    "wof:placetype":"venue"
},
  "geometry": {"coordinates":[-73.600105,45.622513],"type":"Point"}
}