{
  "type": "Feature",
  "properties": {
    "addr:full":"250 Eglinton Ave E Toronto ON M4P 1K2",
    "addr:housenumber":"250",
    "addr:postcode":"m4p 1k2",
    "addr:street":"Eglinton Ave E",
    "iso:country":"CA",
    "sg:address":"250 Eglinton Ave E",
    "sg:city":"Toronto",
    "sg:classifiers":[
        {
            "category":"Restaurant",
            "type":"Food & Drink"
        }
    ],
    "sg:phone":"+1 416 481 6850",
    "sg:postcode":"M4P 1K2",
    "sg:province":"ON",
    "sg:tags":[
        "sandwich"
    ],
    "wof:name":"Subway Sandwiches & Salads",
    "wof:placetype":"venue"
},
  "geometry": {"coordinates":[-79.390755,43.708439],"type":"Point"}
}