{
  "type": "Feature",
  "properties": {
    "addr:full":"4615 Av Van Horne Montreal QC H3W 1H8",
    "addr:housenumber":"4615",
    "addr:postcode":"h3w 1h8",
    "addr:street":"Av Van Horne",
    "iso:country":"CA",
    "sg:address":"4615 Av Van Horne",
    "sg:city":"Montreal",
    "sg:classifiers":[
        {
            "category":"Restaurant",
            "type":"Food & Drink"
        }
    ],
    "sg:phone":"+1 514 733 7776",
    "sg:postcode":"H3W 1H8",
    "sg:province":"QC",
    "wof:name":"Banahay Delicatessen Philippie",
    "wof:placetype":"venue"
},
  "geometry": {"coordinates":[-73.636253,45.496136],"type":"Point"}
}