{
  "type": "Feature",
  "properties": {
    "iso:country":"CA",
    "sg:address":"4814 17 Ave SE",
    "sg:city":"Calgary",
    "sg:classifiers":[
        {
            "category":"Autos & Motor Vehicles",
            "subcategory":"Auto Supplies",
            "type":"Retail Goods"
        }
    ],
    "sg:phone":"+1 403 235 5293",
    "sg:postcode":"T2A 0V2",
    "sg:province":"AB",
    "sg:tags":[
        "tire"
    ],
    "wof:name":"O K Tire & Auto Svc",
    "wof:placetype":"venue"
},
  "geometry": {"coordinates":[-113.965446472,51.0379867554],"type":"Point"}
}