{
  "type": "Feature",
  "properties": {
    "addr:full":"505 Rue Adoncour Longueuil QC J4G 2M6",
    "addr:housenumber":"505",
    "addr:postcode":"j4g 2m6",
    "addr:street":"Rue Adoncour",
    "iso:country":"CA",
    "sg:address":"505 Rue Adoncour",
    "sg:city":"Longueuil",
    "sg:classifiers":[
        {
            "category":"Shopping",
            "subcategory":"Pharmacy",
            "type":"Retail Goods"
        }
    ],
    "sg:phone":"+1 450 677 5267",
    "sg:postcode":"J4G 2M6",
    "sg:province":"QC",
    "wof:name":"Maurice Gregoire Pharmacy",
    "wof:placetype":"venue"
},
  "geometry": {"coordinates":[-73.484131,45.555058],"type":"Point"}
}