{
  "type": "Feature",
  "properties": {
    "addr:full":"Mississauga ON L5B 3C3",
    "addr:postcode":"l5b 3c3",
    "iso:country":"CA",
    "sg:city":"Mississauga",
    "sg:classifiers":[
        {
            "category":"Professional",
            "subcategory":"Accounting & Tax Preparation",
            "type":"Services"
        }
    ],
    "sg:phone":"+1 905 523 8758",
    "sg:postcode":"L5B 3C3",
    "sg:province":"ON",
    "sg:tags":[
        "consultant",
        "accountant"
    ],
    "wof:name":"Ernst & Young",
    "wof:placetype":"venue"
},
  "geometry": {"coordinates":[-79.637421,43.591591],"type":"Point"}
}