{
  "type": "Feature",
  "properties": {
    "iso:country":"CA",
    "sg:address":"963 Martin Grove Rd",
    "sg:city":"Etobicoke",
    "sg:classifiers":[
        {
            "category":"Wholesale",
            "subcategory":"Machinery & Supplies",
            "type":"Manufacturing & Wholesale Goods"
        }
    ],
    "sg:phone":"+1 416 244 5361",
    "sg:postcode":"M9W 4V6",
    "sg:province":"ON",
    "sg:tags":[
        "machine",
        "tool"
    ],
    "wof:name":"Machinery Canada",
    "wof:placetype":"venue"
},
  "geometry": {"coordinates":[-79.572395,43.695343],"type":"Point"}
}