{
  "type": "Feature",
  "properties": {
    "addr:full":"101 6th St Estevan SK S4A 2L7",
    "addr:housenumber":"101",
    "addr:postcode":"s4a 2l7",
    "addr:street":"6Th St",
    "iso:country":"CA",
    "sg:address":"101 6th St",
    "sg:city":"Estevan",
    "sg:classifiers":[
        {
            "category":"Wholesale",
            "subcategory":"Electrical",
            "type":"Manufacturing & Wholesale Goods"
        }
    ],
    "sg:phone":"+1 306 634 8655",
    "sg:postcode":"S4A 2L7",
    "sg:province":"SK",
    "sg:tags":[
        "equipment",
        "electric",
        "supply"
    ],
    "wof:name":"Gescan",
    "wof:placetype":"venue"
},
  "geometry": {"coordinates":[-102.96940600000001,49.133064],"type":"Point"}
}