{
  "type": "Feature",
  "properties": {
    "addr:full":"45 Allan Trailer Crt #57 Allan SK S0K 0C0",
    "addr:housenumber":"45;57",
    "addr:postcode":"s0k 0c0",
    "addr:street":"Allan Trailer Crt #",
    "iso:country":"CA",
    "sg:address":"45 Allan Trailer Crt #57",
    "sg:city":"Allan",
    "sg:classifiers":[
        {
            "category":"Real Estate",
            "subcategory":"Real Estate Operator",
            "type":"Services"
        }
    ],
    "sg:phone":"+1 306 257 4257",
    "sg:postcode":"S0K 0C0",
    "sg:province":"SK",
    "sg:tags":[
        "mobile",
        "home",
        "community"
    ],
    "wof:name":"Allan Trailer Court",
    "wof:placetype":"venue"
},
  "geometry": {"coordinates":[-106.057602,51.893501],"type":"Point"}
}