{
  "type": "Feature",
  "properties": {
    "addr:full":"Sainte-Thecle QC G0X 3G0",
    "addr:postcode":"g0x 3g0",
    "iso:country":"CA",
    "sg:city":"Sainte-Thecle",
    "sg:classifiers":[
        {
            "category":"Home & Garden",
            "subcategory":"Hardware",
            "type":"Retail Goods"
        }
    ],
    "sg:phone":"+1 418 289 2350",
    "sg:postcode":"G0X 3G0",
    "sg:province":"QC",
    "wof:name":"Quincaillerie Lafrance Enr",
    "wof:placetype":"venue"
},
  "geometry": {"coordinates":[-72.50708,46.813911],"type":"Point"}
}