{
  "type": "Feature",
  "properties": {
    "addr:full":"5002 50th St Eckville AB T0M 0X0",
    "addr:housenumber":"5002",
    "addr:postcode":"t0m 0x0",
    "addr:street":"50Th St",
    "iso:country":"CA",
    "sg:address":"5002 50th St",
    "sg:city":"Eckville",
    "sg:classifiers":[
        {
            "category":"Banks & Credit Unions",
            "subcategory":"Bank",
            "type":"Services"
        }
    ],
    "sg:phone":"+1 403 746 2288",
    "sg:postcode":"T0M 0X0",
    "sg:province":"AB",
    "wof:name":"Eckville District Savings",
    "wof:placetype":"venue"
},
  "geometry": {"coordinates":[-114.36819457999999,52.3592224121],"type":"Point"}
}