{
  "type": "Feature",
  "properties": {
    "addr:full":"Kitchener ON N2K 1M5",
    "addr:postcode":"n2k 1m5",
    "iso:country":"CA",
    "sg:city":"Kitchener",
    "sg:classifiers":[
        {
            "category":"Retail",
            "subcategory":"Repair Shop",
            "type":"Services"
        }
    ],
    "sg:phone":"+1 519 570 3776",
    "sg:postcode":"N2K 1M5",
    "sg:province":"ON",
    "sg:tags":[
        "appliance"
    ],
    "wof:name":"Nielsen Appliances",
    "wof:placetype":"venue"
},
  "geometry": {"coordinates":[-80.483559,43.481297],"type":"Point"}
}