{
  "type": "Feature",
  "properties": {
    "addr:full":"39004 Hillside Beach Rd Grand Marais MB R0E 0T0",
    "addr:housenumber":"39004",
    "addr:postcode":"r0e 0t0",
    "addr:street":"Hillside Beach Rd",
    "iso:country":"CA",
    "sg:address":"39004 Hillside Beach Rd",
    "sg:city":"Grand Marais",
    "sg:classifiers":[
        {
            "category":"Building & Trades",
            "subcategory":"Equipment Rental",
            "type":"Services"
        }
    ],
    "sg:phone":"+1 204 756 8184",
    "sg:postcode":"R0E 0T0",
    "sg:province":"MB",
    "sg:tags":[
        "yard"
    ],
    "wof:name":"Mac Donald Brown Rentals",
    "wof:placetype":"venue"
},
  "geometry": {"coordinates":[-96.6255569458,50.5451431274],"type":"Point"}
}