{
  "type": "Feature",
  "properties": {
    "iso:country":"CA",
    "sg:city":"Calgary",
    "sg:classifiers":[
        {
            "category":"Personal",
            "subcategory":"Beauty Salon",
            "type":"Services"
        }
    ],
    "sg:phone":"+1 403 295 0057",
    "sg:postcode":"T2E 7P4",
    "sg:province":"AB",
    "wof:name":"Just Your Style Hair Studio",
    "wof:placetype":"venue"
},
  "geometry": {"coordinates":[-114.041191101,51.1103248596],"type":"Point"}
}