{
  "type": "Feature",
  "properties": {
    "iso:country":"CA",
    "sg:address":"461 Alden Rd",
    "sg:city":"Markham",
    "sg:classifiers":[
        {
            "category":"Professional",
            "subcategory":"Management & Consulting",
            "type":"Services"
        }
    ],
    "sg:phone":"+1 905 479 7000",
    "sg:postcode":"L3R 3L4",
    "sg:province":"ON",
    "sg:tags":[
        "party",
        "planning"
    ],
    "wof:name":"Stardust Events",
    "wof:placetype":"venue"
},
  "geometry": {"coordinates":[-79.333152771,43.8347663879],"type":"Point"}
}