{
  "type": "Feature",
  "properties": {
    "addr:full":"995 Rue Gosford E # A Sainte-Agathe-DE-Lotbiniere QC G0S 2A0",
    "addr:housenumber":"995",
    "addr:postcode":"g0s 2a0",
    "addr:street":"Rue Gosford E # A Sainte-Agathe-De-Lotbiniere",
    "iso:country":"CA",
    "sg:address":"995 Rue Gosford E # A",
    "sg:city":"Sainte-Agathe-DE-Lotbiniere",
    "sg:classifiers":[
        {
            "category":"Restaurant",
            "type":"Food & Drink"
        }
    ],
    "sg:phone":"+1 418 599 2221",
    "sg:postcode":"G0S 2A0",
    "sg:province":"QC",
    "wof:name":"Casse-Croute Chez Ti-Be",
    "wof:placetype":"venue"
},
  "geometry": {"coordinates":[-71.42667400000001,46.360046],"type":"Point"}
}