{
  "type": "Feature",
  "properties": {
    "addr:full":"598 Lorne Ave E Stratford ON N5A 6S5",
    "addr:housenumber":"598",
    "addr:postcode":"n5a 6s5",
    "addr:street":"Lorne Ave E",
    "iso:country":"CA",
    "sg:address":"598 Lorne Ave E",
    "sg:city":"Stratford",
    "sg:classifiers":[
        {
            "category":"Retail",
            "subcategory":"Auto Repair",
            "type":"Services"
        }
    ],
    "sg:phone":"+1 519 272 2728",
    "sg:postcode":"N5A 6S5",
    "sg:province":"ON",
    "sg:tags":[
        "body",
        "automobile",
        "painting"
    ],
    "wof:name":"Mcr Advance Collision Ctr",
    "wof:placetype":"venue"
},
  "geometry": {"coordinates":[-80.9694976807,43.3530044556],"type":"Point"}
}