{
  "type": "Feature",
  "properties": {
    "addr:full":"Surrey BC V3S 2V8",
    "addr:postcode":"v3s 2v8",
    "iso:country":"CA",
    "sg:city":"Surrey",
    "sg:classifiers":[
        {
            "category":"Personal",
            "subcategory":"Beauty Salon",
            "type":"Services"
        }
    ],
    "sg:phone":"+1 604 581 5727",
    "sg:postcode":"V3S 2V8",
    "sg:province":"BC",
    "wof:name":"Master's Touch Unisex Hair Std",
    "wof:placetype":"venue"
},
  "geometry": {"coordinates":[-122.79089399999999,49.162189],"type":"Point"}
}