{
  "type": "Feature",
  "properties": {
    "addr:full":"274 Parleeville Rd Norton NB E5T 1V2",
    "addr:housenumber":"274",
    "addr:postcode":"e5t 1v2",
    "addr:street":"Parleeville Rd",
    "iso:country":"CA",
    "sg:address":"274 Parleeville Rd",
    "sg:city":"Norton",
    "sg:classifiers":[
        {
            "category":"Retail",
            "subcategory":"Repair Shop",
            "type":"Services"
        }
    ],
    "sg:phone":"+1 506 839 2343",
    "sg:postcode":"E5T 1V2",
    "sg:province":"NB",
    "sg:tags":[
        "welding"
    ],
    "wof:name":"Bic's Welding & Mechanical",
    "wof:placetype":"venue"
},
  "geometry": {"coordinates":[-65.701729,45.693962],"type":"Point"}
}