{
  "type": "Feature",
  "properties": {
    "addr:full":"2700 Dufferin St # 47 York ON M6B 4J3",
    "addr:housenumber":"2700;47",
    "addr:postcode":"m6b 4j3",
    "addr:street":"Dufferin St #",
    "iso:country":"CA",
    "sg:address":"2700 Dufferin St # 47",
    "sg:city":"York",
    "sg:classifiers":[
        {
            "category":"Restaurant",
            "type":"Food & Drink"
        }
    ],
    "sg:phone":"+1 416 787 5205",
    "sg:postcode":"M6B 4J3",
    "sg:province":"ON",
    "wof:name":"California Sandwiches",
    "wof:placetype":"venue"
},
  "geometry": {"coordinates":[-79.4521865845,43.701877594],"type":"Point"}
}