{
  "type": "Feature",
  "properties": {
    "addr:full":"184 Rue Notre-Dame Repentigny QC J6A 2P9",
    "addr:housenumber":"184",
    "addr:postcode":"j6a 2p9",
    "addr:street":"Rue Notre-Dame",
    "iso:country":"CA",
    "sg:address":"184 Rue Notre-Dame",
    "sg:city":"Repentigny",
    "sg:classifiers":[
        {
            "category":"Professional",
            "subcategory":"Business Services",
            "type":"Services"
        }
    ],
    "sg:phone":"+1 450 585 4931",
    "sg:postcode":"J6A 2P9",
    "sg:province":"QC",
    "sg:tags":[
        "notary"
    ],
    "wof:name":"Langlade, Jean-Pierre",
    "wof:placetype":"venue"
},
  "geometry": {"coordinates":[-73.467414856,45.7189064026],"type":"Point"}
}