{
  "type": "Feature",
  "properties": {
    "addr:full":"124 10 St NW Calgary AB T2N 1V3",
    "addr:housenumber":"10",
    "addr:postcode":"t2n 1v3",
    "addr:street":"124;St Nw",
    "iso:country":"CA",
    "sg:address":"124 10 St NW",
    "sg:city":"Calgary",
    "sg:classifiers":[
        {
            "category":"Shopping",
            "subcategory":"Bicycles & Sporting Goods",
            "type":"Retail Goods"
        }
    ],
    "sg:phone":"+1 403 270 3719",
    "sg:postcode":"T2N 1V3",
    "sg:province":"AB",
    "sg:tags":[
        "snowboard"
    ],
    "wof:name":"Source",
    "wof:placetype":"venue"
},
  "geometry": {"coordinates":[-114.08573199999999,51.052757],"type":"Point"}
}