{
  "type": "Feature",
  "properties": {
    "addr:full":"6909 Macleod Trail SW Calgary AB T2H 0L6",
    "addr:housenumber":"6909",
    "addr:postcode":"t2h 0l6",
    "addr:street":"Macleod Trail Sw",
    "iso:country":"CA",
    "sg:address":"6909 Macleod Trail SW",
    "sg:city":"Calgary",
    "sg:classifiers":[
        {
            "category":"Shopping",
            "subcategory":"Department Store",
            "type":"Retail Goods"
        }
    ],
    "sg:phone":"+1 403 253 1500",
    "sg:postcode":"T2H 0L6",
    "sg:province":"AB",
    "sg:tags":[
        "shop",
        "liquidator"
    ],
    "wof:name":"Liquidation World Inc",
    "wof:placetype":"venue"
},
  "geometry": {"coordinates":[-114.07175445599999,50.9922103882],"type":"Point"}
}