{
  "type": "Feature",
  "properties": {
    "addr:full":"12464 153 St NW Edmonton AB T5V 1S5",
    "addr:housenumber":"12464",
    "addr:postcode":"t5v 1s5",
    "addr:street":"153 St Nw",
    "iso:country":"CA",
    "sg:address":"12464 153 St NW",
    "sg:city":"Edmonton",
    "sg:classifiers":[
        {
            "category":"Restaurant",
            "type":"Food & Drink"
        }
    ],
    "sg:phone":"+1 780 425 3292",
    "sg:postcode":"T5V 1S5",
    "sg:province":"AB",
    "wof:name":"Stage Coach Grill",
    "wof:placetype":"venue"
},
  "geometry": {"coordinates":[-113.584389,53.579563],"type":"Point"}
}