{
  "type": "Feature",
  "properties": {
    "addr:full":"63 Waterhouse Bay Winnipeg MB R3R 2N5",
    "addr:housenumber":"63",
    "addr:postcode":"r3r 2n5",
    "addr:street":"Waterhouse Bay",
    "iso:country":"CA",
    "sg:address":"63 Waterhouse Bay",
    "sg:city":"Winnipeg",
    "sg:classifiers":[
        {
            "category":"Professional",
            "subcategory":"Research",
            "type":"Services"
        }
    ],
    "sg:phone":"+1 204 831 7740",
    "sg:postcode":"R3R 2N5",
    "sg:province":"MB",
    "sg:tags":[
        "environmental",
        "ecological"
    ],
    "wof:name":"Falk Environmental",
    "wof:placetype":"venue"
},
  "geometry": {"coordinates":[-97.3171157837,49.8686523438],"type":"Point"}
}