{
  "type": "Feature",
  "properties": {
    "iso:country":"CA",
    "sg:address":"255 Dundas St",
    "sg:city":"Waterdown",
    "sg:classifiers":[
        {
            "category":"Retail",
            "subcategory":"Laundry & Dry Cleaning",
            "type":"Services"
        }
    ],
    "sg:phone":"+1 905 689 4056",
    "sg:postcode":"L0R 2H6",
    "sg:province":"ON",
    "sg:tags":[
        "cleaners"
    ],
    "wof:name":"Roma Bella Cleaners",
    "wof:placetype":"venue"
},
  "geometry": {"coordinates":[-79.89720153810001,43.3298835754],"type":"Point"}
}