{
  "type": "Feature",
  "properties": {
    "addr:full":"295 Danforth Rd Scarborough ON M1L 3X2",
    "addr:housenumber":"295",
    "addr:postcode":"m1l 3x2",
    "addr:street":"Danforth Rd",
    "iso:country":"CA",
    "sg:address":"295 Danforth Rd",
    "sg:city":"Scarborough",
    "sg:classifiers":[
        {
            "category":"Autos & Motor Vehicles",
            "subcategory":"Auto Supplies",
            "type":"Retail Goods"
        }
    ],
    "sg:phone":"+1 416 699 2128",
    "sg:postcode":"M1L 3X2",
    "sg:province":"ON",
    "sg:tags":[
        "tire"
    ],
    "wof:name":"Ron Mitton Tire Svc Ltd",
    "wof:placetype":"venue"
},
  "geometry": {"coordinates":[-79.27053070069999,43.7028808594],"type":"Point"}
}