{
  "type": "Feature",
  "properties": {
    "addr:full":"5652 Cowrie St Sechelt BC V0N 3A0",
    "addr:housenumber":"5652",
    "addr:postcode":"v0n 3a0",
    "addr:street":"Cowrie St",
    "iso:country":"CA",
    "sg:address":"5652 Cowrie St",
    "sg:city":"Sechelt",
    "sg:classifiers":[
        {
            "category":"Professional",
            "subcategory":"Accounting & Tax Preparation",
            "type":"Services"
        }
    ],
    "sg:phone":"+1 604 885 4010",
    "sg:postcode":"V0N 3A0",
    "sg:province":"BC",
    "sg:tags":[
        "consultant",
        "management",
        "return",
        "filing",
        "business"
    ],
    "wof:name":"H & R Block Canada Inc",
    "wof:placetype":"venue"
},
  "geometry": {"coordinates":[-123.75891876199999,49.4716453552],"type":"Point"}
}