{
  "type": "Feature",
  "properties": {
    "addr:full":"1178 Concession Rd Fort Erie ON L2A 6S9",
    "addr:housenumber":"1178",
    "addr:postcode":"l2a 6s9",
    "addr:street":"Concession Rd",
    "iso:country":"CA",
    "sg:address":"1178 Concession Rd",
    "sg:city":"Fort Erie",
    "sg:classifiers":[
        {
            "category":"Professional",
            "subcategory":"Business Services",
            "type":"Services"
        }
    ],
    "sg:phone":"+1 905 994 1771",
    "sg:postcode":"L2A 6S9",
    "sg:province":"ON",
    "sg:tags":[
        "event"
    ],
    "wof:name":"Winterfest of Grtr Fort Erie",
    "wof:placetype":"venue"
},
  "geometry": {"coordinates":[-78.927818,42.908302],"type":"Point"}
}