{
  "type": "Feature",
  "properties": {
    "iso:country":"CA",
    "sg:address":"9111 110 Ave NW",
    "sg:city":"Edmonton",
    "sg:classifiers":[
        {
            "category":"Organizations",
            "subcategory":"Professional Association",
            "type":"Services"
        }
    ],
    "sg:phone":"+1 780 425 0766",
    "sg:postcode":"T5H 4J9",
    "sg:province":"AB",
    "wof:name":"Comitato Italiani All Estero",
    "wof:placetype":"venue"
},
  "geometry": {"coordinates":[-113.480773926,53.5592956543],"type":"Point"}
}