{
  "type": "Feature",
  "properties": {
    "addr:full":"160 Hayes Rd Thompson MB R8N 1M4",
    "addr:housenumber":"160",
    "addr:postcode":"r8n 1m4",
    "addr:street":"Hayes Rd",
    "iso:country":"CA",
    "sg:address":"160 Hayes Rd",
    "sg:city":"Thompson",
    "sg:classifiers":[
        {
            "category":"Wholesale",
            "subcategory":"Machinery & Supplies",
            "type":"Manufacturing & Wholesale Goods"
        }
    ],
    "sg:phone":"+1 204 677 2318",
    "sg:postcode":"R8N 1M4",
    "sg:province":"MB",
    "sg:tags":[
        "bearing"
    ],
    "wof:name":"Kinecor",
    "wof:placetype":"venue"
},
  "geometry": {"coordinates":[-97.86756099999999,55.730198],"type":"Point"}
}