{
  "type": "Feature",
  "properties": {
    "addr:full":"168 Angeline St N Lindsay ON K9V 4X2",
    "addr:housenumber":"168",
    "addr:postcode":"k9v 4x2",
    "addr:street":"Angeline St N",
    "iso:country":"CA",
    "sg:address":"168 Angeline St N",
    "sg:city":"Lindsay",
    "sg:classifiers":[
        {
            "category":"Personal",
            "subcategory":"Beauty Salon",
            "type":"Services"
        }
    ],
    "sg:phone":"+1 705 324 3451",
    "sg:postcode":"K9V 4X2",
    "sg:province":"ON",
    "wof:name":"Hair Trends",
    "wof:placetype":"venue"
},
  "geometry": {"coordinates":[-78.756287,44.362858],"type":"Point"}
}