{
  "type": "Feature",
  "properties": {
    "addr:full":"243 King St E Toronto ON M5A 1J9",
    "addr:housenumber":"243",
    "addr:postcode":"m5a 1j9",
    "addr:street":"King St E",
    "iso:country":"CA",
    "sg:address":"243 King St E",
    "sg:city":"Toronto",
    "sg:classifiers":[
        {
            "category":"Restaurant",
            "type":"Food & Drink"
        }
    ],
    "sg:phone":"+1 416 367 8622",
    "sg:postcode":"M5A 1J9",
    "sg:province":"ON",
    "wof:name":"Toba",
    "wof:placetype":"venue"
},
  "geometry": {"coordinates":[-79.368484,43.651066],"type":"Point"}
}