{
  "type": "Feature",
  "properties": {
    "addr:full":"2584 Eglinton Ave E Scarborough ON M1K 2R5",
    "addr:housenumber":"2584",
    "addr:postcode":"m1k 2r5",
    "addr:street":"Eglinton Ave E",
    "iso:country":"CA",
    "sg:address":"2584 Eglinton Ave E",
    "sg:city":"Scarborough",
    "sg:classifiers":[
        {
            "category":"Wholesale",
            "subcategory":"Auto Parts",
            "type":"Manufacturing & Wholesale Goods"
        }
    ],
    "sg:phone":"+1 416 269 0981",
    "sg:postcode":"M1K 2R5",
    "sg:province":"ON",
    "sg:tags":[
        "automobile",
        "supply"
    ],
    "wof:name":"Carmen & Franks Ltd",
    "wof:placetype":"venue"
},
  "geometry": {"coordinates":[-79.25471496580001,43.7354431152],"type":"Point"}
}