{
  "type": "Feature",
  "properties": {
    "addr:full":"5055 Boul Laurier O Saint-Hyacinthe QC J2S 3V4",
    "addr:housenumber":"5055",
    "addr:postcode":"j2s 3v4",
    "addr:street":"Boul Laurier O",
    "iso:country":"CA",
    "sg:address":"5055 Boul Laurier O",
    "sg:city":"Saint-Hyacinthe",
    "sg:classifiers":[
        {
            "category":"Restaurant",
            "type":"Food & Drink"
        }
    ],
    "sg:phone":"+1 450 774 8174",
    "sg:postcode":"J2S 3V4",
    "sg:province":"QC",
    "wof:name":"Restaurant Le Chalet",
    "wof:placetype":"venue"
},
  "geometry": {"coordinates":[-72.9757156372,45.6064109802],"type":"Point"}
}