{
  "type": "Feature",
  "properties": {
    "addr:full":"316 Centre St Assiniboia SK S0H 0B0",
    "addr:housenumber":"316",
    "addr:postcode":"s0h 0b0",
    "addr:street":"Centre St",
    "iso:country":"CA",
    "sg:address":"316 Centre St",
    "sg:city":"Assiniboia",
    "sg:classifiers":[
        {
            "category":"Shopping",
            "subcategory":"Clothing, Apparel, & Fashions",
            "type":"Retail Goods"
        }
    ],
    "sg:phone":"+1 306 642 3700",
    "sg:postcode":"S0H 0B0",
    "sg:province":"SK",
    "sg:tags":[
        "furnishing"
    ],
    "wof:name":"Timothy Daniels Men's Wear",
    "wof:placetype":"venue"
},
  "geometry": {"coordinates":[-105.992576599,49.6316947937],"type":"Point"}
}