{
  "type": "Feature",
  "properties": {
    "addr:full":"3301 Trout Lake Rd North Bay ON P1A 4L7",
    "addr:housenumber":"3301",
    "addr:postcode":"p1a 4l7",
    "addr:street":"Trout Lake Rd",
    "iso:country":"CA",
    "sg:address":"3301 Trout Lake Rd",
    "sg:city":"North Bay",
    "sg:classifiers":[
        {
            "category":"Government",
            "subcategory":"Office",
            "type":"Public Place"
        }
    ],
    "sg:phone":"+1 705 475 5550",
    "sg:postcode":"P1A 4L7",
    "sg:province":"ON",
    "wof:name":"Canada Resources Ministry",
    "wof:placetype":"venue"
},
  "geometry": {"coordinates":[-79.414536,46.328335],"type":"Point"}
}