{
  "type": "Feature",
  "properties": {
    "addr:full":"638 Yonge St Toronto ON M4Y 1Z8",
    "addr:housenumber":"638",
    "addr:postcode":"m4y 1z8",
    "addr:street":"Yonge St",
    "iso:country":"CA",
    "sg:address":"638 Yonge St",
    "sg:city":"Toronto",
    "sg:classifiers":[
        {
            "category":"Shopping",
            "subcategory":"Used Merchandise",
            "type":"Retail Goods"
        }
    ],
    "sg:phone":"+1 416 922 1668",
    "sg:postcode":"M4Y 1Z8",
    "sg:province":"ON",
    "sg:tags":[
        "glassware",
        "chinaware"
    ],
    "wof:name":"Hockridge China",
    "wof:placetype":"venue"
},
  "geometry": {"coordinates":[-79.38529200000001,43.666393],"type":"Point"}
}