{
  "type": "Feature",
  "properties": {
    "addr:full":"Etobicoke ON M9W 6P2",
    "addr:postcode":"m9w 6p2",
    "iso:country":"CA",
    "sg:city":"Etobicoke",
    "sg:classifiers":[
        {
            "category":"Shopping",
            "subcategory":"Computers & Home Electronics",
            "type":"Retail Goods"
        }
    ],
    "sg:phone":"+1 416 744 7191",
    "sg:postcode":"M9W 6P2",
    "sg:province":"ON",
    "sg:tags":[
        "software"
    ],
    "wof:name":"Lynch Technologies Inc",
    "wof:placetype":"venue"
},
  "geometry": {"coordinates":[-79.56667299999999,43.643398],"type":"Point"}
}