{
  "type": "Feature",
  "properties": {
    "addr:full":"5650 Yonge St #1505 North York ON M2M 4G3",
    "addr:housenumber":"5650",
    "addr:postcode":"m2m 4g3",
    "addr:street":"Yonge St # 1505",
    "iso:country":"CA",
    "sg:address":"5650 Yonge St #1505",
    "sg:city":"North York",
    "sg:classifiers":[
        {
            "category":"Professional",
            "subcategory":"Lawyer & Legal Services",
            "type":"Services"
        }
    ],
    "sg:phone":"+1 416 223 5393",
    "sg:postcode":"M2M 4G3",
    "sg:province":"ON",
    "sg:tags":[
        "attorney"
    ],
    "wof:name":"Waisberg, Darrell",
    "wof:placetype":"venue"
},
  "geometry": {"coordinates":[-79.41579400000001,43.779953],"type":"Point"}
}