{
  "type": "Feature",
  "properties": {
    "addr:full":"398 Avenue Rd Toronto ON M4V 2H4",
    "addr:housenumber":"398",
    "addr:postcode":"m4v 2h4",
    "addr:street":"Avenue Rd",
    "iso:country":"CA",
    "sg:address":"398 Avenue Rd",
    "sg:city":"Toronto",
    "sg:classifiers":[
        {
            "category":"Shopping",
            "subcategory":"Discount & Variety Stores",
            "type":"Retail Goods"
        }
    ],
    "sg:phone":"+1 416 922 2127",
    "sg:postcode":"M4V 2H4",
    "sg:province":"ON",
    "wof:name":"Mayfair Mansions Smoke & Gift",
    "wof:placetype":"venue"
},
  "geometry": {"coordinates":[-79.399895,43.682289],"type":"Point"}
}