{
  "type": "Feature",
  "properties": {
    "iso:country":"CA",
    "sg:address":"5035 Hurontario St",
    "sg:city":"Mississauga",
    "sg:classifiers":[
        {
            "category":"Restaurant",
            "type":"Food & Drink"
        }
    ],
    "sg:phone":"+1 905 501 1390",
    "sg:postcode":"L4Z 3X7",
    "sg:province":"ON",
    "wof:name":"Mr Sub",
    "wof:placetype":"venue"
},
  "geometry": {"coordinates":[-79.655266,43.60873],"type":"Point"}
}