{
  "type": "Feature",
  "properties": {
    "addr:full":"1362 Av Greene Westmount QC H3Z 2B1",
    "addr:housenumber":"1362",
    "addr:postcode":"h3z 2b1",
    "addr:street":"Av Greene",
    "iso:country":"CA",
    "sg:address":"1362 Av Greene",
    "sg:city":"Westmount",
    "sg:classifiers":[
        {
            "category":"Restaurant",
            "type":"Food & Drink"
        }
    ],
    "sg:phone":"+1 514 939 6451",
    "sg:postcode":"H3Z 2B1",
    "sg:province":"QC",
    "wof:name":"Bistro on the Avenue",
    "wof:placetype":"venue"
},
  "geometry": {"coordinates":[-73.59101099999999,45.487381],"type":"Point"}
}