{
  "type": "Feature",
  "properties": {
    "addr:full":"300 6th Ave S Cranbrook BC V1C 2H8",
    "addr:housenumber":"300",
    "addr:postcode":"bc v1c 2h8",
    "addr:street":"6Th Ave S",
    "iso:country":"CA",
    "sg:address":"300 6th Ave S",
    "sg:city":"Cranbrook",
    "sg:classifiers":[
        {
            "category":"Organizations",
            "subcategory":"Religious Organization",
            "type":"Services"
        }
    ],
    "sg:phone":"+1 250 426 6563",
    "sg:postcode":"V1C 2H8",
    "sg:province":"BC",
    "sg:tags":[
        "church"
    ],
    "wof:name":"Seventh Day Adventist Chr",
    "wof:placetype":"venue"
},
  "geometry": {"coordinates":[-115.772964477,49.5064964294],"type":"Point"}
}