{
  "type": "Feature",
  "properties": {
    "addr:full":"191 Dundas St W Toronto ON M5G 1C7",
    "addr:housenumber":"191",
    "addr:postcode":"m5g 1c7",
    "addr:street":"Dundas St W",
    "iso:country":"CA",
    "sg:address":"191 Dundas St W",
    "sg:city":"Toronto",
    "sg:classifiers":[
        {
            "category":"Restaurant",
            "type":"Food & Drink"
        }
    ],
    "sg:phone":"+1 416 971 6629",
    "sg:postcode":"M5G 1C7",
    "sg:province":"ON",
    "wof:name":"New Hot Spot",
    "wof:placetype":"venue"
},
  "geometry": {"coordinates":[-79.386848,43.65493],"type":"Point"}
}