{
  "type": "Feature",
  "properties": {
    "addr:full":"320 County Rd 8 Merrickville ON K0G 1N0",
    "addr:housenumber":"320",
    "addr:postcode":"k0g 1n0",
    "addr:street":"County Rd 8 Merrickville",
    "iso:country":"CA",
    "sg:address":"320 County Rd 8",
    "sg:city":"Merrickville",
    "sg:classifiers":[
        {
            "category":"Organizations",
            "subcategory":"Professional Association",
            "type":"Services"
        }
    ],
    "sg:phone":"+1 613 275 2400",
    "sg:postcode":"K0G 1N0",
    "sg:province":"ON",
    "wof:name":"Royal Canadian Legion",
    "wof:placetype":"venue"
},
  "geometry": {"coordinates":[-75.836838,44.915741],"type":"Point"}
}