{
  "type": "Feature",
  "properties": {
    "addr:full":"1331 263 Rte N Princeville QC G6L 4C8",
    "addr:housenumber":"1331",
    "addr:postcode":"g6l 4c8",
    "addr:street":"263 Rte N",
    "iso:country":"CA",
    "sg:address":"1331 263 Rte N",
    "sg:city":"Princeville",
    "sg:classifiers":[
        {
            "category":"Building & Trades",
            "subcategory":"Construction",
            "type":"Services"
        }
    ],
    "sg:phone":"+1 819 364 2371",
    "sg:postcode":"G6L 4C8",
    "sg:province":"QC",
    "sg:tags":[
        "contractor",
        "general"
    ],
    "wof:name":"Constructions R Moreau & Fils",
    "wof:placetype":"venue"
},
  "geometry": {"coordinates":[-71.870232,46.169113],"type":"Point"}
}