{
  "type": "Feature",
  "properties": {
    "iso:country":"CA",
    "sg:address":"1078 Kipling Ave",
    "sg:city":"Etobicoke",
    "sg:classifiers":[
        {
            "category":"Professional",
            "subcategory":"Lawyer & Legal Services",
            "type":"Services"
        }
    ],
    "sg:phone":"+1 416 231 3353",
    "sg:postcode":"M9B 3M2",
    "sg:province":"ON",
    "sg:tags":[
        "attorney"
    ],
    "wof:name":"Hahn, Kenneth A",
    "wof:placetype":"venue"
},
  "geometry": {"coordinates":[-79.53880310060001,43.6493263245],"type":"Point"}
}