{
  "type": "Feature",
  "properties": {
    "addr:full":"5206 68 St NE Calgary AB T3J 3P8",
    "addr:housenumber":"5206",
    "addr:postcode":"t3j 3p8",
    "addr:street":"68 St Ne",
    "iso:country":"CA",
    "sg:address":"5206 68 St NE",
    "sg:city":"Calgary",
    "sg:classifiers":[
        {
            "category":"Recreation",
            "type":"Entertainment"
        }
    ],
    "sg:phone":"+1 403 590 2444",
    "sg:postcode":"T3J 3P8",
    "sg:province":"AB",
    "sg:tags":[
        "arena",
        "athletic",
        "center",
        "stadium",
        "fields"
    ],
    "wof:name":"Don Hartman North East Sports",
    "wof:placetype":"venue"
},
  "geometry": {"coordinates":[-113.935050964,51.0988006592],"type":"Point"}
}