{
  "type": "Feature",
  "properties": {
    "addr:full":"209 Putman Industrial Dr Belleville ON K8N 4Z5",
    "addr:housenumber":"209",
    "addr:postcode":"k8n 4z5",
    "addr:street":"Putman Industrial Dr",
    "iso:country":"CA",
    "sg:address":"209 Putman Industrial Dr",
    "sg:city":"Belleville",
    "sg:classifiers":[
        {
            "category":"Retail",
            "subcategory":"Auto Repair",
            "type":"Services"
        }
    ],
    "sg:phone":"+1 613 962 9019",
    "sg:postcode":"K8N 4Z5",
    "sg:province":"ON",
    "sg:tags":[
        "truck"
    ],
    "wof:name":"Gibson Sales & Svc Inc",
    "wof:placetype":"venue"
},
  "geometry": {"coordinates":[-77.37593099999999,44.207066],"type":"Point"}
}