{
  "type": "Feature",
  "properties": {
    "addr:full":"603 King St E Hamilton ON L8N 1E4",
    "addr:housenumber":"603",
    "addr:postcode":"l8n 1e4",
    "addr:street":"King St E",
    "iso:country":"CA",
    "sg:address":"603 King St E",
    "sg:city":"Hamilton",
    "sg:classifiers":[
        {
            "category":"Autos & Motor Vehicles",
            "subcategory":"Fuel & Gas Station",
            "type":"Retail Goods"
        }
    ],
    "sg:phone":"+1 905 528 6030",
    "sg:postcode":"L8N 1E4",
    "sg:province":"ON",
    "sg:tags":[
        "oil"
    ],
    "wof:name":"Pioneer Petroleums",
    "wof:placetype":"venue"
},
  "geometry": {"coordinates":[-79.8509521484,43.2524452209],"type":"Point"}
}