{
  "type": "Feature",
  "properties": {
    "iso:country":"CA",
    "sg:address":"17123 95 St NW",
    "sg:city":"Edmonton",
    "sg:classifiers":[
        {
            "category":"Organizations",
            "subcategory":"Professional Association",
            "type":"Services"
        }
    ],
    "sg:phone":"+1 780 457 0574",
    "sg:postcode":"T5Z 1Z9",
    "sg:province":"AB",
    "wof:name":"Lago Lindo Community League",
    "wof:placetype":"venue"
},
  "geometry": {"coordinates":[-113.488380432,53.6344833374],"type":"Point"}
}