{
  "type": "Feature",
  "properties": {
    "addr:full":"300 Founders St Tumbler Ridge BC V0C 2W0",
    "addr:housenumber":"300",
    "addr:postcode":"bc v0c 2w0",
    "addr:street":"Founders St",
    "iso:country":"CA",
    "sg:address":"300 Founders St",
    "sg:city":"Tumbler Ridge",
    "sg:classifiers":[
        {
            "category":"Restaurant",
            "type":"Food & Drink"
        }
    ],
    "sg:phone":"+1 250 242 4584",
    "sg:postcode":"V0C 2W0",
    "sg:province":"BC",
    "wof:name":"Dragon Palace",
    "wof:placetype":"venue"
},
  "geometry": {"coordinates":[-120.998589,55.125992],"type":"Point"}
}