{
  "type": "Feature",
  "properties": {
    "addr:full":"419 Rue Heriot Drummondville QC J2B 1B4",
    "addr:housenumber":"419",
    "addr:postcode":"j2b 1b4",
    "addr:street":"Rue Heriot",
    "iso:country":"CA",
    "sg:address":"419 Rue Heriot",
    "sg:city":"Drummondville",
    "sg:classifiers":[
        {
            "category":"Shopping",
            "subcategory":"Jewelry",
            "type":"Retail Goods"
        }
    ],
    "sg:phone":"+1 819 477 3738",
    "sg:postcode":"J2B 1B4",
    "sg:province":"QC",
    "sg:tags":[
        "jeweler"
    ],
    "wof:name":"Bijouterie Bg Brenda Enrg",
    "wof:placetype":"venue"
},
  "geometry": {"coordinates":[-72.4832687378,45.8819503784],"type":"Point"}
}