{
  "type": "Feature",
  "properties": {
    "addr:full":"Richmond BC V6X 2H4",
    "addr:postcode":"v6x 2h4",
    "iso:country":"CA",
    "sg:city":"Richmond",
    "sg:classifiers":[
        {
            "category":"Retail",
            "subcategory":"Car Wash",
            "type":"Services"
        }
    ],
    "sg:phone":"+1 604 821 0040",
    "sg:postcode":"V6X 2H4",
    "sg:province":"BC",
    "sg:tags":[
        "polishing",
        "automobile",
        "washing",
        "detail"
    ],
    "wof:name":"Sparkle Car Wash",
    "wof:placetype":"venue"
},
  "geometry": {"coordinates":[-123.128250122,49.1922531128],"type":"Point"}
}