{
  "type": "Feature",
  "properties": {
    "addr:full":"1053 Carling Ave Ottawa ON K1Y 4E9",
    "addr:housenumber":"1053",
    "addr:postcode":"k1y 4e9",
    "addr:street":"Carling Ave",
    "iso:country":"CA",
    "sg:address":"1053 Carling Ave",
    "sg:city":"Ottawa",
    "sg:classifiers":[
        {
            "category":"Shopping",
            "subcategory":"Pharmacy",
            "type":"Retail Goods"
        }
    ],
    "sg:phone":"+1 613 761 4157",
    "sg:postcode":"K1Y 4E9",
    "sg:province":"ON",
    "wof:name":"Clinic Pharmacy",
    "wof:placetype":"venue"
},
  "geometry": {"coordinates":[-75.71931499999999,45.392708],"type":"Point"}
}