{
  "type": "Feature",
  "properties": {
    "iso:country":"CA",
    "sg:address":"1232 Rue Lachaine",
    "sg:city":"Laval",
    "sg:classifiers":[
        {
            "category":"Retail",
            "subcategory":"Auto Repair",
            "type":"Services"
        }
    ],
    "sg:phone":"+1 450 661 6884",
    "sg:postcode":"H7C 2N7",
    "sg:province":"QC",
    "sg:tags":[
        "repairing",
        "automobile"
    ],
    "wof:name":"Abs Automobile",
    "wof:placetype":"venue"
},
  "geometry": {"coordinates":[-73.657997,45.616768],"type":"Point"}
}