{
  "type": "Feature",
  "properties": {
    "iso:country":"CA",
    "sg:address":"371 Cloverdale Crt",
    "sg:city":"Newmarket",
    "sg:classifiers":[
        {
            "category":"Shopping",
            "type":"Retail Goods"
        }
    ],
    "sg:phone":"+1 905 853 6282",
    "sg:postcode":"L3Y 1C8",
    "sg:province":"ON",
    "sg:tags":[
        "equipment",
        "telephone",
        "supply"
    ],
    "wof:name":"Lowery Communications Ltd",
    "wof:placetype":"venue"
},
  "geometry": {"coordinates":[-79.46022,44.045296],"type":"Point"}
}