{
  "type": "Feature",
  "properties": {
    "iso:country":"CA",
    "sg:address":"253 Rue Garnier",
    "sg:city":"Saint-Romuald",
    "sg:classifiers":[
        {
            "category":"Organizations",
            "subcategory":"Professional Association",
            "type":"Services"
        }
    ],
    "sg:phone":"+1 418 834 5773",
    "sg:postcode":"G6W 3N7",
    "sg:province":"QC",
    "sg:tags":[
        "social",
        "welfare"
    ],
    "wof:name":"Centres Jeunesse Chaudiere",
    "wof:placetype":"venue"
},
  "geometry": {"coordinates":[-71.24695587159999,46.7499732971],"type":"Point"}
}