{
  "type": "Feature",
  "properties": {
    "iso:country":"CA",
    "sg:address":"11099 Currie Rd RR 2",
    "sg:city":"Dutton",
    "sg:classifiers":[
        {
            "category":"Freight",
            "type":"Transportation"
        }
    ],
    "sg:phone":"+1 519 762 2142",
    "sg:postcode":"N0L 1J0",
    "sg:province":"ON",
    "sg:tags":[
        "trucking"
    ],
    "wof:name":"Earl Mac Donald & Son Trnsprt",
    "wof:placetype":"venue"
},
  "geometry": {"coordinates":[-81.5020370483,42.6631813049],"type":"Point"}
}