{
  "type": "Feature",
  "properties": {
    "iso:country":"CA",
    "sg:city":"Sainte-Foy",
    "sg:classifiers":[
        {
            "category":"Communications",
            "subcategory":"Film & Video Production",
            "type":"Services"
        }
    ],
    "sg:phone":"+1 418 682 8204",
    "sg:postcode":"G1N 4P4",
    "sg:province":"QC",
    "sg:tags":[
        "taping"
    ],
    "wof:name":"Sport-Action Video Inc",
    "wof:placetype":"venue"
},
  "geometry": {"coordinates":[-71.288216,46.791302],"type":"Point"}
}