{
  "type": "Feature",
  "properties": {
    "addr:full":"Edmonton AB T5T 3J7",
    "addr:postcode":"t5t 3j7",
    "iso:country":"CA",
    "sg:city":"Edmonton",
    "sg:classifiers":[
        {
            "category":"Shopping",
            "type":"Retail Goods"
        }
    ],
    "sg:phone":"+1 780 444 1362",
    "sg:postcode":"T5T 3J7",
    "sg:province":"AB",
    "sg:tags":[
        "cosmetic",
        "perfume"
    ],
    "wof:name":"Merle Norman Cosmetics",
    "wof:placetype":"venue"
},
  "geometry": {"coordinates":[-113.615601,53.523586],"type":"Point"}
}