{
  "type": "Feature",
  "properties": {
    "addr:full":"RR 1 Sundre AB T0M 1X0",
    "addr:postcode":"t0m 1x0",
    "addr:street":"Rr 1",
    "iso:country":"CA",
    "sg:address":"RR 1",
    "sg:city":"Sundre",
    "sg:classifiers":[
        {
            "category":"Recreation",
            "type":"Entertainment"
        }
    ],
    "sg:phone":"+1 403 556 4010",
    "sg:postcode":"T0M 1X0",
    "sg:province":"AB",
    "sg:tags":[
        "course",
        "golf"
    ],
    "wof:name":"Forest Heights Golf Course",
    "wof:placetype":"venue"
},
  "geometry": {"coordinates":[-114.641212,51.797192],"type":"Point"}
}