{
  "type": "Feature",
  "properties": {
    "addr:full":"4604 49 Ave Rocky Mountain House AB T4T 1E1",
    "addr:housenumber":"4604",
    "addr:postcode":"t4t 1e1",
    "addr:street":"49 Ave",
    "iso:country":"CA",
    "sg:address":"4604 49 Ave",
    "sg:city":"Rocky Mountain House",
    "sg:classifiers":[
        {
            "category":"Social Services",
            "subcategory":"Child Care",
            "type":"Services"
        }
    ],
    "sg:phone":"+1 403 845 7600",
    "sg:postcode":"T4T 1E1",
    "sg:province":"AB",
    "sg:tags":[
        "kindergarten",
        "academic",
        "school",
        "montessori"
    ],
    "wof:name":"Cookie Jar Preschool",
    "wof:placetype":"venue"
},
  "geometry": {"coordinates":[-114.913544,52.372936],"type":"Point"}
}