{
  "type": "Feature",
  "properties": {
    "addr:full":"2485 King George Hwy Miramichi NB E1V 6W3",
    "addr:housenumber":"2485",
    "addr:postcode":"e1v 6w3",
    "addr:street":"King George Hwy",
    "iso:country":"CA",
    "sg:address":"2485 King George Hwy",
    "sg:city":"Miramichi",
    "sg:classifiers":[
        {
            "category":"Food & Beverages",
            "subcategory":"Groceries & Convenience Stores",
            "type":"Retail Goods"
        }
    ],
    "sg:phone":"+1 506 778 2404",
    "sg:postcode":"E1V 6W3",
    "sg:province":"NB",
    "sg:tags":[
        "grocer"
    ],
    "wof:name":"Sobeys Inc",
    "wof:placetype":"venue"
},
  "geometry": {"coordinates":[-65.4898757935,47.0308265686],"type":"Point"}
}