{
  "type": "Feature",
  "properties": {
    "addr:full":"220 Amber St Markham ON L3R 3J8",
    "addr:housenumber":"220",
    "addr:postcode":"l3r 3j8",
    "addr:street":"Amber St",
    "iso:country":"CA",
    "sg:address":"220 Amber St",
    "sg:city":"Markham",
    "sg:classifiers":[
        {
            "category":"Manufacturing",
            "subcategory":"Tools & Machinery",
            "type":"Manufacturing & Wholesale Goods"
        }
    ],
    "sg:phone":"+1 905 477 4707",
    "sg:postcode":"L3R 3J8",
    "sg:province":"ON",
    "sg:tags":[
        "die",
        "cutting"
    ],
    "wof:name":"Kurtz Enterprises Ltd",
    "wof:placetype":"venue"
},
  "geometry": {"coordinates":[-79.333664,43.82785],"type":"Point"}
}