{
  "type": "Feature",
  "properties": {
    "addr:full":"437 Av Arnaud Sept-Iles QC G4R 3B3",
    "addr:housenumber":"437",
    "addr:postcode":"g4r 3b3",
    "addr:street":"Av Arnaud Sept-Iles",
    "iso:country":"CA",
    "sg:address":"437 Av Arnaud",
    "sg:city":"Sept-Iles",
    "sg:classifiers":[
        {
            "category":"Communications",
            "subcategory":"Radio Station",
            "type":"Services"
        }
    ],
    "sg:phone":"+1 418 962 3838",
    "sg:postcode":"G4R 3B3",
    "sg:province":"QC",
    "sg:tags":[
        "company",
        "broadcasting"
    ],
    "wof:name":"Ckcn",
    "wof:placetype":"venue"
},
  "geometry": {"coordinates":[-66.386978,50.204708],"type":"Point"}
}