{
  "type": "Feature",
  "properties": {
    "iso:country":"CA",
    "sg:address":"502 Springbank Dr",
    "sg:city":"London",
    "sg:classifiers":[
        {
            "category":"Home & Garden",
            "subcategory":"Garden Supply",
            "type":"Retail Goods"
        }
    ],
    "sg:phone":"+1 519 657 0745",
    "sg:postcode":"N6J 1G8",
    "sg:province":"ON",
    "sg:tags":[
        "house",
        "bird",
        "feeder"
    ],
    "wof:name":"Wild Birds Unlimited",
    "wof:placetype":"venue"
},
  "geometry": {"coordinates":[-81.28848266599999,42.9656600952],"type":"Point"}
}