{
  "type": "Feature",
  "properties": {
    "addr:full":"Mississauga ON L5L 4X4",
    "addr:postcode":"l5l 4x4",
    "iso:country":"CA",
    "sg:city":"Mississauga",
    "sg:classifiers":[
        {
            "category":"Utilities",
            "subcategory":"Mobile Phone",
            "type":"Services"
        }
    ],
    "sg:phone":"+1 905 607 4567",
    "sg:postcode":"L5L 4X4",
    "sg:province":"ON",
    "sg:tags":[
        "equipment",
        "paging",
        "signaling",
        "system"
    ],
    "wof:name":"Silver Com Distribution Inc",
    "wof:placetype":"venue"
},
  "geometry": {"coordinates":[-79.70966300000001,43.539207],"type":"Point"}
}