{
  "type": "Feature",
  "properties": {
    "addr:full":"3417 Rue Ontario E Montreal QC H1W 1R1",
    "addr:housenumber":"3417",
    "addr:postcode":"h1w 1r1",
    "addr:street":"Rue Ontario E",
    "iso:country":"CA",
    "sg:address":"3417 Rue Ontario E",
    "sg:city":"Montreal",
    "sg:classifiers":[
        {
            "category":"Restaurant",
            "type":"Food & Drink"
        }
    ],
    "sg:phone":"+1 514 523 0931",
    "sg:postcode":"H1W 1R1",
    "sg:province":"QC",
    "wof:name":"Davidson Lunch Inc",
    "wof:placetype":"venue"
},
  "geometry": {"coordinates":[-73.5461730957,45.5433197021],"type":"Point"}
}