{
  "type": "Feature",
  "properties": {
    "addr:full":"104 Main St Bruce AB T0B 0R0",
    "addr:housenumber":"104",
    "addr:postcode":"t0b 0r0",
    "addr:street":"Main St",
    "iso:country":"CA",
    "sg:address":"104 Main St",
    "sg:city":"Bruce",
    "sg:classifiers":[
        {
            "category":"Travel",
            "subcategory":"Hotels & Motels",
            "type":"Entertainment"
        }
    ],
    "sg:phone":"+1 780 688 3922",
    "sg:postcode":"T0B 0R0",
    "sg:province":"AB",
    "wof:name":"Bruce Hotel",
    "wof:placetype":"venue"
},
  "geometry": {"coordinates":[-112.039162,53.172821],"type":"Point"}
}