{
  "type": "Feature",
  "properties": {
    "addr:full":"Toronto ON M4P 1L7",
    "addr:postcode":"m4p 1l7",
    "iso:country":"CA",
    "sg:city":"Toronto",
    "sg:classifiers":[
        {
            "category":"Social Services",
            "type":"Services"
        }
    ],
    "sg:phone":"+1 416 487 7475",
    "sg:postcode":"M4P 1L7",
    "sg:province":"ON",
    "sg:tags":[
        "counselor",
        "marriage",
        "family"
    ],
    "wof:name":"Bolger, Elizabeth",
    "wof:placetype":"venue"
},
  "geometry": {"coordinates":[-79.38685599999999,43.70895],"type":"Point"}
}