{
  "type": "Feature",
  "properties": {
    "iso:country":"CA",
    "sg:address":"4051 Rue Saint-Andre",
    "sg:city":"Montreal",
    "sg:classifiers":[
        {
            "category":"Restaurant",
            "type":"Food & Drink"
        }
    ],
    "sg:phone":"+1 514 524 5771",
    "sg:postcode":"H2L 3W4",
    "sg:province":"QC",
    "wof:name":"Famille Vietnamienne",
    "wof:placetype":"venue"
},
  "geometry": {"coordinates":[-73.573708,45.523483],"type":"Point"}
}