{
  "type": "Feature",
  "properties": {
    "addr:full":"5 Rue Principale E Biencourt QC G0K 1T0",
    "addr:housenumber":"5",
    "addr:postcode":"g0k 1t0",
    "addr:street":"Rue Principale E",
    "iso:country":"CA",
    "sg:address":"5 Rue Principale E",
    "sg:city":"Biencourt",
    "sg:classifiers":[
        {
            "category":"Education",
            "subcategory":"School",
            "type":"Public Place"
        }
    ],
    "sg:phone":"+1 418 499 2805",
    "sg:postcode":"G0K 1T0",
    "sg:province":"QC",
    "wof:name":"Ecole LA Source",
    "wof:placetype":"venue"
},
  "geometry": {"coordinates":[-68.60492706300001,47.9366836548],"type":"Point"}
}