{
  "type": "Feature",
  "properties": {
    "addr:full":"401 1 Ave S Lethbridge AB T1J 4L8",
    "addr:housenumber":"401",
    "addr:postcode":"t1j 4l8",
    "addr:street":"1 Ave S",
    "iso:country":"CA",
    "sg:address":"401 1 Ave S",
    "sg:city":"Lethbridge",
    "sg:classifiers":[
        {
            "category":"Travel",
            "subcategory":"Travel Agent",
            "type":"Entertainment"
        }
    ],
    "sg:phone":"+1 403 327 4609",
    "sg:postcode":"T1J 4L8",
    "sg:province":"AB",
    "sg:tags":[
        "agency",
        "bureau"
    ],
    "wof:name":"Sears Travel Svc",
    "wof:placetype":"venue"
},
  "geometry": {"coordinates":[-112.841965,49.697948],"type":"Point"}
}