{
  "type": "Feature",
  "properties": {
    "iso:country":"CA",
    "sg:city":"Toronto",
    "sg:classifiers":[
        {
            "category":"Professional",
            "subcategory":"Business Services",
            "type":"Services"
        }
    ],
    "sg:phone":"+1 416 410 7570",
    "sg:postcode":"M5E 1W5",
    "sg:province":"ON",
    "sg:tags":[
        "arbitration"
    ],
    "wof:name":"Frank Mc Lean Mediator",
    "wof:placetype":"venue"
},
  "geometry": {"coordinates":[-79.3753356934,43.6461639404],"type":"Point"}
}