{
  "type": "Feature",
  "properties": {
    "addr:full":"4441 Sheppard Ave E Scarborough ON M1S 1V3",
    "addr:housenumber":"4441",
    "addr:postcode":"m1s 1v3",
    "addr:street":"Sheppard Ave E",
    "iso:country":"CA",
    "sg:address":"4441 Sheppard Ave E",
    "sg:city":"Scarborough",
    "sg:classifiers":[
        {
            "category":"Professional",
            "subcategory":"Accounting & Tax Preparation",
            "type":"Services"
        }
    ],
    "sg:phone":"+1 416 299 8500",
    "sg:postcode":"M1S 1V3",
    "sg:province":"ON",
    "sg:tags":[
        "bookkeeping",
        "general"
    ],
    "wof:name":"Truckers Bookkeeping & Accting",
    "wof:placetype":"venue"
},
  "geometry": {"coordinates":[-79.26712000000001,43.787685],"type":"Point"}
}