{
  "type": "Feature",
  "properties": {
    "addr:full":"550 Rue Saint-Jean Longueuil QC J4H 2Y4",
    "addr:housenumber":"550",
    "addr:postcode":"j4h 2y4",
    "addr:street":"Rue Saint-Jean",
    "iso:country":"CA",
    "sg:address":"550 Rue Saint-Jean",
    "sg:city":"Longueuil",
    "sg:classifiers":[
        {
            "category":"Wholesale",
            "subcategory":"Machinery & Supplies",
            "type":"Manufacturing & Wholesale Goods"
        }
    ],
    "sg:phone":"+1 450 674 4341",
    "sg:postcode":"J4H 2Y4",
    "sg:province":"QC",
    "sg:tags":[
        "packaging",
        "baling",
        "equipment"
    ],
    "wof:name":"Distributions Mirage Pharma",
    "wof:placetype":"venue"
},
  "geometry": {"coordinates":[-73.505402,45.534573],"type":"Point"}
}