{
  "type": "Feature",
  "properties": {
    "addr:full":"905 Rue Andre-Soucy Pointe-Calumet QC J0N 1G2",
    "addr:housenumber":"905",
    "addr:postcode":"j0n 1g2",
    "addr:street":"Rue Andre-Soucy",
    "iso:country":"CA",
    "sg:address":"905 Rue Andre-Soucy",
    "sg:city":"Pointe-Calumet",
    "sg:classifiers":[
        {
            "category":"Education",
            "subcategory":"Special Training",
            "type":"Public Place"
        }
    ],
    "sg:phone":"+1 450 623 0288",
    "sg:postcode":"J0N 1G2",
    "sg:province":"QC",
    "sg:tags":[
        "instruction",
        "music"
    ],
    "wof:name":"Ecole DE Musique Musinote",
    "wof:placetype":"venue"
},
  "geometry": {"coordinates":[-73.9750747681,45.498260498],"type":"Point"}
}