{
  "type": "Feature",
  "properties": {
    "addr:full":"Redcliff AB T0J 2P0",
    "addr:postcode":"t0j 2p0",
    "iso:country":"CA",
    "sg:city":"Redcliff",
    "sg:classifiers":[
        {
            "category":"Retail",
            "subcategory":"Car Wash",
            "type":"Services"
        }
    ],
    "sg:phone":"+1 403 548 8182",
    "sg:postcode":"T0J 2P0",
    "sg:province":"AB",
    "sg:tags":[
        "polishing",
        "truck",
        "washing"
    ],
    "wof:name":"Mud Dogs Truck Wash",
    "wof:placetype":"venue"
},
  "geometry": {"coordinates":[-110.76480100000001,50.07465],"type":"Point"}
}