{
  "type": "Feature",
  "properties": {
    "addr:full":"79 Manning Ave Toronto ON M6J 2K6",
    "addr:housenumber":"79",
    "addr:postcode":"m6j 2k6",
    "addr:street":"Manning Ave",
    "iso:country":"CA",
    "sg:address":"79 Manning Ave",
    "sg:city":"Toronto",
    "sg:classifiers":[
        {
            "category":"Education",
            "subcategory":"School",
            "type":"Public Place"
        }
    ],
    "sg:phone":"+1 416 393 1830",
    "sg:postcode":"M6J 2K6",
    "sg:province":"ON",
    "wof:name":"Charles G Fraser Junior Ps",
    "wof:placetype":"venue"
},
  "geometry": {"coordinates":[-79.40960699999999,43.648514],"type":"Point"}
}