{
  "type": "Feature",
  "properties": {
    "addr:full":"9623 Sylvester Rd Mission BC V2V 7K6",
    "addr:housenumber":"9623",
    "addr:postcode":"v2v 7k6",
    "addr:street":"Sylvester Rd",
    "iso:country":"CA",
    "sg:address":"9623 Sylvester Rd",
    "sg:city":"Mission",
    "sg:classifiers":[
        {
            "category":"Wholesale",
            "subcategory":"Plants",
            "type":"Manufacturing & Wholesale Goods"
        }
    ],
    "sg:phone":"+1 604 826 3537",
    "sg:postcode":"V2V 7K6",
    "sg:province":"BC",
    "sg:tags":[
        "nursery",
        "tree"
    ],
    "wof:name":"Sidhu & Sons Nursery",
    "wof:placetype":"venue"
},
  "geometry": {"coordinates":[-122.28280599999999,49.159996],"type":"Point"}
}