{
  "type": "Feature",
  "properties": {
    "addr:full":"1555 Rue Rancourt Lasalle QC H8N 1R7",
    "addr:housenumber":"1555",
    "addr:postcode":"h8n 1r7",
    "addr:street":"Rue Rancourt",
    "iso:country":"CA",
    "sg:address":"1555 Rue Rancourt",
    "sg:city":"Lasalle",
    "sg:classifiers":[
        {
            "category":"Education",
            "subcategory":"School",
            "type":"Public Place"
        }
    ],
    "sg:phone":"+1 514 595 2048",
    "sg:postcode":"H8N 1R7",
    "sg:province":"QC",
    "wof:name":"Lasalle Elementary Senior Schl",
    "wof:placetype":"venue"
},
  "geometry": {"coordinates":[-73.62687683110001,45.4286804199],"type":"Point"}
}