{
  "type": "Feature",
  "properties": {
    "addr:full":"7405 Kingsway Burnaby BC V3N 3B8",
    "addr:housenumber":"7405",
    "addr:postcode":"v3n 3b8",
    "addr:street":"Kingsway",
    "iso:country":"CA",
    "sg:address":"7405 Kingsway",
    "sg:city":"Burnaby",
    "sg:classifiers":[
        {
            "category":"Retail",
            "subcategory":"Auto Repair",
            "type":"Services"
        }
    ],
    "sg:phone":"+1 604 522 9874",
    "sg:postcode":"V3N 3B8",
    "sg:province":"BC",
    "sg:tags":[
        "repairing",
        "automobile"
    ],
    "wof:name":"Lavigne's Engine Rebuilders",
    "wof:placetype":"venue"
},
  "geometry": {"coordinates":[-122.948181152,49.2179222107],"type":"Point"}
}