{
  "type": "Feature",
  "properties": {
    "addr:full":"301 E 1st St Revelstoke BC V0E 2S0",
    "addr:housenumber":"301",
    "addr:postcode":"v0e 2s0",
    "addr:street":"E 1St St",
    "iso:country":"CA",
    "sg:address":"301 E 1st St",
    "sg:city":"Revelstoke",
    "sg:classifiers":[
        {
            "category":"Personal",
            "type":"Services"
        }
    ],
    "sg:phone":"+1 250 837 6677",
    "sg:postcode":"V0E 2S0",
    "sg:province":"BC",
    "sg:tags":[
        "therapist",
        "massage"
    ],
    "wof:name":"Revelstoke Massage Therapy",
    "wof:placetype":"venue"
},
  "geometry": {"coordinates":[-118.192955017,50.9972686768],"type":"Point"}
}