{
  "type": "Feature",
  "properties": {
    "addr:full":"1690 Sismet Rd Mississauga ON L4W 1R4",
    "addr:housenumber":"1690",
    "addr:postcode":"l4w 1r4",
    "addr:street":"Sismet Rd",
    "iso:country":"CA",
    "sg:address":"1690 Sismet Rd",
    "sg:city":"Mississauga",
    "sg:classifiers":[
        {
            "category":"Retail",
            "subcategory":"Auto Repair",
            "type":"Services"
        }
    ],
    "sg:phone":"+1 905 625 7805",
    "sg:postcode":"L4W 1R4",
    "sg:province":"ON",
    "sg:tags":[
        "body",
        "automobile",
        "painting"
    ],
    "wof:name":"Shawson Auto Body Repairs",
    "wof:placetype":"venue"
},
  "geometry": {"coordinates":[-79.6214981079,43.6453514099],"type":"Point"}
}