{
  "type": "Feature",
  "properties": {
    "addr:full":"789 Saunders Lane Brentwood Bay BC V8M 1C5",
    "addr:housenumber":"789",
    "addr:postcode":"v8m 1c5",
    "addr:street":"Saunders Lane",
    "iso:country":"CA",
    "sg:address":"789 Saunders Lane",
    "sg:city":"Brentwood Bay",
    "sg:classifiers":[
        {
            "category":"Recreation",
            "subcategory":"Marina",
            "type":"Entertainment"
        }
    ],
    "sg:phone":"+1 250 652 2211",
    "sg:postcode":"V8M 1C5",
    "sg:province":"BC",
    "wof:name":"Brentwood's Portside Marina",
    "wof:placetype":"venue"
},
  "geometry": {"coordinates":[-123.46661400000001,48.57811],"type":"Point"}
}