{
  "type": "Feature",
  "properties": {
    "addr:full":"600 Main St S Exeter ON N0M 1S1",
    "addr:housenumber":"600",
    "addr:postcode":"n0m 1s1",
    "addr:street":"Main St S",
    "iso:country":"CA",
    "sg:address":"600 Main St S",
    "sg:city":"Exeter",
    "sg:classifiers":[
        {
            "category":"Home & Garden",
            "subcategory":"Garden Supply",
            "type":"Retail Goods"
        }
    ],
    "sg:phone":"+1 519 235 2757",
    "sg:postcode":"N0M 1S1",
    "sg:province":"ON",
    "sg:tags":[
        "lawn",
        "snowmobile"
    ],
    "wof:name":"Becker Power & Leisure Prods",
    "wof:placetype":"venue"
},
  "geometry": {"coordinates":[-81.4792709351,43.3415603638],"type":"Point"}
}