{
  "type": "Feature",
  "properties": {
    "addr:full":"3790 Highway 7 Woodbridge ON L4L 9C3",
    "addr:housenumber":"3790",
    "addr:postcode":"l4l 9c3",
    "addr:street":"Highway 7",
    "iso:country":"CA",
    "sg:address":"3790 Highway 7",
    "sg:city":"Woodbridge",
    "sg:classifiers":[
        {
            "category":"Autos & Motor Vehicles",
            "subcategory":"Automobile Sales",
            "type":"Retail Goods"
        }
    ],
    "sg:phone":"+1 905 851 2851",
    "sg:postcode":"L4L 9C3",
    "sg:province":"ON",
    "sg:tags":[
        "car",
        "dealer"
    ],
    "wof:name":"Pine View Pontiac Buick Gmc",
    "wof:placetype":"venue"
},
  "geometry": {"coordinates":[-79.5921554565,43.7850646973],"type":"Point"}
}