{
  "type": "Feature",
  "properties": {
    "addr:full":"996 Queen St W Toronto ON M6J 1H1",
    "addr:housenumber":"996",
    "addr:postcode":"m6j 1h1",
    "addr:street":"Queen St W",
    "iso:country":"CA",
    "sg:address":"996 Queen St W",
    "sg:city":"Toronto",
    "sg:classifiers":[
        {
            "category":"Restaurant",
            "type":"Food & Drink"
        }
    ],
    "sg:phone":"+1 416 535 4955",
    "sg:postcode":"M6J 1H1",
    "sg:province":"ON",
    "wof:name":"Tom Restaurant",
    "wof:placetype":"venue"
},
  "geometry": {"coordinates":[-79.4184188843,43.644405365],"type":"Point"}
}