{
  "type": "Feature",
  "properties": {
    "addr:full":"13 Market Sq Napanee ON K7R 1J4",
    "addr:housenumber":"13",
    "addr:postcode":"k7r 1j4",
    "addr:street":"Market Sq",
    "iso:country":"CA",
    "sg:address":"13 Market Sq",
    "sg:city":"Napanee",
    "sg:classifiers":[
        {
            "category":"Education",
            "subcategory":"School",
            "type":"Public Place"
        }
    ],
    "sg:phone":"+1 613 354 4603",
    "sg:postcode":"K7R 1J4",
    "sg:province":"ON",
    "sg:tags":[
        "instruction",
        "dancing"
    ],
    "wof:name":"Prestige Dance Academy",
    "wof:placetype":"venue"
},
  "geometry": {"coordinates":[-76.9512176514,44.2483520508],"type":"Point"}
}