{
  "type": "Feature",
  "properties": {
    "iso:country":"CA",
    "sg:address":"192 Rue Principale",
    "sg:city":"Saint-Damase",
    "sg:classifiers":[
        {
            "category":"Professional",
            "subcategory":"Business Services",
            "type":"Services"
        }
    ],
    "sg:phone":"+1 450 797 2334",
    "sg:postcode":"J0H 1J0",
    "sg:province":"QC",
    "sg:tags":[
        "notary"
    ],
    "wof:name":"Sante Jeredque Ctr",
    "wof:placetype":"venue"
},
  "geometry": {"coordinates":[-73.01029968260001,45.525604248],"type":"Point"}
}