{
  "type": "Feature",
  "properties": {
    "addr:full":"3065 Robie St Halifax NS B3K 4P6",
    "addr:housenumber":"3065",
    "addr:postcode":"b3k 4p6",
    "addr:street":"Robie St",
    "iso:country":"CA",
    "sg:address":"3065 Robie St",
    "sg:city":"Halifax",
    "sg:classifiers":[
        {
            "category":"Autos & Motor Vehicles",
            "subcategory":"Auto Supplies",
            "type":"Retail Goods"
        }
    ],
    "sg:phone":"+1 902 493 8344",
    "sg:postcode":"B3K 4P6",
    "sg:province":"NS",
    "sg:tags":[
        "automobile",
        "parts"
    ],
    "wof:name":"Carquest",
    "wof:placetype":"venue"
},
  "geometry": {"coordinates":[-63.601395,44.659245],"type":"Point"}
}