{
  "type": "Feature",
  "properties": {
    "addr:full":"Edmonton AB T5J 0L6",
    "addr:postcode":"t5j 0l6",
    "iso:country":"CA",
    "sg:city":"Edmonton",
    "sg:classifiers":[
        {
            "category":"Professional",
            "subcategory":"Lawyer & Legal Services",
            "type":"Services"
        }
    ],
    "sg:phone":"+1 780 424 3270",
    "sg:postcode":"T5J 0L6",
    "sg:province":"AB",
    "sg:tags":[
        "attorney"
    ],
    "wof:name":"Poitras, Ronald W",
    "wof:placetype":"venue"
},
  "geometry": {"coordinates":[-113.48614502,53.5442733765],"type":"Point"}
}