{
  "type": "Feature",
  "properties": {
    "addr:full":"610 Prospect Ave Acme AB T0M 0A0",
    "addr:housenumber":"610",
    "addr:postcode":"t0m 0a0",
    "addr:street":"Prospect Ave",
    "iso:country":"CA",
    "sg:address":"610 Prospect Ave",
    "sg:city":"Acme",
    "sg:classifiers":[
        {
            "category":"Building & Trades",
            "subcategory":"Construction",
            "type":"Services"
        }
    ],
    "sg:phone":"+1 403 546 4364",
    "sg:postcode":"T0M 0A0",
    "sg:province":"AB",
    "sg:tags":[
        "general",
        "contractor"
    ],
    "wof:name":"Mac-Tern Construction Ltd",
    "wof:placetype":"venue"
},
  "geometry": {"coordinates":[-113.514823914,51.4977111816],"type":"Point"}
}