{
  "type": "Feature",
  "properties": {
    "iso:country":"CA",
    "sg:city":"Toronto",
    "sg:classifiers":[
        {
            "category":"Building & Trades",
            "subcategory":"Construction",
            "type":"Services"
        }
    ],
    "sg:phone":"+1 416 487 6308",
    "sg:postcode":"M4V 2B9",
    "sg:province":"ON",
    "sg:tags":[
        "painter"
    ],
    "wof:name":"Scr Svc",
    "wof:placetype":"venue"
},
  "geometry": {"coordinates":[-79.399826,43.696209],"type":"Point"}
}