{
  "type": "Feature",
  "properties": {
    "addr:full":"330 Highway 7 E Richmond Hill ON L4B 3P8",
    "addr:housenumber":"330;e",
    "addr:postcode":"l4b 3p8",
    "addr:street":"Highway 7",
    "iso:country":"CA",
    "sg:address":"330 Highway 7 E",
    "sg:city":"Richmond Hill",
    "sg:classifiers":[
        {
            "category":"Professional",
            "subcategory":"Computer Services",
            "type":"Services"
        }
    ],
    "sg:phone":"+1 905 763 0064",
    "sg:postcode":"L4B 3P8",
    "sg:province":"ON",
    "sg:tags":[
        "consultant"
    ],
    "wof:name":"Manco Technologies Inc",
    "wof:placetype":"venue"
},
  "geometry": {"coordinates":[-79.378471,43.846554],"type":"Point"}
}