{
  "type": "Feature",
  "properties": {
    "addr:full":"2191 Rue Du Souvenir Montreal QC H3H 1R9",
    "addr:housenumber":"2191",
    "addr:postcode":"h3h 1r9",
    "addr:street":"Rue Du Souvenir",
    "iso:country":"CA",
    "sg:address":"2191 Rue Du Souvenir",
    "sg:city":"Montreal",
    "sg:classifiers":[
        {
            "category":"Retail",
            "subcategory":"Portrait Studio",
            "type":"Services"
        }
    ],
    "sg:phone":"+1 514 935 4192",
    "sg:postcode":"H3H 1R9",
    "sg:province":"QC",
    "sg:tags":[
        "photographer"
    ],
    "wof:name":"Studio Cumming",
    "wof:placetype":"venue"
},
  "geometry": {"coordinates":[-73.580101,45.48843],"type":"Point"}
}