{
  "type": "Feature",
  "properties": {
    "addr:full":"108 Main St N Moose Jaw SK S6H 3J7",
    "addr:housenumber":"108",
    "addr:postcode":"s6h 3j7",
    "addr:street":"Main St N",
    "iso:country":"CA",
    "sg:address":"108 Main St N",
    "sg:city":"Moose Jaw",
    "sg:classifiers":[
        {
            "category":"Shopping",
            "subcategory":"Hobbies, Toys, & Games",
            "type":"Retail Goods"
        }
    ],
    "sg:phone":"+1 306 692 4646",
    "sg:postcode":"S6H 3J7",
    "sg:province":"SK",
    "sg:tags":[
        "shop",
        "craft",
        "gift"
    ],
    "wof:name":"Lastings Impressions Gift",
    "wof:placetype":"venue"
},
  "geometry": {"coordinates":[-105.53494262700001,50.3908653259],"type":"Point"}
}