{
  "type": "Feature",
  "properties": {
    "addr:full":"Burnaby BC V5H 4M1",
    "addr:postcode":"v5h 4m1",
    "iso:country":"CA",
    "sg:city":"Burnaby",
    "sg:classifiers":[
        {
            "category":"Shopping",
            "subcategory":"Gifts & Souvenirs",
            "type":"Retail Goods"
        }
    ],
    "sg:phone":"+1 604 432 9979",
    "sg:postcode":"V5H 4M1",
    "sg:province":"BC",
    "sg:tags":[
        "collectible"
    ],
    "wof:name":"Collectors Den Inc",
    "wof:placetype":"venue"
},
  "geometry": {"coordinates":[-122.999412537,49.2283477783],"type":"Point"}
}