{
  "type": "Feature",
  "properties": {
    "iso:country":"CA",
    "sg:address":"2956 Fleet St",
    "sg:city":"Coquitlam",
    "sg:classifiers":[
        {
            "category":"Social Services",
            "subcategory":"Job Training",
            "type":"Services"
        }
    ],
    "sg:phone":"+1 604 464 2382",
    "sg:postcode":"V3C 3R8",
    "sg:province":"BC",
    "sg:tags":[
        "career",
        "counseling",
        "vocational"
    ],
    "wof:name":"Life Strategies Ltd",
    "wof:placetype":"venue"
},
  "geometry": {"coordinates":[-122.812347,49.262146],"type":"Point"}
}