{
  "type": "Feature",
  "properties": {
    "addr:full":"30 Mohawk Rd London ON N6G 2P5",
    "addr:housenumber":"30",
    "addr:postcode":"n6g 2p5",
    "addr:street":"Mohawk Rd",
    "iso:country":"CA",
    "sg:address":"30 Mohawk Rd",
    "sg:city":"London",
    "sg:classifiers":[
        {
            "category":"Health Services",
            "subcategory":"Doctor",
            "type":"Services"
        }
    ],
    "sg:phone":"+1 519 858 0251",
    "sg:postcode":"N6G 2P5",
    "sg:province":"ON",
    "sg:tags":[
        "physician",
        "surgeon"
    ],
    "wof:name":"Silcox, Jo Ann MD",
    "wof:placetype":"venue"
},
  "geometry": {"coordinates":[-81.284019,43.022621],"type":"Point"}
}