{
  "type": "Feature",
  "properties": {
    "iso:country":"CA",
    "sg:address":"3355 Rue Rolland",
    "sg:city":"Sainte-Adele",
    "sg:classifiers":[
        {
            "category":"Retail",
            "subcategory":"Repair Shop",
            "type":"Services"
        }
    ],
    "sg:phone":"+1 450 229 2158",
    "sg:postcode":"J8B 1E1",
    "sg:province":"QC",
    "sg:tags":[
        "welding"
    ],
    "wof:name":"Atelier Mobile J-G Piche Enr",
    "wof:placetype":"venue"
},
  "geometry": {"coordinates":[-74.1121139526,45.9453659058],"type":"Point"}
}