{
  "type": "Feature",
  "properties": {
    "iso:country":"CA",
    "sg:address":"709 St-Georges",
    "sg:city":"Saint-Bernard",
    "sg:classifiers":[
        {
            "category":"Farming",
            "subcategory":"Farm",
            "type":"Manufacturing & Wholesale Goods"
        }
    ],
    "sg:phone":"+1 418 475 6265",
    "sg:postcode":"G0S 2G0",
    "sg:province":"QC",
    "wof:name":"Porexcel Inc",
    "wof:placetype":"venue"
},
  "geometry": {"coordinates":[-71.17640686039999,46.4721908569],"type":"Point"}
}