{
  "type": "Feature",
  "properties": {
    "addr:full":"566 Main St Durban MB R0L 0P0",
    "addr:housenumber":"566",
    "addr:postcode":"r0l 0p0",
    "addr:street":"Main St",
    "iso:country":"CA",
    "sg:address":"566 Main St",
    "sg:city":"Durban",
    "sg:classifiers":[
        {
            "category":"Organizations",
            "subcategory":"Religious Organization",
            "type":"Services"
        }
    ],
    "sg:phone":"+1 204 539 2271",
    "sg:postcode":"R0L 0P0",
    "sg:province":"MB",
    "sg:tags":[
        "church"
    ],
    "wof:name":"Valley Evangelical Covenant Ch",
    "wof:placetype":"venue"
},
  "geometry": {"coordinates":[-101.435524,51.929279],"type":"Point"}
}