{
  "type": "Feature",
  "properties": {
    "addr:full":"488 Dupont St Toronto ON M6G 1Y7",
    "addr:housenumber":"488",
    "addr:postcode":"m6g 1y7",
    "addr:street":"Dupont St",
    "iso:country":"CA",
    "sg:address":"488 Dupont St",
    "sg:city":"Toronto",
    "sg:classifiers":[
        {
            "category":"Shopping",
            "subcategory":"Computers & Home Electronics",
            "type":"Retail Goods"
        }
    ],
    "sg:phone":"+1 416 533 2001",
    "sg:postcode":"M6G 1Y7",
    "sg:province":"ON",
    "sg:tags":[
        "equipment",
        "dealer"
    ],
    "wof:name":"Cpused",
    "wof:placetype":"venue"
},
  "geometry": {"coordinates":[-79.415024,43.673164],"type":"Point"}
}