{
  "type": "Feature",
  "properties": {
    "addr:full":"540 Rue Labrecque Acton Vale QC J0H 1A0",
    "addr:housenumber":"540",
    "addr:postcode":"j0h 1a0",
    "addr:street":"Rue Labrecque",
    "iso:country":"CA",
    "sg:address":"540 Rue Labrecque",
    "sg:city":"Acton Vale",
    "sg:classifiers":[
        {
            "category":"Arena",
            "subcategory":"Sports Club",
            "type":"Entertainment"
        }
    ],
    "sg:phone":"+1 450 546 7601",
    "sg:postcode":"J0H 1A0",
    "sg:province":"QC",
    "sg:tags":[
        "athletic",
        "fields",
        "stadium",
        "government"
    ],
    "wof:name":"Acton Vale Stade Municipal",
    "wof:placetype":"venue"
},
  "geometry": {"coordinates":[-72.5628356934,45.6419372559],"type":"Point"}
}