{
  "type": "Feature",
  "properties": {
    "addr:full":"5510 26 Ave NE Calgary AB T1Y 6S1",
    "addr:housenumber":"5510",
    "addr:postcode":"t1y 6s1",
    "addr:street":"26 Ave Ne",
    "iso:country":"CA",
    "sg:address":"5510 26 Ave NE",
    "sg:city":"Calgary",
    "sg:classifiers":[
        {
            "category":"Organizations",
            "subcategory":"Religious Organization",
            "type":"Services"
        }
    ],
    "sg:phone":"+1 403 280 9500",
    "sg:postcode":"T1Y 6S1",
    "sg:province":"AB",
    "sg:tags":[
        "church"
    ],
    "wof:name":"Robert Mc Clure United Church",
    "wof:placetype":"venue"
},
  "geometry": {"coordinates":[-113.95581799999999,51.076408],"type":"Point"}
}