{
  "type": "Feature",
  "properties": {
    "addr:full":"841 Henderson Hwy Winnipeg MB R2K 2L4",
    "addr:housenumber":"841",
    "addr:postcode":"r2k 2l4",
    "addr:street":"Henderson Hwy",
    "iso:country":"CA",
    "sg:address":"841 Henderson Hwy",
    "sg:city":"Winnipeg",
    "sg:classifiers":[
        {
            "category":"Personal",
            "subcategory":"Beauty Salon",
            "type":"Services"
        }
    ],
    "sg:phone":"+1 204 661 2389",
    "sg:postcode":"R2K 2L4",
    "sg:province":"MB",
    "wof:name":"Shear Attraction",
    "wof:placetype":"venue"
},
  "geometry": {"coordinates":[-97.10084500000001,49.930565],"type":"Point"}
}