{
  "type": "Feature",
  "properties": {
    "addr:full":"5110 Rue Fairway Lachine QC H8T 1B8",
    "addr:housenumber":"5110",
    "addr:postcode":"h8t 1b8",
    "addr:street":"Rue Fairway",
    "iso:country":"CA",
    "sg:address":"5110 Rue Fairway",
    "sg:city":"Lachine",
    "sg:classifiers":[
        {
            "category":"Freight",
            "type":"Transportation"
        }
    ],
    "sg:phone":"+1 514 631 7925",
    "sg:postcode":"H8T 1B8",
    "sg:province":"QC",
    "sg:tags":[
        "courier"
    ],
    "wof:name":"F B on Board Courier Svc Inc",
    "wof:placetype":"venue"
},
  "geometry": {"coordinates":[-73.7173461914,45.4528808594],"type":"Point"}
}