{
  "type": "Feature",
  "properties": {
    "addr:full":"120 Stanley St Cupar SK S0G 0Y0",
    "addr:housenumber":"120",
    "addr:postcode":"s0g 0y0",
    "addr:street":"Stanley St",
    "iso:country":"CA",
    "sg:address":"120 Stanley St",
    "sg:city":"Cupar",
    "sg:classifiers":[
        {
            "category":"Personal",
            "subcategory":"Beauty Salon",
            "type":"Services"
        }
    ],
    "sg:phone":"+1 306 723 4633",
    "sg:postcode":"S0G 0Y0",
    "sg:province":"SK",
    "wof:name":"Hair Plus",
    "wof:placetype":"venue"
},
  "geometry": {"coordinates":[-104.211624,50.950291],"type":"Point"}
}