{
  "type": "Feature",
  "properties": {
    "iso:country":"CA",
    "sg:address":"925 Alexandra St",
    "sg:city":"Hearst",
    "sg:classifiers":[
        {
            "category":"Government",
            "subcategory":"Office",
            "type":"Public Place"
        }
    ],
    "sg:phone":"+1 705 362 4341",
    "sg:postcode":"P0L 1N0",
    "sg:province":"ON",
    "sg:tags":[
        "child",
        "care",
        "village"
    ],
    "wof:name":"Hearst Childcare Svc",
    "wof:placetype":"venue"
},
  "geometry": {"coordinates":[-83.6662445068,49.6867713928],"type":"Point"}
}