{
  "type": "Feature",
  "properties": {
    "addr:full":"118 Shediac Rd Moncton NB E1A 2R9",
    "addr:housenumber":"118",
    "addr:postcode":"e1a 2r9",
    "addr:street":"Shediac Rd",
    "iso:country":"CA",
    "sg:address":"118 Shediac Rd",
    "sg:city":"Moncton",
    "sg:classifiers":[
        {
            "category":"Personal",
            "subcategory":"Beauty Salon",
            "type":"Services"
        }
    ],
    "sg:phone":"+1 506 858 1909",
    "sg:postcode":"E1A 2R9",
    "sg:province":"NB",
    "wof:name":"Today's Hair Designs",
    "wof:placetype":"venue"
},
  "geometry": {"coordinates":[-64.7625045776,46.1034164429],"type":"Point"}
}