{
  "type": "Feature",
  "properties": {
    "addr:full":"60 Av William-Dobell Baie-Comeau QC G4Z 1T7",
    "addr:postcode":"g4z 1t7",
    "addr:street":"60 Av William-Dobell",
    "iso:country":"CA",
    "sg:address":"60 Av William-Dobell",
    "sg:city":"Baie-Comeau",
    "sg:classifiers":[
        {
            "category":"Home & Garden",
            "subcategory":"Building Materials",
            "type":"Retail Goods"
        }
    ],
    "sg:phone":"+1 418 296 2184",
    "sg:postcode":"G4Z 1T7",
    "sg:province":"QC",
    "sg:tags":[
        "door"
    ],
    "wof:name":"Menuiserie Cote-Nord Inc",
    "wof:placetype":"venue"
},
  "geometry": {"coordinates":[-68.180351,49.216267],"type":"Point"}
}