{
  "type": "Feature",
  "properties": {
    "addr:full":"132 2nd St W Cornwall ON K6J 1G5",
    "addr:housenumber":"132",
    "addr:postcode":"k6j 1g5",
    "addr:street":"2Nd St W",
    "iso:country":"CA",
    "sg:address":"132 2nd St W",
    "sg:city":"Cornwall",
    "sg:classifiers":[
        {
            "category":"Professional",
            "subcategory":"Lawyer & Legal Services",
            "type":"Services"
        }
    ],
    "sg:phone":"+1 613 938 2224",
    "sg:postcode":"K6J 1G5",
    "sg:province":"ON",
    "sg:tags":[
        "attorney"
    ],
    "wof:name":"Wilson Poirier Byrne",
    "wof:placetype":"venue"
},
  "geometry": {"coordinates":[-74.731453,45.017372],"type":"Point"}
}