{
  "type": "Feature",
  "properties": {
    "addr:full":"Yellowknife NT X1A 1G1",
    "addr:postcode":"x1a 1g1",
    "iso:country":"CA",
    "sg:city":"Yellowknife",
    "sg:classifiers":[
        {
            "category":"Government",
            "subcategory":"Office",
            "type":"Public Place"
        }
    ],
    "sg:phone":"+1 867 920 2443",
    "sg:postcode":"X1A 1G1",
    "sg:province":"NT",
    "sg:tags":[
        "senior",
        "citizen"
    ],
    "wof:name":"Aven Manor",
    "wof:placetype":"venue"
},
  "geometry": {"coordinates":[-114.381638,62.449066],"type":"Point"}
}