{
  "type": "Feature",
  "properties": {
    "addr:full":"766 Rue Kirouac Quebec QC G1N 2J4",
    "addr:housenumber":"766",
    "addr:postcode":"g1n 2j4",
    "addr:street":"Rue Kirouac",
    "iso:country":"CA",
    "sg:address":"766 Rue Kirouac",
    "sg:city":"Quebec",
    "sg:classifiers":[
        {
            "category":"Professional",
            "subcategory":"Management & Consulting",
            "type":"Services"
        }
    ],
    "sg:phone":"+1 418 686 4007",
    "sg:postcode":"G1N 2J4",
    "sg:province":"QC",
    "sg:tags":[
        "consultant",
        "educational"
    ],
    "wof:name":"Jeunes Entreprises Du Quebec",
    "wof:placetype":"venue"
},
  "geometry": {"coordinates":[-71.24240112299999,46.8042030334],"type":"Point"}
}