{
  "type": "Feature",
  "properties": {
    "addr:full":"Portland ON K0G 1V0",
    "addr:postcode":"k0g 1v0",
    "iso:country":"CA",
    "sg:city":"Portland",
    "sg:classifiers":[
        {
            "category":"Food & Beverages",
            "subcategory":"Dairy",
            "type":"Retail Goods"
        }
    ],
    "sg:phone":"+1 613 272 2107",
    "sg:postcode":"K0G 1V0",
    "sg:province":"ON",
    "sg:tags":[
        "cheese"
    ],
    "wof:name":"Forfar Dairy Ltd",
    "wof:placetype":"venue"
},
  "geometry": {"coordinates":[-76.1882095337,44.698425293],"type":"Point"}
}