{
  "type": "Feature",
  "properties": {
    "iso:country":"CA",
    "sg:address":"906 Alexandra St",
    "sg:city":"Hearst",
    "sg:classifiers":[
        {
            "category":"Organizations",
            "subcategory":"Religious Organization",
            "type":"Services"
        }
    ],
    "sg:phone":"+1 705 362 7886",
    "sg:postcode":"P0L 1N0",
    "sg:province":"ON",
    "sg:tags":[
        "church"
    ],
    "wof:name":"St Matthew & St Paul Church",
    "wof:placetype":"venue"
},
  "geometry": {"coordinates":[-83.6658325195,49.6870079041],"type":"Point"}
}