{
  "type": "Feature",
  "properties": {
    "addr:full":"Sainte-Foy QC G1N 4K8",
    "addr:postcode":"g1n 4k8",
    "iso:country":"CA",
    "sg:city":"Sainte-Foy",
    "sg:classifiers":[
        {
            "category":"Manufacturing",
            "subcategory":"Tools & Machinery",
            "type":"Manufacturing & Wholesale Goods"
        }
    ],
    "sg:phone":"+1 418 687 7373",
    "sg:postcode":"G1N 4K8",
    "sg:province":"QC",
    "sg:tags":[
        "parts",
        "refrigerating"
    ],
    "wof:name":"Climaref",
    "wof:placetype":"venue"
},
  "geometry": {"coordinates":[-71.269615,46.796223],"type":"Point"}
}