{
  "type": "Feature",
  "properties": {
    "iso:country":"CA",
    "sg:address":"233 Rue Notre-Dame O",
    "sg:city":"Montreal",
    "sg:classifiers":[
        {
            "category":"Restaurant",
            "type":"Food & Drink"
        }
    ],
    "sg:phone":"+1 514 844 9481",
    "sg:postcode":"H2Y 1T4",
    "sg:province":"QC",
    "wof:name":"Da Franco Restorante",
    "wof:placetype":"venue"
},
  "geometry": {"coordinates":[-73.553855896,45.5085983276],"type":"Point"}
}