{
  "type": "Feature",
  "properties": {
    "addr:full":"840 Erie St E Windsor ON N9A 3Y4",
    "addr:housenumber":"840",
    "addr:postcode":"n9a 3y4",
    "addr:street":"Erie St E",
    "iso:country":"CA",
    "sg:address":"840 Erie St E",
    "sg:city":"Windsor",
    "sg:classifiers":[
        {
            "category":"Personal",
            "subcategory":"Beauty Salon",
            "type":"Services"
        }
    ],
    "sg:phone":"+1 519 254 6517",
    "sg:postcode":"N9A 3Y4",
    "sg:province":"ON",
    "wof:name":"Sylvia'a Hair Studio",
    "wof:placetype":"venue"
},
  "geometry": {"coordinates":[-83.02207900000001,42.313213],"type":"Point"}
}