{
  "type": "Feature",
  "properties": {
    "addr:full":"1040 Somerset St W Ottawa ON K1Y 4L3",
    "addr:housenumber":"1040",
    "addr:postcode":"k1y 4l3",
    "addr:street":"Somerset St W",
    "iso:country":"CA",
    "sg:address":"1040 Somerset St W",
    "sg:city":"Ottawa",
    "sg:classifiers":[
        {
            "category":"Retail",
            "subcategory":"Auto Repair",
            "type":"Services"
        }
    ],
    "sg:phone":"+1 613 798 1822",
    "sg:postcode":"K1Y 4L3",
    "sg:province":"ON",
    "sg:tags":[
        "repairing",
        "automobile"
    ],
    "wof:name":"Paradise Auto Repair",
    "wof:placetype":"venue"
},
  "geometry": {"coordinates":[-75.71881866459999,45.4068450928],"type":"Point"}
}