{
  "type": "Feature",
  "properties": {
    "addr:full":"Nepean ON K2G 0G2",
    "addr:postcode":"k2g 0g2",
    "iso:country":"CA",
    "sg:city":"Nepean",
    "sg:classifiers":[
        {
            "category":"Manufacturing",
            "subcategory":"Signs",
            "type":"Manufacturing & Wholesale Goods"
        }
    ],
    "sg:phone":"+1 613 723 9007",
    "sg:postcode":"K2G 0G2",
    "sg:province":"ON",
    "wof:name":"Kennedy Signs & Graphics",
    "wof:placetype":"venue"
},
  "geometry": {"coordinates":[-75.72133599999999,45.323723],"type":"Point"}
}