{
  "type": "Feature",
  "properties": {
    "addr:full":"9701 17 St Dawson Creek BC V1G 4B1",
    "addr:housenumber":"9701",
    "addr:postcode":"v1g 4b1",
    "addr:street":"17 St",
    "iso:country":"CA",
    "sg:address":"9701 17 St",
    "sg:city":"Dawson Creek",
    "sg:classifiers":[
        {
            "category":"Retail",
            "subcategory":"Animal Services",
            "type":"Services"
        }
    ],
    "sg:phone":"+1 250 782 6563",
    "sg:postcode":"V1G 4B1",
    "sg:province":"BC",
    "sg:tags":[
        "pet",
        "grooming",
        "washing"
    ],
    "wof:name":"4 Paws Grooming",
    "wof:placetype":"venue"
},
  "geometry": {"coordinates":[-120.25065600000001,55.76511],"type":"Point"}
}