{
  "type": "Feature",
  "properties": {
    "iso:country":"CA",
    "sg:address":"411 Turenne St",
    "sg:city":"Winnipeg",
    "sg:classifiers":[
        {
            "category":"Professional",
            "subcategory":"Business Services",
            "type":"Services"
        }
    ],
    "sg:phone":"+1 204 237 3473",
    "sg:postcode":"R2J 0S5",
    "sg:province":"MB",
    "sg:tags":[
        "fire",
        "protection"
    ],
    "wof:name":"Bison Fire Protection Inc",
    "wof:placetype":"venue"
},
  "geometry": {"coordinates":[-97.07972717289999,49.8840370178],"type":"Point"}
}