{
  "type": "Feature",
  "properties": {
    "addr:full":"9333 98A St NW Edmonton AB T6E 3N2",
    "addr:housenumber":"9333",
    "addr:postcode":"t6e 3n2",
    "addr:street":"98A St Nw",
    "iso:country":"CA",
    "sg:address":"9333 98A St NW",
    "sg:city":"Edmonton",
    "sg:classifiers":[
        {
            "category":"Wholesale",
            "subcategory":"Hardware",
            "type":"Manufacturing & Wholesale Goods"
        }
    ],
    "sg:phone":"+1 780 413 9234",
    "sg:postcode":"T6E 3N2",
    "sg:province":"AB",
    "sg:tags":[
        "refrigerating"
    ],
    "wof:name":"Ajax Coin Op",
    "wof:placetype":"venue"
},
  "geometry": {"coordinates":[-113.484130859,53.5292472839],"type":"Point"}
}