{
  "type": "Feature",
  "properties": {
    "addr:full":"533 St Anne's Rd Winnipeg MB R2M 3E8",
    "addr:housenumber":"533",
    "addr:postcode":"r2m 3e8",
    "addr:street":"St Anne'S Rd",
    "iso:country":"CA",
    "sg:address":"533 St Anne's Rd",
    "sg:city":"Winnipeg",
    "sg:classifiers":[
        {
            "category":"Social Services",
            "type":"Services"
        }
    ],
    "sg:phone":"+1 204 254 1618",
    "sg:postcode":"R2M 3E8",
    "sg:province":"MB",
    "sg:tags":[
        "youth",
        "organization",
        "center"
    ],
    "wof:name":"Teen Stop Jeunesse",
    "wof:placetype":"venue"
},
  "geometry": {"coordinates":[-97.09312438960001,49.8393936157],"type":"Point"}
}