{
  "type": "Feature",
  "properties": {
    "addr:full":"373 Mcarthur Ave Vanier ON K1L 6N5",
    "addr:housenumber":"373",
    "addr:postcode":"k1l 6n5",
    "addr:street":"Mcarthur Ave",
    "iso:country":"CA",
    "sg:address":"373 Mcarthur Ave",
    "sg:city":"Vanier",
    "sg:classifiers":[
        {
            "category":"Education",
            "subcategory":"School",
            "type":"Public Place"
        }
    ],
    "sg:phone":"+1 613 745 9480",
    "sg:postcode":"K1L 6N5",
    "sg:province":"ON",
    "wof:name":"Robert E Wilson Public School",
    "wof:placetype":"venue"
},
  "geometry": {"coordinates":[-75.65117600000001,45.432079],"type":"Point"}
}