{
  "type": "Feature",
  "properties": {
    "addr:full":"1253 Rue Beaubien E Montreal QC H2S 1V1",
    "addr:housenumber":"1253",
    "addr:postcode":"h2s 1v1",
    "addr:street":"Rue Beaubien E",
    "iso:country":"CA",
    "sg:address":"1253 Rue Beaubien E",
    "sg:city":"Montreal",
    "sg:classifiers":[
        {
            "category":"Food & Beverages",
            "subcategory":"Bakery",
            "type":"Retail Goods"
        }
    ],
    "sg:phone":"+1 514 276 0880",
    "sg:postcode":"H2S 1V1",
    "sg:province":"QC",
    "sg:tags":[
        "baker"
    ],
    "wof:name":"Autour D'Un Pain",
    "wof:placetype":"venue"
},
  "geometry": {"coordinates":[-73.600189,45.539425],"type":"Point"}
}