{
  "type": "Feature",
  "properties": {
    "addr:full":"3040 Lake Trail Rd Courtenay BC V9N 9M1",
    "addr:housenumber":"3040",
    "addr:postcode":"v9n 9m1",
    "addr:street":"Lake Trail Rd",
    "iso:country":"CA",
    "sg:address":"3040 Lake Trail Rd",
    "sg:city":"Courtenay",
    "sg:classifiers":[
        {
            "category":"Education",
            "subcategory":"School",
            "type":"Public Place"
        }
    ],
    "sg:phone":"+1 250 334 3191",
    "sg:postcode":"V9N 9M1",
    "sg:province":"BC",
    "wof:name":"Arden Elementary School",
    "wof:placetype":"venue"
},
  "geometry": {"coordinates":[-125.01789100000001,49.676418],"type":"Point"}
}