{
  "type": "Feature",
  "properties": {
    "iso:country":"CA",
    "sg:address":"22 Rue DE LA Fabrique",
    "sg:city":"Mont-Carmel",
    "sg:classifiers":[
        {
            "category":"Government",
            "subcategory":"Office",
            "type":"Public Place"
        }
    ],
    "sg:phone":"+1 418 498 2050",
    "sg:postcode":"G0L 1W0",
    "sg:province":"QC",
    "sg:tags":[
        "village"
    ],
    "wof:name":"Mont-Carmel Municipalite",
    "wof:placetype":"venue"
},
  "geometry": {"coordinates":[-69.8535079956,47.4404563904],"type":"Point"}
}