{
  "type": "Feature",
  "properties": {
    "addr:full":"697 Kingsway Garden Mall NW Edmonton AB T5G 3E6",
    "addr:housenumber":"697",
    "addr:postcode":"t5g 3e6",
    "addr:street":"Kingsway Garden Mall Nw",
    "iso:country":"CA",
    "sg:address":"697 Kingsway Garden Mall NW",
    "sg:city":"Edmonton",
    "sg:classifiers":[
        {
            "category":"Shopping",
            "subcategory":"Shoes",
            "type":"Retail Goods"
        }
    ],
    "sg:phone":"+1 780 477 3360",
    "sg:postcode":"T5G 3E6",
    "sg:province":"AB",
    "wof:name":"Sterling Shoes",
    "wof:placetype":"venue"
},
  "geometry": {"coordinates":[-113.490371704,53.5462188721],"type":"Point"}
}