{
  "type": "Feature",
  "properties": {
    "iso:country":"CA",
    "sg:address":"52 Fitzwilliam Blvd",
    "sg:city":"London",
    "sg:classifiers":[
        {
            "category":"Real Estate",
            "subcategory":"Real Estate Agent",
            "type":"Services"
        }
    ],
    "sg:phone":"+1 519 474 3033",
    "sg:postcode":"N6H 5H6",
    "sg:province":"ON",
    "wof:name":"Cavaco Realty Inc",
    "wof:placetype":"venue"
},
  "geometry": {"coordinates":[-81.3291320801,42.9819412231],"type":"Point"}
}