{
  "type": "Feature",
  "properties": {
    "addr:full":"80 Boul Larochelle Asbestos QC J1T 3M7",
    "addr:housenumber":"80",
    "addr:postcode":"j1t 3m7",
    "addr:street":"Boul Larochelle",
    "iso:country":"CA",
    "sg:address":"80 Boul Larochelle",
    "sg:city":"Asbestos",
    "sg:classifiers":[
        {
            "category":"Home & Garden",
            "subcategory":"Garden Supply",
            "type":"Retail Goods"
        }
    ],
    "sg:phone":"+1 819 879 5975",
    "sg:postcode":"J1T 3M7",
    "sg:province":"QC",
    "sg:tags":[
        "engine",
        "lawn",
        "mower"
    ],
    "wof:name":"Sports Brindle Inc",
    "wof:placetype":"venue"
},
  "geometry": {"coordinates":[-71.8947296143,45.7921257019],"type":"Point"}
}