{
  "type": "Feature",
  "properties": {
    "iso:country":"CA",
    "sg:address":"2447 Anson Dr",
    "sg:city":"Mississauga",
    "sg:classifiers":[
        {
            "category":"Manufacturing",
            "subcategory":"Chemicals & Compounds",
            "type":"Manufacturing & Wholesale Goods"
        }
    ],
    "sg:phone":"+1 905 672 0372",
    "sg:postcode":"L5S 1G1",
    "sg:province":"ON",
    "sg:tags":[
        "material",
        "caulking",
        "putty"
    ],
    "wof:name":"Lastic Products",
    "wof:placetype":"venue"
},
  "geometry": {"coordinates":[-79.659012,43.696445],"type":"Point"}
}