{
  "type": "Feature",
  "properties": {
    "addr:full":"31 Rang DE LA Petite-Riviere Louiseville QC J5V 2H2",
    "addr:housenumber":"31",
    "addr:postcode":"j5v 2h2",
    "addr:street":"Rang De La Petite-Riviere",
    "iso:country":"CA",
    "sg:address":"31 Rang DE LA Petite-Riviere",
    "sg:city":"Louiseville",
    "sg:classifiers":[
        {
            "category":"Personal",
            "type":"Services"
        }
    ],
    "sg:phone":"+1 819 228 9593",
    "sg:postcode":"J5V 2H2",
    "sg:province":"QC",
    "sg:tags":[
        "electrolysis"
    ],
    "wof:name":"Salon LA Performance",
    "wof:placetype":"venue"
},
  "geometry": {"coordinates":[-72.94998168950001,46.2552642822],"type":"Point"}
}