{
  "type": "Feature",
  "properties": {
    "addr:full":"Montreal QC H3H 1Z5",
    "addr:postcode":"h3h 1z5",
    "iso:country":"CA",
    "sg:city":"Montreal",
    "sg:classifiers":[
        {
            "category":"Arts & Performance",
            "subcategory":"Theater",
            "type":"Entertainment"
        }
    ],
    "sg:phone":"+1 514 939 0100",
    "sg:postcode":"H3H 1Z5",
    "sg:province":"QC",
    "sg:tags":[
        "bureau"
    ],
    "wof:name":"Imc Inc",
    "wof:placetype":"venue"
},
  "geometry": {"coordinates":[-73.58409899999999,45.490589],"type":"Point"}
}