{
  "type": "Feature",
  "properties": {
    "addr:full":"248 Boul Perron O New Richmond QC G0C 2B0",
    "addr:housenumber":"248",
    "addr:postcode":"g0c 2b0",
    "addr:street":"Boul Perron",
    "iso:country":"CA",
    "sg:address":"248 Boul Perron O",
    "sg:city":"New Richmond",
    "sg:classifiers":[
        {
            "category":"Organizations",
            "subcategory":"Religious Organization",
            "type":"Services"
        }
    ],
    "sg:phone":"+1 418 392 5161",
    "sg:postcode":"G0C 2B0",
    "sg:province":"QC",
    "sg:tags":[
        "church"
    ],
    "wof:name":"Eglise Du Plein Evangile",
    "wof:placetype":"venue"
},
  "geometry": {"coordinates":[-65.872101,48.169331],"type":"Point"}
}