{
  "type": "Feature",
  "properties": {
    "addr:full":"43 River Ave Starbuck MB R0G 2P0",
    "addr:housenumber":"43",
    "addr:postcode":"r0g 2p0",
    "addr:street":"River Ave",
    "iso:country":"CA",
    "sg:address":"43 River Ave",
    "sg:city":"Starbuck",
    "sg:classifiers":[
        {
            "category":"Organizations",
            "subcategory":"Religious Organization",
            "type":"Services"
        }
    ],
    "sg:phone":"+1 204 735 2503",
    "sg:postcode":"R0G 2P0",
    "sg:province":"MB",
    "sg:tags":[
        "church"
    ],
    "wof:name":"Lutheran Church Trinity",
    "wof:placetype":"venue"
},
  "geometry": {"coordinates":[-97.6190109253,49.7688713074],"type":"Point"}
}