{
  "type": "Feature",
  "properties": {
    "iso:country":"CA",
    "sg:address":"520 Grand Ave",
    "sg:city":"Indian Head",
    "sg:classifiers":[
        {
            "category":"Shopping",
            "subcategory":"Department Store",
            "type":"Retail Goods"
        }
    ],
    "sg:phone":"+1 306 695 2551",
    "sg:postcode":"S0G 2K0",
    "sg:province":"SK",
    "wof:name":"Stedmans V & S Dept Store",
    "wof:placetype":"venue"
},
  "geometry": {"coordinates":[-103.668861389,50.5325698853],"type":"Point"}
}