{
  "type": "Feature",
  "properties": {
    "addr:full":"Maidstone ON N0R 1K0",
    "addr:postcode":"n0r 1k0",
    "iso:country":"CA",
    "sg:city":"Maidstone",
    "sg:classifiers":[
        {
            "category":"Home & Garden",
            "subcategory":"Garden Supply",
            "type":"Retail Goods"
        }
    ],
    "sg:phone":"+1 519 723 4327",
    "sg:postcode":"N0R 1K0",
    "sg:province":"ON",
    "sg:tags":[
        "nurseryman",
        "center"
    ],
    "wof:name":"Lil's Country Gardens",
    "wof:placetype":"venue"
},
  "geometry": {"coordinates":[-82.89051055909999,42.210067749],"type":"Point"}
}