{
  "type": "Feature",
  "properties": {
    "addr:full":"94 Tranquility St Brantford ON N3R 3H8",
    "addr:housenumber":"94",
    "addr:postcode":"n3r 3h8",
    "addr:street":"Tranquility St",
    "iso:country":"CA",
    "sg:address":"94 Tranquility St",
    "sg:city":"Brantford",
    "sg:classifiers":[
        {
            "category":"Building & Trades",
            "subcategory":"Cleaning & Sanitation",
            "type":"Services"
        }
    ],
    "sg:phone":"+1 519 759 2000",
    "sg:postcode":"N3R 3H8",
    "sg:province":"ON",
    "sg:tags":[
        "janitor"
    ],
    "wof:name":"Bell City Janitor Svc",
    "wof:placetype":"venue"
},
  "geometry": {"coordinates":[-80.2694015503,43.1757621765],"type":"Point"}
}