{
  "type": "Feature",
  "properties": {
    "addr:full":"7400 Rue Verite Saint-Laurent QC H4S 1C5",
    "addr:housenumber":"7400",
    "addr:postcode":"h4s 1c5",
    "addr:street":"Rue Verite",
    "iso:country":"CA",
    "sg:address":"7400 Rue Verite",
    "sg:city":"Saint-Laurent",
    "sg:classifiers":[
        {
            "category":"Building & Trades",
            "subcategory":"Construction",
            "type":"Services"
        }
    ],
    "sg:phone":"+1 514 334 1401",
    "sg:postcode":"H4S 1C5",
    "sg:province":"QC",
    "sg:tags":[
        "excavating",
        "contractor"
    ],
    "wof:name":"Excavation Guerin & Freres Inc",
    "wof:placetype":"venue"
},
  "geometry": {"coordinates":[-73.7485733032,45.4784126282],"type":"Point"}
}