{
  "type": "Feature",
  "properties": {
    "addr:full":"6611 Innovator Dr Mississauga ON L5T 2J3",
    "addr:housenumber":"6611",
    "addr:postcode":"l5t 2j3",
    "addr:street":"Innovator Dr",
    "iso:country":"CA",
    "sg:address":"6611 Innovator Dr",
    "sg:city":"Mississauga",
    "sg:classifiers":[
        {
            "category":"Professional",
            "subcategory":"Business Services",
            "type":"Services"
        }
    ],
    "sg:phone":"+1 905 670 9383",
    "sg:postcode":"L5T 2J3",
    "sg:province":"ON",
    "wof:name":"Harling Marketing Inc",
    "wof:placetype":"venue"
},
  "geometry": {"coordinates":[-79.687325,43.644924],"type":"Point"}
}