{
  "type": "Feature",
  "properties": {
    "addr:full":"100 Front St Queen Charlotte BC V0T 1S1",
    "addr:housenumber":"100",
    "addr:postcode":"v0t 1s1",
    "addr:street":"Front St",
    "iso:country":"CA",
    "sg:address":"100 Front St",
    "sg:city":"Queen Charlotte",
    "sg:classifiers":[
        {
            "category":"Museum",
            "type":"Entertainment"
        }
    ],
    "sg:phone":"+1 250 559 7709",
    "sg:postcode":"V0T 1S1",
    "sg:province":"BC",
    "wof:name":"Qay'Illnagaay Heritage Ctr",
    "wof:placetype":"venue"
},
  "geometry": {"coordinates":[-132.09429900000001,53.25425],"type":"Point"}
}