{
  "type": "Feature",
  "properties": {
    "addr:full":"27 Scanlon Bay NW Calgary AB T3L 1H6",
    "addr:housenumber":"27",
    "addr:postcode":"t3l 1h6",
    "addr:street":"Scanlon Bay Nw",
    "iso:country":"CA",
    "sg:address":"27 Scanlon Bay NW",
    "sg:city":"Calgary",
    "sg:classifiers":[
        {
            "category":"Shopping",
            "subcategory":"Bicycles & Sporting Goods",
            "type":"Retail Goods"
        }
    ],
    "sg:phone":"+1 403 241 1885",
    "sg:postcode":"T3L 1H6",
    "sg:province":"AB",
    "wof:name":"R Michael Slipp Agencies",
    "wof:placetype":"venue"
},
  "geometry": {"coordinates":[-114.218055725,51.1227035522],"type":"Point"}
}