{
  "type": "Feature",
  "properties": {
    "addr:full":"Didsbury AB T0M 0W0",
    "addr:postcode":"t0m 0w0",
    "iso:country":"CA",
    "sg:city":"Didsbury",
    "sg:classifiers":[
        {
            "category":"Building & Trades",
            "subcategory":"Plumbing",
            "type":"Services"
        }
    ],
    "sg:phone":"+1 403 335 9279",
    "sg:postcode":"T0M 0W0",
    "sg:province":"AB",
    "sg:tags":[
        "refrigeration",
        "contractor"
    ],
    "wof:name":"Comp-Tek Refrigeration Svc",
    "wof:placetype":"venue"
},
  "geometry": {"coordinates":[-114.13801599999999,51.658962],"type":"Point"}
}