{
  "type": "Feature",
  "properties": {
    "addr:full":"24 Rue Vanier Ste-Catherine-DE-LA-J-Cartier QC G0A 3M0",
    "addr:housenumber":"24",
    "addr:postcode":"g0a 3m0",
    "addr:street":"Rue Vanier Ste-Catherine-De-La-J-Cartier",
    "iso:country":"CA",
    "sg:address":"24 Rue Vanier",
    "sg:city":"Ste-Catherine-DE-LA-J-Cartier",
    "sg:classifiers":[
        {
            "category":"Wholesale",
            "subcategory":"Groceries",
            "type":"Manufacturing & Wholesale Goods"
        }
    ],
    "sg:phone":"+1 418 875 2415",
    "sg:postcode":"G0A 3M0",
    "sg:province":"QC",
    "sg:tags":[
        "pasta"
    ],
    "wof:name":"Pates Du Quebec Enr",
    "wof:placetype":"venue"
},
  "geometry": {"coordinates":[-77.63571929930001,49.7592773438],"type":"Point"}
}