{
  "type": "Feature",
  "properties": {
    "iso:country":"CA",
    "sg:city":"Calgary",
    "sg:classifiers":[
        {
            "category":"Restaurant",
            "type":"Food & Drink"
        }
    ],
    "sg:phone":"+1 403 207 9896",
    "sg:postcode":"T2A 7X6",
    "sg:province":"AB",
    "wof:name":"Pho Que Huong Vietnemese",
    "wof:placetype":"venue"
},
  "geometry": {"coordinates":[-113.982093811,51.0620079041],"type":"Point"}
}