{
  "type": "Feature",
  "properties": {
    "addr:full":"8500 Boul Henri-Bourassa Charlesbourg QC G1G 5X1",
    "addr:housenumber":"8500",
    "addr:postcode":"g1g 5x1",
    "addr:street":"Boul Henri-Bourassa",
    "iso:country":"CA",
    "sg:address":"8500 Boul Henri-Bourassa",
    "sg:city":"Charlesbourg",
    "sg:classifiers":[
        {
            "category":"Food & Beverages",
            "subcategory":"Groceries & Convenience Stores",
            "type":"Retail Goods"
        }
    ],
    "sg:phone":"+1 418 626 3234",
    "sg:postcode":"G1G 5X1",
    "sg:province":"QC",
    "sg:tags":[
        "grocer"
    ],
    "wof:name":"Partage D'Or",
    "wof:placetype":"venue"
},
  "geometry": {"coordinates":[-71.2707748413,46.8651123047],"type":"Point"}
}