{
  "type": "Feature",
  "properties": {
    "addr:full":"Vancouver BC V5Z 2M9",
    "addr:postcode":"v5z 2m9",
    "iso:country":"CA",
    "sg:city":"Vancouver",
    "sg:classifiers":[
        {
            "category":"Health Services",
            "subcategory":"Doctor",
            "type":"Services"
        }
    ],
    "sg:phone":"+1 604 263 8515",
    "sg:postcode":"V5Z 2M9",
    "sg:province":"BC",
    "sg:tags":[
        "dentist"
    ],
    "wof:name":"Walter, William S DDS",
    "wof:placetype":"venue"
},
  "geometry": {"coordinates":[-123.117675781,49.2335510254],"type":"Point"}
}