{
  "type": "Feature",
  "properties": {
    "addr:full":"4509 Av Coloniale Montreal QC H2T 1V8",
    "addr:housenumber":"4509",
    "addr:postcode":"h2t 1v8",
    "addr:street":"Av Coloniale",
    "iso:country":"CA",
    "sg:address":"4509 Av Coloniale",
    "sg:city":"Montreal",
    "sg:classifiers":[
        {
            "category":"Wholesale",
            "subcategory":"Apparel",
            "type":"Manufacturing & Wholesale Goods"
        }
    ],
    "sg:phone":"+1 514 844 3067",
    "sg:postcode":"H2T 1V8",
    "sg:province":"QC",
    "sg:tags":[
        "shoes"
    ],
    "wof:name":"Pajar Production Ltee",
    "wof:placetype":"venue"
},
  "geometry": {"coordinates":[-73.5856170654,45.5213661194],"type":"Point"}
}