{
  "type": "Feature",
  "properties": {
    "addr:full":"219 Matheson St S Kenora ON P9N 1V1",
    "addr:housenumber":"219",
    "addr:postcode":"p9n 1v1",
    "addr:street":"Matheson St S",
    "iso:country":"CA",
    "sg:address":"219 Matheson St S",
    "sg:city":"Kenora",
    "sg:classifiers":[
        {
            "category":"Personal",
            "subcategory":"Beauty Salon",
            "type":"Services"
        }
    ],
    "sg:phone":"+1 807 468 9516",
    "sg:postcode":"P9N 1V1",
    "sg:province":"ON",
    "wof:name":"Heights of Fashion Ctr",
    "wof:placetype":"venue"
},
  "geometry": {"coordinates":[-94.489273,49.765736],"type":"Point"}
}