{
  "type": "Feature",
  "properties": {
    "addr:full":"5550 Av Trudeau Saint-Hyacinthe QC J2S 1H4",
    "addr:housenumber":"5550",
    "addr:postcode":"j2s 1h4",
    "addr:street":"Av Trudeau",
    "iso:country":"CA",
    "sg:address":"5550 Av Trudeau",
    "sg:city":"Saint-Hyacinthe",
    "sg:classifiers":[
        {
            "category":"Sports & Exercise",
            "subcategory":"Bowling",
            "type":"Entertainment"
        }
    ],
    "sg:phone":"+1 450 774 3335",
    "sg:postcode":"J2S 1H4",
    "sg:province":"QC",
    "sg:tags":[
        "center"
    ],
    "wof:name":"Salon DE Quilles St-Hyacinthe",
    "wof:placetype":"venue"
},
  "geometry": {"coordinates":[-72.97524300000001,45.635868],"type":"Point"}
}