{
  "type": "Feature",
  "properties": {
    "addr:full":"1845 Finch Ave W North York ON M3N 2V2",
    "addr:housenumber":"1845",
    "addr:postcode":"m3n 2v2",
    "addr:street":"Finch Ave W",
    "iso:country":"CA",
    "sg:address":"1845 Finch Ave W",
    "sg:city":"North York",
    "sg:classifiers":[
        {
            "category":"Restaurant",
            "type":"Food & Drink"
        }
    ],
    "sg:phone":"+1 416 630 0825",
    "sg:postcode":"M3N 2V2",
    "sg:province":"ON",
    "wof:name":"Roti Palace",
    "wof:placetype":"venue"
},
  "geometry": {"coordinates":[-79.51412999999999,43.757732],"type":"Point"}
}