{
  "type": "Feature",
  "properties": {
    "addr:full":"Victoria BC V8T 1M2",
    "addr:postcode":"v8t 1m2",
    "iso:country":"CA",
    "sg:city":"Victoria",
    "sg:classifiers":[
        {
            "category":"Education",
            "subcategory":"Vocational School",
            "type":"Public Place"
        }
    ],
    "sg:phone":"+1 250 383 1522",
    "sg:postcode":"V8T 1M2",
    "sg:province":"BC",
    "sg:tags":[
        "technical",
        "trade"
    ],
    "wof:name":"Western Academy of Photography",
    "wof:placetype":"venue"
},
  "geometry": {"coordinates":[-123.363564,48.434086],"type":"Point"}
}