{
  "type": "Feature",
  "properties": {
    "addr:full":"75 Albion St S Amherst NS B4H 2W8",
    "addr:housenumber":"75",
    "addr:postcode":"b4h 2w8",
    "addr:street":"Albion St S",
    "iso:country":"CA",
    "sg:address":"75 Albion St S",
    "sg:city":"Amherst",
    "sg:classifiers":[
        {
            "category":"Food & Beverages",
            "subcategory":"Groceries & Convenience Stores",
            "type":"Retail Goods"
        }
    ],
    "sg:phone":"+1 902 667 4222",
    "sg:postcode":"B4H 2W8",
    "sg:province":"NS",
    "wof:name":"B J's One Stop",
    "wof:placetype":"venue"
},
  "geometry": {"coordinates":[-64.206429,45.82032],"type":"Point"}
}