{
  "type": "Feature",
  "properties": {
    "addr:full":"1403 Dundas St E Mississauga ON L4X 1L3",
    "addr:housenumber":"1403",
    "addr:postcode":"l4x 1l3",
    "addr:street":"Dundas St E",
    "iso:country":"CA",
    "sg:address":"1403 Dundas St E",
    "sg:city":"Mississauga",
    "sg:classifiers":[
        {
            "category":"Banks & Credit Unions",
            "subcategory":"Bank",
            "type":"Services"
        }
    ],
    "sg:phone":"+1 905 206 0044",
    "sg:postcode":"L4X 1L3",
    "sg:province":"ON",
    "sg:tags":[
        "cashing",
        "check"
    ],
    "wof:name":"Cash Money Cheque Cashing Inc",
    "wof:placetype":"venue"
},
  "geometry": {"coordinates":[-79.58367200000001,43.609692],"type":"Point"}
}