{
  "type": "Feature",
  "properties": {
    "iso:country":"CA",
    "sg:city":"Trois-Rivieres",
    "sg:classifiers":[
        {
            "category":"Government",
            "subcategory":"Police Station",
            "type":"Public Place"
        }
    ],
    "sg:phone":"+1 819 375 1074",
    "sg:postcode":"G9A 4H7",
    "sg:province":"QC",
    "sg:tags":[
        "bailiff"
    ],
    "wof:name":"Trudel & Assoc",
    "wof:placetype":"venue"
},
  "geometry": {"coordinates":[-72.542640686,46.3451538086],"type":"Point"}
}