{
  "type": "Feature",
  "properties": {
    "addr:full":"298 Ave Principale Saint-Blaise-Sur-Richelieu QC J0J 1W0",
    "addr:housenumber":"298",
    "addr:postcode":"j0j 1w0",
    "addr:street":"Ave Principale",
    "iso:country":"CA",
    "sg:address":"298 Ave Principale",
    "sg:city":"Saint-Blaise-Sur-Richelieu",
    "sg:classifiers":[
        {
            "category":"Building & Trades",
            "subcategory":"Construction",
            "type":"Services"
        }
    ],
    "sg:phone":"+1 450 291 3318",
    "sg:postcode":"J0J 1W0",
    "sg:province":"QC",
    "sg:tags":[
        "concrete",
        "excavating",
        "contractor"
    ],
    "wof:name":"Entreprises Gm St-Blaise Inc",
    "wof:placetype":"venue"
},
  "geometry": {"coordinates":[-73.271278,45.200535],"type":"Point"}
}