{
  "type": "Feature",
  "properties": {
    "addr:full":"137 Boul Bellerose O Laval QC H7K 3B5",
    "addr:housenumber":"137",
    "addr:postcode":"qc h7k 3b5",
    "addr:street":"Boul Bellerose O",
    "iso:country":"CA",
    "sg:address":"137 Boul Bellerose O",
    "sg:city":"Laval",
    "sg:classifiers":[
        {
            "category":"Wholesale",
            "subcategory":"Construction Materials",
            "type":"Manufacturing & Wholesale Goods"
        }
    ],
    "sg:phone":"+1 450 667 6950",
    "sg:postcode":"H7K 3B5",
    "sg:province":"QC",
    "sg:tags":[
        "building"
    ],
    "wof:name":"Bois Peladeau Inc",
    "wof:placetype":"venue"
},
  "geometry": {"coordinates":[-73.7308273315,45.6143302917],"type":"Point"}
}