{
  "type": "Feature",
  "properties": {
    "addr:full":"Abbotsford BC V2S 5A1",
    "addr:postcode":"v2s 5a1",
    "iso:country":"CA",
    "sg:city":"Abbotsford",
    "sg:classifiers":[
        {
            "category":"Shopping",
            "subcategory":"Photographic Equipment",
            "type":"Retail Goods"
        }
    ],
    "sg:phone":"+1 604 557 0029",
    "sg:postcode":"V2S 5A1",
    "sg:province":"BC",
    "sg:tags":[
        "supply"
    ],
    "wof:name":"Lens & Shutter",
    "wof:placetype":"venue"
},
  "geometry": {"coordinates":[-122.311775,49.050785],"type":"Point"}
}