{
  "type": "Feature",
  "properties": {
    "addr:full":"1612 London Line Sarnia ON N7W 1A8",
    "addr:housenumber":"1612",
    "addr:postcode":"n7w 1a8",
    "addr:street":"London Line",
    "iso:country":"CA",
    "sg:address":"1612 London Line",
    "sg:city":"Sarnia",
    "sg:classifiers":[
        {
            "category":"Travel",
            "subcategory":"Hotels & Motels",
            "type":"Entertainment"
        }
    ],
    "sg:phone":"+1 519 542 7747",
    "sg:postcode":"N7W 1A8",
    "sg:province":"ON",
    "wof:name":"East Court Motel",
    "wof:placetype":"venue"
},
  "geometry": {"coordinates":[-82.3343887329,42.9841156006],"type":"Point"}
}