{
  "type": "Feature",
  "properties": {
    "addr:full":"Hwy 35 Sylvania SK S0E 1S0",
    "addr:postcode":"s0e 1s0",
    "addr:street":"Hwy 35",
    "iso:country":"CA",
    "sg:address":"Hwy 35",
    "sg:city":"Sylvania",
    "sg:classifiers":[
        {
            "category":"Building & Trades",
            "subcategory":"Construction",
            "type":"Services"
        }
    ],
    "sg:phone":"+1 306 873 5329",
    "sg:postcode":"S0E 1S0",
    "sg:province":"SK",
    "sg:tags":[
        "excavating",
        "contractor",
        "general"
    ],
    "wof:name":"Silvertown Contracting",
    "wof:placetype":"venue"
},
  "geometry": {"coordinates":[-104.00453899999999,52.696323],"type":"Point"}
}