{
  "type": "Feature",
  "properties": {
    "iso:country":"CA",
    "sg:address":"200 4th Ave NW",
    "sg:city":"Manning",
    "sg:classifiers":[
        {
            "category":"Home & Garden",
            "subcategory":"Building Materials",
            "type":"Retail Goods"
        }
    ],
    "sg:phone":"+1 780 836 4039",
    "sg:postcode":"T0H 2M0",
    "sg:province":"AB",
    "sg:tags":[
        "lumber"
    ],
    "wof:name":"Homesteader Building Supplies",
    "wof:placetype":"venue"
},
  "geometry": {"coordinates":[-117.62594604500001,56.9272422791],"type":"Point"}
}