{
  "type": "Feature",
  "properties": {
    "iso:country":"CA",
    "sg:address":"41 Rue Alexandre",
    "sg:city":"Salaberry-DE-Valleyfield",
    "sg:classifiers":[
        {
            "category":"Restaurant",
            "type":"Food & Drink"
        }
    ],
    "sg:phone":"+1 450 377 8000",
    "sg:postcode":"J6S 3J4",
    "sg:province":"QC",
    "wof:name":"Pizzafritz Inc",
    "wof:placetype":"venue"
},
  "geometry": {"coordinates":[-74.133605957,45.2616500854],"type":"Point"}
}