{
  "type": "Feature",
  "properties": {
    "addr:full":"3206 Sunshine Coast Hwy Roberts Creek BC V0N 2W1",
    "addr:housenumber":"3206",
    "addr:postcode":"v0n 2w1",
    "addr:street":"Sunshine Coast Hwy",
    "iso:country":"CA",
    "sg:address":"3206 Sunshine Coast Hwy",
    "sg:city":"Roberts Creek",
    "sg:classifiers":[
        {
            "category":"Recreation",
            "type":"Entertainment"
        }
    ],
    "sg:phone":"+1 604 885 9212",
    "sg:postcode":"V0N 2W1",
    "sg:province":"BC",
    "sg:tags":[
        "course",
        "golf"
    ],
    "wof:name":"Sunshine Coast Golf & Country",
    "wof:placetype":"venue"
},
  "geometry": {"coordinates":[-123.606460571,49.4132614136],"type":"Point"}
}