{
  "type": "Feature",
  "properties": {
    "addr:full":"2200 Austin Ave Coquitlam BC V3K 3S1",
    "addr:housenumber":"2200",
    "addr:postcode":"v3k 3s1",
    "addr:street":"Austin Ave",
    "iso:country":"CA",
    "sg:address":"2200 Austin Ave",
    "sg:city":"Coquitlam",
    "sg:classifiers":[
        {
            "category":"Education",
            "subcategory":"School",
            "type":"Public Place"
        }
    ],
    "sg:phone":"+1 604 936 4271",
    "sg:postcode":"V3K 3S1",
    "sg:province":"BC",
    "wof:name":"Mundy Road Elementary School",
    "wof:placetype":"venue"
},
  "geometry": {"coordinates":[-122.83327484100001,49.2489013672],"type":"Point"}
}