{
  "type": "Feature",
  "properties": {
    "addr:full":"467 Ferguson Ave Haileybury ON P0J 1K0",
    "addr:housenumber":"467",
    "addr:postcode":"p0j 1k0",
    "addr:street":"Ferguson Ave",
    "iso:country":"CA",
    "sg:address":"467 Ferguson Ave",
    "sg:city":"Haileybury",
    "sg:classifiers":[
        {
            "category":"Professional",
            "subcategory":"Management & Consulting",
            "type":"Services"
        }
    ],
    "sg:phone":"+1 705 672 3021",
    "sg:postcode":"P0J 1K0",
    "sg:province":"ON",
    "sg:tags":[
        "consultant",
        "business"
    ],
    "wof:name":"South Temiskaming Community",
    "wof:placetype":"venue"
},
  "geometry": {"coordinates":[-79.6329498291,47.4486274719],"type":"Point"}
}