{
  "type": "Feature",
  "properties": {
    "addr:full":"Dieppe NB E1A 1J1",
    "addr:postcode":"e1a 1j1",
    "iso:country":"CA",
    "sg:city":"Dieppe",
    "sg:classifiers":[
        {
            "category":"Retail",
            "subcategory":"Animal Services",
            "type":"Services"
        }
    ],
    "sg:phone":"+1 506 857 0084",
    "sg:postcode":"E1A 1J1",
    "sg:province":"NB",
    "sg:tags":[
        "pet",
        "grooming",
        "washing"
    ],
    "wof:name":"Paradis Des Chiens",
    "wof:placetype":"venue"
},
  "geometry": {"coordinates":[-64.753731,46.0975],"type":"Point"}
}