{
  "type": "Feature",
  "properties": {
    "addr:full":"Lethbridge AB T1J 4E1",
    "addr:postcode":"t1j 4e1",
    "iso:country":"CA",
    "sg:city":"Lethbridge",
    "sg:classifiers":[
        {
            "category":"Health Services",
            "subcategory":"Doctor",
            "type":"Services"
        }
    ],
    "sg:phone":"+1 403 317 4867",
    "sg:postcode":"T1J 4E1",
    "sg:province":"AB",
    "sg:tags":[
        "dentist"
    ],
    "wof:name":"Lethbridge Periodontal Assoc",
    "wof:placetype":"venue"
},
  "geometry": {"coordinates":[-112.841553,49.694149],"type":"Point"}
}