{
  "type": "Feature",
  "properties": {
    "addr:full":"165 Vermilion Ave Princeton BC V0X 1W0",
    "addr:housenumber":"165",
    "addr:postcode":"v0x 1w0",
    "addr:street":"Vermilion Ave",
    "iso:country":"CA",
    "sg:address":"165 Vermilion Ave",
    "sg:city":"Princeton",
    "sg:classifiers":[
        {
            "category":"Organizations",
            "subcategory":"Religious Organization",
            "type":"Services"
        }
    ],
    "sg:phone":"+1 250 295 7951",
    "sg:postcode":"V0X 1W0",
    "sg:province":"BC",
    "sg:tags":[
        "church"
    ],
    "wof:name":"Princeton Pentecostal Tbncl",
    "wof:placetype":"venue"
},
  "geometry": {"coordinates":[-120.50861399999999,49.459229],"type":"Point"}
}