{
  "type": "Feature",
  "properties": {
    "addr:full":"1347 12 Ave SW Calgary AB T3C 0P6",
    "addr:housenumber":"1347",
    "addr:postcode":"t3c 0p6",
    "addr:street":"12 Ave Sw",
    "iso:country":"CA",
    "sg:address":"1347 12 Ave SW",
    "sg:city":"Calgary",
    "sg:classifiers":[
        {
            "category":"Wholesale",
            "subcategory":"Electrical",
            "type":"Manufacturing & Wholesale Goods"
        }
    ],
    "sg:phone":"+1 403 228 1103",
    "sg:postcode":"T3C 0P6",
    "sg:province":"AB",
    "sg:tags":[
        "sound",
        "equipment",
        "system",
        "consultant"
    ],
    "wof:name":"Audio Room",
    "wof:placetype":"venue"
},
  "geometry": {"coordinates":[-114.093917847,51.0422363281],"type":"Point"}
}