{
  "type": "Feature",
  "properties": {
    "iso:country":"CA",
    "sg:address":"21 Franklin St",
    "sg:city":"Markham",
    "sg:classifiers":[
        {
            "category":"Education",
            "subcategory":"School",
            "type":"Public Place"
        }
    ],
    "sg:phone":"+1 905 294 3562",
    "sg:postcode":"L3P 2S7",
    "sg:province":"ON",
    "wof:name":"Franklin Street Public School",
    "wof:placetype":"venue"
},
  "geometry": {"coordinates":[-79.2586593628,43.8791809082],"type":"Point"}
}