{
  "type": "Feature",
  "properties": {
    "addr:full":"320 Arthur Ave Saskatoon SK S7N 1J3",
    "addr:housenumber":"320",
    "addr:postcode":"s7n 1j3",
    "addr:street":"Arthur Ave",
    "iso:country":"CA",
    "sg:address":"320 Arthur Ave",
    "sg:city":"Saskatoon",
    "sg:classifiers":[
        {
            "category":"Manufacturing",
            "subcategory":"Food",
            "type":"Manufacturing & Wholesale Goods"
        }
    ],
    "sg:phone":"+1 306 373 6156",
    "sg:postcode":"S7N 1J3",
    "sg:province":"SK",
    "sg:tags":[
        "distiller"
    ],
    "wof:name":"Maxxium Canada",
    "wof:placetype":"venue"
},
  "geometry": {"coordinates":[-106.645355,52.12254],"type":"Point"}
}