{
  "type": "Feature",
  "properties": {
    "addr:full":"125 Tenth St Nanaimo BC V9R 6Z5",
    "addr:housenumber":"125",
    "addr:postcode":"v9r 6z5",
    "addr:street":"Tenth St",
    "iso:country":"CA",
    "sg:address":"125 Tenth St",
    "sg:city":"Nanaimo",
    "sg:classifiers":[
        {
            "category":"Freight",
            "type":"Transportation"
        }
    ],
    "sg:phone":"+1 250 754 0085",
    "sg:postcode":"V9R 6Z5",
    "sg:province":"BC",
    "sg:tags":[
        "trucking"
    ],
    "wof:name":"Trimac Transportation Systems",
    "wof:placetype":"venue"
},
  "geometry": {"coordinates":[-123.92685699499999,49.1332054138],"type":"Point"}
}