{
  "type": "Feature",
  "properties": {
    "addr:full":"125 Glenmount Ave North York ON M6B 3C2",
    "addr:housenumber":"125",
    "addr:postcode":"m6b 3c2",
    "addr:street":"Glenmount Ave",
    "iso:country":"CA",
    "sg:address":"125 Glenmount Ave",
    "sg:city":"North York",
    "sg:classifiers":[
        {
            "category":"Education",
            "subcategory":"School",
            "type":"Public Place"
        }
    ],
    "sg:phone":"+1 416 393 5265",
    "sg:postcode":"M6B 3C2",
    "sg:province":"ON",
    "wof:name":"Our Lady of the Assumption",
    "wof:placetype":"venue"
},
  "geometry": {"coordinates":[-79.431602,43.715569],"type":"Point"}
}