{
  "type": "Feature",
  "properties": {
    "addr:full":"84 1/2 Front St Sioux Lookout ON P8T 1B7",
    "addr:housenumber":"1 / 2",
    "addr:postcode":"p8t 1b7",
    "addr:street":"84;Front St",
    "iso:country":"CA",
    "sg:address":"84 1/2 Front St",
    "sg:city":"Sioux Lookout",
    "sg:classifiers":[
        {
            "category":"Shopping",
            "subcategory":"Gifts & Souvenirs",
            "type":"Retail Goods"
        }
    ],
    "sg:phone":"+1 807 737 4313",
    "sg:postcode":"P8T 1B7",
    "sg:province":"ON",
    "sg:tags":[
        "shop"
    ],
    "wof:name":"Roy Lane Boutique",
    "wof:placetype":"venue"
},
  "geometry": {"coordinates":[-91.92186700000001,50.098045],"type":"Point"}
}