{
  "type": "Feature",
  "properties": {
    "addr:full":"Toronto ON M5T 3A9",
    "addr:postcode":"m5t 3a9",
    "iso:country":"CA",
    "sg:city":"Toronto",
    "sg:classifiers":[
        {
            "category":"Health Services",
            "subcategory":"Health Practitioner",
            "type":"Services"
        }
    ],
    "sg:phone":"+1 416 961 0208",
    "sg:postcode":"M5T 3A9",
    "sg:province":"ON",
    "sg:tags":[
        "physician"
    ],
    "wof:name":"Love, Daria P",
    "wof:placetype":"venue"
},
  "geometry": {"coordinates":[-79.40334300000001,43.657448],"type":"Point"}
}