{
  "type": "Feature",
  "properties": {
    "addr:full":"505 Government St Victoria BC V8V 2L6",
    "addr:housenumber":"505",
    "addr:postcode":"v8v 2l6",
    "addr:street":"Government St",
    "iso:country":"CA",
    "sg:address":"505 Government St",
    "sg:city":"Victoria",
    "sg:classifiers":[
        {
            "category":"Travel",
            "subcategory":"Hotels & Motels",
            "type":"Entertainment"
        }
    ],
    "sg:phone":"+1 250 389 0804",
    "sg:postcode":"V8V 2L6",
    "sg:province":"BC",
    "sg:tags":[
        "breakfast",
        "accommodation",
        "bed"
    ],
    "wof:name":"Birdcage Walk Guest House",
    "wof:placetype":"venue"
},
  "geometry": {"coordinates":[-123.368629,48.417297],"type":"Point"}
}