{
  "type": "Feature",
  "properties": {
    "addr:full":"20456 Fraser Hwy Langley BC V3A 4G2",
    "addr:housenumber":"20456",
    "addr:postcode":"v3a 4g2",
    "addr:street":"Fraser Hwy",
    "iso:country":"CA",
    "sg:address":"20456 Fraser Hwy",
    "sg:city":"Langley",
    "sg:classifiers":[
        {
            "category":"Shopping",
            "subcategory":"Bicycles & Sporting Goods",
            "type":"Retail Goods"
        }
    ],
    "sg:phone":"+1 604 534 6610",
    "sg:postcode":"V3A 4G2",
    "sg:province":"BC",
    "wof:name":"Mountain Alpine Sports Ltd",
    "wof:placetype":"venue"
},
  "geometry": {"coordinates":[-122.655067,49.104267],"type":"Point"}
}