{
  "type": "Feature",
  "properties": {
    "iso:country":"CA",
    "sg:address":"138 Robertson Rd",
    "sg:city":"Nepean",
    "sg:classifiers":[
        {
            "category":"Health Services",
            "subcategory":"Chiropractor",
            "type":"Services"
        }
    ],
    "sg:phone":"+1 613 829 3580",
    "sg:postcode":"K2H 5Z1",
    "sg:province":"ON",
    "wof:name":"Bells Corners Chiropractic",
    "wof:placetype":"venue"
},
  "geometry": {"coordinates":[-75.8356933594,45.3209381104],"type":"Point"}
}