{
  "type": "Feature",
  "properties": {
    "addr:full":"Hull QC J8Z 1W8",
    "addr:postcode":"j8z 1w8",
    "iso:country":"CA",
    "sg:city":"Hull",
    "sg:classifiers":[
        {
            "category":"Health Services",
            "subcategory":"Doctor",
            "type":"Services"
        }
    ],
    "sg:phone":"+1 819 777 6492",
    "sg:postcode":"J8Z 1W8",
    "sg:province":"QC",
    "sg:tags":[
        "dentist"
    ],
    "wof:name":"Clinique Dentaire Des Vallees",
    "wof:placetype":"venue"
},
  "geometry": {"coordinates":[-75.73809799999999,45.468407],"type":"Point"}
}