{
  "type": "Feature",
  "properties": {
    "addr:full":"256 Knightsbridge Dr Winnipeg MB R2M 4E9",
    "addr:housenumber":"256",
    "addr:postcode":"r2m 4e9",
    "addr:street":"Knightsbridge Dr",
    "iso:country":"CA",
    "sg:address":"256 Knightsbridge Dr",
    "sg:city":"Winnipeg",
    "sg:classifiers":[
        {
            "category":"Recreation",
            "type":"Entertainment"
        }
    ],
    "sg:phone":"+1 204 256 7796",
    "sg:postcode":"R2M 4E9",
    "sg:province":"MB",
    "sg:tags":[
        "psychic",
        "medium"
    ],
    "wof:name":"Lady Phoenix",
    "wof:placetype":"venue"
},
  "geometry": {"coordinates":[-97.10008999999999,49.831871],"type":"Point"}
}