{
  "type": "Feature",
  "properties": {
    "addr:full":"Longueuil QC J4H 4A4",
    "addr:postcode":"j4h 4a4",
    "iso:country":"CA",
    "sg:city":"Longueuil",
    "sg:classifiers":[
        {
            "category":"Social Services",
            "subcategory":"Child Care",
            "type":"Services"
        }
    ],
    "sg:phone":"+1 450 677 8260",
    "sg:postcode":"J4H 4A4",
    "sg:province":"QC",
    "wof:name":"Garderie Montpetit Edouard",
    "wof:placetype":"venue"
},
  "geometry": {"coordinates":[-73.4939880371,45.5382118225],"type":"Point"}
}