{
  "type": "Feature",
  "properties": {
    "addr:full":"273 Rang Des Mines Saint-Augustin-DE-Desmaures QC G3A 1W8",
    "addr:housenumber":"273",
    "addr:postcode":"g3a 1w8",
    "addr:street":"Rang Des Mines",
    "iso:country":"CA",
    "sg:address":"273 Rang Des Mines",
    "sg:city":"Saint-Augustin-DE-Desmaures",
    "sg:classifiers":[
        {
            "category":"Building & Trades",
            "subcategory":"Plumbing",
            "type":"Services"
        }
    ],
    "sg:phone":"+1 418 878 3515",
    "sg:postcode":"G3A 1W8",
    "sg:province":"QC",
    "sg:tags":[
        "contractor"
    ],
    "wof:name":"Plomberie Denis Meunier",
    "wof:placetype":"venue"
},
  "geometry": {"coordinates":[-71.477577,46.765015],"type":"Point"}
}