{
  "type": "Feature",
  "properties": {
    "iso:country":"CA",
    "sg:city":"L'Ancienne-Lorette",
    "sg:classifiers":[
        {
            "category":"Professional",
            "subcategory":"Computer Services",
            "type":"Services"
        }
    ],
    "sg:phone":"+1 514 916 8032",
    "sg:postcode":"G2E 2Y1",
    "sg:province":"QC",
    "sg:tags":[
        "information",
        "training",
        "system",
        "consultant"
    ],
    "wof:name":"Format Conseil Inc",
    "wof:placetype":"venue"
},
  "geometry": {"coordinates":[-71.368118,46.800041],"type":"Point"}
}