{
  "type": "Feature",
  "properties": {
    "iso:country":"CA",
    "sg:address":"495 Eglinton Ave W",
    "sg:city":"Toronto",
    "sg:classifiers":[
        {
            "category":"Restaurant",
            "type":"Food & Drink"
        }
    ],
    "sg:phone":"+1 416 489 0961",
    "sg:postcode":"M5N 1A7",
    "sg:province":"ON",
    "wof:name":"Autogrill",
    "wof:placetype":"venue"
},
  "geometry": {"coordinates":[-79.4129943848,43.7035598755],"type":"Point"}
}