{
  "type": "Feature",
  "properties": {
    "addr:full":"25 Rue Brosseau Saint-Stanislas-DE-Kostka QC J0S 1W0",
    "addr:housenumber":"25",
    "addr:postcode":"j0s 1w0",
    "addr:street":"Rue Brosseau",
    "iso:country":"CA",
    "sg:address":"25 Rue Brosseau",
    "sg:city":"Saint-Stanislas-DE-Kostka",
    "sg:classifiers":[
        {
            "category":"Restaurant",
            "type":"Food & Drink"
        }
    ],
    "sg:phone":"+1 450 377 1489",
    "sg:postcode":"J0S 1W0",
    "sg:province":"QC",
    "wof:name":"Terrasse DE LA Baie Des Brises",
    "wof:placetype":"venue"
},
  "geometry": {"coordinates":[-74.1618652344,45.2038116455],"type":"Point"}
}