{
  "type": "Feature",
  "properties": {
    "addr:full":"619 Rue Kennedy Coaticook QC J1A 2X2",
    "addr:housenumber":"619",
    "addr:postcode":"j1a 2x2",
    "addr:street":"Rue Kennedy",
    "iso:country":"CA",
    "sg:address":"619 Rue Kennedy",
    "sg:city":"Coaticook",
    "sg:classifiers":[
        {
            "category":"Manufacturing",
            "subcategory":"Lumber",
            "type":"Manufacturing & Wholesale Goods"
        }
    ],
    "sg:phone":"+1 819 849 2243",
    "sg:postcode":"J1A 2X2",
    "sg:province":"QC",
    "sg:tags":[
        "syrup",
        "maple",
        "sugar"
    ],
    "wof:name":"Erabliere Carbonneau",
    "wof:placetype":"venue"
},
  "geometry": {"coordinates":[-71.7914810181,45.127986908],"type":"Point"}
}