{
  "type": "Feature",
  "properties": {
    "addr:full":"7482 Vedder Rd Chilliwack BC V2R 4E7",
    "addr:housenumber":"7482",
    "addr:postcode":"v2r 4e7",
    "addr:street":"Vedder Rd",
    "iso:country":"CA",
    "sg:address":"7482 Vedder Rd",
    "sg:city":"Chilliwack",
    "sg:classifiers":[
        {
            "category":"Manufacturing",
            "subcategory":"Food",
            "type":"Manufacturing & Wholesale Goods"
        }
    ],
    "sg:phone":"+1 604 858 4711",
    "sg:postcode":"V2R 4E7",
    "sg:province":"BC",
    "sg:tags":[
        "baker",
        "cookie",
        "bakery"
    ],
    "wof:name":"Sardis Bakery",
    "wof:placetype":"venue"
},
  "geometry": {"coordinates":[-121.958778381,49.1379890442],"type":"Point"}
}