{
  "type": "Feature",
  "properties": {
    "addr:full":"610 10th Ave Montrose BC V0G 1P0",
    "addr:housenumber":"610",
    "addr:postcode":"v0g 1p0",
    "addr:street":"10Th Ave",
    "iso:country":"CA",
    "sg:address":"610 10th Ave",
    "sg:city":"Montrose",
    "sg:classifiers":[
        {
            "category":"Retail",
            "subcategory":"Auto Repair",
            "type":"Services"
        }
    ],
    "sg:phone":"+1 250 367 6676",
    "sg:postcode":"V0G 1P0",
    "sg:province":"BC",
    "sg:tags":[
        "repairing",
        "automobile"
    ],
    "wof:name":"Michel's Auto Repair",
    "wof:placetype":"venue"
},
  "geometry": {"coordinates":[-117.599907,49.074703],"type":"Point"}
}