{
  "type": "Feature",
  "properties": {
    "addr:full":"96 Macpherson St Revelstoke BC V0E 2S0",
    "addr:housenumber":"96",
    "addr:postcode":"v0e 2s0",
    "addr:street":"Macpherson St",
    "iso:country":"CA",
    "sg:address":"96 Macpherson St",
    "sg:city":"Revelstoke",
    "sg:classifiers":[
        {
            "category":"Retail",
            "subcategory":"Auto Rental",
            "type":"Services"
        }
    ],
    "sg:phone":"+1 250 837 3900",
    "sg:postcode":"V0E 2S0",
    "sg:province":"BC",
    "sg:tags":[
        "renting",
        "leasing",
        "truck",
        "trailer"
    ],
    "wof:name":"U-Haul CO Ltd",
    "wof:placetype":"venue"
},
  "geometry": {"coordinates":[-118.170783997,50.9937820435],"type":"Point"}
}