{
  "type": "Feature",
  "properties": {
    "addr:full":"942 Ashdale Cres W Peterborough ON K9H 7H5",
    "addr:housenumber":"942",
    "addr:postcode":"k9h 7h5",
    "addr:street":"Ashdale Cres W",
    "iso:country":"CA",
    "sg:address":"942 Ashdale Cres W",
    "sg:city":"Peterborough",
    "sg:classifiers":[
        {
            "category":"Professional",
            "subcategory":"Management & Consulting",
            "type":"Services"
        }
    ],
    "sg:phone":"+1 705 745 1262",
    "sg:postcode":"K9H 7H5",
    "sg:province":"ON",
    "sg:tags":[
        "break",
        "tea",
        "coffee",
        "supply"
    ],
    "wof:name":"Aroma Coffee Svc",
    "wof:placetype":"venue"
},
  "geometry": {"coordinates":[-78.311164856,44.3346138],"type":"Point"}
}