{
  "type": "Feature",
  "properties": {
    "addr:full":"Inwood ON N0N 1K0",
    "addr:postcode":"n0n 1k0",
    "iso:country":"CA",
    "sg:city":"Inwood",
    "sg:classifiers":[
        {
            "category":"Food & Beverages",
            "subcategory":"Groceries & Convenience Stores",
            "type":"Retail Goods"
        }
    ],
    "sg:phone":"+1 519 844 2433",
    "sg:postcode":"N0N 1K0",
    "sg:province":"ON",
    "sg:tags":[
        "grocer"
    ],
    "wof:name":"Inwood Grocery & Variety",
    "wof:placetype":"venue"
},
  "geometry": {"coordinates":[-81.98247499999999,42.817719],"type":"Point"}
}