{
  "type": "Feature",
  "properties": {
    "addr:full":"Montreal QC H4A 1S9",
    "addr:postcode":"h4a 1s9",
    "iso:country":"CA",
    "sg:city":"Montreal",
    "sg:classifiers":[
        {
            "category":"Health Services",
            "subcategory":"Doctor",
            "type":"Services"
        }
    ],
    "sg:phone":"+1 514 488 4582",
    "sg:postcode":"H4A 1S9",
    "sg:province":"QC",
    "sg:tags":[
        "physician",
        "surgeon"
    ],
    "wof:name":"Tataryn, Donna MD",
    "wof:placetype":"venue"
},
  "geometry": {"coordinates":[-73.55423,45.566135],"type":"Point"}
}