{
  "type": "Feature",
  "properties": {
    "iso:country":"CA",
    "sg:address":"939 Boul Decarie",
    "sg:city":"Saint-Laurent",
    "sg:classifiers":[
        {
            "category":"Food & Beverages",
            "subcategory":"Bakery",
            "type":"Retail Goods"
        }
    ],
    "sg:phone":"+1 514 748 7014",
    "sg:postcode":"H4L 3M3",
    "sg:province":"QC",
    "sg:tags":[
        "baker"
    ],
    "wof:name":"Vinh Hing",
    "wof:placetype":"venue"
},
  "geometry": {"coordinates":[-73.68116,45.513489],"type":"Point"}
}