{
  "type": "Feature",
  "properties": {
    "iso:country":"CA",
    "sg:address":"16 Water St",
    "sg:city":"Port Perry",
    "sg:classifiers":[
        {
            "category":"Government",
            "subcategory":"Office",
            "type":"Public Place"
        }
    ],
    "sg:phone":"+1 905 985 0373",
    "sg:postcode":"L9L 1J1",
    "sg:province":"ON",
    "wof:name":"Ontario Driver & Vehicle",
    "wof:placetype":"venue"
},
  "geometry": {"coordinates":[-78.93956756590001,44.1014213562],"type":"Point"}
}