{
  "type": "Feature",
  "properties": {
    "addr:full":"Calgary AB T2C 2K4",
    "addr:postcode":"t2c 2k4",
    "iso:country":"CA",
    "sg:city":"Calgary",
    "sg:classifiers":[
        {
            "category":"Retail",
            "subcategory":"Car Wash",
            "type":"Services"
        }
    ],
    "sg:phone":"+1 403 273 6630",
    "sg:postcode":"T2C 2K4",
    "sg:province":"AB",
    "sg:tags":[
        "polishing",
        "truck",
        "washing"
    ],
    "wof:name":"Great Northern Truck Wash Ltd",
    "wof:placetype":"venue"
},
  "geometry": {"coordinates":[-113.976783752,50.9892883301],"type":"Point"}
}