{
  "type": "Feature",
  "properties": {
    "iso:country":"CA",
    "sg:address":"978 Rue Saint-Pierre S",
    "sg:city":"Joliette",
    "sg:classifiers":[
        {
            "category":"Personal",
            "subcategory":"Beauty Salon",
            "type":"Services"
        }
    ],
    "sg:phone":"+1 450 759 8775",
    "sg:postcode":"J6E 3Z1",
    "sg:province":"QC",
    "wof:name":"Salon Rollande",
    "wof:placetype":"venue"
},
  "geometry": {"coordinates":[-73.4276504517,46.0085525513],"type":"Point"}
}