{
  "type": "Feature",
  "properties": {
    "addr:full":"2 Algonquin Ave Toronto ON M6R 1K7",
    "addr:housenumber":"2",
    "addr:postcode":"m6r 1k7",
    "addr:street":"Algonquin Ave",
    "iso:country":"CA",
    "sg:address":"2 Algonquin Ave",
    "sg:city":"Toronto",
    "sg:classifiers":[
        {
            "category":"Home & Garden",
            "subcategory":"Household Appliances",
            "type":"Retail Goods"
        }
    ],
    "sg:phone":"+1 905 780 9589",
    "sg:postcode":"M6R 1K7",
    "sg:province":"ON",
    "sg:tags":[
        "cleaners",
        "vacuum"
    ],
    "wof:name":"Rainbow Vacuum Cleaner Sales",
    "wof:placetype":"venue"
},
  "geometry": {"coordinates":[-79.45354500000001,43.643684],"type":"Point"}
}