{
  "type": "Feature",
  "properties": {
    "addr:full":"Saskatoon SK S7H 0W2",
    "addr:postcode":"s7h 0w2",
    "iso:country":"CA",
    "sg:city":"Saskatoon",
    "sg:classifiers":[
        {
            "category":"Health Services",
            "subcategory":"Medical Lab",
            "type":"Services"
        }
    ],
    "sg:phone":"+1 306 477 1000",
    "sg:postcode":"S7H 0W2",
    "sg:province":"SK",
    "sg:tags":[
        "x",
        "laboratory"
    ],
    "wof:name":"Saskatoon Medical Imaging Ctr",
    "wof:placetype":"venue"
},
  "geometry": {"coordinates":[-106.606170654,52.1145515442],"type":"Point"}
}