{
  "type": "Feature",
  "properties": {
    "iso:country":"CA",
    "sg:city":"Calgary",
    "sg:classifiers":[
        {
            "category":"Shopping",
            "subcategory":"Stationery & Office Supplies",
            "type":"Retail Goods"
        }
    ],
    "sg:phone":"+1 403 263 8105",
    "sg:postcode":"T2P 2R9",
    "sg:province":"AB",
    "wof:name":"Grand & Toy",
    "wof:placetype":"venue"
},
  "geometry": {"coordinates":[-114.065612793,51.0476341248],"type":"Point"}
}