{
  "type": "Feature",
  "properties": {
    "addr:full":"135 Sherbourne St Toronto ON M5A 2R5",
    "addr:housenumber":"135",
    "addr:postcode":"m5a 2r5",
    "addr:street":"Sherbourne St",
    "iso:country":"CA",
    "sg:address":"135 Sherbourne St",
    "sg:city":"Toronto",
    "sg:classifiers":[
        {
            "category":"Social Services",
            "type":"Services"
        }
    ],
    "sg:phone":"+1 416 366 2733",
    "sg:postcode":"M5A 2R5",
    "sg:province":"ON",
    "sg:tags":[
        "organization",
        "welfare"
    ],
    "wof:name":"Salvation Army Men's Hostel",
    "wof:placetype":"venue"
},
  "geometry": {"coordinates":[-79.369423,43.655003],"type":"Point"}
}