{
  "type": "Feature",
  "properties": {
    "addr:full":"2657 Rue DE Rouen Montreal QC H2K 1M9",
    "addr:housenumber":"2657",
    "addr:postcode":"h2k 1m9",
    "addr:street":"Rue De Rouen",
    "iso:country":"CA",
    "sg:address":"2657 Rue DE Rouen",
    "sg:city":"Montreal",
    "sg:classifiers":[
        {
            "category":"Restaurant",
            "type":"Food & Drink"
        }
    ],
    "sg:phone":"+1 514 526 0991",
    "sg:postcode":"H2K 1M9",
    "sg:province":"QC",
    "sg:tags":[
        "delicatessen"
    ],
    "wof:name":"Saucisses Polonaises Inc",
    "wof:placetype":"venue"
},
  "geometry": {"coordinates":[-73.555199,45.535473],"type":"Point"}
}