{
  "type": "Feature",
  "properties": {
    "addr:full":"458 Rue Acadie Beresford NB E8K 2C5",
    "addr:housenumber":"458",
    "addr:postcode":"e8k 2c5",
    "addr:street":"Rue Acadie",
    "iso:country":"CA",
    "sg:address":"458 Rue Acadie",
    "sg:city":"Beresford",
    "sg:classifiers":[
        {
            "category":"Retail",
            "subcategory":"Repair Shop",
            "type":"Services"
        }
    ],
    "sg:phone":"+1 506 542 9332",
    "sg:postcode":"E8K 2C5",
    "sg:province":"NB",
    "sg:tags":[
        "upholsterer"
    ],
    "wof:name":"Roy Rembourreur",
    "wof:placetype":"venue"
},
  "geometry": {"coordinates":[-65.730423,47.705353],"type":"Point"}
}