{
  "type": "Feature",
  "properties": {
    "iso:country":"CA",
    "sg:address":"789 Dovercourt Rd",
    "sg:city":"Toronto",
    "sg:classifiers":[
        {
            "category":"Organizations",
            "subcategory":"Religious Organization",
            "type":"Services"
        }
    ],
    "sg:phone":"+1 416 531 8031",
    "sg:postcode":"M6H 2X4",
    "sg:province":"ON",
    "sg:tags":[
        "church"
    ],
    "wof:name":"Salvation Army",
    "wof:placetype":"venue"
},
  "geometry": {"coordinates":[-79.4295806885,43.6625328064],"type":"Point"}
}