{
  "type": "Feature",
  "properties": {
    "iso:country":"CA",
    "sg:address":"110 Community Lane",
    "sg:city":"Fort Mcmurray",
    "sg:classifiers":[
        {
            "category":"Building & Trades",
            "subcategory":"Landscaping Services",
            "type":"Services"
        }
    ],
    "sg:phone":"+1 780 790 2331",
    "sg:postcode":"T9H 5B4",
    "sg:province":"AB",
    "sg:tags":[
        "contractor",
        "landscape",
        "general"
    ],
    "wof:name":"Wilco Landscape Contractors",
    "wof:placetype":"venue"
},
  "geometry": {"coordinates":[-111.134162903,56.6582260132],"type":"Point"}
}