{
  "type": "Feature",
  "properties": {
    "addr:full":"21 Blain Ave Cambridge ON N1R 7Y6",
    "addr:housenumber":"21",
    "addr:postcode":"n1r 7y6",
    "addr:street":"Blain Ave",
    "iso:country":"CA",
    "sg:address":"21 Blain Ave",
    "sg:city":"Cambridge",
    "sg:classifiers":[
        {
            "category":"Retail",
            "subcategory":"Auto Repair",
            "type":"Services"
        }
    ],
    "sg:phone":"+1 519 622 9507",
    "sg:postcode":"N1R 7Y6",
    "sg:province":"ON",
    "sg:tags":[
        "wrecker"
    ],
    "wof:name":"Cabral Towing",
    "wof:placetype":"venue"
},
  "geometry": {"coordinates":[-80.316063,43.377975],"type":"Point"}
}