{
  "type": "Feature",
  "properties": {
    "addr:full":"218 Centennial Crt Kitchener ON N2B 3X2",
    "addr:housenumber":"218",
    "addr:postcode":"n2b 3x2",
    "addr:street":"Centennial Crt",
    "iso:country":"CA",
    "sg:address":"218 Centennial Crt",
    "sg:city":"Kitchener",
    "sg:classifiers":[
        {
            "category":"Wholesale",
            "subcategory":"Electrical",
            "type":"Manufacturing & Wholesale Goods"
        }
    ],
    "sg:phone":"+1 519 742 7010",
    "sg:postcode":"N2B 3X2",
    "sg:province":"ON",
    "sg:tags":[
        "battery"
    ],
    "wof:name":"Interstate Battery",
    "wof:placetype":"venue"
},
  "geometry": {"coordinates":[-80.4285812378,43.4754714966],"type":"Point"}
}