{
  "type": "Feature",
  "properties": {
    "addr:full":"2 Rue Laurier Ste-Catherine-DE-LA-J-Cartier QC G0A 3M0",
    "addr:housenumber":"2",
    "addr:postcode":"g0a 3m0",
    "addr:street":"Rue Laurier",
    "iso:country":"CA",
    "sg:address":"2 Rue Laurier",
    "sg:city":"Ste-Catherine-DE-LA-J-Cartier",
    "sg:classifiers":[
        {
            "category":"Professional",
            "subcategory":"Business Services",
            "type":"Services"
        }
    ],
    "sg:phone":"+1 418 875 1671",
    "sg:postcode":"G0A 3M0",
    "sg:province":"QC",
    "sg:tags":[
        "notary"
    ],
    "wof:name":"Boilard & Renaud",
    "wof:placetype":"venue"
},
  "geometry": {"coordinates":[-66.682510376,49.0959510803],"type":"Point"}
}