{
  "type": "Feature",
  "properties": {
    "iso:country":"CA",
    "sg:address":"5121 9th Ave #B",
    "sg:city":"Okanagan Falls",
    "sg:classifiers":[
        {
            "category":"Manufacturing",
            "subcategory":"Printing",
            "type":"Manufacturing & Wholesale Goods"
        }
    ],
    "sg:phone":"+1 250 497 8880",
    "sg:postcode":"V0H 1R0",
    "sg:province":"BC",
    "sg:tags":[
        "newspaper"
    ],
    "wof:name":"Okanagan Falls Review",
    "wof:placetype":"venue"
},
  "geometry": {"coordinates":[-119.573257446,49.3448219299],"type":"Point"}
}