{
  "type": "Feature",
  "properties": {
    "addr:full":"Elgin MB R0K 0T0",
    "addr:postcode":"r0k 0t0",
    "iso:country":"CA",
    "sg:city":"Elgin",
    "sg:classifiers":[
        {
            "category":"Farming",
            "subcategory":"Farm & Veterinary Services",
            "type":"Manufacturing & Wholesale Goods"
        }
    ],
    "sg:phone":"+1 204 769 2343",
    "sg:postcode":"R0K 0T0",
    "sg:province":"MB",
    "sg:tags":[
        "product",
        "protection",
        "crop"
    ],
    "wof:name":"Agricore United",
    "wof:placetype":"venue"
},
  "geometry": {"coordinates":[-100.05898999999999,49.230293],"type":"Point"}
}