{
  "type": "Feature",
  "properties": {
    "iso:country":"CA",
    "sg:city":"Middleton",
    "sg:classifiers":[
        {
            "category":"Building & Trades",
            "subcategory":"Plumbing",
            "type":"Services"
        }
    ],
    "sg:phone":"+1 902 824 0183",
    "sg:postcode":"B0S 1P0",
    "sg:province":"NS",
    "sg:tags":[
        "contractor"
    ],
    "wof:name":"Scott Punks Plumbing Svc",
    "wof:placetype":"venue"
},
  "geometry": {"coordinates":[-65.068649292,44.9424095154],"type":"Point"}
}