{
  "type": "Feature",
  "properties": {
    "iso:country":"CA",
    "sg:address":"440 Eglinton Ave E",
    "sg:city":"Toronto",
    "sg:classifiers":[
        {
            "category":"Professional",
            "subcategory":"Management & Consulting",
            "type":"Services"
        }
    ],
    "sg:phone":"+1 416 459 6689",
    "sg:postcode":"M4P 1M2",
    "sg:province":"ON",
    "sg:tags":[
        "communications",
        "consultant"
    ],
    "wof:name":"Youthopia Communications",
    "wof:placetype":"venue"
},
  "geometry": {"coordinates":[-79.384644,43.70969],"type":"Point"}
}