{
  "type": "Feature",
  "properties": {
    "addr:full":"1051 Brock Rd Pickering ON L1W 3T7",
    "addr:housenumber":"1051",
    "addr:postcode":"l1w 3t7",
    "addr:street":"Brock Rd",
    "iso:country":"CA",
    "sg:address":"1051 Brock Rd",
    "sg:city":"Pickering",
    "sg:classifiers":[
        {
            "category":"Retail",
            "subcategory":"Auto Repair",
            "type":"Services"
        }
    ],
    "sg:phone":"+1 905 426 5509",
    "sg:postcode":"L1W 3T7",
    "sg:province":"ON",
    "sg:tags":[
        "van",
        "conversion",
        "truck",
        "accessory"
    ],
    "wof:name":"Action Van & Truck World",
    "wof:placetype":"venue"
},
  "geometry": {"coordinates":[-79.068909,43.836094],"type":"Point"}
}