{
  "type": "Feature",
  "properties": {
    "addr:full":"1299 Cheadle St W Swift Current SK S9H 0C8",
    "addr:housenumber":"1299",
    "addr:postcode":"s9h 0c8",
    "addr:street":"Cheadle St W",
    "iso:country":"CA",
    "sg:address":"1299 Cheadle St W",
    "sg:city":"Swift Current",
    "sg:classifiers":[
        {
            "category":"Retail",
            "subcategory":"Repair Shop",
            "type":"Services"
        }
    ],
    "sg:phone":"+1 306 773 7695",
    "sg:postcode":"S9H 0C8",
    "sg:province":"SK",
    "sg:tags":[
        "welding"
    ],
    "wof:name":"Thor Welding & Machining Inc",
    "wof:placetype":"venue"
},
  "geometry": {"coordinates":[-107.816802978,50.283454895],"type":"Point"}
}