{
  "type": "Feature",
  "properties": {
    "addr:full":"301 George St Sarnia ON N7T 4P3",
    "addr:housenumber":"301",
    "addr:postcode":"n7t 4p3",
    "addr:street":"George St",
    "iso:country":"CA",
    "sg:address":"301 George St",
    "sg:city":"Sarnia",
    "sg:classifiers":[
        {
            "category":"Shopping",
            "subcategory":"Computers & Home Electronics",
            "type":"Retail Goods"
        }
    ],
    "sg:phone":"+1 519 383 1474",
    "sg:postcode":"N7T 4P3",
    "sg:province":"ON",
    "sg:tags":[
        "equipment",
        "dealer",
        "software"
    ],
    "wof:name":"Softech Computers",
    "wof:placetype":"venue"
},
  "geometry": {"coordinates":[-82.399368,42.974216],"type":"Point"}
}