{
  "type": "Feature",
  "properties": {
    "addr:full":"3474 Ellis Pl Nanaimo BC V9T 5H5",
    "addr:housenumber":"3474",
    "addr:postcode":"v9t 5h5",
    "addr:street":"Ellis Pl",
    "iso:country":"CA",
    "sg:address":"3474 Ellis Pl",
    "sg:city":"Nanaimo",
    "sg:classifiers":[
        {
            "category":"Professional",
            "subcategory":"Accounting & Tax Preparation",
            "type":"Services"
        }
    ],
    "sg:phone":"+1 250 756 3242",
    "sg:postcode":"V9T 5H5",
    "sg:province":"BC",
    "sg:tags":[
        "bookkeeping",
        "general"
    ],
    "wof:name":"Bickerton Bookkeeping Svc",
    "wof:placetype":"venue"
},
  "geometry": {"coordinates":[-123.946442,49.216557],"type":"Point"}
}