{
  "type": "Feature",
  "properties": {
    "addr:full":"545 Rue Daviau Les Cedres QC J7T 1H5",
    "addr:housenumber":"545",
    "addr:postcode":"j7t 1h5",
    "addr:street":"Rue Daviau",
    "iso:country":"CA",
    "sg:address":"545 Rue Daviau",
    "sg:city":"Les Cedres",
    "sg:classifiers":[
        {
            "category":"Home & Garden",
            "subcategory":"Furniture",
            "type":"Retail Goods"
        }
    ],
    "sg:phone":"+1 450 452 4267",
    "sg:postcode":"J7T 1H5",
    "sg:province":"QC",
    "sg:tags":[
        "kitchen",
        "maker",
        "cabinet"
    ],
    "wof:name":"Ebenisterie Jacques Fortier",
    "wof:placetype":"venue"
},
  "geometry": {"coordinates":[-74.070984,45.325748],"type":"Point"}
}