{
  "type": "Feature",
  "properties": {
    "addr:full":"8250 Boul Taschereau Brossard QC J4X 1C2",
    "addr:housenumber":"8250",
    "addr:postcode":"j4x 1c2",
    "addr:street":"Boul Taschereau",
    "iso:country":"CA",
    "sg:address":"8250 Boul Taschereau",
    "sg:city":"Brossard",
    "sg:classifiers":[
        {
            "category":"Food & Beverages",
            "subcategory":"Groceries & Convenience Stores",
            "type":"Retail Goods"
        }
    ],
    "sg:phone":"+1 450 466 3879",
    "sg:postcode":"J4X 1C2",
    "sg:province":"QC",
    "sg:tags":[
        "product"
    ],
    "wof:name":"Petro-Canada",
    "wof:placetype":"venue"
},
  "geometry": {"coordinates":[-73.4702835083,45.4473228455],"type":"Point"}
}