{
  "type": "Feature",
  "properties": {
    "addr:full":"Calgary AB T2G 5M8",
    "addr:postcode":"t2g 5m8",
    "iso:country":"CA",
    "sg:city":"Calgary",
    "sg:classifiers":[
        {
            "category":"Building & Trades",
            "subcategory":"Construction",
            "type":"Services"
        }
    ],
    "sg:phone":"+1 403 287 2002",
    "sg:postcode":"T2G 5M8",
    "sg:province":"AB",
    "sg:tags":[
        "repairing",
        "deck",
        "builder",
        "contractor",
        "remodeling",
        "patio"
    ],
    "wof:name":"Calgary Weatherdek",
    "wof:placetype":"venue"
},
  "geometry": {"coordinates":[-114.033669,51.007343],"type":"Point"}
}