{
  "type": "Feature",
  "properties": {
    "addr:full":"705 Millidge Ave Saint John NB E2K 2N7",
    "addr:housenumber":"705",
    "addr:postcode":"e2k 2n7",
    "addr:street":"Millidge Ave",
    "iso:country":"CA",
    "sg:address":"705 Millidge Ave",
    "sg:city":"Saint John",
    "sg:classifiers":[
        {
            "category":"Health Services",
            "subcategory":"Doctor",
            "type":"Services"
        }
    ],
    "sg:phone":"+1 506 648 7954",
    "sg:postcode":"E2K 2N7",
    "sg:province":"NB",
    "sg:tags":[
        "physician",
        "surgeon"
    ],
    "wof:name":"Sparkes, Gerald L MD",
    "wof:placetype":"venue"
},
  "geometry": {"coordinates":[-66.096901,45.294579],"type":"Point"}
}