{
  "type": "Feature",
  "properties": {
    "addr:full":"168 Main St Thessalon ON P0R 1L0",
    "addr:housenumber":"168",
    "addr:postcode":"p0r 1l0",
    "addr:street":"Main St",
    "iso:country":"CA",
    "sg:address":"168 Main St",
    "sg:city":"Thessalon",
    "sg:classifiers":[
        {
            "category":"Shopping",
            "subcategory":"Gifts & Souvenirs",
            "type":"Retail Goods"
        }
    ],
    "sg:phone":"+1 705 842 0378",
    "sg:postcode":"P0R 1L0",
    "sg:province":"ON",
    "sg:tags":[
        "apparel",
        "shop"
    ],
    "wof:name":"Forestland Clothing & Gifts",
    "wof:placetype":"venue"
},
  "geometry": {"coordinates":[-83.557137,46.25629],"type":"Point"}
}