{
  "type": "Feature",
  "properties": {
    "addr:full":"655 Place Auclair Vanier QC G1M 3G4",
    "addr:housenumber":"655",
    "addr:postcode":"g1m 3g4",
    "addr:street":"Place Auclair",
    "iso:country":"CA",
    "sg:address":"655 Place Auclair",
    "sg:city":"Vanier",
    "sg:classifiers":[
        {
            "category":"Wholesale",
            "subcategory":"Non-durable Goods",
            "type":"Manufacturing & Wholesale Goods"
        }
    ],
    "sg:phone":"+1 418 681 0213",
    "sg:postcode":"G1M 3G4",
    "sg:province":"QC",
    "wof:name":"Distributions Amj",
    "wof:placetype":"venue"
},
  "geometry": {"coordinates":[-71.263077,46.813946],"type":"Point"}
}