{
  "type": "Feature",
  "properties": {
    "addr:full":"10583 Av L'Archeveque Montreal-Nord QC H1H 3A1",
    "addr:housenumber":"10583",
    "addr:postcode":"h1h 3a1",
    "addr:street":"Av L'Archeveque",
    "iso:country":"CA",
    "sg:address":"10583 Av L'Archeveque",
    "sg:city":"Montreal-Nord",
    "sg:classifiers":[
        {
            "category":"Professional",
            "subcategory":"Business Services",
            "type":"Services"
        }
    ],
    "sg:phone":"+1 514 329 3119",
    "sg:postcode":"H1H 3A1",
    "sg:province":"QC",
    "wof:name":"Distributions E Bianco Inc",
    "wof:placetype":"venue"
},
  "geometry": {"coordinates":[-73.625435,45.593037],"type":"Point"}
}