{
  "type": "Feature",
  "properties": {
    "iso:country":"CA",
    "sg:address":"194 Argyle St S",
    "sg:city":"Caledonia",
    "sg:classifiers":[
        {
            "category":"Retail",
            "subcategory":"Car Wash",
            "type":"Services"
        }
    ],
    "sg:phone":"+1 905 765 0966",
    "sg:postcode":"N3W 1K7",
    "sg:province":"ON",
    "sg:tags":[
        "polishing",
        "washing"
    ],
    "wof:name":"Caledonia Auto Laundry",
    "wof:placetype":"venue"
},
  "geometry": {"coordinates":[-79.9568481445,43.0667648315],"type":"Point"}
}