{
  "type": "Feature",
  "properties": {
    "addr:full":"1 Rue Vieux Chemin Squatec QC G0L 4H0",
    "addr:housenumber":"1",
    "addr:postcode":"g0l 4h0",
    "addr:street":"Rue Vieux Chemin Squatec",
    "iso:country":"CA",
    "sg:address":"1 Rue Vieux Chemin",
    "sg:city":"Squatec",
    "sg:classifiers":[
        {
            "category":"Building & Trades",
            "subcategory":"Construction",
            "type":"Services"
        }
    ],
    "sg:phone":"+1 418 855 2107",
    "sg:postcode":"G0L 4H0",
    "sg:province":"QC",
    "sg:tags":[
        "repairing",
        "contractor",
        "remodeling",
        "general"
    ],
    "wof:name":"Fabricomat Inc",
    "wof:placetype":"venue"
},
  "geometry": {"coordinates":[-68.723145,47.881096],"type":"Point"}
}