{
  "type": "Feature",
  "properties": {
    "addr:full":"Etobicoke ON M9C 5K8",
    "addr:postcode":"m9c 5k8",
    "iso:country":"CA",
    "sg:city":"Etobicoke",
    "sg:classifiers":[
        {
            "category":"Building & Trades",
            "subcategory":"Electrical",
            "type":"Services"
        }
    ],
    "sg:phone":"+1 416 626 2229",
    "sg:postcode":"M9C 5K8",
    "sg:province":"ON",
    "sg:tags":[
        "equipment",
        "telecommunication"
    ],
    "wof:name":"Xentrax Information Systems",
    "wof:placetype":"venue"
},
  "geometry": {"coordinates":[-79.558876,43.626198],"type":"Point"}
}