{
  "type": "Feature",
  "properties": {
    "addr:full":"Delta BC V3M 6S6",
    "addr:postcode":"v3m 6s6",
    "iso:country":"CA",
    "sg:city":"Delta",
    "sg:classifiers":[
        {
            "category":"Manufacturing",
            "subcategory":"Paper Products",
            "type":"Manufacturing & Wholesale Goods"
        }
    ],
    "sg:phone":"+1 604 525 7898",
    "sg:postcode":"V3M 6S6",
    "sg:province":"BC",
    "sg:tags":[
        "scanning",
        "code",
        "bar"
    ],
    "wof:name":"Trans Canada Labels",
    "wof:placetype":"venue"
},
  "geometry": {"coordinates":[-123.059593201,49.0848007202],"type":"Point"}
}