{
  "type": "Feature",
  "properties": {
    "addr:full":"317 River Glen Blvd Oakville ON L6H 5X9",
    "addr:housenumber":"317",
    "addr:postcode":"l6h 5x9",
    "addr:street":"River Glen Blvd",
    "iso:country":"CA",
    "sg:address":"317 River Glen Blvd",
    "sg:city":"Oakville",
    "sg:classifiers":[
        {
            "category":"Professional",
            "subcategory":"Art Services",
            "type":"Services"
        }
    ],
    "sg:phone":"+1 905 257 5667",
    "sg:postcode":"L6H 5X9",
    "sg:province":"ON",
    "sg:tags":[
        "graphic",
        "designer"
    ],
    "wof:name":"Jlc Group",
    "wof:placetype":"venue"
},
  "geometry": {"coordinates":[-79.7360992432,43.469745636],"type":"Point"}
}