{
  "type": "Feature",
  "properties": {
    "addr:full":"854 Boul Laure Sept-Iles QC G4R 1Y7",
    "addr:housenumber":"854",
    "addr:postcode":"g4r 1y7",
    "addr:street":"Boul Laure Sept-Iles",
    "iso:country":"CA",
    "sg:address":"854 Boul Laure",
    "sg:city":"Sept-Iles",
    "sg:classifiers":[
        {
            "category":"Travel",
            "subcategory":"Hotels & Motels",
            "type":"Entertainment"
        }
    ],
    "sg:phone":"+1 418 968 6005",
    "sg:postcode":"G4R 1Y7",
    "sg:province":"QC",
    "wof:name":"Comfort Inn",
    "wof:placetype":"venue"
},
  "geometry": {"coordinates":[-66.390327,50.225071],"type":"Point"}
}