{
  "type": "Feature",
  "properties": {
    "addr:full":"255 Albert St Ottawa ON K1A 0H2",
    "addr:housenumber":"255",
    "addr:postcode":"k1a 0h2",
    "addr:street":"Albert St",
    "iso:country":"CA",
    "sg:address":"255 Albert St",
    "sg:city":"Ottawa",
    "sg:classifiers":[
        {
            "category":"Food & Beverages",
            "subcategory":"Bakery",
            "type":"Retail Goods"
        }
    ],
    "sg:phone":"+1 613 233 9196",
    "sg:postcode":"K1A 0H2",
    "sg:province":"ON",
    "sg:tags":[
        "baker"
    ],
    "wof:name":"Cantor Bakeries",
    "wof:placetype":"venue"
},
  "geometry": {"coordinates":[-75.700729,45.41993],"type":"Point"}
}