{
  "type": "Feature",
  "properties": {
    "iso:country":"CA",
    "sg:address":"1295 Burnhamthorpe Rd E",
    "sg:city":"Mississauga",
    "sg:classifiers":[
        {
            "category":"Insurance",
            "subcategory":"Insurance Agent",
            "type":"Services"
        }
    ],
    "sg:phone":"+1 905 206 0707",
    "sg:postcode":"L4Y 3V7",
    "sg:province":"ON",
    "wof:name":"Humberview Insurance Brokers",
    "wof:placetype":"venue"
},
  "geometry": {"coordinates":[-79.60465240480001,43.620803833],"type":"Point"}
}