{
  "type": "Feature",
  "properties": {
    "iso:country":"CA",
    "sg:address":"4332 48th St #10",
    "sg:city":"Chetwynd",
    "sg:classifiers":[
        {
            "category":"Building & Trades",
            "subcategory":"Construction",
            "type":"Services"
        }
    ],
    "sg:phone":"+1 250 788 3633",
    "sg:postcode":"V0C 1J0",
    "sg:province":"BC",
    "sg:tags":[
        "insulation",
        "heat",
        "contractor"
    ],
    "wof:name":"Albrico Services Ltd",
    "wof:placetype":"venue"
},
  "geometry": {"coordinates":[-121.617104,55.707283],"type":"Point"}
}