{
  "type": "Feature",
  "properties": {
    "addr:full":"9920 Rue Parthenais Montreal QC H2B 2L4",
    "addr:housenumber":"9920",
    "addr:postcode":"h2b 2l4",
    "addr:street":"Rue Parthenais",
    "iso:country":"CA",
    "sg:address":"9920 Rue Parthenais",
    "sg:city":"Montreal",
    "sg:classifiers":[
        {
            "category":"Education",
            "subcategory":"School",
            "type":"Public Place"
        }
    ],
    "sg:phone":"+1 514 596 5560",
    "sg:postcode":"H2B 2L4",
    "sg:province":"QC",
    "wof:name":"Saints-Martyrs-Canadiens Ecole",
    "wof:placetype":"venue"
},
  "geometry": {"coordinates":[-73.645554,45.570454],"type":"Point"}
}