{
  "type": "Feature",
  "properties": {
    "addr:full":"9443 120 St Delta BC V4C 6S2",
    "addr:housenumber":"9443",
    "addr:postcode":"v4c 6s2",
    "addr:street":"120 St",
    "iso:country":"CA",
    "sg:address":"9443 120 St",
    "sg:city":"Delta",
    "sg:classifiers":[
        {
            "category":"Manufacturing",
            "subcategory":"Printing",
            "type":"Manufacturing & Wholesale Goods"
        }
    ],
    "sg:phone":"+1 604 583 4923",
    "sg:postcode":"V4C 6S2",
    "sg:province":"BC",
    "sg:tags":[
        "printer"
    ],
    "wof:name":"Delta Copy Ctr",
    "wof:placetype":"venue"
},
  "geometry": {"coordinates":[-122.890426636,49.1745910645],"type":"Point"}
}