{
  "type": "Feature",
  "properties": {
    "iso:country":"CA",
    "sg:address":"9147 Boul Pie-Ix",
    "sg:city":"Montreal",
    "sg:classifiers":[
        {
            "category":"Shopping",
            "subcategory":"Jewelry",
            "type":"Retail Goods"
        }
    ],
    "sg:phone":"+1 514 328 8990",
    "sg:postcode":"H1Z 3V9",
    "sg:province":"QC",
    "sg:tags":[
        "platinum",
        "silver",
        "gold"
    ],
    "wof:name":"Argent Comptant Paulo Inc",
    "wof:placetype":"venue"
},
  "geometry": {"coordinates":[-73.6215133667,45.5800590515],"type":"Point"}
}