{
  "type": "Feature",
  "properties": {
    "addr:full":"1368 Main St Winnipeg MB R2W 3T8",
    "addr:housenumber":"1368",
    "addr:postcode":"r2w 3t8",
    "addr:street":"Main St",
    "iso:country":"CA",
    "sg:address":"1368 Main St",
    "sg:city":"Winnipeg",
    "sg:classifiers":[
        {
            "category":"Retail",
            "subcategory":"Laundry & Dry Cleaning",
            "type":"Services"
        }
    ],
    "sg:phone":"+1 204 582 2886",
    "sg:postcode":"R2W 3T8",
    "sg:province":"MB",
    "sg:tags":[
        "cleaners"
    ],
    "wof:name":"Aqua-Magic Laundromat",
    "wof:placetype":"venue"
},
  "geometry": {"coordinates":[-97.126137,49.92445],"type":"Point"}
}