{
  "type": "Feature",
  "properties": {
    "iso:country":"CA",
    "sg:address":"725 9th Ave SW",
    "sg:city":"Moose Jaw",
    "sg:classifiers":[
        {
            "category":"Organizations",
            "subcategory":"Religious Organization",
            "type":"Services"
        }
    ],
    "sg:phone":"+1 306 692 7582",
    "sg:postcode":"S6H 5X2",
    "sg:province":"SK",
    "sg:tags":[
        "church"
    ],
    "wof:name":"Holy Trinity Orthodox Church",
    "wof:placetype":"venue"
},
  "geometry": {"coordinates":[-105.557403565,50.3810348511],"type":"Point"}
}