{
  "type": "Feature",
  "properties": {
    "addr:full":"421 Bay St #600 Sault Ste Marie ON P6A 1X3",
    "addr:housenumber":"421",
    "addr:postcode":"p6a 1x3",
    "addr:street":"Bay St # 600",
    "iso:country":"CA",
    "sg:address":"421 Bay St #600",
    "sg:city":"Sault Ste Marie",
    "sg:classifiers":[
        {
            "category":"Professional",
            "subcategory":"Lawyer & Legal Services",
            "type":"Services"
        }
    ],
    "sg:phone":"+1 705 949 7790",
    "sg:postcode":"P6A 1X3",
    "sg:province":"ON",
    "sg:tags":[
        "attorney"
    ],
    "wof:name":"Paciocco, Robert W",
    "wof:placetype":"venue"
},
  "geometry": {"coordinates":[-84.335083,46.51104],"type":"Point"}
}