{
  "type": "Feature",
  "properties": {
    "addr:full":"345 Rainbow Rd Salt Spring Island BC V8K 2M4",
    "addr:housenumber":"345",
    "addr:postcode":"v8k 2m4",
    "addr:street":"Rainbow Rd",
    "iso:country":"CA",
    "sg:address":"345 Rainbow Rd",
    "sg:city":"Salt Spring Island",
    "sg:classifiers":[
        {
            "category":"Home & Garden",
            "subcategory":"Building Materials",
            "type":"Retail Goods"
        }
    ],
    "sg:phone":"+1 250 537 2611",
    "sg:postcode":"V8K 2M4",
    "sg:province":"BC",
    "sg:tags":[
        "mixed",
        "concrete"
    ],
    "wof:name":"Gulf Coast Materials Ltd",
    "wof:placetype":"venue"
},
  "geometry": {"coordinates":[-123.516869,48.854053],"type":"Point"}
}