{
  "type": "Feature",
  "properties": {
    "addr:full":"12180 152 St NW Edmonton AB T5V 1S1",
    "addr:housenumber":"12180",
    "addr:postcode":"t5v 1s1",
    "addr:street":"152 St Nw",
    "iso:country":"CA",
    "sg:address":"12180 152 St NW",
    "sg:city":"Edmonton",
    "sg:classifiers":[
        {
            "category":"Building & Trades",
            "subcategory":"Plumbing",
            "type":"Services"
        }
    ],
    "sg:phone":"+1 780 451 4943",
    "sg:postcode":"T5V 1S1",
    "sg:province":"AB",
    "sg:tags":[
        "contractor"
    ],
    "wof:name":"Petrin Mechanical Ltd",
    "wof:placetype":"venue"
},
  "geometry": {"coordinates":[-113.582427978,53.5746841431],"type":"Point"}
}