{
  "type": "Feature",
  "properties": {
    "iso:country":"CA",
    "sg:address":"10991 Rue Des Montagnards",
    "sg:city":"Beaupre",
    "sg:classifiers":[
        {
            "category":"Arena",
            "subcategory":"Sports Club",
            "type":"Entertainment"
        }
    ],
    "sg:phone":"+1 418 827 4501",
    "sg:postcode":"G0A 1E0",
    "sg:province":"QC",
    "sg:tags":[
        "athletic",
        "fields",
        "stadium"
    ],
    "wof:name":"Arena Cote DE Beaupre",
    "wof:placetype":"venue"
},
  "geometry": {"coordinates":[-70.8994674683,47.041721344],"type":"Point"}
}