{
  "type": "Feature",
  "properties": {
    "addr:full":"310 Bristol Rd E Mississauga ON L4Z 3V5",
    "addr:housenumber":"310",
    "addr:postcode":"l4z 3v5",
    "addr:street":"Bristol Rd E",
    "iso:country":"CA",
    "sg:address":"310 Bristol Rd E",
    "sg:city":"Mississauga",
    "sg:classifiers":[
        {
            "category":"Social Services",
            "subcategory":"Child Care",
            "type":"Services"
        }
    ],
    "sg:phone":"+1 905 501 0436",
    "sg:postcode":"L4Z 3V5",
    "sg:province":"ON",
    "sg:tags":[
        "kindergarten",
        "academic",
        "school"
    ],
    "wof:name":"Heritage Montessori Inc",
    "wof:placetype":"venue"
},
  "geometry": {"coordinates":[-79.6528549194,43.6177215576],"type":"Point"}
}