{
  "type": "Feature",
  "properties": {
    "addr:full":"2027 Churchill Ave Burlington ON L7R 3T8",
    "addr:housenumber":"2027",
    "addr:postcode":"l7r 3t8",
    "addr:street":"Churchill Ave",
    "iso:country":"CA",
    "sg:address":"2027 Churchill Ave",
    "sg:city":"Burlington",
    "sg:classifiers":[
        {
            "category":"Building & Trades",
            "subcategory":"Cleaning & Sanitation",
            "type":"Services"
        }
    ],
    "sg:phone":"+1 905 639 3513",
    "sg:postcode":"L7R 3T8",
    "sg:province":"ON",
    "sg:tags":[
        "butler",
        "maid"
    ],
    "wof:name":"Clean & Tidy Maid Svc",
    "wof:placetype":"venue"
},
  "geometry": {"coordinates":[-79.8187408447,43.3406486511],"type":"Point"}
}