{
  "type": "Feature",
  "properties": {
    "addr:full":"304 Hwy 3 Manitou MB R0G 1G0",
    "addr:housenumber":"304",
    "addr:postcode":"r0g 1g0",
    "addr:street":"Hwy 3",
    "iso:country":"CA",
    "sg:address":"304 Hwy 3",
    "sg:city":"Manitou",
    "sg:classifiers":[
        {
            "category":"Wholesale",
            "subcategory":"Machinery & Supplies",
            "type":"Manufacturing & Wholesale Goods"
        }
    ],
    "sg:phone":"+1 204 242 2646",
    "sg:postcode":"R0G 1G0",
    "sg:province":"MB",
    "sg:tags":[
        "farm",
        "equipment",
        "dryer",
        "grain",
        "drying"
    ],
    "wof:name":"Ark New-Tech Ltd",
    "wof:placetype":"venue"
},
  "geometry": {"coordinates":[-98.529274,49.236725],"type":"Point"}
}