{
  "type": "Feature",
  "properties": {
    "addr:full":"11520 Ellerslie Rd SW Edmonton AB T6W 1A2",
    "addr:housenumber":"11520",
    "addr:postcode":"t6w 1a2",
    "addr:street":"Ellerslie Rd",
    "iso:country":"CA",
    "sg:address":"11520 Ellerslie Rd SW",
    "sg:city":"Edmonton",
    "sg:classifiers":[
        {
            "category":"Organizations",
            "subcategory":"Religious Organization",
            "type":"Services"
        }
    ],
    "sg:phone":"+1 780 988 5433",
    "sg:postcode":"T6W 1A2",
    "sg:province":"AB",
    "sg:tags":[
        "church"
    ],
    "wof:name":"Victory Christian Ctr",
    "wof:placetype":"venue"
},
  "geometry": {"coordinates":[-113.522346,53.425037],"type":"Point"}
}