{
  "type": "Feature",
  "properties": {
    "addr:full":"77 James St N Hamilton ON L8R 2K3",
    "addr:housenumber":"77",
    "addr:postcode":"l8r 2k3",
    "addr:street":"James St N",
    "iso:country":"CA",
    "sg:address":"77 James St N",
    "sg:city":"Hamilton",
    "sg:classifiers":[
        {
            "category":"Shopping",
            "subcategory":"Department Store",
            "type":"Retail Goods"
        }
    ],
    "sg:phone":"+1 905 525 7483",
    "sg:postcode":"L8R 2K3",
    "sg:province":"ON",
    "sg:tags":[
        "shop"
    ],
    "wof:name":"Liquidation World Inc",
    "wof:placetype":"venue"
},
  "geometry": {"coordinates":[-79.86837768549999,43.2587852478],"type":"Point"}
}