{
  "type": "Feature",
  "properties": {
    "iso:country":"CA",
    "sg:address":"RR 1",
    "sg:city":"Eden",
    "sg:classifiers":[
        {
            "category":"Building & Trades",
            "subcategory":"Plumbing",
            "type":"Services"
        }
    ],
    "sg:phone":"+1 519 866 5566",
    "sg:postcode":"N0J 1H0",
    "sg:province":"ON",
    "sg:tags":[
        "heating",
        "contractor"
    ],
    "wof:name":"Firby Heating",
    "wof:placetype":"venue"
},
  "geometry": {"coordinates":[-80.7461853027,42.7933807373],"type":"Point"}
}