{
  "type": "Feature",
  "properties": {
    "addr:full":"338 Montee Des Saules Rimouski QC G5L 8Y9",
    "addr:housenumber":"338",
    "addr:postcode":"g5l 8y9",
    "addr:street":"Montee Des Saules",
    "iso:country":"CA",
    "sg:address":"338 Montee Des Saules",
    "sg:city":"Rimouski",
    "sg:classifiers":[
        {
            "category":"Building & Trades",
            "subcategory":"Construction",
            "type":"Services"
        }
    ],
    "sg:phone":"+1 418 725 4275",
    "sg:postcode":"G5L 8Y9",
    "sg:province":"QC",
    "sg:tags":[
        "general",
        "contractor"
    ],
    "wof:name":"Construction Albert Inc",
    "wof:placetype":"venue"
},
  "geometry": {"coordinates":[-68.576759,48.418514],"type":"Point"}
}