{
  "type": "Feature",
  "properties": {
    "addr:full":"Trois-Pistoles QC G0L 4K0",
    "addr:postcode":"g0l 4k0",
    "iso:country":"CA",
    "sg:city":"Trois-Pistoles",
    "sg:classifiers":[
        {
            "category":"Cinema",
            "subcategory":"Movie Theater",
            "type":"Entertainment"
        }
    ],
    "sg:phone":"+1 418 851 4759",
    "sg:postcode":"G0L 4K0",
    "sg:province":"QC",
    "wof:name":"Theatre DE Trois-Pistoles",
    "wof:placetype":"venue"
},
  "geometry": {"coordinates":[-69.174965,48.125603],"type":"Point"}
}