{
  "type": "Feature",
  "properties": {
    "iso:country":"CA",
    "sg:address":"53533 Range Road 221",
    "sg:city":"Ardrossan",
    "sg:classifiers":[
        {
            "category":"Farming",
            "subcategory":"Nursery",
            "type":"Manufacturing & Wholesale Goods"
        }
    ],
    "sg:phone":"+1 780 922 3243",
    "sg:postcode":"T8E 2K6",
    "sg:province":"AB",
    "sg:tags":[
        "greenhouse"
    ],
    "wof:name":"Ardrossan Greenhouses & Garden",
    "wof:placetype":"venue"
},
  "geometry": {"coordinates":[-113.123268,53.56995],"type":"Point"}
}