{
  "type": "Feature",
  "properties": {
    "addr:full":"1385 Woodroffe Ave Nepean ON K2G 1V8",
    "addr:housenumber":"1385",
    "addr:postcode":"k2g 1v8",
    "addr:street":"Woodroffe Ave",
    "iso:country":"CA",
    "sg:address":"1385 Woodroffe Ave",
    "sg:city":"Nepean",
    "sg:classifiers":[
        {
            "category":"Education",
            "subcategory":"College",
            "type":"Public Place"
        }
    ],
    "sg:phone":"+1 613 727 4723",
    "sg:postcode":"K2G 1V8",
    "sg:province":"ON",
    "sg:tags":[
        "academic",
        "school"
    ],
    "wof:name":"Algonquin College of Applied",
    "wof:placetype":"venue"
},
  "geometry": {"coordinates":[-75.759186,45.346905],"type":"Point"}
}