{
  "type": "Feature",
  "properties": {
    "addr:full":"10035 Boul Saint-Michel Montreal-Nord QC H1H 5G9",
    "addr:housenumber":"10035",
    "addr:postcode":"h1h 5g9",
    "addr:street":"Boul Saint-Michel",
    "iso:country":"CA",
    "sg:address":"10035 Boul Saint-Michel",
    "sg:city":"Montreal-Nord",
    "sg:classifiers":[
        {
            "category":"Building & Trades",
            "subcategory":"Construction",
            "type":"Services"
        }
    ],
    "sg:phone":"+1 514 323 3876",
    "sg:postcode":"H1H 5G9",
    "sg:province":"QC",
    "sg:tags":[
        "contractor"
    ],
    "wof:name":"Enterprises Du Domaines-Lacs",
    "wof:placetype":"venue"
},
  "geometry": {"coordinates":[-73.6408004761,45.578163147],"type":"Point"}
}