{
  "type": "Feature",
  "properties": {
    "addr:full":"1868 Route 3 Cardigan PE C0A 1G0",
    "addr:housenumber":"1868",
    "addr:postcode":"c0a 1g0",
    "addr:street":"Route 3",
    "iso:country":"CA",
    "sg:address":"1868 Route 3",
    "sg:city":"Cardigan",
    "sg:classifiers":[
        {
            "category":"Arts & Performance",
            "subcategory":"Theater",
            "type":"Entertainment"
        }
    ],
    "sg:phone":"+1 902 838 4023",
    "sg:postcode":"C0A 1G0",
    "sg:province":"PE",
    "sg:tags":[
        "live",
        "music"
    ],
    "wof:name":"New Generation Dj Svc",
    "wof:placetype":"venue"
},
  "geometry": {"coordinates":[-62.6186180115,46.2316436768],"type":"Point"}
}