{
  "type": "Feature",
  "properties": {
    "addr:full":"2525 Steeles Ave W North York ON M3J 2P1",
    "addr:housenumber":"2525",
    "addr:postcode":"m3j 2p1",
    "addr:street":"Steeles Ave W",
    "iso:country":"CA",
    "sg:address":"2525 Steeles Ave W",
    "sg:city":"North York",
    "sg:classifiers":[
        {
            "category":"Freight",
            "type":"Transportation"
        }
    ],
    "sg:phone":"+1 416 661 2797",
    "sg:postcode":"M3J 2P1",
    "sg:province":"ON",
    "sg:tags":[
        "mover"
    ],
    "wof:name":"Phillips Moving & Storage",
    "wof:placetype":"venue"
},
  "geometry": {"coordinates":[-79.483086,43.784081],"type":"Point"}
}