{
  "type": "Feature",
  "properties": {
    "addr:full":"Winnipeg MB R3T 2A7",
    "addr:postcode":"r3t 2a7",
    "iso:country":"CA",
    "sg:city":"Winnipeg",
    "sg:classifiers":[
        {
            "category":"Wholesale",
            "subcategory":"Photographic Equipment",
            "type":"Manufacturing & Wholesale Goods"
        }
    ],
    "sg:phone":"+1 204 475 8730",
    "sg:postcode":"R3T 2A7",
    "sg:province":"MB",
    "sg:tags":[
        "audio"
    ],
    "wof:name":"Foto Video",
    "wof:placetype":"venue"
},
  "geometry": {"coordinates":[-97.15284699999999,49.844826],"type":"Point"}
}