{
  "type": "Feature",
  "properties": {
    "addr:full":"Central Rd Onanole MB R0J 1N0",
    "addr:postcode":"r0j 1n0",
    "addr:street":"Central Rd",
    "iso:country":"CA",
    "sg:address":"Central Rd",
    "sg:city":"Onanole",
    "sg:classifiers":[
        {
            "category":"Recreation",
            "type":"Entertainment"
        }
    ],
    "sg:phone":"+1 204 848 2316",
    "sg:postcode":"R0J 1N0",
    "sg:province":"MB",
    "sg:tags":[
        "center"
    ],
    "wof:name":"Onanole Recreation Ctr",
    "wof:placetype":"venue"
},
  "geometry": {"coordinates":[-99.9686050415,50.6227912903],"type":"Point"}
}