{
  "type": "Feature",
  "properties": {
    "addr:full":"11436 65 St NW Edmonton AB T5W 4K8",
    "addr:housenumber":"11436",
    "addr:postcode":"t5w 4k8",
    "addr:street":"65 St Nw",
    "iso:country":"CA",
    "sg:address":"11436 65 St NW",
    "sg:city":"Edmonton",
    "sg:classifiers":[
        {
            "category":"Personal",
            "type":"Services"
        }
    ],
    "sg:phone":"+1 780 474 6734",
    "sg:postcode":"T5W 4K8",
    "sg:province":"AB",
    "sg:tags":[
        "therapist",
        "massage"
    ],
    "wof:name":"Kim Blair Licensed Massage",
    "wof:placetype":"venue"
},
  "geometry": {"coordinates":[-113.440414429,53.5682296753],"type":"Point"}
}