{
  "type": "Feature",
  "properties": {
    "iso:country":"CA",
    "sg:address":"4835 Av Coloniale",
    "sg:city":"Montreal",
    "sg:classifiers":[
        {
            "category":"Manufacturing",
            "subcategory":"Apparel",
            "type":"Manufacturing & Wholesale Goods"
        }
    ],
    "sg:phone":"+1 514 844 3333",
    "sg:postcode":"H2T 1W4",
    "sg:province":"QC",
    "sg:tags":[
        "underwear",
        "material",
        "corset",
        "brassiere"
    ],
    "wof:name":"C J Grenier Ltd",
    "wof:placetype":"venue"
},
  "geometry": {"coordinates":[-73.5894622803,45.5230331421],"type":"Point"}
}