{
  "type": "Feature",
  "properties": {
    "addr:full":"321 Pine Waubaushene ON L0K 2C0",
    "addr:housenumber":"321",
    "addr:postcode":"l0k 2c0",
    "addr:street":"Pine Waubaushene",
    "iso:country":"CA",
    "sg:address":"321 Pine",
    "sg:city":"Waubaushene",
    "sg:classifiers":[
        {
            "category":"Building & Trades",
            "subcategory":"Electrical",
            "type":"Services"
        }
    ],
    "sg:phone":"+1 705 538 1233",
    "sg:postcode":"L0K 2C0",
    "sg:province":"ON",
    "sg:tags":[
        "pole",
        "line",
        "electric",
        "contractor"
    ],
    "wof:name":"Blue Mountain Power Line Const",
    "wof:placetype":"venue"
},
  "geometry": {"coordinates":[-79.7089538574,44.7524299622],"type":"Point"}
}