{
  "type": "Feature",
  "properties": {
    "iso:country":"CA",
    "sg:address":"259 Beardsley Rd",
    "sg:city":"Beardsley",
    "sg:classifiers":[
        {
            "category":"Freight",
            "type":"Transportation"
        }
    ],
    "sg:phone":"+1 506 328 0008",
    "sg:postcode":"E7M 4E1",
    "sg:province":"NB",
    "sg:tags":[
        "trucking"
    ],
    "wof:name":"Bestway Transport",
    "wof:placetype":"venue"
},
  "geometry": {"coordinates":[-67.58038330079999,46.1292114258],"type":"Point"}
}