{
  "type": "Feature",
  "properties": {
    "addr:full":"200 Rue Notre-Dame E Victoriaville QC G6P 4A1",
    "addr:housenumber":"200",
    "addr:postcode":"g6p 4a1",
    "addr:street":"Rue Notre-Dame E",
    "iso:country":"CA",
    "sg:address":"200 Rue Notre-Dame E",
    "sg:city":"Victoriaville",
    "sg:classifiers":[
        {
            "category":"Shopping",
            "subcategory":"Clothing, Apparel, & Fashions",
            "type":"Retail Goods"
        }
    ],
    "sg:phone":"+1 819 752 4536",
    "sg:postcode":"G6P 4A1",
    "sg:province":"QC",
    "sg:tags":[
        "fur",
        "business"
    ],
    "wof:name":"Manteaux Langlois Inc",
    "wof:placetype":"venue"
},
  "geometry": {"coordinates":[-71.954063,46.057457],"type":"Point"}
}