{
  "type": "Feature",
  "properties": {
    "addr:full":"Quesnel BC V2J 7H2",
    "addr:postcode":"v2j 7h2",
    "iso:country":"CA",
    "sg:city":"Quesnel",
    "sg:classifiers":[
        {
            "category":"Manufacturing",
            "subcategory":"Glass & Minerals",
            "type":"Manufacturing & Wholesale Goods"
        }
    ],
    "sg:phone":"+1 250 992 7281",
    "sg:postcode":"V2J 7H2",
    "sg:province":"BC",
    "sg:tags":[
        "concrete",
        "brick",
        "block"
    ],
    "wof:name":"United Concrete & Gravel Ltd",
    "wof:placetype":"venue"
},
  "geometry": {"coordinates":[-122.468735,52.994305],"type":"Point"}
}