{
  "type": "Feature",
  "properties": {
    "addr:full":"2204 Hogan Dr Denare Beach SK S0P 0B0",
    "addr:housenumber":"2204",
    "addr:postcode":"s0p 0b0",
    "addr:street":"Hogan Dr Denare Beach",
    "iso:country":"CA",
    "sg:address":"2204 Hogan Dr",
    "sg:city":"Denare Beach",
    "sg:classifiers":[
        {
            "category":"Building & Trades",
            "subcategory":"Construction",
            "type":"Services"
        }
    ],
    "sg:phone":"+1 306 362 2011",
    "sg:postcode":"S0P 0B0",
    "sg:province":"SK",
    "sg:tags":[
        "general",
        "contractor"
    ],
    "wof:name":"Cdf Building Systems Ltd",
    "wof:placetype":"venue"
},
  "geometry": {"coordinates":[-102.079803,54.658913],"type":"Point"}
}