{
  "type": "Feature",
  "properties": {
    "addr:full":"1086 Scotch Creek Wharf Rd Scotch Creek BC V0E 3L0",
    "addr:housenumber":"1086",
    "addr:postcode":"bc v0e 3l0",
    "addr:street":"Scotch Creek Wharf Rd Scotch",
    "iso:country":"CA",
    "sg:address":"1086 Scotch Creek Wharf Rd",
    "sg:city":"Scotch Creek",
    "sg:classifiers":[
        {
            "category":"Autos & Motor Vehicles",
            "subcategory":"Boat Sales",
            "type":"Retail Goods"
        }
    ],
    "sg:phone":"+1 250 955 6166",
    "sg:postcode":"V0E 3L0",
    "sg:province":"BC",
    "sg:tags":[
        "top",
        "upholstery",
        "cover",
        "upholsterer"
    ],
    "wof:name":"Canvas Man",
    "wof:placetype":"venue"
},
  "geometry": {"coordinates":[-119.55390199999999,50.903519],"type":"Point"}
}