{
  "type": "Feature",
  "properties": {
    "addr:full":"Estevan SK S4A 0W6",
    "addr:postcode":"s4a 0w6",
    "iso:country":"CA",
    "sg:city":"Estevan",
    "sg:classifiers":[
        {
            "category":"Professional",
            "subcategory":"Management & Consulting",
            "type":"Services"
        }
    ],
    "sg:phone":"+1 306 634 8300",
    "sg:postcode":"S4A 0W6",
    "sg:province":"SK",
    "sg:tags":[
        "consultant",
        "business"
    ],
    "wof:name":"Sunrise Community Futures Devl",
    "wof:placetype":"venue"
},
  "geometry": {"coordinates":[-102.993515,49.14006],"type":"Point"}
}