{
  "type": "Feature",
  "properties": {
    "iso:country":"CA",
    "sg:address":"4990 93 Ave NW",
    "sg:city":"Edmonton",
    "sg:classifiers":[
        {
            "category":"Organizations",
            "subcategory":"Labor Organization",
            "type":"Services"
        }
    ],
    "sg:phone":"+1 780 466 1999",
    "sg:postcode":"T6B 2L6",
    "sg:province":"AB",
    "wof:name":"Alberta Sheet Metal Trust Fnds",
    "wof:placetype":"venue"
},
  "geometry": {"coordinates":[-113.41739699999999,53.530472],"type":"Point"}
}