{
  "type": "Feature",
  "properties": {
    "addr:full":"PO Box 179 Windermere ON P0B 1P0",
    "addr:housenumber":"po",
    "addr:postcode":"p0b 1p0",
    "addr:street":"Box 179",
    "iso:country":"CA",
    "sg:address":"PO Box 179",
    "sg:city":"Windermere",
    "sg:classifiers":[
        {
            "category":"Organizations",
            "subcategory":"Religious Organization",
            "type":"Services"
        }
    ],
    "sg:phone":"+1 705 769 3398",
    "sg:postcode":"P0B 1P0",
    "sg:province":"ON",
    "sg:tags":[
        "church"
    ],
    "wof:name":"Windermere United Church",
    "wof:placetype":"venue"
},
  "geometry": {"coordinates":[-79.548958,45.164875],"type":"Point"}
}