{
  "type": "Feature",
  "properties": {
    "addr:full":"Oshawa ON L1J 2K8",
    "addr:postcode":"l1j 2k8",
    "iso:country":"CA",
    "sg:city":"Oshawa",
    "sg:classifiers":[
        {
            "category":"Insurance",
            "subcategory":"Insurance Agent",
            "type":"Services"
        }
    ],
    "sg:phone":"+1 905 434 3880",
    "sg:postcode":"L1J 2K8",
    "sg:province":"ON",
    "wof:name":"Dennis Mc Ivor Insurance Agcy",
    "wof:placetype":"venue"
},
  "geometry": {"coordinates":[-78.87921900000001,43.894142],"type":"Point"}
}