{
  "type": "Feature",
  "properties": {
    "addr:full":"71 Rue Saint-Louis Quebec QC G1R 3Z2",
    "addr:housenumber":"71",
    "addr:postcode":"g1r 3z2",
    "addr:street":"Rue Saint-Louis",
    "iso:country":"CA",
    "sg:address":"71 Rue Saint-Louis",
    "sg:city":"Quebec",
    "sg:classifiers":[
        {
            "category":"Travel",
            "subcategory":"Hotels & Motels",
            "type":"Entertainment"
        }
    ],
    "sg:phone":"+1 418 694 1311",
    "sg:postcode":"G1R 3Z2",
    "sg:province":"QC",
    "wof:name":"Clos St-Louis",
    "wof:placetype":"venue"
},
  "geometry": {"coordinates":[-71.208916,46.810677],"type":"Point"}
}