{
  "type": "Feature",
  "properties": {
    "iso:country":"CA",
    "sg:city":"Pickering",
    "sg:classifiers":[
        {
            "category":"Autos & Motor Vehicles",
            "subcategory":"Auto Supplies",
            "type":"Retail Goods"
        }
    ],
    "sg:phone":"+1 905 686 7778",
    "sg:postcode":"L1W 3N9",
    "sg:province":"ON",
    "sg:tags":[
        "automobile",
        "parts"
    ],
    "wof:name":"East End Automotive Distr",
    "wof:placetype":"venue"
},
  "geometry": {"coordinates":[-79.0655136108,43.8353309631],"type":"Point"}
}