{
  "type": "Feature",
  "properties": {
    "iso:country":"CA",
    "sg:address":"322 Howell Rd",
    "sg:city":"Oakville",
    "sg:classifiers":[
        {
            "category":"Professional",
            "subcategory":"Management & Consulting",
            "type":"Services"
        }
    ],
    "sg:phone":"+1 905 257 6134",
    "sg:postcode":"L6H 5Y2",
    "sg:province":"ON",
    "sg:tags":[
        "consultant",
        "telecommunication"
    ],
    "wof:name":"Design Logic Consulting",
    "wof:placetype":"venue"
},
  "geometry": {"coordinates":[-79.732925,43.469913],"type":"Point"}
}