{
  "type": "Feature",
  "properties": {
    "addr:full":"50285 Camp River Rd Chilliwack BC V2P 6H4",
    "addr:housenumber":"50285",
    "addr:postcode":"v2p 6h4",
    "addr:street":"Camp River Rd",
    "iso:country":"CA",
    "sg:address":"50285 Camp River Rd",
    "sg:city":"Chilliwack",
    "sg:classifiers":[
        {
            "category":"Professional",
            "subcategory":"Accounting & Tax Preparation",
            "type":"Services"
        }
    ],
    "sg:phone":"+1 604 794 7741",
    "sg:postcode":"V2P 6H4",
    "sg:province":"BC",
    "sg:tags":[
        "accountant"
    ],
    "wof:name":"Art Friesen Inc",
    "wof:placetype":"venue"
},
  "geometry": {"coordinates":[-121.833511,49.203053],"type":"Point"}
}