{
  "type": "Feature",
  "properties": {
    "iso:country":"CA",
    "sg:address":"34 Rue Libersan",
    "sg:city":"Dollard-Des-Ormeaux",
    "sg:classifiers":[
        {
            "category":"Professional",
            "subcategory":"Accounting & Tax Preparation",
            "type":"Services"
        }
    ],
    "sg:phone":"+1 514 953 9845",
    "sg:postcode":"H9A 2B6",
    "sg:province":"QC",
    "sg:tags":[
        "accountant"
    ],
    "wof:name":"Peres & CO",
    "wof:placetype":"venue"
},
  "geometry": {"coordinates":[-73.819534,45.504833],"type":"Point"}
}