{
  "type": "Feature",
  "properties": {
    "addr:full":"75 Main St Hagersville ON N0A 1H0",
    "addr:housenumber":"75",
    "addr:postcode":"n0a 1h0",
    "addr:street":"Main St",
    "iso:country":"CA",
    "sg:address":"75 Main St",
    "sg:city":"Hagersville",
    "sg:classifiers":[
        {
            "category":"Building & Trades",
            "subcategory":"Plumbing",
            "type":"Services"
        }
    ],
    "sg:phone":"+1 905 768 1155",
    "sg:postcode":"N0A 1H0",
    "sg:province":"ON",
    "sg:tags":[
        "contractor"
    ],
    "wof:name":"Precise Plumbing & Heating Ltd",
    "wof:placetype":"venue"
},
  "geometry": {"coordinates":[-80.0482330322,42.9660873413],"type":"Point"}
}