{
  "type": "Feature",
  "properties": {
    "addr:full":"169 Rue Belanger Saint-Jerome QC J7Y 1K5",
    "addr:housenumber":"169",
    "addr:postcode":"j7y 1k5",
    "addr:street":"Rue Belanger Saint-Jerome",
    "iso:country":"CA",
    "sg:address":"169 Rue Belanger",
    "sg:city":"Saint-Jerome",
    "sg:classifiers":[
        {
            "category":"Manufacturing",
            "subcategory":"Pet Food",
            "type":"Manufacturing & Wholesale Goods"
        }
    ],
    "sg:phone":"+1 450 432 3714",
    "sg:postcode":"J7Y 1K5",
    "sg:province":"QC",
    "sg:tags":[
        "dog",
        "cat"
    ],
    "wof:name":"Boutique Pappy-Toutou",
    "wof:placetype":"venue"
},
  "geometry": {"coordinates":[-74.006516,45.794525],"type":"Point"}
}