{
  "type": "Feature",
  "properties": {
    "addr:full":"2618 Pandosy St Kelowna BC V1Y 1V6",
    "addr:housenumber":"2618",
    "addr:postcode":"v1y 1v6",
    "addr:street":"Pandosy St",
    "iso:country":"CA",
    "sg:address":"2618 Pandosy St",
    "sg:city":"Kelowna",
    "sg:classifiers":[
        {
            "category":"Banks & Credit Unions",
            "subcategory":"Investment Brokerage",
            "type":"Services"
        }
    ],
    "sg:phone":"+1 250 712 0508",
    "sg:postcode":"V1Y 1V6",
    "sg:province":"BC",
    "wof:name":"Edward Jones",
    "wof:placetype":"venue"
},
  "geometry": {"coordinates":[-119.49143981900001,49.8670463562],"type":"Point"}
}