{
  "type": "Feature",
  "properties": {
    "iso:country":"CA",
    "sg:city":"Calgary",
    "sg:classifiers":[
        {
            "category":"Manufacturing",
            "subcategory":"Signs",
            "type":"Manufacturing & Wholesale Goods"
        }
    ],
    "sg:phone":"+1 403 291 2777",
    "sg:postcode":"T2E 6R8",
    "sg:province":"AB",
    "wof:name":"Trim-Line",
    "wof:placetype":"venue"
},
  "geometry": {"coordinates":[-114.03150177000001,51.087436676],"type":"Point"}
}