{
  "type": "Feature",
  "properties": {
    "iso:country":"CA",
    "sg:address":"2001 107th St",
    "sg:city":"Blairmore",
    "sg:classifiers":[
        {
            "category":"Health Services",
            "subcategory":"Hospital",
            "type":"Services"
        }
    ],
    "sg:phone":"+1 403 562 2831",
    "sg:postcode":"T0K 0E0",
    "sg:province":"AB",
    "wof:name":"Crowsnest Pass Hospital",
    "wof:placetype":"venue"
},
  "geometry": {"coordinates":[-114.475532532,49.6188812256],"type":"Point"}
}