{
  "type": "Feature",
  "properties": {
    "iso:country":"CA",
    "sg:address":"370 Mcgill St",
    "sg:city":"Hawkesbury",
    "sg:classifiers":[
        {
            "category":"Retail",
            "subcategory":"Auto Repair",
            "type":"Services"
        }
    ],
    "sg:phone":"+1 613 632 2337",
    "sg:postcode":"K6A 1R2",
    "sg:province":"ON",
    "sg:tags":[
        "repairing",
        "automobile"
    ],
    "wof:name":"Leduc Ultramar",
    "wof:placetype":"venue"
},
  "geometry": {"coordinates":[-74.6149139404,45.6071891785],"type":"Point"}
}