{
  "type": "Feature",
  "properties": {
    "addr:full":"2 Bishops Rd Bay Roberts NL A0A 1G0",
    "addr:housenumber":"2",
    "addr:postcode":"a0a 1g0",
    "addr:street":"Bishops Rd",
    "iso:country":"CA",
    "sg:address":"2 Bishops Rd",
    "sg:city":"Bay Roberts",
    "sg:classifiers":[
        {
            "category":"Personal",
            "type":"Services"
        }
    ],
    "sg:phone":"+1 709 786 0144",
    "sg:postcode":"A0A 1G0",
    "sg:province":"NL",
    "sg:tags":[
        "program",
        "physical",
        "exercise",
        "fitness"
    ],
    "wof:name":"Bishop's Fitness Ctr",
    "wof:placetype":"venue"
},
  "geometry": {"coordinates":[-53.270145,47.592178],"type":"Point"}
}