{
  "type": "Feature",
  "properties": {
    "addr:full":"1172 Rue Laurier Longueuil QC J4J 5B7",
    "addr:housenumber":"1172",
    "addr:postcode":"j4j 5b7",
    "addr:street":"Rue Laurier",
    "iso:country":"CA",
    "sg:address":"1172 Rue Laurier",
    "sg:city":"Longueuil",
    "sg:classifiers":[
        {
            "category":"Building & Trades",
            "subcategory":"Electrical",
            "type":"Services"
        }
    ],
    "sg:phone":"+1 450 677 7715",
    "sg:postcode":"J4J 5B7",
    "sg:province":"QC",
    "sg:tags":[
        "electric",
        "contractor"
    ],
    "wof:name":"Installations Elec M Lacroix",
    "wof:placetype":"venue"
},
  "geometry": {"coordinates":[-73.486176,45.537041],"type":"Point"}
}