{
  "type": "Feature",
  "properties": {
    "addr:full":"Kakabeka Falls ON P0T 1W0",
    "addr:postcode":"p0t 1w0",
    "addr:street":"Kakabeka Falls",
    "iso:country":"CA",
    "sg:city":"Kakabeka Falls",
    "sg:classifiers":[
        {
            "category":"Government",
            "subcategory":"Office",
            "type":"Public Place"
        }
    ],
    "sg:phone":"+1 807 475 5229",
    "sg:postcode":"P0T 1W0",
    "sg:province":"ON",
    "sg:tags":[
        "municipality"
    ],
    "wof:name":"Conmee City Ofc",
    "wof:placetype":"venue"
},
  "geometry": {"coordinates":[-89.61456298829999,48.4017410278],"type":"Point"}
}