{
  "type": "Feature",
  "properties": {
    "addr:full":"Edam SK S0M 0V0",
    "addr:postcode":"s0m 0v0",
    "iso:country":"CA",
    "sg:city":"Edam",
    "sg:classifiers":[
        {
            "category":"Autos & Motor Vehicles",
            "subcategory":"Fuel & Gas Station",
            "type":"Retail Goods"
        }
    ],
    "sg:phone":"+1 306 397 2992",
    "sg:postcode":"S0M 0V0",
    "sg:province":"SK",
    "sg:tags":[
        "oil"
    ],
    "wof:name":"Country Roads Esso",
    "wof:placetype":"venue"
},
  "geometry": {"coordinates":[-108.767838,53.190716],"type":"Point"}
}