{
  "type": "Feature",
  "properties": {
    "iso:country":"CA",
    "sg:address":"PO Box 380",
    "sg:city":"St Theresa Point",
    "sg:classifiers":[
        {
            "category":"Organizations",
            "subcategory":"Professional Association",
            "type":"Services"
        }
    ],
    "sg:phone":"+1 204 462 2351",
    "sg:postcode":"R0B 1J0",
    "sg:province":"MB",
    "sg:tags":[
        "native"
    ],
    "wof:name":"Island Lake Tribal Council",
    "wof:placetype":"venue"
},
  "geometry": {"coordinates":[-94.84405517579999,53.8212356567],"type":"Point"}
}