{
  "type": "Feature",
  "properties": {
    "addr:full":"9706 99th St LA Crete AB T0H 2H0",
    "addr:housenumber":"9706",
    "addr:postcode":"t0h 2h0",
    "addr:street":"99Th St",
    "iso:country":"CA",
    "sg:address":"9706 99th St",
    "sg:city":"LA Crete",
    "sg:classifiers":[
        {
            "category":"Freight",
            "type":"Transportation"
        }
    ],
    "sg:phone":"+1 780 928 3989",
    "sg:postcode":"T0H 2H0",
    "sg:province":"AB",
    "sg:tags":[
        "trucking"
    ],
    "wof:name":"LA Crete Transport Ltd",
    "wof:placetype":"venue"
},
  "geometry": {"coordinates":[-116.395828247,58.1997337341],"type":"Point"}
}