{
  "type": "Feature",
  "properties": {
    "addr:full":"General Delivery Lyalta AB T0J 1Y0",
    "addr:postcode":"t0j 1y0",
    "iso:country":"CA",
    "sg:address":"General Delivery",
    "sg:city":"Lyalta",
    "sg:classifiers":[
        {
            "category":"Recreation",
            "type":"Entertainment"
        }
    ],
    "sg:phone":"+1 403 934 2888",
    "sg:postcode":"T0J 1Y0",
    "sg:province":"AB",
    "sg:tags":[
        "hall",
        "auditorium"
    ],
    "wof:name":"Lyalta Community Club",
    "wof:placetype":"venue"
},
  "geometry": {"coordinates":[-113.59770965600001,51.1154975891],"type":"Point"}
}