{
  "type": "Feature",
  "properties": {
    "addr:full":"630 Fourth Line Oakville ON L6L 5B2",
    "addr:housenumber":"630",
    "addr:postcode":"l6l 5b2",
    "addr:street":"Fourth Line",
    "iso:country":"CA",
    "sg:address":"630 Fourth Line",
    "sg:city":"Oakville",
    "sg:classifiers":[
        {
            "category":"Autos & Motor Vehicles",
            "subcategory":"Auto Supplies",
            "type":"Retail Goods"
        }
    ],
    "sg:phone":"+1 905 849 5946",
    "sg:postcode":"L6L 5B2",
    "sg:province":"ON",
    "sg:tags":[
        "automobile",
        "parts"
    ],
    "wof:name":"Canadian Tire Gas Bar",
    "wof:placetype":"venue"
},
  "geometry": {"coordinates":[-79.70174400000001,43.433098],"type":"Point"}
}