{
  "type": "Feature",
  "properties": {
    "iso:country":"CA",
    "sg:city":"North Bay",
    "sg:classifiers":[
        {
            "category":"Health Services",
            "subcategory":"Doctor",
            "type":"Services"
        }
    ],
    "sg:phone":"+1 705 472 6111",
    "sg:postcode":"P1B 5Z7",
    "sg:province":"ON",
    "sg:tags":[
        "clinic"
    ],
    "wof:name":"Diabetes Centre/Nipissing Dist",
    "wof:placetype":"venue"
},
  "geometry": {"coordinates":[-79.45486450200001,46.314666748],"type":"Point"}
}