{
  "type": "Feature",
  "properties": {
    "addr:full":"Camrose AB T4V 1Y5",
    "addr:postcode":"t4v 1y5",
    "iso:country":"CA",
    "sg:city":"Camrose",
    "sg:classifiers":[
        {
            "category":"Organizations",
            "subcategory":"Professional Association",
            "type":"Services"
        }
    ],
    "sg:phone":"+1 780 672 7665",
    "sg:postcode":"T4V 1Y5",
    "sg:province":"AB",
    "wof:name":"Canadian Cancer Society",
    "wof:placetype":"venue"
},
  "geometry": {"coordinates":[-112.830933,53.014633],"type":"Point"}
}