{
  "type": "Feature",
  "properties": {
    "addr:full":"114 Central Ave Montmartre SK S0G 3M0",
    "addr:housenumber":"114",
    "addr:postcode":"s0g 3m0",
    "addr:street":"Central Ave",
    "iso:country":"CA",
    "sg:address":"114 Central Ave",
    "sg:city":"Montmartre",
    "sg:classifiers":[
        {
            "category":"Banks & Credit Unions",
            "subcategory":"Bank",
            "type":"Services"
        }
    ],
    "sg:phone":"+1 306 424 2303",
    "sg:postcode":"S0G 3M0",
    "sg:province":"SK",
    "wof:name":"Plainsview Credit Union",
    "wof:placetype":"venue"
},
  "geometry": {"coordinates":[-103.449699,50.220131],"type":"Point"}
}