{
  "type": "Feature",
  "properties": {
    "iso:country":"CA",
    "sg:address":"720 22 St NE",
    "sg:city":"Salmon Arm",
    "sg:classifiers":[
        {
            "category":"Restaurant",
            "type":"Food & Drink"
        }
    ],
    "sg:phone":"+1 250 832 2079",
    "sg:postcode":"V1E 2S4",
    "sg:province":"BC",
    "wof:name":"Minos Greek House",
    "wof:placetype":"venue"
},
  "geometry": {"coordinates":[-119.25892639200001,50.70520401],"type":"Point"}
}