{
  "type": "Feature",
  "properties": {
    "addr:full":"109 Boul Cardinal-Leger Pincourt QC J7V 3Y3",
    "addr:housenumber":"109",
    "addr:postcode":"j7v 3y3",
    "addr:street":"Boul Cardinal-Leger",
    "iso:country":"CA",
    "sg:address":"109 Boul Cardinal-Leger",
    "sg:city":"Pincourt",
    "sg:classifiers":[
        {
            "category":"Food & Beverages",
            "subcategory":"Groceries & Convenience Stores",
            "type":"Retail Goods"
        }
    ],
    "sg:phone":"+1 514 453 9692",
    "sg:postcode":"J7V 3Y3",
    "sg:province":"QC",
    "wof:name":"Depan-Escompte Couche-Tard",
    "wof:placetype":"venue"
},
  "geometry": {"coordinates":[-73.9923706055,45.3827629089],"type":"Point"}
}