{
  "type": "Feature",
  "properties": {
    "addr:full":"513 Rue Principale Petit-Rocher NB E8J 1K7",
    "addr:housenumber":"513",
    "addr:postcode":"e8j 1k7",
    "addr:street":"Rue Principale",
    "iso:country":"CA",
    "sg:address":"513 Rue Principale",
    "sg:city":"Petit-Rocher",
    "sg:classifiers":[
        {
            "category":"Restaurant",
            "type":"Food & Drink"
        }
    ],
    "sg:phone":"+1 506 783 3333",
    "sg:postcode":"E8J 1K7",
    "sg:province":"NB",
    "wof:name":"Restaurant Pizza Terrasse",
    "wof:placetype":"venue"
},
  "geometry": {"coordinates":[-65.721069,47.788982],"type":"Point"}
}