{
  "type": "Feature",
  "properties": {
    "iso:country":"CA",
    "sg:address":"131 Tsawwassen Dr N",
    "sg:city":"Delta",
    "sg:classifiers":[
        {
            "category":"Organizations",
            "subcategory":"Community Association",
            "type":"Services"
        }
    ],
    "sg:phone":"+1 604 943 2112",
    "sg:postcode":"V4M 4G2",
    "sg:province":"BC",
    "sg:tags":[
        "native"
    ],
    "wof:name":"Tsawwassen First Nation Indian",
    "wof:placetype":"venue"
},
  "geometry": {"coordinates":[-123.097106934,49.0357131958],"type":"Point"}
}