{
  "type": "Feature",
  "properties": {
    "iso:country":"CA",
    "sg:address":"1455 Durham St",
    "sg:city":"Oakville",
    "sg:classifiers":[
        {
            "category":"Wholesale",
            "subcategory":"Non-durable Goods",
            "type":"Manufacturing & Wholesale Goods"
        }
    ],
    "sg:phone":"+1 905 844 7787",
    "sg:postcode":"L6J 2P4",
    "sg:province":"ON",
    "sg:tags":[
        "advertising"
    ],
    "wof:name":"Creative Marketing Resources",
    "wof:placetype":"venue"
},
  "geometry": {"coordinates":[-79.65674591059999,43.4739685059],"type":"Point"}
}