{
  "type": "Feature",
  "properties": {
    "addr:full":"162 Reach Industrial Park Rd Port Perry ON L9L 1B2",
    "addr:housenumber":"162",
    "addr:postcode":"l9l 1b2",
    "addr:street":"Reach Industrial Park Rd",
    "iso:country":"CA",
    "sg:address":"162 Reach Industrial Park Rd",
    "sg:city":"Port Perry",
    "sg:classifiers":[
        {
            "category":"Retail",
            "subcategory":"Car Wash",
            "type":"Services"
        }
    ],
    "sg:phone":"+1 905 985 0439",
    "sg:postcode":"L9L 1B2",
    "sg:province":"ON",
    "sg:tags":[
        "polishing",
        "glass",
        "washing"
    ],
    "wof:name":"Classic Rust Control & Glass",
    "wof:placetype":"venue"
},
  "geometry": {"coordinates":[-78.984444,44.103325],"type":"Point"}
}