{
  "type": "Feature",
  "properties": {
    "addr:full":"3505 Boul Cartier O Laval QC H7V 3T4",
    "addr:housenumber":"3505",
    "addr:postcode":"h7v 3t4",
    "addr:street":"Boul Cartier O",
    "iso:country":"CA",
    "sg:address":"3505 Boul Cartier O",
    "sg:city":"Laval",
    "sg:classifiers":[
        {
            "category":"Retail",
            "subcategory":"Laundry & Dry Cleaning",
            "type":"Services"
        }
    ],
    "sg:phone":"+1 450 687 7133",
    "sg:postcode":"H7V 3T4",
    "sg:province":"QC",
    "sg:tags":[
        "cleaners",
        "tailor"
    ],
    "wof:name":"Zako Le Tailleur",
    "wof:placetype":"venue"
},
  "geometry": {"coordinates":[-73.735283,45.538895],"type":"Point"}
}