{
  "type": "Feature",
  "properties": {
    "addr:full":"6166 Yonge St North York ON M2M 3X1",
    "addr:housenumber":"6166",
    "addr:postcode":"m2m 3x1",
    "addr:street":"Yonge St",
    "iso:country":"CA",
    "sg:address":"6166 Yonge St",
    "sg:city":"North York",
    "sg:classifiers":[
        {
            "category":"Home & Garden",
            "subcategory":"Household Appliances",
            "type":"Retail Goods"
        }
    ],
    "sg:phone":"+1 416 225 2367",
    "sg:postcode":"M2M 3X1",
    "sg:province":"ON",
    "wof:name":"County Appliances CO Ltd",
    "wof:placetype":"venue"
},
  "geometry": {"coordinates":[-79.41892199999999,43.793037],"type":"Point"}
}