{
  "type": "Feature",
  "properties": {
    "addr:full":"2401 Denison St Markham ON L3S 1G3",
    "addr:housenumber":"2401",
    "addr:postcode":"l3s 1g3",
    "addr:street":"Denison St",
    "iso:country":"CA",
    "sg:address":"2401 Denison St",
    "sg:city":"Markham",
    "sg:classifiers":[
        {
            "category":"Recreation",
            "type":"Entertainment"
        }
    ],
    "sg:phone":"+1 905 477 3300",
    "sg:postcode":"L3S 1G3",
    "sg:province":"ON",
    "sg:tags":[
        "tennis",
        "court"
    ],
    "wof:name":"Armadale Tennis Club",
    "wof:placetype":"venue"
},
  "geometry": {"coordinates":[-79.280312,43.840923],"type":"Point"}
}