{
  "type": "Feature",
  "properties": {
    "addr:full":"Quebec QC G1N 2C9",
    "addr:postcode":"g1n 2c9",
    "iso:country":"CA",
    "sg:city":"Quebec",
    "sg:classifiers":[
        {
            "category":"Professional",
            "subcategory":"Computer Services",
            "type":"Services"
        }
    ],
    "sg:phone":"+1 418 686 7686",
    "sg:postcode":"G1N 2C9",
    "sg:province":"QC",
    "sg:tags":[
        "internet"
    ],
    "wof:name":"Internet DE LA Capitale",
    "wof:placetype":"venue"
},
  "geometry": {"coordinates":[-71.2537231445,46.7999000549],"type":"Point"}
}