{
  "type": "Feature",
  "properties": {
    "addr:full":"PO Box 1627 Grimshaw AB T0H 1W0",
    "addr:housenumber":"po",
    "addr:postcode":"t0h 1w0",
    "addr:street":"Box 1627",
    "iso:country":"CA",
    "sg:address":"PO Box 1627",
    "sg:city":"Grimshaw",
    "sg:classifiers":[
        {
            "category":"Building & Trades",
            "subcategory":"Construction",
            "type":"Services"
        }
    ],
    "sg:phone":"+1 780 332 2390",
    "sg:postcode":"T0H 1W0",
    "sg:province":"AB",
    "sg:tags":[
        "painter"
    ],
    "wof:name":"Gingell's Painting",
    "wof:placetype":"venue"
},
  "geometry": {"coordinates":[-117.610466003,56.1913795471],"type":"Point"}
}