{
  "type": "Feature",
  "properties": {
    "addr:full":"7 Main St W Smiths Falls ON K7A 1M4",
    "addr:housenumber":"7",
    "addr:postcode":"k7a 1m4",
    "addr:street":"Main St W",
    "iso:country":"CA",
    "sg:address":"7 Main St W",
    "sg:city":"Smiths Falls",
    "sg:classifiers":[
        {
            "category":"Professional",
            "subcategory":"Business Services",
            "type":"Services"
        }
    ],
    "sg:phone":"+1 613 258 0788",
    "sg:postcode":"K7A 1M4",
    "sg:province":"ON",
    "sg:tags":[
        "appraiser",
        "real estate"
    ],
    "wof:name":"Rivington Associates Inc",
    "wof:placetype":"venue"
},
  "geometry": {"coordinates":[-76.02160600000001,44.899464],"type":"Point"}
}