{
  "type": "Feature",
  "properties": {
    "addr:full":"801 Ch Saint-Louis # 160 Quebec QC G1S 1C1",
    "addr:housenumber":"801",
    "addr:postcode":"g1s 1c1",
    "addr:street":"Ch Saint-Louis # 160",
    "iso:country":"CA",
    "sg:address":"801 Ch Saint-Louis # 160",
    "sg:city":"Quebec",
    "sg:classifiers":[
        {
            "category":"Banks & Credit Unions",
            "subcategory":"Bank",
            "type":"Services"
        }
    ],
    "sg:phone":"+1 418 684 0385",
    "sg:postcode":"G1S 1C1",
    "sg:province":"QC",
    "wof:name":"Banque Nationale Du Canada",
    "wof:placetype":"venue"
},
  "geometry": {"coordinates":[-71.339996,46.749989],"type":"Point"}
}