{
  "type": "Feature",
  "properties": {
    "iso:country":"CA",
    "sg:address":"380 Henderson Dr",
    "sg:city":"Regina",
    "sg:classifiers":[
        {
            "category":"Manufacturing",
            "subcategory":"Tools & Machinery",
            "type":"Manufacturing & Wholesale Goods"
        }
    ],
    "sg:phone":"+1 306 721 6455",
    "sg:postcode":"S4N 5W9",
    "sg:province":"SK",
    "sg:tags":[
        "battery",
        "equipment",
        "charging",
        "welding"
    ],
    "wof:name":"Farmtronics Limited",
    "wof:placetype":"venue"
},
  "geometry": {"coordinates":[-104.56171417199999,50.4691848755],"type":"Point"}
}