{
  "type": "Feature",
  "properties": {
    "addr:full":"920 Boul Maloney O Gatineau QC J8T 3R6",
    "addr:housenumber":"920",
    "addr:postcode":"j8t 3r6",
    "addr:street":"Boul Maloney O",
    "iso:country":"CA",
    "sg:address":"920 Boul Maloney O",
    "sg:city":"Gatineau",
    "sg:classifiers":[
        {
            "category":"Banks & Credit Unions",
            "subcategory":"Bank",
            "type":"Services"
        }
    ],
    "sg:phone":"+1 819 561 7779",
    "sg:postcode":"J8T 3R6",
    "sg:province":"QC",
    "sg:tags":[
        "cashing",
        "check"
    ],
    "wof:name":"Money Mart",
    "wof:placetype":"venue"
},
  "geometry": {"coordinates":[-75.5955963135,45.4900436401],"type":"Point"}
}