{
  "type": "Feature",
  "properties": {
    "addr:full":"886 King St E Hamilton ON L8M 1B6",
    "addr:housenumber":"886",
    "addr:postcode":"l8m 1b6",
    "addr:street":"King St E",
    "iso:country":"CA",
    "sg:address":"886 King St E",
    "sg:city":"Hamilton",
    "sg:classifiers":[
        {
            "category":"Professional",
            "subcategory":"Lawyer & Legal Services",
            "type":"Services"
        }
    ],
    "sg:phone":"+1 905 547 1255",
    "sg:postcode":"L8M 1B6",
    "sg:province":"ON",
    "sg:tags":[
        "attorney"
    ],
    "wof:name":"Paquette & Assoc",
    "wof:placetype":"venue"
},
  "geometry": {"coordinates":[-79.839973,43.251175],"type":"Point"}
}