{
  "type": "Feature",
  "properties": {
    "addr:full":"2022 8 Ave SE Calgary AB T2G 0N8",
    "addr:housenumber":"2022",
    "addr:postcode":"t2g 0n8",
    "addr:street":"8 Ave Se",
    "iso:country":"CA",
    "sg:address":"2022 8 Ave SE",
    "sg:city":"Calgary",
    "sg:classifiers":[
        {
            "category":"Building & Trades",
            "subcategory":"Construction",
            "type":"Services"
        }
    ],
    "sg:phone":"+1 403 233 2729",
    "sg:postcode":"T2G 0N8",
    "sg:province":"AB",
    "sg:tags":[
        "general",
        "contractor"
    ],
    "wof:name":"K & K Construction & Bobcat",
    "wof:placetype":"venue"
},
  "geometry": {"coordinates":[-114.016479,51.035145],"type":"Point"}
}