{
  "type": "Feature",
  "properties": {
    "addr:full":"25 Janray Dr Scarborough ON M1G 1Y2",
    "addr:housenumber":"25",
    "addr:postcode":"m1g 1y2",
    "addr:street":"Janray Dr",
    "iso:country":"CA",
    "sg:address":"25 Janray Dr",
    "sg:city":"Scarborough",
    "sg:classifiers":[
        {
            "category":"Education",
            "subcategory":"School",
            "type":"Public Place"
        }
    ],
    "sg:phone":"+1 416 393 5274",
    "sg:postcode":"M1G 1Y2",
    "sg:province":"ON",
    "wof:name":"Saint Barbara Catholic Elem",
    "wof:placetype":"venue"
},
  "geometry": {"coordinates":[-79.21940600000001,43.762569],"type":"Point"}
}