{
  "type": "Feature",
  "properties": {
    "iso:country":"CA",
    "sg:address":"729 Rue Angus N",
    "sg:city":"Westbury",
    "sg:classifiers":[
        {
            "category":"Building & Trades",
            "subcategory":"Construction",
            "type":"Services"
        }
    ],
    "sg:phone":"+1 819 832 3680",
    "sg:postcode":"J0B 1R0",
    "sg:province":"QC",
    "sg:tags":[
        "excavating",
        "contractor"
    ],
    "wof:name":"Excavation Transport Inc",
    "wof:placetype":"venue"
},
  "geometry": {"coordinates":[-71.6612701416,45.5027923584],"type":"Point"}
}