{
  "type": "Feature",
  "properties": {
    "addr:full":"Hanover ON N4N 3B8",
    "addr:postcode":"n4n 3b8",
    "iso:country":"CA",
    "sg:city":"Hanover",
    "sg:classifiers":[
        {
            "category":"Retail",
            "subcategory":"Auto Repair",
            "type":"Services"
        }
    ],
    "sg:phone":"+1 519 364 2740",
    "sg:postcode":"N4N 3B8",
    "sg:province":"ON",
    "sg:tags":[
        "repairing",
        "automobile"
    ],
    "wof:name":"Allan Park Motors",
    "wof:placetype":"venue"
},
  "geometry": {"coordinates":[-81.025826,44.152374],"type":"Point"}
}