{
  "type": "Feature",
  "properties": {
    "iso:country":"CA",
    "sg:address":"113 Country Rd #6",
    "sg:city":"Corner Brook",
    "sg:classifiers":[
        {
            "category":"Food & Beverages",
            "subcategory":"Groceries & Convenience Stores",
            "type":"Retail Goods"
        }
    ],
    "sg:phone":"+1 709 637 6660",
    "sg:postcode":"A2H 4M2",
    "sg:province":"NL",
    "sg:tags":[
        "grocer"
    ],
    "wof:name":"Food Centre",
    "wof:placetype":"venue"
},
  "geometry": {"coordinates":[-57.9695320129,48.943031311],"type":"Point"}
}