{
  "type": "Feature",
  "properties": {
    "addr:full":"1055 Prospect St Fredericton NB E3B 3B9",
    "addr:housenumber":"1055",
    "addr:postcode":"e3b 3b9",
    "addr:street":"Prospect St",
    "iso:country":"CA",
    "sg:address":"1055 Prospect St",
    "sg:city":"Fredericton",
    "sg:classifiers":[
        {
            "category":"Restaurant",
            "type":"Food & Drink"
        }
    ],
    "sg:phone":"+1 506 444 8827",
    "sg:postcode":"E3B 3B9",
    "sg:province":"NB",
    "wof:name":"Subway Sandwiches & Salads",
    "wof:placetype":"venue"
},
  "geometry": {"coordinates":[-66.6669845581,45.9414901733],"type":"Point"}
}