{
  "type": "Feature",
  "properties": {
    "iso:country":"CA",
    "sg:address":"22 Brandon St",
    "sg:city":"Moncton",
    "sg:classifiers":[
        {
            "category":"Building & Trades",
            "subcategory":"Construction",
            "type":"Services"
        }
    ],
    "sg:phone":"+1 506 857 0724",
    "sg:postcode":"E1C 7E6",
    "sg:province":"NB",
    "sg:tags":[
        "tile",
        "dealer"
    ],
    "wof:name":"Coastal Flooring & Wall Ltd",
    "wof:placetype":"venue"
},
  "geometry": {"coordinates":[-64.8061828613,46.0967025757],"type":"Point"}
}