{
  "type": "Feature",
  "properties": {
    "addr:full":"1357 Lincoln Ave Winnipeg MB R3E 0Y2",
    "addr:housenumber":"1357",
    "addr:postcode":"r3e 0y2",
    "addr:street":"Lincoln Ave",
    "iso:country":"CA",
    "sg:address":"1357 Lincoln Ave",
    "sg:city":"Winnipeg",
    "sg:classifiers":[
        {
            "category":"Building & Trades",
            "subcategory":"Construction",
            "type":"Services"
        }
    ],
    "sg:phone":"+1 204 783 8608",
    "sg:postcode":"R3E 0Y2",
    "sg:province":"MB",
    "sg:tags":[
        "resurfacing",
        "laying",
        "refinishing",
        "floor"
    ],
    "wof:name":"Bison Flooring",
    "wof:placetype":"venue"
},
  "geometry": {"coordinates":[-97.18441009519999,49.9129066467],"type":"Point"}
}