{
  "type": "Feature",
  "properties": {
    "addr:full":"1840 Bell Rd Halifax NS B3H 2Z5",
    "addr:housenumber":"1840",
    "addr:postcode":"b3h 2z5",
    "addr:street":"Bell Rd",
    "iso:country":"CA",
    "sg:address":"1840 Bell Rd",
    "sg:city":"Halifax",
    "sg:classifiers":[
        {
            "category":"Communications",
            "subcategory":"Television Station",
            "type":"Services"
        }
    ],
    "sg:phone":"+1 902 420 8311",
    "sg:postcode":"B3H 2Z5",
    "sg:province":"NS",
    "sg:tags":[
        "broadcasting",
        "co"
    ],
    "wof:name":"Canadian Broadcasting Corp",
    "wof:placetype":"venue"
},
  "geometry": {"coordinates":[-63.588127,44.646839],"type":"Point"}
}