{
  "type": "Feature",
  "properties": {
    "iso:country":"CA",
    "sg:address":"7135 85 St NW",
    "sg:city":"Edmonton",
    "sg:classifiers":[
        {
            "category":"Building & Trades",
            "subcategory":"Construction",
            "type":"Services"
        }
    ],
    "sg:phone":"+1 780 466 8812",
    "sg:postcode":"T6C 3A6",
    "sg:province":"AB",
    "sg:tags":[
        "general",
        "contractor"
    ],
    "wof:name":"Bruell Construction Ltd",
    "wof:placetype":"venue"
},
  "geometry": {"coordinates":[-113.456672669,53.5080108643],"type":"Point"}
}