{
  "type": "Feature",
  "properties": {
    "addr:full":"121 First St Orangeville ON L9W 3J8",
    "addr:housenumber":"121",
    "addr:postcode":"l9w 3j8",
    "addr:street":"First St",
    "iso:country":"CA",
    "sg:address":"121 First St",
    "sg:city":"Orangeville",
    "sg:classifiers":[
        {
            "category":"Shopping",
            "subcategory":"Clothing, Apparel, & Fashions",
            "type":"Retail Goods"
        }
    ],
    "sg:phone":"+1 519 942 8257",
    "sg:postcode":"L9W 3J8",
    "sg:province":"ON",
    "wof:name":"Creek Side Creek Clothing CO",
    "wof:placetype":"venue"
},
  "geometry": {"coordinates":[-80.100273,43.931213],"type":"Point"}
}