{
  "type": "Feature",
  "properties": {
    "iso:country":"CA",
    "sg:city":"Richmond",
    "sg:classifiers":[
        {
            "category":"Wholesale",
            "subcategory":"Hardware",
            "type":"Manufacturing & Wholesale Goods"
        }
    ],
    "sg:phone":"+1 604 273 0599",
    "sg:postcode":"V6V 2J6",
    "sg:province":"BC",
    "sg:tags":[
        "fastener"
    ],
    "wof:name":"Interfast Inc",
    "wof:placetype":"venue"
},
  "geometry": {"coordinates":[-123.073425293,49.1867218018],"type":"Point"}
}