{
  "type": "Feature",
  "properties": {
    "iso:country":"CA",
    "sg:address":"1625 Stone Church Rd E",
    "sg:city":"Hamilton",
    "sg:classifiers":[
        {
            "category":"Building & Trades",
            "subcategory":"Construction",
            "type":"Services"
        }
    ],
    "sg:phone":"+1 905 574 3398",
    "sg:postcode":"L8W 3Y5",
    "sg:province":"ON",
    "sg:tags":[
        "excavating",
        "contractor"
    ],
    "wof:name":"Cdn Excavating Inc",
    "wof:placetype":"venue"
},
  "geometry": {"coordinates":[-79.8177871704,43.1938667297],"type":"Point"}
}