{
  "type": "Feature",
  "properties": {
    "addr:full":"25 Artisans Cres London ON N5V 5E9",
    "addr:housenumber":"25",
    "addr:postcode":"n5v 5e9",
    "addr:street":"Artisans Cres",
    "iso:country":"CA",
    "sg:address":"25 Artisans Cres",
    "sg:city":"London",
    "sg:classifiers":[
        {
            "category":"Manufacturing",
            "subcategory":"Tools & Machinery",
            "type":"Manufacturing & Wholesale Goods"
        }
    ],
    "sg:phone":"+1 519 457 7286",
    "sg:postcode":"N5V 5E9",
    "sg:province":"ON",
    "sg:tags":[
        "machine",
        "shop"
    ],
    "wof:name":"Woodside Machine & Tool",
    "wof:placetype":"venue"
},
  "geometry": {"coordinates":[-81.15780639650001,43.0203971863],"type":"Point"}
}