{
  "type": "Feature",
  "properties": {
    "addr:full":"1009 3 Ave S Lethbridge AB T1J 0J3",
    "addr:housenumber":"1009",
    "addr:postcode":"t1j 0j3",
    "addr:street":"3 Ave S",
    "iso:country":"CA",
    "sg:address":"1009 3 Ave S",
    "sg:city":"Lethbridge",
    "sg:classifiers":[
        {
            "category":"Personal",
            "type":"Services"
        }
    ],
    "sg:phone":"+1 403 381 0667",
    "sg:postcode":"T1J 0J3",
    "sg:province":"AB",
    "sg:tags":[
        "therapist",
        "massage"
    ],
    "wof:name":"Stressless Heart",
    "wof:placetype":"venue"
},
  "geometry": {"coordinates":[-112.83214599999999,49.696278],"type":"Point"}
}