{
  "type": "Feature",
  "properties": {
    "addr:full":"Peterborough ON K9J 6X9",
    "addr:postcode":"k9j 6x9",
    "iso:country":"CA",
    "sg:city":"Peterborough",
    "sg:classifiers":[
        {
            "category":"Building & Trades",
            "subcategory":"Construction",
            "type":"Services"
        }
    ],
    "sg:phone":"+1 705 748 2471",
    "sg:postcode":"K9J 6X9",
    "sg:province":"ON",
    "sg:tags":[
        "general",
        "painter",
        "contractor"
    ],
    "wof:name":"Champlain General Contracting",
    "wof:placetype":"venue"
},
  "geometry": {"coordinates":[-78.32131200000001,44.300732],"type":"Point"}
}