{
  "type": "Feature",
  "properties": {
    "addr:full":"765 Cameron St Hawkesbury ON K6A 2B7",
    "addr:housenumber":"765",
    "addr:postcode":"k6a 2b7",
    "addr:street":"Cameron St",
    "iso:country":"CA",
    "sg:address":"765 Cameron St",
    "sg:city":"Hawkesbury",
    "sg:classifiers":[
        {
            "category":"Freight",
            "type":"Transportation"
        }
    ],
    "sg:phone":"+1 613 632 4139",
    "sg:postcode":"K6A 2B7",
    "sg:province":"ON",
    "sg:tags":[
        "commercial",
        "storage"
    ],
    "wof:name":"R & S Storage",
    "wof:placetype":"venue"
},
  "geometry": {"coordinates":[-74.5953674316,45.6029777527],"type":"Point"}
}