{
  "type": "Feature",
  "properties": {
    "addr:full":"Cranbrook BC V1C 6N4",
    "addr:postcode":"v1c 6n4",
    "iso:country":"CA",
    "sg:city":"Cranbrook",
    "sg:classifiers":[
        {
            "category":"Real Estate",
            "subcategory":"Surveying",
            "type":"Services"
        }
    ],
    "sg:phone":"+1 250 426 3822",
    "sg:postcode":"V1C 6N4",
    "sg:province":"BC",
    "sg:tags":[
        "surveyor"
    ],
    "wof:name":"Ekman Land Surveying Ltd",
    "wof:placetype":"venue"
},
  "geometry": {"coordinates":[-115.767349243,49.5288391113],"type":"Point"}
}