{
  "type": "Feature",
  "properties": {
    "addr:full":"4245 118 Ave NW Edmonton AB T5W 1A5",
    "addr:housenumber":"4245",
    "addr:postcode":"t5w 1a5",
    "addr:street":"118 Ave Nw",
    "iso:country":"CA",
    "sg:address":"4245 118 Ave NW",
    "sg:city":"Edmonton",
    "sg:classifiers":[
        {
            "category":"Cinema",
            "subcategory":"Movie Rental",
            "type":"Entertainment"
        }
    ],
    "sg:phone":"+1 780 479 1414",
    "sg:postcode":"T5W 1A5",
    "sg:province":"AB",
    "sg:tags":[
        "player",
        "recorder",
        "video",
        "leasing",
        "tape"
    ],
    "wof:name":"Blockbuster Video",
    "wof:placetype":"venue"
},
  "geometry": {"coordinates":[-113.40679168699999,53.5702476501],"type":"Point"}
}