{
  "type": "Feature",
  "properties": {
    "addr:full":"1315 Regent St Sudbury ON P3E 3Z1",
    "addr:housenumber":"1315",
    "addr:postcode":"p3e 3z1",
    "addr:street":"Regent St",
    "iso:country":"CA",
    "sg:address":"1315 Regent St",
    "sg:city":"Sudbury",
    "sg:classifiers":[
        {
            "category":"Health Services",
            "subcategory":"Nursing And Care Facility",
            "type":"Services"
        }
    ],
    "sg:phone":"+1 705 523 5295",
    "sg:postcode":"P3E 3Z1",
    "sg:province":"ON",
    "sg:tags":[
        "home",
        "retirement",
        "community"
    ],
    "wof:name":"Palambro Palace",
    "wof:placetype":"venue"
},
  "geometry": {"coordinates":[-81.009331,46.463741],"type":"Point"}
}