{
  "type": "Feature",
  "properties": {
    "addr:full":"965 Pacific Ave Winnipeg MB R3E 1G3",
    "addr:housenumber":"965",
    "addr:postcode":"r3e 1g3",
    "addr:street":"Pacific Ave",
    "iso:country":"CA",
    "sg:address":"965 Pacific Ave",
    "sg:city":"Winnipeg",
    "sg:classifiers":[
        {
            "category":"Building & Trades",
            "subcategory":"Construction",
            "type":"Services"
        }
    ],
    "sg:phone":"+1 204 783 2500",
    "sg:postcode":"R3E 1G3",
    "sg:province":"MB",
    "sg:tags":[
        "foundation",
        "general",
        "contractor"
    ],
    "wof:name":"Abalon Foundation Specialists",
    "wof:placetype":"venue"
},
  "geometry": {"coordinates":[-97.166145,49.910603],"type":"Point"}
}