{
  "type": "Feature",
  "properties": {
    "iso:country":"CA",
    "sg:address":"28 Dundas St E",
    "sg:city":"Napanee",
    "sg:classifiers":[
        {
            "category":"Travel",
            "subcategory":"Travel Agent",
            "type":"Entertainment"
        }
    ],
    "sg:phone":"+1 613 354 5416",
    "sg:postcode":"K7R 1H6",
    "sg:province":"ON",
    "sg:tags":[
        "agency",
        "bureau"
    ],
    "wof:name":"Marlin Travel",
    "wof:placetype":"venue"
},
  "geometry": {"coordinates":[-76.94951629640001,44.2476806641],"type":"Point"}
}