{
  "type": "Feature",
  "properties": {
    "addr:full":"228 Limestone Cres North York ON M3J 2S4",
    "addr:housenumber":"228",
    "addr:postcode":"m3j 2s4",
    "addr:street":"Limestone Cres",
    "iso:country":"CA",
    "sg:address":"228 Limestone Cres",
    "sg:city":"North York",
    "sg:classifiers":[
        {
            "category":"Manufacturing",
            "subcategory":"Metals",
            "type":"Manufacturing & Wholesale Goods"
        }
    ],
    "sg:phone":"+1 416 736 4039",
    "sg:postcode":"M3J 2S4",
    "sg:province":"ON",
    "sg:tags":[
        "plating"
    ],
    "wof:name":"Sms Metal Polishing Ltd",
    "wof:placetype":"venue"
},
  "geometry": {"coordinates":[-79.48698400000001,43.780613],"type":"Point"}
}