{
  "type": "Feature",
  "properties": {
    "iso:country":"CA",
    "sg:address":"228 Limestone Cres",
    "sg:city":"North York",
    "sg:classifiers":[
        {
            "category":"Manufacturing",
            "subcategory":"Metals",
            "type":"Manufacturing & Wholesale Goods"
        }
    ],
    "sg:phone":"+1 416 736 4039",
    "sg:postcode":"M3J 2S4",
    "sg:province":"ON",
    "sg:tags":[
        "plating"
    ],
    "wof:name":"Sms Metal Polishing Ltd",
    "wof:placetype":"venue"
},
  "geometry": {"coordinates":[-79.486984,43.780613],"type":"Point"}
}