{
  "type": "Feature",
  "properties": {
    "iso:country":"CA",
    "sg:address":"80 Beaver Crt",
    "sg:city":"Saint John",
    "sg:classifiers":[
        {
            "category":"Home & Garden",
            "subcategory":"Hardware",
            "type":"Retail Goods"
        }
    ],
    "sg:phone":"+1 506 635 1414",
    "sg:postcode":"E2M 3M4",
    "sg:province":"NB",
    "sg:tags":[
        "building",
        "material"
    ],
    "wof:name":"Home Hardware Building Ctr",
    "wof:placetype":"venue"
},
  "geometry": {"coordinates":[-66.0979766846,45.251159668],"type":"Point"}
}