{
  "type": "Feature",
  "properties": {
    "addr:full":"Dartmouth NS B3B 1P7",
    "addr:postcode":"b3b 1p7",
    "iso:country":"CA",
    "sg:city":"Dartmouth",
    "sg:classifiers":[
        {
            "category":"Professional",
            "subcategory":"Research",
            "type":"Services"
        }
    ],
    "sg:phone":"+1 902 468 6486",
    "sg:postcode":"B3B 1P7",
    "sg:province":"NS",
    "sg:tags":[
        "environmental",
        "ecological",
        "engineer"
    ],
    "wof:name":"Maritime Testing Ltd",
    "wof:placetype":"venue"
},
  "geometry": {"coordinates":[-63.6126327515,44.7038726807],"type":"Point"}
}