{
  "type": "Feature",
  "properties": {
    "addr:full":"Calgary AB T2G 5M9",
    "addr:postcode":"t2g 5m9",
    "iso:country":"CA",
    "sg:city":"Calgary",
    "sg:classifiers":[
        {
            "category":"Professional",
            "subcategory":"Business Services",
            "type":"Services"
        }
    ],
    "sg:phone":"+1 403 243 4546",
    "sg:postcode":"T2G 5M9",
    "sg:province":"AB",
    "sg:tags":[
        "fire",
        "protection"
    ],
    "wof:name":"Pds Fire Protection",
    "wof:placetype":"venue"
},
  "geometry": {"coordinates":[-114.03274500000001,51.008133],"type":"Point"}
}