{
  "type": "Feature",
  "properties": {
    "iso:country":"CA",
    "sg:address":"2505 Dunwin Dr",
    "sg:city":"Mississauga",
    "sg:classifiers":[
        {
            "category":"Building & Trades",
            "subcategory":"Construction",
            "type":"Services"
        }
    ],
    "sg:phone":"+1 905 608 0100",
    "sg:postcode":"L5L 1T1",
    "sg:province":"ON",
    "sg:tags":[
        "acoustical",
        "material"
    ],
    "wof:name":"Eomac Limited",
    "wof:placetype":"venue"
},
  "geometry": {"coordinates":[-79.68129730219999,43.529209137],"type":"Point"}
}