{
  "type": "Feature",
  "properties": {
    "addr:full":"567 Ch Saint-Louis Saint-Basile-Le-Grand QC J3N 1H4",
    "addr:housenumber":"567",
    "addr:postcode":"j3n 1h4",
    "addr:street":"Ch Saint-Louis",
    "iso:country":"CA",
    "sg:address":"567 Ch Saint-Louis",
    "sg:city":"Saint-Basile-Le-Grand",
    "sg:classifiers":[
        {
            "category":"Personal",
            "subcategory":"Beauty Salon",
            "type":"Services"
        }
    ],
    "sg:phone":"+1 450 653 3501",
    "sg:postcode":"J3N 1H4",
    "sg:province":"QC",
    "wof:name":"Salon Chez Anne",
    "wof:placetype":"venue"
},
  "geometry": {"coordinates":[-73.289658,45.519276],"type":"Point"}
}