{
  "type": "Feature",
  "properties": {
    "addr:full":"Montreal QC H3G 2A9",
    "addr:postcode":"h3g 2a9",
    "iso:country":"CA",
    "sg:city":"Montreal",
    "sg:classifiers":[
        {
            "category":"Professional",
            "subcategory":"Business Services",
            "type":"Services"
        }
    ],
    "sg:phone":"+1 514 843 6181",
    "sg:postcode":"H3G 2A9",
    "sg:province":"QC",
    "sg:tags":[
        "translator",
        "interpreter"
    ],
    "wof:name":"Bip Bureau Des Interpretes",
    "wof:placetype":"venue"
},
  "geometry": {"coordinates":[-73.57512664790001,45.4967498779],"type":"Point"}
}