{
  "type": "Feature",
  "properties": {
    "addr:full":"Wickham QC J0C 1S0",
    "addr:postcode":"j0c 1s0",
    "iso:country":"CA",
    "sg:city":"Wickham",
    "sg:classifiers":[
        {
            "category":"Building & Trades",
            "subcategory":"Construction",
            "type":"Services"
        }
    ],
    "sg:phone":"+1 819 398 6365",
    "sg:postcode":"J0C 1S0",
    "sg:province":"QC",
    "sg:tags":[
        "concrete",
        "contractor"
    ],
    "wof:name":"Coffrages M & B Enr",
    "wof:placetype":"venue"
},
  "geometry": {"coordinates":[-72.50495910639999,45.7526512146],"type":"Point"}
}