{
  "type": "Feature",
  "properties": {
    "addr:full":"342 Tower Rd Bamfield BC V0R 1B0",
    "addr:housenumber":"342",
    "addr:postcode":"v0r 1b0",
    "addr:street":"Tower Rd",
    "iso:country":"CA",
    "sg:address":"342 Tower Rd",
    "sg:city":"Bamfield",
    "sg:classifiers":[
        {
            "category":"Recreation",
            "type":"Entertainment"
        }
    ],
    "sg:phone":"+1 250 728 3286",
    "sg:postcode":"V0R 1B0",
    "sg:province":"BC",
    "sg:tags":[
        "campground",
        "party",
        "fishing"
    ],
    "wof:name":"Seabeam Fishing Resort",
    "wof:placetype":"venue"
},
  "geometry": {"coordinates":[-125.126289368,48.828502655],"type":"Point"}
}