{
  "type": "Feature",
  "properties": {
    "addr:full":"26 Lincoln St Hamilton ON L8L 7L5",
    "addr:housenumber":"26",
    "addr:postcode":"l8l 7l5",
    "addr:street":"Lincoln St",
    "iso:country":"CA",
    "sg:address":"26 Lincoln St",
    "sg:city":"Hamilton",
    "sg:phone":"+1 905 549 1109",
    "sg:postcode":"L8L 7L5",
    "sg:province":"ON",
    "sg:tags":[
        "equipment",
        "station"
    ],
    "wof:name":"Marty's Pump Svc Ltd",
    "wof:placetype":"venue"
},
  "geometry": {"coordinates":[-79.821152,43.253544],"type":"Point"}
}