{
  "type": "Feature",
  "properties": {
    "addr:full":"2460 St Clair Ave W Toronto ON M6N 1L2",
    "addr:housenumber":"2460",
    "addr:postcode":"m6n 1l2",
    "addr:street":"St Clair Ave W",
    "iso:country":"CA",
    "sg:address":"2460 St Clair Ave W",
    "sg:city":"Toronto",
    "sg:classifiers":[
        {
            "category":"Utilities",
            "subcategory":"Fuel Oil & Lpg",
            "type":"Services"
        }
    ],
    "sg:phone":"+1 416 766 6803",
    "sg:postcode":"M6N 1L2",
    "sg:province":"ON",
    "sg:tags":[
        "propane",
        "gas"
    ],
    "wof:name":"Anyo Svc",
    "wof:placetype":"venue"
},
  "geometry": {"coordinates":[-79.48342132569999,43.6691169739],"type":"Point"}
}