{
  "type": "Feature",
  "properties": {
    "addr:full":"11824 103 St NW Edmonton AB T5G 2J2",
    "addr:housenumber":"11824",
    "addr:postcode":"t5g 2j2",
    "addr:street":"103 St Nw",
    "iso:country":"CA",
    "sg:address":"11824 103 St NW",
    "sg:city":"Edmonton",
    "sg:classifiers":[
        {
            "category":"Restaurant",
            "type":"Food & Drink"
        }
    ],
    "sg:phone":"+1 780 448 0004",
    "sg:postcode":"T5G 2J2",
    "sg:province":"AB",
    "wof:name":"New York Steak & Pizza Lounge",
    "wof:placetype":"venue"
},
  "geometry": {"coordinates":[-113.49762,53.570816],"type":"Point"}
}