{
  "type": "Feature",
  "properties": {
    "addr:full":"Asbestos QC J1T 4R1",
    "addr:postcode":"j1t 4r1",
    "iso:country":"CA",
    "sg:city":"Asbestos",
    "sg:classifiers":[
        {
            "category":"Wholesale",
            "subcategory":"Office Equipment",
            "type":"Manufacturing & Wholesale Goods"
        }
    ],
    "sg:phone":"+1 819 879 5441",
    "sg:postcode":"J1T 4R1",
    "sg:province":"QC",
    "sg:tags":[
        "accounting",
        "bookkeeping",
        "system"
    ],
    "wof:name":"Gaumond Leroux",
    "wof:placetype":"venue"
},
  "geometry": {"coordinates":[-71.9280929565,45.770565033],"type":"Point"}
}