{
  "type": "Feature",
  "properties": {
    "iso:country":"CA",
    "sg:address":"16 Seguin St",
    "sg:city":"Parry Sound",
    "sg:classifiers":[
        {
            "category":"Personal",
            "type":"Services"
        }
    ],
    "sg:phone":"+1 705 746 2582",
    "sg:postcode":"P2A 1B1",
    "sg:province":"ON",
    "sg:tags":[
        "program",
        "physical",
        "exercise",
        "fitness"
    ],
    "wof:name":"Georgian Bay Health & Fitness",
    "wof:placetype":"venue"
},
  "geometry": {"coordinates":[-80.03145599370001,45.3433876038],"type":"Point"}
}