{
  "type": "Feature",
  "properties": {
    "iso:country":"CA",
    "sg:address":"1418 Rue Du Fort",
    "sg:city":"Montreal",
    "sg:classifiers":[
        {
            "category":"Parking",
            "type":"Transportation"
        }
    ],
    "sg:phone":"+1 514 935 4860",
    "sg:postcode":"H3H 2C4",
    "sg:province":"QC",
    "sg:tags":[
        "garage"
    ],
    "wof:name":"Stationnement Ep",
    "wof:placetype":"venue"
},
  "geometry": {"coordinates":[-73.581902,45.491947],"type":"Point"}
}