{
  "type": "Feature",
  "properties": {
    "addr:full":"8268 N Island Hwy Black Creek BC V9J 1H6",
    "addr:housenumber":"8268",
    "addr:postcode":"v9j 1h6",
    "addr:street":"N Island Hwy",
    "iso:country":"CA",
    "sg:address":"8268 N Island Hwy",
    "sg:city":"Black Creek",
    "sg:classifiers":[
        {
            "category":"Shopping",
            "subcategory":"Gifts & Souvenirs",
            "type":"Retail Goods"
        }
    ],
    "sg:phone":"+1 250 337 8522",
    "sg:postcode":"V9J 1H6",
    "sg:province":"BC",
    "sg:tags":[
        "apparel",
        "shop"
    ],
    "wof:name":"Heart & Home Gifts",
    "wof:placetype":"venue"
},
  "geometry": {"coordinates":[-125.131530762,49.8365898132],"type":"Point"}
}