{
  "type": "Feature",
  "properties": {
    "addr:full":"487 St Andrew St W Fergus ON N1M 1P2",
    "addr:housenumber":"487",
    "addr:postcode":"n1m 1p2",
    "addr:street":"St Andrew St W",
    "iso:country":"CA",
    "sg:address":"487 St Andrew St W",
    "sg:city":"Fergus",
    "sg:classifiers":[
        {
            "category":"Restaurant",
            "type":"Food & Drink"
        }
    ],
    "sg:phone":"+1 519 843 4770",
    "sg:postcode":"N1M 1P2",
    "sg:province":"ON",
    "sg:tags":[
        "motel",
        "hotel"
    ],
    "wof:name":"Breadalbane Inn Hotel",
    "wof:placetype":"venue"
},
  "geometry": {"coordinates":[-80.381187439,43.7017250061],"type":"Point"}
}