{
  "type": "Feature",
  "properties": {
    "addr:full":"9965 82 Ave NW Edmonton AB T6E 1Z1",
    "addr:housenumber":"9965",
    "addr:postcode":"t6e 1z1",
    "addr:street":"82 Ave Nw",
    "iso:country":"CA",
    "sg:address":"9965 82 Ave NW",
    "sg:city":"Edmonton",
    "sg:classifiers":[
        {
            "category":"Restaurant",
            "type":"Food & Drink"
        }
    ],
    "sg:phone":"+1 780 437 5761",
    "sg:postcode":"T6E 1Z1",
    "sg:province":"AB",
    "wof:name":"Tasty Tom's",
    "wof:placetype":"venue"
},
  "geometry": {"coordinates":[-113.487724304,53.5177841187],"type":"Point"}
}