{
  "type": "Feature",
  "properties": {
    "addr:full":"Lloydminster AB T9V 0W6",
    "addr:postcode":"t9v 0w6",
    "iso:country":"CA",
    "sg:city":"Lloydminster",
    "sg:classifiers":[
        {
            "category":"Personal",
            "subcategory":"Beauty Salon",
            "type":"Services"
        }
    ],
    "sg:phone":"+1 780 875 8500",
    "sg:postcode":"T9V 0W6",
    "sg:province":"AB",
    "wof:name":"50th Avenue Cuts",
    "wof:placetype":"venue"
},
  "geometry": {"coordinates":[-110.007812,53.278],"type":"Point"}
}