{
  "type": "Feature",
  "properties": {
    "addr:full":"583 Annette St Toronto ON M6S 2C3",
    "addr:housenumber":"583",
    "addr:postcode":"m6s 2c3",
    "addr:street":"Annette St",
    "iso:country":"CA",
    "sg:address":"583 Annette St",
    "sg:city":"Toronto",
    "sg:classifiers":[
        {
            "category":"Organizations",
            "subcategory":"Professional Association",
            "type":"Services"
        }
    ],
    "sg:phone":"+1 416 766 0247",
    "sg:postcode":"M6S 2C3",
    "sg:province":"ON",
    "sg:tags":[
        "club"
    ],
    "wof:name":"West End United Minor Soccer",
    "wof:placetype":"venue"
},
  "geometry": {"coordinates":[-79.480965,43.659687],"type":"Point"}
}