{
  "type": "Feature",
  "properties": {
    "addr:full":"323 Boul Henri-Bourassa O Montreal QC H3L 1N8",
    "addr:housenumber":"323",
    "addr:postcode":"h3l 1n8",
    "addr:street":"Boul Henri-Bourassa O",
    "iso:country":"CA",
    "sg:address":"323 Boul Henri-Bourassa O",
    "sg:city":"Montreal",
    "sg:classifiers":[
        {
            "category":"Professional",
            "subcategory":"Management & Consulting",
            "type":"Services"
        }
    ],
    "sg:phone":"+1 514 331 1727",
    "sg:postcode":"H3L 1N8",
    "sg:province":"QC",
    "sg:tags":[
        "consultant",
        "security",
        "system"
    ],
    "wof:name":"Stephan Cretier & Assoc",
    "wof:placetype":"venue"
},
  "geometry": {"coordinates":[-73.669579,45.553257],"type":"Point"}
}