{
  "type": "Feature",
  "properties": {
    "addr:full":"Mirabel QC J7N 1K9",
    "addr:postcode":"j7n 1k9",
    "iso:country":"CA",
    "sg:city":"Mirabel",
    "sg:classifiers":[
        {
            "category":"Retail",
            "subcategory":"Animal Services",
            "type":"Services"
        }
    ],
    "sg:phone":"+1 450 569 5515",
    "sg:postcode":"J7N 1K9",
    "sg:province":"QC",
    "sg:tags":[
        "pet",
        "grooming",
        "washing"
    ],
    "wof:name":"Niche A Fido",
    "wof:placetype":"venue"
},
  "geometry": {"coordinates":[-74.09459699999999,45.708054],"type":"Point"}
}