{
  "type": "Feature",
  "properties": {
    "addr:full":"18 Ringwood Dr Stouffville ON L4A 8C1",
    "addr:housenumber":"18",
    "addr:postcode":"l4a 8c1",
    "addr:street":"Ringwood Dr",
    "iso:country":"CA",
    "sg:address":"18 Ringwood Dr",
    "sg:city":"Stouffville",
    "sg:classifiers":[
        {
            "category":"Shopping",
            "subcategory":"Used Merchandise",
            "type":"Retail Goods"
        }
    ],
    "sg:phone":"+1 905 642 6415",
    "sg:postcode":"L4A 8C1",
    "sg:province":"ON",
    "sg:tags":[
        "shop",
        "consignment"
    ],
    "wof:name":"Once Is Not Enough",
    "wof:placetype":"venue"
},
  "geometry": {"coordinates":[-79.274269,43.964622],"type":"Point"}
}