{
  "type": "Feature",
  "properties": {
    "addr:full":"175 5th Ave W Vancouver BC V5Y 1H9",
    "addr:housenumber":"175",
    "addr:postcode":"v5y 1h9",
    "addr:street":"5Th Ave W",
    "iso:country":"CA",
    "sg:address":"175 5th Ave W",
    "sg:city":"Vancouver",
    "sg:classifiers":[
        {
            "category":"Retail",
            "subcategory":"Laundry & Dry Cleaning",
            "type":"Services"
        }
    ],
    "sg:phone":"+1 604 874 6073",
    "sg:postcode":"V5Y 1H9",
    "sg:province":"BC",
    "wof:name":"Cambie Laundry",
    "wof:placetype":"venue"
},
  "geometry": {"coordinates":[-123.10862731900001,49.2666893005],"type":"Point"}
}