{
  "type": "Feature",
  "properties": {
    "addr:full":"Wendake QC G0A 4V0",
    "addr:postcode":"g0a 4v0",
    "iso:country":"CA",
    "sg:city":"Wendake",
    "sg:classifiers":[
        {
            "category":"Wholesale",
            "subcategory":"Toys & Hobbies",
            "type":"Manufacturing & Wholesale Goods"
        }
    ],
    "sg:phone":"+1 418 840 0005",
    "sg:postcode":"G0A 4V0",
    "sg:province":"QC",
    "sg:tags":[
        "handicraft"
    ],
    "wof:name":"Art Huron Intl",
    "wof:placetype":"venue"
},
  "geometry": {"coordinates":[-71.365639,46.86882],"type":"Point"}
}