{
  "type": "Feature",
  "properties": {
    "iso:country":"CA",
    "sg:address":"7475 Goreway Dr",
    "sg:city":"Mississauga",
    "sg:classifiers":[
        {
            "category":"Organizations",
            "subcategory":"Religious Organization",
            "type":"Services"
        }
    ],
    "sg:phone":"+1 905 672 2426",
    "sg:postcode":"L4T 3T3",
    "sg:province":"ON",
    "wof:name":"Independent Christ Church",
    "wof:placetype":"venue"
},
  "geometry": {"coordinates":[-79.644096,43.722916],"type":"Point"}
}