{
  "type": "Feature",
  "properties": {
    "addr:full":"225 Spokane St Kimberley BC V1A 2E6",
    "addr:housenumber":"225",
    "addr:postcode":"v1a 2e6",
    "addr:street":"Spokane St",
    "iso:country":"CA",
    "sg:address":"225 Spokane St",
    "sg:city":"Kimberley",
    "sg:classifiers":[
        {
            "category":"Food & Beverages",
            "subcategory":"Specialty",
            "type":"Retail Goods"
        }
    ],
    "sg:phone":"+1 250 427 7838",
    "sg:postcode":"V1A 2E6",
    "sg:province":"BC",
    "sg:tags":[
        "health",
        "diet"
    ],
    "wof:name":"Healthy Horizons Natural Foods",
    "wof:placetype":"venue"
},
  "geometry": {"coordinates":[-115.98329200000001,49.685905],"type":"Point"}
}