{
  "type": "Feature",
  "properties": {
    "addr:full":"51 Ch Sainte-Anne Sorel-Tracy QC J3P 1J3",
    "addr:housenumber":"51",
    "addr:postcode":"j3p 1j3",
    "addr:street":"Ch Sainte-Anne",
    "iso:country":"CA",
    "sg:address":"51 Ch Sainte-Anne",
    "sg:city":"Sorel-Tracy",
    "sg:classifiers":[
        {
            "category":"Personal",
            "subcategory":"Beauty Salon",
            "type":"Services"
        }
    ],
    "sg:phone":"+1 450 742 6813",
    "sg:postcode":"J3P 1J3",
    "sg:province":"QC",
    "wof:name":"Salon Monic",
    "wof:placetype":"venue"
},
  "geometry": {"coordinates":[-73.112633,46.042389],"type":"Point"}
}