{
  "type": "Feature",
  "properties": {
    "addr:full":"4215 Spiers Rd # 1 Kelowna BC V1W 4E3",
    "addr:housenumber":"4215",
    "addr:postcode":"v1w 4e3",
    "addr:street":"Spiers Rd # 1",
    "iso:country":"CA",
    "sg:address":"4215 Spiers Rd # 1",
    "sg:city":"Kelowna",
    "sg:classifiers":[
        {
            "category":"Building & Trades",
            "subcategory":"Construction",
            "type":"Services"
        }
    ],
    "sg:phone":"+1 250 860 2388",
    "sg:postcode":"V1W 4E3",
    "sg:province":"BC",
    "sg:tags":[
        "excavating",
        "contractor"
    ],
    "wof:name":"Serwa Bulldozing CO Ltd",
    "wof:placetype":"venue"
},
  "geometry": {"coordinates":[-119.418671,49.836998],"type":"Point"}
}