{
  "type": "Feature",
  "properties": {
    "addr:full":"178 Main St Unionville ON L3R 2G9",
    "addr:housenumber":"178",
    "addr:postcode":"l3r 2g9",
    "addr:street":"Main St",
    "iso:country":"CA",
    "sg:address":"178 Main St",
    "sg:city":"Unionville",
    "sg:classifiers":[
        {
            "category":"Building & Trades",
            "subcategory":"Construction",
            "type":"Services"
        }
    ],
    "sg:phone":"+1 905 475 5066",
    "sg:postcode":"L3R 2G9",
    "sg:province":"ON",
    "sg:tags":[
        "carpenter"
    ],
    "wof:name":"Dfc Carpentry Contractors Ltd",
    "wof:placetype":"venue"
},
  "geometry": {"coordinates":[-79.31224060060001,43.8674049377],"type":"Point"}
}