{
  "type": "Feature",
  "properties": {
    "addr:full":"Toronto ON M4V 1L5",
    "addr:postcode":"m4v 1l5",
    "iso:country":"CA",
    "sg:city":"Toronto",
    "sg:classifiers":[
        {
            "category":"Arts & Performance",
            "subcategory":"Theater",
            "type":"Entertainment"
        }
    ],
    "sg:phone":"+1 416 922 1290",
    "sg:postcode":"M4V 1L5",
    "sg:province":"ON",
    "sg:tags":[
        "program",
        "radio",
        "producer"
    ],
    "wof:name":"Sound Source",
    "wof:placetype":"venue"
},
  "geometry": {"coordinates":[-79.39459228520001,43.688117981],"type":"Point"}
}