{
  "type": "Feature",
  "properties": {
    "addr:full":"9 Red Pine Crt Shanty Bay ON L0L 2L0",
    "addr:housenumber":"9",
    "addr:postcode":"l0l 2l0",
    "addr:street":"Red Pine Crt",
    "iso:country":"CA",
    "sg:address":"9 Red Pine Crt",
    "sg:city":"Shanty Bay",
    "sg:classifiers":[
        {
            "category":"Building & Trades",
            "subcategory":"Equipment Rental",
            "type":"Services"
        }
    ],
    "sg:phone":"+1 705 737 9222",
    "sg:postcode":"L0L 2L0",
    "sg:province":"ON",
    "sg:tags":[
        "leasing"
    ],
    "wof:name":"Mountstephen, John",
    "wof:placetype":"venue"
},
  "geometry": {"coordinates":[-79.58197800000001,44.412922],"type":"Point"}
}