{
  "type": "Feature",
  "properties": {
    "addr:full":"3255 Highway 7 Markham ON L3R 3P9",
    "addr:housenumber":"3255",
    "addr:postcode":"l3r 3p9",
    "addr:street":"Highway 7",
    "iso:country":"CA",
    "sg:address":"3255 Highway 7",
    "sg:city":"Markham",
    "sg:classifiers":[
        {
            "category":"Travel",
            "subcategory":"Travel Agent",
            "type":"Entertainment"
        }
    ],
    "sg:phone":"+1 905 513 8886",
    "sg:postcode":"L3R 3P9",
    "sg:province":"ON",
    "sg:tags":[
        "agency",
        "bureau"
    ],
    "wof:name":"Safeway Travel",
    "wof:placetype":"venue"
},
  "geometry": {"coordinates":[-79.3399429321,43.8560333252],"type":"Point"}
}