{
  "type": "Feature",
  "properties": {
    "addr:full":"Oka QC J0N 1E0",
    "addr:postcode":"j0n 1e0",
    "iso:country":"CA",
    "sg:city":"Oka",
    "sg:classifiers":[
        {
            "category":"Building & Trades",
            "subcategory":"Construction",
            "type":"Services"
        }
    ],
    "sg:phone":"+1 450 479 6903",
    "sg:postcode":"J0N 1E0",
    "sg:province":"QC",
    "sg:tags":[
        "contractor"
    ],
    "wof:name":"Ferlay, Elie",
    "wof:placetype":"venue"
},
  "geometry": {"coordinates":[-73.835007,45.568024],"type":"Point"}
}