{
  "type": "Feature",
  "properties": {
    "addr:full":"915 St. Anne St Bathurst NB E2A 6X1",
    "addr:housenumber":"915",
    "addr:postcode":"e2a 6x1",
    "addr:street":"St. Anne St",
    "iso:country":"CA",
    "sg:address":"915 St. Anne St",
    "sg:city":"Bathurst",
    "sg:classifiers":[
        {
            "category":"Organizations",
            "subcategory":"Professional Association",
            "type":"Services"
        }
    ],
    "sg:phone":"+1 506 548 4338",
    "sg:postcode":"E2A 6X1",
    "sg:province":"NB",
    "wof:name":"Societe Culturelle Regionale",
    "wof:placetype":"venue"
},
  "geometry": {"coordinates":[-65.6797943115,47.6268997192],"type":"Point"}
}