{
  "type": "Feature",
  "properties": {
    "iso:country":"CA",
    "sg:city":"Toronto",
    "sg:classifiers":[
        {
            "category":"Health Services",
            "subcategory":"Doctor",
            "type":"Services"
        }
    ],
    "sg:phone":"+1 416 766 3401",
    "sg:postcode":"M6S 4W4",
    "sg:province":"ON",
    "sg:tags":[
        "physician",
        "surgeon"
    ],
    "wof:name":"Kempston, John MD",
    "wof:placetype":"venue"
},
  "geometry": {"coordinates":[-79.483658,43.649368],"type":"Point"}
}