{
  "type": "Feature",
  "properties": {
    "addr:full":"720 Linden Ave Victoria BC V8V 4G7",
    "addr:housenumber":"720",
    "addr:postcode":"v8v 4g7",
    "addr:street":"Linden Ave",
    "iso:country":"CA",
    "sg:address":"720 Linden Ave",
    "sg:city":"Victoria",
    "sg:classifiers":[
        {
            "category":"Education",
            "subcategory":"School",
            "type":"Public Place"
        }
    ],
    "sg:phone":"+1 250 388 7225",
    "sg:postcode":"V8V 4G7",
    "sg:province":"BC",
    "sg:tags":[
        "academic",
        "special"
    ],
    "wof:name":"Victoria Read Society",
    "wof:placetype":"venue"
},
  "geometry": {"coordinates":[-123.351562,48.419495],"type":"Point"}
}