{
  "type": "Feature",
  "properties": {
    "iso:country":"CA",
    "sg:address":"138 & Kings Rd",
    "sg:city":"St Andrews West",
    "sg:classifiers":[
        {
            "category":"Restaurant",
            "type":"Food & Drink"
        }
    ],
    "sg:phone":"+1 613 936 1865",
    "sg:postcode":"K0C 2A0",
    "sg:province":"ON",
    "wof:name":"Quinn's Inn",
    "wof:placetype":"venue"
},
  "geometry": {"coordinates":[-74.5807876587,45.2189788818],"type":"Point"}
}