{
  "type": "Feature",
  "properties": {
    "addr:full":"Langley BC V3A 9J8",
    "addr:postcode":"v3a 9j8",
    "iso:country":"CA",
    "sg:city":"Langley",
    "sg:classifiers":[
        {
            "category":"Shopping",
            "subcategory":"Clothing, Apparel, & Fashions",
            "type":"Retail Goods"
        }
    ],
    "sg:phone":"+1 604 539 0257",
    "sg:postcode":"V3A 9J8",
    "sg:province":"BC",
    "sg:tags":[
        "lingerie"
    ],
    "wof:name":"LA Vie En Rose",
    "wof:placetype":"venue"
},
  "geometry": {"coordinates":[-122.664986,49.113213],"type":"Point"}
}