{
  "type": "Feature",
  "properties": {
    "iso:country":"CA",
    "sg:address":"Hwy 587 & James River Rd",
    "sg:city":"James River Bridge",
    "sg:classifiers":[
        {
            "category":"Food & Beverages",
            "subcategory":"Groceries & Convenience Stores",
            "type":"Retail Goods"
        }
    ],
    "sg:phone":"+1 403 638 2103",
    "sg:postcode":"T0M 1C0",
    "sg:province":"AB",
    "sg:tags":[
        "grocer"
    ],
    "wof:name":"James River Bridge Store",
    "wof:placetype":"venue"
},
  "geometry": {"coordinates":[-114.638145447,51.940536499],"type":"Point"}
}