{
  "type": "Feature",
  "properties": {
    "addr:full":"184 Holland St W Bradford ON L3Z 1H7",
    "addr:housenumber":"184",
    "addr:postcode":"l3z 1h7",
    "addr:street":"Holland St W",
    "iso:country":"CA",
    "sg:address":"184 Holland St W",
    "sg:city":"Bradford",
    "sg:classifiers":[
        {
            "category":"Cinema",
            "subcategory":"Movie Rental",
            "type":"Entertainment"
        }
    ],
    "sg:phone":"+1 905 775 0948",
    "sg:postcode":"L3Z 1H7",
    "sg:province":"ON",
    "sg:tags":[
        "leasing",
        "video",
        "disc",
        "tape"
    ],
    "wof:name":"Video Quest Inc",
    "wof:placetype":"venue"
},
  "geometry": {"coordinates":[-79.57176971440001,44.1126060486],"type":"Point"}
}