{
  "type": "Feature",
  "properties": {
    "addr:full":"Drayton Valley AB T7A 1R9",
    "addr:postcode":"t7a 1r9",
    "addr:street":"Drayton",
    "iso:country":"CA",
    "sg:city":"Drayton Valley",
    "sg:classifiers":[
        {
            "category":"Retail",
            "subcategory":"Auto Repair",
            "type":"Services"
        }
    ],
    "sg:phone":"+1 780 542 6965",
    "sg:postcode":"T7A 1R9",
    "sg:province":"AB",
    "sg:tags":[
        "repairing",
        "automobile"
    ],
    "wof:name":"Fak Automotive",
    "wof:placetype":"venue"
},
  "geometry": {"coordinates":[-114.982552,53.228752],"type":"Point"}
}