{
  "type": "Feature",
  "properties": {
    "addr:full":"1375 El Camino Dr Coquitlam BC V3E 2W6",
    "addr:housenumber":"1375",
    "addr:postcode":"v3e 2w6",
    "addr:street":"El Camino Dr",
    "iso:country":"CA",
    "sg:address":"1375 El Camino Dr",
    "sg:city":"Coquitlam",
    "sg:classifiers":[
        {
            "category":"Manufacturing",
            "subcategory":"Printing",
            "type":"Manufacturing & Wholesale Goods"
        }
    ],
    "sg:phone":"+1 604 944 7578",
    "sg:postcode":"V3E 2W6",
    "sg:province":"BC",
    "sg:tags":[
        "bookbinder"
    ],
    "wof:name":"Advantage Books & Binders",
    "wof:placetype":"venue"
},
  "geometry": {"coordinates":[-122.77874,49.2957],"type":"Point"}
}