{
  "type": "Feature",
  "properties": {
    "addr:full":"6900 Maritz Dr Mississauga ON L5W 1L8",
    "addr:housenumber":"6900",
    "addr:postcode":"l5w 1l8",
    "addr:street":"Maritz Dr",
    "iso:country":"CA",
    "sg:address":"6900 Maritz Dr",
    "sg:city":"Mississauga",
    "sg:classifiers":[
        {
            "category":"Social Services",
            "type":"Services"
        }
    ],
    "sg:phone":"+1 905 696 5139",
    "sg:postcode":"L5W 1L8",
    "sg:province":"ON",
    "sg:tags":[
        "organization",
        "welfare"
    ],
    "wof:name":"Boardmatch Altruvest",
    "wof:placetype":"venue"
},
  "geometry": {"coordinates":[-79.705872,43.641109],"type":"Point"}
}