{
  "type": "Feature",
  "properties": {
    "addr:full":"Hamilton ON L8W 2Z9",
    "addr:postcode":"l8w 2z9",
    "iso:country":"CA",
    "sg:city":"Hamilton",
    "sg:classifiers":[
        {
            "category":"Autos & Motor Vehicles",
            "subcategory":"Fuel & Gas Station",
            "type":"Retail Goods"
        }
    ],
    "sg:phone":"+1 905 389 1343",
    "sg:postcode":"L8W 2Z9",
    "sg:province":"ON",
    "sg:tags":[
        "oil"
    ],
    "wof:name":"Rainbow Car Washes & Gas Bars",
    "wof:placetype":"venue"
},
  "geometry": {"coordinates":[-79.84026299999999,43.192608],"type":"Point"}
}