{
  "type": "Feature",
  "properties": {
    "addr:full":"51 Duke St Bedford NS B4A 2Z2",
    "addr:housenumber":"51",
    "addr:postcode":"b4a 2z2",
    "addr:street":"Duke St",
    "iso:country":"CA",
    "sg:address":"51 Duke St",
    "sg:city":"Bedford",
    "sg:classifiers":[
        {
            "category":"Manufacturing",
            "subcategory":"Chemicals & Compounds",
            "type":"Manufacturing & Wholesale Goods"
        }
    ],
    "sg:phone":"+1 902 835 2304",
    "sg:postcode":"B4A 2Z2",
    "sg:province":"NS",
    "sg:tags":[
        "control",
        "pest",
        "supply"
    ],
    "wof:name":"Braemar Pest Control Svc",
    "wof:placetype":"venue"
},
  "geometry": {"coordinates":[-63.635974884,44.747341156],"type":"Point"}
}