{
  "type": "Feature",
  "properties": {
    "addr:full":"Hagensborg BC V0T 1H0",
    "addr:postcode":"v0t 1h0",
    "iso:country":"CA",
    "sg:city":"Hagensborg",
    "sg:classifiers":[
        {
            "category":"Manufacturing",
            "subcategory":"Printing",
            "type":"Manufacturing & Wholesale Goods"
        }
    ],
    "sg:phone":"+1 250 982 2696",
    "sg:postcode":"V0T 1H0",
    "sg:province":"BC",
    "sg:tags":[
        "newspaper"
    ],
    "wof:name":"Coast Mountain News",
    "wof:placetype":"venue"
},
  "geometry": {"coordinates":[-126.509544373,52.395324707],"type":"Point"}
}