{
  "type": "Feature",
  "properties": {
    "addr:full":"Sainte-Foy QC G1V 2L1",
    "addr:postcode":"g1v 2l1",
    "iso:country":"CA",
    "sg:city":"Sainte-Foy",
    "sg:classifiers":[
        {
            "category":"Shopping",
            "subcategory":"Luggage & Leather Goods",
            "type":"Retail Goods"
        }
    ],
    "sg:phone":"+1 418 651 9596",
    "sg:postcode":"G1V 2L1",
    "sg:province":"QC",
    "wof:name":"Access",
    "wof:placetype":"venue"
},
  "geometry": {"coordinates":[-71.27625999999999,46.773705],"type":"Point"}
}