{
  "type": "Feature",
  "properties": {
    "addr:full":"201 Lloyd Manor Rd Etobicoke ON M9B 6H6",
    "addr:housenumber":"201",
    "addr:postcode":"m9b 6h6",
    "addr:street":"Lloyd Manor Rd",
    "iso:country":"CA",
    "sg:address":"201 Lloyd Manor Rd",
    "sg:city":"Etobicoke",
    "sg:classifiers":[
        {
            "category":"Shopping",
            "subcategory":"Pharmacy",
            "type":"Retail Goods"
        }
    ],
    "sg:phone":"+1 416 236 1131",
    "sg:postcode":"M9B 6H6",
    "sg:province":"ON",
    "wof:name":"Shoppers Drug Mart",
    "wof:placetype":"venue"
},
  "geometry": {"coordinates":[-79.556946,43.674702],"type":"Point"}
}