{
  "type": "Feature",
  "properties": {
    "iso:country":"CA",
    "sg:address":"3751 No. 3 Rd",
    "sg:city":"Richmond",
    "sg:classifiers":[
        {
            "category":"Retail",
            "subcategory":"Auto Repair",
            "type":"Services"
        }
    ],
    "sg:phone":"+1 604 270 3831",
    "sg:postcode":"V6X 2B8",
    "sg:province":"BC",
    "sg:tags":[
        "body",
        "automobile",
        "painting"
    ],
    "wof:name":"Simpson Ho Auto Body Rpr Ltd",
    "wof:placetype":"venue"
},
  "geometry": {"coordinates":[-123.13530731199999,49.1863327026],"type":"Point"}
}