{
  "type": "Feature",
  "properties": {
    "addr:full":"160 Mcalpine Ave S Welland ON L3B 1T6",
    "addr:housenumber":"160",
    "addr:postcode":"l3b 1t6",
    "addr:street":"Mcalpine Ave S",
    "iso:country":"CA",
    "sg:address":"160 Mcalpine Ave S",
    "sg:city":"Welland",
    "sg:classifiers":[
        {
            "category":"Retail",
            "subcategory":"Repair Shop",
            "type":"Services"
        }
    ],
    "sg:phone":"+1 905 732 1335",
    "sg:postcode":"L3B 1T6",
    "sg:province":"ON",
    "sg:tags":[
        "appliance"
    ],
    "wof:name":"Ron's Appliance Svc",
    "wof:placetype":"venue"
},
  "geometry": {"coordinates":[-79.2350311279,42.9909095764],"type":"Point"}
}