{
  "type": "Feature",
  "properties": {
    "addr:full":"Saskatoon SK S7K 6M6",
    "addr:postcode":"s7k 6m6",
    "iso:country":"CA",
    "sg:city":"Saskatoon",
    "sg:classifiers":[
        {
            "category":"Manufacturing",
            "subcategory":"Electronics",
            "type":"Manufacturing & Wholesale Goods"
        }
    ],
    "sg:phone":"+1 306 931 3707",
    "sg:postcode":"S7K 6M6",
    "sg:province":"SK",
    "sg:tags":[
        "control",
        "medical",
        "alarm",
        "security"
    ],
    "wof:name":"Save on Security Systems Inc",
    "wof:placetype":"venue"
},
  "geometry": {"coordinates":[-106.664733887,52.1718482971],"type":"Point"}
}