{
  "type": "Feature",
  "properties": {
    "addr:full":"PO Box 71 STN Del Ctr Maple Ridge BC V2X 7E9",
    "addr:housenumber":"po box 71",
    "addr:postcode":"v2x 7e9",
    "addr:street":"Stn Del Ctr",
    "iso:country":"CA",
    "sg:address":"PO Box 71 STN Del Ctr",
    "sg:city":"Maple Ridge",
    "sg:classifiers":[
        {
            "category":"Retail",
            "subcategory":"Repair Shop",
            "type":"Services"
        }
    ],
    "sg:phone":"+1 604 467 5220",
    "sg:postcode":"V2X 7E9",
    "sg:province":"BC",
    "sg:tags":[
        "appliance"
    ],
    "wof:name":"Maple Ridge Appliance Repair",
    "wof:placetype":"venue"
},
  "geometry": {"coordinates":[-122.605827331,49.2168464661],"type":"Point"}
}