{
  "type": "Feature",
  "properties": {
    "addr:full":"418 42nd A St E # A Saskatoon SK S7K 0V3",
    "addr:housenumber":"418",
    "addr:postcode":"s7k 0v3",
    "addr:street":"42Nd A St E # A",
    "iso:country":"CA",
    "sg:address":"418 42nd A St E # A",
    "sg:city":"Saskatoon",
    "sg:classifiers":[
        {
            "category":"Autos & Motor Vehicles",
            "subcategory":"Auto Supplies",
            "type":"Retail Goods"
        }
    ],
    "sg:phone":"+1 306 975 2171",
    "sg:postcode":"S7K 0V3",
    "sg:province":"SK",
    "sg:tags":[
        "automobile",
        "parts"
    ],
    "wof:name":"Tri-West Auto Parts",
    "wof:placetype":"venue"
},
  "geometry": {"coordinates":[-106.664146,52.159332],"type":"Point"}
}