{
  "type": "Feature",
  "properties": {
    "addr:full":"28 Church St Shanty Bay ON L0L 2L0",
    "addr:housenumber":"28",
    "addr:postcode":"l0l 2l0",
    "addr:street":"Church St",
    "iso:country":"CA",
    "sg:address":"28 Church St",
    "sg:city":"Shanty Bay",
    "sg:classifiers":[
        {
            "category":"Social Services",
            "subcategory":"Child Care",
            "type":"Services"
        }
    ],
    "sg:phone":"+1 705 722 7111",
    "sg:postcode":"L0L 2L0",
    "sg:province":"ON",
    "sg:tags":[
        "kindergarten",
        "academic",
        "school"
    ],
    "wof:name":"Shanty Bay Nursery School",
    "wof:placetype":"venue"
},
  "geometry": {"coordinates":[-79.5819015503,44.4105682373],"type":"Point"}
}