{
  "type": "Feature",
  "properties": {
    "addr:full":"22139 South Cooking Lake Rd Sherwood Park AB T8E 1G9",
    "addr:housenumber":"22139",
    "addr:postcode":"t8e 1g9",
    "addr:street":"South Cooking Lake Rd",
    "iso:country":"CA",
    "sg:address":"22139 South Cooking Lake Rd",
    "sg:city":"Sherwood Park",
    "sg:classifiers":[
        {
            "category":"Education",
            "subcategory":"School",
            "type":"Public Place"
        }
    ],
    "sg:phone":"+1 780 922 5920",
    "sg:postcode":"T8E 1G9",
    "sg:province":"AB",
    "wof:name":"St Luke School",
    "wof:placetype":"venue"
},
  "geometry": {"coordinates":[-113.29573822,53.5264015198],"type":"Point"}
}