{
  "type": "Feature",
  "properties": {
    "iso:country":"CA",
    "sg:address":"1163 Highland Ave",
    "sg:city":"Windsor",
    "sg:classifiers":[
        {
            "category":"Home & Garden",
            "subcategory":"Building Materials",
            "type":"Retail Goods"
        }
    ],
    "sg:phone":"+1 519 254 6659",
    "sg:postcode":"N9A 1R6",
    "sg:province":"ON",
    "sg:tags":[
        "door"
    ],
    "wof:name":"Dave's Residential Door Svc",
    "wof:placetype":"venue"
},
  "geometry": {"coordinates":[-83.0254821777,42.3088340759],"type":"Point"}
}