{
  "type": "Feature",
  "properties": {
    "addr:full":"1339 Lakeshore Rd Niagara on the Lake ON L0S 1J0",
    "addr:housenumber":"1339",
    "addr:postcode":"l0s 1j0",
    "addr:street":"Lakeshore Rd;On",
    "iso:country":"CA",
    "sg:address":"1339 Lakeshore Rd",
    "sg:city":"Niagara on the Lake",
    "sg:classifiers":[
        {
            "category":"Manufacturing",
            "subcategory":"Food",
            "type":"Manufacturing & Wholesale Goods"
        }
    ],
    "sg:phone":"+1 905 468 1229",
    "sg:postcode":"L0S 1J0",
    "sg:province":"ON",
    "sg:tags":[
        "winery"
    ],
    "wof:name":"Strewn Winery",
    "wof:placetype":"venue"
},
  "geometry": {"coordinates":[-79.12557200000001,43.252964],"type":"Point"}
}