{
  "type": "Feature",
  "properties": {
    "addr:full":"1955 Boul Industriel Laval QC H7S 1P6",
    "addr:housenumber":"1955",
    "addr:postcode":"h7s 1p6",
    "addr:street":"Boul Industriel",
    "iso:country":"CA",
    "sg:address":"1955 Boul Industriel",
    "sg:city":"Laval",
    "sg:classifiers":[
        {
            "category":"Sports & Exercise",
            "subcategory":"Gym",
            "type":"Entertainment"
        }
    ],
    "sg:phone":"+1 450 629 7875",
    "sg:postcode":"H7S 1P6",
    "sg:province":"QC",
    "sg:tags":[
        "club",
        "health",
        "studio",
        "gymnasium",
        "vitamin"
    ],
    "wof:name":"Supplements Sts Inc",
    "wof:placetype":"venue"
},
  "geometry": {"coordinates":[-73.725166,45.575916],"type":"Point"}
}