{
  "type": "Feature",
  "properties": {
    "addr:full":"Airport Dease Lake BC V0C 1L0",
    "addr:postcode":"bc v0c 1l0",
    "iso:country":"CA",
    "sg:address":"Airport",
    "sg:city":"Dease Lake",
    "sg:classifiers":[
        {
            "category":"Building & Trades",
            "subcategory":"Equipment Rental",
            "type":"Services"
        }
    ],
    "sg:phone":"+1 250 771 4400",
    "sg:postcode":"V0C 1L0",
    "sg:province":"BC",
    "sg:tags":[
        "aircraft",
        "leasing",
        "charter"
    ],
    "wof:name":"Northern Lights Air Dease Lake",
    "wof:placetype":"venue"
},
  "geometry": {"coordinates":[-129.98916600000001,58.438744],"type":"Point"}
}