{
  "type": "Feature",
  "properties": {
    "iso:country":"CA",
    "sg:address":"570 Denison St",
    "sg:city":"Markham",
    "sg:classifiers":[
        {
            "category":"Wholesale",
            "subcategory":"Hardware",
            "type":"Manufacturing & Wholesale Goods"
        }
    ],
    "sg:phone":"+1 905 475 6644",
    "sg:postcode":"L3R 1B9",
    "sg:province":"ON",
    "sg:tags":[
        "equipment",
        "heating",
        "system"
    ],
    "wof:name":"Don Park Inc",
    "wof:placetype":"venue"
},
  "geometry": {"coordinates":[-79.34279600000001,43.823872],"type":"Point"}
}