{
  "type": "Feature",
  "properties": {
    "iso:country":"CA",
    "sg:address":"RR 1",
    "sg:city":"Cherry Valley",
    "sg:classifiers":[
        {
            "category":"Recreation",
            "type":"Entertainment"
        }
    ],
    "sg:phone":"+1 613 476 1060",
    "sg:postcode":"K0K 1P0",
    "sg:province":"ON",
    "sg:tags":[
        "range",
        "practice",
        "golf"
    ],
    "wof:name":"Woodland Echoes",
    "wof:placetype":"venue"
},
  "geometry": {"coordinates":[-77.1544342041,43.9358444214],"type":"Point"}
}