{
  "type": "Feature",
  "properties": {
    "addr:full":"190 Rue Des Bergeres L'Ile-Bizard QC H9C 2T3",
    "addr:housenumber":"190",
    "addr:postcode":"h9c 2t3",
    "addr:street":"Rue Des Bergeres",
    "iso:country":"CA",
    "sg:address":"190 Rue Des Bergeres",
    "sg:city":"L'Ile-Bizard",
    "sg:classifiers":[
        {
            "category":"Real Estate",
            "subcategory":"Architect",
            "type":"Services"
        }
    ],
    "sg:phone":"+1 514 696 1230",
    "sg:postcode":"H9C 2T3",
    "sg:province":"QC",
    "wof:name":"Letuve Architectes",
    "wof:placetype":"venue"
},
  "geometry": {"coordinates":[-73.8814086914,45.4980773926],"type":"Point"}
}