{
  "type": "Feature",
  "properties": {
    "addr:full":"213 4th St Rainy River ON P0W 1L0",
    "addr:housenumber":"213",
    "addr:postcode":"p0w 1l0",
    "addr:street":"4Th St",
    "iso:country":"CA",
    "sg:address":"213 4th St",
    "sg:city":"Rainy River",
    "sg:classifiers":[
        {
            "category":"Insurance",
            "subcategory":"Insurance Agent",
            "type":"Services"
        }
    ],
    "sg:phone":"+1 807 852 3257",
    "sg:postcode":"P0W 1L0",
    "sg:province":"ON",
    "wof:name":"Gillons' Insurance Brokers Ltd",
    "wof:placetype":"venue"
},
  "geometry": {"coordinates":[-94.5685882568,48.7193603516],"type":"Point"}
}