{
  "type": "Feature",
  "properties": {
    "addr:full":"12550 20 Ave Surrey BC V4A 1Y6",
    "addr:housenumber":"12550",
    "addr:postcode":"v4a 1y6",
    "addr:street":"20 Ave",
    "iso:country":"CA",
    "sg:address":"12550 20 Ave",
    "sg:city":"Surrey",
    "sg:classifiers":[
        {
            "category":"Education",
            "subcategory":"School",
            "type":"Public Place"
        }
    ],
    "sg:phone":"+1 604 538 1770",
    "sg:postcode":"V4A 1Y6",
    "sg:province":"BC",
    "wof:name":"Ocean Cliff Elementary School",
    "wof:placetype":"venue"
},
  "geometry": {"coordinates":[-122.874969482,49.0384941101],"type":"Point"}
}