{
  "type": "Feature",
  "properties": {
    "addr:full":"70 Consumers Dr Saint John NB E2J 4Z3",
    "addr:housenumber":"70",
    "addr:postcode":"e2j 4z3",
    "addr:street":"Consumers Dr",
    "iso:country":"CA",
    "sg:address":"70 Consumers Dr",
    "sg:city":"Saint John",
    "sg:classifiers":[
        {
            "category":"Restaurant",
            "type":"Food & Drink"
        }
    ],
    "sg:phone":"+1 506 636 8080",
    "sg:postcode":"E2J 4Z3",
    "sg:province":"NB",
    "sg:tags":[
        "pizza"
    ],
    "wof:name":"Pizza Delight",
    "wof:placetype":"venue"
},
  "geometry": {"coordinates":[-66.021248,45.306416],"type":"Point"}
}