{
  "type": "Feature",
  "properties": {
    "addr:full":"538 Mayor Magrath Dr S Lethbridge AB T1J 3M2",
    "addr:housenumber":"538",
    "addr:postcode":"t1j 3m2",
    "addr:street":"Mayor Magrath Dr S",
    "iso:country":"CA",
    "sg:address":"538 Mayor Magrath Dr S",
    "sg:city":"Lethbridge",
    "sg:classifiers":[
        {
            "category":"Restaurant",
            "type":"Food & Drink"
        }
    ],
    "sg:phone":"+1 403 382 2270",
    "sg:postcode":"T1J 3M2",
    "sg:province":"AB",
    "sg:tags":[
        "parlor",
        "ice",
        "cream"
    ],
    "wof:name":"Cone Zone Ice Cream",
    "wof:placetype":"venue"
},
  "geometry": {"coordinates":[-112.80970000000001,49.691822],"type":"Point"}
}