{
  "type": "Feature",
  "properties": {
    "addr:full":"23 Hamilton St Sandy Hook MB R0C 2W0",
    "addr:housenumber":"23",
    "addr:postcode":"r0c 2w0",
    "addr:street":"Hamilton St",
    "iso:country":"CA",
    "sg:address":"23 Hamilton St",
    "sg:city":"Sandy Hook",
    "sg:classifiers":[
        {
            "category":"Building & Trades",
            "subcategory":"Electrical",
            "type":"Services"
        }
    ],
    "sg:phone":"+1 204 389 4046",
    "sg:postcode":"R0C 2W0",
    "sg:province":"MB",
    "sg:tags":[
        "electric",
        "contractor"
    ],
    "wof:name":"Lakeview Electric",
    "wof:placetype":"venue"
},
  "geometry": {"coordinates":[-96.98571,50.544754],"type":"Point"}
}