{
  "type": "Feature",
  "properties": {
    "addr:full":"Windsor ON N9G 1X2",
    "addr:postcode":"n9g 1x2",
    "iso:country":"CA",
    "sg:city":"Windsor",
    "sg:classifiers":[
        {
            "category":"Health Services",
            "subcategory":"Chiropractor",
            "type":"Services"
        }
    ],
    "sg:phone":"+1 519 967 0004",
    "sg:postcode":"N9G 1X2",
    "sg:province":"ON",
    "wof:name":"Cabana Court Chiropractic",
    "wof:placetype":"venue"
},
  "geometry": {"coordinates":[-83.0028305054,42.2560920715],"type":"Point"}
}