{
  "type": "Feature",
  "properties": {
    "addr:full":"705 Rue Bourget Montreal QC H4C 2M6",
    "addr:housenumber":"705",
    "addr:postcode":"h4c 2m6",
    "addr:street":"Rue Bourget",
    "iso:country":"CA",
    "sg:address":"705 Rue Bourget",
    "sg:city":"Montreal",
    "sg:classifiers":[
        {
            "category":"Professional",
            "subcategory":"Detective & Security Services",
            "type":"Services"
        }
    ],
    "sg:phone":"+1 514 933 7191",
    "sg:postcode":"H4C 2M6",
    "sg:province":"QC",
    "sg:tags":[
        "control",
        "guard",
        "patrol",
        "system"
    ],
    "wof:name":"Garda Du Canada",
    "wof:placetype":"venue"
},
  "geometry": {"coordinates":[-73.58358800000001,45.480885],"type":"Point"}
}