{
  "type": "Feature",
  "properties": {
    "addr:full":"58 Arthur St W Thornbury ON N0H 2P0",
    "addr:housenumber":"58",
    "addr:postcode":"n0h 2p0",
    "addr:street":"Arthur St W",
    "iso:country":"CA",
    "sg:address":"58 Arthur St W",
    "sg:city":"Thornbury",
    "sg:classifiers":[
        {
            "category":"Retail",
            "subcategory":"Auto Repair",
            "type":"Services"
        }
    ],
    "sg:phone":"+1 519 599 7580",
    "sg:postcode":"N0H 2P0",
    "sg:province":"ON",
    "sg:tags":[
        "repairing",
        "automobile"
    ],
    "wof:name":"Earl's Car Care",
    "wof:placetype":"venue"
},
  "geometry": {"coordinates":[-80.456558,44.563976],"type":"Point"}
}