{
  "type": "Feature",
  "properties": {
    "addr:full":"1458 Rue Crescent Montreal QC H3G 2B6",
    "addr:housenumber":"1458",
    "addr:postcode":"h3g 2b6",
    "addr:street":"Rue Crescent",
    "iso:country":"CA",
    "sg:address":"1458 Rue Crescent",
    "sg:city":"Montreal",
    "sg:classifiers":[
        {
            "category":"Restaurant",
            "type":"Food & Drink"
        }
    ],
    "sg:phone":"+1 514 987 1420",
    "sg:postcode":"H3G 2B6",
    "sg:province":"QC",
    "wof:name":"Hard Rock Cafe",
    "wof:placetype":"venue"
},
  "geometry": {"coordinates":[-73.577041626,45.4977836609],"type":"Point"}
}