{
  "type": "Feature",
  "properties": {
    "addr:full":"Toronto ON M5G 1T6",
    "addr:postcode":"m5g 1t6",
    "iso:country":"CA",
    "sg:city":"Toronto",
    "sg:classifiers":[
        {
            "category":"Travel",
            "subcategory":"Travel Agent",
            "type":"Entertainment"
        }
    ],
    "sg:phone":"+1 416 595 9877",
    "sg:postcode":"M5G 1T6",
    "sg:province":"ON",
    "sg:tags":[
        "agency",
        "bureau"
    ],
    "wof:name":"Javisa International Ltd",
    "wof:placetype":"venue"
},
  "geometry": {"coordinates":[-79.387703,43.654259],"type":"Point"}
}