{
  "type": "Feature",
  "properties": {
    "addr:full":"49 Cherry St Simcoe ON N3Y 1B3",
    "addr:housenumber":"49",
    "addr:postcode":"n3y 1b3",
    "addr:street":"Cherry St",
    "iso:country":"CA",
    "sg:address":"49 Cherry St",
    "sg:city":"Simcoe",
    "sg:classifiers":[
        {
            "category":"Professional",
            "subcategory":"Art Services",
            "type":"Services"
        }
    ],
    "sg:phone":"+1 519 426 6462",
    "sg:postcode":"N3Y 1B3",
    "sg:province":"ON",
    "sg:tags":[
        "graphic",
        "designer",
        "sign"
    ],
    "wof:name":"Norfolk Signs",
    "wof:placetype":"venue"
},
  "geometry": {"coordinates":[-80.3022079468,42.8243179321],"type":"Point"}
}