{
  "type": "Feature",
  "properties": {
    "addr:full":"700 Rue Saint-Etienne L'Assomption QC J5W 1Z1",
    "addr:housenumber":"700",
    "addr:postcode":"j5w 1z1",
    "addr:street":"Rue Saint-Etienne",
    "iso:country":"CA",
    "sg:address":"700 Rue Saint-Etienne",
    "sg:city":"L'Assomption",
    "sg:classifiers":[
        {
            "category":"Manufacturing",
            "subcategory":"Tools & Machinery",
            "type":"Manufacturing & Wholesale Goods"
        }
    ],
    "sg:phone":"+1 450 589 9973",
    "sg:postcode":"J5W 1Z1",
    "sg:province":"QC",
    "sg:tags":[
        "equipment",
        "sawmill",
        "supply"
    ],
    "wof:name":"Techni-Sciage & Alignement",
    "wof:placetype":"venue"
},
  "geometry": {"coordinates":[-73.426041,45.815048],"type":"Point"}
}