{
  "type": "Feature",
  "properties": {
    "iso:country":"CA",
    "sg:address":"225 White St",
    "sg:city":"Atikokan",
    "sg:classifiers":[
        {
            "category":"Recreation",
            "type":"Entertainment"
        }
    ],
    "sg:phone":"+1 807 597 6932",
    "sg:postcode":"P0T 1C0",
    "sg:province":"ON",
    "sg:tags":[
        "provincial",
        "parks"
    ],
    "wof:name":"Atikokan Parks & Rec Ofc",
    "wof:placetype":"venue"
},
  "geometry": {"coordinates":[-91.5928726196,48.7592315674],"type":"Point"}
}