{
  "type": "Feature",
  "properties": {
    "addr:full":"4908 50 Ave Provost AB T0B 3S0",
    "addr:housenumber":"4908",
    "addr:postcode":"t0b 3s0",
    "addr:street":"50 Ave",
    "iso:country":"CA",
    "sg:address":"4908 50 Ave",
    "sg:city":"Provost",
    "sg:classifiers":[
        {
            "category":"Building & Trades",
            "subcategory":"Electrical",
            "type":"Services"
        }
    ],
    "sg:phone":"+1 780 753 4770",
    "sg:postcode":"T0B 3S0",
    "sg:province":"AB",
    "sg:tags":[
        "electric",
        "contractor"
    ],
    "wof:name":"Enerflex Syntech",
    "wof:placetype":"venue"
},
  "geometry": {"coordinates":[-110.26405334499999,52.351146698],"type":"Point"}
}