{
  "type": "Feature",
  "properties": {
    "addr:full":"2103 Conc Rd 10 Blackstock ON L0B 1B0",
    "addr:housenumber":"2103;10",
    "addr:postcode":"l0b 1b0",
    "addr:street":"Conc Rd",
    "iso:country":"CA",
    "sg:address":"2103 Conc Rd 10",
    "sg:city":"Blackstock",
    "sg:classifiers":[
        {
            "category":"Retail",
            "subcategory":"Auto Repair",
            "type":"Services"
        }
    ],
    "sg:phone":"+1 905 263 8046",
    "sg:postcode":"L0B 1B0",
    "sg:province":"ON",
    "sg:tags":[
        "repairing",
        "automobile"
    ],
    "wof:name":"Beech's Garage",
    "wof:placetype":"venue"
},
  "geometry": {"coordinates":[-78.82080841059999,44.1082382202],"type":"Point"}
}