{
  "type": "Feature",
  "properties": {
    "addr:full":"175 Rue Sherbrooke E Montreal QC H2X 1C7",
    "addr:housenumber":"175",
    "addr:postcode":"h2x 1c7",
    "addr:street":"Rue Sherbrooke E",
    "iso:country":"CA",
    "sg:address":"175 Rue Sherbrooke E",
    "sg:city":"Montreal",
    "sg:classifiers":[
        {
            "category":"Professional",
            "subcategory":"Research",
            "type":"Services"
        }
    ],
    "sg:phone":"+1 514 844 1929",
    "sg:postcode":"H2X 1C7",
    "sg:province":"QC",
    "sg:tags":[
        "foundation",
        "philanthropic"
    ],
    "wof:name":"Oeuvre DE St Pierre Apotre",
    "wof:placetype":"venue"
},
  "geometry": {"coordinates":[-73.568825,45.514339],"type":"Point"}
}