{
  "type": "Feature",
  "properties": {
    "addr:full":"925 Columbia Ave Castlegar BC V1N 1H4",
    "addr:housenumber":"925",
    "addr:postcode":"v1n 1h4",
    "addr:street":"Columbia Ave",
    "iso:country":"CA",
    "sg:address":"925 Columbia Ave",
    "sg:city":"Castlegar",
    "sg:classifiers":[
        {
            "category":"Recreation",
            "type":"Entertainment"
        }
    ],
    "sg:phone":"+1 250 365 5021",
    "sg:postcode":"V1N 1H4",
    "sg:province":"BC",
    "sg:tags":[
        "center",
        "government"
    ],
    "wof:name":"Castlegar Pioneer Arena",
    "wof:placetype":"venue"
},
  "geometry": {"coordinates":[-117.663719,49.31588],"type":"Point"}
}