{
  "type": "Feature",
  "properties": {
    "addr:full":"1278 Rang Sainte-Cecile Sainte-Beatrix QC J0K 1Y0",
    "addr:housenumber":"1278",
    "addr:postcode":"j0k 1y0",
    "addr:street":"Rang Sainte-Cecile Sainte-Beatrix",
    "iso:country":"CA",
    "sg:address":"1278 Rang Sainte-Cecile",
    "sg:city":"Sainte-Beatrix",
    "sg:classifiers":[
        {
            "category":"Retail",
            "subcategory":"Auto Repair",
            "type":"Services"
        }
    ],
    "sg:phone":"+1 450 883 6905",
    "sg:postcode":"J0K 1Y0",
    "sg:province":"QC",
    "sg:tags":[
        "body",
        "automobile",
        "painting"
    ],
    "wof:name":"Garage Normand Laporte",
    "wof:placetype":"venue"
},
  "geometry": {"coordinates":[-73.620964,46.195309],"type":"Point"}
}