{
  "type": "Feature",
  "properties": {
    "addr:full":"Canora SK S0A 0L0",
    "addr:postcode":"s0a 0l0",
    "addr:street":"Canora",
    "iso:country":"CA",
    "sg:city":"Canora",
    "sg:classifiers":[
        {
            "category":"Manufacturing",
            "subcategory":"Apparel",
            "type":"Manufacturing & Wholesale Goods"
        }
    ],
    "sg:phone":"+1 306 563 4443",
    "sg:postcode":"S0A 0L0",
    "sg:province":"SK",
    "sg:tags":[
        "textile",
        "manufacturer"
    ],
    "wof:name":"Canora Weaving & Manufacturing",
    "wof:placetype":"venue"
},
  "geometry": {"coordinates":[-102.432434,51.635456],"type":"Point"}
}