{
  "type": "Feature",
  "properties": {
    "addr:full":"Windsor ON N8X 5E5",
    "addr:postcode":"n8x 5e5",
    "iso:country":"CA",
    "sg:city":"Windsor",
    "sg:classifiers":[
        {
            "category":"Wholesale",
            "subcategory":"Machinery & Supplies",
            "type":"Manufacturing & Wholesale Goods"
        }
    ],
    "sg:phone":"+1 519 944 4774",
    "sg:postcode":"N8X 5E5",
    "sg:province":"ON",
    "sg:tags":[
        "fire",
        "equipment",
        "protection"
    ],
    "wof:name":"Forest City Fire Protection",
    "wof:placetype":"venue"
},
  "geometry": {"coordinates":[-83.0252151489,42.3030433655],"type":"Point"}
}