{
  "type": "Feature",
  "properties": {
    "addr:full":"43 Morris Ave N Gladstone MB R0J 0T0",
    "addr:housenumber":"43",
    "addr:postcode":"r0j 0t0",
    "addr:street":"Morris Ave N",
    "iso:country":"CA",
    "sg:address":"43 Morris Ave N",
    "sg:city":"Gladstone",
    "sg:classifiers":[
        {
            "category":"Personal",
            "subcategory":"Beauty Salon",
            "type":"Services"
        }
    ],
    "sg:phone":"+1 204 385 2261",
    "sg:postcode":"R0J 0T0",
    "sg:province":"MB",
    "wof:name":"Diane's Beauty Salon",
    "wof:placetype":"venue"
},
  "geometry": {"coordinates":[-98.9507522583,50.2254219055],"type":"Point"}
}