{
  "type": "Feature",
  "properties": {
    "addr:full":"Edmonton AB T5N 2L4",
    "addr:postcode":"t5n 2l4",
    "iso:country":"CA",
    "sg:city":"Edmonton",
    "sg:classifiers":[
        {
            "category":"Personal",
            "subcategory":"Beauty Salon",
            "type":"Services"
        }
    ],
    "sg:phone":"+1 780 452 6245",
    "sg:postcode":"T5N 2L4",
    "sg:province":"AB",
    "wof:name":"Nail Magic on 9th",
    "wof:placetype":"venue"
},
  "geometry": {"coordinates":[-113.563271,53.543579],"type":"Point"}
}