{
  "type": "Feature",
  "properties": {
    "iso:country":"CA",
    "sg:address":"128 Maple Dr",
    "sg:city":"Belleville",
    "sg:classifiers":[
        {
            "category":"Building & Trades",
            "subcategory":"Construction",
            "type":"Services"
        }
    ],
    "sg:phone":"+1 613 962 8444",
    "sg:postcode":"K8P 2R2",
    "sg:province":"ON",
    "sg:tags":[
        "dry wall",
        "contractor"
    ],
    "wof:name":"Zanette Drywall CO Ltd",
    "wof:placetype":"venue"
},
  "geometry": {"coordinates":[-77.3991775513,44.1825828552],"type":"Point"}
}