{
  "type": "Feature",
  "properties": {
    "iso:country":"CA",
    "sg:address":"2720 Queensview Dr # 1177",
    "sg:city":"Ottawa",
    "sg:classifiers":[
        {
            "category":"Professional",
            "subcategory":"Computer Services",
            "type":"Services"
        }
    ],
    "sg:phone":"+1 613 828 4446",
    "sg:postcode":"K2B 1A5",
    "sg:province":"ON",
    "sg:tags":[
        "website",
        "design",
        "internet"
    ],
    "wof:name":"Edigenous Technology",
    "wof:placetype":"venue"
},
  "geometry": {"coordinates":[-75.7881317139,45.3524665833],"type":"Point"}
}