{
  "type": "Feature",
  "properties": {
    "addr:full":"2734 Triumph St Vancouver BC V5K 1T2",
    "addr:housenumber":"2734",
    "addr:postcode":"v5k 1t2",
    "addr:street":"Triumph St",
    "iso:country":"CA",
    "sg:address":"2734 Triumph St",
    "sg:city":"Vancouver",
    "sg:classifiers":[
        {
            "category":"Professional",
            "subcategory":"Art Services",
            "type":"Services"
        }
    ],
    "sg:phone":"+1 604 872 0337",
    "sg:postcode":"V5K 1T2",
    "sg:province":"BC",
    "sg:tags":[
        "graphic",
        "designer"
    ],
    "wof:name":"Zabolotney Graphic Design",
    "wof:placetype":"venue"
},
  "geometry": {"coordinates":[-123.04826355,49.2837486267],"type":"Point"}
}