{
  "type": "Feature",
  "properties": {
    "addr:full":"Quebec QC G1K 6E1",
    "addr:postcode":"g1k 6e1",
    "iso:country":"CA",
    "sg:city":"Quebec",
    "sg:classifiers":[
        {
            "category":"Professional",
            "subcategory":"Business Services",
            "type":"Services"
        }
    ],
    "sg:phone":"+1 418 647 2525",
    "sg:postcode":"G1K 6E1",
    "sg:province":"QC",
    "sg:tags":[
        "event"
    ],
    "wof:name":"Quebe Comm",
    "wof:placetype":"venue"
},
  "geometry": {"coordinates":[-71.225967,46.816093],"type":"Point"}
}