{
  "type": "Feature",
  "properties": {
    "addr:full":"15 St Christopher St Noelville ON P0M 2N0",
    "addr:housenumber":"15",
    "addr:postcode":"p0m 2n0",
    "addr:street":"St Christopher St",
    "iso:country":"CA",
    "sg:address":"15 St Christopher St",
    "sg:city":"Noelville",
    "sg:classifiers":[
        {
            "category":"Social Services",
            "type":"Services"
        }
    ],
    "sg:phone":"+1 705 898 2951",
    "sg:postcode":"P0M 2N0",
    "sg:province":"ON",
    "sg:tags":[
        "organization",
        "welfare"
    ],
    "wof:name":"Knights of Columbus Hall",
    "wof:placetype":"venue"
},
  "geometry": {"coordinates":[-80.42888600000001,46.136082],"type":"Point"}
}