{
  "type": "Feature",
  "properties": {
    "addr:full":"3447 Cawthra Rd Mississauga ON L5A 2X9",
    "addr:housenumber":"3447",
    "addr:postcode":"l5a 2x9",
    "addr:street":"Cawthra Rd",
    "iso:country":"CA",
    "sg:address":"3447 Cawthra Rd",
    "sg:city":"Mississauga",
    "sg:classifiers":[
        {
            "category":"Home & Garden",
            "subcategory":"Building Materials",
            "type":"Retail Goods"
        }
    ],
    "sg:phone":"+1 416 410 7881",
    "sg:postcode":"L5A 2X9",
    "sg:province":"ON",
    "sg:tags":[
        "windows",
        "door"
    ],
    "wof:name":"Olympia Windows & Doors Ltd",
    "wof:placetype":"venue"
},
  "geometry": {"coordinates":[-79.612061,43.603237],"type":"Point"}
}