{
  "type": "Feature",
  "properties": {
    "iso:country":"CA",
    "sg:address":"300 Main St N #200",
    "sg:city":"Brampton",
    "sg:classifiers":[
        {
            "category":"Health Services",
            "subcategory":"Doctor",
            "type":"Services"
        }
    ],
    "sg:phone":"+1 905 451 1937",
    "sg:postcode":"L6V 4H6",
    "sg:province":"ON",
    "sg:tags":[
        "physician",
        "surgeon"
    ],
    "wof:name":"Manson, Nadine MD",
    "wof:placetype":"venue"
},
  "geometry": {"coordinates":[-79.7685546875,43.6925163269],"type":"Point"}
}