{
  "type": "Feature",
  "properties": {
    "addr:full":"3490 157 Rte Notre-Dame-Du-Mont-Carmel QC G0X 3J0",
    "addr:housenumber":"3490",
    "addr:postcode":"g0x 3j0",
    "addr:street":"157 Rte",
    "iso:country":"CA",
    "sg:address":"3490 157 Rte",
    "sg:city":"Notre-Dame-Du-Mont-Carmel",
    "sg:classifiers":[
        {
            "category":"Food & Beverages",
            "subcategory":"Groceries & Convenience Stores",
            "type":"Retail Goods"
        }
    ],
    "sg:phone":"+1 819 378 5242",
    "sg:postcode":"G0X 3J0",
    "sg:province":"QC",
    "wof:name":"Depanneur Station Svc Chez",
    "wof:placetype":"venue"
},
  "geometry": {"coordinates":[-69.84530639650001,47.4493675232],"type":"Point"}
}