{
  "type": "Feature",
  "properties": {
    "addr:full":"25 Pulp Mill Rd Point Tupper NS B9A 1Z3",
    "addr:housenumber":"25",
    "addr:postcode":"b9a 1z3",
    "addr:street":"Pulp Mill Rd",
    "iso:country":"CA",
    "sg:address":"25 Pulp Mill Rd",
    "sg:city":"Point Tupper",
    "sg:classifiers":[
        {
            "category":"Building & Trades",
            "subcategory":"Equipment Rental",
            "type":"Services"
        }
    ],
    "sg:phone":"+1 902 625 1400",
    "sg:postcode":"B9A 1Z3",
    "sg:province":"NS",
    "sg:tags":[
        "house",
        "mover",
        "crane"
    ],
    "wof:name":"Cape Breton Crane Rentals",
    "wof:placetype":"venue"
},
  "geometry": {"coordinates":[-61.3568305969,45.6034736633],"type":"Point"}
}