{
  "type": "Feature",
  "properties": {
    "addr:full":"Prince George BC V2N 4A1",
    "addr:postcode":"v2n 4a1",
    "iso:country":"CA",
    "sg:city":"Prince George",
    "sg:classifiers":[
        {
            "category":"Health Services",
            "subcategory":"Doctor",
            "type":"Services"
        }
    ],
    "sg:phone":"+1 250 964 6464",
    "sg:postcode":"V2N 4A1",
    "sg:province":"BC",
    "sg:tags":[
        "dentist"
    ],
    "wof:name":"Brown, Jonathan DDS",
    "wof:placetype":"venue"
},
  "geometry": {"coordinates":[-122.778060913,53.8686714172],"type":"Point"}
}