{
  "type": "Feature",
  "properties": {
    "addr:full":"14 Weslemkoom Lake Rd Gilmour ON K0L 1W0",
    "addr:housenumber":"14",
    "addr:postcode":"k0l 1w0",
    "addr:street":"Weslemkoom Lake Rd",
    "iso:country":"CA",
    "sg:address":"14 Weslemkoom Lake Rd",
    "sg:city":"Gilmour",
    "sg:classifiers":[
        {
            "category":"Home & Garden",
            "subcategory":"Hardware",
            "type":"Retail Goods"
        }
    ],
    "sg:phone":"+1 613 474 2855",
    "sg:postcode":"K0L 1W0",
    "sg:province":"ON",
    "sg:tags":[
        "saw"
    ],
    "wof:name":"Stan's Service Ctr",
    "wof:placetype":"venue"
},
  "geometry": {"coordinates":[-77.611671,44.823124],"type":"Point"}
}