{
  "type": "Feature",
  "properties": {
    "addr:full":"920 Dundas St W Toronto ON M6J 1W3",
    "addr:housenumber":"920",
    "addr:postcode":"m6j 1w3",
    "addr:street":"Dundas St W",
    "iso:country":"CA",
    "sg:address":"920 Dundas St W",
    "sg:city":"Toronto",
    "sg:classifiers":[
        {
            "category":"Food & Beverages",
            "subcategory":"Specialty",
            "type":"Retail Goods"
        }
    ],
    "sg:phone":"+1 416 603 7978",
    "sg:postcode":"M6J 1W3",
    "sg:province":"ON",
    "sg:tags":[
        "health",
        "diet"
    ],
    "wof:name":"Ervanaria Victoria Inc",
    "wof:placetype":"venue"
},
  "geometry": {"coordinates":[-79.4129486084,43.6509666443],"type":"Point"}
}