{
  "type": "Feature",
  "properties": {
    "addr:full":"110 Rue DE LA Gare Saint-Jerome QC J7Z 2C1",
    "addr:housenumber":"110",
    "addr:postcode":"j7z 2c1",
    "addr:street":"Rue De La Gare Saint-Jerome",
    "iso:country":"CA",
    "sg:address":"110 Rue DE LA Gare",
    "sg:city":"Saint-Jerome",
    "sg:classifiers":[
        {
            "category":"Travel",
            "subcategory":"Hotels & Motels",
            "type":"Entertainment"
        }
    ],
    "sg:phone":"+1 450 432 9010",
    "sg:postcode":"J7Z 2C1",
    "sg:province":"QC",
    "wof:name":"Hotel Plouffe",
    "wof:placetype":"venue"
},
  "geometry": {"coordinates":[-74.0013580322,45.7760925293],"type":"Point"}
}