{
  "type": "Feature",
  "properties": {
    "addr:full":"207 Queens Quay W Toronto ON M5J 1A7",
    "addr:housenumber":"207",
    "addr:postcode":"m5j 1a7",
    "addr:street":"Queens Quay W",
    "iso:country":"CA",
    "sg:address":"207 Queens Quay W",
    "sg:city":"Toronto",
    "sg:classifiers":[
        {
            "category":"Restaurant",
            "type":"Food & Drink"
        }
    ],
    "sg:phone":"+1 416 203 6300",
    "sg:postcode":"M5J 1A7",
    "sg:province":"ON",
    "wof:name":"Boathouse Bar & Grill",
    "wof:placetype":"venue"
},
  "geometry": {"coordinates":[-79.380669,43.639614],"type":"Point"}
}