{
  "type": "Feature",
  "properties": {
    "iso:country":"CA",
    "sg:address":"5122 Av Du Parc",
    "sg:city":"Montreal",
    "sg:classifiers":[
        {
            "category":"Home & Garden",
            "subcategory":"Furniture",
            "type":"Retail Goods"
        }
    ],
    "sg:phone":"+1 514 270 8013",
    "sg:postcode":"H2V 4G5",
    "sg:province":"QC",
    "wof:name":"G M Portal",
    "wof:placetype":"venue"
},
  "geometry": {"coordinates":[-73.596329,45.519733],"type":"Point"}
}