{
  "type": "Feature",
  "properties": {
    "addr:full":"3553 Garrison Gate SW Calgary AB T2T 6E4",
    "addr:housenumber":"3553",
    "addr:postcode":"t2t 6e4",
    "addr:street":"Garrison Gate Sw",
    "iso:country":"CA",
    "sg:address":"3553 Garrison Gate SW",
    "sg:city":"Calgary",
    "sg:classifiers":[
        {
            "category":"Food & Beverages",
            "subcategory":"Liquor & Beverages",
            "type":"Retail Goods"
        }
    ],
    "sg:phone":"+1 403 240 9304",
    "sg:postcode":"T2T 6E4",
    "sg:province":"AB",
    "sg:tags":[
        "store"
    ],
    "wof:name":"Safeway Liquor Store",
    "wof:placetype":"venue"
},
  "geometry": {"coordinates":[-114.114242554,51.0223579407],"type":"Point"}
}