{
  "type": "Feature",
  "properties": {
    "addr:full":"7925 10th Ave New Westminster BC V3L 4Y6",
    "addr:housenumber":"7925",
    "addr:postcode":"v3l 4y6",
    "addr:street":"10Th Ave",
    "iso:country":"CA",
    "sg:address":"7925 10th Ave",
    "sg:city":"New Westminster",
    "sg:classifiers":[
        {
            "category":"Organizations",
            "subcategory":"Religious Organization",
            "type":"Services"
        }
    ],
    "sg:phone":"+1 604 521 9427",
    "sg:postcode":"V3L 4Y6",
    "sg:province":"BC",
    "sg:tags":[
        "church"
    ],
    "wof:name":"Westminster Sda Church",
    "wof:placetype":"venue"
},
  "geometry": {"coordinates":[-122.896156,49.23558],"type":"Point"}
}