{
  "type": "Feature",
  "properties": {
    "addr:full":"211 4th Ave NW Nakusp BC V0G 1R0",
    "addr:housenumber":"211",
    "addr:postcode":"v0g 1r0",
    "addr:street":"4Th Ave Nw",
    "iso:country":"CA",
    "sg:address":"211 4th Ave NW",
    "sg:city":"Nakusp",
    "sg:classifiers":[
        {
            "category":"Organizations",
            "subcategory":"Religious Organization",
            "type":"Services"
        }
    ],
    "sg:phone":"+1 250 265 3380",
    "sg:postcode":"V0G 1R0",
    "sg:province":"BC",
    "sg:tags":[
        "church"
    ],
    "wof:name":"Seventh Day Adventist Church",
    "wof:placetype":"venue"
},
  "geometry": {"coordinates":[-117.80188,50.241211],"type":"Point"}
}