{
  "type": "Feature",
  "properties": {
    "addr:full":"420 Crawforth St Whitby ON L1N 3R5",
    "addr:housenumber":"420",
    "addr:postcode":"l1n 3r5",
    "addr:street":"Crawforth St",
    "iso:country":"CA",
    "sg:address":"420 Crawforth St",
    "sg:city":"Whitby",
    "sg:classifiers":[
        {
            "category":"Health Services",
            "subcategory":"Doctor",
            "type":"Services"
        }
    ],
    "sg:phone":"+1 905 668 3603",
    "sg:postcode":"L1N 3R5",
    "sg:province":"ON",
    "sg:tags":[
        "dentist"
    ],
    "wof:name":"Greenland, Larry DDS",
    "wof:placetype":"venue"
},
  "geometry": {"coordinates":[-78.915077,43.888451],"type":"Point"}
}