{
  "type": "Feature",
  "properties": {
    "addr:full":"Brandon MB R7A 6N5",
    "addr:postcode":"r7a 6n5",
    "iso:country":"CA",
    "sg:city":"Brandon",
    "sg:classifiers":[
        {
            "category":"Personal",
            "subcategory":"Beauty Salon",
            "type":"Services"
        }
    ],
    "sg:phone":"+1 204 728 4488",
    "sg:postcode":"R7A 6N5",
    "sg:province":"MB",
    "wof:name":"Black Orchid Beauty Salon",
    "wof:placetype":"venue"
},
  "geometry": {"coordinates":[-99.948868,49.848358],"type":"Point"}
}