{
  "type": "Feature",
  "properties": {
    "addr:full":"6039 Centre St SW Calgary AB T2H 0C2",
    "addr:housenumber":"6039",
    "addr:postcode":"t2h 0c2",
    "addr:street":"Centre St Sw",
    "iso:country":"CA",
    "sg:address":"6039 Centre St SW",
    "sg:city":"Calgary",
    "sg:classifiers":[
        {
            "category":"Utilities",
            "subcategory":"Mobile Phone",
            "type":"Services"
        }
    ],
    "sg:phone":"+1 403 252 5072",
    "sg:postcode":"T2H 0C2",
    "sg:province":"AB",
    "sg:tags":[
        "telephone",
        "cellular"
    ],
    "wof:name":"Personal Communications Systs",
    "wof:placetype":"venue"
},
  "geometry": {"coordinates":[-114.064049,50.999195],"type":"Point"}
}