{
  "type": "Feature",
  "properties": {
    "addr:full":"5950 Boul Cousineau Saint-Hubert QC J3Y 7R9",
    "addr:housenumber":"5950",
    "addr:postcode":"j3y 7r9",
    "addr:street":"Boul Cousineau",
    "iso:country":"CA",
    "sg:address":"5950 Boul Cousineau",
    "sg:city":"Saint-Hubert",
    "sg:classifiers":[
        {
            "category":"Restaurant",
            "type":"Food & Drink"
        }
    ],
    "sg:phone":"+1 450 462 2263",
    "sg:postcode":"J3Y 7R9",
    "sg:province":"QC",
    "wof:name":"Bella Pasta & Grill",
    "wof:placetype":"venue"
},
  "geometry": {"coordinates":[-73.409729,45.495708],"type":"Point"}
}