{
  "type": "Feature",
  "properties": {
    "addr:full":"Burnaby BC V5H 4C2",
    "addr:postcode":"v5h 4c2",
    "iso:country":"CA",
    "sg:city":"Burnaby",
    "sg:classifiers":[
        {
            "category":"Professional",
            "subcategory":"Business Services",
            "type":"Services"
        }
    ],
    "sg:phone":"+1 604 433 1911",
    "sg:postcode":"V5H 4C2",
    "sg:province":"BC",
    "sg:tags":[
        "notary"
    ],
    "wof:name":"Rechsteiner, Elisabeth",
    "wof:placetype":"venue"
},
  "geometry": {"coordinates":[-122.991355896,49.2257385254],"type":"Point"}
}