{
  "type": "Feature",
  "properties": {
    "iso:country":"CA",
    "sg:address":"302 Erb St W",
    "sg:city":"Waterloo",
    "sg:classifiers":[
        {
            "category":"Health Services",
            "subcategory":"Nursing And Care Facility",
            "type":"Services"
        }
    ],
    "sg:phone":"+1 519 886 1341",
    "sg:postcode":"N2L 1W3",
    "sg:province":"ON",
    "sg:tags":[
        "home",
        "rest"
    ],
    "wof:name":"Woodland Terrace",
    "wof:placetype":"venue"
},
  "geometry": {"coordinates":[-80.542496,43.456516],"type":"Point"}
}