{
  "type": "Feature",
  "properties": {
    "addr:full":"336 2nd St E Cornwall ON K6H 1Y9",
    "addr:housenumber":"336",
    "addr:postcode":"k6h 1y9",
    "addr:street":"2Nd St E",
    "iso:country":"CA",
    "sg:address":"336 2nd St E",
    "sg:city":"Cornwall",
    "sg:classifiers":[
        {
            "category":"Health Services",
            "subcategory":"Doctor",
            "type":"Services"
        }
    ],
    "sg:phone":"+1 613 932 1740",
    "sg:postcode":"K6H 1Y9",
    "sg:province":"ON",
    "sg:tags":[
        "dentist"
    ],
    "wof:name":"Sidorchuk, John DDS",
    "wof:placetype":"venue"
},
  "geometry": {"coordinates":[-74.72165699999999,45.020119],"type":"Point"}
}