{
  "type": "Feature",
  "properties": {
    "addr:full":"4849 Boul Saint-Jean Pierrefonds QC H9H 2A9",
    "addr:housenumber":"4849",
    "addr:postcode":"h9h 2a9",
    "addr:street":"Boul Saint-Jean",
    "iso:country":"CA",
    "sg:address":"4849 Boul Saint-Jean",
    "sg:city":"Pierrefonds",
    "sg:classifiers":[
        {
            "category":"Personal",
            "subcategory":"Shoe Repair & Shine",
            "type":"Services"
        }
    ],
    "sg:phone":"+1 514 696 4184",
    "sg:postcode":"H9H 2A9",
    "sg:province":"QC",
    "sg:tags":[
        "repairing",
        "boot"
    ],
    "wof:name":"Moneysworth & Best",
    "wof:placetype":"venue"
},
  "geometry": {"coordinates":[-73.850433,45.490108],"type":"Point"}
}