{
  "type": "Feature",
  "properties": {
    "iso:country":"CA",
    "sg:city":"Caesarea",
    "sg:classifiers":[
        {
            "category":"Organizations",
            "subcategory":"Religious Organization",
            "type":"Services"
        }
    ],
    "sg:phone":"+1 905 986 5683",
    "sg:postcode":"L0B 1E0",
    "sg:province":"ON",
    "sg:tags":[
        "church"
    ],
    "wof:name":"Caesarea Christian Fellowship",
    "wof:placetype":"venue"
},
  "geometry": {"coordinates":[-78.8316726685,44.1574363708],"type":"Point"}
}