{
  "type": "Feature",
  "properties": {
    "addr:full":"1575 Wesley Rd Moose Jaw SK S6H 5V2",
    "addr:housenumber":"1575",
    "addr:postcode":"s6h 5v2",
    "addr:street":"Wesley Rd",
    "iso:country":"CA",
    "sg:address":"1575 Wesley Rd",
    "sg:city":"Moose Jaw",
    "sg:classifiers":[
        {
            "category":"Food & Beverages",
            "subcategory":"Specialty",
            "type":"Retail Goods"
        }
    ],
    "sg:phone":"+1 306 693 4890",
    "sg:postcode":"S6H 5V2",
    "sg:province":"SK",
    "sg:tags":[
        "health",
        "diet"
    ],
    "wof:name":"Motta Shaklee Enterprises",
    "wof:placetype":"venue"
},
  "geometry": {"coordinates":[-105.536087036,50.3968849182],"type":"Point"}
}