{
  "type": "Feature",
  "properties": {
    "addr:full":"160 Akerley Blvd Dartmouth NS B3B 1Z5",
    "addr:housenumber":"160",
    "addr:postcode":"b3b 1z5",
    "addr:street":"Akerley Blvd",
    "iso:country":"CA",
    "sg:address":"160 Akerley Blvd",
    "sg:city":"Dartmouth",
    "sg:classifiers":[
        {
            "category":"Manufacturing",
            "subcategory":"Motor Vehicles & Parts",
            "type":"Manufacturing & Wholesale Goods"
        }
    ],
    "sg:phone":"+1 902 468 4343",
    "sg:postcode":"B3B 1Z5",
    "sg:province":"NS",
    "sg:tags":[
        "equipment",
        "canopy",
        "cap",
        "truck",
        "shell"
    ],
    "wof:name":"Action Truck Caps & Access",
    "wof:placetype":"venue"
},
  "geometry": {"coordinates":[-63.5847930908,44.7164764404],"type":"Point"}
}