{
  "type": "Feature",
  "properties": {
    "addr:full":"Sylvan Lake AB T4S 1P9",
    "addr:postcode":"t4s 1p9",
    "iso:country":"CA",
    "sg:city":"Sylvan Lake",
    "sg:classifiers":[
        {
            "category":"Health Services",
            "subcategory":"Doctor",
            "type":"Services"
        }
    ],
    "sg:phone":"+1 403 887 2780",
    "sg:postcode":"T4S 1P9",
    "sg:province":"AB",
    "sg:tags":[
        "dentist"
    ],
    "wof:name":"Sylvan Lake Dental Ctr",
    "wof:placetype":"venue"
},
  "geometry": {"coordinates":[-114.097069,52.309307],"type":"Point"}
}