{
  "type": "Feature",
  "properties": {
    "addr:full":"1001 Rue Lenoir Montreal QC H4C 2Z6",
    "addr:housenumber":"1001",
    "addr:postcode":"h4c 2z6",
    "addr:street":"Rue Lenoir",
    "iso:country":"CA",
    "sg:address":"1001 Rue Lenoir",
    "sg:city":"Montreal",
    "sg:classifiers":[
        {
            "category":"Home & Garden",
            "subcategory":"Furniture",
            "type":"Retail Goods"
        }
    ],
    "sg:phone":"+1 514 932 4823",
    "sg:postcode":"H4C 2Z6",
    "sg:province":"QC",
    "sg:tags":[
        "builder",
        "custom"
    ],
    "wof:name":"Magag Construction Inc",
    "wof:placetype":"venue"
},
  "geometry": {"coordinates":[-73.592552,45.476837],"type":"Point"}
}