{
  "type": "Feature",
  "properties": {
    "addr:full":"545 Rue Fleury E Montreal QC H3L 1G6",
    "addr:housenumber":"545",
    "addr:postcode":"h3l 1g6",
    "addr:street":"Rue Fleury E",
    "iso:country":"CA",
    "sg:address":"545 Rue Fleury E",
    "sg:city":"Montreal",
    "sg:classifiers":[
        {
            "category":"Government",
            "subcategory":"Office",
            "type":"Public Place"
        }
    ],
    "sg:phone":"+1 514 872 6742",
    "sg:postcode":"H3L 1G6",
    "sg:province":"QC",
    "sg:tags":[
        "village"
    ],
    "wof:name":"Montreal Acces",
    "wof:placetype":"venue"
},
  "geometry": {"coordinates":[-73.6620788574,45.5533256531],"type":"Point"}
}