{
  "type": "Feature",
  "properties": {
    "addr:full":"5615 50 Ave Bonnyville AB T9N 2L1",
    "addr:housenumber":"5615",
    "addr:postcode":"t9n 2l1",
    "addr:street":"50 Ave",
    "iso:country":"CA",
    "sg:address":"5615 50 Ave",
    "sg:city":"Bonnyville",
    "sg:classifiers":[
        {
            "category":"Mining & Drilling",
            "type":"Manufacturing & Wholesale Goods"
        }
    ],
    "sg:phone":"+1 780 573 1777",
    "sg:postcode":"T9N 2L1",
    "sg:province":"AB",
    "sg:tags":[
        "field",
        "oil"
    ],
    "wof:name":"Natco Canada Ltd",
    "wof:placetype":"venue"
},
  "geometry": {"coordinates":[-110.761268616,54.2685089111],"type":"Point"}
}