{
  "type": "Feature",
  "properties": {
    "iso:country":"CA",
    "sg:address":"3312 Ch DE LA Cote-DE-Liesse",
    "sg:city":"Mont-Royal",
    "sg:classifiers":[
        {
            "category":"Building & Trades",
            "subcategory":"Construction",
            "type":"Services"
        }
    ],
    "sg:phone":"+1 514 731 3369",
    "sg:postcode":"H4N 2P4",
    "sg:province":"QC",
    "sg:tags":[
        "general",
        "contractor"
    ],
    "wof:name":"Renovation Zora",
    "wof:placetype":"venue"
},
  "geometry": {"coordinates":[-73.658806,45.513386],"type":"Point"}
}