{
  "type": "Feature",
  "properties": {
    "addr:full":"Surrey BC V3W 1J8",
    "addr:postcode":"v3w 1j8",
    "iso:country":"CA",
    "sg:city":"Surrey",
    "sg:classifiers":[
        {
            "category":"Professional",
            "type":"Services"
        }
    ],
    "sg:phone":"+1 604 594 6411",
    "sg:postcode":"V3W 1J8",
    "sg:province":"BC",
    "sg:tags":[
        "picture",
        "frame",
        "establishment"
    ],
    "wof:name":"Creative Corner Gallery Frame",
    "wof:placetype":"venue"
},
  "geometry": {"coordinates":[-122.856750488,49.1409606934],"type":"Point"}
}