{
  "type": "Feature",
  "properties": {
    "iso:country":"CA",
    "sg:address":"1914 Boul Edouard",
    "sg:city":"Saint-Hubert",
    "sg:classifiers":[
        {
            "category":"Building & Trades",
            "subcategory":"Construction",
            "type":"Services"
        }
    ],
    "sg:phone":"+1 450 671 5754",
    "sg:postcode":"J4T 1Z4",
    "sg:province":"QC",
    "sg:tags":[
        "repairing",
        "plaster",
        "remodeling",
        "product",
        "contractor"
    ],
    "wof:name":"Domaine D'Art & DE Sculpture",
    "wof:placetype":"venue"
},
  "geometry": {"coordinates":[-73.476692,45.498772],"type":"Point"}
}