{
  "type": "Feature",
  "properties": {
    "addr:full":"5302 56 St Barrhead AB T7N 1C3",
    "addr:housenumber":"5302",
    "addr:postcode":"t7n 1c3",
    "addr:street":"56 St",
    "iso:country":"CA",
    "sg:address":"5302 56 St",
    "sg:city":"Barrhead",
    "sg:classifiers":[
        {
            "category":"Manufacturing",
            "subcategory":"Metals",
            "type":"Manufacturing & Wholesale Goods"
        }
    ],
    "sg:phone":"+1 780 674 4102",
    "sg:postcode":"T7N 1C3",
    "sg:province":"AB",
    "sg:tags":[
        "steel"
    ],
    "wof:name":"Whistle Welding Ltd",
    "wof:placetype":"venue"
},
  "geometry": {"coordinates":[-114.41295599999999,54.123314],"type":"Point"}
}