{
  "type": "Feature",
  "properties": {
    "iso:country":"CA",
    "sg:address":"17103 James Mckevitt Rd SW",
    "sg:city":"Calgary",
    "sg:classifiers":[
        {
            "category":"Restaurant",
            "type":"Food & Drink"
        }
    ],
    "sg:phone":"+1 403 254 4410",
    "sg:postcode":"T2Y 3Y4",
    "sg:province":"AB",
    "sg:tags":[
        "pizza"
    ],
    "wof:name":"Tom's House of Pizza",
    "wof:placetype":"venue"
},
  "geometry": {"coordinates":[-114.0936203,50.8968467712],"type":"Point"}
}