{
  "type": "Feature",
  "properties": {
    "addr:full":"37 Holmes Hill Rd Hantsport NS B0P 1P0",
    "addr:housenumber":"37",
    "addr:postcode":"b0p 1p0",
    "addr:street":"Holmes Hill Rd",
    "iso:country":"CA",
    "sg:address":"37 Holmes Hill Rd",
    "sg:city":"Hantsport",
    "sg:classifiers":[
        {
            "category":"Wholesale",
            "subcategory":"Machinery & Supplies",
            "type":"Manufacturing & Wholesale Goods"
        }
    ],
    "sg:phone":"+1 902 684 9118",
    "sg:postcode":"B0P 1P0",
    "sg:province":"NS",
    "sg:tags":[
        "sharpening",
        "industrial",
        "equipment"
    ],
    "wof:name":"Sears Abrasives Ltd",
    "wof:placetype":"venue"
},
  "geometry": {"coordinates":[-64.183891,45.064922],"type":"Point"}
}