{
  "type": "Feature",
  "properties": {
    "iso:country":"CA",
    "sg:city":"Blainville",
    "sg:classifiers":[
        {
            "category":"Retail",
            "subcategory":"Laundry & Dry Cleaning",
            "type":"Services"
        }
    ],
    "sg:phone":"+1 450 437 3377",
    "sg:postcode":"J7C 2P2",
    "sg:province":"QC",
    "sg:tags":[
        "cleaners"
    ],
    "wof:name":"Nettoyeur Avantage",
    "wof:placetype":"venue"
},
  "geometry": {"coordinates":[-73.90119934080001,45.6873397827],"type":"Point"}
}