{
  "type": "Feature",
  "properties": {
    "addr:full":"1195 Alder St Telkwa BC V0J 2X0",
    "addr:housenumber":"1195",
    "addr:postcode":"v0j 2x0",
    "addr:street":"Alder St",
    "iso:country":"CA",
    "sg:address":"1195 Alder St",
    "sg:city":"Telkwa",
    "sg:classifiers":[
        {
            "category":"Wholesale",
            "subcategory":"Hardware",
            "type":"Manufacturing & Wholesale Goods"
        }
    ],
    "sg:phone":"+1 250 846 5053",
    "sg:postcode":"V0J 2X0",
    "sg:province":"BC",
    "sg:tags":[
        "dust",
        "collecting",
        "system",
        "blower"
    ],
    "wof:name":"Skeena Blower & Sheet Metal",
    "wof:placetype":"venue"
},
  "geometry": {"coordinates":[-127.052628,54.693371],"type":"Point"}
}