{
  "type": "Feature",
  "properties": {
    "addr:full":"Chertsey QC J0K 3K0",
    "addr:postcode":"j0k 3k0",
    "iso:country":"CA",
    "sg:city":"Chertsey",
    "sg:classifiers":[
        {
            "category":"Social Services",
            "subcategory":"Child Care",
            "type":"Services"
        }
    ],
    "sg:phone":"+1 450 882 2020",
    "sg:postcode":"J0K 3K0",
    "sg:province":"QC",
    "wof:name":"Centre DE LA Petite Enfance",
    "wof:placetype":"venue"
},
  "geometry": {"coordinates":[-73.89222717289999,46.0730705261],"type":"Point"}
}