{
  "type": "Feature",
  "properties": {
    "addr:full":"1274 Mckenzie Rd Port Elgin ON N0H 2C0",
    "addr:housenumber":"1274",
    "addr:postcode":"n0h 2c0",
    "addr:street":"Mckenzie Rd",
    "iso:country":"CA",
    "sg:address":"1274 Mckenzie Rd",
    "sg:city":"Port Elgin",
    "sg:phone":"+1 519 832 2612",
    "sg:postcode":"N0H 2C0",
    "sg:province":"ON",
    "sg:tags":[
        "oil"
    ],
    "wof:name":"Dunlop Brothers Fuel Oil",
    "wof:placetype":"venue"
},
  "geometry": {"coordinates":[-81.3745269775,44.4518241882],"type":"Point"}
}