{
  "type": "Feature",
  "properties": {
    "iso:country":"CA",
    "sg:address":"201 Idylwyld Dr S",
    "sg:city":"Saskatoon",
    "sg:classifiers":[
        {
            "category":"Personal",
            "subcategory":"Beauty Salon",
            "type":"Services"
        }
    ],
    "sg:phone":"+1 306 652 3990",
    "sg:postcode":"S7M 1L6",
    "sg:province":"SK",
    "wof:name":"Kazeema Hair Designs",
    "wof:placetype":"venue"
},
  "geometry": {"coordinates":[-106.670455933,52.1276359558],"type":"Point"}
}