{
  "type": "Feature",
  "properties": {
    "addr:full":"210 4th Ave NW Roblin MB R0L 1P0",
    "addr:housenumber":"210",
    "addr:postcode":"roblin;r0l 1p0",
    "addr:street":"4Th Ave Nw",
    "iso:country":"CA",
    "sg:address":"210 4th Ave NW",
    "sg:city":"Roblin",
    "sg:classifiers":[
        {
            "category":"Professional",
            "subcategory":"Computer Services",
            "type":"Services"
        }
    ],
    "sg:phone":"+1 204 937 8979",
    "sg:postcode":"R0L 1P0",
    "sg:province":"MB",
    "sg:tags":[
        "repair",
        "internet"
    ],
    "wof:name":"Computer Solutions",
    "wof:placetype":"venue"
},
  "geometry": {"coordinates":[-101.35763549799999,51.22996521],"type":"Point"}
}