{
  "type": "Feature",
  "properties": {
    "addr:full":"9500 Boul Saint-Laurent Montreal QC H2N 1N3",
    "addr:housenumber":"9500",
    "addr:postcode":"h2n 1n3",
    "addr:street":"Boul Saint-Laurent",
    "iso:country":"CA",
    "sg:address":"9500 Boul Saint-Laurent",
    "sg:city":"Montreal",
    "sg:classifiers":[
        {
            "category":"Real Estate",
            "subcategory":"Real Estate Operator",
            "type":"Services"
        }
    ],
    "sg:phone":"+1 514 387 6409",
    "sg:postcode":"H2N 1N3",
    "sg:province":"QC",
    "sg:tags":[
        "building",
        "parks"
    ],
    "wof:name":"9500 Building Inc",
    "wof:placetype":"venue"
},
  "geometry": {"coordinates":[-73.654366,45.54525],"type":"Point"}
}