{
  "type": "Feature",
  "properties": {
    "iso:country":"CA",
    "sg:address":"2207 Rue Royale",
    "sg:city":"Trois-Rivieres",
    "sg:classifiers":[
        {
            "category":"Freight",
            "type":"Transportation"
        }
    ],
    "sg:phone":"+1 819 374 6094",
    "sg:postcode":"G9A 4L3",
    "sg:province":"QC",
    "sg:tags":[
        "mover",
        "trucking"
    ],
    "wof:name":"Leo Valois & Fils Inc",
    "wof:placetype":"venue"
},
  "geometry": {"coordinates":[-72.54806518549999,46.3356018066],"type":"Point"}
}