{
  "type": "Feature",
  "properties": {
    "iso:country":"CA",
    "sg:address":"1811 91st St",
    "sg:city":"North Battleford",
    "sg:classifiers":[
        {
            "category":"Professional",
            "subcategory":"Secretarial Services",
            "type":"Services"
        }
    ],
    "sg:phone":"+1 306 445 7450",
    "sg:postcode":"S9A 0A6",
    "sg:province":"SK",
    "sg:tags":[
        "convention",
        "court",
        "reporter"
    ],
    "wof:name":"Logan Reporting Svc",
    "wof:placetype":"venue"
},
  "geometry": {"coordinates":[-108.31241607699999,52.784236908],"type":"Point"}
}