{
  "type": "Feature",
  "properties": {
    "addr:full":"620 Richmond St W Toronto ON M5V 1Y9",
    "addr:housenumber":"620",
    "addr:postcode":"m5v 1y9",
    "addr:street":"Richmond St W",
    "iso:country":"CA",
    "sg:address":"620 Richmond St W",
    "sg:city":"Toronto",
    "sg:classifiers":[
        {
            "category":"Professional",
            "subcategory":"Business Services",
            "type":"Services"
        }
    ],
    "sg:phone":"+1 416 703 1255",
    "sg:postcode":"M5V 1Y9",
    "sg:province":"ON",
    "sg:tags":[
        "antique",
        "appraiser"
    ],
    "wof:name":"Artia Russian Fine Art Inc",
    "wof:placetype":"venue"
},
  "geometry": {"coordinates":[-79.40320587159999,43.6467018127],"type":"Point"}
}