{
  "type": "Feature",
  "properties": {
    "addr:full":"182 Mitton St S Sarnia ON N7T 3C9",
    "addr:housenumber":"182",
    "addr:postcode":"n7t 3c9",
    "addr:street":"Mitton St S",
    "iso:country":"CA",
    "sg:address":"182 Mitton St S",
    "sg:city":"Sarnia",
    "sg:classifiers":[
        {
            "category":"Retail",
            "subcategory":"Animal Services",
            "type":"Services"
        }
    ],
    "sg:phone":"+1 519 337 1297",
    "sg:postcode":"N7T 3C9",
    "sg:province":"ON",
    "sg:tags":[
        "pet",
        "grooming",
        "washing"
    ],
    "wof:name":"Affordable Pet Grooming",
    "wof:placetype":"venue"
},
  "geometry": {"coordinates":[-82.398239,42.967815],"type":"Point"}
}