{
  "type": "Feature",
  "properties": {
    "addr:full":"3990 Portage Ave Winnipeg MB R3K 1W3",
    "addr:housenumber":"3990",
    "addr:postcode":"r3k 1w3",
    "addr:street":"Portage Ave",
    "iso:country":"CA",
    "sg:address":"3990 Portage Ave",
    "sg:city":"Winnipeg",
    "sg:classifiers":[
        {
            "category":"Real Estate",
            "subcategory":"Developer",
            "type":"Services"
        }
    ],
    "sg:phone":"+1 204 888 7557",
    "sg:postcode":"R3K 1W3",
    "sg:province":"MB",
    "sg:tags":[
        "cemetery"
    ],
    "wof:name":"Assumption Cemetery-Mausoleum",
    "wof:placetype":"venue"
},
  "geometry": {"coordinates":[-97.332222,49.87957],"type":"Point"}
}