{
  "type": "Feature",
  "properties": {
    "addr:full":"White Rock BC V4B 2L1",
    "addr:postcode":"v4b 2l1",
    "iso:country":"CA",
    "sg:city":"White Rock",
    "sg:classifiers":[
        {
            "category":"Personal",
            "type":"Services"
        }
    ],
    "sg:phone":"+1 604 541 3386",
    "sg:postcode":"V4B 2L1",
    "sg:province":"BC",
    "sg:tags":[
        "care",
        "shopping",
        "center",
        "day"
    ],
    "wof:name":"Home Instead Senior Care",
    "wof:placetype":"venue"
},
  "geometry": {"coordinates":[-122.799957275,49.0273704529],"type":"Point"}
}