{
  "type": "Feature",
  "properties": {
    "iso:country":"CA",
    "sg:city":"Victoria",
    "sg:classifiers":[
        {
            "category":"Shopping",
            "subcategory":"Discount & Variety Stores",
            "type":"Retail Goods"
        }
    ],
    "sg:phone":"+1 250 370 0992",
    "sg:postcode":"V8R 1C9",
    "sg:province":"BC",
    "wof:name":"Oak Bay Dollar Plus Store",
    "wof:placetype":"venue"
},
  "geometry": {"coordinates":[-123.324150085,48.4265937805],"type":"Point"}
}