{
  "type": "Feature",
  "properties": {
    "addr:full":"1067 Spadina Rd Toronto ON M5N 2M7",
    "addr:housenumber":"1067",
    "addr:postcode":"m5n 2m7",
    "addr:street":"Spadina Rd",
    "iso:country":"CA",
    "sg:address":"1067 Spadina Rd",
    "sg:city":"Toronto",
    "sg:classifiers":[
        {
            "category":"Travel",
            "subcategory":"Travel Agent",
            "type":"Entertainment"
        }
    ],
    "sg:phone":"+1 416 489 3355",
    "sg:postcode":"M5N 2M7",
    "sg:province":"ON",
    "sg:tags":[
        "information",
        "tourist"
    ],
    "wof:name":"Travel Transitions Inc",
    "wof:placetype":"venue"
},
  "geometry": {"coordinates":[-79.418915,43.704983],"type":"Point"}
}