{
  "type": "Feature",
  "properties": {
    "addr:full":"389 Main E St Picton ON K0K 2T0",
    "addr:housenumber":"389",
    "addr:postcode":"k0k 2t0",
    "addr:street":"Main E St",
    "iso:country":"CA",
    "sg:address":"389 Main E St",
    "sg:city":"Picton",
    "sg:classifiers":[
        {
            "category":"Health Services",
            "subcategory":"Doctor",
            "type":"Services"
        }
    ],
    "sg:phone":"+1 613 476 3103",
    "sg:postcode":"K0K 2T0",
    "sg:province":"ON",
    "sg:tags":[
        "physician",
        "surgeon"
    ],
    "wof:name":"Koval, D C MD",
    "wof:placetype":"venue"
},
  "geometry": {"coordinates":[-77.138977,44.009224],"type":"Point"}
}