{
  "type": "Feature",
  "properties": {
    "addr:full":"3826 South Oyster School Rd Ladysmith BC V9G 1Z5",
    "addr:housenumber":"3826",
    "addr:postcode":"v9g 1z5",
    "addr:street":"South Oyster School Rd",
    "iso:country":"CA",
    "sg:address":"3826 South Oyster School Rd",
    "sg:city":"Ladysmith",
    "sg:classifiers":[
        {
            "category":"Manufacturing",
            "subcategory":"Lumber",
            "type":"Manufacturing & Wholesale Goods"
        }
    ],
    "sg:phone":"+1 250 245 8020",
    "sg:postcode":"V9G 1Z5",
    "sg:province":"BC",
    "sg:tags":[
        "company",
        "logging"
    ],
    "wof:name":"Carter Holdings Ltd",
    "wof:placetype":"venue"
},
  "geometry": {"coordinates":[-123.82054100000001,48.997356],"type":"Point"}
}