{
  "type": "Feature",
  "properties": {
    "iso:country":"CA",
    "sg:city":"Montreal",
    "sg:classifiers":[
        {
            "category":"Health Services",
            "subcategory":"Health Practitioner",
            "type":"Services"
        }
    ],
    "sg:phone":"+1 514 274 0012",
    "sg:postcode":"H2V 4H1",
    "sg:province":"QC",
    "sg:tags":[
        "psychologist"
    ],
    "wof:name":"Dinard, Renee PhD",
    "wof:placetype":"venue"
},
  "geometry": {"coordinates":[-73.64715576170001,45.5361213684],"type":"Point"}
}