{
  "type": "Feature",
  "properties": {
    "addr:full":"Kirkfield ON K0M 2B0",
    "addr:postcode":"k0m 2b0",
    "addr:street":"Kirkfield",
    "iso:country":"CA",
    "sg:city":"Kirkfield",
    "sg:classifiers":[
        {
            "category":"Health Services",
            "subcategory":"Chiropractor",
            "type":"Services"
        }
    ],
    "sg:phone":"+1 705 454 2784",
    "sg:postcode":"K0M 2B0",
    "sg:province":"ON",
    "wof:name":"White, Peter DC",
    "wof:placetype":"venue"
},
  "geometry": {"coordinates":[-78.927795,44.737858],"type":"Point"}
}