{
  "type": "Feature",
  "properties": {
    "addr:full":"12 Davis Dr Smiths Falls ON K7A 5G7",
    "addr:housenumber":"12",
    "addr:postcode":"k7a 5g7",
    "addr:street":"Davis Dr",
    "iso:country":"CA",
    "sg:address":"12 Davis Dr",
    "sg:city":"Smiths Falls",
    "sg:classifiers":[
        {
            "category":"Building & Trades",
            "subcategory":"Construction",
            "type":"Services"
        }
    ],
    "sg:phone":"+1 613 283 1631",
    "sg:postcode":"K7A 5G7",
    "sg:province":"ON",
    "sg:tags":[
        "dry wall",
        "contractor"
    ],
    "wof:name":"Rene Larochelle Dry Wall",
    "wof:placetype":"venue"
},
  "geometry": {"coordinates":[-76.00994900000001,44.887486],"type":"Point"}
}