{
  "type": "Feature",
  "properties": {
    "addr:full":"East York ON M4B 2S6",
    "addr:postcode":"m4b 2s6",
    "iso:country":"CA",
    "sg:city":"East York",
    "sg:classifiers":[
        {
            "category":"Retail",
            "subcategory":"Laundry & Dry Cleaning",
            "type":"Services"
        }
    ],
    "sg:phone":"+1 416 285 0174",
    "sg:postcode":"M4B 2S6",
    "sg:province":"ON",
    "sg:tags":[
        "cleaners"
    ],
    "wof:name":"A M Dry Cleaners",
    "wof:placetype":"venue"
},
  "geometry": {"coordinates":[-79.336693,43.699051],"type":"Point"}
}