{
  "type": "Feature",
  "properties": {
    "addr:full":"11 Cairns Dr Markham ON L3P 7M8",
    "addr:housenumber":"11",
    "addr:postcode":"l3p 7m8",
    "addr:street":"Cairns Dr",
    "iso:country":"CA",
    "sg:address":"11 Cairns Dr",
    "sg:city":"Markham",
    "sg:classifiers":[
        {
            "category":"Education",
            "subcategory":"School",
            "type":"Public Place"
        }
    ],
    "sg:phone":"+1 905 471 6512",
    "sg:postcode":"L3P 7M8",
    "sg:province":"ON",
    "wof:name":"Ramer Woods Public School",
    "wof:placetype":"venue"
},
  "geometry": {"coordinates":[-79.278137207,43.8798904419],"type":"Point"}
}