{
  "type": "Feature",
  "properties": {
    "addr:full":"19 Rue Saint-Christophe Bellefeuille QC J7Y 3N5",
    "addr:housenumber":"19",
    "addr:postcode":"j7y 3n5",
    "addr:street":"Rue Saint-Christophe Bellefeuille",
    "iso:country":"CA",
    "sg:address":"19 Rue Saint-Christophe",
    "sg:city":"Bellefeuille",
    "sg:classifiers":[
        {
            "category":"Wholesale",
            "subcategory":"Hardware",
            "type":"Manufacturing & Wholesale Goods"
        }
    ],
    "sg:phone":"+1 450 438 8319",
    "sg:postcode":"J7Y 3N5",
    "sg:province":"QC",
    "sg:tags":[
        "refrigerating"
    ],
    "wof:name":"Services DE Refrigeration Inc",
    "wof:placetype":"venue"
},
  "geometry": {"coordinates":[-74.08055899999999,45.785519],"type":"Point"}
}