{
  "type": "Feature",
  "properties": {
    "iso:country":"CA",
    "sg:address":"1152 Rue King O",
    "sg:city":"Sherbrooke",
    "sg:classifiers":[
        {
            "category":"Professional",
            "subcategory":"Business Services",
            "type":"Services"
        }
    ],
    "sg:phone":"+1 819 566 1060",
    "sg:postcode":"J1H 1S2",
    "sg:province":"QC",
    "sg:tags":[
        "notary"
    ],
    "wof:name":"Le Blanc, Suzanne",
    "wof:placetype":"venue"
},
  "geometry": {"coordinates":[-71.86301400000001,45.408161],"type":"Point"}
}