{
  "type": "Feature",
  "properties": {
    "addr:full":"40 Caronport Cres North York ON M3A 1H1",
    "addr:housenumber":"40",
    "addr:postcode":"m3a 1h1",
    "addr:street":"Caronport Cres",
    "iso:country":"CA",
    "sg:address":"40 Caronport Cres",
    "sg:city":"North York",
    "sg:classifiers":[
        {
            "category":"Building & Trades",
            "subcategory":"Construction",
            "type":"Services"
        }
    ],
    "sg:phone":"+1 416 444 1899",
    "sg:postcode":"M3A 1H1",
    "sg:province":"ON",
    "sg:tags":[
        "roofing",
        "contractor"
    ],
    "wof:name":"Don Mills Roofing",
    "wof:placetype":"venue"
},
  "geometry": {"coordinates":[-79.32068599999999,43.743946],"type":"Point"}
}