{
  "type": "Feature",
  "properties": {
    "addr:full":"2470 Apollo Dr Nanoose Bay BC V9P 9J9",
    "addr:housenumber":"2470",
    "addr:postcode":"v9p 9j9",
    "addr:street":"Apollo Dr",
    "iso:country":"CA",
    "sg:address":"2470 Apollo Dr",
    "sg:city":"Nanoose Bay",
    "sg:classifiers":[
        {
            "category":"Health Services",
            "subcategory":"Doctor",
            "type":"Services"
        }
    ],
    "sg:phone":"+1 250 468 5939",
    "sg:postcode":"V9P 9J9",
    "sg:province":"BC",
    "sg:tags":[
        "physician",
        "surgeon"
    ],
    "wof:name":"Nanoose Bay Medical Ctr",
    "wof:placetype":"venue"
},
  "geometry": {"coordinates":[-124.193192,49.272247],"type":"Point"}
}