{
  "type": "Feature",
  "properties": {
    "addr:full":"Winnipeg MB R3B 0R3",
    "addr:postcode":"r3b 0r3",
    "iso:country":"CA",
    "sg:city":"Winnipeg",
    "sg:classifiers":[
        {
            "category":"Education",
            "subcategory":"Vocational School",
            "type":"Public Place"
        }
    ],
    "sg:phone":"+1 204 982 0100",
    "sg:postcode":"R3B 0R3",
    "sg:province":"MB",
    "sg:tags":[
        "training",
        "computer"
    ],
    "wof:name":"Online Business Systems",
    "wof:placetype":"venue"
},
  "geometry": {"coordinates":[-97.13485,49.897278],"type":"Point"}
}