{
  "type": "Feature",
  "properties": {
    "addr:full":"1156 College St Toronto ON M6H 1B6",
    "addr:housenumber":"1156",
    "addr:postcode":"m6h 1b6",
    "addr:street":"College St",
    "iso:country":"CA",
    "sg:address":"1156 College St",
    "sg:city":"Toronto",
    "sg:classifiers":[
        {
            "category":"Restaurant",
            "type":"Food & Drink"
        }
    ],
    "sg:phone":"+1 416 516 3891",
    "sg:postcode":"M6H 1B6",
    "sg:province":"ON",
    "wof:name":"Linh Restaurant",
    "wof:placetype":"venue"
},
  "geometry": {"coordinates":[-79.433746,43.652443],"type":"Point"}
}