{
  "type": "Feature",
  "properties": {
    "addr:full":"Thetford Mines QC G6G 2W2",
    "addr:postcode":"g6g 2w2",
    "iso:country":"CA",
    "sg:city":"Thetford Mines",
    "sg:classifiers":[
        {
            "category":"Retail",
            "subcategory":"Repair Shop",
            "type":"Services"
        }
    ],
    "sg:phone":"+1 418 338 9247",
    "sg:postcode":"G6G 2W2",
    "sg:province":"QC",
    "sg:tags":[
        "builder",
        "stair",
        "welding"
    ],
    "wof:name":"Soudure Generale L Labranche",
    "wof:placetype":"venue"
},
  "geometry": {"coordinates":[-71.188148,46.159996],"type":"Point"}
}