{
  "type": "Feature",
  "properties": {
    "addr:full":"Richmond BC V6X 3Z6",
    "addr:postcode":"v6x 3z6",
    "iso:country":"CA",
    "sg:city":"Richmond",
    "sg:classifiers":[
        {
            "category":"Wholesale",
            "subcategory":"Machinery & Supplies",
            "type":"Manufacturing & Wholesale Goods"
        }
    ],
    "sg:phone":"+1 604 273 6122",
    "sg:postcode":"V6X 3Z6",
    "sg:province":"BC",
    "sg:tags":[
        "salon",
        "beauty"
    ],
    "wof:name":"Appas Professional Beauty Prod",
    "wof:placetype":"venue"
},
  "geometry": {"coordinates":[-123.103088379,49.1777992249],"type":"Point"}
}