{
  "type": "Feature",
  "properties": {
    "addr:full":"440 King St #36 Fredericton NB E3B 5H8",
    "addr:housenumber":"440",
    "addr:postcode":"e3b 5h8",
    "addr:street":"King St # 36",
    "iso:country":"CA",
    "sg:address":"440 King St #36",
    "sg:city":"Fredericton",
    "sg:classifiers":[
        {
            "category":"Shopping",
            "subcategory":"Florist",
            "type":"Retail Goods"
        }
    ],
    "sg:phone":"+1 506 458 9969",
    "sg:postcode":"E3B 5H8",
    "sg:province":"NB",
    "wof:name":"Thorne's Flowers Ltd",
    "wof:placetype":"venue"
},
  "geometry": {"coordinates":[-66.643669,45.961735],"type":"Point"}
}