{
  "type": "Feature",
  "properties": {
    "addr:full":"357 Water St St Andrews NB E5B 2R2",
    "addr:housenumber":"357",
    "addr:postcode":"e5b 2r2",
    "addr:street":"Water St",
    "iso:country":"CA",
    "sg:address":"357 Water St",
    "sg:city":"St Andrews",
    "sg:classifiers":[
        {
            "category":"Professional",
            "subcategory":"Accounting & Tax Preparation",
            "type":"Services"
        }
    ],
    "sg:phone":"+1 506 529 8080",
    "sg:postcode":"E5B 2R2",
    "sg:province":"NB",
    "sg:tags":[
        "accountant"
    ],
    "wof:name":"Johnson, Robert P CA",
    "wof:placetype":"venue"
},
  "geometry": {"coordinates":[-67.04699707029999,45.0708618164],"type":"Point"}
}