{
  "type": "Feature",
  "properties": {
    "addr:full":"Oakbank MB R0E 1J3",
    "addr:postcode":"r0e 1j3",
    "iso:country":"CA",
    "sg:city":"Oakbank",
    "sg:classifiers":[
        {
            "category":"Retail",
            "subcategory":"Auto Repair",
            "type":"Services"
        }
    ],
    "sg:phone":"+1 204 444 5747",
    "sg:postcode":"R0E 1J3",
    "sg:province":"MB",
    "sg:tags":[
        "repairing",
        "automobile"
    ],
    "wof:name":"Best Buy Auto & General Repair",
    "wof:placetype":"venue"
},
  "geometry": {"coordinates":[-96.886803,50.129128],"type":"Point"}
}