{
  "type": "Feature",
  "properties": {
    "addr:full":"450 Av Duluth E Montreal QC H2L 1A5",
    "addr:housenumber":"450",
    "addr:postcode":"h2l 1a5",
    "addr:street":"Av Duluth E",
    "iso:country":"CA",
    "sg:address":"450 Av Duluth E",
    "sg:city":"Montreal",
    "sg:classifiers":[
        {
            "category":"Restaurant",
            "type":"Food & Drink"
        }
    ],
    "sg:phone":"+1 514 842 0969",
    "sg:postcode":"H2L 1A5",
    "sg:province":"QC",
    "wof:name":"Maison Grecque",
    "wof:placetype":"venue"
},
  "geometry": {"coordinates":[-73.57524100000001,45.521381],"type":"Point"}
}