{
  "type": "Feature",
  "properties": {
    "addr:full":"North York ON M3M 2H7",
    "addr:postcode":"m3m 2h7",
    "iso:country":"CA",
    "sg:city":"North York",
    "sg:classifiers":[
        {
            "category":"Personal",
            "subcategory":"Barber",
            "type":"Services"
        }
    ],
    "sg:phone":"+1 416 631 7796",
    "sg:postcode":"M3M 2H7",
    "sg:province":"ON",
    "wof:name":"Tony & Anthony's Barber",
    "wof:placetype":"venue"
},
  "geometry": {"coordinates":[-79.48632000000001,43.744244],"type":"Point"}
}