{
  "type": "Feature",
  "properties": {
    "addr:full":"9518 Yellowhead Hwy Little Fort BC V0E 2C0",
    "addr:housenumber":"9518",
    "addr:postcode":"v0e 2c0",
    "addr:street":"Yellowhead Hwy",
    "iso:country":"CA",
    "sg:address":"9518 Yellowhead Hwy",
    "sg:city":"Little Fort",
    "sg:classifiers":[
        {
            "category":"Home & Garden",
            "subcategory":"Furniture",
            "type":"Retail Goods"
        }
    ],
    "sg:phone":"+1 250 677 4351",
    "sg:postcode":"V0E 2C0",
    "sg:province":"BC",
    "sg:tags":[
        "builder",
        "custom"
    ],
    "wof:name":"Pro Voak Industries",
    "wof:placetype":"venue"
},
  "geometry": {"coordinates":[-120.21006800000001,51.42598],"type":"Point"}
}