{
  "type": "Feature",
  "properties": {
    "addr:full":"254 Av Du Mont-Royal E Montreal QC H2T 1P5",
    "addr:postcode":"h2t 1p5",
    "addr:street":"254 Av Du Mont-Royal E",
    "iso:country":"CA",
    "sg:address":"254 Av Du Mont-Royal E",
    "sg:city":"Montreal",
    "sg:classifiers":[
        {
            "category":"Shopping",
            "subcategory":"Clothing, Apparel, & Fashions",
            "type":"Retail Goods"
        }
    ],
    "sg:phone":"+1 514 844 9435",
    "sg:postcode":"H2T 1P5",
    "sg:province":"QC",
    "sg:tags":[
        "item",
        "boutique"
    ],
    "wof:name":"Scarlett",
    "wof:placetype":"venue"
},
  "geometry": {"coordinates":[-73.5840835571,45.5224685669],"type":"Point"}
}