{
  "type": "Feature",
  "properties": {
    "addr:full":"100 Webster St Kentville NS B4N 1H9",
    "addr:housenumber":"100",
    "addr:postcode":"b4n 1h9",
    "addr:street":"Webster St",
    "iso:country":"CA",
    "sg:address":"100 Webster St",
    "sg:city":"Kentville",
    "sg:classifiers":[
        {
            "category":"Retail",
            "subcategory":"Laundry & Dry Cleaning",
            "type":"Services"
        }
    ],
    "sg:phone":"+1 902 679 3588",
    "sg:postcode":"B4N 1H9",
    "sg:province":"NS",
    "sg:tags":[
        "cleaners"
    ],
    "wof:name":"Vail's Laundry & Cleaners",
    "wof:placetype":"venue"
},
  "geometry": {"coordinates":[-64.49645200000001,45.07832],"type":"Point"}
}