{
  "type": "Feature",
  "properties": {
    "addr:full":"Toronto ON M6C 2E3",
    "addr:postcode":"m6c 2e3",
    "iso:country":"CA",
    "sg:city":"Toronto",
    "sg:classifiers":[
        {
            "category":"Health Services",
            "subcategory":"Doctor",
            "type":"Services"
        }
    ],
    "sg:phone":"+1 416 785 7864",
    "sg:postcode":"M6C 2E3",
    "sg:province":"ON",
    "sg:tags":[
        "clinic"
    ],
    "wof:name":"Forest Hill Aesthetic Svc",
    "wof:placetype":"venue"
},
  "geometry": {"coordinates":[-79.43345600000001,43.699421],"type":"Point"}
}