{
  "type": "Feature",
  "properties": {
    "addr:full":"2172 Rue King O Sherbrooke QC J1J 2E8",
    "addr:housenumber":"2172",
    "addr:postcode":"j1j 2e8",
    "addr:street":"Rue King O",
    "iso:country":"CA",
    "sg:address":"2172 Rue King O",
    "sg:city":"Sherbrooke",
    "sg:classifiers":[
        {
            "category":"Restaurant",
            "type":"Food & Drink"
        }
    ],
    "sg:phone":"+1 819 565 1916",
    "sg:postcode":"J1J 2E8",
    "sg:province":"QC",
    "wof:name":"Restau Soleil En Bouche",
    "wof:placetype":"venue"
},
  "geometry": {"coordinates":[-71.92565917970001,45.3979454041],"type":"Point"}
}