{
  "type": "Feature",
  "properties": {
    "addr:full":"1508 Arlington Ave Saskatoon SK S7H 2Y2",
    "addr:housenumber":"1508",
    "addr:postcode":"s7h 2y2",
    "addr:street":"Arlington Ave",
    "iso:country":"CA",
    "sg:address":"1508 Arlington Ave",
    "sg:city":"Saskatoon",
    "sg:classifiers":[
        {
            "category":"Social Services",
            "subcategory":"Child Care",
            "type":"Services"
        }
    ],
    "sg:phone":"+1 306 668 3149",
    "sg:postcode":"S7H 2Y2",
    "sg:province":"SK",
    "sg:tags":[
        "kindergarten",
        "academic",
        "school"
    ],
    "wof:name":"Mes Amis French Immersion",
    "wof:placetype":"venue"
},
  "geometry": {"coordinates":[-106.60908499999999,52.110237],"type":"Point"}
}