{
  "type": "Feature",
  "properties": {
    "addr:full":"Buckland QC G0R 1G0",
    "addr:postcode":"g0r 1g0",
    "addr:street":"Buckland",
    "iso:country":"CA",
    "sg:city":"Buckland",
    "sg:classifiers":[
        {
            "category":"Government",
            "subcategory":"Office",
            "type":"Public Place"
        }
    ],
    "sg:phone":"+1 418 789 3128",
    "sg:postcode":"G0R 1G0",
    "sg:province":"QC",
    "sg:tags":[
        "village"
    ],
    "wof:name":"Buckland Centre Communautaire",
    "wof:placetype":"venue"
},
  "geometry": {"coordinates":[-70.54406738279999,46.6204605103],"type":"Point"}
}