{
  "type": "Feature",
  "properties": {
    "addr:full":"5136 52 Ave Millet AB T0C 1Z0",
    "addr:housenumber":"5136",
    "addr:postcode":"t0c 1z0",
    "addr:street":"52 Ave",
    "iso:country":"CA",
    "sg:address":"5136 52 Ave",
    "sg:city":"Millet",
    "sg:classifiers":[
        {
            "category":"Building & Trades",
            "subcategory":"Plumbing",
            "type":"Services"
        }
    ],
    "sg:phone":"+1 780 387 5574",
    "sg:postcode":"T0C 1Z0",
    "sg:province":"AB",
    "sg:tags":[
        "contractor"
    ],
    "wof:name":"Millet Plumbing & Gas Fitting",
    "wof:placetype":"venue"
},
  "geometry": {"coordinates":[-113.47816467299999,53.0969772339],"type":"Point"}
}