{
  "type": "Feature",
  "properties": {
    "iso:country":"CA",
    "sg:address":"16 Brighton Rd",
    "sg:city":"Charlottetown",
    "sg:classifiers":[
        {
            "category":"Recreation",
            "type":"Entertainment"
        }
    ],
    "sg:phone":"+1 902 892 8744",
    "sg:postcode":"C1A 1T4",
    "sg:province":"PE",
    "sg:tags":[
        "youth",
        "information",
        "activity",
        "center",
        "organization"
    ],
    "wof:name":"Chances Inc",
    "wof:placetype":"venue"
},
  "geometry": {"coordinates":[-63.1358909607,46.2340927124],"type":"Point"}
}