{
  "type": "Feature",
  "properties": {
    "addr:full":"RR 1 STN Main Cochrane AB T4C 1A1",
    "addr:postcode":"t4c 1a1",
    "addr:street":"Rr 1 Stn Main",
    "iso:country":"CA",
    "sg:address":"RR 1 STN Main",
    "sg:city":"Cochrane",
    "sg:classifiers":[
        {
            "category":"Organizations",
            "subcategory":"Religious Organization",
            "type":"Services"
        }
    ],
    "sg:phone":"+1 403 932 3760",
    "sg:postcode":"T4C 1A1",
    "sg:province":"AB",
    "sg:tags":[
        "church"
    ],
    "wof:name":"Westbrook Community Church",
    "wof:placetype":"venue"
},
  "geometry": {"coordinates":[-114.46800231900001,51.190826416],"type":"Point"}
}