{
  "type": "Feature",
  "properties": {
    "iso:country":"CA",
    "sg:address":"76 Ridley Rd # 10",
    "sg:city":"St Catharines",
    "sg:classifiers":[
        {
            "category":"Building & Trades",
            "subcategory":"Plumbing",
            "type":"Services"
        }
    ],
    "sg:phone":"+1 905 988 9922",
    "sg:postcode":"L2S 3Y8",
    "sg:province":"ON",
    "sg:tags":[
        "air",
        "conditioning",
        "contractor",
        "system",
        "heating"
    ],
    "wof:name":"Commercial Air Svc",
    "wof:placetype":"venue"
},
  "geometry": {"coordinates":[-79.2613449097,43.1488380432],"type":"Point"}
}