{
  "type": "Feature",
  "properties": {
    "addr:full":"Gatineau QC J8T 7X6",
    "addr:postcode":"j8t 7x6",
    "iso:country":"CA",
    "sg:city":"Gatineau",
    "sg:classifiers":[
        {
            "category":"Health Services",
            "subcategory":"Doctor",
            "type":"Services"
        }
    ],
    "sg:phone":"+1 819 243 3221",
    "sg:postcode":"J8T 7X6",
    "sg:province":"QC",
    "sg:tags":[
        "clinic"
    ],
    "wof:name":"Bureau DE Medicine Specialisee",
    "wof:placetype":"venue"
},
  "geometry": {"coordinates":[-75.6070632935,45.4984054565],"type":"Point"}
}