{
  "type": "Feature",
  "properties": {
    "addr:full":"2810 Dehavilland Dr Abbotsford BC V2T 5L2",
    "addr:housenumber":"2810",
    "addr:postcode":"v2t 5l2",
    "addr:street":"Dehavilland Dr",
    "iso:country":"CA",
    "sg:address":"2810 Dehavilland Dr",
    "sg:city":"Abbotsford",
    "sg:classifiers":[
        {
            "category":"Communications",
            "subcategory":"Film & Video Production",
            "type":"Services"
        }
    ],
    "sg:phone":"+1 604 852 1912",
    "sg:postcode":"V2T 5L2",
    "sg:province":"BC",
    "sg:tags":[
        "taping"
    ],
    "wof:name":"Video hi-Lites",
    "wof:placetype":"venue"
},
  "geometry": {"coordinates":[-122.35878,49.052895],"type":"Point"}
}