{
  "type": "Feature",
  "properties": {
    "iso:country":"CA",
    "sg:address":"700 York St",
    "sg:city":"London",
    "sg:classifiers":[
        {
            "category":"Home & Garden",
            "subcategory":"Furniture",
            "type":"Retail Goods"
        }
    ],
    "sg:phone":"+1 519 439 3901",
    "sg:postcode":"N5W 2S8",
    "sg:province":"ON",
    "wof:name":"Corner Furniture Stores",
    "wof:placetype":"venue"
},
  "geometry": {"coordinates":[-81.22733306879999,42.9872894287],"type":"Point"}
}