{
  "type": "Feature",
  "properties": {
    "addr:full":"113 King St N Waterloo ON N2J 2X7",
    "addr:housenumber":"113",
    "addr:postcode":"n2j 2x7",
    "addr:street":"King St N",
    "iso:country":"CA",
    "sg:address":"113 King St N",
    "sg:city":"Waterloo",
    "sg:classifiers":[
        {
            "category":"Home & Garden",
            "subcategory":"Furniture",
            "type":"Retail Goods"
        }
    ],
    "sg:phone":"+1 519 885 2371",
    "sg:postcode":"N2J 2X7",
    "sg:province":"ON",
    "sg:tags":[
        "futon"
    ],
    "wof:name":"Futon Delight",
    "wof:placetype":"venue"
},
  "geometry": {"coordinates":[-80.5237045288,43.4694595337],"type":"Point"}
}