{
  "type": "Feature",
  "properties": {
    "addr:full":"4830 Rue Paquette Notre-Dame-Du-Mont-Carmel QC G0X 3J0",
    "addr:housenumber":"4830",
    "addr:postcode":"g0x 3j0",
    "addr:street":"Rue Paquette",
    "iso:country":"CA",
    "sg:address":"4830 Rue Paquette",
    "sg:city":"Notre-Dame-Du-Mont-Carmel",
    "sg:classifiers":[
        {
            "category":"Freight",
            "type":"Transportation"
        }
    ],
    "sg:phone":"+1 819 537 7278",
    "sg:postcode":"G0X 3J0",
    "sg:province":"QC",
    "sg:tags":[
        "trucking"
    ],
    "wof:name":"J P Transport",
    "wof:placetype":"venue"
},
  "geometry": {"coordinates":[-69.855705,47.44133],"type":"Point"}
}