{
  "type": "Feature",
  "properties": {
    "addr:full":"Carstairs AB T0M 0N0",
    "addr:postcode":"t0m 0n0",
    "iso:country":"CA",
    "sg:city":"Carstairs",
    "sg:classifiers":[
        {
            "category":"Shopping",
            "subcategory":"Clothing, Apparel, & Fashions",
            "type":"Retail Goods"
        }
    ],
    "sg:phone":"+1 403 337 2033",
    "sg:postcode":"T0M 0N0",
    "sg:province":"AB",
    "sg:tags":[
        "western"
    ],
    "wof:name":"Joe Lucas' West World",
    "wof:placetype":"venue"
},
  "geometry": {"coordinates":[-114.095428467,51.5625953674],"type":"Point"}
}