{
  "type": "Feature",
  "properties": {
    "addr:full":"1930 Kingsway Ave Port Coquitlam BC V3C 1S5",
    "addr:housenumber":"1930",
    "addr:postcode":"v3c 1s5",
    "addr:street":"Kingsway Ave",
    "iso:country":"CA",
    "sg:address":"1930 Kingsway Ave",
    "sg:city":"Port Coquitlam",
    "sg:classifiers":[
        {
            "category":"Home & Garden",
            "subcategory":"Building Materials",
            "type":"Retail Goods"
        }
    ],
    "sg:phone":"+1 604 944 9969",
    "sg:postcode":"V3C 1S5",
    "sg:province":"BC",
    "sg:tags":[
        "door"
    ],
    "wof:name":"Stilewood International Mfg",
    "wof:placetype":"venue"
},
  "geometry": {"coordinates":[-122.76995086700001,49.2558441162],"type":"Point"}
}