{
  "type": "Feature",
  "properties": {
    "iso:country":"CA",
    "sg:address":"1734 Rue Dumas",
    "sg:city":"Laval",
    "sg:classifiers":[
        {
            "category":"Building & Trades",
            "subcategory":"Construction",
            "type":"Services"
        }
    ],
    "sg:phone":"+1 450 663 9634",
    "sg:postcode":"H7M 2V3",
    "sg:province":"QC",
    "sg:tags":[
        "acoustical",
        "contractor"
    ],
    "wof:name":"Compagnie D'Accoustique Modele",
    "wof:placetype":"venue"
},
  "geometry": {"coordinates":[-73.7266082764,45.5963058472],"type":"Point"}
}