{
  "type": "Feature",
  "properties": {
    "addr:full":"Mcarthurs Mills ON K0L 2M0",
    "addr:postcode":"k0l 2m0",
    "iso:country":"CA",
    "sg:city":"Mcarthurs Mills",
    "sg:classifiers":[
        {
            "category":"Organizations",
            "subcategory":"Religious Organization",
            "type":"Services"
        }
    ],
    "sg:phone":"+1 613 332 0442",
    "sg:postcode":"K0L 2M0",
    "sg:province":"ON",
    "sg:tags":[
        "church"
    ],
    "wof:name":"Mc Arthur's Mills Christian",
    "wof:placetype":"venue"
},
  "geometry": {"coordinates":[-77.57608,45.126846],"type":"Point"}
}