{
  "type": "Feature",
  "properties": {
    "iso:country":"CA",
    "sg:address":"6299 Quinpool Rd",
    "sg:city":"Halifax",
    "sg:classifiers":[
        {
            "category":"Manufacturing",
            "subcategory":"Metals",
            "type":"Manufacturing & Wholesale Goods"
        }
    ],
    "sg:phone":"+1 902 423 5621",
    "sg:postcode":"B3L 1A4",
    "sg:province":"NS",
    "sg:tags":[
        "jewelry"
    ],
    "wof:name":"Vina's Jewellers",
    "wof:placetype":"venue"
},
  "geometry": {"coordinates":[-63.598473,44.645199],"type":"Point"}
}