{
  "type": "Feature",
  "properties": {
    "iso:country":"CA",
    "sg:address":"PO Box 1036 STN Postal Box Ctr",
    "sg:city":"Red Deer",
    "sg:classifiers":[
        {
            "category":"Shopping",
            "subcategory":"Used Merchandise",
            "type":"Retail Goods"
        }
    ],
    "sg:phone":"+1 403 343 1614",
    "sg:postcode":"T4N 6S5",
    "sg:province":"AB",
    "sg:tags":[
        "antique"
    ],
    "wof:name":"Carswell's Collectibles",
    "wof:placetype":"venue"
},
  "geometry": {"coordinates":[-113.817436218,52.2623023987],"type":"Point"}
}