{
  "type": "Feature",
  "properties": {
    "addr:full":"16 Babb Cres Mount Pearl NL A1N 4K9",
    "addr:housenumber":"16",
    "addr:postcode":"a1n 4k9",
    "addr:street":"Babb Cres",
    "iso:country":"CA",
    "sg:address":"16 Babb Cres",
    "sg:city":"Mount Pearl",
    "sg:classifiers":[
        {
            "category":"Banks & Credit Unions",
            "subcategory":"Financial Services",
            "type":"Services"
        }
    ],
    "sg:phone":"+1 709 745 4450",
    "sg:postcode":"A1N 4K9",
    "sg:province":"NL",
    "sg:tags":[
        "program",
        "scholarship"
    ],
    "wof:name":"Global Educational Markering",
    "wof:placetype":"venue"
},
  "geometry": {"coordinates":[-52.829479,47.515724],"type":"Point"}
}