{
  "type": "Feature",
  "properties": {
    "iso:country":"CA",
    "sg:city":"Surrey",
    "sg:classifiers":[
        {
            "category":"Health Services",
            "subcategory":"Chiropractor",
            "type":"Services"
        }
    ],
    "sg:phone":"+1 604 541 9336",
    "sg:postcode":"V4A 2H9",
    "sg:province":"BC",
    "wof:name":"Peninsula Village Chiropractic",
    "wof:placetype":"venue"
},
  "geometry": {"coordinates":[-122.797424316,49.045791626],"type":"Point"}
}