{
  "type": "Feature",
  "properties": {
    "addr:full":"9600 Rue Meilleur Montreal QC H2N 2E3",
    "addr:housenumber":"9600",
    "addr:postcode":"h2n 2e3",
    "addr:street":"Rue Meilleur",
    "iso:country":"CA",
    "sg:address":"9600 Rue Meilleur",
    "sg:city":"Montreal",
    "sg:classifiers":[
        {
            "category":"Travel",
            "subcategory":"Travel Agent",
            "type":"Entertainment"
        }
    ],
    "sg:phone":"+1 514 382 0990",
    "sg:postcode":"H2N 2E3",
    "sg:province":"QC",
    "sg:tags":[
        "agency",
        "bureau"
    ],
    "wof:name":"Lindberg Travel",
    "wof:placetype":"venue"
},
  "geometry": {"coordinates":[-73.6601409912,45.538860321],"type":"Point"}
}