{
  "type": "Feature",
  "properties": {
    "addr:full":"39 Rue Riley Hudson QC J0P 1H0",
    "addr:housenumber":"39",
    "addr:postcode":"j0p 1h0",
    "addr:street":"Rue Riley",
    "iso:country":"CA",
    "sg:address":"39 Rue Riley",
    "sg:city":"Hudson",
    "sg:classifiers":[
        {
            "category":"Recreation",
            "type":"Entertainment"
        }
    ],
    "sg:phone":"+1 450 458 7645",
    "sg:postcode":"J0P 1H0",
    "sg:province":"QC",
    "sg:tags":[
        "riding",
        "academy"
    ],
    "wof:name":"Equestran Farm",
    "wof:placetype":"venue"
},
  "geometry": {"coordinates":[-74.142563,45.459129],"type":"Point"}
}