{
  "type": "Feature",
  "properties": {
    "iso:country":"CA",
    "sg:address":"804 Main St",
    "sg:city":"Melfort",
    "sg:classifiers":[
        {
            "category":"Retail",
            "subcategory":"Laundry & Dry Cleaning",
            "type":"Services"
        }
    ],
    "sg:phone":"+1 306 752 2871",
    "sg:postcode":"S0E 1A0",
    "sg:province":"SK",
    "sg:tags":[
        "cleaners"
    ],
    "wof:name":"One Hour Cleanitizing",
    "wof:placetype":"venue"
},
  "geometry": {"coordinates":[-104.60894,52.863091],"type":"Point"}
}