{
  "type": "Feature",
  "properties": {
    "addr:full":"48 Jefferson Rd Brampton ON L6S 2N9",
    "addr:housenumber":"48",
    "addr:postcode":"l6s 2n9",
    "addr:street":"Jefferson Rd",
    "iso:country":"CA",
    "sg:address":"48 Jefferson Rd",
    "sg:city":"Brampton",
    "sg:classifiers":[
        {
            "category":"Education",
            "subcategory":"School",
            "type":"Public Place"
        }
    ],
    "sg:phone":"+1 905 791 2818",
    "sg:postcode":"L6S 2N9",
    "sg:province":"ON",
    "wof:name":"Jefferson Public School",
    "wof:placetype":"venue"
},
  "geometry": {"coordinates":[-79.73035400000001,43.737778],"type":"Point"}
}