{
  "type": "Feature",
  "properties": {
    "addr:full":"1240 1E Av Saint-Redempteur QC G6K 1C4",
    "addr:housenumber":"1240",
    "addr:postcode":"g6k 1c4",
    "addr:street":"1E Av Saint-Redempteur",
    "iso:country":"CA",
    "sg:address":"1240 1E Av",
    "sg:city":"Saint-Redempteur",
    "sg:classifiers":[
        {
            "category":"Health Services",
            "subcategory":"Medical Lab",
            "type":"Services"
        }
    ],
    "sg:phone":"+1 418 831 8441",
    "sg:postcode":"G6K 1C4",
    "sg:province":"QC",
    "wof:name":"Belanger, Georges",
    "wof:placetype":"venue"
},
  "geometry": {"coordinates":[-71.28536987299999,46.6992835999],"type":"Point"}
}