{
  "type": "Feature",
  "properties": {
    "addr:full":"43 Rue Principale S Notre-Dame-Du-Nord QC J0Z 3B0",
    "addr:housenumber":"43",
    "addr:postcode":"j0z 3b0",
    "addr:street":"Rue Principale S",
    "iso:country":"CA",
    "sg:address":"43 Rue Principale S",
    "sg:city":"Notre-Dame-Du-Nord",
    "sg:classifiers":[
        {
            "category":"Personal",
            "subcategory":"Beauty Salon",
            "type":"Services"
        }
    ],
    "sg:phone":"+1 819 723 2315",
    "sg:postcode":"J0Z 3B0",
    "sg:province":"QC",
    "wof:name":"Salon Studio 43",
    "wof:placetype":"venue"
},
  "geometry": {"coordinates":[-79.485191,47.590679],"type":"Point"}
}