{
  "type": "Feature",
  "properties": {
    "addr:full":"Toronto ON M6H 3M2",
    "addr:postcode":"m6h 3m2",
    "iso:country":"CA",
    "sg:city":"Toronto",
    "sg:classifiers":[
        {
            "category":"Shopping",
            "subcategory":"Pharmacy",
            "type":"Retail Goods"
        }
    ],
    "sg:phone":"+1 416 651 0052",
    "sg:postcode":"M6H 3M2",
    "sg:province":"ON",
    "wof:name":"Dufferin Drug Mart",
    "wof:placetype":"venue"
},
  "geometry": {"coordinates":[-79.443062,43.677429],"type":"Point"}
}