{
  "type": "Feature",
  "properties": {
    "addr:full":"Pickering ON L1W 3N9",
    "addr:postcode":"l1w 3n9",
    "iso:country":"CA",
    "sg:city":"Pickering",
    "sg:classifiers":[
        {
            "category":"Retail",
            "subcategory":"Auto Repair",
            "type":"Services"
        }
    ],
    "sg:phone":"+1 905 428 8891",
    "sg:postcode":"L1W 3N9",
    "sg:province":"ON",
    "sg:tags":[
        "automobile",
        "top",
        "upholstery"
    ],
    "wof:name":"J R Custom",
    "wof:placetype":"venue"
},
  "geometry": {"coordinates":[-79.0657043457,43.8358001709],"type":"Point"}
}