{
  "type": "Feature",
  "properties": {
    "addr:full":"6085 Uplands Dr Nanaimo BC V9V 1T8",
    "addr:housenumber":"6085",
    "addr:postcode":"v9v 1t8",
    "addr:street":"Uplands Dr",
    "iso:country":"CA",
    "sg:address":"6085 Uplands Dr",
    "sg:city":"Nanaimo",
    "sg:classifiers":[
        {
            "category":"Health Services",
            "subcategory":"Nursing And Care Facility",
            "type":"Services"
        }
    ],
    "sg:phone":"+1 250 729 9524",
    "sg:postcode":"V9V 1T8",
    "sg:province":"BC",
    "sg:tags":[
        "home",
        "retirement",
        "convalescent",
        "community"
    ],
    "wof:name":"Nanaimo Seniors Village",
    "wof:placetype":"venue"
},
  "geometry": {"coordinates":[-124.037078857,49.2365341187],"type":"Point"}
}