{
  "type": "Feature",
  "properties": {
    "iso:country":"CA",
    "sg:address":"1741 Boul DE LA Rive-Sud",
    "sg:city":"Saint-Romuald",
    "sg:classifiers":[
        {
            "category":"Retail",
            "subcategory":"Laundry & Dry Cleaning",
            "type":"Services"
        }
    ],
    "sg:phone":"+1 418 834 0045",
    "sg:postcode":"G6W 5M6",
    "sg:province":"QC",
    "sg:tags":[
        "cleaners"
    ],
    "wof:name":"Nettoyeur Beaurivage Enr",
    "wof:placetype":"venue"
},
  "geometry": {"coordinates":[-71.24652862550001,46.7462043762],"type":"Point"}
}