{
  "type": "Feature",
  "properties": {
    "iso:country":"CA",
    "sg:city":"Etobicoke",
    "sg:classifiers":[
        {
            "category":"Shopping",
            "subcategory":"Clothing, Apparel, & Fashions",
            "type":"Retail Goods"
        }
    ],
    "sg:phone":"+1 416 748 9211",
    "sg:postcode":"M9V 1B4",
    "sg:province":"ON",
    "wof:name":"P & P Fashion Inc",
    "wof:placetype":"venue"
},
  "geometry": {"coordinates":[-79.58191680909999,43.7400894165],"type":"Point"}
}