{
  "type": "Feature",
  "properties": {
    "addr:full":"100 Old Haliburton Rd Pictou NS B0K 1H0",
    "addr:housenumber":"100",
    "addr:postcode":"b0k 1h0",
    "addr:street":"Old Haliburton Rd",
    "iso:country":"CA",
    "sg:address":"100 Old Haliburton Rd",
    "sg:city":"Pictou",
    "sg:classifiers":[
        {
            "category":"Museum",
            "type":"Entertainment"
        }
    ],
    "sg:phone":"+1 902 485 1150",
    "sg:postcode":"B0K 1H0",
    "sg:province":"NS",
    "wof:name":"Mc Culloch House Museum",
    "wof:placetype":"venue"
},
  "geometry": {"coordinates":[-62.7287139893,45.6754264832],"type":"Point"}
}