{
  "type": "Feature",
  "properties": {
    "addr:full":"Range Rd 40 & Hwy 633 Alberta Beach AB T0E 0A0",
    "addr:housenumber":"40",
    "addr:postcode":"t0e 0a0",
    "addr:street":"Range Rd;& Hwy 633",
    "iso:country":"CA",
    "sg:address":"Range Rd 40 & Hwy 633",
    "sg:city":"Alberta Beach",
    "sg:classifiers":[
        {
            "category":"Building & Trades",
            "subcategory":"Construction",
            "type":"Services"
        }
    ],
    "sg:phone":"+1 780 924 2442",
    "sg:postcode":"T0E 0A0",
    "sg:province":"AB",
    "sg:tags":[
        "water",
        "boring",
        "well",
        "drilling",
        "contractor"
    ],
    "wof:name":"Norman Blakeman Drilling Ltd",
    "wof:placetype":"venue"
},
  "geometry": {"coordinates":[-114.443871,53.678749],"type":"Point"}
}