{
  "type": "Feature",
  "properties": {
    "addr:full":"2 Maplewood Crt Beaver Bank NS B4G 1B6",
    "addr:housenumber":"2",
    "addr:postcode":"b4g 1b6",
    "addr:street":"Maplewood Crt",
    "iso:country":"CA",
    "sg:address":"2 Maplewood Crt",
    "sg:city":"Beaver Bank",
    "sg:classifiers":[
        {
            "category":"Building & Trades",
            "subcategory":"Construction",
            "type":"Services"
        }
    ],
    "sg:phone":"+1 902 865 2309",
    "sg:postcode":"B4G 1B6",
    "sg:province":"NS",
    "sg:tags":[
        "excavating",
        "contractor"
    ],
    "wof:name":"Barrett Enterprises Ltd",
    "wof:placetype":"venue"
},
  "geometry": {"coordinates":[-63.680874,44.794449],"type":"Point"}
}