{
  "type": "Feature",
  "properties": {
    "addr:full":"2050 Gottingen St Halifax NS B3K 3A9",
    "addr:housenumber":"2050",
    "addr:postcode":"b3k 3a9",
    "addr:street":"Gottingen St",
    "iso:country":"CA",
    "sg:address":"2050 Gottingen St",
    "sg:city":"Halifax",
    "sg:classifiers":[
        {
            "category":"Professional",
            "subcategory":"Management & Consulting",
            "type":"Services"
        }
    ],
    "sg:phone":"+1 902 425 6800",
    "sg:postcode":"B3K 3A9",
    "sg:province":"NS",
    "sg:tags":[
        "consultant",
        "training",
        "business"
    ],
    "wof:name":"People Development Ltd",
    "wof:placetype":"venue"
},
  "geometry": {"coordinates":[-63.5824813843,44.6512756348],"type":"Point"}
}