{
  "type": "Feature",
  "properties": {
    "addr:full":"106 1st Ave W Vancouver BC V5Y 1A4",
    "addr:housenumber":"106",
    "addr:postcode":"v5y 1a4",
    "addr:street":"1St Ave W",
    "iso:country":"CA",
    "sg:address":"106 1st Ave W",
    "sg:city":"Vancouver",
    "sg:classifiers":[
        {
            "category":"Professional",
            "subcategory":"Management & Consulting",
            "type":"Services"
        }
    ],
    "sg:phone":"+1 604 874 2400",
    "sg:postcode":"V5Y 1A4",
    "sg:province":"BC",
    "sg:tags":[
        "party",
        "planning"
    ],
    "wof:name":"Cliffhanger Indoor Rock Clmbng",
    "wof:placetype":"venue"
},
  "geometry": {"coordinates":[-123.107056,49.270084],"type":"Point"}
}