{
  "type": "Feature",
  "properties": {
    "addr:full":"1595 52 St Delta BC V4M 2Z4",
    "addr:housenumber":"1595",
    "addr:postcode":"v4m 2z4",
    "addr:street":"52 St",
    "iso:country":"CA",
    "sg:address":"1595 52 St",
    "sg:city":"Delta",
    "sg:classifiers":[
        {
            "category":"Sports & Exercise",
            "subcategory":"Golf",
            "type":"Entertainment"
        }
    ],
    "sg:phone":"+1 604 943 3911",
    "sg:postcode":"V4M 2Z4",
    "sg:province":"BC",
    "sg:tags":[
        "course"
    ],
    "wof:name":"Tsawwassen Golf & Country Club",
    "wof:placetype":"venue"
},
  "geometry": {"coordinates":[-123.079971,49.031754],"type":"Point"}
}