{
  "type": "Feature",
  "properties": {
    "addr:full":"631 Rue Lafontaine Riviere-Du-Loup QC G5R 3C5",
    "addr:housenumber":"631",
    "addr:postcode":"g5r 3c5",
    "addr:street":"Rue Lafontaine",
    "iso:country":"CA",
    "sg:address":"631 Rue Lafontaine",
    "sg:city":"Riviere-Du-Loup",
    "sg:classifiers":[
        {
            "category":"Utilities",
            "subcategory":"Fuel Oil & Lpg",
            "type":"Services"
        }
    ],
    "sg:phone":"+1 418 862 4117",
    "sg:postcode":"G5R 3C5",
    "sg:province":"QC",
    "sg:tags":[
        "propane",
        "equipment",
        "gas",
        "heating",
        "system"
    ],
    "wof:name":"Superieur Propane",
    "wof:placetype":"venue"
},
  "geometry": {"coordinates":[-69.526291,47.823845],"type":"Point"}
}