{
  "type": "Feature",
  "properties": {
    "addr:full":"920 Johnson St # 12 Victoria BC V8V 3N4",
    "addr:housenumber":"920;12",
    "addr:postcode":"v8v 3n4",
    "addr:street":"Johnson St #",
    "iso:country":"CA",
    "sg:address":"920 Johnson St # 12",
    "sg:city":"Victoria",
    "sg:classifiers":[
        {
            "category":"Professional",
            "subcategory":"Accounting & Tax Preparation",
            "type":"Services"
        }
    ],
    "sg:phone":"+1 250 881 1350",
    "sg:postcode":"V8V 3N4",
    "sg:province":"BC",
    "sg:tags":[
        "accountant"
    ],
    "wof:name":"Luis H Ambriz Bookkeeping",
    "wof:placetype":"venue"
},
  "geometry": {"coordinates":[-123.358222961,48.4266700745],"type":"Point"}
}