{
  "type": "Feature",
  "properties": {
    "addr:full":"Scarborough ON M1E 4W1",
    "addr:postcode":"m1e 4w1",
    "iso:country":"CA",
    "sg:city":"Scarborough",
    "sg:classifiers":[
        {
            "category":"Restaurant",
            "type":"Food & Drink"
        }
    ],
    "sg:phone":"+1 416 283 4113",
    "sg:postcode":"M1E 4W1",
    "sg:province":"ON",
    "sg:tags":[
        "chicken",
        "dinner"
    ],
    "wof:name":"Chester Fried Chicken",
    "wof:placetype":"venue"
},
  "geometry": {"coordinates":[-79.19722,43.759693],"type":"Point"}
}