{
  "type": "Feature",
  "properties": {
    "addr:full":"2807 116 St NW #A Edmonton AB T6J 4R6",
    "addr:housenumber":"2807",
    "addr:postcode":"t6j 4r6",
    "addr:street":"116 St Nw # A",
    "iso:country":"CA",
    "sg:address":"2807 116 St NW #A",
    "sg:city":"Edmonton",
    "sg:classifiers":[
        {
            "category":"Food & Beverages",
            "subcategory":"Groceries & Convenience Stores",
            "type":"Retail Goods"
        }
    ],
    "sg:phone":"+1 780 437 7732",
    "sg:postcode":"T6J 4R6",
    "sg:province":"AB",
    "wof:name":"Mac's Convenience Stores",
    "wof:placetype":"venue"
},
  "geometry": {"coordinates":[-113.53173099999999,53.460533],"type":"Point"}
}