{
  "type": "Feature",
  "properties": {
    "addr:full":"918 Ash St Sherwood Park AB T8A 2G1",
    "addr:housenumber":"918",
    "addr:postcode":"t8a 2g1",
    "addr:street":"Ash St",
    "iso:country":"CA",
    "sg:address":"918 Ash St",
    "sg:city":"Sherwood Park",
    "sg:classifiers":[
        {
            "category":"Shopping",
            "subcategory":"Computers & Home Electronics",
            "type":"Retail Goods"
        }
    ],
    "sg:phone":"+1 780 449 1234",
    "sg:postcode":"T8A 2G1",
    "sg:province":"AB",
    "sg:tags":[
        "equipment",
        "dealer"
    ],
    "wof:name":"Aerotek Engineering & Dist Ltd",
    "wof:placetype":"venue"
},
  "geometry": {"coordinates":[-113.315247,53.512997],"type":"Point"}
}