{
  "type": "Feature",
  "properties": {
    "iso:country":"CA",
    "sg:address":"6 Manitow Rapids Dr",
    "sg:city":"Emo",
    "sg:classifiers":[
        {
            "category":"Social Services",
            "subcategory":"Child Care",
            "type":"Services"
        }
    ],
    "sg:phone":"+1 807 482 2512",
    "sg:postcode":"P0W 1E0",
    "sg:province":"ON",
    "sg:tags":[
        "government"
    ],
    "wof:name":"Rainy River First Ntns Child",
    "wof:placetype":"venue"
},
  "geometry": {"coordinates":[-93.8388519287,48.6325378418],"type":"Point"}
}