{
  "type": "Feature",
  "properties": {
    "addr:full":"1735 Mackay St Regina SK S4N 6H2",
    "addr:housenumber":"1735",
    "addr:postcode":"s4n 6h2",
    "addr:street":"Mackay St",
    "iso:country":"CA",
    "sg:address":"1735 Mackay St",
    "sg:city":"Regina",
    "sg:classifiers":[
        {
            "category":"Retail",
            "subcategory":"Laundry & Dry Cleaning",
            "type":"Services"
        }
    ],
    "sg:phone":"+1 306 525 4163",
    "sg:postcode":"S4N 6H2",
    "sg:province":"SK",
    "sg:tags":[
        "fire",
        "cleaners",
        "rug",
        "damage",
        "restoration",
        "carpet"
    ],
    "wof:name":"Cameo Cleaning Svc Ltd",
    "wof:placetype":"venue"
},
  "geometry": {"coordinates":[-104.580551,50.451305],"type":"Point"}
}