{
  "type": "Feature",
  "properties": {
    "addr:full":"2020 20th Ave E Owen Sound ON N4K 5N3",
    "addr:housenumber":"2020",
    "addr:postcode":"n4k 5n3",
    "addr:street":"20Th Ave E",
    "iso:country":"CA",
    "sg:address":"2020 20th Ave E",
    "sg:city":"Owen Sound",
    "sg:classifiers":[
        {
            "category":"Wholesale",
            "subcategory":"Machinery & Supplies",
            "type":"Manufacturing & Wholesale Goods"
        }
    ],
    "sg:phone":"+1 519 376 8380",
    "sg:postcode":"N4K 5N3",
    "sg:province":"ON",
    "sg:tags":[
        "pipe",
        "fitting"
    ],
    "wof:name":"Desco Plumbing & Heating Suppl",
    "wof:placetype":"venue"
},
  "geometry": {"coordinates":[-80.899124,44.584091],"type":"Point"}
}