{
  "type": "Feature",
  "properties": {
    "iso:country":"CA",
    "sg:city":"Vancouver",
    "sg:classifiers":[
        {
            "category":"Banks & Credit Unions",
            "subcategory":"Investment Brokerage",
            "type":"Services"
        }
    ],
    "sg:phone":"+1 604 736 7778",
    "sg:postcode":"V6J 1X1",
    "sg:province":"BC",
    "sg:tags":[
        "consultant",
        "planning",
        "financial"
    ],
    "wof:name":"M D Management Ltd",
    "wof:placetype":"venue"
},
  "geometry": {"coordinates":[-123.14253234900001,49.2638168335],"type":"Point"}
}