{
  "type": "Feature",
  "properties": {
    "iso:country":"CA",
    "sg:address":"153 Dufferin St",
    "sg:city":"Toronto",
    "sg:classifiers":[
        {
            "category":"Building & Trades",
            "subcategory":"Landscaping Services",
            "type":"Services"
        }
    ],
    "sg:phone":"+1 416 535 6745",
    "sg:postcode":"M6K 1Y9",
    "sg:province":"ON",
    "sg:tags":[
        "landscape",
        "contractor"
    ],
    "wof:name":"Delta Tech General Landscaping",
    "wof:placetype":"venue"
},
  "geometry": {"coordinates":[-79.42552947999999,43.6346893311],"type":"Point"}
}