{
  "type": "Feature",
  "properties": {
    "addr:full":"901 Sheppard Ave W # 617 North York ON M3H 2T7",
    "addr:housenumber":"901",
    "addr:postcode":"m3h 2t7",
    "addr:street":"Sheppard Ave W # 617",
    "iso:country":"CA",
    "sg:address":"901 Sheppard Ave W # 617",
    "sg:city":"North York",
    "sg:classifiers":[
        {
            "category":"Retail",
            "subcategory":"Auto Repair",
            "type":"Services"
        }
    ],
    "sg:phone":"+1 416 638 0165",
    "sg:postcode":"M3H 2T7",
    "sg:province":"ON",
    "sg:tags":[
        "repairing",
        "automobile",
        "lubrication"
    ],
    "wof:name":"Oil Changers",
    "wof:placetype":"venue"
},
  "geometry": {"coordinates":[-79.45697800000001,43.751457],"type":"Point"}
}