{
  "type": "Feature",
  "properties": {
    "addr:full":"940 Montee Masson Mascouche QC J7K 2L7",
    "addr:housenumber":"940",
    "addr:postcode":"j7k 2l7",
    "addr:street":"Montee Masson",
    "iso:country":"CA",
    "sg:address":"940 Montee Masson",
    "sg:city":"Mascouche",
    "sg:classifiers":[
        {
            "category":"Food & Beverages",
            "subcategory":"Liquor & Beverages",
            "type":"Retail Goods"
        }
    ],
    "sg:phone":"+1 450 966 0981",
    "sg:postcode":"J7K 2L7",
    "sg:province":"QC",
    "sg:tags":[
        "store"
    ],
    "wof:name":"Quebec Societe Des Alcools",
    "wof:placetype":"venue"
},
  "geometry": {"coordinates":[-73.607758,45.745419],"type":"Point"}
}