{
  "type": "Feature",
  "properties": {
    "addr:full":"103 Souris St Melita MB R0M 1L0",
    "addr:housenumber":"103",
    "addr:postcode":"r0m 1l0",
    "addr:street":"Souris St",
    "iso:country":"CA",
    "sg:address":"103 Souris St",
    "sg:city":"Melita",
    "sg:classifiers":[
        {
            "category":"Organizations",
            "subcategory":"Religious Organization",
            "type":"Services"
        }
    ],
    "sg:phone":"+1 204 522 8136",
    "sg:postcode":"R0M 1L0",
    "sg:province":"MB",
    "sg:tags":[
        "church"
    ],
    "wof:name":"United Church",
    "wof:placetype":"venue"
},
  "geometry": {"coordinates":[-100.992302,49.270489],"type":"Point"}
}