{
  "type": "Feature",
  "properties": {
    "addr:full":"Hwy 55 Prince Albert SK S6V 4B1",
    "addr:postcode":"s6v 4b1",
    "addr:street":"Hwy 55",
    "iso:country":"CA",
    "sg:address":"Hwy 55",
    "sg:city":"Prince Albert",
    "sg:classifiers":[
        {
            "category":"Autos & Motor Vehicles",
            "subcategory":"Fuel & Gas Station",
            "type":"Retail Goods"
        }
    ],
    "sg:phone":"+1 306 929 2337",
    "sg:postcode":"S6V 4B1",
    "sg:province":"SK",
    "sg:tags":[
        "oil"
    ],
    "wof:name":"George's Service & Welding",
    "wof:placetype":"venue"
},
  "geometry": {"coordinates":[-105.744789,53.212711],"type":"Point"}
}