{
  "type": "Feature",
  "properties": {
    "addr:full":"221 Ste-Therese Saint-Remi QC J0L 2L0",
    "addr:housenumber":"221",
    "addr:postcode":"j0l 2l0",
    "addr:street":"Ste-Therese Saint-Remi",
    "iso:country":"CA",
    "sg:address":"221 Ste-Therese",
    "sg:city":"Saint-Remi",
    "sg:classifiers":[
        {
            "category":"Government",
            "subcategory":"Office",
            "type":"Public Place"
        }
    ],
    "sg:phone":"+1 450 454 4054",
    "sg:postcode":"J0L 2L0",
    "sg:province":"QC",
    "wof:name":"Quebec Solidarite Sociale",
    "wof:placetype":"venue"
},
  "geometry": {"coordinates":[-73.62638099999999,45.292721],"type":"Point"}
}