{
  "type": "Feature",
  "properties": {
    "iso:country":"CA",
    "sg:address":"5109 44 St",
    "sg:city":"Beaumont",
    "sg:classifiers":[
        {
            "category":"Wholesale",
            "subcategory":"Toys & Hobbies",
            "type":"Manufacturing & Wholesale Goods"
        }
    ],
    "sg:phone":"+1 780 929 2965",
    "sg:postcode":"T4X 1J1",
    "sg:province":"AB",
    "wof:name":"Smalley Agencies Ltd",
    "wof:placetype":"venue"
},
  "geometry": {"coordinates":[-113.40629577599999,53.3544540405],"type":"Point"}
}