{
  "type": "Feature",
  "properties": {
    "addr:full":"5041 1st Ave Edson AB T7E 1T3",
    "addr:housenumber":"5041",
    "addr:postcode":"t7e 1t3",
    "addr:street":"1St Ave",
    "iso:country":"CA",
    "sg:address":"5041 1st Ave",
    "sg:city":"Edson",
    "sg:classifiers":[
        {
            "category":"Home & Garden",
            "subcategory":"Household Appliances",
            "type":"Retail Goods"
        }
    ],
    "sg:phone":"+1 780 723 1827",
    "sg:postcode":"T7E 1T3",
    "sg:province":"AB",
    "sg:tags":[
        "mail",
        "catalog",
        "shopping",
        "order"
    ],
    "wof:name":"Sears Canada Inc",
    "wof:placetype":"venue"
},
  "geometry": {"coordinates":[-116.431831,53.579803],"type":"Point"}
}