{
  "type": "Feature",
  "properties": {
    "addr:full":"Vancouver BC V6B 2T4",
    "addr:postcode":"v6b 2t4",
    "iso:country":"CA",
    "sg:city":"Vancouver",
    "sg:classifiers":[
        {
            "category":"Health Services",
            "subcategory":"Doctor",
            "type":"Services"
        }
    ],
    "sg:phone":"+1 604 633 1199",
    "sg:postcode":"V6B 2T4",
    "sg:province":"BC",
    "sg:tags":[
        "dentist"
    ],
    "wof:name":"Enamel",
    "wof:placetype":"venue"
},
  "geometry": {"coordinates":[-123.119239807,49.2762451172],"type":"Point"}
}