{
  "type": "Feature",
  "properties": {
    "iso:country":"CA",
    "sg:address":"28 King St",
    "sg:city":"Lunenburg",
    "sg:classifiers":[
        {
            "category":"Professional",
            "subcategory":"Lawyer & Legal Services",
            "type":"Services"
        }
    ],
    "sg:phone":"+1 902 634 8354",
    "sg:postcode":"B0J 2C0",
    "sg:province":"NS",
    "sg:tags":[
        "attorney"
    ],
    "wof:name":"Mac Donald, David K",
    "wof:placetype":"venue"
},
  "geometry": {"coordinates":[-64.30944100000001,44.377487],"type":"Point"}
}