{
  "type": "Feature",
  "properties": {
    "addr:full":"17 Queen St Langton ON N0E 1G0",
    "addr:housenumber":"17",
    "addr:postcode":"n0e 1g0",
    "addr:street":"Queen St",
    "iso:country":"CA",
    "sg:address":"17 Queen St",
    "sg:city":"Langton",
    "sg:classifiers":[
        {
            "category":"Autos & Motor Vehicles",
            "subcategory":"Automobile Sales",
            "type":"Retail Goods"
        }
    ],
    "sg:phone":"+1 519 875 3351",
    "sg:postcode":"N0E 1G0",
    "sg:province":"ON",
    "sg:tags":[
        "car",
        "dealer"
    ],
    "wof:name":"Thompson Motors",
    "wof:placetype":"venue"
},
  "geometry": {"coordinates":[-80.5771484375,42.7415771484],"type":"Point"}
}