{
  "type": "Feature",
  "properties": {
    "addr:full":"Toronto ON M4K 1N2",
    "addr:postcode":"m4k 1n2",
    "iso:country":"CA",
    "sg:city":"Toronto",
    "sg:classifiers":[
        {
            "category":"Health Services",
            "subcategory":"Doctor",
            "type":"Services"
        }
    ],
    "sg:phone":"+1 416 461 3000",
    "sg:postcode":"M4K 1N2",
    "sg:province":"ON",
    "sg:tags":[
        "clinic"
    ],
    "wof:name":"Children's After Hours Clinic",
    "wof:placetype":"venue"
},
  "geometry": {"coordinates":[-79.3553161621,43.6767311096],"type":"Point"}
}