{
  "type": "Feature",
  "properties": {
    "addr:full":"5647 Ellen St Chilliwack BC V2R 5N5",
    "addr:housenumber":"5647",
    "addr:postcode":"v2r 5n5",
    "addr:street":"Ellen St",
    "iso:country":"CA",
    "sg:address":"5647 Ellen St",
    "sg:city":"Chilliwack",
    "sg:classifiers":[
        {
            "category":"Building & Trades",
            "subcategory":"Cleaning & Sanitation",
            "type":"Services"
        }
    ],
    "sg:phone":"+1 604 824 0400",
    "sg:postcode":"V2R 5N5",
    "sg:province":"BC",
    "sg:tags":[
        "janitor"
    ],
    "wof:name":"Sparkie's Building Maintenance",
    "wof:placetype":"venue"
},
  "geometry": {"coordinates":[-121.99452209499999,49.1047706604],"type":"Point"}
}