{
  "type": "Feature",
  "properties": {
    "iso:country":"CA",
    "sg:address":"1209 Trans Canada Hwy",
    "sg:city":"Sorrento",
    "sg:classifiers":[
        {
            "category":"Restaurant",
            "type":"Food & Drink"
        }
    ],
    "sg:phone":"+1 250 675 3100",
    "sg:postcode":"V0E 2W0",
    "sg:province":"BC",
    "sg:tags":[
        "pizza"
    ],
    "wof:name":"Freankie's 2 For 1 Pizza",
    "wof:placetype":"venue"
},
  "geometry": {"coordinates":[-119.469642639,50.8771743774],"type":"Point"}
}