{
  "type": "Feature",
  "properties": {
    "addr:full":"2610 Weston Rd # 203 North York ON M9N 2B1",
    "addr:housenumber":"2610",
    "addr:postcode":"m9n 2b1",
    "addr:street":"Weston Rd # 203",
    "iso:country":"CA",
    "sg:address":"2610 Weston Rd # 203",
    "sg:city":"North York",
    "sg:classifiers":[
        {
            "category":"Personal",
            "type":"Services"
        }
    ],
    "sg:phone":"+1 416 248 1047",
    "sg:postcode":"M9N 2B1",
    "sg:province":"ON",
    "sg:tags":[
        "electrolysis"
    ],
    "wof:name":"Brierley Electrolysis",
    "wof:placetype":"venue"
},
  "geometry": {"coordinates":[-79.5354,43.711376],"type":"Point"}
}