{
  "type": "Feature",
  "properties": {
    "addr:full":"160 Crowfoot Way NW Calgary AB T3G 4M4",
    "addr:housenumber":"160",
    "addr:postcode":"t3g 4m4",
    "addr:street":"Crowfoot Way Nw",
    "iso:country":"CA",
    "sg:address":"160 Crowfoot Way NW",
    "sg:city":"Calgary",
    "sg:classifiers":[
        {
            "category":"Retail",
            "subcategory":"Auto Repair",
            "type":"Services"
        }
    ],
    "sg:phone":"+1 403 241 7703",
    "sg:postcode":"T3G 4M4",
    "sg:province":"AB",
    "sg:tags":[
        "muffler",
        "exhaust",
        "system"
    ],
    "wof:name":"Minute Muffler & Brake",
    "wof:placetype":"venue"
},
  "geometry": {"coordinates":[-114.208045959,51.1261672974],"type":"Point"}
}