{
  "type": "Feature",
  "properties": {
    "addr:full":"113 James St N Hamilton ON L8R 2K6",
    "addr:housenumber":"113",
    "addr:postcode":"l8r 2k6",
    "addr:street":"James St N",
    "iso:country":"CA",
    "sg:address":"113 James St N",
    "sg:city":"Hamilton",
    "sg:classifiers":[
        {
            "category":"Restaurant",
            "type":"Food & Drink"
        }
    ],
    "sg:phone":"+1 905 972 8288",
    "sg:postcode":"L8R 2K6",
    "sg:province":"ON",
    "wof:name":"Jade Garden Dining",
    "wof:placetype":"venue"
},
  "geometry": {"coordinates":[-79.86785888670001,43.2596664429],"type":"Point"}
}