{
  "type": "Feature",
  "properties": {
    "addr:full":"1824 Talbot Rd Delhi ON N4B 2W6",
    "addr:housenumber":"1824",
    "addr:postcode":"n4b 2w6",
    "addr:street":"Talbot Rd",
    "iso:country":"CA",
    "sg:address":"1824 Talbot Rd",
    "sg:city":"Delhi",
    "sg:classifiers":[
        {
            "category":"Building & Trades",
            "subcategory":"Electrical",
            "type":"Services"
        }
    ],
    "sg:phone":"+1 519 842 7295",
    "sg:postcode":"N4B 2W6",
    "sg:province":"ON",
    "sg:tags":[
        "electric",
        "contractor"
    ],
    "wof:name":"K O Power & Control Inc",
    "wof:placetype":"venue"
},
  "geometry": {"coordinates":[-80.531158,42.852055],"type":"Point"}
}