{
  "type": "Feature",
  "properties": {
    "addr:full":"Scarborough ON M1S 4N7",
    "addr:postcode":"m1s 4n7",
    "iso:country":"CA",
    "sg:city":"Scarborough",
    "sg:classifiers":[
        {
            "category":"Shopping",
            "subcategory":"Clothing, Apparel, & Fashions",
            "type":"Retail Goods"
        }
    ],
    "sg:phone":"+1 416 291 2108",
    "sg:postcode":"M1S 4N7",
    "sg:province":"ON",
    "sg:tags":[
        "shop",
        "bridal"
    ],
    "wof:name":"Ellis Bridal Boutique",
    "wof:placetype":"venue"
},
  "geometry": {"coordinates":[-79.26939400000001,43.789654],"type":"Point"}
}