{
  "type": "Feature",
  "properties": {
    "addr:full":"101 Av Saint-Redempteur Matane QC G4W 1J8",
    "addr:housenumber":"101",
    "addr:postcode":"g4w 1j8",
    "addr:street":"Av Saint-Redempteur",
    "iso:country":"CA",
    "sg:address":"101 Av Saint-Redempteur",
    "sg:city":"Matane",
    "sg:classifiers":[
        {
            "category":"Food & Beverages",
            "subcategory":"Bakery",
            "type":"Retail Goods"
        }
    ],
    "sg:phone":"+1 418 562 1445",
    "sg:postcode":"G4W 1J8",
    "sg:province":"QC",
    "sg:tags":[
        "baker"
    ],
    "wof:name":"Multi-Marques Inc",
    "wof:placetype":"venue"
},
  "geometry": {"coordinates":[-67.5251464844,48.8465423584],"type":"Point"}
}