{
  "type": "Feature",
  "properties": {
    "addr:full":"North York ON M2J 5A9",
    "addr:postcode":"m2j 5a9",
    "iso:country":"CA",
    "sg:city":"North York",
    "sg:classifiers":[
        {
            "category":"Restaurant",
            "type":"Food & Drink"
        }
    ],
    "sg:phone":"+1 416 490 9838",
    "sg:postcode":"M2J 5A9",
    "sg:province":"ON",
    "sg:tags":[
        "caterer"
    ],
    "wof:name":"Sandwich Plus",
    "wof:placetype":"venue"
},
  "geometry": {"coordinates":[-79.3225479126,43.7736167908],"type":"Point"}
}