{
  "type": "Feature",
  "properties": {
    "iso:country":"CA",
    "sg:address":"514 8th Ave",
    "sg:city":"Keremeos",
    "sg:classifiers":[
        {
            "category":"Retail",
            "subcategory":"Auto Repair",
            "type":"Services"
        }
    ],
    "sg:phone":"+1 250 499 7767",
    "sg:postcode":"V0X 1N0",
    "sg:province":"BC",
    "sg:tags":[
        "repairing",
        "automobile"
    ],
    "wof:name":"Dan's Automotive",
    "wof:placetype":"venue"
},
  "geometry": {"coordinates":[-119.820869446,49.2046356201],"type":"Point"}
}