{
  "type": "Feature",
  "properties": {
    "addr:full":"510 Aut Chomedey Laval QC H7X 3S9",
    "addr:housenumber":"510",
    "addr:postcode":"h7x 3s9",
    "addr:street":"Aut",
    "iso:country":"CA",
    "sg:address":"510 Aut Chomedey",
    "sg:city":"Laval",
    "sg:classifiers":[
        {
            "category":"Shopping",
            "subcategory":"Gifts & Souvenirs",
            "type":"Retail Goods"
        }
    ],
    "sg:phone":"+1 450 969 0281",
    "sg:postcode":"H7X 3S9",
    "sg:province":"QC",
    "sg:tags":[
        "party",
        "supply"
    ],
    "wof:name":"Bou Clair",
    "wof:placetype":"venue"
},
  "geometry": {"coordinates":[-73.7808609009,45.5268363953],"type":"Point"}
}