{
  "type": "Feature",
  "properties": {
    "addr:full":"Ear Falls ON P0V 1T0",
    "addr:postcode":"p0v 1t0",
    "iso:country":"CA",
    "sg:city":"Ear Falls",
    "sg:classifiers":[
        {
            "category":"Travel",
            "subcategory":"Campground",
            "type":"Entertainment"
        }
    ],
    "sg:phone":"+1 807 222 3631",
    "sg:postcode":"P0V 1T0",
    "sg:province":"ON",
    "sg:tags":[
        "camp"
    ],
    "wof:name":"Little Canada Camp",
    "wof:placetype":"venue"
},
  "geometry": {"coordinates":[-93.234421,50.638622],"type":"Point"}
}