{
  "type": "Feature",
  "properties": {
    "addr:full":"558 Scarlett Rd Etobicoke ON M9P 2S2",
    "addr:housenumber":"558",
    "addr:postcode":"m9p 2s2",
    "addr:street":"Scarlett Rd",
    "iso:country":"CA",
    "sg:address":"558 Scarlett Rd",
    "sg:city":"Etobicoke",
    "sg:classifiers":[
        {
            "category":"Recreation",
            "type":"Entertainment"
        }
    ],
    "sg:phone":"+1 416 241 0030",
    "sg:postcode":"M9P 2S2",
    "sg:province":"ON",
    "sg:tags":[
        "amusement"
    ],
    "wof:name":"Boni Goalie Trainers Inc",
    "wof:placetype":"venue"
},
  "geometry": {"coordinates":[-79.514229,43.688652],"type":"Point"}
}