{
  "type": "Feature",
  "properties": {
    "addr:full":"46 Rush Cove Rd Lions Head ON N0H 1W0",
    "addr:housenumber":"46",
    "addr:postcode":"n0h 1w0",
    "addr:street":"Rush Cove Rd",
    "iso:country":"CA",
    "sg:address":"46 Rush Cove Rd",
    "sg:city":"Lions Head",
    "sg:classifiers":[
        {
            "category":"Building & Trades",
            "subcategory":"Electrical",
            "type":"Services"
        }
    ],
    "sg:phone":"+1 519 793 3222",
    "sg:postcode":"N0H 1W0",
    "sg:province":"ON",
    "sg:tags":[
        "electric",
        "contractor"
    ],
    "wof:name":"Roger Meneray Electrical",
    "wof:placetype":"venue"
},
  "geometry": {"coordinates":[-81.25420379640001,44.986579895],"type":"Point"}
}