{
  "type": "Feature",
  "properties": {
    "addr:full":"540 Regional Road 55 Lively ON P3Y 1C4",
    "addr:housenumber":"540",
    "addr:postcode":"p3y 1c4",
    "addr:street":"Regional Road 55",
    "iso:country":"CA",
    "sg:address":"540 Regional Road 55",
    "sg:city":"Lively",
    "sg:classifiers":[
        {
            "category":"Organizations",
            "subcategory":"Religious Organization",
            "type":"Services"
        }
    ],
    "sg:phone":"+1 705 692 7655",
    "sg:postcode":"P3Y 1C4",
    "sg:province":"ON",
    "sg:tags":[
        "church"
    ],
    "wof:name":"Waters Mennonite Church",
    "wof:placetype":"venue"
},
  "geometry": {"coordinates":[-81.1464767456,46.4382286072],"type":"Point"}
}