{
  "type": "Feature",
  "properties": {
    "addr:full":"10 Donald St Winnipeg MB R3C 1L5",
    "addr:housenumber":"10",
    "addr:postcode":"r3c 1l5",
    "addr:street":"Donald St",
    "iso:country":"CA",
    "sg:address":"10 Donald St",
    "sg:city":"Winnipeg",
    "sg:classifiers":[
        {
            "category":"Professional",
            "subcategory":"Lawyer & Legal Services",
            "type":"Services"
        }
    ],
    "sg:phone":"+1 204 942 3311",
    "sg:postcode":"R3C 1L5",
    "sg:province":"MB",
    "sg:tags":[
        "attorney"
    ],
    "wof:name":"Mac Kenzie, Douglas J",
    "wof:placetype":"venue"
},
  "geometry": {"coordinates":[-97.139053,49.885262],"type":"Point"}
}