{
  "type": "Feature",
  "properties": {
    "addr:full":"20 Perron St St Albert AB T8N 1E4",
    "addr:housenumber":"20",
    "addr:postcode":"t8n 1e4",
    "addr:street":"Perron St",
    "iso:country":"CA",
    "sg:address":"20 Perron St",
    "sg:city":"St Albert",
    "sg:classifiers":[
        {
            "category":"Shopping",
            "subcategory":"Bicycles & Sporting Goods",
            "type":"Retail Goods"
        }
    ],
    "sg:phone":"+1 780 460 7766",
    "sg:postcode":"T8N 1E4",
    "sg:province":"AB",
    "wof:name":"Soccer Fanatics Ltd",
    "wof:placetype":"venue"
},
  "geometry": {"coordinates":[-113.626259,53.634396],"type":"Point"}
}