{
  "type": "Feature",
  "properties": {
    "addr:full":"Port Coquitlam BC V3C 6M9",
    "addr:postcode":"v3c 6m9",
    "iso:country":"CA",
    "sg:city":"Port Coquitlam",
    "sg:classifiers":[
        {
            "category":"Manufacturing",
            "subcategory":"Rubber & Plastics",
            "type":"Manufacturing & Wholesale Goods"
        }
    ],
    "sg:phone":"+1 604 552 9734",
    "sg:postcode":"V3C 6M9",
    "sg:province":"BC",
    "sg:tags":[
        "mold",
        "maker"
    ],
    "wof:name":"Northwest Plastics Ltd",
    "wof:placetype":"venue"
},
  "geometry": {"coordinates":[-122.756980896,49.2457542419],"type":"Point"}
}