{
  "type": "Feature",
  "properties": {
    "addr:full":"115 Ironside Cres #13 Scarborough ON M1X 1M1",
    "addr:housenumber":"115",
    "addr:postcode":"m1x 1m1",
    "addr:street":"Ironside Cres # 13",
    "iso:country":"CA",
    "sg:address":"115 Ironside Cres #13",
    "sg:city":"Scarborough",
    "sg:classifiers":[
        {
            "category":"Wholesale",
            "subcategory":"Meat",
            "type":"Manufacturing & Wholesale Goods"
        }
    ],
    "sg:phone":"+1 416 292 6118",
    "sg:postcode":"M1X 1M1",
    "sg:province":"ON",
    "sg:tags":[
        "food",
        "product",
        "manufacturer"
    ],
    "wof:name":"Regent Meat & Poultry CO Ltd",
    "wof:placetype":"venue"
},
  "geometry": {"coordinates":[-79.24746704099999,43.8280105591],"type":"Point"}
}