{
  "type": "Feature",
  "properties": {
    "addr:full":"5000 Av Albert-Tessier Shawinigan QC G9N 8P9",
    "addr:postcode":"g9n 8p9",
    "addr:street":"Av Albert-Tessier",
    "iso:country":"CA",
    "sg:address":"5000 Av Albert-Tessier",
    "sg:city":"Shawinigan",
    "sg:classifiers":[
        {
            "category":"Organizations",
            "subcategory":"Labor Organization",
            "type":"Services"
        }
    ],
    "sg:phone":"+1 819 539 2199",
    "sg:postcode":"G9N 8P9",
    "sg:province":"QC",
    "wof:name":"Syndicat Des Employes DE Ctr",
    "wof:placetype":"venue"
},
  "geometry": {"coordinates":[-72.732803,46.57354],"type":"Point"}
}