{
  "type": "Feature",
  "properties": {
    "addr:full":"446 Union St Vancouver BC V6A 2B6",
    "addr:housenumber":"446",
    "addr:postcode":"v6a 2b6",
    "addr:street":"Union St",
    "iso:country":"CA",
    "sg:address":"446 Union St",
    "sg:city":"Vancouver",
    "sg:classifiers":[
        {
            "category":"Shopping",
            "type":"Retail Goods"
        }
    ],
    "sg:phone":"+1 604 684 1999",
    "sg:postcode":"V6A 2B6",
    "sg:province":"BC",
    "sg:tags":[
        "picture",
        "frame"
    ],
    "wof:name":"Work Shop",
    "wof:placetype":"venue"
},
  "geometry": {"coordinates":[-123.094589,49.277431],"type":"Point"}
}