{
  "type": "Feature",
  "properties": {
    "addr:full":"2020 Main St Penticton BC V2A 5H4",
    "addr:housenumber":"2020",
    "addr:postcode":"v2a 5h4",
    "addr:street":"Main St",
    "iso:country":"CA",
    "sg:address":"2020 Main St",
    "sg:city":"Penticton",
    "sg:classifiers":[
        {
            "category":"Retail",
            "subcategory":"Auto Repair",
            "type":"Services"
        }
    ],
    "sg:phone":"+1 250 493 1984",
    "sg:postcode":"V2A 5H4",
    "sg:province":"BC",
    "sg:tags":[
        "repairing",
        "automobile"
    ],
    "wof:name":"Cherry Lane Petro-Canada",
    "wof:placetype":"venue"
},
  "geometry": {"coordinates":[-119.583015442,49.4759674072],"type":"Point"}
}