{
  "type": "Feature",
  "properties": {
    "addr:full":"1060 Ogilvie Rd Gloucester ON K1J 7P8",
    "addr:housenumber":"1060",
    "addr:postcode":"k1j 7p8",
    "addr:street":"Ogilvie Rd",
    "iso:country":"CA",
    "sg:address":"1060 Ogilvie Rd",
    "sg:city":"Gloucester",
    "sg:classifiers":[
        {
            "category":"Real Estate",
            "subcategory":"Real Estate Agent",
            "type":"Services"
        }
    ],
    "sg:phone":"+1 613 741 1881",
    "sg:postcode":"K1J 7P8",
    "sg:province":"ON",
    "sg:tags":[
        "party",
        "agency",
        "rental",
        "supply"
    ],
    "wof:name":"Cody Party & Event Rentals",
    "wof:placetype":"venue"
},
  "geometry": {"coordinates":[-75.634018,45.425087],"type":"Point"}
}