{
  "type": "Feature",
  "properties": {
    "addr:full":"5039 49 St Innisfail AB T4G 1M1",
    "addr:housenumber":"5039",
    "addr:postcode":"t4g 1m1",
    "addr:street":"49 St",
    "iso:country":"CA",
    "sg:address":"5039 49 St",
    "sg:city":"Innisfail",
    "sg:classifiers":[
        {
            "category":"Restaurant",
            "type":"Food & Drink"
        }
    ],
    "sg:phone":"+1 403 227 2333",
    "sg:postcode":"T4G 1M1",
    "sg:province":"AB",
    "wof:name":"Mulligan's Pizza",
    "wof:placetype":"venue"
},
  "geometry": {"coordinates":[-113.951042175,52.026386261],"type":"Point"}
}