{
  "type": "Feature",
  "properties": {
    "addr:full":"55 Frid St Hamilton ON L8P 4M3",
    "addr:housenumber":"55",
    "addr:postcode":"l8p 4m3",
    "addr:street":"Frid St",
    "iso:country":"CA",
    "sg:address":"55 Frid St",
    "sg:city":"Hamilton",
    "sg:classifiers":[
        {
            "category":"Professional",
            "subcategory":"Management & Consulting",
            "type":"Services"
        }
    ],
    "sg:phone":"+1 905 527 1991",
    "sg:postcode":"L8P 4M3",
    "sg:province":"ON",
    "sg:tags":[
        "employee",
        "consultant",
        "benefit"
    ],
    "wof:name":"Pro Act Consulting Inc",
    "wof:placetype":"venue"
},
  "geometry": {"coordinates":[-79.89247899999999,43.259087],"type":"Point"}
}