{
  "type": "Feature",
  "properties": {
    "addr:full":"68 Munro Blvd North York ON M2P 1C2",
    "addr:housenumber":"68",
    "addr:postcode":"m2p 1c2",
    "addr:street":"Munro Blvd",
    "iso:country":"CA",
    "sg:address":"68 Munro Blvd",
    "sg:city":"North York",
    "sg:classifiers":[
        {
            "category":"Wholesale",
            "subcategory":"Durable Goods & Equipment",
            "type":"Manufacturing & Wholesale Goods"
        }
    ],
    "sg:phone":"+1 416 481 4171",
    "sg:postcode":"M2P 1C2",
    "sg:province":"ON",
    "sg:tags":[
        "importer"
    ],
    "wof:name":"Massisco Inc",
    "wof:placetype":"venue"
},
  "geometry": {"coordinates":[-79.39503479,43.7467956543],"type":"Point"}
}