{
  "type": "Feature",
  "properties": {
    "addr:full":"159 Milvan Dr North York ON M9L 1Z8",
    "addr:housenumber":"159",
    "addr:postcode":"m9l 1z8",
    "addr:street":"Milvan Dr",
    "iso:country":"CA",
    "sg:address":"159 Milvan Dr",
    "sg:city":"North York",
    "sg:classifiers":[
        {
            "category":"Wholesale",
            "subcategory":"Auto Parts",
            "type":"Manufacturing & Wholesale Goods"
        }
    ],
    "sg:phone":"+1 416 745 6116",
    "sg:postcode":"M9L 1Z8",
    "sg:province":"ON",
    "sg:tags":[
        "automobile",
        "rebuilt",
        "wrecking"
    ],
    "wof:name":"Star Line Automotive",
    "wof:placetype":"venue"
},
  "geometry": {"coordinates":[-79.563789,43.757786],"type":"Point"}
}