{
  "type": "Feature",
  "properties": {
    "addr:full":"2 Mercury Ave Atikokan ON P0T 1C0",
    "addr:housenumber":"2",
    "addr:postcode":"p0t 1c0",
    "addr:street":"Mercury Ave",
    "iso:country":"CA",
    "sg:address":"2 Mercury Ave",
    "sg:city":"Atikokan",
    "sg:classifiers":[
        {
            "category":"Autos & Motor Vehicles",
            "subcategory":"Fuel & Gas Station",
            "type":"Retail Goods"
        }
    ],
    "sg:phone":"+1 807 597 6775",
    "sg:postcode":"P0T 1C0",
    "sg:province":"ON",
    "sg:tags":[
        "oil"
    ],
    "wof:name":"Johnson's Esso",
    "wof:placetype":"venue"
},
  "geometry": {"coordinates":[-91.60692596440001,48.7574157715],"type":"Point"}
}