{
  "type": "Feature",
  "properties": {
    "addr:full":"Ladysmith QC J0X 2A0",
    "addr:postcode":"j0x 2a0",
    "iso:country":"CA",
    "sg:city":"Ladysmith",
    "sg:classifiers":[
        {
            "category":"Food & Beverages",
            "subcategory":"Groceries & Convenience Stores",
            "type":"Retail Goods"
        }
    ],
    "sg:phone":"+1 819 647 2328",
    "sg:postcode":"J0X 2A0",
    "sg:province":"QC",
    "sg:tags":[
        "grocer"
    ],
    "wof:name":"Bretzlaff Store",
    "wof:placetype":"venue"
},
  "geometry": {"coordinates":[-76.383224,45.76873],"type":"Point"}
}