{
  "type": "Feature",
  "properties": {
    "addr:full":"661 Hamilton Rd London ON N5Z 1T2",
    "addr:housenumber":"661",
    "addr:postcode":"n5z 1t2",
    "addr:street":"Hamilton Rd",
    "iso:country":"CA",
    "sg:address":"661 Hamilton Rd",
    "sg:city":"London",
    "sg:classifiers":[
        {
            "category":"Travel",
            "subcategory":"Travel Agent",
            "type":"Entertainment"
        }
    ],
    "sg:phone":"+1 519 452 3583",
    "sg:postcode":"N5Z 1T2",
    "sg:province":"ON",
    "sg:tags":[
        "agency",
        "bureau"
    ],
    "wof:name":"Santos Travel Agency Inc",
    "wof:placetype":"venue"
},
  "geometry": {"coordinates":[-81.208771,42.979603],"type":"Point"}
}