{
  "type": "Feature",
  "properties": {
    "addr:full":"240 Merrizzi St Saint-Laurent QC H4T 1S4",
    "addr:housenumber":"240",
    "addr:postcode":"h4t 1s4",
    "addr:street":"Merrizzi St",
    "iso:country":"CA",
    "sg:address":"240 Merrizzi St",
    "sg:city":"Saint-Laurent",
    "sg:classifiers":[
        {
            "category":"Restaurant",
            "type":"Food & Drink"
        }
    ],
    "sg:phone":"+1 514 735 2442",
    "sg:postcode":"H4T 1S4",
    "sg:province":"QC",
    "wof:name":"Cavemo",
    "wof:placetype":"venue"
},
  "geometry": {"coordinates":[-73.6948471069,45.480091095],"type":"Point"}
}