{
  "type": "Feature",
  "properties": {
    "addr:full":"1035 Boul Magenta E Farnham QC J2N 1B9",
    "addr:housenumber":"1035",
    "addr:postcode":"j2n 1b9",
    "addr:street":"Boul Magenta E",
    "iso:country":"CA",
    "sg:address":"1035 Boul Magenta E",
    "sg:city":"Farnham",
    "sg:classifiers":[
        {
            "category":"Manufacturing",
            "subcategory":"Furniture",
            "type":"Manufacturing & Wholesale Goods"
        }
    ],
    "sg:phone":"+1 450 293 5354",
    "sg:postcode":"J2N 1B9",
    "sg:province":"QC",
    "sg:tags":[
        "equipment",
        "school"
    ],
    "wof:name":"Alpha-Vico Canada Inc",
    "wof:placetype":"venue"
},
  "geometry": {"coordinates":[-72.96520200000001,45.287411],"type":"Point"}
}