{
  "type": "Feature",
  "properties": {
    "addr:full":"633 Harmony Rd Corbyville ON K0K 1V0",
    "addr:housenumber":"633",
    "addr:postcode":"k0k 1v0",
    "addr:street":"Harmony Rd",
    "iso:country":"CA",
    "sg:address":"633 Harmony Rd",
    "sg:city":"Corbyville",
    "sg:classifiers":[
        {
            "category":"Retail",
            "subcategory":"Repair Shop",
            "type":"Services"
        }
    ],
    "sg:phone":"+1 613 966 4498",
    "sg:postcode":"K0K 1V0",
    "sg:province":"ON",
    "sg:tags":[
        "equipment",
        "welding"
    ],
    "wof:name":"Excalibur Technical Svc",
    "wof:placetype":"venue"
},
  "geometry": {"coordinates":[-77.38832855219999,44.2199783325],"type":"Point"}
}