{
  "type": "Feature",
  "properties": {
    "addr:full":"449 Rue Jean-Talon O Montreal QC H3N 1P9",
    "addr:housenumber":"449",
    "addr:postcode":"h3n 1p9",
    "addr:street":"Rue Jean-Talon O",
    "iso:country":"CA",
    "sg:address":"449 Rue Jean-Talon O",
    "sg:city":"Montreal",
    "sg:classifiers":[
        {
            "category":"Professional",
            "subcategory":"Business Services",
            "type":"Services"
        }
    ],
    "sg:phone":"+1 514 274 2698",
    "sg:postcode":"H3N 1P9",
    "sg:province":"QC",
    "sg:tags":[
        "paper",
        "lamination"
    ],
    "wof:name":"Miracle Du Dollar",
    "wof:placetype":"venue"
},
  "geometry": {"coordinates":[-73.614273,45.538734],"type":"Point"}
}