{
  "type": "Feature",
  "properties": {
    "addr:full":"2 Pine Haven Lane Perth Road ON K0H 2L0",
    "addr:housenumber":"2",
    "addr:postcode":"k0h 2l0",
    "addr:street":"Pine Haven Lane Perth Road",
    "iso:country":"CA",
    "sg:address":"2 Pine Haven Lane",
    "sg:city":"Perth Road",
    "sg:classifiers":[
        {
            "category":"Travel",
            "subcategory":"Campground",
            "type":"Entertainment"
        }
    ],
    "sg:phone":"+1 613 273 5365",
    "sg:postcode":"K0H 2L0",
    "sg:province":"ON",
    "sg:tags":[
        "camp"
    ],
    "wof:name":"Pine Haven Camps",
    "wof:placetype":"venue"
},
  "geometry": {"coordinates":[-76.491455,44.465244],"type":"Point"}
}