{
  "type": "Feature",
  "properties": {
    "addr:full":"6202 64 St Taber AB T1G 1Z3",
    "addr:housenumber":"6202",
    "addr:postcode":"t1g 1z3",
    "addr:street":"64 St",
    "iso:country":"CA",
    "sg:address":"6202 64 St",
    "sg:city":"Taber",
    "sg:classifiers":[
        {
            "category":"Wholesale",
            "subcategory":"Machinery & Supplies",
            "type":"Manufacturing & Wholesale Goods"
        }
    ],
    "sg:phone":"+1 403 223 9366",
    "sg:postcode":"T1G 1Z3",
    "sg:province":"AB",
    "sg:tags":[
        "field",
        "oil"
    ],
    "wof:name":"Midfield Supply Ltd",
    "wof:placetype":"venue"
},
  "geometry": {"coordinates":[-112.12766265899999,49.7984924316],"type":"Point"}
}