{
  "type": "Feature",
  "properties": {
    "addr:full":"3440 Av Du Musee Montreal QC H3G 2C7",
    "addr:housenumber":"3440",
    "addr:postcode":"h3g 2c7",
    "addr:street":"Av Du Musee",
    "iso:country":"CA",
    "sg:address":"3440 Av Du Musee",
    "sg:city":"Montreal",
    "sg:classifiers":[
        {
            "category":"Shopping",
            "type":"Retail Goods"
        }
    ],
    "sg:phone":"+1 514 843 5024",
    "sg:postcode":"H3G 2C7",
    "sg:province":"QC",
    "sg:tags":[
        "art",
        "gallery",
        "dealer"
    ],
    "wof:name":"Art 45",
    "wof:placetype":"venue"
},
  "geometry": {"coordinates":[-73.581352,45.499496],"type":"Point"}
}