{
  "type": "Feature",
  "properties": {
    "iso:country":"CA",
    "sg:address":"59 Tanoak Park Dr",
    "sg:city":"Winnipeg",
    "sg:classifiers":[
        {
            "category":"Professional",
            "subcategory":"Business Services",
            "type":"Services"
        }
    ],
    "sg:phone":"+1 204 338 4729",
    "sg:postcode":"R2V 2W6",
    "sg:province":"MB",
    "sg:tags":[
        "interior",
        "consultant",
        "design",
        "decorator"
    ],
    "wof:name":"Interiors By Design",
    "wof:placetype":"venue"
},
  "geometry": {"coordinates":[-97.132767,49.947754],"type":"Point"}
}