{
  "type": "Feature",
  "properties": {
    "addr:full":"1067 Bank St Ottawa ON K1S 3W9",
    "addr:housenumber":"1067",
    "addr:postcode":"k1s 3w9",
    "addr:street":"Bank St",
    "iso:country":"CA",
    "sg:address":"1067 Bank St",
    "sg:city":"Ottawa",
    "sg:classifiers":[
        {
            "category":"Organizations",
            "subcategory":"Professional Association",
            "type":"Services"
        }
    ],
    "sg:phone":"+1 613 730 2346",
    "sg:postcode":"K1S 3W9",
    "sg:province":"ON",
    "sg:tags":[
        "book",
        "dealer"
    ],
    "wof:name":"Mother Tongue Books Femmes",
    "wof:placetype":"venue"
},
  "geometry": {"coordinates":[-75.683555603,45.3948020935],"type":"Point"}
}