{
  "type": "Feature",
  "properties": {
    "iso:country":"CA",
    "sg:address":"1720 Rue Effingham",
    "sg:city":"Terrebonne",
    "sg:classifiers":[
        {
            "category":"Manufacturing",
            "subcategory":"Tools & Machinery",
            "type":"Manufacturing & Wholesale Goods"
        }
    ],
    "sg:phone":"+1 450 434 3285",
    "sg:postcode":"J6Y 1R7",
    "sg:province":"QC",
    "sg:tags":[
        "machine",
        "shop"
    ],
    "wof:name":"Societe D'Usinage Barriere Inc",
    "wof:placetype":"venue"
},
  "geometry": {"coordinates":[-73.7786483765,45.6823997498],"type":"Point"}
}