{
  "type": "Feature",
  "properties": {
    "addr:full":"11543 Long Woods Rd Delaware ON N0L 1E0",
    "addr:housenumber":"11543",
    "addr:postcode":"n0l 1e0",
    "addr:street":"Long Woods Rd",
    "iso:country":"CA",
    "sg:address":"11543 Long Woods Rd",
    "sg:city":"Delaware",
    "sg:classifiers":[
        {
            "category":"Wholesale",
            "subcategory":"Machinery & Supplies",
            "type":"Manufacturing & Wholesale Goods"
        }
    ],
    "sg:phone":"+1 519 652 9611",
    "sg:postcode":"N0L 1E0",
    "sg:province":"ON",
    "sg:tags":[
        "farm",
        "equipment"
    ],
    "wof:name":"Delaware Pump & Parts Ltd",
    "wof:placetype":"venue"
},
  "geometry": {"coordinates":[-81.41943359379999,42.9074440002],"type":"Point"}
}