{
  "type": "Feature",
  "properties": {
    "addr:full":"61 Av Cedar Pointe-Claire QC H9S 4Y3",
    "addr:postcode":"h9s 4y3",
    "addr:street":"61 Av Cedar",
    "iso:country":"CA",
    "sg:address":"61 Av Cedar",
    "sg:city":"Pointe-Claire",
    "sg:classifiers":[
        {
            "category":"Real Estate",
            "subcategory":"Surveying",
            "type":"Services"
        }
    ],
    "sg:phone":"+1 514 697 3311",
    "sg:postcode":"H9S 4Y3",
    "sg:province":"QC",
    "sg:tags":[
        "surveyor"
    ],
    "wof:name":"Rabin & Rabin",
    "wof:placetype":"venue"
},
  "geometry": {"coordinates":[-73.81688699999999,45.438641],"type":"Point"}
}