{
  "type": "Feature",
  "properties": {
    "iso:country":"CA",
    "sg:address":"Hwy 48",
    "sg:city":"Montmartre",
    "sg:classifiers":[
        {
            "category":"Autos & Motor Vehicles",
            "subcategory":"Fuel & Gas Station",
            "type":"Retail Goods"
        }
    ],
    "sg:phone":"+1 306 424 2311",
    "sg:postcode":"S0G 3M0",
    "sg:province":"SK",
    "sg:tags":[
        "oil"
    ],
    "wof:name":"Peter's Service",
    "wof:placetype":"venue"
},
  "geometry": {"coordinates":[-103.451774597,50.2221412659],"type":"Point"}
}