{
  "type": "Feature",
  "properties": {
    "addr:full":"10638 Winterburn Rd NW Edmonton AB T5S 1T7",
    "addr:housenumber":"10638",
    "addr:postcode":"t5s 1t7",
    "addr:street":"Winterburn Rd Nw",
    "iso:country":"CA",
    "sg:address":"10638 Winterburn Rd NW",
    "sg:city":"Edmonton",
    "sg:classifiers":[
        {
            "category":"Social Services",
            "subcategory":"Child Care",
            "type":"Services"
        }
    ],
    "sg:phone":"+1 780 447 4699",
    "sg:postcode":"T5S 1T7",
    "sg:province":"AB",
    "wof:name":"Between Friends",
    "wof:placetype":"venue"
},
  "geometry": {"coordinates":[-113.689232,53.550743],"type":"Point"}
}