{
  "type": "Feature",
  "properties": {
    "addr:full":"938 Churchill Ave Sudbury ON P3A 4A4",
    "addr:housenumber":"938",
    "addr:postcode":"p3a 4a4",
    "addr:street":"Churchill Ave",
    "iso:country":"CA",
    "sg:address":"938 Churchill Ave",
    "sg:city":"Sudbury",
    "sg:classifiers":[
        {
            "category":"Personal",
            "type":"Services"
        }
    ],
    "sg:phone":"+1 705 525 1088",
    "sg:postcode":"P3A 4A4",
    "sg:province":"ON",
    "sg:tags":[
        "therapist",
        "massage"
    ],
    "wof:name":"Forth, Penny",
    "wof:placetype":"venue"
},
  "geometry": {"coordinates":[-80.934105,46.51722],"type":"Point"}
}