{
  "type": "Feature",
  "properties": {
    "addr:full":"184991 Cornell Rd Tillsonburg ON N4G 4G8",
    "addr:housenumber":"184991",
    "addr:postcode":"n4g 4g8",
    "addr:street":"Cornell Rd",
    "iso:country":"CA",
    "sg:address":"184991 Cornell Rd",
    "sg:city":"Tillsonburg",
    "sg:classifiers":[
        {
            "category":"Freight",
            "type":"Transportation"
        }
    ],
    "sg:phone":"+1 519 688 3430",
    "sg:postcode":"N4G 4G8",
    "sg:province":"ON",
    "sg:tags":[
        "trucking"
    ],
    "wof:name":"Bdr Intl",
    "wof:placetype":"venue"
},
  "geometry": {"coordinates":[-80.727867,42.860676],"type":"Point"}
}