{
  "type": "Feature",
  "properties": {
    "addr:full":"46229 Yale Rd Chilliwack BC V2P 2P4",
    "addr:housenumber":"46229",
    "addr:postcode":"v2p 2p4",
    "addr:street":"Yale Rd",
    "iso:country":"CA",
    "sg:address":"46229 Yale Rd",
    "sg:city":"Chilliwack",
    "sg:classifiers":[
        {
            "category":"Shopping",
            "type":"Retail Goods"
        }
    ],
    "sg:phone":"+1 604 795 3331",
    "sg:postcode":"V2P 2P4",
    "sg:province":"BC",
    "sg:tags":[
        "stamp",
        "collector",
        "for"
    ],
    "wof:name":"Canada Post Corp",
    "wof:placetype":"venue"
},
  "geometry": {"coordinates":[-121.949516,49.171932],"type":"Point"}
}