{
  "type": "Feature",
  "properties": {
    "addr:full":"2515 Av Dumas Quebec QC G1L 4P9",
    "addr:housenumber":"2515",
    "addr:postcode":"g1l 4p9",
    "addr:street":"Av Dumas",
    "iso:country":"CA",
    "sg:address":"2515 Av Dumas",
    "sg:city":"Quebec",
    "sg:classifiers":[
        {
            "category":"Shopping",
            "subcategory":"Clothing, Apparel, & Fashions",
            "type":"Retail Goods"
        }
    ],
    "sg:phone":"+1 418 623 9955",
    "sg:postcode":"G1L 4P9",
    "sg:province":"QC",
    "sg:tags":[
        "cleaners",
        "fur"
    ],
    "wof:name":"Maranda Lustre Inc",
    "wof:placetype":"venue"
},
  "geometry": {"coordinates":[-71.2532577515,46.8306808472],"type":"Point"}
}