{
  "type": "Feature",
  "properties": {
    "iso:country":"CA",
    "sg:address":"18 Rue DE Courcelette",
    "sg:city":"Quebec",
    "sg:classifiers":[
        {
            "category":"Home & Garden",
            "subcategory":"Furniture",
            "type":"Retail Goods"
        }
    ],
    "sg:phone":"+1 418 681 0171",
    "sg:postcode":"G1N 4S2",
    "sg:province":"QC",
    "wof:name":"Galerie Du Meuble Inc",
    "wof:placetype":"venue"
},
  "geometry": {"coordinates":[-71.248077,46.811447],"type":"Point"}
}