{
  "type": "Feature",
  "properties": {
    "addr:full":"Saint-Cesaire QC J0L 1T0",
    "addr:postcode":"j0l 1t0",
    "iso:country":"CA",
    "sg:city":"Saint-Cesaire",
    "sg:classifiers":[
        {
            "category":"Professional",
            "subcategory":"Business Services",
            "type":"Services"
        }
    ],
    "sg:phone":"+1 450 469 2801",
    "sg:postcode":"J0L 1T0",
    "sg:province":"QC",
    "sg:tags":[
        "notary"
    ],
    "wof:name":"Denicourt Gagnon Calgaro",
    "wof:placetype":"venue"
},
  "geometry": {"coordinates":[-73.004616,45.411564],"type":"Point"}
}