{
  "type": "Feature",
  "properties": {
    "addr:full":"1415 Huron Church Rd Windsor ON N9C 2K9",
    "addr:housenumber":"1415",
    "addr:postcode":"n9c 2k9",
    "addr:street":"Huron Church Rd",
    "iso:country":"CA",
    "sg:address":"1415 Huron Church Rd",
    "sg:city":"Windsor",
    "sg:classifiers":[
        {
            "category":"Bars & Pubs",
            "type":"Food & Drink"
        }
    ],
    "sg:phone":"+1 519 253 6331",
    "sg:postcode":"N9C 2K9",
    "sg:province":"ON",
    "sg:tags":[
        "club",
        "night"
    ],
    "wof:name":"Studio Four Tavern",
    "wof:placetype":"venue"
},
  "geometry": {"coordinates":[-83.059662,42.2896],"type":"Point"}
}