{
  "type": "Feature",
  "properties": {
    "addr:full":"10231 95 St NW Edmonton AB T5H 2B2",
    "addr:housenumber":"10231",
    "addr:postcode":"t5h 2b2",
    "addr:street":"95 St Nw",
    "iso:country":"CA",
    "sg:address":"10231 95 St NW",
    "sg:city":"Edmonton",
    "sg:classifiers":[
        {
            "category":"Bars & Pubs",
            "type":"Food & Drink"
        }
    ],
    "sg:phone":"+1 780 425 4298",
    "sg:postcode":"T5H 2B2",
    "sg:province":"AB",
    "sg:tags":[
        "lounge",
        "cocktail"
    ],
    "wof:name":"Camelot Sports Bar & Lounge",
    "wof:placetype":"venue"
},
  "geometry": {"coordinates":[-113.47901899999999,53.546047],"type":"Point"}
}