{
  "type": "Feature",
  "properties": {
    "addr:full":"Saint-Bernard-DE-Lacolle QC J0J 1V0",
    "addr:postcode":"j0j 1v0",
    "iso:country":"CA",
    "sg:city":"Saint-Bernard-DE-Lacolle",
    "sg:classifiers":[
        {
            "category":"Shopping",
            "type":"Retail Goods"
        }
    ],
    "sg:phone":"+1 450 246 2000",
    "sg:postcode":"J0J 1V0",
    "sg:province":"QC",
    "sg:tags":[
        "miscellaneous",
        "store"
    ],
    "wof:name":"Boutique Hors Taxes Igl Ltee",
    "wof:placetype":"venue"
},
  "geometry": {"coordinates":[-73.372902,45.082474],"type":"Point"}
}