{
  "type": "Feature",
  "properties": {
    "addr:full":"145 Main St Ailsa Craig ON N0M 1A0",
    "addr:housenumber":"145",
    "addr:postcode":"n0m 1a0",
    "addr:street":"Main St",
    "iso:country":"CA",
    "sg:address":"145 Main St",
    "sg:city":"Ailsa Craig",
    "sg:classifiers":[
        {
            "category":"Shopping",
            "subcategory":"Used Merchandise",
            "type":"Retail Goods"
        }
    ],
    "sg:phone":"+1 519 293 3337",
    "sg:postcode":"N0M 1A0",
    "sg:province":"ON",
    "sg:tags":[
        "antique"
    ],
    "wof:name":"Curiosity Shop",
    "wof:placetype":"venue"
},
  "geometry": {"coordinates":[-81.536812,43.147434],"type":"Point"}
}