{
  "type": "Feature",
  "properties": {
    "iso:country":"CA",
    "sg:address":"Deadmans Creek Rd",
    "sg:city":"Savona",
    "sg:classifiers":[
        {
            "category":"Recreation",
            "type":"Entertainment"
        }
    ],
    "sg:phone":"+1 250 373 2636",
    "sg:postcode":"V0K 2J0",
    "sg:province":"BC",
    "sg:tags":[
        "party",
        "fishing"
    ],
    "wof:name":"Circle W hi-Hium Fishing Camp",
    "wof:placetype":"venue"
},
  "geometry": {"coordinates":[-120.85009002699999,50.7499771118],"type":"Point"}
}