{
  "type": "Feature",
  "properties": {
    "iso:country":"CA",
    "sg:address":"5080 Montee Saint-Hubert",
    "sg:city":"Saint-Hubert",
    "sg:classifiers":[
        {
            "category":"Shopping",
            "subcategory":"Pharmacy",
            "type":"Retail Goods"
        }
    ],
    "sg:phone":"+1 450 445 9000",
    "sg:postcode":"J3Y 1V5",
    "sg:province":"QC",
    "sg:tags":[
        "oxygen",
        "supply",
        "equipment",
        "therapy",
        "aid",
        "first"
    ],
    "wof:name":"Sos Technologies",
    "wof:placetype":"venue"
},
  "geometry": {"coordinates":[-73.4424667358,45.4833450317],"type":"Point"}
}