{
  "type": "Feature",
  "properties": {
    "addr:full":"295 Rue Saint-David Magog QC J1X 2Z8",
    "addr:housenumber":"295",
    "addr:postcode":"j1x 2z8",
    "addr:street":"Rue Saint-David",
    "iso:country":"CA",
    "sg:address":"295 Rue Saint-David",
    "sg:city":"Magog",
    "sg:classifiers":[
        {
            "category":"Organizations",
            "subcategory":"Professional Association",
            "type":"Services"
        }
    ],
    "sg:phone":"+1 819 868 1540",
    "sg:postcode":"J1X 2Z8",
    "sg:province":"QC",
    "wof:name":"Memphrerie Scouts Magog",
    "wof:placetype":"venue"
},
  "geometry": {"coordinates":[-72.137711,45.265591],"type":"Point"}
}