{
  "type": "Feature",
  "properties": {
    "addr:full":"Main St Fort Chipewyan AB T0P 1B0",
    "addr:postcode":"t0p 1b0",
    "addr:street":"Main St",
    "iso:country":"CA",
    "sg:address":"Main St",
    "sg:city":"Fort Chipewyan",
    "sg:classifiers":[
        {
            "category":"Organizations",
            "subcategory":"Religious Organization",
            "type":"Services"
        }
    ],
    "sg:phone":"+1 780 697 3555",
    "sg:postcode":"T0P 1B0",
    "sg:province":"AB",
    "sg:tags":[
        "church"
    ],
    "wof:name":"Fort Chipewyan Community Chr",
    "wof:placetype":"venue"
},
  "geometry": {"coordinates":[-111.15284729,58.71326828],"type":"Point"}
}