{
  "type": "Feature",
  "properties": {
    "iso:country":"CA",
    "sg:address":"101 Rue Saint-Pierre",
    "sg:city":"Saint-Constant",
    "sg:classifiers":[
        {
            "category":"Personal",
            "subcategory":"Beauty Salon",
            "type":"Services"
        }
    ],
    "sg:phone":"+1 450 632 8277",
    "sg:postcode":"J5A 1H5",
    "sg:province":"QC",
    "wof:name":"Coiffure Bo Look",
    "wof:placetype":"venue"
},
  "geometry": {"coordinates":[-73.566849,45.375969],"type":"Point"}
}