{
  "type": "Feature",
  "properties": {
    "iso:country":"CA",
    "sg:address":"18025 Yonge St # 6",
    "sg:city":"Newmarket",
    "sg:classifiers":[
        {
            "category":"Retail",
            "subcategory":"Veterinary Services",
            "type":"Services"
        }
    ],
    "sg:phone":"+1 905 836 4001",
    "sg:postcode":"L3Y 8C9",
    "sg:province":"ON",
    "sg:tags":[
        "veterinarian"
    ],
    "wof:name":"Armitage Animal Clinic",
    "wof:placetype":"venue"
},
  "geometry": {"coordinates":[-79.48304,44.066467],"type":"Point"}
}