{
  "type": "Feature",
  "properties": {
    "iso:country":"CA",
    "sg:address":"333 Kingscourt Ave",
    "sg:city":"Kingston",
    "sg:classifiers":[
        {
            "category":"Social Services",
            "type":"Services"
        }
    ],
    "sg:phone":"+1 613 549 6303",
    "sg:postcode":"K7K 4R4",
    "sg:province":"ON",
    "sg:tags":[
        "organization",
        "welfare"
    ],
    "wof:name":"Bridge House Inc",
    "wof:placetype":"venue"
},
  "geometry": {"coordinates":[-76.5018997192,44.252910614],"type":"Point"}
}