{
  "type": "Feature",
  "properties": {
    "addr:full":"Boundary Creek NB E1G 4L9",
    "addr:postcode":"e1g 4l9",
    "iso:country":"CA",
    "sg:city":"Boundary Creek",
    "sg:classifiers":[
        {
            "category":"Retail",
            "subcategory":"Auto Repair",
            "type":"Services"
        }
    ],
    "sg:phone":"+1 506 372 4461",
    "sg:postcode":"E1G 4L9",
    "sg:province":"NB",
    "sg:tags":[
        "lettering",
        "truck"
    ],
    "wof:name":"Custom Truck Painting Ltd",
    "wof:placetype":"venue"
},
  "geometry": {"coordinates":[-64.974411,46.055031],"type":"Point"}
}