{
  "type": "Feature",
  "properties": {
    "addr:full":"2365 Motorway Blvd Mississauga ON L5L 2M4",
    "addr:housenumber":"2365",
    "addr:postcode":"l5l 2m4",
    "addr:street":"Motorway Blvd",
    "iso:country":"CA",
    "sg:address":"2365 Motorway Blvd",
    "sg:city":"Mississauga",
    "sg:classifiers":[
        {
            "category":"Autos & Motor Vehicles",
            "subcategory":"Automobile Sales",
            "type":"Retail Goods"
        }
    ],
    "sg:phone":"+1 905 828 2004",
    "sg:postcode":"L5L 2M4",
    "sg:province":"ON",
    "sg:tags":[
        "car",
        "dealer"
    ],
    "wof:name":"Erin Dodge Chrysler Ltd",
    "wof:placetype":"venue"
},
  "geometry": {"coordinates":[-79.675735,43.530769],"type":"Point"}
}