{
  "type": "Feature",
  "properties": {
    "addr:full":"General Delivery Laurel ON L0N 1L0",
    "addr:postcode":"l0n 1l0",
    "iso:country":"CA",
    "sg:address":"General Delivery",
    "sg:city":"Laurel",
    "sg:classifiers":[
        {
            "category":"Retail",
            "subcategory":"Auto Repair",
            "type":"Services"
        }
    ],
    "sg:phone":"+1 519 941 5030",
    "sg:postcode":"L0N 1L0",
    "sg:province":"ON",
    "sg:tags":[
        "repairing",
        "automobile"
    ],
    "wof:name":"Laurel Motor Svc",
    "wof:placetype":"venue"
},
  "geometry": {"coordinates":[-80.20975494379999,43.9520568848],"type":"Point"}
}