{
  "type": "Feature",
  "properties": {
    "addr:full":"14211 Entertainment Blvd Richmond BC V6W 1K4",
    "addr:housenumber":"14211",
    "addr:postcode":"v6w 1k4",
    "addr:street":"Entertainment Blvd",
    "iso:country":"CA",
    "sg:address":"14211 Entertainment Blvd",
    "sg:city":"Richmond",
    "sg:classifiers":[
        {
            "category":"Arts & Performance",
            "subcategory":"Theater",
            "type":"Entertainment"
        }
    ],
    "sg:phone":"+1 604 277 5993",
    "sg:postcode":"V6W 1K4",
    "sg:province":"BC",
    "wof:name":"Famous Players Inc",
    "wof:placetype":"venue"
},
  "geometry": {"coordinates":[-123.066132,49.134056],"type":"Point"}
}