{
  "type": "Feature",
  "properties": {
    "addr:full":"5402 50th St Clyde AB T0G 0P0",
    "addr:housenumber":"5402",
    "addr:postcode":"t0g 0p0",
    "addr:street":"50Th St",
    "iso:country":"CA",
    "sg:address":"5402 50th St",
    "sg:city":"Clyde",
    "sg:classifiers":[
        {
            "category":"Education",
            "subcategory":"School",
            "type":"Public Place"
        }
    ],
    "sg:phone":"+1 780 348 5341",
    "sg:postcode":"T0G 0P0",
    "sg:province":"AB",
    "wof:name":"Eleanor Hall School",
    "wof:placetype":"venue"
},
  "geometry": {"coordinates":[-113.635941,54.15073],"type":"Point"}
}