{
  "type": "Feature",
  "properties": {
    "addr:full":"5 Victoria Marmora ON K0K 2M0",
    "addr:housenumber":"5",
    "addr:postcode":"k0k 2m0",
    "addr:street":"Victoria Marmora",
    "iso:country":"CA",
    "sg:address":"5 Victoria",
    "sg:city":"Marmora",
    "sg:classifiers":[
        {
            "category":"Food & Beverages",
            "subcategory":"Groceries & Convenience Stores",
            "type":"Retail Goods"
        }
    ],
    "sg:phone":"+1 613 472 1071",
    "sg:postcode":"K0K 2M0",
    "sg:province":"ON",
    "sg:tags":[
        "product"
    ],
    "wof:name":"Marmora Bulk Store",
    "wof:placetype":"venue"
},
  "geometry": {"coordinates":[-77.678291,44.485268],"type":"Point"}
}