{
  "type": "Feature",
  "properties": {
    "iso:country":"CA",
    "sg:city":"Winfield",
    "sg:classifiers":[
        {
            "category":"Organizations",
            "subcategory":"Professional Association",
            "type":"Services"
        }
    ],
    "sg:phone":"+1 250 766 4617",
    "sg:postcode":"V4V 1J2",
    "sg:province":"BC",
    "sg:tags":[
        "club"
    ],
    "wof:name":"Oceola Fish & Game Club",
    "wof:placetype":"venue"
},
  "geometry": {"coordinates":[-119.405601502,50.0245285034],"type":"Point"}
}