{
  "type": "Feature",
  "properties": {
    "addr:full":"375 Boul Marcotte Roberval QC G8H 1Z5",
    "addr:housenumber":"375",
    "addr:postcode":"g8h 1z5",
    "addr:street":"Boul Marcotte",
    "iso:country":"CA",
    "sg:address":"375 Boul Marcotte",
    "sg:city":"Roberval",
    "sg:classifiers":[
        {
            "category":"Real Estate",
            "subcategory":"Real Estate Agent",
            "type":"Services"
        }
    ],
    "sg:phone":"+1 418 275 6411",
    "sg:postcode":"G8H 1Z5",
    "sg:province":"QC",
    "wof:name":"Royal Lepage Saguenay",
    "wof:placetype":"venue"
},
  "geometry": {"coordinates":[-72.2235870361,48.5047225952],"type":"Point"}
}