{
  "type": "Feature",
  "properties": {
    "addr:full":"2221 Manitoba St Vancouver BC V5Y 3A3",
    "addr:housenumber":"2221",
    "addr:postcode":"v5y 3a3",
    "addr:street":"Manitoba St",
    "iso:country":"CA",
    "sg:address":"2221 Manitoba St",
    "sg:city":"Vancouver",
    "sg:classifiers":[
        {
            "category":"Professional",
            "subcategory":"Testing Lab",
            "type":"Services"
        }
    ],
    "sg:phone":"+1 604 879 3585",
    "sg:postcode":"V5Y 3A3",
    "sg:province":"BC",
    "sg:tags":[
        "consultant",
        "forensic",
        "engineer"
    ],
    "wof:name":"Baker Materials Engineering",
    "wof:placetype":"venue"
},
  "geometry": {"coordinates":[-123.10697937,49.2653770447],"type":"Point"}
}