{
  "type": "Feature",
  "properties": {
    "addr:full":"77 Gorge Rd W Victoria BC V9A 1L9",
    "addr:housenumber":"77",
    "addr:postcode":"v9a 1l9",
    "addr:street":"Gorge Rd W",
    "iso:country":"CA",
    "sg:address":"77 Gorge Rd W",
    "sg:city":"Victoria",
    "sg:classifiers":[
        {
            "category":"Real Estate",
            "subcategory":"Real Estate Operator",
            "type":"Services"
        }
    ],
    "sg:phone":"+1 250 383 1241",
    "sg:postcode":"V9A 1L9",
    "sg:province":"BC",
    "sg:tags":[
        "apartment"
    ],
    "wof:name":"Cedar Shores Apartments",
    "wof:placetype":"venue"
},
  "geometry": {"coordinates":[-123.38692500000001,48.443359],"type":"Point"}
}