{
  "type": "Feature",
  "properties": {
    "addr:full":"Saint-Blaise-Sur-Richelieu QC J0J 1W0",
    "addr:postcode":"j0j 1w0",
    "iso:country":"CA",
    "sg:city":"Saint-Blaise-Sur-Richelieu",
    "sg:classifiers":[
        {
            "category":"Autos & Motor Vehicles",
            "subcategory":"Boat Sales",
            "type":"Retail Goods"
        }
    ],
    "sg:phone":"+1 450 291 3444",
    "sg:postcode":"J0J 1W0",
    "sg:province":"QC",
    "sg:tags":[
        "dealer"
    ],
    "wof:name":"Bateau-Depot",
    "wof:placetype":"venue"
},
  "geometry": {"coordinates":[-73.24575042719999,45.4399604797],"type":"Point"}
}