{
  "type": "Feature",
  "properties": {
    "iso:country":"CA",
    "sg:address":"1011 North Service Rd E",
    "sg:city":"Oakville",
    "sg:classifiers":[
        {
            "category":"Freight",
            "type":"Transportation"
        }
    ],
    "sg:phone":"+1 905 845 7023",
    "sg:postcode":"L6H 1A6",
    "sg:province":"ON",
    "sg:tags":[
        "trucking"
    ],
    "wof:name":"Acs Logistics Transportation",
    "wof:placetype":"venue"
},
  "geometry": {"coordinates":[-79.6773300171,43.468120575],"type":"Point"}
}