{
  "type": "Feature",
  "properties": {
    "addr:full":"12 Queen St N Tottenham ON L0G 1W0",
    "addr:housenumber":"12",
    "addr:postcode":"l0g 1w0",
    "addr:street":"Queen St N",
    "iso:country":"CA",
    "sg:address":"12 Queen St N",
    "sg:city":"Tottenham",
    "sg:classifiers":[
        {
            "category":"Professional",
            "subcategory":"Accounting & Tax Preparation",
            "type":"Services"
        }
    ],
    "sg:phone":"+1 905 936 4242",
    "sg:postcode":"L0G 1W0",
    "sg:province":"ON",
    "sg:tags":[
        "return",
        "filing"
    ],
    "wof:name":"K J Hill Financial Svc",
    "wof:placetype":"venue"
},
  "geometry": {"coordinates":[-79.805954,44.022793],"type":"Point"}
}