{
  "type": "Feature",
  "properties": {
    "addr:full":"555 Av Du Palais Saint-Joseph-DE-Beauce QC G0S 2V0",
    "addr:postcode":"g0s 2v0",
    "addr:street":"555 Av Du Palais",
    "iso:country":"CA",
    "sg:address":"555 Av Du Palais",
    "sg:city":"Saint-Joseph-DE-Beauce",
    "sg:classifiers":[
        {
            "category":"Retail",
            "subcategory":"Auto Repair",
            "type":"Services"
        }
    ],
    "sg:phone":"+1 418 397 4555",
    "sg:postcode":"G0S 2V0",
    "sg:province":"QC",
    "sg:tags":[
        "repairing",
        "automobile"
    ],
    "wof:name":"Garage Jacques Pomerleau",
    "wof:placetype":"venue"
},
  "geometry": {"coordinates":[-70.88795471189999,46.3156776428],"type":"Point"}
}