{
  "type": "Feature",
  "properties": {
    "addr:full":"Almonte ON K0A 1A0",
    "addr:postcode":"k0a 1a0",
    "iso:country":"CA",
    "sg:city":"Almonte",
    "sg:classifiers":[
        {
            "category":"Personal",
            "subcategory":"Beauty Salon",
            "type":"Services"
        }
    ],
    "sg:phone":"+1 613 256 0516",
    "sg:postcode":"K0A 1A0",
    "sg:province":"ON",
    "wof:name":"Unique Styling",
    "wof:placetype":"venue"
},
  "geometry": {"coordinates":[-76.197975,45.225182],"type":"Point"}
}