{
  "type": "Feature",
  "properties": {
    "addr:full":"Edmonton AB T5P 4A3",
    "addr:postcode":"t5p 4a3",
    "iso:country":"CA",
    "sg:city":"Edmonton",
    "sg:classifiers":[
        {
            "category":"Restaurant",
            "type":"Food & Drink"
        }
    ],
    "sg:phone":"+1 780 486 7152",
    "sg:postcode":"T5P 4A3",
    "sg:province":"AB",
    "wof:name":"Mr Donair Submarines & Burgers",
    "wof:placetype":"venue"
},
  "geometry": {"coordinates":[-113.601181,53.541199],"type":"Point"}
}