{
  "type": "Feature",
  "properties": {
    "addr:full":"3658 Massey Dr Prince George BC V2N 2S8",
    "addr:housenumber":"3658",
    "addr:postcode":"v2n 2s8",
    "addr:street":"Massey Dr",
    "iso:country":"CA",
    "sg:address":"3658 Massey Dr",
    "sg:city":"Prince George",
    "sg:classifiers":[
        {
            "category":"Manufacturing",
            "subcategory":"Electronics",
            "type":"Manufacturing & Wholesale Goods"
        }
    ],
    "sg:phone":"+1 250 564 9774",
    "sg:postcode":"V2N 2S8",
    "sg:province":"BC",
    "sg:tags":[
        "sound",
        "instrument",
        "musical",
        "system"
    ],
    "wof:name":"Electron Sound & Percussion",
    "wof:placetype":"venue"
},
  "geometry": {"coordinates":[-122.790359497,53.899597168],"type":"Point"}
}