{
  "type": "Feature",
  "properties": {
    "addr:full":"3325 Boul DE LA Grande-Allee Boisbriand QC J7H 1H5",
    "addr:housenumber":"3325",
    "addr:postcode":"j7h 1h5",
    "addr:street":"Boul De La Grande-Allee",
    "iso:country":"CA",
    "sg:address":"3325 Boul DE LA Grande-Allee",
    "sg:city":"Boisbriand",
    "sg:classifiers":[
        {
            "category":"Social Services",
            "subcategory":"Child Care",
            "type":"Services"
        }
    ],
    "sg:phone":"+1 450 435 2828",
    "sg:postcode":"J7H 1H5",
    "sg:province":"QC",
    "wof:name":"Garderie Educative Coccinelle",
    "wof:placetype":"venue"
},
  "geometry": {"coordinates":[-73.85601043699999,45.6268959045],"type":"Point"}
}