{
  "type": "Feature",
  "properties": {
    "addr:full":"Calgary AB T2E 6Z7",
    "addr:postcode":"t2e 6z7",
    "iso:country":"CA",
    "sg:city":"Calgary",
    "sg:classifiers":[
        {
            "category":"Manufacturing",
            "subcategory":"Metals",
            "type":"Manufacturing & Wholesale Goods"
        }
    ],
    "sg:phone":"+1 403 275 0033",
    "sg:postcode":"T2E 6Z7",
    "sg:province":"AB",
    "sg:tags":[
        "spring"
    ],
    "wof:name":"Loyalty Metal Factory Ltd",
    "wof:placetype":"venue"
},
  "geometry": {"coordinates":[-114.03668999999999,51.102943],"type":"Point"}
}