{
  "type": "Feature",
  "properties": {
    "addr:full":"599 Colby Dr Waterloo ON N2V 1A1",
    "addr:housenumber":"599",
    "addr:postcode":"n2v 1a1",
    "addr:street":"Colby Dr",
    "iso:country":"CA",
    "sg:address":"599 Colby Dr",
    "sg:city":"Waterloo",
    "sg:classifiers":[
        {
            "category":"Real Estate",
            "subcategory":"Developer",
            "type":"Services"
        }
    ],
    "sg:phone":"+1 519 884 5800",
    "sg:postcode":"N2V 1A1",
    "sg:province":"ON",
    "sg:tags":[
        "company",
        "land"
    ],
    "wof:name":"Bender Developments Ltd",
    "wof:placetype":"venue"
},
  "geometry": {"coordinates":[-80.541298,43.503296],"type":"Point"}
}