{
  "type": "Feature",
  "properties": {
    "addr:full":"Calgary AB T2G 4C9",
    "addr:postcode":"t2g 4c9",
    "iso:country":"CA",
    "sg:city":"Calgary",
    "sg:classifiers":[
        {
            "category":"Manufacturing",
            "subcategory":"Metals",
            "type":"Manufacturing & Wholesale Goods"
        }
    ],
    "sg:phone":"+1 403 243 7568",
    "sg:postcode":"T2G 4C9",
    "sg:province":"AB",
    "sg:tags":[
        "steel",
        "stainless"
    ],
    "wof:name":"Dura Stainless & Sheet Metal",
    "wof:placetype":"venue"
},
  "geometry": {"coordinates":[-114.03130340600001,51.0140304565],"type":"Point"}
}