{
  "type": "Feature",
  "properties": {
    "iso:country":"CA",
    "sg:address":"667 Townline Rd N",
    "sg:city":"Courtice",
    "sg:classifiers":[
        {
            "category":"Building & Trades",
            "subcategory":"Plumbing",
            "type":"Services"
        }
    ],
    "sg:phone":"+1 905 728 6020",
    "sg:postcode":"L1E 2J4",
    "sg:province":"ON",
    "sg:tags":[
        "conditioning",
        "air",
        "system",
        "contractor"
    ],
    "wof:name":"Portable Home Comfort",
    "wof:placetype":"venue"
},
  "geometry": {"coordinates":[-78.821388,43.925297],"type":"Point"}
}