{
  "type": "Feature",
  "properties": {
    "addr:full":"450 Alexander St Vancouver BC V6A 1C5",
    "addr:housenumber":"450",
    "addr:postcode":"v6a 1c5",
    "addr:street":"Alexander St",
    "iso:country":"CA",
    "sg:address":"450 Alexander St",
    "sg:city":"Vancouver",
    "sg:classifiers":[
        {
            "category":"Wholesale",
            "subcategory":"Seafood",
            "type":"Manufacturing & Wholesale Goods"
        }
    ],
    "sg:phone":"+1 604 254 8251",
    "sg:postcode":"V6A 1C5",
    "sg:province":"BC",
    "wof:name":"Ocean Delight Seafood Ltd",
    "wof:placetype":"venue"
},
  "geometry": {"coordinates":[-123.09420799999999,49.283894],"type":"Point"}
}