{
  "type": "Feature",
  "properties": {
    "addr:full":"2800 Ingleton Ave Burnaby BC V5C 6G7",
    "addr:housenumber":"2800",
    "addr:postcode":"v5c 6g7",
    "addr:street":"Ingleton Ave",
    "iso:country":"CA",
    "sg:address":"2800 Ingleton Ave",
    "sg:city":"Burnaby",
    "sg:classifiers":[
        {
            "category":"Professional",
            "subcategory":"Business Services",
            "type":"Services"
        }
    ],
    "sg:phone":"+1 604 430 1401",
    "sg:postcode":"V5C 6G7",
    "sg:province":"BC",
    "sg:tags":[
        "drafting"
    ],
    "wof:name":"Affinity Drafting Inc",
    "wof:placetype":"venue"
},
  "geometry": {"coordinates":[-123.017792,49.259071],"type":"Point"}
}