{
  "type": "Feature",
  "properties": {
    "addr:full":"11300 River Rd Richmond BC V6X 1Z5",
    "addr:housenumber":"11300",
    "addr:postcode":"v6x 1z5",
    "addr:street":"River Rd",
    "iso:country":"CA",
    "sg:address":"11300 River Rd",
    "sg:city":"Richmond",
    "sg:classifiers":[
        {
            "category":"Manufacturing",
            "subcategory":"Glass & Minerals",
            "type":"Manufacturing & Wholesale Goods"
        }
    ],
    "sg:phone":"+1 604 273 4199",
    "sg:postcode":"V6X 1Z5",
    "sg:province":"BC",
    "wof:name":"Aca Glass Wholesale",
    "wof:placetype":"venue"
},
  "geometry": {"coordinates":[-123.09993,49.197395],"type":"Point"}
}