{
  "type": "Feature",
  "properties": {
    "addr:full":"180 Lincoln Rd Grand Falls-Windsor NL A2A 1P6",
    "addr:housenumber":"180",
    "addr:postcode":"a2a 1p6",
    "addr:street":"Lincoln Rd",
    "iso:country":"CA",
    "sg:address":"180 Lincoln Rd",
    "sg:city":"Grand Falls-Windsor",
    "sg:classifiers":[
        {
            "category":"Restaurant",
            "type":"Food & Drink"
        }
    ],
    "sg:phone":"+1 709 489 2390",
    "sg:postcode":"A2A 1P6",
    "sg:province":"NL",
    "wof:name":"Cathay Empress Restaurant",
    "wof:placetype":"venue"
},
  "geometry": {"coordinates":[-55.6495895386,48.9350662231],"type":"Point"}
}