{
  "type": "Feature",
  "properties": {
    "addr:full":"4993 Road 168 Bornholm ON N0K 1A0",
    "addr:housenumber":"4993",
    "addr:postcode":"n0k 1a0",
    "addr:street":"Road 168 Bornholm",
    "iso:country":"CA",
    "sg:address":"4993 Road 168",
    "sg:city":"Bornholm",
    "sg:classifiers":[
        {
            "category":"Wholesale",
            "subcategory":"Groceries",
            "type":"Manufacturing & Wholesale Goods"
        }
    ],
    "sg:phone":"+1 519 347 4320",
    "sg:postcode":"N0K 1A0",
    "sg:province":"ON",
    "sg:tags":[
        "food",
        "product",
        "manufacturer"
    ],
    "wof:name":"Harmony Organic Dairy Products",
    "wof:placetype":"venue"
},
  "geometry": {"coordinates":[-81.145065,43.531792],"type":"Point"}
}