{
  "type": "Feature",
  "properties": {
    "addr:full":"10151 179 St NW Edmonton AB T5S 1P9",
    "addr:housenumber":"10151",
    "addr:postcode":"t5s 1p9",
    "addr:street":"179 St Nw",
    "iso:country":"CA",
    "sg:address":"10151 179 St NW",
    "sg:city":"Edmonton",
    "sg:classifiers":[
        {
            "category":"Autos & Motor Vehicles",
            "subcategory":"Automobile Sales",
            "type":"Retail Goods"
        }
    ],
    "sg:phone":"+1 780 444 8645",
    "sg:postcode":"T5S 1P9",
    "sg:province":"AB",
    "sg:tags":[
        "car",
        "dealer"
    ],
    "wof:name":"Kia West Edmonton",
    "wof:placetype":"venue"
},
  "geometry": {"coordinates":[-113.630760193,53.5424728394],"type":"Point"}
}