{
  "type": "Feature",
  "properties": {
    "addr:full":"48 Boul Clermont Laval QC H7N 2Z2",
    "addr:housenumber":"48",
    "addr:postcode":"h7n 2z2",
    "addr:street":"Boul Clermont",
    "iso:country":"CA",
    "sg:address":"48 Boul Clermont",
    "sg:city":"Laval",
    "sg:classifiers":[
        {
            "category":"Food & Beverages",
            "subcategory":"Groceries & Convenience Stores",
            "type":"Retail Goods"
        }
    ],
    "sg:phone":"+1 450 688 2400",
    "sg:postcode":"H7N 2Z2",
    "sg:province":"QC",
    "sg:tags":[
        "grocer"
    ],
    "wof:name":"Marche Allaire",
    "wof:placetype":"venue"
},
  "geometry": {"coordinates":[-73.715744,45.545208],"type":"Point"}
}