{
  "type": "Feature",
  "properties": {
    "addr:full":"30 Rue Jacques-Cartier O Chicoutimi QC G7J 1E6",
    "addr:housenumber":"30",
    "addr:postcode":"g7j 1e6",
    "addr:street":"Rue Jacques-Cartier O",
    "iso:country":"CA",
    "sg:address":"30 Rue Jacques-Cartier O",
    "sg:city":"Chicoutimi",
    "sg:classifiers":[
        {
            "category":"Organizations",
            "subcategory":"Professional Association",
            "type":"Services"
        }
    ],
    "sg:phone":"+1 418 696 2871",
    "sg:postcode":"G7J 1E6",
    "sg:province":"QC",
    "wof:name":"Cafe Jeunesse",
    "wof:placetype":"venue"
},
  "geometry": {"coordinates":[-71.0675201416,48.4265098572],"type":"Point"}
}