{
  "type": "Feature",
  "properties": {
    "addr:full":"183 Rue Pie-Xi Thetford Mines QC G6G 3N3",
    "addr:housenumber":"183",
    "addr:postcode":"g6g 3n3",
    "addr:street":"Rue Pie-Xi",
    "iso:country":"CA",
    "sg:address":"183 Rue Pie-Xi",
    "sg:city":"Thetford Mines",
    "sg:classifiers":[
        {
            "category":"Professional",
            "subcategory":"Business Services",
            "type":"Services"
        }
    ],
    "sg:phone":"+1 418 335 2953",
    "sg:postcode":"G6G 3N3",
    "sg:province":"QC",
    "sg:tags":[
        "notary"
    ],
    "wof:name":"Martineau, Yves",
    "wof:placetype":"venue"
},
  "geometry": {"coordinates":[-71.30600699999999,46.089005],"type":"Point"}
}