{
  "type": "Feature",
  "properties": {
    "addr:full":"Orillia ON L3V 2V4",
    "addr:postcode":"l3v 2v4",
    "iso:country":"CA",
    "sg:city":"Orillia",
    "sg:classifiers":[
        {
            "category":"Retail",
            "subcategory":"Repair Shop",
            "type":"Services"
        }
    ],
    "sg:phone":"+1 705 327 1232",
    "sg:postcode":"L3V 2V4",
    "sg:province":"ON",
    "sg:tags":[
        "instrument",
        "musical"
    ],
    "wof:name":"North Winds",
    "wof:placetype":"venue"
},
  "geometry": {"coordinates":[-79.436226,44.597027],"type":"Point"}
}