{
  "type": "Feature",
  "properties": {
    "addr:full":"Alma QC G8B 3J4",
    "addr:postcode":"g8b 3j4",
    "iso:country":"CA",
    "sg:city":"Alma",
    "sg:classifiers":[
        {
            "category":"Retail",
            "subcategory":"Repair Shop",
            "type":"Services"
        }
    ],
    "sg:phone":"+1 418 668 2567",
    "sg:postcode":"G8B 3J4",
    "sg:province":"QC",
    "sg:tags":[
        "lock",
        "locksmith"
    ],
    "wof:name":"Serrurier Protec Inc",
    "wof:placetype":"venue"
},
  "geometry": {"coordinates":[-71.6592712402,48.5463600159],"type":"Point"}
}