{
  "type": "Feature",
  "properties": {
    "addr:full":"Maple Ridge BC V2X 3K2",
    "addr:postcode":"v2x 3k2",
    "iso:country":"CA",
    "sg:city":"Maple Ridge",
    "sg:classifiers":[
        {
            "category":"Personal",
            "subcategory":"Beauty Salon",
            "type":"Services"
        }
    ],
    "sg:phone":"+1 604 466 9896",
    "sg:postcode":"V2X 3K2",
    "sg:province":"BC",
    "wof:name":"Alchemist Hair Stylist Ltd",
    "wof:placetype":"venue"
},
  "geometry": {"coordinates":[-122.592849731,49.2202835083],"type":"Point"}
}