{
  "type": "Feature",
  "properties": {
    "iso:country":"CA",
    "sg:city":"Mississauga",
    "sg:classifiers":[
        {
            "category":"Personal",
            "subcategory":"Beauty Salon",
            "type":"Services"
        }
    ],
    "sg:phone":"+1 905 281 3857",
    "sg:postcode":"L5C 1C6",
    "sg:province":"ON",
    "sg:tags":[
        "manicuring"
    ],
    "wof:name":"Nail Beauty",
    "wof:placetype":"venue"
},
  "geometry": {"coordinates":[-79.64427185060001,43.5563545227],"type":"Point"}
}