{
  "type": "Feature",
  "properties": {
    "addr:full":"1345 Rue Andy Saint-Hubert QC J4T 1H1",
    "addr:housenumber":"1345",
    "addr:postcode":"j4t 1h1",
    "addr:street":"Rue Andy",
    "iso:country":"CA",
    "sg:address":"1345 Rue Andy",
    "sg:city":"Saint-Hubert",
    "sg:classifiers":[
        {
            "category":"Building & Trades",
            "subcategory":"Electrical",
            "type":"Services"
        }
    ],
    "sg:phone":"+1 450 656 4296",
    "sg:postcode":"J4T 1H1",
    "sg:province":"QC",
    "sg:tags":[
        "electric",
        "contractor"
    ],
    "wof:name":"Gilles Dorval Inc",
    "wof:placetype":"venue"
},
  "geometry": {"coordinates":[-73.456772,45.497856],"type":"Point"}
}