{
  "type": "Feature",
  "properties": {
    "addr:full":"North York ON M3J 2G6",
    "addr:postcode":"m3j 2g6",
    "iso:country":"CA",
    "sg:city":"North York",
    "sg:classifiers":[
        {
            "category":"Health Services",
            "subcategory":"Podiatrist",
            "type":"Services"
        }
    ],
    "sg:phone":"+1 416 635 2998",
    "sg:postcode":"M3J 2G6",
    "sg:province":"ON",
    "wof:name":"Warner, Jeffrey S DPM",
    "wof:placetype":"venue"
},
  "geometry": {"coordinates":[-79.4891281128,43.7637443542],"type":"Point"}
}