{
  "type": "Feature",
  "properties": {
    "addr:full":"Scarborough ON M1V 4W8",
    "addr:postcode":"m1v 4w8",
    "iso:country":"CA",
    "sg:city":"Scarborough",
    "sg:classifiers":[
        {
            "category":"Shopping",
            "subcategory":"Books",
            "type":"Retail Goods"
        }
    ],
    "sg:phone":"+1 416 299 7715",
    "sg:postcode":"M1V 4W8",
    "sg:province":"ON",
    "sg:tags":[
        "dealer"
    ],
    "wof:name":"Super Comics",
    "wof:placetype":"venue"
},
  "geometry": {"coordinates":[-79.28743,43.805229],"type":"Point"}
}