{
  "type": "Feature",
  "properties": {
    "addr:full":"1 Dunbar Ave Hamilton ON L8H 3E3",
    "addr:housenumber":"1",
    "addr:postcode":"l8h 3e3",
    "addr:street":"Dunbar Ave",
    "iso:country":"CA",
    "sg:address":"1 Dunbar Ave",
    "sg:city":"Hamilton",
    "sg:classifiers":[
        {
            "category":"Wholesale",
            "subcategory":"Electrical",
            "type":"Manufacturing & Wholesale Goods"
        }
    ],
    "sg:phone":"+1 905 544 5596",
    "sg:postcode":"L8H 3E3",
    "sg:province":"ON",
    "sg:tags":[
        "storage"
    ],
    "wof:name":"Hay Battery",
    "wof:placetype":"venue"
},
  "geometry": {"coordinates":[-79.80463399999999,43.251904],"type":"Point"}
}