{
  "type": "Feature",
  "properties": {
    "addr:full":"6 329 Rte Lachute QC J8H 4M7",
    "addr:housenumber":"6 329",
    "addr:postcode":"j8h 4m7",
    "addr:street":"Rte",
    "iso:country":"CA",
    "sg:address":"6 329 Rte",
    "sg:city":"Lachute",
    "sg:classifiers":[
        {
            "category":"Building & Trades",
            "subcategory":"Construction",
            "type":"Services"
        }
    ],
    "sg:phone":"+1 450 562 0072",
    "sg:postcode":"J8H 4M7",
    "sg:province":"QC",
    "sg:tags":[
        "home",
        "builder"
    ],
    "wof:name":"Maisons Roco Viceroy",
    "wof:placetype":"venue"
},
  "geometry": {"coordinates":[-74.340553,45.655846],"type":"Point"}
}