{
  "type": "Feature",
  "properties": {
    "addr:full":"5795 De Gasp\u00e9 Suite 100 Montreal H2S 2X3",
    "addr:housenumber":"5795",
    "addr:postcode":"h2s 2x3",
    "addr:street":"De Gaspe\u0301 Suite 100",
    "iso:country":"CA",
    "sg:address":"5795 De Gasp\u00e9 Suite 100",
    "sg:city":"Montreal",
    "sg:classifiers":[
        {
            "category":"Professional",
            "subcategory":"Computer Services",
            "type":"Services"
        }
    ],
    "sg:postcode":"H2S 2X3",
    "sg:tags":[
        "search-engine",
        "search",
        "plan",
        "planning",
        "trip",
        "travel"
    ],
    "sg:website":"http://www.hopper.to",
    "wof:name":"Hopper",
    "wof:placetype":"venue"
},
  "geometry": {"coordinates":[-73.5550157,45.5124334],"type":"Point"}
}