{
  "type": "Feature",
  "properties": {
    "addr:full":"159 Harborn Rd Mississauga ON L5B 1A6",
    "addr:housenumber":"159",
    "addr:postcode":"l5b 1a6",
    "addr:street":"Harborn Rd",
    "iso:country":"CA",
    "sg:address":"159 Harborn Rd",
    "sg:city":"Mississauga",
    "sg:classifiers":[
        {
            "category":"Freight",
            "type":"Transportation"
        }
    ],
    "sg:phone":"+1 905 273 6490",
    "sg:postcode":"L5B 1A6",
    "sg:province":"ON",
    "sg:tags":[
        "trucking"
    ],
    "wof:name":"Pavers Plus Inc",
    "wof:placetype":"venue"
},
  "geometry": {"coordinates":[-79.60479736329999,43.5667572021],"type":"Point"}
}