{
  "type": "Feature",
  "properties": {
    "iso:country":"CA",
    "sg:city":"Fonthill",
    "sg:classifiers":[
        {
            "category":"Health Services",
            "subcategory":"Doctor",
            "type":"Services"
        }
    ],
    "sg:phone":"+1 905 892 6322",
    "sg:postcode":"L0S 1E0",
    "sg:province":"ON",
    "sg:tags":[
        "dentist"
    ],
    "wof:name":"Fonthill Dental Clinic",
    "wof:placetype":"venue"
},
  "geometry": {"coordinates":[-79.2855148315,43.0445785522],"type":"Point"}
}