{
  "type": "Feature",
  "properties": {
    "iso:country":"CA",
    "sg:address":"15 Spruce Lane",
    "sg:city":"Strathmore",
    "sg:classifiers":[
        {
            "category":"Building & Trades",
            "subcategory":"Construction",
            "type":"Services"
        }
    ],
    "sg:phone":"+1 403 934 3727",
    "sg:postcode":"T1P 1J2",
    "sg:province":"AB",
    "sg:tags":[
        "excavating",
        "rental",
        "contractor"
    ],
    "wof:name":"Lar-Don Rentals Ltd",
    "wof:placetype":"venue"
},
  "geometry": {"coordinates":[-113.386863709,51.0334396362],"type":"Point"}
}