{
  "type": "Feature",
  "properties": {
    "addr:full":"855 10th Ave W Vancouver BC V5Z 1L7",
    "addr:housenumber":"855",
    "addr:postcode":"v5z 1l7",
    "addr:street":"10Th Ave W",
    "iso:country":"CA",
    "sg:address":"855 10th Ave W",
    "sg:city":"Vancouver",
    "sg:classifiers":[
        {
            "category":"Health Services",
            "subcategory":"Doctor",
            "type":"Services"
        }
    ],
    "sg:phone":"+1 604 875 5770",
    "sg:postcode":"V5Z 1L7",
    "sg:province":"BC",
    "sg:tags":[
        "physician",
        "surgeon"
    ],
    "wof:name":"Davis, Noelle L MD",
    "wof:placetype":"venue"
},
  "geometry": {"coordinates":[-123.123138,49.262535],"type":"Point"}
}