{
  "type": "Feature",
  "properties": {
    "addr:full":"459 St Mary's Rd Winnipeg MB R2M 3K8",
    "addr:housenumber":"459",
    "addr:postcode":"r2m 3k8",
    "addr:street":"St Mary'S Rd",
    "iso:country":"CA",
    "sg:address":"459 St Mary's Rd",
    "sg:city":"Winnipeg",
    "sg:classifiers":[
        {
            "category":"Retail",
            "subcategory":"Auto Repair",
            "type":"Services"
        }
    ],
    "sg:phone":"+1 204 233 6663",
    "sg:postcode":"R2M 3K8",
    "sg:province":"MB",
    "sg:tags":[
        "repairing",
        "automobile"
    ],
    "wof:name":"A-OK Holding Ltd",
    "wof:placetype":"venue"
},
  "geometry": {"coordinates":[-97.149361,49.88903],"type":"Point"}
}