{
  "type": "Feature",
  "properties": {
    "addr:full":"Orillia ON L3V 6H2",
    "addr:postcode":"l3v 6h2",
    "iso:country":"CA",
    "sg:city":"Orillia",
    "sg:classifiers":[
        {
            "category":"Retail",
            "subcategory":"Animal Services",
            "type":"Services"
        }
    ],
    "sg:phone":"+1 705 326 0883",
    "sg:postcode":"L3V 6H2",
    "sg:province":"ON",
    "sg:tags":[
        "pet",
        "boarding",
        "sitting"
    ],
    "wof:name":"North River Ranch Boarding",
    "wof:placetype":"venue"
},
  "geometry": {"coordinates":[-79.41822814939999,44.606590271],"type":"Point"}
}