{
  "type": "Feature",
  "properties": {
    "addr:full":"5 Stewart Cres Leamington ON N8H 3G1",
    "addr:housenumber":"5",
    "addr:postcode":"n8h 3g1",
    "addr:street":"Stewart Cres",
    "iso:country":"CA",
    "sg:address":"5 Stewart Cres",
    "sg:city":"Leamington",
    "sg:classifiers":[
        {
            "category":"Wholesale",
            "subcategory":"Hardware",
            "type":"Manufacturing & Wholesale Goods"
        }
    ],
    "sg:phone":"+1 519 326 5572",
    "sg:postcode":"N8H 3G1",
    "sg:province":"ON",
    "sg:tags":[
        "used",
        "boiler"
    ],
    "wof:name":"Industrial Boiler Specialties",
    "wof:placetype":"venue"
},
  "geometry": {"coordinates":[-82.603058,42.032078],"type":"Point"}
}