{
  "type": "Feature",
  "properties": {
    "addr:full":"145 Guildwood Pky Scarborough ON M1E 1P5",
    "addr:housenumber":"145",
    "addr:postcode":"m1e 1p5",
    "addr:street":"Guildwood Pky",
    "iso:country":"CA",
    "sg:address":"145 Guildwood Pky",
    "sg:city":"Scarborough",
    "sg:classifiers":[
        {
            "category":"Education",
            "subcategory":"School",
            "type":"Public Place"
        }
    ],
    "sg:phone":"+1 416 396 6820",
    "sg:postcode":"M1E 1P5",
    "sg:province":"ON",
    "sg:tags":[
        "technical",
        "institute",
        "college",
        "junior"
    ],
    "wof:name":"Sir Wilfrid Laurier Collegiate",
    "wof:placetype":"venue"
},
  "geometry": {"coordinates":[-79.19807400000001,43.747665],"type":"Point"}
}