{
  "type": "Feature",
  "properties": {
    "addr:full":"310 Mountain St S Killarney MB R0K 1G0",
    "addr:housenumber":"310",
    "addr:postcode":"r0k 1g0",
    "addr:street":"Mountain St S",
    "iso:country":"CA",
    "sg:address":"310 Mountain St S",
    "sg:city":"Killarney",
    "sg:classifiers":[
        {
            "category":"Organizations",
            "subcategory":"Religious Organization",
            "type":"Services"
        }
    ],
    "sg:phone":"+1 204 523 4311",
    "sg:postcode":"R0K 1G0",
    "sg:province":"MB",
    "sg:tags":[
        "church"
    ],
    "wof:name":"Baptist Church",
    "wof:placetype":"venue"
},
  "geometry": {"coordinates":[-99.66426800000001,49.180199],"type":"Point"}
}