{
  "type": "Feature",
  "properties": {
    "iso:country":"CA",
    "sg:address":"108 Rue Du Christ-Roi",
    "sg:city":"Maniwaki",
    "sg:classifiers":[
        {
            "category":"Organizations",
            "subcategory":"Professional Association",
            "type":"Services"
        }
    ],
    "sg:phone":"+1 819 449 8137",
    "sg:postcode":"J9E 1C3",
    "sg:province":"QC",
    "wof:name":"Maison Amitie DE LA Haute",
    "wof:placetype":"venue"
},
  "geometry": {"coordinates":[-75.9846191406,46.3843994141],"type":"Point"}
}