{
  "type": "Feature",
  "properties": {
    "addr:full":"295 Rue Des Baladins Laval QC H7N 2E3",
    "addr:housenumber":"295",
    "addr:postcode":"h7n 2e3",
    "addr:street":"Rue Des Baladins",
    "iso:country":"CA",
    "sg:address":"295 Rue Des Baladins",
    "sg:city":"Laval",
    "sg:classifiers":[
        {
            "category":"Building & Trades",
            "subcategory":"Construction",
            "type":"Services"
        }
    ],
    "sg:phone":"+1 450 667 9216",
    "sg:postcode":"H7N 2E3",
    "sg:province":"QC",
    "sg:tags":[
        "repairing",
        "stone",
        "remodeling",
        "contractor"
    ],
    "wof:name":"Entreprises Valbourg Enr",
    "wof:placetype":"venue"
},
  "geometry": {"coordinates":[-73.69622,45.559605],"type":"Point"}
}