{
  "type": "Feature",
  "properties": {
    "addr:full":"Onoway AB T0E 1V0",
    "addr:postcode":"t0e 1v0",
    "iso:country":"CA",
    "sg:city":"Onoway",
    "sg:classifiers":[
        {
            "category":"Travel",
            "subcategory":"Campground",
            "type":"Entertainment"
        }
    ],
    "sg:phone":"+1 780 967 2173",
    "sg:postcode":"T0E 1V0",
    "sg:province":"AB",
    "sg:tags":[
        "resort"
    ],
    "wof:name":"Sandy Beach Family Campground",
    "wof:placetype":"venue"
},
  "geometry": {"coordinates":[-114.19152800000001,53.703018],"type":"Point"}
}