{
  "type": "Feature",
  "properties": {
    "addr:full":"838 Hwy 26 St Francois Xavier MB R4L 1A2",
    "addr:housenumber":"838",
    "addr:postcode":"r4l 1a2",
    "addr:street":"Hwy 26 St Francois Xavier",
    "iso:country":"CA",
    "sg:address":"838 Hwy 26",
    "sg:city":"St Francois Xavier",
    "sg:classifiers":[
        {
            "category":"Freight",
            "type":"Transportation"
        }
    ],
    "sg:phone":"+1 204 864 2724",
    "sg:postcode":"R4L 1A2",
    "sg:province":"MB",
    "sg:tags":[
        "trucking"
    ],
    "wof:name":"Rene's Trucking",
    "wof:placetype":"venue"
},
  "geometry": {"coordinates":[-97.90888200000001,50.059078],"type":"Point"}
}