{
  "type": "Feature",
  "properties": {
    "iso:country":"CA",
    "sg:address":"2279 Cranbrook St N",
    "sg:city":"Cranbrook",
    "sg:classifiers":[
        {
            "category":"Organizations",
            "subcategory":"Professional Association",
            "type":"Services"
        }
    ],
    "sg:phone":"+1 250 426 4161",
    "sg:postcode":"V1C 3T3",
    "sg:province":"BC",
    "wof:name":"Sam Steele Society",
    "wof:placetype":"venue"
},
  "geometry": {"coordinates":[-115.743141174,49.5332298279],"type":"Point"}
}