{
  "type": "Feature",
  "properties": {
    "addr:full":"844 Kingsway Sudbury ON P3B 2E5",
    "addr:housenumber":"844",
    "addr:postcode":"p3b 2e5",
    "addr:street":"Kingsway",
    "iso:country":"CA",
    "sg:address":"844 Kingsway",
    "sg:city":"Sudbury",
    "sg:classifiers":[
        {
            "category":"Restaurant",
            "type":"Food & Drink"
        }
    ],
    "sg:phone":"+1 705 674 0574",
    "sg:postcode":"P3B 2E5",
    "sg:province":"ON",
    "wof:name":"Apollo Restaurant & Tavern",
    "wof:placetype":"venue"
},
  "geometry": {"coordinates":[-80.969566,46.498821],"type":"Point"}
}