{
  "type": "Feature",
  "properties": {
    "iso:country":"CA",
    "sg:address":"221 Hanlan Rd",
    "sg:city":"Woodbridge",
    "sg:classifiers":[
        {
            "category":"Wholesale",
            "subcategory":"Construction Materials",
            "type":"Manufacturing & Wholesale Goods"
        }
    ],
    "sg:phone":"+1 905 851 0384",
    "sg:postcode":"L4L 3R7",
    "sg:province":"ON",
    "sg:tags":[
        "concrete",
        "form"
    ],
    "wof:name":"Atlas Concrete Accessories Ltd",
    "wof:placetype":"venue"
},
  "geometry": {"coordinates":[-79.5601730347,43.7697639465],"type":"Point"}
}