{
  "type": "Feature",
  "properties": {
    "addr:full":"55 Ontario St S Milton ON L9T 2M3",
    "addr:housenumber":"55",
    "addr:postcode":"l9t 2m3",
    "addr:street":"Ontario St S",
    "iso:country":"CA",
    "sg:address":"55 Ontario St S",
    "sg:city":"Milton",
    "sg:classifiers":[
        {
            "category":"Shopping",
            "subcategory":"Pharmacy",
            "type":"Retail Goods"
        }
    ],
    "sg:phone":"+1 905 878 4521",
    "sg:postcode":"L9T 2M3",
    "sg:province":"ON",
    "wof:name":"Shoppers Drug Mart",
    "wof:placetype":"venue"
},
  "geometry": {"coordinates":[-79.8761291504,43.5175056458],"type":"Point"}
}