{
  "type": "Feature",
  "properties": {
    "addr:full":"PO Box 7 Sexsmith AB T0H 3C0",
    "addr:housenumber":"po;7",
    "addr:postcode":"t0h 3c0",
    "addr:street":"Box",
    "iso:country":"CA",
    "sg:address":"PO Box 7",
    "sg:city":"Sexsmith",
    "sg:classifiers":[
        {
            "category":"Building & Trades",
            "subcategory":"Cleaning & Sanitation",
            "type":"Services"
        }
    ],
    "sg:phone":"+1 780 568 4534",
    "sg:postcode":"T0H 3C0",
    "sg:province":"AB",
    "sg:tags":[
        "janitor"
    ],
    "wof:name":"North Country Cleaners",
    "wof:placetype":"venue"
},
  "geometry": {"coordinates":[-118.780761719,55.3451118469],"type":"Point"}
}