{
  "type": "Feature",
  "properties": {
    "addr:full":"200 Fitch St # 4 Welland ON L3C 4V9",
    "addr:housenumber":"200",
    "addr:postcode":"l3c 4v9",
    "addr:street":"Fitch St # 4",
    "iso:country":"CA",
    "sg:address":"200 Fitch St # 4",
    "sg:city":"Welland",
    "sg:classifiers":[
        {
            "category":"Shopping",
            "subcategory":"Gifts & Souvenirs",
            "type":"Retail Goods"
        }
    ],
    "sg:phone":"+1 905 714 1236",
    "sg:postcode":"L3C 4V9",
    "sg:province":"ON",
    "sg:tags":[
        "shop",
        "basket",
        "cookie",
        "parcel"
    ],
    "wof:name":"Artful Cookie",
    "wof:placetype":"venue"
},
  "geometry": {"coordinates":[-79.263397,42.994576],"type":"Point"}
}