{
  "type": "Feature",
  "properties": {
    "iso:country":"CA",
    "sg:address":"528 Waterloo St",
    "sg:city":"Winnipeg",
    "sg:classifiers":[
        {
            "category":"Banks & Credit Unions",
            "subcategory":"Bank",
            "type":"Services"
        }
    ],
    "sg:phone":"+1 204 985 3740",
    "sg:postcode":"R3N 0T1",
    "sg:province":"MB",
    "wof:name":"Scotiabank",
    "wof:placetype":"venue"
},
  "geometry": {"coordinates":[-97.184441,49.863747],"type":"Point"}
}