{
  "type": "Feature",
  "properties": {
    "addr:full":"Surrey BC V3W 3A6",
    "addr:postcode":"v3w 3a6",
    "iso:country":"CA",
    "sg:city":"Surrey",
    "sg:classifiers":[
        {
            "category":"Home & Garden",
            "subcategory":"Carpets & Floor Coverings",
            "type":"Retail Goods"
        }
    ],
    "sg:phone":"+1 604 592 2100",
    "sg:postcode":"V3W 3A6",
    "sg:province":"BC",
    "sg:tags":[
        "dealer",
        "rug"
    ],
    "wof:name":"Best Carpet Ltd",
    "wof:placetype":"venue"
},
  "geometry": {"coordinates":[-122.871017456,49.1483764648],"type":"Point"}
}