{
  "type": "Feature",
  "properties": {
    "addr:full":"3029 Clayhill Rd Mississauga ON L5B 4L2",
    "addr:housenumber":"3029",
    "addr:postcode":"l5b 4l2",
    "addr:street":"Clayhill Rd",
    "iso:country":"CA",
    "sg:address":"3029 Clayhill Rd",
    "sg:city":"Mississauga",
    "sg:classifiers":[
        {
            "category":"Shopping",
            "subcategory":"Pharmacy",
            "type":"Retail Goods"
        }
    ],
    "sg:phone":"+1 905 615 8887",
    "sg:postcode":"L5B 4L2",
    "sg:province":"ON",
    "sg:tags":[
        "grocer"
    ],
    "wof:name":"Shoppers Drug Mart",
    "wof:placetype":"venue"
},
  "geometry": {"coordinates":[-79.62840300000001,43.57119],"type":"Point"}
}