{
  "type": "Feature",
  "properties": {
    "iso:country":"CA",
    "sg:address":"1183 Av Bernard",
    "sg:city":"Outremont",
    "sg:classifiers":[
        {
            "category":"Shopping",
            "subcategory":"Clothing, Apparel, & Fashions",
            "type":"Retail Goods"
        }
    ],
    "sg:phone":"+1 514 270 3626",
    "sg:postcode":"H2V 1V5",
    "sg:province":"QC",
    "sg:tags":[
        "item",
        "boutique"
    ],
    "wof:name":"Collections Claudine Lacour",
    "wof:placetype":"venue"
},
  "geometry": {"coordinates":[-73.608307,45.52084],"type":"Point"}
}