{
  "type": "Feature",
  "properties": {
    "addr:full":"1790 Kingsway Vancouver BC V5N 2S6",
    "addr:housenumber":"1790",
    "addr:postcode":"v5n 2s6",
    "addr:street":"Kingsway",
    "iso:country":"CA",
    "sg:address":"1790 Kingsway",
    "sg:city":"Vancouver",
    "sg:classifiers":[
        {
            "category":"Home & Garden",
            "subcategory":"Furniture",
            "type":"Retail Goods"
        }
    ],
    "sg:phone":"+1 604 875 6733",
    "sg:postcode":"V5N 2S6",
    "sg:province":"BC",
    "wof:name":"Red Rose Furniture",
    "wof:placetype":"venue"
},
  "geometry": {"coordinates":[-123.068146,49.246384],"type":"Point"}
}