{
  "type": "Feature",
  "properties": {
    "addr:full":"Edmonton AB T5S 1T6",
    "addr:postcode":"t5s 1t6",
    "iso:country":"CA",
    "sg:city":"Edmonton",
    "sg:classifiers":[
        {
            "category":"Retail",
            "subcategory":"Laundry & Dry Cleaning",
            "type":"Services"
        }
    ],
    "sg:phone":"+1 780 455 5931",
    "sg:postcode":"T5S 1T6",
    "sg:province":"AB",
    "sg:tags":[
        "cleaners",
        "rug",
        "carpet"
    ],
    "wof:name":"All Brite Carpet Care Ltd",
    "wof:placetype":"venue"
},
  "geometry": {"coordinates":[-113.68924,53.552742],"type":"Point"}
}