{
  "type": "Feature",
  "properties": {
    "addr:full":"44 Medford Ave Scarborough ON M1L 4G4",
    "addr:housenumber":"44",
    "addr:postcode":"m1l 4g4",
    "addr:street":"Medford Ave",
    "iso:country":"CA",
    "sg:address":"44 Medford Ave",
    "sg:city":"Scarborough",
    "sg:classifiers":[
        {
            "category":"Building & Trades",
            "subcategory":"Construction",
            "type":"Services"
        }
    ],
    "sg:phone":"+1 416 429 2623",
    "sg:postcode":"M1L 4G4",
    "sg:province":"ON",
    "sg:tags":[
        "excavating",
        "contractor"
    ],
    "wof:name":"Andy & Frank's Excavating",
    "wof:placetype":"venue"
},
  "geometry": {"coordinates":[-79.27256800000001,43.697132],"type":"Point"}
}