{
  "type": "Feature",
  "properties": {
    "addr:full":"1045 Cote Du Beaver Hall Montreal QC H2Z 1S5",
    "addr:housenumber":"1045",
    "addr:postcode":"h2z 1s5",
    "addr:street":"Cote Du Beaver Hall",
    "iso:country":"CA",
    "sg:address":"1045 Cote Du Beaver Hall",
    "sg:city":"Montreal",
    "sg:classifiers":[
        {
            "category":"Food & Beverages",
            "subcategory":"Bakery",
            "type":"Retail Goods"
        }
    ],
    "sg:phone":"+1 514 866 8412",
    "sg:postcode":"H2Z 1S5",
    "sg:province":"QC",
    "sg:tags":[
        "baker"
    ],
    "wof:name":"Bagel Expressions Beaver Hall",
    "wof:placetype":"venue"
},
  "geometry": {"coordinates":[-73.5644378662,45.5024337769],"type":"Point"}
}