{
  "type": "Feature",
  "properties": {
    "addr:full":"2762 Wall St Vancouver BC V5K 1A9",
    "addr:housenumber":"2762",
    "addr:postcode":"v5k 1a9",
    "addr:street":"Wall St",
    "iso:country":"CA",
    "sg:address":"2762 Wall St",
    "sg:city":"Vancouver",
    "sg:classifiers":[
        {
            "category":"Professional",
            "subcategory":"Advertising",
            "type":"Services"
        }
    ],
    "sg:phone":"+1 604 258 9084",
    "sg:postcode":"V5K 1A9",
    "sg:province":"BC",
    "sg:tags":[
        "counselor"
    ],
    "wof:name":"John Lynn Communications",
    "wof:placetype":"venue"
},
  "geometry": {"coordinates":[-123.047752,49.291714],"type":"Point"}
}