{
  "type": "Feature",
  "properties": {
    "addr:full":"311 6 Ave SW # 120 Calgary AB T2P 3H2",
    "addr:housenumber":"311",
    "addr:postcode":"t2p 3h2",
    "addr:street":"6 Ave Sw # 120",
    "iso:country":"CA",
    "sg:address":"311 6 Ave SW # 120",
    "sg:city":"Calgary",
    "sg:classifiers":[
        {
            "category":"Manufacturing",
            "subcategory":"Printing",
            "type":"Manufacturing & Wholesale Goods"
        }
    ],
    "sg:phone":"+1 403 263 7575",
    "sg:postcode":"T2P 3H2",
    "sg:province":"AB",
    "sg:tags":[
        "printer"
    ],
    "wof:name":"Color Right Now",
    "wof:placetype":"venue"
},
  "geometry": {"coordinates":[-114.068237,51.04744],"type":"Point"}
}