{
  "type": "Feature",
  "properties": {
    "addr:full":"2125 Boul Saint-Elzear O Laval QC H7L 3N7",
    "addr:housenumber":"2125",
    "addr:postcode":"h7l 3n7",
    "addr:street":"Boul Saint-Elzear O",
    "iso:country":"CA",
    "sg:address":"2125 Boul Saint-Elzear O",
    "sg:city":"Laval",
    "sg:classifiers":[
        {
            "category":"Building & Trades",
            "subcategory":"Construction",
            "type":"Services"
        }
    ],
    "sg:phone":"+1 450 688 2666",
    "sg:postcode":"H7L 3N7",
    "sg:province":"QC",
    "sg:tags":[
        "roofing",
        "contractor"
    ],
    "wof:name":"Toitures & Constr Robitaille",
    "wof:placetype":"venue"
},
  "geometry": {"coordinates":[-73.7515792847,45.5828323364],"type":"Point"}
}