{
  "type": "Feature",
  "properties": {
    "addr:full":"1114 Av Moncton Quebec QC G1S 2Y8",
    "addr:housenumber":"1114",
    "addr:postcode":"g1s 2y8",
    "addr:street":"Av Moncton",
    "iso:country":"CA",
    "sg:address":"1114 Av Moncton",
    "sg:city":"Quebec",
    "sg:classifiers":[
        {
            "category":"Real Estate",
            "subcategory":"Surveying",
            "type":"Services"
        }
    ],
    "sg:phone":"+1 418 681 8064",
    "sg:postcode":"G1S 2Y8",
    "sg:province":"QC",
    "sg:tags":[
        "building",
        "contractor"
    ],
    "wof:name":"Arpentage Alain Paquet",
    "wof:placetype":"venue"
},
  "geometry": {"coordinates":[-71.2315979004,46.7991790771],"type":"Point"}
}