{
  "type": "Feature",
  "properties": {
    "addr:full":"121 Oxford St E London ON N6A 1T4",
    "addr:housenumber":"121",
    "addr:postcode":"n6a 1t4",
    "addr:street":"Oxford St E",
    "iso:country":"CA",
    "sg:address":"121 Oxford St E",
    "sg:city":"London",
    "sg:classifiers":[
        {
            "category":"Retail",
            "subcategory":"Veterinary Services",
            "type":"Services"
        }
    ],
    "sg:phone":"+1 519 672 0672",
    "sg:postcode":"N6A 1T4",
    "sg:province":"ON",
    "sg:tags":[
        "veterinarian"
    ],
    "wof:name":"Talbot Animal Hospital",
    "wof:placetype":"venue"
},
  "geometry": {"coordinates":[-81.2571716309,42.9941482544],"type":"Point"}
}