{
  "type": "Feature",
  "properties": {
    "addr:full":"Scarborough ON M1S 5E8",
    "addr:postcode":"m1s 5e8",
    "iso:country":"CA",
    "sg:city":"Scarborough",
    "sg:classifiers":[
        {
            "category":"Freight",
            "type":"Transportation"
        }
    ],
    "sg:phone":"+1 416 291 3860",
    "sg:postcode":"M1S 5E8",
    "sg:province":"ON",
    "sg:tags":[
        "courier"
    ],
    "wof:name":"Quik Express Delivery",
    "wof:placetype":"venue"
},
  "geometry": {"coordinates":[-79.25163999999999,43.81126],"type":"Point"}
}