{
  "type": "Feature",
  "properties": {
    "addr:full":"2710 Tranquille Rd Kamloops BC V2B 7Y2",
    "addr:housenumber":"2710",
    "addr:postcode":"bc v2b 7y2",
    "addr:street":"Tranquille Rd",
    "iso:country":"CA",
    "sg:address":"2710 Tranquille Rd",
    "sg:city":"Kamloops",
    "sg:classifiers":[
        {
            "category":"Home & Garden",
            "subcategory":"Building Materials",
            "type":"Retail Goods"
        }
    ],
    "sg:phone":"+1 250 376 4812",
    "sg:postcode":"V2B 7Y2",
    "sg:province":"BC",
    "sg:tags":[
        "windows"
    ],
    "wof:name":"Desmond Industries Inc",
    "wof:placetype":"venue"
},
  "geometry": {"coordinates":[-120.429092407,50.7021751404],"type":"Point"}
}