{
  "type": "Feature",
  "properties": {
    "addr:full":"76 Provost St New Glasgow NS B2H 2P4",
    "addr:housenumber":"76",
    "addr:postcode":"b2h 2p4",
    "addr:street":"Provost St",
    "iso:country":"CA",
    "sg:address":"76 Provost St",
    "sg:city":"New Glasgow",
    "sg:classifiers":[
        {
            "category":"Professional",
            "subcategory":"Computer Services",
            "type":"Services"
        }
    ],
    "sg:phone":"+1 902 752 3550",
    "sg:postcode":"B2H 2P4",
    "sg:province":"NS",
    "sg:tags":[
        "internet"
    ],
    "wof:name":"Can Connect Inc",
    "wof:placetype":"venue"
},
  "geometry": {"coordinates":[-62.644501,45.588509],"type":"Point"}
}