{
  "type": "Feature",
  "properties": {
    "iso:country":"CA",
    "sg:address":"672 Av Grosvenor",
    "sg:city":"Westmount",
    "sg:classifiers":[
        {
            "category":"Wholesale",
            "subcategory":"Durable Goods & Equipment",
            "type":"Manufacturing & Wholesale Goods"
        }
    ],
    "sg:phone":"+1 514 482 6265",
    "sg:postcode":"H3Y 2S8",
    "sg:province":"QC",
    "sg:tags":[
        "exporter"
    ],
    "wof:name":"Synthesia Trading Inc",
    "wof:placetype":"venue"
},
  "geometry": {"coordinates":[-73.61307525629999,45.4841995239],"type":"Point"}
}