{
  "type": "Feature",
  "properties": {
    "addr:full":"Mount Stewart PE C0A 1T0",
    "addr:postcode":"c0a 1t0",
    "iso:country":"CA",
    "sg:city":"Mount Stewart",
    "sg:classifiers":[
        {
            "category":"Recreation",
            "type":"Entertainment"
        }
    ],
    "sg:phone":"+1 902 676 2528",
    "sg:postcode":"C0A 1T0",
    "sg:province":"PE",
    "sg:tags":[
        "center"
    ],
    "wof:name":"Tracadie Community Ctr",
    "wof:placetype":"venue"
},
  "geometry": {"coordinates":[-62.862743,46.36451],"type":"Point"}
}