{
  "type": "Feature",
  "properties": {
    "addr:full":"Dalhousie NB E8C 1B7",
    "addr:postcode":"e8c 1b7",
    "iso:country":"CA",
    "sg:city":"Dalhousie",
    "sg:classifiers":[
        {
            "category":"Professional",
            "subcategory":"Accounting & Tax Preparation",
            "type":"Services"
        }
    ],
    "sg:phone":"+1 506 684 5324",
    "sg:postcode":"E8C 1B7",
    "sg:province":"NB",
    "sg:tags":[
        "return",
        "filing"
    ],
    "wof:name":"Liberty Tax Svc",
    "wof:placetype":"venue"
},
  "geometry": {"coordinates":[-66.37897491459999,48.0655136108],"type":"Point"}
}