{
  "type": "Feature",
  "properties": {
    "iso:country":"CA",
    "sg:address":"2000 Rue Cours Le Corbusier",
    "sg:city":"Boisbriand",
    "sg:classifiers":[
        {
            "category":"Shopping",
            "subcategory":"Pharmacy",
            "type":"Retail Goods"
        }
    ],
    "sg:phone":"+1 450 435 8242",
    "sg:postcode":"J7G 3E8",
    "sg:province":"QC",
    "wof:name":"Pharmacie Uniprix",
    "wof:placetype":"venue"
},
  "geometry": {"coordinates":[-73.8388824463,45.6120414734],"type":"Point"}
}