{
  "type": "Feature",
  "properties": {
    "iso:country":"CA",
    "sg:address":"PO Box 240",
    "sg:city":"Warburg",
    "sg:classifiers":[
        {
            "category":"Mining & Drilling",
            "type":"Manufacturing & Wholesale Goods"
        }
    ],
    "sg:phone":"+1 780 848 2100",
    "sg:postcode":"T0C 2T0",
    "sg:province":"AB",
    "sg:tags":[
        "company",
        "oil"
    ],
    "wof:name":"Talisman Energy Inc",
    "wof:placetype":"venue"
},
  "geometry": {"coordinates":[-114.318642,53.181034],"type":"Point"}
}