{
  "type": "Feature",
  "properties": {
    "addr:full":"822 Shuswap Ave # B Chase BC V0E 1M0",
    "addr:housenumber":"822",
    "addr:postcode":"bc v0e 1m0",
    "addr:street":"Shuswap Ave # B Chase",
    "iso:country":"CA",
    "sg:address":"822 Shuswap Ave # B",
    "sg:city":"Chase",
    "sg:classifiers":[
        {
            "category":"Professional",
            "subcategory":"Employment Agencies",
            "type":"Services"
        }
    ],
    "sg:phone":"+1 250 679 8448",
    "sg:postcode":"V0E 1M0",
    "sg:province":"BC",
    "sg:tags":[
        "opportunity"
    ],
    "wof:name":"Chase & District Employment",
    "wof:placetype":"venue"
},
  "geometry": {"coordinates":[-119.68804900000001,50.820293],"type":"Point"}
}