{
  "type": "Feature",
  "properties": {
    "iso:country":"CA",
    "sg:address":"13561 King George Hwy",
    "sg:city":"Surrey",
    "sg:classifiers":[
        {
            "category":"Wholesale",
            "subcategory":"Durable Goods & Equipment",
            "type":"Manufacturing & Wholesale Goods"
        }
    ],
    "sg:phone":"+1 604 589 6053",
    "sg:postcode":"V3T 2V1",
    "sg:province":"BC",
    "sg:tags":[
        "importer"
    ],
    "wof:name":"Duran Imports",
    "wof:placetype":"venue"
},
  "geometry": {"coordinates":[-122.846160889,49.1997489929],"type":"Point"}
}