{
  "type": "Feature",
  "properties": {
    "addr:full":"Langley BC V2Y 1M8",
    "addr:postcode":"v2y 1m8",
    "iso:country":"CA",
    "sg:city":"Langley",
    "sg:classifiers":[
        {
            "category":"Wholesale",
            "subcategory":"Office Equipment",
            "type":"Manufacturing & Wholesale Goods"
        }
    ],
    "sg:phone":"+1 604 532 0500",
    "sg:postcode":"V2Y 1M8",
    "sg:province":"BC",
    "sg:tags":[
        "register",
        "cash",
        "supply"
    ],
    "wof:name":"Bwi Business World Inc",
    "wof:placetype":"venue"
},
  "geometry": {"coordinates":[-122.665412903,49.1188545227],"type":"Point"}
}