{
  "type": "Feature",
  "properties": {
    "addr:full":"Vancouver BC V6B 1G1",
    "addr:postcode":"v6b 1g1",
    "iso:country":"CA",
    "sg:city":"Vancouver",
    "sg:classifiers":[
        {
            "category":"Insurance",
            "subcategory":"Insurance Agent",
            "type":"Services"
        }
    ],
    "sg:phone":"+1 604 261 9200",
    "sg:postcode":"V6B 1G1",
    "sg:province":"BC",
    "wof:name":"Dolphin Insurance",
    "wof:placetype":"venue"
},
  "geometry": {"coordinates":[-123.11183200000001,49.285404],"type":"Point"}
}