{
  "type": "Feature",
  "properties": {
    "addr:full":"1 Cameron Ave Swastika ON P0K 1T0",
    "addr:housenumber":"1",
    "addr:postcode":"p0k 1t0",
    "addr:street":"Cameron Ave",
    "iso:country":"CA",
    "sg:address":"1 Cameron Ave",
    "sg:city":"Swastika",
    "sg:classifiers":[
        {
            "category":"Professional",
            "subcategory":"Testing Lab",
            "type":"Services"
        }
    ],
    "sg:phone":"+1 705 642 3244",
    "sg:postcode":"P0K 1T0",
    "sg:province":"ON",
    "sg:tags":[
        "assayer",
        "assaying"
    ],
    "wof:name":"Swastika Laboratories Ltd",
    "wof:placetype":"venue"
},
  "geometry": {"coordinates":[-80.1040420532,48.1078147888],"type":"Point"}
}