{
  "type": "Feature",
  "properties": {
    "addr:full":"91 Kersdale Ave York ON M6M 1E4",
    "addr:housenumber":"91",
    "addr:postcode":"m6m 1e4",
    "addr:street":"Kersdale Ave",
    "iso:country":"CA",
    "sg:address":"91 Kersdale Ave",
    "sg:city":"York",
    "sg:classifiers":[
        {
            "category":"Organizations",
            "subcategory":"Professional Association",
            "type":"Services"
        }
    ],
    "sg:phone":"+1 416 653 1361",
    "sg:postcode":"M6M 1E4",
    "sg:province":"ON",
    "wof:name":"Russian Canadian Cultural Soc",
    "wof:placetype":"venue"
},
  "geometry": {"coordinates":[-79.468307,43.683098],"type":"Point"}
}