{
  "type": "Feature",
  "properties": {
    "addr:full":"1295 Hammond St North Bay ON P1B 2J2",
    "addr:housenumber":"1295",
    "addr:postcode":"p1b 2j2",
    "addr:street":"Hammond St",
    "iso:country":"CA",
    "sg:address":"1295 Hammond St",
    "sg:city":"North Bay",
    "sg:classifiers":[
        {
            "category":"Home & Garden",
            "subcategory":"Home Furnishings",
            "type":"Retail Goods"
        }
    ],
    "sg:phone":"+1 705 472 7489",
    "sg:postcode":"P1B 2J2",
    "sg:province":"ON",
    "sg:tags":[
        "bathroom",
        "fixture",
        "accessory"
    ],
    "wof:name":"Pixie Shop Bath",
    "wof:placetype":"venue"
},
  "geometry": {"coordinates":[-79.44654800000001,46.311104],"type":"Point"}
}