{
  "type": "Feature",
  "properties": {
    "addr:full":"Maple Ridge BC V2X 1X6",
    "addr:postcode":"v2x 1x6",
    "iso:country":"CA",
    "sg:city":"Maple Ridge",
    "sg:classifiers":[
        {
            "category":"Retail",
            "subcategory":"Laundry & Dry Cleaning",
            "type":"Services"
        }
    ],
    "sg:phone":"+1 604 465 6828",
    "sg:postcode":"V2X 1X6",
    "sg:province":"BC",
    "wof:name":"Home Comfort Coin Laundry",
    "wof:placetype":"venue"
},
  "geometry": {"coordinates":[-122.648040772,49.2199287415],"type":"Point"}
}