{
  "type": "Feature",
  "properties": {
    "addr:full":"2901 Pinnacles Rd Quesnel BC V2J 7G9",
    "addr:housenumber":"2901",
    "addr:postcode":"v2j 7g9",
    "addr:street":"Pinnacles Rd",
    "iso:country":"CA",
    "sg:address":"2901 Pinnacles Rd",
    "sg:city":"Quesnel",
    "sg:classifiers":[
        {
            "category":"Bars & Pubs",
            "type":"Food & Drink"
        }
    ],
    "sg:phone":"+1 250 249 5595",
    "sg:postcode":"V2J 7G9",
    "sg:province":"BC",
    "wof:name":"Hitchin Post Pub",
    "wof:placetype":"venue"
},
  "geometry": {"coordinates":[-122.498245,52.978119],"type":"Point"}
}