{
  "type": "Feature",
  "properties": {
    "addr:full":"765 Rue Pierre-Piche Boucherville QC J4B 3H8",
    "addr:housenumber":"765",
    "addr:postcode":"j4b 3h8",
    "addr:street":"Rue Pierre-Piche",
    "iso:country":"CA",
    "sg:address":"765 Rue Pierre-Piche",
    "sg:city":"Boucherville",
    "sg:classifiers":[
        {
            "category":"Organizations",
            "subcategory":"Religious Organization",
            "type":"Services"
        }
    ],
    "sg:phone":"+1 450 655 2462",
    "sg:postcode":"J4B 3H8",
    "sg:province":"QC",
    "sg:tags":[
        "church"
    ],
    "wof:name":"Holy Cross Parish",
    "wof:placetype":"venue"
},
  "geometry": {"coordinates":[-73.44528961180001,45.6189079285],"type":"Point"}
}