{
  "type": "Feature",
  "properties": {
    "addr:full":"1000 Fort William Rd Thunder Bay ON P7B 6B9",
    "addr:housenumber":"1000",
    "addr:postcode":"p7b 6b9",
    "addr:street":"Fort William Rd",
    "iso:country":"CA",
    "sg:address":"1000 Fort William Rd",
    "sg:city":"Thunder Bay",
    "sg:classifiers":[
        {
            "category":"Shopping",
            "subcategory":"Clothing, Apparel, & Fashions",
            "type":"Retail Goods"
        }
    ],
    "sg:phone":"+1 807 623 3413",
    "sg:postcode":"P7B 6B9",
    "sg:province":"ON",
    "sg:tags":[
        "accessory"
    ],
    "wof:name":"Claire's Boutiques",
    "wof:placetype":"venue"
},
  "geometry": {"coordinates":[-89.242188,48.403786],"type":"Point"}
}