{
  "type": "Feature",
  "properties": {
    "addr:full":"4304 Rue Lalande Mirabel QC J7N 2Z4",
    "addr:housenumber":"4304",
    "addr:postcode":"j7n 2z4",
    "addr:street":"Rue Lalande",
    "iso:country":"CA",
    "sg:address":"4304 Rue Lalande",
    "sg:city":"Mirabel",
    "sg:classifiers":[
        {
            "category":"Building & Trades",
            "subcategory":"Construction",
            "type":"Services"
        }
    ],
    "sg:phone":"+1 450 258 1850",
    "sg:postcode":"J7N 2Z4",
    "sg:province":"QC",
    "sg:tags":[
        "contractor"
    ],
    "wof:name":"Innovation Renovation Enr",
    "wof:placetype":"venue"
},
  "geometry": {"coordinates":[-74.19296300000001,45.602913],"type":"Point"}
}