{
  "type": "Feature",
  "properties": {
    "addr:full":"10626 Av Peloquin Montreal QC H2C 2K3",
    "addr:housenumber":"10626",
    "addr:postcode":"h2c 2k3",
    "addr:street":"Av Peloquin",
    "iso:country":"CA",
    "sg:address":"10626 Av Peloquin",
    "sg:city":"Montreal",
    "sg:classifiers":[
        {
            "category":"Food & Beverages",
            "subcategory":"Groceries & Convenience Stores",
            "type":"Retail Goods"
        }
    ],
    "sg:phone":"+1 514 388 1054",
    "sg:postcode":"H2C 2K3",
    "sg:province":"QC",
    "sg:tags":[
        "grocer"
    ],
    "wof:name":"Marche Vincent Inc",
    "wof:placetype":"venue"
},
  "geometry": {"coordinates":[-73.6651687622,45.5584831238],"type":"Point"}
}