{
  "type": "Feature",
  "properties": {
    "addr:full":"701 Barton St E Hamilton ON L8L 3A5",
    "addr:housenumber":"701",
    "addr:postcode":"l8l 3a5",
    "addr:street":"Barton St E",
    "iso:country":"CA",
    "sg:address":"701 Barton St E",
    "sg:city":"Hamilton",
    "sg:classifiers":[
        {
            "category":"Manufacturing",
            "subcategory":"Food",
            "type":"Manufacturing & Wholesale Goods"
        }
    ],
    "sg:phone":"+1 905 547 9334",
    "sg:postcode":"L8L 3A5",
    "sg:province":"ON",
    "sg:tags":[
        "confectionery",
        "candy"
    ],
    "wof:name":"Wawel Goplana Chocolates",
    "wof:placetype":"venue"
},
  "geometry": {"coordinates":[-79.835747,43.256508],"type":"Point"}
}