{
  "type": "Feature",
  "properties": {
    "addr:full":"1410 Venables St Vancouver BC V5L 2G5",
    "addr:housenumber":"1410",
    "addr:postcode":"v5l 2g5",
    "addr:street":"Venables St",
    "iso:country":"CA",
    "sg:address":"1410 Venables St",
    "sg:city":"Vancouver",
    "sg:classifiers":[
        {
            "category":"Manufacturing",
            "subcategory":"Apparel",
            "type":"Manufacturing & Wholesale Goods"
        }
    ],
    "sg:phone":"+1 604 255 0832",
    "sg:postcode":"V5L 2G5",
    "sg:province":"BC",
    "wof:name":"Parker Clothing Mfg Ltd",
    "wof:placetype":"venue"
},
  "geometry": {"coordinates":[-123.075447,49.276638],"type":"Point"}
}