{
  "type": "Feature",
  "properties": {
    "addr:full":"Mississauga ON L4V 1W1",
    "addr:postcode":"l4v 1w1",
    "iso:country":"CA",
    "sg:city":"Mississauga",
    "sg:classifiers":[
        {
            "category":"Organizations",
            "subcategory":"Professional Association",
            "type":"Services"
        }
    ],
    "sg:phone":"+1 905 678 7748",
    "sg:postcode":"L4V 1W1",
    "sg:province":"ON",
    "wof:name":"Canadian Plastics Industry",
    "wof:placetype":"venue"
},
  "geometry": {"coordinates":[-79.608109,43.686043],"type":"Point"}
}