{
  "type": "Feature",
  "properties": {
    "addr:full":"378 Rue Main Gatineau QC J8P 5K7",
    "addr:housenumber":"378",
    "addr:postcode":"j8p 5k7",
    "addr:street":"Rue Main",
    "iso:country":"CA",
    "sg:address":"378 Rue Main",
    "sg:city":"Gatineau",
    "sg:classifiers":[
        {
            "category":"Shopping",
            "subcategory":"Clothing, Apparel, & Fashions",
            "type":"Retail Goods"
        }
    ],
    "sg:phone":"+1 819 663 6414",
    "sg:postcode":"J8P 5K7",
    "sg:province":"QC",
    "sg:tags":[
        "dancing",
        "supply"
    ],
    "wof:name":"Boutique Deka-Danse",
    "wof:placetype":"venue"
},
  "geometry": {"coordinates":[-75.65173299999999,45.491383],"type":"Point"}
}