{
  "type": "Feature",
  "properties": {
    "addr:full":"701 23 Ave Nisku AB T9E 7Y5",
    "addr:postcode":"t9e 7y5",
    "addr:street":"701 23 Ave",
    "iso:country":"CA",
    "sg:address":"701 23 Ave",
    "sg:city":"Nisku",
    "sg:classifiers":[
        {
            "category":"Mining & Drilling",
            "type":"Manufacturing & Wholesale Goods"
        }
    ],
    "sg:phone":"+1 780 955 2128",
    "sg:postcode":"T9E 7Y5",
    "sg:province":"AB",
    "sg:tags":[
        "field",
        "oil"
    ],
    "wof:name":"Nisku Rig Repair",
    "wof:placetype":"venue"
},
  "geometry": {"coordinates":[-113.520546,53.343994],"type":"Point"}
}