{
  "type": "Feature",
  "properties": {
    "iso:country":"CA",
    "sg:city":"Calgary",
    "sg:classifiers":[
        {
            "category":"Retail",
            "subcategory":"Auto Repair",
            "type":"Services"
        }
    ],
    "sg:phone":"+1 403 277 6404",
    "sg:postcode":"T2M 4L5",
    "sg:province":"AB",
    "sg:tags":[
        "wrecker"
    ],
    "wof:name":"Chinook Towing Ltd",
    "wof:placetype":"venue"
},
  "geometry": {"coordinates":[-114.063194275,51.0450744629],"type":"Point"}
}