{
  "type": "Feature",
  "properties": {
    "addr:full":"Sherwood Park AB T8A 2A6",
    "addr:postcode":"t8a 2a6",
    "iso:country":"CA",
    "sg:city":"Sherwood Park",
    "sg:classifiers":[
        {
            "category":"Wholesale",
            "subcategory":"Machinery & Supplies",
            "type":"Manufacturing & Wholesale Goods"
        }
    ],
    "sg:phone":"+1 780 467 7696",
    "sg:postcode":"T8A 2A6",
    "sg:province":"AB",
    "sg:tags":[
        "water",
        "pump",
        "system"
    ],
    "wof:name":"Aqua-Pump Svc Ltd",
    "wof:placetype":"venue"
},
  "geometry": {"coordinates":[-113.29573822,53.5264015198],"type":"Point"}
}