{
  "type": "Feature",
  "properties": {
    "addr:full":"237 Watt St Winnipeg MB R2L 1S7",
    "addr:housenumber":"237",
    "addr:postcode":"r2l 1s7",
    "addr:street":"Watt St",
    "iso:country":"CA",
    "sg:address":"237 Watt St",
    "sg:city":"Winnipeg",
    "sg:classifiers":[
        {
            "category":"Food & Beverages",
            "subcategory":"Groceries & Convenience Stores",
            "type":"Retail Goods"
        }
    ],
    "sg:phone":"+1 204 669 3555",
    "sg:postcode":"R2L 1S7",
    "sg:province":"MB",
    "wof:name":"Sol Convenience Store",
    "wof:placetype":"venue"
},
  "geometry": {"coordinates":[-97.101845,49.912678],"type":"Point"}
}