{
  "type": "Feature",
  "properties": {
    "addr:full":"120 Mcculloch Dr Espanola ON P5E 1J1",
    "addr:housenumber":"120",
    "addr:postcode":"p5e 1j1",
    "addr:street":"Mcculloch Dr",
    "iso:country":"CA",
    "sg:address":"120 Mcculloch Dr",
    "sg:city":"Espanola",
    "sg:classifiers":[
        {
            "category":"Building & Trades",
            "subcategory":"Plumbing",
            "type":"Services"
        }
    ],
    "sg:phone":"+1 705 869 1683",
    "sg:postcode":"P5E 1J1",
    "sg:province":"ON",
    "sg:tags":[
        "contractor"
    ],
    "wof:name":"Garnet's Plumbing & Heating",
    "wof:placetype":"venue"
},
  "geometry": {"coordinates":[-81.75482177729999,46.2476577759],"type":"Point"}
}