{
  "type": "Feature",
  "properties": {
    "addr:full":"1566 Bloor St W Toronto ON M6P 1A4",
    "addr:housenumber":"1566",
    "addr:postcode":"m6p 1a4",
    "addr:street":"Bloor St W",
    "iso:country":"CA",
    "sg:address":"1566 Bloor St W",
    "sg:city":"Toronto",
    "sg:classifiers":[
        {
            "category":"Cinema",
            "subcategory":"Movie Rental",
            "type":"Entertainment"
        }
    ],
    "sg:phone":"+1 416 532 8370",
    "sg:postcode":"M6P 1A4",
    "sg:province":"ON",
    "sg:tags":[
        "leasing",
        "video",
        "disc",
        "tape"
    ],
    "wof:name":"Movie Art Decor",
    "wof:placetype":"venue"
},
  "geometry": {"coordinates":[-79.45360599999999,43.656288],"type":"Point"}
}