{
  "type": "Feature",
  "properties": {
    "addr:full":"16 Frazee Ave Dartmouth NS B3B 1X4",
    "addr:housenumber":"16",
    "addr:postcode":"b3b 1x4",
    "addr:street":"Frazee Ave",
    "iso:country":"CA",
    "sg:address":"16 Frazee Ave",
    "sg:city":"Dartmouth",
    "sg:classifiers":[
        {
            "category":"Manufacturing",
            "subcategory":"Printing",
            "type":"Manufacturing & Wholesale Goods"
        }
    ],
    "sg:phone":"+1 902 468 1233",
    "sg:postcode":"B3B 1X4",
    "sg:province":"NS",
    "sg:tags":[
        "printer"
    ],
    "wof:name":"Business Cards Tomorrow",
    "wof:placetype":"venue"
},
  "geometry": {"coordinates":[-63.584354,44.713039],"type":"Point"}
}