{
  "type": "Feature",
  "properties": {
    "addr:full":"North Bay ON P1B 6G8",
    "addr:postcode":"p1b 6g8",
    "iso:country":"CA",
    "sg:city":"North Bay",
    "sg:classifiers":[
        {
            "category":"Education",
            "subcategory":"School",
            "type":"Public Place"
        }
    ],
    "sg:phone":"+1 705 474 0900",
    "sg:postcode":"P1B 6G8",
    "sg:province":"ON",
    "wof:name":"Cite Des Jeunes",
    "wof:placetype":"venue"
},
  "geometry": {"coordinates":[-79.449883,46.324776],"type":"Point"}
}