{
  "type": "Feature",
  "properties": {
    "addr:full":"1290 Rang Du Petit-Bois Louiseville QC J5V 2L4",
    "addr:housenumber":"1290",
    "addr:postcode":"j5v 2l4",
    "addr:street":"Rang Du Petit-Bois",
    "iso:country":"CA",
    "sg:address":"1290 Rang Du Petit-Bois",
    "sg:city":"Louiseville",
    "sg:classifiers":[
        {
            "category":"Wholesale",
            "subcategory":"Hardware",
            "type":"Manufacturing & Wholesale Goods"
        }
    ],
    "sg:phone":"+1 819 228 9962",
    "sg:postcode":"J5V 2L4",
    "sg:province":"QC",
    "sg:tags":[
        "oil"
    ],
    "wof:name":"Marcel Paquin & Fils",
    "wof:placetype":"venue"
},
  "geometry": {"coordinates":[-72.97625732420001,46.2477149963],"type":"Point"}
}