{
  "type": "Feature",
  "properties": {
    "iso:country":"CA",
    "sg:address":"135 Varsity Rd",
    "sg:city":"York",
    "sg:classifiers":[
        {
            "category":"Education",
            "subcategory":"School",
            "type":"Public Place"
        }
    ],
    "sg:phone":"+1 416 394 3140",
    "sg:postcode":"M6S 4P4",
    "sg:province":"ON",
    "wof:name":"Warren Park Jr Public School",
    "wof:placetype":"venue"
},
  "geometry": {"coordinates":[-79.4995727539,43.6623191833],"type":"Point"}
}