{
  "type": "Feature",
  "properties": {
    "addr:full":"Charlottetown PE C1A 8R4",
    "addr:postcode":"c1a 8r4",
    "iso:country":"CA",
    "sg:city":"Charlottetown",
    "sg:classifiers":[
        {
            "category":"Insurance",
            "subcategory":"Insurance Agent",
            "type":"Services"
        }
    ],
    "sg:phone":"+1 902 892 2469",
    "sg:postcode":"C1A 8R4",
    "sg:province":"PE",
    "wof:name":"Wawanesa Mutual Insurance CO",
    "wof:placetype":"venue"
},
  "geometry": {"coordinates":[-63.128181,46.236568],"type":"Point"}
}