{
  "type": "Feature",
  "properties": {
    "addr:full":"Quebec QC G2C 1T3",
    "addr:postcode":"qc g2c 1t3",
    "iso:country":"CA",
    "sg:city":"Quebec",
    "sg:classifiers":[
        {
            "category":"Building & Trades",
            "subcategory":"Plumbing",
            "type":"Services"
        }
    ],
    "sg:phone":"+1 418 845 0510",
    "sg:postcode":"G2C 1T3",
    "sg:province":"QC",
    "sg:tags":[
        "ventilating",
        "balancing",
        "contractor"
    ],
    "wof:name":"Caltech",
    "wof:placetype":"venue"
},
  "geometry": {"coordinates":[-71.316261,46.820419],"type":"Point"}
}