{
  "type": "Feature",
  "properties": {
    "addr:full":"Winnipeg MB R2K 2H2",
    "addr:postcode":"r2k 2h2",
    "iso:country":"CA",
    "sg:city":"Winnipeg",
    "sg:classifiers":[
        {
            "category":"Professional",
            "subcategory":"Business Services",
            "type":"Services"
        }
    ],
    "sg:phone":"+1 204 661 2703",
    "sg:postcode":"R2K 2H2",
    "sg:province":"MB",
    "sg:tags":[
        "interior",
        "consultant",
        "design",
        "decorator"
    ],
    "wof:name":"Myers Piske Interior Design",
    "wof:placetype":"venue"
},
  "geometry": {"coordinates":[-97.112892,49.917542],"type":"Point"}
}