{
  "type": "Feature",
  "properties": {
    "addr:full":"117 Centre St Kyle SK S0L 1T0",
    "addr:housenumber":"117",
    "addr:postcode":"s0l 1t0",
    "addr:street":"Centre St",
    "iso:country":"CA",
    "sg:address":"117 Centre St",
    "sg:city":"Kyle",
    "sg:classifiers":[
        {
            "category":"Food & Beverages",
            "subcategory":"Groceries & Convenience Stores",
            "type":"Retail Goods"
        }
    ],
    "sg:phone":"+1 306 375 2333",
    "sg:postcode":"S0L 1T0",
    "sg:province":"SK",
    "sg:tags":[
        "grocer"
    ],
    "wof:name":"Tnt Grocers Ltd",
    "wof:placetype":"venue"
},
  "geometry": {"coordinates":[-108.039581,50.834278],"type":"Point"}
}