{
  "type": "Feature",
  "properties": {
    "addr:full":"366 North Front St Belleville ON K8P 5E6",
    "addr:housenumber":"366",
    "addr:postcode":"k8p 5e6",
    "addr:street":"North Front St",
    "iso:country":"CA",
    "sg:address":"366 North Front St",
    "sg:city":"Belleville",
    "sg:classifiers":[
        {
            "category":"Shopping",
            "subcategory":"Computers & Home Electronics",
            "type":"Retail Goods"
        }
    ],
    "sg:phone":"+1 613 967 4527",
    "sg:postcode":"K8P 5E6",
    "sg:province":"ON",
    "sg:tags":[
        "television",
        "radio"
    ],
    "wof:name":"Sony Store",
    "wof:placetype":"venue"
},
  "geometry": {"coordinates":[-77.3961105347,44.1873321533],"type":"Point"}
}