{
  "type": "Feature",
  "properties": {
    "addr:full":"217 Aberdeen St Cupar SK S0G 0Y0",
    "addr:housenumber":"217",
    "addr:postcode":"s0g 0y0",
    "addr:street":"Aberdeen St",
    "iso:country":"CA",
    "sg:address":"217 Aberdeen St",
    "sg:city":"Cupar",
    "sg:classifiers":[
        {
            "category":"Organizations",
            "subcategory":"Religious Organization",
            "type":"Services"
        }
    ],
    "sg:phone":"+1 306 723 4899",
    "sg:postcode":"S0G 0Y0",
    "sg:province":"SK",
    "sg:tags":[
        "church"
    ],
    "wof:name":"St Paul's Lutheran Church",
    "wof:placetype":"venue"
},
  "geometry": {"coordinates":[-104.211624,50.950291],"type":"Point"}
}