{
  "type": "Feature",
  "properties": {
    "addr:full":"507 Wellington St N Kitchener ON N2H 5L4",
    "addr:housenumber":"507",
    "addr:postcode":"n2h 5l4",
    "addr:street":"Wellington St N",
    "iso:country":"CA",
    "sg:address":"507 Wellington St N",
    "sg:city":"Kitchener",
    "sg:classifiers":[
        {
            "category":"Home & Garden",
            "subcategory":"Building Materials",
            "type":"Retail Goods"
        }
    ],
    "sg:phone":"+1 519 749 8277",
    "sg:postcode":"N2H 5L4",
    "sg:province":"ON",
    "sg:tags":[
        "door"
    ],
    "wof:name":"Master Aluminum & Home",
    "wof:placetype":"venue"
},
  "geometry": {"coordinates":[-80.480873,43.462029],"type":"Point"}
}