{
  "type": "Feature",
  "properties": {
    "addr:full":"3636 Shelbourne St Victoria BC V8P 4H2",
    "addr:housenumber":"3636",
    "addr:postcode":"v8p 4h2",
    "addr:street":"Shelbourne St",
    "iso:country":"CA",
    "sg:address":"3636 Shelbourne St",
    "sg:city":"Victoria",
    "sg:classifiers":[
        {
            "category":"Organizations",
            "subcategory":"Professional Association",
            "type":"Services"
        }
    ],
    "sg:phone":"+1 250 477 7185",
    "sg:postcode":"V8P 4H2",
    "sg:province":"BC",
    "wof:name":"Jewish Community Ctr",
    "wof:placetype":"venue"
},
  "geometry": {"coordinates":[-123.33323669400001,48.4481506348],"type":"Point"}
}