{
  "type": "Feature",
  "properties": {
    "addr:full":"3680 Speedsville Rd Cambridge ON N3H 4R6",
    "addr:housenumber":"3680",
    "addr:postcode":"n3h 4r6",
    "addr:street":"Speedsville Rd",
    "iso:country":"CA",
    "sg:address":"3680 Speedsville Rd",
    "sg:city":"Cambridge",
    "sg:classifiers":[
        {
            "category":"Health Services",
            "subcategory":"Nursing And Care Facility",
            "type":"Services"
        }
    ],
    "sg:phone":"+1 519 650 0100",
    "sg:postcode":"N3H 4R6",
    "sg:province":"ON",
    "sg:tags":[
        "home",
        "convalescent"
    ],
    "wof:name":"Cambridge Country Manor",
    "wof:placetype":"venue"
},
  "geometry": {"coordinates":[-80.3577804565,43.4553108215],"type":"Point"}
}