{
  "type": "Feature",
  "properties": {
    "addr:full":"3600 Boul Matte Brossard QC J4Y 2Z2",
    "addr:housenumber":"3600",
    "addr:postcode":"j4y 2z2",
    "addr:street":"Boul Matte",
    "iso:country":"CA",
    "sg:address":"3600 Boul Matte",
    "sg:city":"Brossard",
    "sg:classifiers":[
        {
            "category":"Manufacturing",
            "subcategory":"Food",
            "type":"Manufacturing & Wholesale Goods"
        }
    ],
    "sg:phone":"+1 450 444 8280",
    "sg:postcode":"J4Y 2Z2",
    "sg:province":"QC",
    "sg:tags":[
        "confectionery",
        "candy"
    ],
    "wof:name":"Nasuco Canada Inc",
    "wof:placetype":"venue"
},
  "geometry": {"coordinates":[-73.4654998779,45.4310951233],"type":"Point"}
}