{
  "type": "Feature",
  "properties": {
    "iso:country":"CA",
    "sg:city":"Stoneham",
    "sg:classifiers":[
        {
            "category":"Government",
            "subcategory":"Office",
            "type":"Public Place"
        }
    ],
    "sg:phone":"+1 418 848 1354",
    "sg:postcode":"G0A 4P0",
    "sg:province":"QC",
    "sg:tags":[
        "village"
    ],
    "wof:name":"Stoneham Pavillon St-Adolphe",
    "wof:placetype":"venue"
},
  "geometry": {"coordinates":[-71.36762237550001,46.9974975586],"type":"Point"}
}