{
  "type": "Feature",
  "properties": {
    "iso:country":"CA",
    "sg:address":"111 Wellington St",
    "sg:city":"Ottawa",
    "sg:classifiers":[
        {
            "category":"Manufacturing",
            "subcategory":"Printing",
            "type":"Manufacturing & Wholesale Goods"
        }
    ],
    "sg:phone":"+1 613 235 1208",
    "sg:postcode":"K1A 0A6",
    "sg:province":"ON",
    "sg:tags":[
        "newspaper"
    ],
    "wof:name":"New Brunswick Telegraph Jrnl",
    "wof:placetype":"venue"
},
  "geometry": {"coordinates":[-75.698967,45.423138],"type":"Point"}
}