{
  "type": "Feature",
  "properties": {
    "addr:full":"37 Sioux Rd Sherwood Park AB T8A 4C7",
    "addr:housenumber":"37",
    "addr:postcode":"t8a 4c7",
    "addr:street":"Sioux Rd",
    "iso:country":"CA",
    "sg:address":"37 Sioux Rd",
    "sg:city":"Sherwood Park",
    "sg:classifiers":[
        {
            "category":"Social Services",
            "subcategory":"Child Care",
            "type":"Services"
        }
    ],
    "sg:phone":"+1 780 417 0991",
    "sg:postcode":"T8A 4C7",
    "sg:province":"AB",
    "wof:name":"Brite Beginnings Daycare",
    "wof:placetype":"venue"
},
  "geometry": {"coordinates":[-113.321342,53.534336],"type":"Point"}
}