{
  "type": "Feature",
  "properties": {
    "addr:full":"430 28E Av Lachine QC H8S 3Z4",
    "addr:housenumber":"430",
    "addr:postcode":"h8s 3z4",
    "addr:street":"28E Av",
    "iso:country":"CA",
    "sg:address":"430 28E Av",
    "sg:city":"Lachine",
    "sg:classifiers":[
        {
            "category":"Restaurant",
            "type":"Food & Drink"
        }
    ],
    "sg:phone":"+1 514 637 5954",
    "sg:postcode":"H8S 3Z4",
    "sg:province":"QC",
    "wof:name":"Mc Donald's",
    "wof:placetype":"venue"
},
  "geometry": {"coordinates":[-73.6884231567,45.4367103577],"type":"Point"}
}