{
  "type": "Feature",
  "properties": {
    "iso:country":"CA",
    "sg:address":"1030 Rue Emond",
    "sg:city":"Mont-Tremblant",
    "sg:classifiers":[
        {
            "category":"Restaurant",
            "type":"Food & Drink"
        }
    ],
    "sg:phone":"+1 819 425 3993",
    "sg:postcode":"J8E 2M5",
    "sg:province":"QC",
    "sg:tags":[
        "caterer"
    ],
    "wof:name":"Buffet France",
    "wof:placetype":"venue"
},
  "geometry": {"coordinates":[-74.59205627439999,46.1371383667],"type":"Point"}
}