{
  "type": "Feature",
  "properties": {
    "addr:full":"43 Brunswick St Truro NS B2N 2G8",
    "addr:housenumber":"43",
    "addr:postcode":"b2n 2g8",
    "addr:street":"Brunswick St",
    "iso:country":"CA",
    "sg:address":"43 Brunswick St",
    "sg:city":"Truro",
    "sg:classifiers":[
        {
            "category":"Home & Garden",
            "subcategory":"Building Materials",
            "type":"Retail Goods"
        }
    ],
    "sg:phone":"+1 902 843 3400",
    "sg:postcode":"B2N 2G8",
    "sg:province":"NS",
    "sg:tags":[
        "paint"
    ],
    "wof:name":"Cameron's Paint Ctr",
    "wof:placetype":"venue"
},
  "geometry": {"coordinates":[-63.276215,45.361492],"type":"Point"}
}