{
  "type": "Feature",
  "properties": {
    "addr:full":"907 9E Rang E Saint-Lazare-DE-Bellechasse QC G0R 3J0",
    "addr:housenumber":"907",
    "addr:postcode":"g0r 3j0",
    "addr:street":"9E Rang E",
    "iso:country":"CA",
    "sg:address":"907 9E Rang E",
    "sg:city":"Saint-Lazare-DE-Bellechasse",
    "sg:classifiers":[
        {
            "category":"Building & Trades",
            "subcategory":"Electrical",
            "type":"Services"
        }
    ],
    "sg:phone":"+1 418 883 2014",
    "sg:postcode":"G0R 3J0",
    "sg:province":"QC",
    "sg:tags":[
        "electric",
        "contractor"
    ],
    "wof:name":"Fradette & Frere",
    "wof:placetype":"venue"
},
  "geometry": {"coordinates":[-70.749306,46.631432],"type":"Point"}
}