{
  "type": "Feature",
  "properties": {
    "addr:full":"22 Fifth St Welland ON L3B 4Z3",
    "addr:housenumber":"22",
    "addr:postcode":"l3b 4z3",
    "addr:street":"Fifth St",
    "iso:country":"CA",
    "sg:address":"22 Fifth St",
    "sg:city":"Welland",
    "sg:classifiers":[
        {
            "category":"Social Services",
            "type":"Services"
        }
    ],
    "sg:phone":"+1 905 788 3800",
    "sg:postcode":"L3B 4Z3",
    "sg:province":"ON",
    "sg:tags":[
        "mission"
    ],
    "wof:name":"Open Arms Mission",
    "wof:placetype":"venue"
},
  "geometry": {"coordinates":[-79.25230407710001,42.9786338806],"type":"Point"}
}