{
  "type": "Feature",
  "properties": {
    "iso:country":"CA",
    "sg:city":"Fort Frances",
    "sg:classifiers":[
        {
            "category":"Building & Trades",
            "subcategory":"Plumbing",
            "type":"Services"
        }
    ],
    "sg:phone":"+1 807 274 6255",
    "sg:postcode":"P9A 3N1",
    "sg:province":"ON",
    "sg:tags":[
        "storage",
        "septic"
    ],
    "wof:name":"Asselin Transportation & Stge",
    "wof:placetype":"venue"
},
  "geometry": {"coordinates":[-93.39110565190001,48.6100158691],"type":"Point"}
}