{
  "type": "Feature",
  "properties": {
    "iso:country":"CA",
    "sg:address":"5147 1E Av",
    "sg:city":"Charlesbourg",
    "sg:classifiers":[
        {
            "category":"Shopping",
            "subcategory":"Pharmacy",
            "type":"Retail Goods"
        }
    ],
    "sg:phone":"+1 418 623 5489",
    "sg:postcode":"G1H 2V1",
    "sg:province":"QC",
    "wof:name":"Pharmacie Andre Guimond Essaim",
    "wof:placetype":"venue"
},
  "geometry": {"coordinates":[-71.2538604736,46.8476066589],"type":"Point"}
}