{
  "type": "Feature",
  "properties": {
    "addr:full":"Espanola ON P5E 1J3",
    "addr:postcode":"p5e 1j3",
    "iso:country":"CA",
    "sg:city":"Espanola",
    "sg:classifiers":[
        {
            "category":"Food & Beverages",
            "subcategory":"Specialty",
            "type":"Retail Goods"
        }
    ],
    "sg:phone":"+1 705 869 1232",
    "sg:postcode":"P5E 1J3",
    "sg:province":"ON",
    "sg:tags":[
        "health",
        "diet"
    ],
    "wof:name":"Natural Choice",
    "wof:placetype":"venue"
},
  "geometry": {"coordinates":[-81.758064,46.247795],"type":"Point"}
}