{
  "type": "Feature",
  "properties": {
    "iso:country":"CA",
    "sg:address":"367 Av Royale",
    "sg:city":"Beauport",
    "sg:classifiers":[
        {
            "category":"Building & Trades",
            "subcategory":"Landscaping Services",
            "type":"Services"
        }
    ],
    "sg:phone":"+1 418 660 3954",
    "sg:postcode":"G1E 1X7",
    "sg:province":"QC",
    "sg:tags":[
        "lawn",
        "maintenance",
        "grounds"
    ],
    "wof:name":"Herbofleurs Inc",
    "wof:placetype":"venue"
},
  "geometry": {"coordinates":[-71.199745,46.85482],"type":"Point"}
}