{
  "type": "Feature",
  "properties": {
    "addr:full":"1150 Main St W Hamilton ON L8S 1C2",
    "addr:housenumber":"1150",
    "addr:postcode":"l8s 1c2",
    "addr:street":"Main St W",
    "iso:country":"CA",
    "sg:address":"1150 Main St W",
    "sg:city":"Hamilton",
    "sg:classifiers":[
        {
            "category":"Education",
            "subcategory":"School",
            "type":"Public Place"
        }
    ],
    "sg:phone":"+1 905 528 8631",
    "sg:postcode":"L8S 1C2",
    "sg:province":"ON",
    "wof:name":"Dalewood School",
    "wof:placetype":"venue"
},
  "geometry": {"coordinates":[-79.9139328003,43.2580795288],"type":"Point"}
}