{
  "type": "Feature",
  "properties": {
    "iso:country":"CA",
    "sg:address":"510 Boul Lacombe",
    "sg:city":"Le Gardeur",
    "sg:classifiers":[
        {
            "category":"Building & Trades",
            "subcategory":"Construction",
            "type":"Services"
        }
    ],
    "sg:phone":"+1 450 582 3037",
    "sg:postcode":"J5Z 1P6",
    "sg:province":"QC",
    "sg:tags":[
        "designer",
        "dealer",
        "pool",
        "swimming"
    ],
    "wof:name":"Au Coin DE LA Piscine",
    "wof:placetype":"venue"
},
  "geometry": {"coordinates":[-73.465813,45.754967],"type":"Point"}
}