{
  "type": "Feature",
  "properties": {
    "addr:full":"21757 125 Ave Maple Ridge BC V2X 4L9",
    "addr:housenumber":"21757",
    "addr:postcode":"v2x 4l9",
    "addr:street":"125 Ave",
    "iso:country":"CA",
    "sg:address":"21757 125 Ave",
    "sg:city":"Maple Ridge",
    "sg:classifiers":[
        {
            "category":"Building & Trades",
            "subcategory":"Construction",
            "type":"Services"
        }
    ],
    "sg:phone":"+1 604 463 6338",
    "sg:postcode":"V2X 4L9",
    "sg:province":"BC",
    "sg:tags":[
        "excavating",
        "contractor"
    ],
    "wof:name":"Dale's Power Digging Ltd",
    "wof:placetype":"venue"
},
  "geometry": {"coordinates":[-122.61905670199999,49.2288398743],"type":"Point"}
}