{
  "type": "Feature",
  "properties": {
    "addr:full":"10 Rue Saint-Raphael Val-Brillant QC G0J 3L0",
    "addr:housenumber":"10",
    "addr:postcode":"g0j 3l0",
    "addr:street":"Rue Saint-Raphael",
    "iso:country":"CA",
    "sg:address":"10 Rue Saint-Raphael",
    "sg:city":"Val-Brillant",
    "sg:classifiers":[
        {
            "category":"Personal",
            "subcategory":"Beauty Salon",
            "type":"Services"
        }
    ],
    "sg:phone":"+1 418 742 3327",
    "sg:postcode":"G0J 3L0",
    "sg:province":"QC",
    "wof:name":"Studio Annik Coiffure Unisexe",
    "wof:placetype":"venue"
},
  "geometry": {"coordinates":[-67.5459365845,48.5324821472],"type":"Point"}
}