{
  "type": "Feature",
  "properties": {
    "addr:full":"1017 Boul Vachon N # 200 Sainte-Marie QC G6E 1M3",
    "addr:housenumber":"1017",
    "addr:postcode":"g6e 1m3",
    "addr:street":"Boul Vachon N # 200",
    "iso:country":"CA",
    "sg:address":"1017 Boul Vachon N # 200",
    "sg:city":"Sainte-Marie",
    "sg:classifiers":[
        {
            "category":"Professional",
            "subcategory":"Engineering",
            "type":"Services"
        }
    ],
    "sg:phone":"+1 418 387 7739",
    "sg:postcode":"G6E 1M3",
    "sg:province":"QC",
    "sg:tags":[
        "engineer"
    ],
    "wof:name":"Axys Consultants Inc",
    "wof:placetype":"venue"
},
  "geometry": {"coordinates":[-71.031639,46.450165],"type":"Point"}
}