{
  "type": "Feature",
  "properties": {
    "addr:full":"1086 Rue Notre-Dame N Thetford Mines QC G6G 2T5",
    "addr:housenumber":"1086",
    "addr:postcode":"g6g 2t5",
    "addr:street":"Rue Notre-Dame N",
    "iso:country":"CA",
    "sg:address":"1086 Rue Notre-Dame N",
    "sg:city":"Thetford Mines",
    "sg:classifiers":[
        {
            "category":"Retail",
            "subcategory":"Funeral Services",
            "type":"Services"
        }
    ],
    "sg:phone":"+1 418 335 6233",
    "sg:postcode":"G6G 2T5",
    "sg:province":"QC",
    "sg:tags":[
        "director"
    ],
    "wof:name":"J-A Savoie & Fils Ltee",
    "wof:placetype":"venue"
},
  "geometry": {"coordinates":[-71.2836608887,46.1031455994],"type":"Point"}
}