{
  "type": "Feature",
  "properties": {
    "addr:full":"RR 1 Drumbo ON N0J 1G0",
    "addr:postcode":"n0j 1g0",
    "addr:street":"Rr 1 Drumbo",
    "iso:country":"CA",
    "sg:address":"RR 1",
    "sg:city":"Drumbo",
    "sg:classifiers":[
        {
            "category":"Travel",
            "subcategory":"Campground",
            "type":"Entertainment"
        }
    ],
    "sg:phone":"+1 519 463 5249",
    "sg:postcode":"N0J 1G0",
    "sg:province":"ON",
    "sg:tags":[
        "camp"
    ],
    "wof:name":"Peacehaven Scout Camp",
    "wof:placetype":"venue"
},
  "geometry": {"coordinates":[-80.552879,43.236755],"type":"Point"}
}