{
  "type": "Feature",
  "properties": {
    "addr:full":"Castlegar BC V1N 2V9",
    "addr:postcode":"v1n 2v9",
    "iso:country":"CA",
    "sg:city":"Castlegar",
    "sg:classifiers":[
        {
            "category":"Real Estate",
            "subcategory":"Real Estate Operator",
            "type":"Services"
        }
    ],
    "sg:phone":"+1 250 365 6213",
    "sg:postcode":"V1N 2V9",
    "sg:province":"BC",
    "sg:tags":[
        "apartment"
    ],
    "wof:name":"Cedar Manor",
    "wof:placetype":"venue"
},
  "geometry": {"coordinates":[-117.649689,49.291332],"type":"Point"}
}