{
  "type": "Feature",
  "properties": {
    "addr:full":"2013 St Laurent Blvd Ottawa ON K1G 1A3",
    "addr:housenumber":"2013",
    "addr:postcode":"k1g 1a3",
    "addr:street":"St Laurent Blvd",
    "iso:country":"CA",
    "sg:address":"2013 St Laurent Blvd",
    "sg:city":"Ottawa",
    "sg:classifiers":[
        {
            "category":"Retail",
            "subcategory":"Auto Repair",
            "type":"Services"
        }
    ],
    "sg:phone":"+1 613 731 4929",
    "sg:postcode":"K1G 1A3",
    "sg:province":"ON",
    "sg:tags":[
        "repairing",
        "automobile"
    ],
    "wof:name":"Allright Automotive Repair Inc",
    "wof:placetype":"venue"
},
  "geometry": {"coordinates":[-75.621796,45.396812],"type":"Point"}
}