{
  "type": "Feature",
  "properties": {
    "addr:full":"4190 Morris Dr Burlington ON L7L 5L6",
    "addr:housenumber":"4190",
    "addr:postcode":"l7l 5l6",
    "addr:street":"Morris Dr",
    "iso:country":"CA",
    "sg:address":"4190 Morris Dr",
    "sg:city":"Burlington",
    "sg:classifiers":[
        {
            "category":"Retail",
            "subcategory":"Auto Repair",
            "type":"Services"
        }
    ],
    "sg:phone":"+1 905 637 8911",
    "sg:postcode":"L7L 5L6",
    "sg:province":"ON",
    "sg:tags":[
        "spring"
    ],
    "wof:name":"Wellwood & Manes Spring Svc",
    "wof:placetype":"venue"
},
  "geometry": {"coordinates":[-79.781052,43.368649],"type":"Point"}
}