{
  "type": "Feature",
  "properties": {
    "addr:full":"5335 Portage Ave Headingley MB R4H 1J9",
    "addr:housenumber":"5335",
    "addr:postcode":"r4h 1j9",
    "addr:street":"Portage Ave",
    "iso:country":"CA",
    "sg:address":"5335 Portage Ave",
    "sg:city":"Headingley",
    "sg:classifiers":[
        {
            "category":"Organizations",
            "subcategory":"Religious Organization",
            "type":"Services"
        }
    ],
    "sg:phone":"+1 204 831 9578",
    "sg:postcode":"R4H 1J9",
    "sg:province":"MB",
    "sg:tags":[
        "church"
    ],
    "wof:name":"Holy Trinity Anglican Chr",
    "wof:placetype":"venue"
},
  "geometry": {"coordinates":[-97.40123,49.875931],"type":"Point"}
}