{
  "type": "Feature",
  "properties": {
    "iso:country":"CA",
    "sg:city":"Minto",
    "sg:classifiers":[
        {
            "category":"Building & Trades",
            "subcategory":"Electrical",
            "type":"Services"
        }
    ],
    "sg:phone":"+1 506 327 6247",
    "sg:postcode":"E4B 2T9",
    "sg:province":"NB",
    "sg:tags":[
        "electric",
        "contractor"
    ],
    "wof:name":"K E Mc Elwain Ltd",
    "wof:placetype":"venue"
},
  "geometry": {"coordinates":[-66.0503311157,46.0772247314],"type":"Point"}
}