{
  "type": "Feature",
  "properties": {
    "addr:full":"4505 101 St NW Edmonton AB T6E 5C6",
    "addr:housenumber":"4505",
    "addr:postcode":"t6e 5c6",
    "addr:street":"101 St Nw",
    "iso:country":"CA",
    "sg:address":"4505 101 St NW",
    "sg:city":"Edmonton",
    "sg:classifiers":[
        {
            "category":"Building & Trades",
            "subcategory":"Cleaning & Sanitation",
            "type":"Services"
        }
    ],
    "sg:phone":"+1 780 435 3355",
    "sg:postcode":"T6E 5C6",
    "sg:province":"AB",
    "sg:tags":[
        "janitor"
    ],
    "wof:name":"Bee-Clean",
    "wof:placetype":"venue"
},
  "geometry": {"coordinates":[-113.488945007,53.4834671021],"type":"Point"}
}