{
  "type": "Feature",
  "properties": {
    "iso:country":"CA",
    "sg:city":"Mont-Saint-Hilaire",
    "sg:classifiers":[
        {
            "category":"Shopping",
            "subcategory":"Florist",
            "type":"Retail Goods"
        }
    ],
    "sg:phone":"+1 450 464 0340",
    "sg:postcode":"J3H 3N8",
    "sg:province":"QC",
    "wof:name":"Fleuriste Fleurs DE Cactus Inc",
    "wof:placetype":"venue"
},
  "geometry": {"coordinates":[-73.1896362305,45.5624771118],"type":"Point"}
}