{
  "type": "Feature",
  "properties": {
    "iso:country":"CA",
    "sg:address":"2365 Thomason Rd",
    "sg:city":"Kimberley",
    "sg:classifiers":[
        {
            "category":"Retail",
            "subcategory":"Animal Services",
            "type":"Services"
        }
    ],
    "sg:phone":"+1 250 427 7090",
    "sg:postcode":"V1A 3L5",
    "sg:province":"BC",
    "sg:tags":[
        "pet",
        "boarding",
        "sitting"
    ],
    "wof:name":"Hyde Away Kennels",
    "wof:placetype":"venue"
},
  "geometry": {"coordinates":[-115.97809600799999,49.6700286865],"type":"Point"}
}