{
  "type": "Feature",
  "properties": {
    "addr:full":"11223 132 St NW Edmonton AB T5M 1E7",
    "addr:housenumber":"11223",
    "addr:postcode":"t5m 1e7",
    "addr:street":"132 St Nw",
    "iso:country":"CA",
    "sg:address":"11223 132 St NW",
    "sg:city":"Edmonton",
    "sg:classifiers":[
        {
            "category":"Travel",
            "subcategory":"Travel Agent",
            "type":"Entertainment"
        }
    ],
    "sg:phone":"+1 780 452 5187",
    "sg:postcode":"T5M 1E7",
    "sg:province":"AB",
    "sg:tags":[
        "agency",
        "bureau"
    ],
    "wof:name":"Alta-Can Tours Inc",
    "wof:placetype":"venue"
},
  "geometry": {"coordinates":[-113.54935500000001,53.560932],"type":"Point"}
}