{
  "type": "Feature",
  "properties": {
    "addr:full":"226 Frank Endean Rd Richmond Hill ON L4S 2C4",
    "addr:housenumber":"226",
    "addr:postcode":"l4s 2c4",
    "addr:street":"Frank Endean Rd",
    "iso:country":"CA",
    "sg:address":"226 Frank Endean Rd",
    "sg:city":"Richmond Hill",
    "sg:classifiers":[
        {
            "category":"Retail",
            "subcategory":"Laundry & Dry Cleaning",
            "type":"Services"
        }
    ],
    "sg:phone":"+1 905 780 9133",
    "sg:postcode":"L4S 2C4",
    "sg:province":"ON",
    "sg:tags":[
        "repairing",
        "rug",
        "carpet"
    ],
    "wof:name":"Thai Dynasty Inc",
    "wof:placetype":"venue"
},
  "geometry": {"coordinates":[-79.4142456055,43.8876037598],"type":"Point"}
}