{
  "type": "Feature",
  "properties": {
    "addr:full":"5410 Richmond Rd Nepean ON K2R 1G7",
    "addr:housenumber":"5410",
    "addr:postcode":"k2r 1g7",
    "addr:street":"Richmond Rd",
    "iso:country":"CA",
    "sg:address":"5410 Richmond Rd",
    "sg:city":"Nepean",
    "sg:classifiers":[
        {
            "category":"Manufacturing",
            "subcategory":"Tools & Machinery",
            "type":"Manufacturing & Wholesale Goods"
        }
    ],
    "sg:phone":"+1 613 271 0988",
    "sg:postcode":"K2R 1G7",
    "sg:province":"ON",
    "sg:tags":[
        "automation",
        "electric",
        "motor",
        "system"
    ],
    "wof:name":"Kcs",
    "wof:placetype":"venue"
},
  "geometry": {"coordinates":[-75.832489,45.272793],"type":"Point"}
}