{
  "type": "Feature",
  "properties": {
    "addr:full":"315 Walden Blvd Fort Erie ON L2A 1R7",
    "addr:housenumber":"315",
    "addr:postcode":"l2a 1r7",
    "addr:street":"Walden Blvd",
    "iso:country":"CA",
    "sg:address":"315 Walden Blvd",
    "sg:city":"Fort Erie",
    "sg:classifiers":[
        {
            "category":"Retail",
            "subcategory":"Veterinary Services",
            "type":"Services"
        }
    ],
    "sg:phone":"+1 905 871 1653",
    "sg:postcode":"L2A 1R7",
    "sg:province":"ON",
    "sg:tags":[
        "veterinarian"
    ],
    "wof:name":"Fort Erie Animal Hospital",
    "wof:placetype":"venue"
},
  "geometry": {"coordinates":[-78.927536,42.907562],"type":"Point"}
}