{
  "type": "Feature",
  "properties": {
    "addr:full":"470 Place Du Commerce Sept-Iles QC G4R 2Z5",
    "addr:housenumber":"470",
    "addr:postcode":"g4r 2z5",
    "addr:street":"Place Du Commerce Sept-Iles",
    "iso:country":"CA",
    "sg:address":"470 Place Du Commerce",
    "sg:city":"Sept-Iles",
    "sg:classifiers":[
        {
            "category":"Shopping",
            "subcategory":"Computers & Home Electronics",
            "type":"Retail Goods"
        }
    ],
    "sg:phone":"+1 418 962 2391",
    "sg:postcode":"G4R 2Z5",
    "sg:province":"QC",
    "sg:tags":[
        "television",
        "radio"
    ],
    "wof:name":"Techserv Inc",
    "wof:placetype":"venue"
},
  "geometry": {"coordinates":[-66.3864440918,50.2062606812],"type":"Point"}
}