{
  "type": "Feature",
  "properties": {
    "iso:country":"CA",
    "sg:address":"550 Eglinton Ave W",
    "sg:city":"Toronto",
    "sg:classifiers":[
        {
            "category":"Shopping",
            "subcategory":"Pharmacy",
            "type":"Retail Goods"
        }
    ],
    "sg:phone":"+1 416 485 3093",
    "sg:postcode":"M5N 1B6",
    "sg:province":"ON",
    "wof:name":"Shoppers Drug Mart",
    "wof:placetype":"venue"
},
  "geometry": {"coordinates":[-79.41515350340001,43.7033233643],"type":"Point"}
}