{
  "type": "Feature",
  "properties": {
    "addr:full":"1185 Regional Rd 21 # 2 Port Perry ON L9L 1B5",
    "addr:housenumber":"1185;21 # 2",
    "addr:postcode":"l9l 1b5",
    "addr:street":"Regional Rd",
    "iso:country":"CA",
    "sg:address":"1185 Regional Rd 21 # 2",
    "sg:city":"Port Perry",
    "sg:classifiers":[
        {
            "category":"Autos & Motor Vehicles",
            "subcategory":"Fuel & Gas Station",
            "type":"Retail Goods"
        }
    ],
    "sg:phone":"+1 905 985 4573",
    "sg:postcode":"L9L 1B5",
    "sg:province":"ON",
    "sg:tags":[
        "oil"
    ],
    "wof:name":"Manchester Country Convenience",
    "wof:placetype":"venue"
},
  "geometry": {"coordinates":[-79.33847045900001,45.5428199768],"type":"Point"}
}