{
  "type": "Feature",
  "properties": {
    "addr:full":"120 Rue Du Quai LA Malbaie QC G5A 2Y1",
    "addr:housenumber":"120",
    "addr:postcode":"g5a 2y1",
    "addr:street":"Rue Du Quai",
    "iso:country":"CA",
    "sg:address":"120 Rue Du Quai",
    "sg:city":"LA Malbaie",
    "sg:classifiers":[
        {
            "category":"Restaurant",
            "type":"Food & Drink"
        }
    ],
    "sg:phone":"+1 418 665 7266",
    "sg:postcode":"G5A 2Y1",
    "sg:province":"QC",
    "wof:name":"Chez Chantal Enr",
    "wof:placetype":"venue"
},
  "geometry": {"coordinates":[-70.1421661377,47.6247940063],"type":"Point"}
}