{
  "type": "Feature",
  "properties": {
    "iso:country":"CA",
    "sg:city":"North York",
    "sg:classifiers":[
        {
            "category":"Professional",
            "subcategory":"Accounting & Tax Preparation",
            "type":"Services"
        }
    ],
    "sg:phone":"+1 416 733 3263",
    "sg:postcode":"M2N 1N5",
    "sg:province":"ON",
    "sg:tags":[
        "accountant"
    ],
    "wof:name":"Goldhar, Alan CA",
    "wof:placetype":"venue"
},
  "geometry": {"coordinates":[-79.4257888794,43.7582321167],"type":"Point"}
}