{
  "type": "Feature",
  "properties": {
    "addr:full":"1104 Princess Ave Brandon MB R7A 0P9",
    "addr:housenumber":"1104",
    "addr:postcode":"r7a 0p9",
    "addr:street":"Princess Ave",
    "iso:country":"CA",
    "sg:address":"1104 Princess Ave",
    "sg:city":"Brandon",
    "sg:classifiers":[
        {
            "category":"Government",
            "subcategory":"Office",
            "type":"Public Place"
        }
    ],
    "sg:phone":"+1 204 726 6240",
    "sg:postcode":"R7A 0P9",
    "sg:province":"MB",
    "wof:name":"Queens Bench Court Office",
    "wof:placetype":"venue"
},
  "geometry": {"coordinates":[-99.95300292970001,49.8467750549],"type":"Point"}
}