{
  "type": "Feature",
  "properties": {
    "iso:country":"CA",
    "sg:address":"211 Brule Rd",
    "sg:city":"Sault Ste Marie",
    "sg:classifiers":[
        {
            "category":"Manufacturing",
            "subcategory":"Lumber",
            "type":"Manufacturing & Wholesale Goods"
        }
    ],
    "sg:phone":"+1 705 254 6114",
    "sg:postcode":"P6A 5K8",
    "sg:province":"ON",
    "sg:tags":[
        "company",
        "logging"
    ],
    "wof:name":"Henson & Tregonning Logging",
    "wof:placetype":"venue"
},
  "geometry": {"coordinates":[-84.36214447019999,46.558971405],"type":"Point"}
}