{
  "type": "Feature",
  "properties": {
    "addr:full":"940 1st Ave W Owen Sound ON N4K 4K5",
    "addr:housenumber":"940",
    "addr:postcode":"n4k 4k5",
    "addr:street":"1St Ave W",
    "iso:country":"CA",
    "sg:address":"940 1st Ave W",
    "sg:city":"Owen Sound",
    "sg:classifiers":[
        {
            "category":"Health Services",
            "subcategory":"Medical Lab",
            "type":"Services"
        }
    ],
    "sg:phone":"+1 519 376 3233",
    "sg:postcode":"N4K 4K5",
    "sg:province":"ON",
    "sg:tags":[
        "laboratory"
    ],
    "wof:name":"K W Bedell Dental Svc",
    "wof:placetype":"venue"
},
  "geometry": {"coordinates":[-80.944855,44.566147],"type":"Point"}
}