{
  "type": "Feature",
  "properties": {
    "addr:full":"2611 Ida Rd Windsor ON N8W 3A6",
    "addr:housenumber":"2611",
    "addr:postcode":"n8w 3a6",
    "addr:street":"Ida Rd",
    "iso:country":"CA",
    "sg:address":"2611 Ida Rd",
    "sg:city":"Windsor",
    "sg:classifiers":[
        {
            "category":"Shopping",
            "subcategory":"Computers & Home Electronics",
            "type":"Retail Goods"
        }
    ],
    "sg:phone":"+1 519 252 5637",
    "sg:postcode":"N8W 3A6",
    "sg:province":"ON",
    "sg:tags":[
        "television",
        "radio"
    ],
    "wof:name":"Walkerville Tv Sales & Svc",
    "wof:placetype":"venue"
},
  "geometry": {"coordinates":[-82.991432,42.291859],"type":"Point"}
}