{
  "type": "Feature",
  "properties": {
    "addr:full":"5106 46 St Olds AB T4H 1A5",
    "addr:housenumber":"5106",
    "addr:postcode":"t4h 1a5",
    "addr:street":"46 St",
    "iso:country":"CA",
    "sg:address":"5106 46 St",
    "sg:city":"Olds",
    "sg:classifiers":[
        {
            "category":"Restaurant",
            "type":"Food & Drink"
        }
    ],
    "sg:phone":"+1 403 556 8899",
    "sg:postcode":"T4H 1A5",
    "sg:province":"AB",
    "wof:name":"Kfc",
    "wof:placetype":"venue"
},
  "geometry": {"coordinates":[-114.10468299999999,51.795132],"type":"Point"}
}