{
  "type": "Feature",
  "properties": {
    "addr:full":"463 Rue Lafontaine Riviere-Du-Loup QC G5R 3C3",
    "addr:housenumber":"463",
    "addr:postcode":"g5r 3c3",
    "addr:street":"Rue Lafontaine",
    "iso:country":"CA",
    "sg:address":"463 Rue Lafontaine",
    "sg:city":"Riviere-Du-Loup",
    "sg:classifiers":[
        {
            "category":"Real Estate",
            "subcategory":"Surveying",
            "type":"Services"
        }
    ],
    "sg:phone":"+1 418 862 0971",
    "sg:postcode":"G5R 3C3",
    "sg:province":"QC",
    "sg:tags":[
        "surveyor"
    ],
    "wof:name":"Parent & Ouellet",
    "wof:placetype":"venue"
},
  "geometry": {"coordinates":[-69.53112,47.828415],"type":"Point"}
}