{
  "type": "Feature",
  "properties": {
    "iso:country":"CA",
    "sg:address":"PO Box 520",
    "sg:city":"Watrous",
    "sg:classifiers":[
        {
            "category":"Education",
            "subcategory":"School",
            "type":"Public Place"
        }
    ],
    "sg:phone":"+1 306 484 2060",
    "sg:postcode":"S0K 4T0",
    "sg:province":"SK",
    "wof:name":"Sask Central School Div",
    "wof:placetype":"venue"
},
  "geometry": {"coordinates":[-105.467880249,51.67162323],"type":"Point"}
}