{
  "type": "Feature",
  "properties": {
    "iso:country":"CA",
    "sg:city":"Duncan",
    "sg:classifiers":[
        {
            "category":"Professional",
            "subcategory":"Lawyer & Legal Services",
            "type":"Services"
        }
    ],
    "sg:phone":"+1 250 748 5253",
    "sg:postcode":"V9L 2P5",
    "sg:province":"BC",
    "sg:tags":[
        "attorney"
    ],
    "wof:name":"Desjardins, Vincent R",
    "wof:placetype":"venue"
},
  "geometry": {"coordinates":[-123.700088501,48.7770042419],"type":"Point"}
}