{
  "type": "Feature",
  "properties": {
    "addr:full":"100 Spy Crt Markham ON L3R 5H6",
    "addr:housenumber":"100",
    "addr:postcode":"l3r 5h6",
    "addr:street":"Spy Crt",
    "iso:country":"CA",
    "sg:address":"100 Spy Crt",
    "sg:city":"Markham",
    "sg:classifiers":[
        {
            "category":"Wholesale",
            "subcategory":"Photographic Equipment",
            "type":"Manufacturing & Wholesale Goods"
        }
    ],
    "sg:phone":"+1 905 944 9400",
    "sg:postcode":"L3R 5H6",
    "sg:province":"ON",
    "sg:tags":[
        "supply"
    ],
    "wof:name":"Day Men Photo Marketing Ltd",
    "wof:placetype":"venue"
},
  "geometry": {"coordinates":[-79.356453,43.856014],"type":"Point"}
}