{
  "type": "Feature",
  "properties": {
    "iso:country":"CA",
    "sg:city":"Vancouver",
    "sg:classifiers":[
        {
            "category":"Organizations",
            "subcategory":"Professional Association",
            "type":"Services"
        }
    ],
    "sg:phone":"+1 604 872 6723",
    "sg:postcode":"V5Y 3W2",
    "sg:province":"BC",
    "sg:tags":[
        "native"
    ],
    "wof:name":"Vancouver Aboriginal Child",
    "wof:placetype":"venue"
},
  "geometry": {"coordinates":[-123.109764099,49.2629928589],"type":"Point"}
}