{
  "type": "Feature",
  "properties": {
    "addr:full":"3660 Rue Chenier Mirabel QC J7N 2N1",
    "addr:housenumber":"3660",
    "addr:postcode":"j7n 2n1",
    "addr:street":"Rue Chenier",
    "iso:country":"CA",
    "sg:address":"3660 Rue Chenier",
    "sg:city":"Mirabel",
    "sg:classifiers":[
        {
            "category":"Real Estate",
            "subcategory":"Real Estate Agent",
            "type":"Services"
        }
    ],
    "sg:phone":"+1 450 258 3111",
    "sg:postcode":"J7N 2N1",
    "sg:province":"QC",
    "sg:tags":[
        "hardware",
        "cooperative"
    ],
    "wof:name":"Centre DE Renovation St-Benoit",
    "wof:placetype":"venue"
},
  "geometry": {"coordinates":[-74.0916595459,45.5651741028],"type":"Point"}
}