{
  "type": "Feature",
  "properties": {
    "addr:full":"280 John St Moncton NB E1C 9W3",
    "addr:housenumber":"280",
    "addr:postcode":"e1c 9w3",
    "addr:street":"John St",
    "iso:country":"CA",
    "sg:address":"280 John St",
    "sg:city":"Moncton",
    "sg:classifiers":[
        {
            "category":"Wholesale",
            "subcategory":"Machinery & Supplies",
            "type":"Manufacturing & Wholesale Goods"
        }
    ],
    "sg:phone":"+1 506 857 8390",
    "sg:postcode":"E1C 9W3",
    "sg:province":"NB",
    "sg:tags":[
        "equipment",
        "welding"
    ],
    "wof:name":"Air Liquide Canada",
    "wof:placetype":"venue"
},
  "geometry": {"coordinates":[-64.79840900000001,46.091949],"type":"Point"}
}