{
  "type": "Feature",
  "properties": {
    "addr:full":"3488 Boul Masson Quebec QC G1P 1K1",
    "addr:housenumber":"3488",
    "addr:postcode":"g1p 1k1",
    "addr:street":"Boul Masson",
    "iso:country":"CA",
    "sg:address":"3488 Boul Masson",
    "sg:city":"Quebec",
    "sg:classifiers":[
        {
            "category":"Personal",
            "subcategory":"Beauty Salon",
            "type":"Services"
        }
    ],
    "sg:phone":"+1 418 872 3512",
    "sg:postcode":"G1P 1K1",
    "sg:province":"QC",
    "wof:name":"Salon DE Coiffure Alexandre",
    "wof:placetype":"venue"
},
  "geometry": {"coordinates":[-71.32395200000001,46.8134],"type":"Point"}
}