{
  "type": "Feature",
  "properties": {
    "iso:country":"CA",
    "sg:address":"4150 Main St",
    "sg:city":"Vancouver",
    "sg:classifiers":[
        {
            "category":"Home & Garden",
            "subcategory":"Home Furnishings",
            "type":"Retail Goods"
        }
    ],
    "sg:phone":"+1 604 872 8983",
    "sg:postcode":"V5V 3P7",
    "sg:province":"BC",
    "sg:tags":[
        "venetian",
        "blind"
    ],
    "wof:name":"New Window Fashion Ltd",
    "wof:placetype":"venue"
},
  "geometry": {"coordinates":[-123.100845337,49.248249054],"type":"Point"}
}