{
  "type": "Feature",
  "properties": {
    "addr:full":"3485 Harvester Rd Burlington ON L7N 3T3",
    "addr:housenumber":"3485",
    "addr:postcode":"l7n 3t3",
    "addr:street":"Harvester Rd",
    "iso:country":"CA",
    "sg:address":"3485 Harvester Rd",
    "sg:city":"Burlington",
    "sg:classifiers":[
        {
            "category":"Home & Garden",
            "subcategory":"Building Materials",
            "type":"Retail Goods"
        }
    ],
    "sg:phone":"+1 416 667 8468",
    "sg:postcode":"L7N 3T3",
    "sg:province":"ON",
    "sg:tags":[
        "glass",
        "window",
        "plate"
    ],
    "wof:name":"Harvester Auto Glass",
    "wof:placetype":"venue"
},
  "geometry": {"coordinates":[-79.786079,43.361374],"type":"Point"}
}