{
  "type": "Feature",
  "properties": {
    "addr:full":"22239 Lougheed Hwy Maple Ridge BC V2X 2S9",
    "addr:housenumber":"22239",
    "addr:postcode":"v2x 2s9",
    "addr:street":"Lougheed Hwy",
    "iso:country":"CA",
    "sg:address":"22239 Lougheed Hwy",
    "sg:city":"Maple Ridge",
    "sg:classifiers":[
        {
            "category":"Home & Garden",
            "subcategory":"Furniture",
            "type":"Retail Goods"
        }
    ],
    "sg:phone":"+1 604 466 4252",
    "sg:postcode":"V2X 2S9",
    "sg:province":"BC",
    "sg:tags":[
        "mattress"
    ],
    "wof:name":"Sleep Shop",
    "wof:placetype":"venue"
},
  "geometry": {"coordinates":[-122.606049,49.21698],"type":"Point"}
}