{
  "type": "Feature",
  "properties": {
    "addr:full":"245 Sunshine Valley Clearwater BC V0E 1N0",
    "addr:housenumber":"245",
    "addr:postcode":"v0e 1n0",
    "addr:street":"Sunshine Valley",
    "iso:country":"CA",
    "sg:address":"245 Sunshine Valley",
    "sg:city":"Clearwater",
    "sg:classifiers":[
        {
            "category":"Building & Trades",
            "subcategory":"Construction",
            "type":"Services"
        }
    ],
    "sg:phone":"+1 250 674 3919",
    "sg:postcode":"V0E 1N0",
    "sg:province":"BC",
    "sg:tags":[
        "road",
        "contractor"
    ],
    "wof:name":"Clearwater Valley Construction",
    "wof:placetype":"venue"
},
  "geometry": {"coordinates":[-120.034820557,51.6509246826],"type":"Point"}
}