{
  "type": "Feature",
  "properties": {
    "addr:full":"65 Rue Fairview Atholville NB E3N 4N3",
    "addr:housenumber":"65",
    "addr:postcode":"e3n 4n3",
    "addr:street":"Rue Fairview Atholville",
    "iso:country":"CA",
    "sg:address":"65 Rue Fairview",
    "sg:city":"Atholville",
    "sg:classifiers":[
        {
            "category":"Professional",
            "subcategory":"Lawyer & Legal Services",
            "type":"Services"
        }
    ],
    "sg:phone":"+1 506 753 4545",
    "sg:postcode":"E3N 4N3",
    "sg:province":"NB",
    "sg:tags":[
        "attorney"
    ],
    "wof:name":"Roger Gauvin Bureau D'Avocat",
    "wof:placetype":"venue"
},
  "geometry": {"coordinates":[-66.7100524902,47.9928627014],"type":"Point"}
}