{
  "type": "Feature",
  "properties": {
    "iso:country":"CA",
    "sg:address":"980 Rue Sainte-Catherine O # 400",
    "sg:city":"Montreal",
    "sg:classifiers":[
        {
            "category":"Professional",
            "subcategory":"Advertising",
            "type":"Services"
        }
    ],
    "sg:phone":"+1 514 871 1616",
    "sg:postcode":"H3B 1E5",
    "sg:province":"QC",
    "sg:tags":[
        "counselor"
    ],
    "wof:name":"Bernier Renauld Communication",
    "wof:placetype":"venue"
},
  "geometry": {"coordinates":[-73.5574417114,45.5167922974],"type":"Point"}
}