{
  "type": "Feature",
  "properties": {
    "addr:full":"Cadomin AB T0E 0E0",
    "addr:postcode":"t0e 0e0",
    "iso:country":"CA",
    "sg:city":"Cadomin",
    "sg:classifiers":[
        {
            "category":"Recreation",
            "type":"Entertainment"
        }
    ],
    "sg:phone":"+1 780 692 3953",
    "sg:postcode":"T0E 0E0",
    "sg:province":"AB",
    "sg:tags":[
        "hall",
        "auditorium"
    ],
    "wof:name":"Royal Canadian Legion Branch",
    "wof:placetype":"venue"
},
  "geometry": {"coordinates":[-117.322433472,53.045463562],"type":"Point"}
}