{
  "type": "Feature",
  "properties": {
    "addr:full":"405 Queen St W Cambridge ON N3C 1G6",
    "addr:housenumber":"405",
    "addr:postcode":"n3c 1g6",
    "addr:street":"Queen St W",
    "iso:country":"CA",
    "sg:address":"405 Queen St W",
    "sg:city":"Cambridge",
    "sg:classifiers":[
        {
            "category":"Building & Trades",
            "subcategory":"Construction",
            "type":"Services"
        }
    ],
    "sg:phone":"+1 519 658 9317",
    "sg:postcode":"N3C 1G6",
    "sg:province":"ON",
    "sg:tags":[
        "general",
        "contractor"
    ],
    "wof:name":"Schiedel Construction Inc",
    "wof:placetype":"venue"
},
  "geometry": {"coordinates":[-80.32630899999999,43.421574],"type":"Point"}
}