{
  "type": "Feature",
  "properties": {
    "addr:full":"10800 Rochdale Dr Richmond BC V7A 3N6",
    "addr:housenumber":"10800",
    "addr:postcode":"v7a 3n6",
    "addr:street":"Rochdale Dr",
    "iso:country":"CA",
    "sg:address":"10800 Rochdale Dr",
    "sg:city":"Richmond",
    "sg:classifiers":[
        {
            "category":"Wholesale",
            "subcategory":"Durable Goods & Equipment",
            "type":"Manufacturing & Wholesale Goods"
        }
    ],
    "sg:phone":"+1 604 275 8957",
    "sg:postcode":"V7A 3N6",
    "sg:province":"BC",
    "sg:tags":[
        "importer"
    ],
    "wof:name":"Noorani Imports & Exports",
    "wof:placetype":"venue"
},
  "geometry": {"coordinates":[-123.107742,49.134315],"type":"Point"}
}