{
  "type": "Feature",
  "properties": {
    "addr:full":"823 Viewfield Rd Victoria BC V9A 4V2",
    "addr:housenumber":"823",
    "addr:postcode":"v9a 4v2",
    "addr:street":"Viewfield Rd",
    "iso:country":"CA",
    "sg:address":"823 Viewfield Rd",
    "sg:city":"Victoria",
    "sg:classifiers":[
        {
            "category":"Autos & Motor Vehicles",
            "subcategory":"Automobile Sales",
            "type":"Retail Goods"
        }
    ],
    "sg:phone":"+1 250 383 5173",
    "sg:postcode":"V9A 4V2",
    "sg:province":"BC",
    "sg:tags":[
        "parts",
        "classic"
    ],
    "wof:name":"Hunter Classic Sports Cars",
    "wof:placetype":"venue"
},
  "geometry": {"coordinates":[-123.36243399999999,48.420654],"type":"Point"}
}