{
  "type": "Feature",
  "properties": {
    "addr:full":"280 Ch Des Poirier Montmagny QC G5V 4S5",
    "addr:housenumber":"280",
    "addr:postcode":"g5v 4s5",
    "addr:street":"Ch Des Poirier",
    "iso:country":"CA",
    "sg:address":"280 Ch Des Poirier",
    "sg:city":"Montmagny",
    "sg:classifiers":[
        {
            "category":"Wholesale",
            "subcategory":"Machinery & Supplies",
            "type":"Manufacturing & Wholesale Goods"
        }
    ],
    "sg:phone":"+1 418 248 2477",
    "sg:postcode":"G5V 4S5",
    "sg:province":"QC",
    "sg:tags":[
        "farm",
        "equipment"
    ],
    "wof:name":"Garage Minville & Fils Inc",
    "wof:placetype":"venue"
},
  "geometry": {"coordinates":[-70.58470916749999,46.9636688232],"type":"Point"}
}