{
  "type": "Feature",
  "properties": {
    "addr:full":"1084 Prince St Truro NS B2N 1J1",
    "addr:housenumber":"1084",
    "addr:postcode":"b2n 1j1",
    "addr:street":"Prince St",
    "iso:country":"CA",
    "sg:address":"1084 Prince St",
    "sg:city":"Truro",
    "sg:classifiers":[
        {
            "category":"Manufacturing",
            "subcategory":"Printing",
            "type":"Manufacturing & Wholesale Goods"
        }
    ],
    "sg:phone":"+1 902 895 2811",
    "sg:postcode":"B2N 1J1",
    "sg:province":"NS",
    "sg:tags":[
        "printer"
    ],
    "wof:name":"Specialty Printers Ltd",
    "wof:placetype":"venue"
},
  "geometry": {"coordinates":[-63.267166,45.364258],"type":"Point"}
}