{
  "type": "Feature",
  "properties": {
    "addr:full":"61 Queenston St Queenston ON L0S 1L0",
    "addr:housenumber":"61",
    "addr:postcode":"l0s 1l0",
    "addr:street":"Queenston St",
    "iso:country":"CA",
    "sg:address":"61 Queenston St",
    "sg:city":"Queenston",
    "sg:classifiers":[
        {
            "category":"Autos & Motor Vehicles",
            "subcategory":"Automobile Sales",
            "type":"Retail Goods"
        }
    ],
    "sg:phone":"+1 905 262 4448",
    "sg:postcode":"L0S 1L0",
    "sg:province":"ON",
    "sg:tags":[
        "car",
        "dealer"
    ],
    "wof:name":"Paul Safari Components",
    "wof:placetype":"venue"
},
  "geometry": {"coordinates":[-79.0556259155,43.1659851074],"type":"Point"}
}