{
  "type": "Feature",
  "properties": {
    "addr:full":"299 9th St E Owen Sound ON N4K 1N8",
    "addr:housenumber":"299",
    "addr:postcode":"n4k 1n8",
    "addr:street":"9Th St E",
    "iso:country":"CA",
    "sg:address":"299 9th St E",
    "sg:city":"Owen Sound",
    "sg:classifiers":[
        {
            "category":"Professional",
            "subcategory":"Engineering",
            "type":"Services"
        }
    ],
    "sg:phone":"+1 519 376 2800",
    "sg:postcode":"N4K 1N8",
    "sg:province":"ON",
    "sg:tags":[
        "engineer"
    ],
    "wof:name":"Aka Information Design",
    "wof:placetype":"venue"
},
  "geometry": {"coordinates":[-80.9411621094,44.5659141541],"type":"Point"}
}