{
  "type": "Feature",
  "properties": {
    "iso:country":"CA",
    "sg:address":"688 Main St",
    "sg:city":"Pincher Creek",
    "sg:classifiers":[
        {
            "category":"Retail",
            "subcategory":"Photofinishing",
            "type":"Services"
        }
    ],
    "sg:phone":"+1 403 627 4858",
    "sg:postcode":"T0K 1W0",
    "sg:province":"AB",
    "sg:tags":[
        "photo",
        "finishing"
    ],
    "wof:name":"Burnham Business Svc",
    "wof:placetype":"venue"
},
  "geometry": {"coordinates":[-113.949676514,49.4855308533],"type":"Point"}
}