{
  "type": "Feature",
  "properties": {
    "addr:full":"104 4th Ave Englehart ON P0J 1H0",
    "addr:housenumber":"104",
    "addr:postcode":"p0j 1h0",
    "addr:street":"4Th Ave",
    "iso:country":"CA",
    "sg:address":"104 4th Ave",
    "sg:city":"Englehart",
    "sg:classifiers":[
        {
            "category":"Recreation",
            "type":"Entertainment"
        }
    ],
    "sg:phone":"+1 705 544 7460",
    "sg:postcode":"P0J 1H0",
    "sg:province":"ON",
    "sg:tags":[
        "hall",
        "auditorium"
    ],
    "wof:name":"Canadian Legion Branch 104",
    "wof:placetype":"venue"
},
  "geometry": {"coordinates":[-79.882561,47.825569],"type":"Point"}
}