{
  "type": "Feature",
  "properties": {
    "addr:full":"566 Rte Du Golf Lac-Etchemin QC G0R 1S0",
    "addr:housenumber":"566",
    "addr:postcode":"g0r 1s0",
    "addr:street":"Rte Du Golf",
    "iso:country":"CA",
    "sg:address":"566 Rte Du Golf",
    "sg:city":"Lac-Etchemin",
    "sg:classifiers":[
        {
            "category":"Sports & Exercise",
            "subcategory":"Golf",
            "type":"Entertainment"
        }
    ],
    "sg:phone":"+1 418 625 2711",
    "sg:postcode":"G0R 1S0",
    "sg:province":"QC",
    "sg:tags":[
        "course"
    ],
    "wof:name":"Club DE Golf",
    "wof:placetype":"venue"
},
  "geometry": {"coordinates":[-70.5317,46.412949],"type":"Point"}
}