{
  "type": "Feature",
  "properties": {
    "addr:full":"1226 Rue Jean-Talon E Montreal QC H2R 1W2",
    "addr:housenumber":"1226",
    "addr:postcode":"h2r 1w2",
    "addr:street":"Rue Jean-Talon E",
    "iso:country":"CA",
    "sg:address":"1226 Rue Jean-Talon E",
    "sg:city":"Montreal",
    "sg:classifiers":[
        {
            "category":"Wholesale",
            "subcategory":"Non-durable Goods",
            "type":"Manufacturing & Wholesale Goods"
        }
    ],
    "sg:phone":"+1 514 495 3353",
    "sg:postcode":"H2R 1W2",
    "sg:province":"QC",
    "sg:tags":[
        "leather",
        "clothes"
    ],
    "wof:name":"Creations Jenny",
    "wof:placetype":"venue"
},
  "geometry": {"coordinates":[-73.61084,45.543541],"type":"Point"}
}