{
  "type": "Feature",
  "properties": {
    "addr:full":"1878 Kennedy Rd Scarborough ON M1P 2L8",
    "addr:housenumber":"1878",
    "addr:postcode":"m1p 2l8",
    "addr:street":"Kennedy Rd",
    "iso:country":"CA",
    "sg:address":"1878 Kennedy Rd",
    "sg:city":"Scarborough",
    "sg:classifiers":[
        {
            "category":"Food & Beverages",
            "subcategory":"Specialty",
            "type":"Retail Goods"
        }
    ],
    "sg:phone":"+1 416 298 3829",
    "sg:postcode":"M1P 2L8",
    "sg:province":"ON",
    "sg:tags":[
        "health",
        "diet"
    ],
    "wof:name":"Nature's Choice",
    "wof:placetype":"venue"
},
  "geometry": {"coordinates":[-79.281387,43.766327],"type":"Point"}
}