{
  "type": "Feature",
  "properties": {
    "addr:full":"1564 Royal York Rd Etobicoke ON M9P 3C3",
    "addr:housenumber":"1564",
    "addr:postcode":"m9p 3c3",
    "addr:street":"Royal York Rd",
    "iso:country":"CA",
    "sg:address":"1564 Royal York Rd",
    "sg:city":"Etobicoke",
    "sg:classifiers":[
        {
            "category":"Cinema",
            "subcategory":"Movie Rental",
            "type":"Entertainment"
        }
    ],
    "sg:phone":"+1 416 245 5759",
    "sg:postcode":"M9P 3C3",
    "sg:province":"ON",
    "sg:tags":[
        "leasing",
        "video",
        "disc",
        "tape"
    ],
    "wof:name":"Blockbuster Video",
    "wof:placetype":"venue"
},
  "geometry": {"coordinates":[-79.53310399999999,43.696686],"type":"Point"}
}