{
  "type": "Feature",
  "properties": {
    "iso:country":"CA",
    "sg:address":"45 Mac Phee Ave",
    "sg:city":"Souris",
    "sg:classifiers":[
        {
            "category":"Restaurant",
            "type":"Food & Drink"
        }
    ],
    "sg:phone":"+1 902 687 4200",
    "sg:postcode":"C0A 2B0",
    "sg:province":"PE",
    "wof:name":"Shirley's Place",
    "wof:placetype":"venue"
},
  "geometry": {"coordinates":[-62.2451324463,46.3485641479],"type":"Point"}
}