{
  "type": "Feature",
  "properties": {
    "iso:country":"CA",
    "sg:address":"1 Rue Mcgill",
    "sg:city":"Montreal",
    "sg:classifiers":[
        {
            "category":"Wholesale",
            "subcategory":"Machinery & Supplies",
            "type":"Manufacturing & Wholesale Goods"
        }
    ],
    "sg:phone":"+1 514 285 9070",
    "sg:postcode":"H2Y 4A3",
    "sg:province":"QC",
    "sg:tags":[
        "ship",
        "broker"
    ],
    "wof:name":"Anderson-Sima Maritime Inc",
    "wof:placetype":"venue"
},
  "geometry": {"coordinates":[-73.552948,45.49889],"type":"Point"}
}