{
  "type": "Feature",
  "properties": {
    "iso:country":"CA",
    "sg:address":"7130 Fisher Rd SE # 100",
    "sg:city":"Calgary",
    "sg:classifiers":[
        {
            "category":"Home & Garden",
            "subcategory":"Home Furnishings",
            "type":"Retail Goods"
        }
    ],
    "sg:phone":"+1 403 292 9444",
    "sg:postcode":"T2H 0W3",
    "sg:province":"AB",
    "sg:tags":[
        "shop",
        "fabric",
        "quilting"
    ],
    "wof:name":"Fanny's Fabrics Ltd",
    "wof:placetype":"venue"
},
  "geometry": {"coordinates":[-114.068031311,50.9908065796],"type":"Point"}
}