{
  "type": "Feature",
  "properties": {
    "addr:full":"Maple ON L6A 1P4",
    "addr:postcode":"l6a 1p4",
    "iso:country":"CA",
    "sg:city":"Maple",
    "sg:classifiers":[
        {
            "category":"Health Services",
            "subcategory":"Doctor",
            "type":"Services"
        }
    ],
    "sg:phone":"+1 905 832 4886",
    "sg:postcode":"L6A 1P4",
    "sg:province":"ON",
    "sg:tags":[
        "dentist"
    ],
    "wof:name":"Maple Dental Ctr",
    "wof:placetype":"venue"
},
  "geometry": {"coordinates":[-79.50865899999999,43.83794],"type":"Point"}
}