{
  "type": "Feature",
  "properties": {
    "addr:full":"Sainte-Julie QC J3E 1Z3",
    "addr:postcode":"j3e 1z3",
    "iso:country":"CA",
    "sg:city":"Sainte-Julie",
    "sg:classifiers":[
        {
            "category":"Retail",
            "subcategory":"Auto Repair",
            "type":"Services"
        }
    ],
    "sg:phone":"+1 450 922 8400",
    "sg:postcode":"J3E 1Z3",
    "sg:province":"QC",
    "sg:tags":[
        "conversion",
        "van",
        "work",
        "metal",
        "accessory",
        "truck",
        "sheet",
        "contractor"
    ],
    "wof:name":"Techno-Fab 9000 Inc",
    "wof:placetype":"venue"
},
  "geometry": {"coordinates":[-73.338623,45.577084],"type":"Point"}
}