{
  "type": "Feature",
  "properties": {
    "addr:full":"Toronto ON M5C 2R9",
    "addr:postcode":"m5c 2r9",
    "iso:country":"CA",
    "sg:city":"Toronto",
    "sg:classifiers":[
        {
            "category":"Professional",
            "subcategory":"Lawyer & Legal Services",
            "type":"Services"
        }
    ],
    "sg:phone":"+1 416 367 0680",
    "sg:postcode":"M5C 2R9",
    "sg:province":"ON",
    "sg:tags":[
        "attorney"
    ],
    "wof:name":"Caskie, Terrence W",
    "wof:placetype":"venue"
},
  "geometry": {"coordinates":[-79.378204,43.651966],"type":"Point"}
}