{
  "type": "Feature",
  "properties": {
    "iso:country":"CA",
    "sg:address":"PO Box 225",
    "sg:city":"Madeira Park",
    "sg:classifiers":[
        {
            "category":"Building & Trades",
            "subcategory":"Electrical",
            "type":"Services"
        }
    ],
    "sg:phone":"+1 604 883 9309",
    "sg:postcode":"V0N 2H0",
    "sg:province":"BC",
    "sg:tags":[
        "electric",
        "contractor"
    ],
    "wof:name":"Reid Electric",
    "wof:placetype":"venue"
},
  "geometry": {"coordinates":[-124.02137,49.613037],"type":"Point"}
}