{
  "type": "Feature",
  "properties": {
    "iso:country":"CA",
    "sg:address":"510 New Maryland Hwy",
    "sg:city":"New Maryland",
    "sg:classifiers":[
        {
            "category":"Retail",
            "subcategory":"Auto Repair",
            "type":"Services"
        }
    ],
    "sg:phone":"+1 506 459 4782",
    "sg:postcode":"E3C 1K1",
    "sg:province":"NB",
    "sg:tags":[
        "repairing",
        "automobile"
    ],
    "wof:name":"Meineke Discount Mufflers",
    "wof:placetype":"venue"
},
  "geometry": {"coordinates":[-66.6849060059,45.8908462524],"type":"Point"}
}