{
  "type": "Feature",
  "properties": {
    "addr:full":"2053 73rd Ave NE Canoe BC V0E 1K0",
    "addr:housenumber":"2053",
    "addr:postcode":"v0e 1k0",
    "addr:street":"73Rd Ave Ne",
    "iso:country":"CA",
    "sg:address":"2053 73rd Ave NE",
    "sg:city":"Canoe",
    "sg:classifiers":[
        {
            "category":"Recreation",
            "subcategory":"Marina",
            "type":"Entertainment"
        }
    ],
    "sg:phone":"+1 250 832 5224",
    "sg:postcode":"V0E 1K0",
    "sg:province":"BC",
    "wof:name":"Captain's Cove Marina",
    "wof:placetype":"venue"
},
  "geometry": {"coordinates":[-119.07890319800001,50.7899589539],"type":"Point"}
}