{
  "type": "Feature",
  "properties": {
    "addr:full":"722 Rte Marie-Victorin Sorel-Tracy QC J3R 1K7",
    "addr:housenumber":"722",
    "addr:postcode":"j3r 1k7",
    "addr:street":"Rte Marie-Victorin",
    "iso:country":"CA",
    "sg:address":"722 Rte Marie-Victorin",
    "sg:city":"Sorel-Tracy",
    "sg:classifiers":[
        {
            "category":"Bars & Pubs",
            "type":"Food & Drink"
        }
    ],
    "sg:phone":"+1 450 743 5270",
    "sg:postcode":"J3R 1K7",
    "sg:province":"QC",
    "sg:tags":[
        "lounge",
        "cocktail"
    ],
    "wof:name":"Bar Salon Place Pigalle",
    "wof:placetype":"venue"
},
  "geometry": {"coordinates":[-73.125198,46.039867],"type":"Point"}
}