{
  "type": "Feature",
  "properties": {
    "iso:country":"CA",
    "sg:address":"889 Hot Springs Rd",
    "sg:city":"Harrison Hot Springs",
    "sg:classifiers":[
        {
            "category":"Food & Beverages",
            "subcategory":"Liquor & Beverages",
            "type":"Retail Goods"
        }
    ],
    "sg:phone":"+1 604 796 2969",
    "sg:postcode":"V0M 1K0",
    "sg:province":"BC",
    "sg:tags":[
        "store"
    ],
    "wof:name":"Bounty",
    "wof:placetype":"venue"
},
  "geometry": {"coordinates":[-121.78067016599999,49.2846794128],"type":"Point"}
}