{
  "type": "Feature",
  "properties": {
    "addr:full":"5136 48 St Rocky Mountain House AB T4T 1M4",
    "addr:housenumber":"5136",
    "addr:postcode":"t4t 1m4",
    "addr:street":"48 St Rocky",
    "iso:country":"CA",
    "sg:address":"5136 48 St",
    "sg:city":"Rocky Mountain House",
    "sg:classifiers":[
        {
            "category":"Social Services",
            "type":"Services"
        }
    ],
    "sg:phone":"+1 403 845 3419",
    "sg:postcode":"T4T 1M4",
    "sg:province":"AB",
    "sg:tags":[
        "counseling"
    ],
    "wof:name":"Burden Bearers of Canada",
    "wof:placetype":"venue"
},
  "geometry": {"coordinates":[-114.91641199999999,52.377106],"type":"Point"}
}