{
  "type": "Feature",
  "properties": {
    "addr:full":"500 George St S Peterborough ON K9J 3E5",
    "addr:housenumber":"500",
    "addr:postcode":"k9j 3e5",
    "addr:street":"George St S",
    "iso:country":"CA",
    "sg:address":"500 George St S",
    "sg:city":"Peterborough",
    "sg:classifiers":[
        {
            "category":"Banks & Credit Unions",
            "subcategory":"Bank",
            "type":"Services"
        }
    ],
    "sg:phone":"+1 705 741 2883",
    "sg:postcode":"K9J 3E5",
    "sg:province":"ON",
    "sg:tags":[
        "machine",
        "teller",
        "automated"
    ],
    "wof:name":"Insta Cash",
    "wof:placetype":"venue"
},
  "geometry": {"coordinates":[-78.31763458250001,44.2894172668],"type":"Point"}
}