{
  "type": "Feature",
  "properties": {
    "addr:full":"188 Victoria Ave Belleville ON K8N 2B8",
    "addr:housenumber":"188",
    "addr:postcode":"k8n 2b8",
    "addr:street":"Victoria Ave",
    "iso:country":"CA",
    "sg:address":"188 Victoria Ave",
    "sg:city":"Belleville",
    "sg:classifiers":[
        {
            "category":"Organizations",
            "subcategory":"Religious Organization",
            "type":"Services"
        }
    ],
    "sg:phone":"+1 613 962 3885",
    "sg:postcode":"K8N 2B8",
    "sg:province":"ON",
    "sg:tags":[
        "church"
    ],
    "wof:name":"Quinte Bible Chapel",
    "wof:placetype":"venue"
},
  "geometry": {"coordinates":[-77.372772,44.169533],"type":"Point"}
}