{
  "type": "Feature",
  "properties": {
    "addr:full":"361 Dufferin Ave London ON N6B 1Z5",
    "addr:housenumber":"361",
    "addr:postcode":"n6b 1z5",
    "addr:street":"Dufferin Ave",
    "iso:country":"CA",
    "sg:address":"361 Dufferin Ave",
    "sg:city":"London",
    "sg:classifiers":[
        {
            "category":"Professional",
            "subcategory":"Engineering",
            "type":"Services"
        }
    ],
    "sg:phone":"+1 519 672 8310",
    "sg:postcode":"N6B 1Z5",
    "sg:province":"ON",
    "sg:tags":[
        "engineer"
    ],
    "wof:name":"Development Engineering Ltd",
    "wof:placetype":"venue"
},
  "geometry": {"coordinates":[-81.243057251,42.9883804321],"type":"Point"}
}