{
  "type": "Feature",
  "properties": {
    "addr:full":"1183 Old Goulais Bay Rd Sault Ste Marie ON P6A 5K8",
    "addr:housenumber":"1183",
    "addr:postcode":"p6a 5k8",
    "addr:street":"Old Goulais Bay Rd",
    "iso:country":"CA",
    "sg:address":"1183 Old Goulais Bay Rd",
    "sg:city":"Sault Ste Marie",
    "sg:classifiers":[
        {
            "category":"Building & Trades",
            "subcategory":"Construction",
            "type":"Services"
        }
    ],
    "sg:phone":"+1 705 759 4491",
    "sg:postcode":"P6A 5K8",
    "sg:province":"ON",
    "sg:tags":[
        "excavating",
        "contractor"
    ],
    "wof:name":"Patrick Possamai Construction",
    "wof:placetype":"venue"
},
  "geometry": {"coordinates":[-84.343323,46.593353],"type":"Point"}
}