{
  "type": "Feature",
  "properties": {
    "addr:full":"606 Caledonia Rd York ON M6E 4V5",
    "addr:housenumber":"606",
    "addr:postcode":"m6e 4v5",
    "addr:street":"Caledonia Rd",
    "iso:country":"CA",
    "sg:address":"606 Caledonia Rd",
    "sg:city":"York",
    "sg:classifiers":[
        {
            "category":"Health Services",
            "subcategory":"Doctor",
            "type":"Services"
        }
    ],
    "sg:phone":"+1 416 787 7627",
    "sg:postcode":"M6E 4V5",
    "sg:province":"ON",
    "sg:tags":[
        "physician",
        "surgeon"
    ],
    "wof:name":"Tam, R MD",
    "wof:placetype":"venue"
},
  "geometry": {"coordinates":[-79.46238700000001,43.693478],"type":"Point"}
}