{
  "type": "Feature",
  "properties": {
    "addr:full":"Thompson MB R8N 0N3",
    "addr:postcode":"r8n 0n3",
    "iso:country":"CA",
    "sg:city":"Thompson",
    "sg:classifiers":[
        {
            "category":"Government",
            "subcategory":"Office",
            "type":"Public Place"
        }
    ],
    "sg:phone":"+1 204 677 6667",
    "sg:postcode":"R8N 0N3",
    "sg:province":"MB",
    "wof:name":"Manitoba Newcareers Program",
    "wof:placetype":"venue"
},
  "geometry": {"coordinates":[-97.849007,55.741905],"type":"Point"}
}