{
  "type": "Feature",
  "properties": {
    "addr:full":"15570 Yonge St Aurora ON L4G 1P2",
    "addr:housenumber":"15570",
    "addr:postcode":"l4g 1p2",
    "addr:street":"Yonge St",
    "iso:country":"CA",
    "sg:address":"15570 Yonge St",
    "sg:city":"Aurora",
    "sg:classifiers":[
        {
            "category":"Home & Garden",
            "subcategory":"Home Furnishings",
            "type":"Retail Goods"
        }
    ],
    "sg:phone":"+1 905 727 7347",
    "sg:postcode":"L4G 1P2",
    "sg:province":"ON",
    "sg:tags":[
        "lighting",
        "fixture"
    ],
    "wof:name":"Light Spot Ltd",
    "wof:placetype":"venue"
},
  "geometry": {"coordinates":[-79.4696807861,44.0076141357],"type":"Point"}
}