{
  "type": "Feature",
  "properties": {
    "addr:full":"207 King St Truro NS B2N 3L3",
    "addr:housenumber":"207",
    "addr:postcode":"b2n 3l3",
    "addr:street":"King St",
    "iso:country":"CA",
    "sg:address":"207 King St",
    "sg:city":"Truro",
    "sg:classifiers":[
        {
            "category":"Food & Beverages",
            "subcategory":"Groceries & Convenience Stores",
            "type":"Retail Goods"
        }
    ],
    "sg:phone":"+1 902 897 9922",
    "sg:postcode":"B2N 3L3",
    "sg:province":"NS",
    "sg:tags":[
        "grocer"
    ],
    "wof:name":"King Street Variety",
    "wof:placetype":"venue"
},
  "geometry": {"coordinates":[-63.283447,45.35788],"type":"Point"}
}