{
  "type": "Feature",
  "properties": {
    "addr:full":"Edmonton AB T5K 1V9",
    "addr:postcode":"t5k 1v9",
    "iso:country":"CA",
    "sg:city":"Edmonton",
    "sg:classifiers":[
        {
            "category":"Real Estate",
            "subcategory":"Real Estate Operator",
            "type":"Services"
        }
    ],
    "sg:phone":"+1 780 488 9322",
    "sg:postcode":"T5K 1V9",
    "sg:province":"AB",
    "sg:tags":[
        "apartment"
    ],
    "wof:name":"Centurian Towers Ltd",
    "wof:placetype":"venue"
},
  "geometry": {"coordinates":[-113.521523,53.542164],"type":"Point"}
}