{
  "type": "Feature",
  "properties": {
    "addr:full":"6812 Fairmount Dr SE Calgary AB T2H 0X3",
    "addr:housenumber":"6812",
    "addr:postcode":"t2h 0x3",
    "addr:street":"Fairmount Dr Se",
    "iso:country":"CA",
    "sg:address":"6812 Fairmount Dr SE",
    "sg:city":"Calgary",
    "sg:classifiers":[
        {
            "category":"Retail",
            "subcategory":"Auto Rental",
            "type":"Services"
        }
    ],
    "sg:phone":"+1 403 253 7000",
    "sg:postcode":"T2H 0X3",
    "sg:province":"AB",
    "sg:tags":[
        "renting",
        "automobile",
        "leasing",
        "truck"
    ],
    "wof:name":"Royalty Canada Auto Sales Ltd",
    "wof:placetype":"venue"
},
  "geometry": {"coordinates":[-114.06356,50.992596],"type":"Point"}
}