{
  "type": "Feature",
  "properties": {
    "iso:country":"CA",
    "sg:address":"2381 Railway Ave #L22",
    "sg:city":"Shell Lake",
    "sg:classifiers":[
        {
            "category":"Restaurant",
            "type":"Food & Drink"
        }
    ],
    "sg:phone":"+1 306 427 4888",
    "sg:postcode":"S0J 2G0",
    "sg:province":"SK",
    "wof:name":"Chippers Takeout",
    "wof:placetype":"venue"
},
  "geometry": {"coordinates":[-107.506530762,53.3656234741],"type":"Point"}
}