{
  "type": "Feature",
  "properties": {
    "addr:full":"605 Gray Ave Saskatoon SK S7N 3Y5",
    "addr:housenumber":"605",
    "addr:postcode":"s7n 3y5",
    "addr:street":"Gray Ave",
    "iso:country":"CA",
    "sg:address":"605 Gray Ave",
    "sg:city":"Saskatoon",
    "sg:classifiers":[
        {
            "category":"Retail",
            "subcategory":"Car Wash",
            "type":"Services"
        }
    ],
    "sg:phone":"+1 306 384 9274",
    "sg:postcode":"S7N 3Y5",
    "sg:province":"SK",
    "sg:tags":[
        "polishing",
        "washing"
    ],
    "wof:name":"Mister Bubbles Car Wash",
    "wof:placetype":"venue"
},
  "geometry": {"coordinates":[-106.595299,52.140263],"type":"Point"}
}