{
  "type": "Feature",
  "properties": {
    "addr:full":"548 1Re Rue Iberville QC J2X 3B4",
    "addr:housenumber":"548",
    "addr:postcode":"j2x 3b4",
    "addr:street":"1Re Rue Iberville",
    "iso:country":"CA",
    "sg:address":"548 1Re Rue",
    "sg:city":"Iberville",
    "sg:classifiers":[
        {
            "category":"Wholesale",
            "subcategory":"Stationery",
            "type":"Manufacturing & Wholesale Goods"
        }
    ],
    "sg:phone":"+1 450 346 8155",
    "sg:postcode":"J2X 3B4",
    "sg:province":"QC",
    "wof:name":"Papeterie Compatible Lebel Enr",
    "wof:placetype":"venue"
},
  "geometry": {"coordinates":[-73.228424,45.303219],"type":"Point"}
}