{
  "type": "Feature",
  "properties": {
    "addr:full":"2225 Village Rd Douglas Lake BC V0E 1S0",
    "addr:housenumber":"2225",
    "addr:postcode":"bc v0e 1s0",
    "addr:street":"Village Rd",
    "iso:country":"CA",
    "sg:address":"2225 Village Rd",
    "sg:city":"Douglas Lake",
    "sg:classifiers":[
        {
            "category":"Organizations",
            "subcategory":"Professional Association",
            "type":"Services"
        }
    ],
    "sg:phone":"+1 250 350 3342",
    "sg:postcode":"V0E 1S0",
    "sg:province":"BC",
    "sg:tags":[
        "native"
    ],
    "wof:name":"Upper Nicola Band Adm",
    "wof:placetype":"venue"
},
  "geometry": {"coordinates":[-120.28409600000001,50.139614],"type":"Point"}
}