{
  "type": "Feature",
  "properties": {
    "addr:full":"Sprucedale ON P0A 1Y0",
    "addr:postcode":"p0a 1y0",
    "iso:country":"CA",
    "sg:city":"Sprucedale",
    "sg:classifiers":[
        {
            "category":"Organizations",
            "subcategory":"Professional Association",
            "type":"Services"
        }
    ],
    "sg:phone":"+1 705 685 7911",
    "sg:postcode":"P0A 1Y0",
    "sg:province":"ON",
    "wof:name":"Doe Lake Girl Guide Camp",
    "wof:placetype":"venue"
},
  "geometry": {"coordinates":[-79.4652709961,45.4892463684],"type":"Point"}
}