{
  "type": "Feature",
  "properties": {
    "addr:full":"64 3rd Ave E Vancouver BC V5T 1C3",
    "addr:housenumber":"64",
    "addr:postcode":"v5t 1c3",
    "addr:street":"3Rd Ave E",
    "iso:country":"CA",
    "sg:address":"64 3rd Ave E",
    "sg:city":"Vancouver",
    "sg:classifiers":[
        {
            "category":"Manufacturing",
            "subcategory":"Paper Products",
            "type":"Manufacturing & Wholesale Goods"
        }
    ],
    "sg:phone":"+1 604 874 4522",
    "sg:postcode":"V5T 1C3",
    "sg:province":"BC",
    "sg:tags":[
        "tag"
    ],
    "wof:name":"Rupert's Place Tag Mfg Inc",
    "wof:placetype":"venue"
},
  "geometry": {"coordinates":[-123.103523,49.268147],"type":"Point"}
}