{
  "type": "Feature",
  "properties": {
    "iso:country":"CA",
    "sg:address":"218 Jane St",
    "sg:city":"Toronto",
    "sg:classifiers":[
        {
            "category":"Real Estate",
            "subcategory":"Architect",
            "type":"Services"
        }
    ],
    "sg:phone":"+1 416 763 5697",
    "sg:postcode":"M6S 3Y9",
    "sg:province":"ON",
    "wof:name":"Ronald Raanan Matthews Inc",
    "wof:placetype":"venue"
},
  "geometry": {"coordinates":[-79.48674800000001,43.654423],"type":"Point"}
}