{
  "type": "Feature",
  "properties": {
    "addr:full":"Beaver Creek YT Y0B 1A0",
    "addr:postcode":"y0b 1a0",
    "addr:street":"Beaver Creek",
    "iso:country":"CA",
    "sg:city":"Beaver Creek",
    "sg:classifiers":[
        {
            "category":"Travel",
            "subcategory":"Hotels & Motels",
            "type":"Entertainment"
        }
    ],
    "sg:phone":"+1 867 862 7223",
    "sg:postcode":"Y0B 1A0",
    "sg:province":"YT",
    "wof:name":"Ida's Motel & Cafe",
    "wof:placetype":"venue"
},
  "geometry": {"coordinates":[-140.87725800000001,62.379002],"type":"Point"}
}