{
  "type": "Feature",
  "properties": {
    "addr:full":"168 Harvey St Harbour Grace NL A0A 2M0",
    "addr:housenumber":"168",
    "addr:postcode":"a0a 2m0",
    "addr:street":"Harvey St",
    "iso:country":"CA",
    "sg:address":"168 Harvey St",
    "sg:city":"Harbour Grace",
    "sg:classifiers":[
        {
            "category":"Restaurant",
            "type":"Food & Drink"
        }
    ],
    "sg:phone":"+1 709 596 6013",
    "sg:postcode":"A0A 2M0",
    "sg:province":"NL",
    "wof:name":"Chong's Chop Suey",
    "wof:placetype":"venue"
},
  "geometry": {"coordinates":[-53.24401474,47.6816673279],"type":"Point"}
}