{
  "type": "Feature",
  "properties": {
    "addr:full":"Edmonton AB T5G 0X5",
    "addr:postcode":"t5g 0x5",
    "iso:country":"CA",
    "sg:city":"Edmonton",
    "sg:classifiers":[
        {
            "category":"Social Services",
            "type":"Services"
        }
    ],
    "sg:phone":"+1 780 450 2810",
    "sg:postcode":"T5G 0X5",
    "sg:province":"AB",
    "sg:tags":[
        "counseling"
    ],
    "wof:name":"Tacit Counselling Svc",
    "wof:placetype":"venue"
},
  "geometry": {"coordinates":[-113.521728516,53.5670471191],"type":"Point"}
}