{
  "type": "Feature",
  "properties": {
    "addr:full":"SE 28-13-1W Warren MB R0C 3E0",
    "addr:postcode":"r0c 3e0",
    "addr:street":"Se 28-13-1W",
    "iso:country":"CA",
    "sg:address":"SE 28-13-1W",
    "sg:city":"Warren",
    "sg:classifiers":[
        {
            "category":"Government",
            "subcategory":"Office",
            "type":"Public Place"
        }
    ],
    "sg:phone":"+1 204 322 5343",
    "sg:postcode":"R0C 3E0",
    "sg:province":"MB",
    "wof:name":"Manitoba Maintenance Yard",
    "wof:placetype":"venue"
},
  "geometry": {"coordinates":[-97.5513839722,50.1337890625],"type":"Point"}
}