{
  "type": "Feature",
  "properties": {
    "addr:full":"1201 105th St North Battleford SK S9A 1S8",
    "addr:housenumber":"1201",
    "addr:postcode":"s9a 1s8",
    "addr:street":"105Th St",
    "iso:country":"CA",
    "sg:address":"1201 105th St",
    "sg:city":"North Battleford",
    "sg:classifiers":[
        {
            "category":"Organizations",
            "subcategory":"Religious Organization",
            "type":"Services"
        }
    ],
    "sg:phone":"+1 306 445 3836",
    "sg:postcode":"S9A 1S8",
    "sg:province":"SK",
    "sg:tags":[
        "church"
    ],
    "wof:name":"Notre Dame Church",
    "wof:placetype":"venue"
},
  "geometry": {"coordinates":[-108.291901,52.77512],"type":"Point"}
}