{
  "type": "Feature",
  "properties": {
    "addr:full":"1339 Khalsa Dr # 202 Mississauga ON L5S 1W6",
    "addr:housenumber":"1339",
    "addr:postcode":"l5s 1w6",
    "addr:street":"Khalsa Dr # 202",
    "iso:country":"CA",
    "sg:address":"1339 Khalsa Dr # 202",
    "sg:city":"Mississauga",
    "sg:classifiers":[
        {
            "category":"Professional",
            "subcategory":"Accounting & Tax Preparation",
            "type":"Services"
        }
    ],
    "sg:phone":"+1 905 696 9486",
    "sg:postcode":"L5S 1W6",
    "sg:province":"ON",
    "sg:tags":[
        "bookkeeping",
        "return",
        "filing",
        "general"
    ],
    "wof:name":"Khalsa Accountax Svc",
    "wof:placetype":"venue"
},
  "geometry": {"coordinates":[-79.679306,43.673557],"type":"Point"}
}