{
  "type": "Feature",
  "properties": {
    "iso:country":"CA",
    "sg:address":"100 Colborne St W # 402",
    "sg:city":"Orillia",
    "sg:classifiers":[
        {
            "category":"Health Services",
            "subcategory":"Doctor",
            "type":"Services"
        }
    ],
    "sg:phone":"+1 705 323 9776",
    "sg:postcode":"L3V 2Y9",
    "sg:province":"ON",
    "sg:tags":[
        "physician",
        "surgeon"
    ],
    "wof:name":"Olupona, Sam MD",
    "wof:placetype":"venue"
},
  "geometry": {"coordinates":[-79.423576,44.605297],"type":"Point"}
}