{
  "type": "Feature",
  "properties": {
    "addr:full":"221 Main St Courtland ON N0J 1E0",
    "addr:housenumber":"221",
    "addr:postcode":"n0j 1e0",
    "addr:street":"Main St",
    "iso:country":"CA",
    "sg:address":"221 Main St",
    "sg:city":"Courtland",
    "sg:classifiers":[
        {
            "category":"Shopping",
            "subcategory":"Used Merchandise",
            "type":"Retail Goods"
        }
    ],
    "sg:phone":"+1 519 688 2626",
    "sg:postcode":"N0J 1E0",
    "sg:province":"ON",
    "sg:tags":[
        "furniture"
    ],
    "wof:name":"Freda's Home Town Store",
    "wof:placetype":"venue"
},
  "geometry": {"coordinates":[-80.623322,42.843227],"type":"Point"}
}