{
  "type": "Feature",
  "properties": {
    "iso:country":"CA",
    "sg:address":"6125 Trafalgar Rd",
    "sg:city":"Stellarton",
    "sg:classifiers":[
        {
            "category":"Social Services",
            "type":"Services"
        }
    ],
    "sg:phone":"+1 902 752 8400",
    "sg:postcode":"B0K 1S0",
    "sg:province":"NS",
    "sg:tags":[
        "senior",
        "citizen"
    ],
    "wof:name":"Senior Citizens Outreach",
    "wof:placetype":"venue"
},
  "geometry": {"coordinates":[-62.6596832275,45.5617446899],"type":"Point"}
}