{
  "type": "Feature",
  "properties": {
    "addr:full":"120 Du Festival Saint-Simeon QC G0T 1X0",
    "addr:housenumber":"120",
    "addr:postcode":"g0t 1x0",
    "addr:street":"Du Festival",
    "iso:country":"CA",
    "sg:address":"120 Du Festival",
    "sg:city":"Saint-Simeon",
    "sg:classifiers":[
        {
            "category":"Travel",
            "subcategory":"Campground",
            "type":"Entertainment"
        }
    ],
    "sg:phone":"+1 418 638 5253",
    "sg:postcode":"G0T 1X0",
    "sg:province":"QC",
    "wof:name":"Camping Municipal St-Simeon",
    "wof:placetype":"venue"
},
  "geometry": {"coordinates":[-69.87539672849999,47.8418731689],"type":"Point"}
}