{
  "type": "Feature",
  "properties": {
    "iso:country":"CA",
    "sg:address":"4518 17 Ave SE",
    "sg:city":"Calgary",
    "sg:classifiers":[
        {
            "category":"Shopping",
            "subcategory":"Musical Instruments",
            "type":"Retail Goods"
        }
    ],
    "sg:phone":"+1 403 248 4272",
    "sg:postcode":"T2A 0T8",
    "sg:province":"AB",
    "sg:tags":[
        "music",
        "dealer"
    ],
    "wof:name":"Harmony Lane Music Studios",
    "wof:placetype":"venue"
},
  "geometry": {"coordinates":[-113.96962738000001,51.0380744934],"type":"Point"}
}