{
  "type": "Feature",
  "properties": {
    "addr:full":"1525 Sherway Dr Mississauga ON L4X 1C5",
    "addr:housenumber":"1525",
    "addr:postcode":"l4x 1c5",
    "addr:street":"Sherway Dr",
    "iso:country":"CA",
    "sg:address":"1525 Sherway Dr",
    "sg:city":"Mississauga",
    "sg:classifiers":[
        {
            "category":"Education",
            "subcategory":"School",
            "type":"Public Place"
        }
    ],
    "sg:phone":"+1 905 272 4303",
    "sg:postcode":"L4X 1C5",
    "sg:province":"ON",
    "wof:name":"Isna Islamic School",
    "wof:placetype":"venue"
},
  "geometry": {"coordinates":[-79.568138,43.603168],"type":"Point"}
}