{
  "type": "Feature",
  "properties": {
    "addr:full":"5045 Townline Rd R Murillo ON P0T 2G0",
    "addr:housenumber":"5045",
    "addr:postcode":"p0t 2g0",
    "addr:street":"Townline Rd R Murillo",
    "iso:country":"CA",
    "sg:address":"5045 Townline Rd R",
    "sg:city":"Murillo",
    "sg:classifiers":[
        {
            "category":"Organizations",
            "subcategory":"Religious Organization",
            "type":"Services"
        }
    ],
    "sg:phone":"+1 807 935 2890",
    "sg:postcode":"P0T 2G0",
    "sg:province":"ON",
    "sg:tags":[
        "church"
    ],
    "wof:name":"St Augustine Church",
    "wof:placetype":"venue"
},
  "geometry": {"coordinates":[-89.507431,48.411819],"type":"Point"}
}