{
  "type": "Feature",
  "properties": {
    "addr:full":"Lasalle QC H8R 2A5",
    "addr:postcode":"h8r 2a5",
    "iso:country":"CA",
    "sg:city":"Lasalle",
    "sg:classifiers":[
        {
            "category":"Bars & Pubs",
            "type":"Food & Drink"
        }
    ],
    "sg:phone":"+1 514 366 1363",
    "sg:postcode":"H8R 2A5",
    "sg:province":"QC",
    "sg:tags":[
        "lounge",
        "cocktail"
    ],
    "wof:name":"Bar L'Excuse",
    "wof:placetype":"venue"
},
  "geometry": {"coordinates":[-73.636047,45.421803],"type":"Point"}
}