{
  "type": "Feature",
  "properties": {
    "addr:full":"1853 Boul Dagenais O Laval QC H7L 5A3",
    "addr:housenumber":"1853",
    "addr:postcode":"h7l 5a3",
    "addr:street":"Boul Dagenais O",
    "iso:country":"CA",
    "sg:address":"1853 Boul Dagenais O",
    "sg:city":"Laval",
    "sg:classifiers":[
        {
            "category":"Manufacturing",
            "subcategory":"Metals",
            "type":"Manufacturing & Wholesale Goods"
        }
    ],
    "sg:phone":"+1 450 625 1230",
    "sg:postcode":"H7L 5A3",
    "sg:province":"QC",
    "sg:tags":[
        "product",
        "wire"
    ],
    "wof:name":"Multi Fil Metalliques",
    "wof:placetype":"venue"
},
  "geometry": {"coordinates":[-73.758247,45.593185],"type":"Point"}
}