{
  "type": "Feature",
  "properties": {
    "iso:country":"CA",
    "sg:address":"1017 Rue Longpre",
    "sg:city":"Mascouche",
    "sg:classifiers":[
        {
            "category":"Building & Trades",
            "subcategory":"Cleaning & Sanitation",
            "type":"Services"
        }
    ],
    "sg:phone":"+1 450 474 5461",
    "sg:postcode":"J7K 2X6",
    "sg:province":"QC",
    "sg:tags":[
        "window",
        "janitor"
    ],
    "wof:name":"Agence DE Nettoyage Du Nord",
    "wof:placetype":"venue"
},
  "geometry": {"coordinates":[-73.59604644780001,45.7441864014],"type":"Point"}
}