{
  "type": "Feature",
  "properties": {
    "addr:full":"794 Rue Principale Saint-Amable QC J0L 1N0",
    "addr:housenumber":"794",
    "addr:postcode":"j0l 1n0",
    "addr:street":"Rue Principale",
    "iso:country":"CA",
    "sg:address":"794 Rue Principale",
    "sg:city":"Saint-Amable",
    "sg:classifiers":[
        {
            "category":"Personal",
            "subcategory":"Beauty Salon",
            "type":"Services"
        }
    ],
    "sg:phone":"+1 450 649 7515",
    "sg:postcode":"J0L 1N0",
    "sg:province":"QC",
    "wof:name":"Chez Manon Coiffure",
    "wof:placetype":"venue"
},
  "geometry": {"coordinates":[-73.299835,45.647957],"type":"Point"}
}