{
  "type": "Feature",
  "properties": {
    "addr:full":"PO Box 266 Rainbow Lake AB T0H 2Y0",
    "addr:housenumber":"po",
    "addr:postcode":"t0h 2y0",
    "addr:street":"Box 266 Rainbow",
    "iso:country":"CA",
    "sg:address":"PO Box 266",
    "sg:city":"Rainbow Lake",
    "sg:classifiers":[
        {
            "category":"Education",
            "subcategory":"Library",
            "type":"Public Place"
        }
    ],
    "sg:phone":"+1 780 956 3656",
    "sg:postcode":"T0H 2Y0",
    "sg:province":"AB",
    "wof:name":"Rainbow Lake Municipal Library",
    "wof:placetype":"venue"
},
  "geometry": {"coordinates":[-119.410248,58.499573],"type":"Point"}
}