{
  "type": "Feature",
  "properties": {
    "addr:full":"Surrey BC V3S 8P5",
    "addr:postcode":"v3s 8p5",
    "iso:country":"CA",
    "sg:city":"Surrey",
    "sg:classifiers":[
        {
            "category":"Building & Trades",
            "subcategory":"Construction",
            "type":"Services"
        }
    ],
    "sg:phone":"+1 604 533 7325",
    "sg:postcode":"V3S 8P5",
    "sg:province":"BC",
    "sg:tags":[
        "downspouts",
        "gutter"
    ],
    "wof:name":"Pro Image Gutters",
    "wof:placetype":"venue"
},
  "geometry": {"coordinates":[-122.681549,49.10268],"type":"Point"}
}