{
  "type": "Feature",
  "properties": {
    "addr:full":"58 Buell St Brockville ON K6V 4Y2",
    "addr:housenumber":"58",
    "addr:postcode":"k6v 4y2",
    "addr:street":"Buell St",
    "iso:country":"CA",
    "sg:address":"58 Buell St",
    "sg:city":"Brockville",
    "sg:classifiers":[
        {
            "category":"Home & Garden",
            "subcategory":"Furniture",
            "type":"Retail Goods"
        }
    ],
    "sg:phone":"+1 613 342 8037",
    "sg:postcode":"K6V 4Y2",
    "sg:province":"ON",
    "sg:tags":[
        "mattress"
    ],
    "wof:name":"Bluell Street Sleep Ctr",
    "wof:placetype":"venue"
},
  "geometry": {"coordinates":[-75.688057,44.590378],"type":"Point"}
}