{
  "type": "Feature",
  "properties": {
    "iso:country":"CA",
    "sg:address":"1003 Brook Rd",
    "sg:city":"Athelstan",
    "sg:classifiers":[
        {
            "category":"Manufacturing",
            "subcategory":"Metals",
            "type":"Manufacturing & Wholesale Goods"
        }
    ],
    "sg:phone":"+1 450 264 4941",
    "sg:postcode":"J0S 1A0",
    "sg:province":"QC",
    "sg:tags":[
        "steel"
    ],
    "wof:name":"Gdl Fabrication",
    "wof:placetype":"venue"
},
  "geometry": {"coordinates":[-74.1755142212,45.0360450745],"type":"Point"}
}