{
  "type": "Feature",
  "properties": {
    "addr:full":"3577 Rue Sainte-Catherine E Montreal QC H1W 2E6",
    "addr:housenumber":"3577",
    "addr:postcode":"h1w 2e6",
    "addr:street":"Rue Sainte-Catherine E",
    "iso:country":"CA",
    "sg:address":"3577 Rue Sainte-Catherine E",
    "sg:city":"Montreal",
    "sg:classifiers":[
        {
            "category":"Organizations",
            "subcategory":"Professional Association",
            "type":"Services"
        }
    ],
    "sg:phone":"+1 514 528 1083",
    "sg:postcode":"H1W 2E6",
    "sg:province":"QC",
    "wof:name":"Societe Des Chefs Cuisiniers",
    "wof:placetype":"venue"
},
  "geometry": {"coordinates":[-73.5388336182,45.54322052],"type":"Point"}
}