{
  "type": "Feature",
  "properties": {
    "addr:full":"Vancouver BC V6A 1E1",
    "addr:postcode":"v6a 1e1",
    "iso:country":"CA",
    "sg:city":"Vancouver",
    "sg:classifiers":[
        {
            "category":"Wholesale",
            "subcategory":"Home Furnishings",
            "type":"Manufacturing & Wholesale Goods"
        }
    ],
    "sg:phone":"+1 604 255 4242",
    "sg:postcode":"V6A 1E1",
    "sg:province":"BC",
    "sg:tags":[
        "curtain",
        "drapery"
    ],
    "wof:name":"Tritex Fabrics Ltd",
    "wof:placetype":"venue"
},
  "geometry": {"coordinates":[-123.090919,49.284077],"type":"Point"}
}