{
  "type": "Feature",
  "properties": {
    "addr:full":"Bradford ON L3Z 2B6",
    "addr:postcode":"l3z 2b6",
    "iso:country":"CA",
    "sg:city":"Bradford",
    "sg:classifiers":[
        {
            "category":"Health Services",
            "subcategory":"Doctor",
            "type":"Services"
        }
    ],
    "sg:phone":"+1 905 775 0081",
    "sg:postcode":"L3Z 2B6",
    "sg:province":"ON",
    "sg:tags":[
        "physician",
        "surgeon"
    ],
    "wof:name":"Tsang, Andy MD",
    "wof:placetype":"venue"
},
  "geometry": {"coordinates":[-79.5609741211,44.1152954102],"type":"Point"}
}