{
  "type": "Feature",
  "properties": {
    "addr:full":"Beaupre QC G0A 1E0",
    "addr:postcode":"g0a 1e0",
    "addr:street":"Beaupre",
    "iso:country":"CA",
    "sg:city":"Beaupre",
    "sg:classifiers":[
        {
            "category":"Shopping",
            "subcategory":"Bicycles & Sporting Goods",
            "type":"Retail Goods"
        }
    ],
    "sg:phone":"+1 418 827 1717",
    "sg:postcode":"G0A 1E0",
    "sg:province":"QC",
    "sg:tags":[
        "equipment",
        "skiing"
    ],
    "wof:name":"Brunelle Sport",
    "wof:placetype":"venue"
},
  "geometry": {"coordinates":[-70.8943786621,47.0480804443],"type":"Point"}
}