{
  "type": "Feature",
  "properties": {
    "addr:full":"Joseph Port Carling ON P0B 1J0",
    "addr:postcode":"p0b 1j0",
    "addr:street":"Joseph",
    "iso:country":"CA",
    "sg:address":"Joseph",
    "sg:city":"Port Carling",
    "sg:classifiers":[
        {
            "category":"Recreation",
            "type":"Entertainment"
        }
    ],
    "sg:phone":"+1 705 765 3150",
    "sg:postcode":"P0B 1J0",
    "sg:province":"ON",
    "sg:tags":[
        "club",
        "curling"
    ],
    "wof:name":"Port Carling Curling Rink",
    "wof:placetype":"venue"
},
  "geometry": {"coordinates":[-79.5717468262,45.1131095886],"type":"Point"}
}