{
  "type": "Feature",
  "properties": {
    "iso:country":"CA",
    "sg:address":"4232 93 St NW",
    "sg:city":"Edmonton",
    "sg:classifiers":[
        {
            "category":"Organizations",
            "subcategory":"Labor Organization",
            "type":"Services"
        }
    ],
    "sg:phone":"+1 780 462 5076",
    "sg:postcode":"T6E 5P5",
    "sg:province":"AB",
    "wof:name":"International Brotherhood-Elec",
    "wof:placetype":"venue"
},
  "geometry": {"coordinates":[-113.472412109,53.4792518616],"type":"Point"}
}