{
  "type": "Feature",
  "properties": {
    "addr:full":"Calgary AB T2P 0T9",
    "addr:postcode":"t2p 0t9",
    "iso:country":"CA",
    "sg:city":"Calgary",
    "sg:classifiers":[
        {
            "category":"Real Estate",
            "subcategory":"Surveying",
            "type":"Services"
        }
    ],
    "sg:phone":"+1 403 234 7599",
    "sg:postcode":"T2P 0T9",
    "sg:province":"AB",
    "sg:tags":[
        "surveyor"
    ],
    "wof:name":"All-West Surveys Ltd",
    "wof:placetype":"venue"
},
  "geometry": {"coordinates":[-114.07648500000001,51.047676],"type":"Point"}
}