{
  "type": "Feature",
  "properties": {
    "addr:full":"15 Rutland Ave Warren ON P0H 2N0",
    "addr:housenumber":"15",
    "addr:postcode":"p0h 2n0",
    "addr:street":"Rutland Ave",
    "iso:country":"CA",
    "sg:address":"15 Rutland Ave",
    "sg:city":"Warren",
    "sg:classifiers":[
        {
            "category":"Professional",
            "type":"Services"
        }
    ],
    "sg:phone":"+1 705 967 0175",
    "sg:postcode":"P0H 2N0",
    "sg:province":"ON",
    "sg:tags":[
        "establishment",
        "butchering"
    ],
    "wof:name":"Bruno's Meats & Variety Inc",
    "wof:placetype":"venue"
},
  "geometry": {"coordinates":[-80.302322,46.440609],"type":"Point"}
}