{
  "type": "Feature",
  "properties": {
    "addr:full":"15 1/2 Windsor St Hamilton ON L8R 2G9",
    "addr:housenumber":"1 / 2",
    "addr:postcode":"l8r 2g9",
    "addr:street":"15;Windsor St",
    "iso:country":"CA",
    "sg:address":"15 1/2 Windsor St",
    "sg:city":"Hamilton",
    "sg:classifiers":[
        {
            "category":"Freight",
            "type":"Transportation"
        }
    ],
    "sg:phone":"+1 905 528 3393",
    "sg:postcode":"L8R 2G9",
    "sg:province":"ON",
    "sg:tags":[
        "mover",
        "trucking"
    ],
    "wof:name":"Stanley Pack Cartage & Moving",
    "wof:placetype":"venue"
},
  "geometry": {"coordinates":[-79.873192,43.265091],"type":"Point"}
}