{
  "type": "Feature",
  "properties": {
    "addr:full":"7112 Kingsway Burnaby BC V5E 1E8",
    "addr:housenumber":"7112",
    "addr:postcode":"v5e 1e8",
    "addr:street":"Kingsway",
    "iso:country":"CA",
    "sg:address":"7112 Kingsway",
    "sg:city":"Burnaby",
    "sg:classifiers":[
        {
            "category":"Autos & Motor Vehicles",
            "subcategory":"Automobile Sales",
            "type":"Retail Goods"
        }
    ],
    "sg:phone":"+1 604 526 1933",
    "sg:postcode":"V5E 1E8",
    "sg:province":"BC",
    "sg:tags":[
        "car",
        "dealer"
    ],
    "wof:name":"Collins Car Sales Ltd",
    "wof:placetype":"venue"
},
  "geometry": {"coordinates":[-122.95713000000001,49.218311],"type":"Point"}
}