{
  "type": "Feature",
  "properties": {
    "iso:country":"CA",
    "sg:address":"5630 Doncaster Rd",
    "sg:city":"Gloucester",
    "sg:classifiers":[
        {
            "category":"Building & Trades",
            "subcategory":"Construction",
            "type":"Services"
        }
    ],
    "sg:phone":"+1 613 822 3300",
    "sg:postcode":"K1G 3N4",
    "sg:province":"ON",
    "sg:tags":[
        "excavating",
        "contractor"
    ],
    "wof:name":"Dalcon",
    "wof:placetype":"venue"
},
  "geometry": {"coordinates":[-75.56353759770001,45.2997665405],"type":"Point"}
}