{
  "type": "Feature",
  "properties": {
    "iso:country":"CA",
    "sg:city":"North Saanich",
    "sg:classifiers":[
        {
            "category":"Education",
            "subcategory":"Special Training",
            "type":"Public Place"
        }
    ],
    "sg:phone":"+1 250 656 2833",
    "sg:postcode":"V8L 5V5",
    "sg:province":"BC",
    "sg:tags":[
        "rental",
        "aircraft",
        "leasing",
        "charter",
        "school"
    ],
    "wof:name":"Victoria Flying Club",
    "wof:placetype":"venue"
},
  "geometry": {"coordinates":[-123.420791626,48.6453132629],"type":"Point"}
}