{
  "type": "Feature",
  "properties": {
    "addr:full":"253 Summerlea Rd # 8 Brampton ON L6T 5A8",
    "addr:housenumber":"253",
    "addr:postcode":"l6t 5a8",
    "addr:street":"Summerlea Rd # 8",
    "iso:country":"CA",
    "sg:address":"253 Summerlea Rd # 8",
    "sg:city":"Brampton",
    "sg:classifiers":[
        {
            "category":"Organizations",
            "subcategory":"Religious Organization",
            "type":"Services"
        }
    ],
    "sg:phone":"+1 905 458 1443",
    "sg:postcode":"L6T 5A8",
    "sg:province":"ON",
    "sg:tags":[
        "church"
    ],
    "wof:name":"Brampton Victory Christian Ctr",
    "wof:placetype":"venue"
},
  "geometry": {"coordinates":[-79.699997,43.73494],"type":"Point"}
}