{
  "type": "Feature",
  "properties": {
    "addr:full":"82 Queen St S Mississauga ON L5M 1K6",
    "addr:housenumber":"82",
    "addr:postcode":"l5m 1k6",
    "addr:street":"Queen St S",
    "iso:country":"CA",
    "sg:address":"82 Queen St S",
    "sg:city":"Mississauga",
    "sg:classifiers":[
        {
            "category":"Professional",
            "subcategory":"Lawyer & Legal Services",
            "type":"Services"
        }
    ],
    "sg:phone":"+1 905 826 1453",
    "sg:postcode":"L5M 1K6",
    "sg:province":"ON",
    "sg:tags":[
        "attorney"
    ],
    "wof:name":"Richard T Bennett Barristers",
    "wof:placetype":"venue"
},
  "geometry": {"coordinates":[-79.5939025879,43.5489692688],"type":"Point"}
}