{
  "type": "Feature",
  "properties": {
    "addr:full":"3910 Rue Archambault Quebec QC G1P 3R9",
    "addr:housenumber":"3910",
    "addr:postcode":"g1p 3r9",
    "addr:street":"Rue Archambault",
    "iso:country":"CA",
    "sg:address":"3910 Rue Archambault",
    "sg:city":"Quebec",
    "sg:classifiers":[
        {
            "category":"Building & Trades",
            "subcategory":"Construction",
            "type":"Services"
        }
    ],
    "sg:phone":"+1 418 802 7473",
    "sg:postcode":"G1P 3R9",
    "sg:province":"QC",
    "sg:tags":[
        "builder",
        "repairer",
        "masonry",
        "chimney",
        "contractor"
    ],
    "wof:name":"Abordable Renovation Ls",
    "wof:placetype":"venue"
},
  "geometry": {"coordinates":[-71.298309,46.819962],"type":"Point"}
}