{
  "type": "Feature",
  "properties": {
    "addr:full":"1148 Weston Rd York ON M6N 3S4",
    "addr:housenumber":"1148",
    "addr:postcode":"m6n 3s4",
    "addr:street":"Weston Rd",
    "iso:country":"CA",
    "sg:address":"1148 Weston Rd",
    "sg:city":"York",
    "sg:classifiers":[
        {
            "category":"Restaurant",
            "type":"Food & Drink"
        }
    ],
    "sg:phone":"+1 416 767 4433",
    "sg:postcode":"M6N 3S4",
    "sg:province":"ON",
    "sg:tags":[
        "pizza"
    ],
    "wof:name":"Always 3 Pizza & Wings",
    "wof:placetype":"venue"
},
  "geometry": {"coordinates":[-79.489182,43.686642],"type":"Point"}
}