{
  "type": "Feature",
  "properties": {
    "iso:country":"CA",
    "sg:address":"525 Av DE LA Sapiniere",
    "sg:city":"Sainte-Marie",
    "sg:classifiers":[
        {
            "category":"Retail",
            "subcategory":"Laundry & Dry Cleaning",
            "type":"Services"
        }
    ],
    "sg:phone":"+1 418 387 2900",
    "sg:postcode":"G6E 1A9",
    "sg:province":"QC",
    "sg:tags":[
        "cleaners",
        "rug",
        "carpet"
    ],
    "wof:name":"Beauce Net Enr",
    "wof:placetype":"venue"
},
  "geometry": {"coordinates":[-71.04029846189999,46.4703407288],"type":"Point"}
}