{
  "type": "Feature",
  "properties": {
    "addr:full":"Clinton ON N0M 1L0",
    "addr:postcode":"n0m 1l0",
    "iso:country":"CA",
    "sg:city":"Clinton",
    "sg:classifiers":[
        {
            "category":"Organizations",
            "subcategory":"Professional Association",
            "type":"Services"
        }
    ],
    "sg:phone":"+1 519 482 1141",
    "sg:postcode":"N0M 1L0",
    "sg:province":"ON",
    "wof:name":"Huron County Aids Network",
    "wof:placetype":"venue"
},
  "geometry": {"coordinates":[-81.53969573969999,43.6176681519],"type":"Point"}
}