{
  "type": "Feature",
  "properties": {
    "iso:country":"CA",
    "sg:address":"16 Coldwater Rd",
    "sg:city":"North York",
    "sg:classifiers":[
        {
            "category":"Professional",
            "subcategory":"Computer Services",
            "type":"Services"
        }
    ],
    "sg:phone":"+1 416 445 7974",
    "sg:postcode":"M3B 1Y7",
    "sg:province":"ON",
    "wof:name":"Line Share Devices",
    "wof:placetype":"venue"
},
  "geometry": {"coordinates":[-79.3600234985,43.7550621033],"type":"Point"}
}