{
  "type": "Feature",
  "properties": {
    "addr:full":"51 Main St S Seaforth ON N0K 1W0",
    "addr:housenumber":"51",
    "addr:postcode":"n0k 1w0",
    "addr:street":"Main St S Seaforth",
    "iso:country":"CA",
    "sg:address":"51 Main St S",
    "sg:city":"Seaforth",
    "sg:classifiers":[
        {
            "category":"Shopping",
            "subcategory":"Stationery & Office Supplies",
            "type":"Retail Goods"
        }
    ],
    "sg:phone":"+1 519 527 1681",
    "sg:postcode":"N0K 1W0",
    "sg:province":"ON",
    "wof:name":"Pete's Paper Clip",
    "wof:placetype":"venue"
},
  "geometry": {"coordinates":[-81.394615,43.552223],"type":"Point"}
}