{
  "type": "Feature",
  "properties": {
    "iso:country":"CA",
    "sg:city":"Kitchener",
    "sg:classifiers":[
        {
            "category":"Health Services",
            "subcategory":"Doctor",
            "type":"Services"
        }
    ],
    "sg:phone":"+1 519 745 2333",
    "sg:postcode":"N2E 2M6",
    "sg:province":"ON",
    "sg:tags":[
        "dentist"
    ],
    "wof:name":"Lam, Gordon K W DDS",
    "wof:placetype":"venue"
},
  "geometry": {"coordinates":[-80.5013656616,43.418964386],"type":"Point"}
}