{
  "type": "Feature",
  "properties": {
    "addr:full":"347 William Ave Winnipeg MB R3A 0H8",
    "addr:housenumber":"347",
    "addr:postcode":"r3a 0h8",
    "addr:street":"William Ave",
    "iso:country":"CA",
    "sg:address":"347 William Ave",
    "sg:city":"Winnipeg",
    "sg:classifiers":[
        {
            "category":"Home & Garden",
            "subcategory":"Home Furnishings",
            "type":"Retail Goods"
        }
    ],
    "sg:phone":"+1 204 943 0999",
    "sg:postcode":"R3A 0H8",
    "sg:province":"MB",
    "sg:tags":[
        "lighting",
        "fixture"
    ],
    "wof:name":"Total Lighting Sales Ltd",
    "wof:placetype":"venue"
},
  "geometry": {"coordinates":[-97.143417,49.900337],"type":"Point"}
}