{
  "type": "Feature",
  "properties": {
    "addr:full":"Delta BC V4G 1G7",
    "addr:postcode":"v4g 1g7",
    "iso:country":"CA",
    "sg:city":"Delta",
    "sg:classifiers":[
        {
            "category":"Professional",
            "type":"Services"
        }
    ],
    "sg:phone":"+1 604 946 4447",
    "sg:postcode":"V4G 1G7",
    "sg:province":"BC",
    "sg:tags":[
        "consulting",
        "chemist"
    ],
    "wof:name":"Canadian Microanalytical Svc",
    "wof:placetype":"venue"
},
  "geometry": {"coordinates":[-122.990867615,49.1494064331],"type":"Point"}
}