{
  "type": "Feature",
  "properties": {
    "addr:full":"965 Northwest Rd Exmoor NB E9E 1L7",
    "addr:housenumber":"965",
    "addr:postcode":"e9e 1l7",
    "addr:street":"Northwest Rd",
    "iso:country":"CA",
    "sg:address":"965 Northwest Rd",
    "sg:city":"Exmoor",
    "sg:classifiers":[
        {
            "category":"Retail",
            "subcategory":"Auto Repair",
            "type":"Services"
        }
    ],
    "sg:phone":"+1 506 836 2700",
    "sg:postcode":"E9E 1L7",
    "sg:province":"NB",
    "sg:tags":[
        "body",
        "automobile",
        "painting"
    ],
    "wof:name":"Sunny Corner Collision Ctr",
    "wof:placetype":"venue"
},
  "geometry": {"coordinates":[-65.827263,46.974201],"type":"Point"}
}