{
  "type": "Feature",
  "properties": {
    "addr:full":"303 Wentworth St W Oshawa ON L1J 1M9",
    "addr:housenumber":"303",
    "addr:postcode":"l1j 1m9",
    "addr:street":"Wentworth St W",
    "iso:country":"CA",
    "sg:address":"303 Wentworth St W",
    "sg:city":"Oshawa",
    "sg:classifiers":[
        {
            "category":"Restaurant",
            "type":"Food & Drink"
        }
    ],
    "sg:phone":"+1 905 576 5221",
    "sg:postcode":"L1J 1M9",
    "sg:province":"ON",
    "wof:name":"Nelson's Restaurant",
    "wof:placetype":"venue"
},
  "geometry": {"coordinates":[-78.853859,43.869312],"type":"Point"}
}