{
  "type": "Feature",
  "properties": {
    "addr:full":"13 Rue Du Lac Saint-Magloire QC G0R 3M0",
    "addr:housenumber":"13",
    "addr:postcode":"g0r 3m0",
    "addr:street":"Rue Du Lac",
    "iso:country":"CA",
    "sg:address":"13 Rue Du Lac",
    "sg:city":"Saint-Magloire",
    "sg:classifiers":[
        {
            "category":"Recreation",
            "type":"Entertainment"
        }
    ],
    "sg:phone":"+1 418 257 4371",
    "sg:postcode":"G0R 3M0",
    "sg:province":"QC",
    "sg:tags":[
        "center"
    ],
    "wof:name":"Chalet Des Loisirs",
    "wof:placetype":"venue"
},
  "geometry": {"coordinates":[-70.289368,46.577644],"type":"Point"}
}