{
  "type": "Feature",
  "properties": {
    "addr:full":"613 Kingston Rd W Ajax ON L1S 6L9",
    "addr:housenumber":"613",
    "addr:postcode":"l1s 6l9",
    "addr:street":"Kingston Rd W",
    "iso:country":"CA",
    "sg:address":"613 Kingston Rd W",
    "sg:city":"Ajax",
    "sg:classifiers":[
        {
            "category":"Retail",
            "subcategory":"Laundry & Dry Cleaning",
            "type":"Services"
        }
    ],
    "sg:phone":"+1 905 683 9000",
    "sg:postcode":"L1S 6L9",
    "sg:province":"ON",
    "sg:tags":[
        "cleaners"
    ],
    "wof:name":"Snow White Dry Cleaners",
    "wof:placetype":"venue"
},
  "geometry": {"coordinates":[-79.0562362671,43.8542251587],"type":"Point"}
}