{
  "type": "Feature",
  "properties": {
    "iso:country":"CA",
    "sg:city":"Burnaby",
    "sg:classifiers":[
        {
            "category":"Restaurant",
            "type":"Food & Drink"
        }
    ],
    "sg:phone":"+1 604 444 2244",
    "sg:postcode":"V3J 7T9",
    "sg:province":"BC",
    "wof:name":"North Road Pizza",
    "wof:placetype":"venue"
},
  "geometry": {"coordinates":[-122.893127,49.254002],"type":"Point"}
}