{
  "type": "Feature",
  "properties": {
    "iso:country":"CA",
    "sg:city":"Woodbridge",
    "sg:classifiers":[
        {
            "category":"Building & Trades",
            "subcategory":"Construction",
            "type":"Services"
        }
    ],
    "sg:phone":"+1 905 265 9255",
    "sg:postcode":"L4L 8N1",
    "sg:province":"ON",
    "sg:tags":[
        "carpenter"
    ],
    "wof:name":"Eurowood Carpentry",
    "wof:placetype":"venue"
},
  "geometry": {"coordinates":[-79.6122970581,43.7712135315],"type":"Point"}
}