{
  "type": "Feature",
  "properties": {
    "addr:full":"Toronto ON M6H 4B1",
    "addr:postcode":"m6h 4b1",
    "iso:country":"CA",
    "sg:city":"Toronto",
    "sg:classifiers":[
        {
            "category":"Shopping",
            "type":"Retail Goods"
        }
    ],
    "sg:phone":"+1 416 536 6680",
    "sg:postcode":"M6H 4B1",
    "sg:province":"ON",
    "sg:tags":[
        "cosmetic",
        "perfume"
    ],
    "wof:name":"Luwinna Cosmetics & Fragrances",
    "wof:placetype":"venue"
},
  "geometry": {"coordinates":[-79.43435700000001,43.656773],"type":"Point"}
}