{
  "type": "Feature",
  "properties": {
    "addr:full":"130 Foord St Stellarton NS B0K 1S0",
    "addr:housenumber":"130",
    "addr:postcode":"b0k 1s0",
    "addr:street":"Foord St",
    "iso:country":"CA",
    "sg:address":"130 Foord St",
    "sg:city":"Stellarton",
    "sg:classifiers":[
        {
            "category":"Travel",
            "subcategory":"Hotels & Motels",
            "type":"Entertainment"
        }
    ],
    "sg:phone":"+1 902 752 8401",
    "sg:postcode":"B0K 1S0",
    "sg:province":"NS",
    "wof:name":"Heather Hotel & Convention Ctr",
    "wof:placetype":"venue"
},
  "geometry": {"coordinates":[-62.659859,45.559391],"type":"Point"}
}