{
  "type": "Feature",
  "properties": {
    "iso:country":"CA",
    "sg:city":"Craven",
    "sg:classifiers":[
        {
            "category":"Wholesale",
            "subcategory":"Machinery & Supplies",
            "type":"Manufacturing & Wholesale Goods"
        }
    ],
    "sg:phone":"+1 306 775 2992",
    "sg:postcode":"S0G 0W0",
    "sg:province":"SK",
    "sg:tags":[
        "agricultural",
        "implement"
    ],
    "wof:name":"Agro Salvage",
    "wof:placetype":"venue"
},
  "geometry": {"coordinates":[-104.808792114,50.707988739],"type":"Point"}
}