{
  "type": "Feature",
  "properties": {
    "addr:full":"2100 Danforth Ave Toronto ON M4C 1J9",
    "addr:housenumber":"2100",
    "addr:postcode":"m4c 1j9",
    "addr:street":"Danforth Ave",
    "iso:country":"CA",
    "sg:address":"2100 Danforth Ave",
    "sg:city":"Toronto",
    "sg:classifiers":[
        {
            "category":"Restaurant",
            "type":"Food & Drink"
        }
    ],
    "sg:phone":"+1 416 696 6663",
    "sg:postcode":"M4C 1J9",
    "sg:province":"ON",
    "wof:name":"Edie's Place Bar & Cafe",
    "wof:placetype":"venue"
},
  "geometry": {"coordinates":[-79.31220245359999,43.6859474182],"type":"Point"}
}