{
  "type": "Feature",
  "properties": {
    "addr:full":"5798 Rue Jean-Talon E Saint-Leonard QC H1S 1M2",
    "addr:housenumber":"5798",
    "addr:postcode":"h1s 1m2",
    "addr:street":"Rue Jean-Talon E",
    "iso:country":"CA",
    "sg:address":"5798 Rue Jean-Talon E",
    "sg:city":"Saint-Leonard",
    "sg:classifiers":[
        {
            "category":"Home & Garden",
            "subcategory":"Household Appliances",
            "type":"Retail Goods"
        }
    ],
    "sg:phone":"+1 514 251 7303",
    "sg:postcode":"H1S 1M2",
    "sg:province":"QC",
    "sg:tags":[
        "cleaners",
        "vacuum"
    ],
    "wof:name":"Electrolux Canada",
    "wof:placetype":"venue"
},
  "geometry": {"coordinates":[-73.58020019529999,45.5849609375],"type":"Point"}
}