{
  "type": "Feature",
  "properties": {
    "addr:full":"560 King St W Toronto ON M5V 1M3",
    "addr:housenumber":"560",
    "addr:postcode":"m5v 1m3",
    "addr:street":"King St W",
    "iso:country":"CA",
    "sg:address":"560 King St W",
    "sg:city":"Toronto",
    "sg:classifiers":[
        {
            "category":"Retail",
            "subcategory":"Auto Repair",
            "type":"Services"
        }
    ],
    "sg:phone":"+1 416 504 4010",
    "sg:postcode":"M5V 1M3",
    "sg:province":"ON",
    "sg:tags":[
        "repairing",
        "automobile"
    ],
    "wof:name":"Cars",
    "wof:placetype":"venue"
},
  "geometry": {"coordinates":[-79.398582,43.644901],"type":"Point"}
}