{
  "type": "Feature",
  "properties": {
    "addr:full":"574 Rue Principale Granby QC J2G 2X6",
    "addr:housenumber":"574",
    "addr:postcode":"j2g 2x6",
    "addr:street":"Rue Principale",
    "iso:country":"CA",
    "sg:address":"574 Rue Principale",
    "sg:city":"Granby",
    "sg:classifiers":[
        {
            "category":"Cinema",
            "subcategory":"Movie Rental",
            "type":"Entertainment"
        }
    ],
    "sg:phone":"+1 450 777 3393",
    "sg:postcode":"J2G 2X6",
    "sg:province":"QC",
    "sg:tags":[
        "leasing",
        "video",
        "disc",
        "tape"
    ],
    "wof:name":"Servideo",
    "wof:placetype":"venue"
},
  "geometry": {"coordinates":[-72.740776,45.406895],"type":"Point"}
}