{
  "type": "Feature",
  "properties": {
    "addr:full":"Etobicoke ON M9V 1B4",
    "addr:postcode":"m9v 1b4",
    "iso:country":"CA",
    "sg:city":"Etobicoke",
    "sg:classifiers":[
        {
            "category":"Personal",
            "subcategory":"Beauty Salon",
            "type":"Services"
        }
    ],
    "sg:phone":"+1 416 741 7282",
    "sg:postcode":"M9V 1B4",
    "sg:province":"ON",
    "wof:name":"Albion Mall Hair Stylist",
    "wof:placetype":"venue"
},
  "geometry": {"coordinates":[-79.581917,43.740089],"type":"Point"}
}