{
  "type": "Feature",
  "properties": {
    "addr:full":"Orangeville ON L9W 3X4",
    "addr:postcode":"l9w 3x4",
    "iso:country":"CA",
    "sg:city":"Orangeville",
    "sg:classifiers":[
        {
            "category":"Real Estate",
            "subcategory":"Real Estate Operator",
            "type":"Services"
        }
    ],
    "sg:phone":"+1 519 941 2310",
    "sg:postcode":"L9W 3X4",
    "sg:province":"ON",
    "sg:tags":[
        "condominium"
    ],
    "wof:name":"Dufferin Condominium Corp No 3",
    "wof:placetype":"venue"
},
  "geometry": {"coordinates":[-80.09963226319999,43.9234390259],"type":"Point"}
}