{
  "type": "Feature",
  "properties": {
    "addr:full":"9 James St Simcoe ON N3Y 1E1",
    "addr:housenumber":"9",
    "addr:postcode":"n3y 1e1",
    "addr:street":"James St",
    "iso:country":"CA",
    "sg:address":"9 James St",
    "sg:city":"Simcoe",
    "sg:classifiers":[
        {
            "category":"Home & Garden",
            "subcategory":"Building Materials",
            "type":"Retail Goods"
        }
    ],
    "sg:phone":"+1 519 426 0791",
    "sg:postcode":"N3Y 1E1",
    "sg:province":"ON",
    "sg:tags":[
        "lumber"
    ],
    "wof:name":"Pickard Lumber & Building Supl",
    "wof:placetype":"venue"
},
  "geometry": {"coordinates":[-80.303436,42.829441],"type":"Point"}
}