{
  "type": "Feature",
  "properties": {
    "addr:full":"Mississauga ON L5T 2J9",
    "addr:postcode":"l5t 2j9",
    "iso:country":"CA",
    "sg:city":"Mississauga",
    "sg:classifiers":[
        {
            "category":"Retail",
            "subcategory":"Auto Repair",
            "type":"Services"
        }
    ],
    "sg:phone":"+1 905 670 0277",
    "sg:postcode":"L5T 2J9",
    "sg:province":"ON",
    "sg:tags":[
        "fuel",
        "equipment",
        "injection"
    ],
    "wof:name":"Dal's Fuel Injection & Turbos",
    "wof:placetype":"venue"
},
  "geometry": {"coordinates":[-79.67289,43.667713],"type":"Point"}
}