{
  "type": "Feature",
  "properties": {
    "addr:full":"15 Mill St W Acton ON L7J 1G3",
    "addr:housenumber":"15",
    "addr:postcode":"l7j 1g3",
    "addr:street":"Mill St W",
    "iso:country":"CA",
    "sg:address":"15 Mill St W",
    "sg:city":"Acton",
    "sg:classifiers":[
        {
            "category":"Insurance",
            "subcategory":"Insurance Agent",
            "type":"Services"
        }
    ],
    "sg:phone":"+1 519 853 0150",
    "sg:postcode":"L7J 1G3",
    "sg:province":"ON",
    "wof:name":"Denny's Insurance",
    "wof:placetype":"venue"
},
  "geometry": {"coordinates":[-80.0421447754,43.6293182373],"type":"Point"}
}