{
  "type": "Feature",
  "properties": {
    "addr:full":"265 2nd Ave E Vancouver BC V5T 1B8",
    "addr:housenumber":"265",
    "addr:postcode":"v5t 1b8",
    "addr:street":"2Nd Ave E",
    "iso:country":"CA",
    "sg:address":"265 2nd Ave E",
    "sg:city":"Vancouver",
    "sg:classifiers":[
        {
            "category":"Professional",
            "subcategory":"Art Services",
            "type":"Services"
        }
    ],
    "sg:phone":"+1 604 876 5680",
    "sg:postcode":"V5T 1B8",
    "sg:province":"BC",
    "sg:tags":[
        "photographer"
    ],
    "wof:name":"Ron Sangha Photography",
    "wof:placetype":"venue"
},
  "geometry": {"coordinates":[-123.09902954099999,49.268447876],"type":"Point"}
}