{
  "type": "Feature",
  "properties": {
    "addr:full":"18158 102 Ave NW Edmonton AB T5S 1S7",
    "addr:housenumber":"18158",
    "addr:postcode":"t5s 1s7",
    "addr:street":"102 Ave Nw",
    "iso:country":"CA",
    "sg:address":"18158 102 Ave NW",
    "sg:city":"Edmonton",
    "sg:classifiers":[
        {
            "category":"Wholesale",
            "subcategory":"Durable Goods & Equipment",
            "type":"Manufacturing & Wholesale Goods"
        }
    ],
    "sg:phone":"+1 780 454 0156",
    "sg:postcode":"T5S 1S7",
    "sg:province":"AB",
    "sg:tags":[
        "representative",
        "manufacturer"
    ],
    "wof:name":"Focus Lighting Agencies Ltd",
    "wof:placetype":"venue"
},
  "geometry": {"coordinates":[-113.635391,53.543537],"type":"Point"}
}