{
  "type": "Feature",
  "properties": {
    "addr:full":"306 Juniper Dr Thompson MB R8N 0S9",
    "addr:housenumber":"306",
    "addr:postcode":"r8n 0s9",
    "addr:street":"Juniper Dr",
    "iso:country":"CA",
    "sg:address":"306 Juniper Dr",
    "sg:city":"Thompson",
    "sg:classifiers":[
        {
            "category":"Education",
            "subcategory":"School",
            "type":"Public Place"
        }
    ],
    "sg:phone":"+1 204 677 6242",
    "sg:postcode":"R8N 0S9",
    "sg:province":"MB",
    "wof:name":"Juniper School",
    "wof:placetype":"venue"
},
  "geometry": {"coordinates":[-97.860916,55.739132],"type":"Point"}
}