{
  "type": "Feature",
  "properties": {
    "addr:full":"84 Hamilton Dr Calgary AB T3R 1A2",
    "addr:housenumber":"84",
    "addr:postcode":"t3r 1a2",
    "addr:street":"Hamilton Dr",
    "iso:country":"CA",
    "sg:address":"84 Hamilton Dr",
    "sg:city":"Calgary",
    "sg:classifiers":[
        {
            "category":"Wholesale",
            "subcategory":"Non-durable Goods",
            "type":"Manufacturing & Wholesale Goods"
        }
    ],
    "sg:phone":"+1 403 274 3885",
    "sg:postcode":"T3R 1A2",
    "sg:province":"AB",
    "sg:tags":[
        "advertising"
    ],
    "wof:name":"Lawsuit Loan Corp",
    "wof:placetype":"venue"
},
  "geometry": {"coordinates":[-114.263794,51.1595],"type":"Point"}
}