{
  "type": "Feature",
  "properties": {
    "addr:full":"3718 103B St NW Edmonton AB T6J 2X9",
    "addr:housenumber":"3718",
    "addr:postcode":"t6j 2x9",
    "addr:street":"103B St Nw",
    "iso:country":"CA",
    "sg:address":"3718 103B St NW",
    "sg:city":"Edmonton",
    "sg:classifiers":[
        {
            "category":"Professional",
            "subcategory":"Management & Consulting",
            "type":"Services"
        }
    ],
    "sg:phone":"+1 780 413 6631",
    "sg:postcode":"T6J 2X9",
    "sg:province":"AB",
    "sg:tags":[
        "consultant",
        "business"
    ],
    "wof:name":"Wellar Consulting",
    "wof:placetype":"venue"
},
  "geometry": {"coordinates":[-113.49720001199999,53.4737052917],"type":"Point"}
}