{
  "type": "Feature",
  "properties": {
    "iso:country":"CA",
    "sg:city":"Oshawa",
    "sg:classifiers":[
        {
            "category":"Professional",
            "subcategory":"Lawyer & Legal Services",
            "type":"Services"
        }
    ],
    "sg:phone":"+1 905 576 5666",
    "sg:postcode":"L1H 8S5",
    "sg:province":"ON",
    "sg:tags":[
        "attorney"
    ],
    "wof:name":"Thomas, David B",
    "wof:placetype":"venue"
},
  "geometry": {"coordinates":[-78.861603,43.897438],"type":"Point"}
}