{
  "type": "Feature",
  "properties": {
    "addr:full":"St Albert AB T8N 5A4",
    "addr:postcode":"t8n 5a4",
    "iso:country":"CA",
    "sg:city":"St Albert",
    "sg:classifiers":[
        {
            "category":"Restaurant",
            "type":"Food & Drink"
        }
    ],
    "sg:phone":"+1 780 459 6401",
    "sg:postcode":"T8N 5A4",
    "sg:province":"AB",
    "wof:name":"Soup & Sandwich Shack",
    "wof:placetype":"venue"
},
  "geometry": {"coordinates":[-113.569252014,53.6368331909],"type":"Point"}
}