{
  "type": "Feature",
  "properties": {
    "iso:country":"CA",
    "sg:address":"63 Chesley St",
    "sg:city":"Southampton",
    "sg:classifiers":[
        {
            "category":"Building & Trades",
            "subcategory":"Construction",
            "type":"Services"
        }
    ],
    "sg:phone":"+1 519 797 2256",
    "sg:postcode":"N0H 2L0",
    "sg:province":"ON",
    "sg:tags":[
        "fire",
        "restoration",
        "damage"
    ],
    "wof:name":"Higgins Cleaning & Restoration",
    "wof:placetype":"venue"
},
  "geometry": {"coordinates":[-81.3615264893,44.5029945374],"type":"Point"}
}