{
  "type": "Feature",
  "properties": {
    "addr:full":"Vancouver BC V5M 1Y8",
    "addr:postcode":"v5m 1y8",
    "iso:country":"CA",
    "sg:city":"Vancouver",
    "sg:classifiers":[
        {
            "category":"Professional",
            "subcategory":"Engineering",
            "type":"Services"
        }
    ],
    "sg:phone":"+1 604 255 0828",
    "sg:postcode":"V5M 1Y8",
    "sg:province":"BC",
    "sg:tags":[
        "engineer"
    ],
    "wof:name":"Centennial Geotechnical Engrs",
    "wof:placetype":"venue"
},
  "geometry": {"coordinates":[-123.04765319800001,49.2618789673],"type":"Point"}
}