{
  "type": "Feature",
  "properties": {
    "addr:full":"PO Box 189 Wawota SK S0G 5A0",
    "addr:housenumber":"po",
    "addr:postcode":"s0g 5a0",
    "addr:street":"Box 189",
    "iso:country":"CA",
    "sg:address":"PO Box 189",
    "sg:city":"Wawota",
    "sg:classifiers":[
        {
            "category":"Organizations",
            "subcategory":"Religious Organization",
            "type":"Services"
        }
    ],
    "sg:phone":"+1 306 739 2222",
    "sg:postcode":"S0G 5A0",
    "sg:province":"SK",
    "sg:tags":[
        "church"
    ],
    "wof:name":"Wawota Alliance Church",
    "wof:placetype":"venue"
},
  "geometry": {"coordinates":[-102.028183,49.90321],"type":"Point"}
}