{
  "type": "Feature",
  "properties": {
    "addr:full":"6 Eastgate Dr Southampton ON N0H 2L0",
    "addr:housenumber":"6",
    "addr:postcode":"n0h 2l0",
    "addr:street":"Eastgate Dr",
    "iso:country":"CA",
    "sg:address":"6 Eastgate Dr",
    "sg:city":"Southampton",
    "sg:classifiers":[
        {
            "category":"Professional",
            "subcategory":"Management & Consulting",
            "type":"Services"
        }
    ],
    "sg:phone":"+1 519 797 3861",
    "sg:postcode":"N0H 2L0",
    "sg:province":"ON",
    "sg:tags":[
        "construction"
    ],
    "wof:name":"Technology Support Svc Inc",
    "wof:placetype":"venue"
},
  "geometry": {"coordinates":[-81.375427,44.481178],"type":"Point"}
}