{
  "type": "Feature",
  "properties": {
    "addr:full":"2112 21 St Coaldale AB T1M 1L9",
    "addr:housenumber":"2112",
    "addr:postcode":"t1m 1l9",
    "addr:street":"21 St",
    "iso:country":"CA",
    "sg:address":"2112 21 St",
    "sg:city":"Coaldale",
    "sg:classifiers":[
        {
            "category":"Education",
            "subcategory":"School",
            "type":"Public Place"
        }
    ],
    "sg:phone":"+1 403 345 3383",
    "sg:postcode":"T1M 1L9",
    "sg:province":"AB",
    "wof:name":"Kate Andrews High School",
    "wof:placetype":"venue"
},
  "geometry": {"coordinates":[-112.62512207,49.7252197266],"type":"Point"}
}