{
  "type": "Feature",
  "properties": {
    "addr:full":"21 Leeson Dr Chatham ON N7M 5T9",
    "addr:housenumber":"21",
    "addr:postcode":"n7m 5t9",
    "addr:street":"Leeson Dr",
    "iso:country":"CA",
    "sg:address":"21 Leeson Dr",
    "sg:city":"Chatham",
    "sg:classifiers":[
        {
            "category":"Manufacturing",
            "subcategory":"Printing",
            "type":"Manufacturing & Wholesale Goods"
        }
    ],
    "sg:phone":"+1 519 354 7735",
    "sg:postcode":"N7M 5T9",
    "sg:province":"ON",
    "sg:tags":[
        "screen"
    ],
    "wof:name":"Screen Craft",
    "wof:placetype":"venue"
},
  "geometry": {"coordinates":[-82.19487762449999,42.3927726746],"type":"Point"}
}