{
  "type": "Feature",
  "properties": {
    "iso:country":"CA",
    "sg:address":"3300 Boul DE LA Cote-Vertu # 304",
    "sg:city":"Saint-Laurent",
    "sg:classifiers":[
        {
            "category":"Banks & Credit Unions",
            "subcategory":"Bank",
            "type":"Services"
        }
    ],
    "sg:phone":"+1 514 956 6005",
    "sg:postcode":"H4R 2B7",
    "sg:province":"QC",
    "sg:tags":[
        "currency",
        "broker",
        "foreign",
        "dealer",
        "exchange"
    ],
    "wof:name":"Societe Financiere Cambridge",
    "wof:placetype":"venue"
},
  "geometry": {"coordinates":[-73.7041397095,45.496887207],"type":"Point"}
}