{
  "type": "Feature",
  "properties": {
    "addr:full":"5800 Hurontario St # B1 Mississauga ON L5R 4B9",
    "addr:housenumber":"5800",
    "addr:postcode":"l5r 4b9",
    "addr:street":"Hurontario St # B1",
    "iso:country":"CA",
    "sg:address":"5800 Hurontario St # B1",
    "sg:city":"Mississauga",
    "sg:classifiers":[
        {
            "category":"Restaurant",
            "type":"Food & Drink"
        }
    ],
    "sg:phone":"+1 905 502 8441",
    "sg:postcode":"L5R 4B9",
    "sg:province":"ON",
    "sg:tags":[
        "sandwich"
    ],
    "wof:name":"Sandwich Board",
    "wof:placetype":"venue"
},
  "geometry": {"coordinates":[-79.675285,43.622997],"type":"Point"}
}