{
  "type": "Feature",
  "properties": {
    "addr:full":"2642 Waverley Ave Vancouver BC V5S 1E7",
    "addr:housenumber":"2642",
    "addr:postcode":"v5s 1e7",
    "addr:street":"Waverley Ave",
    "iso:country":"CA",
    "sg:address":"2642 Waverley Ave",
    "sg:city":"Vancouver",
    "sg:classifiers":[
        {
            "category":"Wholesale",
            "subcategory":"Durable Goods & Equipment",
            "type":"Manufacturing & Wholesale Goods"
        }
    ],
    "sg:phone":"+1 604 437 8444",
    "sg:postcode":"V5S 1E7",
    "sg:province":"BC",
    "sg:tags":[
        "representative",
        "manufacturer"
    ],
    "wof:name":"Eagle Marketing CO",
    "wof:placetype":"venue"
},
  "geometry": {"coordinates":[-123.053405762,49.226650238],"type":"Point"}
}