{
  "type": "Feature",
  "properties": {
    "addr:full":"55 Invicta St Warren MB R0C 3E0",
    "addr:housenumber":"55",
    "addr:postcode":"r0c 3e0",
    "addr:street":"Invicta St",
    "iso:country":"CA",
    "sg:address":"55 Invicta St",
    "sg:city":"Warren",
    "sg:classifiers":[
        {
            "category":"Real Estate",
            "subcategory":"Real Estate Operator",
            "type":"Services"
        }
    ],
    "sg:phone":"+1 204 322 5387",
    "sg:postcode":"R0C 3E0",
    "sg:province":"MB",
    "sg:tags":[
        "mobile",
        "home",
        "community"
    ],
    "wof:name":"Warrenpark Lane Mobile Home",
    "wof:placetype":"venue"
},
  "geometry": {"coordinates":[-97.54644,50.132767],"type":"Point"}
}