{
  "type": "Feature",
  "properties": {
    "addr:full":"1244 Mesa Vista Ashcroft BC V0K 1A0",
    "addr:housenumber":"1244",
    "addr:postcode":"v0k 1a0",
    "addr:street":"Mesa Vista",
    "iso:country":"CA",
    "sg:address":"1244 Mesa Vista",
    "sg:city":"Ashcroft",
    "sg:classifiers":[
        {
            "category":"Organizations",
            "subcategory":"Religious Organization",
            "type":"Services"
        }
    ],
    "sg:phone":"+1 250 453 9033",
    "sg:postcode":"V0K 1A0",
    "sg:province":"BC",
    "sg:tags":[
        "church"
    ],
    "wof:name":"Sage Hills Evangelical Free",
    "wof:placetype":"venue"
},
  "geometry": {"coordinates":[-121.278968811,50.7153358459],"type":"Point"}
}