{
  "type": "Feature",
  "properties": {
    "addr:full":"Scarborough ON M1V 1V3",
    "addr:postcode":"m1v 1v3",
    "iso:country":"CA",
    "sg:city":"Scarborough",
    "sg:classifiers":[
        {
            "category":"Building & Trades",
            "subcategory":"Construction",
            "type":"Services"
        }
    ],
    "sg:phone":"+1 416 299 8312",
    "sg:postcode":"M1V 1V3",
    "sg:province":"ON",
    "sg:tags":[
        "woodworker"
    ],
    "wof:name":"G & B Woodworking",
    "wof:placetype":"venue"
},
  "geometry": {"coordinates":[-79.2961425781,43.8062324524],"type":"Point"}
}