{
  "type": "Feature",
  "properties": {
    "iso:country":"CA",
    "sg:address":"9026 Rue Saint-Etienne",
    "sg:city":"Mirabel",
    "sg:classifiers":[
        {
            "category":"Food & Beverages",
            "subcategory":"Groceries & Convenience Stores",
            "type":"Retail Goods"
        }
    ],
    "sg:phone":"+1 450 258 3837",
    "sg:postcode":"J7N 2P6",
    "sg:province":"QC",
    "wof:name":"Depanneur Le Ravitailleur Enr",
    "wof:placetype":"venue"
},
  "geometry": {"coordinates":[-74.1001586914,45.5704421997],"type":"Point"}
}