{
  "type": "Feature",
  "properties": {
    "addr:full":"2121 Roselynn Way Port Coquitlam BC V3C 2V4",
    "addr:housenumber":"2121",
    "addr:postcode":"v3c 2v4",
    "addr:street":"Roselynn Way",
    "iso:country":"CA",
    "sg:address":"2121 Roselynn Way",
    "sg:city":"Port Coquitlam",
    "sg:classifiers":[
        {
            "category":"Retail",
            "subcategory":"Laundry & Dry Cleaning",
            "type":"Services"
        }
    ],
    "sg:phone":"+1 604 942 6978",
    "sg:postcode":"V3C 2V4",
    "sg:province":"BC",
    "sg:tags":[
        "cleaners",
        "rug",
        "carpet"
    ],
    "wof:name":"Pure Gold Carpet Cleaning",
    "wof:placetype":"venue"
},
  "geometry": {"coordinates":[-122.780227661,49.2400360107],"type":"Point"}
}