{
  "type": "Feature",
  "properties": {
    "addr:full":"17511 59 Ave Surrey BC V3S 1P3",
    "addr:housenumber":"17511",
    "addr:postcode":"v3s 1p3",
    "addr:street":"59 Ave",
    "iso:country":"CA",
    "sg:address":"17511 59 Ave",
    "sg:city":"Surrey",
    "sg:classifiers":[
        {
            "category":"Education",
            "subcategory":"School",
            "type":"Public Place"
        }
    ],
    "sg:phone":"+1 604 574 5151",
    "sg:postcode":"V3S 1P3",
    "sg:province":"BC",
    "wof:name":"Cloverdale Catholic School",
    "wof:placetype":"venue"
},
  "geometry": {"coordinates":[-122.73764799999999,49.10973],"type":"Point"}
}