{
  "type": "Feature",
  "properties": {
    "addr:full":"7197 Canada Way Burnaby BC V5E 4A6",
    "addr:housenumber":"7197",
    "addr:postcode":"v5e 4a6",
    "addr:street":"Canada Way",
    "iso:country":"CA",
    "sg:address":"7197 Canada Way",
    "sg:city":"Burnaby",
    "sg:classifiers":[
        {
            "category":"Social Services",
            "type":"Services"
        }
    ],
    "sg:phone":"+1 604 526 2674",
    "sg:postcode":"V5E 4A6",
    "sg:province":"BC",
    "sg:tags":[
        "home",
        "senior",
        "retirement",
        "community",
        "citizen"
    ],
    "wof:name":"Canada Way Lodge",
    "wof:placetype":"venue"
},
  "geometry": {"coordinates":[-122.941895,49.224594],"type":"Point"}
}