{
  "type": "Feature",
  "properties": {
    "addr:full":"5008 49 Ave Vermilion AB T9X 1B7",
    "addr:housenumber":"5008",
    "addr:postcode":"t9x 1b7",
    "addr:street":"49 Ave",
    "iso:country":"CA",
    "sg:address":"5008 49 Ave",
    "sg:city":"Vermilion",
    "sg:classifiers":[
        {
            "category":"Real Estate",
            "subcategory":"Real Estate Agent",
            "type":"Services"
        }
    ],
    "sg:phone":"+1 780 853 6763",
    "sg:postcode":"T9X 1B7",
    "sg:province":"AB",
    "wof:name":"Northern Lights Realty Ltd",
    "wof:placetype":"venue"
},
  "geometry": {"coordinates":[-110.85303500000001,53.353176],"type":"Point"}
}