{
  "type": "Feature",
  "properties": {
    "iso:country":"CA",
    "sg:address":"2240 Boul Des Recollets",
    "sg:city":"Trois-Rivieres",
    "sg:classifiers":[
        {
            "category":"Wholesale",
            "subcategory":"Electrical",
            "type":"Manufacturing & Wholesale Goods"
        }
    ],
    "sg:phone":"+1 819 375 4877",
    "sg:postcode":"G8Z 3X5",
    "sg:province":"QC",
    "sg:tags":[
        "equipment",
        "electric",
        "supply"
    ],
    "wof:name":"Guillevin International Inc",
    "wof:placetype":"venue"
},
  "geometry": {"coordinates":[-72.582176,46.339733],"type":"Point"}
}