{
  "type": "Feature",
  "properties": {
    "addr:full":"198 Ossington Ave Toronto ON M6J 2Z7",
    "addr:housenumber":"198",
    "addr:postcode":"m6j 2z7",
    "addr:street":"Ossington Ave",
    "iso:country":"CA",
    "sg:address":"198 Ossington Ave",
    "sg:city":"Toronto",
    "sg:classifiers":[
        {
            "category":"Home & Garden",
            "subcategory":"Home Furnishings",
            "type":"Retail Goods"
        }
    ],
    "sg:phone":"+1 416 532 2650",
    "sg:postcode":"M6J 2Z7",
    "sg:province":"ON",
    "sg:tags":[
        "curtain",
        "made",
        "drapery"
    ],
    "wof:name":"Portugal Draperies Textile",
    "wof:placetype":"venue"
},
  "geometry": {"coordinates":[-79.420647,43.648598],"type":"Point"}
}