{
  "type": "Feature",
  "properties": {
    "addr:full":"4 Rue Pare Victoriaville QC G6P 2X6",
    "addr:housenumber":"4",
    "addr:postcode":"g6p 2x6",
    "addr:street":"Rue Pare",
    "iso:country":"CA",
    "sg:address":"4 Rue Pare",
    "sg:city":"Victoriaville",
    "sg:classifiers":[
        {
            "category":"Social Services",
            "subcategory":"Child Care",
            "type":"Services"
        }
    ],
    "sg:phone":"+1 819 758 6344",
    "sg:postcode":"G6P 2X6",
    "sg:province":"QC",
    "wof:name":"Centre DE LA Petite Enfance LA",
    "wof:placetype":"venue"
},
  "geometry": {"coordinates":[-71.95822099999999,46.063477],"type":"Point"}
}