{
  "type": "Feature",
  "properties": {
    "addr:full":"10369 135 St Surrey BC V3T 4C3",
    "addr:housenumber":"10369",
    "addr:postcode":"v3t 4c3",
    "addr:street":"135 St",
    "iso:country":"CA",
    "sg:address":"10369 135 St",
    "sg:city":"Surrey",
    "sg:classifiers":[
        {
            "category":"Shopping",
            "subcategory":"Bicycles & Sporting Goods",
            "type":"Retail Goods"
        }
    ],
    "sg:phone":"+1 604 589 8299",
    "sg:postcode":"V3T 4C3",
    "sg:province":"BC",
    "sg:tags":[
        "sharpening"
    ],
    "wof:name":"Hockey Shop",
    "wof:placetype":"venue"
},
  "geometry": {"coordinates":[-122.847939,49.19112],"type":"Point"}
}