{
  "type": "Feature",
  "properties": {
    "addr:full":"3605 Emerald Rd Westbank BC V4T 1W2",
    "addr:housenumber":"3605",
    "addr:postcode":"v4t 1w2",
    "addr:street":"Emerald Rd",
    "iso:country":"CA",
    "sg:address":"3605 Emerald Rd",
    "sg:city":"Westbank",
    "sg:classifiers":[
        {
            "category":"Retail",
            "subcategory":"Repair Shop",
            "type":"Services"
        }
    ],
    "sg:phone":"+1 250 768 5502",
    "sg:postcode":"V4T 1W2",
    "sg:province":"BC",
    "sg:tags":[
        "taxidermist"
    ],
    "wof:name":"Taxidermy By Harley White",
    "wof:placetype":"venue"
},
  "geometry": {"coordinates":[-119.67841339100001,49.8297767639],"type":"Point"}
}