{
  "type": "Feature",
  "properties": {
    "addr:full":"8950 Boul Industriel Trois-Rivieres QC G9A 5E1",
    "addr:housenumber":"8950",
    "addr:postcode":"g9a 5e1",
    "addr:street":"Boul Industriel Trois-Rivieres",
    "iso:country":"CA",
    "sg:address":"8950 Boul Industriel",
    "sg:city":"Trois-Rivieres",
    "sg:classifiers":[
        {
            "category":"Manufacturing",
            "subcategory":"Tools & Machinery",
            "type":"Manufacturing & Wholesale Goods"
        }
    ],
    "sg:phone":"+1 819 693 2191",
    "sg:postcode":"G9A 5E1",
    "sg:province":"QC",
    "sg:tags":[
        "machine",
        "shop"
    ],
    "wof:name":"Usinage Servitech Inc",
    "wof:placetype":"venue"
},
  "geometry": {"coordinates":[-72.661919,46.370544],"type":"Point"}
}