{
  "type": "Feature",
  "properties": {
    "addr:full":"245 Greenbank Rd Nepean ON K2H 8K9",
    "addr:housenumber":"245",
    "addr:postcode":"k2h 8k9",
    "addr:street":"Greenbank Rd",
    "iso:country":"CA",
    "sg:address":"245 Greenbank Rd",
    "sg:city":"Nepean",
    "sg:classifiers":[
        {
            "category":"Government",
            "subcategory":"Police Station",
            "type":"Public Place"
        }
    ],
    "sg:phone":"+1 613 236 1222",
    "sg:postcode":"K2H 8K9",
    "sg:province":"ON",
    "sg:tags":[
        "department"
    ],
    "wof:name":"Ottawa Carleton Svc DE Police",
    "wof:placetype":"venue"
},
  "geometry": {"coordinates":[-75.778702,45.325474],"type":"Point"}
}