{
  "type": "Feature",
  "properties": {
    "addr:full":"Saskatoon SK S7K 3H3",
    "addr:postcode":"s7k 3h3",
    "iso:country":"CA",
    "sg:city":"Saskatoon",
    "sg:classifiers":[
        {
            "category":"Health Services",
            "subcategory":"Doctor",
            "type":"Services"
        }
    ],
    "sg:phone":"+1 306 652 5414",
    "sg:postcode":"S7K 3H3",
    "sg:province":"SK",
    "sg:tags":[
        "physician",
        "surgeon"
    ],
    "wof:name":"Datta, J MD",
    "wof:placetype":"venue"
},
  "geometry": {"coordinates":[-106.65728,52.128124],"type":"Point"}
}