{
  "type": "Feature",
  "properties": {
    "addr:full":"1300 Shawson Dr #4 Mississauga ON L4W 1C3",
    "addr:housenumber":"1300",
    "addr:postcode":"l4w 1c3",
    "addr:street":"Shawson Dr # 4",
    "iso:country":"CA",
    "sg:address":"1300 Shawson Dr #4",
    "sg:city":"Mississauga",
    "sg:classifiers":[
        {
            "category":"Professional",
            "subcategory":"Computer Services",
            "type":"Services"
        }
    ],
    "sg:phone":"+1 905 564 5722",
    "sg:postcode":"L4W 1C3",
    "sg:province":"ON",
    "wof:name":"Technique Microsystems",
    "wof:placetype":"venue"
},
  "geometry": {"coordinates":[-79.647186,43.649239],"type":"Point"}
}