{
  "type": "Feature",
  "properties": {
    "iso:country":"CA",
    "sg:address":"382 Eglinton Ave W",
    "sg:city":"Toronto",
    "sg:classifiers":[
        {
            "category":"Shopping",
            "subcategory":"Clothing, Apparel, & Fashions",
            "type":"Retail Goods"
        }
    ],
    "sg:phone":"+1 416 482 5577",
    "sg:postcode":"M5N 1A2",
    "sg:province":"ON",
    "wof:name":"Sandro",
    "wof:placetype":"venue"
},
  "geometry": {"coordinates":[-79.40990447999999,43.704460144],"type":"Point"}
}