{
  "type": "Feature",
  "properties": {
    "iso:country":"CA",
    "sg:city":"Halifax",
    "sg:classifiers":[
        {
            "category":"Organizations",
            "subcategory":"Professional Association",
            "type":"Services"
        }
    ],
    "sg:phone":"+1 902 425 4237",
    "sg:postcode":"B3J 2A1",
    "sg:province":"NS",
    "wof:name":"Canadian Federation-Students",
    "wof:placetype":"venue"
},
  "geometry": {"coordinates":[-63.5736541748,44.6468544006],"type":"Point"}
}