{
  "type": "Feature",
  "properties": {
    "addr:full":"6110 95 Ave NW Edmonton AB T6B 1A5",
    "addr:housenumber":"6110",
    "addr:postcode":"t6b 1a5",
    "addr:street":"95 Ave Nw",
    "iso:country":"CA",
    "sg:address":"6110 95 Ave NW",
    "sg:city":"Edmonton",
    "sg:classifiers":[
        {
            "category":"Education",
            "subcategory":"School",
            "type":"Public Place"
        }
    ],
    "sg:phone":"+1 780 466 3161",
    "sg:postcode":"T6B 1A5",
    "sg:province":"AB",
    "wof:name":"Austin O'Brien High School",
    "wof:placetype":"venue"
},
  "geometry": {"coordinates":[-113.426643372,53.5348815918],"type":"Point"}
}