{
  "type": "Feature",
  "properties": {
    "addr:full":"84 Westview Blvd East York ON M4B 3J1",
    "addr:housenumber":"84",
    "addr:postcode":"m4b 3j1",
    "addr:street":"Westview Blvd",
    "iso:country":"CA",
    "sg:address":"84 Westview Blvd",
    "sg:city":"East York",
    "sg:classifiers":[
        {
            "category":"Manufacturing",
            "subcategory":"Printing",
            "type":"Manufacturing & Wholesale Goods"
        }
    ],
    "sg:phone":"+1 416 423 2573",
    "sg:postcode":"M4B 3J1",
    "sg:province":"ON",
    "sg:tags":[
        "printer"
    ],
    "wof:name":"Wots Up Marketing Svc",
    "wof:placetype":"venue"
},
  "geometry": {"coordinates":[-79.30847900000001,43.709534],"type":"Point"}
}