{
  "type": "Feature",
  "properties": {
    "addr:full":"1997 Leslie St North York ON M3B 2M3",
    "addr:housenumber":"1997",
    "addr:postcode":"m3b 2m3",
    "addr:street":"Leslie St",
    "iso:country":"CA",
    "sg:address":"1997 Leslie St",
    "sg:city":"North York",
    "sg:classifiers":[
        {
            "category":"Shopping",
            "subcategory":"Florist",
            "type":"Retail Goods"
        }
    ],
    "sg:phone":"+1 416 441 3131",
    "sg:postcode":"M3B 2M3",
    "sg:province":"ON",
    "wof:name":"A Aberdeen Florists",
    "wof:placetype":"venue"
},
  "geometry": {"coordinates":[-79.36121368409999,43.7592010498],"type":"Point"}
}