{
  "type": "Feature",
  "properties": {
    "addr:full":"174 Rue Vallilee Chute-Aux-Outardes QC G0H 1C0",
    "addr:housenumber":"174",
    "addr:postcode":"g0h 1c0",
    "addr:street":"Rue Vallilee",
    "iso:country":"CA",
    "sg:address":"174 Rue Vallilee",
    "sg:city":"Chute-Aux-Outardes",
    "sg:classifiers":[
        {
            "category":"Wholesale",
            "subcategory":"Meat",
            "type":"Manufacturing & Wholesale Goods"
        }
    ],
    "sg:phone":"+1 418 567 8065",
    "sg:postcode":"G0H 1C0",
    "sg:province":"QC",
    "sg:tags":[
        "butchering"
    ],
    "wof:name":"Boucherie Chez Fernande Enr",
    "wof:placetype":"venue"
},
  "geometry": {"coordinates":[-68.39372253419999,49.1250801086],"type":"Point"}
}