{
  "type": "Feature",
  "properties": {
    "addr:full":"318 Guelph St Georgetown ON L7G 4B5",
    "addr:housenumber":"318",
    "addr:postcode":"l7g 4b5",
    "addr:street":"Guelph St",
    "iso:country":"CA",
    "sg:address":"318 Guelph St",
    "sg:city":"Georgetown",
    "sg:classifiers":[
        {
            "category":"Personal",
            "subcategory":"Beauty Salon",
            "type":"Services"
        }
    ],
    "sg:phone":"+1 905 877 3608",
    "sg:postcode":"L7G 4B5",
    "sg:province":"ON",
    "wof:name":"Creative Reflections Salon Ltd",
    "wof:placetype":"venue"
},
  "geometry": {"coordinates":[-79.891373,43.649467],"type":"Point"}
}