{
  "type": "Feature",
  "properties": {
    "addr:full":"1641 Water St Miramichi NB E1N 1A9",
    "addr:housenumber":"1641",
    "addr:postcode":"e1n 1a9",
    "addr:street":"Water St",
    "iso:country":"CA",
    "sg:address":"1641 Water St",
    "sg:city":"Miramichi",
    "sg:classifiers":[
        {
            "category":"Recreation",
            "subcategory":"Marina",
            "type":"Entertainment"
        }
    ],
    "sg:phone":"+1 506 778 9198",
    "sg:postcode":"E1N 1A9",
    "sg:province":"NB",
    "wof:name":"Station Wharf Marina Inc",
    "wof:placetype":"venue"
},
  "geometry": {"coordinates":[-65.4719924927,47.0270652771],"type":"Point"}
}