{
  "type": "Feature",
  "properties": {
    "addr:full":"Viking AB T0B 4N0",
    "addr:postcode":"t0b 4n0",
    "iso:country":"CA",
    "sg:city":"Viking",
    "sg:classifiers":[
        {
            "category":"Health Services",
            "subcategory":"Doctor",
            "type":"Services"
        }
    ],
    "sg:phone":"+1 780 336 4040",
    "sg:postcode":"T0B 4N0",
    "sg:province":"AB",
    "sg:tags":[
        "dentist"
    ],
    "wof:name":"Nordstrom, Bryan D DDS",
    "wof:placetype":"venue"
},
  "geometry": {"coordinates":[-111.777473,53.094589],"type":"Point"}
}