{
  "type": "Feature",
  "properties": {
    "addr:full":"147 Queensland Pl SE Calgary AB T2J 4G8",
    "addr:housenumber":"147",
    "addr:postcode":"t2j 4g8",
    "addr:street":"Queensland Pl Se",
    "iso:country":"CA",
    "sg:address":"147 Queensland Pl SE",
    "sg:city":"Calgary",
    "sg:classifiers":[
        {
            "category":"Retail",
            "subcategory":"Laundry & Dry Cleaning",
            "type":"Services"
        }
    ],
    "sg:phone":"+1 403 287 2880",
    "sg:postcode":"T2J 4G8",
    "sg:province":"AB",
    "sg:tags":[
        "cleaners",
        "rug",
        "carpet"
    ],
    "wof:name":"Delta Restorations",
    "wof:placetype":"venue"
},
  "geometry": {"coordinates":[-114.025131,50.93821],"type":"Point"}
}