{
  "type": "Feature",
  "properties": {
    "addr:full":"45 King St London ON N6A 1B8",
    "addr:housenumber":"45",
    "addr:postcode":"n6a 1b8",
    "addr:street":"King St",
    "iso:country":"CA",
    "sg:address":"45 King St",
    "sg:city":"London",
    "sg:classifiers":[
        {
            "category":"Professional",
            "subcategory":"Computer Services",
            "type":"Services"
        }
    ],
    "sg:phone":"+1 519 673 3570",
    "sg:postcode":"N6A 1B8",
    "sg:province":"ON",
    "sg:tags":[
        "internet"
    ],
    "wof:name":"Icm Group Inc",
    "wof:placetype":"venue"
},
  "geometry": {"coordinates":[-81.253838,42.981068],"type":"Point"}
}