{
  "type": "Feature",
  "properties": {
    "addr:full":"Conception Bay South NL A1X 1H6",
    "addr:postcode":"a1x 1h6",
    "iso:country":"CA",
    "sg:city":"Conception Bay South",
    "sg:classifiers":[
        {
            "category":"Social Services",
            "type":"Services"
        }
    ],
    "sg:phone":"+1 709 834 5588",
    "sg:postcode":"A1X 1H6",
    "sg:province":"NL",
    "sg:tags":[
        "youth",
        "organization",
        "center"
    ],
    "wof:name":"Cadets Queen Elizabeth Army",
    "wof:placetype":"venue"
},
  "geometry": {"coordinates":[-52.968876,47.512619],"type":"Point"}
}