{
  "type": "Feature",
  "properties": {
    "addr:full":"RR 4 Picton ON K0K 2T0",
    "addr:postcode":"k0k 2t0",
    "addr:street":"Rr 4",
    "iso:country":"CA",
    "sg:address":"RR 4",
    "sg:city":"Picton",
    "sg:classifiers":[
        {
            "category":"Government",
            "subcategory":"Office",
            "type":"Public Place"
        }
    ],
    "sg:phone":"+1 613 476 5439",
    "sg:postcode":"K0K 2T0",
    "sg:province":"ON",
    "sg:tags":[
        "museum",
        "village"
    ],
    "wof:name":"North Marysburgh Township Msm",
    "wof:placetype":"venue"
},
  "geometry": {"coordinates":[-77.138977,44.009224],"type":"Point"}
}