{
  "type": "Feature",
  "properties": {
    "iso:country":"CA",
    "sg:address":"8274 Manitoba St",
    "sg:city":"Vancouver",
    "sg:classifiers":[
        {
            "category":"Wholesale",
            "subcategory":"Groceries",
            "type":"Manufacturing & Wholesale Goods"
        }
    ],
    "sg:phone":"+1 604 321 4231",
    "sg:postcode":"V5X 3A2",
    "sg:province":"BC",
    "sg:tags":[
        "food",
        "product",
        "health"
    ],
    "wof:name":"Elk Products of Canada Inc",
    "wof:placetype":"venue"
},
  "geometry": {"coordinates":[-123.10989379900001,49.2103004456],"type":"Point"}
}