{
  "type": "Feature",
  "properties": {
    "iso:country":"CA",
    "sg:address":"148 Boul Perron O",
    "sg:city":"New Richmond",
    "sg:classifiers":[
        {
            "category":"Health Services",
            "subcategory":"Chiropractor",
            "type":"Services"
        }
    ],
    "sg:phone":"+1 418 392 6262",
    "sg:postcode":"G0C 2B0",
    "sg:province":"QC",
    "wof:name":"Clinique Chiro-Sante",
    "wof:placetype":"venue"
},
  "geometry": {"coordinates":[-65.8481292725,48.155090332],"type":"Point"}
}