{
  "type": "Feature",
  "properties": {
    "addr:full":"111 Main St Wawota SK S0G 5A0",
    "addr:housenumber":"111",
    "addr:postcode":"s0g 5a0",
    "addr:street":"Main St",
    "iso:country":"CA",
    "sg:address":"111 Main St",
    "sg:city":"Wawota",
    "sg:classifiers":[
        {
            "category":"Insurance",
            "subcategory":"Insurance Agent",
            "type":"Services"
        }
    ],
    "sg:phone":"+1 306 739 2245",
    "sg:postcode":"S0G 5A0",
    "sg:province":"SK",
    "wof:name":"Wawota Agencies 2000",
    "wof:placetype":"venue"
},
  "geometry": {"coordinates":[-102.02520752,49.9058609009],"type":"Point"}
}