{
  "type": "Feature",
  "properties": {
    "addr:full":"6295 Mississauga Rd Mississauga ON L5N 1A5",
    "addr:housenumber":"6295",
    "addr:postcode":"l5n 1a5",
    "addr:street":"Mississauga Rd",
    "iso:country":"CA",
    "sg:address":"6295 Mississauga Rd",
    "sg:city":"Mississauga",
    "sg:classifiers":[
        {
            "category":"Manufacturing",
            "subcategory":"Printing",
            "type":"Manufacturing & Wholesale Goods"
        }
    ],
    "sg:phone":"+1 905 812 5237",
    "sg:postcode":"L5N 1A5",
    "sg:province":"ON",
    "sg:tags":[
        "printer",
        "duplicating",
        "copying"
    ],
    "wof:name":"Fine Copy & Printing Ltd",
    "wof:placetype":"venue"
},
  "geometry": {"coordinates":[-79.730705,43.594448],"type":"Point"}
}