{
  "type": "Feature",
  "properties": {
    "addr:full":"Prince George BC V2M 3B7",
    "addr:postcode":"v2m 3b7",
    "iso:country":"CA",
    "sg:city":"Prince George",
    "sg:classifiers":[
        {
            "category":"Personal",
            "subcategory":"Tattoo Parlor",
            "type":"Services"
        }
    ],
    "sg:phone":"+1 250 562 1239",
    "sg:postcode":"V2M 3B7",
    "sg:province":"BC",
    "sg:tags":[
        "tattooing",
        "salon",
        "beauty"
    ],
    "wof:name":"Razors Edge Hair Studio",
    "wof:placetype":"venue"
},
  "geometry": {"coordinates":[-122.781013489,53.9182777405],"type":"Point"}
}