{
  "type": "Feature",
  "properties": {
    "addr:full":"4 King Street Cres York ON M9N 1K6",
    "addr:housenumber":"4",
    "addr:postcode":"m9n 1k6",
    "addr:street":"King Street Cres",
    "iso:country":"CA",
    "sg:address":"4 King Street Cres",
    "sg:city":"York",
    "sg:classifiers":[
        {
            "category":"Health Services",
            "subcategory":"Doctor",
            "type":"Services"
        }
    ],
    "sg:phone":"+1 416 241 5038",
    "sg:postcode":"M9N 1K6",
    "sg:province":"ON",
    "sg:tags":[
        "dentist"
    ],
    "wof:name":"King Crescent Management Inc",
    "wof:placetype":"venue"
},
  "geometry": {"coordinates":[-79.520813,43.701271],"type":"Point"}
}