{
  "type": "Feature",
  "properties": {
    "addr:full":"9249 48 St NW Edmonton AB T6B 2R9",
    "addr:housenumber":"9249",
    "addr:postcode":"t6b 2r9",
    "addr:street":"48 St Nw",
    "iso:country":"CA",
    "sg:address":"9249 48 St NW",
    "sg:city":"Edmonton",
    "sg:classifiers":[
        {
            "category":"Professional",
            "subcategory":"Management & Consulting",
            "type":"Services"
        }
    ],
    "sg:phone":"+1 780 448 0936",
    "sg:postcode":"T6B 2R9",
    "sg:province":"AB",
    "sg:tags":[
        "counselor",
        "public",
        "relations"
    ],
    "wof:name":"Link Pr Inc",
    "wof:placetype":"venue"
},
  "geometry": {"coordinates":[-113.41078186,53.5284881592],"type":"Point"}
}