{
  "type": "Feature",
  "properties": {
    "addr:full":"Gatineau QC J8P 5E6",
    "addr:postcode":"j8p 5e6",
    "iso:country":"CA",
    "sg:city":"Gatineau",
    "sg:classifiers":[
        {
            "category":"Organizations",
            "subcategory":"Religious Organization",
            "type":"Services"
        }
    ],
    "sg:phone":"+1 819 663 7756",
    "sg:postcode":"J8P 5E6",
    "sg:province":"QC",
    "sg:tags":[
        "church"
    ],
    "wof:name":"St-Jean-Marie Vianney",
    "wof:placetype":"venue"
},
  "geometry": {"coordinates":[-75.714935,45.433514],"type":"Point"}
}