{
  "type": "Feature",
  "properties": {
    "addr:full":"27 Av Greystone Pointe-Claire QC H9R 5T7",
    "addr:postcode":"h9r 5t7",
    "addr:street":"27 Av Greystone",
    "iso:country":"CA",
    "sg:address":"27 Av Greystone",
    "sg:city":"Pointe-Claire",
    "sg:classifiers":[
        {
            "category":"Professional",
            "type":"Services"
        }
    ],
    "sg:phone":"+1 514 694 8800",
    "sg:postcode":"H9R 5T7",
    "sg:province":"QC",
    "sg:tags":[
        "establishment",
        "trucking"
    ],
    "wof:name":"Industries John Mooney Inc",
    "wof:placetype":"venue"
},
  "geometry": {"coordinates":[-73.8428573608,45.4613418579],"type":"Point"}
}