{
  "type": "Feature",
  "properties": {
    "addr:full":"Prince George BC V2L 2Y8",
    "addr:postcode":"v2l 2y8",
    "iso:country":"CA",
    "sg:city":"Prince George",
    "sg:classifiers":[
        {
            "category":"Organizations",
            "subcategory":"Community Association",
            "type":"Services"
        }
    ],
    "sg:phone":"+1 250 562 8882",
    "sg:postcode":"V2L 2Y8",
    "sg:province":"BC",
    "sg:tags":[
        "native"
    ],
    "wof:name":"Tsay Keh Dene Band",
    "wof:placetype":"venue"
},
  "geometry": {"coordinates":[-122.753441,53.921307],"type":"Point"}
}