{
  "type": "Feature",
  "properties": {
    "addr:full":"Saskatoon SK S7K 4Z6",
    "addr:postcode":"s7k 4z6",
    "iso:country":"CA",
    "sg:city":"Saskatoon",
    "sg:classifiers":[
        {
            "category":"Building & Trades",
            "subcategory":"Construction",
            "type":"Services"
        }
    ],
    "sg:phone":"+1 306 955 6338",
    "sg:postcode":"S7K 4Z6",
    "sg:province":"SK",
    "sg:tags":[
        "railing",
        "general",
        "contractor"
    ],
    "wof:name":"B P Banister",
    "wof:placetype":"venue"
},
  "geometry": {"coordinates":[-106.657402039,52.1758346558],"type":"Point"}
}