{
  "type": "Feature",
  "properties": {
    "addr:full":"128 Manville Rd Scarborough ON M1L 4J5",
    "addr:housenumber":"128",
    "addr:postcode":"m1l 4j5",
    "addr:street":"Manville Rd",
    "iso:country":"CA",
    "sg:address":"128 Manville Rd",
    "sg:city":"Scarborough",
    "sg:classifiers":[
        {
            "category":"Real Estate",
            "subcategory":"Real Estate Agent",
            "type":"Services"
        }
    ],
    "sg:phone":"+1 416 285 5595",
    "sg:postcode":"M1L 4J5",
    "sg:province":"ON",
    "sg:tags":[
        "management"
    ],
    "wof:name":"Green Zoellner Ltd",
    "wof:placetype":"venue"
},
  "geometry": {"coordinates":[-79.28299,43.724873],"type":"Point"}
}