{
  "type": "Feature",
  "properties": {
    "addr:full":"3473 21st Ave W Vancouver BC V6S 1G8",
    "addr:housenumber":"3473",
    "addr:postcode":"v6s 1g8",
    "addr:street":"21St Ave W",
    "iso:country":"CA",
    "sg:address":"3473 21st Ave W",
    "sg:city":"Vancouver",
    "sg:classifiers":[
        {
            "category":"Professional",
            "subcategory":"Management & Consulting",
            "type":"Services"
        }
    ],
    "sg:phone":"+1 604 681 9969",
    "sg:postcode":"V6S 1G8",
    "sg:province":"BC",
    "sg:tags":[
        "consultant",
        "planning"
    ],
    "wof:name":"Jon Ellis & Assoc",
    "wof:placetype":"venue"
},
  "geometry": {"coordinates":[-123.18100699999999,49.253986],"type":"Point"}
}