{
  "type": "Feature",
  "properties": {
    "addr:full":"8620 53 Ave NW Edmonton AB T6E 5G2",
    "addr:housenumber":"8620",
    "addr:postcode":"t6e 5g2",
    "addr:street":"53 Ave Nw",
    "iso:country":"CA",
    "sg:address":"8620 53 Ave NW",
    "sg:city":"Edmonton",
    "sg:classifiers":[
        {
            "category":"Freight",
            "type":"Transportation"
        }
    ],
    "sg:phone":"+1 780 469 4499",
    "sg:postcode":"T6E 5G2",
    "sg:province":"AB",
    "sg:tags":[
        "mover"
    ],
    "wof:name":"Time Movers",
    "wof:placetype":"venue"
},
  "geometry": {"coordinates":[-113.455513001,53.4901237488],"type":"Point"}
}