{
  "type": "Feature",
  "properties": {
    "addr:full":"1050 Mackenzie Ave S Williams Lake BC V2G 3Y1",
    "addr:housenumber":"1050",
    "addr:postcode":"v2g 3y1",
    "addr:street":"Mackenzie Ave S Williams",
    "iso:country":"CA",
    "sg:address":"1050 Mackenzie Ave S",
    "sg:city":"Williams Lake",
    "sg:classifiers":[
        {
            "category":"Wholesale",
            "subcategory":"Farm Supplies",
            "type":"Manufacturing & Wholesale Goods"
        }
    ],
    "sg:phone":"+1 250 392 6282",
    "sg:postcode":"V2G 3Y1",
    "sg:province":"BC",
    "sg:tags":[
        "feed"
    ],
    "wof:name":"Beaver Valley Feeds",
    "wof:placetype":"venue"
},
  "geometry": {"coordinates":[-122.125801086,52.1248550415],"type":"Point"}
}