{
  "type": "Feature",
  "properties": {
    "addr:full":"100 Broadview Ave Toronto ON M4M 3H3",
    "addr:housenumber":"100",
    "addr:postcode":"m4m 3h3",
    "addr:street":"Broadview Ave",
    "iso:country":"CA",
    "sg:address":"100 Broadview Ave",
    "sg:city":"Toronto",
    "sg:classifiers":[
        {
            "category":"Professional",
            "subcategory":"Engineering",
            "type":"Services"
        }
    ],
    "sg:phone":"+1 416 463 6662",
    "sg:postcode":"M4M 3H3",
    "sg:province":"ON",
    "sg:tags":[
        "engineer"
    ],
    "wof:name":"Weinstein Taylor & Assoc",
    "wof:placetype":"venue"
},
  "geometry": {"coordinates":[-79.34993,43.658646],"type":"Point"}
}