{
  "type": "Feature",
  "properties": {
    "addr:full":"Mississauga ON L4W 1G4",
    "addr:postcode":"l4w 1g4",
    "iso:country":"CA",
    "sg:city":"Mississauga",
    "sg:classifiers":[
        {
            "category":"Wholesale",
            "subcategory":"Hardware",
            "type":"Manufacturing & Wholesale Goods"
        }
    ],
    "sg:phone":"+1 905 629 8005",
    "sg:postcode":"L4W 1G4",
    "sg:province":"ON",
    "wof:name":"Total Builders Hardware",
    "wof:placetype":"venue"
},
  "geometry": {"coordinates":[-79.6274795532,43.6305770874],"type":"Point"}
}