{
  "type": "Feature",
  "properties": {
    "addr:full":"Winnipegosis MB R0L 2G0",
    "addr:postcode":"r0l 2g0",
    "iso:country":"CA",
    "sg:city":"Winnipegosis",
    "sg:classifiers":[
        {
            "category":"Shopping",
            "subcategory":"Catalog Store",
            "type":"Retail Goods"
        }
    ],
    "sg:phone":"+1 204 656 4640",
    "sg:postcode":"R0L 2G0",
    "sg:province":"MB",
    "sg:tags":[
        "mail",
        "order",
        "internet"
    ],
    "wof:name":"Sears Canada Inc",
    "wof:placetype":"venue"
},
  "geometry": {"coordinates":[-99.9255065918,51.6529006958],"type":"Point"}
}