{
  "type": "Feature",
  "properties": {
    "iso:country":"CA",
    "sg:address":"6394 Boul Saint-Laurent",
    "sg:city":"Montreal",
    "sg:classifiers":[
        {
            "category":"Manufacturing",
            "subcategory":"Furniture",
            "type":"Manufacturing & Wholesale Goods"
        }
    ],
    "sg:phone":"+1 514 277 3195",
    "sg:postcode":"H2S 3C4",
    "sg:province":"QC",
    "sg:tags":[
        "awning",
        "canopy"
    ],
    "wof:name":"Roch Lussier Inc",
    "wof:placetype":"venue"
},
  "geometry": {"coordinates":[-73.60804,45.529858],"type":"Point"}
}