{
  "type": "Feature",
  "properties": {
    "addr:full":"123 Inchbury St Hamilton ON L8R 3B7",
    "addr:housenumber":"123",
    "addr:postcode":"l8r 3b7",
    "addr:street":"Inchbury St",
    "iso:country":"CA",
    "sg:address":"123 Inchbury St",
    "sg:city":"Hamilton",
    "sg:classifiers":[
        {
            "category":"Wholesale",
            "subcategory":"Machinery & Supplies",
            "type":"Manufacturing & Wholesale Goods"
        }
    ],
    "sg:phone":"+1 905 521 8477",
    "sg:postcode":"L8R 3B7",
    "sg:province":"ON",
    "sg:tags":[
        "equipment",
        "railroad",
        "parts"
    ],
    "wof:name":"Central Rail Supply",
    "wof:placetype":"venue"
},
  "geometry": {"coordinates":[-79.881844,43.267567],"type":"Point"}
}