{
  "type": "Feature",
  "properties": {
    "addr:full":"2400 Truscott Dr Mississauga ON L5J 2B2",
    "addr:housenumber":"2400",
    "addr:postcode":"l5j 2b2",
    "addr:street":"Truscott Dr",
    "iso:country":"CA",
    "sg:address":"2400 Truscott Dr",
    "sg:city":"Mississauga",
    "sg:classifiers":[
        {
            "category":"Organizations",
            "subcategory":"Religious Organization",
            "type":"Services"
        }
    ],
    "sg:phone":"+1 905 822 3691",
    "sg:postcode":"L5J 2B2",
    "sg:province":"ON",
    "sg:tags":[
        "church"
    ],
    "wof:name":"Park Royal Bible Church",
    "wof:placetype":"venue"
},
  "geometry": {"coordinates":[-79.647774,43.511524],"type":"Point"}
}