{
  "type": "Feature",
  "properties": {
    "addr:full":"7820 Av Mousseau Anjou QC H1K 4N8",
    "addr:housenumber":"7820",
    "addr:postcode":"h1k 4n8",
    "addr:street":"Av Mousseau",
    "iso:country":"CA",
    "sg:address":"7820 Av Mousseau",
    "sg:city":"Anjou",
    "sg:classifiers":[
        {
            "category":"Freight",
            "type":"Transportation"
        }
    ],
    "sg:phone":"+1 514 493 3357",
    "sg:postcode":"H1K 4N8",
    "sg:province":"QC",
    "sg:tags":[
        "trucking"
    ],
    "wof:name":"Transport Jgo Inc",
    "wof:placetype":"venue"
},
  "geometry": {"coordinates":[-73.5545883179,45.6149635315],"type":"Point"}
}