{
  "type": "Feature",
  "properties": {
    "addr:full":"618 Saskatchewan Ave W Portage LA Prairie MB R1N 0M6",
    "addr:housenumber":"618",
    "addr:postcode":"r1n 0m6",
    "addr:street":"Saskatchewan Ave W",
    "iso:country":"CA",
    "sg:address":"618 Saskatchewan Ave W",
    "sg:city":"Portage LA Prairie",
    "sg:classifiers":[
        {
            "category":"Retail",
            "subcategory":"Portrait Studio",
            "type":"Services"
        }
    ],
    "sg:phone":"+1 204 239 7239",
    "sg:postcode":"R1N 0M6",
    "sg:province":"MB",
    "sg:tags":[
        "photographer"
    ],
    "wof:name":"Double Exposure/James Miller",
    "wof:placetype":"venue"
},
  "geometry": {"coordinates":[-98.29922500000001,49.973709],"type":"Point"}
}