{
  "type": "Feature",
  "properties": {
    "addr:full":"100 Bond St Toronto ON M5B 1X8",
    "addr:housenumber":"100",
    "addr:postcode":"m5b 1x8",
    "addr:street":"Bond St",
    "iso:country":"CA",
    "sg:address":"100 Bond St",
    "sg:city":"Toronto",
    "sg:classifiers":[
        {
            "category":"Shopping",
            "subcategory":"Department Store",
            "type":"Retail Goods"
        }
    ],
    "sg:phone":"+1 416 596 6584",
    "sg:postcode":"M5B 1X8",
    "sg:province":"ON",
    "sg:tags":[
        "shop"
    ],
    "wof:name":"Rockwell Warehouse Outlet",
    "wof:placetype":"venue"
},
  "geometry": {"coordinates":[-79.37869999999999,43.656799],"type":"Point"}
}