{
  "type": "Feature",
  "properties": {
    "addr:full":"9411 41 Ave NW Edmonton AB T6E 5X7",
    "addr:housenumber":"9411",
    "addr:postcode":"t6e 5x7",
    "addr:street":"41 Ave Nw",
    "iso:country":"CA",
    "sg:address":"9411 41 Ave NW",
    "sg:city":"Edmonton",
    "sg:classifiers":[
        {
            "category":"Wholesale",
            "subcategory":"Machinery & Supplies",
            "type":"Manufacturing & Wholesale Goods"
        }
    ],
    "sg:phone":"+1 780 437 9411",
    "sg:postcode":"T6E 5X7",
    "sg:province":"AB",
    "sg:tags":[
        "bearing"
    ],
    "wof:name":"Bearing & Transmission Ltd",
    "wof:placetype":"venue"
},
  "geometry": {"coordinates":[-113.473877,53.476246],"type":"Point"}
}