{
  "type": "Feature",
  "properties": {
    "addr:full":"900 Rue Boulet Thetford Mines QC G6G 6N3",
    "addr:housenumber":"900",
    "addr:postcode":"g6g 6n3",
    "addr:street":"Rue Boulet",
    "iso:country":"CA",
    "sg:address":"900 Rue Boulet",
    "sg:city":"Thetford Mines",
    "sg:classifiers":[
        {
            "category":"Retail",
            "subcategory":"Repair Shop",
            "type":"Services"
        }
    ],
    "sg:phone":"+1 418 338 4765",
    "sg:postcode":"G6G 6N3",
    "sg:province":"QC",
    "sg:tags":[
        "repairing",
        "piano",
        "refinishing"
    ],
    "wof:name":"Cave A Piano Inc",
    "wof:placetype":"venue"
},
  "geometry": {"coordinates":[-71.334862,46.094219],"type":"Point"}
}