{
  "type": "Feature",
  "properties": {
    "iso:country":"CA",
    "sg:address":"257 Bestwick Crt W",
    "sg:city":"Kamloops",
    "sg:classifiers":[
        {
            "category":"Health Services",
            "subcategory":"Health Practitioner",
            "type":"Services"
        }
    ],
    "sg:phone":"+1 250 374 4822",
    "sg:postcode":"V2C 1S4",
    "sg:province":"BC",
    "sg:tags":[
        "psychologist"
    ],
    "wof:name":"Kamloops Psychological Svc",
    "wof:placetype":"venue"
},
  "geometry": {"coordinates":[-120.344406128,50.6693878174],"type":"Point"}
}