{
  "type": "Feature",
  "properties": {
    "iso:country":"CA",
    "sg:address":"9636 Academy Dr SE",
    "sg:city":"Calgary",
    "sg:classifiers":[
        {
            "category":"Building & Trades",
            "subcategory":"Construction",
            "type":"Services"
        }
    ],
    "sg:phone":"+1 403 252 2854",
    "sg:postcode":"T2J 1A7",
    "sg:province":"AB",
    "sg:tags":[
        "repairing",
        "remodeling",
        "contractor"
    ],
    "wof:name":"Labco Construction",
    "wof:placetype":"venue"
},
  "geometry": {"coordinates":[-114.04444122300001,50.9667854309],"type":"Point"}
}