{
  "type": "Feature",
  "properties": {
    "addr:full":"4550 Rhodes Dr Windsor ON N8W 5C2",
    "addr:housenumber":"4550",
    "addr:postcode":"n8w 5c2",
    "addr:street":"Rhodes Dr",
    "iso:country":"CA",
    "sg:address":"4550 Rhodes Dr",
    "sg:city":"Windsor",
    "sg:classifiers":[
        {
            "category":"Wholesale",
            "subcategory":"Hardware",
            "type":"Manufacturing & Wholesale Goods"
        }
    ],
    "sg:phone":"+1 519 945 2220",
    "sg:postcode":"N8W 5C2",
    "sg:province":"ON",
    "sg:tags":[
        "refrigerating"
    ],
    "wof:name":"Carrier Canada",
    "wof:placetype":"venue"
},
  "geometry": {"coordinates":[-82.958046,42.285103],"type":"Point"}
}