{
  "type": "Feature",
  "properties": {
    "addr:full":"1449 Birch St Telkwa BC V0J 2X0",
    "addr:housenumber":"1449",
    "addr:postcode":"v0j 2x0",
    "addr:street":"Birch St",
    "iso:country":"CA",
    "sg:address":"1449 Birch St",
    "sg:city":"Telkwa",
    "sg:classifiers":[
        {
            "category":"Government",
            "subcategory":"Office",
            "type":"Public Place"
        }
    ],
    "sg:phone":"+1 250 846 9144",
    "sg:postcode":"V0J 2X0",
    "sg:province":"BC",
    "sg:tags":[
        "village"
    ],
    "wof:name":"Telkwa Village Maintenance Shp",
    "wof:placetype":"venue"
},
  "geometry": {"coordinates":[-127.05027008099999,54.6902694702],"type":"Point"}
}