{
  "type": "Feature",
  "properties": {
    "addr:full":"Fort St John BC V1J 3Y9",
    "addr:postcode":"v1j 3y9",
    "iso:country":"CA",
    "sg:city":"Fort St John",
    "sg:classifiers":[
        {
            "category":"Mining & Drilling",
            "type":"Manufacturing & Wholesale Goods"
        }
    ],
    "sg:phone":"+1 250 787 8540",
    "sg:postcode":"V1J 3Y9",
    "sg:province":"BC",
    "sg:tags":[
        "field",
        "oil"
    ],
    "wof:name":"Dutch Casing Svc",
    "wof:placetype":"venue"
},
  "geometry": {"coordinates":[-120.84761047400001,56.2486763],"type":"Point"}
}