{
  "type": "Feature",
  "properties": {
    "addr:full":"301 2nd St S Wakaw SK S0K 4P0",
    "addr:housenumber":"301",
    "addr:postcode":"s0k 4p0",
    "addr:street":"2Nd St S",
    "iso:country":"CA",
    "sg:address":"301 2nd St S",
    "sg:city":"Wakaw",
    "sg:classifiers":[
        {
            "category":"Building & Trades",
            "subcategory":"Plumbing",
            "type":"Services"
        }
    ],
    "sg:phone":"+1 306 233 7660",
    "sg:postcode":"S0K 4P0",
    "sg:province":"SK",
    "sg:tags":[
        "conditioning",
        "contractor",
        "system",
        "air"
    ],
    "wof:name":"Ben Nagey Plumbing & Heating",
    "wof:placetype":"venue"
},
  "geometry": {"coordinates":[-105.742706,52.65295],"type":"Point"}
}