{
  "type": "Feature",
  "properties": {
    "addr:full":"465 Coronation Dr Scarborough ON M1E 2K2",
    "addr:housenumber":"465",
    "addr:postcode":"m1e 2k2",
    "addr:street":"Coronation Dr",
    "iso:country":"CA",
    "sg:address":"465 Coronation Dr",
    "sg:city":"Scarborough",
    "sg:classifiers":[
        {
            "category":"Manufacturing",
            "subcategory":"Chemicals & Compounds",
            "type":"Manufacturing & Wholesale Goods"
        }
    ],
    "sg:phone":"+1 416 284 6111",
    "sg:postcode":"M1E 2K2",
    "sg:province":"ON",
    "sg:tags":[
        "adhesive",
        "glue"
    ],
    "wof:name":"Halltech Inc",
    "wof:placetype":"venue"
},
  "geometry": {"coordinates":[-79.16937299999999,43.764458],"type":"Point"}
}