{
  "type": "Feature",
  "properties": {
    "addr:full":"765 Ch Du Lac-A-LA-Truite Thetford Mines QC G6G 5R7",
    "addr:housenumber":"765",
    "addr:postcode":"g6g 5r7",
    "addr:street":"Ch Du Lac-A-La-Truite",
    "iso:country":"CA",
    "sg:address":"765 Ch Du Lac-A-LA-Truite",
    "sg:city":"Thetford Mines",
    "sg:classifiers":[
        {
            "category":"Retail",
            "subcategory":"Animal Services",
            "type":"Services"
        }
    ],
    "sg:phone":"+1 418 335 7955",
    "sg:postcode":"G6G 5R7",
    "sg:province":"QC",
    "sg:tags":[
        "pet",
        "boarding",
        "training",
        "sitting"
    ],
    "wof:name":"Elevage Roussi Enr",
    "wof:placetype":"venue"
},
  "geometry": {"coordinates":[-71.23849487299999,46.0361328125],"type":"Point"}
}