{
  "type": "Feature",
  "properties": {
    "addr:full":"Tofield AB T0B 4J0",
    "addr:postcode":"t0b 4j0",
    "iso:country":"CA",
    "sg:city":"Tofield",
    "sg:classifiers":[
        {
            "category":"Restaurant",
            "type":"Food & Drink"
        }
    ],
    "sg:phone":"+1 780 662 3727",
    "sg:postcode":"T0B 4J0",
    "sg:province":"AB",
    "wof:name":"Tilly's Family Dining & Pizza",
    "wof:placetype":"venue"
},
  "geometry": {"coordinates":[-112.668197632,53.3685073853],"type":"Point"}
}