{
  "type": "Feature",
  "properties": {
    "addr:full":"Granby QC J2G 5E6",
    "addr:postcode":"j2g 5e6",
    "iso:country":"CA",
    "sg:city":"Granby",
    "sg:classifiers":[
        {
            "category":"Personal",
            "type":"Services"
        }
    ],
    "sg:phone":"+1 450 777 3330",
    "sg:postcode":"J2G 5E6",
    "sg:province":"QC",
    "sg:tags":[
        "dating"
    ],
    "wof:name":"Agence DE Rencontre Nouvelle",
    "wof:placetype":"venue"
},
  "geometry": {"coordinates":[-72.7248001099,45.4082527161],"type":"Point"}
}