{
  "type": "Feature",
  "properties": {
    "addr:full":"PO Box 443 STN Main Brooks AB T1R 1B4",
    "addr:housenumber":"po",
    "addr:postcode":"ab t1r 1b4",
    "addr:street":"Box 443 Stn Main Brooks",
    "iso:country":"CA",
    "sg:address":"PO Box 443 STN Main",
    "sg:city":"Brooks",
    "sg:classifiers":[
        {
            "category":"Building & Trades",
            "subcategory":"Construction",
            "type":"Services"
        }
    ],
    "sg:phone":"+1 403 362 0476",
    "sg:postcode":"T1R 1B4",
    "sg:province":"AB",
    "sg:tags":[
        "painter"
    ],
    "wof:name":"Creative Painting",
    "wof:placetype":"venue"
},
  "geometry": {"coordinates":[-111.89849100000001,50.565853],"type":"Point"}
}