{
  "type": "Feature",
  "properties": {
    "addr:full":"140 King St W #140 Kitchener ON N2G 1A6",
    "addr:housenumber":"140;140",
    "addr:postcode":"n2g 1a6",
    "addr:street":"King St W #",
    "iso:country":"CA",
    "sg:address":"140 King St W #140",
    "sg:city":"Kitchener",
    "sg:classifiers":[
        {
            "category":"Food & Beverages",
            "subcategory":"Groceries & Convenience Stores",
            "type":"Retail Goods"
        }
    ],
    "sg:phone":"+1 519 578 2060",
    "sg:postcode":"N2G 1A6",
    "sg:province":"ON",
    "sg:tags":[
        "grocer"
    ],
    "wof:name":"Total Convenience",
    "wof:placetype":"venue"
},
  "geometry": {"coordinates":[-80.49166099999999,43.450901],"type":"Point"}
}