{
  "type": "Feature",
  "properties": {
    "iso:country":"CA",
    "sg:address":"25 Del'Eglise",
    "sg:city":"Ham-Nord",
    "sg:classifiers":[
        {
            "category":"Government",
            "subcategory":"Office",
            "type":"Public Place"
        }
    ],
    "sg:phone":"+1 819 344 5806",
    "sg:postcode":"G0P 1A0",
    "sg:province":"QC",
    "sg:tags":[
        "village"
    ],
    "wof:name":"Notre-Dame DE Lourdes DE Ham",
    "wof:placetype":"venue"
},
  "geometry": {"coordinates":[-71.73812103269999,45.9063873291],"type":"Point"}
}