{
  "type": "Feature",
  "properties": {
    "addr:full":"Petrolia ON N0N 1R0",
    "addr:postcode":"n0n 1r0",
    "iso:country":"CA",
    "sg:city":"Petrolia",
    "sg:classifiers":[
        {
            "category":"Professional",
            "subcategory":"Computer Services",
            "type":"Services"
        }
    ],
    "sg:phone":"+1 519 882 3089",
    "sg:postcode":"N0N 1R0",
    "sg:province":"ON",
    "sg:tags":[
        "consultant"
    ],
    "wof:name":"Soft Touch Solutions Inc",
    "wof:placetype":"venue"
},
  "geometry": {"coordinates":[-82.1478729248,42.8818054199],"type":"Point"}
}