{
  "type": "Feature",
  "properties": {
    "addr:full":"3409 35 Ave Vernon BC V1T 2T5",
    "addr:housenumber":"3409",
    "addr:postcode":"v1t 2t5",
    "addr:street":"35 Ave",
    "iso:country":"CA",
    "sg:address":"3409 35 Ave",
    "sg:city":"Vernon",
    "sg:classifiers":[
        {
            "category":"Recreation",
            "type":"Entertainment"
        }
    ],
    "sg:phone":"+1 250 542 8244",
    "sg:postcode":"V1T 2T5",
    "sg:province":"BC",
    "sg:tags":[
        "skating",
        "instruction"
    ],
    "wof:name":"Vernon Figure Skating Club",
    "wof:placetype":"venue"
},
  "geometry": {"coordinates":[-119.277336121,50.2675170898],"type":"Point"}
}