{
  "type": "Feature",
  "properties": {
    "addr:full":"1308 Central Ave Prince Albert SK S6V 4W3",
    "addr:housenumber":"1308",
    "addr:postcode":"s6v 4w3",
    "addr:street":"Central Ave",
    "iso:country":"CA",
    "sg:address":"1308 Central Ave",
    "sg:city":"Prince Albert",
    "sg:classifiers":[
        {
            "category":"Wholesale",
            "subcategory":"Groceries",
            "type":"Manufacturing & Wholesale Goods"
        }
    ],
    "sg:phone":"+1 306 922 4372",
    "sg:postcode":"S6V 4W3",
    "sg:province":"SK",
    "sg:tags":[
        "food",
        "health",
        "diet"
    ],
    "wof:name":"Sunlite Health Foods",
    "wof:placetype":"venue"
},
  "geometry": {"coordinates":[-105.754143,53.201107],"type":"Point"}
}