{
  "type": "Feature",
  "properties": {
    "iso:country":"CA",
    "sg:address":"1500 Ch Du Village",
    "sg:city":"Mont-Tremblant",
    "sg:classifiers":[
        {
            "category":"Building & Trades",
            "subcategory":"Landscaping Services",
            "type":"Services"
        }
    ],
    "sg:phone":"+1 819 425 9551",
    "sg:postcode":"J8E 1G7",
    "sg:province":"QC",
    "sg:tags":[
        "landscape",
        "contractor"
    ],
    "wof:name":"Entreprises Bernard Sigouin",
    "wof:placetype":"venue"
},
  "geometry": {"coordinates":[-74.6255264282,46.1838111877],"type":"Point"}
}