{
  "type": "Feature",
  "properties": {
    "addr:full":"23 Rue Ambroise-Fafard Baie-Saint-Paul QC G3Z 2J2",
    "addr:housenumber":"23",
    "addr:postcode":"g3z 2j2",
    "addr:street":"Rue Ambroise-Fafard",
    "iso:country":"CA",
    "sg:address":"23 Rue Ambroise-Fafard",
    "sg:city":"Baie-Saint-Paul",
    "sg:classifiers":[
        {
            "category":"Shopping",
            "type":"Retail Goods"
        }
    ],
    "sg:phone":"+1 418 435 3681",
    "sg:postcode":"G3Z 2J2",
    "sg:province":"QC",
    "sg:tags":[
        "art",
        "gallery",
        "dealer"
    ],
    "wof:name":"Centre D'Art Baie St-Paul",
    "wof:placetype":"venue"
},
  "geometry": {"coordinates":[-70.505951,47.439838],"type":"Point"}
}