{
  "type": "Feature",
  "properties": {
    "addr:full":"208 Main St Kindersley SK S0L 1S0",
    "addr:housenumber":"208",
    "addr:postcode":"s0l 1s0",
    "addr:street":"Main St",
    "iso:country":"CA",
    "sg:address":"208 Main St",
    "sg:city":"Kindersley",
    "sg:classifiers":[
        {
            "category":"Shopping",
            "subcategory":"Bicycles & Sporting Goods",
            "type":"Retail Goods"
        }
    ],
    "sg:phone":"+1 306 463 4244",
    "sg:postcode":"S0L 1S0",
    "sg:province":"SK",
    "wof:name":"Supreme Source For Sports",
    "wof:placetype":"venue"
},
  "geometry": {"coordinates":[-109.161057,51.47216],"type":"Point"}
}