{
  "type": "Feature",
  "properties": {
    "addr:full":"7274 Canada Way Burnaby BC V5E 3R9",
    "addr:housenumber":"7274",
    "addr:postcode":"v5e 3r9",
    "addr:street":"Canada Way",
    "iso:country":"CA",
    "sg:address":"7274 Canada Way",
    "sg:city":"Burnaby",
    "sg:classifiers":[
        {
            "category":"Autos & Motor Vehicles",
            "subcategory":"Fuel & Gas Station",
            "type":"Retail Goods"
        }
    ],
    "sg:phone":"+1 604 521 0244",
    "sg:postcode":"V5E 3R9",
    "sg:province":"BC",
    "sg:tags":[
        "oil"
    ],
    "wof:name":"Mohawk",
    "wof:placetype":"venue"
},
  "geometry": {"coordinates":[-122.94104799999999,49.224297],"type":"Point"}
}