{
  "type": "Feature",
  "properties": {
    "addr:full":"1038 Boul Saint-Germain Rimouski QC G5L 8Y9",
    "addr:housenumber":"1038",
    "addr:postcode":"g5l 8y9",
    "addr:street":"Boul Saint-Germain",
    "iso:country":"CA",
    "sg:address":"1038 Boul Saint-Germain",
    "sg:city":"Rimouski",
    "sg:classifiers":[
        {
            "category":"Travel",
            "subcategory":"Hotels & Motels",
            "type":"Entertainment"
        }
    ],
    "sg:phone":"+1 418 723 8598",
    "sg:postcode":"G5L 8Y9",
    "sg:province":"QC",
    "wof:name":"Chalets Bellevue Enr",
    "wof:placetype":"venue"
},
  "geometry": {"coordinates":[-68.602615,48.423103],"type":"Point"}
}