{
  "type": "Feature",
  "properties": {
    "addr:full":"1720 Sherwood Forrest Cir Mississauga ON L5K 1R1",
    "addr:housenumber":"1720",
    "addr:postcode":"l5k 1r1",
    "addr:street":"Sherwood Forrest Cir",
    "iso:country":"CA",
    "sg:address":"1720 Sherwood Forrest Cir",
    "sg:city":"Mississauga",
    "sg:classifiers":[
        {
            "category":"Health Services",
            "subcategory":"Nursing And Care Facility",
            "type":"Services"
        }
    ],
    "sg:phone":"+1 905 822 5298",
    "sg:postcode":"L5K 1R1",
    "sg:province":"ON",
    "sg:tags":[
        "home",
        "retirement",
        "community"
    ],
    "wof:name":"Carmel Heights",
    "wof:placetype":"venue"
},
  "geometry": {"coordinates":[-79.6581573486,43.5408706665],"type":"Point"}
}