{
  "type": "Feature",
  "properties": {
    "addr:full":"118 Hillyard St Hamilton ON L8L 6B6",
    "addr:housenumber":"118",
    "addr:postcode":"l8l 6b6",
    "addr:street":"Hillyard St",
    "iso:country":"CA",
    "sg:address":"118 Hillyard St",
    "sg:city":"Hamilton",
    "sg:classifiers":[
        {
            "category":"Retail",
            "subcategory":"Auto Repair",
            "type":"Services"
        }
    ],
    "sg:phone":"+1 905 528 3658",
    "sg:postcode":"L8L 6B6",
    "sg:province":"ON",
    "sg:tags":[
        "body",
        "automobile",
        "painting"
    ],
    "wof:name":"Hillyard Auto Collision",
    "wof:placetype":"venue"
},
  "geometry": {"coordinates":[-79.8388595581,43.2690315247],"type":"Point"}
}