{
  "type": "Feature",
  "properties": {
    "addr:full":"1160 Scarth St Regina SK S4R 2E2",
    "addr:housenumber":"1160",
    "addr:postcode":"s4r 2e2",
    "addr:street":"Scarth St",
    "iso:country":"CA",
    "sg:address":"1160 Scarth St",
    "sg:city":"Regina",
    "sg:classifiers":[
        {
            "category":"Building & Trades",
            "subcategory":"Plumbing",
            "type":"Services"
        }
    ],
    "sg:phone":"+1 306 359 9797",
    "sg:postcode":"S4R 2E2",
    "sg:province":"SK",
    "sg:tags":[
        "system",
        "ice",
        "contractor",
        "machine",
        "equipment",
        "conditioning",
        "making",
        "air"
    ],
    "wof:name":"Refrigerative Supply Ltd",
    "wof:placetype":"venue"
},
  "geometry": {"coordinates":[-104.611053,50.460484],"type":"Point"}
}