{
  "type": "Feature",
  "properties": {
    "addr:full":"823 College St Toronto ON M6G 1C9",
    "addr:housenumber":"823",
    "addr:postcode":"m6g 1c9",
    "addr:street":"College St",
    "iso:country":"CA",
    "sg:address":"823 College St",
    "sg:city":"Toronto",
    "sg:classifiers":[
        {
            "category":"Real Estate",
            "subcategory":"Real Estate Agent",
            "type":"Services"
        }
    ],
    "sg:phone":"+1 416 535 3107",
    "sg:postcode":"M6G 1C9",
    "sg:province":"ON",
    "wof:name":"Home Life Regional Realty Ltd",
    "wof:placetype":"venue"
},
  "geometry": {"coordinates":[-79.42218800000001,43.654362],"type":"Point"}
}