{
  "type": "Feature",
  "properties": {
    "addr:full":"Redditt Rd Kenora ON P9N 3W7",
    "addr:postcode":"p9n 3w7",
    "addr:street":"Redditt Rd",
    "iso:country":"CA",
    "sg:address":"Redditt Rd",
    "sg:city":"Kenora",
    "sg:classifiers":[
        {
            "category":"Retail",
            "subcategory":"Auto Repair",
            "type":"Services"
        }
    ],
    "sg:phone":"+1 807 548 1331",
    "sg:postcode":"P9N 3W7",
    "sg:province":"ON",
    "sg:tags":[
        "truck"
    ],
    "wof:name":"Querel Gravel & Lumber Ltd",
    "wof:placetype":"venue"
},
  "geometry": {"coordinates":[-94.488686,49.783535],"type":"Point"}
}