{
  "type": "Feature",
  "properties": {
    "addr:full":"949 Rue Principale E Abbotsford QC J0E 1A0",
    "addr:housenumber":"949",
    "addr:postcode":"j0e 1a0",
    "addr:street":"Rue Principale E",
    "iso:country":"CA",
    "sg:address":"949 Rue Principale E",
    "sg:city":"Abbotsford",
    "sg:classifiers":[
        {
            "category":"Shopping",
            "type":"Retail Goods"
        }
    ],
    "sg:phone":"+1 450 379 5655",
    "sg:postcode":"J0E 1A0",
    "sg:province":"QC",
    "sg:tags":[
        "stamp",
        "collector",
        "for"
    ],
    "wof:name":"Societe Canadienne Des Postes",
    "wof:placetype":"venue"
},
  "geometry": {"coordinates":[-72.88385009770001,45.4373207092],"type":"Point"}
}