{
  "type": "Feature",
  "properties": {
    "addr:full":"99 Rte Marie-Victorin Saint-Francois-Du-Lac QC J0G 1M0",
    "addr:housenumber":"99",
    "addr:postcode":"j0g 1m0",
    "addr:street":"Rte Marie-Victorin",
    "iso:country":"CA",
    "sg:address":"99 Rte Marie-Victorin",
    "sg:city":"Saint-Francois-Du-Lac",
    "sg:classifiers":[
        {
            "category":"Wholesale",
            "subcategory":"Machinery & Supplies",
            "type":"Manufacturing & Wholesale Goods"
        }
    ],
    "sg:phone":"+1 450 568 0505",
    "sg:postcode":"J0G 1M0",
    "sg:province":"QC",
    "sg:tags":[
        "tool"
    ],
    "wof:name":"Equipements Raydan Inc",
    "wof:placetype":"venue"
},
  "geometry": {"coordinates":[-72.82218899999999,46.059635],"type":"Point"}
}