{
  "type": "Feature",
  "properties": {
    "iso:country":"CA",
    "sg:address":"11743 94 St NW",
    "sg:city":"Edmonton",
    "sg:classifiers":[
        {
            "category":"Personal",
            "subcategory":"Barber",
            "type":"Services"
        }
    ],
    "sg:phone":"+1 780 477 7498",
    "sg:postcode":"T5G 1J1",
    "sg:province":"AB",
    "wof:name":"Stan's Barber Shop",
    "wof:placetype":"venue"
},
  "geometry": {"coordinates":[-113.48548889200001,53.5695571899],"type":"Point"}
}