{
  "type": "Feature",
  "properties": {
    "addr:full":"943 Eglinton Ave E East York ON M4G 4B5",
    "addr:housenumber":"943",
    "addr:postcode":"m4g 4b5",
    "addr:street":"Eglinton Ave E",
    "iso:country":"CA",
    "sg:address":"943 Eglinton Ave E",
    "sg:city":"East York",
    "sg:classifiers":[
        {
            "category":"Retail",
            "subcategory":"Repair Shop",
            "type":"Services"
        }
    ],
    "sg:phone":"+1 416 423 0434",
    "sg:postcode":"M4G 4B5",
    "sg:province":"ON",
    "sg:tags":[
        "repairing",
        "piano",
        "refinishing"
    ],
    "wof:name":"Robert Lowrey's Piano Experts",
    "wof:placetype":"venue"
},
  "geometry": {"coordinates":[-79.35855100000001,43.714783],"type":"Point"}
}