{
  "type": "Feature",
  "properties": {
    "iso:country":"CA",
    "sg:address":"605 Wayoata St",
    "sg:city":"Winnipeg",
    "sg:classifiers":[
        {
            "category":"Education",
            "subcategory":"School",
            "type":"Public Place"
        }
    ],
    "sg:phone":"+1 204 958 6840",
    "sg:postcode":"R2C 1J8",
    "sg:province":"MB",
    "wof:name":"Wayoata Elementary",
    "wof:placetype":"venue"
},
  "geometry": {"coordinates":[-96.98913574220001,49.8977241516],"type":"Point"}
}