{
  "type": "Feature",
  "properties": {
    "addr:full":"210 2nd Ave W Blaine Lake SK S0J 0J0",
    "addr:housenumber":"210",
    "addr:postcode":"s0j 0j0",
    "addr:street":"2Nd Ave W Blaine Lake",
    "iso:country":"CA",
    "sg:address":"210 2nd Ave W",
    "sg:city":"Blaine Lake",
    "sg:classifiers":[
        {
            "category":"Wholesale",
            "subcategory":"Scrap",
            "type":"Manufacturing & Wholesale Goods"
        }
    ],
    "sg:phone":"+1 306 497 3378",
    "sg:postcode":"S0J 0J0",
    "sg:province":"SK",
    "sg:tags":[
        "recycling",
        "center"
    ],
    "wof:name":"Sarcan Recycling",
    "wof:placetype":"venue"
},
  "geometry": {"coordinates":[-106.87867,52.827629],"type":"Point"}
}