{
  "type": "Feature",
  "properties": {
    "addr:full":"95 Cascade St # 2 Hamilton ON L8E 3B7",
    "addr:housenumber":"95",
    "addr:postcode":"l8e 3b7",
    "addr:street":"Cascade St # 2",
    "iso:country":"CA",
    "sg:address":"95 Cascade St # 2",
    "sg:city":"Hamilton",
    "sg:classifiers":[
        {
            "category":"Building & Trades",
            "subcategory":"Construction",
            "type":"Services"
        }
    ],
    "sg:phone":"+1 905 560 5064",
    "sg:postcode":"L8E 3B7",
    "sg:province":"ON",
    "sg:tags":[
        "bridge",
        "builder"
    ],
    "wof:name":"Wercholoz Canada Inc",
    "wof:placetype":"venue"
},
  "geometry": {"coordinates":[-79.7542724609,43.2395553589],"type":"Point"}
}