{
  "type": "Feature",
  "properties": {
    "addr:full":"Toronto ON M5T 1A4",
    "addr:postcode":"m5t 1a4",
    "iso:country":"CA",
    "sg:city":"Toronto",
    "sg:classifiers":[
        {
            "category":"Real Estate",
            "subcategory":"Architect",
            "type":"Services"
        }
    ],
    "sg:phone":"+1 416 703 0866",
    "sg:postcode":"M5T 1A4",
    "sg:province":"ON",
    "wof:name":"Allen, Ellen Vera",
    "wof:placetype":"venue"
},
  "geometry": {"coordinates":[-79.40245819090001,43.6482810974],"type":"Point"}
}