{
  "type": "Feature",
  "properties": {
    "iso:country":"CA",
    "sg:address":"3766 Boul Saint-Laurent",
    "sg:city":"Montreal",
    "sg:classifiers":[
        {
            "category":"Restaurant",
            "type":"Food & Drink"
        }
    ],
    "sg:phone":"+1 514 286 6668",
    "sg:postcode":"H2W 1X6",
    "sg:province":"QC",
    "wof:name":"Gourmet D'Orient",
    "wof:placetype":"venue"
},
  "geometry": {"coordinates":[-73.575546,45.51511],"type":"Point"}
}