{
  "type": "Feature",
  "properties": {
    "addr:full":"885 Taylor Creek Dr Orleans ON K1C 1T1",
    "addr:housenumber":"885",
    "addr:postcode":"k1c 1t1",
    "addr:street":"Taylor Creek Dr",
    "iso:country":"CA",
    "sg:address":"885 Taylor Creek Dr",
    "sg:city":"Orleans",
    "sg:classifiers":[
        {
            "category":"Sports & Exercise",
            "subcategory":"Bowling",
            "type":"Entertainment"
        }
    ],
    "sg:phone":"+1 613 837 7000",
    "sg:postcode":"K1C 1T1",
    "sg:province":"ON",
    "sg:tags":[
        "center"
    ],
    "wof:name":"Orleans Bowling Ctr",
    "wof:placetype":"venue"
},
  "geometry": {"coordinates":[-75.481667,45.491856],"type":"Point"}
}