{
  "type": "Feature",
  "properties": {
    "iso:country":"CA",
    "sg:city":"Kirkland",
    "sg:classifiers":[
        {
            "category":"Shopping",
            "subcategory":"Pharmacy",
            "type":"Retail Goods"
        }
    ],
    "sg:phone":"+1 514 697 1445",
    "sg:postcode":"H9J 3W3",
    "sg:province":"QC",
    "sg:tags":[
        "equipment",
        "hospital",
        "supply",
        "aid",
        "first"
    ],
    "wof:name":"Ranco Impex Canada Ltd",
    "wof:placetype":"venue"
},
  "geometry": {"coordinates":[-73.881111,45.446651],"type":"Point"}
}