{
  "type": "Feature",
  "properties": {
    "addr:full":"11 Railway St S Pilot Mound MB R0G 1P0",
    "addr:housenumber":"11",
    "addr:postcode":"r0g 1p0",
    "addr:street":"Railway St S Pilot Mound",
    "iso:country":"CA",
    "sg:address":"11 Railway St S",
    "sg:city":"Pilot Mound",
    "sg:classifiers":[
        {
            "category":"Shopping",
            "subcategory":"Discount & Variety Stores",
            "type":"Retail Goods"
        }
    ],
    "sg:phone":"+1 204 825 2300",
    "sg:postcode":"R0G 1P0",
    "sg:province":"MB",
    "wof:name":"Margy's This & That",
    "wof:placetype":"venue"
},
  "geometry": {"coordinates":[-98.8960723877,49.202381134],"type":"Point"}
}