{
  "type": "Feature",
  "properties": {
    "addr:full":"5636 Boul Labelle Val-Morin QC J0T 2R0",
    "addr:housenumber":"5636",
    "addr:postcode":"j0t 2r0",
    "addr:street":"Boul Labelle",
    "iso:country":"CA",
    "sg:address":"5636 Boul Labelle",
    "sg:city":"Val-Morin",
    "sg:classifiers":[
        {
            "category":"Manufacturing",
            "subcategory":"Buildings",
            "type":"Manufacturing & Wholesale Goods"
        }
    ],
    "sg:phone":"+1 450 229 2933",
    "sg:postcode":"J0T 2R0",
    "sg:province":"QC",
    "sg:tags":[
        "home",
        "log",
        "cabin"
    ],
    "wof:name":"Maisons En Bois Rond",
    "wof:placetype":"venue"
},
  "geometry": {"coordinates":[-74.19622,45.991116],"type":"Point"}
}