{
  "type": "Feature",
  "properties": {
    "iso:country":"CA",
    "sg:address":"1920 Dundas St",
    "sg:city":"London",
    "sg:classifiers":[
        {
            "category":"Health Services",
            "subcategory":"Doctor",
            "type":"Services"
        }
    ],
    "sg:phone":"+1 519 455 8522",
    "sg:postcode":"N5V 3P1",
    "sg:province":"ON",
    "sg:tags":[
        "dentist"
    ],
    "wof:name":"Lewis, Norman F DDS",
    "wof:placetype":"venue"
},
  "geometry": {"coordinates":[-81.175003,43.005131],"type":"Point"}
}