{
  "type": "Feature",
  "properties": {
    "addr:full":"Melville SK S0A 2P0",
    "addr:postcode":"s0a 2p0",
    "iso:country":"CA",
    "sg:city":"Melville",
    "sg:classifiers":[
        {
            "category":"Museum",
            "type":"Entertainment"
        }
    ],
    "sg:phone":"+1 306 728 2070",
    "sg:postcode":"S0A 2P0",
    "sg:province":"SK",
    "wof:name":"Melville Heritage Museum",
    "wof:placetype":"venue"
},
  "geometry": {"coordinates":[-102.819915772,50.9382362366],"type":"Point"}
}