{
  "type": "Feature",
  "properties": {
    "addr:full":"132 Centre Ave NE Milk River AB T0K 1M0",
    "addr:housenumber":"132",
    "addr:postcode":"t0k 1m0",
    "addr:street":"Centre Ave Ne",
    "iso:country":"CA",
    "sg:address":"132 Centre Ave NE",
    "sg:city":"Milk River",
    "sg:classifiers":[
        {
            "category":"Insurance",
            "subcategory":"Insurance Agent",
            "type":"Services"
        }
    ],
    "sg:phone":"+1 403 647 2083",
    "sg:postcode":"T0K 1M0",
    "sg:province":"AB",
    "wof:name":"B & C Insurance Svc Ltd",
    "wof:placetype":"venue"
},
  "geometry": {"coordinates":[-112.085823,49.148113],"type":"Point"}
}