{
  "type": "Feature",
  "properties": {
    "addr:full":"4520 Boul Saint-Joseph Saint-Nicephore QC J2A 1B2",
    "addr:housenumber":"4520",
    "addr:postcode":"j2a 1b2",
    "addr:street":"Boul Saint-Joseph Saint-Nicephore",
    "iso:country":"CA",
    "sg:address":"4520 Boul Saint-Joseph",
    "sg:city":"Saint-Nicephore",
    "sg:classifiers":[
        {
            "category":"Shopping",
            "subcategory":"Hobbies, Toys, & Games",
            "type":"Retail Goods"
        }
    ],
    "sg:phone":"+1 819 474 6419",
    "sg:postcode":"J2A 1B2",
    "sg:province":"QC",
    "sg:tags":[
        "product",
        "ceramic"
    ],
    "wof:name":"Tfg Ceramique",
    "wof:placetype":"venue"
},
  "geometry": {"coordinates":[-72.4384384155,45.8420677185],"type":"Point"}
}