{
  "type": "Feature",
  "properties": {
    "iso:country":"CA",
    "sg:address":"10801 Chemainus Rd",
    "sg:city":"Ladysmith",
    "sg:classifiers":[
        {
            "category":"Manufacturing",
            "subcategory":"Watercraft",
            "type":"Manufacturing & Wholesale Goods"
        }
    ],
    "sg:phone":"+1 250 245 8027",
    "sg:postcode":"V9G 2A4",
    "sg:province":"BC",
    "sg:tags":[
        "barge"
    ],
    "wof:name":"Saltair Marine Svc Ltd",
    "wof:placetype":"venue"
},
  "geometry": {"coordinates":[-123.803207398,48.9794616699],"type":"Point"}
}