{
  "type": "Feature",
  "properties": {
    "addr:full":"Surrey BC V4A 4N7",
    "addr:postcode":"v4a 4n7",
    "iso:country":"CA",
    "sg:city":"Surrey",
    "sg:classifiers":[
        {
            "category":"Personal",
            "type":"Services"
        }
    ],
    "sg:phone":"+1 604 536 3631",
    "sg:postcode":"V4A 4N7",
    "sg:province":"BC",
    "sg:tags":[
        "therapist",
        "massage"
    ],
    "wof:name":"White Rock Massage Therapy",
    "wof:placetype":"venue"
},
  "geometry": {"coordinates":[-122.801368713,49.0395278931],"type":"Point"}
}