{
  "type": "Feature",
  "properties": {
    "addr:full":"675 Garasraxa St Durham ON N0G 1R0",
    "addr:housenumber":"675",
    "addr:postcode":"n0g 1r0",
    "addr:street":"Garasraxa St",
    "iso:country":"CA",
    "sg:address":"675 Garasraxa St",
    "sg:city":"Durham",
    "sg:classifiers":[
        {
            "category":"Taxi",
            "type":"Transportation"
        }
    ],
    "sg:phone":"+1 519 369 3615",
    "sg:postcode":"N0G 1R0",
    "sg:province":"ON",
    "sg:tags":[
        "taxicab"
    ],
    "wof:name":"Durham Taxi",
    "wof:placetype":"venue"
},
  "geometry": {"coordinates":[-80.7406463623,44.1489067078],"type":"Point"}
}