{
  "type": "Feature",
  "properties": {
    "addr:full":"11 Ch Dyer Sutton QC J0E 2K0",
    "addr:housenumber":"11",
    "addr:postcode":"j0e 2k0",
    "addr:street":"Ch Dyer",
    "iso:country":"CA",
    "sg:address":"11 Ch Dyer",
    "sg:city":"Sutton",
    "sg:classifiers":[
        {
            "category":"Building & Trades",
            "subcategory":"Construction",
            "type":"Services"
        }
    ],
    "sg:phone":"+1 450 538 2277",
    "sg:postcode":"J0E 2K0",
    "sg:province":"QC",
    "sg:tags":[
        "excavating",
        "contractor"
    ],
    "wof:name":"Excavation Claude Laplante Inc",
    "wof:placetype":"venue"
},
  "geometry": {"coordinates":[-72.62312300000001,45.113449],"type":"Point"}
}