{
  "type": "Feature",
  "properties": {
    "addr:full":"4300 15 St SE Calgary AB T2G 3M8",
    "addr:housenumber":"4300",
    "addr:postcode":"t2g 3m8",
    "addr:street":"15 St Se",
    "iso:country":"CA",
    "sg:address":"4300 15 St SE",
    "sg:city":"Calgary",
    "sg:classifiers":[
        {
            "category":"Professional",
            "subcategory":"Research",
            "type":"Services"
        }
    ],
    "sg:phone":"+1 403 265 2128",
    "sg:postcode":"T2G 3M8",
    "sg:province":"AB",
    "sg:tags":[
        "environmental",
        "ecological"
    ],
    "wof:name":"I G Paper Recycling",
    "wof:placetype":"venue"
},
  "geometry": {"coordinates":[-114.02497099999999,51.014755],"type":"Point"}
}