{
  "type": "Feature",
  "properties": {
    "addr:full":"1553 Rue Bagot LA Baie QC G7B 2P7",
    "addr:housenumber":"1553",
    "addr:postcode":"g7b 2p7",
    "addr:street":"Rue Bagot",
    "iso:country":"CA",
    "sg:address":"1553 Rue Bagot",
    "sg:city":"LA Baie",
    "sg:classifiers":[
        {
            "category":"Building & Trades",
            "subcategory":"Construction",
            "type":"Services"
        }
    ],
    "sg:phone":"+1 418 544 0189",
    "sg:postcode":"G7B 2P7",
    "sg:province":"QC",
    "sg:tags":[
        "concrete",
        "cutting",
        "breaking",
        "sawing"
    ],
    "wof:name":"Sciage & Forage DE Beton-Fjord",
    "wof:placetype":"venue"
},
  "geometry": {"coordinates":[-70.888458,48.336803],"type":"Point"}
}