{
  "type": "Feature",
  "properties": {
    "iso:country":"CA",
    "sg:address":"6040 Kestrel Rd",
    "sg:city":"Mississauga",
    "sg:classifiers":[
        {
            "category":"Manufacturing",
            "subcategory":"Tools & Machinery",
            "type":"Manufacturing & Wholesale Goods"
        }
    ],
    "sg:phone":"+1 905 564 3247",
    "sg:postcode":"L5T 1S8",
    "sg:province":"ON",
    "sg:tags":[
        "die",
        "maker"
    ],
    "wof:name":"Molds Plus CO Ltd",
    "wof:placetype":"venue"
},
  "geometry": {"coordinates":[-79.6620254517,43.6445808411],"type":"Point"}
}