{
  "type": "Feature",
  "properties": {
    "iso:country":"CA",
    "sg:address":"218 Nathatch Bamfield E",
    "sg:city":"Bamfield",
    "sg:classifiers":[
        {
            "category":"Recreation",
            "type":"Entertainment"
        }
    ],
    "sg:phone":"+1 250 728 3343",
    "sg:postcode":"V0R 1B0",
    "sg:province":"BC",
    "sg:tags":[
        "hall",
        "auditorium"
    ],
    "wof:name":"Bamfield Community Hall",
    "wof:placetype":"venue"
},
  "geometry": {"coordinates":[-125.134742737,48.8198432922],"type":"Point"}
}