{
  "type": "Feature",
  "properties": {
    "addr:full":"1758 Bath Rd Kingston ON K7M 4Y2",
    "addr:housenumber":"1758",
    "addr:postcode":"k7m 4y2",
    "addr:street":"Bath Rd",
    "iso:country":"CA",
    "sg:address":"1758 Bath Rd",
    "sg:city":"Kingston",
    "sg:classifiers":[
        {
            "category":"Shopping",
            "subcategory":"Computers & Home Electronics",
            "type":"Retail Goods"
        }
    ],
    "sg:phone":"+1 613 384 4755",
    "sg:postcode":"K7M 4Y2",
    "sg:province":"ON",
    "sg:tags":[
        "television",
        "radio"
    ],
    "wof:name":"Atv Electronics",
    "wof:placetype":"venue"
},
  "geometry": {"coordinates":[-76.541168,44.238144],"type":"Point"}
}