{
  "type": "Feature",
  "properties": {
    "addr:full":"7940 56 St SE Calgary AB T2C 4S9",
    "addr:housenumber":"7940",
    "addr:postcode":"t2c 4s9",
    "addr:street":"56 St Se",
    "iso:country":"CA",
    "sg:address":"7940 56 St SE",
    "sg:city":"Calgary",
    "sg:classifiers":[
        {
            "category":"Manufacturing",
            "subcategory":"Metals",
            "type":"Manufacturing & Wholesale Goods"
        }
    ],
    "sg:phone":"+1 403 720 3633",
    "sg:postcode":"T2C 4S9",
    "sg:province":"AB",
    "sg:tags":[
        "coating"
    ],
    "wof:name":"Endurance Technologies Inc",
    "wof:placetype":"venue"
},
  "geometry": {"coordinates":[-113.95207977299999,50.9825134277],"type":"Point"}
}