{
  "type": "Feature",
  "properties": {
    "addr:full":"1160 Commerce St Thunder Bay ON P7E 6E9",
    "addr:housenumber":"1160",
    "addr:postcode":"p7e 6e9",
    "addr:street":"Commerce St",
    "iso:country":"CA",
    "sg:address":"1160 Commerce St",
    "sg:city":"Thunder Bay",
    "sg:classifiers":[
        {
            "category":"Professional",
            "subcategory":"Testing Lab",
            "type":"Services"
        }
    ],
    "sg:phone":"+1 807 475 3329",
    "sg:postcode":"P7E 6E9",
    "sg:province":"ON",
    "sg:tags":[
        "assayer",
        "assaying"
    ],
    "wof:name":"Als Chemex Ltd",
    "wof:placetype":"venue"
},
  "geometry": {"coordinates":[-89.2993392944,48.3726387024],"type":"Point"}
}