{
  "type": "Feature",
  "properties": {
    "iso:country":"CA",
    "sg:city":"Montreal",
    "sg:classifiers":[
        {
            "category":"Retail",
            "subcategory":"Laundry & Dry Cleaning",
            "type":"Services"
        }
    ],
    "sg:phone":"+1 514 285 2155",
    "sg:postcode":"H3A 1N8",
    "sg:province":"QC",
    "sg:tags":[
        "repairing",
        "fur"
    ],
    "wof:name":"Fourrures Robert Vigeant",
    "wof:placetype":"venue"
},
  "geometry": {"coordinates":[-73.5684585571,45.5061721802],"type":"Point"}
}