{
  "type": "Feature",
  "properties": {
    "addr:full":"402 1 Ave S Lethbridge AB T1J 0A6",
    "addr:housenumber":"402",
    "addr:postcode":"t1j 0a6",
    "addr:street":"1 Ave S",
    "iso:country":"CA",
    "sg:address":"402 1 Ave S",
    "sg:city":"Lethbridge",
    "sg:classifiers":[
        {
            "category":"Autos & Motor Vehicles",
            "subcategory":"Auto Supplies",
            "type":"Retail Goods"
        }
    ],
    "sg:phone":"+1 403 394 0482",
    "sg:postcode":"T1J 0A6",
    "sg:province":"AB",
    "sg:tags":[
        "tire"
    ],
    "wof:name":"Tire Direct Canada Ltd",
    "wof:placetype":"venue"
},
  "geometry": {"coordinates":[-112.841553,49.697601],"type":"Point"}
}