{
  "type": "Feature",
  "properties": {
    "addr:full":"1564 Conte Cres Windsor ON N9J 3N4",
    "addr:housenumber":"1564",
    "addr:postcode":"n9j 3n4",
    "addr:street":"Conte Cres",
    "iso:country":"CA",
    "sg:address":"1564 Conte Cres",
    "sg:city":"Windsor",
    "sg:classifiers":[
        {
            "category":"Shopping",
            "subcategory":"Computers & Home Electronics",
            "type":"Retail Goods"
        }
    ],
    "sg:phone":"+1 519 972 1476",
    "sg:postcode":"N9J 3N4",
    "sg:province":"ON",
    "sg:tags":[
        "equipment",
        "dealer"
    ],
    "wof:name":"Pare D Practical Computers",
    "wof:placetype":"venue"
},
  "geometry": {"coordinates":[-83.033913,42.317822],"type":"Point"}
}