{
  "type": "Feature",
  "properties": {
    "addr:full":"48 Northside Rd #109 Nepean ON K2H 5Z5",
    "addr:housenumber":"48;109",
    "addr:postcode":"k2h 5z5",
    "addr:street":"Northside Rd #",
    "iso:country":"CA",
    "sg:address":"48 Northside Rd #109",
    "sg:city":"Nepean",
    "sg:classifiers":[
        {
            "category":"Home & Garden",
            "subcategory":"Home Furnishings",
            "type":"Retail Goods"
        }
    ],
    "sg:phone":"+1 613 828 1515",
    "sg:postcode":"K2H 5Z5",
    "sg:province":"ON",
    "sg:tags":[
        "fixture",
        "bathroom",
        "remodeling"
    ],
    "wof:name":"Paradise Bath & Kitchen Supply",
    "wof:placetype":"venue"
},
  "geometry": {"coordinates":[-75.81665,45.328472],"type":"Point"}
}