{
  "type": "Feature",
  "properties": {
    "addr:full":"333 Fairmont Dr Saskatoon SK S7M 5N5",
    "addr:housenumber":"333",
    "addr:postcode":"s7m 5n5",
    "addr:street":"Fairmont Dr",
    "iso:country":"CA",
    "sg:address":"333 Fairmont Dr",
    "sg:city":"Saskatoon",
    "sg:classifiers":[
        {
            "category":"Organizations",
            "subcategory":"Religious Organization",
            "type":"Services"
        }
    ],
    "sg:phone":"+1 306 384 4202",
    "sg:postcode":"S7M 5N5",
    "sg:province":"SK",
    "sg:tags":[
        "church"
    ],
    "wof:name":"Fairmont Baptist Church",
    "wof:placetype":"venue"
},
  "geometry": {"coordinates":[-106.72181701700001,52.1238212585],"type":"Point"}
}