{
  "type": "Feature",
  "properties": {
    "iso:country":"CA",
    "sg:city":"Mississauga",
    "sg:classifiers":[
        {
            "category":"Wholesale",
            "subcategory":"Stationery",
            "type":"Manufacturing & Wholesale Goods"
        }
    ],
    "sg:phone":"+1 905 542 9150",
    "sg:postcode":"L5N 8G4",
    "sg:province":"ON",
    "sg:tags":[
        "packaging",
        "machinery"
    ],
    "wof:name":"Best Packaging Systems Inc",
    "wof:placetype":"venue"
},
  "geometry": {"coordinates":[-79.7733840942,43.5998001099],"type":"Point"}
}