{
  "type": "Feature",
  "properties": {
    "addr:full":"North York ON M3C 1T5",
    "addr:postcode":"m3c 1t5",
    "iso:country":"CA",
    "sg:city":"North York",
    "sg:classifiers":[
        {
            "category":"Education",
            "subcategory":"Special Training",
            "type":"Public Place"
        }
    ],
    "sg:phone":"+1 416 696 1010",
    "sg:postcode":"M3C 1T5",
    "sg:province":"ON",
    "sg:tags":[
        "management"
    ],
    "wof:name":"Ibec Training Ctr",
    "wof:placetype":"venue"
},
  "geometry": {"coordinates":[-79.3379898071,43.7187538147],"type":"Point"}
}