{
  "type": "Feature",
  "properties": {
    "iso:country":"CA",
    "sg:address":"16266 Morgan Creek Cres",
    "sg:city":"Surrey",
    "sg:classifiers":[
        {
            "category":"Wholesale",
            "subcategory":"Electrical",
            "type":"Manufacturing & Wholesale Goods"
        }
    ],
    "sg:phone":"+1 604 531 7666",
    "sg:postcode":"V3S 0H5",
    "sg:province":"BC",
    "sg:tags":[
        "electronic",
        "representative"
    ],
    "wof:name":"Taylor Marketing Inc",
    "wof:placetype":"venue"
},
  "geometry": {"coordinates":[-122.77169799799999,49.0666046143],"type":"Point"}
}