{
  "type": "Feature",
  "properties": {
    "iso:country":"CA",
    "sg:address":"103 Rue Marquis",
    "sg:city":"Thetford Mines",
    "sg:classifiers":[
        {
            "category":"Building & Trades",
            "subcategory":"Construction",
            "type":"Services"
        }
    ],
    "sg:phone":"+1 418 338 1156",
    "sg:postcode":"G6G 5P5",
    "sg:province":"QC",
    "sg:tags":[
        "contractor"
    ],
    "wof:name":"2735-9256 Quebec Inc",
    "wof:placetype":"venue"
},
  "geometry": {"coordinates":[-71.2645568848,46.1170043945],"type":"Point"}
}