{
  "type": "Feature",
  "properties": {
    "addr:full":"9 Armstrong Dr Smiths Falls ON K7A 5H7",
    "addr:housenumber":"9",
    "addr:postcode":"k7a 5h7",
    "addr:street":"Armstrong Dr",
    "iso:country":"CA",
    "sg:address":"9 Armstrong Dr",
    "sg:city":"Smiths Falls",
    "sg:classifiers":[
        {
            "category":"Health Services",
            "subcategory":"Nursing And Care Facility",
            "type":"Services"
        }
    ],
    "sg:phone":"+1 613 283 0691",
    "sg:postcode":"K7A 5H7",
    "sg:province":"ON",
    "sg:tags":[
        "home",
        "retirement",
        "community"
    ],
    "wof:name":"Willowdale Retirement Ctr",
    "wof:placetype":"venue"
},
  "geometry": {"coordinates":[-76.01752500000001,44.882397],"type":"Point"}
}