{
  "type": "Feature",
  "properties": {
    "addr:full":"550 King St N # C14 Waterloo ON N2L 5W6",
    "addr:housenumber":"550",
    "addr:postcode":"n2l 5w6",
    "addr:street":"King St N # C14",
    "iso:country":"CA",
    "sg:address":"550 King St N # C14",
    "sg:city":"Waterloo",
    "sg:classifiers":[
        {
            "category":"Shopping",
            "subcategory":"Luggage & Leather Goods",
            "type":"Retail Goods"
        }
    ],
    "sg:phone":"+1 519 747 7785",
    "sg:postcode":"N2L 5W6",
    "sg:province":"ON",
    "wof:name":"Bentley Leathers Inc",
    "wof:placetype":"venue"
},
  "geometry": {"coordinates":[-80.5300292969,43.4989242554],"type":"Point"}
}