{
  "type": "Feature",
  "properties": {
    "iso:country":"CA",
    "sg:address":"2991 Lougheed Hwy",
    "sg:city":"Coquitlam",
    "sg:classifiers":[
        {
            "category":"Real Estate",
            "subcategory":"Real Estate Operator",
            "type":"Services"
        }
    ],
    "sg:phone":"+1 604 941 9628",
    "sg:postcode":"V3B 6J6",
    "sg:province":"BC",
    "sg:tags":[
        "mall",
        "shopping",
        "center"
    ],
    "wof:name":"Pinetree Village",
    "wof:placetype":"venue"
},
  "geometry": {"coordinates":[-122.794288635,49.2752609253],"type":"Point"}
}