{
  "type": "Feature",
  "properties": {
    "addr:full":"6 Government Rd Kapuskasing ON P5N 2W3",
    "addr:housenumber":"6",
    "addr:postcode":"p5n 2w3",
    "addr:street":"Rd",
    "iso:country":"CA",
    "sg:address":"6 Government Rd",
    "sg:city":"Kapuskasing",
    "sg:classifiers":[
        {
            "category":"Travel",
            "subcategory":"Hotels & Motels",
            "type":"Entertainment"
        }
    ],
    "sg:phone":"+1 705 335 2366",
    "sg:postcode":"P5N 2W3",
    "sg:province":"ON",
    "wof:name":"Park Inn Motel",
    "wof:placetype":"venue"
},
  "geometry": {"coordinates":[-82.42407989500001,49.413028717],"type":"Point"}
}