{
  "type": "Feature",
  "properties": {
    "addr:full":"5421 Industrial Rd Drayton Valley AB T7A 1S8",
    "addr:housenumber":"5421",
    "addr:postcode":"t7a 1s8",
    "addr:street":"Industrial Rd",
    "iso:country":"CA",
    "sg:address":"5421 Industrial Rd",
    "sg:city":"Drayton Valley",
    "sg:classifiers":[
        {
            "category":"Wholesale",
            "subcategory":"Scrap",
            "type":"Manufacturing & Wholesale Goods"
        }
    ],
    "sg:phone":"+1 780 542 2462",
    "sg:postcode":"T7A 1S8",
    "sg:province":"AB",
    "sg:tags":[
        "environmental",
        "product",
        "recycling",
        "center"
    ],
    "wof:name":"Custom Industrial Cleaners",
    "wof:placetype":"venue"
},
  "geometry": {"coordinates":[-114.986076,53.225674],"type":"Point"}
}