{
  "type": "Feature",
  "properties": {
    "addr:full":"Hudson QC J0P 1H0",
    "addr:postcode":"j0p 1h0",
    "iso:country":"CA",
    "sg:city":"Hudson",
    "sg:classifiers":[
        {
            "category":"Banks & Credit Unions",
            "subcategory":"Bank",
            "type":"Services"
        }
    ],
    "sg:phone":"+1 450 458 5351",
    "sg:postcode":"J0P 1H0",
    "sg:province":"QC",
    "wof:name":"Banque Nationale Du Canada",
    "wof:placetype":"venue"
},
  "geometry": {"coordinates":[-74.1421966553,45.4591941833],"type":"Point"}
}