{
  "type": "Feature",
  "properties": {
    "iso:country":"CA",
    "sg:address":"31838 South Fraser Way",
    "sg:city":"Abbotsford",
    "sg:classifiers":[
        {
            "category":"Education",
            "subcategory":"College",
            "type":"Public Place"
        }
    ],
    "sg:phone":"+1 604 850 8668",
    "sg:postcode":"V2T 1V3",
    "sg:province":"BC",
    "sg:tags":[
        "academic",
        "training",
        "computer"
    ],
    "wof:name":"Cdi College of Business",
    "wof:placetype":"venue"
},
  "geometry": {"coordinates":[-122.341323852,49.0480003357],"type":"Point"}
}