{
  "type": "Feature",
  "properties": {
    "addr:full":"223 Lakeshore Rd E Mississauga ON L5G 1G5",
    "addr:housenumber":"223",
    "addr:postcode":"l5g 1g5",
    "addr:street":"Lakeshore Rd E",
    "iso:country":"CA",
    "sg:address":"223 Lakeshore Rd E",
    "sg:city":"Mississauga",
    "sg:classifiers":[
        {
            "category":"Shopping",
            "subcategory":"Pharmacy",
            "type":"Retail Goods"
        }
    ],
    "sg:phone":"+1 905 278 0747",
    "sg:postcode":"L5G 1G5",
    "sg:province":"ON",
    "wof:name":"Lighthouse Pharmacy Ltd",
    "wof:placetype":"venue"
},
  "geometry": {"coordinates":[-79.577827,43.558804],"type":"Point"}
}