{
  "type": "Feature",
  "properties": {
    "addr:full":"1715 Lakeshore Rd W Mississauga ON L5J 1J4",
    "addr:housenumber":"1715",
    "addr:postcode":"l5j 1j4",
    "addr:street":"Lakeshore Rd W",
    "iso:country":"CA",
    "sg:address":"1715 Lakeshore Rd W",
    "sg:city":"Mississauga",
    "sg:classifiers":[
        {
            "category":"Personal",
            "subcategory":"Beauty Salon",
            "type":"Services"
        }
    ],
    "sg:phone":"+1 905 855 2595",
    "sg:postcode":"L5J 1J4",
    "sg:province":"ON",
    "wof:name":"Prima Donna Hair Salon & Spa",
    "wof:placetype":"venue"
},
  "geometry": {"coordinates":[-79.6225814819,43.5180091858],"type":"Point"}
}