{
  "type": "Feature",
  "properties": {
    "addr:full":"10005 166 St NW Edmonton AB T5P 4Y1",
    "addr:housenumber":"10005",
    "addr:postcode":"t5p 4y1",
    "addr:street":"166 St Nw",
    "iso:country":"CA",
    "sg:address":"10005 166 St NW",
    "sg:city":"Edmonton",
    "sg:classifiers":[
        {
            "category":"Building & Trades",
            "subcategory":"Plumbing",
            "type":"Services"
        }
    ],
    "sg:phone":"+1 780 483 0577",
    "sg:postcode":"T5P 4Y1",
    "sg:province":"AB",
    "sg:tags":[
        "contractor"
    ],
    "wof:name":"Eastgate Mechanical Ltd",
    "wof:placetype":"venue"
},
  "geometry": {"coordinates":[-113.60732299999999,53.539597],"type":"Point"}
}