{
  "type": "Feature",
  "properties": {
    "iso:country":"CA",
    "sg:address":"10005 166 St NW",
    "sg:city":"Edmonton",
    "sg:classifiers":[
        {
            "category":"Building & Trades",
            "subcategory":"Plumbing",
            "type":"Services"
        }
    ],
    "sg:phone":"+1 780 483 0577",
    "sg:postcode":"T5P 4Y1",
    "sg:province":"AB",
    "sg:tags":[
        "contractor"
    ],
    "wof:name":"Eastgate Mechanical Ltd",
    "wof:placetype":"venue"
},
  "geometry": {"coordinates":[-113.607323,53.539597],"type":"Point"}
}