{
  "type": "Feature",
  "properties": {
    "addr:full":"2394 Jane St Brigden ON N0N 1B0",
    "addr:housenumber":"2394",
    "addr:postcode":"n0n 1b0",
    "addr:street":"Jane St",
    "iso:country":"CA",
    "sg:address":"2394 Jane St",
    "sg:city":"Brigden",
    "sg:classifiers":[
        {
            "category":"Banks & Credit Unions",
            "subcategory":"Bank",
            "type":"Services"
        }
    ],
    "sg:phone":"+1 519 864 1026",
    "sg:postcode":"N0N 1B0",
    "sg:province":"ON",
    "wof:name":"Lambton Financial Credit Union",
    "wof:placetype":"venue"
},
  "geometry": {"coordinates":[-82.2832946777,42.8139266968],"type":"Point"}
}