{
  "type": "Feature",
  "properties": {
    "addr:full":"77 Sixth St Earlton ON P0J 1E0",
    "addr:housenumber":"77",
    "addr:postcode":"p0j 1e0",
    "addr:street":"Sixth St",
    "iso:country":"CA",
    "sg:address":"77 Sixth St",
    "sg:city":"Earlton",
    "sg:classifiers":[
        {
            "category":"Professional",
            "type":"Services"
        }
    ],
    "sg:phone":"+1 705 648 3824",
    "sg:postcode":"P0J 1E0",
    "sg:province":"ON",
    "sg:tags":[
        "equipment",
        "mining",
        "establishment"
    ],
    "wof:name":"J M Distribution Ctr",
    "wof:placetype":"venue"
},
  "geometry": {"coordinates":[-79.81883999999999,47.707157],"type":"Point"}
}