{
  "type": "Feature",
  "properties": {
    "addr:full":"1132 14th St W North Vancouver BC V7P 1J8",
    "addr:housenumber":"1132",
    "addr:postcode":"v7p 1j8",
    "addr:street":"14Th St W",
    "iso:country":"CA",
    "sg:address":"1132 14th St W",
    "sg:city":"North Vancouver",
    "sg:classifiers":[
        {
            "category":"Home & Garden",
            "subcategory":"Building Materials",
            "type":"Retail Goods"
        }
    ],
    "sg:phone":"+1 604 985 3154",
    "sg:postcode":"V7P 1J8",
    "sg:province":"BC",
    "sg:tags":[
        "windows"
    ],
    "wof:name":"Ever-Brite Alum Prods Ltd",
    "wof:placetype":"venue"
},
  "geometry": {"coordinates":[-123.093628,49.321259],"type":"Point"}
}