{
  "type": "Feature",
  "properties": {
    "addr:full":"Campbell River BC V9W 3N7",
    "addr:postcode":"v9w 3n7",
    "iso:country":"CA",
    "sg:city":"Campbell River",
    "sg:classifiers":[
        {
            "category":"Home & Garden",
            "subcategory":"Building Materials",
            "type":"Retail Goods"
        }
    ],
    "sg:phone":"+1 250 287 9788",
    "sg:postcode":"V9W 3N7",
    "sg:province":"BC",
    "sg:tags":[
        "door"
    ],
    "wof:name":"Cbs Prehung Doors Ltd",
    "wof:placetype":"venue"
},
  "geometry": {"coordinates":[-125.258606,50.023479],"type":"Point"}
}