{
  "type": "Feature",
  "properties": {
    "addr:full":"889 Ward St # 6 Bridgenorth ON K0L 1H0",
    "addr:housenumber":"889",
    "addr:postcode":"k0l 1h0",
    "addr:street":"Ward St # 6 Bridgenorth",
    "iso:country":"CA",
    "sg:address":"889 Ward St # 6",
    "sg:city":"Bridgenorth",
    "sg:classifiers":[
        {
            "category":"Home & Garden",
            "subcategory":"Home Furnishings",
            "type":"Retail Goods"
        }
    ],
    "sg:phone":"+1 705 292 9889",
    "sg:postcode":"K0L 1H0",
    "sg:province":"ON",
    "sg:tags":[
        "stove",
        "wood",
        "fireplace",
        "burning"
    ],
    "wof:name":"Chemong Chimney",
    "wof:placetype":"venue"
},
  "geometry": {"coordinates":[-78.383408,44.383862],"type":"Point"}
}