{
  "type": "Feature",
  "properties": {
    "addr:full":"608 Ashton Ave E Beausejour MB R0E 0C0",
    "addr:housenumber":"608",
    "addr:postcode":"r0e 0c0",
    "addr:street":"Ashton Ave E",
    "iso:country":"CA",
    "sg:address":"608 Ashton Ave E",
    "sg:city":"Beausejour",
    "sg:classifiers":[
        {
            "category":"Shopping",
            "subcategory":"Hobbies, Toys, & Games",
            "type":"Retail Goods"
        }
    ],
    "sg:phone":"+1 204 268 2653",
    "sg:postcode":"R0E 0C0",
    "sg:province":"MB",
    "sg:tags":[
        "product",
        "ceramic"
    ],
    "wof:name":"Hoey Ceramics",
    "wof:placetype":"venue"
},
  "geometry": {"coordinates":[-96.51420593260001,50.0606956482],"type":"Point"}
}