{
  "type": "Feature",
  "properties": {
    "addr:full":"461 Rue Saint-Francois LA Tuque QC G9X 1T8",
    "addr:housenumber":"461",
    "addr:postcode":"g9x 1t8",
    "addr:street":"Rue Saint-Francois",
    "iso:country":"CA",
    "sg:address":"461 Rue Saint-Francois",
    "sg:city":"LA Tuque",
    "sg:classifiers":[
        {
            "category":"Education",
            "subcategory":"School",
            "type":"Public Place"
        }
    ],
    "sg:phone":"+1 819 676 3006",
    "sg:postcode":"G9X 1T8",
    "sg:province":"QC",
    "wof:name":"Ecole Forestiere DE LA Tuque",
    "wof:placetype":"venue"
},
  "geometry": {"coordinates":[-72.7763671875,47.437664032],"type":"Point"}
}