{
  "type": "Feature",
  "properties": {
    "iso:country":"CA",
    "sg:address":"4370 Boul Des Forges",
    "sg:city":"Trois-Rivieres",
    "sg:classifiers":[
        {
            "category":"Shopping",
            "subcategory":"Luggage & Leather Goods",
            "type":"Retail Goods"
        }
    ],
    "sg:phone":"+1 819 694 1812",
    "sg:postcode":"G8Y 1W4",
    "sg:province":"QC",
    "wof:name":"Cuir Des Forges",
    "wof:placetype":"venue"
},
  "geometry": {"coordinates":[-72.58815002439999,46.3582420349],"type":"Point"}
}