{
  "type": "Feature",
  "properties": {
    "addr:full":"Calgary AB T2H 0K3",
    "addr:postcode":"t2h 0k3",
    "iso:country":"CA",
    "sg:city":"Calgary",
    "sg:classifiers":[
        {
            "category":"Shopping",
            "subcategory":"Clothing, Apparel, & Fashions",
            "type":"Retail Goods"
        }
    ],
    "sg:phone":"+1 403 255 5600",
    "sg:postcode":"T2H 0K3",
    "sg:province":"AB",
    "sg:tags":[
        "furnishing"
    ],
    "wof:name":"Tip Top Tailors",
    "wof:placetype":"venue"
},
  "geometry": {"coordinates":[-114.071830749,50.9961624146],"type":"Point"}
}