{
  "type": "Feature",
  "properties": {
    "addr:full":"2655 Lakeshore Rd Port Hope ON L1A 3V7",
    "addr:housenumber":"2655",
    "addr:postcode":"l1a 3v7",
    "addr:street":"Lakeshore Rd",
    "iso:country":"CA",
    "sg:address":"2655 Lakeshore Rd",
    "sg:city":"Port Hope",
    "sg:classifiers":[
        {
            "category":"Manufacturing",
            "subcategory":"Metals",
            "type":"Manufacturing & Wholesale Goods"
        }
    ],
    "sg:phone":"+1 905 885 2600",
    "sg:postcode":"L1A 3V7",
    "sg:province":"ON",
    "sg:tags":[
        "steel"
    ],
    "wof:name":"Bromley Steel Fabricators",
    "wof:placetype":"venue"
},
  "geometry": {"coordinates":[-78.384972,43.929581],"type":"Point"}
}