{
  "type": "Feature",
  "properties": {
    "addr:full":"1290 Rue Fleury E Montreal QC H2C 1R1",
    "addr:housenumber":"1290",
    "addr:postcode":"h2c 1r1",
    "addr:street":"Rue Fleury E",
    "iso:country":"CA",
    "sg:address":"1290 Rue Fleury E",
    "sg:city":"Montreal",
    "sg:classifiers":[
        {
            "category":"Personal",
            "subcategory":"Beauty Salon",
            "type":"Services"
        }
    ],
    "sg:phone":"+1 514 387 9964",
    "sg:postcode":"H2C 1R1",
    "sg:province":"QC",
    "wof:name":"Scrupule Coiffure",
    "wof:placetype":"venue"
},
  "geometry": {"coordinates":[-73.658081,45.559597],"type":"Point"}
}