{
  "type": "Feature",
  "properties": {
    "iso:country":"CA",
    "sg:address":"12501 20th Ave # 208",
    "sg:city":"Blairmore",
    "sg:classifiers":[
        {
            "category":"Social Services",
            "type":"Services"
        }
    ],
    "sg:phone":"+1 403 562 8000",
    "sg:postcode":"T0K 0E0",
    "sg:province":"AB",
    "sg:tags":[
        "crisis",
        "center"
    ],
    "wof:name":"Crowsnest Pass Women's Ctr",
    "wof:placetype":"venue"
},
  "geometry": {"coordinates":[-114.44410705599999,49.6087303162],"type":"Point"}
}