{
  "type": "Feature",
  "properties": {
    "addr:full":"Saint-Colomban QC J5K 2H9",
    "addr:postcode":"j5k 2h9",
    "iso:country":"CA",
    "sg:city":"Saint-Colomban",
    "sg:classifiers":[
        {
            "category":"Taxi",
            "type":"Transportation"
        }
    ],
    "sg:phone":"+1 450 436 9787",
    "sg:postcode":"J5K 2H9",
    "sg:province":"QC",
    "sg:tags":[
        "taxicab"
    ],
    "wof:name":"Allo Taxi",
    "wof:placetype":"venue"
},
  "geometry": {"coordinates":[-74.13681800000001,45.738972],"type":"Point"}
}