{
  "type": "Feature",
  "properties": {
    "addr:full":"830 Upper James St Hamilton ON L9C 3A4",
    "addr:housenumber":"830",
    "addr:postcode":"l9c 3a4",
    "addr:street":"Upper James St",
    "iso:country":"CA",
    "sg:address":"830 Upper James St",
    "sg:city":"Hamilton",
    "sg:classifiers":[
        {
            "category":"Banks & Credit Unions",
            "subcategory":"Bank",
            "type":"Services"
        }
    ],
    "sg:phone":"+1 905 387 9330",
    "sg:postcode":"L9C 3A4",
    "sg:province":"ON",
    "wof:name":"Td Canada Trust",
    "wof:placetype":"venue"
},
  "geometry": {"coordinates":[-79.88226299999999,43.227879],"type":"Point"}
}