{
  "type": "Feature",
  "properties": {
    "iso:country":"CA",
    "sg:address":"830 Upper James St",
    "sg:city":"Hamilton",
    "sg:classifiers":[
        {
            "category":"Banks & Credit Unions",
            "subcategory":"Bank",
            "type":"Services"
        }
    ],
    "sg:phone":"+1 905 387 9330",
    "sg:postcode":"L9C 3A4",
    "sg:province":"ON",
    "wof:name":"Td Canada Trust",
    "wof:placetype":"venue"
},
  "geometry": {"coordinates":[-79.882263,43.227879],"type":"Point"}
}