{
  "type": "Feature",
  "properties": {
    "iso:country":"CA",
    "sg:address":"250 Trowers Rd # 4",
    "sg:city":"Woodbridge",
    "sg:classifiers":[
        {
            "category":"Education",
            "subcategory":"School",
            "type":"Public Place"
        }
    ],
    "sg:phone":"+1 905 856 1030",
    "sg:postcode":"L4L 5Z6",
    "sg:province":"ON",
    "sg:tags":[
        "academic",
        "instruction",
        "special",
        "dancing"
    ],
    "wof:name":"Performing Dance Arts Inc",
    "wof:placetype":"venue"
},
  "geometry": {"coordinates":[-79.561081,43.785583],"type":"Point"}
}