{
  "type": "Feature",
  "properties": {
    "addr:full":"5755 Boul DE Maisonneuve O Montreal QC H4A 2A1",
    "addr:housenumber":"5755",
    "addr:postcode":"h4a 2a1",
    "addr:street":"Boul De Maisonneuve O",
    "iso:country":"CA",
    "sg:address":"5755 Boul DE Maisonneuve O",
    "sg:city":"Montreal",
    "sg:classifiers":[
        {
            "category":"Retail",
            "subcategory":"Auto Repair",
            "type":"Services"
        }
    ],
    "sg:phone":"+1 514 481 3685",
    "sg:postcode":"H4A 2A1",
    "sg:province":"QC",
    "sg:tags":[
        "repairing",
        "automobile"
    ],
    "wof:name":"Mitch Auto Electrique",
    "wof:placetype":"venue"
},
  "geometry": {"coordinates":[-73.6132278442,45.4688072205],"type":"Point"}
}