{
  "type": "Feature",
  "properties": {
    "addr:full":"Colborne ON K0K 1S0",
    "addr:postcode":"k0k 1s0",
    "iso:country":"CA",
    "sg:city":"Colborne",
    "sg:classifiers":[
        {
            "category":"Building & Trades",
            "subcategory":"Construction",
            "type":"Services"
        }
    ],
    "sg:phone":"+1 905 355 2938",
    "sg:postcode":"K0K 1S0",
    "sg:province":"ON",
    "sg:tags":[
        "contractor"
    ],
    "wof:name":"Mike W Voskamp Construction",
    "wof:placetype":"venue"
},
  "geometry": {"coordinates":[-77.883247,44.02993],"type":"Point"}
}