{
  "type": "Feature",
  "properties": {
    "addr:full":"287 County Blvd Thunder Bay ON P7A 7M9",
    "addr:housenumber":"287",
    "addr:postcode":"p7a 7m9",
    "addr:street":"County Blvd",
    "iso:country":"CA",
    "sg:address":"287 County Blvd",
    "sg:city":"Thunder Bay",
    "sg:classifiers":[
        {
            "category":"Wholesale",
            "subcategory":"Vending Machines",
            "type":"Manufacturing & Wholesale Goods"
        }
    ],
    "sg:phone":"+1 807 767 7800",
    "sg:postcode":"P7A 7M9",
    "sg:province":"ON",
    "wof:name":"R & B Vending",
    "wof:placetype":"venue"
},
  "geometry": {"coordinates":[-89.24992370610001,48.4548301697],"type":"Point"}
}