{
  "type": "Feature",
  "properties": {
    "addr:full":"10 Rouse St E Tillsonburg ON N4G 4J1",
    "addr:housenumber":"10",
    "addr:postcode":"n4g 4j1",
    "addr:street":"Rouse St E",
    "iso:country":"CA",
    "sg:address":"10 Rouse St E",
    "sg:city":"Tillsonburg",
    "sg:classifiers":[
        {
            "category":"Manufacturing",
            "subcategory":"Glass & Minerals",
            "type":"Manufacturing & Wholesale Goods"
        }
    ],
    "sg:phone":"+1 519 842 6421",
    "sg:postcode":"N4G 4J1",
    "sg:province":"ON",
    "wof:name":"Guardian Industries",
    "wof:placetype":"venue"
},
  "geometry": {"coordinates":[-80.7218551636,42.8472175598],"type":"Point"}
}