{
  "type": "Feature",
  "properties": {
    "addr:full":"2724 Highway 6 Slocan Park BC V0G 2E0",
    "addr:housenumber":"2724",
    "addr:postcode":"bc v0g 2e0",
    "addr:street":"Highway 6 Slocan Park",
    "iso:country":"CA",
    "sg:address":"2724 Highway 6",
    "sg:city":"Slocan Park",
    "sg:classifiers":[
        {
            "category":"Freight",
            "type":"Transportation"
        }
    ],
    "sg:phone":"+1 250 226 7764",
    "sg:postcode":"V0G 2E0",
    "sg:province":"BC",
    "sg:tags":[
        "trucking"
    ],
    "wof:name":"Northway Trucking",
    "wof:placetype":"venue"
},
  "geometry": {"coordinates":[-117.627228,49.518002],"type":"Point"}
}