{
  "type": "Feature",
  "properties": {
    "addr:full":"96 Church St Echo Bay ON P0S 1C0",
    "addr:housenumber":"96",
    "addr:postcode":"p0s 1c0",
    "addr:street":"Church St",
    "iso:country":"CA",
    "sg:address":"96 Church St",
    "sg:city":"Echo Bay",
    "sg:classifiers":[
        {
            "category":"Social Services",
            "type":"Services"
        }
    ],
    "sg:phone":"+1 705 248 2989",
    "sg:postcode":"P0S 1C0",
    "sg:province":"ON",
    "sg:tags":[
        "organization",
        "welfare"
    ],
    "wof:name":"Echo Bay Elks Lodge",
    "wof:placetype":"venue"
},
  "geometry": {"coordinates":[-84.07730100000001,46.484932],"type":"Point"}
}