{
  "type": "Feature",
  "properties": {
    "iso:country":"CA",
    "sg:address":"5216 50 Ave",
    "sg:city":"Leduc",
    "sg:classifiers":[
        {
            "category":"Home & Garden",
            "subcategory":"Furniture",
            "type":"Retail Goods"
        }
    ],
    "sg:phone":"+1 780 980 3475",
    "sg:postcode":"T9E 6V2",
    "sg:province":"AB",
    "wof:name":"United Furniture Warehouse",
    "wof:placetype":"venue"
},
  "geometry": {"coordinates":[-113.55824279799999,53.2649269104],"type":"Point"}
}