{
  "type": "Feature",
  "properties": {
    "iso:country":"CA",
    "sg:address":"595 Keith Rd",
    "sg:city":"West Vancouver",
    "sg:classifiers":[
        {
            "category":"Organizations",
            "subcategory":"Religious Organization",
            "type":"Services"
        }
    ],
    "sg:phone":"+1 604 922 1371",
    "sg:postcode":"V7T 1L8",
    "sg:province":"BC",
    "sg:tags":[
        "church"
    ],
    "wof:name":"Christ the Redeemer Church",
    "wof:placetype":"venue"
},
  "geometry": {"coordinates":[-123.132255554,49.3308830261],"type":"Point"}
}