{
  "type": "Feature",
  "properties": {
    "addr:full":"10 Boul Belisle Sainte-Therese QC J7E 3P6",
    "addr:housenumber":"10",
    "addr:postcode":"j7e 3p6",
    "addr:street":"Boul Belisle Sainte-Therese",
    "iso:country":"CA",
    "sg:address":"10 Boul Belisle",
    "sg:city":"Sainte-Therese",
    "sg:classifiers":[
        {
            "category":"Education",
            "subcategory":"School",
            "type":"Public Place"
        }
    ],
    "sg:phone":"+1 450 433 5525",
    "sg:postcode":"J7E 3P6",
    "sg:province":"QC",
    "wof:name":"Pavillon Lionel Bertrand",
    "wof:placetype":"venue"
},
  "geometry": {"coordinates":[-73.83644099999999,45.632183],"type":"Point"}
}