{
  "type": "Feature",
  "properties": {
    "iso:country":"CA",
    "sg:address":"930 Rue Wellington S",
    "sg:city":"Sherbrooke",
    "sg:classifiers":[
        {
            "category":"Retail",
            "subcategory":"Auto Repair",
            "type":"Services"
        }
    ],
    "sg:phone":"+1 819 563 6644",
    "sg:postcode":"J1H 5E4",
    "sg:province":"QC",
    "sg:tags":[
        "repairing",
        "automobile"
    ],
    "wof:name":"Belmont Pneu Inc",
    "wof:placetype":"venue"
},
  "geometry": {"coordinates":[-71.8846664429,45.3921127319],"type":"Point"}
}