{
  "type": "Feature",
  "properties": {
    "addr:full":"322 John St Victoria BC V8T 1T3",
    "addr:housenumber":"322",
    "addr:postcode":"v8t 1t3",
    "addr:street":"John St",
    "iso:country":"CA",
    "sg:address":"322 John St",
    "sg:city":"Victoria",
    "sg:classifiers":[
        {
            "category":"Mining & Drilling",
            "type":"Manufacturing & Wholesale Goods"
        }
    ],
    "sg:phone":"+1 250 386 7791",
    "sg:postcode":"V8T 1T3",
    "sg:province":"BC",
    "sg:tags":[
        "company"
    ],
    "wof:name":"Goldminco Consolidated Mining",
    "wof:placetype":"venue"
},
  "geometry": {"coordinates":[-123.376114,48.435715],"type":"Point"}
}