{
  "type": "Feature",
  "properties": {
    "iso:country":"CA",
    "sg:city":"Halifax",
    "sg:classifiers":[
        {
            "category":"Health Services",
            "subcategory":"Doctor",
            "type":"Services"
        }
    ],
    "sg:phone":"+1 902 420 9383",
    "sg:postcode":"B3J 1H1",
    "sg:province":"NS",
    "sg:tags":[
        "physician",
        "surgeon"
    ],
    "wof:name":"Preventive Medicine Ctr",
    "wof:placetype":"venue"
},
  "geometry": {"coordinates":[-63.5792388916,44.6425704956],"type":"Point"}
}