{
  "type": "Feature",
  "properties": {
    "iso:country":"CA",
    "sg:city":"Ottawa",
    "sg:classifiers":[
        {
            "category":"Freight",
            "type":"Transportation"
        }
    ],
    "sg:phone":"+1 613 244 0586",
    "sg:postcode":"K1B 3V9",
    "sg:province":"ON",
    "sg:tags":[
        "mover"
    ],
    "wof:name":"Simplex Industries Inc",
    "wof:placetype":"venue"
},
  "geometry": {"coordinates":[-75.60409545900001,45.4003982544],"type":"Point"}
}