{
  "type": "Feature",
  "properties": {
    "iso:country":"CA",
    "sg:address":"2120 Prince Charles Rd",
    "sg:city":"Ottawa",
    "sg:classifiers":[
        {
            "category":"Organizations",
            "subcategory":"Religious Organization",
            "type":"Services"
        }
    ],
    "sg:phone":"+1 613 722 6077",
    "sg:postcode":"K2A 3L3",
    "sg:province":"ON",
    "sg:tags":[
        "church"
    ],
    "wof:name":"St Martin's Anglican Church",
    "wof:placetype":"venue"
},
  "geometry": {"coordinates":[-75.77025604249999,45.3760375977],"type":"Point"}
}