{
  "type": "Feature",
  "properties": {
    "iso:country":"CA",
    "sg:address":"19 Robert St",
    "sg:city":"Sioux Lookout",
    "sg:classifiers":[
        {
            "category":"Personal",
            "subcategory":"Beauty Salon",
            "type":"Services"
        }
    ],
    "sg:phone":"+1 807 737 7111",
    "sg:postcode":"P8T 1C8",
    "sg:province":"ON",
    "wof:name":"Chez Cherie Hair Salon",
    "wof:placetype":"venue"
},
  "geometry": {"coordinates":[-91.91270400000001,50.09404],"type":"Point"}
}