{
  "type": "Feature",
  "properties": {
    "addr:full":"1431 Rebecca St Oakville ON L6L 1Z6",
    "addr:housenumber":"1431",
    "addr:postcode":"l6l 1z6",
    "addr:street":"Rebecca St",
    "iso:country":"CA",
    "sg:address":"1431 Rebecca St",
    "sg:city":"Oakville",
    "sg:classifiers":[
        {
            "category":"Food & Beverages",
            "subcategory":"Liquor & Beverages",
            "type":"Retail Goods"
        }
    ],
    "sg:phone":"+1 905 827 1301",
    "sg:postcode":"L6L 1Z6",
    "sg:province":"ON",
    "sg:tags":[
        "beer",
        "ale"
    ],
    "wof:name":"Beer Store",
    "wof:placetype":"venue"
},
  "geometry": {"coordinates":[-79.70319366459999,43.4135398865],"type":"Point"}
}