{
  "type": "Feature",
  "properties": {
    "iso:country":"CA",
    "sg:address":"3035 Ch Gascon",
    "sg:city":"Mascouche",
    "sg:classifiers":[
        {
            "category":"Autos & Motor Vehicles",
            "subcategory":"Automobile Sales",
            "type":"Retail Goods"
        }
    ],
    "sg:phone":"+1 450 477 6348",
    "sg:postcode":"J7L 3X7",
    "sg:province":"QC",
    "sg:tags":[
        "car",
        "dealer"
    ],
    "wof:name":"Trois Diamants Autos Inc",
    "wof:placetype":"venue"
},
  "geometry": {"coordinates":[-73.67527771,45.7310791016],"type":"Point"}
}