{
  "type": "Feature",
  "properties": {
    "iso:country":"CA",
    "sg:address":"438 Alice Ave",
    "sg:city":"Kitchener",
    "sg:classifiers":[
        {
            "category":"Building & Trades",
            "subcategory":"Construction",
            "type":"Services"
        }
    ],
    "sg:phone":"+1 519 745 6765",
    "sg:postcode":"N2M 2A4",
    "sg:province":"ON",
    "sg:tags":[
        "dry wall",
        "contractor"
    ],
    "wof:name":"Campbell's Drywall",
    "wof:placetype":"venue"
},
  "geometry": {"coordinates":[-80.51708221440001,43.4428863525],"type":"Point"}
}