{
  "type": "Feature",
  "properties": {
    "addr:full":"12180 Ch Du Golf Montreal QC H4K 1S5",
    "addr:postcode":"12180;h4k 1s5",
    "addr:street":"Ch Du Golf",
    "iso:country":"CA",
    "sg:address":"12180 Ch Du Golf",
    "sg:city":"Montreal",
    "sg:classifiers":[
        {
            "category":"Professional",
            "subcategory":"Management & Consulting",
            "type":"Services"
        }
    ],
    "sg:phone":"+1 514 338 3745",
    "sg:postcode":"H4K 1S5",
    "sg:province":"QC",
    "sg:tags":[
        "consultant",
        "energy",
        "conservation"
    ],
    "wof:name":"Global Facman Enterprises Inc",
    "wof:placetype":"venue"
},
  "geometry": {"coordinates":[-73.7259902954,45.5267105103],"type":"Point"}
}