{
  "type": "Feature",
  "properties": {
    "iso:country":"CA",
    "sg:address":"220 Railway St",
    "sg:city":"Southampton",
    "sg:classifiers":[
        {
            "category":"Home & Garden",
            "subcategory":"Garden Supply",
            "type":"Retail Goods"
        }
    ],
    "sg:phone":"+1 519 797 1228",
    "sg:postcode":"N0H 2L0",
    "sg:province":"ON",
    "sg:tags":[
        "nurseryman",
        "center"
    ],
    "wof:name":"Poppy's Garden Ctr",
    "wof:placetype":"venue"
},
  "geometry": {"coordinates":[-81.37590026860001,44.4860305786],"type":"Point"}
}