{
  "type": "Feature",
  "properties": {
    "addr:full":"445 Stradbrook Ave Winnipeg MB R3L 0J7",
    "addr:housenumber":"445",
    "addr:postcode":"r3l 0j7",
    "addr:street":"Stradbrook Ave",
    "iso:country":"CA",
    "sg:address":"445 Stradbrook Ave",
    "sg:city":"Winnipeg",
    "sg:classifiers":[
        {
            "category":"Personal",
            "subcategory":"Beauty Salon",
            "type":"Services"
        }
    ],
    "sg:phone":"+1 204 953 3620",
    "sg:postcode":"R3L 0J7",
    "sg:province":"MB",
    "sg:tags":[
        "spa"
    ],
    "wof:name":"Strada Personal Spa",
    "wof:placetype":"venue"
},
  "geometry": {"coordinates":[-97.143929,49.878185],"type":"Point"}
}