{
  "type": "Feature",
  "properties": {
    "addr:full":"Frenchman's Head Hudson ON P0V 1X0",
    "addr:postcode":"p0v 1x0",
    "addr:street":"Frenchman'S",
    "iso:country":"CA",
    "sg:address":"Frenchman's Head",
    "sg:city":"Hudson",
    "sg:classifiers":[
        {
            "category":"Health Services",
            "subcategory":"Hospital",
            "type":"Services"
        }
    ],
    "sg:phone":"+1 807 582 9813",
    "sg:postcode":"P0V 1X0",
    "sg:province":"ON",
    "sg:tags":[
        "mental"
    ],
    "wof:name":"Lac Seul Community Wellness",
    "wof:placetype":"venue"
},
  "geometry": {"coordinates":[-92.169296,50.090832],"type":"Point"}
}