{
  "type": "Feature",
  "properties": {
    "addr:full":"Vancouver BC V6Z 1W2",
    "addr:postcode":"v6z 1w2",
    "iso:country":"CA",
    "sg:city":"Vancouver",
    "sg:classifiers":[
        {
            "category":"Professional",
            "type":"Services"
        }
    ],
    "sg:phone":"+1 604 488 0031",
    "sg:postcode":"V6Z 1W2",
    "sg:province":"BC",
    "sg:tags":[
        "attendant",
        "establishment",
        "parking"
    ],
    "wof:name":"Sunwest Parking",
    "wof:placetype":"venue"
},
  "geometry": {"coordinates":[-123.12895202599999,49.2776947021],"type":"Point"}
}