{
  "type": "Feature",
  "properties": {
    "addr:full":"188 Main St Antigonish NS B2G 2B9",
    "addr:housenumber":"188",
    "addr:postcode":"b2g 2b9",
    "addr:street":"Main St",
    "iso:country":"CA",
    "sg:address":"188 Main St",
    "sg:city":"Antigonish",
    "sg:classifiers":[
        {
            "category":"Insurance",
            "subcategory":"Insurance Agent",
            "type":"Services"
        }
    ],
    "sg:phone":"+1 902 863 3544",
    "sg:postcode":"B2G 2B9",
    "sg:province":"NS",
    "wof:name":"Antigonish Farmers Mutual Fire",
    "wof:placetype":"venue"
},
  "geometry": {"coordinates":[-61.988403,45.622986],"type":"Point"}
}