{
  "type": "Feature",
  "properties": {
    "addr:full":"195 Rue Principale E Magog QC J1X 1Y6",
    "addr:housenumber":"195",
    "addr:postcode":"j1x 1y6",
    "addr:street":"Rue Principale E",
    "iso:country":"CA",
    "sg:address":"195 Rue Principale E",
    "sg:city":"Magog",
    "sg:classifiers":[
        {
            "category":"Shopping",
            "subcategory":"Used Merchandise",
            "type":"Retail Goods"
        }
    ],
    "sg:phone":"+1 819 847 2260",
    "sg:postcode":"J1X 1Y6",
    "sg:province":"QC",
    "sg:tags":[
        "clothing"
    ],
    "wof:name":"Vrai Comptoir Familial Pour",
    "wof:placetype":"venue"
},
  "geometry": {"coordinates":[-72.14128100000001,45.263428],"type":"Point"}
}