{
  "type": "Feature",
  "properties": {
    "addr:full":"142 Rue Principale Saint-Benoit-Labre QC G0M 1P0",
    "addr:housenumber":"142",
    "addr:postcode":"g0m 1p0",
    "addr:street":"Rue Principale",
    "iso:country":"CA",
    "sg:address":"142 Rue Principale",
    "sg:city":"Saint-Benoit-Labre",
    "sg:classifiers":[
        {
            "category":"Building & Trades",
            "subcategory":"Cleaning & Sanitation",
            "type":"Services"
        }
    ],
    "sg:phone":"+1 418 228 3669",
    "sg:postcode":"G0M 1P0",
    "sg:province":"QC",
    "sg:tags":[
        "maintenance"
    ],
    "wof:name":"Specialiste & Nettoyage Haute",
    "wof:placetype":"venue"
},
  "geometry": {"coordinates":[-70.79190800000001,46.069473],"type":"Point"}
}