{
  "type": "Feature",
  "properties": {
    "iso:country":"CA",
    "sg:address":"24 Brian Dr",
    "sg:city":"Burford",
    "sg:classifiers":[
        {
            "category":"Autos & Motor Vehicles",
            "subcategory":"Recreational Vehicle Sales",
            "type":"Retail Goods"
        }
    ],
    "sg:phone":"+1 519 449 2822",
    "sg:postcode":"N0E 1A0",
    "sg:province":"ON",
    "wof:name":"Wrg Ent",
    "wof:placetype":"venue"
},
  "geometry": {"coordinates":[-80.43482971189999,43.0962715149],"type":"Point"}
}