{
  "type": "Feature",
  "properties": {
    "addr:full":"Mississauga ON L5N 4C4",
    "addr:postcode":"l5n 4c4",
    "iso:country":"CA",
    "sg:city":"Mississauga",
    "sg:classifiers":[
        {
            "category":"Shopping",
            "subcategory":"Pharmacy",
            "type":"Retail Goods"
        }
    ],
    "sg:phone":"+1 905 824 0701",
    "sg:postcode":"L5N 4C4",
    "sg:province":"ON",
    "wof:name":"Meadowvale Pharmacy Ltd",
    "wof:placetype":"venue"
},
  "geometry": {"coordinates":[-79.765816,43.584099],"type":"Point"}
}