{
  "type": "Feature",
  "properties": {
    "addr:full":"7083 Rue Jarry E Anjou QC H1J 1G3",
    "addr:housenumber":"7083",
    "addr:postcode":"h1j 1g3",
    "addr:street":"Rue Jarry E",
    "iso:country":"CA",
    "sg:address":"7083 Rue Jarry E",
    "sg:city":"Anjou",
    "sg:classifiers":[
        {
            "category":"Education",
            "subcategory":"Dance Studio",
            "type":"Public Place"
        }
    ],
    "sg:phone":"+1 514 354 1783",
    "sg:postcode":"H1J 1G3",
    "sg:province":"QC",
    "sg:tags":[
        "instruction",
        "dancing"
    ],
    "wof:name":"Perfomdanse Gehanne Wakil Enr",
    "wof:placetype":"venue"
},
  "geometry": {"coordinates":[-73.5760192871,45.6015396118],"type":"Point"}
}