{
  "type": "Feature",
  "properties": {
    "iso:country":"CA",
    "sg:address":"1084 Montee Masson",
    "sg:city":"Laval",
    "sg:classifiers":[
        {
            "category":"Wholesale",
            "subcategory":"Non-durable Goods",
            "type":"Manufacturing & Wholesale Goods"
        }
    ],
    "sg:phone":"+1 450 664 0606",
    "sg:postcode":"H7E 4P2",
    "sg:province":"QC",
    "sg:tags":[
        "pet",
        "supply"
    ],
    "wof:name":"Produits Absorbant Canada Inc",
    "wof:placetype":"venue"
},
  "geometry": {"coordinates":[-73.6405792236,45.6299362183],"type":"Point"}
}