{
  "type": "Feature",
  "properties": {
    "addr:full":"Burnaby BC V5G 4L7",
    "addr:postcode":"v5g 4l7",
    "iso:country":"CA",
    "sg:city":"Burnaby",
    "sg:classifiers":[
        {
            "category":"Manufacturing",
            "subcategory":"Tools & Machinery",
            "type":"Manufacturing & Wholesale Goods"
        }
    ],
    "sg:phone":"+1 604 451 5170",
    "sg:postcode":"V5G 4L7",
    "sg:province":"BC",
    "sg:tags":[
        "lamp",
        "lighting"
    ],
    "wof:name":"Duro-Test Canada Inc",
    "wof:placetype":"venue"
},
  "geometry": {"coordinates":[-123.00700399999999,49.256191],"type":"Point"}
}