{
  "type": "Feature",
  "properties": {
    "addr:full":"328 Urquhart Ave Moncton NB E1H 2R6",
    "addr:housenumber":"328",
    "addr:postcode":"e1h 2r6",
    "addr:street":"Urquhart Ave",
    "iso:country":"CA",
    "sg:address":"328 Urquhart Ave",
    "sg:city":"Moncton",
    "sg:classifiers":[
        {
            "category":"Shopping",
            "subcategory":"Hobbies, Toys, & Games",
            "type":"Retail Goods"
        }
    ],
    "sg:phone":"+1 506 859 7598",
    "sg:postcode":"E1H 2R6",
    "sg:province":"NB",
    "sg:tags":[
        "lottery",
        "agent",
        "supply"
    ],
    "wof:name":"Spielo Gaming Intl",
    "wof:placetype":"venue"
},
  "geometry": {"coordinates":[-64.744484,46.131748],"type":"Point"}
}