{
  "type": "Feature",
  "properties": {
    "addr:full":"Nanaimo BC V9R 5E2",
    "addr:postcode":"v9r 5e2",
    "iso:country":"CA",
    "sg:city":"Nanaimo",
    "sg:classifiers":[
        {
            "category":"Shopping",
            "subcategory":"Shoes",
            "type":"Retail Goods"
        }
    ],
    "sg:phone":"+1 250 754 9206",
    "sg:postcode":"V9R 5E2",
    "sg:province":"BC",
    "wof:name":"Harbour Shoes",
    "wof:placetype":"venue"
},
  "geometry": {"coordinates":[-123.934944,49.164093],"type":"Point"}
}