{
  "type": "Feature",
  "properties": {
    "addr:full":"Etobicoke ON M9W 4W4",
    "addr:postcode":"m9w 4w4",
    "iso:country":"CA",
    "sg:city":"Etobicoke",
    "sg:classifiers":[
        {
            "category":"Wholesale",
            "subcategory":"Durable Goods & Equipment",
            "type":"Manufacturing & Wholesale Goods"
        }
    ],
    "sg:phone":"+1 416 748 8455",
    "sg:postcode":"M9W 4W4",
    "sg:province":"ON",
    "sg:tags":[
        "room",
        "drafting"
    ],
    "wof:name":"Ram Imaging Products Inc",
    "wof:placetype":"venue"
},
  "geometry": {"coordinates":[-79.57337200000001,43.696651],"type":"Point"}
}