{
  "type": "Feature",
  "properties": {
    "addr:full":"Brandon MB R7A 0M6",
    "addr:postcode":"r7a 0m6",
    "iso:country":"CA",
    "sg:city":"Brandon",
    "sg:classifiers":[
        {
            "category":"Shopping",
            "subcategory":"Florist",
            "type":"Retail Goods"
        }
    ],
    "sg:phone":"+1 204 727 6666",
    "sg:postcode":"R7A 0M6",
    "sg:province":"MB",
    "wof:name":"Dilley's Florists",
    "wof:placetype":"venue"
},
  "geometry": {"coordinates":[-99.958443,49.848335],"type":"Point"}
}