{
  "type": "Feature",
  "properties": {
    "iso:country":"CA",
    "sg:address":"375 3 St W",
    "sg:city":"Drumheller",
    "sg:classifiers":[
        {
            "category":"Government",
            "subcategory":"Office",
            "type":"Public Place"
        }
    ],
    "sg:phone":"+1 403 823 4111",
    "sg:postcode":"T0J 0Y0",
    "sg:province":"AB",
    "wof:name":"Farm Credit Corp",
    "wof:placetype":"venue"
},
  "geometry": {"coordinates":[-112.712502,51.463249],"type":"Point"}
}