{
  "type": "Feature",
  "properties": {
    "addr:full":"8728 Aisne St Vancouver BC V6P 6G7",
    "addr:housenumber":"8728",
    "addr:postcode":"v6p 6g7",
    "addr:street":"Aisne St",
    "iso:country":"CA",
    "sg:address":"8728 Aisne St",
    "sg:city":"Vancouver",
    "sg:classifiers":[
        {
            "category":"Retail",
            "subcategory":"Auto Repair",
            "type":"Services"
        }
    ],
    "sg:phone":"+1 604 324 2310",
    "sg:postcode":"V6P 6G7",
    "sg:province":"BC",
    "sg:tags":[
        "repairing",
        "automobile"
    ],
    "wof:name":"Dave's Auto Repair",
    "wof:placetype":"venue"
},
  "geometry": {"coordinates":[-123.122101,49.207428],"type":"Point"}
}