{
  "type": "Feature",
  "properties": {
    "addr:full":"Saint-Bernard QC G0S 2G0",
    "addr:postcode":"g0s 2g0",
    "iso:country":"CA",
    "sg:city":"Saint-Bernard",
    "sg:classifiers":[
        {
            "category":"Wholesale",
            "subcategory":"Machinery & Supplies",
            "type":"Manufacturing & Wholesale Goods"
        }
    ],
    "sg:phone":"+1 418 475 6601",
    "sg:postcode":"G0S 2G0",
    "sg:province":"QC",
    "sg:tags":[
        "equipment",
        "mill"
    ],
    "wof:name":"Aliments Breton Inc",
    "wof:placetype":"venue"
},
  "geometry": {"coordinates":[-71.139038,46.496735],"type":"Point"}
}