{
  "type": "Feature",
  "properties": {
    "addr:full":"241 Leigh Rd Kamloops BC V2B 2L7",
    "addr:housenumber":"241",
    "addr:postcode":"bc v2b 2l7",
    "addr:street":"Leigh Rd",
    "iso:country":"CA",
    "sg:address":"241 Leigh Rd",
    "sg:city":"Kamloops",
    "sg:classifiers":[
        {
            "category":"Home & Garden",
            "subcategory":"Building Materials",
            "type":"Retail Goods"
        }
    ],
    "sg:phone":"+1 250 376 2388",
    "sg:postcode":"V2B 2L7",
    "sg:province":"BC",
    "sg:tags":[
        "glass",
        "window",
        "plate"
    ],
    "wof:name":"Larry's Mobile Auto Glass",
    "wof:placetype":"venue"
},
  "geometry": {"coordinates":[-120.349777,50.686771],"type":"Point"}
}