{
  "type": "Feature",
  "properties": {
    "addr:full":"560 Rue DE L'Aeroport Saint-Honore-DE-Chicoutimi QC G0V 1L0",
    "addr:housenumber":"560",
    "addr:postcode":"g0v 1l0",
    "addr:street":"Rue De L'Aeroport Saint-Honore-De-Chicoutimi",
    "iso:country":"CA",
    "sg:address":"560 Rue DE L'Aeroport",
    "sg:city":"Saint-Honore-DE-Chicoutimi",
    "sg:classifiers":[
        {
            "category":"Education",
            "subcategory":"School",
            "type":"Public Place"
        }
    ],
    "sg:phone":"+1 418 673 6411",
    "sg:postcode":"G0V 1L0",
    "sg:province":"QC",
    "wof:name":"Ecole Jean-Fortin",
    "wof:placetype":"venue"
},
  "geometry": {"coordinates":[-71.1109466553,48.3475990295],"type":"Point"}
}