{
  "type": "Feature",
  "properties": {
    "iso:country":"CA",
    "sg:address":"8575 East Bay Hwy",
    "sg:city":"Big Pond Centre",
    "sg:classifiers":[
        {
            "category":"Organizations",
            "subcategory":"Professional Association",
            "type":"Services"
        }
    ],
    "sg:phone":"+1 902 828 2086",
    "sg:postcode":"B1J 1Z7",
    "sg:province":"NS",
    "wof:name":"Atlantic Marine Trades Assoc",
    "wof:placetype":"venue"
},
  "geometry": {"coordinates":[-60.566998,45.892838],"type":"Point"}
}