{
  "type": "Feature",
  "properties": {
    "addr:full":"702 Bronte Rd Oakville ON L6L 6R9",
    "addr:housenumber":"702",
    "addr:postcode":"l6l 6r9",
    "addr:street":"Bronte Rd",
    "iso:country":"CA",
    "sg:address":"702 Bronte Rd",
    "sg:city":"Oakville",
    "sg:classifiers":[
        {
            "category":"Wholesale",
            "subcategory":"Auto Parts",
            "type":"Manufacturing & Wholesale Goods"
        }
    ],
    "sg:phone":"+1 905 827 8015",
    "sg:postcode":"L6L 6R9",
    "sg:province":"ON",
    "sg:tags":[
        "automobile",
        "rebuilt"
    ],
    "wof:name":"B & D Auto Recycling",
    "wof:placetype":"venue"
},
  "geometry": {"coordinates":[-79.7350769043,43.4056892395],"type":"Point"}
}