{
  "type": "Feature",
  "properties": {
    "addr:full":"10725 Rue Verville Montreal QC H3L 3G1",
    "addr:housenumber":"10725",
    "addr:postcode":"h3l 3g1",
    "addr:street":"Rue Verville",
    "iso:country":"CA",
    "sg:address":"10725 Rue Verville",
    "sg:city":"Montreal",
    "sg:classifiers":[
        {
            "category":"Organizations",
            "subcategory":"Professional Association",
            "type":"Services"
        }
    ],
    "sg:phone":"+1 514 332 4126",
    "sg:postcode":"H3L 3G1",
    "sg:province":"QC",
    "wof:name":"Association Culturelle TX",
    "wof:placetype":"venue"
},
  "geometry": {"coordinates":[-73.674744,45.545406],"type":"Point"}
}