{
  "type": "Feature",
  "properties": {
    "addr:full":"360 Bayly St W #2 Ajax ON L1S 1P1",
    "addr:housenumber":"360",
    "addr:postcode":"l1s 1p1",
    "addr:street":"Bayly St W # 2",
    "iso:country":"CA",
    "sg:address":"360 Bayly St W #2",
    "sg:city":"Ajax",
    "sg:classifiers":[
        {
            "category":"Health Services",
            "subcategory":"Health Practitioner",
            "type":"Services"
        }
    ],
    "sg:phone":"+1 905 426 8503",
    "sg:postcode":"L1S 1P1",
    "sg:province":"ON",
    "sg:tags":[
        "acupuncture"
    ],
    "wof:name":"Phillips, Brian",
    "wof:placetype":"venue"
},
  "geometry": {"coordinates":[-79.0316085815,43.8411865234],"type":"Point"}
}