{
  "type": "Feature",
  "properties": {
    "addr:full":"700 24th Ave N Cranbrook BC V1C 5P6",
    "addr:housenumber":"700",
    "addr:postcode":"v1c 5p6",
    "addr:street":"24Th Ave N",
    "iso:country":"CA",
    "sg:address":"700 24th Ave N",
    "sg:city":"Cranbrook",
    "sg:classifiers":[
        {
            "category":"Education",
            "subcategory":"School",
            "type":"Public Place"
        }
    ],
    "sg:phone":"+1 250 426 3352",
    "sg:postcode":"V1C 5P6",
    "sg:province":"BC",
    "wof:name":"Steeples Elementary School",
    "wof:placetype":"venue"
},
  "geometry": {"coordinates":[-115.74781,49.518314],"type":"Point"}
}