{
  "type": "Feature",
  "properties": {
    "addr:full":"180 Montee DE Liesse Saint-Laurent QC H4T 1N7",
    "addr:housenumber":"180",
    "addr:postcode":"h4t 1n7",
    "addr:street":"Montee De Liesse",
    "iso:country":"CA",
    "sg:address":"180 Montee DE Liesse",
    "sg:city":"Saint-Laurent",
    "sg:classifiers":[
        {
            "category":"Building & Trades",
            "subcategory":"Cleaning & Sanitation",
            "type":"Services"
        }
    ],
    "sg:phone":"+1 514 398 9705",
    "sg:postcode":"H4T 1N7",
    "sg:province":"QC",
    "sg:tags":[
        "conditioning",
        "air",
        "janitor",
        "system",
        "contractor"
    ],
    "wof:name":"Empire Maintenance Industries",
    "wof:placetype":"venue"
},
  "geometry": {"coordinates":[-73.702263,45.475994],"type":"Point"}
}