{
  "type": "Feature",
  "properties": {
    "iso:country":"CA",
    "sg:address":"8234 Rue Saint-Denis",
    "sg:city":"Montreal",
    "sg:classifiers":[
        {
            "category":"Professional",
            "subcategory":"Accounting & Tax Preparation",
            "type":"Services"
        }
    ],
    "sg:phone":"+1 514 389 8282",
    "sg:postcode":"H2P 2G6",
    "sg:province":"QC",
    "sg:tags":[
        "accountant"
    ],
    "wof:name":"Simpson Girardrn",
    "wof:placetype":"venue"
},
  "geometry": {"coordinates":[-73.631271,45.543049],"type":"Point"}
}