{
  "type": "Feature",
  "properties": {
    "addr:full":"3810 Parkhill St SW Calgary AB T2S 2Z6",
    "addr:housenumber":"3810",
    "addr:postcode":"t2s 2z6",
    "addr:street":"Parkhill St Sw",
    "iso:country":"CA",
    "sg:address":"3810 Parkhill St SW",
    "sg:city":"Calgary",
    "sg:classifiers":[
        {
            "category":"Banks & Credit Unions",
            "subcategory":"Bank",
            "type":"Services"
        }
    ],
    "sg:phone":"+1 403 214 0073",
    "sg:postcode":"T2S 2Z6",
    "sg:province":"AB",
    "sg:tags":[
        "loan",
        "real estate"
    ],
    "wof:name":"Stephenson Mortgage Inc",
    "wof:placetype":"venue"
},
  "geometry": {"coordinates":[-114.06409499999999,51.021],"type":"Point"}
}