{
  "type": "Feature",
  "properties": {
    "addr:full":"167 Templegreen Rd NE Calgary AB T1Y 6G3",
    "addr:housenumber":"167",
    "addr:postcode":"t1y 6g3",
    "addr:street":"Templegreen Rd Ne",
    "iso:country":"CA",
    "sg:address":"167 Templegreen Rd NE",
    "sg:city":"Calgary",
    "sg:classifiers":[
        {
            "category":"Organizations",
            "subcategory":"Professional Association",
            "type":"Services"
        }
    ],
    "sg:phone":"+1 403 280 5466",
    "sg:postcode":"T1Y 6G3",
    "sg:province":"AB",
    "wof:name":"Temple Community Assn",
    "wof:placetype":"venue"
},
  "geometry": {"coordinates":[-113.94412199999999,51.08778],"type":"Point"}
}