{
  "type": "Feature",
  "properties": {
    "addr:full":"544 Du Tour-Du-Lac Ch Cheneville QC J0V 1E0",
    "addr:housenumber":"544",
    "addr:postcode":"j0v 1e0",
    "addr:street":"Du Tour-Du-Lac;Cheneville",
    "iso:country":"CA",
    "sg:address":"544 Du Tour-Du-Lac Ch",
    "sg:city":"Cheneville",
    "sg:classifiers":[
        {
            "category":"Travel",
            "subcategory":"Hotels & Motels",
            "type":"Entertainment"
        }
    ],
    "sg:phone":"+1 819 428 2020",
    "sg:postcode":"J0V 1E0",
    "sg:province":"QC",
    "sg:tags":[
        "inn"
    ],
    "wof:name":"Auberge Evasion",
    "wof:placetype":"venue"
},
  "geometry": {"coordinates":[-75.0552825928,45.8866081238],"type":"Point"}
}