{
  "type": "Feature",
  "properties": {
    "addr:full":"75 Watline Ave # 103 Mississauga ON L4Z 3E5",
    "addr:housenumber":"75",
    "addr:postcode":"l4z 3e5",
    "addr:street":"Watline Ave # 103",
    "iso:country":"CA",
    "sg:address":"75 Watline Ave # 103",
    "sg:city":"Mississauga",
    "sg:classifiers":[
        {
            "category":"Organizations",
            "subcategory":"Non-profit Organization",
            "type":"Services"
        }
    ],
    "sg:phone":"+1 905 890 1724",
    "sg:postcode":"L4Z 3E5",
    "sg:province":"ON",
    "sg:tags":[
        "information",
        "referral"
    ],
    "wof:name":"Coordinated Information Peel",
    "wof:placetype":"venue"
},
  "geometry": {"coordinates":[-79.6707458496,43.6224250793],"type":"Point"}
}