{
  "type": "Feature",
  "properties": {
    "addr:full":"20 Gissing Dr SW Calgary AB T3E 4V7",
    "addr:housenumber":"20",
    "addr:postcode":"t3e 4v7",
    "addr:street":"Gissing Dr Sw",
    "iso:country":"CA",
    "sg:address":"20 Gissing Dr SW",
    "sg:city":"Calgary",
    "sg:classifiers":[
        {
            "category":"Banks & Credit Unions",
            "subcategory":"Investment Brokerage",
            "type":"Services"
        }
    ],
    "sg:phone":"+1 403 246 7475",
    "sg:postcode":"T3E 4V7",
    "sg:province":"AB",
    "sg:tags":[
        "consultant",
        "planning",
        "financial"
    ],
    "wof:name":"Lenzburg Capital Corp",
    "wof:placetype":"venue"
},
  "geometry": {"coordinates":[-114.14200599999999,51.016541],"type":"Point"}
}