{
  "type": "Feature",
  "properties": {
    "addr:full":"104 Kimberley Ave Bracebridge ON P1L 1Z8",
    "addr:housenumber":"104",
    "addr:postcode":"p1l 1z8",
    "addr:street":"Kimberley Ave",
    "iso:country":"CA",
    "sg:address":"104 Kimberley Ave",
    "sg:city":"Bracebridge",
    "sg:classifiers":[
        {
            "category":"Professional",
            "subcategory":"Management & Consulting",
            "type":"Services"
        }
    ],
    "sg:phone":"+1 705 645 1556",
    "sg:postcode":"P1L 1Z8",
    "sg:province":"ON",
    "sg:tags":[
        "town",
        "city",
        "regional",
        "planner"
    ],
    "wof:name":"Planscape",
    "wof:placetype":"venue"
},
  "geometry": {"coordinates":[-79.313591,45.041191],"type":"Point"}
}