{
  "type": "Feature",
  "properties": {
    "addr:full":"7 DE LA Polyvalente Gracefield QC J0X 1W0",
    "addr:housenumber":"7",
    "addr:postcode":"j0x 1w0",
    "addr:street":"De La Polyvalente",
    "iso:country":"CA",
    "sg:address":"7 DE LA Polyvalente",
    "sg:city":"Gracefield",
    "sg:classifiers":[
        {
            "category":"Government",
            "subcategory":"Office",
            "type":"Public Place"
        }
    ],
    "sg:phone":"+1 819 463 3241",
    "sg:postcode":"J0X 1W0",
    "sg:province":"QC",
    "sg:tags":[
        "village"
    ],
    "wof:name":"Vallee DE LA Gatineau",
    "wof:placetype":"venue"
},
  "geometry": {"coordinates":[-76.0536270142,46.0905761719],"type":"Point"}
}