{
  "type": "Feature",
  "properties": {
    "addr:full":"888 Guelph St Kitchener ON N2H 5Z6",
    "addr:housenumber":"888",
    "addr:postcode":"n2h 5z6",
    "addr:street":"Guelph St",
    "iso:country":"CA",
    "sg:address":"888 Guelph St",
    "sg:city":"Kitchener",
    "sg:classifiers":[
        {
            "category":"Home & Garden",
            "subcategory":"Building Materials",
            "type":"Retail Goods"
        }
    ],
    "sg:phone":"+1 519 579 3810",
    "sg:postcode":"N2H 5Z6",
    "sg:province":"ON",
    "sg:tags":[
        "windows"
    ],
    "wof:name":"Golden Windows Ltd",
    "wof:placetype":"venue"
},
  "geometry": {"coordinates":[-80.47877502439999,43.4670372009],"type":"Point"}
}