{
  "type": "Feature",
  "properties": {
    "addr:full":"429 Weldrick Rd E Richmond Hill ON L4B 2M5",
    "addr:housenumber":"429",
    "addr:postcode":"l4b 2m5",
    "addr:street":"Weldrick Rd E",
    "iso:country":"CA",
    "sg:address":"429 Weldrick Rd E",
    "sg:city":"Richmond Hill",
    "sg:classifiers":[
        {
            "category":"Professional",
            "type":"Services"
        }
    ],
    "sg:phone":"+1 905 737 1665",
    "sg:postcode":"L4B 2M5",
    "sg:province":"ON",
    "sg:tags":[
        "woodworking",
        "establishment",
        "machinery"
    ],
    "wof:name":"Besco Machinery Ltd",
    "wof:placetype":"venue"
},
  "geometry": {"coordinates":[-79.408203125,43.8696403503],"type":"Point"}
}