{
  "type": "Feature",
  "properties": {
    "addr:full":"73 Milltown Blvd St Stephen NB E3L 1G5",
    "addr:housenumber":"73",
    "addr:postcode":"e3l 1g5",
    "addr:street":"Milltown Blvd",
    "iso:country":"CA",
    "sg:address":"73 Milltown Blvd",
    "sg:city":"St Stephen",
    "sg:classifiers":[
        {
            "category":"Restaurant",
            "type":"Food & Drink"
        }
    ],
    "sg:phone":"+1 506 466 3027",
    "sg:postcode":"E3L 1G5",
    "sg:province":"NB",
    "wof:name":"St Jerome's Family Grill",
    "wof:placetype":"venue"
},
  "geometry": {"coordinates":[-67.2781219482,45.1927108765],"type":"Point"}
}