{
  "type": "Feature",
  "properties": {
    "addr:full":"83 Main St Thedford ON N0M 2N0",
    "addr:housenumber":"83",
    "addr:postcode":"n0m 2n0",
    "addr:street":"Main St",
    "iso:country":"CA",
    "sg:address":"83 Main St",
    "sg:city":"Thedford",
    "sg:classifiers":[
        {
            "category":"Banks & Credit Unions",
            "subcategory":"Bank",
            "type":"Services"
        }
    ],
    "sg:phone":"+1 519 296 4968",
    "sg:postcode":"N0M 2N0",
    "sg:province":"ON",
    "wof:name":"Cibc",
    "wof:placetype":"venue"
},
  "geometry": {"coordinates":[-81.855789,43.163597],"type":"Point"}
}