{
  "type": "Feature",
  "properties": {
    "addr:full":"303 Willan Lane Leamington ON N8H 3V6",
    "addr:housenumber":"303",
    "addr:postcode":"n8h 3v6",
    "addr:street":"Willan Lane",
    "iso:country":"CA",
    "sg:address":"303 Willan Lane",
    "sg:city":"Leamington",
    "sg:classifiers":[
        {
            "category":"Building & Trades",
            "subcategory":"Electrical",
            "type":"Services"
        }
    ],
    "sg:phone":"+1 519 326 4511",
    "sg:postcode":"N8H 3V6",
    "sg:province":"ON",
    "sg:tags":[
        "electric",
        "contractor"
    ],
    "wof:name":"Greene Electrical Contracting",
    "wof:placetype":"venue"
},
  "geometry": {"coordinates":[-82.579132,42.058739],"type":"Point"}
}