{
  "type": "Feature",
  "properties": {
    "addr:full":"St Thomas ON N5P 3S9",
    "addr:postcode":"n5p 3s9",
    "iso:country":"CA",
    "sg:city":"St Thomas",
    "sg:classifiers":[
        {
            "category":"Manufacturing",
            "subcategory":"Printing",
            "type":"Manufacturing & Wholesale Goods"
        }
    ],
    "sg:phone":"+1 519 775 2230",
    "sg:postcode":"N5P 3S9",
    "sg:province":"ON",
    "sg:tags":[
        "screen",
        "sign"
    ],
    "wof:name":"Mc Bain Signs & Graphic Design",
    "wof:placetype":"venue"
},
  "geometry": {"coordinates":[-77.34586334230001,44.3887672424],"type":"Point"}
}