{
  "type": "Feature",
  "properties": {
    "iso:country":"CA",
    "sg:city":"Smooth Rock Falls",
    "sg:classifiers":[
        {
            "category":"Shopping",
            "type":"Retail Goods"
        }
    ],
    "sg:phone":"+1 705 338 2356",
    "sg:postcode":"P0L 2B0",
    "sg:province":"ON",
    "sg:tags":[
        "cosmetic",
        "perfume"
    ],
    "wof:name":"U & I",
    "wof:placetype":"venue"
},
  "geometry": {"coordinates":[-81.6198348999,49.2761535645],"type":"Point"}
}