{
  "type": "Feature",
  "properties": {
    "addr:full":"130 King St London ON N6A 1C5",
    "addr:housenumber":"130",
    "addr:postcode":"n6a 1c5",
    "addr:street":"King St",
    "iso:country":"CA",
    "sg:address":"130 King St",
    "sg:city":"London",
    "sg:classifiers":[
        {
            "category":"Food & Beverages",
            "subcategory":"Specialty",
            "type":"Retail Goods"
        }
    ],
    "sg:phone":"+1 519 663 0237",
    "sg:postcode":"N6A 1C5",
    "sg:province":"ON",
    "sg:tags":[
        "tea",
        "coffee"
    ],
    "wof:name":"Hasbeans",
    "wof:placetype":"venue"
},
  "geometry": {"coordinates":[-81.25057983400001,42.9822425842],"type":"Point"}
}