{
  "type": "Feature",
  "properties": {
    "addr:full":"250 Brackley Point Rd Charlottetown PE C1A 6Y9",
    "addr:housenumber":"250",
    "addr:postcode":"c1a 6y9",
    "addr:street":"Brackley Point Rd",
    "iso:country":"CA",
    "sg:address":"250 Brackley Point Rd",
    "sg:city":"Charlottetown",
    "sg:classifiers":[
        {
            "category":"Building & Trades",
            "subcategory":"Equipment Rental",
            "type":"Services"
        }
    ],
    "sg:phone":"+1 902 566 4488",
    "sg:postcode":"C1A 6Y9",
    "sg:province":"PE",
    "sg:tags":[
        "charter",
        "leasing",
        "courier",
        "company",
        "air",
        "aircraft",
        "airline"
    ],
    "wof:name":"Prince Edward Air Ltd",
    "wof:placetype":"venue"
},
  "geometry": {"coordinates":[-63.131652832,46.276889801],"type":"Point"}
}