{
  "type": "Feature",
  "properties": {
    "addr:full":"124 Charlesworth Ave Cochrane AB T4C 2B7",
    "addr:housenumber":"124",
    "addr:postcode":"t4c 2b7",
    "addr:street":"Charlesworth Ave",
    "iso:country":"CA",
    "sg:address":"124 Charlesworth Ave",
    "sg:city":"Cochrane",
    "sg:classifiers":[
        {
            "category":"Autos & Motor Vehicles",
            "subcategory":"Auto Supplies",
            "type":"Retail Goods"
        }
    ],
    "sg:phone":"+1 403 932 2225",
    "sg:postcode":"T4C 2B7",
    "sg:province":"AB",
    "sg:tags":[
        "automobile",
        "parts"
    ],
    "wof:name":"Town & Country Auto Parts",
    "wof:placetype":"venue"
},
  "geometry": {"coordinates":[-114.465446472,51.1866722107],"type":"Point"}
}