{
  "type": "Feature",
  "properties": {
    "addr:full":"Fort Mcmurray AB T9H 4A4",
    "addr:postcode":"t9h 4a4",
    "iso:country":"CA",
    "sg:city":"Fort Mcmurray",
    "sg:classifiers":[
        {
            "category":"Shopping",
            "subcategory":"Hobbies, Toys, & Games",
            "type":"Retail Goods"
        }
    ],
    "sg:phone":"+1 780 714 2232",
    "sg:postcode":"T9H 4A4",
    "sg:province":"AB",
    "wof:name":"Kottage Toys Ltd",
    "wof:placetype":"venue"
},
  "geometry": {"coordinates":[-111.38537599999999,56.728199],"type":"Point"}
}