{
  "type": "Feature",
  "properties": {
    "addr:full":"5160 Explorer Dr # 38R Mississauga ON L4W 4T7",
    "addr:housenumber":"5160",
    "addr:postcode":"l4w 4t7",
    "addr:street":"Explorer Dr # 38R",
    "iso:country":"CA",
    "sg:address":"5160 Explorer Dr # 38R",
    "sg:city":"Mississauga",
    "sg:classifiers":[
        {
            "category":"Shopping",
            "type":"Retail Goods"
        }
    ],
    "sg:phone":"+1 905 206 9220",
    "sg:postcode":"L4W 4T7",
    "sg:province":"ON",
    "sg:tags":[
        "miscellaneous",
        "store"
    ],
    "wof:name":"Dfass Canada CO",
    "wof:placetype":"venue"
},
  "geometry": {"coordinates":[-79.598221,43.66246],"type":"Point"}
}