{
  "type": "Feature",
  "properties": {
    "addr:full":"Smithville ON L0R 2A0",
    "addr:postcode":"l0r 2a0",
    "iso:country":"CA",
    "sg:city":"Smithville",
    "sg:classifiers":[
        {
            "category":"Building & Trades",
            "subcategory":"Construction",
            "type":"Services"
        }
    ],
    "sg:phone":"+1 905 957 3370",
    "sg:postcode":"L0R 2A0",
    "sg:province":"ON",
    "sg:tags":[
        "water",
        "well",
        "drilling"
    ],
    "wof:name":"Donald Merrit Water Well Drill",
    "wof:placetype":"venue"
},
  "geometry": {"coordinates":[-79.54889678959999,43.0939216614],"type":"Point"}
}