{
  "type": "Feature",
  "properties": {
    "iso:country":"CA",
    "sg:address":"130 Rue Saint-Jacques S",
    "sg:city":"Coaticook",
    "sg:classifiers":[
        {
            "category":"Manufacturing",
            "subcategory":"Metals",
            "type":"Manufacturing & Wholesale Goods"
        }
    ],
    "sg:phone":"+1 819 849 4251",
    "sg:postcode":"J1A 2N8",
    "sg:province":"QC",
    "sg:tags":[
        "shelter",
        "garage",
        "temporary"
    ],
    "wof:name":"L'Hetero Piscine",
    "wof:placetype":"venue"
},
  "geometry": {"coordinates":[-71.7971038818,45.1304855347],"type":"Point"}
}