{
  "type": "Feature",
  "properties": {
    "addr:full":"739 Ossington Ave Toronto ON M6G 3T8",
    "addr:housenumber":"739",
    "addr:postcode":"m6g 3t8",
    "addr:street":"Ossington Ave",
    "iso:country":"CA",
    "sg:address":"739 Ossington Ave",
    "sg:city":"Toronto",
    "sg:classifiers":[
        {
            "category":"Shopping",
            "type":"Retail Goods"
        }
    ],
    "sg:phone":"+1 416 537 1304",
    "sg:postcode":"M6G 3T8",
    "sg:province":"ON",
    "sg:tags":[
        "pet",
        "food",
        "supply"
    ],
    "wof:name":"Ossington Pet Food",
    "wof:placetype":"venue"
},
  "geometry": {"coordinates":[-79.425583,43.662281],"type":"Point"}
}