{
  "type": "Feature",
  "properties": {
    "addr:full":"341 Trunk Rd Sault Ste Marie ON P6A 3S9",
    "addr:housenumber":"341",
    "addr:postcode":"p6a 3s9",
    "addr:street":"Trunk Rd",
    "iso:country":"CA",
    "sg:address":"341 Trunk Rd",
    "sg:city":"Sault Ste Marie",
    "sg:classifiers":[
        {
            "category":"Banks & Credit Unions",
            "subcategory":"Bank",
            "type":"Services"
        }
    ],
    "sg:phone":"+1 705 949 5710",
    "sg:postcode":"P6A 3S9",
    "sg:province":"ON",
    "sg:tags":[
        "loan",
        "real estate"
    ],
    "wof:name":"Citi Financial Canada Inc",
    "wof:placetype":"venue"
},
  "geometry": {"coordinates":[-84.28610992430001,46.5162200928],"type":"Point"}
}