{
  "type": "Feature",
  "properties": {
    "addr:full":"1037 Lorne St Sudbury ON P3C 4S4",
    "addr:housenumber":"1037",
    "addr:postcode":"p3c 4s4",
    "addr:street":"Lorne St",
    "iso:country":"CA",
    "sg:address":"1037 Lorne St",
    "sg:city":"Sudbury",
    "sg:classifiers":[
        {
            "category":"Restaurant",
            "type":"Food & Drink"
        }
    ],
    "sg:phone":"+1 705 673 1585",
    "sg:postcode":"P3C 4S4",
    "sg:province":"ON",
    "wof:name":"Lichee Garden Tavern",
    "wof:placetype":"venue"
},
  "geometry": {"coordinates":[-81.025772,46.473927],"type":"Point"}
}