{
  "type": "Feature",
  "properties": {
    "addr:full":"236 Toryork Dr North York ON M9L 1Y1",
    "addr:housenumber":"236",
    "addr:postcode":"m9l 1y1",
    "addr:street":"Toryork Dr",
    "iso:country":"CA",
    "sg:address":"236 Toryork Dr",
    "sg:city":"North York",
    "sg:classifiers":[
        {
            "category":"Home & Garden",
            "subcategory":"Building Materials",
            "type":"Retail Goods"
        }
    ],
    "sg:phone":"+1 416 748 7027",
    "sg:postcode":"M9L 1Y1",
    "sg:province":"ON",
    "sg:tags":[
        "windows"
    ],
    "wof:name":"Varga Windows",
    "wof:placetype":"venue"
},
  "geometry": {"coordinates":[-79.561554,43.761581],"type":"Point"}
}