{
  "type": "Feature",
  "properties": {
    "addr:full":"222 Main St W Hamilton ON L8P 1J3",
    "addr:housenumber":"222",
    "addr:postcode":"l8p 1j3",
    "addr:street":"Main St W",
    "iso:country":"CA",
    "sg:address":"222 Main St W",
    "sg:city":"Hamilton",
    "sg:classifiers":[
        {
            "category":"Shopping",
            "subcategory":"Used Merchandise",
            "type":"Retail Goods"
        }
    ],
    "sg:phone":"+1 905 529 7173",
    "sg:postcode":"L8P 1J3",
    "sg:province":"ON",
    "sg:tags":[
        "interior",
        "consultant",
        "design",
        "decorator"
    ],
    "wof:name":"Villa",
    "wof:placetype":"venue"
},
  "geometry": {"coordinates":[-79.878952,43.25774],"type":"Point"}
}