{
  "type": "Feature",
  "properties": {
    "iso:country":"CA",
    "sg:address":"2856 Dundas St W",
    "sg:city":"Toronto",
    "sg:classifiers":[
        {
            "category":"Restaurant",
            "type":"Food & Drink"
        }
    ],
    "sg:phone":"+1 416 762 9849",
    "sg:postcode":"M6P 1Y8",
    "sg:province":"ON",
    "sg:tags":[
        "sandwich"
    ],
    "wof:name":"Super Submarine",
    "wof:placetype":"venue"
},
  "geometry": {"coordinates":[-79.46472930909999,43.6654968262],"type":"Point"}
}