{
  "type": "Feature",
  "properties": {
    "addr:full":"15 Memorial Ave Elmira ON N3B 2R1",
    "addr:housenumber":"15",
    "addr:postcode":"n3b 2r1",
    "addr:street":"Memorial Ave",
    "iso:country":"CA",
    "sg:address":"15 Memorial Ave",
    "sg:city":"Elmira",
    "sg:classifiers":[
        {
            "category":"Health Services",
            "subcategory":"Doctor",
            "type":"Services"
        }
    ],
    "sg:phone":"+1 519 669 1535",
    "sg:postcode":"N3B 2R1",
    "sg:province":"ON",
    "sg:tags":[
        "clinic"
    ],
    "wof:name":"Elmira Denture Clinic",
    "wof:placetype":"venue"
},
  "geometry": {"coordinates":[-80.557419,43.598278],"type":"Point"}
}