{
  "type": "Feature",
  "properties": {
    "addr:full":"466 Main St Lewisporte NL A0G 3A0",
    "addr:housenumber":"466",
    "addr:postcode":"a0g 3a0",
    "addr:street":"Main St",
    "iso:country":"CA",
    "sg:address":"466 Main St",
    "sg:city":"Lewisporte",
    "sg:classifiers":[
        {
            "category":"Restaurant",
            "type":"Food & Drink"
        }
    ],
    "sg:phone":"+1 709 535 3100",
    "sg:postcode":"A0G 3A0",
    "sg:province":"NL",
    "wof:name":"Mc Donald's",
    "wof:placetype":"venue"
},
  "geometry": {"coordinates":[-55.059937,49.241798],"type":"Point"}
}