{
  "type": "Feature",
  "properties": {
    "iso:country":"CA",
    "sg:address":"744 Railway Ave W",
    "sg:city":"Nipawin",
    "sg:classifiers":[
        {
            "category":"Retail",
            "subcategory":"Car Wash",
            "type":"Services"
        }
    ],
    "sg:phone":"+1 306 862 4421",
    "sg:postcode":"S0E 1E0",
    "sg:province":"SK",
    "sg:tags":[
        "polishing",
        "washing"
    ],
    "wof:name":"Suds N' Stuff",
    "wof:placetype":"venue"
},
  "geometry": {"coordinates":[-104.02628300000001,53.356743],"type":"Point"}
}