{
  "type": "Feature",
  "properties": {
    "addr:full":"92 Prince William St Saint John NB E2L 2B3",
    "addr:housenumber":"92",
    "addr:postcode":"nb e2l 2b3",
    "addr:street":"Prince William St",
    "iso:country":"CA",
    "sg:address":"92 Prince William St",
    "sg:city":"Saint John",
    "sg:classifiers":[
        {
            "category":"Insurance",
            "subcategory":"Insurance Agent",
            "type":"Services"
        }
    ],
    "sg:phone":"+1 506 634 1282",
    "sg:postcode":"E2L 2B3",
    "sg:province":"NB",
    "wof:name":"Hall & Fairweather Ltd",
    "wof:placetype":"venue"
},
  "geometry": {"coordinates":[-66.061806,45.271824],"type":"Point"}
}