{
  "type": "Feature",
  "properties": {
    "iso:country":"CA",
    "sg:address":"1055 Rue Principale",
    "sg:city":"Saint-Zotique",
    "sg:classifiers":[
        {
            "category":"Personal",
            "subcategory":"Beauty Salon",
            "type":"Services"
        }
    ],
    "sg:phone":"+1 450 267 4545",
    "sg:postcode":"J0P 1Z0",
    "sg:province":"QC",
    "wof:name":"Coiffure Danielle Fortin",
    "wof:placetype":"venue"
},
  "geometry": {"coordinates":[-74.2436904907,45.243850708],"type":"Point"}
}