{
  "type": "Feature",
  "properties": {
    "addr:full":"Grovedale AB T0H 1X0",
    "addr:postcode":"t0h 1x0",
    "iso:country":"CA",
    "sg:city":"Grovedale",
    "sg:classifiers":[
        {
            "category":"Building & Trades",
            "subcategory":"Construction",
            "type":"Services"
        }
    ],
    "sg:phone":"+1 780 539 3583",
    "sg:postcode":"T0H 1X0",
    "sg:province":"AB",
    "sg:tags":[
        "concrete",
        "contractor"
    ],
    "wof:name":"Sunrise Concrete Ltd",
    "wof:placetype":"venue"
},
  "geometry": {"coordinates":[-118.862190247,55.0251312256],"type":"Point"}
}