{
  "type": "Feature",
  "properties": {
    "iso:country":"CA",
    "sg:address":"47 Woodglen Cres SW",
    "sg:city":"Calgary",
    "sg:classifiers":[
        {
            "category":"Health Services",
            "subcategory":"Clinic",
            "type":"Services"
        }
    ],
    "sg:phone":"+1 403 238 4597",
    "sg:postcode":"T2W 4L1",
    "sg:province":"AB",
    "sg:tags":[
        "equipment",
        "therapy",
        "oxygen"
    ],
    "wof:name":"Med Assist Oxygen & Training",
    "wof:placetype":"venue"
},
  "geometry": {"coordinates":[-114.12541961700001,50.9419593811],"type":"Point"}
}