{
  "type": "Feature",
  "properties": {
    "addr:full":"11 Rue Jean-Talon Salaberry-DE-Valleyfield QC J6S 3H5",
    "addr:housenumber":"11",
    "addr:postcode":"j6s 3h5",
    "addr:street":"Rue Jean-Talon",
    "iso:country":"CA",
    "sg:address":"11 Rue Jean-Talon",
    "sg:city":"Salaberry-DE-Valleyfield",
    "sg:classifiers":[
        {
            "category":"Social Services",
            "type":"Services"
        }
    ],
    "sg:phone":"+1 450 373 1217",
    "sg:postcode":"J6S 3H5",
    "sg:province":"QC",
    "sg:tags":[
        "organization",
        "welfare"
    ],
    "wof:name":"Centre Du Partage",
    "wof:placetype":"venue"
},
  "geometry": {"coordinates":[-74.13715362550001,45.2652931213],"type":"Point"}
}