{
  "type": "Feature",
  "properties": {
    "addr:full":"201 Petit Rang Saint-Thomas QC J0K 3L0",
    "addr:housenumber":"201",
    "addr:postcode":"j0k 3l0",
    "addr:street":"Petit Rang",
    "iso:country":"CA",
    "sg:address":"201 Petit Rang",
    "sg:city":"Saint-Thomas",
    "sg:classifiers":[
        {
            "category":"Mining & Drilling",
            "type":"Manufacturing & Wholesale Goods"
        }
    ],
    "sg:phone":"+1 450 759 2777",
    "sg:postcode":"J0K 3L0",
    "sg:province":"QC",
    "sg:tags":[
        "quarry"
    ],
    "wof:name":"Carrieres Pcm",
    "wof:placetype":"venue"
},
  "geometry": {"coordinates":[-73.38464355470001,46.0219345093],"type":"Point"}
}