{
  "type": "Feature",
  "properties": {
    "addr:full":"600 Rue Fraser Saint-Laurent QC H4M 1Z1",
    "addr:housenumber":"600",
    "addr:postcode":"h4m 1z1",
    "addr:street":"Rue Fraser",
    "iso:country":"CA",
    "sg:address":"600 Rue Fraser",
    "sg:city":"Saint-Laurent",
    "sg:classifiers":[
        {
            "category":"Wholesale",
            "subcategory":"Electrical",
            "type":"Manufacturing & Wholesale Goods"
        }
    ],
    "sg:phone":"+1 514 748 8427",
    "sg:postcode":"H4M 1Z1",
    "sg:province":"QC",
    "sg:tags":[
        "control",
        "security",
        "system"
    ],
    "wof:name":"Serabit International",
    "wof:placetype":"venue"
},
  "geometry": {"coordinates":[-73.686164856,45.5001373291],"type":"Point"}
}