{
  "type": "Feature",
  "properties": {
    "addr:full":"358 Albert St N Regina SK S4R 3C1",
    "addr:housenumber":"358",
    "addr:postcode":"s4r 3c1",
    "addr:street":"Albert St N",
    "iso:country":"CA",
    "sg:address":"358 Albert St N",
    "sg:city":"Regina",
    "sg:classifiers":[
        {
            "category":"Shopping",
            "subcategory":"Optical Goods",
            "type":"Retail Goods"
        }
    ],
    "sg:phone":"+1 306 545 2020",
    "sg:postcode":"S4R 3C1",
    "sg:province":"SK",
    "sg:tags":[
        "optician"
    ],
    "wof:name":"Northgate Optical Ltd",
    "wof:placetype":"venue"
},
  "geometry": {"coordinates":[-104.618431,50.481659],"type":"Point"}
}