{
  "type": "Feature",
  "properties": {
    "addr:full":"2001 University Ave E # 104 Waterloo ON N2K 4K4",
    "addr:housenumber":"2001",
    "addr:postcode":"n2k 4k4",
    "addr:street":"University Ave E # 104",
    "iso:country":"CA",
    "sg:address":"2001 University Ave E # 104",
    "sg:city":"Waterloo",
    "sg:classifiers":[
        {
            "category":"Personal",
            "type":"Services"
        }
    ],
    "sg:phone":"+1 519 885 5684",
    "sg:postcode":"N2K 4K4",
    "sg:province":"ON",
    "sg:tags":[
        "physiotherapist",
        "therapist",
        "massage"
    ],
    "wof:name":"Waterloo Sports Medicine Ctr",
    "wof:placetype":"venue"
},
  "geometry": {"coordinates":[-80.5090103149,43.5186195374],"type":"Point"}
}