{
  "type": "Feature",
  "properties": {
    "addr:full":"249 Hwy 2 Brookfield NS B0N 1C0",
    "addr:housenumber":"249",
    "addr:postcode":"b0n 1c0",
    "addr:street":"Hwy 2",
    "iso:country":"CA",
    "sg:address":"249 Hwy 2",
    "sg:city":"Brookfield",
    "sg:classifiers":[
        {
            "category":"Autos & Motor Vehicles",
            "subcategory":"Auto Supplies",
            "type":"Retail Goods"
        }
    ],
    "sg:phone":"+1 902 673 3146",
    "sg:postcode":"B0N 1C0",
    "sg:province":"NS",
    "sg:tags":[
        "automobile",
        "parts"
    ],
    "wof:name":"Dasz Enterprises",
    "wof:placetype":"venue"
},
  "geometry": {"coordinates":[-63.2797775269,45.2546691895],"type":"Point"}
}