{
  "type": "Feature",
  "properties": {
    "iso:country":"CA",
    "sg:address":"3040 Palstan Rd",
    "sg:city":"Mississauga",
    "sg:classifiers":[
        {
            "category":"Health Services",
            "subcategory":"Medical Lab",
            "type":"Services"
        }
    ],
    "sg:phone":"+1 905 279 5612",
    "sg:postcode":"L4Y 2Z6",
    "sg:province":"ON",
    "wof:name":"Magnoli, D R",
    "wof:placetype":"venue"
},
  "geometry": {"coordinates":[-79.59005,43.604729],"type":"Point"}
}