{
  "type": "Feature",
  "properties": {
    "addr:full":"3040 Palstan Rd Mississauga ON L4Y 2Z6",
    "addr:housenumber":"3040",
    "addr:postcode":"l4y 2z6",
    "addr:street":"Palstan Rd",
    "iso:country":"CA",
    "sg:address":"3040 Palstan Rd",
    "sg:city":"Mississauga",
    "sg:classifiers":[
        {
            "category":"Health Services",
            "subcategory":"Medical Lab",
            "type":"Services"
        }
    ],
    "sg:phone":"+1 905 279 5612",
    "sg:postcode":"L4Y 2Z6",
    "sg:province":"ON",
    "wof:name":"Magnoli, D R",
    "wof:placetype":"venue"
},
  "geometry": {"coordinates":[-79.59005000000001,43.604729],"type":"Point"}
}