{
  "type": "Feature",
  "properties": {
    "iso:country":"CA",
    "sg:address":"40 Old Kingston Rd # 108",
    "sg:city":"Ajax",
    "sg:classifiers":[
        {
            "category":"Shopping",
            "subcategory":"Gifts & Souvenirs",
            "type":"Retail Goods"
        }
    ],
    "sg:phone":"+1 905 619 9993",
    "sg:postcode":"L1T 2Z7",
    "sg:province":"ON",
    "sg:tags":[
        "party",
        "supply"
    ],
    "wof:name":"Party Packagers",
    "wof:placetype":"venue"
},
  "geometry": {"coordinates":[-79.057541,43.854546],"type":"Point"}
}