{
  "type": "Feature",
  "properties": {
    "iso:country":"CA",
    "sg:city":"Edmonton",
    "sg:classifiers":[
        {
            "category":"Wholesale",
            "subcategory":"Non-durable Goods",
            "type":"Manufacturing & Wholesale Goods"
        }
    ],
    "sg:phone":"+1 780 413 4124",
    "sg:postcode":"T5S 1K9",
    "sg:province":"AB",
    "sg:tags":[
        "leather",
        "clothes"
    ],
    "wof:name":"Leather Centre",
    "wof:placetype":"venue"
},
  "geometry": {"coordinates":[-113.617736816,53.5469894409],"type":"Point"}
}