{
  "type": "Feature",
  "properties": {
    "addr:full":"Gatineau QC J8V 1E7",
    "addr:postcode":"j8v 1e7",
    "iso:country":"CA",
    "sg:city":"Gatineau",
    "sg:classifiers":[
        {
            "category":"Health Services",
            "subcategory":"Health Practitioner",
            "type":"Services"
        }
    ],
    "sg:phone":"+1 819 246 7277",
    "sg:postcode":"J8V 1E7",
    "sg:province":"QC",
    "sg:tags":[
        "psychotherapist"
    ],
    "wof:name":"Maison Alonzo Wright",
    "wof:placetype":"venue"
},
  "geometry": {"coordinates":[-75.7104873657,45.4278526306],"type":"Point"}
}