{
  "type": "Feature",
  "properties": {
    "addr:full":"5803 90 St NW Edmonton AB T6E 6C2",
    "addr:housenumber":"5803",
    "addr:postcode":"t6e 6c2",
    "addr:street":"90 St Nw",
    "iso:country":"CA",
    "sg:address":"5803 90 St NW",
    "sg:city":"Edmonton",
    "sg:classifiers":[
        {
            "category":"Retail",
            "subcategory":"Auto Repair",
            "type":"Services"
        }
    ],
    "sg:phone":"+1 780 468 5801",
    "sg:postcode":"T6E 6C2",
    "sg:province":"AB",
    "sg:tags":[
        "wheel",
        "alignment",
        "axle"
    ],
    "wof:name":"Ideal Alignment",
    "wof:placetype":"venue"
},
  "geometry": {"coordinates":[-113.465576172,53.4941291809],"type":"Point"}
}