{
  "type": "Feature",
  "properties": {
    "addr:full":"1705 Ranchlands Way NW Calgary AB T3G 3S6",
    "addr:housenumber":"1705",
    "addr:postcode":"t3g 3s6",
    "addr:street":"Ranchlands Way Nw",
    "iso:country":"CA",
    "sg:address":"1705 Ranchlands Way NW",
    "sg:city":"Calgary",
    "sg:classifiers":[
        {
            "category":"Organizations",
            "subcategory":"Religious Organization",
            "type":"Services"
        }
    ],
    "sg:phone":"+1 403 571 0795",
    "sg:postcode":"T3G 3S6",
    "sg:province":"AB",
    "sg:tags":[
        "church"
    ],
    "wof:name":"Jehovah's Witnesses Dalhousie",
    "wof:placetype":"venue"
},
  "geometry": {"coordinates":[-114.199661255,51.1218643188],"type":"Point"}
}