{
  "type": "Feature",
  "properties": {
    "iso:country":"CA",
    "sg:city":"Montreal",
    "sg:classifiers":[
        {
            "category":"Wholesale",
            "subcategory":"Hardware",
            "type":"Manufacturing & Wholesale Goods"
        }
    ],
    "sg:phone":"+1 514 498 7903",
    "sg:postcode":"H1A 3N6",
    "sg:province":"QC",
    "sg:tags":[
        "ventilating",
        "equipment",
        "contractor",
        "system",
        "heating"
    ],
    "wof:name":"Ventilation Manic Inc",
    "wof:placetype":"venue"
},
  "geometry": {"coordinates":[-73.5123291016,45.6574440002],"type":"Point"}
}