{
  "type": "Feature",
  "properties": {
    "addr:full":"13567 105A Ave Surrey BC V3T 2A9",
    "addr:housenumber":"13567",
    "addr:postcode":"v3t 2a9",
    "addr:street":"105A Ave",
    "iso:country":"CA",
    "sg:address":"13567 105A Ave",
    "sg:city":"Surrey",
    "sg:classifiers":[
        {
            "category":"Shopping",
            "type":"Retail Goods"
        }
    ],
    "sg:phone":"+1 604 584 3133",
    "sg:postcode":"V3T 2A9",
    "sg:province":"BC",
    "sg:tags":[
        "trophy",
        "medal",
        "award"
    ],
    "wof:name":"Superior Trophies & More",
    "wof:placetype":"venue"
},
  "geometry": {"coordinates":[-122.830215,49.105179],"type":"Point"}
}