{
  "type": "Feature",
  "properties": {
    "addr:full":"Sept-Iles QC G4R 3B1",
    "addr:postcode":"g4r 3b1",
    "iso:country":"CA",
    "sg:city":"Sept-Iles",
    "sg:classifiers":[
        {
            "category":"Professional",
            "subcategory":"Lawyer & Legal Services",
            "type":"Services"
        }
    ],
    "sg:phone":"+1 418 962 1761",
    "sg:postcode":"G4R 3B1",
    "sg:province":"QC",
    "sg:tags":[
        "attorney"
    ],
    "wof:name":"Roy, Michel QC",
    "wof:placetype":"venue"
},
  "geometry": {"coordinates":[-66.386833,50.20504],"type":"Point"}
}