{
  "type": "Feature",
  "properties": {
    "iso:country":"CA",
    "sg:address":"133 Church St",
    "sg:city":"Antigonish",
    "sg:classifiers":[
        {
            "category":"Education",
            "subcategory":"School",
            "type":"Public Place"
        }
    ],
    "sg:phone":"+1 902 863 7200",
    "sg:postcode":"B2G 2E2",
    "sg:province":"NS",
    "wof:name":"Highland Academy",
    "wof:placetype":"venue"
},
  "geometry": {"coordinates":[-61.985889,45.616169],"type":"Point"}
}