{
  "type": "Feature",
  "properties": {
    "addr:full":"1800 Rue Marie-Victorin Saint-Bruno QC J3V 6B9",
    "addr:housenumber":"1800",
    "addr:postcode":"j3v 6b9",
    "addr:street":"Rue Marie-Victorin",
    "iso:country":"CA",
    "sg:address":"1800 Rue Marie-Victorin",
    "sg:city":"Saint-Bruno",
    "sg:classifiers":[
        {
            "category":"Freight",
            "type":"Transportation"
        }
    ],
    "sg:phone":"+1 450 441 1800",
    "sg:postcode":"J3V 6B9",
    "sg:province":"QC",
    "sg:tags":[
        "warehouse",
        "self",
        "storage"
    ],
    "wof:name":"Entrepots Lapalme",
    "wof:placetype":"venue"
},
  "geometry": {"coordinates":[-71.675522,48.471771],"type":"Point"}
}