{
  "type": "Feature",
  "properties": {
    "addr:full":"12275 Highway 50 Bolton ON L7E 1M1",
    "addr:housenumber":"12275",
    "addr:postcode":"l7e 1m1",
    "addr:street":"Highway 50",
    "iso:country":"CA",
    "sg:address":"12275 Highway 50",
    "sg:city":"Bolton",
    "sg:classifiers":[
        {
            "category":"Retail",
            "subcategory":"Auto Rental",
            "type":"Services"
        }
    ],
    "sg:phone":"+1 905 951 3102",
    "sg:postcode":"L7E 1M1",
    "sg:province":"ON",
    "sg:tags":[
        "recreational",
        "leasing",
        "vehicle"
    ],
    "wof:name":"Cruise Canada Motorhome Rental",
    "wof:placetype":"venue"
},
  "geometry": {"coordinates":[-79.73943300000001,43.880852],"type":"Point"}
}