{
  "type": "Feature",
  "properties": {
    "addr:full":"2922 Millar Ave Saskatoon SK S7K 5X7",
    "addr:housenumber":"2922",
    "addr:postcode":"s7k 5x7",
    "addr:street":"Millar Ave",
    "iso:country":"CA",
    "sg:address":"2922 Millar Ave",
    "sg:city":"Saskatoon",
    "sg:classifiers":[
        {
            "category":"Manufacturing",
            "subcategory":"Rubber & Plastics",
            "type":"Manufacturing & Wholesale Goods"
        }
    ],
    "sg:phone":"+1 306 242 3233",
    "sg:postcode":"S7K 5X7",
    "sg:province":"SK",
    "sg:tags":[
        "tire"
    ],
    "wof:name":"Fountain Tire",
    "wof:placetype":"venue"
},
  "geometry": {"coordinates":[-106.646377563,52.1744689941],"type":"Point"}
}