{
  "type": "Feature",
  "properties": {
    "addr:full":"802 Prince St Truro NS B2N 1H1",
    "addr:housenumber":"802",
    "addr:postcode":"b2n 1h1",
    "addr:street":"Prince St",
    "iso:country":"CA",
    "sg:address":"802 Prince St",
    "sg:city":"Truro",
    "sg:classifiers":[
        {
            "category":"Insurance",
            "subcategory":"Insurance Agent",
            "type":"Services"
        }
    ],
    "sg:phone":"+1 902 895 1282",
    "sg:postcode":"B2N 1H1",
    "sg:province":"NS",
    "wof:name":"Clarica Life Insurance CO",
    "wof:placetype":"venue"
},
  "geometry": {"coordinates":[-63.277489,45.36459],"type":"Point"}
}