{
  "type": "Feature",
  "properties": {
    "iso:country":"CA",
    "sg:address":"PO Box 34",
    "sg:city":"Macdowall",
    "sg:classifiers":[
        {
            "category":"Organizations",
            "subcategory":"Religious Organization",
            "type":"Services"
        }
    ],
    "sg:phone":"+1 306 922 8017",
    "sg:postcode":"S0K 2S0",
    "sg:province":"SK",
    "sg:tags":[
        "church"
    ],
    "wof:name":"Mac Dowall Anglican Rectory",
    "wof:placetype":"venue"
},
  "geometry": {"coordinates":[-106.012535095,53.015335083],"type":"Point"}
}