{
  "type": "Feature",
  "properties": {
    "addr:full":"658 Second Line W # A Sault Ste Marie ON P6C 2K9",
    "addr:housenumber":"658",
    "addr:postcode":"p6c 2k9",
    "addr:street":"Second Line W # A",
    "iso:country":"CA",
    "sg:address":"658 Second Line W # A",
    "sg:city":"Sault Ste Marie",
    "sg:classifiers":[
        {
            "category":"Bars & Pubs",
            "type":"Food & Drink"
        }
    ],
    "sg:phone":"+1 705 256 1988",
    "sg:postcode":"P6C 2K9",
    "sg:province":"ON",
    "wof:name":"Misty's",
    "wof:placetype":"venue"
},
  "geometry": {"coordinates":[-84.382957,46.537041],"type":"Point"}
}