{
  "type": "Feature",
  "properties": {
    "iso:country":"CA",
    "sg:city":"Parksville",
    "sg:classifiers":[
        {
            "category":"Shopping",
            "subcategory":"Books",
            "type":"Retail Goods"
        }
    ],
    "sg:phone":"+1 250 248 2621",
    "sg:postcode":"V9P 2B7",
    "sg:province":"BC",
    "sg:tags":[
        "dealer"
    ],
    "wof:name":"Wembley Books & Lotto",
    "wof:placetype":"venue"
},
  "geometry": {"coordinates":[-124.345870972,49.3324432373],"type":"Point"}
}