{
  "type": "Feature",
  "properties": {
    "addr:full":"1650 Bath Rd Kingston ON K7M 4X6",
    "addr:housenumber":"1650",
    "addr:postcode":"k7m 4x6",
    "addr:street":"Bath Rd",
    "iso:country":"CA",
    "sg:address":"1650 Bath Rd",
    "sg:city":"Kingston",
    "sg:classifiers":[
        {
            "category":"Shopping",
            "subcategory":"Computers & Home Electronics",
            "type":"Retail Goods"
        }
    ],
    "sg:phone":"+1 613 384 9388",
    "sg:postcode":"K7M 4X6",
    "sg:province":"ON",
    "sg:tags":[
        "equipment",
        "dealer"
    ],
    "wof:name":"Redwing Computers",
    "wof:placetype":"venue"
},
  "geometry": {"coordinates":[-76.54089355470001,44.2381706238],"type":"Point"}
}