{
  "type": "Feature",
  "properties": {
    "iso:country":"CA",
    "sg:address":"180 Rang Saint-Luc",
    "sg:city":"Dolbeau-Mistassini",
    "sg:classifiers":[
        {
            "category":"Travel",
            "subcategory":"Hotels & Motels",
            "type":"Entertainment"
        }
    ],
    "sg:phone":"+1 418 276 4664",
    "sg:postcode":"G8L 6A3",
    "sg:province":"QC",
    "sg:tags":[
        "resort",
        "center",
        "skiing"
    ],
    "wof:name":"Centre DE Ski DO-MI-Ski Inc",
    "wof:placetype":"venue"
},
  "geometry": {"coordinates":[-72.2302322388,48.8892631531],"type":"Point"}
}