{
  "type": "Feature",
  "properties": {
    "addr:full":"109 Lakeview Dr Red Lake ON P0V 2M0",
    "addr:housenumber":"109",
    "addr:postcode":"p0v 2m0",
    "addr:street":"Lakeview Dr Red",
    "iso:country":"CA",
    "sg:address":"109 Lakeview Dr",
    "sg:city":"Red Lake",
    "sg:classifiers":[
        {
            "category":"Real Estate",
            "subcategory":"Real Estate Agent",
            "type":"Services"
        }
    ],
    "sg:phone":"+1 807 727 3133",
    "sg:postcode":"P0V 2M0",
    "sg:province":"ON",
    "wof:name":"Re Max First Choice Realty Ltd",
    "wof:placetype":"venue"
},
  "geometry": {"coordinates":[-93.81104278559999,51.0739936829],"type":"Point"}
}