{
  "type": "Feature",
  "properties": {
    "addr:full":"North York ON M3C 1T2",
    "addr:postcode":"m3c 1t2",
    "iso:country":"CA",
    "sg:city":"North York",
    "sg:classifiers":[
        {
            "category":"Restaurant",
            "type":"Food & Drink"
        }
    ],
    "sg:phone":"+1 416 467 7779",
    "sg:postcode":"M3C 1T2",
    "sg:province":"ON",
    "wof:name":"Mr Sub",
    "wof:placetype":"venue"
},
  "geometry": {"coordinates":[-79.33577699999999,43.71381],"type":"Point"}
}