{
  "type": "Feature",
  "properties": {
    "iso:country":"CA",
    "sg:address":"1600 Forest Valley Dr",
    "sg:city":"Orleans",
    "sg:classifiers":[
        {
            "category":"Health Services",
            "subcategory":"Doctor",
            "type":"Services"
        }
    ],
    "sg:phone":"+1 613 830 7003",
    "sg:postcode":"K1C 6X7",
    "sg:province":"ON",
    "sg:tags":[
        "dentist"
    ],
    "wof:name":"Mc Keown, Beverley DDS",
    "wof:placetype":"venue"
},
  "geometry": {"coordinates":[-75.53630065919999,45.449344635],"type":"Point"}
}