{
  "type": "Feature",
  "properties": {
    "iso:country":"CA",
    "sg:address":"41 Av Lorne",
    "sg:city":"Saint-Lambert",
    "sg:classifiers":[
        {
            "category":"Organizations",
            "subcategory":"Religious Organization",
            "type":"Services"
        }
    ],
    "sg:phone":"+1 450 671 7544",
    "sg:postcode":"J4P 2G7",
    "sg:province":"QC",
    "sg:tags":[
        "church"
    ],
    "wof:name":"Eglise Catholique Saint-Lamber",
    "wof:placetype":"venue"
},
  "geometry": {"coordinates":[-73.514221,45.500309],"type":"Point"}
}