{
  "type": "Feature",
  "properties": {
    "iso:country":"CA",
    "sg:address":"182 Algonquin Blvd E",
    "sg:city":"Timmins",
    "sg:classifiers":[
        {
            "category":"Health Services",
            "subcategory":"Health Practitioner",
            "type":"Services"
        }
    ],
    "sg:phone":"+1 705 264 2555",
    "sg:postcode":"P4N 1A9",
    "sg:province":"ON",
    "sg:tags":[
        "acupuncture",
        "holistic"
    ],
    "wof:name":"Common Sense Health Alternativ",
    "wof:placetype":"venue"
},
  "geometry": {"coordinates":[-81.3302307129,48.476272583],"type":"Point"}
}