{
  "type": "Feature",
  "properties": {
    "addr:full":"1085 60E Rue E Charlesbourg QC G1H 2E3",
    "addr:housenumber":"1085",
    "addr:postcode":"g1h 2e3",
    "addr:street":"60E Rue E",
    "iso:country":"CA",
    "sg:address":"1085 60E Rue E",
    "sg:city":"Charlesbourg",
    "sg:classifiers":[
        {
            "category":"Recreation",
            "type":"Entertainment"
        }
    ],
    "sg:phone":"+1 418 624 7753",
    "sg:postcode":"G1H 2E3",
    "sg:province":"QC",
    "sg:tags":[
        "center",
        "government"
    ],
    "wof:name":"Loisirs Bourassa",
    "wof:placetype":"venue"
},
  "geometry": {"coordinates":[-71.25131988530001,46.8456497192],"type":"Point"}
}