{
  "type": "Feature",
  "properties": {
    "addr:full":"38 Prince William St E St Stephen NB E3L 1S3",
    "addr:housenumber":"38",
    "addr:postcode":"e3l 1s3",
    "addr:street":"Prince William St E",
    "iso:country":"CA",
    "sg:address":"38 Prince William St E",
    "sg:city":"St Stephen",
    "sg:classifiers":[
        {
            "category":"Travel",
            "subcategory":"Hotels & Motels",
            "type":"Entertainment"
        }
    ],
    "sg:phone":"+1 506 466 2233",
    "sg:postcode":"E3L 1S3",
    "sg:province":"NB",
    "sg:tags":[
        "breakfast",
        "accommodation",
        "bed"
    ],
    "wof:name":"Blair House",
    "wof:placetype":"venue"
},
  "geometry": {"coordinates":[-67.27011899999999,45.193501],"type":"Point"}
}