{
  "type": "Feature",
  "properties": {
    "addr:full":"238 Boul Gerard-D.-Levesque O Paspebiac QC G0C 2K0",
    "addr:housenumber":"238",
    "addr:postcode":"g0c 2k0",
    "addr:street":"Boul Gerard-D.-Levesque O Paspebiac",
    "iso:country":"CA",
    "sg:address":"238 Boul Gerard-D.-Levesque O",
    "sg:city":"Paspebiac",
    "sg:classifiers":[
        {
            "category":"Retail",
            "subcategory":"Auto Repair",
            "type":"Services"
        }
    ],
    "sg:phone":"+1 418 752 6688",
    "sg:postcode":"G0C 2K0",
    "sg:province":"QC",
    "sg:tags":[
        "body",
        "automobile",
        "painting"
    ],
    "wof:name":"Garage Les Carrosseries",
    "wof:placetype":"venue"
},
  "geometry": {"coordinates":[-65.2302856445,48.0326499939],"type":"Point"}
}