{
  "type": "Feature",
  "properties": {
    "addr:full":"2902 Car Des Argiles Quebec QC G2C 1K3",
    "addr:housenumber":"2902",
    "addr:postcode":"qc g2c 1k3",
    "addr:street":"Car Des Argiles",
    "iso:country":"CA",
    "sg:address":"2902 Car Des Argiles",
    "sg:city":"Quebec",
    "sg:classifiers":[
        {
            "category":"Communications",
            "subcategory":"Film & Video Production",
            "type":"Services"
        }
    ],
    "sg:phone":"+1 418 843 9189",
    "sg:postcode":"G2C 1K3",
    "sg:province":"QC",
    "sg:tags":[
        "multimedia",
        "taping"
    ],
    "wof:name":"E-Video",
    "wof:placetype":"venue"
},
  "geometry": {"coordinates":[-71.3209762573,46.8258628845],"type":"Point"}
}