{
  "type": "Feature",
  "properties": {
    "addr:full":"19 Fallow Lane Mcleod Hill NB E3A 6A7",
    "addr:housenumber":"19",
    "addr:postcode":"e3a 6a7",
    "addr:street":"Fallow Lane",
    "iso:country":"CA",
    "sg:address":"19 Fallow Lane",
    "sg:city":"Mcleod Hill",
    "sg:classifiers":[
        {
            "category":"Professional",
            "subcategory":"Management & Consulting",
            "type":"Services"
        }
    ],
    "sg:phone":"+1 506 455 3663",
    "sg:postcode":"E3A 6A7",
    "sg:province":"NB",
    "sg:tags":[
        "food",
        "facility"
    ],
    "wof:name":"Food Chain Ltd",
    "wof:placetype":"venue"
},
  "geometry": {"coordinates":[-66.686729,46.019337],"type":"Point"}
}