{
  "type": "Feature",
  "properties": {
    "addr:full":"6 Griggsden Ave Etobicoke ON M9P 2Z5",
    "addr:housenumber":"6",
    "addr:postcode":"m9p 2z5",
    "addr:street":"Griggsden Ave",
    "iso:country":"CA",
    "sg:address":"6 Griggsden Ave",
    "sg:city":"Etobicoke",
    "sg:classifiers":[
        {
            "category":"Professional",
            "subcategory":"Engineering",
            "type":"Services"
        }
    ],
    "sg:phone":"+1 416 248 5910",
    "sg:postcode":"M9P 2Z5",
    "sg:province":"ON",
    "sg:tags":[
        "engineer"
    ],
    "wof:name":"Greenviro Engineering Inc",
    "wof:placetype":"venue"
},
  "geometry": {"coordinates":[-79.52624511720001,43.6890945435],"type":"Point"}
}