{
  "type": "Feature",
  "properties": {
    "addr:full":"Stratford ON N5A 3S7",
    "addr:postcode":"n5a 3s7",
    "iso:country":"CA",
    "sg:city":"Stratford",
    "sg:classifiers":[
        {
            "category":"Manufacturing",
            "subcategory":"Printing",
            "type":"Manufacturing & Wholesale Goods"
        }
    ],
    "sg:phone":"+1 519 273 1525",
    "sg:postcode":"N5A 3S7",
    "sg:province":"ON",
    "sg:tags":[
        "printer"
    ],
    "wof:name":"Avon Printer",
    "wof:placetype":"venue"
},
  "geometry": {"coordinates":[-80.963722,43.367237],"type":"Point"}
}