{
  "type": "Feature",
  "properties": {
    "addr:full":"210 16E Av O Venise-En-Quebec QC J0J 2K0",
    "addr:housenumber":"210",
    "addr:postcode":"j0j 2k0",
    "addr:street":"16E Av O Venise-En-Quebec",
    "iso:country":"CA",
    "sg:address":"210 16E Av O",
    "sg:city":"Venise-En-Quebec",
    "sg:classifiers":[
        {
            "category":"Cinema",
            "subcategory":"Movie Rental",
            "type":"Entertainment"
        }
    ],
    "sg:phone":"+1 450 244 5666",
    "sg:postcode":"J0J 2K0",
    "sg:province":"QC",
    "sg:tags":[
        "leasing",
        "video",
        "disc",
        "tape"
    ],
    "wof:name":"Video Plus",
    "wof:placetype":"venue"
},
  "geometry": {"coordinates":[-73.152145,45.085384],"type":"Point"}
}