{
  "type": "Feature",
  "properties": {
    "addr:full":"2601 Ch Du Foulon Sillery QC G1T 1X9",
    "addr:housenumber":"2601",
    "addr:postcode":"g1t 1x9",
    "addr:street":"Ch Du Foulon",
    "iso:country":"CA",
    "sg:address":"2601 Ch Du Foulon",
    "sg:city":"Sillery",
    "sg:classifiers":[
        {
            "category":"Professional",
            "subcategory":"Business Services",
            "type":"Services"
        }
    ],
    "sg:phone":"+1 418 651 1345",
    "sg:postcode":"G1T 1X9",
    "sg:province":"QC",
    "sg:tags":[
        "general",
        "appraiser",
        "contractor"
    ],
    "wof:name":"Groupe Faguy Inc",
    "wof:placetype":"venue"
},
  "geometry": {"coordinates":[-71.26728799999999,46.760681],"type":"Point"}
}