{
  "type": "Feature",
  "properties": {
    "addr:full":"Vancouver BC V6C 2W2",
    "addr:postcode":"v6c 2w2",
    "iso:country":"CA",
    "sg:city":"Vancouver",
    "sg:classifiers":[
        {
            "category":"Wholesale",
            "subcategory":"Electrical",
            "type":"Manufacturing & Wholesale Goods"
        }
    ],
    "sg:phone":"+1 604 669 7800",
    "sg:postcode":"V6C 2W2",
    "sg:province":"BC",
    "sg:tags":[
        "equipment",
        "electronic",
        "supply"
    ],
    "wof:name":"Pan Pacific Ir Ltd",
    "wof:placetype":"venue"
},
  "geometry": {"coordinates":[-123.116889954,49.287147522],"type":"Point"}
}