{
  "type": "Feature",
  "properties": {
    "addr:full":"9 Rue Rainville Canton-DE-Granby QC J2G 8C8",
    "addr:housenumber":"9",
    "addr:postcode":"j2g 8c8",
    "addr:street":"Rue Rainville Canton-De-Granby",
    "iso:country":"CA",
    "sg:address":"9 Rue Rainville",
    "sg:city":"Canton-DE-Granby",
    "sg:classifiers":[
        {
            "category":"Shopping",
            "type":"Retail Goods"
        }
    ],
    "sg:phone":"+1 450 372 0437",
    "sg:postcode":"J2G 8C8",
    "sg:province":"QC",
    "sg:tags":[
        "miscellaneous",
        "store"
    ],
    "wof:name":"Cabanons Hpr Enr",
    "wof:placetype":"venue"
},
  "geometry": {"coordinates":[-72.774002,45.420433],"type":"Point"}
}