{
  "type": "Feature",
  "properties": {
    "addr:full":"278 High St Moncton NB E1C 6C2",
    "addr:housenumber":"278",
    "addr:postcode":"e1c 6c2",
    "addr:street":"High St",
    "iso:country":"CA",
    "sg:address":"278 High St",
    "sg:city":"Moncton",
    "sg:classifiers":[
        {
            "category":"Manufacturing",
            "subcategory":"Metals",
            "type":"Manufacturing & Wholesale Goods"
        }
    ],
    "sg:phone":"+1 506 855 3144",
    "sg:postcode":"E1C 6C2",
    "sg:province":"NB",
    "sg:tags":[
        "engraver",
        "jewelry",
        "bronze"
    ],
    "wof:name":"Prestige Engraving",
    "wof:placetype":"venue"
},
  "geometry": {"coordinates":[-64.79246500000001,46.092735],"type":"Point"}
}