{
  "type": "Feature",
  "properties": {
    "addr:full":"North York ON M3A 3R3",
    "addr:postcode":"m3a 3r3",
    "iso:country":"CA",
    "sg:city":"North York",
    "sg:classifiers":[
        {
            "category":"Real Estate",
            "subcategory":"Architect",
            "type":"Services"
        }
    ],
    "sg:phone":"+1 416 391 3995",
    "sg:postcode":"M3A 3R3",
    "sg:province":"ON",
    "wof:name":"Habash Architects",
    "wof:placetype":"venue"
},
  "geometry": {"coordinates":[-79.3218460083,43.7408790588],"type":"Point"}
}