{
  "type": "Feature",
  "properties": {
    "iso:country":"CA",
    "sg:address":"621 Rue Notre Dame",
    "sg:city":"Bon-Conseil",
    "sg:classifiers":[
        {
            "category":"Food & Beverages",
            "subcategory":"Groceries & Convenience Stores",
            "type":"Retail Goods"
        }
    ],
    "sg:phone":"+1 819 336 2711",
    "sg:postcode":"J0C 1A0",
    "sg:province":"QC",
    "sg:tags":[
        "grocer"
    ],
    "wof:name":"Marche Bon Conseil",
    "wof:placetype":"venue"
},
  "geometry": {"coordinates":[-72.3430023193,46.001121521],"type":"Point"}
}