{
  "type": "Feature",
  "properties": {
    "iso:country":"CA",
    "sg:address":"1 Heritage Way",
    "sg:city":"Lindsay",
    "sg:classifiers":[
        {
            "category":"Real Estate",
            "subcategory":"Real Estate Operator",
            "type":"Services"
        }
    ],
    "sg:phone":"+1 705 324 9647",
    "sg:postcode":"K9V 5P9",
    "sg:province":"ON",
    "sg:tags":[
        "condominium"
    ],
    "wof:name":"Heritage Gardens West",
    "wof:placetype":"venue"
},
  "geometry": {"coordinates":[-78.75737762449999,44.3562660217],"type":"Point"}
}