{
  "type": "Feature",
  "properties": {
    "addr:full":"1st Ave N Beechy SK S0L 0C0",
    "addr:postcode":"s0l 0c0",
    "addr:street":"1St Ave N Beechy",
    "iso:country":"CA",
    "sg:address":"1st Ave N",
    "sg:city":"Beechy",
    "sg:classifiers":[
        {
            "category":"Building & Trades",
            "subcategory":"Construction",
            "type":"Services"
        }
    ],
    "sg:phone":"+1 306 859 2110",
    "sg:postcode":"S0L 0C0",
    "sg:province":"SK",
    "sg:tags":[
        "excavating",
        "contractor"
    ],
    "wof:name":"Stroeder Trenching & Welding",
    "wof:placetype":"venue"
},
  "geometry": {"coordinates":[-107.382469,50.876373],"type":"Point"}
}