{
  "type": "Feature",
  "properties": {
    "addr:full":"759 Willow St Truro NS B2N 5H2",
    "addr:housenumber":"759",
    "addr:postcode":"b2n 5h2",
    "addr:street":"Willow St",
    "iso:country":"CA",
    "sg:address":"759 Willow St",
    "sg:city":"Truro",
    "sg:classifiers":[
        {
            "category":"Utilities",
            "subcategory":"Refuse",
            "type":"Services"
        }
    ],
    "sg:phone":"+1 902 895 5789",
    "sg:postcode":"B2N 5H2",
    "sg:province":"NS",
    "sg:tags":[
        "garbage",
        "collection"
    ],
    "wof:name":"Johnston & Blades Trucking",
    "wof:placetype":"venue"
},
  "geometry": {"coordinates":[-63.2936553955,45.3370857239],"type":"Point"}
}