{
  "type": "Feature",
  "properties": {
    "addr:full":"4067 Chesswood Dr North York ON M3J 2R8",
    "addr:housenumber":"4067",
    "addr:postcode":"m3j 2r8",
    "addr:street":"Chesswood Dr",
    "iso:country":"CA",
    "sg:address":"4067 Chesswood Dr",
    "sg:city":"North York",
    "sg:classifiers":[
        {
            "category":"Retail",
            "subcategory":"Auto Rental",
            "type":"Services"
        }
    ],
    "sg:phone":"+1 416 630 0364",
    "sg:postcode":"M3J 2R8",
    "sg:province":"ON",
    "sg:tags":[
        "renting",
        "automobile",
        "leasing"
    ],
    "wof:name":"Lease X Auto Inc",
    "wof:placetype":"venue"
},
  "geometry": {"coordinates":[-79.477242,43.758446],"type":"Point"}
}