{
  "type": "Feature",
  "properties": {
    "addr:full":"8950 Okanagan Centre Rd W Winfield BC V4V 1N3",
    "addr:housenumber":"8950",
    "addr:postcode":"v4v 1n3",
    "addr:street":"Okanagan Centre Rd W",
    "iso:country":"CA",
    "sg:address":"8950 Okanagan Centre Rd W",
    "sg:city":"Winfield",
    "sg:classifiers":[
        {
            "category":"Retail",
            "subcategory":"Auto Repair",
            "type":"Services"
        }
    ],
    "sg:phone":"+1 250 766 3930",
    "sg:postcode":"V4V 1N3",
    "sg:province":"BC",
    "sg:tags":[
        "repairing",
        "automobile",
        "engine"
    ],
    "wof:name":"Ross Rebuilders Inc",
    "wof:placetype":"venue"
},
  "geometry": {"coordinates":[-119.40640258800001,50.0221595764],"type":"Point"}
}