{
  "type": "Feature",
  "properties": {
    "addr:full":"201 Kaybob Dr Fox Creek AB T0H 1P0",
    "addr:housenumber":"201",
    "addr:postcode":"ab t0h 1p0",
    "addr:street":"Kaybob Dr Fox Creek",
    "iso:country":"CA",
    "sg:address":"201 Kaybob Dr",
    "sg:city":"Fox Creek",
    "sg:classifiers":[
        {
            "category":"Government",
            "subcategory":"Office",
            "type":"Public Place"
        }
    ],
    "sg:phone":"+1 780 622 3921",
    "sg:postcode":"T0H 1P0",
    "sg:province":"AB",
    "wof:name":"Alberta Forest Ranger Station",
    "wof:placetype":"venue"
},
  "geometry": {"coordinates":[-116.809898,54.413643],"type":"Point"}
}