{
  "type": "Feature",
  "properties": {
    "addr:full":"Delta BC V4C 6R4",
    "addr:postcode":"v4c 6r4",
    "iso:country":"CA",
    "sg:city":"Delta",
    "sg:classifiers":[
        {
            "category":"Shopping",
            "type":"Retail Goods"
        }
    ],
    "sg:phone":"+1 604 597 3378",
    "sg:postcode":"V4C 6R4",
    "sg:province":"BC",
    "sg:tags":[
        "video",
        "disc",
        "tape",
        "miscellaneous",
        "store"
    ],
    "wof:name":"Tiffany's Video",
    "wof:placetype":"venue"
},
  "geometry": {"coordinates":[-123.09877014200001,49.0872612],"type":"Point"}
}