{
  "type": "Feature",
  "properties": {
    "addr:full":"24 Coburg St Saint John NB E2L 3J5",
    "addr:housenumber":"24",
    "addr:postcode":"nb e2l 3j5",
    "addr:street":"Coburg St",
    "iso:country":"CA",
    "sg:address":"24 Coburg St",
    "sg:city":"Saint John",
    "sg:classifiers":[
        {
            "category":"Organizations",
            "subcategory":"Community Association",
            "type":"Services"
        }
    ],
    "sg:phone":"+1 506 657 6181",
    "sg:postcode":"E2L 3J5",
    "sg:province":"NB",
    "wof:name":"Knights of Columbus",
    "wof:placetype":"venue"
},
  "geometry": {"coordinates":[-66.05940200000001,45.27562],"type":"Point"}
}