{
  "type": "Feature",
  "properties": {
    "addr:full":"10322 Jasper Ave NW Edmonton AB T5J 1Y7",
    "addr:housenumber":"10322",
    "addr:postcode":"t5j 1y7",
    "addr:street":"Jasper Ave Nw",
    "iso:country":"CA",
    "sg:address":"10322 Jasper Ave NW",
    "sg:city":"Edmonton",
    "sg:classifiers":[
        {
            "category":"Shopping",
            "subcategory":"Shoes",
            "type":"Retail Goods"
        }
    ],
    "sg:phone":"+1 780 422 2718",
    "sg:postcode":"T5J 1Y7",
    "sg:province":"AB",
    "wof:name":"Wener's Shoes",
    "wof:placetype":"venue"
},
  "geometry": {"coordinates":[-113.49793200000001,53.541157],"type":"Point"}
}