{
  "type": "Feature",
  "properties": {
    "iso:country":"CA",
    "sg:address":"9510 Rue Notre-Dame E",
    "sg:city":"Montreal",
    "sg:classifiers":[
        {
            "category":"Retail",
            "subcategory":"Auto Repair",
            "type":"Services"
        }
    ],
    "sg:phone":"+1 514 351 6699",
    "sg:postcode":"H1L 3P3",
    "sg:province":"QC",
    "sg:tags":[
        "repairing",
        "automobile"
    ],
    "wof:name":"Garage Tetreaultville",
    "wof:placetype":"venue"
},
  "geometry": {"coordinates":[-73.511108,45.608856],"type":"Point"}
}