{
  "type": "Feature",
  "properties": {
    "iso:country":"CA",
    "sg:city":"Chilliwack",
    "sg:classifiers":[
        {
            "category":"Shopping",
            "subcategory":"Clothing, Apparel, & Fashions",
            "type":"Retail Goods"
        }
    ],
    "sg:phone":"+1 604 824 1975",
    "sg:postcode":"V2R 1A1",
    "sg:province":"BC",
    "sg:tags":[
        "infant",
        "wear"
    ],
    "wof:name":"Please Mum",
    "wof:placetype":"venue"
},
  "geometry": {"coordinates":[-121.961967468,49.1408920288],"type":"Point"}
}