{
  "type": "Feature",
  "properties": {
    "iso:country":"CA",
    "sg:address":"3875 Rue Isabelle",
    "sg:city":"Brossard",
    "sg:classifiers":[
        {
            "category":"Building & Trades",
            "subcategory":"Construction",
            "type":"Services"
        }
    ],
    "sg:phone":"+1 450 444 7048",
    "sg:postcode":"J4Y 2R2",
    "sg:province":"QC",
    "sg:tags":[
        "maker",
        "cabinet"
    ],
    "wof:name":"Heritage Ebinesterie",
    "wof:placetype":"venue"
},
  "geometry": {"coordinates":[-73.4673843384,45.4274559021],"type":"Point"}
}