{
  "type": "Feature",
  "properties": {
    "addr:full":"Bolton ON L7E 1K5",
    "addr:postcode":"l7e 1k5",
    "iso:country":"CA",
    "sg:city":"Bolton",
    "sg:classifiers":[
        {
            "category":"Retail",
            "subcategory":"Auto Repair",
            "type":"Services"
        }
    ],
    "sg:phone":"+1 905 857 5000",
    "sg:postcode":"L7E 1K5",
    "sg:province":"ON",
    "sg:tags":[
        "body",
        "automobile",
        "painting"
    ],
    "wof:name":"Diamond Auto Collision",
    "wof:placetype":"venue"
},
  "geometry": {"coordinates":[-79.704391,43.860416],"type":"Point"}
}