{
  "type": "Feature",
  "properties": {
    "iso:country":"CA",
    "sg:address":"118 Christina St N",
    "sg:city":"Sarnia",
    "sg:classifiers":[
        {
            "category":"Restaurant",
            "type":"Food & Drink"
        }
    ],
    "sg:phone":"+1 519 332 4077",
    "sg:postcode":"N7T 5T6",
    "sg:province":"ON",
    "sg:tags":[
        "bars"
    ],
    "wof:name":"Ollie's Bar & Grill",
    "wof:placetype":"venue"
},
  "geometry": {"coordinates":[-82.40748596189999,42.9712524414],"type":"Point"}
}