{
  "type": "Feature",
  "properties": {
    "addr:full":"670 Rue Darveau Longueuil QC J4L 4K3",
    "addr:housenumber":"670",
    "addr:postcode":"j4l 4k3",
    "addr:street":"Rue Darveau",
    "iso:country":"CA",
    "sg:address":"670 Rue Darveau",
    "sg:city":"Longueuil",
    "sg:classifiers":[
        {
            "category":"Recreation",
            "type":"Entertainment"
        }
    ],
    "sg:phone":"+1 450 646 8260",
    "sg:postcode":"J4L 4K3",
    "sg:province":"QC",
    "sg:tags":[
        "government",
        "swimming"
    ],
    "wof:name":"Longueuil Piscines Ctr",
    "wof:placetype":"venue"
},
  "geometry": {"coordinates":[-73.46343231199999,45.5129928589],"type":"Point"}
}