{
  "type": "Feature",
  "properties": {
    "addr:full":"North York ON M3J 3G9",
    "addr:postcode":"m3j 3g9",
    "iso:country":"CA",
    "sg:city":"North York",
    "sg:classifiers":[
        {
            "category":"Professional",
            "subcategory":"Research",
            "type":"Services"
        }
    ],
    "sg:phone":"+1 416 663 0445",
    "sg:postcode":"M3J 3G9",
    "sg:province":"ON",
    "sg:tags":[
        "foundation",
        "philanthropic"
    ],
    "wof:name":"Smiles Foundation",
    "wof:placetype":"venue"
},
  "geometry": {"coordinates":[-79.48923492430001,43.7826385498],"type":"Point"}
}