{
  "type": "Feature",
  "properties": {
    "addr:full":"2851 Weston Rd North York ON M9M 2S1",
    "addr:housenumber":"2851",
    "addr:postcode":"m9m 2s1",
    "addr:street":"Weston Rd",
    "iso:country":"CA",
    "sg:address":"2851 Weston Rd",
    "sg:city":"North York",
    "sg:classifiers":[
        {
            "category":"Shopping",
            "subcategory":"Discount & Variety Stores",
            "type":"Retail Goods"
        }
    ],
    "sg:phone":"+1 416 743 2971",
    "sg:postcode":"M9M 2S1",
    "sg:province":"ON",
    "wof:name":"Gaydon Variety",
    "wof:placetype":"venue"
},
  "geometry": {"coordinates":[-79.5371398926,43.721244812],"type":"Point"}
}