{
  "type": "Feature",
  "properties": {
    "addr:full":"1951 Boul Rosemont Montreal QC H2G 1S9",
    "addr:housenumber":"1951",
    "addr:postcode":"h2g 1s9",
    "addr:street":"Boul Rosemont",
    "iso:country":"CA",
    "sg:address":"1951 Boul Rosemont",
    "sg:city":"Montreal",
    "sg:classifiers":[
        {
            "category":"Shopping",
            "subcategory":"Pharmacy",
            "type":"Retail Goods"
        }
    ],
    "sg:phone":"+1 514 273 4165",
    "sg:postcode":"H2G 1S9",
    "sg:province":"QC",
    "wof:name":"Thi Phan Pharmacie",
    "wof:placetype":"venue"
},
  "geometry": {"coordinates":[-73.59033203120001,45.5419387817],"type":"Point"}
}