{
  "type": "Feature",
  "properties": {
    "iso:country":"CA",
    "sg:address":"3615 Weston Rd",
    "sg:city":"North York",
    "sg:classifiers":[
        {
            "category":"Social Services",
            "type":"Services"
        }
    ],
    "sg:phone":"+1 416 749 6234",
    "sg:postcode":"M9L 1V8",
    "sg:province":"ON",
    "sg:tags":[
        "organization",
        "welfare"
    ],
    "wof:name":"Vita Community Living Svc",
    "wof:placetype":"venue"
},
  "geometry": {"coordinates":[-79.5436248779,43.7575759888],"type":"Point"}
}