{
  "type": "Feature",
  "properties": {
    "addr:full":"1418 Weber St E Kitchener ON N2A 1C4",
    "addr:housenumber":"1418",
    "addr:postcode":"n2a 1c4",
    "addr:street":"Weber St E",
    "iso:country":"CA",
    "sg:address":"1418 Weber St E",
    "sg:city":"Kitchener",
    "sg:classifiers":[
        {
            "category":"Shopping",
            "subcategory":"Musical Instruments",
            "type":"Retail Goods"
        }
    ],
    "sg:phone":"+1 519 894 0110",
    "sg:postcode":"N2A 1C4",
    "sg:province":"ON",
    "wof:name":"Bob Gray Music Ltd",
    "wof:placetype":"venue"
},
  "geometry": {"coordinates":[-80.4393615723,43.4326248169],"type":"Point"}
}