{
  "type": "Feature",
  "properties": {
    "iso:country":"CA",
    "sg:address":"471 Av Du Pont N",
    "sg:city":"Alma",
    "sg:classifiers":[
        {
            "category":"Shopping",
            "subcategory":"Pharmacy",
            "type":"Retail Goods"
        }
    ],
    "sg:phone":"+1 418 668 2349",
    "sg:postcode":"G8B 5E5",
    "sg:province":"QC",
    "wof:name":"Jean Coutu",
    "wof:placetype":"venue"
},
  "geometry": {"coordinates":[-71.6388473511,48.5562324524],"type":"Point"}
}