{
  "type": "Feature",
  "properties": {
    "iso:country":"CA",
    "sg:address":"3300 Ninth Line",
    "sg:city":"Oakville",
    "sg:classifiers":[
        {
            "category":"Education",
            "subcategory":"School",
            "type":"Public Place"
        }
    ],
    "sg:phone":"+1 905 257 0022",
    "sg:postcode":"L6H 7A8",
    "sg:province":"ON",
    "wof:name":"Fern Hill School",
    "wof:placetype":"venue"
},
  "geometry": {"coordinates":[-79.706245,43.514633],"type":"Point"}
}