{
  "type": "Feature",
  "properties": {
    "addr:full":"102 Bronte Rd Oakville ON L6L 6J5",
    "addr:housenumber":"102",
    "addr:postcode":"l6l 6j5",
    "addr:street":"Bronte Rd",
    "iso:country":"CA",
    "sg:address":"102 Bronte Rd",
    "sg:city":"Oakville",
    "sg:classifiers":[
        {
            "category":"Real Estate",
            "subcategory":"Real Estate Operator",
            "type":"Services"
        }
    ],
    "sg:phone":"+1 905 827 5365",
    "sg:postcode":"L6L 6J5",
    "sg:province":"ON",
    "sg:tags":[
        "condominium"
    ],
    "wof:name":"Halton Condominium Corp 150",
    "wof:placetype":"venue"
},
  "geometry": {"coordinates":[-79.7118682861,43.3939628601],"type":"Point"}
}