{
  "type": "Feature",
  "properties": {
    "addr:full":"Woodbridge ON L4L 5V2",
    "addr:postcode":"l4l 5v2",
    "iso:country":"CA",
    "sg:city":"Woodbridge",
    "sg:classifiers":[
        {
            "category":"Manufacturing",
            "subcategory":"Metals",
            "type":"Manufacturing & Wholesale Goods"
        }
    ],
    "sg:phone":"+1 905 856 5599",
    "sg:postcode":"L4L 5V2",
    "sg:province":"ON",
    "sg:tags":[
        "trophy",
        "medal",
        "award"
    ],
    "wof:name":"Olympic Trophies",
    "wof:placetype":"venue"
},
  "geometry": {"coordinates":[-79.57010650629999,43.7799034119],"type":"Point"}
}