{
  "type": "Feature",
  "properties": {
    "addr:full":"3630 Ch Gauthier LA Plaine QC J7M 1R7",
    "addr:postcode":"3630;j7m 1r7",
    "addr:street":"Ch Gauthier",
    "iso:country":"CA",
    "sg:address":"3630 Ch Gauthier",
    "sg:city":"LA Plaine",
    "sg:classifiers":[
        {
            "category":"Food & Beverages",
            "subcategory":"Groceries & Convenience Stores",
            "type":"Retail Goods"
        }
    ],
    "sg:phone":"+1 450 838 8727",
    "sg:postcode":"J7M 1R7",
    "sg:province":"QC",
    "wof:name":"Depanneur Boni-Soir",
    "wof:placetype":"venue"
},
  "geometry": {"coordinates":[-73.765587,45.792225],"type":"Point"}
}