{
  "type": "Feature",
  "properties": {
    "addr:full":"2090 Harvey Ave Kelowna BC V1Y 8P8",
    "addr:housenumber":"2090",
    "addr:postcode":"v1y 8p8",
    "addr:street":"Harvey Ave",
    "iso:country":"CA",
    "sg:address":"2090 Harvey Ave",
    "sg:city":"Kelowna",
    "sg:classifiers":[
        {
            "category":"Restaurant",
            "type":"Food & Drink"
        }
    ],
    "sg:phone":"+1 250 860 8777",
    "sg:postcode":"V1Y 8P8",
    "sg:province":"BC",
    "wof:name":"Chinese Laundry Restaurant",
    "wof:placetype":"venue"
},
  "geometry": {"coordinates":[-119.44436645499999,49.8821182251],"type":"Point"}
}