{
  "type": "Feature",
  "properties": {
    "addr:full":"12930 Peggys Cove Rd Tantallon NS B3Z 2K4",
    "addr:housenumber":"12930",
    "addr:postcode":"b3z 2k4",
    "addr:street":"Peggys Cove Rd",
    "iso:country":"CA",
    "sg:address":"12930 Peggys Cove Rd",
    "sg:city":"Tantallon",
    "sg:classifiers":[
        {
            "category":"Organizations",
            "subcategory":"Membership Organization",
            "type":"Services"
        }
    ],
    "sg:phone":"+1 902 826 9272",
    "sg:postcode":"B3Z 2K4",
    "sg:province":"NS",
    "wof:name":"St Margarets Bay Food Bank",
    "wof:placetype":"venue"
},
  "geometry": {"coordinates":[-63.894421,44.665298],"type":"Point"}
}