{
  "type": "Feature",
  "properties": {
    "addr:full":"33441 Thompson Ave Mission BC V2V 2W9",
    "addr:postcode":"33441;v2v 2w9",
    "addr:street":"Thompson Ave",
    "iso:country":"CA",
    "sg:address":"33441 Thompson Ave",
    "sg:city":"Mission",
    "sg:classifiers":[
        {
            "category":"Freight",
            "type":"Transportation"
        }
    ],
    "sg:phone":"+1 604 826 2614",
    "sg:postcode":"V2V 2W9",
    "sg:province":"BC",
    "sg:tags":[
        "trucking"
    ],
    "wof:name":"Fraser Valley Transport Ltd",
    "wof:placetype":"venue"
},
  "geometry": {"coordinates":[-122.297539,49.132828],"type":"Point"}
}