{
  "type": "Feature",
  "properties": {
    "addr:full":"Wikwemikong ON P0P 2J0",
    "addr:postcode":"p0p 2j0",
    "iso:country":"CA",
    "sg:city":"Wikwemikong",
    "sg:classifiers":[
        {
            "category":"Retail",
            "subcategory":"Auto Repair",
            "type":"Services"
        }
    ],
    "sg:phone":"+1 705 859 2366",
    "sg:postcode":"P0P 2J0",
    "sg:province":"ON",
    "sg:tags":[
        "repairing",
        "automobile"
    ],
    "wof:name":"Wikwemikong Municipal Garage",
    "wof:placetype":"venue"
},
  "geometry": {"coordinates":[-81.72570800779999,45.7999382019],"type":"Point"}
}