{
  "type": "Feature",
  "properties": {
    "addr:full":"465 King St E Toronto ON M5A 1L6",
    "addr:housenumber":"465",
    "addr:postcode":"m5a 1l6",
    "addr:street":"King St E",
    "iso:country":"CA",
    "sg:address":"465 King St E",
    "sg:city":"Toronto",
    "sg:classifiers":[
        {
            "category":"Communications",
            "subcategory":"Film & Video Production",
            "type":"Services"
        }
    ],
    "sg:phone":"+1 416 538 4455",
    "sg:postcode":"M5A 1L6",
    "sg:province":"ON",
    "sg:tags":[
        "taping"
    ],
    "wof:name":"Freeway Visuals",
    "wof:placetype":"venue"
},
  "geometry": {"coordinates":[-79.360992,43.65398],"type":"Point"}
}