{
  "type": "Feature",
  "properties": {
    "addr:full":"2421 Royal Windsor Dr Oakville ON L6J 7X6",
    "addr:housenumber":"2421",
    "addr:postcode":"l6j 7x6",
    "addr:street":"Royal Windsor Dr",
    "iso:country":"CA",
    "sg:address":"2421 Royal Windsor Dr",
    "sg:city":"Oakville",
    "sg:classifiers":[
        {
            "category":"Wholesale",
            "subcategory":"Groceries",
            "type":"Manufacturing & Wholesale Goods"
        }
    ],
    "sg:phone":"+1 905 829 8520",
    "sg:postcode":"L6J 7X6",
    "sg:province":"ON",
    "sg:tags":[
        "tea",
        "coffee"
    ],
    "wof:name":"Reunion Island Coffee Ltd",
    "wof:placetype":"venue"
},
  "geometry": {"coordinates":[-79.6503067017,43.4923820496],"type":"Point"}
}