{
  "type": "Feature",
  "properties": {
    "addr:full":"515 Rue Simard Saint-Ambroise QC G7P 2S6",
    "addr:housenumber":"515",
    "addr:postcode":"g7p 2s6",
    "addr:street":"Rue Simard",
    "iso:country":"CA",
    "sg:address":"515 Rue Simard",
    "sg:city":"Saint-Ambroise",
    "sg:classifiers":[
        {
            "category":"Personal",
            "subcategory":"Beauty Salon",
            "type":"Services"
        }
    ],
    "sg:phone":"+1 418 672 4046",
    "sg:postcode":"G7P 2S6",
    "sg:province":"QC",
    "wof:name":"Salon Nathalie",
    "wof:placetype":"venue"
},
  "geometry": {"coordinates":[-71.3239517212,48.5575408936],"type":"Point"}
}