{
  "type": "Feature",
  "properties": {
    "addr:full":"1106 Somerset St W Ottawa ON K1Y 3C8",
    "addr:housenumber":"1106",
    "addr:postcode":"k1y 3c8",
    "addr:street":"Somerset St W",
    "iso:country":"CA",
    "sg:address":"1106 Somerset St W",
    "sg:city":"Ottawa",
    "sg:classifiers":[
        {
            "category":"Shopping",
            "subcategory":"Clothing, Apparel, & Fashions",
            "type":"Retail Goods"
        }
    ],
    "sg:phone":"+1 613 729 9868",
    "sg:postcode":"K1Y 3C8",
    "sg:province":"ON",
    "sg:tags":[
        "shop",
        "bridal"
    ],
    "wof:name":"Yen's Bridal & Designs",
    "wof:placetype":"venue"
},
  "geometry": {"coordinates":[-75.722015,45.405949],"type":"Point"}
}