{
  "type": "Feature",
  "properties": {
    "addr:full":"3827 15A St SE Calgary AB T2G 3N7",
    "addr:housenumber":"3827",
    "addr:postcode":"t2g 3n7",
    "addr:street":"15A St Se",
    "iso:country":"CA",
    "sg:address":"3827 15A St SE",
    "sg:city":"Calgary",
    "sg:classifiers":[
        {
            "category":"Building & Trades",
            "subcategory":"Electrical",
            "type":"Services"
        }
    ],
    "sg:phone":"+1 403 266 2935",
    "sg:postcode":"T2G 3N7",
    "sg:province":"AB",
    "sg:tags":[
        "electric",
        "contractor"
    ],
    "wof:name":"O'Dell Electric Ltd",
    "wof:placetype":"venue"
},
  "geometry": {"coordinates":[-114.023788,51.021221],"type":"Point"}
}