{
  "type": "Feature",
  "properties": {
    "addr:full":"115 3rd Ave S # 6 Saskatoon SK S7K 1L7",
    "addr:housenumber":"115",
    "addr:postcode":"s7k 1l7",
    "addr:street":"3Rd Ave S # 6",
    "iso:country":"CA",
    "sg:address":"115 3rd Ave S # 6",
    "sg:city":"Saskatoon",
    "sg:classifiers":[
        {
            "category":"Manufacturing",
            "subcategory":"Jewelry",
            "type":"Manufacturing & Wholesale Goods"
        }
    ],
    "sg:phone":"+1 306 653 0845",
    "sg:postcode":"S7K 1L7",
    "sg:province":"SK",
    "sg:tags":[
        "lapidary"
    ],
    "wof:name":"Atlantis",
    "wof:placetype":"venue"
},
  "geometry": {"coordinates":[-106.662468,52.128162],"type":"Point"}
}