{
  "type": "Feature",
  "properties": {
    "addr:full":"2740 Sherwood Heights Dr Oakville ON L6J 7V5",
    "addr:housenumber":"2740",
    "addr:postcode":"l6j 7v5",
    "addr:street":"Sherwood Heights Dr",
    "iso:country":"CA",
    "sg:address":"2740 Sherwood Heights Dr",
    "sg:city":"Oakville",
    "sg:classifiers":[
        {
            "category":"Building & Trades",
            "subcategory":"Construction",
            "type":"Services"
        }
    ],
    "sg:phone":"+1 905 829 0280",
    "sg:postcode":"L6J 7V5",
    "sg:province":"ON",
    "sg:tags":[
        "skylight"
    ],
    "wof:name":"Velux Canada",
    "wof:placetype":"venue"
},
  "geometry": {"coordinates":[-79.67017364500001,43.502532959],"type":"Point"}
}