{
  "type": "Feature",
  "properties": {
    "iso:country":"CA",
    "sg:address":"2090 Norris St",
    "sg:city":"Lumby",
    "sg:classifiers":[
        {
            "category":"Restaurant",
            "type":"Food & Drink"
        }
    ],
    "sg:phone":"+1 250 547 8877",
    "sg:postcode":"V0E 2G0",
    "sg:province":"BC",
    "sg:tags":[
        "pizza"
    ],
    "wof:name":"Ana's Just Pizza",
    "wof:placetype":"venue"
},
  "geometry": {"coordinates":[-118.962463379,50.2487869263],"type":"Point"}
}