{
  "type": "Feature",
  "properties": {
    "addr:full":"174 Third St Kitimat BC V8C 2H5",
    "addr:housenumber":"174",
    "addr:postcode":"bc v8c 2h5",
    "addr:street":"Third St",
    "iso:country":"CA",
    "sg:address":"174 Third St",
    "sg:city":"Kitimat",
    "sg:classifiers":[
        {
            "category":"Building & Trades",
            "subcategory":"Plumbing",
            "type":"Services"
        }
    ],
    "sg:phone":"+1 250 632 5403",
    "sg:postcode":"V8C 2H5",
    "sg:province":"BC",
    "sg:tags":[
        "control",
        "air",
        "pollution"
    ],
    "wof:name":"Air-Tec Consulting Ltd",
    "wof:placetype":"venue"
},
  "geometry": {"coordinates":[-128.68814086899999,54.0572891235],"type":"Point"}
}