{
  "type": "Feature",
  "properties": {
    "addr:full":"535 Rue Notre-Dame Repentigny QC J6A 2T6",
    "addr:housenumber":"535",
    "addr:postcode":"j6a 2t6",
    "addr:street":"Rue Notre-Dame",
    "iso:country":"CA",
    "sg:address":"535 Rue Notre-Dame",
    "sg:city":"Repentigny",
    "sg:classifiers":[
        {
            "category":"Banks & Credit Unions",
            "subcategory":"Investment Brokerage",
            "type":"Services"
        }
    ],
    "sg:phone":"+1 450 585 5888",
    "sg:postcode":"J6A 2T6",
    "sg:province":"QC",
    "sg:tags":[
        "advisory",
        "financial"
    ],
    "wof:name":"Veilleux, Jacques",
    "wof:placetype":"venue"
},
  "geometry": {"coordinates":[-73.44064331049999,45.7430419922],"type":"Point"}
}