{
  "type": "Feature",
  "properties": {
    "addr:full":"716 Oakhill Pl SW Calgary AB T2V 3X9",
    "addr:housenumber":"716",
    "addr:postcode":"t2v 3x9",
    "addr:street":"Oakhill Pl Sw",
    "iso:country":"CA",
    "sg:address":"716 Oakhill Pl SW",
    "sg:city":"Calgary",
    "sg:classifiers":[
        {
            "category":"Health Services",
            "subcategory":"Podiatrist",
            "type":"Services"
        }
    ],
    "sg:phone":"+1 403 281 9677",
    "sg:postcode":"T2V 3X9",
    "sg:province":"AB",
    "wof:name":"Foot Nurse",
    "wof:placetype":"venue"
},
  "geometry": {"coordinates":[-114.125671,50.965694],"type":"Point"}
}