{
  "type": "Feature",
  "properties": {
    "addr:full":"Saint-Constant QC J5A 2E7",
    "addr:postcode":"j5a 2e7",
    "iso:country":"CA",
    "sg:city":"Saint-Constant",
    "sg:classifiers":[
        {
            "category":"Health Services",
            "subcategory":"Doctor",
            "type":"Services"
        }
    ],
    "sg:phone":"+1 450 632 1630",
    "sg:postcode":"J5A 2E7",
    "sg:province":"QC",
    "sg:tags":[
        "physician",
        "surgeon"
    ],
    "wof:name":"Gelinas, Lucie MD",
    "wof:placetype":"venue"
},
  "geometry": {"coordinates":[-73.567825,45.37495],"type":"Point"}
}