{
  "type": "Feature",
  "properties": {
    "addr:full":"Mississauga ON L5T 1N3",
    "addr:postcode":"l5t 1n3",
    "iso:country":"CA",
    "sg:city":"Mississauga",
    "sg:classifiers":[
        {
            "category":"Retail",
            "subcategory":"Auto Repair",
            "type":"Services"
        }
    ],
    "sg:phone":"+1 905 795 1895",
    "sg:postcode":"L5T 1N3",
    "sg:province":"ON",
    "sg:tags":[
        "clutches"
    ],
    "wof:name":"Kustom Dezyne Clutch Inc",
    "wof:placetype":"venue"
},
  "geometry": {"coordinates":[-79.643021,43.663086],"type":"Point"}
}