{
  "type": "Feature",
  "properties": {
    "addr:full":"2151 Recreation Ave Vanderhoof BC V0J 3A0",
    "addr:housenumber":"2151",
    "addr:postcode":"v0j 3a0",
    "addr:street":"Recreation Ave",
    "iso:country":"CA",
    "sg:address":"2151 Recreation Ave",
    "sg:city":"Vanderhoof",
    "sg:classifiers":[
        {
            "category":"Freight",
            "type":"Transportation"
        }
    ],
    "sg:phone":"+1 250 567 4968",
    "sg:postcode":"V0J 3A0",
    "sg:province":"BC",
    "sg:tags":[
        "trucking"
    ],
    "wof:name":"Canadian Freightways",
    "wof:placetype":"venue"
},
  "geometry": {"coordinates":[-123.99685700000001,54.019085],"type":"Point"}
}