{
  "type": "Feature",
  "properties": {
    "iso:country":"CA",
    "sg:city":"Salaberry-DE-Valleyfield",
    "sg:classifiers":[
        {
            "category":"Health Services",
            "subcategory":"Nursing And Care Facility",
            "type":"Services"
        }
    ],
    "sg:phone":"+1 450 373 5705",
    "sg:postcode":"J6T 1A7",
    "sg:province":"QC",
    "sg:tags":[
        "hospital"
    ],
    "wof:name":"Sante Mentale Jeunesse",
    "wof:placetype":"venue"
},
  "geometry": {"coordinates":[-74.129112,45.256474],"type":"Point"}
}