{
  "type": "Feature",
  "properties": {
    "addr:full":"1831 Coldwell Rd North Vancouver BC V7G 2P3",
    "addr:housenumber":"1831",
    "addr:postcode":"v7g 2p3",
    "addr:street":"Coldwell Rd",
    "iso:country":"CA",
    "sg:address":"1831 Coldwell Rd",
    "sg:city":"North Vancouver",
    "sg:classifiers":[
        {
            "category":"Professional",
            "subcategory":"Management & Consulting",
            "type":"Services"
        }
    ],
    "sg:phone":"+1 604 929 8676",
    "sg:postcode":"V7G 2P3",
    "sg:province":"BC",
    "sg:tags":[
        "consultant",
        "business"
    ],
    "wof:name":"Michael Docherty & Assoc",
    "wof:placetype":"venue"
},
  "geometry": {"coordinates":[-122.95919000000001,49.323376],"type":"Point"}
}