{
  "type": "Feature",
  "properties": {
    "addr:full":"1790 Meyerside Dr Mississauga ON L5T 1B4",
    "addr:housenumber":"1790",
    "addr:postcode":"l5t 1b4",
    "addr:street":"Meyerside Dr",
    "iso:country":"CA",
    "sg:address":"1790 Meyerside Dr",
    "sg:city":"Mississauga",
    "sg:classifiers":[
        {
            "category":"Retail",
            "subcategory":"Auto Repair",
            "type":"Services"
        }
    ],
    "sg:phone":"+1 905 565 9304",
    "sg:postcode":"L5T 1B4",
    "sg:province":"ON",
    "sg:tags":[
        "truck"
    ],
    "wof:name":"P L Truck Alignment Svc Ltd",
    "wof:placetype":"venue"
},
  "geometry": {"coordinates":[-79.647316,43.665985],"type":"Point"}
}