{
  "type": "Feature",
  "properties": {
    "addr:full":"Cp 1315 Succ Pl Bonaventure Montreal QC H5A 1H1",
    "addr:postcode":"1315;h5a 1h1",
    "addr:street":"Cp;Pl",
    "iso:country":"CA",
    "sg:address":"Cp 1315 Succ Pl Bonaventure",
    "sg:city":"Montreal",
    "sg:classifiers":[
        {
            "category":"Organizations",
            "subcategory":"Professional Association",
            "type":"Services"
        }
    ],
    "sg:phone":"+1 514 277 0228",
    "sg:postcode":"H5A 1H1",
    "sg:province":"QC",
    "wof:name":"Assn Quebecoise D'Urbanisme",
    "wof:placetype":"venue"
},
  "geometry": {"coordinates":[-73.566124,45.499641],"type":"Point"}
}