{
  "type": "Feature",
  "properties": {
    "addr:full":"Saanichton BC V8M 2B4",
    "addr:postcode":"v8m 2b4",
    "iso:country":"CA",
    "sg:city":"Saanichton",
    "sg:classifiers":[
        {
            "category":"Health Services",
            "subcategory":"Doctor",
            "type":"Services"
        }
    ],
    "sg:phone":"+1 250 652 9518",
    "sg:postcode":"V8M 2B4",
    "sg:province":"BC",
    "sg:tags":[
        "physician",
        "surgeon"
    ],
    "wof:name":"Kennedy, Richard MD",
    "wof:placetype":"venue"
},
  "geometry": {"coordinates":[-123.416687,48.594707],"type":"Point"}
}