{
  "type": "Feature",
  "properties": {
    "addr:full":"342 Ottawa Ave S Saskatoon SK S7M 3L7",
    "addr:housenumber":"342",
    "addr:postcode":"s7m 3l7",
    "addr:street":"Ottawa Ave S",
    "iso:country":"CA",
    "sg:address":"342 Ottawa Ave S",
    "sg:city":"Saskatoon",
    "sg:classifiers":[
        {
            "category":"Education",
            "subcategory":"School",
            "type":"Public Place"
        }
    ],
    "sg:phone":"+1 306 683 7510",
    "sg:postcode":"S7M 3L7",
    "sg:province":"SK",
    "wof:name":"W P Bate School",
    "wof:placetype":"venue"
},
  "geometry": {"coordinates":[-106.713066,52.125076],"type":"Point"}
}