{
  "type": "Feature",
  "properties": {
    "addr:full":"3189 Grandview Hwy Vancouver BC V5M 2E9",
    "addr:housenumber":"3189",
    "addr:postcode":"v5m 2e9",
    "addr:street":"Grandview Hwy",
    "iso:country":"CA",
    "sg:address":"3189 Grandview Hwy",
    "sg:city":"Vancouver",
    "sg:classifiers":[
        {
            "category":"Wholesale",
            "subcategory":"Groceries",
            "type":"Manufacturing & Wholesale Goods"
        }
    ],
    "sg:phone":"+1 604 439 5400",
    "sg:postcode":"V5M 2E9",
    "sg:province":"BC",
    "sg:tags":[
        "grocer"
    ],
    "wof:name":"Douglas Kelly & CO Ltd",
    "wof:placetype":"venue"
},
  "geometry": {"coordinates":[-123.037048,49.258305],"type":"Point"}
}