{
  "type": "Feature",
  "properties": {
    "addr:full":"Montreal QC H2Z 1Y6",
    "addr:postcode":"h2z 1y6",
    "iso:country":"CA",
    "sg:city":"Montreal",
    "sg:classifiers":[
        {
            "category":"Food & Beverages",
            "subcategory":"Groceries & Convenience Stores",
            "type":"Retail Goods"
        }
    ],
    "sg:phone":"+1 514 861 1008",
    "sg:postcode":"H2Z 1Y6",
    "sg:province":"QC",
    "sg:tags":[
        "grocer"
    ],
    "wof:name":"Sang Yuen CO",
    "wof:placetype":"venue"
},
  "geometry": {"coordinates":[-73.561302,45.507317],"type":"Point"}
}