{
  "type": "Feature",
  "properties": {
    "addr:full":"Markham ON L3R 6G2",
    "addr:postcode":"l3r 6g2",
    "iso:country":"CA",
    "sg:city":"Markham",
    "sg:classifiers":[
        {
            "category":"Professional",
            "subcategory":"Business Services",
            "type":"Services"
        }
    ],
    "sg:phone":"+1 905 415 1400",
    "sg:postcode":"L3R 6G2",
    "sg:province":"ON",
    "sg:tags":[
        "paralegal"
    ],
    "wof:name":"Acuminous Legal Svc",
    "wof:placetype":"venue"
},
  "geometry": {"coordinates":[-79.349052,43.814854],"type":"Point"}
}