{
  "type": "Feature",
  "properties": {
    "addr:full":"Burlington ON L7N 3G2",
    "addr:postcode":"l7n 3g2",
    "iso:country":"CA",
    "sg:city":"Burlington",
    "sg:classifiers":[
        {
            "category":"Shopping",
            "subcategory":"Clothing, Apparel, & Fashions",
            "type":"Retail Goods"
        }
    ],
    "sg:phone":"+1 905 319 1949",
    "sg:postcode":"L7N 3G2",
    "sg:province":"ON",
    "sg:tags":[
        "industrial",
        "glove"
    ],
    "wof:name":"Drollis Safety Supply CO Ltd",
    "wof:placetype":"venue"
},
  "geometry": {"coordinates":[-79.79174,43.36396],"type":"Point"}
}