{
  "type": "Feature",
  "properties": {
    "addr:full":"721 Boul Saint-Rene E Gatineau QC J8P 8A7",
    "addr:housenumber":"721",
    "addr:postcode":"j8p 8a7",
    "addr:street":"Boul Saint-Rene E",
    "iso:country":"CA",
    "sg:address":"721 Boul Saint-Rene E",
    "sg:city":"Gatineau",
    "sg:classifiers":[
        {
            "category":"Professional",
            "subcategory":"Accounting & Tax Preparation",
            "type":"Services"
        }
    ],
    "sg:phone":"+1 819 643 9898",
    "sg:postcode":"J8P 8A7",
    "sg:province":"QC",
    "sg:tags":[
        "accountant",
        "storage"
    ],
    "wof:name":"St-Rene Mini Entrepots",
    "wof:placetype":"venue"
},
  "geometry": {"coordinates":[-75.624084,45.498531],"type":"Point"}
}