{
  "type": "Feature",
  "properties": {
    "addr:full":"6 Hopperton Dr North York ON M2L 2S6",
    "addr:housenumber":"6",
    "addr:postcode":"m2l 2s6",
    "addr:street":"Hopperton Dr",
    "iso:country":"CA",
    "sg:address":"6 Hopperton Dr",
    "sg:city":"North York",
    "sg:classifiers":[
        {
            "category":"Manufacturing",
            "subcategory":"Metals",
            "type":"Manufacturing & Wholesale Goods"
        }
    ],
    "sg:phone":"+1 416 449 0696",
    "sg:postcode":"M2L 2S6",
    "sg:province":"ON",
    "sg:tags":[
        "door"
    ],
    "wof:name":"Door & Window Excellence Inc",
    "wof:placetype":"venue"
},
  "geometry": {"coordinates":[-79.3724517822,43.7643203735],"type":"Point"}
}