{
  "type": "Feature",
  "properties": {
    "addr:full":"2800 Hurricane Rd Fonthill ON L0S 1E0",
    "addr:housenumber":"2800",
    "addr:postcode":"l0s 1e0",
    "addr:street":"Hurricane Rd",
    "iso:country":"CA",
    "sg:address":"2800 Hurricane Rd",
    "sg:city":"Fonthill",
    "sg:classifiers":[
        {
            "category":"Home & Garden",
            "subcategory":"Garden Supply",
            "type":"Retail Goods"
        }
    ],
    "sg:phone":"+1 905 892 8773",
    "sg:postcode":"L0S 1E0",
    "sg:province":"ON",
    "sg:tags":[
        "nurseryman"
    ],
    "wof:name":"Barron's Flowers",
    "wof:placetype":"venue"
},
  "geometry": {"coordinates":[-79.2670288086,43.0499801636],"type":"Point"}
}