{
  "type": "Feature",
  "properties": {
    "addr:full":"76 Mcintyre Rd Schumacher ON P0N 1G0",
    "addr:housenumber":"76",
    "addr:postcode":"p0n 1g0",
    "addr:street":"Mcintyre Rd",
    "iso:country":"CA",
    "sg:address":"76 Mcintyre Rd",
    "sg:city":"Schumacher",
    "sg:classifiers":[
        {
            "category":"Government",
            "subcategory":"Office",
            "type":"Public Place"
        }
    ],
    "sg:phone":"+1 705 360 1700",
    "sg:postcode":"P0N 1G0",
    "sg:province":"ON",
    "wof:name":"Ontario Driver & Vehicle Agnts",
    "wof:placetype":"venue"
},
  "geometry": {"coordinates":[-81.29834700000001,48.476681],"type":"Point"}
}