{
  "type": "Feature",
  "properties": {
    "addr:full":"1348 Fall River Rd Fall River NS B2T 1E5",
    "addr:housenumber":"1348",
    "addr:postcode":"b2t 1e5",
    "addr:street":"Fall River Rd",
    "iso:country":"CA",
    "sg:address":"1348 Fall River Rd",
    "sg:city":"Fall River",
    "sg:classifiers":[
        {
            "category":"Shopping",
            "subcategory":"Used Merchandise",
            "type":"Retail Goods"
        }
    ],
    "sg:phone":"+1 902 860 2759",
    "sg:postcode":"B2T 1E5",
    "sg:province":"NS",
    "sg:tags":[
        "shop",
        "consignment"
    ],
    "wof:name":"Hidden Treasures Consignment",
    "wof:placetype":"venue"
},
  "geometry": {"coordinates":[-63.6168746948,44.8131370544],"type":"Point"}
}