{
  "type": "Feature",
  "properties": {
    "addr:full":"235 Donald St Ottawa ON K1K 1N1",
    "addr:housenumber":"235",
    "addr:postcode":"k1k 1n1",
    "addr:street":"Donald St",
    "iso:country":"CA",
    "sg:address":"235 Donald St",
    "sg:city":"Ottawa",
    "sg:classifiers":[
        {
            "category":"Organizations",
            "subcategory":"Professional Association",
            "type":"Services"
        }
    ],
    "sg:phone":"+1 613 744 2241",
    "sg:postcode":"K1K 1N1",
    "sg:province":"ON",
    "sg:tags":[
        "social",
        "welfare"
    ],
    "wof:name":"Association Pour L'Integration",
    "wof:placetype":"venue"
},
  "geometry": {"coordinates":[-75.65846252439999,45.4277572632],"type":"Point"}
}