{
  "type": "Feature",
  "properties": {
    "addr:full":"Toronto ON M4L 1H8",
    "addr:postcode":"m4l 1h8",
    "iso:country":"CA",
    "sg:city":"Toronto",
    "sg:classifiers":[
        {
            "category":"Shopping",
            "subcategory":"Jewelry",
            "type":"Retail Goods"
        }
    ],
    "sg:phone":"+1 416 690 1663",
    "sg:postcode":"M4L 1H8",
    "sg:province":"ON",
    "sg:tags":[
        "jeweler"
    ],
    "wof:name":"Artisanos",
    "wof:placetype":"venue"
},
  "geometry": {"coordinates":[-79.301331,43.669884],"type":"Point"}
}