{
  "type": "Feature",
  "properties": {
    "addr:full":"4830 63 Hwy North Bay ON P1B 8G4",
    "addr:housenumber":"4830",
    "addr:postcode":"p1b 8g4",
    "addr:street":"63 Hwy",
    "iso:country":"CA",
    "sg:address":"4830 63 Hwy",
    "sg:city":"North Bay",
    "sg:classifiers":[
        {
            "category":"Manufacturing",
            "subcategory":"Apparel",
            "type":"Manufacturing & Wholesale Goods"
        }
    ],
    "sg:phone":"+1 705 475 0006",
    "sg:postcode":"P1B 8G4",
    "sg:province":"ON",
    "sg:tags":[
        "awning",
        "top",
        "upholstery",
        "cover",
        "boat"
    ],
    "wof:name":"Alpine Canvas & Tops",
    "wof:placetype":"venue"
},
  "geometry": {"coordinates":[-79.3629074097,46.3313865662],"type":"Point"}
}