{
  "type": "Feature",
  "properties": {
    "addr:full":"Fort Macleod AB T0L 0Z0",
    "addr:postcode":"t0l 0z0",
    "addr:street":"Fort",
    "iso:country":"CA",
    "sg:city":"Fort Macleod",
    "sg:classifiers":[
        {
            "category":"Restaurant",
            "type":"Food & Drink"
        }
    ],
    "sg:phone":"+1 403 553 3011",
    "sg:postcode":"T0L 0Z0",
    "sg:province":"AB",
    "wof:name":"A & W Family Restaurant",
    "wof:placetype":"venue"
},
  "geometry": {"coordinates":[-113.401741,49.726284],"type":"Point"}
}