{
  "type": "Feature",
  "properties": {
    "addr:full":"1480 Birchmount Rd Scarborough ON M1P 2E3",
    "addr:housenumber":"1480",
    "addr:postcode":"m1p 2e3",
    "addr:street":"Birchmount Rd",
    "iso:country":"CA",
    "sg:address":"1480 Birchmount Rd",
    "sg:city":"Scarborough",
    "sg:classifiers":[
        {
            "category":"Manufacturing",
            "subcategory":"Tools & Machinery",
            "type":"Manufacturing & Wholesale Goods"
        }
    ],
    "sg:phone":"+1 416 757 2366",
    "sg:postcode":"M1P 2E3",
    "sg:province":"ON",
    "sg:tags":[
        "machine",
        "shop"
    ],
    "wof:name":"Magtron",
    "wof:placetype":"venue"
},
  "geometry": {"coordinates":[-79.288155,43.755199],"type":"Point"}
}