{
  "type": "Feature",
  "properties": {
    "addr:full":"Vancouver BC V5S 1Z1",
    "addr:postcode":"v5s 1z1",
    "iso:country":"CA",
    "sg:city":"Vancouver",
    "sg:classifiers":[
        {
            "category":"Health Services",
            "subcategory":"Doctor",
            "type":"Services"
        }
    ],
    "sg:phone":"+1 604 433 6800",
    "sg:postcode":"V5S 1Z1",
    "sg:province":"BC",
    "sg:tags":[
        "dentist"
    ],
    "wof:name":"Champ-Villa Dental Ctr",
    "wof:placetype":"venue"
},
  "geometry": {"coordinates":[-123.04016900000001,49.220043],"type":"Point"}
}