{
  "type": "Feature",
  "properties": {
    "addr:full":"600 Ch Avila Piedmont QC J0R 1R3",
    "addr:housenumber":"600",
    "addr:postcode":"j0r 1r3",
    "addr:street":"Ch Avila",
    "iso:country":"CA",
    "sg:address":"600 Ch Avila",
    "sg:city":"Piedmont",
    "sg:classifiers":[
        {
            "category":"Real Estate",
            "subcategory":"Real Estate Agent",
            "type":"Services"
        }
    ],
    "sg:phone":"+1 450 227 4671",
    "sg:postcode":"J0R 1R3",
    "sg:province":"QC",
    "wof:name":"Groupe Sutton-Laurentides",
    "wof:placetype":"venue"
},
  "geometry": {"coordinates":[-74.1384353638,45.8878097534],"type":"Point"}
}