{
  "type": "Feature",
  "properties": {
    "addr:full":"3077 Highway 69 N Val Caron ON P3N 1R8",
    "addr:housenumber":"3077",
    "addr:postcode":"p3n 1r8",
    "addr:street":"Highway 69 N",
    "iso:country":"CA",
    "sg:address":"3077 Highway 69 N",
    "sg:city":"Val Caron",
    "sg:classifiers":[
        {
            "category":"Banks & Credit Unions",
            "subcategory":"Bank",
            "type":"Services"
        }
    ],
    "sg:phone":"+1 705 897 6701",
    "sg:postcode":"P3N 1R8",
    "sg:province":"ON",
    "wof:name":"Caisses Populaire Val Caron",
    "wof:placetype":"venue"
},
  "geometry": {"coordinates":[-81.008644,46.610432],"type":"Point"}
}