{
  "type": "Feature",
  "properties": {
    "iso:country":"CA",
    "sg:address":"175 Spruce St",
    "sg:city":"Aurora",
    "sg:classifiers":[
        {
            "category":"Retail",
            "subcategory":"Auto Repair",
            "type":"Services"
        }
    ],
    "sg:phone":"+1 416 410 2634",
    "sg:postcode":"L4G 3T6",
    "sg:province":"ON",
    "sg:tags":[
        "lettering",
        "truck"
    ],
    "wof:name":"Graphic Detail Inc",
    "wof:placetype":"venue"
},
  "geometry": {"coordinates":[-79.46743,44.009827],"type":"Point"}
}