{
  "type": "Feature",
  "properties": {
    "addr:full":"175 Spruce St Aurora ON L4G 3T6",
    "addr:housenumber":"175",
    "addr:postcode":"l4g 3t6",
    "addr:street":"Spruce St",
    "iso:country":"CA",
    "sg:address":"175 Spruce St",
    "sg:city":"Aurora",
    "sg:classifiers":[
        {
            "category":"Retail",
            "subcategory":"Auto Repair",
            "type":"Services"
        }
    ],
    "sg:phone":"+1 416 410 2634",
    "sg:postcode":"L4G 3T6",
    "sg:province":"ON",
    "sg:tags":[
        "lettering",
        "truck"
    ],
    "wof:name":"Graphic Detail Inc",
    "wof:placetype":"venue"
},
  "geometry": {"coordinates":[-79.46742999999999,44.009827],"type":"Point"}
}