{
  "type": "Feature",
  "properties": {
    "addr:full":"1006 Massie Dr Prescott ON K0E 1T0",
    "addr:housenumber":"1006",
    "addr:postcode":"k0e 1t0",
    "addr:street":"Massie Dr",
    "iso:country":"CA",
    "sg:address":"1006 Massie Dr",
    "sg:city":"Prescott",
    "sg:classifiers":[
        {
            "category":"Building & Trades",
            "subcategory":"Electrical",
            "type":"Services"
        }
    ],
    "sg:phone":"+1 613 925 5866",
    "sg:postcode":"K0E 1T0",
    "sg:province":"ON",
    "sg:tags":[
        "electric",
        "contractor"
    ],
    "wof:name":"B W Freer Electrical Inc",
    "wof:placetype":"venue"
},
  "geometry": {"coordinates":[-75.517319,44.721985],"type":"Point"}
}