{
  "type": "Feature",
  "properties": {
    "addr:full":"64 Greenock Ave Scarborough ON M1G 2Z9",
    "addr:housenumber":"64",
    "addr:postcode":"m1g 2z9",
    "addr:street":"Greenock Ave",
    "iso:country":"CA",
    "sg:address":"64 Greenock Ave",
    "sg:city":"Scarborough",
    "sg:classifiers":[
        {
            "category":"Building & Trades",
            "subcategory":"Equipment Rental",
            "type":"Services"
        }
    ],
    "sg:phone":"+1 416 439 6000",
    "sg:postcode":"M1G 2Z9",
    "sg:province":"ON",
    "sg:tags":[
        "crane"
    ],
    "wof:name":"Ernest Crane & Hoist Erectors",
    "wof:placetype":"venue"
},
  "geometry": {"coordinates":[-79.2157287598,43.7738685608],"type":"Point"}
}