{
  "type": "Feature",
  "properties": {
    "addr:full":"PO Box 228 Donnelly AB T0H 1G0",
    "addr:housenumber":"po",
    "addr:postcode":"t0h 1g0",
    "addr:street":"Box 228 Donnelly",
    "iso:country":"CA",
    "sg:address":"PO Box 228",
    "sg:city":"Donnelly",
    "sg:classifiers":[
        {
            "category":"Professional",
            "type":"Services"
        }
    ],
    "sg:phone":"+1 780 925 3600",
    "sg:postcode":"T0H 1G0",
    "sg:province":"AB",
    "sg:tags":[
        "arranger",
        "music",
        "composer"
    ],
    "wof:name":"Frantex Record CO",
    "wof:placetype":"venue"
},
  "geometry": {"coordinates":[-117.10546100000001,55.731026],"type":"Point"}
}