{
  "type": "Feature",
  "properties": {
    "iso:country":"CA",
    "sg:address":"2909 Plymouth Dr",
    "sg:city":"Oakville",
    "sg:classifiers":[
        {
            "category":"Manufacturing",
            "subcategory":"Rubber & Plastics",
            "type":"Manufacturing & Wholesale Goods"
        }
    ],
    "sg:phone":"+1 905 855 8777",
    "sg:postcode":"L6H 6G7",
    "sg:province":"ON",
    "sg:tags":[
        "mold",
        "maker"
    ],
    "wof:name":"Fourmark Inc",
    "wof:placetype":"venue"
},
  "geometry": {"coordinates":[-79.67431640620001,43.5126609802],"type":"Point"}
}