{
  "type": "Feature",
  "properties": {
    "addr:full":"81 Merkley Sq Scarborough ON M1G 2Y5",
    "addr:housenumber":"81",
    "addr:postcode":"m1g 2y5",
    "addr:street":"Merkley Sq",
    "iso:country":"CA",
    "sg:address":"81 Merkley Sq",
    "sg:city":"Scarborough",
    "sg:classifiers":[
        {
            "category":"Professional",
            "subcategory":"Computer Services",
            "type":"Services"
        }
    ],
    "sg:phone":"+1 416 431 7230",
    "sg:postcode":"M1G 2Y5",
    "sg:province":"ON",
    "sg:tags":[
        "consultant"
    ],
    "wof:name":"Performance Tuning Inc",
    "wof:placetype":"venue"
},
  "geometry": {"coordinates":[-79.214218,43.773727],"type":"Point"}
}