{
  "type": "Feature",
  "properties": {
    "iso:country":"CA",
    "sg:city":"Markham",
    "sg:classifiers":[
        {
            "category":"Shopping",
            "subcategory":"Clothing, Apparel, & Fashions",
            "type":"Retail Goods"
        }
    ],
    "sg:phone":"+1 905 474 0538",
    "sg:postcode":"L3R 4M9",
    "sg:province":"ON",
    "sg:tags":[
        "infant",
        "wear"
    ],
    "wof:name":"Northern Getaway",
    "wof:placetype":"venue"
},
  "geometry": {"coordinates":[-79.3399429321,43.8560333252],"type":"Point"}
}