{
  "type": "Feature",
  "properties": {
    "addr:full":"11 Knightsbridge Rd Brampton ON L6T 3X4",
    "addr:housenumber":"11",
    "addr:postcode":"l6t 3x4",
    "addr:street":"Knightsbridge Rd",
    "iso:country":"CA",
    "sg:address":"11 Knightsbridge Rd",
    "sg:city":"Brampton",
    "sg:classifiers":[
        {
            "category":"Building & Trades",
            "subcategory":"Cleaning & Sanitation",
            "type":"Services"
        }
    ],
    "sg:phone":"+1 905 791 2859",
    "sg:postcode":"L6T 3X4",
    "sg:province":"ON",
    "sg:tags":[
        "property",
        "maintenance"
    ],
    "wof:name":"Cap Reit Inc",
    "wof:placetype":"venue"
},
  "geometry": {"coordinates":[-79.7158050537,43.7192192078],"type":"Point"}
}