{
  "type": "Feature",
  "properties": {
    "addr:full":"Repentigny QC J6A 4X6",
    "addr:postcode":"j6a 4x6",
    "iso:country":"CA",
    "sg:city":"Repentigny",
    "sg:classifiers":[
        {
            "category":"Personal",
            "subcategory":"Beauty Salon",
            "type":"Services"
        }
    ],
    "sg:phone":"+1 450 585 2647",
    "sg:postcode":"J6A 4X6",
    "sg:province":"QC",
    "wof:name":"Coiffure Tete DE Linotte Enr",
    "wof:placetype":"venue"
},
  "geometry": {"coordinates":[-73.44258880620001,45.7542228699],"type":"Point"}
}