{
  "type": "Feature",
  "properties": {
    "addr:full":"711 Kennedy Dr W Windsor ON N9G 1S8",
    "addr:housenumber":"711",
    "addr:postcode":"n9g 1s8",
    "addr:street":"Kennedy Dr W",
    "iso:country":"CA",
    "sg:address":"711 Kennedy Dr W",
    "sg:city":"Windsor",
    "sg:classifiers":[
        {
            "category":"Professional",
            "subcategory":"Accounting & Tax Preparation",
            "type":"Services"
        }
    ],
    "sg:phone":"+1 519 972 3030",
    "sg:postcode":"N9G 1S8",
    "sg:province":"ON",
    "sg:tags":[
        "accountant"
    ],
    "wof:name":"Gordon D Boggs Crt Gen Accnt",
    "wof:placetype":"venue"
},
  "geometry": {"coordinates":[-83.0077133179,42.2551612854],"type":"Point"}
}