{
  "type": "Feature",
  "properties": {
    "addr:full":"2 Leading Rd Etobicoke ON M9V 4B5",
    "addr:housenumber":"2",
    "addr:postcode":"m9v 4b5",
    "addr:street":"Leading Rd",
    "iso:country":"CA",
    "sg:address":"2 Leading Rd",
    "sg:city":"Etobicoke",
    "sg:classifiers":[
        {
            "category":"Building & Trades",
            "subcategory":"Construction",
            "type":"Services"
        }
    ],
    "sg:phone":"+1 416 749 2584",
    "sg:postcode":"M9V 4B5",
    "sg:province":"ON",
    "sg:tags":[
        "contractor",
        "paving",
        "general"
    ],
    "wof:name":"Atlas Paving CO",
    "wof:placetype":"venue"
},
  "geometry": {"coordinates":[-79.6077423096,43.750743866],"type":"Point"}
}