{
  "type": "Feature",
  "properties": {
    "addr:full":"5 Fourth Ave Badger NL A0H 1A0",
    "addr:housenumber":"5",
    "addr:postcode":"a0h 1a0",
    "addr:street":"Fourth Ave",
    "iso:country":"CA",
    "sg:address":"5 Fourth Ave",
    "sg:city":"Badger",
    "sg:classifiers":[
        {
            "category":"Organizations",
            "subcategory":"Religious Organization",
            "type":"Services"
        }
    ],
    "sg:phone":"+1 709 539 2692",
    "sg:postcode":"A0H 1A0",
    "sg:province":"NL",
    "sg:tags":[
        "church"
    ],
    "wof:name":"Full Gospel Pentecostal Church",
    "wof:placetype":"venue"
},
  "geometry": {"coordinates":[-56.0345420837,48.9806098938],"type":"Point"}
}