{
  "type": "Feature",
  "properties": {
    "addr:full":"Mississauga ON L4W 3C6",
    "addr:postcode":"l4w 3c6",
    "iso:country":"CA",
    "sg:city":"Mississauga",
    "sg:phone":"+1 905 565 7044",
    "sg:postcode":"L4W 3C6",
    "sg:province":"ON",
    "sg:tags":[
        "equipment",
        "station"
    ],
    "wof:name":"Servatronic Test Equipment Inc",
    "wof:placetype":"venue"
},
  "geometry": {"coordinates":[-79.64653,43.656513],"type":"Point"}
}