{
  "type": "Feature",
  "properties": {
    "addr:full":"2473 Boul Saint-Martin E # 208 Laval QC H7E 4X6",
    "addr:housenumber":"2473",
    "addr:postcode":"h7e 4x6",
    "addr:street":"Boul Saint-Martin E # 208",
    "iso:country":"CA",
    "sg:address":"2473 Boul Saint-Martin E # 208",
    "sg:city":"Laval",
    "sg:classifiers":[
        {
            "category":"Banks & Credit Unions",
            "subcategory":"Investment Brokerage",
            "type":"Services"
        }
    ],
    "sg:phone":"+1 450 668 2400",
    "sg:postcode":"H7E 4X6",
    "sg:province":"QC",
    "sg:tags":[
        "advisory",
        "financial"
    ],
    "wof:name":"Gestion Cote Gauthier",
    "wof:placetype":"venue"
},
  "geometry": {"coordinates":[-73.68469238279999,45.5988616943],"type":"Point"}
}