{
  "type": "Feature",
  "properties": {
    "addr:full":"136 Rue Marguerite-Bourgeoys Joliette QC J6E 4C1",
    "addr:housenumber":"136",
    "addr:postcode":"j6e 4c1",
    "addr:street":"Rue Marguerite-Bourgeoys",
    "iso:country":"CA",
    "sg:address":"136 Rue Marguerite-Bourgeoys",
    "sg:city":"Joliette",
    "sg:classifiers":[
        {
            "category":"Professional",
            "subcategory":"Engineering",
            "type":"Services"
        }
    ],
    "sg:phone":"+1 450 752 6555",
    "sg:postcode":"J6E 4C1",
    "sg:province":"QC",
    "sg:tags":[
        "engineer"
    ],
    "wof:name":"Lbha & Assoc",
    "wof:placetype":"venue"
},
  "geometry": {"coordinates":[-73.435196,46.018234],"type":"Point"}
}