{
  "type": "Feature",
  "properties": {
    "addr:full":"2269 Riverside Dr # 23 Ottawa ON K1H 8K2",
    "addr:housenumber":"2269",
    "addr:postcode":"k1h 8k2",
    "addr:street":"Riverside Dr # 23",
    "iso:country":"CA",
    "sg:address":"2269 Riverside Dr # 23",
    "sg:city":"Ottawa",
    "sg:classifiers":[
        {
            "category":"Personal",
            "subcategory":"Beauty Salon",
            "type":"Services"
        }
    ],
    "sg:phone":"+1 613 731 0323",
    "sg:postcode":"K1H 8K2",
    "sg:province":"ON",
    "wof:name":"Supreme Stylists",
    "wof:placetype":"venue"
},
  "geometry": {"coordinates":[-75.6797409058,45.3866271973],"type":"Point"}
}