{
  "type": "Feature",
  "properties": {
    "addr:full":"Saskatoon SK S7H 0S7",
    "addr:postcode":"s7h 0s7",
    "iso:country":"CA",
    "sg:city":"Saskatoon",
    "sg:classifiers":[
        {
            "category":"Restaurant",
            "type":"Food & Drink"
        }
    ],
    "sg:phone":"+1 306 956 3131",
    "sg:postcode":"S7H 0S7",
    "sg:province":"SK",
    "wof:name":"Peter D's on 8th",
    "wof:placetype":"venue"
},
  "geometry": {"coordinates":[-106.63803900000001,52.114906],"type":"Point"}
}