{
  "type": "Feature",
  "properties": {
    "iso:country":"CA",
    "sg:address":"2133 Heritage Dr",
    "sg:city":"Winfield",
    "sg:classifiers":[
        {
            "category":"Building & Trades",
            "subcategory":"Construction",
            "type":"Services"
        }
    ],
    "sg:phone":"+1 250 766 1758",
    "sg:postcode":"V4V 2L3",
    "sg:province":"BC",
    "sg:tags":[
        "railing"
    ],
    "wof:name":"Columbia Vinyldeck",
    "wof:placetype":"venue"
},
  "geometry": {"coordinates":[-119.405601502,50.0245361328],"type":"Point"}
}