{
  "type": "Feature",
  "properties": {
    "addr:full":"200 4 Ave S Lethbridge AB T1J 4C9",
    "addr:housenumber":"200",
    "addr:postcode":"t1j 4c9",
    "addr:street":"4 Ave S",
    "iso:country":"CA",
    "sg:address":"200 4 Ave S",
    "sg:city":"Lethbridge",
    "sg:classifiers":[
        {
            "category":"Shopping",
            "subcategory":"Clothing, Apparel, & Fashions",
            "type":"Retail Goods"
        }
    ],
    "sg:phone":"+1 403 329 1774",
    "sg:postcode":"T1J 4C9",
    "sg:province":"AB",
    "sg:tags":[
        "alteration"
    ],
    "wof:name":"Betty's Fashion Sewing",
    "wof:placetype":"venue"
},
  "geometry": {"coordinates":[-112.844367981,49.693977356],"type":"Point"}
}