{
  "type": "Feature",
  "properties": {
    "addr:full":"668 Sackville Dr Lower Sackville NS B4C 2S5",
    "addr:housenumber":"668",
    "addr:postcode":"b4c 2s5",
    "addr:street":"Sackville Dr",
    "iso:country":"CA",
    "sg:address":"668 Sackville Dr",
    "sg:city":"Lower Sackville",
    "sg:classifiers":[
        {
            "category":"Home & Garden",
            "subcategory":"Building Materials",
            "type":"Retail Goods"
        }
    ],
    "sg:phone":"+1 902 864 7333",
    "sg:postcode":"B4C 2S5",
    "sg:province":"NS",
    "sg:tags":[
        "paint"
    ],
    "wof:name":"C Weeks Contracting Ltd",
    "wof:placetype":"venue"
},
  "geometry": {"coordinates":[-63.689365,44.769917],"type":"Point"}
}