{
  "type": "Feature",
  "properties": {
    "iso:country":"CA",
    "sg:address":"450 8th Ave W",
    "sg:city":"Vancouver",
    "sg:classifiers":[
        {
            "category":"Restaurant",
            "type":"Food & Drink"
        }
    ],
    "sg:phone":"+1 604 739 7389",
    "sg:postcode":"V5Y 1N9",
    "sg:province":"BC",
    "wof:name":"Unforgettable Pizza & Pasta",
    "wof:placetype":"venue"
},
  "geometry": {"coordinates":[-123.113891602,49.2638168335],"type":"Point"}
}