{
  "type": "Feature",
  "properties": {
    "addr:full":"6245 Boul Metropolitain E Saint-Leonard QC H1P 1X7",
    "addr:housenumber":"6245",
    "addr:postcode":"h1p 1x7",
    "addr:street":"Boul Metropolitain E",
    "iso:country":"CA",
    "sg:address":"6245 Boul Metropolitain E",
    "sg:city":"Saint-Leonard",
    "sg:classifiers":[
        {
            "category":"Shopping",
            "subcategory":"Music",
            "type":"Retail Goods"
        }
    ],
    "sg:phone":"+1 514 321 0010",
    "sg:postcode":"H1P 1X7",
    "sg:province":"QC",
    "sg:tags":[
        "compact",
        "record",
        "disc",
        "tape"
    ],
    "wof:name":"Bass Mint Rec",
    "wof:placetype":"venue"
},
  "geometry": {"coordinates":[-73.58168792719999,45.5910415649],"type":"Point"}
}