{
  "type": "Feature",
  "properties": {
    "addr:full":"665 Oliver St Williams Lake BC V2G 1M8",
    "addr:housenumber":"665",
    "addr:postcode":"v2g 1m8",
    "addr:street":"Oliver St",
    "iso:country":"CA",
    "sg:address":"665 Oliver St",
    "sg:city":"Williams Lake",
    "sg:classifiers":[
        {
            "category":"Autos & Motor Vehicles",
            "subcategory":"Automobile Sales",
            "type":"Retail Goods"
        }
    ],
    "sg:phone":"+1 250 392 6828",
    "sg:postcode":"V2G 1M8",
    "sg:province":"BC",
    "sg:tags":[
        "renting",
        "car"
    ],
    "wof:name":"Ron Ridley Rentals Ltd",
    "wof:placetype":"venue"
},
  "geometry": {"coordinates":[-122.13621521,52.1282730103],"type":"Point"}
}