{
  "type": "Feature",
  "properties": {
    "addr:full":"421 Shepherdson Rd New Liskeard ON P0J 1P0",
    "addr:housenumber":"421",
    "addr:postcode":"p0j 1p0",
    "addr:street":"Shepherdson Rd",
    "iso:country":"CA",
    "sg:address":"421 Shepherdson Rd",
    "sg:city":"New Liskeard",
    "sg:classifiers":[
        {
            "category":"Health Services",
            "subcategory":"Doctor",
            "type":"Services"
        }
    ],
    "sg:phone":"+1 705 647 5405",
    "sg:postcode":"P0J 1P0",
    "sg:province":"ON",
    "sg:tags":[
        "physician",
        "surgeon"
    ],
    "wof:name":"Rahn, Raymond MD",
    "wof:placetype":"venue"
},
  "geometry": {"coordinates":[-79.6954498291,47.4953422546],"type":"Point"}
}