{
  "type": "Feature",
  "properties": {
    "addr:full":"North York ON M3J 3A4",
    "addr:postcode":"m3j 3a4",
    "iso:country":"CA",
    "sg:city":"North York",
    "sg:classifiers":[
        {
            "category":"Professional",
            "subcategory":"Accounting & Tax Preparation",
            "type":"Services"
        }
    ],
    "sg:phone":"+1 416 667 1616",
    "sg:postcode":"M3J 3A4",
    "sg:province":"ON",
    "sg:tags":[
        "accountant"
    ],
    "wof:name":"Steinberg & Schatzker",
    "wof:placetype":"venue"
},
  "geometry": {"coordinates":[-79.4937820435,43.7756462097],"type":"Point"}
}