{
  "type": "Feature",
  "properties": {
    "iso:country":"CA",
    "sg:address":"441 Second Ave W",
    "sg:city":"North Bay",
    "sg:classifiers":[
        {
            "category":"Building & Trades",
            "subcategory":"Construction",
            "type":"Services"
        }
    ],
    "sg:phone":"+1 705 474 4103",
    "sg:postcode":"P1B 3L4",
    "sg:province":"ON",
    "sg:tags":[
        "general",
        "contractor"
    ],
    "wof:name":"Sam's Cement Finishing",
    "wof:placetype":"venue"
},
  "geometry": {"coordinates":[-79.4633407593,46.3169174194],"type":"Point"}
}