{
  "type": "Feature",
  "properties": {
    "addr:full":"38 Grenfell St Happy Valley-Goose Bay NL A0P 1E0",
    "addr:housenumber":"38",
    "addr:postcode":"a0p 1e0",
    "addr:street":"Grenfell St",
    "iso:country":"CA",
    "sg:address":"38 Grenfell St",
    "sg:city":"Happy Valley-Goose Bay",
    "sg:classifiers":[
        {
            "category":"Organizations",
            "subcategory":"Professional Association",
            "type":"Services"
        }
    ],
    "sg:phone":"+1 709 896 4398",
    "sg:postcode":"A0P 1E0",
    "sg:province":"NL",
    "sg:tags":[
        "social",
        "welfare"
    ],
    "wof:name":"Aboriginal Family Ctr",
    "wof:placetype":"venue"
},
  "geometry": {"coordinates":[-60.310474,53.296951],"type":"Point"}
}