{
  "type": "Feature",
  "properties": {
    "addr:full":"2230 Ch Du Pays-Brule Nicolet-Sud QC J3T 1T5",
    "addr:postcode":"2230;j3t 1t5",
    "addr:street":"Ch Du Pays-Brule Nicolet-Sud",
    "iso:country":"CA",
    "sg:address":"2230 Ch Du Pays-Brule",
    "sg:city":"Nicolet-Sud",
    "sg:classifiers":[
        {
            "category":"Farming",
            "subcategory":"Farm",
            "type":"Manufacturing & Wholesale Goods"
        }
    ],
    "sg:phone":"+1 819 293 5275",
    "sg:postcode":"J3T 1T5",
    "sg:province":"QC",
    "wof:name":"Ferme Bernovain",
    "wof:placetype":"venue"
},
  "geometry": {"coordinates":[-72.622833,46.179703],"type":"Point"}
}