{
  "type": "Feature",
  "properties": {
    "addr:full":"6246 Glengate St Niagara Falls ON L2E 5S3",
    "addr:housenumber":"6246",
    "addr:postcode":"l2e 5s3",
    "addr:street":"Glengate St",
    "iso:country":"CA",
    "sg:address":"6246 Glengate St",
    "sg:city":"Niagara Falls",
    "sg:classifiers":[
        {
            "category":"Organizations",
            "subcategory":"Professional Association",
            "type":"Services"
        }
    ],
    "sg:phone":"+1 905 354 4881",
    "sg:postcode":"L2E 5S3",
    "sg:province":"ON",
    "sg:tags":[
        "club"
    ],
    "wof:name":"Kiwanis Club of Stamford",
    "wof:placetype":"venue"
},
  "geometry": {"coordinates":[-79.099197,43.109879],"type":"Point"}
}