{
  "type": "Feature",
  "properties": {
    "addr:full":"1 Dunns Rd Mount Pearl NL A1N 3L1",
    "addr:housenumber":"1",
    "addr:postcode":"a1n 3l1",
    "addr:street":"Dunns Rd",
    "iso:country":"CA",
    "sg:address":"1 Dunns Rd",
    "sg:city":"Mount Pearl",
    "sg:classifiers":[
        {
            "category":"Food & Beverages",
            "subcategory":"Groceries & Convenience Stores",
            "type":"Retail Goods"
        }
    ],
    "sg:phone":"+1 709 368 4346",
    "sg:postcode":"A1N 3L1",
    "sg:province":"NL",
    "wof:name":"Marie's Mini Mart",
    "wof:placetype":"venue"
},
  "geometry": {"coordinates":[-52.819725,47.516403],"type":"Point"}
}