{
  "type": "Feature",
  "properties": {
    "iso:country":"CA",
    "sg:address":"13655 Rue Du Blizzard",
    "sg:city":"Mirabel",
    "sg:classifiers":[
        {
            "category":"Personal",
            "subcategory":"Beauty Salon",
            "type":"Services"
        }
    ],
    "sg:phone":"+1 450 434 2039",
    "sg:postcode":"J7J 1T3",
    "sg:province":"QC",
    "wof:name":"Maison DE Coiffure Martine",
    "wof:placetype":"venue"
},
  "geometry": {"coordinates":[-74.0104598999,45.6634941101],"type":"Point"}
}