{
  "type": "Feature",
  "properties": {
    "iso:country":"CA",
    "sg:address":"10611 Rue J.-J.-Gagnier",
    "sg:city":"Montreal",
    "sg:classifiers":[
        {
            "category":"Health Services",
            "subcategory":"Optometrist",
            "type":"Services"
        }
    ],
    "sg:phone":"+1 514 384 9606",
    "sg:postcode":"H2B 3A3",
    "sg:province":"QC",
    "wof:name":"Lanouette, Guy OD",
    "wof:placetype":"venue"
},
  "geometry": {"coordinates":[-73.649307251,45.5810050964],"type":"Point"}
}