{
  "type": "Feature",
  "properties": {
    "addr:full":"745 Hammonds Plains Rd Bedford NS B4B 1A8",
    "addr:housenumber":"745",
    "addr:postcode":"b4b 1a8",
    "addr:street":"Hammonds Plains Rd",
    "iso:country":"CA",
    "sg:address":"745 Hammonds Plains Rd",
    "sg:city":"Bedford",
    "sg:classifiers":[
        {
            "category":"Farming",
            "subcategory":"Dairy Farm",
            "type":"Manufacturing & Wholesale Goods"
        }
    ],
    "sg:phone":"+1 902 742 2434",
    "sg:postcode":"B4B 1A8",
    "sg:province":"NS",
    "wof:name":"Farmers CO-Operative Dairy Ltd",
    "wof:placetype":"venue"
},
  "geometry": {"coordinates":[-63.716164,44.726021],"type":"Point"}
}