{
  "type": "Feature",
  "properties": {
    "addr:full":"Victoria BC V8Z 6S8",
    "addr:postcode":"v8z 6s8",
    "iso:country":"CA",
    "sg:city":"Victoria",
    "sg:classifiers":[
        {
            "category":"Building & Trades",
            "subcategory":"Equipment Rental",
            "type":"Services"
        }
    ],
    "sg:phone":"+1 250 383 5431",
    "sg:postcode":"V8Z 6S8",
    "sg:province":"BC",
    "sg:tags":[
        "party",
        "supply"
    ],
    "wof:name":"Gala-Van Party Shop",
    "wof:placetype":"venue"
},
  "geometry": {"coordinates":[-123.364517212,48.428314209],"type":"Point"}
}