{
  "type": "Feature",
  "properties": {
    "addr:full":"640 Old Sambro Rd Harrietsfield NS B3V 1A2",
    "addr:housenumber":"640",
    "addr:postcode":"b3v 1a2",
    "addr:street":"Old Sambro Rd",
    "iso:country":"CA",
    "sg:address":"640 Old Sambro Rd",
    "sg:city":"Harrietsfield",
    "sg:classifiers":[
        {
            "category":"Manufacturing",
            "subcategory":"Signs",
            "type":"Manufacturing & Wholesale Goods"
        }
    ],
    "sg:phone":"+1 902 477 4786",
    "sg:postcode":"B3V 1A2",
    "sg:province":"NS",
    "wof:name":"Brown's Quality Signs",
    "wof:placetype":"venue"
},
  "geometry": {"coordinates":[-63.6378211975,44.5873336792],"type":"Point"}
}