{
  "type": "Feature",
  "properties": {
    "addr:full":"478 Queen St E Sault Ste Marie ON P6A 1Z8",
    "addr:housenumber":"478",
    "addr:postcode":"p6a 1z8",
    "addr:street":"Queen St E",
    "iso:country":"CA",
    "sg:address":"478 Queen St E",
    "sg:city":"Sault Ste Marie",
    "sg:classifiers":[
        {
            "category":"Restaurant",
            "type":"Food & Drink"
        }
    ],
    "sg:phone":"+1 705 541 9999",
    "sg:postcode":"P6A 1Z8",
    "sg:province":"ON",
    "wof:name":"Tazzi's Cafe",
    "wof:placetype":"venue"
},
  "geometry": {"coordinates":[-84.3316497803,46.5106773376],"type":"Point"}
}