{
  "type": "Feature",
  "properties": {
    "addr:full":"1480 Carlton St Halifax NS B3H 3B7",
    "addr:housenumber":"1480",
    "addr:postcode":"b3h 3b7",
    "addr:street":"Carlton St",
    "iso:country":"CA",
    "sg:address":"1480 Carlton St",
    "sg:city":"Halifax",
    "sg:classifiers":[
        {
            "category":"Travel",
            "subcategory":"Travel Agent",
            "type":"Entertainment"
        }
    ],
    "sg:phone":"+1 902 421 0202",
    "sg:postcode":"B3H 3B7",
    "sg:province":"NS",
    "sg:tags":[
        "agency",
        "bureau"
    ],
    "wof:name":"Atlantic Explorer Travel Group",
    "wof:placetype":"venue"
},
  "geometry": {"coordinates":[-63.585133,44.640537],"type":"Point"}
}