{
  "type": "Feature",
  "properties": {
    "iso:country":"CA",
    "sg:address":"710 Tache Rue",
    "sg:city":"Saint-Pascal",
    "sg:classifiers":[
        {
            "category":"Organizations",
            "subcategory":"Professional Association",
            "type":"Services"
        }
    ],
    "sg:phone":"+1 418 492 1449",
    "sg:postcode":"G0L 3Y0",
    "sg:province":"QC",
    "sg:tags":[
        "social",
        "welfare"
    ],
    "wof:name":"Centre Femmes LA Passerelle",
    "wof:placetype":"venue"
},
  "geometry": {"coordinates":[-69.8018569946,47.5239601135],"type":"Point"}
}