{
  "type": "Feature",
  "properties": {
    "addr:full":"796 Hamilton Rd London ON N5Z 1V3",
    "addr:housenumber":"796",
    "addr:postcode":"n5z 1v3",
    "addr:street":"Hamilton Rd",
    "iso:country":"CA",
    "sg:address":"796 Hamilton Rd",
    "sg:city":"London",
    "sg:classifiers":[
        {
            "category":"Personal",
            "subcategory":"Shoe Repair & Shine",
            "type":"Services"
        }
    ],
    "sg:phone":"+1 519 451 7260",
    "sg:postcode":"N5Z 1V3",
    "sg:province":"ON",
    "sg:tags":[
        "repairing",
        "boot"
    ],
    "wof:name":"Ealing Shoe Repair",
    "wof:placetype":"venue"
},
  "geometry": {"coordinates":[-81.20251500000001,42.978981],"type":"Point"}
}