{
  "type": "Feature",
  "properties": {
    "addr:full":"4 Louis-Hebert St Rockland ON K4K 1K7",
    "addr:housenumber":"4",
    "addr:postcode":"k4k 1k7",
    "addr:street":"Louis-Hebert St",
    "iso:country":"CA",
    "sg:address":"4 Louis-Hebert St",
    "sg:city":"Rockland",
    "sg:classifiers":[
        {
            "category":"Building & Trades",
            "subcategory":"Construction",
            "type":"Services"
        }
    ],
    "sg:phone":"+1 613 446 7891",
    "sg:postcode":"K4K 1K7",
    "sg:province":"ON",
    "sg:tags":[
        "resurfacing",
        "laying",
        "refinishing",
        "floor"
    ],
    "wof:name":"Mel's Floor Sanding & Refinish",
    "wof:placetype":"venue"
},
  "geometry": {"coordinates":[-75.2475967407,45.5639724731],"type":"Point"}
}