{
  "type": "Feature",
  "properties": {
    "addr:full":"920 Mackay St Regina SK S4N 4X7",
    "addr:housenumber":"920",
    "addr:postcode":"s4n 4x7",
    "addr:street":"Mackay St",
    "iso:country":"CA",
    "sg:address":"920 Mackay St",
    "sg:city":"Regina",
    "sg:classifiers":[
        {
            "category":"Freight",
            "type":"Transportation"
        }
    ],
    "sg:phone":"+1 306 359 3222",
    "sg:postcode":"S4N 4X7",
    "sg:province":"SK",
    "sg:tags":[
        "trucking"
    ],
    "wof:name":"Reimer Express Lines Ltd",
    "wof:placetype":"venue"
},
  "geometry": {"coordinates":[-104.580772,50.46405],"type":"Point"}
}