{
  "type": "Feature",
  "properties": {
    "addr:full":"Dartmouth NS B3B 1S9",
    "addr:postcode":"b3b 1s9",
    "iso:country":"CA",
    "sg:city":"Dartmouth",
    "sg:classifiers":[
        {
            "category":"Wholesale",
            "subcategory":"Electrical",
            "type":"Manufacturing & Wholesale Goods"
        }
    ],
    "sg:phone":"+1 902 468 5851",
    "sg:postcode":"B3B 1S9",
    "sg:province":"NS",
    "sg:tags":[
        "equipment",
        "electric",
        "supply"
    ],
    "wof:name":"Wesco Distribution-Canada Inc",
    "wof:placetype":"venue"
},
  "geometry": {"coordinates":[-63.5833625793,44.6950492859],"type":"Point"}
}