{
  "type": "Feature",
  "properties": {
    "addr:full":"179 Kirby Ave Timmins ON P4N 1K1",
    "addr:housenumber":"179",
    "addr:postcode":"p4n 1k1",
    "addr:street":"Kirby Ave",
    "iso:country":"CA",
    "sg:address":"179 Kirby Ave",
    "sg:city":"Timmins",
    "sg:classifiers":[
        {
            "category":"Education",
            "subcategory":"School",
            "type":"Public Place"
        }
    ],
    "sg:phone":"+1 705 264 6510",
    "sg:postcode":"P4N 1K1",
    "sg:province":"ON",
    "wof:name":"Flora Mac Donald Public School",
    "wof:placetype":"venue"
},
  "geometry": {"coordinates":[-81.3306655884,48.4707984924],"type":"Point"}
}