{
  "type": "Feature",
  "properties": {
    "iso:country":"CA",
    "sg:address":"609 Boul Neptune",
    "sg:city":"Dorval",
    "sg:classifiers":[
        {
            "category":"Wholesale",
            "subcategory":"Machinery & Supplies",
            "type":"Manufacturing & Wholesale Goods"
        }
    ],
    "sg:phone":"+1 514 631 2079",
    "sg:postcode":"H9P 2A7",
    "sg:province":"QC",
    "sg:tags":[
        "equipment",
        "material",
        "truck",
        "handling"
    ],
    "wof:name":"Chariots Elevateurs Parents",
    "wof:placetype":"venue"
},
  "geometry": {"coordinates":[-73.775093,45.45282],"type":"Point"}
}