{
  "type": "Feature",
  "properties": {
    "addr:full":"132 Queen St S Hamilton ON L8P 3S2",
    "addr:housenumber":"132",
    "addr:postcode":"l8p 3s2",
    "addr:street":"Queen St S",
    "iso:country":"CA",
    "sg:address":"132 Queen St S",
    "sg:city":"Hamilton",
    "sg:classifiers":[
        {
            "category":"Restaurant",
            "type":"Food & Drink"
        }
    ],
    "sg:phone":"+1 905 528 6907",
    "sg:postcode":"L8P 3S2",
    "sg:province":"ON",
    "wof:name":"Nimmi's Restaurant",
    "wof:placetype":"venue"
},
  "geometry": {"coordinates":[-79.88059199999999,43.255337],"type":"Point"}
}