{
  "type": "Feature",
  "properties": {
    "addr:full":"15018 Longwoods Rd Bothwell ON N0P 1C0",
    "addr:housenumber":"15018",
    "addr:postcode":"n0p 1c0",
    "addr:street":"Longwoods Rd",
    "iso:country":"CA",
    "sg:address":"15018 Longwoods Rd",
    "sg:city":"Bothwell",
    "sg:classifiers":[
        {
            "category":"Retail",
            "subcategory":"Auto Repair",
            "type":"Services"
        }
    ],
    "sg:phone":"+1 519 695 6229",
    "sg:postcode":"N0P 1C0",
    "sg:province":"ON",
    "sg:tags":[
        "exchanging",
        "engine"
    ],
    "wof:name":"Lagace's Tall Oaks",
    "wof:placetype":"venue"
},
  "geometry": {"coordinates":[-81.89241,42.594429],"type":"Point"}
}