{
  "type": "Feature",
  "properties": {
    "addr:full":"210 Main St Unionville ON L3R 2G9",
    "addr:housenumber":"210",
    "addr:postcode":"l3r 2g9",
    "addr:street":"Main St",
    "iso:country":"CA",
    "sg:address":"210 Main St",
    "sg:city":"Unionville",
    "sg:classifiers":[
        {
            "category":"Recreation",
            "type":"Entertainment"
        }
    ],
    "sg:phone":"+1 905 475 8161",
    "sg:postcode":"L3R 2G9",
    "sg:province":"ON",
    "sg:tags":[
        "instruction",
        "swimming"
    ],
    "wof:name":"Markham Aquatic Club",
    "wof:placetype":"venue"
},
  "geometry": {"coordinates":[-79.3124465942,43.8685798645],"type":"Point"}
}