{
  "type": "Feature",
  "properties": {
    "addr:full":"394 10th St Hanover ON N4N 1P6",
    "addr:housenumber":"394",
    "addr:postcode":"n4n 1p6",
    "addr:street":"10Th St",
    "iso:country":"CA",
    "sg:address":"394 10th St",
    "sg:city":"Hanover",
    "sg:classifiers":[
        {
            "category":"Restaurant",
            "type":"Food & Drink"
        }
    ],
    "sg:phone":"+1 519 364 2600",
    "sg:postcode":"N4N 1P6",
    "sg:province":"ON",
    "wof:name":"Grey Rose Cafe Fine Dining",
    "wof:placetype":"venue"
},
  "geometry": {"coordinates":[-81.02469600000001,44.152676],"type":"Point"}
}