{
  "type": "Feature",
  "properties": {
    "addr:full":"Richmond Hill ON L4B 3A8",
    "addr:postcode":"l4b 3a8",
    "iso:country":"CA",
    "sg:city":"Richmond Hill",
    "sg:classifiers":[
        {
            "category":"Shopping",
            "subcategory":"Jewelry",
            "type":"Retail Goods"
        }
    ],
    "sg:phone":"+1 905 709 2422",
    "sg:postcode":"L4B 3A8",
    "sg:province":"ON",
    "sg:tags":[
        "jeweler"
    ],
    "wof:name":"New Century Designs Ltd",
    "wof:placetype":"venue"
},
  "geometry": {"coordinates":[-79.38646697999999,43.8453369141],"type":"Point"}
}