{
  "type": "Feature",
  "properties": {
    "addr:full":"311 Main St Geraldton ON P0T 1M0",
    "addr:housenumber":"311",
    "addr:postcode":"p0t 1m0",
    "addr:street":"Main St",
    "iso:country":"CA",
    "sg:address":"311 Main St",
    "sg:city":"Geraldton",
    "sg:classifiers":[
        {
            "category":"Shopping",
            "subcategory":"Clothing, Apparel, & Fashions",
            "type":"Retail Goods"
        }
    ],
    "sg:phone":"+1 807 854 1803",
    "sg:postcode":"P0T 1M0",
    "sg:province":"ON",
    "sg:tags":[
        "furnishing"
    ],
    "wof:name":"Rene's",
    "wof:placetype":"venue"
},
  "geometry": {"coordinates":[-86.94859313960001,49.7243003845],"type":"Point"}
}