{
  "type": "Feature",
  "properties": {
    "addr:full":"125 Railway Ave Meacham SK S0K 2V0",
    "addr:housenumber":"125",
    "addr:postcode":"s0k 2v0",
    "addr:street":"Railway Ave",
    "iso:country":"CA",
    "sg:address":"125 Railway Ave",
    "sg:city":"Meacham",
    "sg:classifiers":[
        {
            "category":"Wholesale",
            "subcategory":"Petroleum",
            "type":"Manufacturing & Wholesale Goods"
        }
    ],
    "sg:phone":"+1 306 376 2144",
    "sg:postcode":"S0K 2V0",
    "sg:province":"SK",
    "sg:tags":[
        "oil"
    ],
    "wof:name":"Meacham CO-OP",
    "wof:placetype":"venue"
},
  "geometry": {"coordinates":[-105.758911,52.107155],"type":"Point"}
}