{
  "type": "Feature",
  "properties": {
    "addr:full":"845 Main St E Milton ON L9T 3Z3",
    "addr:housenumber":"845",
    "addr:postcode":"l9t 3z3",
    "addr:street":"Main St E",
    "iso:country":"CA",
    "sg:address":"845 Main St E",
    "sg:city":"Milton",
    "sg:classifiers":[
        {
            "category":"Building & Trades",
            "subcategory":"Construction",
            "type":"Services"
        }
    ],
    "sg:phone":"+1 905 878 7087",
    "sg:postcode":"L9T 3Z3",
    "sg:province":"ON",
    "sg:tags":[
        "designer",
        "dealer",
        "pool",
        "swimming"
    ],
    "wof:name":"Halton Pool N' Spas",
    "wof:placetype":"venue"
},
  "geometry": {"coordinates":[-79.8699417114,43.5255737305],"type":"Point"}
}