{
  "type": "Feature",
  "properties": {
    "addr:full":"1200 Boul Henri-Bourassa O Montreal QC H3M 3G1",
    "addr:housenumber":"1200",
    "addr:postcode":"h3m 3g1",
    "addr:street":"Boul Henri-Bourassa O",
    "iso:country":"CA",
    "sg:address":"1200 Boul Henri-Bourassa O",
    "sg:city":"Montreal",
    "sg:classifiers":[
        {
            "category":"Government",
            "subcategory":"Office",
            "type":"Public Place"
        }
    ],
    "sg:phone":"+1 514 872 1376",
    "sg:postcode":"H3M 3G1",
    "sg:province":"QC",
    "sg:tags":[
        "village"
    ],
    "wof:name":"Montreal Eco-Ctr",
    "wof:placetype":"venue"
},
  "geometry": {"coordinates":[-73.67691000000001,45.539799],"type":"Point"}
}