{
  "type": "Feature",
  "properties": {
    "iso:country":"CA",
    "sg:address":"1200 Boul Henri-Bourassa O",
    "sg:city":"Montreal",
    "sg:classifiers":[
        {
            "category":"Government",
            "subcategory":"Office",
            "type":"Public Place"
        }
    ],
    "sg:phone":"+1 514 872 1376",
    "sg:postcode":"H3M 3G1",
    "sg:province":"QC",
    "sg:tags":[
        "village"
    ],
    "wof:name":"Montreal Eco-Ctr",
    "wof:placetype":"venue"
},
  "geometry": {"coordinates":[-73.67691,45.539799],"type":"Point"}
}