{
  "type": "Feature",
  "properties": {
    "addr:full":"3071 Riverside Dr Ottawa ON K1V 8W5",
    "addr:housenumber":"3071",
    "addr:postcode":"k1v 8w5",
    "addr:street":"Riverside Dr",
    "iso:country":"CA",
    "sg:address":"3071 Riverside Dr",
    "sg:city":"Ottawa",
    "sg:classifiers":[
        {
            "category":"Social Services",
            "subcategory":"Child Care",
            "type":"Services"
        }
    ],
    "sg:phone":"+1 613 521 4912",
    "sg:postcode":"K1V 8W5",
    "sg:province":"ON",
    "wof:name":"Bayview Kindergarten School",
    "wof:placetype":"venue"
},
  "geometry": {"coordinates":[-75.6880722046,45.3637123108],"type":"Point"}
}