{
  "type": "Feature",
  "properties": {
    "addr:full":"6770 65 Ave Red Deer AB T4P 1A5",
    "addr:housenumber":"6770",
    "addr:postcode":"t4p 1a5",
    "addr:street":"65 Ave",
    "iso:country":"CA",
    "sg:address":"6770 65 Ave",
    "sg:city":"Red Deer",
    "sg:classifiers":[
        {
            "category":"Manufacturing",
            "subcategory":"Tools & Machinery",
            "type":"Manufacturing & Wholesale Goods"
        }
    ],
    "sg:phone":"+1 403 342 4494",
    "sg:postcode":"T4P 1A5",
    "sg:province":"AB",
    "sg:tags":[
        "control",
        "equipment",
        "oil",
        "well",
        "supply"
    ],
    "wof:name":"Canalta Controls Ltd",
    "wof:placetype":"venue"
},
  "geometry": {"coordinates":[-113.841202,52.293602],"type":"Point"}
}