{
  "type": "Feature",
  "properties": {
    "iso:country":"CA",
    "sg:address":"PO Box 136",
    "sg:city":"Forest Grove",
    "sg:classifiers":[
        {
            "category":"Building & Trades",
            "subcategory":"Construction",
            "type":"Services"
        }
    ],
    "sg:phone":"+1 250 706 9060",
    "sg:postcode":"V0K 1M0",
    "sg:province":"BC",
    "sg:tags":[
        "downspouts",
        "gutter"
    ],
    "wof:name":"Northwest Gutters",
    "wof:placetype":"venue"
},
  "geometry": {"coordinates":[-121.173500061,51.7117919922],"type":"Point"}
}