{
  "type": "Feature",
  "properties": {
    "iso:country":"CA",
    "sg:address":"1473 Birmingham St",
    "sg:city":"Halifax",
    "sg:classifiers":[
        {
            "category":"Personal",
            "subcategory":"Beauty Salon",
            "type":"Services"
        }
    ],
    "sg:phone":"+1 902 422 1778",
    "sg:postcode":"B3J 2J4",
    "sg:province":"NS",
    "sg:tags":[
        "barber"
    ],
    "wof:name":"Kings Krown CO Ltd",
    "wof:placetype":"venue"
},
  "geometry": {"coordinates":[-63.5765342712,44.6427154541],"type":"Point"}
}