{
  "type": "Feature",
  "properties": {
    "addr:full":"431 Gowland Cres Milton ON L9T 4B9",
    "addr:housenumber":"431",
    "addr:postcode":"l9t 4b9",
    "addr:street":"Gowland Cres",
    "iso:country":"CA",
    "sg:address":"431 Gowland Cres",
    "sg:city":"Milton",
    "sg:classifiers":[
        {
            "category":"Professional",
            "subcategory":"Management & Consulting",
            "type":"Services"
        }
    ],
    "sg:phone":"+1 905 875 1795",
    "sg:postcode":"L9T 4B9",
    "sg:province":"ON",
    "sg:tags":[
        "marketing",
        "consultant"
    ],
    "wof:name":"Mc Marketing Enterprises",
    "wof:placetype":"venue"
},
  "geometry": {"coordinates":[-79.8638763428,43.5111351013],"type":"Point"}
}