{
  "type": "Feature",
  "properties": {
    "addr:full":"278 O'Connor St Ottawa ON K2P 1V4",
    "addr:housenumber":"278",
    "addr:postcode":"k2p 1v4",
    "addr:street":"O'Connor St",
    "iso:country":"CA",
    "sg:address":"278 O'Connor St",
    "sg:city":"Ottawa",
    "sg:classifiers":[
        {
            "category":"Health Services",
            "subcategory":"Doctor",
            "type":"Services"
        }
    ],
    "sg:phone":"+1 613 233 1565",
    "sg:postcode":"K2P 1V4",
    "sg:province":"ON",
    "sg:tags":[
        "physician",
        "surgeon"
    ],
    "wof:name":"Pytlak, Hanna MD",
    "wof:placetype":"venue"
},
  "geometry": {"coordinates":[-75.6988983154,45.4217605591],"type":"Point"}
}