{
  "type": "Feature",
  "properties": {
    "addr:full":"685 Av Orly Dorval QC H9P 1G1",
    "addr:housenumber":"685",
    "addr:postcode":"h9p 1g1",
    "addr:street":"Av Orly",
    "iso:country":"CA",
    "sg:address":"685 Av Orly",
    "sg:city":"Dorval",
    "sg:classifiers":[
        {
            "category":"Wholesale",
            "subcategory":"Machinery & Supplies",
            "type":"Manufacturing & Wholesale Goods"
        }
    ],
    "sg:phone":"+1 514 636 8323",
    "sg:postcode":"H9P 1G1",
    "sg:province":"QC",
    "sg:tags":[
        "machine",
        "tool"
    ],
    "wof:name":"Belmag Inc",
    "wof:placetype":"venue"
},
  "geometry": {"coordinates":[-73.73175000000001,45.455032],"type":"Point"}
}