{
  "type": "Feature",
  "properties": {
    "addr:full":"Timmins ON P4N 5Y4",
    "addr:postcode":"p4n 5y4",
    "iso:country":"CA",
    "sg:city":"Timmins",
    "sg:classifiers":[
        {
            "category":"Social Services",
            "type":"Services"
        }
    ],
    "sg:phone":"+1 705 268 8811",
    "sg:postcode":"P4N 5Y4",
    "sg:province":"ON",
    "sg:tags":[
        "organization",
        "welfare"
    ],
    "wof:name":"Community Living Timmins Intgr",
    "wof:placetype":"venue"
},
  "geometry": {"coordinates":[-81.3305358887,48.4882965088],"type":"Point"}
}