{
  "type": "Feature",
  "properties": {
    "addr:full":"713 Main St Moncton NB E1C 1E3",
    "addr:housenumber":"713",
    "addr:postcode":"e1c 1e3",
    "addr:street":"Main St",
    "iso:country":"CA",
    "sg:address":"713 Main St",
    "sg:city":"Moncton",
    "sg:classifiers":[
        {
            "category":"Professional",
            "subcategory":"Business Services",
            "type":"Services"
        }
    ],
    "sg:phone":"+1 506 861 6340",
    "sg:postcode":"E1C 1E3",
    "sg:province":"NB",
    "sg:tags":[
        "translator",
        "interpreter"
    ],
    "wof:name":"Alias Communications Inc",
    "wof:placetype":"venue"
},
  "geometry": {"coordinates":[-64.7767410278,46.088760376],"type":"Point"}
}