{
  "type": "Feature",
  "properties": {
    "addr:full":"7725 46 St SE Calgary AB T2C 2Y5",
    "addr:housenumber":"7725",
    "addr:postcode":"t2c 2y5",
    "addr:street":"46 St Se",
    "iso:country":"CA",
    "sg:address":"7725 46 St SE",
    "sg:city":"Calgary",
    "sg:classifiers":[
        {
            "category":"Wholesale",
            "subcategory":"Electrical",
            "type":"Manufacturing & Wholesale Goods"
        }
    ],
    "sg:phone":"+1 403 236 0580",
    "sg:postcode":"T2C 2Y5",
    "sg:province":"AB",
    "sg:tags":[
        "instrument"
    ],
    "wof:name":"Simark Controls Ltd",
    "wof:placetype":"venue"
},
  "geometry": {"coordinates":[-113.967285,50.984589],"type":"Point"}
}