{
  "type": "Feature",
  "properties": {
    "addr:full":"14 Farm Rd Howley NL A0K 3E0",
    "addr:housenumber":"14",
    "addr:postcode":"a0k 3e0",
    "addr:street":"Farm Rd",
    "iso:country":"CA",
    "sg:address":"14 Farm Rd",
    "sg:city":"Howley",
    "sg:classifiers":[
        {
            "category":"Shopping",
            "subcategory":"Computers & Home Electronics",
            "type":"Retail Goods"
        }
    ],
    "sg:phone":"+1 709 635 5323",
    "sg:postcode":"A0K 3E0",
    "sg:province":"NL",
    "sg:tags":[
        "equipment",
        "satellite",
        "system"
    ],
    "wof:name":"Satellite Tv",
    "wof:placetype":"venue"
},
  "geometry": {"coordinates":[-57.1140785217,49.1691818237],"type":"Point"}
}