{
  "type": "Feature",
  "properties": {
    "addr:full":"Burnaby BC V5G 4K6",
    "addr:postcode":"v5g 4k6",
    "iso:country":"CA",
    "sg:city":"Burnaby",
    "sg:classifiers":[
        {
            "category":"Organizations",
            "subcategory":"Labor Organization",
            "type":"Services"
        }
    ],
    "sg:phone":"+1 604 298 0200",
    "sg:postcode":"V5G 4K6",
    "sg:province":"BC",
    "wof:name":"Burnaby Civic Employees Union",
    "wof:placetype":"venue"
},
  "geometry": {"coordinates":[-122.97353363000001,49.2450294495],"type":"Point"}
}