{
  "type": "Feature",
  "properties": {
    "addr:full":"4585 Canada Way # 322 Burnaby BC V5G 4L6",
    "addr:housenumber":"4585",
    "addr:postcode":"v5g 4l6",
    "addr:street":"Canada Way # 322",
    "iso:country":"CA",
    "sg:address":"4585 Canada Way # 322",
    "sg:city":"Burnaby",
    "sg:classifiers":[
        {
            "category":"Recreation",
            "subcategory":"Arcade",
            "type":"Entertainment"
        }
    ],
    "sg:phone":"+1 604 294 8084",
    "sg:postcode":"V5G 4L6",
    "sg:province":"BC",
    "sg:tags":[
        "amusement",
        "devices"
    ],
    "wof:name":"Superstar Dragsters Inc",
    "wof:placetype":"venue"
},
  "geometry": {"coordinates":[-122.997337,49.254845],"type":"Point"}
}