{
  "type": "Feature",
  "properties": {
    "iso:country":"CA",
    "sg:city":"Winnipeg",
    "sg:classifiers":[
        {
            "category":"Retail",
            "subcategory":"Auto Rental",
            "type":"Services"
        }
    ],
    "sg:phone":"+1 204 831 4244",
    "sg:postcode":"R3K 2H7",
    "sg:province":"MB",
    "sg:tags":[
        "renting",
        "automobile"
    ],
    "wof:name":"A Enterprise Rent-A-Car",
    "wof:placetype":"venue"
},
  "geometry": {"coordinates":[-97.330574,49.880169],"type":"Point"}
}