{
  "type": "Feature",
  "properties": {
    "iso:country":"CA",
    "sg:address":"640 Memorial Ave",
    "sg:city":"Thunder Bay",
    "sg:classifiers":[
        {
            "category":"Autos & Motor Vehicles",
            "subcategory":"Automobile Sales",
            "type":"Retail Goods"
        }
    ],
    "sg:phone":"+1 807 344 9611",
    "sg:postcode":"P7B 3Z5",
    "sg:province":"ON",
    "sg:tags":[
        "car",
        "dealer"
    ],
    "wof:name":"Pinewood Ford Ltd",
    "wof:placetype":"venue"
},
  "geometry": {"coordinates":[-89.2416,48.41674],"type":"Point"}
}