{
  "type": "Feature",
  "properties": {
    "addr:full":"16419 117 Ave NW Edmonton AB T5M 3V3",
    "addr:housenumber":"16419",
    "addr:postcode":"t5m 3v3",
    "addr:street":"117 Ave Nw",
    "iso:country":"CA",
    "sg:address":"16419 117 Ave NW",
    "sg:city":"Edmonton",
    "sg:classifiers":[
        {
            "category":"Professional",
            "subcategory":"Management & Consulting",
            "type":"Services"
        }
    ],
    "sg:phone":"+1 780 452 9103",
    "sg:postcode":"T5M 3V3",
    "sg:province":"AB",
    "sg:tags":[
        "marketing",
        "mailing",
        "shipping",
        "consultant"
    ],
    "wof:name":"Penny Lane Communications Inc",
    "wof:placetype":"venue"
},
  "geometry": {"coordinates":[-113.604995727,53.5675926208],"type":"Point"}
}