{
  "type": "Feature",
  "properties": {
    "addr:full":"870 Westminster Ave Kamloops BC V2B 1N9",
    "addr:housenumber":"870",
    "addr:postcode":"bc v2b 1n9",
    "addr:street":"Westminster Ave",
    "iso:country":"CA",
    "sg:address":"870 Westminster Ave",
    "sg:city":"Kamloops",
    "sg:classifiers":[
        {
            "category":"Social Services",
            "type":"Services"
        }
    ],
    "sg:phone":"+1 250 376 0315",
    "sg:postcode":"V2B 1N9",
    "sg:province":"BC",
    "sg:tags":[
        "home",
        "senior",
        "retirement",
        "community",
        "citizen"
    ],
    "wof:name":"Shores Retirement Residence",
    "wof:placetype":"venue"
},
  "geometry": {"coordinates":[-120.365227,50.700909],"type":"Point"}
}