{
  "type": "Feature",
  "properties": {
    "addr:full":"Calgary AB T2G 3Z8",
    "addr:postcode":"t2g 3z8",
    "iso:country":"CA",
    "sg:city":"Calgary",
    "sg:classifiers":[
        {
            "category":"Retail",
            "subcategory":"Repair Shop",
            "type":"Services"
        }
    ],
    "sg:phone":"+1 403 243 6662",
    "sg:postcode":"T2G 3Z8",
    "sg:province":"AB",
    "sg:tags":[
        "plumbing",
        "fixture",
        "supply"
    ],
    "wof:name":"Amre Supply CO Ltd",
    "wof:placetype":"venue"
},
  "geometry": {"coordinates":[-114.05808258099999,51.0205307007],"type":"Point"}
}