{
  "type": "Feature",
  "properties": {
    "addr:full":"2242 Boul Des Chutes Beauport QC G1C 1W9",
    "addr:housenumber":"2242",
    "addr:postcode":"qc g1c 1w9",
    "addr:street":"Boul Des Chutes",
    "iso:country":"CA",
    "sg:address":"2242 Boul Des Chutes",
    "sg:city":"Beauport",
    "sg:classifiers":[
        {
            "category":"Personal",
            "subcategory":"Beauty Salon",
            "type":"Services"
        }
    ],
    "sg:phone":"+1 418 663 6199",
    "sg:postcode":"G1C 1W9",
    "sg:province":"QC",
    "wof:name":"Coiffure Richard Duclos",
    "wof:placetype":"venue"
},
  "geometry": {"coordinates":[-71.16015625,46.8816833496],"type":"Point"}
}