{
  "type": "Feature",
  "properties": {
    "addr:full":"21 Channel St Killarney ON P0M 2A0",
    "addr:housenumber":"21",
    "addr:postcode":"p0m 2a0",
    "addr:street":"Channel St",
    "iso:country":"CA",
    "sg:address":"21 Channel St",
    "sg:city":"Killarney",
    "sg:classifiers":[
        {
            "category":"Food & Beverages",
            "subcategory":"Meat & Fish",
            "type":"Retail Goods"
        }
    ],
    "sg:phone":"+1 705 287 2214",
    "sg:postcode":"P0M 2A0",
    "sg:province":"ON",
    "sg:tags":[
        "seafood"
    ],
    "wof:name":"Herbert's Fisheries",
    "wof:placetype":"venue"
},
  "geometry": {"coordinates":[-81.512215,45.97036],"type":"Point"}
}