{
  "type": "Feature",
  "properties": {
    "addr:full":"1003 Cn Towers Saskatoon SK S7K 1J5",
    "addr:housenumber":"1003 cn",
    "addr:postcode":"s7k 1j5",
    "iso:country":"CA",
    "sg:address":"1003 Cn Towers",
    "sg:city":"Saskatoon",
    "sg:classifiers":[
        {
            "category":"Professional",
            "subcategory":"Accounting & Tax Preparation",
            "type":"Services"
        }
    ],
    "sg:phone":"+1 306 933 2222",
    "sg:postcode":"S7K 1J5",
    "sg:province":"SK",
    "sg:tags":[
        "accountant"
    ],
    "wof:name":"Robinson, G W CA",
    "wof:placetype":"venue"
},
  "geometry": {"coordinates":[-106.61367,52.099373],"type":"Point"}
}