{
  "type": "Feature",
  "properties": {
    "addr:full":"Toronto ON M4Y 1H5",
    "addr:postcode":"m4y 1h5",
    "iso:country":"CA",
    "sg:city":"Toronto",
    "sg:classifiers":[
        {
            "category":"Real Estate",
            "subcategory":"Real Estate Operator",
            "type":"Services"
        }
    ],
    "sg:phone":"+1 416 924 1330",
    "sg:postcode":"M4Y 1H5",
    "sg:province":"ON",
    "sg:tags":[
        "apartment"
    ],
    "wof:name":"Greenwin Property Management",
    "wof:placetype":"venue"
},
  "geometry": {"coordinates":[-79.379166,43.666229],"type":"Point"}
}