{
  "type": "Feature",
  "properties": {
    "addr:full":"127 E Track St Revelstoke BC V0E 2S0",
    "addr:housenumber":"127",
    "addr:postcode":"v0e 2s0",
    "addr:street":"E Track St",
    "iso:country":"CA",
    "sg:address":"127 E Track St",
    "sg:city":"Revelstoke",
    "sg:classifiers":[
        {
            "category":"Railroad",
            "type":"Transportation"
        }
    ],
    "sg:phone":"+1 250 837 8253",
    "sg:postcode":"V0E 2S0",
    "sg:province":"BC",
    "wof:name":"Canadian Pacific Railway CO",
    "wof:placetype":"venue"
},
  "geometry": {"coordinates":[-118.19098700000001,50.998589],"type":"Point"}
}