{
  "type": "Feature",
  "properties": {
    "addr:full":"8 Stavebank Rd # 201 Mississauga ON L5G 2T4",
    "addr:housenumber":"8",
    "addr:postcode":"l5g 2t4",
    "addr:street":"Stavebank Rd # 201",
    "iso:country":"CA",
    "sg:address":"8 Stavebank Rd # 201",
    "sg:city":"Mississauga",
    "sg:classifiers":[
        {
            "category":"Health Services",
            "subcategory":"Health Practitioner",
            "type":"Services"
        }
    ],
    "sg:phone":"+1 905 278 7101",
    "sg:postcode":"L5G 2T4",
    "sg:province":"ON",
    "sg:tags":[
        "physiotherapist",
        "rehabilitation"
    ],
    "wof:name":"Physiotherapy & Beyond Ctr",
    "wof:placetype":"venue"
},
  "geometry": {"coordinates":[-79.609489,43.55843],"type":"Point"}
}