{
  "type": "Feature",
  "properties": {
    "iso:country":"CA",
    "sg:address":"67 High St W",
    "sg:city":"Moose Jaw",
    "sg:classifiers":[
        {
            "category":"Shopping",
            "subcategory":"Photographic Equipment",
            "type":"Retail Goods"
        }
    ],
    "sg:phone":"+1 306 694 5922",
    "sg:postcode":"S6H 1S4",
    "sg:province":"SK",
    "sg:tags":[
        "supply"
    ],
    "wof:name":"Moose Jaw Photo Depot",
    "wof:placetype":"venue"
},
  "geometry": {"coordinates":[-105.53636169400001,50.3914260864],"type":"Point"}
}