{
  "type": "Feature",
  "properties": {
    "addr:full":"1104 Av Saint-Louis Plessisville QC G6L 2M3",
    "addr:housenumber":"1104",
    "addr:postcode":"g6l 2m3",
    "addr:street":"Av Saint-Louis",
    "iso:country":"CA",
    "sg:address":"1104 Av Saint-Louis",
    "sg:city":"Plessisville",
    "sg:classifiers":[
        {
            "category":"Home & Garden",
            "subcategory":"Hardware",
            "type":"Retail Goods"
        }
    ],
    "sg:phone":"+1 819 362 6391",
    "sg:postcode":"G6L 2M3",
    "sg:province":"QC",
    "wof:name":"Centre DE Renovation Drolet",
    "wof:placetype":"venue"
},
  "geometry": {"coordinates":[-71.7653808594,46.2150421143],"type":"Point"}
}