{
  "type": "Feature",
  "properties": {
    "addr:full":"1305 Cawthra Rd Mississauga ON L5G 4L1",
    "addr:housenumber":"1305",
    "addr:postcode":"l5g 4l1",
    "addr:street":"Cawthra Rd",
    "iso:country":"CA",
    "sg:address":"1305 Cawthra Rd",
    "sg:city":"Mississauga",
    "sg:classifiers":[
        {
            "category":"Education",
            "subcategory":"School",
            "type":"Public Place"
        }
    ],
    "sg:phone":"+1 905 274 1271",
    "sg:postcode":"L5G 4L1",
    "sg:province":"ON",
    "wof:name":"Cawthra Park Secondary School",
    "wof:placetype":"venue"
},
  "geometry": {"coordinates":[-79.574562,43.575909],"type":"Point"}
}