{
  "type": "Feature",
  "properties": {
    "addr:full":"812 Woodpark Way SW Calgary AB T2W 2V8",
    "addr:housenumber":"812",
    "addr:postcode":"t2w 2v8",
    "addr:street":"Woodpark Way Sw",
    "iso:country":"CA",
    "sg:address":"812 Woodpark Way SW",
    "sg:city":"Calgary",
    "sg:classifiers":[
        {
            "category":"Wholesale",
            "subcategory":"Machinery & Supplies",
            "type":"Manufacturing & Wholesale Goods"
        }
    ],
    "sg:phone":"+1 403 692 0000",
    "sg:postcode":"T2W 2V8",
    "sg:province":"AB",
    "sg:tags":[
        "sheet",
        "metal",
        "working"
    ],
    "wof:name":"Fox Air Systems Inc",
    "wof:placetype":"venue"
},
  "geometry": {"coordinates":[-114.107834,50.944347],"type":"Point"}
}