{
  "type": "Feature",
  "properties": {
    "addr:full":"Toronto ON M5H 2G4",
    "addr:postcode":"m5h 2g4",
    "iso:country":"CA",
    "sg:city":"Toronto",
    "sg:classifiers":[
        {
            "category":"Professional",
            "subcategory":"Lawyer & Legal Services",
            "type":"Services"
        }
    ],
    "sg:phone":"+1 416 867 1010",
    "sg:postcode":"M5H 2G4",
    "sg:province":"ON",
    "sg:tags":[
        "attorney"
    ],
    "wof:name":"Kirby Lyon & Gatward",
    "wof:placetype":"venue"
},
  "geometry": {"coordinates":[-79.383835,43.650475],"type":"Point"}
}