{
  "type": "Feature",
  "properties": {
    "addr:full":"1126 Cluculz Ave Prince George BC V2M 4G2",
    "addr:housenumber":"1126",
    "addr:postcode":"v2m 4g2",
    "addr:street":"Cluculz Ave",
    "iso:country":"CA",
    "sg:address":"1126 Cluculz Ave",
    "sg:city":"Prince George",
    "sg:classifiers":[
        {
            "category":"Communications",
            "subcategory":"Film & Video Production",
            "type":"Services"
        }
    ],
    "sg:phone":"+1 250 612 0456",
    "sg:postcode":"V2M 4G2",
    "sg:province":"BC",
    "sg:tags":[
        "taping"
    ],
    "wof:name":"20-20 Video Productions",
    "wof:placetype":"venue"
},
  "geometry": {"coordinates":[-122.79892,53.914249],"type":"Point"}
}