{
  "type": "Feature",
  "properties": {
    "iso:country":"CA",
    "sg:address":"545 Van Horne Ave",
    "sg:city":"North York",
    "sg:classifiers":[
        {
            "category":"Government",
            "subcategory":"Office",
            "type":"Public Place"
        }
    ],
    "sg:phone":"+1 416 395 6006",
    "sg:postcode":"M2J 4S8",
    "sg:province":"ON",
    "sg:tags":[
        "village"
    ],
    "wof:name":"Pleasantview Community Ctr",
    "wof:placetype":"venue"
},
  "geometry": {"coordinates":[-79.3373718262,43.7873497009],"type":"Point"}
}