{
  "type": "Feature",
  "properties": {
    "addr:full":"5911 63 St Red Deer AB T4N 5N8",
    "addr:housenumber":"5911",
    "addr:postcode":"t4n 5n8",
    "addr:street":"63 St",
    "iso:country":"CA",
    "sg:address":"5911 63 St",
    "sg:city":"Red Deer",
    "sg:classifiers":[
        {
            "category":"Organizations",
            "subcategory":"Religious Organization",
            "type":"Services"
        }
    ],
    "sg:phone":"+1 403 346 6366",
    "sg:postcode":"T4N 5N8",
    "sg:province":"AB",
    "sg:tags":[
        "church"
    ],
    "wof:name":"Church of God Northside",
    "wof:placetype":"venue"
},
  "geometry": {"coordinates":[-113.827499,52.283943],"type":"Point"}
}