{
  "type": "Feature",
  "properties": {
    "addr:full":"1584 7th Ave # 2 Prince George BC V2L 3P4",
    "addr:housenumber":"1584",
    "addr:postcode":"v2l 3p4",
    "addr:street":"7Th Ave # 2",
    "iso:country":"CA",
    "sg:address":"1584 7th Ave # 2",
    "sg:city":"Prince George",
    "sg:classifiers":[
        {
            "category":"Government",
            "subcategory":"Office",
            "type":"Public Place"
        }
    ],
    "sg:phone":"+1 250 565 7077",
    "sg:postcode":"V2L 3P4",
    "sg:province":"BC",
    "wof:name":"B C Adult Forensic Psychiatric",
    "wof:placetype":"venue"
},
  "geometry": {"coordinates":[-122.75293000000001,53.915314],"type":"Point"}
}