{
  "type": "Feature",
  "properties": {
    "iso:country":"CA",
    "sg:address":"2164 Rte Marie-Victorin",
    "sg:city":"Varennes",
    "sg:classifiers":[
        {
            "category":"Autos & Motor Vehicles",
            "subcategory":"Automobile Sales",
            "type":"Retail Goods"
        }
    ],
    "sg:phone":"+1 450 652 3901",
    "sg:postcode":"J3X 1R4",
    "sg:province":"QC",
    "sg:tags":[
        "car",
        "dealer"
    ],
    "wof:name":"Chaput Automobile Inc",
    "wof:placetype":"venue"
},
  "geometry": {"coordinates":[-73.4376068115,45.6808128357],"type":"Point"}
}