{
  "type": "Feature",
  "properties": {
    "addr:full":"123 Bourget St Thurso QC J0X 3B0",
    "addr:housenumber":"123",
    "addr:postcode":"j0x 3b0",
    "addr:street":"Bourget St",
    "iso:country":"CA",
    "sg:address":"123 Bourget St",
    "sg:city":"Thurso",
    "sg:classifiers":[
        {
            "category":"Organizations",
            "subcategory":"Professional Association",
            "type":"Services"
        }
    ],
    "sg:phone":"+1 819 985 2883",
    "sg:postcode":"J0X 3B0",
    "sg:province":"QC",
    "wof:name":"Chevaliers DE Colomb Conseil",
    "wof:placetype":"venue"
},
  "geometry": {"coordinates":[-75.24049377439999,45.5990943909],"type":"Point"}
}