{
  "type": "Feature",
  "properties": {
    "iso:country":"CA",
    "sg:city":"Winnipeg",
    "sg:classifiers":[
        {
            "category":"Shopping",
            "subcategory":"Jewelry",
            "type":"Retail Goods"
        }
    ],
    "sg:phone":"+1 204 957 5994",
    "sg:postcode":"R3B 3H6",
    "sg:province":"MB",
    "sg:tags":[
        "jeweler"
    ],
    "wof:name":"City Jewellers",
    "wof:placetype":"venue"
},
  "geometry": {"coordinates":[-97.14073944090001,49.8994255066],"type":"Point"}
}