{
  "type": "Feature",
  "properties": {
    "addr:full":"Ange-Gardien QC J0E 1E0",
    "addr:postcode":"j0e 1e0",
    "addr:street":"Ange-Gardien",
    "iso:country":"CA",
    "sg:city":"Ange-Gardien",
    "sg:classifiers":[
        {
            "category":"Organizations",
            "subcategory":"Professional Association",
            "type":"Services"
        }
    ],
    "sg:phone":"+1 450 293 6162",
    "sg:postcode":"J0E 1E0",
    "sg:province":"QC",
    "wof:name":"Club DE L'Age D'Or",
    "wof:placetype":"venue"
},
  "geometry": {"coordinates":[-72.93498200000001,45.355572],"type":"Point"}
}