{
  "type": "Feature",
  "properties": {
    "addr:full":"1030 Queen St E Toronto ON M4M 1K4",
    "addr:housenumber":"1030",
    "addr:postcode":"m4m 1k4",
    "addr:street":"Queen St E",
    "iso:country":"CA",
    "sg:address":"1030 Queen St E",
    "sg:city":"Toronto",
    "sg:classifiers":[
        {
            "category":"Shopping",
            "subcategory":"Used Merchandise",
            "type":"Retail Goods"
        }
    ],
    "sg:phone":"+1 416 406 5192",
    "sg:postcode":"M4M 1K4",
    "sg:province":"ON",
    "sg:tags":[
        "pawnbroker"
    ],
    "wof:name":"Queen & Jones Pawnbroker",
    "wof:placetype":"venue"
},
  "geometry": {"coordinates":[-79.33841700000001,43.661583],"type":"Point"}
}