{
  "type": "Feature",
  "properties": {
    "addr:full":"1905 Main St Vancouver BC V5T 3C1",
    "addr:housenumber":"1905",
    "addr:postcode":"v5t 3c1",
    "addr:street":"Main St",
    "iso:country":"CA",
    "sg:address":"1905 Main St",
    "sg:city":"Vancouver",
    "sg:classifiers":[
        {
            "category":"Wholesale",
            "subcategory":"Machinery & Supplies",
            "type":"Manufacturing & Wholesale Goods"
        }
    ],
    "sg:phone":"+1 604 874 7455",
    "sg:postcode":"V5T 3C1",
    "sg:province":"BC",
    "sg:tags":[
        "salon",
        "beauty"
    ],
    "wof:name":"Breizh Salon Svc Ltd",
    "wof:placetype":"venue"
},
  "geometry": {"coordinates":[-123.10092163100001,49.2681083679],"type":"Point"}
}