{
  "type": "Feature",
  "properties": {
    "addr:full":"2100 Av DE Marlowe Montreal QC H4A 3L5",
    "addr:housenumber":"2100",
    "addr:postcode":"h4a 3l5",
    "addr:street":"Av De Marlowe",
    "iso:country":"CA",
    "sg:address":"2100 Av DE Marlowe",
    "sg:city":"Montreal",
    "sg:classifiers":[
        {
            "category":"Recreation",
            "type":"Entertainment"
        }
    ],
    "sg:phone":"+1 514 483 2022",
    "sg:postcode":"H4A 3L5",
    "sg:province":"QC",
    "sg:tags":[
        "center"
    ],
    "wof:name":"Consortium Therapeutic Rec",
    "wof:placetype":"venue"
},
  "geometry": {"coordinates":[-73.60623200000001,45.474472],"type":"Point"}
}