{
  "type": "Feature",
  "properties": {
    "addr:full":"12914 50 St NW Edmonton AB T5A 4L2",
    "addr:housenumber":"12914",
    "addr:postcode":"t5a 4l2",
    "addr:street":"50 St Nw",
    "iso:country":"CA",
    "sg:address":"12914 50 St NW",
    "sg:city":"Edmonton",
    "sg:classifiers":[
        {
            "category":"Restaurant",
            "type":"Food & Drink"
        }
    ],
    "sg:phone":"+1 780 414 6200",
    "sg:postcode":"T5A 4L2",
    "sg:province":"AB",
    "wof:name":"Queen Donair",
    "wof:placetype":"venue"
},
  "geometry": {"coordinates":[-113.41864,53.588024],"type":"Point"}
}