{
  "type": "Feature",
  "properties": {
    "addr:full":"1 South Branch Rd Cornwall ON K6K 1T3",
    "addr:housenumber":"1",
    "addr:postcode":"k6k 1t3",
    "addr:street":"South Branch Rd",
    "iso:country":"CA",
    "sg:address":"1 South Branch Rd",
    "sg:city":"Cornwall",
    "sg:classifiers":[
        {
            "category":"Wholesale",
            "subcategory":"Electrical",
            "type":"Manufacturing & Wholesale Goods"
        }
    ],
    "sg:phone":"+1 613 448 9090",
    "sg:postcode":"K6K 1T3",
    "sg:province":"ON",
    "sg:tags":[
        "control",
        "security",
        "system"
    ],
    "wof:name":"Adt Security Svc",
    "wof:placetype":"venue"
},
  "geometry": {"coordinates":[-74.764351,45.06282],"type":"Point"}
}