{
  "type": "Feature",
  "properties": {
    "addr:full":"North Vancouver BC V7M 1T4",
    "addr:postcode":"v7m 1t4",
    "iso:country":"CA",
    "sg:city":"North Vancouver",
    "sg:classifiers":[
        {
            "category":"Banks & Credit Unions",
            "subcategory":"Financial Services",
            "type":"Services"
        }
    ],
    "sg:phone":"+1 604 987 6525",
    "sg:postcode":"V7M 1T4",
    "sg:province":"BC",
    "sg:tags":[
        "company",
        "holding"
    ],
    "wof:name":"Goodwood Property Investments",
    "wof:placetype":"venue"
},
  "geometry": {"coordinates":[-123.073708,49.323296],"type":"Point"}
}