{
  "type": "Feature",
  "properties": {
    "addr:full":"2498 41st Ave W Vancouver BC V6M 2A7",
    "addr:housenumber":"2498",
    "addr:postcode":"v6m 2a7",
    "addr:street":"41St Ave W",
    "iso:country":"CA",
    "sg:address":"2498 41st Ave W",
    "sg:city":"Vancouver",
    "sg:classifiers":[
        {
            "category":"Manufacturing",
            "subcategory":"Metals",
            "type":"Manufacturing & Wholesale Goods"
        }
    ],
    "sg:phone":"+1 604 267 2457",
    "sg:postcode":"V6M 2A7",
    "sg:province":"BC",
    "sg:tags":[
        "mail",
        "courier"
    ],
    "wof:name":"Global Shipdepot",
    "wof:placetype":"venue"
},
  "geometry": {"coordinates":[-123.162514,49.234577],"type":"Point"}
}