{
  "type": "Feature",
  "properties": {
    "addr:full":"PO Box 1005 Lac LA Biche AB T0A 2C0",
    "addr:housenumber":"po",
    "addr:postcode":"t0a 2c0",
    "addr:street":"Box 1005 Lac La Biche",
    "iso:country":"CA",
    "sg:address":"PO Box 1005",
    "sg:city":"Lac LA Biche",
    "sg:classifiers":[
        {
            "category":"Manufacturing",
            "subcategory":"Lumber",
            "type":"Manufacturing & Wholesale Goods"
        }
    ],
    "sg:phone":"+1 780 623 2579",
    "sg:postcode":"T0A 2C0",
    "sg:province":"AB",
    "sg:tags":[
        "company",
        "logging"
    ],
    "wof:name":"Jaward Developments Ltd",
    "wof:placetype":"venue"
},
  "geometry": {"coordinates":[-111.97445678699999,54.77110672],"type":"Point"}
}