{
  "type": "Feature",
  "properties": {
    "iso:country":"CA",
    "sg:address":"2 Athabascan Ave",
    "sg:city":"Sherwood Park",
    "sg:classifiers":[
        {
            "category":"Shopping",
            "type":"Retail Goods"
        }
    ],
    "sg:phone":"+1 780 467 7869",
    "sg:postcode":"T8A 4E3",
    "sg:province":"AB",
    "sg:tags":[
        "picture",
        "framing"
    ],
    "wof:name":"Hall of Frame",
    "wof:placetype":"venue"
},
  "geometry": {"coordinates":[-113.32056427000001,53.5365600586],"type":"Point"}
}