{
  "type": "Feature",
  "properties": {
    "addr:full":"3204 Yonge St Toronto ON M4N 2L2",
    "addr:housenumber":"3204",
    "addr:postcode":"m4n 2l2",
    "addr:street":"Yonge St",
    "iso:country":"CA",
    "sg:address":"3204 Yonge St",
    "sg:city":"Toronto",
    "sg:classifiers":[
        {
            "category":"Banks & Credit Unions",
            "subcategory":"Investment Brokerage",
            "type":"Services"
        }
    ],
    "sg:phone":"+1 416 606 8808",
    "sg:postcode":"M4N 2L2",
    "sg:province":"ON",
    "sg:tags":[
        "retirement",
        "planning"
    ],
    "wof:name":"Berkshire Investment Group Inc",
    "wof:placetype":"venue"
},
  "geometry": {"coordinates":[-79.40310700000001,43.728348],"type":"Point"}
}