{
  "type": "Feature",
  "properties": {
    "addr:full":"215 Rue Principale O RR 2 Cacouna QC G0L 1G0",
    "addr:housenumber":"215",
    "addr:postcode":"g0l 1g0",
    "addr:street":"Rue Principale O Rr 2",
    "iso:country":"CA",
    "sg:address":"215 Rue Principale O RR 2",
    "sg:city":"Cacouna",
    "sg:classifiers":[
        {
            "category":"Retail",
            "subcategory":"Auto Repair",
            "type":"Services"
        }
    ],
    "sg:phone":"+1 418 862 4519",
    "sg:postcode":"G0L 1G0",
    "sg:province":"QC",
    "sg:tags":[
        "repairing",
        "automobile"
    ],
    "wof:name":"Garage Saindon Inc",
    "wof:placetype":"venue"
},
  "geometry": {"coordinates":[-69.50769805909999,47.909614563],"type":"Point"}
}