{
  "type": "Feature",
  "properties": {
    "addr:full":"4141 Yonge St North York ON M2P 2A8",
    "addr:housenumber":"4141",
    "addr:postcode":"m2p 2a8",
    "addr:street":"Yonge St",
    "iso:country":"CA",
    "sg:address":"4141 Yonge St",
    "sg:city":"North York",
    "sg:classifiers":[
        {
            "category":"Professional",
            "subcategory":"Management & Consulting",
            "type":"Services"
        }
    ],
    "sg:phone":"+1 416 512 9100",
    "sg:postcode":"M2P 2A8",
    "sg:province":"ON",
    "sg:tags":[
        "marketing",
        "consultant"
    ],
    "wof:name":"Hazelton Group Inc",
    "wof:placetype":"venue"
},
  "geometry": {"coordinates":[-79.40716552729999,43.7468986511],"type":"Point"}
}