{
  "type": "Feature",
  "properties": {
    "addr:full":"2355 Rue Beaubien E Montreal QC H2G 1N3",
    "addr:housenumber":"2355",
    "addr:postcode":"h2g 1n3",
    "addr:street":"Rue Beaubien E",
    "iso:country":"CA",
    "sg:address":"2355 Rue Beaubien E",
    "sg:city":"Montreal",
    "sg:classifiers":[
        {
            "category":"Food & Beverages",
            "subcategory":"Bakery",
            "type":"Retail Goods"
        }
    ],
    "sg:phone":"+1 514 722 4301",
    "sg:postcode":"H2G 1N3",
    "sg:province":"QC",
    "sg:tags":[
        "baker"
    ],
    "wof:name":"Froment & DE Seve",
    "wof:placetype":"venue"
},
  "geometry": {"coordinates":[-73.592789,45.547817],"type":"Point"}
}