{
  "type": "Feature",
  "properties": {
    "addr:full":"338 Boyne Ave W Morris MB R0G 1K0",
    "addr:housenumber":"338",
    "addr:postcode":"r0g 1k0",
    "addr:street":"Boyne Ave W",
    "iso:country":"CA",
    "sg:address":"338 Boyne Ave W",
    "sg:city":"Morris",
    "sg:classifiers":[
        {
            "category":"Retail",
            "subcategory":"Auto Repair",
            "type":"Services"
        }
    ],
    "sg:phone":"+1 204 746 6969",
    "sg:postcode":"R0G 1K0",
    "sg:province":"MB",
    "sg:tags":[
        "repairing",
        "automobile"
    ],
    "wof:name":"J C Auto Svc",
    "wof:placetype":"venue"
},
  "geometry": {"coordinates":[-97.366043,49.354687],"type":"Point"}
}