{
  "type": "Feature",
  "properties": {
    "iso:country":"CA",
    "sg:address":"283 St Rose Ave",
    "sg:city":"Windsor",
    "sg:classifiers":[
        {
            "category":"Organizations",
            "subcategory":"Religious Organization",
            "type":"Services"
        }
    ],
    "sg:phone":"+1 519 945 2280",
    "sg:postcode":"N8S 1X1",
    "sg:province":"ON",
    "sg:tags":[
        "church"
    ],
    "wof:name":"St Ignatius of Antioch Orthdx",
    "wof:placetype":"venue"
},
  "geometry": {"coordinates":[-82.95491790769999,42.3316726685],"type":"Point"}
}