{
  "type": "Feature",
  "properties": {
    "addr:full":"151 Esna Park Dr # 25 Markham ON L3R 3B1",
    "addr:housenumber":"151",
    "addr:postcode":"l3r 3b1",
    "addr:street":"Esna Park Dr # 25",
    "iso:country":"CA",
    "sg:address":"151 Esna Park Dr # 25",
    "sg:city":"Markham",
    "sg:classifiers":[
        {
            "category":"Building & Trades",
            "subcategory":"Plumbing",
            "type":"Services"
        }
    ],
    "sg:phone":"+1 905 415 5113",
    "sg:postcode":"L3R 3B1",
    "sg:province":"ON",
    "sg:tags":[
        "contractor"
    ],
    "wof:name":"Ready Rooter Plumbing & Drain",
    "wof:placetype":"venue"
},
  "geometry": {"coordinates":[-79.3391418457,43.8266716003],"type":"Point"}
}