{
  "type": "Feature",
  "properties": {
    "addr:full":"252 Manning Cross NW Edmonton AB T5A 5A1",
    "addr:housenumber":"252",
    "addr:postcode":"t5a 5a1",
    "addr:street":"Manning Cross Nw",
    "iso:country":"CA",
    "sg:address":"252 Manning Cross NW",
    "sg:city":"Edmonton",
    "sg:classifiers":[
        {
            "category":"Food & Beverages",
            "subcategory":"Liquor & Beverages",
            "type":"Retail Goods"
        }
    ],
    "sg:phone":"+1 780 476 7269",
    "sg:postcode":"T5A 5A1",
    "sg:province":"AB",
    "sg:tags":[
        "store"
    ],
    "wof:name":"Liquor Depot At Manning",
    "wof:placetype":"venue"
},
  "geometry": {"coordinates":[-113.514541626,53.4388313293],"type":"Point"}
}