{
  "type": "Feature",
  "properties": {
    "iso:country":"CA",
    "sg:address":"9696 199A St",
    "sg:city":"Langley",
    "sg:classifiers":[
        {
            "category":"Wholesale",
            "subcategory":"Groceries",
            "type":"Manufacturing & Wholesale Goods"
        }
    ],
    "sg:phone":"+1 604 888 8662",
    "sg:postcode":"V1M 2X7",
    "sg:province":"BC",
    "sg:tags":[
        "food",
        "product"
    ],
    "wof:name":"J D Sweid Ltd",
    "wof:placetype":"venue"
},
  "geometry": {"coordinates":[-122.65657043500001,49.1041221619],"type":"Point"}
}