{
  "type": "Feature",
  "properties": {
    "addr:full":"47 Boul Cartier Riviere-Du-Loup QC G5R 5Z3",
    "addr:housenumber":"47",
    "addr:postcode":"g5r 5z3",
    "addr:street":"Boul Cartier Riviere-Du-Loup",
    "iso:country":"CA",
    "sg:address":"47 Boul Cartier",
    "sg:city":"Riviere-Du-Loup",
    "sg:classifiers":[
        {
            "category":"Restaurant",
            "type":"Food & Drink"
        }
    ],
    "sg:phone":"+1 418 867 1649",
    "sg:postcode":"G5R 5Z3",
    "sg:province":"QC",
    "wof:name":"D'Amours Snack Bar",
    "wof:placetype":"venue"
},
  "geometry": {"coordinates":[-69.547791,47.857479],"type":"Point"}
}