{
  "type": "Feature",
  "properties": {
    "addr:full":"324 Rue Saint-Joseph Saint-Raymond QC G3L 1J7",
    "addr:housenumber":"324",
    "addr:postcode":"g3l 1j7",
    "addr:street":"Rue Saint-Joseph",
    "iso:country":"CA",
    "sg:address":"324 Rue Saint-Joseph",
    "sg:city":"Saint-Raymond",
    "sg:classifiers":[
        {
            "category":"Social Services",
            "type":"Services"
        }
    ],
    "sg:phone":"+1 418 337 4661",
    "sg:postcode":"G3L 1J7",
    "sg:province":"QC",
    "sg:tags":[
        "home",
        "welfare",
        "rest",
        "organization"
    ],
    "wof:name":"Centre D'Accueil St-Raymond",
    "wof:placetype":"venue"
},
  "geometry": {"coordinates":[-71.83307647709999,46.8902244568],"type":"Point"}
}