{
  "type": "Feature",
  "properties": {
    "iso:country":"CA",
    "sg:city":"Sarnia",
    "sg:classifiers":[
        {
            "category":"Shopping",
            "subcategory":"Musical Instruments",
            "type":"Retail Goods"
        }
    ],
    "sg:phone":"+1 519 336 3971",
    "sg:postcode":"N7T 7V3",
    "sg:province":"ON",
    "sg:tags":[
        "piano"
    ],
    "wof:name":"Jack Kennedy's Music Ctr",
    "wof:placetype":"venue"
},
  "geometry": {"coordinates":[-82.405907,42.97506],"type":"Point"}
}