{
  "type": "Feature",
  "properties": {
    "iso:country":"CA",
    "sg:address":"739 101 Rte N",
    "sg:city":"Duhamel-Ouest",
    "sg:classifiers":[
        {
            "category":"Manufacturing",
            "subcategory":"Signs",
            "type":"Manufacturing & Wholesale Goods"
        }
    ],
    "sg:phone":"+1 819 629 2100",
    "sg:postcode":"J9V 2E2",
    "sg:province":"QC",
    "wof:name":"Andre Gauthier Lettrage",
    "wof:placetype":"venue"
},
  "geometry": {"coordinates":[-79.4127578735,47.3374214172],"type":"Point"}
}