{
  "type": "Feature",
  "properties": {
    "addr:full":"9805 Boul Louis-H.-Lafontaine Anjou QC H1J 2A3",
    "addr:housenumber":"9805",
    "addr:postcode":"h1j 2a3",
    "addr:street":"Boul Louis-H.-Lafontaine",
    "iso:country":"CA",
    "sg:address":"9805 Boul Louis-H.-Lafontaine",
    "sg:city":"Anjou",
    "sg:classifiers":[
        {
            "category":"Professional",
            "subcategory":"Business Services",
            "type":"Services"
        }
    ],
    "sg:phone":"+1 514 354 1112",
    "sg:postcode":"H1J 2A3",
    "sg:province":"QC",
    "sg:tags":[
        "packaging"
    ],
    "wof:name":"Ready Pak",
    "wof:placetype":"venue"
},
  "geometry": {"coordinates":[-73.5786514282,45.6106491089],"type":"Point"}
}