{
  "type": "Feature",
  "properties": {
    "addr:full":"Winnipeg MB R3B 3K6",
    "addr:postcode":"r3b 3k6",
    "iso:country":"CA",
    "sg:city":"Winnipeg",
    "sg:classifiers":[
        {
            "category":"Restaurant",
            "type":"Food & Drink"
        }
    ],
    "sg:phone":"+1 204 956 0303",
    "sg:postcode":"R3B 3K6",
    "sg:province":"MB",
    "wof:name":"Dee's Chicken",
    "wof:placetype":"venue"
},
  "geometry": {"coordinates":[-97.13913700000001,49.895382],"type":"Point"}
}