{
  "type": "Feature",
  "properties": {
    "addr:full":"8545 Hemlock St Youbou BC V0R 3E1",
    "addr:housenumber":"8545",
    "addr:postcode":"v0r 3e1",
    "addr:street":"Hemlock St",
    "iso:country":"CA",
    "sg:address":"8545 Hemlock St",
    "sg:city":"Youbou",
    "sg:classifiers":[
        {
            "category":"Education",
            "subcategory":"School",
            "type":"Public Place"
        }
    ],
    "sg:phone":"+1 250 745 6621",
    "sg:postcode":"V0R 3E1",
    "sg:province":"BC",
    "wof:name":"Yount Elementary School",
    "wof:placetype":"venue"
},
  "geometry": {"coordinates":[-124.21421100000001,48.87529],"type":"Point"}
}