{
  "type": "Feature",
  "properties": {
    "addr:full":"476 Ch DE Hatley O Magog QC J1X 3G4",
    "addr:housenumber":"476",
    "addr:postcode":"j1x 3g4",
    "addr:street":"Ch De Hatley O",
    "iso:country":"CA",
    "sg:address":"476 Ch DE Hatley O",
    "sg:city":"Magog",
    "sg:classifiers":[
        {
            "category":"Food & Beverages",
            "subcategory":"Groceries & Convenience Stores",
            "type":"Retail Goods"
        }
    ],
    "sg:phone":"+1 819 843 2992",
    "sg:postcode":"J1X 3G4",
    "sg:province":"QC",
    "sg:tags":[
        "grocer"
    ],
    "wof:name":"Epicerie Lussier Inc",
    "wof:placetype":"venue"
},
  "geometry": {"coordinates":[-72.14357800000001,45.258682],"type":"Point"}
}