{
  "type": "Feature",
  "properties": {
    "addr:full":"2036 42 Ave SW Calgary AB T2T 2M7",
    "addr:housenumber":"2036",
    "addr:postcode":"t2t 2m7",
    "addr:street":"42 Ave Sw",
    "iso:country":"CA",
    "sg:address":"2036 42 Ave SW",
    "sg:city":"Calgary",
    "sg:classifiers":[
        {
            "category":"Health Services",
            "subcategory":"Clinic",
            "type":"Services"
        }
    ],
    "sg:phone":"+1 403 287 2991",
    "sg:postcode":"T2T 2M7",
    "sg:province":"AB",
    "sg:tags":[
        "information",
        "program",
        "herbalist",
        "referral"
    ],
    "wof:name":"Cobblestone Health Ltd",
    "wof:placetype":"venue"
},
  "geometry": {"coordinates":[-114.107429504,51.0161437988],"type":"Point"}
}