{
  "type": "Feature",
  "properties": {
    "iso:country":"CA",
    "sg:address":"5534 Rue Des Erables",
    "sg:city":"Saint-Emile",
    "sg:classifiers":[
        {
            "category":"Personal",
            "subcategory":"Beauty Salon",
            "type":"Services"
        }
    ],
    "sg:phone":"+1 418 847 3566",
    "sg:postcode":"G3E 1H4",
    "sg:province":"QC",
    "wof:name":"Esthetique L'Air Du Temps",
    "wof:placetype":"venue"
},
  "geometry": {"coordinates":[-71.33708190919999,46.8712081909],"type":"Point"}
}