{
  "type": "Feature",
  "properties": {
    "addr:full":"10 Ormond St N Thorold ON L2V 1Y7",
    "addr:housenumber":"10",
    "addr:postcode":"l2v 1y7",
    "addr:street":"Ormond St N",
    "iso:country":"CA",
    "sg:address":"10 Ormond St N",
    "sg:city":"Thorold",
    "sg:classifiers":[
        {
            "category":"Health Services",
            "subcategory":"Nursing And Care Facility",
            "type":"Services"
        }
    ],
    "sg:phone":"+1 905 227 5550",
    "sg:postcode":"L2V 1Y7",
    "sg:province":"ON",
    "sg:tags":[
        "home",
        "retirement",
        "community"
    ],
    "wof:name":"Chestnut Court Retirement Home",
    "wof:placetype":"venue"
},
  "geometry": {"coordinates":[-79.1988449097,43.125541687],"type":"Point"}
}