{
  "type": "Feature",
  "properties": {
    "iso:country":"CA",
    "sg:address":"450 King St E",
    "sg:city":"Cambridge",
    "sg:classifiers":[
        {
            "category":"Social Services",
            "subcategory":"Child Care",
            "type":"Services"
        }
    ],
    "sg:phone":"+1 519 653 5700",
    "sg:postcode":"N3H 3M9",
    "sg:province":"ON",
    "wof:name":"All in A Days Play Child Care",
    "wof:placetype":"venue"
},
  "geometry": {"coordinates":[-80.361671,43.397381],"type":"Point"}
}