{
  "type": "Feature",
  "properties": {
    "addr:full":"475 Av Du President-Kennedy Montreal QC H3A 1J7",
    "addr:housenumber":"475",
    "addr:postcode":"h3a 1j7",
    "addr:street":"Av Du President-Kennedy",
    "iso:country":"CA",
    "sg:address":"475 Av Du President-Kennedy",
    "sg:city":"Montreal",
    "sg:classifiers":[
        {
            "category":"Travel",
            "subcategory":"Hotels & Motels",
            "type":"Entertainment"
        }
    ],
    "sg:phone":"+1 514 286 1986",
    "sg:postcode":"H3A 1J7",
    "sg:province":"QC",
    "wof:name":"Delta Montreal",
    "wof:placetype":"venue"
},
  "geometry": {"coordinates":[-73.5707321167,45.5063323975],"type":"Point"}
}