{
  "type": "Feature",
  "properties": {
    "addr:full":"91 Wellington St London ON N6B 2K5",
    "addr:housenumber":"91",
    "addr:postcode":"n6b 2k5",
    "addr:street":"Wellington St",
    "iso:country":"CA",
    "sg:address":"91 Wellington St",
    "sg:city":"London",
    "sg:classifiers":[
        {
            "category":"Restaurant",
            "type":"Food & Drink"
        }
    ],
    "sg:phone":"+1 519 433 6260",
    "sg:postcode":"N6B 2K5",
    "sg:province":"ON",
    "sg:tags":[
        "delicatessen"
    ],
    "wof:name":"K's Place",
    "wof:placetype":"venue"
},
  "geometry": {"coordinates":[-81.24067700000001,42.975529],"type":"Point"}
}