{
  "type": "Feature",
  "properties": {
    "addr:full":"Saskatoon SK S7H 0W2",
    "addr:postcode":"s7h 0w2",
    "iso:country":"CA",
    "sg:city":"Saskatoon",
    "sg:classifiers":[
        {
            "category":"Food & Beverages",
            "subcategory":"Liquor & Beverages",
            "type":"Retail Goods"
        }
    ],
    "sg:phone":"+1 306 933 5318",
    "sg:postcode":"S7H 0W2",
    "sg:province":"SK",
    "sg:tags":[
        "store"
    ],
    "wof:name":"Liquor Board Stores",
    "wof:placetype":"venue"
},
  "geometry": {"coordinates":[-106.606133,52.114521],"type":"Point"}
}