{
  "type": "Feature",
  "properties": {
    "addr:full":"14004 95 Ave NW Edmonton AB T5N 0A1",
    "addr:housenumber":"14004",
    "addr:postcode":"t5n 0a1",
    "addr:street":"95 Ave Nw",
    "iso:country":"CA",
    "sg:address":"14004 95 Ave NW",
    "sg:city":"Edmonton",
    "sg:classifiers":[
        {
            "category":"Banks & Credit Unions",
            "subcategory":"Investment Brokerage",
            "type":"Services"
        }
    ],
    "sg:phone":"+1 780 451 0314",
    "sg:postcode":"T5N 0A1",
    "sg:province":"AB",
    "wof:name":"Roland Stefan & CO Ltd",
    "wof:placetype":"venue"
},
  "geometry": {"coordinates":[-113.561684,53.53215],"type":"Point"}
}