{
  "type": "Feature",
  "properties": {
    "addr:full":"200 Saskatchewan Ave W Portage LA Prairie MB R1N 0M2",
    "addr:housenumber":"200",
    "addr:postcode":"r1n 0m2",
    "addr:street":"Saskatchewan Ave W",
    "iso:country":"CA",
    "sg:address":"200 Saskatchewan Ave W",
    "sg:city":"Portage LA Prairie",
    "sg:classifiers":[
        {
            "category":"Restaurant",
            "type":"Food & Drink"
        }
    ],
    "sg:phone":"+1 204 857 6047",
    "sg:postcode":"R1N 0M2",
    "sg:province":"MB",
    "sg:tags":[
        "parlor",
        "ice",
        "cream"
    ],
    "wof:name":"Dairy Queen",
    "wof:placetype":"venue"
},
  "geometry": {"coordinates":[-98.293762207,49.9733505249],"type":"Point"}
}