{
  "type": "Feature",
  "properties": {
    "iso:country":"CA",
    "sg:address":"1050 125 Rte",
    "sg:city":"Sainte-Julienne",
    "sg:classifiers":[
        {
            "category":"Home & Garden",
            "subcategory":"Garden Supply",
            "type":"Retail Goods"
        }
    ],
    "sg:phone":"+1 450 831 2583",
    "sg:postcode":"J0K 2T0",
    "sg:province":"QC",
    "sg:tags":[
        "nurseryman"
    ],
    "wof:name":"Pepiniere 1050 Ds Enr",
    "wof:placetype":"venue"
},
  "geometry": {"coordinates":[-73.7034912109,45.9536552429],"type":"Point"}
}