{
  "type": "Feature",
  "properties": {
    "addr:full":"Burnaby BC V5C 2H9",
    "addr:postcode":"v5c 2h9",
    "iso:country":"CA",
    "sg:city":"Burnaby",
    "sg:classifiers":[
        {
            "category":"Health Services",
            "subcategory":"Medical Lab",
            "type":"Services"
        }
    ],
    "sg:phone":"+1 604 294 6911",
    "sg:postcode":"V5C 2H9",
    "sg:province":"BC",
    "wof:name":"Francisco Gino Interprise",
    "wof:placetype":"venue"
},
  "geometry": {"coordinates":[-123.015739,49.280865],"type":"Point"}
}