{
  "type": "Feature",
  "properties": {
    "addr:full":"170 Broadway St Tillsonburg ON N4G 5A8",
    "addr:housenumber":"170",
    "addr:postcode":"n4g 5a8",
    "addr:street":"Broadway St",
    "iso:country":"CA",
    "sg:address":"170 Broadway St",
    "sg:city":"Tillsonburg",
    "sg:classifiers":[
        {
            "category":"Shopping",
            "subcategory":"Department Store",
            "type":"Retail Goods"
        }
    ],
    "sg:phone":"+1 519 842 8888",
    "sg:postcode":"N4G 5A8",
    "sg:province":"ON",
    "wof:name":"Zellers",
    "wof:placetype":"venue"
},
  "geometry": {"coordinates":[-80.72846199999999,42.861465],"type":"Point"}
}