{
  "type": "Feature",
  "properties": {
    "addr:full":"7423 Edmonds St Burnaby BC V3N 1B1",
    "addr:housenumber":"7423",
    "addr:postcode":"v3n 1b1",
    "addr:street":"Edmonds St",
    "iso:country":"CA",
    "sg:address":"7423 Edmonds St",
    "sg:city":"Burnaby",
    "sg:classifiers":[
        {
            "category":"Health Services",
            "subcategory":"Doctor",
            "type":"Services"
        }
    ],
    "sg:phone":"+1 604 526 2401",
    "sg:postcode":"V3N 1B1",
    "sg:province":"BC",
    "sg:tags":[
        "physician",
        "surgeon"
    ],
    "wof:name":"Sanghera, Baldev MD",
    "wof:placetype":"venue"
},
  "geometry": {"coordinates":[-122.948059082,49.2204742432],"type":"Point"}
}