{
  "type": "Feature",
  "properties": {
    "addr:full":"860 Prospect St Fredericton NB E3B 2T8",
    "addr:housenumber":"860",
    "addr:postcode":"e3b 2t8",
    "addr:street":"Prospect St",
    "iso:country":"CA",
    "sg:address":"860 Prospect St",
    "sg:city":"Fredericton",
    "sg:classifiers":[
        {
            "category":"Insurance",
            "subcategory":"Insurance Agent",
            "type":"Services"
        }
    ],
    "sg:phone":"+1 506 459 3000",
    "sg:postcode":"E3B 2T8",
    "sg:province":"NB",
    "wof:name":"Cain Insurance Svc Ltd",
    "wof:placetype":"venue"
},
  "geometry": {"coordinates":[-66.67441599999999,45.944363],"type":"Point"}
}