{
  "type": "Feature",
  "properties": {
    "addr:full":"58 Crossroads St Bay Roberts NL A0A 1G0",
    "addr:housenumber":"58",
    "addr:postcode":"a0a 1g0",
    "addr:street":"Crossroads St",
    "iso:country":"CA",
    "sg:address":"58 Crossroads St",
    "sg:city":"Bay Roberts",
    "sg:classifiers":[
        {
            "category":"Home & Garden",
            "subcategory":"Household Appliances",
            "type":"Retail Goods"
        }
    ],
    "sg:phone":"+1 709 786 9735",
    "sg:postcode":"A0A 1G0",
    "sg:province":"NL",
    "wof:name":"Gleeson's Appliance Repairs",
    "wof:placetype":"venue"
},
  "geometry": {"coordinates":[-53.281509,47.583984],"type":"Point"}
}