{
  "type": "Feature",
  "properties": {
    "addr:full":"190 Av Alexandra Montreal QC H2S 1A8",
    "addr:housenumber":"190",
    "addr:postcode":"h2s 1a8",
    "addr:street":"Av Alexandra",
    "iso:country":"CA",
    "sg:address":"190 Av Alexandra",
    "sg:city":"Montreal",
    "sg:classifiers":[
        {
            "category":"Retail",
            "subcategory":"Auto Repair",
            "type":"Services"
        }
    ],
    "sg:phone":"+1 514 276 9116",
    "sg:postcode":"H2S 1A8",
    "sg:province":"QC",
    "sg:tags":[
        "repairing",
        "automobile"
    ],
    "wof:name":"Carrosserie Alexandra",
    "wof:placetype":"venue"
},
  "geometry": {"coordinates":[-73.618202,45.531227],"type":"Point"}
}