{
  "type": "Feature",
  "properties": {
    "addr:full":"6435 Erin Mills Pky Mississauga ON L5N 4H4",
    "addr:housenumber":"6435",
    "addr:postcode":"l5n 4h4",
    "addr:street":"Erin Mills Pky",
    "iso:country":"CA",
    "sg:address":"6435 Erin Mills Pky",
    "sg:city":"Mississauga",
    "sg:classifiers":[
        {
            "category":"Home & Garden",
            "subcategory":"Furniture",
            "type":"Retail Goods"
        }
    ],
    "sg:phone":"+1 905 542 0481",
    "sg:postcode":"L5N 4H4",
    "sg:province":"ON",
    "sg:tags":[
        "mattress"
    ],
    "wof:name":"Sleep Factory",
    "wof:placetype":"venue"
},
  "geometry": {"coordinates":[-79.74192810060001,43.5874137878],"type":"Point"}
}