{
  "type": "Feature",
  "properties": {
    "iso:country":"CA",
    "sg:address":"1820 Rue Guimond",
    "sg:city":"Saint-Paulin",
    "sg:classifiers":[
        {
            "category":"Manufacturing",
            "subcategory":"Furniture",
            "type":"Manufacturing & Wholesale Goods"
        }
    ],
    "sg:phone":"+1 819 268 2206",
    "sg:postcode":"J0K 3G0",
    "sg:province":"QC",
    "wof:name":"Industries Cherbourg Inc",
    "wof:placetype":"venue"
},
  "geometry": {"coordinates":[-73.0134887695,46.4262657166],"type":"Point"}
}