{
  "type": "Feature",
  "properties": {
    "addr:full":"4400 Marine Ave Powell River BC V8A 2K1",
    "addr:housenumber":"4400",
    "addr:postcode":"v8a 2k1",
    "addr:street":"Marine Ave Powell",
    "iso:country":"CA",
    "sg:address":"4400 Marine Ave",
    "sg:city":"Powell River",
    "sg:classifiers":[
        {
            "category":"Manufacturing",
            "subcategory":"Printing",
            "type":"Manufacturing & Wholesale Goods"
        }
    ],
    "sg:phone":"+1 604 485 5313",
    "sg:postcode":"V8A 2K1",
    "sg:province":"BC",
    "sg:tags":[
        "newspaper"
    ],
    "wof:name":"Powell River Peak",
    "wof:placetype":"venue"
},
  "geometry": {"coordinates":[-124.527786255,49.8349494934],"type":"Point"}
}