{
  "type": "Feature",
  "properties": {
    "iso:country":"CA",
    "sg:address":"186 Smith's Cove Rd",
    "sg:city":"Smiths Cove",
    "sg:classifiers":[
        {
            "category":"Building & Trades",
            "subcategory":"Plumbing",
            "type":"Services"
        }
    ],
    "sg:phone":"+1 902 245 5105",
    "sg:postcode":"B0S 1S0",
    "sg:province":"NS",
    "sg:tags":[
        "water",
        "treatment",
        "contractor"
    ],
    "wof:name":"John F Roop Plumbing & Heating",
    "wof:placetype":"venue"
},
  "geometry": {"coordinates":[-65.71440887449999,44.6104888916],"type":"Point"}
}