{
  "type": "Feature",
  "properties": {
    "addr:full":"Ottawa ON K2H 8S9",
    "addr:postcode":"k2h 8s9",
    "iso:country":"CA",
    "sg:city":"Ottawa",
    "sg:classifiers":[
        {
            "category":"Wholesale",
            "subcategory":"Electrical",
            "type":"Manufacturing & Wholesale Goods"
        }
    ],
    "sg:phone":"+1 613 596 1144",
    "sg:postcode":"K2H 8S9",
    "sg:province":"ON",
    "sg:tags":[
        "equipment",
        "electric",
        "supply"
    ],
    "wof:name":"Franklin Empire",
    "wof:placetype":"venue"
},
  "geometry": {"coordinates":[-75.79695129389999,45.3450393677],"type":"Point"}
}