{
  "type": "Feature",
  "properties": {
    "addr:full":"Black Lake QC G6H 1M9",
    "addr:postcode":"g6h 1m9",
    "addr:street":"Black Lake",
    "iso:country":"CA",
    "sg:city":"Black Lake",
    "sg:classifiers":[
        {
            "category":"Autos & Motor Vehicles",
            "subcategory":"Motorcycle Sales",
            "type":"Retail Goods"
        }
    ],
    "sg:phone":"+1 418 423 4737",
    "sg:postcode":"G6H 1M9",
    "sg:province":"QC",
    "sg:tags":[
        "snowmobile"
    ],
    "wof:name":"G Guillemette & Fils",
    "wof:placetype":"venue"
},
  "geometry": {"coordinates":[-71.386078,46.049713],"type":"Point"}
}