{
  "type": "Feature",
  "properties": {
    "addr:full":"2147 Boul Talbot Chicoutimi QC G7H 8B3",
    "addr:housenumber":"2147",
    "addr:postcode":"g7h 8b3",
    "addr:street":"Boul Talbot",
    "iso:country":"CA",
    "sg:address":"2147 Boul Talbot",
    "sg:city":"Chicoutimi",
    "sg:classifiers":[
        {
            "category":"Professional",
            "subcategory":"Computer Services",
            "type":"Services"
        }
    ],
    "sg:phone":"+1 418 545 0070",
    "sg:postcode":"G7H 8B3",
    "sg:province":"QC",
    "sg:tags":[
        "electronics"
    ],
    "wof:name":"Services Electroniques Maxima",
    "wof:placetype":"venue"
},
  "geometry": {"coordinates":[-71.0746917725,48.3897438049],"type":"Point"}
}