{
  "type": "Feature",
  "properties": {
    "addr:full":"Norwood ON K0L 2V0",
    "addr:postcode":"k0l 2v0",
    "iso:country":"CA",
    "sg:city":"Norwood",
    "sg:classifiers":[
        {
            "category":"Autos & Motor Vehicles",
            "subcategory":"Automobile Sales",
            "type":"Retail Goods"
        }
    ],
    "sg:phone":"+1 705 639 5383",
    "sg:postcode":"K0L 2V0",
    "sg:province":"ON",
    "sg:tags":[
        "car",
        "dealer"
    ],
    "wof:name":"J J Stewart Motors",
    "wof:placetype":"venue"
},
  "geometry": {"coordinates":[-77.978088,44.384007],"type":"Point"}
}