{
  "type": "Feature",
  "properties": {
    "addr:full":"1698 Dartmouth Rd Penticton BC V2A 4B8",
    "addr:housenumber":"1698",
    "addr:postcode":"v2a 4b8",
    "addr:street":"Dartmouth Rd",
    "iso:country":"CA",
    "sg:address":"1698 Dartmouth Rd",
    "sg:city":"Penticton",
    "sg:classifiers":[
        {
            "category":"Wholesale",
            "subcategory":"Machinery & Supplies",
            "type":"Manufacturing & Wholesale Goods"
        }
    ],
    "sg:phone":"+1 250 493 4545",
    "sg:postcode":"V2A 4B8",
    "sg:province":"BC",
    "wof:name":"Pacific Rim Equipment Inc",
    "wof:placetype":"venue"
},
  "geometry": {"coordinates":[-119.56952667199999,49.4818611145],"type":"Point"}
}