{
  "type": "Feature",
  "properties": {
    "addr:full":"477 Davie St Vancouver BC V6B 2G2",
    "addr:housenumber":"477",
    "addr:postcode":"bc v6b 2g2",
    "addr:street":"Davie St",
    "iso:country":"CA",
    "sg:address":"477 Davie St",
    "sg:city":"Vancouver",
    "sg:classifiers":[
        {
            "category":"Restaurant",
            "type":"Food & Drink"
        }
    ],
    "sg:phone":"+1 604 605 0938",
    "sg:postcode":"V6B 2G2",
    "sg:province":"BC",
    "sg:tags":[
        "shop",
        "coffee"
    ],
    "wof:name":"COO COO Coffee",
    "wof:placetype":"venue"
},
  "geometry": {"coordinates":[-123.12387099999999,49.275822],"type":"Point"}
}