{
  "type": "Feature",
  "properties": {
    "iso:country":"CA",
    "sg:address":"120 Main St",
    "sg:city":"Climax",
    "sg:classifiers":[
        {
            "category":"Professional",
            "subcategory":"Accounting & Tax Preparation",
            "type":"Services"
        }
    ],
    "sg:phone":"+1 306 293 2124",
    "sg:postcode":"S0N 0N0",
    "sg:province":"SK",
    "sg:tags":[
        "accountant"
    ],
    "wof:name":"Monette & CO",
    "wof:placetype":"venue"
},
  "geometry": {"coordinates":[-108.383881,49.211163],"type":"Point"}
}