{
  "type": "Feature",
  "properties": {
    "addr:full":"120 Main St Climax SK S0N 0N0",
    "addr:housenumber":"120",
    "addr:postcode":"s0n 0n0",
    "addr:street":"Main St",
    "iso:country":"CA",
    "sg:address":"120 Main St",
    "sg:city":"Climax",
    "sg:classifiers":[
        {
            "category":"Professional",
            "subcategory":"Accounting & Tax Preparation",
            "type":"Services"
        }
    ],
    "sg:phone":"+1 306 293 2124",
    "sg:postcode":"S0N 0N0",
    "sg:province":"SK",
    "sg:tags":[
        "accountant"
    ],
    "wof:name":"Monette & CO",
    "wof:placetype":"venue"
},
  "geometry": {"coordinates":[-108.383881,49.211163],"type":"Point"}
}