{
  "type": "Feature",
  "properties": {
    "addr:full":"Corner Brook NL A2H 2Y6",
    "addr:postcode":"a2h 2y6",
    "iso:country":"CA",
    "sg:city":"Corner Brook",
    "sg:classifiers":[
        {
            "category":"Health Services",
            "subcategory":"Doctor",
            "type":"Services"
        }
    ],
    "sg:phone":"+1 709 634 6954",
    "sg:postcode":"A2H 2Y6",
    "sg:province":"NL",
    "sg:tags":[
        "physician",
        "surgeon"
    ],
    "wof:name":"Kathir, Mylo MD",
    "wof:placetype":"venue"
},
  "geometry": {"coordinates":[-57.944237,48.952606],"type":"Point"}
}