{
  "type": "Feature",
  "properties": {
    "addr:full":"Chetwynd BC V0C 1J0",
    "addr:postcode":"bc v0c 1j0",
    "iso:country":"CA",
    "sg:city":"Chetwynd",
    "sg:classifiers":[
        {
            "category":"Professional",
            "subcategory":"Business Services",
            "type":"Services"
        }
    ],
    "sg:phone":"+1 250 788 1679",
    "sg:postcode":"V0C 1J0",
    "sg:province":"BC",
    "sg:tags":[
        "water",
        "treatment"
    ],
    "wof:name":"Ecohomes By Scott",
    "wof:placetype":"venue"
},
  "geometry": {"coordinates":[-121.614357,55.696232],"type":"Point"}
}