{
  "type": "Feature",
  "properties": {
    "addr:full":"5465 192 St Surrey BC V3S 8E5",
    "addr:housenumber":"5465",
    "addr:postcode":"v3s 8e5",
    "addr:street":"192 St",
    "iso:country":"CA",
    "sg:address":"5465 192 St",
    "sg:city":"Surrey",
    "sg:classifiers":[
        {
            "category":"Wholesale",
            "subcategory":"Machinery & Supplies",
            "type":"Manufacturing & Wholesale Goods"
        }
    ],
    "sg:phone":"+1 604 574 1397",
    "sg:postcode":"V3S 8E5",
    "sg:province":"BC",
    "sg:tags":[
        "equipment",
        "sawmill"
    ],
    "wof:name":"Mpm Engineering Ltd",
    "wof:placetype":"venue"
},
  "geometry": {"coordinates":[-122.691322,49.102234],"type":"Point"}
}