{
  "type": "Feature",
  "properties": {
    "addr:full":"94 St. Peters Rd Sydney NS B1P 4P4",
    "addr:housenumber":"94",
    "addr:postcode":"b1p 4p4",
    "addr:street":"St. Peters Rd",
    "iso:country":"CA",
    "sg:address":"94 St. Peters Rd",
    "sg:city":"Sydney",
    "sg:classifiers":[
        {
            "category":"Health Services",
            "subcategory":"Doctor",
            "type":"Services"
        }
    ],
    "sg:phone":"+1 902 539 9205",
    "sg:postcode":"B1P 4P4",
    "sg:province":"NS",
    "sg:tags":[
        "dentist"
    ],
    "wof:name":"Conrod, A L DDS",
    "wof:placetype":"venue"
},
  "geometry": {"coordinates":[-60.1804504395,46.1324043274],"type":"Point"}
}