{
  "type": "Feature",
  "properties": {
    "iso:country":"CA",
    "sg:city":"Oakville",
    "sg:classifiers":[
        {
            "category":"Insurance",
            "subcategory":"Insurance Agent",
            "type":"Services"
        }
    ],
    "sg:phone":"+1 905 847 7900",
    "sg:postcode":"L6M 3E3",
    "sg:province":"ON",
    "wof:name":"Industrial Alliance Pacific",
    "wof:placetype":"venue"
},
  "geometry": {"coordinates":[-79.7147979736,43.4349441528],"type":"Point"}
}