{
  "type": "Feature",
  "properties": {
    "addr:full":"2800 Victoria Park Ave North York ON M2J 4A8",
    "addr:housenumber":"2800",
    "addr:postcode":"m2j 4a8",
    "addr:street":"Victoria Park Ave",
    "iso:country":"CA",
    "sg:address":"2800 Victoria Park Ave",
    "sg:city":"North York",
    "sg:classifiers":[
        {
            "category":"Banks & Credit Unions",
            "subcategory":"Bank",
            "type":"Services"
        }
    ],
    "sg:phone":"+1 416 491 1074",
    "sg:postcode":"M2J 4A8",
    "sg:province":"ON",
    "wof:name":"Cibc",
    "wof:placetype":"venue"
},
  "geometry": {"coordinates":[-79.3287734985,43.7871246338],"type":"Point"}
}