{
  "type": "Feature",
  "properties": {
    "addr:full":"5844 Malden Rd Windsor ON N9H 1S4",
    "addr:housenumber":"5844",
    "addr:postcode":"n9h 1s4",
    "addr:street":"Malden Rd",
    "iso:country":"CA",
    "sg:address":"5844 Malden Rd",
    "sg:city":"Windsor",
    "sg:classifiers":[
        {
            "category":"Shopping",
            "subcategory":"Department Store",
            "type":"Retail Goods"
        }
    ],
    "sg:phone":"+1 519 250 2875",
    "sg:postcode":"N9H 1S4",
    "sg:province":"ON",
    "sg:tags":[
        "shop"
    ],
    "wof:name":"A Buck or Two",
    "wof:placetype":"venue"
},
  "geometry": {"coordinates":[-83.060508728,42.2527389526],"type":"Point"}
}