{
  "type": "Feature",
  "properties": {
    "addr:full":"35 Glasgow St S Guelph ON N1H 4T6",
    "addr:housenumber":"35",
    "addr:postcode":"n1h 4t6",
    "addr:street":"Glasgow St S",
    "iso:country":"CA",
    "sg:address":"35 Glasgow St S",
    "sg:city":"Guelph",
    "sg:classifiers":[
        {
            "category":"Real Estate",
            "subcategory":"Real Estate Agent",
            "type":"Services"
        }
    ],
    "sg:phone":"+1 519 763 6500",
    "sg:postcode":"N1H 4T6",
    "sg:province":"ON",
    "wof:name":"Worton Real Estate Ltd",
    "wof:placetype":"venue"
},
  "geometry": {"coordinates":[-80.251625,43.539024],"type":"Point"}
}