{
  "type": "Feature",
  "properties": {
    "addr:full":"400 Boul DE Maisonneuve O #1053 Montreal QC H3A 1L4",
    "addr:housenumber":"400",
    "addr:postcode":"h3a 1l4",
    "addr:street":"Boul De Maisonneuve O # 1053",
    "iso:country":"CA",
    "sg:address":"400 Boul DE Maisonneuve O #1053",
    "sg:city":"Montreal",
    "sg:classifiers":[
        {
            "category":"Manufacturing",
            "subcategory":"Apparel",
            "type":"Manufacturing & Wholesale Goods"
        }
    ],
    "sg:phone":"+1 514 849 8810",
    "sg:postcode":"H3A 1L4",
    "sg:province":"QC",
    "sg:tags":[
        "clothing"
    ],
    "wof:name":"Dino Gaspari",
    "wof:placetype":"venue"
},
  "geometry": {"coordinates":[-73.56179,45.514435],"type":"Point"}
}