{
  "type": "Feature",
  "properties": {
    "addr:full":"Glencoe ON N0L 1M0",
    "addr:postcode":"n0l 1m0",
    "iso:country":"CA",
    "sg:city":"Glencoe",
    "sg:classifiers":[
        {
            "category":"Building & Trades",
            "subcategory":"Construction",
            "type":"Services"
        }
    ],
    "sg:phone":"+1 519 287 2488",
    "sg:postcode":"N0L 1M0",
    "sg:province":"ON",
    "sg:tags":[
        "home",
        "improvement"
    ],
    "wof:name":"Building/Basement Boss Dealer",
    "wof:placetype":"venue"
},
  "geometry": {"coordinates":[-81.7108078003,42.7485580444],"type":"Point"}
}