{
  "type": "Feature",
  "properties": {
    "addr:full":"24707 Woodbine Ave Keswick ON L4P 3E9",
    "addr:housenumber":"24707",
    "addr:postcode":"l4p 3e9",
    "addr:street":"Woodbine Ave",
    "iso:country":"CA",
    "sg:address":"24707 Woodbine Ave",
    "sg:city":"Keswick",
    "sg:classifiers":[
        {
            "category":"Freight",
            "type":"Transportation"
        }
    ],
    "sg:phone":"+1 905 476 6581",
    "sg:postcode":"L4P 3E9",
    "sg:province":"ON",
    "sg:tags":[
        "mover"
    ],
    "wof:name":"Daystar Moving Packing Supls",
    "wof:placetype":"venue"
},
  "geometry": {"coordinates":[-79.45141599999999,44.245602],"type":"Point"}
}