{
  "type": "Feature",
  "properties": {
    "addr:full":"1041 Gill Rd Williams Lake BC V2G 2V5",
    "addr:housenumber":"1041",
    "addr:postcode":"v2g 2v5",
    "addr:street":"Gill Rd",
    "iso:country":"CA",
    "sg:address":"1041 Gill Rd",
    "sg:city":"Williams Lake",
    "sg:classifiers":[
        {
            "category":"Mining & Drilling",
            "type":"Manufacturing & Wholesale Goods"
        }
    ],
    "sg:phone":"+1 250 392 4944",
    "sg:postcode":"V2G 2V5",
    "sg:province":"BC",
    "sg:tags":[
        "product",
        "oil",
        "petroleum",
        "company"
    ],
    "wof:name":"Petro-Canada",
    "wof:placetype":"venue"
},
  "geometry": {"coordinates":[-122.12773900000001,52.120354],"type":"Point"}
}