{
  "type": "Feature",
  "properties": {
    "addr:full":"882 4th St W Canora SK S0A 0L0",
    "addr:housenumber":"882",
    "addr:postcode":"s0a 0l0",
    "addr:street":"4Th St W Canora",
    "iso:country":"CA",
    "sg:address":"882 4th St W",
    "sg:city":"Canora",
    "sg:classifiers":[
        {
            "category":"Organizations",
            "subcategory":"Professional Association",
            "type":"Services"
        }
    ],
    "sg:phone":"+1 306 563 4240",
    "sg:postcode":"S0A 0L0",
    "sg:province":"SK",
    "sg:tags":[
        "club"
    ],
    "wof:name":"Canora Golden Age Ctr",
    "wof:placetype":"venue"
},
  "geometry": {"coordinates":[-102.432434082,51.6354560852],"type":"Point"}
}