{
  "type": "Feature",
  "properties": {
    "addr:full":"Hamilton ON L8N 2A1",
    "addr:postcode":"l8n 2a1",
    "iso:country":"CA",
    "sg:city":"Hamilton",
    "sg:classifiers":[
        {
            "category":"Professional",
            "subcategory":"Lawyer & Legal Services",
            "type":"Services"
        }
    ],
    "sg:phone":"+1 905 525 0400",
    "sg:postcode":"L8N 2A1",
    "sg:province":"ON",
    "sg:tags":[
        "attorney"
    ],
    "wof:name":"Cohen, Lawrence J QC",
    "wof:placetype":"venue"
},
  "geometry": {"coordinates":[-79.8683547974,43.255569458],"type":"Point"}
}