{
  "type": "Feature",
  "properties": {
    "addr:full":"41 Pembroke St Toronto ON M5A 2N6",
    "addr:housenumber":"41",
    "addr:postcode":"m5a 2n6",
    "addr:street":"Pembroke St",
    "iso:country":"CA",
    "sg:address":"41 Pembroke St",
    "sg:city":"Toronto",
    "sg:classifiers":[
        {
            "category":"Social Services",
            "type":"Services"
        }
    ],
    "sg:phone":"+1 416 360 7882",
    "sg:postcode":"M5A 2N6",
    "sg:province":"ON",
    "sg:tags":[
        "housing",
        "assistance"
    ],
    "wof:name":"Pembroke Lodges",
    "wof:placetype":"venue"
},
  "geometry": {"coordinates":[-79.371849,43.657394],"type":"Point"}
}