{
  "type": "Feature",
  "properties": {
    "addr:full":"9844 45 Ave NW Edmonton AB T6E 5C5",
    "addr:housenumber":"9844",
    "addr:postcode":"t6e 5c5",
    "addr:street":"45 Ave Nw",
    "iso:country":"CA",
    "sg:address":"9844 45 Ave NW",
    "sg:city":"Edmonton",
    "sg:classifiers":[
        {
            "category":"Building & Trades",
            "subcategory":"Construction",
            "type":"Services"
        }
    ],
    "sg:phone":"+1 780 437 5750",
    "sg:postcode":"T6E 5C5",
    "sg:province":"AB",
    "sg:tags":[
        "resurfacing",
        "material",
        "laying",
        "refinishing",
        "floor"
    ],
    "wof:name":"Builders' Floor Ctr Ltd",
    "wof:placetype":"venue"
},
  "geometry": {"coordinates":[-113.48389434800001,53.4833564758],"type":"Point"}
}