{
  "type": "Feature",
  "properties": {
    "addr:full":"76 Kensington Ave Toronto ON M5T 2K1",
    "addr:housenumber":"76",
    "addr:postcode":"m5t 2k1",
    "addr:street":"Kensington Ave",
    "iso:country":"CA",
    "sg:address":"76 Kensington Ave",
    "sg:city":"Toronto",
    "sg:classifiers":[
        {
            "category":"Food & Beverages",
            "subcategory":"Dairy",
            "type":"Retail Goods"
        }
    ],
    "sg:phone":"+1 416 593 9251",
    "sg:postcode":"M5T 2K1",
    "sg:province":"ON",
    "sg:tags":[
        "cheese",
        "product"
    ],
    "wof:name":"Global Cheese Shoppe Ltd",
    "wof:placetype":"venue"
},
  "geometry": {"coordinates":[-79.400749,43.654385],"type":"Point"}
}