{
  "type": "Feature",
  "properties": {
    "addr:full":"609 Ch Paul Ascot Corner QC J0B 1A0",
    "addr:housenumber":"609",
    "addr:postcode":"j0b 1a0",
    "addr:street":"Ch Paul",
    "iso:country":"CA",
    "sg:address":"609 Ch Paul",
    "sg:city":"Ascot Corner",
    "sg:classifiers":[
        {
            "category":"Wholesale",
            "subcategory":"Fruits & Vegetables",
            "type":"Manufacturing & Wholesale Goods"
        }
    ],
    "sg:phone":"+1 819 832 3959",
    "sg:postcode":"J0B 1A0",
    "sg:province":"QC",
    "sg:tags":[
        "shipper"
    ],
    "wof:name":"Ferme Au Pre Bleu",
    "wof:placetype":"venue"
},
  "geometry": {"coordinates":[-71.72840118409999,45.4390907288],"type":"Point"}
}