{
  "type": "Feature",
  "properties": {
    "addr:full":"335025 Rd 33 Ingersoll ON N5C 3J5",
    "addr:postcode":"335025;n5c 3j5",
    "addr:street":"Rd 33",
    "iso:country":"CA",
    "sg:address":"335025 Rd 33",
    "sg:city":"Ingersoll",
    "sg:classifiers":[
        {
            "category":"Wholesale",
            "subcategory":"Auto Parts",
            "type":"Manufacturing & Wholesale Goods"
        }
    ],
    "sg:phone":"+1 519 425 4555",
    "sg:postcode":"N5C 3J5",
    "sg:province":"ON",
    "sg:tags":[
        "automobile",
        "rebuilt",
        "wrecking"
    ],
    "wof:name":"Ace Auto Parts",
    "wof:placetype":"venue"
},
  "geometry": {"coordinates":[-80.88385,43.038116],"type":"Point"}
}