{
  "type": "Feature",
  "properties": {
    "addr:full":"Terrace BC V8G 1L2",
    "addr:postcode":"v8g 1l2",
    "iso:country":"CA",
    "sg:city":"Terrace",
    "sg:classifiers":[
        {
            "category":"Freight",
            "type":"Transportation"
        }
    ],
    "sg:phone":"+1 250 635 4030",
    "sg:postcode":"V8G 1L2",
    "sg:province":"BC",
    "sg:tags":[
        "trucking"
    ],
    "wof:name":"Excel Transportation Inc",
    "wof:placetype":"venue"
},
  "geometry": {"coordinates":[-128.625854,54.513519],"type":"Point"}
}