{
  "type": "Feature",
  "properties": {
    "addr:full":"Oakville ON L6J 1H3",
    "addr:postcode":"l6j 1h3",
    "iso:country":"CA",
    "sg:city":"Oakville",
    "sg:classifiers":[
        {
            "category":"Personal",
            "type":"Services"
        }
    ],
    "sg:phone":"+1 905 845 3137",
    "sg:postcode":"L6J 1H3",
    "sg:province":"ON",
    "sg:tags":[
        "therapist",
        "massage"
    ],
    "wof:name":"Oakville Shiatsu & Massage Ctr",
    "wof:placetype":"venue"
},
  "geometry": {"coordinates":[-79.6699752808,43.4443321228],"type":"Point"}
}