{
  "type": "Feature",
  "properties": {
    "addr:full":"230 Notre Dame Ave W Notre Dame DE Lourdes MB R0G 1M0",
    "addr:housenumber":"230",
    "addr:postcode":"r0g 1m0",
    "addr:street":"Notre Dame Ave W Notre Dame De Lourdes",
    "iso:country":"CA",
    "sg:address":"230 Notre Dame Ave W",
    "sg:city":"Notre Dame DE Lourdes",
    "sg:classifiers":[
        {
            "category":"Retail",
            "subcategory":"Auto Repair",
            "type":"Services"
        }
    ],
    "sg:phone":"+1 204 248 2260",
    "sg:postcode":"R0G 1M0",
    "sg:province":"MB",
    "sg:tags":[
        "transmission"
    ],
    "wof:name":"Boisvert Garage",
    "wof:placetype":"venue"
},
  "geometry": {"coordinates":[-98.55750274659999,49.5327186584],"type":"Point"}
}