{
  "type": "Feature",
  "properties": {
    "iso:country":"CA",
    "sg:address":"40 Spencer Trail",
    "sg:city":"Shanty Bay",
    "sg:classifiers":[
        {
            "category":"Home & Garden",
            "subcategory":"Garden Supply",
            "type":"Retail Goods"
        }
    ],
    "sg:phone":"+1 705 726 5576",
    "sg:postcode":"L0L 2L0",
    "sg:province":"ON",
    "sg:tags":[
        "landscape",
        "contractor"
    ],
    "wof:name":"Riverwood Irrigation",
    "wof:placetype":"venue"
},
  "geometry": {"coordinates":[-79.5778045654,44.4159164429],"type":"Point"}
}