{
  "type": "Feature",
  "properties": {
    "addr:full":"18964 96 Ave Surrey BC V4N 3R2",
    "addr:housenumber":"18964",
    "addr:postcode":"v4n 3r2",
    "addr:street":"96 Ave",
    "iso:country":"CA",
    "sg:address":"18964 96 Ave",
    "sg:city":"Surrey",
    "sg:classifiers":[
        {
            "category":"Autos & Motor Vehicles",
            "subcategory":"Automobile Sales",
            "type":"Retail Goods"
        }
    ],
    "sg:phone":"+1 604 888 5577",
    "sg:postcode":"V4N 3R2",
    "sg:province":"BC",
    "sg:tags":[
        "truck"
    ],
    "wof:name":"Volvo Trucks of Vancouver",
    "wof:placetype":"venue"
},
  "geometry": {"coordinates":[-122.69704400000001,49.176861],"type":"Point"}
}