{
  "type": "Feature",
  "properties": {
    "addr:full":"8025 265 Rd Groundbirch BC V0C 1T0",
    "addr:housenumber":"8025",
    "addr:postcode":"bc v0c 1t0",
    "addr:street":"265 Rd",
    "iso:country":"CA",
    "sg:address":"8025 265 Rd",
    "sg:city":"Groundbirch",
    "sg:classifiers":[
        {
            "category":"Education",
            "subcategory":"School",
            "type":"Public Place"
        }
    ],
    "sg:phone":"+1 250 843 7374",
    "sg:postcode":"V0C 1T0",
    "sg:province":"BC",
    "wof:name":"Mc Leod Elementary School",
    "wof:placetype":"venue"
},
  "geometry": {"coordinates":[-120.920135,55.781277],"type":"Point"}
}