{
  "type": "Feature",
  "properties": {
    "iso:country":"CA",
    "sg:address":"PO Box 51",
    "sg:city":"Glendon",
    "sg:classifiers":[
        {
            "category":"Building & Trades",
            "subcategory":"Landscaping Services",
            "type":"Services"
        }
    ],
    "sg:phone":"+1 780 635 2170",
    "sg:postcode":"T0A 1P0",
    "sg:province":"AB",
    "sg:tags":[
        "excavating",
        "landscape",
        "contractor"
    ],
    "wof:name":"Sydor Scaping & Tilling Ltd",
    "wof:placetype":"venue"
},
  "geometry": {"coordinates":[-111.153831482,54.2471961975],"type":"Point"}
}