{
  "type": "Feature",
  "properties": {
    "addr:full":"9135 Ch Cote-DE-Liesse Dorval QC H9P 2N9",
    "addr:housenumber":"9135",
    "addr:postcode":"h9p 2n9",
    "addr:street":"Ch Cote-De-Liesse",
    "iso:country":"CA",
    "sg:address":"9135 Ch Cote-DE-Liesse",
    "sg:city":"Dorval",
    "sg:classifiers":[
        {
            "category":"Wholesale",
            "subcategory":"Machinery & Supplies",
            "type":"Manufacturing & Wholesale Goods"
        }
    ],
    "sg:phone":"+1 514 631 6781",
    "sg:postcode":"H9P 2N9",
    "sg:province":"QC",
    "sg:tags":[
        "rubber",
        "belting",
        "product"
    ],
    "wof:name":"Jason Industrial Ltd",
    "wof:placetype":"venue"
},
  "geometry": {"coordinates":[-73.709801,45.472492],"type":"Point"}
}