{
  "type": "Feature",
  "properties": {
    "addr:full":"80 Riverside Dr Penticton BC V2A 5Y3",
    "addr:housenumber":"80",
    "addr:postcode":"v2a 5y3",
    "addr:street":"Riverside Dr",
    "iso:country":"CA",
    "sg:address":"80 Riverside Dr",
    "sg:city":"Penticton",
    "sg:classifiers":[
        {
            "category":"Travel",
            "subcategory":"Hotels & Motels",
            "type":"Entertainment"
        }
    ],
    "sg:phone":"+1 250 492 0112",
    "sg:postcode":"V2A 5Y3",
    "sg:province":"BC",
    "wof:name":"Bowmont Motel",
    "wof:placetype":"venue"
},
  "geometry": {"coordinates":[-119.611068726,49.5005302429],"type":"Point"}
}