{
  "type": "Feature",
  "properties": {
    "addr:full":"4566 Dawson St Burnaby BC V5C 4C1",
    "addr:housenumber":"4566",
    "addr:postcode":"v5c 4c1",
    "addr:street":"Dawson St",
    "iso:country":"CA",
    "sg:address":"4566 Dawson St",
    "sg:city":"Burnaby",
    "sg:classifiers":[
        {
            "category":"Shopping",
            "type":"Retail Goods"
        }
    ],
    "sg:phone":"+1 604 294 1080",
    "sg:postcode":"V5C 4C1",
    "sg:province":"BC",
    "sg:tags":[
        "hearing",
        "equipment",
        "supply",
        "impaired"
    ],
    "wof:name":"Acoustica Hearing Aid",
    "wof:placetype":"venue"
},
  "geometry": {"coordinates":[-123.00145000000001,49.264355],"type":"Point"}
}