{
  "type": "Feature",
  "properties": {
    "addr:full":"Vancouver BC V6J 3H9",
    "addr:postcode":"v6j 3h9",
    "iso:country":"CA",
    "sg:city":"Vancouver",
    "sg:classifiers":[
        {
            "category":"Personal",
            "subcategory":"Beauty Salon",
            "type":"Services"
        }
    ],
    "sg:phone":"+1 604 736 9950",
    "sg:postcode":"V6J 3H9",
    "sg:province":"BC",
    "sg:tags":[
        "consultant",
        "health"
    ],
    "wof:name":"Renaissance Health Ctr",
    "wof:placetype":"venue"
},
  "geometry": {"coordinates":[-123.14589700000001,49.266022],"type":"Point"}
}