{
  "type": "Feature",
  "properties": {
    "iso:country":"CA",
    "sg:address":"109 Boul Saint-Joseph",
    "sg:city":"Hull",
    "sg:classifiers":[
        {
            "category":"Shopping",
            "subcategory":"Jewelry",
            "type":"Retail Goods"
        }
    ],
    "sg:phone":"+1 819 777 6586",
    "sg:postcode":"J8Y 3W7",
    "sg:province":"QC",
    "sg:tags":[
        "jeweler"
    ],
    "wof:name":"Le Page Florent Ltee",
    "wof:placetype":"venue"
},
  "geometry": {"coordinates":[-75.7335281372,45.4302558899],"type":"Point"}
}