{
  "type": "Feature",
  "properties": {
    "addr:full":"4190 Finch Ave E Scarborough ON M1S 4T7",
    "addr:housenumber":"4190",
    "addr:postcode":"m1s 4t7",
    "addr:street":"Finch Ave E",
    "iso:country":"CA",
    "sg:address":"4190 Finch Ave E",
    "sg:city":"Scarborough",
    "sg:classifiers":[
        {
            "category":"Health Services",
            "subcategory":"Doctor",
            "type":"Services"
        }
    ],
    "sg:phone":"+1 416 299 4463",
    "sg:postcode":"M1S 4T7",
    "sg:province":"ON",
    "sg:tags":[
        "physician",
        "surgeon"
    ],
    "wof:name":"Medina, Xavier MD",
    "wof:placetype":"venue"
},
  "geometry": {"coordinates":[-79.287064,43.803734],"type":"Point"}
}