{
  "type": "Feature",
  "properties": {
    "addr:full":"103 Riverside Dr North Vancouver BC V7H 1T6",
    "addr:housenumber":"103",
    "addr:postcode":"v7h 1t6",
    "addr:street":"Riverside Dr",
    "iso:country":"CA",
    "sg:address":"103 Riverside Dr",
    "sg:city":"North Vancouver",
    "sg:classifiers":[
        {
            "category":"Manufacturing",
            "subcategory":"Metals",
            "type":"Manufacturing & Wholesale Goods"
        }
    ],
    "sg:phone":"+1 604 924 0914",
    "sg:postcode":"V7H 1T6",
    "sg:province":"BC",
    "sg:tags":[
        "gates"
    ],
    "wof:name":"Iron Age Mfg Ltd",
    "wof:placetype":"venue"
},
  "geometry": {"coordinates":[-123.014267,49.305714],"type":"Point"}
}