{
  "type": "Feature",
  "properties": {
    "addr:full":"60 St-Joseph St-Barnabe-Nord QC G0X 2K0",
    "addr:housenumber":"60",
    "addr:postcode":"g0x 2k0",
    "addr:street":"St-Joseph St-Barnabe-Nord",
    "iso:country":"CA",
    "sg:address":"60 St-Joseph",
    "sg:city":"St-Barnabe-Nord",
    "sg:classifiers":[
        {
            "category":"Professional",
            "subcategory":"Detective & Security Services",
            "type":"Services"
        }
    ],
    "sg:phone":"+1 819 264 5262",
    "sg:postcode":"G0X 2K0",
    "sg:province":"QC",
    "sg:tags":[
        "burglary",
        "protective",
        "robbery"
    ],
    "wof:name":"Service DE Prevention Miltech",
    "wof:placetype":"venue"
},
  "geometry": {"coordinates":[-72.879509,46.393532],"type":"Point"}
}