{
  "type": "Feature",
  "properties": {
    "addr:full":"8351 Alexandra Rd # 210B Richmond BC V6X 3P3",
    "addr:housenumber":"8351;210b",
    "addr:postcode":"v6x 3p3",
    "addr:street":"Alexandra Rd #",
    "iso:country":"CA",
    "sg:address":"8351 Alexandra Rd # 210B",
    "sg:city":"Richmond",
    "sg:classifiers":[
        {
            "category":"Professional",
            "subcategory":"Accounting & Tax Preparation",
            "type":"Services"
        }
    ],
    "sg:phone":"+1 604 273 8781",
    "sg:postcode":"V6X 3P3",
    "sg:province":"BC",
    "sg:tags":[
        "accountant"
    ],
    "wof:name":"Wong, Tony",
    "wof:placetype":"venue"
},
  "geometry": {"coordinates":[-123.130882263,49.1784744263],"type":"Point"}
}