{
  "type": "Feature",
  "properties": {
    "addr:full":"Ottawa ON K1Z 5N4",
    "addr:postcode":"k1z 5n4",
    "iso:country":"CA",
    "sg:city":"Ottawa",
    "sg:classifiers":[
        {
            "category":"Building & Trades",
            "subcategory":"Construction",
            "type":"Services"
        }
    ],
    "sg:phone":"+1 613 722 2769",
    "sg:postcode":"K1Z 5N4",
    "sg:province":"ON",
    "sg:tags":[
        "home",
        "contractor",
        "improvement",
        "concrete"
    ],
    "wof:name":"Westboro Home Improvements",
    "wof:placetype":"venue"
},
  "geometry": {"coordinates":[-75.7514419556,45.395778656],"type":"Point"}
}