{
  "type": "Feature",
  "properties": {
    "addr:full":"70 Rue Du Terminus O Rouyn-Noranda QC J9X 2P5",
    "addr:housenumber":"70",
    "addr:postcode":"j9x 2p5",
    "addr:street":"Rue Du Terminus O",
    "iso:country":"CA",
    "sg:address":"70 Rue Du Terminus O",
    "sg:city":"Rouyn-Noranda",
    "sg:classifiers":[
        {
            "category":"Retail",
            "subcategory":"Self-service Laundry",
            "type":"Services"
        }
    ],
    "sg:phone":"+1 819 762 0054",
    "sg:postcode":"J9X 2P5",
    "sg:province":"QC",
    "wof:name":"Buanderie Du Terminus",
    "wof:placetype":"venue"
},
  "geometry": {"coordinates":[-79.019066,48.241673],"type":"Point"}
}