{
  "type": "Feature",
  "properties": {
    "addr:full":"116 West St Smithville ON L0R 2A0",
    "addr:housenumber":"116",
    "addr:postcode":"l0r 2a0",
    "addr:street":"West St",
    "iso:country":"CA",
    "sg:address":"116 West St",
    "sg:city":"Smithville",
    "sg:classifiers":[
        {
            "category":"Organizations",
            "subcategory":"Religious Organization",
            "type":"Services"
        }
    ],
    "sg:phone":"+1 905 957 3176",
    "sg:postcode":"L0R 2A0",
    "sg:province":"ON",
    "sg:tags":[
        "church"
    ],
    "wof:name":"Smithville United Church",
    "wof:placetype":"venue"
},
  "geometry": {"coordinates":[-79.54776,43.099937],"type":"Point"}
}