{
  "type": "Feature",
  "properties": {
    "iso:country":"CA",
    "sg:address":"5450 Cornwallis St",
    "sg:city":"Halifax",
    "sg:classifiers":[
        {
            "category":"Professional",
            "subcategory":"Engineering",
            "type":"Services"
        }
    ],
    "sg:phone":"+1 902 429 0701",
    "sg:postcode":"B3K 1A9",
    "sg:province":"NS",
    "sg:tags":[
        "engineer"
    ],
    "wof:name":"F C O'Neill Scriven & Assoc",
    "wof:placetype":"venue"
},
  "geometry": {"coordinates":[-63.5832481384,44.6527328491],"type":"Point"}
}