{
  "type": "Feature",
  "properties": {
    "addr:full":"LA Pocatiere QC G0R 1Z0",
    "addr:postcode":"g0r 1z0",
    "iso:country":"CA",
    "sg:city":"LA Pocatiere",
    "sg:classifiers":[
        {
            "category":"Food & Beverages",
            "subcategory":"Groceries & Convenience Stores",
            "type":"Retail Goods"
        }
    ],
    "sg:phone":"+1 418 856 2468",
    "sg:postcode":"G0R 1Z0",
    "sg:province":"QC",
    "wof:name":"LA Pocatiere Esso Enr",
    "wof:placetype":"venue"
},
  "geometry": {"coordinates":[-70.016708374,47.4136695862],"type":"Point"}
}