{
  "type": "Feature",
  "properties": {
    "addr:full":"1101 Front St Hearst ON P0L 1N0",
    "addr:housenumber":"1101",
    "addr:postcode":"p0l 1n0",
    "addr:street":"Front St",
    "iso:country":"CA",
    "sg:address":"1101 Front St",
    "sg:city":"Hearst",
    "sg:classifiers":[
        {
            "category":"Recreation",
            "type":"Entertainment"
        }
    ],
    "sg:phone":"+1 705 362 5800",
    "sg:postcode":"P0L 1N0",
    "sg:province":"ON",
    "sg:tags":[
        "parlor",
        "billiard"
    ],
    "wof:name":"Cue",
    "wof:placetype":"venue"
},
  "geometry": {"coordinates":[-83.67012800000001,49.689987],"type":"Point"}
}