{
  "type": "Feature",
  "properties": {
    "addr:full":"Baie-Comeau QC G4Z 1C6",
    "addr:postcode":"g4z 1c6",
    "iso:country":"CA",
    "sg:city":"Baie-Comeau",
    "sg:classifiers":[
        {
            "category":"Bars & Pubs",
            "type":"Food & Drink"
        }
    ],
    "sg:phone":"+1 418 294 4490",
    "sg:postcode":"G4Z 1C6",
    "sg:province":"QC",
    "sg:tags":[
        "lounge",
        "cocktail"
    ],
    "wof:name":"Bar Le Retro",
    "wof:placetype":"venue"
},
  "geometry": {"coordinates":[-68.1484909058,49.2426948547],"type":"Point"}
}