{
  "type": "Feature",
  "properties": {
    "addr:full":"Cornwall ON K6H 5R5",
    "addr:postcode":"k6h 5r5",
    "iso:country":"CA",
    "sg:city":"Cornwall",
    "sg:classifiers":[
        {
            "category":"Wholesale",
            "subcategory":"Electrical",
            "type":"Manufacturing & Wholesale Goods"
        }
    ],
    "sg:phone":"+1 613 938 5031",
    "sg:postcode":"K6H 5R5",
    "sg:province":"ON",
    "sg:tags":[
        "equipment",
        "electric",
        "supply"
    ],
    "wof:name":"Allnoram Supply Ltd",
    "wof:placetype":"venue"
},
  "geometry": {"coordinates":[-74.73569488530001,45.0284347534],"type":"Point"}
}