{
  "type": "Feature",
  "properties": {
    "addr:full":"350 138E Rue Shawinigan-Sud QC G9P 4S9",
    "addr:housenumber":"350",
    "addr:postcode":"g9p 4s9",
    "addr:street":"138E Rue Shawinigan-Sud",
    "iso:country":"CA",
    "sg:address":"350 138E Rue",
    "sg:city":"Shawinigan-Sud",
    "sg:classifiers":[
        {
            "category":"Building & Trades",
            "subcategory":"Plumbing",
            "type":"Services"
        }
    ],
    "sg:phone":"+1 819 537 7465",
    "sg:postcode":"G9P 4S9",
    "sg:province":"QC",
    "sg:tags":[
        "contractor"
    ],
    "wof:name":"Video DE Canalisation DE LA",
    "wof:placetype":"venue"
},
  "geometry": {"coordinates":[-72.731667,46.511833],"type":"Point"}
}