{
  "type": "Feature",
  "properties": {
    "addr:full":"1206 Yonge St Toronto ON M4T 1W1",
    "addr:housenumber":"1206",
    "addr:postcode":"m4t 1w1",
    "addr:street":"Yonge St",
    "iso:country":"CA",
    "sg:address":"1206 Yonge St",
    "sg:city":"Toronto",
    "sg:classifiers":[
        {
            "category":"Shopping",
            "subcategory":"Florist",
            "type":"Retail Goods"
        }
    ],
    "sg:phone":"+1 416 960 5800",
    "sg:postcode":"M4T 1W1",
    "sg:province":"ON",
    "wof:name":"Thriving Metropolis Flowers",
    "wof:placetype":"venue"
},
  "geometry": {"coordinates":[-79.391609,43.681671],"type":"Point"}
}