{
  "type": "Feature",
  "properties": {
    "addr:full":"Brampton ON L6T 5K9",
    "addr:postcode":"l6t 5k9",
    "iso:country":"CA",
    "sg:city":"Brampton",
    "sg:classifiers":[
        {
            "category":"Wholesale",
            "subcategory":"Machinery & Supplies",
            "type":"Manufacturing & Wholesale Goods"
        }
    ],
    "sg:phone":"+1 905 799 1618",
    "sg:postcode":"L6T 5K9",
    "sg:province":"ON",
    "sg:tags":[
        "machine"
    ],
    "wof:name":"Spindle Canada & Bearings",
    "wof:placetype":"venue"
},
  "geometry": {"coordinates":[-79.6511688232,43.7352867126],"type":"Point"}
}