{
  "type": "Feature",
  "properties": {
    "addr:full":"825 Coxwell Ave East York ON M4C 3E7",
    "addr:housenumber":"825",
    "addr:postcode":"m4c 3e7",
    "addr:street":"Coxwell Ave",
    "iso:country":"CA",
    "sg:address":"825 Coxwell Ave",
    "sg:city":"East York",
    "sg:classifiers":[
        {
            "category":"Health Services",
            "subcategory":"Hospital",
            "type":"Services"
        }
    ],
    "sg:phone":"+1 416 461 8272",
    "sg:postcode":"M4C 3E7",
    "sg:province":"ON",
    "wof:name":"Toronto East General Hospital",
    "wof:placetype":"venue"
},
  "geometry": {"coordinates":[-79.326286,43.690365],"type":"Point"}
}