{
  "type": "Feature",
  "properties": {
    "iso:country":"CA",
    "sg:address":"1301 Millwood Ave",
    "sg:city":"Brockville",
    "sg:classifiers":[
        {
            "category":"Real Estate",
            "subcategory":"Real Estate Operator",
            "type":"Services"
        }
    ],
    "sg:phone":"+1 613 498 2129",
    "sg:postcode":"K6V 6J4",
    "sg:province":"ON",
    "sg:tags":[
        "apartment"
    ],
    "wof:name":"Sheridan Green Townhouses",
    "wof:placetype":"venue"
},
  "geometry": {"coordinates":[-75.70309399999999,44.609756],"type":"Point"}
}