{
  "type": "Feature",
  "properties": {
    "addr:full":"10105 96 St NW Edmonton AB T5H 2G3",
    "addr:housenumber":"10105",
    "addr:postcode":"t5h 2g3",
    "addr:street":"96 St Nw",
    "iso:country":"CA",
    "sg:address":"10105 96 St NW",
    "sg:city":"Edmonton",
    "sg:classifiers":[
        {
            "category":"Organizations",
            "subcategory":"Religious Organization",
            "type":"Services"
        }
    ],
    "sg:phone":"+1 780 422 0277",
    "sg:postcode":"T5H 2G3",
    "sg:province":"AB",
    "sg:tags":[
        "church"
    ],
    "wof:name":"Russian Orthodox Cathedral",
    "wof:placetype":"venue"
},
  "geometry": {"coordinates":[-113.481567383,53.5432090759],"type":"Point"}
}