{
  "type": "Feature",
  "properties": {
    "addr:full":"1560 Bayview Ave Toronto ON M4G 3B8",
    "addr:housenumber":"1560",
    "addr:postcode":"m4g 3b8",
    "addr:street":"Bayview Ave",
    "iso:country":"CA",
    "sg:address":"1560 Bayview Ave",
    "sg:city":"Toronto",
    "sg:classifiers":[
        {
            "category":"Recreation",
            "type":"Entertainment"
        }
    ],
    "sg:phone":"+1 416 486 4448",
    "sg:postcode":"M4G 3B8",
    "sg:province":"ON",
    "sg:tags":[
        "instruction",
        "yoga"
    ],
    "wof:name":"Big Stretch Yoga Ctr",
    "wof:placetype":"venue"
},
  "geometry": {"coordinates":[-79.37520599370001,43.7053604126],"type":"Point"}
}