{
  "type": "Feature",
  "properties": {
    "addr:full":"Sexsmith AB T0H 3C0",
    "addr:postcode":"t0h 3c0",
    "iso:country":"CA",
    "sg:city":"Sexsmith",
    "sg:classifiers":[
        {
            "category":"Home & Garden",
            "subcategory":"Hardware",
            "type":"Retail Goods"
        }
    ],
    "sg:phone":"+1 780 568 4441",
    "sg:postcode":"T0H 3C0",
    "sg:province":"AB",
    "wof:name":"Handee Hardware & Rentals Ltd",
    "wof:placetype":"venue"
},
  "geometry": {"coordinates":[-118.784103,55.350163],"type":"Point"}
}