{
  "type": "Feature",
  "properties": {
    "addr:full":"Kingston ON K7L 3S7",
    "addr:postcode":"k7l 3s7",
    "iso:country":"CA",
    "sg:city":"Kingston",
    "sg:classifiers":[
        {
            "category":"Education",
            "subcategory":"School",
            "type":"Public Place"
        }
    ],
    "sg:phone":"+1 613 544 7698",
    "sg:postcode":"K7L 3S7",
    "sg:province":"ON",
    "wof:name":"Module Vanier Unit",
    "wof:placetype":"venue"
},
  "geometry": {"coordinates":[-76.498276,44.229359],"type":"Point"}
}