{
  "type": "Feature",
  "properties": {
    "iso:country":"CA",
    "sg:address":"7308 Delwood Rd NW",
    "sg:city":"Edmonton",
    "sg:classifiers":[
        {
            "category":"Real Estate",
            "subcategory":"Real Estate Agent",
            "type":"Services"
        }
    ],
    "sg:phone":"+1 780 478 5381",
    "sg:postcode":"T5C 3A7",
    "sg:province":"AB",
    "wof:name":"Milligan Realty Ltd",
    "wof:placetype":"venue"
},
  "geometry": {"coordinates":[-113.454185,53.597034],"type":"Point"}
}