{
  "type": "Feature",
  "properties": {
    "addr:full":"228 Rue Duquette Papineauville QC J0V 1R0",
    "addr:housenumber":"228",
    "addr:postcode":"j0v 1r0",
    "addr:street":"Rue Duquette",
    "iso:country":"CA",
    "sg:address":"228 Rue Duquette",
    "sg:city":"Papineauville",
    "sg:classifiers":[
        {
            "category":"Travel",
            "subcategory":"Hotels & Motels",
            "type":"Entertainment"
        }
    ],
    "sg:phone":"+1 819 427 5167",
    "sg:postcode":"J0V 1R0",
    "sg:province":"QC",
    "sg:tags":[
        "breakfast",
        "accommodation",
        "bed"
    ],
    "wof:name":"Au Fil Des Ans",
    "wof:placetype":"venue"
},
  "geometry": {"coordinates":[-75.01384,45.617924],"type":"Point"}
}