{
  "type": "Feature",
  "properties": {
    "addr:full":"103 Bates St Earl Grey SK S0G 1J0",
    "addr:housenumber":"103",
    "addr:postcode":"s0g 1j0",
    "addr:street":"Bates St",
    "iso:country":"CA",
    "sg:address":"103 Bates St",
    "sg:city":"Earl Grey",
    "sg:classifiers":[
        {
            "category":"Insurance",
            "subcategory":"Insurance Agent",
            "type":"Services"
        }
    ],
    "sg:phone":"+1 306 939 2136",
    "sg:postcode":"S0G 1J0",
    "sg:province":"SK",
    "wof:name":"Southery Agencies Inc",
    "wof:placetype":"venue"
},
  "geometry": {"coordinates":[-104.706329,50.937641],"type":"Point"}
}