{
  "type": "Feature",
  "properties": {
    "addr:full":"Saint-Marc-Des-Carrieres QC G0A 4B0",
    "addr:postcode":"g0a 4b0",
    "iso:country":"CA",
    "sg:city":"Saint-Marc-Des-Carrieres",
    "sg:classifiers":[
        {
            "category":"Building & Trades",
            "subcategory":"Landscaping Services",
            "type":"Services"
        }
    ],
    "sg:phone":"+1 418 268 8075",
    "sg:postcode":"G0A 4B0",
    "sg:province":"QC",
    "sg:tags":[
        "landscape",
        "contractor"
    ],
    "wof:name":"Cultures Tournesol Inc",
    "wof:placetype":"venue"
},
  "geometry": {"coordinates":[-72.05178100000001,46.682899],"type":"Point"}
}