{
  "type": "Feature",
  "properties": {
    "addr:full":"204 Rue Notre-Dame O Montreal QC H2Y 1T3",
    "addr:housenumber":"204",
    "addr:postcode":"h2y 1t3",
    "addr:street":"Rue Notre-Dame O",
    "iso:country":"CA",
    "sg:address":"204 Rue Notre-Dame O",
    "sg:city":"Montreal",
    "sg:classifiers":[
        {
            "category":"Professional",
            "subcategory":"Lawyer & Legal Services",
            "type":"Services"
        }
    ],
    "sg:phone":"+1 514 284 3058",
    "sg:postcode":"H2Y 1T3",
    "sg:province":"QC",
    "sg:tags":[
        "attorney"
    ],
    "wof:name":"Papineau & Assoc",
    "wof:placetype":"venue"
},
  "geometry": {"coordinates":[-73.55384100000001,45.508373],"type":"Point"}
}