{
  "type": "Feature",
  "properties": {
    "addr:full":"343 Airport Rd North Bay ON P1B 8W8",
    "addr:housenumber":"343",
    "addr:postcode":"p1b 8w8",
    "addr:street":"Airport Rd",
    "iso:country":"CA",
    "sg:address":"343 Airport Rd",
    "sg:city":"North Bay",
    "sg:classifiers":[
        {
            "category":"Education",
            "subcategory":"Special Training",
            "type":"Public Place"
        }
    ],
    "sg:phone":"+1 705 476 5320",
    "sg:postcode":"P1B 8W8",
    "sg:province":"ON",
    "sg:tags":[
        "instruction",
        "driving"
    ],
    "wof:name":"Young Drivers of Canada",
    "wof:placetype":"venue"
},
  "geometry": {"coordinates":[-79.4580535889,46.3359031677],"type":"Point"}
}