{
  "type": "Feature",
  "properties": {
    "addr:full":"300 Kane Ave York ON M6M 3P1",
    "addr:housenumber":"300",
    "addr:postcode":"m6m 3p1",
    "addr:street":"Kane Ave",
    "iso:country":"CA",
    "sg:address":"300 Kane Ave",
    "sg:city":"York",
    "sg:classifiers":[
        {
            "category":"Education",
            "subcategory":"School",
            "type":"Public Place"
        }
    ],
    "sg:phone":"+1 416 394 3033",
    "sg:postcode":"M6M 3P1",
    "sg:province":"ON",
    "wof:name":"Kane Middle School",
    "wof:placetype":"venue"
},
  "geometry": {"coordinates":[-79.4687957764,43.6869659424],"type":"Point"}
}