{
  "type": "Feature",
  "properties": {
    "addr:full":"York Haliburton ON K0M 1S0",
    "addr:postcode":"k0m 1s0",
    "iso:country":"CA",
    "sg:address":"York",
    "sg:city":"Haliburton",
    "sg:classifiers":[
        {
            "category":"Government",
            "subcategory":"Office",
            "type":"Public Place"
        }
    ],
    "sg:phone":"+1 705 457 2871",
    "sg:postcode":"K0M 1S0",
    "sg:province":"ON",
    "sg:tags":[
        "village"
    ],
    "wof:name":"Dysart & Al Tourist Info Booth",
    "wof:placetype":"venue"
},
  "geometry": {"coordinates":[-78.510628,45.046513],"type":"Point"}
}