{
  "type": "Feature",
  "properties": {
    "addr:full":"19 Rue Sonia Les Coteaux QC J7X 1M8",
    "addr:housenumber":"19",
    "addr:postcode":"j7x 1m8",
    "addr:street":"Rue Sonia",
    "iso:country":"CA",
    "sg:address":"19 Rue Sonia",
    "sg:city":"Les Coteaux",
    "sg:classifiers":[
        {
            "category":"Building & Trades",
            "subcategory":"Landscaping Services",
            "type":"Services"
        }
    ],
    "sg:phone":"+1 450 267 0227",
    "sg:postcode":"J7X 1M8",
    "sg:province":"QC",
    "sg:tags":[
        "lawn",
        "maintenance",
        "grounds"
    ],
    "wof:name":"Gazons Francois Levac",
    "wof:placetype":"venue"
},
  "geometry": {"coordinates":[-74.22893500000001,45.281273],"type":"Point"}
}