{
  "type": "Feature",
  "properties": {
    "addr:full":"593 Alma St Port Perry ON L9L 1C8",
    "addr:housenumber":"593",
    "addr:postcode":"l9l 1c8",
    "addr:street":"Alma St",
    "iso:country":"CA",
    "sg:address":"593 Alma St",
    "sg:city":"Port Perry",
    "sg:classifiers":[
        {
            "category":"Organizations",
            "subcategory":"Religious Organization",
            "type":"Services"
        }
    ],
    "sg:phone":"+1 905 985 1346",
    "sg:postcode":"L9L 1C8",
    "sg:province":"ON",
    "sg:tags":[
        "church"
    ],
    "wof:name":"Victory Christian Ctr",
    "wof:placetype":"venue"
},
  "geometry": {"coordinates":[-78.956741333,44.0959968567],"type":"Point"}
}