{
  "type": "Feature",
  "properties": {
    "addr:full":"White Rock BC V4B 2P7",
    "addr:postcode":"v4b 2p7",
    "iso:country":"CA",
    "sg:city":"White Rock",
    "sg:classifiers":[
        {
            "category":"Professional",
            "subcategory":"Lawyer & Legal Services",
            "type":"Services"
        }
    ],
    "sg:phone":"+1 604 531 9121",
    "sg:postcode":"V4B 2P7",
    "sg:province":"BC",
    "sg:tags":[
        "attorney"
    ],
    "wof:name":"Ginther, J Lorne",
    "wof:placetype":"venue"
},
  "geometry": {"coordinates":[-122.799446,49.029518],"type":"Point"}
}