{
  "type": "Feature",
  "properties": {
    "iso:country":"CA",
    "sg:address":"6223 Main St",
    "sg:city":"Stouffville",
    "sg:classifiers":[
        {
            "category":"Real Estate",
            "subcategory":"Real Estate Agent",
            "type":"Services"
        }
    ],
    "sg:phone":"+1 905 640 4151",
    "sg:postcode":"L4A 4J3",
    "sg:province":"ON",
    "wof:name":"Farquharson Realty Ltd",
    "wof:placetype":"venue"
},
  "geometry": {"coordinates":[-79.249344,43.97073],"type":"Point"}
}