{
  "type": "Feature",
  "properties": {
    "addr:full":"6223 Main St Stouffville ON L4A 4J3",
    "addr:housenumber":"6223",
    "addr:postcode":"l4a 4j3",
    "addr:street":"Main St",
    "iso:country":"CA",
    "sg:address":"6223 Main St",
    "sg:city":"Stouffville",
    "sg:classifiers":[
        {
            "category":"Real Estate",
            "subcategory":"Real Estate Agent",
            "type":"Services"
        }
    ],
    "sg:phone":"+1 905 640 4151",
    "sg:postcode":"L4A 4J3",
    "sg:province":"ON",
    "wof:name":"Farquharson Realty Ltd",
    "wof:placetype":"venue"
},
  "geometry": {"coordinates":[-79.24934399999999,43.97073],"type":"Point"}
}