{
  "type": "Feature",
  "properties": {
    "iso:country":"CA",
    "sg:address":"1753 Rue Grenet",
    "sg:city":"Saint-Laurent",
    "sg:classifiers":[
        {
            "category":"Real Estate",
            "subcategory":"Real Estate Operator",
            "type":"Services"
        }
    ],
    "sg:phone":"+1 514 875 6010",
    "sg:postcode":"H4L 2R6",
    "sg:province":"QC",
    "sg:tags":[
        "building",
        "parks"
    ],
    "wof:name":"Magil Laurentienne",
    "wof:placetype":"venue"
},
  "geometry": {"coordinates":[-73.69718933110001,45.5180854797],"type":"Point"}
}