{
  "type": "Feature",
  "properties": {
    "addr:full":"565 Rue DE LA Falaise Levis QC G6W 1A4",
    "addr:housenumber":"565",
    "addr:postcode":"g6w 1a4",
    "addr:street":"Rue De La Falaise",
    "iso:country":"CA",
    "sg:address":"565 Rue DE LA Falaise",
    "sg:city":"Levis",
    "sg:classifiers":[
        {
            "category":"Professional",
            "subcategory":"Advertising",
            "type":"Services"
        }
    ],
    "sg:phone":"+1 418 837 6068",
    "sg:postcode":"G6W 1A4",
    "sg:province":"QC",
    "wof:name":"Publicite Raymond Inc",
    "wof:placetype":"venue"
},
  "geometry": {"coordinates":[-71.191963,46.790527],"type":"Point"}
}