{
  "type": "Feature",
  "properties": {
    "addr:full":"1462 7E Av Pointe-Aux-Trembles QC H1B 4J7",
    "addr:housenumber":"1462",
    "addr:postcode":"h1b 4j7",
    "addr:street":"7E Av Pointe-Aux-Trembles",
    "iso:country":"CA",
    "sg:address":"1462 7E Av",
    "sg:city":"Pointe-Aux-Trembles",
    "sg:classifiers":[
        {
            "category":"Shopping",
            "subcategory":"Computers & Home Electronics",
            "type":"Retail Goods"
        }
    ],
    "sg:phone":"+1 514 645 1225",
    "sg:postcode":"H1B 4J7",
    "sg:province":"QC",
    "sg:tags":[
        "television",
        "radio"
    ],
    "wof:name":"Richard Omer & Fils Radio Tv",
    "wof:placetype":"venue"
},
  "geometry": {"coordinates":[-73.505081,45.639675],"type":"Point"}
}