{
  "type": "Feature",
  "properties": {
    "iso:country":"CA",
    "sg:address":"3960 20E Ave",
    "sg:city":"Saint-Prosper-DE-Dorchester",
    "sg:classifiers":[
        {
            "category":"Personal",
            "subcategory":"Beauty Salon",
            "type":"Services"
        }
    ],
    "sg:phone":"+1 418 594 5516",
    "sg:postcode":"G0M 1Y0",
    "sg:province":"QC",
    "wof:name":"Salon Lady Enr",
    "wof:placetype":"venue"
},
  "geometry": {"coordinates":[-70.49774932859999,46.2215538025],"type":"Point"}
}