{
  "type": "Feature",
  "properties": {
    "addr:full":"5371 Rue Frontenac Lac-Megantic QC G6B 1H4",
    "addr:housenumber":"5371",
    "addr:postcode":"g6b 1h4",
    "addr:street":"Rue Frontenac Lac-Megantic",
    "iso:country":"CA",
    "sg:address":"5371 Rue Frontenac",
    "sg:city":"Lac-Megantic",
    "sg:classifiers":[
        {
            "category":"Manufacturing",
            "subcategory":"Printing",
            "type":"Manufacturing & Wholesale Goods"
        }
    ],
    "sg:phone":"+1 819 583 1775",
    "sg:postcode":"G6B 1H4",
    "sg:province":"QC",
    "sg:tags":[
        "printer"
    ],
    "wof:name":"Imprimerie Multi-Copie Inc",
    "wof:placetype":"venue"
},
  "geometry": {"coordinates":[-70.882935,45.575256],"type":"Point"}
}