{
  "type": "Feature",
  "properties": {
    "iso:country":"CA",
    "sg:address":"55 Huron Rd E",
    "sg:city":"Shakespeare",
    "sg:classifiers":[
        {
            "category":"Shopping",
            "subcategory":"Discount & Variety Stores",
            "type":"Retail Goods"
        }
    ],
    "sg:phone":"+1 519 625 8205",
    "sg:postcode":"N0B 2P0",
    "sg:province":"ON",
    "wof:name":"Shakespeare Video & Variety",
    "wof:placetype":"venue"
},
  "geometry": {"coordinates":[-80.83023834230001,43.3695297241],"type":"Point"}
}