{
  "type": "Feature",
  "properties": {
    "addr:full":"9470 192 St Surrey BC V4N 3R9",
    "addr:housenumber":"9470",
    "addr:postcode":"v4n 3r9",
    "addr:street":"192 St",
    "iso:country":"CA",
    "sg:address":"9470 192 St",
    "sg:city":"Surrey",
    "sg:classifiers":[
        {
            "category":"Freight",
            "type":"Transportation"
        }
    ],
    "sg:phone":"+1 604 888 4322",
    "sg:postcode":"V4N 3R9",
    "sg:province":"BC",
    "sg:tags":[
        "trucking"
    ],
    "wof:name":"West Rim Express Lines Ltd",
    "wof:placetype":"venue"
},
  "geometry": {"coordinates":[-122.690262,49.174702],"type":"Point"}
}