{
  "type": "Feature",
  "properties": {
    "addr:full":"2400 Av Saint-Antoine Vaudreuil-Dorion QC J7V 8P2",
    "addr:housenumber":"2400",
    "addr:postcode":"j7v 8p2",
    "addr:street":"Av Saint-Antoine",
    "iso:country":"CA",
    "sg:address":"2400 Av Saint-Antoine",
    "sg:city":"Vaudreuil-Dorion",
    "sg:classifiers":[
        {
            "category":"Restaurant",
            "type":"Food & Drink"
        }
    ],
    "sg:phone":"+1 450 455 1100",
    "sg:postcode":"J7V 8P2",
    "sg:province":"QC",
    "wof:name":"Resto Pub Sunny's",
    "wof:placetype":"venue"
},
  "geometry": {"coordinates":[-74.035606,45.365795],"type":"Point"}
}