{
  "type": "Feature",
  "properties": {
    "addr:full":"8705 Rue Sherbrooke E Montreal QC H1L 1C1",
    "addr:housenumber":"8705",
    "addr:postcode":"h1l 1c1",
    "addr:street":"Rue Sherbrooke E",
    "iso:country":"CA",
    "sg:address":"8705 Rue Sherbrooke E",
    "sg:city":"Montreal",
    "sg:classifiers":[
        {
            "category":"Personal",
            "subcategory":"Beauty Salon",
            "type":"Services"
        }
    ],
    "sg:phone":"+1 514 352 5555",
    "sg:postcode":"H1L 1C1",
    "sg:province":"QC",
    "wof:name":"Coiffure LA Detente",
    "wof:placetype":"venue"
},
  "geometry": {"coordinates":[-73.53059399999999,45.604443],"type":"Point"}
}