{
  "type": "Feature",
  "properties": {
    "addr:full":"Richmond Hill ON L4B 1L6",
    "addr:postcode":"l4b 1l6",
    "iso:country":"CA",
    "sg:city":"Richmond Hill",
    "sg:classifiers":[
        {
            "category":"Retail",
            "subcategory":"Repair Shop",
            "type":"Services"
        }
    ],
    "sg:phone":"+1 905 764 8369",
    "sg:postcode":"L4B 1L6",
    "sg:province":"ON",
    "sg:tags":[
        "refinishing",
        "furniture"
    ],
    "wof:name":"Palmer Professional Rfnshng",
    "wof:placetype":"venue"
},
  "geometry": {"coordinates":[-79.3877487183,43.8472633362],"type":"Point"}
}