{
  "type": "Feature",
  "properties": {
    "addr:full":"Calgary AB T2P 3L8",
    "addr:postcode":"t2p 3l8",
    "iso:country":"CA",
    "sg:city":"Calgary",
    "sg:classifiers":[
        {
            "category":"Wholesale",
            "subcategory":"Petroleum",
            "type":"Manufacturing & Wholesale Goods"
        }
    ],
    "sg:phone":"+1 403 231 3900",
    "sg:postcode":"T2P 3L8",
    "sg:province":"AB",
    "sg:tags":[
        "pipe",
        "line",
        "company"
    ],
    "wof:name":"Enbridge Inc",
    "wof:placetype":"venue"
},
  "geometry": {"coordinates":[-114.065353,51.049057],"type":"Point"}
}