{
  "type": "Feature",
  "properties": {
    "addr:full":"242 Mary St #1132 Victoria BC V9A 3V9",
    "addr:housenumber":"242",
    "addr:postcode":"v9a 3v9",
    "addr:street":"Mary St # 1132",
    "iso:country":"CA",
    "sg:address":"242 Mary St #1132",
    "sg:city":"Victoria",
    "sg:classifiers":[
        {
            "category":"Arts & Performance",
            "subcategory":"Theater",
            "type":"Entertainment"
        }
    ],
    "sg:phone":"+1 250 479 1161",
    "sg:postcode":"V9A 3V9",
    "sg:province":"BC",
    "sg:tags":[
        "entertainer",
        "party",
        "planning"
    ],
    "wof:name":"In the Spotlight",
    "wof:placetype":"venue"
},
  "geometry": {"coordinates":[-123.386101,48.428997],"type":"Point"}
}