{
  "type": "Feature",
  "properties": {
    "addr:full":"190 Creditstone Rd Concord ON L4K 1P3",
    "addr:housenumber":"190",
    "addr:postcode":"l4k 1p3",
    "addr:street":"Creditstone Rd",
    "iso:country":"CA",
    "sg:address":"190 Creditstone Rd",
    "sg:city":"Concord",
    "sg:classifiers":[
        {
            "category":"Building & Trades",
            "subcategory":"Plumbing",
            "type":"Services"
        }
    ],
    "sg:phone":"+1 905 660 6163",
    "sg:postcode":"L4K 1P3",
    "sg:province":"ON",
    "sg:tags":[
        "contractor"
    ],
    "wof:name":"Bruno Plumbing & Contracting",
    "wof:placetype":"venue"
},
  "geometry": {"coordinates":[-79.5174789429,43.7935256958],"type":"Point"}
}