{
  "type": "Feature",
  "properties": {
    "addr:full":"652 2E Ave Grandes-Piles QC G0X 1H0",
    "addr:housenumber":"652",
    "addr:postcode":"g0x 1h0",
    "addr:street":"2E Ave",
    "iso:country":"CA",
    "sg:address":"652 2E Ave",
    "sg:city":"Grandes-Piles",
    "sg:classifiers":[
        {
            "category":"Home & Garden",
            "subcategory":"Household Appliances",
            "type":"Retail Goods"
        }
    ],
    "sg:phone":"+1 819 376 6419",
    "sg:postcode":"G0X 1H0",
    "sg:province":"QC",
    "wof:name":"Louis Pothier Enr",
    "wof:placetype":"venue"
},
  "geometry": {"coordinates":[-72.727119,46.686165],"type":"Point"}
}