{
  "type": "Feature",
  "properties": {
    "iso:country":"CA",
    "sg:address":"529 Queen St W",
    "sg:city":"Toronto",
    "sg:classifiers":[
        {
            "category":"Shopping",
            "subcategory":"Used Merchandise",
            "type":"Retail Goods"
        }
    ],
    "sg:phone":"+1 416 504 6036",
    "sg:postcode":"M5V 2B4",
    "sg:province":"ON",
    "sg:tags":[
        "antique"
    ],
    "wof:name":"Camelot Antiques",
    "wof:placetype":"venue"
},
  "geometry": {"coordinates":[-79.3992843628,43.6479759216],"type":"Point"}
}