{
  "type": "Feature",
  "properties": {
    "addr:full":"PO Box 6284 STN Main Edson AB T7E 1T7",
    "addr:housenumber":"po",
    "addr:postcode":"6284;t7e 1t7",
    "addr:street":"Box;Stn Main",
    "iso:country":"CA",
    "sg:address":"PO Box 6284 STN Main",
    "sg:city":"Edson",
    "sg:classifiers":[
        {
            "category":"Mining & Drilling",
            "type":"Manufacturing & Wholesale Goods"
        }
    ],
    "sg:phone":"+1 780 723 6171",
    "sg:postcode":"T7E 1T7",
    "sg:province":"AB",
    "sg:tags":[
        "field",
        "oil"
    ],
    "wof:name":"Gibsons Energy",
    "wof:placetype":"venue"
},
  "geometry": {"coordinates":[-116.43409729,53.5821304321],"type":"Point"}
}