{
  "type": "Feature",
  "properties": {
    "addr:full":"1600 Boul Henri-Bourassa O Montreal QC H3M 3E2",
    "addr:housenumber":"1600",
    "addr:postcode":"h3m 3e2",
    "addr:street":"Boul Henri-Bourassa O",
    "iso:country":"CA",
    "sg:address":"1600 Boul Henri-Bourassa O",
    "sg:city":"Montreal",
    "sg:classifiers":[
        {
            "category":"Wholesale",
            "subcategory":"Electrical",
            "type":"Manufacturing & Wholesale Goods"
        }
    ],
    "sg:phone":"+1 514 336 4143",
    "sg:postcode":"H3M 3E2",
    "sg:province":"QC",
    "sg:tags":[
        "light",
        "tube",
        "bulb"
    ],
    "wof:name":"Duro-Test Canada Inc",
    "wof:placetype":"venue"
},
  "geometry": {"coordinates":[-73.678719,45.5368],"type":"Point"}
}