{
  "type": "Feature",
  "properties": {
    "addr:full":"203 Bathurst St London ON N6B 1P1",
    "addr:housenumber":"203",
    "addr:postcode":"n6b 1p1",
    "addr:street":"Bathurst St",
    "iso:country":"CA",
    "sg:address":"203 Bathurst St",
    "sg:city":"London",
    "sg:classifiers":[
        {
            "category":"Freight",
            "type":"Transportation"
        }
    ],
    "sg:phone":"+1 519 645 2466",
    "sg:postcode":"N6B 1P1",
    "sg:province":"ON",
    "sg:tags":[
        "commercial",
        "storage"
    ],
    "wof:name":"City Centre Storage",
    "wof:placetype":"venue"
},
  "geometry": {"coordinates":[-81.24751281739999,42.9800567627],"type":"Point"}
}