{
  "type": "Feature",
  "properties": {
    "iso:country":"CA",
    "sg:address":"131 Kee Rd",
    "sg:city":"Keswick Ridge",
    "sg:classifiers":[
        {
            "category":"Professional",
            "subcategory":"Management & Consulting",
            "type":"Services"
        }
    ],
    "sg:phone":"+1 506 363 2060",
    "sg:postcode":"E6L 1V3",
    "sg:province":"NB",
    "sg:tags":[
        "consultant",
        "business"
    ],
    "wof:name":"Gallop Associates",
    "wof:placetype":"venue"
},
  "geometry": {"coordinates":[-66.8811035156,45.9913749695],"type":"Point"}
}