{
  "type": "Feature",
  "properties": {
    "addr:full":"6115 Rue Jogues Montreal QC H4E 2W2",
    "addr:housenumber":"6115",
    "addr:postcode":"h4e 2w2",
    "addr:street":"Rue Jogues",
    "iso:country":"CA",
    "sg:address":"6115 Rue Jogues",
    "sg:city":"Montreal",
    "sg:classifiers":[
        {
            "category":"Organizations",
            "subcategory":"Religious Organization",
            "type":"Services"
        }
    ],
    "sg:phone":"+1 514 766 7615",
    "sg:postcode":"H4E 2W2",
    "sg:province":"QC",
    "sg:tags":[
        "church"
    ],
    "wof:name":"St-Jean-Damascene Church",
    "wof:placetype":"venue"
},
  "geometry": {"coordinates":[-73.6026382446,45.456489563],"type":"Point"}
}