{
  "type": "Feature",
  "properties": {
    "addr:full":"369 Prince St #2 Sydney NS B1P 5L2",
    "addr:housenumber":"369",
    "addr:postcode":"b1p 5l2",
    "addr:street":"Prince St # 2",
    "iso:country":"CA",
    "sg:address":"369 Prince St #2",
    "sg:city":"Sydney",
    "sg:classifiers":[
        {
            "category":"Organizations",
            "subcategory":"Labor Organization",
            "type":"Services"
        }
    ],
    "sg:phone":"+1 902 562 5659",
    "sg:postcode":"B1P 5L2",
    "sg:province":"NS",
    "wof:name":"International Union-Operating",
    "wof:placetype":"venue"
},
  "geometry": {"coordinates":[-60.182133,46.140118],"type":"Point"}
}