{
  "type": "Feature",
  "properties": {
    "iso:country":"CA",
    "sg:city":"Senneterre",
    "sg:classifiers":[
        {
            "category":"Government",
            "subcategory":"Office",
            "type":"Public Place"
        }
    ],
    "sg:phone":"+1 819 737 7719",
    "sg:postcode":"J0Y 2M0",
    "sg:province":"QC",
    "wof:name":"Canada Deputes Federaux",
    "wof:placetype":"venue"
},
  "geometry": {"coordinates":[-77.2422714233,48.3907318115],"type":"Point"}
}