{
  "type": "Feature",
  "properties": {
    "addr:full":"100 Dundas St W Whitby ON L1N 2L9",
    "addr:housenumber":"100",
    "addr:postcode":"l1n 2l9",
    "addr:street":"Dundas St W",
    "iso:country":"CA",
    "sg:address":"100 Dundas St W",
    "sg:city":"Whitby",
    "sg:classifiers":[
        {
            "category":"Shopping",
            "subcategory":"Florist",
            "type":"Retail Goods"
        }
    ],
    "sg:phone":"+1 905 668 1650",
    "sg:postcode":"L1N 2L9",
    "sg:province":"ON",
    "wof:name":"Van Belle Floral & Plant",
    "wof:placetype":"venue"
},
  "geometry": {"coordinates":[-78.9423980713,43.8799285889],"type":"Point"}
}