{
  "type": "Feature",
  "properties": {
    "addr:full":"5 Rue Church Ormstown QC J0S 1K0",
    "addr:housenumber":"5",
    "addr:postcode":"j0s 1k0",
    "addr:street":"Rue Church",
    "iso:country":"CA",
    "sg:address":"5 Rue Church",
    "sg:city":"Ormstown",
    "sg:classifiers":[
        {
            "category":"Shopping",
            "subcategory":"Used Merchandise",
            "type":"Retail Goods"
        }
    ],
    "sg:phone":"+1 450 829 3647",
    "sg:postcode":"J0S 1K0",
    "sg:province":"QC",
    "sg:tags":[
        "second",
        "store",
        "hand"
    ],
    "wof:name":"Rosie's Enr",
    "wof:placetype":"venue"
},
  "geometry": {"coordinates":[-73.99395,45.126789],"type":"Point"}
}