{
  "type": "Feature",
  "properties": {
    "addr:full":"100th St Tisdale SK S0E 1T0",
    "addr:postcode":"s0e 1t0",
    "addr:street":"St",
    "iso:country":"CA",
    "sg:address":"100th St",
    "sg:city":"Tisdale",
    "sg:classifiers":[
        {
            "category":"Manufacturing",
            "subcategory":"Metals",
            "type":"Manufacturing & Wholesale Goods"
        }
    ],
    "sg:phone":"+1 306 873 3015",
    "sg:postcode":"S0E 1T0",
    "sg:province":"SK",
    "sg:tags":[
        "steel"
    ],
    "wof:name":"Delorme's Steel & Repair",
    "wof:placetype":"venue"
},
  "geometry": {"coordinates":[-104.045059204,52.8570213318],"type":"Point"}
}