{
  "type": "Feature",
  "properties": {
    "addr:full":"Kitchener ON N2R 1J5",
    "addr:postcode":"n2r 1j5",
    "iso:country":"CA",
    "sg:city":"Kitchener",
    "sg:classifiers":[
        {
            "category":"Wholesale",
            "subcategory":"Groceries",
            "type":"Manufacturing & Wholesale Goods"
        }
    ],
    "sg:phone":"+1 519 748 0121",
    "sg:postcode":"N2R 1J5",
    "sg:province":"ON",
    "sg:tags":[
        "beverage"
    ],
    "wof:name":"Slush Puppies Canada Inc",
    "wof:placetype":"venue"
},
  "geometry": {"coordinates":[-80.4776,43.404171],"type":"Point"}
}