{
  "type": "Feature",
  "properties": {
    "addr:full":"Meadow Bank Cornwall PE C0A 1H0",
    "addr:postcode":"c0a 1h0",
    "iso:country":"CA",
    "sg:address":"Meadow Bank",
    "sg:city":"Cornwall",
    "sg:classifiers":[
        {
            "category":"Travel",
            "subcategory":"Hotels & Motels",
            "type":"Entertainment"
        }
    ],
    "sg:phone":"+1 902 628 2022",
    "sg:postcode":"C0A 1H0",
    "sg:province":"PE",
    "sg:tags":[
        "cottage",
        "cabin"
    ],
    "wof:name":"Meadowbank Cottages",
    "wof:placetype":"venue"
},
  "geometry": {"coordinates":[-63.2194404602,46.2235488892],"type":"Point"}
}