{
  "type": "Feature",
  "properties": {
    "addr:full":"427 Talbot St St Thomas ON N5P 1C1",
    "addr:housenumber":"427",
    "addr:postcode":"n5p 1c1",
    "addr:street":"Talbot St",
    "iso:country":"CA",
    "sg:address":"427 Talbot St",
    "sg:city":"St Thomas",
    "sg:classifiers":[
        {
            "category":"Government",
            "subcategory":"Office",
            "type":"Public Place"
        }
    ],
    "sg:phone":"+1 519 631 3032",
    "sg:postcode":"N5P 1C1",
    "sg:province":"ON",
    "wof:name":"Ontario Community & Social Svc",
    "wof:placetype":"venue"
},
  "geometry": {"coordinates":[-81.196198,42.77916],"type":"Point"}
}