{
  "type": "Feature",
  "properties": {
    "iso:country":"CA",
    "sg:address":"314 Kitchener Rd",
    "sg:city":"Cambridge",
    "sg:classifiers":[
        {
            "category":"Wholesale",
            "subcategory":"Vending Machines",
            "type":"Manufacturing & Wholesale Goods"
        }
    ],
    "sg:phone":"+1 519 650 6500",
    "sg:postcode":"N3H 1A6",
    "sg:province":"ON",
    "wof:name":"Galt Vending Ltd",
    "wof:placetype":"venue"
},
  "geometry": {"coordinates":[-80.3745422363,43.4018249512],"type":"Point"}
}