{
  "type": "Feature",
  "properties": {
    "iso:country":"CA",
    "sg:address":"6155 Ch Saint-Francois",
    "sg:city":"Saint-Laurent",
    "sg:classifiers":[
        {
            "category":"Manufacturing",
            "subcategory":"Tools & Machinery",
            "type":"Manufacturing & Wholesale Goods"
        }
    ],
    "sg:phone":"+1 514 956 1603",
    "sg:postcode":"H4S 1B6",
    "sg:province":"QC",
    "sg:tags":[
        "packaging"
    ],
    "wof:name":"Saturn Machinerie D'Emballage",
    "wof:placetype":"venue"
},
  "geometry": {"coordinates":[-73.74211120610001,45.4849853516],"type":"Point"}
}