{
  "type": "Feature",
  "properties": {
    "addr:full":"93 Rte Jacques-Cartier Ste-Catherine-DE-LA-J-Cartier QC G0A 3M0",
    "addr:housenumber":"93",
    "addr:postcode":"g0a 3m0",
    "addr:street":"Rte Jacques-Cartier Ste-Catherine-De-La-J-Cartier",
    "iso:country":"CA",
    "sg:address":"93 Rte Jacques-Cartier",
    "sg:city":"Ste-Catherine-DE-LA-J-Cartier",
    "sg:classifiers":[
        {
            "category":"Building & Trades",
            "subcategory":"Construction",
            "type":"Services"
        }
    ],
    "sg:phone":"+1 418 655 3207",
    "sg:postcode":"G0A 3M0",
    "sg:province":"QC",
    "sg:tags":[
        "tile",
        "dealer"
    ],
    "wof:name":"Ceramiques Ceramtek Inc",
    "wof:placetype":"venue"
},
  "geometry": {"coordinates":[-71.6016693115,46.8471717834],"type":"Point"}
}