{
  "type": "Feature",
  "properties": {
    "addr:full":"2925 Boul Pere-Lelievre Quebec QC G1P 2X9",
    "addr:housenumber":"2925",
    "addr:postcode":"g1p 2x9",
    "addr:street":"Boul Pere-Lelievre",
    "iso:country":"CA",
    "sg:address":"2925 Boul Pere-Lelievre",
    "sg:city":"Quebec",
    "sg:classifiers":[
        {
            "category":"Retail",
            "subcategory":"Animal Services",
            "type":"Services"
        }
    ],
    "sg:phone":"+1 418 683 1121",
    "sg:postcode":"G1P 2X9",
    "sg:province":"QC",
    "sg:tags":[
        "pet",
        "grooming",
        "washing"
    ],
    "wof:name":"Salon Canin",
    "wof:placetype":"venue"
},
  "geometry": {"coordinates":[-71.311218,46.812283],"type":"Point"}
}