{
  "type": "Feature",
  "properties": {
    "addr:full":"55 Moffatt's Rd Mount Pearl NL A1N 5B9",
    "addr:housenumber":"55",
    "addr:postcode":"a1n 5b9",
    "addr:street":"Moffatt'S Rd",
    "iso:country":"CA",
    "sg:address":"55 Moffatt's Rd",
    "sg:city":"Mount Pearl",
    "sg:classifiers":[
        {
            "category":"Manufacturing",
            "subcategory":"Metals",
            "type":"Manufacturing & Wholesale Goods"
        }
    ],
    "sg:phone":"+1 709 368 8541",
    "sg:postcode":"A1N 5B9",
    "sg:province":"NL",
    "sg:tags":[
        "steel"
    ],
    "wof:name":"Harris Rebar",
    "wof:placetype":"venue"
},
  "geometry": {"coordinates":[-52.8197212219,47.5163993835],"type":"Point"}
}