{
  "type": "Feature",
  "properties": {
    "addr:full":"2506 Yonge St Toronto ON M4P 2H7",
    "addr:housenumber":"2506",
    "addr:postcode":"m4p 2h7",
    "addr:street":"Yonge St",
    "iso:country":"CA",
    "sg:address":"2506 Yonge St",
    "sg:city":"Toronto",
    "sg:classifiers":[
        {
            "category":"Shopping",
            "subcategory":"Shoes",
            "type":"Retail Goods"
        }
    ],
    "sg:phone":"+1 416 489 3290",
    "sg:postcode":"M4P 2H7",
    "sg:province":"ON",
    "wof:name":"Susanne Shoe Salon",
    "wof:placetype":"venue"
},
  "geometry": {"coordinates":[-79.3996582031,43.7121315002],"type":"Point"}
}