{
  "type": "Feature",
  "properties": {
    "addr:full":"Edmonton AB T6E 5J3",
    "addr:postcode":"t6e 5j3",
    "iso:country":"CA",
    "sg:city":"Edmonton",
    "sg:classifiers":[
        {
            "category":"Banks & Credit Unions",
            "subcategory":"Investment Brokerage",
            "type":"Services"
        }
    ],
    "sg:phone":"+1 780 468 1658",
    "sg:postcode":"T6E 5J3",
    "sg:province":"AB",
    "sg:tags":[
        "consultant",
        "planning",
        "financial"
    ],
    "wof:name":"Investors Group Financial Svc",
    "wof:placetype":"venue"
},
  "geometry": {"coordinates":[-113.464347839,53.4879302979],"type":"Point"}
}