{
  "type": "Feature",
  "properties": {
    "addr:full":"1138 Boul Sainte-Marguerite Mercier QC J6R 2L1",
    "addr:housenumber":"1138",
    "addr:postcode":"j6r 2l1",
    "addr:street":"Boul Sainte-Marguerite",
    "iso:country":"CA",
    "sg:address":"1138 Boul Sainte-Marguerite",
    "sg:city":"Mercier",
    "sg:classifiers":[
        {
            "category":"Wholesale",
            "subcategory":"Machinery & Supplies",
            "type":"Manufacturing & Wholesale Goods"
        }
    ],
    "sg:phone":"+1 450 692 0702",
    "sg:postcode":"J6R 2L1",
    "sg:province":"QC",
    "sg:tags":[
        "pulverizing",
        "recycling",
        "crushing",
        "center"
    ],
    "wof:name":"Recy-Mat Inc",
    "wof:placetype":"venue"
},
  "geometry": {"coordinates":[-73.7320480347,45.2975959778],"type":"Point"}
}