{
  "type": "Feature",
  "properties": {
    "addr:full":"Stratford QC G0Y 1P0",
    "addr:postcode":"g0y 1p0",
    "iso:country":"CA",
    "sg:city":"Stratford",
    "sg:classifiers":[
        {
            "category":"Education",
            "subcategory":"Library",
            "type":"Public Place"
        }
    ],
    "sg:phone":"+1 418 443 2665",
    "sg:postcode":"G0Y 1P0",
    "sg:province":"QC",
    "sg:tags":[
        "government"
    ],
    "wof:name":"Stratford Bibliotheque",
    "wof:placetype":"venue"
},
  "geometry": {"coordinates":[-71.2829818726,45.7819252014],"type":"Point"}
}