{
  "type": "Feature",
  "properties": {
    "addr:full":"1500 Fisher St North Bay ON P1B 2H3",
    "addr:housenumber":"1500",
    "addr:postcode":"p1b 2h3",
    "addr:street":"Fisher St",
    "iso:country":"CA",
    "sg:address":"1500 Fisher St",
    "sg:city":"North Bay",
    "sg:classifiers":[
        {
            "category":"Food & Beverages",
            "subcategory":"Groceries & Convenience Stores",
            "type":"Retail Goods"
        }
    ],
    "sg:phone":"+1 705 475 9128",
    "sg:postcode":"P1B 2H3",
    "sg:province":"ON",
    "sg:tags":[
        "health",
        "diet"
    ],
    "wof:name":"Bulk Barn",
    "wof:placetype":"venue"
},
  "geometry": {"coordinates":[-79.4432067871,46.3128318787],"type":"Point"}
}