{
  "type": "Feature",
  "properties": {
    "addr:full":"591 Rue DE Roberval Boucherville QC J4B 7S9",
    "addr:housenumber":"591",
    "addr:postcode":"j4b 7s9",
    "addr:street":"Rue De Roberval",
    "iso:country":"CA",
    "sg:address":"591 Rue DE Roberval",
    "sg:city":"Boucherville",
    "sg:classifiers":[
        {
            "category":"Professional",
            "subcategory":"Accounting & Tax Preparation",
            "type":"Services"
        }
    ],
    "sg:phone":"+1 450 655 0061",
    "sg:postcode":"J4B 7S9",
    "sg:province":"QC",
    "sg:tags":[
        "accountant"
    ],
    "wof:name":"Solution Impot & Comptabilite",
    "wof:placetype":"venue"
},
  "geometry": {"coordinates":[-73.4323501587,45.5957756042],"type":"Point"}
}