{
  "type": "Feature",
  "properties": {
    "addr:full":"1130 Concession Rd 4 Brock Sunderland ON L0C 1H0",
    "addr:housenumber":"1130",
    "addr:postcode":"l0c 1h0",
    "addr:street":"Concession Rd 4",
    "iso:country":"CA",
    "sg:address":"1130 Concession Rd 4 Brock",
    "sg:city":"Sunderland",
    "sg:classifiers":[
        {
            "category":"Building & Trades",
            "subcategory":"Landscaping Services",
            "type":"Services"
        }
    ],
    "sg:phone":"+1 705 357 1434",
    "sg:postcode":"L0C 1H0",
    "sg:province":"ON",
    "sg:tags":[
        "landscape",
        "contractor"
    ],
    "wof:name":"Revive Landscaping",
    "wof:placetype":"venue"
},
  "geometry": {"coordinates":[-79.06613900000001,44.254913],"type":"Point"}
}