{
  "type": "Feature",
  "properties": {
    "addr:full":"245 Edward St St Thomas ON N5P 1Z4",
    "addr:housenumber":"245",
    "addr:postcode":"n5p 1z4",
    "addr:street":"Edward St",
    "iso:country":"CA",
    "sg:address":"245 Edward St",
    "sg:city":"St Thomas",
    "sg:classifiers":[
        {
            "category":"Wholesale",
            "subcategory":"Electrical",
            "type":"Manufacturing & Wholesale Goods"
        }
    ],
    "sg:phone":"+1 519 637 0826",
    "sg:postcode":"N5P 1Z4",
    "sg:province":"ON",
    "sg:tags":[
        "communication",
        "radio",
        "system"
    ],
    "wof:name":"Spectrum Communications",
    "wof:placetype":"venue"
},
  "geometry": {"coordinates":[-81.151566,42.785881],"type":"Point"}
}