{
  "type": "Feature",
  "properties": {
    "addr:full":"Mississauga ON L4W 4X8",
    "addr:postcode":"l4w 4x8",
    "iso:country":"CA",
    "sg:city":"Mississauga",
    "sg:classifiers":[
        {
            "category":"Retail",
            "subcategory":"Car Wash",
            "type":"Services"
        }
    ],
    "sg:phone":"+1 905 565 0110",
    "sg:postcode":"L4W 4X8",
    "sg:province":"ON",
    "sg:tags":[
        "repairing",
        "automobile",
        "polishing",
        "washing"
    ],
    "wof:name":"Hanmark Auto Salon",
    "wof:placetype":"venue"
},
  "geometry": {"coordinates":[-79.63665008540001,43.6582794189],"type":"Point"}
}