{
  "type": "Feature",
  "properties": {
    "addr:full":"596 Westmeath Rd Pembroke ON K8A 6W2",
    "addr:housenumber":"596",
    "addr:postcode":"k8a 6w2",
    "addr:street":"Westmeath Rd",
    "iso:country":"CA",
    "sg:address":"596 Westmeath Rd",
    "sg:city":"Pembroke",
    "sg:classifiers":[
        {
            "category":"Manufacturing",
            "subcategory":"Electronics",
            "type":"Manufacturing & Wholesale Goods"
        }
    ],
    "sg:phone":"+1 613 582 7372",
    "sg:postcode":"K8A 6W2",
    "sg:province":"ON",
    "sg:tags":[
        "equipment",
        "industrial",
        "electronic"
    ],
    "wof:name":"Technifest",
    "wof:placetype":"venue"
},
  "geometry": {"coordinates":[-77.1122131348,45.8264808655],"type":"Point"}
}