{
  "type": "Feature",
  "properties": {
    "addr:full":"7640 200 St Langley BC V2Y 1S4",
    "addr:housenumber":"7640",
    "addr:postcode":"v2y 1s4",
    "addr:street":"200 St",
    "iso:country":"CA",
    "sg:address":"7640 200 St",
    "sg:city":"Langley",
    "sg:classifiers":[
        {
            "category":"Organizations",
            "subcategory":"Religious Organization",
            "type":"Services"
        }
    ],
    "sg:phone":"+1 604 530 2662",
    "sg:postcode":"V2Y 1S4",
    "sg:province":"BC",
    "sg:tags":[
        "church"
    ],
    "wof:name":"Mountainview Alliance Church",
    "wof:placetype":"venue"
},
  "geometry": {"coordinates":[-122.668083,49.141579],"type":"Point"}
}