{
  "type": "Feature",
  "properties": {
    "addr:full":"5970 Rochdale Blvd Regina SK S4X 4J7",
    "addr:housenumber":"5970",
    "addr:postcode":"s4x 4j7",
    "addr:street":"Rochdale Blvd",
    "iso:country":"CA",
    "sg:address":"5970 Rochdale Blvd",
    "sg:city":"Regina",
    "sg:classifiers":[
        {
            "category":"Restaurant",
            "type":"Food & Drink"
        }
    ],
    "sg:phone":"+1 306 791 0133",
    "sg:postcode":"S4X 4J7",
    "sg:province":"SK",
    "wof:name":"Mr Sub",
    "wof:placetype":"venue"
},
  "geometry": {"coordinates":[-104.66506200000001,50.496014],"type":"Point"}
}