{
  "type": "Feature",
  "properties": {
    "addr:full":"400 Boul Cremazie O Montreal QC H2P 1C7",
    "addr:housenumber":"400",
    "addr:postcode":"h2p 1c7",
    "addr:street":"Boul Cremazie O",
    "iso:country":"CA",
    "sg:address":"400 Boul Cremazie O",
    "sg:city":"Montreal",
    "sg:classifiers":[
        {
            "category":"Wholesale",
            "subcategory":"Fruits & Vegetables",
            "type":"Manufacturing & Wholesale Goods"
        }
    ],
    "sg:phone":"+1 514 382 7520",
    "sg:postcode":"H2P 1C7",
    "sg:province":"QC",
    "wof:name":"J B Laverdure Inc",
    "wof:placetype":"venue"
},
  "geometry": {"coordinates":[-73.6382980347,45.5455284119],"type":"Point"}
}