{
  "type": "Feature",
  "properties": {
    "addr:full":"Saskatoon SK S7L 6H2",
    "addr:postcode":"s7l 6h2",
    "iso:country":"CA",
    "sg:city":"Saskatoon",
    "sg:classifiers":[
        {
            "category":"Manufacturing",
            "subcategory":"Printing",
            "type":"Manufacturing & Wholesale Goods"
        }
    ],
    "sg:phone":"+1 306 244 3988",
    "sg:postcode":"S7L 6H2",
    "sg:province":"SK",
    "sg:tags":[
        "printer"
    ],
    "wof:name":"Saskatoon Fastprint Ltd",
    "wof:placetype":"venue"
},
  "geometry": {"coordinates":[-106.673317,52.16404],"type":"Point"}
}