{
  "type": "Feature",
  "properties": {
    "iso:country":"CA",
    "sg:address":"98 Durand Rd",
    "sg:city":"Winnipeg",
    "sg:classifiers":[
        {
            "category":"Manufacturing",
            "subcategory":"Apparel",
            "type":"Manufacturing & Wholesale Goods"
        }
    ],
    "sg:phone":"+1 204 661 6428",
    "sg:postcode":"R2J 3T2",
    "sg:province":"MB",
    "sg:tags":[
        "cloth",
        "wiping"
    ],
    "wof:name":"Superior Wiping Products Ltd",
    "wof:placetype":"venue"
},
  "geometry": {"coordinates":[-97.03960418699999,49.8843078613],"type":"Point"}
}