{
  "type": "Feature",
  "properties": {
    "addr:full":"Jasper AB T0E 1E0",
    "addr:postcode":"t0e 1e0",
    "iso:country":"CA",
    "sg:city":"Jasper",
    "sg:classifiers":[
        {
            "category":"Health Services",
            "subcategory":"Doctor",
            "type":"Services"
        }
    ],
    "sg:phone":"+1 780 852 3012",
    "sg:postcode":"T0E 1E0",
    "sg:province":"AB",
    "sg:tags":[
        "dentist"
    ],
    "wof:name":"Jasper Dental Clinic",
    "wof:placetype":"venue"
},
  "geometry": {"coordinates":[-118.07963599999999,52.878777],"type":"Point"}
}