{
  "type": "Feature",
  "properties": {
    "addr:full":"Medicine Hat AB T1A 8G3",
    "addr:postcode":"t1a 8g3",
    "iso:country":"CA",
    "sg:city":"Medicine Hat",
    "sg:classifiers":[
        {
            "category":"Professional",
            "subcategory":"Engineering",
            "type":"Services"
        }
    ],
    "sg:phone":"+1 403 527 5871",
    "sg:postcode":"T1A 8G3",
    "sg:province":"AB",
    "sg:tags":[
        "engineer"
    ],
    "wof:name":"Amec Earth Environmental Ltd",
    "wof:placetype":"venue"
},
  "geometry": {"coordinates":[-110.708450317,50.0177879333],"type":"Point"}
}