{
  "type": "Feature",
  "properties": {
    "iso:country":"CA",
    "sg:city":"Parry Sound",
    "sg:classifiers":[
        {
            "category":"Home & Garden",
            "subcategory":"Household Appliances",
            "type":"Retail Goods"
        }
    ],
    "sg:phone":"+1 705 746 2191",
    "sg:postcode":"P2A 3A9",
    "sg:province":"ON",
    "wof:name":"Sears Canada Inc",
    "wof:placetype":"venue"
},
  "geometry": {"coordinates":[-80.04033660890001,45.3603630066],"type":"Point"}
}