{
  "type": "Feature",
  "properties": {
    "addr:full":"105 Rowena Dr #1B North York ON M3A 1R2",
    "addr:housenumber":"105;1b",
    "addr:postcode":"m3a 1r2",
    "addr:street":"Rowena Dr #",
    "iso:country":"CA",
    "sg:address":"105 Rowena Dr #1B",
    "sg:city":"North York",
    "sg:classifiers":[
        {
            "category":"Freight",
            "type":"Transportation"
        }
    ],
    "sg:phone":"+1 416 444 2322",
    "sg:postcode":"M3A 1R2",
    "sg:province":"ON",
    "sg:tags":[
        "delivery",
        "courier"
    ],
    "wof:name":"Pds Courier Ltd",
    "wof:placetype":"venue"
},
  "geometry": {"coordinates":[-79.315079,43.750927],"type":"Point"}
}