{
  "type": "Feature",
  "properties": {
    "addr:full":"8531 Ch Delmeade Mont-Royal QC H4T 1M1",
    "addr:housenumber":"8531",
    "addr:postcode":"h4t 1m1",
    "addr:street":"Ch Delmeade",
    "iso:country":"CA",
    "sg:address":"8531 Ch Delmeade",
    "sg:city":"Mont-Royal",
    "sg:classifiers":[
        {
            "category":"Manufacturing",
            "subcategory":"Textiles",
            "type":"Manufacturing & Wholesale Goods"
        }
    ],
    "sg:phone":"+1 514 343 5511",
    "sg:postcode":"H4T 1M1",
    "sg:province":"QC",
    "sg:tags":[
        "knitted",
        "fabric"
    ],
    "wof:name":"Tricots Interlock Knit",
    "wof:placetype":"venue"
},
  "geometry": {"coordinates":[-73.679306,45.491749],"type":"Point"}
}