{
  "type": "Feature",
  "properties": {
    "iso:country":"CA",
    "sg:address":"17388 Ch Sainte-Marie",
    "sg:city":"Kirkland",
    "sg:classifiers":[
        {
            "category":"Social Services",
            "subcategory":"Child Care",
            "type":"Services"
        }
    ],
    "sg:phone":"+1 514 426 3339",
    "sg:postcode":"H9J 2L2",
    "sg:province":"QC",
    "wof:name":"Royaume Des Reves",
    "wof:placetype":"venue"
},
  "geometry": {"coordinates":[-73.8688201904,45.4444465637],"type":"Point"}
}