{
  "type": "Feature",
  "properties": {
    "addr:full":"2139 Huron Church Rd Windsor ON N9C 2L8",
    "addr:housenumber":"2139",
    "addr:postcode":"n9c 2l8",
    "addr:street":"Huron Church Rd",
    "iso:country":"CA",
    "sg:address":"2139 Huron Church Rd",
    "sg:city":"Windsor",
    "sg:classifiers":[
        {
            "category":"Autos & Motor Vehicles",
            "subcategory":"Motorcycle Sales",
            "type":"Retail Goods"
        }
    ],
    "sg:phone":"+1 519 966 1520",
    "sg:postcode":"N9C 2L8",
    "sg:province":"ON",
    "sg:tags":[
        "scooter"
    ],
    "wof:name":"Thunder Road Harley Davidson",
    "wof:placetype":"venue"
},
  "geometry": {"coordinates":[-83.051574707,42.276512146],"type":"Point"}
}