{
  "type": "Feature",
  "properties": {
    "addr:full":"3725 Rue Saint-Henri Beauport QC G1E 2T4",
    "addr:housenumber":"3725",
    "addr:postcode":"qc g1e 2t4",
    "addr:street":"Rue Saint-Henri",
    "iso:country":"CA",
    "sg:address":"3725 Rue Saint-Henri",
    "sg:city":"Beauport",
    "sg:classifiers":[
        {
            "category":"Mining & Drilling",
            "type":"Manufacturing & Wholesale Goods"
        }
    ],
    "sg:phone":"+1 418 854 0908",
    "sg:postcode":"G1E 2T4",
    "sg:province":"QC",
    "sg:tags":[
        "concrete"
    ],
    "wof:name":"Unibeton",
    "wof:placetype":"venue"
},
  "geometry": {"coordinates":[-71.201965,46.855465],"type":"Point"}
}