{
  "type": "Feature",
  "properties": {
    "addr:full":"Halifax NS B3L 1A1",
    "addr:postcode":"b3l 1a1",
    "iso:country":"CA",
    "sg:city":"Halifax",
    "sg:classifiers":[
        {
            "category":"Professional",
            "subcategory":"Accounting & Tax Preparation",
            "type":"Services"
        }
    ],
    "sg:phone":"+1 902 454 2459",
    "sg:postcode":"B3L 1A1",
    "sg:province":"NS",
    "sg:tags":[
        "accountant",
        "return",
        "filing"
    ],
    "wof:name":"U & R Tax Depot",
    "wof:placetype":"venue"
},
  "geometry": {"coordinates":[-63.592606,44.64653],"type":"Point"}
}