{
  "type": "Feature",
  "properties": {
    "addr:full":"Etobicoke ON M9C 4Z5",
    "addr:postcode":"m9c 4z5",
    "iso:country":"CA",
    "sg:city":"Etobicoke",
    "sg:classifiers":[
        {
            "category":"Real Estate",
            "subcategory":"Real Estate Agent",
            "type":"Services"
        }
    ],
    "sg:phone":"+1 416 626 3971",
    "sg:postcode":"M9C 4Z5",
    "sg:province":"ON",
    "sg:tags":[
        "management"
    ],
    "wof:name":"Melia Corp",
    "wof:placetype":"venue"
},
  "geometry": {"coordinates":[-79.5632781982,43.6395187378],"type":"Point"}
}