{
  "type": "Feature",
  "properties": {
    "addr:full":"510 Hwy 1 Strathmore AB T1P 1M6",
    "addr:housenumber":"510",
    "addr:postcode":"t1p 1m6",
    "addr:street":"Hwy 1",
    "iso:country":"CA",
    "sg:address":"510 Hwy 1",
    "sg:city":"Strathmore",
    "sg:classifiers":[
        {
            "category":"Autos & Motor Vehicles",
            "subcategory":"Fuel & Gas Station",
            "type":"Retail Goods"
        }
    ],
    "sg:phone":"+1 403 934 6318",
    "sg:postcode":"T1P 1M6",
    "sg:province":"AB",
    "sg:tags":[
        "oil"
    ],
    "wof:name":"Dc's Mohawk",
    "wof:placetype":"venue"
},
  "geometry": {"coordinates":[-113.39141082800001,51.0378303528],"type":"Point"}
}