{
  "type": "Feature",
  "properties": {
    "iso:country":"CA",
    "sg:address":"15535 115A Ave NW",
    "sg:city":"Edmonton",
    "sg:classifiers":[
        {
            "category":"Shopping",
            "subcategory":"Department Store",
            "type":"Retail Goods"
        }
    ],
    "sg:phone":"+1 780 455 9001",
    "sg:postcode":"T5M 3S7",
    "sg:province":"AB",
    "sg:tags":[
        "shop",
        "liquidator"
    ],
    "wof:name":"Liquidation World Inc",
    "wof:placetype":"venue"
},
  "geometry": {"coordinates":[-113.589256287,53.5654525757],"type":"Point"}
}