{
  "type": "Feature",
  "properties": {
    "addr:full":"7210 76 Ave NW Edmonton AB T6B 0B2",
    "addr:housenumber":"7210",
    "addr:postcode":"t6b 0b2",
    "addr:street":"76 Ave Nw",
    "iso:country":"CA",
    "sg:address":"7210 76 Ave NW",
    "sg:city":"Edmonton",
    "sg:classifiers":[
        {
            "category":"Retail",
            "subcategory":"Auto Repair",
            "type":"Services"
        }
    ],
    "sg:phone":"+1 780 461 1687",
    "sg:postcode":"T6B 0B2",
    "sg:province":"AB",
    "sg:tags":[
        "automobile",
        "restoration",
        "painting"
    ],
    "wof:name":"King's Classics Ltd",
    "wof:placetype":"venue"
},
  "geometry": {"coordinates":[-113.438698,53.512527],"type":"Point"}
}