{
  "type": "Feature",
  "properties": {
    "iso:country":"CA",
    "sg:address":"35 Mountain View Rd",
    "sg:city":"Winnipeg",
    "sg:classifiers":[
        {
            "category":"Building & Trades",
            "subcategory":"Construction",
            "type":"Services"
        }
    ],
    "sg:phone":"+1 204 632 6364",
    "sg:postcode":"R3C 2E6",
    "sg:province":"MB",
    "sg:tags":[
        "excavating",
        "contractor"
    ],
    "wof:name":"W Mc Taggart Equipment Ltd",
    "wof:placetype":"venue"
},
  "geometry": {"coordinates":[-97.0424957275,49.853427887],"type":"Point"}
}