{
  "type": "Feature",
  "properties": {
    "addr:full":"420 N Medford Rd Canning NS B0P 1H0",
    "addr:housenumber":"420",
    "addr:postcode":"b0p 1h0",
    "addr:street":"N Medford Rd",
    "iso:country":"CA",
    "sg:address":"420 N Medford Rd",
    "sg:city":"Canning",
    "sg:classifiers":[
        {
            "category":"Farming",
            "subcategory":"Farm",
            "type":"Manufacturing & Wholesale Goods"
        }
    ],
    "sg:phone":"+1 902 582 7939",
    "sg:postcode":"B0P 1H0",
    "sg:province":"NS",
    "wof:name":"Melvin Farms Ltd",
    "wof:placetype":"venue"
},
  "geometry": {"coordinates":[-64.431664,45.156918],"type":"Point"}
}