{
  "type": "Feature",
  "properties": {
    "addr:full":"405 2nd Ave E Spiritwood SK S0J 2M0",
    "addr:housenumber":"405",
    "addr:postcode":"s0j 2m0",
    "addr:street":"2Nd Ave E Spiritwood",
    "iso:country":"CA",
    "sg:address":"405 2nd Ave E",
    "sg:city":"Spiritwood",
    "sg:classifiers":[
        {
            "category":"Organizations",
            "subcategory":"Religious Organization",
            "type":"Services"
        }
    ],
    "sg:phone":"+1 306 883 2216",
    "sg:postcode":"S0J 2M0",
    "sg:province":"SK",
    "sg:tags":[
        "church"
    ],
    "wof:name":"Trinity Bissell Memorial",
    "wof:placetype":"venue"
},
  "geometry": {"coordinates":[-107.521980286,53.3638954163],"type":"Point"}
}