{
  "type": "Feature",
  "properties": {
    "addr:full":"Cold Lake AB T9M 1P2",
    "addr:postcode":"t9m 1p2",
    "iso:country":"CA",
    "sg:city":"Cold Lake",
    "sg:classifiers":[
        {
            "category":"Freight",
            "type":"Transportation"
        }
    ],
    "sg:phone":"+1 780 639 2084",
    "sg:postcode":"T9M 1P2",
    "sg:province":"AB",
    "sg:tags":[
        "automobile",
        "storage"
    ],
    "wof:name":"Chevroke Developments",
    "wof:placetype":"venue"
},
  "geometry": {"coordinates":[-110.17379,54.465027],"type":"Point"}
}