{
  "type": "Feature",
  "properties": {
    "addr:full":"1875 Rue Notre-Dame # 200 L'Ancienne-Lorette QC G2E 4K1",
    "addr:housenumber":"1875",
    "addr:postcode":"g2e 4k1",
    "addr:street":"Rue Notre-Dame # 200",
    "iso:country":"CA",
    "sg:address":"1875 Rue Notre-Dame # 200",
    "sg:city":"L'Ancienne-Lorette",
    "sg:classifiers":[
        {
            "category":"Health Services",
            "subcategory":"Health Practitioner",
            "type":"Services"
        }
    ],
    "sg:phone":"+1 418 872 5312",
    "sg:postcode":"G2E 4K1",
    "sg:province":"QC",
    "sg:tags":[
        "psychologist"
    ],
    "wof:name":"Bourdon, Jocelyne",
    "wof:placetype":"venue"
},
  "geometry": {"coordinates":[-71.36863700000001,46.809658],"type":"Point"}
}