{
  "type": "Feature",
  "properties": {
    "addr:full":"Edmonton AB T6B 1E6",
    "addr:postcode":"t6b 1e6",
    "iso:country":"CA",
    "sg:city":"Edmonton",
    "sg:classifiers":[
        {
            "category":"Mining & Drilling",
            "type":"Manufacturing & Wholesale Goods"
        }
    ],
    "sg:phone":"+1 780 462 4486",
    "sg:postcode":"T6B 1E6",
    "sg:province":"AB",
    "sg:tags":[
        "environmental",
        "ecological",
        "oil",
        "field"
    ],
    "wof:name":"Pioneer Land & Envir Svc Ltd",
    "wof:placetype":"venue"
},
  "geometry": {"coordinates":[-113.41881600000001,53.517506],"type":"Point"}
}