{
  "type": "Feature",
  "properties": {
    "addr:full":"313 Main St E Kingsville ON N9Y 1A7",
    "addr:housenumber":"313",
    "addr:postcode":"n9y 1a7",
    "addr:street":"Main St E",
    "iso:country":"CA",
    "sg:address":"313 Main St E",
    "sg:city":"Kingsville",
    "sg:classifiers":[
        {
            "category":"Personal",
            "type":"Services"
        }
    ],
    "sg:phone":"+1 519 733 1100",
    "sg:postcode":"N9Y 1A7",
    "sg:province":"ON",
    "sg:tags":[
        "program",
        "physical",
        "exercise",
        "fitness"
    ],
    "wof:name":"Total Fitness",
    "wof:placetype":"venue"
},
  "geometry": {"coordinates":[-82.725815,42.038342],"type":"Point"}
}