{
  "type": "Feature",
  "properties": {
    "addr:full":"3 Rue Sainte-Anne Ville-Marie QC J9V 2B6",
    "addr:housenumber":"3",
    "addr:postcode":"j9v 2b6",
    "addr:street":"Rue Sainte-Anne",
    "iso:country":"CA",
    "sg:address":"3 Rue Sainte-Anne",
    "sg:city":"Ville-Marie",
    "sg:classifiers":[
        {
            "category":"Professional",
            "subcategory":"Business Services",
            "type":"Services"
        }
    ],
    "sg:phone":"+1 819 629 2314",
    "sg:postcode":"J9V 2B6",
    "sg:province":"QC",
    "sg:tags":[
        "arbitration"
    ],
    "wof:name":"Aide Jurdique DE L'Abitibi",
    "wof:placetype":"venue"
},
  "geometry": {"coordinates":[-79.44244399999999,47.330223],"type":"Point"}
}