{
  "type": "Feature",
  "properties": {
    "addr:full":"408 Rue Temiscouata Riviere-Du-Loup QC G5R 6B4",
    "addr:housenumber":"408",
    "addr:postcode":"g5r 6b4",
    "addr:street":"Rue Temiscouata Riviere-Du-Loup",
    "iso:country":"CA",
    "sg:address":"408 Rue Temiscouata",
    "sg:city":"Riviere-Du-Loup",
    "sg:classifiers":[
        {
            "category":"Retail",
            "subcategory":"Repair Shop",
            "type":"Services"
        }
    ],
    "sg:phone":"+1 418 862 9900",
    "sg:postcode":"G5R 6B4",
    "sg:province":"QC",
    "sg:tags":[
        "upholsterer"
    ],
    "wof:name":"Dumont Rembourrage Enr",
    "wof:placetype":"venue"
},
  "geometry": {"coordinates":[-69.501266,47.818588],"type":"Point"}
}