{
  "type": "Feature",
  "properties": {
    "iso:country":"CA",
    "sg:address":"500 Boul Du Cure-Labelle",
    "sg:city":"Blainville",
    "sg:classifiers":[
        {
            "category":"Organizations",
            "subcategory":"Professional Association",
            "type":"Services"
        }
    ],
    "sg:phone":"+1 450 971 2250",
    "sg:postcode":"J7C 2L5",
    "sg:province":"QC",
    "sg:tags":[
        "social",
        "welfare"
    ],
    "wof:name":"Petit Peuple",
    "wof:placetype":"venue"
},
  "geometry": {"coordinates":[-73.8516159058,45.6552505493],"type":"Point"}
}