{
  "type": "Feature",
  "properties": {
    "iso:country":"CA",
    "sg:address":"2740 Rock Bay Ave",
    "sg:city":"Victoria",
    "sg:classifiers":[
        {
            "category":"Manufacturing",
            "subcategory":"Toys & Sporting Goods",
            "type":"Manufacturing & Wholesale Goods"
        }
    ],
    "sg:phone":"+1 250 383 5342",
    "sg:postcode":"V8T 4R9",
    "sg:province":"BC",
    "sg:tags":[
        "tackle",
        "fishing"
    ],
    "wof:name":"Peetz Manufacturing Ltd",
    "wof:placetype":"venue"
},
  "geometry": {"coordinates":[-123.370155334,48.4379692078],"type":"Point"}
}