{
  "type": "Feature",
  "properties": {
    "addr:full":"649 Main St Lillooet BC V0K 1V0",
    "addr:housenumber":"649",
    "addr:postcode":"v0k 1v0",
    "addr:street":"Main St",
    "iso:country":"CA",
    "sg:address":"649 Main St",
    "sg:city":"Lillooet",
    "sg:classifiers":[
        {
            "category":"Banks & Credit Unions",
            "subcategory":"Bank",
            "type":"Services"
        }
    ],
    "sg:phone":"+1 250 256 4221",
    "sg:postcode":"V0K 1V0",
    "sg:province":"BC",
    "wof:name":"Cibc",
    "wof:placetype":"venue"
},
  "geometry": {"coordinates":[-121.932846,50.682789],"type":"Point"}
}