{
  "type": "Feature",
  "properties": {
    "addr:full":"Langley BC V1M 2K4",
    "addr:postcode":"v1m 2k4",
    "iso:country":"CA",
    "sg:city":"Langley",
    "sg:classifiers":[
        {
            "category":"Insurance",
            "subcategory":"Insurance Agent",
            "type":"Services"
        }
    ],
    "sg:phone":"+1 604 888 4656",
    "sg:postcode":"V1M 2K4",
    "sg:province":"BC",
    "wof:name":"Atkinson & Terry Insurance",
    "wof:placetype":"venue"
},
  "geometry": {"coordinates":[-122.657203674,49.163646698],"type":"Point"}
}