{
  "type": "Feature",
  "properties": {
    "addr:full":"Montreal QC H2T 2S6",
    "addr:postcode":"h2t 2s6",
    "iso:country":"CA",
    "sg:city":"Montreal",
    "sg:classifiers":[
        {
            "category":"Cinema",
            "subcategory":"Movie Theater",
            "type":"Entertainment"
        }
    ],
    "sg:phone":"+1 514 845 4676",
    "sg:postcode":"H2T 2S6",
    "sg:province":"QC",
    "sg:tags":[
        "motion",
        "picture",
        "film"
    ],
    "wof:name":"Anra Mediatextes",
    "wof:placetype":"venue"
},
  "geometry": {"coordinates":[-73.585876,45.520737],"type":"Point"}
}