{
  "type": "Feature",
  "properties": {
    "addr:full":"194 Main St E Milton ON L9T 1N8",
    "addr:housenumber":"194",
    "addr:postcode":"l9t 1n8",
    "addr:street":"Main St E",
    "iso:country":"CA",
    "sg:address":"194 Main St E",
    "sg:city":"Milton",
    "sg:classifiers":[
        {
            "category":"Building & Trades",
            "subcategory":"Landscaping Services",
            "type":"Services"
        }
    ],
    "sg:phone":"+1 905 878 2142",
    "sg:postcode":"L9T 1N8",
    "sg:province":"ON",
    "sg:tags":[
        "landscape",
        "contractor"
    ],
    "wof:name":"Pinebrook Landscape & Design",
    "wof:placetype":"venue"
},
  "geometry": {"coordinates":[-79.883537,43.512566],"type":"Point"}
}