{
  "type": "Feature",
  "properties": {
    "iso:country":"CA",
    "sg:address":"194 Main St E",
    "sg:city":"Milton",
    "sg:classifiers":[
        {
            "category":"Building & Trades",
            "subcategory":"Landscaping Services",
            "type":"Services"
        }
    ],
    "sg:phone":"+1 905 878 2142",
    "sg:postcode":"L9T 1N8",
    "sg:province":"ON",
    "sg:tags":[
        "landscape",
        "contractor"
    ],
    "wof:name":"Pinebrook Landscape & Design",
    "wof:placetype":"venue"
},
  "geometry": {"coordinates":[-79.883537,43.512566],"type":"Point"}
}