{
  "type": "Feature",
  "properties": {
    "addr:full":"186 Columbia Ave Castlegar BC V1N 1A9",
    "addr:housenumber":"186",
    "addr:postcode":"v1n 1a9",
    "addr:street":"Columbia Ave",
    "iso:country":"CA",
    "sg:address":"186 Columbia Ave",
    "sg:city":"Castlegar",
    "sg:classifiers":[
        {
            "category":"Professional",
            "subcategory":"Engineering",
            "type":"Services"
        }
    ],
    "sg:phone":"+1 250 365 8455",
    "sg:postcode":"V1N 1A9",
    "sg:province":"BC",
    "sg:tags":[
        "engineer"
    ],
    "wof:name":"Emco Engineering Ltd",
    "wof:placetype":"venue"
},
  "geometry": {"coordinates":[-117.666489,49.327854],"type":"Point"}
}