{
  "type": "Feature",
  "properties": {
    "iso:country":"CA",
    "sg:address":"1514 Ch Des Patriotes",
    "sg:city":"Sainte-Victoire-DE-Sorel",
    "sg:classifiers":[
        {
            "category":"Manufacturing",
            "subcategory":"Rubber & Plastics",
            "type":"Manufacturing & Wholesale Goods"
        }
    ],
    "sg:phone":"+1 450 743 7587",
    "sg:postcode":"J0G 1T0",
    "sg:province":"QC",
    "sg:tags":[
        "container"
    ],
    "wof:name":"Solidec Inc",
    "wof:placetype":"venue"
},
  "geometry": {"coordinates":[-73.1364517212,45.9895858765],"type":"Point"}
}