{
  "type": "Feature",
  "properties": {
    "addr:full":"94 Mcnair Dr Nackawic NB E6G 1A8",
    "addr:housenumber":"94",
    "addr:postcode":"e6g 1a8",
    "addr:street":"Mcnair Dr",
    "iso:country":"CA",
    "sg:address":"94 Mcnair Dr",
    "sg:city":"Nackawic",
    "sg:classifiers":[
        {
            "category":"Organizations",
            "subcategory":"Religious Organization",
            "type":"Services"
        }
    ],
    "sg:phone":"+1 506 575 2313",
    "sg:postcode":"E6G 1A8",
    "sg:province":"NB",
    "sg:tags":[
        "church"
    ],
    "wof:name":"Nackawic United Baptist Church",
    "wof:placetype":"venue"
},
  "geometry": {"coordinates":[-67.241569519,45.9954376221],"type":"Point"}
}