{
  "type": "Feature",
  "properties": {
    "addr:full":"7077 Bathurst St Thornhill ON L4J 2J6",
    "addr:housenumber":"7077",
    "addr:postcode":"l4j 2j6",
    "addr:street":"Bathurst St",
    "iso:country":"CA",
    "sg:address":"7077 Bathurst St",
    "sg:city":"Thornhill",
    "sg:classifiers":[
        {
            "category":"Personal",
            "subcategory":"Beauty Salon",
            "type":"Services"
        }
    ],
    "sg:phone":"+1 905 707 7910",
    "sg:postcode":"L4J 2J6",
    "sg:province":"ON",
    "wof:name":"Nupoliton Beauty Lounge",
    "wof:placetype":"venue"
},
  "geometry": {"coordinates":[-79.446091,43.794472],"type":"Point"}
}