{
  "type": "Feature",
  "properties": {
    "addr:full":"Desboro ON N0H 1K0",
    "addr:postcode":"n0h 1k0",
    "iso:country":"CA",
    "sg:city":"Desboro",
    "sg:classifiers":[
        {
            "category":"Wholesale",
            "subcategory":"Machinery & Supplies",
            "type":"Manufacturing & Wholesale Goods"
        }
    ],
    "sg:phone":"+1 519 794 2053",
    "sg:postcode":"N0H 1K0",
    "sg:province":"ON",
    "sg:tags":[
        "contractor"
    ],
    "wof:name":"Maluskie Farm Equipment Ltd",
    "wof:placetype":"venue"
},
  "geometry": {"coordinates":[-80.9919204712,44.4063835144],"type":"Point"}
}