{
  "type": "Feature",
  "properties": {
    "addr:full":"Chesley ON N0G 1L0",
    "addr:postcode":"n0g 1l0",
    "iso:country":"CA",
    "sg:city":"Chesley",
    "sg:classifiers":[
        {
            "category":"Building & Trades",
            "subcategory":"Landscaping Services",
            "type":"Services"
        }
    ],
    "sg:phone":"+1 519 363 0493",
    "sg:postcode":"N0G 1L0",
    "sg:province":"ON",
    "sg:tags":[
        "tree",
        "landscape",
        "contractor"
    ],
    "wof:name":"Dave's Tree Svc",
    "wof:placetype":"venue"
},
  "geometry": {"coordinates":[-81.0945510864,44.29504776],"type":"Point"}
}