{
  "type": "Feature",
  "properties": {
    "addr:full":"4402 Boul Royal Shawinigan QC G9N 8P1",
    "addr:housenumber":"4402",
    "addr:postcode":"g9n 8p1",
    "addr:street":"Boul Royal",
    "iso:country":"CA",
    "sg:address":"4402 Boul Royal",
    "sg:city":"Shawinigan",
    "sg:classifiers":[
        {
            "category":"Shopping",
            "subcategory":"Musical Instruments",
            "type":"Retail Goods"
        }
    ],
    "sg:phone":"+1 819 539 6969",
    "sg:postcode":"G9N 8P1",
    "sg:province":"QC",
    "wof:name":"Musique Gn Inc",
    "wof:placetype":"venue"
},
  "geometry": {"coordinates":[-72.730553,46.566505],"type":"Point"}
}