{
  "type": "Feature",
  "properties": {
    "addr:full":"1045 Av Du Palais Saint-Joseph-DE-Beauce QC G0S 2V0",
    "addr:housenumber":"1045",
    "addr:postcode":"g0s 2v0",
    "addr:street":"Av Du Palais",
    "iso:country":"CA",
    "sg:address":"1045 Av Du Palais",
    "sg:city":"Saint-Joseph-DE-Beauce",
    "sg:classifiers":[
        {
            "category":"Retail",
            "subcategory":"Auto Repair",
            "type":"Services"
        }
    ],
    "sg:phone":"+1 418 397 5663",
    "sg:postcode":"G0S 2V0",
    "sg:province":"QC",
    "sg:tags":[
        "repairing",
        "automobile"
    ],
    "wof:name":"Garage Chs-Henri Fortin",
    "wof:placetype":"venue"
},
  "geometry": {"coordinates":[-70.873436,46.301422],"type":"Point"}
}