{
  "type": "Feature",
  "properties": {
    "iso:country":"CA",
    "sg:address":"227 Maple St N",
    "sg:city":"Timmins",
    "sg:classifiers":[
        {
            "category":"Organizations",
            "subcategory":"Non-profit Organization",
            "type":"Services"
        }
    ],
    "sg:phone":"+1 705 268 6696",
    "sg:postcode":"P4N 6B9",
    "sg:province":"ON",
    "sg:tags":[
        "addiction",
        "treatment",
        "center"
    ],
    "wof:name":"Narcotics Annonymous",
    "wof:placetype":"venue"
},
  "geometry": {"coordinates":[-81.33354949949999,48.480632782],"type":"Point"}
}