{
  "type": "Feature",
  "properties": {
    "addr:full":"103 Colborne St Brantford ON N3T 2G4",
    "addr:housenumber":"103",
    "addr:postcode":"n3t 2g4",
    "addr:street":"Colborne St",
    "iso:country":"CA",
    "sg:address":"103 Colborne St",
    "sg:city":"Brantford",
    "sg:classifiers":[
        {
            "category":"Shopping",
            "subcategory":"Used Merchandise",
            "type":"Retail Goods"
        }
    ],
    "sg:phone":"+1 519 752 5830",
    "sg:postcode":"N3T 2G4",
    "sg:province":"ON",
    "sg:tags":[
        "second",
        "store",
        "hand"
    ],
    "wof:name":"Shelter Shop",
    "wof:placetype":"venue"
},
  "geometry": {"coordinates":[-80.2660446167,43.1382064819],"type":"Point"}
}