{
  "type": "Feature",
  "properties": {
    "addr:full":"318 Pleasant St Miramichi NB E1V 1Y9",
    "addr:housenumber":"318",
    "addr:postcode":"e1v 1y9",
    "addr:street":"Pleasant St",
    "iso:country":"CA",
    "sg:address":"318 Pleasant St",
    "sg:city":"Miramichi",
    "sg:classifiers":[
        {
            "category":"Insurance",
            "subcategory":"Insurance Agent",
            "type":"Services"
        }
    ],
    "sg:phone":"+1 506 622 3490",
    "sg:postcode":"E1V 1Y9",
    "sg:province":"NB",
    "wof:name":"Burchill, Kathy",
    "wof:placetype":"venue"
},
  "geometry": {"coordinates":[-65.5655593872,47.0020675659],"type":"Point"}
}