{
  "type": "Feature",
  "properties": {
    "addr:full":"9196 160 St Surrey BC V4N 3A5",
    "addr:housenumber":"9196",
    "addr:postcode":"v4n 3a5",
    "addr:street":"160 St",
    "iso:country":"CA",
    "sg:address":"9196 160 St",
    "sg:city":"Surrey",
    "sg:classifiers":[
        {
            "category":"Food & Beverages",
            "subcategory":"Fruits & Vegetables",
            "type":"Retail Goods"
        }
    ],
    "sg:phone":"+1 604 588 0568",
    "sg:postcode":"V4N 3A5",
    "sg:province":"BC",
    "sg:tags":[
        "produce"
    ],
    "wof:name":"Fruitcana",
    "wof:placetype":"venue"
},
  "geometry": {"coordinates":[-122.778694153,49.1698303223],"type":"Point"}
}