{
  "type": "Feature",
  "properties": {
    "addr:full":"209 Victoria Ave Regina SK S4N 0P4",
    "addr:housenumber":"209",
    "addr:postcode":"s4n 0p4",
    "addr:street":"Victoria Ave",
    "iso:country":"CA",
    "sg:address":"209 Victoria Ave",
    "sg:city":"Regina",
    "sg:classifiers":[
        {
            "category":"Retail",
            "subcategory":"Laundry & Dry Cleaning",
            "type":"Services"
        }
    ],
    "sg:phone":"+1 306 569 2003",
    "sg:postcode":"S4N 0P4",
    "sg:province":"SK",
    "sg:tags":[
        "cleaners"
    ],
    "wof:name":"Klein's Food Mart",
    "wof:placetype":"venue"
},
  "geometry": {"coordinates":[-104.584,50.446999],"type":"Point"}
}