{
  "type": "Feature",
  "properties": {
    "addr:full":"Gracefield QC J0X 1W0",
    "addr:postcode":"j0x 1w0",
    "iso:country":"CA",
    "sg:city":"Gracefield",
    "sg:classifiers":[
        {
            "category":"Autos & Motor Vehicles",
            "subcategory":"Boat Sales",
            "type":"Retail Goods"
        }
    ],
    "sg:phone":"+1 819 463 3580",
    "sg:postcode":"J0X 1W0",
    "sg:province":"QC",
    "sg:tags":[
        "dealer"
    ],
    "wof:name":"Hors-Bords Lafontaine Enr",
    "wof:placetype":"venue"
},
  "geometry": {"coordinates":[-76.05707550050001,46.0342140198],"type":"Point"}
}