{
  "type": "Feature",
  "properties": {
    "iso:country":"CA",
    "sg:address":"655 10th St",
    "sg:city":"Brandon",
    "sg:classifiers":[
        {
            "category":"Shopping",
            "type":"Retail Goods"
        }
    ],
    "sg:phone":"+1 204 725 1141",
    "sg:postcode":"R7A 4G6",
    "sg:province":"MB",
    "sg:tags":[
        "picture",
        "art",
        "gallery",
        "dealer"
    ],
    "wof:name":"Prairie Showcase",
    "wof:placetype":"venue"
},
  "geometry": {"coordinates":[-99.9512252808,49.8397903442],"type":"Point"}
}