{
  "type": "Feature",
  "properties": {
    "addr:full":"95 Commander Blvd Scarborough ON M1S 3M7",
    "addr:housenumber":"95",
    "addr:postcode":"m1s 3m7",
    "addr:street":"Commander Blvd",
    "iso:country":"CA",
    "sg:address":"95 Commander Blvd",
    "sg:city":"Scarborough",
    "sg:classifiers":[
        {
            "category":"Professional",
            "subcategory":"Detective & Security Services",
            "type":"Services"
        }
    ],
    "sg:phone":"+1 416 297 7494",
    "sg:postcode":"M1S 3M7",
    "sg:province":"ON",
    "sg:tags":[
        "investigator"
    ],
    "wof:name":"Trillium Investigations",
    "wof:placetype":"venue"
},
  "geometry": {"coordinates":[-79.2656326294,43.7937583923],"type":"Point"}
}