{
  "type": "Feature",
  "properties": {
    "addr:full":"Saint-Malachie QC G0R 3N0",
    "addr:postcode":"g0r 3n0",
    "iso:country":"CA",
    "sg:city":"Saint-Malachie",
    "sg:classifiers":[
        {
            "category":"Manufacturing",
            "subcategory":"Rubber & Plastics",
            "type":"Manufacturing & Wholesale Goods"
        }
    ],
    "sg:phone":"+1 418 642 5707",
    "sg:postcode":"G0R 3N0",
    "sg:province":"QC",
    "wof:name":"Plastiques Abenakis Inc",
    "wof:placetype":"venue"
},
  "geometry": {"coordinates":[-70.81512451170001,46.5527648926],"type":"Point"}
}