{
  "type": "Feature",
  "properties": {
    "addr:full":"Montreal QC H2J 2W8",
    "addr:postcode":"h2j 2w8",
    "iso:country":"CA",
    "sg:city":"Montreal",
    "sg:classifiers":[
        {
            "category":"Social Services",
            "type":"Services"
        }
    ],
    "sg:phone":"+1 514 521 9191",
    "sg:postcode":"H2J 2W8",
    "sg:province":"QC",
    "sg:tags":[
        "organization",
        "welfare"
    ],
    "wof:name":"Centre DE Svc Communautaire",
    "wof:placetype":"venue"
},
  "geometry": {"coordinates":[-73.580635,45.525249],"type":"Point"}
}