{
  "type": "Feature",
  "properties": {
    "addr:full":"1123 Rue Sainte-Marguerite Trois-Rivieres QC G8Z 1Y2",
    "addr:housenumber":"1123",
    "addr:postcode":"g8z 1y2",
    "addr:street":"Rue Sainte-Marguerite Trois-Rivieres",
    "iso:country":"CA",
    "sg:address":"1123 Rue Sainte-Marguerite",
    "sg:city":"Trois-Rivieres",
    "sg:classifiers":[
        {
            "category":"Shopping",
            "subcategory":"Pharmacy",
            "type":"Retail Goods"
        }
    ],
    "sg:phone":"+1 819 375 7353",
    "sg:postcode":"G8Z 1Y2",
    "sg:province":"QC",
    "wof:name":"Brunet Pharmacie Affiliee",
    "wof:placetype":"venue"
},
  "geometry": {"coordinates":[-72.554543,46.342937],"type":"Point"}
}