{
  "type": "Feature",
  "properties": {
    "addr:full":"24 Main St Picton ON K0K 2T0",
    "addr:housenumber":"24",
    "addr:postcode":"k0k 2t0",
    "addr:street":"Main St",
    "iso:country":"CA",
    "sg:address":"24 Main St",
    "sg:city":"Picton",
    "sg:classifiers":[
        {
            "category":"Real Estate",
            "subcategory":"Real Estate Agent",
            "type":"Services"
        }
    ],
    "sg:phone":"+1 613 476 0096",
    "sg:postcode":"K0K 2T0",
    "sg:province":"ON",
    "wof:name":"Crombie, Elizabeth",
    "wof:placetype":"venue"
},
  "geometry": {"coordinates":[-77.15315200000001,44.00267],"type":"Point"}
}