{
  "type": "Feature",
  "properties": {
    "iso:country":"CA",
    "sg:address":"154 Bruce St",
    "sg:city":"Oshawa",
    "sg:classifiers":[
        {
            "category":"Retail",
            "subcategory":"Repair Shop",
            "type":"Services"
        }
    ],
    "sg:phone":"+1 905 576 7448",
    "sg:postcode":"L1H 1R2",
    "sg:province":"ON",
    "sg:tags":[
        "appliance"
    ],
    "wof:name":"Stephenson's Appliances",
    "wof:placetype":"venue"
},
  "geometry": {"coordinates":[-78.8573,43.896709],"type":"Point"}
}