{
  "type": "Feature",
  "properties": {
    "iso:country":"CA",
    "sg:address":"1300 Boul Du MI-Vallon",
    "sg:city":"Rock Forest",
    "sg:classifiers":[
        {
            "category":"Bars & Pubs",
            "type":"Food & Drink"
        }
    ],
    "sg:phone":"+1 819 821 9460",
    "sg:postcode":"J1N 3B9",
    "sg:province":"QC",
    "sg:tags":[
        "lounge",
        "cocktail"
    ],
    "wof:name":"Bar MI Vallon",
    "wof:placetype":"venue"
},
  "geometry": {"coordinates":[-71.977722168,45.3754959106],"type":"Point"}
}