{
  "type": "Feature",
  "properties": {
    "iso:country":"CA",
    "sg:city":"Mississauga",
    "sg:classifiers":[
        {
            "category":"Retail",
            "subcategory":"Auto Repair",
            "type":"Services"
        }
    ],
    "sg:phone":"+1 905 858 0900",
    "sg:postcode":"L5M 2P3",
    "sg:province":"ON",
    "sg:tags":[
        "body",
        "automobile",
        "painting"
    ],
    "wof:name":"Impact Auto Collision",
    "wof:placetype":"venue"
},
  "geometry": {"coordinates":[-79.715134,43.577518],"type":"Point"}
}