{
  "type": "Feature",
  "properties": {
    "addr:full":"196960 Conc 5A Chatsworth ON N0H 1G0",
    "addr:housenumber":"196960;5a",
    "addr:postcode":"n0h 1g0",
    "addr:street":"Conc",
    "iso:country":"CA",
    "sg:address":"196960 Conc 5A",
    "sg:city":"Chatsworth",
    "sg:classifiers":[
        {
            "category":"Building & Trades",
            "subcategory":"Construction",
            "type":"Services"
        }
    ],
    "sg:phone":"+1 519 794 2427",
    "sg:postcode":"N0H 1G0",
    "sg:province":"ON",
    "sg:tags":[
        "roofing",
        "contractor"
    ],
    "wof:name":"Edward Mc Nabb Roofing",
    "wof:placetype":"venue"
},
  "geometry": {"coordinates":[-80.95414,44.44944],"type":"Point"}
}