{
  "type": "Feature",
  "properties": {
    "addr:full":"Havre-Saint-Pierre QC G0G 1P0",
    "addr:postcode":"g0g 1p0",
    "iso:country":"CA",
    "sg:city":"Havre-Saint-Pierre",
    "sg:classifiers":[
        {
            "category":"Taxi",
            "type":"Transportation"
        }
    ],
    "sg:phone":"+1 418 538 2077",
    "sg:postcode":"G0G 1P0",
    "sg:province":"QC",
    "sg:tags":[
        "taxicab"
    ],
    "wof:name":"Taxi Du Havre Inc",
    "wof:placetype":"venue"
},
  "geometry": {"coordinates":[-63.6045303345,50.2447509766],"type":"Point"}
}