{
  "type": "Feature",
  "properties": {
    "addr:full":"St Catharines ON L2S 3V7",
    "addr:postcode":"l2s 3v7",
    "iso:country":"CA",
    "sg:city":"St Catharines",
    "sg:classifiers":[
        {
            "category":"Restaurant",
            "type":"Food & Drink"
        }
    ],
    "sg:phone":"+1 905 708 1178",
    "sg:postcode":"L2S 3V7",
    "sg:province":"ON",
    "wof:name":"Nan King Chinese Cuisine",
    "wof:placetype":"venue"
},
  "geometry": {"coordinates":[-79.273338,43.172131],"type":"Point"}
}