{
  "type": "Feature",
  "properties": {
    "addr:full":"Elmira ON N3B 2Z5",
    "addr:postcode":"n3b 2z5",
    "iso:country":"CA",
    "sg:city":"Elmira",
    "sg:classifiers":[
        {
            "category":"Freight",
            "type":"Transportation"
        }
    ],
    "sg:phone":"+1 519 669 4964",
    "sg:postcode":"N3B 2Z5",
    "sg:province":"ON",
    "sg:tags":[
        "commercial",
        "storage"
    ],
    "wof:name":"Elmira Self Storage",
    "wof:placetype":"venue"
},
  "geometry": {"coordinates":[-80.558716,43.598652],"type":"Point"}
}