{
  "type": "Feature",
  "properties": {
    "iso:country":"CA",
    "sg:address":"805 Squire Green Dr",
    "sg:city":"Bathurst",
    "sg:classifiers":[
        {
            "category":"Building & Trades",
            "subcategory":"Construction",
            "type":"Services"
        }
    ],
    "sg:phone":"+1 506 546 2233",
    "sg:postcode":"E2A 4W8",
    "sg:province":"NB",
    "sg:tags":[
        "downspouts",
        "roofing",
        "gutter",
        "contractor"
    ],
    "wof:name":"Gouttieres Bruma Gutters",
    "wof:placetype":"venue"
},
  "geometry": {"coordinates":[-65.67487335209999,47.6078224182],"type":"Point"}
}