{
  "type": "Feature",
  "properties": {
    "addr:full":"81 Stewart St Ottawa ON K1N 6H9",
    "addr:housenumber":"81",
    "addr:postcode":"k1n 6h9",
    "addr:street":"Stewart St",
    "iso:country":"CA",
    "sg:address":"81 Stewart St",
    "sg:city":"Ottawa",
    "sg:classifiers":[
        {
            "category":"Health Services",
            "subcategory":"Doctor",
            "type":"Services"
        }
    ],
    "sg:phone":"+1 613 233 9497",
    "sg:postcode":"K1N 6H9",
    "sg:province":"ON",
    "sg:tags":[
        "physician",
        "surgeon"
    ],
    "wof:name":"Pentland, N MD",
    "wof:placetype":"venue"
},
  "geometry": {"coordinates":[-75.68506622309999,45.426700592],"type":"Point"}
}