{
  "type": "Feature",
  "properties": {
    "addr:full":"27 Ruth Ave Brampton ON L6Z 4R2",
    "addr:housenumber":"27",
    "addr:postcode":"l6z 4r2",
    "addr:street":"Ruth Ave",
    "iso:country":"CA",
    "sg:address":"27 Ruth Ave",
    "sg:city":"Brampton",
    "sg:classifiers":[
        {
            "category":"Restaurant",
            "type":"Food & Drink"
        }
    ],
    "sg:phone":"+1 905 846 2188",
    "sg:postcode":"L6Z 4R2",
    "sg:province":"ON",
    "wof:name":"Kfc",
    "wof:placetype":"venue"
},
  "geometry": {"coordinates":[-79.787018,43.722282],"type":"Point"}
}