{
  "type": "Feature",
  "properties": {
    "addr:full":"7839 Rue Foucher Montreal QC H2R 2K8",
    "addr:housenumber":"7839",
    "addr:postcode":"h2r 2k8",
    "addr:street":"Rue Foucher",
    "iso:country":"CA",
    "sg:address":"7839 Rue Foucher",
    "sg:city":"Montreal",
    "sg:classifiers":[
        {
            "category":"Health Services",
            "subcategory":"Health Practitioner",
            "type":"Services"
        }
    ],
    "sg:phone":"+1 514 270 1325",
    "sg:postcode":"H2R 2K8",
    "sg:province":"QC",
    "sg:tags":[
        "psychologist"
    ],
    "wof:name":"Julien, Denis",
    "wof:placetype":"venue"
},
  "geometry": {"coordinates":[-73.6237869263,45.5439414978],"type":"Point"}
}