{
  "type": "Feature",
  "properties": {
    "iso:country":"CA",
    "sg:city":"Woodbridge",
    "sg:classifiers":[
        {
            "category":"Building & Trades",
            "subcategory":"Construction",
            "type":"Services"
        }
    ],
    "sg:phone":"+1 905 850 5590",
    "sg:postcode":"L4L 8M6",
    "sg:province":"ON",
    "sg:tags":[
        "railing"
    ],
    "wof:name":"Cpl Aluminum Rail",
    "wof:placetype":"venue"
},
  "geometry": {"coordinates":[-79.612419,43.772453],"type":"Point"}
}