{
  "type": "Feature",
  "properties": {
    "iso:country":"CA",
    "sg:address":"1 Post St",
    "sg:city":"Whitney",
    "sg:classifiers":[
        {
            "category":"Education",
            "subcategory":"School",
            "type":"Public Place"
        }
    ],
    "sg:phone":"+1 613 637 2720",
    "sg:postcode":"K0J 2M0",
    "sg:province":"ON",
    "wof:name":"St Martin's School",
    "wof:placetype":"venue"
},
  "geometry": {"coordinates":[-78.24499511720001,45.4991912842],"type":"Point"}
}