{
  "type": "Feature",
  "properties": {
    "addr:full":"300 Rue Leo-Pariseau Montreal QC H2X 4B3",
    "addr:housenumber":"300",
    "addr:postcode":"h2x 4b3",
    "addr:street":"Rue Leo-Pariseau",
    "iso:country":"CA",
    "sg:address":"300 Rue Leo-Pariseau",
    "sg:city":"Montreal",
    "sg:classifiers":[
        {
            "category":"Professional",
            "subcategory":"Lawyer & Legal Services",
            "type":"Services"
        }
    ],
    "sg:phone":"+1 514 288 8383",
    "sg:postcode":"H2X 4B3",
    "sg:province":"QC",
    "sg:tags":[
        "attorney"
    ],
    "wof:name":"Grana, Vincent",
    "wof:placetype":"venue"
},
  "geometry": {"coordinates":[-73.57666778559999,45.5114440918],"type":"Point"}
}