{
  "type": "Feature",
  "properties": {
    "addr:full":"525 Stephens Ave Portage LA Prairie MB R1N 3J9",
    "addr:housenumber":"525",
    "addr:postcode":"r1n 3j9",
    "addr:street":"Stephens Ave",
    "iso:country":"CA",
    "sg:address":"525 Stephens Ave",
    "sg:city":"Portage LA Prairie",
    "sg:classifiers":[
        {
            "category":"Building & Trades",
            "subcategory":"Construction",
            "type":"Services"
        }
    ],
    "sg:phone":"+1 204 239 6267",
    "sg:postcode":"R1N 3J9",
    "sg:province":"MB",
    "sg:tags":[
        "excavating",
        "contractor"
    ],
    "wof:name":"Meseyton Construction",
    "wof:placetype":"venue"
},
  "geometry": {"coordinates":[-98.26117706300001,49.9794425964],"type":"Point"}
}