{
  "type": "Feature",
  "properties": {
    "addr:full":"Milton ON L9T 2V4",
    "addr:postcode":"l9t 2v4",
    "iso:country":"CA",
    "sg:city":"Milton",
    "sg:classifiers":[
        {
            "category":"Building & Trades",
            "subcategory":"Construction",
            "type":"Services"
        }
    ],
    "sg:phone":"+1 905 878 7173",
    "sg:postcode":"L9T 2V4",
    "sg:province":"ON",
    "sg:tags":[
        "general",
        "contractor"
    ],
    "wof:name":"Hobden Construction CO Ltd",
    "wof:placetype":"venue"
},
  "geometry": {"coordinates":[-79.9039840698,43.5128364563],"type":"Point"}
}