{
  "type": "Feature",
  "properties": {
    "addr:full":"335 Melvin Ave Hamilton ON L8H 2K6",
    "addr:housenumber":"335",
    "addr:postcode":"l8h 2k6",
    "addr:street":"Melvin Ave",
    "iso:country":"CA",
    "sg:address":"335 Melvin Ave",
    "sg:city":"Hamilton",
    "sg:classifiers":[
        {
            "category":"Real Estate",
            "subcategory":"Real Estate Operator",
            "type":"Services"
        }
    ],
    "sg:phone":"+1 905 544 2509",
    "sg:postcode":"L8H 2K6",
    "sg:province":"ON",
    "sg:tags":[
        "apartment"
    ],
    "wof:name":"Barton Court",
    "wof:placetype":"venue"
},
  "geometry": {"coordinates":[-79.782372,43.241932],"type":"Point"}
}