{
  "type": "Feature",
  "properties": {
    "addr:full":"260 Sugarloaf St Port Colborne ON L3K 2N7",
    "addr:housenumber":"260",
    "addr:postcode":"l3k 2n7",
    "addr:street":"Sugarloaf St",
    "iso:country":"CA",
    "sg:address":"260 Sugarloaf St",
    "sg:city":"Port Colborne",
    "sg:classifiers":[
        {
            "category":"Organizations",
            "subcategory":"Non-profit Organization",
            "type":"Services"
        }
    ],
    "sg:phone":"+1 905 834 4501",
    "sg:postcode":"L3K 2N7",
    "sg:province":"ON",
    "sg:tags":[
        "addiction",
        "treatment",
        "center"
    ],
    "wof:name":"New Port Ctr",
    "wof:placetype":"venue"
},
  "geometry": {"coordinates":[-79.259201,42.880493],"type":"Point"}
}