{
  "type": "Feature",
  "properties": {
    "addr:full":"5728 104 St NW Edmonton AB T6H 2K2",
    "addr:housenumber":"5728",
    "addr:postcode":"t6h 2k2",
    "addr:street":"104 St Nw",
    "iso:country":"CA",
    "sg:address":"5728 104 St NW",
    "sg:city":"Edmonton",
    "sg:classifiers":[
        {
            "category":"Shopping",
            "subcategory":"Computers & Home Electronics",
            "type":"Retail Goods"
        }
    ],
    "sg:phone":"+1 780 431 1919",
    "sg:postcode":"T6H 2K2",
    "sg:province":"AB",
    "sg:tags":[
        "equipment",
        "dealer"
    ],
    "wof:name":"Computer Trends",
    "wof:placetype":"venue"
},
  "geometry": {"coordinates":[-113.497795,53.494457],"type":"Point"}
}