{
  "type": "Feature",
  "properties": {
    "addr:full":"338 Falstaff Ave North York ON M6L 3E7",
    "addr:housenumber":"338",
    "addr:postcode":"m6l 3e7",
    "addr:street":"Falstaff Ave",
    "iso:country":"CA",
    "sg:address":"338 Falstaff Ave",
    "sg:city":"North York",
    "sg:classifiers":[
        {
            "category":"Social Services",
            "type":"Services"
        }
    ],
    "sg:phone":"+1 416 244 6844",
    "sg:postcode":"M6L 3E7",
    "sg:province":"ON",
    "sg:tags":[
        "housing",
        "assistance"
    ],
    "wof:name":"Casa Abruzzo Benevolent",
    "wof:placetype":"venue"
},
  "geometry": {"coordinates":[-79.481583,43.72044],"type":"Point"}
}