{
  "type": "Feature",
  "properties": {
    "iso:country":"CA",
    "sg:city":"Belleville",
    "sg:classifiers":[
        {
            "category":"Personal",
            "type":"Services"
        }
    ],
    "sg:phone":"+1 613 966 3556",
    "sg:postcode":"K8P 3H8",
    "sg:province":"ON",
    "sg:tags":[
        "credit",
        "debt",
        "counseling"
    ],
    "wof:name":"Credit Counselling Svc",
    "wof:placetype":"venue"
},
  "geometry": {"coordinates":[-77.3867111206,44.1648406982],"type":"Point"}
}