{
  "type": "Feature",
  "properties": {
    "addr:full":"Laval QC H7K 3V6",
    "addr:postcode":"qc h7k 3v6",
    "iso:country":"CA",
    "sg:city":"Laval",
    "sg:classifiers":[
        {
            "category":"Professional",
            "subcategory":"Art Services",
            "type":"Services"
        }
    ],
    "sg:phone":"+1 450 668 5829",
    "sg:postcode":"H7K 3V6",
    "sg:province":"QC",
    "sg:tags":[
        "graphic",
        "designer"
    ],
    "wof:name":"Design Boutique Daniel Brien",
    "wof:placetype":"venue"
},
  "geometry": {"coordinates":[-73.726738,45.622746],"type":"Point"}
}