{
  "type": "Feature",
  "properties": {
    "iso:country":"CA",
    "sg:address":"1511 3 Ave S",
    "sg:city":"Lethbridge",
    "sg:classifiers":[
        {
            "category":"Health Services",
            "subcategory":"Doctor",
            "type":"Services"
        }
    ],
    "sg:phone":"+1 403 320 6644",
    "sg:postcode":"T1J 0K9",
    "sg:province":"AB",
    "sg:tags":[
        "dentist"
    ],
    "wof:name":"Apple Dental Ctr",
    "wof:placetype":"venue"
},
  "geometry": {"coordinates":[-112.820602417,49.6967086792],"type":"Point"}
}