{
  "type": "Feature",
  "properties": {
    "addr:full":"6850 Thorold Stone Rd Niagara Falls ON L2J 1B4",
    "addr:housenumber":"6850",
    "addr:postcode":"l2j 1b4",
    "addr:street":"Thorold Stone Rd",
    "iso:country":"CA",
    "sg:address":"6850 Thorold Stone Rd",
    "sg:city":"Niagara Falls",
    "sg:classifiers":[
        {
            "category":"Food & Beverages",
            "subcategory":"Groceries & Convenience Stores",
            "type":"Retail Goods"
        }
    ],
    "sg:phone":"+1 905 371 1511",
    "sg:postcode":"L2J 1B4",
    "sg:province":"ON",
    "wof:name":"Lee Mart",
    "wof:placetype":"venue"
},
  "geometry": {"coordinates":[-79.11084747309999,43.1149139404],"type":"Point"}
}