{
  "type": "Feature",
  "properties": {
    "addr:full":"11 Elgin St Grimsby ON L3M 1C5",
    "addr:housenumber":"11",
    "addr:postcode":"l3m 1c5",
    "addr:street":"Elgin St",
    "iso:country":"CA",
    "sg:address":"11 Elgin St",
    "sg:city":"Grimsby",
    "sg:classifiers":[
        {
            "category":"Professional",
            "subcategory":"Business Services",
            "type":"Services"
        }
    ],
    "sg:phone":"+1 905 945 1138",
    "sg:postcode":"L3M 1C5",
    "sg:province":"ON",
    "wof:name":"Grimsby Paralegal Svc",
    "wof:placetype":"venue"
},
  "geometry": {"coordinates":[-79.595192,43.19677],"type":"Point"}
}