{
  "type": "Feature",
  "properties": {
    "iso:country":"CA",
    "sg:address":"490 Rte 325",
    "sg:city":"Block House",
    "sg:classifiers":[
        {
            "category":"Shopping",
            "subcategory":"Hobbies, Toys, & Games",
            "type":"Retail Goods"
        }
    ],
    "sg:phone":"+1 902 624 9519",
    "sg:postcode":"B0J 1E0",
    "sg:province":"NS",
    "sg:tags":[
        "model",
        "supply"
    ],
    "wof:name":"R/C Wings & Wheels Hobbies",
    "wof:placetype":"venue"
},
  "geometry": {"coordinates":[-64.4131774902,44.4476394653],"type":"Point"}
}