{
  "type": "Feature",
  "properties": {
    "addr:full":"1437 Rue Stanley Montreal QC H3A 1P4",
    "addr:housenumber":"1437",
    "addr:postcode":"h3a 1p4",
    "addr:street":"Rue Stanley",
    "iso:country":"CA",
    "sg:address":"1437 Rue Stanley",
    "sg:city":"Montreal",
    "sg:classifiers":[
        {
            "category":"Professional",
            "subcategory":"Business Services",
            "type":"Services"
        }
    ],
    "sg:phone":"+1 514 845 5220",
    "sg:postcode":"H3A 1P4",
    "sg:province":"QC",
    "sg:tags":[
        "computer",
        "telemarketing"
    ],
    "wof:name":"Proxymedia",
    "wof:placetype":"venue"
},
  "geometry": {"coordinates":[-73.57416499999999,45.499741],"type":"Point"}
}