{
  "type": "Feature",
  "properties": {
    "iso:country":"CA",
    "sg:address":"1420 Sheppard Ave W",
    "sg:city":"North York",
    "sg:classifiers":[
        {
            "category":"Restaurant",
            "type":"Food & Drink"
        }
    ],
    "sg:phone":"+1 416 633 9701",
    "sg:postcode":"M3M 2W9",
    "sg:province":"ON",
    "sg:tags":[
        "parlor",
        "ice",
        "cream"
    ],
    "wof:name":"Dairy Queen",
    "wof:placetype":"venue"
},
  "geometry": {"coordinates":[-79.48947099999999,43.744328],"type":"Point"}
}