{
  "type": "Feature",
  "properties": {
    "iso:country":"CA",
    "sg:address":"401 Manson",
    "sg:city":"Fort St James",
    "sg:classifiers":[
        {
            "category":"Personal",
            "subcategory":"Beauty Salon",
            "type":"Services"
        }
    ],
    "sg:phone":"+1 250 996 6950",
    "sg:postcode":"V0J 1P0",
    "sg:province":"BC",
    "wof:name":"Karen's Beauty Spot",
    "wof:placetype":"venue"
},
  "geometry": {"coordinates":[-124.25680542000001,54.4445304871],"type":"Point"}
}