{
  "type": "Feature",
  "properties": {
    "addr:full":"2960 Danforth Ave East York ON M4C 1M6",
    "addr:housenumber":"2960",
    "addr:postcode":"m4c 1m6",
    "addr:street":"Danforth Ave",
    "iso:country":"CA",
    "sg:address":"2960 Danforth Ave",
    "sg:city":"East York",
    "sg:classifiers":[
        {
            "category":"Travel",
            "subcategory":"Travel Agent",
            "type":"Entertainment"
        }
    ],
    "sg:phone":"+1 416 698 6846",
    "sg:postcode":"M4C 1M6",
    "sg:province":"ON",
    "sg:tags":[
        "agency",
        "bureau"
    ],
    "wof:name":"Del Mare Travel Svc Ltd",
    "wof:placetype":"venue"
},
  "geometry": {"coordinates":[-79.292297,43.690441],"type":"Point"}
}