{
  "type": "Feature",
  "properties": {
    "addr:full":"280 Sheppard Ave E # 213 North York ON M2N 3B1",
    "addr:housenumber":"280",
    "addr:postcode":"m2n 3b1",
    "addr:street":"Sheppard Ave E # 213",
    "iso:country":"CA",
    "sg:address":"280 Sheppard Ave E # 213",
    "sg:city":"North York",
    "sg:classifiers":[
        {
            "category":"Health Services",
            "subcategory":"Doctor",
            "type":"Services"
        }
    ],
    "sg:phone":"+1 416 222 7979",
    "sg:postcode":"M2N 3B1",
    "sg:province":"ON",
    "sg:tags":[
        "dentist"
    ],
    "wof:name":"Dencs, Katalin DDS",
    "wof:placetype":"venue"
},
  "geometry": {"coordinates":[-79.3983078003,43.7644462585],"type":"Point"}
}