{
  "type": "Feature",
  "properties": {
    "addr:full":"Surrey BC V3R 4J7",
    "addr:postcode":"v3r 4j7",
    "iso:country":"CA",
    "sg:city":"Surrey",
    "sg:classifiers":[
        {
            "category":"Insurance",
            "subcategory":"Insurance Agent",
            "type":"Services"
        }
    ],
    "sg:phone":"+1 604 581 2134",
    "sg:postcode":"V3R 4J7",
    "sg:province":"BC",
    "wof:name":"Global Pacific Financial Svc",
    "wof:placetype":"venue"
},
  "geometry": {"coordinates":[-122.795547485,49.1891288757],"type":"Point"}
}