{
  "type": "Feature",
  "properties": {
    "addr:full":"56 Esplanade St Truro NS B2N 2K3",
    "addr:housenumber":"56",
    "addr:postcode":"b2n 2k3",
    "addr:street":"Esplanade St",
    "iso:country":"CA",
    "sg:address":"56 Esplanade St",
    "sg:city":"Truro",
    "sg:classifiers":[
        {
            "category":"Shopping",
            "type":"Retail Goods"
        }
    ],
    "sg:phone":"+1 902 895 8436",
    "sg:postcode":"B2N 2K3",
    "sg:province":"NS",
    "sg:tags":[
        "picture",
        "photographic",
        "supply"
    ],
    "wof:name":"Carsand-Mosher Photographic",
    "wof:placetype":"venue"
},
  "geometry": {"coordinates":[-63.276653,45.362637],"type":"Point"}
}