{
  "type": "Feature",
  "properties": {
    "addr:full":"87 Bronte Rd Oakville ON L6L 3B7",
    "addr:housenumber":"87",
    "addr:postcode":"l6l 3b7",
    "addr:street":"Bronte Rd",
    "iso:country":"CA",
    "sg:address":"87 Bronte Rd",
    "sg:city":"Oakville",
    "sg:classifiers":[
        {
            "category":"Shopping",
            "subcategory":"Jewelry",
            "type":"Retail Goods"
        }
    ],
    "sg:phone":"+1 905 469 0687",
    "sg:postcode":"L6L 3B7",
    "sg:province":"ON",
    "sg:tags":[
        "watch"
    ],
    "wof:name":"European Time",
    "wof:placetype":"venue"
},
  "geometry": {"coordinates":[-79.711479,43.394184],"type":"Point"}
}