{
  "type": "Feature",
  "properties": {
    "iso:country":"CA",
    "sg:address":"468 Queen St E",
    "sg:city":"Toronto",
    "sg:classifiers":[
        {
            "category":"Education",
            "subcategory":"Special Training",
            "type":"Public Place"
        }
    ],
    "sg:phone":"+1 416 368 1968",
    "sg:postcode":"M5A 1T7",
    "sg:province":"ON",
    "sg:tags":[
        "management"
    ],
    "wof:name":"Twi Inc",
    "wof:placetype":"venue"
},
  "geometry": {"coordinates":[-79.360405,43.656559],"type":"Point"}
}