{
  "type": "Feature",
  "properties": {
    "addr:full":"Etobicoke ON M8X 1X8",
    "addr:postcode":"m8x 1x8",
    "iso:country":"CA",
    "sg:city":"Etobicoke",
    "sg:classifiers":[
        {
            "category":"Taxi",
            "type":"Transportation"
        }
    ],
    "sg:phone":"+1 416 232 2222",
    "sg:postcode":"M8X 1X8",
    "sg:province":"ON",
    "sg:tags":[
        "taxicab"
    ],
    "wof:name":"Kingsboro Taxi Ltd",
    "wof:placetype":"venue"
},
  "geometry": {"coordinates":[-79.50992599999999,43.660984],"type":"Point"}
}