{
  "type": "Feature",
  "properties": {
    "addr:full":"209 4th St W North Vancouver BC V7M 1H8",
    "addr:housenumber":"209",
    "addr:postcode":"v7m 1h8",
    "addr:street":"4Th St W",
    "iso:country":"CA",
    "sg:address":"209 4th St W",
    "sg:city":"North Vancouver",
    "sg:classifiers":[
        {
            "category":"Museum",
            "type":"Entertainment"
        }
    ],
    "sg:phone":"+1 604 987 5618",
    "sg:postcode":"V7M 1H8",
    "sg:province":"BC",
    "sg:tags":[
        "government"
    ],
    "wof:name":"North Vancouver Museum & Archv",
    "wof:placetype":"venue"
},
  "geometry": {"coordinates":[-123.079987,49.315716],"type":"Point"}
}