{
  "type": "Feature",
  "properties": {
    "addr:full":"4066 Sheppard Ave E Scarborough ON M1S 1S9",
    "addr:housenumber":"4066",
    "addr:postcode":"m1s 1s9",
    "addr:street":"Sheppard Ave E",
    "iso:country":"CA",
    "sg:address":"4066 Sheppard Ave E",
    "sg:city":"Scarborough",
    "sg:classifiers":[
        {
            "category":"Autos & Motor Vehicles",
            "subcategory":"Automobile Sales",
            "type":"Retail Goods"
        }
    ],
    "sg:phone":"+1 416 335 0040",
    "sg:postcode":"M1S 1S9",
    "sg:province":"ON",
    "sg:tags":[
        "car",
        "dealer"
    ],
    "wof:name":"M & M Auto Sales",
    "wof:placetype":"venue"
},
  "geometry": {"coordinates":[-79.28513336180001,43.7840995789],"type":"Point"}
}