{
  "type": "Feature",
  "properties": {
    "addr:full":"1047 Rue Principale Beresford NB E8K 1H2",
    "addr:housenumber":"1047",
    "addr:postcode":"e8k 1h2",
    "addr:street":"Rue Principale",
    "iso:country":"CA",
    "sg:address":"1047 Rue Principale",
    "sg:city":"Beresford",
    "sg:classifiers":[
        {
            "category":"Education",
            "subcategory":"Dance Studio",
            "type":"Public Place"
        }
    ],
    "sg:phone":"+1 506 546 8000",
    "sg:postcode":"E8K 1H2",
    "sg:province":"NB",
    "sg:tags":[
        "instruction",
        "dancing"
    ],
    "wof:name":"Ecole Danse Acadie",
    "wof:placetype":"venue"
},
  "geometry": {"coordinates":[-65.69684599999999,47.684803],"type":"Point"}
}