{
  "type": "Feature",
  "properties": {
    "addr:full":"3233 Brandon Gate Dr # 3 Mississauga ON L4T 3V8",
    "addr:housenumber":"3233",
    "addr:postcode":"l4t 3v8",
    "addr:street":"Brandon Gate Dr # 3",
    "iso:country":"CA",
    "sg:address":"3233 Brandon Gate Dr # 3",
    "sg:city":"Mississauga",
    "sg:classifiers":[
        {
            "category":"Restaurant",
            "type":"Food & Drink"
        }
    ],
    "sg:phone":"+1 905 677 8383",
    "sg:postcode":"L4T 3V8",
    "sg:province":"ON",
    "wof:name":"Jamaica Finest Restaurant",
    "wof:placetype":"venue"
},
  "geometry": {"coordinates":[-79.65254974370001,43.7203521729],"type":"Point"}
}