{
  "type": "Feature",
  "properties": {
    "addr:full":"Calgary AB T2P 3W2",
    "addr:postcode":"t2p 3w2",
    "iso:country":"CA",
    "sg:city":"Calgary",
    "sg:classifiers":[
        {
            "category":"Utilities",
            "subcategory":"Natural Gas",
            "type":"Services"
        }
    ],
    "sg:phone":"+1 403 237 7828",
    "sg:postcode":"T2P 3W2",
    "sg:province":"AB",
    "wof:name":"Global Petroleum Marketing Inc",
    "wof:placetype":"venue"
},
  "geometry": {"coordinates":[-114.078941345,51.0477561951],"type":"Point"}
}