{
  "type": "Feature",
  "properties": {
    "addr:full":"20470 Logan Ave Langley BC V3A 4L9",
    "addr:housenumber":"20470",
    "addr:postcode":"v3a 4l9",
    "addr:street":"Logan Ave",
    "iso:country":"CA",
    "sg:address":"20470 Logan Ave",
    "sg:city":"Langley",
    "sg:classifiers":[
        {
            "category":"Shopping",
            "subcategory":"Used Merchandise",
            "type":"Retail Goods"
        }
    ],
    "sg:phone":"+1 604 530 3232",
    "sg:postcode":"V3A 4L9",
    "sg:province":"BC",
    "sg:tags":[
        "shop",
        "second",
        "hand",
        "store",
        "thrift"
    ],
    "wof:name":"Penny Pincher",
    "wof:placetype":"venue"
},
  "geometry": {"coordinates":[-122.65576900000001,49.106892],"type":"Point"}
}