{
  "type": "Feature",
  "properties": {
    "addr:full":"710 Mount Paul Way Kamloops BC V2H 1B5",
    "addr:housenumber":"710",
    "addr:postcode":"bc v2h 1b5",
    "addr:street":"Mount Paul Way",
    "iso:country":"CA",
    "sg:address":"710 Mount Paul Way",
    "sg:city":"Kamloops",
    "sg:classifiers":[
        {
            "category":"Retail",
            "subcategory":"Auto Rental",
            "type":"Services"
        }
    ],
    "sg:phone":"+1 250 374 2835",
    "sg:postcode":"V2H 1B5",
    "sg:province":"BC",
    "sg:tags":[
        "renting",
        "truck",
        "leasing"
    ],
    "wof:name":"U-Haul CO Ltd",
    "wof:placetype":"venue"
},
  "geometry": {"coordinates":[-120.32229599999999,50.690983],"type":"Point"}
}