{
  "type": "Feature",
  "properties": {
    "addr:full":"Iqaluit NU X0A 0H0",
    "addr:postcode":"x0a 0h0",
    "iso:country":"CA",
    "sg:city":"Iqaluit",
    "sg:classifiers":[
        {
            "category":"Real Estate",
            "subcategory":"Real Estate Agent",
            "type":"Services"
        }
    ],
    "sg:phone":"+1 867 979 6800",
    "sg:postcode":"X0A 0H0",
    "sg:province":"NU",
    "sg:tags":[
        "building",
        "material",
        "rental",
        "agency"
    ],
    "wof:name":"Frobuild Construction Ltd",
    "wof:placetype":"venue"
},
  "geometry": {"coordinates":[-68.51902,63.751469],"type":"Point"}
}