{
  "type": "Feature",
  "properties": {
    "addr:full":"676 Monarch Ave Ajax ON L1S 4S2",
    "addr:housenumber":"676",
    "addr:postcode":"l1s 4s2",
    "addr:street":"Monarch Ave",
    "iso:country":"CA",
    "sg:address":"676 Monarch Ave",
    "sg:city":"Ajax",
    "sg:classifiers":[
        {
            "category":"Retail",
            "subcategory":"Repair Shop",
            "type":"Services"
        }
    ],
    "sg:phone":"+1 905 686 8662",
    "sg:postcode":"L1S 4S2",
    "sg:province":"ON",
    "sg:tags":[
        "pump"
    ],
    "wof:name":"Accurate Pump & Motor Svc",
    "wof:placetype":"venue"
},
  "geometry": {"coordinates":[-79.019241333,43.8321228027],"type":"Point"}
}