{
  "type": "Feature",
  "properties": {
    "addr:full":"Richmond BC V7E 2Z3",
    "addr:postcode":"v7e 2z3",
    "iso:country":"CA",
    "sg:city":"Richmond",
    "sg:classifiers":[
        {
            "category":"Building & Trades",
            "subcategory":"Landscaping Services",
            "type":"Services"
        }
    ],
    "sg:phone":"+1 604 275 3484",
    "sg:postcode":"V7E 2Z3",
    "sg:province":"BC",
    "sg:tags":[
        "tree"
    ],
    "wof:name":"Arbortech Consulting Ltd",
    "wof:placetype":"venue"
},
  "geometry": {"coordinates":[-123.183601,49.126213],"type":"Point"}
}