{
  "type": "Feature",
  "properties": {
    "addr:full":"857 Quail Dr Kamloops BC V2B 8P2",
    "addr:housenumber":"857",
    "addr:postcode":"bc v2b 8p2",
    "addr:street":"Quail Dr",
    "iso:country":"CA",
    "sg:address":"857 Quail Dr",
    "sg:city":"Kamloops",
    "sg:classifiers":[
        {
            "category":"Building & Trades",
            "subcategory":"Construction",
            "type":"Services"
        }
    ],
    "sg:phone":"+1 250 376 3944",
    "sg:postcode":"V2B 8P2",
    "sg:province":"BC",
    "sg:tags":[
        "dry wall",
        "contractor"
    ],
    "wof:name":"DO-All Drywall Ltd",
    "wof:placetype":"venue"
},
  "geometry": {"coordinates":[-120.364173889,50.7212905884],"type":"Point"}
}