{
  "type": "Feature",
  "properties": {
    "addr:full":"West Vancouver BC V7T 2W9",
    "addr:postcode":"v7t 2w9",
    "iso:country":"CA",
    "sg:city":"West Vancouver",
    "sg:classifiers":[
        {
            "category":"Professional",
            "subcategory":"Management & Consulting",
            "type":"Services"
        }
    ],
    "sg:phone":"+1 604 926 4509",
    "sg:postcode":"V7T 2W9",
    "sg:province":"BC",
    "sg:tags":[
        "consultant",
        "business"
    ],
    "wof:name":"Mc Neal & Assoc Conslnts Ltd",
    "wof:placetype":"venue"
},
  "geometry": {"coordinates":[-123.15322113000001,49.3288536072],"type":"Point"}
}