{
  "type": "Feature",
  "properties": {
    "addr:full":"181 Main St S Mount Forest ON N0G 2L0",
    "addr:housenumber":"181",
    "addr:postcode":"n0g 2l0",
    "addr:street":"Main St S Mount",
    "iso:country":"CA",
    "sg:address":"181 Main St S",
    "sg:city":"Mount Forest",
    "sg:classifiers":[
        {
            "category":"Shopping",
            "subcategory":"Jewelry",
            "type":"Retail Goods"
        }
    ],
    "sg:phone":"+1 519 323 1313",
    "sg:postcode":"N0G 2L0",
    "sg:province":"ON",
    "sg:tags":[
        "jeweler"
    ],
    "wof:name":"Wendt's Jewellery Ltd",
    "wof:placetype":"venue"
},
  "geometry": {"coordinates":[-80.73438299999999,43.980759],"type":"Point"}
}