{
  "type": "Feature",
  "properties": {
    "addr:full":"187 North Fork Rd Lumby BC V0E 2G3",
    "addr:housenumber":"187",
    "addr:postcode":"v0e 2g3",
    "addr:street":"North Fork Rd",
    "iso:country":"CA",
    "sg:address":"187 North Fork Rd",
    "sg:city":"Lumby",
    "sg:classifiers":[
        {
            "category":"Wholesale",
            "subcategory":"Farm Supplies",
            "type":"Manufacturing & Wholesale Goods"
        }
    ],
    "sg:phone":"+1 250 547 6755",
    "sg:postcode":"V0E 2G3",
    "sg:province":"BC",
    "sg:tags":[
        "feed"
    ],
    "wof:name":"Cherryville Emporium",
    "wof:placetype":"venue"
},
  "geometry": {"coordinates":[-118.966888428,50.2472686768],"type":"Point"}
}