{
  "type": "Feature",
  "properties": {
    "addr:full":"111 Fairford St E Moose Jaw SK S6H 7X5",
    "addr:housenumber":"111",
    "addr:postcode":"s6h 7x5",
    "addr:street":"Fairford St E",
    "iso:country":"CA",
    "sg:address":"111 Fairford St E",
    "sg:city":"Moose Jaw",
    "sg:classifiers":[
        {
            "category":"Government",
            "subcategory":"Office",
            "type":"Public Place"
        }
    ],
    "sg:phone":"+1 306 694 3900",
    "sg:postcode":"S6H 7X5",
    "sg:province":"SK",
    "wof:name":"Saskatchewan Water Corp",
    "wof:placetype":"venue"
},
  "geometry": {"coordinates":[-105.53153228799999,50.3927154541],"type":"Point"}
}