{
  "type": "Feature",
  "properties": {
    "addr:full":"120 Ch Val Comeau Val Comeau NB E1X 1J7",
    "addr:housenumber":"120",
    "addr:postcode":"e1x 1j7",
    "addr:street":"Ch Val Comeau Val Comeau",
    "iso:country":"CA",
    "sg:address":"120 Ch Val Comeau",
    "sg:city":"Val Comeau",
    "sg:classifiers":[
        {
            "category":"Restaurant",
            "type":"Food & Drink"
        }
    ],
    "sg:phone":"+1 506 395 7559",
    "sg:postcode":"E1X 1J7",
    "sg:province":"NB",
    "wof:name":"Cantine DE Chez-Nous",
    "wof:placetype":"venue"
},
  "geometry": {"coordinates":[-64.88098100000001,47.461391],"type":"Point"}
}