{
  "type": "Feature",
  "properties": {
    "iso:country":"CA",
    "sg:address":"1447 Rue Wolfe",
    "sg:city":"Montreal",
    "sg:classifiers":[
        {
            "category":"Travel",
            "subcategory":"Hotels & Motels",
            "type":"Entertainment"
        }
    ],
    "sg:phone":"+1 514 598 9587",
    "sg:postcode":"H2L 3J5",
    "sg:province":"QC",
    "sg:tags":[
        "breakfast",
        "accommodation",
        "bed"
    ],
    "wof:name":"Chez Roger Bontemps",
    "wof:placetype":"venue"
},
  "geometry": {"coordinates":[-73.557205,45.518372],"type":"Point"}
}