{
  "type": "Feature",
  "properties": {
    "addr:full":"55 Ormond St N Thorold ON L2V 1Y9",
    "addr:housenumber":"55",
    "addr:postcode":"l2v 1y9",
    "addr:street":"Ormond St N",
    "iso:country":"CA",
    "sg:address":"55 Ormond St N",
    "sg:city":"Thorold",
    "sg:classifiers":[
        {
            "category":"Retail",
            "subcategory":"Auto Repair",
            "type":"Services"
        }
    ],
    "sg:phone":"+1 905 680 1712",
    "sg:postcode":"L2V 1Y9",
    "sg:province":"ON",
    "sg:tags":[
        "repairing",
        "automobile"
    ],
    "wof:name":"Keniry's Service Station",
    "wof:placetype":"venue"
},
  "geometry": {"coordinates":[-79.199387,43.129059],"type":"Point"}
}