{
  "type": "Feature",
  "properties": {
    "addr:full":"Port Coquitlam BC V3C 5P1",
    "addr:postcode":"v3c 5p1",
    "iso:country":"CA",
    "sg:city":"Port Coquitlam",
    "sg:classifiers":[
        {
            "category":"Retail",
            "subcategory":"Car Wash",
            "type":"Services"
        }
    ],
    "sg:phone":"+1 604 944 8104",
    "sg:postcode":"V3C 5P1",
    "sg:province":"BC",
    "sg:tags":[
        "polishing",
        "truck",
        "washing"
    ],
    "wof:name":"Mary Hill Truck Wash",
    "wof:placetype":"venue"
},
  "geometry": {"coordinates":[-122.755959,49.243256],"type":"Point"}
}