{
  "type": "Feature",
  "properties": {
    "addr:full":"810 Railway Ave Carnduff SK S0C 0S0",
    "addr:housenumber":"810",
    "addr:postcode":"s0c 0s0",
    "addr:street":"Railway Ave",
    "iso:country":"CA",
    "sg:address":"810 Railway Ave",
    "sg:city":"Carnduff",
    "sg:classifiers":[
        {
            "category":"Sports & Exercise",
            "subcategory":"Bowling",
            "type":"Entertainment"
        }
    ],
    "sg:phone":"+1 306 482 5166",
    "sg:postcode":"S0C 0S0",
    "sg:province":"SK",
    "sg:tags":[
        "center"
    ],
    "wof:name":"Carnduff Bowl Ltd",
    "wof:placetype":"venue"
},
  "geometry": {"coordinates":[-101.799049377,49.1772232056],"type":"Point"}
}