{
  "type": "Feature",
  "properties": {
    "addr:full":"Barrie ON L4N 7L2",
    "addr:postcode":"l4n 7l2",
    "iso:country":"CA",
    "sg:city":"Barrie",
    "sg:classifiers":[
        {
            "category":"Personal",
            "subcategory":"Tanning Parlor",
            "type":"Services"
        }
    ],
    "sg:phone":"+1 705 722 0079",
    "sg:postcode":"L4N 7L2",
    "sg:province":"ON",
    "sg:tags":[
        "salon"
    ],
    "wof:name":"Beverly Hills Tanning Salon",
    "wof:placetype":"venue"
},
  "geometry": {"coordinates":[-79.70693199999999,44.381973],"type":"Point"}
}