{
  "type": "Feature",
  "properties": {
    "addr:full":"601 45th St E Saskatoon SK S7K 0W4",
    "addr:housenumber":"601",
    "addr:postcode":"s7k 0w4",
    "addr:street":"45Th St E",
    "iso:country":"CA",
    "sg:address":"601 45th St E",
    "sg:city":"Saskatoon",
    "sg:classifiers":[
        {
            "category":"Wholesale",
            "subcategory":"Machinery & Supplies",
            "type":"Manufacturing & Wholesale Goods"
        }
    ],
    "sg:phone":"+1 306 652 4133",
    "sg:postcode":"S7K 0W4",
    "sg:province":"SK",
    "sg:tags":[
        "agricultural",
        "implement"
    ],
    "wof:name":"Bridon Cordage Ltd",
    "wof:placetype":"venue"
},
  "geometry": {"coordinates":[-106.659828,52.162262],"type":"Point"}
}