{
  "type": "Feature",
  "properties": {
    "addr:full":"25 St Michael St St Albert AB T8N 1C7",
    "addr:housenumber":"25",
    "addr:postcode":"t8n 1c7",
    "addr:street":"St Michael St",
    "iso:country":"CA",
    "sg:address":"25 St Michael St",
    "sg:city":"St Albert",
    "sg:classifiers":[
        {
            "category":"Personal",
            "type":"Services"
        }
    ],
    "sg:phone":"+1 780 419 3227",
    "sg:postcode":"T8N 1C7",
    "sg:province":"AB",
    "sg:tags":[
        "electrolysis"
    ],
    "wof:name":"Kim's Electrolysis Ctr",
    "wof:placetype":"venue"
},
  "geometry": {"coordinates":[-113.625252,53.633915],"type":"Point"}
}