{
  "type": "Feature",
  "properties": {
    "addr:full":"Champlain QC G0X 1C0",
    "addr:postcode":"g0x 1c0",
    "iso:country":"CA",
    "sg:city":"Champlain",
    "sg:classifiers":[
        {
            "category":"Government",
            "subcategory":"Office",
            "type":"Public Place"
        }
    ],
    "sg:phone":"+1 819 295 3979",
    "sg:postcode":"G0X 1C0",
    "sg:province":"QC",
    "sg:tags":[
        "village"
    ],
    "wof:name":"Champlain Corportation Mncpl",
    "wof:placetype":"venue"
},
  "geometry": {"coordinates":[-72.35440800000001,46.437027],"type":"Point"}
}