{
  "type": "Feature",
  "properties": {
    "addr:full":"Castlegar BC V1N 1Z9",
    "addr:postcode":"v1n 1z9",
    "iso:country":"CA",
    "sg:city":"Castlegar",
    "sg:classifiers":[
        {
            "category":"Shopping",
            "subcategory":"Pharmacy",
            "type":"Retail Goods"
        }
    ],
    "sg:phone":"+1 250 365 7813",
    "sg:postcode":"V1N 1Z9",
    "sg:province":"BC",
    "wof:name":"Pharmasave Drugs",
    "wof:placetype":"venue"
},
  "geometry": {"coordinates":[-117.664596558,49.3263511658],"type":"Point"}
}