{
  "type": "Feature",
  "properties": {
    "iso:country":"CA",
    "sg:address":"7 Arbour Lake Dr NW",
    "sg:city":"Calgary",
    "sg:classifiers":[
        {
            "category":"Food & Beverages",
            "subcategory":"Specialty",
            "type":"Retail Goods"
        }
    ],
    "sg:phone":"+1 403 547 6333",
    "sg:postcode":"T3G 5G8",
    "sg:province":"AB",
    "sg:tags":[
        "health",
        "diet"
    ],
    "wof:name":"Amaranth Whole Foods Market",
    "wof:placetype":"venue"
},
  "geometry": {"coordinates":[-114.203262329,51.1337661743],"type":"Point"}
}