{
  "type": "Feature",
  "properties": {
    "addr:full":"2303 Boul Saint-Paul Chicoutimi QC G7K 1E5",
    "addr:housenumber":"2303",
    "addr:postcode":"g7k 1e5",
    "addr:street":"Boul Saint-Paul",
    "iso:country":"CA",
    "sg:address":"2303 Boul Saint-Paul",
    "sg:city":"Chicoutimi",
    "sg:classifiers":[
        {
            "category":"Retail",
            "subcategory":"Auto Repair",
            "type":"Services"
        }
    ],
    "sg:phone":"+1 418 545 0616",
    "sg:postcode":"G7K 1E5",
    "sg:province":"QC",
    "sg:tags":[
        "body",
        "automobile",
        "painting"
    ],
    "wof:name":"Carrosserie Futuriste",
    "wof:placetype":"venue"
},
  "geometry": {"coordinates":[-71.11378499999999,48.388725],"type":"Point"}
}