{
  "type": "Feature",
  "properties": {
    "iso:country":"CA",
    "sg:city":"Edmonton",
    "sg:classifiers":[
        {
            "category":"Government",
            "subcategory":"Office",
            "type":"Public Place"
        }
    ],
    "sg:phone":"+1 780 496 5993",
    "sg:postcode":"T5J 3A3",
    "sg:province":"AB",
    "sg:tags":[
        "village"
    ],
    "wof:name":"Edmonton Office-Environment",
    "wof:placetype":"venue"
},
  "geometry": {"coordinates":[-113.48796844500001,53.5445594788],"type":"Point"}
}