{
  "type": "Feature",
  "properties": {
    "iso:country":"CA",
    "sg:city":"Ottawa",
    "sg:classifiers":[
        {
            "category":"Restaurant",
            "type":"Food & Drink"
        }
    ],
    "sg:phone":"+1 613 234 5544",
    "sg:postcode":"K1N 9J7",
    "sg:province":"ON",
    "wof:name":"Elephant & Castle Restaurant",
    "wof:placetype":"venue"
},
  "geometry": {"coordinates":[-75.691765,45.444431],"type":"Point"}
}