{
  "type": "Feature",
  "properties": {
    "iso:country":"CA",
    "sg:address":"5120 49th Ave",
    "sg:city":"Edgerton",
    "sg:classifiers":[
        {
            "category":"Food & Beverages",
            "subcategory":"Groceries & Convenience Stores",
            "type":"Retail Goods"
        }
    ],
    "sg:phone":"+1 780 755 3930",
    "sg:postcode":"T0B 1K0",
    "sg:province":"AB",
    "wof:name":"Herbie's Auto & Confectionery",
    "wof:placetype":"venue"
},
  "geometry": {"coordinates":[-110.462524414,52.7591362],"type":"Point"}
}