{
  "type": "Feature",
  "properties": {
    "addr:full":"9 Grange St Annapolis Royal NS B0S 1A0",
    "addr:housenumber":"9",
    "addr:postcode":"b0s 1a0",
    "addr:street":"Grange St",
    "iso:country":"CA",
    "sg:address":"9 Grange St",
    "sg:city":"Annapolis Royal",
    "sg:classifiers":[
        {
            "category":"Social Services",
            "subcategory":"Child Care",
            "type":"Services"
        }
    ],
    "sg:phone":"+1 902 532 7736",
    "sg:postcode":"B0S 1A0",
    "sg:province":"NS",
    "wof:name":"Good Beginings Day Care Ctr",
    "wof:placetype":"venue"
},
  "geometry": {"coordinates":[-65.509216,44.740761],"type":"Point"}
}