{
  "type": "Feature",
  "properties": {
    "addr:full":"864 Pacific Dr Delta BC V4M 2K3",
    "addr:housenumber":"864",
    "addr:postcode":"v4m 2k3",
    "addr:street":"Pacific Dr",
    "iso:country":"CA",
    "sg:address":"864 Pacific Dr",
    "sg:city":"Delta",
    "sg:classifiers":[
        {
            "category":"Professional",
            "subcategory":"Management & Consulting",
            "type":"Services"
        }
    ],
    "sg:phone":"+1 604 943 3715",
    "sg:postcode":"V4M 2K3",
    "sg:province":"BC",
    "sg:tags":[
        "consultant",
        "business"
    ],
    "wof:name":"Ian D Robertson Inc",
    "wof:placetype":"venue"
},
  "geometry": {"coordinates":[-123.092934,49.018593],"type":"Point"}
}