{
  "type": "Feature",
  "properties": {
    "addr:full":"3785 13 Ave SE Medicine Hat AB T1B 1J2",
    "addr:housenumber":"3785",
    "addr:postcode":"t1b 1j2",
    "addr:street":"13 Ave Se",
    "iso:country":"CA",
    "sg:address":"3785 13 Ave SE",
    "sg:city":"Medicine Hat",
    "sg:classifiers":[
        {
            "category":"Organizations",
            "subcategory":"Religious Organization",
            "type":"Services"
        }
    ],
    "sg:phone":"+1 403 526 4010",
    "sg:postcode":"T1B 1J2",
    "sg:province":"AB",
    "sg:tags":[
        "church"
    ],
    "wof:name":"Hillcrest Evangelical Mssnry",
    "wof:placetype":"venue"
},
  "geometry": {"coordinates":[-110.665634,50.002857],"type":"Point"}
}