{
  "type": "Feature",
  "properties": {
    "addr:full":"2451 Bloor St W Toronto ON M6S 1P7",
    "addr:housenumber":"2451",
    "addr:postcode":"m6s 1p7",
    "addr:street":"Bloor St W",
    "iso:country":"CA",
    "sg:address":"2451 Bloor St W",
    "sg:city":"Toronto",
    "sg:classifiers":[
        {
            "category":"Education",
            "subcategory":"Special Training",
            "type":"Public Place"
        }
    ],
    "sg:phone":"+1 416 766 0662",
    "sg:postcode":"M6S 1P7",
    "sg:province":"ON",
    "sg:tags":[
        "school",
        "instruction",
        "art"
    ],
    "wof:name":"Art Works Art School",
    "wof:placetype":"venue"
},
  "geometry": {"coordinates":[-79.48448944090001,43.6492805481],"type":"Point"}
}