{
  "type": "Feature",
  "properties": {
    "addr:full":"Edmonton AB T6J 6R5",
    "addr:postcode":"t6j 6r5",
    "iso:country":"CA",
    "sg:city":"Edmonton",
    "sg:classifiers":[
        {
            "category":"Shopping",
            "subcategory":"Luggage & Leather Goods",
            "type":"Retail Goods"
        }
    ],
    "sg:phone":"+1 780 437 1040",
    "sg:postcode":"T6J 6R5",
    "sg:province":"AB",
    "wof:name":"Boutique of Leathers Ltd",
    "wof:placetype":"venue"
},
  "geometry": {"coordinates":[-113.492279,53.468937],"type":"Point"}
}