{
  "type": "Feature",
  "properties": {
    "addr:full":"588 Boul Du Royaume O Chicoutimi QC G7H 5B1",
    "addr:housenumber":"588",
    "addr:postcode":"g7h 5b1",
    "addr:street":"Boul Du Royaume O",
    "iso:country":"CA",
    "sg:address":"588 Boul Du Royaume O",
    "sg:city":"Chicoutimi",
    "sg:classifiers":[
        {
            "category":"Building & Trades",
            "subcategory":"Construction",
            "type":"Services"
        }
    ],
    "sg:phone":"+1 418 696 1260",
    "sg:postcode":"G7H 5B1",
    "sg:province":"QC",
    "sg:tags":[
        "general",
        "contractor"
    ],
    "wof:name":"J Perron Euclide Ltee",
    "wof:placetype":"venue"
},
  "geometry": {"coordinates":[-71.095001,48.384216],"type":"Point"}
}