{
  "type": "Feature",
  "properties": {
    "addr:full":"8427 112 St NW Edmonton AB T6G 1K5",
    "addr:housenumber":"8427",
    "addr:postcode":"t6g 1k5",
    "addr:street":"112 St Nw",
    "iso:country":"CA",
    "sg:address":"8427 112 St NW",
    "sg:city":"Edmonton",
    "sg:classifiers":[
        {
            "category":"Restaurant",
            "type":"Food & Drink"
        }
    ],
    "sg:phone":"+1 780 434 6608",
    "sg:postcode":"T6G 1K5",
    "sg:province":"AB",
    "wof:name":"Wendy's",
    "wof:placetype":"venue"
},
  "geometry": {"coordinates":[-113.520622,53.520348],"type":"Point"}
}