{
  "type": "Feature",
  "properties": {
    "iso:country":"CA",
    "sg:address":"350 Rue Principale",
    "sg:city":"Saint-Donat-DE-Montcalm",
    "sg:classifiers":[
        {
            "category":"Home & Garden",
            "subcategory":"Carpets & Floor Coverings",
            "type":"Retail Goods"
        }
    ],
    "sg:phone":"+1 819 424 2929",
    "sg:postcode":"J0T 2C0",
    "sg:province":"QC",
    "sg:tags":[
        "dealer",
        "rug"
    ],
    "wof:name":"Couvre-Planchers Laforest Inc",
    "wof:placetype":"venue"
},
  "geometry": {"coordinates":[-74.22481536870001,46.320438385],"type":"Point"}
}