{
  "type": "Feature",
  "properties": {
    "addr:full":"1415 1 Ave NW Calgary AB T2N 0A9",
    "addr:housenumber":"1415",
    "addr:postcode":"t2n 0a9",
    "addr:street":"1 Ave Nw",
    "iso:country":"CA",
    "sg:address":"1415 1 Ave NW",
    "sg:city":"Calgary",
    "sg:classifiers":[
        {
            "category":"Organizations",
            "subcategory":"Religious Organization",
            "type":"Services"
        }
    ],
    "sg:phone":"+1 403 283 5284",
    "sg:postcode":"T2N 0A9",
    "sg:province":"AB",
    "sg:tags":[
        "church"
    ],
    "wof:name":"Sisters of Charity of St Louis",
    "wof:placetype":"venue"
},
  "geometry": {"coordinates":[-114.092102051,51.0532798767],"type":"Point"}
}