{
  "type": "Feature",
  "properties": {
    "addr:full":"1159 Highbury Ave N London ON N5Y 1A6",
    "addr:housenumber":"1159",
    "addr:postcode":"n5y 1a6",
    "addr:street":"Highbury Ave N",
    "iso:country":"CA",
    "sg:address":"1159 Highbury Ave N",
    "sg:city":"London",
    "sg:classifiers":[
        {
            "category":"Restaurant",
            "type":"Food & Drink"
        }
    ],
    "sg:phone":"+1 519 451 6830",
    "sg:postcode":"N5Y 1A6",
    "sg:province":"ON",
    "wof:name":"Mc Donald's",
    "wof:placetype":"venue"
},
  "geometry": {"coordinates":[-81.212929,43.014801],"type":"Point"}
}