{
  "type": "Feature",
  "properties": {
    "addr:full":"Etobicoke ON M9R 1T1",
    "addr:postcode":"m9r 1t1",
    "iso:country":"CA",
    "sg:city":"Etobicoke",
    "sg:classifiers":[
        {
            "category":"Shopping",
            "subcategory":"Stationery & Office Supplies",
            "type":"Retail Goods"
        }
    ],
    "sg:phone":"+1 416 249 4002",
    "sg:postcode":"M9R 1T1",
    "sg:province":"ON",
    "sg:tags":[
        "importer"
    ],
    "wof:name":"Malani International",
    "wof:placetype":"venue"
},
  "geometry": {"coordinates":[-79.553719,43.695591],"type":"Point"}
}