{
  "type": "Feature",
  "properties": {
    "addr:full":"10 Taber Rd Etobicoke ON M9W 3A4",
    "addr:housenumber":"10",
    "addr:postcode":"m9w 3a4",
    "addr:street":"Taber Rd",
    "iso:country":"CA",
    "sg:address":"10 Taber Rd",
    "sg:city":"Etobicoke",
    "sg:classifiers":[
        {
            "category":"Restaurant",
            "type":"Food & Drink"
        }
    ],
    "sg:phone":"+1 416 748 2941",
    "sg:postcode":"M9W 3A4",
    "sg:province":"ON",
    "wof:name":"Remo's Place",
    "wof:placetype":"venue"
},
  "geometry": {"coordinates":[-79.57220458979999,43.7190704346],"type":"Point"}
}