{
  "type": "Feature",
  "properties": {
    "addr:full":"46 Boul Rene-Levesque O Quebec QC G1R 2A4",
    "addr:housenumber":"46",
    "addr:postcode":"g1r 2a4",
    "addr:street":"Boul Rene-Levesque O",
    "iso:country":"CA",
    "sg:address":"46 Boul Rene-Levesque O",
    "sg:city":"Quebec",
    "sg:classifiers":[
        {
            "category":"Restaurant",
            "type":"Food & Drink"
        }
    ],
    "sg:phone":"+1 418 523 2013",
    "sg:postcode":"G1R 2A4",
    "sg:province":"QC",
    "wof:name":"Cochon Dingue",
    "wof:placetype":"venue"
},
  "geometry": {"coordinates":[-71.224991,46.805428],"type":"Point"}
}