{
  "type": "Feature",
  "properties": {
    "iso:country":"CA",
    "sg:city":"Warwick",
    "sg:classifiers":[
        {
            "category":"Education",
            "subcategory":"Dance Studio",
            "type":"Public Place"
        }
    ],
    "sg:phone":"+1 819 358 6749",
    "sg:postcode":"J0A 1M0",
    "sg:province":"QC",
    "sg:tags":[
        "instruction",
        "dancing"
    ],
    "wof:name":"Multidance Enr",
    "wof:placetype":"venue"
},
  "geometry": {"coordinates":[-71.9865036011,45.9438896179],"type":"Point"}
}