{
  "type": "Feature",
  "properties": {
    "addr:full":"338 5th St Courtenay BC V9N 1K1",
    "addr:housenumber":"338",
    "addr:postcode":"v9n 1k1",
    "addr:street":"5Th St",
    "iso:country":"CA",
    "sg:address":"338 5th St",
    "sg:city":"Courtenay",
    "sg:classifiers":[
        {
            "category":"Shopping",
            "subcategory":"Clothing, Apparel, & Fashions",
            "type":"Retail Goods"
        }
    ],
    "sg:phone":"+1 250 338 6613",
    "sg:postcode":"V9N 1K1",
    "sg:province":"BC",
    "wof:name":"Fairhearts",
    "wof:placetype":"venue"
},
  "geometry": {"coordinates":[-124.999138,49.690636],"type":"Point"}
}