{
  "type": "Feature",
  "properties": {
    "iso:country":"CA",
    "sg:city":"Guelph",
    "sg:classifiers":[
        {
            "category":"Health Services",
            "subcategory":"Optometrist",
            "type":"Services"
        }
    ],
    "sg:phone":"+1 519 824 4425",
    "sg:postcode":"N1G 3W8",
    "sg:province":"ON",
    "wof:name":"Hrvatin, Doris OD",
    "wof:placetype":"venue"
},
  "geometry": {"coordinates":[-80.231354,43.508366],"type":"Point"}
}