{
  "type": "Feature",
  "properties": {
    "addr:full":"132 Mccaul St Toronto ON M5T 1W2",
    "addr:housenumber":"132",
    "addr:postcode":"m5t 1w2",
    "addr:street":"Mccaul St",
    "iso:country":"CA",
    "sg:address":"132 Mccaul St",
    "sg:city":"Toronto",
    "sg:classifiers":[
        {
            "category":"Restaurant",
            "type":"Food & Drink"
        }
    ],
    "sg:phone":"+1 416 595 1943",
    "sg:postcode":"M5T 1W2",
    "sg:province":"ON",
    "sg:tags":[
        "cafe"
    ],
    "wof:name":"Frecklebean Cafe",
    "wof:placetype":"venue"
},
  "geometry": {"coordinates":[-79.3918457031,43.6548194885],"type":"Point"}
}