{
  "type": "Feature",
  "properties": {
    "addr:full":"289 Graham St Woodstock ON N4S 6K8",
    "addr:housenumber":"289",
    "addr:postcode":"n4s 6k8",
    "addr:street":"Graham St",
    "iso:country":"CA",
    "sg:address":"289 Graham St",
    "sg:city":"Woodstock",
    "sg:classifiers":[
        {
            "category":"Social Services",
            "type":"Services"
        }
    ],
    "sg:phone":"+1 519 539 3051",
    "sg:postcode":"N4S 6K8",
    "sg:province":"ON",
    "sg:tags":[
        "organization",
        "welfare"
    ],
    "wof:name":"Horizon House Oxford",
    "wof:placetype":"venue"
},
  "geometry": {"coordinates":[-80.761421,43.139729],"type":"Point"}
}