{
  "type": "Feature",
  "properties": {
    "addr:full":"220 Portage Ave Winnipeg MB R3C 0C2",
    "addr:housenumber":"220",
    "addr:postcode":"r3c 0c2",
    "addr:street":"Portage Ave",
    "iso:country":"CA",
    "sg:address":"220 Portage Ave",
    "sg:city":"Winnipeg",
    "sg:classifiers":[
        {
            "category":"Restaurant",
            "type":"Food & Drink"
        }
    ],
    "sg:phone":"+1 204 956 5738",
    "sg:postcode":"R3C 0C2",
    "sg:province":"MB",
    "sg:tags":[
        "shop",
        "coffee"
    ],
    "wof:name":"Gaberniks Cafe Etc",
    "wof:placetype":"venue"
},
  "geometry": {"coordinates":[-97.13906860349999,49.8949775696],"type":"Point"}
}