{
  "type": "Feature",
  "properties": {
    "iso:country":"CA",
    "sg:city":"Fairview",
    "sg:classifiers":[
        {
            "category":"Travel",
            "subcategory":"Travel Agent",
            "type":"Entertainment"
        }
    ],
    "sg:phone":"+1 780 835 4252",
    "sg:postcode":"T0H 1L0",
    "sg:province":"AB",
    "sg:tags":[
        "agency",
        "bureau"
    ],
    "wof:name":"Marlin Fairview Travel",
    "wof:placetype":"venue"
},
  "geometry": {"coordinates":[-118.384498596,56.0688056946],"type":"Point"}
}