{
  "type": "Feature",
  "properties": {
    "addr:full":"341 Stanley St Winnipeg MB R3A 1S7",
    "addr:housenumber":"341",
    "addr:postcode":"r3a 1s7",
    "addr:street":"Stanley St",
    "iso:country":"CA",
    "sg:address":"341 Stanley St",
    "sg:city":"Winnipeg",
    "sg:classifiers":[
        {
            "category":"Freight",
            "type":"Transportation"
        }
    ],
    "sg:phone":"+1 204 956 4665",
    "sg:postcode":"R3A 1S7",
    "sg:province":"MB",
    "sg:tags":[
        "wrecker",
        "trucking"
    ],
    "wof:name":"Dr Hook Towing",
    "wof:placetype":"venue"
},
  "geometry": {"coordinates":[-97.13859600000001,49.905594],"type":"Point"}
}