{
  "type": "Feature",
  "properties": {
    "addr:full":"7317 Toni Sailor Lane Whistler BC V0N 1B7",
    "addr:housenumber":"7317",
    "addr:postcode":"v0n 1b7",
    "addr:street":"Toni Sailor Lane",
    "iso:country":"CA",
    "sg:address":"7317 Toni Sailor Lane",
    "sg:city":"Whistler",
    "sg:classifiers":[
        {
            "category":"Professional",
            "subcategory":"Art Services",
            "type":"Services"
        }
    ],
    "sg:phone":"+1 604 938 1372",
    "sg:postcode":"V0N 1B7",
    "sg:province":"BC",
    "sg:tags":[
        "photographer"
    ],
    "wof:name":"Bonny Makarewicz Photography",
    "wof:placetype":"venue"
},
  "geometry": {"coordinates":[-122.950287,50.125671],"type":"Point"}
}