{
  "type": "Feature",
  "properties": {
    "addr:full":"2786 Agricola St # 215 Halifax NS B3K 4E1",
    "addr:housenumber":"2786",
    "addr:postcode":"b3k 4e1",
    "addr:street":"Agricola St # 215",
    "iso:country":"CA",
    "sg:address":"2786 Agricola St # 215",
    "sg:city":"Halifax",
    "sg:classifiers":[
        {
            "category":"Manufacturing",
            "subcategory":"Printing",
            "type":"Manufacturing & Wholesale Goods"
        }
    ],
    "sg:phone":"+1 902 453 5510",
    "sg:postcode":"B3K 4E1",
    "sg:province":"NS",
    "sg:tags":[
        "newspaper"
    ],
    "wof:name":"Street Feat",
    "wof:placetype":"venue"
},
  "geometry": {"coordinates":[-63.5973777771,44.6579322815],"type":"Point"}
}