{
  "type": "Feature",
  "properties": {
    "addr:full":"137 4th St Cochrane ON P0L 1C0",
    "addr:housenumber":"137",
    "addr:postcode":"p0l 1c0",
    "addr:street":"4Th St",
    "iso:country":"CA",
    "sg:address":"137 4th St",
    "sg:city":"Cochrane",
    "sg:classifiers":[
        {
            "category":"Food & Beverages",
            "subcategory":"Liquor & Beverages",
            "type":"Retail Goods"
        }
    ],
    "sg:phone":"+1 705 272 3263",
    "sg:postcode":"P0L 1C0",
    "sg:province":"ON",
    "sg:tags":[
        "store"
    ],
    "wof:name":"Liquor Control Board of Ont",
    "wof:placetype":"venue"
},
  "geometry": {"coordinates":[-81.0268936157,49.0638046265],"type":"Point"}
}