{
  "type": "Feature",
  "properties": {
    "addr:full":"475 Georgia St W #1015 Vancouver BC V6B 4M9",
    "addr:housenumber":"475;1015",
    "addr:postcode":"v6b 4m9",
    "addr:street":"Georgia St W #",
    "iso:country":"CA",
    "sg:address":"475 Georgia St W #1015",
    "sg:city":"Vancouver",
    "sg:classifiers":[
        {
            "category":"Professional",
            "subcategory":"Management & Consulting",
            "type":"Services"
        }
    ],
    "sg:phone":"+1 604 683 3363",
    "sg:postcode":"V6B 4M9",
    "sg:province":"BC",
    "sg:tags":[
        "consultant",
        "business"
    ],
    "wof:name":"Golden Visa Consultants",
    "wof:placetype":"venue"
},
  "geometry": {"coordinates":[-123.115631103,49.281124115],"type":"Point"}
}