{
  "type": "Feature",
  "properties": {
    "addr:full":"1821 Lonsdale Ave North Vancouver BC V7M 2J8",
    "addr:housenumber":"1821",
    "addr:postcode":"v7m 2j8",
    "addr:street":"Lonsdale Ave",
    "iso:country":"CA",
    "sg:address":"1821 Lonsdale Ave",
    "sg:city":"North Vancouver",
    "sg:classifiers":[
        {
            "category":"Education",
            "subcategory":"Special Training",
            "type":"Public Place"
        }
    ],
    "sg:phone":"+1 604 299 9292",
    "sg:postcode":"V7M 2J8",
    "sg:province":"BC",
    "sg:tags":[
        "instruction",
        "driving"
    ],
    "wof:name":"North Shore Driving School Ltd",
    "wof:placetype":"venue"
},
  "geometry": {"coordinates":[-123.072411,49.325474],"type":"Point"}
}