{
  "type": "Feature",
  "properties": {
    "addr:full":"Barrie ON L4M 1A4",
    "addr:postcode":"l4m 1a4",
    "iso:country":"CA",
    "sg:city":"Barrie",
    "sg:classifiers":[
        {
            "category":"Shopping",
            "subcategory":"Used Merchandise",
            "type":"Retail Goods"
        }
    ],
    "sg:phone":"+1 705 737 1322",
    "sg:postcode":"L4M 1A4",
    "sg:province":"ON",
    "sg:tags":[
        "shop",
        "consignment"
    ],
    "wof:name":"Gingham Door",
    "wof:placetype":"venue"
},
  "geometry": {"coordinates":[-79.6860046387,44.3894424438],"type":"Point"}
}