{
  "type": "Feature",
  "properties": {
    "addr:full":"Montreal QC H3V 1B5",
    "addr:postcode":"h3v 1b5",
    "iso:country":"CA",
    "sg:city":"Montreal",
    "sg:classifiers":[
        {
            "category":"Professional",
            "type":"Services"
        }
    ],
    "sg:phone":"+1 514 737 0558",
    "sg:postcode":"H3V 1B5",
    "sg:province":"QC",
    "sg:tags":[
        "writer"
    ],
    "wof:name":"Editions Francine Breton",
    "wof:placetype":"venue"
},
  "geometry": {"coordinates":[-73.611572,45.494408],"type":"Point"}
}