{
  "type": "Feature",
  "properties": {
    "iso:country":"CA",
    "sg:address":"36 Easton Rd",
    "sg:city":"Brantford",
    "sg:classifiers":[
        {
            "category":"Manufacturing",
            "subcategory":"Apparel",
            "type":"Manufacturing & Wholesale Goods"
        }
    ],
    "sg:phone":"+1 519 751 1980",
    "sg:postcode":"N3P 1J5",
    "sg:province":"ON",
    "sg:tags":[
        "clothing"
    ],
    "wof:name":"Pro Knitting Inc",
    "wof:placetype":"venue"
},
  "geometry": {"coordinates":[-80.2430114746,43.1783294678],"type":"Point"}
}