{
  "type": "Feature",
  "properties": {
    "addr:full":"Wabamun AB T0E 2K0",
    "addr:postcode":"t0e 2k0",
    "iso:country":"CA",
    "sg:city":"Wabamun",
    "sg:classifiers":[
        {
            "category":"Food & Beverages",
            "subcategory":"Liquor & Beverages",
            "type":"Retail Goods"
        }
    ],
    "sg:phone":"+1 780 892 3463",
    "sg:postcode":"T0E 2K0",
    "sg:province":"AB",
    "sg:tags":[
        "store"
    ],
    "wof:name":"Wabamun Lakeside Liquor Ltd",
    "wof:placetype":"venue"
},
  "geometry": {"coordinates":[-114.47302999999999,53.559547],"type":"Point"}
}