{
  "type": "Feature",
  "properties": {
    "addr:full":"526 5 St S Lethbridge AB T1J 2B8",
    "addr:housenumber":"526 5",
    "addr:postcode":"t1j 2b8",
    "addr:street":"St S",
    "iso:country":"CA",
    "sg:address":"526 5 St S",
    "sg:city":"Lethbridge",
    "sg:classifiers":[
        {
            "category":"Real Estate",
            "subcategory":"Real Estate Agent",
            "type":"Services"
        }
    ],
    "sg:phone":"+1 403 327 2111",
    "sg:postcode":"T1J 2B8",
    "sg:province":"AB",
    "wof:name":"South Country Real Estate Svc",
    "wof:placetype":"venue"
},
  "geometry": {"coordinates":[-112.840141296,49.6921958923],"type":"Point"}
}