{
  "type": "Feature",
  "properties": {
    "addr:full":"New Ross NS B0J 2M0",
    "addr:postcode":"b0j 2m0",
    "iso:country":"CA",
    "sg:city":"New Ross",
    "sg:classifiers":[
        {
            "category":"Home & Garden",
            "subcategory":"Garden Supply",
            "type":"Retail Goods"
        }
    ],
    "sg:phone":"+1 902 689 2262",
    "sg:postcode":"B0J 2M0",
    "sg:province":"NS",
    "sg:tags":[
        "tree",
        "christmas"
    ],
    "wof:name":"Sanders Tree Yard",
    "wof:placetype":"venue"
},
  "geometry": {"coordinates":[-64.4535827637,44.7370452881],"type":"Point"}
}