{
  "type": "Feature",
  "properties": {
    "addr:full":"8750 Boul Provencher Saint-Leonard QC H1R 3N7",
    "addr:housenumber":"8750",
    "addr:postcode":"h1r 3n7",
    "addr:street":"Boul Provencher",
    "iso:country":"CA",
    "sg:address":"8750 Boul Provencher",
    "sg:city":"Saint-Leonard",
    "sg:classifiers":[
        {
            "category":"Restaurant",
            "type":"Food & Drink"
        }
    ],
    "sg:phone":"+1 514 374 7428",
    "sg:postcode":"H1R 3N7",
    "sg:province":"QC",
    "sg:tags":[
        "auditorium",
        "rooms",
        "banquet",
        "hall"
    ],
    "wof:name":"Madison",
    "wof:placetype":"venue"
},
  "geometry": {"coordinates":[-73.610710144,45.581073761],"type":"Point"}
}