{
  "type": "Feature",
  "properties": {
    "addr:full":"10702 108A St Grande Prairie AB T8V 7M5",
    "addr:housenumber":"10702",
    "addr:postcode":"t8v 7m5",
    "addr:street":"108A St",
    "iso:country":"CA",
    "sg:address":"10702 108A St",
    "sg:city":"Grande Prairie",
    "sg:classifiers":[
        {
            "category":"Bars & Pubs",
            "type":"Food & Drink"
        }
    ],
    "sg:phone":"+1 780 513 5511",
    "sg:postcode":"T8V 7M5",
    "sg:province":"AB",
    "wof:name":"Lions Den Pub",
    "wof:placetype":"venue"
},
  "geometry": {"coordinates":[-118.794891357,55.1711616516],"type":"Point"}
}