{
  "type": "Feature",
  "properties": {
    "addr:full":"1121 15 St SE Salmon Arm BC V1E 2E3",
    "addr:housenumber":"1121",
    "addr:postcode":"v1e 2e3",
    "addr:street":"15 St Se",
    "iso:country":"CA",
    "sg:address":"1121 15 St SE",
    "sg:city":"Salmon Arm",
    "sg:classifiers":[
        {
            "category":"Organizations",
            "subcategory":"Religious Organization",
            "type":"Services"
        }
    ],
    "sg:phone":"+1 250 832 9918",
    "sg:postcode":"V1E 2E3",
    "sg:province":"BC",
    "sg:tags":[
        "church"
    ],
    "wof:name":"Emmanuel Lutheran Church",
    "wof:placetype":"venue"
},
  "geometry": {"coordinates":[-119.268035889,50.6924514771],"type":"Point"}
}