{
  "type": "Feature",
  "properties": {
    "iso:country":"CA",
    "sg:address":"1286 Des Pionniers Ave",
    "sg:city":"Balmoral",
    "sg:classifiers":[
        {
            "category":"Wholesale",
            "subcategory":"Machinery & Supplies",
            "type":"Manufacturing & Wholesale Goods"
        }
    ],
    "sg:phone":"+1 506 826 2310",
    "sg:postcode":"E8E 1E7",
    "sg:province":"NB",
    "sg:tags":[
        "contractor"
    ],
    "wof:name":"Maurice Senechal Crane Rental",
    "wof:placetype":"venue"
},
  "geometry": {"coordinates":[-66.45017242430001,47.9712867737],"type":"Point"}
}