{
  "type": "Feature",
  "properties": {
    "addr:full":"165 Turnbull Crt Cambridge ON N1T 1C6",
    "addr:housenumber":"165",
    "addr:postcode":"n1t 1c6",
    "addr:street":"Turnbull Crt",
    "iso:country":"CA",
    "sg:address":"165 Turnbull Crt",
    "sg:city":"Cambridge",
    "sg:classifiers":[
        {
            "category":"Retail",
            "subcategory":"Auto Repair",
            "type":"Services"
        }
    ],
    "sg:phone":"+1 519 624 2322",
    "sg:postcode":"N1T 1C6",
    "sg:province":"ON",
    "sg:tags":[
        "repairing",
        "automobile"
    ],
    "wof:name":"Robertson Automotive Inc",
    "wof:placetype":"venue"
},
  "geometry": {"coordinates":[-80.301529,43.404312],"type":"Point"}
}