{
  "type": "Feature",
  "properties": {
    "addr:full":"Calgary AB T2G 4X4",
    "addr:postcode":"t2g 4x4",
    "iso:country":"CA",
    "sg:city":"Calgary",
    "sg:classifiers":[
        {
            "category":"Wholesale",
            "subcategory":"Machinery & Supplies",
            "type":"Manufacturing & Wholesale Goods"
        }
    ],
    "sg:phone":"+1 403 214 3626",
    "sg:postcode":"T2G 4X4",
    "sg:province":"AB",
    "sg:tags":[
        "pump"
    ],
    "wof:name":"Jbl Petroleum Equipment",
    "wof:placetype":"venue"
},
  "geometry": {"coordinates":[-114.038849,51.013836],"type":"Point"}
}