{
  "type": "Feature",
  "properties": {
    "addr:full":"Delta BC V4K 5B3",
    "addr:postcode":"v4k 5b3",
    "iso:country":"CA",
    "sg:city":"Delta",
    "sg:classifiers":[
        {
            "category":"Education",
            "subcategory":"Special Training",
            "type":"Public Place"
        }
    ],
    "sg:phone":"+1 604 940 8841",
    "sg:postcode":"V4K 5B3",
    "sg:province":"BC",
    "sg:tags":[
        "aircraft",
        "school"
    ],
    "wof:name":"Regency Express Flight Oprtns",
    "wof:placetype":"venue"
},
  "geometry": {"coordinates":[-123.023888,49.082771],"type":"Point"}
}