{
  "type": "Feature",
  "properties": {
    "iso:country":"CA",
    "sg:address":"3575 Boul Saint-Laurent # 217",
    "sg:city":"Montreal",
    "sg:classifiers":[
        {
            "category":"Professional",
            "subcategory":"Advertising",
            "type":"Services"
        }
    ],
    "sg:phone":"+1 514 286 9229",
    "sg:postcode":"H2X 2T7",
    "sg:province":"QC",
    "sg:tags":[
        "publicity"
    ],
    "wof:name":"Publicite Normand Binette Inc",
    "wof:placetype":"venue"
},
  "geometry": {"coordinates":[-73.5719299316,45.51379776],"type":"Point"}
}