{
  "type": "Feature",
  "properties": {
    "addr:full":"Cap-Saint-Ignace QC G0R 1H0",
    "addr:postcode":"g0r 1h0",
    "iso:country":"CA",
    "sg:city":"Cap-Saint-Ignace",
    "sg:classifiers":[
        {
            "category":"Shopping",
            "subcategory":"Pharmacy",
            "type":"Retail Goods"
        }
    ],
    "sg:phone":"+1 418 246 5613",
    "sg:postcode":"G0R 1H0",
    "sg:province":"QC",
    "wof:name":"Pharmacien Jacques Bernier",
    "wof:placetype":"venue"
},
  "geometry": {"coordinates":[-70.45826700000001,47.038303],"type":"Point"}
}