{
  "type": "Feature",
  "properties": {
    "iso:country":"CA",
    "sg:address":"4270 Hastings St",
    "sg:city":"Burnaby",
    "sg:classifiers":[
        {
            "category":"Shopping",
            "subcategory":"Used Merchandise",
            "type":"Retail Goods"
        }
    ],
    "sg:phone":"+1 604 205 7250",
    "sg:postcode":"V5C 2J6",
    "sg:province":"BC",
    "sg:tags":[
        "furniture"
    ],
    "wof:name":"Sajc Used Furniture",
    "wof:placetype":"venue"
},
  "geometry": {"coordinates":[-123.009536743,49.2809104919],"type":"Point"}
}