{
  "type": "Feature",
  "properties": {
    "addr:full":"Peachland BC V0H 1X7",
    "addr:postcode":"v0h 1x7",
    "iso:country":"CA",
    "sg:city":"Peachland",
    "sg:classifiers":[
        {
            "category":"Health Services",
            "subcategory":"Doctor",
            "type":"Services"
        }
    ],
    "sg:phone":"+1 250 767 2215",
    "sg:postcode":"V0H 1X7",
    "sg:province":"BC",
    "sg:tags":[
        "physician",
        "surgeon"
    ],
    "wof:name":"Peachland Medical Ctr",
    "wof:placetype":"venue"
},
  "geometry": {"coordinates":[-119.736214,49.773891],"type":"Point"}
}