{
  "type": "Feature",
  "properties": {
    "addr:full":"4714 1 St SW Calgary AB T2G 0A2",
    "addr:housenumber":"4714 1",
    "addr:postcode":"t2g 0a2",
    "addr:street":"St Sw",
    "iso:country":"CA",
    "sg:address":"4714 1 St SW",
    "sg:city":"Calgary",
    "sg:classifiers":[
        {
            "category":"Professional",
            "subcategory":"Accounting & Tax Preparation",
            "type":"Services"
        }
    ],
    "sg:phone":"+1 403 225 1000",
    "sg:postcode":"T2G 0A2",
    "sg:province":"AB",
    "sg:tags":[
        "accountant"
    ],
    "wof:name":"Maertens-Poole, Robert CA",
    "wof:placetype":"venue"
},
  "geometry": {"coordinates":[-114.06510900000001,51.0107],"type":"Point"}
}