{
  "type": "Feature",
  "properties": {
    "addr:full":"513 Route 820 Baxters Corner NB E2S 2J7",
    "addr:housenumber":"513",
    "addr:postcode":"e2s 2j7",
    "addr:street":"Route 820;Corner",
    "iso:country":"CA",
    "sg:address":"513 Route 820",
    "sg:city":"Baxters Corner",
    "sg:classifiers":[
        {
            "category":"Food & Beverages",
            "subcategory":"Groceries & Convenience Stores",
            "type":"Retail Goods"
        }
    ],
    "sg:phone":"+1 506 696 8828",
    "sg:postcode":"E2S 2J7",
    "sg:province":"NB",
    "sg:tags":[
        "grocer"
    ],
    "wof:name":"Baxter's Corner Convenience",
    "wof:placetype":"venue"
},
  "geometry": {"coordinates":[-65.821136,45.384872],"type":"Point"}
}