{
  "type": "Feature",
  "properties": {
    "addr:full":"3107 Av Des Hotels Sainte-Foy QC G1W 4W5",
    "addr:housenumber":"3107",
    "addr:postcode":"g1w 4w5",
    "addr:street":"Av Des Hotels",
    "iso:country":"CA",
    "sg:address":"3107 Av Des Hotels",
    "sg:city":"Sainte-Foy",
    "sg:classifiers":[
        {
            "category":"Professional",
            "subcategory":"Computer Services",
            "type":"Services"
        }
    ],
    "sg:phone":"+1 418 657 1422",
    "sg:postcode":"G1W 4W5",
    "sg:province":"QC",
    "sg:tags":[
        "repair"
    ],
    "wof:name":"Univers Du Micro",
    "wof:placetype":"venue"
},
  "geometry": {"coordinates":[-71.2959289551,46.7627296448],"type":"Point"}
}