{
  "type": "Feature",
  "properties": {
    "addr:full":"Langley BC V2Y 1M8",
    "addr:postcode":"v2y 1m8",
    "iso:country":"CA",
    "sg:city":"Langley",
    "sg:classifiers":[
        {
            "category":"Professional",
            "subcategory":"Testing Lab",
            "type":"Services"
        }
    ],
    "sg:phone":"+1 604 532 9620",
    "sg:postcode":"V2Y 1M8",
    "sg:province":"BC",
    "sg:tags":[
        "laboratory"
    ],
    "wof:name":"Evolutionary Extractions Inc",
    "wof:placetype":"venue"
},
  "geometry": {"coordinates":[-122.665412903,49.1188545227],"type":"Point"}
}