{
  "type": "Feature",
  "properties": {
    "addr:full":"325 Main St Kentville NS B4N 1K5",
    "addr:housenumber":"325",
    "addr:postcode":"b4n 1k5",
    "addr:street":"Main St",
    "iso:country":"CA",
    "sg:address":"325 Main St",
    "sg:city":"Kentville",
    "sg:classifiers":[
        {
            "category":"Banks & Credit Unions",
            "subcategory":"Investment Brokerage",
            "type":"Services"
        }
    ],
    "sg:phone":"+1 902 678 9200",
    "sg:postcode":"B4N 1K5",
    "sg:province":"NS",
    "wof:name":"Investors Group Financial Svc",
    "wof:placetype":"venue"
},
  "geometry": {"coordinates":[-64.490517,45.075756],"type":"Point"}
}