{
  "type": "Feature",
  "properties": {
    "addr:full":"Nanaimo BC V9T 6C9",
    "addr:postcode":"v9t 6c9",
    "iso:country":"CA",
    "sg:city":"Nanaimo",
    "sg:classifiers":[
        {
            "category":"Home & Garden",
            "subcategory":"Carpets & Floor Coverings",
            "type":"Retail Goods"
        }
    ],
    "sg:phone":"+1 250 756 2555",
    "sg:postcode":"V9T 6C9",
    "sg:province":"BC",
    "sg:tags":[
        "dealer",
        "rug"
    ],
    "wof:name":"Motion Carpets",
    "wof:placetype":"venue"
},
  "geometry": {"coordinates":[-124.034713745,49.2070884705],"type":"Point"}
}