{
  "type": "Feature",
  "properties": {
    "addr:full":"Fleurimont QC J1E 4A8",
    "addr:postcode":"j1e 4a8",
    "iso:country":"CA",
    "sg:city":"Fleurimont",
    "sg:classifiers":[
        {
            "category":"Building & Trades",
            "subcategory":"Plumbing",
            "type":"Services"
        }
    ],
    "sg:phone":"+1 819 565 7990",
    "sg:postcode":"J1E 4A8",
    "sg:province":"QC",
    "sg:tags":[
        "heating",
        "contractor"
    ],
    "wof:name":"Chauffage Marc Braun",
    "wof:placetype":"venue"
},
  "geometry": {"coordinates":[-71.8630142212,45.427028656],"type":"Point"}
}