{
  "type": "Feature",
  "properties": {
    "addr:full":"8710 Rue DE Marseille Montreal QC H1L 1R9",
    "addr:housenumber":"8710",
    "addr:postcode":"h1l 1r9",
    "addr:street":"Rue De Marseille",
    "iso:country":"CA",
    "sg:address":"8710 Rue DE Marseille",
    "sg:city":"Montreal",
    "sg:classifiers":[
        {
            "category":"Social Services",
            "type":"Services"
        }
    ],
    "sg:phone":"+1 514 351 6661",
    "sg:postcode":"H1L 1R9",
    "sg:province":"QC",
    "sg:tags":[
        "crisis",
        "intervention"
    ],
    "wof:name":"L'Appoint",
    "wof:placetype":"venue"
},
  "geometry": {"coordinates":[-73.525932,45.603172],"type":"Point"}
}