{
  "type": "Feature",
  "properties": {
    "iso:country":"CA",
    "sg:city":"Burlington",
    "sg:classifiers":[
        {
            "category":"Professional",
            "subcategory":"Business Services",
            "type":"Services"
        }
    ],
    "sg:phone":"+1 905 639 5442",
    "sg:postcode":"L7R 2E3",
    "sg:province":"ON",
    "sg:tags":[
        "paralegal"
    ],
    "wof:name":"F G Suter & Assoc Inc",
    "wof:placetype":"venue"
},
  "geometry": {"coordinates":[-79.80182647709999,43.344078064],"type":"Point"}
}