{
  "type": "Feature",
  "properties": {
    "addr:full":"24965 Route 2 Kensington PE C0B 1M0",
    "addr:housenumber":"24965",
    "addr:postcode":"c0b 1m0",
    "addr:street":"Route 2",
    "iso:country":"CA",
    "sg:address":"24965 Route 2",
    "sg:city":"Kensington",
    "sg:classifiers":[
        {
            "category":"Autos & Motor Vehicles",
            "subcategory":"Recreational Vehicle Sales",
            "type":"Retail Goods"
        }
    ],
    "sg:phone":"+1 902 836 4622",
    "sg:postcode":"C0B 1M0",
    "sg:province":"PE",
    "wof:name":"Pine Acres Rv",
    "wof:placetype":"venue"
},
  "geometry": {"coordinates":[-63.644119,46.438969],"type":"Point"}
}