{
  "type": "Feature",
  "properties": {
    "addr:full":"58 Railway Ave W Pierson MB R0M 1S0",
    "addr:housenumber":"58",
    "addr:postcode":"r0m 1s0",
    "addr:street":"Railway Ave W",
    "iso:country":"CA",
    "sg:address":"58 Railway Ave W",
    "sg:city":"Pierson",
    "sg:classifiers":[
        {
            "category":"Government",
            "subcategory":"Office",
            "type":"Public Place"
        }
    ],
    "sg:phone":"+1 204 634 2231",
    "sg:postcode":"R0M 1S0",
    "sg:province":"MB",
    "sg:tags":[
        "village"
    ],
    "wof:name":"Edward Rural Municipality",
    "wof:placetype":"venue"
},
  "geometry": {"coordinates":[-101.267303467,49.1780433655],"type":"Point"}
}