{
  "type": "Feature",
  "properties": {
    "iso:country":"CA",
    "sg:city":"Richmond Hill",
    "sg:classifiers":[
        {
            "category":"Taxi",
            "type":"Transportation"
        }
    ],
    "sg:phone":"+1 905 508 1801",
    "sg:postcode":"L4C 9V5",
    "sg:province":"ON",
    "sg:tags":[
        "taxicab"
    ],
    "wof:name":"Kids Kabbie",
    "wof:placetype":"venue"
},
  "geometry": {"coordinates":[-79.427513,43.873257],"type":"Point"}
}