{
  "type": "Feature",
  "properties": {
    "addr:full":"7700 Pine Valley Dr Woodbridge ON L4L 2X4",
    "addr:housenumber":"7700",
    "addr:postcode":"l4l 2x4",
    "addr:street":"Pine Valley Dr",
    "iso:country":"CA",
    "sg:address":"7700 Pine Valley Dr",
    "sg:city":"Woodbridge",
    "sg:classifiers":[
        {
            "category":"Shopping",
            "subcategory":"Pharmacy",
            "type":"Retail Goods"
        }
    ],
    "sg:phone":"+1 905 851 2121",
    "sg:postcode":"L4L 2X4",
    "sg:province":"ON",
    "wof:name":"Pine Valley Pharmacy",
    "wof:placetype":"venue"
},
  "geometry": {"coordinates":[-79.57287599999999,43.782433],"type":"Point"}
}