{
  "type": "Feature",
  "properties": {
    "addr:full":"Saint-Alphonse-DE-Caplan QC G0C 2V0",
    "addr:postcode":"g0c 2v0",
    "iso:country":"CA",
    "sg:city":"Saint-Alphonse-DE-Caplan",
    "sg:classifiers":[
        {
            "category":"Manufacturing",
            "subcategory":"Lumber",
            "type":"Manufacturing & Wholesale Goods"
        }
    ],
    "sg:phone":"+1 418 388 5216",
    "sg:postcode":"G0C 2V0",
    "sg:province":"QC",
    "sg:tags":[
        "sawmill"
    ],
    "wof:name":"Rosairo Poirier Inc",
    "wof:placetype":"venue"
},
  "geometry": {"coordinates":[-65.67924499999999,48.101181],"type":"Point"}
}