{
  "type": "Feature",
  "properties": {
    "addr:full":"1119 Renfrew St Gull Lake SK S0N 1A0",
    "addr:housenumber":"1119",
    "addr:postcode":"s0n 1a0",
    "addr:street":"Renfrew St",
    "iso:country":"CA",
    "sg:address":"1119 Renfrew St",
    "sg:city":"Gull Lake",
    "sg:classifiers":[
        {
            "category":"Wholesale",
            "subcategory":"Machinery & Supplies",
            "type":"Manufacturing & Wholesale Goods"
        }
    ],
    "sg:phone":"+1 306 672 3470",
    "sg:postcode":"S0N 1A0",
    "sg:province":"SK",
    "sg:tags":[
        "equipment",
        "oil",
        "well"
    ],
    "wof:name":"Midfield Supply Ltd",
    "wof:placetype":"venue"
},
  "geometry": {"coordinates":[-108.483924866,50.0979690552],"type":"Point"}
}