{
  "type": "Feature",
  "properties": {
    "addr:full":"Toronto ON M6C 2K5",
    "addr:postcode":"m6c 2k5",
    "iso:country":"CA",
    "sg:city":"Toronto",
    "sg:classifiers":[
        {
            "category":"Personal",
            "subcategory":"Barber",
            "type":"Services"
        }
    ],
    "sg:phone":"+1 416 651 7056",
    "sg:postcode":"M6C 2K5",
    "sg:province":"ON",
    "wof:name":"Sam's Barber Shop & Hair Place",
    "wof:placetype":"venue"
},
  "geometry": {"coordinates":[-79.4193496704,43.6830406189],"type":"Point"}
}