{
  "type": "Feature",
  "properties": {
    "addr:full":"1210 Rue Sainte-Catherine E Montreal QC H2L 2G9",
    "addr:housenumber":"1210",
    "addr:postcode":"h2l 2g9",
    "addr:street":"Rue Sainte-Catherine E",
    "iso:country":"CA",
    "sg:address":"1210 Rue Sainte-Catherine E",
    "sg:city":"Montreal",
    "sg:classifiers":[
        {
            "category":"Shopping",
            "subcategory":"Florist",
            "type":"Retail Goods"
        }
    ],
    "sg:phone":"+1 514 529 2029",
    "sg:postcode":"H2L 2G9",
    "sg:province":"QC",
    "wof:name":"Image Innee",
    "wof:placetype":"venue"
},
  "geometry": {"coordinates":[-73.55596160890001,45.5184288025],"type":"Point"}
}