{
  "type": "Feature",
  "properties": {
    "addr:full":"1 Adelaide St E Toronto ON M5C 2V9",
    "addr:housenumber":"1",
    "addr:postcode":"m5c 2v9",
    "addr:street":"Adelaide St E",
    "iso:country":"CA",
    "sg:address":"1 Adelaide St E",
    "sg:city":"Toronto",
    "sg:classifiers":[
        {
            "category":"Mining & Drilling",
            "type":"Manufacturing & Wholesale Goods"
        }
    ],
    "sg:phone":"+1 416 350 3780",
    "sg:postcode":"M5C 2V9",
    "sg:province":"ON",
    "sg:tags":[
        "company"
    ],
    "wof:name":"Pangea Goldfields Inc",
    "wof:placetype":"venue"
},
  "geometry": {"coordinates":[-79.37823486329999,43.6503601074],"type":"Point"}
}