{
  "type": "Feature",
  "properties": {
    "addr:full":"2155 Rue DE LA Montagne Montreal QC H3G 1Z8",
    "addr:housenumber":"2155",
    "addr:postcode":"h3g 1z8",
    "addr:street":"Rue De La Montagne",
    "iso:country":"CA",
    "sg:address":"2155 Rue DE LA Montagne",
    "sg:city":"Montreal",
    "sg:classifiers":[
        {
            "category":"Restaurant",
            "type":"Food & Drink"
        }
    ],
    "sg:phone":"+1 514 844 9292",
    "sg:postcode":"H3G 1Z8",
    "sg:province":"QC",
    "wof:name":"Restaurant Toyo Grillade A LA",
    "wof:placetype":"venue"
},
  "geometry": {"coordinates":[-73.57769,45.499359],"type":"Point"}
}