{
  "type": "Feature",
  "properties": {
    "addr:full":"1930 Rue Principale Saint-Faustin-Lac-Carre QC J0T 1J1",
    "addr:housenumber":"1930",
    "addr:postcode":"j0t 1j1",
    "addr:street":"Rue Principale",
    "iso:country":"CA",
    "sg:address":"1930 Rue Principale",
    "sg:city":"Saint-Faustin-Lac-Carre",
    "sg:classifiers":[
        {
            "category":"Restaurant",
            "type":"Food & Drink"
        }
    ],
    "sg:phone":"+1 819 688 6004",
    "sg:postcode":"J0T 1J1",
    "sg:province":"QC",
    "wof:name":"Restaurant DE LA Place Enr",
    "wof:placetype":"venue"
},
  "geometry": {"coordinates":[-74.472984314,46.1312217712],"type":"Point"}
}