{
  "type": "Feature",
  "properties": {
    "iso:country":"CA",
    "sg:address":"2000 Rue Victoria #C",
    "sg:city":"Greenfield Park",
    "sg:classifiers":[
        {
            "category":"Personal",
            "subcategory":"Beauty Salon",
            "type":"Services"
        }
    ],
    "sg:phone":"+1 450 672 1153",
    "sg:postcode":"J4V 1M6",
    "sg:province":"QC",
    "wof:name":"Douceur Angevine",
    "wof:placetype":"venue"
},
  "geometry": {"coordinates":[-73.47705078120001,45.478729248],"type":"Point"}
}