{
  "type": "Feature",
  "properties": {
    "addr:full":"68 Jaimie Rd Thornhill ON L4J 6A3",
    "addr:housenumber":"68",
    "addr:postcode":"l4j 6a3",
    "addr:street":"Jaimie Rd",
    "iso:country":"CA",
    "sg:address":"68 Jaimie Rd",
    "sg:city":"Thornhill",
    "sg:classifiers":[
        {
            "category":"Building & Trades",
            "subcategory":"Electrical",
            "type":"Services"
        }
    ],
    "sg:phone":"+1 905 669 4584",
    "sg:postcode":"L4J 6A3",
    "sg:province":"ON",
    "sg:tags":[
        "electric",
        "contractor"
    ],
    "wof:name":"Kva Electrical Systems Ltd",
    "wof:placetype":"venue"
},
  "geometry": {"coordinates":[-79.472618103,43.800567627],"type":"Point"}
}