{
  "type": "Feature",
  "properties": {
    "addr:full":"4230 Fraser St Vancouver BC V5V 4G2",
    "addr:housenumber":"4230",
    "addr:postcode":"v5v 4g2",
    "addr:street":"Fraser St",
    "iso:country":"CA",
    "sg:address":"4230 Fraser St",
    "sg:city":"Vancouver",
    "sg:classifiers":[
        {
            "category":"Personal",
            "subcategory":"Beauty Salon",
            "type":"Services"
        }
    ],
    "sg:phone":"+1 604 879 1525",
    "sg:postcode":"V5V 4G2",
    "sg:province":"BC",
    "wof:name":"Dave Hair Salon",
    "wof:placetype":"venue"
},
  "geometry": {"coordinates":[-123.08989,49.247295],"type":"Point"}
}