{
  "type": "Feature",
  "properties": {
    "addr:full":"145 Douglasfield Rd Miramichi NB E1N 4S4",
    "addr:housenumber":"145",
    "addr:postcode":"e1n 4s4",
    "addr:street":"Douglasfield Rd",
    "iso:country":"CA",
    "sg:address":"145 Douglasfield Rd",
    "sg:city":"Miramichi",
    "sg:classifiers":[
        {
            "category":"Building & Trades",
            "subcategory":"Plumbing",
            "type":"Services"
        }
    ],
    "sg:phone":"+1 506 622 9005",
    "sg:postcode":"E1N 4S4",
    "sg:province":"NB",
    "sg:tags":[
        "conditioning",
        "air",
        "system",
        "contractor"
    ],
    "wof:name":"Northumberland Mechanical",
    "wof:placetype":"venue"
},
  "geometry": {"coordinates":[-65.5017623901,46.994102478],"type":"Point"}
}