{
  "type": "Feature",
  "properties": {
    "addr:full":"4315 27 St Vernon BC V1T 4Y5",
    "addr:housenumber":"4315",
    "addr:postcode":"v1t 4y5",
    "addr:street":"27 St",
    "iso:country":"CA",
    "sg:address":"4315 27 St",
    "sg:city":"Vernon",
    "sg:classifiers":[
        {
            "category":"Personal",
            "subcategory":"Beauty Salon",
            "type":"Services"
        }
    ],
    "sg:phone":"+1 250 545 6962",
    "sg:postcode":"V1T 4Y5",
    "sg:province":"BC",
    "sg:tags":[
        "manicuring"
    ],
    "wof:name":"Expert Nails",
    "wof:placetype":"venue"
},
  "geometry": {"coordinates":[-119.266616821,50.275062561],"type":"Point"}
}