{
  "type": "Feature",
  "properties": {
    "iso:country":"CA",
    "sg:city":"Campbell River",
    "sg:classifiers":[
        {
            "category":"Retail",
            "subcategory":"Animal Services",
            "type":"Services"
        }
    ],
    "sg:phone":"+1 250 286 0900",
    "sg:postcode":"V9W 6R4",
    "sg:province":"BC",
    "sg:tags":[
        "pet",
        "grooming",
        "washing"
    ],
    "wof:name":"Grooming Shoppe",
    "wof:placetype":"venue"
},
  "geometry": {"coordinates":[-125.247741699,49.9982376099],"type":"Point"}
}