{
  "type": "Feature",
  "properties": {
    "addr:full":"268 Codrington St Barrie ON L4M 1S5",
    "addr:housenumber":"268",
    "addr:postcode":"l4m 1s5",
    "addr:street":"Codrington St",
    "iso:country":"CA",
    "sg:address":"268 Codrington St",
    "sg:city":"Barrie",
    "sg:classifiers":[
        {
            "category":"Building & Trades",
            "subcategory":"Electrical",
            "type":"Services"
        }
    ],
    "sg:phone":"+1 705 726 8832",
    "sg:postcode":"L4M 1S5",
    "sg:province":"ON",
    "sg:tags":[
        "electric",
        "contractor"
    ],
    "wof:name":"L R Parry Electric",
    "wof:placetype":"venue"
},
  "geometry": {"coordinates":[-79.6716461182,44.3971748352],"type":"Point"}
}