{
  "type": "Feature",
  "properties": {
    "addr:full":"3 Parklane Way Strathmore AB T1P 1N6",
    "addr:housenumber":"3",
    "addr:postcode":"t1p 1n6",
    "addr:street":"Parklane Way",
    "iso:country":"CA",
    "sg:address":"3 Parklane Way",
    "sg:city":"Strathmore",
    "sg:classifiers":[
        {
            "category":"Freight",
            "type":"Transportation"
        }
    ],
    "sg:phone":"+1 403 934 6722",
    "sg:postcode":"T1P 1N6",
    "sg:province":"AB",
    "sg:tags":[
        "courier"
    ],
    "wof:name":"Greyhound Canada",
    "wof:placetype":"venue"
},
  "geometry": {"coordinates":[-113.391777,51.04509],"type":"Point"}
}