{
  "type": "Feature",
  "properties": {
    "addr:full":"3883 Buckshot Lake Rd Plevna ON K0H 2M0",
    "addr:housenumber":"3883",
    "addr:postcode":"k0h 2m0",
    "addr:street":"Buckshot Lake Rd",
    "iso:country":"CA",
    "sg:address":"3883 Buckshot Lake Rd",
    "sg:city":"Plevna",
    "sg:classifiers":[
        {
            "category":"Travel",
            "subcategory":"Hotels & Motels",
            "type":"Entertainment"
        }
    ],
    "sg:phone":"+1 613 479 2215",
    "sg:postcode":"K0H 2M0",
    "sg:province":"ON",
    "sg:tags":[
        "cottage",
        "cabin"
    ],
    "wof:name":"Birch Lodge",
    "wof:placetype":"venue"
},
  "geometry": {"coordinates":[-76.981842,44.96542],"type":"Point"}
}