{
  "type": "Feature",
  "properties": {
    "addr:full":"Chapleau ON P0M 1K0",
    "addr:postcode":"p0m 1k0",
    "iso:country":"CA",
    "sg:city":"Chapleau",
    "sg:classifiers":[
        {
            "category":"Travel",
            "subcategory":"Hotels & Motels",
            "type":"Entertainment"
        }
    ],
    "sg:phone":"+1 705 864 0770",
    "sg:postcode":"P0M 1K0",
    "sg:province":"ON",
    "wof:name":"Blue Heron Inn",
    "wof:placetype":"venue"
},
  "geometry": {"coordinates":[-83.4048995972,47.8424758911],"type":"Point"}
}