{
  "type": "Feature",
  "properties": {
    "iso:country":"CA",
    "sg:address":"176 Oxford St E",
    "sg:city":"London",
    "sg:classifiers":[
        {
            "category":"Personal",
            "subcategory":"Beauty Salon",
            "type":"Services"
        }
    ],
    "sg:phone":"+1 519 433 3860",
    "sg:postcode":"N6A 1T6",
    "sg:province":"ON",
    "wof:name":"Skintreet",
    "wof:placetype":"venue"
},
  "geometry": {"coordinates":[-81.255135,42.995041],"type":"Point"}
}