{
  "type": "Feature",
  "properties": {
    "addr:full":"5764 Whard Rd Sechelt BC V0N 3A0",
    "addr:housenumber":"5764",
    "addr:postcode":"v0n 3a0",
    "addr:street":"Whard Rd",
    "iso:country":"CA",
    "sg:address":"5764 Whard Rd",
    "sg:city":"Sechelt",
    "sg:classifiers":[
        {
            "category":"Bars & Pubs",
            "type":"Food & Drink"
        }
    ],
    "sg:phone":"+1 604 885 9494",
    "sg:postcode":"V0N 3A0",
    "sg:province":"BC",
    "wof:name":"Lighthouse Marine Pub",
    "wof:placetype":"venue"
},
  "geometry": {"coordinates":[-123.756783,49.480339],"type":"Point"}
}