{
  "type": "Feature",
  "properties": {
    "iso:country":"CA",
    "sg:address":"5715 Malpass Rd",
    "sg:city":"Nanaimo",
    "sg:classifiers":[
        {
            "category":"Health Services",
            "subcategory":"Clinic",
            "type":"Services"
        }
    ],
    "sg:phone":"+1 250 758 3902",
    "sg:postcode":"V9T 2N3",
    "sg:province":"BC",
    "sg:tags":[
        "agency",
        "welfare"
    ],
    "wof:name":"Kidney Foundation of Canada",
    "wof:placetype":"venue"
},
  "geometry": {"coordinates":[-124.041107178,49.2204246521],"type":"Point"}
}