{
  "type": "Feature",
  "properties": {
    "iso:country":"CA",
    "sg:address":"132 Laurier Dr NW",
    "sg:city":"Edmonton",
    "sg:classifiers":[
        {
            "category":"Building & Trades",
            "subcategory":"Construction",
            "type":"Services"
        }
    ],
    "sg:phone":"+1 780 483 1589",
    "sg:postcode":"T5R 5P8",
    "sg:province":"AB",
    "sg:tags":[
        "general",
        "contractor"
    ],
    "wof:name":"Westhill Construction Ltd",
    "wof:placetype":"venue"
},
  "geometry": {"coordinates":[-113.57006072999999,53.512298584],"type":"Point"}
}