{
  "type": "Feature",
  "properties": {
    "addr:full":"2760 1E Ave Quebec QC G1L 3N8",
    "addr:housenumber":"2760",
    "addr:postcode":"g1l 3n8",
    "addr:street":"1E Ave",
    "iso:country":"CA",
    "sg:address":"2760 1E Ave",
    "sg:city":"Quebec",
    "sg:classifiers":[
        {
            "category":"Retail",
            "subcategory":"Auto Repair",
            "type":"Services"
        }
    ],
    "sg:phone":"+1 418 626 1025",
    "sg:postcode":"G1L 3N8",
    "sg:province":"QC",
    "sg:tags":[
        "transmission",
        "automobile",
        "repairing"
    ],
    "wof:name":"Transmissions Automatiques",
    "wof:placetype":"venue"
},
  "geometry": {"coordinates":[-71.243858,46.836861],"type":"Point"}
}