{
  "type": "Feature",
  "properties": {
    "addr:full":"Morpeth ON N0P 1X0",
    "addr:postcode":"n0p 1x0",
    "iso:country":"CA",
    "sg:city":"Morpeth",
    "sg:classifiers":[
        {
            "category":"Travel",
            "subcategory":"Campground",
            "type":"Entertainment"
        }
    ],
    "sg:phone":"+1 519 674 5516",
    "sg:postcode":"N0P 1X0",
    "sg:province":"ON",
    "wof:name":"Wildwood By the Lake Rondeau",
    "wof:placetype":"venue"
},
  "geometry": {"coordinates":[-81.8433914185,42.393283844],"type":"Point"}
}