{
  "type": "Feature",
  "properties": {
    "addr:full":"Sayabec QC G0J 3K0",
    "addr:postcode":"g0j 3k0",
    "iso:country":"CA",
    "sg:city":"Sayabec",
    "sg:classifiers":[
        {
            "category":"Manufacturing",
            "subcategory":"Tools & Machinery",
            "type":"Manufacturing & Wholesale Goods"
        }
    ],
    "sg:phone":"+1 418 536 5000",
    "sg:postcode":"G0J 3K0",
    "sg:province":"QC",
    "sg:tags":[
        "equipment",
        "system",
        "automation"
    ],
    "wof:name":"Automation D'Amours Inc",
    "wof:placetype":"venue"
},
  "geometry": {"coordinates":[-67.64259300000001,48.564453],"type":"Point"}
}