{
  "type": "Feature",
  "properties": {
    "addr:full":"1809 Douglas St Victoria BC V8T 4K5",
    "addr:housenumber":"1809",
    "addr:postcode":"v8t 4k5",
    "addr:street":"Douglas St",
    "iso:country":"CA",
    "sg:address":"1809 Douglas St",
    "sg:city":"Victoria",
    "sg:classifiers":[
        {
            "category":"Real Estate",
            "subcategory":"Real Estate Agent",
            "type":"Services"
        }
    ],
    "sg:phone":"+1 250 384 7663",
    "sg:postcode":"V8T 4K5",
    "sg:province":"BC",
    "sg:tags":[
        "management"
    ],
    "wof:name":"Tpm Management Ltd",
    "wof:placetype":"venue"
},
  "geometry": {"coordinates":[-123.36431899999999,48.430382],"type":"Point"}
}