{
  "type": "Feature",
  "properties": {
    "addr:full":"540 Rue Lucien-L'Allier Montreal QC H3C 4N9",
    "addr:housenumber":"540",
    "addr:postcode":"h3c 4n9",
    "addr:street":"Rue Lucien-L'Allier",
    "iso:country":"CA",
    "sg:address":"540 Rue Lucien-L'Allier",
    "sg:city":"Montreal",
    "sg:classifiers":[
        {
            "category":"Manufacturing",
            "subcategory":"Printing",
            "type":"Manufacturing & Wholesale Goods"
        }
    ],
    "sg:phone":"+1 514 932 1246",
    "sg:postcode":"H3C 4N9",
    "sg:province":"QC",
    "sg:tags":[
        "printer"
    ],
    "wof:name":"Seville Printing & Graphics",
    "wof:placetype":"venue"
},
  "geometry": {"coordinates":[-73.554558,45.502434],"type":"Point"}
}