{
  "type": "Feature",
  "properties": {
    "addr:full":"7973 River Rd Delta BC V4G 1B4",
    "addr:housenumber":"7973",
    "addr:postcode":"v4g 1b4",
    "addr:street":"River Rd",
    "iso:country":"CA",
    "sg:address":"7973 River Rd",
    "sg:city":"Delta",
    "sg:classifiers":[
        {
            "category":"Retail",
            "subcategory":"Auto Rental",
            "type":"Services"
        }
    ],
    "sg:phone":"+1 604 946 3696",
    "sg:postcode":"V4G 1B4",
    "sg:province":"BC",
    "sg:tags":[
        "recreational",
        "leasing",
        "vehicle"
    ],
    "wof:name":"Ambassador Motor Home & Rec",
    "wof:placetype":"venue"
},
  "geometry": {"coordinates":[-123.003113,49.145691],"type":"Point"}
}