{
  "type": "Feature",
  "properties": {
    "addr:full":"50 Rue Lorne Granby QC J2G 4W2",
    "addr:housenumber":"50",
    "addr:postcode":"j2g 4w2",
    "addr:street":"Rue Lorne",
    "iso:country":"CA",
    "sg:address":"50 Rue Lorne",
    "sg:city":"Granby",
    "sg:classifiers":[
        {
            "category":"Education",
            "subcategory":"School",
            "type":"Public Place"
        }
    ],
    "sg:phone":"+1 450 372 6058",
    "sg:postcode":"J2G 4W2",
    "sg:province":"QC",
    "wof:name":"Parkview School",
    "wof:placetype":"venue"
},
  "geometry": {"coordinates":[-72.719696,45.401512],"type":"Point"}
}