{
  "type": "Feature",
  "properties": {
    "addr:full":"3005 Temple Dr Windsor ON N8W 5E5",
    "addr:housenumber":"3005",
    "addr:postcode":"n8w 5e5",
    "addr:street":"Temple Dr",
    "iso:country":"CA",
    "sg:address":"3005 Temple Dr",
    "sg:city":"Windsor",
    "sg:classifiers":[
        {
            "category":"Organizations",
            "subcategory":"Religious Organization",
            "type":"Services"
        }
    ],
    "sg:phone":"+1 519 948 7055",
    "sg:postcode":"N8W 5E5",
    "sg:province":"ON",
    "sg:tags":[
        "church"
    ],
    "wof:name":"Parkwood Gospel Temple",
    "wof:placetype":"venue"
},
  "geometry": {"coordinates":[-82.974197,42.287636],"type":"Point"}
}