{
  "type": "Feature",
  "properties": {
    "addr:full":"1535 Park St Regina SK S4N 2E9",
    "addr:housenumber":"1535",
    "addr:postcode":"s4n 2e9",
    "addr:street":"Park St",
    "iso:country":"CA",
    "sg:address":"1535 Park St",
    "sg:city":"Regina",
    "sg:classifiers":[
        {
            "category":"Retail",
            "subcategory":"Auto Rental",
            "type":"Services"
        }
    ],
    "sg:phone":"+1 306 569 8801",
    "sg:postcode":"S4N 2E9",
    "sg:province":"SK",
    "sg:tags":[
        "renting",
        "truck",
        "leasing"
    ],
    "wof:name":"U-Haul CO Ltd",
    "wof:placetype":"venue"
},
  "geometry": {"coordinates":[-104.572044373,50.4545135498],"type":"Point"}
}