{
  "type": "Feature",
  "properties": {
    "addr:full":"1172 Rue Saint-Gregoire Farnham QC J2N 1R6",
    "addr:housenumber":"1172",
    "addr:postcode":"j2n 1r6",
    "addr:street":"Rue Saint-Gregoire",
    "iso:country":"CA",
    "sg:address":"1172 Rue Saint-Gregoire",
    "sg:city":"Farnham",
    "sg:classifiers":[
        {
            "category":"Personal",
            "subcategory":"Beauty Salon",
            "type":"Services"
        }
    ],
    "sg:phone":"+1 450 293 2913",
    "sg:postcode":"J2N 1R6",
    "sg:province":"QC",
    "wof:name":"Salon Entete Enr",
    "wof:placetype":"venue"
},
  "geometry": {"coordinates":[-72.997108,45.282784],"type":"Point"}
}