{
  "type": "Feature",
  "properties": {
    "addr:full":"Front St Dawson YT Y0B 1G0",
    "addr:postcode":"y0b 1g0",
    "addr:street":"Front St",
    "iso:country":"CA",
    "sg:address":"Front St",
    "sg:city":"Dawson",
    "sg:classifiers":[
        {
            "category":"Travel",
            "subcategory":"Travel Agent",
            "type":"Entertainment"
        }
    ],
    "sg:phone":"+1 867 993 6167",
    "sg:postcode":"Y0B 1G0",
    "sg:province":"YT",
    "sg:tags":[
        "information",
        "tourist"
    ],
    "wof:name":"Northwest Territories Visitors",
    "wof:placetype":"venue"
},
  "geometry": {"coordinates":[-139.43615700000001,64.06201900000001],"type":"Point"}
}