{
  "type": "Feature",
  "properties": {
    "addr:full":"5144 Rue Frontenac Lac-Megantic QC G6B 1H3",
    "addr:housenumber":"5144",
    "addr:postcode":"g6b 1h3",
    "addr:street":"Rue Frontenac Lac-Megantic",
    "iso:country":"CA",
    "sg:address":"5144 Rue Frontenac",
    "sg:city":"Lac-Megantic",
    "sg:classifiers":[
        {
            "category":"Cinema",
            "subcategory":"Movie Rental",
            "type":"Entertainment"
        }
    ],
    "sg:phone":"+1 819 583 0660",
    "sg:postcode":"G6B 1H3",
    "sg:province":"QC",
    "sg:tags":[
        "leasing",
        "video",
        "disc",
        "tape"
    ],
    "wof:name":"Superclub Videotron",
    "wof:placetype":"venue"
},
  "geometry": {"coordinates":[-70.883904,45.576885],"type":"Point"}
}