{
  "type": "Feature",
  "properties": {
    "addr:full":"50 Main St E Grimsby ON L3M 1N1",
    "addr:housenumber":"50",
    "addr:postcode":"l3m 1n1",
    "addr:street":"Main St E",
    "iso:country":"CA",
    "sg:address":"50 Main St E",
    "sg:city":"Grimsby",
    "sg:classifiers":[
        {
            "category":"Retail",
            "subcategory":"Auto Repair",
            "type":"Services"
        }
    ],
    "sg:phone":"+1 905 945 2823",
    "sg:postcode":"L3M 1N1",
    "sg:province":"ON",
    "sg:tags":[
        "wrecker"
    ],
    "wof:name":"Clausen's Towing",
    "wof:placetype":"venue"
},
  "geometry": {"coordinates":[-79.5585098267,43.1915931702],"type":"Point"}
}