{
  "type": "Feature",
  "properties": {
    "addr:full":"Ferryland St E St. John's NL A1E 5Y7",
    "addr:postcode":"a1e 5y7",
    "addr:street":"Ferryland St E St.",
    "iso:country":"CA",
    "sg:address":"Ferryland St E",
    "sg:city":"St. John's",
    "sg:classifiers":[
        {
            "category":"Organizations",
            "subcategory":"Religious Organization",
            "type":"Services"
        }
    ],
    "sg:phone":"+1 709 368 2601",
    "sg:postcode":"A1E 5Y7",
    "sg:province":"NL",
    "sg:tags":[
        "church"
    ],
    "wof:name":"Church of Jesus Christ-Lds",
    "wof:placetype":"venue"
},
  "geometry": {"coordinates":[-52.759769,47.531418],"type":"Point"}
}