{
  "type": "Feature",
  "properties": {
    "addr:full":"311 Valleymede Dr Richmond Hill ON L4B 2E1",
    "addr:housenumber":"311",
    "addr:postcode":"l4b 2e1",
    "addr:street":"Valleymede Dr",
    "iso:country":"CA",
    "sg:address":"311 Valleymede Dr",
    "sg:city":"Richmond Hill",
    "sg:classifiers":[
        {
            "category":"Arena",
            "subcategory":"Sports Club",
            "type":"Entertainment"
        }
    ],
    "sg:phone":"+1 905 771 8570",
    "sg:postcode":"L4B 2E1",
    "sg:province":"ON",
    "sg:tags":[
        "athletic",
        "fields",
        "stadium",
        "government"
    ],
    "wof:name":"Ed Sackfield Arena",
    "wof:placetype":"venue"
},
  "geometry": {"coordinates":[-79.399086,43.857132],"type":"Point"}
}