{
  "type": "Feature",
  "properties": {
    "addr:full":"201 Brookview Crt Ancaster ON L9G 1J5",
    "addr:housenumber":"201",
    "addr:postcode":"l9g 1j5",
    "addr:street":"Brookview Crt",
    "iso:country":"CA",
    "sg:address":"201 Brookview Crt",
    "sg:city":"Ancaster",
    "sg:classifiers":[
        {
            "category":"Building & Trades",
            "subcategory":"Construction",
            "type":"Services"
        }
    ],
    "sg:phone":"+1 905 648 7242",
    "sg:postcode":"L9G 1J5",
    "sg:province":"ON",
    "sg:tags":[
        "designer",
        "dealer",
        "pool",
        "swimming"
    ],
    "wof:name":"Coombs Pool Svc",
    "wof:placetype":"venue"
},
  "geometry": {"coordinates":[-80.00018300000001,43.225224],"type":"Point"}
}