{
  "type": "Feature",
  "properties": {
    "addr:full":"Vernon BC V1T 2C1",
    "addr:postcode":"v1t 2c1",
    "iso:country":"CA",
    "sg:city":"Vernon",
    "sg:classifiers":[
        {
            "category":"Shopping",
            "subcategory":"Bicycles & Sporting Goods",
            "type":"Retail Goods"
        }
    ],
    "sg:phone":"+1 250 558 1088",
    "sg:postcode":"V1T 2C1",
    "sg:province":"BC",
    "sg:tags":[
        "equipment",
        "exercise"
    ],
    "wof:name":"Starting Block",
    "wof:placetype":"venue"
},
  "geometry": {"coordinates":[-119.273803711,50.2656784058],"type":"Point"}
}