{
  "type": "Feature",
  "properties": {
    "addr:full":"Stony Plain AB T7Z 2L6",
    "addr:postcode":"t7z 2l6",
    "iso:country":"CA",
    "sg:city":"Stony Plain",
    "sg:classifiers":[
        {
            "category":"Restaurant",
            "type":"Food & Drink"
        }
    ],
    "sg:phone":"+1 780 963 6635",
    "sg:postcode":"T7Z 2L6",
    "sg:province":"AB",
    "sg:tags":[
        "shop",
        "coffee"
    ],
    "wof:name":"Espresso Station Inc",
    "wof:placetype":"venue"
},
  "geometry": {"coordinates":[-113.999596,53.531773],"type":"Point"}
}