{
  "type": "Feature",
  "properties": {
    "addr:full":"500 Gertrude Ave Winnipeg MB R3L 0M8",
    "addr:housenumber":"500",
    "addr:postcode":"r3l 0m8",
    "addr:street":"Gertrude Ave",
    "iso:country":"CA",
    "sg:address":"500 Gertrude Ave",
    "sg:city":"Winnipeg",
    "sg:classifiers":[
        {
            "category":"Education",
            "subcategory":"School",
            "type":"Public Place"
        }
    ],
    "sg:phone":"+1 204 475 4767",
    "sg:postcode":"R3L 0M8",
    "sg:province":"MB",
    "wof:name":"Gladstone School",
    "wof:placetype":"venue"
},
  "geometry": {"coordinates":[-97.1452865601,49.8753356934],"type":"Point"}
}