{
  "type": "Feature",
  "properties": {
    "addr:full":"Prince George BC V2L 2J2",
    "addr:postcode":"v2l 2j2",
    "iso:country":"CA",
    "sg:city":"Prince George",
    "sg:classifiers":[
        {
            "category":"Professional",
            "subcategory":"Accounting & Tax Preparation",
            "type":"Services"
        }
    ],
    "sg:phone":"+1 250 564 2014",
    "sg:postcode":"V2L 2J2",
    "sg:province":"BC",
    "sg:tags":[
        "accountant"
    ],
    "wof:name":"Terlesky Braithwaite Janzen",
    "wof:placetype":"venue"
},
  "geometry": {"coordinates":[-122.74806213399999,53.9189414978],"type":"Point"}
}