{
  "type": "Feature",
  "properties": {
    "addr:full":"48 Hotel DE Ville Tingwick QC J0A 1L0",
    "addr:housenumber":"48",
    "addr:postcode":"j0a 1l0",
    "addr:street":"De Ville",
    "iso:country":"CA",
    "sg:address":"48 Hotel DE Ville",
    "sg:city":"Tingwick",
    "sg:classifiers":[
        {
            "category":"Government",
            "subcategory":"Office",
            "type":"Public Place"
        }
    ],
    "sg:phone":"+1 819 359 2454",
    "sg:postcode":"J0A 1L0",
    "sg:province":"QC",
    "sg:tags":[
        "village"
    ],
    "wof:name":"Tingwick Municipalite",
    "wof:placetype":"venue"
},
  "geometry": {"coordinates":[-71.940804,45.878944],"type":"Point"}
}