{
  "type": "Feature",
  "properties": {
    "addr:full":"115 50th St Edson AB T7E 1T7",
    "addr:housenumber":"115",
    "addr:postcode":"t7e 1t7",
    "addr:street":"50Th St",
    "iso:country":"CA",
    "sg:address":"115 50th St",
    "sg:city":"Edson",
    "sg:classifiers":[
        {
            "category":"Shopping",
            "subcategory":"Florist",
            "type":"Retail Goods"
        }
    ],
    "sg:phone":"+1 780 723 5050",
    "sg:postcode":"T7E 1T7",
    "sg:province":"AB",
    "wof:name":"Yellowhead Florists Ltd",
    "wof:placetype":"venue"
},
  "geometry": {"coordinates":[-116.42980957,53.5807952881],"type":"Point"}
}