{
  "type": "Feature",
  "properties": {
    "addr:full":"1376 Caserta Pl Orleans ON K4A 3B9",
    "addr:housenumber":"1376",
    "addr:postcode":"k4a 3b9",
    "addr:street":"Caserta Pl",
    "iso:country":"CA",
    "sg:address":"1376 Caserta Pl",
    "sg:city":"Orleans",
    "sg:classifiers":[
        {
            "category":"Restaurant",
            "type":"Food & Drink"
        }
    ],
    "sg:phone":"+1 613 837 9237",
    "sg:postcode":"K4A 3B9",
    "sg:province":"ON",
    "sg:tags":[
        "management"
    ],
    "wof:name":"Kennell & Assoc",
    "wof:placetype":"venue"
},
  "geometry": {"coordinates":[-75.48155975340001,45.4864730835],"type":"Point"}
}