{
  "type": "Feature",
  "properties": {
    "addr:full":"29 Rue Saint-Pierre Saint-Constant QC J5A 1B8",
    "addr:housenumber":"29",
    "addr:postcode":"j5a 1b8",
    "addr:street":"Rue Saint-Pierre",
    "iso:country":"CA",
    "sg:address":"29 Rue Saint-Pierre",
    "sg:city":"Saint-Constant",
    "sg:classifiers":[
        {
            "category":"Manufacturing",
            "subcategory":"Motor Vehicles & Parts",
            "type":"Manufacturing & Wholesale Goods"
        }
    ],
    "sg:phone":"+1 450 635 1526",
    "sg:postcode":"J5A 1B8",
    "sg:province":"QC",
    "sg:tags":[
        "automobile",
        "supply"
    ],
    "wof:name":"Auto Prescription",
    "wof:placetype":"venue"
},
  "geometry": {"coordinates":[-73.5597457886,45.3834991455],"type":"Point"}
}