{
  "type": "Feature",
  "properties": {
    "addr:full":"Henribourg SK S0J 1C0",
    "addr:postcode":"s0j 1c0",
    "addr:street":"Henribourg",
    "iso:country":"CA",
    "sg:city":"Henribourg",
    "sg:classifiers":[
        {
            "category":"Professional",
            "subcategory":"Management & Consulting",
            "type":"Services"
        }
    ],
    "sg:phone":"+1 306 764 2032",
    "sg:postcode":"S0J 1C0",
    "sg:province":"SK",
    "sg:tags":[
        "party",
        "planning"
    ],
    "wof:name":"Puff'n Bounce",
    "wof:placetype":"venue"
},
  "geometry": {"coordinates":[-105.62100982699999,53.3945236206],"type":"Point"}
}