{
  "type": "Feature",
  "properties": {
    "addr:full":"700 Boul Saint-Joseph # 1516 Hull QC J8Y 4B1",
    "addr:housenumber":"700",
    "addr:postcode":"j8y 4b1",
    "addr:street":"Boul Saint-Joseph # 1516",
    "iso:country":"CA",
    "sg:address":"700 Boul Saint-Joseph # 1516",
    "sg:city":"Hull",
    "sg:classifiers":[
        {
            "category":"Real Estate",
            "subcategory":"Real Estate Agent",
            "type":"Services"
        }
    ],
    "sg:phone":"+1 819 771 7799",
    "sg:postcode":"J8Y 4B1",
    "sg:province":"QC",
    "wof:name":"Tapp Realty Inc",
    "wof:placetype":"venue"
},
  "geometry": {"coordinates":[-75.7408370972,45.4550209045],"type":"Point"}
}