{
  "type": "Feature",
  "properties": {
    "iso:country":"CA",
    "sg:city":"Coquitlam",
    "sg:classifiers":[
        {
            "category":"Food & Beverages",
            "subcategory":"Meat & Fish",
            "type":"Retail Goods"
        }
    ],
    "sg:phone":"+1 604 931 3713",
    "sg:postcode":"V3K 3V9",
    "sg:province":"BC",
    "sg:tags":[
        "seafood"
    ],
    "wof:name":"Matsuzuski",
    "wof:placetype":"venue"
},
  "geometry": {"coordinates":[-122.892494,49.246086],"type":"Point"}
}