{
  "type": "Feature",
  "properties": {
    "addr:full":"Highway 3 Paradise Hill SK S0M 2G0",
    "addr:postcode":"s0m 2g0",
    "addr:street":"Highway 3 Paradise Hill",
    "iso:country":"CA",
    "sg:address":"Highway 3",
    "sg:city":"Paradise Hill",
    "sg:classifiers":[
        {
            "category":"Mining & Drilling",
            "type":"Manufacturing & Wholesale Goods"
        }
    ],
    "sg:phone":"+1 306 344 2272",
    "sg:postcode":"S0M 2G0",
    "sg:province":"SK",
    "sg:tags":[
        "oil",
        "well"
    ],
    "wof:name":"Paradise Oilfield Svc Ltd",
    "wof:placetype":"venue"
},
  "geometry": {"coordinates":[-109.45829000000001,53.539154],"type":"Point"}
}