{
  "type": "Feature",
  "properties": {
    "addr:full":"190 Colonnade Rd Nepean ON K2E 7J5",
    "addr:housenumber":"190",
    "addr:postcode":"k2e 7j5",
    "addr:street":"Colonnade Rd",
    "iso:country":"CA",
    "sg:address":"190 Colonnade Rd",
    "sg:city":"Nepean",
    "sg:classifiers":[
        {
            "category":"Building & Trades",
            "subcategory":"Electrical",
            "type":"Services"
        }
    ],
    "sg:phone":"+1 613 723 6629",
    "sg:postcode":"K2E 7J5",
    "sg:province":"ON",
    "sg:tags":[
        "equipment",
        "telecommunication"
    ],
    "wof:name":"Parslow Radio Communications",
    "wof:placetype":"venue"
},
  "geometry": {"coordinates":[-75.71137237550001,45.3421821594],"type":"Point"}
}