{
  "type": "Feature",
  "properties": {
    "addr:full":"825 Boul DE LA Grande-Baie S LA Baie QC G7B 1C3",
    "addr:housenumber":"825",
    "addr:postcode":"g7b 1c3",
    "addr:street":"Boul De La Grande-Baie S La Baie",
    "iso:country":"CA",
    "sg:address":"825 Boul DE LA Grande-Baie S",
    "sg:city":"LA Baie",
    "sg:classifiers":[
        {
            "category":"Social Services",
            "type":"Services"
        }
    ],
    "sg:phone":"+1 418 697 0634",
    "sg:postcode":"G7B 1C3",
    "sg:province":"QC",
    "sg:tags":[
        "youth",
        "organization",
        "center",
        "association"
    ],
    "wof:name":"Carrefour Jeunesse-Emploi",
    "wof:placetype":"venue"
},
  "geometry": {"coordinates":[-70.87776184080001,48.3281593323],"type":"Point"}
}