{
  "type": "Feature",
  "properties": {
    "iso:country":"CA",
    "sg:address":"13611 102 Ave NW",
    "sg:city":"Edmonton",
    "sg:classifiers":[
        {
            "category":"Personal",
            "type":"Services"
        }
    ],
    "sg:phone":"+1 780 448 2557",
    "sg:postcode":"T5N 0N9",
    "sg:province":"AB",
    "sg:tags":[
        "dating"
    ],
    "wof:name":"Personal Connections",
    "wof:placetype":"venue"
},
  "geometry": {"coordinates":[-113.556625,53.542812],"type":"Point"}
}