{
  "type": "Feature",
  "properties": {
    "iso:country":"CA",
    "sg:address":"128 Queen St E",
    "sg:city":"St Marys",
    "sg:classifiers":[
        {
            "category":"Shopping",
            "subcategory":"Used Merchandise",
            "type":"Retail Goods"
        }
    ],
    "sg:phone":"+1 519 284 8117",
    "sg:postcode":"N4X 1B1",
    "sg:province":"ON",
    "sg:tags":[
        "antique"
    ],
    "wof:name":"Eclectic Treasure",
    "wof:placetype":"venue"
},
  "geometry": {"coordinates":[-81.142296,43.259281],"type":"Point"}
}