{
  "type": "Feature",
  "properties": {
    "addr:full":"Winnipeg MB R3L 1Y5",
    "addr:postcode":"r3l 1y5",
    "iso:country":"CA",
    "sg:city":"Winnipeg",
    "sg:classifiers":[
        {
            "category":"Travel",
            "subcategory":"Travel Agent",
            "type":"Entertainment"
        }
    ],
    "sg:phone":"+1 204 985 9200",
    "sg:postcode":"R3L 1Y5",
    "sg:province":"MB",
    "sg:tags":[
        "agency",
        "bureau"
    ],
    "wof:name":"Out'n About Travel Inc",
    "wof:placetype":"venue"
},
  "geometry": {"coordinates":[-97.146095,49.879086],"type":"Point"}
}