{
  "type": "Feature",
  "properties": {
    "addr:full":"Windsor NS B0N 2T0",
    "addr:postcode":"b0n 2t0",
    "iso:country":"CA",
    "sg:city":"Windsor",
    "sg:classifiers":[
        {
            "category":"Professional",
            "type":"Services"
        }
    ],
    "sg:phone":"+1 902 798 1841",
    "sg:postcode":"B0N 2T0",
    "sg:province":"NS",
    "sg:tags":[
        "consultant",
        "geological"
    ],
    "wof:name":"D R Duncan & Assoc",
    "wof:placetype":"venue"
},
  "geometry": {"coordinates":[-64.139961,44.994392],"type":"Point"}
}