{
  "type": "Feature",
  "properties": {
    "addr:full":"21048 Lower Laplanche St Amherst NS B4H 3Y6",
    "addr:housenumber":"21048",
    "addr:postcode":"b4h 3y6",
    "addr:street":"Lower Laplanche St",
    "iso:country":"CA",
    "sg:address":"21048 Lower Laplanche St",
    "sg:city":"Amherst",
    "sg:classifiers":[
        {
            "category":"Autos & Motor Vehicles",
            "subcategory":"Auto Supplies",
            "type":"Retail Goods"
        }
    ],
    "sg:phone":"+1 902 667 3303",
    "sg:postcode":"B4H 3Y6",
    "sg:province":"NS",
    "sg:tags":[
        "repairing",
        "automobile"
    ],
    "wof:name":"Tire Shack",
    "wof:placetype":"venue"
},
  "geometry": {"coordinates":[-64.218369,45.835491],"type":"Point"}
}