{
  "type": "Feature",
  "properties": {
    "addr:full":"400 Boul DE Sainte-Adele Sainte-Adele QC J8B 2N2",
    "addr:housenumber":"400",
    "addr:postcode":"j8b 2n2",
    "addr:street":"Boul De Sainte-Adele Sainte-Adele",
    "iso:country":"CA",
    "sg:address":"400 Boul DE Sainte-Adele",
    "sg:city":"Sainte-Adele",
    "sg:classifiers":[
        {
            "category":"Government",
            "subcategory":"Office",
            "type":"Public Place"
        }
    ],
    "sg:phone":"+1 450 229 6560",
    "sg:postcode":"J8B 2N2",
    "sg:province":"QC",
    "wof:name":"Quebec Solidarite Sociale",
    "wof:placetype":"venue"
},
  "geometry": {"coordinates":[-74.12011699999999,45.985798],"type":"Point"}
}