{
  "type": "Feature",
  "properties": {
    "addr:full":"Winnipeg MB R3C 3X1",
    "addr:postcode":"r3c 3x1",
    "iso:country":"CA",
    "sg:city":"Winnipeg",
    "sg:classifiers":[
        {
            "category":"Health Services",
            "subcategory":"Doctor",
            "type":"Services"
        }
    ],
    "sg:phone":"+1 204 783 2971",
    "sg:postcode":"R3C 3X1",
    "sg:province":"MB",
    "sg:tags":[
        "dentist"
    ],
    "wof:name":"Kaufmann, Robert M DDS",
    "wof:placetype":"venue"
},
  "geometry": {"coordinates":[-97.152283,49.890209],"type":"Point"}
}