{
  "type": "Feature",
  "properties": {
    "addr:full":"1555 Rue Des Cascades O Saint-Hyacinthe QC J2S 3H7",
    "addr:housenumber":"1555",
    "addr:postcode":"j2s 3h7",
    "addr:street":"Rue Des Cascades O",
    "iso:country":"CA",
    "sg:address":"1555 Rue Des Cascades O",
    "sg:city":"Saint-Hyacinthe",
    "sg:classifiers":[
        {
            "category":"Food & Beverages",
            "subcategory":"Specialty",
            "type":"Retail Goods"
        }
    ],
    "sg:phone":"+1 450 771 4331",
    "sg:postcode":"J2S 3H7",
    "sg:province":"QC",
    "sg:tags":[
        "gourmet",
        "shop",
        "delicatessen"
    ],
    "wof:name":"William J Walter Inc",
    "wof:placetype":"venue"
},
  "geometry": {"coordinates":[-72.945747,45.624573],"type":"Point"}
}