{
  "type": "Feature",
  "properties": {
    "iso:country":"CA",
    "sg:address":"23256 Highway 48",
    "sg:city":"Sutton West",
    "sg:classifiers":[
        {
            "category":"Building & Trades",
            "subcategory":"Electrical",
            "type":"Services"
        }
    ],
    "sg:phone":"+1 905 895 6727",
    "sg:postcode":"L0E 1R0",
    "sg:province":"ON",
    "sg:tags":[
        "electric",
        "contractor"
    ],
    "wof:name":"Vern Stephens Electric Ltd",
    "wof:placetype":"venue"
},
  "geometry": {"coordinates":[-79.3612365723,44.3048667908],"type":"Point"}
}