{
  "type": "Feature",
  "properties": {
    "addr:full":"105 1st Ave NW Leroy SK S0K 2P0",
    "addr:housenumber":"105",
    "addr:postcode":"s0k 2p0",
    "addr:street":"1St Ave Nw Leroy",
    "iso:country":"CA",
    "sg:address":"105 1st Ave NW",
    "sg:city":"Leroy",
    "sg:classifiers":[
        {
            "category":"Travel",
            "subcategory":"Hotels & Motels",
            "type":"Entertainment"
        }
    ],
    "sg:phone":"+1 306 286 3271",
    "sg:postcode":"S0K 2P0",
    "sg:province":"SK",
    "wof:name":"Leroy Hotel",
    "wof:placetype":"venue"
},
  "geometry": {"coordinates":[-104.744072,52.003365],"type":"Point"}
}