{
  "type": "Feature",
  "properties": {
    "addr:full":"Edmonton AB T5V 1K8",
    "addr:postcode":"t5v 1k8",
    "iso:country":"CA",
    "sg:city":"Edmonton",
    "sg:classifiers":[
        {
            "category":"Building & Trades",
            "subcategory":"Plumbing",
            "type":"Services"
        }
    ],
    "sg:phone":"+1 780 454 2514",
    "sg:postcode":"T5V 1K8",
    "sg:province":"AB",
    "sg:tags":[
        "heating",
        "contractor"
    ],
    "wof:name":"Philco Heating & Air Cond",
    "wof:placetype":"venue"
},
  "geometry": {"coordinates":[-113.58532,53.5769],"type":"Point"}
}