{
  "type": "Feature",
  "properties": {
    "addr:full":"7481 Edmonds St Burnaby BC V3N 1B3",
    "addr:housenumber":"7481",
    "addr:postcode":"v3n 1b3",
    "addr:street":"Edmonds St",
    "iso:country":"CA",
    "sg:address":"7481 Edmonds St",
    "sg:city":"Burnaby",
    "sg:classifiers":[
        {
            "category":"Restaurant",
            "type":"Food & Drink"
        }
    ],
    "sg:phone":"+1 604 520 6649",
    "sg:postcode":"V3N 1B3",
    "sg:province":"BC",
    "sg:tags":[
        "out",
        "pizza"
    ],
    "wof:name":"Mona Pizza",
    "wof:placetype":"venue"
},
  "geometry": {"coordinates":[-122.945831,49.221653],"type":"Point"}
}