{
  "type": "Feature",
  "properties": {
    "addr:full":"1534 Rue Principale Canton-DE-Granby QC J2G 8C8",
    "addr:housenumber":"1534",
    "addr:postcode":"j2g 8c8",
    "addr:street":"Rue Principale",
    "iso:country":"CA",
    "sg:address":"1534 Rue Principale",
    "sg:city":"Canton-DE-Granby",
    "sg:classifiers":[
        {
            "category":"Manufacturing",
            "subcategory":"Tools & Machinery",
            "type":"Manufacturing & Wholesale Goods"
        }
    ],
    "sg:phone":"+1 450 378 8096",
    "sg:postcode":"J2G 8C8",
    "sg:province":"QC",
    "sg:tags":[
        "machine",
        "shop"
    ],
    "wof:name":"Machinage Sylvain Inc",
    "wof:placetype":"venue"
},
  "geometry": {"coordinates":[-72.806808,45.425014],"type":"Point"}
}