{
  "type": "Feature",
  "properties": {
    "iso:country":"CA",
    "sg:city":"Oshawa",
    "sg:classifiers":[
        {
            "category":"Shopping",
            "subcategory":"Bicycles & Sporting Goods",
            "type":"Retail Goods"
        }
    ],
    "sg:phone":"+1 905 723 7824",
    "sg:postcode":"L1H 7P8",
    "sg:province":"ON",
    "sg:tags":[
        "dancing",
        "supply"
    ],
    "wof:name":"Gymstytch",
    "wof:placetype":"venue"
},
  "geometry": {"coordinates":[-78.83079528810001,43.8761863708],"type":"Point"}
}