{
  "type": "Feature",
  "properties": {
    "addr:full":"301 Centre St Ponteix SK S0N 1Z0",
    "addr:housenumber":"301",
    "addr:postcode":"s0n 1z0",
    "addr:street":"Centre St",
    "iso:country":"CA",
    "sg:address":"301 Centre St",
    "sg:city":"Ponteix",
    "sg:classifiers":[
        {
            "category":"Shopping",
            "subcategory":"Florist",
            "type":"Retail Goods"
        }
    ],
    "sg:phone":"+1 306 625 3332",
    "sg:postcode":"S0N 1Z0",
    "sg:province":"SK",
    "sg:tags":[
        "grocer"
    ],
    "wof:name":"Scully's Ag Foods",
    "wof:placetype":"venue"
},
  "geometry": {"coordinates":[-107.490470886,49.7448692322],"type":"Point"}
}