{
  "type": "Feature",
  "properties": {
    "addr:full":"583 Rue Centrale Memramcook NB E4K 3R5",
    "addr:housenumber":"583",
    "addr:postcode":"e4k 3r5",
    "addr:street":"Rue Centrale",
    "iso:country":"CA",
    "sg:address":"583 Rue Centrale",
    "sg:city":"Memramcook",
    "sg:classifiers":[
        {
            "category":"Restaurant",
            "type":"Food & Drink"
        }
    ],
    "sg:phone":"+1 506 758 2554",
    "sg:postcode":"E4K 3R5",
    "sg:province":"NB",
    "wof:name":"Le Blanc Restaurant",
    "wof:placetype":"venue"
},
  "geometry": {"coordinates":[-64.56550598139999,45.9741973877],"type":"Point"}
}