{
  "type": "Feature",
  "properties": {
    "iso:country":"CA",
    "sg:address":"1063 Eglinton Ave W",
    "sg:city":"York",
    "sg:classifiers":[
        {
            "category":"Professional",
            "subcategory":"Advertising",
            "type":"Services"
        }
    ],
    "sg:phone":"+1 416 783 3311",
    "sg:postcode":"M6C 2C9",
    "sg:province":"ON",
    "sg:tags":[
        "counselor"
    ],
    "wof:name":"Guidelines Advertising Ltd",
    "wof:placetype":"venue"
},
  "geometry": {"coordinates":[-79.433631897,43.6991653442],"type":"Point"}
}