{
  "type": "Feature",
  "properties": {
    "addr:full":"1486 Rue Sainte-Catherine O Montreal QC H3G 1S8",
    "addr:housenumber":"1486",
    "addr:postcode":"h3g 1s8",
    "addr:street":"Rue Sainte-Catherine O",
    "iso:country":"CA",
    "sg:address":"1486 Rue Sainte-Catherine O",
    "sg:city":"Montreal",
    "sg:classifiers":[
        {
            "category":"Shopping",
            "subcategory":"Clothing, Apparel, & Fashions",
            "type":"Retail Goods"
        }
    ],
    "sg:phone":"+1 514 935 6800",
    "sg:postcode":"H3G 1S8",
    "sg:province":"QC",
    "sg:tags":[
        "jean"
    ],
    "wof:name":"Jeans Homogene",
    "wof:placetype":"venue"
},
  "geometry": {"coordinates":[-73.553596,45.520954],"type":"Point"}
}