{
  "type": "Feature",
  "properties": {
    "iso:country":"CA",
    "sg:address":"191 Rue Sainte-Genevieve",
    "sg:city":"Saint-Isidore",
    "sg:classifiers":[
        {
            "category":"Home & Garden",
            "subcategory":"Building Materials",
            "type":"Retail Goods"
        }
    ],
    "sg:phone":"+1 418 882 5664",
    "sg:postcode":"G0S 2S0",
    "sg:province":"QC",
    "wof:name":"Materiaux St-Isidore Inc",
    "wof:placetype":"venue"
},
  "geometry": {"coordinates":[-71.09014129640001,46.5863227844],"type":"Point"}
}