{
  "type": "Feature",
  "properties": {
    "addr:full":"5 Main St N St George Brant ON N0E 1N0",
    "addr:housenumber":"5",
    "addr:postcode":"n0e 1n0",
    "addr:street":"Main St N",
    "iso:country":"CA",
    "sg:address":"5 Main St N",
    "sg:city":"St George Brant",
    "sg:classifiers":[
        {
            "category":"Government",
            "subcategory":"Office",
            "type":"Public Place"
        }
    ],
    "sg:phone":"+1 519 448 1432",
    "sg:postcode":"N0E 1N0",
    "sg:province":"ON",
    "sg:tags":[
        "municipality"
    ],
    "wof:name":"South Dumfries Township Office",
    "wof:placetype":"venue"
},
  "geometry": {"coordinates":[-80.4266586304,43.1024703979],"type":"Point"}
}