{
  "type": "Feature",
  "properties": {
    "addr:full":"1509 Marine Dr North Vancouver BC V7P 1T8",
    "addr:housenumber":"1509",
    "addr:postcode":"v7p 1t8",
    "addr:street":"Marine Dr",
    "iso:country":"CA",
    "sg:address":"1509 Marine Dr",
    "sg:city":"North Vancouver",
    "sg:classifiers":[
        {
            "category":"Restaurant",
            "type":"Food & Drink"
        }
    ],
    "sg:phone":"+1 604 986 1334",
    "sg:postcode":"V7P 1T8",
    "sg:province":"BC",
    "wof:name":"LA Cucina Italiana Restaurant",
    "wof:placetype":"venue"
},
  "geometry": {"coordinates":[-123.205879,49.273483],"type":"Point"}
}