{
  "type": "Feature",
  "properties": {
    "addr:full":"Saint-Denis-DE-Brompton QC J0B 2P0",
    "addr:postcode":"j0b 2p0",
    "iso:country":"CA",
    "sg:city":"Saint-Denis-DE-Brompton",
    "sg:classifiers":[
        {
            "category":"Manufacturing",
            "subcategory":"Glass & Minerals",
            "type":"Manufacturing & Wholesale Goods"
        }
    ],
    "sg:phone":"+1 819 846 0813",
    "sg:postcode":"J0B 2P0",
    "sg:province":"QC",
    "sg:tags":[
        "foundation",
        "brick",
        "block",
        "concrete"
    ],
    "wof:name":"Coffrage Jcm Mongeau Inc",
    "wof:placetype":"venue"
},
  "geometry": {"coordinates":[-72.1189422607,45.4581832886],"type":"Point"}
}