{
  "type": "Feature",
  "properties": {
    "addr:full":"Saskatoon SK S7L 1B4",
    "addr:postcode":"s7l 1b4",
    "iso:country":"CA",
    "sg:city":"Saskatoon",
    "sg:classifiers":[
        {
            "category":"Shopping",
            "subcategory":"Photographic Equipment",
            "type":"Retail Goods"
        }
    ],
    "sg:phone":"+1 306 934 3111",
    "sg:postcode":"S7L 1B4",
    "sg:province":"SK",
    "sg:tags":[
        "supply"
    ],
    "wof:name":"Don's Photo Shop Ltd",
    "wof:placetype":"venue"
},
  "geometry": {"coordinates":[-106.670547,52.151955],"type":"Point"}
}