{
  "type": "Feature",
  "properties": {
    "addr:full":"22 Rue Seguin Rigaud QC J0P 1P0",
    "addr:housenumber":"22",
    "addr:postcode":"j0p 1p0",
    "addr:street":"Rue Seguin",
    "iso:country":"CA",
    "sg:address":"22 Rue Seguin",
    "sg:city":"Rigaud",
    "sg:classifiers":[
        {
            "category":"Professional",
            "subcategory":"Management & Consulting",
            "type":"Services"
        }
    ],
    "sg:phone":"+1 450 456 0714",
    "sg:postcode":"J0P 1P0",
    "sg:province":"QC",
    "sg:tags":[
        "consultant",
        "instructional"
    ],
    "wof:name":"Experts Conseils Rl Inc",
    "wof:placetype":"venue"
},
  "geometry": {"coordinates":[-74.308037,45.485626],"type":"Point"}
}