{
  "type": "Feature",
  "properties": {
    "addr:full":"407 Rue Ericka Laval QC H7P 5S3",
    "addr:housenumber":"407",
    "addr:postcode":"h7p 5s3",
    "addr:street":"Rue Ericka",
    "iso:country":"CA",
    "sg:address":"407 Rue Ericka",
    "sg:city":"Laval",
    "sg:classifiers":[
        {
            "category":"Shopping",
            "subcategory":"Computers & Home Electronics",
            "type":"Retail Goods"
        }
    ],
    "sg:phone":"+1 450 625 3865",
    "sg:postcode":"H7P 5S3",
    "sg:province":"QC",
    "sg:tags":[
        "equipment",
        "dealer"
    ],
    "wof:name":"Frequence Informatique",
    "wof:placetype":"venue"
},
  "geometry": {"coordinates":[-73.785583,45.577759],"type":"Point"}
}