{
  "type": "Feature",
  "properties": {
    "addr:full":"Saint-Damien QC J0K 2E0",
    "addr:postcode":"j0k 2e0",
    "iso:country":"CA",
    "sg:city":"Saint-Damien",
    "sg:classifiers":[
        {
            "category":"Food & Beverages",
            "subcategory":"Groceries & Convenience Stores",
            "type":"Retail Goods"
        }
    ],
    "sg:phone":"+1 450 886 0010",
    "sg:postcode":"J0K 2E0",
    "sg:province":"QC",
    "wof:name":"Depanneur Relais Des Brises",
    "wof:placetype":"venue"
},
  "geometry": {"coordinates":[-73.55574,46.308067],"type":"Point"}
}