{
  "type": "Feature",
  "properties": {
    "addr:full":"9 Rue Des Loisirs St-Marcel-DE-L'Islet QC G0R 3R0",
    "addr:housenumber":"9",
    "addr:postcode":"g0r 3r0",
    "addr:street":"Rue Des Loisirs St-Marcel-De-L'Islet",
    "iso:country":"CA",
    "sg:address":"9 Rue Des Loisirs",
    "sg:city":"St-Marcel-DE-L'Islet",
    "sg:classifiers":[
        {
            "category":"Health Services",
            "subcategory":"Nursing And Care Facility",
            "type":"Services"
        }
    ],
    "sg:phone":"+1 418 356 2420",
    "sg:postcode":"G0R 3R0",
    "sg:province":"QC",
    "sg:tags":[
        "home",
        "retirement",
        "community"
    ],
    "wof:name":"Marcellois Inc",
    "wof:placetype":"venue"
},
  "geometry": {"coordinates":[-70.331535,47.089802],"type":"Point"}
}