{
  "type": "Feature",
  "properties": {
    "addr:full":"12200 Av Rene-Masson Montreal QC H1E 4T4",
    "addr:housenumber":"12200",
    "addr:postcode":"h1e 4t4",
    "addr:street":"Av Rene-Masson",
    "iso:country":"CA",
    "sg:address":"12200 Av Rene-Masson",
    "sg:city":"Montreal",
    "sg:classifiers":[
        {
            "category":"Education",
            "subcategory":"School",
            "type":"Public Place"
        }
    ],
    "sg:phone":"+1 514 881 7170",
    "sg:postcode":"H1E 4T4",
    "sg:province":"QC",
    "wof:name":"Notre-Dame-DE-Fatima Ecole",
    "wof:placetype":"venue"
},
  "geometry": {"coordinates":[-73.57452392579999,45.6472396851],"type":"Point"}
}