{
  "type": "Feature",
  "properties": {
    "addr:full":"9127 Academy Dr SE Calgary AB T2J 1A5",
    "addr:housenumber":"9127",
    "addr:postcode":"t2j 1a5",
    "addr:street":"Academy Dr Se",
    "iso:country":"CA",
    "sg:address":"9127 Academy Dr SE",
    "sg:city":"Calgary",
    "sg:classifiers":[
        {
            "category":"Retail",
            "subcategory":"Repair Shop",
            "type":"Services"
        }
    ],
    "sg:phone":"+1 403 279 6692",
    "sg:postcode":"T2J 1A5",
    "sg:province":"AB",
    "sg:tags":[
        "upholsterer"
    ],
    "wof:name":"Whippletree Upholstery",
    "wof:placetype":"venue"
},
  "geometry": {"coordinates":[-114.047211,50.971661],"type":"Point"}
}