{
  "type": "Feature",
  "properties": {
    "addr:full":"1500 Gulleden Dr Mississauga ON L4X 2T7",
    "addr:housenumber":"1500",
    "addr:postcode":"l4x 2t7",
    "addr:street":"Gulleden Dr",
    "iso:country":"CA",
    "sg:address":"1500 Gulleden Dr",
    "sg:city":"Mississauga",
    "sg:classifiers":[
        {
            "category":"Arena",
            "subcategory":"Sports Club",
            "type":"Entertainment"
        }
    ],
    "sg:phone":"+1 905 625 1583",
    "sg:postcode":"L4X 2T7",
    "sg:province":"ON",
    "sg:tags":[
        "athletic",
        "fields",
        "stadium"
    ],
    "wof:name":"Chic Murray Arena",
    "wof:placetype":"venue"
},
  "geometry": {"coordinates":[-79.5989532471,43.6231498718],"type":"Point"}
}