{
  "type": "Feature",
  "properties": {
    "iso:country":"CA",
    "sg:address":"615 Macleod Trail SE",
    "sg:city":"Calgary",
    "sg:classifiers":[
        {
            "category":"Government",
            "subcategory":"Office",
            "type":"Public Place"
        }
    ],
    "sg:phone":"+1 403 297 8444",
    "sg:postcode":"T2G 4T8",
    "sg:province":"AB",
    "sg:tags":[
        "village"
    ],
    "wof:name":"Alberta Crown Prosecutors",
    "wof:placetype":"venue"
},
  "geometry": {"coordinates":[-114.058151245,51.0470962524],"type":"Point"}
}