{
  "type": "Feature",
  "properties": {
    "addr:full":"PO Box 2864 Pincher Creek AB T0K 1W0",
    "addr:housenumber":"po",
    "addr:postcode":"t0k 1w0",
    "addr:street":"Box 2864 Pincher Creek",
    "iso:country":"CA",
    "sg:address":"PO Box 2864",
    "sg:city":"Pincher Creek",
    "sg:classifiers":[
        {
            "category":"Travel",
            "subcategory":"Hotels & Motels",
            "type":"Entertainment"
        }
    ],
    "sg:phone":"+1 403 627 5128",
    "sg:postcode":"T0K 1W0",
    "sg:province":"AB",
    "sg:tags":[
        "breakfast",
        "accommodation",
        "bed"
    ],
    "wof:name":"Stepping Stone Cabins B & B",
    "wof:placetype":"venue"
},
  "geometry": {"coordinates":[-113.95009613000001,49.4856681824],"type":"Point"}
}