{
  "type": "Feature",
  "properties": {
    "addr:full":"33 City Centre Dr #210 Mississauga ON L5B 2N5",
    "addr:housenumber":"33",
    "addr:postcode":"l5b 2n5",
    "addr:street":"City Centre Dr # 210",
    "iso:country":"CA",
    "sg:address":"33 City Centre Dr #210",
    "sg:city":"Mississauga",
    "sg:classifiers":[
        {
            "category":"Banks & Credit Unions",
            "subcategory":"Investment Brokerage",
            "type":"Services"
        }
    ],
    "sg:phone":"+1 905 897 8333",
    "sg:postcode":"L5B 2N5",
    "sg:province":"ON",
    "wof:name":"Rbc Dominion Securities Inc",
    "wof:placetype":"venue"
},
  "geometry": {"coordinates":[-79.6391296387,43.5944290161],"type":"Point"}
}