{
  "type": "Feature",
  "properties": {
    "addr:full":"Charlottetown PE C1A 8C2",
    "addr:postcode":"c1a 8c2",
    "iso:country":"CA",
    "sg:city":"Charlottetown",
    "sg:classifiers":[
        {
            "category":"Restaurant",
            "type":"Food & Drink"
        }
    ],
    "sg:phone":"+1 902 894 8566",
    "sg:postcode":"C1A 8C2",
    "sg:province":"PE",
    "wof:name":"Gallery Restaurant",
    "wof:placetype":"venue"
},
  "geometry": {"coordinates":[-63.182697,46.257809],"type":"Point"}
}