{
  "type": "Feature",
  "properties": {
    "iso:country":"CA",
    "sg:address":"1013 Mountcastle Cres",
    "sg:city":"Pickering",
    "sg:classifiers":[
        {
            "category":"Professional",
            "subcategory":"Business Services",
            "type":"Services"
        }
    ],
    "sg:phone":"+1 905 420 8625",
    "sg:postcode":"L1V 5J4",
    "sg:province":"ON",
    "sg:tags":[
        "recording",
        "studio"
    ],
    "wof:name":"Acrobat Music Inc",
    "wof:placetype":"venue"
},
  "geometry": {"coordinates":[-79.108291626,43.8416519165],"type":"Point"}
}