{
  "type": "Feature",
  "properties": {
    "addr:full":"8656 164 St Surrey BC V4N 1E6",
    "addr:housenumber":"8656",
    "addr:postcode":"v4n 1e6",
    "addr:street":"164 St",
    "iso:country":"CA",
    "sg:address":"8656 164 St",
    "sg:city":"Surrey",
    "sg:classifiers":[
        {
            "category":"Wholesale",
            "subcategory":"Apparel",
            "type":"Manufacturing & Wholesale Goods"
        }
    ],
    "sg:phone":"+1 604 597 9115",
    "sg:postcode":"V4N 1E6",
    "sg:province":"BC",
    "sg:tags":[
        "sportswear"
    ],
    "wof:name":"Images in Flight Designs Ltd",
    "wof:placetype":"venue"
},
  "geometry": {"coordinates":[-122.767478943,49.1606941223],"type":"Point"}
}