{
  "type": "Feature",
  "properties": {
    "addr:full":"Edmonton AB T5S 1J8",
    "addr:postcode":"t5s 1j8",
    "iso:country":"CA",
    "sg:city":"Edmonton",
    "sg:classifiers":[
        {
            "category":"Professional",
            "subcategory":"Engineering",
            "type":"Services"
        }
    ],
    "sg:phone":"+1 780 483 5200",
    "sg:postcode":"T5S 1J8",
    "sg:province":"AB",
    "sg:tags":[
        "engineer"
    ],
    "wof:name":"Morrison Hershfield Ltd",
    "wof:placetype":"venue"
},
  "geometry": {"coordinates":[-113.619773865,53.5433006287],"type":"Point"}
}