{
  "type": "Feature",
  "properties": {
    "addr:full":"Calgary AB T2E 6P1",
    "addr:postcode":"t2e 6p1",
    "iso:country":"CA",
    "sg:city":"Calgary",
    "sg:classifiers":[
        {
            "category":"Home & Garden",
            "subcategory":"Furniture",
            "type":"Retail Goods"
        }
    ],
    "sg:phone":"+1 403 291 2936",
    "sg:postcode":"T2E 6P1",
    "sg:province":"AB",
    "sg:tags":[
        "cabinet",
        "kitchen",
        "woodworker"
    ],
    "wof:name":"Kaswood Developments",
    "wof:placetype":"venue"
},
  "geometry": {"coordinates":[-114.030838,51.094612],"type":"Point"}
}