{
  "type": "Feature",
  "properties": {
    "addr:full":"215 Lakeside Dr Labrador City NL A2V 1B4",
    "addr:housenumber":"215",
    "addr:postcode":"a2v 1b4",
    "addr:street":"Lakeside Dr",
    "iso:country":"CA",
    "sg:address":"215 Lakeside Dr",
    "sg:city":"Labrador City",
    "sg:classifiers":[
        {
            "category":"Building & Trades",
            "subcategory":"Cleaning & Sanitation",
            "type":"Services"
        }
    ],
    "sg:phone":"+1 709 944 2503",
    "sg:postcode":"A2V 1B4",
    "sg:province":"NL",
    "sg:tags":[
        "house"
    ],
    "wof:name":"Pat's Dial-A-Maid Ltd",
    "wof:placetype":"venue"
},
  "geometry": {"coordinates":[-66.90376281739999,52.9408531189],"type":"Point"}
}