{
  "type": "Feature",
  "properties": {
    "addr:full":"640 Dufferin St Toronto ON M6K 2B4",
    "addr:housenumber":"640",
    "addr:postcode":"m6k 2b4",
    "addr:street":"Dufferin St",
    "iso:country":"CA",
    "sg:address":"640 Dufferin St",
    "sg:city":"Toronto",
    "sg:classifiers":[
        {
            "category":"Shopping",
            "subcategory":"Clothing, Apparel, & Fashions",
            "type":"Retail Goods"
        }
    ],
    "sg:phone":"+1 416 533 4157",
    "sg:postcode":"M6K 2B4",
    "sg:province":"ON",
    "wof:name":"M & M Tailor",
    "wof:placetype":"venue"
},
  "geometry": {"coordinates":[-79.4316482544,43.6497383118],"type":"Point"}
}