{
  "type": "Feature",
  "properties": {
    "addr:full":"571 Boul Richelieu Richelieu QC J3L 4Y3",
    "addr:housenumber":"571",
    "addr:postcode":"j3l 4y3",
    "addr:street":"Boul Richelieu",
    "iso:country":"CA",
    "sg:address":"571 Boul Richelieu",
    "sg:city":"Richelieu",
    "sg:classifiers":[
        {
            "category":"Restaurant",
            "type":"Food & Drink"
        }
    ],
    "sg:phone":"+1 450 447 6282",
    "sg:postcode":"J3L 4Y3",
    "sg:province":"QC",
    "wof:name":"Restaurant LA Belle Province",
    "wof:placetype":"venue"
},
  "geometry": {"coordinates":[-73.2466964722,45.4433784485],"type":"Point"}
}