{
  "type": "Feature",
  "properties": {
    "addr:full":"Nanaimo BC V9S 1H8",
    "addr:postcode":"v9s 1h8",
    "iso:country":"CA",
    "sg:city":"Nanaimo",
    "sg:classifiers":[
        {
            "category":"Professional",
            "subcategory":"Computer Services",
            "type":"Services"
        }
    ],
    "sg:phone":"+1 250 756 3915",
    "sg:postcode":"V9S 1H8",
    "sg:province":"BC",
    "wof:name":"Interserve Technologies Corp",
    "wof:placetype":"venue"
},
  "geometry": {"coordinates":[-123.990883,49.190716],"type":"Point"}
}