{
  "type": "Feature",
  "properties": {
    "addr:full":"Mississauga ON L5M 4Z5",
    "addr:postcode":"l5m 4z5",
    "iso:country":"CA",
    "sg:city":"Mississauga",
    "sg:classifiers":[
        {
            "category":"Personal",
            "type":"Services"
        }
    ],
    "sg:phone":"+1 905 569 6390",
    "sg:postcode":"L5M 4Z5",
    "sg:province":"ON",
    "sg:tags":[
        "wear",
        "formal"
    ],
    "wof:name":"Tip Top Tailors",
    "wof:placetype":"venue"
},
  "geometry": {"coordinates":[-79.70681,43.558788],"type":"Point"}
}