{
  "type": "Feature",
  "properties": {
    "addr:full":"145 Kent W Bobcaygeon ON K0M 1A0",
    "addr:housenumber":"145",
    "addr:postcode":"k0m 1a0",
    "addr:street":"Kent W Bobcaygeon",
    "iso:country":"CA",
    "sg:address":"145 Kent W",
    "sg:city":"Bobcaygeon",
    "sg:classifiers":[
        {
            "category":"Restaurant",
            "type":"Food & Drink"
        }
    ],
    "sg:phone":"+1 705 328 1111",
    "sg:postcode":"K0M 1A0",
    "sg:province":"ON",
    "sg:tags":[
        "pizza"
    ],
    "wof:name":"Pizza Pizza",
    "wof:placetype":"venue"
},
  "geometry": {"coordinates":[-78.53755187989999,44.5363006592],"type":"Point"}
}