{
  "type": "Feature",
  "properties": {
    "addr:full":"605 Strouds Lane Pickering ON L1V 5M5",
    "addr:housenumber":"605",
    "addr:postcode":"l1v 5m5",
    "addr:street":"Strouds Lane",
    "iso:country":"CA",
    "sg:address":"605 Strouds Lane",
    "sg:city":"Pickering",
    "sg:classifiers":[
        {
            "category":"Education",
            "subcategory":"School",
            "type":"Public Place"
        }
    ],
    "sg:phone":"+1 905 839 5289",
    "sg:postcode":"L1V 5M5",
    "sg:province":"ON",
    "wof:name":"Highbush Public School",
    "wof:placetype":"venue"
},
  "geometry": {"coordinates":[-79.12567138670001,43.8279838562],"type":"Point"}
}