{
  "type": "Feature",
  "properties": {
    "addr:full":"65 Brawley Rd Damascus NB E5N 4C3",
    "addr:housenumber":"65",
    "addr:postcode":"e5n 4c3",
    "addr:street":"Brawley Rd",
    "iso:country":"CA",
    "sg:address":"65 Brawley Rd",
    "sg:city":"Damascus",
    "sg:classifiers":[
        {
            "category":"Retail",
            "subcategory":"Auto Repair",
            "type":"Services"
        }
    ],
    "sg:phone":"+1 506 832 5166",
    "sg:postcode":"E5N 4C3",
    "sg:province":"NB",
    "sg:tags":[
        "repairing",
        "automobile"
    ],
    "wof:name":"Saunders Garage",
    "wof:placetype":"venue"
},
  "geometry": {"coordinates":[-65.80437499999999,45.46286],"type":"Point"}
}