{
  "type": "Feature",
  "properties": {
    "iso:country":"CA",
    "sg:address":"65 Brawley Rd",
    "sg:city":"Damascus",
    "sg:classifiers":[
        {
            "category":"Retail",
            "subcategory":"Auto Repair",
            "type":"Services"
        }
    ],
    "sg:phone":"+1 506 832 5166",
    "sg:postcode":"E5N 4C3",
    "sg:province":"NB",
    "sg:tags":[
        "repairing",
        "automobile"
    ],
    "wof:name":"Saunders Garage",
    "wof:placetype":"venue"
},
  "geometry": {"coordinates":[-65.80437499999999,45.46286],"type":"Point"}
}