{
  "type": "Feature",
  "properties": {
    "iso:country":"CA",
    "sg:address":"10871 Av Salk",
    "sg:city":"Montreal-Nord",
    "sg:classifiers":[
        {
            "category":"Freight",
            "type":"Transportation"
        }
    ],
    "sg:phone":"+1 514 329 5683",
    "sg:postcode":"H1G 6M7",
    "sg:province":"QC",
    "sg:tags":[
        "trucking"
    ],
    "wof:name":"Lodico Transport",
    "wof:placetype":"venue"
},
  "geometry": {"coordinates":[-73.62075,45.599041],"type":"Point"}
}