{
  "type": "Feature",
  "properties": {
    "addr:full":"General Delivery Lower Wedgeport NS B0W 2B0",
    "addr:postcode":"b0w 2b0",
    "iso:country":"CA",
    "sg:address":"General Delivery",
    "sg:city":"Lower Wedgeport",
    "sg:classifiers":[
        {
            "category":"Retail",
            "subcategory":"Auto Repair",
            "type":"Services"
        }
    ],
    "sg:phone":"+1 902 663 2738",
    "sg:postcode":"B0W 2B0",
    "sg:province":"NS",
    "sg:tags":[
        "body",
        "automobile",
        "painting"
    ],
    "wof:name":"Pothier Gordon Auto Body Shop",
    "wof:placetype":"venue"
},
  "geometry": {"coordinates":[-65.97927856450001,43.7161026001],"type":"Point"}
}