{
  "type": "Feature",
  "properties": {
    "iso:country":"CA",
    "sg:address":"2385 Boul Des Recollets",
    "sg:city":"Trois-Rivieres",
    "sg:classifiers":[
        {
            "category":"Home & Garden",
            "subcategory":"Furniture",
            "type":"Retail Goods"
        }
    ],
    "sg:phone":"+1 819 379 3636",
    "sg:postcode":"G8Z 4G1",
    "sg:province":"QC",
    "sg:tags":[
        "mattress"
    ],
    "wof:name":"Rene Matelas Inc",
    "wof:placetype":"venue"
},
  "geometry": {"coordinates":[-72.579056,46.337959],"type":"Point"}
}