{
  "type": "Feature",
  "properties": {
    "addr:full":"1062 Millar Creek Rd #1 Whistler BC V0N 1B1",
    "addr:housenumber":"1062",
    "addr:postcode":"v0n 1b1",
    "addr:street":"Millar Creek Rd # 1",
    "iso:country":"CA",
    "sg:address":"1062 Millar Creek Rd #1",
    "sg:city":"Whistler",
    "sg:classifiers":[
        {
            "category":"Professional",
            "subcategory":"Computer Services",
            "type":"Services"
        }
    ],
    "sg:phone":"+1 604 905 3426",
    "sg:postcode":"V0N 1B1",
    "sg:province":"BC",
    "wof:name":"Altitude Computers",
    "wof:placetype":"venue"
},
  "geometry": {"coordinates":[-123.041023254,50.0874252319],"type":"Point"}
}