{
  "type": "Feature",
  "properties": {
    "addr:full":"Carleton QC G0C 1J0",
    "addr:postcode":"g0c 1j0",
    "iso:country":"CA",
    "sg:city":"Carleton",
    "sg:classifiers":[
        {
            "category":"Manufacturing",
            "subcategory":"Printing",
            "type":"Manufacturing & Wholesale Goods"
        }
    ],
    "sg:phone":"+1 418 364 6369",
    "sg:postcode":"G0C 1J0",
    "sg:province":"QC",
    "sg:tags":[
        "newspaper"
    ],
    "wof:name":"Gagne, Gilles",
    "wof:placetype":"venue"
},
  "geometry": {"coordinates":[-66.123154,48.106884],"type":"Point"}
}