{
  "type": "Feature",
  "properties": {
    "addr:full":"Brampton ON L6T 4V5",
    "addr:postcode":"l6t 4v5",
    "iso:country":"CA",
    "sg:city":"Brampton",
    "sg:classifiers":[
        {
            "category":"Manufacturing",
            "subcategory":"Metals",
            "type":"Manufacturing & Wholesale Goods"
        }
    ],
    "sg:phone":"+1 905 791 2077",
    "sg:postcode":"L6T 4V5",
    "sg:province":"ON",
    "sg:tags":[
        "production",
        "grinding"
    ],
    "wof:name":"G & R Precision Grinding",
    "wof:placetype":"venue"
},
  "geometry": {"coordinates":[-79.696105957,43.693862915],"type":"Point"}
}