{
  "type": "Feature",
  "properties": {
    "addr:full":"305 Port Union Rd # 3 Scarborough ON M1C 2L5",
    "addr:housenumber":"305",
    "addr:postcode":"m1c 2l5",
    "addr:street":"Port Union Rd # 3",
    "iso:country":"CA",
    "sg:address":"305 Port Union Rd # 3",
    "sg:city":"Scarborough",
    "sg:classifiers":[
        {
            "category":"Personal",
            "subcategory":"Barber",
            "type":"Services"
        }
    ],
    "sg:phone":"+1 416 284 5562",
    "sg:postcode":"M1C 2L5",
    "sg:province":"ON",
    "wof:name":"Riviera Barber Shop",
    "wof:placetype":"venue"
},
  "geometry": {"coordinates":[-79.14083099370001,43.7899665833],"type":"Point"}
}