{
  "type": "Feature",
  "properties": {
    "addr:full":"1500 St Laurent Blvd Ottawa ON K1G 0Z8",
    "addr:housenumber":"1500",
    "addr:postcode":"k1g 0z8",
    "addr:street":"St Laurent Blvd",
    "iso:country":"CA",
    "sg:address":"1500 St Laurent Blvd",
    "sg:city":"Ottawa",
    "sg:classifiers":[
        {
            "category":"Government",
            "subcategory":"Office",
            "type":"Public Place"
        }
    ],
    "sg:phone":"+1 613 741 4390",
    "sg:postcode":"K1G 0Z8",
    "sg:province":"ON",
    "sg:tags":[
        "village"
    ],
    "wof:name":"O C Transpo",
    "wof:placetype":"venue"
},
  "geometry": {"coordinates":[-75.631607,45.413586],"type":"Point"}
}