{
  "type": "Feature",
  "properties": {
    "addr:full":"39 Point West Dr Winnipeg MB R3T 5G8",
    "addr:housenumber":"39",
    "addr:postcode":"r3t 5g8",
    "addr:street":"Point West Dr",
    "iso:country":"CA",
    "sg:address":"39 Point West Dr",
    "sg:city":"Winnipeg",
    "sg:classifiers":[
        {
            "category":"Manufacturing",
            "subcategory":"Wood Products",
            "type":"Manufacturing & Wholesale Goods"
        }
    ],
    "sg:phone":"+1 204 269 1855",
    "sg:postcode":"R3T 5G8",
    "sg:province":"MB",
    "sg:tags":[
        "scaffolding"
    ],
    "wof:name":"Spartan Agencies Ltd",
    "wof:placetype":"venue"
},
  "geometry": {"coordinates":[-97.17053199999999,49.777374],"type":"Point"}
}