{
  "type": "Feature",
  "properties": {
    "iso:country":"CA",
    "sg:address":"230 Canboro St",
    "sg:city":"Smithville",
    "sg:classifiers":[
        {
            "category":"Health Services",
            "subcategory":"Doctor",
            "type":"Services"
        }
    ],
    "sg:phone":"+1 905 957 3328",
    "sg:postcode":"L0R 2A0",
    "sg:province":"ON",
    "sg:tags":[
        "physician",
        "surgeon"
    ],
    "wof:name":"Bellaire, J MD",
    "wof:placetype":"venue"
},
  "geometry": {"coordinates":[-79.5479888916,43.095615387],"type":"Point"}
}