{
  "type": "Feature",
  "properties": {
    "addr:full":"Saint-Cesaire QC J0L 1T0",
    "addr:postcode":"j0l 1t0",
    "iso:country":"CA",
    "sg:city":"Saint-Cesaire",
    "sg:classifiers":[
        {
            "category":"Building & Trades",
            "subcategory":"Construction",
            "type":"Services"
        }
    ],
    "sg:phone":"+1 450 469 0205",
    "sg:postcode":"J0L 1T0",
    "sg:province":"QC",
    "sg:tags":[
        "general",
        "contractor"
    ],
    "wof:name":"Construction Cebel Inc",
    "wof:placetype":"venue"
},
  "geometry": {"coordinates":[-73.022255,45.411976],"type":"Point"}
}