{
  "type": "Feature",
  "properties": {
    "addr:full":"1119 Ch Kennedy Scott QC G0S 3G0",
    "addr:housenumber":"1119",
    "addr:postcode":"g0s 3g0",
    "addr:street":"Ch Kennedy",
    "iso:country":"CA",
    "sg:address":"1119 Ch Kennedy",
    "sg:city":"Scott",
    "sg:classifiers":[
        {
            "category":"Food & Beverages",
            "subcategory":"Groceries & Convenience Stores",
            "type":"Retail Goods"
        }
    ],
    "sg:phone":"+1 418 387 2102",
    "sg:postcode":"G0S 3G0",
    "sg:province":"QC",
    "wof:name":"Depanneur Tabagie Brochu Enr",
    "wof:placetype":"venue"
},
  "geometry": {"coordinates":[-71.07473,46.506287],"type":"Point"}
}