{
  "type": "Feature",
  "properties": {
    "addr:full":"10777 180 St NW Edmonton AB T5S 1G6",
    "addr:housenumber":"10777",
    "addr:postcode":"t5s 1g6",
    "addr:street":"180 St Nw",
    "iso:country":"CA",
    "sg:address":"10777 180 St NW",
    "sg:city":"Edmonton",
    "sg:classifiers":[
        {
            "category":"Retail",
            "subcategory":"Auto Repair",
            "type":"Services"
        }
    ],
    "sg:phone":"+1 780 484 0067",
    "sg:postcode":"T5S 1G6",
    "sg:province":"AB",
    "sg:tags":[
        "clutches",
        "brake"
    ],
    "wof:name":"Edmonton Brake & Clutch Ltd",
    "wof:placetype":"venue"
},
  "geometry": {"coordinates":[-113.630211,53.554367],"type":"Point"}
}