{
  "type": "Feature",
  "properties": {
    "addr:full":"Burlington ON L7P 4X4",
    "addr:postcode":"l7p 4x4",
    "iso:country":"CA",
    "sg:city":"Burlington",
    "sg:classifiers":[
        {
            "category":"Insurance",
            "subcategory":"Insurance Agent",
            "type":"Services"
        }
    ],
    "sg:phone":"+1 905 319 8240",
    "sg:postcode":"L7P 4X4",
    "sg:province":"ON",
    "wof:name":"O'Hallaoran Insurance Ltd",
    "wof:placetype":"venue"
},
  "geometry": {"coordinates":[-79.823364,43.365807],"type":"Point"}
}