{
  "type": "Feature",
  "properties": {
    "addr:full":"217 Main St Kelvington SK S0A 1W0",
    "addr:housenumber":"217",
    "addr:postcode":"s0a 1w0",
    "addr:street":"Main St",
    "iso:country":"CA",
    "sg:address":"217 Main St",
    "sg:city":"Kelvington",
    "sg:classifiers":[
        {
            "category":"Home & Garden",
            "subcategory":"Carpets & Floor Coverings",
            "type":"Retail Goods"
        }
    ],
    "sg:phone":"+1 306 327 4944",
    "sg:postcode":"S0A 1W0",
    "sg:province":"SK",
    "sg:tags":[
        "dealer",
        "rug"
    ],
    "wof:name":"G K Flooring & Paint Ctr",
    "wof:placetype":"venue"
},
  "geometry": {"coordinates":[-103.52950300000001,52.164566],"type":"Point"}
}