{
  "type": "Feature",
  "properties": {
    "iso:country":"CA",
    "sg:address":"830 Vickers St N",
    "sg:city":"Thunder Bay",
    "sg:classifiers":[
        {
            "category":"Retail",
            "subcategory":"Auto Repair",
            "type":"Services"
        }
    ],
    "sg:phone":"+1 807 622 9271",
    "sg:postcode":"P7C 4C1",
    "sg:province":"ON",
    "sg:tags":[
        "body",
        "automobile",
        "painting"
    ],
    "wof:name":"Frankie & Johnny's Auto Body",
    "wof:placetype":"venue"
},
  "geometry": {"coordinates":[-89.2509918213,48.3971977234],"type":"Point"}
}