{
  "type": "Feature",
  "properties": {
    "addr:full":"7508 Monastery Dr Niagara Falls ON L2H 3A7",
    "addr:housenumber":"7508",
    "addr:postcode":"l2h 3a7",
    "addr:street":"Monastery Dr",
    "iso:country":"CA",
    "sg:address":"7508 Monastery Dr",
    "sg:city":"Niagara Falls",
    "sg:classifiers":[
        {
            "category":"Food & Beverages",
            "subcategory":"Bakery",
            "type":"Retail Goods"
        }
    ],
    "sg:phone":"+1 905 358 3432",
    "sg:postcode":"L2H 3A7",
    "sg:province":"ON",
    "sg:tags":[
        "wedding",
        "supply"
    ],
    "wof:name":"Sweetart By Elizabeth",
    "wof:placetype":"venue"
},
  "geometry": {"coordinates":[-79.12256622309999,43.1205329895],"type":"Point"}
}