{
  "type": "Feature",
  "properties": {
    "iso:country":"CA",
    "sg:address":"3463 22nd Ave",
    "sg:city":"Prince George",
    "sg:classifiers":[
        {
            "category":"Autos & Motor Vehicles",
            "subcategory":"Auto Supplies",
            "type":"Retail Goods"
        }
    ],
    "sg:phone":"+1 250 612 0223",
    "sg:postcode":"V2N 1B4",
    "sg:province":"BC",
    "sg:tags":[
        "automobile",
        "parts"
    ],
    "wof:name":"Lordco Parts Ltd",
    "wof:placetype":"venue"
},
  "geometry": {"coordinates":[-122.78550720200001,53.9034614563],"type":"Point"}
}