{
  "type": "Feature",
  "properties": {
    "addr:full":"212 Queen St Fredericton NB E3B 1A7",
    "addr:housenumber":"212",
    "addr:postcode":"e3b 1a7",
    "addr:street":"Queen St",
    "iso:country":"CA",
    "sg:address":"212 Queen St",
    "sg:city":"Fredericton",
    "sg:classifiers":[
        {
            "category":"Social Services",
            "type":"Services"
        }
    ],
    "sg:phone":"+1 506 457 2684",
    "sg:postcode":"E3B 1A7",
    "sg:province":"NB",
    "sg:tags":[
        "counselor",
        "marriage",
        "family"
    ],
    "wof:name":"Wendi Nixon Counseling Svc",
    "wof:placetype":"venue"
},
  "geometry": {"coordinates":[-66.647277832,45.9645576477],"type":"Point"}
}