{
  "type": "Feature",
  "properties": {
    "addr:full":"Ottawa ON K1N 9C3",
    "addr:postcode":"k1n 9c3",
    "iso:country":"CA",
    "sg:city":"Ottawa",
    "sg:classifiers":[
        {
            "category":"Food & Beverages",
            "subcategory":"Bakery",
            "type":"Retail Goods"
        }
    ],
    "sg:phone":"+1 613 244 1906",
    "sg:postcode":"K1N 9C3",
    "sg:province":"ON",
    "sg:tags":[
        "baker"
    ],
    "wof:name":"Farm House",
    "wof:placetype":"venue"
},
  "geometry": {"coordinates":[-75.692497,45.427639],"type":"Point"}
}