{
  "type": "Feature",
  "properties": {
    "addr:full":"219 Rue DE LA Madone Mont-Laurier QC J9L 1R3",
    "addr:housenumber":"219",
    "addr:postcode":"j9l 1r3",
    "addr:street":"Rue De La Madone",
    "iso:country":"CA",
    "sg:address":"219 Rue DE LA Madone",
    "sg:city":"Mont-Laurier",
    "sg:classifiers":[
        {
            "category":"Retail",
            "subcategory":"Laundry & Dry Cleaning",
            "type":"Services"
        }
    ],
    "sg:phone":"+1 819 623 1635",
    "sg:postcode":"J9L 1R3",
    "sg:province":"QC",
    "sg:tags":[
        "cleaners"
    ],
    "wof:name":"Nettoyeur Meilleur & Martineau",
    "wof:placetype":"venue"
},
  "geometry": {"coordinates":[-75.5070266724,46.5495986938],"type":"Point"}
}