{
  "type": "Feature",
  "properties": {
    "addr:full":"401 2nd Ave N Saskatoon SK S7K 2C1",
    "addr:housenumber":"401",
    "addr:postcode":"s7k 2c1",
    "addr:street":"2Nd Ave N",
    "iso:country":"CA",
    "sg:address":"401 2nd Ave N",
    "sg:city":"Saskatoon",
    "sg:classifiers":[
        {
            "category":"Home & Garden",
            "subcategory":"Home Furnishings",
            "type":"Retail Goods"
        }
    ],
    "sg:phone":"+1 306 242 3266",
    "sg:postcode":"S7K 2C1",
    "sg:province":"SK",
    "sg:tags":[
        "lighting",
        "fixture"
    ],
    "wof:name":"Fandango Lighthouse",
    "wof:placetype":"venue"
},
  "geometry": {"coordinates":[-106.66166687,52.1337165833],"type":"Point"}
}