{
  "type": "Feature",
  "properties": {
    "addr:full":"4 3E Ave Saint-Raphael QC G0R 4C0",
    "addr:housenumber":"4",
    "addr:postcode":"g0r 4c0",
    "addr:street":"3E Ave",
    "iso:country":"CA",
    "sg:address":"4 3E Ave",
    "sg:city":"Saint-Raphael",
    "sg:classifiers":[
        {
            "category":"Building & Trades",
            "subcategory":"Electrical",
            "type":"Services"
        }
    ],
    "sg:phone":"+1 418 243 2074",
    "sg:postcode":"G0R 4C0",
    "sg:province":"QC",
    "sg:tags":[
        "electric",
        "contractor"
    ],
    "wof:name":"Joachim Laferriere Electr Inc",
    "wof:placetype":"venue"
},
  "geometry": {"coordinates":[-70.755081,46.795422],"type":"Point"}
}