{
  "type": "Feature",
  "properties": {
    "addr:full":"1076 Elm Tree Rd Arden ON K0H 1B0",
    "addr:housenumber":"1076",
    "addr:postcode":"k0h 1b0",
    "addr:street":"Elm Tree Rd",
    "iso:country":"CA",
    "sg:address":"1076 Elm Tree Rd",
    "sg:city":"Arden",
    "sg:classifiers":[
        {
            "category":"Organizations",
            "subcategory":"Religious Organization",
            "type":"Services"
        }
    ],
    "sg:phone":"+1 613 335 2474",
    "sg:postcode":"K0H 1B0",
    "sg:province":"ON",
    "sg:tags":[
        "church"
    ],
    "wof:name":"Arden United Church",
    "wof:placetype":"venue"
},
  "geometry": {"coordinates":[-76.928116,44.719299],"type":"Point"}
}