{
  "type": "Feature",
  "properties": {
    "addr:full":"8 Rue Deschenes Saint-Charles-Borromee QC J6E 1Z3",
    "addr:housenumber":"8",
    "addr:postcode":"j6e 1z3",
    "addr:street":"Rue Deschenes Saint-Charles-Borromee",
    "iso:country":"CA",
    "sg:address":"8 Rue Deschenes",
    "sg:city":"Saint-Charles-Borromee",
    "sg:classifiers":[
        {
            "category":"Banks & Credit Unions",
            "subcategory":"Investment Brokerage",
            "type":"Services"
        }
    ],
    "sg:phone":"+1 450 752 0000",
    "sg:postcode":"J6E 1Z3",
    "sg:province":"QC",
    "sg:tags":[
        "funds",
        "mutual"
    ],
    "wof:name":"Larrivee, Gaby",
    "wof:placetype":"venue"
},
  "geometry": {"coordinates":[-73.464279,46.045105],"type":"Point"}
}