{
  "type": "Feature",
  "properties": {
    "addr:full":"2763 Danforth Ave Toronto ON M4C 1L8",
    "addr:housenumber":"2763",
    "addr:postcode":"m4c 1l8",
    "addr:street":"Danforth Ave",
    "iso:country":"CA",
    "sg:address":"2763 Danforth Ave",
    "sg:city":"Toronto",
    "sg:classifiers":[
        {
            "category":"Shopping",
            "subcategory":"Optical Goods",
            "type":"Retail Goods"
        }
    ],
    "sg:phone":"+1 416 686 1591",
    "sg:postcode":"M4C 1L8",
    "sg:province":"ON",
    "sg:tags":[
        "optician"
    ],
    "wof:name":"Public Optical",
    "wof:placetype":"venue"
},
  "geometry": {"coordinates":[-79.297173,43.689049],"type":"Point"}
}