{
  "type": "Feature",
  "properties": {
    "addr:full":"11420 57E Av Montreal QC H1E 4B6",
    "addr:housenumber":"11420",
    "addr:postcode":"h1e 4b6",
    "addr:street":"57E Av",
    "iso:country":"CA",
    "sg:address":"11420 57E Av",
    "sg:city":"Montreal",
    "sg:classifiers":[
        {
            "category":"Manufacturing",
            "subcategory":"Apparel",
            "type":"Manufacturing & Wholesale Goods"
        }
    ],
    "sg:phone":"+1 514 494 7935",
    "sg:postcode":"H1E 4B6",
    "sg:province":"QC",
    "sg:tags":[
        "sewing",
        "contractor"
    ],
    "wof:name":"Moda Sportswear Inc",
    "wof:placetype":"venue"
},
  "geometry": {"coordinates":[-73.55680847169999,45.6435890198],"type":"Point"}
}