{
  "type": "Feature",
  "properties": {
    "addr:full":"77 Bloor St W Toronto ON M5S 1M2",
    "addr:housenumber":"77",
    "addr:postcode":"m5s 1m2",
    "addr:street":"Bloor St W",
    "iso:country":"CA",
    "sg:address":"77 Bloor St W",
    "sg:city":"Toronto",
    "sg:classifiers":[
        {
            "category":"Food & Beverages",
            "subcategory":"Groceries & Convenience Stores",
            "type":"Retail Goods"
        }
    ],
    "sg:phone":"+1 416 920 9429",
    "sg:postcode":"M5S 1M2",
    "sg:province":"ON",
    "wof:name":"Harrington's News & Tobacco",
    "wof:placetype":"venue"
},
  "geometry": {"coordinates":[-79.389847,43.669441],"type":"Point"}
}