{
  "type": "Feature",
  "properties": {
    "addr:full":"PO Box 1078 STN Main Coaldale AB T1M 1M9",
    "addr:housenumber":"po",
    "addr:postcode":"t1m 1m9",
    "addr:street":"Box 1078 Stn Main",
    "iso:country":"CA",
    "sg:address":"PO Box 1078 STN Main",
    "sg:city":"Coaldale",
    "sg:classifiers":[
        {
            "category":"Building & Trades",
            "subcategory":"Landscaping Services",
            "type":"Services"
        }
    ],
    "sg:phone":"+1 403 345 2716",
    "sg:postcode":"T1M 1M9",
    "sg:province":"AB",
    "sg:tags":[
        "nurseryman",
        "landscape",
        "contractor"
    ],
    "wof:name":"Simon Bos Nurseries Ltd",
    "wof:placetype":"venue"
},
  "geometry": {"coordinates":[-112.603607178,49.7315177917],"type":"Point"}
}