{
  "type": "Feature",
  "properties": {
    "addr:full":"Scarborough ON M1W 3Y3",
    "addr:postcode":"m1w 3y3",
    "iso:country":"CA",
    "sg:city":"Scarborough",
    "sg:classifiers":[
        {
            "category":"Travel",
            "subcategory":"Travel Agent",
            "type":"Entertainment"
        }
    ],
    "sg:phone":"+1 416 499 6688",
    "sg:postcode":"M1W 3Y3",
    "sg:province":"ON",
    "sg:tags":[
        "agency",
        "bureau"
    ],
    "wof:name":"Happy Holidays",
    "wof:placetype":"venue"
},
  "geometry": {"coordinates":[-79.335105896,43.8018188477],"type":"Point"}
}