{
  "type": "Feature",
  "properties": {
    "addr:full":"1861 117 Rte Val-David QC J0T 2N0",
    "addr:housenumber":"1861",
    "addr:postcode":"j0t 2n0",
    "addr:street":"117 Rte Val-David",
    "iso:country":"CA",
    "sg:address":"1861 117 Rte",
    "sg:city":"Val-David",
    "sg:classifiers":[
        {
            "category":"Professional",
            "subcategory":"Art Services",
            "type":"Services"
        }
    ],
    "sg:phone":"+1 819 322 5112",
    "sg:postcode":"J0T 2N0",
    "sg:province":"QC",
    "sg:tags":[
        "graphic",
        "designer"
    ],
    "wof:name":"Conception Graphique G",
    "wof:placetype":"venue"
},
  "geometry": {"coordinates":[-76.80175800000001,45.897766],"type":"Point"}
}