{
  "type": "Feature",
  "properties": {
    "iso:country":"CA",
    "sg:address":"3944 Rue Wellington",
    "sg:city":"Verdun",
    "sg:classifiers":[
        {
            "category":"Shopping",
            "subcategory":"Clothing, Apparel, & Fashions",
            "type":"Retail Goods"
        }
    ],
    "sg:phone":"+1 514 766 1701",
    "sg:postcode":"H4G 1V3",
    "sg:province":"QC",
    "sg:tags":[
        "item",
        "boutique"
    ],
    "wof:name":"Bellissimo",
    "wof:placetype":"venue"
},
  "geometry": {"coordinates":[-73.566696167,45.4643058777],"type":"Point"}
}