{
  "type": "Feature",
  "properties": {
    "addr:full":"301 17th St W Prince Albert SK S6V 3X6",
    "addr:housenumber":"301",
    "addr:postcode":"s6v 3x6",
    "addr:street":"17Th St",
    "iso:country":"CA",
    "sg:address":"301 17th St W",
    "sg:city":"Prince Albert",
    "sg:classifiers":[
        {
            "category":"Building & Trades",
            "subcategory":"Electrical",
            "type":"Services"
        }
    ],
    "sg:phone":"+1 306 922 3488",
    "sg:postcode":"S6V 3X6",
    "sg:province":"SK",
    "sg:tags":[
        "electric",
        "contractor"
    ],
    "wof:name":"Bill's Electric City Ltd",
    "wof:placetype":"venue"
},
  "geometry": {"coordinates":[-105.76259613000001,53.1972427368],"type":"Point"}
}