{
  "type": "Feature",
  "properties": {
    "iso:country":"CA",
    "sg:address":"549 Wilson Hts",
    "sg:city":"North York",
    "sg:classifiers":[
        {
            "category":"Health Services",
            "subcategory":"Medical Lab",
            "type":"Services"
        }
    ],
    "sg:phone":"+1 416 748 0219",
    "sg:postcode":"M3H 2V7",
    "sg:province":"ON",
    "wof:name":"Michael Dragonetti Denture",
    "wof:placetype":"venue"
},
  "geometry": {"coordinates":[-79.44770812989999,43.7343330383],"type":"Point"}
}