{
  "type": "Feature",
  "properties": {
    "addr:full":"Tom St Buffalo Narrows SK S0M 0J0",
    "addr:postcode":"s0m 0j0",
    "addr:street":"Tom St",
    "iso:country":"CA",
    "sg:address":"Tom St",
    "sg:city":"Buffalo Narrows",
    "sg:classifiers":[
        {
            "category":"Arena",
            "subcategory":"Sports Club",
            "type":"Entertainment"
        }
    ],
    "sg:phone":"+1 306 235 4451",
    "sg:postcode":"S0M 0J0",
    "sg:province":"SK",
    "sg:tags":[
        "athletic",
        "fields",
        "stadium"
    ],
    "wof:name":"Lakeview Complex Arena",
    "wof:placetype":"venue"
},
  "geometry": {"coordinates":[-108.48188,55.865105],"type":"Point"}
}