{
  "type": "Feature",
  "properties": {
    "addr:full":"4535 Gregoire Rd Russell ON K4R 1E5",
    "addr:housenumber":"4535",
    "addr:postcode":"k4r 1e5",
    "addr:street":"Gregoire Rd",
    "iso:country":"CA",
    "sg:address":"4535 Gregoire Rd",
    "sg:city":"Russell",
    "sg:classifiers":[
        {
            "category":"Social Services",
            "type":"Services"
        }
    ],
    "sg:phone":"+1 613 445 5522",
    "sg:postcode":"K4R 1E5",
    "sg:province":"ON",
    "sg:tags":[
        "senior",
        "citizen"
    ],
    "wof:name":"Villa Sainte Therese",
    "wof:placetype":"venue"
},
  "geometry": {"coordinates":[-75.35633900000001,45.187447],"type":"Point"}
}