{
  "type": "Feature",
  "properties": {
    "addr:full":"Aurora ON L4G 1N9",
    "addr:postcode":"l4g 1n9",
    "iso:country":"CA",
    "sg:city":"Aurora",
    "sg:classifiers":[
        {
            "category":"Insurance",
            "subcategory":"Insurance Agent",
            "type":"Services"
        }
    ],
    "sg:phone":"+1 905 841 7703",
    "sg:postcode":"L4G 1N9",
    "sg:province":"ON",
    "wof:name":"Allstate Insurance CO",
    "wof:placetype":"venue"
},
  "geometry": {"coordinates":[-79.468704,44.003551],"type":"Point"}
}