{
  "type": "Feature",
  "properties": {
    "addr:full":"553 Upper Wentworth St Hamilton ON L9A 4T8",
    "addr:housenumber":"553",
    "addr:postcode":"l9a 4t8",
    "addr:street":"Upper Wentworth St",
    "iso:country":"CA",
    "sg:address":"553 Upper Wentworth St",
    "sg:city":"Hamilton",
    "sg:classifiers":[
        {
            "category":"Personal",
            "subcategory":"Beauty Salon",
            "type":"Services"
        }
    ],
    "sg:phone":"+1 905 383 6130",
    "sg:postcode":"L9A 4T8",
    "sg:province":"ON",
    "wof:name":"Jacqueline's Beauty Salon",
    "wof:placetype":"venue"
},
  "geometry": {"coordinates":[-79.856888,43.234749],"type":"Point"}
}