{
  "type": "Feature",
  "properties": {
    "addr:full":"5102 50 Ave Camrose AB T4V 0S7",
    "addr:housenumber":"5102",
    "addr:postcode":"t4v 0s7",
    "addr:street":"50 Ave",
    "iso:country":"CA",
    "sg:address":"5102 50 Ave",
    "sg:city":"Camrose",
    "sg:classifiers":[
        {
            "category":"Banks & Credit Unions",
            "subcategory":"Investment Brokerage",
            "type":"Services"
        }
    ],
    "sg:phone":"+1 780 672 8776",
    "sg:postcode":"T4V 0S7",
    "sg:province":"AB",
    "wof:name":"Rbc Dominion Securities Inc",
    "wof:placetype":"venue"
},
  "geometry": {"coordinates":[-112.826759,53.022572],"type":"Point"}
}