{
  "type": "Feature",
  "properties": {
    "iso:country":"CA",
    "sg:address":"225 Senlac Rd",
    "sg:city":"North York",
    "sg:classifiers":[
        {
            "category":"Education",
            "subcategory":"School",
            "type":"Public Place"
        }
    ],
    "sg:phone":"+1 416 395 2973",
    "sg:postcode":"M2R 1P6",
    "sg:province":"ON",
    "wof:name":"Willowdale Middle School",
    "wof:placetype":"venue"
},
  "geometry": {"coordinates":[-79.42668151860001,43.7690734863],"type":"Point"}
}