{
  "type": "Feature",
  "properties": {
    "iso:country":"CA",
    "sg:address":"1899 Merivale Rd",
    "sg:city":"Nepean",
    "sg:classifiers":[
        {
            "category":"Retail",
            "subcategory":"Auto Repair",
            "type":"Services"
        }
    ],
    "sg:phone":"+1 613 228 7878",
    "sg:postcode":"K2G 1E7",
    "sg:province":"ON",
    "sg:tags":[
        "automobile",
        "rustproofing",
        "undercoating"
    ],
    "wof:name":"Antirouille Metropolitain Inc",
    "wof:placetype":"venue"
},
  "geometry": {"coordinates":[-75.7215270996,45.3308105469],"type":"Point"}
}