{
  "type": "Feature",
  "properties": {
    "iso:country":"CA",
    "sg:city":"Vancouver",
    "sg:classifiers":[
        {
            "category":"Professional",
            "subcategory":"Employment Agencies",
            "type":"Services"
        }
    ],
    "sg:phone":"+1 604 685 0609",
    "sg:postcode":"V6C 2T5",
    "sg:province":"BC",
    "sg:tags":[
        "consultant",
        "search",
        "executive"
    ],
    "wof:name":"Galt Global Recruiting",
    "wof:placetype":"venue"
},
  "geometry": {"coordinates":[-123.117279053,49.2843551636],"type":"Point"}
}