{
  "type": "Feature",
  "properties": {
    "iso:country":"CA",
    "sg:address":"3504 80 Ave SE",
    "sg:city":"Calgary",
    "sg:classifiers":[
        {
            "category":"Manufacturing",
            "subcategory":"Tools & Machinery",
            "type":"Manufacturing & Wholesale Goods"
        }
    ],
    "sg:phone":"+1 403 720 2888",
    "sg:postcode":"T2C 1J3",
    "sg:province":"AB",
    "sg:tags":[
        "spindle"
    ],
    "wof:name":"Spiral Spindles & Turnings",
    "wof:placetype":"venue"
},
  "geometry": {"coordinates":[-113.983757019,50.9800682068],"type":"Point"}
}