{
  "type": "Feature",
  "properties": {
    "iso:country":"CA",
    "sg:address":"5337 50th Ave",
    "sg:city":"Vegreville",
    "sg:classifiers":[
        {
            "category":"Restaurant",
            "type":"Food & Drink"
        }
    ],
    "sg:phone":"+1 780 632 6411",
    "sg:postcode":"T9C 1M9",
    "sg:province":"AB",
    "wof:name":"Albert's Family Restaurant",
    "wof:placetype":"venue"
},
  "geometry": {"coordinates":[-112.061683655,53.49817276],"type":"Point"}
}