{
  "type": "Feature",
  "properties": {
    "addr:full":"280 Townsend St Sydney NS B1P 5E9",
    "addr:housenumber":"280",
    "addr:postcode":"b1p 5e9",
    "addr:street":"Townsend St",
    "iso:country":"CA",
    "sg:address":"280 Townsend St",
    "sg:city":"Sydney",
    "sg:classifiers":[
        {
            "category":"Manufacturing",
            "subcategory":"Tools & Machinery",
            "type":"Manufacturing & Wholesale Goods"
        }
    ],
    "sg:phone":"+1 902 539 1716",
    "sg:postcode":"B1P 5E9",
    "sg:province":"NS",
    "sg:tags":[
        "equipment",
        "register",
        "computer",
        "dealer",
        "cash"
    ],
    "wof:name":"Merritt Business Machines Ltd",
    "wof:placetype":"venue"
},
  "geometry": {"coordinates":[-60.185749054,46.1356925964],"type":"Point"}
}