{
  "type": "Feature",
  "properties": {
    "addr:full":"2271 Rosser Ave Burnaby BC V5C 5E3",
    "addr:housenumber":"2271",
    "addr:postcode":"v5c 5e3",
    "addr:street":"Rosser Ave",
    "iso:country":"CA",
    "sg:address":"2271 Rosser Ave",
    "sg:city":"Burnaby",
    "sg:classifiers":[
        {
            "category":"Manufacturing",
            "subcategory":"Metals",
            "type":"Manufacturing & Wholesale Goods"
        }
    ],
    "sg:phone":"+1 604 291 6491",
    "sg:postcode":"V5C 5E3",
    "sg:province":"BC",
    "sg:tags":[
        "tank"
    ],
    "wof:name":"Canadian Stebbins Engrg & Mfg",
    "wof:placetype":"venue"
},
  "geometry": {"coordinates":[-123.00614166299999,49.2639274597],"type":"Point"}
}