{
  "type": "Feature",
  "properties": {
    "addr:full":"318 Erie St S Leamington ON N8H 3C5",
    "addr:housenumber":"318",
    "addr:postcode":"n8h 3c5",
    "addr:street":"Erie St S",
    "iso:country":"CA",
    "sg:address":"318 Erie St S",
    "sg:city":"Leamington",
    "sg:classifiers":[
        {
            "category":"Retail",
            "subcategory":"Funeral Services",
            "type":"Services"
        }
    ],
    "sg:phone":"+1 519 326 8423",
    "sg:postcode":"N8H 3C5",
    "sg:province":"ON",
    "sg:tags":[
        "director"
    ],
    "wof:name":"Hammond Funeral Home",
    "wof:placetype":"venue"
},
  "geometry": {"coordinates":[-82.6008987427,42.0342597961],"type":"Point"}
}