{
  "type": "Feature",
  "properties": {
    "addr:full":"430 Topsail Rd St. John's NL A1E 4N1",
    "addr:housenumber":"430",
    "addr:postcode":"a1e 4n1",
    "addr:street":"Topsail Rd",
    "iso:country":"CA",
    "sg:address":"430 Topsail Rd",
    "sg:city":"St. John's",
    "sg:classifiers":[
        {
            "category":"Shopping",
            "type":"Retail Goods"
        }
    ],
    "sg:phone":"+1 709 368 7771",
    "sg:postcode":"A1E 4N1",
    "sg:province":"NL",
    "sg:tags":[
        "picture",
        "frame",
        "art",
        "gallery",
        "dealer"
    ],
    "wof:name":"Decor Framing & Gallery",
    "wof:placetype":"venue"
},
  "geometry": {"coordinates":[-52.7516555786,47.5327682495],"type":"Point"}
}