{
  "type": "Feature",
  "properties": {
    "addr:full":"349 13th St E Prince Albert SK S6V 1C8",
    "addr:housenumber":"349",
    "addr:postcode":"s6v 1c8",
    "addr:street":"13Th St",
    "iso:country":"CA",
    "sg:address":"349 13th St E",
    "sg:city":"Prince Albert",
    "sg:classifiers":[
        {
            "category":"Retail",
            "subcategory":"Laundry & Dry Cleaning",
            "type":"Services"
        }
    ],
    "sg:phone":"+1 306 764 6262",
    "sg:postcode":"S6V 1C8",
    "sg:province":"SK",
    "sg:tags":[
        "cleaners"
    ],
    "wof:name":"Dresswell Dry Cleaners",
    "wof:placetype":"venue"
},
  "geometry": {"coordinates":[-105.745956421,53.2011299133],"type":"Point"}
}