{
  "type": "Feature",
  "properties": {
    "iso:country":"CA",
    "sg:address":"20 Wellington St E",
    "sg:city":"Aurora",
    "sg:classifiers":[
        {
            "category":"Professional",
            "subcategory":"Management & Consulting",
            "type":"Services"
        }
    ],
    "sg:phone":"+1 905 841 7409",
    "sg:postcode":"L4G 1H5",
    "sg:province":"ON",
    "sg:tags":[
        "consultant",
        "freight"
    ],
    "wof:name":"Fleetwood Freight Consultants",
    "wof:placetype":"venue"
},
  "geometry": {"coordinates":[-79.466705,43.999973],"type":"Point"}
}