{
  "type": "Feature",
  "properties": {
    "addr:full":"20 Rue Alphonse-Grenier Saint-Liguori QC J0K 2X0",
    "addr:housenumber":"20",
    "addr:postcode":"j0k 2x0",
    "addr:street":"Rue Alphonse-Grenier",
    "iso:country":"CA",
    "sg:address":"20 Rue Alphonse-Grenier",
    "sg:city":"Saint-Liguori",
    "sg:classifiers":[
        {
            "category":"Freight",
            "type":"Transportation"
        }
    ],
    "sg:phone":"+1 450 752 1174",
    "sg:postcode":"J0K 2X0",
    "sg:province":"QC",
    "sg:tags":[
        "automobile",
        "transporter",
        "drive",
        "trucking"
    ],
    "wof:name":"Transports DE Machinerie Mayer",
    "wof:placetype":"venue"
},
  "geometry": {"coordinates":[-73.5654296875,46.012462616],"type":"Point"}
}