{
  "type": "Feature",
  "properties": {
    "iso:country":"CA",
    "sg:address":"6002 Rue Alphonse",
    "sg:city":"Brossard",
    "sg:classifiers":[
        {
            "category":"Personal",
            "subcategory":"Beauty Salon",
            "type":"Services"
        }
    ],
    "sg:phone":"+1 450 445 0610",
    "sg:postcode":"J4Z 1C3",
    "sg:province":"QC",
    "wof:name":"Studio Atmosphair",
    "wof:placetype":"venue"
},
  "geometry": {"coordinates":[-73.4613876343,45.4802703857],"type":"Point"}
}