{
  "type": "Feature",
  "properties": {
    "addr:full":"1309 Main St W Hamilton ON L8S 1C5",
    "addr:housenumber":"1309",
    "addr:postcode":"l8s 1c5",
    "addr:street":"Main St W",
    "iso:country":"CA",
    "sg:address":"1309 Main St W",
    "sg:city":"Hamilton",
    "sg:classifiers":[
        {
            "category":"Manufacturing",
            "subcategory":"Printing",
            "type":"Manufacturing & Wholesale Goods"
        }
    ],
    "sg:phone":"+1 905 526 1762",
    "sg:postcode":"L8S 1C5",
    "sg:province":"ON",
    "sg:tags":[
        "printer",
        "duplicating",
        "copying"
    ],
    "wof:name":"Sure Print & Copy Ctr",
    "wof:placetype":"venue"
},
  "geometry": {"coordinates":[-79.91790008540001,43.2576217651],"type":"Point"}
}