{
  "type": "Feature",
  "properties": {
    "iso:country":"CA",
    "sg:address":"5019 4 Ave",
    "sg:city":"Edson",
    "sg:classifiers":[
        {
            "category":"Shopping",
            "subcategory":"Books",
            "type":"Retail Goods"
        }
    ],
    "sg:phone":"+1 780 723 7565",
    "sg:postcode":"T7E 1T5",
    "sg:province":"AB",
    "sg:tags":[
        "dealer"
    ],
    "wof:name":"Shining Stars Book & Gift Shop",
    "wof:placetype":"venue"
},
  "geometry": {"coordinates":[-116.432609558,53.5829696655],"type":"Point"}
}