{
  "type": "Feature",
  "properties": {
    "iso:country":"CA",
    "sg:address":"631 Av Chapdelaine S",
    "sg:city":"Alma",
    "sg:classifiers":[
        {
            "category":"Building & Trades",
            "subcategory":"Construction",
            "type":"Services"
        }
    ],
    "sg:phone":"+1 418 668 4444",
    "sg:postcode":"G8B 2N8",
    "sg:province":"QC",
    "sg:tags":[
        "plastering",
        "contractor"
    ],
    "wof:name":"Verreault, Bruno",
    "wof:placetype":"venue"
},
  "geometry": {"coordinates":[-71.6398468018,48.5394935608],"type":"Point"}
}