{
  "type": "Feature",
  "properties": {
    "addr:full":"350 Deer Park Ave Kimberley BC V1A 2J6",
    "addr:housenumber":"350",
    "addr:postcode":"v1a 2j6",
    "addr:street":"Deer Park Ave",
    "iso:country":"CA",
    "sg:address":"350 Deer Park Ave",
    "sg:city":"Kimberley",
    "sg:classifiers":[
        {
            "category":"Manufacturing",
            "subcategory":"Glass & Minerals",
            "type":"Manufacturing & Wholesale Goods"
        }
    ],
    "sg:phone":"+1 250 427 5243",
    "sg:postcode":"V1A 2J6",
    "sg:province":"BC",
    "sg:tags":[
        "concrete",
        "brick",
        "ornament",
        "garden",
        "block"
    ],
    "wof:name":"Halls Ornamental Concrete",
    "wof:placetype":"venue"
},
  "geometry": {"coordinates":[-115.984421,49.684555],"type":"Point"}
}