{
  "type": "Feature",
  "properties": {
    "addr:full":"406 Pth 5 W Roblin MB R0L 1P0",
    "addr:housenumber":"406;5",
    "addr:postcode":"r0l 1p0",
    "addr:street":"Pth;W Roblin",
    "iso:country":"CA",
    "sg:address":"406 Pth 5 W",
    "sg:city":"Roblin",
    "sg:classifiers":[
        {
            "category":"Organizations",
            "subcategory":"Religious Organization",
            "type":"Services"
        }
    ],
    "sg:phone":"+1 204 937 2375",
    "sg:postcode":"R0L 1P0",
    "sg:province":"MB",
    "sg:tags":[
        "church"
    ],
    "wof:name":"Ukrainina Orthodox Church",
    "wof:placetype":"venue"
},
  "geometry": {"coordinates":[-101.352851868,51.2281532288],"type":"Point"}
}