{
  "type": "Feature",
  "properties": {
    "addr:full":"1021 Railway Ave Canmore AB T1W 1P3",
    "addr:housenumber":"1021",
    "addr:postcode":"t1w 1p3",
    "addr:street":"Railway Ave",
    "iso:country":"CA",
    "sg:address":"1021 Railway Ave",
    "sg:city":"Canmore",
    "sg:classifiers":[
        {
            "category":"Local Transit",
            "type":"Transportation"
        }
    ],
    "sg:phone":"+1 403 678 6199",
    "sg:postcode":"T1W 1P3",
    "sg:province":"AB",
    "sg:tags":[
        "government",
        "ambulance"
    ],
    "wof:name":"Canmore Emergency Svc",
    "wof:placetype":"venue"
},
  "geometry": {"coordinates":[-115.356026,51.09082],"type":"Point"}
}