{
  "type": "Feature",
  "properties": {
    "addr:full":"3845 Dougall Ave Windsor ON N9G 1X3",
    "addr:housenumber":"3845",
    "addr:postcode":"n9g 1x3",
    "addr:street":"Dougall Ave",
    "iso:country":"CA",
    "sg:address":"3845 Dougall Ave",
    "sg:city":"Windsor",
    "sg:classifiers":[
        {
            "category":"Food & Beverages",
            "subcategory":"Groceries & Convenience Stores",
            "type":"Retail Goods"
        }
    ],
    "sg:phone":"+1 519 969 1521",
    "sg:postcode":"N9G 1X3",
    "sg:province":"ON",
    "sg:tags":[
        "variety"
    ],
    "wof:name":"Mac's Convenience Stores Ltd",
    "wof:placetype":"venue"
},
  "geometry": {"coordinates":[-83.003197,42.256035],"type":"Point"}
}