{
  "type": "Feature",
  "properties": {
    "addr:full":"280 Plains Rd W Burlington ON L7T 1G4",
    "addr:housenumber":"280",
    "addr:postcode":"l7t 1g4",
    "addr:street":"Plains Rd W",
    "iso:country":"CA",
    "sg:address":"280 Plains Rd W",
    "sg:city":"Burlington",
    "sg:classifiers":[
        {
            "category":"Health Services",
            "subcategory":"Chiropractor",
            "type":"Services"
        }
    ],
    "sg:phone":"+1 905 527 5573",
    "sg:postcode":"L7T 1G4",
    "sg:province":"ON",
    "wof:name":"Healthview Chiropractic Wllnss",
    "wof:placetype":"venue"
},
  "geometry": {"coordinates":[-79.8620681763,43.299369812],"type":"Point"}
}