{
  "type": "Feature",
  "properties": {
    "addr:full":"5245 Chute Lake Rd Kelowna BC V1W 4L6",
    "addr:housenumber":"5245",
    "addr:postcode":"v1w 4l6",
    "addr:street":"Chute Lake Rd",
    "iso:country":"CA",
    "sg:address":"5245 Chute Lake Rd",
    "sg:city":"Kelowna",
    "sg:classifiers":[
        {
            "category":"Building & Trades",
            "subcategory":"Landscaping Services",
            "type":"Services"
        }
    ],
    "sg:phone":"+1 250 764 2232",
    "sg:postcode":"V1W 4L6",
    "sg:province":"BC",
    "sg:tags":[
        "lawn",
        "contractor",
        "landscape",
        "maintenance",
        "grounds"
    ],
    "wof:name":"Artscapes",
    "wof:placetype":"venue"
},
  "geometry": {"coordinates":[-119.506248,49.795506],"type":"Point"}
}