{
  "type": "Feature",
  "properties": {
    "addr:full":"Kelowna BC V1Y 6Z2",
    "addr:postcode":"v1y 6z2",
    "iso:country":"CA",
    "sg:city":"Kelowna",
    "sg:classifiers":[
        {
            "category":"Professional",
            "subcategory":"Lawyer & Legal Services",
            "type":"Services"
        }
    ],
    "sg:phone":"+1 250 763 6776",
    "sg:postcode":"V1Y 6Z2",
    "sg:province":"BC",
    "sg:tags":[
        "attorney"
    ],
    "wof:name":"Mc Allister Law Office",
    "wof:placetype":"venue"
},
  "geometry": {"coordinates":[-119.4923172,49.8918609619],"type":"Point"}
}