{
  "type": "Feature",
  "properties": {
    "addr:full":"1st St E Briercrest SK S0H 0K0",
    "addr:postcode":"s0h 0k0",
    "addr:street":"1St St;Briercrest",
    "iso:country":"CA",
    "sg:address":"1st St E",
    "sg:city":"Briercrest",
    "sg:classifiers":[
        {
            "category":"Organizations",
            "subcategory":"Religious Organization",
            "type":"Services"
        }
    ],
    "sg:phone":"+1 306 799 2033",
    "sg:postcode":"S0H 0K0",
    "sg:province":"SK",
    "sg:tags":[
        "church"
    ],
    "wof:name":"United Church",
    "wof:placetype":"venue"
},
  "geometry": {"coordinates":[-105.261826,50.165936],"type":"Point"}
}