{
  "type": "Feature",
  "properties": {
    "iso:country":"CA",
    "sg:address":"366 Dalhousie St",
    "sg:city":"Ottawa",
    "sg:classifiers":[
        {
            "category":"Restaurant",
            "type":"Food & Drink"
        }
    ],
    "sg:phone":"+1 613 241 6582",
    "sg:postcode":"K1N 7G3",
    "sg:province":"ON",
    "wof:name":"Takara Japanese Restaurant",
    "wof:placetype":"venue"
},
  "geometry": {"coordinates":[-75.6902999878,45.4275169373],"type":"Point"}
}