{
  "type": "Feature",
  "properties": {
    "addr:full":"1500 Rte 202 Franklin QC J0S 1E0",
    "addr:housenumber":"1500",
    "addr:postcode":"j0s 1e0",
    "addr:street":"Rte 202",
    "iso:country":"CA",
    "sg:address":"1500 Rte 202",
    "sg:city":"Franklin",
    "sg:classifiers":[
        {
            "category":"Freight",
            "type":"Transportation"
        }
    ],
    "sg:phone":"+1 450 827 2547",
    "sg:postcode":"J0S 1E0",
    "sg:province":"QC",
    "sg:tags":[
        "trucking"
    ],
    "wof:name":"Blair Ck Inc",
    "wof:placetype":"venue"
},
  "geometry": {"coordinates":[-73.9334106445,45.0279083252],"type":"Point"}
}