{
  "type": "Feature",
  "properties": {
    "iso:country":"CA",
    "sg:address":"80 Adair Ave S",
    "sg:city":"Hamilton",
    "sg:classifiers":[
        {
            "category":"Building & Trades",
            "subcategory":"Plumbing",
            "type":"Services"
        }
    ],
    "sg:phone":"+1 905 549 4438",
    "sg:postcode":"L8K 3S5",
    "sg:province":"ON",
    "sg:tags":[
        "sheet",
        "work",
        "metal",
        "contractor"
    ],
    "wof:name":"Mike Fournier Custom Sheet Mtl",
    "wof:placetype":"venue"
},
  "geometry": {"coordinates":[-79.7912979126,43.2335472107],"type":"Point"}
}