{
  "type": "Feature",
  "properties": {
    "iso:country":"CA",
    "sg:address":"337 Trafalgar Rd",
    "sg:city":"Oakville",
    "sg:classifiers":[
        {
            "category":"Education",
            "subcategory":"School",
            "type":"Public Place"
        }
    ],
    "sg:phone":"+1 905 844 0372",
    "sg:postcode":"L6J 3H3",
    "sg:province":"ON",
    "wof:name":"Mac Lachlan College",
    "wof:placetype":"venue"
},
  "geometry": {"coordinates":[-79.675598,43.452251],"type":"Point"}
}