{
  "type": "Feature",
  "properties": {
    "addr:full":"153 Lake Shore Dr Etobicoke ON M8V 2A1",
    "addr:housenumber":"153",
    "addr:postcode":"m8v 2a1",
    "addr:street":"Lake Shore Dr",
    "iso:country":"CA",
    "sg:address":"153 Lake Shore Dr",
    "sg:city":"Etobicoke",
    "sg:classifiers":[
        {
            "category":"Sports & Exercise",
            "subcategory":"Bowling",
            "type":"Entertainment"
        }
    ],
    "sg:phone":"+1 416 259 8776",
    "sg:postcode":"M8V 2A1",
    "sg:province":"ON",
    "sg:tags":[
        "center"
    ],
    "wof:name":"New Toronto Lawn Bowling Club",
    "wof:placetype":"venue"
},
  "geometry": {"coordinates":[-79.505219,43.594704],"type":"Point"}
}