{
  "type": "Feature",
  "properties": {
    "addr:full":"7 Industrial Dr Chesterville ON K0C 1H0",
    "addr:housenumber":"7",
    "addr:postcode":"k0c 1h0",
    "addr:street":"Industrial Dr",
    "iso:country":"CA",
    "sg:address":"7 Industrial Dr",
    "sg:city":"Chesterville",
    "sg:classifiers":[
        {
            "category":"Personal",
            "subcategory":"Beauty Salon",
            "type":"Services"
        }
    ],
    "sg:phone":"+1 613 448 3674",
    "sg:postcode":"K0C 1H0",
    "sg:province":"ON",
    "wof:name":"Chesterville Hair Studio",
    "wof:placetype":"venue"
},
  "geometry": {"coordinates":[-75.2384185791,45.1024703979],"type":"Point"}
}