{
  "type": "Feature",
  "properties": {
    "iso:country":"CA",
    "sg:city":"Winnipeg",
    "sg:classifiers":[
        {
            "category":"Real Estate",
            "subcategory":"Real Estate Operator",
            "type":"Services"
        }
    ],
    "sg:phone":"+1 204 623 2982",
    "sg:postcode":"R2W 0Y7",
    "sg:province":"MB",
    "sg:tags":[
        "apartment"
    ],
    "wof:name":"Cathedral Apartments",
    "wof:placetype":"venue"
},
  "geometry": {"coordinates":[-97.1429595947,49.9295005798],"type":"Point"}
}