{
  "type": "Feature",
  "properties": {
    "addr:full":"1300 Marleau Ave Cornwall ON K6H 2W8",
    "addr:housenumber":"1300",
    "addr:postcode":"k6h 2w8",
    "addr:street":"Marleau Ave",
    "iso:country":"CA",
    "sg:address":"1300 Marleau Ave",
    "sg:city":"Cornwall",
    "sg:classifiers":[
        {
            "category":"Retail",
            "subcategory":"Auto Repair",
            "type":"Services"
        }
    ],
    "sg:phone":"+1 613 933 7722",
    "sg:postcode":"K6H 2W8",
    "sg:province":"ON",
    "sg:tags":[
        "repairing",
        "automobile"
    ],
    "wof:name":"Jiffy Auto Svc",
    "wof:placetype":"venue"
},
  "geometry": {"coordinates":[-74.711563,45.035938],"type":"Point"}
}