{
  "type": "Feature",
  "properties": {
    "addr:full":"4660 Hastings St Burnaby BC V5C 2K5",
    "addr:housenumber":"4660",
    "addr:postcode":"v5c 2k5",
    "addr:street":"Hastings St",
    "iso:country":"CA",
    "sg:address":"4660 Hastings St",
    "sg:city":"Burnaby",
    "sg:classifiers":[
        {
            "category":"Restaurant",
            "type":"Food & Drink"
        }
    ],
    "sg:phone":"+1 604 298 7252",
    "sg:postcode":"V5C 2K5",
    "sg:province":"BC",
    "wof:name":"Romana Pizza & Steak House Ltd",
    "wof:placetype":"venue"
},
  "geometry": {"coordinates":[-122.998580933,49.2807846069],"type":"Point"}
}