{
  "type": "Feature",
  "properties": {
    "addr:full":"Penticton BC V2A 1H5",
    "addr:postcode":"v2a 1h5",
    "iso:country":"CA",
    "sg:city":"Penticton",
    "sg:classifiers":[
        {
            "category":"Recreation",
            "type":"Entertainment"
        }
    ],
    "sg:phone":"+1 250 492 2853",
    "sg:postcode":"V2A 1H5",
    "sg:province":"BC",
    "sg:tags":[
        "hall",
        "auditorium"
    ],
    "wof:name":"Penticton Yacht & Tennis Club",
    "wof:placetype":"venue"
},
  "geometry": {"coordinates":[-119.584289551,49.5047912598],"type":"Point"}
}