{
  "type": "Feature",
  "properties": {
    "addr:full":"Aylesford NS B0P 1C0",
    "addr:postcode":"b0p 1c0",
    "iso:country":"CA",
    "sg:city":"Aylesford",
    "sg:classifiers":[
        {
            "category":"Organizations",
            "subcategory":"Religious Organization",
            "type":"Services"
        }
    ],
    "sg:phone":"+1 902 847 9624",
    "sg:postcode":"B0P 1C0",
    "sg:province":"NS",
    "sg:tags":[
        "church"
    ],
    "wof:name":"United Church Aylesford",
    "wof:placetype":"venue"
},
  "geometry": {"coordinates":[-64.837524,45.027794],"type":"Point"}
}