{
  "type": "Feature",
  "properties": {
    "addr:full":"Gravenhurst ON P1P 1T7",
    "addr:postcode":"p1p 1t7",
    "iso:country":"CA",
    "sg:city":"Gravenhurst",
    "sg:classifiers":[
        {
            "category":"Wholesale",
            "subcategory":"Construction Materials",
            "type":"Manufacturing & Wholesale Goods"
        }
    ],
    "sg:phone":"+1 705 687 3425",
    "sg:postcode":"P1P 1T7",
    "sg:province":"ON",
    "sg:tags":[
        "building",
        "plywood",
        "veneer"
    ],
    "wof:name":"Silvaplex",
    "wof:placetype":"venue"
},
  "geometry": {"coordinates":[-79.3736953735,44.920841217],"type":"Point"}
}