{
  "type": "Feature",
  "properties": {
    "addr:full":"2598 Eglinton Ave E Scarborough ON M1K 2R9",
    "addr:housenumber":"2598",
    "addr:postcode":"m1k 2r9",
    "addr:street":"Eglinton Ave E",
    "iso:country":"CA",
    "sg:address":"2598 Eglinton Ave E",
    "sg:city":"Scarborough",
    "sg:classifiers":[
        {
            "category":"Shopping",
            "subcategory":"Department Store",
            "type":"Retail Goods"
        }
    ],
    "sg:phone":"+1 416 269 8306",
    "sg:postcode":"M1K 2R9",
    "sg:province":"ON",
    "sg:tags":[
        "shop"
    ],
    "wof:name":"Gilder Dollar & Variety",
    "wof:placetype":"venue"
},
  "geometry": {"coordinates":[-79.253021,43.735809],"type":"Point"}
}