{
  "type": "Feature",
  "properties": {
    "iso:country":"CA",
    "sg:address":"338 Main St E",
    "sg:city":"Hawkesbury",
    "sg:classifiers":[
        {
            "category":"Shopping",
            "subcategory":"Shoes",
            "type":"Retail Goods"
        }
    ],
    "sg:phone":"+1 613 632 2027",
    "sg:postcode":"K6A 1A5",
    "sg:province":"ON",
    "wof:name":"Pitt Shoe Store",
    "wof:placetype":"venue"
},
  "geometry": {"coordinates":[-74.6064147949,45.6101264954],"type":"Point"}
}