{
  "type": "Feature",
  "properties": {
    "addr:full":"2320 Rue Dubose Jonquiere QC G7S 5G5",
    "addr:housenumber":"2320",
    "addr:postcode":"g7s 5g5",
    "addr:street":"Rue Dubose",
    "iso:country":"CA",
    "sg:address":"2320 Rue Dubose",
    "sg:city":"Jonquiere",
    "sg:classifiers":[
        {
            "category":"Food & Beverages",
            "subcategory":"Groceries & Convenience Stores",
            "type":"Retail Goods"
        }
    ],
    "sg:phone":"+1 418 548 2977",
    "sg:postcode":"G7S 5G5",
    "sg:province":"QC",
    "sg:tags":[
        "grocer"
    ],
    "wof:name":"Maestro Dubose",
    "wof:placetype":"venue"
},
  "geometry": {"coordinates":[-71.14571380620001,48.4005775452],"type":"Point"}
}