{
  "type": "Feature",
  "properties": {
    "addr:full":"487 Brunswick Ave Toronto ON M5R 2Z6",
    "addr:housenumber":"487",
    "addr:postcode":"m5r 2z6",
    "addr:street":"Brunswick Ave",
    "iso:country":"CA",
    "sg:address":"487 Brunswick Ave",
    "sg:city":"Toronto",
    "sg:classifiers":[
        {
            "category":"Health Services",
            "subcategory":"Health Practitioner",
            "type":"Services"
        }
    ],
    "sg:phone":"+1 416 361 6059",
    "sg:postcode":"M5R 2Z6",
    "sg:province":"ON",
    "sg:tags":[
        "psychotherapist",
        "counselor",
        "marriage",
        "family"
    ],
    "wof:name":"Jane Kennedy Marriage Cnsllng",
    "wof:placetype":"venue"
},
  "geometry": {"coordinates":[-79.409592,43.672184],"type":"Point"}
}