{
  "type": "Feature",
  "properties": {
    "addr:full":"660 Pembina Hwy Winnipeg MB R3M 2M5",
    "addr:housenumber":"660",
    "addr:postcode":"r3m 2m5",
    "addr:street":"Pembina Hwy",
    "iso:country":"CA",
    "sg:address":"660 Pembina Hwy",
    "sg:city":"Winnipeg",
    "sg:classifiers":[
        {
            "category":"Autos & Motor Vehicles",
            "subcategory":"Automobile Sales",
            "type":"Retail Goods"
        }
    ],
    "sg:phone":"+1 204 284 7520",
    "sg:postcode":"R3M 2M5",
    "sg:province":"MB",
    "sg:tags":[
        "car",
        "dealer"
    ],
    "wof:name":"Auto Haus Volkswagen",
    "wof:placetype":"venue"
},
  "geometry": {"coordinates":[-97.14837646479999,49.862575531],"type":"Point"}
}