{
  "type": "Feature",
  "properties": {
    "iso:country":"CA",
    "sg:address":"Corner of 2nd St & Hwy 11",
    "sg:city":"Englehart",
    "sg:classifiers":[
        {
            "category":"Home & Garden",
            "subcategory":"Hardware",
            "type":"Retail Goods"
        }
    ],
    "sg:phone":"+1 705 544 2325",
    "sg:postcode":"P0J 1H0",
    "sg:province":"ON",
    "wof:name":"Jcd Home Hardware",
    "wof:placetype":"venue"
},
  "geometry": {"coordinates":[-79.8776397705,47.8202857971],"type":"Point"}
}