{
  "type": "Feature",
  "properties": {
    "addr:full":"126 Danforth Ave Leamington ON N8H 2R2",
    "addr:housenumber":"126",
    "addr:postcode":"n8h 2r2",
    "addr:street":"Danforth Ave",
    "iso:country":"CA",
    "sg:address":"126 Danforth Ave",
    "sg:city":"Leamington",
    "sg:classifiers":[
        {
            "category":"Retail",
            "subcategory":"Laundry & Dry Cleaning",
            "type":"Services"
        }
    ],
    "sg:phone":"+1 519 326 6833",
    "sg:postcode":"N8H 2R2",
    "sg:province":"ON",
    "sg:tags":[
        "cleaners",
        "rug",
        "carpet"
    ],
    "wof:name":"Coulter Cleaning Systems",
    "wof:placetype":"venue"
},
  "geometry": {"coordinates":[-82.592499,42.037922],"type":"Point"}
}