{
  "type": "Feature",
  "properties": {
    "iso:country":"CA",
    "sg:city":"Sherwood Park",
    "sg:classifiers":[
        {
            "category":"Restaurant",
            "type":"Food & Drink"
        }
    ],
    "sg:phone":"+1 780 449 5029",
    "sg:postcode":"T8A 3H9",
    "sg:province":"AB",
    "wof:name":"Albert's Restaurant",
    "wof:placetype":"venue"
},
  "geometry": {"coordinates":[-113.295417786,53.5296707153],"type":"Point"}
}