{
  "type": "Feature",
  "properties": {
    "addr:full":"1136 Glenayre Dr Port Moody BC V3H 1J7",
    "addr:housenumber":"1136",
    "addr:postcode":"v3h 1j7",
    "addr:street":"Glenayre Dr",
    "iso:country":"CA",
    "sg:address":"1136 Glenayre Dr",
    "sg:city":"Port Moody",
    "sg:classifiers":[
        {
            "category":"Retail",
            "subcategory":"Repair Shop",
            "type":"Services"
        }
    ],
    "sg:phone":"+1 604 936 1335",
    "sg:postcode":"V3H 1J7",
    "sg:province":"BC",
    "sg:tags":[
        "lock",
        "locksmith"
    ],
    "wof:name":"Reliable Locksmith Ltd",
    "wof:placetype":"venue"
},
  "geometry": {"coordinates":[-122.880523682,49.2773284912],"type":"Point"}
}