{
  "type": "Feature",
  "properties": {
    "addr:full":"Port Hardy BC V0N 2P0",
    "addr:postcode":"v0n 2p0",
    "iso:country":"CA",
    "sg:city":"Port Hardy",
    "sg:classifiers":[
        {
            "category":"Shopping",
            "subcategory":"Florist",
            "type":"Retail Goods"
        }
    ],
    "sg:phone":"+1 250 949 7212",
    "sg:postcode":"V0N 2P0",
    "sg:province":"BC",
    "wof:name":"Port Hardy Florist",
    "wof:placetype":"venue"
},
  "geometry": {"coordinates":[-127.492111206,50.7212638855],"type":"Point"}
}