{
  "type": "Feature",
  "properties": {
    "addr:full":"783 Fairville Blvd Saint John NB E2M 5T9",
    "addr:housenumber":"783",
    "addr:postcode":"e2m 5t9",
    "addr:street":"Fairville Blvd",
    "iso:country":"CA",
    "sg:address":"783 Fairville Blvd",
    "sg:city":"Saint John",
    "sg:classifiers":[
        {
            "category":"Food & Beverages",
            "subcategory":"Groceries & Convenience Stores",
            "type":"Retail Goods"
        }
    ],
    "sg:phone":"+1 506 672 9228",
    "sg:postcode":"E2M 5T9",
    "sg:province":"NB",
    "wof:name":"Lancaster Irving Convenience",
    "wof:placetype":"venue"
},
  "geometry": {"coordinates":[-66.099571,45.251953],"type":"Point"}
}