{
  "type": "Feature",
  "properties": {
    "addr:full":"192 Boul Trudel O Saint-Boniface-DE-Shawinigan QC G0X 2L0",
    "addr:housenumber":"192",
    "addr:postcode":"g0x 2l0",
    "addr:street":"Boul Trudel O Saint-Boniface-De-Shawinigan",
    "iso:country":"CA",
    "sg:address":"192 Boul Trudel O",
    "sg:city":"Saint-Boniface-DE-Shawinigan",
    "sg:classifiers":[
        {
            "category":"Utilities",
            "subcategory":"Fuel Oil & Lpg",
            "type":"Services"
        }
    ],
    "sg:phone":"+1 819 535 3921",
    "sg:postcode":"G0X 2L0",
    "sg:province":"QC",
    "sg:tags":[
        "propane",
        "gas"
    ],
    "wof:name":"Shell",
    "wof:placetype":"venue"
},
  "geometry": {"coordinates":[-72.82699599999999,46.506836],"type":"Point"}
}