{
  "type": "Feature",
  "properties": {
    "addr:full":"RR 4 STN Main Innisfail AB T4G 1T9",
    "addr:postcode":"t4g 1t9",
    "addr:street":"Rr 4 Stn Main",
    "iso:country":"CA",
    "sg:address":"RR 4 STN Main",
    "sg:city":"Innisfail",
    "sg:classifiers":[
        {
            "category":"Wholesale",
            "subcategory":"Chemicals & Plastics",
            "type":"Manufacturing & Wholesale Goods"
        }
    ],
    "sg:phone":"+1 403 227 3466",
    "sg:postcode":"T4G 1T9",
    "sg:province":"AB",
    "sg:tags":[
        "fertilizer"
    ],
    "wof:name":"Green Way Farm Supply Ltd",
    "wof:placetype":"venue"
},
  "geometry": {"coordinates":[-113.948623657,52.0274085999],"type":"Point"}
}