{
  "type": "Feature",
  "properties": {
    "addr:full":"Kelowna BC V1Y 8K5",
    "addr:postcode":"v1y 8k5",
    "iso:country":"CA",
    "sg:city":"Kelowna",
    "sg:classifiers":[
        {
            "category":"Health Services",
            "subcategory":"Doctor",
            "type":"Services"
        }
    ],
    "sg:phone":"+1 250 861 3235",
    "sg:postcode":"V1Y 8K5",
    "sg:province":"BC",
    "sg:tags":[
        "physician",
        "clinic",
        "surgeon"
    ],
    "wof:name":"Orchard Medical Ctr",
    "wof:placetype":"venue"
},
  "geometry": {"coordinates":[-119.44348100000001,49.87888],"type":"Point"}
}