{
  "type": "Feature",
  "properties": {
    "addr:full":"6788 20E Av Montreal QC H1X 2J7",
    "addr:housenumber":"6788",
    "addr:postcode":"h1x 2j7",
    "addr:street":"20E Av",
    "iso:country":"CA",
    "sg:address":"6788 20E Av",
    "sg:city":"Montreal",
    "sg:classifiers":[
        {
            "category":"Professional",
            "subcategory":"Business Services",
            "type":"Services"
        }
    ],
    "sg:phone":"+1 514 979 7615",
    "sg:postcode":"H1X 2J7",
    "sg:province":"QC",
    "sg:tags":[
        "painter",
        "sign"
    ],
    "wof:name":"Lettrage Jbl Enr",
    "wof:placetype":"venue"
},
  "geometry": {"coordinates":[-73.5862731934,45.5626602173],"type":"Point"}
}