{
  "type": "Feature",
  "properties": {
    "addr:full":"1680 Rue King E Sherbrooke QC J1J 2C9",
    "addr:housenumber":"1680",
    "addr:postcode":"j1j 2c9",
    "addr:street":"Rue King E",
    "iso:country":"CA",
    "sg:address":"1680 Rue King E",
    "sg:city":"Sherbrooke",
    "sg:classifiers":[
        {
            "category":"Food & Beverages",
            "subcategory":"Bakery",
            "type":"Retail Goods"
        }
    ],
    "sg:phone":"+1 819 566 6777",
    "sg:postcode":"J1J 2C9",
    "sg:province":"QC",
    "sg:tags":[
        "tea",
        "coffee",
        "doughnut"
    ],
    "wof:name":"Tim Hortons",
    "wof:placetype":"venue"
},
  "geometry": {"coordinates":[-71.848923,45.409378],"type":"Point"}
}