{
  "type": "Feature",
  "properties": {
    "addr:full":"36 King St E Dundas ON L9H 1B8",
    "addr:housenumber":"36",
    "addr:postcode":"l9h 1b8",
    "addr:street":"King St E",
    "iso:country":"CA",
    "sg:address":"36 King St E",
    "sg:city":"Dundas",
    "sg:classifiers":[
        {
            "category":"Shopping",
            "subcategory":"Hobbies, Toys, & Games",
            "type":"Retail Goods"
        }
    ],
    "sg:phone":"+1 905 628 6062",
    "sg:postcode":"L9H 1B8",
    "sg:province":"ON",
    "sg:tags":[
        "planning",
        "party",
        "ceramic"
    ],
    "wof:name":"Kool Klay Kafe",
    "wof:placetype":"venue"
},
  "geometry": {"coordinates":[-79.9519958496,43.2657165527],"type":"Point"}
}