{
  "type": "Feature",
  "properties": {
    "addr:full":"155 Glen Ave Brandon MB R7C 1A4",
    "addr:housenumber":"155",
    "addr:postcode":"r7c 1a4",
    "addr:street":"Glen Ave",
    "iso:country":"CA",
    "sg:address":"155 Glen Ave",
    "sg:city":"Brandon",
    "sg:classifiers":[
        {
            "category":"Wholesale",
            "subcategory":"Machinery & Supplies",
            "type":"Manufacturing & Wholesale Goods"
        }
    ],
    "sg:phone":"+1 204 727 0925",
    "sg:postcode":"R7C 1A4",
    "sg:province":"MB",
    "sg:tags":[
        "contractor"
    ],
    "wof:name":"Snowdon Equipment Repairs",
    "wof:placetype":"venue"
},
  "geometry": {"coordinates":[-99.940186,49.876301],"type":"Point"}
}