{
  "type": "Feature",
  "properties": {
    "addr:full":"1707 18 Ave NW Calgary AB T2M 0X4",
    "addr:housenumber":"1707",
    "addr:postcode":"t2m 0x4",
    "addr:street":"18 Ave Nw",
    "iso:country":"CA",
    "sg:address":"1707 18 Ave NW",
    "sg:city":"Calgary",
    "sg:classifiers":[
        {
            "category":"Building & Trades",
            "subcategory":"Landscaping Services",
            "type":"Services"
        }
    ],
    "sg:phone":"+1 403 282 2698",
    "sg:postcode":"T2M 0X4",
    "sg:province":"AB",
    "sg:tags":[
        "landscape",
        "contractor"
    ],
    "wof:name":"Hayley Landscaping",
    "wof:placetype":"venue"
},
  "geometry": {"coordinates":[-114.100075,51.068539],"type":"Point"}
}