{
  "type": "Feature",
  "properties": {
    "addr:full":"86 Wildwood Trail Barrie ON L4N 7Z8",
    "addr:housenumber":"86",
    "addr:postcode":"l4n 7z8",
    "addr:street":"Wildwood Trail",
    "iso:country":"CA",
    "sg:address":"86 Wildwood Trail",
    "sg:city":"Barrie",
    "sg:classifiers":[
        {
            "category":"Wholesale",
            "subcategory":"Hardware",
            "type":"Manufacturing & Wholesale Goods"
        }
    ],
    "sg:phone":"+1 705 737 9842",
    "sg:postcode":"L4N 7Z8",
    "sg:province":"ON",
    "sg:tags":[
        "tool"
    ],
    "wof:name":"Hytorc",
    "wof:placetype":"venue"
},
  "geometry": {"coordinates":[-79.705871582,44.3525161743],"type":"Point"}
}