{
  "type": "Feature",
  "properties": {
    "iso:country":"CA",
    "sg:address":"240 Raleigh Ave",
    "sg:city":"Scarborough",
    "sg:classifiers":[
        {
            "category":"Building & Trades",
            "subcategory":"Construction",
            "type":"Services"
        }
    ],
    "sg:phone":"+1 416 261 0101",
    "sg:postcode":"M1K 1A8",
    "sg:province":"ON",
    "sg:tags":[
        "railing"
    ],
    "wof:name":"Metro Railing Ltd",
    "wof:placetype":"venue"
},
  "geometry": {"coordinates":[-79.2615814209,43.708782196],"type":"Point"}
}