{
  "type": "Feature",
  "properties": {
    "addr:full":"3332A Parsons Rd NW Edmonton AB T6N 1B5",
    "addr:housenumber":"3332a",
    "addr:postcode":"t6n 1b5",
    "addr:street":"Parsons Rd Nw",
    "iso:country":"CA",
    "sg:address":"3332A Parsons Rd NW",
    "sg:city":"Edmonton",
    "sg:classifiers":[
        {
            "category":"Food & Beverages",
            "subcategory":"Specialty",
            "type":"Retail Goods"
        }
    ],
    "sg:phone":"+1 780 496 3578",
    "sg:postcode":"T6N 1B5",
    "sg:province":"AB",
    "sg:tags":[
        "product",
        "health",
        "diet"
    ],
    "wof:name":"Sun Vita Intl Inc",
    "wof:placetype":"venue"
},
  "geometry": {"coordinates":[-113.486351013,53.4663543701],"type":"Point"}
}