{
  "type": "Feature",
  "properties": {
    "addr:full":"Surrey BC V3V 3T3",
    "addr:postcode":"v3v 3t3",
    "iso:country":"CA",
    "sg:city":"Surrey",
    "sg:classifiers":[
        {
            "category":"Building & Trades",
            "subcategory":"Construction",
            "type":"Services"
        }
    ],
    "sg:phone":"+1 604 580 0512",
    "sg:postcode":"V3V 3T3",
    "sg:province":"BC",
    "sg:tags":[
        "railing"
    ],
    "wof:name":"Best Railings",
    "wof:placetype":"venue"
},
  "geometry": {"coordinates":[-122.900085449,49.1945610046],"type":"Point"}
}