{
  "type": "Feature",
  "properties": {
    "addr:full":"800 Franklin Blvd Cambridge ON N1R 7Z1",
    "addr:housenumber":"800",
    "addr:postcode":"n1r 7z1",
    "addr:street":"Franklin Blvd",
    "iso:country":"CA",
    "sg:address":"800 Franklin Blvd",
    "sg:city":"Cambridge",
    "sg:classifiers":[
        {
            "category":"Education",
            "subcategory":"School",
            "type":"Public Place"
        }
    ],
    "sg:phone":"+1 519 624 8762",
    "sg:postcode":"N1R 7Z1",
    "sg:province":"ON",
    "wof:name":"Oxford Learning Ctr",
    "wof:placetype":"venue"
},
  "geometry": {"coordinates":[-80.299171,43.380241],"type":"Point"}
}