{
  "type": "Feature",
  "properties": {
    "addr:full":"148 Main St W Ridgetown ON N0P 2C0",
    "addr:housenumber":"148",
    "addr:postcode":"n0p 2c0",
    "addr:street":"Main St W",
    "iso:country":"CA",
    "sg:address":"148 Main St W",
    "sg:city":"Ridgetown",
    "sg:classifiers":[
        {
            "category":"Building & Trades",
            "subcategory":"Construction",
            "type":"Services"
        }
    ],
    "sg:phone":"+1 519 674 3979",
    "sg:postcode":"N0P 2C0",
    "sg:province":"ON",
    "sg:tags":[
        "contractor"
    ],
    "wof:name":"John Faas Construction Ltd",
    "wof:placetype":"venue"
},
  "geometry": {"coordinates":[-81.894859314,42.4336395264],"type":"Point"}
}