{
  "type": "Feature",
  "properties": {
    "addr:full":"6 Rue Des Bouleaux E Sainte-Perpetue-DE-L'Islet QC G0R 3Z0",
    "addr:housenumber":"6",
    "addr:postcode":"g0r 3z0",
    "addr:street":"Rue Des Bouleaux E Sainte-Perpetue-De-L'Islet",
    "iso:country":"CA",
    "sg:address":"6 Rue Des Bouleaux E",
    "sg:city":"Sainte-Perpetue-DE-L'Islet",
    "sg:classifiers":[
        {
            "category":"Shopping",
            "subcategory":"Jewelry",
            "type":"Retail Goods"
        }
    ],
    "sg:phone":"+1 418 359 3080",
    "sg:postcode":"G0R 3Z0",
    "sg:province":"QC",
    "sg:tags":[
        "jeweler"
    ],
    "wof:name":"Bijouterie LA Maison Horloges",
    "wof:placetype":"venue"
},
  "geometry": {"coordinates":[-70.331535,47.089802],"type":"Point"}
}