{
  "type": "Feature",
  "properties": {
    "addr:full":"730 Av Bombardier N Alma QC G8B 7E9",
    "addr:housenumber":"730",
    "addr:postcode":"g8b 7e9",
    "addr:street":"Av Bombardier N",
    "iso:country":"CA",
    "sg:address":"730 Av Bombardier N",
    "sg:city":"Alma",
    "sg:classifiers":[
        {
            "category":"Professional",
            "subcategory":"Research",
            "type":"Services"
        }
    ],
    "sg:phone":"+1 418 662 2789",
    "sg:postcode":"G8B 7E9",
    "sg:province":"QC",
    "sg:tags":[
        "environmental",
        "ecological",
        "laboratory"
    ],
    "wof:name":"Laboratoire Geo Construction",
    "wof:placetype":"venue"
},
  "geometry": {"coordinates":[-71.64774300000001,48.565758],"type":"Point"}
}