{
  "type": "Feature",
  "properties": {
    "addr:full":"45 Ancaster Rd North York ON M3K 1S7",
    "addr:housenumber":"45",
    "addr:postcode":"m3k 1s7",
    "addr:street":"Ancaster Rd",
    "iso:country":"CA",
    "sg:address":"45 Ancaster Rd",
    "sg:city":"North York",
    "sg:classifiers":[
        {
            "category":"Social Services",
            "subcategory":"Child Care",
            "type":"Services"
        }
    ],
    "sg:phone":"+1 416 392 5064",
    "sg:postcode":"M3K 1S7",
    "sg:province":"ON",
    "sg:tags":[
        "government"
    ],
    "wof:name":"Toronto Child Care Ctr",
    "wof:placetype":"venue"
},
  "geometry": {"coordinates":[-79.46612500000001,43.732891],"type":"Point"}
}