{
  "type": "Feature",
  "properties": {
    "addr:full":"4387 Ch Saint-Andre Jonquiere QC G7X 7V4",
    "addr:postcode":"4387;g7x 7v4",
    "addr:street":"Ch Saint-Andre",
    "iso:country":"CA",
    "sg:address":"4387 Ch Saint-Andre",
    "sg:city":"Jonquiere",
    "sg:classifiers":[
        {
            "category":"Manufacturing",
            "subcategory":"Printing",
            "type":"Manufacturing & Wholesale Goods"
        }
    ],
    "sg:phone":"+1 418 695 4453",
    "sg:postcode":"G7X 7V4",
    "sg:province":"QC",
    "sg:tags":[
        "bookbinder"
    ],
    "wof:name":"Reliure Jonquiere",
    "wof:placetype":"venue"
},
  "geometry": {"coordinates":[-71.29015350340001,48.4370498657],"type":"Point"}
}