{
  "type": "Feature",
  "properties": {
    "addr:full":"South Haven Baddeck NS B0E 1B0",
    "addr:postcode":"b0e 1b0",
    "addr:street":"Haven",
    "iso:country":"CA",
    "sg:address":"South Haven",
    "sg:city":"Baddeck",
    "sg:classifiers":[
        {
            "category":"Restaurant",
            "type":"Food & Drink"
        }
    ],
    "sg:phone":"+1 902 295 3100",
    "sg:postcode":"B0E 1B0",
    "sg:province":"NS",
    "wof:name":"Lobster Galley",
    "wof:placetype":"venue"
},
  "geometry": {"coordinates":[-60.7526054382,46.0998725891],"type":"Point"}
}