{
  "type": "Feature",
  "properties": {
    "iso:country":"CA",
    "sg:address":"744 Duplex Ave",
    "sg:city":"Toronto",
    "sg:classifiers":[
        {
            "category":"Professional",
            "subcategory":"Management & Consulting",
            "type":"Services"
        }
    ],
    "sg:phone":"+1 416 961 5328",
    "sg:postcode":"M4R 1W3",
    "sg:province":"ON",
    "sg:tags":[
        "communications",
        "consultant"
    ],
    "wof:name":"Pierce Communications",
    "wof:placetype":"venue"
},
  "geometry": {"coordinates":[-79.4031829834,43.7164573669],"type":"Point"}
}