{
  "type": "Feature",
  "properties": {
    "addr:full":"391 Boul Tache E Montmagny QC G5V 1E3",
    "addr:housenumber":"391",
    "addr:postcode":"g5v 1e3",
    "addr:street":"Boul Tache E",
    "iso:country":"CA",
    "sg:address":"391 Boul Tache E",
    "sg:city":"Montmagny",
    "sg:classifiers":[
        {
            "category":"Professional",
            "subcategory":"Business Services",
            "type":"Services"
        }
    ],
    "sg:phone":"+1 418 248 7840",
    "sg:postcode":"G5V 1E3",
    "sg:province":"QC",
    "sg:tags":[
        "consultant",
        "rug",
        "design",
        "interior",
        "dealer",
        "decorator",
        "carpet"
    ],
    "wof:name":"Tapis Montmagny",
    "wof:placetype":"venue"
},
  "geometry": {"coordinates":[-70.5359420776,46.9874763489],"type":"Point"}
}