{
  "type": "Feature",
  "properties": {
    "addr:full":"10065 Boul Henri-Bourassa E Montreal QC H1C 1G5",
    "addr:housenumber":"10065",
    "addr:postcode":"h1c 1g5",
    "addr:street":"Boul Henri-Bourassa E",
    "iso:country":"CA",
    "sg:address":"10065 Boul Henri-Bourassa E",
    "sg:city":"Montreal",
    "sg:classifiers":[
        {
            "category":"Building & Trades",
            "subcategory":"Landscaping Services",
            "type":"Services"
        }
    ],
    "sg:phone":"+1 514 648 0760",
    "sg:postcode":"H1C 1G5",
    "sg:province":"QC",
    "sg:tags":[
        "nurseryman",
        "landscape",
        "contractor"
    ],
    "wof:name":"A Mucci Pepiniere Inc",
    "wof:placetype":"venue"
},
  "geometry": {"coordinates":[-73.5540466309,45.6436195374],"type":"Point"}
}