{
  "type": "Feature",
  "properties": {
    "addr:full":"108 Forest St Chatham ON N7L 2A4",
    "addr:housenumber":"108",
    "addr:postcode":"n7l 2a4",
    "addr:street":"Forest St",
    "iso:country":"CA",
    "sg:address":"108 Forest St",
    "sg:city":"Chatham",
    "sg:classifiers":[
        {
            "category":"Retail",
            "subcategory":"Laundry & Dry Cleaning",
            "type":"Services"
        }
    ],
    "sg:phone":"+1 519 352 2930",
    "sg:postcode":"N7L 2A4",
    "sg:province":"ON",
    "sg:tags":[
        "cleaners",
        "rug",
        "carpet"
    ],
    "wof:name":"Noel's Carpet Cleaning",
    "wof:placetype":"venue"
},
  "geometry": {"coordinates":[-82.189255,42.411613],"type":"Point"}
}