{
  "type": "Feature",
  "properties": {
    "addr:full":"1660 6E Rue Trois-Rivieres QC G8Y 5B8",
    "addr:housenumber":"1660",
    "addr:postcode":"g8y 5b8",
    "addr:street":"6E Rue Trois-Rivieres",
    "iso:country":"CA",
    "sg:address":"1660 6E Rue",
    "sg:city":"Trois-Rivieres",
    "sg:classifiers":[
        {
            "category":"Personal",
            "subcategory":"Beauty Salon",
            "type":"Services"
        }
    ],
    "sg:phone":"+1 819 694 0695",
    "sg:postcode":"G8Y 5B8",
    "sg:province":"QC",
    "wof:name":"Coiffure L'Antete",
    "wof:placetype":"venue"
},
  "geometry": {"coordinates":[-72.5916595459,46.3593025208],"type":"Point"}
}