{
  "type": "Feature",
  "properties": {
    "iso:country":"CA",
    "sg:address":"5150 Forest Rd",
    "sg:city":"Watford",
    "sg:classifiers":[
        {
            "category":"Building & Trades",
            "subcategory":"Construction",
            "type":"Services"
        }
    ],
    "sg:phone":"+1 519 849 5440",
    "sg:postcode":"N0M 2S0",
    "sg:province":"ON",
    "sg:tags":[
        "tunneling",
        "contractor"
    ],
    "wof:name":"Roger H Woods Ltd",
    "wof:placetype":"venue"
},
  "geometry": {"coordinates":[-81.8800125122,42.9494743347],"type":"Point"}
}