{
  "type": "Feature",
  "properties": {
    "iso:country":"CA",
    "sg:address":"9715 141 St NW",
    "sg:city":"Edmonton",
    "sg:classifiers":[
        {
            "category":"Real Estate",
            "subcategory":"Architect",
            "type":"Services"
        }
    ],
    "sg:phone":"+1 780 454 3048",
    "sg:postcode":"T5N 2M5",
    "sg:province":"AB",
    "wof:name":"Swanson, Patti L",
    "wof:placetype":"venue"
},
  "geometry": {"coordinates":[-113.56172180199999,53.5350494385],"type":"Point"}
}