{
  "type": "Feature",
  "properties": {
    "iso:country":"CA",
    "sg:city":"Granby",
    "sg:classifiers":[
        {
            "category":"Health Services",
            "subcategory":"Doctor",
            "type":"Services"
        }
    ],
    "sg:phone":"+1 450 378 0030",
    "sg:postcode":"J2G 2W6",
    "sg:province":"QC",
    "sg:tags":[
        "clinic"
    ],
    "wof:name":"Centre DE Medecine-Chirurgie",
    "wof:placetype":"venue"
},
  "geometry": {"coordinates":[-72.7217712402,45.3979949951],"type":"Point"}
}