{
  "type": "Feature",
  "properties": {
    "addr:full":"605 Rue Provost Lachine QC H8S 1M5",
    "addr:housenumber":"605",
    "addr:postcode":"h8s 1m5",
    "addr:street":"Rue Provost",
    "iso:country":"CA",
    "sg:address":"605 Rue Provost",
    "sg:city":"Lachine",
    "sg:classifiers":[
        {
            "category":"Real Estate",
            "subcategory":"Real Estate Agent",
            "type":"Services"
        }
    ],
    "sg:phone":"+1 514 637 4431",
    "sg:postcode":"H8S 1M5",
    "sg:province":"QC",
    "sg:tags":[
        "management"
    ],
    "wof:name":"Champagne Ce",
    "wof:placetype":"venue"
},
  "geometry": {"coordinates":[-73.6695404053,45.4418525696],"type":"Point"}
}