{
  "type": "Feature",
  "properties": {
    "addr:full":"211 Centrum Blvd Orleans ON K1E 3X1",
    "addr:housenumber":"211",
    "addr:postcode":"k1e 3x1",
    "addr:street":"Centrum Blvd",
    "iso:country":"CA",
    "sg:address":"211 Centrum Blvd",
    "sg:city":"Orleans",
    "sg:classifiers":[
        {
            "category":"Banks & Credit Unions",
            "subcategory":"Bank",
            "type":"Services"
        }
    ],
    "sg:phone":"+1 613 830 1010",
    "sg:postcode":"K1E 3X1",
    "sg:province":"ON",
    "wof:name":"Rbc Banque Royale",
    "wof:placetype":"venue"
},
  "geometry": {"coordinates":[-75.512428,45.479538],"type":"Point"}
}