{
  "type": "Feature",
  "properties": {
    "iso:country":"CA",
    "sg:city":"Woodbridge",
    "sg:classifiers":[
        {
            "category":"Manufacturing",
            "subcategory":"Rubber & Plastics",
            "type":"Manufacturing & Wholesale Goods"
        }
    ],
    "sg:phone":"+1 905 851 7272",
    "sg:postcode":"L4L 6E3",
    "sg:province":"ON",
    "wof:name":"Perplas Corp",
    "wof:placetype":"venue"
},
  "geometry": {"coordinates":[-79.555466,43.785572],"type":"Point"}
}