{
  "type": "Feature",
  "properties": {
    "addr:full":"Richmond BC V7A 5J3",
    "addr:postcode":"v7a 5j3",
    "iso:country":"CA",
    "sg:city":"Richmond",
    "sg:classifiers":[
        {
            "category":"Food & Beverages",
            "subcategory":"Specialty",
            "type":"Retail Goods"
        }
    ],
    "sg:phone":"+1 604 272 1141",
    "sg:postcode":"V7A 5J3",
    "sg:province":"BC",
    "sg:tags":[
        "health",
        "diet"
    ],
    "wof:name":"General Nutrition Ctr",
    "wof:placetype":"venue"
},
  "geometry": {"coordinates":[-123.095413208,49.1331443787],"type":"Point"}
}