{
  "type": "Feature",
  "properties": {
    "addr:full":"5403 Harvester Rd Burlington ON L7L 5J7",
    "addr:housenumber":"5403",
    "addr:postcode":"l7l 5j7",
    "addr:street":"Harvester Rd",
    "iso:country":"CA",
    "sg:address":"5403 Harvester Rd",
    "sg:city":"Burlington",
    "sg:classifiers":[
        {
            "category":"Arts & Performance",
            "subcategory":"Theater",
            "type":"Entertainment"
        }
    ],
    "sg:phone":"+1 416 260 0538",
    "sg:postcode":"L7L 5J7",
    "sg:province":"ON",
    "sg:tags":[
        "television",
        "program",
        "producer"
    ],
    "wof:name":"S & S Productions Inc",
    "wof:placetype":"venue"
},
  "geometry": {"coordinates":[-79.75640106199999,43.3884124756],"type":"Point"}
}