{
  "type": "Feature",
  "properties": {
    "addr:full":"Calgary AB T2Y 3S5",
    "addr:postcode":"t2y 3s5",
    "iso:country":"CA",
    "sg:city":"Calgary",
    "sg:classifiers":[
        {
            "category":"Shopping",
            "subcategory":"Stationery & Office Supplies",
            "type":"Retail Goods"
        }
    ],
    "sg:phone":"+1 403 254 2604",
    "sg:postcode":"T2Y 3S5",
    "sg:province":"AB",
    "sg:tags":[
        "consultant",
        "educational",
        "material"
    ],
    "wof:name":"Scholars Choice",
    "wof:placetype":"venue"
},
  "geometry": {"coordinates":[-114.06420135499999,50.9076042175],"type":"Point"}
}