{
  "type": "Feature",
  "properties": {
    "iso:country":"CA",
    "sg:city":"Repentigny",
    "sg:classifiers":[
        {
            "category":"Health Services",
            "subcategory":"Doctor",
            "type":"Services"
        }
    ],
    "sg:phone":"+1 450 657 2001",
    "sg:postcode":"J6A 4X6",
    "sg:province":"QC",
    "sg:tags":[
        "clinic",
        "dentist"
    ],
    "wof:name":"Clinique Dentaire L Deschesnes",
    "wof:placetype":"venue"
},
  "geometry": {"coordinates":[-73.44258880620001,45.7542228699],"type":"Point"}
}