{
  "type": "Feature",
  "properties": {
    "iso:country":"CA",
    "sg:address":"Foley St",
    "sg:city":"Westville",
    "sg:classifiers":[
        {
            "category":"Recreation",
            "type":"Entertainment"
        }
    ],
    "sg:phone":"+1 902 396 4151",
    "sg:postcode":"B0K 2A0",
    "sg:province":"NS",
    "sg:tags":[
        "club",
        "curling"
    ],
    "wof:name":"Westville Curling Club",
    "wof:placetype":"venue"
},
  "geometry": {"coordinates":[-62.7130622864,45.5620193481],"type":"Point"}
}