{
  "type": "Feature",
  "properties": {
    "addr:full":"159 Jane St Toronto ON M6S 3Y8",
    "addr:housenumber":"159",
    "addr:postcode":"m6s 3y8",
    "addr:street":"Jane St",
    "iso:country":"CA",
    "sg:address":"159 Jane St",
    "sg:city":"Toronto",
    "sg:classifiers":[
        {
            "category":"Professional",
            "subcategory":"Computer Services",
            "type":"Services"
        }
    ],
    "sg:phone":"+1 416 763 3862",
    "sg:postcode":"M6S 3Y8",
    "sg:province":"ON",
    "sg:tags":[
        "consultant"
    ],
    "wof:name":"Bush Mison & Assoc",
    "wof:placetype":"venue"
},
  "geometry": {"coordinates":[-79.4859008789,43.6532897949],"type":"Point"}
}