{
  "type": "Feature",
  "properties": {
    "iso:country":"CA",
    "sg:city":"Cap-DE-LA-Madeleine",
    "sg:classifiers":[
        {
            "category":"Wholesale",
            "subcategory":"Auto Parts",
            "type":"Manufacturing & Wholesale Goods"
        }
    ],
    "sg:phone":"+1 819 374 2448",
    "sg:postcode":"G8T 6X6",
    "sg:province":"QC",
    "sg:tags":[
        "automobile",
        "supply"
    ],
    "wof:name":"Pieces D'Auto Henri Paul",
    "wof:placetype":"venue"
},
  "geometry": {"coordinates":[-72.532829,46.366772],"type":"Point"}
}