{
  "type": "Feature",
  "properties": {
    "addr:full":"88 Fawcett Rd Coquitlam BC V3K 6V5",
    "addr:housenumber":"88",
    "addr:postcode":"v3k 6v5",
    "addr:street":"Fawcett Rd",
    "iso:country":"CA",
    "sg:address":"88 Fawcett Rd",
    "sg:city":"Coquitlam",
    "sg:classifiers":[
        {
            "category":"Wholesale",
            "subcategory":"Scrap",
            "type":"Manufacturing & Wholesale Goods"
        }
    ],
    "sg:phone":"+1 604 520 0333",
    "sg:postcode":"V3K 6V5",
    "sg:province":"BC",
    "sg:tags":[
        "recycling",
        "container",
        "center",
        "depot"
    ],
    "wof:name":"Vanguard Bottle Depots Ltd",
    "wof:placetype":"venue"
},
  "geometry": {"coordinates":[-122.834312,49.227898],"type":"Point"}
}