{
  "type": "Feature",
  "properties": {
    "addr:full":"298 Lauzon Rd Windsor ON N8S 3L6",
    "addr:housenumber":"298",
    "addr:postcode":"n8s 3l6",
    "addr:street":"Lauzon Rd",
    "iso:country":"CA",
    "sg:address":"298 Lauzon Rd",
    "sg:city":"Windsor",
    "sg:classifiers":[
        {
            "category":"Building & Trades",
            "subcategory":"Plumbing",
            "type":"Services"
        }
    ],
    "sg:phone":"+1 519 945 0298",
    "sg:postcode":"N8S 3L6",
    "sg:province":"ON",
    "sg:tags":[
        "contractor"
    ],
    "wof:name":"R W Fowler Plumbing",
    "wof:placetype":"venue"
},
  "geometry": {"coordinates":[-82.946533,42.337952],"type":"Point"}
}