{
  "type": "Feature",
  "properties": {
    "addr:full":"775 Rue Amedee Baie-Comeau QC G5C 1W8",
    "addr:housenumber":"775",
    "addr:postcode":"g5c 1w8",
    "addr:street":"Rue Amedee",
    "iso:country":"CA",
    "sg:address":"775 Rue Amedee",
    "sg:city":"Baie-Comeau",
    "sg:classifiers":[
        {
            "category":"Retail",
            "subcategory":"Laundry & Dry Cleaning",
            "type":"Services"
        }
    ],
    "sg:phone":"+1 418 296 2057",
    "sg:postcode":"G5C 1W8",
    "sg:province":"QC",
    "sg:tags":[
        "leather",
        "cleaners"
    ],
    "wof:name":"Nettoyage Express Inc-Bur",
    "wof:placetype":"venue"
},
  "geometry": {"coordinates":[-68.24560546879999,49.1929206848],"type":"Point"}
}