{
  "type": "Feature",
  "properties": {
    "addr:full":"320 Hanlan Rd # 6 Woodbridge ON L4L 3T4",
    "addr:housenumber":"320",
    "addr:postcode":"l4l 3t4",
    "addr:street":"Hanlan Rd # 6",
    "iso:country":"CA",
    "sg:address":"320 Hanlan Rd # 6",
    "sg:city":"Woodbridge",
    "sg:classifiers":[
        {
            "category":"Building & Trades",
            "subcategory":"Plumbing",
            "type":"Services"
        }
    ],
    "sg:phone":"+1 905 850 1744",
    "sg:postcode":"L4L 3T4",
    "sg:province":"ON",
    "sg:tags":[
        "contractor"
    ],
    "wof:name":"Rocky's Plumbing",
    "wof:placetype":"venue"
},
  "geometry": {"coordinates":[-79.557091,43.770679],"type":"Point"}
}