{
  "type": "Feature",
  "properties": {
    "addr:full":"492 Archibald Brook Rd Middle Musquodoboit NS B0N 1X0",
    "addr:housenumber":"492",
    "addr:postcode":"b0n 1x0",
    "addr:street":"Archibald Brook Rd",
    "iso:country":"CA",
    "sg:address":"492 Archibald Brook Rd",
    "sg:city":"Middle Musquodoboit",
    "sg:classifiers":[
        {
            "category":"Health Services",
            "subcategory":"Doctor",
            "type":"Services"
        }
    ],
    "sg:phone":"+1 902 384 2834",
    "sg:postcode":"B0N 1X0",
    "sg:province":"NS",
    "sg:tags":[
        "physician",
        "surgeon"
    ],
    "wof:name":"Hawes, Violet C MD",
    "wof:placetype":"venue"
},
  "geometry": {"coordinates":[-63.144798,45.038097],"type":"Point"}
}