{
  "type": "Feature",
  "properties": {
    "addr:full":"618 Saskatchewan Ave W Portage LA Prairie MB R1N 0M6",
    "addr:housenumber":"618",
    "addr:postcode":"r1n 0m6",
    "addr:street":"Saskatchewan Ave W",
    "iso:country":"CA",
    "sg:address":"618 Saskatchewan Ave W",
    "sg:city":"Portage LA Prairie",
    "sg:classifiers":[
        {
            "category":"Personal",
            "subcategory":"Beauty Salon",
            "type":"Services"
        }
    ],
    "sg:phone":"+1 204 239 6605",
    "sg:postcode":"R1N 0M6",
    "sg:province":"MB",
    "wof:name":"Hair Artistique",
    "wof:placetype":"venue"
},
  "geometry": {"coordinates":[-98.29922485349999,49.9737091064],"type":"Point"}
}