{
  "type": "Feature",
  "properties": {
    "addr:full":"138 Rue Saint-Georges # A Windsor QC J1S 1J8",
    "addr:housenumber":"138",
    "addr:postcode":"j1s 1j8",
    "addr:street":"Rue Saint-Georges # A",
    "iso:country":"CA",
    "sg:address":"138 Rue Saint-Georges # A",
    "sg:city":"Windsor",
    "sg:classifiers":[
        {
            "category":"Wholesale",
            "subcategory":"Office Equipment",
            "type":"Manufacturing & Wholesale Goods"
        }
    ],
    "sg:phone":"+1 819 845 2085",
    "sg:postcode":"J1S 1J8",
    "sg:province":"QC",
    "sg:tags":[
        "accounting",
        "bookkeeping",
        "system"
    ],
    "wof:name":"Ayotte, Denis",
    "wof:placetype":"venue"
},
  "geometry": {"coordinates":[-72.000809,45.571537],"type":"Point"}
}