{
  "type": "Feature",
  "properties": {
    "addr:full":"RR 1 Oakwood ON K0M 2M0",
    "addr:postcode":"k0m 2m0",
    "addr:street":"Rr 1",
    "iso:country":"CA",
    "sg:address":"RR 1",
    "sg:city":"Oakwood",
    "sg:classifiers":[
        {
            "category":"Building & Trades",
            "subcategory":"Plumbing",
            "type":"Services"
        }
    ],
    "sg:phone":"+1 705 953 9555",
    "sg:postcode":"K0M 2M0",
    "sg:province":"ON",
    "sg:tags":[
        "septic"
    ],
    "wof:name":"Reg Garbutt",
    "wof:placetype":"venue"
},
  "geometry": {"coordinates":[-78.879425,44.333038],"type":"Point"}
}