{
  "type": "Feature",
  "properties": {
    "addr:full":"1526 6th Ave W Vancouver BC V6J 1R2",
    "addr:housenumber":"1526",
    "addr:postcode":"v6j 1r2",
    "addr:street":"6Th Ave W",
    "iso:country":"CA",
    "sg:address":"1526 6th Ave W",
    "sg:city":"Vancouver",
    "sg:classifiers":[
        {
            "category":"Food & Beverages",
            "subcategory":"Liquor & Beverages",
            "type":"Retail Goods"
        }
    ],
    "sg:phone":"+1 604 737 0018",
    "sg:postcode":"V6J 1R2",
    "sg:province":"BC",
    "sg:tags":[
        "store"
    ],
    "wof:name":"David Herman & Son Ltd",
    "wof:placetype":"venue"
},
  "geometry": {"coordinates":[-123.13919067400001,49.2660751343],"type":"Point"}
}