{
  "type": "Feature",
  "properties": {
    "iso:country":"CA",
    "sg:address":"1020 17th St W",
    "sg:city":"Saskatoon",
    "sg:classifiers":[
        {
            "category":"Retail",
            "subcategory":"Repair Shop",
            "type":"Services"
        }
    ],
    "sg:phone":"+1 306 653 2211",
    "sg:postcode":"S7M 1E3",
    "sg:province":"SK",
    "sg:tags":[
        "welding"
    ],
    "wof:name":"Beck Industries Ltd",
    "wof:placetype":"venue"
},
  "geometry": {"coordinates":[-106.6848526,52.1216773987],"type":"Point"}
}