{
  "type": "Feature",
  "properties": {
    "addr:full":"Vancouver BC V6Z 2T1",
    "addr:postcode":"v6z 2t1",
    "iso:country":"CA",
    "sg:city":"Vancouver",
    "sg:classifiers":[
        {
            "category":"Professional",
            "subcategory":"Lawyer & Legal Services",
            "type":"Services"
        }
    ],
    "sg:phone":"+1 604 682 0494",
    "sg:postcode":"V6Z 2T1",
    "sg:province":"BC",
    "sg:tags":[
        "attorney"
    ],
    "wof:name":"Glen Sherman Law Office",
    "wof:placetype":"venue"
},
  "geometry": {"coordinates":[-123.124962,49.278999],"type":"Point"}
}