{
  "type": "Feature",
  "properties": {
    "addr:full":"Montreal QC H2Z 1J6",
    "addr:postcode":"h2z 1j6",
    "iso:country":"CA",
    "sg:city":"Montreal",
    "sg:classifiers":[
        {
            "category":"Personal",
            "subcategory":"Beauty Salon",
            "type":"Services"
        }
    ],
    "sg:phone":"+1 514 875 4904",
    "sg:postcode":"H2Z 1J6",
    "sg:province":"QC",
    "wof:name":"Coiffure Alan & Fong",
    "wof:placetype":"venue"
},
  "geometry": {"coordinates":[-73.5601577759,45.508392334],"type":"Point"}
}