{
  "type": "Feature",
  "properties": {
    "addr:full":"PO Box 10 Nakina ON P0T 2H0",
    "addr:housenumber":"po box 10",
    "addr:postcode":"p0t 2h0",
    "addr:street":"Nakina",
    "iso:country":"CA",
    "sg:address":"PO Box 10",
    "sg:city":"Nakina",
    "sg:classifiers":[
        {
            "category":"Government",
            "subcategory":"Office",
            "type":"Public Place"
        }
    ],
    "sg:phone":"+1 807 329 5737",
    "sg:postcode":"P0T 2H0",
    "sg:province":"ON",
    "wof:name":"Aroland Band Projects",
    "wof:placetype":"venue"
},
  "geometry": {"coordinates":[-86.711861,50.17976],"type":"Point"}
}