{
  "type": "Feature",
  "properties": {
    "addr:full":"Vanderhoof BC V0J 3A0",
    "addr:postcode":"v0j 3a0",
    "iso:country":"CA",
    "sg:city":"Vanderhoof",
    "sg:classifiers":[
        {
            "category":"Restaurant",
            "type":"Food & Drink"
        }
    ],
    "sg:phone":"+1 250 567 2404",
    "sg:postcode":"V0J 3A0",
    "sg:province":"BC",
    "wof:name":"Blue Spruce Restaurant",
    "wof:placetype":"venue"
},
  "geometry": {"coordinates":[-123.99026499999999,53.984257],"type":"Point"}
}