{
  "type": "Feature",
  "properties": {
    "iso:country":"CA",
    "sg:address":"285 Yorkland Blvd",
    "sg:city":"North York",
    "sg:classifiers":[
        {
            "category":"Professional",
            "subcategory":"Engineering",
            "type":"Services"
        }
    ],
    "sg:phone":"+1 416 499 8000",
    "sg:postcode":"M2J 1S5",
    "sg:province":"ON",
    "sg:tags":[
        "engineer"
    ],
    "wof:name":"Mitchell Partnership",
    "wof:placetype":"venue"
},
  "geometry": {"coordinates":[-79.335205,43.773254],"type":"Point"}
}