{
  "type": "Feature",
  "properties": {
    "addr:full":"285 Yorkland Blvd North York ON M2J 1S5",
    "addr:housenumber":"285",
    "addr:postcode":"m2j 1s5",
    "addr:street":"Yorkland Blvd",
    "iso:country":"CA",
    "sg:address":"285 Yorkland Blvd",
    "sg:city":"North York",
    "sg:classifiers":[
        {
            "category":"Professional",
            "subcategory":"Engineering",
            "type":"Services"
        }
    ],
    "sg:phone":"+1 416 499 8000",
    "sg:postcode":"M2J 1S5",
    "sg:province":"ON",
    "sg:tags":[
        "engineer"
    ],
    "wof:name":"Mitchell Partnership",
    "wof:placetype":"venue"
},
  "geometry": {"coordinates":[-79.335205,43.773254],"type":"Point"}
}