{
  "type": "Feature",
  "properties": {
    "addr:full":"Toronto ON M5H 1S3",
    "addr:postcode":"m5h 1s3",
    "iso:country":"CA",
    "sg:city":"Toronto",
    "sg:classifiers":[
        {
            "category":"Professional",
            "subcategory":"Computer Services",
            "type":"Services"
        }
    ],
    "sg:phone":"+1 416 360 6678",
    "sg:postcode":"M5H 1S3",
    "sg:province":"ON",
    "wof:name":"Alan Todd & Assoc",
    "wof:placetype":"venue"
},
  "geometry": {"coordinates":[-79.3824234009,43.6496734619],"type":"Point"}
}