{
  "type": "Feature",
  "properties": {
    "addr:full":"Vancouver BC V6H 3S2",
    "addr:postcode":"v6h 3s2",
    "iso:country":"CA",
    "sg:city":"Vancouver",
    "sg:classifiers":[
        {
            "category":"Shopping",
            "subcategory":"Hobbies, Toys, & Games",
            "type":"Retail Goods"
        }
    ],
    "sg:phone":"+1 604 669 3939",
    "sg:postcode":"V6H 3S2",
    "sg:province":"BC",
    "sg:tags":[
        "craft",
        "supply"
    ],
    "wof:name":"Maiwa Handprints Ltd",
    "wof:placetype":"venue"
},
  "geometry": {"coordinates":[-123.135726929,49.2723312378],"type":"Point"}
}