{
  "type": "Feature",
  "properties": {
    "iso:country":"CA",
    "sg:address":"1145 Heron Rd",
    "sg:city":"Ottawa",
    "sg:classifiers":[
        {
            "category":"Restaurant",
            "type":"Food & Drink"
        }
    ],
    "sg:phone":"+1 613 731 8752",
    "sg:postcode":"K1V 6B5",
    "sg:province":"ON",
    "wof:name":"O'Brien's Eatery & Pub",
    "wof:placetype":"venue"
},
  "geometry": {"coordinates":[-75.671089,45.378433],"type":"Point"}
}