{
  "type": "Feature",
  "properties": {
    "addr:full":"Scarborough ON M1P 2G7",
    "addr:postcode":"m1p 2g7",
    "iso:country":"CA",
    "sg:city":"Scarborough",
    "sg:classifiers":[
        {
            "category":"Cinema",
            "subcategory":"Movie Rental",
            "type":"Entertainment"
        }
    ],
    "sg:phone":"+1 416 755 5367",
    "sg:postcode":"M1P 2G7",
    "sg:province":"ON",
    "sg:tags":[
        "leasing",
        "video",
        "disc",
        "tape"
    ],
    "wof:name":"S K Video Ltd",
    "wof:placetype":"venue"
},
  "geometry": {"coordinates":[-79.28923,43.758747],"type":"Point"}
}