{
  "type": "Feature",
  "properties": {
    "addr:full":"372 Rue Saint-Joseph # 2 Laurier-Station QC G0S 1N0",
    "addr:housenumber":"372",
    "addr:postcode":"g0s 1n0",
    "addr:street":"Rue Saint-Joseph # 2 Laurier-Station",
    "iso:country":"CA",
    "sg:address":"372 Rue Saint-Joseph # 2",
    "sg:city":"Laurier-Station",
    "sg:classifiers":[
        {
            "category":"Real Estate",
            "subcategory":"Real Estate Agent",
            "type":"Services"
        }
    ],
    "sg:phone":"+1 418 728 4881",
    "sg:postcode":"G0S 1N0",
    "sg:province":"QC",
    "sg:tags":[
        "cooperative"
    ],
    "wof:name":"Cooperative DE Solidarite DE",
    "wof:placetype":"venue"
},
  "geometry": {"coordinates":[-71.631248,46.538593],"type":"Point"}
}