{
  "type": "Feature",
  "properties": {
    "addr:full":"1666 Pritchard Dr Westbank BC V4T 1X5",
    "addr:housenumber":"1666",
    "addr:postcode":"v4t 1x5",
    "addr:street":"Pritchard Dr",
    "iso:country":"CA",
    "sg:address":"1666 Pritchard Dr",
    "sg:city":"Westbank",
    "sg:classifiers":[
        {
            "category":"Food & Beverages",
            "subcategory":"Specialty",
            "type":"Retail Goods"
        }
    ],
    "sg:phone":"+1 250 768 7295",
    "sg:postcode":"V4T 1X5",
    "sg:province":"BC",
    "sg:tags":[
        "vitamin"
    ],
    "wof:name":"Amway Distributors",
    "wof:placetype":"venue"
},
  "geometry": {"coordinates":[-119.62961578399999,49.8295707703],"type":"Point"}
}