{
  "type": "Feature",
  "properties": {
    "addr:full":"Concession Rd Fenelon Falls ON K0M 1N0",
    "addr:postcode":"k0m 1n0",
    "addr:street":"Concession Rd",
    "iso:country":"CA",
    "sg:address":"Concession Rd",
    "sg:city":"Fenelon Falls",
    "sg:classifiers":[
        {
            "category":"Real Estate",
            "subcategory":"Developer",
            "type":"Services"
        }
    ],
    "sg:phone":"+1 705 887 4656",
    "sg:postcode":"K0M 1N0",
    "sg:province":"ON",
    "sg:tags":[
        "cemetery"
    ],
    "wof:name":"Fenelon Falls Cemetery",
    "wof:placetype":"venue"
},
  "geometry": {"coordinates":[-78.726646,44.533051],"type":"Point"}
}