{
  "type": "Feature",
  "properties": {
    "addr:full":"94 James St Ottawa ON K1R 5M3",
    "addr:housenumber":"94",
    "addr:postcode":"k1r 5m3",
    "addr:street":"James St",
    "iso:country":"CA",
    "sg:address":"94 James St",
    "sg:city":"Ottawa",
    "sg:classifiers":[
        {
            "category":"Social Services",
            "subcategory":"Child Care",
            "type":"Services"
        }
    ],
    "sg:phone":"+1 613 235 7473",
    "sg:postcode":"K1R 5M3",
    "sg:province":"ON",
    "wof:name":"Centretown Parents Daycare Inc",
    "wof:placetype":"venue"
},
  "geometry": {"coordinates":[-75.6976699829,45.4120521545],"type":"Point"}
}