{
  "type": "Feature",
  "properties": {
    "addr:full":"Boucherville QC J4B 7L6",
    "addr:postcode":"j4b 7l6",
    "iso:country":"CA",
    "sg:city":"Boucherville",
    "sg:classifiers":[
        {
            "category":"Manufacturing",
            "subcategory":"Tools & Machinery",
            "type":"Manufacturing & Wholesale Goods"
        }
    ],
    "sg:phone":"+1 450 449 2664",
    "sg:postcode":"J4B 7L6",
    "sg:province":"QC",
    "sg:tags":[
        "packaging"
    ],
    "wof:name":"Controles Gmc Inc",
    "wof:placetype":"venue"
},
  "geometry": {"coordinates":[-73.428864,45.55864],"type":"Point"}
}