{
  "type": "Feature",
  "properties": {
    "addr:full":"Calgary AB T2A 6A3",
    "addr:postcode":"t2a 6a3",
    "iso:country":"CA",
    "sg:city":"Calgary",
    "sg:classifiers":[
        {
            "category":"Manufacturing",
            "subcategory":"Tools & Machinery",
            "type":"Manufacturing & Wholesale Goods"
        }
    ],
    "sg:phone":"+1 403 272 6605",
    "sg:postcode":"T2A 6A3",
    "sg:province":"AB",
    "sg:tags":[
        "gas",
        "oxygen"
    ],
    "wof:name":"Airgas Canada Inc",
    "wof:placetype":"venue"
},
  "geometry": {"coordinates":[-113.989265,51.061661],"type":"Point"}
}