{
  "type": "Feature",
  "properties": {
    "addr:full":"Surrey BC V3W 0B5",
    "addr:postcode":"v3w 0b5",
    "iso:country":"CA",
    "sg:city":"Surrey",
    "sg:classifiers":[
        {
            "category":"Real Estate",
            "subcategory":"Real Estate Agent",
            "type":"Services"
        }
    ],
    "sg:phone":"+1 604 597 1195",
    "sg:postcode":"V3W 0B5",
    "sg:province":"BC",
    "sg:tags":[
        "cooperative"
    ],
    "wof:name":"Avondale Housing CO-Operative",
    "wof:placetype":"venue"
},
  "geometry": {"coordinates":[-122.84035491900001,49.1370429993],"type":"Point"}
}