{
  "type": "Feature",
  "properties": {
    "iso:country":"CA",
    "sg:address":"PO Box 874",
    "sg:city":"Pincher Creek",
    "sg:classifiers":[
        {
            "category":"Retail",
            "subcategory":"Repair Shop",
            "type":"Services"
        }
    ],
    "sg:phone":"+1 403 627 2235",
    "sg:postcode":"T0K 1W0",
    "sg:province":"AB",
    "sg:tags":[
        "welding"
    ],
    "wof:name":"Norm's Welding",
    "wof:placetype":"venue"
},
  "geometry": {"coordinates":[-113.95009613000001,49.4856681824],"type":"Point"}
}