{
  "type": "Feature",
  "properties": {
    "addr:full":"1204 Howard Ave Windsor ON N8X 3S9",
    "addr:housenumber":"1204",
    "addr:postcode":"n8x 3s9",
    "addr:street":"Howard Ave",
    "iso:country":"CA",
    "sg:address":"1204 Howard Ave",
    "sg:city":"Windsor",
    "sg:classifiers":[
        {
            "category":"Food & Beverages",
            "subcategory":"Groceries & Convenience Stores",
            "type":"Retail Goods"
        }
    ],
    "sg:phone":"+1 519 256 5581",
    "sg:postcode":"N8X 3S9",
    "sg:province":"ON",
    "wof:name":"Express Convenience",
    "wof:placetype":"venue"
},
  "geometry": {"coordinates":[-83.0234451294,42.3082046509],"type":"Point"}
}