{
  "type": "Feature",
  "properties": {
    "addr:full":"8011 No. 3 Rd Richmond BC V6Y 2E4",
    "addr:postcode":"8011;v6y 2e4",
    "addr:street":"3 Rd",
    "iso:country":"CA",
    "sg:address":"8011 No. 3 Rd",
    "sg:city":"Richmond",
    "sg:classifiers":[
        {
            "category":"Autos & Motor Vehicles",
            "subcategory":"Fuel & Gas Station",
            "type":"Retail Goods"
        }
    ],
    "sg:phone":"+1 604 270 3822",
    "sg:postcode":"V6Y 2E4",
    "sg:province":"BC",
    "sg:tags":[
        "oil"
    ],
    "wof:name":"Steve's Husky",
    "wof:placetype":"venue"
},
  "geometry": {"coordinates":[-123.137046814,49.1547546387],"type":"Point"}
}