{
  "type": "Feature",
  "properties": {
    "addr:full":"2004 4th Ave W Vancouver BC V6J 1M9",
    "addr:housenumber":"2004",
    "addr:postcode":"v6j 1m9",
    "addr:street":"4Th Ave W",
    "iso:country":"CA",
    "sg:address":"2004 4th Ave W",
    "sg:city":"Vancouver",
    "sg:classifiers":[
        {
            "category":"Shopping",
            "subcategory":"Department Store",
            "type":"Retail Goods"
        }
    ],
    "sg:phone":"+1 604 739 6982",
    "sg:postcode":"V6J 1M9",
    "sg:province":"BC",
    "sg:tags":[
        "shop"
    ],
    "wof:name":"Kitstlano Houseware Depot Inc",
    "wof:placetype":"venue"
},
  "geometry": {"coordinates":[-123.150673,49.267982],"type":"Point"}
}