{
  "type": "Feature",
  "properties": {
    "iso:country":"CA",
    "sg:address":"1003 Brandycrest Rd",
    "sg:city":"Port Carling",
    "sg:classifiers":[
        {
            "category":"Building & Trades",
            "subcategory":"Electrical",
            "type":"Services"
        }
    ],
    "sg:phone":"+1 705 764 5555",
    "sg:postcode":"P0B 1J0",
    "sg:province":"ON",
    "sg:tags":[
        "electric",
        "contractor"
    ],
    "wof:name":"Mc Morran Electric",
    "wof:placetype":"venue"
},
  "geometry": {"coordinates":[-79.5342788696,45.1013946533],"type":"Point"}
}