{
  "type": "Feature",
  "properties": {
    "iso:country":"CA",
    "sg:address":"3488 Rue DE Verdun",
    "sg:city":"Verdun",
    "sg:classifiers":[
        {
            "category":"Wholesale",
            "subcategory":"Machinery & Supplies",
            "type":"Manufacturing & Wholesale Goods"
        }
    ],
    "sg:phone":"+1 514 766 4004",
    "sg:postcode":"H4G 1K3",
    "sg:province":"QC",
    "sg:tags":[
        "parts",
        "elevator"
    ],
    "wof:name":"Distribution Marley",
    "wof:placetype":"venue"
},
  "geometry": {"coordinates":[-73.57061004640001,45.4690895081],"type":"Point"}
}