{
  "type": "Feature",
  "properties": {
    "iso:country":"CA",
    "sg:address":"144 Steelcase Rd W",
    "sg:city":"Markham",
    "sg:classifiers":[
        {
            "category":"Professional",
            "subcategory":"Business Services",
            "type":"Services"
        }
    ],
    "sg:phone":"+1 905 947 1168",
    "sg:postcode":"L3R 3J9",
    "sg:province":"ON",
    "sg:tags":[
        "paging",
        "answering"
    ],
    "wof:name":"Message on Hold Network",
    "wof:placetype":"venue"
},
  "geometry": {"coordinates":[-79.357635,43.818764],"type":"Point"}
}