{
  "type": "Feature",
  "properties": {
    "addr:full":"9415 47 St NW Edmonton AB T6B 2R7",
    "addr:housenumber":"9415",
    "addr:postcode":"t6b 2r7",
    "addr:street":"47 St Nw",
    "iso:country":"CA",
    "sg:address":"9415 47 St NW",
    "sg:city":"Edmonton",
    "sg:classifiers":[
        {
            "category":"Wholesale",
            "subcategory":"Electrical",
            "type":"Manufacturing & Wholesale Goods"
        }
    ],
    "sg:phone":"+1 780 463 5002",
    "sg:postcode":"T6B 2R7",
    "sg:province":"AB",
    "sg:tags":[
        "high",
        "fidelity",
        "stereophonic"
    ],
    "wof:name":"Pro Distributors Inc",
    "wof:placetype":"venue"
},
  "geometry": {"coordinates":[-113.40778400000001,53.531326],"type":"Point"}
}