{
  "type": "Feature",
  "properties": {
    "iso:country":"CA",
    "sg:address":"1120 Mcgill Rd",
    "sg:city":"Kamloops",
    "sg:classifiers":[
        {
            "category":"Freight",
            "type":"Transportation"
        }
    ],
    "sg:phone":"+1 250 374 5544",
    "sg:postcode":"V2C 6N6",
    "sg:province":"BC",
    "sg:tags":[
        "trucking"
    ],
    "wof:name":"Canadian Freightways Ltd",
    "wof:placetype":"venue"
},
  "geometry": {"coordinates":[-120.37084197999999,50.6682472229],"type":"Point"}
}