{
  "type": "Feature",
  "properties": {
    "iso:country":"CA",
    "sg:address":"56 Rue DE LA Fabrique",
    "sg:city":"Saint-Benoit-Labre",
    "sg:classifiers":[
        {
            "category":"Education",
            "subcategory":"School",
            "type":"Public Place"
        }
    ],
    "sg:phone":"+1 418 226 2677",
    "sg:postcode":"G0M 1P0",
    "sg:province":"QC",
    "wof:name":"Ecole Notre-Dame-Du-Rosaire",
    "wof:placetype":"venue"
},
  "geometry": {"coordinates":[-70.793297,46.067677],"type":"Point"}
}