{
  "type": "Feature",
  "properties": {
    "addr:full":"592 Erin St Winnipeg MB R3G 2V9",
    "addr:housenumber":"592",
    "addr:postcode":"r3g 2v9",
    "addr:street":"Erin St",
    "iso:country":"CA",
    "sg:address":"592 Erin St",
    "sg:city":"Winnipeg",
    "sg:classifiers":[
        {
            "category":"Utilities",
            "type":"Services"
        }
    ],
    "sg:phone":"+1 204 885 4445",
    "sg:postcode":"R3G 2V9",
    "sg:province":"MB",
    "sg:tags":[
        "locating"
    ],
    "wof:name":"Age Pipe & Cable Locators Inc",
    "wof:placetype":"venue"
},
  "geometry": {"coordinates":[-97.18531,49.885117],"type":"Point"}
}