{
  "type": "Feature",
  "properties": {
    "addr:full":"Brampton ON L6X 3E1",
    "addr:postcode":"l6x 3e1",
    "iso:country":"CA",
    "sg:city":"Brampton",
    "sg:classifiers":[
        {
            "category":"Shopping",
            "subcategory":"Discount & Variety Stores",
            "type":"Retail Goods"
        }
    ],
    "sg:phone":"+1 905 459 8137",
    "sg:postcode":"L6X 3E1",
    "sg:province":"ON",
    "wof:name":"Hasty Market",
    "wof:placetype":"venue"
},
  "geometry": {"coordinates":[-79.773582,43.673771],"type":"Point"}
}