{
  "type": "Feature",
  "properties": {
    "addr:full":"Calgary AB T2P 3P8",
    "addr:postcode":"t2p 3p8",
    "iso:country":"CA",
    "sg:city":"Calgary",
    "sg:classifiers":[
        {
            "category":"Professional",
            "subcategory":"Engineering",
            "type":"Services"
        }
    ],
    "sg:phone":"+1 403 232 6206",
    "sg:postcode":"T2P 3P8",
    "sg:province":"AB",
    "sg:tags":[
        "engineer"
    ],
    "wof:name":"Ashton Jenkins & Assoc Ltd",
    "wof:placetype":"venue"
},
  "geometry": {"coordinates":[-114.07717895499999,51.0470161438],"type":"Point"}
}