{
  "type": "Feature",
  "properties": {
    "addr:full":"171 Lombard St Smiths Falls ON K7A 5B8",
    "addr:housenumber":"171",
    "addr:postcode":"k7a 5b8",
    "addr:street":"Lombard St",
    "iso:country":"CA",
    "sg:address":"171 Lombard St",
    "sg:city":"Smiths Falls",
    "sg:classifiers":[
        {
            "category":"Autos & Motor Vehicles",
            "subcategory":"Automobile Sales",
            "type":"Retail Goods"
        }
    ],
    "sg:phone":"+1 613 284 0023",
    "sg:postcode":"K7A 5B8",
    "sg:province":"ON",
    "sg:tags":[
        "car",
        "dealer"
    ],
    "wof:name":"Street Kia",
    "wof:placetype":"venue"
},
  "geometry": {"coordinates":[-76.033463,44.886524],"type":"Point"}
}