{
  "type": "Feature",
  "properties": {
    "addr:full":"Sainte-Foy QC G1N 2G3",
    "addr:postcode":"g1n 2g3",
    "iso:country":"CA",
    "sg:city":"Sainte-Foy",
    "sg:classifiers":[
        {
            "category":"Building & Trades",
            "subcategory":"Equipment Rental",
            "type":"Services"
        }
    ],
    "sg:phone":"+1 418 527 2133",
    "sg:postcode":"G1N 2G3",
    "sg:province":"QC",
    "sg:tags":[
        "sound",
        "leasing",
        "system"
    ],
    "wof:name":"Sonorisation Delta Eclairage",
    "wof:placetype":"venue"
},
  "geometry": {"coordinates":[-71.28211212159999,46.7951965332],"type":"Point"}
}