{
  "type": "Feature",
  "properties": {
    "addr:full":"Montreal QC H2N 1N7",
    "addr:postcode":"h2n 1n7",
    "iso:country":"CA",
    "sg:city":"Montreal",
    "sg:classifiers":[
        {
            "category":"Wholesale",
            "subcategory":"Apparel",
            "type":"Manufacturing & Wholesale Goods"
        }
    ],
    "sg:phone":"+1 514 388 4840",
    "sg:postcode":"H2N 1N7",
    "sg:province":"QC",
    "sg:tags":[
        "textile",
        "converting"
    ],
    "wof:name":"Perlini Fabrics Intl Ltd",
    "wof:placetype":"venue"
},
  "geometry": {"coordinates":[-73.6517410278,45.5444831848],"type":"Point"}
}