{
  "type": "Feature",
  "properties": {
    "addr:full":"251 Spadina Ave Toronto ON M5T 2E2",
    "addr:housenumber":"251",
    "addr:postcode":"m5t 2e2",
    "addr:street":"Spadina Ave",
    "iso:country":"CA",
    "sg:address":"251 Spadina Ave",
    "sg:city":"Toronto",
    "sg:classifiers":[
        {
            "category":"Shopping",
            "subcategory":"Clothing, Apparel, & Fashions",
            "type":"Retail Goods"
        }
    ],
    "sg:phone":"+1 416 979 1668",
    "sg:postcode":"M5T 2E2",
    "sg:province":"ON",
    "sg:tags":[
        "accessory"
    ],
    "wof:name":"U C Fashion Mfr",
    "wof:placetype":"venue"
},
  "geometry": {"coordinates":[-79.397324,43.651794],"type":"Point"}
}