{
  "type": "Feature",
  "properties": {
    "addr:full":"138 8th Ave E Vancouver BC V5T 1R7",
    "addr:housenumber":"138",
    "addr:postcode":"v5t 1r7",
    "addr:street":"8Th Ave E",
    "iso:country":"CA",
    "sg:address":"138 8th Ave E",
    "sg:city":"Vancouver",
    "sg:classifiers":[
        {
            "category":"Manufacturing",
            "subcategory":"Apparel",
            "type":"Manufacturing & Wholesale Goods"
        }
    ],
    "sg:phone":"+1 604 873 2118",
    "sg:postcode":"V5T 1R7",
    "sg:province":"BC",
    "sg:tags":[
        "clothing"
    ],
    "wof:name":"Dynasty Fashion Wear Mfg Ltd",
    "wof:placetype":"venue"
},
  "geometry": {"coordinates":[-123.102111816,49.2635803223],"type":"Point"}
}