{
  "type": "Feature",
  "properties": {
    "addr:full":"51 Delta Park Blvd # 4 Brampton ON L6T 5E7",
    "addr:housenumber":"51",
    "addr:postcode":"l6t 5e7",
    "addr:street":"Delta Park Blvd # 4",
    "iso:country":"CA",
    "sg:address":"51 Delta Park Blvd # 4",
    "sg:city":"Brampton",
    "sg:classifiers":[
        {
            "category":"Home & Garden",
            "subcategory":"Building Materials",
            "type":"Retail Goods"
        }
    ],
    "sg:phone":"+1 905 793 4773",
    "sg:postcode":"L6T 5E7",
    "sg:province":"ON",
    "sg:tags":[
        "glass",
        "window",
        "plate"
    ],
    "wof:name":"Limited Edition Glassworks Inc",
    "wof:placetype":"venue"
},
  "geometry": {"coordinates":[-79.686745,43.738995],"type":"Point"}
}