{
  "type": "Feature",
  "properties": {
    "addr:full":"New Hamburg ON N3A 1E7",
    "addr:postcode":"n3a 1e7",
    "iso:country":"CA",
    "sg:city":"New Hamburg",
    "sg:classifiers":[
        {
            "category":"Autos & Motor Vehicles",
            "subcategory":"Auto Supplies",
            "type":"Retail Goods"
        }
    ],
    "sg:phone":"+1 519 662 2063",
    "sg:postcode":"N3A 1E7",
    "sg:province":"ON",
    "sg:tags":[
        "automobile",
        "parts"
    ],
    "wof:name":"Mc Farlane Automotive Inc",
    "wof:placetype":"venue"
},
  "geometry": {"coordinates":[-80.708961,43.377975],"type":"Point"}
}