{
  "type": "Feature",
  "properties": {
    "addr:full":"640 Windmill Rd Dartmouth NS B3B 1B8",
    "addr:housenumber":"640",
    "addr:postcode":"b3b 1b8",
    "addr:street":"Windmill Rd",
    "iso:country":"CA",
    "sg:address":"640 Windmill Rd",
    "sg:city":"Dartmouth",
    "sg:classifiers":[
        {
            "category":"Manufacturing",
            "subcategory":"Signs",
            "type":"Manufacturing & Wholesale Goods"
        }
    ],
    "sg:phone":"+1 902 468 6229",
    "sg:postcode":"B3B 1B8",
    "sg:province":"NS",
    "wof:name":"Signs Now",
    "wof:placetype":"venue"
},
  "geometry": {"coordinates":[-63.60498,44.698578],"type":"Point"}
}