{
  "type": "Feature",
  "properties": {
    "addr:full":"1215 Wyandotte St E Windsor ON N9A 3K6",
    "addr:housenumber":"1215",
    "addr:postcode":"n9a 3k6",
    "addr:street":"Wyandotte St E",
    "iso:country":"CA",
    "sg:address":"1215 Wyandotte St E",
    "sg:city":"Windsor",
    "sg:classifiers":[
        {
            "category":"Autos & Motor Vehicles",
            "subcategory":"Automobile Sales",
            "type":"Retail Goods"
        }
    ],
    "sg:phone":"+1 519 255 1953",
    "sg:postcode":"N9A 3K6",
    "sg:province":"ON",
    "sg:tags":[
        "car",
        "dealer"
    ],
    "wof:name":"Sam's Auto Ctr Ltd",
    "wof:placetype":"venue"
},
  "geometry": {"coordinates":[-83.01979799999999,42.32003],"type":"Point"}
}