{
  "type": "Feature",
  "properties": {
    "addr:full":"348 11E Av S Sherbrooke QC J1G 2T5",
    "addr:housenumber":"348",
    "addr:postcode":"j1g 2t5",
    "addr:street":"11E Av S",
    "iso:country":"CA",
    "sg:address":"348 11E Av S",
    "sg:city":"Sherbrooke",
    "sg:classifiers":[
        {
            "category":"Personal",
            "subcategory":"Beauty Salon",
            "type":"Services"
        }
    ],
    "sg:phone":"+1 819 821 4100",
    "sg:postcode":"J1G 2T5",
    "sg:province":"QC",
    "wof:name":"Salon DE Coiffure Coupe Ideale",
    "wof:placetype":"venue"
},
  "geometry": {"coordinates":[-71.87130737299999,45.4029273987],"type":"Point"}
}