{
  "type": "Feature",
  "properties": {
    "addr:full":"378 Rue Saint-Pierre Saint-Marcel-DE-Richelieu QC J0H 1T0",
    "addr:housenumber":"378",
    "addr:postcode":"j0h 1t0",
    "addr:street":"Rue Saint-Pierre",
    "iso:country":"CA",
    "sg:address":"378 Rue Saint-Pierre",
    "sg:city":"Saint-Marcel-DE-Richelieu",
    "sg:classifiers":[
        {
            "category":"Retail",
            "subcategory":"Auto Repair",
            "type":"Services"
        }
    ],
    "sg:phone":"+1 450 794 2860",
    "sg:postcode":"J0H 1T0",
    "sg:province":"QC",
    "sg:tags":[
        "repairing",
        "automobile"
    ],
    "wof:name":"G L Chamberland Garage Inc",
    "wof:placetype":"venue"
},
  "geometry": {"coordinates":[-72.89228799999999,45.857121],"type":"Point"}
}