{
  "type": "Feature",
  "properties": {
    "iso:country":"CA",
    "sg:address":"130 Jane Ave",
    "sg:city":"Kingston",
    "sg:classifiers":[
        {
            "category":"Health Services",
            "subcategory":"Doctor",
            "type":"Services"
        }
    ],
    "sg:phone":"+1 613 546 4388",
    "sg:postcode":"K7M 7J1",
    "sg:province":"ON",
    "sg:tags":[
        "clinic"
    ],
    "wof:name":"Acupuncture Clinic",
    "wof:placetype":"venue"
},
  "geometry": {"coordinates":[-76.523026,44.249294],"type":"Point"}
}