{
  "type": "Feature",
  "properties": {
    "addr:full":"Saskatoon SK S7K 5E4",
    "addr:postcode":"s7k 5e4",
    "iso:country":"CA",
    "sg:city":"Saskatoon",
    "sg:classifiers":[
        {
            "category":"Retail",
            "subcategory":"Veterinary Services",
            "type":"Services"
        }
    ],
    "sg:phone":"+1 306 668 4223",
    "sg:postcode":"S7K 5E4",
    "sg:province":"SK",
    "sg:tags":[
        "veterinarian"
    ],
    "wof:name":"Griebel, Elizabeth DVM",
    "wof:placetype":"venue"
},
  "geometry": {"coordinates":[-106.63551330599999,52.1680145264],"type":"Point"}
}