{
  "type": "Feature",
  "properties": {
    "addr:full":"348 Queen Mary St Ottawa ON K1K 1W9",
    "addr:housenumber":"348",
    "addr:postcode":"k1k 1w9",
    "addr:street":"Queen Mary St",
    "iso:country":"CA",
    "sg:address":"348 Queen Mary St",
    "sg:city":"Ottawa",
    "sg:classifiers":[
        {
            "category":"Local Transit",
            "type":"Transportation"
        }
    ],
    "sg:phone":"+1 613 744 1312",
    "sg:postcode":"K1K 1W9",
    "sg:province":"ON",
    "sg:tags":[
        "bus",
        "line"
    ],
    "wof:name":"G Boudria Transportation Inc",
    "wof:placetype":"venue"
},
  "geometry": {"coordinates":[-75.650352,45.425186],"type":"Point"}
}