{
  "type": "Feature",
  "properties": {
    "addr:full":"936 Eglinton Ave W Toronto ON M6C 2C2",
    "addr:housenumber":"936",
    "addr:postcode":"m6c 2c2",
    "addr:street":"Eglinton Ave W",
    "iso:country":"CA",
    "sg:address":"936 Eglinton Ave W",
    "sg:city":"Toronto",
    "sg:classifiers":[
        {
            "category":"Restaurant",
            "type":"Food & Drink"
        }
    ],
    "sg:phone":"+1 416 781 1717",
    "sg:postcode":"M6C 2C2",
    "sg:province":"ON",
    "wof:name":"Sette Mezzo",
    "wof:placetype":"venue"
},
  "geometry": {"coordinates":[-79.428299,43.700565],"type":"Point"}
}