{
  "type": "Feature",
  "properties": {
    "addr:full":"Toronto ON M5N 1B1",
    "addr:postcode":"m5n 1b1",
    "iso:country":"CA",
    "sg:city":"Toronto",
    "sg:classifiers":[
        {
            "category":"Professional",
            "subcategory":"Business Services",
            "type":"Services"
        }
    ],
    "sg:phone":"+1 905 771 3685",
    "sg:postcode":"M5N 1B1",
    "sg:province":"ON",
    "sg:tags":[
        "interior",
        "consultant",
        "design",
        "decorator"
    ],
    "wof:name":"Office Interior Design Group",
    "wof:placetype":"venue"
},
  "geometry": {"coordinates":[-79.41338348390001,43.7034683228],"type":"Point"}
}