{
  "type": "Feature",
  "properties": {
    "addr:full":"526 7th Ave Keremeos BC V0X 1N0",
    "addr:housenumber":"526",
    "addr:postcode":"v0x 1n0",
    "addr:street":"7Th Ave",
    "iso:country":"CA",
    "sg:address":"526 7th Ave",
    "sg:city":"Keremeos",
    "sg:classifiers":[
        {
            "category":"Shopping",
            "subcategory":"Gifts & Souvenirs",
            "type":"Retail Goods"
        }
    ],
    "sg:phone":"+1 250 499 5543",
    "sg:postcode":"V0X 1N0",
    "sg:province":"BC",
    "sg:tags":[
        "shop",
        "pharmacy"
    ],
    "wof:name":"Pharmasave",
    "wof:placetype":"venue"
},
  "geometry": {"coordinates":[-119.82665252699999,49.2052879333],"type":"Point"}
}