{
  "type": "Feature",
  "properties": {
    "addr:full":"4912 Still Creek Ave Burnaby BC V5C 4E4",
    "addr:housenumber":"4912",
    "addr:postcode":"v5c 4e4",
    "addr:street":"Still Creek Ave",
    "iso:country":"CA",
    "sg:address":"4912 Still Creek Ave",
    "sg:city":"Burnaby",
    "sg:classifiers":[
        {
            "category":"Shopping",
            "subcategory":"Used Merchandise",
            "type":"Retail Goods"
        }
    ],
    "sg:phone":"+1 604 299 2967",
    "sg:postcode":"V5C 4E4",
    "sg:province":"BC",
    "sg:tags":[
        "antique"
    ],
    "wof:name":"Jack's Used Building Materials",
    "wof:placetype":"venue"
},
  "geometry": {"coordinates":[-122.99215700000001,49.260715],"type":"Point"}
}