{
  "type": "Feature",
  "properties": {
    "iso:country":"CA",
    "sg:city":"Bedford",
    "sg:classifiers":[
        {
            "category":"Building & Trades",
            "subcategory":"Construction",
            "type":"Services"
        }
    ],
    "sg:phone":"+1 450 248 2850",
    "sg:postcode":"J0J 1A0",
    "sg:province":"QC",
    "sg:tags":[
        "excavating",
        "contractor"
    ],
    "wof:name":"J A Beaudoin Construction Ltee",
    "wof:placetype":"venue"
},
  "geometry": {"coordinates":[-72.98598480219999,45.1198005676],"type":"Point"}
}