{
  "type": "Feature",
  "properties": {
    "iso:country":"CA",
    "sg:address":"4250 1E Av",
    "sg:city":"Charlesbourg",
    "sg:classifiers":[
        {
            "category":"Retail",
            "subcategory":"Laundry & Dry Cleaning",
            "type":"Services"
        }
    ],
    "sg:phone":"+1 418 623 0432",
    "sg:postcode":"G1H 2S5",
    "sg:province":"QC",
    "sg:tags":[
        "cleaners"
    ],
    "wof:name":"Nettoyeur Betty Brite",
    "wof:placetype":"venue"
},
  "geometry": {"coordinates":[-71.249405,46.842777],"type":"Point"}
}