{
  "type": "Feature",
  "properties": {
    "addr:full":"947 19 St S Lethbridge AB T1J 3H5",
    "addr:housenumber":"19",
    "addr:postcode":"t1j 3h5",
    "addr:street":"947;St S",
    "iso:country":"CA",
    "sg:address":"947 19 St S",
    "sg:city":"Lethbridge",
    "sg:classifiers":[
        {
            "category":"Health Services",
            "subcategory":"Doctor",
            "type":"Services"
        }
    ],
    "sg:phone":"+1 403 328 5121",
    "sg:postcode":"T1J 3H5",
    "sg:province":"AB",
    "sg:tags":[
        "physician",
        "surgeon"
    ],
    "wof:name":"Munoz, Washington MD",
    "wof:placetype":"venue"
},
  "geometry": {"coordinates":[-112.814453,49.684814],"type":"Point"}
}