{
  "type": "Feature",
  "properties": {
    "addr:full":"295 Main St Florenceville NB E7L 3G5",
    "addr:housenumber":"295",
    "addr:postcode":"e7l 3g5",
    "addr:street":"Main St",
    "iso:country":"CA",
    "sg:address":"295 Main St",
    "sg:city":"Florenceville",
    "sg:classifiers":[
        {
            "category":"Shopping",
            "subcategory":"Catalog Store",
            "type":"Retail Goods"
        }
    ],
    "sg:phone":"+1 506 392 5561",
    "sg:postcode":"E7L 3G5",
    "sg:province":"NB",
    "sg:tags":[
        "mail",
        "order",
        "internet"
    ],
    "wof:name":"Sears Canada Inc",
    "wof:placetype":"venue"
},
  "geometry": {"coordinates":[-67.6188201904,46.442276001],"type":"Point"}
}