{
  "type": "Feature",
  "properties": {
    "addr:full":"825 Coxwell Ave #4 East York ON M4C 3E7",
    "addr:housenumber":"825",
    "addr:postcode":"m4c 3e7",
    "addr:street":"Coxwell Ave # 4",
    "iso:country":"CA",
    "sg:address":"825 Coxwell Ave #4",
    "sg:city":"East York",
    "sg:classifiers":[
        {
            "category":"Health Services",
            "subcategory":"Doctor",
            "type":"Services"
        }
    ],
    "sg:phone":"+1 416 462 9449",
    "sg:postcode":"M4C 3E7",
    "sg:province":"ON",
    "sg:tags":[
        "physician",
        "surgeon"
    ],
    "wof:name":"Borrett, D MD",
    "wof:placetype":"venue"
},
  "geometry": {"coordinates":[-79.326286,43.690365],"type":"Point"}
}