{
  "type": "Feature",
  "properties": {
    "addr:full":"6511A Mississauga Rd Mississauga ON L5N 1A6",
    "addr:housenumber":"6511a",
    "addr:postcode":"l5n 1a6",
    "addr:street":"Mississauga Rd",
    "iso:country":"CA",
    "sg:address":"6511A Mississauga Rd",
    "sg:city":"Mississauga",
    "sg:classifiers":[
        {
            "category":"Shopping",
            "subcategory":"Clothing, Apparel, & Fashions",
            "type":"Retail Goods"
        }
    ],
    "sg:phone":"+1 905 814 7933",
    "sg:postcode":"L5N 1A6",
    "sg:province":"ON",
    "wof:name":"Images That Suit Ltd",
    "wof:placetype":"venue"
},
  "geometry": {"coordinates":[-79.7376861572,43.5980529785],"type":"Point"}
}