{
  "type": "Feature",
  "properties": {
    "addr:full":"2523 Ch Du Fleuve Saint-Romuald QC G6W 1X5",
    "addr:postcode":"2523;g6w 1x5",
    "addr:street":"Ch Du Fleuve",
    "iso:country":"CA",
    "sg:address":"2523 Ch Du Fleuve",
    "sg:city":"Saint-Romuald",
    "sg:classifiers":[
        {
            "category":"Personal",
            "subcategory":"Beauty Salon",
            "type":"Services"
        }
    ],
    "sg:phone":"+1 418 839 0562",
    "sg:postcode":"G6W 1X5",
    "sg:province":"QC",
    "wof:name":"Salon Martine",
    "wof:placetype":"venue"
},
  "geometry": {"coordinates":[-71.23024700000001,46.759205],"type":"Point"}
}