{
  "type": "Feature",
  "properties": {
    "iso:country":"CA",
    "sg:city":"Saint-Clet",
    "sg:classifiers":[
        {
            "category":"Government",
            "subcategory":"Post Office",
            "type":"Public Place"
        }
    ],
    "sg:phone":"+1 450 456 9650",
    "sg:postcode":"J0P 1S0",
    "sg:province":"QC",
    "wof:name":"Comptoir Postal St-Clet",
    "wof:placetype":"venue"
},
  "geometry": {"coordinates":[-74.22295379640001,45.3517684937],"type":"Point"}
}