{
  "type": "Feature",
  "properties": {
    "addr:full":"5678 Burleigh Cres SE Calgary AB T2H 1Z8",
    "addr:housenumber":"5678",
    "addr:postcode":"t2h 1z8",
    "addr:street":"Burleigh Cres Se",
    "iso:country":"CA",
    "sg:address":"5678 Burleigh Cres SE",
    "sg:city":"Calgary",
    "sg:classifiers":[
        {
            "category":"Professional",
            "subcategory":"Business Services",
            "type":"Services"
        }
    ],
    "sg:phone":"+1 403 253 9401",
    "sg:postcode":"T2H 1Z8",
    "sg:province":"AB",
    "sg:tags":[
        "appraiser",
        "auctioneer"
    ],
    "wof:name":"Galvin Auction CO Ltd",
    "wof:placetype":"venue"
},
  "geometry": {"coordinates":[-114.043159,51.004368],"type":"Point"}
}