{
  "type": "Feature",
  "properties": {
    "addr:full":"890 Dufferin St Woodstock ON N4S 1Z1",
    "addr:housenumber":"890",
    "addr:postcode":"n4s 1z1",
    "addr:street":"Dufferin St",
    "iso:country":"CA",
    "sg:address":"890 Dufferin St",
    "sg:city":"Woodstock",
    "sg:classifiers":[
        {
            "category":"Retail",
            "subcategory":"Auto Repair",
            "type":"Services"
        }
    ],
    "sg:phone":"+1 519 539 2525",
    "sg:postcode":"N4S 1Z1",
    "sg:province":"ON",
    "sg:tags":[
        "automobile",
        "rustproofing",
        "undercoating"
    ],
    "wof:name":"Krown Rust Control Ctr",
    "wof:placetype":"venue"
},
  "geometry": {"coordinates":[-80.7378921509,43.1278305054],"type":"Point"}
}