{
  "type": "Feature",
  "properties": {
    "addr:full":"9610 287 St Maple Ridge BC V2W 1L1",
    "addr:housenumber":"9610",
    "addr:postcode":"v2w 1l1",
    "addr:street":"287 St",
    "iso:country":"CA",
    "sg:address":"9610 287 St",
    "sg:city":"Maple Ridge",
    "sg:classifiers":[
        {
            "category":"Bars & Pubs",
            "type":"Food & Drink"
        }
    ],
    "sg:phone":"+1 604 462 8445",
    "sg:postcode":"V2W 1L1",
    "sg:province":"BC",
    "wof:name":"Shake & Shingle Pub Ltd",
    "wof:placetype":"venue"
},
  "geometry": {"coordinates":[-122.42834499999999,49.177017],"type":"Point"}
}