{
  "type": "Feature",
  "properties": {
    "addr:full":"1149 Gladstone Ave Ottawa ON K1Y 3H7",
    "addr:housenumber":"1149",
    "addr:postcode":"k1y 3h7",
    "addr:street":"Gladstone Ave",
    "iso:country":"CA",
    "sg:address":"1149 Gladstone Ave",
    "sg:city":"Ottawa",
    "sg:classifiers":[
        {
            "category":"Education",
            "subcategory":"School",
            "type":"Public Place"
        }
    ],
    "sg:phone":"+1 613 728 4671",
    "sg:postcode":"K1Y 3H7",
    "sg:province":"ON",
    "wof:name":"Connaught Public School",
    "wof:placetype":"venue"
},
  "geometry": {"coordinates":[-75.7259979248,45.4002571106],"type":"Point"}
}