{
  "type": "Feature",
  "properties": {
    "addr:full":"2478 Thompson Rd Smithville ON L0R 2A0",
    "addr:housenumber":"2478",
    "addr:postcode":"l0r 2a0",
    "addr:street":"Thompson Rd",
    "iso:country":"CA",
    "sg:address":"2478 Thompson Rd",
    "sg:city":"Smithville",
    "sg:classifiers":[
        {
            "category":"Wholesale",
            "subcategory":"Farm Supplies",
            "type":"Manufacturing & Wholesale Goods"
        }
    ],
    "sg:phone":"+1 905 957 3397",
    "sg:postcode":"L0R 2A0",
    "sg:province":"ON",
    "sg:tags":[
        "grain"
    ],
    "wof:name":"Niagara Grain & Feed Elevator",
    "wof:placetype":"venue"
},
  "geometry": {"coordinates":[-79.53628500000001,43.107239],"type":"Point"}
}