{
  "type": "Feature",
  "properties": {
    "addr:full":"1944 Lincoln Rd Fredericton NB E3B 8M7",
    "addr:housenumber":"1944",
    "addr:postcode":"e3b 8m7",
    "addr:street":"Lincoln Rd",
    "iso:country":"CA",
    "sg:address":"1944 Lincoln Rd",
    "sg:city":"Fredericton",
    "sg:classifiers":[
        {
            "category":"Autos & Motor Vehicles",
            "subcategory":"Automobile Sales",
            "type":"Retail Goods"
        }
    ],
    "sg:phone":"+1 506 457 1905",
    "sg:postcode":"E3B 8M7",
    "sg:province":"NB",
    "sg:tags":[
        "car",
        "dealer"
    ],
    "wof:name":"East Coast Wheels Ltd",
    "wof:placetype":"venue"
},
  "geometry": {"coordinates":[-66.577209,45.903183],"type":"Point"}
}