{
  "type": "Feature",
  "properties": {
    "iso:country":"CA",
    "sg:address":"1248 Ward Rd",
    "sg:city":"Aylesford",
    "sg:classifiers":[
        {
            "category":"Restaurant",
            "type":"Food & Drink"
        }
    ],
    "sg:phone":"+1 902 847 1900",
    "sg:postcode":"B0P 1C0",
    "sg:province":"NS",
    "wof:name":"Farmer's Family Diner",
    "wof:placetype":"venue"
},
  "geometry": {"coordinates":[-64.8375244141,45.0277938843],"type":"Point"}
}