{
  "type": "Feature",
  "properties": {
    "addr:full":"1245 Av Felix-Leclerc Saint-Jerome QC J7Z 7C1",
    "addr:housenumber":"1245",
    "addr:postcode":"j7z 7c1",
    "addr:street":"Av Felix-Leclerc Saint-Jerome",
    "iso:country":"CA",
    "sg:address":"1245 Av Felix-Leclerc",
    "sg:city":"Saint-Jerome",
    "sg:classifiers":[
        {
            "category":"Building & Trades",
            "subcategory":"Electrical",
            "type":"Services"
        }
    ],
    "sg:phone":"+1 450 431 7065",
    "sg:postcode":"J7Z 7C1",
    "sg:province":"QC",
    "sg:tags":[
        "electric",
        "contractor"
    ],
    "wof:name":"Sylvain Landry & Fils Inc",
    "wof:placetype":"venue"
},
  "geometry": {"coordinates":[-73.96960449220001,45.7658843994],"type":"Point"}
}