{
  "type": "Feature",
  "properties": {
    "iso:country":"CA",
    "sg:address":"15827 87 Ave NW",
    "sg:city":"Edmonton",
    "sg:classifiers":[
        {
            "category":"Personal",
            "subcategory":"Beauty Salon",
            "type":"Services"
        }
    ],
    "sg:phone":"+1 780 484 8347",
    "sg:postcode":"T5R 4G7",
    "sg:province":"AB",
    "wof:name":"Singleton's Hair Care",
    "wof:placetype":"venue"
},
  "geometry": {"coordinates":[-113.59565734900001,53.5193252563],"type":"Point"}
}