{
  "type": "Feature",
  "properties": {
    "addr:full":"516 Plains Rd E # 11 Burlington ON L7T 2E1",
    "addr:housenumber":"516",
    "addr:postcode":"l7t 2e1",
    "addr:street":"Plains Rd E # 11",
    "iso:country":"CA",
    "sg:address":"516 Plains Rd E # 11",
    "sg:city":"Burlington",
    "sg:classifiers":[
        {
            "category":"Shopping",
            "subcategory":"Optical Goods",
            "type":"Retail Goods"
        }
    ],
    "sg:phone":"+1 905 631 6588",
    "sg:postcode":"L7T 2E1",
    "sg:province":"ON",
    "sg:tags":[
        "optician"
    ],
    "wof:name":"Optical Clearance Outlet Inc",
    "wof:placetype":"venue"
},
  "geometry": {"coordinates":[-79.835724,43.319336],"type":"Point"}
}