{
  "type": "Feature",
  "properties": {
    "iso:country":"CA",
    "sg:address":"525 Boul Wilfrid-Hamel # A07",
    "sg:city":"Quebec",
    "sg:classifiers":[
        {
            "category":"Organizations",
            "subcategory":"Professional Association",
            "type":"Services"
        }
    ],
    "sg:phone":"+1 418 647 3684",
    "sg:postcode":"G1M 2S8",
    "sg:province":"QC",
    "wof:name":"Assn-Personnes Interessees",
    "wof:placetype":"venue"
},
  "geometry": {"coordinates":[-71.2484588623,46.8202056885],"type":"Point"}
}