{
  "type": "Feature",
  "properties": {
    "addr:full":"25 Kirby Ave E Dauphin MB R7N 0E8",
    "addr:housenumber":"25",
    "addr:postcode":"r7n 0e8",
    "addr:street":"Kirby Ave E Dauphin",
    "iso:country":"CA",
    "sg:address":"25 Kirby Ave E",
    "sg:city":"Dauphin",
    "sg:classifiers":[
        {
            "category":"Organizations",
            "subcategory":"Religious Organization",
            "type":"Services"
        }
    ],
    "sg:phone":"+1 204 638 8141",
    "sg:postcode":"R7N 0E8",
    "sg:province":"MB",
    "sg:tags":[
        "church"
    ],
    "wof:name":"Anglican Church",
    "wof:placetype":"venue"
},
  "geometry": {"coordinates":[-100.038948,51.156841],"type":"Point"}
}