{
  "type": "Feature",
  "properties": {
    "iso:country":"CA",
    "sg:address":"847 1st Ave W",
    "sg:city":"Prince Rupert",
    "sg:classifiers":[
        {
            "category":"Organizations",
            "subcategory":"Labor Organization",
            "type":"Services"
        }
    ],
    "sg:phone":"+1 250 624 3558",
    "sg:postcode":"V8J 1B3",
    "sg:province":"BC",
    "wof:name":"International Longshoreman",
    "wof:placetype":"venue"
},
  "geometry": {"coordinates":[-130.331497192,54.3109588623],"type":"Point"}
}