{
  "type": "Feature",
  "properties": {
    "addr:full":"99 King St E Chatham ON N7M 3M9",
    "addr:housenumber":"99",
    "addr:postcode":"n7m 3m9",
    "addr:street":"King St E",
    "iso:country":"CA",
    "sg:address":"99 King St E",
    "sg:city":"Chatham",
    "sg:classifiers":[
        {
            "category":"Banks & Credit Unions",
            "subcategory":"Bank",
            "type":"Services"
        }
    ],
    "sg:phone":"+1 519 352 7150",
    "sg:postcode":"N7M 3M9",
    "sg:province":"ON",
    "wof:name":"Cibc",
    "wof:placetype":"venue"
},
  "geometry": {"coordinates":[-82.177773,42.405609],"type":"Point"}
}