{
  "type": "Feature",
  "properties": {
    "addr:full":"Lajeunesse Ave Ile-A-LA-Crosse SK S0M 1C0",
    "addr:postcode":"s0m 1c0",
    "addr:street":"Lajeunesse Ave",
    "iso:country":"CA",
    "sg:address":"Lajeunesse Ave",
    "sg:city":"Ile-A-LA-Crosse",
    "sg:classifiers":[
        {
            "category":"Building & Trades",
            "subcategory":"Electrical",
            "type":"Services"
        }
    ],
    "sg:phone":"+1 306 833 2185",
    "sg:postcode":"S0M 1C0",
    "sg:province":"SK",
    "sg:tags":[
        "electric",
        "contractor"
    ],
    "wof:name":"Sakitawak Electric Ltd",
    "wof:placetype":"venue"
},
  "geometry": {"coordinates":[-107.90625799999999,55.452347],"type":"Point"}
}