{
  "type": "Feature",
  "properties": {
    "addr:full":"664 Red River Rd Thunder Bay ON P7B 1H8",
    "addr:housenumber":"664",
    "addr:postcode":"p7b 1h8",
    "addr:street":"Red River Rd",
    "iso:country":"CA",
    "sg:address":"664 Red River Rd",
    "sg:city":"Thunder Bay",
    "sg:classifiers":[
        {
            "category":"Organizations",
            "subcategory":"Religious Organization",
            "type":"Services"
        }
    ],
    "sg:phone":"+1 807 345 6541",
    "sg:postcode":"P7B 1H8",
    "sg:province":"ON",
    "sg:tags":[
        "church"
    ],
    "wof:name":"Corpus Christi Church",
    "wof:placetype":"venue"
},
  "geometry": {"coordinates":[-89.243263,48.440842],"type":"Point"}
}