{
  "type": "Feature",
  "properties": {
    "iso:country":"CA",
    "sg:address":"3670 Aut Laval O",
    "sg:city":"Chomedey",
    "sg:classifiers":[
        {
            "category":"Autos & Motor Vehicles",
            "subcategory":"Automobile Sales",
            "type":"Retail Goods"
        }
    ],
    "sg:phone":"+1 450 682 3670",
    "sg:postcode":"H7T 2H6",
    "sg:province":"QC",
    "sg:tags":[
        "car",
        "dealer"
    ],
    "wof:name":"Contact Pontiac Buick Inc",
    "wof:placetype":"venue"
},
  "geometry": {"coordinates":[-73.747871,45.535],"type":"Point"}
}