{
  "type": "Feature",
  "properties": {
    "addr:full":"Oakville ON L6J 6G6",
    "addr:postcode":"l6j 6g6",
    "iso:country":"CA",
    "sg:city":"Oakville",
    "sg:classifiers":[
        {
            "category":"Wholesale",
            "subcategory":"Non-durable Goods",
            "type":"Manufacturing & Wholesale Goods"
        }
    ],
    "sg:phone":"+1 905 845 1923",
    "sg:postcode":"L6J 6G6",
    "sg:province":"ON",
    "sg:tags":[
        "advertising"
    ],
    "wof:name":"Executayne Marketing Ltd",
    "wof:placetype":"venue"
},
  "geometry": {"coordinates":[-79.68436431879999,43.458065033],"type":"Point"}
}