{
  "type": "Feature",
  "properties": {
    "iso:country":"CA",
    "sg:city":"Vancouver",
    "sg:classifiers":[
        {
            "category":"Professional",
            "subcategory":"Management & Consulting",
            "type":"Services"
        }
    ],
    "sg:phone":"+1 604 669 7300",
    "sg:postcode":"V6B 2S8",
    "sg:province":"BC",
    "sg:tags":[
        "consultant",
        "business"
    ],
    "wof:name":"Context Research Ltd",
    "wof:placetype":"venue"
},
  "geometry": {"coordinates":[-123.123497009,49.2741661072],"type":"Point"}
}