{
  "type": "Feature",
  "properties": {
    "addr:full":"34 Main St Selkirk ON N0A 1P0",
    "addr:housenumber":"34",
    "addr:postcode":"n0a 1p0",
    "addr:street":"Main St",
    "iso:country":"CA",
    "sg:address":"34 Main St",
    "sg:city":"Selkirk",
    "sg:classifiers":[
        {
            "category":"Education",
            "subcategory":"Library",
            "type":"Public Place"
        }
    ],
    "sg:phone":"+1 905 776 2127",
    "sg:postcode":"N0A 1P0",
    "sg:province":"ON",
    "wof:name":"Selkirk Public Library",
    "wof:placetype":"venue"
},
  "geometry": {"coordinates":[-79.928574,42.834045],"type":"Point"}
}