{
  "type": "Feature",
  "properties": {
    "addr:full":"1365 Place Port-Royal Brossard QC J4W 1S7",
    "addr:housenumber":"1365",
    "addr:postcode":"j4w 1s7",
    "addr:street":"Place Port-Royal",
    "iso:country":"CA",
    "sg:address":"1365 Place Port-Royal",
    "sg:city":"Brossard",
    "sg:classifiers":[
        {
            "category":"Organizations",
            "subcategory":"Religious Organization",
            "type":"Services"
        }
    ],
    "sg:phone":"+1 450 466 9300",
    "sg:postcode":"J4W 1S7",
    "sg:province":"QC",
    "sg:tags":[
        "church"
    ],
    "wof:name":"Light House Chappel",
    "wof:placetype":"venue"
},
  "geometry": {"coordinates":[-73.4800872803,45.4745445251],"type":"Point"}
}