{
  "type": "Feature",
  "properties": {
    "addr:full":"135 Alberni Hwy Parksville BC V9P 2G6",
    "addr:housenumber":"135",
    "addr:postcode":"v9p 2g6",
    "addr:street":"Alberni Hwy",
    "iso:country":"CA",
    "sg:address":"135 Alberni Hwy",
    "sg:city":"Parksville",
    "sg:classifiers":[
        {
            "category":"Real Estate",
            "subcategory":"Real Estate Agent",
            "type":"Services"
        }
    ],
    "sg:phone":"+1 250 248 8801",
    "sg:postcode":"V9P 2G6",
    "sg:province":"BC",
    "wof:name":"Whitecap Realty",
    "wof:placetype":"venue"
},
  "geometry": {"coordinates":[-124.313812,49.320137],"type":"Point"}
}