{
  "type": "Feature",
  "properties": {
    "iso:country":"CA",
    "sg:address":"1261 Shawson Dr",
    "sg:city":"Mississauga",
    "sg:classifiers":[
        {
            "category":"Manufacturing",
            "subcategory":"Metals",
            "type":"Manufacturing & Wholesale Goods"
        }
    ],
    "sg:phone":"+1 905 564 0476",
    "sg:postcode":"L4W 1C4",
    "sg:province":"ON",
    "sg:tags":[
        "foundry"
    ],
    "wof:name":"L S Metal Foundry Inc",
    "wof:placetype":"venue"
},
  "geometry": {"coordinates":[-79.6485290527,43.6484947205],"type":"Point"}
}