{
  "type": "Feature",
  "properties": {
    "addr:full":"1530 Rena Cres West Vancouver BC V7V 2Z3",
    "addr:postcode":"1530;v7v 2z3",
    "addr:street":"Cres",
    "iso:country":"CA",
    "sg:address":"1530 Rena Cres",
    "sg:city":"West Vancouver",
    "sg:classifiers":[
        {
            "category":"Communications",
            "subcategory":"Film & Video Production",
            "type":"Services"
        }
    ],
    "sg:phone":"+1 604 299 4570",
    "sg:postcode":"V7V 2Z3",
    "sg:province":"BC",
    "sg:tags":[
        "taping"
    ],
    "wof:name":"Full Frame Productions Inc",
    "wof:placetype":"venue"
},
  "geometry": {"coordinates":[-123.158379,49.342297],"type":"Point"}
}