{
  "type": "Feature",
  "properties": {
    "iso:country":"CA",
    "sg:address":"731 Eastern Ave",
    "sg:city":"Toronto",
    "sg:classifiers":[
        {
            "category":"Food & Beverages",
            "subcategory":"Bakery",
            "type":"Retail Goods"
        }
    ],
    "sg:phone":"+1 416 466 3580",
    "sg:postcode":"M4M 3H6",
    "sg:province":"ON",
    "sg:tags":[
        "doughnut"
    ],
    "wof:name":"Tim Hortons",
    "wof:placetype":"venue"
},
  "geometry": {"coordinates":[-79.331963,43.659821],"type":"Point"}
}