{
  "type": "Feature",
  "properties": {
    "addr:full":"St Albert AB T8N 1H4",
    "addr:postcode":"t8n 1h4",
    "iso:country":"CA",
    "sg:city":"St Albert",
    "sg:classifiers":[
        {
            "category":"Banks & Credit Unions",
            "subcategory":"Bank",
            "type":"Services"
        }
    ],
    "sg:phone":"+1 780 418 3895",
    "sg:postcode":"T8N 1H4",
    "sg:province":"AB",
    "sg:tags":[
        "loan",
        "real estate"
    ],
    "wof:name":"Cash Now St Albert",
    "wof:placetype":"venue"
},
  "geometry": {"coordinates":[-113.62590789799999,53.6368408203],"type":"Point"}
}