{
  "type": "Feature",
  "properties": {
    "addr:full":"7342 Kingsway Burnaby BC V3N 4P2",
    "addr:housenumber":"7342",
    "addr:postcode":"v3n 4p2",
    "addr:street":"Kingsway",
    "iso:country":"CA",
    "sg:address":"7342 Kingsway",
    "sg:city":"Burnaby",
    "sg:classifiers":[
        {
            "category":"Shopping",
            "subcategory":"Used Merchandise",
            "type":"Retail Goods"
        }
    ],
    "sg:phone":"+1 604 520 7199",
    "sg:postcode":"V3N 4P2",
    "sg:province":"BC",
    "sg:tags":[
        "pawnbroker"
    ],
    "wof:name":"Common Exchange Ltd",
    "wof:placetype":"venue"
},
  "geometry": {"coordinates":[-122.94963799999999,49.218346],"type":"Point"}
}