{
  "type": "Feature",
  "properties": {
    "addr:full":"304 Ch Kelly Dsl DE Grand-Sault/Falls NB E3Z 1K3",
    "addr:housenumber":"304",
    "addr:postcode":"e3z 1k3",
    "addr:street":"Ch Kelly Dsl De Grand-Sault /",
    "iso:country":"CA",
    "sg:address":"304 Ch Kelly",
    "sg:city":"Dsl DE Grand-Sault/Falls",
    "sg:classifiers":[
        {
            "category":"Manufacturing",
            "subcategory":"Metals",
            "type":"Manufacturing & Wholesale Goods"
        }
    ],
    "sg:phone":"+1 506 473 5409",
    "sg:postcode":"E3Z 1K3",
    "sg:province":"NB",
    "sg:tags":[
        "scrap",
        "iron"
    ],
    "wof:name":"D & N Metals CO",
    "wof:placetype":"venue"
},
  "geometry": {"coordinates":[-67.72035200000001,46.95734],"type":"Point"}
}