{
  "type": "Feature",
  "properties": {
    "addr:full":"Richmond BC V6V 1P8",
    "addr:postcode":"v6v 1p8",
    "iso:country":"CA",
    "sg:city":"Richmond",
    "sg:classifiers":[
        {
            "category":"Wholesale",
            "subcategory":"Durable Goods & Equipment",
            "type":"Manufacturing & Wholesale Goods"
        }
    ],
    "sg:phone":"+1 604 276 9559",
    "sg:postcode":"V6V 1P8",
    "sg:province":"BC",
    "sg:tags":[
        "representative",
        "manufacturer"
    ],
    "wof:name":"Tri-Mor Sales Ltd",
    "wof:placetype":"venue"
},
  "geometry": {"coordinates":[-123.069397,49.182133],"type":"Point"}
}