{
  "type": "Feature",
  "properties": {
    "addr:full":"Mont-Royal QC H3P 3E9",
    "addr:postcode":"h3p 3e9",
    "iso:country":"CA",
    "sg:city":"Mont-Royal",
    "sg:classifiers":[
        {
            "category":"Shopping",
            "subcategory":"Bicycles & Sporting Goods",
            "type":"Retail Goods"
        }
    ],
    "sg:phone":"+1 514 735 4751",
    "sg:postcode":"H3P 3E9",
    "sg:province":"QC",
    "sg:tags":[
        "sportswear"
    ],
    "wof:name":"Sports Experts",
    "wof:placetype":"venue"
},
  "geometry": {"coordinates":[-73.6484832764,45.5267295837],"type":"Point"}
}