{
  "type": "Feature",
  "properties": {
    "addr:full":"Trail BC V1R 4S9",
    "addr:postcode":"bc v1r 4s9",
    "addr:street":"Trail",
    "iso:country":"CA",
    "sg:city":"Trail",
    "sg:classifiers":[
        {
            "category":"Government",
            "subcategory":"Office",
            "type":"Public Place"
        }
    ],
    "sg:phone":"+1 250 364 0540",
    "sg:postcode":"V1R 4S9",
    "sg:province":"BC",
    "wof:name":"B C Trail Child Family Svc",
    "wof:placetype":"venue"
},
  "geometry": {"coordinates":[-117.70874000000001,49.097145],"type":"Point"}
}