{
  "type": "Feature",
  "properties": {
    "addr:full":"8614 Rue Centrale Lasalle QC H8P 1N5",
    "addr:housenumber":"8614",
    "addr:postcode":"h8p 1n5",
    "addr:street":"Rue Centrale",
    "iso:country":"CA",
    "sg:address":"8614 Rue Centrale",
    "sg:city":"Lasalle",
    "sg:classifiers":[
        {
            "category":"Personal",
            "subcategory":"Beauty Salon",
            "type":"Services"
        }
    ],
    "sg:phone":"+1 514 366 7594",
    "sg:postcode":"H8P 1N5",
    "sg:province":"QC",
    "wof:name":"Esthetique Electrolyse",
    "wof:placetype":"venue"
},
  "geometry": {"coordinates":[-73.61991119379999,45.4172134399],"type":"Point"}
}