{
  "type": "Feature",
  "properties": {
    "addr:full":"78 Av DE Gaspe E Saint-Jean-Port-Joli QC G0R 3G0",
    "addr:postcode":"g0r 3g0",
    "addr:street":"78 Av De Gaspe E",
    "iso:country":"CA",
    "sg:address":"78 Av DE Gaspe E",
    "sg:city":"Saint-Jean-Port-Joli",
    "sg:classifiers":[
        {
            "category":"Professional",
            "subcategory":"Business Services",
            "type":"Services"
        }
    ],
    "sg:phone":"+1 418 598 3542",
    "sg:postcode":"G0R 3G0",
    "sg:province":"QC",
    "sg:tags":[
        "notary"
    ],
    "wof:name":"Maltais Audet Senc",
    "wof:placetype":"venue"
},
  "geometry": {"coordinates":[-70.264526,47.218067],"type":"Point"}
}