{
  "type": "Feature",
  "properties": {
    "addr:full":"190 Cherry Chapleau ON P0M 1K0",
    "addr:housenumber":"190",
    "addr:postcode":"p0m 1k0",
    "addr:street":"Cherry Chapleau",
    "iso:country":"CA",
    "sg:address":"190 Cherry",
    "sg:city":"Chapleau",
    "sg:classifiers":[
        {
            "category":"Government",
            "subcategory":"Office",
            "type":"Public Place"
        }
    ],
    "sg:phone":"+1 705 864 1515",
    "sg:postcode":"P0M 1K0",
    "sg:province":"ON",
    "wof:name":"Ontario Northern Dev Officers",
    "wof:placetype":"venue"
},
  "geometry": {"coordinates":[-83.3974533081,47.8466033936],"type":"Point"}
}