{
  "type": "Feature",
  "properties": {
    "addr:full":"Delta BC V4C 6R2",
    "addr:postcode":"v4c 6r2",
    "iso:country":"CA",
    "sg:city":"Delta",
    "sg:classifiers":[
        {
            "category":"Health Services",
            "subcategory":"Health Practitioner",
            "type":"Services"
        }
    ],
    "sg:phone":"+1 604 591 8973",
    "sg:postcode":"V4C 6R2",
    "sg:province":"BC",
    "sg:tags":[
        "acupuncture"
    ],
    "wof:name":"Feng Li Acupuncture Clinic",
    "wof:placetype":"venue"
},
  "geometry": {"coordinates":[-122.89051055900001,49.1565170288],"type":"Point"}
}