{
  "type": "Feature",
  "properties": {
    "addr:full":"Stittsville ON K2S 1A5",
    "addr:postcode":"k2s 1a5",
    "iso:country":"CA",
    "sg:city":"Stittsville",
    "sg:classifiers":[
        {
            "category":"Banks & Credit Unions",
            "subcategory":"Investment Brokerage",
            "type":"Services"
        }
    ],
    "sg:phone":"+1 613 831 8028",
    "sg:postcode":"K2S 1A5",
    "sg:province":"ON",
    "wof:name":"Edward Jones Investments",
    "wof:placetype":"venue"
},
  "geometry": {"coordinates":[-75.927216,45.263855],"type":"Point"}
}