{
  "type": "Feature",
  "properties": {
    "iso:country":"CA",
    "sg:address":"285 Boul Hymus",
    "sg:city":"Pointe-Claire",
    "sg:phone":"+1 514 694 4070",
    "sg:postcode":"H9R 1G6",
    "sg:province":"QC",
    "sg:tags":[
        "equipment",
        "supply"
    ],
    "wof:name":"Equipement DE Cuisine Astor",
    "wof:placetype":"venue"
},
  "geometry": {"coordinates":[-73.831993103,45.4553527832],"type":"Point"}
}