{
  "type": "Feature",
  "properties": {
    "addr:full":"2415 Maynard St Halifax NS B3K 3V2",
    "addr:housenumber":"2415",
    "addr:postcode":"b3k 3v2",
    "addr:street":"Maynard St",
    "iso:country":"CA",
    "sg:address":"2415 Maynard St",
    "sg:city":"Halifax",
    "sg:classifiers":[
        {
            "category":"Organizations",
            "subcategory":"Non-profit Organization",
            "type":"Services"
        }
    ],
    "sg:phone":"+1 902 423 9918",
    "sg:postcode":"B3K 3V2",
    "sg:province":"NS",
    "sg:tags":[
        "charitable",
        "institution"
    ],
    "wof:name":"Metro Care & Share",
    "wof:placetype":"venue"
},
  "geometry": {"coordinates":[-63.589169,44.654057],"type":"Point"}
}