{
  "type": "Feature",
  "properties": {
    "addr:full":"802 Pelton Rd Kemptville ON K0G 1J0",
    "addr:housenumber":"802",
    "addr:postcode":"k0g 1j0",
    "addr:street":"Pelton Rd",
    "iso:country":"CA",
    "sg:address":"802 Pelton Rd",
    "sg:city":"Kemptville",
    "sg:classifiers":[
        {
            "category":"Manufacturing",
            "subcategory":"Signs",
            "type":"Manufacturing & Wholesale Goods"
        }
    ],
    "sg:phone":"+1 613 258 2926",
    "sg:postcode":"K0G 1J0",
    "sg:province":"ON",
    "wof:name":"Signs & Design",
    "wof:placetype":"venue"
},
  "geometry": {"coordinates":[-75.55819700000001,44.992485],"type":"Point"}
}