{
  "type": "Feature",
  "properties": {
    "addr:full":"14 Wellington St E Aurora ON L4G 1H5",
    "addr:housenumber":"14",
    "addr:postcode":"l4g 1h5",
    "addr:street":"Wellington St E",
    "iso:country":"CA",
    "sg:address":"14 Wellington St E",
    "sg:city":"Aurora",
    "sg:classifiers":[
        {
            "category":"Personal",
            "subcategory":"Beauty Salon",
            "type":"Services"
        }
    ],
    "sg:phone":"+1 905 727 0100",
    "sg:postcode":"L4G 1H5",
    "sg:province":"ON",
    "wof:name":"Designers Edge Inc",
    "wof:placetype":"venue"
},
  "geometry": {"coordinates":[-79.466927,43.999924],"type":"Point"}
}