{
  "type": "Feature",
  "properties": {
    "iso:country":"CA",
    "sg:city":"Laval",
    "sg:classifiers":[
        {
            "category":"Professional",
            "subcategory":"Lawyer & Legal Services",
            "type":"Services"
        }
    ],
    "sg:phone":"+1 450 686 8525",
    "sg:postcode":"H7V 3Z2",
    "sg:province":"QC",
    "sg:tags":[
        "attorney"
    ],
    "wof:name":"Mottet, Jean Marius",
    "wof:placetype":"venue"
},
  "geometry": {"coordinates":[-73.74646,45.551037],"type":"Point"}
}