{
  "type": "Feature",
  "properties": {
    "addr:full":"Vancouver BC V6H 1G5",
    "addr:postcode":"v6h 1g5",
    "iso:country":"CA",
    "sg:city":"Vancouver",
    "sg:classifiers":[
        {
            "category":"Food & Beverages",
            "subcategory":"Specialty",
            "type":"Retail Goods"
        }
    ],
    "sg:phone":"+1 604 730 1162",
    "sg:postcode":"V6H 1G5",
    "sg:province":"BC",
    "sg:tags":[
        "health",
        "diet"
    ],
    "wof:name":"Greenleaf Organic Health Corp",
    "wof:placetype":"venue"
},
  "geometry": {"coordinates":[-123.129791,49.263336],"type":"Point"}
}