{
  "type": "Feature",
  "properties": {
    "addr:full":"162 Scenic Dr South Tetagouche NB E2A 4Z2",
    "addr:housenumber":"162",
    "addr:postcode":"e2a 4z2",
    "addr:street":"Scenic Dr South",
    "iso:country":"CA",
    "sg:address":"162 Scenic Dr",
    "sg:city":"South Tetagouche",
    "sg:classifiers":[
        {
            "category":"Building & Trades",
            "subcategory":"Cleaning & Sanitation",
            "type":"Services"
        }
    ],
    "sg:phone":"+1 506 548 8874",
    "sg:postcode":"E2A 4Z2",
    "sg:province":"NB",
    "sg:tags":[
        "snow",
        "removal"
    ],
    "wof:name":"A & A Beach Svc",
    "wof:placetype":"venue"
},
  "geometry": {"coordinates":[-65.82136535639999,47.6085205078],"type":"Point"}
}