{
  "type": "Feature",
  "properties": {
    "addr:full":"4683 Marine Ave Powell River BC V8A 2L2",
    "addr:housenumber":"4683",
    "addr:postcode":"v8a 2l2",
    "addr:street":"Marine Ave Powell",
    "iso:country":"CA",
    "sg:address":"4683 Marine Ave",
    "sg:city":"Powell River",
    "sg:classifiers":[
        {
            "category":"Home & Garden",
            "subcategory":"Carpets & Floor Coverings",
            "type":"Retail Goods"
        }
    ],
    "sg:phone":"+1 604 485 5356",
    "sg:postcode":"V8A 2L2",
    "sg:province":"BC",
    "sg:tags":[
        "dealer",
        "rug"
    ],
    "wof:name":"Ken's Personal Touch Carpet",
    "wof:placetype":"venue"
},
  "geometry": {"coordinates":[-124.528381,49.842247],"type":"Point"}
}