{
  "type": "Feature",
  "properties": {
    "addr:full":"Laval QC H7M 2Y4",
    "addr:postcode":"h7m 2y4",
    "iso:country":"CA",
    "sg:city":"Laval",
    "sg:classifiers":[
        {
            "category":"Building & Trades",
            "subcategory":"Plumbing",
            "type":"Services"
        }
    ],
    "sg:phone":"+1 450 629 5559",
    "sg:postcode":"H7M 2Y4",
    "sg:province":"QC",
    "sg:tags":[
        "conditioning",
        "air",
        "system",
        "contractor"
    ],
    "wof:name":"Midbec Limitee",
    "wof:placetype":"venue"
},
  "geometry": {"coordinates":[-73.707611,45.583378],"type":"Point"}
}