{
  "type": "Feature",
  "properties": {
    "iso:country":"CA",
    "sg:city":"Ajax",
    "sg:classifiers":[
        {
            "category":"Manufacturing",
            "subcategory":"Tools & Machinery",
            "type":"Manufacturing & Wholesale Goods"
        }
    ],
    "sg:phone":"+1 905 683 1642",
    "sg:postcode":"L1S 2G2",
    "sg:province":"ON",
    "sg:tags":[
        "pattern",
        "maker"
    ],
    "wof:name":"Complex Pattern & Model",
    "wof:placetype":"venue"
},
  "geometry": {"coordinates":[-79.0255432129,43.8363380432],"type":"Point"}
}