{
  "type": "Feature",
  "properties": {
    "addr:full":"Tache St #3 Fisher Branch MB R0C 0Z0",
    "addr:postcode":"r0c 0z0",
    "addr:street":"Tache St # 3 Fisher Branch",
    "iso:country":"CA",
    "sg:address":"Tache St #3",
    "sg:city":"Fisher Branch",
    "sg:classifiers":[
        {
            "category":"Food & Beverages",
            "subcategory":"Liquor & Beverages",
            "type":"Retail Goods"
        }
    ],
    "sg:phone":"+1 204 372 8402",
    "sg:postcode":"R0C 0Z0",
    "sg:province":"MB",
    "sg:tags":[
        "store"
    ],
    "wof:name":"Fisher Branch Health Ctr",
    "wof:placetype":"venue"
},
  "geometry": {"coordinates":[-97.61844600000001,51.0826],"type":"Point"}
}