{
  "type": "Feature",
  "properties": {
    "addr:full":"Burnaby BC V5C 6A7",
    "addr:postcode":"v5c 6a7",
    "iso:country":"CA",
    "sg:city":"Burnaby",
    "sg:classifiers":[
        {
            "category":"Professional",
            "subcategory":"Accounting & Tax Preparation",
            "type":"Services"
        }
    ],
    "sg:phone":"+1 604 294 3178",
    "sg:postcode":"V5C 6A7",
    "sg:province":"BC",
    "sg:tags":[
        "accountant"
    ],
    "wof:name":"Matthews Campbell",
    "wof:placetype":"venue"
},
  "geometry": {"coordinates":[-123.011047363,49.2661056519],"type":"Point"}
}