{
  "type": "Feature",
  "properties": {
    "addr:full":"114 Rue Heriot Drummondville QC J2C 1J6",
    "addr:housenumber":"114",
    "addr:postcode":"j2c 1j6",
    "addr:street":"Rue Heriot",
    "iso:country":"CA",
    "sg:address":"114 Rue Heriot",
    "sg:city":"Drummondville",
    "sg:classifiers":[
        {
            "category":"Restaurant",
            "type":"Food & Drink"
        }
    ],
    "sg:phone":"+1 819 477 6111",
    "sg:postcode":"J2C 1J6",
    "sg:province":"QC",
    "wof:name":"Restaurant Pub Le Charlemagne",
    "wof:placetype":"venue"
},
  "geometry": {"coordinates":[-72.49176,45.886993],"type":"Point"}
}