{
  "type": "Feature",
  "properties": {
    "addr:full":"3187 Albion Rd S Ottawa ON K1V 8Y3",
    "addr:housenumber":"3187",
    "addr:postcode":"k1v 8y3",
    "addr:street":"Albion Rd",
    "iso:country":"CA",
    "sg:address":"3187 Albion Rd S",
    "sg:city":"Ottawa",
    "sg:classifiers":[
        {
            "category":"Building & Trades",
            "subcategory":"Construction",
            "type":"Services"
        }
    ],
    "sg:phone":"+1 613 739 2919",
    "sg:postcode":"K1V 8Y3",
    "sg:province":"ON",
    "sg:tags":[
        "contractor"
    ],
    "wof:name":"Tamarack Developments Corp",
    "wof:placetype":"venue"
},
  "geometry": {"coordinates":[-75.64916229249999,45.3653335571],"type":"Point"}
}