{
  "type": "Feature",
  "properties": {
    "iso:country":"CA",
    "sg:address":"21 Leslie Dr",
    "sg:city":"Stoney Creek",
    "sg:classifiers":[
        {
            "category":"Real Estate",
            "subcategory":"Architect",
            "type":"Services"
        }
    ],
    "sg:phone":"+1 905 662 1400",
    "sg:postcode":"L8G 2P9",
    "sg:province":"ON",
    "wof:name":"G L Heeringa Ltd",
    "wof:placetype":"venue"
},
  "geometry": {"coordinates":[-79.75439453120001,43.2131652832],"type":"Point"}
}