{
  "type": "Feature",
  "properties": {
    "addr:full":"1626 Boul Saint-Laurent Montreal QC H2X 2T1",
    "addr:housenumber":"1626",
    "addr:postcode":"h2x 2t1",
    "addr:street":"Boul Saint-Laurent",
    "iso:country":"CA",
    "sg:address":"1626 Boul Saint-Laurent",
    "sg:city":"Montreal",
    "sg:classifiers":[
        {
            "category":"Wholesale",
            "subcategory":"Meat",
            "type":"Manufacturing & Wholesale Goods"
        }
    ],
    "sg:phone":"+1 514 287 7489",
    "sg:postcode":"H2X 2T1",
    "sg:province":"QC",
    "sg:tags":[
        "butchering"
    ],
    "wof:name":"Boucherie Le Soleil Halal",
    "wof:placetype":"venue"
},
  "geometry": {"coordinates":[-73.566284,45.510891],"type":"Point"}
}