{
  "type": "Feature",
  "properties": {
    "iso:country":"CA",
    "sg:address":"560 Talbot St E",
    "sg:city":"Aylmer",
    "sg:classifiers":[
        {
            "category":"Professional",
            "subcategory":"Business Services",
            "type":"Services"
        }
    ],
    "sg:phone":"+1 519 765 1771",
    "sg:postcode":"N5H 2W2",
    "sg:province":"ON",
    "sg:tags":[
        "interior",
        "consultant",
        "wallpaper",
        "design",
        "decorator"
    ],
    "wof:name":"Lovells Home Decorating Ctr",
    "wof:placetype":"venue"
},
  "geometry": {"coordinates":[-80.96924591059999,42.7698974609],"type":"Point"}
}