{
  "type": "Feature",
  "properties": {
    "iso:country":"CA",
    "sg:address":"980 King St",
    "sg:city":"Midland",
    "sg:classifiers":[
        {
            "category":"Travel",
            "subcategory":"Hotels & Motels",
            "type":"Entertainment"
        }
    ],
    "sg:phone":"+1 705 526 2090",
    "sg:postcode":"L4R 4K5",
    "sg:province":"ON",
    "wof:name":"Comfort Inn",
    "wof:placetype":"venue"
},
  "geometry": {"coordinates":[-79.868706,44.730225],"type":"Point"}
}