{
  "type": "Feature",
  "properties": {
    "addr:full":"Richmond BC V7B 1K7",
    "addr:postcode":"v7b 1k7",
    "iso:country":"CA",
    "sg:city":"Richmond",
    "sg:classifiers":[
        {
            "category":"Airline",
            "type":"Transportation"
        }
    ],
    "sg:phone":"+1 604 273 8856",
    "sg:postcode":"V7B 1K7",
    "sg:province":"BC",
    "sg:tags":[
        "cargo",
        "air"
    ],
    "wof:name":"Swissport Cargo Svc",
    "wof:placetype":"venue"
},
  "geometry": {"coordinates":[-123.173439,49.190857],"type":"Point"}
}