{
  "type": "Feature",
  "properties": {
    "addr:full":"206 Rue Commerciale Saint-Louis-Du-Ha-Ha QC G0L 3S0",
    "addr:housenumber":"206",
    "addr:postcode":"g0l 3s0",
    "addr:street":"Rue Commerciale Saint-Louis-Du-Ha-Ha",
    "iso:country":"CA",
    "sg:address":"206 Rue Commerciale",
    "sg:city":"Saint-Louis-Du-Ha-Ha",
    "sg:classifiers":[
        {
            "category":"Retail",
            "subcategory":"Auto Repair",
            "type":"Services"
        }
    ],
    "sg:phone":"+1 418 854 3528",
    "sg:postcode":"G0L 3S0",
    "sg:province":"QC",
    "sg:tags":[
        "body",
        "automobile",
        "painting"
    ],
    "wof:name":"Denis Beaulieu Garage",
    "wof:placetype":"venue"
},
  "geometry": {"coordinates":[-68.97788199999999,47.670971],"type":"Point"}
}