{
  "type": "Feature",
  "properties": {
    "addr:full":"8155 Boul Saint-Laurent Montreal QC H2P 2M1",
    "addr:housenumber":"8155",
    "addr:postcode":"h2p 2m1",
    "addr:street":"Boul Saint-Laurent",
    "iso:country":"CA",
    "sg:address":"8155 Boul Saint-Laurent",
    "sg:city":"Montreal",
    "sg:classifiers":[
        {
            "category":"Building & Trades",
            "subcategory":"Construction",
            "type":"Services"
        }
    ],
    "sg:phone":"+1 514 382 8222",
    "sg:postcode":"H2P 2M1",
    "sg:province":"QC",
    "sg:tags":[
        "builder",
        "repairer",
        "chimney"
    ],
    "wof:name":"Cheminee Universel",
    "wof:placetype":"venue"
},
  "geometry": {"coordinates":[-73.6322479248,45.539390564],"type":"Point"}
}