{
  "type": "Feature",
  "properties": {
    "iso:country":"CA",
    "sg:address":"455 Brant St",
    "sg:city":"Burlington",
    "sg:classifiers":[
        {
            "category":"Shopping",
            "subcategory":"Clothing, Apparel, & Fashions",
            "type":"Retail Goods"
        }
    ],
    "sg:phone":"+1 905 631 7918",
    "sg:postcode":"L7R 2G3",
    "sg:province":"ON",
    "wof:name":"Joelle's",
    "wof:placetype":"venue"
},
  "geometry": {"coordinates":[-79.79917907710001,43.3268051147],"type":"Point"}
}