{
  "type": "Feature",
  "properties": {
    "addr:full":"263 Roncesvalles Ave Toronto ON M6R 2L9",
    "addr:housenumber":"263",
    "addr:postcode":"m6r 2l9",
    "addr:street":"Roncesvalles Ave",
    "iso:country":"CA",
    "sg:address":"263 Roncesvalles Ave",
    "sg:city":"Toronto",
    "sg:classifiers":[
        {
            "category":"Organizations",
            "subcategory":"Religious Organization",
            "type":"Services"
        }
    ],
    "sg:phone":"+1 416 535 7646",
    "sg:postcode":"M6R 2L9",
    "sg:province":"ON",
    "sg:tags":[
        "church"
    ],
    "wof:name":"St Vincent DE Paul Church",
    "wof:placetype":"venue"
},
  "geometry": {"coordinates":[-79.449074,43.646908],"type":"Point"}
}