{
  "type": "Feature",
  "properties": {
    "addr:full":"Edmonton AB T5G 0B4",
    "addr:postcode":"t5g 0b4",
    "iso:country":"CA",
    "sg:city":"Edmonton",
    "sg:classifiers":[
        {
            "category":"Health Services",
            "subcategory":"Doctor",
            "type":"Services"
        }
    ],
    "sg:phone":"+1 780 474 3712",
    "sg:postcode":"T5G 0B4",
    "sg:province":"AB",
    "sg:tags":[
        "physician",
        "surgeon"
    ],
    "wof:name":"Borkent, Amy MD",
    "wof:placetype":"venue"
},
  "geometry": {"coordinates":[-113.493904,53.55901],"type":"Point"}
}