{
  "type": "Feature",
  "properties": {
    "addr:full":"Kenora ON P9N 3W8",
    "addr:postcode":"p9n 3w8",
    "iso:country":"CA",
    "sg:city":"Kenora",
    "sg:classifiers":[
        {
            "category":"Shopping",
            "subcategory":"Bicycles & Sporting Goods",
            "type":"Retail Goods"
        }
    ],
    "sg:phone":"+1 807 548 5337",
    "sg:postcode":"P9N 3W8",
    "sg:province":"ON",
    "sg:tags":[
        "bait",
        "fishing"
    ],
    "wof:name":"Charlebois Baits",
    "wof:placetype":"venue"
},
  "geometry": {"coordinates":[-94.489311,49.770626],"type":"Point"}
}