{
  "type": "Feature",
  "properties": {
    "addr:full":"Toronto ON M4W 3R8",
    "addr:postcode":"m4w 3r8",
    "iso:country":"CA",
    "sg:city":"Toronto",
    "sg:classifiers":[
        {
            "category":"Professional",
            "subcategory":"Management & Consulting",
            "type":"Services"
        }
    ],
    "sg:phone":"+1 416 968 7311",
    "sg:postcode":"M4W 3R8",
    "sg:province":"ON",
    "sg:tags":[
        "communications",
        "consultant"
    ],
    "wof:name":"Argyle Rowland Worldwide",
    "wof:placetype":"venue"
},
  "geometry": {"coordinates":[-79.38299600000001,43.670967],"type":"Point"}
}