{
  "type": "Feature",
  "properties": {
    "iso:country":"CA",
    "sg:city":"Coldwater",
    "sg:classifiers":[
        {
            "category":"Building & Trades",
            "subcategory":"Construction",
            "type":"Services"
        }
    ],
    "sg:phone":"+1 705 327 1564",
    "sg:postcode":"L0K 1E0",
    "sg:province":"ON",
    "sg:tags":[
        "dry wall",
        "contractor"
    ],
    "wof:name":"Orillia Drywall Ltd",
    "wof:placetype":"venue"
},
  "geometry": {"coordinates":[-79.644363,44.710224],"type":"Point"}
}