{
  "type": "Feature",
  "properties": {
    "addr:full":"252 Rue Notre-Dame Tring-Jonction QC G0N 1X0",
    "addr:housenumber":"252",
    "addr:postcode":"g0n 1x0",
    "addr:street":"Rue Notre-Dame",
    "iso:country":"CA",
    "sg:address":"252 Rue Notre-Dame",
    "sg:city":"Tring-Jonction",
    "sg:classifiers":[
        {
            "category":"Bars & Pubs",
            "type":"Food & Drink"
        }
    ],
    "sg:phone":"+1 418 426 2306",
    "sg:postcode":"G0N 1X0",
    "sg:province":"QC",
    "sg:tags":[
        "lounge",
        "cocktail"
    ],
    "wof:name":"Bar Chez Leo",
    "wof:placetype":"venue"
},
  "geometry": {"coordinates":[-70.99511,46.272274],"type":"Point"}
}