{
  "type": "Feature",
  "properties": {
    "addr:full":"2104 Boul Des Laurentides # A Vimont QC H7M 2R5",
    "addr:housenumber":"2104;# a",
    "addr:postcode":"h7m 2r5",
    "addr:street":"Boul Des Laurentides",
    "iso:country":"CA",
    "sg:address":"2104 Boul Des Laurentides # A",
    "sg:city":"Vimont",
    "sg:classifiers":[
        {
            "category":"Personal",
            "subcategory":"Beauty Salon",
            "type":"Services"
        }
    ],
    "sg:phone":"+1 450 667 0844",
    "sg:postcode":"H7M 2R5",
    "sg:province":"QC",
    "sg:tags":[
        "manicuring"
    ],
    "wof:name":"Onglerie DE Vimont",
    "wof:placetype":"venue"
},
  "geometry": {"coordinates":[-73.7341308594,45.6081123352],"type":"Point"}
}