{
  "type": "Feature",
  "properties": {
    "addr:full":"3600 Rue Bleriot Mascouche QC J7K 3C1",
    "addr:housenumber":"3600",
    "addr:postcode":"j7k 3c1",
    "addr:street":"Rue Bleriot",
    "iso:country":"CA",
    "sg:address":"3600 Rue Bleriot",
    "sg:city":"Mascouche",
    "sg:classifiers":[
        {
            "category":"Autos & Motor Vehicles",
            "subcategory":"Automobile Sales",
            "type":"Retail Goods"
        }
    ],
    "sg:phone":"+1 450 474 3333",
    "sg:postcode":"J7K 3C1",
    "sg:province":"QC",
    "sg:tags":[
        "car",
        "dealer"
    ],
    "wof:name":"Albi Kia",
    "wof:placetype":"venue"
},
  "geometry": {"coordinates":[-73.60034899999999,45.721783],"type":"Point"}
}