{
  "type": "Feature",
  "properties": {
    "addr:full":"265 King St N # 4 Alliston ON L9R 1N3",
    "addr:housenumber":"265",
    "addr:postcode":"l9r 1n3",
    "addr:street":"King St N # 4 Alliston",
    "iso:country":"CA",
    "sg:address":"265 King St N # 4",
    "sg:city":"Alliston",
    "sg:classifiers":[
        {
            "category":"Food & Beverages",
            "subcategory":"Groceries & Convenience Stores",
            "type":"Retail Goods"
        }
    ],
    "sg:phone":"+1 705 434 9500",
    "sg:postcode":"L9R 1N3",
    "sg:province":"ON",
    "wof:name":"Tlc Convenience",
    "wof:placetype":"venue"
},
  "geometry": {"coordinates":[-79.8808746338,44.1605834961],"type":"Point"}
}