{
  "type": "Feature",
  "properties": {
    "addr:full":"1525 33 St N Lethbridge AB T1H 5H2",
    "addr:housenumber":"1525",
    "addr:postcode":"t1h 5h2",
    "addr:street":"33 St N",
    "iso:country":"CA",
    "sg:address":"1525 33 St N",
    "sg:city":"Lethbridge",
    "sg:classifiers":[
        {
            "category":"Building & Trades",
            "subcategory":"Construction",
            "type":"Services"
        }
    ],
    "sg:phone":"+1 403 327 6606",
    "sg:postcode":"T1H 5H2",
    "sg:province":"AB",
    "sg:tags":[
        "excavating",
        "contractor"
    ],
    "wof:name":"Draco Excavating",
    "wof:placetype":"venue"
},
  "geometry": {"coordinates":[-112.791625977,49.7193336487],"type":"Point"}
}