{
  "type": "Feature",
  "properties": {
    "addr:full":"3192 Logan Farm Rd # 103 Osgoode ON K0A 2W0",
    "addr:housenumber":"3192",
    "addr:postcode":"k0a 2w0",
    "addr:street":"Logan Farm Rd # 103",
    "iso:country":"CA",
    "sg:address":"3192 Logan Farm Rd # 103",
    "sg:city":"Osgoode",
    "sg:classifiers":[
        {
            "category":"Shopping",
            "type":"Retail Goods"
        }
    ],
    "sg:phone":"+1 613 837 9902",
    "sg:postcode":"K0A 2W0",
    "sg:province":"ON",
    "sg:tags":[
        "hearing",
        "equipment",
        "supply",
        "impaired"
    ],
    "wof:name":"Hearing Health Clinic",
    "wof:placetype":"venue"
},
  "geometry": {"coordinates":[-75.60247039790001,45.1484718323],"type":"Point"}
}