{
  "type": "Feature",
  "properties": {
    "addr:full":"451 Main St Alberton PE C0B 1B0",
    "addr:housenumber":"451",
    "addr:postcode":"c0b 1b0",
    "addr:street":"Main St",
    "iso:country":"CA",
    "sg:address":"451 Main St",
    "sg:city":"Alberton",
    "sg:classifiers":[
        {
            "category":"Food & Beverages",
            "subcategory":"Bakery",
            "type":"Retail Goods"
        }
    ],
    "sg:phone":"+1 902 853 2796",
    "sg:postcode":"C0B 1B0",
    "sg:province":"PE",
    "sg:tags":[
        "baker"
    ],
    "wof:name":"Alberton Bakery & Cafe",
    "wof:placetype":"venue"
},
  "geometry": {"coordinates":[-64.06420900000001,46.811249],"type":"Point"}
}