{
  "type": "Feature",
  "properties": {
    "addr:full":"90 Main St E #1 Huntsville ON P1H 2C7",
    "addr:housenumber":"90",
    "addr:postcode":"p1h 2c7",
    "addr:street":"Main St E # 1",
    "iso:country":"CA",
    "sg:address":"90 Main St E #1",
    "sg:city":"Huntsville",
    "sg:classifiers":[
        {
            "category":"Restaurant",
            "type":"Food & Drink"
        }
    ],
    "sg:phone":"+1 705 789 1111",
    "sg:postcode":"P1H 2C7",
    "sg:province":"ON",
    "sg:tags":[
        "pizza"
    ],
    "wof:name":"Pizza Pizza",
    "wof:placetype":"venue"
},
  "geometry": {"coordinates":[-79.21611,45.327366],"type":"Point"}
}