{
  "type": "Feature",
  "properties": {
    "iso:country":"CA",
    "sg:address":"4055 12E Av",
    "sg:city":"Shawinigan-Sud",
    "sg:classifiers":[
        {
            "category":"Autos & Motor Vehicles",
            "subcategory":"Auto Supplies",
            "type":"Retail Goods"
        }
    ],
    "sg:phone":"+1 819 537 1777",
    "sg:postcode":"G9P 4G3",
    "sg:province":"QC",
    "sg:tags":[
        "tire"
    ],
    "wof:name":"Entrepot Du Pneu",
    "wof:placetype":"venue"
},
  "geometry": {"coordinates":[-72.7302474976,46.504863739],"type":"Point"}
}