{
  "type": "Feature",
  "properties": {
    "iso:country":"CA",
    "sg:address":"9 Church St",
    "sg:city":"Springhill",
    "sg:classifiers":[
        {
            "category":"Travel",
            "subcategory":"Hotels & Motels",
            "type":"Entertainment"
        }
    ],
    "sg:phone":"+1 902 597 3713",
    "sg:postcode":"B0M 1X0",
    "sg:province":"NS",
    "sg:tags":[
        "tourist",
        "accommodation"
    ],
    "wof:name":"Rollways Motel",
    "wof:placetype":"venue"
},
  "geometry": {"coordinates":[-64.0573501587,45.650554657],"type":"Point"}
}