{
  "type": "Feature",
  "properties": {
    "addr:full":"4200 Rue Saint-Patrick Montreal QC H4E 1A5",
    "addr:housenumber":"4200",
    "addr:postcode":"h4e 1a5",
    "addr:street":"Rue Saint-Patrick",
    "iso:country":"CA",
    "sg:address":"4200 Rue Saint-Patrick",
    "sg:city":"Montreal",
    "sg:classifiers":[
        {
            "category":"Wholesale",
            "subcategory":"Machinery & Supplies",
            "type":"Manufacturing & Wholesale Goods"
        }
    ],
    "sg:phone":"+1 514 767 5363",
    "sg:postcode":"H4E 1A5",
    "sg:province":"QC",
    "sg:tags":[
        "compressor",
        "gas"
    ],
    "wof:name":"Larry Enterprises Inc",
    "wof:placetype":"venue"
},
  "geometry": {"coordinates":[-73.58532,45.468155],"type":"Point"}
}