{
  "type": "Feature",
  "properties": {
    "iso:country":"CA",
    "sg:city":"Calgary",
    "sg:classifiers":[
        {
            "category":"Professional",
            "subcategory":"Printing & Photocopies",
            "type":"Services"
        }
    ],
    "sg:phone":"+1 403 266 6976",
    "sg:postcode":"T2P 3S2",
    "sg:province":"AB",
    "sg:tags":[
        "duplicating",
        "copying"
    ],
    "wof:name":"A-1 Copy Bureau",
    "wof:placetype":"venue"
},
  "geometry": {"coordinates":[-114.073417664,51.0484848022],"type":"Point"}
}