{
  "type": "Feature",
  "properties": {
    "addr:full":"Val-D'Or QC J9P 1T4",
    "addr:postcode":"j9p 1t4",
    "iso:country":"CA",
    "sg:city":"Val-D'Or",
    "sg:classifiers":[
        {
            "category":"Professional",
            "subcategory":"Lawyer & Legal Services",
            "type":"Services"
        }
    ],
    "sg:phone":"+1 819 874 2525",
    "sg:postcode":"J9P 1T4",
    "sg:province":"QC",
    "sg:tags":[
        "attorney"
    ],
    "wof:name":"Girouard Adam & Assoc",
    "wof:placetype":"venue"
},
  "geometry": {"coordinates":[-68.42929100000001,53.890121],"type":"Point"}
}