{
  "type": "Feature",
  "properties": {
    "addr:full":"449 Dundas St Cambridge ON N1R 5R5",
    "addr:housenumber":"449",
    "addr:postcode":"n1r 5r5",
    "addr:street":"Dundas St",
    "iso:country":"CA",
    "sg:address":"449 Dundas St",
    "sg:city":"Cambridge",
    "sg:classifiers":[
        {
            "category":"Manufacturing",
            "subcategory":"Tools & Machinery",
            "type":"Manufacturing & Wholesale Goods"
        }
    ],
    "sg:phone":"+1 519 622 4558",
    "sg:postcode":"N1R 5R5",
    "sg:province":"ON",
    "sg:tags":[
        "machine",
        "shop"
    ],
    "wof:name":"Mc Garr Industries Inc",
    "wof:placetype":"venue"
},
  "geometry": {"coordinates":[-80.3135147095,43.3704223633],"type":"Point"}
}