{
  "type": "Feature",
  "properties": {
    "addr:full":"156 Nassau St Charlottetown PE C1A 2X2",
    "addr:housenumber":"156",
    "addr:postcode":"c1a 2x2",
    "addr:street":"Nassau St",
    "iso:country":"CA",
    "sg:address":"156 Nassau St",
    "sg:city":"Charlottetown",
    "sg:classifiers":[
        {
            "category":"Home & Garden",
            "subcategory":"Household Appliances",
            "type":"Retail Goods"
        }
    ],
    "sg:phone":"+1 902 892 8308",
    "sg:postcode":"C1A 2X2",
    "sg:province":"PE",
    "sg:tags":[
        "refrigerator",
        "freezer"
    ],
    "wof:name":"Gass Refrigeration Inc",
    "wof:placetype":"venue"
},
  "geometry": {"coordinates":[-63.138832,46.247631],"type":"Point"}
}