{
  "type": "Feature",
  "properties": {
    "addr:full":"1988 Triumph St Vancouver BC V5L 1K5",
    "addr:housenumber":"1988",
    "addr:postcode":"v5l 1k5",
    "addr:street":"Triumph St",
    "iso:country":"CA",
    "sg:address":"1988 Triumph St",
    "sg:city":"Vancouver",
    "sg:classifiers":[
        {
            "category":"Professional",
            "subcategory":"Testing Lab",
            "type":"Services"
        }
    ],
    "sg:phone":"+1 604 253 4188",
    "sg:postcode":"V5L 1K5",
    "sg:province":"BC",
    "sg:tags":[
        "environmental",
        "ecological"
    ],
    "wof:name":"Als Environmental",
    "wof:placetype":"venue"
},
  "geometry": {"coordinates":[-123.063911,49.283836],"type":"Point"}
}