{
  "type": "Feature",
  "properties": {
    "addr:full":"13 Shemogue Rd Port Elgin NB E4M 1C2",
    "addr:housenumber":"13",
    "addr:postcode":"e4m 1c2",
    "addr:street":"Shemogue Rd",
    "iso:country":"CA",
    "sg:address":"13 Shemogue Rd",
    "sg:city":"Port Elgin",
    "sg:classifiers":[
        {
            "category":"Food & Beverages",
            "subcategory":"Groceries & Convenience Stores",
            "type":"Retail Goods"
        }
    ],
    "sg:phone":"+1 506 538 7525",
    "sg:postcode":"E4M 1C2",
    "sg:province":"NB",
    "sg:tags":[
        "variety"
    ],
    "wof:name":"Murphy's Variety & Confctnry",
    "wof:placetype":"venue"
},
  "geometry": {"coordinates":[-64.090782,46.052528],"type":"Point"}
}