{
  "type": "Feature",
  "properties": {
    "iso:country":"CA",
    "sg:city":"Nepean",
    "sg:classifiers":[
        {
            "category":"Retail",
            "subcategory":"Auto Repair",
            "type":"Services"
        }
    ],
    "sg:phone":"+1 613 225 3715",
    "sg:postcode":"K2E 6T8",
    "sg:province":"ON",
    "sg:tags":[
        "repairing",
        "automobile"
    ],
    "wof:name":"Blastech Automotive",
    "wof:placetype":"venue"
},
  "geometry": {"coordinates":[-75.7200088501,45.3324508667],"type":"Point"}
}