{
  "type": "Feature",
  "properties": {
    "addr:full":"Huron St Embro ON N0J 1J0",
    "addr:postcode":"n0j 1j0",
    "addr:street":"Huron St",
    "iso:country":"CA",
    "sg:address":"Huron St",
    "sg:city":"Embro",
    "sg:classifiers":[
        {
            "category":"Organizations",
            "subcategory":"Professional Association",
            "type":"Services"
        }
    ],
    "sg:phone":"+1 519 475 4904",
    "sg:postcode":"N0J 1J0",
    "sg:province":"ON",
    "wof:name":"Royal Canadian Legion",
    "wof:placetype":"venue"
},
  "geometry": {"coordinates":[-80.90023040769999,43.154094696],"type":"Point"}
}