{
  "type": "Feature",
  "properties": {
    "addr:full":"1914 Rue DE LA Gaillarde Jonquiere QC G7S 5V9",
    "addr:housenumber":"1914",
    "addr:postcode":"g7s 5v9",
    "addr:street":"Rue De La Gaillarde",
    "iso:country":"CA",
    "sg:address":"1914 Rue DE LA Gaillarde",
    "sg:city":"Jonquiere",
    "sg:classifiers":[
        {
            "category":"Professional",
            "subcategory":"Business Services",
            "type":"Services"
        }
    ],
    "sg:phone":"+1 418 695 5771",
    "sg:postcode":"G7S 5V9",
    "sg:province":"QC",
    "sg:tags":[
        "notary"
    ],
    "wof:name":"Simard, Louise",
    "wof:placetype":"venue"
},
  "geometry": {"coordinates":[-71.214409,48.424236],"type":"Point"}
}