{
  "type": "Feature",
  "properties": {
    "addr:full":"106 Rue Vallilee Chute-Aux-Outardes QC G0H 1C0",
    "addr:housenumber":"106",
    "addr:postcode":"g0h 1c0",
    "addr:street":"Rue Vallilee",
    "iso:country":"CA",
    "sg:address":"106 Rue Vallilee",
    "sg:city":"Chute-Aux-Outardes",
    "sg:classifiers":[
        {
            "category":"Restaurant",
            "type":"Food & Drink"
        }
    ],
    "sg:phone":"+1 418 567 2621",
    "sg:postcode":"G0H 1C0",
    "sg:province":"QC",
    "wof:name":"Restaurant Chez Gram'm",
    "wof:placetype":"venue"
},
  "geometry": {"coordinates":[-68.393761,49.128864],"type":"Point"}
}