{
  "type": "Feature",
  "properties": {
    "addr:full":"666 St James St Winnipeg MB R3G 3J6",
    "addr:housenumber":"666",
    "addr:postcode":"r3g 3j6",
    "addr:street":"St James St",
    "iso:country":"CA",
    "sg:address":"666 St James St",
    "sg:city":"Winnipeg",
    "sg:classifiers":[
        {
            "category":"Social Services",
            "type":"Services"
        }
    ],
    "sg:phone":"+1 204 775 3003",
    "sg:postcode":"R3G 3J6",
    "sg:province":"MB",
    "sg:tags":[
        "youth",
        "organization",
        "center",
        "association"
    ],
    "wof:name":"Girl Guides of Canada",
    "wof:placetype":"venue"
},
  "geometry": {"coordinates":[-97.2017593384,49.8826217651],"type":"Point"}
}