{
  "type": "Feature",
  "properties": {
    "addr:full":"Senneterre QC J0Y 2M0",
    "addr:postcode":"j0y 2m0",
    "iso:country":"CA",
    "sg:city":"Senneterre",
    "sg:classifiers":[
        {
            "category":"Government",
            "subcategory":"Office",
            "type":"Public Place"
        }
    ],
    "sg:phone":"+1 819 737 8086",
    "sg:postcode":"J0Y 2M0",
    "sg:province":"QC",
    "wof:name":"Quebec Justice",
    "wof:placetype":"venue"
},
  "geometry": {"coordinates":[-77.21824646,48.3618431091],"type":"Point"}
}