{
  "type": "Feature",
  "properties": {
    "addr:full":"134 Eighth St Etobicoke ON M8V 3C6",
    "addr:housenumber":"134",
    "addr:postcode":"m8v 3c6",
    "addr:street":"Eighth St",
    "iso:country":"CA",
    "sg:address":"134 Eighth St",
    "sg:city":"Etobicoke",
    "sg:classifiers":[
        {
            "category":"Home & Garden",
            "subcategory":"Building Materials",
            "type":"Retail Goods"
        }
    ],
    "sg:phone":"+1 416 251 2281",
    "sg:postcode":"M8V 3C6",
    "sg:province":"ON",
    "sg:tags":[
        "lumber"
    ],
    "wof:name":"Lakeshore Lumber CO",
    "wof:placetype":"venue"
},
  "geometry": {"coordinates":[-79.506805,43.600948],"type":"Point"}
}