{
  "type": "Feature",
  "properties": {
    "addr:full":"151 Broadway #A Orangeville ON L9W 1K2",
    "addr:housenumber":"151",
    "addr:postcode":"l9w 1k2",
    "addr:street":"Broadway # A",
    "iso:country":"CA",
    "sg:address":"151 Broadway #A",
    "sg:city":"Orangeville",
    "sg:classifiers":[
        {
            "category":"Shopping",
            "subcategory":"Used Merchandise",
            "type":"Retail Goods"
        }
    ],
    "sg:phone":"+1 519 940 8740",
    "sg:postcode":"L9W 1K2",
    "sg:province":"ON",
    "sg:tags":[
        "book",
        "rare",
        "dealer"
    ],
    "wof:name":"Readers' Choice",
    "wof:placetype":"venue"
},
  "geometry": {"coordinates":[-80.096535,43.91959],"type":"Point"}
}