{
  "type": "Feature",
  "properties": {
    "addr:full":"9590 Scott St Port Hardy BC V0N 2P0",
    "addr:housenumber":"9590",
    "addr:postcode":"v0n 2p0",
    "addr:street":"Scott St",
    "iso:country":"CA",
    "sg:address":"9590 Scott St",
    "sg:city":"Port Hardy",
    "sg:classifiers":[
        {
            "category":"Autos & Motor Vehicles",
            "subcategory":"Boat Sales",
            "type":"Retail Goods"
        }
    ],
    "sg:phone":"+1 250 902 0565",
    "sg:postcode":"V0N 2P0",
    "sg:province":"BC",
    "sg:tags":[
        "dealer"
    ],
    "wof:name":"Odyssey Kayaking",
    "wof:placetype":"venue"
},
  "geometry": {"coordinates":[-127.512489319,50.7211151123],"type":"Point"}
}