{
  "type": "Feature",
  "properties": {
    "addr:full":"2420 Crowchild Trail NW Calgary AB T2M 4N5",
    "addr:housenumber":"2420",
    "addr:postcode":"t2m 4n5",
    "addr:street":"Crowchild Trail Nw",
    "iso:country":"CA",
    "sg:address":"2420 Crowchild Trail NW",
    "sg:city":"Calgary",
    "sg:classifiers":[
        {
            "category":"Autos & Motor Vehicles",
            "subcategory":"Automobile Sales",
            "type":"Retail Goods"
        }
    ],
    "sg:phone":"+1 403 284 4611",
    "sg:postcode":"T2M 4N5",
    "sg:province":"AB",
    "sg:tags":[
        "car",
        "dealer"
    ],
    "wof:name":"Stadium Nissan Inc",
    "wof:placetype":"venue"
},
  "geometry": {"coordinates":[-114.1173172,51.0719604492],"type":"Point"}
}