{
  "type": "Feature",
  "properties": {
    "addr:full":"4350 Boul Wilfrid-Hamel Quebec QC G1P 2J8",
    "addr:housenumber":"4350",
    "addr:postcode":"g1p 2j8",
    "addr:street":"Boul Wilfrid-Hamel",
    "iso:country":"CA",
    "sg:address":"4350 Boul Wilfrid-Hamel",
    "sg:city":"Quebec",
    "sg:classifiers":[
        {
            "category":"Health Services",
            "subcategory":"Podiatrist",
            "type":"Services"
        }
    ],
    "sg:phone":"+1 418 872 4346",
    "sg:postcode":"G1P 2J8",
    "sg:province":"QC",
    "wof:name":"Clinique DE Med Podiatrique",
    "wof:placetype":"venue"
},
  "geometry": {"coordinates":[-71.32085418699999,46.8062553406],"type":"Point"}
}