{
  "type": "Feature",
  "properties": {
    "iso:country":"CA",
    "sg:city":"Saint-Etienne-Des-Gres",
    "sg:classifiers":[
        {
            "category":"Autos & Motor Vehicles",
            "subcategory":"Automobile Sales",
            "type":"Retail Goods"
        }
    ],
    "sg:phone":"+1 819 535 2067",
    "sg:postcode":"G0X 2P0",
    "sg:province":"QC",
    "sg:tags":[
        "car",
        "dealer"
    ],
    "wof:name":"J M Grenier Inc",
    "wof:placetype":"venue"
},
  "geometry": {"coordinates":[-72.82978057859999,46.4176063538],"type":"Point"}
}