{
  "type": "Feature",
  "properties": {
    "addr:full":"Winnipeg MB R2V 3C4",
    "addr:postcode":"r2v 3c4",
    "iso:country":"CA",
    "sg:city":"Winnipeg",
    "sg:classifiers":[
        {
            "category":"Recreation",
            "type":"Entertainment"
        }
    ],
    "sg:phone":"+1 204 334 3547",
    "sg:postcode":"R2V 3C4",
    "sg:province":"MB",
    "sg:tags":[
        "lottery",
        "agent"
    ],
    "wof:name":"Northgate Lottery Gifts & Prty",
    "wof:placetype":"venue"
},
  "geometry": {"coordinates":[-97.15757000000001,49.941643],"type":"Point"}
}