{
  "type": "Feature",
  "properties": {
    "addr:full":"6115 47th St Barrhead AB T7N 1A1",
    "addr:housenumber":"6115",
    "addr:postcode":"t7n 1a1",
    "addr:street":"47Th St",
    "iso:country":"CA",
    "sg:address":"6115 47th St",
    "sg:city":"Barrhead",
    "sg:classifiers":[
        {
            "category":"Wholesale",
            "subcategory":"Scrap",
            "type":"Manufacturing & Wholesale Goods"
        }
    ],
    "sg:phone":"+1 780 674 4604",
    "sg:postcode":"T7N 1A1",
    "sg:province":"AB",
    "sg:tags":[
        "recycling",
        "can",
        "bottle",
        "depot"
    ],
    "wof:name":"Barrhead Bottle Depot",
    "wof:placetype":"venue"
},
  "geometry": {"coordinates":[-114.39634700000001,54.131977],"type":"Point"}
}