{
  "type": "Feature",
  "properties": {
    "addr:full":"113 Murray St Ottawa ON K1N 5M5",
    "addr:housenumber":"113",
    "addr:postcode":"k1n 5m5",
    "addr:street":"Murray St",
    "iso:country":"CA",
    "sg:address":"113 Murray St",
    "sg:city":"Ottawa",
    "sg:classifiers":[
        {
            "category":"Shopping",
            "type":"Retail Goods"
        }
    ],
    "sg:phone":"+1 613 241 7020",
    "sg:postcode":"K1N 5M5",
    "sg:province":"ON",
    "sg:tags":[
        "oriental",
        "art",
        "gallery",
        "dealer"
    ],
    "wof:name":"Darshan Gallery",
    "wof:placetype":"venue"
},
  "geometry": {"coordinates":[-75.69287109379999,45.4301643372],"type":"Point"}
}