{
  "type": "Feature",
  "properties": {
    "addr:full":"830 Colonia Dr Ladysmith BC V9G 1N3",
    "addr:housenumber":"830",
    "addr:postcode":"v9g 1n3",
    "addr:street":"Colonia Dr",
    "iso:country":"CA",
    "sg:address":"830 Colonia Dr",
    "sg:city":"Ladysmith",
    "sg:classifiers":[
        {
            "category":"Retail",
            "subcategory":"Laundry & Dry Cleaning",
            "type":"Services"
        }
    ],
    "sg:phone":"+1 250 245 2777",
    "sg:postcode":"V9G 1N3",
    "sg:province":"BC",
    "sg:tags":[
        "cleaners",
        "rug",
        "carpet"
    ],
    "wof:name":"Doug's Carpet Cleaning",
    "wof:placetype":"venue"
},
  "geometry": {"coordinates":[-123.83307647700001,48.9893112183],"type":"Point"}
}