{
  "type": "Feature",
  "properties": {
    "addr:full":"15 York St Stratford ON N5A 1A1",
    "addr:housenumber":"15",
    "addr:postcode":"n5a 1a1",
    "addr:street":"York St",
    "iso:country":"CA",
    "sg:address":"15 York St",
    "sg:city":"Stratford",
    "sg:classifiers":[
        {
            "category":"Shopping",
            "subcategory":"Books",
            "type":"Retail Goods"
        }
    ],
    "sg:phone":"+1 519 273 5767",
    "sg:postcode":"N5A 1A1",
    "sg:province":"ON",
    "sg:tags":[
        "dealer"
    ],
    "wof:name":"Callan Books",
    "wof:placetype":"venue"
},
  "geometry": {"coordinates":[-80.9841766357,43.3716850281],"type":"Point"}
}