{
  "type": "Feature",
  "properties": {
    "addr:full":"23 Bluewater Rd # A Bedford NS B4B 1G8",
    "addr:housenumber":"23",
    "addr:postcode":"b4b 1g8",
    "addr:street":"Bluewater Rd # A",
    "iso:country":"CA",
    "sg:address":"23 Bluewater Rd # A",
    "sg:city":"Bedford",
    "sg:classifiers":[
        {
            "category":"Building & Trades",
            "subcategory":"Landscaping Services",
            "type":"Services"
        }
    ],
    "sg:phone":"+1 902 835 7760",
    "sg:postcode":"B4B 1G8",
    "sg:province":"NS",
    "sg:tags":[
        "landscape",
        "contractor"
    ],
    "wof:name":"Acme Environmentals Ltd",
    "wof:placetype":"venue"
},
  "geometry": {"coordinates":[-63.7077102661,44.7260246277],"type":"Point"}
}