{
  "type": "Feature",
  "properties": {
    "addr:full":"801 Weldon Ave Saskatoon SK S7M 2V3",
    "addr:housenumber":"801",
    "addr:postcode":"s7m 2v3",
    "addr:street":"Weldon Ave",
    "iso:country":"CA",
    "sg:address":"801 Weldon Ave",
    "sg:city":"Saskatoon",
    "sg:classifiers":[
        {
            "category":"Museum",
            "type":"Entertainment"
        }
    ],
    "sg:phone":"+1 306 665 1911",
    "sg:postcode":"S7M 2V3",
    "sg:province":"SK",
    "wof:name":"Prime Artifact",
    "wof:placetype":"venue"
},
  "geometry": {"coordinates":[-106.693398,52.118301],"type":"Point"}
}