{
  "type": "Feature",
  "properties": {
    "addr:full":"Cote Saint-Luc QC H4W 2T5",
    "addr:postcode":"h4w 2t5",
    "addr:street":"Cote Saint-Luc",
    "iso:country":"CA",
    "sg:city":"Cote Saint-Luc",
    "sg:classifiers":[
        {
            "category":"Real Estate",
            "subcategory":"Real Estate Operator",
            "type":"Services"
        }
    ],
    "sg:phone":"+1 514 487 4511",
    "sg:postcode":"H4W 2T5",
    "sg:province":"QC",
    "sg:tags":[
        "mall",
        "shopping",
        "center"
    ],
    "wof:name":"Cavendish Mall",
    "wof:placetype":"venue"
},
  "geometry": {"coordinates":[-73.66176605219999,45.4759483337],"type":"Point"}
}