{
  "type": "Feature",
  "properties": {
    "addr:full":"30 Vanier Dr Pinawa MB R0E 1L0",
    "addr:housenumber":"30",
    "addr:postcode":"r0e 1l0",
    "addr:street":"Vanier Dr Pinawa",
    "iso:country":"CA",
    "sg:address":"30 Vanier Dr",
    "sg:city":"Pinawa",
    "sg:classifiers":[
        {
            "category":"Health Services",
            "subcategory":"Doctor",
            "type":"Services"
        }
    ],
    "sg:phone":"+1 204 753 2351",
    "sg:postcode":"R0E 1L0",
    "sg:province":"MB",
    "sg:tags":[
        "physician",
        "surgeon"
    ],
    "wof:name":"Pinawa Medical Clinic",
    "wof:placetype":"venue"
},
  "geometry": {"coordinates":[-95.8785018921,50.1492385864],"type":"Point"}
}