{
  "type": "Feature",
  "properties": {
    "addr:full":"967 Route 445 Fairisle NB E9G 2X1",
    "addr:housenumber":"967",
    "addr:postcode":"e9g 2x1",
    "addr:street":"Route 445",
    "iso:country":"CA",
    "sg:address":"967 Route 445",
    "sg:city":"Fairisle",
    "sg:classifiers":[
        {
            "category":"Recreation",
            "type":"Entertainment"
        }
    ],
    "sg:phone":"+1 506 776 5678",
    "sg:postcode":"E9G 2X1",
    "sg:province":"NB",
    "sg:tags":[
        "hall",
        "auditorium"
    ],
    "wof:name":"Centre Mgr Godin DE Fairisle",
    "wof:placetype":"venue"
},
  "geometry": {"coordinates":[-65.12557983400001,47.2778396606],"type":"Point"}
}