{
  "type": "Feature",
  "properties": {
    "addr:full":"Chelsea QC J9B 1J3",
    "addr:postcode":"qc j9b 1j3",
    "iso:country":"CA",
    "sg:city":"Chelsea",
    "sg:classifiers":[
        {
            "category":"Restaurant",
            "type":"Food & Drink"
        }
    ],
    "sg:phone":"+1 819 827 7687",
    "sg:postcode":"J9B 1J3",
    "sg:province":"QC",
    "wof:name":"Soup Herbe",
    "wof:placetype":"venue"
},
  "geometry": {"coordinates":[-75.8022613525,45.5033988953],"type":"Point"}
}