{
  "type": "Feature",
  "properties": {
    "addr:full":"Rosemere QC J7A 3T2",
    "addr:postcode":"j7a 3t2",
    "iso:country":"CA",
    "sg:city":"Rosemere",
    "sg:classifiers":[
        {
            "category":"Shopping",
            "subcategory":"Clothing, Apparel, & Fashions",
            "type":"Retail Goods"
        }
    ],
    "sg:phone":"+1 450 437 3913",
    "sg:postcode":"J7A 3T2",
    "sg:province":"QC",
    "sg:tags":[
        "handbag"
    ],
    "wof:name":"Bagagerie Alda",
    "wof:placetype":"venue"
},
  "geometry": {"coordinates":[-73.817199707,45.6328964233],"type":"Point"}
}