{
  "type": "Feature",
  "properties": {
    "addr:full":"8205 90 Ave NW Edmonton AB T6C 1N8",
    "addr:housenumber":"8205",
    "addr:postcode":"t6c 1n8",
    "addr:street":"90 Ave Nw",
    "iso:country":"CA",
    "sg:address":"8205 90 Ave NW",
    "sg:city":"Edmonton",
    "sg:classifiers":[
        {
            "category":"Education",
            "subcategory":"Dance Studio",
            "type":"Public Place"
        }
    ],
    "sg:phone":"+1 780 413 0985",
    "sg:postcode":"T6C 1N8",
    "sg:province":"AB",
    "sg:tags":[
        "instruction",
        "dancing"
    ],
    "wof:name":"Edmonton Festival Ballet",
    "wof:placetype":"venue"
},
  "geometry": {"coordinates":[-113.456626892,53.5255241394],"type":"Point"}
}