{
  "type": "Feature",
  "properties": {
    "addr:full":"28 Willow St Yarmouth NS B5A 1V3",
    "addr:housenumber":"28",
    "addr:postcode":"b5a 1v3",
    "addr:street":"Willow St",
    "iso:country":"CA",
    "sg:address":"28 Willow St",
    "sg:city":"Yarmouth",
    "sg:classifiers":[
        {
            "category":"Retail",
            "subcategory":"Repair Shop",
            "type":"Services"
        }
    ],
    "sg:phone":"+1 902 742 1705",
    "sg:postcode":"B5A 1V3",
    "sg:province":"NS",
    "sg:tags":[
        "upholsterer"
    ],
    "wof:name":"Sweeny's Restoration",
    "wof:placetype":"venue"
},
  "geometry": {"coordinates":[-66.11767578120001,43.8362998962],"type":"Point"}
}