{
  "type": "Feature",
  "properties": {
    "addr:full":"St Catharines ON L2T 3Y4",
    "addr:postcode":"l2t 3y4",
    "iso:country":"CA",
    "sg:city":"St Catharines",
    "sg:classifiers":[
        {
            "category":"Health Services",
            "subcategory":"Doctor",
            "type":"Services"
        }
    ],
    "sg:phone":"+1 905 682 7776",
    "sg:postcode":"L2T 3Y4",
    "sg:province":"ON",
    "sg:tags":[
        "physician",
        "surgeon"
    ],
    "wof:name":"Henry, David D A MD",
    "wof:placetype":"venue"
},
  "geometry": {"coordinates":[-79.2395248413,43.1398773193],"type":"Point"}
}