{
  "type": "Feature",
  "properties": {
    "iso:country":"CA",
    "sg:address":"115 Rue Chopin",
    "sg:city":"Charlemagne",
    "sg:classifiers":[
        {
            "category":"Travel",
            "subcategory":"Hotels & Motels",
            "type":"Entertainment"
        }
    ],
    "sg:phone":"+1 450 582 5933",
    "sg:postcode":"J5Z 4P8",
    "sg:province":"QC",
    "wof:name":"Hotel Charlemagne",
    "wof:placetype":"venue"
},
  "geometry": {"coordinates":[-73.48941,45.719326],"type":"Point"}
}