{
  "type": "Feature",
  "properties": {
    "iso:country":"CA",
    "sg:address":"250 Princess St",
    "sg:city":"Brussels",
    "sg:classifiers":[
        {
            "category":"Organizations",
            "subcategory":"Religious Organization",
            "type":"Services"
        }
    ],
    "sg:phone":"+1 519 887 6388",
    "sg:postcode":"N0G 1H0",
    "sg:province":"ON",
    "sg:tags":[
        "church"
    ],
    "wof:name":"Brussels Mennonite Fellowship",
    "wof:placetype":"venue"
},
  "geometry": {"coordinates":[-81.2459869385,43.7471466064],"type":"Point"}
}