{
  "type": "Feature",
  "properties": {
    "iso:country":"CA",
    "sg:city":"Chisasibi",
    "sg:classifiers":[
        {
            "category":"Shopping",
            "subcategory":"Department Store",
            "type":"Retail Goods"
        }
    ],
    "sg:phone":"+1 819 855 2710",
    "sg:postcode":"J0M 1E0",
    "sg:province":"QC",
    "wof:name":"Magasins Du Nord-Northern Stre",
    "wof:placetype":"venue"
},
  "geometry": {"coordinates":[-78.3332061768,53.6605644226],"type":"Point"}
}