{
  "type": "Feature",
  "properties": {
    "addr:full":"209 1st Ave Borden SK S0K 0N0",
    "addr:housenumber":"209",
    "addr:postcode":"s0k 0n0",
    "addr:street":"1St Ave",
    "iso:country":"CA",
    "sg:address":"209 1st Ave",
    "sg:city":"Borden",
    "sg:classifiers":[
        {
            "category":"Food & Beverages",
            "subcategory":"Groceries & Convenience Stores",
            "type":"Retail Goods"
        }
    ],
    "sg:phone":"+1 306 997 2030",
    "sg:postcode":"S0K 0N0",
    "sg:province":"SK",
    "sg:tags":[
        "grocer"
    ],
    "wof:name":"Foster's Store",
    "wof:placetype":"venue"
},
  "geometry": {"coordinates":[-107.238723755,52.4032249451],"type":"Point"}
}