{
  "type": "Feature",
  "properties": {
    "addr:full":"1117 Lakeside Dr Nelson BC V1L 5Z3",
    "addr:housenumber":"1117",
    "addr:postcode":"bc v1l 5z3",
    "addr:street":"Lakeside Dr",
    "iso:country":"CA",
    "sg:address":"1117 Lakeside Dr",
    "sg:city":"Nelson",
    "sg:classifiers":[
        {
            "category":"Shopping",
            "type":"Retail Goods"
        }
    ],
    "sg:phone":"+1 250 354 1611",
    "sg:postcode":"V1L 5Z3",
    "sg:province":"BC",
    "sg:tags":[
        "art",
        "gallery",
        "dealer"
    ],
    "wof:name":"Glass House Art Gallery",
    "wof:placetype":"venue"
},
  "geometry": {"coordinates":[-117.292404,49.498142],"type":"Point"}
}