{
  "type": "Feature",
  "properties": {
    "iso:country":"CA",
    "sg:address":"6070 Av DE Darlington",
    "sg:city":"Montreal",
    "sg:classifiers":[
        {
            "category":"Food & Beverages",
            "subcategory":"Bakery",
            "type":"Retail Goods"
        }
    ],
    "sg:phone":"+1 514 738 1064",
    "sg:postcode":"H3S 2H8",
    "sg:province":"QC",
    "sg:tags":[
        "baker"
    ],
    "wof:name":"Faculte DE LA Bouffe Inc",
    "wof:placetype":"venue"
},
  "geometry": {"coordinates":[-73.624283,45.507122],"type":"Point"}
}