{
  "type": "Feature",
  "properties": {
    "iso:country":"CA",
    "sg:city":"Brampton",
    "sg:classifiers":[
        {
            "category":"Shopping",
            "subcategory":"Clothing, Apparel, & Fashions",
            "type":"Retail Goods"
        }
    ],
    "sg:phone":"+1 905 458 4547",
    "sg:postcode":"L6T 3R5",
    "sg:province":"ON",
    "wof:name":"Cleo",
    "wof:placetype":"venue"
},
  "geometry": {"coordinates":[-79.7233657837,43.7172966003],"type":"Point"}
}