{
  "type": "Feature",
  "properties": {
    "addr:full":"72 Av DE LA Graviere Coaticook QC J1A 3E6",
    "addr:postcode":"j1a 3e6",
    "addr:street":"72 Av De La Graviere",
    "iso:country":"CA",
    "sg:address":"72 Av DE LA Graviere",
    "sg:city":"Coaticook",
    "sg:classifiers":[
        {
            "category":"Real Estate",
            "subcategory":"Real Estate Agent",
            "type":"Services"
        }
    ],
    "sg:phone":"+1 819 849 9303",
    "sg:postcode":"J1A 3E6",
    "sg:province":"QC",
    "sg:tags":[
        "agency",
        "rental"
    ],
    "wof:name":"Location Coaticook Inc",
    "wof:placetype":"venue"
},
  "geometry": {"coordinates":[-71.81377410890001,45.1287879944],"type":"Point"}
}