{
  "type": "Feature",
  "properties": {
    "iso:country":"CA",
    "sg:address":"12 Sturgeon Bay Rd",
    "sg:city":"Coldwater",
    "sg:classifiers":[
        {
            "category":"Health Services",
            "subcategory":"Doctor",
            "type":"Services"
        }
    ],
    "sg:phone":"+1 705 835 3711",
    "sg:postcode":"L0K 1E0",
    "sg:province":"ON",
    "sg:tags":[
        "dentist"
    ],
    "wof:name":"Coldwater Dental Office",
    "wof:placetype":"venue"
},
  "geometry": {"coordinates":[-79.6468048096,44.7092590332],"type":"Point"}
}