{
  "type": "Feature",
  "properties": {
    "addr:full":"430 Av Lariviere Rouyn-Noranda QC J9X 4J1",
    "addr:housenumber":"430",
    "addr:postcode":"j9x 4j1",
    "addr:street":"Av Lariviere",
    "iso:country":"CA",
    "sg:address":"430 Av Lariviere",
    "sg:city":"Rouyn-Noranda",
    "sg:classifiers":[
        {
            "category":"Bars & Pubs",
            "type":"Food & Drink"
        }
    ],
    "sg:phone":"+1 819 797 1991",
    "sg:postcode":"J9X 4J1",
    "sg:province":"QC",
    "sg:tags":[
        "lounge",
        "cocktail"
    ],
    "wof:name":"Bar Restaurant LA Rencontre",
    "wof:placetype":"venue"
},
  "geometry": {"coordinates":[-79.01475499999999,48.231026],"type":"Point"}
}