{
  "type": "Feature",
  "properties": {
    "addr:full":"378 Circlebrooke Dr Yorkton SK S3N 2Y8",
    "addr:housenumber":"378",
    "addr:postcode":"s3n 2y8",
    "addr:street":"Circlebrooke Dr",
    "iso:country":"CA",
    "sg:address":"378 Circlebrooke Dr",
    "sg:city":"Yorkton",
    "sg:classifiers":[
        {
            "category":"Retail",
            "subcategory":"Auto Repair",
            "type":"Services"
        }
    ],
    "sg:phone":"+1 306 621 1577",
    "sg:postcode":"S3N 2Y8",
    "sg:province":"SK",
    "sg:tags":[
        "glass",
        "coating",
        "tinting"
    ],
    "wof:name":"Nutone Glass Coating",
    "wof:placetype":"venue"
},
  "geometry": {"coordinates":[-102.495621,51.197765],"type":"Point"}
}