{
  "type": "Feature",
  "properties": {
    "iso:country":"CA",
    "sg:address":"1540 Albert St",
    "sg:city":"Regina",
    "sg:classifiers":[
        {
            "category":"Shopping",
            "subcategory":"Computers & Home Electronics",
            "type":"Retail Goods"
        }
    ],
    "sg:phone":"+1 306 569 1434",
    "sg:postcode":"S4P 2S4",
    "sg:province":"SK",
    "sg:tags":[
        "equipment",
        "dealer"
    ],
    "wof:name":"Complete Medical Billing Systs",
    "wof:placetype":"venue"
},
  "geometry": {"coordinates":[-104.618438721,50.4543914795],"type":"Point"}
}