{
  "type": "Feature",
  "properties": {
    "iso:country":"CA",
    "sg:city":"Montreal",
    "sg:classifiers":[
        {
            "category":"Health Services",
            "subcategory":"Podiatrist",
            "type":"Services"
        }
    ],
    "sg:phone":"+1 514 766 2024",
    "sg:postcode":"H4E 3W4",
    "sg:province":"QC",
    "sg:tags":[
        "attorney"
    ],
    "wof:name":"Clinique Podiatric",
    "wof:placetype":"venue"
},
  "geometry": {"coordinates":[-73.5879440308,45.4613265991],"type":"Point"}
}