{
  "type": "Feature",
  "properties": {
    "addr:full":"77 West Beaver Creek Rd Richmond Hill ON L4B 3A7",
    "addr:housenumber":"77",
    "addr:postcode":"l4b 3a7",
    "addr:street":"West Beaver Creek Rd",
    "iso:country":"CA",
    "sg:address":"77 West Beaver Creek Rd",
    "sg:city":"Richmond Hill",
    "sg:classifiers":[
        {
            "category":"Manufacturing",
            "subcategory":"Printing",
            "type":"Manufacturing & Wholesale Goods"
        }
    ],
    "sg:phone":"+1 905 886 6339",
    "sg:postcode":"L4B 3A7",
    "sg:province":"ON",
    "sg:tags":[
        "printer"
    ],
    "wof:name":"Canpak Trade Print & Svc Inc",
    "wof:placetype":"venue"
},
  "geometry": {"coordinates":[-79.393265,43.85434],"type":"Point"}
}