{
  "type": "Feature",
  "properties": {
    "addr:full":"6830 216 St Langley BC V2Y 2P7",
    "addr:housenumber":"6830",
    "addr:postcode":"v2y 2p7",
    "addr:street":"216 St",
    "iso:country":"CA",
    "sg:address":"6830 216 St",
    "sg:city":"Langley",
    "sg:classifiers":[
        {
            "category":"Autos & Motor Vehicles",
            "subcategory":"Fuel & Gas Station",
            "type":"Retail Goods"
        }
    ],
    "sg:phone":"+1 604 530 3622",
    "sg:postcode":"V2Y 2P7",
    "sg:province":"BC",
    "sg:tags":[
        "oil"
    ],
    "wof:name":"Milner Esso",
    "wof:placetype":"venue"
},
  "geometry": {"coordinates":[-122.62419128400001,49.1260871887],"type":"Point"}
}