{
  "type": "Feature",
  "properties": {
    "iso:country":"CA",
    "sg:city":"Barrie",
    "sg:classifiers":[
        {
            "category":"Wholesale",
            "subcategory":"Construction Materials",
            "type":"Manufacturing & Wholesale Goods"
        }
    ],
    "sg:phone":"+1 705 739 9877",
    "sg:postcode":"L4N 9A8",
    "sg:province":"ON",
    "sg:tags":[
        "windows",
        "fence"
    ],
    "wof:name":"Superior Seal Inc",
    "wof:placetype":"venue"
},
  "geometry": {"coordinates":[-79.681091,44.330406],"type":"Point"}
}