{
  "type": "Feature",
  "properties": {
    "addr:full":"2523 Portage Ave Winnipeg MB R3J 0P1",
    "addr:housenumber":"2523",
    "addr:postcode":"r3j 0p1",
    "addr:street":"Portage Ave",
    "iso:country":"CA",
    "sg:address":"2523 Portage Ave",
    "sg:city":"Winnipeg",
    "sg:classifiers":[
        {
            "category":"Health Services",
            "subcategory":"Chiropractor",
            "type":"Services"
        }
    ],
    "sg:phone":"+1 204 885 5407",
    "sg:postcode":"R3J 0P1",
    "sg:province":"MB",
    "wof:name":"Birchwood Chiropractic Ctr",
    "wof:placetype":"venue"
},
  "geometry": {"coordinates":[-97.258949,49.875175],"type":"Point"}
}