{
  "type": "Feature",
  "properties": {
    "addr:full":"708 Rte DE L'Eglise Saint-Jean-Port-Joli QC G0R 3G0",
    "addr:housenumber":"708",
    "addr:postcode":"g0r 3g0",
    "addr:street":"Rte De L'Eglise",
    "iso:country":"CA",
    "sg:address":"708 Rte DE L'Eglise",
    "sg:city":"Saint-Jean-Port-Joli",
    "sg:classifiers":[
        {
            "category":"Travel",
            "subcategory":"Hotels & Motels",
            "type":"Entertainment"
        }
    ],
    "sg:phone":"+1 418 598 3351",
    "sg:postcode":"G0R 3G0",
    "sg:province":"QC",
    "wof:name":"Motel LA Seigneurie",
    "wof:placetype":"venue"
},
  "geometry": {"coordinates":[-70.266769,47.212101],"type":"Point"}
}