{
  "type": "Feature",
  "properties": {
    "addr:full":"687 Malenfant Blvd Dieppe NB E1A 5T8",
    "addr:housenumber":"687",
    "addr:postcode":"e1a 5t8",
    "addr:street":"Malenfant Blvd",
    "iso:country":"CA",
    "sg:address":"687 Malenfant Blvd",
    "sg:city":"Dieppe",
    "sg:classifiers":[
        {
            "category":"Building & Trades",
            "subcategory":"Equipment Rental",
            "type":"Services"
        }
    ],
    "sg:phone":"+1 506 859 6199",
    "sg:postcode":"E1A 5T8",
    "sg:province":"NB",
    "sg:tags":[
        "crane"
    ],
    "wof:name":"Brunswick Crane Rentals",
    "wof:placetype":"venue"
},
  "geometry": {"coordinates":[-64.7238311768,46.1027374268],"type":"Point"}
}