{
  "type": "Feature",
  "properties": {
    "iso:country":"CA",
    "sg:address":"1425 Regional Rd 21 RR 1",
    "sg:city":"Delhi",
    "sg:classifiers":[
        {
            "category":"Wholesale",
            "subcategory":"Electrical",
            "type":"Manufacturing & Wholesale Goods"
        }
    ],
    "sg:phone":"+1 519 875 2571",
    "sg:postcode":"N4B 2W4",
    "sg:province":"ON",
    "sg:tags":[
        "plumbing",
        "contractor"
    ],
    "wof:name":"Darlington Wiring & Plumbing",
    "wof:placetype":"venue"
},
  "geometry": {"coordinates":[-80.49281311039999,42.8518447876],"type":"Point"}
}