{
  "type": "Feature",
  "properties": {
    "iso:country":"CA",
    "sg:city":"Hamilton",
    "sg:classifiers":[
        {
            "category":"Personal",
            "type":"Services"
        }
    ],
    "sg:phone":"+1 905 549 8780",
    "sg:postcode":"L8H 5W9",
    "sg:province":"ON",
    "sg:tags":[
        "control",
        "weight",
        "program",
        "fitness",
        "exercise",
        "physical"
    ],
    "wof:name":"Lillian's Passive Reducing",
    "wof:placetype":"venue"
},
  "geometry": {"coordinates":[-79.7905578613,43.2394638062],"type":"Point"}
}