{
  "type": "Feature",
  "properties": {
    "addr:full":"Port Coquitlam BC V3C 1T7",
    "addr:postcode":"v3c 1t7",
    "iso:country":"CA",
    "sg:city":"Port Coquitlam",
    "sg:classifiers":[
        {
            "category":"Restaurant",
            "type":"Food & Drink"
        }
    ],
    "sg:phone":"+1 604 941 0319",
    "sg:postcode":"V3C 1T7",
    "sg:province":"BC",
    "wof:name":"Boxcar Leis Lunch Express",
    "wof:placetype":"venue"
},
  "geometry": {"coordinates":[-122.788628,49.265228],"type":"Point"}
}