{
  "type": "Feature",
  "properties": {
    "addr:full":"3865 Seminole St Windsor ON N8Y 1Y9",
    "addr:housenumber":"3865",
    "addr:postcode":"n8y 1y9",
    "addr:street":"Seminole St",
    "iso:country":"CA",
    "sg:address":"3865 Seminole St",
    "sg:city":"Windsor",
    "sg:classifiers":[
        {
            "category":"Personal",
            "subcategory":"Beauty Salon",
            "type":"Services"
        }
    ],
    "sg:phone":"+1 519 974 3154",
    "sg:postcode":"N8Y 1Y9",
    "sg:province":"ON",
    "wof:name":"Backstage Hair Designs",
    "wof:placetype":"venue"
},
  "geometry": {"coordinates":[-82.9839935303,42.315410614],"type":"Point"}
}