{
  "type": "Feature",
  "properties": {
    "addr:full":"1201 Marine Dr Port Alice BC V0N 2N0",
    "addr:housenumber":"1201",
    "addr:postcode":"v0n 2n0",
    "addr:street":"Marine Dr Port",
    "iso:country":"CA",
    "sg:address":"1201 Marine Dr",
    "sg:city":"Port Alice",
    "sg:classifiers":[
        {
            "category":"Travel",
            "subcategory":"Campground",
            "type":"Entertainment"
        }
    ],
    "sg:phone":"+1 250 284 3422",
    "sg:postcode":"V0N 2N0",
    "sg:province":"BC",
    "wof:name":"Port Alice Motel Camping Ltd",
    "wof:placetype":"venue"
},
  "geometry": {"coordinates":[-127.48487854,50.424446106],"type":"Point"}
}