{
  "type": "Feature",
  "properties": {
    "iso:country":"CA",
    "sg:address":"8201 Weston Rd",
    "sg:city":"Woodbridge",
    "sg:classifiers":[
        {
            "category":"Home & Garden",
            "subcategory":"Home Furnishings",
            "type":"Retail Goods"
        }
    ],
    "sg:phone":"+1 905 856 9285",
    "sg:postcode":"L4L 1A6",
    "sg:province":"ON",
    "sg:tags":[
        "curtain",
        "made",
        "drapery"
    ],
    "wof:name":"Drapery Interiors Etc",
    "wof:placetype":"venue"
},
  "geometry": {"coordinates":[-79.5500030518,43.8008499146],"type":"Point"}
}