{
  "type": "Feature",
  "properties": {
    "iso:country":"CA",
    "sg:city":"Brampton",
    "sg:classifiers":[
        {
            "category":"Manufacturing",
            "subcategory":"Tools & Machinery",
            "type":"Manufacturing & Wholesale Goods"
        }
    ],
    "sg:phone":"+1 905 791 0652",
    "sg:postcode":"L6S 5P6",
    "sg:province":"ON",
    "sg:tags":[
        "equipment",
        "material",
        "handling"
    ],
    "wof:name":"Aerdon Equipment Ltd",
    "wof:placetype":"venue"
},
  "geometry": {"coordinates":[-79.6982040405,43.7595367432],"type":"Point"}
}