{
  "type": "Feature",
  "properties": {
    "iso:country":"CA",
    "sg:city":"Barrie",
    "sg:classifiers":[
        {
            "category":"Shopping",
            "type":"Retail Goods"
        }
    ],
    "sg:phone":"+1 705 726 3131",
    "sg:postcode":"L4N 5W4",
    "sg:province":"ON",
    "sg:tags":[
        "art",
        "gallery",
        "dealer"
    ],
    "wof:name":"Crescent Hill Gallery",
    "wof:placetype":"venue"
},
  "geometry": {"coordinates":[-79.675095,44.370953],"type":"Point"}
}