{
  "type": "Feature",
  "properties": {
    "iso:country":"CA",
    "sg:city":"Toronto",
    "sg:classifiers":[
        {
            "category":"Professional",
            "subcategory":"Business Services",
            "type":"Services"
        }
    ],
    "sg:phone":"+1 416 923 2601",
    "sg:postcode":"M5S 1N5",
    "sg:province":"ON",
    "sg:tags":[
        "attorney"
    ],
    "wof:name":"Zammit Semple Llp",
    "wof:placetype":"venue"
},
  "geometry": {"coordinates":[-79.3919906616,43.6692962646],"type":"Point"}
}