{
  "type": "Feature",
  "properties": {
    "addr:full":"1782 Stellys Cross Rd Saanichton BC V8M 1S8",
    "addr:housenumber":"1782",
    "addr:postcode":"v8m 1s8",
    "addr:street":"Stellys Cross Rd",
    "iso:country":"CA",
    "sg:address":"1782 Stellys Cross Rd",
    "sg:city":"Saanichton",
    "sg:classifiers":[
        {
            "category":"Retail",
            "subcategory":"Veterinary Services",
            "type":"Services"
        }
    ],
    "sg:phone":"+1 250 652 4312",
    "sg:postcode":"V8M 1S8",
    "sg:province":"BC",
    "sg:tags":[
        "veterinarian"
    ],
    "wof:name":"Central Saanich Animal Hosp",
    "wof:placetype":"venue"
},
  "geometry": {"coordinates":[-123.416893,48.5952],"type":"Point"}
}