{
  "type": "Feature",
  "properties": {
    "addr:full":"12631 Vulcan Way Richmond BC V6V 1J7",
    "addr:housenumber":"12631",
    "addr:postcode":"v6v 1j7",
    "addr:street":"Vulcan Way",
    "iso:country":"CA",
    "sg:address":"12631 Vulcan Way",
    "sg:city":"Richmond",
    "sg:classifiers":[
        {
            "category":"Professional",
            "subcategory":"Engineering",
            "type":"Services"
        }
    ],
    "sg:phone":"+1 604 273 1915",
    "sg:postcode":"V6V 1J7",
    "sg:province":"BC",
    "sg:tags":[
        "engineer"
    ],
    "wof:name":"Stolberg Engineering Ltd",
    "wof:placetype":"venue"
},
  "geometry": {"coordinates":[-123.08416748,49.1952476501],"type":"Point"}
}