{
  "type": "Feature",
  "properties": {
    "addr:full":"18 Regalbuto Ave Petawawa ON K8H 1L3",
    "addr:housenumber":"18",
    "addr:postcode":"k8h 1l3",
    "addr:street":"Regalbuto Ave",
    "iso:country":"CA",
    "sg:address":"18 Regalbuto Ave",
    "sg:city":"Petawawa",
    "sg:classifiers":[
        {
            "category":"Education",
            "subcategory":"School",
            "type":"Public Place"
        }
    ],
    "sg:phone":"+1 613 687 4167",
    "sg:postcode":"K8H 1L3",
    "sg:province":"ON",
    "wof:name":"St Francis of Assisi School",
    "wof:placetype":"venue"
},
  "geometry": {"coordinates":[-77.270325,45.906269],"type":"Point"}
}