{
  "type": "Feature",
  "properties": {
    "addr:full":"339 Rte 111 LA Corne QC J0Y 1R0",
    "addr:housenumber":"339",
    "addr:postcode":"j0y 1r0",
    "addr:street":"Rte 111",
    "iso:country":"CA",
    "sg:address":"339 Rte 111",
    "sg:city":"LA Corne",
    "sg:classifiers":[
        {
            "category":"Organizations",
            "subcategory":"Professional Association",
            "type":"Services"
        }
    ],
    "sg:phone":"+1 819 799 2181",
    "sg:postcode":"J0Y 1R0",
    "sg:province":"QC",
    "wof:name":"Dispensaire DE LA Garde DE LA",
    "wof:placetype":"venue"
},
  "geometry": {"coordinates":[-77.99597930909999,48.3529853821],"type":"Point"}
}