{
  "type": "Feature",
  "properties": {
    "addr:full":"3569 3rd Ave Port Alberni BC V9Y 4E6",
    "addr:housenumber":"3569",
    "addr:postcode":"v9y 4e6",
    "addr:street":"3Rd Ave",
    "iso:country":"CA",
    "sg:address":"3569 3rd Ave",
    "sg:city":"Port Alberni",
    "sg:classifiers":[
        {
            "category":"Shopping",
            "subcategory":"Computers & Home Electronics",
            "type":"Retail Goods"
        }
    ],
    "sg:phone":"+1 250 724 1257",
    "sg:postcode":"V9Y 4E6",
    "sg:province":"BC",
    "sg:tags":[
        "equipment",
        "satellite",
        "system"
    ],
    "wof:name":"Barlow's Home Entertainment",
    "wof:placetype":"venue"
},
  "geometry": {"coordinates":[-124.807250977,49.2412948608],"type":"Point"}
}