{
  "type": "Feature",
  "properties": {
    "iso:country":"CA",
    "sg:address":"988 Ontario St",
    "sg:city":"Stratford",
    "sg:classifiers":[
        {
            "category":"Restaurant",
            "type":"Food & Drink"
        }
    ],
    "sg:phone":"+1 519 271 2250",
    "sg:postcode":"N5A 6Z3",
    "sg:province":"ON",
    "wof:name":"Crabby Joe's Tap & Grill",
    "wof:placetype":"venue"
},
  "geometry": {"coordinates":[-80.9493637085,43.3709526062],"type":"Point"}
}