{
  "type": "Feature",
  "properties": {
    "addr:full":"2006 Highway 7 # 3 Concord ON L4K 1W6",
    "addr:housenumber":"2006",
    "addr:postcode":"l4k 1w6",
    "addr:street":"Highway 7 # 3",
    "iso:country":"CA",
    "sg:address":"2006 Highway 7 # 3",
    "sg:city":"Concord",
    "sg:classifiers":[
        {
            "category":"Retail",
            "subcategory":"Auto Repair",
            "type":"Services"
        }
    ],
    "sg:phone":"+1 905 761 1616",
    "sg:postcode":"L4K 1W6",
    "sg:province":"ON",
    "sg:tags":[
        "transmission"
    ],
    "wof:name":"Transmission Depot",
    "wof:placetype":"venue"
},
  "geometry": {"coordinates":[-79.50717926030001,43.7982368469],"type":"Point"}
}