{
  "type": "Feature",
  "properties": {
    "iso:country":"CA",
    "sg:address":"1556 Bath Rd",
    "sg:city":"Kingston",
    "sg:classifiers":[
        {
            "category":"Autos & Motor Vehicles",
            "subcategory":"Automobile Sales",
            "type":"Retail Goods"
        }
    ],
    "sg:phone":"+1 613 634 3262",
    "sg:postcode":"K7M 4X6",
    "sg:province":"ON",
    "sg:tags":[
        "car",
        "dealer"
    ],
    "wof:name":"Autohouse Kingston",
    "wof:placetype":"venue"
},
  "geometry": {"coordinates":[-76.539955,44.238239],"type":"Point"}
}