{
  "type": "Feature",
  "properties": {
    "addr:full":"1280 Terwillegar Ave # 4 Oshawa ON L1J 7A5",
    "addr:housenumber":"1280",
    "addr:postcode":"l1j 7a5",
    "addr:street":"Terwillegar Ave # 4",
    "iso:country":"CA",
    "sg:address":"1280 Terwillegar Ave # 4",
    "sg:city":"Oshawa",
    "sg:classifiers":[
        {
            "category":"Building & Trades",
            "subcategory":"Construction",
            "type":"Services"
        }
    ],
    "sg:phone":"+1 905 438 0909",
    "sg:postcode":"L1J 7A5",
    "sg:province":"ON",
    "sg:tags":[
        "general",
        "contractor"
    ],
    "wof:name":"Sorichetti Project & Constr",
    "wof:placetype":"venue"
},
  "geometry": {"coordinates":[-78.877167,43.856171],"type":"Point"}
}