{
  "type": "Feature",
  "properties": {
    "addr:full":"131 Parks Dr #A Belleville ON K8N 4Z5",
    "addr:housenumber":"131",
    "addr:postcode":"k8n 4z5",
    "addr:street":"Parks Dr # A",
    "iso:country":"CA",
    "sg:address":"131 Parks Dr #A",
    "sg:city":"Belleville",
    "sg:classifiers":[
        {
            "category":"Retail",
            "subcategory":"Auto Repair",
            "type":"Services"
        }
    ],
    "sg:phone":"+1 613 969 7730",
    "sg:postcode":"K8N 4Z5",
    "sg:province":"ON",
    "sg:tags":[
        "truck"
    ],
    "wof:name":"Penske Truck Leasing",
    "wof:placetype":"venue"
},
  "geometry": {"coordinates":[-77.3954925537,44.2001647949],"type":"Point"}
}