{
  "type": "Feature",
  "properties": {
    "addr:full":"11621 149 St NW Edmonton AB T5M 1X1",
    "addr:housenumber":"11621",
    "addr:postcode":"t5m 1x1",
    "addr:street":"149 St Nw",
    "iso:country":"CA",
    "sg:address":"11621 149 St NW",
    "sg:city":"Edmonton",
    "sg:classifiers":[
        {
            "category":"Wholesale",
            "subcategory":"Electrical",
            "type":"Manufacturing & Wholesale Goods"
        }
    ],
    "sg:phone":"+1 780 454 1001",
    "sg:postcode":"T5M 1X1",
    "sg:province":"AB",
    "sg:tags":[
        "automobile",
        "parts",
        "supply"
    ],
    "wof:name":"East Penn/Power Battery Sales",
    "wof:placetype":"venue"
},
  "geometry": {"coordinates":[-113.577782,53.568336],"type":"Point"}
}