{
  "type": "Feature",
  "properties": {
    "iso:country":"CA",
    "sg:address":"172 Main St",
    "sg:city":"Selkirk",
    "sg:classifiers":[
        {
            "category":"Restaurant",
            "type":"Food & Drink"
        }
    ],
    "sg:phone":"+1 204 785 1011",
    "sg:postcode":"R1A 1R3",
    "sg:province":"MB",
    "wof:name":"Mc Donald's",
    "wof:placetype":"venue"
},
  "geometry": {"coordinates":[-96.8843154907,50.133895874],"type":"Point"}
}