{
  "type": "Feature",
  "properties": {
    "addr:full":"335 Rue Principale Saint-Bernard-DE-Michaudville QC J0H 1C0",
    "addr:housenumber":"335",
    "addr:postcode":"j0h 1c0",
    "addr:street":"Rue Principale",
    "iso:country":"CA",
    "sg:address":"335 Rue Principale",
    "sg:city":"Saint-Bernard-DE-Michaudville",
    "sg:classifiers":[
        {
            "category":"Retail",
            "subcategory":"Repair Shop",
            "type":"Services"
        }
    ],
    "sg:phone":"+1 450 792 3706",
    "sg:postcode":"J0H 1C0",
    "sg:province":"QC",
    "sg:tags":[
        "welding"
    ],
    "wof:name":"Soudures J-L Claing Inc",
    "wof:placetype":"venue"
},
  "geometry": {"coordinates":[-73.057571,45.823811],"type":"Point"}
}