{
  "type": "Feature",
  "properties": {
    "iso:country":"CA",
    "sg:address":"10432 100 Ave",
    "sg:city":"Westlock",
    "sg:classifiers":[
        {
            "category":"Shopping",
            "type":"Retail Goods"
        }
    ],
    "sg:phone":"+1 780 349 3496",
    "sg:postcode":"T7P 1T6",
    "sg:province":"AB",
    "sg:tags":[
        "trophy",
        "medal",
        "award"
    ],
    "wof:name":"B-J Trophies",
    "wof:placetype":"venue"
},
  "geometry": {"coordinates":[-113.86000824,54.1535453796],"type":"Point"}
}