{
  "type": "Feature",
  "properties": {
    "addr:full":"107 Main St Watrous SK S0K 4T0",
    "addr:housenumber":"107",
    "addr:postcode":"s0k 4t0",
    "addr:street":"Main St",
    "iso:country":"CA",
    "sg:address":"107 Main St",
    "sg:city":"Watrous",
    "sg:classifiers":[
        {
            "category":"Real Estate",
            "subcategory":"Real Estate Agent",
            "type":"Services"
        }
    ],
    "sg:phone":"+1 306 946 3655",
    "sg:postcode":"S0K 4T0",
    "sg:province":"SK",
    "wof:name":"Watrous Realty",
    "wof:placetype":"venue"
},
  "geometry": {"coordinates":[-105.469009,51.672207],"type":"Point"}
}