{
  "type": "Feature",
  "properties": {
    "addr:full":"410 South Service Rd W Oakville ON L6K 2H4",
    "addr:housenumber":"410",
    "addr:postcode":"l6k 2h4",
    "addr:street":"South Service Rd W",
    "iso:country":"CA",
    "sg:address":"410 South Service Rd W",
    "sg:city":"Oakville",
    "sg:classifiers":[
        {
            "category":"Autos & Motor Vehicles",
            "subcategory":"Automobile Sales",
            "type":"Retail Goods"
        }
    ],
    "sg:phone":"+1 905 845 1681",
    "sg:postcode":"L6K 2H4",
    "sg:province":"ON",
    "sg:tags":[
        "car",
        "dealer"
    ],
    "wof:name":"Kerr Cadillac Pontiac Buick",
    "wof:placetype":"venue"
},
  "geometry": {"coordinates":[-79.7054977417,43.4411125183],"type":"Point"}
}