{
  "type": "Feature",
  "properties": {
    "iso:country":"CA",
    "sg:address":"RR 1 Box 388",
    "sg:city":"Scotland",
    "sg:classifiers":[
        {
            "category":"Building & Trades",
            "subcategory":"Construction",
            "type":"Services"
        }
    ],
    "sg:phone":"+1 519 443 4393",
    "sg:postcode":"N0E 1R0",
    "sg:province":"ON",
    "sg:tags":[
        "painter"
    ],
    "wof:name":"Senko Restoration",
    "wof:placetype":"venue"
},
  "geometry": {"coordinates":[-80.3754043579,43.0257759094],"type":"Point"}
}