{
  "type": "Feature",
  "properties": {
    "addr:full":"36 Hastings Dr Dartmouth NS B2Y 2C5",
    "addr:housenumber":"36",
    "addr:postcode":"b2y 2c5",
    "addr:street":"Hastings Dr",
    "iso:country":"CA",
    "sg:address":"36 Hastings Dr",
    "sg:city":"Dartmouth",
    "sg:classifiers":[
        {
            "category":"Education",
            "subcategory":"School",
            "type":"Public Place"
        }
    ],
    "sg:phone":"+1 902 464 2081",
    "sg:postcode":"B2Y 2C5",
    "sg:province":"NS",
    "wof:name":"Southdale/North Woodside Schl",
    "wof:placetype":"venue"
},
  "geometry": {"coordinates":[-63.547672,44.666271],"type":"Point"}
}