{
  "type": "Feature",
  "properties": {
    "addr:full":"Chatsworth ON N0H 1G0",
    "addr:postcode":"n0h 1g0",
    "iso:country":"CA",
    "sg:city":"Chatsworth",
    "sg:classifiers":[
        {
            "category":"Manufacturing",
            "subcategory":"Food",
            "type":"Manufacturing & Wholesale Goods"
        }
    ],
    "sg:phone":"+1 519 794 3848",
    "sg:postcode":"N0H 1G0",
    "sg:province":"ON",
    "sg:tags":[
        "product",
        "seafood",
        "fish",
        "prepared"
    ],
    "wof:name":"Hatten Fish Farm",
    "wof:placetype":"venue"
},
  "geometry": {"coordinates":[-80.8974075317,44.4536552429],"type":"Point"}
}