{
  "type": "Feature",
  "properties": {
    "addr:full":"2480 Rue Marmier Longueuil QC J4L 2N8",
    "addr:housenumber":"2480",
    "addr:postcode":"j4l 2n8",
    "addr:street":"Rue Marmier",
    "iso:country":"CA",
    "sg:address":"2480 Rue Marmier",
    "sg:city":"Longueuil",
    "sg:classifiers":[
        {
            "category":"Social Services",
            "subcategory":"Child Care",
            "type":"Services"
        }
    ],
    "sg:phone":"+1 450 677 3117",
    "sg:postcode":"J4L 2N8",
    "sg:province":"QC",
    "wof:name":"Garderie Ecole Du Village",
    "wof:placetype":"venue"
},
  "geometry": {"coordinates":[-73.47575378419999,45.5146827698],"type":"Point"}
}