{
  "type": "Feature",
  "properties": {
    "iso:country":"CA",
    "sg:address":"259 Boul Saint-Joseph # 310",
    "sg:city":"Hull",
    "sg:classifiers":[
        {
            "category":"Organizations",
            "subcategory":"Labor Organization",
            "type":"Services"
        }
    ],
    "sg:phone":"+1 819 777 5441",
    "sg:postcode":"J8Y 6T1",
    "sg:province":"QC",
    "wof:name":"Federation Des Travailleurs",
    "wof:placetype":"venue"
},
  "geometry": {"coordinates":[-75.73317,45.437069],"type":"Point"}
}