{
  "type": "Feature",
  "properties": {
    "addr:full":"Saint-Jean-Chrysostome QC G6Z 2E2",
    "addr:postcode":"g6z 2e2",
    "iso:country":"CA",
    "sg:city":"Saint-Jean-Chrysostome",
    "sg:classifiers":[
        {
            "category":"Health Services",
            "subcategory":"Doctor",
            "type":"Services"
        }
    ],
    "sg:phone":"+1 418 839 4433",
    "sg:postcode":"G6Z 2E2",
    "sg:province":"QC",
    "sg:tags":[
        "clinic"
    ],
    "wof:name":"Clinique Medicale Taniata",
    "wof:placetype":"venue"
},
  "geometry": {"coordinates":[-71.203217,46.725739],"type":"Point"}
}