{
  "type": "Feature",
  "properties": {
    "addr:full":"4141 River Rd W Delta BC V4K 1R9",
    "addr:housenumber":"4141",
    "addr:postcode":"v4k 1r9",
    "addr:street":"River Rd W",
    "iso:country":"CA",
    "sg:address":"4141 River Rd W",
    "sg:city":"Delta",
    "sg:classifiers":[
        {
            "category":"Recreation",
            "type":"Entertainment"
        }
    ],
    "sg:phone":"+1 604 946 0020",
    "sg:postcode":"V4K 1R9",
    "sg:province":"BC",
    "sg:tags":[
        "charter",
        "boat"
    ],
    "wof:name":"Silver Challenger Marine Tours",
    "wof:placetype":"venue"
},
  "geometry": {"coordinates":[-123.109642029,49.0847434998],"type":"Point"}
}