{
  "type": "Feature",
  "properties": {
    "addr:full":"Head of Chezzetcook NS B0J 1N0",
    "addr:postcode":"b0j 1n0",
    "iso:country":"CA",
    "sg:city":"Head of Chezzetcook",
    "sg:classifiers":[
        {
            "category":"Manufacturing",
            "subcategory":"Tools & Machinery",
            "type":"Manufacturing & Wholesale Goods"
        }
    ],
    "sg:phone":"+1 902 827 4500",
    "sg:postcode":"B0J 1N0",
    "sg:province":"NS",
    "sg:tags":[
        "alternator",
        "starter"
    ],
    "wof:name":"Down East Starter & Alternator",
    "wof:placetype":"venue"
},
  "geometry": {"coordinates":[-63.237865448,44.7506942749],"type":"Point"}
}