{
  "type": "Feature",
  "properties": {
    "addr:full":"10102 180 St NW Edmonton AB T5S 1N4",
    "addr:housenumber":"10102",
    "addr:postcode":"t5s 1n4",
    "addr:street":"180 St Nw",
    "iso:country":"CA",
    "sg:address":"10102 180 St NW",
    "sg:city":"Edmonton",
    "sg:classifiers":[
        {
            "category":"Bars & Pubs",
            "type":"Food & Drink"
        }
    ],
    "sg:phone":"+1 780 481 8739",
    "sg:postcode":"T5S 1N4",
    "sg:province":"AB",
    "sg:tags":[
        "club",
        "night"
    ],
    "wof:name":"Cowboys Country Saloon",
    "wof:placetype":"venue"
},
  "geometry": {"coordinates":[-113.63299600000001,53.541862],"type":"Point"}
}