{
  "type": "Feature",
  "properties": {
    "addr:full":"128 Park St Sussex NB E4E 1V3",
    "addr:housenumber":"128",
    "addr:postcode":"e4e 1v3",
    "addr:street":"Park St",
    "iso:country":"CA",
    "sg:address":"128 Park St",
    "sg:city":"Sussex",
    "sg:classifiers":[
        {
            "category":"Retail",
            "subcategory":"Auto Repair",
            "type":"Services"
        }
    ],
    "sg:phone":"+1 506 433 6576",
    "sg:postcode":"E4E 1V3",
    "sg:province":"NB",
    "sg:tags":[
        "body",
        "automobile",
        "painting"
    ],
    "wof:name":"Young's Body Shop",
    "wof:placetype":"venue"
},
  "geometry": {"coordinates":[-65.51522827150001,45.7206230164],"type":"Point"}
}