{
  "type": "Feature",
  "properties": {
    "addr:full":"2400 Anson Dr Mississauga ON L5S 1G2",
    "addr:housenumber":"2400",
    "addr:postcode":"l5s 1g2",
    "addr:street":"Anson Dr",
    "iso:country":"CA",
    "sg:address":"2400 Anson Dr",
    "sg:city":"Mississauga",
    "sg:classifiers":[
        {
            "category":"Manufacturing",
            "subcategory":"Tools & Machinery",
            "type":"Manufacturing & Wholesale Goods"
        }
    ],
    "sg:phone":"+1 905 678 0009",
    "sg:postcode":"L5S 1G2",
    "sg:province":"ON",
    "sg:tags":[
        "equipment",
        "hydraulic"
    ],
    "wof:name":"Canadian Hydraulics Ltd",
    "wof:placetype":"venue"
},
  "geometry": {"coordinates":[-79.65949999999999,43.69558],"type":"Point"}
}