{
  "type": "Feature",
  "properties": {
    "addr:full":"2085 Av Union Montreal QC H3A 2C3",
    "addr:housenumber":"2085",
    "addr:postcode":"h3a 2c3",
    "addr:street":"Av Union",
    "iso:country":"CA",
    "sg:address":"2085 Av Union",
    "sg:city":"Montreal",
    "sg:classifiers":[
        {
            "category":"Airline",
            "type":"Transportation"
        }
    ],
    "sg:phone":"+1 514 842 2500",
    "sg:postcode":"H3A 2C3",
    "sg:province":"QC",
    "sg:tags":[
        "company"
    ],
    "wof:name":"Austrian Airlines",
    "wof:placetype":"venue"
},
  "geometry": {"coordinates":[-73.57251739500001,45.5055084229],"type":"Point"}
}