{
  "type": "Feature",
  "properties": {
    "addr:full":"Montreal QC H2V 4L5",
    "addr:postcode":"h2v 4l5",
    "iso:country":"CA",
    "sg:city":"Montreal",
    "sg:classifiers":[
        {
            "category":"Manufacturing",
            "subcategory":"Tools & Machinery",
            "type":"Manufacturing & Wholesale Goods"
        }
    ],
    "sg:phone":"+1 514 279 1686",
    "sg:postcode":"H2V 4L5",
    "sg:province":"QC",
    "sg:tags":[
        "model",
        "maker"
    ],
    "wof:name":"Castilloux Bergeron",
    "wof:placetype":"venue"
},
  "geometry": {"coordinates":[-73.554359436,45.5123100281],"type":"Point"}
}