{
  "type": "Feature",
  "properties": {
    "addr:full":"2385 Eglinton Ave E Scarborough ON M1K 2M5",
    "addr:housenumber":"2385",
    "addr:postcode":"m1k 2m5",
    "addr:street":"Eglinton Ave E",
    "iso:country":"CA",
    "sg:address":"2385 Eglinton Ave E",
    "sg:city":"Scarborough",
    "sg:classifiers":[
        {
            "category":"Personal",
            "subcategory":"Beauty Salon",
            "type":"Services"
        }
    ],
    "sg:phone":"+1 416 267 9312",
    "sg:postcode":"M1K 2M5",
    "sg:province":"ON",
    "wof:name":"Vince & Tony's Salon",
    "wof:placetype":"venue"
},
  "geometry": {"coordinates":[-79.2691955566,43.7318000793],"type":"Point"}
}