{
  "type": "Feature",
  "properties": {
    "iso:country":"CA",
    "sg:address":"1200 Queens Bush Rd #E",
    "sg:city":"Wellesley",
    "sg:classifiers":[
        {
            "category":"Food & Beverages",
            "subcategory":"Groceries & Convenience Stores",
            "type":"Retail Goods"
        }
    ],
    "sg:phone":"+1 519 656 3400",
    "sg:postcode":"N0B 2T0",
    "sg:province":"ON",
    "sg:tags":[
        "product"
    ],
    "wof:name":"Bulk Pantry",
    "wof:placetype":"venue"
},
  "geometry": {"coordinates":[-80.7647857666,43.4774284363],"type":"Point"}
}