{
  "type": "Feature",
  "properties": {
    "addr:full":"8911 Dunn St Canal Flats BC V0B 1B0",
    "addr:housenumber":"8911",
    "addr:postcode":"v0b 1b0",
    "addr:street":"Dunn St",
    "iso:country":"CA",
    "sg:address":"8911 Dunn St",
    "sg:city":"Canal Flats",
    "sg:classifiers":[
        {
            "category":"Recreation",
            "subcategory":"Amusement Park",
            "type":"Entertainment"
        }
    ],
    "sg:phone":"+1 250 349 5260",
    "sg:postcode":"V0B 1B0",
    "sg:province":"BC",
    "wof:name":"Canal Flats Civic Ctr",
    "wof:placetype":"venue"
},
  "geometry": {"coordinates":[-115.811577,50.158497],"type":"Point"}
}