{
  "type": "Feature",
  "properties": {
    "addr:full":"2 Dundonald St Toronto ON M4Y 1K2",
    "addr:housenumber":"2",
    "addr:postcode":"m4y 1k2",
    "addr:street":"Dundonald St",
    "iso:country":"CA",
    "sg:address":"2 Dundonald St",
    "sg:city":"Toronto",
    "sg:classifiers":[
        {
            "category":"Personal",
            "subcategory":"Tattoo Parlor",
            "type":"Services"
        }
    ],
    "sg:phone":"+1 416 250 0025",
    "sg:postcode":"M4Y 1K2",
    "sg:province":"ON",
    "sg:tags":[
        "tattooing"
    ],
    "wof:name":"Body Graphics",
    "wof:placetype":"venue"
},
  "geometry": {"coordinates":[-79.38458300000001,43.666031],"type":"Point"}
}