{
  "type": "Feature",
  "properties": {
    "iso:country":"CA",
    "sg:address":"3990 Rue Saint-Joseph",
    "sg:city":"Trois-Rivieres",
    "sg:classifiers":[
        {
            "category":"Wholesale",
            "subcategory":"Metals & Minerals",
            "type":"Manufacturing & Wholesale Goods"
        }
    ],
    "sg:phone":"+1 819 693 0106",
    "sg:postcode":"G8Z 2Y3",
    "sg:province":"QC",
    "sg:tags":[
        "steel",
        "specialty"
    ],
    "wof:name":"Metaux Lamy Inc",
    "wof:placetype":"venue"
},
  "geometry": {"coordinates":[-72.5739974976,46.3390731812],"type":"Point"}
}