{
  "type": "Feature",
  "properties": {
    "addr:full":"1601 North Service Rd Swift Current SK S9H 3X6",
    "addr:housenumber":"1601",
    "addr:postcode":"s9h 3x6",
    "addr:street":"North Service Rd",
    "iso:country":"CA",
    "sg:address":"1601 North Service Rd",
    "sg:city":"Swift Current",
    "sg:classifiers":[
        {
            "category":"Restaurant",
            "type":"Food & Drink"
        }
    ],
    "sg:phone":"+1 306 778 7666",
    "sg:postcode":"S9H 3X6",
    "sg:province":"SK",
    "wof:name":"Boston Pizza",
    "wof:placetype":"venue"
},
  "geometry": {"coordinates":[-107.779984,50.304623],"type":"Point"}
}