{
  "type": "Feature",
  "properties": {
    "addr:full":"27 Rue Maguire Montreal QC H2T 1B7",
    "addr:housenumber":"27",
    "addr:postcode":"h2t 1b7",
    "addr:street":"Rue Maguire",
    "iso:country":"CA",
    "sg:address":"27 Rue Maguire",
    "sg:city":"Montreal",
    "sg:classifiers":[
        {
            "category":"Building & Trades",
            "subcategory":"Plumbing",
            "type":"Services"
        }
    ],
    "sg:phone":"+1 514 274 4348",
    "sg:postcode":"H2T 1B7",
    "sg:province":"QC",
    "sg:tags":[
        "contractor"
    ],
    "wof:name":"Bel-Air Plumbing & Heating",
    "wof:placetype":"venue"
},
  "geometry": {"coordinates":[-73.5956878662,45.5249214172],"type":"Point"}
}