{
  "type": "Feature",
  "properties": {
    "addr:full":"Toronto ON M5T 1K5",
    "addr:postcode":"m5t 1k5",
    "iso:country":"CA",
    "sg:city":"Toronto",
    "sg:classifiers":[
        {
            "category":"Organizations",
            "subcategory":"Professional Association",
            "type":"Services"
        }
    ],
    "sg:phone":"+1 416 971 8886",
    "sg:postcode":"M5T 1K5",
    "sg:province":"ON",
    "wof:name":"Toronto Mainland Chinese Comm",
    "wof:placetype":"venue"
},
  "geometry": {"coordinates":[-79.39115099999999,43.656071],"type":"Point"}
}